{
  "type": "Feature",
  "properties": {
    "iso:country":"BE",
    "sg:address":"Gouvernementsweg 31",
    "sg:city":"Bruxelles (woluwe-saint-pierre)",
    "sg:classifiers":[
        {
            "category":"Wholesale",
            "subcategory":"Scrap",
            "type":"Manufacturing & Wholesale Goods"
        }
    ],
    "sg:phone":"+32 2 771 65 99",
    "sg:postcode":"1150",
    "sg:province":"Bruxelles-Capitale",
    "sg:tags":[
        "dustbin",
        "dustbagholders"
    ],
    "wof:name":"Stima Belgium Sprl",
    "wof:placetype":"venue"
},
  "geometry": {"coordinates":[4.4671220779,50.8333740234],"type":"Point"}
}