{
  "type": "Feature",
  "properties": {
    "addr:full":"Gasstraat 17 Roeselare West-Vlaanderen 8800",
    "addr:housenumber":"17",
    "addr:postcode":"8800",
    "addr:street":"Gasstraat",
    "iso:country":"BE",
    "sg:address":"Gasstraat 17",
    "sg:city":"Roeselare",
    "sg:orig_category":"M\u00e9decins and sp\u00e9cialistes",
    "sg:phone":"+32 51 20 50 26",
    "sg:postcode":"8800",
    "sg:province":"West-Vlaanderen",
    "wof:name":"Michiel Vlaeminck",
    "wof:placetype":"venue"
},
  "geometry": {"coordinates":[3.1306180954,50.9468193054],"type":"Point"}
}