{
  "type": "Feature",
  "properties": {
    "iso:country":"BE",
    "sg:address":"Baugn\u00e9e 11-13",
    "sg:city":"Anthisnes (tavier)",
    "sg:classifiers":[
        {
            "category":"Animal Shelter",
            "type":"Public Place"
        }
    ],
    "sg:phone":"+32 4 239 25 80",
    "sg:postcode":"4163",
    "sg:province":"Li\u00e8ge",
    "sg:tags":[
        "clinic"
    ],
    "wof:name":"Cereq",
    "wof:placetype":"venue"
},
  "geometry": {"coordinates":[5.4676561356,50.50989151],"type":"Point"}
}