{
  "type": "Feature",
  "properties": {
    "iso:country":"BE",
    "sg:address":"Heidestatiestraat 85",
    "sg:city":"Kalmthout",
    "sg:orig_category":"Slagers",
    "sg:phone":"+32 3 666 83 22",
    "sg:postcode":"2920",
    "sg:province":"Antwerpen",
    "wof:name":"De Vos",
    "wof:placetype":"venue"
},
  "geometry": {"coordinates":[4.461168766,51.3645324707],"type":"Point"}
}