{
  "type": "Feature",
  "properties": {
    "iso:country":"BE",
    "sg:address":"Sportlaan 11",
    "sg:city":"Moerbeke (moerbeke-waas)",
    "sg:classifiers":[
        {
            "category":"Health Services",
            "subcategory":"Health Practitioner",
            "type":"Services"
        }
    ],
    "sg:phone":"+32 9 346 85 28",
    "sg:postcode":"9180",
    "sg:province":"Oost-Vlaanderen",
    "sg:tags":[
        "physiotherapist"
    ],
    "wof:name":"Dirinck Etienne",
    "wof:placetype":"venue"
},
  "geometry": {"coordinates":[3.945152998,51.1737594604],"type":"Point"}
}