{
  "type": "Feature",
  "properties": {
    "addr:full":"Rue Du Cerf 9 Rixensart (genval) Brabant Wallon 1332",
    "addr:housenumber":"9",
    "addr:postcode":"1332",
    "addr:street":"Rue Du Cerf",
    "iso:country":"BE",
    "sg:address":"Rue Du Cerf 9",
    "sg:city":"Rixensart (genval)",
    "sg:classifiers":[
        {
            "category":"Health Services",
            "subcategory":"Health Practitioner",
            "type":"Services"
        }
    ],
    "sg:phone":"+32 476 98 50 71",
    "sg:postcode":"1332",
    "sg:province":"Brabant Wallon",
    "sg:tags":[
        "physiotherapist"
    ],
    "wof:name":"De Coninck Delphine",
    "wof:placetype":"venue"
},
  "geometry": {"coordinates":[4.5128278732,50.7261238098],"type":"Point"}
}