{
  "type": "Feature",
  "properties": {
    "addr:full":"Baliebrugstraat 31 Oostkamp West-Vlaanderen 8020",
    "addr:housenumber":"31",
    "addr:postcode":"8020",
    "addr:street":"Baliebrugstraat",
    "iso:country":"BE",
    "sg:address":"Baliebrugstraat 31",
    "sg:city":"Oostkamp",
    "sg:orig_category":"Catering and organisatie van feesten",
    "sg:phone":"+32 50 28 05 67",
    "sg:postcode":"8020",
    "sg:province":"West-Vlaanderen",
    "wof:name":"Peter Constant",
    "wof:placetype":"venue"
},
  "geometry": {"coordinates":[3.168612957,51.0731163025],"type":"Point"}
}