{
  "type": "Feature",
  "properties": {
    "iso:country":"BE",
    "sg:address":"Boshoek 91",
    "sg:city":"Nijlen",
    "sg:orig_category":"Rundveehouders",
    "sg:phone":"+32 3 481 88 02",
    "sg:postcode":"2560",
    "sg:province":"Antwerpen",
    "wof:name":"Jozef Hens",
    "wof:placetype":"venue"
},
  "geometry": {"coordinates":[4.6999731064,51.1555328369],"type":"Point"}
}