{
  "type": "Feature",
  "properties": {
    "addr:full":"Brusselsesteenweg 379 Herent Vlaams-Brabant 3020",
    "addr:housenumber":"379",
    "addr:postcode":"3020",
    "addr:street":"Brusselsesteenweg",
    "iso:country":"BE",
    "sg:address":"Brusselsesteenweg 379",
    "sg:city":"Herent",
    "sg:orig_category":"Animaux domestiques and accessoires. Fleurs and plantes. Articles de jardin. Souvenirs and objets ar",
    "sg:phone":"+32 16 48 02 60",
    "sg:postcode":"3020",
    "sg:province":"Vlaams-Brabant",
    "wof:name":"Tuincentrum Botanica",
    "wof:placetype":"venue"
},
  "geometry": {"coordinates":[4.6591420174,50.888584137],"type":"Point"}
}