{
  "type": "Feature",
  "properties": {
    "addr:full":"Dreef 15 Buggenhout Oost-Vlaanderen 9255",
    "addr:housenumber":"15",
    "addr:postcode":"9255",
    "addr:street":"Dreef",
    "iso:country":"BE",
    "sg:address":"Dreef 15",
    "sg:city":"Buggenhout",
    "sg:orig_category":"Installation \u00e9lectrique r\u00e9sidentielle",
    "sg:phone":"+32 52 35 65 08",
    "sg:postcode":"9255",
    "sg:province":"Oost-Vlaanderen",
    "wof:name":"Vincent Vandenbroeck",
    "wof:placetype":"venue"
},
  "geometry": {"coordinates":[4.1733832359,51.0037994385],"type":"Point"}
}