{
  "type": "Feature",
  "properties": {
    "addr:full":"Molenstraat 50 Heist-op-den-berg Antwerpen 2220",
    "addr:housenumber":"50",
    "addr:postcode":"2220",
    "addr:street":"Molenstraat",
    "iso:country":"BE",
    "sg:address":"Molenstraat 50",
    "sg:city":"Heist-op-den-berg",
    "sg:orig_category":"Diverse organisaties and verenigingen",
    "sg:phone":"+32 15 24 19 21",
    "sg:postcode":"2220",
    "sg:province":"Antwerpen",
    "wof:name":"Jeugdclub Vibro",
    "wof:placetype":"venue"
},
  "geometry": {"coordinates":[4.718665123,51.0792884827],"type":"Point"}
}