{
  "type": "Feature",
  "properties": {
    "addr:full":"Rue Du Village 139 Quaregnon Hainaut 7390",
    "addr:housenumber":"139",
    "addr:postcode":"7390",
    "addr:street":"Rue Du Village",
    "iso:country":"BE",
    "sg:address":"Rue Du Village 139",
    "sg:city":"Quaregnon",
    "sg:classifiers":[
        {
            "category":"Personal",
            "subcategory":"Beauty Salon",
            "type":"Services"
        }
    ],
    "sg:phone":"+32 65 79 22 66",
    "sg:postcode":"7390",
    "sg:province":"Hainaut",
    "wof:name":"Meli Belle",
    "wof:placetype":"venue"
},
  "geometry": {"coordinates":[3.8654398918,50.4410552979],"type":"Point"}
}