{
  "type": "Feature",
  "properties": {
    "addr:full":"Rue Du Roi Albert 24 Seneffe Hainaut 7180",
    "addr:housenumber":"24",
    "addr:postcode":"7180",
    "addr:street":"Rue Du Roi Albert",
    "iso:country":"BE",
    "sg:address":"Rue Du Roi Albert 24",
    "sg:city":"Seneffe",
    "sg:orig_category":"Studios photographiques",
    "sg:phone":"+32 64 54 15 04",
    "sg:postcode":"7180",
    "sg:province":"Hainaut",
    "wof:name":"L\u00b4art D\u00b4oise Ltd",
    "wof:placetype":"venue"
},
  "geometry": {"coordinates":[4.2562718391,50.5270347595],"type":"Point"}
}