{
  "type": "Feature",
  "properties": {
    "iso:country":"BE",
    "sg:address":"Rue D'en Haut 43",
    "sg:city":"Momignies",
    "sg:classifiers":[
        {
            "category":"Health Services",
            "subcategory":"Dentist",
            "type":"Services"
        }
    ],
    "sg:phone":"+32 60 51 28 50",
    "sg:postcode":"6590",
    "sg:province":"Hainaut",
    "wof:name":"Florio P",
    "wof:placetype":"venue"
},
  "geometry": {"coordinates":[4.2241849899,50.0360145569],"type":"Point"}
}