{
  "type": "Feature",
  "properties": {
    "iso:country":"BE",
    "sg:address":"Rue De La Collectivit\u00c9 72",
    "sg:city":"Saint-nicolas",
    "sg:orig_category":"Artiesten and kunstenaars",
    "sg:phone":"+32 4 226 19 21",
    "sg:postcode":"4420",
    "sg:province":"Li\u00e8ge",
    "wof:name":"Roger Francel",
    "wof:placetype":"venue"
},
  "geometry": {"coordinates":[5.5310339928,50.6385192871],"type":"Point"}
}