{
  "type": "Feature",
  "properties": {
    "addr:full":"Schoolstr 13 Oosterzele Oost-Vlaanderen 9860",
    "addr:housenumber":"13",
    "addr:postcode":"9860",
    "addr:street":"Schoolstr;Oost-Vlaanderen",
    "iso:country":"BE",
    "sg:address":"Schoolstr 13",
    "sg:city":"Oosterzele",
    "sg:classifiers":[
        {
            "category":"Home & Garden",
            "subcategory":"Furniture",
            "type":"Retail Goods"
        }
    ],
    "sg:phone":"+32 9 362 57 93",
    "sg:postcode":"9860",
    "sg:province":"Oost-Vlaanderen",
    "sg:tags":[
        "household",
        "wood"
    ],
    "wof:name":"Quipor & Zn Bvba",
    "wof:placetype":"venue"
},
  "geometry": {"coordinates":[3.8174350262,50.9716300964],"type":"Point"}
}