{
  "type": "Feature",
  "properties": {
    "addr:full":"Vlaanderenlaan 1 Leopoldsburg Limburg 3970",
    "addr:housenumber":"1",
    "addr:postcode":"3970",
    "addr:street":"Vlaanderenlaan",
    "iso:country":"BE",
    "sg:address":"Vlaanderenlaan 1",
    "sg:city":"Leopoldsburg",
    "sg:orig_category":"Gespecialiseerde residenti\u00eble bouw",
    "sg:phone":"+32 11 34 75 93",
    "sg:postcode":"3970",
    "sg:province":"Limburg",
    "wof:name":"Luc Jacobs",
    "wof:placetype":"venue"
},
  "geometry": {"coordinates":[5.2643780708,51.1114578247],"type":"Point"}
}