{
  "type": "Feature",
  "properties": {
    "iso:country":"BE",
    "sg:address":"Zeuningenstraat 8ba",
    "sg:city":"Galmaarden",
    "sg:classifiers":[
        {
            "category":"Arena",
            "subcategory":"Sports Club",
            "type":"Entertainment"
        }
    ],
    "sg:phone":"+32 54 58 65 14",
    "sg:postcode":"1570",
    "sg:province":"Vlaams-Brabant",
    "sg:tags":[
        "de"
    ],
    "wof:name":"March.team-polit.anderl.",
    "wof:placetype":"venue"
},
  "geometry": {"coordinates":[3.9941749573,50.7414321899],"type":"Point"}
}