{
  "type": "Feature",
  "properties": {
    "addr:full":"Rue Haie Monseu 35 Nandrin Li\u00e8ge 4550",
    "addr:housenumber":"35",
    "addr:postcode":"4550",
    "addr:street":"Rue Haie Monseu",
    "iso:country":"BE",
    "sg:address":"Rue Haie Monseu 35",
    "sg:city":"Nandrin",
    "sg:classifiers":[
        {
            "category":"Building & Trades",
            "subcategory":"Plumbing",
            "type":"Services"
        }
    ],
    "sg:phone":"+32 475 58 28 88",
    "sg:postcode":"4550",
    "sg:province":"Li\u00e8ge",
    "sg:tags":[
        "repair",
        "mainten",
        "-",
        "central",
        "heating"
    ],
    "wof:name":"De Prez Ets",
    "wof:placetype":"venue"
},
  "geometry": {"coordinates":[5.4283299446,50.4995803833],"type":"Point"}
}