{
  "type": "Feature",
  "properties": {
    "iso:country":"BE",
    "sg:address":"Sleepstraat 126",
    "sg:city":"Gent",
    "sg:classifiers":[
        {
            "category":"Home & Garden",
            "subcategory":"Household Appliances",
            "type":"Retail Goods"
        }
    ],
    "sg:phone":"+32 9 329 41 94",
    "sg:postcode":"9000",
    "sg:province":"Oost-Vlaanderen",
    "sg:tags":[
        "repair",
        "mainten",
        "-",
        "electric"
    ],
    "wof:name":"Electro Sehan",
    "wof:placetype":"venue"
},
  "geometry": {"coordinates":[3.7275528908,51.0620956421],"type":"Point"}
}