{
  "type": "Feature",
  "properties": {
    "iso:country":"BE",
    "sg:address":"Torhoutse Steenweg 283 Box 1",
    "sg:city":"Brugge (sint-andries)",
    "sg:classifiers":[
        {
            "category":"Home & Garden",
            "subcategory":"Home Furnishings",
            "type":"Retail Goods"
        }
    ],
    "sg:phone":"+32 50 39 00 47",
    "sg:postcode":"8200",
    "sg:province":"West-Vlaanderen",
    "sg:tags":[
        "curtain",
        "-",
        "fixture"
    ],
    "wof:name":"Artline Wooncreatie",
    "wof:placetype":"venue"
},
  "geometry": {"coordinates":[3.1989500523,51.1945343018],"type":"Point"}
}