{
  "type": "Feature",
  "properties": {
    "addr:full":"Eikelaarstraat 2ba Genk Limburg 3600",
    "addr:postcode":"3600",
    "addr:street":"Eikelaarstraat",
    "iso:country":"BE",
    "sg:address":"Eikelaarstraat 2ba",
    "sg:city":"Genk",
    "sg:orig_category":"M\u00e9decins and sp\u00e9cialistes",
    "sg:phone":"+32 89 35 15 72",
    "sg:postcode":"3600",
    "sg:province":"Limburg",
    "wof:name":"Marc Hemeryck",
    "wof:placetype":"venue"
},
  "geometry": {"coordinates":[5.4828228951,50.9271125793],"type":"Point"}
}