{
  "type": "Feature",
  "properties": {
    "addr:full":"Chauss\u00e9e De Spa 92a Theux Li\u00e8ge 4910",
    "addr:housenumber":"92a",
    "addr:postcode":"4910",
    "addr:street":"Chausse\u0301E De Spa",
    "iso:country":"BE",
    "sg:address":"Chauss\u00e9e De Spa 92a",
    "sg:city":"Theux",
    "sg:classifiers":[
        {
            "category":"Shopping",
            "subcategory":"Bicycles & Sporting Goods",
            "type":"Retail Goods"
        }
    ],
    "sg:phone":"+32 87 54 13 03",
    "sg:postcode":"4910",
    "sg:province":"Li\u00e8ge",
    "sg:tags":[
        "-"
    ],
    "wof:name":"Espace Bike",
    "wof:placetype":"venue"
},
  "geometry": {"coordinates":[5.8156609535,50.5171470642],"type":"Point"}
}