{
  "type": "Feature",
  "properties": {
    "iso:country":"BE",
    "sg:address":"Weg Naar Opoeteren 77",
    "sg:city":"Opglabbeek",
    "sg:orig_category":"Installation de menuiserie en bois and plastique",
    "sg:phone":"+32 89 85 83 64",
    "sg:postcode":"3660",
    "sg:province":"Limburg",
    "wof:name":"Ludo Geeraerts",
    "wof:placetype":"venue"
},
  "geometry": {"coordinates":[5.5939650536,51.0475997925],"type":"Point"}
}