{
  "type": "Feature",
  "properties": {
    "iso:country":"BE",
    "sg:address":"Kammenstraat 57",
    "sg:city":"Antwerpen",
    "sg:classifiers":[
        {
            "category":"Shopping",
            "subcategory":"Clothing, Apparel, & Fashions",
            "type":"Retail Goods"
        }
    ],
    "sg:phone":"+32 3 289 33 68",
    "sg:postcode":"2000",
    "sg:province":"Antwerpen",
    "sg:tags":[
        "lady",
        "clothing",
        "-"
    ],
    "wof:name":"Vegas",
    "wof:placetype":"venue"
},
  "geometry": {"coordinates":[4.4013791084,51.2167816162],"type":"Point"}
}