{
  "type": "Feature",
  "properties": {
    "addr:full":"Hoogveld 26 Dendermonde (sint-gillis-bij-dendermonde) Oost-Vlaanderen 9200",
    "addr:housenumber":"26",
    "addr:postcode":"9200",
    "addr:street":"Hoogveld",
    "iso:country":"BE",
    "sg:address":"Hoogveld 26",
    "sg:city":"Dendermonde (sint-gillis-bij-dendermonde)",
    "sg:orig_category":"Non-Classified Establishments",
    "sg:phone":"+32 52 21 57 47",
    "sg:postcode":"9200",
    "sg:province":"Oost-Vlaanderen",
    "wof:name":"A.g. Classic-design",
    "wof:placetype":"venue"
},
  "geometry": {"coordinates":[4.1352968216,51.0328559875],"type":"Point"}
}