{
  "type": "Feature",
  "properties": {
    "iso:country":"BE",
    "sg:address":"Rue D'en Haut 55",
    "sg:city":"Couvin (gonrieux)",
    "sg:classifiers":[
        {
            "category":"Health Services",
            "subcategory":"Health Practitioner",
            "type":"Services"
        }
    ],
    "sg:phone":"+32 60 34 91 34",
    "sg:postcode":"5660",
    "sg:province":"Namur",
    "sg:tags":[
        "psychologist"
    ],
    "wof:name":"Fierens F",
    "wof:placetype":"venue"
},
  "geometry": {"coordinates":[4.4966697693,50.0532112122],"type":"Point"}
}