{
  "type": "Feature",
  "properties": {
    "addr:full":"Avenue De La Floride 7 Bruxelles (uccle) Bruxelles-Capitale 1180",
    "addr:housenumber":"7",
    "addr:postcode":"1180",
    "addr:street":"Avenue De La Floride",
    "iso:country":"BE",
    "sg:address":"Avenue De La Floride 7",
    "sg:city":"Bruxelles (uccle)",
    "sg:classifiers":[
        {
            "category":"Manufacturing",
            "subcategory":"Chemicals & Compounds",
            "type":"Manufacturing & Wholesale Goods"
        }
    ],
    "sg:phone":"+32 2 374 76 14",
    "sg:postcode":"1180",
    "sg:province":"Bruxelles-Capitale",
    "sg:tags":[
        "pharmaceutical",
        "product"
    ],
    "wof:name":"I C P Sprl",
    "wof:placetype":"venue"
},
  "geometry": {"coordinates":[4.3650622368,50.8096733093],"type":"Point"}
}