{
  "type": "Feature",
  "properties": {
    "iso:country":"BE",
    "sg:address":"Rue De La Jonction 5",
    "sg:city":"Manhay (odeigne)",
    "sg:orig_category":"Non-Classified Establishments",
    "sg:phone":"+32 86 45 59 34",
    "sg:postcode":"6960",
    "sg:province":"Luxembourg",
    "wof:name":"Carlor Engineering Sa",
    "wof:placetype":"venue"
},
  "geometry": {"coordinates":[5.6754698753,50.291759491],"type":"Point"}
}