{
  "type": "Feature",
  "properties": {
    "addr:full":"Place Royale 10b2 Sint-genesius-rode/rhode-saint-genese Vlaams-Brabant 1640",
    "addr:housenumber":"10b2",
    "addr:postcode":"1640",
    "addr:street":"Place Royale",
    "iso:country":"BE",
    "sg:address":"Place Royale 10b2",
    "sg:city":"Sint-genesius-rode/rhode-saint-genese",
    "sg:orig_category":"Services de Nettoyage and de D\u00e9sinfection. Peinture. Rev\u00eatements pour sols and murs",
    "sg:phone":"+32 2 381 24 40",
    "sg:postcode":"1640",
    "sg:province":"Vlaams-Brabant",
    "wof:name":"Sousa",
    "wof:placetype":"venue"
},
  "geometry": {"coordinates":[4.3441500664,50.7446784973],"type":"Point"}
}