{
  "type": "Feature",
  "properties": {
    "iso:country":"BE",
    "sg:address":"Rue Mitoyenne 343",
    "sg:city":"Welkenraedt",
    "sg:orig_category":"Non-Classified Establishments",
    "sg:phone":"+32 87 88 39 15",
    "sg:postcode":"4840",
    "sg:province":"Li\u00e8ge",
    "wof:name":"Mabrilux Sprl",
    "wof:placetype":"venue"
},
  "geometry": {"coordinates":[5.972796917,50.6689758301],"type":"Point"}
}