{
  "type": "Feature",
  "properties": {
    "iso:country":"BE",
    "sg:address":"Rue De L\u00b4 Abbaye 12",
    "sg:city":"Assesse",
    "sg:orig_category":"Fotogravure and zetwerk",
    "sg:phone":"+32 83 65 67 55",
    "sg:postcode":"5336",
    "sg:province":"Namur",
    "wof:name":"Eurostamps",
    "wof:placetype":"venue"
},
  "geometry": {"coordinates":[4.9970359802,50.3921356201],"type":"Point"}
}