{
  "type": "Feature",
  "properties": {
    "iso:country":"BE",
    "sg:address":"Rue De Montigny 38",
    "sg:city":"Charleroi",
    "sg:classifiers":[
        {
            "category":"Personal",
            "subcategory":"Beauty Salon",
            "type":"Services"
        }
    ],
    "sg:phone":"+32 71 32 14 98",
    "sg:postcode":"6000",
    "sg:province":"Hainaut",
    "sg:tags":[
        "de",
        "coiffure"
    ],
    "wof:name":"Coiffure Casale",
    "wof:placetype":"venue"
},
  "geometry": {"coordinates":[4.4451870918,50.4084243774],"type":"Point"}
}