{
  "type": "Feature",
  "properties": {
    "iso:country":"BE",
    "sg:address":"Avenue Jules Destr\u00c9e 11",
    "sg:city":"Charleroi",
    "sg:orig_category":"Action sociale avec h\u00e9bergement",
    "sg:phone":"+32 71 30 18 47",
    "sg:postcode":"6031",
    "sg:province":"Hainaut",
    "wof:name":"Promotion Famille",
    "wof:placetype":"venue"
},
  "geometry": {"coordinates":[4.4512372017,50.4190483093],"type":"Point"}
}