{
  "type": "Feature",
  "properties": {
    "addr:full":"Paepmunte 40 Lierde Oost-Vlaanderen 9571",
    "addr:housenumber":"40",
    "addr:postcode":"9571",
    "addr:street":"Paepmunte",
    "iso:country":"BE",
    "sg:address":"Paepmunte 40",
    "sg:city":"Lierde",
    "sg:orig_category":"Industri\u00eble and commerci\u00eble bouw Woningbouw",
    "sg:phone":"+32 54 41 73 10",
    "sg:postcode":"9571",
    "sg:province":"Oost-Vlaanderen",
    "wof:name":"Johan Seghers",
    "wof:placetype":"venue"
},
  "geometry": {"coordinates":[3.8635339737,50.8086547852],"type":"Point"}
}