{
  "type": "Feature",
  "properties": {
    "iso:country":"BE",
    "sg:address":"Place Saint-guibert 8",
    "sg:city":"Gembloux-sur-orneau (gembloux)",
    "sg:classifiers":[
        {
            "category":"Personal",
            "subcategory":"Beauty Salon",
            "type":"Services"
        }
    ],
    "sg:phone":"+32 81 61 13 75",
    "sg:postcode":"5030",
    "sg:province":"Namur",
    "sg:tags":[
        "lady",
        "-",
        "hairdressing"
    ],
    "wof:name":"Lebeau M",
    "wof:placetype":"venue"
},
  "geometry": {"coordinates":[4.6979699135,50.5615348816],"type":"Point"}
}