{
  "type": "Feature",
  "properties": {
    "addr:full":"Rue De Rouillon 10 Anhee Namur 5537",
    "addr:housenumber":"10",
    "addr:postcode":"5537",
    "addr:street":"Rue De Rouillon;Namur",
    "iso:country":"BE",
    "sg:address":"Rue De Rouillon 10",
    "sg:city":"Anhee",
    "sg:classifiers":[
        {
            "category":"Cafe",
            "type":"Food & Drink"
        }
    ],
    "sg:phone":"+32 71 79 80 87",
    "sg:postcode":"5537",
    "sg:province":"Namur",
    "sg:tags":[
        "caf\u00e9s"
    ],
    "wof:name":"Caf\u00c9 Des Arcades",
    "wof:placetype":"venue"
},
  "geometry": {"coordinates":[4.8005890846,50.3332138062],"type":"Point"}
}