{
  "type": "Feature",
  "properties": {
    "addr:full":"Oostrozebekestraat 53 Meulebeke West-Vlaanderen 8760",
    "addr:housenumber":"53",
    "addr:postcode":"8760",
    "addr:street":"Oostrozebekestraat",
    "iso:country":"BE",
    "sg:address":"Oostrozebekestraat 53",
    "sg:city":"Meulebeke",
    "sg:classifiers":[
        {
            "category":"Personal",
            "subcategory":"Beauty Salon",
            "type":"Services"
        }
    ],
    "sg:phone":"+32 51 48 86 98",
    "sg:postcode":"8760",
    "sg:province":"West-Vlaanderen",
    "sg:tags":[
        "lady",
        "-",
        "hairdressing"
    ],
    "wof:name":"Kapsalon Viviane",
    "wof:placetype":"venue"
},
  "geometry": {"coordinates":[3.2912108898,50.9476356506],"type":"Point"}
}