{
  "type": "Feature",
  "properties": {
    "iso:country":"BE",
    "sg:address":"Bovenrij 65 A",
    "sg:city":"Herentals",
    "sg:orig_category":"Agences d\u00b4interim and personnel temporaire",
    "sg:phone":"+32 14 22 08 80",
    "sg:postcode":"2200",
    "sg:province":"Antwerpen",
    "wof:name":"Creyf\u00b4s Interim",
    "wof:placetype":"venue"
},
  "geometry": {"coordinates":[4.8370261192,51.1752166748],"type":"Point"}
}