{
  "type": "Feature",
  "properties": {
    "iso:country":"BE",
    "sg:address":"Hageland 14",
    "sg:city":"Aalter",
    "sg:orig_category":"Pluimveekwekers",
    "sg:phone":"+32 9 374 01 26",
    "sg:postcode":"9880",
    "sg:province":"Oost-Vlaanderen",
    "wof:name":"Christian Staelens",
    "wof:placetype":"venue"
},
  "geometry": {"coordinates":[3.3911120892,51.0819206238],"type":"Point"}
}