{
  "type": "Feature",
  "properties": {
    "addr:full":"Kloosterbergstraat 12 Diest Vlaams-Brabant 3290",
    "addr:housenumber":"12",
    "addr:postcode":"3290",
    "addr:street":"Kloosterbergstraat",
    "iso:country":"BE",
    "sg:address":"Kloosterbergstraat 12",
    "sg:city":"Diest",
    "sg:classifiers":[
        {
            "category":"Personal",
            "subcategory":"Beauty Salon",
            "type":"Services"
        }
    ],
    "sg:phone":"+32 13 32 21 61",
    "sg:postcode":"3290",
    "sg:province":"Vlaams-Brabant",
    "sg:tags":[
        "lady",
        "-",
        "hairdressing"
    ],
    "wof:name":"Ginjo Kapsalon",
    "wof:placetype":"venue"
},
  "geometry": {"coordinates":[5.056637764,50.9765205383],"type":"Point"}
}