{
  "type": "Feature",
  "properties": {
    "iso:country":"BE",
    "sg:address":"Boulevard Frans Dewandre 10",
    "sg:city":"Charleroi",
    "sg:orig_category":"Artsen and specialisten",
    "sg:phone":"+32 71 32 91 45",
    "sg:postcode":"6000",
    "sg:province":"Hainaut",
    "wof:name":"Marianne Demogue",
    "wof:placetype":"venue"
},
  "geometry": {"coordinates":[4.4510059357,50.4158744812],"type":"Point"}
}