{
  "type": "Feature",
  "properties": {
    "addr:full":"Stationsstraat 86 Sint-katelijne-waver Antwerpen 2860",
    "addr:housenumber":"86",
    "addr:postcode":"2860",
    "addr:street":"Stationsstraat",
    "iso:country":"BE",
    "sg:address":"Stationsstraat 86",
    "sg:city":"Sint-katelijne-waver",
    "sg:orig_category":"Sportclubs",
    "sg:phone":"+32 15 31 56 42",
    "sg:postcode":"2860",
    "sg:province":"Antwerpen",
    "wof:name":"Kt Moed En Kracht Mechelen",
    "wof:placetype":"venue"
},
  "geometry": {"coordinates":[4.522851944,51.07056427],"type":"Point"}
}