{
  "type": "Feature",
  "properties": {
    "iso:country":"BE",
    "sg:address":"Torenstraat 3",
    "sg:city":"Zwijndrecht",
    "sg:orig_category":"Installation \u00e9lectrique industrielle",
    "sg:phone":"+32 3 252 41 90",
    "sg:postcode":"2070",
    "sg:province":"Antwerpen",
    "wof:name":"Thyssen Aufzuge Gmbh",
    "wof:placetype":"venue"
},
  "geometry": {"coordinates":[4.3420081139,51.2166366577],"type":"Point"}
}