{
  "type": "Feature",
  "properties": {
    "addr:full":"Termerestraat 6a Herent (winksele) Vlaams-Brabant 3020",
    "addr:housenumber":"6a",
    "addr:postcode":"3020",
    "addr:street":"Termerestraat",
    "iso:country":"BE",
    "sg:address":"Termerestraat 6a",
    "sg:city":"Herent (winksele)",
    "sg:classifiers":[
        {
            "category":"Personal",
            "subcategory":"Beauty Salon",
            "type":"Services"
        }
    ],
    "sg:phone":"+32 16 48 05 89",
    "sg:postcode":"3020",
    "sg:province":"Vlaams-Brabant",
    "sg:tags":[
        "lady",
        "-",
        "hairdressing"
    ],
    "wof:name":"Claudine",
    "wof:placetype":"venue"
},
  "geometry": {"coordinates":[4.6749200821,50.9079055786],"type":"Point"}
}