{
  "type": "Feature",
  "properties": {
    "addr:full":"Denderdreve 102 Zelzate Oost-Vlaanderen 9060",
    "addr:housenumber":"102",
    "addr:postcode":"9060",
    "addr:street":"Denderdreve",
    "iso:country":"BE",
    "sg:address":"Denderdreve 102",
    "sg:city":"Zelzate",
    "sg:orig_category":"Rundveehouders",
    "sg:phone":"+32 9 344 62 57",
    "sg:postcode":"9060",
    "sg:province":"Oost-Vlaanderen",
    "wof:name":"Georges Van Thuyne",
    "wof:placetype":"venue"
},
  "geometry": {"coordinates":[3.7894220352,51.2051734924],"type":"Point"}
}