{
  "type": "Feature",
  "properties": {
    "iso:country":"BE",
    "sg:address":"Duivelshoek 11",
    "sg:city":"Sint-katelijne-waver",
    "sg:orig_category":"Producteurs de l\u00e9gumes",
    "sg:phone":"+32 15 75 35 55",
    "sg:postcode":"2861",
    "sg:province":"Antwerpen",
    "wof:name":"Jan Jaspers",
    "wof:placetype":"venue"
},
  "geometry": {"coordinates":[4.5803399086,51.0623168945],"type":"Point"}
}