{
  "type": "Feature",
  "properties": {
    "iso:country":"BE",
    "sg:address":"Lieven-gevaertln 10",
    "sg:city":"Overpelt",
    "sg:classifiers":[
        {
            "category":"Shopping",
            "subcategory":"Crafts & Fabrics",
            "type":"Retail Goods"
        }
    ],
    "sg:phone":"+32 11 80 77 07",
    "sg:postcode":"3900",
    "sg:province":"Limburg",
    "sg:tags":[
        "textile",
        "linen",
        "clothing"
    ],
    "wof:name":"Decoline Nv",
    "wof:placetype":"venue"
},
  "geometry": {"coordinates":[5.3781647682,51.2214622498],"type":"Point"}
}