{
  "type": "Feature",
  "properties": {
    "addr:full":"Vrasenestraat 83 Sint-niklaas (nieuwkerken-waas) Oost-Vlaanderen 9100",
    "addr:housenumber":"83",
    "addr:postcode":"9100",
    "addr:street":"Vrasenestraat",
    "iso:country":"BE",
    "sg:address":"Vrasenestraat 83",
    "sg:city":"Sint-niklaas (nieuwkerken-waas)",
    "sg:classifiers":[
        {
            "category":"Professional",
            "subcategory":"Accounting & Tax Preparation",
            "type":"Services"
        }
    ],
    "sg:phone":"+32 476 41 04 68",
    "sg:postcode":"9100",
    "sg:province":"Oost-Vlaanderen",
    "sg:tags":[
        "accountant"
    ],
    "wof:name":"De Vetter D",
    "wof:placetype":"venue"
},
  "geometry": {"coordinates":[4.182311058,51.1965141296],"type":"Point"}
}