{
  "type": "Feature",
  "properties": {
    "addr:full":"Hoogstraat 31 Wachtebeke Oost-Vlaanderen 9185",
    "addr:housenumber":"31",
    "addr:postcode":"9185",
    "addr:street":"Hoogstraat",
    "iso:country":"BE",
    "sg:address":"Hoogstraat 31",
    "sg:city":"Wachtebeke",
    "sg:orig_category":"Eleveurs de bovins",
    "sg:phone":"+32 9 345 64 14",
    "sg:postcode":"9185",
    "sg:province":"Oost-Vlaanderen",
    "wof:name":"Robert Van Hoecke",
    "wof:placetype":"venue"
},
  "geometry": {"coordinates":[3.9039030075,51.1881942749],"type":"Point"}
}