{
  "type": "Feature",
  "properties": {
    "iso:country":"BE",
    "sg:address":"Groene-sprietstraat 7",
    "sg:city":"Ruiselede",
    "sg:orig_category":"Installation de menuiserie m\u00e9tallique",
    "sg:phone":"+32 51 68 83 75",
    "sg:postcode":"8755",
    "sg:province":"West-Vlaanderen",
    "wof:name":"Neirinck Stalinrichtingen",
    "wof:placetype":"venue"
},
  "geometry": {"coordinates":[3.3688728809,51.0498008728],"type":"Point"}
}