{
  "type": "Feature",
  "properties": {
    "iso:country":"BE",
    "sg:address":"Nieuwstraat 13",
    "sg:city":"Sint-gillis-waas",
    "sg:classifiers":[
        {
            "category":"Personal",
            "subcategory":"Beauty Salon",
            "type":"Services"
        }
    ],
    "sg:phone":"+32 3 770 72 91",
    "sg:postcode":"9170",
    "sg:province":"Oost-Vlaanderen",
    "sg:tags":[
        "lady",
        "-",
        "hairdressing"
    ],
    "wof:name":"Haarmode Johan",
    "wof:placetype":"venue"
},
  "geometry": {"coordinates":[4.1290278435,51.2177658081],"type":"Point"}
}