{
  "type": "Feature",
  "properties": {
    "iso:country":"BE",
    "sg:address":"Rue J.-b. Vanp\u00c9 74",
    "sg:city":"Vorst/forest",
    "sg:orig_category":"Pain, p\u00e2tisseries and confiseries",
    "sg:phone":"+32 2 376 00 73",
    "sg:postcode":"1190",
    "sg:province":"Bruxelles-Capitale",
    "wof:name":"P\u00c2tisserie Grenson",
    "wof:placetype":"venue"
},
  "geometry": {"coordinates":[4.3200359344,50.8094787598],"type":"Point"}
}