{
  "type": "Feature",
  "properties": {
    "iso:country":"BE",
    "sg:address":"Pollepelstraat 11",
    "sg:city":"Wervik (geluwe)",
    "sg:classifiers":[
        {
            "category":"Building & Trades",
            "subcategory":"Construction",
            "type":"Services"
        }
    ],
    "sg:phone":"+32 56 52 02 75",
    "sg:postcode":"8940",
    "sg:province":"West-Vlaanderen",
    "sg:tags":[
        "stucco",
        "contractor"
    ],
    "wof:name":"Bostyn M",
    "wof:placetype":"venue"
},
  "geometry": {"coordinates":[3.0788760185,50.8297386169],"type":"Point"}
}