{
  "type": "Feature",
  "properties": {
    "addr:full":"Achterveld 40 De Panne (adinkerke) West-Vlaanderen 8660",
    "addr:housenumber":"40",
    "addr:postcode":"8660",
    "addr:street":"Achterveld",
    "iso:country":"BE",
    "sg:address":"Achterveld 40",
    "sg:city":"De Panne (adinkerke)",
    "sg:classifiers":[
        {
            "category":"Personal",
            "subcategory":"Beauty Salon",
            "type":"Services"
        }
    ],
    "sg:phone":"+32 58 42 01 20",
    "sg:postcode":"8660",
    "sg:province":"West-Vlaanderen",
    "sg:tags":[
        "lady",
        "-",
        "hairdressing"
    ],
    "wof:name":"Coiffure Carine",
    "wof:placetype":"venue"
},
  "geometry": {"coordinates":[2.5899751186,51.0716247559],"type":"Point"}
}