{
  "type": "Feature",
  "properties": {
    "addr:full":"Bois D\u00b4acren 99 Bever/bi\u00c9v\u00c8ne Vlaams-Brabant 1547",
    "addr:housenumber":"99;1547",
    "addr:street":"Vlaams-Brabant",
    "iso:country":"BE",
    "sg:address":"Bois D\u00b4acren 99",
    "sg:city":"Bever/bi\u00c9v\u00c8ne",
    "sg:orig_category":"Installation \u00e9lectrique r\u00e9sidentielle",
    "sg:phone":"+32 54 58 81 66",
    "sg:postcode":"1547",
    "sg:province":"Vlaams-Brabant",
    "wof:name":"Electro Avez",
    "wof:placetype":"venue"
},
  "geometry": {"coordinates":[3.913351059,50.7317962646],"type":"Point"}
}