{
  "type": "Feature",
  "properties": {
    "addr:full":"Rue De La Bont\u00e9 7 Bruxelles (saint-gilles) Bruxelles-Capitale 1060",
    "addr:housenumber":"7",
    "addr:postcode":"1060",
    "addr:street":"Rue De La Bonte\u0301",
    "iso:country":"BE",
    "sg:address":"Rue De La Bont\u00e9 7",
    "sg:city":"Bruxelles (saint-gilles)",
    "sg:classifiers":[
        {
            "category":"Manufacturing",
            "subcategory":"Food",
            "type":"Manufacturing & Wholesale Goods"
        }
    ],
    "sg:phone":"+32 2 541 02 20",
    "sg:postcode":"1060",
    "sg:province":"Bruxelles-Capitale",
    "sg:tags":[
        "industry",
        "-",
        "ingredient"
    ],
    "wof:name":"Tablas Belgium",
    "wof:placetype":"venue"
},
  "geometry": {"coordinates":[4.3578119278,50.8313827515],"type":"Point"}
}