{
  "type": "Feature",
  "properties": {
    "iso:country":"BE",
    "sg:address":"Wolvengracht 38",
    "sg:city":"Brussel",
    "sg:orig_category":"Boekhandels",
    "sg:phone":"+32 2 223 62 23",
    "sg:postcode":"1000",
    "sg:province":"Bruxelles-Capitale",
    "wof:name":"Sterling Books",
    "wof:placetype":"venue"
},
  "geometry": {"coordinates":[4.3550410271,50.8502464294],"type":"Point"}
}