{
  "type": "Feature",
  "properties": {
    "addr:full":"Rue Des Ardoisi\u00e8res 3 Bertrix Luxembourg 6880",
    "addr:housenumber":"3",
    "addr:postcode":"6880",
    "addr:street":"Rue Des Ardoisie\u0300Res",
    "iso:country":"BE",
    "sg:address":"Rue Des Ardoisi\u00e8res 3",
    "sg:city":"Bertrix",
    "sg:classifiers":[
        {
            "category":"Home & Garden",
            "subcategory":"Household Appliances",
            "type":"Retail Goods"
        }
    ],
    "sg:phone":"+32 61 41 33 46",
    "sg:postcode":"6880",
    "sg:province":"Luxembourg",
    "sg:tags":[
        "repair",
        "mainten",
        "-",
        "electric"
    ],
    "wof:name":"Beldi Electro Sprl",
    "wof:placetype":"venue"
},
  "geometry": {"coordinates":[5.2709140778,49.8445930481],"type":"Point"}
}