{
  "type": "Feature",
  "properties": {
    "addr:full":"Hoogakkers 13bc Arendonk Antwerpen 2370",
    "addr:housenumber":"13bc",
    "addr:postcode":"2370",
    "addr:street":"Hoogakkers",
    "iso:country":"BE",
    "sg:address":"Hoogakkers 13bc",
    "sg:city":"Arendonk",
    "sg:orig_category":"Woningbouw",
    "sg:phone":"+32 14 67 07 91",
    "sg:postcode":"2370",
    "sg:province":"Antwerpen",
    "wof:name":"C & M Bouw",
    "wof:placetype":"venue"
},
  "geometry": {"coordinates":[5.0778398514,51.3237380981],"type":"Point"}
}