{
  "type": "Feature",
  "properties": {
    "iso:country":"BE",
    "sg:address":"Notelaarslaan 8",
    "sg:city":"Harelbeke",
    "sg:classifiers":[
        {
            "category":"Professional",
            "subcategory":"Accounting & Tax Preparation",
            "type":"Services"
        }
    ],
    "sg:phone":"+32 56 70 60 68",
    "sg:postcode":"8530",
    "sg:province":"West-Vlaanderen",
    "sg:tags":[
        "accountant"
    ],
    "wof:name":"Jan Baert",
    "wof:placetype":"venue"
},
  "geometry": {"coordinates":[3.3019618988,50.8403778076],"type":"Point"}
}