{
  "type": "Feature",
  "properties": {
    "iso:country":"BE",
    "sg:address":"Koninklijke Baan 88",
    "sg:city":"De Haan (vlissegem)",
    "sg:classifiers":[
        {
            "category":"Tea Room",
            "subcategory":"None",
            "type":"Food & Drink"
        }
    ],
    "sg:phone":"+32 59 23 37 54",
    "sg:postcode":"8421",
    "sg:province":"West-Vlaanderen",
    "wof:name":"Riccordi",
    "wof:placetype":"venue"
},
  "geometry": {"coordinates":[3.0387649536,51.2800941467],"type":"Point"}
}