{
  "type": "Feature",
  "properties": {
    "addr:full":"Borreshoefstraat 42 Dilsen-stokkem Limburg 3650",
    "addr:housenumber":"42",
    "addr:postcode":"3650",
    "addr:street":"Borreshoefstraat",
    "iso:country":"BE",
    "sg:address":"Borreshoefstraat 42",
    "sg:city":"Dilsen-stokkem",
    "sg:orig_category":"Advocaten and juridische adviseurs",
    "sg:phone":"+32 89 75 45 44",
    "sg:postcode":"3650",
    "sg:province":"Limburg",
    "wof:name":"Dirk Arits",
    "wof:placetype":"venue"
},
  "geometry": {"coordinates":[5.7225642204,51.0343856812],"type":"Point"}
}