{
  "type": "Feature",
  "properties": {
    "iso:country":"BE",
    "sg:address":"Moerdijk 43",
    "sg:city":"Maasmechelen",
    "sg:orig_category":"Rundveehouders",
    "sg:phone":"+32 89 76 38 79",
    "sg:postcode":"3631",
    "sg:province":"Limburg",
    "wof:name":"Dieudonne Mechels",
    "wof:placetype":"venue"
},
  "geometry": {"coordinates":[5.7239232063,50.9423713684],"type":"Point"}
}