{
  "type": "Feature",
  "properties": {
    "iso:country":"BE",
    "sg:address":"Pastoor Wuytsstraat 15",
    "sg:city":"Mol",
    "sg:orig_category":"Installatie van houten of kunststof schrijnwerk",
    "sg:phone":"+32 14 31 49 01",
    "sg:postcode":"2400",
    "sg:province":"Antwerpen",
    "wof:name":"Karel Mensch",
    "wof:placetype":"venue"
},
  "geometry": {"coordinates":[5.1355051994,51.2099266052],"type":"Point"}
}