{
  "type": "Feature",
  "properties": {
    "addr:full":"Avenue Des Alouettes 37 Bruxelles (woluwe-saint-pierre) Bruxelles-Capitale 1150",
    "addr:housenumber":"37",
    "addr:postcode":"1150",
    "addr:street":"Avenue Des Alouettes",
    "iso:country":"BE",
    "sg:address":"Avenue Des Alouettes 37",
    "sg:city":"Bruxelles (woluwe-saint-pierre)",
    "sg:classifiers":[
        {
            "category":"Professional",
            "subcategory":"Art Services",
            "type":"Services"
        }
    ],
    "sg:phone":"+32 2 672 18 87",
    "sg:postcode":"1150",
    "sg:province":"Bruxelles-Capitale",
    "sg:tags":[
        "-",
        "painter",
        "artist"
    ],
    "wof:name":"Machri",
    "wof:placetype":"venue"
},
  "geometry": {"coordinates":[4.4164171219,50.8231124878],"type":"Point"}
}