{
  "type": "Feature",
  "properties": {
    "iso:country":"BE",
    "sg:address":"Rue Henri Aubry 74",
    "sg:city":"La Louviere",
    "sg:orig_category":"R\u00e9parations d'appareils \u00e9lectrom\u00e9nagers. Electrom\u00e9nager, t\u00e9l\u00e9visions and radios",
    "sg:phone":"+32 64 26 63 24",
    "sg:postcode":"7100",
    "sg:province":"Hainaut",
    "wof:name":"J.v. Services",
    "wof:placetype":"venue"
},
  "geometry": {"coordinates":[4.1850848198,50.4748649597],"type":"Point"}
}