{
  "type": "Feature",
  "properties": {
    "addr:full":"Industriepark 1247 Halen Limburg 3545",
    "addr:postcode":"1247 halen;3545",
    "addr:street":"Industriepark",
    "iso:country":"BE",
    "sg:address":"Industriepark 1247",
    "sg:city":"Halen",
    "sg:classifiers":[
        {
            "category":"Transit Center",
            "subcategory":"Freight",
            "type":"Transportation"
        }
    ],
    "sg:phone":"+32 13 46 22 76",
    "sg:postcode":"3545",
    "sg:province":"Limburg",
    "sg:tags":[
        "weighbridge"
    ],
    "wof:name":"Acw-ronox Bvba",
    "wof:placetype":"venue"
},
  "geometry": {"coordinates":[5.1106219292,50.953250885],"type":"Point"}
}