{
  "type": "Feature",
  "properties": {
    "iso:country":"BE",
    "sg:address":"Zuidlaan 115",
    "sg:city":"Wetteren",
    "sg:orig_category":"Supermarch\u00e9s",
    "sg:phone":"+32 9 365 66 11",
    "sg:postcode":"9230",
    "sg:province":"Oost-Vlaanderen",
    "wof:name":"Super G.b.",
    "wof:placetype":"venue"
},
  "geometry": {"coordinates":[3.8493950367,50.9890327454],"type":"Point"}
}