{
  "type": "Feature",
  "properties": {
    "iso:country":"BE",
    "sg:address":"Tereken 138",
    "sg:city":"Sint-niklaas",
    "sg:classifiers":[
        {
            "category":"Shopping",
            "subcategory":"Bicycles & Sporting Goods",
            "type":"Retail Goods"
        }
    ],
    "sg:phone":"+32 3 766 61 64",
    "sg:postcode":"9100",
    "sg:province":"Oost-Vlaanderen",
    "sg:tags":[
        "accessory"
    ],
    "wof:name":"Agu Belgi\u00eb Nv",
    "wof:placetype":"venue"
},
  "geometry": {"coordinates":[4.1487321854,51.1505584717],"type":"Point"}
}