{
  "type": "Feature",
  "properties": {
    "iso:country":"BE",
    "sg:address":"Avenue Du Bois De La Cambre 195",
    "sg:city":"Bruxelles (ixelles)",
    "sg:classifiers":[
        {
            "category":"Bakery",
            "type":"Food & Drink"
        }
    ],
    "sg:phone":"+32 2 646 00 87",
    "sg:postcode":"1050",
    "sg:province":"Bruxelles-Capitale",
    "sg:tags":[
        "confectioner",
        "baker"
    ],
    "wof:name":"Bois Gourmand (le)-p\u00e2tisserie De Baere",
    "wof:placetype":"venue"
},
  "geometry": {"coordinates":[4.3899669647,50.8068199158],"type":"Point"}
}