{
  "type": "Feature",
  "properties": {
    "iso:country":"BE",
    "sg:address":"Lusambostraat 9-11",
    "sg:city":"Vorst",
    "sg:orig_category":"Troc International",
    "sg:phone":"+32 2 376 34 85",
    "sg:postcode":"1190",
    "sg:province":"Bruxelles-Capitale",
    "wof:name":"Troc International",
    "wof:placetype":"venue"
},
  "geometry": {"coordinates":[4.3168148994,50.8004493713],"type":"Point"}
}