{
  "type": "Feature",
  "properties": {
    "iso:country":"BE",
    "sg:address":"Rue Grande 69",
    "sg:city":"Dinant",
    "sg:orig_category":"Boucheries",
    "sg:phone":"+32 82 22 26 18",
    "sg:postcode":"5500",
    "sg:province":"Namur",
    "wof:name":"Marc Dozot",
    "wof:placetype":"venue"
},
  "geometry": {"coordinates":[4.9145112038,50.2579421997],"type":"Point"}
}