{
  "type": "Feature",
  "properties": {
    "iso:country":"BE",
    "sg:address":"Kerkstraat 34",
    "sg:city":"Kruibeke",
    "sg:orig_category":"Rundveehouders Varkenskwekers",
    "sg:phone":"+32 3 744 06 37",
    "sg:postcode":"9150",
    "sg:province":"Oost-Vlaanderen",
    "wof:name":"Raphael Verdoorent",
    "wof:placetype":"venue"
},
  "geometry": {"coordinates":[4.2964611053,51.1477355957],"type":"Point"}
}