{
  "type": "Feature",
  "properties": {
    "iso:country":"BE",
    "sg:address":"Hoekskensweg 1",
    "sg:city":"Berlare",
    "sg:classifiers":[
        {
            "category":"Retail",
            "subcategory":"Driving School",
            "type":"Services"
        }
    ],
    "sg:phone":"+32 52 42 74 04",
    "sg:postcode":"9290",
    "sg:province":"Oost-Vlaanderen",
    "sg:tags":[
        "automobile",
        "officially",
        "-",
        "recognized"
    ],
    "wof:name":"Donkmeer",
    "wof:placetype":"venue"
},
  "geometry": {"coordinates":[4.0068101883,51.0168991089],"type":"Point"}
}