{
  "type": "Feature",
  "properties": {
    "iso:country":"BE",
    "sg:address":"Vordensteinstraat 78",
    "sg:city":"Schoten",
    "sg:classifiers":[
        {
            "category":"Bars & Pubs",
            "type":"Food & Drink"
        }
    ],
    "sg:phone":"+32 3 658 55 56",
    "sg:postcode":"2900",
    "sg:province":"Antwerpen",
    "sg:tags":[
        "tavern"
    ],
    "wof:name":"Vordensteyn",
    "wof:placetype":"venue"
},
  "geometry": {"coordinates":[4.4927158356,51.2533340454],"type":"Point"}
}