{
  "type": "Feature",
  "properties": {
    "addr:full":"Rue Marcel Thiry 15 Liege Li\u00e8ge 4000",
    "addr:housenumber":"15",
    "addr:postcode":"4000",
    "addr:street":"Rue Marcel Thiry",
    "iso:country":"BE",
    "sg:address":"Rue Marcel Thiry 15",
    "sg:city":"Liege",
    "sg:orig_category":"Paramedische behandelingen",
    "sg:phone":"+32 4 252 23 03",
    "sg:postcode":"4000",
    "sg:province":"Li\u00e8ge",
    "wof:name":"Michel Franklin",
    "wof:placetype":"venue"
},
  "geometry": {"coordinates":[5.572163105,50.6189918518],"type":"Point"}
}