{
  "type": "Feature",
  "properties": {
    "iso:country":"BE",
    "sg:address":"Lauwestraat 98",
    "sg:city":"Wevelgem",
    "sg:classifiers":[
        {
            "category":"Airport",
            "subcategory":"International",
            "type":"Transportation"
        }
    ],
    "sg:phone":"+32 56 40 22 98",
    "sg:postcode":"8560",
    "sg:province":"West-Vlaanderen",
    "sg:tags":[
        "-",
        "transport"
    ],
    "wof:name":"Transport Vanhauwaert Bvba",
    "wof:placetype":"venue"
},
  "geometry": {"coordinates":[3.1864891052,50.8060188293],"type":"Point"}
}