{
  "type": "Feature",
  "properties": {
    "addr:full":"Demervallei 8 Aarschot Vlaams-Brabant 3200",
    "addr:housenumber":"8",
    "addr:postcode":"3200",
    "addr:street":"Demervallei",
    "iso:country":"BE",
    "sg:address":"Demervallei 8",
    "sg:city":"Aarschot",
    "sg:classifiers":[
        {
            "category":"Cafe",
            "type":"Food & Drink"
        }
    ],
    "sg:phone":"+32 16 56 10 66",
    "sg:postcode":"3200",
    "sg:province":"Vlaams-Brabant",
    "sg:tags":[
        "caf\u00e9s"
    ],
    "wof:name":"Caf\u00c9 Demervallei",
    "wof:placetype":"venue"
},
  "geometry": {"coordinates":[4.8388838768,50.9823188782],"type":"Point"}
}