{
  "type": "Feature",
  "properties": {
    "addr:full":"Boulevard L\u00e9on Philippet 83 Li\u00e8ge 1 Li\u00e8ge 4000",
    "addr:housenumber":"83;1",
    "addr:postcode":"4000",
    "addr:street":"Boulevard Le\u0301On Philippet",
    "iso:country":"BE",
    "sg:address":"Boulevard L\u00e9on Philippet 83",
    "sg:city":"Li\u00e8ge 1",
    "sg:classifiers":[
        {
            "category":"Retail",
            "subcategory":"Event Space",
            "type":"Services"
        }
    ],
    "sg:phone":"+32 4 226 98 31",
    "sg:postcode":"4000",
    "sg:province":"Li\u00e8ge",
    "sg:tags":[
        "rental",
        "-",
        "hall"
    ],
    "wof:name":"Rfcl-cafetaria Athletisme",
    "wof:placetype":"venue"
},
  "geometry": {"coordinates":[5.5573329926,50.6534996033],"type":"Point"}
}