{
  "type": "Feature",
  "properties": {
    "iso:country":"BE",
    "sg:address":"Quai D\u00b4aa 7a",
    "sg:city":"Brussel/bruxelles",
    "sg:orig_category":"Quincailleries. Vis and boulons Fab",
    "sg:phone":"+32 2 521 25 39",
    "sg:postcode":"1070",
    "sg:province":"Bruxelles-Capitale",
    "wof:name":"A.d. Leydens",
    "wof:placetype":"venue"
},
  "geometry": {"coordinates":[4.3068780899,50.8239059448],"type":"Point"}
}