{
  "type": "Feature",
  "properties": {
    "iso:country":"BE",
    "sg:address":"Diepenbeekvelde 23",
    "sg:city":"Borsbeek",
    "sg:orig_category":"Rev\u00eatements de sols and murs",
    "sg:phone":"+32 3 321 44 87",
    "sg:postcode":"2150",
    "sg:province":"Antwerpen",
    "wof:name":"Mario Meyskens",
    "wof:placetype":"venue"
},
  "geometry": {"coordinates":[4.4931840897,51.1880645752],"type":"Point"}
}