{
  "type": "Feature",
  "properties": {
    "addr:full":"Adamstraat 42 Geraardsbergen Oost-Vlaanderen 9500",
    "addr:housenumber":"42",
    "addr:postcode":"9500",
    "addr:street":"Adamstraat",
    "iso:country":"BE",
    "sg:address":"Adamstraat 42",
    "sg:city":"Geraardsbergen",
    "sg:classifiers":[
        {
            "category":"Personal",
            "subcategory":"Beauty Salon",
            "type":"Services"
        }
    ],
    "sg:phone":"+32 54 41 67 83",
    "sg:postcode":"9500",
    "sg:province":"Oost-Vlaanderen",
    "sg:tags":[
        "de",
        "coiffure"
    ],
    "wof:name":"Coiffure Stef",
    "wof:placetype":"venue"
},
  "geometry": {"coordinates":[3.8742470741,50.771648407],"type":"Point"}
}