{
  "type": "Feature",
  "properties": {
    "addr:full":"Guillaume Lambertlaan 66 Genk Limburg 3600",
    "addr:housenumber":"66",
    "addr:postcode":"3600",
    "addr:street":"Guillaume Lambertlaan",
    "iso:country":"BE",
    "sg:address":"Guillaume Lambertlaan 66",
    "sg:city":"Genk",
    "sg:orig_category":"Artsen and specialisten",
    "sg:phone":"+32 89 38 51 09",
    "sg:postcode":"3600",
    "sg:province":"Limburg",
    "wof:name":"W. Olkuski",
    "wof:placetype":"venue"
},
  "geometry": {"coordinates":[5.4959712029,51.0039901733],"type":"Point"}
}