{
  "type": "Feature",
  "properties": {
    "iso:country":"BE",
    "sg:address":"K. De Backerstraat 41b1",
    "sg:city":"Hemiksem",
    "sg:orig_category":"Installation \u00e9lectrique r\u00e9sidentielle",
    "sg:phone":"+32 3 877 60 63",
    "sg:postcode":"2620",
    "sg:province":"Antwerpen",
    "wof:name":"All Tech",
    "wof:placetype":"venue"
},
  "geometry": {"coordinates":[4.3428478241,51.1455307007],"type":"Point"}
}