{
  "type": "Feature",
  "properties": {
    "iso:country":"BE",
    "sg:address":"Boskantstraat 47",
    "sg:city":"Londerzeel",
    "sg:classifiers":[
        {
            "category":"Shopping",
            "subcategory":"Clothing, Apparel, & Fashions",
            "type":"Retail Goods"
        }
    ],
    "sg:phone":"+32 52 30 24 17",
    "sg:postcode":"1840",
    "sg:province":"Vlaams-Brabant",
    "sg:tags":[
        "v\u00eatements",
        "pour",
        "dame"
    ],
    "wof:name":"Willem Vranckaert",
    "wof:placetype":"venue"
},
  "geometry": {"coordinates":[4.2336478233,50.9950714111],"type":"Point"}
}