{
  "type": "Feature",
  "properties": {
    "iso:country":"BE",
    "sg:address":"Werchtersesteenweg 11",
    "sg:city":"Haacht",
    "sg:classifiers":[
        {
            "category":"Health Services",
            "subcategory":"Dentist",
            "type":"Services"
        }
    ],
    "sg:phone":"+32 16 60 58 08",
    "sg:postcode":"3150",
    "sg:province":"Vlaams-Brabant",
    "wof:name":"Marcelis Steven",
    "wof:placetype":"venue"
},
  "geometry": {"coordinates":[4.6389579773,50.9760246277],"type":"Point"}
}