{
  "type": "Feature",
  "properties": {
    "iso:country":"BE",
    "sg:address":"Rue Du Coll\u00e8ge 3",
    "sg:city":"Vis\u00e9",
    "sg:classifiers":[
        {
            "category":"Food & Beverages",
            "subcategory":"Groceries & Convenience Stores",
            "type":"Retail Goods"
        }
    ],
    "sg:phone":"+32 4 379 11 23",
    "sg:postcode":"4600",
    "sg:province":"Li\u00e8ge",
    "sg:tags":[
        "grocer"
    ],
    "wof:name":"Juprelle Cie Sa",
    "wof:placetype":"venue"
},
  "geometry": {"coordinates":[5.6947951317,50.7352905273],"type":"Point"}
}