{
  "type": "Feature",
  "properties": {
    "addr:full":"Leeuwerikstraat 7 Lede Oost-Vlaanderen 9340",
    "addr:housenumber":"7",
    "addr:postcode":"9340",
    "addr:street":"Leeuwerikstraat",
    "iso:country":"BE",
    "sg:address":"Leeuwerikstraat 7",
    "sg:city":"Lede",
    "sg:orig_category":"Rev\u00eatements de sols and murs. Peinture. Rev\u00eatements pour sols and murs",
    "sg:phone":"+32 53 80 18 41",
    "sg:postcode":"9340",
    "sg:province":"Oost-Vlaanderen",
    "wof:name":"All Decor",
    "wof:placetype":"venue"
},
  "geometry": {"coordinates":[3.9943480492,50.9702644348],"type":"Point"}
}