{
  "type": "Feature",
  "properties": {
    "addr:full":"Schavei 79 Overijse Vlaams-Brabant 3090",
    "addr:housenumber":"79",
    "addr:postcode":"3090",
    "addr:street":"Schavei",
    "iso:country":"BE",
    "sg:address":"Schavei 79",
    "sg:city":"Overijse",
    "sg:orig_category":"Instellingen voor mindervalide volwassenen",
    "sg:phone":"+32 2 686 05 20",
    "sg:postcode":"3090",
    "sg:province":"Vlaams-Brabant",
    "wof:name":"Home De Kerselaar",
    "wof:placetype":"venue"
},
  "geometry": {"coordinates":[4.5273098946,50.7769699097],"type":"Point"}
}