{
  "type": "Feature",
  "properties": {
    "iso:country":"BE",
    "sg:address":"Fraterstraat 30",
    "sg:city":"Merelbeke",
    "sg:orig_category":"Elektrische installaties voor woningen Industri\u00eble elektrische installaties",
    "sg:phone":"+32 9 227 82 46",
    "sg:postcode":"9820",
    "sg:province":"Oost-Vlaanderen",
    "wof:name":"Avanse",
    "wof:placetype":"venue"
},
  "geometry": {"coordinates":[3.7615299225,51.0133895874],"type":"Point"}
}