{
  "type": "Feature",
  "properties": {
    "addr:full":"Schoorstraat 18 Aalst (gijzegem) Oost-Vlaanderen 9308",
    "addr:housenumber":"18",
    "addr:postcode":"9308",
    "addr:street":"Schoorstraat",
    "iso:country":"BE",
    "sg:address":"Schoorstraat 18",
    "sg:city":"Aalst (gijzegem)",
    "sg:classifiers":[
        {
            "category":"Retail",
            "subcategory":"Event Space",
            "type":"Services"
        }
    ],
    "sg:phone":"+32 53 78 34 44",
    "sg:postcode":"9308",
    "sg:province":"Oost-Vlaanderen",
    "sg:tags":[
        "rental",
        "-",
        "hall"
    ],
    "wof:name":"Dendergalm",
    "wof:placetype":"venue"
},
  "geometry": {"coordinates":[4.0347590446,50.9603500366],"type":"Point"}
}