{
  "type": "Feature",
  "properties": {
    "addr:full":"Rue De March\u00c9 34 Vaux-sur-sure Luxembourg 6640",
    "addr:housenumber":"34",
    "addr:postcode":"6640",
    "addr:street":"Rue De Marche\u0301",
    "iso:country":"BE",
    "sg:address":"Rue De March\u00c9 34",
    "sg:city":"Vaux-sur-sure",
    "sg:orig_category":"Artsen and specialisten",
    "sg:phone":"+32 61 25 57 08",
    "sg:postcode":"6640",
    "sg:province":"Luxembourg",
    "wof:name":"Pierre Joris",
    "wof:placetype":"venue"
},
  "geometry": {"coordinates":[5.5638680458,49.9169425964],"type":"Point"}
}