{
  "type": "Feature",
  "properties": {
    "addr:full":"Gilainstraat 42 Tienen Vlaams-Brabant 3300",
    "addr:housenumber":"42",
    "addr:postcode":"3300",
    "addr:street":"Gilainstraat",
    "iso:country":"BE",
    "sg:address":"Gilainstraat 42",
    "sg:city":"Tienen",
    "sg:classifiers":[
        {
            "category":"Retail",
            "subcategory":"Repair Shop",
            "type":"Services"
        }
    ],
    "sg:phone":"+32 16 81 98 13",
    "sg:postcode":"3300",
    "sg:province":"Vlaams-Brabant",
    "sg:tags":[
        "-",
        "clothing",
        "alteration"
    ],
    "wof:name":"Cindy Shop",
    "wof:placetype":"venue"
},
  "geometry": {"coordinates":[4.9370851517,50.8093414307],"type":"Point"}
}