{
  "type": "Feature",
  "properties": {
    "addr:full":"Aalstersesteenweg 146 Ninove Oost-Vlaanderen 9400",
    "addr:housenumber":"146",
    "addr:postcode":"9400",
    "addr:street":"Aalstersesteenweg",
    "iso:country":"BE",
    "sg:address":"Aalstersesteenweg 146",
    "sg:city":"Ninove",
    "sg:classifiers":[
        {
            "category":"Real Estate",
            "subcategory":"Architect",
            "type":"Services"
        }
    ],
    "sg:postcode":"9400",
    "sg:province":"Oost-Vlaanderen",
    "wof:name":"D'hauwer A",
    "wof:placetype":"venue"
},
  "geometry": {"coordinates":[4.0289697647,50.8438186646],"type":"Point"}
}