{
  "type": "Feature",
  "properties": {
    "iso:country":"BE",
    "sg:address":"Kasteellaan 23",
    "sg:city":"Willebroek",
    "sg:orig_category":"Cr\u00e9meries",
    "sg:phone":"+32 3 886 33 91",
    "sg:postcode":"2830",
    "sg:province":"Antwerpen",
    "wof:name":"Fa. Jolesko",
    "wof:placetype":"venue"
},
  "geometry": {"coordinates":[4.3427081108,51.0511169434],"type":"Point"}
}