{
  "type": "Feature",
  "properties": {
    "addr:full":"Posthoornstraat 68 Aalst Oost-Vlaanderen 9300",
    "addr:housenumber":"68",
    "addr:postcode":"9300",
    "addr:street":"Posthoornstraat",
    "iso:country":"BE",
    "sg:address":"Posthoornstraat 68",
    "sg:city":"Aalst",
    "sg:orig_category":"Sportclubs",
    "sg:phone":"+32 53 78 77 99",
    "sg:postcode":"9300",
    "sg:province":"Oost-Vlaanderen",
    "wof:name":"Knuroo",
    "wof:placetype":"venue"
},
  "geometry": {"coordinates":[4.0259151459,50.9356842041],"type":"Point"}
}