{
  "type": "Feature",
  "properties": {
    "addr:full":"Dr. Emiel Van Winckellaan 6 Dendermonde Oost-Vlaanderen 9200",
    "addr:housenumber":"6",
    "addr:postcode":"9200",
    "addr:street":"Emiel;Winckellaan;Oost-Vlaanderen",
    "iso:country":"BE",
    "sg:address":"Dr. Emiel Van Winckellaan 6",
    "sg:city":"Dendermonde",
    "sg:classifiers":[
        {
            "category":"Education",
            "subcategory":"School",
            "type":"Public Place"
        }
    ],
    "sg:phone":"+32 52 21 17 96",
    "sg:postcode":"9200",
    "sg:province":"Oost-Vlaanderen",
    "sg:tags":[
        "secondary"
    ],
    "wof:name":"Vrij Technisch Instituut",
    "wof:placetype":"venue"
},
  "geometry": {"coordinates":[4.0970721245,51.0301971436],"type":"Point"}
}