{
  "type": "Feature",
  "properties": {
    "addr:full":"Axpoelmolenstraat 6 Tielt West-Vlaanderen 8700",
    "addr:housenumber":"6",
    "addr:postcode":"8700",
    "addr:street":"Axpoelmolenstraat",
    "iso:country":"BE",
    "sg:address":"Axpoelmolenstraat 6",
    "sg:city":"Tielt",
    "sg:orig_category":"Plantes and fleurs Producteurs de l\u00e9gumes. Fruits and l\u00e9gumes",
    "sg:phone":"+32 51 68 63 01",
    "sg:postcode":"8700",
    "sg:province":"West-Vlaanderen",
    "wof:name":"Davy Verbeke",
    "wof:placetype":"venue"
},
  "geometry": {"coordinates":[3.3804130554,51.0182266235],"type":"Point"}
}