{
  "type": "Feature",
  "properties": {
    "addr:full":"Louiza Espace 31 Bruxelles (ixelles) Bruxelles-Capitale 1050",
    "addr:postcode":"1050",
    "iso:country":"BE",
    "sg:address":"Louiza Espace 31",
    "sg:city":"Bruxelles (ixelles)",
    "sg:classifiers":[
        {
            "category":"Personal",
            "subcategory":"Beauty Salon",
            "type":"Services"
        }
    ],
    "sg:phone":"+32 2 511 20 13",
    "sg:postcode":"1050",
    "sg:province":"Bruxelles-Capitale",
    "wof:name":"Lazartigue",
    "wof:placetype":"venue"
},
  "geometry": {"coordinates":[4.3577098846,50.8363456726],"type":"Point"}
}