{
  "type": "Feature",
  "properties": {
    "iso:country":"BE",
    "sg:address":"Rue De La Station 75",
    "sg:city":"Moeskroen/mouscron",
    "sg:orig_category":"Fleurs and plantes. Souvenirs and objets artisanaux. Articles de jardin",
    "sg:phone":"+32 56 34 74 24",
    "sg:postcode":"7712",
    "sg:province":"Hainaut",
    "wof:name":"Centre Jardinage Cardoen",
    "wof:placetype":"venue"
},
  "geometry": {"coordinates":[3.2535879612,50.714931488],"type":"Point"}
}