{
  "type": "Feature",
  "properties": {
    "iso:country":"BE",
    "sg:address":"Chauss\u00e9e Du Risquons-tout 233",
    "sg:city":"Mouscron",
    "sg:classifiers":[
        {
            "category":"Health Services",
            "subcategory":"Health Practitioner",
            "type":"Services"
        }
    ],
    "sg:phone":"+32 56 34 82 81",
    "sg:postcode":"7700",
    "sg:province":"Hainaut",
    "sg:tags":[
        "physiotherapist"
    ],
    "wof:name":"Landsweerdt P",
    "wof:placetype":"venue"
},
  "geometry": {"coordinates":[3.197922945,50.7467803955],"type":"Point"}
}