{
  "type": "Feature",
  "properties": {
    "addr:full":"Mussestraat 6 Maarkedal Oost-Vlaanderen 9680",
    "addr:housenumber":"6",
    "addr:postcode":"9680",
    "addr:street":"Mussestraat",
    "iso:country":"BE",
    "sg:address":"Mussestraat 6",
    "sg:city":"Maarkedal",
    "sg:orig_category":"Rundveehouders",
    "sg:phone":"+32 55 31 36 94",
    "sg:postcode":"9680",
    "sg:province":"Oost-Vlaanderen",
    "wof:name":"Paul De Medts",
    "wof:placetype":"venue"
},
  "geometry": {"coordinates":[3.6184949875,50.7977371216],"type":"Point"}
}