{
  "type": "Feature",
  "properties": {
    "addr:full":"Stevennekens 158 Rijkevorsel Antwerpen 2310",
    "addr:housenumber":"158",
    "addr:postcode":"2310",
    "iso:country":"BE",
    "sg:address":"Stevennekens 158",
    "sg:city":"Rijkevorsel",
    "sg:classifiers":[
        {
            "category":"Bakery",
            "type":"Food & Drink"
        }
    ],
    "sg:phone":"+32 3 312 16 44",
    "sg:postcode":"2310",
    "sg:province":"Antwerpen",
    "sg:tags":[
        "confectioner",
        "baker"
    ],
    "wof:name":"Adriaensen-adams",
    "wof:placetype":"venue"
},
  "geometry": {"coordinates":[4.7701501846,51.3403816223],"type":"Point"}
}