{
  "type": "Feature",
  "properties": {
    "iso:country":"BE",
    "sg:address":"Bonneviestraat 12",
    "sg:city":"Sint-jans-molenbeek/molenbeek-saint-jean",
    "sg:orig_category":"Advocaten and juridische adviseurs",
    "sg:phone":"+32 2 453 22 00",
    "sg:postcode":"1080",
    "sg:province":"Bruxelles-Capitale",
    "wof:name":"Stephan Stoop",
    "wof:placetype":"venue"
},
  "geometry": {"coordinates":[4.3370881081,50.8565254211],"type":"Point"}
}