{
  "type": "Feature",
  "properties": {
    "addr:full":"Chauss\u00e9e Romaine 17a Frameries (noirchain) Hainaut 7080",
    "addr:housenumber":"17a",
    "addr:postcode":"7080",
    "addr:street":"Chausse\u0301E Romaine",
    "iso:country":"BE",
    "sg:address":"Chauss\u00e9e Romaine 17a",
    "sg:city":"Frameries (noirchain)",
    "sg:classifiers":[
        {
            "category":"Banks & Credit Unions",
            "subcategory":"Investment Brokerage",
            "type":"Services"
        }
    ],
    "sg:phone":"+32 65 51 20 09",
    "sg:postcode":"7080",
    "sg:province":"Hainaut",
    "sg:tags":[
        "auditor"
    ],
    "wof:name":"Toubeau Th",
    "wof:placetype":"venue"
},
  "geometry": {"coordinates":[3.9286599159,50.4029006958],"type":"Point"}
}