{
  "type": "Feature",
  "properties": {
    "addr:full":"Otegemstraat 39 Zwevegem West-Vlaanderen 8550",
    "addr:housenumber":"39",
    "addr:postcode":"8550",
    "addr:street":"Otegemstraat",
    "iso:country":"BE",
    "sg:address":"Otegemstraat 39",
    "sg:city":"Zwevegem",
    "sg:classifiers":[
        {
            "category":"Travel",
            "subcategory":"Hotels & Motels",
            "type":"Entertainment"
        }
    ],
    "sg:phone":"+32 56 50 07 46",
    "sg:postcode":"8550",
    "sg:province":"West-Vlaanderen",
    "sg:tags":[
        "supply",
        "hotels",
        "catering"
    ],
    "wof:name":"Vercapack Verpakkingen",
    "wof:placetype":"venue"
},
  "geometry": {"coordinates":[3.3362679482,50.812915802],"type":"Point"}
}