{
  "type": "Feature",
  "properties": {
    "addr:full":"Av Des Biolleux Verviers Li\u00e8ge 4800",
    "addr:postcode":"4800",
    "addr:street":"Av Des Biolleux",
    "iso:country":"BE",
    "sg:address":"Av Des Biolleux",
    "sg:city":"Verviers",
    "sg:classifiers":[
        {
            "category":"Transit Center",
            "subcategory":"Freight",
            "type":"Transportation"
        }
    ],
    "sg:phone":"+32 87 33 71 78",
    "sg:postcode":"4800",
    "sg:province":"Li\u00e8ge",
    "sg:tags":[
        "metallurgy",
        "pipe",
        "metalworking",
        "sheet"
    ],
    "wof:name":"Tuyauteries De L'est (anc: Ets Charles Verstra) Sa",
    "wof:placetype":"venue"
},
  "geometry": {"coordinates":[5.8594508171,50.5917663574],"type":"Point"}
}