{
  "type": "Feature",
  "properties": {
    "iso:country":"BE",
    "sg:address":"Georges Eekhoudlaan 15",
    "sg:city":"Brussel",
    "sg:orig_category":"Fotografen and fotostudio's",
    "sg:phone":"+32 2 241 20 84",
    "sg:postcode":"1030",
    "sg:province":"Bruxelles-Capitale",
    "wof:name":"Baeyens",
    "wof:placetype":"venue"
},
  "geometry": {"coordinates":[4.387242794,50.8758850098],"type":"Point"}
}