{
  "type": "Feature",
  "properties": {
    "addr:full":"Ommegangstraat 7 Zulte Oost-Vlaanderen 9870",
    "addr:housenumber":"7",
    "addr:postcode":"9870",
    "addr:street":"Ommegangstraat",
    "iso:country":"BE",
    "sg:address":"Ommegangstraat 7",
    "sg:city":"Zulte",
    "sg:orig_category":"Rundveehouders",
    "sg:phone":"+32 56 60 48 31",
    "sg:postcode":"9870",
    "sg:province":"Oost-Vlaanderen",
    "wof:name":"Kinderen Taelman",
    "wof:placetype":"venue"
},
  "geometry": {"coordinates":[3.4175820351,50.9046440125],"type":"Point"}
}