{
  "type": "Feature",
  "properties": {
    "addr:full":"Noordstraat 18 Heist-op-den-berg Antwerpen 2220",
    "addr:housenumber":"18",
    "addr:postcode":"2220",
    "addr:street":"Noordstraat",
    "iso:country":"BE",
    "sg:address":"Noordstraat 18",
    "sg:city":"Heist-op-den-berg",
    "sg:orig_category":"V\u00e9hicules automobiles. Entretien and r\u00e9parations de voitures",
    "sg:phone":"+32 15 24 14 25",
    "sg:postcode":"2220",
    "sg:province":"Antwerpen",
    "wof:name":"Julo Car Center",
    "wof:placetype":"venue"
},
  "geometry": {"coordinates":[4.7227311134,51.078540802],"type":"Point"}
}