{
  "type": "Feature",
  "properties": {
    "addr:full":"Industrieweg 150 Beringen (paal) Limburg 3583",
    "addr:housenumber":"150",
    "addr:postcode":"3583",
    "addr:street":"Industrieweg",
    "iso:country":"BE",
    "sg:address":"Industrieweg 150",
    "sg:city":"Beringen (paal)",
    "sg:orig_category":"Non-Classified Establishments",
    "sg:phone":"+32 11 45 85 90",
    "sg:postcode":"3583",
    "sg:province":"Limburg",
    "wof:name":"Hercules Beringen Bvba",
    "wof:placetype":"venue"
},
  "geometry": {"coordinates":[5.1706700325,51.0389442444],"type":"Point"}
}