{
  "type": "Feature",
  "properties": {
    "addr:full":"Boulevard Joseph Tirou 67-71 Charleroi Hainaut 6000",
    "addr:housenumber":"67-71",
    "addr:postcode":"6000",
    "addr:street":"Boulevard Joseph Tirou;Hainaut",
    "iso:country":"BE",
    "sg:address":"Boulevard Joseph Tirou 67-71",
    "sg:city":"Charleroi",
    "sg:classifiers":[
        {
            "category":"Shopping",
            "subcategory":"Clothing, Apparel, & Fashions",
            "type":"Retail Goods"
        }
    ],
    "sg:phone":"+32 71 31 59 39",
    "sg:postcode":"6000",
    "sg:province":"Hainaut",
    "sg:tags":[
        "lady",
        "clothing",
        "-"
    ],
    "wof:name":"Styl Sa",
    "wof:placetype":"venue"
},
  "geometry": {"coordinates":[4.4408931732,50.4086685181],"type":"Point"}
}