{
  "type": "Feature",
  "properties": {
    "addr:full":"Rue De Gilly 30 Chatelet Hainaut 6200",
    "addr:housenumber":"30",
    "addr:postcode":"6200",
    "addr:street":"Rue De Gilly;Hainaut",
    "iso:country":"BE",
    "sg:address":"Rue De Gilly 30",
    "sg:city":"Chatelet",
    "sg:orig_category":"Journaux. Tabac",
    "sg:phone":"+32 71 38 29 31",
    "sg:postcode":"6200",
    "sg:province":"Hainaut",
    "wof:name":"Press Shop",
    "wof:placetype":"venue"
},
  "geometry": {"coordinates":[4.5177760124,50.4095535278],"type":"Point"}
}