{
  "type": "Feature",
  "properties": {
    "iso:country":"BE",
    "sg:address":"Tuinstraat 9bc",
    "sg:city":"Lommel",
    "sg:orig_category":"Peinture. Rev\u00eatements pour sols and murs",
    "sg:phone":"+32 11 54 10 90",
    "sg:postcode":"3920",
    "sg:province":"Limburg",
    "wof:name":"Yvo Vandenboer",
    "wof:placetype":"venue"
},
  "geometry": {"coordinates":[5.3170981407,51.2286186218],"type":"Point"}
}