{
  "type": "Feature",
  "properties": {
    "addr:full":"Avenue Albert Elisabeth 2 Nivelles Brabant Wallon 1404",
    "addr:housenumber":"2",
    "addr:postcode":"1404",
    "addr:street":"Avenue Albert Elisabeth",
    "iso:country":"BE",
    "sg:address":"Avenue Albert Elisabeth 2",
    "sg:city":"Nivelles",
    "sg:orig_category":"Filosofische and religieuze organisaties",
    "sg:phone":"+32 67 22 09 95",
    "sg:postcode":"1404",
    "sg:province":"Brabant Wallon",
    "wof:name":"Eglise Evang\u00c9lique De R\u00c9veil",
    "wof:placetype":"venue"
},
  "geometry": {"coordinates":[4.2718701363,50.599773407],"type":"Point"}
}