{
  "type": "Feature",
  "properties": {
    "iso:country":"BE",
    "sg:address":"Place Marie-jose 1",
    "sg:city":"Elsene/ixelles",
    "sg:orig_category":"Boucheries",
    "sg:phone":"+32 2 647 79 30",
    "sg:postcode":"1050",
    "sg:province":"Bruxelles-Capitale",
    "wof:name":"Boucherie Marie-jos\u00c9",
    "wof:placetype":"venue"
},
  "geometry": {"coordinates":[4.3875231743,50.8066635132],"type":"Point"}
}