{
  "type": "Feature",
  "properties": {
    "addr:full":"Albertstraat 10 Beerse Antwerpen 2340",
    "addr:housenumber":"10",
    "addr:postcode":"2340",
    "addr:street":"Albertstraat",
    "iso:country":"BE",
    "sg:address":"Albertstraat 10",
    "sg:city":"Beerse",
    "sg:orig_category":"M\u00e9decins and sp\u00e9cialistes",
    "sg:phone":"+32 14 61 16 04",
    "sg:postcode":"2340",
    "sg:province":"Antwerpen",
    "wof:name":"A. Aerts",
    "wof:placetype":"venue"
},
  "geometry": {"coordinates":[4.8575978279,51.3222007751],"type":"Point"}
}