{
  "type": "Feature",
  "properties": {
    "iso:country":"BE",
    "sg:address":"Rue De L\u00b4arsenal 25",
    "sg:city":"Pont-a-celle",
    "sg:orig_category":"Babyspullen Meubelzaken, woning- and keukeninrichting",
    "sg:phone":"+32 71 84 39 77",
    "sg:postcode":"6230",
    "sg:province":"Hainaut",
    "wof:name":"Denuit",
    "wof:placetype":"venue"
},
  "geometry": {"coordinates":[-0.1088199988,51.554901123],"type":"Point"}
}