{
  "type": "Feature",
  "properties": {
    "addr:full":"Mathias Joostenslaan 6 Zoersel Antwerpen 2980",
    "addr:housenumber":"6",
    "addr:postcode":"2980",
    "addr:street":"Joostenslaan",
    "iso:country":"BE",
    "sg:address":"Mathias Joostenslaan 6",
    "sg:city":"Zoersel",
    "sg:orig_category":"Pleisterwerk",
    "sg:phone":"+32 3 384 12 06",
    "sg:postcode":"2980",
    "sg:province":"Antwerpen",
    "wof:name":"Willy Laureyssens",
    "wof:placetype":"venue"
},
  "geometry": {"coordinates":[4.6290478706,51.2608947754],"type":"Point"}
}