{
  "type": "Feature",
  "properties": {
    "iso:country":"BE",
    "sg:address":"Oude Beselarestraat 148",
    "sg:city":"Wervik",
    "sg:orig_category":"Banques and organismes de cr\u00e9dit",
    "sg:phone":"+32 56 31 17 18",
    "sg:postcode":"8940",
    "sg:province":"West-Vlaanderen",
    "wof:name":"Ippa",
    "wof:placetype":"venue"
},
  "geometry": {"coordinates":[3.0459411144,50.7893180847],"type":"Point"}
}