{
  "type": "Feature",
  "properties": {
    "iso:country":"BE",
    "sg:address":"K. Madoudreef 17",
    "sg:city":"Brecht",
    "sg:orig_category":"Ordinateurs and \u00e9quipement informatique",
    "sg:phone":"+32 3 663 28 05",
    "sg:postcode":"2960",
    "sg:province":"Antwerpen",
    "wof:name":"Axis Consult",
    "wof:placetype":"venue"
},
  "geometry": {"coordinates":[4.5576729774,51.3143157959],"type":"Point"}
}