{
  "type": "Feature",
  "properties": {
    "addr:full":"Engelsenlaan 164 Ronse/renaix Oost-Vlaanderen 9600",
    "addr:housenumber":"164",
    "addr:postcode":"9600",
    "addr:street":"Engelsenlaan",
    "iso:country":"BE",
    "sg:address":"Engelsenlaan 164",
    "sg:city":"Ronse/renaix",
    "sg:orig_category":"Kapsalons",
    "sg:phone":"+32 55 21 87 88",
    "sg:postcode":"9600",
    "sg:province":"Oost-Vlaanderen",
    "wof:name":"Coiffure Orchidee",
    "wof:placetype":"venue"
},
  "geometry": {"coordinates":[3.5853359699,50.7438812256],"type":"Point"}
}