{
  "type": "Feature",
  "properties": {
    "iso:country":"BE",
    "sg:address":"Kattestraat 81",
    "sg:city":"Kuurne",
    "sg:orig_category":"Non-Classified Establishments",
    "sg:phone":"+32 56 71 84 31",
    "sg:postcode":"8520",
    "sg:province":"West-Vlaanderen",
    "wof:name":"Oosterlynck Nv",
    "wof:placetype":"venue"
},
  "geometry": {"coordinates":[3.2804820538,50.8563575745],"type":"Point"}
}