{
  "type": "Feature",
  "properties": {
    "addr:full":"Quai De Couronmeuse 70 Liege Li\u00e8ge 4000",
    "addr:housenumber":"70",
    "addr:postcode":"4000",
    "addr:street":"Quai De Couronmeuse",
    "iso:country":"BE",
    "sg:address":"Quai De Couronmeuse 70",
    "sg:city":"Liege",
    "sg:orig_category":"Diverse machines voor de nijverheid Gh",
    "sg:phone":"+32 4 227 06 71",
    "sg:postcode":"4000",
    "sg:province":"Li\u00e8ge",
    "wof:name":"Li\u00c8ge Soudage",
    "wof:placetype":"venue"
},
  "geometry": {"coordinates":[5.6073970795,50.6538467407],"type":"Point"}
}