{
  "type": "Feature",
  "properties": {
    "addr:full":"Langestraat 96 Kruibeke Oost-Vlaanderen 9150",
    "addr:housenumber":"96",
    "addr:postcode":"9150",
    "addr:street":"Langestraat",
    "iso:country":"BE",
    "sg:address":"Langestraat 96",
    "sg:city":"Kruibeke",
    "sg:orig_category":"Centres de relaxation and bien-\u00eatre",
    "sg:phone":"+32 3 774 06 79",
    "sg:postcode":"9150",
    "sg:province":"Oost-Vlaanderen",
    "wof:name":"Mode Mirano",
    "wof:placetype":"venue"
},
  "geometry": {"coordinates":[4.3150811195,51.1752433777],"type":"Point"}
}