{
  "type": "Feature",
  "properties": {
    "iso:country":"BE",
    "sg:address":"Karperstraat 10",
    "sg:city":"Oostende (zandvoorde)",
    "sg:classifiers":[
        {
            "category":"Real Estate",
            "subcategory":"Real Estate Services",
            "type":"Services"
        }
    ],
    "sg:phone":"+32 59 70 60 35",
    "sg:postcode":"8400",
    "sg:province":"West-Vlaanderen",
    "wof:name":"West Horeca Invest Nv",
    "wof:placetype":"venue"
},
  "geometry": {"coordinates":[2.9428339005,51.2088165283],"type":"Point"}
}