{
  "type": "Feature",
  "properties": {
    "addr:full":"Avenue D'itterbeek 460 Bruxelles (anderlecht) Bruxelles-Capitale 1070",
    "addr:housenumber":"460",
    "addr:postcode":"1070",
    "addr:street":"Avenue D'Itterbeek",
    "iso:country":"BE",
    "sg:address":"Avenue D'itterbeek 460",
    "sg:city":"Bruxelles (anderlecht)",
    "sg:classifiers":[
        {
            "category":"Bars & Pubs",
            "type":"Food & Drink"
        }
    ],
    "sg:phone":"+32 2 522 47 68",
    "sg:postcode":"1070",
    "sg:province":"Bruxelles-Capitale",
    "sg:tags":[
        "tavern"
    ],
    "wof:name":"Le Brel",
    "wof:placetype":"venue"
},
  "geometry": {"coordinates":[4.2727150917,50.836025238],"type":"Point"}
}