{
  "type": "Feature",
  "properties": {
    "addr:full":"Dorpsstraat 152 Knokke-heist West-Vlaanderen 8300",
    "addr:housenumber":"152",
    "addr:postcode":"8300",
    "addr:street":"Dorpsstraat",
    "iso:country":"BE",
    "sg:address":"Dorpsstraat 152",
    "sg:city":"Knokke-heist",
    "sg:orig_category":"Antiquit\u00e9s",
    "sg:phone":"+32 50 60 06 72",
    "sg:postcode":"8300",
    "sg:province":"West-Vlaanderen",
    "wof:name":"Stephan Van Allemeersch",
    "wof:placetype":"venue"
},
  "geometry": {"coordinates":[3.287694931,51.3467254639],"type":"Point"}
}