{
  "type": "Feature",
  "properties": {
    "iso:country":"BE",
    "sg:address":"Rue Des Wallons 14",
    "sg:city":"Ottignies-louvain-la-neuve",
    "sg:orig_category":"Baby- and kinderkleding Dameskledingzaken Lingerie and ondergoed",
    "sg:phone":"+32 10 45 15 69",
    "sg:postcode":"1348",
    "sg:province":"Brabant Wallon",
    "wof:name":"Jane Jeans",
    "wof:placetype":"venue"
},
  "geometry": {"coordinates":[4.616133213,50.6689491272],"type":"Point"}
}