{
  "type": "Feature",
  "properties": {
    "addr:full":"Waverse Steenweg 372 Etterbeek/etterbeek Bruxelles-Capitale 1040",
    "addr:housenumber":"372",
    "addr:postcode":"1040",
    "addr:street":"Waverse Steenweg",
    "iso:country":"BE",
    "sg:address":"Waverse Steenweg 372",
    "sg:city":"Etterbeek/etterbeek",
    "sg:orig_category":"Bagage and lederwaren",
    "sg:phone":"+32 2 230 84 34",
    "sg:postcode":"1040",
    "sg:province":"Bruxelles-Capitale",
    "wof:name":"Maison Accolade",
    "wof:placetype":"venue"
},
  "geometry": {"coordinates":[4.3951997757,50.8335914612],"type":"Point"}
}