{
  "type": "Feature",
  "properties": {
    "iso:country":"BE",
    "sg:address":"Rue Du Petit Villerot 16",
    "sg:city":"Saint-ghislain",
    "sg:orig_category":"Epiceries",
    "sg:phone":"+32 65 62 08 88",
    "sg:postcode":"7333",
    "sg:province":"Hainaut",
    "wof:name":"Alfredo Gris",
    "wof:placetype":"venue"
},
  "geometry": {"coordinates":[3.7759261131,50.4593582153],"type":"Point"}
}