{
  "type": "Feature",
  "properties": {
    "iso:country":"BE",
    "sg:address":"Jagerspad 16",
    "sg:city":"Brugge (assebroek)",
    "sg:classifiers":[
        {
            "category":"Health Services",
            "subcategory":"Health Practitioner",
            "type":"Services"
        }
    ],
    "sg:phone":"+32 50 35 41 40",
    "sg:postcode":"8310",
    "sg:province":"West-Vlaanderen",
    "sg:tags":[
        "osteopath"
    ],
    "wof:name":"Ranson Gilbert D.o.",
    "wof:placetype":"venue"
},
  "geometry": {"coordinates":[3.2513859272,51.1893196106],"type":"Point"}
}