{
  "type": "Feature",
  "properties": {
    "iso:country":"BE",
    "sg:address":"Rue De Mont 46",
    "sg:city":"Yvoir",
    "sg:orig_category":"Peinture. Rev\u00eatements pour sols and murs",
    "sg:phone":"+32 82 61 33 23",
    "sg:postcode":"5530",
    "sg:province":"Namur",
    "wof:name":"Rene Thyange",
    "wof:placetype":"venue"
},
  "geometry": {"coordinates":[4.8751621246,50.3480033875],"type":"Point"}
}