{
  "type": "Feature",
  "properties": {
    "addr:full":"Papenaard 25 Sint-martens-latem Oost-Vlaanderen 9830",
    "addr:housenumber":"25",
    "addr:postcode":"9830",
    "addr:street":"Papenaard",
    "iso:country":"BE",
    "sg:address":"Papenaard 25",
    "sg:city":"Sint-martens-latem",
    "sg:classifiers":[
        {
            "category":"Health Services",
            "subcategory":"Doctor",
            "type":"Services"
        }
    ],
    "sg:phone":"+32 9 282 30 66",
    "sg:postcode":"9830",
    "sg:province":"Oost-Vlaanderen",
    "sg:tags":[
        "medicinephysicians",
        "surgeon"
    ],
    "wof:name":"Derom P",
    "wof:placetype":"venue"
},
  "geometry": {"coordinates":[3.6126880646,51.0213165283],"type":"Point"}
}