{
  "type": "Feature",
  "properties": {
    "addr:full":"Rue Louvrex 77b11 Li\u00c8ge Li\u00e8ge 4000",
    "addr:housenumber":"77b11",
    "addr:postcode":"4000",
    "addr:street":"Rue Louvrex",
    "iso:country":"BE",
    "sg:address":"Rue Louvrex 77b11",
    "sg:city":"Li\u00c8ge",
    "sg:orig_category":"Avocats and conseillers juridiques",
    "sg:phone":"+32 4 223 18 63",
    "sg:postcode":"4000",
    "sg:province":"Li\u00e8ge",
    "wof:name":"P. Defourny",
    "wof:placetype":"venue"
},
  "geometry": {"coordinates":[5.564180851,50.6346817017],"type":"Point"}
}