{
  "type": "Feature",
  "properties": {
    "addr:full":"Naamsesteenweg 46 Oud-heverlee Vlaams-Brabant 3052",
    "addr:housenumber":"46",
    "addr:postcode":"3052",
    "addr:street":"Naamsesteenweg",
    "iso:country":"BE",
    "sg:address":"Naamsesteenweg 46",
    "sg:city":"Oud-heverlee",
    "sg:classifiers":[
        {
            "category":"Restaurant",
            "type":"Food & Drink"
        }
    ],
    "sg:phone":"+32 16 40 07 06",
    "sg:postcode":"3052",
    "sg:province":"Vlaams-Brabant",
    "wof:name":"La Pergola",
    "wof:placetype":"venue"
},
  "geometry": {"coordinates":[4.700876236,50.8276748657],"type":"Point"}
}