{
  "type": "Feature",
  "properties": {
    "addr:full":"Zanddijk 64 Dessel Antwerpen 2480",
    "addr:housenumber":"64",
    "addr:postcode":"2480",
    "addr:street":"Zanddijk",
    "iso:country":"BE",
    "sg:address":"Zanddijk 64",
    "sg:city":"Dessel",
    "sg:orig_category":"Catering and organisation de f\u00eates. Restaurants. Restaurants livraison \u00e0 domicile. Restaurants fast ",
    "sg:phone":"+32 14 37 20 49",
    "sg:postcode":"2480",
    "sg:province":"Antwerpen",
    "wof:name":"Taverne Vijverzicht",
    "wof:placetype":"venue"
},
  "geometry": {"coordinates":[5.1396150589,51.2638816833],"type":"Point"}
}