{
  "type": "Feature",
  "properties": {
    "iso:country":"BE",
    "sg:address":"Karel Van Manderstraat 14",
    "sg:city":"Meulebeke",
    "sg:classifiers":[
        {
            "category":"Professional",
            "subcategory":"Printing & Photocopies",
            "type":"Services"
        }
    ],
    "sg:phone":"+32 51 48 95 89",
    "sg:postcode":"8760",
    "sg:province":"West-Vlaanderen",
    "sg:tags":[
        "silkscreen",
        "-"
    ],
    "wof:name":"Dejonghe",
    "wof:placetype":"venue"
},
  "geometry": {"coordinates":[3.2901220322,50.9499511719],"type":"Point"}
}