{
  "type": "Feature",
  "properties": {
    "iso:country":"BE",
    "sg:address":"Kirchstrasse 42",
    "sg:city":"Lontzen",
    "sg:classifiers":[
        {
            "category":"Government",
            "subcategory":"Fire Station",
            "type":"Public Place"
        }
    ],
    "sg:phone":"+32 87 88 02 42",
    "sg:postcode":"4710",
    "sg:province":"Li\u00e8ge",
    "sg:tags":[
        "extinguisher"
    ],
    "wof:name":"Nu-swift",
    "wof:placetype":"venue"
},
  "geometry": {"coordinates":[5.9855508804,50.6616363525],"type":"Point"}
}