{
  "type": "Feature",
  "properties": {
    "iso:country":"BE",
    "sg:address":"Rue Belle-vue 30a",
    "sg:city":"Welkenraedt",
    "sg:classifiers":[
        {
            "category":"Professional",
            "subcategory":"Accounting & Tax Preparation",
            "type":"Services"
        }
    ],
    "sg:phone":"+32 87 88 07 80",
    "sg:postcode":"4840",
    "sg:province":"Li\u00e8ge",
    "sg:tags":[
        "accountant"
    ],
    "wof:name":"Fawe F",
    "wof:placetype":"venue"
},
  "geometry": {"coordinates":[5.9659237862,50.6601295471],"type":"Point"}
}