{
  "type": "Feature",
  "properties": {
    "addr:full":"Rue Du Repos 13 Bruxelles (uccle) Bruxelles-Capitale 1180",
    "addr:housenumber":"13",
    "addr:postcode":"1180",
    "addr:street":"Rue Du Repos",
    "iso:country":"BE",
    "sg:address":"Rue Du Repos 13",
    "sg:city":"Bruxelles (uccle)",
    "sg:classifiers":[
        {
            "category":"Professional",
            "subcategory":"Engineering",
            "type":"Services"
        }
    ],
    "sg:phone":"+32 2 375 03 37",
    "sg:postcode":"1180",
    "sg:province":"Bruxelles-Capitale",
    "sg:tags":[
        "-"
    ],
    "wof:name":"Antex Sa",
    "wof:placetype":"venue"
},
  "geometry": {"coordinates":[4.3439350128,50.7971839905],"type":"Point"}
}