{
  "type": "Feature",
  "properties": {
    "iso:country":"BE",
    "sg:address":"Rue Vert Lion 40",
    "sg:city":"Tournai",
    "sg:orig_category":"Biblioth\u00e8ques and archives publiques",
    "sg:phone":"+32 69 22 02 45",
    "sg:postcode":"7540",
    "sg:province":"Hainaut",
    "wof:name":"Ludoth\u00c8que De Kain",
    "wof:placetype":"venue"
},
  "geometry": {"coordinates":[3.389480114,50.6276397705],"type":"Point"}
}