{
  "type": "Feature",
  "properties": {
    "iso:country":"BE",
    "sg:address":"Spoelstraat 2",
    "sg:city":"Aalst",
    "sg:orig_category":"Schoonheidssalons",
    "sg:phone":"+32 53 70 18 00",
    "sg:postcode":"9300",
    "sg:province":"Oost-Vlaanderen",
    "wof:name":"Estetiek Martinez",
    "wof:placetype":"venue"
},
  "geometry": {"coordinates":[4.0519399643,50.9477081299],"type":"Point"}
}