{
  "type": "Feature",
  "properties": {
    "addr:full":"Vuilputstraat 96 Meulebeke West-Vlaanderen 8760",
    "addr:housenumber":"96",
    "addr:postcode":"8760",
    "addr:street":"Vuilputstraat",
    "iso:country":"BE",
    "sg:address":"Vuilputstraat 96",
    "sg:city":"Meulebeke",
    "sg:classifiers":[
        {
            "category":"Structure",
            "subcategory":"Building",
            "type":"Public Place"
        }
    ],
    "sg:phone":"+32 51 48 86 31",
    "sg:postcode":"8760",
    "sg:province":"West-Vlaanderen",
    "sg:tags":[
        "door"
    ],
    "wof:name":"Declerck & Zn",
    "wof:placetype":"venue"
},
  "geometry": {"coordinates":[3.2883019447,50.9302368164],"type":"Point"}
}