{
  "type": "Feature",
  "properties": {
    "addr:full":"Rue Alfred Haulotte 22 Ottignies-louvain-la-neuve (limelette) Brabant Wallon 1342",
    "addr:housenumber":"22",
    "addr:postcode":"1342",
    "addr:street":"Rue Alfred Haulotte",
    "iso:country":"BE",
    "sg:address":"Rue Alfred Haulotte 22",
    "sg:city":"Ottignies-louvain-la-neuve (limelette)",
    "sg:classifiers":[
        {
            "category":"Building & Trades",
            "subcategory":"Electrical",
            "type":"Services"
        }
    ],
    "sg:phone":"+32 10 41 85 40",
    "sg:postcode":"1342",
    "sg:province":"Brabant Wallon",
    "sg:tags":[
        "electric",
        "-",
        "housewiring",
        "contractor"
    ],
    "wof:name":"Elextra",
    "wof:placetype":"venue"
},
  "geometry": {"coordinates":[4.5401749611,50.6890258789],"type":"Point"}
}