{
  "type": "Feature",
  "properties": {
    "addr:full":"Rue Des Fran\u00e7ais 12 Les Bons Villers (frasnes-lez-gosselies) Hainaut 6210",
    "addr:housenumber":"12",
    "addr:postcode":"6210",
    "addr:street":"Rue Des Franc\u0327Ais",
    "iso:country":"BE",
    "sg:address":"Rue Des Fran\u00e7ais 12",
    "sg:city":"Les Bons Villers (frasnes-lez-gosselies)",
    "sg:classifiers":[
        {
            "category":"Food & Beverages",
            "subcategory":"Meat & Fish",
            "type":"Retail Goods"
        }
    ],
    "sg:phone":"+32 71 85 11 46",
    "sg:postcode":"6210",
    "sg:province":"Hainaut",
    "sg:tags":[
        "-",
        "livestock"
    ],
    "wof:name":"Robert R",
    "wof:placetype":"venue"
},
  "geometry": {"coordinates":[4.4511561394,50.5378227234],"type":"Point"}
}