{
  "type": "Feature",
  "properties": {
    "addr:full":"Avenue Des Combattants 53 Genappe Brabant Wallon 1470",
    "addr:housenumber":"53",
    "addr:postcode":"1470",
    "addr:street":"Avenue Des Combattants;Wallon",
    "iso:country":"BE",
    "sg:address":"Avenue Des Combattants 53",
    "sg:city":"Genappe",
    "sg:orig_category":"Boekhandels",
    "sg:phone":"+32 67 78 07 13",
    "sg:postcode":"1470",
    "sg:province":"Brabant Wallon",
    "wof:name":"Balon",
    "wof:placetype":"venue"
},
  "geometry": {"coordinates":[4.5115709305,50.6169929504],"type":"Point"}
}