{
  "type": "Feature",
  "properties": {
    "addr:full":"Rue Vert Vin\u00e2ve 112 Herstal (vottem) Li\u00e8ge 4041",
    "addr:housenumber":"112",
    "addr:postcode":"4041",
    "addr:street":"Rue Vert Vina\u0302Ve;Vottem",
    "iso:country":"BE",
    "sg:address":"Rue Vert Vin\u00e2ve 112",
    "sg:city":"Herstal (vottem)",
    "sg:classifiers":[
        {
            "category":"Health Services",
            "subcategory":"Nursing And Care Facility",
            "type":"Services"
        }
    ],
    "sg:phone":"+32 4 228 11 14",
    "sg:postcode":"4041",
    "sg:province":"Li\u00e8ge",
    "sg:tags":[
        "home"
    ],
    "wof:name":"Sombreffe",
    "wof:placetype":"venue"
},
  "geometry": {"coordinates":[5.5911359787,50.6730766296],"type":"Point"}
}