{
  "type": "Feature",
  "properties": {
    "iso:country":"BE",
    "sg:address":"Gemeenteplein 6",
    "sg:city":"Mortsel",
    "sg:classifiers":[
        {
            "category":"Cafe",
            "type":"Food & Drink"
        }
    ],
    "sg:phone":"+32 3 449 99 19",
    "sg:postcode":"2640",
    "sg:province":"Antwerpen",
    "sg:tags":[
        "caf\u00e9s"
    ],
    "wof:name":"Caf\u00c9 Breughel",
    "wof:placetype":"venue"
},
  "geometry": {"coordinates":[4.4505448341,51.1701965332],"type":"Point"}
}