{
  "type": "Feature",
  "properties": {
    "iso:country":"BE",
    "sg:address":"Goudenkruispunt 31",
    "sg:city":"Tielt-winge (sint-joris-winge)",
    "sg:classifiers":[
        {
            "category":"Shopping",
            "subcategory":"Clothing, Apparel, & Fashions",
            "type":"Retail Goods"
        }
    ],
    "sg:phone":"+32 16 63 23 16",
    "sg:postcode":"3390",
    "sg:province":"Vlaams-Brabant",
    "sg:tags":[
        "underwear",
        "lingerie",
        "-"
    ],
    "wof:name":"Lingerie Fashion",
    "wof:placetype":"venue"
},
  "geometry": {"coordinates":[4.8719830513,50.9057693481],"type":"Point"}
}