{
  "type": "Feature",
  "properties": {
    "addr:full":"Avenue De La Reine 169 Bruxelles (schaerbeek) Bruxelles-Capitale 1030",
    "addr:housenumber":"169",
    "addr:postcode":"1030",
    "addr:street":"Avenue De La Reine",
    "iso:country":"BE",
    "sg:address":"Avenue De La Reine 169",
    "sg:city":"Bruxelles (schaerbeek)",
    "sg:classifiers":[
        {
            "category":"Food & Beverages",
            "subcategory":"Groceries & Convenience Stores",
            "type":"Retail Goods"
        }
    ],
    "sg:phone":"+32 2 201 59 44",
    "sg:postcode":"1030",
    "sg:province":"Bruxelles-Capitale",
    "sg:tags":[
        "grocer"
    ],
    "wof:name":"Guven Market",
    "wof:placetype":"venue"
},
  "geometry": {"coordinates":[4.3622469902,50.8697319031],"type":"Point"}
}