{
  "type": "Feature",
  "properties": {
    "iso:country":"BE",
    "sg:address":"Provinciale Steenweg 451",
    "sg:city":"Schelle",
    "sg:orig_category":"Messageries",
    "sg:phone":"+32 3 887 89 79",
    "sg:postcode":"2627",
    "sg:province":"Antwerpen",
    "wof:name":"Transport Asto",
    "wof:placetype":"venue"
},
  "geometry": {"coordinates":[4.3328790665,51.1160125732],"type":"Point"}
}