{
  "type": "Feature",
  "properties": {
    "addr:full":"Kuringenstraat 26 Hasselt (kuringen) Limburg 3511",
    "addr:housenumber":"26",
    "addr:postcode":"3511",
    "addr:street":"Kuringenstraat",
    "iso:country":"BE",
    "sg:address":"Kuringenstraat 26",
    "sg:city":"Hasselt (kuringen)",
    "sg:classifiers":[
        {
            "category":"Arena",
            "subcategory":"Sports Club",
            "type":"Entertainment"
        }
    ],
    "sg:phone":"+32 11 55 44 56",
    "sg:postcode":"3511",
    "sg:province":"Limburg",
    "wof:name":"Time To Dive",
    "wof:placetype":"venue"
},
  "geometry": {"coordinates":[5.3024601936,50.9398117065],"type":"Point"}
}