{
  "type": "Feature",
  "properties": {
    "iso:country":"BE",
    "sg:address":"Rue Des Grands-pr\u00e9s 25",
    "sg:city":"Li\u00e8ge 1 (ch\u00ean\u00e9e)",
    "sg:classifiers":[
        {
            "category":"Social Services",
            "type":"Services"
        }
    ],
    "sg:phone":"+32 4 365 72 56",
    "sg:postcode":"4032",
    "sg:province":"Li\u00e8ge",
    "wof:name":"Emmaus Asbl",
    "wof:placetype":"venue"
},
  "geometry": {"coordinates":[5.6190099716,50.606426239],"type":"Point"}
}