{
  "type": "Feature",
  "properties": {
    "addr:full":"Wijerken 140 Lommel Limburg 3920",
    "addr:housenumber":"140",
    "addr:postcode":"3920",
    "addr:street":"Wijerken",
    "iso:country":"BE",
    "sg:address":"Wijerken 140",
    "sg:city":"Lommel",
    "sg:orig_category":"Beautyfarms, relaxatie and lichamelijk welzijn Schoonheidssalons",
    "sg:phone":"+32 11 54 35 27",
    "sg:postcode":"3920",
    "sg:province":"Limburg",
    "wof:name":"Sauna Osiris",
    "wof:placetype":"venue"
},
  "geometry": {"coordinates":[5.2936267853,51.2359161377],"type":"Point"}
}