{
  "type": "Feature",
  "properties": {
    "addr:full":"Burg. Callewaertlaan 134 Lichtervelde West-Vlaanderen 8810",
    "addr:housenumber":"134",
    "addr:postcode":"8810",
    "addr:street":"Burg. Callewaertlaan",
    "iso:country":"BE",
    "sg:address":"Burg. Callewaertlaan 134",
    "sg:city":"Lichtervelde",
    "sg:orig_category":"Assurances. Agences immobili\u00e8res",
    "sg:phone":"+32 51 72 30 77",
    "sg:postcode":"8810",
    "sg:province":"West-Vlaanderen",
    "wof:name":"Bureau De Groote",
    "wof:placetype":"venue"
},
  "geometry": {"coordinates":[3.1292479038,51.0257339478],"type":"Point"}
}