{
  "type": "Feature",
  "properties": {
    "iso:country":"BE",
    "sg:address":"Rijksweg 470",
    "sg:city":"Dilsen-stokkem (dilsen)",
    "sg:classifiers":[
        {
            "category":"Health Services",
            "subcategory":"Dentist",
            "type":"Services"
        }
    ],
    "sg:phone":"+32 89 79 20 62",
    "sg:postcode":"3650",
    "sg:province":"Limburg",
    "wof:name":"Van De Boel-swinnen",
    "wof:placetype":"venue"
},
  "geometry": {"coordinates":[5.7304620743,51.0385665894],"type":"Point"}
}