{
  "type": "Feature",
  "properties": {
    "iso:country":"BE",
    "sg:address":"Gentstraat 37",
    "sg:city":"Deinze",
    "sg:classifiers":[
        {
            "category":"Insurance",
            "subcategory":"Life Insurance",
            "type":"Services"
        }
    ],
    "sg:phone":"+32 9 386 61 29",
    "sg:postcode":"9800",
    "sg:province":"Oost-Vlaanderen",
    "sg:tags":[
        "assurance"
    ],
    "wof:name":"Oosterynck P.",
    "wof:placetype":"venue"
},
  "geometry": {"coordinates":[3.5332410336,50.9797897339],"type":"Point"}
}