{
  "type": "Feature",
  "properties": {
    "addr:full":"Boulevard Du Midi 143 Bruxelles Bruxelles-Capitale 1000",
    "addr:housenumber":"143",
    "addr:postcode":"1000",
    "addr:street":"Boulevard Du Midi",
    "iso:country":"BE",
    "sg:address":"Boulevard Du Midi 143",
    "sg:city":"Bruxelles",
    "sg:classifiers":[
        {
            "category":"Bars & Pubs",
            "type":"Food & Drink"
        }
    ],
    "sg:phone":"+32 2 537 38 02",
    "sg:postcode":"1000",
    "sg:province":"Bruxelles-Capitale",
    "sg:tags":[
        "tavern"
    ],
    "wof:name":"Faucon (le)",
    "wof:placetype":"venue"
},
  "geometry": {"coordinates":[4.3443961143,50.8334693909],"type":"Point"}
}