{
  "type": "Feature",
  "properties": {
    "iso:country":"BE",
    "sg:address":"Rue D'esneux 133",
    "sg:city":"Sprimont (dolembreux)",
    "sg:classifiers":[
        {
            "category":"Social Services",
            "type":"Services"
        }
    ],
    "sg:phone":"+32 4 380 42 18",
    "sg:postcode":"4140",
    "sg:province":"Li\u00e8ge",
    "wof:name":"Sarasvati Aed",
    "wof:placetype":"venue"
},
  "geometry": {"coordinates":[5.6147551537,50.5312614441],"type":"Point"}
}