{
  "type": "Feature",
  "properties": {
    "iso:country":"BE",
    "sg:address":"Carrefour De La Spetz 0",
    "sg:city":"Arlon",
    "sg:classifiers":[
        {
            "category":"Sports & Exercise",
            "subcategory":"Sports Center",
            "type":"Entertainment"
        }
    ],
    "sg:phone":"+32 63 22 55 28",
    "sg:postcode":"6700",
    "sg:province":"Luxembourg",
    "sg:tags":[
        "terrain",
        "hors",
        "de",
        "installation",
        "sportifs"
    ],
    "wof:name":"Hall Des Sports Beau Site",
    "wof:placetype":"venue"
},
  "geometry": {"coordinates":[5.8241848946,49.6753997803],"type":"Point"}
}