{
  "type": "Feature",
  "properties": {
    "addr:full":"Thiewinkelstraat 82 Lummen Limburg 3560",
    "addr:housenumber":"82",
    "addr:postcode":"3560",
    "addr:street":"Thiewinkelstraat",
    "iso:country":"BE",
    "sg:address":"Thiewinkelstraat 82",
    "sg:city":"Lummen",
    "sg:classifiers":[
        {
            "category":"Building & Trades",
            "subcategory":"Construction",
            "type":"Services"
        }
    ],
    "sg:phone":"+32 13 53 13 14",
    "sg:postcode":"3560",
    "sg:province":"Limburg",
    "sg:tags":[
        "stucco",
        "contractor"
    ],
    "wof:name":"Putzeys Joseph",
    "wof:placetype":"venue"
},
  "geometry": {"coordinates":[5.2308897972,50.9683494568],"type":"Point"}
}