{
  "type": "Feature",
  "properties": {
    "iso:country":"BE",
    "sg:address":"Chemin Des Roses 2",
    "sg:city":"Lessines (ollignies)",
    "sg:classifiers":[
        {
            "category":"Building & Trades",
            "subcategory":"Cleaning & Sanitation",
            "type":"Services"
        }
    ],
    "sg:phone":"+32 68 33 83 30",
    "sg:postcode":"7866",
    "sg:province":"Hainaut",
    "sg:tags":[
        "janitor"
    ],
    "wof:name":"M.p. Propret\u00e9",
    "wof:placetype":"venue"
},
  "geometry": {"coordinates":[3.8577609062,50.6785812378],"type":"Point"}
}