{
  "type": "Feature",
  "properties": {
    "addr:full":"Tramstraat 22 Destelbergen Oost-Vlaanderen 9070",
    "addr:housenumber":"22",
    "addr:postcode":"9070",
    "addr:street":"Tramstraat",
    "iso:country":"BE",
    "sg:address":"Tramstraat 22",
    "sg:city":"Destelbergen",
    "sg:orig_category":"Artsen and specialisten",
    "sg:phone":"+32 9 230 63 60",
    "sg:postcode":"9070",
    "sg:province":"Oost-Vlaanderen",
    "wof:name":"E. Dierickx",
    "wof:placetype":"venue"
},
  "geometry": {"coordinates":[3.8016459942,51.0299758911],"type":"Point"}
}