{
  "type": "Feature",
  "properties": {
    "iso:country":"BE",
    "sg:address":"Leuvensesteenweg 1094",
    "sg:city":"Evere",
    "sg:orig_category":"Bouwmaterialen Gh",
    "sg:phone":"+32 2 726 00 30",
    "sg:postcode":"1140",
    "sg:province":"Bruxelles-Capitale",
    "wof:name":"H\u00dcppe Belgium",
    "wof:placetype":"venue"
},
  "geometry": {"coordinates":[4.4229288101,50.8610305786],"type":"Point"}
}