{
  "type": "Feature",
  "properties": {
    "addr:full":"Rue De Rotheux 72 Seraing Li\u00e8ge 4100",
    "addr:housenumber":"72",
    "addr:postcode":"4100",
    "addr:street":"Rue De Rotheux",
    "iso:country":"BE",
    "sg:address":"Rue De Rotheux 72",
    "sg:city":"Seraing",
    "sg:orig_category":"Tabac",
    "sg:phone":"+32 4 337 51 87",
    "sg:postcode":"4100",
    "sg:province":"Li\u00e8ge",
    "wof:name":"Claudio Testa",
    "wof:placetype":"venue"
},
  "geometry": {"coordinates":[5.5047388077,50.5858917236],"type":"Point"}
}