{
  "type": "Feature",
  "properties": {
    "iso:country":"BE",
    "sg:address":"Ren\u00c9 Declercqstraat 12",
    "sg:city":"Sint-pieters-woluwe/woluwe-saint-pierre",
    "sg:orig_category":"Schoenen",
    "sg:phone":"+32 2 771 40 27",
    "sg:postcode":"1150",
    "sg:province":"Bruxelles-Capitale",
    "wof:name":"Tirone",
    "wof:placetype":"venue"
},
  "geometry": {"coordinates":[4.4320340157,50.8369445801],"type":"Point"}
}