{
  "type": "Feature",
  "properties": {
    "iso:country":"BE",
    "sg:address":"Rue D'ath 9",
    "sg:city":"Leuze-en-hainaut",
    "sg:orig_category":"Slagers",
    "sg:phone":"+32 69 66 46 46",
    "sg:postcode":"7900",
    "sg:province":"Hainaut",
    "wof:name":"Centrale Des Viandes",
    "wof:placetype":"venue"
},
  "geometry": {"coordinates":[3.6233890057,50.5998535156],"type":"Point"}
}