{
  "type": "Feature",
  "properties": {
    "iso:country":"BE",
    "sg:address":"Rue Joseph Wauters 17",
    "sg:city":"Marchin",
    "sg:orig_category":"Artsen and specialisten",
    "sg:phone":"+32 85 21 35 65",
    "sg:postcode":"4570",
    "sg:province":"Li\u00e8ge",
    "wof:name":"Pierre Wathieu",
    "wof:placetype":"venue"
},
  "geometry": {"coordinates":[5.2293782234,50.4797325134],"type":"Point"}
}