{
  "type": "Feature",
  "properties": {
    "addr:full":"Rue Du Bailli 25 Brussel/bruxelles Bruxelles-Capitale 1000",
    "addr:housenumber":"25",
    "addr:postcode":"1000",
    "addr:street":"Rue Du Bailli;/",
    "iso:country":"BE",
    "sg:address":"Rue Du Bailli 25",
    "sg:city":"Brussel/bruxelles",
    "sg:orig_category":"Textiles. V\u00eatements. Accessoires vestimentaires",
    "sg:phone":"+32 2 647 64 51",
    "sg:postcode":"1000",
    "sg:province":"Bruxelles-Capitale",
    "wof:name":"Maison Art & Fil",
    "wof:placetype":"venue"
},
  "geometry": {"coordinates":[4.3620882034,50.8267364502],"type":"Point"}
}