{
  "type": "Feature",
  "properties": {
    "addr:full":"Kerkwegel 12a Wetteren Oost-Vlaanderen 9230",
    "addr:housenumber":"12a",
    "addr:postcode":"9230",
    "addr:street":"Kerkwegel",
    "iso:country":"BE",
    "sg:address":"Kerkwegel 12a",
    "sg:city":"Wetteren",
    "sg:classifiers":[
        {
            "category":"Professional",
            "subcategory":"Management & Consulting",
            "type":"Services"
        }
    ],
    "sg:phone":"+32 9 366 28 35",
    "sg:postcode":"9230",
    "sg:province":"Oost-Vlaanderen",
    "sg:tags":[
        "consultant"
    ],
    "wof:name":"Tilkon Studie- En Adviesbureau",
    "wof:placetype":"venue"
},
  "geometry": {"coordinates":[3.8858399391,51.0058670044],"type":"Point"}
}