{
  "type": "Feature",
  "properties": {
    "iso:country":"BE",
    "sg:address":"Chauss\u00c9e De Charleroi 501",
    "sg:city":"Fleurus",
    "sg:classifiers":[
        {
            "category":"Insurance",
            "subcategory":"Insurance Agent",
            "type":"Services"
        }
    ],
    "sg:phone":"+32 71 81 17 47",
    "sg:postcode":"6220",
    "sg:province":"Hainaut",
    "sg:tags":[
        "verzekeringsmakelaars",
        "expert"
    ],
    "wof:name":"Hupe Freres",
    "wof:placetype":"venue"
},
  "geometry": {"coordinates":[4.5427470207,50.4730987549],"type":"Point"}
}