{
  "type": "Feature",
  "properties": {
    "iso:country":"BE",
    "sg:address":"Rue De La Loi 83",
    "sg:city":"Bruxelles",
    "sg:classifiers":[
        {
            "category":"Government",
            "subcategory":"Embassy",
            "type":"Public Place"
        }
    ],
    "sg:phone":"+32 2 231 03 13",
    "sg:postcode":"1000",
    "sg:province":"Bruxelles-Capitale",
    "sg:tags":[
        "consulate"
    ],
    "wof:name":"Espana Oficina De Castilla La Mancha",
    "wof:placetype":"venue"
},
  "geometry": {"coordinates":[4.3682599068,50.8455886841],"type":"Point"}
}