{
  "type": "Feature",
  "properties": {
    "iso:country":"BE",
    "sg:address":"Boskant 39a",
    "sg:city":"Bornem",
    "sg:classifiers":[
        {
            "category":"Professional",
            "subcategory":"Management & Consulting",
            "type":"Services"
        }
    ],
    "sg:phone":"+32 3 899 16 51",
    "sg:postcode":"2880",
    "sg:province":"Antwerpen",
    "sg:tags":[
        "consultant"
    ],
    "wof:name":"A.p. Logistics & Marketing Consulting",
    "wof:placetype":"venue"
},
  "geometry": {"coordinates":[4.2229919434,51.0821304321],"type":"Point"}
}