{
  "type": "Feature",
  "properties": {
    "iso:country":"BE",
    "sg:address":"Rue Joseph Coosemans 107",
    "sg:city":"Schaarbeek/schaerbeek",
    "sg:orig_category":"Activit\u00e9s diverses d'imprimerie. R\u00e9alisation de programmes and logiciels. Production de films, t\u00e9l\u00e9f",
    "sg:phone":"+32 2 732 03 65",
    "sg:postcode":"1030",
    "sg:province":"Bruxelles-Capitale",
    "wof:name":"Grab It",
    "wof:placetype":"venue"
},
  "geometry": {"coordinates":[4.3904561996,50.8557853699],"type":"Point"}
}