{
  "type": "Feature",
  "properties": {
    "addr:full":"Kortakker Aarschot (rillaar) Vlaams-Brabant 3202",
    "addr:postcode":"3202",
    "addr:street":"Kortakker",
    "iso:country":"BE",
    "sg:address":"Kortakker",
    "sg:city":"Aarschot (rillaar)",
    "sg:classifiers":[
        {
            "category":"Education",
            "subcategory":"Music School",
            "type":"Public Place"
        }
    ],
    "sg:phone":"+32 16 56 18 25",
    "sg:postcode":"3202",
    "sg:province":"Vlaams-Brabant",
    "sg:tags":[
        "-",
        "teacher",
        "private"
    ],
    "wof:name":"Muziekschool A Meulemans Vzw",
    "wof:placetype":"venue"
},
  "geometry": {"coordinates":[4.8926901817,50.9797515869],"type":"Point"}
}