{
  "type": "Feature",
  "properties": {
    "iso:country":"BE",
    "sg:address":"Molenpoel 14",
    "sg:city":"Lanaken",
    "sg:orig_category":"Artsen and specialisten",
    "sg:phone":"+32 89 71 55 00",
    "sg:postcode":"3620",
    "sg:province":"Limburg",
    "wof:name":"Bernardus Jans",
    "wof:placetype":"venue"
},
  "geometry": {"coordinates":[5.6551351547,50.8912277222],"type":"Point"}
}