{
  "type": "Feature",
  "properties": {
    "iso:country":"BE",
    "sg:address":"Rue Malibran 75",
    "sg:city":"Elsene/ixelles",
    "sg:classifiers":[
        {
            "category":"Insurance",
            "subcategory":"Insurance Agent",
            "type":"Services"
        }
    ],
    "sg:phone":"+32 2 640 26 66",
    "sg:postcode":"1050",
    "sg:province":"Bruxelles-Capitale",
    "sg:tags":[
        "verzekeringsmakelaars",
        "expert"
    ],
    "wof:name":"Reynaers Marc",
    "wof:placetype":"venue"
},
  "geometry": {"coordinates":[4.3739199638,50.8311195374],"type":"Point"}
}