{
  "type": "Feature",
  "properties": {
    "addr:full":"Schoolstraat 18 Roeselare West-Vlaanderen 8800",
    "addr:housenumber":"18",
    "addr:postcode":"8800",
    "addr:street":"Schoolstraat",
    "iso:country":"BE",
    "sg:address":"Schoolstraat 18",
    "sg:city":"Roeselare",
    "sg:classifiers":[
        {
            "category":"Cafe",
            "type":"Food & Drink"
        }
    ],
    "sg:phone":"+32 51 24 23 67",
    "sg:postcode":"8800",
    "sg:province":"West-Vlaanderen",
    "sg:tags":[
        "caf\u00e9s"
    ],
    "wof:name":"Peter Depla",
    "wof:placetype":"venue"
},
  "geometry": {"coordinates":[3.1424360275,50.9697494507],"type":"Point"}
}