{
  "type": "Feature",
  "properties": {
    "addr:full":"Rue De Taillis-pr\u00c9 8 Chatelet Hainaut 6200",
    "addr:housenumber":"8",
    "addr:postcode":"6200",
    "addr:street":"Rue De Taillis-Pre\u0301;Hainaut",
    "iso:country":"BE",
    "sg:address":"Rue De Taillis-pr\u00c9 8",
    "sg:city":"Chatelet",
    "sg:orig_category":"Apotheken",
    "sg:phone":"+32 71 38 33 05",
    "sg:postcode":"6200",
    "sg:province":"Hainaut",
    "wof:name":"Pharmacie De Soleilmont",
    "wof:placetype":"venue"
},
  "geometry": {"coordinates":[4.5058860779,50.431930542],"type":"Point"}
}