{
  "type": "Feature",
  "properties": {
    "addr:full":"'t Walletje 70 Knokke-heist (westkapelle) West-Vlaanderen 8300",
    "addr:housenumber":"70",
    "addr:postcode":"8300",
    "addr:street":"' T Walletje",
    "iso:country":"BE",
    "sg:address":"'t Walletje 70",
    "sg:city":"Knokke-heist (westkapelle)",
    "sg:classifiers":[
        {
            "category":"Manufacturing",
            "subcategory":"Wood Products",
            "type":"Manufacturing & Wholesale Goods"
        }
    ],
    "sg:phone":"+32 50 61 22 75",
    "sg:postcode":"8300",
    "sg:province":"West-Vlaanderen",
    "sg:tags":[
        "firewood"
    ],
    "wof:name":"Loeys D",
    "wof:placetype":"venue"
},
  "geometry": {"coordinates":[3.2887070179,51.3197555542],"type":"Point"}
}