{
  "type": "Feature",
  "properties": {
    "addr:full":"Hellebeemden 5 Hasselt Limburg 3500",
    "addr:housenumber":"5",
    "addr:postcode":"3500",
    "addr:street":"Hellebeemden",
    "iso:country":"BE",
    "sg:address":"Hellebeemden 5",
    "sg:city":"Hasselt",
    "sg:classifiers":[
        {
            "category":"Building & Trades",
            "subcategory":"Cleaning & Sanitation",
            "type":"Services"
        }
    ],
    "sg:phone":"+32 11 27 05 05",
    "sg:postcode":"3500",
    "sg:province":"Limburg",
    "sg:tags":[
        "equipment",
        "industrial",
        "maintenance"
    ],
    "wof:name":"Karcher Center Limburg",
    "wof:placetype":"venue"
},
  "geometry": {"coordinates":[5.3383321762,50.9121818542],"type":"Point"}
}