{
  "type": "Feature",
  "properties": {
    "addr:full":"Rue Des Chrysanth\u00e8mes 7 Bruxelles Bruxelles-Capitale 1020",
    "addr:housenumber":"7",
    "addr:postcode":"1020",
    "addr:street":"Rue Des Chrysanthe\u0300Mes",
    "iso:country":"BE",
    "sg:address":"Rue Des Chrysanth\u00e8mes 7",
    "sg:city":"Bruxelles",
    "sg:classifiers":[
        {
            "category":"Communications",
            "subcategory":"News Services",
            "type":"Services"
        }
    ],
    "sg:phone":"+32 2 478 15 19",
    "sg:postcode":"1020",
    "sg:province":"Bruxelles-Capitale",
    "sg:tags":[
        "illustrator"
    ],
    "wof:name":"Sanchez V",
    "wof:placetype":"venue"
},
  "geometry": {"coordinates":[4.3496208191,50.879611969],"type":"Point"}
}