{
  "type": "Feature",
  "properties": {
    "addr:full":"Avenue Louis Goblet 56 Saint-ghislain Hainaut 7331",
    "addr:housenumber":"56",
    "addr:postcode":"7331",
    "addr:street":"Avenue Louis Goblet;Hainaut",
    "iso:country":"BE",
    "sg:address":"Avenue Louis Goblet 56",
    "sg:city":"Saint-ghislain",
    "sg:orig_category":"Dierenartsen",
    "sg:phone":"+32 65 64 46 30",
    "sg:postcode":"7331",
    "sg:province":"Hainaut",
    "wof:name":"Freddy Grisez",
    "wof:placetype":"venue"
},
  "geometry": {"coordinates":[3.8487169743,50.4829673767],"type":"Point"}
}