{
  "type": "Feature",
  "properties": {
    "addr:full":"Avenue De L'universit\u00e9 42 Bruxelles (ixelles) Bruxelles-Capitale 1050",
    "addr:housenumber":"42",
    "addr:postcode":"1050",
    "addr:street":"Avenue De L'Universite \u0301",
    "iso:country":"BE",
    "sg:address":"Avenue De L'universit\u00e9 42",
    "sg:city":"Bruxelles (ixelles)",
    "sg:classifiers":[
        {
            "category":"Bakery",
            "type":"Food & Drink"
        }
    ],
    "sg:phone":"+32 2 647 12 60",
    "sg:postcode":"1050",
    "sg:province":"Bruxelles-Capitale",
    "sg:tags":[
        "confectioner",
        "baker"
    ],
    "wof:name":"Van Reet Patisserie",
    "wof:placetype":"venue"
},
  "geometry": {"coordinates":[4.3876299858,50.8147277832],"type":"Point"}
}