{
  "type": "Feature",
  "properties": {
    "addr:full":"Bikschotestraat 118 Langemark-poelkapelle (langemark) West-Vlaanderen 8920",
    "addr:housenumber":"118",
    "addr:postcode":"langemark-poelkapelle;8920",
    "addr:street":"Bikschotestraat",
    "iso:country":"BE",
    "sg:address":"Bikschotestraat 118",
    "sg:city":"Langemark-poelkapelle (langemark)",
    "sg:classifiers":[
        {
            "category":"Building & Trades",
            "subcategory":"Landscaping Services",
            "type":"Services"
        }
    ],
    "sg:phone":"+32 51 54 40 27",
    "sg:postcode":"8920",
    "sg:province":"West-Vlaanderen",
    "sg:tags":[
        "gardening",
        "garden",
        "maintenance"
    ],
    "wof:name":"Parret H",
    "wof:placetype":"venue"
},
  "geometry": {"coordinates":[2.919770956,50.9132423401],"type":"Point"}
}