{
  "type": "Feature",
  "properties": {
    "addr:full":"Rue Du Bailli 39 Elsene/ixelles Bruxelles-Capitale 1050",
    "addr:housenumber":"39",
    "addr:postcode":"1050",
    "addr:street":"Rue Du Bailli",
    "iso:country":"BE",
    "sg:address":"Rue Du Bailli 39",
    "sg:city":"Elsene/ixelles",
    "sg:classifiers":[
        {
            "category":"Professional",
            "subcategory":"Art Services",
            "type":"Services"
        }
    ],
    "sg:phone":"+32 2 640 65 12",
    "sg:postcode":"1050",
    "sg:province":"Bruxelles-Capitale",
    "sg:tags":[
        "designer",
        "ontwerpers"
    ],
    "wof:name":"Anne Alexandra",
    "wof:placetype":"venue"
},
  "geometry": {"coordinates":[4.361495018,50.8265342712],"type":"Point"}
}