{
  "type": "Feature",
  "properties": {
    "addr:full":"Bredabaan 155 Brasschaat Antwerpen 2930",
    "addr:housenumber":"155",
    "addr:postcode":"2930",
    "addr:street":"Bredabaan",
    "iso:country":"BE",
    "sg:address":"Bredabaan 155",
    "sg:city":"Brasschaat",
    "sg:orig_category":"Produits interm\u00e9diaires Gr",
    "sg:phone":"+32 3 651 58 92",
    "sg:postcode":"2930",
    "sg:province":"Antwerpen",
    "wof:name":"Fran\u00c7ois Lemmens",
    "wof:placetype":"venue"
},
  "geometry": {"coordinates":[4.4841508865,51.2853050232],"type":"Point"}
}