{
  "type": "Feature",
  "properties": {
    "iso:country":"BE",
    "sg:address":"Rue Lieutenant G\u00e9n\u00e9ral Conreur 2",
    "sg:city":"Thuin (ragnies)",
    "sg:classifiers":[
        {
            "category":"Health Services",
            "subcategory":"Dentist",
            "type":"Services"
        }
    ],
    "sg:phone":"+32 71 53 34 77",
    "sg:postcode":"6532",
    "sg:province":"Hainaut",
    "wof:name":"Lef\u00e8vre R",
    "wof:placetype":"venue"
},
  "geometry": {"coordinates":[4.2827620506,50.3083953857],"type":"Point"}
}