{
  "type": "Feature",
  "properties": {
    "addr:full":"Goedendagstraat 32 Wevelgem West-Vlaanderen 8560",
    "addr:housenumber":"32",
    "addr:postcode":"8560",
    "addr:street":"Goedendagstraat",
    "iso:country":"BE",
    "sg:address":"Goedendagstraat 32",
    "sg:city":"Wevelgem",
    "sg:classifiers":[
        {
            "category":"Insurance",
            "subcategory":"Insurance Agent",
            "type":"Services"
        }
    ],
    "sg:phone":"+32 56 41 95 09",
    "sg:postcode":"8560",
    "sg:province":"West-Vlaanderen",
    "sg:tags":[
        "verzekeringsmakelaars",
        "expert"
    ],
    "wof:name":"Johan Dessauvage",
    "wof:placetype":"venue"
},
  "geometry": {"coordinates":[3.1845378876,50.8155975342],"type":"Point"}
}