{
  "type": "Feature",
  "properties": {
    "iso:country":"BE",
    "sg:address":"Rue Des Charbonnages 449",
    "sg:city":"Chatelet",
    "sg:orig_category":"Slagers",
    "sg:phone":"+32 71 38 07 60",
    "sg:postcode":"6200",
    "sg:province":"Hainaut",
    "wof:name":"Jean Moureau",
    "wof:placetype":"venue"
},
  "geometry": {"coordinates":[4.5189399719,50.4307670593],"type":"Point"}
}