{
  "type": "Feature",
  "properties": {
    "addr:full":"Rue Emile Vandervelde 41 Courcelles Hainaut 6182",
    "addr:housenumber":"41",
    "addr:postcode":"6182",
    "addr:street":"Rue Emile Vandervelde",
    "iso:country":"BE",
    "sg:address":"Rue Emile Vandervelde 41",
    "sg:city":"Courcelles",
    "sg:classifiers":[
        {
            "category":"Cafe",
            "type":"Food & Drink"
        }
    ],
    "sg:phone":"+32 71 45 92 21",
    "sg:postcode":"6182",
    "sg:province":"Hainaut",
    "sg:tags":[
        "caf\u00e9s"
    ],
    "wof:name":"Fatima Rihani",
    "wof:placetype":"venue"
},
  "geometry": {"coordinates":[4.3544559479,50.4461517334],"type":"Point"}
}