{
  "type": "Feature",
  "properties": {
    "addr:full":"Latemdreef 105 Zwalm (munkzwalm) Oost-Vlaanderen 9630",
    "addr:housenumber":"105",
    "addr:postcode":"9630",
    "addr:street":"Zwalm Munkzwalm Oost-Vlaanderen",
    "iso:country":"BE",
    "sg:address":"Latemdreef 105",
    "sg:city":"Zwalm (munkzwalm)",
    "sg:classifiers":[
        {
            "category":"Retail",
            "subcategory":"Veterinary Services",
            "type":"Services"
        }
    ],
    "sg:phone":"+32 55 49 82 03",
    "sg:postcode":"9630",
    "sg:province":"Oost-Vlaanderen",
    "sg:tags":[
        "veterinarian"
    ],
    "wof:name":"De Meulemeester L",
    "wof:placetype":"venue"
},
  "geometry": {"coordinates":[3.6950500011,50.8861198425],"type":"Point"}
}