{
  "type": "Feature",
  "properties": {
    "addr:full":"Chauss\u00c9e De Gand 1103 Sint-agatha-berchem/berchem-sainte-agathe Bruxelles-Capitale 1082",
    "addr:housenumber":"1103",
    "addr:postcode":"1082",
    "addr:street":"Chausse\u0301E De Gand;/",
    "iso:country":"BE",
    "sg:address":"Chauss\u00c9e De Gand 1103",
    "sg:city":"Sint-agatha-berchem/berchem-sainte-agathe",
    "sg:orig_category":"Electrom\u00e9nager, t\u00e9l\u00e9visions and radios",
    "sg:phone":"+32 2 469 02 09",
    "sg:postcode":"1082",
    "sg:province":"Bruxelles-Capitale",
    "wof:name":"C.d.m.-maison Rainbow",
    "wof:placetype":"venue"
},
  "geometry": {"coordinates":[4.29941082,50.8631401062],"type":"Point"}
}