{
  "type": "Feature",
  "properties": {
    "addr:full":"Sint-norbertusstraat 56 Landen Vlaams-Brabant 3400",
    "addr:housenumber":"56",
    "addr:postcode":"3400",
    "addr:street":"Sint-Norbertusstraat",
    "iso:country":"BE",
    "sg:address":"Sint-norbertusstraat 56",
    "sg:city":"Landen",
    "sg:orig_category":"Charpentes and couvertures. Plomberie, chauffage and installations sanitaires",
    "sg:phone":"+32 11 83 20 51",
    "sg:postcode":"3400",
    "sg:province":"Vlaams-Brabant",
    "wof:name":"Luc Beine Of Toitures",
    "wof:placetype":"venue"
},
  "geometry": {"coordinates":[5.0767049789,50.7456169128],"type":"Point"}
}