{
  "type": "Feature",
  "properties": {
    "addr:full":"Dorpstraat 9ba Temse Oost-Vlaanderen 9140",
    "addr:housenumber":"9ba",
    "addr:postcode":"9140",
    "addr:street":"Dorpstraat",
    "iso:country":"BE",
    "sg:address":"Dorpstraat 9ba",
    "sg:city":"Temse",
    "sg:orig_category":"Boucheries",
    "sg:phone":"+32 52 46 24 46",
    "sg:postcode":"9140",
    "sg:province":"Oost-Vlaanderen",
    "wof:name":"Rudi Dierick",
    "wof:placetype":"venue"
},
  "geometry": {"coordinates":[4.1339921951,51.1142692566],"type":"Point"}
}