{
  "type": "Feature",
  "properties": {
    "iso:country":"BE",
    "sg:address":"Place Du Sablon 14",
    "sg:city":"Gembloux-sur-orneau (gembloux)",
    "sg:classifiers":[
        {
            "category":"Bakery",
            "type":"Food & Drink"
        }
    ],
    "sg:phone":"+32 81 61 15 91",
    "sg:postcode":"5030",
    "sg:province":"Namur",
    "sg:tags":[
        "confectioner",
        "baker"
    ],
    "wof:name":"Noel M",
    "wof:placetype":"venue"
},
  "geometry": {"coordinates":[4.7253890038,50.5816802979],"type":"Point"}
}