{
  "type": "Feature",
  "properties": {
    "iso:country":"BE",
    "sg:address":"Rue Du Commerce 122",
    "sg:city":"Brussel/bruxelles",
    "sg:classifiers":[
        {
            "category":"Insurance",
            "subcategory":"Life Insurance",
            "type":"Services"
        }
    ],
    "sg:phone":"+32 2 289 48 00",
    "sg:postcode":"1000",
    "sg:province":"Bruxelles-Capitale",
    "sg:tags":[
        "compagnies",
        "habitation",
        "assurance",
        "vie"
    ],
    "wof:name":"Hermes",
    "wof:placetype":"venue"
},
  "geometry": {"coordinates":[4.3700671196,50.84557724],"type":"Point"}
}