{
  "type": "Feature",
  "properties": {
    "iso:country":"BE",
    "sg:address":"Moorseelsesteenweg 77",
    "sg:city":"Roeselare (rumbeke)",
    "sg:classifiers":[
        {
            "category":"Farming",
            "subcategory":"Farm & Veterinary Services",
            "type":"Manufacturing & Wholesale Goods"
        }
    ],
    "sg:phone":"+32 51 24 50 39",
    "sg:postcode":"8800",
    "sg:province":"West-Vlaanderen",
    "sg:tags":[
        "agricultural",
        "contractor"
    ],
    "wof:name":"Vandemoortele-sioen R",
    "wof:placetype":"venue"
},
  "geometry": {"coordinates":[3.1395800114,50.9236412048],"type":"Point"}
}