{
  "type": "Feature",
  "properties": {
    "addr:full":"Alsembergse Steenweg 882 Ukkel/uccle Bruxelles-Capitale 1180",
    "addr:housenumber":"882",
    "addr:postcode":"1180",
    "addr:street":"Alsembergse Steenweg;/",
    "iso:country":"BE",
    "sg:address":"Alsembergse Steenweg 882",
    "sg:city":"Ukkel/uccle",
    "sg:orig_category":"Voertuigen",
    "sg:phone":"+32 2 332 10 19",
    "sg:postcode":"1180",
    "sg:province":"Bruxelles-Capitale",
    "wof:name":"Car Connection",
    "wof:placetype":"venue"
},
  "geometry": {"coordinates":[4.3354029655,50.7955551147],"type":"Point"}
}