{
  "type": "Feature",
  "properties": {
    "iso:country":"BE",
    "sg:address":"Heistraat 145",
    "sg:city":"Sint-niklaas",
    "sg:classifiers":[
        {
            "category":"Health Services",
            "subcategory":"Health Practitioner",
            "type":"Services"
        }
    ],
    "sg:phone":"+32 3 766 10 91",
    "sg:postcode":"9100",
    "sg:province":"Oost-Vlaanderen",
    "sg:tags":[
        "physiotherapist"
    ],
    "wof:name":"De Boom Karin",
    "wof:placetype":"venue"
},
  "geometry": {"coordinates":[4.1309280396,51.1743507385],"type":"Point"}
}