{
  "type": "Feature",
  "properties": {
    "iso:country":"BE",
    "sg:address":"Zoning Industriel - Bastogne 1",
    "sg:city":"Bastogne",
    "sg:orig_category":"Miscellaneous Products",
    "sg:phone":"+32 61 24 06 70",
    "sg:postcode":"6600",
    "sg:province":"Luxembourg",
    "wof:name":"Serviplast Asbl",
    "wof:placetype":"venue"
},
  "geometry": {"coordinates":[5.7220602036,50.004524231],"type":"Point"}
}