{
  "type": "Feature",
  "properties": {
    "addr:full":"Vierkeerstraat 79 Zwevegem (heestert) West-Vlaanderen 8551",
    "addr:housenumber":"79",
    "addr:postcode":"8551",
    "addr:street":"Vierkeerstraat",
    "iso:country":"BE",
    "sg:address":"Vierkeerstraat 79",
    "sg:city":"Zwevegem (heestert)",
    "sg:classifiers":[
        {
            "category":"Retail",
            "subcategory":"Auto Rental",
            "type":"Services"
        }
    ],
    "sg:phone":"+32 56 64 77 21",
    "sg:postcode":"8551",
    "sg:province":"West-Vlaanderen",
    "sg:tags":[
        "van",
        "hire",
        "-",
        "truck"
    ],
    "wof:name":"Vuylsteke Verhuur",
    "wof:placetype":"venue"
},
  "geometry": {"coordinates":[3.4109840393,50.782283783],"type":"Point"}
}