{
  "type": "Feature",
  "properties": {
    "iso:country":"BE",
    "sg:address":"Minderbroedersgang 5",
    "sg:city":"Mechelen",
    "sg:classifiers":[
        {
            "category":"Organizations",
            "subcategory":"Community Association",
            "type":"Services"
        }
    ],
    "sg:phone":"+32 15 29 40 00",
    "sg:postcode":"2800",
    "sg:province":"Antwerpen",
    "sg:tags":[
        "cultural"
    ],
    "wof:name":"Cultuur Centrum Mechelen",
    "wof:placetype":"venue"
},
  "geometry": {"coordinates":[4.4767231941,51.0289154053],"type":"Point"}
}