{
  "type": "Feature",
  "properties": {
    "iso:country":"BE",
    "sg:address":"Rue Brigade Piron 307",
    "sg:city":"Charleroi (montignies-sur-sambre)",
    "sg:classifiers":[
        {
            "category":"Retail",
            "subcategory":"Auto Repair",
            "type":"Services"
        }
    ],
    "sg:phone":"+32 71 31 68 21",
    "sg:postcode":"6061",
    "sg:province":"Hainaut",
    "sg:tags":[
        "garage"
    ],
    "wof:name":"Bila (garage)",
    "wof:placetype":"venue"
},
  "geometry": {"coordinates":[4.4559698105,50.4076347351],"type":"Point"}
}