{
  "type": "Feature",
  "properties": {
    "addr:full":"Stationsstraat 110 Oostrozebeke West-Vlaanderen 8780",
    "addr:housenumber":"110",
    "addr:postcode":"8780",
    "addr:street":"Stationsstraat",
    "iso:country":"BE",
    "sg:address":"Stationsstraat 110",
    "sg:city":"Oostrozebeke",
    "sg:classifiers":[
        {
            "category":"Insurance",
            "subcategory":"Life Insurance",
            "type":"Services"
        }
    ],
    "sg:phone":"+32 56 66 56 62",
    "sg:postcode":"8780",
    "sg:province":"West-Vlaanderen",
    "sg:tags":[
        "assurance"
    ],
    "wof:name":"Bureau Bonte-belaen",
    "wof:placetype":"venue"
},
  "geometry": {"coordinates":[3.3320860863,50.9152526855],"type":"Point"}
}