{
  "type": "Feature",
  "properties": {
    "addr:full":"St-severinusstraat 2a Roeselare West-Vlaanderen 8800",
    "addr:housenumber":"2a",
    "addr:postcode":"8800",
    "addr:street":"St-Severinusstraat",
    "iso:country":"BE",
    "sg:address":"St-severinusstraat 2a",
    "sg:city":"Roeselare",
    "sg:orig_category":"Meubles Fab",
    "sg:phone":"+32 56 50 95 06",
    "sg:postcode":"8800",
    "sg:province":"West-Vlaanderen",
    "wof:name":"Herman - Meeuws",
    "wof:placetype":"venue"
},
  "geometry": {"coordinates":[3.1133599281,50.8929290771],"type":"Point"}
}