{
  "type": "Feature",
  "properties": {
    "iso:country":"BE",
    "sg:address":"Boulevard Henri Rolin 5",
    "sg:city":"Waterloo",
    "sg:classifiers":[
        {
            "category":"Education",
            "subcategory":"Special Training",
            "type":"Public Place"
        }
    ],
    "sg:phone":"+32 2 353 22 53",
    "sg:postcode":"1410",
    "sg:province":"Brabant Wallon",
    "sg:tags":[
        "-",
        "processing",
        "data"
    ],
    "wof:name":"Quicksoft",
    "wof:placetype":"venue"
},
  "geometry": {"coordinates":[4.3998417854,50.7115440369],"type":"Point"}
}