{
  "type": "Feature",
  "properties": {
    "iso:country":"BE",
    "sg:address":"Handboogstraat 14",
    "sg:city":"Kuurne",
    "sg:orig_category":"Rev\u00eatements de sols and murs",
    "sg:phone":"+32 56 35 52 72",
    "sg:postcode":"8520",
    "sg:province":"West-Vlaanderen",
    "wof:name":"Carlo Deknock",
    "wof:placetype":"venue"
},
  "geometry": {"coordinates":[3.2679669857,50.8487548828],"type":"Point"}
}