{
  "type": "Feature",
  "properties": {
    "iso:country":"BE",
    "sg:address":"Turnhoutsebaan 5",
    "sg:city":"Wijnegem",
    "sg:orig_category":"Baby- and kinderkleding Dameskledingzaken Herenkledingzaken",
    "sg:phone":"+32 3 355 34 60",
    "sg:postcode":"2110",
    "sg:province":"Antwerpen",
    "wof:name":"Peek & Cloppenburg ( P&c)",
    "wof:placetype":"venue"
},
  "geometry": {"coordinates":[4.5043401718,51.2240219116],"type":"Point"}
}