{
  "type": "Feature",
  "properties": {
    "iso:country":"BE",
    "sg:address":"Rue Du Rivage 35",
    "sg:city":"Sambreville (moignel\u00e9e)",
    "sg:classifiers":[
        {
            "category":"Landmark",
            "subcategory":"Memorial",
            "type":"Public Place"
        }
    ],
    "sg:phone":"+32 71 74 08 81",
    "sg:postcode":"5060",
    "sg:province":"Namur",
    "sg:tags":[
        "-",
        "monument"
    ],
    "wof:name":"Sobra",
    "wof:placetype":"venue"
},
  "geometry": {"coordinates":[4.5866928101,50.4351501465],"type":"Point"}
}