{
  "type": "Feature",
  "properties": {
    "iso:country":"BE",
    "sg:address":"Rue Grande 42",
    "sg:city":"Gedinne (vencimont)",
    "sg:classifiers":[
        {
            "category":"Food & Beverages",
            "subcategory":"Groceries & Convenience Stores",
            "type":"Retail Goods"
        }
    ],
    "sg:phone":"+32 61 58 80 81",
    "sg:postcode":"5575",
    "sg:province":"Namur",
    "sg:tags":[
        "grocer"
    ],
    "wof:name":"Uma",
    "wof:placetype":"venue"
},
  "geometry": {"coordinates":[4.9227848053,50.0326652527],"type":"Point"}
}