{
  "type": "Feature",
  "properties": {
    "iso:country":"BE",
    "sg:address":"Avenue Jean Et Pierre Carsoel 2",
    "sg:city":"Bruxelles (uccle)",
    "sg:orig_category":"Non-Classified Establishments",
    "sg:phone":"+32 2 374 72 79",
    "sg:postcode":"1180",
    "sg:province":"Bruxelles-Capitale",
    "wof:name":"Centre Pms Libre-uccle",
    "wof:placetype":"venue"
},
  "geometry": {"coordinates":[4.3645091057,50.7943458557],"type":"Point"}
}