{
  "type": "Feature",
  "properties": {
    "addr:full":"Boulevard Brand Whitlock 85 Bruxelles (woluwe-saint-lambert) Bruxelles-Capitale 1200",
    "addr:housenumber":"85",
    "addr:postcode":"1200",
    "addr:street":"Boulevard Brand Whitlock",
    "iso:country":"BE",
    "sg:address":"Boulevard Brand Whitlock 85",
    "sg:city":"Bruxelles (woluwe-saint-lambert)",
    "sg:classifiers":[
        {
            "category":"Shopping",
            "subcategory":"Clothing, Apparel, & Fashions",
            "type":"Retail Goods"
        }
    ],
    "sg:phone":"+32 2 732 85 52",
    "sg:postcode":"1200",
    "sg:province":"Bruxelles-Capitale",
    "sg:tags":[
        "shawl"
    ],
    "wof:name":"Texseta Sa",
    "wof:placetype":"venue"
},
  "geometry": {"coordinates":[4.4062790871,50.8416175842],"type":"Point"}
}