{
  "type": "Feature",
  "properties": {
    "addr:full":"Groteweg 27 Geraardsbergen Oost-Vlaanderen 9500",
    "addr:housenumber":"27",
    "addr:postcode":"9500",
    "addr:street":"Groteweg",
    "iso:country":"BE",
    "sg:address":"Groteweg 27",
    "sg:city":"Geraardsbergen",
    "sg:orig_category":"Maisons de repos and r\u00e9sidences",
    "sg:phone":"+32 54 43 30 61",
    "sg:postcode":"9500",
    "sg:province":"Oost-Vlaanderen",
    "wof:name":"Rusthuis De Maretak",
    "wof:placetype":"venue"
},
  "geometry": {"coordinates":[3.8707270622,50.7675209045],"type":"Point"}
}