{
  "type": "Feature",
  "properties": {
    "iso:country":"BE",
    "sg:address":"Jozef Ii Straat 29b33",
    "sg:city":"Oostende",
    "sg:classifiers":[
        {
            "category":"Cafe",
            "type":"Food & Drink"
        }
    ],
    "sg:phone":"+32 59 80 48 65",
    "sg:postcode":"8400",
    "sg:province":"West-Vlaanderen",
    "sg:tags":[
        "caf\u00e9s"
    ],
    "wof:name":"Robert Daele",
    "wof:placetype":"venue"
},
  "geometry": {"coordinates":[2.9194350243,51.2288589478],"type":"Point"}
}