{
  "type": "Feature",
  "properties": {
    "iso:country":"BE",
    "sg:address":"Rue Royale 236",
    "sg:city":"Sint-joost-ten-node/saint-josse-ten-noode",
    "sg:orig_category":"Jardins botaniques, zoologiques, observatoires and r\u00e9serves naturelles. Restaurants",
    "sg:phone":"+32 2 218 83 49",
    "sg:postcode":"1210",
    "sg:province":"Bruxelles-Capitale",
    "wof:name":"Le Jardin Du Botanique",
    "wof:placetype":"venue"
},
  "geometry": {"coordinates":[4.3660731316,50.8543128967],"type":"Point"}
}