{
  "type": "Feature",
  "properties": {
    "iso:country":"BE",
    "sg:address":"Kerkstraat 21",
    "sg:city":"Herzele",
    "sg:orig_category":"Brood, gebak and snoepgoed",
    "sg:phone":"+32 53 62 71 16",
    "sg:postcode":"9550",
    "sg:province":"Oost-Vlaanderen",
    "wof:name":"Huis Symphony",
    "wof:placetype":"venue"
},
  "geometry": {"coordinates":[3.8917589188,50.886177063],"type":"Point"}
}