{
  "type": "Feature",
  "properties": {
    "iso:country":"BE",
    "sg:address":"Genieskensstraat 7",
    "sg:city":"Maasmechelen (leut)",
    "sg:classifiers":[
        {
            "category":"Home & Garden",
            "subcategory":"Carpets & Floor Coverings",
            "type":"Retail Goods"
        }
    ],
    "sg:phone":"+32 89 62 27 52",
    "sg:postcode":"3630",
    "sg:province":"Limburg",
    "sg:tags":[
        "armoring"
    ],
    "wof:name":"L'arte Posata Bvba",
    "wof:placetype":"venue"
},
  "geometry": {"coordinates":[5.6961350441,50.963848114],"type":"Point"}
}