{
  "type": "Feature",
  "properties": {
    "addr:full":"Rue Des Sk\u00e2ssis 11 Houyet (wanlin) Namur 5564",
    "addr:housenumber":"11",
    "addr:postcode":"5564",
    "addr:street":"Rue Des Ska\u0302Ssis",
    "iso:country":"BE",
    "sg:address":"Rue Des Sk\u00e2ssis 11",
    "sg:city":"Houyet (wanlin)",
    "sg:classifiers":[
        {
            "category":"Recreation",
            "subcategory":"Campground",
            "type":"Entertainment"
        }
    ],
    "sg:phone":"+32 82 66 66 70",
    "sg:postcode":"5564",
    "sg:province":"Namur",
    "sg:tags":[
        "site",
        "camping"
    ],
    "wof:name":"De-wanlin (camping Le)",
    "wof:placetype":"venue"
},
  "geometry": {"coordinates":[5.0614261627,50.1595497131],"type":"Point"}
}