{
  "type": "Feature",
  "properties": {
    "addr:full":"Rue De La Terre Franche 77 Eghezee Namur 5310",
    "addr:housenumber":"77",
    "addr:postcode":"5310",
    "addr:street":"Rue De La Terre Franche;Namur",
    "iso:country":"BE",
    "sg:address":"Rue De La Terre Franche 77",
    "sg:city":"Eghezee",
    "sg:orig_category":"Artistes ind\u00e9pendants",
    "sg:phone":"+32 81 51 16 50",
    "sg:postcode":"5310",
    "sg:province":"Namur",
    "wof:name":"Edouard Bruyere",
    "wof:placetype":"venue"
},
  "geometry": {"coordinates":[4.9018287659,50.5687637329],"type":"Point"}
}