{
  "type": "Feature",
  "properties": {
    "addr:full":"Korenstraat 3 Harelbeke West-Vlaanderen 8531",
    "addr:housenumber":"3",
    "addr:postcode":"8531",
    "addr:street":"Korenstraat",
    "iso:country":"BE",
    "sg:address":"Korenstraat 3",
    "sg:city":"Harelbeke",
    "sg:orig_category":"Installation \u00e9lectrique r\u00e9sidentielle",
    "sg:phone":"+32 56 71 01 68",
    "sg:postcode":"8531",
    "sg:province":"West-Vlaanderen",
    "wof:name":"Callewaert",
    "wof:placetype":"venue"
},
  "geometry": {"coordinates":[3.3162209988,50.8823471069],"type":"Point"}
}