{
  "type": "Feature",
  "properties": {
    "iso:country":"BE",
    "sg:address":"Boskantstraat 8",
    "sg:city":"Neerpelt",
    "sg:orig_category":"Boekhouders",
    "sg:phone":"+32 11 64 56 42",
    "sg:postcode":"3910",
    "sg:province":"Limburg",
    "wof:name":"Lisette Oyen",
    "wof:placetype":"venue"
},
  "geometry": {"coordinates":[5.4430060387,51.2231674194],"type":"Point"}
}