{
  "type": "Feature",
  "properties": {
    "addr:full":"Rue Salomon Deloye 1ba5 Seraing Li\u00e8ge 4102",
    "addr:postcode":"4102",
    "addr:street":"Rue Salomon Deloye 1Ba5",
    "iso:country":"BE",
    "sg:address":"Rue Salomon Deloye 1ba5",
    "sg:city":"Seraing",
    "sg:orig_category":"M\u00e9decins and sp\u00e9cialistes",
    "sg:phone":"+32 4 337 95 99",
    "sg:postcode":"4102",
    "sg:province":"Li\u00e8ge",
    "wof:name":"Fernand Geubelle",
    "wof:placetype":"venue"
},
  "geometry": {"coordinates":[5.5503001213,50.5811080933],"type":"Point"}
}