{
  "type": "Feature",
  "properties": {
    "addr:full":"Ter Moude 11 Zwevegem 8552",
    "addr:housenumber":"11",
    "addr:postcode":"8552",
    "addr:street":"Zwevegem",
    "iso:country":"BE",
    "sg:address":"Ter Moude 11",
    "sg:city":"Zwevegem",
    "sg:orig_category":"Boucheries",
    "sg:phone":"+32 56 64 44 70",
    "sg:postcode":"8552",
    "wof:name":"Andre Allegaert",
    "wof:placetype":"venue"
},
  "geometry": {"coordinates":[3.3976860046,50.7679252625],"type":"Point"}
}