{
  "type": "Feature",
  "properties": {
    "addr:full":"Rue Du Coll\u00c8ge 17b5 Yvoir Namur 5530",
    "addr:housenumber":"17b5",
    "addr:postcode":"5530",
    "addr:street":"Rue Du Colle\u0300Ge",
    "iso:country":"BE",
    "sg:address":"Rue Du Coll\u00c8ge 17b5",
    "sg:city":"Yvoir",
    "sg:classifiers":[
        {
            "category":"Arena",
            "subcategory":"Sports Club",
            "type":"Entertainment"
        }
    ],
    "sg:phone":"+32 82 61 12 01",
    "sg:postcode":"5530",
    "sg:province":"Namur",
    "sg:tags":[
        "terrain",
        "hors",
        "de",
        "installation",
        "sportifs"
    ],
    "wof:name":"R.c.s. Ent. Mosane",
    "wof:placetype":"venue"
},
  "geometry": {"coordinates":[4.8660311699,50.3468360901],"type":"Point"}
}