{
  "type": "Feature",
  "properties": {
    "iso:country":"BE",
    "sg:address":"Bruggestraat 131",
    "sg:city":"Torhout",
    "sg:orig_category":"Fournitures de bureau",
    "sg:phone":"+32 50 22 11 66",
    "sg:postcode":"8820",
    "sg:province":"West-Vlaanderen",
    "wof:name":"Acima",
    "wof:placetype":"venue"
},
  "geometry": {"coordinates":[3.1127800941,51.0782928467],"type":"Point"}
}