{
  "type": "Feature",
  "properties": {
    "addr:full":"Schachteweidestraat 41 Ieper West-Vlaanderen 8902",
    "addr:housenumber":"41",
    "addr:postcode":"8902",
    "addr:street":"Schachteweidestraat",
    "iso:country":"BE",
    "sg:address":"Schachteweidestraat 41",
    "sg:city":"Ieper",
    "sg:orig_category":"Eleveurs de bovins",
    "sg:phone":"+32 57 20 08 24",
    "sg:postcode":"8902",
    "sg:province":"West-Vlaanderen",
    "wof:name":"Gabriel Deknudt",
    "wof:placetype":"venue"
},
  "geometry": {"coordinates":[2.9315838814,50.8402481079],"type":"Point"}
}