{
  "type": "Feature",
  "properties": {
    "addr:full":"Muizenstraat 4ba Zonhoven Limburg 3520",
    "addr:housenumber":"4ba",
    "addr:postcode":"3520",
    "addr:street":"Muizenstraat",
    "iso:country":"BE",
    "sg:address":"Muizenstraat 4ba",
    "sg:city":"Zonhoven",
    "sg:orig_category":"Plomberie, chauffage and installations sanitaires",
    "sg:phone":"+32 11 81 69 28",
    "sg:postcode":"3520",
    "sg:province":"Limburg",
    "wof:name":"Georges Vandevoort",
    "wof:placetype":"venue"
},
  "geometry": {"coordinates":[5.3845291138,50.9898719788],"type":"Point"}
}