{
  "type": "Feature",
  "properties": {
    "iso:country":"BE",
    "sg:address":"Rue De Charneux 32",
    "sg:city":"Herve",
    "sg:orig_category":"Non-Classified Establishments",
    "sg:phone":"+32 87 69 35 50",
    "sg:postcode":"4650",
    "sg:province":"Li\u00e8ge",
    "wof:name":"Herve Soci\u00e9t\u00e9 Sa",
    "wof:placetype":"venue"
},
  "geometry": {"coordinates":[5.7963619232,50.6462173462],"type":"Point"}
}