{
  "type": "Feature",
  "properties": {
    "addr:full":"Kerselarestraat 7 Kortessem Limburg 3720",
    "addr:housenumber":"7",
    "addr:postcode":"3720",
    "addr:street":"Kerselarestraat",
    "iso:country":"BE",
    "sg:address":"Kerselarestraat 7",
    "sg:city":"Kortessem",
    "sg:classifiers":[
        {
            "category":"Insurance",
            "subcategory":"Life Insurance",
            "type":"Services"
        }
    ],
    "sg:phone":"+32 11 37 69 51",
    "sg:postcode":"3720",
    "sg:province":"Limburg",
    "sg:tags":[
        "assurance"
    ],
    "wof:name":"Vandenreyt",
    "wof:placetype":"venue"
},
  "geometry": {"coordinates":[5.3807229996,50.8641204834],"type":"Point"}
}