{
  "type": "Feature",
  "properties": {
    "iso:country":"BE",
    "sg:address":"Rue De Mons 2",
    "sg:city":"Nivelles",
    "sg:orig_category":"Journaux. Tabac",
    "sg:phone":"+32 67 21 77 36",
    "sg:postcode":"1400",
    "sg:province":"Brabant Wallon",
    "wof:name":"Librairie Du Centre",
    "wof:placetype":"venue"
},
  "geometry": {"coordinates":[4.3140501976,50.5902481079],"type":"Point"}
}