{
  "type": "Feature",
  "properties": {
    "iso:country":"BE",
    "sg:address":"Krogstraat 21",
    "sg:city":"Meise",
    "sg:orig_category":"Oldtimers",
    "sg:phone":"+32 2 269 21 03",
    "sg:postcode":"1860",
    "sg:province":"Vlaams-Brabant",
    "wof:name":"Rs-classics",
    "wof:placetype":"venue"
},
  "geometry": {"coordinates":[4.3256120682,50.9343109131],"type":"Point"}
}