{
  "type": "Feature",
  "properties": {
    "iso:country":"BE",
    "sg:address":"Borgtstraat 55",
    "sg:city":"Laakdal (forest)",
    "sg:classifiers":[
        {
            "category":"Bars & Pubs",
            "type":"Food & Drink"
        }
    ],
    "sg:phone":"+32 13 67 22 00",
    "sg:postcode":"2430",
    "sg:province":"Antwerpen",
    "wof:name":"Sportkring",
    "wof:placetype":"venue"
},
  "geometry": {"coordinates":[5.0331301689,51.0802307129],"type":"Point"}
}