{
  "type": "Feature",
  "properties": {
    "addr:full":"Diestersesteenweg 41 Bus 1 Hasselt Limburg 3510",
    "addr:housenumber":"41 bus 1",
    "addr:postcode":"3510",
    "addr:street":"Diestersesteenweg",
    "iso:country":"BE",
    "sg:address":"Diestersesteenweg 41 Bus 1",
    "sg:city":"Hasselt",
    "sg:orig_category":"E-activit\u00e9s. Conseils en syst\u00e8mes informatiques. Secr\u00e9tariats. Entretien and r\u00e9parations de machines",
    "sg:phone":"+32 11 87 22 33",
    "sg:postcode":"3510",
    "sg:province":"Limburg",
    "wof:name":"Insight G & Cc Bvba",
    "wof:placetype":"venue"
},
  "geometry": {"coordinates":[5.2531552315,50.9474906921],"type":"Point"}
}