{
  "type": "Feature",
  "properties": {
    "addr:full":"Rue De Bertransart Gerpinnes Hainaut 6280",
    "addr:postcode":"6280",
    "addr:street":"Rue De Bertransart;Hainaut",
    "iso:country":"BE",
    "sg:address":"Rue De Bertransart",
    "sg:city":"Gerpinnes",
    "sg:classifiers":[
        {
            "category":"Home & Garden",
            "subcategory":"Building Materials",
            "type":"Retail Goods"
        }
    ],
    "sg:phone":"+32 71 22 82 45",
    "sg:postcode":"6280",
    "sg:province":"Hainaut",
    "sg:tags":[
        "article",
        "-",
        "do-it-yourself"
    ],
    "wof:name":"Brico Sys",
    "wof:placetype":"venue"
},
  "geometry": {"coordinates":[4.4810099602,50.3322601318],"type":"Point"}
}