{
  "type": "Feature",
  "properties": {
    "addr:full":"Boulevard De La Sauveni\u00e8re 34-1 Li\u00e8ge 1 Li\u00e8ge 4000",
    "addr:housenumber":"34-1;1",
    "addr:postcode":"4000",
    "addr:street":"Boulevard De La Sauvenie\u0300Re",
    "iso:country":"BE",
    "sg:address":"Boulevard De La Sauveni\u00e8re 34-1",
    "sg:city":"Li\u00e8ge 1",
    "sg:classifiers":[
        {
            "category":"Professional",
            "subcategory":"Employment Agencies",
            "type":"Services"
        }
    ],
    "sg:phone":"+32 4 222 30 20",
    "sg:postcode":"4000",
    "sg:province":"Li\u00e8ge",
    "sg:tags":[
        "temping",
        "-",
        "manual"
    ],
    "wof:name":"Ads Interim Sa",
    "wof:placetype":"venue"
},
  "geometry": {"coordinates":[5.5683660507,50.6443519592],"type":"Point"}
}