{
  "type": "Feature",
  "properties": {
    "addr:full":"Fr Rooseveltpl 26 Ronse Oost-Vlaanderen 9600",
    "addr:housenumber":"26",
    "addr:postcode":"9600",
    "iso:country":"BE",
    "sg:address":"Fr Rooseveltpl 26",
    "sg:city":"Ronse",
    "sg:classifiers":[
        {
            "category":"Banks & Credit Unions",
            "subcategory":"Bank",
            "type":"Services"
        }
    ],
    "sg:phone":"+32 55 21 52 42",
    "sg:postcode":"9600",
    "sg:province":"Oost-Vlaanderen",
    "wof:name":"Gemeentekrediet",
    "wof:placetype":"venue"
},
  "geometry": {"coordinates":[3.5998399258,50.7464981079],"type":"Point"}
}