{
  "type": "Feature",
  "properties": {
    "iso:country":"BE",
    "sg:address":"Jeu De Balle 8",
    "sg:city":"Leuze-en-hainaut",
    "sg:classifiers":[
        {
            "category":"Cafe",
            "type":"Food & Drink"
        }
    ],
    "sg:phone":"+32 69 66 22 69",
    "sg:postcode":"7900",
    "sg:province":"Hainaut",
    "sg:tags":[
        "caf\u00e9s"
    ],
    "wof:name":"Caf\u00c9 Balle D'argent",
    "wof:placetype":"venue"
},
  "geometry": {"coordinates":[3.6170809269,50.5977363586],"type":"Point"}
}