{
  "type": "Feature",
  "properties": {
    "addr:full":"Cadixstraat 49 Antwerpen Antwerpen 2000",
    "addr:housenumber":"49",
    "addr:postcode":"2000",
    "addr:street":"Cadixstraat",
    "iso:country":"BE",
    "sg:address":"Cadixstraat 49",
    "sg:city":"Antwerpen",
    "sg:orig_category":"Agences d'exp\u00e9dition",
    "sg:phone":"+32 3 234 28 80",
    "sg:postcode":"2000",
    "sg:province":"Antwerpen",
    "wof:name":"I.l.s.",
    "wof:placetype":"venue"
},
  "geometry": {"coordinates":[4.4125351906,51.2335357666],"type":"Point"}
}