{
  "type": "Feature",
  "properties": {
    "addr:full":"Koninklijke Baan 160 Koksijde West-Vlaanderen 8670",
    "addr:housenumber":"160",
    "addr:postcode":"8670",
    "addr:street":"Koninklijke Baan",
    "iso:country":"BE",
    "sg:address":"Koninklijke Baan 160",
    "sg:city":"Koksijde",
    "sg:orig_category":"Pain, p\u00e2tisseries and confiseries",
    "sg:phone":"+32 58 51 92 02",
    "sg:postcode":"8670",
    "sg:province":"West-Vlaanderen",
    "wof:name":"Huis Maryline",
    "wof:placetype":"venue"
},
  "geometry": {"coordinates":[2.6331729889,51.1200218201],"type":"Point"}
}