{
  "type": "Feature",
  "properties": {
    "addr:full":"Kuilenstraat 7 Hasselt Limburg 3500",
    "addr:housenumber":"7",
    "addr:postcode":"3500",
    "addr:street":"Kuilenstraat",
    "iso:country":"BE",
    "sg:address":"Kuilenstraat 7",
    "sg:city":"Hasselt",
    "sg:orig_category":"Installation \u00e9lectrique r\u00e9sidentielle",
    "sg:phone":"+32 11 22 28 10",
    "sg:postcode":"3500",
    "sg:province":"Limburg",
    "wof:name":"Andre Maris",
    "wof:placetype":"venue"
},
  "geometry": {"coordinates":[5.3710727692,50.9446678162],"type":"Point"}
}