{
  "type": "Feature",
  "properties": {
    "iso:country":"BE",
    "sg:address":"Prolstraat 12",
    "sg:city":"Ronse/renaix",
    "sg:orig_category":"Artsen and specialisten",
    "sg:phone":"+32 55 21 14 90",
    "sg:postcode":"9600",
    "sg:province":"Oost-Vlaanderen",
    "wof:name":"Bruno De Meyere",
    "wof:placetype":"venue"
},
  "geometry": {"coordinates":[3.6368939877,50.7613830566],"type":"Point"}
}