{
  "type": "Feature",
  "properties": {
    "addr:full":"Krijgsbaan 27 Wijnegem Antwerpen 2110",
    "addr:housenumber":"27",
    "addr:postcode":"2110",
    "addr:street":"Krijgsbaan",
    "iso:country":"BE",
    "sg:address":"Krijgsbaan 27",
    "sg:city":"Wijnegem",
    "sg:classifiers":[
        {
            "category":"Manufacturing",
            "subcategory":"Textiles",
            "type":"Manufacturing & Wholesale Goods"
        }
    ],
    "sg:phone":"+32 3 353 91 05",
    "sg:postcode":"2110",
    "sg:province":"Antwerpen",
    "sg:tags":[
        "fab",
        "diverse",
        "textielproducten"
    ],
    "wof:name":"D'houwer",
    "wof:placetype":"venue"
},
  "geometry": {"coordinates":[4.4977588654,51.2203521729],"type":"Point"}
}