{
  "type": "Feature",
  "properties": {
    "iso:country":"BE",
    "sg:address":"Rue Du Halage 39b",
    "sg:city":"Aywaille",
    "sg:orig_category":"D\u00e9molition d\u00b4immeubles and terrassements. Construction de rev\u00eatements routiers and sportifs",
    "sg:phone":"+32 4 384 43 28",
    "sg:postcode":"4920",
    "sg:province":"Li\u00e8ge",
    "wof:name":"Hallet-remacle",
    "wof:placetype":"venue"
},
  "geometry": {"coordinates":[5.6897230148,50.4790611267],"type":"Point"}
}