{
  "type": "Feature",
  "properties": {
    "addr:full":"Chauss\u00e9e De Wavre 553 Grez-doiceau Brabant Wallon 1390",
    "addr:housenumber":"553",
    "addr:postcode":"1390",
    "addr:street":"Chausse\u0301E De Wavre",
    "iso:country":"BE",
    "sg:address":"Chauss\u00e9e De Wavre 553",
    "sg:city":"Grez-doiceau",
    "sg:classifiers":[
        {
            "category":"Transit Center",
            "subcategory":"Passenger",
            "type":"Transportation"
        }
    ],
    "sg:phone":"+32 16 47 15 36",
    "sg:postcode":"1390",
    "sg:province":"Brabant Wallon",
    "sg:tags":[
        "sand",
        "gravel"
    ],
    "wof:name":"Belmeco",
    "wof:placetype":"venue"
},
  "geometry": {"coordinates":[4.6452999115,50.7299613953],"type":"Point"}
}