{
  "type": "Feature",
  "properties": {
    "addr:full":"Chauss\u00c9e De Louvain 249 Eghez\u00c9e Namur 5310",
    "addr:housenumber":"249",
    "addr:postcode":"5310",
    "addr:street":"Chausse\u0301E De Louvain",
    "iso:country":"BE",
    "sg:address":"Chauss\u00c9e De Louvain 249",
    "sg:city":"Eghez\u00c9e",
    "sg:orig_category":"D\u00e9taillants en pi\u00e8ces and accessoires de voitures",
    "sg:phone":"+32 81 81 12 39",
    "sg:postcode":"5310",
    "sg:province":"Namur",
    "wof:name":"Soregi",
    "wof:placetype":"venue"
},
  "geometry": {"coordinates":[4.9012298584,50.6018600464],"type":"Point"}
}