{
  "type": "Feature",
  "properties": {
    "addr:full":"Ind Terr De Arend 13 Zedelgem West-Vlaanderen 8210",
    "addr:housenumber":"13",
    "addr:postcode":"8210",
    "addr:street":"Terr De Arend",
    "iso:country":"BE",
    "sg:address":"Ind Terr De Arend 13",
    "sg:city":"Zedelgem",
    "sg:classifiers":[
        {
            "category":"Professional",
            "type":"Services"
        }
    ],
    "sg:phone":"+32 50 25 03 10",
    "sg:postcode":"8210",
    "sg:province":"West-Vlaanderen",
    "sg:tags":[
        "transport",
        "road"
    ],
    "wof:name":"Decanar Nv",
    "wof:placetype":"venue"
},
  "geometry": {"coordinates":[3.1458399296,51.1376457214],"type":"Point"}
}