{
  "type": "Feature",
  "properties": {
    "addr:full":"Baaikensstraat 17 Zele Oost-Vlaanderen 9240",
    "addr:housenumber":"17",
    "addr:postcode":"9240",
    "addr:street":"Baaikensstraat",
    "iso:country":"BE",
    "sg:address":"Baaikensstraat 17",
    "sg:city":"Zele",
    "sg:orig_category":"Tankcleaning",
    "sg:phone":"+32 52 44 86 94",
    "sg:postcode":"9240",
    "sg:province":"Oost-Vlaanderen",
    "wof:name":"Romarco Nv",
    "wof:placetype":"venue"
},
  "geometry": {"coordinates":[4.05479002,51.0787811279],"type":"Point"}
}