{
  "type": "Feature",
  "properties": {
    "addr:full":"Rue Isabelle-brunelle 13 Fernelmont Namur 5380",
    "addr:housenumber":"13",
    "addr:postcode":"5380",
    "addr:street":"Rue Isabelle-Brunelle",
    "iso:country":"BE",
    "sg:address":"Rue Isabelle-brunelle 13",
    "sg:city":"Fernelmont",
    "sg:orig_category":"Production de films, t\u00e9l\u00e9films and vid\u00e9os",
    "sg:phone":"+32 81 83 56 18",
    "sg:postcode":"5380",
    "sg:province":"Namur",
    "wof:name":"Joseph Ferraro",
    "wof:placetype":"venue"
},
  "geometry": {"coordinates":[4.9747247696,50.5466537476],"type":"Point"}
}