{
  "type": "Feature",
  "properties": {
    "addr:full":"Avenue Marcel Thiry 208 Brussels Bruxelles-Capitale 1200",
    "addr:housenumber":"208",
    "addr:postcode":"1200",
    "addr:street":"Avenue Marcel Thiry",
    "iso:country":"BE",
    "sg:address":"Avenue Marcel Thiry 208",
    "sg:city":"Brussels",
    "sg:classifiers":[
        {
            "category":"Banks & Credit Unions",
            "subcategory":"Bank",
            "type":"Services"
        }
    ],
    "sg:phone":"+32 9 267 32 11",
    "sg:postcode":"1200",
    "sg:province":"Bruxelles-Capitale",
    "wof:name":"Vdk Spaarbank Nv/sa",
    "wof:placetype":"venue"
},
  "geometry": {"coordinates":[3.7187070847,51.0537643433],"type":"Point"}
}