{
  "type": "Feature",
  "properties": {
    "iso:country":"BE",
    "sg:address":"Brusselsestraat 53",
    "sg:city":"Dendermonde",
    "sg:orig_category":"Mobistar Centres Telecommunicatiesystemen",
    "sg:phone":"+32 52 25 60 81",
    "sg:postcode":"9200",
    "sg:province":"Oost-Vlaanderen",
    "wof:name":"Mobistar Center Pentacall",
    "wof:placetype":"venue"
},
  "geometry": {"coordinates":[4.0999531746,51.0272254944],"type":"Point"}
}