{
  "type": "Feature",
  "properties": {
    "addr:full":"Barnestraat 1bb Koekelare West-Vlaanderen 8680",
    "addr:postcode":"8680",
    "addr:street":"Barnestraat",
    "iso:country":"BE",
    "sg:address":"Barnestraat 1bb",
    "sg:city":"Koekelare",
    "sg:orig_category":"Herstellingen and onderhoud van auto's",
    "sg:phone":"+32 51 58 13 52",
    "sg:postcode":"8680",
    "sg:province":"West-Vlaanderen",
    "wof:name":"Garage Denoo",
    "wof:placetype":"venue"
},
  "geometry": {"coordinates":[2.9615259171,51.0943222046],"type":"Point"}
}