{
  "type": "Feature",
  "properties": {
    "addr:full":"Pieter Reypenslei 7 Mortsel Antwerpen 2640",
    "addr:housenumber":"7",
    "addr:postcode":"2640",
    "addr:street":"Pieter Reypenslei",
    "iso:country":"BE",
    "sg:address":"Pieter Reypenslei 7",
    "sg:city":"Mortsel",
    "sg:classifiers":[
        {
            "category":"Personal",
            "subcategory":"Beauty Salon",
            "type":"Services"
        }
    ],
    "sg:phone":"+32 3 440 62 04",
    "sg:postcode":"2640",
    "sg:province":"Antwerpen",
    "wof:name":"Fanny's Nail Care",
    "wof:placetype":"venue"
},
  "geometry": {"coordinates":[4.453605175,51.169960022],"type":"Point"}
}