{
  "type": "Feature",
  "properties": {
    "iso:country":"BE",
    "sg:address":"Duffelsesteenweg 82",
    "sg:city":"Sint-katelijne-waver",
    "sg:orig_category":"Groententeelt",
    "sg:phone":"+32 15 31 32 49",
    "sg:postcode":"2860",
    "sg:province":"Antwerpen",
    "wof:name":"Alfons Beullens",
    "wof:placetype":"venue"
},
  "geometry": {"coordinates":[4.5302538872,51.0766029358],"type":"Point"}
}