{
  "type": "Feature",
  "properties": {
    "addr:full":"Rue Des Tanneurs 41 Bruxelles Bruxelles-Capitale 1000",
    "addr:housenumber":"41",
    "addr:postcode":"1000",
    "addr:street":"Rue Des Tanneurs",
    "iso:country":"BE",
    "sg:address":"Rue Des Tanneurs 41",
    "sg:city":"Bruxelles",
    "sg:classifiers":[
        {
            "category":"Education",
            "subcategory":"School",
            "type":"Public Place"
        }
    ],
    "sg:phone":"+32 2 512 14 75",
    "sg:postcode":"1000",
    "sg:province":"Bruxelles-Capitale",
    "sg:tags":[
        "secondary"
    ],
    "wof:name":"Zaveldal School Voor Aangepast Beroepsonderwijs",
    "wof:placetype":"venue"
},
  "geometry": {"coordinates":[4.346487999,50.8404464722],"type":"Point"}
}