{
  "type": "Feature",
  "properties": {
    "addr:full":"Excelsiorlaan 10 (i.z.keiberg) Zaventem Vlaams-Brabant 1930",
    "addr:housenumber":"10",
    "addr:postcode":"1930",
    "addr:street":"Excelsiorlaan",
    "iso:country":"BE",
    "sg:address":"Excelsiorlaan 10 (i.z.keiberg)",
    "sg:city":"Zaventem",
    "sg:classifiers":[
        {
            "category":"Banks & Credit Unions",
            "subcategory":"Investment Brokerage",
            "type":"Services"
        }
    ],
    "sg:phone":"+32 2 720 96 70",
    "sg:postcode":"1930",
    "sg:province":"Vlaams-Brabant",
    "sg:tags":[
        "machine",
        "mat\u00e9riel",
        "de",
        "bureau",
        "gr"
    ],
    "wof:name":"Minolta Business Equipement",
    "wof:placetype":"venue"
},
  "geometry": {"coordinates":[4.458026886,50.8833656311],"type":"Point"}
}