{
  "type": "Feature",
  "properties": {
    "iso:country":"BE",
    "sg:address":"Rue Ren\u00e9 Magritte 163",
    "sg:city":"Lessines",
    "sg:classifiers":[
        {
            "category":"Shopping",
            "subcategory":"Pharmacy",
            "type":"Retail Goods"
        }
    ],
    "sg:phone":"+32 68 33 49 13",
    "sg:postcode":"7860",
    "sg:province":"Hainaut",
    "sg:tags":[
        "chemical",
        "pharmaceutical",
        "chemistry"
    ],
    "wof:name":"Benechim Sa",
    "wof:placetype":"venue"
},
  "geometry": {"coordinates":[3.8395719528,50.7201919556],"type":"Point"}
}