{
  "type": "Feature",
  "properties": {
    "addr:full":"Place De La R\u00c9sistance 1 Anderlecht Bruxelles-Capitale 1070",
    "addr:housenumber":"1",
    "addr:postcode":"1070",
    "addr:street":"Place De La Re\u0301Sistance",
    "iso:country":"BE",
    "sg:address":"Place De La R\u00c9sistance 1",
    "sg:city":"Anderlecht",
    "sg:orig_category":"Mat\u00e9riel m\u00e9dical and orthop\u00e9dique and proth\u00e8ses Fab",
    "sg:phone":"+32 2 521 31 09",
    "sg:postcode":"1070",
    "sg:province":"Bruxelles-Capitale",
    "wof:name":"Labo Loiselet",
    "wof:placetype":"venue"
},
  "geometry": {"coordinates":[4.3113379478,50.8362388611],"type":"Point"}
}