{
  "type": "Feature",
  "properties": {
    "iso:country":"BE",
    "sg:address":"Blasiusdriesstraat 9bis",
    "sg:city":"Nevele",
    "sg:orig_category":"Schoonheidssalons",
    "sg:phone":"+32 9 371 81 30",
    "sg:postcode":"9850",
    "sg:province":"Oost-Vlaanderen",
    "wof:name":"Beautysalon Chris",
    "wof:placetype":"venue"
},
  "geometry": {"coordinates":[3.5542669296,51.0304336548],"type":"Point"}
}