{
  "type": "Feature",
  "properties": {
    "addr:full":"Krom Genthof 7 Brugge West-Vlaanderen 8000",
    "addr:housenumber":"7",
    "addr:postcode":"8000",
    "addr:street":"Krom Genthof",
    "iso:country":"BE",
    "sg:address":"Krom Genthof 7",
    "sg:city":"Brugge",
    "sg:orig_category":"Elektrische installaties voor woningen",
    "sg:phone":"+32 50 34 31 00",
    "sg:postcode":"8000",
    "sg:province":"West-Vlaanderen",
    "wof:name":"Celestin Vuylsteke",
    "wof:placetype":"venue"
},
  "geometry": {"coordinates":[3.2259619236,51.2120666504],"type":"Point"}
}