{
  "type": "Feature",
  "properties": {
    "addr:full":"Van Reynegomlaan 29 Herenthout Antwerpen 2270",
    "addr:housenumber":"29",
    "addr:postcode":"2270",
    "addr:street":"Van Reynegomlaan",
    "iso:country":"BE",
    "sg:address":"Van Reynegomlaan 29",
    "sg:city":"Herenthout",
    "sg:classifiers":[
        {
            "category":"Personal",
            "subcategory":"Beauty Salon",
            "type":"Services"
        }
    ],
    "sg:phone":"+32 14 50 01 67",
    "sg:postcode":"2270",
    "sg:province":"Antwerpen",
    "sg:tags":[
        "lady",
        "-",
        "hairdressing"
    ],
    "wof:name":"Inga",
    "wof:placetype":"venue"
},
  "geometry": {"coordinates":[4.7529668808,51.138671875],"type":"Point"}
}