{
  "type": "Feature",
  "properties": {
    "iso:country":"BE",
    "sg:address":"Kioskplein 28",
    "sg:city":"Beringen",
    "sg:orig_category":"Installatie van houten of kunststof schrijnwerk",
    "sg:phone":"+32 11 42 52 97",
    "sg:postcode":"3582",
    "sg:province":"Limburg",
    "wof:name":"Paul Vlaminck",
    "wof:placetype":"venue"
},
  "geometry": {"coordinates":[5.2168989182,51.070602417],"type":"Point"}
}