{
  "type": "Feature",
  "properties": {
    "addr:full":"Brustemdorp 88 Sint-truiden Limburg 3800",
    "addr:housenumber":"88",
    "addr:postcode":"3800",
    "addr:street":"Brustemdorp",
    "iso:country":"BE",
    "sg:address":"Brustemdorp 88",
    "sg:city":"Sint-truiden",
    "sg:classifiers":[
        {
            "category":"Cafe",
            "type":"Food & Drink"
        }
    ],
    "sg:phone":"+32 11 67 11 58",
    "sg:postcode":"3800",
    "sg:province":"Limburg",
    "sg:tags":[
        "caf\u00e9s"
    ],
    "wof:name":"'t Kroegske",
    "wof:placetype":"venue"
},
  "geometry": {"coordinates":[5.2201418877,50.8010597229],"type":"Point"}
}