{
  "type": "Feature",
  "properties": {
    "addr:full":"Maarschalk Haiglaan 23a Ieper West-Vlaanderen 8900",
    "addr:housenumber":"23a",
    "addr:postcode":"8900",
    "addr:street":"Maarschalk Haiglaan",
    "iso:country":"BE",
    "sg:address":"Maarschalk Haiglaan 23a",
    "sg:city":"Ieper",
    "sg:classifiers":[
        {
            "category":"Personal",
            "subcategory":"Beauty Salon",
            "type":"Services"
        }
    ],
    "sg:postcode":"8900",
    "sg:province":"West-Vlaanderen",
    "sg:tags":[
        "slimming"
    ],
    "wof:name":"Body Dynamic",
    "wof:placetype":"venue"
},
  "geometry": {"coordinates":[2.875371933,50.8522224426],"type":"Point"}
}