{
  "type": "Feature",
  "properties": {
    "addr:full":"Rue Fernand Stimart 31 Namur Namur 5020",
    "addr:housenumber":"31",
    "addr:postcode":"5020",
    "addr:street":"Rue Fernand Stimart",
    "iso:country":"BE",
    "sg:address":"Rue Fernand Stimart 31",
    "sg:city":"Namur",
    "sg:classifiers":[
        {
            "category":"Shopping",
            "subcategory":"Clothing, Apparel, & Fashions",
            "type":"Retail Goods"
        }
    ],
    "sg:phone":"+32 81 21 10 02",
    "sg:postcode":"5020",
    "sg:province":"Namur",
    "sg:tags":[
        "v\u00eatements",
        "pour",
        "dame"
    ],
    "wof:name":"Willy-angie-patricia",
    "wof:placetype":"venue"
},
  "geometry": {"coordinates":[4.7952418327,50.4352035522],"type":"Point"}
}