{
  "type": "Feature",
  "properties": {
    "addr:full":"Rue Ulens 83 Bruxelles (molenbeek-saint-jean) Bruxelles-Capitale 1080",
    "addr:housenumber":"83",
    "addr:postcode":"1080",
    "addr:street":"Rue Ulens",
    "iso:country":"BE",
    "sg:address":"Rue Ulens 83",
    "sg:city":"Bruxelles (molenbeek-saint-jean)",
    "sg:classifiers":[
        {
            "category":"Education",
            "subcategory":"School",
            "type":"Public Place"
        }
    ],
    "sg:phone":"+32 2 426 40 42",
    "sg:postcode":"1080",
    "sg:province":"Bruxelles-Capitale",
    "sg:tags":[
        "primary"
    ],
    "wof:name":"Regenboog (de)",
    "wof:placetype":"venue"
},
  "geometry": {"coordinates":[4.3425068855,50.8630027771],"type":"Point"}
}