{
  "type": "Feature",
  "properties": {
    "iso:country":"BE",
    "sg:address":"Leeuwerstraat 2",
    "sg:city":"Gingelom",
    "sg:orig_category":"Producteurs de fruits. Eleveurs and marchands de porcs",
    "sg:phone":"+32 11 88 14 41",
    "sg:postcode":"3890",
    "sg:province":"Limburg",
    "wof:name":"Jeannine Houwaer",
    "wof:placetype":"venue"
},
  "geometry": {"coordinates":[5.1300702095,50.7535247803],"type":"Point"}
}