{
  "type": "Feature",
  "properties": {
    "addr:full":"Bosdorp 80 Stekene Oost-Vlaanderen 9190",
    "addr:housenumber":"80",
    "addr:postcode":"9190",
    "addr:street":"Bosdorp",
    "iso:country":"BE",
    "sg:address":"Bosdorp 80",
    "sg:city":"Stekene",
    "sg:classifiers":[
        {
            "category":"Cafe",
            "type":"Food & Drink"
        }
    ],
    "sg:phone":"+32 3 789 27 59",
    "sg:postcode":"9190",
    "sg:province":"Oost-Vlaanderen",
    "sg:tags":[
        "caf\u00e9s"
    ],
    "wof:name":"Caf\u00c9 Bosdorp",
    "wof:placetype":"venue"
},
  "geometry": {"coordinates":[4.0300068855,51.1953048706],"type":"Point"}
}