{
  "type": "Feature",
  "properties": {
    "addr:full":"De Reinelaan 15 Machelen (diegem) Vlaams-Brabant 1831",
    "addr:housenumber":"15",
    "addr:postcode":"1831",
    "addr:street":"De Reinelaan",
    "iso:country":"BE",
    "sg:address":"De Reinelaan 15",
    "sg:city":"Machelen (diegem)",
    "sg:classifiers":[
        {
            "category":"Manufacturing",
            "subcategory":"Furniture",
            "type":"Manufacturing & Wholesale Goods"
        }
    ],
    "sg:phone":"+32 2 725 86 94",
    "sg:postcode":"1831",
    "sg:province":"Vlaams-Brabant",
    "sg:tags":[
        "made",
        "-",
        "custom"
    ],
    "wof:name":"Calcoen L",
    "wof:placetype":"venue"
},
  "geometry": {"coordinates":[4.4329519272,50.8951377869],"type":"Point"}
}