{
  "type": "Feature",
  "properties": {
    "addr:full":"Bovekerkestraat 36 Koekelare West-Vlaanderen 8680",
    "addr:housenumber":"36",
    "addr:postcode":"8680",
    "addr:street":"Bovekerkestraat",
    "iso:country":"BE",
    "sg:address":"Bovekerkestraat 36",
    "sg:city":"Koekelare",
    "sg:classifiers":[
        {
            "category":"Arena",
            "subcategory":"Sports Club",
            "type":"Entertainment"
        }
    ],
    "sg:phone":"+32 477 30 18 21",
    "sg:postcode":"8680",
    "sg:province":"West-Vlaanderen",
    "sg:tags":[
        "de"
    ],
    "wof:name":"Judoschool Smis F.",
    "wof:placetype":"venue"
},
  "geometry": {"coordinates":[2.9631330967,51.0634002686],"type":"Point"}
}