{
  "type": "Feature",
  "properties": {
    "addr:full":"Meerlaan 15 Knokke-heist (knokke) West-Vlaanderen 8300",
    "addr:housenumber":"15",
    "addr:postcode":"8300",
    "addr:street":"Meerlaan",
    "iso:country":"BE",
    "sg:address":"Meerlaan 15",
    "sg:city":"Knokke-heist (knokke)",
    "sg:classifiers":[
        {
            "category":"Utilities",
            "subcategory":"Refuse",
            "type":"Services"
        }
    ],
    "sg:phone":"+32 50 60 17 30",
    "sg:postcode":"8300",
    "sg:province":"West-Vlaanderen",
    "sg:tags":[
        "removal"
    ],
    "wof:name":"Omer Van Maele Cv",
    "wof:placetype":"venue"
},
  "geometry": {"coordinates":[3.2832760811,51.3424453735],"type":"Point"}
}