{
  "type": "Feature",
  "properties": {
    "addr:full":"Ledebergstraat 65-67 Gent (ledeberg) Oost-Vlaanderen 9050",
    "addr:housenumber":"65-67",
    "addr:postcode":"9050",
    "addr:street":"Ledebergstraat",
    "iso:country":"BE",
    "sg:address":"Ledebergstraat 65-67",
    "sg:city":"Gent (ledeberg)",
    "sg:classifiers":[
        {
            "category":"Retail",
            "subcategory":"Repair Shop",
            "type":"Services"
        }
    ],
    "sg:phone":"+32 9 231 25 56",
    "sg:postcode":"9050",
    "sg:province":"Oost-Vlaanderen",
    "sg:tags":[
        "-",
        "mainten",
        "watch",
        "clock"
    ],
    "wof:name":"Goudsmederij Thienpont Bvba",
    "wof:placetype":"venue"
},
  "geometry": {"coordinates":[3.7416529655,51.0352706909],"type":"Point"}
}