{
  "type": "Feature",
  "properties": {
    "addr:full":"A. Vandenpeereboomplein 5 Ieper West-Vlaanderen 8900",
    "addr:housenumber":"5",
    "addr:postcode":"8900",
    "addr:street":"Vandenpeereboomplein",
    "iso:country":"BE",
    "sg:address":"A. Vandenpeereboomplein 5",
    "sg:city":"Ieper",
    "sg:classifiers":[
        {
            "category":"Cafe",
            "type":"Food & Drink"
        }
    ],
    "sg:phone":"+32 57 20 00 09",
    "sg:postcode":"8900",
    "sg:province":"West-Vlaanderen",
    "sg:tags":[
        "caf\u00e9s"
    ],
    "wof:name":"Caf\u00c9 't Ganzeke",
    "wof:placetype":"venue"
},
  "geometry": {"coordinates":[2.8842840195,50.8508796692],"type":"Point"}
}