{
  "type": "Feature",
  "properties": {
    "addr:full":"Rue Bois Pauvres 3 Chastre Brabant Wallon 1450",
    "addr:housenumber":"3",
    "addr:postcode":"1450",
    "addr:street":"Rue Bois Pauvres",
    "iso:country":"BE",
    "sg:address":"Rue Bois Pauvres 3",
    "sg:city":"Chastre",
    "sg:orig_category":"Loodgieterij, verwarming and sanitaire installaties",
    "sg:phone":"+32 10 65 07 43",
    "sg:postcode":"1450",
    "sg:province":"Brabant Wallon",
    "wof:name":"Sani-foucart",
    "wof:placetype":"venue"
},
  "geometry": {"coordinates":[4.6116552353,50.6081352234],"type":"Point"}
}