{
  "type": "Feature",
  "properties": {
    "addr:full":"Oudstrijderslaan 3 Kraainem/kraainem Vlaams-Brabant 1950",
    "addr:housenumber":"3",
    "addr:postcode":"1950",
    "addr:street":"Oudstrijderslaan",
    "iso:country":"BE",
    "sg:address":"Oudstrijderslaan 3",
    "sg:city":"Kraainem/kraainem",
    "sg:classifiers":[
        {
            "category":"Cafe",
            "type":"Food & Drink"
        }
    ],
    "sg:phone":"+32 2 720 16 97",
    "sg:postcode":"1950",
    "sg:province":"Vlaams-Brabant",
    "sg:tags":[
        "caf\u00e9s"
    ],
    "wof:name":"Caf\u00c9 De Kloeke Duiver",
    "wof:placetype":"venue"
},
  "geometry": {"coordinates":[4.464193821,50.8624534607],"type":"Point"}
}