{
  "type": "Feature",
  "properties": {
    "iso:country":"BE",
    "sg:address":"Tiensesteenweg 140",
    "sg:city":"Leuven (heverlee)",
    "sg:classifiers":[
        {
            "category":"Food & Beverages",
            "subcategory":"Meat & Fish",
            "type":"Retail Goods"
        }
    ],
    "sg:phone":"+32 16 35 34 29",
    "sg:postcode":"3001",
    "sg:province":"Vlaams-Brabant",
    "sg:tags":[
        "poultry",
        "whol",
        "game",
        "-"
    ],
    "wof:name":"Kiekeboer (de)",
    "wof:placetype":"venue"
},
  "geometry": {"coordinates":[4.7147669792,50.8754615784],"type":"Point"}
}