{
  "type": "Feature",
  "properties": {
    "addr:full":"Noeverseweg 6 Niel Antwerpen 2845",
    "addr:housenumber":"6",
    "addr:postcode":"2845",
    "addr:street":"Noeverseweg",
    "iso:country":"BE",
    "sg:address":"Noeverseweg 6",
    "sg:city":"Niel",
    "sg:orig_category":"Sportclubs",
    "sg:phone":"+32 3 888 18 36",
    "sg:postcode":"2845",
    "sg:province":"Antwerpen",
    "wof:name":"Wielerclub Hellegat",
    "wof:placetype":"venue"
},
  "geometry": {"coordinates":[4.3419108391,51.0968666077],"type":"Point"}
}