{
  "type": "Feature",
  "properties": {
    "addr:full":"Violetstraat 27 Westerlo Antwerpen 2260",
    "addr:housenumber":"27",
    "addr:postcode":"2260",
    "addr:street":"Violetstraat",
    "iso:country":"BE",
    "sg:address":"Violetstraat 27",
    "sg:city":"Westerlo",
    "sg:orig_category":"Banques and organismes de cr\u00e9dit",
    "sg:phone":"+32 14 21 42 32",
    "sg:postcode":"2260",
    "sg:province":"Antwerpen",
    "wof:name":"Citibank",
    "wof:placetype":"venue"
},
  "geometry": {"coordinates":[4.9098939896,51.1361618042],"type":"Point"}
}