{
  "type": "Feature",
  "properties": {
    "addr:full":"Stokrooieweg 29 Stokrooie Hasselt Limburg 3511",
    "addr:housenumber":"29",
    "addr:postcode":"3511",
    "addr:street":"Stokrooieweg",
    "iso:country":"BE",
    "sg:address":"Stokrooieweg 29",
    "sg:city":"Stokrooie Hasselt",
    "sg:orig_category":"Non-Classified Establishments",
    "sg:phone":"+32 11 25 09 14",
    "sg:postcode":"3511",
    "sg:province":"Limburg",
    "wof:name":"Vandevijvere",
    "wof:placetype":"venue"
},
  "geometry": {"coordinates":[5.2641320229,50.9567680359],"type":"Point"}
}