{
  "type": "Feature",
  "properties": {
    "addr:full":"Waterlelieplein 2 Box 205 Leuven (kessel-lo) Vlaams-Brabant 3010",
    "addr:housenumber":"2 box 205",
    "addr:postcode":"3010",
    "addr:street":"Waterlelieplein",
    "iso:country":"BE",
    "sg:address":"Waterlelieplein 2 Box 205",
    "sg:city":"Leuven (kessel-lo)",
    "sg:classifiers":[
        {
            "category":"Health Services",
            "subcategory":"Nursing And Care Facility",
            "type":"Services"
        }
    ],
    "sg:phone":"+32 16 35 03 87",
    "sg:postcode":"3010",
    "sg:province":"Vlaams-Brabant",
    "sg:tags":[
        "home"
    ],
    "wof:name":"Nazorg Hageland",
    "wof:placetype":"venue"
},
  "geometry": {"coordinates":[4.7304501534,50.889755249],"type":"Point"}
}