{
  "type": "Feature",
  "properties": {
    "iso:country":"BE",
    "sg:address":"Oude Kasteellaan 30",
    "sg:city":"Bonheiden",
    "sg:classifiers":[
        {
            "category":"Retail",
            "subcategory":"Animal Services",
            "type":"Services"
        }
    ],
    "sg:phone":"+32 15 51 42 30",
    "sg:postcode":"2820",
    "sg:province":"Antwerpen",
    "sg:tags":[
        "training",
        "dog"
    ],
    "wof:name":"Hondenschool Easy Mechelen Vzw",
    "wof:placetype":"venue"
},
  "geometry": {"coordinates":[4.5649828911,51.0196456909],"type":"Point"}
}