{
  "type": "Feature",
  "properties": {
    "addr:full":"Rue Des Chartreux 70a Bruxelles Bruxelles-Capitale 1000",
    "addr:housenumber":"70a",
    "addr:postcode":"1000",
    "addr:street":"Rue Des Chartreux",
    "iso:country":"BE",
    "sg:address":"Rue Des Chartreux 70a",
    "sg:city":"Bruxelles",
    "sg:classifiers":[
        {
            "category":"Shopping Center",
            "type":"Public Place"
        }
    ],
    "sg:phone":"+32 2 502 38 74",
    "sg:postcode":"1000",
    "sg:province":"Bruxelles-Capitale",
    "sg:tags":[
        "enseignement",
        "formation"
    ],
    "wof:name":"Bruxelles Formation",
    "wof:placetype":"venue"
},
  "geometry": {"coordinates":[4.3438901901,50.8484191895],"type":"Point"}
}