{
  "type": "Feature",
  "properties": {
    "addr:full":"Derrevoortstraat 23 Roosdaal Vlaams-Brabant 1760",
    "addr:housenumber":"23",
    "addr:postcode":"1760",
    "addr:street":"Derrevoortstraat",
    "iso:country":"BE",
    "sg:address":"Derrevoortstraat 23",
    "sg:city":"Roosdaal",
    "sg:orig_category":"S\u00e9curit\u00e9 sociale",
    "sg:phone":"+32 54 32 77 40",
    "sg:postcode":"1760",
    "sg:province":"Vlaams-Brabant",
    "wof:name":"Liberale Mutualiteit",
    "wof:placetype":"venue"
},
  "geometry": {"coordinates":[4.0744271278,50.8435707092],"type":"Point"}
}