{
  "type": "Feature",
  "properties": {
    "iso:country":"BE",
    "sg:address":"Steenweg Op Nieuwrode 237",
    "sg:city":"Rotselaar",
    "sg:orig_category":"Vins Fab. Distilleries",
    "sg:phone":"+32 16 58 17 67",
    "sg:postcode":"3111",
    "sg:province":"Vlaams-Brabant",
    "wof:name":"Wesemaeler Wijnbrouwers",
    "wof:placetype":"venue"
},
  "geometry": {"coordinates":[4.7836899757,50.9424209595],"type":"Point"}
}