{
  "type": "Feature",
  "properties": {
    "iso:country":"BE",
    "sg:address":"Grootstraat 89a",
    "sg:city":"Alken",
    "sg:classifiers":[
        {
            "category":"Building & Trades",
            "subcategory":"Electrical",
            "type":"Services"
        }
    ],
    "sg:phone":"+32 11 31 12 41",
    "sg:postcode":"3570",
    "sg:province":"Limburg",
    "sg:tags":[
        "electric",
        "-",
        "housewiring",
        "contractor"
    ],
    "wof:name":"Grosemans Y",
    "wof:placetype":"venue"
},
  "geometry": {"coordinates":[5.3221540451,50.8791351318],"type":"Point"}
}