{
  "type": "Feature",
  "properties": {
    "addr:full":"Astridlaan 7 Mol Antwerpen 2400",
    "addr:housenumber":"7",
    "addr:postcode":"2400",
    "addr:street":"Astridlaan",
    "iso:country":"BE",
    "sg:address":"Astridlaan 7",
    "sg:city":"Mol",
    "sg:orig_category":"Dakwerken Loodgieterij, verwarming and sanitaire installaties",
    "sg:phone":"+32 14 81 12 39",
    "sg:postcode":"2400",
    "sg:province":"Antwerpen",
    "wof:name":"Jozef Diels",
    "wof:placetype":"venue"
},
  "geometry": {"coordinates":[5.2101922035,51.1903572083],"type":"Point"}
}