{
  "type": "Feature",
  "properties": {
    "addr:full":"De Schiervelstraat 33 Tongeren Limburg 3700",
    "addr:housenumber":"33",
    "addr:postcode":"3700",
    "addr:street":"Schiervelstraat",
    "iso:country":"BE",
    "sg:address":"De Schiervelstraat 33",
    "sg:city":"Tongeren",
    "sg:orig_category":"Agences de mannequins and h\u00f4tesses",
    "sg:phone":"+32 12 26 34 64",
    "sg:postcode":"3700",
    "sg:province":"Limburg",
    "wof:name":"Ludwina Jacobs",
    "wof:placetype":"venue"
},
  "geometry": {"coordinates":[5.4682650566,50.7816696167],"type":"Point"}
}