{
  "type": "Feature",
  "properties": {
    "iso:country":"BE",
    "sg:address":"Rue Ramoux 7a",
    "sg:city":"Seraing",
    "sg:classifiers":[
        {
            "category":"Wholesale",
            "subcategory":"Construction Materials",
            "type":"Manufacturing & Wholesale Goods"
        }
    ],
    "sg:phone":"+32 4 338 43 14",
    "sg:postcode":"4100",
    "sg:province":"Li\u00e8ge",
    "sg:tags":[
        "tubing",
        "industrial"
    ],
    "wof:name":"M G P Sprl",
    "wof:placetype":"venue"
},
  "geometry": {"coordinates":[5.5038199425,50.6103134155],"type":"Point"}
}