{
  "type": "Feature",
  "properties": {
    "addr:full":"Rue Provinciale 119 Celles Hainaut 7760",
    "addr:housenumber":"119",
    "addr:postcode":"7760",
    "addr:street":"Rue Provinciale",
    "iso:country":"BE",
    "sg:address":"Rue Provinciale 119",
    "sg:city":"Celles",
    "sg:classifiers":[
        {
            "category":"Health Services",
            "subcategory":"Nursing And Care Facility",
            "type":"Services"
        }
    ],
    "sg:phone":"+32 69 45 43 11",
    "sg:postcode":"7760",
    "sg:province":"Hainaut",
    "sg:tags":[
        "home",
        "rest"
    ],
    "wof:name":"Roseraie (la)",
    "wof:placetype":"venue"
},
  "geometry": {"coordinates":[3.455657959,50.7189331055],"type":"Point"}
}