{
  "type": "Feature",
  "properties": {
    "addr:full":"Wezestraat 117 Izegem West-Vlaanderen 8870",
    "addr:housenumber":"117",
    "addr:postcode":"8870",
    "addr:street":"Wezestraat",
    "iso:country":"BE",
    "sg:address":"Wezestraat 117",
    "sg:city":"Izegem",
    "sg:orig_category":"Groententeelt",
    "sg:phone":"+32 51 31 81 77",
    "sg:postcode":"8870",
    "sg:province":"West-Vlaanderen",
    "wof:name":"Luc Desmet",
    "wof:placetype":"venue"
},
  "geometry": {"coordinates":[3.2180809975,50.9378509521],"type":"Point"}
}