{
  "type": "Feature",
  "properties": {
    "addr:full":"Leopoldlaan 40 Ninove Oost-Vlaanderen 9400",
    "addr:housenumber":"40",
    "addr:postcode":"9400",
    "addr:street":"Leopoldlaan",
    "iso:country":"BE",
    "sg:address":"Leopoldlaan 40",
    "sg:city":"Ninove",
    "sg:orig_category":"Artsen and specialisten",
    "sg:phone":"+32 54 32 59 11",
    "sg:postcode":"9400",
    "sg:province":"Oost-Vlaanderen",
    "wof:name":"C. Huyghe",
    "wof:placetype":"venue"
},
  "geometry": {"coordinates":[4.0222401619,50.8265304565],"type":"Point"}
}