{
  "type": "Feature",
  "properties": {
    "addr:full":"Weg Naar Zwartberg 0 Opglabbeek Limburg 3660",
    "addr:housenumber":"0",
    "addr:postcode":"3660",
    "addr:street":"Weg Naar Zwartberg",
    "iso:country":"BE",
    "sg:address":"Weg Naar Zwartberg 0",
    "sg:city":"Opglabbeek",
    "sg:orig_category":"Disneyland Parijs Reisbureaus",
    "sg:phone":"+32 89 81 20 00",
    "sg:postcode":"3660",
    "sg:province":"Limburg",
    "wof:name":"Trendy Travel Bvba",
    "wof:placetype":"venue"
},
  "geometry": {"coordinates":[5.5819501877,51.0420532227],"type":"Point"}
}