{
  "type": "Feature",
  "properties": {
    "addr:full":"Hoogkamerstraat 27 Sint-niklaas Oost-Vlaanderen 9100",
    "addr:housenumber":"27",
    "addr:postcode":"9100",
    "addr:street":"Hoogkamerstraat",
    "iso:country":"BE",
    "sg:address":"Hoogkamerstraat 27",
    "sg:city":"Sint-niklaas",
    "sg:orig_category":"Jardinage",
    "sg:phone":"+32 3 766 81 40",
    "sg:postcode":"9100",
    "sg:province":"Oost-Vlaanderen",
    "wof:name":"Bureau Krist & Annick",
    "wof:placetype":"venue"
},
  "geometry": {"coordinates":[4.18024683,51.1456985474],"type":"Point"}
}