{
  "type": "Feature",
  "properties": {
    "iso:country":"BE",
    "sg:address":"De Fierlantstraat 161",
    "sg:city":"Vorst/forest",
    "sg:orig_category":"Artsen and specialisten",
    "sg:phone":"+32 2 343 70 80",
    "sg:postcode":"1190",
    "sg:province":"Bruxelles-Capitale",
    "wof:name":"Richard Hallez",
    "wof:placetype":"venue"
},
  "geometry": {"coordinates":[4.3319330215,50.8234519958],"type":"Point"}
}