{
  "type": "Feature",
  "properties": {
    "addr:full":"Kapelstraat 91 Wommelgem Antwerpen 2160",
    "addr:housenumber":"91",
    "addr:postcode":"2160",
    "addr:street":"Kapelstraat",
    "iso:country":"BE",
    "sg:address":"Kapelstraat 91",
    "sg:city":"Wommelgem",
    "sg:classifiers":[
        {
            "category":"Wholesale",
            "subcategory":"Plants",
            "type":"Manufacturing & Wholesale Goods"
        }
    ],
    "sg:phone":"+32 3 353 78 68",
    "sg:postcode":"2160",
    "sg:province":"Antwerpen",
    "sg:tags":[
        "whol",
        "flower",
        "-",
        "grower"
    ],
    "wof:name":"Bloemenhandel Luc Janssens-mol Bvba",
    "wof:placetype":"venue"
},
  "geometry": {"coordinates":[4.5239491463,51.2093849182],"type":"Point"}
}