{
  "type": "Feature",
  "properties": {
    "addr:full":"Avenue Du Sud 7 Charleroi (marcinelle) Hainaut 6001",
    "addr:housenumber":"7",
    "addr:postcode":"6001",
    "addr:street":"Avenue Du Sud",
    "iso:country":"BE",
    "sg:address":"Avenue Du Sud 7",
    "sg:city":"Charleroi (marcinelle)",
    "sg:classifiers":[
        {
            "category":"Retail",
            "subcategory":"Car Wash",
            "type":"Services"
        }
    ],
    "sg:phone":"+32 71 43 59 50",
    "sg:postcode":"6001",
    "sg:province":"Hainaut",
    "sg:tags":[
        "automobile",
        "washing",
        "-",
        "truck"
    ],
    "wof:name":"Stefalex",
    "wof:placetype":"venue"
},
  "geometry": {"coordinates":[4.4523591995,50.3777770996],"type":"Point"}
}