{
  "type": "Feature",
  "properties": {
    "addr:full":"Boulevard Anspach 30-36 Bruxelles Bruxelles-Capitale 1000",
    "addr:postcode":"30-36;1000",
    "addr:street":"Boulevard Anspach",
    "iso:country":"BE",
    "sg:address":"Boulevard Anspach 30-36",
    "sg:city":"Bruxelles",
    "sg:classifiers":[
        {
            "category":"Organizations",
            "subcategory":"Community Association",
            "type":"Services"
        }
    ],
    "sg:phone":"+32 2 214 20 00",
    "sg:postcode":"1000",
    "sg:province":"Bruxelles-Capitale",
    "sg:tags":[
        "cultural"
    ],
    "wof:name":"Bruxelles 2000",
    "wof:placetype":"venue"
},
  "geometry": {"coordinates":[4.3515338898,50.849899292],"type":"Point"}
}