{
  "type": "Feature",
  "properties": {
    "addr:full":"Boomsesteenweg 14 Schelle Antwerpen 2627",
    "addr:housenumber":"14",
    "addr:postcode":"2627",
    "addr:street":"Boomsesteenweg",
    "iso:country":"BE",
    "sg:address":"Boomsesteenweg 14",
    "sg:city":"Schelle",
    "sg:orig_category":"MEUBELONTWERP AND -INSTALLATIE Meubelzaken, woning- and keukeninrichting",
    "sg:phone":"+32 3 828 29 47",
    "sg:postcode":"2627",
    "sg:province":"Antwerpen",
    "wof:name":"Kitchen Lovers",
    "wof:placetype":"venue"
},
  "geometry": {"coordinates":[4.371819973,51.117225647],"type":"Point"}
}