{
  "type": "Feature",
  "properties": {
    "iso:country":"BE",
    "sg:address":"Gentstraat 101",
    "sg:city":"Meulebeke",
    "sg:orig_category":"Non-Classified Establishments",
    "sg:phone":"+32 51 48 05 80",
    "sg:postcode":"8760",
    "sg:province":"West-Vlaanderen",
    "wof:name":"Unic Design Nv",
    "wof:placetype":"venue"
},
  "geometry": {"coordinates":[3.3047800064,50.9509010315],"type":"Point"}
}