{
  "type": "Feature",
  "properties": {
    "iso:country":"BE",
    "sg:address":"Clementstraat 3",
    "sg:city":"Bornem",
    "sg:classifiers":[
        {
            "category":"Food & Beverages",
            "subcategory":"Fruits & Vegetables",
            "type":"Retail Goods"
        }
    ],
    "sg:phone":"+32 3 889 13 76",
    "sg:postcode":"2880",
    "sg:province":"Antwerpen",
    "sg:tags":[
        "groenten"
    ],
    "wof:name":"E. De Saeger",
    "wof:placetype":"venue"
},
  "geometry": {"coordinates":[4.2350959778,51.0947608948],"type":"Point"}
}