{
  "type": "Feature",
  "properties": {
    "addr:full":"Floralaan 19 Beveren Oost-Vlaanderen 9120",
    "addr:housenumber":"19",
    "addr:postcode":"9120",
    "addr:street":"Floralaan",
    "iso:country":"BE",
    "sg:address":"Floralaan 19",
    "sg:city":"Beveren",
    "sg:orig_category":"Administration d'immeubles",
    "sg:phone":"+32 3 775 49 46",
    "sg:postcode":"9120",
    "sg:province":"Oost-Vlaanderen",
    "wof:name":"Dirk Van De Velde",
    "wof:placetype":"venue"
},
  "geometry": {"coordinates":[4.260638237,51.2209815979],"type":"Point"}
}