{
  "type": "Feature",
  "properties": {
    "addr:full":"Fr\u00e4iheetswee 115 Attert Luxembourg 6717",
    "addr:housenumber":"115",
    "addr:postcode":"6717",
    "addr:street":"Fraeiheetswee",
    "iso:country":"BE",
    "sg:address":"Fr\u00e4iheetswee 115",
    "sg:city":"Attert",
    "sg:classifiers":[
        {
            "category":"Arena",
            "subcategory":"Sports Club",
            "type":"Entertainment"
        }
    ],
    "sg:phone":"+32 63 23 28 89",
    "sg:postcode":"6717",
    "sg:province":"Luxembourg",
    "wof:name":"Tennis Club Val D'attert",
    "wof:placetype":"venue"
},
  "geometry": {"coordinates":[5.7888741493,49.7506217957],"type":"Point"}
}