{
  "type": "Feature",
  "properties": {
    "addr:full":"Zulzekestraat 13 Kluisbergen (zulzeke) Oost-Vlaanderen 9690",
    "addr:housenumber":"13",
    "addr:postcode":"9690",
    "addr:street":"Zulzekestraat",
    "iso:country":"BE",
    "sg:address":"Zulzekestraat 13",
    "sg:city":"Kluisbergen (zulzeke)",
    "sg:classifiers":[
        {
            "category":"Home & Garden",
            "subcategory":"Carpets & Floor Coverings",
            "type":"Retail Goods"
        }
    ],
    "sg:phone":"+32 55 38 78 05",
    "sg:postcode":"9690",
    "sg:province":"Oost-Vlaanderen",
    "sg:tags":[
        "layer",
        "mosaicists"
    ],
    "wof:name":"Goedertier D",
    "wof:placetype":"venue"
},
  "geometry": {"coordinates":[3.5712599754,50.7882041931],"type":"Point"}
}