{
  "type": "Feature",
  "properties": {
    "addr:full":"Hertog Janlaan 18 Ganshoren/ganshoren Bruxelles-Capitale 1083",
    "addr:housenumber":"18",
    "addr:postcode":"1083",
    "addr:street":"Hertog Janlaan",
    "iso:country":"BE",
    "sg:address":"Hertog Janlaan 18",
    "sg:city":"Ganshoren/ganshoren",
    "sg:orig_category":"Kapsalons",
    "sg:phone":"+32 2 426 81 09",
    "sg:postcode":"1083",
    "sg:province":"Bruxelles-Capitale",
    "wof:name":"Coiffure Louis Michel",
    "wof:placetype":"venue"
},
  "geometry": {"coordinates":[4.320166111,50.8681373596],"type":"Point"}
}