{
  "type": "Feature",
  "properties": {
    "addr:full":"Rue Achille Detienne 6 Bruxelles (schaerbeek) Bruxelles-Capitale 1030",
    "addr:housenumber":"6",
    "addr:postcode":"1030",
    "addr:street":"Rue Achille Detienne",
    "iso:country":"BE",
    "sg:address":"Rue Achille Detienne 6",
    "sg:city":"Bruxelles (schaerbeek)",
    "sg:classifiers":[
        {
            "category":"Wholesale",
            "subcategory":"Seafood",
            "type":"Manufacturing & Wholesale Goods"
        }
    ],
    "sg:phone":"+32 2 242 19 02",
    "sg:postcode":"1030",
    "sg:province":"Bruxelles-Capitale",
    "sg:tags":[
        "whol",
        "fish",
        "-",
        "shellfish"
    ],
    "wof:name":"Fructimar Sprl",
    "wof:placetype":"venue"
},
  "geometry": {"coordinates":[4.3887548447,50.8711585999],"type":"Point"}
}