{
  "type": "Feature",
  "properties": {
    "iso:country":"BE",
    "sg:address":"Industrielaan 1",
    "sg:city":"Aalst",
    "sg:orig_category":"Agences d'exp\u00e9dition",
    "sg:phone":"+32 53 83 70 02",
    "sg:postcode":"9320",
    "sg:province":"Oost-Vlaanderen",
    "wof:name":"Trase Bvba",
    "wof:placetype":"venue"
},
  "geometry": {"coordinates":[4.0553851128,50.9209976196],"type":"Point"}
}