{
  "type": "Feature",
  "properties": {
    "addr:full":"Rue De Bosnie 101 Bruxelles Bruxelles-Capitale 1060",
    "addr:housenumber":"101",
    "addr:postcode":"1060",
    "addr:street":"Rue De Bosnie",
    "iso:country":"BE",
    "sg:address":"Rue De Bosnie 101",
    "sg:city":"Bruxelles",
    "sg:classifiers":[
        {
            "category":"Manufacturing",
            "subcategory":"Leather Goods",
            "type":"Manufacturing & Wholesale Goods"
        }
    ],
    "sg:phone":"+32 2 537 55 26",
    "sg:postcode":"1060",
    "sg:province":"Bruxelles-Capitale",
    "sg:tags":[
        "shoe"
    ],
    "wof:name":"Jacques David Sprl",
    "wof:placetype":"venue"
},
  "geometry": {"coordinates":[4.3377552032,50.8269004822],"type":"Point"}
}