{
  "type": "Feature",
  "properties": {
    "iso:country":"BE",
    "sg:address":"Rue De La Station 78",
    "sg:city":"Herve",
    "sg:orig_category":"Herstelling horloges and juwelen Juwelen and horloges Opticiens",
    "sg:phone":"+32 87 67 48 18",
    "sg:postcode":"4650",
    "sg:province":"Li\u00e8ge",
    "wof:name":"N Baurens",
    "wof:placetype":"venue"
},
  "geometry": {"coordinates":[5.7917780876,50.6416244507],"type":"Point"}
}