{
  "type": "Feature",
  "properties": {
    "addr:full":"Availles Limousinelaan 7 Zaventem (sint-stevens-woluwe) Vlaams-Brabant 1932",
    "addr:housenumber":"7",
    "addr:postcode":"1932",
    "addr:street":"Limousinelaan",
    "iso:country":"BE",
    "sg:address":"Availles Limousinelaan 7",
    "sg:city":"Zaventem (sint-stevens-woluwe)",
    "sg:classifiers":[
        {
            "category":"Building & Trades",
            "subcategory":"Plumbing",
            "type":"Services"
        }
    ],
    "sg:phone":"+32 2 720 60 62",
    "sg:postcode":"1932",
    "sg:province":"Vlaams-Brabant",
    "sg:tags":[
        "repair",
        "mainten",
        "-",
        "central",
        "heating"
    ],
    "wof:name":"Amapa",
    "wof:placetype":"venue"
},
  "geometry": {"coordinates":[4.4327878952,50.8654441833],"type":"Point"}
}