{
  "type": "Feature",
  "properties": {
    "addr:full":"Grote Steenweg 67 Zulte (olsene) Oost-Vlaanderen 9870",
    "addr:housenumber":"67",
    "addr:postcode":"9870",
    "addr:street":"Grote Steenweg",
    "iso:country":"BE",
    "sg:address":"Grote Steenweg 67",
    "sg:city":"Zulte (olsene)",
    "sg:classifiers":[
        {
            "category":"Home & Garden",
            "subcategory":"Household Appliances",
            "type":"Retail Goods"
        }
    ],
    "sg:phone":"+32 9 388 61 34",
    "sg:postcode":"9870",
    "sg:province":"Oost-Vlaanderen",
    "sg:tags":[
        "repair",
        "mainten",
        "-",
        "electric"
    ],
    "wof:name":"Lippens (elektro)",
    "wof:placetype":"venue"
},
  "geometry": {"coordinates":[3.4676671028,50.9375953674],"type":"Point"}
}