{
  "type": "Feature",
  "properties": {
    "iso:country":"BE",
    "sg:address":"Houtzijde 74ba",
    "sg:city":"Lille",
    "sg:orig_category":"Travail and traitement du bois. Bois Quincailleries",
    "sg:phone":"+32 14 88 31 00",
    "sg:postcode":"2275",
    "sg:province":"Antwerpen",
    "wof:name":"Erik Willemsens",
    "wof:placetype":"venue"
},
  "geometry": {"coordinates":[4.8336248398,51.2575798035],"type":"Point"}
}