{
  "type": "Feature",
  "properties": {
    "iso:country":"BE",
    "sg:address":"Route De Wasseiges 266",
    "sg:city":"Namur",
    "sg:orig_category":"Installatie van houten of kunststof schrijnwerk",
    "sg:phone":"+32 81 51 30 97",
    "sg:postcode":"5022",
    "sg:province":"Namur",
    "wof:name":"Beno\u00cet Baugnet",
    "wof:placetype":"venue"
},
  "geometry": {"coordinates":[4.902985096,50.513671875],"type":"Point"}
}