{
  "type": "Feature",
  "properties": {
    "addr:full":"Dr. J. Vermylenstraat 4 Heist-op-den-berg Antwerpen 2223",
    "addr:housenumber":"4",
    "addr:postcode":"2223",
    "addr:street":"Dr. J. Vermylenstraat",
    "iso:country":"BE",
    "sg:address":"Dr. J. Vermylenstraat 4",
    "sg:city":"Heist-op-den-berg",
    "sg:orig_category":"Woningbouw",
    "sg:phone":"+32 15 23 32 62",
    "sg:postcode":"2223",
    "sg:province":"Antwerpen",
    "wof:name":"Van Den Broeck & Zoon",
    "wof:placetype":"venue"
},
  "geometry": {"coordinates":[4.6935648918,51.0282707214],"type":"Point"}
}