{
  "type": "Feature",
  "properties": {
    "addr:full":"Grand'route 378 Braine-l'alleud Brabant Wallon 1428",
    "addr:housenumber":"378",
    "addr:postcode":"1428",
    "addr:street":"Grand'Route",
    "iso:country":"BE",
    "sg:address":"Grand'route 378",
    "sg:city":"Braine-l'alleud",
    "sg:orig_category":"V\u00e9hicules automobiles. Entretien and r\u00e9parations de voitures",
    "sg:phone":"+32 2 384 38 92",
    "sg:postcode":"1428",
    "sg:province":"Brabant Wallon",
    "wof:name":"Garage Moutteau",
    "wof:placetype":"venue"
},
  "geometry": {"coordinates":[-0.6584389806,47.4034957886],"type":"Point"}
}