{
  "type": "Feature",
  "properties": {
    "iso:country":"BE",
    "sg:address":"Rue De Houtain 39",
    "sg:city":"Hannut",
    "sg:orig_category":"Gespecialiseerde residenti\u00eble bouw Woningbouw",
    "sg:phone":"+32 19 63 56 61",
    "sg:postcode":"4280",
    "sg:province":"Li\u00e8ge",
    "wof:name":"Luc Douette",
    "wof:placetype":"venue"
},
  "geometry": {"coordinates":[5.0469489098,50.6999511719],"type":"Point"}
}