{
  "type": "Feature",
  "properties": {
    "addr:full":"Rue Rausa 8 Modave Li\u00e8ge 4577",
    "addr:housenumber":"8",
    "addr:postcode":"4577",
    "addr:street":"Rue Rausa",
    "iso:country":"BE",
    "sg:address":"Rue Rausa 8",
    "sg:city":"Modave",
    "sg:orig_category":"Fotografen and fotostudio's",
    "sg:phone":"+32 85 51 14 36",
    "sg:postcode":"4577",
    "sg:province":"Li\u00e8ge",
    "wof:name":"Gilles Destexhe",
    "wof:placetype":"venue"
},
  "geometry": {"coordinates":[5.3258299828,50.5102310181],"type":"Point"}
}