{
  "type": "Feature",
  "properties": {
    "addr:full":"Avenue Houba De Strooper 46 Brussel/bruxelles Bruxelles-Capitale 1020",
    "addr:housenumber":"46",
    "addr:postcode":"1020",
    "addr:street":"Avenue Houba De Strooper;/",
    "iso:country":"BE",
    "sg:address":"Avenue Houba De Strooper 46",
    "sg:city":"Brussel/bruxelles",
    "sg:classifiers":[
        {
            "category":"Shopping",
            "subcategory":"Clothing, Apparel, & Fashions",
            "type":"Retail Goods"
        }
    ],
    "sg:phone":"+32 2 478 41 98",
    "sg:postcode":"1020",
    "sg:province":"Bruxelles-Capitale",
    "sg:tags":[
        "v\u00eatements",
        "pour",
        "dame"
    ],
    "wof:name":"Maison Capriccio",
    "wof:placetype":"venue"
},
  "geometry": {"coordinates":[4.3408370018,50.8867111206],"type":"Point"}
}