{
  "type": "Feature",
  "properties": {
    "iso:country":"BE",
    "sg:address":"Harenstraat 48",
    "sg:city":"Borgloon (bommershoven)",
    "sg:orig_category":"Non-Classified Establishments",
    "sg:phone":"+32 12 74 33 73",
    "sg:postcode":"3840",
    "sg:province":"Limburg",
    "wof:name":"Haesen A",
    "wof:placetype":"venue"
},
  "geometry": {"coordinates":[5.3441700935,50.8012466431],"type":"Point"}
}