{
  "type": "Feature",
  "properties": {
    "iso:country":"BE",
    "sg:address":"Sint-eloois Winkelstraat 110",
    "sg:city":"Ledegem",
    "sg:orig_category":"Producteurs de l\u00e9gumes",
    "sg:phone":"+32 56 50 02 24",
    "sg:postcode":"8880",
    "sg:province":"West-Vlaanderen",
    "wof:name":"Roland Lauwers",
    "wof:placetype":"venue"
},
  "geometry": {"coordinates":[3.1445770264,50.8584785461],"type":"Point"}
}