{
  "type": "Feature",
  "properties": {
    "iso:country":"BE",
    "sg:address":"19",
    "sg:city":"Ijzerenweglei 2640 Mortsel-belgium",
    "sg:classifiers":[
        {
            "category":"Manufacturing",
            "subcategory":"Tools & Machinery",
            "type":"Manufacturing & Wholesale Goods"
        }
    ],
    "sg:phone":"+32 3 448 19 33",
    "sg:postcode":"19",
    "sg:tags":[
        "metallurgy",
        "metalworking"
    ],
    "wof:name":"Duvimex Nv-sa",
    "wof:placetype":"venue"
},
  "geometry": {"coordinates":[4.4571509361,51.1773796082],"type":"Point"}
}