{
  "type": "Feature",
  "properties": {
    "iso:country":"BE",
    "sg:address":"Zavel 17",
    "sg:city":"Lebbeke",
    "sg:orig_category":"Secretariaatsdiensten",
    "sg:phone":"+32 52 41 49 34",
    "sg:postcode":"9280",
    "sg:province":"Oost-Vlaanderen",
    "wof:name":"Abbeel Vertalinge",
    "wof:placetype":"venue"
},
  "geometry": {"coordinates":[4.1354250908,50.9914627075],"type":"Point"}
}