{
  "type": "Feature",
  "properties": {
    "iso:country":"BE",
    "sg:address":"Bosveldstraat 46",
    "sg:city":"Alken",
    "sg:classifiers":[
        {
            "category":"Utilities",
            "subcategory":"Mobile Phone",
            "type":"Services"
        }
    ],
    "sg:postcode":"3570",
    "sg:province":"Limburg",
    "sg:tags":[
        "answering",
        "telephone"
    ],
    "wof:name":"Francon Bvba",
    "wof:placetype":"venue"
},
  "geometry": {"coordinates":[5.2668299675,50.897693634],"type":"Point"}
}