{
  "type": "Feature",
  "properties": {
    "addr:full":"Hayenhoek 15 Neerpelt Limburg 3910",
    "addr:housenumber":"15",
    "addr:postcode":"3910",
    "addr:street":"Hayenhoek",
    "iso:country":"BE",
    "sg:address":"Hayenhoek 15",
    "sg:city":"Neerpelt",
    "sg:classifiers":[
        {
            "category":"Building & Trades",
            "subcategory":"Construction",
            "type":"Services"
        }
    ],
    "sg:phone":"+32 11 80 34 08",
    "sg:postcode":"3910",
    "sg:province":"Limburg",
    "sg:tags":[
        "ceiling"
    ],
    "wof:name":"Jansen Montagebedrijf",
    "wof:placetype":"venue"
},
  "geometry": {"coordinates":[5.4314389229,51.2358055115],"type":"Point"}
}