{
  "type": "Feature",
  "properties": {
    "iso:country":"BE",
    "sg:address":"Rue Des D\u00c9port\u00c9s 4",
    "sg:city":"Tournai",
    "sg:orig_category":"Brood, gebak and snoepgoed",
    "sg:phone":"+32 69 35 22 51",
    "sg:postcode":"7522",
    "sg:province":"Hainaut",
    "wof:name":"Marcel Dupriez",
    "wof:placetype":"venue"
},
  "geometry": {"coordinates":[3.4003939629,50.6112365723],"type":"Point"}
}