{
  "type": "Feature",
  "properties": {
    "addr:full":"Rue Charles Lejeune 11 Waremme Li\u00e8ge 4300",
    "addr:housenumber":"11",
    "addr:postcode":"4300",
    "addr:street":"Rue Charles Lejeune",
    "iso:country":"BE",
    "sg:address":"Rue Charles Lejeune 11",
    "sg:city":"Waremme",
    "sg:orig_category":"Foto-uitrusting",
    "sg:phone":"+32 19 32 81 74",
    "sg:postcode":"4300",
    "sg:province":"Li\u00e8ge",
    "wof:name":"Phot'o'clock",
    "wof:placetype":"venue"
},
  "geometry": {"coordinates":[5.2571768761,50.6970481873],"type":"Point"}
}