{
  "type": "Feature",
  "properties": {
    "addr:full":"Kessel-dorp 19 Nijlen (kessel) Antwerpen 2560",
    "addr:housenumber":"19",
    "addr:postcode":"2560",
    "addr:street":"Kessel-Dorp",
    "iso:country":"BE",
    "sg:address":"Kessel-dorp 19",
    "sg:city":"Nijlen (kessel)",
    "sg:classifiers":[
        {
            "category":"Insurance",
            "subcategory":"Insurance Agent",
            "type":"Services"
        }
    ],
    "sg:phone":"+32 3 488 17 45",
    "sg:postcode":"2560",
    "sg:province":"Antwerpen",
    "sg:tags":[
        "broker"
    ],
    "wof:name":"Thijs & Pieters Nv",
    "wof:placetype":"venue"
},
  "geometry": {"coordinates":[4.6264939308,51.1389923096],"type":"Point"}
}