{
  "type": "Feature",
  "properties": {
    "iso:country":"BE",
    "sg:address":"Place Du Tuquet 18",
    "sg:city":"Mouscron",
    "sg:classifiers":[
        {
            "category":"Health Services",
            "subcategory":"Health Practitioner",
            "type":"Services"
        }
    ],
    "sg:phone":"+32 56 84 44 50",
    "sg:postcode":"7700",
    "sg:province":"Hainaut",
    "sg:tags":[
        "physiotherapist"
    ],
    "wof:name":"Alsters J-c",
    "wof:placetype":"venue"
},
  "geometry": {"coordinates":[3.1961050034,50.7409439087],"type":"Point"}
}