{
  "type": "Feature",
  "properties": {
    "iso:country":"BE",
    "sg:address":"Capucienenlaan 80",
    "sg:city":"Kraainem/kraainem",
    "sg:orig_category":"Artsen and specialisten",
    "sg:phone":"+32 2 720 09 79",
    "sg:postcode":"1950",
    "sg:province":"Vlaams-Brabant",
    "wof:name":"Pierre Roupin",
    "wof:placetype":"venue"
},
  "geometry": {"coordinates":[4.4620018005,50.8556518555],"type":"Point"}
}