{
  "type": "Feature",
  "properties": {
    "addr:full":"Lariksbos 5 Grobbendonk Antwerpen 2280",
    "addr:housenumber":"5",
    "addr:postcode":"2280",
    "addr:street":"Lariksbos",
    "iso:country":"BE",
    "sg:address":"Lariksbos 5",
    "sg:city":"Grobbendonk",
    "sg:orig_category":"Etalage- and showroomontwerpers",
    "sg:phone":"+32 14 51 33 19",
    "sg:postcode":"2280",
    "sg:province":"Antwerpen",
    "wof:name":"Jo Canters",
    "wof:placetype":"venue"
},
  "geometry": {"coordinates":[4.7265467644,51.1941947937],"type":"Point"}
}