{
  "type": "Feature",
  "properties": {
    "addr:full":"Amberloup 111 Sainte-ode Luxembourg 6680",
    "addr:housenumber":"111",
    "addr:postcode":"6680",
    "addr:street":"Amberloup",
    "iso:country":"BE",
    "sg:address":"Amberloup 111",
    "sg:city":"Sainte-ode",
    "sg:orig_category":"Apotheken",
    "sg:phone":"+32 61 68 84 17",
    "sg:postcode":"6680",
    "sg:province":"Luxembourg",
    "wof:name":"J. Hubermont",
    "wof:placetype":"venue"
},
  "geometry": {"coordinates":[5.5172657967,50.0253715515],"type":"Point"}
}