{
  "type": "Feature",
  "properties": {
    "addr:full":"Harlemboislaan 1 Harelbeke West-Vlaanderen 8530",
    "addr:housenumber":"1",
    "addr:postcode":"8530",
    "addr:street":"Harlemboislaan",
    "iso:country":"BE",
    "sg:address":"Harlemboislaan 1",
    "sg:city":"Harelbeke",
    "sg:classifiers":[
        {
            "category":"Bars & Pubs",
            "subcategory":"Nightclub",
            "type":"Food & Drink"
        }
    ],
    "sg:phone":"+32 56 72 06 01",
    "sg:postcode":"8530",
    "sg:province":"West-Vlaanderen",
    "wof:name":"The New Country",
    "wof:placetype":"venue"
},
  "geometry": {"coordinates":[3.294023037,50.8384742737],"type":"Point"}
}