{
  "type": "Feature",
  "properties": {
    "addr:full":"De Merodelei 8 Turnhout Antwerpen 2300",
    "addr:housenumber":"8",
    "addr:postcode":"2300",
    "addr:street":"De Merodelei",
    "iso:country":"BE",
    "sg:address":"De Merodelei 8",
    "sg:city":"Turnhout",
    "sg:classifiers":[
        {
            "category":"Shopping",
            "subcategory":"Clothing, Apparel, & Fashions",
            "type":"Retail Goods"
        }
    ],
    "sg:phone":"+32 14 42 99 59",
    "sg:postcode":"2300",
    "sg:province":"Antwerpen",
    "sg:tags":[
        "lady",
        "clothing",
        "-"
    ],
    "wof:name":"Rodier",
    "wof:placetype":"venue"
},
  "geometry": {"coordinates":[4.9424462318,51.3224716187],"type":"Point"}
}