{
  "type": "Feature",
  "properties": {
    "addr:full":"Rue Du Temple 57 La Louvi\u00c8re Hainaut 7100",
    "addr:housenumber":"57",
    "addr:postcode":"7100",
    "addr:street":"Rue Du Temple",
    "iso:country":"BE",
    "sg:address":"Rue Du Temple 57",
    "sg:city":"La Louvi\u00c8re",
    "sg:orig_category":"Tijdelijke werkgelegenheid and uitzendkantoren",
    "sg:phone":"+32 64 26 26 40",
    "sg:postcode":"7100",
    "sg:province":"Hainaut",
    "wof:name":"T. Interim",
    "wof:placetype":"venue"
},
  "geometry": {"coordinates":[4.1867599487,50.4748306274],"type":"Point"}
}