{
  "type": "Feature",
  "properties": {
    "addr:full":"Rue De Pr\u00e9e 5a Mettet (biesme) Namur 5640",
    "addr:housenumber":"5a",
    "addr:postcode":"5640",
    "addr:street":"Rue De Pre\u0301E;Biesme",
    "iso:country":"BE",
    "sg:address":"Rue De Pr\u00e9e 5a",
    "sg:city":"Mettet (biesme)",
    "sg:classifiers":[
        {
            "category":"Freight",
            "type":"Transportation"
        }
    ],
    "sg:phone":"+32 71 72 70 73",
    "sg:postcode":"5640",
    "sg:province":"Namur",
    "sg:tags":[
        "-",
        "transport"
    ],
    "wof:name":"Deravet P",
    "wof:placetype":"venue"
},
  "geometry": {"coordinates":[4.6049380302,50.3244781494],"type":"Point"}
}