{
  "type": "Feature",
  "properties": {
    "iso:country":"BE",
    "sg:address":"Rue Du Lombard 43",
    "sg:city":"Brussel/bruxelles",
    "sg:orig_category":"Alimentation sp\u00e9cialis\u00e9e",
    "sg:phone":"+32 2 512 68 28",
    "sg:postcode":"1000",
    "sg:province":"Bruxelles-Capitale",
    "wof:name":"Lombard R\u00c9gime",
    "wof:placetype":"venue"
},
  "geometry": {"coordinates":[4.3507962227,50.8453979492],"type":"Point"}
}