{
  "type": "Feature",
  "properties": {
    "addr:full":"Bien 26 Hamont-achel (achel) Limburg 3930",
    "addr:housenumber":"26",
    "addr:postcode":"3930",
    "addr:street":"Bien",
    "iso:country":"BE",
    "sg:address":"Bien 26",
    "sg:city":"Hamont-achel (achel)",
    "sg:classifiers":[
        {
            "category":"Shopping",
            "subcategory":"Pets & Pet Supplies",
            "type":"Retail Goods"
        }
    ],
    "sg:phone":"+32 11 80 15 11",
    "sg:postcode":"3930",
    "sg:province":"Limburg",
    "sg:tags":[
        "aquarium",
        "accessory"
    ],
    "wof:name":"Aquarium New Style",
    "wof:placetype":"venue"
},
  "geometry": {"coordinates":[5.4719648361,51.2522087097],"type":"Point"}
}