{
  "type": "Feature",
  "properties": {
    "iso:country":"BE",
    "sg:address":"Gellenberg 14",
    "sg:city":"Lubbeek",
    "sg:classifiers":[
        {
            "category":"Bars & Pubs",
            "type":"Food & Drink"
        }
    ],
    "sg:phone":"+32 16 64 05 02",
    "sg:postcode":"3210",
    "sg:province":"Vlaams-Brabant",
    "sg:tags":[
        "tavern"
    ],
    "wof:name":"Taverne Sporthal",
    "wof:placetype":"venue"
},
  "geometry": {"coordinates":[4.8398308754,50.8829536438],"type":"Point"}
}