{
  "type": "Feature",
  "properties": {
    "iso:country":"BE",
    "sg:address":"Kerkstraat 26",
    "sg:city":"Blankenberge",
    "sg:classifiers":[
        {
            "category":"Restaurant",
            "type":"Food & Drink"
        }
    ],
    "sg:phone":"+32 50 43 28 64",
    "sg:postcode":"8370",
    "sg:province":"West-Vlaanderen",
    "wof:name":"Caf\u00c9 Leffe",
    "wof:placetype":"venue"
},
  "geometry": {"coordinates":[3.1291790009,51.3153266907],"type":"Point"}
}