{
  "type": "Feature",
  "properties": {
    "iso:country":"BE",
    "sg:address":"Chauss\u00c9e De Fleurus 159",
    "sg:city":"Charleroi",
    "sg:orig_category":"Installation de menuiserie en bois and plastique",
    "sg:phone":"+32 71 48 80 20",
    "sg:postcode":"6060",
    "sg:province":"Hainaut",
    "wof:name":"Baticoma",
    "wof:placetype":"venue"
},
  "geometry": {"coordinates":[4.4880981445,50.4251937866],"type":"Point"}
}