{
  "type": "Feature",
  "properties": {
    "iso:country":"BE",
    "sg:address":"Kerkgate 91",
    "sg:city":"Oudenaarde",
    "sg:classifiers":[
        {
            "category":"Insurance",
            "subcategory":"Life Insurance",
            "type":"Services"
        }
    ],
    "sg:phone":"+32 55 45 52 07",
    "sg:postcode":"9700",
    "sg:province":"Oost-Vlaanderen",
    "sg:tags":[
        "assurance"
    ],
    "wof:name":"Bur. Van Cauwenberghe J.",
    "wof:placetype":"venue"
},
  "geometry": {"coordinates":[3.6696588993,50.8499183655],"type":"Point"}
}