{
  "type": "Feature",
  "properties": {
    "iso:country":"BE",
    "sg:address":"Rue De Nalinnes 84",
    "sg:city":"Walcourt",
    "sg:orig_category":"Matelas Fab",
    "sg:phone":"+32 71 61 22 14",
    "sg:postcode":"5651",
    "sg:province":"Namur",
    "wof:name":"Andr\u00c9 Tellier",
    "wof:placetype":"venue"
},
  "geometry": {"coordinates":[4.4262080193,50.2824401855],"type":"Point"}
}