{
  "type": "Feature",
  "properties": {
    "addr:full":"Rue De Herve 217 Grivegnee Li\u00e8ge 4030",
    "addr:housenumber":"217",
    "addr:postcode":"4030",
    "addr:street":"Rue De Herve",
    "iso:country":"BE",
    "sg:address":"Rue De Herve 217",
    "sg:city":"Grivegnee",
    "sg:classifiers":[
        {
            "category":"Professional",
            "subcategory":"Accounting & Tax Preparation",
            "type":"Services"
        }
    ],
    "sg:phone":"+32 4 343 10 14",
    "sg:postcode":"4030",
    "sg:province":"Li\u00e8ge",
    "sg:tags":[
        "bookkeeper"
    ],
    "wof:name":"Wagneur Yvette",
    "wof:placetype":"venue"
},
  "geometry": {"coordinates":[5.6102237701,50.6303596497],"type":"Point"}
}