{
  "type": "Feature",
  "properties": {
    "addr:full":"Avenue G\u00c9n. Vandamme 17 Couvin (grand) Namur 5660",
    "addr:housenumber":"17",
    "addr:postcode":"5660",
    "addr:street":"Avenue Ge\u0301N Vandamme",
    "iso:country":"BE",
    "sg:address":"Avenue G\u00c9n. Vandamme 17",
    "sg:city":"Couvin (grand)",
    "sg:classifiers":[
        {
            "category":"Personal",
            "subcategory":"Beauty Salon",
            "type":"Services"
        }
    ],
    "sg:postcode":"5660",
    "sg:province":"Namur",
    "sg:tags":[
        "de",
        "coiffure"
    ],
    "wof:name":"Evasion",
    "wof:placetype":"venue"
},
  "geometry": {"coordinates":[4.5274500847,50.1098518372],"type":"Point"}
}