{
  "type": "Feature",
  "properties": {
    "iso:country":"BE",
    "sg:address":"Sint-laurentiusstraat 21",
    "sg:city":"Maasmechelen",
    "sg:orig_category":"Boekhouders",
    "sg:phone":"+32 89 75 55 72",
    "sg:postcode":"3630",
    "sg:province":"Limburg",
    "wof:name":"Robert Albrechts",
    "wof:placetype":"venue"
},
  "geometry": {"coordinates":[5.7479481697,50.9988975525],"type":"Point"}
}