{
  "type": "Feature",
  "properties": {
    "addr:full":"Rue D\u00b4ostende 53 Sint-jans-molenbeek/molenbeek- Bruxelles-Capitale 1080",
    "addr:housenumber":"53",
    "addr:postcode":"1080",
    "addr:street":"Rue D\u00b4Ostende",
    "iso:country":"BE",
    "sg:address":"Rue D\u00b4ostende 53",
    "sg:city":"Sint-jans-molenbeek/molenbeek-",
    "sg:orig_category":"Jeux and jouets",
    "sg:phone":"+32 2 411 76 56",
    "sg:postcode":"1080",
    "sg:province":"Bruxelles-Capitale",
    "wof:name":"R.c. Pro Car",
    "wof:placetype":"venue"
},
  "geometry": {"coordinates":[4.3312911987,50.8559188843],"type":"Point"}
}