{
  "type": "Feature",
  "properties": {
    "iso:country":"BE",
    "sg:address":"Medelaar 142",
    "sg:city":"Zoersel",
    "sg:orig_category":"Pleisterwerk",
    "sg:phone":"+32 3 383 10 69",
    "sg:postcode":"2980",
    "sg:province":"Antwerpen",
    "wof:name":"De Feyter J",
    "wof:placetype":"venue"
},
  "geometry": {"coordinates":[4.6544299126,51.2543907166],"type":"Point"}
}