{
  "type": "Feature",
  "properties": {
    "iso:country":"BE",
    "sg:address":"Rue Bois No\u00ebl 1b",
    "sg:city":"Charleroi (jumet)",
    "sg:classifiers":[
        {
            "category":"Manufacturing",
            "subcategory":"Metals",
            "type":"Manufacturing & Wholesale Goods"
        }
    ],
    "sg:phone":"+32 71 42 21 94",
    "sg:postcode":"6040",
    "sg:province":"Hainaut",
    "sg:tags":[
        "ironwork"
    ],
    "wof:name":"Favretto",
    "wof:placetype":"venue"
},
  "geometry": {"coordinates":[4.472782135,50.4444351196],"type":"Point"}
}