{
  "type": "Feature",
  "properties": {
    "addr:full":"Mellestraat 459 Kortrijk West-Vlaanderen 8501",
    "addr:housenumber":"459",
    "addr:postcode":"8501",
    "addr:street":"Mellestraat",
    "iso:country":"BE",
    "sg:address":"Mellestraat 459",
    "sg:city":"Kortrijk",
    "sg:orig_category":"Rundveehouders Varkenskwekers",
    "sg:phone":"+32 56 35 46 24",
    "sg:postcode":"8501",
    "sg:province":"West-Vlaanderen",
    "wof:name":"Vandaele Frans & Noel",
    "wof:placetype":"venue"
},
  "geometry": {"coordinates":[3.2132270336,50.8720741272],"type":"Point"}
}