{
  "type": "Feature",
  "properties": {
    "iso:country":"BE",
    "sg:address":"Rue De La Station 87",
    "sg:city":"Blegny",
    "sg:orig_category":"Installatie van houten of kunststof schrijnwerk",
    "sg:phone":"+32 4 387 74 19",
    "sg:postcode":"4670",
    "sg:province":"Li\u00e8ge",
    "wof:name":"Ernst",
    "wof:placetype":"venue"
},
  "geometry": {"coordinates":[5.722796917,50.6777038574],"type":"Point"}
}