{
  "type": "Feature",
  "properties": {
    "addr:full":"Prins Boudewijnlaan 43 Edegem Antwerpen 2650",
    "addr:housenumber":"43",
    "addr:postcode":"2650",
    "addr:street":"Prins Boudewijnlaan",
    "iso:country":"BE",
    "sg:address":"Prins Boudewijnlaan 43",
    "sg:city":"Edegem",
    "sg:orig_category":"Bagage and lederwaren",
    "sg:phone":"+32 3 326 38 39",
    "sg:postcode":"2650",
    "sg:province":"Antwerpen",
    "wof:name":"Kipling",
    "wof:placetype":"venue"
},
  "geometry": {"coordinates":[4.4359350204,51.1476325989],"type":"Point"}
}