{
  "type": "Feature",
  "properties": {
    "addr:full":"Meerbos 20 Wichelen Oost-Vlaanderen 9260",
    "addr:housenumber":"20",
    "addr:postcode":"9260",
    "addr:street":"Meerbos",
    "iso:country":"BE",
    "sg:address":"Meerbos 20",
    "sg:city":"Wichelen",
    "sg:classifiers":[
        {
            "category":"Utilities",
            "subcategory":"Natural Gas",
            "type":"Services"
        }
    ],
    "sg:phone":"+32 52 42 21 29",
    "sg:postcode":"9260",
    "sg:province":"Oost-Vlaanderen",
    "sg:tags":[
        "blacksmith"
    ],
    "wof:name":"Denolf Smederij Bvba",
    "wof:placetype":"venue"
},
  "geometry": {"coordinates":[3.9576430321,51.0078277588],"type":"Point"}
}