{
  "type": "Feature",
  "properties": {
    "iso:country":"BE",
    "sg:address":"Rollegemseweg",
    "sg:city":"Kortrijk",
    "sg:orig_category":"Beheer van afvalopslag- and stortplaatsen",
    "sg:phone":"+32 56 23 98 11",
    "sg:postcode":"8510",
    "sg:province":"West-Vlaanderen",
    "wof:name":"Containerpark Rollegem",
    "wof:placetype":"venue"
},
  "geometry": {"coordinates":[3.2609550953,50.777305603],"type":"Point"}
}