{
  "type": "Feature",
  "properties": {
    "iso:country":"BE",
    "sg:address":"Elsensegalerij 49-50",
    "sg:city":"Bruxelles (ixelles)",
    "sg:classifiers":[
        {
            "category":"Shopping",
            "subcategory":"Beauty & Cosmetics",
            "type":"Retail Goods"
        }
    ],
    "sg:phone":"+32 2 502 71 22",
    "sg:postcode":"1050",
    "sg:province":"Bruxelles-Capitale",
    "sg:tags":[
        "-",
        "perfumery"
    ],
    "wof:name":"Sam",
    "wof:placetype":"venue"
},
  "geometry": {"coordinates":[4.3627500534,50.8364982605],"type":"Point"}
}