{
  "type": "Feature",
  "properties": {
    "addr:full":"Nieuwe Kassei 62 Affligem Vlaams-Brabant 1790",
    "addr:housenumber":"62",
    "addr:postcode":"1790",
    "addr:street":"Nieuwe Kassei",
    "iso:country":"BE",
    "sg:address":"Nieuwe Kassei 62",
    "sg:city":"Affligem",
    "sg:classifiers":[
        {
            "category":"Shopping",
            "subcategory":"Clothing, Apparel, & Fashions",
            "type":"Retail Goods"
        }
    ],
    "sg:phone":"+32 53 66 89 32",
    "sg:postcode":"1790",
    "sg:province":"Vlaams-Brabant",
    "sg:tags":[
        "v\u00eatements",
        "pour",
        "dame"
    ],
    "wof:name":"Mary's Moden",
    "wof:placetype":"venue"
},
  "geometry": {"coordinates":[4.1144380569,50.9192466736],"type":"Point"}
}