{
  "type": "Feature",
  "properties": {
    "iso:country":"BE",
    "sg:address":"Herbefays 9",
    "sg:city":"Yvoir",
    "sg:orig_category":"Boucheries",
    "sg:phone":"+32 83 69 91 87",
    "sg:postcode":"5530",
    "sg:province":"Namur",
    "wof:name":"Bruno Wauthier",
    "wof:placetype":"venue"
},
  "geometry": {"coordinates":[4.9894008636,50.3444366455],"type":"Point"}
}