{
  "type": "Feature",
  "properties": {
    "iso:country":"BE",
    "sg:address":"August Coolslaan 9/6",
    "sg:city":"Edegem",
    "sg:orig_category":"Mat\u00e9riel m\u00e9dical and orthop\u00e9dique and proth\u00e8ses Fab",
    "sg:phone":"+32 3 457 98 81",
    "sg:postcode":"2650",
    "sg:province":"Antwerpen",
    "wof:name":"Tandlabo Michel Morre",
    "wof:placetype":"venue"
},
  "geometry": {"coordinates":[4.4428510666,51.1513595581],"type":"Point"}
}