{
  "type": "Feature",
  "properties": {
    "addr:full":"Beernemsestw 51 Wingene West-Vlaanderen 8750",
    "addr:housenumber":"51",
    "addr:postcode":"8750",
    "addr:street":"Beernemsestw",
    "iso:country":"BE",
    "sg:address":"Beernemsestw 51",
    "sg:city":"Wingene",
    "sg:classifiers":[
        {
            "category":"Shopping",
            "subcategory":"Crafts & Fabrics",
            "type":"Retail Goods"
        }
    ],
    "sg:phone":"+32 51 65 77 70",
    "sg:postcode":"8750",
    "sg:province":"West-Vlaanderen",
    "sg:tags":[
        "textile",
        "clothing"
    ],
    "wof:name":"Indecor-europe Nv",
    "wof:placetype":"venue"
},
  "geometry": {"coordinates":[3.2787899971,51.0574951172],"type":"Point"}
}