{
  "type": "Feature",
  "properties": {
    "addr:full":"Rue Du Pont Couwez 39 Silly Hainaut 7830",
    "addr:housenumber":"39",
    "addr:postcode":"7830",
    "addr:street":"Rue Du Pont Couwez",
    "iso:country":"BE",
    "sg:address":"Rue Du Pont Couwez 39",
    "sg:city":"Silly",
    "sg:orig_category":"Eleveurs de bovins",
    "sg:phone":"+32 68 55 14 64",
    "sg:postcode":"7830",
    "sg:province":"Hainaut",
    "wof:name":"Franz Chevalier",
    "wof:placetype":"venue"
},
  "geometry": {"coordinates":[3.9562819004,50.6593666077],"type":"Point"}
}