{
  "type": "Feature",
  "properties": {
    "addr:full":"Chauss\u00c9e De Marche 61 Assesse Namur 5330",
    "addr:housenumber":"61",
    "addr:postcode":"5330",
    "addr:street":"Chausse\u0301E De Marche",
    "iso:country":"BE",
    "sg:address":"Chauss\u00c9e De Marche 61",
    "sg:city":"Assesse",
    "sg:orig_category":"Kapsalons",
    "sg:phone":"+32 83 65 51 03",
    "sg:postcode":"5330",
    "sg:province":"Namur",
    "wof:name":"Coiffure Elle-lui & Petits",
    "wof:placetype":"venue"
},
  "geometry": {"coordinates":[5.0232582092,50.3705482483],"type":"Point"}
}