{
  "type": "Feature",
  "properties": {
    "iso:country":"BE",
    "sg:address":"Rue Baudoin 1er 46",
    "sg:city":"Courcelles",
    "sg:classifiers":[
        {
            "category":"Personal",
            "subcategory":"Beauty Salon",
            "type":"Services"
        }
    ],
    "sg:phone":"+32 71 46 36 65",
    "sg:postcode":"6180",
    "sg:province":"Hainaut",
    "wof:name":"Mille Et Une Beaut\u00e9s",
    "wof:placetype":"venue"
},
  "geometry": {"coordinates":[4.3754930496,50.4570503235],"type":"Point"}
}