{
  "type": "Feature",
  "properties": {
    "addr:full":"Avenue Albert Ier 6 Namur Namur 5000",
    "addr:housenumber":"6",
    "addr:postcode":"5000",
    "addr:street":"Avenue Albert Ier",
    "iso:country":"BE",
    "sg:address":"Avenue Albert Ier 6",
    "sg:city":"Namur",
    "sg:orig_category":"Kapsalons",
    "sg:phone":"+32 81 22 32 71",
    "sg:postcode":"5000",
    "sg:province":"Namur",
    "wof:name":"Coiffure Style New-look",
    "wof:placetype":"venue"
},
  "geometry": {"coordinates":[4.8786358833,50.4659233093],"type":"Point"}
}