{
  "type": "Feature",
  "properties": {
    "iso:country":"BE",
    "sg:address":"Avenue De La Basilique 21",
    "sg:city":"Peruwelz",
    "sg:orig_category":"Jeux de hasard. Fleurs and plantes",
    "sg:phone":"+32 69 77 31 09",
    "sg:postcode":"7603",
    "sg:province":"Hainaut",
    "wof:name":"Amaryllis",
    "wof:placetype":"venue"
},
  "geometry": {"coordinates":[3.6057939529,50.4980812073],"type":"Point"}
}