{
  "type": "Feature",
  "properties": {
    "iso:country":"BE",
    "sg:address":"Oudburgstraat 17",
    "sg:city":"Zele",
    "sg:classifiers":[
        {
            "category":"Shopping",
            "subcategory":"Clothing, Apparel, & Fashions",
            "type":"Retail Goods"
        }
    ],
    "sg:phone":"+32 52 44 69 79",
    "sg:postcode":"9240",
    "sg:province":"Oost-Vlaanderen",
    "sg:tags":[
        "underwear",
        "lingerie",
        "-"
    ],
    "wof:name":"Eva",
    "wof:placetype":"venue"
},
  "geometry": {"coordinates":[4.0357809067,51.066734314],"type":"Point"}
}