{
  "type": "Feature",
  "properties": {
    "iso:country":"BE",
    "sg:address":"Valkestraat 5",
    "sg:city":"Aalter",
    "sg:classifiers":[
        {
            "category":"Real Estate",
            "subcategory":"Architect",
            "type":"Services"
        }
    ],
    "sg:phone":"+32 9 375 38 00",
    "sg:postcode":"9880",
    "sg:province":"Oost-Vlaanderen",
    "wof:name":"Slabbinck S",
    "wof:placetype":"venue"
},
  "geometry": {"coordinates":[3.4495470524,51.0837936401],"type":"Point"}
}