{
  "type": "Feature",
  "properties": {
    "iso:country":"BE",
    "sg:address":"Stalenstraat 19",
    "sg:city":"Genk",
    "sg:orig_category":"Pharmaciens",
    "sg:phone":"+32 89 38 24 29",
    "sg:postcode":"3600",
    "sg:province":"Limburg",
    "wof:name":"Apoth. Dirickx-paulissen",
    "wof:placetype":"venue"
},
  "geometry": {"coordinates":[5.5227880478,50.9967422485],"type":"Point"}
}