{
  "type": "Feature",
  "properties": {
    "addr:full":"Koningin Astridlaan 105 Moeskroen/mouscron Hainaut 7700",
    "addr:housenumber":"105",
    "addr:postcode":"7700",
    "addr:street":"Koningin Astridlaan",
    "iso:country":"BE",
    "sg:address":"Koningin Astridlaan 105",
    "sg:city":"Moeskroen/mouscron",
    "sg:orig_category":"Paramedische behandelingen",
    "sg:phone":"+32 56 84 14 10",
    "sg:postcode":"7700",
    "sg:province":"Hainaut",
    "wof:name":"M. De Cooman",
    "wof:placetype":"venue"
},
  "geometry": {"coordinates":[3.2323200703,50.7400932312],"type":"Point"}
}