{
  "type": "Feature",
  "properties": {
    "addr:full":"Rue Du Ch\u00e2teau D'eau 6 Lessines Hainaut 7860",
    "addr:housenumber":"6",
    "addr:postcode":"7860",
    "addr:street":"Rue Du Cha\u0302Teau D'Eau;Hainaut",
    "iso:country":"BE",
    "sg:address":"Rue Du Ch\u00e2teau D'eau 6",
    "sg:city":"Lessines",
    "sg:classifiers":[
        {
            "category":"Professional",
            "subcategory":"Accounting & Tax Preparation",
            "type":"Services"
        }
    ],
    "sg:phone":"+32 68 33 53 22",
    "sg:postcode":"7860",
    "sg:province":"Hainaut",
    "sg:tags":[
        "accountant"
    ],
    "wof:name":"Laudisoit C",
    "wof:placetype":"venue"
},
  "geometry": {"coordinates":[3.8447699547,50.7150726318],"type":"Point"}
}