{
  "type": "Feature",
  "properties": {
    "addr:full":"Rue Jos\u00e9phine Rauscent 79 Wavre (limal) Brabant Wallon 1300",
    "addr:housenumber":"79",
    "addr:postcode":"1300",
    "addr:street":"Rue Jose\u0301Phine Rauscent;Wallon",
    "iso:country":"BE",
    "sg:address":"Rue Jos\u00e9phine Rauscent 79",
    "sg:city":"Wavre (limal)",
    "sg:classifiers":[
        {
            "category":"Building & Trades",
            "subcategory":"Plumbing",
            "type":"Services"
        }
    ],
    "sg:phone":"+32 10 41 29 37",
    "sg:postcode":"1300",
    "sg:province":"Brabant Wallon",
    "sg:tags":[
        "repair",
        "mainten",
        "-",
        "central",
        "heating"
    ],
    "wof:name":"Nys P",
    "wof:placetype":"venue"
},
  "geometry": {"coordinates":[4.6116552353,50.7134132385],"type":"Point"}
}