{
  "type": "Feature",
  "properties": {
    "iso:country":"BE",
    "sg:address":"Blanklaerstraat 8",
    "sg:city":"Diest",
    "sg:orig_category":"R\u00e9parations d'appareils \u00e9lectrom\u00e9nagers",
    "sg:phone":"+32 13 31 20 01",
    "sg:postcode":"3290",
    "sg:province":"Vlaams-Brabant",
    "wof:name":"Marc Ceusters",
    "wof:placetype":"venue"
},
  "geometry": {"coordinates":[5.1186699867,51.0108108521],"type":"Point"}
}