{
  "type": "Feature",
  "properties": {
    "addr:full":"Vlinderstraat 8 Heusden-zolder (zolder) Limburg 3550",
    "addr:housenumber":"8",
    "addr:postcode":"3550",
    "addr:street":"Vlinderstraat",
    "iso:country":"BE",
    "sg:address":"Vlinderstraat 8",
    "sg:city":"Heusden-zolder (zolder)",
    "sg:orig_category":"Non-Classified Establishments",
    "sg:phone":"+32 11 53 31 64",
    "sg:postcode":"3550",
    "sg:province":"Limburg",
    "wof:name":"Limburgse Vleesmarkt Nv",
    "wof:placetype":"venue"
},
  "geometry": {"coordinates":[5.344894886,51.0205154419],"type":"Point"}
}