{
  "type": "Feature",
  "properties": {
    "addr:full":"Avenue De La Lib\u00e9ration 50 Sambreville (auvelais) Namur 5060",
    "addr:housenumber":"50",
    "addr:postcode":"5060",
    "addr:street":"Avenue De La Libe\u0301Ration",
    "iso:country":"BE",
    "sg:address":"Avenue De La Lib\u00e9ration 50",
    "sg:city":"Sambreville (auvelais)",
    "sg:classifiers":[
        {
            "category":"Fast Food",
            "type":"Food & Drink"
        }
    ],
    "sg:phone":"+32 71 74 34 60",
    "sg:postcode":"5060",
    "sg:province":"Namur",
    "sg:tags":[
        "fried",
        "stand",
        "potato"
    ],
    "wof:name":"Sur Le Coin",
    "wof:placetype":"venue"
},
  "geometry": {"coordinates":[4.6285200119,50.4448738098],"type":"Point"}
}