{
  "type": "Feature",
  "properties": {
    "addr:full":"Rue De Trazegnies 183b Courcelles Hainaut 6180",
    "addr:housenumber":"183b",
    "addr:postcode":"6180",
    "addr:street":"Rue De Trazegnies",
    "iso:country":"BE",
    "sg:address":"Rue De Trazegnies 183b",
    "sg:city":"Courcelles",
    "sg:orig_category":"Verhuisdiensten",
    "sg:phone":"+32 71 45 55 28",
    "sg:postcode":"6180",
    "sg:province":"Hainaut",
    "wof:name":"Alto Chiapparo & Fils",
    "wof:placetype":"venue"
},
  "geometry": {"coordinates":[4.3510742188,50.4626274109],"type":"Point"}
}