{
  "type": "Feature",
  "properties": {
    "addr:full":"Rue De La Ferr\u00e9e 29 Gerpinnes Hainaut 6280",
    "addr:housenumber":"29",
    "addr:postcode":"6280",
    "addr:street":"Rue De La Ferre\u0301E;Hainaut",
    "iso:country":"BE",
    "sg:address":"Rue De La Ferr\u00e9e 29",
    "sg:city":"Gerpinnes",
    "sg:classifiers":[
        {
            "category":"Real Estate",
            "subcategory":"Architect",
            "type":"Services"
        }
    ],
    "sg:phone":"+32 71 43 92 55",
    "sg:postcode":"6280",
    "sg:province":"Hainaut",
    "wof:name":"Bastien B",
    "wof:placetype":"venue"
},
  "geometry": {"coordinates":[4.465929985,50.3576889038],"type":"Point"}
}