{
  "type": "Feature",
  "properties": {
    "addr:full":"Avenue Des Lilas 75 Waterloo Brabant Wallon 1410",
    "addr:housenumber":"75",
    "addr:postcode":"1410",
    "addr:street":"Avenue Des Lilas",
    "iso:country":"BE",
    "sg:address":"Avenue Des Lilas 75",
    "sg:city":"Waterloo",
    "sg:classifiers":[
        {
            "category":"Professional",
            "subcategory":"Management & Consulting",
            "type":"Services"
        }
    ],
    "sg:phone":"+32 2 351 30 44",
    "sg:postcode":"1410",
    "sg:province":"Brabant Wallon",
    "sg:tags":[
        "consultant"
    ],
    "wof:name":"S Management Sprl",
    "wof:placetype":"venue"
},
  "geometry": {"coordinates":[4.3912248611,50.7244224548],"type":"Point"}
}