{
  "type": "Feature",
  "properties": {
    "iso:country":"BE",
    "sg:address":"Beselarestraat 110",
    "sg:city":"Wervik (geluwe)",
    "sg:classifiers":[
        {
            "category":"Real Estate",
            "subcategory":"Architect",
            "type":"Services"
        }
    ],
    "sg:phone":"+32 56 53 37 53",
    "sg:postcode":"8940",
    "sg:province":"West-Vlaanderen",
    "wof:name":"Vandorpe K",
    "wof:placetype":"venue"
},
  "geometry": {"coordinates":[3.045445919,50.7879867554],"type":"Point"}
}