{
  "type": "Feature",
  "properties": {
    "iso:country":"BE",
    "sg:address":"Noordlaan 107ba3",
    "sg:city":"Dendermonde",
    "sg:orig_category":"Banques and organismes de cr\u00e9dit",
    "sg:phone":"+32 52 22 36 08",
    "sg:postcode":"9200",
    "sg:province":"Oost-Vlaanderen",
    "wof:name":"Sofibank",
    "wof:placetype":"venue"
},
  "geometry": {"coordinates":[4.088988781,51.0333747864],"type":"Point"}
}