{
  "type": "Feature",
  "properties": {
    "iso:country":"BE",
    "sg:address":"Rue Montgom\u00e9ry 22",
    "sg:city":"Enghien",
    "sg:classifiers":[
        {
            "category":"Personal",
            "subcategory":"Beauty Salon",
            "type":"Services"
        }
    ],
    "sg:phone":"+32 2 395 72 22",
    "sg:postcode":"7850",
    "sg:province":"Hainaut",
    "wof:name":"Le Jardin De Marie Sc",
    "wof:placetype":"venue"
},
  "geometry": {"coordinates":[4.0375170708,50.6929664612],"type":"Point"}
}