{
  "type": "Feature",
  "properties": {
    "iso:country":"BE",
    "sg:address":"Rue Favette 12",
    "sg:city":"Charleroi",
    "sg:orig_category":"Epiceries",
    "sg:phone":"+32 71 31 72 07",
    "sg:postcode":"6030",
    "sg:province":"Hainaut",
    "wof:name":"Sonia Meurat",
    "wof:placetype":"venue"
},
  "geometry": {"coordinates":[4.3989629745,50.4240570068],"type":"Point"}
}