{
  "type": "Feature",
  "properties": {
    "iso:country":"BE",
    "sg:address":"Dikkebusstraat 139",
    "sg:city":"Heuvelland (loker)",
    "sg:classifiers":[
        {
            "category":"Building & Trades",
            "subcategory":"Landscaping Services",
            "type":"Services"
        }
    ],
    "sg:phone":"+32 57 44 87 39",
    "sg:postcode":"8958",
    "sg:province":"West-Vlaanderen",
    "sg:tags":[
        "gardening",
        "garden",
        "maintenance"
    ],
    "wof:name":"Groenidee",
    "wof:placetype":"venue"
},
  "geometry": {"coordinates":[2.7723040581,50.7892684937],"type":"Point"}
}