{
  "type": "Feature",
  "properties": {
    "addr:full":"Rue Du Huit Mai 7 Beyne-heusay Li\u00e8ge 4610",
    "addr:housenumber":"7",
    "addr:postcode":"4610",
    "addr:street":"Rue Du Huit Mai",
    "iso:country":"BE",
    "sg:address":"Rue Du Huit Mai 7",
    "sg:city":"Beyne-heusay",
    "sg:classifiers":[
        {
            "category":"Health Services",
            "subcategory":"Nursing And Care Facility",
            "type":"Services"
        }
    ],
    "sg:phone":"+32 4 355 04 19",
    "sg:postcode":"4610",
    "sg:province":"Li\u00e8ge",
    "sg:tags":[
        "home"
    ],
    "wof:name":"Jacquet J-a",
    "wof:placetype":"venue"
},
  "geometry": {"coordinates":[5.6585788727,50.6253852844],"type":"Point"}
}