{
  "type": "Feature",
  "properties": {
    "addr:full":"Rue Du Progr\u00c8s 9 Bievre Namur 5555",
    "addr:housenumber":"9",
    "addr:postcode":"5555",
    "addr:street":"Rue Du Progre\u0300S",
    "iso:country":"BE",
    "sg:address":"Rue Du Progr\u00c8s 9",
    "sg:city":"Bievre",
    "sg:orig_category":"Elektrische installaties voor woningen",
    "sg:phone":"+32 61 51 11 08",
    "sg:postcode":"5555",
    "sg:province":"Namur",
    "wof:name":"Maldague Roger",
    "wof:placetype":"venue"
},
  "geometry": {"coordinates":[5.0438928604,49.9349899292],"type":"Point"}
}