{
  "type": "Feature",
  "properties": {
    "iso:country":"BE",
    "sg:address":"Regentiestraat 6",
    "sg:city":"Meulebeke",
    "sg:classifiers":[
        {
            "category":"Insurance",
            "subcategory":"Life Insurance",
            "type":"Services"
        }
    ],
    "sg:phone":"+32 51 48 52 36",
    "sg:postcode":"8760",
    "sg:province":"West-Vlaanderen",
    "sg:tags":[
        "assurance"
    ],
    "wof:name":"J. Kesteloot",
    "wof:placetype":"venue"
},
  "geometry": {"coordinates":[3.2881040573,50.9513244629],"type":"Point"}
}