{
  "type": "Feature",
  "properties": {
    "addr:full":"R. L'h\u00d4tel Des Monnaies 52 Sint-gillis/saint-gilles Bruxelles-Capitale 1060",
    "addr:housenumber":"52 sint-gillis",
    "addr:postcode":"1060",
    "iso:country":"BE",
    "sg:address":"R. L'h\u00d4tel Des Monnaies 52",
    "sg:city":"Sint-gillis/saint-gilles",
    "sg:orig_category":"Activit\u00e9s d\u00b4action sociale sans h\u00e9bergement",
    "sg:phone":"+32 2 538 26 06",
    "sg:postcode":"1060",
    "sg:province":"Bruxelles-Capitale",
    "wof:name":"Colonie Amitie",
    "wof:placetype":"venue"
},
  "geometry": {"coordinates":[4.3489451408,50.8313598633],"type":"Point"}
}