{
  "type": "Feature",
  "properties": {
    "addr:full":"Legen Heirweg 71 Gavere (asper) Oost-Vlaanderen 9890",
    "addr:housenumber":"71",
    "addr:postcode":"9890",
    "addr:street":"Legen Heirweg",
    "iso:country":"BE",
    "sg:address":"Legen Heirweg 71",
    "sg:city":"Gavere (asper)",
    "sg:classifiers":[
        {
            "category":"Building & Trades",
            "subcategory":"Cleaning & Sanitation",
            "type":"Services"
        }
    ],
    "sg:phone":"+32 9 281 23 27",
    "sg:postcode":"9890",
    "sg:province":"Oost-Vlaanderen",
    "sg:tags":[
        "machine",
        "street",
        "maintenance"
    ],
    "wof:name":"Vermargo Nv",
    "wof:placetype":"venue"
},
  "geometry": {"coordinates":[3.6467459202,50.9340362549],"type":"Point"}
}