{
  "type": "Feature",
  "properties": {
    "addr:full":"Georges Brugmannplein 12b1 Elsene/ixelles Bruxelles-Capitale 1050",
    "addr:postcode":"1050",
    "iso:country":"BE",
    "sg:address":"Georges Brugmannplein 12b1",
    "sg:city":"Elsene/ixelles",
    "sg:orig_category":"Advocaten and juridische adviseurs",
    "sg:phone":"+32 2 345 12 92",
    "sg:postcode":"1050",
    "sg:province":"Bruxelles-Capitale",
    "wof:name":"R. D\u00b4hondt",
    "wof:placetype":"venue"
},
  "geometry": {"coordinates":[4.3539099693,50.8173904419],"type":"Point"}
}