{
  "type": "Feature",
  "properties": {
    "addr:full":"Beeweg 8 Lochristi Oost-Vlaanderen 9080",
    "addr:housenumber":"8",
    "addr:postcode":"9080",
    "addr:street":"Beeweg",
    "iso:country":"BE",
    "sg:address":"Beeweg 8",
    "sg:city":"Lochristi",
    "sg:classifiers":[
        {
            "category":"Food & Beverages",
            "subcategory":"Fruits & Vegetables",
            "type":"Retail Goods"
        }
    ],
    "sg:phone":"+32 9 355 60 46",
    "sg:postcode":"9080",
    "sg:province":"Oost-Vlaanderen",
    "sg:tags":[
        "l\u00e9gumes"
    ],
    "wof:name":"Huis Jacobs",
    "wof:placetype":"venue"
},
  "geometry": {"coordinates":[3.8811500072,51.1257171631],"type":"Point"}
}