{
  "type": "Feature",
  "properties": {
    "addr:full":"Rue Du Pressoir 36 Li\u00c8ge Li\u00e8ge 4000",
    "addr:housenumber":"36",
    "addr:postcode":"4000",
    "addr:street":"Rue Du Pressoir",
    "iso:country":"BE",
    "sg:address":"Rue Du Pressoir 36",
    "sg:city":"Li\u00c8ge",
    "sg:orig_category":"Experts-comptables",
    "sg:phone":"+32 4 252 80 74",
    "sg:postcode":"4000",
    "sg:province":"Li\u00e8ge",
    "wof:name":"Emile Defrere",
    "wof:placetype":"venue"
},
  "geometry": {"coordinates":[5.5578660965,50.6171913147],"type":"Point"}
}