{
  "type": "Feature",
  "properties": {
    "addr:full":"Rue Neuvice 49 Li\u00c8ge Li\u00e8ge 4000",
    "addr:housenumber":"49",
    "addr:postcode":"4000",
    "addr:street":"Rue Neuvice",
    "iso:country":"BE",
    "sg:address":"Rue Neuvice 49",
    "sg:city":"Li\u00c8ge",
    "sg:orig_category":"Epiceries",
    "sg:phone":"+32 4 222 93 52",
    "sg:postcode":"4000",
    "sg:province":"Li\u00e8ge",
    "wof:name":"Maison Le Matonge",
    "wof:placetype":"venue"
},
  "geometry": {"coordinates":[5.5774898529,50.6446647644],"type":"Point"}
}