{
  "type": "Feature",
  "properties": {
    "addr:full":"Rue De L' Avenir 89 Courcelles Hainaut 6182",
    "addr:housenumber":"89",
    "addr:postcode":"6182",
    "addr:street":"Rue De L ' Avenir",
    "iso:country":"BE",
    "sg:address":"Rue De L' Avenir 89",
    "sg:city":"Courcelles",
    "sg:orig_category":"Installation de menuiserie en bois and plastique",
    "sg:phone":"+32 71 45 68 26",
    "sg:postcode":"6182",
    "sg:province":"Hainaut",
    "wof:name":"Jean-nicolas Michaux",
    "wof:placetype":"venue"
},
  "geometry": {"coordinates":[4.3473339081,50.440990448],"type":"Point"}
}