{
  "type": "Feature",
  "properties": {
    "iso:country":"BE",
    "sg:address":"Celestijnenlaan 24",
    "sg:city":"Leuven",
    "sg:classifiers":[
        {
            "category":"Insurance",
            "subcategory":"Insurance Agent",
            "type":"Services"
        }
    ],
    "sg:phone":"+32 16 29 08 09",
    "sg:postcode":"3001",
    "sg:province":"Vlaams-Brabant",
    "sg:tags":[
        "verzekeringsmakelaars",
        "expert"
    ],
    "wof:name":"Vandeput Dirk",
    "wof:placetype":"venue"
},
  "geometry": {"coordinates":[4.6802401543,50.8660812378],"type":"Point"}
}