{
  "type": "Feature",
  "properties": {
    "iso:country":"BE",
    "sg:address":"Rue Des Vignes 55",
    "sg:city":"Mont-saint-guibert",
    "sg:orig_category":"Installation de menuiserie en bois and plastique",
    "sg:phone":"+32 10 65 76 24",
    "sg:postcode":"1435",
    "sg:province":"Brabant Wallon",
    "wof:name":"Frans Eggen",
    "wof:placetype":"venue"
},
  "geometry": {"coordinates":[4.6051011086,50.640663147],"type":"Point"}
}