{
  "type": "Feature",
  "properties": {
    "addr:full":"Diestsevest 82 Leuven Vlaams-Brabant 3000",
    "addr:housenumber":"82",
    "addr:postcode":"3000",
    "addr:street":"Diestsevest",
    "iso:country":"BE",
    "sg:address":"Diestsevest 82",
    "sg:city":"Leuven",
    "sg:classifiers":[
        {
            "category":"Organizations",
            "subcategory":"Professional Association",
            "type":"Services"
        }
    ],
    "sg:phone":"+32 16 28 44 40",
    "sg:postcode":"3000",
    "sg:province":"Vlaams-Brabant",
    "sg:tags":[
        "trade-union",
        "federation"
    ],
    "wof:name":"Unizo Vzw",
    "wof:placetype":"venue"
},
  "geometry": {"coordinates":[4.7070789337,50.8805046082],"type":"Point"}
}