{
  "type": "Feature",
  "properties": {
    "iso:country":"BE",
    "sg:address":"Koninginneplein 32",
    "sg:city":"Schaarbeek/schaerbeek",
    "sg:orig_category":"Herstelling leer and schoeisel",
    "sg:phone":"+32 2 218 33 40",
    "sg:postcode":"1030",
    "sg:province":"Bruxelles-Capitale",
    "wof:name":"Tirone Et Fils",
    "wof:placetype":"venue"
},
  "geometry": {"coordinates":[4.3656129837,50.8652153015],"type":"Point"}
}