{
  "type": "Feature",
  "properties": {
    "addr:full":"Place L\u00c9opold 15 Chimay Hainaut 6460",
    "addr:housenumber":"15",
    "addr:postcode":"6460",
    "addr:street":"Place Le\u0301Opold",
    "iso:country":"BE",
    "sg:address":"Place L\u00c9opold 15",
    "sg:city":"Chimay",
    "sg:classifiers":[
        {
            "category":"Restaurant",
            "type":"Food & Drink"
        }
    ],
    "sg:phone":"+32 60 21 17 41",
    "sg:postcode":"6460",
    "sg:province":"Hainaut",
    "wof:name":"Le Chaudron D\u00b4or",
    "wof:placetype":"venue"
},
  "geometry": {"coordinates":[4.3171839714,50.0471496582],"type":"Point"}
}