{
  "type": "Feature",
  "properties": {
    "addr:full":"Rue Du Ch\u00c2telain 42 Elsene/ixelles Bruxelles-Capitale 1050",
    "addr:housenumber":"42",
    "addr:postcode":"1050",
    "addr:street":"Rue Du Cha\u0302Telain",
    "iso:country":"BE",
    "sg:address":"Rue Du Ch\u00c2telain 42",
    "sg:city":"Elsene/ixelles",
    "sg:orig_category":"Services de Nettoyage and de D\u00e9sinfection",
    "sg:phone":"+32 2 647 34 04",
    "sg:postcode":"1050",
    "sg:province":"Bruxelles-Capitale",
    "wof:name":"Maurice",
    "wof:placetype":"venue"
},
  "geometry": {"coordinates":[4.3618459702,50.8252830505],"type":"Point"}
}