{
  "type": "Feature",
  "properties": {
    "addr:full":"Obterrestraat 28 Poperinge (proven) West-Vlaanderen 8972",
    "addr:housenumber":"28",
    "addr:postcode":"8972",
    "addr:street":"Obterrestraat",
    "iso:country":"BE",
    "sg:address":"Obterrestraat 28",
    "sg:city":"Poperinge (proven)",
    "sg:classifiers":[
        {
            "category":"Farming",
            "subcategory":"Livestock Farm",
            "type":"Manufacturing & Wholesale Goods"
        }
    ],
    "sg:phone":"+32 57 30 05 45",
    "sg:postcode":"8972",
    "sg:province":"West-Vlaanderen",
    "sg:tags":[
        "buyer"
    ],
    "wof:name":"Decapmaker A",
    "wof:placetype":"venue"
},
  "geometry": {"coordinates":[2.6543450356,50.8915519714],"type":"Point"}
}