{
  "type": "Feature",
  "properties": {
    "addr:full":"Haagdoornstraat 22 Lummen Limburg 3560",
    "addr:housenumber":"22",
    "addr:postcode":"3560",
    "addr:street":"Haagdoornstraat",
    "iso:country":"BE",
    "sg:address":"Haagdoornstraat 22",
    "sg:city":"Lummen",
    "sg:orig_category":"Installation \u00e9lectrique r\u00e9sidentielle",
    "sg:phone":"+32 11 45 10 94",
    "sg:postcode":"3560",
    "sg:province":"Limburg",
    "wof:name":"Philippe Everaerts",
    "wof:placetype":"venue"
},
  "geometry": {"coordinates":[5.2006440163,51.0104255676],"type":"Point"}
}