{
  "type": "Feature",
  "properties": {
    "iso:country":"BE",
    "sg:address":"Werkenplein 1",
    "sg:city":"Kortemark",
    "sg:classifiers":[
        {
            "category":"Personal",
            "subcategory":"Beauty Salon",
            "type":"Services"
        }
    ],
    "sg:phone":"+32 51 56 60 93",
    "sg:postcode":"8610",
    "sg:province":"West-Vlaanderen",
    "sg:tags":[
        "de",
        "coiffure"
    ],
    "wof:name":"Ginette Willaert",
    "wof:placetype":"venue"
},
  "geometry": {"coordinates":[3.0029890537,51.0260848999],"type":"Point"}
}