{
  "type": "Feature",
  "properties": {
    "iso:country":"BE",
    "sg:address":"Ambachtstraat 7",
    "sg:city":"Hoogstraten (minderhout)",
    "sg:classifiers":[
        {
            "category":"Building & Trades",
            "subcategory":"Landscaping Services",
            "type":"Services"
        }
    ],
    "sg:phone":"+32 3 314 73 48",
    "sg:postcode":"2322",
    "sg:province":"Antwerpen",
    "sg:tags":[
        "irrigation",
        "system"
    ],
    "wof:name":"Sprancomatic Bvba",
    "wof:placetype":"venue"
},
  "geometry": {"coordinates":[4.763384819,51.4160041809],"type":"Point"}
}