{
  "type": "Feature",
  "properties": {
    "iso:country":"BE",
    "sg:address":"Kapelstraat 6",
    "sg:city":"Willebroek",
    "sg:classifiers":[
        {
            "category":"Social Services",
            "subcategory":"Child Care",
            "type":"Services"
        }
    ],
    "sg:phone":"+32 3 866 57 89",
    "sg:postcode":"2830",
    "sg:province":"Antwerpen",
    "sg:tags":[
        "home"
    ],
    "wof:name":"Ckg",
    "wof:placetype":"venue"
},
  "geometry": {"coordinates":[4.3572978973,51.0530471802],"type":"Point"}
}