{
  "type": "Feature",
  "properties": {
    "addr:full":"Herlinval 101 La Roche-en-ardenne Luxembourg 6983",
    "addr:housenumber":"101",
    "addr:postcode":"6983",
    "addr:street":"Herlinval",
    "iso:country":"BE",
    "sg:address":"Herlinval 101",
    "sg:city":"La Roche-en-ardenne",
    "sg:orig_category":"Rundveehouders",
    "sg:phone":"+32 84 43 32 30",
    "sg:postcode":"6983",
    "sg:province":"Luxembourg",
    "wof:name":"Georges Mousny",
    "wof:placetype":"venue"
},
  "geometry": {"coordinates":[5.6033000946,50.1450004578],"type":"Point"}
}