{
  "type": "Feature",
  "properties": {
    "addr:full":"Avenue Cardinal Mercier 76 Namur Namur 5000",
    "addr:housenumber":"76",
    "addr:postcode":"5000",
    "addr:street":"Avenue Cardinal Mercier",
    "iso:country":"BE",
    "sg:address":"Avenue Cardinal Mercier 76",
    "sg:city":"Namur",
    "sg:orig_category":"Epiceries",
    "sg:phone":"+32 476 22 23 91",
    "sg:postcode":"5000",
    "sg:province":"Namur",
    "wof:name":"Asia Food",
    "wof:placetype":"venue"
},
  "geometry": {"coordinates":[4.8495779037,50.4648628235],"type":"Point"}
}