{
  "type": "Feature",
  "properties": {
    "addr:full":"Ti\u00e8ge 144 Jalhay (sart) Li\u00e8ge 4845",
    "addr:housenumber":"144",
    "addr:postcode":"4845",
    "addr:street":"Tie\u0300Ge;Sart Lie\u0300Ge",
    "iso:country":"BE",
    "sg:address":"Ti\u00e8ge 144",
    "sg:city":"Jalhay (sart)",
    "sg:classifiers":[
        {
            "category":"Animal Shelter",
            "type":"Public Place"
        }
    ],
    "sg:phone":"+32 87 47 46 84",
    "sg:postcode":"4845",
    "sg:province":"Li\u00e8ge",
    "wof:name":"Chansay V",
    "wof:placetype":"venue"
},
  "geometry": {"coordinates":[5.9049901962,50.5258483887],"type":"Point"}
}