{
  "type": "Feature",
  "properties": {
    "iso:country":"BE",
    "sg:address":"Hoogstraat 2",
    "sg:city":"Mechelen",
    "sg:orig_category":"Brood, gebak and snoepgoed",
    "sg:phone":"+32 15 42 27 01",
    "sg:postcode":"2800",
    "sg:province":"Antwerpen",
    "wof:name":"Temmerman",
    "wof:placetype":"venue"
},
  "geometry": {"coordinates":[4.4752531052,51.0239448547],"type":"Point"}
}