{
  "type": "Feature",
  "properties": {
    "addr:full":"Dorpsstraat 5 Brugge (sint-michiels) West-Vlaanderen 8200",
    "addr:housenumber":"5",
    "addr:postcode":"8200",
    "addr:street":"Dorpsstraat",
    "iso:country":"BE",
    "sg:address":"Dorpsstraat 5",
    "sg:city":"Brugge (sint-michiels)",
    "sg:classifiers":[
        {
            "category":"Banks & Credit Unions",
            "subcategory":"Bureau De Change",
            "type":"Services"
        }
    ],
    "sg:phone":"+32 495 82 43 34",
    "sg:postcode":"8200",
    "sg:province":"West-Vlaanderen",
    "sg:tags":[
        "window",
        "display",
        "supply"
    ],
    "wof:name":"Requisiet",
    "wof:placetype":"venue"
},
  "geometry": {"coordinates":[3.2121019363,51.1887054443],"type":"Point"}
}