{
  "type": "Feature",
  "properties": {
    "addr:full":"Zuivelmarkt 38e Hasselt Limburg 3500",
    "addr:housenumber":"38e",
    "addr:postcode":"3500",
    "addr:street":"Zuivelmarkt",
    "iso:country":"BE",
    "sg:address":"Zuivelmarkt 38e",
    "sg:city":"Hasselt",
    "sg:classifiers":[
        {
            "category":"Cafe",
            "type":"Food & Drink"
        }
    ],
    "sg:phone":"+32 11 23 20 02",
    "sg:postcode":"3500",
    "sg:province":"Limburg",
    "sg:tags":[
        "snack-bars"
    ],
    "wof:name":"Ketch-up",
    "wof:placetype":"venue"
},
  "geometry": {"coordinates":[5.3399147987,50.931602478],"type":"Point"}
}