{
  "type": "Feature",
  "properties": {
    "addr:full":"Industrizone Ii  Nederwijk Oost Ninove Oost-Vlaanderen 9400",
    "addr:postcode":"9400",
    "addr:street":"Nederwijk",
    "iso:country":"BE",
    "sg:address":"Industrizone Ii  Nederwijk Oost",
    "sg:city":"Ninove",
    "sg:orig_category":"Agences d'exp\u00e9dition",
    "sg:phone":"+32 54 32 65 01",
    "sg:postcode":"9400",
    "sg:province":"Oost-Vlaanderen",
    "wof:name":"United Fashion",
    "wof:placetype":"venue"
},
  "geometry": {"coordinates":[4.0453019142,50.8419837952],"type":"Point"}
}