{
  "type": "Feature",
  "properties": {
    "addr:full":"Eikstraat 5 Scherpenheuvel-zichem Vlaams-Brabant 3271",
    "addr:housenumber":"5",
    "addr:postcode":"3271",
    "addr:street":"Eikstraat",
    "iso:country":"BE",
    "sg:address":"Eikstraat 5",
    "sg:city":"Scherpenheuvel-zichem",
    "sg:orig_category":"Diensten voor huisdieren",
    "sg:phone":"+32 13 78 39 16",
    "sg:postcode":"3271",
    "sg:province":"Vlaams-Brabant",
    "wof:name":"Trimkelderke",
    "wof:placetype":"venue"
},
  "geometry": {"coordinates":[4.952837944,50.9872932434],"type":"Point"}
}