{
  "type": "Feature",
  "properties": {
    "addr:full":"Avenue De La F\u00c9condit\u00c9 80 Anderlecht/anderlecht Bruxelles-Capitale 1070",
    "addr:housenumber":"80",
    "addr:postcode":"1070",
    "addr:street":"Avenue De La Fe\u0301Condite\u0301",
    "iso:country":"BE",
    "sg:address":"Avenue De La F\u00c9condit\u00c9 80",
    "sg:city":"Anderlecht/anderlecht",
    "sg:orig_category":"Peinture. Rev\u00eatements pour sols and murs",
    "sg:phone":"+32 2 527 08 33",
    "sg:postcode":"1070",
    "sg:province":"Bruxelles-Capitale",
    "wof:name":"V.p. Reno",
    "wof:placetype":"venue"
},
  "geometry": {"coordinates":[4.2749609947,50.838104248],"type":"Point"}
}