{
  "type": "Feature",
  "properties": {
    "iso:country":"BE",
    "sg:address":"Boulevard De L'eurozone 5",
    "sg:city":"Moeskroen/mouscron",
    "sg:orig_category":"Blanchisseries and teintureries",
    "sg:phone":"+32 56 85 08 11",
    "sg:postcode":"7700",
    "sg:province":"Hainaut",
    "wof:name":"Nettoyage \u00c0 Sec Sofisolk",
    "wof:placetype":"venue"
},
  "geometry": {"coordinates":[3.2190279961,50.7275848389],"type":"Point"}
}