{
  "type": "Feature",
  "properties": {
    "addr:full":"Rue Du Z\u00c9nith 40 Sint-agatha-berchem Bruxelles-Capitale 1082",
    "addr:housenumber":"40",
    "addr:postcode":"1082",
    "addr:street":"Rue Du Ze\u0301Nith",
    "iso:country":"BE",
    "sg:address":"Rue Du Z\u00c9nith 40",
    "sg:city":"Sint-agatha-berchem",
    "sg:orig_category":"V\u00eatements, chaussures and accessoires Gr",
    "sg:phone":"+32 2 465 11 18",
    "sg:postcode":"1082",
    "sg:province":"Bruxelles-Capitale",
    "wof:name":"B.k.s. T-shirts",
    "wof:placetype":"venue"
},
  "geometry": {"coordinates":[4.2818422318,50.864074707],"type":"Point"}
}