{
  "type": "Feature",
  "properties": {
    "iso:country":"BE",
    "sg:address":"Rue Du Fort 85",
    "sg:city":"Sint-gillis/saint-gilles",
    "sg:orig_category":"Services fun\u00e9raires",
    "sg:phone":"+32 2 538 83 71",
    "sg:postcode":"1060",
    "sg:province":"Bruxelles-Capitale",
    "wof:name":"Le Centre Fun\u00c9raire Bxl",
    "wof:placetype":"venue"
},
  "geometry": {"coordinates":[4.3410282135,50.8275108337],"type":"Point"}
}