{
  "type": "Feature",
  "properties": {
    "addr:full":"Waaslandln 8 Lokeren Oost-Vlaanderen 9160",
    "addr:housenumber":"8",
    "addr:postcode":"9160",
    "addr:street":"Waaslandln",
    "iso:country":"BE",
    "sg:address":"Waaslandln 8",
    "sg:city":"Lokeren",
    "sg:classifiers":[
        {
            "category":"Manufacturing",
            "subcategory":"Chemicals & Compounds",
            "type":"Manufacturing & Wholesale Goods"
        }
    ],
    "sg:phone":"+32 9 349 34 77",
    "sg:postcode":"9160",
    "sg:province":"Oost-Vlaanderen",
    "sg:tags":[
        "pharmaceutical",
        "chemistry",
        "-",
        "by-product"
    ],
    "wof:name":"All Chemicals Research Nv",
    "wof:placetype":"venue"
},
  "geometry": {"coordinates":[4.0108809471,51.1206588745],"type":"Point"}
}