{
  "type": "Feature",
  "properties": {
    "addr:full":"Hovestraat 4 Edegem Antwerpen 2650",
    "addr:housenumber":"4",
    "addr:postcode":"2650",
    "addr:street":"Hovestraat",
    "iso:country":"BE",
    "sg:address":"Hovestraat 4",
    "sg:city":"Edegem",
    "sg:classifiers":[
        {
            "category":"Food & Beverages",
            "subcategory":"Chocolate",
            "type":"Retail Goods"
        }
    ],
    "sg:phone":"+32 3 458 61 65",
    "sg:postcode":"2650",
    "sg:province":"Antwerpen",
    "sg:tags":[
        "confectionery",
        "-"
    ],
    "wof:name":"Chocolat",
    "wof:placetype":"venue"
},
  "geometry": {"coordinates":[4.445625782,51.1556015015],"type":"Point"}
}