{
  "type": "Feature",
  "properties": {
    "addr:full":"Arthur Odevaertstraat 13 Maarkedal Oost-Vlaanderen 9688",
    "addr:housenumber":"13",
    "addr:postcode":"9688",
    "addr:street":"Odevaertstraat",
    "iso:country":"BE",
    "sg:address":"Arthur Odevaertstraat 13",
    "sg:city":"Maarkedal",
    "sg:orig_category":"Installation \u00e9lectrique r\u00e9sidentielle",
    "sg:phone":"+32 55 45 63 99",
    "sg:postcode":"9688",
    "sg:province":"Oost-Vlaanderen",
    "wof:name":"Karel Besard",
    "wof:placetype":"venue"
},
  "geometry": {"coordinates":[3.6923179626,50.7902793884],"type":"Point"}
}