{
  "type": "Feature",
  "properties": {
    "addr:full":"Rue Des Aub\u00c9pines 6 Rochefort Namur 5580",
    "addr:housenumber":"6",
    "addr:postcode":"5580",
    "addr:street":"Rue Des Aube\u0301Pines",
    "iso:country":"BE",
    "sg:address":"Rue Des Aub\u00c9pines 6",
    "sg:city":"Rochefort",
    "sg:orig_category":"Sportclubs",
    "sg:phone":"+32 84 37 70 90",
    "sg:postcode":"5580",
    "sg:province":"Namur",
    "wof:name":"Tennis Club Des Grottes",
    "wof:placetype":"venue"
},
  "geometry": {"coordinates":[5.1904878616,50.1251373291],"type":"Point"}
}