{
  "type": "Feature",
  "properties": {
    "iso:country":"BE",
    "sg:address":"Meensesteenweg 674",
    "sg:city":"Roeselare",
    "sg:classifiers":[
        {
            "category":"Autos & Motor Vehicles",
            "subcategory":"Automobile Sales",
            "type":"Retail Goods"
        }
    ],
    "sg:phone":"+32 51 21 13 71",
    "sg:postcode":"8800",
    "sg:province":"West-Vlaanderen",
    "sg:tags":[
        "car",
        "used",
        "-"
    ],
    "wof:name":"Foulon Jozef",
    "wof:placetype":"venue"
},
  "geometry": {"coordinates":[3.1145029068,50.9002227783],"type":"Point"}
}