{
  "type": "Feature",
  "properties": {
    "addr:full":"Boeretang 200 Mol Antwerpen 2400",
    "addr:housenumber":"200",
    "addr:postcode":"2400",
    "addr:street":"Boeretang",
    "iso:country":"BE",
    "sg:address":"Boeretang 200",
    "sg:city":"Mol",
    "sg:classifiers":[
        {
            "category":"Arena",
            "subcategory":"Sports Club",
            "type":"Entertainment"
        }
    ],
    "sg:phone":"+32 14 33 20 21",
    "sg:postcode":"2400",
    "sg:province":"Antwerpen",
    "sg:tags":[
        "de"
    ],
    "wof:name":"N.y.c.",
    "wof:placetype":"venue"
},
  "geometry": {"coordinates":[5.0968852043,51.2170372009],"type":"Point"}
}