{
  "type": "Feature",
  "properties": {
    "iso:country":"BE",
    "sg:address":"Koningin Elisabethstraat 19",
    "sg:city":"Kuurne",
    "sg:classifiers":[
        {
            "category":"Travel",
            "subcategory":"Travel Agent",
            "type":"Entertainment"
        }
    ],
    "sg:phone":"+32 56 70 55 55",
    "sg:postcode":"8520",
    "sg:province":"West-Vlaanderen",
    "sg:tags":[
        "agency"
    ],
    "wof:name":"Doris Reizen Bvba",
    "wof:placetype":"venue"
},
  "geometry": {"coordinates":[3.2853500843,50.8511009216],"type":"Point"}
}