{
  "type": "Feature",
  "properties": {
    "addr:full":"Rue De La Sabli\u00e8re 48 Villers-le-bouillet (fize-fontaine) Li\u00e8ge 4530",
    "addr:housenumber":"48",
    "addr:postcode":"4530",
    "addr:street":"Rue De La Sablie\u0300Re;Fize-Fontaine",
    "iso:country":"BE",
    "sg:address":"Rue De La Sabli\u00e8re 48",
    "sg:city":"Villers-le-bouillet (fize-fontaine)",
    "sg:classifiers":[
        {
            "category":"Food & Beverages",
            "subcategory":"Groceries & Convenience Stores",
            "type":"Retail Goods"
        }
    ],
    "sg:phone":"+32 4 259 52 26",
    "sg:postcode":"4530",
    "sg:province":"Li\u00e8ge",
    "sg:tags":[
        "grocer"
    ],
    "wof:name":"Wegria",
    "wof:placetype":"venue"
},
  "geometry": {"coordinates":[5.279009819,50.5768203735],"type":"Point"}
}