{
  "type": "Feature",
  "properties": {
    "addr:full":"Izegemsestraat 33 Ardooie West-Vlaanderen 8850",
    "addr:housenumber":"33",
    "addr:postcode":"8850",
    "addr:street":"Izegemsestraat",
    "iso:country":"BE",
    "sg:address":"Izegemsestraat 33",
    "sg:city":"Ardooie",
    "sg:orig_category":"Bouwmaterialen Gh",
    "sg:phone":"+32 51 74 40 80",
    "sg:postcode":"8850",
    "sg:province":"West-Vlaanderen",
    "wof:name":"Govar - Industriebouw",
    "wof:placetype":"venue"
},
  "geometry": {"coordinates":[3.1972680092,50.9672241211],"type":"Point"}
}