{
  "type": "Feature",
  "properties": {
    "addr:full":"Rue Fran\u00e7ois Hittelet 151 Jemeppe-sur-sambre Namur 5190",
    "addr:housenumber":"151",
    "addr:postcode":"jemeppe-sur-sambre;5190",
    "addr:street":"Rue Franc\u0327Ois Hittelet",
    "iso:country":"BE",
    "sg:address":"Rue Fran\u00e7ois Hittelet 151",
    "sg:city":"Jemeppe-sur-sambre",
    "sg:classifiers":[
        {
            "category":"Professional",
            "subcategory":"Accounting & Tax Preparation",
            "type":"Services"
        }
    ],
    "sg:phone":"+32 71 78 04 44",
    "sg:postcode":"5190",
    "sg:province":"Namur",
    "sg:tags":[
        "bookkeeper"
    ],
    "wof:name":"Lemaire Ph",
    "wof:placetype":"venue"
},
  "geometry": {"coordinates":[4.6634378433,50.4606208801],"type":"Point"}
}