{
  "type": "Feature",
  "properties": {
    "addr:full":"Neerstraat 12b1a Lummen Limburg 3560",
    "addr:postcode":"3560",
    "addr:street":"Neerstraat",
    "iso:country":"BE",
    "sg:address":"Neerstraat 12b1a",
    "sg:city":"Lummen",
    "sg:orig_category":"Advocaten and juridische adviseurs",
    "sg:phone":"+32 13 53 24 92",
    "sg:postcode":"3560",
    "sg:province":"Limburg",
    "wof:name":"Bart Vrancken",
    "wof:placetype":"venue"
},
  "geometry": {"coordinates":[5.1918702126,50.9847679138],"type":"Point"}
}