{
  "type": "Feature",
  "properties": {
    "addr:full":"Place Paul Pastur 37 Anderlues Hainaut 6150",
    "addr:housenumber":"37",
    "addr:postcode":"6150",
    "addr:street":"Place Paul Pastur",
    "iso:country":"BE",
    "sg:address":"Place Paul Pastur 37",
    "sg:city":"Anderlues",
    "sg:classifiers":[
        {
            "category":"Personal",
            "subcategory":"Beauty Salon",
            "type":"Services"
        }
    ],
    "sg:phone":"+32 71 52 40 80",
    "sg:postcode":"6150",
    "sg:province":"Hainaut",
    "sg:tags":[
        "lady",
        "-",
        "hairdressing"
    ],
    "wof:name":"Eddy Coupe (l')",
    "wof:placetype":"venue"
},
  "geometry": {"coordinates":[4.270401001,50.407409668],"type":"Point"}
}