{
  "type": "Feature",
  "properties": {
    "iso:country":"BE",
    "sg:address":"Neysetterstr 10",
    "sg:city":"Haacht (groot)",
    "sg:orig_category":"Kapsalons",
    "sg:phone":"+32 16 60 99 57",
    "sg:postcode":"3150",
    "sg:province":"Vlaams-Brabant",
    "wof:name":"Hair Design",
    "wof:placetype":"venue"
},
  "geometry": {"coordinates":[4.6052441597,50.9611816406],"type":"Point"}
}