{
  "type": "Feature",
  "properties": {
    "addr:full":"Krommewege 24e Maldegem Oost-Vlaanderen 9990",
    "addr:housenumber":"24e",
    "addr:postcode":"9990",
    "addr:street":"Krommewege",
    "iso:country":"BE",
    "sg:address":"Krommewege 24e",
    "sg:city":"Maldegem",
    "sg:classifiers":[
        {
            "category":"Building & Trades",
            "subcategory":"Construction",
            "type":"Services"
        }
    ],
    "sg:phone":"+32 50 71 08 10",
    "sg:postcode":"9990",
    "sg:province":"Oost-Vlaanderen",
    "sg:tags":[
        "insulation",
        "thermical",
        "work",
        "acoustical"
    ],
    "wof:name":"Amix Bvba",
    "wof:placetype":"venue"
},
  "geometry": {"coordinates":[3.4612820148,51.1968612671],"type":"Point"}
}