{
  "type": "Feature",
  "properties": {
    "addr:full":"Hoogpoort 51 Gent Oost-Vlaanderen 9000",
    "addr:housenumber":"51",
    "addr:postcode":"9000",
    "addr:street":"Hoogpoort;Oost-Vlaanderen",
    "iso:country":"BE",
    "sg:address":"Hoogpoort 51",
    "sg:city":"Gent",
    "sg:classifiers":[
        {
            "category":"Retail",
            "subcategory":"Repair Shop",
            "type":"Services"
        }
    ],
    "sg:phone":"+32 9 223 75 79",
    "sg:postcode":"9000",
    "sg:province":"Oost-Vlaanderen",
    "sg:tags":[
        "-",
        "mainten",
        "watch",
        "clock"
    ],
    "wof:name":"Vander Haeghen Goudsmederij",
    "wof:placetype":"venue"
},
  "geometry": {"coordinates":[3.7246530056,51.0549697876],"type":"Point"}
}