{
  "type": "Feature",
  "properties": {
    "addr:full":"Bogaert 108ba Wichelen Oost-Vlaanderen 9260",
    "addr:postcode":"9260",
    "addr:street":"Oost-Vlaanderen",
    "iso:country":"BE",
    "sg:address":"Bogaert 108ba",
    "sg:city":"Wichelen",
    "sg:classifiers":[
        {
            "category":"Personal",
            "subcategory":"Beauty Salon",
            "type":"Services"
        }
    ],
    "sg:phone":"+32 52 42 45 64",
    "sg:postcode":"9260",
    "sg:province":"Oost-Vlaanderen",
    "sg:tags":[
        "de",
        "coiffure"
    ],
    "wof:name":"Coiffure Rita",
    "wof:placetype":"venue"
},
  "geometry": {"coordinates":[3.9743049145,51.0067749023],"type":"Point"}
}