{
  "type": "Feature",
  "properties": {
    "iso:country":"BE",
    "sg:address":"Dadizeelsestraat 73ba",
    "sg:city":"Moorslede",
    "sg:classifiers":[
        {
            "category":"Food & Beverages",
            "subcategory":"Fruits & Vegetables",
            "type":"Retail Goods"
        }
    ],
    "sg:phone":"+32 51 77 02 01",
    "sg:postcode":"8890",
    "sg:province":"West-Vlaanderen",
    "sg:tags":[
        "l\u00e9gumes",
        "gr"
    ],
    "wof:name":"De Duytsche",
    "wof:placetype":"venue"
},
  "geometry": {"coordinates":[3.061300993,50.8882102966],"type":"Point"}
}