{
  "type": "Feature",
  "properties": {
    "iso:country":"BE",
    "sg:address":"Brusselstraat 257",
    "sg:city":"Dilbeek",
    "sg:classifiers":[
        {
            "category":"Cafe",
            "type":"Food & Drink"
        }
    ],
    "sg:phone":"+32 2 466 79 79",
    "sg:postcode":"1702",
    "sg:province":"Vlaams-Brabant",
    "sg:tags":[
        "caf\u00e9s"
    ],
    "wof:name":"Ludo Kerckhofs",
    "wof:placetype":"venue"
},
  "geometry": {"coordinates":[4.2618741989,50.8709983826],"type":"Point"}
}