{
  "type": "Feature",
  "properties": {
    "iso:country":"BE",
    "sg:address":"Gilainstraat 112",
    "sg:city":"Tienen",
    "sg:orig_category":"Apotheken",
    "sg:phone":"+32 16 81 21 08",
    "sg:postcode":"3300",
    "sg:province":"Vlaams-Brabant",
    "wof:name":"Kabephar",
    "wof:placetype":"venue"
},
  "geometry": {"coordinates":[4.9348669052,50.8120651245],"type":"Point"}
}