{
  "type": "Feature",
  "properties": {
    "iso:country":"BE",
    "sg:address":"Veerhuisdreef 33",
    "sg:city":"Schoten",
    "sg:orig_category":"Traitements param\u00e9dicaux",
    "sg:phone":"+32 3 685 55 07",
    "sg:postcode":"2900",
    "sg:province":"Antwerpen",
    "wof:name":"E. Van Eynde",
    "wof:placetype":"venue"
},
  "geometry": {"coordinates":[4.513147831,51.2599906921],"type":"Point"}
}