{
  "type": "Feature",
  "properties": {
    "addr:full":"Rue Des Chats 146 Bruxelles Bruxelles-Capitale 1082",
    "addr:housenumber":"146",
    "addr:postcode":"1082",
    "addr:street":"Rue Des Chats",
    "iso:country":"BE",
    "sg:address":"Rue Des Chats 146",
    "sg:city":"Bruxelles",
    "sg:classifiers":[
        {
            "category":"Professional",
            "subcategory":"Management & Consulting",
            "type":"Services"
        }
    ],
    "sg:phone":"+32 2 504 73 05",
    "sg:postcode":"1082",
    "sg:province":"Bruxelles-Capitale",
    "sg:tags":[
        "information"
    ],
    "wof:name":"S.i.d. - Services Informatiques S.a.",
    "wof:placetype":"venue"
},
  "geometry": {"coordinates":[4.2820658684,50.8620834351],"type":"Point"}
}