{
  "type": "Feature",
  "properties": {
    "addr:full":"Kerkelei 69 Schilde Antwerpen 2970",
    "addr:housenumber":"69",
    "addr:postcode":"2970",
    "addr:street":"Kerkelei",
    "iso:country":"BE",
    "sg:address":"Kerkelei 69",
    "sg:city":"Schilde",
    "sg:orig_category":"Brood, gebak and snoepgoed",
    "sg:phone":"+32 3 383 01 38",
    "sg:postcode":"2970",
    "sg:province":"Antwerpen",
    "wof:name":"Peeters",
    "wof:placetype":"venue"
},
  "geometry": {"coordinates":[4.5842380524,51.2365646362],"type":"Point"}
}