{
  "type": "Feature",
  "properties": {
    "addr:full":"Robijnstraat 1 Brugge West-Vlaanderen 8000",
    "addr:housenumber":"1",
    "addr:postcode":"8000",
    "addr:street":"Robijnstraat",
    "iso:country":"BE",
    "sg:address":"Robijnstraat 1",
    "sg:city":"Brugge",
    "sg:classifiers":[
        {
            "category":"Personal",
            "subcategory":"Beauty Salon",
            "type":"Services"
        }
    ],
    "sg:phone":"+32 50 33 66 40",
    "sg:postcode":"8000",
    "sg:province":"West-Vlaanderen",
    "sg:tags":[
        "lady",
        "-",
        "hairdressing"
    ],
    "wof:name":"Fidji Bvba",
    "wof:placetype":"venue"
},
  "geometry": {"coordinates":[3.2234179974,51.2111167908],"type":"Point"}
}