{
  "type": "Feature",
  "properties": {
    "iso:country":"BE",
    "sg:address":"Koerselsesteenweg 34",
    "sg:city":"Beringen",
    "sg:classifiers":[
        {
            "category":"Wholesale",
            "subcategory":"Medical Equipment & Supplies",
            "type":"Manufacturing & Wholesale Goods"
        }
    ],
    "sg:phone":"+32 11 45 25 80",
    "sg:postcode":"3580",
    "sg:province":"Limburg",
    "sg:tags":[
        "instrument",
        "apparatus"
    ],
    "wof:name":"Fysioplus",
    "wof:placetype":"venue"
},
  "geometry": {"coordinates":[5.2285628319,51.049495697],"type":"Point"}
}