{
  "type": "Feature",
  "properties": {
    "addr:full":"Statielei 69 Mortsel Antwerpen 2640",
    "addr:housenumber":"69",
    "addr:postcode":"2640",
    "addr:street":"Statielei",
    "iso:country":"BE",
    "sg:address":"Statielei 69",
    "sg:city":"Mortsel",
    "sg:orig_category":"Cr\u00e9dits divers",
    "sg:postcode":"2640",
    "sg:province":"Antwerpen",
    "wof:name":"Bancontact-mister Cash",
    "wof:placetype":"venue"
},
  "geometry": {"coordinates":[4.4524922371,51.170665741],"type":"Point"}
}