{
  "type": "Feature",
  "properties": {
    "addr:full":"Motstraat 37 Alken Limburg 3570",
    "addr:housenumber":"37",
    "addr:postcode":"3570",
    "addr:street":"Motstraat",
    "iso:country":"BE",
    "sg:address":"Motstraat 37",
    "sg:city":"Alken",
    "sg:classifiers":[
        {
            "category":"Retail",
            "subcategory":"Veterinary Services",
            "type":"Services"
        }
    ],
    "sg:phone":"+32 11 31 55 55",
    "sg:postcode":"3570",
    "sg:province":"Limburg",
    "sg:tags":[
        "veterinarian"
    ],
    "wof:name":"Theuwis S",
    "wof:placetype":"venue"
},
  "geometry": {"coordinates":[5.3088760376,50.8727722168],"type":"Point"}
}