{
  "type": "Feature",
  "properties": {
    "iso:country":"BE",
    "sg:address":"Route Du Lion 252-254",
    "sg:city":"Braine L'alleud (braine-l'alleud)",
    "sg:classifiers":[
        {
            "category":"Landmark",
            "subcategory":"Tourist Attraction",
            "type":"Public Place"
        }
    ],
    "sg:phone":"+32 2 385 19 12",
    "sg:postcode":"1420",
    "sg:province":"Brabant Wallon",
    "sg:tags":[
        "-",
        "tourism",
        "interest",
        "sight"
    ],
    "wof:name":"Butte Du Lion (la)",
    "wof:placetype":"venue"
},
  "geometry": {"coordinates":[-0.6697199941,47.4606246948],"type":"Point"}
}