{
  "type": "Feature",
  "properties": {
    "iso:country":"BE",
    "sg:address":"Steenkuilstraat 3",
    "sg:city":"Maasmechelen",
    "sg:orig_category":"Industri\u00eble and commerci\u00eble bouw",
    "sg:phone":"+32 89 76 42 68",
    "sg:postcode":"3630",
    "sg:province":"Limburg",
    "wof:name":"Bemong",
    "wof:placetype":"venue"
},
  "geometry": {"coordinates":[5.6897268295,50.9649734497],"type":"Point"}
}