{
  "type": "Feature",
  "properties": {
    "addr:full":"Grufflingen 51 Burg-reuland/burg-reuland Li\u00e8ge 4791",
    "addr:housenumber":"51",
    "addr:postcode":"4791",
    "addr:street":"Grufflingen",
    "iso:country":"BE",
    "sg:address":"Grufflingen 51",
    "sg:city":"Burg-reuland/burg-reuland",
    "sg:orig_category":"Rundveehouders",
    "sg:phone":"+32 80 32 93 66",
    "sg:postcode":"4791",
    "sg:province":"Li\u00e8ge",
    "wof:name":"Caecilia Thome",
    "wof:placetype":"venue"
},
  "geometry": {"coordinates":[6.0771751404,50.2173156738],"type":"Point"}
}