{
  "type": "Feature",
  "properties": {
    "iso:country":"BE",
    "sg:address":"Boulevard Des Canadiens 3",
    "sg:city":"Moeskroen/mouscron",
    "sg:orig_category":"Supermarch\u00e9s. Grands magasins",
    "sg:phone":"+32 56 48 73 46",
    "sg:postcode":"7711",
    "sg:province":"Hainaut",
    "wof:name":"Unic",
    "wof:placetype":"venue"
},
  "geometry": {"coordinates":[3.3098390102,50.7286834717],"type":"Point"}
}