{
  "type": "Feature",
  "properties": {
    "addr:full":"Kalmthoutse Steenweg 46 Wuustwezel Antwerpen 2990",
    "addr:housenumber":"46",
    "addr:postcode":"2990",
    "addr:street":"Kalmthoutse Steenweg",
    "iso:country":"BE",
    "sg:address":"Kalmthoutse Steenweg 46",
    "sg:city":"Wuustwezel",
    "sg:orig_category":"Studios photographiques",
    "sg:phone":"+32 3 669 69 16",
    "sg:postcode":"2990",
    "sg:province":"Antwerpen",
    "wof:name":"Fotostudio Focus",
    "wof:placetype":"venue"
},
  "geometry": {"coordinates":[4.5871510506,51.3897705078],"type":"Point"}
}