{
  "type": "Feature",
  "properties": {
    "addr:full":"Quai Notre-dame 18 Tournai Hainaut 7500",
    "addr:housenumber":"18",
    "addr:postcode":"7500",
    "addr:street":"Quai Notre-Dame",
    "iso:country":"BE",
    "sg:address":"Quai Notre-dame 18",
    "sg:city":"Tournai",
    "sg:classifiers":[
        {
            "category":"Restaurant",
            "type":"Food & Drink"
        }
    ],
    "sg:phone":"+32 69 23 29 22",
    "sg:postcode":"7500",
    "sg:province":"Hainaut",
    "wof:name":"P\u00c8res Au Quai",
    "wof:placetype":"venue"
},
  "geometry": {"coordinates":[3.3893771172,50.6089363098],"type":"Point"}
}