{
  "type": "Feature",
  "properties": {
    "iso:country":"BE",
    "sg:address":"Krom Dagwand 14",
    "sg:city":"Asse",
    "sg:orig_category":"Installatie van metalen schrijnwerk",
    "sg:phone":"+32 2 452 53 07",
    "sg:postcode":"1730",
    "sg:province":"Vlaams-Brabant",
    "wof:name":"Michel Pauwels",
    "wof:placetype":"venue"
},
  "geometry": {"coordinates":[4.1525421143,50.9200668335],"type":"Point"}
}