{
  "type": "Feature",
  "properties": {
    "addr:full":"Rue Du Heysel 62-66 Bruxelles Bruxelles-Capitale 1020",
    "addr:housenumber":"62-66",
    "addr:postcode":"1020",
    "addr:street":"Rue Du Heysel",
    "iso:country":"BE",
    "sg:address":"Rue Du Heysel 62-66",
    "sg:city":"Bruxelles",
    "sg:classifiers":[
        {
            "category":"Banks & Credit Unions",
            "subcategory":"Financial Services",
            "type":"Services"
        }
    ],
    "sg:phone":"+32 2 478 56 46",
    "sg:postcode":"1020",
    "sg:province":"Bruxelles-Capitale",
    "sg:tags":[
        "debt",
        "recovery"
    ],
    "wof:name":"R.d.t.c. Sa",
    "wof:placetype":"venue"
},
  "geometry": {"coordinates":[4.3410749435,50.8911323547],"type":"Point"}
}