{
  "type": "Feature",
  "properties": {
    "addr:full":"Dahliastraat 8 Ledegem West-Vlaanderen 8880",
    "addr:housenumber":"8",
    "addr:postcode":"8880",
    "addr:street":"Dahliastraat",
    "iso:country":"BE",
    "sg:address":"Dahliastraat 8",
    "sg:city":"Ledegem",
    "sg:classifiers":[
        {
            "category":"Personal",
            "subcategory":"Beauty Salon",
            "type":"Services"
        }
    ],
    "sg:phone":"+32 56 50 10 92",
    "sg:postcode":"8880",
    "sg:province":"West-Vlaanderen",
    "sg:tags":[
        "de",
        "coiffure"
    ],
    "wof:name":"Coiffure Leen",
    "wof:placetype":"venue"
},
  "geometry": {"coordinates":[3.1270749569,50.8548545837],"type":"Point"}
}