{
  "type": "Feature",
  "properties": {
    "iso:country":"BE",
    "sg:address":"Graankaai 3",
    "sg:city":"Roeselare",
    "sg:classifiers":[
        {
            "category":"Home & Garden",
            "subcategory":"Garden Supply",
            "type":"Retail Goods"
        }
    ],
    "sg:phone":"+32 51 22 72 20",
    "sg:postcode":"8800",
    "sg:province":"West-Vlaanderen",
    "sg:tags":[
        "fertilizer",
        "organic"
    ],
    "wof:name":"Jan Sterckx Nv",
    "wof:placetype":"venue"
},
  "geometry": {"coordinates":[3.1536519527,50.9447479248],"type":"Point"}
}