{
  "type": "Feature",
  "properties": {
    "iso:country":"BE",
    "sg:address":"La Marli\u00e8re 7",
    "sg:city":"Wellin",
    "sg:orig_category":"Bonsa\u00ef",
    "sg:phone":"+32 84 38 89 60",
    "sg:postcode":"6920",
    "sg:province":"Luxembourg",
    "wof:name":"Bonsa\u00ef Passion",
    "wof:placetype":"venue"
},
  "geometry": {"coordinates":[5.1080141068,50.0880393982],"type":"Point"}
}