{
  "type": "Feature",
  "properties": {
    "iso:country":"BE",
    "sg:address":"Lodewijk De Koninckstraat 23",
    "sg:city":"Turnhout",
    "sg:classifiers":[
        {
            "category":"Shopping",
            "subcategory":"Bicycles & Sporting Goods",
            "type":"Retail Goods"
        }
    ],
    "sg:phone":"+32 14 41 35 47",
    "sg:postcode":"2300",
    "sg:province":"Antwerpen",
    "sg:tags":[
        "sport",
        "-"
    ],
    "wof:name":"Tafeltenniscentrum",
    "wof:placetype":"venue"
},
  "geometry": {"coordinates":[4.9285988808,51.3221931458],"type":"Point"}
}