{
  "type": "Feature",
  "properties": {
    "iso:country":"BE",
    "sg:address":"Tiensestraat 45",
    "sg:city":"Landen",
    "sg:classifiers":[
        {
            "category":"Home & Garden",
            "subcategory":"Home Furnishings",
            "type":"Retail Goods"
        }
    ],
    "sg:phone":"+32 477 36 52 71",
    "sg:postcode":"3400",
    "sg:province":"Vlaams-Brabant",
    "sg:tags":[
        "interior",
        "decoration"
    ],
    "wof:name":"Pol Net Deco",
    "wof:placetype":"venue"
},
  "geometry": {"coordinates":[5.0763320923,50.7588424683],"type":"Point"}
}