{
  "type": "Feature",
  "properties": {
    "addr:full":"Rue De La Station 81 Fleurus Hainaut 6220",
    "addr:housenumber":"81",
    "addr:postcode":"6220",
    "addr:street":"Rue De La Station",
    "iso:country":"BE",
    "sg:address":"Rue De La Station 81",
    "sg:city":"Fleurus",
    "sg:orig_category":"Agences d'exp\u00e9dition",
    "sg:phone":"+32 71 81 72 20",
    "sg:postcode":"6220",
    "sg:province":"Hainaut",
    "wof:name":"J.m.c.diffusion",
    "wof:placetype":"venue"
},
  "geometry": {"coordinates":[4.5467309952,50.4832878113],"type":"Point"}
}