{
  "type": "Feature",
  "properties": {
    "addr:full":"Plezantstraat 2 Hamme Oost-Vlaanderen 9220",
    "addr:housenumber":"2",
    "addr:postcode":"9220",
    "addr:street":"Plezantstraat",
    "iso:country":"BE",
    "sg:address":"Plezantstraat 2",
    "sg:city":"Hamme",
    "sg:classifiers":[
        {
            "category":"Banks & Credit Unions",
            "subcategory":"Investment Brokerage",
            "type":"Services"
        }
    ],
    "sg:phone":"+32 52 48 14 52",
    "sg:postcode":"9220",
    "sg:province":"Oost-Vlaanderen",
    "sg:tags":[
        "jean",
        "casual",
        "wear"
    ],
    "wof:name":"Dock 2",
    "wof:placetype":"venue"
},
  "geometry": {"coordinates":[4.1358289719,51.0964050293],"type":"Point"}
}