{
  "type": "Feature",
  "properties": {
    "iso:country":"BE",
    "sg:address":"Rue De La Vall\u00c9e 4",
    "sg:city":"Saint-georges-sur-meuse",
    "sg:orig_category":"Architectes",
    "sg:phone":"+32 4 359 61 71",
    "sg:postcode":"4470",
    "sg:province":"Li\u00e8ge",
    "wof:name":"Marguerite Mauhin",
    "wof:placetype":"venue"
},
  "geometry": {"coordinates":[5.3597831726,50.6036911011],"type":"Point"}
}