{
  "type": "Feature",
  "properties": {
    "addr:full":"Legen Heirweg 77b Gavere (asper) Oost-Vlaanderen 9890",
    "addr:housenumber":"77b",
    "addr:postcode":"9890",
    "addr:street":"Legen Heirweg",
    "iso:country":"BE",
    "sg:address":"Legen Heirweg 77b",
    "sg:city":"Gavere (asper)",
    "sg:classifiers":[
        {
            "category":"Home & Garden",
            "subcategory":"Carpets & Floor Coverings",
            "type":"Retail Goods"
        }
    ],
    "sg:phone":"+32 9 390 80 82",
    "sg:postcode":"9890",
    "sg:province":"Oost-Vlaanderen",
    "sg:tags":[
        "parquet"
    ],
    "wof:name":"Stemafloor Nv",
    "wof:placetype":"venue"
},
  "geometry": {"coordinates":[3.6469240189,50.9349250793],"type":"Point"}
}