{
  "type": "Feature",
  "properties": {
    "addr:full":"Papenbruggestraat 66 Turnhout Antwerpen 2300",
    "addr:housenumber":"66",
    "addr:postcode":"2300",
    "addr:street":"Papenbruggestraat",
    "iso:country":"BE",
    "sg:address":"Papenbruggestraat 66",
    "sg:city":"Turnhout",
    "sg:orig_category":"Architectes",
    "sg:phone":"+32 14 43 80 07",
    "sg:postcode":"2300",
    "sg:province":"Antwerpen",
    "wof:name":"Patrick Verhamme",
    "wof:placetype":"venue"
},
  "geometry": {"coordinates":[4.9452981949,51.3133201599],"type":"Point"}
}