{
  "type": "Feature",
  "properties": {
    "addr:full":"Gistelsesteenweg 146 Varsenare West-Vlaanderen 8490",
    "addr:housenumber":"146",
    "addr:postcode":"8490",
    "addr:street":"Gistelsesteenweg",
    "iso:country":"BE",
    "sg:address":"Gistelsesteenweg 146",
    "sg:city":"Varsenare",
    "sg:orig_category":"Bloemen and planten",
    "sg:phone":"+32 50 38 55 34",
    "sg:postcode":"8490",
    "sg:province":"West-Vlaanderen",
    "wof:name":"Floresco",
    "wof:placetype":"venue"
},
  "geometry": {"coordinates":[3.1385629177,51.1815299988],"type":"Point"}
}