{
  "type": "Feature",
  "properties": {
    "addr:full":"Rue De La Bruy\u00e8re 7 Lasne (lasne-chapelle-saint-lambert) Brabant Wallon 1380",
    "addr:housenumber":"7",
    "addr:postcode":"1380",
    "addr:street":"Rue De La Bruye\u0300Re;Wallon",
    "iso:country":"BE",
    "sg:address":"Rue De La Bruy\u00e8re 7",
    "sg:city":"Lasne (lasne-chapelle-saint-lambert)",
    "sg:classifiers":[
        {
            "category":"Building & Trades",
            "subcategory":"Electrical",
            "type":"Services"
        }
    ],
    "sg:phone":"+32 2 633 56 08",
    "sg:postcode":"1380",
    "sg:province":"Brabant Wallon",
    "sg:tags":[
        "electric",
        "-",
        "housewiring",
        "contractor"
    ],
    "wof:name":"Dagniau P",
    "wof:placetype":"venue"
},
  "geometry": {"coordinates":[4.5046200752,50.7024230957],"type":"Point"}
}