{
  "type": "Feature",
  "properties": {
    "addr:full":"Bree\u00cbrsteenweg 290 Kinrooi Limburg 3640",
    "addr:housenumber":"290",
    "addr:postcode":"3640",
    "addr:street":"Breee\u0308Rsteenweg",
    "iso:country":"BE",
    "sg:address":"Bree\u00cbrsteenweg 290",
    "sg:city":"Kinrooi",
    "sg:classifiers":[
        {
            "category":"Fast Food",
            "type":"Food & Drink"
        }
    ],
    "sg:phone":"+32 89 46 70 39",
    "sg:postcode":"3640",
    "sg:province":"Limburg",
    "sg:tags":[
        "meeneem",
        "restaurant"
    ],
    "wof:name":"Frituur Gi-gi",
    "wof:placetype":"venue"
},
  "geometry": {"coordinates":[5.7587652206,51.1448097229],"type":"Point"}
}