{
  "type": "Feature",
  "properties": {
    "iso:country":"BE",
    "sg:address":"Zilverberklaan 10",
    "sg:city":"Putte",
    "sg:classifiers":[
        {
            "category":"Restaurant",
            "type":"Food & Drink"
        }
    ],
    "sg:phone":"+32 15 24 79 99",
    "sg:postcode":"2580",
    "sg:province":"Antwerpen",
    "wof:name":"Den Pottelikker",
    "wof:placetype":"venue"
},
  "geometry": {"coordinates":[4.6691679955,51.0764350891],"type":"Point"}
}