{
  "type": "Feature",
  "properties": {
    "addr:full":"Zoutbrugstraat 12 Box 3 Herk-de-stad Limburg 3540",
    "addr:housenumber":"12;3",
    "addr:postcode":"3540",
    "addr:street":"Zoutbrugstraat;Box",
    "iso:country":"BE",
    "sg:address":"Zoutbrugstraat 12 Box 3",
    "sg:city":"Herk-de-stad",
    "sg:classifiers":[
        {
            "category":"Communications",
            "type":"Services"
        }
    ],
    "sg:phone":"+32 13 55 53 06",
    "sg:postcode":"3540",
    "sg:province":"Limburg",
    "sg:tags":[
        "translator"
    ],
    "wof:name":"Dessart E",
    "wof:placetype":"venue"
},
  "geometry": {"coordinates":[5.1665501595,50.9400253296],"type":"Point"}
}