{
  "type": "Feature",
  "properties": {
    "addr:full":"Rue De Goz\u00c9e 552 Montigny-le-tilleul Hainaut 6110",
    "addr:housenumber":"552",
    "addr:postcode":"6110",
    "addr:street":"Rue De Goze\u0301E",
    "iso:country":"BE",
    "sg:address":"Rue De Goz\u00c9e 552",
    "sg:city":"Montigny-le-tilleul",
    "sg:orig_category":"Ordinateurs and \u00e9quipement informatique",
    "sg:phone":"+32 71 56 06 96",
    "sg:postcode":"6110",
    "sg:province":"Hainaut",
    "wof:name":"Patrick Lixon",
    "wof:placetype":"venue"
},
  "geometry": {"coordinates":[4.3642320633,50.3701324463],"type":"Point"}
}