{
  "type": "Feature",
  "properties": {
    "iso:country":"BE",
    "sg:address":"Avenue Des Combattants 17",
    "sg:city":"Vis\u00e9",
    "sg:classifiers":[
        {
            "category":"Health Services",
            "subcategory":"Health Practitioner",
            "type":"Services"
        }
    ],
    "sg:phone":"+32 4 379 45 60",
    "sg:postcode":"4600",
    "sg:province":"Li\u00e8ge",
    "sg:tags":[
        "osteopath"
    ],
    "wof:name":"Mailleu E",
    "wof:placetype":"venue"
},
  "geometry": {"coordinates":[5.697658062,50.7365684509],"type":"Point"}
}