{
  "type": "Feature",
  "properties": {
    "iso:country":"BE",
    "sg:address":"Artoisstraat 25",
    "sg:city":"Wevelgem",
    "sg:classifiers":[
        {
            "category":"Conference Center",
            "type":"Public Place"
        }
    ],
    "sg:phone":"+32 56 42 04 72",
    "sg:postcode":"8560",
    "sg:province":"West-Vlaanderen",
    "sg:tags":[
        "chair",
        "easy"
    ],
    "wof:name":"Novosit Nv",
    "wof:placetype":"venue"
},
  "geometry": {"coordinates":[3.1784870625,50.8060874939],"type":"Point"}
}