{
  "type": "Feature",
  "properties": {
    "addr:full":"Boulevard L\u00e9opold 97 Tournai Hainaut 7500",
    "addr:housenumber":"97",
    "addr:postcode":"7500",
    "addr:street":"Boulevard Le\u0301Opold",
    "iso:country":"BE",
    "sg:address":"Boulevard L\u00e9opold 97",
    "sg:city":"Tournai",
    "sg:classifiers":[
        {
            "category":"Insurance",
            "subcategory":"Insurance Agent",
            "type":"Services"
        }
    ],
    "sg:phone":"+32 69 22 12 93",
    "sg:postcode":"7500",
    "sg:province":"Hainaut",
    "sg:tags":[
        "broker"
    ],
    "wof:name":"Wilfart M",
    "wof:placetype":"venue"
},
  "geometry": {"coordinates":[3.3796041012,50.6112823486],"type":"Point"}
}