{
  "type": "Feature",
  "properties": {
    "addr:full":"Industrieweg 20 Hoogstraten Antwerpen 2320",
    "addr:housenumber":"20",
    "addr:postcode":"2320",
    "addr:street":"Industrieweg",
    "iso:country":"BE",
    "sg:address":"Industrieweg 20",
    "sg:city":"Hoogstraten",
    "sg:classifiers":[
        {
            "category":"Industrial Area",
            "type":"Public Place"
        }
    ],
    "sg:phone":"+32 3 314 47 47",
    "sg:postcode":"2320",
    "sg:province":"Antwerpen",
    "sg:tags":[
        "shed"
    ],
    "wof:name":"Martens Metaalkonstructie Nv",
    "wof:placetype":"venue"
},
  "geometry": {"coordinates":[4.736934185,51.3893966675],"type":"Point"}
}