{
  "type": "Feature",
  "properties": {
    "iso:country":"BE",
    "sg:address":"Kartuizersvest 7",
    "sg:city":"Lier",
    "sg:orig_category":"Opticiens",
    "sg:phone":"+32 3 480 84 48",
    "sg:postcode":"2500",
    "sg:province":"Antwerpen",
    "wof:name":"Trioptic",
    "wof:placetype":"venue"
},
  "geometry": {"coordinates":[4.5677700043,51.1336402893],"type":"Point"}
}