{
  "type": "Feature",
  "properties": {
    "addr:full":"Ouwegemstraat 43 Zingem (ouwegem) Oost-Vlaanderen 9750",
    "addr:housenumber":"43",
    "addr:postcode":"9750",
    "addr:street":"Ouwegemstraat",
    "iso:country":"BE",
    "sg:address":"Ouwegemstraat 43",
    "sg:city":"Zingem (ouwegem)",
    "sg:classifiers":[
        {
            "category":"Utilities",
            "subcategory":"Telephone",
            "type":"Services"
        }
    ],
    "sg:phone":"+32 9 384 87 38",
    "sg:postcode":"9750",
    "sg:province":"Oost-Vlaanderen",
    "sg:tags":[
        "-",
        "internet"
    ],
    "wof:name":"Text And Data Care",
    "wof:placetype":"venue"
},
  "geometry": {"coordinates":[3.6519870758,50.9060554504],"type":"Point"}
}