{
  "type": "Feature",
  "properties": {
    "addr:full":"Ten Akkerdreef 135 Kortrijk West-Vlaanderen 8500",
    "addr:housenumber":"135",
    "addr:postcode":"8500",
    "addr:street":"Ten Akkerdreef",
    "iso:country":"BE",
    "sg:address":"Ten Akkerdreef 135",
    "sg:city":"Kortrijk",
    "sg:orig_category":"Blanchisseries and teintureries",
    "sg:phone":"+32 56 21 12 77",
    "sg:postcode":"8500",
    "sg:province":"West-Vlaanderen",
    "wof:name":"Nova",
    "wof:placetype":"venue"
},
  "geometry": {"coordinates":[3.278247118,50.8223304749],"type":"Point"}
}