{
  "type": "Feature",
  "properties": {
    "iso:country":"BE",
    "sg:address":"Maurits Sacr\u00c9straat 42",
    "sg:city":"Merchtem",
    "sg:orig_category":"Enseignement maternel and primaire",
    "sg:phone":"+32 52 37 18 53",
    "sg:postcode":"1785",
    "sg:province":"Vlaams-Brabant",
    "wof:name":"Vrije Lagere School",
    "wof:placetype":"venue"
},
  "geometry": {"coordinates":[4.2349338531,50.9537353516],"type":"Point"}
}