{
  "type": "Feature",
  "properties": {
    "iso:country":"BE",
    "sg:address":"Boomsesteenweg 1000",
    "sg:city":"Antwerpen",
    "sg:classifiers":[
        {
            "category":"Professional",
            "subcategory":"Engineering",
            "type":"Services"
        }
    ],
    "sg:phone":"+32 3 877 28 55",
    "sg:postcode":"2610",
    "sg:province":"Antwerpen",
    "sg:tags":[
        "machine",
        "-",
        "mechanical"
    ],
    "wof:name":"Intercommunale Voor Slib- En Vuilverwijdering Cvba",
    "wof:placetype":"venue"
},
  "geometry": {"coordinates":[4.3946051598,51.1691131592],"type":"Point"}
}