{
  "type": "Feature",
  "properties": {
    "addr:full":"Beekseweg 23 Ravels (poppel) Antwerpen 2382",
    "addr:housenumber":"23",
    "addr:postcode":"2382",
    "addr:street":"Beekseweg",
    "iso:country":"BE",
    "sg:address":"Beekseweg 23",
    "sg:city":"Ravels (poppel)",
    "sg:classifiers":[
        {
            "category":"Insurance",
            "subcategory":"Insurance Agent",
            "type":"Services"
        }
    ],
    "sg:phone":"+32 14 65 15 76",
    "sg:postcode":"2382",
    "sg:province":"Antwerpen",
    "sg:tags":[
        "broker"
    ],
    "wof:name":"Braaksma",
    "wof:placetype":"venue"
},
  "geometry": {"coordinates":[5.041768074,51.4469108582],"type":"Point"}
}