{
  "type": "Feature",
  "properties": {
    "addr:full":"Avenue Louis Lepoutre 54 Bruxelles (ixelles) Bruxelles-Capitale 1050",
    "addr:housenumber":"54",
    "addr:postcode":"1050",
    "addr:street":"Avenue Louis Lepoutre",
    "iso:country":"BE",
    "sg:address":"Avenue Louis Lepoutre 54",
    "sg:city":"Bruxelles (ixelles)",
    "sg:classifiers":[
        {
            "category":"Professional",
            "subcategory":"Art Services",
            "type":"Services"
        }
    ],
    "sg:phone":"+32 2 345 35 35",
    "sg:postcode":"1050",
    "sg:province":"Bruxelles-Capitale",
    "sg:tags":[
        "realization",
        "audio-visual"
    ],
    "wof:name":"Buisseret J-l",
    "wof:placetype":"venue"
},
  "geometry": {"coordinates":[4.3577919006,50.8187789917],"type":"Point"}
}