{
  "type": "Feature",
  "properties": {
    "addr:full":"Rue Des Sabli\u00c8res 176 Chatelet Hainaut 6200",
    "addr:housenumber":"176",
    "addr:postcode":"chatelet;6200",
    "addr:street":"Rue Des Sablie\u0300Res",
    "iso:country":"BE",
    "sg:address":"Rue Des Sabli\u00c8res 176",
    "sg:city":"Chatelet",
    "sg:orig_category":"Instituts de beaut\u00e9",
    "sg:phone":"+32 71 38 07 08",
    "sg:postcode":"6200",
    "sg:province":"Hainaut",
    "wof:name":"Monique Sibille",
    "wof:placetype":"venue"
},
  "geometry": {"coordinates":[4.5331687927,50.3951225281],"type":"Point"}
}