{
  "type": "Feature",
  "properties": {
    "addr:full":"Rodenbachstraat 42 Ingelmunster West-Vlaanderen 8770",
    "addr:housenumber":"42",
    "addr:postcode":"8770",
    "addr:street":"Rodenbachstraat",
    "iso:country":"BE",
    "sg:address":"Rodenbachstraat 42",
    "sg:city":"Ingelmunster",
    "sg:classifiers":[
        {
            "category":"Shopping",
            "subcategory":"Discount & Variety Stores",
            "type":"Retail Goods"
        }
    ],
    "sg:phone":"+32 51 31 50 78",
    "sg:postcode":"8770",
    "sg:province":"West-Vlaanderen",
    "sg:tags":[
        "shop",
        "clearers",
        "curiosity",
        "furniture"
    ],
    "wof:name":"Vansteenkiste L",
    "wof:placetype":"venue"
},
  "geometry": {"coordinates":[3.2544798851,50.926738739],"type":"Point"}
}