{
  "type": "Feature",
  "properties": {
    "iso:country":"BE",
    "sg:address":"Rue Du Charnois 28",
    "sg:city":"Ottignies-louvain-la-neuve",
    "sg:orig_category":"Gespecialiseerde residenti\u00eble bouw Loodgieterij, verwarming and sanitaire installaties Zwembadinstal",
    "sg:phone":"+32 10 41 01 36",
    "sg:postcode":"1342",
    "sg:province":"Brabant Wallon",
    "wof:name":"Dromursec Isotechnic",
    "wof:placetype":"venue"
},
  "geometry": {"coordinates":[4.5418539047,50.6845092773],"type":"Point"}
}