{
  "type": "Feature",
  "properties": {
    "iso:country":"BE",
    "sg:address":"Malderendorp 15",
    "sg:city":"Londerzeel (malderen)",
    "sg:classifiers":[
        {
            "category":"Shopping",
            "subcategory":"Florist",
            "type":"Retail Goods"
        }
    ],
    "sg:phone":"+32 52 33 34 25",
    "sg:postcode":"1840",
    "sg:province":"Vlaams-Brabant",
    "wof:name":"Prieeltje ('t)",
    "wof:placetype":"venue"
},
  "geometry": {"coordinates":[4.2450537682,51.0201644897],"type":"Point"}
}