{
  "type": "Feature",
  "properties": {
    "iso:country":"BE",
    "sg:address":"Rue De B\u00e9tissart 9b",
    "sg:city":"Ath (ormeignies)",
    "sg:classifiers":[
        {
            "category":"Real Estate",
            "subcategory":"Architect",
            "type":"Services"
        }
    ],
    "sg:phone":"+32 68 84 27 71",
    "sg:postcode":"7802",
    "sg:province":"Hainaut",
    "wof:name":"Picron St",
    "wof:placetype":"venue"
},
  "geometry": {"coordinates":[3.7527279854,50.5938110352],"type":"Point"}
}