{
  "type": "Feature",
  "properties": {
    "addr:full":"Avenue Hellevelt 30 Bruxelles (uccle) Bruxelles-Capitale 1180",
    "addr:housenumber":"30",
    "addr:postcode":"1180",
    "addr:street":"Avenue Hellevelt",
    "iso:country":"BE",
    "sg:address":"Avenue Hellevelt 30",
    "sg:city":"Bruxelles (uccle)",
    "sg:classifiers":[
        {
            "category":"Professional",
            "subcategory":"Accounting & Tax Preparation",
            "type":"Services"
        }
    ],
    "sg:phone":"+32 2 372 28 03",
    "sg:postcode":"1180",
    "sg:province":"Bruxelles-Capitale",
    "sg:tags":[
        "bookkeeper"
    ],
    "wof:name":"Gerome A",
    "wof:placetype":"venue"
},
  "geometry": {"coordinates":[4.3426017761,50.7930145264],"type":"Point"}
}