{
  "type": "Feature",
  "properties": {
    "addr:full":"Rue Paepsem 136 Bruxelles (anderlecht) Bruxelles-Capitale 1070",
    "addr:housenumber":"136",
    "addr:postcode":"1070",
    "addr:street":"Rue Paepsem",
    "iso:country":"BE",
    "sg:address":"Rue Paepsem 136",
    "sg:city":"Bruxelles (anderlecht)",
    "sg:classifiers":[
        {
            "category":"Professional",
            "subcategory":"Engineering",
            "type":"Services"
        }
    ],
    "sg:phone":"+32 2 346 64 84",
    "sg:postcode":"1070",
    "sg:province":"Bruxelles-Capitale",
    "sg:tags":[
        "technical",
        "equipment",
        "offices-"
    ],
    "wof:name":"Etg Sa",
    "wof:placetype":"venue"
},
  "geometry": {"coordinates":[4.3149709702,50.822429657],"type":"Point"}
}