{
  "type": "Feature",
  "properties": {
    "addr:full":"Grote Herreweg 127 Kluisbergen Oost-Vlaanderen 9690",
    "addr:housenumber":"127",
    "addr:postcode":"9690",
    "addr:street":"Grote Herreweg",
    "iso:country":"BE",
    "sg:address":"Grote Herreweg 127",
    "sg:city":"Kluisbergen",
    "sg:classifiers":[
        {
            "category":"Cafe",
            "type":"Food & Drink"
        }
    ],
    "sg:phone":"+32 55 38 70 38",
    "sg:postcode":"9690",
    "sg:province":"Oost-Vlaanderen",
    "sg:tags":[
        "caf\u00e9s"
    ],
    "wof:name":"Dirk Verbrugghe",
    "wof:placetype":"venue"
},
  "geometry": {"coordinates":[3.4862890244,50.7722854614],"type":"Point"}
}