{
  "type": "Feature",
  "properties": {
    "addr:full":"Akkerstraat 64 Brugge West-Vlaanderen 8310",
    "addr:housenumber":"64",
    "addr:postcode":"8310",
    "addr:street":"Akkerstraat",
    "iso:country":"BE",
    "sg:address":"Akkerstraat 64",
    "sg:city":"Brugge",
    "sg:orig_category":"Boekhouders",
    "sg:phone":"+32 50 35 96 95",
    "sg:postcode":"8310",
    "sg:province":"West-Vlaanderen",
    "wof:name":"Walter Serroels",
    "wof:placetype":"venue"
},
  "geometry": {"coordinates":[3.2568659782,51.2105178833],"type":"Point"}
}