{
  "type": "Feature",
  "properties": {
    "addr:full":"Rogierlaan 188 Schaarbeek/schaerbeek Bruxelles-Capitale 1030",
    "addr:housenumber":"188",
    "addr:postcode":"1030",
    "addr:street":"Rogierlaan",
    "iso:country":"BE",
    "sg:address":"Rogierlaan 188",
    "sg:city":"Schaarbeek/schaerbeek",
    "sg:orig_category":"Boekhouders",
    "sg:phone":"+32 2 215 11 24",
    "sg:postcode":"1030",
    "sg:province":"Bruxelles-Capitale",
    "wof:name":"August Deconinck",
    "wof:placetype":"venue"
},
  "geometry": {"coordinates":[4.3851809502,50.8579177856],"type":"Point"}
}