{
  "type": "Feature",
  "properties": {
    "addr:full":"Rue Des Bouchers 14 Jemeppe-sur-sambre Namur 5190",
    "addr:housenumber":"14",
    "addr:postcode":"5190",
    "addr:street":"Rue Des Bouchers",
    "iso:country":"BE",
    "sg:address":"Rue Des Bouchers 14",
    "sg:city":"Jemeppe-sur-sambre",
    "sg:orig_category":"Ordinateurs and \u00e9quipement informatique",
    "sg:phone":"+32 71 78 62 38",
    "sg:postcode":"5190",
    "sg:province":"Namur",
    "wof:name":"Micro-land",
    "wof:placetype":"venue"
},
  "geometry": {"coordinates":[4.6952161789,50.466884613],"type":"Point"}
}