{
  "type": "Feature",
  "properties": {
    "addr:full":"Kruibekesteenweg 202 Beveren Oost-Vlaanderen 9120",
    "addr:housenumber":"202",
    "addr:postcode":"9120",
    "addr:street":"Kruibekesteenweg",
    "iso:country":"BE",
    "sg:address":"Kruibekesteenweg 202",
    "sg:city":"Beveren",
    "sg:orig_category":"Boissons",
    "sg:phone":"+32 3 775 93 19",
    "sg:postcode":"9120",
    "sg:province":"Oost-Vlaanderen",
    "wof:name":"De Beverse Drankenhal",
    "wof:placetype":"venue"
},
  "geometry": {"coordinates":[4.2654452324,51.2003822327],"type":"Point"}
}