{
  "type": "Feature",
  "properties": {
    "iso:country":"BE",
    "sg:address":"Chauss\u00c9e De Bruxelles 4",
    "sg:city":"La Bruyere",
    "sg:orig_category":"Herstellingen and onderhoud aan huis voor voertuigen Metaalafval, schrootrecyclage and sloperijen",
    "sg:phone":"+32 81 56 88 88",
    "sg:postcode":"5081",
    "sg:province":"Namur",
    "wof:name":"S.o.s. Utilitaires",
    "wof:placetype":"venue"
},
  "geometry": {"coordinates":[4.7882180214,50.5460700989],"type":"Point"}
}