{
  "type": "Feature",
  "properties": {
    "addr:full":"Meerweg 151 Sint-pieters-leeuw Vlaams-Brabant 1601",
    "addr:housenumber":"151",
    "addr:postcode":"1601",
    "addr:street":"Meerweg",
    "iso:country":"BE",
    "sg:address":"Meerweg 151",
    "sg:city":"Sint-pieters-leeuw",
    "sg:orig_category":"Paramedische behandelingen",
    "sg:phone":"+32 2 331 24 61",
    "sg:postcode":"1601",
    "sg:province":"Vlaams-Brabant",
    "wof:name":"De Rong\u00c9",
    "wof:placetype":"venue"
},
  "geometry": {"coordinates":[4.2864041328,50.7845954895],"type":"Point"}
}