{
  "type": "Feature",
  "properties": {
    "iso:country":"BE",
    "sg:address":"Maasbone 8",
    "sg:city":"Maldegem",
    "sg:orig_category":"Eleveurs de bovins",
    "sg:phone":"+32 50 71 15 88",
    "sg:postcode":"9991",
    "sg:province":"Oost-Vlaanderen",
    "wof:name":"Simonne Meuleman",
    "wof:placetype":"venue"
},
  "geometry": {"coordinates":[3.486880064,51.2046394348],"type":"Point"}
}