{
  "type": "Feature",
  "properties": {
    "iso:country":"BE",
    "sg:address":"Gasthuisstraat 17",
    "sg:city":"Opwijk",
    "sg:orig_category":"Epiceries. Supermarch\u00e9s",
    "sg:phone":"+32 52 35 62 93",
    "sg:postcode":"1745",
    "sg:province":"Vlaams-Brabant",
    "wof:name":"Prima Pa De Bondt",
    "wof:placetype":"venue"
},
  "geometry": {"coordinates":[4.191242218,50.9684944153],"type":"Point"}
}