{
  "type": "Feature",
  "properties": {
    "addr:full":"Bohemen 45ba Wichelen Oost-Vlaanderen 9260",
    "addr:housenumber":"45ba",
    "addr:postcode":"9260",
    "addr:street":"Bohemen",
    "iso:country":"BE",
    "sg:address":"Bohemen 45ba",
    "sg:city":"Wichelen",
    "sg:orig_category":"Verplichte sociale verzekeringen",
    "sg:phone":"+32 52 42 46 29",
    "sg:postcode":"9260",
    "sg:province":"Oost-Vlaanderen",
    "wof:name":"Bond Moyson",
    "wof:placetype":"venue"
},
  "geometry": {"coordinates":[3.9821820259,51.0033226013],"type":"Point"}
}