{
  "type": "Feature",
  "properties": {
    "iso:country":"BE",
    "sg:address":"Albert Scheuremanspark 2",
    "sg:city":"Zedelgem",
    "sg:orig_category":"Banken and kredietinstellingen",
    "sg:phone":"+32 50 82 34 95",
    "sg:postcode":"8210",
    "sg:province":"West-Vlaanderen",
    "wof:name":"Dipo",
    "wof:placetype":"venue"
},
  "geometry": {"coordinates":[3.1458399296,51.1376457214],"type":"Point"}
}