{
  "type": "Feature",
  "properties": {
    "iso:country":"BE",
    "sg:address":"Rue Kaeramis 47",
    "sg:city":"La Louviere",
    "sg:orig_category":"Meubles Fab. Eclairage et \u00e9quipements du foyer. Meubles D\u00e9taillants, Am\u00e9nagement de B\u00e2timents et de ",
    "sg:phone":"+32 64 22 38 73",
    "sg:postcode":"7100",
    "sg:province":"Hainaut",
    "wof:name":"Maison Art & Formes",
    "wof:placetype":"venue"
},
  "geometry": {"coordinates":[4.1852679253,50.4768218994],"type":"Point"}
}