{
  "type": "Feature",
  "properties": {
    "addr:full":"Place Loix 7 Bruxelles (saint-gilles) Bruxelles-Capitale 1060",
    "addr:housenumber":"7",
    "addr:postcode":"1060",
    "addr:street":"Place Loix",
    "iso:country":"BE",
    "sg:address":"Place Loix 7",
    "sg:city":"Bruxelles (saint-gilles)",
    "sg:classifiers":[
        {
            "category":"Professional",
            "subcategory":"Art Services",
            "type":"Services"
        }
    ],
    "sg:phone":"+32 2 543 13 80",
    "sg:postcode":"1060",
    "sg:province":"Bruxelles-Capitale",
    "sg:tags":[
        "design",
        "packing",
        "-",
        "realization"
    ],
    "wof:name":"In Spirit Group Sa",
    "wof:placetype":"venue"
},
  "geometry": {"coordinates":[4.3530640602,50.8316955566],"type":"Point"}
}