{
  "type": "Feature",
  "properties": {
    "addr:full":"Rue Denis Verdonck 10 Anderlecht Bruxelles-Capitale 1070",
    "addr:housenumber":"10",
    "addr:postcode":"1070",
    "addr:street":"Rue Denis Verdonck",
    "iso:country":"BE",
    "sg:address":"Rue Denis Verdonck 10",
    "sg:city":"Anderlecht",
    "sg:orig_category":"Installation \u00e9lectrique r\u00e9sidentielle",
    "sg:phone":"+32 2 522 95 03",
    "sg:postcode":"1070",
    "sg:province":"Bruxelles-Capitale",
    "wof:name":"Thierry D'adam",
    "wof:placetype":"venue"
},
  "geometry": {"coordinates":[4.3142008781,50.8474311829],"type":"Point"}
}