{
  "type": "Feature",
  "properties": {
    "addr:full":"Quai De Rome 17b41 Li\u00c8ge Li\u00e8ge 4000",
    "addr:housenumber":"17b41",
    "addr:postcode":"4000",
    "addr:street":"Quai De Rome",
    "iso:country":"BE",
    "sg:address":"Quai De Rome 17b41",
    "sg:city":"Li\u00c8ge",
    "sg:orig_category":"Artsen and specialisten",
    "sg:phone":"+32 4 253 47 82",
    "sg:postcode":"4000",
    "sg:province":"Li\u00e8ge",
    "wof:name":"Nelly Delcomminette",
    "wof:placetype":"venue"
},
  "geometry": {"coordinates":[5.5746250153,50.6255455017],"type":"Point"}
}