{
  "type": "Feature",
  "properties": {
    "addr:full":"Rue De La R\u00c9sistance 152 Remicourt Li\u00e8ge 4351",
    "addr:housenumber":"152",
    "addr:postcode":"4351",
    "addr:street":"Rue De La Re\u0301Sistance",
    "iso:country":"BE",
    "sg:address":"Rue De La R\u00c9sistance 152",
    "sg:city":"Remicourt",
    "sg:orig_category":"Services de Nettoyage and de D\u00e9sinfection",
    "sg:phone":"+32 19 54 49 69",
    "sg:postcode":"4351",
    "sg:province":"Li\u00e8ge",
    "wof:name":"Jean Oceh",
    "wof:placetype":"venue"
},
  "geometry": {"coordinates":[5.3345108032,50.6945648193],"type":"Point"}
}