{
  "type": "Feature",
  "properties": {
    "iso:country":"BE",
    "sg:address":"Donklaan 152a",
    "sg:city":"Berlare",
    "sg:orig_category":"Kampeerterreinen",
    "sg:phone":"+32 9 369 27 34",
    "sg:postcode":"9290",
    "sg:province":"Oost-Vlaanderen",
    "wof:name":"Camping Kloosterputten",
    "wof:placetype":"venue"
},
  "geometry": {"coordinates":[3.9825050831,51.0285491943],"type":"Point"}
}