{
  "type": "Feature",
  "properties": {
    "iso:country":"BE",
    "sg:address":"Wielendaalstraat 8 Box 1",
    "sg:city":"Brakel (nederbrakel)",
    "sg:classifiers":[
        {
            "category":"Insurance",
            "subcategory":"Insurance Agent",
            "type":"Services"
        }
    ],
    "sg:phone":"+32 55 42 75 05",
    "sg:postcode":"9660",
    "sg:province":"Oost-Vlaanderen",
    "sg:tags":[
        "broker"
    ],
    "wof:name":"D'haeyer (kantoor)",
    "wof:placetype":"venue"
},
  "geometry": {"coordinates":[3.7633829117,50.8032417297],"type":"Point"}
}