{
  "type": "Feature",
  "properties": {
    "iso:country":"BE",
    "sg:address":"Rue Docteur Charles Leemans 48-50",
    "sg:city":"Bruxelles (berchem-sainte-agathe)",
    "sg:classifiers":[
        {
            "category":"Shopping",
            "subcategory":"Florist",
            "type":"Retail Goods"
        }
    ],
    "sg:phone":"+32 2 465 56 02",
    "sg:postcode":"1082",
    "sg:province":"Bruxelles-Capitale",
    "wof:name":"Le Bouquet Royal",
    "wof:placetype":"venue"
},
  "geometry": {"coordinates":[4.2945728302,50.8611526489],"type":"Point"}
}