{
  "type": "Feature",
  "properties": {
    "iso:country":"BE",
    "sg:address":"Albert Panisstraat 172",
    "sg:city":"Beveren (beveren-waas)",
    "sg:classifiers":[
        {
            "category":"Wholesale",
            "subcategory":"Medical Equipment & Supplies",
            "type":"Manufacturing & Wholesale Goods"
        }
    ],
    "sg:phone":"+32 3 755 33 54",
    "sg:postcode":"9120",
    "sg:province":"Oost-Vlaanderen",
    "sg:tags":[
        "aid",
        "hearing"
    ],
    "wof:name":"Thys",
    "wof:placetype":"venue"
},
  "geometry": {"coordinates":[4.2467679977,51.2085876465],"type":"Point"}
}