{
  "type": "Feature",
  "properties": {
    "addr:full":"Dr\u00c8ve Du Renard 10 Oudergem/auderghem Bruxelles-Capitale 1160",
    "addr:housenumber":"10",
    "addr:postcode":"1160",
    "addr:street":"Dre\u0300Ve Du Renard;/",
    "iso:country":"BE",
    "sg:address":"Dr\u00c8ve Du Renard 10",
    "sg:city":"Oudergem/auderghem",
    "sg:orig_category":"Assurances. Editeurs de livres",
    "sg:phone":"+32 2 660 12 35",
    "sg:postcode":"1160",
    "sg:province":"Bruxelles-Capitale",
    "wof:name":"Orgassim",
    "wof:placetype":"venue"
},
  "geometry": {"coordinates":[4.44186306,50.8188781738],"type":"Point"}
}