{
  "type": "Feature",
  "properties": {
    "iso:country":"BE",
    "sg:address":"Heuvenstraat 5",
    "sg:city":"Zonhoven",
    "sg:classifiers":[
        {
            "category":"Bars & Pubs",
            "type":"Food & Drink"
        }
    ],
    "sg:phone":"+32 11 81 62 57",
    "sg:postcode":"3520",
    "sg:province":"Limburg",
    "wof:name":"Tropical",
    "wof:placetype":"venue"
},
  "geometry": {"coordinates":[5.3683128357,50.9909706116],"type":"Point"}
}