{
  "type": "Feature",
  "properties": {
    "addr:full":"Rue De Wespin 102 Dinant Namur 5500",
    "addr:housenumber":"102",
    "addr:postcode":"5500",
    "addr:street":"Rue De Wespin",
    "iso:country":"BE",
    "sg:address":"Rue De Wespin 102",
    "sg:city":"Dinant",
    "sg:classifiers":[
        {
            "category":"Building & Trades",
            "subcategory":"Construction",
            "type":"Services"
        }
    ],
    "sg:phone":"+32 82 22 57 58",
    "sg:postcode":"5500",
    "sg:province":"Namur",
    "sg:tags":[
        "installation",
        "-",
        "central",
        "heating"
    ],
    "wof:name":"Picard R",
    "wof:placetype":"venue"
},
  "geometry": {"coordinates":[4.9003410339,50.258518219],"type":"Point"}
}