{
  "type": "Feature",
  "properties": {
    "addr:full":"Route Provinciale 96 Clabecq Brabant Wallon 1480",
    "addr:postcode":"1480",
    "addr:street":"Route Provinciale 96;Wallon",
    "iso:country":"BE",
    "sg:address":"Route Provinciale 96",
    "sg:city":"Clabecq",
    "sg:orig_category":"Fietsen Herstellingen motorfietsen Motorfietsen Tuinbenodigdheden",
    "sg:phone":"+32 78 16 94 91",
    "sg:postcode":"1480",
    "sg:province":"Brabant Wallon",
    "wof:name":"Glibert Yamaha Center S.a.",
    "wof:placetype":"venue"
},
  "geometry": {"coordinates":[4.2331409454,50.6798591614],"type":"Point"}
}