{
  "type": "Feature",
  "properties": {
    "addr:full":"Sur Les Greux Chaudfontaine (embourg) Li\u00e8ge 4053",
    "addr:postcode":"4053",
    "addr:street":"Sur Les Greux",
    "iso:country":"BE",
    "sg:address":"Sur Les Greux",
    "sg:city":"Chaudfontaine (embourg)",
    "sg:classifiers":[
        {
            "category":"Arena",
            "subcategory":"Sports Club",
            "type":"Entertainment"
        }
    ],
    "sg:phone":"+32 4 365 35 18",
    "sg:postcode":"4053",
    "sg:province":"Li\u00e8ge",
    "wof:name":"Embourg F C",
    "wof:placetype":"venue"
},
  "geometry": {"coordinates":[5.6194171906,50.5883178711],"type":"Point"}
}