{
  "type": "Feature",
  "properties": {
    "iso:country":"BE",
    "sg:address":"Chauss\u00e9e De Li\u00e8ge 69",
    "sg:city":"Gr\u00e2ce-hollogne (hollogne-aux-pierres)",
    "sg:classifiers":[
        {
            "category":"Retail",
            "subcategory":"Animal Services",
            "type":"Services"
        }
    ],
    "sg:phone":"+32 4 246 49 07",
    "sg:postcode":"4460",
    "sg:province":"Li\u00e8ge",
    "sg:tags":[
        "grooming",
        "-",
        "dog"
    ],
    "wof:name":"C M J Toilettage",
    "wof:placetype":"venue"
},
  "geometry": {"coordinates":[5.4754710197,50.6495819092],"type":"Point"}
}