{
  "type": "Feature",
  "properties": {
    "addr:full":"Rue Chapelle Dieu 48 Gembloux-sur-orneau (gembloux) Namur 5030",
    "addr:housenumber":"48",
    "addr:postcode":"5030",
    "addr:street":"Rue Chapelle Dieu;Namur",
    "iso:country":"BE",
    "sg:address":"Rue Chapelle Dieu 48",
    "sg:city":"Gembloux-sur-orneau (gembloux)",
    "sg:classifiers":[
        {
            "category":"Arena",
            "subcategory":"Sports Club",
            "type":"Entertainment"
        }
    ],
    "sg:phone":"+32 81 61 29 10",
    "sg:postcode":"5030",
    "sg:province":"Namur",
    "wof:name":"Gembloux Omnisport",
    "wof:placetype":"venue"
},
  "geometry": {"coordinates":[4.6985001564,50.5586013794],"type":"Point"}
}