{
  "type": "Feature",
  "properties": {
    "iso:country":"BE",
    "sg:address":"Hoofdrioolstraat 22",
    "sg:city":"Anderlecht/anderlecht",
    "sg:orig_category":"Decoratiestoffen and buitenhuistextiel Fab",
    "sg:phone":"+32 2 521 58 20",
    "sg:postcode":"1070",
    "sg:province":"Bruxelles-Capitale",
    "wof:name":"Renoma Auvent",
    "wof:placetype":"venue"
},
  "geometry": {"coordinates":[4.3220877647,50.8394355774],"type":"Point"}
}