{
  "type": "Feature",
  "properties": {
    "addr:full":"Kerkskenhoek 62 Haaltert Oost-Vlaanderen 9450",
    "addr:housenumber":"62",
    "addr:postcode":"9450",
    "addr:street":"Kerkskenhoek",
    "iso:country":"BE",
    "sg:address":"Kerkskenhoek 62",
    "sg:city":"Haaltert",
    "sg:classifiers":[
        {
            "category":"Insurance",
            "subcategory":"Life Insurance",
            "type":"Services"
        }
    ],
    "sg:phone":"+32 53 83 72 97",
    "sg:postcode":"9450",
    "sg:province":"Oost-Vlaanderen",
    "sg:tags":[
        "assurance"
    ],
    "wof:name":"Bureau Van Yperzele & Co",
    "wof:placetype":"venue"
},
  "geometry": {"coordinates":[3.9957749844,50.8932495117],"type":"Point"}
}