{
  "type": "Feature",
  "properties": {
    "addr:full":"Walgoedstraat 19 Temse Oost-Vlaanderen 9140",
    "addr:housenumber":"19",
    "addr:postcode":"9140",
    "addr:street":"Walgoedstraat",
    "iso:country":"BE",
    "sg:address":"Walgoedstraat 19",
    "sg:city":"Temse",
    "sg:orig_category":"Gespecialiseerde niet-residenti\u00eble bouw",
    "sg:phone":"+32 3 711 24 64",
    "sg:postcode":"9140",
    "sg:province":"Oost-Vlaanderen",
    "wof:name":"Enginered Pressure Systems International",
    "wof:placetype":"venue"
},
  "geometry": {"coordinates":[4.1877479553,51.1400756836],"type":"Point"}
}