{
  "type": "Feature",
  "properties": {
    "addr:full":"Lorzestraat 15 Dessel Antwerpen 2480",
    "addr:housenumber":"15",
    "addr:postcode":"2480",
    "addr:street":"Lorzestraat",
    "iso:country":"BE",
    "sg:address":"Lorzestraat 15",
    "sg:city":"Dessel",
    "sg:orig_category":"Brood, gebak and snoepgoed",
    "sg:phone":"+32 14 37 71 31",
    "sg:postcode":"2480",
    "sg:province":"Antwerpen",
    "wof:name":"Bakdes",
    "wof:placetype":"venue"
},
  "geometry": {"coordinates":[5.1159529686,51.2392044067],"type":"Point"}
}