{
  "type": "Feature",
  "properties": {
    "iso:country":"BE",
    "sg:address":"Groenstraat 28",
    "sg:city":"Sint-katelijne-waver",
    "sg:classifiers":[
        {
            "category":"Real Estate",
            "subcategory":"Architect",
            "type":"Services"
        }
    ],
    "sg:phone":"+32 15 21 65 28",
    "sg:postcode":"2860",
    "sg:province":"Antwerpen",
    "wof:name":"Van Itterbeeck W",
    "wof:placetype":"venue"
},
  "geometry": {"coordinates":[4.487074852,51.058216095],"type":"Point"}
}