{
  "type": "Feature",
  "properties": {
    "addr:full":"Chauss\u00c9e De Wavre 96 Sombreffe Namur 5140",
    "addr:housenumber":"96",
    "addr:postcode":"5140",
    "addr:street":"Chausse\u0301E De Wavre",
    "iso:country":"BE",
    "sg:address":"Chauss\u00c9e De Wavre 96",
    "sg:city":"Sombreffe",
    "sg:classifiers":[
        {
            "category":"Restaurant",
            "type":"Food & Drink"
        }
    ],
    "sg:phone":"+32 71 88 90 68",
    "sg:postcode":"5140",
    "sg:province":"Namur",
    "wof:name":"Larive Maurice",
    "wof:placetype":"venue"
},
  "geometry": {"coordinates":[4.6026000977,50.5362472534],"type":"Point"}
}