{
  "type": "Feature",
  "properties": {
    "iso:country":"BE",
    "sg:address":"Rue Grand-sart 4ba",
    "sg:city":"Lierneux",
    "sg:orig_category":"Entretien and r\u00e9parations de voitures",
    "sg:phone":"+32 80 41 83 33",
    "sg:postcode":"4990",
    "sg:province":"Li\u00e8ge",
    "wof:name":"C.f.r.",
    "wof:placetype":"venue"
},
  "geometry": {"coordinates":[5.8506369591,50.2662506104],"type":"Point"}
}