{
  "type": "Feature",
  "properties": {
    "addr:full":"Burgmolenstraat 22 Alveringem West-Vlaanderen 8690",
    "addr:housenumber":"22",
    "addr:postcode":"8690",
    "addr:street":"Burgmolenstraat",
    "iso:country":"BE",
    "sg:address":"Burgmolenstraat 22",
    "sg:city":"Alveringem",
    "sg:orig_category":"Rundveehouders Varkenskwekers",
    "sg:phone":"+32 58 28 83 42",
    "sg:postcode":"8690",
    "sg:province":"West-Vlaanderen",
    "wof:name":"Luc Vanhauwe",
    "wof:placetype":"venue"
},
  "geometry": {"coordinates":[2.7056040764,50.9989280701],"type":"Point"}
}