{
  "type": "Feature",
  "properties": {
    "addr:full":"Rue Du Haut Pr\u00e9 5 Li\u00e8ge 1 Li\u00e8ge 4000",
    "addr:housenumber":"5;1",
    "addr:postcode":"4000",
    "addr:street":"Rue Du Haut Pre\u0301",
    "iso:country":"BE",
    "sg:address":"Rue Du Haut Pr\u00e9 5",
    "sg:city":"Li\u00e8ge 1",
    "sg:classifiers":[
        {
            "category":"Shopping",
            "subcategory":"Florist",
            "type":"Retail Goods"
        }
    ],
    "sg:phone":"+32 4 224 70 44",
    "sg:postcode":"4000",
    "sg:province":"Li\u00e8ge",
    "wof:name":"Capucine (la)",
    "wof:placetype":"venue"
},
  "geometry": {"coordinates":[5.5533509254,50.6463699341],"type":"Point"}
}