{
  "type": "Feature",
  "properties": {
    "addr:full":"Rue Grande 60 Messancy Luxembourg 6780",
    "addr:housenumber":"60",
    "addr:postcode":"6780",
    "addr:street":"Rue Grande",
    "iso:country":"BE",
    "sg:address":"Rue Grande 60",
    "sg:city":"Messancy",
    "sg:classifiers":[
        {
            "category":"Communications",
            "subcategory":"Film & Video Production",
            "type":"Services"
        }
    ],
    "sg:phone":"+32 63 37 06 04",
    "sg:postcode":"6780",
    "sg:province":"Luxembourg",
    "sg:tags":[
        "hiring",
        "-"
    ],
    "wof:name":"Vid\u00e9o-messancy",
    "wof:placetype":"venue"
},
  "geometry": {"coordinates":[5.8147377968,49.5929985046],"type":"Point"}
}