{
  "type": "Feature",
  "properties": {
    "iso:country":"BE",
    "sg:address":"Kerrebroek 52",
    "sg:city":"Nevele",
    "sg:orig_category":"Installation de menuiserie en bois and plastique. Installation de menuiserie m\u00e9tallique",
    "sg:phone":"+32 9 371 61 69",
    "sg:postcode":"9850",
    "sg:province":"Oost-Vlaanderen",
    "wof:name":"Hertoge Herve",
    "wof:placetype":"venue"
},
  "geometry": {"coordinates":[3.5330610275,51.0274009705],"type":"Point"}
}