{
  "type": "Feature",
  "properties": {
    "addr:full":"Weg Naar Zwartberg 90 Houthalen-helchteren Limburg 3530",
    "addr:housenumber":"90",
    "addr:postcode":"3530",
    "addr:street":"Weg Naar Zwartberg",
    "iso:country":"BE",
    "sg:address":"Weg Naar Zwartberg 90",
    "sg:city":"Houthalen-helchteren",
    "sg:orig_category":"Transports terrestres de voyageurs. Agences de voyages",
    "sg:phone":"+32 89 38 37 41",
    "sg:postcode":"3530",
    "sg:province":"Limburg",
    "wof:name":"De Blauwvoet",
    "wof:placetype":"venue"
},
  "geometry": {"coordinates":[5.4123802185,51.0261192322],"type":"Point"}
}