{
  "type": "Feature",
  "properties": {
    "addr:full":"Hoogstraat 399 Brussel/bruxelles Bruxelles-Capitale 1000",
    "addr:housenumber":"399",
    "addr:postcode":"1000",
    "addr:street":"Hoogstraat;/",
    "iso:country":"BE",
    "sg:address":"Hoogstraat 399",
    "sg:city":"Brussel/bruxelles",
    "sg:orig_category":"Schoonmaakbedrijven and ongediertebestrijding",
    "sg:phone":"+32 2 537 62 13",
    "sg:postcode":"1000",
    "sg:province":"Bruxelles-Capitale",
    "wof:name":"Correia",
    "wof:placetype":"venue"
},
  "geometry": {"coordinates":[4.3449239731,50.8336868286],"type":"Point"}
}