{
  "type": "Feature",
  "properties": {
    "addr:full":"Charlottalei 70 Antwerpen Antwerpen 2018",
    "addr:housenumber":"70",
    "addr:postcode":"2018",
    "addr:street":"Charlottalei",
    "iso:country":"BE",
    "sg:address":"Charlottalei 70",
    "sg:city":"Antwerpen",
    "sg:classifiers":[
        {
            "category":"Shopping",
            "subcategory":"Clothing, Apparel, & Fashions",
            "type":"Retail Goods"
        }
    ],
    "sg:phone":"+32 3 218 75 18",
    "sg:postcode":"2018",
    "sg:province":"Antwerpen",
    "sg:tags":[
        "lady",
        "clothing",
        "-"
    ],
    "wof:name":"Mannequin",
    "wof:placetype":"venue"
},
  "geometry": {"coordinates":[4.4191408157,51.2072601318],"type":"Point"}
}