{
  "type": "Feature",
  "properties": {
    "iso:country":"BE",
    "sg:address":"Rue G\u00c9n\u00c9ral Eenens 12",
    "sg:city":"Schaarbeek/schaerbeek",
    "sg:orig_category":"Pain, p\u00e2tisseries and confiseries",
    "sg:phone":"+32 2 215 23 75",
    "sg:postcode":"1030",
    "sg:province":"Bruxelles-Capitale",
    "wof:name":"P\u00c2tisserie Defever",
    "wof:placetype":"venue"
},
  "geometry": {"coordinates":[4.3748178482,50.8681144714],"type":"Point"}
}