{
  "type": "Feature",
  "properties": {
    "addr:full":"Waastensestraat 1 Ieper West-Vlaanderen 8902",
    "addr:housenumber":"1",
    "addr:postcode":"8902",
    "addr:street":"Waastensestraat",
    "iso:country":"BE",
    "sg:address":"Waastensestraat 1",
    "sg:city":"Ieper",
    "sg:orig_category":"Eleveurs de bovins",
    "sg:phone":"+32 57 20 31 54",
    "sg:postcode":"8902",
    "sg:province":"West-Vlaanderen",
    "wof:name":"Michel Menu",
    "wof:placetype":"venue"
},
  "geometry": {"coordinates":[2.9014658928,50.8254165649],"type":"Point"}
}