{
  "type": "Feature",
  "properties": {
    "addr:full":"Sint-margrietestraat 121 Sint-laureins Oost-Vlaanderen 9981",
    "addr:housenumber":"121",
    "addr:postcode":"9981",
    "addr:street":"Sint-Margrietestraat",
    "iso:country":"BE",
    "sg:address":"Sint-margrietestraat 121",
    "sg:city":"Sint-laureins",
    "sg:orig_category":"Varkenskwekers",
    "sg:phone":"+32 9 379 81 14",
    "sg:postcode":"9981",
    "sg:province":"Oost-Vlaanderen",
    "wof:name":"Johan Herrebout",
    "wof:placetype":"venue"
},
  "geometry": {"coordinates":[3.5428419113,51.2832756042],"type":"Point"}
}