{
  "type": "Feature",
  "properties": {
    "addr:full":"Acaciastraat 59 Lummen Limburg 3560",
    "addr:housenumber":"59",
    "addr:postcode":"3560",
    "addr:street":"Acaciastraat",
    "iso:country":"BE",
    "sg:address":"Acaciastraat 59",
    "sg:city":"Lummen",
    "sg:orig_category":"Architecten",
    "sg:phone":"+32 13 52 21 79",
    "sg:postcode":"3560",
    "sg:province":"Limburg",
    "wof:name":"Bettina Luyten",
    "wof:placetype":"venue"
},
  "geometry": {"coordinates":[5.2126278877,50.9942512512],"type":"Point"}
}