{
  "type": "Feature",
  "properties": {
    "iso:country":"BE",
    "sg:address":"Grote Bollostraat 167",
    "sg:city":"Tremelo",
    "sg:classifiers":[
        {
            "category":"Cafe",
            "type":"Food & Drink"
        }
    ],
    "sg:phone":"+32 16 53 53 92",
    "sg:postcode":"3120",
    "sg:province":"Vlaams-Brabant",
    "sg:tags":[
        "caf\u00e9s"
    ],
    "wof:name":"Gabrielle Steurs",
    "wof:placetype":"venue"
},
  "geometry": {"coordinates":[4.7219138145,51.0088386536],"type":"Point"}
}