{
  "type": "Feature",
  "properties": {
    "iso:country":"BE",
    "sg:address":"Grand'rue 69",
    "sg:city":"Walcourt",
    "sg:orig_category":"Woningbouw",
    "sg:phone":"+32 71 65 52 12",
    "sg:postcode":"5651",
    "sg:province":"Namur",
    "wof:name":"C. Locatelli",
    "wof:placetype":"venue"
},
  "geometry": {"coordinates":[4.4332799911,50.2857818604],"type":"Point"}
}