{
  "type": "Feature",
  "properties": {
    "iso:country":"BE",
    "sg:address":"Rue Auguste Buisseret 13",
    "sg:city":"Li\u00c8ge",
    "sg:orig_category":"Pain, p\u00e2tisseries and confiseries",
    "sg:phone":"+32 4 252 02 49",
    "sg:postcode":"4000",
    "sg:province":"Li\u00e8ge",
    "wof:name":"Albert Gerday",
    "wof:placetype":"venue"
},
  "geometry": {"coordinates":[5.5716137886,50.6229934692],"type":"Point"}
}