{
  "type": "Feature",
  "properties": {
    "iso:country":"BE",
    "sg:address":"Rue Saint-roch 45",
    "sg:city":"Fernelmont (hingeon)",
    "sg:classifiers":[
        {
            "category":"Retail",
            "subcategory":"Repair Shop",
            "type":"Services"
        }
    ],
    "sg:phone":"+32 81 83 44 27",
    "sg:postcode":"5380",
    "sg:province":"Namur",
    "sg:tags":[
        "machine",
        "sewing",
        "-"
    ],
    "wof:name":"Mathy D",
    "wof:placetype":"venue"
},
  "geometry": {"coordinates":[5.0109930038,50.5214805603],"type":"Point"}
}