{
  "type": "Feature",
  "properties": {
    "addr:full":"Rue De Fromenteau 18 Welkenraedt Li\u00e8ge 4840",
    "addr:housenumber":"18",
    "addr:postcode":"4840",
    "addr:street":"Rue De Fromenteau",
    "iso:country":"BE",
    "sg:address":"Rue De Fromenteau 18",
    "sg:city":"Welkenraedt",
    "sg:classifiers":[
        {
            "category":"Real Estate",
            "subcategory":"Architect",
            "type":"Services"
        }
    ],
    "sg:phone":"+32 87 88 18 64",
    "sg:postcode":"4840",
    "sg:province":"Li\u00e8ge",
    "wof:name":"Rensonnet V",
    "wof:placetype":"venue"
},
  "geometry": {"coordinates":[5.9634690285,50.6630363464],"type":"Point"}
}