{
  "type": "Feature",
  "properties": {
    "addr:full":"Oude Baan 48 Rumst (terhagen) Antwerpen 2840",
    "addr:housenumber":"48",
    "addr:postcode":"2840",
    "addr:street":"Oude Baan",
    "iso:country":"BE",
    "sg:address":"Oude Baan 48",
    "sg:city":"Rumst (terhagen)",
    "sg:orig_category":"Non-Classified Establishments",
    "sg:phone":"+32 3 880 51 80",
    "sg:postcode":"2840",
    "sg:province":"Antwerpen",
    "wof:name":"Steenfabriek Heylen",
    "wof:placetype":"venue"
},
  "geometry": {"coordinates":[4.4026842117,51.0784873962],"type":"Point"}
}