{
  "type": "Feature",
  "properties": {
    "iso:country":"BE",
    "sg:address":"Nattehofstraat 33",
    "sg:city":"Mechelen",
    "sg:classifiers":[
        {
            "category":"Health Services",
            "subcategory":"Doctor",
            "type":"Services"
        }
    ],
    "sg:phone":"+32 15 26 08 82",
    "sg:postcode":"2800",
    "sg:province":"Antwerpen",
    "sg:tags":[
        "medicinephysicians",
        "surgeon"
    ],
    "wof:name":"Dhondt F",
    "wof:placetype":"venue"
},
  "geometry": {"coordinates":[4.4649782181,51.0274925232],"type":"Point"}
}