{
  "type": "Feature",
  "properties": {
    "iso:country":"BE",
    "sg:address":"Witte-stedeweg 6",
    "sg:city":"Kontich",
    "sg:orig_category":"R\u00e9parations and entretien de motos. Motos. V\u00e9los",
    "sg:phone":"+32 3 457 73 02",
    "sg:postcode":"2550",
    "sg:province":"Antwerpen",
    "wof:name":"Jozef Francis",
    "wof:placetype":"venue"
},
  "geometry": {"coordinates":[4.4747872353,51.12241745],"type":"Point"}
}