{
  "type": "Feature",
  "properties": {
    "addr:full":"Leugenberg 105 Antwerpen (ekeren) Antwerpen 2180",
    "addr:housenumber":"105",
    "addr:postcode":"2180",
    "addr:street":"Leugenberg",
    "iso:country":"BE",
    "sg:address":"Leugenberg 105",
    "sg:city":"Antwerpen (ekeren)",
    "sg:classifiers":[
        {
            "category":"Retail",
            "subcategory":"Auto Repair",
            "type":"Services"
        }
    ],
    "sg:phone":"+32 3 660 29 40",
    "sg:postcode":"2180",
    "sg:province":"Antwerpen",
    "sg:tags":[
        "garage"
    ],
    "wof:name":"Van Gansen Services Nv",
    "wof:placetype":"venue"
},
  "geometry": {"coordinates":[4.410490036,51.3021583557],"type":"Point"}
}