{
  "type": "Feature",
  "properties": {
    "addr:full":"Rue De Toulouse 17 Brussel/bruxelles Bruxelles-Capitale 1040",
    "addr:housenumber":"17",
    "addr:postcode":"1040",
    "addr:street":"Rue De Toulouse;/",
    "iso:country":"BE",
    "sg:address":"Rue De Toulouse 17",
    "sg:city":"Brussel/bruxelles",
    "sg:orig_category":"M\u00e9decins and sp\u00e9cialistes",
    "sg:phone":"+32 2 230 74 82",
    "sg:postcode":"1040",
    "sg:province":"Bruxelles-Capitale",
    "wof:name":"M. Xhardez",
    "wof:placetype":"venue"
},
  "geometry": {"coordinates":[4.3870849609,50.8363609314],"type":"Point"}
}