{
  "type": "Feature",
  "properties": {
    "addr:full":"Kievitlaan 12 Ranst Antwerpen 2520",
    "addr:housenumber":"12",
    "addr:postcode":"2520",
    "addr:street":"Kievitlaan",
    "iso:country":"BE",
    "sg:address":"Kievitlaan 12",
    "sg:city":"Ranst",
    "sg:orig_category":"Parfumeries",
    "sg:phone":"+32 3 485 65 74",
    "sg:postcode":"2520",
    "sg:province":"Antwerpen",
    "wof:name":"Parfumerie Kolibri",
    "wof:placetype":"venue"
},
  "geometry": {"coordinates":[4.5580210686,51.1873931885],"type":"Point"}
}