{
  "type": "Feature",
  "properties": {
    "iso:country":"BE",
    "sg:address":"Rue De Buresse 49",
    "sg:city":"Hamois",
    "sg:orig_category":"Eleveurs de bovins",
    "sg:phone":"+32 83 61 23 93",
    "sg:postcode":"5360",
    "sg:province":"Namur",
    "wof:name":"Michel Warzee",
    "wof:placetype":"venue"
},
  "geometry": {"coordinates":[5.1653680801,50.3561172485],"type":"Point"}
}