{
  "type": "Feature",
  "properties": {
    "iso:country":"BE",
    "sg:address":"Borgueuse He 18",
    "sg:city":"Malmedy",
    "sg:classifiers":[
        {
            "category":"Building & Trades",
            "subcategory":"Construction",
            "type":"Services"
        }
    ],
    "sg:phone":"+32 80 57 08 56",
    "sg:postcode":"4960",
    "sg:province":"Li\u00e8ge",
    "sg:tags":[
        "stucco",
        "contractor"
    ],
    "wof:name":"Pirotte A",
    "wof:placetype":"venue"
},
  "geometry": {"coordinates":[6.030921936,50.3712997437],"type":"Point"}
}