{
  "type": "Feature",
  "properties": {
    "iso:country":"BE",
    "sg:address":"Grotesteenweg 564",
    "sg:city":"Antwerpen",
    "sg:orig_category":"Banken and kredietinstellingen",
    "sg:phone":"+32 3 230 60 23",
    "sg:postcode":"2600",
    "sg:province":"Antwerpen",
    "wof:name":"Kbc",
    "wof:placetype":"venue"
},
  "geometry": {"coordinates":[4.4174151421,51.1974411011],"type":"Point"}
}