{
  "type": "Feature",
  "properties": {
    "iso:country":"BE",
    "sg:address":"Neststraat 22",
    "sg:city":"Gent (sint-denijs-westrem - Afsnee)",
    "sg:classifiers":[
        {
            "category":"Real Estate",
            "subcategory":"Real Estate Services",
            "type":"Services"
        }
    ],
    "sg:phone":"+32 9 222 27 72",
    "sg:postcode":"9051",
    "sg:province":"Oost-Vlaanderen",
    "wof:name":"Meersman E",
    "wof:placetype":"venue"
},
  "geometry": {"coordinates":[3.6668028831,51.0254707336],"type":"Point"}
}