{
  "type": "Feature",
  "properties": {
    "addr:full":"Steenweg Op Bergen 19 Sint-pieters-leeuw (grand) Vlaams-Brabant 1600",
    "addr:housenumber":"19;1600",
    "addr:street":"Steenweg Op Bergen",
    "iso:country":"BE",
    "sg:address":"Steenweg Op Bergen 19",
    "sg:city":"Sint-pieters-leeuw (grand)",
    "sg:orig_category":"Ilwa Keukens",
    "sg:phone":"+32 2 377 43 59",
    "sg:postcode":"1600",
    "sg:province":"Vlaams-Brabant",
    "wof:name":"Ilwa - De Wolf Design",
    "wof:placetype":"venue"
},
  "geometry": {"coordinates":[4.289124012,50.8072891235],"type":"Point"}
}