{
  "type": "Feature",
  "properties": {
    "addr:full":"Ijzerenkruisstraat 78 Brussel/bruxelles Bruxelles-Capitale 1000",
    "addr:housenumber":"78",
    "addr:postcode":"1000",
    "addr:street":"Ijzerenkruisstraat;/",
    "iso:country":"BE",
    "sg:address":"Ijzerenkruisstraat 78",
    "sg:city":"Brussel/bruxelles",
    "sg:orig_category":"Apotheken",
    "sg:phone":"+32 2 218 35 78",
    "sg:postcode":"1000",
    "sg:province":"Bruxelles-Capitale",
    "wof:name":"Pharm De La Croix De Fer",
    "wof:placetype":"venue"
},
  "geometry": {"coordinates":[4.3665699959,50.8485717773],"type":"Point"}
}