{
  "type": "Feature",
  "properties": {
    "iso:country":"BE",
    "sg:address":"Keizer Karelstraat 144",
    "sg:city":"Gent",
    "sg:orig_category":"Jeux and jouets",
    "sg:phone":"+32 9 223 61 88",
    "sg:postcode":"9000",
    "sg:province":"Oost-Vlaanderen",
    "wof:name":"Huis Krat",
    "wof:placetype":"venue"
},
  "geometry": {"coordinates":[3.7325720787,51.0515708923],"type":"Point"}
}