{
  "type": "Feature",
  "properties": {
    "addr:full":"Ch. De Bruxelles 612 Les Bons Villers Hainaut 6210",
    "addr:housenumber":"612",
    "addr:postcode":"6210",
    "addr:street":"Ch. De Bruxelles",
    "iso:country":"BE",
    "sg:address":"Ch. De Bruxelles 612",
    "sg:city":"Les Bons Villers",
    "sg:orig_category":"Elektrische installaties voor woningen Huishoudapparaten, televisies and radio's Telecommunicatieapp",
    "sg:phone":"+32 71 85 18 01",
    "sg:postcode":"6210",
    "sg:province":"Hainaut",
    "wof:name":"Vander Eyden",
    "wof:placetype":"venue"
},
  "geometry": {"coordinates":[4.4511561394,50.5378227234],"type":"Point"}
}