{
  "type": "Feature",
  "properties": {
    "iso:country":"BE",
    "sg:address":"Kerkstraat 216",
    "sg:city":"Gent (gentbrugge)",
    "sg:classifiers":[
        {
            "category":"Social Services",
            "type":"Services"
        }
    ],
    "sg:phone":"+32 9 232 45 32",
    "sg:postcode":"9050",
    "sg:province":"Oost-Vlaanderen",
    "wof:name":"Stedelijke Buurtwerking",
    "wof:placetype":"venue"
},
  "geometry": {"coordinates":[3.7456920147,51.0433731079],"type":"Point"}
}