{
  "type": "Feature",
  "properties": {
    "iso:country":"BE",
    "sg:address":"Hekkestraat 2",
    "sg:city":"Torhout",
    "sg:orig_category":"Entretien and r\u00e9parations de voitures",
    "sg:phone":"+32 50 72 37 69",
    "sg:postcode":"8820",
    "sg:province":"West-Vlaanderen",
    "wof:name":"Johny Verbrugghe",
    "wof:placetype":"venue"
},
  "geometry": {"coordinates":[3.084430933,51.0199241638],"type":"Point"}
}