{
  "type": "Feature",
  "properties": {
    "addr:full":"Rue Des Fouarges 24 Huy Li\u00e8ge 4500",
    "addr:housenumber":"24",
    "addr:postcode":"4500",
    "addr:street":"Rue Des Fouarges",
    "iso:country":"BE",
    "sg:address":"Rue Des Fouarges 24",
    "sg:city":"Huy",
    "sg:classifiers":[
        {
            "category":"Shopping",
            "subcategory":"Clothing, Apparel, & Fashions",
            "type":"Retail Goods"
        }
    ],
    "sg:phone":"+32 85 25 27 72",
    "sg:postcode":"4500",
    "sg:province":"Li\u00e8ge",
    "sg:tags":[
        "clothing",
        "-",
        "gentleman"
    ],
    "wof:name":"Homme & Gars",
    "wof:placetype":"venue"
},
  "geometry": {"coordinates":[5.2417221069,50.5187835693],"type":"Point"}
}