{
  "type": "Feature",
  "properties": {
    "addr:full":"Rue Royale 72 Tournai Hainaut 7500",
    "addr:housenumber":"72",
    "addr:postcode":"7500",
    "addr:street":"Rue Royale",
    "iso:country":"BE",
    "sg:address":"Rue Royale 72",
    "sg:city":"Tournai",
    "sg:orig_category":"Afval and schroot Gh",
    "sg:phone":"+32 69 84 58 78",
    "sg:postcode":"7500",
    "sg:province":"Hainaut",
    "wof:name":"Buro-tec Services Tournai",
    "wof:placetype":"venue"
},
  "geometry": {"coordinates":[3.3945229053,50.6112670898],"type":"Point"}
}