{
  "type": "Feature",
  "properties": {
    "addr:full":"Lepelstraat 50 Lommel Limburg 3920",
    "addr:housenumber":"50",
    "addr:postcode":"3920",
    "addr:street":"Lepelstraat",
    "iso:country":"BE",
    "sg:address":"Lepelstraat 50",
    "sg:city":"Lommel",
    "sg:classifiers":[
        {
            "category":"Fast Food",
            "type":"Food & Drink"
        }
    ],
    "sg:phone":"+32 11 54 16 00",
    "sg:postcode":"3920",
    "sg:province":"Limburg",
    "sg:tags":[
        "\u00c0",
        "emporter",
        "restaurants"
    ],
    "wof:name":"Frituur Pik Nik",
    "wof:placetype":"venue"
},
  "geometry": {"coordinates":[5.3099660873,51.2328987122],"type":"Point"}
}