{
  "type": "Feature",
  "properties": {
    "iso:country":"BE",
    "sg:address":"Oude Truierbaan 160",
    "sg:city":"Hasselt",
    "sg:classifiers":[
        {
            "category":"Building & Trades",
            "subcategory":"Construction",
            "type":"Services"
        }
    ],
    "sg:phone":"+32 11 27 44 69",
    "sg:postcode":"3500",
    "sg:province":"Limburg",
    "sg:tags":[
        "installation",
        "-",
        "central",
        "heating"
    ],
    "wof:name":"Motmans C",
    "wof:placetype":"venue"
},
  "geometry": {"coordinates":[5.3154058456,50.9079093933],"type":"Point"}
}