{
  "type": "Feature",
  "properties": {
    "addr:full":"Lozenhoekstraat 66 Keerbergen Vlaams-Brabant 3140",
    "addr:housenumber":"66",
    "addr:postcode":"3140",
    "addr:street":"Lozenhoekstraat",
    "iso:country":"BE",
    "sg:address":"Lozenhoekstraat 66",
    "sg:city":"Keerbergen",
    "sg:classifiers":[
        {
            "category":"Building & Trades",
            "subcategory":"Landscaping Services",
            "type":"Services"
        }
    ],
    "sg:phone":"+32 15 22 05 01",
    "sg:postcode":"3140",
    "sg:province":"Vlaams-Brabant",
    "sg:tags":[
        "architect",
        "landscape"
    ],
    "wof:name":"Priapus Bvba",
    "wof:placetype":"venue"
},
  "geometry": {"coordinates":[4.6998791695,51.0136871338],"type":"Point"}
}