{
  "type": "Feature",
  "properties": {
    "addr:full":"Aartshertogstraat 9 Oostende West-Vlaanderen 8400",
    "addr:housenumber":"9",
    "addr:postcode":"8400",
    "addr:street":"Aartshertogstraat",
    "iso:country":"BE",
    "sg:address":"Aartshertogstraat 9",
    "sg:city":"Oostende",
    "sg:orig_category":"Royal Canin",
    "sg:phone":"+32 59 80 14 21",
    "sg:postcode":"8400",
    "sg:province":"West-Vlaanderen",
    "wof:name":"Verhelst Guy",
    "wof:placetype":"venue"
},
  "geometry": {"coordinates":[2.917001009,51.2297592163],"type":"Point"}
}