{
  "type": "Feature",
  "properties": {
    "addr:full":"Chauss\u00e9e De Bruxelles 31 Wemmel Vlaams-Brabant 1780",
    "addr:housenumber":"31",
    "addr:postcode":"1780",
    "addr:street":"Chausse\u0301E De Bruxelles;Vlaams-Brabant",
    "iso:country":"BE",
    "sg:address":"Chauss\u00e9e De Bruxelles 31",
    "sg:city":"Wemmel",
    "sg:classifiers":[
        {
            "category":"Farming",
            "subcategory":"Fish & Marine Products",
            "type":"Manufacturing & Wholesale Goods"
        }
    ],
    "sg:phone":"+32 2 461 13 20",
    "sg:postcode":"1780",
    "sg:province":"Vlaams-Brabant",
    "sg:tags":[
        "retail",
        "-",
        "shellfish"
    ],
    "wof:name":"Triton",
    "wof:placetype":"venue"
},
  "geometry": {"coordinates":[4.3071541786,50.9064750671],"type":"Point"}
}