{
  "type": "Feature",
  "properties": {
    "iso:country":"BE",
    "sg:address":"Rue Vanderkindere 209",
    "sg:city":"Ukkel/uccle",
    "sg:orig_category":"Agences immobili\u00e8res",
    "sg:phone":"+32 2 340 16 30",
    "sg:postcode":"1180",
    "sg:province":"Bruxelles-Capitale",
    "wof:name":"Trustim",
    "wof:placetype":"venue"
},
  "geometry": {"coordinates":[4.3507928848,50.8138504028],"type":"Point"}
}