{
  "type": "Feature",
  "properties": {
    "addr:full":"Vierbunderstraat 1 Ingelmunster West-Vlaanderen 8770",
    "addr:housenumber":"1",
    "addr:postcode":"8770",
    "addr:street":"Vierbunderstraat",
    "iso:country":"BE",
    "sg:address":"Vierbunderstraat 1",
    "sg:city":"Ingelmunster",
    "sg:classifiers":[
        {
            "category":"Farming",
            "subcategory":"Livestock Farm",
            "type":"Manufacturing & Wholesale Goods"
        }
    ],
    "sg:phone":"+32 51 30 12 53",
    "sg:postcode":"8770",
    "sg:province":"West-Vlaanderen",
    "sg:tags":[
        "buyer"
    ],
    "wof:name":"Vandecasteele P",
    "wof:placetype":"venue"
},
  "geometry": {"coordinates":[3.2489800453,50.914768219],"type":"Point"}
}