{
  "type": "Feature",
  "properties": {
    "addr:full":"Rue De P\u00c2turages 6 Colfontaine Hainaut 7340",
    "addr:housenumber":"6",
    "addr:postcode":"7340",
    "addr:street":"Rue De Pa\u0302Turages",
    "iso:country":"BE",
    "sg:address":"Rue De P\u00c2turages 6",
    "sg:city":"Colfontaine",
    "sg:orig_category":"Boucheries",
    "sg:phone":"+32 65 67 12 66",
    "sg:postcode":"7340",
    "sg:province":"Hainaut",
    "wof:name":"Boucherie Pochet",
    "wof:placetype":"venue"
},
  "geometry": {"coordinates":[3.8636329174,50.4130401611],"type":"Point"}
}