{
  "type": "Feature",
  "properties": {
    "addr:full":"Dunantplein 1 Heusden-zolder Limburg 3550",
    "addr:housenumber":"1",
    "addr:postcode":"3550",
    "addr:street":"Dunantplein",
    "iso:country":"BE",
    "sg:address":"Dunantplein 1",
    "sg:city":"Heusden-zolder",
    "sg:orig_category":"Artistes ind\u00e9pendants",
    "sg:phone":"+32 11 53 64 17",
    "sg:postcode":"3550",
    "sg:province":"Limburg",
    "wof:name":"Maria Beckers",
    "wof:placetype":"venue"
},
  "geometry": {"coordinates":[5.3194189072,51.0224723816],"type":"Point"}
}