{
  "type": "Feature",
  "properties": {
    "addr:full":"Ankerstraat 91 Sint-niklaas Oost-Vlaanderen 9100",
    "addr:housenumber":"91",
    "addr:postcode":"9100",
    "addr:street":"Ankerstraat",
    "iso:country":"BE",
    "sg:address":"Ankerstraat 91",
    "sg:city":"Sint-niklaas",
    "sg:classifiers":[
        {
            "category":"Community Center",
            "type":"Public Place"
        }
    ],
    "sg:phone":"+32 3 760 07 70",
    "sg:postcode":"9100",
    "sg:province":"Oost-Vlaanderen",
    "sg:tags":[
        "medical"
    ],
    "wof:name":"Multifunctionele Eenheid Waasland het Klaverblad",
    "wof:placetype":"venue"
},
  "geometry": {"coordinates":[4.1473851204,51.1664085388],"type":"Point"}
}