{
  "type": "Feature",
  "properties": {
    "iso:country":"BE",
    "sg:address":"Nieuwdreef 70",
    "sg:city":"Merksem",
    "sg:classifiers":[
        {
            "category":"Shopping",
            "subcategory":"Clothing, Apparel, & Fashions",
            "type":"Retail Goods"
        }
    ],
    "sg:phone":"+32 3 646 38 63",
    "sg:postcode":"2170",
    "sg:province":"Antwerpen",
    "sg:tags":[
        "textile",
        "clothing",
        "clothes"
    ],
    "wof:name":"Usa Trade Bvba",
    "wof:placetype":"venue"
},
  "geometry": {"coordinates":[4.4406862259,51.2453804016],"type":"Point"}
}