{
  "type": "Feature",
  "properties": {
    "addr:full":"Vlierkensstraat 57 Vilvoorde Vlaams-Brabant 1800",
    "addr:housenumber":"57",
    "addr:postcode":"1800",
    "addr:street":"Vlierkensstraat",
    "iso:country":"BE",
    "sg:address":"Vlierkensstraat 57",
    "sg:city":"Vilvoorde",
    "sg:orig_category":"Schoonheidssalons",
    "sg:phone":"+32 2 251 28 55",
    "sg:postcode":"1800",
    "sg:province":"Vlaams-Brabant",
    "wof:name":"Michele Glazemakers",
    "wof:placetype":"venue"
},
  "geometry": {"coordinates":[4.4108839035,50.9237937927],"type":"Point"}
}