{
  "type": "Feature",
  "properties": {
    "addr:full":"Veldstraat 37 Koekelare West-Vlaanderen 8680",
    "addr:housenumber":"37",
    "addr:postcode":"8680",
    "addr:street":"Veldstraat",
    "iso:country":"BE",
    "sg:address":"Veldstraat 37",
    "sg:city":"Koekelare",
    "sg:classifiers":[
        {
            "category":"Farming",
            "subcategory":"Fish & Marine Products",
            "type":"Manufacturing & Wholesale Goods"
        }
    ],
    "sg:phone":"+32 51 58 27 44",
    "sg:postcode":"8680",
    "sg:province":"West-Vlaanderen",
    "sg:tags":[
        "retail",
        "-",
        "shellfish"
    ],
    "wof:name":"Vandichele D",
    "wof:placetype":"venue"
},
  "geometry": {"coordinates":[2.9736471176,51.0871315002],"type":"Point"}
}