{
  "type": "Feature",
  "properties": {
    "addr:full":"Langveldstraat 18 Dendermonde Oost-Vlaanderen 9200",
    "addr:housenumber":"18",
    "addr:postcode":"9200",
    "addr:street":"Langveldstraat;Oost-Vlaanderen",
    "iso:country":"BE",
    "sg:address":"Langveldstraat 18",
    "sg:city":"Dendermonde",
    "sg:orig_category":"Installatie van houten of kunststof schrijnwerk",
    "sg:phone":"+32 52 21 64 78",
    "sg:postcode":"9200",
    "sg:province":"Oost-Vlaanderen",
    "wof:name":"Geert Vlaeminck",
    "wof:placetype":"venue"
},
  "geometry": {"coordinates":[4.0958709717,51.0192146301],"type":"Point"}
}