{
  "type": "Feature",
  "properties": {
    "addr:full":"Rue Mulhoff 54c Waremme Li\u00e8ge 4300",
    "addr:housenumber":"54c",
    "addr:postcode":"4300",
    "addr:street":"Rue Mulhoff",
    "iso:country":"BE",
    "sg:address":"Rue Mulhoff 54c",
    "sg:city":"Waremme",
    "sg:orig_category":"Tuinen",
    "sg:phone":"+32 19 32 42 29",
    "sg:postcode":"4300",
    "sg:province":"Li\u00e8ge",
    "wof:name":"Dessy J-c.",
    "wof:placetype":"venue"
},
  "geometry": {"coordinates":[5.2333111763,50.7111358643],"type":"Point"}
}