{
  "type": "Feature",
  "properties": {
    "iso:country":"BE",
    "sg:address":"Kortedagsteeg 13-15",
    "sg:city":"Gent",
    "sg:orig_category":"Eclairage et \u00e9quipements du foyer",
    "sg:phone":"+32 9 223 36 53",
    "sg:postcode":"9000",
    "sg:province":"Oost-Vlaanderen",
    "wof:name":"Huis Chinoh",
    "wof:placetype":"venue"
},
  "geometry": {"coordinates":[3.7265100479,51.0502166748],"type":"Point"}
}