{
  "type": "Feature",
  "properties": {
    "iso:country":"BE",
    "sg:address":"Sint-jobsesteenweg 112",
    "sg:city":"Brasschaat",
    "sg:classifiers":[
        {
            "category":"Health Services",
            "subcategory":"Doctor",
            "type":"Services"
        }
    ],
    "sg:phone":"+32 3 663 35 68",
    "sg:postcode":"2930",
    "sg:province":"Antwerpen",
    "sg:tags":[
        "orthopedist"
    ],
    "wof:name":"De Baecker Bvba",
    "wof:placetype":"venue"
},
  "geometry": {"coordinates":[4.5546460152,51.3112449646],"type":"Point"}
}