{
  "type": "Feature",
  "properties": {
    "addr:full":"Molenstraat 214 Nijlen Antwerpen 2560",
    "addr:housenumber":"214",
    "addr:postcode":"2560",
    "addr:street":"Molenstraat",
    "iso:country":"BE",
    "sg:address":"Molenstraat 214",
    "sg:city":"Nijlen",
    "sg:classifiers":[
        {
            "category":"Home & Garden",
            "subcategory":"Carpets & Floor Coverings",
            "type":"Retail Goods"
        }
    ],
    "sg:phone":"+32 3 481 62 12",
    "sg:postcode":"2560",
    "sg:province":"Antwerpen",
    "sg:tags":[
        "parquet"
    ],
    "wof:name":"Croon Parket",
    "wof:placetype":"venue"
},
  "geometry": {"coordinates":[4.6495461464,51.1685447693],"type":"Point"}
}