{
  "type": "Feature",
  "properties": {
    "iso:country":"BE",
    "sg:address":"Rue De La Libert\u00c9 78bb",
    "sg:city":"Tournai",
    "sg:orig_category":"Services pour animaux domestiques",
    "sg:phone":"+32 69 22 46 63",
    "sg:postcode":"7540",
    "sg:province":"Hainaut",
    "wof:name":"Toilettage Sophie",
    "wof:placetype":"venue"
},
  "geometry": {"coordinates":[3.4172759056,50.6169281006],"type":"Point"}
}