{
  "type": "Feature",
  "properties": {
    "addr:full":"Romboutstraat 1 Bilzen Limburg 3740",
    "addr:housenumber":"1",
    "addr:postcode":"3740",
    "addr:street":"Romboutstraat",
    "iso:country":"BE",
    "sg:address":"Romboutstraat 1",
    "sg:city":"Bilzen",
    "sg:classifiers":[
        {
            "category":"Fast Food",
            "type":"Food & Drink"
        }
    ],
    "sg:phone":"+32 89 79 17 97",
    "sg:postcode":"3740",
    "sg:province":"Limburg",
    "sg:tags":[
        "fried",
        "stand",
        "potato"
    ],
    "wof:name":"Troemeltsje",
    "wof:placetype":"venue"
},
  "geometry": {"coordinates":[5.5162258148,50.8695297241],"type":"Point"}
}