{
  "type": "Feature",
  "properties": {
    "addr:full":"Rue Edouard Olivier 59 Bruxelles (watermael-boitsfort) Bruxelles-Capitale 1170",
    "addr:housenumber":"59",
    "addr:postcode":"1170",
    "addr:street":"Rue Edouard Olivier",
    "iso:country":"BE",
    "sg:address":"Rue Edouard Olivier 59",
    "sg:city":"Bruxelles (watermael-boitsfort)",
    "sg:classifiers":[
        {
            "category":"Professional",
            "subcategory":"Management & Consulting",
            "type":"Services"
        }
    ],
    "sg:phone":"+32 2 662 12 07",
    "sg:postcode":"1170",
    "sg:province":"Bruxelles-Capitale",
    "sg:tags":[
        "consultant",
        "agency",
        "advertising"
    ],
    "wof:name":"J.f.e.",
    "wof:placetype":"venue"
},
  "geometry": {"coordinates":[4.372551918,50.8585014343],"type":"Point"}
}