{
  "type": "Feature",
  "properties": {
    "addr:full":"Jules Vandenbemptlaan 71 Leuven (heverlee) Vlaams-Brabant 3001",
    "addr:housenumber":"71",
    "addr:postcode":"3001",
    "addr:street":"Jules Vandenbemptlaan",
    "iso:country":"BE",
    "sg:address":"Jules Vandenbemptlaan 71",
    "sg:city":"Leuven (heverlee)",
    "sg:classifiers":[
        {
            "category":"Utilities",
            "subcategory":"Sewage",
            "type":"Services"
        }
    ],
    "sg:phone":"+32 16 23 89 88",
    "sg:postcode":"3001",
    "sg:province":"Vlaams-Brabant",
    "sg:tags":[
        "acoustic",
        "consultant"
    ],
    "wof:name":"Dynamics-structures & Systems International Nv",
    "wof:placetype":"venue"
},
  "geometry": {"coordinates":[4.6881370544,50.8617668152],"type":"Point"}
}