{
  "type": "Feature",
  "properties": {
    "addr:full":"Place Baurain 3a Florennes Namur 5620",
    "addr:housenumber":"3a",
    "addr:postcode":"5620",
    "addr:street":"Place Baurain",
    "iso:country":"BE",
    "sg:address":"Place Baurain 3a",
    "sg:city":"Florennes",
    "sg:classifiers":[
        {
            "category":"Restaurant",
            "type":"Food & Drink"
        }
    ],
    "sg:phone":"+32 71 68 61 84",
    "sg:postcode":"5620",
    "sg:province":"Namur",
    "wof:name":"Snack-bar Charly's",
    "wof:placetype":"venue"
},
  "geometry": {"coordinates":[4.6033859253,50.2513656616],"type":"Point"}
}