{
  "type": "Feature",
  "properties": {
    "addr:full":"Rijksweg 411 Maasmechelen Limburg 3630",
    "addr:housenumber":"411",
    "addr:postcode":"3630",
    "addr:street":"Rijksweg",
    "iso:country":"BE",
    "sg:address":"Rijksweg 411",
    "sg:city":"Maasmechelen",
    "sg:classifiers":[
        {
            "category":"Insurance",
            "subcategory":"Life Insurance",
            "type":"Services"
        }
    ],
    "sg:phone":"+32 89 76 43 35",
    "sg:postcode":"3630",
    "sg:province":"Limburg",
    "sg:tags":[
        "assurance"
    ],
    "wof:name":"G. Op 't Roodt",
    "wof:placetype":"venue"
},
  "geometry": {"coordinates":[5.6957759857,50.9654083252],"type":"Point"}
}