{
  "type": "Feature",
  "properties": {
    "iso:country":"BE",
    "sg:address":"Aachener Strasse 9",
    "sg:city":"Eupen",
    "sg:orig_category":"Artsen and specialisten",
    "sg:phone":"+32 87 74 42 44",
    "sg:postcode":"4700",
    "sg:province":"Li\u00e8ge",
    "wof:name":"Christine Mennicken",
    "wof:placetype":"venue"
},
  "geometry": {"coordinates":[6.0311207771,50.6323471069],"type":"Point"}
}