{
  "type": "Feature",
  "properties": {
    "addr:full":"Schemkensstraat 8 Paal Limburg 3583",
    "addr:housenumber":"8",
    "addr:postcode":"3583",
    "addr:street":"Schemkensstraat",
    "iso:country":"BE",
    "sg:address":"Schemkensstraat 8",
    "sg:city":"Paal",
    "sg:classifiers":[
        {
            "category":"Retail",
            "subcategory":"Auto Repair",
            "type":"Services"
        }
    ],
    "sg:phone":"+32 11 42 29 31",
    "sg:postcode":"3583",
    "sg:province":"Limburg",
    "sg:tags":[
        "engine",
        "industrial",
        "diesel",
        "maintenance"
    ],
    "wof:name":"Truckcenter Frederix Nv",
    "wof:placetype":"venue"
},
  "geometry": {"coordinates":[5.1754460335,51.0518112183],"type":"Point"}
}