{
  "type": "Feature",
  "properties": {
    "addr:full":"Rue Du M\u00e9ridien 56 Bruxelles (saint-josse-ten-noode) Bruxelles-Capitale 1210",
    "addr:housenumber":"56",
    "addr:postcode":"1210",
    "addr:street":"Rue Du Me\u0301Ridien",
    "iso:country":"BE",
    "sg:address":"Rue Du M\u00e9ridien 56",
    "sg:city":"Bruxelles (saint-josse-ten-noode)",
    "sg:classifiers":[
        {
            "category":"Food & Beverages",
            "subcategory":"Groceries & Convenience Stores",
            "type":"Retail Goods"
        }
    ],
    "sg:phone":"+32 2 219 88 13",
    "sg:postcode":"1210",
    "sg:province":"Bruxelles-Capitale",
    "sg:tags":[
        "grocer"
    ],
    "wof:name":"Nazmi Bakkali",
    "wof:placetype":"venue"
},
  "geometry": {"coordinates":[4.3690690994,50.8548088074],"type":"Point"}
}