{
  "type": "Feature",
  "properties": {
    "iso:country":"BE",
    "sg:address":"Rue De Boign\u00e9e 43",
    "sg:city":"Sombreffe (tongrinne)",
    "sg:classifiers":[
        {
            "category":"Health Services",
            "subcategory":"Health Practitioner",
            "type":"Services"
        }
    ],
    "sg:phone":"+32 71 88 83 06",
    "sg:postcode":"5140",
    "sg:province":"Namur",
    "sg:tags":[
        "physiotherapist"
    ],
    "wof:name":"Willems Alain",
    "wof:placetype":"venue"
},
  "geometry": {"coordinates":[4.6216168404,50.5121994019],"type":"Point"}
}