{
  "type": "Feature",
  "properties": {
    "iso:country":"BE",
    "sg:address":"Rue Herla 1",
    "sg:city":"Verviers",
    "sg:classifiers":[
        {
            "category":"Travel",
            "subcategory":"Hotels & Motels",
            "type":"Entertainment"
        }
    ],
    "sg:phone":"+32 87 23 03 69",
    "sg:postcode":"4800",
    "sg:province":"Li\u00e8ge",
    "wof:name":"Hotel Amigo",
    "wof:placetype":"venue"
},
  "geometry": {"coordinates":[5.8603801727,50.5836257935],"type":"Point"}
}