{
  "type": "Feature",
  "properties": {
    "iso:country":"BE",
    "sg:address":"Boulevard Des G\u00e9rardchamps 118b",
    "sg:city":"Verviers",
    "sg:classifiers":[
        {
            "category":"Autos & Motor Vehicles",
            "subcategory":"Boat Sales",
            "type":"Retail Goods"
        }
    ],
    "sg:phone":"+32 87 35 52 40",
    "sg:postcode":"4800",
    "sg:province":"Li\u00e8ge",
    "sg:tags":[
        "automobile",
        "racing",
        "accessory"
    ],
    "wof:name":"Moteur + Sprl",
    "wof:placetype":"venue"
},
  "geometry": {"coordinates":[5.8484349251,50.5890312195],"type":"Point"}
}