{
  "type": "Feature",
  "properties": {
    "addr:full":"Mutsereelstraat 34 Aalst Oost-Vlaanderen 9310",
    "addr:housenumber":"34",
    "addr:postcode":"9310",
    "addr:street":"Mutsereelstraat",
    "iso:country":"BE",
    "sg:address":"Mutsereelstraat 34",
    "sg:city":"Aalst",
    "sg:orig_category":"Activit\u00e9s diverses d'imprimerie",
    "sg:phone":"+32 52 35 20 68",
    "sg:postcode":"9310",
    "sg:province":"Oost-Vlaanderen",
    "wof:name":"Bureau Kwadri",
    "wof:placetype":"venue"
},
  "geometry": {"coordinates":[4.1398468018,50.9369316101],"type":"Point"}
}