{
  "type": "Feature",
  "properties": {
    "iso:country":"BE",
    "sg:address":"Molenstraat 23",
    "sg:city":"Haaltert",
    "sg:orig_category":"Banken and kredietinstellingen",
    "sg:phone":"+32 54 32 21 03",
    "sg:postcode":"9450",
    "sg:province":"Oost-Vlaanderen",
    "wof:name":"Kbc",
    "wof:placetype":"venue"
},
  "geometry": {"coordinates":[3.9967770576,50.8976745605],"type":"Point"}
}