{
  "type": "Feature",
  "properties": {
    "addr:full":"Route D'ath 213ba Jurbise Hainaut 7050",
    "addr:postcode":"7050",
    "addr:street":"Route D'Ath 213Ba;Hainaut",
    "iso:country":"BE",
    "sg:address":"Route D'ath 213ba",
    "sg:city":"Jurbise",
    "sg:orig_category":"Electrom\u00e9nager, t\u00e9l\u00e9visions and radios",
    "sg:phone":"+32 65 22 71 51",
    "sg:postcode":"7050",
    "sg:province":"Hainaut",
    "wof:name":"Jean-paul Baggio",
    "wof:placetype":"venue"
},
  "geometry": {"coordinates":[3.9308259487,50.5038566589],"type":"Point"}
}