{
  "type": "Feature",
  "properties": {
    "iso:country":"BE",
    "sg:address":"Beukenpark 12",
    "sg:city":"Aalter",
    "sg:classifiers":[
        {
            "category":"Arena",
            "subcategory":"Sports Club",
            "type":"Entertainment"
        }
    ],
    "sg:phone":"+32 9 374 66 44",
    "sg:postcode":"9880",
    "sg:province":"Oost-Vlaanderen",
    "sg:tags":[
        "de"
    ],
    "wof:name":"T.c. Nobel",
    "wof:placetype":"venue"
},
  "geometry": {"coordinates":[3.4562690258,51.072883606],"type":"Point"}
}