{
  "type": "Feature",
  "properties": {
    "iso:country":"BE",
    "sg:address":"Dracenastraat 8",
    "sg:city":"Gent",
    "sg:orig_category":"Activit\u00e9s r\u00e9cr\u00e9atives diverses. Clubs de sport. Installations and terrains de sport hors centres spo",
    "sg:phone":"+32 9 226 28 72",
    "sg:postcode":"9000",
    "sg:province":"Oost-Vlaanderen",
    "wof:name":"Jan Yoens",
    "wof:placetype":"venue"
},
  "geometry": {"coordinates":[3.71459198,51.0753479004],"type":"Point"}
}