{
  "type": "Feature",
  "properties": {
    "addr:full":"Bruulstraat 77 Brussel Bruxelles-Capitale 1130",
    "addr:housenumber":"77",
    "addr:postcode":"1130",
    "addr:street":"Bruulstraat",
    "iso:country":"BE",
    "sg:address":"Bruulstraat 77",
    "sg:city":"Brussel",
    "sg:classifiers":[
        {
            "category":"Farming",
            "subcategory":"Fish & Marine Products",
            "type":"Manufacturing & Wholesale Goods"
        }
    ],
    "sg:phone":"+32 2 245 14 35",
    "sg:postcode":"1130",
    "sg:province":"Bruxelles-Capitale",
    "sg:tags":[
        "asphalt"
    ],
    "wof:name":"Bruda Nv",
    "wof:placetype":"venue"
},
  "geometry": {"coordinates":[4.4143948555,50.9031448364],"type":"Point"}
}