{
  "type": "Feature",
  "properties": {
    "addr:full":"Industrieweg 5 Borgloon Limburg 3840",
    "addr:housenumber":"5",
    "addr:postcode":"3840",
    "addr:street":"Industrieweg",
    "iso:country":"BE",
    "sg:address":"Industrieweg 5",
    "sg:city":"Borgloon",
    "sg:classifiers":[
        {
            "category":"Freight",
            "type":"Transportation"
        }
    ],
    "sg:phone":"+32 12 74 66 08",
    "sg:postcode":"3840",
    "sg:province":"Limburg",
    "sg:tags":[
        "-",
        "transport"
    ],
    "wof:name":"L.w.s. Nv",
    "wof:placetype":"venue"
},
  "geometry": {"coordinates":[5.3436970711,50.8130531311],"type":"Point"}
}