{
  "type": "Feature",
  "properties": {
    "addr:full":"Rue Du Moulin 225 Ohey Namur 5350",
    "addr:housenumber":"225",
    "addr:postcode":"5350",
    "addr:street":"Rue Du Moulin",
    "iso:country":"BE",
    "sg:address":"Rue Du Moulin 225",
    "sg:city":"Ohey",
    "sg:orig_category":"Paramedische behandelingen",
    "sg:phone":"+32 85 61 22 98",
    "sg:postcode":"5350",
    "sg:province":"Namur",
    "wof:name":"C. Baert",
    "wof:placetype":"venue"
},
  "geometry": {"coordinates":[5.127805233,50.4363708496],"type":"Point"}
}