{
  "type": "Feature",
  "properties": {
    "addr:full":"Statiestraat 2 Zwijndrecht Antwerpen 2070",
    "addr:housenumber":"2",
    "addr:postcode":"2070",
    "addr:street":"Statiestraat",
    "iso:country":"BE",
    "sg:address":"Statiestraat 2",
    "sg:city":"Zwijndrecht",
    "sg:orig_category":"Fiduciairies",
    "sg:phone":"+32 3 252 46 06",
    "sg:postcode":"2070",
    "sg:province":"Antwerpen",
    "wof:name":"Thir\u00e9 M",
    "wof:placetype":"venue"
},
  "geometry": {"coordinates":[4.3266649246,51.2189216614],"type":"Point"}
}