{
  "type": "Feature",
  "properties": {
    "addr:full":"Markgravelei 21-35 Antwerpen Antwerpen 2018",
    "addr:postcode":"21-35;2018",
    "iso:country":"BE",
    "sg:address":"Markgravelei 21-35",
    "sg:city":"Antwerpen",
    "sg:orig_category":"Non-Classified Establishments",
    "sg:phone":"+32 3 238 32 89",
    "sg:postcode":"2018",
    "sg:province":"Antwerpen",
    "wof:name":"Cashwell Antwerpen",
    "wof:placetype":"venue"
},
  "geometry": {"coordinates":[4.3992261887,51.2004013062],"type":"Point"}
}