{
  "type": "Feature",
  "properties": {
    "addr:full":"Rue A Campenhout 8-10 Elsene/ixelles Bruxelles-Capitale 1050",
    "addr:housenumber":"8-10",
    "addr:postcode":"1050",
    "addr:street":"Rue A Campenhout",
    "iso:country":"BE",
    "sg:address":"Rue A Campenhout 8-10",
    "sg:city":"Elsene/ixelles",
    "sg:orig_category":"Herstellingen and onderhoud van auto's",
    "sg:phone":"+32 2 649 53 24",
    "sg:postcode":"1050",
    "sg:province":"Bruxelles-Capitale",
    "wof:name":"New Astic Auto",
    "wof:placetype":"venue"
},
  "geometry": {"coordinates":[4.3613448143,50.8246803284],"type":"Point"}
}