{
  "type": "Feature",
  "properties": {
    "iso:country":"BE",
    "sg:address":"Chauss\u00c9e De Li\u00c8ge 39",
    "sg:city":"Huy",
    "sg:orig_category":"Sociale huisvestingsmaatschappijen",
    "sg:phone":"+32 85 23 31 71",
    "sg:postcode":"4500",
    "sg:province":"Li\u00e8ge",
    "wof:name":"La Petite Pr Ter Pays Huy",
    "wof:placetype":"venue"
},
  "geometry": {"coordinates":[5.2380871773,50.5258712769],"type":"Point"}
}