{
  "type": "Feature",
  "properties": {
    "iso:country":"BE",
    "sg:address":"Rue Des Champs Verts 51",
    "sg:city":"Namur",
    "sg:orig_category":"Dakwerken Hout and afgeleiden Gh Installatie van houten of kunststof schrijnwerk",
    "sg:phone":"+32 81 21 38 29",
    "sg:postcode":"5020",
    "sg:province":"Namur",
    "wof:name":"Andre Sacr\u00c9",
    "wof:placetype":"venue"
},
  "geometry": {"coordinates":[4.8897199631,50.4960289001],"type":"Point"}
}