{
  "type": "Feature",
  "properties": {
    "iso:country":"BE",
    "sg:address":"Route De L'etat 45",
    "sg:city":"Oupeye",
    "sg:classifiers":[
        {
            "category":"Building & Trades",
            "subcategory":"Construction",
            "type":"Services"
        }
    ],
    "sg:phone":"+32 4 286 19 91",
    "sg:postcode":"4682",
    "sg:province":"Li\u00e8ge",
    "sg:tags":[
        "la",
        "de",
        "\u00e9quipement",
        "pour",
        "machine",
        "location"
    ],
    "wof:name":"Atelier R.c",
    "wof:placetype":"venue"
},
  "geometry": {"coordinates":[5.611700058,50.7471961975],"type":"Point"}
}