{
  "type": "Feature",
  "properties": {
    "addr:full":"Hertogsstraat 27 Brussel/bruxelles Bruxelles-Capitale 1000",
    "addr:housenumber":"27",
    "addr:postcode":"1000",
    "addr:street":"Hertogsstraat;/",
    "iso:country":"BE",
    "sg:address":"Hertogsstraat 27",
    "sg:city":"Brussel/bruxelles",
    "sg:orig_category":"Antiek Diverse zakelijke dienstverlening",
    "sg:phone":"+32 2 512 86 92",
    "sg:postcode":"1000",
    "sg:province":"Bruxelles-Capitale",
    "wof:name":"Maison Nathanaelle",
    "wof:placetype":"venue"
},
  "geometry": {"coordinates":[4.3664031029,50.8448562622],"type":"Point"}
}