{
  "type": "Feature",
  "properties": {
    "iso:country":"BE",
    "sg:address":"Rue Joseph Wauters 57",
    "sg:city":"Amay",
    "sg:classifiers":[
        {
            "category":"Retail",
            "subcategory":"Laundry & Dry Cleaning",
            "type":"Services"
        }
    ],
    "sg:phone":"+32 85 31 26 06",
    "sg:postcode":"4540",
    "sg:province":"Li\u00e8ge",
    "wof:name":"Lavoir De La Gare Scrl",
    "wof:placetype":"venue"
},
  "geometry": {"coordinates":[5.3211197853,50.5464782715],"type":"Point"}
}