{
  "type": "Feature",
  "properties": {
    "iso:country":"BE",
    "sg:address":"Veldonkstraat 321",
    "sg:city":"Tremelo (baal)",
    "sg:classifiers":[
        {
            "category":"Airport",
            "subcategory":"International",
            "type":"Transportation"
        }
    ],
    "sg:phone":"+32 16 53 05 36",
    "sg:postcode":"3128",
    "sg:province":"Vlaams-Brabant",
    "sg:tags":[
        "-",
        "transport"
    ],
    "wof:name":"Van Den Acker L & Zn Bvba",
    "wof:placetype":"venue"
},
  "geometry": {"coordinates":[4.764480114,50.9902687073],"type":"Point"}
}