{
  "type": "Feature",
  "properties": {
    "iso:country":"BE",
    "sg:address":"Hameau Du Touquet 2",
    "sg:city":"Tournai",
    "sg:classifiers":[
        {
            "category":"Food & Beverages",
            "subcategory":"Fruits & Vegetables",
            "type":"Retail Goods"
        }
    ],
    "sg:phone":"+32 69 35 23 05",
    "sg:postcode":"7522",
    "sg:province":"Hainaut",
    "sg:tags":[
        "l\u00e9gumes",
        "gr"
    ],
    "wof:name":"Millet Joseph Et Cie",
    "wof:placetype":"venue"
},
  "geometry": {"coordinates":[3.3002359867,50.6223831177],"type":"Point"}
}