{
  "type": "Feature",
  "properties": {
    "iso:country":"BE",
    "sg:address":"Place Saint-martin 3",
    "sg:city":"Beauvechain",
    "sg:orig_category":"Enseignement maternel and primaire",
    "sg:phone":"+32 10 86 60 09",
    "sg:postcode":"1320",
    "sg:province":"Brabant Wallon",
    "wof:name":"Ecole Fond. Communale",
    "wof:placetype":"venue"
},
  "geometry": {"coordinates":[4.7462058067,50.7782745361],"type":"Point"}
}