{
  "type": "Feature",
  "properties": {
    "addr:full":"Kapelaanstraat 7 Maldegem Oost-Vlaanderen 9990",
    "addr:housenumber":"7",
    "addr:postcode":"9990",
    "addr:street":"Kapelaanstraat",
    "iso:country":"BE",
    "sg:address":"Kapelaanstraat 7",
    "sg:city":"Maldegem",
    "sg:classifiers":[
        {
            "category":"Professional",
            "subcategory":"Computer Services",
            "type":"Services"
        }
    ],
    "sg:phone":"+32 50 72 89 89",
    "sg:postcode":"9990",
    "sg:province":"Oost-Vlaanderen",
    "sg:tags":[
        "-",
        "processing",
        "data",
        "software"
    ],
    "wof:name":"Ardis I.s. Optimalisatie",
    "wof:placetype":"venue"
},
  "geometry": {"coordinates":[3.450592041,51.210269928],"type":"Point"}
}