{
  "type": "Feature",
  "properties": {
    "addr:full":"Chem Du Fort Des Voiles 64 Bonlez Brabant Wallon 1325",
    "addr:housenumber":"64",
    "addr:postcode":"1325",
    "addr:street":"Chem Du Fort Des Voiles",
    "iso:country":"BE",
    "sg:address":"Chem Du Fort Des Voiles 64",
    "sg:city":"Bonlez",
    "sg:classifiers":[
        {
            "category":"Farming",
            "subcategory":"Livestock Farm",
            "type":"Manufacturing & Wholesale Goods"
        }
    ],
    "sg:phone":"+32 10 68 84 42",
    "sg:postcode":"1325",
    "sg:province":"Brabant Wallon",
    "sg:tags":[
        "breeding",
        "agriculture",
        "animal"
    ],
    "wof:name":"M Denis Collette",
    "wof:placetype":"venue"
},
  "geometry": {"coordinates":[4.7065119743,50.7055511475],"type":"Point"}
}