{
  "type": "Feature",
  "properties": {
    "addr:full":"Bredestraat 46 Antwerpen Antwerpen 2000",
    "addr:housenumber":"46",
    "addr:postcode":"2000",
    "addr:street":"Bredestraat",
    "iso:country":"BE",
    "sg:address":"Bredestraat 46",
    "sg:city":"Antwerpen",
    "sg:orig_category":"Pain, p\u00e2tisseries and confiseries",
    "sg:phone":"+32 3 233 49 13",
    "sg:postcode":"2000",
    "sg:province":"Antwerpen",
    "wof:name":"Fa. Bruers",
    "wof:placetype":"venue"
},
  "geometry": {"coordinates":[4.4018921852,51.2141189575],"type":"Point"}
}