{
  "type": "Feature",
  "properties": {
    "iso:country":"BE",
    "sg:address":"Rue Du Centre 103",
    "sg:city":"Lierneux",
    "sg:classifiers":[
        {
            "category":"Wholesale",
            "subcategory":"Medical Equipment & Supplies",
            "type":"Manufacturing & Wholesale Goods"
        }
    ],
    "sg:phone":"+32 80 31 84 22",
    "sg:postcode":"4990",
    "sg:province":"Li\u00e8ge",
    "sg:tags":[
        "aid",
        "hearing"
    ],
    "wof:name":"Monic'optic",
    "wof:placetype":"venue"
},
  "geometry": {"coordinates":[5.7908787727,50.2834968567],"type":"Point"}
}