{
  "type": "Feature",
  "properties": {
    "iso:country":"BE",
    "sg:address":"Armand Thierrylaan 21",
    "sg:city":"Leuven",
    "sg:orig_category":"Rusthuizen and serviceflats",
    "sg:phone":"+32 16 40 48 03",
    "sg:postcode":"3001",
    "sg:province":"Vlaams-Brabant",
    "wof:name":"Ons Geluk",
    "wof:placetype":"venue"
},
  "geometry": {"coordinates":[4.7090940475,50.8606910706],"type":"Point"}
}