{
  "type": "Feature",
  "properties": {
    "addr:full":"Avenue Guillaume Joachim 44 Waremme Li\u00e8ge 4300",
    "addr:housenumber":"44",
    "addr:postcode":"4300",
    "addr:street":"Avenue Guillaume Joachim",
    "iso:country":"BE",
    "sg:address":"Avenue Guillaume Joachim 44",
    "sg:city":"Waremme",
    "sg:orig_category":"Enseignement maternel and primaire",
    "sg:phone":"+32 19 32 60 38",
    "sg:postcode":"4300",
    "sg:province":"Li\u00e8ge",
    "wof:name":"Ecole Primaire Libre",
    "wof:placetype":"venue"
},
  "geometry": {"coordinates":[5.2567372322,50.6962280273],"type":"Point"}
}