{
  "type": "Feature",
  "properties": {
    "iso:country":"BE",
    "sg:address":"Grand'place 21",
    "sg:city":"Arlon",
    "sg:classifiers":[
        {
            "category":"Shopping",
            "subcategory":"Books",
            "type":"Retail Goods"
        }
    ],
    "sg:phone":"+32 63 22 24 74",
    "sg:postcode":"6700",
    "sg:province":"Luxembourg",
    "sg:tags":[
        "bookseller"
    ],
    "wof:name":"Le Point Virgule",
    "wof:placetype":"venue"
},
  "geometry": {"coordinates":[5.7947201729,49.6745986938],"type":"Point"}
}