{
  "type": "Feature",
  "properties": {
    "addr:full":"Rue F. Nicolay 136 Saint-nicolas Li\u00e8ge 4420",
    "addr:housenumber":"136",
    "addr:postcode":"4420",
    "addr:street":"Rue F. Nicolay;Saint-Nicolas Lie\u0300Ge",
    "iso:country":"BE",
    "sg:address":"Rue F. Nicolay 136",
    "sg:city":"Saint-nicolas",
    "sg:orig_category":"Services de publipostage",
    "sg:phone":"+32 4 252 81 70",
    "sg:postcode":"4420",
    "sg:province":"Li\u00e8ge",
    "wof:name":"Medi Quick",
    "wof:placetype":"venue"
},
  "geometry": {"coordinates":[5.5415239334,50.63123703],"type":"Point"}
}