{
  "type": "Feature",
  "properties": {
    "addr:full":"Stationsstraat 13b1 Linkebeek Vlaams-Brabant 1630",
    "addr:housenumber":"13b1",
    "addr:postcode":"1630",
    "addr:street":"Stationsstraat",
    "iso:country":"BE",
    "sg:address":"Stationsstraat 13b1",
    "sg:city":"Linkebeek",
    "sg:orig_category":"Verhuisdiensten",
    "sg:phone":"+32 2 380 64 05",
    "sg:postcode":"1630",
    "sg:province":"Vlaams-Brabant",
    "wof:name":"Charles Verbeeck",
    "wof:placetype":"venue"
},
  "geometry": {"coordinates":[4.3383078575,50.7738304138],"type":"Point"}
}