{
  "type": "Feature",
  "properties": {
    "addr:full":"Mandekensstraat 138 Dendermonde Oost-Vlaanderen 9200",
    "addr:housenumber":"138",
    "addr:postcode":"9200",
    "addr:street":"Mandekensstraat;Oost-Vlaanderen",
    "iso:country":"BE",
    "sg:address":"Mandekensstraat 138",
    "sg:city":"Dendermonde",
    "sg:orig_category":"Alimentation sp\u00e9cialis\u00e9e",
    "sg:phone":"+32 52 33 30 74",
    "sg:postcode":"9200",
    "sg:province":"Oost-Vlaanderen",
    "wof:name":"H. Cools",
    "wof:placetype":"venue"
},
  "geometry": {"coordinates":[4.0983099937,51.0315208435],"type":"Point"}
}