{
  "type": "Feature",
  "properties": {
    "addr:full":"All\u00e9e Des Noisetiers 25 Li\u00e8ge 1 (angleur) Li\u00e8ge 4031",
    "addr:housenumber":"25;1",
    "addr:postcode":"4031",
    "addr:street":"Alle\u0301E Des Noisetiers",
    "iso:country":"BE",
    "sg:address":"All\u00e9e Des Noisetiers 25",
    "sg:city":"Li\u00e8ge 1 (angleur)",
    "sg:classifiers":[
        {
            "category":"Professional",
            "subcategory":"Engineering",
            "type":"Services"
        }
    ],
    "sg:phone":"+32 4 366 16 16",
    "sg:postcode":"4031",
    "sg:province":"Li\u00e8ge",
    "sg:tags":[
        "-"
    ],
    "wof:name":"Greisch Ing\u00e9nierie Sa",
    "wof:placetype":"venue"
},
  "geometry": {"coordinates":[5.5713028908,50.599822998],"type":"Point"}
}