{
  "type": "Feature",
  "properties": {
    "addr:full":"Parklaan 54 Middelkerke West-Vlaanderen 8430",
    "addr:housenumber":"54",
    "addr:postcode":"8430",
    "addr:street":"Parklaan",
    "iso:country":"BE",
    "sg:address":"Parklaan 54",
    "sg:city":"Middelkerke",
    "sg:orig_category":"Activit\u00e9s diverses d'imprimerie",
    "sg:phone":"+32 59 31 11 31",
    "sg:postcode":"8430",
    "sg:province":"West-Vlaanderen",
    "wof:name":"K. Flamey",
    "wof:placetype":"venue"
},
  "geometry": {"coordinates":[2.8186399937,51.1875267029],"type":"Point"}
}