{
  "type": "Feature",
  "properties": {
    "addr:full":"Avenue Boulogne Billancourt 33 Rixensart Brabant Wallon 1330",
    "addr:housenumber":"33",
    "addr:postcode":"1330",
    "addr:street":"Avenue;Billancourt;Wallon",
    "iso:country":"BE",
    "sg:address":"Avenue Boulogne Billancourt 33",
    "sg:city":"Rixensart",
    "sg:classifiers":[
        {
            "category":"Health Services",
            "subcategory":"Doctor",
            "type":"Services"
        }
    ],
    "sg:phone":"+32 2 654 01 65",
    "sg:postcode":"1330",
    "sg:province":"Brabant Wallon",
    "sg:tags":[
        "medicinephysicians",
        "surgeon"
    ],
    "wof:name":"Adam Christian",
    "wof:placetype":"venue"
},
  "geometry": {"coordinates":[4.529291153,50.7010574341],"type":"Point"}
}