{
  "type": "Feature",
  "properties": {
    "iso:country":"BE",
    "sg:address":"Centrum Zuid 2080",
    "sg:city":"Houthalen",
    "sg:classifiers":[
        {
            "category":"Shopping",
            "subcategory":"Clothing, Apparel, & Fashions",
            "type":"Retail Goods"
        }
    ],
    "sg:phone":"+32 11 60 88 06",
    "sg:postcode":"3530",
    "sg:province":"Limburg",
    "sg:tags":[
        "textile",
        "clothing",
        "clothes"
    ],
    "wof:name":"Jbc Nv",
    "wof:placetype":"venue"
},
  "geometry": {"coordinates":[5.3605260849,51.0150642395],"type":"Point"}
}