{
  "type": "Feature",
  "properties": {
    "addr:full":"Sint-martensstraat 36 Ronse/renaix Oost-Vlaanderen 9600",
    "addr:housenumber":"36",
    "addr:postcode":"9600",
    "addr:street":"Sint-Martensstraat",
    "iso:country":"BE",
    "sg:address":"Sint-martensstraat 36",
    "sg:city":"Ronse/renaix",
    "sg:orig_category":"Artsen and specialisten",
    "sg:phone":"+32 55 21 66 98",
    "sg:postcode":"9600",
    "sg:province":"Oost-Vlaanderen",
    "wof:name":"Eva Debusscher",
    "wof:placetype":"venue"
},
  "geometry": {"coordinates":[3.6001899242,50.74842453],"type":"Point"}
}