{
  "type": "Feature",
  "properties": {
    "iso:country":"BE",
    "sg:address":"De Bruynlaan 51",
    "sg:city":"Antwerpen",
    "sg:orig_category":"Instruments de musique",
    "sg:phone":"+32 3 825 48 38",
    "sg:postcode":"2610",
    "sg:province":"Antwerpen",
    "wof:name":"Huis Mills Audio",
    "wof:placetype":"venue"
},
  "geometry": {"coordinates":[4.3946051598,51.1691131592],"type":"Point"}
}