{
  "type": "Feature",
  "properties": {
    "iso:country":"BE",
    "sg:address":"Pachtgoedstraat 2",
    "sg:city":"Temse",
    "sg:classifiers":[
        {
            "category":"Utilities",
            "subcategory":"Cable",
            "type":"Services"
        }
    ],
    "sg:phone":"+32 3 780 67 30",
    "sg:postcode":"9140",
    "sg:province":"Oost-Vlaanderen",
    "sg:tags":[
        "wire",
        "electric"
    ],
    "wof:name":"Eltra Nv",
    "wof:placetype":"venue"
},
  "geometry": {"coordinates":[4.1920719147,51.1481018066],"type":"Point"}
}