{
  "type": "Feature",
  "properties": {
    "addr:full":"Patronagestrasse 3be Kelmis/la Calamine Li\u00e8ge 4720",
    "addr:housenumber":"3be",
    "addr:postcode":"4720",
    "addr:street":"Patronagestrasse",
    "iso:country":"BE",
    "sg:address":"Patronagestrasse 3be",
    "sg:city":"Kelmis/la Calamine",
    "sg:orig_category":"Kapsalons",
    "sg:phone":"+32 87 65 39 43",
    "sg:postcode":"4720",
    "sg:province":"Li\u00e8ge",
    "wof:name":"Coiffure La Donna",
    "wof:placetype":"venue"
},
  "geometry": {"coordinates":[6.0099949837,50.7174415588],"type":"Point"}
}