{
  "type": "Feature",
  "properties": {
    "addr:full":"Liersesteenweg 25 Lint Antwerpen 2547",
    "addr:housenumber":"25",
    "addr:postcode":"2547",
    "addr:street":"Liersesteenweg",
    "iso:country":"BE",
    "sg:address":"Liersesteenweg 25",
    "sg:city":"Lint",
    "sg:classifiers":[
        {
            "category":"Bars & Pubs",
            "type":"Food & Drink"
        }
    ],
    "sg:phone":"+32 3 455 12 43",
    "sg:postcode":"2547",
    "sg:province":"Antwerpen",
    "sg:tags":[
        "tavern"
    ],
    "wof:name":"Witte Merel (de)",
    "wof:placetype":"venue"
},
  "geometry": {"coordinates":[4.4979228973,51.1272621155],"type":"Point"}
}