{
  "type": "Feature",
  "properties": {
    "addr:full":"Morelgem 8 Sint-lievens-houtem Oost-Vlaanderen 9520",
    "addr:housenumber":"8",
    "addr:postcode":"9520",
    "addr:street":"Morelgem;Oost-Vlaanderen",
    "iso:country":"BE",
    "sg:address":"Morelgem 8",
    "sg:city":"Sint-lievens-houtem",
    "sg:orig_category":"Installatie van houten of kunststof schrijnwerk Installatie van metalen schrijnwerk",
    "sg:phone":"+32 53 62 41 84",
    "sg:postcode":"9520",
    "sg:province":"Oost-Vlaanderen",
    "wof:name":"Patho",
    "wof:placetype":"venue"
},
  "geometry": {"coordinates":[3.8933811188,50.9259223938],"type":"Point"}
}