{
  "type": "Feature",
  "properties": {
    "iso:country":"BE",
    "sg:address":"Dumortierlaan 159",
    "sg:city":"Knokke-heist (knokke)",
    "sg:classifiers":[
        {
            "category":"Real Estate",
            "subcategory":"Real Estate Services",
            "type":"Services"
        }
    ],
    "sg:phone":"+32 50 61 16 75",
    "sg:postcode":"8300",
    "sg:province":"West-Vlaanderen",
    "wof:name":"Immo Service",
    "wof:placetype":"venue"
},
  "geometry": {"coordinates":[3.287694931,51.3467254639],"type":"Point"}
}