{
  "type": "Feature",
  "properties": {
    "iso:country":"BE",
    "sg:address":"Opperstebosstraat 17",
    "sg:city":"Gooik (oetingen)",
    "sg:classifiers":[
        {
            "category":"Health Services",
            "subcategory":"Doctor",
            "type":"Services"
        }
    ],
    "sg:phone":"+32 54 56 73 26",
    "sg:postcode":"1755",
    "sg:province":"Vlaams-Brabant",
    "sg:tags":[
        "psychotherapist",
        "psychoanalyst"
    ],
    "wof:name":"Berghmans",
    "wof:placetype":"venue"
},
  "geometry": {"coordinates":[4.0451607704,50.7769165039],"type":"Point"}
}