{
  "type": "Feature",
  "properties": {
    "iso:country":"BE",
    "sg:address":"Rue Des Roses 10",
    "sg:city":"Charleroi",
    "sg:orig_category":"Editeurs de livres",
    "sg:phone":"+32 71 36 84 19",
    "sg:postcode":"6001",
    "sg:province":"Hainaut",
    "wof:name":"Immo Music",
    "wof:placetype":"venue"
},
  "geometry": {"coordinates":[4.4436531067,50.3862915039],"type":"Point"}
}