{
  "type": "Feature",
  "properties": {
    "iso:country":"BE",
    "sg:address":"Rue Jules Destr\u00c9e 194",
    "sg:city":"Quaregnon",
    "sg:orig_category":"Pain, p\u00e2tisseries and confiseries",
    "sg:phone":"+32 65 78 18 75",
    "sg:postcode":"7390",
    "sg:province":"Hainaut",
    "wof:name":"Boulang. Moderne Jemappes",
    "wof:placetype":"venue"
},
  "geometry": {"coordinates":[3.8653740883,50.4444274902],"type":"Point"}
}