{
  "type": "Feature",
  "properties": {
    "addr:full":"Paleizenstraat 70 Brussel Bruxelles-Capitale 1030",
    "addr:housenumber":"70",
    "addr:postcode":"1030",
    "addr:street":"Paleizenstraat",
    "iso:country":"BE",
    "sg:address":"Paleizenstraat 70",
    "sg:city":"Brussel",
    "sg:orig_category":"Villages de vacances",
    "sg:phone":"+32 2 217 08 27",
    "sg:postcode":"1030",
    "sg:province":"Bruxelles-Capitale",
    "wof:name":"Openluchtcentra Voor Scholieren Vzw",
    "wof:placetype":"venue"
},
  "geometry": {"coordinates":[4.3679461479,50.8597984314],"type":"Point"}
}