{
  "type": "Feature",
  "properties": {
    "addr:full":"Rue De La Goffe 25 Esneux Li\u00e8ge 4130",
    "addr:housenumber":"25",
    "addr:postcode":"4130",
    "addr:street":"Rue De La Goffe",
    "iso:country":"BE",
    "sg:address":"Rue De La Goffe 25",
    "sg:city":"Esneux",
    "sg:orig_category":"Maisons de repos and r\u00e9sidences",
    "sg:phone":"+32 4 380 35 61",
    "sg:postcode":"4130",
    "sg:province":"Li\u00e8ge",
    "wof:name":"R\u00c9sidence Les Prunus",
    "wof:placetype":"venue"
},
  "geometry": {"coordinates":[5.5845179558,50.5390892029],"type":"Point"}
}