{
  "type": "Feature",
  "properties": {
    "addr:full":"Voie De Rossart 36 Libin (ochamps) Luxembourg 6890",
    "addr:housenumber":"36",
    "addr:postcode":"6890",
    "addr:street":"Voie De Rossart",
    "iso:country":"BE",
    "sg:address":"Voie De Rossart 36",
    "sg:city":"Libin (ochamps)",
    "sg:classifiers":[
        {
            "category":"Professional",
            "subcategory":"Accounting & Tax Preparation",
            "type":"Services"
        }
    ],
    "sg:phone":"+32 61 22 20 40",
    "sg:postcode":"6890",
    "sg:province":"Luxembourg",
    "sg:tags":[
        "bookkeeper"
    ],
    "wof:name":"Moniotte J-l",
    "wof:placetype":"venue"
},
  "geometry": {"coordinates":[5.2790141106,49.9194335938],"type":"Point"}
}