{
  "type": "Feature",
  "properties": {
    "addr:full":"Eikelaarstraat 24 Genk Limburg 3600",
    "addr:housenumber":"24",
    "addr:postcode":"3600",
    "addr:street":"Eikelaarstraat",
    "iso:country":"BE",
    "sg:address":"Eikelaarstraat 24",
    "sg:city":"Genk",
    "sg:classifiers":[
        {
            "category":"Airport",
            "subcategory":"International",
            "type":"Transportation"
        }
    ],
    "sg:phone":"+32 89 35 66 00",
    "sg:postcode":"3600",
    "sg:province":"Limburg",
    "sg:tags":[
        "-",
        "transport"
    ],
    "wof:name":"Trippaers Nv",
    "wof:placetype":"venue"
},
  "geometry": {"coordinates":[5.4811401367,50.9264411926],"type":"Point"}
}