{
  "type": "Feature",
  "properties": {
    "addr:full":"Vaerestraat 22 Dentergem (oeselgem) West-Vlaanderen 8720",
    "addr:housenumber":"22",
    "addr:postcode":"8720",
    "addr:street":"Vaerestraat",
    "iso:country":"BE",
    "sg:address":"Vaerestraat 22",
    "sg:city":"Dentergem (oeselgem)",
    "sg:classifiers":[
        {
            "category":"Parking",
            "subcategory":"Garage",
            "type":"Transportation"
        }
    ],
    "sg:phone":"+32 9 388 90 24",
    "sg:postcode":"8720",
    "sg:province":"West-Vlaanderen",
    "sg:tags":[
        "truck",
        "-",
        "dump",
        "transport"
    ],
    "wof:name":"Van Betsbrugge Luc Bvba",
    "wof:placetype":"venue"
},
  "geometry": {"coordinates":[3.4230720997,50.9349365234],"type":"Point"}
}