{
  "type": "Feature",
  "properties": {
    "addr:full":"Rue Saint-s\u00e9bastien 29 Wavre Brabant Wallon 1300",
    "addr:housenumber":"29;1300",
    "addr:street":"Rue Saint-Se\u0301Bastien",
    "iso:country":"BE",
    "sg:address":"Rue Saint-s\u00e9bastien 29",
    "sg:city":"Wavre",
    "sg:classifiers":[
        {
            "category":"Professional",
            "subcategory":"Management & Consulting",
            "type":"Services"
        }
    ],
    "sg:phone":"+32 10 24 78 87",
    "sg:postcode":"1300",
    "sg:province":"Brabant Wallon",
    "sg:tags":[
        "-",
        "processing",
        "data",
        "consultant"
    ],
    "wof:name":"Dehaen P",
    "wof:placetype":"venue"
},
  "geometry": {"coordinates":[4.6158618927,50.7190437317],"type":"Point"}
}