{
  "type": "Feature",
  "properties": {
    "iso:country":"BE",
    "sg:address":"Rue De L\u00b4h\u00d4tel De Ville 7",
    "sg:city":"Frasnes-lez-anvaing",
    "sg:orig_category":"S\u00e9lection de personnel and placement",
    "sg:phone":"+32 69 87 16 43",
    "sg:postcode":"7911",
    "sg:province":"Hainaut",
    "wof:name":"S.l.a.i.e. Frasnes-lez-anvaing",
    "wof:placetype":"venue"
},
  "geometry": {"coordinates":[3.618432045,50.6672363281],"type":"Point"}
}