{
  "type": "Feature",
  "properties": {
    "addr:full":"Sint-katharinastraat 58 Kortrijk West-Vlaanderen 8501",
    "addr:housenumber":"58",
    "addr:postcode":"8501",
    "addr:street":"Sint-Katharinastraat",
    "iso:country":"BE",
    "sg:address":"Sint-katharinastraat 58",
    "sg:city":"Kortrijk",
    "sg:orig_category":"Electrom\u00e9nager, t\u00e9l\u00e9visions and radios. R\u00e9parations \u00e0 domicile d'appareils \u00e9lectriques. R\u00e9parations ",
    "sg:phone":"+32 56 35 94 10",
    "sg:postcode":"8501",
    "sg:province":"West-Vlaanderen",
    "wof:name":"Werner Gheysen",
    "wof:placetype":"venue"
},
  "geometry": {"coordinates":[3.2312951088,50.8663749695],"type":"Point"}
}