{
  "type": "Feature",
  "properties": {
    "iso:country":"BE",
    "sg:address":"Gentsesteenweg 303",
    "sg:city":"Erpe-mere",
    "sg:classifiers":[
        {
            "category":"Wholesale",
            "subcategory":"Vending Machines",
            "type":"Manufacturing & Wholesale Goods"
        }
    ],
    "sg:phone":"+32 53 80 35 12",
    "sg:postcode":"9420",
    "sg:province":"Oost-Vlaanderen",
    "sg:tags":[
        "shop",
        "plants",
        "technical",
        "factory",
        "cleaning",
        "maintenance"
    ],
    "wof:name":"De Wolf Nv",
    "wof:placetype":"venue"
},
  "geometry": {"coordinates":[3.9620680809,50.9458694458],"type":"Point"}
}