{
  "type": "Feature",
  "properties": {
    "addr:full":"Kasteelstraat 9 Denderleeuw Oost-Vlaanderen 9470",
    "addr:housenumber":"9",
    "addr:postcode":"9470",
    "addr:street":"Kasteelstraat",
    "iso:country":"BE",
    "sg:address":"Kasteelstraat 9",
    "sg:city":"Denderleeuw",
    "sg:classifiers":[
        {
            "category":"Fast Food",
            "type":"Food & Drink"
        }
    ],
    "sg:phone":"+32 53 68 35 14",
    "sg:postcode":"9470",
    "sg:province":"Oost-Vlaanderen",
    "sg:tags":[
        "fried",
        "stand",
        "potato"
    ],
    "wof:name":"Kasteelken",
    "wof:placetype":"venue"
},
  "geometry": {"coordinates":[4.0782117844,50.873626709],"type":"Point"}
}