{
  "type": "Feature",
  "properties": {
    "addr:full":"Rue Des Tendeurs 72 Seraing Li\u00e8ge 4100",
    "addr:housenumber":"72",
    "addr:postcode":"4100",
    "addr:street":"Rue Des Tendeurs",
    "iso:country":"BE",
    "sg:address":"Rue Des Tendeurs 72",
    "sg:city":"Seraing",
    "sg:orig_category":"Artistes ind\u00e9pendants",
    "sg:phone":"+32 4 336 54 22",
    "sg:postcode":"4100",
    "sg:province":"Li\u00e8ge",
    "wof:name":"Lucien Thunus",
    "wof:placetype":"venue"
},
  "geometry": {"coordinates":[5.5123529434,50.5938682556],"type":"Point"}
}