{
  "type": "Feature",
  "properties": {
    "addr:full":"Jan Bolstraat 69 Mechelen Antwerpen 2800",
    "addr:housenumber":"69",
    "addr:postcode":"2800",
    "addr:street":"Jan Bolstraat",
    "iso:country":"BE",
    "sg:address":"Jan Bolstraat 69",
    "sg:city":"Mechelen",
    "sg:classifiers":[
        {
            "category":"Health Services",
            "subcategory":"Health Practitioner",
            "type":"Services"
        }
    ],
    "sg:phone":"+32 15 34 04 69",
    "sg:postcode":"2800",
    "sg:province":"Antwerpen",
    "sg:tags":[
        "physiotherapist"
    ],
    "wof:name":"Pepermans Bart",
    "wof:placetype":"venue"
},
  "geometry": {"coordinates":[4.4890890121,51.0322647095],"type":"Point"}
}