{
  "type": "Feature",
  "properties": {
    "addr:full":"Seminariestraat 2 Gent Oost-Vlaanderen 9000",
    "addr:housenumber":"2",
    "addr:postcode":"9000",
    "addr:street":"Seminariestraat;Oost-Vlaanderen",
    "iso:country":"BE",
    "sg:address":"Seminariestraat 2",
    "sg:city":"Gent",
    "sg:orig_category":"Krantenuitgeverijen Tijdschriftenuitgeverijen",
    "sg:phone":"+32 9 267 86 30",
    "sg:postcode":"9000",
    "sg:province":"Oost-Vlaanderen",
    "wof:name":"G.o.m.o.v.",
    "wof:placetype":"venue"
},
  "geometry": {"coordinates":[3.7298018932,51.0518760681],"type":"Point"}
}