{
  "type": "Feature",
  "properties": {
    "iso:country":"BE",
    "sg:address":"P. De Denterghemlaan 50",
    "sg:city":"Sint-martens-latem",
    "sg:orig_category":"Installation de menuiserie en bois and plastique",
    "sg:phone":"+32 9 282 52 71",
    "sg:postcode":"9831",
    "sg:province":"Oost-Vlaanderen",
    "wof:name":"Schelde International",
    "wof:placetype":"venue"
},
  "geometry": {"coordinates":[3.6116878986,51.011920929],"type":"Point"}
}