{
  "type": "Feature",
  "properties": {
    "iso:country":"BE",
    "sg:address":"Weg Naar As 99",
    "sg:city":"Meeuwen-gruitrode",
    "sg:orig_category":"Paardenfokkers",
    "sg:phone":"+32 89 85 35 78",
    "sg:postcode":"3670",
    "sg:province":"Limburg",
    "wof:name":"Philippaerts Ludo",
    "wof:placetype":"venue"
},
  "geometry": {"coordinates":[5.5205497742,51.0963516235],"type":"Point"}
}