{
  "type": "Feature",
  "properties": {
    "addr:full":"Haasstrasse 21 Eupen Li\u00e8ge 4700",
    "addr:housenumber":"21",
    "addr:postcode":"4700",
    "addr:street":"Haasstrasse",
    "iso:country":"BE",
    "sg:address":"Haasstrasse 21",
    "sg:city":"Eupen",
    "sg:orig_category":"Verplichte sociale verzekeringen",
    "sg:phone":"+32 87 55 47 61",
    "sg:postcode":"4700",
    "sg:province":"Li\u00e8ge",
    "wof:name":"Christl. Krankenkasse",
    "wof:placetype":"venue"
},
  "geometry": {"coordinates":[6.0375437737,50.62342453],"type":"Point"}
}