{
  "type": "Feature",
  "properties": {
    "addr:full":"Tuyaertsstraat 16 Boom Antwerpen 2850",
    "addr:housenumber":"16",
    "addr:postcode":"2850",
    "addr:street":"Tuyaertsstraat",
    "iso:country":"BE",
    "sg:address":"Tuyaertsstraat 16",
    "sg:city":"Boom",
    "sg:classifiers":[
        {
            "category":"Retail",
            "subcategory":"Repair Shop",
            "type":"Services"
        }
    ],
    "sg:phone":"+32 3 844 86 68",
    "sg:postcode":"2850",
    "sg:province":"Antwerpen",
    "sg:tags":[
        "-",
        "clothing",
        "alteration"
    ],
    "wof:name":"Creatief",
    "wof:placetype":"venue"
},
  "geometry": {"coordinates":[4.366710186,51.0877914429],"type":"Point"}
}