{
  "type": "Feature",
  "properties": {
    "addr:full":"Eksaardedorp 116 Lokeren 9108",
    "addr:housenumber":"116",
    "addr:postcode":"9108",
    "addr:street":"Lokeren",
    "iso:country":"BE",
    "sg:address":"Eksaardedorp 116",
    "sg:city":"Lokeren",
    "sg:classifiers":[
        {
            "category":"Banks & Credit Unions",
            "subcategory":"Bank",
            "type":"Services"
        }
    ],
    "sg:phone":"+32 55 46 82 79",
    "sg:postcode":"9108",
    "wof:name":"Gemeentekrediet",
    "wof:placetype":"venue"
},
  "geometry": {"coordinates":[9.3477802277,47.3141899109],"type":"Point"}
}