{
  "type": "Feature",
  "properties": {
    "iso:country":"BE",
    "sg:address":"Musschaverstraat 51",
    "sg:city":"Nevele (landegem)",
    "sg:classifiers":[
        {
            "category":"Professional",
            "subcategory":"Management & Consulting",
            "type":"Services"
        }
    ],
    "sg:phone":"+32 9 371 75 17",
    "sg:postcode":"9850",
    "sg:province":"Oost-Vlaanderen",
    "sg:tags":[
        "consultant"
    ],
    "wof:name":"Atw Technisch Adviesbureau",
    "wof:placetype":"venue"
},
  "geometry": {"coordinates":[3.6071310043,51.0635528564],"type":"Point"}
}