{
  "type": "Feature",
  "properties": {
    "addr:full":"Groene Wandeling 18 Schilde ('s Gravenwezel) Antwerpen 2970",
    "addr:housenumber":"18",
    "addr:postcode":"2970",
    "addr:street":"Groene Wandeling;S",
    "iso:country":"BE",
    "sg:address":"Groene Wandeling 18",
    "sg:city":"Schilde ('s Gravenwezel)",
    "sg:classifiers":[
        {
            "category":"Professional",
            "subcategory":"Accounting & Tax Preparation",
            "type":"Services"
        }
    ],
    "sg:phone":"+32 3 383 67 74",
    "sg:postcode":"2970",
    "sg:province":"Antwerpen",
    "sg:tags":[
        "bookkeeper"
    ],
    "wof:name":"Goeminne Bvba",
    "wof:placetype":"venue"
},
  "geometry": {"coordinates":[4.5799231529,51.261100769],"type":"Point"}
}