{
  "type": "Feature",
  "properties": {
    "iso:country":"BE",
    "sg:address":"De Judestraat 101",
    "sg:city":"Knokke-heist (knokke)",
    "sg:classifiers":[
        {
            "category":"Building & Trades",
            "subcategory":"Pest Control",
            "type":"Services"
        }
    ],
    "sg:phone":"+32 50 61 21 34",
    "sg:postcode":"8300",
    "sg:province":"West-Vlaanderen",
    "sg:tags":[
        "painting",
        "contractor"
    ],
    "wof:name":"Crabbe F",
    "wof:placetype":"venue"
},
  "geometry": {"coordinates":[3.2954149246,51.3409080505],"type":"Point"}
}