{
  "type": "Feature",
  "properties": {
    "addr:full":"Steenstraat 37 Antwerpen (ekeren) Antwerpen 2180",
    "addr:housenumber":"37",
    "addr:postcode":"2180",
    "addr:street":"Steenstraat",
    "iso:country":"BE",
    "sg:address":"Steenstraat 37",
    "sg:city":"Antwerpen (ekeren)",
    "sg:orig_category":"Accumulators",
    "sg:phone":"+32 3 542 69 88",
    "sg:postcode":"2180",
    "sg:province":"Antwerpen",
    "wof:name":"Axioma Nv",
    "wof:placetype":"venue"
},
  "geometry": {"coordinates":[4.4182572365,51.2778625488],"type":"Point"}
}