{
  "type": "Feature",
  "properties": {
    "iso:country":"BE",
    "sg:address":"Rue De Bomel 105",
    "sg:city":"Namur",
    "sg:orig_category":"Zalen voor culturele evenementen",
    "sg:phone":"+32 81 22 99 39",
    "sg:postcode":"5000",
    "sg:province":"Namur",
    "wof:name":"Th\u00c9\u00c2tre De L'escalier",
    "wof:placetype":"venue"
},
  "geometry": {"coordinates":[4.8641462326,50.4749984741],"type":"Point"}
}