{
  "type": "Feature",
  "properties": {
    "addr:full":"Ten Akkerdreef 8 Kortrijk West-Vlaanderen 8500",
    "addr:housenumber":"8",
    "addr:postcode":"8500",
    "addr:street":"Ten Akkerdreef",
    "iso:country":"BE",
    "sg:address":"Ten Akkerdreef 8",
    "sg:city":"Kortrijk",
    "sg:classifiers":[
        {
            "category":"Professional",
            "subcategory":"Printing & Photocopies",
            "type":"Services"
        }
    ],
    "sg:phone":"+32 56 22 28 74",
    "sg:postcode":"8500",
    "sg:province":"West-Vlaanderen",
    "sg:tags":[
        "shop",
        "industrial"
    ],
    "wof:name":"Nolf Nv",
    "wof:placetype":"venue"
},
  "geometry": {"coordinates":[3.2748610973,50.8199577332],"type":"Point"}
}