{
  "type": "Feature",
  "properties": {
    "addr:full":"Koninklijke Baan 291 Koksijde West-Vlaanderen 8670",
    "addr:housenumber":"291",
    "addr:postcode":"8670",
    "addr:street":"Koninklijke Baan",
    "iso:country":"BE",
    "sg:address":"Koninklijke Baan 291",
    "sg:city":"Koksijde",
    "sg:classifiers":[
        {
            "category":"Shopping",
            "subcategory":"Shoes",
            "type":"Retail Goods"
        }
    ],
    "sg:phone":"+32 58 52 22 36",
    "sg:postcode":"8670",
    "sg:province":"West-Vlaanderen",
    "sg:tags":[
        "slipper",
        "-"
    ],
    "wof:name":"Nomade",
    "wof:placetype":"venue"
},
  "geometry": {"coordinates":[2.6268680096,51.1137161255],"type":"Point"}
}