{
  "type": "Feature",
  "properties": {
    "iso:country":"BE",
    "sg:address":"Legevoorde 42",
    "sg:city":"Waarschoot",
    "sg:orig_category":"Eleveurs de bovins",
    "sg:phone":"+32 9 372 63 60",
    "sg:postcode":"9950",
    "sg:province":"Oost-Vlaanderen",
    "wof:name":"Juliaan De Reu",
    "wof:placetype":"venue"
},
  "geometry": {"coordinates":[3.612983942,51.1290893555],"type":"Point"}
}