{
  "type": "Feature",
  "properties": {
    "iso:country":"BE",
    "sg:address":"Ruggeveldlaan 603",
    "sg:city":"Deurne",
    "sg:orig_category":"Centres de fitness. Cours de danse. Centres de fitness",
    "sg:phone":"+32 3 326 36 72",
    "sg:postcode":"2100",
    "sg:province":"Antwerpen",
    "wof:name":"Go-fit",
    "wof:placetype":"venue"
},
  "geometry": {"coordinates":[4.4789128304,51.2229385376],"type":"Point"}
}