{
  "type": "Feature",
  "properties": {
    "addr:full":"Raeventuyn 23 Brecht Antwerpen 2960",
    "addr:housenumber":"23",
    "addr:postcode":"2960",
    "addr:street":"Raeventuyn",
    "iso:country":"BE",
    "sg:address":"Raeventuyn 23",
    "sg:city":"Brecht",
    "sg:orig_category":"Woningbouw",
    "sg:phone":"+32 3 313 09 41",
    "sg:postcode":"2960",
    "sg:province":"Antwerpen",
    "wof:name":"Gomico",
    "wof:placetype":"venue"
},
  "geometry": {"coordinates":[4.6415200233,51.3512115479],"type":"Point"}
}