{
  "type": "Feature",
  "properties": {
    "addr:full":"Sint-amandstraat 2 Nazareth Oost-Vlaanderen 9810",
    "addr:housenumber":"2",
    "addr:postcode":"9810",
    "addr:street":"Sint-Amandstraat",
    "iso:country":"BE",
    "sg:address":"Sint-amandstraat 2",
    "sg:city":"Nazareth",
    "sg:orig_category":"Koekjes, gebak and taart Fab",
    "sg:phone":"+32 9 385 56 56",
    "sg:postcode":"9810",
    "sg:province":"Oost-Vlaanderen",
    "wof:name":"Temmerman",
    "wof:placetype":"venue"
},
  "geometry": {"coordinates":[3.6419489384,50.9554481506],"type":"Point"}
}