{
  "type": "Feature",
  "properties": {
    "iso:country":"BE",
    "sg:address":"Pezelstraat 69ba",
    "sg:city":"Poperinge",
    "sg:orig_category":"Verlichting and huishoudartikelen",
    "sg:phone":"+32 57 33 57 92",
    "sg:postcode":"8970",
    "sg:province":"West-Vlaanderen",
    "wof:name":"Lesschaeve & Pattyn",
    "wof:placetype":"venue"
},
  "geometry": {"coordinates":[2.7259778976,50.8636665344],"type":"Point"}
}