{
  "type": "Feature",
  "properties": {
    "iso:country":"BE",
    "sg:address":"Soelstraat 84",
    "sg:city":"Betekom",
    "sg:classifiers":[
        {
            "category":"Government",
            "subcategory":"Fire Station",
            "type":"Public Place"
        }
    ],
    "sg:phone":"+32 16 57 22 04",
    "sg:postcode":"3130",
    "sg:province":"Vlaams-Brabant",
    "sg:tags":[
        "packard",
        "nec",
        "bell"
    ],
    "wof:name":"Soles",
    "wof:placetype":"venue"
},
  "geometry": {"coordinates":[4.7935929298,50.9977760315],"type":"Point"}
}