{
  "type": "Feature",
  "properties": {
    "iso:country":"BE",
    "sg:address":"Rue De La Boverie 379",
    "sg:city":"Seraing",
    "sg:classifiers":[
        {
            "category":"Building & Trades",
            "subcategory":"Equipment Rental",
            "type":"Services"
        }
    ],
    "sg:phone":"+32 4 385 94 50",
    "sg:postcode":"4100",
    "sg:province":"Li\u00e8ge",
    "sg:tags":[
        "industrial",
        "maintenance"
    ],
    "wof:name":"Axima S.a.",
    "wof:placetype":"venue"
},
  "geometry": {"coordinates":[5.5039830208,50.5986213684],"type":"Point"}
}