{
  "type": "Feature",
  "properties": {
    "addr:full":"Jukstraat 4 Lommel Limburg 3920",
    "addr:housenumber":"4",
    "addr:postcode":"3920",
    "addr:street":"Jukstraat",
    "iso:country":"BE",
    "sg:address":"Jukstraat 4",
    "sg:city":"Lommel",
    "sg:orig_category":"Viessmann. Plomberie, chauffage and installations sanitaires",
    "sg:phone":"+32 11 54 34 87",
    "sg:postcode":"3920",
    "sg:province":"Limburg",
    "wof:name":"Janssen Willy",
    "wof:placetype":"venue"
},
  "geometry": {"coordinates":[5.2969641685,51.2348060608],"type":"Point"}
}