{
  "type": "Feature",
  "properties": {
    "iso:country":"BE",
    "sg:address":"Ossegemstraat 79a",
    "sg:city":"Meise",
    "sg:classifiers":[
        {
            "category":"Building & Trades",
            "subcategory":"Landscaping Services",
            "type":"Services"
        }
    ],
    "sg:phone":"+32 2 270 58 48",
    "sg:postcode":"1860",
    "sg:province":"Vlaams-Brabant",
    "sg:tags":[
        "nurseryman"
    ],
    "wof:name":"Van Doorslaer G",
    "wof:placetype":"venue"
},
  "geometry": {"coordinates":[4.3198060989,50.960521698],"type":"Point"}
}