{
  "type": "Feature",
  "properties": {
    "iso:country":"BE",
    "sg:address":"Steenweg Op Oosthoven 157",
    "sg:city":"Turnhout",
    "sg:orig_category":"Pain, p\u00e2tisseries and confiseries",
    "sg:phone":"+32 14 41 33 39",
    "sg:postcode":"2300",
    "sg:province":"Antwerpen",
    "wof:name":"Bakkerij Vera",
    "wof:placetype":"venue"
},
  "geometry": {"coordinates":[4.9566822052,51.3315315247],"type":"Point"}
}