{
  "type": "Feature",
  "properties": {
    "iso:country":"BE",
    "sg:address":"Molenstraat 26bd",
    "sg:city":"Zingem",
    "sg:orig_category":"Fruitteelt",
    "sg:phone":"+32 9 383 66 23",
    "sg:postcode":"9750",
    "sg:province":"Oost-Vlaanderen",
    "wof:name":"Ignace Deconinck",
    "wof:placetype":"venue"
},
  "geometry": {"coordinates":[3.5885579586,50.9020881653],"type":"Point"}
}