{
  "type": "Feature",
  "properties": {
    "addr:full":"Kerkstraat 212 Grimbergen Vlaams-Brabant 1851",
    "addr:housenumber":"212",
    "addr:postcode":"1851",
    "addr:street":"Kerkstraat",
    "iso:country":"BE",
    "sg:address":"Kerkstraat 212",
    "sg:city":"Grimbergen",
    "sg:classifiers":[
        {
            "category":"Insurance",
            "subcategory":"Life Insurance",
            "type":"Services"
        }
    ],
    "sg:phone":"+32 2 272 03 03",
    "sg:postcode":"1851",
    "sg:province":"Vlaams-Brabant",
    "sg:tags":[
        "assurance"
    ],
    "wof:name":"G.k.c.",
    "wof:placetype":"venue"
},
  "geometry": {"coordinates":[4.3887867928,50.9762878418],"type":"Point"}
}