{
  "type": "Feature",
  "properties": {
    "addr:full":"Meiberg 20 Meerhout Antwerpen 2450",
    "addr:housenumber":"20",
    "addr:postcode":"2450",
    "addr:street":"Meiberg",
    "iso:country":"BE",
    "sg:address":"Meiberg 20",
    "sg:city":"Meerhout",
    "sg:classifiers":[
        {
            "category":"Wholesale",
            "subcategory":"Beer",
            "type":"Manufacturing & Wholesale Goods"
        }
    ],
    "sg:phone":"+32 14 30 09 29",
    "sg:postcode":"2450",
    "sg:province":"Antwerpen",
    "sg:tags":[
        "ale",
        "-"
    ],
    "wof:name":"Sevenans Gebr Bvba",
    "wof:placetype":"venue"
},
  "geometry": {"coordinates":[5.0663762093,51.1350822449],"type":"Point"}
}