{
  "type": "Feature",
  "properties": {
    "iso:country":"BE",
    "sg:address":"Rue Des Ecoles 21",
    "sg:city":"Viroinval",
    "sg:orig_category":"Vins Fab. Distilleries",
    "sg:phone":"+32 60 39 05 47",
    "sg:postcode":"5670",
    "sg:province":"Namur",
    "wof:name":"Divegesem",
    "wof:placetype":"venue"
},
  "geometry": {"coordinates":[4.6370558739,50.0795860291],"type":"Point"}
}