{
  "type": "Feature",
  "properties": {
    "addr:full":"Patersstraat 72 Turnhout Antwerpen 2300",
    "addr:housenumber":"72",
    "addr:postcode":"2300",
    "addr:street":"Patersstraat",
    "iso:country":"BE",
    "sg:address":"Patersstraat 72",
    "sg:city":"Turnhout",
    "sg:classifiers":[
        {
            "category":"Shopping",
            "subcategory":"Clothing, Apparel, & Fashions",
            "type":"Retail Goods"
        }
    ],
    "sg:phone":"+32 14 41 13 97",
    "sg:postcode":"2300",
    "sg:province":"Antwerpen",
    "sg:tags":[
        "underwear",
        "lingerie",
        "-"
    ],
    "wof:name":"Huis Maria",
    "wof:placetype":"venue"
},
  "geometry": {"coordinates":[4.949655056,51.3261451721],"type":"Point"}
}