{
  "type": "Feature",
  "properties": {
    "iso:country":"BE",
    "sg:address":"Fr. Vd Berghelaan 69",
    "sg:city":"Aartselaar",
    "sg:orig_category":"Equipement photographique",
    "sg:phone":"+32 3 887 06 37",
    "sg:postcode":"2630",
    "sg:province":"Antwerpen",
    "wof:name":"Vdp Video",
    "wof:placetype":"venue"
},
  "geometry": {"coordinates":[4.3885111809,51.1384658813],"type":"Point"}
}