{
  "type": "Feature",
  "properties": {
    "iso:country":"BE",
    "sg:address":"Avenue Galil\u00c9e 8",
    "sg:city":"Wavre",
    "sg:orig_category":"Imprimeries and copyshops",
    "sg:phone":"+32 10 24 19 65",
    "sg:postcode":"1300",
    "sg:province":"Brabant Wallon",
    "wof:name":"Label-pak Int. Co",
    "wof:placetype":"venue"
},
  "geometry": {"coordinates":[4.5826201439,50.736076355],"type":"Point"}
}