{
  "type": "Feature",
  "properties": {
    "addr:full":"Avenue De La M\u00c9trologie 4 Brussel/bruxelles Bruxelles-Capitale 1130",
    "addr:housenumber":"4",
    "addr:postcode":"1130",
    "addr:street":"Avenue De La Me\u0301Trologie;/",
    "iso:country":"BE",
    "sg:address":"Avenue De La M\u00c9trologie 4",
    "sg:city":"Brussel/bruxelles",
    "sg:classifiers":[
        {
            "category":"Insurance",
            "subcategory":"Life Insurance",
            "type":"Services"
        }
    ],
    "sg:phone":"+32 2 245 86 60",
    "sg:postcode":"1130",
    "sg:province":"Bruxelles-Capitale",
    "sg:tags":[
        "assurance"
    ],
    "wof:name":"Lincoln National Life",
    "wof:placetype":"venue"
},
  "geometry": {"coordinates":[4.4290781021,50.894153595],"type":"Point"}
}