{
  "type": "Feature",
  "properties": {
    "addr:full":"Grote-kapellestraat 58 Knesselare Oost-Vlaanderen 9910",
    "addr:housenumber":"58",
    "addr:postcode":"9910",
    "addr:street":"Grote-Kapellestraat;Oost-Vlaanderen",
    "iso:country":"BE",
    "sg:address":"Grote-kapellestraat 58",
    "sg:city":"Knesselare",
    "sg:orig_category":"Rundveehouders",
    "sg:phone":"+32 9 374 42 51",
    "sg:postcode":"9910",
    "sg:province":"Oost-Vlaanderen",
    "wof:name":"Marc Verheye",
    "wof:placetype":"venue"
},
  "geometry": {"coordinates":[3.4278740883,51.1240158081],"type":"Point"}
}