{
  "type": "Feature",
  "properties": {
    "addr:full":"Beselarestraat 28 Wervik West-Vlaanderen 8940",
    "addr:housenumber":"28",
    "addr:postcode":"8940",
    "addr:street":"Beselarestraat",
    "iso:country":"BE",
    "sg:address":"Beselarestraat 28",
    "sg:city":"Wervik",
    "sg:orig_category":"Apotheken",
    "sg:phone":"+32 56 51 14 22",
    "sg:postcode":"8940",
    "sg:province":"West-Vlaanderen",
    "wof:name":"Myriam Vandenbroucke",
    "wof:placetype":"venue"
},
  "geometry": {"coordinates":[3.0445530415,50.7852859497],"type":"Point"}
}