{
  "type": "Feature",
  "properties": {
    "iso:country":"BE",
    "sg:address":"Albertlei 28",
    "sg:city":"Kontich",
    "sg:classifiers":[
        {
            "category":"Government",
            "subcategory":"Department Of Motor Vehicles",
            "type":"Public Place"
        }
    ],
    "sg:phone":"+32 3 457 05 36",
    "sg:postcode":"2550",
    "sg:province":"Antwerpen",
    "sg:tags":[
        "planing",
        "wood",
        "sawing"
    ],
    "wof:name":"Vervoort Gebr",
    "wof:placetype":"venue"
},
  "geometry": {"coordinates":[4.4382967949,51.1363639832],"type":"Point"}
}