{
  "type": "Feature",
  "properties": {
    "addr:full":"Bercheux 66b Vaux-sur-s\u00dbre Luxembourg 6642",
    "addr:housenumber":"66b",
    "addr:postcode":"6642",
    "addr:street":"Bercheux",
    "iso:country":"BE",
    "sg:address":"Bercheux 66b",
    "sg:city":"Vaux-sur-s\u00dbre",
    "sg:orig_category":"Installation de menuiserie en bois and plastique",
    "sg:phone":"+32 61 25 62 21",
    "sg:postcode":"6642",
    "sg:province":"Luxembourg",
    "wof:name":"S. Fena",
    "wof:placetype":"venue"
},
  "geometry": {"coordinates":[5.5497012138,49.8756828308],"type":"Point"}
}