{
  "type": "Feature",
  "properties": {
    "addr:full":"Boskant 135 Lille Antwerpen 2275",
    "addr:housenumber":"135",
    "addr:postcode":"2275",
    "addr:street":"Boskant",
    "iso:country":"BE",
    "sg:address":"Boskant 135",
    "sg:city":"Lille",
    "sg:classifiers":[
        {
            "category":"Food & Beverages",
            "subcategory":"Meat & Fish",
            "type":"Retail Goods"
        }
    ],
    "sg:phone":"+32 14 88 30 46",
    "sg:postcode":"2275",
    "sg:province":"Antwerpen",
    "sg:tags":[
        "poultry",
        "whol",
        "game",
        "-"
    ],
    "wof:name":"Bijnens Kip- Pluimveehandel",
    "wof:placetype":"venue"
},
  "geometry": {"coordinates":[4.8713498116,51.2974205017],"type":"Point"}
}