{
  "type": "Feature",
  "properties": {
    "iso:country":"BE",
    "sg:address":"Kinderwelzijnstr 16",
    "sg:city":"Kalmthout",
    "sg:classifiers":[
        {
            "category":"Banks & Credit Unions",
            "subcategory":"Investment Brokerage",
            "type":"Services"
        }
    ],
    "sg:phone":"+32 3 666 00 82",
    "sg:postcode":"2920",
    "sg:province":"Antwerpen",
    "sg:tags":[
        "-",
        "transport",
        "related"
    ],
    "wof:name":"Delmelle Maritime Bvba",
    "wof:placetype":"venue"
},
  "geometry": {"coordinates":[4.4627380371,51.3747673035],"type":"Point"}
}