{
  "type": "Feature",
  "properties": {
    "addr:full":"Lindestraat 47 Lochristi (zaffelare) Oost-Vlaanderen 9080",
    "addr:housenumber":"47",
    "addr:postcode":"9080",
    "addr:street":"Lindestraat",
    "iso:country":"BE",
    "sg:address":"Lindestraat 47",
    "sg:city":"Lochristi (zaffelare)",
    "sg:classifiers":[
        {
            "category":"Banks & Credit Unions",
            "subcategory":"Investment Brokerage",
            "type":"Services"
        }
    ],
    "sg:phone":"+32 9 355 97 89",
    "sg:postcode":"9080",
    "sg:province":"Oost-Vlaanderen",
    "sg:tags":[
        "repair",
        "-",
        "installation",
        "sanitary",
        "article"
    ],
    "wof:name":"Vaernewyck M",
    "wof:placetype":"venue"
},
  "geometry": {"coordinates":[3.8246779442,51.1208190918],"type":"Point"}
}