{
  "type": "Feature",
  "properties": {
    "addr:full":"Chauss\u00c9e De Dinant 1149 Namur Namur 5100",
    "addr:postcode":"1149;5100",
    "addr:street":"Chausse\u0301E De Dinant",
    "iso:country":"BE",
    "sg:address":"Chauss\u00c9e De Dinant 1149",
    "sg:city":"Namur",
    "sg:orig_category":"H\u00f4tels. Salles de conf\u00e9rences and de r\u00e9ceptions",
    "sg:phone":"+32 81 46 08 11",
    "sg:postcode":"5100",
    "sg:province":"Namur",
    "wof:name":"Novotel Namur",
    "wof:placetype":"venue"
},
  "geometry": {"coordinates":[4.8819599152,50.4103965759],"type":"Point"}
}