{
  "type": "Feature",
  "properties": {
    "iso:country":"BE",
    "sg:address":"Rue De La Procession 25",
    "sg:city":"Nivelles",
    "sg:classifiers":[
        {
            "category":"Professional",
            "subcategory":"Lawyer & Legal Services",
            "type":"Services"
        }
    ],
    "sg:phone":"+32 67 89 39 39",
    "sg:postcode":"1400",
    "sg:province":"Brabant Wallon",
    "wof:name":"Janssens Michel",
    "wof:placetype":"venue"
},
  "geometry": {"coordinates":[4.3149170876,50.5884437561],"type":"Point"}
}