{
  "type": "Feature",
  "properties": {
    "iso:country":"BE",
    "sg:address":"Rue Albert Ier 121",
    "sg:city":"Mettet",
    "sg:orig_category":"Supermarkten",
    "sg:phone":"+32 71 72 86 94",
    "sg:postcode":"5640",
    "sg:province":"Namur",
    "wof:name":"Battard",
    "wof:placetype":"venue"
},
  "geometry": {"coordinates":[4.6559638977,50.3277511597],"type":"Point"}
}