{
  "type": "Feature",
  "properties": {
    "addr:full":"Luikersteenweg 130 Tongeren Limburg 3700",
    "addr:housenumber":"130",
    "addr:postcode":"3700",
    "addr:street":"Luikersteenweg",
    "iso:country":"BE",
    "sg:address":"Luikersteenweg 130",
    "sg:city":"Tongeren",
    "sg:orig_category":"Baby- and kinderkleding Dameskledingzaken Herenkledingzaken",
    "sg:phone":"+32 12 39 24 78",
    "sg:postcode":"3700",
    "sg:province":"Limburg",
    "wof:name":"E5 Mode",
    "wof:placetype":"venue"
},
  "geometry": {"coordinates":[5.4629378319,50.7708053589],"type":"Point"}
}