{
  "type": "Feature",
  "properties": {
    "iso:country":"BE",
    "sg:address":"Noordstraat 122",
    "sg:city":"Roeselare",
    "sg:orig_category":"Agences d\u00b4interim and personnel temporaire",
    "sg:phone":"+32 51 25 18 25",
    "sg:postcode":"8800",
    "sg:province":"West-Vlaanderen",
    "wof:name":"Forum Interim",
    "wof:placetype":"venue"
},
  "geometry": {"coordinates":[3.1214680672,50.9486618042],"type":"Point"}
}