{
  "type": "Feature",
  "properties": {
    "iso:country":"BE",
    "sg:address":"Rue De J\u00e9rusalem 40-42",
    "sg:city":"Bruxelles (schaerbeek)",
    "sg:classifiers":[
        {
            "category":"Wholesale",
            "subcategory":"Wine & Distilled Alcoholic Beverages",
            "type":"Manufacturing & Wholesale Goods"
        }
    ],
    "sg:phone":"+32 2 215 37 75",
    "sg:postcode":"1030",
    "sg:province":"Bruxelles-Capitale",
    "sg:tags":[
        "whol",
        "-",
        "spirit",
        "mfg"
    ],
    "wof:name":"Benevins Sprl",
    "wof:placetype":"venue"
},
  "geometry": {"coordinates":[4.3781290054,50.8662872314],"type":"Point"}
}