{
  "type": "Feature",
  "properties": {
    "addr:full":"Kleine Kraaiwijk 12 Antwerpen Antwerpen 2000",
    "addr:housenumber":"12",
    "addr:postcode":"2000",
    "addr:street":"Kleine Kraaiwijk",
    "iso:country":"BE",
    "sg:address":"Kleine Kraaiwijk 12",
    "sg:city":"Antwerpen",
    "sg:classifiers":[
        {
            "category":"Personal",
            "subcategory":"Piercing",
            "type":"Services"
        }
    ],
    "sg:phone":"+32 3 232 82 89",
    "sg:postcode":"2000",
    "sg:province":"Antwerpen",
    "sg:tags":[
        "piercings",
        "tatouages"
    ],
    "wof:name":"Piercing Studio Roxy-romy",
    "wof:placetype":"venue"
},
  "geometry": {"coordinates":[4.4006290436,51.2244529724],"type":"Point"}
}