{
  "type": "Feature",
  "properties": {
    "iso:country":"BE",
    "sg:address":"Lange Torhoutstraat 48",
    "sg:city":"Ieper",
    "sg:orig_category":"Travaux de finition and nettoyage de b\u00e2timents. Constructions r\u00e9sidentielles sp\u00e9cifiques",
    "sg:phone":"+32 57 21 93 59",
    "sg:postcode":"8900",
    "sg:province":"West-Vlaanderen",
    "wof:name":"Rimal",
    "wof:placetype":"venue"
},
  "geometry": {"coordinates":[2.8904030323,50.8547973633],"type":"Point"}
}