{
  "type": "Feature",
  "properties": {
    "addr:full":"Betonweg 10 Meeuwen-gruitrode (ellikom) Limburg 3670",
    "addr:housenumber":"10",
    "addr:postcode":"3670",
    "addr:street":"Betonweg",
    "iso:country":"BE",
    "sg:address":"Betonweg 10",
    "sg:city":"Meeuwen-gruitrode (ellikom)",
    "sg:classifiers":[
        {
            "category":"Retail",
            "subcategory":"Auto Repair",
            "type":"Services"
        }
    ],
    "sg:postcode":"3670",
    "sg:province":"Limburg",
    "sg:tags":[
        "garage"
    ],
    "wof:name":"Leyssen Rik Garage Nv",
    "wof:placetype":"venue"
},
  "geometry": {"coordinates":[5.5205497742,51.0963516235],"type":"Point"}
}