{
  "type": "Feature",
  "properties": {
    "addr:full":"Rue Du Ch\u00canois 50 Charleroi Hainaut 6042",
    "addr:housenumber":"50",
    "addr:postcode":"6042",
    "addr:street":"Rue Du Che\u0302Nois;Hainaut",
    "iso:country":"BE",
    "sg:address":"Rue Du Ch\u00canois 50",
    "sg:city":"Charleroi",
    "sg:classifiers":[
        {
            "category":"Insurance",
            "subcategory":"Life Insurance",
            "type":"Services"
        }
    ],
    "sg:phone":"+32 71 20 26 00",
    "sg:postcode":"6042",
    "sg:province":"Hainaut",
    "sg:tags":[
        "assurance"
    ],
    "wof:name":"Ferrara Assurances",
    "wof:placetype":"venue"
},
  "geometry": {"coordinates":[4.4476428032,50.4286422729],"type":"Point"}
}