{
  "type": "Feature",
  "properties": {
    "addr:full":"Beversesteenweg 310 Roeselare West-Vlaanderen 8800",
    "addr:housenumber":"310",
    "addr:postcode":"8800",
    "addr:street":"Beversesteenweg",
    "iso:country":"BE",
    "sg:address":"Beversesteenweg 310",
    "sg:city":"Roeselare",
    "sg:classifiers":[
        {
            "category":"Arena",
            "subcategory":"Sports Club",
            "type":"Entertainment"
        }
    ],
    "sg:phone":"+32 51 21 24 45",
    "sg:postcode":"8800",
    "sg:province":"West-Vlaanderen",
    "wof:name":"Gymclub F & F",
    "wof:placetype":"venue"
},
  "geometry": {"coordinates":[3.1337099075,50.9615402222],"type":"Point"}
}