{
  "type": "Feature",
  "properties": {
    "addr:full":"Twijnstraat 6 Brugge West-Vlaanderen 8000",
    "addr:housenumber":"6",
    "addr:postcode":"8000",
    "addr:street":"Twijnstraat",
    "iso:country":"BE",
    "sg:address":"Twijnstraat 6",
    "sg:city":"Brugge",
    "sg:classifiers":[
        {
            "category":"Professional",
            "subcategory":"Art Services",
            "type":"Services"
        }
    ],
    "sg:phone":"+32 50 34 16 50",
    "sg:postcode":"8000",
    "sg:province":"West-Vlaanderen",
    "sg:tags":[
        "-",
        "painter",
        "artist"
    ],
    "wof:name":"Retsin G",
    "wof:placetype":"venue"
},
  "geometry": {"coordinates":[3.2282590866,51.2098121643],"type":"Point"}
}