{
  "type": "Feature",
  "properties": {
    "iso:country":"BE",
    "sg:address":"Nieuwe Steenweg 11",
    "sg:city":"Temse",
    "sg:orig_category":"Parfumeries",
    "sg:phone":"+32 52 46 17 51",
    "sg:postcode":"9140",
    "sg:province":"Oost-Vlaanderen",
    "wof:name":"Soap Cosmetics",
    "wof:placetype":"venue"
},
  "geometry": {"coordinates":[4.1437177658,51.1192131042],"type":"Point"}
}