{
  "type": "Feature",
  "properties": {
    "iso:country":"BE",
    "sg:address":"Rue Puits \u00c0 Leval 30",
    "sg:city":"Chievres",
    "sg:orig_category":"Eleveurs and marchands de porcs",
    "sg:phone":"+32 69 68 85 60",
    "sg:postcode":"7950",
    "sg:province":"Hainaut",
    "wof:name":"Hainaut Porcs",
    "wof:placetype":"venue"
},
  "geometry": {"coordinates":[3.7564098835,50.5483093262],"type":"Point"}
}