{
  "type": "Feature",
  "properties": {
    "addr:full":"Hollestraat 35 Haaltert Oost-Vlaanderen 9451",
    "addr:housenumber":"35",
    "addr:postcode":"9451",
    "addr:street":"Hollestraat",
    "iso:country":"BE",
    "sg:address":"Hollestraat 35",
    "sg:city":"Haaltert",
    "sg:classifiers":[
        {
            "category":"Cafe",
            "type":"Food & Drink"
        }
    ],
    "sg:phone":"+32 53 83 15 35",
    "sg:postcode":"9451",
    "sg:province":"Oost-Vlaanderen",
    "sg:tags":[
        "caf\u00e9s"
    ],
    "wof:name":"Caf\u00c9 Ariadne",
    "wof:placetype":"venue"
},
  "geometry": {"coordinates":[3.9900789261,50.8927955627],"type":"Point"}
}