{
  "type": "Feature",
  "properties": {
    "addr:full":"Rue Jean De Greef 16 Bruxelles (ganshoren) Bruxelles-Capitale 1083",
    "addr:housenumber":"16",
    "addr:postcode":"1083",
    "addr:street":"Rue Jean De Greef",
    "iso:country":"BE",
    "sg:address":"Rue Jean De Greef 16",
    "sg:city":"Bruxelles (ganshoren)",
    "sg:classifiers":[
        {
            "category":"Social Services",
            "type":"Services"
        }
    ],
    "sg:phone":"+32 2 426 99 74",
    "sg:postcode":"1083",
    "sg:province":"Bruxelles-Capitale",
    "wof:name":"Beschut Wonen Nieuwe Thuis Vzw",
    "wof:placetype":"venue"
},
  "geometry": {"coordinates":[4.31518507,50.8733329773],"type":"Point"}
}