{
  "type": "Feature",
  "properties": {
    "addr:full":"9000 Gent-centrum Oost-Vlaanderen 9000",
    "addr:postcode":"9000;9000",
    "addr:street":"Gent-Centrum Oost-Vlaanderen",
    "iso:country":"BE",
    "sg:address":"9000",
    "sg:city":"Gent-centrum",
    "sg:classifiers":[
        {
            "category":"Travel",
            "subcategory":"Hotels & Motels",
            "type":"Entertainment"
        }
    ],
    "sg:phone":"+32 9 355 98 01",
    "sg:postcode":"9000",
    "sg:province":"Oost-Vlaanderen",
    "sg:tags":[
        "sleepy"
    ],
    "wof:name":"Sleepy",
    "wof:placetype":"venue"
},
  "geometry": {"coordinates":[3.7703149319,51.1020812988],"type":"Point"}
}