{
  "type": "Feature",
  "properties": {
    "addr:full":"La-vir\u00c9e 36 Bertrix Luxembourg 6880",
    "addr:housenumber":"36",
    "addr:postcode":"6880",
    "addr:street":"La-Vire\u0301E",
    "iso:country":"BE",
    "sg:address":"La-vir\u00c9e 36",
    "sg:city":"Bertrix",
    "sg:orig_category":"Radioproductie and uitzendingen",
    "sg:phone":"+32 61 41 33 65",
    "sg:postcode":"6880",
    "sg:province":"Luxembourg",
    "wof:name":"Radio Joker Fm",
    "wof:placetype":"venue"
},
  "geometry": {"coordinates":[5.2555689812,49.84633255],"type":"Point"}
}