{
  "type": "Feature",
  "properties": {
    "iso:country":"BE",
    "sg:address":"Moenstraat 8",
    "sg:city":"Zwevegem",
    "sg:orig_category":"Dierenartsen",
    "sg:phone":"+32 56 45 50 80",
    "sg:postcode":"8554",
    "sg:province":"West-Vlaanderen",
    "wof:name":"Dirk Samain",
    "wof:placetype":"venue"
},
  "geometry": {"coordinates":[3.3745999336,50.7587623596],"type":"Point"}
}