{
  "type": "Feature",
  "properties": {
    "addr:full":"Place Emile-de-lalieux 15b4 Nivelles Brabant Wallon 1400",
    "addr:housenumber":"15b4",
    "addr:postcode":"1400",
    "addr:street":"Place Emile-De-Lalieux",
    "iso:country":"BE",
    "sg:address":"Place Emile-de-lalieux 15b4",
    "sg:city":"Nivelles",
    "sg:orig_category":"Advocaten and juridische adviseurs",
    "sg:phone":"+32 67 21 17 21",
    "sg:postcode":"1400",
    "sg:province":"Brabant Wallon",
    "wof:name":"Maurice Beauduin",
    "wof:placetype":"venue"
},
  "geometry": {"coordinates":[4.3286151886,50.5984115601],"type":"Point"}
}