{
  "type": "Feature",
  "properties": {
    "iso:country":"BE",
    "sg:address":"Avenue De L\u00b4ecuyer 75",
    "sg:city":"Sint-genesius-rode/rhode-saint-gen\u00c8se",
    "sg:orig_category":"Antiquit\u00e9s",
    "sg:phone":"+32 2 359 97 70",
    "sg:postcode":"1640",
    "sg:province":"Vlaams-Brabant",
    "wof:name":"Chintz En Antique",
    "wof:placetype":"venue"
},
  "geometry": {"coordinates":[4.3985671997,50.7358856201],"type":"Point"}
}