{
  "type": "Feature",
  "properties": {
    "iso:country":"BE",
    "sg:address":"Torhoutse Steenweg 246 Box 1",
    "sg:city":"Brugge (sint-andries)",
    "sg:classifiers":[
        {
            "category":"Professional",
            "subcategory":"Engineering",
            "type":"Services"
        }
    ],
    "sg:phone":"+32 50 40 64 00",
    "sg:postcode":"8200",
    "sg:province":"West-Vlaanderen",
    "sg:tags":[
        "-"
    ],
    "wof:name":"Costobel Nv",
    "wof:placetype":"venue"
},
  "geometry": {"coordinates":[3.1975800991,51.1936340332],"type":"Point"}
}