{
  "type": "Feature",
  "properties": {
    "addr:full":"Bontinkstraat 4 Laarne Oost-Vlaanderen 9270",
    "addr:housenumber":"4",
    "addr:postcode":"9270",
    "addr:street":"Bontinkstraat",
    "iso:country":"BE",
    "sg:address":"Bontinkstraat 4",
    "sg:city":"Laarne",
    "sg:orig_category":"Rundveehouders",
    "sg:phone":"+32 9 367 74 35",
    "sg:postcode":"9270",
    "sg:province":"Oost-Vlaanderen",
    "wof:name":"Meverco",
    "wof:placetype":"venue"
},
  "geometry": {"coordinates":[3.9299139977,51.0494766235],"type":"Point"}
}