{
  "type": "Feature",
  "properties": {
    "iso:country":"BE",
    "sg:address":"Rue Octave Lotin 16a",
    "sg:city":"Chastre (cortil-noirmont)",
    "sg:classifiers":[
        {
            "category":"Home & Garden",
            "subcategory":"Kitchen Supply",
            "type":"Retail Goods"
        }
    ],
    "sg:phone":"+32 81 61 09 29",
    "sg:postcode":"1450",
    "sg:province":"Brabant Wallon",
    "sg:tags":[
        "installation"
    ],
    "wof:name":"Atelier 10",
    "wof:placetype":"venue"
},
  "geometry": {"coordinates":[4.636452198,50.6085243225],"type":"Point"}
}