{
  "type": "Feature",
  "properties": {
    "iso:country":"BE",
    "sg:address":"Smisveld 62",
    "sg:city":"Wellen (ulbeek)",
    "sg:classifiers":[
        {
            "category":"Building & Trades",
            "subcategory":"Cleaning & Sanitation",
            "type":"Services"
        }
    ],
    "sg:phone":"+32 12 74 58 03",
    "sg:postcode":"3832",
    "sg:province":"Limburg",
    "sg:tags":[
        "mainten",
        "-",
        "boiler"
    ],
    "wof:name":"Grosemans P",
    "wof:placetype":"venue"
},
  "geometry": {"coordinates":[5.30479002,50.8411521912],"type":"Point"}
}