{
  "type": "Feature",
  "properties": {
    "iso:country":"BE",
    "sg:address":"Rue Champeau 36",
    "sg:city":"Charleroi (montignies-sur-sambre)",
    "sg:orig_category":"Non-Classified Establishments",
    "sg:phone":"+32 71 39 07 15",
    "sg:postcode":"6061",
    "sg:province":"Hainaut",
    "wof:name":"Ceditex Sprl",
    "wof:placetype":"venue"
},
  "geometry": {"coordinates":[4.4942169189,50.403263092],"type":"Point"}
}