{
  "type": "Feature",
  "properties": {
    "addr:full":"Chauss\u00c9e De Charleroi 40 Namur Namur 5000",
    "addr:housenumber":"40",
    "addr:postcode":"5000",
    "addr:street":"Chausse\u0301E De Charleroi",
    "iso:country":"BE",
    "sg:address":"Chauss\u00c9e De Charleroi 40",
    "sg:city":"Namur",
    "sg:orig_category":"Pleisterwerk Woningbouw",
    "sg:phone":"+32 81 73 70 52",
    "sg:postcode":"5000",
    "sg:province":"Namur",
    "wof:name":"Remacle & Fils",
    "wof:placetype":"venue"
},
  "geometry": {"coordinates":[4.8422298431,50.4626808167],"type":"Point"}
}