{
  "type": "Feature",
  "properties": {
    "addr:full":"Bleichstrasse 20 Sankt Vith Li\u00e8ge 4780",
    "addr:housenumber":"20",
    "addr:postcode":"4780",
    "addr:street":"Bleichstrasse",
    "iso:country":"BE",
    "sg:address":"Bleichstrasse 20",
    "sg:city":"Sankt Vith",
    "sg:classifiers":[
        {
            "category":"Personal",
            "subcategory":"Beauty Salon",
            "type":"Services"
        }
    ],
    "sg:phone":"+32 80 22 75 65",
    "sg:postcode":"4780",
    "sg:province":"Li\u00e8ge",
    "wof:name":"Michels",
    "wof:placetype":"venue"
},
  "geometry": {"coordinates":[6.1263642311,50.2821617126],"type":"Point"}
}