{
  "type": "Feature",
  "properties": {
    "iso:country":"BE",
    "sg:address":"Weertersteenweg 384",
    "sg:city":"Kinrooi",
    "sg:orig_category":"Electrom\u00e9nager, t\u00e9l\u00e9visions and radios",
    "sg:phone":"+32 89 70 27 64",
    "sg:postcode":"3640",
    "sg:province":"Limburg",
    "wof:name":"Hub Vandermeulen",
    "wof:placetype":"venue"
},
  "geometry": {"coordinates":[5.7421097755,51.1599807739],"type":"Point"}
}