{
  "type": "Feature",
  "properties": {
    "iso:country":"BE",
    "sg:address":"Jordaenskaai 15",
    "sg:city":"Antwerpen",
    "sg:orig_category":"Agences d'exp\u00e9dition",
    "sg:phone":"+32 3 205 17 00",
    "sg:postcode":"2000",
    "sg:province":"Antwerpen",
    "wof:name":"U.r.s.",
    "wof:placetype":"venue"
},
  "geometry": {"coordinates":[4.3989510536,51.2236366272],"type":"Point"}
}