{
  "type": "Feature",
  "properties": {
    "iso:country":"BE",
    "sg:address":"Torhoutse Steenweg 136",
    "sg:city":"Sint-andries",
    "sg:classifiers":[
        {
            "category":"Manufacturing",
            "subcategory":"Jewelry",
            "type":"Manufacturing & Wholesale Goods"
        }
    ],
    "sg:phone":"+32 50 39 48 13",
    "sg:postcode":"8200",
    "sg:province":"West-Vlaanderen",
    "sg:tags":[
        "gemstone",
        "gold",
        "jewellery"
    ],
    "wof:name":"B & B New Nv",
    "wof:placetype":"venue"
},
  "geometry": {"coordinates":[3.2025780678,51.1988754272],"type":"Point"}
}