{
  "type": "Feature",
  "properties": {
    "iso:country":"BE",
    "sg:address":"Oudaen 3",
    "sg:city":"Schilde",
    "sg:orig_category":"Plaatsen van vloer- and muurbekleding Schilders Textiel Verlichting and huishoudartikelen Vloer- and",
    "sg:phone":"+32 3 658 87 76",
    "sg:postcode":"2970",
    "sg:province":"Antwerpen",
    "wof:name":"Van Echelpoel",
    "wof:placetype":"venue"
},
  "geometry": {"coordinates":[4.5535449982,51.2646141052],"type":"Point"}
}