{
  "type": "Feature",
  "properties": {
    "addr:full":"Avenue Mutsaard 39 Bruxelles Bruxelles-Capitale 1020",
    "addr:housenumber":"39",
    "addr:postcode":"1020",
    "addr:street":"Avenue Mutsaard",
    "iso:country":"BE",
    "sg:address":"Avenue Mutsaard 39",
    "sg:city":"Bruxelles",
    "sg:classifiers":[
        {
            "category":"Professional",
            "subcategory":"Testing Lab",
            "type":"Services"
        }
    ],
    "sg:phone":"+32 2 262 09 72",
    "sg:postcode":"1020",
    "sg:province":"Bruxelles-Capitale",
    "sg:tags":[
        "chemist"
    ],
    "wof:name":"Mutsaerd Pharmacie",
    "wof:placetype":"venue"
},
  "geometry": {"coordinates":[4.3568367958,50.8970870972],"type":"Point"}
}