{
  "type": "Feature",
  "properties": {
    "addr:full":"Papaverstraat 4 Middelkerke West-Vlaanderen 8430",
    "addr:housenumber":"4",
    "addr:postcode":"8430",
    "addr:street":"Papaverstraat",
    "iso:country":"BE",
    "sg:address":"Papaverstraat 4",
    "sg:city":"Middelkerke",
    "sg:classifiers":[
        {
            "category":"Wholesale",
            "subcategory":"Plants",
            "type":"Manufacturing & Wholesale Goods"
        }
    ],
    "sg:phone":"+32 59 30 50 20",
    "sg:postcode":"8430",
    "sg:province":"West-Vlaanderen",
    "sg:tags":[
        "decoration",
        "flower",
        "-"
    ],
    "wof:name":"Mayflower",
    "wof:placetype":"venue"
},
  "geometry": {"coordinates":[2.8446750641,51.1939353943],"type":"Point"}
}