{
  "type": "Feature",
  "properties": {
    "addr:full":"Hemelingenstraat 18 Tongeren Limburg 3700",
    "addr:housenumber":"18",
    "addr:postcode":"3700",
    "addr:street":"Hemelingenstraat",
    "iso:country":"BE",
    "sg:address":"Hemelingenstraat 18",
    "sg:city":"Tongeren",
    "sg:orig_category":"Baby- and kinderkleding",
    "sg:phone":"+32 12 26 26 84",
    "sg:postcode":"3700",
    "sg:province":"Limburg",
    "wof:name":"Jean-marie Martens",
    "wof:placetype":"venue"
},
  "geometry": {"coordinates":[5.4626488686,50.7813072205],"type":"Point"}
}