{
  "type": "Feature",
  "properties": {
    "iso:country":"BE",
    "sg:address":"Heesstraat 87",
    "sg:city":"Kinrooi (kessenich)",
    "sg:classifiers":[
        {
            "category":"Retail",
            "subcategory":"Driving School",
            "type":"Services"
        }
    ],
    "sg:phone":"+32 89 56 62 30",
    "sg:postcode":"3640",
    "sg:province":"Limburg",
    "sg:tags":[
        "automobile",
        "officially",
        "-",
        "recognized"
    ],
    "wof:name":"Wirix J Autorijschool",
    "wof:placetype":"venue"
},
  "geometry": {"coordinates":[5.7883248329,51.1500358582],"type":"Point"}
}