{
  "type": "Feature",
  "properties": {
    "iso:country":"BE",
    "sg:address":"Square Saint-julien 9",
    "sg:city":"Ath",
    "sg:orig_category":"Hoger onderwijs",
    "sg:phone":"+32 68 84 13 93",
    "sg:postcode":"7800",
    "sg:province":"Hainaut",
    "wof:name":"H.e.p.h.o.-d\u00c9p.param\u00c9dic.",
    "wof:placetype":"venue"
},
  "geometry": {"coordinates":[3.7769339085,50.6287498474],"type":"Point"}
}