{
  "type": "Feature",
  "properties": {
    "iso:country":"BE",
    "sg:address":"Grand Place 4",
    "sg:city":"Mouscron",
    "sg:classifiers":[
        {
            "category":"Bars & Pubs",
            "type":"Food & Drink"
        }
    ],
    "sg:phone":"+32 56 84 33 63",
    "sg:postcode":"7700",
    "sg:province":"Hainaut",
    "wof:name":"Caf\u00e9 De La Mairie",
    "wof:placetype":"venue"
},
  "geometry": {"coordinates":[3.2148640156,50.7446098328],"type":"Point"}
}