{
  "type": "Feature",
  "properties": {
    "iso:country":"BE",
    "sg:address":"Driehoekstraat 70",
    "sg:city":"Komen-waasten/comines-warneton",
    "sg:orig_category":"Artiesten and kunstenaars",
    "sg:phone":"+32 56 55 55 39",
    "sg:postcode":"7780",
    "sg:province":"Hainaut",
    "wof:name":"Paul Desmet",
    "wof:placetype":"venue"
},
  "geometry": {"coordinates":[2.9984300137,50.7863311768],"type":"Point"}
}