{
  "type": "Feature",
  "properties": {
    "iso:country":"BE",
    "sg:address":"Dr\u00c8ve Des Alli\u00c9s 28",
    "sg:city":"Thuin",
    "sg:orig_category":"Advocaten and juridische adviseurs",
    "sg:phone":"+32 71 59 01 51",
    "sg:postcode":"6530",
    "sg:province":"Hainaut",
    "wof:name":"Marie-fran\u00c7oise Nicaise",
    "wof:placetype":"venue"
},
  "geometry": {"coordinates":[4.2974348068,50.3403205872],"type":"Point"}
}