{
  "type": "Feature",
  "properties": {
    "iso:country":"BE",
    "sg:address":"W. Van Moerbekestraat 32",
    "sg:city":"Geraardsbergen",
    "sg:orig_category":"Enseignement maternel and primaire",
    "sg:phone":"+32 54 41 09 68",
    "sg:postcode":"9500",
    "sg:province":"Oost-Vlaanderen",
    "wof:name":"Vrije Kleuterschool",
    "wof:placetype":"venue"
},
  "geometry": {"coordinates":[3.9175810814,50.7535705566],"type":"Point"}
}