{
  "type": "Feature",
  "properties": {
    "addr:full":"Rue De Biesme 155 Hastiere Namur 5544",
    "addr:housenumber":"155",
    "addr:postcode":"5544",
    "addr:street":"Rue De Biesme;Namur",
    "iso:country":"BE",
    "sg:address":"Rue De Biesme 155",
    "sg:city":"Hastiere",
    "sg:orig_category":"Installation \u00e9lectrique r\u00e9sidentielle",
    "sg:phone":"+32 82 67 83 46",
    "sg:postcode":"5544",
    "sg:province":"Namur",
    "wof:name":"Claude Dubois",
    "wof:placetype":"venue"
},
  "geometry": {"coordinates":[4.7985229492,50.1641616821],"type":"Point"}
}