{
  "type": "Feature",
  "properties": {
    "iso:country":"BE",
    "sg:address":"Rue Du Mitan 34",
    "sg:city":"Les Bons Villers (mellet)",
    "sg:classifiers":[
        {
            "category":"Health Services",
            "subcategory":"Doctor",
            "type":"Services"
        }
    ],
    "sg:phone":"+32 71 85 28 64",
    "sg:postcode":"6211",
    "sg:province":"Hainaut",
    "sg:tags":[
        "medicinephysicians",
        "surgeon"
    ],
    "wof:name":"Girard J",
    "wof:placetype":"venue"
},
  "geometry": {"coordinates":[4.4791898727,50.5055961609],"type":"Point"}
}