{
  "type": "Feature",
  "properties": {
    "iso:country":"BE",
    "sg:address":"Leuvensesteenweg 139",
    "sg:city":"Tervuren (vossem)",
    "sg:orig_category":"Autombile concessionaires",
    "sg:phone":"+32 2 767 49 32",
    "sg:postcode":"3080",
    "sg:province":"Vlaams-Brabant",
    "wof:name":"Gar. Vandenplas",
    "wof:placetype":"venue"
},
  "geometry": {"coordinates":[4.5504617691,50.8410224915],"type":"Point"}
}