{
  "type": "Feature",
  "properties": {
    "iso:country":"BE",
    "sg:address":"Veeweideweg 4",
    "sg:city":"Haacht",
    "sg:orig_category":"Procesbesturingssystemen Fab",
    "sg:phone":"+32 16 60 24 62",
    "sg:postcode":"3150",
    "sg:province":"Vlaams-Brabant",
    "wof:name":"Elec M",
    "wof:placetype":"venue"
},
  "geometry": {"coordinates":[4.6233849525,50.9829788208],"type":"Point"}
}