{
  "type": "Feature",
  "properties": {
    "iso:country":"BE",
    "sg:address":"Aartrijkestraat 51",
    "sg:city":"Torhout",
    "sg:orig_category":"IJzerwaren, bouw- and verfmaterialen Installatie van houten of kunststof schrijnwerk MEUBELONTWERP A",
    "sg:phone":"+32 50 21 64 21",
    "sg:postcode":"8820",
    "sg:province":"West-Vlaanderen",
    "wof:name":"Wilco-design",
    "wof:placetype":"venue"
},
  "geometry": {"coordinates":[3.1004269123,51.0708236694],"type":"Point"}
}