{
  "type": "Feature",
  "properties": {
    "addr:full":"Velm 56 Asse Vlaams-Brabant 1730",
    "addr:housenumber":"56",
    "addr:postcode":"1730",
    "addr:street":"Velm",
    "iso:country":"BE",
    "sg:address":"Velm 56",
    "sg:city":"Asse",
    "sg:orig_category":"Woningbouw",
    "sg:phone":"+32 2 452 22 24",
    "sg:postcode":"1730",
    "sg:province":"Vlaams-Brabant",
    "wof:name":"Luppens",
    "wof:placetype":"venue"
},
  "geometry": {"coordinates":[4.2331528664,50.9245796204],"type":"Point"}
}