{
  "type": "Feature",
  "properties": {
    "addr:full":"Bollestraat 31 Merchtem Vlaams-Brabant 1785",
    "addr:housenumber":"31",
    "addr:postcode":"1785",
    "addr:street":"Bollestraat",
    "iso:country":"BE",
    "sg:address":"Bollestraat 31",
    "sg:city":"Merchtem",
    "sg:orig_category":"Producteurs de l\u00e9gumes",
    "sg:phone":"+32 2 460 31 20",
    "sg:postcode":"1785",
    "sg:province":"Vlaams-Brabant",
    "wof:name":"Maria Van Doorslaer",
    "wof:placetype":"venue"
},
  "geometry": {"coordinates":[4.2765798569,50.9409599304],"type":"Point"}
}