{
  "type": "Feature",
  "properties": {
    "addr:full":"Van Pulstraat 19 Brecht Antwerpen 2960",
    "addr:housenumber":"19",
    "addr:postcode":"2960",
    "addr:street":"Pulstraat",
    "iso:country":"BE",
    "sg:address":"Van Pulstraat 19",
    "sg:city":"Brecht",
    "sg:orig_category":"Activit\u00e9s d\u00b4action sociale sans h\u00e9bergement",
    "sg:phone":"+32 3 313 93 10",
    "sg:postcode":"2960",
    "sg:province":"Antwerpen",
    "wof:name":"Rode Kruis Sint-job-in-'t-goor",
    "wof:placetype":"venue"
},
  "geometry": {"coordinates":[4.6439919472,51.3456726074],"type":"Point"}
}