{
  "type": "Feature",
  "properties": {
    "addr:full":"Jan Frans Willemsstraat 24 Boom Antwerpen 2850",
    "addr:housenumber":"24",
    "addr:postcode":"2850",
    "addr:street":"Jan Frans Willemsstraat",
    "iso:country":"BE",
    "sg:address":"Jan Frans Willemsstraat 24",
    "sg:city":"Boom",
    "sg:classifiers":[
        {
            "category":"Social Services",
            "type":"Services"
        }
    ],
    "sg:phone":"+32 3 888 32 36",
    "sg:postcode":"2850",
    "sg:province":"Antwerpen",
    "wof:name":"Vlaamse Vereniging Voor Mensen Met Een Gehoorstoornis",
    "wof:placetype":"venue"
},
  "geometry": {"coordinates":[4.3753380775,51.0970878601],"type":"Point"}
}