{
  "type": "Feature",
  "properties": {
    "iso:country":"BE",
    "sg:address":"Middelvelden 58",
    "sg:city":"Arendonk",
    "sg:orig_category":"Rev\u00eatements pour sols and murs",
    "sg:phone":"+32 14 67 84 81",
    "sg:postcode":"2370",
    "sg:province":"Antwerpen",
    "wof:name":"Van Bergen J.",
    "wof:placetype":"venue"
},
  "geometry": {"coordinates":[5.0935192108,51.317489624],"type":"Point"}
}