{
  "type": "Feature",
  "properties": {
    "addr:full":"Belegstraat 51-53 Antwerpen Antwerpen 2018",
    "addr:postcode":"51-53;2018",
    "addr:street":"Belegstraat",
    "iso:country":"BE",
    "sg:address":"Belegstraat 51-53",
    "sg:city":"Antwerpen",
    "sg:orig_category":"Cr\u00e9dit \u00e0 la consommation. Assurances. Pr\u00eats hypoth\u00e9caires and cr\u00e9dits immobiliers",
    "sg:phone":"+32 3 216 99 25",
    "sg:postcode":"2018",
    "sg:province":"Antwerpen",
    "wof:name":"Assuran",
    "wof:placetype":"venue"
},
  "geometry": {"coordinates":[4.3963470459,51.2042922974],"type":"Point"}
}