{
  "type": "Feature",
  "properties": {
    "addr:full":"Avenue Des Sources 2 Braine L'alleud (braine-l'alleud) Brabant Wallon 1420",
    "addr:housenumber":"2",
    "addr:postcode":"1420",
    "addr:street":"Avenue Des Sources",
    "iso:country":"BE",
    "sg:address":"Avenue Des Sources 2",
    "sg:city":"Braine L'alleud (braine-l'alleud)",
    "sg:classifiers":[
        {
            "category":"Real Estate",
            "subcategory":"Architect",
            "type":"Services"
        }
    ],
    "sg:phone":"+32 2 354 52 09",
    "sg:postcode":"1420",
    "sg:province":"Brabant Wallon",
    "wof:name":"Mardikian H",
    "wof:placetype":"venue"
},
  "geometry": {"coordinates":[-0.765887022,47.4031219482],"type":"Point"}
}