{
  "type": "Feature",
  "properties": {
    "iso:country":"BE",
    "sg:address":"Rue Augustin Berger 21",
    "sg:city":"Chapelle-lez-herlaimont",
    "sg:orig_category":"Travaux de pl\u00e2trage",
    "sg:phone":"+32 71 52 30 21",
    "sg:postcode":"7160",
    "sg:province":"Hainaut",
    "wof:name":"Isota",
    "wof:placetype":"venue"
},
  "geometry": {"coordinates":[4.2865371704,50.4719848633],"type":"Point"}
}