{
  "type": "Feature",
  "properties": {
    "iso:country":"BE",
    "sg:address":"Sudermanstraat 5",
    "sg:city":"Antwerpen",
    "sg:classifiers":[
        {
            "category":"Government",
            "subcategory":"Post Office",
            "type":"Public Place"
        }
    ],
    "sg:phone":"+32 3 457 73 37",
    "sg:postcode":"2000",
    "sg:province":"Antwerpen",
    "sg:tags":[
        "stamp"
    ],
    "wof:name":"Antwerpse Postzegelclub Vzw apc",
    "wof:placetype":"venue"
},
  "geometry": {"coordinates":[4.4046139717,51.2199249268],"type":"Point"}
}