{
  "type": "Feature",
  "properties": {
    "iso:country":"BE",
    "sg:address":"Vraagheideweg 16",
    "sg:city":"Schilde",
    "sg:orig_category":"Fa\u00e7ade covering",
    "sg:phone":"+32 3 384 21 35",
    "sg:postcode":"2970",
    "sg:province":"Antwerpen",
    "wof:name":"Christiaens Peter",
    "wof:placetype":"venue"
},
  "geometry": {"coordinates":[4.6172590256,51.2883872986],"type":"Point"}
}