{
  "type": "Feature",
  "properties": {
    "addr:full":"Antwerpsesteenweg 705 Gent Oost-Vlaanderen 9040",
    "addr:housenumber":"705",
    "addr:postcode":"9040",
    "addr:street":"Antwerpsesteenweg;Oost-Vlaanderen",
    "iso:country":"BE",
    "sg:address":"Antwerpsesteenweg 705",
    "sg:city":"Gent",
    "sg:orig_category":"Bouwmaterialen Gh",
    "sg:phone":"+32 9 228 21 69",
    "sg:postcode":"9040",
    "sg:province":"Oost-Vlaanderen",
    "wof:name":"Fa. Van Hecke-van Hecke",
    "wof:placetype":"venue"
},
  "geometry": {"coordinates":[3.7728118896,51.071559906],"type":"Point"}
}