{
  "type": "Feature",
  "properties": {
    "addr:full":"Parochiestraat 17 Zandhoven (viersel) Antwerpen 2240",
    "addr:housenumber":"17",
    "addr:postcode":"2240",
    "addr:street":"Parochiestraat",
    "iso:country":"BE",
    "sg:address":"Parochiestraat 17",
    "sg:city":"Zandhoven (viersel)",
    "sg:classifiers":[
        {
            "category":"Bars & Pubs",
            "type":"Food & Drink"
        }
    ],
    "sg:phone":"+32 3 475 15 28",
    "sg:postcode":"2240",
    "sg:province":"Antwerpen",
    "wof:name":"Cruyck (de)",
    "wof:placetype":"venue"
},
  "geometry": {"coordinates":[4.6492319107,51.1876296997],"type":"Point"}
}