{
  "type": "Feature",
  "properties": {
    "addr:full":"Van Putlei 8 Antwerpen Antwerpen 2018",
    "addr:housenumber":"8",
    "addr:postcode":"2018",
    "iso:country":"BE",
    "sg:address":"Van Putlei 8",
    "sg:city":"Antwerpen",
    "sg:classifiers":[
        {
            "category":"Education",
            "subcategory":"Special Training",
            "type":"Public Place"
        }
    ],
    "sg:phone":"+32 3 248 50 18",
    "sg:postcode":"2018",
    "sg:province":"Antwerpen",
    "sg:tags":[
        "school",
        "language"
    ],
    "wof:name":"Apostrophe",
    "wof:placetype":"venue"
},
  "geometry": {"coordinates":[4.4043807983,51.1971511841],"type":"Point"}
}