{
  "type": "Feature",
  "properties": {
    "iso:country":"BE",
    "sg:address":"Bld Des Gerardchamps 184",
    "sg:city":"Verviers",
    "sg:orig_category":"R\u00e9parations de chaussures and articles en cuir",
    "sg:phone":"+32 87 33 17 53",
    "sg:postcode":"4800",
    "sg:province":"Li\u00e8ge",
    "wof:name":"Rene Wuidar",
    "wof:placetype":"venue"
},
  "geometry": {"coordinates":[5.8498930931,50.5858459473],"type":"Point"}
}