{
  "type": "Feature",
  "properties": {
    "iso:country":"BE",
    "sg:address":"Wezelbaan 78",
    "sg:city":"Diest",
    "sg:orig_category":"Babyspullen",
    "sg:phone":"+32 13 32 16 09",
    "sg:postcode":"3290",
    "sg:province":"Vlaams-Brabant",
    "wof:name":"Den Ooievaar",
    "wof:placetype":"venue"
},
  "geometry": {"coordinates":[5.0909099579,51.0014801025],"type":"Point"}
}