{
  "type": "Feature",
  "properties": {
    "iso:country":"BE",
    "sg:address":"Schijnpoortweg 55",
    "sg:city":"Antwerpen",
    "sg:orig_category":"DIVERSE RECREATIEVE ACTIVITEITEN",
    "sg:phone":"+32 3 236 96 75",
    "sg:postcode":"2060",
    "sg:province":"Antwerpen",
    "wof:name":"B.c. Merksem",
    "wof:placetype":"venue"
},
  "geometry": {"coordinates":[4.4411101341,51.2287521362],"type":"Point"}
}