{
  "type": "Feature",
  "properties": {
    "iso:country":"BE",
    "sg:address":"Grand Chemin De Messines 100",
    "sg:city":"Komen-waasten/comines-warneton",
    "sg:orig_category":"Eleveurs de bovins",
    "sg:phone":"+32 56 55 52 05",
    "sg:postcode":"7780",
    "sg:province":"Hainaut",
    "wof:name":"Joseph Charlets",
    "wof:placetype":"venue"
},
  "geometry": {"coordinates":[2.9984300137,50.7863311768],"type":"Point"}
}