{
  "type": "Feature",
  "properties": {
    "iso:country":"BE",
    "sg:address":"Slangbeekstraat 21",
    "sg:city":"Hasselt",
    "sg:orig_category":"Sportclubs",
    "sg:phone":"+32 11 23 34 48",
    "sg:postcode":"3511",
    "sg:province":"Limburg",
    "wof:name":"Ygdrasil Shotokan Karate",
    "wof:placetype":"venue"
},
  "geometry": {"coordinates":[5.3151230812,50.9604682922],"type":"Point"}
}