{
  "type": "Feature",
  "properties": {
    "iso:country":"BE",
    "sg:address":"Kapellei 21",
    "sg:city":"Zoersel",
    "sg:orig_category":"Banques and organismes de cr\u00e9dit",
    "sg:phone":"+32 3 383 54 41",
    "sg:postcode":"2980",
    "sg:province":"Antwerpen",
    "wof:name":"Anhyp",
    "wof:placetype":"venue"
},
  "geometry": {"coordinates":[4.6319088936,51.2625541687],"type":"Point"}
}