{
  "type": "Feature",
  "properties": {
    "addr:full":"Voogdijstraat 21a Heist-op-den-berg Antwerpen 2220",
    "addr:housenumber":"21a",
    "addr:postcode":"2220",
    "addr:street":"Voogdijstraat",
    "iso:country":"BE",
    "sg:address":"Voogdijstraat 21a",
    "sg:city":"Heist-op-den-berg",
    "sg:classifiers":[
        {
            "category":"Health Services",
            "subcategory":"Health Practitioner",
            "type":"Services"
        }
    ],
    "sg:phone":"+32 15 24 92 38",
    "sg:postcode":"2220",
    "sg:province":"Antwerpen",
    "sg:tags":[
        "physiotherapist"
    ],
    "wof:name":"Mattijs Herman",
    "wof:placetype":"venue"
},
  "geometry": {"coordinates":[4.7283000946,51.0768203735],"type":"Point"}
}