{
  "type": "Feature",
  "properties": {
    "addr:full":"Avenue De La Paix 48 Li\u00e8ge 1 (grivegn\u00e9e) Li\u00e8ge 4030",
    "addr:housenumber":"48;1",
    "addr:postcode":"4030",
    "addr:street":"Avenue De La Paix",
    "iso:country":"BE",
    "sg:address":"Avenue De La Paix 48",
    "sg:city":"Li\u00e8ge 1 (grivegn\u00e9e)",
    "sg:classifiers":[
        {
            "category":"Health Services",
            "subcategory":"Doctor",
            "type":"Services"
        }
    ],
    "sg:phone":"+32 4 343 82 63",
    "sg:postcode":"4030",
    "sg:province":"Li\u00e8ge",
    "sg:tags":[
        "medicinephysicians",
        "surgeon"
    ],
    "wof:name":"Markiewicz D",
    "wof:placetype":"venue"
},
  "geometry": {"coordinates":[5.6088218689,50.6275863647],"type":"Point"}
}