{
  "type": "Feature",
  "properties": {
    "addr:full":"Verhoogstraat 24 Wichelen Oost-Vlaanderen 9260",
    "addr:housenumber":"24",
    "addr:postcode":"9260",
    "addr:street":"Verhoogstraat",
    "iso:country":"BE",
    "sg:address":"Verhoogstraat 24",
    "sg:city":"Wichelen",
    "sg:orig_category":"Plaatsen van vloer- and muurbekleding Schilders Verlichting and huishoudartikelen",
    "sg:phone":"+32 9 366 46 73",
    "sg:postcode":"9260",
    "sg:province":"Oost-Vlaanderen",
    "wof:name":"Tom Haentjens",
    "wof:placetype":"venue"
},
  "geometry": {"coordinates":[3.9467439651,50.987991333],"type":"Point"}
}