{
  "type": "Feature",
  "properties": {
    "addr:full":"Chauss\u00c9e De Haecht 1405 Brussel/bruxelles Bruxelles-Capitale 1130",
    "addr:postcode":"1405;/ bruxelles;1130",
    "addr:street":"Chausse\u0301E De Haecht",
    "iso:country":"BE",
    "sg:address":"Chauss\u00c9e De Haecht 1405",
    "sg:city":"Brussel/bruxelles",
    "sg:orig_category":"Editeurs de revues and p\u00e9riodiques. Editeurs de journaux",
    "sg:phone":"+32 2 244 15 11",
    "sg:postcode":"1130",
    "sg:province":"Bruxelles-Capitale",
    "wof:name":"B.i.v.v.",
    "wof:placetype":"venue"
},
  "geometry": {"coordinates":[4.4200730324,50.8837471008],"type":"Point"}
}