{
  "type": "Feature",
  "properties": {
    "addr:full":"Buizegemlei 58 Edegem Antwerpen 2650",
    "addr:housenumber":"58",
    "addr:postcode":"2650",
    "addr:street":"Buizegemlei",
    "iso:country":"BE",
    "sg:address":"Buizegemlei 58",
    "sg:city":"Edegem",
    "sg:orig_category":"Brood, gebak and snoepgoed",
    "sg:phone":"+32 3 457 32 84",
    "sg:postcode":"2650",
    "sg:province":"Antwerpen",
    "wof:name":"Sint-antonius",
    "wof:placetype":"venue"
},
  "geometry": {"coordinates":[4.4540982246,51.1504249573],"type":"Point"}
}