{
  "type": "Feature",
  "properties": {
    "addr:full":"Rue Neuve 30 Boussu Hainaut 7300",
    "addr:housenumber":"30",
    "addr:postcode":"7300",
    "addr:street":"Rue Neuve",
    "iso:country":"BE",
    "sg:address":"Rue Neuve 30",
    "sg:city":"Boussu",
    "sg:orig_category":"Supermarch\u00e9s. Epiceries",
    "sg:phone":"+32 65 78 35 74",
    "sg:postcode":"7300",
    "sg:province":"Hainaut",
    "wof:name":"Ad Delhaize",
    "wof:placetype":"venue"
},
  "geometry": {"coordinates":[3.7946279049,50.4323539734],"type":"Point"}
}