{
  "type": "Feature",
  "properties": {
    "iso:country":"BE",
    "sg:address":"Molenweg 23",
    "sg:city":"Dilsen-stokkem (rotem)",
    "sg:classifiers":[
        {
            "category":"Health Services",
            "subcategory":"Health Practitioner",
            "type":"Services"
        }
    ],
    "sg:phone":"+32 89 75 53 91",
    "sg:postcode":"3650",
    "sg:province":"Limburg",
    "sg:tags":[
        "physiotherapist"
    ],
    "wof:name":"Van Oeteren Relinde",
    "wof:placetype":"venue"
},
  "geometry": {"coordinates":[5.733520031,51.058429718],"type":"Point"}
}