{
  "type": "Feature",
  "properties": {
    "addr:full":"Rue Mimberc\u00e9e 5 Walcourt (yves-gomez\u00e9e) Namur 5650",
    "addr:housenumber":"5",
    "addr:postcode":"5650",
    "addr:street":"Rue Mimberce\u0301E",
    "iso:country":"BE",
    "sg:address":"Rue Mimberc\u00e9e 5",
    "sg:city":"Walcourt (yves-gomez\u00e9e)",
    "sg:classifiers":[
        {
            "category":"Building & Trades",
            "subcategory":"Construction",
            "type":"Services"
        }
    ],
    "sg:phone":"+32 71 65 52 45",
    "sg:postcode":"5650",
    "sg:province":"Namur",
    "sg:tags":[
        "installation",
        "-",
        "central",
        "heating"
    ],
    "wof:name":"Desormeaux G",
    "wof:placetype":"venue"
},
  "geometry": {"coordinates":[4.4313349724,50.2514762878],"type":"Point"}
}