{
  "type": "Feature",
  "properties": {
    "addr:full":"Sint-denijsplein 16 Vorst/forest Bruxelles-Capitale 1190",
    "addr:housenumber":"16",
    "addr:postcode":"1190",
    "addr:street":"Sint-Denijsplein;/ Forest",
    "iso:country":"BE",
    "sg:address":"Sint-denijsplein 16",
    "sg:city":"Vorst/forest",
    "sg:orig_category":"Verplichte sociale verzekeringen",
    "sg:phone":"+32 2 376 22 40",
    "sg:postcode":"1190",
    "sg:province":"Bruxelles-Capitale",
    "wof:name":"Pr\u00c9voyance Mutualit\u00c9",
    "wof:placetype":"venue"
},
  "geometry": {"coordinates":[4.3164248466,50.8098869324],"type":"Point"}
}