{
  "type": "Feature",
  "properties": {
    "addr:full":"Andries Pevernagestraat 50 Harelbeke West-Vlaanderen 8530",
    "addr:housenumber":"50",
    "addr:postcode":"8530",
    "addr:street":"Andries Pevernagestraat",
    "iso:country":"BE",
    "sg:address":"Andries Pevernagestraat 50",
    "sg:city":"Harelbeke",
    "sg:orig_category":"Services de Nettoyage and de D\u00e9sinfection",
    "sg:phone":"+32 56 72 50 41",
    "sg:postcode":"8530",
    "sg:province":"West-Vlaanderen",
    "wof:name":"Perfect",
    "wof:placetype":"venue"
},
  "geometry": {"coordinates":[3.3084750175,50.8523521423],"type":"Point"}
}