{
  "type": "Feature",
  "properties": {
    "iso:country":"BE",
    "sg:address":"Rue Du Noyer 285",
    "sg:city":"Bruxelles",
    "sg:classifiers":[
        {
            "category":"Wholesale",
            "subcategory":"Hardware",
            "type":"Manufacturing & Wholesale Goods"
        }
    ],
    "sg:phone":"+32 2 735 06 76",
    "sg:postcode":"1000",
    "sg:province":"Bruxelles-Capitale",
    "sg:tags":[
        "lubricating",
        "compound"
    ],
    "wof:name":"Minerv'oil",
    "wof:placetype":"venue"
},
  "geometry": {"coordinates":[4.3956727982,50.8438072205],"type":"Point"}
}