{
  "type": "Feature",
  "properties": {
    "iso:country":"BE",
    "sg:address":"Kapelstraat 61",
    "sg:city":"Kapellen",
    "sg:orig_category":"Agences d'exp\u00e9dition",
    "sg:phone":"+32 3 664 20 88",
    "sg:postcode":"2950",
    "sg:province":"Antwerpen",
    "wof:name":"China Commercial Center Antwerp",
    "wof:placetype":"venue"
},
  "geometry": {"coordinates":[4.4166378975,51.3277397156],"type":"Point"}
}