{
  "type": "Feature",
  "properties": {
    "iso:country":"BE",
    "sg:address":"Greinschuurstraat 21",
    "sg:city":"Brugge",
    "sg:orig_category":"Kapsalons",
    "sg:phone":"+32 50 33 60 09",
    "sg:postcode":"8000",
    "sg:province":"West-Vlaanderen",
    "wof:name":"Cupido Hairstyling",
    "wof:placetype":"venue"
},
  "geometry": {"coordinates":[3.213917017,51.2059516907],"type":"Point"}
}