{
  "type": "Feature",
  "properties": {
    "addr:full":"Amelbergastraat 14 Zandhoven Antwerpen 2240",
    "addr:housenumber":"14",
    "addr:postcode":"2240",
    "addr:street":"Amelbergastraat",
    "iso:country":"BE",
    "sg:address":"Amelbergastraat 14",
    "sg:city":"Zandhoven",
    "sg:classifiers":[
        {
            "category":"Real Estate",
            "subcategory":"Real Estate Services",
            "type":"Services"
        }
    ],
    "sg:phone":"+32 3 464 06 01",
    "sg:postcode":"2240",
    "sg:province":"Antwerpen",
    "wof:name":"Century 21 D.w. Zandhoven",
    "wof:placetype":"venue"
},
  "geometry": {"coordinates":[4.6612291336,51.2157783508],"type":"Point"}
}