{
  "type": "Feature",
  "properties": {
    "addr:full":"Leuvensesteenweg 166 Diest Vlaams-Brabant 3290",
    "addr:housenumber":"166",
    "addr:postcode":"3290",
    "addr:street":"Leuvensesteenweg",
    "iso:country":"BE",
    "sg:address":"Leuvensesteenweg 166",
    "sg:city":"Diest",
    "sg:orig_category":"Geschenken and souvenirs Speelgoed Verlichting and huishoudartikelen",
    "sg:phone":"+32 13 32 33 73",
    "sg:postcode":"3290",
    "sg:province":"Vlaams-Brabant",
    "wof:name":"Blokker",
    "wof:placetype":"venue"
},
  "geometry": {"coordinates":[5.0362567902,50.9709701538],"type":"Point"}
}