{
  "type": "Feature",
  "properties": {
    "iso:country":"BE",
    "sg:address":"Ponjaardhoekstraat 5",
    "sg:city":"Beveren",
    "sg:orig_category":"Producteurs de fruits",
    "sg:phone":"+32 3 755 02 50",
    "sg:postcode":"9120",
    "sg:province":"Oost-Vlaanderen",
    "wof:name":"Louis Truyman",
    "wof:placetype":"venue"
},
  "geometry": {"coordinates":[4.3019928932,51.2074775696],"type":"Point"}
}