{
  "type": "Feature",
  "properties": {
    "addr:full":"Havenkaai Kortrijk West-Vlaanderen 8500",
    "addr:postcode":"8500",
    "iso:country":"BE",
    "sg:address":"Havenkaai",
    "sg:city":"Kortrijk",
    "sg:classifiers":[
        {
            "category":"Food & Beverages",
            "subcategory":"Fruits & Vegetables",
            "type":"Retail Goods"
        }
    ],
    "sg:phone":"+32 56 25 21 10",
    "sg:postcode":"8500",
    "sg:province":"West-Vlaanderen",
    "sg:tags":[
        "-"
    ],
    "wof:name":"Fruitpoort (de)",
    "wof:placetype":"venue"
},
  "geometry": {"coordinates":[3.2501039505,50.8270606995],"type":"Point"}
}