{
  "type": "Feature",
  "properties": {
    "addr:full":"Bruggestraat 232 Menen West-Vlaanderen 8930",
    "addr:housenumber":"232",
    "addr:postcode":"8930",
    "addr:street":"Bruggestraat",
    "iso:country":"BE",
    "sg:address":"Bruggestraat 232",
    "sg:city":"Menen",
    "sg:orig_category":"Banques and organismes de cr\u00e9dit",
    "sg:phone":"+32 56 51 76 77",
    "sg:postcode":"8930",
    "sg:province":"West-Vlaanderen",
    "wof:name":"Dexia",
    "wof:placetype":"venue"
},
  "geometry": {"coordinates":[3.123169899,50.8027801514],"type":"Point"}
}