{
  "type": "Feature",
  "properties": {
    "iso:country":"BE",
    "sg:address":"Rue Du Plateau 38",
    "sg:city":"Moeskroen/mouscron",
    "sg:orig_category":"M\u00e9decins and sp\u00e9cialistes",
    "sg:phone":"+32 56 34 90 55",
    "sg:postcode":"7700",
    "sg:province":"Hainaut",
    "wof:name":"J.p. Delaby",
    "wof:placetype":"venue"
},
  "geometry": {"coordinates":[3.2323200703,50.7400932312],"type":"Point"}
}