{
  "type": "Feature",
  "properties": {
    "addr:full":"Kerkstraat 31 Ieper West-Vlaanderen 8900",
    "addr:housenumber":"31",
    "addr:postcode":"8900",
    "addr:street":"Kerkstraat",
    "iso:country":"BE",
    "sg:address":"Kerkstraat 31",
    "sg:city":"Ieper",
    "sg:orig_category":"Bedrijfsamusement Sportactiviteiten en -evenementen",
    "sg:phone":"+32 57 21 74 15",
    "sg:postcode":"8900",
    "sg:province":"West-Vlaanderen",
    "wof:name":"Sport-track Outdoor",
    "wof:placetype":"venue"
},
  "geometry": {"coordinates":[2.8324561119,50.8173294067],"type":"Point"}
}