{
  "type": "Feature",
  "properties": {
    "iso:country":"BE",
    "sg:address":"Staatsbaan 279",
    "sg:city":"Bekkevoort",
    "sg:orig_category":"Fietsen Fab",
    "sg:phone":"+32 16 63 20 95",
    "sg:postcode":"3460",
    "sg:province":"Vlaams-Brabant",
    "wof:name":"Simons",
    "wof:placetype":"venue"
},
  "geometry": {"coordinates":[4.9673299789,50.9426612854],"type":"Point"}
}