{
  "type": "Feature",
  "properties": {
    "addr:full":"Bevrijdingsstraat 42 Brecht Antwerpen 2960",
    "addr:housenumber":"42",
    "addr:postcode":"2960",
    "addr:street":"Bevrijdingsstraat",
    "iso:country":"BE",
    "sg:address":"Bevrijdingsstraat 42",
    "sg:city":"Brecht",
    "sg:classifiers":[
        {
            "category":"Insurance",
            "subcategory":"Life Insurance",
            "type":"Services"
        }
    ],
    "sg:phone":"+32 3 313 61 36",
    "sg:postcode":"2960",
    "sg:province":"Antwerpen",
    "sg:tags":[
        "assurance"
    ],
    "wof:name":"Bureau Triple A",
    "wof:placetype":"venue"
},
  "geometry": {"coordinates":[4.6415200233,51.3512115479],"type":"Point"}
}