{
  "type": "Feature",
  "properties": {
    "addr:full":"Koornbloemstraat 82 Antwerpen (wilrijk) Antwerpen 2610",
    "addr:housenumber":"82",
    "addr:postcode":"2610",
    "addr:street":"Koornbloemstraat;Antwerpen",
    "iso:country":"BE",
    "sg:address":"Koornbloemstraat 82",
    "sg:city":"Antwerpen (wilrijk)",
    "sg:classifiers":[
        {
            "category":"Retail",
            "subcategory":"Repair Shop",
            "type":"Services"
        }
    ],
    "sg:phone":"+32 3 830 59 77",
    "sg:postcode":"2610",
    "sg:province":"Antwerpen",
    "sg:tags":[
        "upholsterer"
    ],
    "wof:name":"De Potter D Renovaria",
    "wof:placetype":"venue"
},
  "geometry": {"coordinates":[4.3946051598,51.1691131592],"type":"Point"}
}