{
  "type": "Feature",
  "properties": {
    "iso:country":"BE",
    "sg:address":"Lichterveldestraat 20",
    "sg:city":"Wingene (zwevezele)",
    "sg:classifiers":[
        {
            "category":"Bakery",
            "type":"Food & Drink"
        }
    ],
    "sg:phone":"+32 51 61 15 74",
    "sg:postcode":"8750",
    "sg:province":"West-Vlaanderen",
    "sg:tags":[
        "confectioner",
        "baker"
    ],
    "wof:name":"Billiet G",
    "wof:placetype":"venue"
},
  "geometry": {"coordinates":[3.2087550163,51.0363807678],"type":"Point"}
}