{
  "type": "Feature",
  "properties": {
    "addr:full":"Mayel\u00e8ne 15 Malmedy (bellevaux-lignueville) Li\u00e8ge 4960",
    "addr:housenumber":"15",
    "addr:postcode":"4960",
    "addr:street":"Mayele\u0300Ne",
    "iso:country":"BE",
    "sg:address":"Mayel\u00e8ne 15",
    "sg:city":"Malmedy (bellevaux-lignueville)",
    "sg:classifiers":[
        {
            "category":"Retail",
            "subcategory":"Auto Repair",
            "type":"Services"
        }
    ],
    "sg:phone":"+32 80 57 03 31",
    "sg:postcode":"4960",
    "sg:province":"Li\u00e8ge",
    "sg:tags":[
        "automobile-body"
    ],
    "wof:name":"Blaise R & Fils",
    "wof:placetype":"venue"
},
  "geometry": {"coordinates":[6.0613188744,50.3776626587],"type":"Point"}
}