{
  "type": "Feature",
  "properties": {
    "addr:full":"Torhoutsesteenweg 24 Loppem West-Vlaanderen 8210",
    "addr:housenumber":"24",
    "addr:postcode":"8210",
    "addr:street":"Torhoutsesteenweg",
    "iso:country":"BE",
    "sg:address":"Torhoutsesteenweg 24",
    "sg:city":"Loppem",
    "sg:orig_category":"MEUBELONTWERP AND -INSTALLATIE",
    "sg:phone":"+32 50 84 18 84",
    "sg:postcode":"8210",
    "sg:province":"West-Vlaanderen",
    "wof:name":"H & P, Keuken En Bad",
    "wof:placetype":"venue"
},
  "geometry": {"coordinates":[3.1666750908,51.1547241211],"type":"Point"}
}