{
  "type": "Feature",
  "properties": {
    "addr:full":"Rue Carly 2 Ham-sur-heure-nalinnes Hainaut 6120",
    "addr:housenumber":"2",
    "addr:postcode":"6120",
    "addr:street":"Rue Carly;Hainaut",
    "iso:country":"BE",
    "sg:address":"Rue Carly 2",
    "sg:city":"Ham-sur-heure-nalinnes",
    "sg:orig_category":"Sportclubs",
    "sg:phone":"+32 71 22 05 21",
    "sg:postcode":"6120",
    "sg:province":"Hainaut",
    "wof:name":"T.c. Mont-sur-marchienne",
    "wof:placetype":"venue"
},
  "geometry": {"coordinates":[4.3872900009,50.3219146729],"type":"Point"}
}