{
  "type": "Feature",
  "properties": {
    "iso:country":"BE",
    "sg:address":"Laerstraat 10",
    "sg:city":"Opglabbeek",
    "sg:orig_category":"Drogueries",
    "sg:phone":"+32 89 85 57 48",
    "sg:postcode":"3660",
    "sg:province":"Limburg",
    "wof:name":"Mathieu Dirkx",
    "wof:placetype":"venue"
},
  "geometry": {"coordinates":[5.5912117958,51.0528755188],"type":"Point"}
}