{
  "type": "Feature",
  "properties": {
    "iso:country":"BE",
    "sg:address":"Chauss\u00c9e De Waterloo 699",
    "sg:city":"Ukkel/uccle",
    "sg:orig_category":"Grands magasins. Services annexes des transports terrestres",
    "sg:phone":"+32 2 345 38 90",
    "sg:postcode":"1180",
    "sg:province":"Bruxelles-Capitale",
    "wof:name":"Inno",
    "wof:placetype":"venue"
},
  "geometry": {"coordinates":[4.3667678833,50.8158836365],"type":"Point"}
}