{
  "type": "Feature",
  "properties": {
    "iso:country":"BE",
    "sg:address":"Speelhofdreef 43",
    "sg:city":"Schilde",
    "sg:classifiers":[
        {
            "category":"Professional",
            "subcategory":"Art Services",
            "type":"Services"
        }
    ],
    "sg:phone":"+32 3 385 27 22",
    "sg:postcode":"2970",
    "sg:province":"Antwerpen",
    "sg:tags":[
        "interior",
        "designer"
    ],
    "wof:name":"Boumans T",
    "wof:placetype":"venue"
},
  "geometry": {"coordinates":[4.5738677979,51.2274703979],"type":"Point"}
}