{
  "type": "Feature",
  "properties": {
    "addr:full":"Eekhoutstraat 15 Brugge West-Vlaanderen 8000",
    "addr:housenumber":"15",
    "addr:postcode":"8000",
    "addr:street":"Eekhoutstraat",
    "iso:country":"BE",
    "sg:address":"Eekhoutstraat 15",
    "sg:city":"Brugge",
    "sg:classifiers":[
        {
            "category":"Personal",
            "subcategory":"Barber",
            "type":"Services"
        }
    ],
    "sg:phone":"+32 50 33 36 03",
    "sg:postcode":"8000",
    "sg:province":"West-Vlaanderen",
    "sg:tags":[
        "gentleman",
        "salon",
        "-",
        "hairdressing"
    ],
    "wof:name":"Wallez R",
    "wof:placetype":"venue"
},
  "geometry": {"coordinates":[3.2279438972,51.2065849304],"type":"Point"}
}