{
  "type": "Feature",
  "properties": {
    "addr:full":"Mechelsestraat 101 Londerzeel Vlaams-Brabant 1840",
    "addr:housenumber":"101",
    "addr:postcode":"1840",
    "addr:street":"Mechelsestraat",
    "iso:country":"BE",
    "sg:address":"Mechelsestraat 101",
    "sg:city":"Londerzeel",
    "sg:classifiers":[
        {
            "category":"Personal",
            "subcategory":"Beauty Salon",
            "type":"Services"
        }
    ],
    "sg:phone":"+32 52 30 22 59",
    "sg:postcode":"1840",
    "sg:province":"Vlaams-Brabant",
    "sg:tags":[
        "lady",
        "-",
        "hairdressing"
    ],
    "wof:name":"Van Pee K",
    "wof:placetype":"venue"
},
  "geometry": {"coordinates":[4.3090591431,51.0052032471],"type":"Point"}
}