{
  "type": "Feature",
  "properties": {
    "addr:full":"Grote Molenweg 154 Stabroek Antwerpen 2940",
    "addr:housenumber":"154",
    "addr:postcode":"2940",
    "addr:street":"Grote Molenweg",
    "iso:country":"BE",
    "sg:address":"Grote Molenweg 154",
    "sg:city":"Stabroek",
    "sg:orig_category":"Verhuur diversen Winkelinrichting and handelsuitrusting Gh",
    "sg:phone":"+32 3 568 19 28",
    "sg:postcode":"2940",
    "sg:province":"Antwerpen",
    "wof:name":"De Kinderkoning",
    "wof:placetype":"venue"
},
  "geometry": {"coordinates":[4.3792681694,51.3301086426],"type":"Point"}
}