{
  "type": "Feature",
  "properties": {
    "iso:country":"BE",
    "sg:address":"Pas 121",
    "sg:city":"Geel",
    "sg:classifiers":[
        {
            "category":"Food & Beverages",
            "subcategory":"Chocolate",
            "type":"Retail Goods"
        }
    ],
    "sg:phone":"+32 14 58 57 28",
    "sg:postcode":"2440",
    "sg:province":"Antwerpen",
    "sg:tags":[
        "confectionery",
        "-"
    ],
    "wof:name":"Verlooy-coeurs D'amour",
    "wof:placetype":"venue"
},
  "geometry": {"coordinates":[4.988134861,51.15832901],"type":"Point"}
}