{
  "type": "Feature",
  "properties": {
    "iso:country":"BE",
    "sg:address":"Hansbekestraat 18",
    "sg:city":"Wervik",
    "sg:orig_category":"Papeteries. Imprimeries and copyshops",
    "sg:phone":"+32 56 31 15 01",
    "sg:postcode":"8940",
    "sg:province":"West-Vlaanderen",
    "wof:name":"Drukkerij Six-blieck",
    "wof:placetype":"venue"
},
  "geometry": {"coordinates":[3.0290100574,50.7783660889],"type":"Point"}
}