{
  "type": "Feature",
  "properties": {
    "iso:country":"BE",
    "sg:address":"Prinsessestraat 166",
    "sg:city":"Izegem",
    "sg:classifiers":[
        {
            "category":"Health Services",
            "subcategory":"Health Practitioner",
            "type":"Services"
        }
    ],
    "sg:phone":"+32 51 30 79 05",
    "sg:postcode":"8870",
    "sg:province":"West-Vlaanderen",
    "sg:tags":[
        "physiotherapist"
    ],
    "wof:name":"Lievens M",
    "wof:placetype":"venue"
},
  "geometry": {"coordinates":[3.2203919888,50.9234886169],"type":"Point"}
}