{
  "type": "Feature",
  "properties": {
    "addr:full":"Stationsstraat 7 Oosterzele Oost-Vlaanderen 9860",
    "addr:housenumber":"7",
    "addr:postcode":"9860",
    "addr:street":"Stationsstraat;Oost-Vlaanderen",
    "iso:country":"BE",
    "sg:address":"Stationsstraat 7",
    "sg:city":"Oosterzele",
    "sg:orig_category":"Banques and organismes de cr\u00e9dit",
    "sg:phone":"+32 9 362 69 35",
    "sg:postcode":"9860",
    "sg:province":"Oost-Vlaanderen",
    "wof:name":"Kbc",
    "wof:placetype":"venue"
},
  "geometry": {"coordinates":[3.7833480835,50.9379348755],"type":"Point"}
}