{
  "type": "Feature",
  "properties": {
    "addr:full":"Rue De La Prelle 12 Charleroi (gosselies) Hainaut 6041",
    "addr:housenumber":"12",
    "addr:postcode":"6041",
    "addr:street":"Rue De La Prelle",
    "iso:country":"BE",
    "sg:address":"Rue De La Prelle 12",
    "sg:city":"Charleroi (gosselies)",
    "sg:orig_category":"Non-Classified Establishments",
    "sg:phone":"+32 71 34 00 44",
    "sg:postcode":"6041",
    "sg:province":"Hainaut",
    "wof:name":"Quintart Designer Sprl",
    "wof:placetype":"venue"
},
  "geometry": {"coordinates":[4.4314317703,50.4685935974],"type":"Point"}
}