{
  "type": "Feature",
  "properties": {
    "iso:country":"BE",
    "sg:address":"Lattenklieversstraat 126",
    "sg:city":"Beernem",
    "sg:orig_category":"Artsen and specialisten",
    "sg:phone":"+32 50 78 81 67",
    "sg:postcode":"8730",
    "sg:province":"West-Vlaanderen",
    "wof:name":"Erik Vromman",
    "wof:placetype":"venue"
},
  "geometry": {"coordinates":[3.3593420982,51.1266098022],"type":"Point"}
}