{
  "type": "Feature",
  "properties": {
    "addr:full":"Avenue Louis Bertrand 121 Bruxelles (schaerbeek) Bruxelles-Capitale 1030",
    "addr:housenumber":"121",
    "addr:postcode":"1030",
    "addr:street":"Avenue Louis Bertrand",
    "iso:country":"BE",
    "sg:address":"Avenue Louis Bertrand 121",
    "sg:city":"Bruxelles (schaerbeek)",
    "sg:classifiers":[
        {
            "category":"Communications",
            "subcategory":"News Services",
            "type":"Services"
        }
    ],
    "sg:phone":"+32 2 216 83 55",
    "sg:postcode":"1030",
    "sg:province":"Bruxelles-Capitale",
    "sg:tags":[
        "illustrator"
    ],
    "wof:name":"Salemi J.c.",
    "wof:placetype":"venue"
},
  "geometry": {"coordinates":[4.3794350624,50.8632087708],"type":"Point"}
}