{
  "type": "Feature",
  "properties": {
    "addr:full":"Quai Du Bassin 16-18 Herstal Li\u00e8ge 4040",
    "addr:postcode":"16-18;4040",
    "addr:street":"Quai Du Bassin",
    "iso:country":"BE",
    "sg:address":"Quai Du Bassin 16-18",
    "sg:city":"Herstal",
    "sg:classifiers":[
        {
            "category":"Retail",
            "subcategory":"Auto Repair",
            "type":"Services"
        }
    ],
    "sg:phone":"+32 4 240 68 30",
    "sg:postcode":"4040",
    "sg:province":"Li\u00e8ge",
    "sg:tags":[
        "garage"
    ],
    "wof:name":"Catalogne Automobiles Sa",
    "wof:placetype":"venue"
},
  "geometry": {"coordinates":[5.615445137,50.6553001404],"type":"Point"}
}