{
  "type": "Feature",
  "properties": {
    "addr:full":"Rue J Wauters 125 Anderlues Hainaut 6500",
    "addr:housenumber":"125",
    "addr:postcode":"6500",
    "addr:street":"Rue J Wauters",
    "iso:country":"BE",
    "sg:address":"Rue J Wauters 125",
    "sg:city":"Anderlues",
    "sg:classifiers":[
        {
            "category":"Insurance",
            "subcategory":"Life Insurance",
            "type":"Services"
        }
    ],
    "sg:phone":"+32 71 52 17 80",
    "sg:postcode":"6500",
    "sg:province":"Hainaut",
    "sg:tags":[
        "assurance"
    ],
    "wof:name":"Immo Pret",
    "wof:placetype":"venue"
},
  "geometry": {"coordinates":[4.2353200912,50.2372131348],"type":"Point"}
}