{
  "type": "Feature",
  "properties": {
    "addr:full":"Rue Fernand Houget 19 Verviers Li\u00e8ge 4800",
    "addr:housenumber":"19",
    "addr:postcode":"4800",
    "addr:street":"Rue Fernand Houget",
    "iso:country":"BE",
    "sg:address":"Rue Fernand Houget 19",
    "sg:city":"Verviers",
    "sg:classifiers":[
        {
            "category":"Manufacturing",
            "subcategory":"Tools & Machinery",
            "type":"Manufacturing & Wholesale Goods"
        }
    ],
    "sg:phone":"+32 87 31 52 89",
    "sg:postcode":"4800",
    "sg:province":"Li\u00e8ge",
    "sg:tags":[
        "-"
    ],
    "wof:name":"Outibest Sa",
    "wof:placetype":"venue"
},
  "geometry": {"coordinates":[5.8476219177,50.5891036987],"type":"Point"}
}