{
  "type": "Feature",
  "properties": {
    "addr:full":"Rue Walth\u00c8re Jamar 210 Ans Li\u00e8ge 4430",
    "addr:housenumber":"210",
    "addr:postcode":"4430",
    "addr:street":"Rue Walthe\u0300Re Jamar",
    "iso:country":"BE",
    "sg:address":"Rue Walth\u00c8re Jamar 210",
    "sg:city":"Ans",
    "sg:classifiers":[
        {
            "category":"Cafe",
            "type":"Food & Drink"
        }
    ],
    "sg:phone":"+32 4 263 67 79",
    "sg:postcode":"4430",
    "sg:province":"Li\u00e8ge",
    "sg:tags":[
        "caf\u00e9s"
    ],
    "wof:name":"Luciano Sommacal",
    "wof:placetype":"venue"
},
  "geometry": {"coordinates":[5.5312709808,50.6558685303],"type":"Point"}
}