{
  "type": "Feature",
  "properties": {
    "addr:full":"Nijverheidszone 'begijnenmeers' 73 Liedekerke Vlaams-Brabant 1770",
    "addr:postcode":"1770",
    "addr:street":"Vlaams-Brabant",
    "iso:country":"BE",
    "sg:address":"Nijverheidszone 'begijnenmeers' 73",
    "sg:city":"Liedekerke",
    "sg:orig_category":"Matrices",
    "sg:phone":"+32 53 68 12 40",
    "sg:postcode":"1770",
    "sg:province":"Vlaams-Brabant",
    "wof:name":"Matrix Engineering Belgium Nv",
    "wof:placetype":"venue"
},
  "geometry": {"coordinates":[4.0872688293,50.8854942322],"type":"Point"}
}