{
  "type": "Feature",
  "properties": {
    "iso:country":"BE",
    "sg:address":"Rue De Marche 9",
    "sg:city":"Bastogne",
    "sg:classifiers":[
        {
            "category":"Health Services",
            "subcategory":"Dentist",
            "type":"Services"
        }
    ],
    "sg:phone":"+32 61 21 76 73",
    "sg:postcode":"6600",
    "sg:province":"Luxembourg",
    "wof:name":"Cop Patricia",
    "wof:placetype":"venue"
},
  "geometry": {"coordinates":[5.7137789726,50.001159668],"type":"Point"}
}