{
  "type": "Feature",
  "properties": {
    "iso:country":"BE",
    "sg:address":"Rue Du Marotin 23",
    "sg:city":"Tintigny",
    "sg:orig_category":"Boekhouders",
    "sg:phone":"+32 63 44 41 34",
    "sg:postcode":"6730",
    "sg:province":"Luxembourg",
    "wof:name":"M. Vigneron",
    "wof:placetype":"venue"
},
  "geometry": {"coordinates":[5.5147800446,49.6819381714],"type":"Point"}
}