{
  "type": "Feature",
  "properties": {
    "addr:full":"Nijverheidsstraat 105 Gavere (dikkelvenne) Oost-Vlaanderen 9890",
    "addr:housenumber":"105",
    "addr:postcode":"9890",
    "addr:street":"Nijverheidsstraat",
    "iso:country":"BE",
    "sg:address":"Nijverheidsstraat 105",
    "sg:city":"Gavere (dikkelvenne)",
    "sg:classifiers":[
        {
            "category":"Building & Trades",
            "subcategory":"Pest Control",
            "type":"Services"
        }
    ],
    "sg:phone":"+32 9 384 18 74",
    "sg:postcode":"9890",
    "sg:province":"Oost-Vlaanderen",
    "sg:tags":[
        "painting",
        "contractor"
    ],
    "wof:name":"Gevaert E",
    "wof:placetype":"venue"
},
  "geometry": {"coordinates":[3.6776208878,50.9223861694],"type":"Point"}
}