{
  "type": "Feature",
  "properties": {
    "addr:full":"Rue Vivier Anon 7 Sombreffe Namur 5140",
    "addr:housenumber":"7",
    "addr:postcode":"5140",
    "addr:street":"Rue Vivier Anon",
    "iso:country":"BE",
    "sg:address":"Rue Vivier Anon 7",
    "sg:city":"Sombreffe",
    "sg:classifiers":[
        {
            "category":"Health Services",
            "subcategory":"Doctor",
            "type":"Services"
        }
    ],
    "sg:phone":"+32 71 88 56 76",
    "sg:postcode":"5140",
    "sg:province":"Namur",
    "sg:tags":[
        "psychotherapist",
        "psychoanalyst"
    ],
    "wof:name":"Huybrecht Bernadette",
    "wof:placetype":"venue"
},
  "geometry": {"coordinates":[4.6038661003,50.5408554077],"type":"Point"}
}