{
  "type": "Feature",
  "properties": {
    "iso:country":"BE",
    "sg:address":"Thier Ghisbert 183",
    "sg:city":"Wanze",
    "sg:orig_category":"Enseignement maternel and primaire",
    "sg:phone":"+32 85 71 11 86",
    "sg:postcode":"4520",
    "sg:province":"Li\u00e8ge",
    "wof:name":"Ecole Prim. Communale",
    "wof:placetype":"venue"
},
  "geometry": {"coordinates":[5.1665558815,50.5649490356],"type":"Point"}
}