{
  "type": "Feature",
  "properties": {
    "iso:country":"BE",
    "sg:address":"Rue Emile Muselle 24",
    "sg:city":"Berloz",
    "sg:orig_category":"Blanchisseries and teintureries",
    "sg:phone":"+32 19 32 27 10",
    "sg:postcode":"4257",
    "sg:province":"Li\u00e8ge",
    "wof:name":"Nettoyage De Hesbaye",
    "wof:placetype":"venue"
},
  "geometry": {"coordinates":[5.2118010521,50.7004585266],"type":"Point"}
}