{
  "type": "Feature",
  "properties": {
    "iso:country":"BE",
    "sg:address":"Rue Raymond Noel 41",
    "sg:city":"Profondeville",
    "sg:orig_category":"V\u00e9hicules automobiles",
    "sg:phone":"+32 81 43 33 45",
    "sg:postcode":"5170",
    "sg:province":"Namur",
    "wof:name":"Garage Neuville",
    "wof:placetype":"venue"
},
  "geometry": {"coordinates":[4.8109622002,50.3908691406],"type":"Point"}
}