{
  "type": "Feature",
  "properties": {
    "iso:country":"BE",
    "sg:address":"Route De Luxembourg 357",
    "sg:city":"Arlon",
    "sg:classifiers":[
        {
            "category":"Cafe",
            "type":"Food & Drink"
        }
    ],
    "sg:phone":"+32 63 22 52 36",
    "sg:postcode":"6706",
    "sg:province":"Luxembourg",
    "sg:tags":[
        "caf\u00e9s"
    ],
    "wof:name":"Cafe Du Wolberg",
    "wof:placetype":"venue"
},
  "geometry": {"coordinates":[5.8697757721,49.6491928101],"type":"Point"}
}