{
  "type": "Feature",
  "properties": {
    "addr:full":"Transcontinentaalweg 6 Antwerpen Antwerpen 2030",
    "addr:housenumber":"6",
    "addr:postcode":"2030",
    "addr:street":"Transcontinentaalweg",
    "iso:country":"BE",
    "sg:address":"Transcontinentaalweg 6",
    "sg:city":"Antwerpen",
    "sg:classifiers":[
        {
            "category":"Shopping",
            "subcategory":"Discount & Variety Stores",
            "type":"Retail Goods"
        }
    ],
    "sg:phone":"+32 3 545 02 00",
    "sg:postcode":"2030",
    "sg:province":"Antwerpen",
    "sg:tags":[
        "warehouse",
        "-",
        "merchandise"
    ],
    "wof:name":"Trans Polymer International Nv",
    "wof:placetype":"venue"
},
  "geometry": {"coordinates":[4.3946199417,51.2735786438],"type":"Point"}
}