{
  "type": "Feature",
  "properties": {
    "addr:full":"Heuvelstraat 82 Lommel Limburg 3920",
    "addr:housenumber":"82",
    "addr:postcode":"3920",
    "addr:street":"Heuvelstraat",
    "iso:country":"BE",
    "sg:address":"Heuvelstraat 82",
    "sg:city":"Lommel",
    "sg:orig_category":"Royal Canin. Produits c\u00e9r\u00e9aliers Fab",
    "sg:phone":"+32 11 54 42 76",
    "sg:postcode":"3920",
    "sg:province":"Limburg",
    "wof:name":"Vanheukelom G.",
    "wof:placetype":"venue"
},
  "geometry": {"coordinates":[5.3419451714,51.242767334],"type":"Point"}
}