{
  "type": "Feature",
  "properties": {
    "addr:full":"Casselstraat 5 Poperinge West-Vlaanderen 8970",
    "addr:housenumber":"5",
    "addr:postcode":"8970",
    "addr:street":"Casselstraat",
    "iso:country":"BE",
    "sg:address":"Casselstraat 5",
    "sg:city":"Poperinge",
    "sg:orig_category":"Herstelling horloges and juwelen Juwelen and horloges",
    "sg:phone":"+32 57 33 37 98",
    "sg:postcode":"8970",
    "sg:province":"West-Vlaanderen",
    "wof:name":"Annie Dejonghe",
    "wof:placetype":"venue"
},
  "geometry": {"coordinates":[2.7221529484,50.8543815613],"type":"Point"}
}