{
  "type": "Feature",
  "properties": {
    "addr:full":"Fosselstraat 60c Affligem Vlaams-Brabant 1790",
    "addr:housenumber":"60c",
    "addr:postcode":"1790",
    "addr:street":"Fosselstraat",
    "iso:country":"BE",
    "sg:address":"Fosselstraat 60c",
    "sg:city":"Affligem",
    "sg:orig_category":"Herstellingen and onderhoud van auto's",
    "sg:phone":"+32 53 68 02 43",
    "sg:postcode":"1790",
    "sg:province":"Vlaams-Brabant",
    "wof:name":"Fabian Plas",
    "wof:placetype":"venue"
},
  "geometry": {"coordinates":[4.1126708984,50.9157676697],"type":"Point"}
}