{
  "type": "Feature",
  "properties": {
    "iso:country":"BE",
    "sg:address":"Avenue Jean Van Horenbeeck 33",
    "sg:city":"Bruxelles (auderghem)",
    "sg:classifiers":[
        {
            "category":"Education",
            "subcategory":"School",
            "type":"Public Place"
        }
    ],
    "sg:phone":"+32 2 672 32 80",
    "sg:postcode":"1160",
    "sg:province":"Bruxelles-Capitale",
    "sg:tags":[
        "primary"
    ],
    "wof:name":"Blankedelle-colin (centre Scolaire De)",
    "wof:placetype":"venue"
},
  "geometry": {"coordinates":[4.4347457886,50.8069038391],"type":"Point"}
}