{
  "type": "Feature",
  "properties": {
    "iso:country":"BE",
    "sg:address":"Meerlaan 185",
    "sg:city":"Overijse",
    "sg:orig_category":"Eclairage et \u00e9quipements du foyer",
    "sg:phone":"+32 2 687 21 55",
    "sg:postcode":"3090",
    "sg:province":"Vlaams-Brabant",
    "wof:name":"Fleurissa",
    "wof:placetype":"venue"
},
  "geometry": {"coordinates":[4.5222082138,50.7298316956],"type":"Point"}
}