{
  "type": "Feature",
  "properties": {
    "addr:full":"Avenue Neptune 12 Bruxelles (forest) Bruxelles-Capitale 1190",
    "addr:housenumber":"12",
    "addr:postcode":"1190",
    "addr:street":"Avenue Neptune",
    "iso:country":"BE",
    "sg:address":"Avenue Neptune 12",
    "sg:city":"Bruxelles (forest)",
    "sg:classifiers":[
        {
            "category":"Health Services",
            "subcategory":"Doctor",
            "type":"Services"
        }
    ],
    "sg:phone":"+32 2 343 20 65",
    "sg:postcode":"1190",
    "sg:province":"Bruxelles-Capitale",
    "sg:tags":[
        "medicinephysicians",
        "surgeon"
    ],
    "wof:name":"Demoulin A",
    "wof:placetype":"venue"
},
  "geometry": {"coordinates":[4.3325181007,50.8135490417],"type":"Point"}
}