{
  "type": "Feature",
  "properties": {
    "iso:country":"BE",
    "sg:address":"Azaleastraat 5",
    "sg:city":"Zomergem",
    "sg:orig_category":"Bloemen and planten Gh",
    "sg:phone":"+32 9 372 70 92",
    "sg:postcode":"9930",
    "sg:province":"Oost-Vlaanderen",
    "wof:name":"Haerens A",
    "wof:placetype":"venue"
},
  "geometry": {"coordinates":[3.5675649643,51.1214942932],"type":"Point"}
}