{
  "type": "Feature",
  "properties": {
    "addr:full":"Marie-louiselaan 30 Dilbeek Vlaams-Brabant 1700",
    "addr:housenumber":"30",
    "addr:postcode":"1700",
    "addr:street":"Marie-Louiselaan",
    "iso:country":"BE",
    "sg:address":"Marie-louiselaan 30",
    "sg:city":"Dilbeek",
    "sg:classifiers":[
        {
            "category":"Health Services",
            "subcategory":"Doctor",
            "type":"Services"
        }
    ],
    "sg:phone":"+32 2 466 06 05",
    "sg:postcode":"1700",
    "sg:province":"Vlaams-Brabant",
    "sg:tags":[
        "medicinephysicians",
        "surgeon"
    ],
    "wof:name":"Glinoer D",
    "wof:placetype":"venue"
},
  "geometry": {"coordinates":[4.2832841873,50.8486862183],"type":"Point"}
}