{
  "type": "Feature",
  "properties": {
    "addr:full":"Rue Du Radoux 79 Rebecq (bierghes) Brabant Wallon 1430",
    "addr:housenumber":"79",
    "addr:postcode":"1430",
    "addr:street":"Rue Du Radoux;Wallon",
    "iso:country":"BE",
    "sg:address":"Rue Du Radoux 79",
    "sg:city":"Rebecq (bierghes)",
    "sg:classifiers":[
        {
            "category":"Professional",
            "subcategory":"Management & Consulting",
            "type":"Services"
        }
    ],
    "sg:phone":"+32 2 395 30 10",
    "sg:postcode":"1430",
    "sg:province":"Brabant Wallon",
    "sg:tags":[
        "-",
        "processing",
        "data",
        "consultant"
    ],
    "wof:name":"Admi Sprl",
    "wof:placetype":"venue"
},
  "geometry": {"coordinates":[4.110874176,50.7124290466],"type":"Point"}
}