{
  "type": "Feature",
  "properties": {
    "addr:full":"Astridlaan 174 Brugge West-Vlaanderen 8310",
    "addr:housenumber":"174",
    "addr:postcode":"8310",
    "addr:street":"Astridlaan",
    "iso:country":"BE",
    "sg:address":"Astridlaan 174",
    "sg:city":"Brugge",
    "sg:orig_category":"Artsen and specialisten",
    "sg:phone":"+32 50 35 32 53",
    "sg:postcode":"8310",
    "sg:province":"West-Vlaanderen",
    "wof:name":"Filip Callebaut",
    "wof:placetype":"venue"
},
  "geometry": {"coordinates":[3.2542290688,51.1949806213],"type":"Point"}
}