{
  "type": "Feature",
  "properties": {
    "iso:country":"BE",
    "sg:address":"Broesveldstraat 16",
    "sg:city":"Neerpelt",
    "sg:classifiers":[
        {
            "category":"Manufacturing",
            "subcategory":"Textiles",
            "type":"Manufacturing & Wholesale Goods"
        }
    ],
    "sg:phone":"+32 11 64 21 14",
    "sg:postcode":"3910",
    "sg:province":"Limburg",
    "sg:tags":[
        "retail",
        "-"
    ],
    "wof:name":"Van Den Rul M J",
    "wof:placetype":"venue"
},
  "geometry": {"coordinates":[5.4298791885,51.2301445007],"type":"Point"}
}