{
  "type": "Feature",
  "properties": {
    "addr:full":"Dijkstraat 21 Lokeren Oost-Vlaanderen 9160",
    "addr:housenumber":"21",
    "addr:postcode":"9160",
    "addr:street":"Dijkstraat",
    "iso:country":"BE",
    "sg:address":"Dijkstraat 21",
    "sg:city":"Lokeren",
    "sg:classifiers":[
        {
            "category":"Communications",
            "subcategory":"Radio Station",
            "type":"Services"
        }
    ],
    "sg:phone":"+32 9 348 24 20",
    "sg:postcode":"9160",
    "sg:province":"Oost-Vlaanderen",
    "sg:tags":[
        "control",
        "changing",
        "signal",
        "traffic"
    ],
    "wof:name":"Aqua-reno Industries B.v.b.a.",
    "wof:placetype":"venue"
},
  "geometry": {"coordinates":[4.0280399323,51.0934944153],"type":"Point"}
}