{
  "type": "Feature",
  "properties": {
    "addr:full":"De Tuintjes 18 Brugge West-Vlaanderen 8310",
    "addr:housenumber":"18",
    "addr:postcode":"8310",
    "addr:street":"De Tuintjes",
    "iso:country":"BE",
    "sg:address":"De Tuintjes 18",
    "sg:city":"Brugge",
    "sg:orig_category":"Boekhouders Verzekeringsmakelaars and experts",
    "sg:phone":"+32 50 35 14 09",
    "sg:postcode":"8310",
    "sg:province":"West-Vlaanderen",
    "wof:name":"Bureau Descheemaecker",
    "wof:placetype":"venue"
},
  "geometry": {"coordinates":[3.240087986,51.2208557129],"type":"Point"}
}