{
  "type": "Feature",
  "properties": {
    "addr:full":"Chauss\u00c9e D'enghien 384 Soignies Hainaut 7060",
    "addr:housenumber":"384",
    "addr:postcode":"7060",
    "addr:street":"Chausse\u0301E D'Enghien",
    "iso:country":"BE",
    "sg:address":"Chauss\u00c9e D'enghien 384",
    "sg:city":"Soignies",
    "sg:orig_category":"Dancings and bo\u00eetes de nuit",
    "sg:phone":"+32 67 33 26 09",
    "sg:postcode":"7060",
    "sg:province":"Hainaut",
    "wof:name":"La Turbine",
    "wof:placetype":"venue"
},
  "geometry": {"coordinates":[4.0549941063,50.6152572632],"type":"Point"}
}