{
  "type": "Feature",
  "properties": {
    "addr:full":"Honvelez 33a Gouvy (bovigny) Luxembourg 6671",
    "addr:housenumber":"33a",
    "addr:postcode":"6671",
    "addr:street":"Honvelez",
    "iso:country":"BE",
    "sg:address":"Honvelez 33a",
    "sg:city":"Gouvy (bovigny)",
    "sg:classifiers":[
        {
            "category":"Retail",
            "subcategory":"Auto Repair",
            "type":"Services"
        }
    ],
    "sg:phone":"+32 80 21 66 13",
    "sg:postcode":"6671",
    "sg:province":"Luxembourg",
    "sg:tags":[
        "garage"
    ],
    "wof:name":"Peters",
    "wof:placetype":"venue"
},
  "geometry": {"coordinates":[5.9206929207,50.2257118225],"type":"Point"}
}