{
  "type": "Feature",
  "properties": {
    "addr:full":"Avenue Montjoie 165 Ukkel/uccle Bruxelles-Capitale 1180",
    "addr:housenumber":"165",
    "addr:postcode":"1180",
    "addr:street":"Avenue Montjoie;/",
    "iso:country":"BE",
    "sg:address":"Avenue Montjoie 165",
    "sg:city":"Ukkel/uccle",
    "sg:orig_category":"Agences de publicit\u00e9",
    "sg:phone":"+32 2 349 34 11",
    "sg:postcode":"1180",
    "sg:province":"Bruxelles-Capitale",
    "wof:name":"Associate Holding",
    "wof:placetype":"venue"
},
  "geometry": {"coordinates":[4.3603029251,50.8094825745],"type":"Point"}
}