{
  "type": "Feature",
  "properties": {
    "iso:country":"BE",
    "sg:address":"Rue L\u00c9opold I 263",
    "sg:city":"Brussel/bruxelles",
    "sg:classifiers":[
        {
            "category":"Building & Trades",
            "subcategory":"Construction",
            "type":"Services"
        }
    ],
    "sg:phone":"+32 2 427 02 32",
    "sg:postcode":"1020",
    "sg:province":"Bruxelles-Capitale",
    "sg:tags":[
        "ventilation",
        "conditionn\u00e9",
        "air"
    ],
    "wof:name":"D.j.s.",
    "wof:placetype":"venue"
},
  "geometry": {"coordinates":[4.3392000198,50.8765296936],"type":"Point"}
}