{
  "type": "Feature",
  "properties": {
    "addr:full":"Dorpsstraat 47 Wellen Limburg 3830",
    "addr:housenumber":"47",
    "addr:postcode":"3830",
    "addr:street":"Dorpsstraat",
    "iso:country":"BE",
    "sg:address":"Dorpsstraat 47",
    "sg:city":"Wellen",
    "sg:classifiers":[
        {
            "category":"Fast Food",
            "type":"Food & Drink"
        }
    ],
    "sg:phone":"+32 12 74 40 29",
    "sg:postcode":"3830",
    "sg:province":"Limburg",
    "sg:tags":[
        "meeneem",
        "restaurant"
    ],
    "wof:name":"Frituur De Lekkerbek",
    "wof:placetype":"venue"
},
  "geometry": {"coordinates":[5.3317418098,50.8406181335],"type":"Point"}
}