{
  "type": "Feature",
  "properties": {
    "iso:country":"BE",
    "sg:address":"Blockhouse 14",
    "sg:city":"Thimister-clermont (clermont)",
    "sg:classifiers":[
        {
            "category":"Health Services",
            "subcategory":"Health Practitioner",
            "type":"Services"
        }
    ],
    "sg:phone":"+32 87 44 68 15",
    "sg:postcode":"4890",
    "sg:province":"Li\u00e8ge",
    "sg:tags":[
        "physiotherapist"
    ],
    "wof:name":"Renard Paul",
    "wof:placetype":"venue"
},
  "geometry": {"coordinates":[5.8725328445,50.6658058167],"type":"Point"}
}