{
  "type": "Feature",
  "properties": {
    "addr:full":"Theaterplein 1 Antwerpen (groot) Antwerpen 2000",
    "addr:housenumber":"1",
    "addr:postcode":"2000",
    "addr:street":"Theaterplein;Groot Antwerpen",
    "iso:country":"BE",
    "sg:address":"Theaterplein 1",
    "sg:city":"Antwerpen (groot)",
    "sg:orig_category":"Diverse zakelijke dienstverlening",
    "sg:phone":"+32 3 229 18 00",
    "sg:postcode":"2000",
    "sg:province":"Antwerpen",
    "wof:name":"Music Hall",
    "wof:placetype":"venue"
},
  "geometry": {"coordinates":[4.4090890884,51.2147140503],"type":"Point"}
}