{
  "type": "Feature",
  "properties": {
    "iso:country":"BE",
    "sg:address":"Fazantstraat 41",
    "sg:city":"Mol",
    "sg:orig_category":"Dansscholen",
    "sg:phone":"+32 14 31 06 31",
    "sg:postcode":"2400",
    "sg:province":"Antwerpen",
    "wof:name":"Dansliga Sportfederatie",
    "wof:placetype":"venue"
},
  "geometry": {"coordinates":[5.0769891739,51.1913375854],"type":"Point"}
}