{
  "type": "Feature",
  "properties": {
    "addr:full":"Rue Du Centenaire 1 Boussu Hainaut 7300",
    "addr:housenumber":"1",
    "addr:postcode":"7300",
    "addr:street":"Rue Du Centenaire",
    "iso:country":"BE",
    "sg:address":"Rue Du Centenaire 1",
    "sg:city":"Boussu",
    "sg:orig_category":"Postkantoren Verzekeringsmakelaars and experts",
    "sg:phone":"+32 65 78 42 07",
    "sg:postcode":"7300",
    "sg:province":"Hainaut",
    "wof:name":"La Poste",
    "wof:placetype":"venue"
},
  "geometry": {"coordinates":[3.7965350151,50.432723999],"type":"Point"}
}