{
  "type": "Feature",
  "properties": {
    "addr:full":"August Vermeylenlaan 15b5 Antwerpen Antwerpen 2050",
    "addr:housenumber":"15b5",
    "addr:postcode":"2050",
    "addr:street":"August Vermeylenlaan",
    "iso:country":"BE",
    "sg:address":"August Vermeylenlaan 15b5",
    "sg:city":"Antwerpen",
    "sg:orig_category":"Installation \u00e9lectrique r\u00e9sidentielle",
    "sg:phone":"+32 3 219 40 12",
    "sg:postcode":"2050",
    "sg:province":"Antwerpen",
    "wof:name":"Bijl",
    "wof:placetype":"venue"
},
  "geometry": {"coordinates":[4.3786802292,51.2308807373],"type":"Point"}
}