{
  "type": "Feature",
  "properties": {
    "iso:country":"BE",
    "sg:address":"Fernand Neuraystraat 23",
    "sg:city":"Elsene/ixelles",
    "sg:orig_category":"Meubelzaken, woning- and keukeninrichting",
    "sg:phone":"+32 2 343 19 00",
    "sg:postcode":"1050",
    "sg:province":"Bruxelles-Capitale",
    "wof:name":"Ex Nihilo",
    "wof:placetype":"venue"
},
  "geometry": {"coordinates":[4.3560090065,50.8208045959],"type":"Point"}
}