{
  "type": "Feature",
  "properties": {
    "iso:country":"BE",
    "sg:address":"Rijselsestraat 9",
    "sg:city":"Kortrijk",
    "sg:orig_category":"Herstelling horloges and juwelen Juwelen and horloges Verlichting and huishoudartikelen",
    "sg:phone":"+32 56 22 00 03",
    "sg:postcode":"8500",
    "sg:province":"West-Vlaanderen",
    "wof:name":"Jean Pierre D'hulst",
    "wof:placetype":"venue"
},
  "geometry": {"coordinates":[3.2642591,50.827747345],"type":"Point"}
}