{
  "type": "Feature",
  "properties": {
    "addr:full":"Turnhoutsebaan 464 Wijnegem Antwerpen 2110",
    "addr:housenumber":"464",
    "addr:postcode":"2110",
    "addr:street":"Turnhoutsebaan",
    "iso:country":"BE",
    "sg:address":"Turnhoutsebaan 464",
    "sg:city":"Wijnegem",
    "sg:classifiers":[
        {
            "category":"Health Services",
            "subcategory":"Health Practitioner",
            "type":"Services"
        }
    ],
    "sg:phone":"+32 3 354 34 94",
    "sg:postcode":"2110",
    "sg:province":"Antwerpen",
    "sg:tags":[
        "therapist",
        "speech"
    ],
    "wof:name":"Kompas (groepspraktijk Logopedie-psychologie)",
    "wof:placetype":"venue"
},
  "geometry": {"coordinates":[4.5272278786,51.2284622192],"type":"Point"}
}