{
  "type": "Feature",
  "properties": {
    "addr:full":"Rue Victor Delporte 21 Hensies (thulin) Hainaut 7350",
    "addr:housenumber":"21",
    "addr:postcode":"7350",
    "addr:street":"Rue Victor Delporte",
    "iso:country":"BE",
    "sg:address":"Rue Victor Delporte 21",
    "sg:city":"Hensies (thulin)",
    "sg:classifiers":[
        {
            "category":"Professional",
            "subcategory":"Testing Lab",
            "type":"Services"
        }
    ],
    "sg:phone":"+32 65 65 28 90",
    "sg:postcode":"7350",
    "sg:province":"Hainaut",
    "sg:tags":[
        "chemist"
    ],
    "wof:name":"Li\u00e9geois M",
    "wof:placetype":"venue"
},
  "geometry": {"coordinates":[3.73864007,50.427570343],"type":"Point"}
}