{
  "type": "Feature",
  "properties": {
    "addr:full":"5550 Vresse-sur-semois Namur 5550",
    "addr:postcode":"5550;5550",
    "iso:country":"BE",
    "sg:address":"5550",
    "sg:city":"Vresse-sur-semois",
    "sg:classifiers":[
        {
            "category":"Sports & Exercise",
            "subcategory":"Sports Center",
            "type":"Entertainment"
        }
    ],
    "sg:phone":"+32 61 50 12 22",
    "sg:postcode":"5550",
    "sg:province":"Namur",
    "sg:tags":[
        "terrain",
        "hors",
        "de",
        "installation",
        "sportifs"
    ],
    "wof:name":"Piste De Sugny",
    "wof:placetype":"venue"
},
  "geometry": {"coordinates":[4.9336900711,49.8729820251],"type":"Point"}
}