{
  "type": "Feature",
  "properties": {
    "iso:country":"BE",
    "sg:address":"Rozenstraat 1",
    "sg:city":"Riemst",
    "sg:orig_category":"Traitements param\u00e9dicaux. S\u00e9curit\u00e9 sociale",
    "sg:phone":"+32 12 45 37 10",
    "sg:postcode":"3770",
    "sg:province":"Limburg",
    "wof:name":"Liberale Mutualiteit",
    "wof:placetype":"venue"
},
  "geometry": {"coordinates":[5.6048660278,50.80884552],"type":"Point"}
}