{
  "type": "Feature",
  "properties": {
    "addr:full":"Chauss\u00c9e De Charleroi 385 Gembloux (groot) Namur 5030",
    "addr:housenumber":"385",
    "addr:postcode":"5030",
    "addr:street":"Chausse\u0301E De Charleroi;Groot Namur",
    "iso:country":"BE",
    "sg:address":"Chauss\u00c9e De Charleroi 385",
    "sg:city":"Gembloux (groot)",
    "sg:orig_category":"Baby- and kinderkleding Dameskledingzaken Herenkledingzaken",
    "sg:phone":"+32 81 63 45 45",
    "sg:postcode":"5030",
    "sg:province":"Namur",
    "wof:name":"Jbc Mode",
    "wof:placetype":"venue"
},
  "geometry": {"coordinates":[4.6829199791,50.5614318848],"type":"Point"}
}