{
  "type": "Feature",
  "properties": {
    "addr:full":"Tieltsteenweg 32 Oostrozebeke West-Vlaanderen 8780",
    "addr:housenumber":"32",
    "addr:postcode":"8780",
    "addr:street":"Tieltsteenweg",
    "iso:country":"BE",
    "sg:address":"Tieltsteenweg 32",
    "sg:city":"Oostrozebeke",
    "sg:orig_category":"Installatie van metalen schrijnwerk",
    "sg:phone":"+32 56 66 56 58",
    "sg:postcode":"8780",
    "sg:province":"West-Vlaanderen",
    "wof:name":"Declerck",
    "wof:placetype":"venue"
},
  "geometry": {"coordinates":[3.332611084,50.9268455505],"type":"Point"}
}