{
  "type": "Feature",
  "properties": {
    "addr:full":"Wingepark 15 Rotselaar Vlaams-Brabant 3110",
    "addr:housenumber":"15",
    "addr:postcode":"3110",
    "addr:street":"Wingepark",
    "iso:country":"BE",
    "sg:address":"Wingepark 15",
    "sg:city":"Rotselaar",
    "sg:classifiers":[
        {
            "category":"Wholesale",
            "subcategory":"Medical Equipment & Supplies",
            "type":"Manufacturing & Wholesale Goods"
        }
    ],
    "sg:phone":"+32 16 44 86 31",
    "sg:postcode":"3110",
    "sg:province":"Vlaams-Brabant",
    "sg:tags":[
        "instrument",
        "health",
        "-",
        "precision"
    ],
    "wof:name":"Anvarex Nv",
    "wof:placetype":"venue"
},
  "geometry": {"coordinates":[4.7451500893,50.9412307739],"type":"Point"}
}