{
  "type": "Feature",
  "properties": {
    "addr:full":"Larmont 3 Somme-leuze Namur 5377",
    "addr:housenumber":"3",
    "addr:postcode":"5377",
    "addr:street":"Larmont",
    "iso:country":"BE",
    "sg:address":"Larmont 3",
    "sg:city":"Somme-leuze",
    "sg:orig_category":"Diverse organisaties and verenigingen",
    "sg:phone":"+32 86 32 15 20",
    "sg:postcode":"5377",
    "sg:province":"Namur",
    "wof:name":"Missing Animals",
    "wof:placetype":"venue"
},
  "geometry": {"coordinates":[5.3765749931,50.3075828552],"type":"Point"}
}