{
  "type": "Feature",
  "properties": {
    "iso:country":"BE",
    "sg:address":"Avenue Des D\u00e9port\u00e9s 60",
    "sg:city":"Wavre",
    "sg:classifiers":[
        {
            "category":"Education",
            "subcategory":"Music School",
            "type":"Public Place"
        }
    ],
    "sg:phone":"+32 10 22 28 06",
    "sg:postcode":"1300",
    "sg:province":"Brabant Wallon",
    "sg:tags":[
        "-",
        "teacher",
        "private"
    ],
    "wof:name":"Acad\u00e9mie De Musique",
    "wof:placetype":"venue"
},
  "geometry": {"coordinates":[4.613948822,50.716293335],"type":"Point"}
}