{
  "type": "Feature",
  "properties": {
    "addr:full":"Mezenstraat 92 Bertem Vlaams-Brabant 3061",
    "addr:housenumber":"92",
    "addr:postcode":"3061",
    "addr:street":"Mezenstraat",
    "iso:country":"BE",
    "sg:address":"Mezenstraat 92",
    "sg:city":"Bertem",
    "sg:orig_category":"Rev\u00eatements pour sols and murs. Peinture",
    "sg:phone":"+32 2 767 52 60",
    "sg:postcode":"3061",
    "sg:province":"Vlaams-Brabant",
    "wof:name":"Marcel Dewals",
    "wof:placetype":"venue"
},
  "geometry": {"coordinates":[4.5806899071,50.8510017395],"type":"Point"}
}