{
  "type": "Feature",
  "properties": {
    "iso:country":"BE",
    "sg:address":"Ettelgemstraat 11",
    "sg:city":"Jabbeke",
    "sg:orig_category":"Installation de menuiserie en bois and plastique. Installation de menuiserie m\u00e9tallique. Mat\u00e9riaux d",
    "sg:phone":"+32 50 81 19 31",
    "sg:postcode":"8490",
    "sg:province":"West-Vlaanderen",
    "wof:name":"Eric Cappelle",
    "wof:placetype":"venue"
},
  "geometry": {"coordinates":[3.0810289383,51.179725647],"type":"Point"}
}