{
  "type": "Feature",
  "properties": {
    "addr:full":"Proosdijstraat 50 Oostkamp (hertsberge) West-Vlaanderen 8020",
    "addr:housenumber":"50",
    "addr:postcode":"8020",
    "addr:street":"Proosdijstraat",
    "iso:country":"BE",
    "sg:address":"Proosdijstraat 50",
    "sg:city":"Oostkamp (hertsberge)",
    "sg:classifiers":[
        {
            "category":"Insurance",
            "subcategory":"Insurance Agent",
            "type":"Services"
        }
    ],
    "sg:phone":"+32 50 27 95 19",
    "sg:postcode":"8020",
    "sg:province":"West-Vlaanderen",
    "sg:tags":[
        "broker"
    ],
    "wof:name":"Bollaert E",
    "wof:placetype":"venue"
},
  "geometry": {"coordinates":[3.2652289867,51.106098175],"type":"Point"}
}