{
  "type": "Feature",
  "properties": {
    "addr:full":"Rue Du Coll\u00e8ge 9 Charleroi Hainaut 6000",
    "addr:housenumber":"9",
    "addr:postcode":"6000",
    "addr:street":"Rue Du Colle\u0300Ge;Hainaut",
    "iso:country":"BE",
    "sg:address":"Rue Du Coll\u00e8ge 9",
    "sg:city":"Charleroi",
    "sg:classifiers":[
        {
            "category":"Arts & Performance",
            "subcategory":"Arts Center",
            "type":"Entertainment"
        }
    ],
    "sg:phone":"+32 71 32 21 37",
    "sg:postcode":"6000",
    "sg:province":"Hainaut",
    "sg:tags":[
        "slide"
    ],
    "wof:name":"Clic Clac 1h",
    "wof:placetype":"venue"
},
  "geometry": {"coordinates":[4.4397258759,50.4072799683],"type":"Point"}
}