{
  "type": "Feature",
  "properties": {
    "addr:full":"Boechtstraat 27 Meise Vlaams-Brabant 1860",
    "addr:housenumber":"27",
    "addr:postcode":"1860",
    "addr:street":"Boechtstraat",
    "iso:country":"BE",
    "sg:address":"Boechtstraat 27",
    "sg:city":"Meise",
    "sg:orig_category":"Banques and organismes de cr\u00e9dit",
    "sg:phone":"+32 2 269 76 82",
    "sg:postcode":"1860",
    "sg:province":"Vlaams-Brabant",
    "wof:name":"Bacob",
    "wof:placetype":"venue"
},
  "geometry": {"coordinates":[4.3288822174,50.9349822998],"type":"Point"}
}