{
  "type": "Feature",
  "properties": {
    "iso:country":"BE",
    "sg:address":"Sur Les Roches 39",
    "sg:city":"Tellin",
    "sg:orig_category":"Jardinage",
    "sg:phone":"+32 84 38 89 25",
    "sg:postcode":"6927",
    "sg:province":"Luxembourg",
    "wof:name":"Lambert S.",
    "wof:placetype":"venue"
},
  "geometry": {"coordinates":[5.1766428947,50.081905365],"type":"Point"}
}