{
  "type": "Feature",
  "properties": {
    "addr:full":"Rue Des Alli\u00c9s 33 Frameries Hainaut 7080",
    "addr:housenumber":"33",
    "addr:postcode":"7080",
    "addr:street":"Rue Des Allie\u0301S",
    "iso:country":"BE",
    "sg:address":"Rue Des Alli\u00c9s 33",
    "sg:city":"Frameries",
    "sg:orig_category":"Banken and kredietinstellingen",
    "sg:phone":"+32 65 67 20 92",
    "sg:postcode":"7080",
    "sg:province":"Hainaut",
    "wof:name":"Fortis",
    "wof:placetype":"venue"
},
  "geometry": {"coordinates":[3.8945980072,50.4099617004],"type":"Point"}
}