{
  "type": "Feature",
  "properties": {
    "iso:country":"BE",
    "sg:address":"Hovesteenweg 156",
    "sg:city":"Boechout",
    "sg:orig_category":"Werk and personeelsselectie",
    "sg:phone":"+32 3 454 15 38",
    "sg:postcode":"2530",
    "sg:province":"Antwerpen",
    "wof:name":"V.s.a.",
    "wof:placetype":"venue"
},
  "geometry": {"coordinates":[4.4822998047,51.156539917],"type":"Point"}
}