{
  "type": "Feature",
  "properties": {
    "addr:full":"Rue Neuve 5 Tournai Hainaut 7500",
    "addr:housenumber":"5",
    "addr:postcode":"7500",
    "addr:street":"Rue Neuve",
    "iso:country":"BE",
    "sg:address":"Rue Neuve 5",
    "sg:city":"Tournai",
    "sg:orig_category":"Enseignement maternel and primaire",
    "sg:phone":"+32 69 64 92 11",
    "sg:postcode":"7500",
    "sg:province":"Hainaut",
    "wof:name":"Ecole Primaire Libre",
    "wof:placetype":"venue"
},
  "geometry": {"coordinates":[3.3002619743,50.6236343384],"type":"Point"}
}