{
  "type": "Feature",
  "properties": {
    "iso:country":"BE",
    "sg:address":"Chauss\u00c9e De Dinant 379",
    "sg:city":"Namur",
    "sg:classifiers":[
        {
            "category":"Cafe",
            "type":"Food & Drink"
        }
    ],
    "sg:phone":"+32 81 22 41 06",
    "sg:postcode":"5000",
    "sg:province":"Namur",
    "sg:tags":[
        "caf\u00e9s"
    ],
    "wof:name":"Luc Gonay",
    "wof:placetype":"venue"
},
  "geometry": {"coordinates":[4.8601789474,50.4388694763],"type":"Point"}
}