{
  "type": "Feature",
  "properties": {
    "iso:country":"BE",
    "sg:address":"Rue Aux Roses 16",
    "sg:city":"Leglise",
    "sg:orig_category":"Electrom\u00e9nager, t\u00e9l\u00e9visions and radios",
    "sg:phone":"+32 61 25 52 78",
    "sg:postcode":"6860",
    "sg:province":"Luxembourg",
    "wof:name":"Albert Pulfer",
    "wof:placetype":"venue"
},
  "geometry": {"coordinates":[5.5416898727,49.8505554199],"type":"Point"}
}