{
  "type": "Feature",
  "properties": {
    "addr:full":"Avenue Des Aub\u00c9pines 14 Wavre Brabant Wallon 1301",
    "addr:housenumber":"14;1301",
    "addr:street":"Avenue Des Aube\u0301Pines",
    "iso:country":"BE",
    "sg:address":"Avenue Des Aub\u00c9pines 14",
    "sg:city":"Wavre",
    "sg:orig_category":"M\u00e9decins and sp\u00e9cialistes",
    "sg:phone":"+32 10 43 90 86",
    "sg:postcode":"1301",
    "sg:province":"Brabant Wallon",
    "wof:name":"Emmanuel Rombaut",
    "wof:placetype":"venue"
},
  "geometry": {"coordinates":[4.608068943,50.7032546997],"type":"Point"}
}