{
  "type": "Feature",
  "properties": {
    "addr:full":"Fazantenlaan 26 Bredene West-Vlaanderen 8450",
    "addr:housenumber":"26",
    "addr:postcode":"8450",
    "addr:street":"Fazantenlaan",
    "iso:country":"BE",
    "sg:address":"Fazantenlaan 26",
    "sg:city":"Bredene",
    "sg:classifiers":[
        {
            "category":"Insurance",
            "subcategory":"Insurance Agent",
            "type":"Services"
        }
    ],
    "sg:phone":"+32 59 32 49 34",
    "sg:postcode":"8450",
    "sg:province":"West-Vlaanderen",
    "sg:tags":[
        "verzekeringsmakelaars",
        "expert"
    ],
    "wof:name":"Antoon Nolf",
    "wof:placetype":"venue"
},
  "geometry": {"coordinates":[2.9530589581,51.2436599731],"type":"Point"}
}