{
  "type": "Feature",
  "properties": {
    "addr:full":"Kattestraat 8 Sint-agatha-berchem/berchem-sainte-agathe Bruxelles-Capitale 1082",
    "addr:housenumber":"8",
    "addr:postcode":"1082",
    "addr:street":"Kattestraat",
    "iso:country":"BE",
    "sg:address":"Kattestraat 8",
    "sg:city":"Sint-agatha-berchem/berchem-sainte-agathe",
    "sg:orig_category":"Artsen and specialisten",
    "sg:phone":"+32 2 468 54 02",
    "sg:postcode":"1082",
    "sg:province":"Bruxelles-Capitale",
    "wof:name":"D. Moreau",
    "wof:placetype":"venue"
},
  "geometry": {"coordinates":[4.2811288834,50.8665161133],"type":"Point"}
}