{
  "type": "Feature",
  "properties": {
    "addr:full":"Rijselstraat 294 Menen West-Vlaanderen 8930",
    "addr:housenumber":"294",
    "addr:postcode":"8930",
    "addr:street":"Rijselstraat",
    "iso:country":"BE",
    "sg:address":"Rijselstraat 294",
    "sg:city":"Menen",
    "sg:classifiers":[
        {
            "category":"Food & Beverages",
            "subcategory":"Chocolate",
            "type":"Retail Goods"
        }
    ],
    "sg:phone":"+32 56 53 09 70",
    "sg:postcode":"8930",
    "sg:province":"West-Vlaanderen",
    "sg:tags":[
        "confectionery",
        "-"
    ],
    "wof:name":"Candy-house",
    "wof:placetype":"venue"
},
  "geometry": {"coordinates":[3.1270620823,50.7871055603],"type":"Point"}
}