{
  "type": "Feature",
  "properties": {
    "addr:full":"Ter Voort Westerlo Antwerpen 2260",
    "addr:postcode":"2260",
    "addr:street":"Ter Voort",
    "iso:country":"BE",
    "sg:address":"Ter Voort",
    "sg:city":"Westerlo",
    "sg:classifiers":[
        {
            "category":"Fast Food",
            "type":"Food & Drink"
        }
    ],
    "sg:phone":"+32 14 26 50 75",
    "sg:postcode":"2260",
    "sg:province":"Antwerpen",
    "sg:tags":[
        "fried",
        "stand",
        "potato"
    ],
    "wof:name":"Nief Plenke ('t)",
    "wof:placetype":"venue"
},
  "geometry": {"coordinates":[4.8447399139,51.1206665039],"type":"Point"}
}