{
  "type": "Feature",
  "properties": {
    "addr:full":"Louis De Naeyerplein 18 Willebroek Antwerpen 2830",
    "addr:housenumber":"18",
    "addr:postcode":"2830",
    "addr:street":"Louis De Naeyerplein",
    "iso:country":"BE",
    "sg:address":"Louis De Naeyerplein 18",
    "sg:city":"Willebroek",
    "sg:classifiers":[
        {
            "category":"Insurance",
            "subcategory":"Life Insurance",
            "type":"Services"
        }
    ],
    "sg:phone":"+32 3 886 85 28",
    "sg:postcode":"2830",
    "sg:province":"Antwerpen",
    "sg:tags":[
        "assurance"
    ],
    "wof:name":"Portugaels - Imcover",
    "wof:placetype":"venue"
},
  "geometry": {"coordinates":[4.3613200188,51.0611495972],"type":"Point"}
}