{
  "type": "Feature",
  "properties": {
    "addr:full":"Chauss\u00e9e De Waterloo 496 Bruxelles (ixelles) Bruxelles-Capitale 1050",
    "addr:housenumber":"496",
    "addr:postcode":"1050",
    "addr:street":"Chausse\u0301E De Waterloo",
    "iso:country":"BE",
    "sg:address":"Chauss\u00e9e De Waterloo 496",
    "sg:city":"Bruxelles (ixelles)",
    "sg:classifiers":[
        {
            "category":"Home & Garden",
            "subcategory":"Home Furnishings",
            "type":"Retail Goods"
        }
    ],
    "sg:phone":"+32 2 538 24 82",
    "sg:postcode":"1050",
    "sg:province":"Bruxelles-Capitale",
    "sg:tags":[
        "lighting",
        "fixture",
        "-"
    ],
    "wof:name":"Courant Qui Passe (le)",
    "wof:placetype":"venue"
},
  "geometry": {"coordinates":[4.3590450287,50.8204879761],"type":"Point"}
}