{
  "type": "Feature",
  "properties": {
    "addr:full":"Graafjansdijk 11 Sint-laureins Oost-Vlaanderen 9982",
    "addr:housenumber":"11",
    "addr:postcode":"9982",
    "addr:street":"Graafjansdijk",
    "iso:country":"BE",
    "sg:address":"Graafjansdijk 11",
    "sg:city":"Sint-laureins",
    "sg:orig_category":"Eleveurs de bovins",
    "sg:phone":"+32 9 379 84 38",
    "sg:postcode":"9982",
    "sg:province":"Oost-Vlaanderen",
    "wof:name":"Jacques Serrarens",
    "wof:placetype":"venue"
},
  "geometry": {"coordinates":[3.5809369087,51.2488021851],"type":"Point"}
}