{
  "type": "Feature",
  "properties": {
    "iso:country":"BE",
    "sg:address":"Mechelsesteenweg 492",
    "sg:city":"Zaventem",
    "sg:orig_category":"Journaux. Tabac. Blanchisseries and teintureries",
    "sg:phone":"+32 2 759 50 83",
    "sg:postcode":"1930",
    "sg:province":"Vlaams-Brabant",
    "wof:name":"Kennes",
    "wof:placetype":"venue"
},
  "geometry": {"coordinates":[4.5067667961,50.8799591064],"type":"Point"}
}