{
  "type": "Feature",
  "properties": {
    "addr:full":"Massinweg 16 Hasselt Limburg 3511",
    "addr:housenumber":"16",
    "addr:postcode":"3511",
    "addr:street":"Massinweg",
    "iso:country":"BE",
    "sg:address":"Massinweg 16",
    "sg:city":"Hasselt",
    "sg:orig_category":"Fietsen Watersport-, Sport- and Kampeerbenodigdheden Verhuur",
    "sg:phone":"+32 11 25 44 72",
    "sg:postcode":"3511",
    "sg:province":"Limburg",
    "wof:name":"Fietsenherstelling Deroy",
    "wof:placetype":"venue"
},
  "geometry": {"coordinates":[5.2849321365,50.9726524353],"type":"Point"}
}