{
  "type": "Feature",
  "properties": {
    "iso:country":"BE",
    "sg:address":"Avenue Lavoisier 31",
    "sg:city":"Wavre",
    "sg:orig_category":"Advocaten and juridische adviseurs",
    "sg:phone":"+32 10 23 39 85",
    "sg:postcode":"1300",
    "sg:province":"Brabant Wallon",
    "wof:name":"J.m. Leclere",
    "wof:placetype":"venue"
},
  "geometry": {"coordinates":[4.5878300667,50.7362785339],"type":"Point"}
}