{
  "type": "Feature",
  "properties": {
    "addr:full":"Avenue Du Castillon 52 Chastre Brabant Wallon 1450",
    "addr:housenumber":"52",
    "addr:postcode":"1450",
    "addr:street":"Avenue Du Castillon",
    "iso:country":"BE",
    "sg:address":"Avenue Du Castillon 52",
    "sg:city":"Chastre",
    "sg:orig_category":"ACCOUNTANTS Beheer onroerend goed",
    "sg:phone":"+32 10 65 85 16",
    "sg:postcode":"1450",
    "sg:province":"Brabant Wallon",
    "wof:name":"Christian Pirsoul",
    "wof:placetype":"venue"
},
  "geometry": {"coordinates":[4.6454758644,50.6096458435],"type":"Point"}
}