{
  "type": "Feature",
  "properties": {
    "iso:country":"BE",
    "sg:address":"Rue Belle Vue 14",
    "sg:city":"Mettet",
    "sg:orig_category":"Installation de menuiserie m\u00e9tallique. Travaux de pl\u00e2trage",
    "sg:phone":"+32 71 72 88 24",
    "sg:postcode":"5640",
    "sg:province":"Namur",
    "wof:name":"Rene Marchand",
    "wof:placetype":"venue"
},
  "geometry": {"coordinates":[4.617087841,50.3466644287],"type":"Point"}
}