{
  "type": "Feature",
  "properties": {
    "addr:full":"Stationsstraat 143 Niel Antwerpen 2845",
    "addr:housenumber":"143",
    "addr:postcode":"2845",
    "addr:street":"Stationsstraat",
    "iso:country":"BE",
    "sg:address":"Stationsstraat 143",
    "sg:city":"Niel",
    "sg:classifiers":[
        {
            "category":"Bars & Pubs",
            "type":"Food & Drink"
        }
    ],
    "sg:phone":"+32 3 844 91 53",
    "sg:postcode":"2845",
    "sg:province":"Antwerpen",
    "sg:tags":[
        "tavern"
    ],
    "wof:name":"D'a Statie",
    "wof:placetype":"venue"
},
  "geometry": {"coordinates":[4.3381958008,51.1116905212],"type":"Point"}
}