{
  "type": "Feature",
  "properties": {
    "addr:full":"Rue Du Marquisat 193 Attert (thiaumont) Luxembourg 6717",
    "addr:housenumber":"193",
    "addr:postcode":"6717",
    "addr:street":"Rue Du Marquisat",
    "iso:country":"BE",
    "sg:address":"Rue Du Marquisat 193",
    "sg:city":"Attert (thiaumont)",
    "sg:classifiers":[
        {
            "category":"Personal",
            "subcategory":"Beauty Salon",
            "type":"Services"
        }
    ],
    "sg:phone":"+32 63 22 33 66",
    "sg:postcode":"6717",
    "sg:province":"Luxembourg",
    "sg:tags":[
        "lady",
        "-",
        "hairdressing"
    ],
    "wof:name":"Artisanat Coiffure",
    "wof:placetype":"venue"
},
  "geometry": {"coordinates":[5.7888741493,49.7506217957],"type":"Point"}
}