{
  "type": "Feature",
  "properties": {
    "addr:full":"Egemsebinnenweg 21 Pittem West-Vlaanderen 8740",
    "addr:housenumber":"21",
    "addr:postcode":"8740",
    "addr:street":"Egemsebinnenweg",
    "iso:country":"BE",
    "sg:address":"Egemsebinnenweg 21",
    "sg:city":"Pittem",
    "sg:orig_category":"Producteurs de l\u00e9gumes",
    "sg:phone":"+32 51 46 67 63",
    "sg:postcode":"8740",
    "sg:province":"West-Vlaanderen",
    "wof:name":"Wim Cool",
    "wof:placetype":"venue"
},
  "geometry": {"coordinates":[3.254997015,51.00157547],"type":"Point"}
}