{
  "type": "Feature",
  "properties": {
    "iso:country":"BE",
    "sg:address":"Provooststraat 112",
    "sg:city":"Elsene/ixelles",
    "sg:orig_category":"Fotografen and fotostudio's",
    "sg:phone":"+32 2 344 54 04",
    "sg:postcode":"1050",
    "sg:province":"Bruxelles-Capitale",
    "wof:name":"Studio Blue Eye",
    "wof:placetype":"venue"
},
  "geometry": {"coordinates":[4.3619298935,50.8207778931],"type":"Point"}
}