{
  "type": "Feature",
  "properties": {
    "iso:country":"BE",
    "sg:address":"Rue De Roulers 53",
    "sg:city":"Mouscron",
    "sg:classifiers":[
        {
            "category":"Banks & Credit Unions",
            "subcategory":"Financial Services",
            "type":"Services"
        }
    ],
    "sg:phone":"+32 56 84 28 24",
    "sg:postcode":"7700",
    "sg:province":"Hainaut",
    "sg:tags":[
        "financing"
    ],
    "wof:name":"Investment Consulting Management",
    "wof:placetype":"venue"
},
  "geometry": {"coordinates":[3.2101299763,50.7473182678],"type":"Point"}
}