{
  "type": "Feature",
  "properties": {
    "iso:country":"BE",
    "sg:address":"Rue Du Petit Audenarde 2",
    "sg:city":"Mouscron (herseaux)",
    "sg:classifiers":[
        {
            "category":"Bakery",
            "type":"Food & Drink"
        }
    ],
    "sg:phone":"+32 56 33 21 30",
    "sg:postcode":"7712",
    "sg:province":"Hainaut",
    "sg:tags":[
        "confectioner",
        "baker"
    ],
    "wof:name":"Kriss",
    "wof:placetype":"venue"
},
  "geometry": {"coordinates":[3.236978054,50.7119865417],"type":"Point"}
}