{
  "type": "Feature",
  "properties": {
    "addr:full":"Rue Bellaire 36a Neupr\u00e9 (rotheux-rimi\u00e8re) Li\u00e8ge 4120",
    "addr:housenumber":"36a",
    "addr:postcode":"4120",
    "addr:street":"Rue Bellaire;Rotheux-Rimie\u0300Re",
    "iso:country":"BE",
    "sg:address":"Rue Bellaire 36a",
    "sg:city":"Neupr\u00e9 (rotheux-rimi\u00e8re)",
    "sg:classifiers":[
        {
            "category":"Professional",
            "subcategory":"Computer Services",
            "type":"Services"
        }
    ],
    "sg:phone":"+32 4 371 31 26",
    "sg:postcode":"4120",
    "sg:province":"Li\u00e8ge",
    "sg:tags":[
        "-",
        "processing",
        "data"
    ],
    "wof:name":"P.c.s. Informatique",
    "wof:placetype":"venue"
},
  "geometry": {"coordinates":[5.474383831,50.5384635925],"type":"Point"}
}