{
  "type": "Feature",
  "properties": {
    "addr:full":"Tombergstraat 7 Lennik Vlaams-Brabant 1750",
    "addr:housenumber":"7;1750",
    "addr:street":"Tombergstraat;Vlaams-Brabant",
    "iso:country":"BE",
    "sg:address":"Tombergstraat 7",
    "sg:city":"Lennik",
    "sg:orig_category":"Architecten",
    "sg:phone":"+32 2 532 54 78",
    "sg:postcode":"1750",
    "sg:province":"Vlaams-Brabant",
    "wof:name":"Anne-laure Masure",
    "wof:placetype":"venue"
},
  "geometry": {"coordinates":[4.1611380577,50.8226890564],"type":"Point"}
}