{
  "type": "Feature",
  "properties": {
    "addr:full":"Rue De Bruxelles 56 Namur Namur 5000",
    "addr:housenumber":"56",
    "addr:postcode":"5000",
    "addr:street":"Rue De Bruxelles",
    "iso:country":"BE",
    "sg:address":"Rue De Bruxelles 56",
    "sg:city":"Namur",
    "sg:orig_category":"Journaux. Fournitures de bureau. Tabac",
    "sg:phone":"+32 81 22 72 57",
    "sg:postcode":"5000",
    "sg:province":"Namur",
    "wof:name":"Librairie Arc-en-ciel",
    "wof:placetype":"venue"
},
  "geometry": {"coordinates":[4.8610839844,50.46616745],"type":"Point"}
}