{
  "type": "Feature",
  "properties": {
    "addr:full":"Place Jos\u00c9ph. Charlotte 40 Namur Namur 5100",
    "addr:housenumber":"40",
    "addr:postcode":"5100",
    "addr:street":"Place Jose\u0301Ph Charlotte",
    "iso:country":"BE",
    "sg:address":"Place Jos\u00c9ph. Charlotte 40",
    "sg:city":"Namur",
    "sg:orig_category":"Centres de relaxation and bien-\u00eatre",
    "sg:phone":"+32 81 30 79 78",
    "sg:postcode":"5100",
    "sg:province":"Namur",
    "wof:name":"Solarium Pause-vitale Sun",
    "wof:placetype":"venue"
},
  "geometry": {"coordinates":[4.8713750839,50.4566345215],"type":"Point"}
}