{
  "type": "Feature",
  "properties": {
    "addr:full":"Bruulstraat 28 Kortenberg (erps-kwerps) Vlaams-Brabant 3071",
    "addr:housenumber":"28",
    "addr:postcode":"3071",
    "addr:street":"Bruulstraat",
    "iso:country":"BE",
    "sg:address":"Bruulstraat 28",
    "sg:city":"Kortenberg (erps-kwerps)",
    "sg:classifiers":[
        {
            "category":"Health Services",
            "subcategory":"Health Practitioner",
            "type":"Services"
        }
    ],
    "sg:phone":"+32 2 759 40 41",
    "sg:postcode":"3071",
    "sg:province":"Vlaams-Brabant",
    "sg:tags":[
        "physiotherapist"
    ],
    "wof:name":"Vandegaer K",
    "wof:placetype":"venue"
},
  "geometry": {"coordinates":[4.5849480629,50.9078369141],"type":"Point"}
}