{
  "type": "Feature",
  "properties": {
    "addr:full":"Sijselestraat 3 Beernem West-Vlaanderen 8730",
    "addr:housenumber":"3",
    "addr:postcode":"8730",
    "addr:street":"Sijselestraat",
    "iso:country":"BE",
    "sg:address":"Sijselestraat 3",
    "sg:city":"Beernem",
    "sg:classifiers":[
        {
            "category":"Cafe",
            "type":"Food & Drink"
        }
    ],
    "sg:phone":"+32 50 78 08 43",
    "sg:postcode":"8730",
    "sg:province":"West-Vlaanderen",
    "sg:tags":[
        "caf\u00e9s"
    ],
    "wof:name":"Suzanne Riemaeker",
    "wof:placetype":"venue"
},
  "geometry": {"coordinates":[3.3387439251,51.1703491211],"type":"Point"}
}