{
  "type": "Feature",
  "properties": {
    "addr:full":"Kleine Veldstraat 61 Staden West-Vlaanderen 8840",
    "addr:housenumber":"61",
    "addr:postcode":"8840",
    "addr:street":"Kleine Veldstraat",
    "iso:country":"BE",
    "sg:address":"Kleine Veldstraat 61",
    "sg:city":"Staden",
    "sg:orig_category":"Groententeelt Varkenskwekers",
    "sg:phone":"+32 51 70 05 87",
    "sg:postcode":"8840",
    "sg:province":"West-Vlaanderen",
    "wof:name":"Norbert Deleu",
    "wof:placetype":"venue"
},
  "geometry": {"coordinates":[3.0157589912,50.9450035095],"type":"Point"}
}