{
  "type": "Feature",
  "properties": {
    "iso:country":"BE",
    "sg:address":"Burgpotiaulaan 87",
    "sg:city":"Dendermonde",
    "sg:orig_category":"Motos",
    "sg:phone":"+32 52 20 19 36",
    "sg:postcode":"9200",
    "sg:province":"Oost-Vlaanderen",
    "wof:name":"Frank Fietsen En Scooters",
    "wof:placetype":"venue"
},
  "geometry": {"coordinates":[4.0983099937,51.0315208435],"type":"Point"}
}