{
  "type": "Feature",
  "properties": {
    "iso:country":"BE",
    "sg:address":"Moortselestraat 20",
    "sg:city":"Oosterzele",
    "sg:orig_category":"Installation de menuiserie en bois and plastique",
    "sg:phone":"+32 9 362 63 42",
    "sg:postcode":"9860",
    "sg:province":"Oost-Vlaanderen",
    "wof:name":"Jodie",
    "wof:placetype":"venue"
},
  "geometry": {"coordinates":[3.7801311016,50.9550704956],"type":"Point"}
}