{
  "type": "Feature",
  "properties": {
    "addr:full":"Kalverveld 8-12 Antwerpen (borgerhout) Antwerpen 2140",
    "addr:housenumber":"8-12",
    "addr:postcode":"2140",
    "iso:country":"BE",
    "sg:address":"Kalverveld 8-12",
    "sg:city":"Antwerpen (borgerhout)",
    "sg:classifiers":[
        {
            "category":"Retail",
            "subcategory":"Event Space",
            "type":"Services"
        }
    ],
    "sg:phone":"+32 3 217 40 40",
    "sg:postcode":"2140",
    "sg:province":"Antwerpen",
    "sg:tags":[
        "rental",
        "-",
        "hall"
    ],
    "wof:name":"City Inn",
    "wof:placetype":"venue"
},
  "geometry": {"coordinates":[4.4332199097,51.2137565613],"type":"Point"}
}