{
  "type": "Feature",
  "properties": {
    "addr:full":"Jan Van Ruusbroecstraat 5 Roeselare West-Vlaanderen 8800",
    "addr:housenumber":"5",
    "addr:postcode":"8800",
    "addr:street":"Jan Van Ruusbroecstraat",
    "iso:country":"BE",
    "sg:address":"Jan Van Ruusbroecstraat 5",
    "sg:city":"Roeselare",
    "sg:orig_category":"Diverse bedrijfsbeheeradviesbureaus",
    "sg:phone":"+32 51 20 44 37",
    "sg:postcode":"8800",
    "sg:province":"West-Vlaanderen",
    "wof:name":"T.c.m.c.",
    "wof:placetype":"venue"
},
  "geometry": {"coordinates":[3.13053298,50.9628601074],"type":"Point"}
}