{
  "type": "Feature",
  "properties": {
    "iso:country":"BE",
    "sg:address":"Troonstraat 226",
    "sg:city":"Elsene/ixelles",
    "sg:orig_category":"Zalen voor culturele evenementen",
    "sg:phone":"+32 2 644 09 25",
    "sg:postcode":"1050",
    "sg:province":"Bruxelles-Capitale",
    "wof:name":"Th\u00c9\u00c2t. Commedia All'impr.",
    "wof:placetype":"venue"
},
  "geometry": {"coordinates":[4.3798799515,50.8206710815],"type":"Point"}
}