{
  "type": "Feature",
  "properties": {
    "addr:full":"Rue De L'acad\u00c9mie 15 Ath Hainaut 7810",
    "addr:housenumber":"15",
    "addr:postcode":"7810",
    "addr:street":"Rue De L'Acade \u0301Mie",
    "iso:country":"BE",
    "sg:address":"Rue De L'acad\u00c9mie 15",
    "sg:city":"Ath",
    "sg:orig_category":"Assurances. Bureaux de poste",
    "sg:phone":"+32 68 28 18 05",
    "sg:postcode":"7810",
    "sg:province":"Hainaut",
    "wof:name":"La Poste",
    "wof:placetype":"venue"
},
  "geometry": {"coordinates":[3.8049149513,50.6159896851],"type":"Point"}
}