{
  "type": "Feature",
  "properties": {
    "addr:full":"Kleppestraat 18 Moorslede West-Vlaanderen 8890",
    "addr:housenumber":"18",
    "addr:postcode":"8890",
    "addr:street":"Kleppestraat",
    "iso:country":"BE",
    "sg:address":"Kleppestraat 18",
    "sg:city":"Moorslede",
    "sg:orig_category":"Beautyfarms, relaxatie and lichamelijk welzijn Schoonheidssalons",
    "sg:phone":"+32 56 50 36 37",
    "sg:postcode":"8890",
    "sg:province":"West-Vlaanderen",
    "wof:name":"Instituut Conny",
    "wof:placetype":"venue"
},
  "geometry": {"coordinates":[3.0997240543,50.8517150879],"type":"Point"}
}