{
  "type": "Feature",
  "properties": {
    "iso:country":"BE",
    "sg:address":"Iepenstraat 94",
    "sg:city":"Sint-niklaas",
    "sg:orig_category":"Boekhouders",
    "sg:phone":"+32 3 777 78 83",
    "sg:postcode":"9100",
    "sg:province":"Oost-Vlaanderen",
    "wof:name":"Christiane Van Mullem",
    "wof:placetype":"venue"
},
  "geometry": {"coordinates":[4.1548390388,51.1793670654],"type":"Point"}
}