{
  "type": "Feature",
  "properties": {
    "iso:country":"BE",
    "sg:address":"Almaplein 4b3",
    "sg:city":"Sint-lambrechts-woluwe/woluwe-saint-lambert",
    "sg:orig_category":"Artsen and specialisten",
    "sg:phone":"+32 2 772 63 25",
    "sg:postcode":"1200",
    "sg:province":"Bruxelles-Capitale",
    "wof:name":"Pascale Holef",
    "wof:placetype":"venue"
},
  "geometry": {"coordinates":[4.4531497955,50.8495864868],"type":"Point"}
}