{
  "type": "Feature",
  "properties": {
    "addr:full":"Avenue Astrid 2 Charleroi Hainaut 6032",
    "addr:housenumber":"2",
    "addr:postcode":"6032",
    "addr:street":"Avenue Astrid;Hainaut",
    "iso:country":"BE",
    "sg:address":"Avenue Astrid 2",
    "sg:city":"Charleroi",
    "sg:orig_category":"V\u00e9hicules automobiles",
    "sg:phone":"+32 71 43 66 88",
    "sg:postcode":"6032",
    "sg:province":"Hainaut",
    "wof:name":"Autocass Trapletti",
    "wof:placetype":"venue"
},
  "geometry": {"coordinates":[4.4256300926,50.3992347717],"type":"Point"}
}