{
  "type": "Feature",
  "properties": {
    "iso:country":"BE",
    "sg:address":"Rue De L'eglise 2",
    "sg:city":"Remicourt",
    "sg:classifiers":[
        {
            "category":"Restaurant",
            "type":"Food & Drink"
        }
    ],
    "sg:phone":"+32 4 250 60 90",
    "sg:postcode":"4350",
    "sg:province":"Li\u00e8ge",
    "wof:name":"Piccolo Teatro",
    "wof:placetype":"venue"
},
  "geometry": {"coordinates":[5.3722858429,50.6839866638],"type":"Point"}
}