{
  "type": "Feature",
  "properties": {
    "iso:country":"BE",
    "sg:address":"Van Wesenbekestraat 75",
    "sg:city":"Antwerpen",
    "sg:classifiers":[
        {
            "category":"Travel",
            "subcategory":"Travel Agent",
            "type":"Entertainment"
        }
    ],
    "sg:phone":"+32 3 231 08 58",
    "sg:postcode":"2060",
    "sg:province":"Antwerpen",
    "sg:tags":[
        "agency"
    ],
    "wof:name":"Intimex Travel Service",
    "wof:placetype":"venue"
},
  "geometry": {"coordinates":[4.4206361771,51.2210845947],"type":"Point"}
}