{
  "type": "Feature",
  "properties": {
    "iso:country":"BE",
    "sg:address":"Oude Bruglaan 106-6",
    "sg:city":"Lokeren",
    "sg:classifiers":[
        {
            "category":"Retail",
            "subcategory":"Repair Shop",
            "type":"Services"
        }
    ],
    "sg:phone":"+32 495 54 98 47",
    "sg:postcode":"9160",
    "sg:province":"Oost-Vlaanderen",
    "wof:name":"Van Leeuwen W",
    "wof:placetype":"venue"
},
  "geometry": {"coordinates":[4.0038728714,51.1052856445],"type":"Point"}
}