{
  "type": "Feature",
  "properties": {
    "addr:full":"Rue Du Palais 79 Verviers Li\u00e8ge 4800",
    "addr:housenumber":"79",
    "addr:postcode":"4800",
    "addr:street":"Rue Du Palais",
    "iso:country":"BE",
    "sg:address":"Rue Du Palais 79",
    "sg:city":"Verviers",
    "sg:classifiers":[
        {
            "category":"Shopping",
            "subcategory":"Discount & Variety Stores",
            "type":"Retail Goods"
        }
    ],
    "sg:phone":"+32 87 22 95 21",
    "sg:postcode":"4800",
    "sg:province":"Li\u00e8ge",
    "sg:tags":[
        "shop",
        "clearers",
        "curiosity",
        "furniture"
    ],
    "wof:name":"La Vieille Halle 2",
    "wof:placetype":"venue"
},
  "geometry": {"coordinates":[5.8609371185,50.5897674561],"type":"Point"}
}