{
  "type": "Feature",
  "properties": {
    "addr:full":"Bruggestraat 192 Ingelmunster West-Vlaanderen 8770",
    "addr:housenumber":"192",
    "addr:postcode":"8770",
    "addr:street":"Bruggestraat",
    "iso:country":"BE",
    "sg:address":"Bruggestraat 192",
    "sg:city":"Ingelmunster",
    "sg:orig_category":"Benzinestations and brandstoffen",
    "sg:phone":"+32 51 30 34 69",
    "sg:postcode":"8770",
    "sg:province":"West-Vlaanderen",
    "wof:name":"Fa. Degezelle-buysse",
    "wof:placetype":"venue"
},
  "geometry": {"coordinates":[3.2521018982,50.9305458069],"type":"Point"}
}