{
  "type": "Feature",
  "properties": {
    "iso:country":"BE",
    "sg:address":"Asschout 57",
    "sg:city":"Evergem",
    "sg:classifiers":[
        {
            "category":"Autos & Motor Vehicles",
            "subcategory":"Automobile Sales",
            "type":"Retail Goods"
        }
    ],
    "sg:phone":"+32 9 370 87 50",
    "sg:postcode":"9940",
    "sg:province":"Oost-Vlaanderen",
    "sg:tags":[
        "car",
        "used",
        "-"
    ],
    "wof:name":"Autohandel G & F Cars",
    "wof:placetype":"venue"
},
  "geometry": {"coordinates":[3.687650919,51.1163139343],"type":"Point"}
}