{
  "type": "Feature",
  "properties": {
    "iso:country":"BE",
    "sg:address":"Rue Steyls 118",
    "sg:city":"Bruxelles",
    "sg:classifiers":[
        {
            "category":"Brewery",
            "type":"Food & Drink"
        }
    ],
    "sg:phone":"+32 2 425 39 51",
    "sg:postcode":"1020",
    "sg:province":"Bruxelles-Capitale",
    "wof:name":"Jetta Drinks",
    "wof:placetype":"venue"
},
  "geometry": {"coordinates":[4.3400201797,50.8788337708],"type":"Point"}
}