{
  "type": "Feature",
  "properties": {
    "addr:full":"Lange Leemstraat 364 Antwerpen Antwerpen 2018",
    "addr:housenumber":"364",
    "addr:postcode":"2018",
    "addr:street":"Lange Leemstraat",
    "iso:country":"BE",
    "sg:address":"Lange Leemstraat 364",
    "sg:city":"Antwerpen",
    "sg:classifiers":[
        {
            "category":"Professional",
            "subcategory":"Art Services",
            "type":"Services"
        }
    ],
    "sg:phone":"+32 3 281 49 41",
    "sg:postcode":"2018",
    "sg:province":"Antwerpen",
    "sg:tags":[
        "interior",
        "designer"
    ],
    "wof:name":"Het Ontwerpatelier",
    "wof:placetype":"venue"
},
  "geometry": {"coordinates":[4.4267969131,51.2034988403],"type":"Point"}
}