{
  "type": "Feature",
  "properties": {
    "addr:full":"Boulevard Emile Bockstael 19 Bruxelles Bruxelles-Capitale 1020",
    "addr:housenumber":"19",
    "addr:postcode":"1020",
    "addr:street":"Boulevard Emile Bockstael",
    "iso:country":"BE",
    "sg:address":"Boulevard Emile Bockstael 19",
    "sg:city":"Bruxelles",
    "sg:classifiers":[
        {
            "category":"Communications",
            "subcategory":"Film & Video Production",
            "type":"Services"
        }
    ],
    "sg:phone":"+32 2 216 60 55",
    "sg:postcode":"1020",
    "sg:province":"Bruxelles-Capitale",
    "sg:tags":[
        "multimedia",
        "-",
        "system"
    ],
    "wof:name":"Live Media",
    "wof:placetype":"venue"
},
  "geometry": {"coordinates":[4.3438539505,50.8705635071],"type":"Point"}
}