{
  "type": "Feature",
  "properties": {
    "iso:country":"BE",
    "sg:address":"35",
    "sg:city":"Abelestraat 8870 Izegem",
    "sg:classifiers":[
        {
            "category":"Shopping",
            "subcategory":"Clothing, Apparel, & Fashions",
            "type":"Retail Goods"
        }
    ],
    "sg:phone":"+32 57 44 40 47",
    "sg:postcode":"35",
    "sg:tags":[
        "textile",
        "clothing",
        "clothes"
    ],
    "wof:name":"Quality Consult Bvba",
    "wof:placetype":"venue"
},
  "geometry": {"coordinates":[3.189209938,50.9217758179],"type":"Point"}
}