{
  "type": "Feature",
  "properties": {
    "addr:full":"Rue De La Collectivit\u00c9 74 Saint-nicolas Li\u00e8ge 4420",
    "addr:housenumber":"74",
    "addr:postcode":"4420",
    "addr:street":"Rue De La Collectivite\u0301",
    "iso:country":"BE",
    "sg:address":"Rue De La Collectivit\u00c9 74",
    "sg:city":"Saint-nicolas",
    "sg:orig_category":"Charpentes and couvertures. Plomberie, chauffage and installations sanitaires",
    "sg:phone":"+32 4 225 02 04",
    "sg:postcode":"4420",
    "sg:province":"Li\u00e8ge",
    "wof:name":"Keusters",
    "wof:placetype":"venue"
},
  "geometry": {"coordinates":[5.5310049057,50.638469696],"type":"Point"}
}