{
  "type": "Feature",
  "properties": {
    "iso:country":"BE",
    "sg:address":"Valkenberg 24",
    "sg:city":"Brakel",
    "sg:classifiers":[
        {
            "category":"Cafe",
            "type":"Food & Drink"
        }
    ],
    "sg:phone":"+32 55 42 22 72",
    "sg:postcode":"9660",
    "sg:province":"Oost-Vlaanderen",
    "sg:tags":[
        "caf\u00e9s"
    ],
    "wof:name":"Andy Maes",
    "wof:placetype":"venue"
},
  "geometry": {"coordinates":[3.7568819523,50.8130302429],"type":"Point"}
}