{
  "type": "Feature",
  "properties": {
    "addr:full":"Rue Des Tanneurs 49 Estaimpuis Hainaut 7730",
    "addr:housenumber":"49",
    "addr:postcode":"7730",
    "addr:street":"Rue Des Tanneurs;Hainaut",
    "iso:country":"BE",
    "sg:address":"Rue Des Tanneurs 49",
    "sg:city":"Estaimpuis",
    "sg:orig_category":"HUISBRANDOLIE",
    "sg:phone":"+32 69 55 64 02",
    "sg:postcode":"7730",
    "sg:province":"Hainaut",
    "wof:name":"Dhulst",
    "wof:placetype":"venue"
},
  "geometry": {"coordinates":[3.3084030151,50.6762542725],"type":"Point"}
}