{
  "type": "Feature",
  "properties": {
    "addr:full":"Rue De La Pirire 29 Marche-en-famenne Luxembourg 6900",
    "addr:housenumber":"29",
    "addr:postcode":"6900",
    "addr:street":"Rue De La Pirire",
    "iso:country":"BE",
    "sg:address":"Rue De La Pirire 29",
    "sg:city":"Marche-en-famenne",
    "sg:orig_category":"Fruits and l\u00e9gumes Produits \u00e0 base de pommes de terre Gr",
    "sg:phone":"+32 84 31 43 55",
    "sg:postcode":"6900",
    "sg:province":"Luxembourg",
    "wof:name":"Maison Le Pr\u00c9 Vert",
    "wof:placetype":"venue"
},
  "geometry": {"coordinates":[5.3358697891,50.2236709595],"type":"Point"}
}