{
  "type": "Feature",
  "properties": {
    "iso:country":"BE",
    "sg:address":"Hoogstraat 198",
    "sg:city":"Brussel",
    "sg:classifiers":[
        {
            "category":"Restaurant",
            "type":"Food & Drink"
        }
    ],
    "sg:phone":"+32 2 513 88 82",
    "sg:postcode":"1000",
    "sg:province":"Bruxelles-Capitale",
    "wof:name":"Le Bermuchet",
    "wof:placetype":"venue"
},
  "geometry": {"coordinates":[4.3494138718,50.837600708],"type":"Point"}
}