{
  "type": "Feature",
  "properties": {
    "iso:country":"BE",
    "sg:address":"Bondgenotenlaan 152",
    "sg:city":"Leuven",
    "sg:orig_category":"Agences d\u00b4interim and personnel temporaire",
    "sg:phone":"+32 16 29 52 38",
    "sg:postcode":"3000",
    "sg:province":"Vlaams-Brabant",
    "wof:name":"Konvert Interim",
    "wof:placetype":"venue"
},
  "geometry": {"coordinates":[4.7137579918,50.8808937073],"type":"Point"}
}