{
  "type": "Feature",
  "properties": {
    "iso:country":"BE",
    "sg:address":"Rue Centrale 19",
    "sg:city":"Ath (meslin - L'ev\u00eaque)",
    "sg:classifiers":[
        {
            "category":"Professional",
            "subcategory":"Detective & Security Services",
            "type":"Services"
        }
    ],
    "sg:phone":"+32 68 57 21 51",
    "sg:postcode":"7822",
    "sg:province":"Hainaut",
    "sg:tags":[
        "access-control",
        "system"
    ],
    "wof:name":"Boisdenghien G Ets",
    "wof:placetype":"venue"
},
  "geometry": {"coordinates":[3.8572490215,50.6497917175],"type":"Point"}
}