{
  "type": "Feature",
  "properties": {
    "iso:country":"BE",
    "sg:address":"Mercatorstraat 32",
    "sg:city":"Antwerpen",
    "sg:orig_category":"V\u00eatements",
    "sg:phone":"+32 3 239 01 76",
    "sg:postcode":"2018",
    "sg:province":"Antwerpen",
    "wof:name":"Lichtert",
    "wof:placetype":"venue"
},
  "geometry": {"coordinates":[4.42233181,51.2096176147],"type":"Point"}
}