{
  "type": "Feature",
  "properties": {
    "addr:full":"Avenue Du Gris Moulin 23 La Hulpe Brabant Wallon 1310",
    "addr:housenumber":"23",
    "addr:postcode":"1310",
    "addr:street":"Avenue Du Gris Moulin",
    "iso:country":"BE",
    "sg:address":"Avenue Du Gris Moulin 23",
    "sg:city":"La Hulpe",
    "sg:classifiers":[
        {
            "category":"Shopping Center",
            "type":"Public Place"
        }
    ],
    "sg:phone":"+32 2 653 28 81",
    "sg:postcode":"1310",
    "sg:province":"Brabant Wallon",
    "sg:tags":[
        "enseignement",
        "formation"
    ],
    "wof:name":"Go Partners",
    "wof:placetype":"venue"
},
  "geometry": {"coordinates":[4.4775261879,50.7306861877],"type":"Point"}
}