{
  "type": "Feature",
  "properties": {
    "addr:full":"Rue Du Centre 1 Profondeville Namur 5170",
    "addr:housenumber":"1",
    "addr:postcode":"5170",
    "addr:street":"Rue Du Centre",
    "iso:country":"BE",
    "sg:address":"Rue Du Centre 1",
    "sg:city":"Profondeville",
    "sg:orig_category":"Postkantoren Verzekeringsmakelaars and experts",
    "sg:phone":"+32 81 43 31 37",
    "sg:postcode":"5170",
    "sg:province":"Namur",
    "wof:name":"La Poste",
    "wof:placetype":"venue"
},
  "geometry": {"coordinates":[4.8674049377,50.3786392212],"type":"Point"}
}