{
  "type": "Feature",
  "properties": {
    "addr:full":"Rue Des Bonniers 74 Lobbes Hainaut 6540",
    "addr:housenumber":"74",
    "addr:postcode":"6540",
    "addr:street":"Rue Des Bonniers",
    "iso:country":"BE",
    "sg:address":"Rue Des Bonniers 74",
    "sg:city":"Lobbes",
    "sg:orig_category":"Journaux. Tabac. Epiceries",
    "sg:phone":"+32 71 59 25 79",
    "sg:postcode":"6540",
    "sg:province":"Hainaut",
    "wof:name":"Librairie Des Bonniers",
    "wof:placetype":"venue"
},
  "geometry": {"coordinates":[4.2745900154,50.367805481],"type":"Point"}
}