{
  "type": "Feature",
  "properties": {
    "iso:country":"BE",
    "sg:address":"De Mortel 32",
    "sg:city":"Brasschaat",
    "sg:orig_category":"Brandweer and civiele bescherming",
    "sg:phone":"+32 3 651 63 98",
    "sg:postcode":"2930",
    "sg:province":"Antwerpen",
    "wof:name":"Brandweerkazerne",
    "wof:placetype":"venue"
},
  "geometry": {"coordinates":[4.4960708618,51.296333313],"type":"Point"}
}