{
  "type": "Feature",
  "properties": {
    "iso:country":"BE",
    "sg:address":"Dorp 2",
    "sg:city":"Asse",
    "sg:orig_category":"Installation \u00e9lectrique r\u00e9sidentielle",
    "sg:phone":"+32 2 453 25 25",
    "sg:postcode":"1730",
    "sg:province":"Vlaams-Brabant",
    "wof:name":"Marcel Meulenijzer",
    "wof:placetype":"venue"
},
  "geometry": {"coordinates":[4.1551141739,50.9213180542],"type":"Point"}
}