{
  "type": "Feature",
  "properties": {
    "iso:country":"BE",
    "sg:address":"Rue Pirka 21b",
    "sg:city":"Amay",
    "sg:classifiers":[
        {
            "category":"Retail",
            "subcategory":"Funeral Services",
            "type":"Services"
        }
    ],
    "sg:phone":"+32 85 31 12 11",
    "sg:postcode":"4540",
    "sg:province":"Li\u00e8ge",
    "sg:tags":[
        "director"
    ],
    "wof:name":"Cornet N",
    "wof:placetype":"venue"
},
  "geometry": {"coordinates":[5.306456089,50.5505447388],"type":"Point"}
}