{
  "type": "Feature",
  "properties": {
    "addr:full":"Doornzele Dries 131 Evergem Oost-Vlaanderen 9940",
    "addr:housenumber":"131",
    "addr:postcode":"9940",
    "addr:street":"Dries;Oost-Vlaanderen",
    "iso:country":"BE",
    "sg:address":"Doornzele Dries 131",
    "sg:city":"Evergem",
    "sg:orig_category":"Peinture. Rev\u00eatements pour sols and murs",
    "sg:phone":"+32 9 253 73 68",
    "sg:postcode":"9940",
    "sg:province":"Oost-Vlaanderen",
    "wof:name":"David De Clercq",
    "wof:placetype":"venue"
},
  "geometry": {"coordinates":[3.7534189224,51.1366081238],"type":"Point"}
}