{
  "type": "Feature",
  "properties": {
    "addr:full":"Ieperstraat 177-179 Menen West-Vlaanderen 8930",
    "addr:housenumber":"177-179",
    "addr:postcode":"8930",
    "addr:street":"Ieperstraat",
    "iso:country":"BE",
    "sg:address":"Ieperstraat 177-179",
    "sg:city":"Menen",
    "sg:classifiers":[
        {
            "category":"Building & Trades",
            "subcategory":"Locksmith",
            "type":"Services"
        }
    ],
    "sg:phone":"+32 56 53 05 75",
    "sg:postcode":"8930",
    "sg:province":"West-Vlaanderen",
    "sg:tags":[
        "lock",
        "key"
    ],
    "wof:name":"Edwin Multi-service",
    "wof:placetype":"venue"
},
  "geometry": {"coordinates":[3.1106948853,50.7995262146],"type":"Point"}
}