{
  "type": "Feature",
  "properties": {
    "addr:full":"Marktstraat 1 Box 11 Maldegem Oost-Vlaanderen 9990",
    "addr:housenumber":"1 box 11",
    "addr:postcode":"9990",
    "addr:street":"Marktstraat",
    "iso:country":"BE",
    "sg:address":"Marktstraat 1 Box 11",
    "sg:city":"Maldegem",
    "sg:classifiers":[
        {
            "category":"Professional",
            "subcategory":"Accounting & Tax Preparation",
            "type":"Services"
        }
    ],
    "sg:phone":"+32 50 71 45 61",
    "sg:postcode":"9990",
    "sg:province":"Oost-Vlaanderen",
    "sg:tags":[
        "bookkeeper"
    ],
    "wof:name":"G & E De Bruyckere Bvba",
    "wof:placetype":"venue"
},
  "geometry": {"coordinates":[3.4445559978,51.2091293335],"type":"Point"}
}