{
  "type": "Feature",
  "properties": {
    "iso:country":"BE",
    "sg:address":"Sluisstraat 18",
    "sg:city":"Knokke-heist",
    "sg:orig_category":"Diensten voor huisdieren",
    "sg:phone":"+32 50 60 66 77",
    "sg:postcode":"8300",
    "sg:province":"West-Vlaanderen",
    "wof:name":"Esteti-chien",
    "wof:placetype":"venue"
},
  "geometry": {"coordinates":[3.287694931,51.3467254639],"type":"Point"}
}