{
  "type": "Feature",
  "properties": {
    "addr:full":"Izegemstraat 4 Ingelmunster West-Vlaanderen 8770",
    "addr:housenumber":"4",
    "addr:postcode":"8770",
    "addr:street":"Izegemstraat",
    "iso:country":"BE",
    "sg:address":"Izegemstraat 4",
    "sg:city":"Ingelmunster",
    "sg:orig_category":"Medische apparatuur, orthopedische artikelen and prothesen Fab",
    "sg:phone":"+32 51 31 88 97",
    "sg:postcode":"8770",
    "sg:province":"West-Vlaanderen",
    "wof:name":"Steven De Maesschalck",
    "wof:placetype":"venue"
},
  "geometry": {"coordinates":[3.2546639442,50.9140090942],"type":"Point"}
}