{
  "type": "Feature",
  "properties": {
    "addr:full":"Hoogeind 24 Stabroek Antwerpen 2940",
    "addr:housenumber":"24",
    "addr:postcode":"2940",
    "addr:street":"Hoogeind",
    "iso:country":"BE",
    "sg:address":"Hoogeind 24",
    "sg:city":"Stabroek",
    "sg:orig_category":"Traitements param\u00e9dicaux",
    "sg:phone":"+32 3 568 64 39",
    "sg:postcode":"2940",
    "sg:province":"Antwerpen",
    "wof:name":"M. Havermaet",
    "wof:placetype":"venue"
},
  "geometry": {"coordinates":[4.3878188133,51.3433685303],"type":"Point"}
}