{
  "type": "Feature",
  "properties": {
    "iso:country":"BE",
    "sg:address":"Rue Ren\u00e9 Delbrouck 2",
    "sg:city":"Oupeye (hermalle-sous-argenteau)",
    "sg:classifiers":[
        {
            "category":"Health Services",
            "subcategory":"Doctor",
            "type":"Services"
        }
    ],
    "sg:phone":"+32 4 379 65 82",
    "sg:postcode":"4681",
    "sg:province":"Li\u00e8ge",
    "sg:tags":[
        "medicinephysicians",
        "surgeon"
    ],
    "wof:name":"L\u00e9onet J",
    "wof:placetype":"venue"
},
  "geometry": {"coordinates":[5.6723799706,50.7014312744],"type":"Point"}
}