{
  "type": "Feature",
  "properties": {
    "addr:full":"Kremerslei 13 Duffel Antwerpen 2570",
    "addr:housenumber":"13",
    "addr:postcode":"2570",
    "addr:street":"Kremerslei",
    "iso:country":"BE",
    "sg:address":"Kremerslei 13",
    "sg:city":"Duffel",
    "sg:orig_category":"Artsen and specialisten",
    "sg:phone":"+32 15 31 09 22",
    "sg:postcode":"2570",
    "sg:province":"Antwerpen",
    "wof:name":"W. De Block",
    "wof:placetype":"venue"
},
  "geometry": {"coordinates":[4.5017747879,51.1003112793],"type":"Point"}
}