{
  "type": "Feature",
  "properties": {
    "iso:country":"BE",
    "sg:address":"Slangstraat 46",
    "sg:city":"Hamme",
    "sg:orig_category":"Begrafeniswezen",
    "sg:phone":"+32 52 47 20 06",
    "sg:postcode":"9220",
    "sg:province":"Oost-Vlaanderen",
    "wof:name":"Begrafenissen D'hooge",
    "wof:placetype":"venue"
},
  "geometry": {"coordinates":[4.1356210709,51.0938796997],"type":"Point"}
}