{
  "type": "Feature",
  "properties": {
    "iso:country":"BE",
    "sg:address":"Winkelstraat 63",
    "sg:city":"Sint-amands",
    "sg:classifiers":[
        {
            "category":"Home & Garden",
            "subcategory":"Hardware",
            "type":"Retail Goods"
        }
    ],
    "sg:phone":"+32 52 33 50 50",
    "sg:postcode":"2890",
    "sg:province":"Antwerpen",
    "sg:tags":[
        "machine",
        "horticultural"
    ],
    "wof:name":"De Bock Eddy Bvba",
    "wof:placetype":"venue"
},
  "geometry": {"coordinates":[4.2074050903,51.0497550964],"type":"Point"}
}