{
  "type": "Feature",
  "properties": {
    "iso:country":"BE",
    "sg:address":"Marvie 9",
    "sg:city":"Bastogne (wardin)",
    "sg:classifiers":[
        {
            "category":"Home & Garden",
            "subcategory":"Carpets & Floor Coverings",
            "type":"Retail Goods"
        }
    ],
    "sg:phone":"+32 61 21 15 87",
    "sg:postcode":"6600",
    "sg:province":"Luxembourg",
    "sg:tags":[
        "tile"
    ],
    "wof:name":"Peschon A",
    "wof:placetype":"venue"
},
  "geometry": {"coordinates":[5.7463831902,49.9864196777],"type":"Point"}
}