{
  "type": "Feature",
  "properties": {
    "addr:full":"Hauptstrasse 35 Sankt Vith Li\u00e8ge 4780",
    "addr:housenumber":"35",
    "addr:postcode":"4780",
    "addr:street":"Hauptstrasse",
    "iso:country":"BE",
    "sg:address":"Hauptstrasse 35",
    "sg:city":"Sankt Vith",
    "sg:classifiers":[
        {
            "category":"Insurance",
            "subcategory":"Insurance Agent",
            "type":"Services"
        }
    ],
    "sg:phone":"+32 80 22 61 45",
    "sg:postcode":"4780",
    "sg:province":"Li\u00e8ge",
    "sg:tags":[
        "broker"
    ],
    "wof:name":"Maraite & Lentz Ag",
    "wof:placetype":"venue"
},
  "geometry": {"coordinates":[6.1261229515,50.2800712585],"type":"Point"}
}