{
  "type": "Feature",
  "properties": {
    "addr:full":"Waalvest 0 Menen West-Vlaanderen 8930",
    "addr:housenumber":"0",
    "addr:postcode":"8930",
    "addr:street":"Waalvest",
    "iso:country":"BE",
    "sg:address":"Waalvest 0",
    "sg:city":"Menen",
    "sg:orig_category":"Biblioth\u00e8ques and archives publiques",
    "sg:phone":"+32 56 51 58 70",
    "sg:postcode":"8930",
    "sg:province":"West-Vlaanderen",
    "wof:name":"Openbare Bibliotheek",
    "wof:placetype":"venue"
},
  "geometry": {"coordinates":[3.1239280701,50.7931137085],"type":"Point"}
}