{
  "type": "Feature",
  "properties": {
    "addr:full":"Oosteeklostraat 38 Gent Oost-Vlaanderen 9000",
    "addr:housenumber":"38",
    "addr:postcode":"9000",
    "addr:street":"Oosteeklostraat;Oost-Vlaanderen",
    "iso:country":"BE",
    "sg:address":"Oosteeklostraat 38",
    "sg:city":"Gent",
    "sg:orig_category":"Sportclubs Sportterreinen and installaties behalve sportcentra",
    "sg:phone":"+32 9 233 03 75",
    "sg:postcode":"9000",
    "sg:province":"Oost-Vlaanderen",
    "wof:name":"F.c. Avrasya Gent",
    "wof:placetype":"venue"
},
  "geometry": {"coordinates":[3.7195720673,51.0663566589],"type":"Point"}
}