{
  "type": "Feature",
  "properties": {
    "iso:country":"BE",
    "sg:address":"Avenue Du P\u00e9rou 77b",
    "sg:city":"Bruxelles",
    "sg:orig_category":"Newspapers, magazines, periodicals - Publishers",
    "sg:phone":"+32 2 672 23 40",
    "sg:postcode":"1000",
    "sg:province":"Bruxelles-Capitale",
    "wof:name":"Usines & Industries Sa",
    "wof:placetype":"venue"
},
  "geometry": {"coordinates":[4.3974919319,50.7983055115],"type":"Point"}
}