{
  "type": "Feature",
  "properties": {
    "addr:full":"Heistraat 92 Sint-niklaas Oost-Vlaanderen 9100",
    "addr:housenumber":"92",
    "addr:postcode":"9100",
    "addr:street":"Heistraat",
    "iso:country":"BE",
    "sg:address":"Heistraat 92",
    "sg:city":"Sint-niklaas",
    "sg:classifiers":[
        {
            "category":"Home & Garden",
            "subcategory":"Home Furnishings",
            "type":"Retail Goods"
        }
    ],
    "sg:phone":"+32 3 777 62 84",
    "sg:postcode":"9100",
    "sg:province":"Oost-Vlaanderen",
    "sg:tags":[
        "curtain",
        "-",
        "fixture"
    ],
    "wof:name":"Modecoupon St-niklaas",
    "wof:placetype":"venue"
},
  "geometry": {"coordinates":[4.1322622299,51.1750488281],"type":"Point"}
}