{
  "type": "Feature",
  "properties": {
    "iso:country":"BE",
    "sg:address":"Rue De La Concorde 24",
    "sg:city":"Elsene/ixelles",
    "sg:orig_category":"Avocats and conseillers juridiques",
    "sg:phone":"+32 2 511 51 38",
    "sg:postcode":"1050",
    "sg:province":"Bruxelles-Capitale",
    "wof:name":"P. Loir",
    "wof:placetype":"venue"
},
  "geometry": {"coordinates":[4.3615679741,50.8334274292],"type":"Point"}
}