{
  "type": "Feature",
  "properties": {
    "iso:country":"BE",
    "sg:address":"Warmifontaine 118",
    "sg:city":"Neufchateau",
    "sg:classifiers":[
        {
            "category":"Cafe",
            "type":"Food & Drink"
        }
    ],
    "sg:phone":"+32 61 27 72 91",
    "sg:postcode":"6840",
    "sg:province":"Luxembourg",
    "sg:tags":[
        "caf\u00e9s"
    ],
    "wof:name":"Lucie Chauvaux",
    "wof:placetype":"venue"
},
  "geometry": {"coordinates":[5.4346451759,49.8411598206],"type":"Point"}
}