{
  "type": "Feature",
  "properties": {
    "addr:full":"Postelsebaan 74 Retie Antwerpen 2470",
    "addr:housenumber":"74",
    "addr:postcode":"2470",
    "addr:street":"Postelsebaan",
    "iso:country":"BE",
    "sg:address":"Postelsebaan 74",
    "sg:city":"Retie",
    "sg:classifiers":[
        {
            "category":"Bars & Pubs",
            "type":"Food & Drink"
        }
    ],
    "sg:phone":"+32 14 37 23 21",
    "sg:postcode":"2470",
    "sg:province":"Antwerpen",
    "sg:tags":[
        "tavern"
    ],
    "wof:name":"Postel Ter Heyde",
    "wof:placetype":"venue"
},
  "geometry": {"coordinates":[5.1493878365,51.2768096924],"type":"Point"}
}