{
  "type": "Feature",
  "properties": {
    "iso:country":"BE",
    "sg:address":"Vieille-route 4",
    "sg:city":"Rendeux",
    "sg:orig_category":"Eleveurs de bovins",
    "sg:phone":"+32 84 47 81 12",
    "sg:postcode":"6987",
    "sg:province":"Luxembourg",
    "wof:name":"Fernand Leonard",
    "wof:placetype":"venue"
},
  "geometry": {"coordinates":[5.5223259926,50.199760437],"type":"Point"}
}