{
  "type": "Feature",
  "properties": {
    "addr:full":"Ooststraat 34 Veurne West-Vlaanderen 8630",
    "addr:housenumber":"34",
    "addr:postcode":"8630",
    "addr:street":"Ooststraat",
    "iso:country":"BE",
    "sg:address":"Ooststraat 34",
    "sg:city":"Veurne",
    "sg:orig_category":"Pain, p\u00e2tisseries and confiseries",
    "sg:phone":"+32 58 31 14 26",
    "sg:postcode":"8630",
    "sg:province":"West-Vlaanderen",
    "wof:name":"Bakkerij Notredame",
    "wof:placetype":"venue"
},
  "geometry": {"coordinates":[2.6641149521,51.0727996826],"type":"Point"}
}