{
  "type": "Feature",
  "properties": {
    "iso:country":"BE",
    "sg:address":"De Vri\u00c8restraat 38",
    "sg:city":"Antwerpen",
    "sg:classifiers":[
        {
            "category":"Wholesale",
            "subcategory":"Sporting Goods",
            "type":"Manufacturing & Wholesale Goods"
        }
    ],
    "sg:phone":"+32 3 237 56 58",
    "sg:postcode":"2000",
    "sg:province":"Antwerpen",
    "sg:tags":[
        "sport-",
        "kampeermateriaal"
    ],
    "wof:name":"Aqua Diver Shop",
    "wof:placetype":"venue"
},
  "geometry": {"coordinates":[4.3975491524,51.208694458],"type":"Point"}
}