{
  "type": "Feature",
  "properties": {
    "iso:country":"BE",
    "sg:address":"Dikkebusstraat 119",
    "sg:city":"Heuvelland (loker)",
    "sg:classifiers":[
        {
            "category":"Manufacturing",
            "subcategory":"Textiles",
            "type":"Manufacturing & Wholesale Goods"
        }
    ],
    "sg:phone":"+32 57 44 42 61",
    "sg:postcode":"8958",
    "sg:province":"West-Vlaanderen",
    "sg:tags":[
        "retail",
        "-"
    ],
    "wof:name":"Haezebrouck G",
    "wof:placetype":"venue"
},
  "geometry": {"coordinates":[2.7723040581,50.7892684937],"type":"Point"}
}