{
  "type": "Feature",
  "properties": {
    "iso:country":"BE",
    "sg:address":"Bovenstraat 4",
    "sg:city":"Maarkedal",
    "sg:classifiers":[
        {
            "category":"Restaurant",
            "type":"Food & Drink"
        }
    ],
    "sg:phone":"+32 55 30 35 56",
    "sg:postcode":"9680",
    "sg:province":"Oost-Vlaanderen",
    "wof:name":"Het Genot Op Den Berg",
    "wof:placetype":"venue"
},
  "geometry": {"coordinates":[3.6527619362,50.8015213013],"type":"Point"}
}