{
  "type": "Feature",
  "properties": {
    "iso:country":"BE",
    "sg:address":"Rue Des Ecriniers 5",
    "sg:city":"Ath",
    "sg:classifiers":[
        {
            "category":"Arts & Performance",
            "subcategory":"Theater",
            "type":"Entertainment"
        }
    ],
    "sg:phone":"+32 68 84 04 70",
    "sg:postcode":"7800",
    "sg:province":"Hainaut",
    "sg:tags":[
        "theatrical",
        "agency"
    ],
    "wof:name":"Walrus Productions Asbl",
    "wof:placetype":"venue"
},
  "geometry": {"coordinates":[3.7781569958,50.6292419434],"type":"Point"}
}