{
  "type": "Feature",
  "properties": {
    "addr:full":"Rue De La Forge 16 Fernelmont Namur 5380",
    "addr:housenumber":"16",
    "addr:postcode":"5380",
    "addr:street":"Rue De La Forge",
    "iso:country":"BE",
    "sg:address":"Rue De La Forge 16",
    "sg:city":"Fernelmont",
    "sg:orig_category":"Entretien and r\u00e9parations de voitures",
    "sg:phone":"+32 81 83 53 13",
    "sg:postcode":"5380",
    "sg:province":"Namur",
    "wof:name":"Carrosserie Smal Product",
    "wof:placetype":"venue"
},
  "geometry": {"coordinates":[4.9861078262,50.5531463623],"type":"Point"}
}