{
  "type": "Feature",
  "properties": {
    "iso:country":"BE",
    "sg:address":"Rue De Wallonie 0",
    "sg:city":"Grace-hollogne",
    "sg:orig_category":"Verlichting and huishoudartikelen",
    "sg:phone":"+32 4 239 73 10",
    "sg:postcode":"4460",
    "sg:province":"Li\u00e8ge",
    "wof:name":"Elma Obreg",
    "wof:placetype":"venue"
},
  "geometry": {"coordinates":[5.4854469299,50.6515045166],"type":"Point"}
}