{
  "type": "Feature",
  "properties": {
    "addr:full":"Merksplassesteenweg 9 Rijkevorsel Antwerpen 2310",
    "addr:housenumber":"9",
    "addr:postcode":"2310",
    "addr:street":"Merksplassesteenweg",
    "iso:country":"BE",
    "sg:address":"Merksplassesteenweg 9",
    "sg:city":"Rijkevorsel",
    "sg:classifiers":[
        {
            "category":"Professional",
            "subcategory":"Accounting & Tax Preparation",
            "type":"Services"
        }
    ],
    "sg:phone":"+32 3 314 75 73",
    "sg:postcode":"2310",
    "sg:province":"Antwerpen",
    "sg:tags":[
        "bookkeeper"
    ],
    "wof:name":"Luyckx P",
    "wof:placetype":"venue"
},
  "geometry": {"coordinates":[4.7834200859,51.3465309143],"type":"Point"}
}