{
  "type": "Feature",
  "properties": {
    "addr:full":"Opperstraat 108 Elsene/ixelles Bruxelles-Capitale 1050",
    "addr:housenumber":"108",
    "addr:postcode":"1050",
    "addr:street":"Opperstraat",
    "iso:country":"BE",
    "sg:address":"Opperstraat 108",
    "sg:city":"Elsene/ixelles",
    "sg:orig_category":"Tuinen",
    "sg:phone":"+32 2 644 08 40",
    "sg:postcode":"1050",
    "sg:province":"Bruxelles-Capitale",
    "wof:name":"L\u00b4arbre Enchanteur",
    "wof:placetype":"venue"
},
  "geometry": {"coordinates":[4.3623142242,50.8308906555],"type":"Point"}
}