{
  "type": "Feature",
  "properties": {
    "addr:full":"Rue Belliard 25 Bruxelles (etterbeek) Bruxelles-Capitale 1040",
    "addr:housenumber":"25",
    "addr:postcode":"1040",
    "addr:street":"Rue Belliard",
    "iso:country":"BE",
    "sg:address":"Rue Belliard 25",
    "sg:city":"Bruxelles (etterbeek)",
    "sg:classifiers":[
        {
            "category":"Banks & Credit Unions",
            "subcategory":"Investment Brokerage",
            "type":"Services"
        }
    ],
    "sg:phone":"+32 2 238 45 11",
    "sg:postcode":"1040",
    "sg:province":"Bruxelles-Capitale",
    "sg:tags":[
        "lottery",
        "pool"
    ],
    "wof:name":"Nationale Loterij",
    "wof:placetype":"venue"
},
  "geometry": {"coordinates":[4.3700900078,50.8420372009],"type":"Point"}
}