{
  "type": "Feature",
  "properties": {
    "addr:full":"Rue De Ciney 28 Ohey Namur 5350",
    "addr:housenumber":"28",
    "addr:postcode":"5350",
    "addr:street":"Rue De Ciney",
    "iso:country":"BE",
    "sg:address":"Rue De Ciney 28",
    "sg:city":"Ohey",
    "sg:orig_category":"Kapsalons",
    "sg:phone":"+32 85 61 17 71",
    "sg:postcode":"5350",
    "sg:province":"Namur",
    "wof:name":"Coiffure Marie-france",
    "wof:placetype":"venue"
},
  "geometry": {"coordinates":[5.1234102249,50.435798645],"type":"Point"}
}