{
  "type": "Feature",
  "properties": {
    "addr:full":"Rue De Lannoy 22 Tournai Hainaut 7500",
    "addr:housenumber":"22",
    "addr:postcode":"7500",
    "addr:street":"Rue De Lannoy",
    "iso:country":"BE",
    "sg:address":"Rue De Lannoy 22",
    "sg:city":"Tournai",
    "sg:classifiers":[
        {
            "category":"Building & Trades",
            "subcategory":"Construction",
            "type":"Services"
        }
    ],
    "sg:phone":"+32 69 21 41 66",
    "sg:postcode":"7500",
    "sg:province":"Hainaut",
    "sg:tags":[
        "work",
        "waterproofing"
    ],
    "wof:name":"Meuleman Jp Sa",
    "wof:placetype":"venue"
},
  "geometry": {"coordinates":[3.3747940063,50.6146087646],"type":"Point"}
}