{
  "type": "Feature",
  "properties": {
    "addr:full":"Place Des Clo\u00cetres 4 Amay Li\u00e8ge 4540",
    "addr:housenumber":"4",
    "addr:postcode":"4540",
    "addr:street":"Place Des Cloi\u0302Tres",
    "iso:country":"BE",
    "sg:address":"Place Des Clo\u00cetres 4",
    "sg:city":"Amay",
    "sg:orig_category":"V\u00e9t\u00e9rinaires",
    "sg:phone":"+32 85 51 22 05",
    "sg:postcode":"4540",
    "sg:province":"Li\u00e8ge",
    "wof:name":"Fr\u00c9d\u00c9ric Boland",
    "wof:placetype":"venue"
},
  "geometry": {"coordinates":[5.318051815,50.548992157],"type":"Point"}
}