{
  "type": "Feature",
  "properties": {
    "iso:country":"BE",
    "sg:address":"Rue De Montauban 21",
    "sg:city":"Etalle",
    "sg:orig_category":"Charpentes and couvertures",
    "sg:phone":"+32 63 45 54 97",
    "sg:postcode":"6743",
    "sg:province":"Luxembourg",
    "wof:name":"Toitures Artisanales",
    "wof:placetype":"venue"
},
  "geometry": {"coordinates":[5.5948181152,49.6454582214],"type":"Point"}
}