{
  "type": "Feature",
  "properties": {
    "iso:country":"BE",
    "sg:address":"Stefaniastraat 22",
    "sg:city":"Brussel/bruxelles",
    "sg:orig_category":"Plaatsen van vloer- and muurbekleding Schilders",
    "sg:phone":"+32 2 426 33 73",
    "sg:postcode":"1020",
    "sg:province":"Bruxelles-Capitale",
    "wof:name":"Papasergio",
    "wof:placetype":"venue"
},
  "geometry": {"coordinates":[4.355866909,50.8764648438],"type":"Point"}
}