{
  "type": "Feature",
  "properties": {
    "iso:country":"BE",
    "sg:address":"Aarschotsesteenweg 706",
    "sg:city":"Leuven (wilsele)",
    "sg:classifiers":[
        {
            "category":"Food & Beverages",
            "subcategory":"Fruits & Vegetables",
            "type":"Retail Goods"
        }
    ],
    "sg:phone":"+32 16 44 04 04",
    "sg:postcode":"3012",
    "sg:province":"Vlaams-Brabant",
    "sg:tags":[
        "-"
    ],
    "wof:name":"Marc's Delicatessen",
    "wof:placetype":"venue"
},
  "geometry": {"coordinates":[4.7228050232,50.926738739],"type":"Point"}
}