{
  "type": "Feature",
  "properties": {
    "addr:full":"Swytswal 2a Koekelare West-Vlaanderen 8680",
    "addr:housenumber":"2a",
    "addr:postcode":"8680",
    "addr:street":"Swytswal",
    "iso:country":"BE",
    "sg:address":"Swytswal 2a",
    "sg:city":"Koekelare",
    "sg:classifiers":[
        {
            "category":"Real Estate",
            "subcategory":"Surveying",
            "type":"Services"
        }
    ],
    "sg:phone":"+32 51 58 87 04",
    "sg:postcode":"8680",
    "sg:province":"West-Vlaanderen",
    "sg:tags":[
        "surveyor",
        "land"
    ],
    "wof:name":"D'haene J",
    "wof:placetype":"venue"
},
  "geometry": {"coordinates":[2.9882390499,51.0896873474],"type":"Point"}
}