{
  "type": "Feature",
  "properties": {
    "iso:country":"BE",
    "sg:address":"Kerkstraat 15b4",
    "sg:city":"Hechtel-eksel",
    "sg:orig_category":"Elektrische installaties voor woningen",
    "sg:phone":"+32 11 73 11 35",
    "sg:postcode":"3941",
    "sg:province":"Limburg",
    "wof:name":"Electro Paesen",
    "wof:placetype":"venue"
},
  "geometry": {"coordinates":[5.3928489685,51.1532707214],"type":"Point"}
}