{
  "type": "Feature",
  "properties": {
    "iso:country":"BE",
    "sg:address":"Sterrebosdreef 66",
    "sg:city":"Roeselare",
    "sg:orig_category":"Recreatie- and lunaparken",
    "sg:phone":"+32 51 20 11 80",
    "sg:postcode":"8800",
    "sg:province":"West-Vlaanderen",
    "wof:name":"Prov. Domein Sterrebos",
    "wof:placetype":"venue"
},
  "geometry": {"coordinates":[3.1369640827,50.9240074158],"type":"Point"}
}