{
  "type": "Feature",
  "properties": {
    "addr:full":"Rue Victor Delporte 21 Hensies Hainaut 7350",
    "addr:housenumber":"21",
    "addr:postcode":"7350",
    "addr:street":"Rue Victor Delporte",
    "iso:country":"BE",
    "sg:address":"Rue Victor Delporte 21",
    "sg:city":"Hensies",
    "sg:orig_category":"Pharmaciens",
    "sg:phone":"+32 65 65 28 90",
    "sg:postcode":"7350",
    "sg:province":"Hainaut",
    "wof:name":"Martine Liegeois",
    "wof:placetype":"venue"
},
  "geometry": {"coordinates":[3.73864007,50.427570343],"type":"Point"}
}