{
  "type": "Feature",
  "properties": {
    "addr:full":"President Kennedylaan 21 Vilvoorde Vlaams-Brabant 1800",
    "addr:housenumber":"21",
    "addr:postcode":"1800",
    "addr:street":"President Kennedylaan",
    "iso:country":"BE",
    "sg:address":"President Kennedylaan 21",
    "sg:city":"Vilvoorde",
    "sg:classifiers":[
        {
            "category":"Taxi",
            "type":"Transportation"
        }
    ],
    "sg:phone":"+32 2 252 23 29",
    "sg:postcode":"1800",
    "sg:province":"Vlaams-Brabant",
    "wof:name":"Taxis Services",
    "wof:placetype":"venue"
},
  "geometry": {"coordinates":[4.4050951004,50.9185523987],"type":"Point"}
}