{
  "type": "Feature",
  "properties": {
    "addr:full":"Pastoor Petersstraat 16 Bornem Antwerpen 2880",
    "addr:housenumber":"16",
    "addr:postcode":"2880",
    "addr:street":"Pastoor Petersstraat",
    "iso:country":"BE",
    "sg:address":"Pastoor Petersstraat 16",
    "sg:city":"Bornem",
    "sg:orig_category":"Antiek Tweedehandsgoederen",
    "sg:phone":"+32 3 899 42 70",
    "sg:postcode":"2880",
    "sg:province":"Antwerpen",
    "wof:name":"De Rommelaar",
    "wof:placetype":"venue"
},
  "geometry": {"coordinates":[4.2032032013,51.0817146301],"type":"Point"}
}