{
  "type": "Feature",
  "properties": {
    "addr:full":"Ingelmunsterstraat 179 Ingelmunster West-Vlaanderen 8770",
    "addr:housenumber":"179",
    "addr:postcode":"8770",
    "addr:street":"Ingelmunsterstraat",
    "iso:country":"BE",
    "sg:address":"Ingelmunsterstraat 179",
    "sg:city":"Ingelmunster",
    "sg:orig_category":"Kapsalons",
    "sg:phone":"+32 51 31 54 71",
    "sg:postcode":"8770",
    "sg:province":"West-Vlaanderen",
    "wof:name":"Coiffure Cinthy",
    "wof:placetype":"venue"
},
  "geometry": {"coordinates":[3.2418000698,50.9276199341],"type":"Point"}
}