{
  "type": "Feature",
  "properties": {
    "iso:country":"BE",
    "sg:address":"Chauss\u00c9e De Ruisbroek 378",
    "sg:city":"Drogenbos",
    "sg:orig_category":"Voertuigen",
    "sg:phone":"+32 2 331 02 67",
    "sg:postcode":"1620",
    "sg:province":"Vlaams-Brabant",
    "wof:name":"Auto Evasion",
    "wof:placetype":"venue"
},
  "geometry": {"coordinates":[4.3054580688,50.7944869995],"type":"Point"}
}