{
  "type": "Feature",
  "properties": {
    "iso:country":"BE",
    "sg:address":"Saint-hadelin 14",
    "sg:city":"Olne",
    "sg:orig_category":"Rev\u00eatements pour sols and murs",
    "sg:phone":"+32 4 358 17 21",
    "sg:postcode":"4877",
    "sg:province":"Li\u00e8ge",
    "wof:name":"Marcel Kerf",
    "wof:placetype":"venue"
},
  "geometry": {"coordinates":[5.7219929695,50.5956573486],"type":"Point"}
}