{
  "type": "Feature",
  "properties": {
    "addr:full":"Stationsstraat 14 Liedekerke Vlaams-Brabant 1770",
    "addr:housenumber":"14",
    "addr:postcode":"1770",
    "addr:street":"Stationsstraat;Vlaams-Brabant",
    "iso:country":"BE",
    "sg:address":"Stationsstraat 14",
    "sg:city":"Liedekerke",
    "sg:orig_category":"V\u00eatements pour Dames. V\u00eatements pour b\u00e9b\u00e9s and enfants. Articles pour b\u00e9b\u00e9s",
    "sg:phone":"+32 53 66 40 81",
    "sg:postcode":"1770",
    "sg:province":"Vlaams-Brabant",
    "wof:name":"Pr\u00c9maman",
    "wof:placetype":"venue"
},
  "geometry": {"coordinates":[4.0832471848,50.8718566895],"type":"Point"}
}