{
  "type": "Feature",
  "properties": {
    "addr:full":"Avenue Marius Meur\u00e9e 99 Box 7 Charleroi (marcinelle) Hainaut 6001",
    "addr:housenumber":"99;7",
    "addr:postcode":"6001",
    "addr:street":"Avenue Marius Meure\u0301E;Box",
    "iso:country":"BE",
    "sg:address":"Avenue Marius Meur\u00e9e 99 Box 7",
    "sg:city":"Charleroi (marcinelle)",
    "sg:classifiers":[
        {
            "category":"Professional",
            "subcategory":"Management & Consulting",
            "type":"Services"
        }
    ],
    "sg:phone":"+32 71 43 74 99",
    "sg:postcode":"6001",
    "sg:province":"Hainaut",
    "sg:tags":[
        "marketing",
        "-",
        "direct",
        "consultant"
    ],
    "wof:name":"Nerinckx L",
    "wof:placetype":"venue"
},
  "geometry": {"coordinates":[4.4446668625,50.4028701782],"type":"Point"}
}