{
  "type": "Feature",
  "properties": {
    "iso:country":"BE",
    "sg:address":"Boterstraat 22",
    "sg:city":"Tielt-winge",
    "sg:orig_category":"Kapsalons",
    "sg:phone":"+32 16 50 19 52",
    "sg:postcode":"3390",
    "sg:province":"Vlaams-Brabant",
    "wof:name":"Coiffure Nina",
    "wof:placetype":"venue"
},
  "geometry": {"coordinates":[4.9022698402,50.9438972473],"type":"Point"}
}