{
  "type": "Feature",
  "properties": {
    "iso:country":"BE",
    "sg:address":"All\u00c9e De L'entr'aide 18",
    "sg:city":"Bassenge",
    "sg:orig_category":"Schoonheidssalons",
    "sg:phone":"+32 4 286 16 70",
    "sg:postcode":"4690",
    "sg:province":"Li\u00e8ge",
    "wof:name":"Christiane Hilderson",
    "wof:placetype":"venue"
},
  "geometry": {"coordinates":[5.5956330299,50.7563591003],"type":"Point"}
}