{
  "type": "Feature",
  "properties": {
    "iso:country":"BE",
    "sg:address":"Lageweg 22b22",
    "sg:city":"Menen",
    "sg:orig_category":"Pain, p\u00e2tisseries and confiseries",
    "sg:phone":"+32 56 51 73 09",
    "sg:postcode":"8930",
    "sg:province":"West-Vlaanderen",
    "wof:name":"Carl Van Den Bogaerde",
    "wof:placetype":"venue"
},
  "geometry": {"coordinates":[3.1067950726,50.7933425903],"type":"Point"}
}