{
  "type": "Feature",
  "properties": {
    "iso:country":"BE",
    "sg:address":"Bellestraat 218",
    "sg:city":"Affligem",
    "sg:orig_category":"Meubelzaken, woning- and keukeninrichting",
    "sg:phone":"+32 53 66 12 44",
    "sg:postcode":"1790",
    "sg:province":"Vlaams-Brabant",
    "wof:name":"B. & B. Racks",
    "wof:placetype":"venue"
},
  "geometry": {"coordinates":[4.1294307709,50.8929138184],"type":"Point"}
}