{
  "type": "Feature",
  "properties": {
    "addr:full":"H. Hartlaan 50 Lokeren Oost-Vlaanderen 9160",
    "addr:housenumber":"50",
    "addr:postcode":"9160",
    "addr:street":"Hartlaan",
    "iso:country":"BE",
    "sg:address":"H. Hartlaan 50",
    "sg:city":"Lokeren",
    "sg:orig_category":"M\u00e9decins and sp\u00e9cialistes",
    "sg:phone":"+32 9 348 91 68",
    "sg:postcode":"9160",
    "sg:province":"Oost-Vlaanderen",
    "wof:name":"L. Peelman",
    "wof:placetype":"venue"
},
  "geometry": {"coordinates":[3.9884080887,51.0993728638],"type":"Point"}
}