{
  "type": "Feature",
  "properties": {
    "iso:country":"BE",
    "sg:address":"Rue Du Vieux H\u00eatre 10",
    "sg:city":"Weismes (robertville)",
    "sg:classifiers":[
        {
            "category":"Health Services",
            "subcategory":"Dentist",
            "type":"Services"
        }
    ],
    "sg:phone":"+32 80 44 41 88",
    "sg:postcode":"4950",
    "sg:province":"Li\u00e8ge",
    "wof:name":"Hugo Philippe",
    "wof:placetype":"venue"
},
  "geometry": {"coordinates":[6.1245827675,50.4664802551],"type":"Point"}
}