{
  "type": "Feature",
  "properties": {
    "addr:full":"Lijnwaadstraat 66 Roeselare West-Vlaanderen 8800",
    "addr:housenumber":"66",
    "addr:postcode":"8800",
    "addr:street":"Lijnwaadstraat",
    "iso:country":"BE",
    "sg:address":"Lijnwaadstraat 66",
    "sg:city":"Roeselare",
    "sg:orig_category":"Jardinage",
    "sg:phone":"+32 51 24 24 89",
    "sg:postcode":"8800",
    "sg:province":"West-Vlaanderen",
    "wof:name":"Johan Vroman",
    "wof:placetype":"venue"
},
  "geometry": {"coordinates":[3.1130099297,50.9652748108],"type":"Point"}
}