{
  "type": "Feature",
  "properties": {
    "addr:full":"Louis Robbeplein 1b1 Kortrijk West-Vlaanderen 8500",
    "addr:postcode":"8500",
    "iso:country":"BE",
    "sg:address":"Louis Robbeplein 1b1",
    "sg:city":"Kortrijk",
    "sg:orig_category":"Medische apparatuur, orthopedische artikelen and prothesen Fab",
    "sg:phone":"+32 56 21 96 66",
    "sg:postcode":"8500",
    "sg:province":"West-Vlaanderen",
    "wof:name":"Dento Lab",
    "wof:placetype":"venue"
},
  "geometry": {"coordinates":[3.2604990005,50.8270187378],"type":"Point"}
}