{
  "type": "Feature",
  "properties": {
    "addr:full":"Rue Benne Br\u00fbl\u00e9e 102 Florennes (morialm\u00e9) Namur 5621",
    "addr:housenumber":"102",
    "addr:postcode":"5621",
    "addr:street":"Rue Benne Bru\u0302Le\u0301E",
    "iso:country":"BE",
    "sg:address":"Rue Benne Br\u00fbl\u00e9e 102",
    "sg:city":"Florennes (morialm\u00e9)",
    "sg:classifiers":[
        {
            "category":"Building & Trades",
            "subcategory":"Electrical",
            "type":"Services"
        }
    ],
    "sg:phone":"+32 71 68 82 55",
    "sg:postcode":"5621",
    "sg:province":"Namur",
    "sg:tags":[
        "electric",
        "-",
        "housewiring",
        "contractor"
    ],
    "wof:name":"Cobbaert P",
    "wof:placetype":"venue"
},
  "geometry": {"coordinates":[4.5761170387,50.274520874],"type":"Point"}
}