{
  "type": "Feature",
  "properties": {
    "iso:country":"BE",
    "sg:address":"En-pierreux 1",
    "sg:city":"Manhay",
    "sg:orig_category":"R\u00e9cup\u00e9ration de mati\u00e8res m\u00e9talliques recyclables and d\u00e9molisseurs de voitures. Entretien et r\u00e9parati",
    "sg:phone":"+32 86 45 51 66",
    "sg:postcode":"6960",
    "sg:province":"Luxembourg",
    "wof:name":"Garage Cornet F.",
    "wof:placetype":"venue"
},
  "geometry": {"coordinates":[5.6750068665,50.3173980713],"type":"Point"}
}