{
  "type": "Feature",
  "properties": {
    "addr:full":"Lippenslaan 136 Knokke-heist West-Vlaanderen 8300",
    "addr:housenumber":"136",
    "addr:postcode":"8300",
    "addr:street":"Lippenslaan",
    "iso:country":"BE",
    "sg:address":"Lippenslaan 136",
    "sg:city":"Knokke-heist",
    "sg:classifiers":[
        {
            "category":"Shopping",
            "subcategory":"Clothing, Apparel, & Fashions",
            "type":"Retail Goods"
        }
    ],
    "sg:phone":"+32 50 62 78 81",
    "sg:postcode":"8300",
    "sg:province":"West-Vlaanderen",
    "sg:tags":[
        "v\u00eatements",
        "pour",
        "dame"
    ],
    "wof:name":"Beach Club",
    "wof:placetype":"venue"
},
  "geometry": {"coordinates":[3.2884008884,51.3459663391],"type":"Point"}
}