{
  "type": "Feature",
  "properties": {
    "iso:country":"BE",
    "sg:address":"Magretstraat 34",
    "sg:city":"Lochristi",
    "sg:orig_category":"Bloemen and planten Gh",
    "sg:phone":"+32 9 355 60 35",
    "sg:postcode":"9080",
    "sg:province":"Oost-Vlaanderen",
    "wof:name":"Donnairs P",
    "wof:placetype":"venue"
},
  "geometry": {"coordinates":[3.871434927,51.0675926208],"type":"Point"}
}