{
  "type": "Feature",
  "properties": {
    "addr:full":"Lisbloemlaan 19 Middelkerke West-Vlaanderen 8430",
    "addr:housenumber":"19",
    "addr:postcode":"8430",
    "addr:street":"Lisbloemlaan",
    "iso:country":"BE",
    "sg:address":"Lisbloemlaan 19",
    "sg:city":"Middelkerke",
    "sg:classifiers":[
        {
            "category":"Arena",
            "subcategory":"Sports Club",
            "type":"Entertainment"
        }
    ],
    "sg:phone":"+32 59 30 06 02",
    "sg:postcode":"8430",
    "sg:province":"West-Vlaanderen",
    "sg:tags":[
        "de"
    ],
    "wof:name":"Kon.v.c. Jonge Vluchters Middelkerke",
    "wof:placetype":"venue"
},
  "geometry": {"coordinates":[2.8141539097,51.1833496094],"type":"Point"}
}