{
  "type": "Feature",
  "properties": {
    "iso:country":"BE",
    "sg:address":"Burgemeester Bertenplein 35",
    "sg:city":"Poperinge",
    "sg:classifiers":[
        {
            "category":"Cafe",
            "type":"Food & Drink"
        }
    ],
    "sg:phone":"+32 57 33 50 42",
    "sg:postcode":"8970",
    "sg:province":"West-Vlaanderen",
    "sg:tags":[
        "caf\u00e9s"
    ],
    "wof:name":"M.c. Decaesteker",
    "wof:placetype":"venue"
},
  "geometry": {"coordinates":[2.7245869637,50.8534698486],"type":"Point"}
}