{
  "type": "Feature",
  "properties": {
    "addr:full":"Stationsstraat 62 Aalst (gijzegem) Oost-Vlaanderen 9308",
    "addr:housenumber":"62",
    "addr:postcode":"9308",
    "addr:street":"Stationsstraat",
    "iso:country":"BE",
    "sg:address":"Stationsstraat 62",
    "sg:city":"Aalst (gijzegem)",
    "sg:classifiers":[
        {
            "category":"Bars & Pubs",
            "type":"Food & Drink"
        }
    ],
    "sg:phone":"+32 53 78 04 11",
    "sg:postcode":"9308",
    "sg:province":"Oost-Vlaanderen",
    "wof:name":"Uil (den)",
    "wof:placetype":"venue"
},
  "geometry": {"coordinates":[4.0347590446,50.9603500366],"type":"Point"}
}