{
  "type": "Feature",
  "properties": {
    "addr:full":"Rue Pont-\u00c0-la-faulx 14 P\u00c9ruwelz Hainaut 7600",
    "addr:housenumber":"14",
    "addr:postcode":"7600",
    "addr:street":"Rue Pont-A\u0300-La-Faulx",
    "iso:country":"BE",
    "sg:address":"Rue Pont-\u00c0-la-faulx 14",
    "sg:city":"P\u00c9ruwelz",
    "sg:orig_category":"Advocaten and juridische adviseurs",
    "sg:phone":"+32 69 78 08 00",
    "sg:postcode":"7600",
    "sg:province":"Hainaut",
    "wof:name":"St\u00c9phane Carlier",
    "wof:placetype":"venue"
},
  "geometry": {"coordinates":[3.5949709415,50.510635376],"type":"Point"}
}