{
  "type": "Feature",
  "properties": {
    "addr:full":"Avenue De La For\u00eat De Soignes 191 Rhode-saint-gen\u00e8se Vlaams-Brabant 1640",
    "addr:housenumber":"191",
    "addr:postcode":"rhode-saint-gene\u0300se;1640",
    "addr:street":"Avenue De La Fore\u0302T De Soignes",
    "iso:country":"BE",
    "sg:address":"Avenue De La For\u00eat De Soignes 191",
    "sg:city":"Rhode-saint-gen\u00e8se",
    "sg:classifiers":[
        {
            "category":"Home & Garden",
            "subcategory":"Building Materials",
            "type":"Retail Goods"
        }
    ],
    "sg:phone":"+32 2 380 99 44",
    "sg:postcode":"1640",
    "sg:province":"Vlaams-Brabant",
    "sg:tags":[
        "wall",
        "cupboard"
    ],
    "wof:name":"Kitchen Center Bvba",
    "wof:placetype":"venue"
},
  "geometry": {"coordinates":[4.3574647903,50.7460250854],"type":"Point"}
}