{
  "type": "Feature",
  "properties": {
    "addr:full":"Grand-rue 18 Froidchapelle (boussu-lez-walcourt) Hainaut 6440",
    "addr:housenumber":"18",
    "addr:postcode":"6440",
    "addr:street":"Grand-Rue",
    "iso:country":"BE",
    "sg:address":"Grand-rue 18",
    "sg:city":"Froidchapelle (boussu-lez-walcourt)",
    "sg:classifiers":[
        {
            "category":"Utilities",
            "subcategory":"Natural Gas",
            "type":"Services"
        }
    ],
    "sg:phone":"+32 71 63 33 15",
    "sg:postcode":"6440",
    "sg:province":"Hainaut",
    "sg:tags":[
        "industrial",
        "-"
    ],
    "wof:name":"Mme Depuis M",
    "wof:placetype":"venue"
},
  "geometry": {"coordinates":[4.37647295,50.2270965576],"type":"Point"}
}