{
  "type": "Feature",
  "properties": {
    "iso:country":"BE",
    "sg:address":"Avenue Jules Bruyr 7",
    "sg:city":"Gembloux-sur-orneau (gembloux)",
    "sg:classifiers":[
        {
            "category":"Building & Trades",
            "subcategory":"Cleaning & Sanitation",
            "type":"Services"
        }
    ],
    "sg:phone":"+32 81 61 66 24",
    "sg:postcode":"5030",
    "sg:province":"Namur",
    "sg:tags":[
        "cleaner",
        "window"
    ],
    "wof:name":"Ruszcyk A",
    "wof:placetype":"venue"
},
  "geometry": {"coordinates":[4.6957960129,50.549697876],"type":"Point"}
}