{
  "type": "Feature",
  "properties": {
    "iso:country":"BE",
    "sg:address":"Rue Des Bosseuses 32",
    "sg:city":"Mettet",
    "sg:orig_category":"Installatie van houten of kunststof schrijnwerk",
    "sg:phone":"+32 71 72 91 81",
    "sg:postcode":"5640",
    "sg:province":"Namur",
    "wof:name":"Albert Brouillard",
    "wof:placetype":"venue"
},
  "geometry": {"coordinates":[4.6460661888,50.3307495117],"type":"Point"}
}