{
  "type": "Feature",
  "properties": {
    "addr:full":"De Vri\u00c8restraat 52 Antwerpen Antwerpen 2000",
    "addr:housenumber":"52",
    "addr:postcode":"2000",
    "addr:street":"De Vrie\u0300Restraat",
    "iso:country":"BE",
    "sg:address":"De Vri\u00c8restraat 52",
    "sg:city":"Antwerpen",
    "sg:orig_category":"Vertalers and tolken",
    "sg:phone":"+32 3 248 64 74",
    "sg:postcode":"2000",
    "sg:province":"Antwerpen",
    "wof:name":"Wilsens International",
    "wof:placetype":"venue"
},
  "geometry": {"coordinates":[4.3976488113,51.208190918],"type":"Point"}
}