{
  "type": "Feature",
  "properties": {
    "iso:country":"BE",
    "sg:address":"Klapstraat 4",
    "sg:city":"Nazareth",
    "sg:classifiers":[
        {
            "category":"Building & Trades",
            "subcategory":"Cleaning & Sanitation",
            "type":"Services"
        }
    ],
    "sg:phone":"+32 9 385 43 94",
    "sg:postcode":"9810",
    "sg:province":"Oost-Vlaanderen",
    "sg:tags":[
        "equipment",
        "industrial",
        "maintenance"
    ],
    "wof:name":"A.t.l. Service Bvba",
    "wof:placetype":"venue"
},
  "geometry": {"coordinates":[3.6130890846,50.979385376],"type":"Point"}
}