{
  "type": "Feature",
  "properties": {
    "iso:country":"BE",
    "sg:address":"Noorderlaan 151",
    "sg:city":"Antwerpen",
    "sg:orig_category":"Produits chimiques Mat\u00e9riaux de construction Gr",
    "sg:phone":"+32 3 543 90 20",
    "sg:postcode":"2030",
    "sg:province":"Antwerpen",
    "wof:name":"Intermark Service",
    "wof:placetype":"venue"
},
  "geometry": {"coordinates":[4.3973817825,51.2644195557],"type":"Point"}
}