{
  "type": "Feature",
  "properties": {
    "addr:full":"Kasteelbrakelsesteenweg 718 Halle Vlaams-Brabant 1500",
    "addr:housenumber":"718",
    "addr:postcode":"1500",
    "addr:street":"Kasteelbrakelsesteenweg",
    "iso:country":"BE",
    "sg:address":"Kasteelbrakelsesteenweg 718",
    "sg:city":"Halle",
    "sg:orig_category":"Entretien and r\u00e9parations de voitures",
    "sg:phone":"+32 2 361 58 08",
    "sg:postcode":"1500",
    "sg:province":"Vlaams-Brabant",
    "wof:name":"Wim Vanderheyden",
    "wof:placetype":"venue"
},
  "geometry": {"coordinates":[4.2627792358,50.7003135681],"type":"Point"}
}