{
  "type": "Feature",
  "properties": {
    "iso:country":"BE",
    "sg:address":"Oudeheerwegruiter 183",
    "sg:city":"Waasmunster",
    "sg:orig_category":"Bouwmaterialen Gh IJzerwaren, bouw- and verfmaterialen Loodgieterij, verwarming and sanitaire instal",
    "sg:phone":"+32 9 348 47 87",
    "sg:postcode":"9250",
    "sg:province":"Oost-Vlaanderen",
    "wof:name":"Sani- & Keukendecor",
    "wof:placetype":"venue"
},
  "geometry": {"coordinates":[4.0365800858,51.1163482666],"type":"Point"}
}