{
  "type": "Feature",
  "properties": {
    "iso:country":"BE",
    "sg:address":"Rue Lambert Etienne 32",
    "sg:city":"Ciney",
    "sg:orig_category":"Reliure and finition",
    "sg:phone":"+32 83 21 53 42",
    "sg:postcode":"5590",
    "sg:province":"Namur",
    "wof:name":"Isabelle Jadot",
    "wof:placetype":"venue"
},
  "geometry": {"coordinates":[5.0946788788,50.2975616455],"type":"Point"}
}