{
  "type": "Feature",
  "properties": {
    "addr:full":"Nieuwstraat 31 Asse Vlaams-Brabant 1730",
    "addr:housenumber":"31",
    "addr:postcode":"1730",
    "addr:street":"Nieuwstraat",
    "iso:country":"BE",
    "sg:address":"Nieuwstraat 31",
    "sg:city":"Asse",
    "sg:classifiers":[
        {
            "category":"Building & Trades",
            "subcategory":"Pest Control",
            "type":"Services"
        }
    ],
    "sg:phone":"+32 2 452 68 55",
    "sg:postcode":"1730",
    "sg:province":"Vlaams-Brabant",
    "sg:tags":[
        "painting",
        "contractor"
    ],
    "wof:name":"Pollet & Zonen Bvba",
    "wof:placetype":"venue"
},
  "geometry": {"coordinates":[4.1951379776,50.9108810425],"type":"Point"}
}