{
  "type": "Feature",
  "properties": {
    "addr:full":"Barastraat 131 Brussel Bruxelles-Capitale 1070",
    "addr:housenumber":"131",
    "addr:postcode":"1070",
    "addr:street":"Barastraat",
    "iso:country":"BE",
    "sg:address":"Barastraat 131",
    "sg:city":"Brussel",
    "sg:classifiers":[
        {
            "category":"Building & Trades",
            "subcategory":"Landfill",
            "type":"Services"
        }
    ],
    "sg:phone":"+32 2 522 79 95",
    "sg:postcode":"1070",
    "sg:province":"Bruxelles-Capitale",
    "sg:tags":[
        "leather",
        "industry",
        "leatherware"
    ],
    "wof:name":"Eurocuir Nv",
    "wof:placetype":"venue"
},
  "geometry": {"coordinates":[4.3300309181,50.8349227905],"type":"Point"}
}