{
  "type": "Feature",
  "properties": {
    "iso:country":"BE",
    "sg:address":"Bouwensstraat 37",
    "sg:city":"Antwerpen (borgerhout)",
    "sg:classifiers":[
        {
            "category":"Sports & Exercise",
            "subcategory":"Gym",
            "type":"Entertainment"
        }
    ],
    "sg:phone":"+32 3 206 72 83",
    "sg:postcode":"2140",
    "sg:province":"Antwerpen",
    "sg:tags":[
        "fitness"
    ],
    "wof:name":"Center Court Fitness & Squash",
    "wof:placetype":"venue"
},
  "geometry": {"coordinates":[4.4332199097,51.2137565613],"type":"Point"}
}