{
  "type": "Feature",
  "properties": {
    "addr:full":"Rue De Tournai 8 Tournai Hainaut 7520",
    "addr:housenumber":"8",
    "addr:postcode":"7520",
    "addr:street":"Rue De Tournai",
    "iso:country":"BE",
    "sg:address":"Rue De Tournai 8",
    "sg:city":"Tournai",
    "sg:orig_category":"Kapsalons",
    "sg:phone":"+32 69 35 12 72",
    "sg:postcode":"7520",
    "sg:province":"Hainaut",
    "wof:name":"Coif'actuel",
    "wof:placetype":"venue"
},
  "geometry": {"coordinates":[3.2939870358,50.6405181885],"type":"Point"}
}