{
  "type": "Feature",
  "properties": {
    "addr:full":"Turnhoutseweg 14ba Baarle-hertog Antwerpen 2387",
    "addr:housenumber":"14ba",
    "addr:postcode":"2387",
    "addr:street":"Turnhoutseweg",
    "iso:country":"BE",
    "sg:address":"Turnhoutseweg 14ba",
    "sg:city":"Baarle-hertog",
    "sg:orig_category":"Etalage- and showroomontwerpers",
    "sg:phone":"+32 14 69 97 71",
    "sg:postcode":"2387",
    "sg:province":"Antwerpen",
    "wof:name":"Karel Verbeek",
    "wof:placetype":"venue"
},
  "geometry": {"coordinates":[4.9311170578,51.4342346191],"type":"Point"}
}