{
  "type": "Feature",
  "properties": {
    "addr:full":"Kegelslei 2ba Sint-katelijne-waver Antwerpen 2861",
    "addr:housenumber":"2ba",
    "addr:postcode":"2861",
    "addr:street":"Kegelslei",
    "iso:country":"BE",
    "sg:address":"Kegelslei 2ba",
    "sg:city":"Sint-katelijne-waver",
    "sg:orig_category":"Producteurs de l\u00e9gumes",
    "sg:phone":"+32 15 75 63 95",
    "sg:postcode":"2861",
    "sg:province":"Antwerpen",
    "wof:name":"Herman Jacobs",
    "wof:placetype":"venue"
},
  "geometry": {"coordinates":[4.5831160545,51.0552330017],"type":"Point"}
}