{
  "type": "Feature",
  "properties": {
    "iso:country":"BE",
    "sg:address":"Xavier De Cocklaan 36",
    "sg:city":"Sint-martens-latem",
    "sg:orig_category":"Sportclubs",
    "sg:phone":"+32 9 282 54 96",
    "sg:postcode":"9831",
    "sg:province":"Oost-Vlaanderen",
    "wof:name":"Sportgroep Godefroot",
    "wof:placetype":"venue"
},
  "geometry": {"coordinates":[3.6115190983,50.9998588562],"type":"Point"}
}