{
  "type": "Feature",
  "properties": {
    "addr:full":"Kerkomdorp 53 Sint-truiden Limburg 3800",
    "addr:housenumber":"53",
    "addr:postcode":"3800",
    "addr:street":"Kerkomdorp",
    "iso:country":"BE",
    "sg:address":"Kerkomdorp 53",
    "sg:city":"Sint-truiden",
    "sg:orig_category":"Eleveurs and marchands de porcs",
    "sg:phone":"+32 11 68 72 18",
    "sg:postcode":"3800",
    "sg:province":"Limburg",
    "wof:name":"Karel Masco",
    "wof:placetype":"venue"
},
  "geometry": {"coordinates":[5.1754989624,50.7748908997],"type":"Point"}
}