{
  "type": "Feature",
  "properties": {
    "iso:country":"BE",
    "sg:address":"Rue Elise 92",
    "sg:city":"Elsene/ixelles",
    "sg:orig_category":"Informaticaconsulenten Software ontwikkeling and ontwerp",
    "sg:phone":"+32 2 646 67 65",
    "sg:postcode":"1050",
    "sg:province":"Bruxelles-Capitale",
    "wof:name":"Inzenet",
    "wof:placetype":"venue"
},
  "geometry": {"coordinates":[4.3831338882,50.8175582886],"type":"Point"}
}