{
  "type": "Feature",
  "properties": {
    "addr:full":"Zijdelingsestr 54 Tienen Vlaams-Brabant 3300",
    "addr:housenumber":"54",
    "addr:postcode":"3300",
    "addr:street":"Zijdelingsestr",
    "iso:country":"BE",
    "sg:address":"Zijdelingsestr 54",
    "sg:city":"Tienen",
    "sg:orig_category":"Finished goods - metallic Industrial vehicles Metallurgy and Metalworking Motor-cars Tools Vehicles ",
    "sg:phone":"+32 16 82 20 00",
    "sg:postcode":"3300",
    "sg:province":"Vlaams-Brabant",
    "wof:name":"Verbol Nv",
    "wof:placetype":"venue"
},
  "geometry": {"coordinates":[4.9231557846,50.811252594],"type":"Point"}
}