{
  "type": "Feature",
  "properties": {
    "addr:full":"Chauss\u00c9e De Brunehault 52 Herstal Li\u00e8ge 4041",
    "addr:housenumber":"52",
    "addr:postcode":"4041",
    "addr:street":"Chausse\u0301E De Brunehault",
    "iso:country":"BE",
    "sg:address":"Chauss\u00c9e De Brunehault 52",
    "sg:city":"Herstal",
    "sg:orig_category":"Boekhandels",
    "sg:phone":"+32 4 227 30 76",
    "sg:postcode":"4041",
    "sg:province":"Li\u00e8ge",
    "wof:name":"Marie Joirkin",
    "wof:placetype":"venue"
},
  "geometry": {"coordinates":[5.5830597878,50.6788482666],"type":"Point"}
}