{
  "type": "Feature",
  "properties": {
    "addr:full":"Oostendse Steenweg 243 Brugge West-Vlaanderen 8000",
    "addr:housenumber":"243",
    "addr:postcode":"8000",
    "addr:street":"Oostendse Steenweg",
    "iso:country":"BE",
    "sg:address":"Oostendse Steenweg 243",
    "sg:city":"Brugge",
    "sg:orig_category":"Boomkwekerijen",
    "sg:phone":"+32 50 31 19 60",
    "sg:postcode":"8000",
    "sg:province":"West-Vlaanderen",
    "wof:name":"Denis Stroo",
    "wof:placetype":"venue"
},
  "geometry": {"coordinates":[3.1826519966,51.2341957092],"type":"Point"}
}