{
  "type": "Feature",
  "properties": {
    "iso:country":"BE",
    "sg:address":"Holenteerstraat 2",
    "sg:city":"Tongeren",
    "sg:classifiers":[
        {
            "category":"Health Services",
            "subcategory":"Doctor",
            "type":"Services"
        }
    ],
    "sg:phone":"+32 12 39 54 24",
    "sg:postcode":"3700",
    "sg:province":"Limburg",
    "sg:tags":[
        "medicinephysicians",
        "surgeon"
    ],
    "wof:name":"D'hondt Bruno",
    "wof:placetype":"venue"
},
  "geometry": {"coordinates":[5.4452209473,50.7752227783],"type":"Point"}
}