{
  "type": "Feature",
  "properties": {
    "iso:country":"BE",
    "sg:address":"Grand Route 62",
    "sg:city":"Crisnee",
    "sg:classifiers":[
        {
            "category":"Fast Food",
            "type":"Food & Drink"
        }
    ],
    "sg:phone":"+32 4 257 41 41",
    "sg:postcode":"4367",
    "sg:province":"Li\u00e8ge",
    "sg:tags":[
        "caf\u00e9s",
        "meeneem",
        "restaurant"
    ],
    "wof:name":"Le B'tisier",
    "wof:placetype":"venue"
},
  "geometry": {"coordinates":[5.4013671875,50.7079124451],"type":"Point"}
}