{
  "type": "Feature",
  "properties": {
    "iso:country":"BE",
    "sg:address":"Dr\u00e8ve Emmanuelle 15",
    "sg:city":"Genappe (bousval)",
    "sg:classifiers":[
        {
            "category":"Professional",
            "subcategory":"Management & Consulting",
            "type":"Services"
        }
    ],
    "sg:phone":"+32 10 61 54 06",
    "sg:postcode":"1470",
    "sg:province":"Brabant Wallon",
    "sg:tags":[
        "-",
        "processing",
        "data",
        "consultant"
    ],
    "wof:name":"A.q.s.",
    "wof:placetype":"venue"
},
  "geometry": {"coordinates":[4.5373301506,50.6440505981],"type":"Point"}
}