{
  "type": "Feature",
  "properties": {
    "addr:full":"Kortrijksesteenweg 14c Sint-martens-latem Oost-Vlaanderen 9830",
    "addr:housenumber":"14c",
    "addr:postcode":"9830",
    "addr:street":"Kortrijksesteenweg",
    "iso:country":"BE",
    "sg:address":"Kortrijksesteenweg 14c",
    "sg:city":"Sint-martens-latem",
    "sg:classifiers":[
        {
            "category":"Wholesale",
            "subcategory":"Construction Materials",
            "type":"Manufacturing & Wholesale Goods"
        }
    ],
    "sg:phone":"+32 9 280 95 70",
    "sg:postcode":"9830",
    "sg:province":"Oost-Vlaanderen",
    "sg:tags":[
        "tubing",
        "industrial"
    ],
    "wof:name":"Vma Contracting",
    "wof:placetype":"venue"
},
  "geometry": {"coordinates":[3.6475069523,51.0141334534],"type":"Point"}
}