{
  "type": "Feature",
  "properties": {
    "addr:full":"Avenue De La Salm 37 Vielsalm Luxembourg 6690",
    "addr:housenumber":"37",
    "addr:postcode":"6690",
    "addr:street":"Avenue De La Salm",
    "iso:country":"BE",
    "sg:address":"Avenue De La Salm 37",
    "sg:city":"Vielsalm",
    "sg:orig_category":"Articles de camping and de sport. Chaussures",
    "sg:phone":"+32 80 21 68 94",
    "sg:postcode":"6690",
    "sg:province":"Luxembourg",
    "wof:name":"Chaussures Monique Et Francis Sport",
    "wof:placetype":"venue"
},
  "geometry": {"coordinates":[5.9120578766,50.2801933289],"type":"Point"}
}