{
  "type": "Feature",
  "properties": {
    "addr:full":"Wezelbaan 46 Diest Vlaams-Brabant 3290",
    "addr:housenumber":"46",
    "addr:postcode":"3290",
    "addr:street":"Wezelbaan",
    "iso:country":"BE",
    "sg:address":"Wezelbaan 46",
    "sg:city":"Diest",
    "sg:orig_category":"Herstellingen and onderhoud van auto's Voertuigen",
    "sg:phone":"+32 13 32 77 93",
    "sg:postcode":"3290",
    "sg:province":"Vlaams-Brabant",
    "wof:name":"N.e.c. Cars",
    "wof:placetype":"venue"
},
  "geometry": {"coordinates":[5.0890197754,51.0010910034],"type":"Point"}
}