{
  "type": "Feature",
  "properties": {
    "addr:full":"Geraardsbergsestraat 70 Ninove Oost-Vlaanderen 9400",
    "addr:housenumber":"70",
    "addr:postcode":"9400",
    "addr:street":"Geraardsbergsestraat",
    "iso:country":"BE",
    "sg:address":"Geraardsbergsestraat 70",
    "sg:city":"Ninove",
    "sg:classifiers":[
        {
            "category":"Food & Beverages",
            "subcategory":"Fruits & Vegetables",
            "type":"Retail Goods"
        }
    ],
    "sg:phone":"+32 54 33 37 65",
    "sg:postcode":"9400",
    "sg:province":"Oost-Vlaanderen",
    "sg:tags":[
        "l\u00e9gumes"
    ],
    "wof:name":"Etienne D'herde",
    "wof:placetype":"venue"
},
  "geometry": {"coordinates":[3.9601540565,50.8616714478],"type":"Point"}
}