{
  "type": "Feature",
  "properties": {
    "addr:full":"Rue Des Cayats 82 Charleroi Hainaut 6001",
    "addr:housenumber":"82",
    "addr:postcode":"6001",
    "addr:street":"Rue Des Cayats;Hainaut",
    "iso:country":"BE",
    "sg:address":"Rue Des Cayats 82",
    "sg:city":"Charleroi",
    "sg:classifiers":[
        {
            "category":"Autos & Motor Vehicles",
            "subcategory":"Fuel & Gas Station",
            "type":"Retail Goods"
        }
    ],
    "sg:phone":"+32 71 47 08 80",
    "sg:postcode":"6001",
    "sg:province":"Hainaut",
    "sg:tags":[
        "stations-service",
        "carburants"
    ],
    "wof:name":"Guru International",
    "wof:placetype":"venue"
},
  "geometry": {"coordinates":[4.4420552254,50.3918037415],"type":"Point"}
}