{
  "type": "Feature",
  "properties": {
    "addr:full":"Avenue Emile Vandervelde 23 Sint-lambrechts-woluwe/woluwe-saint-lambert Bruxelles-Capitale 1200",
    "addr:housenumber":"23",
    "addr:postcode":"1200",
    "addr:street":"Avenue Emile Vandervelde",
    "iso:country":"BE",
    "sg:address":"Avenue Emile Vandervelde 23",
    "sg:city":"Sint-lambrechts-woluwe/woluwe-saint-lambert",
    "sg:orig_category":"Auto-\u00e9coles",
    "sg:phone":"+32 2 733 18 33",
    "sg:postcode":"1200",
    "sg:province":"Bruxelles-Capitale",
    "wof:name":"Auto-ecole Stop",
    "wof:placetype":"venue"
},
  "geometry": {"coordinates":[4.4414300919,50.8470993042],"type":"Point"}
}