{
  "type": "Feature",
  "properties": {
    "iso:country":"BE",
    "sg:address":"Fr\u00e4iheetswee 4",
    "sg:city":"Attert",
    "sg:classifiers":[
        {
            "category":"Building & Trades",
            "subcategory":"Pest Control",
            "type":"Services"
        }
    ],
    "sg:phone":"+32 63 21 80 73",
    "sg:postcode":"6717",
    "sg:province":"Luxembourg",
    "sg:tags":[
        "painting",
        "contractor"
    ],
    "wof:name":"Top D\u00e9cor-mortier M",
    "wof:placetype":"venue"
},
  "geometry": {"coordinates":[5.7888741493,49.7506217957],"type":"Point"}
}