{
  "type": "Feature",
  "properties": {
    "addr:full":"Ruisstraat 56 Temse (tielrode) Oost-Vlaanderen 9140",
    "addr:housenumber":"56",
    "addr:postcode":"9140",
    "addr:street":"Ruisstraat",
    "iso:country":"BE",
    "sg:address":"Ruisstraat 56",
    "sg:city":"Temse (tielrode)",
    "sg:classifiers":[
        {
            "category":"Wholesale",
            "subcategory":"Furniture",
            "type":"Manufacturing & Wholesale Goods"
        }
    ],
    "sg:phone":"+32 3 771 13 17",
    "sg:postcode":"9140",
    "sg:province":"Oost-Vlaanderen",
    "sg:tags":[
        "-",
        "collectivities"
    ],
    "wof:name":"Galle M",
    "wof:placetype":"venue"
},
  "geometry": {"coordinates":[4.184732914,51.1191749573],"type":"Point"}
}