{
  "type": "Feature",
  "properties": {
    "addr:full":"Nieuwstraat 30 Lummen Limburg 3560",
    "addr:housenumber":"30",
    "addr:postcode":"3560",
    "addr:street":"Nieuwstraat",
    "iso:country":"BE",
    "sg:address":"Nieuwstraat 30",
    "sg:city":"Lummen",
    "sg:classifiers":[
        {
            "category":"Home & Garden",
            "subcategory":"Carpets & Floor Coverings",
            "type":"Retail Goods"
        }
    ],
    "sg:phone":"+32 11 42 84 91",
    "sg:postcode":"3560",
    "sg:province":"Limburg",
    "sg:tags":[
        "layer",
        "mosaicists"
    ],
    "wof:name":"Poels A",
    "wof:placetype":"venue"
},
  "geometry": {"coordinates":[5.2253689766,51.0113182068],"type":"Point"}
}