{
  "type": "Feature",
  "properties": {
    "iso:country":"BE",
    "sg:address":"Rue Joseph Bouch\u00c9 20",
    "sg:city":"Eghezee",
    "sg:orig_category":"Rundveehouders",
    "sg:phone":"+32 81 81 14 18",
    "sg:postcode":"5310",
    "sg:province":"Namur",
    "wof:name":"Jean-pol Corroy",
    "wof:placetype":"venue"
},
  "geometry": {"coordinates":[4.9169478416,50.60729599],"type":"Point"}
}