{
  "type": "Feature",
  "properties": {
    "iso:country":"BE",
    "sg:address":"Rue De Grupont 40",
    "sg:city":"Tellin",
    "sg:orig_category":"Eleveurs de bovins",
    "sg:phone":"+32 84 36 69 30",
    "sg:postcode":"6927",
    "sg:province":"Luxembourg",
    "wof:name":"Pierre Volvert",
    "wof:placetype":"venue"
},
  "geometry": {"coordinates":[5.2634291649,50.0898704529],"type":"Point"}
}