{
  "type": "Feature",
  "properties": {
    "iso:country":"BE",
    "sg:address":"Antwerpsestraat 52",
    "sg:city":"Boom",
    "sg:orig_category":"Plomberie, chauffage and installations sanitaires. Meubles D\u00e9taillants, Am\u00e9nagement de B\u00e2timents et ",
    "sg:phone":"+32 3 888 00 83",
    "sg:postcode":"2850",
    "sg:province":"Antwerpen",
    "wof:name":"Johnny Van Breedam",
    "wof:placetype":"venue"
},
  "geometry": {"coordinates":[4.3657059669,51.0880012512],"type":"Point"}
}