{
  "type": "Feature",
  "properties": {
    "addr:full":"Rue De Fleurus 27 Farciennes Hainaut 6240",
    "addr:housenumber":"27",
    "addr:postcode":"6240",
    "addr:street":"Rue De Fleurus",
    "iso:country":"BE",
    "sg:address":"Rue De Fleurus 27",
    "sg:city":"Farciennes",
    "sg:orig_category":"Entretien and r\u00e9parations de voitures",
    "sg:phone":"+32 71 38 22 47",
    "sg:postcode":"6240",
    "sg:province":"Hainaut",
    "wof:name":"D. Finet",
    "wof:placetype":"venue"
},
  "geometry": {"coordinates":[4.5307331085,50.4468536377],"type":"Point"}
}