{
  "type": "Feature",
  "properties": {
    "addr:full":"Parkln 56 Turnhout Antwerpen 2300",
    "addr:housenumber":"56",
    "addr:postcode":"2300",
    "addr:street":"Parkln",
    "iso:country":"BE",
    "sg:address":"Parkln 56",
    "sg:city":"Turnhout",
    "sg:classifiers":[
        {
            "category":"Travel",
            "subcategory":"Hotels & Motels",
            "type":"Entertainment"
        }
    ],
    "sg:phone":"+32 14 43 87 87",
    "sg:postcode":"2300",
    "sg:province":"Antwerpen",
    "sg:tags":[
        "hotels",
        "business",
        "restaurant"
    ],
    "wof:name":"Stadspark Nv",
    "wof:placetype":"venue"
},
  "geometry": {"coordinates":[4.9502749443,51.3175506592],"type":"Point"}
}