{
  "type": "Feature",
  "properties": {
    "iso:country":"BE",
    "sg:address":"Rue Des Epingliers 18",
    "sg:city":"Mons",
    "sg:orig_category":"Opticiens",
    "sg:phone":"+32 65 31 76 92",
    "sg:postcode":"7000",
    "sg:province":"Hainaut",
    "wof:name":"Henri Scoubeau",
    "wof:placetype":"venue"
},
  "geometry": {"coordinates":[3.9545269012,50.4531135559],"type":"Point"}
}