{
  "type": "Feature",
  "properties": {
    "addr:full":"Abrahamstraat 7 Riemst (zichen-zussen-bolder) Limburg 3770",
    "addr:housenumber":"7",
    "addr:postcode":"3770",
    "addr:street":"Abrahamstraat",
    "iso:country":"BE",
    "sg:address":"Abrahamstraat 7",
    "sg:city":"Riemst (zichen-zussen-bolder)",
    "sg:classifiers":[
        {
            "category":"Health Services",
            "subcategory":"Health Practitioner",
            "type":"Services"
        }
    ],
    "sg:phone":"+32 12 45 24 65",
    "sg:postcode":"3770",
    "sg:province":"Limburg",
    "sg:tags":[
        "physiotherapist"
    ],
    "wof:name":"Christiaens H",
    "wof:placetype":"venue"
},
  "geometry": {"coordinates":[5.5969901085,50.8109016418],"type":"Point"}
}