{
  "type": "Feature",
  "properties": {
    "addr:full":"Veldstraat 13 Antwerpen Antwerpen 2060",
    "addr:housenumber":"13",
    "addr:postcode":"2060",
    "addr:street":"Veldstraat",
    "iso:country":"BE",
    "sg:address":"Veldstraat 13",
    "sg:city":"Antwerpen",
    "sg:classifiers":[
        {
            "category":"Organizations",
            "subcategory":"Community Association",
            "type":"Services"
        }
    ],
    "sg:phone":"+32 3 236 57 95",
    "sg:postcode":"2060",
    "sg:province":"Antwerpen",
    "sg:tags":[
        "cultural"
    ],
    "wof:name":"Provinciale Federatie Antwerpse Karnavalvrienden",
    "wof:placetype":"venue"
},
  "geometry": {"coordinates":[4.4309258461,51.2253875732],"type":"Point"}
}