{
  "type": "Feature",
  "properties": {
    "addr:full":"Rue De Brimez 240 Namur (w\u00e9pion) Namur 5100",
    "addr:housenumber":"240",
    "addr:postcode":"5100",
    "addr:street":"Rue De Brimez",
    "iso:country":"BE",
    "sg:address":"Rue De Brimez 240",
    "sg:city":"Namur (w\u00e9pion)",
    "sg:classifiers":[
        {
            "category":"Health Services",
            "subcategory":"Doctor",
            "type":"Services"
        }
    ],
    "sg:phone":"+32 81 46 15 14",
    "sg:postcode":"5100",
    "sg:province":"Namur",
    "sg:tags":[
        "medicinephysicians",
        "surgeon"
    ],
    "wof:name":"Fox A",
    "wof:placetype":"venue"
},
  "geometry": {"coordinates":[4.8605489731,50.4116744995],"type":"Point"}
}