{
  "type": "Feature",
  "properties": {
    "iso:country":"BE",
    "sg:address":"Duinbergenlaan 109",
    "sg:city":"Knokke-heist",
    "sg:orig_category":"Immobili\u00ebnkantoren Projectontwikkelaars",
    "sg:phone":"+32 50 51 84 51",
    "sg:postcode":"8301",
    "sg:province":"West-Vlaanderen",
    "wof:name":"Stone Group",
    "wof:placetype":"venue"
},
  "geometry": {"coordinates":[3.2586500645,51.3440818787],"type":"Point"}
}