{
  "type": "Feature",
  "properties": {
    "addr:full":"Keyserlei 42 Antwerpen Antwerpen 2018",
    "addr:housenumber":"42",
    "addr:postcode":"2018",
    "addr:street":"Keyserlei",
    "iso:country":"BE",
    "sg:address":"Keyserlei 42",
    "sg:city":"Antwerpen",
    "sg:orig_category":"Herstelling horloges and juwelen Juwelen and horloges",
    "sg:phone":"+32 3 213 50 81",
    "sg:postcode":"2018",
    "sg:province":"Antwerpen",
    "wof:name":"Slaets",
    "wof:placetype":"venue"
},
  "geometry": {"coordinates":[4.4183030128,51.2174263],"type":"Point"}
}