{
  "type": "Feature",
  "properties": {
    "addr:full":"Place Du Ballon 35 Charleroi Hainaut 6040",
    "addr:housenumber":"35",
    "addr:postcode":"6040",
    "addr:street":"Place Du Ballon;Hainaut",
    "iso:country":"BE",
    "sg:address":"Place Du Ballon 35",
    "sg:city":"Charleroi",
    "sg:classifiers":[
        {
            "category":"Fast Food",
            "type":"Food & Drink"
        }
    ],
    "sg:phone":"+32 71 34 20 72",
    "sg:postcode":"6040",
    "sg:province":"Hainaut",
    "sg:tags":[
        "\u00c0",
        "emporter",
        "restaurants"
    ],
    "wof:name":"Friterie J.r. Burger",
    "wof:placetype":"venue"
},
  "geometry": {"coordinates":[4.4142842293,50.4349746704],"type":"Point"}
}