{
  "type": "Feature",
  "properties": {
    "iso:country":"BE",
    "sg:address":"Philip De Pillecijnlaan 10",
    "sg:city":"Rumst (reet)",
    "sg:classifiers":[
        {
            "category":"Health Services",
            "subcategory":"Health Practitioner",
            "type":"Services"
        }
    ],
    "sg:phone":"+32 3 888 47 78",
    "sg:postcode":"2840",
    "sg:province":"Antwerpen",
    "sg:tags":[
        "alternative",
        "therapy",
        "treatment"
    ],
    "wof:name":"Reusens C",
    "wof:placetype":"venue"
},
  "geometry": {"coordinates":[4.3647837639,51.1085739136],"type":"Point"}
}