{
  "type": "Feature",
  "properties": {
    "iso:country":"BE",
    "sg:address":"Alfons Pieterslaan 100",
    "sg:city":"Oostende",
    "sg:classifiers":[
        {
            "category":"Retail",
            "subcategory":"Repair Shop",
            "type":"Services"
        }
    ],
    "sg:phone":"+32 59 80 28 48",
    "sg:postcode":"8400",
    "sg:province":"West-Vlaanderen",
    "sg:tags":[
        "photographic",
        "equipment",
        "-",
        "accessory"
    ],
    "wof:name":"Tuyttens Top Camera",
    "wof:placetype":"venue"
},
  "geometry": {"coordinates":[2.9108378887,51.2250099182],"type":"Point"}
}