{
  "type": "Feature",
  "properties": {
    "iso:country":"BE",
    "sg:address":"Rue Les Communes 29a",
    "sg:city":"Amay (ombret-rawsa)",
    "sg:classifiers":[
        {
            "category":"Health Services",
            "subcategory":"Doctor",
            "type":"Services"
        }
    ],
    "sg:phone":"+32 85 31 82 05",
    "sg:postcode":"4540",
    "sg:province":"Li\u00e8ge",
    "sg:tags":[
        "medicinephysicians",
        "surgeon"
    ],
    "wof:name":"Fouarge Pascale",
    "wof:placetype":"venue"
},
  "geometry": {"coordinates":[5.3325810432,50.5350952148],"type":"Point"}
}