{
  "type": "Feature",
  "properties": {
    "iso:country":"BE",
    "sg:address":"Hundelgemsesteenweg 258",
    "sg:city":"Merelbeke (groot)",
    "sg:orig_category":"Kapsalons",
    "sg:phone":"+32 9 230 56 91",
    "sg:postcode":"9820",
    "sg:province":"Oost-Vlaanderen",
    "wof:name":"Haarmode",
    "wof:placetype":"venue"
},
  "geometry": {"coordinates":[3.7525269985,51.0148200989],"type":"Point"}
}