{
  "type": "Feature",
  "properties": {
    "iso:country":"BE",
    "sg:address":"Houba De Strooperlaan 152",
    "sg:city":"Laeken",
    "sg:orig_category":"Arrivero",
    "sg:phone":"+32 2 478 95 00",
    "sg:postcode":"1020",
    "sg:province":"Bruxelles-Capitale",
    "wof:name":"Arrivero",
    "wof:placetype":"venue"
},
  "geometry": {"coordinates":[4.3370537758,50.8898887634],"type":"Point"}
}