{
  "type": "Feature",
  "properties": {
    "addr:full":"Brusselsesteenweg 644 Asse Vlaams-Brabant 1731",
    "addr:housenumber":"644",
    "addr:postcode":"1731",
    "addr:street":"Brusselsesteenweg",
    "iso:country":"BE",
    "sg:address":"Brusselsesteenweg 644",
    "sg:city":"Asse",
    "sg:orig_category":"Postkantoren Verzekeringsmakelaars and experts",
    "sg:phone":"+32 2 466 74 62",
    "sg:postcode":"1731",
    "sg:province":"Vlaams-Brabant",
    "wof:name":"De Post",
    "wof:placetype":"venue"
},
  "geometry": {"coordinates":[4.2767801285,50.882598877],"type":"Point"}
}