{
  "type": "Feature",
  "properties": {
    "iso:country":"BE",
    "sg:address":"Rue Malmaison 144",
    "sg:city":"Gembloux",
    "sg:orig_category":"Eleveurs de bovins",
    "sg:phone":"+32 81 56 83 68",
    "sg:postcode":"5032",
    "sg:province":"Namur",
    "wof:name":"Godfrind H. & A.",
    "wof:placetype":"venue"
},
  "geometry": {"coordinates":[4.738424778,50.5091285706],"type":"Point"}
}