{
  "type": "Feature",
  "properties": {
    "iso:country":"BE",
    "sg:address":"Gladiolenlaan 19",
    "sg:city":"Liedekerke",
    "sg:orig_category":"Boucheries",
    "sg:phone":"+32 53 66 60 50",
    "sg:postcode":"1770",
    "sg:province":"Vlaams-Brabant",
    "wof:name":"Hubert Pletinckx",
    "wof:placetype":"venue"
},
  "geometry": {"coordinates":[4.1098918915,50.8591079712],"type":"Point"}
}