{
  "type": "Feature",
  "properties": {
    "iso:country":"BE",
    "sg:address":"Rue La Chapelle Saint-donat 24",
    "sg:city":"Namur",
    "sg:orig_category":"Instituts de beaut\u00e9. Formation permanente",
    "sg:phone":"+32 81 73 02 15",
    "sg:postcode":"5002",
    "sg:province":"Namur",
    "wof:name":"Ecole Esth\u00c9t.biolog.& Pedic.",
    "wof:placetype":"venue"
},
  "geometry": {"coordinates":[4.8538451195,50.4728813171],"type":"Point"}
}