{
  "type": "Feature",
  "properties": {
    "addr:full":"Rue Du Pressoir 58 Li\u00c8ge Li\u00e8ge 4000",
    "addr:housenumber":"58",
    "addr:postcode":"4000",
    "addr:street":"Rue Du Pressoir",
    "iso:country":"BE",
    "sg:address":"Rue Du Pressoir 58",
    "sg:city":"Li\u00c8ge",
    "sg:orig_category":"Artsen and specialisten",
    "sg:phone":"+32 4 252 36 24",
    "sg:postcode":"4000",
    "sg:province":"Li\u00e8ge",
    "wof:name":"Xavier Kurz",
    "wof:placetype":"venue"
},
  "geometry": {"coordinates":[5.5568699837,50.6160507202],"type":"Point"}
}