{
  "type": "Feature",
  "properties": {
    "iso:country":"BE",
    "sg:address":"Hoge Warande 10-1",
    "sg:city":"Malle",
    "sg:orig_category":"Notaires",
    "sg:phone":"+32 3 312 29 12",
    "sg:postcode":"2390",
    "sg:province":"Antwerpen",
    "wof:name":"G. Nouwkens",
    "wof:placetype":"venue"
},
  "geometry": {"coordinates":[4.7272410393,51.3022117615],"type":"Point"}
}