{
  "type": "Feature",
  "properties": {
    "iso:country":"BE",
    "sg:address":"Chee. De Gand 678",
    "sg:city":"Sint-jans-molenbeek/molenbeek-saint-jean",
    "sg:orig_category":"Motorfietsen",
    "sg:phone":"+32 2 465 25 88",
    "sg:postcode":"1080",
    "sg:province":"Bruxelles-Capitale",
    "wof:name":"N.vandenhoute",
    "wof:placetype":"venue"
},
  "geometry": {"coordinates":[4.3083481789,50.8596038818],"type":"Point"}
}