{
  "type": "Feature",
  "properties": {
    "addr:full":"Sint-paulusstraat 3 Oostende West-Vlaanderen 8400",
    "addr:housenumber":"3",
    "addr:postcode":"8400",
    "addr:street":"Sint-Paulusstraat",
    "iso:country":"BE",
    "sg:address":"Sint-paulusstraat 3",
    "sg:city":"Oostende",
    "sg:classifiers":[
        {
            "category":"Community Center",
            "subcategory":"Youth",
            "type":"Public Place"
        }
    ],
    "sg:phone":"+32 59 51 63 28",
    "sg:postcode":"8400",
    "sg:province":"West-Vlaanderen",
    "sg:tags":[
        "club"
    ],
    "wof:name":"Natuur 2000 Vlaamse Jeugdbond Voor Natuurstudie En Milieubehoud",
    "wof:placetype":"venue"
},
  "geometry": {"coordinates":[2.9178359509,51.2292098999],"type":"Point"}
}