{
  "type": "Feature",
  "properties": {
    "iso:country":"BE",
    "sg:address":"Koning Leopoldstraat 18",
    "sg:city":"Antwerpen (wilrijk)",
    "sg:classifiers":[
        {
            "category":"Manufacturing",
            "subcategory":"Paper Products",
            "type":"Manufacturing & Wholesale Goods"
        }
    ],
    "sg:phone":"+32 3 828 12 21",
    "sg:postcode":"2610",
    "sg:province":"Antwerpen",
    "sg:tags":[
        "flag",
        "banner"
    ],
    "wof:name":"Alferus Vlaggen",
    "wof:placetype":"venue"
},
  "geometry": {"coordinates":[4.4066619873,51.2150726318],"type":"Point"}
}