{
  "type": "Feature",
  "properties": {
    "iso:country":"BE",
    "sg:address":"Spijkstraat 1",
    "sg:city":"Gent",
    "sg:orig_category":"Zalen voor culturele evenementen",
    "sg:phone":"+32 9 238 24 90",
    "sg:postcode":"9000",
    "sg:province":"Oost-Vlaanderen",
    "wof:name":"Richard Foncke Gallery",
    "wof:placetype":"venue"
},
  "geometry": {"coordinates":[3.7412068844,51.0582885742],"type":"Point"}
}