{
  "type": "Feature",
  "properties": {
    "addr:full":"Chauss\u00c9e Brunehaut 15 Quevy Hainaut 7041",
    "addr:housenumber":"15",
    "addr:postcode":"7041",
    "addr:street":"Chausse\u0301E Brunehaut;Hainaut",
    "iso:country":"BE",
    "sg:address":"Chauss\u00c9e Brunehaut 15",
    "sg:city":"Quevy",
    "sg:orig_category":"Verplichte sociale verzekeringen",
    "sg:phone":"+32 65 58 72 04",
    "sg:postcode":"7041",
    "sg:province":"Hainaut",
    "wof:name":"Euromut",
    "wof:placetype":"venue"
},
  "geometry": {"coordinates":[4.0361337662,50.374584198],"type":"Point"}
}