{
  "type": "Feature",
  "properties": {
    "iso:country":"BE",
    "sg:address":"Passtraat 126",
    "sg:city":"Sint-niklaas",
    "sg:classifiers":[
        {
            "category":"Retail",
            "subcategory":"Auto Repair",
            "type":"Services"
        }
    ],
    "sg:phone":"+32 3 766 63 33",
    "sg:postcode":"9100",
    "sg:province":"Oost-Vlaanderen",
    "sg:tags":[
        "garage"
    ],
    "wof:name":"De Rudder",
    "wof:placetype":"venue"
},
  "geometry": {"coordinates":[4.1683630943,51.1707000732],"type":"Point"}
}