{
  "type": "Feature",
  "properties": {
    "addr:full":"Rue Du Brou 7 Hannut (abolens) Li\u00e8ge 4280",
    "addr:housenumber":"7",
    "addr:postcode":"4280",
    "addr:street":"Rue Du Brou;Abolens",
    "iso:country":"BE",
    "sg:address":"Rue Du Brou 7",
    "sg:city":"Hannut (abolens)",
    "sg:classifiers":[
        {
            "category":"Health Services",
            "subcategory":"Health Practitioner",
            "type":"Services"
        }
    ],
    "sg:phone":"+32 19 58 89 08",
    "sg:postcode":"4280",
    "sg:province":"Li\u00e8ge",
    "sg:tags":[
        "physiotherapist"
    ],
    "wof:name":"Fallais Corinne",
    "wof:placetype":"venue"
},
  "geometry": {"coordinates":[5.151597023,50.6724815369],"type":"Point"}
}