{
  "type": "Feature",
  "properties": {
    "iso:country":"BE",
    "sg:address":"Rijsmortelstraat 4",
    "sg:city":"Bierbeek",
    "sg:orig_category":"P\u00e9pini\u00e9ristes. Jardinage",
    "sg:phone":"+32 16 46 07 06",
    "sg:postcode":"3360",
    "sg:province":"Vlaams-Brabant",
    "wof:name":"Rausch Tuin",
    "wof:placetype":"venue"
},
  "geometry": {"coordinates":[4.7867622375,50.8502693176],"type":"Point"}
}