{
  "type": "Feature",
  "properties": {
    "iso:country":"BE",
    "sg:address":"Steenweg Op Mol 62",
    "sg:city":"Turnhout",
    "sg:orig_category":"Banken and kredietinstellingen Effectenmakelaars and vermogensbeheer",
    "sg:phone":"+32 14 44 36 50",
    "sg:postcode":"2300",
    "sg:province":"Antwerpen",
    "wof:name":"Bank Van Lanschot F.",
    "wof:placetype":"venue"
},
  "geometry": {"coordinates":[4.963763237,51.3213043213],"type":"Point"}
}