{
  "type": "Feature",
  "properties": {
    "iso:country":"BE",
    "sg:address":"Rue Du Pr\u00c9sident 14",
    "sg:city":"Namur",
    "sg:orig_category":"M\u00e9decins and sp\u00e9cialistes",
    "sg:phone":"+32 81 23 08 26",
    "sg:postcode":"5000",
    "sg:province":"Namur",
    "wof:name":"M. Seinlet",
    "wof:placetype":"venue"
},
  "geometry": {"coordinates":[4.8635849953,50.4633026123],"type":"Point"}
}