{
  "type": "Feature",
  "properties": {
    "addr:full":"Processiestraat 24 Opwijk Vlaams-Brabant 1745",
    "addr:housenumber":"24",
    "addr:postcode":"1745",
    "addr:street":"Processiestraat",
    "iso:country":"BE",
    "sg:address":"Processiestraat 24",
    "sg:city":"Opwijk",
    "sg:orig_category":"Protection civile",
    "sg:phone":"+32 52 35 98 36",
    "sg:postcode":"1745",
    "sg:province":"Vlaams-Brabant",
    "wof:name":"Brandweerkazerne",
    "wof:placetype":"venue"
},
  "geometry": {"coordinates":[4.1866641045,50.9702033997],"type":"Point"}
}