{
  "type": "Feature",
  "properties": {
    "addr:full":"Rue De La Pompe 7 Braives Li\u00e8ge 4260",
    "addr:housenumber":"7",
    "addr:postcode":"4260",
    "addr:street":"Rue De La Pompe",
    "iso:country":"BE",
    "sg:address":"Rue De La Pompe 7",
    "sg:city":"Braives",
    "sg:classifiers":[
        {
            "category":"Sports & Exercise",
            "subcategory":"Sports Center",
            "type":"Entertainment"
        }
    ],
    "sg:phone":"+32 19 69 85 69",
    "sg:postcode":"4260",
    "sg:province":"Li\u00e8ge",
    "sg:tags":[
        "terrain",
        "hors",
        "de",
        "installation",
        "sportifs"
    ],
    "wof:name":"Centre Equestre Braives",
    "wof:placetype":"venue"
},
  "geometry": {"coordinates":[5.1468939781,50.6209907532],"type":"Point"}
}