{
  "type": "Feature",
  "properties": {
    "addr:full":"Geneikenstraat 97 Lummen Limburg 3560",
    "addr:housenumber":"97",
    "addr:postcode":"3560",
    "addr:street":"Geneikenstraat",
    "iso:country":"BE",
    "sg:address":"Geneikenstraat 97",
    "sg:city":"Lummen",
    "sg:orig_category":"Elektrische installaties voor woningen",
    "sg:phone":"+32 11 42 92 05",
    "sg:postcode":"3560",
    "sg:province":"Limburg",
    "wof:name":"Electro Geerts Guido",
    "wof:placetype":"venue"
},
  "geometry": {"coordinates":[5.2200798988,51.0187225342],"type":"Point"}
}