{
  "type": "Feature",
  "properties": {
    "iso:country":"BE",
    "sg:address":"Sweynbeerstraat 46",
    "sg:city":"Zemst (elewijt)",
    "sg:classifiers":[
        {
            "category":"Banks & Credit Unions",
            "subcategory":"Investment Brokerage",
            "type":"Services"
        }
    ],
    "sg:phone":"+32 2 774 91 11",
    "sg:postcode":"1982",
    "sg:province":"Vlaams-Brabant",
    "sg:tags":[
        "auditor"
    ],
    "wof:name":"Pauwels W",
    "wof:placetype":"venue"
},
  "geometry": {"coordinates":[4.4972949028,50.9666938782],"type":"Point"}
}