{
  "type": "Feature",
  "properties": {
    "addr:full":"Avenue De La Grotte 4 Esneux (tilff) Li\u00e8ge 4130",
    "addr:housenumber":"4",
    "addr:postcode":"4130",
    "addr:street":"Avenue De La Grotte",
    "iso:country":"BE",
    "sg:address":"Avenue De La Grotte 4",
    "sg:city":"Esneux (tilff)",
    "sg:classifiers":[
        {
            "category":"Wholesale",
            "subcategory":"Computers",
            "type":"Manufacturing & Wholesale Goods"
        }
    ],
    "sg:phone":"+32 4 388 15 34",
    "sg:postcode":"4130",
    "sg:province":"Li\u00e8ge",
    "sg:tags":[
        "cabling",
        "processing",
        "-",
        "data"
    ],
    "wof:name":"V & V",
    "wof:placetype":"venue"
},
  "geometry": {"coordinates":[5.5818939209,50.5656242371],"type":"Point"}
}