{
  "type": "Feature",
  "properties": {
    "addr:full":"Hoogboomsteenweg 104b Brasschaat Antwerpen 2930",
    "addr:housenumber":"104b",
    "addr:postcode":"2930",
    "addr:street":"Hoogboomsteenweg",
    "iso:country":"BE",
    "sg:address":"Hoogboomsteenweg 104b",
    "sg:city":"Brasschaat",
    "sg:classifiers":[
        {
            "category":"Home & Garden",
            "subcategory":"Building Materials",
            "type":"Retail Goods"
        }
    ],
    "sg:phone":"+32 3 652 17 69",
    "sg:postcode":"2930",
    "sg:province":"Antwerpen",
    "sg:tags":[
        "window"
    ],
    "wof:name":"Gemis P",
    "wof:placetype":"venue"
},
  "geometry": {"coordinates":[4.4832859039,51.3086357117],"type":"Point"}
}