{
  "type": "Feature",
  "properties": {
    "addr:full":"Place Van Meyel 23 Etterbeek/etterbeek Bruxelles-Capitale 1040",
    "addr:housenumber":"23",
    "addr:postcode":"1040",
    "addr:street":"Place Van Meyel",
    "iso:country":"BE",
    "sg:address":"Place Van Meyel 23",
    "sg:city":"Etterbeek/etterbeek",
    "sg:orig_category":"M\u00e9decins and sp\u00e9cialistes",
    "sg:phone":"+32 2 735 53 98",
    "sg:postcode":"1040",
    "sg:province":"Bruxelles-Capitale",
    "wof:name":"Brigitte Michaux",
    "wof:placetype":"venue"
},
  "geometry": {"coordinates":[4.3897018433,50.8365402222],"type":"Point"}
}