{
  "type": "Feature",
  "properties": {
    "addr:full":"Damberdstraat 16 Wevelgem West-Vlaanderen 8560",
    "addr:housenumber":"16",
    "addr:postcode":"8560",
    "addr:street":"Damberdstraat",
    "iso:country":"BE",
    "sg:address":"Damberdstraat 16",
    "sg:city":"Wevelgem",
    "sg:orig_category":"Boucheries",
    "sg:phone":"+32 56 41 19 06",
    "sg:postcode":"8560",
    "sg:province":"West-Vlaanderen",
    "wof:name":"Bart Quaegebeur",
    "wof:placetype":"venue"
},
  "geometry": {"coordinates":[3.1626679897,50.8397102356],"type":"Point"}
}