{
  "type": "Feature",
  "properties": {
    "iso:country":"BE",
    "sg:address":"Stationsplein",
    "sg:city":"Geraardsbergen",
    "sg:orig_category":"Newspapers, magazines, periodicals - Distribution",
    "sg:phone":"+32 54 41 93 39",
    "sg:postcode":"9500",
    "sg:province":"Oost-Vlaanderen",
    "wof:name":"Press Shop",
    "wof:placetype":"venue"
},
  "geometry": {"coordinates":[3.8741950989,50.7703857422],"type":"Point"}
}