{
  "type": "Feature",
  "properties": {
    "iso:country":"BE",
    "sg:address":"Prins Albertlaan 53",
    "sg:city":"Izegem",
    "sg:classifiers":[
        {
            "category":"Building & Trades",
            "subcategory":"Electrical",
            "type":"Services"
        }
    ],
    "sg:phone":"+32 51 30 10 50",
    "sg:postcode":"8870",
    "sg:province":"West-Vlaanderen",
    "sg:tags":[
        "electric",
        "-",
        "housewiring",
        "contractor"
    ],
    "wof:name":"D'hoop-lybeer",
    "wof:placetype":"venue"
},
  "geometry": {"coordinates":[3.1991209984,50.9243202209],"type":"Point"}
}