{
  "type": "Feature",
  "properties": {
    "addr:full":"Molenweg 10 Houthulst West-Vlaanderen 8650",
    "addr:housenumber":"10",
    "addr:postcode":"8650",
    "addr:street":"Molenweg",
    "iso:country":"BE",
    "sg:address":"Molenweg 10",
    "sg:city":"Houthulst",
    "sg:orig_category":"Eleveurs and marchands de porcs. Eleveurs de bovins",
    "sg:phone":"+32 51 50 04 45",
    "sg:postcode":"8650",
    "sg:province":"West-Vlaanderen",
    "wof:name":"Dirk Balloey",
    "wof:placetype":"venue"
},
  "geometry": {"coordinates":[2.9265639782,50.9947662354],"type":"Point"}
}