{
  "type": "Feature",
  "properties": {
    "iso:country":"BE",
    "sg:address":"Rue Du Pont-quelin 8",
    "sg:city":"Ath",
    "sg:orig_category":"Voedingsspeciaalzaken",
    "sg:phone":"+32 68 84 20 30",
    "sg:postcode":"7800",
    "sg:province":"Hainaut",
    "wof:name":"Traiteur Frix",
    "wof:placetype":"venue"
},
  "geometry": {"coordinates":[3.7780070305,50.6311378479],"type":"Point"}
}