{
  "type": "Feature",
  "properties": {
    "addr:full":"Avenue Reine Fabiola 19 Ottignies-louvain-la-neuve Brabant Wallon 1340",
    "addr:housenumber":"19",
    "addr:postcode":"1340",
    "addr:street":"Avenue Reine Fabiola",
    "iso:country":"BE",
    "sg:address":"Avenue Reine Fabiola 19",
    "sg:city":"Ottignies-louvain-la-neuve",
    "sg:classifiers":[
        {
            "category":"Arena",
            "subcategory":"Sports Club",
            "type":"Entertainment"
        }
    ],
    "sg:phone":"+32 10 41 22 89",
    "sg:postcode":"1340",
    "sg:province":"Brabant Wallon",
    "sg:tags":[
        "terrain",
        "hors",
        "de",
        "installation",
        "sportifs"
    ],
    "wof:name":"F.c. Limelette",
    "wof:placetype":"venue"
},
  "geometry": {"coordinates":[4.5624318123,50.6677093506],"type":"Point"}
}