{
  "type": "Feature",
  "properties": {
    "iso:country":"BE",
    "sg:address":"Wiegstraat 28",
    "sg:city":"Antwerpen",
    "sg:orig_category":"Cr\u00e9meries",
    "sg:phone":"+32 3 233 37 29",
    "sg:postcode":"2000",
    "sg:province":"Antwerpen",
    "wof:name":"Vervloet",
    "wof:placetype":"venue"
},
  "geometry": {"coordinates":[4.4041957855,51.2178916931],"type":"Point"}
}