{
  "type": "Feature",
  "properties": {
    "addr:full":"Boulevard D\u00b4avroy 256 Li\u00c8ge Li\u00e8ge 4000",
    "addr:housenumber":"256",
    "addr:postcode":"4000",
    "addr:street":"Boulevard D\u00b4Avroy",
    "iso:country":"BE",
    "sg:address":"Boulevard D\u00b4avroy 256",
    "sg:city":"Li\u00c8ge",
    "sg:orig_category":"Administration d'immeubles. Agences immobili\u00e8res",
    "sg:phone":"+32 4 229 66 10",
    "sg:postcode":"4000",
    "sg:province":"Li\u00e8ge",
    "wof:name":"Conceptimmo",
    "wof:placetype":"venue"
},
  "geometry": {"coordinates":[5.5674848557,50.6312713623],"type":"Point"}
}