{
  "type": "Feature",
  "properties": {
    "iso:country":"BE",
    "sg:address":"Rue Denis 38",
    "sg:city":"Courcelles",
    "sg:orig_category":"Gespecialiseerde residenti\u00eble bouw",
    "sg:phone":"+32 71 45 02 51",
    "sg:postcode":"6180",
    "sg:province":"Hainaut",
    "wof:name":"Hirsoux",
    "wof:placetype":"venue"
},
  "geometry": {"coordinates":[4.3790750504,50.4547462463],"type":"Point"}
}