{
  "type": "Feature",
  "properties": {
    "iso:country":"BE",
    "sg:address":"Fazantstraat 19",
    "sg:city":"Gent",
    "sg:classifiers":[
        {
            "category":"Professional",
            "subcategory":"Accounting & Tax Preparation",
            "type":"Services"
        }
    ],
    "sg:phone":"+32 9 251 80 32",
    "sg:postcode":"9000",
    "sg:province":"Oost-Vlaanderen",
    "sg:tags":[
        "accountant"
    ],
    "wof:name":"Frank Haenebalcke",
    "wof:placetype":"venue"
},
  "geometry": {"coordinates":[3.7323439121,51.0750045776],"type":"Point"}
}