{
  "type": "Feature",
  "properties": {
    "iso:country":"BE",
    "sg:address":"Saint-pierre 56b1",
    "sg:city":"Libramont-chevigny",
    "sg:orig_category":"Traitements param\u00e9dicaux",
    "sg:phone":"+32 61 22 44 20",
    "sg:postcode":"6800",
    "sg:province":"Luxembourg",
    "wof:name":"Croix Jaune & Blanche",
    "wof:placetype":"venue"
},
  "geometry": {"coordinates":[5.3872699738,49.9037590027],"type":"Point"}
}