{
  "type": "Feature",
  "properties": {
    "iso:country":"BE",
    "sg:address":"Wez-des-rules 27",
    "sg:city":"Bertrix",
    "sg:orig_category":"Sportclubs",
    "sg:phone":"+32 61 41 38 59",
    "sg:postcode":"6880",
    "sg:province":"Luxembourg",
    "wof:name":"Union Cycliste Bertrig.",
    "wof:placetype":"venue"
},
  "geometry": {"coordinates":[5.2688269615,49.8426742554],"type":"Point"}
}