{
  "type": "Feature",
  "properties": {
    "iso:country":"BE",
    "sg:address":"Weertersteenweg 198",
    "sg:city":"Kinrooi",
    "sg:orig_category":"Woningbouw",
    "sg:phone":"+32 89 70 26 19",
    "sg:postcode":"3640",
    "sg:province":"Limburg",
    "wof:name":"Nicolas Tondeur",
    "wof:placetype":"venue"
},
  "geometry": {"coordinates":[5.742099762,51.1493988037],"type":"Point"}
}