{
  "type": "Feature",
  "properties": {
    "addr:full":"Rue De Bas\u00c8cles 19 Bernissart Hainaut 7321",
    "addr:housenumber":"19",
    "addr:postcode":"7321",
    "addr:street":"Rue De Base\u0300Cles",
    "iso:country":"BE",
    "sg:address":"Rue De Bas\u00c8cles 19",
    "sg:city":"Bernissart",
    "sg:orig_category":"Architecten Landmeters and schatters",
    "sg:phone":"+32 69 57 51 51",
    "sg:postcode":"7321",
    "sg:province":"Hainaut",
    "wof:name":"Bureau Querson Francis",
    "wof:placetype":"venue"
},
  "geometry": {"coordinates":[3.6611618996,50.5015869141],"type":"Point"}
}