{
  "type": "Feature",
  "properties": {
    "iso:country":"BE",
    "sg:address":"Hoefijzerlaan 56 Box 1",
    "sg:city":"Brugge",
    "sg:classifiers":[
        {
            "category":"Professional",
            "subcategory":"Computer Services",
            "type":"Services"
        }
    ],
    "sg:phone":"+32 50 67 31 98",
    "sg:postcode":"8000",
    "sg:province":"West-Vlaanderen",
    "sg:tags":[
        "webdesign",
        "-",
        "internet"
    ],
    "wof:name":"Beseen",
    "wof:placetype":"venue"
},
  "geometry": {"coordinates":[3.2145290375,51.2087249756],"type":"Point"}
}