{
  "type": "Feature",
  "properties": {
    "iso:country":"BE",
    "sg:address":"Chauss\u00c9e D\u00b4ecaussinnes 152",
    "sg:city":"Braine-le-comte",
    "sg:orig_category":"Plomberie, chauffage and installations sanitaires",
    "sg:phone":"+32 67 44 22 94",
    "sg:postcode":"7090",
    "sg:province":"Hainaut",
    "wof:name":"Superma",
    "wof:placetype":"venue"
},
  "geometry": {"coordinates":[4.1436657906,50.5824699402],"type":"Point"}
}