{
  "type": "Feature",
  "properties": {
    "addr:full":"Moerkerkse Steenweg 244 Brugge (sint-kruis) West-Vlaanderen 8310",
    "addr:housenumber":"244",
    "addr:postcode":"8310",
    "addr:street":"Moerkerkse Steenweg",
    "iso:country":"BE",
    "sg:address":"Moerkerkse Steenweg 244",
    "sg:city":"Brugge (sint-kruis)",
    "sg:classifiers":[
        {
            "category":"Bars & Pubs",
            "type":"Food & Drink"
        }
    ],
    "sg:phone":"+32 50 35 44 19",
    "sg:postcode":"8310",
    "sg:province":"West-Vlaanderen",
    "wof:name":"De Gasterie",
    "wof:placetype":"venue"
},
  "geometry": {"coordinates":[3.2551190853,51.2142601013],"type":"Point"}
}