{
  "type": "Feature",
  "properties": {
    "addr:full":"Turnhoutsebaan 14 Schilde Antwerpen 2970",
    "addr:housenumber":"14",
    "addr:postcode":"2970",
    "addr:street":"Turnhoutsebaan",
    "iso:country":"BE",
    "sg:address":"Turnhoutsebaan 14",
    "sg:city":"Schilde",
    "sg:orig_category":"Dranken",
    "sg:phone":"+32 3 353 27 00",
    "sg:postcode":"2970",
    "sg:province":"Antwerpen",
    "wof:name":"Wilfried Lens Wijnimport",
    "wof:placetype":"venue"
},
  "geometry": {"coordinates":[4.5549759865,51.2317886353],"type":"Point"}
}