{
  "type": "Feature",
  "properties": {
    "iso:country":"BE",
    "sg:address":"Stationsstraat 65",
    "sg:city":"Neerpelt",
    "sg:orig_category":"Bloemen and planten",
    "sg:phone":"+32 11 64 84 74",
    "sg:postcode":"3910",
    "sg:province":"Limburg",
    "wof:name":"'t Winkeltje",
    "wof:placetype":"venue"
},
  "geometry": {"coordinates":[5.4373168945,51.2237434387],"type":"Point"}
}