{
  "type": "Feature",
  "properties": {
    "iso:country":"BE",
    "sg:address":"Krabbendijk 4",
    "sg:city":"Sint-laureins",
    "sg:orig_category":"Rundveehouders",
    "sg:phone":"+32 9 379 81 84",
    "sg:postcode":"9982",
    "sg:province":"Oost-Vlaanderen",
    "wof:name":"Paul Supre",
    "wof:placetype":"venue"
},
  "geometry": {"coordinates":[3.6102900505,51.2569847107],"type":"Point"}
}