{
  "type": "Feature",
  "properties": {
    "iso:country":"BE",
    "sg:address":"Diestsesteenweg 443",
    "sg:city":"Leuven",
    "sg:classifiers":[
        {
            "category":"Personal",
            "subcategory":"Beauty Salon",
            "type":"Services"
        }
    ],
    "sg:phone":"+32 16 26 22 20",
    "sg:postcode":"3000",
    "sg:province":"Vlaams-Brabant",
    "wof:name":"Mensaert L",
    "wof:placetype":"venue"
},
  "geometry": {"coordinates":[4.7090997696,50.8863601685],"type":"Point"}
}