{
  "type": "Feature",
  "properties": {
    "iso:country":"BE",
    "sg:address":"Pullaard 18",
    "sg:city":"Grobbendonk",
    "sg:orig_category":"Non-Classified Establishments",
    "sg:phone":"+32 14 50 66 69",
    "sg:postcode":"2280",
    "sg:province":"Antwerpen",
    "wof:name":"Vinco Bvba",
    "wof:placetype":"venue"
},
  "geometry": {"coordinates":[4.7331590652,51.2132492065],"type":"Point"}
}