{
  "type": "Feature",
  "properties": {
    "iso:country":"BE",
    "sg:address":"Rue De Charleroi 20",
    "sg:city":"Genappe",
    "sg:orig_category":"Banken and kredietinstellingen",
    "sg:phone":"+32 67 77 13 88",
    "sg:postcode":"1470",
    "sg:province":"Brabant Wallon",
    "wof:name":"Cr\u00c9dit \u00c0 L'industrie",
    "wof:placetype":"venue"
},
  "geometry": {"coordinates":[4.4504718781,50.6100158691],"type":"Point"}
}