{
  "type": "Feature",
  "properties": {
    "iso:country":"BE",
    "sg:address":"Route De La Basse Sambre",
    "sg:city":"Charleroi",
    "sg:orig_category":"Jeux and jouets",
    "sg:phone":"+32 71 48 81 20",
    "sg:postcode":"6061",
    "sg:province":"Hainaut",
    "wof:name":"Jouets Broze",
    "wof:placetype":"venue"
},
  "geometry": {"coordinates":[4.4581289291,50.4166603088],"type":"Point"}
}