{
  "type": "Feature",
  "properties": {
    "addr:full":"Tentoonstellingslaan 123 Gent Oost-Vlaanderen 9000",
    "addr:housenumber":"123",
    "addr:postcode":"9000",
    "addr:street":"Tentoonstellingslaan;Oost-Vlaanderen",
    "iso:country":"BE",
    "sg:address":"Tentoonstellingslaan 123",
    "sg:city":"Gent",
    "sg:classifiers":[
        {
            "category":"Professional",
            "subcategory":"Testing Lab",
            "type":"Services"
        }
    ],
    "sg:phone":"+32 9 225 18 65",
    "sg:postcode":"9000",
    "sg:province":"Oost-Vlaanderen",
    "sg:tags":[
        "chemist"
    ],
    "wof:name":"Mestdagh P",
    "wof:placetype":"venue"
},
  "geometry": {"coordinates":[3.7326300144,51.0401611328],"type":"Point"}
}