{
  "type": "Feature",
  "properties": {
    "iso:country":"BE",
    "sg:address":"Rue De Savoie 38",
    "sg:city":"Bruxelles (saint-gilles)",
    "sg:classifiers":[
        {
            "category":"Professional",
            "subcategory":"Management & Consulting",
            "type":"Services"
        }
    ],
    "sg:phone":"+32 2 537 72 48",
    "sg:postcode":"1060",
    "sg:province":"Bruxelles-Capitale",
    "sg:tags":[
        "consultant",
        "agency",
        "advertising"
    ],
    "wof:name":"Leclercq P",
    "wof:placetype":"venue"
},
  "geometry": {"coordinates":[4.3464522362,50.8241767883],"type":"Point"}
}