{
  "type": "Feature",
  "properties": {
    "addr:full":"Elsum 116 Geel Antwerpen 2440",
    "addr:housenumber":"116",
    "addr:postcode":"2440",
    "addr:street":"Elsum",
    "iso:country":"BE",
    "sg:address":"Elsum 116",
    "sg:city":"Geel",
    "sg:classifiers":[
        {
            "category":"Bars & Pubs",
            "type":"Food & Drink"
        }
    ],
    "sg:phone":"+32 14 58 36 21",
    "sg:postcode":"2440",
    "sg:province":"Antwerpen",
    "wof:name":"Muske ('t)",
    "wof:placetype":"venue"
},
  "geometry": {"coordinates":[4.9773321152,51.1637687683],"type":"Point"}
}