{
  "type": "Feature",
  "properties": {
    "iso:country":"BE",
    "sg:address":"Rue F\u00e9lix Dutry 49",
    "sg:city":"Beaumont",
    "sg:classifiers":[
        {
            "category":"Personal",
            "subcategory":"Beauty Salon",
            "type":"Services"
        }
    ],
    "sg:phone":"+32 71 58 85 45",
    "sg:postcode":"6500",
    "sg:province":"Hainaut",
    "sg:tags":[
        "lady",
        "-",
        "hairdressing"
    ],
    "wof:name":"Stud'hair",
    "wof:placetype":"venue"
},
  "geometry": {"coordinates":[4.2372040749,50.235874176],"type":"Point"}
}