{
  "type": "Feature",
  "properties": {
    "addr:full":"Bessemstraat 31 Waregem West-Vlaanderen 8790",
    "addr:housenumber":"31",
    "addr:postcode":"8790",
    "addr:street":"Bessemstraat",
    "iso:country":"BE",
    "sg:address":"Bessemstraat 31",
    "sg:city":"Waregem",
    "sg:orig_category":"Charpentes and couvertures. Plomberie, chauffage and installations sanitaires. Services de Nettoyage",
    "sg:phone":"+32 56 60 69 70",
    "sg:postcode":"8790",
    "sg:province":"West-Vlaanderen",
    "wof:name":"Andre Vervaeke",
    "wof:placetype":"venue"
},
  "geometry": {"coordinates":[3.4509720802,50.8833656311],"type":"Point"}
}