{
  "type": "Feature",
  "properties": {
    "iso:country":"BE",
    "sg:address":"Hazegewoud 9",
    "sg:city":"Arendonk",
    "sg:classifiers":[
        {
            "category":"Home & Garden",
            "subcategory":"Furniture",
            "type":"Retail Goods"
        }
    ],
    "sg:phone":"+32 14 67 27 17",
    "sg:postcode":"2370",
    "sg:province":"Antwerpen",
    "sg:tags":[
        "-"
    ],
    "wof:name":"Diba",
    "wof:placetype":"venue"
},
  "geometry": {"coordinates":[5.0972948074,51.3359413147],"type":"Point"}
}