{
  "type": "Feature",
  "properties": {
    "iso:country":"BE",
    "sg:address":"Urselweg 33c",
    "sg:city":"Maldegem",
    "sg:orig_category":"MEUBELONTWERP AND -INSTALLATIE",
    "sg:phone":"+32 50 71 43 12",
    "sg:postcode":"9990",
    "sg:province":"Oost-Vlaanderen",
    "wof:name":"Keukeninrichting Marlido",
    "wof:placetype":"venue"
},
  "geometry": {"coordinates":[3.4660410881,51.174823761],"type":"Point"}
}