{
  "type": "Feature",
  "properties": {
    "iso:country":"BE",
    "sg:address":"Wezestraat 20",
    "sg:city":"Ardooie",
    "sg:orig_category":"Varkenskwekers",
    "sg:phone":"+32 51 74 48 31",
    "sg:postcode":"8850",
    "sg:province":"West-Vlaanderen",
    "wof:name":"Palmer Devisschere",
    "wof:placetype":"venue"
},
  "geometry": {"coordinates":[3.2095620632,50.9647903442],"type":"Point"}
}