{
  "type": "Feature",
  "properties": {
    "addr:full":"Koninginnelaan 83 Oostende West-Vlaanderen 8400",
    "addr:housenumber":"83",
    "addr:postcode":"8400",
    "addr:street":"Koninginnelaan",
    "iso:country":"BE",
    "sg:address":"Koninginnelaan 83",
    "sg:city":"Oostende",
    "sg:orig_category":"Sportclubs Sportterreinen and installaties behalve sportcentra",
    "sg:phone":"+32 59 70 21 70",
    "sg:postcode":"8400",
    "sg:province":"West-Vlaanderen",
    "wof:name":"Ostend Tennisclub",
    "wof:placetype":"venue"
},
  "geometry": {"coordinates":[2.9133629799,51.2215309143],"type":"Point"}
}