{
  "type": "Feature",
  "properties": {
    "addr:full":"Wijkstraat 13 Diepenbeek Limburg 3590",
    "addr:housenumber":"13",
    "addr:postcode":"3590",
    "addr:street":"Wijkstraat",
    "iso:country":"BE",
    "sg:address":"Wijkstraat 13",
    "sg:city":"Diepenbeek",
    "sg:orig_category":"Blanchisseries and teintureries",
    "sg:phone":"+32 11 32 33 11",
    "sg:postcode":"3590",
    "sg:province":"Limburg",
    "wof:name":"Prima Pressing",
    "wof:placetype":"venue"
},
  "geometry": {"coordinates":[5.4230451584,50.9078521729],"type":"Point"}
}