{
  "type": "Feature",
  "properties": {
    "iso:country":"BE",
    "sg:address":"Godfroid Kurthstraat 17",
    "sg:city":"Evere/evere",
    "sg:orig_category":"Installatie van houten of kunststof schrijnwerk",
    "sg:phone":"+32 2 216 60 17",
    "sg:postcode":"1140",
    "sg:province":"Bruxelles-Capitale",
    "wof:name":"Jan Kampert",
    "wof:placetype":"venue"
},
  "geometry": {"coordinates":[4.396818161,50.869102478],"type":"Point"}
}