{
  "type": "Feature",
  "properties": {
    "addr:full":"Kiezelweg 254 Lanaken Limburg 3620",
    "addr:housenumber":"254",
    "addr:postcode":"3620",
    "addr:street":"Kiezelweg",
    "iso:country":"BE",
    "sg:address":"Kiezelweg 254",
    "sg:city":"Lanaken",
    "sg:orig_category":"Pharmaciens",
    "sg:phone":"+32 89 71 85 10",
    "sg:postcode":"3620",
    "sg:province":"Limburg",
    "wof:name":"Dirk Van Clooster",
    "wof:placetype":"venue"
},
  "geometry": {"coordinates":[5.6303129196,50.8812713623],"type":"Point"}
}