{
  "type": "Feature",
  "properties": {
    "iso:country":"BE",
    "sg:address":"Chauss\u00c9e De Li\u00c8ge 135",
    "sg:city":"Marche-en-famenne",
    "sg:orig_category":"Machines and mat\u00e9riel agricoles Bois Installation de menuiserie m\u00e9tallique",
    "sg:phone":"+32 84 31 24 15",
    "sg:postcode":"6900",
    "sg:province":"Luxembourg",
    "wof:name":"Atel. Delzandre Industr.",
    "wof:placetype":"venue"
},
  "geometry": {"coordinates":[5.3453221321,50.2426109314],"type":"Point"}
}