{
  "type": "Feature",
  "properties": {
    "iso:country":"BE",
    "sg:address":"Rue Gustave Bo\u00ebl 83",
    "sg:city":"La Louvi\u00e8re",
    "sg:classifiers":[
        {
            "category":"Food & Beverages",
            "subcategory":"Groceries & Convenience Stores",
            "type":"Retail Goods"
        }
    ],
    "sg:phone":"+32 64 28 34 91",
    "sg:postcode":"7100",
    "sg:province":"Hainaut",
    "sg:tags":[
        "grocer"
    ],
    "wof:name":"Superette Du Canal",
    "wof:placetype":"venue"
},
  "geometry": {"coordinates":[4.1711649895,50.4800071716],"type":"Point"}
}