{
  "type": "Feature",
  "properties": {
    "iso:country":"BE",
    "sg:address":"Route De Philippeville 158-160",
    "sg:city":"Charleroi (couillet)",
    "sg:classifiers":[
        {
            "category":"Sports & Exercise",
            "subcategory":"Climbing Gym",
            "type":"Entertainment"
        }
    ],
    "sg:phone":"+32 71 36 98 37",
    "sg:postcode":"6010",
    "sg:province":"Hainaut",
    "sg:tags":[
        "water",
        "article"
    ],
    "wof:name":"Delalieux Sa",
    "wof:placetype":"venue"
},
  "geometry": {"coordinates":[4.4609007835,50.3883552551],"type":"Point"}
}