{
  "type": "Feature",
  "properties": {
    "iso:country":"BE",
    "sg:address":"Rue De Bouillon 50",
    "sg:city":"Beauraing",
    "sg:orig_category":"V\u00eatements",
    "sg:phone":"+32 473 28 47 35",
    "sg:postcode":"5570",
    "sg:province":"Namur",
    "wof:name":"Delta Zone",
    "wof:placetype":"venue"
},
  "geometry": {"coordinates":[4.9570112228,50.1089363098],"type":"Point"}
}