{
  "type": "Feature",
  "properties": {
    "addr:full":"Hoogstraat 42 Oosterzele (gijzenzele) Oost-Vlaanderen 9860",
    "addr:housenumber":"42",
    "addr:postcode":"9860",
    "addr:street":"Hoogstraat",
    "iso:country":"BE",
    "sg:address":"Hoogstraat 42",
    "sg:city":"Oosterzele (gijzenzele)",
    "sg:classifiers":[
        {
            "category":"Professional",
            "subcategory":"Accounting & Tax Preparation",
            "type":"Services"
        }
    ],
    "sg:phone":"+32 9 362 32 00",
    "sg:postcode":"9860",
    "sg:province":"Oost-Vlaanderen",
    "sg:tags":[
        "bookkeeper"
    ],
    "wof:name":"Vdm-van Durme Ch - Michiels A Bvba",
    "wof:placetype":"venue"
},
  "geometry": {"coordinates":[3.8194630146,50.9698257446],"type":"Point"}
}