{
  "type": "Feature",
  "properties": {
    "iso:country":"BE",
    "sg:address":"Gemeentehuisstraat 1",
    "sg:city":"Grimbergen",
    "sg:orig_category":"Enseignement maternel and primaire",
    "sg:phone":"+32 2 269 50 17",
    "sg:postcode":"1852",
    "sg:province":"Vlaams-Brabant",
    "wof:name":"Gemeentelijke Basisschool",
    "wof:placetype":"venue"
},
  "geometry": {"coordinates":[4.36419487,50.9568252563],"type":"Point"}
}