{
  "type": "Feature",
  "properties": {
    "iso:country":"BE",
    "sg:address":"Varentstraat 62",
    "sg:city":"Anzegem",
    "sg:orig_category":"Eleveurs de bovins",
    "sg:phone":"+32 55 38 84 61",
    "sg:postcode":"8572",
    "sg:province":"West-Vlaanderen",
    "wof:name":"Patrick Planquaert",
    "wof:placetype":"venue"
},
  "geometry": {"coordinates":[3.5084879398,50.807849884],"type":"Point"}
}