{
  "type": "Feature",
  "properties": {
    "iso:country":"BE",
    "sg:address":"Lange Nieuwstraat 10",
    "sg:city":"Antwerpen",
    "sg:orig_category":"Drukkerijen and copyshops",
    "sg:phone":"+32 3 233 03 47",
    "sg:postcode":"2000",
    "sg:province":"Antwerpen",
    "wof:name":"Aertssens Copy Service",
    "wof:placetype":"venue"
},
  "geometry": {"coordinates":[4.4056720734,51.2199478149],"type":"Point"}
}