{
  "type": "Feature",
  "properties": {
    "addr:full":"Albertlaan 72 Knokke-heist (knokke) West-Vlaanderen 8300",
    "addr:housenumber":"72",
    "addr:postcode":"8300",
    "addr:street":"Albertlaan",
    "iso:country":"BE",
    "sg:address":"Albertlaan 72",
    "sg:city":"Knokke-heist (knokke)",
    "sg:classifiers":[
        {
            "category":"Health Services",
            "subcategory":"Health Practitioner",
            "type":"Services"
        }
    ],
    "sg:phone":"+32 50 60 59 11",
    "sg:postcode":"8300",
    "sg:province":"West-Vlaanderen",
    "sg:tags":[
        "physiotherapist"
    ],
    "wof:name":"Walraet C",
    "wof:placetype":"venue"
},
  "geometry": {"coordinates":[3.289896965,51.3462181091],"type":"Point"}
}