{
  "type": "Feature",
  "properties": {
    "iso:country":"BE",
    "sg:address":"Industrie Strasse 30",
    "sg:city":"Eupen",
    "sg:classifiers":[
        {
            "category":"Government",
            "subcategory":"Post Office",
            "type":"Public Place"
        }
    ],
    "sg:phone":"+32 87 63 98 90",
    "sg:postcode":"4700",
    "sg:province":"Li\u00e8ge",
    "sg:tags":[
        "part",
        "-axis",
        "cnc",
        "milled"
    ],
    "wof:name":"Mustad",
    "wof:placetype":"venue"
},
  "geometry": {"coordinates":[6.00440979,50.63904953],"type":"Point"}
}