{
  "type": "Feature",
  "properties": {
    "iso:country":"BE",
    "sg:address":"Noordstraat 138",
    "sg:city":"Roeselare",
    "sg:classifiers":[
        {
            "category":"Manufacturing",
            "subcategory":"Electronics",
            "type":"Manufacturing & Wholesale Goods"
        }
    ],
    "sg:phone":"+32 51 20 31 41",
    "sg:postcode":"8800",
    "sg:province":"West-Vlaanderen",
    "sg:tags":[
        "component",
        "-"
    ],
    "wof:name":"Teleshop Bvba",
    "wof:placetype":"venue"
},
  "geometry": {"coordinates":[3.1212570667,50.9489784241],"type":"Point"}
}