{
  "type": "Feature",
  "properties": {
    "addr:full":"Rue Du Vieux-march\u00c9 42 Vielsalm Luxembourg 6690",
    "addr:housenumber":"42",
    "addr:postcode":"6690",
    "addr:street":"Rue Du Vieux-Marche\u0301",
    "iso:country":"BE",
    "sg:address":"Rue Du Vieux-march\u00c9 42",
    "sg:city":"Vielsalm",
    "sg:orig_category":"Immobili\u00ebnkantoren Verzekeringsmakelaars and experts",
    "sg:phone":"+32 80 21 48 74",
    "sg:postcode":"6690",
    "sg:province":"Luxembourg",
    "wof:name":"Immobili\u00c8re Des Ardennes",
    "wof:placetype":"venue"
},
  "geometry": {"coordinates":[5.9147801399,50.2852134705],"type":"Point"}
}