{
  "type": "Feature",
  "properties": {
    "addr:full":"Kasteelstraat 42 Staden West-Vlaanderen 8840",
    "addr:housenumber":"42",
    "addr:postcode":"8840",
    "addr:street":"Kasteelstraat",
    "iso:country":"BE",
    "sg:address":"Kasteelstraat 42",
    "sg:city":"Staden",
    "sg:orig_category":"Eleveurs and marchands de porcs",
    "sg:phone":"+32 51 70 21 32",
    "sg:postcode":"8840",
    "sg:province":"West-Vlaanderen",
    "wof:name":"Mevar",
    "wof:placetype":"venue"
},
  "geometry": {"coordinates":[3.0070819855,50.9521636963],"type":"Point"}
}