{
  "type": "Feature",
  "properties": {
    "iso:country":"BE",
    "sg:address":"Manestraat 33",
    "sg:city":"Opglabbeek",
    "sg:classifiers":[
        {
            "category":"Home & Garden",
            "subcategory":"Kitchen Supply",
            "type":"Retail Goods"
        }
    ],
    "sg:phone":"+32 89 85 51 36",
    "sg:postcode":"3660",
    "sg:province":"Limburg",
    "sg:tags":[
        "installation"
    ],
    "wof:name":"Paredis I",
    "wof:placetype":"venue"
},
  "geometry": {"coordinates":[5.5773301125,51.0474815369],"type":"Point"}
}