{
  "type": "Feature",
  "properties": {
    "addr:full":"Rue Du Grandchamp 2 Ch\u00e2telet Hainaut 6200",
    "addr:housenumber":"2",
    "addr:postcode":"6200",
    "addr:street":"Rue Du Grandchamp",
    "iso:country":"BE",
    "sg:address":"Rue Du Grandchamp 2",
    "sg:city":"Ch\u00e2telet",
    "sg:classifiers":[
        {
            "category":"Insurance",
            "subcategory":"Insurance Agent",
            "type":"Services"
        }
    ],
    "sg:phone":"+32 71 38 25 13",
    "sg:postcode":"6200",
    "sg:province":"Hainaut",
    "sg:tags":[
        "-",
        "representative"
    ],
    "wof:name":"M.v. Consult",
    "wof:placetype":"venue"
},
  "geometry": {"coordinates":[4.5336771011,50.3924026489],"type":"Point"}
}