{
  "type": "Feature",
  "properties": {
    "addr:full":"Cit\u00c9 Des Cerisiers 23 Chimay Hainaut 6460",
    "addr:housenumber":"23",
    "addr:postcode":"6460",
    "addr:street":"Cite\u0301 Des Cerisiers",
    "iso:country":"BE",
    "sg:address":"Cit\u00c9 Des Cerisiers 23",
    "sg:city":"Chimay",
    "sg:orig_category":"Activit\u00e9s r\u00e9cr\u00e9atives diverses",
    "sg:phone":"+32 60 21 34 94",
    "sg:postcode":"6460",
    "sg:province":"Hainaut",
    "wof:name":"Petites Ailes Frontiere",
    "wof:placetype":"venue"
},
  "geometry": {"coordinates":[4.3286299706,50.0445365906],"type":"Point"}
}