{
  "type": "Feature",
  "properties": {
    "addr:full":"Antwerpsestraat 56 Lier Antwerpen 2500",
    "addr:housenumber":"56",
    "addr:postcode":"2500",
    "addr:street":"Antwerpsestraat",
    "iso:country":"BE",
    "sg:address":"Antwerpsestraat 56",
    "sg:city":"Lier",
    "sg:orig_category":"Baby- and kinderkleding",
    "sg:phone":"+32 3 480 18 23",
    "sg:postcode":"2500",
    "sg:province":"Antwerpen",
    "wof:name":"De Kleine Kat",
    "wof:placetype":"venue"
},
  "geometry": {"coordinates":[4.5682587624,51.1330909729],"type":"Point"}
}