{
  "type": "Feature",
  "properties": {
    "addr:full":"Rue De Pousset 16 Oreye Li\u00e8ge 4360",
    "addr:housenumber":"16",
    "addr:postcode":"4360",
    "addr:street":"Rue De Pousset",
    "iso:country":"BE",
    "sg:address":"Rue De Pousset 16",
    "sg:city":"Oreye",
    "sg:orig_category":"Charpentes and couvertures. Plomberie, chauffage and installations sanitaires",
    "sg:phone":"+32 19 67 83 72",
    "sg:postcode":"4360",
    "sg:province":"Li\u00e8ge",
    "wof:name":"Scaglitoit",
    "wof:placetype":"venue"
},
  "geometry": {"coordinates":[5.3262619972,50.7131881714],"type":"Point"}
}