{
  "type": "Feature",
  "properties": {
    "iso:country":"BE",
    "sg:address":"Koning Albert I Laan 19",
    "sg:city":"Roeselare",
    "sg:classifiers":[
        {
            "category":"Utilities",
            "subcategory":"Cable",
            "type":"Services"
        }
    ],
    "sg:phone":"+32 51 20 21 60",
    "sg:postcode":"8800",
    "sg:province":"West-Vlaanderen",
    "sg:tags":[
        "wire",
        "electric"
    ],
    "wof:name":"Electro Mandel Nv",
    "wof:placetype":"venue"
},
  "geometry": {"coordinates":[3.1319200993,50.9447937012],"type":"Point"}
}