{
  "type": "Feature",
  "properties": {
    "iso:country":"BE",
    "sg:address":"Rue Garde-dieu 43",
    "sg:city":"Li\u00c8ge",
    "sg:orig_category":"Woningbouw",
    "sg:phone":"+32 4 341 38 48",
    "sg:postcode":"4031",
    "sg:province":"Li\u00e8ge",
    "wof:name":"Alain Helmus",
    "wof:placetype":"venue"
},
  "geometry": {"coordinates":[5.5839648247,50.6192359924],"type":"Point"}
}