{
  "type": "Feature",
  "properties": {
    "iso:country":"BE",
    "sg:address":"Preshoekstraat 6",
    "sg:city":"Kortrijk",
    "sg:orig_category":"Traducteurs and interpr\u00e8tes",
    "sg:phone":"+32 56 25 78 48",
    "sg:postcode":"8510",
    "sg:province":"West-Vlaanderen",
    "wof:name":"Delannoy B. Cbtip/bkvtf",
    "wof:placetype":"venue"
},
  "geometry": {"coordinates":[3.2182519436,50.792049408],"type":"Point"}
}