{
  "type": "Feature",
  "properties": {
    "addr:full":"Pijkstraat 71 Waregem West-Vlaanderen 8790",
    "addr:housenumber":"71",
    "addr:postcode":"8790",
    "addr:street":"Pijkstraat",
    "iso:country":"BE",
    "sg:address":"Pijkstraat 71",
    "sg:city":"Waregem",
    "sg:orig_category":"Loodgieterij, verwarming and sanitaire installaties",
    "sg:phone":"+32 56 60 89 66",
    "sg:postcode":"8790",
    "sg:province":"West-Vlaanderen",
    "wof:name":"Guy Staelens",
    "wof:placetype":"venue"
},
  "geometry": {"coordinates":[3.412322998,50.8859863281],"type":"Point"}
}