{
  "type": "Feature",
  "properties": {
    "iso:country":"BE",
    "sg:address":"Deken Adamsstraat 72",
    "sg:city":"Turnhout",
    "sg:classifiers":[
        {
            "category":"Real Estate",
            "subcategory":"Architect",
            "type":"Services"
        }
    ],
    "sg:phone":"+32 14 72 33 14",
    "sg:postcode":"2300",
    "sg:province":"Antwerpen",
    "wof:name":"Van Gils B",
    "wof:placetype":"venue"
},
  "geometry": {"coordinates":[4.9484548569,51.3207817078],"type":"Point"}
}