{
  "type": "Feature",
  "properties": {
    "iso:country":"BE",
    "sg:address":"Cuperuslei 31",
    "sg:city":"Heist-op-den-berg",
    "sg:classifiers":[
        {
            "category":"Health Services",
            "subcategory":"Medical Lab",
            "type":"Services"
        }
    ],
    "sg:phone":"+32 15 24 77 74",
    "sg:postcode":"2220",
    "sg:province":"Antwerpen",
    "sg:tags":[
        "laboratory",
        "dental"
    ],
    "wof:name":"Peeters F",
    "wof:placetype":"venue"
},
  "geometry": {"coordinates":[4.7213439941,51.0671615601],"type":"Point"}
}