{
  "type": "Feature",
  "properties": {
    "iso:country":"BE",
    "sg:address":"Chemin De Bl\u00c9haries 4ba",
    "sg:city":"Brunehaut",
    "sg:orig_category":"Woningbouw",
    "sg:phone":"+32 69 34 53 36",
    "sg:postcode":"7623",
    "sg:province":"Hainaut",
    "wof:name":"Francis Leclercq",
    "wof:placetype":"venue"
},
  "geometry": {"coordinates":[3.3951969147,50.5083732605],"type":"Point"}
}