{
  "type": "Feature",
  "properties": {
    "iso:country":"BE",
    "sg:address":"Boulevard Cuivre Et Zinc 28",
    "sg:city":"Li\u00e8ge 1 (grivegn\u00e9e)",
    "sg:orig_category":"Autombile concessionaires",
    "sg:phone":"+32 4 344 01 01",
    "sg:postcode":"4030",
    "sg:province":"Li\u00e8ge",
    "wof:name":"Jaguar Liege",
    "wof:placetype":"venue"
},
  "geometry": {"coordinates":[5.5925140381,50.6241989136],"type":"Point"}
}