{
  "type": "Feature",
  "properties": {
    "addr:full":"Veemarkt 17 Kortrijk West-Vlaanderen 8500",
    "addr:housenumber":"17",
    "addr:postcode":"8500",
    "addr:street":"Veemarkt",
    "iso:country":"BE",
    "sg:address":"Veemarkt 17",
    "sg:city":"Kortrijk",
    "sg:orig_category":"V\u00eatements",
    "sg:phone":"+32 56 22 83 02",
    "sg:postcode":"8500",
    "sg:province":"West-Vlaanderen",
    "wof:name":"Huis Sox",
    "wof:placetype":"venue"
},
  "geometry": {"coordinates":[3.272758007,50.826259613],"type":"Point"}
}