{
  "type": "Feature",
  "properties": {
    "iso:country":"BE",
    "sg:address":"Oud-strijderslaan 49",
    "sg:city":"Lokeren",
    "sg:classifiers":[
        {
            "category":"Arena",
            "subcategory":"Sports Club",
            "type":"Entertainment"
        }
    ],
    "sg:phone":"+32 9 349 37 88",
    "sg:postcode":"9160",
    "sg:province":"Oost-Vlaanderen",
    "wof:name":"Biljart Palace",
    "wof:placetype":"venue"
},
  "geometry": {"coordinates":[3.9969830513,51.1032676697],"type":"Point"}
}