{
  "type": "Feature",
  "properties": {
    "iso:country":"BE",
    "sg:address":"Rue Du Jardinier 46b146",
    "sg:city":"Braine-l'alleud",
    "sg:orig_category":"Plomberie, chauffage and installations sanitaires. Fabrication and montage de mobilier",
    "sg:phone":"+32 2 384 29 08",
    "sg:postcode":"1420",
    "sg:province":"Brabant Wallon",
    "wof:name":"Derpa",
    "wof:placetype":"venue"
},
  "geometry": {"coordinates":[-75.60595703120001,37.7877616882],"type":"Point"}
}