{
  "type": "Feature",
  "properties": {
    "iso:country":"BE",
    "sg:address":"Paalsteenstraat 207",
    "sg:city":"Hasselt",
    "sg:orig_category":"Dakwerken",
    "sg:phone":"+32 11 24 28 95",
    "sg:postcode":"3500",
    "sg:province":"Limburg",
    "wof:name":"Eurodak",
    "wof:placetype":"venue"
},
  "geometry": {"coordinates":[5.3419380188,50.9635238647],"type":"Point"}
}