{
  "type": "Feature",
  "properties": {
    "addr:full":"Rue Des D\u00e9port\u00e9s 45 Charleroi (mont-sur-marchienne) Hainaut 6032",
    "addr:housenumber":"45",
    "addr:postcode":"6032",
    "addr:street":"Rue Des De\u0301Porte\u0301S",
    "iso:country":"BE",
    "sg:address":"Rue Des D\u00e9port\u00e9s 45",
    "sg:city":"Charleroi (mont-sur-marchienne)",
    "sg:classifiers":[
        {
            "category":"Personal",
            "subcategory":"Beauty Salon",
            "type":"Services"
        }
    ],
    "sg:phone":"+32 71 43 74 53",
    "sg:postcode":"6032",
    "sg:province":"Hainaut",
    "sg:tags":[
        "lady",
        "-",
        "hairdressing"
    ],
    "wof:name":"Lauryvonne",
    "wof:placetype":"venue"
},
  "geometry": {"coordinates":[4.4112930298,50.38514328],"type":"Point"}
}