{
  "type": "Feature",
  "properties": {
    "addr:full":"Route De Saint-g\u00c9rard 21 Fosses-la-ville Namur 5070",
    "addr:housenumber":"21",
    "addr:postcode":"5070",
    "addr:street":"Route De Saint-Ge\u0301Rard",
    "iso:country":"BE",
    "sg:address":"Route De Saint-g\u00c9rard 21",
    "sg:city":"Fosses-la-ville",
    "sg:orig_category":"Slagers",
    "sg:phone":"+32 71 71 17 64",
    "sg:postcode":"5070",
    "sg:province":"Namur",
    "wof:name":"Marcel Lessire",
    "wof:placetype":"venue"
},
  "geometry": {"coordinates":[4.7030901909,50.3756599426],"type":"Point"}
}