{
  "type": "Feature",
  "properties": {
    "addr:full":"Rue Gustave Lhoir 10 Saint-ghislain (hautrage) Hainaut 7334",
    "addr:housenumber":"10",
    "addr:postcode":"7334",
    "addr:street":"Rue Gustave Lhoir",
    "iso:country":"BE",
    "sg:address":"Rue Gustave Lhoir 10",
    "sg:city":"Saint-ghislain (hautrage)",
    "sg:classifiers":[
        {
            "category":"Health Services",
            "subcategory":"Health Practitioner",
            "type":"Services"
        }
    ],
    "sg:phone":"+32 65 62 20 86",
    "sg:postcode":"7334",
    "sg:province":"Hainaut",
    "sg:tags":[
        "physiotherapist"
    ],
    "wof:name":"Jeuniaux J-j",
    "wof:placetype":"venue"
},
  "geometry": {"coordinates":[3.7644500732,50.479675293],"type":"Point"}
}