{
  "type": "Feature",
  "properties": {
    "addr:full":"Heirentstraat 8 Meulebeke West-Vlaanderen 8760",
    "addr:housenumber":"8",
    "addr:postcode":"8760",
    "addr:street":"Heirentstraat",
    "iso:country":"BE",
    "sg:address":"Heirentstraat 8",
    "sg:city":"Meulebeke",
    "sg:classifiers":[
        {
            "category":"Freight",
            "type":"Transportation"
        }
    ],
    "sg:phone":"+32 51 40 06 31",
    "sg:postcode":"8760",
    "sg:province":"West-Vlaanderen",
    "sg:tags":[
        "-",
        "transport"
    ],
    "wof:name":"Devroe M",
    "wof:placetype":"venue"
},
  "geometry": {"coordinates":[3.3475399017,50.9603996277],"type":"Point"}
}