{
  "type": "Feature",
  "properties": {
    "addr:full":"Seizoenwerkersstraat 4 Houthulst West-Vlaanderen 8650",
    "addr:housenumber":"4",
    "addr:postcode":"8650",
    "addr:street":"Seizoenwerkersstraat",
    "iso:country":"BE",
    "sg:address":"Seizoenwerkersstraat 4",
    "sg:city":"Houthulst",
    "sg:classifiers":[
        {
            "category":"Arena",
            "subcategory":"Sports Club",
            "type":"Entertainment"
        }
    ],
    "sg:phone":"+32 51 50 23 01",
    "sg:postcode":"8650",
    "sg:province":"West-Vlaanderen",
    "sg:tags":[
        "terrain",
        "hors",
        "de",
        "installation",
        "sportifs"
    ],
    "wof:name":"K.s.v. Diksmuide",
    "wof:placetype":"venue"
},
  "geometry": {"coordinates":[2.9509439468,50.9778862],"type":"Point"}
}