{
  "type": "Feature",
  "properties": {
    "iso:country":"BE",
    "sg:address":"Vaartdijkstraat 36",
    "sg:city":"Brugge",
    "sg:orig_category":"Quincailleries. Bois Gr",
    "sg:phone":"+32 50 38 12 80",
    "sg:postcode":"8200",
    "sg:province":"West-Vlaanderen",
    "wof:name":"Houthandel Rammant",
    "wof:placetype":"venue"
},
  "geometry": {"coordinates":[3.2299029827,51.1924057007],"type":"Point"}
}