{
  "type": "Feature",
  "properties": {
    "addr:full":"Nederrij 15 Herentals Antwerpen 2200",
    "addr:housenumber":"15",
    "addr:postcode":"2200",
    "addr:street":"Nederrij",
    "iso:country":"BE",
    "sg:address":"Nederrij 15",
    "sg:city":"Herentals",
    "sg:classifiers":[
        {
            "category":"Retail",
            "subcategory":"Funeral Services",
            "type":"Services"
        }
    ],
    "sg:phone":"+32 14 23 10 67",
    "sg:postcode":"2200",
    "sg:province":"Antwerpen",
    "sg:tags":[
        "director"
    ],
    "wof:name":"Daneels Marcel Bvba",
    "wof:placetype":"venue"
},
  "geometry": {"coordinates":[4.8348278999,51.1823997498],"type":"Point"}
}