{
  "type": "Feature",
  "properties": {
    "iso:country":"BE",
    "sg:address":"Cipresstraat 7",
    "sg:city":"Brussel/bruxelles",
    "sg:orig_category":"Beheer onroerend goed",
    "sg:phone":"+32 2 219 79 67",
    "sg:postcode":"1000",
    "sg:province":"Bruxelles-Capitale",
    "wof:name":"Fejeco",
    "wof:placetype":"venue"
},
  "geometry": {"coordinates":[4.3503279686,50.8521232605],"type":"Point"}
}