{
  "type": "Feature",
  "properties": {
    "addr:full":"Rue Haeck 6 Sint-jans-molenbeek/molenbeek-saint-jean Bruxelles-Capitale 1080",
    "addr:housenumber":"6",
    "addr:postcode":"1080",
    "addr:street":"Rue Haeck",
    "iso:country":"BE",
    "sg:address":"Rue Haeck 6",
    "sg:city":"Sint-jans-molenbeek/molenbeek-saint-jean",
    "sg:orig_category":"Pharmaciens",
    "sg:phone":"+32 2 425 81 30",
    "sg:postcode":"1080",
    "sg:province":"Bruxelles-Capitale",
    "wof:name":"Brigitte De Coen",
    "wof:placetype":"venue"
},
  "geometry": {"coordinates":[4.3333911896,50.8639297485],"type":"Point"}
}