{
  "type": "Feature",
  "properties": {
    "addr:full":"Haneveldstraat 38b12 Genk Limburg 3600",
    "addr:housenumber":"38b12",
    "addr:postcode":"3600",
    "addr:street":"Haneveldstraat",
    "iso:country":"BE",
    "sg:address":"Haneveldstraat 38b12",
    "sg:city":"Genk",
    "sg:orig_category":"Sportclubs",
    "sg:phone":"+32 89 38 58 80",
    "sg:postcode":"3600",
    "sg:province":"Limburg",
    "wof:name":"P.c. Genk",
    "wof:placetype":"venue"
},
  "geometry": {"coordinates":[5.5318589211,50.9896202087],"type":"Point"}
}