{
  "type": "Feature",
  "properties": {
    "iso:country":"BE",
    "sg:address":"Rue De Mazy 96",
    "sg:city":"Gembloux-sur-orneau (gembloux)",
    "sg:classifiers":[
        {
            "category":"Professional",
            "subcategory":"Art Services",
            "type":"Services"
        }
    ],
    "sg:phone":"+32 81 61 34 83",
    "sg:postcode":"5030",
    "sg:province":"Namur",
    "sg:tags":[
        "sculptor"
    ],
    "wof:name":"Guiot D",
    "wof:placetype":"venue"
},
  "geometry": {"coordinates":[4.6951608658,50.5520896912],"type":"Point"}
}