{
  "type": "Feature",
  "properties": {
    "iso:country":"BE",
    "sg:address":"Molenvoetweg 41",
    "sg:city":"Lint",
    "sg:orig_category":"Film-, tv- and videoproductie Geluidsopnames",
    "sg:phone":"+32 3 455 97 54",
    "sg:postcode":"2547",
    "sg:province":"Antwerpen",
    "wof:name":"Johan Primusz",
    "wof:placetype":"venue"
},
  "geometry": {"coordinates":[4.4902238846,51.1315460205],"type":"Point"}
}