{
  "type": "Feature",
  "properties": {
    "addr:full":"Chauss\u00c9e De Douai 17 Tournai Hainaut 7500",
    "addr:housenumber":"17",
    "addr:postcode":"7500",
    "addr:street":"Chausse\u0301E De Douai",
    "iso:country":"BE",
    "sg:address":"Chauss\u00c9e De Douai 17",
    "sg:city":"Tournai",
    "sg:orig_category":"Boucheries",
    "sg:phone":"+32 69 22 53 72",
    "sg:postcode":"7500",
    "sg:province":"Hainaut",
    "wof:name":"Jacques Depotter",
    "wof:placetype":"venue"
},
  "geometry": {"coordinates":[3.3810930252,50.600353241],"type":"Point"}
}