{
  "type": "Feature",
  "properties": {
    "addr:full":"Antwerpse Steenweg 98e Lochristi Oost-Vlaanderen 9080",
    "addr:housenumber":"98e",
    "addr:postcode":"9080",
    "addr:street":"Antwerpse Steenweg",
    "iso:country":"BE",
    "sg:address":"Antwerpse Steenweg 98e",
    "sg:city":"Lochristi",
    "sg:classifiers":[
        {
            "category":"Communications",
            "subcategory":"Film & Video Production",
            "type":"Services"
        }
    ],
    "sg:phone":"+32 9 356 67 56",
    "sg:postcode":"9080",
    "sg:province":"Oost-Vlaanderen",
    "sg:tags":[
        "hiring",
        "-"
    ],
    "wof:name":"Videoland",
    "wof:placetype":"venue"
},
  "geometry": {"coordinates":[3.8079309464,51.0885391235],"type":"Point"}
}