{
  "type": "Feature",
  "properties": {
    "iso:country":"BE",
    "sg:address":"Waversesteenweg 1616",
    "sg:city":"Brussel",
    "sg:orig_category":"Non-Classified Establishments",
    "sg:phone":"+32 2 675 56 32",
    "sg:postcode":"1160",
    "sg:province":"Bruxelles-Capitale",
    "wof:name":"Peclers (psr)",
    "wof:placetype":"venue"
},
  "geometry": {"coordinates":[4.4249911308,50.8169059753],"type":"Point"}
}