{
  "type": "Feature",
  "properties": {
    "iso:country":"BE",
    "sg:address":"Avenue Charles Woeste 95",
    "sg:city":"Jette",
    "sg:orig_category":"Assistances juridiques. Conseillers fiscaux",
    "sg:phone":"+32 2 428 80 44",
    "sg:postcode":"1090",
    "sg:province":"Bruxelles-Capitale",
    "wof:name":"Fiduciair Kantoor Deltour",
    "wof:placetype":"venue"
},
  "geometry": {"coordinates":[4.3330740929,50.8758239746],"type":"Point"}
}