{
  "type": "Feature",
  "properties": {
    "addr:full":"Gillebertusstraat 19 Jette/jette Bruxelles-Capitale 1090",
    "addr:housenumber":"19",
    "addr:postcode":"1090",
    "addr:street":"Gillebertusstraat",
    "iso:country":"BE",
    "sg:address":"Gillebertusstraat 19",
    "sg:city":"Jette/jette",
    "sg:orig_category":"Paramedische behandelingen",
    "sg:phone":"+32 2 428 37 31",
    "sg:postcode":"1090",
    "sg:province":"Bruxelles-Capitale",
    "wof:name":"Bellini",
    "wof:placetype":"venue"
},
  "geometry": {"coordinates":[4.3250632286,50.8768882751],"type":"Point"}
}