{
  "type": "Feature",
  "properties": {
    "addr:full":"Oostendelaan 71 Middelkerke West-Vlaanderen 8430",
    "addr:housenumber":"71",
    "addr:postcode":"8430",
    "addr:street":"Oostendelaan",
    "iso:country":"BE",
    "sg:address":"Oostendelaan 71",
    "sg:city":"Middelkerke",
    "sg:classifiers":[
        {
            "category":"Professional",
            "subcategory":"Computer Services",
            "type":"Services"
        }
    ],
    "sg:phone":"+32 59 31 56 40",
    "sg:postcode":"8430",
    "sg:province":"West-Vlaanderen",
    "sg:tags":[
        "-",
        "processing",
        "data"
    ],
    "wof:name":"System X Computers",
    "wof:placetype":"venue"
},
  "geometry": {"coordinates":[2.822439909,51.1859397888],"type":"Point"}
}