{
  "type": "Feature",
  "properties": {
    "iso:country":"BE",
    "sg:address":"Place Ferrer 4",
    "sg:city":"Soumagne",
    "sg:orig_category":"Huishoudapparaten, televisies and radio's Telecommunicatieapparaten",
    "sg:phone":"+32 4 377 27 09",
    "sg:postcode":"4630",
    "sg:province":"Li\u00e8ge",
    "wof:name":"Carol Ets",
    "wof:placetype":"venue"
},
  "geometry": {"coordinates":[5.7477822304,50.6117477417],"type":"Point"}
}