{
  "type": "Feature",
  "properties": {
    "addr:full":"Avenue Du Pesage 22 Bruxelles (ixelles) Bruxelles-Capitale 1050",
    "addr:housenumber":"22",
    "addr:postcode":"1050",
    "addr:street":"Avenue Du Pesage",
    "iso:country":"BE",
    "sg:address":"Avenue Du Pesage 22",
    "sg:city":"Bruxelles (ixelles)",
    "sg:classifiers":[
        {
            "category":"Personal",
            "subcategory":"Beauty Salon",
            "type":"Services"
        }
    ],
    "sg:phone":"+32 2 640 11 26",
    "sg:postcode":"1050",
    "sg:province":"Bruxelles-Capitale",
    "sg:tags":[
        "lady",
        "-",
        "hairdressing"
    ],
    "wof:name":"Coiff Hair 2000",
    "wof:placetype":"venue"
},
  "geometry": {"coordinates":[4.386783123,50.8094825745],"type":"Point"}
}