{
  "type": "Feature",
  "properties": {
    "addr:full":"Voorstraat 4 Kaprijke Oost-Vlaanderen 9970",
    "addr:housenumber":"4",
    "addr:postcode":"9970",
    "addr:street":"Voorstraat",
    "iso:country":"BE",
    "sg:address":"Voorstraat 4",
    "sg:city":"Kaprijke",
    "sg:classifiers":[
        {
            "category":"Insurance",
            "subcategory":"Insurance Agent",
            "type":"Services"
        }
    ],
    "sg:phone":"+32 9 373 83 05",
    "sg:postcode":"9970",
    "sg:province":"Oost-Vlaanderen",
    "sg:tags":[
        "verzekeringsmakelaars",
        "expert"
    ],
    "wof:name":"Matthijs-van Petegem",
    "wof:placetype":"venue"
},
  "geometry": {"coordinates":[3.6159410477,51.2182388306],"type":"Point"}
}