{
  "type": "Feature",
  "properties": {
    "iso:country":"BE",
    "sg:address":"Lokerseweg 32",
    "sg:city":"Poperinge",
    "sg:classifiers":[
        {
            "category":"Cafe",
            "type":"Food & Drink"
        }
    ],
    "sg:phone":"+32 57 44 59 04",
    "sg:postcode":"8970",
    "sg:province":"West-Vlaanderen",
    "sg:tags":[
        "caf\u00e9s"
    ],
    "wof:name":"Caf\u00c9 De Brander",
    "wof:placetype":"venue"
},
  "geometry": {"coordinates":[2.7705600262,50.800151825],"type":"Point"}
}