{
  "type": "Feature",
  "properties": {
    "addr:full":"Av. Marq. De Villalobar 2 Sint-pieters-woluwe/woluwe-saint-pierre Bruxelles-Capitale 1150",
    "addr:housenumber":"2",
    "addr:postcode":"1150",
    "addr:street":"Av. Marq. De Villalobar;/",
    "iso:country":"BE",
    "sg:address":"Av. Marq. De Villalobar 2",
    "sg:city":"Sint-pieters-woluwe/woluwe-saint-pierre",
    "sg:orig_category":"M\u00e9decins and sp\u00e9cialistes",
    "sg:phone":"+32 2 521 11 52",
    "sg:postcode":"1150",
    "sg:province":"Bruxelles-Capitale",
    "wof:name":"Doris Demoor",
    "wof:placetype":"venue"
},
  "geometry": {"coordinates":[4.4373531342,50.8270378113],"type":"Point"}
}