{
  "type": "Feature",
  "properties": {
    "addr:full":"Korenbloemstraat 8b Bree Limburg 3960",
    "addr:housenumber":"8b",
    "addr:postcode":"3960",
    "addr:street":"Korenbloemstraat",
    "iso:country":"BE",
    "sg:address":"Korenbloemstraat 8b",
    "sg:city":"Bree",
    "sg:classifiers":[
        {
            "category":"Professional",
            "type":"Services"
        }
    ],
    "sg:phone":"+32 89 48 17 08",
    "sg:postcode":"3960",
    "sg:province":"Limburg",
    "sg:tags":[
        "industrial",
        "automation"
    ],
    "wof:name":"Van Overeem Consulting",
    "wof:placetype":"venue"
},
  "geometry": {"coordinates":[5.6043801308,51.1519813538],"type":"Point"}
}