{
  "type": "Feature",
  "properties": {
    "iso:country":"BE",
    "sg:address":"Rue De Monnel 10",
    "sg:city":"Tournai",
    "sg:classifiers":[
        {
            "category":"Health Services",
            "subcategory":"Dentist",
            "type":"Services"
        }
    ],
    "sg:phone":"+32 69 22 70 31",
    "sg:postcode":"7500",
    "sg:province":"Hainaut",
    "wof:name":"Dehout J",
    "wof:placetype":"venue"
},
  "geometry": {"coordinates":[3.393791914,50.6098594666],"type":"Point"}
}