{
  "type": "Feature",
  "properties": {
    "addr:full":"Bertogne 53 Bertogne Luxembourg 6687",
    "addr:housenumber":"53",
    "addr:postcode":"6687",
    "addr:street":"Bertogne",
    "iso:country":"BE",
    "sg:address":"Bertogne 53",
    "sg:city":"Bertogne",
    "sg:classifiers":[
        {
            "category":"Professional",
            "type":"Services"
        }
    ],
    "sg:phone":"+32 61 21 40 07",
    "sg:postcode":"6687",
    "sg:province":"Luxembourg",
    "sg:tags":[
        "forestry",
        "agriculture",
        "-",
        "auctioneer"
    ],
    "wof:name":"Etienne M-a",
    "wof:placetype":"venue"
},
  "geometry": {"coordinates":[5.664085865,50.081237793],"type":"Point"}
}