{
  "type": "Feature",
  "properties": {
    "iso:country":"BE",
    "sg:address":"Mechelsesteenweg 1109",
    "sg:city":"Herent",
    "sg:orig_category":"Boucheries",
    "sg:phone":"+32 16 48 80 92",
    "sg:postcode":"3020",
    "sg:province":"Vlaams-Brabant",
    "wof:name":"Jan Verheyden",
    "wof:placetype":"venue"
},
  "geometry": {"coordinates":[4.64812994,50.9203414917],"type":"Point"}
}