{
  "type": "Feature",
  "properties": {
    "iso:country":"BE",
    "sg:address":"Chauss\u00e9e Romaine 90",
    "sg:city":"Gembloux-sur-orneau (gembloux)",
    "sg:classifiers":[
        {
            "category":"Utilities",
            "subcategory":"Natural Gas",
            "type":"Services"
        }
    ],
    "sg:phone":"+32 81 61 15 04",
    "sg:postcode":"5030",
    "sg:province":"Namur",
    "sg:tags":[
        "industrial",
        "-"
    ],
    "wof:name":"Vergote B",
    "wof:placetype":"venue"
},
  "geometry": {"coordinates":[4.6855530739,50.5792617798],"type":"Point"}
}