{
  "type": "Feature",
  "properties": {
    "addr:full":"Kapellekouter Wetteren (massemen) Oost-Vlaanderen 9230",
    "addr:postcode":"9230",
    "addr:street":"Oost-Vlaanderen",
    "iso:country":"BE",
    "sg:address":"Kapellekouter",
    "sg:city":"Wetteren (massemen)",
    "sg:classifiers":[
        {
            "category":"Building & Trades",
            "subcategory":"Landscaping Services",
            "type":"Services"
        }
    ],
    "sg:phone":"+32 9 369 94 33",
    "sg:postcode":"9230",
    "sg:province":"Oost-Vlaanderen",
    "sg:tags":[
        "access",
        "pond",
        "laying-out",
        "-"
    ],
    "wof:name":"Van De Steen G",
    "wof:placetype":"venue"
},
  "geometry": {"coordinates":[3.8855400085,51.0070304871],"type":"Point"}
}