{
  "type": "Feature",
  "properties": {
    "addr:full":"Rue Du Palais 25-27 Verviers Li\u00e8ge 4800",
    "addr:postcode":"25-27;4800",
    "addr:street":"Rue Du Palais",
    "iso:country":"BE",
    "sg:address":"Rue Du Palais 25-27",
    "sg:city":"Verviers",
    "sg:classifiers":[
        {
            "category":"Organizations",
            "subcategory":"Professional Association",
            "type":"Services"
        }
    ],
    "sg:phone":"+32 87 29 10 60",
    "sg:postcode":"4800",
    "sg:province":"Li\u00e8ge",
    "sg:tags":[
        "trade-union",
        "federation"
    ],
    "wof:name":"Conf\u00e9d\u00e9ration Construction-arrondissement De Verviers",
    "wof:placetype":"venue"
},
  "geometry": {"coordinates":[5.8638181686,50.5903091431],"type":"Point"}
}