{
  "type": "Feature",
  "properties": {
    "addr:full":"Kasteelstraat 6b3 Diksmuide West-Vlaanderen 8600",
    "addr:housenumber":"6b3",
    "addr:postcode":"8600",
    "addr:street":"Kasteelstraat",
    "iso:country":"BE",
    "sg:address":"Kasteelstraat 6b3",
    "sg:city":"Diksmuide",
    "sg:orig_category":"Installation de menuiserie en bois and plastique",
    "sg:phone":"+32 51 50 53 93",
    "sg:postcode":"8600",
    "sg:province":"West-Vlaanderen",
    "wof:name":"Kurt Spriet",
    "wof:placetype":"venue"
},
  "geometry": {"coordinates":[2.8555788994,51.0342063904],"type":"Point"}
}