{
  "type": "Feature",
  "properties": {
    "addr:full":"Wolterslaan 118 Gent Oost-Vlaanderen 9000",
    "addr:housenumber":"118",
    "addr:postcode":"9000",
    "addr:street":"Wolterslaan;Oost-Vlaanderen",
    "iso:country":"BE",
    "sg:address":"Wolterslaan 118",
    "sg:city":"Gent",
    "sg:classifiers":[
        {
            "category":"Food & Beverages",
            "subcategory":"Chocolate",
            "type":"Retail Goods"
        }
    ],
    "sg:phone":"+32 9 228 15 27",
    "sg:postcode":"9000",
    "sg:province":"Oost-Vlaanderen",
    "sg:tags":[
        "candy"
    ],
    "wof:name":"Chocolaterie D\u00e9esse B.v.b.a.",
    "wof:placetype":"venue"
},
  "geometry": {"coordinates":[3.7502040863,51.0482063293],"type":"Point"}
}