{
  "type": "Feature",
  "properties": {
    "addr:full":"Chauss\u00c9e De Ninove 715 Anderlecht Bruxelles-Capitale 1070",
    "addr:housenumber":"715",
    "addr:postcode":"1070",
    "addr:street":"Chausse\u0301E De Ninove",
    "iso:country":"BE",
    "sg:address":"Chauss\u00c9e De Ninove 715",
    "sg:city":"Anderlecht",
    "sg:orig_category":"Autoverhuur",
    "sg:phone":"+32 2 522 57 07",
    "sg:postcode":"1070",
    "sg:province":"Bruxelles-Capitale",
    "wof:name":"Avis",
    "wof:placetype":"venue"
},
  "geometry": {"coordinates":[4.2937898636,50.8466339111],"type":"Point"}
}