{
  "type": "Feature",
  "properties": {
    "iso:country":"BE",
    "sg:address":"Rue Ernotte 60",
    "sg:city":"Bruxelles",
    "sg:orig_category":"Activit\u00e9s r\u00e9cr\u00e9atives diverses",
    "sg:phone":"+32 2 673 47 60",
    "sg:postcode":"1170",
    "sg:province":"Bruxelles-Capitale",
    "wof:name":"Cercle Des Echecs De Watermael-boitsfort",
    "wof:placetype":"venue"
},
  "geometry": {"coordinates":[4.396709919,50.8040084839],"type":"Point"}
}