{
  "type": "Feature",
  "properties": {
    "addr:full":"Grand'rue 30 Sankt Vith/saint-vith Li\u00e8ge 4780",
    "addr:housenumber":"30",
    "addr:postcode":"4780",
    "addr:street":"Grand'Rue",
    "iso:country":"BE",
    "sg:address":"Grand'rue 30",
    "sg:city":"Sankt Vith/saint-vith",
    "sg:orig_category":"Banques and organismes de cr\u00e9dit",
    "sg:phone":"+32 80 22 61 12",
    "sg:postcode":"4780",
    "sg:province":"Li\u00e8ge",
    "wof:name":"Centea",
    "wof:placetype":"venue"
},
  "geometry": {"coordinates":[6.1256599426,50.2810783386],"type":"Point"}
}