{
  "type": "Feature",
  "properties": {
    "addr:full":"Alphonse Asselbergsstr. 78 Ukkel/uccle Bruxelles-Capitale 1180",
    "addr:housenumber":"78",
    "addr:postcode":"1180",
    "addr:street":"/",
    "iso:country":"BE",
    "sg:address":"Alphonse Asselbergsstr. 78",
    "sg:city":"Ukkel/uccle",
    "sg:orig_category":"Boekhouders",
    "sg:phone":"+32 2 376 11 48",
    "sg:postcode":"1180",
    "sg:province":"Bruxelles-Capitale",
    "wof:name":"Henri Vanherberghen",
    "wof:placetype":"venue"
},
  "geometry": {"coordinates":[4.3326840401,50.8057250977],"type":"Point"}
}