{
  "type": "Feature",
  "properties": {
    "addr:full":"Mezenstraat 72 Bertem Vlaams-Brabant 3061",
    "addr:housenumber":"72",
    "addr:postcode":"3061",
    "addr:street":"Mezenstraat",
    "iso:country":"BE",
    "sg:address":"Mezenstraat 72",
    "sg:city":"Bertem",
    "sg:orig_category":"Loodgieterij, verwarming and sanitaire installaties",
    "sg:phone":"+32 2 767 61 52",
    "sg:postcode":"3061",
    "sg:province":"Vlaams-Brabant",
    "wof:name":"Van Campenhoudt",
    "wof:placetype":"venue"
},
  "geometry": {"coordinates":[4.5818939209,50.8498306274],"type":"Point"}
}