{
  "type": "Feature",
  "properties": {
    "addr:full":"Tuileboomstraat 17 Sint-eloois-winkel West-Vlaanderen 8880",
    "addr:housenumber":"17",
    "addr:postcode":"8880",
    "addr:street":"Tuileboomstraat;West-Vlaanderen",
    "iso:country":"BE",
    "sg:address":"Tuileboomstraat 17",
    "sg:city":"Sint-eloois-winkel",
    "sg:orig_category":"HOTELS: CHINA",
    "sg:phone":"+32 3 887 80 00",
    "sg:postcode":"8880",
    "sg:province":"West-Vlaanderen",
    "wof:name":"Hgr Verbeelen & Compagnie Nv",
    "wof:placetype":"venue"
},
  "geometry": {"coordinates":[4.3719339371,51.1542778015],"type":"Point"}
}