{
  "type": "Feature",
  "properties": {
    "addr:full":"Rerum-novarumplein 28 Gent Oost-Vlaanderen 9000",
    "addr:housenumber":"28",
    "addr:postcode":"9000",
    "addr:street":"Rerum-Novarumplein;Oost-Vlaanderen",
    "iso:country":"BE",
    "sg:address":"Rerum-novarumplein 28",
    "sg:city":"Gent",
    "sg:classifiers":[
        {
            "category":"Government",
            "subcategory":"Police Station",
            "type":"Public Place"
        }
    ],
    "sg:phone":"+32 9 266 66 71",
    "sg:postcode":"9000",
    "sg:province":"Oost-Vlaanderen",
    "sg:tags":[
        "gendarmerie"
    ],
    "wof:name":"Federale Politie",
    "wof:placetype":"venue"
},
  "geometry": {"coordinates":[3.7188808918,51.0236549377],"type":"Point"}
}