{
  "type": "Feature",
  "properties": {
    "addr:full":"Rue Fabry 35 Li\u00c8ge Li\u00e8ge 4000",
    "addr:housenumber":"35",
    "addr:postcode":"4000",
    "addr:street":"Rue Fabry",
    "iso:country":"BE",
    "sg:address":"Rue Fabry 35",
    "sg:city":"Li\u00c8ge",
    "sg:classifiers":[
        {
            "category":"Shopping",
            "subcategory":"Bicycles & Sporting Goods",
            "type":"Retail Goods"
        }
    ],
    "sg:phone":"+32 4 252 83 47",
    "sg:postcode":"4000",
    "sg:province":"Li\u00e8ge",
    "sg:tags":[
        "article",
        "de",
        "sport",
        "camping"
    ],
    "wof:name":"La Scouterie",
    "wof:placetype":"venue"
},
  "geometry": {"coordinates":[5.5657668114,50.6301574707],"type":"Point"}
}