{
  "type": "Feature",
  "properties": {
    "addr:full":"Gentstraat 24 Deinze Oost-Vlaanderen 9800",
    "addr:housenumber":"24",
    "addr:postcode":"9800",
    "addr:street":"Gentstraat",
    "iso:country":"BE",
    "sg:address":"Gentstraat 24",
    "sg:city":"Deinze",
    "sg:classifiers":[
        {
            "category":"Home & Garden",
            "subcategory":"Home Furnishings",
            "type":"Retail Goods"
        }
    ],
    "sg:phone":"+32 9 386 15 41",
    "sg:postcode":"9800",
    "sg:province":"Oost-Vlaanderen",
    "sg:tags":[
        "interior",
        "decoration"
    ],
    "wof:name":"D'haenens F",
    "wof:placetype":"venue"
},
  "geometry": {"coordinates":[3.5320990086,50.9797668457],"type":"Point"}
}