{
  "type": "Feature",
  "properties": {
    "iso:country":"BE",
    "sg:address":"Galglaan 32",
    "sg:city":"Gent",
    "sg:classifiers":[
        {
            "category":"Health Services",
            "subcategory":"Health Practitioner",
            "type":"Services"
        }
    ],
    "sg:phone":"+32 9 221 22 49",
    "sg:postcode":"9000",
    "sg:province":"Oost-Vlaanderen",
    "sg:tags":[
        "physiotherapist"
    ],
    "wof:name":"Gadeyne Philip",
    "wof:placetype":"venue"
},
  "geometry": {"coordinates":[3.7203249931,51.0255279541],"type":"Point"}
}