{
  "type": "Feature",
  "properties": {
    "addr:full":"Diksmuidesteenweg 32 A Staden West-Vlaanderen 8840",
    "addr:housenumber":"32 a",
    "addr:postcode":"8840",
    "addr:street":"Diksmuidesteenweg",
    "iso:country":"BE",
    "sg:address":"Diksmuidesteenweg 32 A",
    "sg:city":"Staden",
    "sg:orig_category":"Mat\u00e9riel de contr\u00f4le des processus industriels Fab",
    "sg:phone":"+32 51 24 05 62",
    "sg:postcode":"8840",
    "sg:province":"West-Vlaanderen",
    "wof:name":"Boone Hydro-elektro",
    "wof:placetype":"venue"
},
  "geometry": {"coordinates":[3.0098230839,50.9773139954],"type":"Point"}
}