{
  "type": "Feature",
  "properties": {
    "addr:full":"Sint-jorisstraat 53 Brugge West-Vlaanderen 8000",
    "addr:housenumber":"53",
    "addr:postcode":"8000",
    "addr:street":"Sint-Jorisstraat",
    "iso:country":"BE",
    "sg:address":"Sint-jorisstraat 53",
    "sg:city":"Brugge",
    "sg:classifiers":[
        {
            "category":"Food & Beverages",
            "subcategory":"Specialty",
            "type":"Retail Goods"
        }
    ],
    "sg:phone":"+32 50 34 09 33",
    "sg:postcode":"8000",
    "sg:province":"West-Vlaanderen",
    "sg:tags":[
        "health",
        "dietary",
        "-",
        "biological"
    ],
    "wof:name":"De Grote Beer",
    "wof:placetype":"venue"
},
  "geometry": {"coordinates":[3.2213289738,51.2143478394],"type":"Point"}
}