{
  "type": "Feature",
  "properties": {
    "addr:full":"Dorpsstraat 22 Sint-laureins Oost-Vlaanderen 9980",
    "addr:housenumber":"22",
    "addr:postcode":"9980",
    "addr:street":"Dorpsstraat",
    "iso:country":"BE",
    "sg:address":"Dorpsstraat 22",
    "sg:city":"Sint-laureins",
    "sg:classifiers":[
        {
            "category":"Wholesale",
            "subcategory":"Plants",
            "type":"Manufacturing & Wholesale Goods"
        }
    ],
    "sg:phone":"+32 9 379 85 88",
    "sg:postcode":"9980",
    "sg:province":"Oost-Vlaanderen",
    "sg:tags":[
        "whol",
        "flower",
        "-",
        "grower"
    ],
    "wof:name":"Van Gucht L",
    "wof:placetype":"venue"
},
  "geometry": {"coordinates":[3.5184350014,51.2435722351],"type":"Point"}
}