{
  "type": "Feature",
  "properties": {
    "iso:country":"BE",
    "sg:address":"Pacificatiestraat 34",
    "sg:city":"Antwerpen",
    "sg:classifiers":[
        {
            "category":"Arts & Performance",
            "subcategory":"Art Gallery",
            "type":"Entertainment"
        }
    ],
    "sg:phone":"+32 3 248 84 83",
    "sg:postcode":"2000",
    "sg:province":"Antwerpen",
    "wof:name":"Galerij Zuid",
    "wof:placetype":"venue"
},
  "geometry": {"coordinates":[4.3897538185,51.2060699463],"type":"Point"}
}