{
  "type": "Feature",
  "properties": {
    "addr:full":"Rue Basse Campagne 45 Herstal Li\u00e8ge 4040",
    "addr:housenumber":"45",
    "addr:postcode":"4040",
    "addr:street":"Rue Basse Campagne",
    "iso:country":"BE",
    "sg:address":"Rue Basse Campagne 45",
    "sg:city":"Herstal",
    "sg:orig_category":"Meubelzaken, woning- and keukeninrichting Verlichting and huishoudartikelen Vloer- and muurbekleding",
    "sg:phone":"+32 4 264 50 54",
    "sg:postcode":"4040",
    "sg:province":"Li\u00e8ge",
    "wof:name":"Leenbakker",
    "wof:placetype":"venue"
},
  "geometry": {"coordinates":[5.644288063,50.6865234375],"type":"Point"}
}