{
  "type": "Feature",
  "properties": {
    "iso:country":"BE",
    "sg:address":"Winkel 29",
    "sg:city":"Turnhout",
    "sg:classifiers":[
        {
            "category":"Building & Trades",
            "subcategory":"Plumbing",
            "type":"Services"
        }
    ],
    "sg:phone":"+32 14 85 14 68",
    "sg:postcode":"2300",
    "sg:province":"Antwerpen",
    "sg:tags":[
        "repair",
        "mainten",
        "-",
        "central",
        "heating"
    ],
    "wof:name":"Van Loy G",
    "wof:placetype":"venue"
},
  "geometry": {"coordinates":[4.9522500038,51.2754936218],"type":"Point"}
}