{
  "type": "Feature",
  "properties": {
    "addr:full":"Hoevestraat 22 Sint-genesius-rode/rhode-saint-genese Vlaams-Brabant 1640",
    "addr:housenumber":"22",
    "addr:postcode":"1640",
    "addr:street":"Hoevestraat",
    "iso:country":"BE",
    "sg:address":"Hoevestraat 22",
    "sg:city":"Sint-genesius-rode/rhode-saint-genese",
    "sg:orig_category":"Artsen and specialisten",
    "sg:phone":"+32 2 380 81 49",
    "sg:postcode":"1640",
    "sg:province":"Vlaams-Brabant",
    "wof:name":"M. Pieront",
    "wof:placetype":"venue"
},
  "geometry": {"coordinates":[4.3574938774,50.7521972656],"type":"Point"}
}