{
  "type": "Feature",
  "properties": {
    "iso:country":"BE",
    "sg:address":"Chemin Des Vignerons 27",
    "sg:city":"Namur (w\u00e9pion)",
    "sg:classifiers":[
        {
            "category":"Health Services",
            "subcategory":"Health Practitioner",
            "type":"Services"
        }
    ],
    "sg:phone":"+32 81 46 21 41",
    "sg:postcode":"5100",
    "sg:province":"Namur",
    "sg:tags":[
        "dietitian"
    ],
    "wof:name":"Henrard Christian",
    "wof:placetype":"venue"
},
  "geometry": {"coordinates":[4.8619570732,50.4254074097],"type":"Point"}
}