{
  "type": "Feature",
  "properties": {
    "addr:full":"Krapstraat 66 Buggenhout Oost-Vlaanderen 9255",
    "addr:housenumber":"66",
    "addr:postcode":"9255",
    "addr:street":"Krapstraat",
    "iso:country":"BE",
    "sg:address":"Krapstraat 66",
    "sg:city":"Buggenhout",
    "sg:orig_category":"Diverse bedrijfsbeheeradviesbureaus",
    "sg:phone":"+32 52 33 05 77",
    "sg:postcode":"9255",
    "sg:province":"Oost-Vlaanderen",
    "wof:name":"Cd Management",
    "wof:placetype":"venue"
},
  "geometry": {"coordinates":[4.1813378334,51.004989624],"type":"Point"}
}