{
  "type": "Feature",
  "properties": {
    "addr:full":"Boulevard Edmond Machtens 75 Box 17 Bruxelles (molenbeek-saint-jean) Bruxelles-Capitale 1080",
    "addr:housenumber":"75 box 17",
    "addr:postcode":"1080",
    "addr:street":"Boulevard Edmond Machtens",
    "iso:country":"BE",
    "sg:address":"Boulevard Edmond Machtens 75 Box 17",
    "sg:city":"Bruxelles (molenbeek-saint-jean)",
    "sg:classifiers":[
        {
            "category":"Retail",
            "subcategory":"Veterinary Services",
            "type":"Services"
        }
    ],
    "sg:phone":"+32 2 415 92 22",
    "sg:postcode":"1080",
    "sg:province":"Bruxelles-Capitale",
    "sg:tags":[
        "veterinarian"
    ],
    "wof:name":"Van Den Borre M",
    "wof:placetype":"venue"
},
  "geometry": {"coordinates":[4.3137998581,50.8518180847],"type":"Point"}
}