{
  "type": "Feature",
  "properties": {
    "addr:full":"Assenedesteenweg 221 Zelzate Oost-Vlaanderen 9060",
    "addr:housenumber":"221",
    "addr:postcode":"9060",
    "addr:street":"Assenedesteenweg",
    "iso:country":"BE",
    "sg:address":"Assenedesteenweg 221",
    "sg:city":"Zelzate",
    "sg:classifiers":[
        {
            "category":"Bars & Pubs",
            "type":"Food & Drink"
        }
    ],
    "sg:phone":"+32 9 344 06 10",
    "sg:postcode":"9060",
    "sg:province":"Oost-Vlaanderen",
    "wof:name":"Jenny",
    "wof:placetype":"venue"
},
  "geometry": {"coordinates":[3.7849829197,51.2022514343],"type":"Point"}
}