{
  "type": "Feature",
  "properties": {
    "iso:country":"BE",
    "sg:address":"Eikelendreef 6",
    "sg:city":"Beringen",
    "sg:orig_category":"Maisons de vacances",
    "sg:phone":"+32 11 42 99 45",
    "sg:postcode":"3582",
    "sg:province":"Limburg",
    "wof:name":"Domein Steenveld",
    "wof:placetype":"venue"
},
  "geometry": {"coordinates":[5.2708749771,51.0595359802],"type":"Point"}
}