{
  "type": "Feature",
  "properties": {
    "addr:full":". Ramillies Brabant Wallon 1367",
    "addr:postcode":"1367",
    "iso:country":"BE",
    "sg:address":".",
    "sg:city":"Ramillies",
    "sg:orig_category":"Huisdierenkwekers",
    "sg:phone":"+32 10 81 12 40",
    "sg:postcode":"1367",
    "sg:province":"Brabant Wallon",
    "wof:name":"Canichoules Petites Beaut\u00c9es",
    "wof:placetype":"venue"
},
  "geometry": {"coordinates":[4.9146900177,50.636631012],"type":"Point"}
}