{
  "type": "Feature",
  "properties": {
    "addr:full":"Dorpstraat 5 Ichtegem West-Vlaanderen 8480",
    "addr:housenumber":"5",
    "addr:postcode":"8480",
    "addr:street":"Dorpstraat",
    "iso:country":"BE",
    "sg:address":"Dorpstraat 5",
    "sg:city":"Ichtegem",
    "sg:orig_category":"Enseignement maternel and primaire",
    "sg:phone":"+32 50 81 40 83",
    "sg:postcode":"8480",
    "sg:province":"West-Vlaanderen",
    "wof:name":"Vrije Basisschool",
    "wof:placetype":"venue"
},
  "geometry": {"coordinates":[3.0468099117,51.1594314575],"type":"Point"}
}