{
  "type": "Feature",
  "properties": {
    "addr:full":"Avenue Misonne 27 Ch\u00e2telet (ch\u00e2telineau) Hainaut 6200",
    "addr:housenumber":"27",
    "addr:postcode":"6200",
    "addr:street":"Avenue Misonne",
    "iso:country":"BE",
    "sg:address":"Avenue Misonne 27",
    "sg:city":"Ch\u00e2telet (ch\u00e2telineau)",
    "sg:classifiers":[
        {
            "category":"Professional",
            "subcategory":"Accounting & Tax Preparation",
            "type":"Services"
        }
    ],
    "sg:phone":"+32 71 39 74 62",
    "sg:postcode":"6200",
    "sg:province":"Hainaut",
    "sg:tags":[
        "bookkeeper"
    ],
    "wof:name":"Delreux P",
    "wof:placetype":"venue"
},
  "geometry": {"coordinates":[4.5227570534,50.4149856567],"type":"Point"}
}