{
  "type": "Feature",
  "properties": {
    "addr:full":"Pastoor Pitetlaan 26 Begijnendijk (betekom) Vlaams-Brabant 3130",
    "addr:housenumber":"26",
    "addr:postcode":"3130",
    "addr:street":"Pastoor Pitetlaan",
    "iso:country":"BE",
    "sg:address":"Pastoor Pitetlaan 26",
    "sg:city":"Begijnendijk (betekom)",
    "sg:classifiers":[
        {
            "category":"Education",
            "subcategory":"School",
            "type":"Public Place"
        }
    ],
    "sg:phone":"+32 16 56 25 72",
    "sg:postcode":"3130",
    "sg:province":"Vlaams-Brabant",
    "sg:tags":[
        "primary"
    ],
    "wof:name":"Sjibke ('t)",
    "wof:placetype":"venue"
},
  "geometry": {"coordinates":[4.7815198898,50.9864883423],"type":"Point"}
}