{
  "type": "Feature",
  "properties": {
    "addr:full":"Avenue Des Casernes 61 Bruxelles (etterbeek) Bruxelles-Capitale 1040",
    "addr:housenumber":"61",
    "addr:postcode":"1040",
    "addr:street":"Avenue Des Casernes",
    "iso:country":"BE",
    "sg:address":"Avenue Des Casernes 61",
    "sg:city":"Bruxelles (etterbeek)",
    "sg:classifiers":[
        {
            "category":"Shopping",
            "subcategory":"Antiques",
            "type":"Retail Goods"
        }
    ],
    "sg:phone":"+32 2 640 29 16",
    "sg:postcode":"1040",
    "sg:province":"Bruxelles-Capitale",
    "wof:name":"Hemeleers Frantz",
    "wof:placetype":"venue"
},
  "geometry": {"coordinates":[4.3902111053,50.8273239136],"type":"Point"}
}