{
  "type": "Feature",
  "properties": {
    "iso:country":"BE",
    "sg:address":"Toekomststraat 68",
    "sg:city":"Waregem",
    "sg:orig_category":"Slagers",
    "sg:phone":"+32 56 60 17 43",
    "sg:postcode":"8790",
    "sg:province":"West-Vlaanderen",
    "wof:name":"Walter Baert",
    "wof:placetype":"venue"
},
  "geometry": {"coordinates":[3.4188199043,50.8864784241],"type":"Point"}
}