{
  "type": "Feature",
  "properties": {
    "iso:country":"BE",
    "sg:address":"Clos Dandoy 2",
    "sg:city":"Ukkel/uccle",
    "sg:orig_category":"M\u00e9decins and sp\u00e9cialistes",
    "sg:phone":"+32 2 374 33 44",
    "sg:postcode":"1180",
    "sg:province":"Bruxelles-Capitale",
    "wof:name":"Jacques Massaux",
    "wof:placetype":"venue"
},
  "geometry": {"coordinates":[4.361577034,50.8070487976],"type":"Point"}
}