{
  "type": "Feature",
  "properties": {
    "iso:country":"BE",
    "sg:address":"Majoor Woodstraat 11",
    "sg:city":"Oostkamp",
    "sg:classifiers":[
        {
            "category":"Health Services",
            "subcategory":"Dentist",
            "type":"Services"
        }
    ],
    "sg:phone":"+32 50 82 25 48",
    "sg:postcode":"8020",
    "sg:province":"West-Vlaanderen",
    "wof:name":"Herteleer P",
    "wof:placetype":"venue"
},
  "geometry": {"coordinates":[3.2345240116,51.1543159485],"type":"Point"}
}