{
  "type": "Feature",
  "properties": {
    "addr:full":"Muizensteenweg 6 Bonheiden Antwerpen 2820",
    "addr:housenumber":"6",
    "addr:postcode":"2820",
    "addr:street":"Muizensteenweg",
    "iso:country":"BE",
    "sg:address":"Muizensteenweg 6",
    "sg:city":"Bonheiden",
    "sg:classifiers":[
        {
            "category":"Banks & Credit Unions",
            "subcategory":"Investment Brokerage",
            "type":"Services"
        }
    ],
    "sg:phone":"+32 15 51 13 13",
    "sg:postcode":"2820",
    "sg:province":"Antwerpen",
    "wof:name":"De Herdt E",
    "wof:placetype":"venue"
},
  "geometry": {"coordinates":[4.5425629616,51.0234565735],"type":"Point"}
}