{
  "type": "Feature",
  "properties": {
    "addr:full":"Vingerlingstraat 3 Antwerpen Antwerpen 2000",
    "addr:housenumber":"3",
    "addr:postcode":"2000",
    "addr:street":"Vingerlingstraat",
    "iso:country":"BE",
    "sg:address":"Vingerlingstraat 3",
    "sg:city":"Antwerpen",
    "sg:classifiers":[
        {
            "category":"Bars & Pubs",
            "type":"Food & Drink"
        }
    ],
    "sg:phone":"+32 3 232 50 48",
    "sg:postcode":"2000",
    "sg:province":"Antwerpen",
    "wof:name":"Perla (la)",
    "wof:placetype":"venue"
},
  "geometry": {"coordinates":[4.4036221504,51.2263183594],"type":"Point"}
}