{
  "type": "Feature",
  "properties": {
    "iso:country":"BE",
    "sg:address":"Opperstraat 126",
    "sg:city":"Liedekerke",
    "sg:orig_category":"Pharmaciens",
    "sg:phone":"+32 53 66 74 74",
    "sg:postcode":"1770",
    "sg:province":"Vlaams-Brabant",
    "wof:name":"Paul De Schepper",
    "wof:placetype":"venue"
},
  "geometry": {"coordinates":[4.0896477699,50.8690986633],"type":"Point"}
}