{
  "type": "Feature",
  "properties": {
    "iso:country":"BE",
    "sg:address":"Graethemstraat 11b2",
    "sg:city":"Borgloon",
    "sg:orig_category":"Belastingconsulenten Diverse juridische dienstverlening",
    "sg:phone":"+32 12 67 08 08",
    "sg:postcode":"3840",
    "sg:province":"Limburg",
    "wof:name":"Ben-account",
    "wof:placetype":"venue"
},
  "geometry": {"coordinates":[5.3425011635,50.8029670715],"type":"Point"}
}