{
  "type": "Feature",
  "properties": {
    "iso:country":"BE",
    "sg:address":"Sauveghrdestraat 51",
    "sg:city":"Ruisbroek",
    "sg:orig_category":"Electrom\u00e9nager, t\u00e9l\u00e9visions and radios",
    "sg:phone":"+32 3 889 38 66",
    "sg:postcode":"2870",
    "sg:province":"Antwerpen",
    "wof:name":"Daelemans Koeltechniek",
    "wof:placetype":"venue"
},
  "geometry": {"coordinates":[4.2772698402,51.0763244629],"type":"Point"}
}