{
  "type": "Feature",
  "properties": {
    "iso:country":"BE",
    "sg:address":"Meulebeeksestraat 38ba",
    "sg:city":"Ardooie",
    "sg:orig_category":"Producteurs de l\u00e9gumes",
    "sg:phone":"+32 51 74 59 00",
    "sg:postcode":"8850",
    "sg:province":"West-Vlaanderen",
    "wof:name":"Greet Biesbrouk",
    "wof:placetype":"venue"
},
  "geometry": {"coordinates":[3.2410640717,50.9654922485],"type":"Point"}
}