{
  "type": "Feature",
  "properties": {
    "iso:country":"BE",
    "sg:address":"Chauss\u00c9e De Waterloo 992",
    "sg:city":"Ukkel/uccle",
    "sg:orig_category":"Epiceries",
    "sg:phone":"+32 2 374 04 55",
    "sg:postcode":"1180",
    "sg:province":"Bruxelles-Capitale",
    "wof:name":"P\u00c2tisserie Serroukh",
    "wof:placetype":"venue"
},
  "geometry": {"coordinates":[4.3741960526,50.8010940552],"type":"Point"}
}