{
  "type": "Feature",
  "properties": {
    "iso:country":"BE",
    "sg:address":"Avenue Hanssen-soulie 78",
    "sg:city":"Bruxelles-etterbeek",
    "sg:orig_category":"Restaurants Verhuur cateringmateriaal and evenementuitrusting Winkelinrichting and handelsuitrusting",
    "sg:phone":"+32 2 734 35 25",
    "sg:postcode":"1040",
    "sg:province":"Bruxelles-Capitale",
    "wof:name":"L'r Du Temps",
    "wof:placetype":"venue"
},
  "geometry": {"coordinates":[4.3997998238,50.8301773071],"type":"Point"}
}