{
  "type": "Feature",
  "properties": {
    "iso:country":"BE",
    "sg:address":"Koolskampstraat 64",
    "sg:city":"Lichtervelde",
    "sg:orig_category":"Cnc-Milled Parts",
    "sg:phone":"+32 51 72 29 01",
    "sg:postcode":"8810",
    "sg:province":"West-Vlaanderen",
    "wof:name":"Radius Fijnmechaniek Nv",
    "wof:placetype":"venue"
},
  "geometry": {"coordinates":[3.148761034,51.0239868164],"type":"Point"}
}