{
  "type": "Feature",
  "properties": {
    "addr:full":"Avenue De Tervueren 196 Box 9 Bruxelles (woluwe-saint-pierre) Bruxelles-Capitale 1150",
    "addr:housenumber":"196;9",
    "addr:postcode":"1150",
    "addr:street":"Avenue De Tervueren;Box",
    "iso:country":"BE",
    "sg:address":"Avenue De Tervueren 196 Box 9",
    "sg:city":"Bruxelles (woluwe-saint-pierre)",
    "sg:classifiers":[
        {
            "category":"Real Estate",
            "subcategory":"Real Estate Services",
            "type":"Services"
        }
    ],
    "sg:phone":"+32 2 772 70 89",
    "sg:postcode":"1150",
    "sg:province":"Bruxelles-Capitale",
    "wof:name":"Via Veneto Investment Sprl",
    "wof:placetype":"venue"
},
  "geometry": {"coordinates":[4.4126091003,50.8367843628],"type":"Point"}
}