{
  "type": "Feature",
  "properties": {
    "iso:country":"BE",
    "sg:address":"6671",
    "sg:city":"Gouvy",
    "sg:orig_category":"Activit\u00e9s d\u00b4action sociale sans h\u00e9bergement",
    "sg:phone":"+32 80 51 70 40",
    "sg:postcode":"6671",
    "sg:province":"Luxembourg",
    "wof:name":"La Croix Rouge",
    "wof:placetype":"venue"
},
  "geometry": {"coordinates":[5.9265899658,50.2296295166],"type":"Point"}
}