{
  "type": "Feature",
  "properties": {
    "addr:full":"Kamerstraat 34 Buggenhout Oost-Vlaanderen 9255",
    "addr:housenumber":"34",
    "addr:postcode":"9255",
    "addr:street":"Kamerstraat",
    "iso:country":"BE",
    "sg:address":"Kamerstraat 34",
    "sg:city":"Buggenhout",
    "sg:orig_category":"Kapsalons",
    "sg:phone":"+32 52 33 44 90",
    "sg:postcode":"9255",
    "sg:province":"Oost-Vlaanderen",
    "wof:name":"Coiffure Willy",
    "wof:placetype":"venue"
},
  "geometry": {"coordinates":[4.2023429871,51.0192832947],"type":"Point"}
}