{
  "type": "Feature",
  "properties": {
    "addr:full":"Torenlaan 89 Waregem West-Vlaanderen 8790",
    "addr:housenumber":"89",
    "addr:postcode":"8790",
    "addr:street":"Torenlaan",
    "iso:country":"BE",
    "sg:address":"Torenlaan 89",
    "sg:city":"Waregem",
    "sg:classifiers":[
        {
            "category":"Building & Trades",
            "subcategory":"Landscaping Services",
            "type":"Services"
        }
    ],
    "sg:phone":"+32 56 61 34 87",
    "sg:postcode":"8790",
    "sg:province":"West-Vlaanderen",
    "sg:tags":[
        "gardening",
        "garden",
        "maintenance"
    ],
    "wof:name":"Vandelanotte P",
    "wof:placetype":"venue"
},
  "geometry": {"coordinates":[3.4391989708,50.8911132812],"type":"Point"}
}