{
  "type": "Feature",
  "properties": {
    "iso:country":"BE",
    "sg:address":"Hertenlaan 13",
    "sg:city":"Hoeilaart",
    "sg:classifiers":[
        {
            "category":"Health Services",
            "subcategory":"Dentist",
            "type":"Services"
        }
    ],
    "sg:phone":"+32 2 657 33 62",
    "sg:postcode":"1560",
    "sg:province":"Vlaams-Brabant",
    "wof:name":"Delescaille P",
    "wof:placetype":"venue"
},
  "geometry": {"coordinates":[4.45540905,50.7788963318],"type":"Point"}
}