{
  "type": "Feature",
  "properties": {
    "addr:full":"Rue Bastenier 48 La Louvi\u00e8re (saint-vaast) Hainaut 7100",
    "addr:housenumber":"48",
    "addr:postcode":"7100",
    "addr:street":"Rue Bastenier",
    "iso:country":"BE",
    "sg:address":"Rue Bastenier 48",
    "sg:city":"La Louvi\u00e8re (saint-vaast)",
    "sg:classifiers":[
        {
            "category":"Professional",
            "type":"Services"
        }
    ],
    "sg:phone":"+32 64 23 96 00",
    "sg:postcode":"7100",
    "sg:province":"Hainaut",
    "sg:tags":[
        "industrial",
        "work",
        "-",
        "maintenance"
    ],
    "wof:name":"Montacentre Sa",
    "wof:placetype":"venue"
},
  "geometry": {"coordinates":[4.1762971878,50.4663772583],"type":"Point"}
}