{
  "type": "Feature",
  "properties": {
    "addr:full":"Place Des Doyens 1 Ottignies-louvain-la-neuve Brabant Wallon 1348",
    "addr:housenumber":"1",
    "addr:postcode":"1348",
    "addr:street":"Place Des Doyens",
    "iso:country":"BE",
    "sg:address":"Place Des Doyens 1",
    "sg:city":"Ottignies-louvain-la-neuve",
    "sg:orig_category":"Enseignement sup\u00e9rieur",
    "sg:phone":"+32 10 47 83 00",
    "sg:postcode":"1348",
    "sg:province":"Brabant Wallon",
    "wof:name":"U.c.l.-d\u00c9p.admin.& Gest.",
    "wof:placetype":"venue"
},
  "geometry": {"coordinates":[4.6121249199,50.6682701111],"type":"Point"}
}