{
  "type": "Feature",
  "properties": {
    "iso:country":"BE",
    "sg:address":"Kleitestraat 18",
    "sg:city":"Aalter",
    "sg:orig_category":"Varkenskwekers",
    "sg:phone":"+32 9 371 62 47",
    "sg:postcode":"9880",
    "sg:province":"Oost-Vlaanderen",
    "wof:name":"Hugo Sucaet",
    "wof:placetype":"venue"
},
  "geometry": {"coordinates":[3.4864039421,51.0338973999],"type":"Point"}
}