{
  "type": "Feature",
  "properties": {
    "addr:full":"Kasteelstraat 22 Langemark-poelkapelle West-Vlaanderen 8920",
    "addr:housenumber":"22",
    "addr:postcode":"8920",
    "addr:street":"Kasteelstraat",
    "iso:country":"BE",
    "sg:address":"Kasteelstraat 22",
    "sg:city":"Langemark-poelkapelle",
    "sg:orig_category":"Banken and kredietinstellingen",
    "sg:phone":"+32 57 48 86 44",
    "sg:postcode":"8920",
    "sg:province":"West-Vlaanderen",
    "wof:name":"Bank Van Roeselare",
    "wof:placetype":"venue"
},
  "geometry": {"coordinates":[2.919770956,50.9132423401],"type":"Point"}
}