{
  "type": "Feature",
  "properties": {
    "iso:country":"BE",
    "sg:address":"Larenweg 10",
    "sg:city":"Wuustwezel",
    "sg:orig_category":"Eleveurs de bovins. Eleveurs and marchands de porcs",
    "sg:phone":"+32 3 669 63 86",
    "sg:postcode":"2990",
    "sg:province":"Antwerpen",
    "wof:name":"Joannes Aertsen",
    "wof:placetype":"venue"
},
  "geometry": {"coordinates":[4.6546998024,51.4234657288],"type":"Point"}
}