{
  "type": "Feature",
  "properties": {
    "addr:full":"Muinkkaai 73 Gent Oost-Vlaanderen 9000",
    "addr:housenumber":"73",
    "addr:postcode":"9000",
    "addr:street":"Muinkkaai;Oost-Vlaanderen",
    "iso:country":"BE",
    "sg:address":"Muinkkaai 73",
    "sg:city":"Gent",
    "sg:classifiers":[
        {
            "category":"Home & Garden",
            "subcategory":"Kitchen Supply",
            "type":"Retail Goods"
        }
    ],
    "sg:phone":"+32 9 233 51 59",
    "sg:postcode":"9000",
    "sg:province":"Oost-Vlaanderen",
    "sg:tags":[
        "plotter",
        "-",
        "apparatus"
    ],
    "wof:name":"Double Precision",
    "wof:placetype":"venue"
},
  "geometry": {"coordinates":[3.7314600945,51.0432510376],"type":"Point"}
}