{
  "type": "Feature",
  "properties": {
    "addr:full":"Boulevard De L'europe 3 Wavre Brabant Wallon 1300",
    "addr:housenumber":"3;1300",
    "addr:street":"Boulevard De L'Europe",
    "iso:country":"BE",
    "sg:address":"Boulevard De L'europe 3",
    "sg:city":"Wavre",
    "sg:classifiers":[
        {
            "category":"Personal",
            "subcategory":"Beauty Salon",
            "type":"Services"
        }
    ],
    "sg:phone":"+32 10 22 63 51",
    "sg:postcode":"1300",
    "sg:province":"Brabant Wallon",
    "sg:tags":[
        "de",
        "coiffure"
    ],
    "wof:name":"Salon Martin",
    "wof:placetype":"venue"
},
  "geometry": {"coordinates":[4.6100921631,50.7142791748],"type":"Point"}
}