{
  "type": "Feature",
  "properties": {
    "iso:country":"BE",
    "sg:address":"Meyenbos 4",
    "sg:city":"Merksplas",
    "sg:orig_category":"Plantes and fleurs Gr",
    "sg:phone":"+32 14 63 53 08",
    "sg:postcode":"2330",
    "sg:province":"Antwerpen",
    "wof:name":"Pelckmans - Gijsels",
    "wof:placetype":"venue"
},
  "geometry": {"coordinates":[4.8905482292,51.3430595398],"type":"Point"}
}