{
  "type": "Feature",
  "properties": {
    "iso:country":"BE",
    "sg:address":"Neerstraat 107",
    "sg:city":"Tessenderlo",
    "sg:classifiers":[
        {
            "category":"Professional",
            "subcategory":"Computer Services",
            "type":"Services"
        }
    ],
    "sg:phone":"+32 13 67 76 66",
    "sg:postcode":"3980",
    "sg:province":"Limburg",
    "sg:tags":[
        "-",
        "processing",
        "data",
        "software"
    ],
    "wof:name":"Famca Informatica",
    "wof:placetype":"venue"
},
  "geometry": {"coordinates":[5.089222908,51.0728607178],"type":"Point"}
}