{
  "type": "Feature",
  "properties": {
    "addr:full":"Woluwelaan 31 Machelen Vlaams-Brabant 1830",
    "addr:housenumber":"31",
    "addr:postcode":"1830",
    "addr:street":"Woluwelaan",
    "iso:country":"BE",
    "sg:address":"Woluwelaan 31",
    "sg:city":"Machelen",
    "sg:orig_category":"Sociale huisvestingsmaatschappijen",
    "sg:phone":"+32 2 251 81 21",
    "sg:postcode":"1830",
    "sg:province":"Vlaams-Brabant",
    "wof:name":"Machelse Huisvesting",
    "wof:placetype":"venue"
},
  "geometry": {"coordinates":[4.4304409027,50.9104881287],"type":"Point"}
}