{
  "type": "Feature",
  "properties": {
    "iso:country":"BE",
    "sg:address":"Rue Du Village 3ba",
    "sg:city":"Mettet",
    "sg:orig_category":"Enseignement maternel and primaire",
    "sg:phone":"+32 71 72 93 01",
    "sg:postcode":"5640",
    "sg:province":"Namur",
    "wof:name":"Ecole Fond. Communale",
    "wof:placetype":"venue"
},
  "geometry": {"coordinates":[4.6807069778,50.2972946167],"type":"Point"}
}