{
  "type": "Feature",
  "properties": {
    "addr:full":"Quai Des Usines 22 Brussel/bruxelles Bruxelles-Capitale 1000",
    "addr:housenumber":"22",
    "addr:postcode":"1000",
    "addr:street":"Quai Des Usines;/",
    "iso:country":"BE",
    "sg:address":"Quai Des Usines 22",
    "sg:city":"Brussel/bruxelles",
    "sg:orig_category":"Auto-\u00e9coles",
    "sg:phone":"+32 2 245 67 00",
    "sg:postcode":"1000",
    "sg:province":"Bruxelles-Capitale",
    "wof:name":"I.n.e.r.",
    "wof:placetype":"venue"
},
  "geometry": {"coordinates":[4.3659901619,50.8771324158],"type":"Point"}
}