{
  "type": "Feature",
  "properties": {
    "iso:country":"BE",
    "sg:address":"Rue Alfred Musin 7",
    "sg:city":"Courcelles (souvret)",
    "sg:classifiers":[
        {
            "category":"Health Services",
            "subcategory":"Health Practitioner",
            "type":"Services"
        }
    ],
    "sg:phone":"+32 71 45 41 40",
    "sg:postcode":"6182",
    "sg:province":"Hainaut",
    "sg:tags":[
        "physiotherapist"
    ],
    "wof:name":"Musolino Mario",
    "wof:placetype":"venue"
},
  "geometry": {"coordinates":[4.3523340225,50.447265625],"type":"Point"}
}