{
  "type": "Feature",
  "properties": {
    "addr:full":"Paleisstraat 5 Antwerpen Antwerpen 2018",
    "addr:housenumber":"5",
    "addr:postcode":"2018",
    "addr:street":"Paleisstraat",
    "iso:country":"BE",
    "sg:address":"Paleisstraat 5",
    "sg:city":"Antwerpen",
    "sg:classifiers":[
        {
            "category":"Insurance",
            "subcategory":"Insurance Agent",
            "type":"Services"
        }
    ],
    "sg:phone":"+32 3 238 80 78",
    "sg:postcode":"2018",
    "sg:province":"Antwerpen",
    "sg:tags":[
        "verzekeringsmakelaars",
        "expert"
    ],
    "wof:name":"Van Den Herten",
    "wof:placetype":"venue"
},
  "geometry": {"coordinates":[4.4028558731,51.2077598572],"type":"Point"}
}