{
  "type": "Feature",
  "properties": {
    "iso:country":"BE",
    "sg:address":"Kimpestraat 17",
    "sg:city":"Brakel",
    "sg:orig_category":"Radioproductie and uitzendingen",
    "sg:phone":"+32 55 42 19 19",
    "sg:postcode":"9660",
    "sg:province":"Oost-Vlaanderen",
    "wof:name":"Radio Vlaamse Ardennen",
    "wof:placetype":"venue"
},
  "geometry": {"coordinates":[3.7280759811,50.7910461426],"type":"Point"}
}