{
  "type": "Feature",
  "properties": {
    "addr:full":"Rue Du Moulin 23bc Cerfontaine Namur 5630",
    "addr:housenumber":"23bc",
    "addr:postcode":"5630",
    "addr:street":"Rue Du Moulin",
    "iso:country":"BE",
    "sg:address":"Rue Du Moulin 23bc",
    "sg:city":"Cerfontaine",
    "sg:orig_category":"Supermarch\u00e9s",
    "sg:phone":"+32 71 64 48 99",
    "sg:postcode":"5630",
    "sg:province":"Namur",
    "wof:name":"Ad Delhaize",
    "wof:placetype":"venue"
},
  "geometry": {"coordinates":[4.4088869095,50.1736183167],"type":"Point"}
}