{
  "type": "Feature",
  "properties": {
    "addr:full":"Eikelstraat 34 Eeklo Oost-Vlaanderen 9900",
    "addr:housenumber":"34",
    "addr:postcode":"9900",
    "addr:street":"Eikelstraat",
    "iso:country":"BE",
    "sg:address":"Eikelstraat 34",
    "sg:city":"Eeklo",
    "sg:orig_category":"Non-Classified Establishments",
    "sg:phone":"+32 9 377 29 15",
    "sg:postcode":"9900",
    "sg:province":"Oost-Vlaanderen",
    "wof:name":"Morbee L",
    "wof:placetype":"venue"
},
  "geometry": {"coordinates":[3.5614960194,51.1885032654],"type":"Point"}
}