{
  "type": "Feature",
  "properties": {
    "iso:country":"BE",
    "sg:address":"Regentiestraat 74",
    "sg:city":"Sint-niklaas",
    "sg:classifiers":[
        {
            "category":"Real Estate",
            "subcategory":"Architect",
            "type":"Services"
        }
    ],
    "sg:phone":"+32 3 778 88 40",
    "sg:postcode":"9100",
    "sg:province":"Oost-Vlaanderen",
    "wof:name":"Bulterys L",
    "wof:placetype":"venue"
},
  "geometry": {"coordinates":[4.1460599899,51.1683425903],"type":"Point"}
}