{
  "type": "Feature",
  "properties": {
    "iso:country":"BE",
    "sg:address":"Avenue Des Alli\u00e9s 91",
    "sg:city":"Malmedy",
    "sg:classifiers":[
        {
            "category":"Banks & Credit Unions",
            "subcategory":"Investment Brokerage",
            "type":"Services"
        }
    ],
    "sg:phone":"+32 80 79 97 77",
    "sg:postcode":"4960",
    "sg:province":"Li\u00e8ge",
    "sg:tags":[
        "incentive"
    ],
    "wof:name":"School Voor Automobielbeheersing",
    "wof:placetype":"venue"
},
  "geometry": {"coordinates":[6.0157361031,50.4223823547],"type":"Point"}
}