{
  "type": "Feature",
  "properties": {
    "iso:country":"BE",
    "sg:address":"Avenue Des D\u00e9port\u00e9s 45",
    "sg:city":"Wavre",
    "sg:orig_category":"Oldtimers",
    "sg:phone":"+32 10 22 33 40",
    "sg:postcode":"1300",
    "sg:province":"Brabant Wallon",
    "wof:name":"Style Auto",
    "wof:placetype":"venue"
},
  "geometry": {"coordinates":[4.613735199,50.7158813477],"type":"Point"}
}