{
  "type": "Feature",
  "properties": {
    "addr:full":"Rue De La Station 48 Braine-le-comte Hainaut 7090",
    "addr:housenumber":"48",
    "addr:postcode":"7090",
    "addr:street":"Rue De La Station",
    "iso:country":"BE",
    "sg:address":"Rue De La Station 48",
    "sg:city":"Braine-le-comte",
    "sg:orig_category":"Artsen and specialisten",
    "sg:phone":"+32 67 55 27 12",
    "sg:postcode":"7090",
    "sg:province":"Hainaut",
    "wof:name":"Paul Cheron",
    "wof:placetype":"venue"
},
  "geometry": {"coordinates":[4.1374278069,50.6090507507],"type":"Point"}
}