{
  "type": "Feature",
  "properties": {
    "iso:country":"BE",
    "sg:address":"Place Brugmann 15",
    "sg:city":"Ukkel/uccle",
    "sg:orig_category":"Souvenirs and objets artisanaux. V\u00eatements",
    "sg:phone":"+32 2 344 31 92",
    "sg:postcode":"1180",
    "sg:province":"Bruxelles-Capitale",
    "wof:name":"Graphie Sud",
    "wof:placetype":"venue"
},
  "geometry": {"coordinates":[4.3482198715,50.8141403198],"type":"Point"}
}