{
  "type": "Feature",
  "properties": {
    "iso:country":"BE",
    "sg:address":"Van Colenstraat 2",
    "sg:city":"Boechout",
    "sg:classifiers":[
        {
            "category":"Bakery",
            "type":"Food & Drink"
        }
    ],
    "sg:phone":"+32 3 455 23 05",
    "sg:postcode":"2530",
    "sg:province":"Antwerpen",
    "sg:tags":[
        "confectioner",
        "baker"
    ],
    "wof:name":"Van Volsem F",
    "wof:placetype":"venue"
},
  "geometry": {"coordinates":[4.4915690422,51.1594467163],"type":"Point"}
}