{
  "type": "Feature",
  "properties": {
    "iso:country":"BE",
    "sg:address":"Markt 17",
    "sg:city":"Sint-katelijne-waver",
    "sg:classifiers":[
        {
            "category":"Bars & Pubs",
            "type":"Food & Drink"
        }
    ],
    "sg:phone":"+32 15 31 41 72",
    "sg:postcode":"2860",
    "sg:province":"Antwerpen",
    "wof:name":"Onder De Toren",
    "wof:placetype":"venue"
},
  "geometry": {"coordinates":[4.5313940048,51.0701332092],"type":"Point"}
}