{
  "type": "Feature",
  "properties": {
    "iso:country":"BE",
    "sg:address":"Kon Elisabethln 3",
    "sg:city":"Gent",
    "sg:classifiers":[
        {
            "category":"Banks & Credit Unions",
            "subcategory":"Bank",
            "type":"Services"
        }
    ],
    "sg:phone":"+32 54 22 71 30",
    "sg:postcode":"9000",
    "sg:province":"Oost-Vlaanderen",
    "wof:name":"Kredietbank",
    "wof:placetype":"venue"
},
  "geometry": {"coordinates":[3.7139220238,51.0372085571],"type":"Point"}
}