{
  "type": "Feature",
  "properties": {
    "addr:full":"Rue Priv\u00c9e 44 Kelmis/la Calamine Li\u00e8ge 4720",
    "addr:housenumber":"44",
    "addr:postcode":"4720",
    "addr:street":"Rue Prive\u0301E",
    "iso:country":"BE",
    "sg:address":"Rue Priv\u00c9e 44",
    "sg:city":"Kelmis/la Calamine",
    "sg:classifiers":[
        {
            "category":"Cinema",
            "subcategory":"Movie Rental",
            "type":"Entertainment"
        }
    ],
    "sg:phone":"+32 87 65 88 87",
    "sg:postcode":"4720",
    "sg:province":"Li\u00e8ge",
    "sg:tags":[
        "de",
        "cassette",
        "location",
        "vid\u00e9o",
        "audio"
    ],
    "wof:name":"Marc Vluggen",
    "wof:placetype":"venue"
},
  "geometry": {"coordinates":[6.0046949387,50.7152786255],"type":"Point"}
}