{
  "type": "Feature",
  "properties": {
    "addr:full":"Eksterlaan 1 Kapellen Antwerpen 2950",
    "addr:housenumber":"1",
    "addr:postcode":"2950",
    "addr:street":"Eksterlaan",
    "iso:country":"BE",
    "sg:address":"Eksterlaan 1",
    "sg:city":"Kapellen",
    "sg:orig_category":"Experts-comptables",
    "sg:phone":"+32 3 666 58 38",
    "sg:postcode":"2950",
    "sg:province":"Antwerpen",
    "wof:name":"Marc Bisschops",
    "wof:placetype":"venue"
},
  "geometry": {"coordinates":[4.4514608383,51.3456954956],"type":"Point"}
}