{
  "type": "Feature",
  "properties": {
    "iso:country":"BE",
    "sg:address":"Avenue De Jette 295",
    "sg:city":"Ganshoren/ganshoren",
    "sg:orig_category":"Pharmaciens",
    "sg:phone":"+32 2 427 52 02",
    "sg:postcode":"1083",
    "sg:province":"Bruxelles-Capitale",
    "wof:name":"Guy Roufosse/g. Roufosse",
    "wof:placetype":"venue"
},
  "geometry": {"coordinates":[4.3210148811,50.8746147156],"type":"Point"}
}