{
  "type": "Feature",
  "properties": {
    "iso:country":"BE",
    "sg:address":"Avenue De Cortenbergh 52",
    "sg:city":"Bruxelles",
    "sg:classifiers":[
        {
            "category":"Organizations",
            "subcategory":"Non-profit Organization",
            "type":"Services"
        }
    ],
    "sg:phone":"+32 2 743 30 70",
    "sg:postcode":"1000",
    "sg:province":"Bruxelles-Capitale",
    "sg:tags":[
        "international",
        "organisation"
    ],
    "wof:name":"European Space Agency",
    "wof:placetype":"venue"
},
  "geometry": {"coordinates":[4.3866710663,50.8437385559],"type":"Point"}
}