{
  "type": "Feature",
  "properties": {
    "addr:full":"Rue De L'industrie 3 Nivelles Brabant Wallon 1400",
    "addr:housenumber":"3",
    "addr:postcode":"1400",
    "addr:street":"Rue De L'Industrie",
    "iso:country":"BE",
    "sg:address":"Rue De L'industrie 3",
    "sg:city":"Nivelles",
    "sg:classifiers":[
        {
            "category":"Retail",
            "subcategory":"Repair Shop",
            "type":"Services"
        }
    ],
    "sg:phone":"+32 67 84 05 03",
    "sg:postcode":"1400",
    "sg:province":"Brabant Wallon",
    "sg:tags":[
        "-",
        "clothing",
        "alteration"
    ],
    "wof:name":"Delforges",
    "wof:placetype":"venue"
},
  "geometry": {"coordinates":[4.3595738411,50.5953674316],"type":"Point"}
}