{
  "type": "Feature",
  "properties": {
    "addr:full":"Steenweg Op Asse 76 Merchtem Vlaams-Brabant 1785",
    "addr:housenumber":"76",
    "addr:postcode":"1785",
    "addr:street":"Steenweg Op Asse",
    "iso:country":"BE",
    "sg:address":"Steenweg Op Asse 76",
    "sg:city":"Merchtem",
    "sg:classifiers":[
        {
            "category":"Arena",
            "subcategory":"Sports Club",
            "type":"Entertainment"
        }
    ],
    "sg:phone":"+32 2 452 60 10",
    "sg:postcode":"1785",
    "sg:province":"Vlaams-Brabant",
    "sg:tags":[
        "de"
    ],
    "wof:name":"Wc Bollebeek-herleeft",
    "wof:placetype":"venue"
},
  "geometry": {"coordinates":[4.2501392365,50.9248085022],"type":"Point"}
}