{
  "type": "Feature",
  "properties": {
    "addr:full":"Oude Markt 30 Overpelt Limburg 3900",
    "addr:housenumber":"30",
    "addr:postcode":"3900",
    "addr:street":"Oude Markt",
    "iso:country":"BE",
    "sg:address":"Oude Markt 30",
    "sg:city":"Overpelt",
    "sg:orig_category":"Diverse kredietdiensten",
    "sg:postcode":"3900",
    "sg:province":"Limburg",
    "wof:name":"Bancontact-mister Cash",
    "wof:placetype":"venue"
},
  "geometry": {"coordinates":[5.4235010147,51.211971283],"type":"Point"}
}