{
  "type": "Feature",
  "properties": {
    "addr:full":"Rue De La Pastorale 86 Bruxelles (anderlecht) Bruxelles-Capitale 1070",
    "addr:housenumber":"86",
    "addr:postcode":"1070",
    "addr:street":"Rue De La Pastorale",
    "iso:country":"BE",
    "sg:address":"Rue De La Pastorale 86",
    "sg:city":"Bruxelles (anderlecht)",
    "sg:classifiers":[
        {
            "category":"Professional",
            "subcategory":"Computer Services",
            "type":"Services"
        }
    ],
    "sg:phone":"+32 2 411 25 67",
    "sg:postcode":"1070",
    "sg:province":"Bruxelles-Capitale",
    "sg:tags":[
        "-",
        "processing",
        "data",
        "software"
    ],
    "wof:name":"Dritech",
    "wof:placetype":"venue"
},
  "geometry": {"coordinates":[4.3008871078,50.8481330872],"type":"Point"}
}