{
  "type": "Feature",
  "properties": {
    "addr:full":"Provinciebaan 28 Rotselaar Vlaams-Brabant 3110",
    "addr:housenumber":"28",
    "addr:postcode":"3110",
    "addr:street":"Provinciebaan",
    "iso:country":"BE",
    "sg:address":"Provinciebaan 28",
    "sg:city":"Rotselaar",
    "sg:classifiers":[
        {
            "category":"Retail",
            "subcategory":"Veterinary Services",
            "type":"Services"
        }
    ],
    "sg:phone":"+32 16 44 42 87",
    "sg:postcode":"3110",
    "sg:province":"Vlaams-Brabant",
    "sg:tags":[
        "veterinarian"
    ],
    "wof:name":"Nackaerts J",
    "wof:placetype":"venue"
},
  "geometry": {"coordinates":[4.7080039978,50.9530982971],"type":"Point"}
}