{
  "type": "Feature",
  "properties": {
    "iso:country":"BE",
    "sg:address":"Rue De La Tannerie 19",
    "sg:city":"Chiny (jamoigne)",
    "sg:classifiers":[
        {
            "category":"Building & Trades",
            "subcategory":"Construction",
            "type":"Services"
        }
    ],
    "sg:phone":"+32 61 32 96 46",
    "sg:postcode":"6810",
    "sg:province":"Luxembourg",
    "sg:tags":[
        "stucco",
        "contractor"
    ],
    "wof:name":"Homel Fr\u00e8res Sprl",
    "wof:placetype":"venue"
},
  "geometry": {"coordinates":[5.3405580521,49.7382736206],"type":"Point"}
}