{
  "type": "Feature",
  "properties": {
    "iso:country":"BE",
    "sg:address":"Walkurenstraat 23",
    "sg:city":"Roeselare",
    "sg:orig_category":"Epiceries",
    "sg:phone":"+32 51 22 45 42",
    "sg:postcode":"8800",
    "sg:province":"West-Vlaanderen",
    "wof:name":"Annie Rambour",
    "wof:placetype":"venue"
},
  "geometry": {"coordinates":[3.1081409454,50.9403114319],"type":"Point"}
}