{
  "type": "Feature",
  "properties": {
    "addr:full":"Trou Du Bois 23 Herve (xhendelesse) Li\u00e8ge 4652",
    "addr:housenumber":"23",
    "addr:postcode":"4652",
    "addr:street":"Trou Du Bois",
    "iso:country":"BE",
    "sg:address":"Trou Du Bois 23",
    "sg:city":"Herve (xhendelesse)",
    "sg:classifiers":[
        {
            "category":"Professional",
            "subcategory":"Management & Consulting",
            "type":"Services"
        }
    ],
    "sg:phone":"+32 87 26 93 87",
    "sg:postcode":"4652",
    "sg:province":"Li\u00e8ge",
    "sg:tags":[
        "consultant"
    ],
    "wof:name":"Fraternity Sprl",
    "wof:placetype":"venue"
},
  "geometry": {"coordinates":[5.7804818153,50.6042518616],"type":"Point"}
}