{
  "type": "Feature",
  "properties": {
    "addr:full":"Bouwelsesteenweg 279 Nijlen Antwerpen 2560",
    "addr:housenumber":"279",
    "addr:postcode":"2560",
    "addr:street":"Bouwelsesteenweg",
    "iso:country":"BE",
    "sg:address":"Bouwelsesteenweg 279",
    "sg:city":"Nijlen",
    "sg:orig_category":"Etablissements Erotiques",
    "sg:phone":"+32 3 411 00 85",
    "sg:postcode":"2560",
    "sg:province":"Antwerpen",
    "wof:name":"L & M",
    "wof:placetype":"venue"
},
  "geometry": {"coordinates":[4.6987271309,51.1645050049],"type":"Point"}
}