{
  "type": "Feature",
  "properties": {
    "addr:full":"Pastorijstraat 3 Landen Vlaams-Brabant 3401",
    "addr:housenumber":"3",
    "addr:postcode":"3401",
    "addr:street":"Pastorijstraat",
    "iso:country":"BE",
    "sg:address":"Pastorijstraat 3",
    "sg:city":"Landen",
    "sg:orig_category":"Varkenskwekers",
    "sg:phone":"+32 11 88 47 23",
    "sg:postcode":"3401",
    "sg:province":"Vlaams-Brabant",
    "wof:name":"Robert Vandecan",
    "wof:placetype":"venue"
},
  "geometry": {"coordinates":[5.0961308479,50.7234230042],"type":"Point"}
}