{
  "type": "Feature",
  "properties": {
    "iso:country":"BE",
    "sg:address":"Rene Colaertplein 1",
    "sg:city":"Ieper",
    "sg:classifiers":[
        {
            "category":"Restaurant",
            "type":"Food & Drink"
        }
    ],
    "sg:phone":"+32 57 20 27 88",
    "sg:postcode":"8900",
    "sg:province":"West-Vlaanderen",
    "wof:name":"Het Torentje",
    "wof:placetype":"venue"
},
  "geometry": {"coordinates":[2.8777160645,50.8492622375],"type":"Point"}
}