{
  "type": "Feature",
  "properties": {
    "addr:full":"Eindhovensebaan 77 Hechtel-eksel (eksel) Limburg 3941",
    "addr:housenumber":"77",
    "addr:postcode":"3941",
    "addr:street":"Eindhovensebaan",
    "iso:country":"BE",
    "sg:address":"Eindhovensebaan 77",
    "sg:city":"Hechtel-eksel (eksel)",
    "sg:classifiers":[
        {
            "category":"Autos & Motor Vehicles",
            "subcategory":"Automobile Sales",
            "type":"Retail Goods"
        }
    ],
    "sg:phone":"+32 11 73 56 43",
    "sg:postcode":"3941",
    "sg:province":"Limburg",
    "sg:tags":[
        "car",
        "used",
        "-"
    ],
    "wof:name":"Geboers J",
    "wof:placetype":"venue"
},
  "geometry": {"coordinates":[5.3643088341,51.1628341675],"type":"Point"}
}