{
  "type": "Feature",
  "properties": {
    "addr:full":"Herentalsesteenweg 37 Heist-op-den-berg Antwerpen 2220",
    "addr:housenumber":"37",
    "addr:postcode":"2220",
    "addr:street":"Herentalsesteenweg",
    "iso:country":"BE",
    "sg:address":"Herentalsesteenweg 37",
    "sg:city":"Heist-op-den-berg",
    "sg:classifiers":[
        {
            "category":"Food & Beverages",
            "subcategory":"Fruits & Vegetables",
            "type":"Retail Goods"
        }
    ],
    "sg:phone":"+32 15 24 43 22",
    "sg:postcode":"2220",
    "sg:province":"Antwerpen",
    "sg:tags":[
        "l\u00e9gumes"
    ],
    "wof:name":"Jozef Vetters",
    "wof:placetype":"venue"
},
  "geometry": {"coordinates":[4.7341771126,51.0754013062],"type":"Point"}
}