{
  "type": "Feature",
  "properties": {
    "addr:full":"Europalaan 1 Overpelt Limburg 3900",
    "addr:housenumber":"1",
    "addr:postcode":"3900",
    "addr:street":"Europalaan",
    "iso:country":"BE",
    "sg:address":"Europalaan 1",
    "sg:city":"Overpelt",
    "sg:classifiers":[
        {
            "category":"Building & Trades",
            "subcategory":"Electrical",
            "type":"Services"
        }
    ],
    "sg:phone":"+32 11 80 95 80",
    "sg:postcode":"3900",
    "sg:province":"Limburg",
    "sg:tags":[
        "plants",
        "plant",
        "industrial",
        "buildings",
        "construction"
    ],
    "wof:name":"Fal Nv",
    "wof:placetype":"venue"
},
  "geometry": {"coordinates":[5.37687397,51.2160987854],"type":"Point"}
}