{
  "type": "Feature",
  "properties": {
    "addr:full":"Herbert Hooverplein 21 Box 1 Leuven Vlaams-Brabant 3000",
    "addr:housenumber":"21;1",
    "addr:postcode":"3000",
    "addr:street":"Box",
    "iso:country":"BE",
    "sg:address":"Herbert Hooverplein 21 Box 1",
    "sg:city":"Leuven",
    "sg:classifiers":[
        {
            "category":"Wholesale",
            "subcategory":"Medical Equipment & Supplies",
            "type":"Manufacturing & Wholesale Goods"
        }
    ],
    "sg:phone":"+32 16 22 15 92",
    "sg:postcode":"3000",
    "sg:province":"Vlaams-Brabant",
    "sg:tags":[
        "aid",
        "hearing"
    ],
    "wof:name":"Dialogue Hoorcentrum",
    "wof:placetype":"venue"
},
  "geometry": {"coordinates":[4.7067241669,50.8771972656],"type":"Point"}
}