{
  "type": "Feature",
  "properties": {
    "iso:country":"BE",
    "sg:address":"Geraardsbergsesteenweg 179",
    "sg:city":"Ninove",
    "sg:orig_category":"Boucheries",
    "sg:phone":"+32 54 33 35 34",
    "sg:postcode":"9400",
    "sg:province":"Oost-Vlaanderen",
    "wof:name":"Michel Danckaert",
    "wof:placetype":"venue"
},
  "geometry": {"coordinates":[3.958616972,50.8476982117],"type":"Point"}
}