{
  "type": "Feature",
  "properties": {
    "addr:full":"Marktstraat 96 Harelbeke West-Vlaanderen 8530",
    "addr:housenumber":"96",
    "addr:postcode":"8530",
    "addr:street":"Marktstraat",
    "iso:country":"BE",
    "sg:address":"Marktstraat 96",
    "sg:city":"Harelbeke",
    "sg:orig_category":"Landmeters Landmeters and schatters",
    "sg:phone":"+32 56 73 38 91",
    "sg:postcode":"8530",
    "sg:province":"West-Vlaanderen",
    "wof:name":"Pol Hautekiet",
    "wof:placetype":"venue"
},
  "geometry": {"coordinates":[3.3080070019,50.8548240662],"type":"Point"}
}