{
  "type": "Feature",
  "properties": {
    "addr:full":"Haven 399 Industrieweg 16 Antwerpen Antwerpen 2030",
    "addr:housenumber":"399;16",
    "addr:postcode":"2030",
    "addr:street":"Haven;Industrieweg",
    "iso:country":"BE",
    "sg:address":"Haven 399 Industrieweg 16",
    "sg:city":"Antwerpen",
    "sg:classifiers":[
        {
            "category":"Banks & Credit Unions",
            "subcategory":"Investment Brokerage",
            "type":"Services"
        }
    ],
    "sg:phone":"+32 3 545 73 00",
    "sg:postcode":"2030",
    "sg:province":"Antwerpen",
    "sg:tags":[
        "-",
        "transport",
        "related"
    ],
    "wof:name":"Vopak Terminal Eurotank Nv",
    "wof:placetype":"venue"
},
  "geometry": {"coordinates":[4.3551578522,51.2505989075],"type":"Point"}
}