{
  "type": "Feature",
  "properties": {
    "addr:full":"Doorniksewijk 83bb Kortrijk West-Vlaanderen 8500",
    "addr:housenumber":"83bb",
    "addr:postcode":"8500",
    "addr:street":"Doorniksewijk",
    "iso:country":"BE",
    "sg:address":"Doorniksewijk 83bb",
    "sg:city":"Kortrijk",
    "sg:orig_category":"Krantenuitgeverijen Tijdschriftenuitgeverijen",
    "sg:phone":"+32 56 20 02 81",
    "sg:postcode":"8500",
    "sg:province":"West-Vlaanderen",
    "wof:name":"Het Kortrijks Handelsblad",
    "wof:placetype":"venue"
},
  "geometry": {"coordinates":[3.2694120407,50.8201446533],"type":"Point"}
}