{
  "type": "Feature",
  "properties": {
    "addr:full":"R Grambompre 11 Parc Scientifique De Louvain La Neuve Mont-saint-guibert Brabant Wallon 1348",
    "addr:housenumber":"11",
    "addr:postcode":"1348",
    "addr:street":"Parc Scientifique De Louvain La Neuve",
    "iso:country":"BE",
    "sg:address":"R Grambompre 11 Parc Scientifique De Louvain La Neuve",
    "sg:city":"Mont-saint-guibert",
    "sg:classifiers":[
        {
            "category":"Health Services",
            "subcategory":"Medical Lab",
            "type":"Services"
        }
    ],
    "sg:phone":"+32 10 47 62 11",
    "sg:postcode":"1348",
    "sg:province":"Brabant Wallon",
    "sg:tags":[
        "chemical",
        "pharmaceutical",
        "pharmacy"
    ],
    "wof:name":"Lilly Development Centre Sa",
    "wof:placetype":"venue"
},
  "geometry": {"coordinates":[4.6171450615,50.670124054],"type":"Point"}
}