{
  "type": "Feature",
  "properties": {
    "iso:country":"BE",
    "sg:address":"Neerstraat 19",
    "sg:city":"Avelgem",
    "sg:orig_category":"Bouwmaterialen Gh",
    "sg:phone":"+32 56 64 40 67",
    "sg:postcode":"8580",
    "sg:province":"West-Vlaanderen",
    "wof:name":"Stichelbaut A",
    "wof:placetype":"venue"
},
  "geometry": {"coordinates":[3.4442770481,50.7765960693],"type":"Point"}
}