{
  "type": "Feature",
  "properties": {
    "addr:full":"Kwademeerslaan 13 Harelbeke West-Vlaanderen 8531",
    "addr:housenumber":"13",
    "addr:postcode":"8531",
    "addr:street":"Kwademeerslaan",
    "iso:country":"BE",
    "sg:address":"Kwademeerslaan 13",
    "sg:city":"Harelbeke",
    "sg:orig_category":"Entretien and r\u00e9parations de voitures",
    "sg:phone":"+32 56 71 45 82",
    "sg:postcode":"8531",
    "sg:province":"West-Vlaanderen",
    "wof:name":"Romain Devolder",
    "wof:placetype":"venue"
},
  "geometry": {"coordinates":[3.2887721062,50.887260437],"type":"Point"}
}