{
  "type": "Feature",
  "properties": {
    "iso:country":"BE",
    "sg:address":"Herbert Hooverlaan 32",
    "sg:city":"Sint-lambrechts-woluwe/woluwe-saint-lambert",
    "sg:orig_category":"Boekhouders",
    "sg:phone":"+32 2 732 92 72",
    "sg:postcode":"1200",
    "sg:province":"Bruxelles-Capitale",
    "wof:name":"Fe. Petre Frank",
    "wof:placetype":"venue"
},
  "geometry": {"coordinates":[4.4067120552,50.8468818665],"type":"Point"}
}