{
  "type": "Feature",
  "properties": {
    "iso:country":"BE",
    "sg:address":"Rue Vieille Leuze 7",
    "sg:city":"Somme-leuze",
    "sg:orig_category":"Vakantiehuizen",
    "sg:phone":"+32 86 32 27 71",
    "sg:postcode":"5377",
    "sg:province":"Namur",
    "wof:name":"Le Gite Rural L\u00b4 O\u00dbh\u00c9 De Bw\u00c8s",
    "wof:placetype":"venue"
},
  "geometry": {"coordinates":[5.3294301033,50.3201026917],"type":"Point"}
}