{
  "type": "Feature",
  "properties": {
    "addr:full":"Rue Point Du Jour 50 Genappe Brabant Wallon 1470",
    "addr:housenumber":"50",
    "addr:postcode":"1470",
    "addr:street":"Rue Point Du Jour;Wallon",
    "iso:country":"BE",
    "sg:address":"Rue Point Du Jour 50",
    "sg:city":"Genappe",
    "sg:orig_category":"Peinture. Rev\u00eatements pour sols and murs",
    "sg:phone":"+32 10 61 21 69",
    "sg:postcode":"1470",
    "sg:province":"Brabant Wallon",
    "wof:name":"Liliane Lebon",
    "wof:placetype":"venue"
},
  "geometry": {"coordinates":[4.5152220726,50.6330718994],"type":"Point"}
}