{
  "type": "Feature",
  "properties": {
    "iso:country":"BE",
    "sg:address":"Gestelstraat 61",
    "sg:city":"Lummen",
    "sg:orig_category":"D\u00e9molition d\u00b4immeubles and terrassements. Constructions r\u00e9sidentielles sp\u00e9cifiques",
    "sg:phone":"+32 11 43 50 54",
    "sg:postcode":"3560",
    "sg:province":"Limburg",
    "wof:name":"Johan Vandevenne",
    "wof:placetype":"venue"
},
  "geometry": {"coordinates":[5.210931778,51.0318946838],"type":"Point"}
}