{
  "type": "Feature",
  "properties": {
    "addr:full":"Rue Des Sables 4 Seraing Li\u00e8ge 4100",
    "addr:housenumber":"4",
    "addr:postcode":"4100",
    "addr:street":"Rue Des Sables",
    "iso:country":"BE",
    "sg:address":"Rue Des Sables 4",
    "sg:city":"Seraing",
    "sg:classifiers":[
        {
            "category":"Shopping",
            "subcategory":"Clothing, Apparel, & Fashions",
            "type":"Retail Goods"
        }
    ],
    "sg:phone":"+32 4 336 30 82",
    "sg:postcode":"4100",
    "sg:province":"Li\u00e8ge",
    "sg:tags":[
        "lady",
        "clothing",
        "-"
    ],
    "wof:name":"Nadine (boutique)",
    "wof:placetype":"venue"
},
  "geometry": {"coordinates":[5.500234127,50.5794792175],"type":"Point"}
}