{
  "type": "Feature",
  "properties": {
    "addr:full":"Stationsstraat 87 Halen (zelem) Limburg 3545",
    "addr:housenumber":"87",
    "addr:postcode":"3545",
    "addr:street":"Stationsstraat",
    "iso:country":"BE",
    "sg:address":"Stationsstraat 87",
    "sg:city":"Halen (zelem)",
    "sg:classifiers":[
        {
            "category":"Food & Beverages",
            "subcategory":"Chocolate",
            "type":"Retail Goods"
        }
    ],
    "sg:phone":"+32 13 44 14 82",
    "sg:postcode":"3545",
    "sg:province":"Limburg",
    "sg:tags":[
        "confectionery",
        "-"
    ],
    "wof:name":"Schepers-cels Nv",
    "wof:placetype":"venue"
},
  "geometry": {"coordinates":[5.1214079857,50.977645874],"type":"Point"}
}