{
  "type": "Feature",
  "properties": {
    "addr:full":"Rue Des Sarts 16 Hotton Luxembourg 6990",
    "addr:housenumber":"16",
    "addr:postcode":"6990",
    "addr:street":"Rue Des Sarts",
    "iso:country":"BE",
    "sg:address":"Rue Des Sarts 16",
    "sg:city":"Hotton",
    "sg:classifiers":[
        {
            "category":"Building & Trades",
            "subcategory":"Construction",
            "type":"Services"
        }
    ],
    "sg:phone":"+32 84 31 32 29",
    "sg:postcode":"6990",
    "sg:province":"Luxembourg",
    "sg:tags":[
        "surveyor",
        "-"
    ],
    "wof:name":"Gueibe D",
    "wof:placetype":"venue"
},
  "geometry": {"coordinates":[5.4341621399,50.2644004822],"type":"Point"}
}