{
  "type": "Feature",
  "properties": {
    "addr:full":"Gryspeerdts Hof 7 Roeselare West-Vlaanderen 8800",
    "addr:housenumber":"7",
    "addr:postcode":"8800",
    "addr:street":"Gryspeerdts Hof",
    "iso:country":"BE",
    "sg:address":"Gryspeerdts Hof 7",
    "sg:city":"Roeselare",
    "sg:classifiers":[
        {
            "category":"Health Services",
            "subcategory":"Nursing And Care Facility",
            "type":"Services"
        }
    ],
    "sg:phone":"+32 51 24 21 71",
    "sg:postcode":"8800",
    "sg:province":"West-Vlaanderen",
    "sg:tags":[
        "home"
    ],
    "wof:name":"Wallays M",
    "wof:placetype":"venue"
},
  "geometry": {"coordinates":[3.1202189922,50.9589347839],"type":"Point"}
}