{
  "type": "Feature",
  "properties": {
    "iso:country":"BE",
    "sg:address":"Industriestrasse 39",
    "sg:city":"Eupen",
    "sg:classifiers":[
        {
            "category":"Professional",
            "subcategory":"Engineering",
            "type":"Services"
        }
    ],
    "sg:phone":"+32 87 59 55 60",
    "sg:postcode":"4700",
    "sg:province":"Li\u00e8ge",
    "sg:tags":[
        "precision"
    ],
    "wof:name":"Capaul Sa",
    "wof:placetype":"venue"
},
  "geometry": {"coordinates":[6.0050377846,50.6395988464],"type":"Point"}
}