{
  "type": "Feature",
  "properties": {
    "addr:full":"Nederhasseltstraat 297 Ninove (nederhasselt) Oost-Vlaanderen 9400",
    "addr:housenumber":"297",
    "addr:postcode":"9400",
    "addr:street":"Nederhasseltstraat",
    "iso:country":"BE",
    "sg:address":"Nederhasseltstraat 297",
    "sg:city":"Ninove (nederhasselt)",
    "sg:classifiers":[
        {
            "category":"Freight",
            "type":"Transportation"
        }
    ],
    "sg:phone":"+32 54 33 10 74",
    "sg:postcode":"9400",
    "sg:province":"Oost-Vlaanderen",
    "sg:tags":[
        "-",
        "transport"
    ],
    "wof:name":"De Braekeleer Andy Bvba",
    "wof:placetype":"venue"
},
  "geometry": {"coordinates":[3.9694828987,50.8464584351],"type":"Point"}
}