{
  "type": "Feature",
  "properties": {
    "iso:country":"BE",
    "sg:address":"Struypenbergstraat 11",
    "sg:city":"Ninove",
    "sg:classifiers":[
        {
            "category":"Cafe",
            "type":"Food & Drink"
        }
    ],
    "sg:phone":"+32 54 33 50 29",
    "sg:postcode":"9406",
    "sg:province":"Oost-Vlaanderen",
    "sg:tags":[
        "caf\u00e9s"
    ],
    "wof:name":"Caf\u00c9 Wegsteek",
    "wof:placetype":"venue"
},
  "geometry": {"coordinates":[3.996860981,50.8439674377],"type":"Point"}
}