{
  "type": "Feature",
  "properties": {
    "iso:country":"BE",
    "sg:address":"Rue Gustave Bo\u00ebl 23a",
    "sg:city":"La Louvi\u00e8re",
    "sg:orig_category":"Autombile concessionaires",
    "sg:phone":"+32 64 23 91 00",
    "sg:postcode":"7100",
    "sg:province":"Hainaut",
    "wof:name":"Auto Satellites Sa",
    "wof:placetype":"venue"
},
  "geometry": {"coordinates":[4.1769042015,50.4779853821],"type":"Point"}
}