{
  "type": "Feature",
  "properties": {
    "addr:full":"Boudewijnlaan 15 Balen Antwerpen 2490",
    "addr:housenumber":"15",
    "addr:postcode":"2490",
    "addr:street":"Boudewijnlaan",
    "iso:country":"BE",
    "sg:address":"Boudewijnlaan 15",
    "sg:city":"Balen",
    "sg:classifiers":[
        {
            "category":"Education",
            "subcategory":"School",
            "type":"Public Place"
        }
    ],
    "sg:phone":"+32 14 81 72 66",
    "sg:postcode":"2490",
    "sg:province":"Antwerpen",
    "sg:tags":[
        "secondary"
    ],
    "wof:name":"Centrum Deeltijds Onderwijs",
    "wof:placetype":"venue"
},
  "geometry": {"coordinates":[5.1630592346,51.1730575562],"type":"Point"}
}