{
  "type": "Feature",
  "properties": {
    "iso:country":"BE",
    "sg:address":"Weidestraat 4",
    "sg:city":"Meeuwen-gruitrode",
    "sg:orig_category":"Eleveurs and marchands de porcs",
    "sg:phone":"+32 11 79 20 29",
    "sg:postcode":"3670",
    "sg:province":"Limburg",
    "wof:name":"Leopold Meermans",
    "wof:placetype":"venue"
},
  "geometry": {"coordinates":[5.4927549362,51.0879516602],"type":"Point"}
}