{
  "type": "Feature",
  "properties": {
    "addr:full":"Avenue G\u00c9n\u00c9ral Leman 8 Seraing Li\u00e8ge 4101",
    "addr:housenumber":"8",
    "addr:postcode":"4101",
    "addr:street":"Avenue Ge\u0301Ne\u0301Ral Leman",
    "iso:country":"BE",
    "sg:address":"Avenue G\u00c9n\u00c9ral Leman 8",
    "sg:city":"Seraing",
    "sg:orig_category":"RESTAURANTS: CAF\u00c9S",
    "sg:phone":"+32 4 233 11 66",
    "sg:postcode":"4101",
    "sg:province":"Li\u00e8ge",
    "wof:name":"Taverne Le Leman",
    "wof:placetype":"venue"
},
  "geometry": {"coordinates":[5.4992399216,50.6170692444],"type":"Point"}
}