{
  "type": "Feature",
  "properties": {
    "iso:country":"BE",
    "sg:address":"Cipressenstraat 11",
    "sg:city":"Roeselare",
    "sg:classifiers":[
        {
            "category":"Manufacturing",
            "subcategory":"Wood Products",
            "type":"Manufacturing & Wholesale Goods"
        }
    ],
    "sg:phone":"+32 51 24 10 49",
    "sg:postcode":"8800",
    "sg:province":"West-Vlaanderen",
    "sg:tags":[
        "chip",
        "fiber",
        "board"
    ],
    "wof:name":"Desseyn Louis-hornitex Werke",
    "wof:placetype":"venue"
},
  "geometry": {"coordinates":[3.1067500114,50.9354553223],"type":"Point"}
}