{
  "type": "Feature",
  "properties": {
    "addr:full":"Rue Du G\u00e9ant 8 Nivelles Brabant Wallon 1400",
    "addr:housenumber":"8",
    "addr:postcode":"1400",
    "addr:street":"Rue Du Ge\u0301Ant",
    "iso:country":"BE",
    "sg:address":"Rue Du G\u00e9ant 8",
    "sg:city":"Nivelles",
    "sg:classifiers":[
        {
            "category":"Shopping",
            "subcategory":"Crafts & Fabrics",
            "type":"Retail Goods"
        }
    ],
    "sg:phone":"+32 67 48 53 90",
    "sg:postcode":"1400",
    "sg:province":"Brabant Wallon",
    "sg:tags":[
        "plant",
        "flower",
        "artificial"
    ],
    "wof:name":"Art Du Bouquet (l')",
    "wof:placetype":"venue"
},
  "geometry": {"coordinates":[4.3269729614,50.5984382629],"type":"Point"}
}