{
  "type": "Feature",
  "properties": {
    "addr:full":"Avenue Van Volxem 234 Vorst Bruxelles-Capitale 1190",
    "addr:housenumber":"234",
    "addr:postcode":"1190",
    "addr:street":"Avenue Van Volxem",
    "iso:country":"BE",
    "sg:address":"Avenue Van Volxem 234",
    "sg:city":"Vorst",
    "sg:orig_category":"SMEEDWERK, METAALBEWERKING AND POEDERMETALLURGIE",
    "sg:phone":"+32 2 344 19 68",
    "sg:postcode":"1190",
    "sg:province":"Bruxelles-Capitale",
    "wof:name":"Alexandre",
    "wof:placetype":"venue"
},
  "geometry": {"coordinates":[4.3260779381,50.8207702637],"type":"Point"}
}