{
  "type": "Feature",
  "properties": {
    "iso:country":"BE",
    "sg:address":"Fortlaan 48",
    "sg:city":"Gent",
    "sg:classifiers":[
        {
            "category":"Real Estate",
            "subcategory":"Architect",
            "type":"Services"
        }
    ],
    "sg:phone":"+32 9 220 46 20",
    "sg:postcode":"9000",
    "sg:province":"Oost-Vlaanderen",
    "wof:name":"Delaere S",
    "wof:placetype":"venue"
},
  "geometry": {"coordinates":[3.717648983,51.035736084],"type":"Point"}
}