{
  "type": "Feature",
  "properties": {
    "iso:country":"BE",
    "sg:address":"Rue Des Quatre Vents 94",
    "sg:city":"Sint-jans-molenbeek/molenbeek-saint-jean",
    "sg:orig_category":"Plomberie, chauffage and installations sanitaires",
    "sg:phone":"+32 2 410 25 63",
    "sg:postcode":"1080",
    "sg:province":"Bruxelles-Capitale",
    "wof:name":"B. Atnnani",
    "wof:placetype":"venue"
},
  "geometry": {"coordinates":[4.3317828178,50.8532485962],"type":"Point"}
}