{
  "type": "Feature",
  "properties": {
    "addr:full":"Rijmenamseweg 116 Bonheiden Antwerpen 2820",
    "addr:housenumber":"116",
    "addr:postcode":"2820",
    "addr:street":"Rijmenamseweg",
    "iso:country":"BE",
    "sg:address":"Rijmenamseweg 116",
    "sg:city":"Bonheiden",
    "sg:classifiers":[
        {
            "category":"Retail",
            "subcategory":"Laundry & Dry Cleaning",
            "type":"Services"
        }
    ],
    "sg:phone":"+32 15 34 60 70",
    "sg:postcode":"2820",
    "sg:province":"Antwerpen",
    "sg:tags":[
        "dyer",
        "cleaner"
    ],
    "wof:name":"Lux-shop Bvba",
    "wof:placetype":"venue"
},
  "geometry": {"coordinates":[4.5651841164,51.0188865662],"type":"Point"}
}