{
  "type": "Feature",
  "properties": {
    "iso:country":"BE",
    "sg:address":"Statiestraat 99a",
    "sg:city":"Kalmthout",
    "sg:classifiers":[
        {
            "category":"Shopping",
            "subcategory":"Clothing, Apparel, & Fashions",
            "type":"Retail Goods"
        }
    ],
    "sg:phone":"+32 3 666 03 61",
    "sg:postcode":"2920",
    "sg:province":"Antwerpen",
    "sg:tags":[
        "boutique"
    ],
    "wof:name":"Jonas B",
    "wof:placetype":"venue"
},
  "geometry": {"coordinates":[4.4673137665,51.3916778564],"type":"Point"}
}