{
  "type": "Feature",
  "properties": {
    "addr:full":"Rue Du Bois De Buis 134 Walhain Brabant Wallon 1457",
    "addr:housenumber":"134;1457",
    "addr:street":"Rue Du Bois De Buis",
    "iso:country":"BE",
    "sg:address":"Rue Du Bois De Buis 134",
    "sg:city":"Walhain",
    "sg:orig_category":"R\u00e9alisation de programmes and logiciels",
    "sg:phone":"+32 10 65 87 96",
    "sg:postcode":"1457",
    "sg:province":"Brabant Wallon",
    "wof:name":"Logic Al Systems",
    "wof:placetype":"venue"
},
  "geometry": {"coordinates":[4.726776123,50.611869812],"type":"Point"}
}