{
  "type": "Feature",
  "properties": {
    "addr:full":"Rooberg 35 Oosterzele (landskouter) Oost-Vlaanderen 9860",
    "addr:housenumber":"35",
    "addr:postcode":"9860",
    "addr:street":"Rooberg",
    "iso:country":"BE",
    "sg:address":"Rooberg 35",
    "sg:city":"Oosterzele (landskouter)",
    "sg:classifiers":[
        {
            "category":"Autos & Motor Vehicles",
            "subcategory":"Automobile Sales",
            "type":"Retail Goods"
        }
    ],
    "sg:phone":"+32 9 362 69 02",
    "sg:postcode":"9860",
    "sg:province":"Oost-Vlaanderen",
    "sg:tags":[
        "ceremony",
        "car"
    ],
    "wof:name":"Bekaert Frans",
    "wof:placetype":"venue"
},
  "geometry": {"coordinates":[3.8034880161,50.9637145996],"type":"Point"}
}