{
  "type": "Feature",
  "properties": {
    "iso:country":"BE",
    "sg:address":"Rue Du Moulin 7",
    "sg:city":"Charleroi",
    "sg:orig_category":"Rijscholen",
    "sg:phone":"+32 71 47 65 35",
    "sg:postcode":"6010",
    "sg:province":"Hainaut",
    "wof:name":"Aibv",
    "wof:placetype":"venue"
},
  "geometry": {"coordinates":[4.4387922287,50.4077949524],"type":"Point"}
}