{
  "type": "Feature",
  "properties": {
    "addr:full":"Rue De L'orme 2 Virton (saint-mard) Luxembourg 6762",
    "addr:housenumber":"2",
    "addr:postcode":"6762",
    "addr:street":"Rue De L'Orme",
    "iso:country":"BE",
    "sg:address":"Rue De L'orme 2",
    "sg:city":"Virton (saint-mard)",
    "sg:classifiers":[
        {
            "category":"Health Services",
            "subcategory":"Doctor",
            "type":"Services"
        }
    ],
    "sg:phone":"+32 63 57 73 67",
    "sg:postcode":"6762",
    "sg:province":"Luxembourg",
    "sg:tags":[
        "medicinephysicians",
        "surgeon"
    ],
    "wof:name":"Jacques Christian",
    "wof:placetype":"venue"
},
  "geometry": {"coordinates":[5.5282812119,49.5566291809],"type":"Point"}
}