{
  "type": "Feature",
  "properties": {
    "iso:country":"BE",
    "sg:address":"Glasblazerijlaan 47",
    "sg:city":"Vorst/forest",
    "sg:orig_category":"Huishoudapparaten, televisies and radio's",
    "sg:phone":"+32 2 376 50 00",
    "sg:postcode":"1190",
    "sg:province":"Bruxelles-Capitale",
    "wof:name":"Coffernils-dee",
    "wof:placetype":"venue"
},
  "geometry": {"coordinates":[4.3160610199,50.8045921326],"type":"Point"}
}