{
  "type": "Feature",
  "properties": {
    "iso:country":"BE",
    "sg:address":"Markizaatstraat 48",
    "sg:city":"Zonnebeke",
    "sg:orig_category":"Aardappelproducten Gh Groenten and fruit Gh",
    "sg:phone":"+32 57 46 65 89",
    "sg:postcode":"8980",
    "sg:province":"West-Vlaanderen",
    "wof:name":"Michel Verbeerst",
    "wof:placetype":"venue"
},
  "geometry": {"coordinates":[2.9872550964,50.8730812073],"type":"Point"}
}