{
  "type": "Feature",
  "properties": {
    "iso:country":"BE",
    "sg:address":"Eiland 12",
    "sg:city":"Nevele",
    "sg:orig_category":"M\u00e9decins and sp\u00e9cialistes",
    "sg:phone":"+32 9 371 67 58",
    "sg:postcode":"9850",
    "sg:province":"Oost-Vlaanderen",
    "wof:name":"Eric Van Hecke",
    "wof:placetype":"venue"
},
  "geometry": {"coordinates":[3.561029911,51.0875968933],"type":"Point"}
}