{
  "type": "Feature",
  "properties": {
    "addr:full":"Fabriekstraat 162 Sint-pieters-leeuw Vlaams-Brabant 1601",
    "addr:housenumber":"162",
    "addr:postcode":"1601",
    "addr:street":"Fabriekstraat",
    "iso:country":"BE",
    "sg:address":"Fabriekstraat 162",
    "sg:city":"Sint-pieters-leeuw",
    "sg:orig_category":"Charpentes and couvertures",
    "sg:phone":"+32 2 377 85 50",
    "sg:postcode":"1601",
    "sg:province":"Vlaams-Brabant",
    "wof:name":"De Greef J.p. & J.m.",
    "wof:placetype":"venue"
},
  "geometry": {"coordinates":[4.2916808128,50.7835083008],"type":"Point"}
}