{
  "type": "Feature",
  "properties": {
    "iso:country":"BE",
    "sg:address":"Avenue Des Combattants 33",
    "sg:city":"Genappe",
    "sg:orig_category":"Peinture. Rev\u00eatements pour sols and murs",
    "sg:phone":"+32 67 77 21 27",
    "sg:postcode":"1470",
    "sg:province":"Brabant Wallon",
    "wof:name":"Serge Denis",
    "wof:placetype":"venue"
},
  "geometry": {"coordinates":[4.5067939758,50.6158447266],"type":"Point"}
}