{
  "type": "Feature",
  "properties": {
    "iso:country":"BE",
    "sg:address":"Tiensevest 61",
    "sg:city":"Leuven",
    "sg:classifiers":[
        {
            "category":"Shopping",
            "subcategory":"Computers & Home Electronics",
            "type":"Retail Goods"
        }
    ],
    "sg:phone":"+32 16 22 26 89",
    "sg:postcode":"3010",
    "sg:province":"Vlaams-Brabant",
    "sg:tags":[
        "chamber",
        "commerce"
    ],
    "wof:name":"Leuven Chamber Of Commerce And Industry",
    "wof:placetype":"venue"
},
  "geometry": {"coordinates":[4.7332701683,50.8693008423],"type":"Point"}
}