{
  "type": "Feature",
  "properties": {
    "iso:country":"BE",
    "sg:address":"Hovesstraat 97",
    "sg:city":"Edingen/enghien",
    "sg:orig_category":"Boekhandels",
    "sg:phone":"+32 2 395 84 63",
    "sg:postcode":"7850",
    "sg:province":"Hainaut",
    "wof:name":"Les Potains De La Dodane",
    "wof:placetype":"venue"
},
  "geometry": {"coordinates":[4.0340881348,50.6919746399],"type":"Point"}
}