{
  "type": "Feature",
  "properties": {
    "addr:full":"Rue De La Gare 56 Kelmis/la Calamine Li\u00e8ge 4728",
    "addr:housenumber":"56",
    "addr:postcode":"4728",
    "addr:street":"Rue De La Gare",
    "iso:country":"BE",
    "sg:address":"Rue De La Gare 56",
    "sg:city":"Kelmis/la Calamine",
    "sg:orig_category":"Artistes ind\u00e9pendants",
    "sg:phone":"+32 87 65 98 93",
    "sg:postcode":"4728",
    "sg:province":"Li\u00e8ge",
    "wof:name":"Hermann Scheiff",
    "wof:placetype":"venue"
},
  "geometry": {"coordinates":[6.0394158363,50.7077674866],"type":"Point"}
}