{
  "type": "Feature",
  "properties": {
    "iso:country":"BE",
    "sg:address":"Bar F Du Fourstraat 7",
    "sg:city":"Turnhout",
    "sg:orig_category":"Transports routiers de marchandises",
    "sg:phone":"+32 14 42 54 17",
    "sg:postcode":"2300",
    "sg:province":"Antwerpen",
    "wof:name":"Migatra",
    "wof:placetype":"venue"
},
  "geometry": {"coordinates":[4.9507679939,51.3236961365],"type":"Point"}
}