{
  "type": "Feature",
  "properties": {
    "addr:full":"Avenue De L'exposition Universelle 3 Bruxelles (ganshoren) Bruxelles-Capitale 1083",
    "addr:housenumber":"3",
    "addr:postcode":"1083",
    "addr:street":"Avenue De L'Exposition Universelle",
    "iso:country":"BE",
    "sg:address":"Avenue De L'exposition Universelle 3",
    "sg:city":"Bruxelles (ganshoren)",
    "sg:classifiers":[
        {
            "category":"Personal",
            "subcategory":"Beauty Salon",
            "type":"Services"
        }
    ],
    "sg:phone":"+32 2 428 92 19",
    "sg:postcode":"1083",
    "sg:province":"Bruxelles-Capitale",
    "sg:tags":[
        "lady",
        "-",
        "hairdressing"
    ],
    "wof:name":"Baumans V",
    "wof:placetype":"venue"
},
  "geometry": {"coordinates":[4.3202872276,50.8721542358],"type":"Point"}
}