{
  "type": "Feature",
  "properties": {
    "addr:full":"Kerkstraat 26 Duffel Antwerpen 2570",
    "addr:housenumber":"26",
    "addr:postcode":"2570",
    "addr:street":"Kerkstraat",
    "iso:country":"BE",
    "sg:address":"Kerkstraat 26",
    "sg:city":"Duffel",
    "sg:orig_category":"Banques and organismes de cr\u00e9dit",
    "sg:phone":"+32 15 30 71 10",
    "sg:postcode":"2570",
    "sg:province":"Antwerpen",
    "wof:name":"Kbc",
    "wof:placetype":"venue"
},
  "geometry": {"coordinates":[4.5004458427,51.0948867798],"type":"Point"}
}