{
  "type": "Feature",
  "properties": {
    "iso:country":"BE",
    "sg:address":"Hoenderstraat 2",
    "sg:city":"Destelbergen",
    "sg:orig_category":"Eleveurs de bovins",
    "sg:phone":"+32 9 355 66 11",
    "sg:postcode":"9070",
    "sg:province":"Oost-Vlaanderen",
    "wof:name":"Georges Steendam",
    "wof:placetype":"venue"
},
  "geometry": {"coordinates":[3.8244740963,51.0697937012],"type":"Point"}
}