{
  "type": "Feature",
  "properties": {
    "addr:full":"Rue De Ch\u00e8vremont 61 Seneffe (arquennes) Hainaut 7181",
    "addr:housenumber":"61",
    "addr:postcode":"7181",
    "addr:street":"Rue De Che\u0300Vremont",
    "iso:country":"BE",
    "sg:address":"Rue De Ch\u00e8vremont 61",
    "sg:city":"Seneffe (arquennes)",
    "sg:classifiers":[
        {
            "category":"Personal",
            "subcategory":"Beauty Salon",
            "type":"Services"
        }
    ],
    "sg:phone":"+32 67 87 73 60",
    "sg:postcode":"7181",
    "sg:province":"Hainaut",
    "sg:tags":[
        "lady",
        "-",
        "hairdressing"
    ],
    "wof:name":"Jacqueline",
    "wof:placetype":"venue"
},
  "geometry": {"coordinates":[4.2589969635,50.5626296997],"type":"Point"}
}