{
  "type": "Feature",
  "properties": {
    "iso:country":"BE",
    "sg:address":"Rue Pionveau 8",
    "sg:city":"Momignies",
    "sg:orig_category":"Artsen and specialisten",
    "sg:phone":"+32 60 51 26 95",
    "sg:postcode":"6591",
    "sg:province":"Hainaut",
    "wof:name":"G. Hostier",
    "wof:placetype":"venue"
},
  "geometry": {"coordinates":[4.201695919,50.0388031006],"type":"Point"}
}