{
  "type": "Feature",
  "properties": {
    "addr:full":"Rue Valentin Hougardy 19 Havelange Namur 5370",
    "addr:housenumber":"19",
    "addr:postcode":"5370",
    "addr:street":"Rue Valentin Hougardy",
    "iso:country":"BE",
    "sg:address":"Rue Valentin Hougardy 19",
    "sg:city":"Havelange",
    "sg:orig_category":"Eleveurs de bovins",
    "sg:phone":"+32 83 63 36 27",
    "sg:postcode":"5370",
    "sg:province":"Namur",
    "wof:name":"Yvan Macors",
    "wof:placetype":"venue"
},
  "geometry": {"coordinates":[5.2476358414,50.3882331848],"type":"Point"}
}