{
  "type": "Feature",
  "properties": {
    "addr:full":"R\u00c9sidence Du Haut Lieu 35 La Louviere Hainaut 7110",
    "addr:housenumber":"35",
    "addr:postcode":"7110",
    "addr:street":"Re\u0301Sidence Du Haut Lieu",
    "iso:country":"BE",
    "sg:address":"R\u00c9sidence Du Haut Lieu 35",
    "sg:city":"La Louviere",
    "sg:orig_category":"Schoonheidssalons",
    "sg:phone":"+32 64 66 48 63",
    "sg:postcode":"7110",
    "sg:province":"Hainaut",
    "wof:name":"Nancy Matthys",
    "wof:placetype":"venue"
},
  "geometry": {"coordinates":[4.117125988,50.4812393188],"type":"Point"}
}