{
  "type": "Feature",
  "properties": {
    "iso:country":"BE",
    "sg:address":"Avenue Des Combattants 171",
    "sg:city":"Genappe (bousval)",
    "sg:orig_category":"Non-Classified Establishments",
    "sg:phone":"+32 10 61 10 36",
    "sg:postcode":"1470",
    "sg:province":"Brabant Wallon",
    "wof:name":"De Broux (papeteries) Sprl",
    "wof:placetype":"venue"
},
  "geometry": {"coordinates":[4.5357627869,50.6321411133],"type":"Point"}
}