{
  "type": "Feature",
  "properties": {
    "addr:full":"Avenue D'orbaix 19a Bruxelles (uccle) Bruxelles-Capitale 1180",
    "addr:housenumber":"19a",
    "addr:postcode":"1180",
    "addr:street":"Avenue D'Orbaix",
    "iso:country":"BE",
    "sg:address":"Avenue D'orbaix 19a",
    "sg:city":"Bruxelles (uccle)",
    "sg:classifiers":[
        {
            "category":"Health Services",
            "subcategory":"Doctor",
            "type":"Services"
        }
    ],
    "sg:phone":"+32 2 375 93 92",
    "sg:postcode":"1180",
    "sg:province":"Bruxelles-Capitale",
    "sg:tags":[
        "psychotherapist",
        "psychoanalyst"
    ],
    "wof:name":"Bool A",
    "wof:placetype":"venue"
},
  "geometry": {"coordinates":[4.3706421852,50.7891197205],"type":"Point"}
}