{
  "type": "Feature",
  "properties": {
    "iso:country":"BE",
    "sg:address":"Burewee",
    "sg:city":"Toernich",
    "sg:orig_category":"Entretien and r\u00e9parations de machines de bureau and ordinateurs. Fournitures de bureau. Ordinateurs ",
    "sg:phone":"+32 63 21 83 83",
    "sg:postcode":"6700",
    "sg:province":"Luxembourg",
    "wof:name":"Houba Informatique",
    "wof:placetype":"venue"
},
  "geometry": {"coordinates":[5.7780370712,49.651184082],"type":"Point"}
}