{
  "type": "Feature",
  "properties": {
    "iso:country":"BE",
    "sg:address":"Edgard Sohiestraat 7",
    "sg:city":"Hoeilaart",
    "sg:classifiers":[
        {
            "category":"Retail",
            "subcategory":"Auto Repair",
            "type":"Services"
        }
    ],
    "sg:phone":"+32 2 657 01 77",
    "sg:postcode":"1560",
    "sg:province":"Vlaams-Brabant",
    "sg:tags":[
        "garage"
    ],
    "wof:name":"Vandenhaute",
    "wof:placetype":"venue"
},
  "geometry": {"coordinates":[4.4756889343,50.7702674866],"type":"Point"}
}