{
  "type": "Feature",
  "properties": {
    "iso:country":"BE",
    "sg:address":"Rue Gillebertus 23",
    "sg:city":"Jette/jette",
    "sg:orig_category":"M\u00e9decins and sp\u00e9cialistes",
    "sg:phone":"+32 2 428 56 27",
    "sg:postcode":"1090",
    "sg:province":"Bruxelles-Capitale",
    "wof:name":"Paul Kestelyn",
    "wof:placetype":"venue"
},
  "geometry": {"coordinates":[4.3252158165,50.8769264221],"type":"Point"}
}