{
  "type": "Feature",
  "properties": {
    "addr:full":"Neuve Voie 25 Durbuy Luxembourg 6940",
    "addr:housenumber":"25",
    "addr:postcode":"6940",
    "addr:street":"Neuve Voie",
    "iso:country":"BE",
    "sg:address":"Neuve Voie 25",
    "sg:city":"Durbuy",
    "sg:classifiers":[
        {
            "category":"Arts & Performance",
            "subcategory":"Art Gallery",
            "type":"Entertainment"
        }
    ],
    "sg:phone":"+32 86 21 13 74",
    "sg:postcode":"6940",
    "sg:province":"Luxembourg",
    "wof:name":"L\u00e9v\u00eaque B",
    "wof:placetype":"venue"
},
  "geometry": {"coordinates":[5.4585680962,50.3490333557],"type":"Point"}
}