{
  "type": "Feature",
  "properties": {
    "addr:full":"Rue Vanderlinden 180 Schaarbeek/schaerbeek Bruxelles-Capitale 1030",
    "addr:housenumber":"180",
    "addr:postcode":"1030",
    "addr:street":"Rue Vanderlinden",
    "iso:country":"BE",
    "sg:address":"Rue Vanderlinden 180",
    "sg:city":"Schaarbeek/schaerbeek",
    "sg:classifiers":[
        {
            "category":"Arena",
            "subcategory":"Sports Club",
            "type":"Entertainment"
        }
    ],
    "sg:phone":"+32 2 215 81 80",
    "sg:postcode":"1030",
    "sg:province":"Bruxelles-Capitale",
    "sg:tags":[
        "de"
    ],
    "wof:name":"B.c. Bowlmaster",
    "wof:placetype":"venue"
},
  "geometry": {"coordinates":[4.3706378937,50.8702011108],"type":"Point"}
}