{
  "type": "Feature",
  "properties": {
    "iso:country":"BE",
    "sg:address":"Sint-jan Berchmansstraat 9",
    "sg:city":"Diest",
    "sg:orig_category":"Agences d\u00b4interim and personnel temporaire",
    "sg:phone":"+32 13 32 52 40",
    "sg:postcode":"3290",
    "sg:province":"Vlaams-Brabant",
    "wof:name":"Manpower",
    "wof:placetype":"venue"
},
  "geometry": {"coordinates":[5.0510430336,50.9837036133],"type":"Point"}
}