{
  "type": "Feature",
  "properties": {
    "addr:full":"Rue Porte-de-france 2 Virton Luxembourg 6760",
    "addr:housenumber":"2",
    "addr:postcode":"6760",
    "addr:street":"Rue Porte-De-France",
    "iso:country":"BE",
    "sg:address":"Rue Porte-de-france 2",
    "sg:city":"Virton",
    "sg:orig_category":"Studios photographiques",
    "sg:phone":"+32 63 58 39 48",
    "sg:postcode":"6760",
    "sg:province":"Luxembourg",
    "wof:name":"P. Gaillet",
    "wof:placetype":"venue"
},
  "geometry": {"coordinates":[5.5332779884,49.5668258667],"type":"Point"}
}