{
  "type": "Feature",
  "properties": {
    "iso:country":"BE",
    "sg:address":"Kasteeldreef 174",
    "sg:city":"Beveren (beveren-waas)",
    "sg:classifiers":[
        {
            "category":"Health Services",
            "subcategory":"Doctor",
            "type":"Services"
        }
    ],
    "sg:phone":"+32 3 775 71 24",
    "sg:postcode":"9120",
    "sg:province":"Oost-Vlaanderen",
    "sg:tags":[
        "medicinephysicians",
        "surgeon"
    ],
    "wof:name":"De Mesel Freddy",
    "wof:placetype":"venue"
},
  "geometry": {"coordinates":[4.253964901,51.2210388184],"type":"Point"}
}