{
  "type": "Feature",
  "properties": {
    "iso:country":"BE",
    "sg:address":"Veldstraat 39",
    "sg:city":"Brasschaat",
    "sg:orig_category":"Jardinage",
    "sg:phone":"+32 3 652 18 22",
    "sg:postcode":"2930",
    "sg:province":"Antwerpen",
    "wof:name":"Tuinen Van (h)eden",
    "wof:placetype":"venue"
},
  "geometry": {"coordinates":[4.4883317947,51.2903366089],"type":"Point"}
}