{
  "type": "Feature",
  "properties": {
    "iso:country":"BE",
    "sg:address":"Zoning Du Brule 0",
    "sg:city":"Quaregnon",
    "sg:orig_category":"Kunststofrecipi\u00ebnten and -verpakkingen Fab Winkelinrichting and handelsuitrusting Gh",
    "sg:phone":"+32 65 76 57 57",
    "sg:postcode":"7390",
    "sg:province":"Hainaut",
    "wof:name":"Laurence",
    "wof:placetype":"venue"
},
  "geometry": {"coordinates":[3.8639008999,50.446937561],"type":"Point"}
}