{
  "type": "Feature",
  "properties": {
    "addr:full":"Kruishoutemsestw 2 Zingem Oost-Vlaanderen 9750",
    "addr:housenumber":"2",
    "addr:postcode":"9750",
    "addr:street":"Kruishoutemsestw;Oost-Vlaanderen",
    "iso:country":"BE",
    "sg:address":"Kruishoutemsestw 2",
    "sg:city":"Zingem",
    "sg:classifiers":[
        {
            "category":"Banks & Credit Unions",
            "subcategory":"Bank",
            "type":"Services"
        }
    ],
    "sg:phone":"+32 16 64 07 42",
    "sg:postcode":"9750",
    "sg:province":"Oost-Vlaanderen",
    "wof:name":"G\u00e9n\u00e9rale De Banque Sa",
    "wof:placetype":"venue"
},
  "geometry": {"coordinates":[3.3261549473,51.0001182556],"type":"Point"}
}