{
  "type": "Feature",
  "properties": {
    "addr:full":"Avenue Du Karreveld 25 Bruxelles (molenbeek-saint-jean) Bruxelles-Capitale 1080",
    "addr:housenumber":"25",
    "addr:postcode":"1080",
    "addr:street":"Avenue Du Karreveld",
    "iso:country":"BE",
    "sg:address":"Avenue Du Karreveld 25",
    "sg:city":"Bruxelles (molenbeek-saint-jean)",
    "sg:classifiers":[
        {
            "category":"Health Services",
            "subcategory":"Health Practitioner",
            "type":"Services"
        }
    ],
    "sg:phone":"+32 2 410 03 94",
    "sg:postcode":"1080",
    "sg:province":"Bruxelles-Capitale",
    "sg:tags":[
        "physiotherapist"
    ],
    "wof:name":"Van Nyverseel Bart",
    "wof:placetype":"venue"
},
  "geometry": {"coordinates":[4.3185648918,50.8590164185],"type":"Point"}
}