{
  "type": "Feature",
  "properties": {
    "addr:full":"Alfons Braeckmanlaan 145 Gent (sint-amandsberg) Oost-Vlaanderen 9040",
    "addr:housenumber":"145",
    "addr:postcode":"9040",
    "addr:street":"Braeckmanlaan",
    "iso:country":"BE",
    "sg:address":"Alfons Braeckmanlaan 145",
    "sg:city":"Gent (sint-amandsberg)",
    "sg:classifiers":[
        {
            "category":"Health Services",
            "subcategory":"Health Practitioner",
            "type":"Services"
        }
    ],
    "sg:phone":"+32 9 228 51 03",
    "sg:postcode":"9040",
    "sg:province":"Oost-Vlaanderen",
    "sg:tags":[
        "physiotherapist"
    ],
    "wof:name":"Vincke E",
    "wof:placetype":"venue"
},
  "geometry": {"coordinates":[3.7731831074,51.0643997192],"type":"Point"}
}