{
  "type": "Feature",
  "properties": {
    "iso:country":"BE",
    "sg:address":"Chauss\u00c9e De Waremme 79",
    "sg:city":"Onhaye",
    "sg:orig_category":"Travaux d'isolation. Travaux de pl\u00e2trage",
    "sg:phone":"+32 85 21 65 57",
    "sg:postcode":"4520",
    "sg:province":"Li\u00e8ge",
    "wof:name":"Benoit Felgenhauer",
    "wof:placetype":"venue"
},
  "geometry": {"coordinates":[5.2139430046,50.5367546082],"type":"Point"}
}