{
  "type": "Feature",
  "properties": {
    "iso:country":"BE",
    "sg:address":"Chauss\u00e9e De Charleroi 43",
    "sg:city":"Perwez (thorembais-saint-trond)",
    "sg:classifiers":[
        {
            "category":"Real Estate",
            "subcategory":"Real Estate Services",
            "type":"Services"
        }
    ],
    "sg:phone":"+32 10 22 89 04",
    "sg:postcode":"1360",
    "sg:province":"Brabant Wallon",
    "wof:name":"Immo Region",
    "wof:placetype":"venue"
},
  "geometry": {"coordinates":[4.7800917625,50.6364212036],"type":"Point"}
}