{
  "type": "Feature",
  "properties": {
    "addr:full":"Kapelstraat 71 Temse (steendorp) Oost-Vlaanderen 9140",
    "addr:housenumber":"71",
    "addr:postcode":"9140",
    "addr:street":"Kapelstraat",
    "iso:country":"BE",
    "sg:address":"Kapelstraat 71",
    "sg:city":"Temse (steendorp)",
    "sg:classifiers":[
        {
            "category":"Home & Garden",
            "subcategory":"Carpets & Floor Coverings",
            "type":"Retail Goods"
        }
    ],
    "sg:phone":"+32 3 744 10 19",
    "sg:postcode":"9140",
    "sg:province":"Oost-Vlaanderen",
    "sg:tags":[
        "layer",
        "mosaicists"
    ],
    "wof:name":"Wuytack R Bvba",
    "wof:placetype":"venue"
},
  "geometry": {"coordinates":[4.2492799759,51.1289596558],"type":"Point"}
}