{
  "type": "Feature",
  "properties": {
    "addr:full":"Rue Jacques Jansen 7 Bruxelles (schaerbeek) Bruxelles-Capitale 1030",
    "addr:housenumber":"7",
    "addr:postcode":"1030",
    "addr:street":"Rue Jacques Jansen",
    "iso:country":"BE",
    "sg:address":"Rue Jacques Jansen 7",
    "sg:city":"Bruxelles (schaerbeek)",
    "sg:classifiers":[
        {
            "category":"Food & Beverages",
            "subcategory":"Candy",
            "type":"Retail Goods"
        }
    ],
    "sg:phone":"+32 2 736 23 05",
    "sg:postcode":"1030",
    "sg:province":"Bruxelles-Capitale",
    "wof:name":"Pral'inn",
    "wof:placetype":"venue"
},
  "geometry": {"coordinates":[4.3886041641,50.853351593],"type":"Point"}
}