{
  "type": "Feature",
  "properties": {
    "iso:country":"BE",
    "sg:address":"Rue Edouard Etienne 4",
    "sg:city":"Braine-le-comte",
    "sg:classifiers":[
        {
            "category":"Building & Trades",
            "subcategory":"Construction",
            "type":"Services"
        }
    ],
    "sg:phone":"+32 67 55 41 57",
    "sg:postcode":"7090",
    "sg:province":"Hainaut",
    "sg:tags":[
        "installation",
        "-",
        "central",
        "heating"
    ],
    "wof:name":"Mercier M",
    "wof:placetype":"venue"
},
  "geometry": {"coordinates":[4.1372098923,50.6106338501],"type":"Point"}
}