{
  "type": "Feature",
  "properties": {
    "iso:country":"BE",
    "sg:address":"De Keyserlei 5 B 4",
    "sg:city":"Antwerpen",
    "sg:classifiers":[
        {
            "category":"Airport",
            "type":"Transportation"
        }
    ],
    "sg:phone":"+32 3 205 16 16",
    "sg:postcode":"2018",
    "sg:province":"Antwerpen",
    "sg:tags":[
        "transport",
        "air"
    ],
    "wof:name":"Maersk Logistieks Benelux Bv",
    "wof:placetype":"venue"
},
  "geometry": {"coordinates":[4.4162421227,51.2180023193],"type":"Point"}
}