{
  "type": "Feature",
  "properties": {
    "addr:full":"De Dellekens 38 Grobbendonk (bouwel) Antwerpen 2288",
    "addr:housenumber":"38",
    "addr:postcode":"2288",
    "addr:street":"De Dellekens",
    "iso:country":"BE",
    "sg:address":"De Dellekens 38",
    "sg:city":"Grobbendonk (bouwel)",
    "sg:classifiers":[
        {
            "category":"Building & Trades",
            "subcategory":"Construction",
            "type":"Services"
        }
    ],
    "sg:phone":"+32 14 51 75 65",
    "sg:postcode":"2288",
    "sg:province":"Antwerpen",
    "sg:tags":[
        "stucco",
        "contractor"
    ],
    "wof:name":"Driessens P",
    "wof:placetype":"venue"
},
  "geometry": {"coordinates":[4.7330160141,51.1656799316],"type":"Point"}
}