{
  "type": "Feature",
  "properties": {
    "iso:country":"BE",
    "sg:address":"Boulevard Fr\u00e8re-orban",
    "sg:city":"Li\u00e8ge 1",
    "sg:classifiers":[
        {
            "category":"Government",
            "subcategory":"Fire Station",
            "type":"Public Place"
        }
    ],
    "sg:phone":"+32 4 252 76 76",
    "sg:postcode":"4000",
    "sg:province":"Li\u00e8ge",
    "sg:tags":[
        "installation",
        "-",
        "air conditioning"
    ],
    "wof:name":"Bielen P",
    "wof:placetype":"venue"
},
  "geometry": {"coordinates":[5.5726890564,50.6360473633],"type":"Point"}
}