{
  "type": "Feature",
  "properties": {
    "addr:full":"Donklaan 77 Box 12 Berlare Oost-Vlaanderen 9290",
    "addr:housenumber":"77 box 12",
    "addr:postcode":"9290",
    "addr:street":"Donklaan",
    "iso:country":"BE",
    "sg:address":"Donklaan 77 Box 12",
    "sg:city":"Berlare",
    "sg:classifiers":[
        {
            "category":"Professional",
            "subcategory":"Lawyer & Legal Services",
            "type":"Services"
        }
    ],
    "sg:phone":"+32 9 367 61 43",
    "sg:postcode":"9290",
    "sg:province":"Oost-Vlaanderen",
    "wof:name":"Van Keer Greta",
    "wof:placetype":"venue"
},
  "geometry": {"coordinates":[3.9817318916,51.0395088196],"type":"Point"}
}