{
  "type": "Feature",
  "properties": {
    "addr:full":"Leiselestraat 55 Sint-michiels West-Vlaanderen 8200",
    "addr:housenumber":"55",
    "addr:postcode":"8200",
    "addr:street":"Leiselestraat",
    "iso:country":"BE",
    "sg:address":"Leiselestraat 55",
    "sg:city":"Sint-michiels",
    "sg:orig_category":"Banques and organismes de cr\u00e9dit. Assurances",
    "sg:phone":"+32 50 38 49 05",
    "sg:postcode":"8200",
    "sg:province":"West-Vlaanderen",
    "wof:name":"Zakenkantoor Dejaeger",
    "wof:placetype":"venue"
},
  "geometry": {"coordinates":[3.2203838825,51.1862487793],"type":"Point"}
}