{
  "type": "Feature",
  "properties": {
    "addr:full":"Steenveldstraat 58 Lubbeek (linden) Vlaams-Brabant 3210",
    "addr:housenumber":"58",
    "addr:postcode":"3210",
    "addr:street":"Steenveldstraat",
    "iso:country":"BE",
    "sg:address":"Steenveldstraat 58",
    "sg:city":"Lubbeek (linden)",
    "sg:classifiers":[
        {
            "category":"Building & Trades",
            "subcategory":"Electrical",
            "type":"Services"
        }
    ],
    "sg:phone":"+32 16 62 22 65",
    "sg:postcode":"3210",
    "sg:province":"Vlaams-Brabant",
    "sg:tags":[
        "electric",
        "-",
        "housewiring",
        "contractor"
    ],
    "wof:name":"Breysem",
    "wof:placetype":"venue"
},
  "geometry": {"coordinates":[4.7803010941,50.9008712769],"type":"Point"}
}