{
  "type": "Feature",
  "properties": {
    "iso:country":"BE",
    "sg:address":"Geluwestraat 2",
    "sg:city":"Menen",
    "sg:orig_category":"M\u00e9decins and sp\u00e9cialistes",
    "sg:phone":"+32 56 57 73 69",
    "sg:postcode":"8930",
    "sg:province":"West-Vlaanderen",
    "wof:name":"Geertrui Spruytte",
    "wof:placetype":"venue"
},
  "geometry": {"coordinates":[3.1108579636,50.8056755066],"type":"Point"}
}