{
  "type": "Feature",
  "properties": {
    "iso:country":"BE",
    "sg:address":"Leopold Iii Straat 40",
    "sg:city":"Kortessem",
    "sg:orig_category":"Kruideniers Verzekeringsmakelaars and experts",
    "sg:phone":"+32 12 23 35 01",
    "sg:postcode":"3724",
    "sg:province":"Limburg",
    "wof:name":"Smeers",
    "wof:placetype":"venue"
},
  "geometry": {"coordinates":[5.43141222,50.8420066833],"type":"Point"}
}