{
  "type": "Feature",
  "properties": {
    "iso:country":"BE",
    "sg:address":"Rue Burette 22",
    "sg:city":"Crisn\u00e9e",
    "sg:classifiers":[
        {
            "category":"Health Services",
            "subcategory":"Doctor",
            "type":"Services"
        }
    ],
    "sg:phone":"+32 4 257 43 96",
    "sg:postcode":"4367",
    "sg:province":"Li\u00e8ge",
    "sg:tags":[
        "medicinephysicians",
        "surgeon"
    ],
    "wof:name":"Lamboray-brisbois Anne-marie",
    "wof:placetype":"venue"
},
  "geometry": {"coordinates":[5.3967180252,50.7034416199],"type":"Point"}
}