{
  "type": "Feature",
  "properties": {
    "iso:country":"BE",
    "sg:address":"Vrijestraat 3",
    "sg:city":"Lo-reninge",
    "sg:orig_category":"Eleveurs and marchands de porcs. Eleveurs de bovins",
    "sg:phone":"+32 58 28 83 13",
    "sg:postcode":"8647",
    "sg:province":"West-Vlaanderen",
    "wof:name":"Guido Decroos",
    "wof:placetype":"venue"
},
  "geometry": {"coordinates":[2.7150220871,50.9791221619],"type":"Point"}
}