{
  "type": "Feature",
  "properties": {
    "iso:country":"BE",
    "sg:address":"Chauss\u00c9e D'aelbeke 14",
    "sg:city":"Moeskroen/mouscron",
    "sg:orig_category":"Pain, p\u00e2tisseries and confiseries",
    "sg:phone":"+32 56 34 12 39",
    "sg:postcode":"7700",
    "sg:province":"Hainaut",
    "wof:name":"Guy Veys-van Heuverswijn",
    "wof:placetype":"venue"
},
  "geometry": {"coordinates":[3.2260398865,50.7484664917],"type":"Point"}
}