{
  "type": "Feature",
  "properties": {
    "iso:country":"BE",
    "sg:address":"Burgemeester Geyskensstraat 10",
    "sg:city":"Beringen",
    "sg:classifiers":[
        {
            "category":"Health Services",
            "subcategory":"Health Practitioner",
            "type":"Services"
        }
    ],
    "sg:phone":"+32 11 43 18 48",
    "sg:postcode":"3580",
    "sg:province":"Limburg",
    "sg:tags":[
        "physiotherapist"
    ],
    "wof:name":"Vanhoudt Polic",
    "wof:placetype":"venue"
},
  "geometry": {"coordinates":[5.2198529243,51.048866272],"type":"Point"}
}