{
  "type": "Feature",
  "properties": {
    "addr:full":"Mechelsestraat 32 Vilvoorde Vlaams-Brabant 1800",
    "addr:housenumber":"32",
    "addr:postcode":"1800",
    "addr:street":"Mechelsestraat",
    "iso:country":"BE",
    "sg:address":"Mechelsestraat 32",
    "sg:city":"Vilvoorde",
    "sg:orig_category":"Pain, p\u00e2tisseries and confiseries",
    "sg:phone":"+32 2 251 24 43",
    "sg:postcode":"1800",
    "sg:province":"Vlaams-Brabant",
    "wof:name":"Stefaan Kiekens",
    "wof:placetype":"venue"
},
  "geometry": {"coordinates":[4.4242172241,50.9320068359],"type":"Point"}
}