{
  "type": "Feature",
  "properties": {
    "iso:country":"BE",
    "sg:address":"Rue Brisselot 14",
    "sg:city":"Mons",
    "sg:orig_category":"Ordinateurs and \u00e9quipement informatique. R\u00e9alisation de programmes and logiciels. Formation and ense",
    "sg:phone":"+32 65 34 86 67",
    "sg:postcode":"7000",
    "sg:province":"Hainaut",
    "wof:name":"B.h. Cad",
    "wof:placetype":"venue"
},
  "geometry": {"coordinates":[3.959043026,50.4508781433],"type":"Point"}
}