{
  "type": "Feature",
  "properties": {
    "addr:full":"Rue Basse-voye 64-65 Doische Namur 5680",
    "addr:housenumber":"64-65",
    "addr:postcode":"5680",
    "addr:street":"Rue Basse-Voye",
    "iso:country":"BE",
    "sg:address":"Rue Basse-voye 64-65",
    "sg:city":"Doische",
    "sg:orig_category":"V\u00e9hicules automobiles. Entretien and r\u00e9parations de voitures",
    "sg:phone":"+32 82 67 76 26",
    "sg:postcode":"5680",
    "sg:province":"Namur",
    "wof:name":"Garage Radelet",
    "wof:placetype":"venue"
},
  "geometry": {"coordinates":[4.7328739166,50.1701431274],"type":"Point"}
}