{
  "type": "Feature",
  "properties": {
    "addr:full":"Rue De La Bataille 5 Neufch\u00e2teau Luxembourg 6840",
    "addr:housenumber":"5",
    "addr:postcode":"6840",
    "addr:street":"Rue De La Bataille",
    "iso:country":"BE",
    "sg:address":"Rue De La Bataille 5",
    "sg:city":"Neufch\u00e2teau",
    "sg:classifiers":[
        {
            "category":"Travel",
            "subcategory":"Hotels & Motels",
            "type":"Entertainment"
        }
    ],
    "sg:phone":"+32 61 27 70 71",
    "sg:postcode":"6840",
    "sg:province":"Luxembourg",
    "wof:name":"Potini\u00e8re (la)",
    "wof:placetype":"venue"
},
  "geometry": {"coordinates":[5.4319357872,49.8415908813],"type":"Point"}
}