{
  "type": "Feature",
  "properties": {
    "addr:full":"Kerkstraat 13ba Lummen Limburg 3560",
    "addr:housenumber":"13ba",
    "addr:postcode":"3560",
    "addr:street":"Kerkstraat",
    "iso:country":"BE",
    "sg:address":"Kerkstraat 13ba",
    "sg:city":"Lummen",
    "sg:orig_category":"Supermarch\u00e9s. Grands magasins",
    "sg:phone":"+32 13 52 14 89",
    "sg:postcode":"3560",
    "sg:province":"Limburg",
    "wof:name":"Gb Contact",
    "wof:placetype":"venue"
},
  "geometry": {"coordinates":[5.190100193,50.9858436584],"type":"Point"}
}