{
  "type": "Feature",
  "properties": {
    "iso:country":"BE",
    "sg:address":"Oostrozebekestraat 96",
    "sg:city":"Meulebeke",
    "sg:classifiers":[
        {
            "category":"Banks & Credit Unions",
            "subcategory":"Bank",
            "type":"Services"
        }
    ],
    "sg:phone":"+32 51 48 90 66",
    "sg:postcode":"8760",
    "sg:province":"West-Vlaanderen",
    "sg:tags":[
        "savings-banks"
    ],
    "wof:name":"Vervaeke M",
    "wof:placetype":"venue"
},
  "geometry": {"coordinates":[3.2921481133,50.9454994202],"type":"Point"}
}