{
  "type": "Feature",
  "properties": {
    "addr:full":"Avenue Du Martin P\u00eacheur 23-25 Bruxelles (watermael-boitsfort) Bruxelles-Capitale 1170",
    "addr:housenumber":"23-25",
    "addr:postcode":"1170",
    "addr:street":"Avenue Du Martin Pe\u0302Cheur",
    "iso:country":"BE",
    "sg:address":"Avenue Du Martin P\u00eacheur 23-25",
    "sg:city":"Bruxelles (watermael-boitsfort)",
    "sg:classifiers":[
        {
            "category":"Professional",
            "subcategory":"Engineering",
            "type":"Services"
        }
    ],
    "sg:phone":"+32 2 673 87 52",
    "sg:postcode":"1170",
    "sg:province":"Bruxelles-Capitale",
    "sg:tags":[
        "civil",
        "offices-"
    ],
    "wof:name":"G C I",
    "wof:placetype":"venue"
},
  "geometry": {"coordinates":[4.4035758972,50.8122825623],"type":"Point"}
}