{
  "type": "Feature",
  "properties": {
    "addr:full":"Groenestraat 191 Zedelgem West-Vlaanderen 8210",
    "addr:housenumber":"191",
    "addr:postcode":"8210",
    "addr:street":"Groenestraat",
    "iso:country":"BE",
    "sg:address":"Groenestraat 191",
    "sg:city":"Zedelgem",
    "sg:orig_category":"Brood, gebak and snoepgoed",
    "sg:phone":"+32 50 20 95 68",
    "sg:postcode":"8210",
    "sg:province":"West-Vlaanderen",
    "wof:name":"Bakkerij Verschaeve",
    "wof:placetype":"venue"
},
  "geometry": {"coordinates":[3.1528499126,51.1308097839],"type":"Point"}
}