{
  "type": "Feature",
  "properties": {
    "addr:full":"Stationsstr 274 Deerlijk West-Vlaanderen 8540",
    "addr:housenumber":"274",
    "addr:postcode":"8540",
    "iso:country":"BE",
    "sg:address":"Stationsstr 274",
    "sg:city":"Deerlijk",
    "sg:classifiers":[
        {
            "category":"Government",
            "subcategory":"Department Of Motor Vehicles",
            "type":"Public Place"
        }
    ],
    "sg:phone":"+32 56 22 44 84",
    "sg:postcode":"8540",
    "sg:province":"West-Vlaanderen",
    "sg:tags":[
        "equipment",
        "industrial",
        "transport",
        "motor-cars"
    ],
    "wof:name":"Kortrijkse Venn Druant-galle Bvba",
    "wof:placetype":"venue"
},
  "geometry": {"coordinates":[3.3489360809,50.8376808167],"type":"Point"}
}