{
  "type": "Feature",
  "properties": {
    "iso:country":"BE",
    "sg:address":"Rue Du Pont 7",
    "sg:city":"Hamoir",
    "sg:classifiers":[
        {
            "category":"Shopping",
            "subcategory":"Florist",
            "type":"Retail Goods"
        }
    ],
    "sg:phone":"+32 86 38 83 90",
    "sg:postcode":"4180",
    "sg:province":"Li\u00e8ge",
    "wof:name":"Marie-flore",
    "wof:placetype":"venue"
},
  "geometry": {"coordinates":[5.5356078148,50.4256286621],"type":"Point"}
}