{
  "type": "Feature",
  "properties": {
    "iso:country":"BE",
    "sg:address":"Meistraat 28",
    "sg:city":"Genk",
    "sg:orig_category":"Voertuigen",
    "sg:phone":"+32 89 62 11 50",
    "sg:postcode":"3600",
    "sg:province":"Limburg",
    "wof:name":"Joosten Trucks",
    "wof:placetype":"venue"
},
  "geometry": {"coordinates":[5.5353550911,50.9383926392],"type":"Point"}
}