{
  "type": "Feature",
  "properties": {
    "addr:full":"Rue Des Compagnons 13 Mons Hainaut 7000",
    "addr:housenumber":"13",
    "addr:postcode":"7000",
    "addr:street":"Rue Des Compagnons;Hainaut",
    "iso:country":"BE",
    "sg:address":"Rue Des Compagnons 13",
    "sg:city":"Mons",
    "sg:orig_category":"Advocaten and juridische adviseurs",
    "sg:phone":"+32 65 31 72 22",
    "sg:postcode":"7000",
    "sg:province":"Hainaut",
    "wof:name":"V. Hanton",
    "wof:placetype":"venue"
},
  "geometry": {"coordinates":[3.9482479095,50.4562034607],"type":"Point"}
}