{
  "type": "Feature",
  "properties": {
    "iso:country":"BE",
    "sg:address":"Lispersteenweg 21",
    "sg:city":"Lier",
    "sg:orig_category":"Pain, p\u00e2tisseries and confiseries",
    "sg:phone":"+32 3 489 28 34",
    "sg:postcode":"2500",
    "sg:province":"Antwerpen",
    "wof:name":"Edeltraud Weber",
    "wof:placetype":"venue"
},
  "geometry": {"coordinates":[4.5722141266,51.1386299133],"type":"Point"}
}