{
  "type": "Feature",
  "properties": {
    "addr:full":"Rue Emile Muraille 118 Herstal Li\u00e8ge 4040",
    "addr:housenumber":"118",
    "addr:postcode":"4040",
    "addr:street":"Rue Emile Muraille",
    "iso:country":"BE",
    "sg:address":"Rue Emile Muraille 118",
    "sg:city":"Herstal",
    "sg:orig_category":"Kapsalons",
    "sg:phone":"+32 4 264 20 09",
    "sg:postcode":"4040",
    "sg:province":"Li\u00e8ge",
    "wof:name":"Elia Papi",
    "wof:placetype":"venue"
},
  "geometry": {"coordinates":[5.6156520844,50.6727180481],"type":"Point"}
}