{
  "type": "Feature",
  "properties": {
    "iso:country":"BE",
    "sg:address":"Migrostraat 68",
    "sg:city":"Dendermonde (schoonaarde)",
    "sg:classifiers":[
        {
            "category":"Professional",
            "type":"Services"
        }
    ],
    "sg:phone":"+32 52 42 21 38",
    "sg:postcode":"9200",
    "sg:province":"Oost-Vlaanderen",
    "sg:tags":[
        "surveyor",
        "-",
        "valuer"
    ],
    "wof:name":"Van Den Steen K",
    "wof:placetype":"venue"
},
  "geometry": {"coordinates":[4.0283269882,50.9940185547],"type":"Point"}
}