{
  "type": "Feature",
  "properties": {
    "iso:country":"BE",
    "sg:address":"Av. Franklin Roosevelt 4",
    "sg:city":"Vise",
    "sg:orig_category":"Gespecialiseerde residenti\u00eble bouw",
    "sg:phone":"+32 4 379 88 55",
    "sg:postcode":"4600",
    "sg:province":"Li\u00e8ge",
    "wof:name":"Jean-pierre Dzisiak",
    "wof:placetype":"venue"
},
  "geometry": {"coordinates":[5.6882047653,50.7375450134],"type":"Point"}
}