{
  "type": "Feature",
  "properties": {
    "iso:country":"BE",
    "sg:address":"Lepelstraat 55",
    "sg:city":"Lommel",
    "sg:orig_category":"Brood, gebak and snoepgoed",
    "sg:phone":"+32 11 54 42 60",
    "sg:postcode":"3920",
    "sg:province":"Limburg",
    "wof:name":"Marina Vanbael",
    "wof:placetype":"venue"
},
  "geometry": {"coordinates":[5.3092260361,51.2334709167],"type":"Point"}
}