{
  "type": "Feature",
  "properties": {
    "addr:full":"Abeleplein 31 Poperinge West-Vlaanderen 8978",
    "addr:housenumber":"31",
    "addr:postcode":"8978",
    "addr:street":"Abeleplein",
    "iso:country":"BE",
    "sg:address":"Abeleplein 31",
    "sg:city":"Poperinge",
    "sg:orig_category":"Peinture. Rev\u00eatements pour sols and murs",
    "sg:phone":"+32 57 33 37 92",
    "sg:postcode":"8978",
    "sg:province":"West-Vlaanderen",
    "wof:name":"Odul G.m.",
    "wof:placetype":"venue"
},
  "geometry": {"coordinates":[2.6206049919,50.8592453003],"type":"Point"}
}