{
  "type": "Feature",
  "properties": {
    "addr:full":"Roomstraat 32 Lokeren Oost-Vlaanderen 9160",
    "addr:housenumber":"32",
    "addr:postcode":"9160",
    "addr:street":"Roomstraat",
    "iso:country":"BE",
    "sg:address":"Roomstraat 32",
    "sg:city":"Lokeren",
    "sg:orig_category":"M\u00e9decins and sp\u00e9cialistes",
    "sg:phone":"+32 9 348 50 48",
    "sg:postcode":"9160",
    "sg:province":"Oost-Vlaanderen",
    "wof:name":"Philippe De Clercq",
    "wof:placetype":"venue"
},
  "geometry": {"coordinates":[3.987983942,51.1030235291],"type":"Point"}
}