{
  "type": "Feature",
  "properties": {
    "iso:country":"BE",
    "sg:address":"Rue Du Pige 129",
    "sg:city":"Philippeville",
    "sg:orig_category":"Rundveehouders",
    "sg:phone":"+32 82 67 71 89",
    "sg:postcode":"5600",
    "sg:province":"Namur",
    "wof:name":"Paul Danneels",
    "wof:placetype":"venue"
},
  "geometry": {"coordinates":[4.6771459579,50.2011604309],"type":"Point"}
}