{
  "type": "Feature",
  "properties": {
    "addr:full":"Avenue Des Merisiers 24 Tournai Hainaut 7536",
    "addr:housenumber":"24",
    "addr:postcode":"7536",
    "addr:street":"Avenue Des Merisiers",
    "iso:country":"BE",
    "sg:address":"Avenue Des Merisiers 24",
    "sg:city":"Tournai",
    "sg:orig_category":"Sportclubs",
    "sg:phone":"+32 69 23 42 59",
    "sg:postcode":"7536",
    "sg:province":"Hainaut",
    "wof:name":"B.b.c. Tournai Mini",
    "wof:placetype":"venue"
},
  "geometry": {"coordinates":[3.426500082,50.5953903198],"type":"Point"}
}