{
  "type": "Feature",
  "properties": {
    "iso:country":"BE",
    "sg:address":"Rue De Mont Saint-pont 23",
    "sg:city":"Braine-le-chateau",
    "sg:classifiers":[
        {
            "category":"Personal",
            "subcategory":"Beauty Salon",
            "type":"Services"
        }
    ],
    "sg:phone":"+32 2 366 90 48",
    "sg:postcode":"1440",
    "sg:province":"Brabant Wallon",
    "sg:tags":[
        "de",
        "coiffure"
    ],
    "wof:name":"Coiffure R\u00c9tro",
    "wof:placetype":"venue"
},
  "geometry": {"coordinates":[4.2759728432,50.6840705872],"type":"Point"}
}