{
  "type": "Feature",
  "properties": {
    "addr:full":"Rue Trieu L'abb\u00c9 11 Walcourt Namur 5651",
    "addr:housenumber":"11",
    "addr:postcode":"5651",
    "addr:street":"Rue Trieu L'Abbe \u0301",
    "iso:country":"BE",
    "sg:address":"Rue Trieu L'abb\u00c9 11",
    "sg:city":"Walcourt",
    "sg:orig_category":"Kapsalons",
    "sg:phone":"+32 71 61 33 62",
    "sg:postcode":"5651",
    "sg:province":"Namur",
    "wof:name":"Coiffure Cara",
    "wof:placetype":"venue"
},
  "geometry": {"coordinates":[4.4510979652,50.2893486023],"type":"Point"}
}