{
  "type": "Feature",
  "properties": {
    "addr:full":"Pastorieweg 19 Brugge West-Vlaanderen 8310",
    "addr:housenumber":"19",
    "addr:postcode":"8310",
    "addr:street":"Pastorieweg",
    "iso:country":"BE",
    "sg:address":"Pastorieweg 19",
    "sg:city":"Brugge",
    "sg:orig_category":"Kinderopvang",
    "sg:phone":"+32 50 35 99 47",
    "sg:postcode":"8310",
    "sg:province":"West-Vlaanderen",
    "wof:name":"Kinderdagverblijven Ons Tuintje",
    "wof:placetype":"venue"
},
  "geometry": {"coordinates":[3.25116992,51.2156715393],"type":"Point"}
}