{
  "type": "Feature",
  "properties": {
    "iso:country":"BE",
    "sg:address":"Wittestraat 2",
    "sg:city":"Kortrijk",
    "sg:classifiers":[
        {
            "category":"Restaurant",
            "type":"Food & Drink"
        }
    ],
    "sg:phone":"+32 56 35 15 19",
    "sg:postcode":"8501",
    "sg:province":"West-Vlaanderen",
    "wof:name":"'t Rattekasteel",
    "wof:placetype":"venue"
},
  "geometry": {"coordinates":[3.2400100231,50.8491172791],"type":"Point"}
}