{
  "type": "Feature",
  "properties": {
    "addr:full":"Rue De La Seconde Reine 7 Bruxelles (uccle) Bruxelles-Capitale 1180",
    "addr:housenumber":"7",
    "addr:postcode":"1180",
    "addr:street":"Rue De La Seconde Reine",
    "iso:country":"BE",
    "sg:address":"Rue De La Seconde Reine 7",
    "sg:city":"Bruxelles (uccle)",
    "sg:classifiers":[
        {
            "category":"Health Services",
            "subcategory":"Doctor",
            "type":"Services"
        }
    ],
    "sg:phone":"+32 2 345 84 52",
    "sg:postcode":"1180",
    "sg:province":"Bruxelles-Capitale",
    "sg:tags":[
        "medicinephysicians",
        "surgeon"
    ],
    "wof:name":"Hershkowitz Charles",
    "wof:placetype":"venue"
},
  "geometry": {"coordinates":[4.3413238525,50.8133277893],"type":"Point"}
}