{
  "type": "Feature",
  "properties": {
    "addr:full":"Rue Du For\u00cat 319 Florennes Namur 5621",
    "addr:housenumber":"319",
    "addr:postcode":"5621",
    "addr:street":"Rue Du Fore\u0302T",
    "iso:country":"BE",
    "sg:address":"Rue Du For\u00cat 319",
    "sg:city":"Florennes",
    "sg:orig_category":"Gespecialiseerde residenti\u00eble bouw",
    "sg:phone":"+32 71 68 83 46",
    "sg:postcode":"5621",
    "sg:province":"Namur",
    "wof:name":"Alain Everard",
    "wof:placetype":"venue"
},
  "geometry": {"coordinates":[4.561068058,50.2795372009],"type":"Point"}
}