{
  "type": "Feature",
  "properties": {
    "iso:country":"BE",
    "sg:address":"Avenue Louise 287bte 12",
    "sg:city":"Bruxelles",
    "sg:classifiers":[
        {
            "category":"Professional",
            "subcategory":"Business Services",
            "type":"Services"
        }
    ],
    "sg:phone":"+32 2 627 47 47",
    "sg:postcode":"1051",
    "sg:tags":[
        "industry",
        "trade"
    ],
    "wof:name":"Nissho Iwai (benelux) S.a.",
    "wof:placetype":"venue"
},
  "geometry": {"coordinates":[4.3671460152,50.8236999512],"type":"Point"}
}