{
  "type": "Feature",
  "properties": {
    "addr:full":"Rue Des Brasseurs 6 Li\u00e8ge 1 Li\u00e8ge 4000",
    "addr:housenumber":"6;1",
    "addr:postcode":"4000",
    "addr:street":"Rue Des Brasseurs",
    "iso:country":"BE",
    "sg:address":"Rue Des Brasseurs 6",
    "sg:city":"Li\u00e8ge 1",
    "sg:classifiers":[
        {
            "category":"Organizations",
            "subcategory":"Community Association",
            "type":"Services"
        }
    ],
    "sg:phone":"+32 4 221 41 91",
    "sg:postcode":"4000",
    "sg:province":"Li\u00e8ge",
    "sg:tags":[
        "cultural"
    ],
    "wof:name":"Brasseurs (les) Asbl",
    "wof:placetype":"venue"
},
  "geometry": {"coordinates":[5.5805850029,50.6470298767],"type":"Point"}
}