{
  "type": "Feature",
  "properties": {
    "iso:country":"BE",
    "sg:address":"Rue Emile Dury 164a",
    "sg:city":"Waterloo",
    "sg:orig_category":"Electrom\u00e9nager, t\u00e9l\u00e9visions and radios",
    "sg:phone":"+32 2 354 85 81",
    "sg:postcode":"1410",
    "sg:province":"Brabant Wallon",
    "wof:name":"Maison Quoilin",
    "wof:placetype":"venue"
},
  "geometry": {"coordinates":[4.3808078766,50.7089080811],"type":"Point"}
}