{
  "type": "Feature",
  "properties": {
    "iso:country":"BE",
    "sg:address":"Chauss\u00c9e De Bascoup 9",
    "sg:city":"Anderlues",
    "sg:orig_category":"Maisons de repos and r\u00e9sidences",
    "sg:phone":"+32 71 54 86 81",
    "sg:postcode":"6150",
    "sg:province":"Hainaut",
    "wof:name":"Pavillons Pourtois",
    "wof:placetype":"venue"
},
  "geometry": {"coordinates":[4.2837758064,50.4062461853],"type":"Point"}
}