{
  "type": "Feature",
  "properties": {
    "addr:full":"Chemin De La Fontaine 8 Genappe Brabant Wallon 1472",
    "addr:housenumber":"8",
    "addr:postcode":"1472",
    "addr:street":"Chemin De La Fontaine;Wallon",
    "iso:country":"BE",
    "sg:address":"Chemin De La Fontaine 8",
    "sg:city":"Genappe",
    "sg:orig_category":"Eleveurs de bovins",
    "sg:phone":"+32 67 77 21 90",
    "sg:postcode":"1472",
    "sg:province":"Brabant Wallon",
    "wof:name":"Jean-pierre Ferket",
    "wof:placetype":"venue"
},
  "geometry": {"coordinates":[4.412498951,50.6166801453],"type":"Point"}
}