{
  "type": "Feature",
  "properties": {
    "addr:full":"Diksmuidelaan 52 Antwerpen Antwerpen 2600",
    "addr:housenumber":"52",
    "addr:postcode":"2600",
    "addr:street":"Diksmuidelaan",
    "iso:country":"BE",
    "sg:address":"Diksmuidelaan 52",
    "sg:city":"Antwerpen",
    "sg:classifiers":[
        {
            "category":"Communications",
            "subcategory":"Film & Video Production",
            "type":"Services"
        }
    ],
    "sg:phone":"+32 3 321 65 81",
    "sg:postcode":"2600",
    "sg:province":"Antwerpen",
    "sg:tags":[
        "platen",
        "cassette",
        "cd's"
    ],
    "wof:name":"L.p. & C.d. Discount",
    "wof:placetype":"venue"
},
  "geometry": {"coordinates":[4.4174151421,51.1974411011],"type":"Point"}
}