{
  "type": "Feature",
  "properties": {
    "addr:full":"Rue Jules Destr\u00c9e 84 La Louviere Hainaut 7100",
    "addr:housenumber":"84",
    "addr:postcode":"7100",
    "addr:street":"Rue Jules Destre\u0301E",
    "iso:country":"BE",
    "sg:address":"Rue Jules Destr\u00c9e 84",
    "sg:city":"La Louviere",
    "sg:orig_category":"Sportclubs Sportterreinen and installaties behalve sportcentra",
    "sg:phone":"+32 64 21 25 02",
    "sg:postcode":"7100",
    "sg:province":"Hainaut",
    "wof:name":"Employ\u00c9s Comm.la Louvi\u00c8re",
    "wof:placetype":"venue"
},
  "geometry": {"coordinates":[4.1985769272,50.4792633057],"type":"Point"}
}