{
  "type": "Feature",
  "properties": {
    "iso:country":"BE",
    "sg:address":"Linde 81",
    "sg:city":"Londerzeel",
    "sg:orig_category":"Rundveehouders",
    "sg:phone":"+32 52 30 93 24",
    "sg:postcode":"1840",
    "sg:province":"Vlaams-Brabant",
    "wof:name":"Jan Van Campenhout",
    "wof:placetype":"venue"
},
  "geometry": {"coordinates":[4.3011660576,51.0014343262],"type":"Point"}
}