{
  "type": "Feature",
  "properties": {
    "addr:full":"Rue M Lespagne 80 Hasti\u00e8re Namur 5540",
    "addr:housenumber":"80",
    "addr:postcode":"5540",
    "addr:street":"Rue M Lespagne",
    "iso:country":"BE",
    "sg:address":"Rue M Lespagne 80",
    "sg:city":"Hasti\u00e8re",
    "sg:classifiers":[
        {
            "category":"Banks & Credit Unions",
            "subcategory":"Bank",
            "type":"Services"
        }
    ],
    "sg:phone":"+32 82 64 57 80",
    "sg:postcode":"5540",
    "sg:province":"Namur",
    "wof:name":"Aslk-cger Bank",
    "wof:placetype":"venue"
},
  "geometry": {"coordinates":[4.8203291893,50.2135505676],"type":"Point"}
}