{
  "type": "Feature",
  "properties": {
    "iso:country":"BE",
    "sg:address":"Avenue Des Vaillants 36",
    "sg:city":"Bruxelles",
    "sg:orig_category":"Diverse bedrijfsbeheeradviesbureaus",
    "sg:phone":"+32 2 779 38 36",
    "sg:postcode":"1200",
    "sg:province":"Bruxelles-Capitale",
    "wof:name":"K-2",
    "wof:placetype":"venue"
},
  "geometry": {"coordinates":[4.4302492142,50.8439025879],"type":"Point"}
}