{
  "type": "Feature",
  "properties": {
    "addr:full":"Place Des Martyrs 14 Bruxelles Bruxelles-Capitale 1000",
    "addr:housenumber":"14",
    "addr:postcode":"1000",
    "addr:street":"Place Des Martyrs",
    "iso:country":"BE",
    "sg:address":"Place Des Martyrs 14",
    "sg:city":"Bruxelles",
    "sg:classifiers":[
        {
            "category":"Shopping",
            "subcategory":"Books",
            "type":"Retail Goods"
        }
    ],
    "sg:phone":"+32 2 227 34 00",
    "sg:postcode":"1000",
    "sg:province":"Bruxelles-Capitale",
    "sg:tags":[
        "bookseller"
    ],
    "wof:name":"Quartiers Latins (librairies) Asbl",
    "wof:placetype":"venue"
},
  "geometry": {"coordinates":[4.3565897942,50.8515396118],"type":"Point"}
}