{
  "type": "Feature",
  "properties": {
    "addr:full":"Rue Bayemont 30b76 Charleroi Hainaut 6000",
    "addr:housenumber":"30b76",
    "addr:postcode":"6000",
    "addr:street":"Rue Bayemont;Hainaut",
    "iso:country":"BE",
    "sg:address":"Rue Bayemont 30b76",
    "sg:city":"Charleroi",
    "sg:classifiers":[
        {
            "category":"Cafe",
            "type":"Food & Drink"
        }
    ],
    "sg:phone":"+32 71 31 88 35",
    "sg:postcode":"6000",
    "sg:province":"Hainaut",
    "sg:tags":[
        "caf\u00e9s"
    ],
    "wof:name":"Elisabeth Hubert",
    "wof:placetype":"venue"
},
  "geometry": {"coordinates":[4.4469227791,50.4220657349],"type":"Point"}
}