{
  "type": "Feature",
  "properties": {
    "addr:full":"Gentsesteenweg 383 Erpe-mere (erondegem) Oost-Vlaanderen 9420",
    "addr:housenumber":"383",
    "addr:postcode":"9420",
    "addr:street":"Gentsesteenweg",
    "iso:country":"BE",
    "sg:address":"Gentsesteenweg 383",
    "sg:city":"Erpe-mere (erondegem)",
    "sg:classifiers":[
        {
            "category":"Retail",
            "subcategory":"Auto Repair",
            "type":"Services"
        }
    ],
    "sg:phone":"+32 53 80 41 91",
    "sg:postcode":"9420",
    "sg:province":"Oost-Vlaanderen",
    "sg:tags":[
        "automobile-body"
    ],
    "wof:name":"Carrosserie Dirk Bvba",
    "wof:placetype":"venue"
},
  "geometry": {"coordinates":[3.9576630592,50.9463539124],"type":"Point"}
}