{
  "type": "Feature",
  "properties": {
    "iso:country":"BE",
    "sg:address":"Antwerpsesteenweg 114",
    "sg:city":"Leopoldsburg",
    "sg:orig_category":"Artsen and specialisten",
    "sg:phone":"+32 11 34 53 84",
    "sg:postcode":"3970",
    "sg:province":"Limburg",
    "wof:name":"Miriame L. Van Baelen",
    "wof:placetype":"venue"
},
  "geometry": {"coordinates":[5.2525658607,51.1266937256],"type":"Point"}
}