{
  "type": "Feature",
  "properties": {
    "addr:full":"Hermisweg 4 Opglabbeek Limburg 3660",
    "addr:housenumber":"4",
    "addr:postcode":"3660",
    "addr:street":"Hermisweg",
    "iso:country":"BE",
    "sg:address":"Hermisweg 4",
    "sg:city":"Opglabbeek",
    "sg:orig_category":"Tijdelijke werkgelegenheid and uitzendkantoren",
    "sg:phone":"+32 89 85 83 71",
    "sg:postcode":"3660",
    "sg:province":"Limburg",
    "wof:name":"Asb Interim",
    "wof:placetype":"venue"
},
  "geometry": {"coordinates":[5.5801901817,51.0415496826],"type":"Point"}
}