{
  "type": "Feature",
  "properties": {
    "addr:full":"Rue De La Pr\u00c9fecture 25 Li\u00c8ge Li\u00e8ge 4000",
    "addr:housenumber":"25",
    "addr:postcode":"4000",
    "addr:street":"Rue De La Pre\u0301Fecture",
    "iso:country":"BE",
    "sg:address":"Rue De La Pr\u00c9fecture 25",
    "sg:city":"Li\u00c8ge",
    "sg:classifiers":[
        {
            "category":"Personal",
            "subcategory":"Beauty Salon",
            "type":"Services"
        }
    ],
    "sg:phone":"+32 4 253 10 21",
    "sg:postcode":"4000",
    "sg:province":"Li\u00e8ge",
    "sg:tags":[
        "de",
        "coiffure"
    ],
    "wof:name":"Michel Thielen",
    "wof:placetype":"venue"
},
  "geometry": {"coordinates":[5.5691199303,50.610370636],"type":"Point"}
}