{
  "type": "Feature",
  "properties": {
    "addr:full":"Boondaalse Steenweg 94 Elsene/ixelles Bruxelles-Capitale 1050",
    "addr:housenumber":"94",
    "addr:postcode":"1050",
    "addr:street":"Boondaalse Steenweg",
    "iso:country":"BE",
    "sg:address":"Boondaalse Steenweg 94",
    "sg:city":"Elsene/ixelles",
    "sg:orig_category":"Rusthuizen and serviceflats",
    "sg:phone":"+32 2 641 41 00",
    "sg:postcode":"1050",
    "sg:province":"Bruxelles-Capitale",
    "wof:name":"R\u00c9sidence Jean Van Aa",
    "wof:placetype":"venue"
},
  "geometry": {"coordinates":[4.377158165,50.8248443604],"type":"Point"}
}