{
  "type": "Feature",
  "properties": {
    "addr:full":"Hondschotestraat 156 Wevelgem West-Vlaanderen 8560",
    "addr:housenumber":"156",
    "addr:postcode":"8560",
    "addr:street":"Hondschotestraat",
    "iso:country":"BE",
    "sg:address":"Hondschotestraat 156",
    "sg:city":"Wevelgem",
    "sg:orig_category":"Rev\u00eatements pour sols and murs. Peinture",
    "sg:phone":"+32 56 42 31 10",
    "sg:postcode":"8560",
    "sg:province":"West-Vlaanderen",
    "wof:name":"Yserbyt Marc",
    "wof:placetype":"venue"
},
  "geometry": {"coordinates":[3.1874320507,50.8444328308],"type":"Point"}
}