{
  "type": "Feature",
  "properties": {
    "iso:country":"BE",
    "sg:address":"Bd Paul-henri Spaak 6",
    "sg:city":"Leuze-en-hainaut",
    "sg:classifiers":[
        {
            "category":"Autos & Motor Vehicles",
            "subcategory":"Automobile Sales",
            "type":"Retail Goods"
        }
    ],
    "sg:phone":"+32 69 66 12 12",
    "sg:postcode":"7900",
    "sg:province":"Hainaut",
    "sg:tags":[
        "equipment",
        "motor-cars",
        "transport"
    ],
    "wof:name":"Ets D'haene Sprl",
    "wof:placetype":"venue"
},
  "geometry": {"coordinates":[3.6160159111,50.6050567627],"type":"Point"}
}