{
  "type": "Feature",
  "properties": {
    "addr:full":"\u00b4t Ranke Riet 3 Kortrijk West-Vlaanderen 8501",
    "addr:housenumber":"3",
    "addr:postcode":"8501",
    "addr:street":"Riet",
    "iso:country":"BE",
    "sg:address":"\u00b4t Ranke Riet 3",
    "sg:city":"Kortrijk",
    "sg:orig_category":"Architecten",
    "sg:phone":"+32 56 35 64 97",
    "sg:postcode":"8501",
    "sg:province":"West-Vlaanderen",
    "wof:name":"Tom Vanhee",
    "wof:placetype":"venue"
},
  "geometry": {"coordinates":[3.2515890598,50.8465843201],"type":"Point"}
}