{
  "type": "Feature",
  "properties": {
    "iso:country":"BE",
    "sg:address":"Rue De Tournai 6",
    "sg:city":"Estaimpuis",
    "sg:orig_category":"Eleveurs de bovins",
    "sg:phone":"+32 69 55 63 64",
    "sg:postcode":"7730",
    "sg:province":"Hainaut",
    "wof:name":"Freddy Ducatillon",
    "wof:placetype":"venue"
},
  "geometry": {"coordinates":[3.2964580059,50.6779899597],"type":"Point"}
}