{
  "type": "Feature",
  "properties": {
    "iso:country":"BE",
    "sg:address":"Brugstraat 8",
    "sg:city":"Mechelen (muizen)",
    "sg:classifiers":[
        {
            "category":"Professional",
            "subcategory":"Accounting & Tax Preparation",
            "type":"Services"
        }
    ],
    "sg:phone":"+32 15 41 50 54",
    "sg:postcode":"2812",
    "sg:province":"Antwerpen",
    "sg:tags":[
        "bookkeeper"
    ],
    "wof:name":"Lauwens H",
    "wof:placetype":"venue"
},
  "geometry": {"coordinates":[4.5170779228,51.0101280212],"type":"Point"}
}