{
  "type": "Feature",
  "properties": {
    "addr:full":"Atheneumstraat 31 Leopoldsburg Limburg 3970",
    "addr:housenumber":"31",
    "addr:postcode":"3970",
    "addr:street":"Atheneumstraat",
    "iso:country":"BE",
    "sg:address":"Atheneumstraat 31",
    "sg:city":"Leopoldsburg",
    "sg:classifiers":[
        {
            "category":"Retail",
            "subcategory":"Auto Rental",
            "type":"Services"
        }
    ],
    "sg:phone":"+32 11 34 21 94",
    "sg:postcode":"3970",
    "sg:province":"Limburg",
    "sg:tags":[
        "chauffeur",
        "automobile",
        "driven",
        "-",
        "car"
    ],
    "wof:name":"Jagam Bvba",
    "wof:placetype":"venue"
},
  "geometry": {"coordinates":[5.2496747971,51.1216316223],"type":"Point"}
}