{
  "type": "Feature",
  "properties": {
    "iso:country":"BE",
    "sg:address":"Steenstraat 57",
    "sg:city":"Erpe-mere",
    "sg:orig_category":"Woningbouw",
    "sg:phone":"+32 53 83 15 10",
    "sg:postcode":"9420",
    "sg:province":"Oost-Vlaanderen",
    "wof:name":"Hoffelinck Construction",
    "wof:placetype":"venue"
},
  "geometry": {"coordinates":[3.9696528912,50.92004776],"type":"Point"}
}