{
  "type": "Feature",
  "properties": {
    "addr:full":"Edingsesteenweg 292 Ninove Oost-Vlaanderen 9400",
    "addr:housenumber":"292",
    "addr:postcode":"9400",
    "addr:street":"Edingsesteenweg",
    "iso:country":"BE",
    "sg:address":"Edingsesteenweg 292",
    "sg:city":"Ninove",
    "sg:classifiers":[
        {
            "category":"Utilities",
            "subcategory":"Refuse",
            "type":"Services"
        }
    ],
    "sg:phone":"+32 54 32 30 39",
    "sg:postcode":"9400",
    "sg:province":"Oost-Vlaanderen",
    "sg:tags":[
        "removal"
    ],
    "wof:name":"C.d.r. Bvba",
    "wof:placetype":"venue"
},
  "geometry": {"coordinates":[4.0232839584,50.8047676086],"type":"Point"}
}