{
  "type": "Feature",
  "properties": {
    "addr:full":"Boterlaarbaan 522 Antwerpen Antwerpen 2100",
    "addr:housenumber":"522",
    "addr:postcode":"2100",
    "iso:country":"BE",
    "sg:address":"Boterlaarbaan 522",
    "sg:city":"Antwerpen",
    "sg:orig_category":"Ramassage and traitement des d\u00e9chets m\u00e9nagers. D\u00e9chets and d\u00e9bris Gr",
    "sg:phone":"+32 3 322 19 80",
    "sg:postcode":"2100",
    "sg:province":"Antwerpen",
    "wof:name":"Van Looveren",
    "wof:placetype":"venue"
},
  "geometry": {"coordinates":[4.4586100578,51.2203941345],"type":"Point"}
}