{
  "type": "Feature",
  "properties": {
    "iso:country":"BE",
    "sg:address":"Rozenberg 2",
    "sg:city":"Mol",
    "sg:classifiers":[
        {
            "category":"Education",
            "subcategory":"School",
            "type":"Public Place"
        }
    ],
    "sg:phone":"+32 14 31 33 43",
    "sg:postcode":"2400",
    "sg:province":"Antwerpen",
    "sg:tags":[
        "secondary"
    ],
    "wof:name":"Rozenberg S.o.",
    "wof:placetype":"venue"
},
  "geometry": {"coordinates":[5.1209959984,51.1885528564],"type":"Point"}
}