{
  "type": "Feature",
  "properties": {
    "addr:full":"Rue Du Croissant 9 Sint-gillis/saint-gilles Bruxelles-Capitale 1060",
    "addr:housenumber":"9",
    "addr:postcode":"1060",
    "addr:street":"Rue Du Croissant",
    "iso:country":"BE",
    "sg:address":"Rue Du Croissant 9",
    "sg:city":"Sint-gillis/saint-gilles",
    "sg:orig_category":"Artistes ind\u00e9pendants",
    "sg:phone":"+32 2 534 00 25",
    "sg:postcode":"1060",
    "sg:province":"Bruxelles-Capitale",
    "wof:name":"Alain Laurent",
    "wof:placetype":"venue"
},
  "geometry": {"coordinates":[4.3321919441,50.8290939331],"type":"Point"}
}