{
  "type": "Feature",
  "properties": {
    "addr:full":"Kontichstraat 99 Edegem Antwerpen 2650",
    "addr:housenumber":"99",
    "addr:postcode":"2650",
    "addr:street":"Kontichstraat",
    "iso:country":"BE",
    "sg:address":"Kontichstraat 99",
    "sg:city":"Edegem",
    "sg:orig_category":"Artsen and specialisten",
    "sg:phone":"+32 3 457 18 75",
    "sg:postcode":"2650",
    "sg:province":"Antwerpen",
    "wof:name":"E. Goedtkindt",
    "wof:placetype":"venue"
},
  "geometry": {"coordinates":[4.4464840889,51.1506576538],"type":"Point"}
}