{
  "type": "Feature",
  "properties": {
    "addr:full":". Malmedy Li\u00e8ge 4960",
    "addr:postcode":"4960",
    "iso:country":"BE",
    "sg:address":".",
    "sg:city":"Malmedy",
    "sg:orig_category":"Sportterreinen and installaties behalve sportcentra",
    "sg:phone":"+32 80 33 75 35",
    "sg:postcode":"4960",
    "sg:province":"Li\u00e8ge",
    "wof:name":"Piste Houyres",
    "wof:placetype":"venue"
},
  "geometry": {"coordinates":[6.0306248665,50.4252433777],"type":"Point"}
}