{
  "type": "Feature",
  "properties": {
    "addr:full":"Zoutelaan 49 Knokke-heist (knokke) West-Vlaanderen 8300",
    "addr:housenumber":"49",
    "addr:postcode":"8300",
    "addr:street":"Zoutelaan",
    "iso:country":"BE",
    "sg:address":"Zoutelaan 49",
    "sg:city":"Knokke-heist (knokke)",
    "sg:classifiers":[
        {
            "category":"Shopping",
            "subcategory":"Antiques",
            "type":"Retail Goods"
        }
    ],
    "sg:phone":"+32 50 61 08 43",
    "sg:postcode":"8300",
    "sg:province":"West-Vlaanderen",
    "wof:name":"Smitz J",
    "wof:placetype":"venue"
},
  "geometry": {"coordinates":[3.287694931,51.3467254639],"type":"Point"}
}