{
  "type": "Feature",
  "properties": {
    "addr:full":"Avenue Georges Eekhoud 11 Brussel/bruxelles Bruxelles-Capitale 1030",
    "addr:housenumber":"11",
    "addr:postcode":"1030",
    "addr:street":"Avenue Georges Eekhoud;/",
    "iso:country":"BE",
    "sg:address":"Avenue Georges Eekhoud 11",
    "sg:city":"Brussel/bruxelles",
    "sg:orig_category":"Sportclubs",
    "sg:phone":"+32 2 241 04 65",
    "sg:postcode":"1030",
    "sg:province":"Bruxelles-Capitale",
    "wof:name":"Koninklijke Belgisch Boksbond",
    "wof:placetype":"venue"
},
  "geometry": {"coordinates":[4.3871860504,50.8757820129],"type":"Point"}
}