{
  "type": "Feature",
  "properties": {
    "iso:country":"BE",
    "sg:address":"Diesterstraat 23 Box 1",
    "sg:city":"Sint-truiden",
    "sg:classifiers":[
        {
            "category":"Professional",
            "subcategory":"Detective & Security Services",
            "type":"Services"
        }
    ],
    "sg:phone":"+32 476 45 02 33",
    "sg:postcode":"3800",
    "sg:province":"Limburg",
    "sg:tags":[
        "installation",
        "alarm",
        "-",
        "system"
    ],
    "wof:name":"Home Security Systems Bvba",
    "wof:placetype":"venue"
},
  "geometry": {"coordinates":[5.1855249405,50.8174476624],"type":"Point"}
}