{
  "type": "Feature",
  "properties": {
    "iso:country":"BE",
    "sg:address":"Van Iseghemlaan 80",
    "sg:city":"Oostende",
    "sg:orig_category":"Biens d'occasion",
    "sg:phone":"+32 59 80 48 81",
    "sg:postcode":"8400",
    "sg:province":"West-Vlaanderen",
    "wof:name":"Pompoen",
    "wof:placetype":"venue"
},
  "geometry": {"coordinates":[2.9123210907,51.2305297852],"type":"Point"}
}