{
  "type": "Feature",
  "properties": {
    "iso:country":"BE",
    "sg:address":"Horst 8",
    "sg:city":"Merksplas",
    "sg:orig_category":"Groententeelt",
    "sg:phone":"+32 14 63 26 64",
    "sg:postcode":"2330",
    "sg:province":"Antwerpen",
    "wof:name":"Nuyens Wim & Ben",
    "wof:placetype":"venue"
},
  "geometry": {"coordinates":[4.8936171532,51.3616485596],"type":"Point"}
}