{
  "type": "Feature",
  "properties": {
    "addr:full":"Rue Bajart Binam\u00e9 43 Profondeville (bois-de-villers) Namur 5170",
    "addr:housenumber":"43",
    "addr:postcode":"5170",
    "addr:street":"Rue Bajart Biname\u0301",
    "iso:country":"BE",
    "sg:address":"Rue Bajart Binam\u00e9 43",
    "sg:city":"Profondeville (bois-de-villers)",
    "sg:classifiers":[
        {
            "category":"Building & Trades",
            "subcategory":"Landscaping Services",
            "type":"Services"
        }
    ],
    "sg:phone":"+32 475 89 50 40",
    "sg:postcode":"5170",
    "sg:province":"Namur",
    "sg:tags":[
        "gardening",
        "garden",
        "maintenance"
    ],
    "wof:name":"Magermans R",
    "wof:placetype":"venue"
},
  "geometry": {"coordinates":[4.8311457634,50.3947677612],"type":"Point"}
}