{
  "type": "Feature",
  "properties": {
    "addr:full":"1000 Bruxelles Bruxelles-Capitale 1000",
    "addr:postcode":"1000;1000",
    "iso:country":"BE",
    "sg:address":"1000",
    "sg:city":"Bruxelles",
    "sg:orig_category":"Eclairage et \u00e9quipements du foyer",
    "sg:phone":"+32 475 63 98 22",
    "sg:postcode":"1000",
    "sg:province":"Bruxelles-Capitale",
    "wof:name":"Denis",
    "wof:placetype":"venue"
},
  "geometry": {"coordinates":[4.3513898849,50.8584594727],"type":"Point"}
}