{
  "type": "Feature",
  "properties": {
    "iso:country":"BE",
    "sg:address":"Cassiersstraat 19",
    "sg:city":"Antwerpen",
    "sg:classifiers":[
        {
            "category":"Marine",
            "type":"Transportation"
        }
    ],
    "sg:phone":"+32 3 221 22 70",
    "sg:postcode":"2060",
    "sg:province":"Antwerpen",
    "sg:tags":[
        "chartering",
        "ship"
    ],
    "wof:name":"Gandamar Nv",
    "wof:placetype":"venue"
},
  "geometry": {"coordinates":[4.4158968925,51.2267417908],"type":"Point"}
}