{
  "type": "Feature",
  "properties": {
    "addr:full":"Wijngaardveld 1 Aalst Oost-Vlaanderen 9300",
    "addr:housenumber":"1",
    "addr:postcode":"9300",
    "addr:street":"Wijngaardveld",
    "iso:country":"BE",
    "sg:address":"Wijngaardveld 1",
    "sg:city":"Aalst",
    "sg:classifiers":[
        {
            "category":"Wholesale",
            "subcategory":"Machinery & Supplies",
            "type":"Manufacturing & Wholesale Goods"
        }
    ],
    "sg:phone":"+32 53 72 51 11",
    "sg:postcode":"9300",
    "sg:province":"Oost-Vlaanderen",
    "sg:tags":[
        "water",
        "pump",
        "-"
    ],
    "wof:name":"Honda Motor Europe (north) Gmbh",
    "wof:placetype":"venue"
},
  "geometry": {"coordinates":[4.0463891029,50.9606513977],"type":"Point"}
}