{
  "type": "Feature",
  "properties": {
    "addr:full":"Rue Combatt. & D\u00c9port\u00c9s 26 Thuin Hainaut 6536",
    "addr:housenumber":"26",
    "addr:postcode":"6536",
    "addr:street":"Rue Combatt. & De\u0301Porte\u0301S",
    "iso:country":"BE",
    "sg:address":"Rue Combatt. & D\u00c9port\u00c9s 26",
    "sg:city":"Thuin",
    "sg:orig_category":"Divers amusement Huishoudapparaten, televisies and radio's Verhuur televisie- and audiovisuele appar",
    "sg:phone":"+32 71 53 33 70",
    "sg:postcode":"6536",
    "sg:province":"Hainaut",
    "wof:name":"Cellophan Ev\u00c9nement",
    "wof:placetype":"venue"
},
  "geometry": {"coordinates":[4.3320260048,50.2948646545],"type":"Point"}
}