{
  "type": "Feature",
  "properties": {
    "addr:full":"Nieuwpoortsesteenweg 250-254 Oostende West-Vlaanderen 8400",
    "addr:housenumber":"250-254",
    "addr:postcode":"8400",
    "addr:street":"Nieuwpoortsesteenweg",
    "iso:country":"BE",
    "sg:address":"Nieuwpoortsesteenweg 250-254",
    "sg:city":"Oostende",
    "sg:orig_category":"Meubles D\u00e9taillants, Am\u00e9nagement de B\u00e2timents et de Cuisines",
    "sg:phone":"+32 59 50 70 77",
    "sg:postcode":"8400",
    "sg:province":"West-Vlaanderen",
    "wof:name":"Aquatrend",
    "wof:placetype":"venue"
},
  "geometry": {"coordinates":[2.891315937,51.2168045044],"type":"Point"}
}