{
  "type": "Feature",
  "properties": {
    "iso:country":"BE",
    "sg:address":"Molsekiezel 227",
    "sg:city":"Lommel",
    "sg:classifiers":[
        {
            "category":"Professional",
            "subcategory":"Testing Lab",
            "type":"Services"
        }
    ],
    "sg:phone":"+32 11 54 04 61",
    "sg:postcode":"3920",
    "sg:province":"Limburg",
    "sg:tags":[
        "chemist"
    ],
    "wof:name":"Sevens H",
    "wof:placetype":"venue"
},
  "geometry": {"coordinates":[5.2874798775,51.2329177856],"type":"Point"}
}