{
  "type": "Feature",
  "properties": {
    "addr:full":"Gemeenteplein 7 Meise Vlaams-Brabant 1861",
    "addr:housenumber":"7",
    "addr:postcode":"1861",
    "addr:street":"Gemeenteplein",
    "iso:country":"BE",
    "sg:address":"Gemeenteplein 7",
    "sg:city":"Meise",
    "sg:orig_category":"Assurances. Banques and organismes de cr\u00e9dit",
    "sg:phone":"+32 2 272 06 10",
    "sg:postcode":"1861",
    "sg:province":"Vlaams-Brabant",
    "wof:name":"Kbc",
    "wof:placetype":"venue"
},
  "geometry": {"coordinates":[4.3088359833,50.9508323669],"type":"Point"}
}