{
  "type": "Feature",
  "properties": {
    "addr:full":"Statiestraat 155 Zwijndrecht Antwerpen 2070",
    "addr:housenumber":"155",
    "addr:postcode":"2070",
    "addr:street":"Statiestraat",
    "iso:country":"BE",
    "sg:address":"Statiestraat 155",
    "sg:city":"Zwijndrecht",
    "sg:orig_category":"Blanchisseries and teintureries",
    "sg:phone":"+32 3 253 01 67",
    "sg:postcode":"2070",
    "sg:province":"Antwerpen",
    "wof:name":"Droogkuis Gaverland",
    "wof:placetype":"venue"
},
  "geometry": {"coordinates":[4.3297991753,51.2145843506],"type":"Point"}
}