{
  "type": "Feature",
  "properties": {
    "iso:country":"BE",
    "sg:address":"Place De Lille 7",
    "sg:city":"Tournai",
    "sg:classifiers":[
        {
            "category":"Restaurant",
            "type":"Food & Drink"
        }
    ],
    "sg:phone":"+32 69 84 18 88",
    "sg:postcode":"7500",
    "sg:province":"Hainaut",
    "wof:name":"La Grotte Azteque",
    "wof:placetype":"venue"
},
  "geometry": {"coordinates":[3.3808419704,50.6065711975],"type":"Point"}
}