{
  "type": "Feature",
  "properties": {
    "iso:country":"BE",
    "sg:address":"Alsembergse Steenweg 342",
    "sg:city":"Vorst/forest",
    "sg:orig_category":"Diverse zakelijke dienstverlening Marktonderzoekbureaus Public-relationsbureaus Reclamebureaus",
    "sg:phone":"+32 2 346 59 49",
    "sg:postcode":"1190",
    "sg:province":"Bruxelles-Capitale",
    "wof:name":"V.o. Communication",
    "wof:placetype":"venue"
},
  "geometry": {"coordinates":[4.3401889801,50.8161506653],"type":"Point"}
}