{
  "type": "Feature",
  "properties": {
    "addr:full":"Chauss\u00c9e De Maubeuge 358 Mons Hainaut 7033",
    "addr:housenumber":"358",
    "addr:postcode":"7033",
    "addr:street":"Chausse\u0301E De Maubeuge;Hainaut",
    "iso:country":"BE",
    "sg:address":"Chauss\u00c9e De Maubeuge 358",
    "sg:city":"Mons",
    "sg:orig_category":"Benzinestations and brandstoffen",
    "sg:phone":"+32 65 35 10 32",
    "sg:postcode":"7033",
    "sg:province":"Hainaut",
    "wof:name":"Texaco",
    "wof:placetype":"venue"
},
  "geometry": {"coordinates":[3.9472529888,50.4337120056],"type":"Point"}
}