{
  "type": "Feature",
  "properties": {
    "addr:full":"Hoogstraat 32 Antwerpen Antwerpen 2000",
    "addr:housenumber":"32",
    "addr:postcode":"2000",
    "addr:street":"Hoogstraat",
    "iso:country":"BE",
    "sg:address":"Hoogstraat 32",
    "sg:city":"Antwerpen",
    "sg:classifiers":[
        {
            "category":"Cafe",
            "type":"Food & Drink"
        }
    ],
    "sg:phone":"+32 3 226 99 34",
    "sg:postcode":"2000",
    "sg:province":"Antwerpen",
    "sg:tags":[
        "snack-bars"
    ],
    "wof:name":"Gregory's",
    "wof:placetype":"venue"
},
  "geometry": {"coordinates":[4.3983020782,51.2199211121],"type":"Point"}
}