{
  "type": "Feature",
  "properties": {
    "addr:full":"Legeweg 19 Beernem West-Vlaanderen 8730",
    "addr:housenumber":"19",
    "addr:postcode":"8730",
    "addr:street":"Legeweg",
    "iso:country":"BE",
    "sg:address":"Legeweg 19",
    "sg:city":"Beernem",
    "sg:classifiers":[
        {
            "category":"Food & Beverages",
            "subcategory":"Meat & Fish",
            "type":"Retail Goods"
        }
    ],
    "sg:phone":"+32 50 78 07 50",
    "sg:postcode":"8730",
    "sg:province":"West-Vlaanderen",
    "sg:tags":[
        "-",
        "livestock"
    ],
    "wof:name":"Van Belleghem P",
    "wof:placetype":"venue"
},
  "geometry": {"coordinates":[3.3168749809,51.1446151733],"type":"Point"}
}