{
  "type": "Feature",
  "properties": {
    "addr:full":"Neerveldstraat 179 Opwijk Vlaams-Brabant 1745",
    "addr:housenumber":"179",
    "addr:postcode":"1745",
    "addr:street":"Neerveldstraat",
    "iso:country":"BE",
    "sg:address":"Neerveldstraat 179",
    "sg:city":"Opwijk",
    "sg:orig_category":"Installatie van houten of kunststof schrijnwerk",
    "sg:phone":"+32 52 35 23 25",
    "sg:postcode":"1745",
    "sg:province":"Vlaams-Brabant",
    "wof:name":"Filip Verbelen",
    "wof:placetype":"venue"
},
  "geometry": {"coordinates":[4.1805348396,50.981338501],"type":"Point"}
}