{
  "type": "Feature",
  "properties": {
    "addr:full":"Ringdreef 12 Wuustwezel Antwerpen 2990",
    "addr:housenumber":"12",
    "addr:postcode":"2990",
    "addr:street":"Ringdreef",
    "iso:country":"BE",
    "sg:address":"Ringdreef 12",
    "sg:city":"Wuustwezel",
    "sg:classifiers":[
        {
            "category":"Real Estate",
            "subcategory":"Architect",
            "type":"Services"
        }
    ],
    "sg:phone":"+32 3 663 14 36",
    "sg:postcode":"2990",
    "sg:province":"Antwerpen",
    "wof:name":"Van Houdt G",
    "wof:placetype":"venue"
},
  "geometry": {"coordinates":[4.5387711525,51.3493423462],"type":"Point"}
}