{
  "type": "Feature",
  "properties": {
    "iso:country":"BE",
    "sg:address":"Rue De La Commune 139",
    "sg:city":"Seraing (jemeppe-sur-meuse)",
    "sg:classifiers":[
        {
            "category":"Manufacturing",
            "subcategory":"Metals",
            "type":"Manufacturing & Wholesale Goods"
        }
    ],
    "sg:phone":"+32 4 233 80 65",
    "sg:postcode":"4101",
    "sg:province":"Li\u00e8ge",
    "sg:tags":[
        "ornamental",
        "work",
        "-"
    ],
    "wof:name":"Scibona Decor Sprl",
    "wof:placetype":"venue"
},
  "geometry": {"coordinates":[5.5009598732,50.6120986938],"type":"Point"}
}