{
  "type": "Feature",
  "properties": {
    "addr:full":"Avenue Ren\u00e9 Lange 62 Theux (polleur) Li\u00e8ge 4910",
    "addr:housenumber":"62",
    "addr:postcode":"4910",
    "addr:street":"Avenue Rene\u0301 Lange",
    "iso:country":"BE",
    "sg:address":"Avenue Ren\u00e9 Lange 62",
    "sg:city":"Theux (polleur)",
    "sg:classifiers":[
        {
            "category":"Structure",
            "subcategory":"Office Building",
            "type":"Public Place"
        }
    ],
    "sg:phone":"+32 87 23 21 07",
    "sg:postcode":"4910",
    "sg:province":"Li\u00e8ge",
    "sg:tags":[
        "roofing",
        "slate"
    ],
    "wof:name":"Grandry A",
    "wof:placetype":"venue"
},
  "geometry": {"coordinates":[5.9028310776,50.5613136292],"type":"Point"}
}