{
  "type": "Feature",
  "properties": {
    "addr:full":"Avenue De Limburg Stirum 98 Wemmel Vlaams-Brabant 1780",
    "addr:housenumber":"98",
    "addr:postcode":"1780",
    "addr:street":"Avenue De Limburg Stirum;Vlaams-Brabant",
    "iso:country":"BE",
    "sg:address":"Avenue De Limburg Stirum 98",
    "sg:city":"Wemmel",
    "sg:classifiers":[
        {
            "category":"Health Services",
            "subcategory":"Health Practitioner",
            "type":"Services"
        }
    ],
    "sg:phone":"+32 2 460 74 13",
    "sg:postcode":"1780",
    "sg:province":"Vlaams-Brabant",
    "sg:tags":[
        "physiotherapist"
    ],
    "wof:name":"Van Den Houte Anne",
    "wof:placetype":"venue"
},
  "geometry": {"coordinates":[4.3123049736,50.9038696289],"type":"Point"}
}