{
  "type": "Feature",
  "properties": {
    "addr:full":"Prosper De Vochtlaan 20 Kontich Antwerpen 2550",
    "addr:housenumber":"20",
    "addr:postcode":"2550",
    "addr:street":"Prosper De Vochtlaan",
    "iso:country":"BE",
    "sg:address":"Prosper De Vochtlaan 20",
    "sg:city":"Kontich",
    "sg:orig_category":"Elektrische installaties voor woningen",
    "sg:phone":"+32 15 31 22 55",
    "sg:postcode":"2550",
    "sg:province":"Antwerpen",
    "wof:name":"Roger Van Cleynenbreugel",
    "wof:placetype":"venue"
},
  "geometry": {"coordinates":[4.4542379379,51.1023139954],"type":"Point"}
}