{
  "type": "Feature",
  "properties": {
    "iso:country":"BE",
    "sg:address":"Rue De La Justice 70",
    "sg:city":"Ch\u00c2telet",
    "sg:orig_category":"Sportclubs",
    "sg:phone":"+32 71 38 33 77",
    "sg:postcode":"6200",
    "sg:province":"Hainaut",
    "wof:name":"Cyclo-club Bouffioulx",
    "wof:placetype":"venue"
},
  "geometry": {"coordinates":[4.5364861488,50.3974876404],"type":"Point"}
}