{
  "type": "Feature",
  "properties": {
    "iso:country":"BE",
    "sg:address":"Landbouwstraat 56",
    "sg:city":"Zaventem",
    "sg:orig_category":"Location de voitures",
    "sg:phone":"+32 2 722 58 01",
    "sg:postcode":"1930",
    "sg:province":"Vlaams-Brabant",
    "wof:name":"Avis",
    "wof:placetype":"venue"
},
  "geometry": {"coordinates":[4.4760842323,50.8853378296],"type":"Point"}
}