{
  "type": "Feature",
  "properties": {
    "addr:full":"Place Georges Ista 25 Li\u00e8ge 1 (grivegn\u00e9e) Li\u00e8ge 4030",
    "addr:housenumber":"25;1",
    "addr:postcode":"4030",
    "addr:street":"Place Georges Ista",
    "iso:country":"BE",
    "sg:address":"Place Georges Ista 25",
    "sg:city":"Li\u00e8ge 1 (grivegn\u00e9e)",
    "sg:classifiers":[
        {
            "category":"Utilities",
            "subcategory":"Cable",
            "type":"Services"
        }
    ],
    "sg:phone":"+32 4 342 56 18",
    "sg:postcode":"4030",
    "sg:province":"Li\u00e8ge",
    "sg:tags":[
        "rope",
        "twine"
    ],
    "wof:name":"Bauwens-gheur (corderie)",
    "wof:placetype":"venue"
},
  "geometry": {"coordinates":[5.5933670998,50.6225852966],"type":"Point"}
}