{
  "type": "Feature",
  "properties": {
    "iso:country":"BE",
    "sg:address":"Doggenhoutstraat 63",
    "sg:city":"Ranst",
    "sg:orig_category":"Installation \u00e9lectrique r\u00e9sidentielle. Plomberie, chauffage and installations sanitaires",
    "sg:phone":"+32 3 485 84 74",
    "sg:postcode":"2520",
    "sg:province":"Antwerpen",
    "wof:name":"Rasalec",
    "wof:placetype":"venue"
},
  "geometry": {"coordinates":[4.5636019707,51.1878013611],"type":"Point"}
}