{
  "type": "Feature",
  "properties": {
    "addr:full":"Place De Beloeil 24 Beloeil Hainaut 7970",
    "addr:housenumber":"24",
    "addr:postcode":"7970",
    "addr:street":"Place De Beloeil",
    "iso:country":"BE",
    "sg:address":"Place De Beloeil 24",
    "sg:city":"Beloeil",
    "sg:classifiers":[
        {
            "category":"Professional",
            "subcategory":"Art Services",
            "type":"Services"
        }
    ],
    "sg:phone":"+32 69 68 96 79",
    "sg:postcode":"7970",
    "sg:province":"Hainaut",
    "sg:tags":[
        "photographer",
        "-",
        "portrait"
    ],
    "wof:name":"Lefebvre",
    "wof:placetype":"venue"
},
  "geometry": {"coordinates":[3.7354249954,50.5487861633],"type":"Point"}
}