{
  "type": "Feature",
  "properties": {
    "addr:full":"Norbert Neeckxlaan 35 Lommel Limburg 3920",
    "addr:housenumber":"35",
    "addr:postcode":"3920",
    "addr:street":"Neeckxlaan",
    "iso:country":"BE",
    "sg:address":"Norbert Neeckxlaan 35",
    "sg:city":"Lommel",
    "sg:classifiers":[
        {
            "category":"Professional",
            "subcategory":"Management & Consulting",
            "type":"Services"
        }
    ],
    "sg:phone":"+32 11 55 14 70",
    "sg:postcode":"3920",
    "sg:province":"Limburg",
    "sg:tags":[
        "consultant"
    ],
    "wof:name":"Alexander International Executive Search",
    "wof:placetype":"venue"
},
  "geometry": {"coordinates":[5.3199968338,51.2274436951],"type":"Point"}
}