{
  "type": "Feature",
  "properties": {
    "iso:country":"BE",
    "sg:address":"Maarschalk Haiglaan 120",
    "sg:city":"Ieper",
    "sg:classifiers":[
        {
            "category":"Retail",
            "subcategory":"Auto Repair",
            "type":"Services"
        }
    ],
    "sg:phone":"+32 57 21 60 40",
    "sg:postcode":"8900",
    "sg:province":"West-Vlaanderen",
    "sg:tags":[
        "truck-body"
    ],
    "wof:name":"Ypcar Nv",
    "wof:placetype":"venue"
},
  "geometry": {"coordinates":[2.8735690117,50.855430603],"type":"Point"}
}