{
  "type": "Feature",
  "properties": {
    "addr:full":"Brusselsepoortstraat 156 Gent Oost-Vlaanderen 9000",
    "addr:housenumber":"156",
    "addr:postcode":"9000",
    "addr:street":"Brusselsepoortstraat;Oost-Vlaanderen",
    "iso:country":"BE",
    "sg:address":"Brusselsepoortstraat 156",
    "sg:city":"Gent",
    "sg:classifiers":[
        {
            "category":"Manufacturing",
            "subcategory":"Leather Goods",
            "type":"Manufacturing & Wholesale Goods"
        }
    ],
    "sg:phone":"+32 9 224 22 42",
    "sg:postcode":"9000",
    "sg:province":"Oost-Vlaanderen",
    "sg:tags":[
        "repair",
        "buckskin",
        "-",
        "fur",
        "cleaning"
    ],
    "wof:name":"Knip Knap Bvba",
    "wof:placetype":"venue"
},
  "geometry": {"coordinates":[3.7372910976,51.043422699],"type":"Point"}
}