{
  "type": "Feature",
  "properties": {
    "addr:full":"Klein Leenstraat 11 Herne Vlaams-Brabant 1540",
    "addr:housenumber":"11",
    "addr:postcode":"1540",
    "addr:street":"Klein Leenstraat",
    "iso:country":"BE",
    "sg:address":"Klein Leenstraat 11",
    "sg:city":"Herne",
    "sg:classifiers":[
        {
            "category":"Recreation",
            "subcategory":"Campground",
            "type":"Entertainment"
        }
    ],
    "sg:phone":"+32 2 396 21 55",
    "sg:postcode":"1540",
    "sg:province":"Vlaams-Brabant",
    "sg:tags":[
        "site",
        "camping"
    ],
    "wof:name":"Green Valley",
    "wof:placetype":"venue"
},
  "geometry": {"coordinates":[4.0389409065,50.7385520935],"type":"Point"}
}