{
  "type": "Feature",
  "properties": {
    "iso:country":"BE",
    "sg:address":"Onledestraat 31",
    "sg:city":"Hooglede",
    "sg:classifiers":[
        {
            "category":"Food & Beverages",
            "subcategory":"Fruits & Vegetables",
            "type":"Retail Goods"
        }
    ],
    "sg:phone":"+32 51 72 39 47",
    "sg:postcode":"8830",
    "sg:province":"West-Vlaanderen",
    "sg:tags":[
        "groenten"
    ],
    "wof:name":"\u00b4t Klokhuis",
    "wof:placetype":"venue"
},
  "geometry": {"coordinates":[3.1329689026,50.9945373535],"type":"Point"}
}