{
  "type": "Feature",
  "properties": {
    "iso:country":"BE",
    "sg:address":"Kanegemstraat 52",
    "sg:city":"Tielt",
    "sg:classifiers":[
        {
            "category":"Professional",
            "type":"Services"
        }
    ],
    "sg:phone":"+32 51 40 70 77",
    "sg:postcode":"8700",
    "sg:province":"West-Vlaanderen",
    "sg:tags":[
        "industrial",
        "work",
        "-",
        "maintenance"
    ],
    "wof:name":"R S Mechanics Bvba",
    "wof:placetype":"venue"
},
  "geometry": {"coordinates":[3.3628129959,51.0052146912],"type":"Point"}
}