{
  "type": "Feature",
  "properties": {
    "addr:full":"Oude Houtlei 10 Gent Oost-Vlaanderen 9000",
    "addr:housenumber":"10",
    "addr:postcode":"9000",
    "addr:street":"Oude Houtlei;Oost-Vlaanderen",
    "iso:country":"BE",
    "sg:address":"Oude Houtlei 10",
    "sg:city":"Gent",
    "sg:classifiers":[
        {
            "category":"Health Services",
            "subcategory":"Doctor",
            "type":"Services"
        }
    ],
    "sg:phone":"+32 9 245 54 10",
    "sg:postcode":"9000",
    "sg:province":"Oost-Vlaanderen",
    "sg:tags":[
        "psychotherapist",
        "psychoanalyst"
    ],
    "wof:name":"Danniau F",
    "wof:placetype":"venue"
},
  "geometry": {"coordinates":[3.7164149284,51.0541114807],"type":"Point"}
}