{
  "type": "Feature",
  "properties": {
    "addr:full":"Rijksweg 49 Box 2 Puurs Antwerpen 2870",
    "addr:housenumber":"49;2",
    "addr:postcode":"2870",
    "addr:street":"Rijksweg;Box",
    "iso:country":"BE",
    "sg:address":"Rijksweg 49 Box 2",
    "sg:city":"Puurs",
    "sg:classifiers":[
        {
            "category":"Wholesale",
            "subcategory":"Hardware",
            "type":"Manufacturing & Wholesale Goods"
        }
    ],
    "sg:phone":"+32 3 866 11 32",
    "sg:postcode":"2870",
    "sg:province":"Antwerpen",
    "sg:tags":[
        "lubricating",
        "compound"
    ],
    "wof:name":"Viba Nv",
    "wof:placetype":"venue"
},
  "geometry": {"coordinates":[4.325261116,51.0640144348],"type":"Point"}
}