{
  "type": "Feature",
  "properties": {
    "iso:country":"BE",
    "sg:address":"Chauss\u00e9e D'aelbeke 101",
    "sg:city":"Mouscron",
    "sg:classifiers":[
        {
            "category":"Professional",
            "subcategory":"Accounting & Tax Preparation",
            "type":"Services"
        }
    ],
    "sg:phone":"+32 56 33 36 11",
    "sg:postcode":"7700",
    "sg:province":"Hainaut",
    "sg:tags":[
        "bookkeeper"
    ],
    "wof:name":"Renard N",
    "wof:placetype":"venue"
},
  "geometry": {"coordinates":[3.2263700962,50.7515335083],"type":"Point"}
}