{
  "type": "Feature",
  "properties": {
    "addr:full":"Brusselsestw 1 Mechelen Antwerpen 2800",
    "addr:housenumber":"1",
    "addr:postcode":"2800",
    "addr:street":"Brusselsestw",
    "iso:country":"BE",
    "sg:address":"Brusselsestw 1",
    "sg:city":"Mechelen",
    "sg:classifiers":[
        {
            "category":"Banks & Credit Unions",
            "subcategory":"Bank",
            "type":"Services"
        }
    ],
    "sg:phone":"+32 15 41 99 44",
    "sg:postcode":"2800",
    "sg:province":"Antwerpen",
    "wof:name":"Aslk-cger Bank",
    "wof:placetype":"venue"
},
  "geometry": {"coordinates":[4.4723911285,51.0204544067],"type":"Point"}
}