{
  "type": "Feature",
  "properties": {
    "iso:country":"BE",
    "sg:address":"Heide 52",
    "sg:city":"Diest",
    "sg:orig_category":"Eleveurs de bovins",
    "sg:phone":"+32 13 31 13 89",
    "sg:postcode":"3294",
    "sg:province":"Vlaams-Brabant",
    "wof:name":"Alfons Peeters",
    "wof:placetype":"venue"
},
  "geometry": {"coordinates":[5.0221500397,51.0197715759],"type":"Point"}
}