{
  "type": "Feature",
  "properties": {
    "addr:full":"Rue Antoine Labarre 53 Elsene/ixelles Bruxelles-Capitale 1050",
    "addr:housenumber":"53",
    "addr:postcode":"1050",
    "addr:street":"Rue Antoine Labarre",
    "iso:country":"BE",
    "sg:address":"Rue Antoine Labarre 53",
    "sg:city":"Elsene/ixelles",
    "sg:orig_category":"Pain, p\u00e2tisseries and confiseries",
    "sg:phone":"+32 2 648 17 10",
    "sg:postcode":"1050",
    "sg:province":"Bruxelles-Capitale",
    "wof:name":"P\u00c2tisserie Epi D'or",
    "wof:placetype":"venue"
},
  "geometry": {"coordinates":[4.3757100105,50.8253860474],"type":"Point"}
}