{
  "type": "Feature",
  "properties": {
    "addr:full":"Rue Reine-astrid 34 Gembloux Namur 5030",
    "addr:housenumber":"34",
    "addr:postcode":"5030",
    "addr:street":"Rue Reine-Astrid;Namur",
    "iso:country":"BE",
    "sg:address":"Rue Reine-astrid 34",
    "sg:city":"Gembloux",
    "sg:orig_category":"Paramedische behandelingen",
    "sg:phone":"+32 81 60 07 10",
    "sg:postcode":"5030",
    "sg:province":"Namur",
    "wof:name":"L. Vanderast",
    "wof:placetype":"venue"
},
  "geometry": {"coordinates":[4.6992092133,50.5607643127],"type":"Point"}
}