{
  "type": "Feature",
  "properties": {
    "addr:full":"Stenenmolenstraat 151b001 Mechelen Antwerpen 2800",
    "addr:housenumber":"151b001",
    "addr:postcode":"2800",
    "addr:street":"Stenenmolenstraat",
    "iso:country":"BE",
    "sg:address":"Stenenmolenstraat 151b001",
    "sg:city":"Mechelen",
    "sg:orig_category":"Entretien and r\u00e9parations de voitures",
    "sg:phone":"+32 15 43 11 62",
    "sg:postcode":"2800",
    "sg:province":"Antwerpen",
    "wof:name":"Marc Cauwenberghs",
    "wof:placetype":"venue"
},
  "geometry": {"coordinates":[4.4764771461,51.0093383789],"type":"Point"}
}