{
  "type": "Feature",
  "properties": {
    "addr:full":"Pav\u00c9 Bayart 37 Estaimpuis Hainaut 7730",
    "addr:housenumber":"37",
    "addr:postcode":"7730",
    "addr:street":"Estaimpuis Hainaut",
    "iso:country":"BE",
    "sg:address":"Pav\u00c9 Bayart 37",
    "sg:city":"Estaimpuis",
    "sg:orig_category":"Woningbouw",
    "sg:phone":"+32 56 48 40 51",
    "sg:postcode":"7730",
    "sg:province":"Hainaut",
    "wof:name":"Daniel Esser",
    "wof:placetype":"venue"
},
  "geometry": {"coordinates":[3.2731089592,50.7123565674],"type":"Point"}
}