{
  "type": "Feature",
  "properties": {
    "iso:country":"BE",
    "sg:address":"Scheldestraat 2a",
    "sg:city":"Temse",
    "sg:classifiers":[
        {
            "category":"Travel",
            "subcategory":"Hotels & Motels",
            "type":"Entertainment"
        }
    ],
    "sg:phone":"+32 3 771 21 59",
    "sg:postcode":"9140",
    "sg:province":"Oost-Vlaanderen",
    "sg:tags":[
        "international",
        "hotels",
        "reservation"
    ],
    "wof:name":"Scheldeboorden Travel",
    "wof:placetype":"venue"
},
  "geometry": {"coordinates":[4.2143602371,51.1252632141],"type":"Point"}
}