{
  "type": "Feature",
  "properties": {
    "addr:full":"Avenue Des Bruy\u00c8res 4 Namur Namur 5100",
    "addr:housenumber":"4",
    "addr:postcode":"5100",
    "addr:street":"Avenue Des Bruye\u0300Res",
    "iso:country":"BE",
    "sg:address":"Avenue Des Bruy\u00c8res 4",
    "sg:city":"Namur",
    "sg:orig_category":"Tuinen",
    "sg:phone":"+32 81 30 36 85",
    "sg:postcode":"5100",
    "sg:province":"Namur",
    "wof:name":"Van Serveyt Jean",
    "wof:placetype":"venue"
},
  "geometry": {"coordinates":[4.884745121,50.4383277893],"type":"Point"}
}