{
  "type": "Feature",
  "properties": {
    "addr:full":"Ruelle Des Messes 14 Modave (vierset-barse) Li\u00e8ge 4577",
    "addr:housenumber":"14",
    "addr:postcode":"4577",
    "addr:street":"Ruelle Des Messes;Vierset-Barse",
    "iso:country":"BE",
    "sg:address":"Ruelle Des Messes 14",
    "sg:city":"Modave (vierset-barse)",
    "sg:classifiers":[
        {
            "category":"Professional",
            "subcategory":"Management & Consulting",
            "type":"Services"
        }
    ],
    "sg:phone":"+32 85 41 37 17",
    "sg:postcode":"4577",
    "sg:province":"Li\u00e8ge",
    "sg:tags":[
        "marketing",
        "-",
        "consultant"
    ],
    "wof:name":"Happy Marketing",
    "wof:placetype":"venue"
},
  "geometry": {"coordinates":[5.2964558601,50.4814224243],"type":"Point"}
}