{
  "type": "Feature",
  "properties": {
    "addr:full":"Felicien Cauwelstraat 2 Geraardsbergen (nederboelare) Oost-Vlaanderen 9500",
    "addr:housenumber":"2",
    "addr:postcode":"9500",
    "addr:street":"Cauwelstraat",
    "iso:country":"BE",
    "sg:address":"Felicien Cauwelstraat 2",
    "sg:city":"Geraardsbergen (nederboelare)",
    "sg:classifiers":[
        {
            "category":"Bars & Pubs",
            "type":"Food & Drink"
        }
    ],
    "sg:phone":"+32 54 41 42 21",
    "sg:postcode":"9500",
    "sg:province":"Oost-Vlaanderen",
    "wof:name":"Hoeksken ('t)",
    "wof:placetype":"venue"
},
  "geometry": {"coordinates":[3.8721001148,50.7751235962],"type":"Point"}
}