{
  "type": "Feature",
  "properties": {
    "addr:full":"Rodt 217 Sankt Vith Li\u00e8ge 4780",
    "addr:housenumber":"217",
    "addr:postcode":"4780",
    "addr:street":"Rodt",
    "iso:country":"BE",
    "sg:address":"Rodt 217",
    "sg:city":"Sankt Vith",
    "sg:orig_category":"Voedingsspeciaalzaken",
    "sg:phone":"+32 80 22 79 53",
    "sg:postcode":"4780",
    "sg:province":"Li\u00e8ge",
    "wof:name":"Smeets Esther",
    "wof:placetype":"venue"
},
  "geometry": {"coordinates":[6.1044769287,50.2834739685],"type":"Point"}
}