{
  "type": "Feature",
  "properties": {
    "addr:full":"Herdersliedstraat 99 Anderlecht/anderlecht Bruxelles-Capitale 1070",
    "addr:housenumber":"99",
    "addr:postcode":"1070",
    "addr:street":"Herdersliedstraat",
    "iso:country":"BE",
    "sg:address":"Herdersliedstraat 99",
    "sg:city":"Anderlecht/anderlecht",
    "sg:orig_category":"Diverse bouwafwerking and reiniging Schoonmaakbedrijven and ongediertebestrijding",
    "sg:phone":"+32 2 411 42 38",
    "sg:postcode":"1070",
    "sg:province":"Bruxelles-Capitale",
    "wof:name":"Aluclean",
    "wof:placetype":"venue"
},
  "geometry": {"coordinates":[4.299946785,50.8482398987],"type":"Point"}
}