{
  "type": "Feature",
  "properties": {
    "iso:country":"BE",
    "sg:address":"Rue Verte 604ba",
    "sg:city":"Andenne",
    "sg:classifiers":[
        {
            "category":"Personal",
            "subcategory":"Beauty Salon",
            "type":"Services"
        }
    ],
    "sg:phone":"+32 81 58 14 08",
    "sg:postcode":"5300",
    "sg:province":"Namur",
    "sg:tags":[
        "de",
        "coiffure"
    ],
    "wof:name":"Claudia Biasio",
    "wof:placetype":"venue"
},
  "geometry": {"coordinates":[5.013051033,50.4975662231],"type":"Point"}
}