{
  "type": "Feature",
  "properties": {
    "iso:country":"BE",
    "sg:address":"Ringlaan 134",
    "sg:city":"Zandhoven",
    "sg:classifiers":[
        {
            "category":"Retail",
            "subcategory":"Auto Repair",
            "type":"Services"
        }
    ],
    "sg:phone":"+32 3 484 31 58",
    "sg:postcode":"2240",
    "sg:province":"Antwerpen",
    "sg:tags":[
        "garage"
    ],
    "wof:name":"Van Beirendonck Garage Bvba",
    "wof:placetype":"venue"
},
  "geometry": {"coordinates":[4.6659469604,51.2159156799],"type":"Point"}
}