{
  "type": "Feature",
  "properties": {
    "addr:full":"Zomerstraat-oost 38 Beernem West-Vlaanderen 8730",
    "addr:housenumber":"38",
    "addr:postcode":"8730",
    "addr:street":"Zomerstraat-Oost",
    "iso:country":"BE",
    "sg:address":"Zomerstraat-oost 38",
    "sg:city":"Beernem",
    "sg:orig_category":"Varkenskwekers",
    "sg:phone":"+32 50 35 17 80",
    "sg:postcode":"8730",
    "sg:province":"West-Vlaanderen",
    "wof:name":"Yvan Keerman",
    "wof:placetype":"venue"
},
  "geometry": {"coordinates":[3.3454799652,51.1934204102],"type":"Point"}
}