{
  "type": "Feature",
  "properties": {
    "addr:full":"Rue Du Cur\u00c9 109 Vorst/forest Bruxelles-Capitale 1190",
    "addr:housenumber":"109",
    "addr:postcode":"1190",
    "addr:street":"Rue Du Cure\u0301;/ Forest",
    "iso:country":"BE",
    "sg:address":"Rue Du Cur\u00c9 109",
    "sg:city":"Vorst/forest",
    "sg:orig_category":"M\u00e9decins and sp\u00e9cialistes",
    "sg:phone":"+32 2 376 16 82",
    "sg:postcode":"1190",
    "sg:province":"Bruxelles-Capitale",
    "wof:name":"Maria De Flores Canales",
    "wof:placetype":"venue"
},
  "geometry": {"coordinates":[4.3188581467,50.8111953735],"type":"Point"}
}