{
  "type": "Feature",
  "properties": {
    "iso:country":"BE",
    "sg:address":"Rue De Chimay 43",
    "sg:city":"Chimay (virelles)",
    "sg:classifiers":[
        {
            "category":"Health Services",
            "subcategory":"Health Practitioner",
            "type":"Services"
        }
    ],
    "sg:phone":"+32 60 21 49 49",
    "sg:postcode":"6461",
    "sg:province":"Hainaut",
    "sg:tags":[
        "physiotherapist"
    ],
    "wof:name":"Jacques M-a",
    "wof:placetype":"venue"
},
  "geometry": {"coordinates":[4.3287358284,50.0520706177],"type":"Point"}
}