{
  "type": "Feature",
  "properties": {
    "addr:full":"Zonhovenstraat 45 Hasselt Limburg 3500",
    "addr:housenumber":"45",
    "addr:postcode":"3500",
    "addr:street":"Zonhovenstraat",
    "iso:country":"BE",
    "sg:address":"Zonhovenstraat 45",
    "sg:city":"Hasselt",
    "sg:orig_category":"Verhuisdiensten",
    "sg:phone":"+32 11 82 32 87",
    "sg:postcode":"3500",
    "sg:province":"Limburg",
    "wof:name":"Im-gcm",
    "wof:placetype":"venue"
},
  "geometry": {"coordinates":[5.3850150108,50.9752159119],"type":"Point"}
}