{
  "type": "Feature",
  "properties": {
    "iso:country":"BE",
    "sg:address":"Menenstraat 120",
    "sg:city":"Wevelgem",
    "sg:orig_category":"Sportcentra",
    "sg:phone":"+32 56 42 22 40",
    "sg:postcode":"8560",
    "sg:province":"West-Vlaanderen",
    "wof:name":"De Vlasschaard",
    "wof:placetype":"venue"
},
  "geometry": {"coordinates":[3.1711781025,50.8062553406],"type":"Point"}
}