{
  "type": "Feature",
  "properties": {
    "iso:country":"BE",
    "sg:address":"Oostkerkestraat 32",
    "sg:city":"Diksmuide",
    "sg:orig_category":"Eleveurs and marchands de porcs. Eleveurs de bovins",
    "sg:phone":"+32 51 55 52 63",
    "sg:postcode":"8600",
    "sg:province":"West-Vlaanderen",
    "wof:name":"Andre Vandenbussche",
    "wof:placetype":"venue"
},
  "geometry": {"coordinates":[2.7946789265,51.0532531738],"type":"Point"}
}