{
  "type": "Feature",
  "properties": {
    "iso:country":"BE",
    "sg:address":"Leuerbroek 1002",
    "sg:city":"Kinrooi",
    "sg:orig_category":"Installation de menuiserie en bois and plastique",
    "sg:phone":"+32 89 70 01 20",
    "sg:postcode":"3640",
    "sg:province":"Limburg",
    "wof:name":"Afwerkingsbedrijf Baens",
    "wof:placetype":"venue"
},
  "geometry": {"coordinates":[5.7422151566,51.1452484131],"type":"Point"}
}