{
  "type": "Feature",
  "properties": {
    "addr:full":"Rue De Nivelles 4 Wavre Brabant Wallon 1300",
    "addr:housenumber":"4;1300",
    "addr:street":"Rue De Nivelles",
    "iso:country":"BE",
    "sg:address":"Rue De Nivelles 4",
    "sg:city":"Wavre",
    "sg:classifiers":[
        {
            "category":"Shopping",
            "subcategory":"Clothing, Apparel, & Fashions",
            "type":"Retail Goods"
        }
    ],
    "sg:phone":"+32 10 24 25 90",
    "sg:postcode":"1300",
    "sg:province":"Brabant Wallon",
    "sg:tags":[
        "ondergoed",
        "lingerie"
    ],
    "wof:name":"Caprices De Botticelli",
    "wof:placetype":"venue"
},
  "geometry": {"coordinates":[4.6084508896,50.7156257629],"type":"Point"}
}