{
  "type": "Feature",
  "properties": {
    "addr:full":"Sint-kwintens-heideweg 60 Zonhoven Limburg 3520",
    "addr:housenumber":"60",
    "addr:postcode":"3520",
    "addr:street":"Sint-Kwintens-Heideweg",
    "iso:country":"BE",
    "sg:address":"Sint-kwintens-heideweg 60",
    "sg:city":"Zonhoven",
    "sg:orig_category":"Services de s\u00e9curit\u00e9 and entreprises de gardiennage",
    "sg:phone":"+32 11 82 31 98",
    "sg:postcode":"3520",
    "sg:province":"Limburg",
    "wof:name":"Total Security",
    "wof:placetype":"venue"
},
  "geometry": {"coordinates":[5.3970170021,50.9786987305],"type":"Point"}
}