{
  "type": "Feature",
  "properties": {
    "iso:country":"BE",
    "sg:address":"Deinsesteenweg 91",
    "sg:city":"Kruishoutem",
    "sg:orig_category":"Herstellingen and onderhoud van auto's",
    "sg:phone":"+32 9 380 11 80",
    "sg:postcode":"9770",
    "sg:province":"Oost-Vlaanderen",
    "wof:name":"Martin Garage",
    "wof:placetype":"venue"
},
  "geometry": {"coordinates":[3.5316340923,50.9243927002],"type":"Point"}
}