{
  "type": "Feature",
  "properties": {
    "iso:country":"BE",
    "sg:address":"Esplanade 38de Du Heysel",
    "sg:city":"Bruxelles",
    "sg:orig_category":"Software For The Recording Of Operating Data",
    "sg:phone":"+32 2 474 03 60",
    "sg:postcode":"1020",
    "sg:province":"Bruxelles-Capitale",
    "wof:name":"Showcase Benelux S.a.",
    "wof:placetype":"venue"
},
  "geometry": {"coordinates":[4.341627121,50.8912887573],"type":"Point"}
}