{
  "type": "Feature",
  "properties": {
    "addr:full":"All\u00e9es Du Languedoc 1b Box 22 Bruxelles (evere) Bruxelles-Capitale 1140",
    "addr:housenumber":"1b box 22",
    "addr:postcode":"1140",
    "addr:street":"Alle\u0301Es Du Languedoc",
    "iso:country":"BE",
    "sg:address":"All\u00e9es Du Languedoc 1b Box 22",
    "sg:city":"Bruxelles (evere)",
    "sg:classifiers":[
        {
            "category":"Professional",
            "subcategory":"Testing Lab",
            "type":"Services"
        }
    ],
    "sg:phone":"+32 2 705 29 56",
    "sg:postcode":"1140",
    "sg:province":"Bruxelles-Capitale",
    "sg:tags":[
        "chemist"
    ],
    "wof:name":"Pharmacie Laperche",
    "wof:placetype":"venue"
},
  "geometry": {"coordinates":[4.4054179192,50.8719139099],"type":"Point"}
}