{
  "type": "Feature",
  "properties": {
    "iso:country":"BE",
    "sg:address":"Turnhoutsebaan 135",
    "sg:city":"Scherpenheuvel-zichem (zichem)",
    "sg:classifiers":[
        {
            "category":"Building & Trades",
            "subcategory":"Electrical",
            "type":"Services"
        }
    ],
    "sg:phone":"+32 13 77 11 11",
    "sg:postcode":"3271",
    "sg:province":"Vlaams-Brabant",
    "sg:tags":[
        "tool",
        "electric"
    ],
    "wof:name":"Vandendries Bvba",
    "wof:placetype":"venue"
},
  "geometry": {"coordinates":[5.0141887665,51.0302810669],"type":"Point"}
}