{
  "type": "Feature",
  "properties": {
    "iso:country":"BE",
    "sg:address":"Rue Fernand Vinet 82",
    "sg:city":"Soignies",
    "sg:orig_category":"Landmeters Landmeters and schatters",
    "sg:phone":"+32 67 33 14 24",
    "sg:postcode":"7060",
    "sg:province":"Hainaut",
    "wof:name":"Jose Vanderwhale",
    "wof:placetype":"venue"
},
  "geometry": {"coordinates":[4.0796871185,50.5770568848],"type":"Point"}
}