{
  "type": "Feature",
  "properties": {
    "addr:full":"Oost Eindeken 6 Stekene Oost-Vlaanderen 9190",
    "addr:housenumber":"6",
    "addr:postcode":"9190",
    "addr:street":"Eindeken",
    "iso:country":"BE",
    "sg:address":"Oost Eindeken 6",
    "sg:city":"Stekene",
    "sg:classifiers":[
        {
            "category":"Professional",
            "subcategory":"Computer Services",
            "type":"Services"
        }
    ],
    "sg:phone":"+32 476 28 97 08",
    "sg:postcode":"9190",
    "sg:province":"Oost-Vlaanderen",
    "sg:tags":[
        "webdesign",
        "-",
        "internet"
    ],
    "wof:name":"Dirickx M",
    "wof:placetype":"venue"
},
  "geometry": {"coordinates":[4.0452828407,51.210067749],"type":"Point"}
}