{
  "type": "Feature",
  "properties": {
    "iso:country":"BE",
    "sg:address":"Aartrijkestraat 12a",
    "sg:city":"Ichtegem (eernegem)",
    "sg:classifiers":[
        {
            "category":"Education",
            "subcategory":"School",
            "type":"Public Place"
        }
    ],
    "sg:phone":"+32 59 29 02 12",
    "sg:postcode":"8480",
    "sg:province":"West-Vlaanderen",
    "sg:tags":[
        "secondary"
    ],
    "wof:name":"St-godelievecollege",
    "wof:placetype":"venue"
},
  "geometry": {"coordinates":[3.010445118,51.0919189453],"type":"Point"}
}