{
  "type": "Feature",
  "properties": {
    "addr:full":"Basilieklaan 77 Scherpenheuvel-zichem Vlaams-Brabant 3270",
    "addr:housenumber":"77",
    "addr:postcode":"3270",
    "addr:street":"Basilieklaan",
    "iso:country":"BE",
    "sg:address":"Basilieklaan 77",
    "sg:city":"Scherpenheuvel-zichem",
    "sg:orig_category":"Lampes and appareils \u00e9lectriques Fab. Travaux d\u00b4installation divers",
    "sg:phone":"+32 13 77 72 90",
    "sg:postcode":"3270",
    "sg:province":"Vlaams-Brabant",
    "wof:name":"Luna Lights",
    "wof:placetype":"venue"
},
  "geometry": {"coordinates":[4.9790902138,50.9785232544],"type":"Point"}
}