{
  "type": "Feature",
  "properties": {
    "iso:country":"BE",
    "sg:address":"Place Aux Foires 6",
    "sg:city":"Marche-en-famenne",
    "sg:orig_category":"Quincailleries",
    "sg:phone":"+32 84 31 18 10",
    "sg:postcode":"6900",
    "sg:province":"Luxembourg",
    "wof:name":"Rouffin-lecomte",
    "wof:placetype":"venue"
},
  "geometry": {"coordinates":[5.344189167,50.2257881165],"type":"Point"}
}