{
  "type": "Feature",
  "properties": {
    "addr:full":"Lageweg 41 Retie Antwerpen 2470",
    "addr:housenumber":"41",
    "addr:postcode":"2470",
    "addr:street":"Lageweg",
    "iso:country":"BE",
    "sg:address":"Lageweg 41",
    "sg:city":"Retie",
    "sg:orig_category":"Kapsalons",
    "sg:phone":"+32 14 37 86 82",
    "sg:postcode":"2470",
    "sg:province":"Antwerpen",
    "wof:name":"Haarstudio Ilse",
    "wof:placetype":"venue"
},
  "geometry": {"coordinates":[5.080698967,51.2557640076],"type":"Point"}
}