{
  "type": "Feature",
  "properties": {
    "iso:country":"BE",
    "sg:address":"Oude Baan 118",
    "sg:city":"Mechelen",
    "sg:orig_category":"Loodgieterij, verwarming and sanitaire installaties",
    "sg:phone":"+32 15 21 67 13",
    "sg:postcode":"2800",
    "sg:province":"Antwerpen",
    "wof:name":"Leon Sol",
    "wof:placetype":"venue"
},
  "geometry": {"coordinates":[4.4570789337,51.0639305115],"type":"Point"}
}