{
  "type": "Feature",
  "properties": {
    "iso:country":"BE",
    "sg:address":"De Merodedreef 89f",
    "sg:city":"Westerlo",
    "sg:classifiers":[
        {
            "category":"Professional",
            "subcategory":"Lawyer & Legal Services",
            "type":"Services"
        }
    ],
    "sg:phone":"+32 14 54 75 55",
    "sg:postcode":"2260",
    "sg:province":"Antwerpen",
    "wof:name":"Van Rompaey Paul",
    "wof:placetype":"venue"
},
  "geometry": {"coordinates":[4.9173212051,51.0906715393],"type":"Point"}
}