{
  "type": "Feature",
  "properties": {
    "addr:full":"Wijsstraat 1 Bilzen Limburg 3740",
    "addr:housenumber":"1",
    "addr:postcode":"3740",
    "addr:street":"Wijsstraat",
    "iso:country":"BE",
    "sg:address":"Wijsstraat 1",
    "sg:city":"Bilzen",
    "sg:orig_category":"M\u00e9decins and sp\u00e9cialistes",
    "sg:phone":"+32 89 41 26 07",
    "sg:postcode":"3740",
    "sg:province":"Limburg",
    "wof:name":"Wim Remans",
    "wof:placetype":"venue"
},
  "geometry": {"coordinates":[5.5125198364,50.8675117493],"type":"Point"}
}