{
  "type": "Feature",
  "properties": {
    "iso:country":"BE",
    "sg:address":"Victor Adriaenssensstraat 76",
    "sg:city":"Schoten",
    "sg:classifiers":[
        {
            "category":"Social Services",
            "subcategory":"Child Care",
            "type":"Services"
        }
    ],
    "sg:phone":"+32 3 685 04 25",
    "sg:postcode":"2900",
    "sg:province":"Antwerpen",
    "sg:tags":[
        "baby",
        "nursery",
        "day",
        "sitting"
    ],
    "wof:name":"Koekoek (de) Occas Kinderopvang",
    "wof:placetype":"venue"
},
  "geometry": {"coordinates":[4.4975938797,51.2452125549],"type":"Point"}
}