{
  "type": "Feature",
  "properties": {
    "addr:full":"Eupener Strasse 5 Raeren (eynatten) Li\u00e8ge 4731",
    "addr:housenumber":"5",
    "addr:postcode":"4731",
    "addr:street":"Eupener Strasse",
    "iso:country":"BE",
    "sg:address":"Eupener Strasse 5",
    "sg:city":"Raeren (eynatten)",
    "sg:classifiers":[
        {
            "category":"Retail",
            "subcategory":"Auto Repair",
            "type":"Services"
        }
    ],
    "sg:phone":"+32 87 85 01 37",
    "sg:postcode":"4731",
    "sg:province":"Li\u00e8ge",
    "sg:tags":[
        "garage"
    ],
    "wof:name":"Bongartz R",
    "wof:placetype":"venue"
},
  "geometry": {"coordinates":[6.082649231,50.6915893555],"type":"Point"}
}