{
  "type": "Feature",
  "properties": {
    "addr:full":"Oude Liersebaan 33ba Heist-op-den-berg Antwerpen 2220",
    "addr:housenumber":"33ba",
    "addr:postcode":"2220",
    "addr:street":"Oude Liersebaan",
    "iso:country":"BE",
    "sg:address":"Oude Liersebaan 33ba",
    "sg:city":"Heist-op-den-berg",
    "sg:orig_category":"Enseignement maternel and primaire",
    "sg:phone":"+32 15 24 67 44",
    "sg:postcode":"2220",
    "sg:province":"Antwerpen",
    "wof:name":"Vrije Basisschool",
    "wof:placetype":"venue"
},
  "geometry": {"coordinates":[4.7118711472,51.0775527954],"type":"Point"}
}