{
  "type": "Feature",
  "properties": {
    "addr:full":"Oosteneinde 16 Beerse Antwerpen 2340",
    "addr:housenumber":"16",
    "addr:postcode":"2340",
    "addr:street":"Oosteneinde",
    "iso:country":"BE",
    "sg:address":"Oosteneinde 16",
    "sg:city":"Beerse",
    "sg:orig_category":"HERSTELLING ELEKTRISCHE HUISHOUDAPPARATEN Huishoudapparaten, televisies and radio's",
    "sg:phone":"+32 14 61 11 99",
    "sg:postcode":"2340",
    "sg:province":"Antwerpen",
    "wof:name":"Tontrager",
    "wof:placetype":"venue"
},
  "geometry": {"coordinates":[4.8701739311,51.3310661316],"type":"Point"}
}