{
  "type": "Feature",
  "properties": {
    "iso:country":"BE",
    "sg:address":"Chauss\u00c9e De Waterloo 1361",
    "sg:city":"Ukkel/uccle",
    "sg:orig_category":"Herenkledingzaken",
    "sg:phone":"+32 2 372 22 72",
    "sg:postcode":"1180",
    "sg:province":"Bruxelles-Capitale",
    "wof:name":"Oldriver",
    "wof:placetype":"venue"
},
  "geometry": {"coordinates":[4.3752012253,50.7883987427],"type":"Point"}
}