{
  "type": "Feature",
  "properties": {
    "iso:country":"BE",
    "sg:address":"Quartier Joseph Gailly 62a",
    "sg:city":"Charleroi (gilly)",
    "sg:classifiers":[
        {
            "category":"Mining & Drilling",
            "type":"Manufacturing & Wholesale Goods"
        }
    ],
    "sg:phone":"+32 71 39 53 87",
    "sg:postcode":"6060",
    "sg:province":"Hainaut",
    "sg:tags":[
        "concrete",
        "reinforced",
        "sawing"
    ],
    "wof:name":"Pirlot Jacques",
    "wof:placetype":"venue"
},
  "geometry": {"coordinates":[4.4880981445,50.4251937866],"type":"Point"}
}