{
  "type": "Feature",
  "properties": {
    "addr:full":"Rue De L'eglise 100 Bruxelles (woluwe-saint-pierre) Bruxelles-Capitale 1150",
    "addr:housenumber":"100",
    "addr:postcode":"1150",
    "addr:street":"Rue De L'Eglise",
    "iso:country":"BE",
    "sg:address":"Rue De L'eglise 100",
    "sg:city":"Bruxelles (woluwe-saint-pierre)",
    "sg:classifiers":[
        {
            "category":"Professional",
            "subcategory":"Art Services",
            "type":"Services"
        }
    ],
    "sg:phone":"+32 2 772 72 14",
    "sg:postcode":"1150",
    "sg:province":"Bruxelles-Capitale",
    "sg:tags":[
        "graphic",
        "designer"
    ],
    "wof:name":"Plan Libre Sc",
    "wof:placetype":"venue"
},
  "geometry": {"coordinates":[4.4641041756,50.8406906128],"type":"Point"}
}