{
  "type": "Feature",
  "properties": {
    "addr:full":"Rue Des Moulins 39 Grez-doiceau (archennes) Brabant Wallon 1390",
    "addr:housenumber":"39",
    "addr:postcode":"1390",
    "addr:street":"Rue Des Moulins;Wallon",
    "iso:country":"BE",
    "sg:address":"Rue Des Moulins 39",
    "sg:city":"Grez-doiceau (archennes)",
    "sg:classifiers":[
        {
            "category":"Building & Trades",
            "subcategory":"Landscaping Services",
            "type":"Services"
        }
    ],
    "sg:phone":"+32 10 84 31 08",
    "sg:postcode":"1390",
    "sg:province":"Brabant Wallon",
    "sg:tags":[
        "gardening",
        "garden",
        "maintenance"
    ],
    "wof:name":"Vanroy V",
    "wof:placetype":"venue"
},
  "geometry": {"coordinates":[4.6851148605,50.7503547668],"type":"Point"}
}