{
  "type": "Feature",
  "properties": {
    "iso:country":"BE",
    "sg:address":"Hokken 4",
    "sg:city":"Arendonk",
    "sg:classifiers":[
        {
            "category":"Fast Food",
            "type":"Food & Drink"
        }
    ],
    "sg:phone":"+32 14 67 22 18",
    "sg:postcode":"2370",
    "sg:province":"Antwerpen",
    "sg:tags":[
        "fried",
        "stand",
        "potato"
    ],
    "wof:name":"Den Draai",
    "wof:placetype":"venue"
},
  "geometry": {"coordinates":[5.0929298401,51.3282737732],"type":"Point"}
}