{
  "type": "Feature",
  "properties": {
    "iso:country":"BE",
    "sg:address":"Kluizenhof 6",
    "sg:city":"Sint-gillis-waas",
    "sg:classifiers":[
        {
            "category":"Freight",
            "type":"Transportation"
        }
    ],
    "sg:phone":"+32 3 770 65 92",
    "sg:postcode":"9170",
    "sg:province":"Oost-Vlaanderen",
    "sg:tags":[
        "-",
        "transport"
    ],
    "wof:name":"Dullaert P",
    "wof:placetype":"venue"
},
  "geometry": {"coordinates":[4.0998439789,51.2292518616],"type":"Point"}
}