{
  "type": "Feature",
  "properties": {
    "iso:country":"BE",
    "sg:address":"Sint-sebastiaansstraat 16ba",
    "sg:city":"Oostende",
    "sg:orig_category":"Opvangtehuizen and vluchthuizen",
    "sg:phone":"+32 59 70 35 25",
    "sg:postcode":"8400",
    "sg:province":"West-Vlaanderen",
    "wof:name":"C.a.w. Middenkust",
    "wof:placetype":"venue"
},
  "geometry": {"coordinates":[2.9162230492,51.2310523987],"type":"Point"}
}