{
  "type": "Feature",
  "properties": {
    "iso:country":"BE",
    "sg:address":"Chauss\u00c9e De Wavre 1468",
    "sg:city":"Oudergem/auderghem",
    "sg:orig_category":"Entretien et r\u00e9parations de v\u00e9hicules \u00e0 domicile",
    "sg:phone":"+32 2 346 20 20",
    "sg:postcode":"1160",
    "sg:province":"Bruxelles-Capitale",
    "wof:name":"E.c.c.s.",
    "wof:placetype":"venue"
},
  "geometry": {"coordinates":[4.4182629585,50.8182868958],"type":"Point"}
}