{
  "type": "Feature",
  "properties": {
    "addr:full":"Antoon Catriestraat 13 Gent (drongen) Oost-Vlaanderen 9031",
    "addr:housenumber":"13",
    "addr:postcode":"9031",
    "addr:street":"Antoon Catriestraat",
    "iso:country":"BE",
    "sg:address":"Antoon Catriestraat 13",
    "sg:city":"Gent (drongen)",
    "sg:classifiers":[
        {
            "category":"Cafe",
            "type":"Food & Drink"
        }
    ],
    "sg:phone":"+32 9 236 52 35",
    "sg:postcode":"9031",
    "sg:province":"Oost-Vlaanderen",
    "sg:tags":[
        "snack-bars"
    ],
    "wof:name":"Ovenkoekje",
    "wof:placetype":"venue"
},
  "geometry": {"coordinates":[3.6567230225,51.0502204895],"type":"Point"}
}