{
  "type": "Feature",
  "properties": {
    "iso:country":"BE",
    "sg:address":"Rue Martin Pfeiffer 9b7",
    "sg:city":"Sint-jans-molenbeek/molenbeek-saint-jean",
    "sg:orig_category":"Gestion de portefeuilles and fortunes, conseils en placements. Assurances",
    "sg:phone":"+32 2 414 30 47",
    "sg:postcode":"1080",
    "sg:province":"Bruxelles-Capitale",
    "wof:name":"P. Dessart",
    "wof:placetype":"venue"
},
  "geometry": {"coordinates":[4.3154740334,50.8588981628],"type":"Point"}
}