{
  "type": "Feature",
  "properties": {
    "addr:full":"Rue De Marche 38 Nandrin Li\u00e8ge 4550",
    "addr:housenumber":"38",
    "addr:postcode":"4550",
    "addr:street":"Rue De Marche",
    "iso:country":"BE",
    "sg:address":"Rue De Marche 38",
    "sg:city":"Nandrin",
    "sg:classifiers":[
        {
            "category":"Professional",
            "subcategory":"Accounting & Tax Preparation",
            "type":"Services"
        }
    ],
    "sg:phone":"+32 85 51 15 53",
    "sg:postcode":"4550",
    "sg:province":"Li\u00e8ge",
    "sg:tags":[
        "bookkeeper"
    ],
    "wof:name":"Devaux M",
    "wof:placetype":"venue"
},
  "geometry": {"coordinates":[5.441010952,50.5418548584],"type":"Point"}
}