{
  "type": "Feature",
  "properties": {
    "addr:full":"Narcislaan 4 Kapelle-op-den-bos Vlaams-Brabant 1880",
    "addr:housenumber":"4",
    "addr:postcode":"1880",
    "addr:street":"Narcislaan",
    "iso:country":"BE",
    "sg:address":"Narcislaan 4",
    "sg:city":"Kapelle-op-den-bos",
    "sg:classifiers":[
        {
            "category":"Arena",
            "subcategory":"Sports Club",
            "type":"Entertainment"
        }
    ],
    "sg:phone":"+32 15 71 26 50",
    "sg:postcode":"1880",
    "sg:province":"Vlaams-Brabant",
    "sg:tags":[
        "terrain",
        "hors",
        "de",
        "installation",
        "sportifs"
    ],
    "wof:name":"F.c. Ramsdonk",
    "wof:placetype":"venue"
},
  "geometry": {"coordinates":[4.3489341736,51.0154838562],"type":"Point"}
}