{
  "type": "Feature",
  "properties": {
    "iso:country":"BE",
    "sg:address":"Rue Groeselenberg 159",
    "sg:city":"Bruxelles (uccle)",
    "sg:classifiers":[
        {
            "category":"Bakery",
            "type":"Food & Drink"
        }
    ],
    "sg:phone":"+32 2 374 44 13",
    "sg:postcode":"1180",
    "sg:province":"Bruxelles-Capitale",
    "sg:tags":[
        "confectioner",
        "baker"
    ],
    "wof:name":"Jacqueline",
    "wof:placetype":"venue"
},
  "geometry": {"coordinates":[4.3585600853,50.8027610779],"type":"Point"}
}