{
  "type": "Feature",
  "properties": {
    "iso:country":"BE",
    "sg:address":"Gemeentestraat 27",
    "sg:city":"Antwerpen",
    "sg:orig_category":"Pain, p\u00e2tisseries and confiseries",
    "sg:phone":"+32 3 231 45 29",
    "sg:postcode":"2060",
    "sg:province":"Antwerpen",
    "wof:name":"Bakkerij Europe",
    "wof:placetype":"venue"
},
  "geometry": {"coordinates":[4.4199957848,51.2193412781],"type":"Point"}
}