{
  "type": "Feature",
  "properties": {
    "addr:full":"Markt 29 Eeklo Oost-Vlaanderen 9900",
    "addr:housenumber":"29",
    "addr:postcode":"9900",
    "addr:street":"Markt",
    "iso:country":"BE",
    "sg:address":"Markt 29",
    "sg:city":"Eeklo",
    "sg:orig_category":"Pharmaciens",
    "sg:phone":"+32 9 377 22 22",
    "sg:postcode":"9900",
    "sg:province":"Oost-Vlaanderen",
    "wof:name":"Mebi",
    "wof:placetype":"venue"
},
  "geometry": {"coordinates":[3.5663030148,51.1839981079],"type":"Point"}
}