{
  "type": "Feature",
  "properties": {
    "addr:full":"Place De L'h\u00f4tel De Ville 10 Walcourt Namur 5650",
    "addr:housenumber":"10",
    "addr:postcode":"5650",
    "addr:street":"Place De L'Ho \u0302Tel De Ville",
    "iso:country":"BE",
    "sg:address":"Place De L'h\u00f4tel De Ville 10",
    "sg:city":"Walcourt",
    "sg:classifiers":[
        {
            "category":"Bars & Pubs",
            "type":"Food & Drink"
        }
    ],
    "sg:phone":"+32 71 61 35 65",
    "sg:postcode":"5650",
    "sg:province":"Namur",
    "wof:name":"Taverne De L'h\u00f4tel De Ville",
    "wof:placetype":"venue"
},
  "geometry": {"coordinates":[4.4154701233,50.2493095398],"type":"Point"}
}