{
  "type": "Feature",
  "properties": {
    "addr:full":"Rue De Gozee 654 Montigny Le Tilleul Hainaut 6110",
    "addr:housenumber":"654",
    "addr:postcode":"6110",
    "addr:street":"Rue De Gozee;Montigny Le;Hainaut",
    "iso:country":"BE",
    "sg:address":"Rue De Gozee 654",
    "sg:city":"Montigny Le Tilleul",
    "sg:classifiers":[
        {
            "category":"Banks & Credit Unions",
            "subcategory":"Bank",
            "type":"Services"
        }
    ],
    "sg:phone":"+32 60 51 85 77",
    "sg:postcode":"6110",
    "sg:province":"Hainaut",
    "wof:name":"Cr\u00e9dit Communal",
    "wof:placetype":"venue"
},
  "geometry": {"coordinates":[4.3641080856,50.36302948],"type":"Point"}
}