{
  "type": "Feature",
  "properties": {
    "addr:full":"Bosmolenstraat 3 Lendelede West-Vlaanderen 8860",
    "addr:housenumber":"3",
    "addr:postcode":"8860",
    "addr:street":"Bosmolenstraat",
    "iso:country":"BE",
    "sg:address":"Bosmolenstraat 3",
    "sg:city":"Lendelede",
    "sg:classifiers":[
        {
            "category":"Building & Trades",
            "subcategory":"Electrical",
            "type":"Services"
        }
    ],
    "sg:phone":"+32 51 30 44 05",
    "sg:postcode":"8860",
    "sg:province":"West-Vlaanderen",
    "sg:tags":[
        "electric",
        "-",
        "housewiring",
        "contractor"
    ],
    "wof:name":"Dedeurwaerder F",
    "wof:placetype":"venue"
},
  "geometry": {"coordinates":[3.1964039803,50.8878250122],"type":"Point"}
}