{
  "type": "Feature",
  "properties": {
    "addr:full":"Chauss\u00c9e De Mons 789 Anderlecht Bruxelles-Capitale 1070",
    "addr:housenumber":"789",
    "addr:postcode":"1070",
    "addr:street":"Chausse\u0301E De Mons",
    "iso:country":"BE",
    "sg:address":"Chauss\u00c9e De Mons 789",
    "sg:city":"Anderlecht",
    "sg:orig_category":"Imprimeries and copyshops",
    "sg:phone":"+32 2 521 47 85",
    "sg:postcode":"1070",
    "sg:province":"Bruxelles-Capitale",
    "wof:name":"Copy & Co",
    "wof:placetype":"venue"
},
  "geometry": {"coordinates":[4.3061327934,50.8295898438],"type":"Point"}
}