{
  "type": "Feature",
  "properties": {
    "addr:full":"Van Thorenburghlaan 20 Oosterzele (scheldewindeke) Oost-Vlaanderen 9860",
    "addr:housenumber":"20",
    "addr:postcode":"9860",
    "addr:street":"Thorenburghlaan",
    "iso:country":"BE",
    "sg:address":"Van Thorenburghlaan 20",
    "sg:city":"Oosterzele (scheldewindeke)",
    "sg:classifiers":[
        {
            "category":"Professional",
            "subcategory":"Computer Services",
            "type":"Services"
        }
    ],
    "sg:phone":"+32 9 362 12 85",
    "sg:postcode":"9860",
    "sg:province":"Oost-Vlaanderen",
    "sg:tags":[
        "genealogist"
    ],
    "wof:name":"Landsbond V/d Belgische Varkensstamboeken-beva",
    "wof:placetype":"venue"
},
  "geometry": {"coordinates":[3.785877943,50.9497070312],"type":"Point"}
}