{
  "type": "Feature",
  "properties": {
    "addr:full":"Rue Martin-sandron 131 Doische Namur 5680",
    "addr:housenumber":"131",
    "addr:postcode":"5680",
    "addr:street":"Rue Martin-Sandron",
    "iso:country":"BE",
    "sg:address":"Rue Martin-sandron 131",
    "sg:city":"Doische",
    "sg:orig_category":"Banken and kredietinstellingen",
    "sg:phone":"+32 82 67 70 80",
    "sg:postcode":"5680",
    "sg:province":"Namur",
    "wof:name":"Dexia",
    "wof:placetype":"venue"
},
  "geometry": {"coordinates":[4.7467699051,50.1375923157],"type":"Point"}
}