{
  "type": "Feature",
  "properties": {
    "addr:full":"Rumbeeksesteenweg 229b1 Roeselare West-Vlaanderen 8800",
    "addr:housenumber":"229b1",
    "addr:postcode":"8800",
    "addr:street":"Rumbeeksesteenweg",
    "iso:country":"BE",
    "sg:address":"Rumbeeksesteenweg 229b1",
    "sg:city":"Roeselare",
    "sg:orig_category":"Landmeters",
    "sg:phone":"+32 51 22 48 11",
    "sg:postcode":"8800",
    "sg:province":"West-Vlaanderen",
    "wof:name":"Dumoulin J.",
    "wof:placetype":"venue"
},
  "geometry": {"coordinates":[3.1341159344,50.9386978149],"type":"Point"}
}