{
  "type": "Feature",
  "properties": {
    "iso:country":"BE",
    "sg:address":"Ruelle Botte 8",
    "sg:city":"Court-saint-etienne",
    "sg:classifiers":[
        {
            "category":"Home & Garden",
            "subcategory":"Building Materials",
            "type":"Retail Goods"
        }
    ],
    "sg:phone":"+32 10 61 31 42",
    "sg:postcode":"1490",
    "sg:province":"Brabant Wallon",
    "sg:tags":[
        "window"
    ],
    "wof:name":"Dockx G",
    "wof:placetype":"venue"
},
  "geometry": {"coordinates":[4.5289168358,50.6086616516],"type":"Point"}
}