{
  "type": "Feature",
  "properties": {
    "addr:full":"Chauss\u00c9e De Li\u00c8ge 55 Hamois Namur 5360",
    "addr:housenumber":"55",
    "addr:postcode":"5360",
    "addr:street":"Chausse\u0301E De Lie\u0300Ge",
    "iso:country":"BE",
    "sg:address":"Chauss\u00c9e De Li\u00c8ge 55",
    "sg:city":"Hamois",
    "sg:classifiers":[
        {
            "category":"Restaurant",
            "type":"Food & Drink"
        }
    ],
    "sg:phone":"+32 83 61 26 51",
    "sg:postcode":"5360",
    "sg:province":"Namur",
    "wof:name":"Taverne Le Tramino",
    "wof:placetype":"venue"
},
  "geometry": {"coordinates":[5.157186985,50.3412971497],"type":"Point"}
}