{
  "type": "Feature",
  "properties": {
    "addr:full":"Rue Thomas 8 Mont-saint-guibert (corbais) Brabant Wallon 1435",
    "addr:housenumber":"8",
    "addr:postcode":"1435",
    "addr:street":"Rue Thomas;Corbais;Wallon",
    "iso:country":"BE",
    "sg:address":"Rue Thomas 8",
    "sg:city":"Mont-saint-guibert (corbais)",
    "sg:classifiers":[
        {
            "category":"Health Services",
            "subcategory":"Doctor",
            "type":"Services"
        }
    ],
    "sg:phone":"+32 10 65 82 03",
    "sg:postcode":"1435",
    "sg:province":"Brabant Wallon",
    "sg:tags":[
        "psychotherapist",
        "psychoanalyst"
    ],
    "wof:name":"Louche M-f",
    "wof:placetype":"venue"
},
  "geometry": {"coordinates":[4.6481318474,50.6433372498],"type":"Point"}
}