{
  "type": "Feature",
  "properties": {
    "iso:country":"BE",
    "sg:address":"Industrieweg Noord 1141",
    "sg:city":"Opglabbeek",
    "sg:classifiers":[
        {
            "category":"Utilities",
            "subcategory":"Natural Gas",
            "type":"Services"
        }
    ],
    "sg:phone":"+32 89 85 55 21",
    "sg:postcode":"3660",
    "sg:province":"Limburg",
    "sg:tags":[
        "extraction",
        "-",
        "smoke",
        "equipment"
    ],
    "wof:name":"Limoco Industries",
    "wof:placetype":"venue"
},
  "geometry": {"coordinates":[5.5458068848,51.0385322571],"type":"Point"}
}