{
  "type": "Feature",
  "properties": {
    "addr:full":"Odon Warlandlaan 170 Jette/jette Bruxelles-Capitale 1090",
    "addr:housenumber":"170",
    "addr:postcode":"1090",
    "addr:street":"Odon Warlandlaan",
    "iso:country":"BE",
    "sg:address":"Odon Warlandlaan 170",
    "sg:city":"Jette/jette",
    "sg:orig_category":"Artsen and specialisten",
    "sg:phone":"+32 2 425 01 61",
    "sg:postcode":"1090",
    "sg:province":"Bruxelles-Capitale",
    "wof:name":"Jean Bosman",
    "wof:placetype":"venue"
},
  "geometry": {"coordinates":[4.3367929459,50.871837616],"type":"Point"}
}