{
  "type": "Feature",
  "properties": {
    "iso:country":"BE",
    "sg:address":"Rue Hameau -les- Bois 12",
    "sg:city":"Pont-a-celles",
    "sg:orig_category":"Huishoudapparaten, televisies and radio's Telecommunicatieapparaten",
    "sg:phone":"+32 67 22 02 50",
    "sg:postcode":"6230",
    "sg:province":"Hainaut",
    "wof:name":"Semaille",
    "wof:placetype":"venue"
},
  "geometry": {"coordinates":[4.3707361221,50.507106781],"type":"Point"}
}