{
  "type": "Feature",
  "properties": {
    "addr:full":"Rue Edith Cavell 86 Bruxelles (uccle) Bruxelles-Capitale 1180",
    "addr:housenumber":"86",
    "addr:postcode":"1180",
    "addr:street":"Rue Edith Cavell",
    "iso:country":"BE",
    "sg:address":"Rue Edith Cavell 86",
    "sg:city":"Bruxelles (uccle)",
    "sg:classifiers":[
        {
            "category":"Home & Garden",
            "subcategory":"Carpets & Floor Coverings",
            "type":"Retail Goods"
        }
    ],
    "sg:phone":"+32 2 345 45 71",
    "sg:postcode":"1180",
    "sg:province":"Bruxelles-Capitale",
    "sg:tags":[
        "tile"
    ],
    "wof:name":"Dereau N",
    "wof:placetype":"venue"
},
  "geometry": {"coordinates":[4.3579120636,50.8111381531],"type":"Point"}
}