{
  "type": "Feature",
  "properties": {
    "addr:full":"Dokter Roosensplein 13 Brasschaat Antwerpen 2930",
    "addr:housenumber":"13",
    "addr:postcode":"2930",
    "addr:street":"Dokter Roosensplein",
    "iso:country":"BE",
    "sg:address":"Dokter Roosensplein 13",
    "sg:city":"Brasschaat",
    "sg:classifiers":[
        {
            "category":"Shopping",
            "subcategory":"Jewelry",
            "type":"Retail Goods"
        }
    ],
    "sg:phone":"+32 3 651 80 15",
    "sg:postcode":"2930",
    "sg:province":"Antwerpen",
    "sg:tags":[
        "jeweller",
        "-"
    ],
    "wof:name":"De Beenhouwer P",
    "wof:placetype":"venue"
},
  "geometry": {"coordinates":[4.4863052368,51.287940979],"type":"Point"}
}