{
  "type": "Feature",
  "properties": {
    "addr:full":"Rue De Herve 544 Beyne-heusay Li\u00e8ge 4610",
    "addr:housenumber":"544",
    "addr:postcode":"4610",
    "addr:street":"Rue De Herve",
    "iso:country":"BE",
    "sg:address":"Rue De Herve 544",
    "sg:city":"Beyne-heusay",
    "sg:orig_category":"HUISBRANDOLIE",
    "sg:phone":"+32 4 365 52 45",
    "sg:postcode":"4610",
    "sg:province":"Li\u00e8ge",
    "wof:name":"Bodson Bonmariage",
    "wof:placetype":"venue"
},
  "geometry": {"coordinates":[5.6398839951,50.6262512207],"type":"Point"}
}