{
  "type": "Feature",
  "properties": {
    "addr:full":"Zijpstraat 108 Aalst Oost-Vlaanderen 9308",
    "addr:housenumber":"108",
    "addr:postcode":"9308",
    "addr:street":"Zijpstraat",
    "iso:country":"BE",
    "sg:address":"Zijpstraat 108",
    "sg:city":"Aalst",
    "sg:orig_category":"Fruits and l\u00e9gumes Producteurs de l\u00e9gumes",
    "sg:phone":"+32 53 78 54 77",
    "sg:postcode":"9308",
    "sg:province":"Oost-Vlaanderen",
    "wof:name":"Dirk Van Wilder",
    "wof:placetype":"venue"
},
  "geometry": {"coordinates":[4.0347590446,50.9603500366],"type":"Point"}
}