{
  "type": "Feature",
  "properties": {
    "addr:full":"Bosstraat 36 Dilbeek Vlaams-Brabant 1702",
    "addr:housenumber":"36",
    "addr:postcode":"1702",
    "addr:street":"Bosstraat",
    "iso:country":"BE",
    "sg:address":"Bosstraat 36",
    "sg:city":"Dilbeek",
    "sg:orig_category":"Informaticaconsulenten Software ontwikkeling and ontwerp",
    "sg:phone":"+32 2 463 29 00",
    "sg:postcode":"1702",
    "sg:province":"Vlaams-Brabant",
    "wof:name":"Claessens Netwerk Planning",
    "wof:placetype":"venue"
},
  "geometry": {"coordinates":[4.2624578476,50.8684768677],"type":"Point"}
}