{
  "type": "Feature",
  "properties": {
    "addr:full":"Rue D`esneux 55 Poulseur Li\u00e8ge 4171",
    "addr:housenumber":"55",
    "addr:postcode":"4171",
    "addr:street":"Rue D`Esneux",
    "iso:country":"BE",
    "sg:address":"Rue D`esneux 55",
    "sg:city":"Poulseur",
    "sg:orig_category":"Mazda Voertuigen",
    "sg:phone":"+32 4 380 40 58",
    "sg:postcode":"4171",
    "sg:province":"Li\u00e8ge",
    "wof:name":"Garage Fran\u00c7ois",
    "wof:placetype":"venue"
},
  "geometry": {"coordinates":[5.5698370934,50.5060043335],"type":"Point"}
}