{
  "type": "Feature",
  "properties": {
    "iso:country":"BE",
    "sg:address":"Village 53",
    "sg:city":"Welkenraedt/welkenraedt",
    "sg:orig_category":"Installation \u00e9lectrique r\u00e9sidentielle",
    "sg:phone":"+32 87 88 05 23",
    "sg:postcode":"4841",
    "sg:province":"Li\u00e8ge",
    "wof:name":"Jean-marie Marechal",
    "wof:placetype":"venue"
},
  "geometry": {"coordinates":[5.9307398796,50.6762619019],"type":"Point"}
}