{
  "type": "Feature",
  "properties": {
    "addr:full":"Diksmuidseweg 339 Ieper West-Vlaanderen 8904",
    "addr:housenumber":"339",
    "addr:postcode":"8904",
    "iso:country":"BE",
    "sg:address":"Diksmuidseweg 339",
    "sg:city":"Ieper",
    "sg:orig_category":"Plomberie, chauffage and installations sanitaires. Electrom\u00e9nager, t\u00e9l\u00e9visions and radios",
    "sg:phone":"+32 57 42 21 24",
    "sg:postcode":"8904",
    "sg:province":"West-Vlaanderen",
    "wof:name":"Lode Vanhaelemeersch",
    "wof:placetype":"venue"
},
  "geometry": {"coordinates":[2.8642399311,50.890411377],"type":"Point"}
}