{
  "type": "Feature",
  "properties": {
    "addr:full":"Rue Du Pont De Wandre 22 Li\u00e8ge 1 (wandre) Li\u00e8ge 4020",
    "addr:housenumber":"22;1",
    "addr:postcode":"4020",
    "addr:street":"Rue Du Pont De Wandre",
    "iso:country":"BE",
    "sg:address":"Rue Du Pont De Wandre 22",
    "sg:city":"Li\u00e8ge 1 (wandre)",
    "sg:classifiers":[
        {
            "category":"Structure",
            "subcategory":"Office Building",
            "type":"Public Place"
        }
    ],
    "sg:phone":"+32 4 362 71 61",
    "sg:postcode":"4020",
    "sg:province":"Li\u00e8ge",
    "sg:tags":[
        "roofing",
        "slate"
    ],
    "wof:name":"D'heur & Fils Sa",
    "wof:placetype":"venue"
},
  "geometry": {"coordinates":[5.6599750519,50.6698265076],"type":"Point"}
}