{
  "type": "Feature",
  "properties": {
    "iso:country":"BE",
    "sg:address":"Lambert Crickxstraat 19",
    "sg:city":"Anderlecht",
    "sg:orig_category":"Benzinestations and brandstoffen",
    "sg:phone":"+32 2 558 04 26",
    "sg:postcode":"1070",
    "sg:province":"Bruxelles-Capitale",
    "wof:name":"Cargas Info",
    "wof:placetype":"venue"
},
  "geometry": {"coordinates":[4.3371558189,50.8409996033],"type":"Point"}
}