{
  "type": "Feature",
  "properties": {
    "addr:full":"Meiboomstraat 48ba Staden West-Vlaanderen 8840",
    "addr:housenumber":"48ba",
    "addr:postcode":"8840",
    "addr:street":"Meiboomstraat",
    "iso:country":"BE",
    "sg:address":"Meiboomstraat 48ba",
    "sg:city":"Staden",
    "sg:orig_category":"Plaatsen van vloer- and muurbekleding Woningbouw",
    "sg:phone":"+32 51 20 38 87",
    "sg:postcode":"8840",
    "sg:province":"West-Vlaanderen",
    "wof:name":"Etienne Deprince",
    "wof:placetype":"venue"
},
  "geometry": {"coordinates":[3.0389480591,50.9375267029],"type":"Point"}
}