{
  "type": "Feature",
  "properties": {
    "iso:country":"BE",
    "sg:address":"Sint-anna 132ba",
    "sg:city":"Hamme",
    "sg:classifiers":[
        {
            "category":"Insurance",
            "subcategory":"Insurance Agent",
            "type":"Services"
        }
    ],
    "sg:phone":"+32 52 47 04 18",
    "sg:postcode":"9220",
    "sg:province":"Oost-Vlaanderen",
    "sg:tags":[
        "verzekeringsmakelaars",
        "expert"
    ],
    "wof:name":"Andre Vehent",
    "wof:placetype":"venue"
},
  "geometry": {"coordinates":[4.0644540787,51.0912208557],"type":"Point"}
}