{
  "type": "Feature",
  "properties": {
    "iso:country":"BE",
    "sg:address":"Hubert D'ydewallestraat 20",
    "sg:city":"Beernem",
    "sg:orig_category":"M\u00e9decins and sp\u00e9cialistes",
    "sg:phone":"+32 50 78 09 92",
    "sg:postcode":"8730",
    "sg:province":"West-Vlaanderen",
    "wof:name":"Geert Michiels",
    "wof:placetype":"venue"
},
  "geometry": {"coordinates":[3.3256149292,51.1287078857],"type":"Point"}
}