{
  "type": "Feature",
  "properties": {
    "iso:country":"BE",
    "sg:address":"Grand\u00b4place 5",
    "sg:city":"Nivelles",
    "sg:classifiers":[
        {
            "category":"Restaurant",
            "type":"Food & Drink"
        }
    ],
    "sg:phone":"+32 67 21 76 75",
    "sg:postcode":"1400",
    "sg:province":"Brabant Wallon",
    "wof:name":"Restaurant Les Arcades",
    "wof:placetype":"venue"
},
  "geometry": {"coordinates":[4.3248100281,50.597278595],"type":"Point"}
}