{
  "type": "Feature",
  "properties": {
    "iso:country":"BE",
    "sg:address":"Rue Augustin Berger 200",
    "sg:city":"Chapelle-lez-herlaimont",
    "sg:orig_category":"Groententeelt",
    "sg:phone":"+32 71 52 93 50",
    "sg:postcode":"7160",
    "sg:province":"Hainaut",
    "wof:name":"Serge Dumont",
    "wof:placetype":"venue"
},
  "geometry": {"coordinates":[4.292154789,50.4363555908],"type":"Point"}
}