{
  "type": "Feature",
  "properties": {
    "addr:full":"Chauss\u00e9e De Waterloo 1340 Bruxelles (uccle) Bruxelles-Capitale 1180",
    "addr:postcode":"1340;1180",
    "addr:street":"Chausse\u0301E De Waterloo",
    "iso:country":"BE",
    "sg:address":"Chauss\u00e9e De Waterloo 1340",
    "sg:city":"Bruxelles (uccle)",
    "sg:classifiers":[
        {
            "category":"Personal",
            "subcategory":"Shoe Repair & Shine",
            "type":"Services"
        }
    ],
    "sg:phone":"+32 2 374 87 24",
    "sg:postcode":"1180",
    "sg:province":"Bruxelles-Capitale",
    "sg:tags":[
        "shoemaker"
    ],
    "wof:name":"Cuffaro",
    "wof:placetype":"venue"
},
  "geometry": {"coordinates":[4.375026226,50.7898635864],"type":"Point"}
}