{
  "type": "Feature",
  "properties": {
    "addr:full":"Kl. Omstraat 17 Lanaken Limburg 3620",
    "addr:housenumber":"17",
    "addr:postcode":"3620",
    "addr:street":"Omstraat",
    "iso:country":"BE",
    "sg:address":"Kl. Omstraat 17",
    "sg:city":"Lanaken",
    "sg:orig_category":"Aardappelproducten Gh Groenten and fruit Gh",
    "sg:phone":"+32 89 71 45 75",
    "sg:postcode":"3620",
    "sg:province":"Limburg",
    "wof:name":"M. Jorissen",
    "wof:placetype":"venue"
},
  "geometry": {"coordinates":[5.6551351547,50.8912277222],"type":"Point"}
}