{
  "type": "Feature",
  "properties": {
    "iso:country":"BE",
    "sg:address":"Ketelbuizerstraat 132",
    "sg:city":"Lichtervelde",
    "sg:classifiers":[
        {
            "category":"Personal",
            "subcategory":"Beauty Salon",
            "type":"Services"
        }
    ],
    "sg:phone":"+32 51 72 35 10",
    "sg:postcode":"8810",
    "sg:province":"West-Vlaanderen",
    "sg:tags":[
        "lady",
        "-",
        "hairdressing"
    ],
    "wof:name":"Marie-christine",
    "wof:placetype":"venue"
},
  "geometry": {"coordinates":[3.1326019764,51.0363426208],"type":"Point"}
}