{
  "type": "Feature",
  "properties": {
    "addr:full":"Rue Du Beffroi 12 Saint-nicolas Li\u00e8ge 4420",
    "addr:housenumber":"12",
    "addr:postcode":"4420",
    "addr:street":"Rue Du Beffroi",
    "iso:country":"BE",
    "sg:address":"Rue Du Beffroi 12",
    "sg:city":"Saint-nicolas",
    "sg:orig_category":"Alimentation sp\u00e9cialis\u00e9e",
    "sg:phone":"+32 4 263 69 88",
    "sg:postcode":"4420",
    "sg:province":"Li\u00e8ge",
    "wof:name":"Maison Mondy",
    "wof:placetype":"venue"
},
  "geometry": {"coordinates":[5.5144481659,50.6401939392],"type":"Point"}
}