{
  "type": "Feature",
  "properties": {
    "iso:country":"BE",
    "sg:address":"Kaperberg 6",
    "sg:city":"Eupen",
    "sg:classifiers":[
        {
            "category":"Organizations",
            "subcategory":"Professional Association",
            "type":"Services"
        }
    ],
    "sg:phone":"+32 87 55 60 00",
    "sg:postcode":"4700",
    "sg:province":"Li\u00e8ge",
    "sg:tags":[
        "trade-union",
        "federation"
    ],
    "wof:name":"Ecolo Fraktion Im Rdg",
    "wof:placetype":"venue"
},
  "geometry": {"coordinates":[6.0399107933,50.6313552856],"type":"Point"}
}