{
  "type": "Feature",
  "properties": {
    "addr:full":"Rue Chapelle \u00e0 La Barre 99 Perwez (orbais) Brabant Wallon 1360",
    "addr:housenumber":"99",
    "addr:postcode":"1360",
    "addr:street":"Rue Chapelle A\u0300 La Barre;Wallon",
    "iso:country":"BE",
    "sg:address":"Rue Chapelle \u00e0 La Barre 99",
    "sg:city":"Perwez (orbais)",
    "sg:classifiers":[
        {
            "category":"Wholesale",
            "subcategory":"Machinery & Supplies",
            "type":"Manufacturing & Wholesale Goods"
        }
    ],
    "sg:phone":"+32 81 65 52 72",
    "sg:postcode":"1360",
    "sg:province":"Brabant Wallon",
    "sg:tags":[
        "agricultural",
        "tractor"
    ],
    "wof:name":"Fadeur Sa",
    "wof:placetype":"venue"
},
  "geometry": {"coordinates":[4.7648000717,50.6368484497],"type":"Point"}
}