{
  "type": "Feature",
  "properties": {
    "iso:country":"BE",
    "sg:address":"Steenakkerstraat 3",
    "sg:city":"Destelbergen (heusden)",
    "sg:classifiers":[
        {
            "category":"Health Services",
            "subcategory":"Dentist",
            "type":"Services"
        }
    ],
    "sg:phone":"+32 9 230 74 68",
    "sg:postcode":"9070",
    "sg:province":"Oost-Vlaanderen",
    "wof:name":"Pas P",
    "wof:placetype":"venue"
},
  "geometry": {"coordinates":[3.779845953,51.0533294678],"type":"Point"}
}