{
  "type": "Feature",
  "properties": {
    "addr:full":"Martelarenstraat 16 Aarschot Vlaams-Brabant 3200",
    "addr:housenumber":"16",
    "addr:postcode":"3200",
    "addr:street":"Martelarenstraat",
    "iso:country":"BE",
    "sg:address":"Martelarenstraat 16",
    "sg:city":"Aarschot",
    "sg:orig_category":"Foto-uitrusting Fotografen and fotostudio's Huishoudapparaten, televisies and radio's Telecommunicat",
    "sg:phone":"+32 16 56 06 29",
    "sg:postcode":"3200",
    "sg:province":"Vlaams-Brabant",
    "wof:name":"Top Camera Fotoland Mali Marcel",
    "wof:placetype":"venue"
},
  "geometry": {"coordinates":[4.8351349831,50.984336853],"type":"Point"}
}