{
  "type": "Feature",
  "properties": {
    "addr:full":"Roger Vansteenbruggestraat 72 Waregem West-Vlaanderen 8790",
    "addr:housenumber":"72",
    "addr:postcode":"8790",
    "addr:street":"Vansteenbruggestraat",
    "iso:country":"BE",
    "sg:address":"Roger Vansteenbruggestraat 72",
    "sg:city":"Waregem",
    "sg:classifiers":[
        {
            "category":"Health Services",
            "subcategory":"Health Practitioner",
            "type":"Services"
        }
    ],
    "sg:phone":"+32 56 60 28 15",
    "sg:postcode":"8790",
    "sg:province":"West-Vlaanderen",
    "sg:tags":[
        "physiotherapist"
    ],
    "wof:name":"Baetens Raoul",
    "wof:placetype":"venue"
},
  "geometry": {"coordinates":[3.4185659885,50.8931083679],"type":"Point"}
}