{
  "type": "Feature",
  "properties": {
    "addr:full":"Zammelseweg 90 Geel Antwerpen 2440",
    "addr:housenumber":"90",
    "addr:postcode":"2440",
    "addr:street":"Zammelseweg",
    "iso:country":"BE",
    "sg:address":"Zammelseweg 90",
    "sg:city":"Geel",
    "sg:classifiers":[
        {
            "category":"Health Services",
            "subcategory":"Health Practitioner",
            "type":"Services"
        }
    ],
    "sg:phone":"+32 14 86 11 24",
    "sg:postcode":"2440",
    "sg:province":"Antwerpen",
    "sg:tags":[
        "psychologist"
    ],
    "wof:name":"Thijs E",
    "wof:placetype":"venue"
},
  "geometry": {"coordinates":[4.964922905,51.1036720276],"type":"Point"}
}