{
  "type": "Feature",
  "properties": {
    "addr:full":"Hofeinde 51 Vosselaar Antwerpen 2350",
    "addr:housenumber":"51",
    "addr:postcode":"2350",
    "addr:street":"Hofeinde",
    "iso:country":"BE",
    "sg:address":"Hofeinde 51",
    "sg:city":"Vosselaar",
    "sg:orig_category":"Woningbouw",
    "sg:phone":"+32 14 61 69 30",
    "sg:postcode":"2350",
    "sg:province":"Antwerpen",
    "wof:name":"Franciscus Lavrijssen",
    "wof:placetype":"venue"
},
  "geometry": {"coordinates":[4.8830838203,51.3167648315],"type":"Point"}
}