{
  "type": "Feature",
  "properties": {
    "iso:country":"BE",
    "sg:address":"Dendermondesteenweg 616",
    "sg:city":"Destelbergen",
    "sg:classifiers":[
        {
            "category":"Organizations",
            "subcategory":"Professional Association",
            "type":"Services"
        }
    ],
    "sg:phone":"+32 9 229 37 51",
    "sg:postcode":"9070",
    "sg:province":"Oost-Vlaanderen",
    "sg:tags":[
        "trade-union",
        "federation"
    ],
    "wof:name":"Veva Vzw",
    "wof:placetype":"venue"
},
  "geometry": {"coordinates":[3.8150889874,51.0583229065],"type":"Point"}
}