{
  "type": "Feature",
  "properties": {
    "iso:country":"BE",
    "sg:address":"Rue Sinton 16",
    "sg:city":"Fosses-la-ville",
    "sg:orig_category":"Installatie van houten of kunststof schrijnwerk Tweedehandsgoederen",
    "sg:phone":"+32 71 71 16 68",
    "sg:postcode":"5070",
    "sg:province":"Namur",
    "wof:name":"Menuiserie Armand Eischen",
    "wof:placetype":"venue"
},
  "geometry": {"coordinates":[4.7013778687,50.3974571228],"type":"Point"}
}