{
  "type": "Feature",
  "properties": {
    "iso:country":"BE",
    "sg:address":"Vlierbeekstraat 19",
    "sg:city":"Oud-heverlee",
    "sg:orig_category":"Dakwerken Installatie van houten of kunststof schrijnwerk",
    "sg:phone":"+32 16 40 16 60",
    "sg:postcode":"3052",
    "sg:province":"Vlaams-Brabant",
    "wof:name":"Adams",
    "wof:placetype":"venue"
},
  "geometry": {"coordinates":[4.7103271484,50.830997467],"type":"Point"}
}