{
  "type": "Feature",
  "properties": {
    "addr:full":"Hockelbach 53 Welkenraedt Li\u00e8ge 4841",
    "addr:housenumber":"53",
    "addr:postcode":"4841",
    "addr:street":"Hockelbach",
    "iso:country":"BE",
    "sg:address":"Hockelbach 53",
    "sg:city":"Welkenraedt",
    "sg:orig_category":"Bruids- and ceremoniekledij",
    "sg:phone":"+32 87 44 63 35",
    "sg:postcode":"4841",
    "sg:province":"Li\u00e8ge",
    "wof:name":"La Chiffonni\u00c8re",
    "wof:placetype":"venue"
},
  "geometry": {"coordinates":[5.9133119583,50.660243988],"type":"Point"}
}