{
  "type": "Feature",
  "properties": {
    "addr:full":"Muizenheuvelstraat 47 Ranst (oelegem) Antwerpen 2520",
    "addr:housenumber":"47",
    "addr:postcode":"2520",
    "addr:street":"Muizenheuvelstraat",
    "iso:country":"BE",
    "sg:address":"Muizenheuvelstraat 47",
    "sg:city":"Ranst (oelegem)",
    "sg:classifiers":[
        {
            "category":"Personal",
            "subcategory":"Beauty Salon",
            "type":"Services"
        }
    ],
    "sg:phone":"+32 3 383 57 85",
    "sg:postcode":"2520",
    "sg:province":"Antwerpen",
    "sg:tags":[
        "lady",
        "-",
        "hairdressing"
    ],
    "wof:name":"Lieve",
    "wof:placetype":"venue"
},
  "geometry": {"coordinates":[4.5938000679,51.2157173157],"type":"Point"}
}