{
  "type": "Feature",
  "properties": {
    "addr:full":"Zuurstraat 153 Ninove Oost-Vlaanderen 9404",
    "addr:housenumber":"153",
    "addr:postcode":"9404",
    "addr:street":"Zuurstraat",
    "iso:country":"BE",
    "sg:address":"Zuurstraat 153",
    "sg:city":"Ninove",
    "sg:orig_category":"Plaatsen van vloer- and muurbekleding Schilders Verlichting and huishoudartikelen",
    "sg:phone":"+32 54 50 12 28",
    "sg:postcode":"9404",
    "sg:province":"Oost-Vlaanderen",
    "wof:name":"Vanderpoorten W. & Zn",
    "wof:placetype":"venue"
},
  "geometry": {"coordinates":[3.9315989017,50.8394584656],"type":"Point"}
}