{
  "type": "Feature",
  "properties": {
    "iso:country":"BE",
    "sg:address":"Ingelmunstersteenweg 39",
    "sg:city":"Oostrozebeke",
    "sg:orig_category":"Plomberie, chauffage and installations sanitaires",
    "sg:phone":"+32 56 66 73 10",
    "sg:postcode":"8780",
    "sg:province":"West-Vlaanderen",
    "wof:name":"Lambert-c.v.-san",
    "wof:placetype":"venue"
},
  "geometry": {"coordinates":[3.3207790852,50.9196548462],"type":"Point"}
}