{
  "type": "Feature",
  "properties": {
    "iso:country":"BE",
    "sg:address":"Rue De Valenciennes 388",
    "sg:city":"Boussu",
    "sg:classifiers":[
        {
            "category":"Freight",
            "type":"Transportation"
        }
    ],
    "sg:phone":"+32 65 78 38 26",
    "sg:postcode":"7300",
    "sg:province":"Hainaut",
    "sg:tags":[
        "express",
        "transport"
    ],
    "wof:name":"Transports Prevot-delannoy Sprl",
    "wof:placetype":"venue"
},
  "geometry": {"coordinates":[3.8089179993,50.4325408936],"type":"Point"}
}