{
  "type": "Feature",
  "properties": {
    "iso:country":"BE",
    "sg:address":"Goudvinkenlaan 11",
    "sg:city":"De Pinte",
    "sg:classifiers":[
        {
            "category":"Communications",
            "subcategory":"Film & Video Production",
            "type":"Services"
        }
    ],
    "sg:phone":"+32 9 282 73 37",
    "sg:postcode":"9840",
    "sg:province":"Oost-Vlaanderen",
    "sg:tags":[
        "sound",
        "recording",
        "studio"
    ],
    "wof:name":"Heaven Eleven Sound Production (the)",
    "wof:placetype":"venue"
},
  "geometry": {"coordinates":[3.6368880272,50.9890060425],"type":"Point"}
}