{
  "type": "Feature",
  "properties": {
    "addr:full":"Avenue Reine Astrid 1 Huy Li\u00e8ge 4500",
    "addr:housenumber":"1",
    "addr:postcode":"4500",
    "addr:street":"Avenue Reine Astrid",
    "iso:country":"BE",
    "sg:address":"Avenue Reine Astrid 1",
    "sg:city":"Huy",
    "sg:orig_category":"Paramedische behandelingen",
    "sg:phone":"+32 85 21 26 64",
    "sg:postcode":"4500",
    "sg:province":"Li\u00e8ge",
    "wof:name":"P. Guyaux",
    "wof:placetype":"venue"
},
  "geometry": {"coordinates":[5.2294888496,50.525352478],"type":"Point"}
}