{
  "type": "Feature",
  "properties": {
    "iso:country":"BE",
    "sg:address":"Kattewegel 8",
    "sg:city":"Aalter",
    "sg:orig_category":"Herstelling and restauratie van meubelen",
    "sg:phone":"+32 9 374 60 48",
    "sg:postcode":"9880",
    "sg:province":"Oost-Vlaanderen",
    "wof:name":"Huis Van Den Steen",
    "wof:placetype":"venue"
},
  "geometry": {"coordinates":[3.4305450916,51.0680389404],"type":"Point"}
}