{
  "type": "Feature",
  "properties": {
    "addr:full":"Niklaas Desparsstraat 8 Brugge West-Vlaanderen 8000",
    "addr:housenumber":"8",
    "addr:postcode":"8000",
    "addr:street":"Niklaas Desparsstraat",
    "iso:country":"BE",
    "sg:address":"Niklaas Desparsstraat 8",
    "sg:city":"Brugge",
    "sg:classifiers":[
        {
            "category":"Shopping",
            "subcategory":"Clothing, Apparel, & Fashions",
            "type":"Retail Goods"
        }
    ],
    "sg:phone":"+32 50 33 80 66",
    "sg:postcode":"8000",
    "sg:province":"West-Vlaanderen",
    "sg:tags":[
        "boutique"
    ],
    "wof:name":"Ann C",
    "wof:placetype":"venue"
},
  "geometry": {"coordinates":[3.2238938808,51.2097892761],"type":"Point"}
}