{
  "type": "Feature",
  "properties": {
    "iso:country":"BE",
    "sg:address":"Larstraat 26",
    "sg:city":"Menen",
    "sg:orig_category":"Hout and afgeleiden Gh IJzerwaren, bouw- and verfmaterialen",
    "sg:phone":"+32 56 41 26 19",
    "sg:postcode":"8930",
    "sg:province":"West-Vlaanderen",
    "wof:name":"Transport En Handel G B L",
    "wof:placetype":"venue"
},
  "geometry": {"coordinates":[3.1943130493,50.7747154236],"type":"Point"}
}