{
  "type": "Feature",
  "properties": {
    "iso:country":"BE",
    "sg:address":"Rozenstraat 27",
    "sg:city":"Halen",
    "sg:orig_category":"Installation de menuiserie m\u00e9tallique",
    "sg:phone":"+32 475 39 74 91",
    "sg:postcode":"3545",
    "sg:province":"Limburg",
    "wof:name":"Gelade",
    "wof:placetype":"venue"
},
  "geometry": {"coordinates":[5.0662908554,50.9466896057],"type":"Point"}
}