{
  "type": "Feature",
  "properties": {
    "iso:country":"BE",
    "sg:address":"Voorhout 20",
    "sg:city":"Stekene (kemzeke)",
    "sg:classifiers":[
        {
            "category":"Building & Trades",
            "subcategory":"Plumbing",
            "type":"Services"
        }
    ],
    "sg:phone":"+32 3 789 29 76",
    "sg:postcode":"9190",
    "sg:province":"Oost-Vlaanderen",
    "sg:tags":[
        "repair",
        "mainten",
        "-",
        "central",
        "heating"
    ],
    "wof:name":"Van Belleghem Ch",
    "wof:placetype":"venue"
},
  "geometry": {"coordinates":[4.0700001717,51.2150115967],"type":"Point"}
}