{
  "type": "Feature",
  "properties": {
    "iso:country":"BE",
    "sg:address":"Stationsstraat 1",
    "sg:city":"Blankenberge",
    "sg:orig_category":"Mat\u00e9riel de T\u00e9l\u00e9communication",
    "sg:phone":"+32 800 22 800",
    "sg:postcode":"8370",
    "sg:province":"West-Vlaanderen",
    "wof:name":"Teleboetiek",
    "wof:placetype":"venue"
},
  "geometry": {"coordinates":[3.1331779957,51.3136062622],"type":"Point"}
}