{
  "type": "Feature",
  "properties": {
    "iso:country":"BE",
    "sg:address":"Koningin Astridlaan 4",
    "sg:city":"Brugge",
    "sg:orig_category":"Enseignement secondaire technique and professionnel",
    "sg:phone":"+32 50 40 45 00",
    "sg:postcode":"8200",
    "sg:province":"West-Vlaanderen",
    "wof:name":"Immaculata-instituut",
    "wof:placetype":"venue"
},
  "geometry": {"coordinates":[3.2470510006,51.2003479004],"type":"Point"}
}