{
  "type": "Feature",
  "properties": {
    "addr:full":"Kouterstraat 90 Zele Oost-Vlaanderen 9240",
    "addr:housenumber":"90",
    "addr:postcode":"9240",
    "addr:street":"Kouterstraat",
    "iso:country":"BE",
    "sg:address":"Kouterstraat 90",
    "sg:city":"Zele",
    "sg:classifiers":[
        {
            "category":"Arena",
            "subcategory":"Sports Club",
            "type":"Entertainment"
        }
    ],
    "sg:phone":"+32 52 44 46 09",
    "sg:postcode":"9240",
    "sg:province":"Oost-Vlaanderen",
    "sg:tags":[
        "de"
    ],
    "wof:name":"Zele B.b.c.",
    "wof:placetype":"venue"
},
  "geometry": {"coordinates":[4.029613018,51.0654525757],"type":"Point"}
}