{
  "type": "Feature",
  "properties": {
    "iso:country":"BE",
    "sg:address":"Rue De La Semois 36b",
    "sg:city":"Arlon",
    "sg:classifiers":[
        {
            "category":"Brewery",
            "type":"Food & Drink"
        }
    ],
    "sg:phone":"+32 63 44 68 14",
    "sg:postcode":"6700",
    "sg:province":"Luxembourg",
    "wof:name":"Arel Bi\u00e8res",
    "wof:placetype":"venue"
},
  "geometry": {"coordinates":[5.8097000122,49.6786117554],"type":"Point"}
}