{
  "type": "Feature",
  "properties": {
    "iso:country":"BE",
    "sg:address":"Chauss\u00c9e D'ixelles 27",
    "sg:city":"Elsene/ixelles",
    "sg:orig_category":"Assurances. Bureaux de poste",
    "sg:phone":"+32 2 511 98 90",
    "sg:postcode":"1050",
    "sg:province":"Bruxelles-Capitale",
    "wof:name":"La Poste",
    "wof:placetype":"venue"
},
  "geometry": {"coordinates":[4.3621020317,50.8371505737],"type":"Point"}
}