{
  "type": "Feature",
  "properties": {
    "addr:full":"172 Berchemstraat 9690 Kluisbergen 172",
    "addr:housenumber":"172;172",
    "addr:postcode":"9690",
    "addr:street":"Berchemstraat",
    "iso:country":"BE",
    "sg:address":"172",
    "sg:city":"Berchemstraat 9690 Kluisbergen",
    "sg:classifiers":[
        {
            "category":"Manufacturing",
            "subcategory":"Rubber & Plastics",
            "type":"Manufacturing & Wholesale Goods"
        }
    ],
    "sg:phone":"+32 55 38 94 44",
    "sg:postcode":"172",
    "wof:name":"Van De Wiele Nv",
    "wof:placetype":"venue"
},
  "geometry": {"coordinates":[3.5223219395,50.7954216003],"type":"Point"}
}