{
  "type": "Feature",
  "properties": {
    "addr:full":"Rue Haute 56 Vise Li\u00e8ge 4600",
    "addr:housenumber":"56",
    "addr:postcode":"4600",
    "addr:street":"Rue Haute",
    "iso:country":"BE",
    "sg:address":"Rue Haute 56",
    "sg:city":"Vise",
    "sg:orig_category":"Herstelling leer and schoeisel Herstellingswinkels voor diverse persoonlijke and huishoudartikelen",
    "sg:phone":"+32 4 379 41 86",
    "sg:postcode":"4600",
    "sg:province":"Li\u00e8ge",
    "wof:name":"Mister Minit",
    "wof:placetype":"venue"
},
  "geometry": {"coordinates":[5.6963801384,50.7337417603],"type":"Point"}
}