{
  "type": "Feature",
  "properties": {
    "addr:full":"Burgstraat 100-102 Gent Oost-Vlaanderen 9000",
    "addr:housenumber":"100-102",
    "addr:postcode":"9000",
    "addr:street":"Burgstraat;Oost-Vlaanderen",
    "iso:country":"BE",
    "sg:address":"Burgstraat 100-102",
    "sg:city":"Gent",
    "sg:classifiers":[
        {
            "category":"Shopping",
            "subcategory":"Shoes",
            "type":"Retail Goods"
        }
    ],
    "sg:phone":"+32 9 225 30 17",
    "sg:postcode":"9000",
    "sg:province":"Oost-Vlaanderen",
    "sg:tags":[
        "slipper",
        "-"
    ],
    "wof:name":"Claeys-bauwens",
    "wof:placetype":"venue"
},
  "geometry": {"coordinates":[3.7161951065,51.056438446],"type":"Point"}
}