{
  "type": "Feature",
  "properties": {
    "addr:full":"Chauss\u00e9e De Mons 52 Soignies Hainaut 7060",
    "addr:housenumber":"52",
    "addr:postcode":"7060",
    "addr:street":"Chausse\u0301E De Mons",
    "iso:country":"BE",
    "sg:address":"Chauss\u00e9e De Mons 52",
    "sg:city":"Soignies",
    "sg:classifiers":[
        {
            "category":"Communications",
            "subcategory":"Film & Video Production",
            "type":"Services"
        }
    ],
    "sg:phone":"+32 67 34 11 86",
    "sg:postcode":"7060",
    "sg:province":"Hainaut",
    "sg:tags":[
        "hiring",
        "-"
    ],
    "wof:name":"Vid\u00e9o Club De La Ch\u00e9e De Mons",
    "wof:placetype":"venue"
},
  "geometry": {"coordinates":[4.0653882027,50.5695838928],"type":"Point"}
}