{
  "type": "Feature",
  "properties": {
    "addr:full":"Stadspoortstraat 7 Herentals Antwerpen 2200",
    "addr:housenumber":"7",
    "addr:postcode":"2200",
    "addr:street":"Stadspoortstraat",
    "iso:country":"BE",
    "sg:address":"Stadspoortstraat 7",
    "sg:city":"Herentals",
    "sg:classifiers":[
        {
            "category":"Fast Food",
            "type":"Food & Drink"
        }
    ],
    "sg:phone":"+32 14 22 05 54",
    "sg:postcode":"2200",
    "sg:province":"Antwerpen",
    "sg:tags":[
        "\u00c0",
        "emporter",
        "restaurants"
    ],
    "wof:name":"Frituur Quiq",
    "wof:placetype":"venue"
},
  "geometry": {"coordinates":[4.8395981789,51.1734275818],"type":"Point"}
}