{
  "type": "Feature",
  "properties": {
    "addr:full":"Auberlaan 11 Anderlecht/anderlecht Bruxelles-Capitale 1070",
    "addr:housenumber":"11",
    "addr:postcode":"1070",
    "addr:street":"Auberlaan",
    "iso:country":"BE",
    "sg:address":"Auberlaan 11",
    "sg:city":"Anderlecht/anderlecht",
    "sg:orig_category":"Herstellingswinkels voor diverse persoonlijke and huishoudartikelen",
    "sg:phone":"+32 2 524 04 63",
    "sg:postcode":"1070",
    "sg:province":"Bruxelles-Capitale",
    "wof:name":"Couture Moda",
    "wof:placetype":"venue"
},
  "geometry": {"coordinates":[4.3121509552,50.8389434814],"type":"Point"}
}