{
  "type": "Feature",
  "properties": {
    "addr:full":"Rue Saint-joseph 92 Couvin Namur 5660",
    "addr:housenumber":"92",
    "addr:postcode":"5660",
    "addr:street":"Rue Saint-Joseph",
    "iso:country":"BE",
    "sg:address":"Rue Saint-joseph 92",
    "sg:city":"Couvin",
    "sg:orig_category":"Sportclubs Sportterreinen and installaties behalve sportcentra",
    "sg:phone":"+32 60 31 15 50",
    "sg:postcode":"5660",
    "sg:province":"Namur",
    "wof:name":"E.s. Petigny-frasnes",
    "wof:placetype":"venue"
},
  "geometry": {"coordinates":[4.5015912056,50.0753669739],"type":"Point"}
}