{
  "type": "Feature",
  "properties": {
    "addr:full":"Rue Ernest Solvay 238 Morlanwelz Hainaut 7141",
    "addr:housenumber":"238",
    "addr:postcode":"7141",
    "addr:street":"Rue Ernest Solvay",
    "iso:country":"BE",
    "sg:address":"Rue Ernest Solvay 238",
    "sg:city":"Morlanwelz",
    "sg:orig_category":"Woningbouw",
    "sg:phone":"+32 64 44 86 73",
    "sg:postcode":"7141",
    "sg:province":"Hainaut",
    "wof:name":"Camille Potvin",
    "wof:placetype":"venue"
},
  "geometry": {"coordinates":[4.2573199272,50.4501609802],"type":"Point"}
}