{
  "type": "Feature",
  "properties": {
    "iso:country":"BE",
    "sg:address":"Bredabaan 431",
    "sg:city":"Brasschaat",
    "sg:orig_category":"Gespecialiseerde residenti\u00eble bouw Installatie van metalen schrijnwerk",
    "sg:phone":"+32 3 651 30 41",
    "sg:postcode":"2930",
    "sg:province":"Antwerpen",
    "wof:name":"Ultrax",
    "wof:placetype":"venue"
},
  "geometry": {"coordinates":[4.4939899445,51.291759491],"type":"Point"}
}