{
  "type": "Feature",
  "properties": {
    "iso:country":"BE",
    "sg:address":"Chauss\u00c9e De Huy 47 A",
    "sg:city":"Chaumont-gistoux",
    "sg:orig_category":"Articles de jardin. Jardinage. Plomberie, chauffage and installations sanitaires. Installation de pi",
    "sg:phone":"+32 10 24 44 32",
    "sg:postcode":"1325",
    "sg:province":"Brabant Wallon",
    "wof:name":"Les Jardins De Valmont",
    "wof:placetype":"venue"
},
  "geometry": {"coordinates":[4.6867628098,50.6901473999],"type":"Point"}
}