{
  "type": "Feature",
  "properties": {
    "iso:country":"BE",
    "sg:address":"Dalstraat 10",
    "sg:city":"Mol",
    "sg:orig_category":"Kruideniers SMEEDWERK, METAALBEWERKING AND POEDERMETALLURGIE",
    "sg:phone":"+32 14 31 88 75",
    "sg:postcode":"2400",
    "sg:province":"Antwerpen",
    "wof:name":"Breugelmans",
    "wof:placetype":"venue"
},
  "geometry": {"coordinates":[5.1373548508,51.2028884888],"type":"Point"}
}