{
  "type": "Feature",
  "properties": {
    "iso:country":"BE",
    "sg:address":"Herentalsesteenweg 55",
    "sg:city":"Lichtaart",
    "sg:classifiers":[
        {
            "category":"Restaurant",
            "type":"Food & Drink"
        }
    ],
    "sg:phone":"+32 14 55 69 65",
    "sg:postcode":"2460",
    "sg:province":"Antwerpen",
    "wof:name":"Restaurant Da Pino",
    "wof:placetype":"venue"
},
  "geometry": {"coordinates":[4.9094781876,51.2170791626],"type":"Point"}
}