{
  "type": "Feature",
  "properties": {
    "addr:full":"Suikerrui 22 Antwerpen Antwerpen 2000",
    "addr:housenumber":"22",
    "addr:postcode":"2000",
    "addr:street":"Suikerrui",
    "iso:country":"BE",
    "sg:address":"Suikerrui 22",
    "sg:city":"Antwerpen",
    "sg:classifiers":[
        {
            "category":"Manufacturing",
            "subcategory":"Glass & Minerals",
            "type":"Manufacturing & Wholesale Goods"
        }
    ],
    "sg:phone":"+32 3 233 29 67",
    "sg:postcode":"2000",
    "sg:province":"Antwerpen",
    "sg:tags":[
        "precious",
        "stone"
    ],
    "wof:name":"Gouden Ram (de)",
    "wof:placetype":"venue"
},
  "geometry": {"coordinates":[4.3982601166,51.2208137512],"type":"Point"}
}