{
  "type": "Feature",
  "properties": {
    "iso:country":"BE",
    "sg:address":"Kerkstraat 79",
    "sg:city":"Lille",
    "sg:classifiers":[
        {
            "category":"Home & Garden",
            "subcategory":"Garden Supply",
            "type":"Retail Goods"
        }
    ],
    "sg:phone":"+32 14 88 04 03",
    "sg:postcode":"2275",
    "sg:province":"Antwerpen",
    "sg:tags":[
        "seed",
        "-"
    ],
    "wof:name":"Van Eyndt J Bvba",
    "wof:placetype":"venue"
},
  "geometry": {"coordinates":[4.817358017,51.2372894287],"type":"Point"}
}