{
  "type": "Feature",
  "properties": {
    "addr:full":"Grensstraat 41 Zandhoven (pulle) Antwerpen 2243",
    "addr:housenumber":"41",
    "addr:postcode":"2243",
    "addr:street":"Grensstraat",
    "iso:country":"BE",
    "sg:address":"Grensstraat 41",
    "sg:city":"Zandhoven (pulle)",
    "sg:classifiers":[
        {
            "category":"Retail",
            "subcategory":"Auto Repair",
            "type":"Services"
        }
    ],
    "sg:phone":"+32 3 484 50 39",
    "sg:postcode":"2243",
    "sg:province":"Antwerpen",
    "sg:tags":[
        "garage"
    ],
    "wof:name":"Struyfs",
    "wof:placetype":"venue"
},
  "geometry": {"coordinates":[4.7150168419,51.2024841309],"type":"Point"}
}