{
  "type": "Feature",
  "properties": {
    "addr:full":"Haachtsesteenweg 48 Machelen (diegem) Vlaams-Brabant 1831",
    "addr:housenumber":"48",
    "addr:postcode":"1831",
    "addr:street":"Haachtsesteenweg",
    "iso:country":"BE",
    "sg:address":"Haachtsesteenweg 48",
    "sg:city":"Machelen (diegem)",
    "sg:classifiers":[
        {
            "category":"Professional",
            "subcategory":"Computer Services",
            "type":"Services"
        }
    ],
    "sg:phone":"+32 2 714 08 00",
    "sg:postcode":"1831",
    "sg:province":"Vlaams-Brabant",
    "sg:tags":[
        "repair",
        "processing",
        "-",
        "maintenance",
        "data"
    ],
    "wof:name":"Everaert Sa",
    "wof:placetype":"venue"
},
  "geometry": {"coordinates":[4.4376878738,50.8989257812],"type":"Point"}
}