{
  "type": "Feature",
  "properties": {
    "iso:country":"BE",
    "sg:address":"Hageveldstraat 47ba",
    "sg:city":"Denderleeuw",
    "sg:orig_category":"Installation de menuiserie en bois and plastique",
    "sg:phone":"+32 53 66 77 80",
    "sg:postcode":"9470",
    "sg:province":"Oost-Vlaanderen",
    "wof:name":"Herman Pede",
    "wof:placetype":"venue"
},
  "geometry": {"coordinates":[4.0744819641,50.8733482361],"type":"Point"}
}