{
  "type": "Feature",
  "properties": {
    "addr:full":"Generaal Lemanlaan 70 Brugge (assebroek) West-Vlaanderen 8310",
    "addr:housenumber":"70",
    "addr:postcode":"8310",
    "addr:street":"Generaal Lemanlaan",
    "iso:country":"BE",
    "sg:address":"Generaal Lemanlaan 70",
    "sg:city":"Brugge (assebroek)",
    "sg:classifiers":[
        {
            "category":"Professional",
            "subcategory":"Testing Lab",
            "type":"Services"
        }
    ],
    "sg:phone":"+32 50 37 23 03",
    "sg:postcode":"8310",
    "sg:province":"West-Vlaanderen",
    "sg:tags":[
        "chemist"
    ],
    "wof:name":"Maertens G",
    "wof:placetype":"venue"
},
  "geometry": {"coordinates":[3.237844944,51.2020263672],"type":"Point"}
}