{
  "type": "Feature",
  "properties": {
    "iso:country":"BE",
    "sg:address":"Langendam 86",
    "sg:city":"Evergem",
    "sg:orig_category":"Bloemen and planten Gh Boomkwekerijen",
    "sg:phone":"+32 9 357 57 64",
    "sg:postcode":"9940",
    "sg:province":"Oost-Vlaanderen",
    "wof:name":"Declerq Willy & Zn",
    "wof:placetype":"venue"
},
  "geometry": {"coordinates":[3.6556758881,51.1389923096],"type":"Point"}
}