{
  "type": "Feature",
  "properties": {
    "addr:full":"Paleizenstr.over Bruggen 446ba Brussel/bruxelles Bruxelles-Capitale 1020",
    "addr:postcode":"1020",
    "addr:street":"446Ba",
    "iso:country":"BE",
    "sg:address":"Paleizenstr.over Bruggen 446ba",
    "sg:city":"Brussel/bruxelles",
    "sg:orig_category":"Diverse zakelijke dienstverlening",
    "sg:phone":"+32 2 479 35 76",
    "sg:postcode":"1020",
    "sg:province":"Bruxelles-Capitale",
    "wof:name":"Fran\u00c7ois Carton",
    "wof:placetype":"venue"
},
  "geometry": {"coordinates":[4.3601927757,50.8767051697],"type":"Point"}
}