{
  "type": "Feature",
  "properties": {
    "addr:full":"Avenue Sur Cortil 57 Esneux Li\u00e8ge 4130",
    "addr:housenumber":"57",
    "addr:postcode":"4130",
    "addr:street":"Avenue;Cortil",
    "iso:country":"BE",
    "sg:address":"Avenue Sur Cortil 57",
    "sg:city":"Esneux",
    "sg:orig_category":"Architectes",
    "sg:phone":"+32 4 388 17 52",
    "sg:postcode":"4130",
    "sg:province":"Li\u00e8ge",
    "wof:name":"Dispa Jean-marc",
    "wof:placetype":"venue"
},
  "geometry": {"coordinates":[5.5978422165,50.5624580383],"type":"Point"}
}