{
  "type": "Feature",
  "properties": {
    "addr:full":"Bredabaan 424 Wuustwezel Antwerpen 2990",
    "addr:housenumber":"424",
    "addr:postcode":"2990",
    "addr:street":"Bredabaan",
    "iso:country":"BE",
    "sg:address":"Bredabaan 424",
    "sg:city":"Wuustwezel",
    "sg:orig_category":"Meubles D\u00e9taillants, Am\u00e9nagement de B\u00e2timents et de Cuisines",
    "sg:phone":"+32 3 669 63 00",
    "sg:postcode":"2990",
    "sg:province":"Antwerpen",
    "wof:name":"Meubelcharme",
    "wof:placetype":"venue"
},
  "geometry": {"coordinates":[4.5928769112,51.3912849426],"type":"Point"}
}