{
  "type": "Feature",
  "properties": {
    "iso:country":"BE",
    "sg:address":"Tombergstraat 38",
    "sg:city":"Tielt-winge",
    "sg:orig_category":"Reclamebureaus",
    "sg:phone":"+32 16 63 27 30",
    "sg:postcode":"3390",
    "sg:province":"Vlaams-Brabant",
    "wof:name":"Agrippa",
    "wof:placetype":"venue"
},
  "geometry": {"coordinates":[4.946890831,50.9414634705],"type":"Point"}
}