{
  "type": "Feature",
  "properties": {
    "addr:full":"Kiewitheide 34 Lanaken Limburg 3620",
    "addr:housenumber":"34",
    "addr:postcode":"3620",
    "addr:street":"Kiewitheide",
    "iso:country":"BE",
    "sg:address":"Kiewitheide 34",
    "sg:city":"Lanaken",
    "sg:orig_category":"Artsen and specialisten",
    "sg:phone":"+32 89 71 24 74",
    "sg:postcode":"3620",
    "sg:province":"Limburg",
    "wof:name":"Roberto Roddi",
    "wof:placetype":"venue"
},
  "geometry": {"coordinates":[5.6249289513,50.8965148926],"type":"Point"}
}