{
  "type": "Feature",
  "properties": {
    "addr:full":"Leopoldstraat 131 Duffel Antwerpen 2570",
    "addr:housenumber":"131",
    "addr:postcode":"2570",
    "addr:street":"Leopoldstraat",
    "iso:country":"BE",
    "sg:address":"Leopoldstraat 131",
    "sg:city":"Duffel",
    "sg:orig_category":"Binnenhuisarchitecten",
    "sg:phone":"+32 15 31 46 71",
    "sg:postcode":"2570",
    "sg:province":"Antwerpen",
    "wof:name":"G.k.s.",
    "wof:placetype":"venue"
},
  "geometry": {"coordinates":[4.5058908463,51.0986022949],"type":"Point"}
}