{
  "type": "Feature",
  "properties": {
    "addr:full":"Rue De L'arsenal 15 Namur Namur 5000",
    "addr:housenumber":"15",
    "addr:postcode":"5000",
    "addr:street":"Rue De L'Arsenal",
    "iso:country":"BE",
    "sg:address":"Rue De L'arsenal 15",
    "sg:city":"Namur",
    "sg:classifiers":[
        {
            "category":"Professional",
            "subcategory":"Lawyer & Legal Services",
            "type":"Services"
        }
    ],
    "sg:phone":"+32 81 22 00 00",
    "sg:postcode":"5000",
    "sg:province":"Namur",
    "wof:name":"Kerkhofs P",
    "wof:placetype":"venue"
},
  "geometry": {"coordinates":[4.8583340645,50.464214325],"type":"Point"}
}