{
  "type": "Feature",
  "properties": {
    "iso:country":"BE",
    "sg:address":"Bergstraat 49bb",
    "sg:city":"Heist-op-den-berg",
    "sg:orig_category":"Chaussures. Maroquinerie and articles de voyage",
    "sg:phone":"+32 15 24 42 03",
    "sg:postcode":"2220",
    "sg:province":"Antwerpen",
    "wof:name":"Piampiani",
    "wof:placetype":"venue"
},
  "geometry": {"coordinates":[4.723277092,51.0757522583],"type":"Point"}
}