{
  "type": "Feature",
  "properties": {
    "addr:full":"Scheps 21 Balen Antwerpen 2490",
    "addr:housenumber":"21",
    "addr:postcode":"2490",
    "addr:street":"Scheps",
    "iso:country":"BE",
    "sg:address":"Scheps 21",
    "sg:city":"Balen",
    "sg:classifiers":[
        {
            "category":"Food & Beverages",
            "subcategory":"Dairy",
            "type":"Retail Goods"
        }
    ],
    "sg:phone":"+32 14 81 50 90",
    "sg:postcode":"2490",
    "sg:province":"Antwerpen",
    "sg:tags":[
        "product",
        "-"
    ],
    "wof:name":"Willekens J P",
    "wof:placetype":"venue"
},
  "geometry": {"coordinates":[5.1772751808,51.1575508118],"type":"Point"}
}