{
  "type": "Feature",
  "properties": {
    "iso:country":"BE",
    "sg:address":"Leegstraat 264",
    "sg:city":"Oostrozebeke",
    "sg:orig_category":"Loodgieterij, verwarming and sanitaire installaties",
    "sg:phone":"+32 56 66 98 42",
    "sg:postcode":"8780",
    "sg:province":"West-Vlaanderen",
    "wof:name":"Patrick Maes",
    "wof:placetype":"venue"
},
  "geometry": {"coordinates":[3.3048288822,50.9149513245],"type":"Point"}
}