{
  "type": "Feature",
  "properties": {
    "iso:country":"BE",
    "sg:address":"Rue Lonhienne 26b1",
    "sg:city":"Li\u00c8ge",
    "sg:orig_category":"Advocaten and juridische adviseurs",
    "sg:phone":"+32 4 221 25 58",
    "sg:postcode":"4000",
    "sg:province":"Li\u00e8ge",
    "wof:name":"Michel Reenaers",
    "wof:placetype":"venue"
},
  "geometry": {"coordinates":[5.5649528503,50.6419487],"type":"Point"}
}