{
  "type": "Feature",
  "properties": {
    "iso:country":"BE",
    "sg:address":"Torhoutsesteenweg 80",
    "sg:city":"Oostende",
    "sg:classifiers":[
        {
            "category":"Food & Beverages",
            "subcategory":"Groceries & Convenience Stores",
            "type":"Retail Goods"
        }
    ],
    "sg:phone":"+32 59 70 26 07",
    "sg:postcode":"8400",
    "sg:province":"West-Vlaanderen",
    "sg:tags":[
        "grocer"
    ],
    "wof:name":"A B C",
    "wof:placetype":"venue"
},
  "geometry": {"coordinates":[2.9092569351,51.2244567871],"type":"Point"}
}