{
  "type": "Feature",
  "properties": {
    "addr:full":"Hogeweg 5 Brugge West-Vlaanderen 8200",
    "addr:housenumber":"5",
    "addr:postcode":"8200",
    "addr:street":"Hogeweg",
    "iso:country":"BE",
    "sg:address":"Hogeweg 5",
    "sg:city":"Brugge",
    "sg:orig_category":"H\u00f4tels",
    "sg:phone":"+32 50 31 26 77",
    "sg:postcode":"8200",
    "sg:province":"West-Vlaanderen",
    "wof:name":"Belfort Hotels",
    "wof:placetype":"venue"
},
  "geometry": {"coordinates":[3.2050600052,51.2035140991],"type":"Point"}
}