{
  "type": "Feature",
  "properties": {
    "addr:full":"Chafour 41b Jalhay Li\u00e8ge 4845",
    "addr:housenumber":"41b",
    "addr:postcode":"4845",
    "addr:street":"Chafour",
    "iso:country":"BE",
    "sg:address":"Chafour 41b",
    "sg:city":"Jalhay",
    "sg:orig_category":"Non-Classified Establishments",
    "sg:phone":"+32 87 64 85 65",
    "sg:postcode":"4845",
    "sg:province":"Li\u00e8ge",
    "wof:name":"Galux Gaufres",
    "wof:placetype":"venue"
},
  "geometry": {"coordinates":[5.9721851349,50.5571899414],"type":"Point"}
}