{
  "type": "Feature",
  "properties": {
    "addr:full":"Oekensestraat 24 Ledegem (sint-eloois-winkel) West-Vlaanderen 8880",
    "addr:housenumber":"24",
    "addr:postcode":"8880",
    "addr:street":"Oekensestraat",
    "iso:country":"BE",
    "sg:address":"Oekensestraat 24",
    "sg:city":"Ledegem (sint-eloois-winkel)",
    "sg:classifiers":[
        {
            "category":"Farming",
            "subcategory":"Crops",
            "type":"Manufacturing & Wholesale Goods"
        }
    ],
    "sg:phone":"+32 51 21 02 09",
    "sg:postcode":"8880",
    "sg:province":"West-Vlaanderen",
    "sg:tags":[
        "vegetable",
        "fruit",
        "-",
        "grower"
    ],
    "wof:name":"Fraeye W",
    "wof:placetype":"venue"
},
  "geometry": {"coordinates":[3.1701669693,50.8881263733],"type":"Point"}
}