{
  "type": "Feature",
  "properties": {
    "addr:full":"Rue Jean-baptiste Labarre 21 Bruxelles (uccle) Bruxelles-Capitale 1180",
    "addr:housenumber":"21",
    "addr:postcode":"1180",
    "addr:street":"Rue Jean-Baptiste Labarre",
    "iso:country":"BE",
    "sg:address":"Rue Jean-baptiste Labarre 21",
    "sg:city":"Bruxelles (uccle)",
    "sg:classifiers":[
        {
            "category":"Health Services",
            "subcategory":"Doctor",
            "type":"Services"
        }
    ],
    "sg:phone":"+32 2 376 63 67",
    "sg:postcode":"1180",
    "sg:province":"Bruxelles-Capitale",
    "sg:tags":[
        "medicinephysicians",
        "surgeon"
    ],
    "wof:name":"Derveaux Luc",
    "wof:placetype":"venue"
},
  "geometry": {"coordinates":[4.3354182243,50.8011054993],"type":"Point"}
}