{
  "type": "Feature",
  "properties": {
    "iso:country":"BE",
    "sg:address":"Rue De Gonrieux 13",
    "sg:city":"Couvin",
    "sg:orig_category":"Rundveehouders",
    "sg:phone":"+32 60 34 43 87",
    "sg:postcode":"5660",
    "sg:province":"Namur",
    "wof:name":"Jean-claude Xhauflaire",
    "wof:placetype":"venue"
},
  "geometry": {"coordinates":[4.4408550262,50.0429039001],"type":"Point"}
}