{
  "type": "Feature",
  "properties": {
    "iso:country":"BE",
    "sg:address":"Kloosterstraat 50",
    "sg:city":"Antwerpen",
    "sg:orig_category":"Epiceries",
    "sg:phone":"+32 3 541 48 14",
    "sg:postcode":"2180",
    "sg:province":"Antwerpen",
    "wof:name":"A B Super Tropical",
    "wof:placetype":"venue"
},
  "geometry": {"coordinates":[4.3947491646,51.2159767151],"type":"Point"}
}