{
  "type": "Feature",
  "properties": {
    "iso:country":"BE",
    "sg:address":"Voordestraat 4",
    "sg:city":"Zingem",
    "sg:classifiers":[
        {
            "category":"Health Services",
            "subcategory":"Health Practitioner",
            "type":"Services"
        }
    ],
    "sg:phone":"+32 9 384 01 60",
    "sg:postcode":"9750",
    "sg:province":"Oost-Vlaanderen",
    "sg:tags":[
        "physiotherapist"
    ],
    "wof:name":"Vancoppernolle Katrien",
    "wof:placetype":"venue"
},
  "geometry": {"coordinates":[3.6511800289,50.9058914185],"type":"Point"}
}