{
  "type": "Feature",
  "properties": {
    "addr:full":"Kaaldries 16-18 Hamme Oost-Vlaanderen 9220",
    "addr:housenumber":"16-18",
    "addr:postcode":"9220",
    "addr:street":"Hamme Oost-Vlaanderen",
    "iso:country":"BE",
    "sg:address":"Kaaldries 16-18",
    "sg:city":"Hamme",
    "sg:classifiers":[
        {
            "category":"Home & Garden",
            "subcategory":"Building Materials",
            "type":"Retail Goods"
        }
    ],
    "sg:phone":"+32 52 47 75 68",
    "sg:postcode":"9220",
    "sg:province":"Oost-Vlaanderen",
    "sg:tags":[
        "-",
        "fireplace",
        "open",
        "ornamental"
    ],
    "wof:name":"Westerlinck F",
    "wof:placetype":"venue"
},
  "geometry": {"coordinates":[4.1266789436,51.0991668701],"type":"Point"}
}