{
  "type": "Feature",
  "properties": {
    "addr:full":"Kerkstraat 20 Aarschot Vlaams-Brabant 3200",
    "addr:housenumber":"20",
    "addr:postcode":"3200",
    "addr:street":"Kerkstraat",
    "iso:country":"BE",
    "sg:address":"Kerkstraat 20",
    "sg:city":"Aarschot",
    "sg:orig_category":"Banques and organismes de cr\u00e9dit",
    "sg:phone":"+32 16 56 42 07",
    "sg:postcode":"3200",
    "sg:province":"Vlaams-Brabant",
    "wof:name":"Kbc",
    "wof:placetype":"venue"
},
  "geometry": {"coordinates":[4.834528923,51.005569458],"type":"Point"}
}