{
  "type": "Feature",
  "properties": {
    "iso:country":"BE",
    "sg:address":"Dr. Armand Rubbensstraat 3",
    "sg:city":"Zele",
    "sg:orig_category":"Cr\u00e9dit \u00e0 la consommation",
    "sg:phone":"+32 52 44 92 52",
    "sg:postcode":"9240",
    "sg:province":"Oost-Vlaanderen",
    "wof:name":"De Block Assurity",
    "wof:placetype":"venue"
},
  "geometry": {"coordinates":[4.040681839,51.0684738159],"type":"Point"}
}