{
  "type": "Feature",
  "properties": {
    "addr:full":"Rue De Jolimont 3 Manage Hainaut 7170",
    "addr:housenumber":"3",
    "addr:postcode":"7170",
    "addr:street":"Rue De Jolimont",
    "iso:country":"BE",
    "sg:address":"Rue De Jolimont 3",
    "sg:city":"Manage",
    "sg:classifiers":[
        {
            "category":"Personal",
            "subcategory":"Beauty Salon",
            "type":"Services"
        }
    ],
    "sg:phone":"+32 64 26 54 95",
    "sg:postcode":"7170",
    "sg:province":"Hainaut",
    "sg:tags":[
        "de",
        "coiffure"
    ],
    "wof:name":"Coiffure Pino",
    "wof:placetype":"venue"
},
  "geometry": {"coordinates":[4.2336702347,50.4733428955],"type":"Point"}
}