{
  "type": "Feature",
  "properties": {
    "iso:country":"BE",
    "sg:address":"Avenue De La Pairelle 68",
    "sg:city":"Namur",
    "sg:orig_category":"Artsen and specialisten",
    "sg:phone":"+32 81 22 51 45",
    "sg:postcode":"5000",
    "sg:province":"Namur",
    "wof:name":"Ren\u00c9 Stevens",
    "wof:placetype":"venue"
},
  "geometry": {"coordinates":[4.8610420227,50.4387359619],"type":"Point"}
}