{
  "type": "Feature",
  "properties": {
    "iso:country":"BE",
    "sg:address":"Rue De L\u00b4eglise 41",
    "sg:city":"Pont-\u00c0-celles",
    "sg:orig_category":"Enseignement maternel and primaire",
    "sg:phone":"+32 71 84 47 12",
    "sg:postcode":"6230",
    "sg:province":"Hainaut",
    "wof:name":"E.f.l. N.d. De Celles",
    "wof:placetype":"venue"
},
  "geometry": {"coordinates":[4.3635811806,50.5103912354],"type":"Point"}
}