{
  "type": "Feature",
  "properties": {
    "iso:country":"BE",
    "sg:address":"Dorpsstraat 9",
    "sg:city":"Lier (koningshooikt)",
    "sg:orig_category":"Newspapers, magazines, periodicals - Distribution",
    "sg:phone":"+32 3 422 55 54",
    "sg:postcode":"2500",
    "sg:province":"Antwerpen",
    "wof:name":"Nieuwspunt (het) Bvba",
    "wof:placetype":"venue"
},
  "geometry": {"coordinates":[4.6101670265,51.095123291],"type":"Point"}
}