{
  "type": "Feature",
  "properties": {
    "addr:full":"Koestraat 17bc Scherpenheuvel-zichem Vlaams-Brabant 3270",
    "addr:housenumber":"17bc",
    "addr:postcode":"3270",
    "addr:street":"Koestraat",
    "iso:country":"BE",
    "sg:address":"Koestraat 17bc",
    "sg:city":"Scherpenheuvel-zichem",
    "sg:orig_category":"Boekhouders",
    "sg:phone":"+32 13 78 43 38",
    "sg:postcode":"3270",
    "sg:province":"Vlaams-Brabant",
    "wof:name":"Franceska Princen",
    "wof:placetype":"venue"
},
  "geometry": {"coordinates":[4.944647789,50.975151062],"type":"Point"}
}