{
  "type": "Feature",
  "properties": {
    "addr:full":"Groendalstraat 4 Antwerpen Antwerpen 2000",
    "addr:housenumber":"4",
    "addr:postcode":"2000",
    "addr:street":"Groendalstraat",
    "iso:country":"BE",
    "sg:address":"Groendalstraat 4",
    "sg:city":"Antwerpen",
    "sg:orig_category":"Chaussures",
    "sg:phone":"+32 3 213 29 87",
    "sg:postcode":"2000",
    "sg:province":"Antwerpen",
    "wof:name":"Rikiki",
    "wof:placetype":"venue"
},
  "geometry": {"coordinates":[4.4043750763,51.2174339294],"type":"Point"}
}