{
  "type": "Feature",
  "properties": {
    "addr:full":"Hoogdorpsstraat 32 Alken Limburg 3570",
    "addr:housenumber":"32",
    "addr:postcode":"3570",
    "addr:street":"Hoogdorpsstraat",
    "iso:country":"BE",
    "sg:address":"Hoogdorpsstraat 32",
    "sg:city":"Alken",
    "sg:classifiers":[
        {
            "category":"Shopping",
            "subcategory":"Clothing, Apparel, & Fashions",
            "type":"Retail Goods"
        }
    ],
    "sg:phone":"+32 11 31 21 45",
    "sg:postcode":"3570",
    "sg:province":"Limburg",
    "sg:tags":[
        "ondergoed",
        "lingerie"
    ],
    "wof:name":"Lingerie Selis",
    "wof:placetype":"venue"
},
  "geometry": {"coordinates":[5.3059329987,50.8753128052],"type":"Point"}
}