{
  "type": "Feature",
  "properties": {
    "iso:country":"BE",
    "sg:address":"Pastoor H.scherpereelstraat 23",
    "sg:city":"Veurne",
    "sg:classifiers":[
        {
            "category":"Restaurant",
            "type":"Food & Drink"
        }
    ],
    "sg:phone":"+32 58 23 37 19",
    "sg:postcode":"8630",
    "sg:province":"West-Vlaanderen",
    "wof:name":"Boikenschoc",
    "wof:placetype":"venue"
},
  "geometry": {"coordinates":[2.7441689968,51.0871543884],"type":"Point"}
}