{
  "type": "Feature",
  "properties": {
    "addr:full":"Ballaarstraat 115 Antwerpen Antwerpen 2018",
    "addr:housenumber":"115",
    "addr:postcode":"2018",
    "addr:street":"Ballaarstraat",
    "iso:country":"BE",
    "sg:address":"Ballaarstraat 115",
    "sg:city":"Antwerpen",
    "sg:classifiers":[
        {
            "category":"Building & Trades",
            "subcategory":"Pest Control",
            "type":"Services"
        }
    ],
    "sg:phone":"+32 3 238 04 79",
    "sg:postcode":"2018",
    "sg:province":"Antwerpen",
    "sg:tags":[
        "painting",
        "contractor"
    ],
    "wof:name":"Derie A",
    "wof:placetype":"venue"
},
  "geometry": {"coordinates":[4.4011039734,51.2021522522],"type":"Point"}
}