{
  "type": "Feature",
  "properties": {
    "iso:country":"BE",
    "sg:address":"Antwerpsesteenweg 94",
    "sg:city":"Malle",
    "sg:orig_category":"Secr\u00e9tariats",
    "sg:phone":"+32 3 309 08 00",
    "sg:postcode":"2390",
    "sg:province":"Antwerpen",
    "wof:name":"Fa. Catronga Caeiro",
    "wof:placetype":"venue"
},
  "geometry": {"coordinates":[4.7212572098,51.300037384],"type":"Point"}
}