{
  "type": "Feature",
  "properties": {
    "addr:full":"Rue De Ways 87 Genappe Brabant Wallon 1470",
    "addr:housenumber":"87",
    "addr:postcode":"1470",
    "addr:street":"Rue De Ways;Wallon",
    "iso:country":"BE",
    "sg:address":"Rue De Ways 87",
    "sg:city":"Genappe",
    "sg:classifiers":[
        {
            "category":"Fast Food",
            "type":"Food & Drink"
        }
    ],
    "sg:phone":"+32 67 79 03 79",
    "sg:postcode":"1470",
    "sg:province":"Brabant Wallon",
    "sg:tags":[
        "meeneem",
        "restaurant"
    ],
    "wof:name":"Restaurant Ginkgo",
    "wof:placetype":"venue"
},
  "geometry": {"coordinates":[4.4545998573,50.6112136841],"type":"Point"}
}