{
  "type": "Feature",
  "properties": {
    "iso:country":"BE",
    "sg:address":"Industrieterrein 12",
    "sg:city":"Diest",
    "sg:classifiers":[
        {
            "category":"Food & Beverages",
            "subcategory":"Farmers Market",
            "type":"Retail Goods"
        }
    ],
    "sg:phone":"+32 3 321 49 55",
    "sg:postcode":"3290",
    "sg:province":"Vlaams-Brabant",
    "sg:tags":[
        "dietetic",
        "product"
    ],
    "wof:name":"Dieximport Nv",
    "wof:placetype":"venue"
},
  "geometry": {"coordinates":[4.4619760513,51.208732605],"type":"Point"}
}