{
  "type": "Feature",
  "properties": {
    "iso:country":"BE",
    "sg:address":"Rue Paul Pastur 256",
    "sg:city":"Quaregnon",
    "sg:classifiers":[
        {
            "category":"Landmark",
            "subcategory":"Tourist Attraction",
            "type":"Public Place"
        }
    ],
    "sg:phone":"+32 65 78 52 08",
    "sg:postcode":"7390",
    "sg:province":"Hainaut",
    "sg:tags":[
        "-",
        "tourism",
        "interest",
        "sight"
    ],
    "wof:name":"Trains Touristiques Bultot",
    "wof:placetype":"venue"
},
  "geometry": {"coordinates":[3.8571820259,50.4480514526],"type":"Point"}
}