{
  "type": "Feature",
  "properties": {
    "iso:country":"BE",
    "sg:address":"Rue Draps Dom 12",
    "sg:city":"Bruxelles",
    "sg:classifiers":[
        {
            "category":"Real Estate",
            "subcategory":"Architect",
            "type":"Services"
        }
    ],
    "sg:phone":"+32 2 479 12 20",
    "sg:postcode":"1020",
    "sg:province":"Bruxelles-Capitale",
    "wof:name":"A.a.w.- Architectuur Atelier Weyers",
    "wof:placetype":"venue"
},
  "geometry": {"coordinates":[4.350812912,50.8818206787],"type":"Point"}
}