{
  "type": "Feature",
  "properties": {
    "addr:full":"Rue De Strouvia 3 Gesves (mozet) Namur 5340",
    "addr:housenumber":"3",
    "addr:postcode":"5340",
    "addr:street":"Rue De Strouvia",
    "iso:country":"BE",
    "sg:address":"Rue De Strouvia 3",
    "sg:city":"Gesves (mozet)",
    "sg:classifiers":[
        {
            "category":"Landmark",
            "subcategory":"Tourist Attraction",
            "type":"Public Place"
        }
    ],
    "sg:phone":"+32 81 58 85 45",
    "sg:postcode":"5340",
    "sg:province":"Namur",
    "sg:tags":[
        "-",
        "tourism",
        "interest",
        "sight"
    ],
    "wof:name":"Goyet La Pr\u00e9historique",
    "wof:placetype":"venue"
},
  "geometry": {"coordinates":[5.0140380859,50.4438591003],"type":"Point"}
}