{
  "type": "Feature",
  "properties": {
    "addr:full":"Rupelmondestraat 14 Kruibeke Oost-Vlaanderen 9150",
    "addr:housenumber":"14",
    "addr:postcode":"9150",
    "addr:street":"Rupelmondestraat",
    "iso:country":"BE",
    "sg:address":"Rupelmondestraat 14",
    "sg:city":"Kruibeke",
    "sg:classifiers":[
        {
            "category":"Food & Beverages",
            "subcategory":"Fruits & Vegetables",
            "type":"Retail Goods"
        }
    ],
    "sg:phone":"+32 3 744 11 87",
    "sg:postcode":"9150",
    "sg:province":"Oost-Vlaanderen",
    "sg:tags":[
        "l\u00e9gumes",
        "gr"
    ],
    "wof:name":"Luc De Letter",
    "wof:placetype":"venue"
},
  "geometry": {"coordinates":[4.2983818054,51.1469497681],"type":"Point"}
}