{
  "type": "Feature",
  "properties": {
    "addr:full":"Boulevard Mairaux 21 La Louviere Hainaut 7100",
    "addr:housenumber":"21",
    "addr:postcode":"7100",
    "addr:street":"Boulevard Mairaux",
    "iso:country":"BE",
    "sg:address":"Boulevard Mairaux 21",
    "sg:city":"La Louviere",
    "sg:classifiers":[
        {
            "category":"Fast Food",
            "type":"Food & Drink"
        }
    ],
    "sg:phone":"+32 64 21 21 86",
    "sg:postcode":"7100",
    "sg:province":"Hainaut",
    "sg:tags":[
        "\u00c0",
        "restaurants",
        "emporter",
        "restaurant"
    ],
    "wof:name":"Bertoni",
    "wof:placetype":"venue"
},
  "geometry": {"coordinates":[4.1875300407,50.4787406921],"type":"Point"}
}