{
  "type": "Feature",
  "properties": {
    "iso:country":"BE",
    "sg:address":"Gaversstraat 16",
    "sg:city":"Harelbeke",
    "sg:classifiers":[
        {
            "category":"Cafe",
            "type":"Food & Drink"
        }
    ],
    "sg:phone":"+32 56 71 37 94",
    "sg:postcode":"8530",
    "sg:province":"West-Vlaanderen",
    "sg:tags":[
        "caf\u00e9s"
    ],
    "wof:name":"De Nieuwe Wandeling",
    "wof:placetype":"venue"
},
  "geometry": {"coordinates":[3.3145859241,50.8548164368],"type":"Point"}
}