{
  "type": "Feature",
  "properties": {
    "addr:full":"Akkerstraat 104 Beernem (oedelem) West-Vlaanderen 8730",
    "addr:housenumber":"104",
    "addr:postcode":"8730",
    "addr:street":"Akkerstraat",
    "iso:country":"BE",
    "sg:address":"Akkerstraat 104",
    "sg:city":"Beernem (oedelem)",
    "sg:classifiers":[
        {
            "category":"Health Services",
            "subcategory":"Health Practitioner",
            "type":"Services"
        }
    ],
    "sg:phone":"+32 50 79 18 86",
    "sg:postcode":"8730",
    "sg:province":"West-Vlaanderen",
    "sg:tags":[
        "physiotherapist"
    ],
    "wof:name":"Van Parys Kaat",
    "wof:placetype":"venue"
},
  "geometry": {"coordinates":[3.3268198967,51.154548645],"type":"Point"}
}