{
  "type": "Feature",
  "properties": {
    "addr:full":"Rue Victor Lef\u00c8vre 25 Schaarbeek/schaerbeek Bruxelles-Capitale 1030",
    "addr:housenumber":"25",
    "addr:postcode":"1030",
    "addr:street":"Rue Victor Lefe\u0300Vre",
    "iso:country":"BE",
    "sg:address":"Rue Victor Lef\u00c8vre 25",
    "sg:city":"Schaarbeek/schaerbeek",
    "sg:orig_category":"Avocats and conseillers juridiques",
    "sg:phone":"+32 2 736 81 13",
    "sg:postcode":"1030",
    "sg:province":"Bruxelles-Capitale",
    "wof:name":"Maryse Maupin",
    "wof:placetype":"venue"
},
  "geometry": {"coordinates":[4.396654129,50.8449172974],"type":"Point"}
}