{
  "type": "Feature",
  "properties": {
    "addr:full":"Sint-jansweg 2 Beveren Oost-Vlaanderen 9130",
    "addr:housenumber":"2",
    "addr:postcode":"9130",
    "addr:street":"Sint-Jansweg",
    "iso:country":"BE",
    "sg:address":"Sint-jansweg 2",
    "sg:city":"Beveren",
    "sg:orig_category":"Produits chimiques Gr",
    "sg:phone":"+32 3 570 52 11",
    "sg:postcode":"9130",
    "sg:province":"Oost-Vlaanderen",
    "wof:name":"Borealis Kallo",
    "wof:placetype":"venue"
},
  "geometry": {"coordinates":[4.2616200447,51.2697944641],"type":"Point"}
}