{
  "type": "Feature",
  "properties": {
    "addr:full":"Busingenstraat 25 Lennik Vlaams-Brabant 1750",
    "addr:housenumber":"25;1750",
    "addr:street":"Busingenstraat;Vlaams-Brabant",
    "iso:country":"BE",
    "sg:address":"Busingenstraat 25",
    "sg:city":"Lennik",
    "sg:classifiers":[
        {
            "category":"Arena",
            "subcategory":"Sports Club",
            "type":"Entertainment"
        }
    ],
    "sg:phone":"+32 2 532 59 62",
    "sg:postcode":"1750",
    "sg:province":"Vlaams-Brabant",
    "sg:tags":[
        "de"
    ],
    "wof:name":"Davo Lennik",
    "wof:placetype":"venue"
},
  "geometry": {"coordinates":[4.1465129852,50.8108482361],"type":"Point"}
}