{
  "type": "Feature",
  "properties": {
    "iso:country":"BE",
    "sg:address":"Jan Van Rijswijcklaan 153",
    "sg:city":"Antwerpen",
    "sg:classifiers":[
        {
            "category":"Social Services",
            "subcategory":"Job Training",
            "type":"Services"
        }
    ],
    "sg:phone":"+32 3 237 61 48",
    "sg:postcode":"2018",
    "sg:province":"Antwerpen",
    "sg:tags":[
        "personnel",
        "-selection",
        "recruitment"
    ],
    "wof:name":"Algemeen Bureau Voor Grafologie",
    "wof:placetype":"venue"
},
  "geometry": {"coordinates":[4.4034662247,51.1947021484],"type":"Point"}
}