{
  "type": "Feature",
  "properties": {
    "iso:country":"BE",
    "sg:address":"Kerkstraat 32",
    "sg:city":"Oostende",
    "sg:classifiers":[
        {
            "category":"Health Services",
            "subcategory":"Hospital",
            "type":"Services"
        }
    ],
    "sg:phone":"+32 59 50 49 18",
    "sg:postcode":"8400",
    "sg:province":"West-Vlaanderen",
    "wof:name":"Medicolabor",
    "wof:placetype":"venue"
},
  "geometry": {"coordinates":[2.9198129177,51.230796814],"type":"Point"}
}