{
  "type": "Feature",
  "properties": {
    "iso:country":"BE",
    "sg:address":"Zondereigen 7",
    "sg:city":"Baarle-hertog",
    "sg:orig_category":"Enseignement maternel and primaire",
    "sg:phone":"+32 14 63 50 71",
    "sg:postcode":"2387",
    "sg:province":"Antwerpen",
    "wof:name":"Vrije Kleuterschool",
    "wof:placetype":"venue"
},
  "geometry": {"coordinates":[4.9034881592,51.4047927856],"type":"Point"}
}