{
  "type": "Feature",
  "properties": {
    "iso:country":"BE",
    "sg:address":"Koning Boudewijnstraat 20",
    "sg:city":"Kuurne",
    "sg:orig_category":"Slagers",
    "sg:phone":"+32 56 70 53 71",
    "sg:postcode":"8520",
    "sg:province":"West-Vlaanderen",
    "wof:name":"Jean Vanderbeke",
    "wof:placetype":"venue"
},
  "geometry": {"coordinates":[3.2863900661,50.8553276062],"type":"Point"}
}