{
  "type": "Feature",
  "properties": {
    "addr:full":"Rue Du Stoquet 19 Nassogne (harsin) Luxembourg 6950",
    "addr:housenumber":"19",
    "addr:postcode":"6950",
    "addr:street":"Rue Du Stoquet",
    "iso:country":"BE",
    "sg:address":"Rue Du Stoquet 19",
    "sg:city":"Nassogne (harsin)",
    "sg:classifiers":[
        {
            "category":"Building & Trades",
            "subcategory":"Landscaping Services",
            "type":"Services"
        }
    ],
    "sg:phone":"+32 84 34 42 04",
    "sg:postcode":"6950",
    "sg:province":"Luxembourg",
    "sg:tags":[
        "forestry"
    ],
    "wof:name":"Mars J-c",
    "wof:placetype":"venue"
},
  "geometry": {"coordinates":[5.341301918,50.1289215088],"type":"Point"}
}