{
  "type": "Feature",
  "properties": {
    "addr:full":"Rue Paul Pastur 178 Charleroi Hainaut 6042",
    "addr:housenumber":"178",
    "addr:postcode":"6042",
    "addr:street":"Rue Paul Pastur;Hainaut",
    "iso:country":"BE",
    "sg:address":"Rue Paul Pastur 178",
    "sg:city":"Charleroi",
    "sg:orig_category":"Persagentschappen",
    "sg:phone":"+32 71 30 79 49",
    "sg:postcode":"6042",
    "sg:province":"Hainaut",
    "wof:name":"Pascal Delizee",
    "wof:placetype":"venue"
},
  "geometry": {"coordinates":[4.3560061455,50.4131088257],"type":"Point"}
}