{
  "type": "Feature",
  "properties": {
    "iso:country":"BE",
    "sg:address":"Rue Du Parc 9-10",
    "sg:city":"Verviers",
    "sg:classifiers":[
        {
            "category":"Banks & Credit Unions",
            "subcategory":"Investment Brokerage",
            "type":"Services"
        }
    ],
    "sg:phone":"+32 87 22 30 48",
    "sg:postcode":"4800",
    "sg:province":"Li\u00e8ge",
    "sg:tags":[
        "auditor"
    ],
    "wof:name":"Gatz M",
    "wof:placetype":"venue"
},
  "geometry": {"coordinates":[5.8608441353,50.5839347839],"type":"Point"}
}