{
  "type": "Feature",
  "properties": {
    "iso:country":"BE",
    "sg:address":"Suikerlei 21",
    "sg:city":"Antwerpen",
    "sg:orig_category":"Salles de conf\u00e9rences and de r\u00e9ceptions",
    "sg:phone":"+32 3 233 91 83",
    "sg:postcode":"2000",
    "sg:province":"Antwerpen",
    "wof:name":"Manella",
    "wof:placetype":"venue"
},
  "geometry": {"coordinates":[4.3983697891,51.2210769653],"type":"Point"}
}