{
  "type": "Feature",
  "properties": {
    "addr:full":"Avenue Petites-epines 9 Bastogne Luxembourg 6600",
    "addr:housenumber":"9",
    "addr:postcode":"6600",
    "addr:street":"Avenue Petites-Epines",
    "iso:country":"BE",
    "sg:address":"Avenue Petites-epines 9",
    "sg:city":"Bastogne",
    "sg:classifiers":[
        {
            "category":"Insurance",
            "subcategory":"Life Insurance",
            "type":"Services"
        }
    ],
    "sg:phone":"+32 61 21 61 58",
    "sg:postcode":"6600",
    "sg:province":"Luxembourg",
    "sg:tags":[
        "assurance"
    ],
    "wof:name":"Christophe Duponcheele",
    "wof:placetype":"venue"
},
  "geometry": {"coordinates":[5.6999769211,50.001159668],"type":"Point"}
}