{
  "type": "Feature",
  "properties": {
    "addr:full":"Jan Van Rijswijcklaan 281 Antwerpen Antwerpen 2020",
    "addr:housenumber":"281",
    "addr:postcode":"2020",
    "addr:street":"Jan Van Rijswijcklaan",
    "iso:country":"BE",
    "sg:address":"Jan Van Rijswijcklaan 281",
    "sg:city":"Antwerpen",
    "sg:orig_category":"Banques and organismes de cr\u00e9dit",
    "sg:phone":"+32 3 238 16 54",
    "sg:postcode":"2020",
    "sg:province":"Antwerpen",
    "wof:name":"Kbc",
    "wof:placetype":"venue"
},
  "geometry": {"coordinates":[4.3914117813,51.1842384338],"type":"Point"}
}