{
  "type": "Feature",
  "properties": {
    "addr:full":"Kalkhoevestraat 52 Waregem West-Vlaanderen 8790",
    "addr:housenumber":"52",
    "addr:postcode":"8790",
    "addr:street":"Kalkhoevestraat",
    "iso:country":"BE",
    "sg:address":"Kalkhoevestraat 52",
    "sg:city":"Waregem",
    "sg:classifiers":[
        {
            "category":"Building & Trades",
            "subcategory":"Electrical",
            "type":"Services"
        }
    ],
    "sg:phone":"+32 56 62 78 78",
    "sg:postcode":"8790",
    "sg:province":"West-Vlaanderen",
    "sg:tags":[
        "electric",
        "-",
        "housewiring",
        "contractor"
    ],
    "wof:name":"Madelec Nv",
    "wof:placetype":"venue"
},
  "geometry": {"coordinates":[3.4492809772,50.8715744019],"type":"Point"}
}