{
  "type": "Feature",
  "properties": {
    "iso:country":"BE",
    "sg:address":"Herkenrodesingel 85",
    "sg:city":"Hasselt",
    "sg:classifiers":[
        {
            "category":"Building & Trades",
            "subcategory":"Construction",
            "type":"Services"
        }
    ],
    "sg:phone":"+32 11 25 25 00",
    "sg:postcode":"3500",
    "sg:province":"Limburg",
    "sg:tags":[
        "ceiling"
    ],
    "wof:name":"Beulen Houtmarkt Nv",
    "wof:placetype":"venue"
},
  "geometry": {"coordinates":[5.3299031258,50.9420547485],"type":"Point"}
}