{
  "type": "Feature",
  "properties": {
    "addr:full":"Zwarte Nonnenstraat 15ba Veurne West-Vlaanderen 8630",
    "addr:housenumber":"15ba",
    "addr:postcode":"8630",
    "addr:street":"Zwarte Nonnenstraat",
    "iso:country":"BE",
    "sg:address":"Zwarte Nonnenstraat 15ba",
    "sg:city":"Veurne",
    "sg:orig_category":"M\u00e9decins and sp\u00e9cialistes",
    "sg:phone":"+32 58 31 37 84",
    "sg:postcode":"8630",
    "sg:province":"West-Vlaanderen",
    "wof:name":"Conrad Haelterman",
    "wof:placetype":"venue"
},
  "geometry": {"coordinates":[2.6593921185,51.0726394653],"type":"Point"}
}