{
  "type": "Feature",
  "properties": {
    "addr:full":"Pastoriestraat 6 Alken Limburg 3570",
    "addr:housenumber":"6",
    "addr:postcode":"3570",
    "addr:street":"Pastoriestraat",
    "iso:country":"BE",
    "sg:address":"Pastoriestraat 6",
    "sg:city":"Alken",
    "sg:classifiers":[
        {
            "category":"Personal",
            "subcategory":"Beauty Salon",
            "type":"Services"
        }
    ],
    "sg:phone":"+32 11 31 57 19",
    "sg:postcode":"3570",
    "sg:province":"Limburg",
    "sg:tags":[
        "lady",
        "-",
        "hairdressing"
    ],
    "wof:name":"Capellini",
    "wof:placetype":"venue"
},
  "geometry": {"coordinates":[5.2758917809,50.8997764587],"type":"Point"}
}