{
  "type": "Feature",
  "properties": {
    "addr:full":"Langstraat 108 Westerlo (tongerlo) Antwerpen 2260",
    "addr:housenumber":"108",
    "addr:postcode":"2260",
    "addr:street":"Langstraat",
    "iso:country":"BE",
    "sg:address":"Langstraat 108",
    "sg:city":"Westerlo (tongerlo)",
    "sg:classifiers":[
        {
            "category":"Health Services",
            "subcategory":"Health Practitioner",
            "type":"Services"
        }
    ],
    "sg:phone":"+32 14 54 56 50",
    "sg:postcode":"2260",
    "sg:province":"Antwerpen",
    "sg:tags":[
        "physiotherapist"
    ],
    "wof:name":"Wellens Annie",
    "wof:placetype":"venue"
},
  "geometry": {"coordinates":[4.9118719101,51.1150856018],"type":"Point"}
}