{
  "type": "Feature",
  "properties": {
    "addr:full":"Rue D'aulnois 5 Qu\u00e9vy (blaregnies) Hainaut 7040",
    "addr:housenumber":"5",
    "addr:postcode":"7040",
    "addr:street":"Rue D'Aulnois;Blaregnies Hainaut",
    "iso:country":"BE",
    "sg:address":"Rue D'aulnois 5",
    "sg:city":"Qu\u00e9vy (blaregnies)",
    "sg:classifiers":[
        {
            "category":"Food & Beverages",
            "subcategory":"Groceries & Convenience Stores",
            "type":"Retail Goods"
        }
    ],
    "sg:phone":"+32 65 56 81 49",
    "sg:postcode":"7040",
    "sg:province":"Hainaut",
    "sg:tags":[
        "baker",
        "-",
        "ingredient"
    ],
    "wof:name":"Flament Pierre",
    "wof:placetype":"venue"
},
  "geometry": {"coordinates":[3.897767067,50.3562164307],"type":"Point"}
}