{
  "type": "Feature",
  "properties": {
    "addr:full":"Place Joseph Thiry 38 Aywaille Li\u00e8ge 4920",
    "addr:housenumber":"38",
    "addr:postcode":"4920",
    "addr:street":"Place Joseph Thiry",
    "iso:country":"BE",
    "sg:address":"Place Joseph Thiry 38",
    "sg:city":"Aywaille",
    "sg:classifiers":[
        {
            "category":"Shopping",
            "subcategory":"Optician",
            "type":"Retail Goods"
        }
    ],
    "sg:phone":"+32 4 384 41 03",
    "sg:postcode":"4920",
    "sg:province":"Li\u00e8ge",
    "sg:tags":[
        "-"
    ],
    "wof:name":"Bonnesire (opticiens)",
    "wof:placetype":"venue"
},
  "geometry": {"coordinates":[5.6753001213,50.4745407104],"type":"Point"}
}