{
  "type": "Feature",
  "properties": {
    "addr:full":"Dam 39 Kortrijk West-Vlaanderen 8500",
    "addr:housenumber":"39",
    "addr:postcode":"8500",
    "addr:street":"Dam",
    "iso:country":"BE",
    "sg:address":"Dam 39",
    "sg:city":"Kortrijk",
    "sg:orig_category":"Artsen and specialisten",
    "sg:phone":"+32 56 21 55 88",
    "sg:postcode":"8500",
    "sg:province":"West-Vlaanderen",
    "wof:name":"M. Couckuyt",
    "wof:placetype":"venue"
},
  "geometry": {"coordinates":[3.2654929161,50.8318214417],"type":"Point"}
}