{
  "type": "Feature",
  "properties": {
    "addr:full":"Gilainstraat 31 Tienen Vlaams-Brabant 3300",
    "addr:housenumber":"31",
    "addr:postcode":"3300",
    "addr:street":"Gilainstraat",
    "iso:country":"BE",
    "sg:address":"Gilainstraat 31",
    "sg:city":"Tienen",
    "sg:classifiers":[
        {
            "category":"Shopping",
            "subcategory":"Clothing, Apparel, & Fashions",
            "type":"Retail Goods"
        }
    ],
    "sg:phone":"+32 16 81 73 36",
    "sg:postcode":"3300",
    "sg:province":"Vlaams-Brabant",
    "sg:tags":[
        "boutique"
    ],
    "wof:name":"Friends",
    "wof:placetype":"venue"
},
  "geometry": {"coordinates":[4.9374880791,50.8094406128],"type":"Point"}
}