{
  "type": "Feature",
  "properties": {
    "iso:country":"BE",
    "sg:address":"Rue Du C\u00c9leri 24",
    "sg:city":"Sint-gillis/saint-gilles",
    "sg:orig_category":"Installation \u00e9lectrique r\u00e9sidentielle",
    "sg:phone":"+32 2 537 08 21",
    "sg:postcode":"1060",
    "sg:province":"Bruxelles-Capitale",
    "wof:name":"S N B Schnarrbach",
    "wof:placetype":"venue"
},
  "geometry": {"coordinates":[4.3435997963,50.8281707764],"type":"Point"}
}