{
  "type": "Feature",
  "properties": {
    "iso:country":"BE",
    "sg:address":"Weehage 7",
    "sg:city":"Sint-lievens-houtem",
    "sg:orig_category":"Groententeelt",
    "sg:phone":"+32 53 62 39 07",
    "sg:postcode":"9521",
    "sg:province":"Oost-Vlaanderen",
    "wof:name":"Vandevelde",
    "wof:placetype":"venue"
},
  "geometry": {"coordinates":[3.8663809299,50.9277267456],"type":"Point"}
}