{
  "type": "Feature",
  "properties": {
    "iso:country":"BE",
    "sg:address":"Driegotenkouter 5",
    "sg:city":"Hamme",
    "sg:classifiers":[
        {
            "category":"Cafe",
            "type":"Food & Drink"
        }
    ],
    "sg:phone":"+32 52 47 96 06",
    "sg:postcode":"9220",
    "sg:province":"Oost-Vlaanderen",
    "sg:tags":[
        "caf\u00e9s"
    ],
    "wof:name":"Thierry Van Cauteren",
    "wof:placetype":"venue"
},
  "geometry": {"coordinates":[4.1489448547,51.0958061218],"type":"Point"}
}