{
  "type": "Feature",
  "properties": {
    "iso:country":"BE",
    "sg:address":"Jetse-laan 93",
    "sg:city":"Jette",
    "sg:classifiers":[
        {
            "category":"Cafe",
            "type":"Food & Drink"
        }
    ],
    "sg:phone":"+32 2 427 76 82",
    "sg:postcode":"1090",
    "sg:province":"Bruxelles-Capitale",
    "sg:tags":[
        "caf\u00e9s"
    ],
    "wof:name":"Le Bureau M.b.",
    "wof:placetype":"venue"
},
  "geometry": {"coordinates":[4.3261837959,50.8680419922],"type":"Point"}
}