{
  "type": "Feature",
  "properties": {
    "addr:full":"Rue Basse Marquet 98 Saint-georges-sur-meuse Li\u00e8ge 4470",
    "addr:housenumber":"98",
    "addr:postcode":"4470",
    "addr:street":"Rue Basse Marquet",
    "iso:country":"BE",
    "sg:address":"Rue Basse Marquet 98",
    "sg:city":"Saint-georges-sur-meuse",
    "sg:classifiers":[
        {
            "category":"Autos & Motor Vehicles",
            "subcategory":"Fuel & Gas Station",
            "type":"Retail Goods"
        }
    ],
    "sg:phone":"+32 4 275 54 03",
    "sg:postcode":"4470",
    "sg:province":"Li\u00e8ge",
    "sg:tags":[
        "stations-service",
        "carburants"
    ],
    "wof:name":"Willy Lamproye",
    "wof:placetype":"venue"
},
  "geometry": {"coordinates":[5.349902153,50.5813598633],"type":"Point"}
}