{
  "type": "Feature",
  "properties": {
    "addr:full":"Eikendreef 5a Kapellen Antwerpen 2950",
    "addr:housenumber":"5a",
    "addr:postcode":"2950",
    "addr:street":"Eikendreef",
    "iso:country":"BE",
    "sg:address":"Eikendreef 5a",
    "sg:city":"Kapellen",
    "sg:orig_category":"Video-Equipment - Mainten. and Repair",
    "sg:phone":"+32 3 605 07 60",
    "sg:postcode":"2950",
    "sg:province":"Antwerpen",
    "wof:name":"Cyberdrome Plaza",
    "wof:placetype":"venue"
},
  "geometry": {"coordinates":[4.4261388779,51.3119354248],"type":"Point"}
}