{
  "type": "Feature",
  "properties": {
    "addr:full":"Chauss\u00c9e De Charleroi 102 Namur Namur 5000",
    "addr:housenumber":"102",
    "addr:postcode":"5000",
    "addr:street":"Chausse\u0301E De Charleroi",
    "iso:country":"BE",
    "sg:address":"Chauss\u00c9e De Charleroi 102",
    "sg:city":"Namur",
    "sg:orig_category":"Travaux de pl\u00e2trage",
    "sg:phone":"+32 81 22 75 19",
    "sg:postcode":"5000",
    "sg:province":"Namur",
    "wof:name":"A. Duchene",
    "wof:placetype":"venue"
},
  "geometry": {"coordinates":[4.8399271965,50.4617195129],"type":"Point"}
}