{
  "type": "Feature",
  "properties": {
    "addr:full":"Rue Augustin Berger 23 Chapelle-lez-herlaimont Hainaut 7160",
    "addr:housenumber":"23",
    "addr:postcode":"7160",
    "addr:street":"Rue Augustin Berger",
    "iso:country":"BE",
    "sg:address":"Rue Augustin Berger 23",
    "sg:city":"Chapelle-lez-herlaimont",
    "sg:orig_category":"M\u00e9decins and sp\u00e9cialistes",
    "sg:phone":"+32 71 52 37 59",
    "sg:postcode":"7160",
    "sg:province":"Hainaut",
    "wof:name":"Nuray Yarol",
    "wof:placetype":"venue"
},
  "geometry": {"coordinates":[4.286509037,50.4719467163],"type":"Point"}
}