{
  "type": "Feature",
  "properties": {
    "addr:full":"Otegemstraat 190-192 Zwevegem West-Vlaanderen 8550",
    "addr:housenumber":"190-192",
    "addr:postcode":"8550",
    "addr:street":"Otegemstraat",
    "iso:country":"BE",
    "sg:address":"Otegemstraat 190-192",
    "sg:city":"Zwevegem",
    "sg:classifiers":[
        {
            "category":"Shopping",
            "subcategory":"Computers & Home Electronics",
            "type":"Retail Goods"
        }
    ],
    "sg:phone":"+32 56 75 71 78",
    "sg:postcode":"8550",
    "sg:province":"West-Vlaanderen",
    "sg:tags":[
        "-",
        "television",
        "radio"
    ],
    "wof:name":"Lapierre C",
    "wof:placetype":"venue"
},
  "geometry": {"coordinates":[3.346476078,50.8152885437],"type":"Point"}
}