{
  "type": "Feature",
  "properties": {
    "iso:country":"BE",
    "sg:address":"Gouv. Verwilghensingel 38",
    "sg:city":"Hasselt",
    "sg:orig_category":"Winkelinrichting and handelsuitrusting Gh",
    "sg:phone":"+32 11 23 23 51",
    "sg:postcode":"3500",
    "sg:province":"Limburg",
    "wof:name":"Commerciale",
    "wof:placetype":"venue"
},
  "geometry": {"coordinates":[5.3582539558,50.9368667603],"type":"Point"}
}