{
  "type": "Feature",
  "properties": {
    "addr:full":"Rue Lieutenant Cotton 39 Flobecq Hainaut 7880",
    "addr:housenumber":"39",
    "addr:postcode":"7880",
    "addr:street":"Rue Lieutenant Cotton;Hainaut",
    "iso:country":"BE",
    "sg:address":"Rue Lieutenant Cotton 39",
    "sg:city":"Flobecq",
    "sg:classifiers":[
        {
            "category":"Bakery",
            "type":"Food & Drink"
        }
    ],
    "sg:phone":"+32 68 44 97 31",
    "sg:postcode":"7880",
    "sg:province":"Hainaut",
    "sg:tags":[
        "confectioner",
        "baker"
    ],
    "wof:name":"Dumont G",
    "wof:placetype":"venue"
},
  "geometry": {"coordinates":[3.7405350208,50.7359046936],"type":"Point"}
}