{
  "type": "Feature",
  "properties": {
    "addr:full":"Rue Joseph Wauters 9 Manage (bois-d'haine) Hainaut 7170",
    "addr:housenumber":"9",
    "addr:postcode":"7170",
    "addr:street":"Rue Joseph Wauters;Hainaut",
    "iso:country":"BE",
    "sg:address":"Rue Joseph Wauters 9",
    "sg:city":"Manage (bois-d'haine)",
    "sg:classifiers":[
        {
            "category":"Personal",
            "subcategory":"Beauty Salon",
            "type":"Services"
        }
    ],
    "sg:phone":"+32 64 55 58 41",
    "sg:postcode":"7170",
    "sg:province":"Hainaut",
    "sg:tags":[
        "lady",
        "-",
        "hairdressing"
    ],
    "wof:name":"Carla",
    "wof:placetype":"venue"
},
  "geometry": {"coordinates":[4.2355399132,50.4747200012],"type":"Point"}
}