{
  "type": "Feature",
  "properties": {
    "addr:full":"Rue F\u00e9licien Canart 1 Nivelles (bornival) Brabant Wallon 1404",
    "addr:housenumber":"1",
    "addr:postcode":"1404",
    "addr:street":"Rue Fe\u0301Licien Canart",
    "iso:country":"BE",
    "sg:address":"Rue F\u00e9licien Canart 1",
    "sg:city":"Nivelles (bornival)",
    "sg:classifiers":[
        {
            "category":"Education",
            "subcategory":"School",
            "type":"Public Place"
        }
    ],
    "sg:phone":"+32 67 84 25 78",
    "sg:postcode":"1404",
    "sg:province":"Brabant Wallon",
    "sg:tags":[
        "primary"
    ],
    "wof:name":"Ecole Communale",
    "wof:placetype":"venue"
},
  "geometry": {"coordinates":[4.2659091949,50.6042366028],"type":"Point"}
}