{
  "type": "Feature",
  "properties": {
    "iso:country":"BE",
    "sg:address":"Koning Albert I Plein 5",
    "sg:city":"Merelbeke (bottelare)",
    "sg:classifiers":[
        {
            "category":"Bars & Pubs",
            "type":"Food & Drink"
        }
    ],
    "sg:phone":"+32 9 362 05 52",
    "sg:postcode":"9820",
    "sg:province":"Oost-Vlaanderen",
    "wof:name":"Parking",
    "wof:placetype":"venue"
},
  "geometry": {"coordinates":[3.7546470165,50.9630813599],"type":"Point"}
}