{
  "type": "Feature",
  "properties": {
    "iso:country":"BE",
    "sg:address":"Asbroekstraat 24",
    "sg:city":"Zoutleeuw",
    "sg:orig_category":"Kapsalons",
    "sg:phone":"+32 11 78 17 32",
    "sg:postcode":"3440",
    "sg:province":"Vlaams-Brabant",
    "wof:name":"Kapsalon Ann",
    "wof:placetype":"venue"
},
  "geometry": {"coordinates":[5.1105651855,50.8068466187],"type":"Point"}
}