{
  "type": "Feature",
  "properties": {
    "addr:full":"Landegemstraat 27 Nevele (vosselare) Oost-Vlaanderen 9850",
    "addr:housenumber":"27",
    "addr:postcode":"9850",
    "addr:street":"Landegemstraat",
    "iso:country":"BE",
    "sg:address":"Landegemstraat 27",
    "sg:city":"Nevele (vosselare)",
    "sg:classifiers":[
        {
            "category":"Home & Garden",
            "subcategory":"Building Materials",
            "type":"Retail Goods"
        }
    ],
    "sg:phone":"+32 9 371 62 17",
    "sg:postcode":"9850",
    "sg:province":"Oost-Vlaanderen",
    "sg:tags":[
        "article",
        "-",
        "do-it-yourself"
    ],
    "wof:name":"Electro De Waele L Bvba",
    "wof:placetype":"venue"
},
  "geometry": {"coordinates":[3.5598249435,51.0345878601],"type":"Point"}
}