{
  "type": "Feature",
  "properties": {
    "addr:full":"Rozendaalstr 107 Ieper West-Vlaanderen 8900",
    "addr:housenumber":"107",
    "addr:postcode":"8900",
    "iso:country":"BE",
    "sg:address":"Rozendaalstr 107",
    "sg:city":"Ieper",
    "sg:classifiers":[
        {
            "category":"Manufacturing",
            "subcategory":"Metals",
            "type":"Manufacturing & Wholesale Goods"
        }
    ],
    "sg:phone":"+32 57 21 99 16",
    "sg:postcode":"8900",
    "sg:province":"West-Vlaanderen",
    "sg:tags":[
        "metallurgy",
        "metalworking",
        "processing"
    ],
    "wof:name":"L.c.m.c. Nv",
    "wof:placetype":"venue"
},
  "geometry": {"coordinates":[2.8771030903,50.8787536621],"type":"Point"}
}