{
  "type": "Feature",
  "properties": {
    "addr:full":"Keibergstraat 122 Torhout West-Vlaanderen 8820",
    "addr:housenumber":"122",
    "addr:postcode":"8820",
    "addr:street":"Keibergstraat",
    "iso:country":"BE",
    "sg:address":"Keibergstraat 122",
    "sg:city":"Torhout",
    "sg:classifiers":[
        {
            "category":"Professional",
            "type":"Services"
        }
    ],
    "sg:phone":"+32 50 22 23 18",
    "sg:postcode":"8820",
    "sg:province":"West-Vlaanderen",
    "sg:tags":[
        "ceremony",
        "master"
    ],
    "wof:name":"Rommelaere J",
    "wof:placetype":"venue"
},
  "geometry": {"coordinates":[3.1260929108,51.0825004578],"type":"Point"}
}