{
  "type": "Feature",
  "properties": {
    "iso:country":"BE",
    "sg:address":"Vredelaan 16",
    "sg:city":"Houthalen-helchteren (houthalen)",
    "sg:classifiers":[
        {
            "category":"Professional",
            "subcategory":"Art Services",
            "type":"Services"
        }
    ],
    "sg:phone":"+32 11 60 47 76",
    "sg:postcode":"3530",
    "sg:province":"Limburg",
    "sg:tags":[
        "photographer"
    ],
    "wof:name":"Brouwers Johan Fotoatelier",
    "wof:placetype":"venue"
},
  "geometry": {"coordinates":[5.3730669022,51.0317153931],"type":"Point"}
}