{
  "type": "Feature",
  "properties": {
    "addr:full":"Wolvengracht 48 Brussels Bruxelles-Capitale 1000",
    "addr:housenumber":"48",
    "addr:postcode":"1000",
    "addr:street":"Wolvengracht",
    "iso:country":"BE",
    "sg:address":"Wolvengracht 48",
    "sg:city":"Brussels",
    "sg:classifiers":[
        {
            "category":"Banks & Credit Unions",
            "subcategory":"Bank",
            "type":"Services"
        }
    ],
    "sg:postcode":"1000",
    "sg:province":"Bruxelles-Capitale",
    "wof:name":"Corluy & Co Sa",
    "wof:placetype":"venue"
},
  "geometry": {"coordinates":[4.4157991409,51.203830719],"type":"Point"}
}