{
  "type": "Feature",
  "properties": {
    "iso:country":"BE",
    "sg:address":"Kaiserbaracke",
    "sg:city":"Amel",
    "sg:classifiers":[
        {
            "category":"Autos & Motor Vehicles",
            "subcategory":"Automobile Sales",
            "type":"Retail Goods"
        }
    ],
    "sg:phone":"+32 80 57 09 20",
    "sg:postcode":"4770",
    "sg:province":"Li\u00e8ge",
    "sg:tags":[
        "-",
        "truck"
    ],
    "wof:name":"Truck Center Jost Ag/sa",
    "wof:placetype":"venue"
},
  "geometry": {"coordinates":[6.0802798271,50.3418807983],"type":"Point"}
}