{
  "type": "Feature",
  "properties": {
    "iso:country":"BE",
    "sg:address":"Sint-rochusplein 5",
    "sg:city":"Gent (sint-denijs-westrem - Afsnee)",
    "sg:classifiers":[
        {
            "category":"Retail",
            "subcategory":"Repair Shop",
            "type":"Services"
        }
    ],
    "sg:phone":"+32 9 220 49 91",
    "sg:postcode":"9051",
    "sg:province":"Oost-Vlaanderen",
    "sg:tags":[
        "-",
        "clothing",
        "alteration"
    ],
    "wof:name":"Nuance",
    "wof:placetype":"venue"
},
  "geometry": {"coordinates":[3.6747748852,51.0205383301],"type":"Point"}
}