{
  "type": "Feature",
  "properties": {
    "addr:full":"Tulpestraat 39 Sint-katelijne-waver Antwerpen 2860",
    "addr:housenumber":"39",
    "addr:postcode":"2860",
    "addr:street":"Tulpestraat",
    "iso:country":"BE",
    "sg:address":"Tulpestraat 39",
    "sg:city":"Sint-katelijne-waver",
    "sg:classifiers":[
        {
            "category":"Utilities",
            "subcategory":"Fuel Oil & Lpg",
            "type":"Services"
        }
    ],
    "sg:phone":"+32 15 31 34 58",
    "sg:postcode":"2860",
    "sg:province":"Antwerpen",
    "wof:name":"Verkoopmaatschappij C.c.d.",
    "wof:placetype":"venue"
},
  "geometry": {"coordinates":[4.526263237,51.0644874573],"type":"Point"}
}