{
  "type": "Feature",
  "properties": {
    "addr:full":"Fays Village 18 Sprimont Li\u00e8ge 4140",
    "addr:housenumber":"18",
    "addr:postcode":"4140",
    "iso:country":"BE",
    "sg:address":"Fays Village 18",
    "sg:city":"Sprimont",
    "sg:orig_category":"Elektrische installaties voor woningen Loodgieterij, verwarming and sanitaire installaties",
    "sg:phone":"+32 4 382 28 13",
    "sg:postcode":"4140",
    "sg:province":"Li\u00e8ge",
    "wof:name":"Ets. Montulet G.",
    "wof:placetype":"venue"
},
  "geometry": {"coordinates":[5.6062321663,50.5119247437],"type":"Point"}
}