{
  "type": "Feature",
  "properties": {
    "addr:full":"Antwerpsebaan 216 Antwerpen Antwerpen 2040",
    "addr:housenumber":"216",
    "addr:postcode":"2040",
    "addr:street":"Antwerpsebaan",
    "iso:country":"BE",
    "sg:address":"Antwerpsebaan 216",
    "sg:city":"Antwerpen",
    "sg:classifiers":[
        {
            "category":"Home & Garden",
            "subcategory":"Building Materials",
            "type":"Retail Goods"
        }
    ],
    "sg:phone":"+32 3 569 26 06",
    "sg:postcode":"2040",
    "sg:province":"Antwerpen",
    "sg:tags":[
        "article",
        "-",
        "do-it-yourself"
    ],
    "wof:name":"Abasales Nv",
    "wof:placetype":"venue"
},
  "geometry": {"coordinates":[4.3202137947,51.3486442566],"type":"Point"}
}