{
  "type": "Feature",
  "properties": {
    "addr:full":"Nieuwstraat 112 Rumst (terhagen) Antwerpen 2840",
    "addr:housenumber":"112",
    "addr:postcode":"2840",
    "addr:street":"Nieuwstraat",
    "iso:country":"BE",
    "sg:address":"Nieuwstraat 112",
    "sg:city":"Rumst (terhagen)",
    "sg:classifiers":[
        {
            "category":"Health Services",
            "subcategory":"Health Practitioner",
            "type":"Services"
        }
    ],
    "sg:phone":"+32 475 87 90 58",
    "sg:postcode":"2840",
    "sg:province":"Antwerpen",
    "sg:tags":[
        "physiotherapist"
    ],
    "wof:name":"De Koninck Sven",
    "wof:placetype":"venue"
},
  "geometry": {"coordinates":[4.4105100632,51.0808601379],"type":"Point"}
}