{
  "type": "Feature",
  "properties": {
    "addr:full":"De Robianostraat 91 Borsbeek Antwerpen 2150",
    "addr:housenumber":"91",
    "addr:postcode":"2150",
    "addr:street":"De Robianostraat",
    "iso:country":"BE",
    "sg:address":"De Robianostraat 91",
    "sg:city":"Borsbeek",
    "sg:orig_category":"Loodgieterij, verwarming and sanitaire installaties",
    "sg:phone":"+32 475 38 15 57",
    "sg:postcode":"2150",
    "sg:province":"Antwerpen",
    "wof:name":"De Prins Patrick",
    "wof:placetype":"venue"
},
  "geometry": {"coordinates":[4.4832029343,51.1946563721],"type":"Point"}
}