{
  "type": "Feature",
  "properties": {
    "iso:country":"BE",
    "sg:address":"Avenue De La Lib\u00c9ration 87",
    "sg:city":"Soumagne",
    "sg:orig_category":"Fournitures de bureau. Ordinateurs and \u00e9quipement informatique. Entretien and r\u00e9parations de machine",
    "sg:phone":"+32 4 355 08 36",
    "sg:postcode":"4630",
    "sg:province":"Li\u00e8ge",
    "wof:name":"Bureau I. Janssens",
    "wof:placetype":"venue"
},
  "geometry": {"coordinates":[5.7094287872,50.611125946],"type":"Point"}
}