{
  "type": "Feature",
  "properties": {
    "addr:full":"Groenstraat 46 Opglabbeek Limburg 3660",
    "addr:housenumber":"46",
    "addr:postcode":"3660",
    "addr:street":"Groenstraat",
    "iso:country":"BE",
    "sg:address":"Groenstraat 46",
    "sg:city":"Opglabbeek",
    "sg:classifiers":[
        {
            "category":"Building & Trades",
            "subcategory":"Pest Control",
            "type":"Services"
        }
    ],
    "sg:phone":"+32 89 85 48 16",
    "sg:postcode":"3660",
    "sg:province":"Limburg",
    "sg:tags":[
        "painting",
        "contractor"
    ],
    "wof:name":"Grobben M",
    "wof:placetype":"venue"
},
  "geometry": {"coordinates":[5.5742630959,51.0370788574],"type":"Point"}
}