{
  "type": "Feature",
  "properties": {
    "iso:country":"BE",
    "sg:address":"Prins Kavelhof 35",
    "sg:city":"Brasschaat",
    "sg:classifiers":[
        {
            "category":"Health Services",
            "subcategory":"Nursing And Care Facility",
            "type":"Services"
        }
    ],
    "sg:phone":"+32 3 650 13 30",
    "sg:postcode":"2930",
    "sg:province":"Antwerpen",
    "sg:tags":[
        "home",
        "rest"
    ],
    "wof:name":"Prins Kavelhof (ocmw)",
    "wof:placetype":"venue"
},
  "geometry": {"coordinates":[4.4920759201,51.2969932556],"type":"Point"}
}