{
  "type": "Feature",
  "properties": {
    "addr:full":"Rue Du Saule 26 Bruxelles (jette) Bruxelles-Capitale 1090",
    "addr:housenumber":"26",
    "addr:postcode":"1090",
    "addr:street":"Rue Du Saule",
    "iso:country":"BE",
    "sg:address":"Rue Du Saule 26",
    "sg:city":"Bruxelles (jette)",
    "sg:classifiers":[
        {
            "category":"Professional",
            "subcategory":"Accounting & Tax Preparation",
            "type":"Services"
        }
    ],
    "sg:phone":"+32 2 428 78 40",
    "sg:postcode":"1090",
    "sg:province":"Bruxelles-Capitale",
    "sg:tags":[
        "bookkeeper"
    ],
    "wof:name":"Remacle M",
    "wof:placetype":"venue"
},
  "geometry": {"coordinates":[4.3202152252,50.8781967163],"type":"Point"}
}