{
  "type": "Feature",
  "properties": {
    "iso:country":"BE",
    "sg:address":"Sterstraat 11",
    "sg:city":"Moeskroen/mouscron",
    "sg:orig_category":"Plaatsen van vloer- and muurbekleding Schilders Verlichting and huishoudartikelen",
    "sg:phone":"+32 56 48 66 62",
    "sg:postcode":"7711",
    "sg:province":"Hainaut",
    "wof:name":"Yves Verbeke",
    "wof:placetype":"venue"
},
  "geometry": {"coordinates":[3.2978880405,50.7360954285],"type":"Point"}
}