{
  "type": "Feature",
  "properties": {
    "iso:country":"BE",
    "sg:address":"Maanstraat 33",
    "sg:city":"Lier",
    "sg:classifiers":[
        {
            "category":"Professional",
            "subcategory":"Art Services",
            "type":"Services"
        }
    ],
    "sg:phone":"+32 3 480 57 02",
    "sg:postcode":"2500",
    "sg:province":"Antwerpen",
    "sg:tags":[
        "designer",
        "display"
    ],
    "wof:name":"Arras L",
    "wof:placetype":"venue"
},
  "geometry": {"coordinates":[4.5641469955,51.1396713257],"type":"Point"}
}