{
  "type": "Feature",
  "properties": {
    "addr:full":"Chemin De La Bouvi\u00e8re 19 Malmedy (beverc\u00e9) Li\u00e8ge 4960",
    "addr:housenumber":"19",
    "addr:postcode":"4960",
    "addr:street":"Chemin De La Bouvie\u0300Re",
    "iso:country":"BE",
    "sg:address":"Chemin De La Bouvi\u00e8re 19",
    "sg:city":"Malmedy (beverc\u00e9)",
    "sg:classifiers":[
        {
            "category":"Professional",
            "subcategory":"Art Services",
            "type":"Services"
        }
    ],
    "sg:phone":"+32 80 33 78 34",
    "sg:postcode":"4960",
    "sg:province":"Li\u00e8ge",
    "sg:tags":[
        "photography",
        "reporting",
        "-"
    ],
    "wof:name":"Letihon J",
    "wof:placetype":"venue"
},
  "geometry": {"coordinates":[5.9824128151,50.4201126099],"type":"Point"}
}