{
  "type": "Feature",
  "properties": {
    "addr:full":"Mechelsesteenweg 450b2 Zaventem Vlaams-Brabant 1930",
    "addr:housenumber":"450b2",
    "addr:postcode":"1930",
    "addr:street":"Mechelsesteenweg",
    "iso:country":"BE",
    "sg:address":"Mechelsesteenweg 450b2",
    "sg:city":"Zaventem",
    "sg:orig_category":"Bedrijvencentra and kantoordiensten",
    "sg:phone":"+32 2 756 06 06",
    "sg:postcode":"1930",
    "sg:province":"Vlaams-Brabant",
    "wof:name":"Helping Hands",
    "wof:placetype":"venue"
},
  "geometry": {"coordinates":[4.5075030327,50.8773269653],"type":"Point"}
}