{
  "type": "Feature",
  "properties": {
    "addr:full":"Rue Thier Du Ry 3 Bl\u00e9gny (barchon) Li\u00e8ge 4671",
    "addr:housenumber":"3",
    "addr:postcode":"4671",
    "addr:street":"Rue Thier Du Ry;Barchon",
    "iso:country":"BE",
    "sg:address":"Rue Thier Du Ry 3",
    "sg:city":"Bl\u00e9gny (barchon)",
    "sg:classifiers":[
        {
            "category":"Retail",
            "subcategory":"Auto Repair",
            "type":"Services"
        }
    ],
    "sg:phone":"+32 4 387 47 61",
    "sg:postcode":"4671",
    "sg:province":"Li\u00e8ge",
    "sg:tags":[
        "automobile-body"
    ],
    "wof:name":"Bonemme & Fils",
    "wof:placetype":"venue"
},
  "geometry": {"coordinates":[5.6984329224,50.6686897278],"type":"Point"}
}