{
  "type": "Feature",
  "properties": {
    "addr:full":"Rue De La Tour 16 Verviers (stembert) Li\u00e8ge 4801",
    "addr:housenumber":"16",
    "addr:postcode":"4801",
    "addr:street":"Rue De La Tour",
    "iso:country":"BE",
    "sg:address":"Rue De La Tour 16",
    "sg:city":"Verviers (stembert)",
    "sg:classifiers":[
        {
            "category":"Banks & Credit Unions",
            "subcategory":"Investment Brokerage",
            "type":"Services"
        }
    ],
    "sg:phone":"+32 87 31 79 01",
    "sg:postcode":"4801",
    "sg:province":"Li\u00e8ge",
    "sg:tags":[
        "repair",
        "-",
        "installation",
        "sanitary",
        "article"
    ],
    "wof:name":"Bourdon P",
    "wof:placetype":"venue"
},
  "geometry": {"coordinates":[5.8976759911,50.5856628418],"type":"Point"}
}