{
  "type": "Feature",
  "properties": {
    "iso:country":"BE",
    "sg:address":"Chauss\u00c9e De Huy 40",
    "sg:city":"Chaumont-gistoux",
    "sg:orig_category":"Woningbouw",
    "sg:phone":"+32 10 68 90 80",
    "sg:postcode":"1325",
    "sg:province":"Brabant Wallon",
    "wof:name":"C.n.r.j. Construct",
    "wof:placetype":"venue"
},
  "geometry": {"coordinates":[4.686647892,50.6902313232],"type":"Point"}
}