{
  "type": "Feature",
  "properties": {
    "iso:country":"BE",
    "sg:address":"Driehoekstraat 60ba",
    "sg:city":"Haaltert",
    "sg:orig_category":"Brood, gebak and snoepgoed",
    "sg:phone":"+32 53 83 51 50",
    "sg:postcode":"9451",
    "sg:province":"Oost-Vlaanderen",
    "wof:name":"Huis Sweet Success",
    "wof:placetype":"venue"
},
  "geometry": {"coordinates":[3.9828579426,50.8870735168],"type":"Point"}
}