{
  "type": "Feature",
  "properties": {
    "iso:country":"BE",
    "sg:address":"Avenue Brugmann 263",
    "sg:city":"Bruxelles (uccle)",
    "sg:classifiers":[
        {
            "category":"Shopping",
            "subcategory":"Clothing, Apparel, & Fashions",
            "type":"Retail Goods"
        }
    ],
    "sg:phone":"+32 2 345 59 74",
    "sg:postcode":"1180",
    "sg:province":"Bruxelles-Capitale",
    "sg:tags":[
        "boutique"
    ],
    "wof:name":"Rodier Uccle",
    "wof:placetype":"venue"
},
  "geometry": {"coordinates":[4.3472728729,50.8129386902],"type":"Point"}
}