{
  "type": "Feature",
  "properties": {
    "iso:country":"BE",
    "sg:address":"Boulevard Des D\u00e9port\u00e9s 50",
    "sg:city":"Estaimpuis",
    "sg:classifiers":[
        {
            "category":"Retail",
            "subcategory":"Event Space",
            "type":"Services"
        }
    ],
    "sg:phone":"+32 56 48 99 95",
    "sg:postcode":"7730",
    "sg:province":"Hainaut",
    "sg:tags":[
        "organisation"
    ],
    "wof:name":"G\u00e9n\u00e9rations Collections",
    "wof:placetype":"venue"
},
  "geometry": {"coordinates":[3.261400938,50.7083702087],"type":"Point"}
}