{
  "type": "Feature",
  "properties": {
    "addr:full":"Rue Nacfer 8 Dour (wih\u00e9ries) Hainaut 7370",
    "addr:housenumber":"8",
    "addr:postcode":"7370",
    "addr:street":"Rue Nacfer;Wihe\u0301Ries Hainaut",
    "iso:country":"BE",
    "sg:address":"Rue Nacfer 8",
    "sg:city":"Dour (wih\u00e9ries)",
    "sg:classifiers":[
        {
            "category":"Health Services",
            "subcategory":"Health Practitioner",
            "type":"Services"
        }
    ],
    "sg:phone":"+32 65 63 09 51",
    "sg:postcode":"7370",
    "sg:province":"Hainaut",
    "sg:tags":[
        "physiotherapist"
    ],
    "wof:name":"Delhaye Isabelle",
    "wof:placetype":"venue"
},
  "geometry": {"coordinates":[3.7549939156,50.3856887817],"type":"Point"}
}