{
  "type": "Feature",
  "properties": {
    "iso:country":"BE",
    "sg:address":"Avenue De La Verrerie 17/23 A",
    "sg:city":"Bruxelles",
    "sg:classifiers":[
        {
            "category":"Banks & Credit Unions",
            "subcategory":"Investment Brokerage",
            "type":"Services"
        }
    ],
    "sg:phone":"+32 2 370 59 59",
    "sg:postcode":"1190",
    "sg:province":"Bruxelles-Capitale",
    "sg:tags":[
        "curtain",
        "accessory"
    ],
    "wof:name":"Vanroy G. (ateliers) S.a.",
    "wof:placetype":"venue"
},
  "geometry": {"coordinates":[4.3143892288,50.8058280945],"type":"Point"}
}