{
  "type": "Feature",
  "properties": {
    "iso:country":"BE",
    "sg:address":"Koekelarestraat 40",
    "sg:city":"Kortemark",
    "sg:orig_category":"Gespecialiseerde residenti\u00eble bouw Installatie van houten of kunststof schrijnwerk Plaatsen van vloe",
    "sg:phone":"+32 51 56 93 34",
    "sg:postcode":"8610",
    "sg:province":"West-Vlaanderen",
    "wof:name":"Bouwwerken Wybo",
    "wof:placetype":"venue"
},
  "geometry": {"coordinates":[3.0229940414,51.0461997986],"type":"Point"}
}