{
  "type": "Feature",
  "properties": {
    "iso:country":"BE",
    "sg:address":"Nieuwlandstraat 12",
    "sg:city":"Beveren",
    "sg:orig_category":"Goederenvervoer over de weg",
    "sg:phone":"+32 3 254 09 09",
    "sg:postcode":"9120",
    "sg:province":"Oost-Vlaanderen",
    "wof:name":"Van Moer & Co",
    "wof:placetype":"venue"
},
  "geometry": {"coordinates":[4.3115448952,51.2034454346],"type":"Point"}
}