{
  "type": "Feature",
  "properties": {
    "iso:country":"BE",
    "sg:address":"Spinnewielstraat 36",
    "sg:city":"Lommel",
    "sg:classifiers":[
        {
            "category":"Real Estate",
            "subcategory":"Surveying",
            "type":"Services"
        }
    ],
    "sg:phone":"+32 11 55 19 69",
    "sg:postcode":"3920",
    "sg:province":"Limburg",
    "sg:tags":[
        "surveyor",
        "land"
    ],
    "wof:name":"Janssen Leo",
    "wof:placetype":"venue"
},
  "geometry": {"coordinates":[5.3153719902,51.208984375],"type":"Point"}
}