{
  "type": "Feature",
  "properties": {
    "iso:country":"BE",
    "sg:address":"Rue De Graty 18",
    "sg:city":"Silly (hoves)",
    "sg:classifiers":[
        {
            "category":"Building & Trades",
            "subcategory":"Construction",
            "type":"Services"
        }
    ],
    "sg:phone":"+32 2 395 30 84",
    "sg:postcode":"7830",
    "sg:province":"Hainaut",
    "sg:tags":[
        "carpenter"
    ],
    "wof:name":"Vandenberg",
    "wof:placetype":"venue"
},
  "geometry": {"coordinates":[4.033408165,50.6688194275],"type":"Point"}
}