{
  "type": "Feature",
  "properties": {
    "addr:full":"Poorthoevestraat 4 Heusden-zolder Limburg 3550",
    "addr:housenumber":"4",
    "addr:postcode":"3550",
    "addr:street":"Poorthoevestraat",
    "iso:country":"BE",
    "sg:address":"Poorthoevestraat 4",
    "sg:city":"Heusden-zolder",
    "sg:orig_category":"Pharmaciens",
    "sg:phone":"+32 11 42 24 57",
    "sg:postcode":"3550",
    "sg:province":"Limburg",
    "wof:name":"Apoteek Nerum",
    "wof:placetype":"venue"
},
  "geometry": {"coordinates":[5.2827420235,51.0333175659],"type":"Point"}
}