{
  "type": "Feature",
  "properties": {
    "iso:country":"BE",
    "sg:address":"Elizabetlaan 125",
    "sg:city":"Knokke-heist (knokke)",
    "sg:classifiers":[
        {
            "category":"Real Estate",
            "subcategory":"Architect",
            "type":"Services"
        }
    ],
    "sg:phone":"+32 50 62 36 10",
    "sg:postcode":"8300",
    "sg:province":"West-Vlaanderen",
    "wof:name":"Architectenbureau Luc De Beir Bvba",
    "wof:placetype":"venue"
},
  "geometry": {"coordinates":[3.2899339199,51.3470077515],"type":"Point"}
}