{
  "type": "Feature",
  "properties": {
    "addr:full":"Stationsstraat 57 Bierbeek Vlaams-Brabant 3360",
    "addr:housenumber":"57",
    "addr:postcode":"3360",
    "addr:street":"Stationsstraat",
    "iso:country":"BE",
    "sg:address":"Stationsstraat 57",
    "sg:city":"Bierbeek",
    "sg:classifiers":[
        {
            "category":"Insurance",
            "subcategory":"Life Insurance",
            "type":"Services"
        }
    ],
    "sg:phone":"+32 16 46 02 85",
    "sg:postcode":"3360",
    "sg:province":"Vlaams-Brabant",
    "sg:tags":[
        "assurance"
    ],
    "wof:name":"Debecker L",
    "wof:placetype":"venue"
},
  "geometry": {"coordinates":[4.784758091,50.8522377014],"type":"Point"}
}