{
  "type": "Feature",
  "properties": {
    "addr:full":"Vieille-route-de-givet 2bb Hasti\u00c8re Namur 5540",
    "addr:postcode":"5540",
    "addr:street":"Namur",
    "iso:country":"BE",
    "sg:address":"Vieille-route-de-givet 2bb",
    "sg:city":"Hasti\u00c8re",
    "sg:orig_category":"Diensten voor huisdieren",
    "sg:phone":"+32 82 64 64 62",
    "sg:postcode":"5540",
    "sg:province":"Namur",
    "wof:name":"Calin-caline",
    "wof:placetype":"venue"
},
  "geometry": {"coordinates":[4.8158869743,50.2044296265],"type":"Point"}
}