{
  "type": "Feature",
  "properties": {
    "addr:full":"Wildersedreef 26 Kampenhout Vlaams-Brabant 1910",
    "addr:housenumber":"26",
    "addr:postcode":"1910",
    "addr:street":"Wildersedreef",
    "iso:country":"BE",
    "sg:address":"Wildersedreef 26",
    "sg:city":"Kampenhout",
    "sg:classifiers":[
        {
            "category":"Manufacturing",
            "subcategory":"Textiles",
            "type":"Manufacturing & Wholesale Goods"
        }
    ],
    "sg:phone":"+32 16 65 78 17",
    "sg:postcode":"1910",
    "sg:province":"Vlaams-Brabant",
    "sg:tags":[
        "fab",
        "diver"
    ],
    "wof:name":"Jaco Productions",
    "wof:placetype":"venue"
},
  "geometry": {"coordinates":[4.5708370209,50.9392623901],"type":"Point"}
}