{
  "type": "Feature",
  "properties": {
    "addr:full":"Doornbaan 4 Ranst (oelegem) Antwerpen 2520",
    "addr:housenumber":"4",
    "addr:postcode":"2520",
    "addr:street":"Doornbaan",
    "iso:country":"BE",
    "sg:address":"Doornbaan 4",
    "sg:city":"Ranst (oelegem)",
    "sg:classifiers":[
        {
            "category":"Professional",
            "subcategory":"Management & Consulting",
            "type":"Services"
        }
    ],
    "sg:phone":"+32 3 383 35 10",
    "sg:postcode":"2520",
    "sg:province":"Antwerpen",
    "sg:tags":[
        "consultant"
    ],
    "wof:name":"Rv-consult",
    "wof:placetype":"venue"
},
  "geometry": {"coordinates":[4.6250400543,51.2133674622],"type":"Point"}
}