{
  "type": "Feature",
  "properties": {
    "addr:full":"Molenhuizen 25 Tessenderlo Limburg 3980",
    "addr:housenumber":"25",
    "addr:postcode":"3980",
    "addr:street":"Molenhuizen",
    "iso:country":"BE",
    "sg:address":"Molenhuizen 25",
    "sg:city":"Tessenderlo",
    "sg:orig_category":"Microsoft. Ordinateurs and \u00e9quipement informatique. Epuration des eaux",
    "sg:phone":"+32 13 67 56 52",
    "sg:postcode":"3980",
    "sg:province":"Limburg",
    "wof:name":"Axtron It Consult",
    "wof:placetype":"venue"
},
  "geometry": {"coordinates":[5.0832910538,51.0547103882],"type":"Point"}
}