{
  "type": "Feature",
  "properties": {
    "iso:country":"BE",
    "sg:address":"Stwg. Op Dendermonde 198",
    "sg:city":"Opwijk",
    "sg:orig_category":"Produits \u00e0 base de pommes de terre Fruits and l\u00e9gumes Fruits and l\u00e9gumes",
    "sg:phone":"+32 52 35 60 45",
    "sg:postcode":"1745",
    "sg:province":"Vlaams-Brabant",
    "wof:name":"Transport Van Mulders",
    "wof:placetype":"venue"
},
  "geometry": {"coordinates":[4.1507568359,50.9687728882],"type":"Point"}
}