{
  "type": "Feature",
  "properties": {
    "addr:full":"Brugseweg 272 Ieper West-Vlaanderen 8900",
    "addr:housenumber":"272",
    "addr:postcode":"8900",
    "addr:street":"Brugseweg",
    "iso:country":"BE",
    "sg:address":"Brugseweg 272",
    "sg:city":"Ieper",
    "sg:orig_category":"Enseignement maternel and primaire",
    "sg:phone":"+32 57 20 19 75",
    "sg:postcode":"8900",
    "sg:province":"West-Vlaanderen",
    "wof:name":"Vrije Basisschool",
    "wof:placetype":"venue"
},
  "geometry": {"coordinates":[2.896600008,50.8594894409],"type":"Point"}
}