{
  "type": "Feature",
  "properties": {
    "iso:country":"BE",
    "sg:address":"Nieuwpoortlaan 70",
    "sg:city":"De Panne",
    "sg:classifiers":[
        {
            "category":"Restaurant",
            "type":"Food & Drink"
        }
    ],
    "sg:phone":"+32 58 41 40 61",
    "sg:postcode":"8660",
    "sg:province":"West-Vlaanderen",
    "wof:name":"Bistrot Merlot",
    "wof:placetype":"venue"
},
  "geometry": {"coordinates":[2.594794035,51.1043663025],"type":"Point"}
}