{
  "type": "Feature",
  "properties": {
    "addr:full":"Beverestraat 36 Oudenaarde Oost-Vlaanderen 9700",
    "addr:housenumber":"36",
    "addr:postcode":"9700",
    "addr:street":"Beverestraat",
    "iso:country":"BE",
    "sg:address":"Beverestraat 36",
    "sg:city":"Oudenaarde",
    "sg:classifiers":[
        {
            "category":"Fast Food",
            "type":"Food & Drink"
        }
    ],
    "sg:phone":"+32 55 30 36 55",
    "sg:postcode":"9700",
    "sg:province":"Oost-Vlaanderen",
    "sg:tags":[
        "meeneem",
        "restaurant"
    ],
    "wof:name":"Pitta & Doner Kebab",
    "wof:placetype":"venue"
},
  "geometry": {"coordinates":[3.599353075,50.8485870361],"type":"Point"}
}