{
  "type": "Feature",
  "properties": {
    "addr:full":"Kloosterstraat 79 Knesselare Oost-Vlaanderen 9910",
    "addr:housenumber":"79",
    "addr:postcode":"9910",
    "addr:street":"Kloosterstraat;Oost-Vlaanderen",
    "iso:country":"BE",
    "sg:address":"Kloosterstraat 79",
    "sg:city":"Knesselare",
    "sg:orig_category":"Enseignement maternel and primaire",
    "sg:phone":"+32 9 374 53 33",
    "sg:postcode":"9910",
    "sg:province":"Oost-Vlaanderen",
    "wof:name":"Vrije Basisschool",
    "wof:placetype":"venue"
},
  "geometry": {"coordinates":[3.4057130814,51.1434326172],"type":"Point"}
}