{
  "type": "Feature",
  "properties": {
    "iso:country":"BE",
    "sg:address":"Avenue D\u00b4auderghem 92",
    "sg:city":"Etterbeek",
    "sg:orig_category":"Agences de publicit\u00e9",
    "sg:phone":"+32 2 743 35 40",
    "sg:postcode":"1040",
    "sg:province":"Bruxelles-Capitale",
    "wof:name":"Bureau Pro Services",
    "wof:placetype":"venue"
},
  "geometry": {"coordinates":[4.3863210678,50.8381958008],"type":"Point"}
}