{
  "type": "Feature",
  "properties": {
    "iso:country":"BE",
    "sg:address":"Weitstraat 37",
    "sg:city":"Maarkedal",
    "sg:orig_category":"Rundveehouders",
    "sg:phone":"+32 55 21 22 79",
    "sg:postcode":"9681",
    "sg:province":"Oost-Vlaanderen",
    "wof:name":"Armand De Weer",
    "wof:placetype":"venue"
},
  "geometry": {"coordinates":[3.5952050686,50.7969856262],"type":"Point"}
}