{
  "type": "Feature",
  "properties": {
    "iso:country":"BE",
    "sg:address":"Lindestr. 57",
    "sg:city":"Hamme-merchtem",
    "sg:classifiers":[
        {
            "category":"Wholesale",
            "subcategory":"Medical Equipment & Supplies",
            "type":"Manufacturing & Wholesale Goods"
        }
    ],
    "sg:phone":"+32 2 460 60 99",
    "sg:postcode":"1785",
    "sg:province":"Vlaams-Brabant",
    "sg:tags":[
        "instrument",
        "health",
        "-",
        "precision"
    ],
    "wof:name":"Bogman Medical Equipment Nv",
    "wof:placetype":"venue"
},
  "geometry": {"coordinates":[4.2634701729,50.9275932312],"type":"Point"}
}