{
  "type": "Feature",
  "properties": {
    "addr:full":"Rue De Marcinelle 109 Charleroi Hainaut 6032",
    "addr:housenumber":"109",
    "addr:postcode":"6032",
    "addr:street":"Rue De Marcinelle;Hainaut",
    "iso:country":"BE",
    "sg:address":"Rue De Marcinelle 109",
    "sg:city":"Charleroi",
    "sg:orig_category":"Mat\u00e9riaux de construction Quincailleries",
    "sg:phone":"+32 71 36 10 73",
    "sg:postcode":"6032",
    "sg:province":"Hainaut",
    "wof:name":"Jean Antoine",
    "wof:placetype":"venue"
},
  "geometry": {"coordinates":[4.4161601067,50.3751335144],"type":"Point"}
}