{
  "type": "Feature",
  "properties": {
    "addr:full":"Leeuwbeekstraat 16 Geetbets Vlaams-Brabant 3454",
    "addr:housenumber":"16",
    "addr:postcode":"3454",
    "addr:street":"Leeuwbeekstraat",
    "iso:country":"BE",
    "sg:address":"Leeuwbeekstraat 16",
    "sg:city":"Geetbets",
    "sg:orig_category":"Groententeelt",
    "sg:phone":"+32 11 58 96 11",
    "sg:postcode":"3454",
    "sg:province":"Vlaams-Brabant",
    "wof:name":"Herman Brants",
    "wof:placetype":"venue"
},
  "geometry": {"coordinates":[5.1474947929,50.9052047729],"type":"Point"}
}