{
  "type": "Feature",
  "properties": {
    "addr:full":"Boomstraat 77 Gent Oost-Vlaanderen 9000",
    "addr:housenumber":"77",
    "addr:postcode":"9000",
    "addr:street":"Boomstraat;Oost-Vlaanderen",
    "iso:country":"BE",
    "sg:address":"Boomstraat 77",
    "sg:city":"Gent",
    "sg:classifiers":[
        {
            "category":"Education",
            "subcategory":"School",
            "type":"Public Place"
        }
    ],
    "sg:phone":"+32 9 227 85 15",
    "sg:postcode":"9000",
    "sg:province":"Oost-Vlaanderen",
    "sg:tags":[
        "primary"
    ],
    "wof:name":"De Boomhut",
    "wof:placetype":"venue"
},
  "geometry": {"coordinates":[3.6925139427,51.0639915466],"type":"Point"}
}