{
  "type": "Feature",
  "properties": {
    "iso:country":"BE",
    "sg:address":"Dorpsstraat 33",
    "sg:city":"Bocholt",
    "sg:classifiers":[
        {
            "category":"Bars & Pubs",
            "type":"Food & Drink"
        }
    ],
    "sg:phone":"+32 89 48 13 48",
    "sg:postcode":"3950",
    "sg:province":"Limburg",
    "wof:name":"Rembrandt Jr",
    "wof:placetype":"venue"
},
  "geometry": {"coordinates":[5.5792660713,51.1727752686],"type":"Point"}
}