{
  "type": "Feature",
  "properties": {
    "addr:full":"Hoogdorpsstraat 21 Alken Limburg 3570",
    "addr:housenumber":"21",
    "addr:postcode":"3570",
    "addr:street":"Hoogdorpsstraat",
    "iso:country":"BE",
    "sg:address":"Hoogdorpsstraat 21",
    "sg:city":"Alken",
    "sg:orig_category":"Banques and organismes de cr\u00e9dit",
    "sg:phone":"+32 11 31 29 99",
    "sg:postcode":"3570",
    "sg:province":"Limburg",
    "wof:name":"Dexia",
    "wof:placetype":"venue"
},
  "geometry": {"coordinates":[5.3065638542,50.8756828308],"type":"Point"}
}