{
  "type": "Feature",
  "properties": {
    "iso:country":"BE",
    "sg:address":"Cit\u00e9 Reine Astrid 27",
    "sg:city":"Quaregnon",
    "sg:classifiers":[
        {
            "category":"Building & Trades",
            "subcategory":"Construction",
            "type":"Services"
        }
    ],
    "sg:phone":"+32 65 79 57 81",
    "sg:postcode":"7390",
    "sg:province":"Hainaut",
    "sg:tags":[
        "carpenter"
    ],
    "wof:name":"Montagna M",
    "wof:placetype":"venue"
},
  "geometry": {"coordinates":[3.858864069,50.4408454895],"type":"Point"}
}