{
  "type": "Feature",
  "properties": {
    "addr:full":"Avenue De La Ferme Rose 9b35 Ukkel/uccle Bruxelles-Capitale 1180",
    "addr:housenumber":"9b35",
    "addr:postcode":"1180",
    "addr:street":"Avenue De La Ferme Rose;/",
    "iso:country":"BE",
    "sg:address":"Avenue De La Ferme Rose 9b35",
    "sg:city":"Ukkel/uccle",
    "sg:classifiers":[
        {
            "category":"Professional",
            "subcategory":"Business Services",
            "type":"Services"
        }
    ],
    "sg:phone":"+32 2 346 83 36",
    "sg:postcode":"1180",
    "sg:province":"Bruxelles-Capitale",
    "sg:tags":[
        "aux",
        "diver",
        "entreprises"
    ],
    "wof:name":"F.x. D\u00b4huart",
    "wof:placetype":"venue"
},
  "geometry": {"coordinates":[4.3483109474,50.8064041138],"type":"Point"}
}