{
  "type": "Feature",
  "properties": {
    "addr:full":"Chauss\u00c9e De La Hulpe 338 Watermaal-bosvoorde/watermael- Bruxelles-Capitale 1170",
    "addr:housenumber":"338;/ watermael",
    "addr:postcode":"1170",
    "addr:street":"Chausse\u0301E De La Hulpe;Watermaal-Bosvoorde",
    "iso:country":"BE",
    "sg:address":"Chauss\u00c9e De La Hulpe 338",
    "sg:city":"Watermaal-bosvoorde/watermael-",
    "sg:orig_category":"Agences de voyages",
    "sg:phone":"+32 475 91 98 53",
    "sg:postcode":"1170",
    "sg:province":"Bruxelles-Capitale",
    "wof:name":"Ritiere D",
    "wof:placetype":"venue"
},
  "geometry": {"coordinates":[4.4226732254,50.7904663086],"type":"Point"}
}