{
  "type": "Feature",
  "properties": {
    "iso:country":"BE",
    "sg:address":"Donckstraat 66",
    "sg:city":"Dendermonde",
    "sg:orig_category":"Kapsalons",
    "sg:phone":"+32 52 22 12 72",
    "sg:postcode":"9200",
    "sg:province":"Oost-Vlaanderen",
    "wof:name":"Coiffure An",
    "wof:placetype":"venue"
},
  "geometry": {"coordinates":[4.0879001617,51.0337562561],"type":"Point"}
}