{
  "type": "Feature",
  "properties": {
    "iso:country":"BE",
    "sg:address":"Dr. Van De Perrestraat 7be",
    "sg:city":"Geel",
    "sg:orig_category":"Fotografen and fotostudio's",
    "sg:phone":"+32 14 58 92 22",
    "sg:postcode":"2440",
    "sg:province":"Antwerpen",
    "wof:name":"Vansant Johan",
    "wof:placetype":"venue"
},
  "geometry": {"coordinates":[4.9882822037,51.1695365906],"type":"Point"}
}