{
  "type": "Feature",
  "properties": {
    "iso:country":"BE",
    "sg:address":"Paddevijverstraat 58",
    "sg:city":"Ieper",
    "sg:orig_category":"Autoverhuur",
    "sg:phone":"+32 57 20 41 92",
    "sg:postcode":"8900",
    "sg:province":"West-Vlaanderen",
    "wof:name":"V.h.z.",
    "wof:placetype":"venue"
},
  "geometry": {"coordinates":[2.8845748901,50.8670349121],"type":"Point"}
}