{
  "type": "Feature",
  "properties": {
    "iso:country":"BE",
    "sg:address":"Parklaan 17",
    "sg:city":"Oostende",
    "sg:classifiers":[
        {
            "category":"Insurance",
            "subcategory":"Insurance Agent",
            "type":"Services"
        }
    ],
    "sg:phone":"+32 59 70 43 42",
    "sg:postcode":"8400",
    "sg:province":"West-Vlaanderen",
    "sg:tags":[
        "broker"
    ],
    "wof:name":"Kbc-verzekeringen",
    "wof:placetype":"venue"
},
  "geometry": {"coordinates":[2.9161200523,51.216381073],"type":"Point"}
}