{
  "type": "Feature",
  "properties": {
    "addr:full":"Liersesteenweg 135 Ranst Antwerpen 2520",
    "addr:housenumber":"135",
    "addr:postcode":"2520",
    "addr:street":"Liersesteenweg",
    "iso:country":"BE",
    "sg:address":"Liersesteenweg 135",
    "sg:city":"Ranst",
    "sg:orig_category":"Voertuigen",
    "sg:phone":"+32 3 480 06 08",
    "sg:postcode":"2520",
    "sg:province":"Antwerpen",
    "wof:name":"Garage Wouters",
    "wof:placetype":"venue"
},
  "geometry": {"coordinates":[4.5812568665,51.1525421143],"type":"Point"}
}