{
  "type": "Feature",
  "properties": {
    "addr:full":"Koeistraat 9 Kaprijke Oost-Vlaanderen 9971",
    "addr:housenumber":"9",
    "addr:postcode":"9971",
    "addr:street":"Koeistraat",
    "iso:country":"BE",
    "sg:address":"Koeistraat 9",
    "sg:city":"Kaprijke",
    "sg:orig_category":"Woningbouw",
    "sg:phone":"+32 9 377 27 97",
    "sg:postcode":"9971",
    "sg:province":"Oost-Vlaanderen",
    "wof:name":"Rudy Goethals",
    "wof:placetype":"venue"
},
  "geometry": {"coordinates":[3.6108539104,51.2054634094],"type":"Point"}
}