{
  "type": "Feature",
  "properties": {
    "addr:full":"Chauss\u00c9e De Gand 459 Brussel/bruxelles Bruxelles-Capitale 1080",
    "addr:housenumber":"459",
    "addr:postcode":"1080",
    "addr:street":"Chausse\u0301E De Gand;/",
    "iso:country":"BE",
    "sg:address":"Chauss\u00c9e De Gand 459",
    "sg:city":"Brussel/bruxelles",
    "sg:classifiers":[
        {
            "category":"Taxi",
            "type":"Transportation"
        }
    ],
    "sg:phone":"+32 2 770 13 00",
    "sg:postcode":"1080",
    "sg:province":"Bruxelles-Capitale",
    "wof:name":"Airport Service Benelux",
    "wof:placetype":"venue"
},
  "geometry": {"coordinates":[4.3159060478,50.8584327698],"type":"Point"}
}