{
  "type": "Feature",
  "properties": {
    "iso:country":"BE",
    "sg:address":"Rue Des V\u00e9hinnes 9",
    "sg:city":"Lierneux",
    "sg:classifiers":[
        {
            "category":"Insurance",
            "subcategory":"Insurance Agent",
            "type":"Services"
        }
    ],
    "sg:phone":"+32 80 31 99 58",
    "sg:postcode":"4990",
    "sg:province":"Li\u00e8ge",
    "sg:tags":[
        "broker"
    ],
    "wof:name":"Wilmotte G",
    "wof:placetype":"venue"
},
  "geometry": {"coordinates":[5.7936282158,50.2845916748],"type":"Point"}
}