{
  "type": "Feature",
  "properties": {
    "addr:full":"Dorpstraat 24 Overpelt Limburg 3900",
    "addr:housenumber":"24",
    "addr:postcode":"3900",
    "addr:street":"Dorpstraat",
    "iso:country":"BE",
    "sg:address":"Dorpstraat 24",
    "sg:city":"Overpelt",
    "sg:classifiers":[
        {
            "category":"Fast Food",
            "type":"Food & Drink"
        }
    ],
    "sg:phone":"+32 11 64 46 09",
    "sg:postcode":"3900",
    "sg:province":"Limburg",
    "sg:tags":[
        "meeneem",
        "restaurant"
    ],
    "wof:name":"Pelt",
    "wof:placetype":"venue"
},
  "geometry": {"coordinates":[5.4250268936,51.2145576477],"type":"Point"}
}