{
  "type": "Feature",
  "properties": {
    "addr:full":"Nijverheidstraat 1 Oostkamp West-Vlaanderen 8020",
    "addr:housenumber":"1",
    "addr:postcode":"8020",
    "addr:street":"Nijverheidstraat",
    "iso:country":"BE",
    "sg:address":"Nijverheidstraat 1",
    "sg:city":"Oostkamp",
    "sg:classifiers":[
        {
            "category":"Utilities",
            "subcategory":"Telephone",
            "type":"Services"
        }
    ],
    "sg:phone":"+32 50 82 24 98",
    "sg:postcode":"8020",
    "sg:province":"West-Vlaanderen",
    "sg:tags":[
        "telecommunication"
    ],
    "wof:name":"Neon Royal Bvba",
    "wof:placetype":"venue"
},
  "geometry": {"coordinates":[3.2563710213,51.1275634766],"type":"Point"}
}