{
  "type": "Feature",
  "properties": {
    "addr:full":"Sint-jans Gasthuisstraat 35 Gistel West-Vlaanderen 8470",
    "addr:housenumber":"35",
    "addr:postcode":"8470",
    "addr:street":"Sint-Jans Gasthuisstraat",
    "iso:country":"BE",
    "sg:address":"Sint-jans Gasthuisstraat 35",
    "sg:city":"Gistel",
    "sg:classifiers":[
        {
            "category":"Social Services",
            "subcategory":"Retirement Home",
            "type":"Services"
        }
    ],
    "sg:phone":"+32 59 27 01 10",
    "sg:postcode":"8470",
    "sg:province":"West-Vlaanderen",
    "sg:tags":[
        "residence"
    ],
    "wof:name":"Service Flats D'oostpoorte",
    "wof:placetype":"venue"
},
  "geometry": {"coordinates":[2.9702949524,51.1570549011],"type":"Point"}
}