{
  "type": "Feature",
  "properties": {
    "addr:full":"Route Du Ch\u00c2teau Magis 20 Aubel Li\u00e8ge 4880",
    "addr:housenumber":"20",
    "addr:postcode":"4880",
    "addr:street":"Route Du Cha\u0302Teau Magis",
    "iso:country":"BE",
    "sg:address":"Route Du Ch\u00c2teau Magis 20",
    "sg:city":"Aubel",
    "sg:orig_category":"Loodgieterij, verwarming and sanitaire installaties",
    "sg:phone":"+32 87 68 84 25",
    "sg:postcode":"4880",
    "sg:province":"Li\u00e8ge",
    "wof:name":"Daniel Charlier",
    "wof:placetype":"venue"
},
  "geometry": {"coordinates":[5.8547449112,50.7130241394],"type":"Point"}
}