{
  "type": "Feature",
  "properties": {
    "addr:full":"Bosdreef 50 Harelbeke West-Vlaanderen 8530",
    "addr:housenumber":"50",
    "addr:postcode":"8530",
    "addr:street":"Bosdreef",
    "iso:country":"BE",
    "sg:address":"Bosdreef 50",
    "sg:city":"Harelbeke",
    "sg:classifiers":[
        {
            "category":"Personal",
            "subcategory":"Beauty Salon",
            "type":"Services"
        }
    ],
    "sg:phone":"+32 56 25 77 90",
    "sg:postcode":"8530",
    "sg:province":"West-Vlaanderen",
    "sg:tags":[
        "de",
        "coiffure"
    ],
    "wof:name":"Coiffure M-line",
    "wof:placetype":"venue"
},
  "geometry": {"coordinates":[3.3122169971,50.8294525146],"type":"Point"}
}