{
  "type": "Feature",
  "properties": {
    "addr:full":"Voie De Li\u00c8ge 114 Herstal Li\u00e8ge 4040",
    "addr:housenumber":"114",
    "addr:postcode":"4040",
    "addr:street":"Voie De Lie\u0300Ge",
    "iso:country":"BE",
    "sg:address":"Voie De Li\u00c8ge 114",
    "sg:city":"Herstal",
    "sg:orig_category":"Epiceries",
    "sg:phone":"+32 4 264 09 72",
    "sg:postcode":"4040",
    "sg:province":"Li\u00e8ge",
    "wof:name":"Leon Wathion",
    "wof:placetype":"venue"
},
  "geometry": {"coordinates":[5.6310281754,50.6682319641],"type":"Point"}
}