{
  "type": "Feature",
  "properties": {
    "addr:full":"Place Destr\u00e9e 22 Fontaine-l'ev\u00eaque (forchies-la-marche) Hainaut 6141",
    "addr:housenumber":"22",
    "addr:postcode":"6141",
    "addr:street":"Place Destre\u0301E;Hainaut",
    "iso:country":"BE",
    "sg:address":"Place Destr\u00e9e 22",
    "sg:city":"Fontaine-l'ev\u00eaque (forchies-la-marche)",
    "sg:classifiers":[
        {
            "category":"Bars & Pubs",
            "type":"Food & Drink"
        }
    ],
    "sg:phone":"+32 71 52 62 29",
    "sg:postcode":"6141",
    "sg:province":"Hainaut",
    "wof:name":"D'elia",
    "wof:placetype":"venue"
},
  "geometry": {"coordinates":[-111.9644622803,46.2507972717],"type":"Point"}
}