{
  "type": "Feature",
  "properties": {
    "addr:full":"Putstraat 74 Tienen (hakendover) Vlaams-Brabant 3300",
    "addr:housenumber":"74",
    "addr:postcode":"3300",
    "addr:street":"Putstraat",
    "iso:country":"BE",
    "sg:address":"Putstraat 74",
    "sg:city":"Tienen (hakendover)",
    "sg:classifiers":[
        {
            "category":"Personal",
            "subcategory":"Beauty Salon",
            "type":"Services"
        }
    ],
    "sg:phone":"+32 16 78 20 28",
    "sg:postcode":"3300",
    "sg:province":"Vlaams-Brabant",
    "sg:tags":[
        "lady",
        "-",
        "hairdressing"
    ],
    "wof:name":"La Cortesia",
    "wof:placetype":"venue"
},
  "geometry": {"coordinates":[4.930077076,50.8096694946],"type":"Point"}
}