{
  "type": "Feature",
  "properties": {
    "iso:country":"BE",
    "sg:address":"Clos Des Charmes 407 Box 1",
    "sg:city":"Tubize",
    "sg:classifiers":[
        {
            "category":"Building & Trades",
            "subcategory":"Cleaning & Sanitation",
            "type":"Services"
        }
    ],
    "sg:phone":"+32 477 23 94 28",
    "sg:postcode":"1480",
    "sg:province":"Brabant Wallon",
    "sg:tags":[
        "janitor"
    ],
    "wof:name":"Demortier J",
    "wof:placetype":"venue"
},
  "geometry": {"coordinates":[4.2067990303,50.67943573],"type":"Point"}
}