{
  "type": "Feature",
  "properties": {
    "addr:full":". Roosdaal (groot) Vlaams-Brabant 1760",
    "addr:housenumber":"1760",
    "addr:street":"Groot Vlaams-Brabant",
    "iso:country":"BE",
    "sg:address":".",
    "sg:city":"Roosdaal (groot)",
    "sg:orig_category":"Apotheken",
    "sg:phone":"+32 900 10 500",
    "sg:postcode":"1760",
    "sg:province":"Vlaams-Brabant",
    "wof:name":"Apothekers Van Wacht",
    "wof:placetype":"venue"
},
  "geometry": {"coordinates":[4.0744271278,50.8435707092],"type":"Point"}
}