{
  "type": "Feature",
  "properties": {
    "addr:full":"Place De Taviers 26 Eghez\u00c9e Namur 5310",
    "addr:housenumber":"26",
    "addr:postcode":"5310",
    "addr:street":"Place De Taviers;Namur",
    "iso:country":"BE",
    "sg:address":"Place De Taviers 26",
    "sg:city":"Eghez\u00c9e",
    "sg:orig_category":"Boekhouders",
    "sg:phone":"+32 81 81 29 91",
    "sg:postcode":"5310",
    "sg:province":"Namur",
    "wof:name":"Baudouin Leclaire",
    "wof:placetype":"venue"
},
  "geometry": {"coordinates":[4.9278669357,50.6171112061],"type":"Point"}
}