{
  "type": "Feature",
  "properties": {
    "addr:full":"Bovenveld 33a Holsbeek Vlaams-Brabant 3220",
    "addr:housenumber":"33a",
    "addr:postcode":"3220",
    "addr:street":"Bovenveld",
    "iso:country":"BE",
    "sg:address":"Bovenveld 33a",
    "sg:city":"Holsbeek",
    "sg:classifiers":[
        {
            "category":"Health Services",
            "subcategory":"Health Practitioner",
            "type":"Services"
        }
    ],
    "sg:phone":"+32 16 44 67 76",
    "sg:postcode":"3220",
    "sg:province":"Vlaams-Brabant",
    "sg:tags":[
        "physiotherapist"
    ],
    "wof:name":"De Cordt E",
    "wof:placetype":"venue"
},
  "geometry": {"coordinates":[4.7233681679,50.9091682434],"type":"Point"}
}