{
  "type": "Feature",
  "properties": {
    "iso:country":"BE",
    "sg:address":"Chauss\u00c9e De Tubize 256",
    "sg:city":"Wauthier-braine",
    "sg:orig_category":"Location de machines-outils and de mat\u00e9riel de bricolage",
    "sg:phone":"+32 67 84 21 40",
    "sg:postcode":"1440",
    "sg:province":"Brabant Wallon",
    "wof:name":"Locmat",
    "wof:placetype":"venue"
},
  "geometry": {"coordinates":[4.3197717667,50.6898727417],"type":"Point"}
}