{
  "type": "Feature",
  "properties": {
    "addr:full":"Rozendalestraat 64ba Wingene West-Vlaanderen 8750",
    "addr:postcode":"8750",
    "addr:street":"Rozendalestraat",
    "iso:country":"BE",
    "sg:address":"Rozendalestraat 64ba",
    "sg:city":"Wingene",
    "sg:classifiers":[
        {
            "category":"Cafe",
            "type":"Food & Drink"
        }
    ],
    "sg:phone":"+32 51 65 64 56",
    "sg:postcode":"8750",
    "sg:province":"West-Vlaanderen",
    "sg:tags":[
        "caf\u00e9s"
    ],
    "wof:name":"Caf\u00c9 De Hoeve",
    "wof:placetype":"venue"
},
  "geometry": {"coordinates":[3.2624890804,51.0641593933],"type":"Point"}
}