{
  "type": "Feature",
  "properties": {
    "addr:full":"Luchtvaartsquare 6 Anderlecht Bruxelles-Capitale 1070",
    "addr:housenumber":"6",
    "addr:postcode":"1070",
    "addr:street":"Luchtvaartsquare",
    "iso:country":"BE",
    "sg:address":"Luchtvaartsquare 6",
    "sg:city":"Anderlecht",
    "sg:classifiers":[
        {
            "category":"Travel",
            "subcategory":"Hotels & Motels",
            "type":"Entertainment"
        }
    ],
    "sg:phone":"+32 2 520 60 53",
    "sg:postcode":"1070",
    "sg:province":"Bruxelles-Capitale",
    "wof:name":"H\u00d4tel Ustel",
    "wof:placetype":"venue"
},
  "geometry": {"coordinates":[4.3296580315,50.8392295837],"type":"Point"}
}