{
  "type": "Feature",
  "properties": {
    "addr:full":"Kartuizersstraat 3 Brussel/bruxelles Bruxelles-Capitale 1000",
    "addr:housenumber":"3",
    "addr:postcode":"1000",
    "addr:street":"Kartuizersstraat;/",
    "iso:country":"BE",
    "sg:address":"Kartuizersstraat 3",
    "sg:city":"Brussel/bruxelles",
    "sg:orig_category":"Antiek Herstelling horloges and juwelen",
    "sg:phone":"+32 2 502 18 94",
    "sg:postcode":"1000",
    "sg:province":"Bruxelles-Capitale",
    "wof:name":"An-hor",
    "wof:placetype":"venue"
},
  "geometry": {"coordinates":[4.3474111557,50.8489685059],"type":"Point"}
}