{
  "type": "Feature",
  "properties": {
    "iso:country":"BE",
    "sg:address":"Smedenstraat 31",
    "sg:city":"Brugge",
    "sg:classifiers":[
        {
            "category":"Shopping",
            "subcategory":"Clothing, Apparel, & Fashions",
            "type":"Retail Goods"
        }
    ],
    "sg:phone":"+32 50 33 26 51",
    "sg:postcode":"8000",
    "sg:province":"West-Vlaanderen",
    "sg:tags":[
        "lady",
        "clothing",
        "-"
    ],
    "wof:name":"Hera",
    "wof:placetype":"venue"
},
  "geometry": {"coordinates":[3.2149829865,51.2053031921],"type":"Point"}
}