{
  "type": "Feature",
  "properties": {
    "addr:full":"Dorpsstraat 12 Stekene Oost-Vlaanderen 9190",
    "addr:housenumber":"12",
    "addr:postcode":"9190",
    "addr:street":"Dorpsstraat",
    "iso:country":"BE",
    "sg:address":"Dorpsstraat 12",
    "sg:city":"Stekene",
    "sg:classifiers":[
        {
            "category":"Professional",
            "subcategory":"Testing Lab",
            "type":"Services"
        }
    ],
    "sg:phone":"+32 3 779 43 86",
    "sg:postcode":"9190",
    "sg:province":"Oost-Vlaanderen",
    "sg:tags":[
        "chemist"
    ],
    "wof:name":"De Smet K",
    "wof:placetype":"venue"
},
  "geometry": {"coordinates":[4.0402112007,51.2058105469],"type":"Point"}
}