{
  "type": "Feature",
  "properties": {
    "iso:country":"BE",
    "sg:address":"Rue Edmond Leburton 49",
    "sg:city":"Waremme (lantremange)",
    "sg:classifiers":[
        {
            "category":"Real Estate",
            "subcategory":"Architect",
            "type":"Services"
        }
    ],
    "sg:phone":"+32 19 33 08 45",
    "sg:postcode":"4300",
    "sg:province":"Li\u00e8ge",
    "wof:name":"Saey A",
    "wof:placetype":"venue"
},
  "geometry": {"coordinates":[5.2942438126,50.7116546631],"type":"Point"}
}