{
  "type": "Feature",
  "properties": {
    "iso:country":"BE",
    "sg:address":"Hekkestraat 20ba",
    "sg:city":"Aalst",
    "sg:orig_category":"Goederenvervoer over de weg",
    "sg:phone":"+32 53 70 33 89",
    "sg:postcode":"9308",
    "sg:province":"Oost-Vlaanderen",
    "wof:name":"Transport De Wolf",
    "wof:placetype":"venue"
},
  "geometry": {"coordinates":[4.0347590446,50.9603500366],"type":"Point"}
}