{
  "type": "Feature",
  "properties": {
    "iso:country":"BE",
    "sg:address":"Keppestraat 92",
    "sg:city":"Aalst (erembodegem)",
    "sg:classifiers":[
        {
            "category":"Banks & Credit Unions",
            "subcategory":"Bureau De Change",
            "type":"Services"
        }
    ],
    "sg:phone":"+32 53 21 41 60",
    "sg:postcode":"9320",
    "sg:province":"Oost-Vlaanderen",
    "sg:tags":[
        "-",
        "household",
        "gas"
    ],
    "wof:name":"De Ridder",
    "wof:placetype":"venue"
},
  "geometry": {"coordinates":[4.0553851128,50.9209976196],"type":"Point"}
}