{
  "type": "Feature",
  "properties": {
    "addr:full":"Chauss\u00e9e De Perwez 137 Namur (saint-servais) Namur 5002",
    "addr:housenumber":"137",
    "addr:postcode":"5002",
    "addr:street":"Chausse\u0301E De Perwez",
    "iso:country":"BE",
    "sg:address":"Chauss\u00e9e De Perwez 137",
    "sg:city":"Namur (saint-servais)",
    "sg:classifiers":[
        {
            "category":"Retail",
            "subcategory":"Laundry & Dry Cleaning",
            "type":"Services"
        }
    ],
    "sg:phone":"+32 81 73 33 25",
    "sg:postcode":"5002",
    "sg:province":"Namur",
    "sg:tags":[
        "dyer",
        "cleaner"
    ],
    "wof:name":"Mosane (la)",
    "wof:placetype":"venue"
},
  "geometry": {"coordinates":[4.8462319374,50.4782791138],"type":"Point"}
}