{
  "type": "Feature",
  "properties": {
    "addr:full":"Ch De Forest 54 Saint-gilles (bruxelles) Bruxelles-Capitale 1060",
    "addr:housenumber":"54",
    "addr:postcode":"1060",
    "addr:street":"Ch De Forest",
    "iso:country":"BE",
    "sg:address":"Ch De Forest 54",
    "sg:city":"Saint-gilles (bruxelles)",
    "sg:orig_category":"Kapsalons",
    "sg:phone":"+32 2 538 31 88",
    "sg:postcode":"1060",
    "sg:province":"Bruxelles-Capitale",
    "wof:name":"Alain",
    "wof:placetype":"venue"
},
  "geometry": {"coordinates":[4.3409638405,50.8318557739],"type":"Point"}
}