{
  "type": "Feature",
  "properties": {
    "iso:country":"BE",
    "sg:address":"Stanleystraat 42",
    "sg:city":"Ukkel/uccle",
    "sg:orig_category":"Tweedehandsgoederen",
    "sg:phone":"+32 2 347 06 98",
    "sg:postcode":"1180",
    "sg:province":"Bruxelles-Capitale",
    "wof:name":"Maison Zig & Puce",
    "wof:placetype":"venue"
},
  "geometry": {"coordinates":[4.3654661179,50.8158454895],"type":"Point"}
}