{
  "type": "Feature",
  "properties": {
    "iso:country":"BE",
    "sg:address":"Kortenbergsesteenweg 74",
    "sg:city":"Steenokkerzeel",
    "sg:orig_category":"Producteurs de l\u00e9gumes",
    "sg:phone":"+32 2 759 72 70",
    "sg:postcode":"1820",
    "sg:province":"Vlaams-Brabant",
    "wof:name":"Maurice Huys",
    "wof:placetype":"venue"
},
  "geometry": {"coordinates":[4.5204539299,50.9038772583],"type":"Point"}
}