{
  "type": "Feature",
  "properties": {
    "addr:full":"Diksmuidsestraat 10 Ieper West-Vlaanderen 8900",
    "addr:housenumber":"10",
    "addr:postcode":"8900",
    "addr:street":"Diksmuidsestraat",
    "iso:country":"BE",
    "sg:address":"Diksmuidsestraat 10",
    "sg:city":"Ieper",
    "sg:classifiers":[
        {
            "category":"Shopping",
            "subcategory":"Clothing, Apparel, & Fashions",
            "type":"Retail Goods"
        }
    ],
    "sg:phone":"+32 57 20 00 80",
    "sg:postcode":"8900",
    "sg:province":"West-Vlaanderen",
    "sg:tags":[
        "underwear",
        "lingerie",
        "-"
    ],
    "wof:name":"Okapi",
    "wof:placetype":"venue"
},
  "geometry": {"coordinates":[2.886854887,50.8520965576],"type":"Point"}
}