{
  "type": "Feature",
  "properties": {
    "iso:country":"BE",
    "sg:address":"Pamelstraat 323",
    "sg:city":"Ninove",
    "sg:orig_category":"Woningbouw",
    "sg:phone":"+32 54 32 50 27",
    "sg:postcode":"9400",
    "sg:province":"Oost-Vlaanderen",
    "wof:name":"Stevens Gebroeders",
    "wof:placetype":"venue"
},
  "geometry": {"coordinates":[4.0359039307,50.8396987915],"type":"Point"}
}