{
  "type": "Feature",
  "properties": {
    "addr:full":"Hoogveld 1 Zoersel Antwerpen 2980",
    "addr:housenumber":"1",
    "addr:postcode":"2980",
    "addr:street":"Hoogveld",
    "iso:country":"BE",
    "sg:address":"Hoogveld 1",
    "sg:city":"Zoersel",
    "sg:classifiers":[
        {
            "category":"Building & Trades",
            "subcategory":"Construction",
            "type":"Services"
        }
    ],
    "sg:phone":"+32 3 312 29 45",
    "sg:postcode":"2980",
    "sg:province":"Antwerpen",
    "sg:tags":[
        "stucco",
        "contractor"
    ],
    "wof:name":"Van Dijck Karel & Zn Bvba",
    "wof:placetype":"venue"
},
  "geometry": {"coordinates":[4.7099499702,51.2623710632],"type":"Point"}
}