{
  "type": "Feature",
  "properties": {
    "addr:full":"Rue Saint-eloy 2a Waremme Li\u00e8ge 4300",
    "addr:housenumber":"2a",
    "addr:postcode":"4300",
    "addr:street":"Rue Saint-Eloy",
    "iso:country":"BE",
    "sg:address":"Rue Saint-eloy 2a",
    "sg:city":"Waremme",
    "sg:classifiers":[
        {
            "category":"Autos & Motor Vehicles",
            "subcategory":"Fuel & Gas Station",
            "type":"Retail Goods"
        }
    ],
    "sg:phone":"+32 19 33 02 87",
    "sg:postcode":"4300",
    "sg:province":"Li\u00e8ge",
    "sg:tags":[
        "stations-service",
        "carburants"
    ],
    "wof:name":"Jet",
    "wof:placetype":"venue"
},
  "geometry": {"coordinates":[5.2653260231,50.6964492798],"type":"Point"}
}