{
  "type": "Feature",
  "properties": {
    "addr:full":"Rue Basse Pr\u00c9alle 133 Herstal Li\u00e8ge 4040",
    "addr:housenumber":"133",
    "addr:postcode":"4040",
    "addr:street":"Rue Basse Pre\u0301Alle",
    "iso:country":"BE",
    "sg:address":"Rue Basse Pr\u00c9alle 133",
    "sg:city":"Herstal",
    "sg:orig_category":"Meubles D\u00e9taillants, Am\u00e9nagement de B\u00e2timents et de Cuisines. Assistances juridiques. Fabrication an",
    "sg:phone":"+32 4 264 92 66",
    "sg:postcode":"4040",
    "sg:province":"Li\u00e8ge",
    "wof:name":"Europa Cuisine",
    "wof:placetype":"venue"
},
  "geometry": {"coordinates":[5.6118431091,50.666229248],"type":"Point"}
}