{
  "type": "Feature",
  "properties": {
    "addr:full":"Kerkhofweg 10 Laakdal Antwerpen 2430",
    "addr:housenumber":"10",
    "addr:postcode":"2430",
    "addr:street":"Kerkhofweg",
    "iso:country":"BE",
    "sg:address":"Kerkhofweg 10",
    "sg:city":"Laakdal",
    "sg:orig_category":"Tuinen",
    "sg:phone":"+32 14 86 75 30",
    "sg:postcode":"2430",
    "sg:province":"Antwerpen",
    "wof:name":"Couwberghs",
    "wof:placetype":"venue"
},
  "geometry": {"coordinates":[5.0687851906,51.0857543945],"type":"Point"}
}