{
  "type": "Feature",
  "properties": {
    "iso:country":"BE",
    "sg:address":"Smissestraat 43",
    "sg:city":"Laakdal",
    "sg:orig_category":"V\u00e9los. Articles de jardin",
    "sg:phone":"+32 13 67 44 56",
    "sg:postcode":"2430",
    "sg:province":"Antwerpen",
    "wof:name":"Fa. T\u00b4wieleke",
    "wof:placetype":"venue"
},
  "geometry": {"coordinates":[5.0264749527,51.0801200867],"type":"Point"}
}