{
  "type": "Feature",
  "properties": {
    "iso:country":"BE",
    "sg:address":"Morgenlandstraat 15",
    "sg:city":"Etterbeek/etterbeek",
    "sg:orig_category":"Reclamebureaus",
    "sg:phone":"+32 2 649 67 93",
    "sg:postcode":"1040",
    "sg:province":"Bruxelles-Capitale",
    "wof:name":"Publi D\u00c9cor Collinge",
    "wof:placetype":"venue"
},
  "geometry": {"coordinates":[4.3803930283,50.8345489502],"type":"Point"}
}