{
  "type": "Feature",
  "properties": {
    "iso:country":"BE",
    "sg:address":"Rue Du Vivier 36",
    "sg:city":"Oupeye (heure-le-romain)",
    "sg:classifiers":[
        {
            "category":"Health Services",
            "subcategory":"Doctor",
            "type":"Services"
        }
    ],
    "sg:phone":"+32 4 286 36 27",
    "sg:postcode":"4682",
    "sg:province":"Li\u00e8ge",
    "sg:tags":[
        "medicinephysicians",
        "surgeon"
    ],
    "wof:name":"Bonhomme S",
    "wof:placetype":"venue"
},
  "geometry": {"coordinates":[5.6338701248,50.7312393188],"type":"Point"}
}