{
  "type": "Feature",
  "properties": {
    "addr:full":"Warande 7 Oud-turnhout Antwerpen 2360",
    "addr:housenumber":"7",
    "addr:postcode":"2360",
    "addr:street":"Warande",
    "iso:country":"BE",
    "sg:address":"Warande 7",
    "sg:city":"Oud-turnhout",
    "sg:orig_category":"Boekhouders",
    "sg:phone":"+32 14 45 02 26",
    "sg:postcode":"2360",
    "sg:province":"Antwerpen",
    "wof:name":"Antoine Geentjens",
    "wof:placetype":"venue"
},
  "geometry": {"coordinates":[5.0093231201,51.31016922],"type":"Point"}
}