{
  "type": "Feature",
  "properties": {
    "addr:full":"Pastoor Somerslaan 24 Puurs (breendonk) Antwerpen 2870",
    "addr:housenumber":"24",
    "addr:postcode":"2870",
    "addr:street":"Pastoor Somerslaan",
    "iso:country":"BE",
    "sg:address":"Pastoor Somerslaan 24",
    "sg:city":"Puurs (breendonk)",
    "sg:classifiers":[
        {
            "category":"Retail",
            "subcategory":"Funeral Services",
            "type":"Services"
        }
    ],
    "sg:phone":"+32 3 886 72 73",
    "sg:postcode":"2870",
    "sg:province":"Antwerpen",
    "sg:tags":[
        "director"
    ],
    "wof:name":"Stevens",
    "wof:placetype":"venue"
},
  "geometry": {"coordinates":[4.2772698402,51.0763244629],"type":"Point"}
}