{
  "type": "Feature",
  "properties": {
    "addr:full":"Mechelsesteenweg 100 Leuven Vlaams-Brabant 3000",
    "addr:housenumber":"100",
    "addr:postcode":"3000",
    "addr:street":"Mechelsesteenweg",
    "iso:country":"BE",
    "sg:address":"Mechelsesteenweg 100",
    "sg:city":"Leuven",
    "sg:classifiers":[
        {
            "category":"Retail",
            "subcategory":"Auto Repair",
            "type":"Services"
        }
    ],
    "sg:phone":"+32 495 50 80 87",
    "sg:postcode":"3000",
    "sg:province":"Vlaams-Brabant",
    "sg:tags":[
        "garage"
    ],
    "wof:name":"Chikhi",
    "wof:placetype":"venue"
},
  "geometry": {"coordinates":[4.6889748573,50.8870429993],"type":"Point"}
}