{
  "type": "Feature",
  "properties": {
    "iso:country":"BE",
    "sg:address":"Vlaamsesteenweg 75",
    "sg:city":"Brussel/bruxelles",
    "sg:orig_category":"Decoratiestoffen and buitenhuistextiel Fab Fantasieartikelen",
    "sg:phone":"+32 2 513 78 74",
    "sg:postcode":"1000",
    "sg:province":"Bruxelles-Capitale",
    "wof:name":"Abac",
    "wof:placetype":"venue"
},
  "geometry": {"coordinates":[4.3462758064,50.8522949219],"type":"Point"}
}