{
  "type": "Feature",
  "properties": {
    "addr:full":"Chauss\u00e9e De Bruxelles 4 Sombreffe Namur 5140",
    "addr:housenumber":"4",
    "addr:postcode":"5140",
    "addr:street":"Chausse\u0301E De Bruxelles",
    "iso:country":"BE",
    "sg:address":"Chauss\u00e9e De Bruxelles 4",
    "sg:city":"Sombreffe",
    "sg:classifiers":[
        {
            "category":"Building & Trades",
            "subcategory":"Locksmith",
            "type":"Services"
        }
    ],
    "sg:phone":"+32 71 88 62 32",
    "sg:postcode":"5140",
    "sg:province":"Namur",
    "sg:tags":[
        "lock",
        "key"
    ],
    "wof:name":"Serrurerie Generale Hayon",
    "wof:placetype":"venue"
},
  "geometry": {"coordinates":[4.618637085,50.5244598389],"type":"Point"}
}