{
  "type": "Feature",
  "properties": {
    "iso:country":"BE",
    "sg:address":"De Merodelei 96",
    "sg:city":"Turnhout",
    "sg:orig_category":"Immobili\u00ebnkantoren",
    "sg:phone":"+32 14 41 80 74",
    "sg:postcode":"2300",
    "sg:province":"Antwerpen",
    "wof:name":"I.b.s.",
    "wof:placetype":"venue"
},
  "geometry": {"coordinates":[4.9387631416,51.3219413757],"type":"Point"}
}