{
  "type": "Feature",
  "properties": {
    "iso:country":"BE",
    "sg:address":"Rue Du Veill\u00c9 44",
    "sg:city":"Brunehaut",
    "sg:orig_category":"M\u00e9decins and sp\u00e9cialistes",
    "sg:phone":"+32 69 64 94 21",
    "sg:postcode":"7620",
    "sg:province":"Hainaut",
    "wof:name":"V. Bonnet",
    "wof:placetype":"venue"
},
  "geometry": {"coordinates":[3.3765089512,50.5482559204],"type":"Point"}
}