{
  "type": "Feature",
  "properties": {
    "iso:country":"BE",
    "sg:address":"Leopoldlaan 17",
    "sg:city":"Middelkerke",
    "sg:orig_category":"V\u00eatements pour Hommes",
    "sg:phone":"+32 59 31 06 20",
    "sg:postcode":"8430",
    "sg:province":"West-Vlaanderen",
    "wof:name":"Rufus Men's Wear",
    "wof:placetype":"venue"
},
  "geometry": {"coordinates":[2.815666914,51.1877250671],"type":"Point"}
}