{
  "type": "Feature",
  "properties": {
    "addr:full":"Rue De La Station 19 Silly Hainaut 7830",
    "addr:housenumber":"19",
    "addr:postcode":"7830",
    "addr:street":"Rue De La Station",
    "iso:country":"BE",
    "sg:address":"Rue De La Station 19",
    "sg:city":"Silly",
    "sg:classifiers":[
        {
            "category":"Cafe",
            "type":"Food & Drink"
        }
    ],
    "sg:phone":"+32 68 55 18 88",
    "sg:postcode":"7830",
    "sg:province":"Hainaut",
    "sg:tags":[
        "caf\u00e9s"
    ],
    "wof:name":"Miguel Brisaert",
    "wof:placetype":"venue"
},
  "geometry": {"coordinates":[3.9201440811,50.6506729126],"type":"Point"}
}