{
  "type": "Feature",
  "properties": {
    "addr:full":"Rue Thier Du Moulin 20 Villers-le-bouillet Li\u00e8ge 4530",
    "addr:housenumber":"20",
    "addr:postcode":"4530",
    "addr:street":"Rue Thier Du Moulin",
    "iso:country":"BE",
    "sg:address":"Rue Thier Du Moulin 20",
    "sg:city":"Villers-le-bouillet",
    "sg:orig_category":"Quincailleries. R\u00e9parations \u00e0 domicile d'articles divers. Plomberie, chauffage and installations san",
    "sg:phone":"+32 85 23 36 72",
    "sg:postcode":"4530",
    "sg:province":"Li\u00e8ge",
    "wof:name":"Serge Godefroid",
    "wof:placetype":"venue"
},
  "geometry": {"coordinates":[5.2807211876,50.5651473999],"type":"Point"}
}