{
  "type": "Feature",
  "properties": {
    "iso:country":"BE",
    "sg:address":"Sportstraat 52",
    "sg:city":"Kaprijke",
    "sg:orig_category":"Brood, gebak and snoepgoed",
    "sg:phone":"+32 9 377 48 94",
    "sg:postcode":"9971",
    "sg:province":"Oost-Vlaanderen",
    "wof:name":"Katrien Haers",
    "wof:placetype":"venue"
},
  "geometry": {"coordinates":[3.6351559162,51.1913490295],"type":"Point"}
}