{
  "type": "Feature",
  "properties": {
    "iso:country":"BE",
    "sg:address":"Rue De L'industrie 152",
    "sg:city":"Frameries",
    "sg:classifiers":[
        {
            "category":"Autos & Motor Vehicles",
            "subcategory":"Fuel & Gas Station",
            "type":"Retail Goods"
        }
    ],
    "sg:phone":"+32 65 66 41 67",
    "sg:postcode":"7080",
    "sg:province":"Hainaut",
    "sg:tags":[
        "stations-service",
        "carburants"
    ],
    "wof:name":"Fuel Spilmont Frameries",
    "wof:placetype":"venue"
},
  "geometry": {"coordinates":[3.8787279129,50.4095344543],"type":"Point"}
}