{
  "type": "Feature",
  "properties": {
    "iso:country":"BE",
    "sg:address":"Kapelstraat 64",
    "sg:city":"Lille",
    "sg:classifiers":[
        {
            "category":"Parking",
            "subcategory":"Lot",
            "type":"Transportation"
        }
    ],
    "sg:phone":"+32 14 88 28 11",
    "sg:postcode":"2275",
    "sg:province":"Antwerpen",
    "sg:tags":[
        "parking-places",
        "laying-out"
    ],
    "wof:name":"Dockx Bestratingswerken Bvba",
    "wof:placetype":"venue"
},
  "geometry": {"coordinates":[4.826004982,51.2473297119],"type":"Point"}
}