{
  "type": "Feature",
  "properties": {
    "addr:full":"Kolkstraat 18 Dessel Antwerpen 2480",
    "addr:housenumber":"18",
    "addr:postcode":"2480",
    "addr:street":"Kolkstraat",
    "iso:country":"BE",
    "sg:address":"Kolkstraat 18",
    "sg:city":"Dessel",
    "sg:classifiers":[
        {
            "category":"Cafe",
            "type":"Food & Drink"
        }
    ],
    "sg:phone":"+32 14 37 71 22",
    "sg:postcode":"2480",
    "sg:province":"Antwerpen",
    "sg:tags":[
        "caf\u00e9s"
    ],
    "wof:name":"Parochiehuis",
    "wof:placetype":"venue"
},
  "geometry": {"coordinates":[5.114648819,51.2384643555],"type":"Point"}
}