{
  "type": "Feature",
  "properties": {
    "addr:full":"Rue De La-roche 32 Houffalize Luxembourg 6660",
    "addr:housenumber":"32",
    "addr:postcode":"6660",
    "addr:street":"Rue De La-Roche",
    "iso:country":"BE",
    "sg:address":"Rue De La-roche 32",
    "sg:city":"Houffalize",
    "sg:orig_category":"RESTAURANTS: H\u00d4TELS",
    "sg:phone":"+32 61 28 81 40",
    "sg:postcode":"6660",
    "sg:province":"Luxembourg",
    "wof:name":"H\u00d4tel L'ermitage",
    "wof:placetype":"venue"
},
  "geometry": {"coordinates":[5.7757411003,50.1317634583],"type":"Point"}
}