{
  "type": "Feature",
  "properties": {
    "addr:full":"Rue D'ougr\u00e9e 11 Seraing (boncelles) Li\u00e8ge 4100",
    "addr:housenumber":"11",
    "addr:postcode":"4100",
    "addr:street":"Rue D'Ougre \u0301E",
    "iso:country":"BE",
    "sg:address":"Rue D'ougr\u00e9e 11",
    "sg:city":"Seraing (boncelles)",
    "sg:classifiers":[
        {
            "category":"Personal",
            "subcategory":"Beauty Salon",
            "type":"Services"
        }
    ],
    "sg:phone":"+32 4 337 78 20",
    "sg:postcode":"4100",
    "sg:province":"Li\u00e8ge",
    "sg:tags":[
        "lady",
        "-",
        "hairdressing"
    ],
    "wof:name":"Maryl\u00e8ne Coiffure",
    "wof:placetype":"venue"
},
  "geometry": {"coordinates":[5.5082731247,50.5836410522],"type":"Point"}
}