{
  "type": "Feature",
  "properties": {
    "addr:full":"Guido Gezellestraat 31ba Wielsbeke West-Vlaanderen 8710",
    "addr:housenumber":"31ba",
    "addr:postcode":"8710",
    "addr:street":"Guido Gezellestraat",
    "iso:country":"BE",
    "sg:address":"Guido Gezellestraat 31ba",
    "sg:city":"Wielsbeke",
    "sg:classifiers":[
        {
            "category":"Arena",
            "subcategory":"Sports Club",
            "type":"Entertainment"
        }
    ],
    "sg:phone":"+32 56 66 83 56",
    "sg:postcode":"8710",
    "sg:province":"West-Vlaanderen",
    "sg:tags":[
        "de"
    ],
    "wof:name":"De Postduif",
    "wof:placetype":"venue"
},
  "geometry": {"coordinates":[3.3288719654,50.8941688538],"type":"Point"}
}