{
  "type": "Feature",
  "properties": {
    "addr:full":"Elfde-julistraat 109 Harelbeke West-Vlaanderen 8530",
    "addr:housenumber":"109",
    "addr:postcode":"8530",
    "iso:country":"BE",
    "sg:address":"Elfde-julistraat 109",
    "sg:city":"Harelbeke",
    "sg:orig_category":"Epiceries",
    "sg:phone":"+32 56 71 36 62",
    "sg:postcode":"8530",
    "sg:province":"West-Vlaanderen",
    "wof:name":"Spar",
    "wof:placetype":"venue"
},
  "geometry": {"coordinates":[3.298320055,50.8457717896],"type":"Point"}
}