{
  "type": "Feature",
  "properties": {
    "iso:country":"BE",
    "sg:address":"Provincieweg 201",
    "sg:city":"Gistel",
    "sg:orig_category":"Rundveehouders",
    "sg:phone":"+32 59 27 87 79",
    "sg:postcode":"8470",
    "sg:province":"West-Vlaanderen",
    "wof:name":"Maurits Coddens",
    "wof:placetype":"venue"
},
  "geometry": {"coordinates":[2.9401578903,51.1162338257],"type":"Point"}
}