{
  "type": "Feature",
  "properties": {
    "iso:country":"BE",
    "sg:address":"Arendstraat 3",
    "sg:city":"Anzegem",
    "sg:classifiers":[
        {
            "category":"Retail",
            "subcategory":"Auto Repair",
            "type":"Services"
        }
    ],
    "sg:phone":"+32 56 68 89 81",
    "sg:postcode":"8570",
    "sg:province":"West-Vlaanderen",
    "sg:tags":[
        "garage"
    ],
    "wof:name":"De Winter W",
    "wof:placetype":"venue"
},
  "geometry": {"coordinates":[3.4814488888,50.8531684875],"type":"Point"}
}