{
  "type": "Feature",
  "properties": {
    "iso:country":"BE",
    "sg:address":"Perronstraat 12a",
    "sg:city":"Bilzen (munsterbilzen)",
    "sg:classifiers":[
        {
            "category":"Bars & Pubs",
            "type":"Food & Drink"
        }
    ],
    "sg:phone":"+32 89 41 76 64",
    "sg:postcode":"3740",
    "sg:province":"Limburg",
    "wof:name":"Centrum",
    "wof:placetype":"venue"
},
  "geometry": {"coordinates":[5.5269532204,50.8888168335],"type":"Point"}
}