{
  "type": "Feature",
  "properties": {
    "addr:full":"Gentse Steenweg 281 Zottegem Oost-Vlaanderen 9620",
    "addr:housenumber":"281",
    "addr:postcode":"9620",
    "addr:street":"Gentse Steenweg",
    "iso:country":"BE",
    "sg:address":"Gentse Steenweg 281",
    "sg:city":"Zottegem",
    "sg:orig_category":"RESTAURANTS: CAF\u00c9S",
    "sg:phone":"+32 9 360 99 09",
    "sg:postcode":"9620",
    "sg:province":"Oost-Vlaanderen",
    "wof:name":"Taverne Chapoo",
    "wof:placetype":"venue"
},
  "geometry": {"coordinates":[3.8306729794,50.8870162964],"type":"Point"}
}