{
  "type": "Feature",
  "properties": {
    "iso:country":"BE",
    "sg:address":"Londerzeelseweg 139",
    "sg:city":"Kapelle-op-den-bos",
    "sg:orig_category":"Pain, p\u00e2tisseries and confiseries",
    "sg:phone":"+32 15 71 39 14",
    "sg:postcode":"1880",
    "sg:province":"Vlaams-Brabant",
    "wof:name":"Snoepcenter De Buyser",
    "wof:placetype":"venue"
},
  "geometry": {"coordinates":[4.3435401917,51.0130081177],"type":"Point"}
}