{
  "type": "Feature",
  "properties": {
    "addr:full":"Mosselstraat 14 Gistel West-Vlaanderen 8470",
    "addr:housenumber":"14",
    "addr:postcode":"8470",
    "addr:street":"Mosselstraat",
    "iso:country":"BE",
    "sg:address":"Mosselstraat 14",
    "sg:city":"Gistel",
    "sg:orig_category":"Mat\u00e9riel de T\u00e9l\u00e9communication",
    "sg:phone":"+32 59 27 67 35",
    "sg:postcode":"8470",
    "sg:province":"West-Vlaanderen",
    "wof:name":"Demeulemeester Filip",
    "wof:placetype":"venue"
},
  "geometry": {"coordinates":[2.968569994,51.1552200317],"type":"Point"}
}