{
  "type": "Feature",
  "properties": {
    "addr:full":"Rue Des Clercs 6 Mons Hainaut 7000",
    "addr:housenumber":"6",
    "addr:postcode":"7000",
    "addr:street":"Rue Des Clercs;Hainaut",
    "iso:country":"BE",
    "sg:address":"Rue Des Clercs 6",
    "sg:city":"Mons",
    "sg:classifiers":[
        {
            "category":"Bars & Pubs",
            "type":"Food & Drink"
        }
    ],
    "sg:phone":"+32 65 34 84 25",
    "sg:postcode":"7000",
    "sg:province":"Hainaut",
    "wof:name":"Pacific Sprl",
    "wof:placetype":"venue"
},
  "geometry": {"coordinates":[3.9515719414,50.4541397095],"type":"Point"}
}