{
  "type": "Feature",
  "properties": {
    "iso:country":"BE",
    "sg:address":"Driepikkelstraat 6",
    "sg:city":"Ledegem (rollegem Kapelle)",
    "sg:classifiers":[
        {
            "category":"Home & Garden",
            "subcategory":"Home Furnishings",
            "type":"Retail Goods"
        }
    ],
    "sg:phone":"+32 56 50 61 31",
    "sg:postcode":"8880",
    "sg:province":"West-Vlaanderen",
    "sg:tags":[
        "interior",
        "decoration"
    ],
    "wof:name":"Deco Nova Bvba",
    "wof:placetype":"venue"
},
  "geometry": {"coordinates":[3.1377050877,50.8798065186],"type":"Point"}
}