{
  "type": "Feature",
  "properties": {
    "addr:full":"Rue D\u00c9sir\u00c9 Janson 14 Herstal Li\u00e8ge 4040",
    "addr:housenumber":"14",
    "addr:postcode":"4040",
    "addr:street":"Rue De\u0301Sire\u0301 Janson",
    "iso:country":"BE",
    "sg:address":"Rue D\u00c9sir\u00c9 Janson 14",
    "sg:city":"Herstal",
    "sg:orig_category":"Gespecialiseerde residenti\u00eble bouw Woningbouw",
    "sg:phone":"+32 495 66 00 56",
    "sg:postcode":"4040",
    "sg:province":"Li\u00e8ge",
    "wof:name":"Angeletti Marcel",
    "wof:placetype":"venue"
},
  "geometry": {"coordinates":[5.6271491051,50.6731872559],"type":"Point"}
}