{
  "type": "Feature",
  "properties": {
    "addr:full":"Kruiskalsijdestraat 33 Diksmuide West-Vlaanderen 8600",
    "addr:housenumber":"33",
    "addr:postcode":"8600",
    "addr:street":"Kruiskalsijdestraat",
    "iso:country":"BE",
    "sg:address":"Kruiskalsijdestraat 33",
    "sg:city":"Diksmuide",
    "sg:orig_category":"Mat\u00e9riaux de construction Gr",
    "sg:phone":"+32 51 50 11 02",
    "sg:postcode":"8600",
    "sg:province":"West-Vlaanderen",
    "wof:name":"Bouwstoffen Fosse",
    "wof:placetype":"venue"
},
  "geometry": {"coordinates":[2.8657801151,51.0334663391],"type":"Point"}
}