{
  "type": "Feature",
  "properties": {
    "addr:full":"Sint-pietersstraat 20 Ieper West-Vlaanderen 8906",
    "addr:housenumber":"20",
    "addr:postcode":"8906",
    "addr:street":"Sint-Pietersstraat",
    "iso:country":"BE",
    "sg:address":"Sint-pietersstraat 20",
    "sg:city":"Ieper",
    "sg:classifiers":[
        {
            "category":"Professional",
            "type":"Services"
        }
    ],
    "sg:phone":"+32 57 42 29 07",
    "sg:postcode":"8906",
    "sg:province":"West-Vlaanderen",
    "sg:tags":[
        "aux",
        "diver",
        "personnes"
    ],
    "wof:name":"Jos\u00c9 Lemahieu",
    "wof:placetype":"venue"
},
  "geometry": {"coordinates":[2.7897400856,50.8705749512],"type":"Point"}
}