{
  "type": "Feature",
  "properties": {
    "addr:full":"Steenkaaistraat 13 Dendermonde (baasrode) Oost-Vlaanderen 9200",
    "addr:housenumber":"13",
    "addr:postcode":"9200",
    "addr:street":"Steenkaaistraat",
    "iso:country":"BE",
    "sg:address":"Steenkaaistraat 13",
    "sg:city":"Dendermonde (baasrode)",
    "sg:classifiers":[
        {
            "category":"Professional",
            "subcategory":"Printing & Photocopies",
            "type":"Services"
        }
    ],
    "sg:phone":"+32 52 33 16 44",
    "sg:postcode":"9200",
    "sg:province":"Oost-Vlaanderen",
    "sg:tags":[
        "silkscreen",
        "-"
    ],
    "wof:name":"Proshirt",
    "wof:placetype":"venue"
},
  "geometry": {"coordinates":[4.0983099937,51.0315208435],"type":"Point"}
}