{
  "type": "Feature",
  "properties": {
    "addr:full":"Sluisstraat 26 Diepenbeek Limburg 3590",
    "addr:housenumber":"26",
    "addr:postcode":"3590",
    "addr:street":"Sluisstraat",
    "iso:country":"BE",
    "sg:address":"Sluisstraat 26",
    "sg:city":"Diepenbeek",
    "sg:orig_category":"M\u00e9decins and sp\u00e9cialistes",
    "sg:phone":"+32 11 22 54 58",
    "sg:postcode":"3590",
    "sg:province":"Limburg",
    "wof:name":"M. Aelvoet",
    "wof:placetype":"venue"
},
  "geometry": {"coordinates":[5.4270858765,50.9423789978],"type":"Point"}
}