{
  "type": "Feature",
  "properties": {
    "addr:full":"Zoning Industriel De Frasnes 4 Les Bons Villers (frasnes-lez-gosselies) Hainaut 6210",
    "addr:housenumber":"4",
    "addr:postcode":"6210",
    "addr:street":"Zoning Industriel De Frasnes",
    "iso:country":"BE",
    "sg:address":"Zoning Industriel De Frasnes 4",
    "sg:city":"Les Bons Villers (frasnes-lez-gosselies)",
    "sg:classifiers":[
        {
            "category":"Banks & Credit Unions",
            "subcategory":"Atm",
            "type":"Services"
        }
    ],
    "sg:phone":"+32 71 85 17 64",
    "sg:postcode":"6210",
    "sg:province":"Hainaut",
    "sg:tags":[
        "case",
        "crate",
        "maker"
    ],
    "wof:name":"Cuvelier Fr\u00e8res Sca",
    "wof:placetype":"venue"
},
  "geometry": {"coordinates":[4.473528862,50.5546188354],"type":"Point"}
}