{
  "type": "Feature",
  "properties": {
    "iso:country":"BE",
    "sg:address":"Boulevard Chapman 6",
    "sg:city":"Spa",
    "sg:classifiers":[
        {
            "category":"Health Services",
            "subcategory":"Doctor",
            "type":"Services"
        }
    ],
    "sg:phone":"+32 87 77 52 94",
    "sg:postcode":"4900",
    "sg:province":"Li\u00e8ge",
    "sg:tags":[
        "medicinephysicians",
        "surgeon"
    ],
    "wof:name":"Berckmoes J",
    "wof:placetype":"venue"
},
  "geometry": {"coordinates":[5.86714077,50.4886894226],"type":"Point"}
}