{
  "type": "Feature",
  "properties": {
    "addr:full":"Belv\u00c9d\u00c8restraat 30 Elsene/ixelles Bruxelles-Capitale 1050",
    "addr:housenumber":"30",
    "addr:postcode":"1050",
    "addr:street":"Belve\u0301De\u0300Restraat",
    "iso:country":"BE",
    "sg:address":"Belv\u00c9d\u00c8restraat 30",
    "sg:city":"Elsene/ixelles",
    "sg:classifiers":[
        {
            "category":"Cafe",
            "type":"Food & Drink"
        }
    ],
    "sg:phone":"+32 2 648 38 43",
    "sg:postcode":"1050",
    "sg:province":"Bruxelles-Capitale",
    "sg:tags":[
        "caf\u00e9s"
    ],
    "wof:name":"Chez Jos\u00c9",
    "wof:placetype":"venue"
},
  "geometry": {"coordinates":[4.3731079102,50.8264465332],"type":"Point"}
}