{
  "type": "Feature",
  "properties": {
    "iso:country":"BE",
    "sg:address":"De Waterwilgen 4",
    "sg:city":"Brugge",
    "sg:orig_category":"Binnenhuisarchitecten",
    "sg:phone":"+32 50 35 53 37",
    "sg:postcode":"8310",
    "sg:province":"West-Vlaanderen",
    "wof:name":"Jan De Bruyne",
    "wof:placetype":"venue"
},
  "geometry": {"coordinates":[3.2449839115,51.2148590088],"type":"Point"}
}