{
  "type": "Feature",
  "properties": {
    "addr:full":"Avenue Brugmann 231 Ukkel/uccle Bruxelles-Capitale 1180",
    "addr:housenumber":"231",
    "addr:postcode":"1180",
    "addr:street":"Avenue Brugmann;/",
    "iso:country":"BE",
    "sg:address":"Avenue Brugmann 231",
    "sg:city":"Ukkel/uccle",
    "sg:orig_category":"Kapsalons",
    "sg:phone":"+32 2 344 13 97",
    "sg:postcode":"1180",
    "sg:province":"Bruxelles-Capitale",
    "wof:name":"Jacques Dessange",
    "wof:placetype":"venue"
},
  "geometry": {"coordinates":[4.347799778,50.8133888245],"type":"Point"}
}