{
  "type": "Feature",
  "properties": {
    "addr:full":"Krekelweg 10 Oud-turnhout Antwerpen 2360",
    "addr:housenumber":"10",
    "addr:postcode":"2360",
    "addr:street":"Krekelweg",
    "iso:country":"BE",
    "sg:address":"Krekelweg 10",
    "sg:city":"Oud-turnhout",
    "sg:orig_category":"Quincailleries",
    "sg:phone":"+32 14 45 36 22",
    "sg:postcode":"2360",
    "sg:province":"Antwerpen",
    "wof:name":"Cph",
    "wof:placetype":"venue"
},
  "geometry": {"coordinates":[5.0201258659,51.3184318542],"type":"Point"}
}