{
  "type": "Feature",
  "properties": {
    "iso:country":"BE",
    "sg:address":"Chemin De La Place 8",
    "sg:city":"Tournai (barry - Maulde)",
    "sg:classifiers":[
        {
            "category":"Insurance",
            "subcategory":"Insurance Agent",
            "type":"Services"
        }
    ],
    "sg:phone":"+32 69 54 64 51",
    "sg:postcode":"7534",
    "sg:province":"Hainaut",
    "sg:tags":[
        "broker"
    ],
    "wof:name":"Westrade Assurances Sa",
    "wof:placetype":"venue"
},
  "geometry": {"coordinates":[3.543694973,50.5866851807],"type":"Point"}
}