{
  "type": "Feature",
  "properties": {
    "iso:country":"BE",
    "sg:address":"Leopoldlaan 156",
    "sg:city":"Overpelt",
    "sg:classifiers":[
        {
            "category":"Utilities",
            "subcategory":"Fuel Oil & Lpg",
            "type":"Services"
        }
    ],
    "sg:phone":"+32 11 64 10 80",
    "sg:postcode":"3900",
    "sg:province":"Limburg",
    "sg:tags":[
        "stations-service",
        "combustible",
        "carburants"
    ],
    "wof:name":"Verkoyen Brandstoffen",
    "wof:placetype":"venue"
},
  "geometry": {"coordinates":[5.429787159,51.2268218994],"type":"Point"}
}