{
  "type": "Feature",
  "properties": {
    "iso:country":"BE",
    "sg:address":"Chauss\u00e9e De Bruxelles 307",
    "sg:city":"Charleroi (dampremy)",
    "sg:classifiers":[
        {
            "category":"Arena",
            "subcategory":"Sports Club",
            "type":"Entertainment"
        }
    ],
    "sg:phone":"+32 71 32 12 62",
    "sg:postcode":"6020",
    "sg:province":"Hainaut",
    "sg:tags":[
        "martial art",
        "accessory"
    ],
    "wof:name":"Staid",
    "wof:placetype":"venue"
},
  "geometry": {"coordinates":[4.4400839806,50.420841217],"type":"Point"}
}