{
  "type": "Feature",
  "properties": {
    "addr:full":"Dries 52 Lede (oordegem) Oost-Vlaanderen 9340",
    "addr:housenumber":"52",
    "addr:postcode":"9340",
    "addr:street":"Dries",
    "iso:country":"BE",
    "sg:address":"Dries 52",
    "sg:city":"Lede (oordegem)",
    "sg:classifiers":[
        {
            "category":"Real Estate",
            "subcategory":"Architect",
            "type":"Services"
        }
    ],
    "sg:phone":"+32 9 366 69 86",
    "sg:postcode":"9340",
    "sg:province":"Oost-Vlaanderen",
    "wof:name":"Desimpele K",
    "wof:placetype":"venue"
},
  "geometry": {"coordinates":[3.8920090199,50.9627952576],"type":"Point"}
}