{
  "type": "Feature",
  "properties": {
    "addr:full":"Steenvoordestraat 47-49 Ternat Vlaams-Brabant 1740",
    "addr:postcode":"47-49;1740",
    "addr:street":"Steenvoordestraat",
    "iso:country":"BE",
    "sg:address":"Steenvoordestraat 47-49",
    "sg:city":"Ternat",
    "sg:classifiers":[
        {
            "category":"Professional",
            "subcategory":"Lawyer & Legal Services",
            "type":"Services"
        }
    ],
    "sg:phone":"+32 2 465 75 61",
    "sg:postcode":"1740",
    "sg:province":"Vlaams-Brabant",
    "wof:name":"Cornelis Elke",
    "wof:placetype":"venue"
},
  "geometry": {"coordinates":[4.1563978195,50.8820304871],"type":"Point"}
}