{
  "type": "Feature",
  "properties": {
    "iso:country":"BE",
    "sg:address":"Route Nationale 4 11",
    "sg:city":"Nassogne (bande)",
    "sg:classifiers":[
        {
            "category":"Wholesale",
            "subcategory":"Scrap",
            "type":"Manufacturing & Wholesale Goods"
        }
    ],
    "sg:phone":"+32 84 36 81 88",
    "sg:postcode":"6951",
    "sg:province":"Luxembourg",
    "sg:tags":[
        "metal"
    ],
    "wof:name":"Wirtz M",
    "wof:placetype":"venue"
},
  "geometry": {"coordinates":[5.4151701927,50.1667518616],"type":"Point"}
}