{
  "type": "Feature",
  "properties": {
    "addr:full":"Rue Du G\u00e9n\u00e9ral De Gaulle 184 Courcelles Hainaut 6180",
    "addr:housenumber":"184",
    "addr:postcode":"6180",
    "addr:street":"Rue Du Ge\u0301Ne\u0301Ral De Gaulle",
    "iso:country":"BE",
    "sg:address":"Rue Du G\u00e9n\u00e9ral De Gaulle 184",
    "sg:city":"Courcelles",
    "sg:classifiers":[
        {
            "category":"Personal",
            "subcategory":"Barber",
            "type":"Services"
        }
    ],
    "sg:phone":"+32 71 46 28 34",
    "sg:postcode":"6180",
    "sg:province":"Hainaut",
    "sg:tags":[
        "gentleman",
        "salon",
        "-",
        "hairdressing"
    ],
    "wof:name":"Euro Coiffure",
    "wof:placetype":"venue"
},
  "geometry": {"coordinates":[4.381606102,50.4543533325],"type":"Point"}
}