{
  "type": "Feature",
  "properties": {
    "iso:country":"BE",
    "sg:address":"Rue De Limbourg 71",
    "sg:city":"Verviers",
    "sg:orig_category":"D\u00e9taillants en pi\u00e8ces and accessoires de voitures. Entretien and r\u00e9parations de voitures",
    "sg:phone":"+32 87 33 12 10",
    "sg:postcode":"4800",
    "sg:province":"Li\u00e8ge",
    "wof:name":"Multi - Glass - Service",
    "wof:placetype":"venue"
},
  "geometry": {"coordinates":[5.879732132,50.6002807617],"type":"Point"}
}