{
  "type": "Feature",
  "properties": {
    "addr:full":"'s Gravendreef 8a Eke Oost-Vlaanderen 9810",
    "addr:housenumber":"8a",
    "addr:postcode":"9810",
    "addr:street":"';Gravendreef",
    "iso:country":"BE",
    "sg:address":"'s Gravendreef 8a",
    "sg:city":"Eke",
    "sg:classifiers":[
        {
            "category":"Community Center",
            "subcategory":"Youth",
            "type":"Public Place"
        }
    ],
    "sg:phone":"+32 9 385 43 87",
    "sg:postcode":"9810",
    "sg:province":"Oost-Vlaanderen",
    "sg:tags":[
        "steel",
        "section",
        "sections",
        "special"
    ],
    "wof:name":"Profilsteel Nv",
    "wof:placetype":"venue"
},
  "geometry": {"coordinates":[3.6486821175,50.9617881775],"type":"Point"}
}