{
  "type": "Feature",
  "properties": {
    "iso:country":"BE",
    "sg:address":"Gavergrachtstraat 143",
    "sg:city":"Gent",
    "sg:classifiers":[
        {
            "category":"Food & Beverages",
            "subcategory":"Fruits & Vegetables",
            "type":"Retail Goods"
        }
    ],
    "sg:phone":"+32 9 226 90 75",
    "sg:postcode":"9031",
    "sg:province":"Oost-Vlaanderen",
    "sg:tags":[
        "l\u00e9gumes"
    ],
    "wof:name":"Bij Boer Jan",
    "wof:placetype":"venue"
},
  "geometry": {"coordinates":[3.6369249821,51.0815162659],"type":"Point"}
}