{
  "type": "Feature",
  "properties": {
    "addr:full":"Place Du Rinsdelle 31 Etterbeek Bruxelles-Capitale 1040",
    "addr:housenumber":"31",
    "addr:postcode":"1040",
    "addr:street":"Place Du Rinsdelle",
    "iso:country":"BE",
    "sg:address":"Place Du Rinsdelle 31",
    "sg:city":"Etterbeek",
    "sg:orig_category":"Charpentes and couvertures",
    "sg:phone":"+32 2 732 08 82",
    "sg:postcode":"1040",
    "sg:province":"Bruxelles-Capitale",
    "wof:name":"Aqua Roof",
    "wof:placetype":"venue"
},
  "geometry": {"coordinates":[4.3963489532,50.8340644836],"type":"Point"}
}