{
  "type": "Feature",
  "properties": {
    "addr:full":"Turnhoutsebaan 276 Wijnegem Antwerpen 2110",
    "addr:housenumber":"276",
    "addr:postcode":"2110",
    "addr:street":"Turnhoutsebaan",
    "iso:country":"BE",
    "sg:address":"Turnhoutsebaan 276",
    "sg:city":"Wijnegem",
    "sg:classifiers":[
        {
            "category":"Home & Garden",
            "subcategory":"Home Furnishings",
            "type":"Retail Goods"
        }
    ],
    "sg:phone":"+32 3 353 90 23",
    "sg:postcode":"2110",
    "sg:province":"Antwerpen",
    "sg:tags":[
        "lock",
        "high-security",
        "cabinet"
    ],
    "wof:name":"Hillaert B.v.b.a.",
    "wof:placetype":"venue"
},
  "geometry": {"coordinates":[4.5152001381,51.2265396118],"type":"Point"}
}