{
  "type": "Feature",
  "properties": {
    "addr:full":"Hoogweg 94 Buggenhout Oost-Vlaanderen 9255",
    "addr:housenumber":"94",
    "addr:postcode":"9255",
    "addr:street":"Hoogweg",
    "iso:country":"BE",
    "sg:address":"Hoogweg 94",
    "sg:city":"Buggenhout",
    "sg:orig_category":"Kapsalons",
    "sg:phone":"+32 52 33 33 57",
    "sg:postcode":"9255",
    "sg:province":"Oost-Vlaanderen",
    "wof:name":"Coiffure Pieter",
    "wof:placetype":"venue"
},
  "geometry": {"coordinates":[4.2278652191,51.0174102783],"type":"Point"}
}