{
  "type": "Feature",
  "properties": {
    "iso:country":"BE",
    "sg:address":"Leopold De Waelplaats 28 Box 11",
    "sg:city":"Antwerpen",
    "sg:classifiers":[
        {
            "category":"Health Services",
            "subcategory":"Doctor",
            "type":"Services"
        }
    ],
    "sg:phone":"+32 3 248 90 94",
    "sg:postcode":"2000",
    "sg:province":"Antwerpen",
    "sg:tags":[
        "medicinephysicians",
        "surgeon"
    ],
    "wof:name":"Baute L",
    "wof:placetype":"venue"
},
  "geometry": {"coordinates":[4.3928070068,51.2088508606],"type":"Point"}
}