{
  "type": "Feature",
  "properties": {
    "iso:country":"BE",
    "sg:address":"Rue De Bouillon 25",
    "sg:city":"Bievre",
    "sg:orig_category":"Slagers",
    "sg:phone":"+32 61 51 11 39",
    "sg:postcode":"5555",
    "sg:province":"Namur",
    "wof:name":"A.j.b.",
    "wof:placetype":"venue"
},
  "geometry": {"coordinates":[5.0206341743,49.939414978],"type":"Point"}
}