{
  "type": "Feature",
  "properties": {
    "addr:full":"Rue De Stassart 43 Bruxelles (ixelles) Bruxelles-Capitale 1050",
    "addr:housenumber":"43",
    "addr:postcode":"1050",
    "addr:street":"Rue De Stassart",
    "iso:country":"BE",
    "sg:address":"Rue De Stassart 43",
    "sg:city":"Bruxelles (ixelles)",
    "sg:classifiers":[
        {
            "category":"Internet Cafe",
            "subcategory":"None",
            "type":"Food & Drink"
        }
    ],
    "sg:phone":"+32 2 400 08 88",
    "sg:postcode":"1050",
    "sg:province":"Bruxelles-Capitale",
    "sg:tags":[
        "access",
        "-",
        "provider"
    ],
    "wof:name":"World Online",
    "wof:placetype":"venue"
},
  "geometry": {"coordinates":[4.3604989052,50.8365936279],"type":"Point"}
}