{
  "type": "Feature",
  "properties": {
    "addr:full":"Izegemstraat 107 Roeselare West-Vlaanderen 8800",
    "addr:housenumber":"107",
    "addr:postcode":"8800",
    "addr:street":"Izegemstraat",
    "iso:country":"BE",
    "sg:address":"Izegemstraat 107",
    "sg:city":"Roeselare",
    "sg:orig_category":"Herstellingen and onderhoud van auto's",
    "sg:phone":"+32 51 20 10 44",
    "sg:postcode":"8800",
    "sg:province":"West-Vlaanderen",
    "wof:name":"Carrosserie Devrieze",
    "wof:placetype":"venue"
},
  "geometry": {"coordinates":[3.1680300236,50.9310035706],"type":"Point"}
}