{
  "type": "Feature",
  "properties": {
    "iso:country":"BE",
    "sg:address":"Place Des Arcades 4",
    "sg:city":"Watermaal-bosvoorde/watermael-boitsfort",
    "sg:orig_category":"Instituts de beaut\u00e9",
    "sg:phone":"+32 2 660 34 04",
    "sg:postcode":"1170",
    "sg:province":"Bruxelles-Capitale",
    "wof:name":"Liliane Dasnoy",
    "wof:placetype":"venue"
},
  "geometry": {"coordinates":[4.3989620209,50.8095283508],"type":"Point"}
}