{
  "type": "Feature",
  "properties": {
    "addr:full":"Potteriestraat 20 Zonnebeke West-Vlaanderen 8980",
    "addr:housenumber":"20",
    "addr:postcode":"8980",
    "addr:street":"Potteriestraat",
    "iso:country":"BE",
    "sg:address":"Potteriestraat 20",
    "sg:city":"Zonnebeke",
    "sg:orig_category":"Eleveurs de bovins",
    "sg:phone":"+32 57 46 66 59",
    "sg:postcode":"8980",
    "sg:province":"West-Vlaanderen",
    "wof:name":"Charles Deneut",
    "wof:placetype":"venue"
},
  "geometry": {"coordinates":[3.0342299938,50.8434410095],"type":"Point"}
}