{
  "type": "Feature",
  "properties": {
    "addr:full":"Place De Plancenoit 23 Lasne (plancenoit) Brabant Wallon 1380",
    "addr:housenumber":"23",
    "addr:postcode":"1380",
    "addr:street":"Place De Plancenoit",
    "iso:country":"BE",
    "sg:address":"Place De Plancenoit 23",
    "sg:city":"Lasne (plancenoit)",
    "sg:classifiers":[
        {
            "category":"Food & Beverages",
            "subcategory":"Groceries & Convenience Stores",
            "type":"Retail Goods"
        }
    ],
    "sg:phone":"+32 2 633 16 71",
    "sg:postcode":"1380",
    "sg:province":"Brabant Wallon",
    "sg:tags":[
        "grocer"
    ],
    "wof:name":"Epece",
    "wof:placetype":"venue"
},
  "geometry": {"coordinates":[4.4302711487,50.660697937],"type":"Point"}
}