{
  "type": "Feature",
  "properties": {
    "iso:country":"BE",
    "sg:address":"Tervuursesteenweg 3",
    "sg:city":"Mechelen",
    "sg:classifiers":[
        {
            "category":"Cafe",
            "type":"Food & Drink"
        }
    ],
    "sg:phone":"+32 15 43 04 46",
    "sg:postcode":"2800",
    "sg:province":"Antwerpen",
    "sg:tags":[
        "snack-bars"
    ],
    "wof:name":"Wagamamas",
    "wof:placetype":"venue"
},
  "geometry": {"coordinates":[4.4833269119,51.0140113831],"type":"Point"}
}