{
  "type": "Feature",
  "properties": {
    "iso:country":"BE",
    "sg:address":"Avenue De La Libert\u00e9 155",
    "sg:city":"Bruxelles (molenbeek-saint-jean)",
    "sg:classifiers":[
        {
            "category":"Professional",
            "subcategory":"Advertising",
            "type":"Services"
        }
    ],
    "sg:phone":"+32 2 410 35 22",
    "sg:postcode":"1080",
    "sg:province":"Bruxelles-Capitale",
    "sg:tags":[
        "item",
        "-",
        "business",
        "gift",
        "promotional"
    ],
    "wof:name":"Belgo Concept Sa",
    "wof:placetype":"venue"
},
  "geometry": {"coordinates":[4.3190879822,50.8610076904],"type":"Point"}
}