{
  "type": "Feature",
  "properties": {
    "iso:country":"BE",
    "sg:address":"Dekkenstraat 73",
    "sg:city":"Sint-truiden",
    "sg:orig_category":"Sportclubs",
    "sg:phone":"+32 11 59 22 60",
    "sg:postcode":"3800",
    "sg:province":"Limburg",
    "wof:name":"Aviaclub Brustem",
    "wof:placetype":"venue"
},
  "geometry": {"coordinates":[5.2590470314,50.8369827271],"type":"Point"}
}