{
  "type": "Feature",
  "properties": {
    "addr:full":"Petite Rue Du Vallon 27 Rixensart (genval) Brabant Wallon 1332",
    "addr:housenumber":"27",
    "addr:postcode":"1332",
    "addr:street":"Petite Rue Du Vallon",
    "iso:country":"BE",
    "sg:address":"Petite Rue Du Vallon 27",
    "sg:city":"Rixensart (genval)",
    "sg:classifiers":[
        {
            "category":"Real Estate",
            "subcategory":"Architect",
            "type":"Services"
        }
    ],
    "sg:phone":"+32 2 653 71 57",
    "sg:postcode":"1332",
    "sg:province":"Brabant Wallon",
    "wof:name":"Moens A",
    "wof:placetype":"venue"
},
  "geometry": {"coordinates":[4.5028672218,50.7206077576],"type":"Point"}
}