{
  "type": "Feature",
  "properties": {
    "iso:country":"BE",
    "sg:address":"Rue Elisa Dumonceau 15",
    "sg:city":"Herstal",
    "sg:orig_category":"Drukkerijen and copyshops",
    "sg:phone":"+32 4 240 48 58",
    "sg:postcode":"4040",
    "sg:province":"Li\u00e8ge",
    "wof:name":"Copyservice Jeurissen",
    "wof:placetype":"venue"
},
  "geometry": {"coordinates":[5.6304597855,50.6646766663],"type":"Point"}
}