{
  "type": "Feature",
  "properties": {
    "addr:full":"Gontrode Heirweg 130 Melle Oost-Vlaanderen 9090",
    "addr:housenumber":"130",
    "addr:postcode":"9090",
    "addr:street":"Gontrode Heirweg",
    "iso:country":"BE",
    "sg:address":"Gontrode Heirweg 130",
    "sg:city":"Melle",
    "sg:classifiers":[
        {
            "category":"Professional",
            "subcategory":"Testing Lab",
            "type":"Services"
        }
    ],
    "sg:phone":"+32 9 272 50 70",
    "sg:postcode":"9090",
    "sg:province":"Oost-Vlaanderen",
    "sg:tags":[
        "laboratory",
        "-"
    ],
    "wof:name":"Becetel Vzw",
    "wof:placetype":"venue"
},
  "geometry": {"coordinates":[3.7916560173,50.9956207275],"type":"Point"}
}