{
  "type": "Feature",
  "properties": {
    "addr:full":"Laagsimsestraat 96 Alken Limburg 3570",
    "addr:housenumber":"96",
    "addr:postcode":"3570",
    "addr:street":"Laagsimsestraat",
    "iso:country":"BE",
    "sg:address":"Laagsimsestraat 96",
    "sg:city":"Alken",
    "sg:classifiers":[
        {
            "category":"Home & Garden",
            "subcategory":"Building Materials",
            "type":"Retail Goods"
        }
    ],
    "sg:phone":"+32 11 31 11 85",
    "sg:postcode":"3570",
    "sg:province":"Limburg",
    "sg:tags":[
        "veranda"
    ],
    "wof:name":"Croes A & D Bvba",
    "wof:placetype":"venue"
},
  "geometry": {"coordinates":[5.2885961533,50.8710212708],"type":"Point"}
}