{
  "type": "Feature",
  "properties": {
    "iso:country":"BE",
    "sg:address":"Rue Chalets Finlandais 19",
    "sg:city":"Frameries",
    "sg:orig_category":"Elektrische installaties voor woningen",
    "sg:phone":"+32 65 67 16 82",
    "sg:postcode":"7080",
    "sg:province":"Hainaut",
    "wof:name":"Fe. Elec",
    "wof:placetype":"venue"
},
  "geometry": {"coordinates":[3.8722519875,50.4119338989],"type":"Point"}
}