{
  "type": "Feature",
  "properties": {
    "addr:full":"Domaine Univ.sart-tilman 0 Li\u00c8ge Li\u00e8ge 4000",
    "addr:housenumber":"0",
    "addr:postcode":"4000",
    "iso:country":"BE",
    "sg:address":"Domaine Univ.sart-tilman 0",
    "sg:city":"Li\u00c8ge",
    "sg:orig_category":"Assurances. Bureaux de poste",
    "sg:phone":"+32 4 367 56 38",
    "sg:postcode":"4000",
    "sg:province":"Li\u00e8ge",
    "wof:name":"La Poste",
    "wof:placetype":"venue"
},
  "geometry": {"coordinates":[5.541164875,50.6114616394],"type":"Point"}
}