{
  "type": "Feature",
  "properties": {
    "iso:country":"BE",
    "sg:address":"18",
    "sg:city":"Rue Bois Des Iles 1082 Brussel",
    "sg:classifiers":[
        {
            "category":"Wholesale",
            "subcategory":"Machinery & Supplies",
            "type":"Manufacturing & Wholesale Goods"
        }
    ],
    "sg:phone":"+32 2 465 81 91",
    "sg:postcode":"18",
    "sg:tags":[
        "equipment",
        "optical",
        "precision",
        "instrument"
    ],
    "wof:name":"Action Twenty Five Scrl",
    "wof:placetype":"venue"
},
  "geometry": {"coordinates":[4.2934298515,50.8736000061],"type":"Point"}
}