{
  "type": "Feature",
  "properties": {
    "addr:full":"Duinenweg 143 Middelkerke West-Vlaanderen 8430",
    "addr:housenumber":"143",
    "addr:postcode":"8430",
    "addr:street":"Duinenweg",
    "iso:country":"BE",
    "sg:address":"Duinenweg 143",
    "sg:city":"Middelkerke",
    "sg:classifiers":[
        {
            "category":"Recreation",
            "subcategory":"Campground",
            "type":"Entertainment"
        }
    ],
    "sg:phone":"+32 59 30 00 62",
    "sg:postcode":"8430",
    "sg:province":"West-Vlaanderen",
    "sg:tags":[
        "site",
        "camping"
    ],
    "wof:name":"Pollentier Park Bvba",
    "wof:placetype":"venue"
},
  "geometry": {"coordinates":[2.8407349586,51.1977043152],"type":"Point"}
}