{
  "type": "Feature",
  "properties": {
    "iso:country":"BE",
    "sg:address":"Heiken 27a",
    "sg:city":"Brecht",
    "sg:classifiers":[
        {
            "category":"Arena",
            "subcategory":"Horse Racetrack",
            "type":"Entertainment"
        }
    ],
    "sg:phone":"+32 3 313 00 32",
    "sg:postcode":"2960",
    "sg:province":"Antwerpen",
    "sg:tags":[
        "trailer"
    ],
    "wof:name":"Van Geel Bvba (geak)",
    "wof:placetype":"venue"
},
  "geometry": {"coordinates":[4.6415200233,51.3512115479],"type":"Point"}
}