{
  "type": "Feature",
  "properties": {
    "addr:full":"Runkstersteenweg 87 Hasselt Limburg 3500",
    "addr:housenumber":"87",
    "addr:postcode":"3500",
    "addr:street":"Runkstersteenweg",
    "iso:country":"BE",
    "sg:address":"Runkstersteenweg 87",
    "sg:city":"Hasselt",
    "sg:orig_category":"M\u00e9decins and sp\u00e9cialistes",
    "sg:phone":"+32 11 27 05 65",
    "sg:postcode":"3500",
    "sg:province":"Limburg",
    "wof:name":"Lucien Thon\u00c9",
    "wof:placetype":"venue"
},
  "geometry": {"coordinates":[5.3276062012,50.9276008606],"type":"Point"}
}