{
  "type": "Feature",
  "properties": {
    "addr:full":"Haachtsebaan 64 Keerbergen Vlaams-Brabant 3140",
    "addr:housenumber":"64",
    "addr:postcode":"3140",
    "addr:street":"Haachtsebaan",
    "iso:country":"BE",
    "sg:address":"Haachtsebaan 64",
    "sg:city":"Keerbergen",
    "sg:classifiers":[
        {
            "category":"Shopping",
            "subcategory":"Stationery & Office Supplies",
            "type":"Retail Goods"
        }
    ],
    "sg:phone":"+32 15 52 89 66",
    "sg:postcode":"3140",
    "sg:province":"Vlaams-Brabant",
    "sg:tags":[
        "-"
    ],
    "wof:name":"Serka Office Nv",
    "wof:placetype":"venue"
},
  "geometry": {"coordinates":[4.6325378418,51.0024375916],"type":"Point"}
}