{
  "type": "Feature",
  "properties": {
    "iso:country":"BE",
    "sg:address":"Rooigemlaan 469",
    "sg:city":"Gent",
    "sg:orig_category":"Boekhouders",
    "sg:phone":"+32 9 226 07 34",
    "sg:postcode":"9000",
    "sg:province":"Oost-Vlaanderen",
    "wof:name":"Bertine Debeil",
    "wof:placetype":"venue"
},
  "geometry": {"coordinates":[3.6945090294,51.0629043579],"type":"Point"}
}