{
  "type": "Feature",
  "properties": {
    "addr:full":"Rue Du Moulin 8 Ottignies-louvain-la-neuve Brabant Wallon 1340",
    "addr:housenumber":"8",
    "addr:postcode":"1340",
    "addr:street":"Rue Du Moulin",
    "iso:country":"BE",
    "sg:address":"Rue Du Moulin 8",
    "sg:city":"Ottignies-louvain-la-neuve",
    "sg:orig_category":"Beheer onroerend goed",
    "sg:phone":"+32 10 41 50 47",
    "sg:postcode":"1340",
    "sg:province":"Brabant Wallon",
    "wof:name":"Jean Houbart",
    "wof:placetype":"venue"
},
  "geometry": {"coordinates":[4.5680370331,50.6653862],"type":"Point"}
}