{
  "type": "Feature",
  "properties": {
    "addr:full":"Rue Jean-de-boh\u00c8me 5 Durbuy Luxembourg 6940",
    "addr:housenumber":"5",
    "addr:postcode":"6940",
    "addr:street":"Rue Jean-De-Bohe\u0300Me",
    "iso:country":"BE",
    "sg:address":"Rue Jean-de-boh\u00c8me 5",
    "sg:city":"Durbuy",
    "sg:orig_category":"Agences immobili\u00e8res. Evaluation and estimation de biens immobiliers",
    "sg:phone":"+32 86 21 14 65",
    "sg:postcode":"6940",
    "sg:province":"Luxembourg",
    "wof:name":"Immo Cosse",
    "wof:placetype":"venue"
},
  "geometry": {"coordinates":[5.4569587708,50.3518447876],"type":"Point"}
}