{
  "type": "Feature",
  "properties": {
    "iso:country":"BE",
    "sg:address":"Ruweschuurstraat 3",
    "sg:city":"Beernem",
    "sg:orig_category":"Rundveehouders",
    "sg:phone":"+32 50 78 97 02",
    "sg:postcode":"8730",
    "sg:province":"West-Vlaanderen",
    "wof:name":"Placide De Zutter",
    "wof:placetype":"venue"
},
  "geometry": {"coordinates":[3.3778450489,51.1745452881],"type":"Point"}
}