{
  "type": "Feature",
  "properties": {
    "iso:country":"BE",
    "sg:address":"Chauss\u00e9e De Namur 18",
    "sg:city":"Gembloux-sur-orneau (gembloux)",
    "sg:classifiers":[
        {
            "category":"Retail",
            "subcategory":"Auto Repair",
            "type":"Services"
        }
    ],
    "sg:phone":"+32 81 61 16 26",
    "sg:postcode":"5030",
    "sg:province":"Namur",
    "sg:tags":[
        "garage"
    ],
    "wof:name":"Garage De La Crois\u00e9e Sprl",
    "wof:placetype":"venue"
},
  "geometry": {"coordinates":[4.6982169151,50.5719909668],"type":"Point"}
}