{
  "type": "Feature",
  "properties": {
    "iso:country":"BE",
    "sg:address":"Stippelstraat 40",
    "sg:city":"Sint-truiden",
    "sg:orig_category":"Producteurs de fruits",
    "sg:phone":"+32 11 31 44 46",
    "sg:postcode":"3800",
    "sg:province":"Limburg",
    "wof:name":"Richard Neven",
    "wof:placetype":"venue"
},
  "geometry": {"coordinates":[5.2566461563,50.8434906006],"type":"Point"}
}