{
  "type": "Feature",
  "properties": {
    "addr:full":"Tinhoutstraat 159 Beernem (oedelem) West-Vlaanderen 8730",
    "addr:housenumber":"159",
    "addr:postcode":"8730",
    "addr:street":"Tinhoutstraat",
    "iso:country":"BE",
    "sg:address":"Tinhoutstraat 159",
    "sg:city":"Beernem (oedelem)",
    "sg:classifiers":[
        {
            "category":"Home & Garden",
            "subcategory":"Building Materials",
            "type":"Retail Goods"
        }
    ],
    "sg:phone":"+32 50 78 85 84",
    "sg:postcode":"8730",
    "sg:province":"West-Vlaanderen",
    "sg:tags":[
        "window"
    ],
    "wof:name":"Goethals Filip",
    "wof:placetype":"venue"
},
  "geometry": {"coordinates":[3.3931360245,51.1625595093],"type":"Point"}
}