{
  "type": "Feature",
  "properties": {
    "iso:country":"BE",
    "sg:address":"Grand'place 12",
    "sg:city":"Le Roeulx",
    "sg:orig_category":"Technisch and beroeps secundair onderwijs",
    "sg:phone":"+32 64 66 23 04",
    "sg:postcode":"7070",
    "sg:province":"Hainaut",
    "wof:name":"Institut St.joseph",
    "wof:placetype":"venue"
},
  "geometry": {"coordinates":[4.1089048386,50.5016059875],"type":"Point"}
}