{
  "type": "Feature",
  "properties": {
    "addr:full":"Koninklijke Baan 38b301 De Panne West-Vlaanderen 8660",
    "addr:housenumber":"38b301",
    "addr:postcode":"8660",
    "addr:street":"Koninklijke Baan",
    "iso:country":"BE",
    "sg:address":"Koninklijke Baan 38b301",
    "sg:city":"De Panne",
    "sg:orig_category":"Sportclubs",
    "sg:phone":"+32 58 41 30 77",
    "sg:postcode":"8660",
    "sg:province":"West-Vlaanderen",
    "wof:name":"T.c. Westhoek",
    "wof:placetype":"venue"
},
  "geometry": {"coordinates":[2.5845160484,51.0964431763],"type":"Point"}
}