{
  "type": "Feature",
  "properties": {
    "iso:country":"BE",
    "sg:address":"Place De Jamblinne De Meux 12",
    "sg:city":"Bruxelles (schaerbeek)",
    "sg:classifiers":[
        {
            "category":"Health Services",
            "subcategory":"Doctor",
            "type":"Services"
        }
    ],
    "sg:phone":"+32 2 735 16 15",
    "sg:postcode":"1030",
    "sg:province":"Bruxelles-Capitale",
    "sg:tags":[
        "medicinephysicians",
        "surgeon"
    ],
    "wof:name":"Costigliola V",
    "wof:placetype":"venue"
},
  "geometry": {"coordinates":[4.3946089745,50.847038269],"type":"Point"}
}