{
  "type": "Feature",
  "properties": {
    "iso:country":"BE",
    "sg:address":"Hagenstraat 91",
    "sg:city":"Moeskroen/mouscron",
    "sg:orig_category":"Beautyfarms, relaxatie and lichamelijk welzijn Schoonheidssalons",
    "sg:phone":"+32 56 84 23 48",
    "sg:postcode":"7712",
    "sg:province":"Hainaut",
    "wof:name":"Instituut De Beaut\u00c9 Armelle",
    "wof:placetype":"venue"
},
  "geometry": {"coordinates":[3.2172839642,50.717212677],"type":"Point"}
}