{
  "type": "Feature",
  "properties": {
    "addr:full":"Baan 27 Wuustwezel Antwerpen 2990",
    "addr:housenumber":"27",
    "addr:postcode":"2990",
    "addr:street":"Baan",
    "iso:country":"BE",
    "sg:address":"Baan 27",
    "sg:city":"Wuustwezel",
    "sg:orig_category":"Rundveehouders",
    "sg:phone":"+32 3 669 65 10",
    "sg:postcode":"2990",
    "sg:province":"Antwerpen",
    "wof:name":"Franciscus Cools",
    "wof:placetype":"venue"
},
  "geometry": {"coordinates":[4.5888547897,51.3970298767],"type":"Point"}
}