{
  "type": "Feature",
  "properties": {
    "addr:full":"Leopoldlei 94 Heist-op-den-berg Antwerpen 2220",
    "addr:housenumber":"94",
    "addr:postcode":"2220",
    "addr:street":"Leopoldlei",
    "iso:country":"BE",
    "sg:address":"Leopoldlei 94",
    "sg:city":"Heist-op-den-berg",
    "sg:classifiers":[
        {
            "category":"Restaurant",
            "type":"Food & Drink"
        }
    ],
    "sg:phone":"+32 15 24 95 85",
    "sg:postcode":"2220",
    "sg:province":"Antwerpen",
    "wof:name":"Zapatas",
    "wof:placetype":"venue"
},
  "geometry": {"coordinates":[4.7272701263,51.0778312683],"type":"Point"}
}