{
  "type": "Feature",
  "properties": {
    "addr:full":"Volkstraat 16 Antwerpen Antwerpen 2000",
    "addr:housenumber":"16",
    "addr:postcode":"2000",
    "addr:street":"Volkstraat",
    "iso:country":"BE",
    "sg:address":"Volkstraat 16",
    "sg:city":"Antwerpen",
    "sg:orig_category":"Blanchisseries and teintureries",
    "sg:phone":"+32 3 237 14 56",
    "sg:postcode":"2000",
    "sg:province":"Antwerpen",
    "wof:name":"Teralux",
    "wof:placetype":"venue"
},
  "geometry": {"coordinates":[4.396490097,51.2116851807],"type":"Point"}
}