{
  "type": "Feature",
  "properties": {
    "iso:country":"BE",
    "sg:address":"Brugseweg 157",
    "sg:city":"Ieper",
    "sg:classifiers":[
        {
            "category":"Cafe",
            "type":"Food & Drink"
        }
    ],
    "sg:phone":"+32 57 20 79 33",
    "sg:postcode":"8900",
    "sg:province":"West-Vlaanderen",
    "sg:tags":[
        "caf\u00e9s"
    ],
    "wof:name":"Caf\u00c9 Nova",
    "wof:placetype":"venue"
},
  "geometry": {"coordinates":[2.895720005,50.8590240479],"type":"Point"}
}