{
  "type": "Feature",
  "properties": {
    "addr:full":"Chauss\u00c9e De Mons 52 Le Roeulx Hainaut 7070",
    "addr:housenumber":"52",
    "addr:postcode":"7070",
    "addr:street":"Chausse\u0301E De Mons",
    "iso:country":"BE",
    "sg:address":"Chauss\u00c9e De Mons 52",
    "sg:city":"Le Roeulx",
    "sg:orig_category":"Kapsalons Rundveehouders",
    "sg:phone":"+32 64 67 78 61",
    "sg:postcode":"7070",
    "sg:province":"Hainaut",
    "wof:name":"Coiffure Nathalie",
    "wof:placetype":"venue"
},
  "geometry": {"coordinates":[4.1061401367,50.501750946],"type":"Point"}
}