{
  "type": "Feature",
  "properties": {
    "addr:full":"Rue D\u00e9sir\u00e9 Manne 27 Wanze (bas-oha) Li\u00e8ge 4520",
    "addr:housenumber":"27",
    "addr:postcode":"4520",
    "addr:street":"Rue De\u0301Sire\u0301 Manne;Bas-Oha",
    "iso:country":"BE",
    "sg:address":"Rue D\u00e9sir\u00e9 Manne 27",
    "sg:city":"Wanze (bas-oha)",
    "sg:classifiers":[
        {
            "category":"Health Services",
            "subcategory":"Health Practitioner",
            "type":"Services"
        }
    ],
    "sg:phone":"+32 85 21 65 37",
    "sg:postcode":"4520",
    "sg:province":"Li\u00e8ge",
    "sg:tags":[
        "physiotherapist"
    ],
    "wof:name":"Kestens Michel",
    "wof:placetype":"venue"
},
  "geometry": {"coordinates":[5.193171978,50.526134491],"type":"Point"}
}