{
  "type": "Feature",
  "properties": {
    "addr:full":"Avenue Eug\u00c8ne Demolder 51 Schaarbeek/schaerbeek Bruxelles-Capitale 1030",
    "addr:housenumber":"51",
    "addr:postcode":"1030",
    "addr:street":"Avenue Euge\u0300Ne Demolder",
    "iso:country":"BE",
    "sg:address":"Avenue Eug\u00c8ne Demolder 51",
    "sg:city":"Schaarbeek/schaerbeek",
    "sg:orig_category":"Cr\u00e8ches and garderies d'enfants",
    "sg:phone":"+32 2 216 23 01",
    "sg:postcode":"1030",
    "sg:province":"Bruxelles-Capitale",
    "wof:name":"Cr\u00c8che Little Baby",
    "wof:placetype":"venue"
},
  "geometry": {"coordinates":[4.3785037994,50.8719940186],"type":"Point"}
}