{
  "type": "Feature",
  "properties": {
    "addr:full":"Kortrijkseweg 128 Waregem West-Vlaanderen 8791",
    "addr:housenumber":"128",
    "addr:postcode":"8791",
    "iso:country":"BE",
    "sg:address":"Kortrijkseweg 128",
    "sg:city":"Waregem",
    "sg:orig_category":"Herstellingen and onderhoud van auto's",
    "sg:phone":"+32 56 71 18 34",
    "sg:postcode":"8791",
    "sg:province":"West-Vlaanderen",
    "wof:name":"J. Debraeve",
    "wof:placetype":"venue"
},
  "geometry": {"coordinates":[3.3399910927,50.8706626892],"type":"Point"}
}