{
  "type": "Feature",
  "properties": {
    "addr:full":"Renbaanlaan 132 Elsene Bruxelles-Capitale 1050",
    "addr:housenumber":"132",
    "addr:postcode":"1050",
    "addr:street":"Renbaanlaan",
    "iso:country":"BE",
    "sg:address":"Renbaanlaan 132",
    "sg:city":"Elsene",
    "sg:orig_category":"Antiek Herstellingswinkels voor diverse persoonlijke and huishoudartikelen Vloer- and muurbekleding",
    "sg:phone":"+32 2 649 65 34",
    "sg:postcode":"1050",
    "sg:province":"Bruxelles-Capitale",
    "wof:name":"Antoine Michel",
    "wof:placetype":"venue"
},
  "geometry": {"coordinates":[4.3771882057,50.8203582764],"type":"Point"}
}