{
  "type": "Feature",
  "properties": {
    "addr:full":"Rue Du Col\u00e2 82 Beloeil (stambruges) Hainaut 7973",
    "addr:housenumber":"82",
    "addr:postcode":"7973",
    "addr:street":"Rue Du Cola\u0302",
    "iso:country":"BE",
    "sg:address":"Rue Du Col\u00e2 82",
    "sg:city":"Beloeil (stambruges)",
    "sg:classifiers":[
        {
            "category":"Professional",
            "subcategory":"Management & Consulting",
            "type":"Services"
        }
    ],
    "sg:phone":"+32 69 57 66 42",
    "sg:postcode":"7973",
    "sg:province":"Hainaut",
    "sg:tags":[
        "consultant"
    ],
    "wof:name":"Cepha",
    "wof:placetype":"venue"
},
  "geometry": {"coordinates":[3.7141671181,50.5021476746],"type":"Point"}
}