{
  "type": "Feature",
  "properties": {
    "iso:country":"BE",
    "sg:address":"Grand\u00b4place 25",
    "sg:city":"Mont-saint-guibert",
    "sg:orig_category":"Fleurs and plantes",
    "sg:phone":"+32 10 65 94 88",
    "sg:postcode":"1435",
    "sg:province":"Brabant Wallon",
    "wof:name":"Il Etait Une Fleur...",
    "wof:placetype":"venue"
},
  "geometry": {"coordinates":[4.6104288101,50.6340293884],"type":"Point"}
}