{
  "type": "Feature",
  "properties": {
    "iso:country":"BE",
    "sg:address":"Boulevard Auguste Reyers 41",
    "sg:city":"Bruxelles (schaerbeek)",
    "sg:classifiers":[
        {
            "category":"Professional",
            "subcategory":"Lawyer & Legal Services",
            "type":"Services"
        }
    ],
    "sg:phone":"+32 2 735 70 51",
    "sg:postcode":"1030",
    "sg:province":"Bruxelles-Capitale",
    "sg:tags":[
        "notary"
    ],
    "wof:name":"Wets X",
    "wof:placetype":"venue"
},
  "geometry": {"coordinates":[4.3999519348,50.8525505066],"type":"Point"}
}