{
  "type": "Feature",
  "properties": {
    "addr:full":"Rue De Burhaimont 18 Bertrix Luxembourg 6880",
    "addr:housenumber":"18",
    "addr:postcode":"6880",
    "addr:street":"Rue De Burhaimont",
    "iso:country":"BE",
    "sg:address":"Rue De Burhaimont 18",
    "sg:city":"Bertrix",
    "sg:orig_category":"Cr\u00e8ches and garderies d'enfants",
    "sg:phone":"+32 61 41 37 83",
    "sg:postcode":"6880",
    "sg:province":"Luxembourg",
    "wof:name":"Bienvenue Tout Petits",
    "wof:placetype":"venue"
},
  "geometry": {"coordinates":[5.2518401146,49.8572845459],"type":"Point"}
}