{
  "type": "Feature",
  "properties": {
    "iso:country":"BE",
    "sg:address":"Fazantendreef 1-a",
    "sg:city":"Keerbergen",
    "sg:classifiers":[
        {
            "category":"Professional",
            "subcategory":"Management & Consulting",
            "type":"Services"
        }
    ],
    "sg:phone":"+32 15 51 10 68",
    "sg:postcode":"3140",
    "sg:province":"Vlaams-Brabant",
    "sg:tags":[
        "consultant"
    ],
    "wof:name":"Bright Company (the)",
    "wof:placetype":"venue"
},
  "geometry": {"coordinates":[4.6574687958,50.9978675842],"type":"Point"}
}