{
  "type": "Feature",
  "properties": {
    "addr:full":"Rue De L'eglise 2 Verlaine Li\u00e8ge 4537",
    "addr:housenumber":"2",
    "addr:postcode":"4537",
    "addr:street":"Rue De L'Eglise",
    "iso:country":"BE",
    "sg:address":"Rue De L'eglise 2",
    "sg:city":"Verlaine",
    "sg:classifiers":[
        {
            "category":"Banks & Credit Unions",
            "subcategory":"Investment Brokerage",
            "type":"Services"
        }
    ],
    "sg:phone":"+32 4 259 69 39",
    "sg:postcode":"4537",
    "sg:province":"Li\u00e8ge",
    "sg:tags":[
        "auditor"
    ],
    "wof:name":"Evrard M",
    "wof:placetype":"venue"
},
  "geometry": {"coordinates":[5.3179969788,50.6072006226],"type":"Point"}
}