{
  "type": "Feature",
  "properties": {
    "iso:country":"BE",
    "sg:address":"Bruggeske 14",
    "sg:city":"Mol",
    "sg:classifiers":[
        {
            "category":"Recreation",
            "subcategory":"Amusement Park",
            "type":"Entertainment"
        }
    ],
    "sg:phone":"+32 14 31 65 51",
    "sg:postcode":"2400",
    "sg:province":"Antwerpen",
    "sg:tags":[
        "attraction",
        "-",
        "sale",
        "fair",
        "hiring"
    ],
    "wof:name":"Vanhoof",
    "wof:placetype":"venue"
},
  "geometry": {"coordinates":[5.0962781906,51.1981315613],"type":"Point"}
}