{
  "type": "Feature",
  "properties": {
    "addr:full":"Chauss\u00c9e De Bruxelles 41 Leuze-en-hainaut Hainaut 7903",
    "addr:housenumber":"41",
    "addr:postcode":"7903",
    "addr:street":"Chausse\u0301E De Bruxelles",
    "iso:country":"BE",
    "sg:address":"Chauss\u00c9e De Bruxelles 41",
    "sg:city":"Leuze-en-hainaut",
    "sg:orig_category":"Caf\u00e9s Herstellingen and onderhoud aan huis voor voertuigen Metaalafval, schrootrecyclage and sloperi",
    "sg:phone":"+32 69 66 32 10",
    "sg:postcode":"7903",
    "sg:province":"Hainaut",
    "wof:name":"Fe. Fournier Deverchin",
    "wof:placetype":"venue"
},
  "geometry": {"coordinates":[3.6720991135,50.6097831726],"type":"Point"}
}