{
  "type": "Feature",
  "properties": {
    "addr:full":"Avenue Th\u00c9o Verbeeck 71 Anderlecht Bruxelles-Capitale 1070",
    "addr:housenumber":"71",
    "addr:postcode":"1070",
    "addr:street":"Avenue The\u0301O Verbeeck",
    "iso:country":"BE",
    "sg:address":"Avenue Th\u00c9o Verbeeck 71",
    "sg:city":"Anderlecht",
    "sg:orig_category":"Services fun\u00e9raires",
    "sg:phone":"+32 2 522 08 51",
    "sg:postcode":"1070",
    "sg:province":"Bruxelles-Capitale",
    "wof:name":"Duch\u00cane S.p.r.l.",
    "wof:placetype":"venue"
},
  "geometry": {"coordinates":[4.2957630157,50.8340339661],"type":"Point"}
}