{
  "type": "Feature",
  "properties": {
    "iso:country":"BE",
    "sg:address":"Mannenberg 192",
    "sg:city":"Messelbroek",
    "sg:classifiers":[
        {
            "category":"Autos & Motor Vehicles",
            "subcategory":"Motorcycle Sales",
            "type":"Retail Goods"
        }
    ],
    "sg:phone":"+32 13 77 15 66",
    "sg:postcode":"3272",
    "sg:province":"Vlaams-Brabant",
    "sg:tags":[
        "yamaha"
    ],
    "wof:name":"Gebroeders Cresens",
    "wof:placetype":"venue"
},
  "geometry": {"coordinates":[4.9337182045,50.9770545959],"type":"Point"}
}