{
  "type": "Feature",
  "properties": {
    "iso:country":"BE",
    "sg:address":"Grote Bergstraat 6",
    "sg:city":"Tienen",
    "sg:classifiers":[
        {
            "category":"Health Services",
            "subcategory":"Health Practitioner",
            "type":"Services"
        }
    ],
    "sg:phone":"+32 16 81 45 34",
    "sg:postcode":"3300",
    "sg:province":"Vlaams-Brabant",
    "sg:tags":[
        "physiotherapist"
    ],
    "wof:name":"Rabau Paul",
    "wof:placetype":"venue"
},
  "geometry": {"coordinates":[4.9400930405,50.8044929504],"type":"Point"}
}