{
  "type": "Feature",
  "properties": {
    "addr:full":"Kloosterstraat 34 Antwerpen Antwerpen 2180",
    "addr:housenumber":"34",
    "addr:postcode":"2180",
    "addr:street":"Kloosterstraat",
    "iso:country":"BE",
    "sg:address":"Kloosterstraat 34",
    "sg:city":"Antwerpen",
    "sg:classifiers":[
        {
            "category":"Personal",
            "subcategory":"Beauty Salon",
            "type":"Services"
        }
    ],
    "sg:phone":"+32 3 541 22 12",
    "sg:postcode":"2180",
    "sg:province":"Antwerpen",
    "sg:tags":[
        "de",
        "coiffure"
    ],
    "wof:name":"Coiffure Britt",
    "wof:placetype":"venue"
},
  "geometry": {"coordinates":[4.3951301575,51.2165527344],"type":"Point"}
}