{
  "type": "Feature",
  "properties": {
    "addr:full":"Duffelsesteenweg 55a Sint-katelijne-waver Antwerpen 2860",
    "addr:housenumber":"55a",
    "addr:postcode":"2860",
    "addr:street":"Duffelsesteenweg",
    "iso:country":"BE",
    "sg:address":"Duffelsesteenweg 55a",
    "sg:city":"Sint-katelijne-waver",
    "sg:classifiers":[
        {
            "category":"Building & Trades",
            "subcategory":"Construction",
            "type":"Services"
        }
    ],
    "sg:phone":"+32 15 32 04 94",
    "sg:postcode":"2860",
    "sg:province":"Antwerpen",
    "sg:tags":[
        "roofing",
        "material",
        "-"
    ],
    "wof:name":"D.i.v.c. Bvba",
    "wof:placetype":"venue"
},
  "geometry": {"coordinates":[4.5314269066,51.0732574463],"type":"Point"}
}