{
  "type": "Feature",
  "properties": {
    "iso:country":"BE",
    "sg:address":"Rue Gendarmerie 9",
    "sg:city":"Comblain-au-pont",
    "sg:orig_category":"Gespecialiseerde niet-residenti\u00eble bouw",
    "sg:phone":"+32 4 369 35 85",
    "sg:postcode":"4170",
    "sg:province":"Li\u00e8ge",
    "wof:name":"Detracharp",
    "wof:placetype":"venue"
},
  "geometry": {"coordinates":[5.5782361031,50.4778289795],"type":"Point"}
}