{
  "type": "Feature",
  "properties": {
    "addr:full":"Steenstraat 13 Ardooie (koolskamp) West-Vlaanderen 8851",
    "addr:housenumber":"13",
    "addr:postcode":"8851",
    "addr:street":"Steenstraat",
    "iso:country":"BE",
    "sg:address":"Steenstraat 13",
    "sg:city":"Ardooie (koolskamp)",
    "sg:classifiers":[
        {
            "category":"Building & Trades",
            "subcategory":"Construction",
            "type":"Services"
        }
    ],
    "sg:phone":"+32 478 50 91 79",
    "sg:postcode":"8851",
    "sg:province":"West-Vlaanderen",
    "sg:tags":[
        "carpenter"
    ],
    "wof:name":"New-driessens Bvba",
    "wof:placetype":"venue"
},
  "geometry": {"coordinates":[3.2077929974,51.0040626526],"type":"Point"}
}