{
  "type": "Feature",
  "properties": {
    "addr:full":"Vis\u00c9 Voie 301 Herstal Li\u00e8ge 4041",
    "addr:housenumber":"301",
    "addr:postcode":"4041",
    "addr:street":"Voie",
    "iso:country":"BE",
    "sg:address":"Vis\u00c9 Voie 301",
    "sg:city":"Herstal",
    "sg:orig_category":"Kantoormateriaal Gh",
    "sg:phone":"+32 4 227 31 00",
    "sg:postcode":"4041",
    "sg:province":"Li\u00e8ge",
    "wof:name":"Philippe Fichefet",
    "wof:placetype":"venue"
},
  "geometry": {"coordinates":[5.5814061165,50.6738891602],"type":"Point"}
}