{
  "type": "Feature",
  "properties": {
    "addr:full":"Quai Des Ardennes 117 Li\u00c8ge Li\u00e8ge 4031",
    "addr:housenumber":"117",
    "addr:postcode":"4031",
    "addr:street":"Quai Des Ardennes",
    "iso:country":"BE",
    "sg:address":"Quai Des Ardennes 117",
    "sg:city":"Li\u00c8ge",
    "sg:orig_category":"V\u00e9hicules automobiles",
    "sg:phone":"+32 4 365 39 90",
    "sg:postcode":"4031",
    "sg:province":"Li\u00e8ge",
    "wof:name":"Esso",
    "wof:placetype":"venue"
},
  "geometry": {"coordinates":[5.6058387756,50.6153297424],"type":"Point"}
}