{
  "type": "Feature",
  "properties": {
    "addr:full":"Snelwegstraat 15b Westerlo (oevel) Antwerpen 2260",
    "addr:housenumber":"15b",
    "addr:postcode":"2260",
    "addr:street":"Snelwegstraat",
    "iso:country":"BE",
    "sg:address":"Snelwegstraat 15b",
    "sg:city":"Westerlo (oevel)",
    "sg:classifiers":[
        {
            "category":"Building & Trades",
            "subcategory":"Electrical",
            "type":"Services"
        }
    ],
    "sg:phone":"+32 14 47 11 74",
    "sg:postcode":"2260",
    "sg:province":"Antwerpen",
    "sg:tags":[
        "tool",
        "electric"
    ],
    "wof:name":"Fabory Centre Turnhout & Geel",
    "wof:placetype":"venue"
},
  "geometry": {"coordinates":[4.9387331009,51.1364517212],"type":"Point"}
}