{
  "type": "Feature",
  "properties": {
    "addr:full":"Route De Mortier 3 Bl\u00c9gny Li\u00e8ge 4670",
    "addr:housenumber":"3",
    "addr:postcode":"4670",
    "addr:street":"Route De Mortier",
    "iso:country":"BE",
    "sg:address":"Route De Mortier 3",
    "sg:city":"Bl\u00c9gny",
    "sg:orig_category":"Pain, p\u00e2tisseries and confiseries",
    "sg:phone":"+32 4 387 46 63",
    "sg:postcode":"4670",
    "sg:province":"Li\u00e8ge",
    "wof:name":"Boulangerie M. Colson",
    "wof:placetype":"venue"
},
  "geometry": {"coordinates":[5.7502498627,50.6820487976],"type":"Point"}
}