{
  "type": "Feature",
  "properties": {
    "iso:country":"BE",
    "sg:address":"Nieuwstraat 49",
    "sg:city":"Bierbeek",
    "sg:orig_category":"Catering and organisatie van feesten",
    "sg:phone":"+32 16 46 39 40",
    "sg:postcode":"3360",
    "sg:province":"Vlaams-Brabant",
    "wof:name":"Hugues Braekeleire",
    "wof:placetype":"venue"
},
  "geometry": {"coordinates":[4.7582178116,50.8657226562],"type":"Point"}
}