{
  "type": "Feature",
  "properties": {
    "iso:country":"BE",
    "sg:address":"Lenneke Marelaan 18b43",
    "sg:city":"Zaventem",
    "sg:orig_category":"M\u00e9decins and sp\u00e9cialistes",
    "sg:phone":"+32 2 725 94 82",
    "sg:postcode":"1932",
    "sg:province":"Vlaams-Brabant",
    "wof:name":"Sandra Malburny",
    "wof:placetype":"venue"
},
  "geometry": {"coordinates":[4.4504079819,50.8566894531],"type":"Point"}
}