{
  "type": "Feature",
  "properties": {
    "iso:country":"BE",
    "sg:address":"Steenwinkelstraat 344",
    "sg:city":"Schelle",
    "sg:orig_category":"Messageries",
    "sg:phone":"+32 475 75 09 16",
    "sg:postcode":"2627",
    "sg:province":"Antwerpen",
    "wof:name":"Koerier Mario",
    "wof:placetype":"venue"
},
  "geometry": {"coordinates":[4.3485198021,51.1248092651],"type":"Point"}
}