{
  "type": "Feature",
  "properties": {
    "addr:full":"Rue Jules Monoyer 101 La Louviere Hainaut 7110",
    "addr:housenumber":"101",
    "addr:postcode":"7110",
    "addr:street":"Rue Jules Monoyer",
    "iso:country":"BE",
    "sg:address":"Rue Jules Monoyer 101",
    "sg:city":"La Louviere",
    "sg:orig_category":"Pharmaciens",
    "sg:phone":"+32 64 22 10 20",
    "sg:postcode":"7110",
    "sg:province":"Hainaut",
    "wof:name":"Decleve A.",
    "wof:placetype":"venue"
},
  "geometry": {"coordinates":[4.1505050659,50.4826698303],"type":"Point"}
}