{
  "type": "Feature",
  "properties": {
    "iso:country":"BE",
    "sg:address":"Van Frachenlaan 69",
    "sg:city":"Steenokkerzeel",
    "sg:classifiers":[
        {
            "category":"Health Services",
            "subcategory":"Dentist",
            "type":"Services"
        }
    ],
    "sg:phone":"+32 2 759 44 15",
    "sg:postcode":"1820",
    "sg:province":"Vlaams-Brabant",
    "wof:name":"Van Elst Ph",
    "wof:placetype":"venue"
},
  "geometry": {"coordinates":[4.5076160431,50.9147491455],"type":"Point"}
}