{
  "type": "Feature",
  "properties": {
    "addr:full":"Oudasserstraat 29 Genk Limburg 3600",
    "addr:housenumber":"29",
    "addr:postcode":"3600",
    "addr:street":"Oudasserstraat",
    "iso:country":"BE",
    "sg:address":"Oudasserstraat 29",
    "sg:city":"Genk",
    "sg:orig_category":"Traitements param\u00e9dicaux. Instituts de beaut\u00e9",
    "sg:phone":"+32 89 38 47 04",
    "sg:postcode":"3600",
    "sg:province":"Limburg",
    "wof:name":"Anne Trumpener",
    "wof:placetype":"venue"
},
  "geometry": {"coordinates":[5.5466170311,50.9858436584],"type":"Point"}
}