{
  "type": "Feature",
  "properties": {
    "iso:country":"BE",
    "sg:address":"Rue De Joie 21",
    "sg:city":"Li\u00e8ge 1",
    "sg:orig_category":"Domotics",
    "sg:phone":"+32 4 229 37 97",
    "sg:postcode":"4000",
    "sg:province":"Li\u00e8ge",
    "wof:name":"Anb Securit\u00e9 Sa",
    "wof:placetype":"venue"
},
  "geometry": {"coordinates":[5.5603609085,50.6290740967],"type":"Point"}
}