{
  "type": "Feature",
  "properties": {
    "iso:country":"BE",
    "sg:address":"Kerkstraat 29",
    "sg:city":"Wemmel",
    "sg:orig_category":"Voedingsspeciaalzaken",
    "sg:phone":"+32 2 461 39 69",
    "sg:postcode":"1780",
    "sg:province":"Vlaams-Brabant",
    "wof:name":"Huis Dandelion",
    "wof:placetype":"venue"
},
  "geometry": {"coordinates":[4.3019199371,50.9097747803],"type":"Point"}
}