{
  "type": "Feature",
  "properties": {
    "iso:country":"BE",
    "sg:address":"Pauwstraat 91",
    "sg:city":"Beveren",
    "sg:orig_category":"Sportclubs",
    "sg:phone":"+32 3 775 34 25",
    "sg:postcode":"9120",
    "sg:province":"Oost-Vlaanderen",
    "wof:name":"Alcatel Bell Fv",
    "wof:placetype":"venue"
},
  "geometry": {"coordinates":[4.2938199043,51.2153053284],"type":"Point"}
}