{
  "type": "Feature",
  "properties": {
    "addr:full":"Rue Buche 6 Couvin Namur 5660",
    "addr:housenumber":"6",
    "addr:postcode":"5660",
    "addr:street":"Rue Buche",
    "iso:country":"BE",
    "sg:address":"Rue Buche 6",
    "sg:city":"Couvin",
    "sg:orig_category":"Woningbouw",
    "sg:phone":"+32 60 34 42 06",
    "sg:postcode":"5660",
    "sg:province":"Namur",
    "wof:name":"Regnier Guy",
    "wof:placetype":"venue"
},
  "geometry": {"coordinates":[4.4590549469,50.0437202454],"type":"Point"}
}