{
  "type": "Feature",
  "properties": {
    "addr:full":"Rue Du Village 11 Ciney Namur 5590",
    "addr:housenumber":"11",
    "addr:postcode":"5590",
    "addr:street":"Rue Du Village",
    "iso:country":"BE",
    "sg:address":"Rue Du Village 11",
    "sg:city":"Ciney",
    "sg:orig_category":"Traitements param\u00e9dicaux",
    "sg:phone":"+32 83 21 62 25",
    "sg:postcode":"5590",
    "sg:province":"Namur",
    "wof:name":"F. Ballaux",
    "wof:placetype":"venue"
},
  "geometry": {"coordinates":[5.1037697792,50.2244644165],"type":"Point"}
}