{
  "type": "Feature",
  "properties": {
    "iso:country":"BE",
    "sg:address":"Vennehoeveweg 34",
    "sg:city":"Boechout (vremde)",
    "sg:classifiers":[
        {
            "category":"Farming",
            "subcategory":"Crops",
            "type":"Manufacturing & Wholesale Goods"
        }
    ],
    "sg:phone":"+32 3 485 64 83",
    "sg:postcode":"2531",
    "sg:province":"Antwerpen",
    "sg:tags":[
        "vegetable",
        "fruit",
        "-",
        "grower"
    ],
    "wof:name":"Dewinter I",
    "wof:placetype":"venue"
},
  "geometry": {"coordinates":[4.5487232208,51.1765937805],"type":"Point"}
}