{
  "type": "Feature",
  "properties": {
    "addr:full":"Beenderstraat 3a Nijlen Antwerpen 2560",
    "addr:housenumber":"3a",
    "addr:postcode":"2560",
    "addr:street":"Beenderstraat",
    "iso:country":"BE",
    "sg:address":"Beenderstraat 3a",
    "sg:city":"Nijlen",
    "sg:orig_category":"Artsen and specialisten Astrologen, grafologen and mediums",
    "sg:phone":"+32 3 411 28 07",
    "sg:postcode":"2560",
    "sg:province":"Antwerpen",
    "wof:name":"Mandala Lier",
    "wof:placetype":"venue"
},
  "geometry": {"coordinates":[4.6936211586,51.1642379761],"type":"Point"}
}