{
  "type": "Feature",
  "properties": {
    "iso:country":"BE",
    "sg:address":"Braamstraat 59",
    "sg:city":"Schoten",
    "sg:classifiers":[
        {
            "category":"Real Estate",
            "subcategory":"Developer",
            "type":"Services"
        }
    ],
    "sg:phone":"+32 3 610 03 00",
    "sg:postcode":"2900",
    "sg:province":"Antwerpen",
    "sg:tags":[
        "project"
    ],
    "wof:name":"Buco Nv",
    "wof:placetype":"venue"
},
  "geometry": {"coordinates":[4.4988899231,51.2436485291],"type":"Point"}
}