{
  "type": "Feature",
  "properties": {
    "addr:full":"Avenue Des Gerfauts 5 Bruxelles (watermael-boitsfort) Bruxelles-Capitale 1170",
    "addr:housenumber":"5",
    "addr:postcode":"1170",
    "addr:street":"Avenue Des Gerfauts",
    "iso:country":"BE",
    "sg:address":"Avenue Des Gerfauts 5",
    "sg:city":"Bruxelles (watermael-boitsfort)",
    "sg:classifiers":[
        {
            "category":"Health Services",
            "subcategory":"Doctor",
            "type":"Services"
        }
    ],
    "sg:phone":"+32 2 673 63 28",
    "sg:postcode":"1170",
    "sg:province":"Bruxelles-Capitale",
    "sg:tags":[
        "medicinephysicians",
        "surgeon"
    ],
    "wof:name":"Bier Henri",
    "wof:placetype":"venue"
},
  "geometry": {"coordinates":[4.4166111946,50.8112678528],"type":"Point"}
}