{
  "type": "Feature",
  "properties": {
    "iso:country":"BE",
    "sg:address":"Casselsestraat 54",
    "sg:city":"Ieper",
    "sg:orig_category":"Rundveehouders Varkenskwekers",
    "sg:phone":"+32 57 33 38 56",
    "sg:postcode":"8908",
    "sg:province":"West-Vlaanderen",
    "wof:name":"Jacques Delva",
    "wof:placetype":"venue"
},
  "geometry": {"coordinates":[2.7861731052,50.8466300964],"type":"Point"}
}