{
  "type": "Feature",
  "properties": {
    "addr:full":"Rootstraat 24 Hasselt Limburg 3510",
    "addr:housenumber":"24",
    "addr:postcode":"3510",
    "addr:street":"Rootstraat",
    "iso:country":"BE",
    "sg:address":"Rootstraat 24",
    "sg:city":"Hasselt",
    "sg:orig_category":"Artsen and specialisten",
    "sg:phone":"+32 11 25 39 36",
    "sg:postcode":"3510",
    "sg:province":"Limburg",
    "wof:name":"Paul Theuwis",
    "wof:placetype":"venue"
},
  "geometry": {"coordinates":[5.2375340462,50.9535064697],"type":"Point"}
}