{
  "type": "Feature",
  "properties": {
    "iso:country":"BE",
    "sg:address":"All\u00c9e Des Fr\u00canes 8",
    "sg:city":"Couvin",
    "sg:orig_category":"Quincailleries. Fabrication and montage de mobilier",
    "sg:phone":"+32 475 62 37 04",
    "sg:postcode":"5660",
    "sg:province":"Namur",
    "wof:name":"Espace C & Sdb - Sb",
    "wof:placetype":"venue"
},
  "geometry": {"coordinates":[4.5084748268,50.0731697083],"type":"Point"}
}