{
  "type": "Feature",
  "properties": {
    "iso:country":"BE",
    "sg:address":"Steenstr 10",
    "sg:city":"Mere",
    "sg:classifiers":[
        {
            "category":"Banks & Credit Unions",
            "subcategory":"Bank",
            "type":"Services"
        }
    ],
    "sg:phone":"+32 53 77 36 84",
    "sg:postcode":"9420",
    "sg:province":"Oost-Vlaanderen",
    "wof:name":"Aslk-cger Bank",
    "wof:placetype":"venue"
},
  "geometry": {"coordinates":[3.9683389664,50.9219741821],"type":"Point"}
}