{
  "type": "Feature",
  "properties": {
    "addr:full":"Rue Des Noyers 81 Li\u00e8ge 1 Li\u00e8ge 4000",
    "addr:housenumber":"81;1",
    "addr:postcode":"4000",
    "addr:street":"Rue Des Noyers",
    "iso:country":"BE",
    "sg:address":"Rue Des Noyers 81",
    "sg:city":"Li\u00e8ge 1",
    "sg:orig_category":"Non-Classified Establishments",
    "sg:phone":"+32 4 226 51 96",
    "sg:postcode":"4000",
    "sg:province":"Li\u00e8ge",
    "wof:name":"Calentzos G",
    "wof:placetype":"venue"
},
  "geometry": {"coordinates":[5.5380811691,50.6383972168],"type":"Point"}
}