{
  "type": "Feature",
  "properties": {
    "iso:country":"BE",
    "sg:address":"Chauss\u00e9e De Charleroi 153",
    "sg:city":"Fleurus",
    "sg:classifiers":[
        {
            "category":"Health Services",
            "subcategory":"Health Practitioner",
            "type":"Services"
        }
    ],
    "sg:phone":"+32 71 81 36 63",
    "sg:postcode":"6220",
    "sg:province":"Hainaut",
    "sg:tags":[
        "physiotherapist"
    ],
    "wof:name":"Desmanet G",
    "wof:placetype":"venue"
},
  "geometry": {"coordinates":[4.5528850555,50.4839859009],"type":"Point"}
}