{
  "type": "Feature",
  "properties": {
    "iso:country":"BE",
    "sg:address":"Rue De La Brasserie 3",
    "sg:city":"La Bruy\u00c8re",
    "sg:orig_category":"Binnenhuisarchitecten",
    "sg:phone":"+32 81 51 15 79",
    "sg:postcode":"5080",
    "sg:province":"Namur",
    "wof:name":"Gregory Radart",
    "wof:placetype":"venue"
},
  "geometry": {"coordinates":[4.8651938438,50.5353965759],"type":"Point"}
}