{
  "type": "Feature",
  "properties": {
    "addr:full":"Grote Steenweg 141a Zoutleeuw (halle-booienhoven) Vlaams-Brabant 3440",
    "addr:housenumber":"141a",
    "addr:postcode":"3440",
    "addr:street":"Grote Steenweg",
    "iso:country":"BE",
    "sg:address":"Grote Steenweg 141a",
    "sg:city":"Zoutleeuw (halle-booienhoven)",
    "sg:classifiers":[
        {
            "category":"Autos & Motor Vehicles",
            "subcategory":"Recreational Vehicle Sales",
            "type":"Retail Goods"
        }
    ],
    "sg:phone":"+32 11 78 18 17",
    "sg:postcode":"3440",
    "sg:province":"Vlaams-Brabant",
    "sg:tags":[
        "caravan",
        "accessory"
    ],
    "wof:name":"Castermans & Leclere",
    "wof:placetype":"venue"
},
  "geometry": {"coordinates":[5.1226038933,50.8098716736],"type":"Point"}
}