{
  "type": "Feature",
  "properties": {
    "addr:full":"Rue Jean Monnet 5b56 Charleroi Hainaut 6000",
    "addr:housenumber":"5b56",
    "addr:postcode":"6000",
    "addr:street":"Rue Jean Monnet;Hainaut",
    "iso:country":"BE",
    "sg:address":"Rue Jean Monnet 5b56",
    "sg:city":"Charleroi",
    "sg:classifiers":[
        {
            "category":"Health Services",
            "subcategory":"Nursing And Care Facility",
            "type":"Services"
        }
    ],
    "sg:phone":"+32 71 23 12 11",
    "sg:postcode":"6000",
    "sg:province":"Hainaut",
    "sg:tags":[
        "public"
    ],
    "wof:name":"Admin. Contrib. Directes",
    "wof:placetype":"venue"
},
  "geometry": {"coordinates":[4.4372549057,50.4073982239],"type":"Point"}
}