{
  "type": "Feature",
  "properties": {
    "iso:country":"BE",
    "sg:address":"Rue De Goz\u00c9e 108",
    "sg:city":"Montigny-le-tilleul",
    "sg:orig_category":"Herstellingen and onderhoud van auto's",
    "sg:phone":"+32 71 51 74 16",
    "sg:postcode":"6110",
    "sg:province":"Hainaut",
    "wof:name":"Garage Piteraerens",
    "wof:placetype":"venue"
},
  "geometry": {"coordinates":[4.384018898,50.388343811],"type":"Point"}
}