{
  "type": "Feature",
  "properties": {
    "addr:full":"Hansevelde 6b2 Zele Oost-Vlaanderen 9240",
    "addr:housenumber":"6b2",
    "addr:postcode":"9240",
    "addr:street":"Hansevelde",
    "iso:country":"BE",
    "sg:address":"Hansevelde 6b2",
    "sg:city":"Zele",
    "sg:orig_category":"Dierenartsen",
    "sg:phone":"+32 52 44 60 97",
    "sg:postcode":"9240",
    "sg:province":"Oost-Vlaanderen",
    "wof:name":"Herman De Brabander",
    "wof:placetype":"venue"
},
  "geometry": {"coordinates":[4.0751471519,51.0669174194],"type":"Point"}
}