{
  "type": "Feature",
  "properties": {
    "iso:country":"BE",
    "sg:address":"Waterhoek 46",
    "sg:city":"Kortrijk (heule)",
    "sg:classifiers":[
        {
            "category":"Personal",
            "subcategory":"Nail Salon",
            "type":"Services"
        }
    ],
    "sg:phone":"+32 56 35 25 60",
    "sg:postcode":"8501",
    "sg:province":"West-Vlaanderen",
    "sg:tags":[
        "pedicure"
    ],
    "wof:name":"Sophie",
    "wof:placetype":"venue"
},
  "geometry": {"coordinates":[3.253786087,50.841835022],"type":"Point"}
}