{
  "type": "Feature",
  "properties": {
    "iso:country":"BE",
    "sg:address":"Rue Eug\u00e8ne Vandenhoff 88",
    "sg:city":"Li\u00e8ge 1 (grivegn\u00e9e)",
    "sg:classifiers":[
        {
            "category":"Banks & Credit Unions",
            "subcategory":"Investment Brokerage",
            "type":"Services"
        }
    ],
    "sg:phone":"+32 4 342 85 96",
    "sg:postcode":"4030",
    "sg:province":"Li\u00e8ge",
    "sg:tags":[
        "printing",
        "-"
    ],
    "wof:name":"Serinco",
    "wof:placetype":"venue"
},
  "geometry": {"coordinates":[5.6027550697,50.6303939819],"type":"Point"}
}