{
  "type": "Feature",
  "properties": {
    "iso:country":"BE",
    "sg:address":"Tielensteenweg 39",
    "sg:city":"Kasterlee",
    "sg:orig_category":"Benzinestations and brandstoffen",
    "sg:phone":"+32 14 55 70 21",
    "sg:postcode":"2460",
    "sg:province":"Antwerpen",
    "wof:name":"Garage Van Pelt J.",
    "wof:placetype":"venue"
},
  "geometry": {"coordinates":[4.8998818398,51.2403411865],"type":"Point"}
}