{
  "type": "Feature",
  "properties": {
    "iso:country":"BE",
    "sg:address":"Hoefslagstraat 8",
    "sg:city":"Nazareth",
    "sg:orig_category":"Drukkerijen and copyshops",
    "sg:phone":"+32 9 385 62 78",
    "sg:postcode":"9810",
    "sg:province":"Oost-Vlaanderen",
    "wof:name":"Joris Rowaert",
    "wof:placetype":"venue"
},
  "geometry": {"coordinates":[3.5927219391,50.9545135498],"type":"Point"}
}