{
  "type": "Feature",
  "properties": {
    "addr:full":"Wampenberg 1b9 Arendonk Antwerpen 2370",
    "addr:housenumber":"1b9",
    "addr:postcode":"2370",
    "addr:street":"Wampenberg",
    "iso:country":"BE",
    "sg:address":"Wampenberg 1b9",
    "sg:city":"Arendonk",
    "sg:orig_category":"Projectontwikkelaars",
    "sg:phone":"+32 14 42 16 07",
    "sg:postcode":"2370",
    "sg:province":"Antwerpen",
    "wof:name":"Green Fields",
    "wof:placetype":"venue"
},
  "geometry": {"coordinates":[5.091176033,51.3244628906],"type":"Point"}
}