{
  "type": "Feature",
  "properties": {
    "addr:full":"Gaucheretstraat 139 Schaarbeek/schaerbeek Bruxelles-Capitale 1030",
    "addr:housenumber":"139",
    "addr:postcode":"1030",
    "addr:street":"Gaucheretstraat",
    "iso:country":"BE",
    "sg:address":"Gaucheretstraat 139",
    "sg:city":"Schaarbeek/schaerbeek",
    "sg:orig_category":"Drukkerijen and copyshops",
    "sg:phone":"+32 2 201 15 45",
    "sg:postcode":"1030",
    "sg:province":"Bruxelles-Capitale",
    "wof:name":"Drukkerij Carto",
    "wof:placetype":"venue"
},
  "geometry": {"coordinates":[4.361330986,50.8655700684],"type":"Point"}
}