{
  "type": "Feature",
  "properties": {
    "addr:full":"Rue Hors-ch\u00c2teau 108bb Li\u00c8ge Li\u00e8ge 4000",
    "addr:housenumber":"108bb",
    "addr:postcode":"4000",
    "addr:street":"Rue Hors-Cha\u0302Teau",
    "iso:country":"BE",
    "sg:address":"Rue Hors-ch\u00c2teau 108bb",
    "sg:city":"Li\u00c8ge",
    "sg:orig_category":"M\u00e9decins and sp\u00e9cialistes",
    "sg:phone":"+32 4 221 16 20",
    "sg:postcode":"4000",
    "sg:province":"Li\u00e8ge",
    "wof:name":"Virginie Pierre",
    "wof:placetype":"venue"
},
  "geometry": {"coordinates":[5.5811038017,50.6476707458],"type":"Point"}
}