{
  "type": "Feature",
  "properties": {
    "iso:country":"BE",
    "sg:address":"Schansstraat 226",
    "sg:city":"Heusden-zolder",
    "sg:orig_category":"Sportclubs",
    "sg:phone":"+32 11 57 34 62",
    "sg:postcode":"3550",
    "sg:province":"Limburg",
    "wof:name":"B.c. 't Kanaal",
    "wof:placetype":"venue"
},
  "geometry": {"coordinates":[5.3193240166,51.0490264893],"type":"Point"}
}