{
  "type": "Feature",
  "properties": {
    "addr:full":"Route De Becco 33 Theux Li\u00e8ge 4910",
    "addr:housenumber":"33",
    "addr:postcode":"4910",
    "addr:street":"Route De Becco",
    "iso:country":"BE",
    "sg:address":"Route De Becco 33",
    "sg:city":"Theux",
    "sg:orig_category":"Ergotherapists",
    "sg:phone":"+32 87 54 27 77",
    "sg:postcode":"4910",
    "sg:province":"Li\u00e8ge",
    "wof:name":"Paternoster N",
    "wof:placetype":"venue"
},
  "geometry": {"coordinates":[5.8137478828,50.51537323],"type":"Point"}
}