{
  "type": "Feature",
  "properties": {
    "iso:country":"BE",
    "sg:address":"Rue Navez 12",
    "sg:city":"Charleroi",
    "sg:classifiers":[
        {
            "category":"Restaurant",
            "type":"Food & Drink"
        }
    ],
    "sg:phone":"+32 71 32 44 82",
    "sg:postcode":"6000",
    "sg:province":"Hainaut",
    "wof:name":"La Patte Folle",
    "wof:placetype":"venue"
},
  "geometry": {"coordinates":[4.4441142082,50.4071922302],"type":"Point"}
}