{
  "type": "Feature",
  "properties": {
    "iso:country":"BE",
    "sg:address":"Goethalsstraat 1",
    "sg:city":"Nieuwpoort",
    "sg:classifiers":[
        {
            "category":"Travel",
            "subcategory":"Hotels & Motels",
            "type":"Entertainment"
        }
    ],
    "sg:phone":"+32 58 23 41 53",
    "sg:postcode":"8620",
    "sg:province":"West-Vlaanderen",
    "wof:name":"Sandeshoved Nv",
    "wof:placetype":"venue"
},
  "geometry": {"coordinates":[2.7162330151,51.1488685608],"type":"Point"}
}