{
  "type": "Feature",
  "properties": {
    "iso:country":"BE",
    "sg:address":"Hoogstraat 28",
    "sg:city":"Landen",
    "sg:orig_category":"Artsen and specialisten",
    "sg:phone":"+32 11 88 35 50",
    "sg:postcode":"3400",
    "sg:province":"Vlaams-Brabant",
    "wof:name":"J. Ieven",
    "wof:placetype":"venue"
},
  "geometry": {"coordinates":[5.0793237686,50.7558746338],"type":"Point"}
}