{
  "type": "Feature",
  "properties": {
    "addr:full":"Meerstraat 141 Grimbergen (beigem) Vlaams-Brabant 1852",
    "addr:housenumber":"141",
    "addr:postcode":"1852",
    "addr:street":"Meerstraat",
    "iso:country":"BE",
    "sg:address":"Meerstraat 141",
    "sg:city":"Grimbergen (beigem)",
    "sg:classifiers":[
        {
            "category":"Home & Garden",
            "subcategory":"Building Materials",
            "type":"Retail Goods"
        }
    ],
    "sg:phone":"+32 2 269 04 90",
    "sg:postcode":"1852",
    "sg:province":"Vlaams-Brabant",
    "sg:tags":[
        "window"
    ],
    "wof:name":"Stepp\u00e9 Bvba",
    "wof:placetype":"venue"
},
  "geometry": {"coordinates":[4.3604369164,50.9571495056],"type":"Point"}
}