{
  "type": "Feature",
  "properties": {
    "iso:country":"BE",
    "sg:address":"Rue De Momalle 14",
    "sg:city":"Remicourt (hodeige)",
    "sg:classifiers":[
        {
            "category":"Building & Trades",
            "subcategory":"Locksmith",
            "type":"Services"
        }
    ],
    "sg:phone":"+32 19 54 59 03",
    "sg:postcode":"4351",
    "sg:province":"Li\u00e8ge",
    "sg:tags":[
        "material",
        "road"
    ],
    "wof:name":"Bairin",
    "wof:placetype":"venue"
},
  "geometry": {"coordinates":[5.3476948738,50.695022583],"type":"Point"}
}