{
  "type": "Feature",
  "properties": {
    "iso:country":"BE",
    "sg:address":"Aardeweg 57",
    "sg:city":"Ninove",
    "sg:classifiers":[
        {
            "category":"Insurance",
            "subcategory":"Insurance Agent",
            "type":"Services"
        }
    ],
    "sg:phone":"+32 54 33 02 54",
    "sg:postcode":"9406",
    "sg:province":"Oost-Vlaanderen",
    "sg:tags":[
        "verzekeringsmakelaars",
        "expert"
    ],
    "wof:name":"D. Beeckman",
    "wof:placetype":"venue"
},
  "geometry": {"coordinates":[3.9944410324,50.8315238953],"type":"Point"}
}