{
  "type": "Feature",
  "properties": {
    "addr:full":"Klein-hulststraat 104 Sint-niklaas Oost-Vlaanderen 9100",
    "addr:housenumber":"104",
    "addr:postcode":"9100",
    "iso:country":"BE",
    "sg:address":"Klein-hulststraat 104",
    "sg:city":"Sint-niklaas",
    "sg:classifiers":[
        {
            "category":"Banks & Credit Unions",
            "subcategory":"Investment Brokerage",
            "type":"Services"
        }
    ],
    "sg:phone":"+32 3 776 36 63",
    "sg:postcode":"9100",
    "sg:province":"Oost-Vlaanderen",
    "sg:tags":[
        "repair",
        "-",
        "installation",
        "sanitary",
        "article"
    ],
    "wof:name":"Pat Sanitair",
    "wof:placetype":"venue"
},
  "geometry": {"coordinates":[4.151198864,51.1674613953],"type":"Point"}
}