{
  "type": "Feature",
  "properties": {
    "addr:full":"Rue Adrienne Bolland 47 Gosselies Hainaut 6041",
    "addr:housenumber":"47",
    "addr:postcode":"6041",
    "addr:street":"Rue Adrienne Bolland",
    "iso:country":"BE",
    "sg:address":"Rue Adrienne Bolland 47",
    "sg:city":"Gosselies",
    "sg:classifiers":[
        {
            "category":"Health Services",
            "subcategory":"Medical Lab",
            "type":"Services"
        }
    ],
    "sg:phone":"+32 71 34 85 00",
    "sg:postcode":"6041",
    "sg:province":"Hainaut",
    "sg:tags":[
        "laboratory",
        "bio-technology",
        "biological"
    ],
    "wof:name":"Euroscreen S.a.",
    "wof:placetype":"venue"
},
  "geometry": {"coordinates":[4.4710898399,50.4715843201],"type":"Point"}
}