{
  "type": "Feature",
  "properties": {
    "addr:full":"Rue Houlteau 22 Chaineux Li\u00e8ge 4650",
    "addr:housenumber":"22",
    "addr:postcode":"4650",
    "addr:street":"Rue Houlteau",
    "iso:country":"BE",
    "sg:address":"Rue Houlteau 22",
    "sg:city":"Chaineux",
    "sg:orig_category":"Travaux de pl\u00e2trage",
    "sg:phone":"+32 87 44 53 73",
    "sg:postcode":"4650",
    "sg:province":"Li\u00e8ge",
    "wof:name":"Jamar St\u00c9phane Sprl",
    "wof:placetype":"venue"
},
  "geometry": {"coordinates":[5.8527479172,50.6270599365],"type":"Point"}
}