{
  "type": "Feature",
  "properties": {
    "iso:country":"BE",
    "sg:address":"Paleizenstraat 149",
    "sg:city":"Schaarbeek/schaerbeek",
    "sg:orig_category":"Kapsalons",
    "sg:phone":"+32 2 215 26 75",
    "sg:postcode":"1030",
    "sg:province":"Bruxelles-Capitale",
    "wof:name":"Liedts",
    "wof:placetype":"venue"
},
  "geometry": {"coordinates":[4.3663592339,50.865978241],"type":"Point"}
}