{
  "type": "Feature",
  "properties": {
    "addr:full":"Koninklijkestraat 27 Kortrijk (kooigem) West-Vlaanderen 8510",
    "addr:housenumber":"27",
    "addr:postcode":"8510",
    "addr:street":"Koninklijkestraat",
    "iso:country":"BE",
    "sg:address":"Koninklijkestraat 27",
    "sg:city":"Kortrijk (kooigem)",
    "sg:classifiers":[
        {
            "category":"Bakery",
            "type":"Food & Drink"
        }
    ],
    "sg:phone":"+32 56 45 55 18",
    "sg:postcode":"8510",
    "sg:province":"West-Vlaanderen",
    "sg:tags":[
        "confectioner",
        "baker"
    ],
    "wof:name":"Haelewijn G",
    "wof:placetype":"venue"
},
  "geometry": {"coordinates":[3.3297228813,50.7383270264],"type":"Point"}
}