{
  "type": "Feature",
  "properties": {
    "addr:full":"Rue Robert Boisacq 8 Rixensart Brabant Wallon 1330",
    "addr:housenumber":"8",
    "addr:postcode":"1330",
    "addr:street":"Rue Robert Boisacq;Wallon",
    "iso:country":"BE",
    "sg:address":"Rue Robert Boisacq 8",
    "sg:city":"Rixensart",
    "sg:orig_category":"Cr\u00e9dits divers",
    "sg:postcode":"1330",
    "sg:province":"Brabant Wallon",
    "wof:name":"Bancontact-mister Cash",
    "wof:placetype":"venue"
},
  "geometry": {"coordinates":[4.5299100876,50.7130699158],"type":"Point"}
}