{
  "type": "Feature",
  "properties": {
    "iso:country":"BE",
    "sg:address":"Diercxsensstraat 37",
    "sg:city":"Antwerpen",
    "sg:classifiers":[
        {
            "category":"Arts & Performance",
            "subcategory":"Music",
            "type":"Entertainment"
        }
    ],
    "sg:phone":"+32 3 238 83 34",
    "sg:postcode":"2018",
    "sg:province":"Antwerpen",
    "sg:tags":[
        "freelance",
        "musician"
    ],
    "wof:name":"Haegemans H",
    "wof:placetype":"venue"
},
  "geometry": {"coordinates":[4.3988199234,51.2045516968],"type":"Point"}
}