{
  "type": "Feature",
  "properties": {
    "iso:country":"BE",
    "sg:address":"Rue L\u00e9opold 1er 374",
    "sg:city":"Bruxelles",
    "sg:classifiers":[
        {
            "category":"Manufacturing",
            "subcategory":"Printing",
            "type":"Manufacturing & Wholesale Goods"
        }
    ],
    "sg:phone":"+32 2 428 20 55",
    "sg:postcode":"1090",
    "sg:province":"Bruxelles-Capitale",
    "sg:tags":[
        "publishing"
    ],
    "wof:name":"Litho P Jacquet Sa",
    "wof:placetype":"venue"
},
  "geometry": {"coordinates":[4.3315300941,50.8739433289],"type":"Point"}
}