{
  "type": "Feature",
  "properties": {
    "addr:full":"Normaalschoolstraat 8 Gent Oost-Vlaanderen 9000",
    "addr:housenumber":"8",
    "addr:postcode":"9000",
    "addr:street":"Normaalschoolstraat;Oost-Vlaanderen",
    "iso:country":"BE",
    "sg:address":"Normaalschoolstraat 8",
    "sg:city":"Gent",
    "sg:orig_category":"Banken and kredietinstellingen",
    "sg:phone":"+32 9 222 27 61",
    "sg:postcode":"9000",
    "sg:province":"Oost-Vlaanderen",
    "wof:name":"Kbc",
    "wof:placetype":"venue"
},
  "geometry": {"coordinates":[3.726140976,51.0380783081],"type":"Point"}
}