{
  "type": "Feature",
  "properties": {
    "iso:country":"BE",
    "sg:address":"Grote Markt 5",
    "sg:city":"Ieper",
    "sg:orig_category":"Catering and organisatie van feesten Fast food and meeneem restaurants Levering aan huis restaurants",
    "sg:phone":"+32 57 21 73 39",
    "sg:postcode":"8900",
    "sg:province":"West-Vlaanderen",
    "wof:name":"Restaurant Cyper",
    "wof:placetype":"venue"
},
  "geometry": {"coordinates":[2.8880259991,50.8513069153],"type":"Point"}
}