{
  "type": "Feature",
  "properties": {
    "addr:full":"Rue De L'eglise 1 Seraing (boncelles) Li\u00e8ge 4100",
    "addr:housenumber":"1",
    "addr:postcode":"4100",
    "addr:street":"Rue De L'Eglise",
    "iso:country":"BE",
    "sg:address":"Rue De L'eglise 1",
    "sg:city":"Seraing (boncelles)",
    "sg:classifiers":[
        {
            "category":"Bars & Pubs",
            "type":"Food & Drink"
        }
    ],
    "sg:phone":"+32 4 337 84 50",
    "sg:postcode":"4100",
    "sg:province":"Li\u00e8ge",
    "wof:name":"Caf\u00e9 Des Sports",
    "wof:placetype":"venue"
},
  "geometry": {"coordinates":[5.5353169441,50.5724143982],"type":"Point"}
}