{
  "type": "Feature",
  "properties": {
    "addr:full":"Onderwijslaan 9 Neerpelt Limburg 3910",
    "addr:housenumber":"9",
    "addr:postcode":"3910",
    "addr:street":"Onderwijslaan",
    "iso:country":"BE",
    "sg:address":"Onderwijslaan 9",
    "sg:city":"Neerpelt",
    "sg:classifiers":[
        {
            "category":"Health Services",
            "subcategory":"Health Practitioner",
            "type":"Services"
        }
    ],
    "sg:phone":"+32 11 64 58 07",
    "sg:postcode":"3910",
    "sg:province":"Limburg",
    "sg:tags":[
        "physiotherapist"
    ],
    "wof:name":"Ras Ruddi",
    "wof:placetype":"venue"
},
  "geometry": {"coordinates":[5.4306387901,51.23072052],"type":"Point"}
}