{
  "type": "Feature",
  "properties": {
    "addr:full":"Meensestraat 35 Ieper West-Vlaanderen 8900",
    "addr:housenumber":"35",
    "addr:postcode":"8900",
    "addr:street":"Meensestraat",
    "iso:country":"BE",
    "sg:address":"Meensestraat 35",
    "sg:city":"Ieper",
    "sg:classifiers":[
        {
            "category":"Shopping",
            "subcategory":"Gifts & Souvenirs",
            "type":"Retail Goods"
        }
    ],
    "sg:phone":"+32 57 20 12 08",
    "sg:postcode":"8900",
    "sg:province":"West-Vlaanderen",
    "sg:tags":[
        "-"
    ],
    "wof:name":"Beiaard (de)",
    "wof:placetype":"venue"
},
  "geometry": {"coordinates":[2.8899281025,50.8519248962],"type":"Point"}
}