{
  "type": "Feature",
  "properties": {
    "addr:full":"Vandeweyerstraat 28 Schaarbeek/schaerbeek Bruxelles-Capitale 1030",
    "addr:housenumber":"28",
    "addr:postcode":"1030",
    "addr:street":"Vandeweyerstraat",
    "iso:country":"BE",
    "sg:address":"Vandeweyerstraat 28",
    "sg:city":"Schaarbeek/schaerbeek",
    "sg:orig_category":"Artiesten and kunstenaars",
    "sg:phone":"+32 2 242 28 87",
    "sg:postcode":"1030",
    "sg:province":"Bruxelles-Capitale",
    "wof:name":"Philibert Delecluse",
    "wof:placetype":"venue"
},
  "geometry": {"coordinates":[4.3682379723,50.8640518188],"type":"Point"}
}