{
  "type": "Feature",
  "properties": {
    "addr:full":"Hageputstraat 2a Houthulst (merkem) West-Vlaanderen 8650",
    "addr:housenumber":"2a",
    "addr:postcode":"8650",
    "addr:street":"Hageputstraat",
    "iso:country":"BE",
    "sg:address":"Hageputstraat 2a",
    "sg:city":"Houthulst (merkem)",
    "sg:classifiers":[
        {
            "category":"Home & Garden",
            "subcategory":"Kitchen Supply",
            "type":"Retail Goods"
        }
    ],
    "sg:phone":"+32 51 54 55 14",
    "sg:postcode":"8650",
    "sg:province":"West-Vlaanderen",
    "sg:tags":[
        "installation"
    ],
    "wof:name":"Crea Design Bvba",
    "wof:placetype":"venue"
},
  "geometry": {"coordinates":[2.9509439468,50.9778862],"type":"Point"}
}