{
  "type": "Feature",
  "properties": {
    "addr:full":"Vlaanderenstraat 8 Destelbergen Oost-Vlaanderen 9070",
    "addr:housenumber":"8",
    "addr:postcode":"9070",
    "addr:street":"Vlaanderenstraat",
    "iso:country":"BE",
    "sg:address":"Vlaanderenstraat 8",
    "sg:city":"Destelbergen",
    "sg:classifiers":[
        {
            "category":"Shopping",
            "type":"Retail Goods"
        }
    ],
    "sg:phone":"+32 9 228 42 46",
    "sg:postcode":"9070",
    "sg:province":"Oost-Vlaanderen",
    "sg:tags":[
        "product",
        "cleaning",
        "maintenance"
    ],
    "wof:name":"H & H",
    "wof:placetype":"venue"
},
  "geometry": {"coordinates":[3.7673499584,51.0548248291],"type":"Point"}
}