{
  "type": "Feature",
  "properties": {
    "addr:full":"Bergense Steenweg 54 Anderlecht/anderlecht Bruxelles-Capitale 1070",
    "addr:housenumber":"54",
    "addr:postcode":"1070",
    "addr:street":"Bergense Steenweg",
    "iso:country":"BE",
    "sg:address":"Bergense Steenweg 54",
    "sg:city":"Anderlecht/anderlecht",
    "sg:orig_category":"HUISBRANDOLIE Onderdelen and accessoires voor auto's",
    "sg:phone":"+32 2 521 01 76",
    "sg:postcode":"1070",
    "sg:province":"Bruxelles-Capitale",
    "wof:name":"Seddik Batteries Discount",
    "wof:placetype":"venue"
},
  "geometry": {"coordinates":[4.3359189034,50.843963623],"type":"Point"}
}