{
  "type": "Feature",
  "properties": {
    "addr:full":"Putstraat 13 Tongeren Limburg 3700",
    "addr:housenumber":"13",
    "addr:postcode":"3700",
    "addr:street":"Putstraat",
    "iso:country":"BE",
    "sg:address":"Putstraat 13",
    "sg:city":"Tongeren",
    "sg:classifiers":[
        {
            "category":"Insurance",
            "subcategory":"Insurance Agent",
            "type":"Services"
        }
    ],
    "sg:phone":"+32 12 24 18 10",
    "sg:postcode":"3700",
    "sg:province":"Limburg",
    "sg:tags":[
        "broker"
    ],
    "wof:name":"Zakenkantoor David S",
    "wof:placetype":"venue"
},
  "geometry": {"coordinates":[5.462211132,50.7791938782],"type":"Point"}
}