{
  "type": "Feature",
  "properties": {
    "iso:country":"BE",
    "sg:address":"Grevensmolenweg 167",
    "sg:city":"Sint-truiden",
    "sg:orig_category":"Drogisterijen",
    "sg:phone":"+32 11 68 12 45",
    "sg:postcode":"3800",
    "sg:province":"Limburg",
    "wof:name":"Michel Hermans",
    "wof:placetype":"venue"
},
  "geometry": {"coordinates":[5.168656826,50.8272399902],"type":"Point"}
}