{
  "type": "Feature",
  "properties": {
    "addr:full":"Rue Emile Vandervelde 47 Charleroi (roux) Hainaut 6044",
    "addr:housenumber":"47;6044",
    "addr:street":"Rue Emile Vandervelde",
    "iso:country":"BE",
    "sg:address":"Rue Emile Vandervelde 47",
    "sg:city":"Charleroi (roux)",
    "sg:classifiers":[
        {
            "category":"Building & Trades",
            "subcategory":"Construction",
            "type":"Services"
        }
    ],
    "sg:phone":"+32 71 21 95 27",
    "sg:postcode":"6044",
    "sg:province":"Hainaut",
    "sg:tags":[
        "stucco",
        "contractor"
    ],
    "wof:name":"Marcolini Sc",
    "wof:placetype":"venue"
},
  "geometry": {"coordinates":[4.3728718758,50.4386711121],"type":"Point"}
}