{
  "type": "Feature",
  "properties": {
    "iso:country":"BE",
    "sg:address":"Hogerheistraat 130",
    "sg:city":"Kapelle-op-den-bos",
    "sg:classifiers":[
        {
            "category":"Coffee & Tea",
            "type":"Food & Drink"
        }
    ],
    "sg:phone":"+32 15 71 40 30",
    "sg:postcode":"1880",
    "sg:province":"Vlaams-Brabant",
    "sg:tags":[
        "truffle",
        "chocolate"
    ],
    "wof:name":"Meroso Foods Nv",
    "wof:placetype":"venue"
},
  "geometry": {"coordinates":[4.3472189903,51.0030593872],"type":"Point"}
}