{
  "type": "Feature",
  "properties": {
    "addr:full":"Everselstraat 34a Beringen Limburg 3580",
    "addr:housenumber":"34a",
    "addr:postcode":"3580",
    "addr:street":"Everselstraat",
    "iso:country":"BE",
    "sg:address":"Everselstraat 34a",
    "sg:city":"Beringen",
    "sg:classifiers":[
        {
            "category":"Building & Trades",
            "subcategory":"Construction",
            "type":"Services"
        }
    ],
    "sg:phone":"+32 11 42 28 14",
    "sg:postcode":"3580",
    "sg:province":"Limburg",
    "sg:tags":[
        "glazier"
    ],
    "wof:name":"Tripo Glaswerken Bvba",
    "wof:placetype":"venue"
},
  "geometry": {"coordinates":[5.2294859886,51.0418624878],"type":"Point"}
}