{
  "type": "Feature",
  "properties": {
    "addr:full":"Jabekestraat 96-100 Wetteren Oost-Vlaanderen 9230",
    "addr:postcode":"96-100;9230",
    "addr:street":"Jabekestraat",
    "iso:country":"BE",
    "sg:address":"Jabekestraat 96-100",
    "sg:city":"Wetteren",
    "sg:orig_category":"P\u00e9pini\u00e9ristes",
    "sg:phone":"+32 9 369 58 28",
    "sg:postcode":"9230",
    "sg:province":"Oost-Vlaanderen",
    "wof:name":"Boomkwekerij Gebr De Winter",
    "wof:placetype":"venue"
},
  "geometry": {"coordinates":[3.9196910858,51.0148963928],"type":"Point"}
}