{
  "type": "Feature",
  "properties": {
    "iso:country":"BE",
    "sg:address":"Groenestraat 6",
    "sg:city":"Alveringem",
    "sg:orig_category":"Location d'appareils audio-visuels",
    "sg:phone":"+32 58 29 91 66",
    "sg:postcode":"8691",
    "sg:province":"West-Vlaanderen",
    "wof:name":"Fa. Uilenspiegel",
    "wof:placetype":"venue"
},
  "geometry": {"coordinates":[2.6652519703,50.9701004028],"type":"Point"}
}