{
  "type": "Feature",
  "properties": {
    "addr:full":"Aartshertoginnestraat 60 Oostende West-Vlaanderen 8400",
    "addr:housenumber":"60",
    "addr:postcode":"8400",
    "addr:street":"Aartshertoginnestraat",
    "iso:country":"BE",
    "sg:address":"Aartshertoginnestraat 60",
    "sg:city":"Oostende",
    "sg:orig_category":"Verplichte sociale verzekeringen",
    "sg:phone":"+32 59 70 46 39",
    "sg:postcode":"8400",
    "sg:province":"West-Vlaanderen",
    "wof:name":"Onafh. Ziekenfonds",
    "wof:placetype":"venue"
},
  "geometry": {"coordinates":[2.9184799194,51.2276115417],"type":"Point"}
}