{
  "type": "Feature",
  "properties": {
    "addr:full":"Rue Ernest Salu 86 Bruxelles Bruxelles-Capitale 1020",
    "addr:housenumber":"86",
    "addr:postcode":"1020",
    "addr:street":"Rue Ernest Salu",
    "iso:country":"BE",
    "sg:address":"Rue Ernest Salu 86",
    "sg:city":"Bruxelles",
    "sg:classifiers":[
        {
            "category":"Banks & Credit Unions",
            "subcategory":"Investment Brokerage",
            "type":"Services"
        }
    ],
    "sg:phone":"+32 2 478 68 92",
    "sg:postcode":"1020",
    "sg:province":"Bruxelles-Capitale",
    "sg:tags":[
        "auditor"
    ],
    "wof:name":"Serckx A",
    "wof:placetype":"venue"
},
  "geometry": {"coordinates":[4.3387308121,50.887134552],"type":"Point"}
}