{
  "type": "Feature",
  "properties": {
    "addr:full":"Rue De Spy 45 Floreffe (soye) Namur 5150",
    "addr:housenumber":"45",
    "addr:postcode":"5150",
    "addr:street":"Rue De Spy",
    "iso:country":"BE",
    "sg:address":"Rue De Spy 45",
    "sg:city":"Floreffe (soye)",
    "sg:classifiers":[
        {
            "category":"Arts & Performance",
            "subcategory":"Music",
            "type":"Entertainment"
        }
    ],
    "sg:phone":"+32 81 74 28 90",
    "sg:postcode":"5150",
    "sg:province":"Namur",
    "sg:tags":[
        "disc-jockeys"
    ],
    "wof:name":"One O One Production",
    "wof:placetype":"venue"
},
  "geometry": {"coordinates":[4.7269492149,50.4615898132],"type":"Point"}
}