{
  "type": "Feature",
  "properties": {
    "addr:full":"Rue Haut-vin\u00c2ve 11 Ans Li\u00e8ge 4432",
    "addr:housenumber":"11",
    "addr:postcode":"4432",
    "addr:street":"Rue Haut-Vina\u0302Ve",
    "iso:country":"BE",
    "sg:address":"Rue Haut-vin\u00c2ve 11",
    "sg:city":"Ans",
    "sg:orig_category":"Dakwerken",
    "sg:phone":"+32 4 257 48 30",
    "sg:postcode":"4432",
    "sg:province":"Li\u00e8ge",
    "wof:name":"Jean-luc Brulmans",
    "wof:placetype":"venue"
},
  "geometry": {"coordinates":[5.4791002274,50.7038192749],"type":"Point"}
}