{
  "type": "Feature",
  "properties": {
    "iso:country":"BE",
    "sg:address":"Maastrichtersteenweg 28",
    "sg:city":"Maaseik",
    "sg:classifiers":[
        {
            "category":"Home & Garden",
            "subcategory":"Carpets & Floor Coverings",
            "type":"Retail Goods"
        }
    ],
    "sg:phone":"+32 89 56 01 80",
    "sg:postcode":"3680",
    "sg:province":"Limburg",
    "sg:tags":[
        "parquet"
    ],
    "wof:name":"Houthandel Lbm Nv",
    "wof:placetype":"venue"
},
  "geometry": {"coordinates":[5.7783241272,51.094417572],"type":"Point"}
}