{
  "type": "Feature",
  "properties": {
    "addr:full":"Kuringersteenweg 510 Hasselt Limburg 3500",
    "addr:housenumber":"510",
    "addr:postcode":"3500",
    "addr:street":"Kuringersteenweg",
    "iso:country":"BE",
    "sg:address":"Kuringersteenweg 510",
    "sg:city":"Hasselt",
    "sg:classifiers":[
        {
            "category":"Shopping",
            "subcategory":"Crafts & Fabrics",
            "type":"Retail Goods"
        }
    ],
    "sg:phone":"+32 11 25 20 25",
    "sg:postcode":"3500",
    "sg:province":"Limburg",
    "sg:tags":[
        "paints",
        "varnish",
        "-",
        "lacquers",
        "enamel"
    ],
    "wof:name":"Swysen - Schepers Nv",
    "wof:placetype":"venue"
},
  "geometry": {"coordinates":[5.3112659454,50.9367523193],"type":"Point"}
}