{
  "type": "Feature",
  "properties": {
    "iso:country":"BE",
    "sg:address":"Avenue Brillat-savarin 25",
    "sg:city":"Elsene/ixelles",
    "sg:orig_category":"Fournitures de bureau. Journaux. Librairies. Tabac",
    "sg:phone":"+32 2 648 78 76",
    "sg:postcode":"1050",
    "sg:province":"Bruxelles-Capitale",
    "wof:name":"Jacques Van Houtte",
    "wof:placetype":"venue"
},
  "geometry": {"coordinates":[4.386841774,50.8170166016],"type":"Point"}
}