{
  "type": "Feature",
  "properties": {
    "iso:country":"BE",
    "sg:address":"Postbaan 117b",
    "sg:city":"Diest (schaffen)",
    "sg:classifiers":[
        {
            "category":"Health Services",
            "subcategory":"Doctor",
            "type":"Services"
        }
    ],
    "sg:phone":"+32 13 31 43 38",
    "sg:postcode":"3290",
    "sg:province":"Vlaams-Brabant",
    "sg:tags":[
        "medicinephysicians",
        "surgeon"
    ],
    "wof:name":"Coolen Luc",
    "wof:placetype":"venue"
},
  "geometry": {"coordinates":[5.0898151398,50.9978981018],"type":"Point"}
}