{
  "type": "Feature",
  "properties": {
    "addr:full":"Stadsetstr 17 Olen Antwerpen 2250",
    "addr:housenumber":"17",
    "addr:postcode":"2250",
    "addr:street":"Stadsetstr",
    "iso:country":"BE",
    "sg:address":"Stadsetstr 17",
    "sg:city":"Olen",
    "sg:classifiers":[
        {
            "category":"Autos & Motor Vehicles",
            "subcategory":"Automobile Sales",
            "type":"Retail Goods"
        }
    ],
    "sg:phone":"+32 14 25 82 85",
    "sg:postcode":"2250",
    "sg:province":"Antwerpen",
    "sg:tags":[
        "equipment",
        "transport"
    ],
    "wof:name":"Pacauto Nv",
    "wof:placetype":"venue"
},
  "geometry": {"coordinates":[4.7798848152,51.1661109924],"type":"Point"}
}