{
  "type": "Feature",
  "properties": {
    "addr:full":"Rozendalstraat 11 Tervuren Vlaams-Brabant 3080",
    "addr:housenumber":"11",
    "addr:postcode":"3080",
    "addr:street":"Rozendalstraat",
    "iso:country":"BE",
    "sg:address":"Rozendalstraat 11",
    "sg:city":"Tervuren",
    "sg:orig_category":"Installation de menuiserie en bois and plastique",
    "sg:phone":"+32 2 767 74 97",
    "sg:postcode":"3080",
    "sg:province":"Vlaams-Brabant",
    "wof:name":"Francis Labro",
    "wof:placetype":"venue"
},
  "geometry": {"coordinates":[4.5121212006,50.8218574524],"type":"Point"}
}