{
  "type": "Feature",
  "properties": {
    "addr:full":"Kasteelstraat 67 Asse Vlaams-Brabant 1730",
    "addr:housenumber":"67",
    "addr:postcode":"1730",
    "addr:street":"Kasteelstraat",
    "iso:country":"BE",
    "sg:address":"Kasteelstraat 67",
    "sg:city":"Asse",
    "sg:orig_category":"Epiceries",
    "sg:phone":"+32 2 452 54 95",
    "sg:postcode":"1730",
    "sg:province":"Vlaams-Brabant",
    "wof:name":"Gilbert Leon",
    "wof:placetype":"venue"
},
  "geometry": {"coordinates":[4.2240991592,50.9333534241],"type":"Point"}
}