{
  "type": "Feature",
  "properties": {
    "addr:full":"Waregemseweg 35bb Wortegem-petegem Oost-Vlaanderen 9790",
    "addr:housenumber":"35bb",
    "addr:postcode":"9790",
    "addr:street":"Waregemseweg",
    "iso:country":"BE",
    "sg:address":"Waregemseweg 35bb",
    "sg:city":"Wortegem-petegem",
    "sg:orig_category":"Openbare veiligheid",
    "sg:phone":"+32 56 68 70 70",
    "sg:postcode":"9790",
    "sg:province":"Oost-Vlaanderen",
    "wof:name":"Federale Politie",
    "wof:placetype":"venue"
},
  "geometry": {"coordinates":[3.5039680004,50.8547935486],"type":"Point"}
}