{
  "type": "Feature",
  "properties": {
    "iso:country":"BE",
    "sg:address":"Schoolstraat 89",
    "sg:city":"Buggenhout",
    "sg:orig_category":"Charpentes and couvertures",
    "sg:phone":"+32 52 33 09 31",
    "sg:postcode":"9255",
    "sg:province":"Oost-Vlaanderen",
    "wof:name":"Van Der Plas Ludo",
    "wof:placetype":"venue"
},
  "geometry": {"coordinates":[4.1945462227,51.0119628906],"type":"Point"}
}