{
  "type": "Feature",
  "properties": {
    "addr:full":"Metropoolstraat 33 Schoten Antwerpen 2900",
    "addr:housenumber":"33",
    "addr:postcode":"2900",
    "addr:street":"Metropoolstraat",
    "iso:country":"BE",
    "sg:address":"Metropoolstraat 33",
    "sg:city":"Schoten",
    "sg:classifiers":[
        {
            "category":"Banks & Credit Unions",
            "subcategory":"Investment Brokerage",
            "type":"Services"
        }
    ],
    "sg:phone":"+32 3 647 14 00",
    "sg:postcode":"2900",
    "sg:province":"Antwerpen",
    "sg:tags":[
        "roofing",
        "sealing",
        "roll",
        "roof",
        "bitumen"
    ],
    "wof:name":"De Boer Nv",
    "wof:placetype":"venue"
},
  "geometry": {"coordinates":[4.4643511772,51.2396011353],"type":"Point"}
}