{
  "type": "Feature",
  "properties": {
    "addr:full":"Place Du Samedi 6 Bruxelles Bruxelles-Capitale 1000",
    "addr:housenumber":"6",
    "addr:postcode":"1000",
    "addr:street":"Place Du Samedi",
    "iso:country":"BE",
    "sg:address":"Place Du Samedi 6",
    "sg:city":"Bruxelles",
    "sg:classifiers":[
        {
            "category":"Banks & Credit Unions",
            "subcategory":"Investment Brokerage",
            "type":"Services"
        }
    ],
    "sg:phone":"+32 2 227 00 90",
    "sg:postcode":"1000",
    "sg:province":"Bruxelles-Capitale",
    "sg:tags":[
        "printing",
        "-"
    ],
    "wof:name":"Valan Sprl",
    "wof:placetype":"venue"
},
  "geometry": {"coordinates":[4.3498311043,50.8514976501],"type":"Point"}
}