{
  "type": "Feature",
  "properties": {
    "addr:full":"2 Nieuwstraat Oostrozebeke West-Vlaanderen 8780",
    "addr:postcode":"8780",
    "addr:street":"Nieuwstraat",
    "iso:country":"BE",
    "sg:address":"2 Nieuwstraat",
    "sg:city":"Oostrozebeke",
    "sg:classifiers":[
        {
            "category":"Manufacturing",
            "subcategory":"Textiles",
            "type":"Manufacturing & Wholesale Goods"
        }
    ],
    "sg:phone":"+32 56 66 61 73",
    "sg:postcode":"8780",
    "sg:province":"West-Vlaanderen",
    "sg:tags":[
        "linen",
        "clothing",
        "fabric"
    ],
    "wof:name":"Texpol Bvba",
    "wof:placetype":"venue"
},
  "geometry": {"coordinates":[3.3239700794,50.9197158813],"type":"Point"}
}