{
  "type": "Feature",
  "properties": {
    "addr:full":"Hoge Akker 39 Kontich Antwerpen 2550",
    "addr:housenumber":"39",
    "addr:postcode":"2550",
    "addr:street":"Hoge Akker",
    "iso:country":"BE",
    "sg:address":"Hoge Akker 39",
    "sg:city":"Kontich",
    "sg:orig_category":"Fietsen",
    "sg:phone":"+32 3 458 40 59",
    "sg:postcode":"2550",
    "sg:province":"Antwerpen",
    "wof:name":"Huis Vercammen",
    "wof:placetype":"venue"
},
  "geometry": {"coordinates":[4.4769802094,51.1275482178],"type":"Point"}
}