{
  "type": "Feature",
  "properties": {
    "iso:country":"BE",
    "sg:address":"Avenue Du Roi 210-212",
    "sg:city":"Bruxelles (forest)",
    "sg:orig_category":"Non-Classified Establishments",
    "sg:phone":"+32 2 538 76 12",
    "sg:postcode":"1190",
    "sg:province":"Bruxelles-Capitale",
    "wof:name":"Sissi K.o.",
    "wof:placetype":"venue"
},
  "geometry": {"coordinates":[4.3350992203,50.8250961304],"type":"Point"}
}