{
  "type": "Feature",
  "properties": {
    "iso:country":"BE",
    "sg:address":"Keperenbergstraat 37c",
    "sg:city":"Dilbeek",
    "sg:orig_category":"Sportclubs",
    "sg:phone":"+32 2 569 72 13",
    "sg:postcode":"1701",
    "sg:province":"Vlaams-Brabant",
    "wof:name":"Tennis S D I",
    "wof:placetype":"venue"
},
  "geometry": {"coordinates":[4.2489171028,50.8360671997],"type":"Point"}
}