{
  "type": "Feature",
  "properties": {
    "iso:country":"BE",
    "sg:address":"Albert Vanderkelenstraat 5",
    "sg:city":"Lennik",
    "sg:orig_category":"Brood, gebak and snoepgoed",
    "sg:phone":"+32 2 532 44 54",
    "sg:postcode":"1750",
    "sg:province":"Vlaams-Brabant",
    "wof:name":"Geert Van Snick",
    "wof:placetype":"venue"
},
  "geometry": {"coordinates":[4.155424118,50.80651474],"type":"Point"}
}