{
  "type": "Feature",
  "properties": {
    "iso:country":"BE",
    "sg:address":"Frankrijklei 8b127",
    "sg:city":"Antwerpen",
    "sg:orig_category":"Opinieonderzoekbureaus",
    "sg:phone":"+32 3 233 55 22",
    "sg:postcode":"2000",
    "sg:province":"Antwerpen",
    "wof:name":"Communitel",
    "wof:placetype":"venue"
},
  "geometry": {"coordinates":[4.4154119492,51.2192802429],"type":"Point"}
}