{
  "type": "Feature",
  "properties": {
    "addr:full":"Dorpstraat 48a Aalst (meldert) Oost-Vlaanderen 9310",
    "addr:housenumber":"48a",
    "addr:postcode":"9310",
    "addr:street":"Dorpstraat",
    "iso:country":"BE",
    "sg:address":"Dorpstraat 48a",
    "sg:city":"Aalst (meldert)",
    "sg:classifiers":[
        {
            "category":"Building & Trades",
            "subcategory":"Electrical",
            "type":"Services"
        }
    ],
    "sg:phone":"+32 52 35 67 30",
    "sg:postcode":"9310",
    "sg:province":"Oost-Vlaanderen",
    "sg:tags":[
        "heating"
    ],
    "wof:name":"Beeckman C",
    "wof:placetype":"venue"
},
  "geometry": {"coordinates":[4.098400116,50.9477767944],"type":"Point"}
}