{
  "type": "Feature",
  "properties": {
    "addr:full":"Kelfsstraat 81 Haacht Vlaams-Brabant 3150",
    "addr:housenumber":"81",
    "addr:postcode":"3150",
    "addr:street":"Kelfsstraat",
    "iso:country":"BE",
    "sg:address":"Kelfsstraat 81",
    "sg:city":"Haacht",
    "sg:orig_category":"V\u00e9hicules automobiles",
    "sg:phone":"+32 16 60 32 82",
    "sg:postcode":"3150",
    "sg:province":"Vlaams-Brabant",
    "wof:name":"A. Labro",
    "wof:placetype":"venue"
},
  "geometry": {"coordinates":[4.6816391945,50.9493255615],"type":"Point"}
}