{
  "type": "Feature",
  "properties": {
    "addr:full":"Van Eycklaan 6 Moorslede West-Vlaanderen 8890",
    "addr:housenumber":"6",
    "addr:postcode":"8890",
    "addr:street":"Van Eycklaan",
    "iso:country":"BE",
    "sg:address":"Van Eycklaan 6",
    "sg:city":"Moorslede",
    "sg:classifiers":[
        {
            "category":"Professional",
            "subcategory":"Accounting & Tax Preparation",
            "type":"Services"
        }
    ],
    "sg:phone":"+32 51 77 89 18",
    "sg:postcode":"8890",
    "sg:province":"West-Vlaanderen",
    "sg:tags":[
        "bookkeeper"
    ],
    "wof:name":"Foulon V",
    "wof:placetype":"venue"
},
  "geometry": {"coordinates":[3.0634250641,50.8853645325],"type":"Point"}
}