{
  "type": "Feature",
  "properties": {
    "iso:country":"BE",
    "sg:address":"Schlierbach 9b",
    "sg:city":"Sankt Vith (lommersweiler)",
    "sg:classifiers":[
        {
            "category":"Professional",
            "subcategory":"Secretarial Services",
            "type":"Services"
        }
    ],
    "sg:phone":"+32 80 22 96 82",
    "sg:postcode":"4783",
    "sg:province":"Li\u00e8ge",
    "sg:tags":[
        "-",
        "wordprocessing"
    ],
    "wof:name":"Scripto",
    "wof:placetype":"venue"
},
  "geometry": {"coordinates":[6.1624388695,50.2378196716],"type":"Point"}
}