{
  "type": "Feature",
  "properties": {
    "addr:full":"Breestraeten 253 Merchtem Vlaams-Brabant 1785",
    "addr:housenumber":"253",
    "addr:postcode":"1785",
    "addr:street":"Breestraeten",
    "iso:country":"BE",
    "sg:address":"Breestraeten 253",
    "sg:city":"Merchtem",
    "sg:orig_category":"Producteurs de l\u00e9gumes",
    "sg:phone":"+32 52 37 11 20",
    "sg:postcode":"1785",
    "sg:province":"Vlaams-Brabant",
    "wof:name":"Leopold De Neve",
    "wof:placetype":"venue"
},
  "geometry": {"coordinates":[4.267220974,50.9749984741],"type":"Point"}
}