{
  "type": "Feature",
  "properties": {
    "addr:full":"Place Joseph Wauters 11 Andenne Namur 5300",
    "addr:housenumber":"11",
    "addr:postcode":"5300",
    "addr:street":"Place Joseph Wauters",
    "iso:country":"BE",
    "sg:address":"Place Joseph Wauters 11",
    "sg:city":"Andenne",
    "sg:classifiers":[
        {
            "category":"Fast Food",
            "type":"Food & Drink"
        }
    ],
    "sg:phone":"+32 85 82 67 00",
    "sg:postcode":"5300",
    "sg:province":"Namur",
    "sg:tags":[
        "meeneem",
        "restaurant"
    ],
    "wof:name":"Au P\u00b4tit Creux",
    "wof:placetype":"venue"
},
  "geometry": {"coordinates":[5.0920000076,50.4906387329],"type":"Point"}
}