{
  "type": "Feature",
  "properties": {
    "addr:full":"Route De Cortil-wodon 111 Eghezee Namur 5310",
    "addr:housenumber":"111",
    "addr:postcode":"5310",
    "addr:street":"Route De Cortil-Wodon;Namur",
    "iso:country":"BE",
    "sg:address":"Route De Cortil-wodon 111",
    "sg:city":"Eghezee",
    "sg:orig_category":"Dakwerken",
    "sg:phone":"+32 81 51 20 80",
    "sg:postcode":"5310",
    "sg:province":"Namur",
    "wof:name":"Marcel Robert",
    "wof:placetype":"venue"
},
  "geometry": {"coordinates":[4.9215230942,50.5654182434],"type":"Point"}
}