{
  "type": "Feature",
  "properties": {
    "iso:country":"BE",
    "sg:address":"Guilleminlaan 74",
    "sg:city":"Geraardsbergen",
    "sg:orig_category":"Herstellingen and onderhoud van auto's",
    "sg:phone":"+32 54 41 23 82",
    "sg:postcode":"9500",
    "sg:province":"Oost-Vlaanderen",
    "wof:name":"Nico De Motte",
    "wof:placetype":"venue"
},
  "geometry": {"coordinates":[3.8908450603,50.7698135376],"type":"Point"}
}