{
  "type": "Feature",
  "properties": {
    "addr:full":"Mercatorstraat 149 Sint-niklaas Oost-Vlaanderen 9100",
    "addr:housenumber":"149",
    "addr:postcode":"9100",
    "addr:street":"Mercatorstraat",
    "iso:country":"BE",
    "sg:address":"Mercatorstraat 149",
    "sg:city":"Sint-niklaas",
    "sg:classifiers":[
        {
            "category":"Insurance",
            "subcategory":"Insurance Agent",
            "type":"Services"
        }
    ],
    "sg:phone":"+32 3 776 54 34",
    "sg:postcode":"9100",
    "sg:province":"Oost-Vlaanderen",
    "sg:tags":[
        "broker"
    ],
    "wof:name":"Penneman Groep Bvba",
    "wof:placetype":"venue"
},
  "geometry": {"coordinates":[4.1507411003,51.1684646606],"type":"Point"}
}