{
  "type": "Feature",
  "properties": {
    "iso:country":"BE",
    "sg:address":"Kapellemarkt 8",
    "sg:city":"Brussel/bruxelles",
    "sg:classifiers":[
        {
            "category":"Communications",
            "subcategory":"Television Station",
            "type":"Services"
        }
    ],
    "sg:phone":"+32 2 502 30 75",
    "sg:postcode":"1000",
    "sg:province":"Bruxelles-Capitale",
    "sg:tags":[
        "video",
        "audio",
        "verhuur"
    ],
    "wof:name":"Monev",
    "wof:placetype":"venue"
},
  "geometry": {"coordinates":[4.3506169319,50.8410873413],"type":"Point"}
}