{
  "type": "Feature",
  "properties": {
    "addr:full":"Cataloniestraat 6 Gent Oost-Vlaanderen 9000",
    "addr:housenumber":"6",
    "addr:postcode":"9000",
    "addr:street":"Cataloniestraat;Oost-Vlaanderen",
    "iso:country":"BE",
    "sg:address":"Cataloniestraat 6",
    "sg:city":"Gent",
    "sg:orig_category":"Diverse kredietdiensten",
    "sg:postcode":"9000",
    "sg:province":"Oost-Vlaanderen",
    "wof:name":"Bancontact-mister Cash",
    "wof:placetype":"venue"
},
  "geometry": {"coordinates":[3.7227659225,51.0536193848],"type":"Point"}
}