{
  "type": "Feature",
  "properties": {
    "addr:full":"Ossebilkstraat 86 Zedelgem West-Vlaanderen 8211",
    "addr:housenumber":"86",
    "addr:postcode":"8211",
    "addr:street":"Ossebilkstraat",
    "iso:country":"BE",
    "sg:address":"Ossebilkstraat 86",
    "sg:city":"Zedelgem",
    "sg:orig_category":"Rundveehouders",
    "sg:phone":"+32 50 21 18 01",
    "sg:postcode":"8211",
    "sg:province":"West-Vlaanderen",
    "wof:name":"Martin Borra",
    "wof:placetype":"venue"
},
  "geometry": {"coordinates":[3.0889649391,51.1200408936],"type":"Point"}
}