{
  "type": "Feature",
  "properties": {
    "iso:country":"BE",
    "sg:address":"Pamelstraat-oost 412",
    "sg:city":"Ninove",
    "sg:classifiers":[
        {
            "category":"Food & Beverages",
            "subcategory":"Meat & Fish",
            "type":"Retail Goods"
        }
    ],
    "sg:phone":"+32 54 32 32 48",
    "sg:postcode":"9400",
    "sg:province":"Oost-Vlaanderen",
    "sg:tags":[
        "bacon",
        "ham"
    ],
    "wof:name":"Vleeswaren Primera Nv",
    "wof:placetype":"venue"
},
  "geometry": {"coordinates":[4.0377998352,50.8405952454],"type":"Point"}
}