{
  "type": "Feature",
  "properties": {
    "addr:full":"Quai L\u00e9opold Herten 14 Engis Li\u00e8ge 4480",
    "addr:housenumber":"14",
    "addr:postcode":"4480",
    "addr:street":"Quai Le\u0301Opold Herten",
    "iso:country":"BE",
    "sg:address":"Quai L\u00e9opold Herten 14",
    "sg:city":"Engis",
    "sg:classifiers":[
        {
            "category":"Home & Garden",
            "subcategory":"Home Furnishings",
            "type":"Retail Goods"
        }
    ],
    "sg:phone":"+32 4 275 23 22",
    "sg:postcode":"4480",
    "sg:province":"Li\u00e8ge",
    "sg:tags":[
        "wallpaper",
        "-"
    ],
    "wof:name":"Engis D\u00e9cor",
    "wof:placetype":"venue"
},
  "geometry": {"coordinates":[5.405298233,50.5816841125],"type":"Point"}
}