{
  "type": "Feature",
  "properties": {
    "iso:country":"BE",
    "sg:address":"Rue De Flandre 169",
    "sg:city":"Bruxelles",
    "sg:classifiers":[
        {
            "category":"Professional",
            "subcategory":"Printing & Photocopies",
            "type":"Services"
        }
    ],
    "sg:phone":"+32 2 218 68 00",
    "sg:postcode":"1000",
    "sg:province":"Bruxelles-Capitale",
    "sg:tags":[
        "digital"
    ],
    "wof:name":"I.p.m. Printing",
    "wof:placetype":"venue"
},
  "geometry": {"coordinates":[4.3430562019,50.8531150818],"type":"Point"}
}