{
  "type": "Feature",
  "properties": {
    "addr:full":"R. L'h\u00d4tel Des Monnaies 64 Sint-gillis/saint-gilles Bruxelles-Capitale 1060",
    "addr:housenumber":"64 sint-gillis",
    "addr:postcode":"1060",
    "iso:country":"BE",
    "sg:address":"R. L'h\u00d4tel Des Monnaies 64",
    "sg:city":"Sint-gillis/saint-gilles",
    "sg:orig_category":"Antiquit\u00e9s",
    "sg:phone":"+32 2 537 80 63",
    "sg:postcode":"1060",
    "sg:province":"Bruxelles-Capitale",
    "wof:name":"Maison Vanderslyen",
    "wof:placetype":"venue"
},
  "geometry": {"coordinates":[4.3486571312,50.8310432434],"type":"Point"}
}