{
  "type": "Feature",
  "properties": {
    "iso:country":"BE",
    "sg:address":"Chemin Des Feuill\u00c9es 14",
    "sg:city":"Frasnes-lez-anvaing",
    "sg:orig_category":"Pain, p\u00e2tisseries and confiseries",
    "sg:phone":"+32 69 86 60 68",
    "sg:postcode":"7911",
    "sg:province":"Hainaut",
    "wof:name":"Freddy Willocq",
    "wof:placetype":"venue"
},
  "geometry": {"coordinates":[3.6311070919,50.6481819153],"type":"Point"}
}