{
  "type": "Feature",
  "properties": {
    "iso:country":"BE",
    "sg:address":"All\u00c9e Des Platanes 16",
    "sg:city":"Vise",
    "sg:orig_category":"Banques and organismes de cr\u00e9dit",
    "sg:phone":"+32 4 379 32 91",
    "sg:postcode":"4600",
    "sg:province":"Li\u00e8ge",
    "wof:name":"Cr\u00c9dit Agricole",
    "wof:placetype":"venue"
},
  "geometry": {"coordinates":[5.7020230293,50.7415161133],"type":"Point"}
}