{
  "type": "Feature",
  "properties": {
    "addr:full":"Hannuitstraat 14b Gingelom (montenaken) Limburg 3890",
    "addr:housenumber":"14b",
    "addr:postcode":"3890",
    "addr:street":"Hannuitstraat",
    "iso:country":"BE",
    "sg:address":"Hannuitstraat 14b",
    "sg:city":"Gingelom (montenaken)",
    "sg:classifiers":[
        {
            "category":"Social Services",
            "subcategory":"Job Training",
            "type":"Services"
        }
    ],
    "sg:phone":"+32 477 23 19 64",
    "sg:postcode":"3890",
    "sg:province":"Limburg",
    "sg:tags":[
        "personnel"
    ],
    "wof:name":"N M B Consulting",
    "wof:placetype":"venue"
},
  "geometry": {"coordinates":[5.1271967888,50.7187614441],"type":"Point"}
}