{
  "type": "Feature",
  "properties": {
    "iso:country":"BE",
    "sg:address":"Mechelsesteenweg 376",
    "sg:city":"Willebroek (blaasveld)",
    "sg:classifiers":[
        {
            "category":"Retail",
            "subcategory":"Auto Repair",
            "type":"Services"
        }
    ],
    "sg:phone":"+32 3 886 25 86",
    "sg:postcode":"2830",
    "sg:province":"Antwerpen",
    "sg:tags":[
        "garage"
    ],
    "wof:name":"Termens M Cv",
    "wof:placetype":"venue"
},
  "geometry": {"coordinates":[4.3789539337,51.0472793579],"type":"Point"}
}