{
  "type": "Feature",
  "properties": {
    "addr:full":"Boulevard Leopold Ii 166 Bruxelles (molenbeek-saint-jean) Bruxelles-Capitale 1080",
    "addr:housenumber":"166",
    "addr:postcode":"1080",
    "addr:street":"Boulevard Leopold Ii",
    "iso:country":"BE",
    "sg:address":"Boulevard Leopold Ii 166",
    "sg:city":"Bruxelles (molenbeek-saint-jean)",
    "sg:classifiers":[
        {
            "category":"Professional",
            "subcategory":"Engineering",
            "type":"Services"
        }
    ],
    "sg:phone":"+32 2 414 20 22",
    "sg:postcode":"1080",
    "sg:province":"Bruxelles-Capitale",
    "sg:tags":[
        "-"
    ],
    "wof:name":"Tensen & Huon",
    "wof:placetype":"venue"
},
  "geometry": {"coordinates":[4.3364901543,50.8611946106],"type":"Point"}
}