{
  "type": "Feature",
  "properties": {
    "iso:country":"BE",
    "sg:address":"Zevenkaven 5",
    "sg:city":"Wevelgem",
    "sg:orig_category":"Architecten",
    "sg:phone":"+32 56 21 09 90",
    "sg:postcode":"8560",
    "sg:province":"West-Vlaanderen",
    "wof:name":"Jose Dedeurwaerder",
    "wof:placetype":"venue"
},
  "geometry": {"coordinates":[3.207034111,50.8468055725],"type":"Point"}
}