{
  "type": "Feature",
  "properties": {
    "addr:full":"Sint-truidersteenweg 172 Hasselt Limburg 3500",
    "addr:housenumber":"172",
    "addr:postcode":"3500",
    "addr:street":"Sint-Truidersteenweg",
    "iso:country":"BE",
    "sg:address":"Sint-truidersteenweg 172",
    "sg:city":"Hasselt",
    "sg:classifiers":[
        {
            "category":"Real Estate",
            "subcategory":"Architect",
            "type":"Services"
        }
    ],
    "sg:phone":"+32 11 23 53 31",
    "sg:postcode":"3500",
    "sg:province":"Limburg",
    "wof:name":"Berben J",
    "wof:placetype":"venue"
},
  "geometry": {"coordinates":[5.3311800957,50.9221687317],"type":"Point"}
}