{
  "type": "Feature",
  "properties": {
    "iso:country":"BE",
    "sg:address":"Voie Du Puits 13",
    "sg:city":"Oupeye",
    "sg:orig_category":"Enseignement maternel and primaire",
    "sg:phone":"+32 4 286 15 02",
    "sg:postcode":"4682",
    "sg:province":"Li\u00e8ge",
    "wof:name":"Ecole Fond. Communale",
    "wof:placetype":"venue"
},
  "geometry": {"coordinates":[5.6108169556,50.7372016907],"type":"Point"}
}