{
  "type": "Feature",
  "properties": {
    "addr:full":"Lijkveldestraat 134 Sint-gillis-waas Oost-Vlaanderen 9170",
    "addr:housenumber":"134",
    "addr:postcode":"sint-gillis-waas;9170",
    "addr:street":"Lijkveldestraat",
    "iso:country":"BE",
    "sg:address":"Lijkveldestraat 134",
    "sg:city":"Sint-gillis-waas",
    "sg:orig_category":"Sportclubs Sportterreinen and installaties behalve sportcentra",
    "sg:phone":"+32 3 789 27 74",
    "sg:postcode":"9170",
    "sg:province":"Oost-Vlaanderen",
    "wof:name":"F.c. Herleving St.pauwels",
    "wof:placetype":"venue"
},
  "geometry": {"coordinates":[4.0679020882,51.1856842041],"type":"Point"}
}