{
  "type": "Feature",
  "properties": {
    "addr:full":"Jan Baptist Davidstraat 2 Boom Antwerpen 2850",
    "addr:housenumber":"2",
    "addr:postcode":"2850",
    "addr:street":"Jan Baptist Davidstraat",
    "iso:country":"BE",
    "sg:address":"Jan Baptist Davidstraat 2",
    "sg:city":"Boom",
    "sg:orig_category":"Algemeen secundair onderwijs Technisch and beroeps secundair onderwijs",
    "sg:phone":"+32 3 888 05 24",
    "sg:postcode":"2850",
    "sg:province":"Antwerpen",
    "wof:name":"Koninklijk Atheneum",
    "wof:placetype":"venue"
},
  "geometry": {"coordinates":[4.3730149269,51.0958976746],"type":"Point"}
}