{
  "type": "Feature",
  "properties": {
    "iso:country":"BE",
    "sg:address":"Molenstraat 48",
    "sg:city":"Zonnebeke",
    "sg:orig_category":"Sportclubs",
    "sg:phone":"+32 51 77 76 52",
    "sg:postcode":"8980",
    "sg:province":"West-Vlaanderen",
    "wof:name":"W.c. De Gildevrienden",
    "wof:placetype":"venue"
},
  "geometry": {"coordinates":[3.0217859745,50.9027252197],"type":"Point"}
}