{
  "type": "Feature",
  "properties": {
    "addr:full":"Rue Du Centre 7 Anthisnes Li\u00e8ge 4160",
    "addr:housenumber":"7",
    "addr:postcode":"4160",
    "addr:street":"Rue Du Centre",
    "iso:country":"BE",
    "sg:address":"Rue Du Centre 7",
    "sg:city":"Anthisnes",
    "sg:classifiers":[
        {
            "category":"Manufacturing",
            "subcategory":"Tools & Machinery",
            "type":"Manufacturing & Wholesale Goods"
        }
    ],
    "sg:phone":"+32 4 383 62 63",
    "sg:postcode":"4160",
    "sg:province":"Li\u00e8ge",
    "sg:tags":[
        "-"
    ],
    "wof:name":"Stock Am\u00e9ricain",
    "wof:placetype":"venue"
},
  "geometry": {"coordinates":[5.5206418037,50.4803581238],"type":"Point"}
}