{
  "type": "Feature",
  "properties": {
    "iso:country":"BE",
    "sg:address":"Lekestraat 35",
    "sg:city":"Stekene",
    "sg:classifiers":[
        {
            "category":"Building & Trades",
            "subcategory":"Landscaping Services",
            "type":"Services"
        }
    ],
    "sg:phone":"+32 3 779 76 75",
    "sg:postcode":"9190",
    "sg:province":"Oost-Vlaanderen",
    "sg:tags":[
        "nurseryman"
    ],
    "wof:name":"Van Hecke A",
    "wof:placetype":"venue"
},
  "geometry": {"coordinates":[4.0132398605,51.2444953918],"type":"Point"}
}