{
  "type": "Feature",
  "properties": {
    "iso:country":"BE",
    "sg:address":"Pastorijstraat 78",
    "sg:city":"Tienen",
    "sg:orig_category":"Enseignement maternel and primaire",
    "sg:phone":"+32 16 81 83 88",
    "sg:postcode":"3300",
    "sg:province":"Vlaams-Brabant",
    "wof:name":"Stedelijke Basisschool",
    "wof:placetype":"venue"
},
  "geometry": {"coordinates":[4.9526200294,50.8025283813],"type":"Point"}
}