{
  "type": "Feature",
  "properties": {
    "addr:full":"Kerkdijk 23 Overpelt Limburg 3900",
    "addr:housenumber":"23",
    "addr:postcode":"3900",
    "addr:street":"Kerkdijk",
    "iso:country":"BE",
    "sg:address":"Kerkdijk 23",
    "sg:city":"Overpelt",
    "sg:classifiers":[
        {
            "category":"Health Services",
            "subcategory":"Health Practitioner",
            "type":"Services"
        }
    ],
    "sg:phone":"+32 11 64 20 95",
    "sg:postcode":"3900",
    "sg:province":"Limburg",
    "sg:tags":[
        "physiotherapist"
    ],
    "wof:name":"Cuyvers Rony",
    "wof:placetype":"venue"
},
  "geometry": {"coordinates":[5.430270195,51.2086372375],"type":"Point"}
}