{
  "type": "Feature",
  "properties": {
    "iso:country":"BE",
    "sg:address":"Frankrijklei 133",
    "sg:city":"Antwerpen",
    "sg:classifiers":[
        {
            "category":"Banks & Credit Unions",
            "subcategory":"Financial Services",
            "type":"Services"
        }
    ],
    "sg:phone":"+32 3 232 71 78",
    "sg:postcode":"2000",
    "sg:province":"Antwerpen",
    "sg:tags":[
        "financing"
    ],
    "wof:name":"Soficorp Nv",
    "wof:placetype":"venue"
},
  "geometry": {"coordinates":[4.4082608223,51.2111778259],"type":"Point"}
}