{
  "type": "Feature",
  "properties": {
    "iso:country":"BE",
    "sg:address":"Nieuwe Kaai 25",
    "sg:city":"Turnhout",
    "sg:classifiers":[
        {
            "category":"Wholesale",
            "subcategory":"Books, Periodicals, & Newspapers",
            "type":"Manufacturing & Wholesale Goods"
        }
    ],
    "sg:phone":"+32 14 44 89 89",
    "sg:postcode":"2300",
    "sg:province":"Antwerpen",
    "sg:tags":[
        "publisher"
    ],
    "wof:name":"Software Group International Nv",
    "wof:placetype":"venue"
},
  "geometry": {"coordinates":[4.9317178726,51.3258171082],"type":"Point"}
}