{
  "type": "Feature",
  "properties": {
    "iso:country":"BE",
    "sg:address":"Rue Frisles 33 Box 1",
    "sg:city":"Anh\u00e9e (bioul)",
    "sg:classifiers":[
        {
            "category":"Shopping",
            "subcategory":"Pets & Pet Supplies",
            "type":"Retail Goods"
        }
    ],
    "sg:phone":"+32 71 53 53 22",
    "sg:postcode":"5537",
    "sg:province":"Namur",
    "sg:tags":[
        "horseriding"
    ],
    "wof:name":"Le Pied \u00e0 L'etrier",
    "wof:placetype":"venue"
},
  "geometry": {"coordinates":[4.7903628349,50.3371772766],"type":"Point"}
}