{
  "type": "Feature",
  "properties": {
    "iso:country":"BE",
    "sg:address":"Hottonstraat 15",
    "sg:city":"Izegem",
    "sg:classifiers":[
        {
            "category":"Health Services",
            "subcategory":"Health Practitioner",
            "type":"Services"
        }
    ],
    "sg:phone":"+32 51 31 21 50",
    "sg:postcode":"8870",
    "sg:province":"West-Vlaanderen",
    "sg:tags":[
        "osteopath"
    ],
    "wof:name":"Keirsschieter Erwin",
    "wof:placetype":"venue"
},
  "geometry": {"coordinates":[3.1906859875,50.9209098816],"type":"Point"}
}