{
  "type": "Feature",
  "properties": {
    "addr:full":"Noordstraat 160 Maldegem Oost-Vlaanderen 9990",
    "addr:housenumber":"160",
    "addr:postcode":"9990",
    "addr:street":"Noordstraat",
    "iso:country":"BE",
    "sg:address":"Noordstraat 160",
    "sg:city":"Maldegem",
    "sg:classifiers":[
        {
            "category":"Professional",
            "subcategory":"Art Services",
            "type":"Services"
        }
    ],
    "sg:phone":"+32 50 70 06 75",
    "sg:postcode":"9990",
    "sg:province":"Oost-Vlaanderen",
    "sg:tags":[
        "graphic",
        "designer"
    ],
    "wof:name":"Piece Of Cake",
    "wof:placetype":"venue"
},
  "geometry": {"coordinates":[3.4467489719,51.2155990601],"type":"Point"}
}