{
  "type": "Feature",
  "properties": {
    "iso:country":"BE",
    "sg:address":"Steenweg 51",
    "sg:city":"Brakel",
    "sg:orig_category":"Enseignement maternel and primaire",
    "sg:phone":"+32 55 42 30 94",
    "sg:postcode":"9661",
    "sg:province":"Oost-Vlaanderen",
    "wof:name":"Gemeentel. Lagere School",
    "wof:placetype":"venue"
},
  "geometry": {"coordinates":[3.8028891087,50.7795143127],"type":"Point"}
}