{
  "type": "Feature",
  "properties": {
    "iso:country":"BE",
    "sg:address":"Rue Du Coll\u00e8ge 16",
    "sg:city":"Ch\u00e2telet",
    "sg:classifiers":[
        {
            "category":"Education",
            "subcategory":"School",
            "type":"Public Place"
        }
    ],
    "sg:phone":"+32 71 38 05 69",
    "sg:postcode":"6200",
    "sg:province":"Hainaut",
    "sg:tags":[
        "primary"
    ],
    "wof:name":"Ath\u00e9n\u00e9e Royal Ren\u00e9 Magritte",
    "wof:placetype":"venue"
},
  "geometry": {"coordinates":[4.524409771,50.4053611755],"type":"Point"}
}