{
  "type": "Feature",
  "properties": {
    "iso:country":"BE",
    "sg:address":"Avenue Victor Tahon 6",
    "sg:city":"Bruxelles (auderghem)",
    "sg:classifiers":[
        {
            "category":"Real Estate",
            "subcategory":"Surveying",
            "type":"Services"
        }
    ],
    "sg:phone":"+32 2 675 07 04",
    "sg:postcode":"1160",
    "sg:province":"Bruxelles-Capitale",
    "sg:tags":[
        "surveyor",
        "land"
    ],
    "wof:name":"Husson T",
    "wof:placetype":"venue"
},
  "geometry": {"coordinates":[4.4399251938,50.8177528381],"type":"Point"}
}