{
  "type": "Feature",
  "properties": {
    "addr:full":"Pompelhoekstraat 13 Hamme Oost-Vlaanderen 9220",
    "addr:housenumber":"13",
    "addr:postcode":"9220",
    "addr:street":"Pompelhoekstraat",
    "iso:country":"BE",
    "sg:address":"Pompelhoekstraat 13",
    "sg:city":"Hamme",
    "sg:orig_category":"Loodgieterij, verwarming and sanitaire installaties",
    "sg:phone":"+32 52 47 06 80",
    "sg:postcode":"9220",
    "sg:province":"Oost-Vlaanderen",
    "wof:name":"Willy Vincke",
    "wof:placetype":"venue"
},
  "geometry": {"coordinates":[4.1522197723,51.0711517334],"type":"Point"}
}