{
  "type": "Feature",
  "properties": {
    "addr:full":"Parc Industriel Naninne 51 Namur Namur 5100",
    "addr:housenumber":"51",
    "addr:postcode":"5100",
    "addr:street":"Parc Industriel",
    "iso:country":"BE",
    "sg:address":"Parc Industriel Naninne 51",
    "sg:city":"Namur",
    "sg:orig_category":"Articles de sport, camping and jouets Gr",
    "sg:phone":"+32 81 40 91 11",
    "sg:postcode":"5100",
    "sg:province":"Namur",
    "wof:name":"Mosa Import",
    "wof:placetype":"venue"
},
  "geometry": {"coordinates":[4.8713750839,50.4566345215],"type":"Point"}
}