{
  "type": "Feature",
  "properties": {
    "addr:full":"Jan Van Rijswijcklaan 92 Antwerpen Antwerpen 2018",
    "addr:housenumber":"92",
    "addr:postcode":"2018",
    "addr:street":"Jan Van Rijswijcklaan",
    "iso:country":"BE",
    "sg:address":"Jan Van Rijswijcklaan 92",
    "sg:city":"Antwerpen",
    "sg:orig_category":"Kapsalons",
    "sg:phone":"+32 3 248 01 92",
    "sg:postcode":"2018",
    "sg:province":"Antwerpen",
    "wof:name":"Coiffure Empire",
    "wof:placetype":"venue"
},
  "geometry": {"coordinates":[4.4025950432,51.1946716309],"type":"Point"}
}