{
  "type": "Feature",
  "properties": {
    "iso:country":"BE",
    "sg:address":"Breendonkdorp 105",
    "sg:city":"Puurs",
    "sg:classifiers":[
        {
            "category":"Cafe",
            "type":"Food & Drink"
        }
    ],
    "sg:phone":"+32 3 886 92 87",
    "sg:postcode":"2870",
    "sg:province":"Antwerpen",
    "sg:tags":[
        "caf\u00e9s"
    ],
    "wof:name":"Leo Taelman",
    "wof:placetype":"venue"
},
  "geometry": {"coordinates":[4.3254818916,51.044303894],"type":"Point"}
}