{
  "type": "Feature",
  "properties": {
    "addr:full":"Blauwkasteelweg 8 Box 2 Brugge (sint-kruis) West-Vlaanderen 8310",
    "addr:housenumber":"8;2",
    "addr:postcode":"8310",
    "addr:street":"Blauwkasteelweg;Box",
    "iso:country":"BE",
    "sg:address":"Blauwkasteelweg 8 Box 2",
    "sg:city":"Brugge (sint-kruis)",
    "sg:classifiers":[
        {
            "category":"Real Estate",
            "subcategory":"Developer",
            "type":"Services"
        }
    ],
    "sg:phone":"+32 50 37 09 42",
    "sg:postcode":"8310",
    "sg:province":"West-Vlaanderen",
    "sg:tags":[
        "project"
    ],
    "wof:name":"Brugse Promotie Maatschappij Nv",
    "wof:placetype":"venue"
},
  "geometry": {"coordinates":[3.243240118,51.2157211304],"type":"Point"}
}