{
  "type": "Feature",
  "properties": {
    "addr:full":"Square De Meeus 1 - Brussels Bruxelles-Capitale 1000",
    "addr:housenumber":"1",
    "addr:postcode":"1000",
    "addr:street":"Square De Meeus",
    "iso:country":"BE",
    "sg:address":"Square De Meeus 1 -",
    "sg:city":"Brussels",
    "sg:classifiers":[
        {
            "category":"Professional",
            "subcategory":"Art Services",
            "type":"Services"
        }
    ],
    "sg:phone":"+32 2 512 10 40",
    "sg:postcode":"1000",
    "sg:province":"Bruxelles-Capitale",
    "sg:tags":[
        "export-import"
    ],
    "wof:name":"New Zealand Embassy",
    "wof:placetype":"venue"
},
  "geometry": {"coordinates":[4.3685231209,50.8399162292],"type":"Point"}
}