{
  "type": "Feature",
  "properties": {
    "iso:country":"BE",
    "sg:address":"Koolmijnlaan 348",
    "sg:city":"Beringen (beverlo)",
    "sg:classifiers":[
        {
            "category":"Wholesale",
            "subcategory":"Medical Equipment & Supplies",
            "type":"Manufacturing & Wholesale Goods"
        }
    ],
    "sg:phone":"+32 11 42 21 34",
    "sg:postcode":"3581",
    "sg:province":"Limburg",
    "sg:tags":[
        "aid",
        "hearing"
    ],
    "wof:name":"Deferme Optiek",
    "wof:placetype":"venue"
},
  "geometry": {"coordinates":[5.2193927765,51.0766716003],"type":"Point"}
}