{
  "type": "Feature",
  "properties": {
    "iso:country":"BE",
    "sg:address":"Dolfijnenstraat 32",
    "sg:city":"Sint-jans-molenbeek/molenbeek-saint-jean",
    "sg:orig_category":"Reclamebureaus",
    "sg:phone":"+32 2 411 19 13",
    "sg:postcode":"1080",
    "sg:province":"Bruxelles-Capitale",
    "wof:name":"Pavy Conseil",
    "wof:placetype":"venue"
},
  "geometry": {"coordinates":[4.3090529442,50.8523750305],"type":"Point"}
}