{
  "type": "Feature",
  "properties": {
    "iso:country":"BE",
    "sg:address":"Holstraat 29",
    "sg:city":"Evergem",
    "sg:orig_category":"Herstellingswinkels voor diverse persoonlijke and huishoudartikelen",
    "sg:phone":"+32 9 344 48 38",
    "sg:postcode":"9940",
    "sg:province":"Oost-Vlaanderen",
    "wof:name":"Retouche Huisje",
    "wof:placetype":"venue"
},
  "geometry": {"coordinates":[3.7443749905,51.1819534302],"type":"Point"}
}