{
  "type": "Feature",
  "properties": {
    "addr:full":"Vichtestraat 35 Zwevegem West-Vlaanderen 8553",
    "addr:housenumber":"35",
    "addr:postcode":"8553",
    "addr:street":"Vichtestraat",
    "iso:country":"BE",
    "sg:address":"Vichtestraat 35",
    "sg:city":"Zwevegem",
    "sg:orig_category":"Banques and organismes de cr\u00e9dit",
    "sg:phone":"+32 56 77 75 22",
    "sg:postcode":"8553",
    "sg:province":"West-Vlaanderen",
    "wof:name":"Centea",
    "wof:placetype":"venue"
},
  "geometry": {"coordinates":[3.3933019638,50.8207473755],"type":"Point"}
}