{
  "type": "Feature",
  "properties": {
    "addr:full":"Chauss\u00e9e De Lodelinsart 38 Charleroi (gilly) Hainaut 6060",
    "addr:housenumber":"38",
    "addr:postcode":"6060",
    "addr:street":"Chausse\u0301E De Lodelinsart",
    "iso:country":"BE",
    "sg:address":"Chauss\u00e9e De Lodelinsart 38",
    "sg:city":"Charleroi (gilly)",
    "sg:classifiers":[
        {
            "category":"Food & Beverages",
            "subcategory":"Specialty",
            "type":"Retail Goods"
        }
    ],
    "sg:phone":"+32 71 41 08 32",
    "sg:postcode":"6060",
    "sg:province":"Hainaut",
    "sg:tags":[
        "health",
        "dietary",
        "-",
        "biological"
    ],
    "wof:name":"La Sante Verte",
    "wof:placetype":"venue"
},
  "geometry": {"coordinates":[4.4880981445,50.4251937866],"type":"Point"}
}