{
  "type": "Feature",
  "properties": {
    "addr:full":"Bakkerswegel 1 Sint-lievens-houtem (letterhoutem) Oost-Vlaanderen 9521",
    "addr:housenumber":"1",
    "addr:postcode":"9521",
    "addr:street":"Bakkerswegel;Letterhoutem",
    "iso:country":"BE",
    "sg:address":"Bakkerswegel 1",
    "sg:city":"Sint-lievens-houtem (letterhoutem)",
    "sg:classifiers":[
        {
            "category":"Bakery",
            "type":"Food & Drink"
        }
    ],
    "sg:phone":"+32 53 62 29 80",
    "sg:postcode":"9521",
    "sg:province":"Oost-Vlaanderen",
    "sg:tags":[
        "confectioner",
        "baker"
    ],
    "wof:name":"De Jaegher P",
    "wof:placetype":"venue"
},
  "geometry": {"coordinates":[3.8766670227,50.9297714233],"type":"Point"}
}