{
  "type": "Feature",
  "properties": {
    "iso:country":"BE",
    "sg:address":"Eikenstraat 16",
    "sg:city":"Zutendaal",
    "sg:orig_category":"Enseignement maternel and primaire",
    "sg:phone":"+32 89 61 32 52",
    "sg:postcode":"3690",
    "sg:province":"Limburg",
    "wof:name":"Vrije Basisschool",
    "wof:placetype":"venue"
},
  "geometry": {"coordinates":[5.5897011757,50.9362068176],"type":"Point"}
}