{
  "type": "Feature",
  "properties": {
    "iso:country":"BE",
    "sg:address":"Robert Molsstraat 36",
    "sg:city":"Antwerpen",
    "sg:orig_category":"Plaatsen van vloer- and muurbekleding Schilders",
    "sg:phone":"+32 3 248 27 02",
    "sg:postcode":"2018",
    "sg:province":"Antwerpen",
    "wof:name":"Ronald Steffen",
    "wof:placetype":"venue"
},
  "geometry": {"coordinates":[4.4020271301,51.2003479004],"type":"Point"}
}