{
  "type": "Feature",
  "properties": {
    "addr:full":"Koningin Fabiolastraat 130 Wevelgem (gullegem) West-Vlaanderen 8560",
    "addr:housenumber":"130",
    "addr:postcode":"8560",
    "addr:street":"Koningin Fabiolastraat",
    "iso:country":"BE",
    "sg:address":"Koningin Fabiolastraat 130",
    "sg:city":"Wevelgem (gullegem)",
    "sg:classifiers":[
        {
            "category":"Utilities",
            "subcategory":"Refuse",
            "type":"Services"
        }
    ],
    "sg:phone":"+32 56 43 53 73",
    "sg:postcode":"8560",
    "sg:province":"West-Vlaanderen",
    "sg:tags":[
        "catering"
    ],
    "wof:name":"Frans Hanssens Nv-sa",
    "wof:placetype":"venue"
},
  "geometry": {"coordinates":[3.1990230083,50.8369865417],"type":"Point"}
}