{
  "type": "Feature",
  "properties": {
    "iso:country":"BE",
    "sg:address":"Chauss\u00c9e De Forest 78",
    "sg:city":"Sint-gillis/saint-gilles",
    "sg:orig_category":"Epiceries",
    "sg:phone":"+32 2 537 06 58",
    "sg:postcode":"1060",
    "sg:province":"Bruxelles-Capitale",
    "wof:name":"Maison Banger & Son",
    "wof:placetype":"venue"
},
  "geometry": {"coordinates":[4.3398480415,50.8312301636],"type":"Point"}
}