{
  "type": "Feature",
  "properties": {
    "addr:full":"Rutting 6 Dilbeek (itterbeek) Vlaams-Brabant 1701",
    "addr:housenumber":"6",
    "addr:postcode":"1701",
    "addr:street":"Rutting",
    "iso:country":"BE",
    "sg:address":"Rutting 6",
    "sg:city":"Dilbeek (itterbeek)",
    "sg:classifiers":[
        {
            "category":"Bakery",
            "type":"Food & Drink"
        }
    ],
    "sg:phone":"+32 2 569 00 98",
    "sg:postcode":"1701",
    "sg:province":"Vlaams-Brabant",
    "sg:tags":[
        "confectioner",
        "baker"
    ],
    "wof:name":"Plas",
    "wof:placetype":"venue"
},
  "geometry": {"coordinates":[4.2437157631,50.8400344849],"type":"Point"}
}