{
  "type": "Feature",
  "properties": {
    "addr:full":"Rue Du Suxy 8 Les Bulles Luxembourg 6811",
    "addr:housenumber":"8",
    "addr:postcode":"6811",
    "addr:street":"Rue Du Suxy",
    "iso:country":"BE",
    "sg:address":"Rue Du Suxy 8",
    "sg:city":"Les Bulles",
    "sg:orig_category":"Installatie van houten of kunststof schrijnwerk",
    "sg:phone":"+32 61 32 96 65",
    "sg:postcode":"6811",
    "sg:province":"Luxembourg",
    "wof:name":"Daniel Cl\u00c9ment",
    "wof:placetype":"venue"
},
  "geometry": {"coordinates":[5.4228129387,49.7061004639],"type":"Point"}
}