{
  "type": "Feature",
  "properties": {
    "addr:full":"R\u00c9sidence Saturne 4 Wavre Brabant Wallon 1300",
    "addr:housenumber":"4;1300",
    "iso:country":"BE",
    "sg:address":"R\u00c9sidence Saturne 4",
    "sg:city":"Wavre",
    "sg:orig_category":"Verlichting and huishoudartikelen",
    "sg:phone":"+32 10 41 86 03",
    "sg:postcode":"1300",
    "sg:province":"Brabant Wallon",
    "wof:name":"De Knoop",
    "wof:placetype":"venue"
},
  "geometry": {"coordinates":[4.6116552353,50.7134132385],"type":"Point"}
}