{
  "type": "Feature",
  "properties": {
    "addr:full":"Brusselsesteenweg 268 Edingen/enghien Hainaut 7850",
    "addr:housenumber":"268",
    "addr:postcode":"7850",
    "addr:street":"Brusselsesteenweg",
    "iso:country":"BE",
    "sg:address":"Brusselsesteenweg 268",
    "sg:city":"Edingen/enghien",
    "sg:orig_category":"Passagiersvervoer over de weg Reisbureaus",
    "sg:phone":"+32 2 395 67 44",
    "sg:postcode":"7850",
    "sg:province":"Hainaut",
    "wof:name":"Autobus Naway",
    "wof:placetype":"venue"
},
  "geometry": {"coordinates":[4.0746779442,50.6902503967],"type":"Point"}
}