{
  "type": "Feature",
  "properties": {
    "iso:country":"BE",
    "sg:address":"Galeries Des Deux Places 12",
    "sg:city":"Verviers",
    "sg:classifiers":[
        {
            "category":"Manufacturing",
            "subcategory":"Textiles",
            "type":"Manufacturing & Wholesale Goods"
        }
    ],
    "sg:phone":"+32 87 33 06 28",
    "sg:postcode":"4800",
    "sg:province":"Li\u00e8ge",
    "sg:tags":[
        "retail",
        "-"
    ],
    "wof:name":"Loviane Style",
    "wof:placetype":"venue"
},
  "geometry": {"coordinates":[5.8594508171,50.5917663574],"type":"Point"}
}