{
  "type": "Feature",
  "properties": {
    "addr:full":"Molenheidestraat 7 Houthalen-helchteren Limburg 3530",
    "addr:housenumber":"7",
    "addr:postcode":"3530",
    "addr:street":"Molenheidestraat",
    "iso:country":"BE",
    "sg:address":"Molenheidestraat 7",
    "sg:city":"Houthalen-helchteren",
    "sg:orig_category":"Kampeerterreinen Krantenwinkels Ruimtes voor conferenties, recepties and feesten Sportterreinen and ",
    "sg:phone":"+32 11 52 10 44",
    "sg:postcode":"3530",
    "sg:province":"Limburg",
    "wof:name":"Molenheide Park",
    "wof:placetype":"venue"
},
  "geometry": {"coordinates":[5.3719201088,51.0310020447],"type":"Point"}
}