{
  "type": "Feature",
  "properties": {
    "iso:country":"BE",
    "sg:address":"Chauss\u00c9e De Lannoy 128",
    "sg:city":"Tournai",
    "sg:orig_category":"Vertalers and tolken",
    "sg:phone":"+32 69 84 69 51",
    "sg:postcode":"7503",
    "sg:province":"Hainaut",
    "wof:name":"Tosatto E. Cbtip/bkvtf",
    "wof:placetype":"venue"
},
  "geometry": {"coordinates":[3.346200943,50.6236457825],"type":"Point"}
}