{
  "type": "Feature",
  "properties": {
    "addr:full":"Colonel Silvertopstraat 11 Boom Antwerpen 2850",
    "addr:housenumber":"11",
    "addr:postcode":"2850",
    "addr:street":"Silvertopstraat",
    "iso:country":"BE",
    "sg:address":"Colonel Silvertopstraat 11",
    "sg:city":"Boom",
    "sg:classifiers":[
        {
            "category":"Restaurant",
            "type":"Food & Drink"
        }
    ],
    "sg:phone":"+32 3 844 22 87",
    "sg:postcode":"2850",
    "sg:province":"Antwerpen",
    "wof:name":"Andy's Koffieshop",
    "wof:placetype":"venue"
},
  "geometry": {"coordinates":[4.3621559143,51.0860099792],"type":"Point"}
}