{
  "type": "Feature",
  "properties": {
    "addr:full":"Rue De L\u00b4ermitage 23 Neupr\u00c9 Li\u00e8ge 4121",
    "addr:housenumber":"23",
    "addr:postcode":"4121",
    "addr:street":"Rue De L\u00b4Ermitage",
    "iso:country":"BE",
    "sg:address":"Rue De L\u00b4ermitage 23",
    "sg:city":"Neupr\u00c9",
    "sg:orig_category":"Meubelzaken, woning- and keukeninrichting",
    "sg:phone":"+32 4 372 01 51",
    "sg:postcode":"4121",
    "sg:province":"Li\u00e8ge",
    "wof:name":"Pietro Mignosi",
    "wof:placetype":"venue"
},
  "geometry": {"coordinates":[5.4611411095,50.5530586243],"type":"Point"}
}