{
  "type": "Feature",
  "properties": {
    "iso:country":"BE",
    "sg:address":"Rue Du Marais 124",
    "sg:city":"Qui\u00e9vrain",
    "sg:classifiers":[
        {
            "category":"Insurance",
            "subcategory":"Insurance Agent",
            "type":"Services"
        }
    ],
    "sg:phone":"+32 65 45 74 37",
    "sg:postcode":"7380",
    "sg:province":"Hainaut",
    "sg:tags":[
        "broker"
    ],
    "wof:name":"Cuvelier",
    "wof:placetype":"venue"
},
  "geometry": {"coordinates":[3.6852359772,50.4173927307],"type":"Point"}
}