{
  "type": "Feature",
  "properties": {
    "iso:country":"BE",
    "sg:address":"Rue D'angleterre 12",
    "sg:city":"La Louviere",
    "sg:orig_category":"Elektrische installaties voor woningen",
    "sg:phone":"+32 64 21 36 80",
    "sg:postcode":"7110",
    "sg:province":"Hainaut",
    "wof:name":"Etienne Piotrowski",
    "wof:placetype":"venue"
},
  "geometry": {"coordinates":[4.1481399536,50.4951896667],"type":"Point"}
}