{
  "type": "Feature",
  "properties": {
    "iso:country":"BE",
    "sg:address":"Heirbrugstraat 41",
    "sg:city":"Lokeren",
    "sg:orig_category":"Tabac",
    "sg:phone":"+32 9 348 12 88",
    "sg:postcode":"9160",
    "sg:province":"Oost-Vlaanderen",
    "wof:name":"Huis Trienpont",
    "wof:placetype":"venue"
},
  "geometry": {"coordinates":[3.9813270569,51.1024780273],"type":"Point"}
}