{
  "type": "Feature",
  "properties": {
    "iso:country":"BE",
    "sg:address":"Avenue Des Marni\u00c8res 7",
    "sg:city":"Waterloo",
    "sg:orig_category":"S\u00e9lection de personnel and placement. Maisons de vacances",
    "sg:phone":"+32 2 384 47 30",
    "sg:postcode":"1410",
    "sg:province":"Brabant Wallon",
    "wof:name":"New Careers",
    "wof:placetype":"venue"
},
  "geometry": {"coordinates":[4.4091529846,50.6910972595],"type":"Point"}
}