{
  "type": "Feature",
  "properties": {
    "addr:full":"Eduard De Cuyperstraat 14 Oostende West-Vlaanderen 8400",
    "addr:housenumber":"14",
    "addr:postcode":"8400",
    "addr:street":"Eduard De Cuyperstraat",
    "iso:country":"BE",
    "sg:address":"Eduard De Cuyperstraat 14",
    "sg:city":"Oostende",
    "sg:orig_category":"Boekhouders",
    "sg:phone":"+32 59 70 21 75",
    "sg:postcode":"8400",
    "sg:province":"West-Vlaanderen",
    "wof:name":"Walter Hosten",
    "wof:placetype":"venue"
},
  "geometry": {"coordinates":[2.9036619663,51.2226905823],"type":"Point"}
}