{
  "type": "Feature",
  "properties": {
    "iso:country":"BE",
    "sg:address":"Heliotropenlaan 32",
    "sg:city":"Schaarbeek/schaerbeek",
    "sg:orig_category":"Beheer onroerend goed",
    "sg:phone":"+32 2 215 38 45",
    "sg:postcode":"1030",
    "sg:province":"Bruxelles-Capitale",
    "wof:name":"La Sobelim",
    "wof:placetype":"venue"
},
  "geometry": {"coordinates":[4.3896617889,50.8643493652],"type":"Point"}
}