{
  "type": "Feature",
  "properties": {
    "iso:country":"BE",
    "sg:address":"Leuerbroek 1038",
    "sg:city":"Kinrooi (ophoven)",
    "sg:classifiers":[
        {
            "category":"Building & Trades",
            "subcategory":"Electrical",
            "type":"Services"
        }
    ],
    "sg:phone":"+32 89 70 15 73",
    "sg:postcode":"3640",
    "sg:province":"Limburg",
    "sg:tags":[
        "electric",
        "-",
        "housewiring",
        "contractor"
    ],
    "wof:name":"Maco Bvba",
    "wof:placetype":"venue"
},
  "geometry": {"coordinates":[5.7478260994,51.1378135681],"type":"Point"}
}