{
  "type": "Feature",
  "properties": {
    "addr:full":"Nerenhoek 72 Lochristi (zaffelare) Oost-Vlaanderen 9080",
    "addr:housenumber":"72",
    "addr:postcode":"9080",
    "addr:street":"Nerenhoek",
    "iso:country":"BE",
    "sg:address":"Nerenhoek 72",
    "sg:city":"Lochristi (zaffelare)",
    "sg:classifiers":[
        {
            "category":"Wholesale",
            "subcategory":"Plants",
            "type":"Manufacturing & Wholesale Goods"
        }
    ],
    "sg:phone":"+32 9 355 67 21",
    "sg:postcode":"9080",
    "sg:province":"Oost-Vlaanderen",
    "sg:tags":[
        "whol",
        "flower",
        "-",
        "grower"
    ],
    "wof:name":"Tollenaere T",
    "wof:placetype":"venue"
},
  "geometry": {"coordinates":[3.8326859474,51.1339454651],"type":"Point"}
}