{
  "type": "Feature",
  "properties": {
    "iso:country":"BE",
    "sg:address":"Dirk Boutslaan 6-1",
    "sg:city":"Leuven",
    "sg:classifiers":[
        {
            "category":"Health Services",
            "subcategory":"Dentist",
            "type":"Services"
        }
    ],
    "sg:phone":"+32 16 23 50 08",
    "sg:postcode":"3000",
    "sg:province":"Vlaams-Brabant",
    "wof:name":"Vanherle-lemaire",
    "wof:placetype":"venue"
},
  "geometry": {"coordinates":[4.6998310089,50.8802986145],"type":"Point"}
}