{
  "type": "Feature",
  "properties": {
    "iso:country":"BE",
    "sg:address":"Quai Vercour 106",
    "sg:city":"Liege",
    "sg:orig_category":"Opel Bedrijfsvoertuigen",
    "sg:phone":"+32 4 252 71 30",
    "sg:postcode":"4000",
    "sg:province":"Li\u00e8ge",
    "wof:name":"Ets. Bounameaux",
    "wof:placetype":"venue"
},
  "geometry": {"coordinates":[5.5487580299,50.6077804565],"type":"Point"}
}