{
  "type": "Feature",
  "properties": {
    "iso:country":"BE",
    "sg:address":"Pastoriestraat 28",
    "sg:city":"Gooik",
    "sg:orig_category":"Kapsalons",
    "sg:phone":"+32 54 56 69 26",
    "sg:postcode":"1755",
    "sg:province":"Vlaams-Brabant",
    "wof:name":"Coiffure Liliane",
    "wof:placetype":"venue"
},
  "geometry": {"coordinates":[4.0679788589,50.7716217041],"type":"Point"}
}