{
  "type": "Feature",
  "properties": {
    "addr:full":"Beiaardstraat 96 Izegem West-Vlaanderen 8870",
    "addr:housenumber":"96",
    "addr:postcode":"8870",
    "addr:street":"Beiaardstraat",
    "iso:country":"BE",
    "sg:address":"Beiaardstraat 96",
    "sg:city":"Izegem",
    "sg:orig_category":"Maatkleding Fab",
    "sg:phone":"+32 51 30 18 37",
    "sg:postcode":"8870",
    "sg:province":"West-Vlaanderen",
    "wof:name":"Rosa Baert",
    "wof:placetype":"venue"
},
  "geometry": {"coordinates":[3.2128539085,50.904384613],"type":"Point"}
}