{
  "type": "Feature",
  "properties": {
    "addr:full":"Rue De La Cr\u00eate 20 Flobecq Hainaut 7880",
    "addr:housenumber":"20",
    "addr:postcode":"7880",
    "addr:street":"Rue De La Cre\u0302Te;Hainaut",
    "iso:country":"BE",
    "sg:address":"Rue De La Cr\u00eate 20",
    "sg:city":"Flobecq",
    "sg:classifiers":[
        {
            "category":"Building & Trades",
            "subcategory":"Landscaping Services",
            "type":"Services"
        }
    ],
    "sg:phone":"+32 68 44 84 10",
    "sg:postcode":"7880",
    "sg:province":"Hainaut",
    "sg:tags":[
        "handicraft"
    ],
    "wof:name":"Cotton B",
    "wof:placetype":"venue"
},
  "geometry": {"coordinates":[3.739356041,50.7336120605],"type":"Point"}
}