{
  "type": "Feature",
  "properties": {
    "addr:full":"Rue Arthur Warocqu\u00e9 5 La Louvi\u00e8re Hainaut 7100",
    "addr:housenumber":"5",
    "addr:postcode":"7100",
    "addr:street":"Rue Arthur Warocque\u0301",
    "iso:country":"BE",
    "sg:address":"Rue Arthur Warocqu\u00e9 5",
    "sg:city":"La Louvi\u00e8re",
    "sg:classifiers":[
        {
            "category":"Health Services",
            "subcategory":"Nursing And Care Facility",
            "type":"Services"
        }
    ],
    "sg:phone":"+32 64 46 01 46",
    "sg:postcode":"7100",
    "sg:province":"Hainaut",
    "sg:tags":[
        "home"
    ],
    "wof:name":"Palmieri L",
    "wof:placetype":"venue"
},
  "geometry": {"coordinates":[4.1902189255,50.4777297974],"type":"Point"}
}