{
  "type": "Feature",
  "properties": {
    "iso:country":"BE",
    "sg:address":"Rue Du Calvaire 7",
    "sg:city":"Leuze-en-hainaut (chapelle-\u00e0-wattines)",
    "sg:classifiers":[
        {
            "category":"Home & Garden",
            "subcategory":"Garden Supply",
            "type":"Retail Goods"
        }
    ],
    "sg:phone":"+32 69 66 23 46",
    "sg:postcode":"7903",
    "sg:province":"Hainaut",
    "sg:tags":[
        "seed",
        "-"
    ],
    "wof:name":"Despret A",
    "wof:placetype":"venue"
},
  "geometry": {"coordinates":[3.6507771015,50.613609314],"type":"Point"}
}