{
  "type": "Feature",
  "properties": {
    "addr:full":"Avenue Laboulle 61 Esneux (tilff) Li\u00e8ge 4130",
    "addr:housenumber":"61",
    "addr:postcode":"4130",
    "addr:street":"Avenue Laboulle",
    "iso:country":"BE",
    "sg:address":"Avenue Laboulle 61",
    "sg:city":"Esneux (tilff)",
    "sg:classifiers":[
        {
            "category":"Home & Garden",
            "subcategory":"Household Appliances",
            "type":"Retail Goods"
        }
    ],
    "sg:phone":"+32 4 388 16 64",
    "sg:postcode":"4130",
    "sg:province":"Li\u00e8ge",
    "sg:tags":[
        "repair",
        "mainten",
        "-",
        "electric"
    ],
    "wof:name":"Chamberland Electromenager",
    "wof:placetype":"venue"
},
  "geometry": {"coordinates":[5.5669360161,50.5327568054],"type":"Point"}
}