{
  "type": "Feature",
  "properties": {
    "iso:country":"BE",
    "sg:address":"Kleine Zauwerstraat 2",
    "sg:city":"Laarne (kalken)",
    "sg:classifiers":[
        {
            "category":"Food & Beverages",
            "subcategory":"Meat & Fish",
            "type":"Retail Goods"
        }
    ],
    "sg:phone":"+32 9 367 63 28",
    "sg:postcode":"9270",
    "sg:province":"Oost-Vlaanderen",
    "sg:tags":[
        "-",
        "livestock"
    ],
    "wof:name":"Rogiers E",
    "wof:placetype":"venue"
},
  "geometry": {"coordinates":[3.9253718853,51.049369812],"type":"Point"}
}