{
  "type": "Feature",
  "properties": {
    "iso:country":"BE",
    "sg:address":"Rue De La Briqueterie 86",
    "sg:city":"Fleron",
    "sg:orig_category":"Journaux. Tabac",
    "sg:phone":"+32 4 358 72 05",
    "sg:postcode":"4621",
    "sg:province":"Li\u00e8ge",
    "wof:name":"Marie-line Masset",
    "wof:placetype":"venue"
},
  "geometry": {"coordinates":[5.703938961,50.6263847351],"type":"Point"}
}