{
  "type": "Feature",
  "properties": {
    "addr:full":"Brusselsesteenweg 183 Waterloo (groot) Brabant Wallon 1410",
    "addr:housenumber":"183",
    "addr:postcode":"1410",
    "addr:street":"Brusselsesteenweg;Groot Brabant Wallon",
    "iso:country":"BE",
    "sg:address":"Brusselsesteenweg 183",
    "sg:city":"Waterloo (groot)",
    "sg:orig_category":"Baby- and kinderkleding Dameskledingzaken Herenkledingzaken",
    "sg:phone":"+32 2 354 75 72",
    "sg:postcode":"1410",
    "sg:province":"Brabant Wallon",
    "wof:name":"Benetton",
    "wof:placetype":"venue"
},
  "geometry": {"coordinates":[4.3984827995,50.716583252],"type":"Point"}
}