{
  "type": "Feature",
  "properties": {
    "iso:country":"BE",
    "sg:address":"Walenweg 41",
    "sg:city":"Zaventem (nossegem)",
    "sg:classifiers":[
        {
            "category":"Farming",
            "subcategory":"Crops",
            "type":"Manufacturing & Wholesale Goods"
        }
    ],
    "sg:phone":"+32 2 759 84 91",
    "sg:postcode":"1930",
    "sg:province":"Vlaams-Brabant",
    "sg:tags":[
        "vegetable",
        "fruit",
        "-",
        "grower"
    ],
    "wof:name":"Brussels Grondwitloof Vzw",
    "wof:placetype":"venue"
},
  "geometry": {"coordinates":[4.5203480721,50.8803749084],"type":"Point"}
}