{
  "type": "Feature",
  "properties": {
    "iso:country":"BE",
    "sg:address":"Turnhoutsebaan 448",
    "sg:city":"Wijnegem",
    "sg:classifiers":[
        {
            "category":"Wholesale",
            "subcategory":"Beer",
            "type":"Manufacturing & Wholesale Goods"
        }
    ],
    "sg:phone":"+32 3 353 61 01",
    "sg:postcode":"2110",
    "sg:province":"Antwerpen",
    "sg:tags":[
        "ale",
        "-"
    ],
    "wof:name":"De Kroon Bvba",
    "wof:placetype":"venue"
},
  "geometry": {"coordinates":[4.5259342194,51.228302002],"type":"Point"}
}