{
  "type": "Feature",
  "properties": {
    "addr:full":"Lozenberg 9 Zaventem (sint-stevens-woluwe) Vlaams-Brabant 1932",
    "addr:housenumber":"9",
    "addr:postcode":"1932",
    "addr:street":"Lozenberg",
    "iso:country":"BE",
    "sg:address":"Lozenberg 9",
    "sg:city":"Zaventem (sint-stevens-woluwe)",
    "sg:orig_category":"Autombile concessionaires",
    "sg:phone":"+32 2 723 99 11",
    "sg:postcode":"1932",
    "sg:province":"Vlaams-Brabant",
    "wof:name":"Mg Rover Belux Nv",
    "wof:placetype":"venue"
},
  "geometry": {"coordinates":[4.4646859169,50.8691291809],"type":"Point"}
}