{
  "type": "Feature",
  "properties": {
    "addr:full":"Bd De Smet De Naeyer 611 Bruxelles Bruxelles-Capitale 1020",
    "addr:housenumber":"611",
    "addr:postcode":"1020",
    "addr:street":"Bd De Smet De Naeyer",
    "iso:country":"BE",
    "sg:address":"Bd De Smet De Naeyer 611",
    "sg:city":"Bruxelles",
    "sg:classifiers":[
        {
            "category":"Professional",
            "subcategory":"Computer Services",
            "type":"Services"
        }
    ],
    "sg:phone":"+32 2 478 29 38",
    "sg:postcode":"1020",
    "sg:province":"Bruxelles-Capitale",
    "sg:tags":[
        "information",
        "technology",
        "software"
    ],
    "wof:name":"Masact Sa",
    "wof:placetype":"venue"
},
  "geometry": {"coordinates":[4.3420729637,50.8865356445],"type":"Point"}
}