{
  "type": "Feature",
  "properties": {
    "addr:full":"Chauss\u00c9e De Maubeuge 228 Mons Hainaut 7022",
    "addr:housenumber":"228",
    "addr:postcode":"7022",
    "addr:street":"Chausse\u0301E De Maubeuge;Hainaut",
    "iso:country":"BE",
    "sg:address":"Chauss\u00c9e De Maubeuge 228",
    "sg:city":"Mons",
    "sg:orig_category":"Eclairage et \u00e9quipements du foyer. Electrom\u00e9nager, t\u00e9l\u00e9visions and radios",
    "sg:phone":"+32 65 36 23 52",
    "sg:postcode":"7022",
    "sg:province":"Hainaut",
    "wof:name":"Audio Technic Services",
    "wof:placetype":"venue"
},
  "geometry": {"coordinates":[3.9471709728,50.436958313],"type":"Point"}
}