{
  "type": "Feature",
  "properties": {
    "addr:full":"Itegemse Steenweg 30a Herenthout Antwerpen 2270",
    "addr:housenumber":"30a",
    "addr:postcode":"2270",
    "addr:street":"Itegemse Steenweg",
    "iso:country":"BE",
    "sg:address":"Itegemse Steenweg 30a",
    "sg:city":"Herenthout",
    "sg:classifiers":[
        {
            "category":"Home & Garden",
            "subcategory":"Building Materials",
            "type":"Retail Goods"
        }
    ],
    "sg:phone":"+32 14 51 16 79",
    "sg:postcode":"2270",
    "sg:province":"Antwerpen",
    "sg:tags":[
        "window"
    ],
    "wof:name":"R & M",
    "wof:placetype":"venue"
},
  "geometry": {"coordinates":[4.7610487938,51.1379165649],"type":"Point"}
}