{
  "type": "Feature",
  "properties": {
    "iso:country":"BE",
    "sg:address":"Rue De Tournai 12b",
    "sg:city":"Brunehaut",
    "sg:orig_category":"Tuinen",
    "sg:phone":"+32 69 44 41 35",
    "sg:postcode":"7620",
    "sg:province":"Hainaut",
    "wof:name":"Lescaut S",
    "wof:placetype":"venue"
},
  "geometry": {"coordinates":[3.4203300476,50.5198097229],"type":"Point"}
}