{
  "type": "Feature",
  "properties": {
    "addr:full":"Avenue Jupiter 101 Bruxelles (forest) Bruxelles-Capitale 1190",
    "addr:housenumber":"101",
    "addr:postcode":"1190",
    "addr:street":"Avenue Jupiter",
    "iso:country":"BE",
    "sg:address":"Avenue Jupiter 101",
    "sg:city":"Bruxelles (forest)",
    "sg:classifiers":[
        {
            "category":"Health Services",
            "subcategory":"Doctor",
            "type":"Services"
        }
    ],
    "sg:phone":"+32 2 346 91 30",
    "sg:postcode":"1190",
    "sg:province":"Bruxelles-Capitale",
    "sg:tags":[
        "psychotherapist",
        "psychoanalyst"
    ],
    "wof:name":"Jacques Jean-pierre",
    "wof:placetype":"venue"
},
  "geometry": {"coordinates":[4.3351230621,50.8183784485],"type":"Point"}
}