{
  "type": "Feature",
  "properties": {
    "addr:full":"Hendrik Speecqvest 54 Mechelen Antwerpen 2800",
    "addr:housenumber":"54",
    "addr:postcode":"2800",
    "addr:street":"Hendrik Speecqvest",
    "iso:country":"BE",
    "sg:address":"Hendrik Speecqvest 54",
    "sg:city":"Mechelen",
    "sg:classifiers":[
        {
            "category":"Real Estate",
            "subcategory":"Architect",
            "type":"Services"
        }
    ],
    "sg:phone":"+32 15 41 34 90",
    "sg:postcode":"2800",
    "sg:province":"Antwerpen",
    "wof:name":"Van Craen A",
    "wof:placetype":"venue"
},
  "geometry": {"coordinates":[4.4854001999,51.0210189819],"type":"Point"}
}