{
  "type": "Feature",
  "properties": {
    "addr:full":"Dorpstraat 1 Jabbeke West-Vlaanderen 8490",
    "addr:housenumber":"1",
    "addr:postcode":"8490",
    "addr:street":"Dorpstraat",
    "iso:country":"BE",
    "sg:address":"Dorpstraat 1",
    "sg:city":"Jabbeke",
    "sg:orig_category":"Artsen and specialisten",
    "sg:phone":"+32 50 81 13 06",
    "sg:postcode":"8490",
    "sg:province":"West-Vlaanderen",
    "wof:name":"Ann Dumon",
    "wof:placetype":"venue"
},
  "geometry": {"coordinates":[3.095097065,51.1829452515],"type":"Point"}
}