{
  "type": "Feature",
  "properties": {
    "iso:country":"BE",
    "sg:address":"Leuvensesteenweg 502",
    "sg:city":"Zaventem",
    "sg:orig_category":"Mat\u00e9riaux de construction Gr",
    "sg:phone":"+32 2 721 22 26",
    "sg:postcode":"1930",
    "sg:province":"Vlaams-Brabant",
    "wof:name":"Dyka Plastics",
    "wof:placetype":"venue"
},
  "geometry": {"coordinates":[4.4990801811,50.8763809204],"type":"Point"}
}