{
  "type": "Feature",
  "properties": {
    "addr:full":"Rue Du Progr\u00c8s 2 Nivelles Brabant Wallon 1400",
    "addr:housenumber":"2",
    "addr:postcode":"1400",
    "addr:street":"Rue Du Progre\u0300S",
    "iso:country":"BE",
    "sg:address":"Rue Du Progr\u00c8s 2",
    "sg:city":"Nivelles",
    "sg:orig_category":"Agences de voyages",
    "sg:phone":"+32 67 88 83 70",
    "sg:postcode":"1400",
    "sg:province":"Brabant Wallon",
    "wof:name":"Carlson Wagonlit Travel Nivelles",
    "wof:placetype":"venue"
},
  "geometry": {"coordinates":[4.3602170944,50.594379425],"type":"Point"}
}