{
  "type": "Feature",
  "properties": {
    "iso:country":"BE",
    "sg:address":"Wayenborgstraat 8",
    "sg:city":"Mechelen",
    "sg:classifiers":[
        {
            "category":"Professional",
            "type":"Services"
        }
    ],
    "sg:phone":"+32 15 21 27 01",
    "sg:postcode":"2800",
    "sg:province":"Antwerpen",
    "sg:tags":[
        "packing",
        "-"
    ],
    "wof:name":"Dispack Industriele & Promotio Bvba",
    "wof:placetype":"venue"
},
  "geometry": {"coordinates":[4.4426760674,51.0497131348],"type":"Point"}
}