{
  "type": "Feature",
  "properties": {
    "iso:country":"BE",
    "sg:address":"Visesteenweg 174",
    "sg:city":"Zichen-zussen-bolder",
    "sg:classifiers":[
        {
            "category":"Home & Garden",
            "subcategory":"Furniture",
            "type":"Retail Goods"
        }
    ],
    "sg:phone":"+32 12 45 11 67",
    "sg:postcode":"3770",
    "sg:province":"Limburg",
    "sg:tags":[
        "household",
        "wood"
    ],
    "wof:name":"Palais Du Meuble Vrijens Bvba",
    "wof:placetype":"venue"
},
  "geometry": {"coordinates":[5.6166901588,50.7963409424],"type":"Point"}
}