{
  "type": "Feature",
  "properties": {
    "iso:country":"BE",
    "sg:address":"Mee\u00ebnweg 38",
    "sg:city":"Genk",
    "sg:classifiers":[
        {
            "category":"Airport",
            "subcategory":"International",
            "type":"Transportation"
        }
    ],
    "sg:phone":"+32 89 35 35 75",
    "sg:postcode":"3600",
    "sg:province":"Limburg",
    "sg:tags":[
        "-",
        "transport"
    ],
    "wof:name":"All Freight & Transport Nv",
    "wof:placetype":"venue"
},
  "geometry": {"coordinates":[5.4739217758,50.9483528137],"type":"Point"}
}