{
  "type": "Feature",
  "properties": {
    "iso:country":"BE",
    "sg:address":"Rue Saint-l\u00c9onard 438",
    "sg:city":"Li\u00c8ge",
    "sg:orig_category":"Advocaten and juridische adviseurs",
    "sg:phone":"+32 4 228 04 40",
    "sg:postcode":"4000",
    "sg:province":"Li\u00e8ge",
    "wof:name":"F.j. Santos Rey",
    "wof:placetype":"venue"
},
  "geometry": {"coordinates":[5.6008319855,50.6528244019],"type":"Point"}
}