{
  "type": "Feature",
  "properties": {
    "addr:full":"Rue Du Couvent 13 Fleurus Hainaut 6220",
    "addr:housenumber":"13",
    "addr:postcode":"6220",
    "addr:street":"Rue Du Couvent",
    "iso:country":"BE",
    "sg:address":"Rue Du Couvent 13",
    "sg:city":"Fleurus",
    "sg:classifiers":[
        {
            "category":"Shopping",
            "subcategory":"Jewelry",
            "type":"Retail Goods"
        }
    ],
    "sg:phone":"+32 71 81 89 22",
    "sg:postcode":"6220",
    "sg:province":"Hainaut",
    "sg:tags":[
        "jeweller",
        "-"
    ],
    "wof:name":"Imperial Bijoux",
    "wof:placetype":"venue"
},
  "geometry": {"coordinates":[4.5508022308,50.4823188782],"type":"Point"}
}