{
  "type": "Feature",
  "properties": {
    "iso:country":"BE",
    "sg:address":"Stationsstraat 34 Box 13",
    "sg:city":"Alken",
    "sg:classifiers":[
        {
            "category":"Health Services",
            "subcategory":"Health Practitioner",
            "type":"Services"
        }
    ],
    "sg:phone":"+32 11 59 78 05",
    "sg:postcode":"3570",
    "sg:province":"Limburg",
    "sg:tags":[
        "therapist",
        "speech"
    ],
    "wof:name":"Willems Barbara",
    "wof:placetype":"venue"
},
  "geometry": {"coordinates":[5.3024258614,50.8816795349],"type":"Point"}
}