{
  "type": "Feature",
  "properties": {
    "addr:full":"Bredabaan 245 Brasschaat Antwerpen 2930",
    "addr:housenumber":"245",
    "addr:postcode":"2930",
    "addr:street":"Bredabaan",
    "iso:country":"BE",
    "sg:address":"Bredabaan 245",
    "sg:city":"Brasschaat",
    "sg:orig_category":"Beautyfarms, relaxatie and lichamelijk welzijn Cosmetica and toiletartikelen Schoonheidssalons",
    "sg:phone":"+32 3 652 00 40",
    "sg:postcode":"2930",
    "sg:province":"Antwerpen",
    "wof:name":"Yves Rocher",
    "wof:placetype":"venue"
},
  "geometry": {"coordinates":[4.4866681099,51.2874412537],"type":"Point"}
}