{
  "type": "Feature",
  "properties": {
    "addr:full":"Stationsstraat 45 Oudenaarde Oost-Vlaanderen 9700",
    "addr:housenumber":"45",
    "addr:postcode":"9700",
    "addr:street":"Stationsstraat",
    "iso:country":"BE",
    "sg:address":"Stationsstraat 45",
    "sg:city":"Oudenaarde",
    "sg:orig_category":"Supermarkten",
    "sg:postcode":"9700",
    "sg:province":"Oost-Vlaanderen",
    "wof:name":"Aldi",
    "wof:placetype":"venue"
},
  "geometry": {"coordinates":[3.6007800102,50.8499298096],"type":"Point"}
}