{
  "type": "Feature",
  "properties": {
    "addr:full":"Roosbeeksestraat 31 Boutersem Vlaams-Brabant 3370",
    "addr:housenumber":"31",
    "addr:postcode":"3370",
    "addr:street":"Roosbeeksestraat",
    "iso:country":"BE",
    "sg:address":"Roosbeeksestraat 31",
    "sg:city":"Boutersem",
    "sg:classifiers":[
        {
            "category":"Arena",
            "subcategory":"Sports Club",
            "type":"Entertainment"
        }
    ],
    "sg:phone":"+32 16 73 50 96",
    "sg:postcode":"3370",
    "sg:province":"Vlaams-Brabant",
    "sg:tags":[
        "de"
    ],
    "wof:name":"W.cl. De Jean Pierre's Vrienden Vertrijk",
    "wof:placetype":"venue"
},
  "geometry": {"coordinates":[4.8375349045,50.8313446045],"type":"Point"}
}