{
  "type": "Feature",
  "properties": {
    "addr:full":"Houtemstraat 72 Herzele Oost-Vlaanderen 9550",
    "addr:housenumber":"72",
    "addr:postcode":"9550",
    "addr:street":"Houtemstraat;Oost-Vlaanderen",
    "iso:country":"BE",
    "sg:address":"Houtemstraat 72",
    "sg:city":"Herzele",
    "sg:classifiers":[
        {
            "category":"Parking",
            "subcategory":"Lot",
            "type":"Transportation"
        }
    ],
    "sg:phone":"+32 53 62 59 28",
    "sg:postcode":"9550",
    "sg:province":"Oost-Vlaanderen",
    "sg:tags":[
        "parking-places",
        "laying-out"
    ],
    "wof:name":"Van Delsen Bart",
    "wof:placetype":"venue"
},
  "geometry": {"coordinates":[3.876709938,50.9033889771],"type":"Point"}
}