{
  "type": "Feature",
  "properties": {
    "iso:country":"BE",
    "sg:address":"Avenue Du Bois De Rognac 1",
    "sg:city":"Neupre",
    "sg:orig_category":"Installatie van houten of kunststof schrijnwerk",
    "sg:phone":"+32 4 372 09 44",
    "sg:postcode":"4121",
    "sg:province":"Li\u00e8ge",
    "wof:name":"Albini Et Fontanot Benelux",
    "wof:placetype":"venue"
},
  "geometry": {"coordinates":[5.4884619713,50.5435295105],"type":"Point"}
}