{
  "type": "Feature",
  "properties": {
    "addr:full":"Essensteenweg 12 Kapellen Antwerpen 2950",
    "addr:housenumber":"12",
    "addr:postcode":"2950",
    "addr:street":"Essensteenweg",
    "iso:country":"BE",
    "sg:address":"Essensteenweg 12",
    "sg:city":"Kapellen",
    "sg:classifiers":[
        {
            "category":"Building & Trades",
            "subcategory":"Construction",
            "type":"Services"
        }
    ],
    "sg:phone":"+32 3 666 02 85",
    "sg:postcode":"2950",
    "sg:province":"Antwerpen",
    "sg:tags":[
        "la",
        "de",
        "\u00e9quipement",
        "pour",
        "machine",
        "location"
    ],
    "wof:name":"Centrum",
    "wof:placetype":"venue"
},
  "geometry": {"coordinates":[4.5073699951,51.3547706604],"type":"Point"}
}