{
  "type": "Feature",
  "properties": {
    "addr:full":"Rue Neuve 83 Charleroi Hainaut 6000",
    "addr:housenumber":"83",
    "addr:postcode":"6000",
    "addr:street":"Rue Neuve;Hainaut",
    "iso:country":"BE",
    "sg:address":"Rue Neuve 83",
    "sg:city":"Charleroi",
    "sg:orig_category":"Agences d\u00b4interim and personnel temporaire",
    "sg:phone":"+32 71 20 20 80",
    "sg:postcode":"6000",
    "sg:province":"Hainaut",
    "wof:name":"T-int\u00c9rim",
    "wof:placetype":"venue"
},
  "geometry": {"coordinates":[4.4465708733,50.4139289856],"type":"Point"}
}