{
  "type": "Feature",
  "properties": {
    "iso:country":"BE",
    "sg:address":"Rue Jean-baptiste Ledoux 43bb",
    "sg:city":"Charleroi",
    "sg:orig_category":"Travaux d\u00b4installation divers. Lampes and appareils \u00e9lectriques Fab",
    "sg:phone":"+32 71 35 44 05",
    "sg:postcode":"6040",
    "sg:province":"Hainaut",
    "wof:name":"Eliplast",
    "wof:placetype":"venue"
},
  "geometry": {"coordinates":[4.427822113,50.4400787354],"type":"Point"}
}