{
  "type": "Feature",
  "properties": {
    "iso:country":"BE",
    "sg:address":"Place Saint-laurent 7",
    "sg:city":"Walcourt",
    "sg:orig_category":"Tuinen",
    "sg:phone":"+32 71 65 06 52",
    "sg:postcode":"5650",
    "sg:province":"Namur",
    "wof:name":"Colmant J-f.",
    "wof:placetype":"venue"
},
  "geometry": {"coordinates":[4.4313349724,50.2514762878],"type":"Point"}
}