{
  "type": "Feature",
  "properties": {
    "iso:country":"BE",
    "sg:address":"Burgemeester Van Gansberghelaan 31",
    "sg:city":"Merelbeke",
    "sg:classifiers":[
        {
            "category":"Insurance",
            "subcategory":"Insurance Agent",
            "type":"Services"
        }
    ],
    "sg:phone":"+32 9 362 87 24",
    "sg:postcode":"9820",
    "sg:province":"Oost-Vlaanderen",
    "sg:tags":[
        "broker"
    ],
    "wof:name":"Van De Putte",
    "wof:placetype":"venue"
},
  "geometry": {"coordinates":[3.7661399841,50.971660614],"type":"Point"}
}