{
  "type": "Feature",
  "properties": {
    "iso:country":"BE",
    "sg:address":"Dorpsstraat 135",
    "sg:city":"Damme (sijsele)",
    "sg:classifiers":[
        {
            "category":"Health Services",
            "subcategory":"Health Practitioner",
            "type":"Services"
        }
    ],
    "sg:phone":"+32 50 35 48 97",
    "sg:postcode":"8340",
    "sg:province":"West-Vlaanderen",
    "sg:tags":[
        "physiotherapist"
    ],
    "wof:name":"Jacobus L",
    "wof:placetype":"venue"
},
  "geometry": {"coordinates":[3.3210198879,51.2016868591],"type":"Point"}
}