{
  "type": "Feature",
  "properties": {
    "addr:full":"Kleinmijlveld 44 Lint Antwerpen 2547",
    "addr:housenumber":"44",
    "addr:postcode":"2547",
    "addr:street":"Kleinmijlveld",
    "iso:country":"BE",
    "sg:address":"Kleinmijlveld 44",
    "sg:city":"Lint",
    "sg:orig_category":"M\u00e9decins and sp\u00e9cialistes",
    "sg:phone":"+32 3 454 50 77",
    "sg:postcode":"2547",
    "sg:province":"Antwerpen",
    "wof:name":"F. Somville",
    "wof:placetype":"venue"
},
  "geometry": {"coordinates":[4.4736618996,51.1407775879],"type":"Point"}
}