{
  "type": "Feature",
  "properties": {
    "addr:full":"Rue De Goz\u00c9e 629 Montigny-le-tilleul Hainaut 6110",
    "addr:housenumber":"629",
    "addr:postcode":"6110",
    "addr:street":"Rue De Goze\u0301E",
    "iso:country":"BE",
    "sg:address":"Rue De Goz\u00c9e 629",
    "sg:city":"Montigny-le-tilleul",
    "sg:classifiers":[
        {
            "category":"Military Area",
            "subcategory":"Armory",
            "type":"Public Place"
        }
    ],
    "sg:phone":"+32 71 51 17 51",
    "sg:postcode":"6110",
    "sg:province":"Hainaut",
    "sg:tags":[
        "armes",
        "munition"
    ],
    "wof:name":"Vereecke Hubert",
    "wof:placetype":"venue"
},
  "geometry": {"coordinates":[4.3637671471,50.3661460876],"type":"Point"}
}