{
  "type": "Feature",
  "properties": {
    "addr:full":"Marktplein 27 Box 7 Diepenbeek Limburg 3590",
    "addr:housenumber":"27;7",
    "addr:postcode":"3590",
    "addr:street":"Marktplein;Box",
    "iso:country":"BE",
    "sg:address":"Marktplein 27 Box 7",
    "sg:city":"Diepenbeek",
    "sg:classifiers":[
        {
            "category":"Cafe",
            "type":"Food & Drink"
        }
    ],
    "sg:phone":"+32 11 33 34 99",
    "sg:postcode":"3590",
    "sg:province":"Limburg",
    "sg:tags":[
        "snack-bars"
    ],
    "wof:name":"Karolien",
    "wof:placetype":"venue"
},
  "geometry": {"coordinates":[5.4182720184,50.9077224731],"type":"Point"}
}