{
  "type": "Feature",
  "properties": {
    "addr:full":"Eikenlaan 17 Beveren Oost-Vlaanderen 9120",
    "addr:housenumber":"17",
    "addr:postcode":"9120",
    "addr:street":"Eikenlaan",
    "iso:country":"BE",
    "sg:address":"Eikenlaan 17",
    "sg:city":"Beveren",
    "sg:orig_category":"Boekhouders",
    "sg:phone":"+32 3 775 18 25",
    "sg:postcode":"9120",
    "sg:province":"Oost-Vlaanderen",
    "wof:name":"Franky Vergauwen",
    "wof:placetype":"venue"
},
  "geometry": {"coordinates":[4.2777500153,51.2157402039],"type":"Point"}
}