{
  "type": "Feature",
  "properties": {
    "addr:full":"Koolmijnlaan 360-362 Beringen (beverlo) Limburg 3581",
    "addr:housenumber":"360-362",
    "addr:postcode":"3581",
    "addr:street":"Koolmijnlaan",
    "iso:country":"BE",
    "sg:address":"Koolmijnlaan 360-362",
    "sg:city":"Beringen (beverlo)",
    "sg:orig_category":"Non-Classified Establishments",
    "sg:phone":"+32 11 42 29 18",
    "sg:postcode":"3581",
    "sg:province":"Limburg",
    "wof:name":"Moons Herenkleding Nv",
    "wof:placetype":"venue"
},
  "geometry": {"coordinates":[5.2192339897,51.0776557922],"type":"Point"}
}