{
  "type": "Feature",
  "properties": {
    "iso:country":"BE",
    "sg:address":"Les Champs Servais 38",
    "sg:city":"Bouillon",
    "sg:orig_category":"Maisons de vacances",
    "sg:phone":"+32 61 46 64 19",
    "sg:postcode":"6830",
    "sg:province":"Luxembourg",
    "wof:name":"Le Champ Pommiers",
    "wof:placetype":"venue"
},
  "geometry": {"coordinates":[5.1459012032,49.81690979],"type":"Point"}
}