{
  "type": "Feature",
  "properties": {
    "addr:full":"Diepestraat 20 Oosterzele (balegem) Oost-Vlaanderen 9860",
    "addr:housenumber":"20",
    "addr:postcode":"9860",
    "addr:street":"Diepestraat",
    "iso:country":"BE",
    "sg:address":"Diepestraat 20",
    "sg:city":"Oosterzele (balegem)",
    "sg:classifiers":[
        {
            "category":"Health Services",
            "subcategory":"Doctor",
            "type":"Services"
        }
    ],
    "sg:phone":"+32 9 362 71 55",
    "sg:postcode":"9860",
    "sg:province":"Oost-Vlaanderen",
    "sg:tags":[
        "medicinephysicians",
        "surgeon"
    ],
    "wof:name":"De Breuck J",
    "wof:placetype":"venue"
},
  "geometry": {"coordinates":[3.8069839478,50.9159202576],"type":"Point"}
}