{
  "type": "Feature",
  "properties": {
    "addr:full":"Dranouterstraat 44 Heuvelland West-Vlaanderen 8950",
    "addr:housenumber":"44",
    "addr:postcode":"8950",
    "addr:street":"Dranouterstraat",
    "iso:country":"BE",
    "sg:address":"Dranouterstraat 44",
    "sg:city":"Heuvelland",
    "sg:orig_category":"Producteurs de l\u00e9gumes",
    "sg:phone":"+32 57 44 58 02",
    "sg:postcode":"8950",
    "sg:province":"West-Vlaanderen",
    "wof:name":"Aime Deconinck",
    "wof:placetype":"venue"
},
  "geometry": {"coordinates":[2.8055870533,50.7523956299],"type":"Point"}
}