{
  "type": "Feature",
  "properties": {
    "addr:full":"Avenue Georges-truffaut 42 Li\u00e8ge 1 (li\u00e8ge 2) Li\u00e8ge 4020",
    "addr:housenumber":"42;1;2",
    "addr:postcode":"4020",
    "addr:street":"Avenue Georges-Truffaut",
    "iso:country":"BE",
    "sg:address":"Avenue Georges-truffaut 42",
    "sg:city":"Li\u00e8ge 1 (li\u00e8ge 2)",
    "sg:classifiers":[
        {
            "category":"Retail",
            "subcategory":"Repair Shop",
            "type":"Services"
        }
    ],
    "sg:phone":"+32 4 345 93 11",
    "sg:postcode":"4020",
    "sg:province":"Li\u00e8ge",
    "sg:tags":[
        "radio",
        "television",
        "-",
        "maintenance"
    ],
    "wof:name":"Prodis Nv",
    "wof:placetype":"venue"
},
  "geometry": {"coordinates":[5.6110367775,50.6496429443],"type":"Point"}
}