{
  "type": "Feature",
  "properties": {
    "addr:full":"Chauss\u00c9e Brunehault 273 Binche Hainaut 7134",
    "addr:housenumber":"273",
    "addr:postcode":"7134",
    "addr:street":"Chausse\u0301E Brunehault",
    "iso:country":"BE",
    "sg:address":"Chauss\u00c9e Brunehault 273",
    "sg:city":"Binche",
    "sg:orig_category":"Boucheries",
    "sg:phone":"+32 64 33 22 35",
    "sg:postcode":"7134",
    "sg:province":"Hainaut",
    "wof:name":"Josef Marszalkowski",
    "wof:placetype":"venue"
},
  "geometry": {"coordinates":[4.1947951317,50.4320831299],"type":"Point"}
}