{
  "type": "Feature",
  "properties": {
    "iso:country":"BE",
    "sg:address":"Place De Pecq 1",
    "sg:city":"Pecq",
    "sg:orig_category":"S\u00e9curit\u00e9 sociale",
    "sg:phone":"+32 69 55 65 51",
    "sg:postcode":"7740",
    "sg:province":"Hainaut",
    "wof:name":"Union Travailleurs",
    "wof:placetype":"venue"
},
  "geometry": {"coordinates":[3.3387200832,50.6856994629],"type":"Point"}
}