{
  "type": "Feature",
  "properties": {
    "addr:full":"Avenue R\u00eave D'or 14 Box 14 La Louvi\u00e8re Hainaut 7100",
    "addr:housenumber":"14 box 14",
    "addr:postcode":"7100",
    "addr:street":"Avenue Re\u0302Ve D'Or",
    "iso:country":"BE",
    "sg:address":"Avenue R\u00eave D'or 14 Box 14",
    "sg:city":"La Louvi\u00e8re",
    "sg:classifiers":[
        {
            "category":"Real Estate",
            "subcategory":"Architect",
            "type":"Services"
        }
    ],
    "sg:phone":"+32 64 84 93 06",
    "sg:postcode":"7100",
    "sg:province":"Hainaut",
    "wof:name":"Nicod\u00e8me J-j",
    "wof:placetype":"venue"
},
  "geometry": {"coordinates":[4.171020031,50.4790992737],"type":"Point"}
}