{
  "type": "Feature",
  "properties": {
    "addr:full":"Rue J. Severijns 7 Quevy Hainaut 7040",
    "addr:housenumber":"7",
    "addr:postcode":"7040",
    "addr:street":"Rue J. Severijns;Hainaut",
    "iso:country":"BE",
    "sg:address":"Rue J. Severijns 7",
    "sg:city":"Quevy",
    "sg:orig_category":"Eleveurs de bovins",
    "sg:phone":"+32 65 56 85 14",
    "sg:postcode":"7040",
    "sg:province":"Hainaut",
    "wof:name":"Pierre Chleider",
    "wof:placetype":"venue"
},
  "geometry": {"coordinates":[3.8920910358,50.3529205322],"type":"Point"}
}