{
  "type": "Feature",
  "properties": {
    "addr:full":"Rue De Flandre 8 Brussel/bruxelles Bruxelles-Capitale 1000",
    "addr:housenumber":"8",
    "addr:postcode":"1000",
    "addr:street":"Rue De Flandre;/",
    "iso:country":"BE",
    "sg:address":"Rue De Flandre 8",
    "sg:city":"Brussel/bruxelles",
    "sg:classifiers":[
        {
            "category":"Restaurant",
            "type":"Food & Drink"
        }
    ],
    "sg:phone":"+32 2 511 79 36",
    "sg:postcode":"1000",
    "sg:province":"Bruxelles-Capitale",
    "wof:name":"La Iberica",
    "wof:placetype":"venue"
},
  "geometry": {"coordinates":[4.34689188,50.8506469727],"type":"Point"}
}