{
  "type": "Feature",
  "properties": {
    "addr:full":"Dieveldenstraat 7ba Rumst Antwerpen 2840",
    "addr:housenumber":"7ba",
    "addr:postcode":"2840",
    "addr:street":"Dieveldenstraat",
    "iso:country":"BE",
    "sg:address":"Dieveldenstraat 7ba",
    "sg:city":"Rumst",
    "sg:orig_category":"Groententeelt",
    "sg:phone":"+32 3 888 21 70",
    "sg:postcode":"2840",
    "sg:province":"Antwerpen",
    "wof:name":"Eddy Van Reeth",
    "wof:placetype":"venue"
},
  "geometry": {"coordinates":[4.4137358665,51.1091690063],"type":"Point"}
}