{
  "type": "Feature",
  "properties": {
    "iso:country":"BE",
    "sg:address":"Rue Provinciale 521",
    "sg:city":"Juprelle (fexhe-slins)",
    "sg:classifiers":[
        {
            "category":"Retail",
            "subcategory":"Auto Repair",
            "type":"Services"
        }
    ],
    "sg:phone":"+32 4 278 12 00",
    "sg:postcode":"4458",
    "sg:province":"Li\u00e8ge",
    "sg:tags":[
        "automobile-body"
    ],
    "wof:name":"G H Motors Sprl",
    "wof:placetype":"venue"
},
  "geometry": {"coordinates":[5.5669198036,50.7078514099],"type":"Point"}
}