{
  "type": "Feature",
  "properties": {
    "addr:full":"Avenue Des Marguerites 11 Wezembeek-oppem Vlaams-Brabant 1970",
    "addr:housenumber":"11",
    "addr:postcode":"1970",
    "addr:street":"Avenue Des Marguerites",
    "iso:country":"BE",
    "sg:address":"Avenue Des Marguerites 11",
    "sg:city":"Wezembeek-oppem",
    "sg:orig_category":"Enseignement maternel and primaire",
    "sg:phone":"+32 2 731 09 78",
    "sg:postcode":"1970",
    "sg:province":"Vlaams-Brabant",
    "wof:name":"Ecole Fondamentale Libre",
    "wof:placetype":"venue"
},
  "geometry": {"coordinates":[4.480779171,50.8416824341],"type":"Point"}
}