{
  "type": "Feature",
  "properties": {
    "addr:full":"Heirweg 84 Zulte Oost-Vlaanderen 9870",
    "addr:housenumber":"84",
    "addr:postcode":"9870",
    "addr:street":"Heirweg",
    "iso:country":"BE",
    "sg:address":"Heirweg 84",
    "sg:city":"Zulte",
    "sg:classifiers":[
        {
            "category":"Personal",
            "subcategory":"Beauty Salon",
            "type":"Services"
        }
    ],
    "sg:phone":"+32 9 388 91 42",
    "sg:postcode":"9870",
    "sg:province":"Oost-Vlaanderen",
    "sg:tags":[
        "de",
        "coiffure"
    ],
    "wof:name":"Marijke Bossuyt",
    "wof:placetype":"venue"
},
  "geometry": {"coordinates":[3.4631268978,50.9439888],"type":"Point"}
}