{
  "type": "Feature",
  "properties": {
    "addr:full":"Rue De La Laiterie 14 Durbuy (tohogne) Luxembourg 6941",
    "addr:housenumber":"14",
    "addr:postcode":"6941",
    "addr:street":"Rue De La Laiterie",
    "iso:country":"BE",
    "sg:address":"Rue De La Laiterie 14",
    "sg:city":"Durbuy (tohogne)",
    "sg:classifiers":[
        {
            "category":"Health Services",
            "subcategory":"Health Practitioner",
            "type":"Services"
        }
    ],
    "sg:phone":"+32 86 21 39 55",
    "sg:postcode":"6941",
    "sg:province":"Luxembourg",
    "sg:tags":[
        "physiotherapist"
    ],
    "wof:name":"Burniat G",
    "wof:placetype":"venue"
},
  "geometry": {"coordinates":[5.4827480316,50.3848762512],"type":"Point"}
}