{
  "type": "Feature",
  "properties": {
    "addr:full":"Rue De Bavay 46 Qu\u00e9vy (genly) Hainaut 7040",
    "addr:housenumber":"46",
    "addr:postcode":"7040",
    "addr:street":"Rue De Bavay",
    "iso:country":"BE",
    "sg:address":"Rue De Bavay 46",
    "sg:city":"Qu\u00e9vy (genly)",
    "sg:classifiers":[
        {
            "category":"Structure",
            "subcategory":"Building",
            "type":"Public Place"
        }
    ],
    "sg:phone":"+32 65 56 02 00",
    "sg:postcode":"7040",
    "sg:province":"Hainaut",
    "sg:tags":[
        "door"
    ],
    "wof:name":"Godart Ghislain Sprl",
    "wof:placetype":"venue"
},
  "geometry": {"coordinates":[3.9131720066,50.3935127258],"type":"Point"}
}