{
  "type": "Feature",
  "properties": {
    "iso:country":"BE",
    "sg:address":"Mechelbaan 99",
    "sg:city":"Sint-katelijne-waver",
    "sg:classifiers":[
        {
            "category":"Arena",
            "subcategory":"Sports Club",
            "type":"Entertainment"
        }
    ],
    "sg:phone":"+32 15 56 00 45",
    "sg:postcode":"2861",
    "sg:province":"Antwerpen",
    "sg:tags":[
        "de"
    ],
    "wof:name":"Waverse Badmintonclub",
    "wof:placetype":"venue"
},
  "geometry": {"coordinates":[4.5586800575,51.0541152954],"type":"Point"}
}