{
  "type": "Feature",
  "properties": {
    "iso:country":"BE",
    "sg:address":"Dreef 11",
    "sg:city":"Zomergem",
    "sg:orig_category":"Boucheries",
    "sg:phone":"+32 9 372 74 26",
    "sg:postcode":"9930",
    "sg:province":"Oost-Vlaanderen",
    "wof:name":"Johan Yde",
    "wof:placetype":"venue"
},
  "geometry": {"coordinates":[3.5619089603,51.1188087463],"type":"Point"}
}