{
  "type": "Feature",
  "properties": {
    "iso:country":"BE",
    "sg:address":"Hertstraat 31",
    "sg:city":"Hoeselt",
    "sg:orig_category":"Producteurs de l\u00e9gumes",
    "sg:phone":"+32 12 23 92 43",
    "sg:postcode":"3732",
    "sg:province":"Limburg",
    "wof:name":"Hilda Wouters",
    "wof:placetype":"venue"
},
  "geometry": {"coordinates":[5.448032856,50.8396186829],"type":"Point"}
}