{
  "type": "Feature",
  "properties": {
    "addr:full":"Haenhoutstraat 120 Destelbergen Oost-Vlaanderen 9070",
    "addr:housenumber":"120",
    "addr:postcode":"9070",
    "addr:street":"Haenhoutstraat",
    "iso:country":"BE",
    "sg:address":"Haenhoutstraat 120",
    "sg:city":"Destelbergen",
    "sg:classifiers":[
        {
            "category":"Health Services",
            "subcategory":"Health Practitioner",
            "type":"Services"
        }
    ],
    "sg:phone":"+32 9 355 91 35",
    "sg:postcode":"9070",
    "sg:province":"Oost-Vlaanderen",
    "sg:tags":[
        "physiotherapist"
    ],
    "wof:name":"Van Avermaet A",
    "wof:placetype":"venue"
},
  "geometry": {"coordinates":[3.8259959221,51.0691566467],"type":"Point"}
}