{
  "type": "Feature",
  "properties": {
    "iso:country":"BE",
    "sg:address":"Rue Moris 37",
    "sg:city":"Sint-gillis/saint-gilles",
    "sg:orig_category":"Jeux and jouets",
    "sg:phone":"+32 2 537 10 23",
    "sg:postcode":"1060",
    "sg:province":"Bruxelles-Capitale",
    "wof:name":"Heaumerie Du Casque D'or",
    "wof:placetype":"venue"
},
  "geometry": {"coordinates":[4.3512229919,50.824546814],"type":"Point"}
}