{
  "type": "Feature",
  "properties": {
    "addr:full":"Halsteenweg 59 Ninove Oost-Vlaanderen 9402",
    "addr:housenumber":"59",
    "addr:postcode":"9402",
    "addr:street":"Halsteenweg",
    "iso:country":"BE",
    "sg:address":"Halsteenweg 59",
    "sg:city":"Ninove",
    "sg:orig_category":"Eclairage et \u00e9quipements du foyer. Meubles D\u00e9taillants, Am\u00e9nagement de B\u00e2timents et de Cuisines",
    "sg:phone":"+32 54 32 10 47",
    "sg:postcode":"9402",
    "sg:province":"Oost-Vlaanderen",
    "wof:name":"De Plus Interieur",
    "wof:placetype":"venue"
},
  "geometry": {"coordinates":[4.04037714,50.8239440918],"type":"Point"}
}