{
  "type": "Feature",
  "properties": {
    "iso:country":"BE",
    "sg:address":"Rue De Limbourg 76-78",
    "sg:city":"Lontzen",
    "sg:orig_category":"Winkelinrichting and handelsuitrusting Gh",
    "sg:phone":"+32 87 88 24 41",
    "sg:postcode":"4710",
    "sg:province":"Li\u00e8ge",
    "wof:name":"Baguette H",
    "wof:placetype":"venue"
},
  "geometry": {"coordinates":[6.0046401024,50.6704711914],"type":"Point"}
}