{
  "type": "Feature",
  "properties": {
    "addr:full":"Orchideestraat 57 Oostakker Oost-Vlaanderen 9041",
    "addr:housenumber":"57",
    "addr:postcode":"9041",
    "addr:street":"Orchideestraat",
    "iso:country":"BE",
    "sg:address":"Orchideestraat 57",
    "sg:city":"Oostakker",
    "sg:orig_category":"Schilders",
    "sg:phone":"+32 475 43 26 30",
    "sg:postcode":"9041",
    "sg:province":"Oost-Vlaanderen",
    "wof:name":"Hubert Van Waes Schildersbedrijf",
    "wof:placetype":"venue"
},
  "geometry": {"coordinates":[3.797440052,51.0766410828],"type":"Point"}
}