{
  "type": "Feature",
  "properties": {
    "iso:country":"BE",
    "sg:address":"Baarle-frankrijkstraat 1",
    "sg:city":"Sint-martens-latem",
    "sg:classifiers":[
        {
            "category":"Restaurant",
            "type":"Food & Drink"
        }
    ],
    "sg:phone":"+32 9 282 33 65",
    "sg:postcode":"9830",
    "sg:province":"Oost-Vlaanderen",
    "wof:name":"D'oude Schuur",
    "wof:placetype":"venue"
},
  "geometry": {"coordinates":[3.6237690449,51.0241012573],"type":"Point"}
}