{
  "type": "Feature",
  "properties": {
    "iso:country":"BE",
    "sg:address":"Nervi\u00cbrslaan 65",
    "sg:city":"Etterbeek/etterbeek",
    "sg:orig_category":"Schoonmaakbedrijven and ongediertebestrijding",
    "sg:phone":"+32 2 735 99 22",
    "sg:postcode":"1040",
    "sg:province":"Bruxelles-Capitale",
    "wof:name":"C.c.a. Services",
    "wof:placetype":"venue"
},
  "geometry": {"coordinates":[4.3893079758,50.8385925293],"type":"Point"}
}