{
  "type": "Feature",
  "properties": {
    "iso:country":"BE",
    "sg:address":"Bizetplein 53",
    "sg:city":"Anderlecht",
    "sg:orig_category":"Diensten voor huisdieren",
    "sg:phone":"+32 2 520 14 18",
    "sg:postcode":"1070",
    "sg:province":"Bruxelles-Capitale",
    "wof:name":"Dog's Welkom",
    "wof:placetype":"venue"
},
  "geometry": {"coordinates":[4.2988371849,50.8254051208],"type":"Point"}
}