{
  "type": "Feature",
  "properties": {
    "iso:country":"BE",
    "sg:address":"Blauwkasteelstraat 124",
    "sg:city":"Oostende",
    "sg:classifiers":[
        {
            "category":"Cafe",
            "type":"Food & Drink"
        }
    ],
    "sg:phone":"+32 59 80 33 51",
    "sg:postcode":"8400",
    "sg:province":"West-Vlaanderen",
    "sg:tags":[
        "snack-bars"
    ],
    "wof:name":"Smoefelgatje",
    "wof:placetype":"venue"
},
  "geometry": {"coordinates":[2.9131469727,51.2164840698],"type":"Point"}
}