{
  "type": "Feature",
  "properties": {
    "addr:full":"Dr\u00e8ve Richelle 161 Box 3 Waterloo Brabant Wallon 1410",
    "addr:housenumber":"161;3",
    "addr:postcode":"1410",
    "addr:street":"Dre\u0300Ve Richelle;Box",
    "iso:country":"BE",
    "sg:address":"Dr\u00e8ve Richelle 161 Box 3",
    "sg:city":"Waterloo",
    "sg:classifiers":[
        {
            "category":"Manufacturing",
            "subcategory":"Metals",
            "type":"Manufacturing & Wholesale Goods"
        }
    ],
    "sg:phone":"+32 2 352 09 60",
    "sg:postcode":"1410",
    "sg:province":"Brabant Wallon",
    "sg:tags":[
        "non-ferrous",
        "-"
    ],
    "wof:name":"Sudamin Sa",
    "wof:placetype":"venue"
},
  "geometry": {"coordinates":[4.4104981422,50.7075843811],"type":"Point"}
}