{
  "type": "Feature",
  "properties": {
    "iso:country":"BE",
    "sg:address":"Blauwepoortstraat 5",
    "sg:city":"Heuvelland",
    "sg:orig_category":"Varkenskwekers",
    "sg:phone":"+32 57 44 50 83",
    "sg:postcode":"8953",
    "sg:province":"West-Vlaanderen",
    "wof:name":"Marcel Deklerck",
    "wof:placetype":"venue"
},
  "geometry": {"coordinates":[2.7501089573,50.7987823486],"type":"Point"}
}