{
  "type": "Feature",
  "properties": {
    "addr:full":"Avenue Des Traquets 5 Bruxelles (auderghem) Bruxelles-Capitale 1160",
    "addr:housenumber":"5",
    "addr:postcode":"1160",
    "addr:street":"Avenue Des Traquets",
    "iso:country":"BE",
    "sg:address":"Avenue Des Traquets 5",
    "sg:city":"Bruxelles (auderghem)",
    "sg:classifiers":[
        {
            "category":"Social Services",
            "subcategory":"Child Care",
            "type":"Services"
        }
    ],
    "sg:phone":"+32 2 660 74 03",
    "sg:postcode":"1160",
    "sg:province":"Bruxelles-Capitale",
    "sg:tags":[
        "baby",
        "nursery",
        "day",
        "sitting"
    ],
    "wof:name":"Comme Dans Un R\u00eave",
    "wof:placetype":"venue"
},
  "geometry": {"coordinates":[4.4145140648,50.8204154968],"type":"Point"}
}