{
  "type": "Feature",
  "properties": {
    "addr:full":"Anselmostraat 79 Antwerpen Antwerpen 2018",
    "addr:housenumber":"79",
    "addr:postcode":"2018",
    "addr:street":"Anselmostraat",
    "iso:country":"BE",
    "sg:address":"Anselmostraat 79",
    "sg:city":"Antwerpen",
    "sg:orig_category":"Avocats and conseillers juridiques",
    "sg:phone":"+32 3 238 64 04",
    "sg:postcode":"2018",
    "sg:province":"Antwerpen",
    "wof:name":"Fabienne Kusters",
    "wof:placetype":"venue"
},
  "geometry": {"coordinates":[4.4046440125,51.2056388855],"type":"Point"}
}