{
  "type": "Feature",
  "properties": {
    "addr:full":"Leireken 74 Merchtem Vlaams-Brabant 1785",
    "addr:housenumber":"74",
    "addr:postcode":"1785",
    "addr:street":"Leireken",
    "iso:country":"BE",
    "sg:address":"Leireken 74",
    "sg:city":"Merchtem",
    "sg:orig_category":"Schoenen",
    "sg:phone":"+32 52 37 67 08",
    "sg:postcode":"1785",
    "sg:province":"Vlaams-Brabant",
    "wof:name":"Bot En Bottin",
    "wof:placetype":"venue"
},
  "geometry": {"coordinates":[4.223405838,50.9819793701],"type":"Point"}
}