{
  "type": "Feature",
  "properties": {
    "addr:full":"Rue De 7e-d.i.-fran\u00c7aise 18 Virton Luxembourg 6760",
    "addr:housenumber":"18",
    "addr:postcode":"6760",
    "addr:street":"Rue De 7E-D.I.-Franc\u0327Aise",
    "iso:country":"BE",
    "sg:address":"Rue De 7e-d.i.-fran\u00c7aise 18",
    "sg:city":"Virton",
    "sg:orig_category":"Antiek",
    "sg:phone":"+32 63 57 97 11",
    "sg:postcode":"6760",
    "sg:province":"Luxembourg",
    "wof:name":"Marie-noelle Mouchout",
    "wof:placetype":"venue"
},
  "geometry": {"coordinates":[5.5347180367,49.5672607422],"type":"Point"}
}