{
  "type": "Feature",
  "properties": {
    "iso:country":"BE",
    "sg:address":"Stationsstraat 22",
    "sg:city":"Oud-heverlee",
    "sg:orig_category":"Banken and kredietinstellingen",
    "sg:phone":"+32 16 47 23 15",
    "sg:postcode":"3051",
    "sg:province":"Vlaams-Brabant",
    "wof:name":"Kbc",
    "wof:placetype":"venue"
},
  "geometry": {"coordinates":[4.6511011124,50.8008232117],"type":"Point"}
}