{
  "type": "Feature",
  "properties": {
    "addr:full":"Ren\u00c9 Declercqstraat 46 Sint-pieters-woluwe/woluwe-saint-pierre Bruxelles-Capitale 1150",
    "addr:housenumber":"46",
    "addr:postcode":"1150",
    "addr:street":"Rene\u0301 Declercqstraat;/",
    "iso:country":"BE",
    "sg:address":"Ren\u00c9 Declercqstraat 46",
    "sg:city":"Sint-pieters-woluwe/woluwe-saint-pierre",
    "sg:orig_category":"Verplichte sociale verzekeringen",
    "sg:phone":"+32 2 770 16 89",
    "sg:postcode":"1150",
    "sg:province":"Bruxelles-Capitale",
    "wof:name":"Mutualit\u00c9 Socialiste",
    "wof:placetype":"venue"
},
  "geometry": {"coordinates":[4.4317140579,50.8363800049],"type":"Point"}
}