{
  "type": "Feature",
  "properties": {
    "addr:full":"Koornbloemstraat 10 Anzegem West-Vlaanderen 8570",
    "addr:housenumber":"10",
    "addr:postcode":"8570",
    "addr:street":"Koornbloemstraat",
    "iso:country":"BE",
    "sg:address":"Koornbloemstraat 10",
    "sg:city":"Anzegem",
    "sg:orig_category":"Peinture. Rev\u00eatements pour sols and murs",
    "sg:phone":"+32 56 77 64 67",
    "sg:postcode":"8570",
    "sg:province":"West-Vlaanderen",
    "wof:name":"Kristin Vandeghinste",
    "wof:placetype":"venue"
},
  "geometry": {"coordinates":[3.4141480923,50.8365631104],"type":"Point"}
}