{
  "type": "Feature",
  "properties": {
    "addr:full":"Drongensesteenweg 68 Gent Oost-Vlaanderen 9000",
    "addr:housenumber":"68",
    "addr:postcode":"9000",
    "addr:street":"Drongensesteenweg;Oost-Vlaanderen",
    "iso:country":"BE",
    "sg:address":"Drongensesteenweg 68",
    "sg:city":"Gent",
    "sg:classifiers":[
        {
            "category":"Utilities",
            "subcategory":"Telephone",
            "type":"Services"
        }
    ],
    "sg:phone":"+32 9 227 54 29",
    "sg:postcode":"9000",
    "sg:province":"Oost-Vlaanderen",
    "sg:tags":[
        "-",
        "internet"
    ],
    "wof:name":"Fruyt D",
    "wof:placetype":"venue"
},
  "geometry": {"coordinates":[3.6994559765,51.0568122864],"type":"Point"}
}