{
  "type": "Feature",
  "properties": {
    "addr:full":"Lange Munteplein 8 Kortrijk West-Vlaanderen 8500",
    "addr:housenumber":"8",
    "addr:postcode":"8500",
    "addr:street":"Lange Munteplein",
    "iso:country":"BE",
    "sg:address":"Lange Munteplein 8",
    "sg:city":"Kortrijk",
    "sg:classifiers":[
        {
            "category":"Parking",
            "subcategory":"Bicycle",
            "type":"Transportation"
        }
    ],
    "sg:phone":"+32 56 22 55 72",
    "sg:postcode":"8500",
    "sg:province":"West-Vlaanderen",
    "sg:tags":[
        "chiropodist"
    ],
    "wof:name":"Mieke",
    "wof:placetype":"venue"
},
  "geometry": {"coordinates":[3.299612999,50.8110427856],"type":"Point"}
}