{
  "type": "Feature",
  "properties": {
    "iso:country":"BE",
    "sg:address":"Heidedreef 5",
    "sg:city":"Malle",
    "sg:orig_category":"Architecten",
    "sg:phone":"+32 3 312 33 07",
    "sg:postcode":"2390",
    "sg:province":"Antwerpen",
    "wof:name":"Els Gepts",
    "wof:placetype":"venue"
},
  "geometry": {"coordinates":[4.7400360107,51.2931442261],"type":"Point"}
}