{
  "type": "Feature",
  "properties": {
    "iso:country":"BE",
    "sg:address":"Sint-antoniusstraat 17a",
    "sg:city":"Lendelede",
    "sg:classifiers":[
        {
            "category":"Real Estate",
            "subcategory":"Surveying",
            "type":"Services"
        }
    ],
    "sg:phone":"+32 56 32 54 98",
    "sg:postcode":"8860",
    "sg:province":"West-Vlaanderen",
    "sg:tags":[
        "surveyor",
        "land"
    ],
    "wof:name":"Spiessens Christ",
    "wof:placetype":"venue"
},
  "geometry": {"coordinates":[3.2075359821,50.875705719],"type":"Point"}
}