{
  "type": "Feature",
  "properties": {
    "iso:country":"BE",
    "sg:address":"Schoon Verblijflaan 42",
    "sg:city":"Ukkel/uccle",
    "sg:orig_category":"Architecten",
    "sg:phone":"+32 2 375 37 91",
    "sg:postcode":"1180",
    "sg:province":"Bruxelles-Capitale",
    "wof:name":"Jean-claude Van Hoof",
    "wof:placetype":"venue"
},
  "geometry": {"coordinates":[4.3678689003,50.8086662292],"type":"Point"}
}