{
  "type": "Feature",
  "properties": {
    "iso:country":"BE",
    "sg:address":"Otegemstraat 156",
    "sg:city":"Zwevegem",
    "sg:orig_category":"Brood, gebak and snoepgoed",
    "sg:phone":"+32 56 75 51 98",
    "sg:postcode":"8550",
    "sg:province":"West-Vlaanderen",
    "wof:name":"Bakkerij Gaby",
    "wof:placetype":"venue"
},
  "geometry": {"coordinates":[3.3441839218,50.8146514893],"type":"Point"}
}