{
  "type": "Feature",
  "properties": {
    "iso:country":"BE",
    "sg:address":"Hellestraat 23",
    "sg:city":"Boechout",
    "sg:orig_category":"Boekhouders",
    "sg:phone":"+32 3 454 37 02",
    "sg:postcode":"2530",
    "sg:province":"Antwerpen",
    "wof:name":"Hermine De Bruyn",
    "wof:placetype":"venue"
},
  "geometry": {"coordinates":[4.5062828064,51.1654319763],"type":"Point"}
}