{
  "type": "Feature",
  "properties": {
    "addr:full":"Hogeweg 24 Menen West-Vlaanderen 8930",
    "addr:housenumber":"24",
    "addr:postcode":"8930",
    "addr:street":"Hogeweg",
    "iso:country":"BE",
    "sg:address":"Hogeweg 24",
    "sg:city":"Menen",
    "sg:orig_category":"Installatie van houten of kunststof schrijnwerk",
    "sg:phone":"+32 56 51 46 72",
    "sg:postcode":"8930",
    "sg:province":"West-Vlaanderen",
    "wof:name":"Rene Denolf",
    "wof:placetype":"venue"
},
  "geometry": {"coordinates":[3.1098198891,50.7958831787],"type":"Point"}
}