{
  "type": "Feature",
  "properties": {
    "addr:full":"Chauss\u00c9e D'ottenbourg 123 Wavre Brabant Wallon 1300",
    "addr:housenumber":"123;1300",
    "addr:street":"Chausse\u0301E D'Ottenbourg",
    "iso:country":"BE",
    "sg:address":"Chauss\u00c9e D'ottenbourg 123",
    "sg:city":"Wavre",
    "sg:orig_category":"Architecten",
    "sg:phone":"+32 10 22 25 89",
    "sg:postcode":"1300",
    "sg:province":"Brabant Wallon",
    "wof:name":"Jean-philippe Annys",
    "wof:placetype":"venue"
},
  "geometry": {"coordinates":[4.6155891418,50.7241859436],"type":"Point"}
}