{
  "type": "Feature",
  "properties": {
    "addr:full":"Rue Robesse 1 Charleroi Hainaut 6041",
    "addr:housenumber":"1",
    "addr:postcode":"6041",
    "addr:street":"Rue Robesse;Hainaut",
    "iso:country":"BE",
    "sg:address":"Rue Robesse 1",
    "sg:city":"Charleroi",
    "sg:classifiers":[
        {
            "category":"Autos & Motor Vehicles",
            "subcategory":"Fuel & Gas Station",
            "type":"Retail Goods"
        }
    ],
    "sg:phone":"+32 71 85 23 08",
    "sg:postcode":"6041",
    "sg:province":"Hainaut",
    "sg:tags":[
        "stations-service",
        "carburants"
    ],
    "wof:name":"Esso",
    "wof:placetype":"venue"
},
  "geometry": {"coordinates":[4.4314317703,50.4685935974],"type":"Point"}
}