{
  "type": "Feature",
  "properties": {
    "addr:full":"Halledorp 67 Zoersel Antwerpen 2980",
    "addr:housenumber":"67",
    "addr:postcode":"2980",
    "addr:street":"Halledorp",
    "iso:country":"BE",
    "sg:address":"Halledorp 67",
    "sg:city":"Zoersel",
    "sg:orig_category":"Biblioth\u00e8ques and archives publiques",
    "sg:phone":"+32 3 384 02 52",
    "sg:postcode":"2980",
    "sg:province":"Antwerpen",
    "wof:name":"Gemeentelijke Bibliotheek",
    "wof:placetype":"venue"
},
  "geometry": {"coordinates":[4.6449980736,51.2401161194],"type":"Point"}
}