{
  "type": "Feature",
  "properties": {
    "iso:country":"BE",
    "sg:address":"Steenstraat 2",
    "sg:city":"Borgloon",
    "sg:classifiers":[
        {
            "category":"Bars & Pubs",
            "type":"Food & Drink"
        }
    ],
    "sg:phone":"+32 12 74 12 27",
    "sg:postcode":"3840",
    "sg:province":"Limburg",
    "wof:name":"Bruin Kafeeke ('t)",
    "wof:placetype":"venue"
},
  "geometry": {"coordinates":[5.3452382088,50.8017272949],"type":"Point"}
}