{
  "type": "Feature",
  "properties": {
    "iso:country":"BE",
    "sg:address":"Place De L\u00b4eglise 0",
    "sg:city":"Marche En Famenne",
    "sg:orig_category":"R\u00e9parations d'horloges, montres and bijoux. R\u00e9paration and restauration de meubles",
    "sg:phone":"+32 84 22 19 22",
    "sg:postcode":"6900",
    "sg:province":"Luxembourg",
    "wof:name":"Mr Stevens Ma\u00cetre Horloger Restaurateur",
    "wof:placetype":"venue"
},
  "geometry": {"coordinates":[5.3430151939,50.2273483276],"type":"Point"}
}