{
  "type": "Feature",
  "properties": {
    "iso:country":"BE",
    "sg:address":"Avenue Des Anciens Combattants 63",
    "sg:city":"Bruxelles (evere)",
    "sg:classifiers":[
        {
            "category":"Professional",
            "subcategory":"Testing Lab",
            "type":"Services"
        }
    ],
    "sg:phone":"+32 2 705 30 48",
    "sg:postcode":"1140",
    "sg:province":"Bruxelles-Capitale",
    "sg:tags":[
        "laboratory",
        "medical"
    ],
    "wof:name":"Laboratoire Analyses M\u00e9dicales",
    "wof:placetype":"venue"
},
  "geometry": {"coordinates":[4.4120821953,50.861530304],"type":"Point"}
}