{
  "type": "Feature",
  "properties": {
    "iso:country":"BE",
    "sg:address":"St-truidensestw 368",
    "sg:city":"Tongeren (groot)",
    "sg:classifiers":[
        {
            "category":"Personal",
            "subcategory":"Beauty Salon",
            "type":"Services"
        }
    ],
    "sg:phone":"+32 12 24 15 85",
    "sg:postcode":"3700",
    "sg:province":"Limburg",
    "sg:tags":[
        "de",
        "coiffure"
    ],
    "wof:name":"Anita Coiffure",
    "wof:placetype":"venue"
},
  "geometry": {"coordinates":[5.4636240005,50.7807197571],"type":"Point"}
}