{
  "type": "Feature",
  "properties": {
    "addr:full":"Onledemeersstraat 5 Roeselare West-Vlaanderen 8800",
    "addr:housenumber":"5",
    "addr:postcode":"8800",
    "addr:street":"Onledemeersstraat",
    "iso:country":"BE",
    "sg:address":"Onledemeersstraat 5",
    "sg:city":"Roeselare",
    "sg:orig_category":"Installation de menuiserie en bois and plastique",
    "sg:phone":"+32 51 22 48 24",
    "sg:postcode":"8800",
    "sg:province":"West-Vlaanderen",
    "wof:name":"Vervaeke D",
    "wof:placetype":"venue"
},
  "geometry": {"coordinates":[3.1404540539,50.9691123962],"type":"Point"}
}