{
  "type": "Feature",
  "properties": {
    "addr:full":"Rue Des Cr\u00c8ches 1 Profondeville Namur 5170",
    "addr:housenumber":"1",
    "addr:postcode":"5170",
    "addr:street":"Rue Des Cre\u0300Ches",
    "iso:country":"BE",
    "sg:address":"Rue Des Cr\u00c8ches 1",
    "sg:city":"Profondeville",
    "sg:orig_category":"Enseignement maternel and primaire",
    "sg:phone":"+32 81 43 31 51",
    "sg:postcode":"5170",
    "sg:province":"Namur",
    "wof:name":"E.f.l. St.joseph",
    "wof:placetype":"venue"
},
  "geometry": {"coordinates":[4.8674049377,50.3786392212],"type":"Point"}
}