{
  "type": "Feature",
  "properties": {
    "addr:full":"Sentier De La Dr\u00c8ve 48 Anderlecht Bruxelles-Capitale 1070",
    "addr:housenumber":"48",
    "addr:postcode":"1070",
    "addr:street":"Sentier De La Dre\u0300Ve",
    "iso:country":"BE",
    "sg:address":"Sentier De La Dr\u00c8ve 48",
    "sg:city":"Anderlecht",
    "sg:orig_category":"M\u00e9decins and sp\u00e9cialistes",
    "sg:phone":"+32 2 526 70 16",
    "sg:postcode":"1070",
    "sg:province":"Bruxelles-Capitale",
    "wof:name":"Steven Bessemans",
    "wof:placetype":"venue"
},
  "geometry": {"coordinates":[4.29190588,50.8143196106],"type":"Point"}
}