{
  "type": "Feature",
  "properties": {
    "iso:country":"BE",
    "sg:address":"Steurenambachtstraat 22",
    "sg:city":"Kortrijk (bissegem)",
    "sg:classifiers":[
        {
            "category":"Personal",
            "subcategory":"Nail Salon",
            "type":"Services"
        }
    ],
    "sg:phone":"+32 56 37 12 75",
    "sg:postcode":"8501",
    "sg:province":"West-Vlaanderen",
    "sg:tags":[
        "pedicure"
    ],
    "wof:name":"Vandenbroucke H",
    "wof:placetype":"venue"
},
  "geometry": {"coordinates":[3.2287700176,50.8295860291],"type":"Point"}
}