{
  "type": "Feature",
  "properties": {
    "iso:country":"BE",
    "sg:address":"Mechelsesteenweg 715",
    "sg:city":"Herent",
    "sg:orig_category":"Herstellingen motorfietsen Motorfietsen",
    "sg:phone":"+32 16 20 61 66",
    "sg:postcode":"3020",
    "sg:province":"Vlaams-Brabant",
    "wof:name":"Atelier O.k.",
    "wof:placetype":"venue"
},
  "geometry": {"coordinates":[4.6537661552,50.9169197083],"type":"Point"}
}