{
  "type": "Feature",
  "properties": {
    "iso:country":"BE",
    "sg:address":"Ooststraat 56",
    "sg:city":"Veurne",
    "sg:orig_category":"Herenkledingzaken Verhuur textielartikelen and schoenen",
    "sg:phone":"+32 58 31 11 53",
    "sg:postcode":"8630",
    "sg:province":"West-Vlaanderen",
    "wof:name":"Huis Paula",
    "wof:placetype":"venue"
},
  "geometry": {"coordinates":[2.6655449867,51.0729866028],"type":"Point"}
}