{
  "type": "Feature",
  "properties": {
    "addr:full":"Avenue Albert 29 Bruxelles (forest) Bruxelles-Capitale 1190",
    "addr:housenumber":"29",
    "addr:postcode":"1190",
    "addr:street":"Avenue Albert",
    "iso:country":"BE",
    "sg:address":"Avenue Albert 29",
    "sg:city":"Bruxelles (forest)",
    "sg:classifiers":[
        {
            "category":"Real Estate",
            "subcategory":"Real Estate Services",
            "type":"Services"
        }
    ],
    "sg:phone":"+32 2 344 57 52",
    "sg:postcode":"1190",
    "sg:province":"Bruxelles-Capitale",
    "wof:name":"Unie Der Immobilien Beroepen Van Belgie-(uib)",
    "wof:placetype":"venue"
},
  "geometry": {"coordinates":[4.3433179855,50.8210144043],"type":"Point"}
}