{
  "type": "Feature",
  "properties": {
    "iso:country":"BE",
    "sg:address":"Chauss\u00c9e De Ch\u00c2telet 247",
    "sg:city":"Charleroi",
    "sg:orig_category":"Elektrische installaties voor woningen Huishoudapparaten, televisies and radio's",
    "sg:phone":"+32 71 38 37 92",
    "sg:postcode":"6060",
    "sg:province":"Hainaut",
    "wof:name":"Biuso",
    "wof:placetype":"venue"
},
  "geometry": {"coordinates":[4.4880981445,50.4251937866],"type":"Point"}
}