{
  "type": "Feature",
  "properties": {
    "addr:full":"Guido Gezellestraat 12 Boom Antwerpen 2850",
    "addr:housenumber":"12",
    "addr:postcode":"2850",
    "addr:street":"Guido Gezellestraat",
    "iso:country":"BE",
    "sg:address":"Guido Gezellestraat 12",
    "sg:city":"Boom",
    "sg:classifiers":[
        {
            "category":"Professional",
            "subcategory":"Secretarial Services",
            "type":"Services"
        }
    ],
    "sg:phone":"+32 3 844 19 63",
    "sg:postcode":"2850",
    "sg:province":"Antwerpen",
    "sg:tags":[
        "-",
        "wordprocessing"
    ],
    "wof:name":"Van De Velde K",
    "wof:placetype":"venue"
},
  "geometry": {"coordinates":[4.3729162216,51.0950813293],"type":"Point"}
}