{
  "type": "Feature",
  "properties": {
    "iso:country":"BE",
    "sg:address":"Beekstraat 21",
    "sg:city":"Niel",
    "sg:orig_category":"Rev\u00eatements de sols and murs",
    "sg:phone":"+32 3 844 06 75",
    "sg:postcode":"2845",
    "sg:province":"Antwerpen",
    "wof:name":"Parketvloeren Pintens",
    "wof:placetype":"venue"
},
  "geometry": {"coordinates":[4.3320598602,51.1154899597],"type":"Point"}
}