{
  "type": "Feature",
  "properties": {
    "iso:country":"BE",
    "sg:address":"Rue De Fayembois 97",
    "sg:city":"Beyne-heusay",
    "sg:classifiers":[
        {
            "category":"Insurance",
            "subcategory":"Insurance Agent",
            "type":"Services"
        }
    ],
    "sg:phone":"+32 4 367 29 65",
    "sg:postcode":"4610",
    "sg:province":"Li\u00e8ge",
    "sg:tags":[
        "verzekeringsmakelaars",
        "expert"
    ],
    "wof:name":"Bureau Cuvelier",
    "wof:placetype":"venue"
},
  "geometry": {"coordinates":[5.6464891434,50.6276779175],"type":"Point"}
}