{
  "type": "Feature",
  "properties": {
    "iso:country":"BE",
    "sg:address":"Churchilllaan 22",
    "sg:city":"Schoten",
    "sg:classifiers":[
        {
            "category":"Personal",
            "subcategory":"Barber",
            "type":"Services"
        }
    ],
    "sg:phone":"+32 3 658 49 01",
    "sg:postcode":"2900",
    "sg:province":"Antwerpen",
    "sg:tags":[
        "gentleman",
        "salon",
        "-",
        "hairdressing"
    ],
    "wof:name":"Lacroix",
    "wof:placetype":"venue"
},
  "geometry": {"coordinates":[4.4961681366,51.2507591248],"type":"Point"}
}