{
  "type": "Feature",
  "properties": {
    "addr:full":"Rue De La Royaut\u00c9 37 Brussel/bruxelles Bruxelles-Capitale 1020",
    "addr:housenumber":"37",
    "addr:postcode":"1020",
    "addr:street":"Rue De La Royaute\u0301;/",
    "iso:country":"BE",
    "sg:address":"Rue De La Royaut\u00c9 37",
    "sg:city":"Brussel/bruxelles",
    "sg:orig_category":"M\u00e9decins and sp\u00e9cialistes",
    "sg:phone":"+32 2 426 64 53",
    "sg:postcode":"1020",
    "sg:province":"Bruxelles-Capitale",
    "wof:name":"Brigitte Piette",
    "wof:placetype":"venue"
},
  "geometry": {"coordinates":[4.3526968956,50.8767547607],"type":"Point"}
}