{
  "type": "Feature",
  "properties": {
    "iso:country":"BE",
    "sg:address":"Quai Des Vicinaux",
    "sg:city":"Tournai",
    "sg:classifiers":[
        {
            "category":"Sports & Exercise",
            "subcategory":"Ice Rink",
            "type":"Entertainment"
        }
    ],
    "sg:phone":"+32 69 22 76 58",
    "sg:postcode":"7500",
    "sg:province":"Hainaut",
    "sg:tags":[
        "skating"
    ],
    "wof:name":"Patinoire (la)",
    "wof:placetype":"venue"
},
  "geometry": {"coordinates":[3.3797500134,50.6182289124],"type":"Point"}
}