{
  "type": "Feature",
  "properties": {
    "iso:country":"BE",
    "sg:address":"Rue Maximilien Wattelar 68",
    "sg:city":"Charleroi",
    "sg:orig_category":"Pharmaciens",
    "sg:phone":"+32 71 35 04 41",
    "sg:postcode":"6040",
    "sg:province":"Hainaut",
    "wof:name":"Pharmacie Vilain",
    "wof:placetype":"venue"
},
  "geometry": {"coordinates":[4.4172739983,50.4437179565],"type":"Point"}
}