{
  "type": "Feature",
  "properties": {
    "addr:full":"Collegelaan 46 Bornem Antwerpen 2880",
    "addr:housenumber":"46",
    "addr:postcode":"2880",
    "addr:street":"Collegelaan",
    "iso:country":"BE",
    "sg:address":"Collegelaan 46",
    "sg:city":"Bornem",
    "sg:orig_category":"Belastingconsulenten Diverse juridische dienstverlening",
    "sg:phone":"+32 3 889 23 62",
    "sg:postcode":"2880",
    "sg:province":"Antwerpen",
    "wof:name":"Vp Management",
    "wof:placetype":"venue"
},
  "geometry": {"coordinates":[4.2258529663,51.090839386],"type":"Point"}
}