{
  "type": "Feature",
  "properties": {
    "iso:country":"BE",
    "sg:address":"Molenstraat 171",
    "sg:city":"Heist-op-den-berg",
    "sg:orig_category":"Loodgieterij, verwarming and sanitaire installaties",
    "sg:phone":"+32 15 24 89 04",
    "sg:postcode":"2220",
    "sg:province":"Antwerpen",
    "wof:name":"Dupont Sanitair",
    "wof:placetype":"venue"
},
  "geometry": {"coordinates":[4.7249279022,51.0829048157],"type":"Point"}
}