{
  "type": "Feature",
  "properties": {
    "iso:country":"BE",
    "sg:address":"Bodegemstraat 76",
    "sg:city":"Dilbeek",
    "sg:orig_category":"M\u00e9decins and sp\u00e9cialistes",
    "sg:phone":"+32 2 569 75 18",
    "sg:postcode":"1700",
    "sg:province":"Vlaams-Brabant",
    "wof:name":"Stefan De Brandt",
    "wof:placetype":"venue"
},
  "geometry": {"coordinates":[4.237112999,50.8449745178],"type":"Point"}
}