{
  "type": "Feature",
  "properties": {
    "addr:full":"Walbekestraat 4 Jabbeke West-Vlaanderen 8490",
    "addr:housenumber":"4",
    "addr:postcode":"8490",
    "addr:street":"Walbekestraat",
    "iso:country":"BE",
    "sg:address":"Walbekestraat 4",
    "sg:city":"Jabbeke",
    "sg:orig_category":"G\u00e9om\u00e8tres",
    "sg:phone":"+32 50 81 34 41",
    "sg:postcode":"8490",
    "sg:province":"West-Vlaanderen",
    "wof:name":"R. Vanoverschelde",
    "wof:placetype":"venue"
},
  "geometry": {"coordinates":[3.1021850109,51.1771697998],"type":"Point"}
}