{
  "type": "Feature",
  "properties": {
    "addr:full":"Castertstraat 3 Menen (rekkem) West-Vlaanderen 8930",
    "addr:housenumber":"3",
    "addr:postcode":"8930",
    "addr:street":"Castertstraat",
    "iso:country":"BE",
    "sg:address":"Castertstraat 3",
    "sg:city":"Menen (rekkem)",
    "sg:classifiers":[
        {
            "category":"Retail",
            "subcategory":"Repair Shop",
            "type":"Services"
        }
    ],
    "sg:phone":"+32 56 41 49 75",
    "sg:postcode":"8930",
    "sg:province":"West-Vlaanderen",
    "sg:tags":[
        "upholsterer"
    ],
    "wof:name":"Claus D",
    "wof:placetype":"venue"
},
  "geometry": {"coordinates":[3.1848120689,50.7662658691],"type":"Point"}
}