{
  "type": "Feature",
  "properties": {
    "iso:country":"BE",
    "sg:address":"Centrum Zuid",
    "sg:city":"Houthalen",
    "sg:classifiers":[
        {
            "category":"Building & Trades",
            "subcategory":"Construction",
            "type":"Services"
        }
    ],
    "sg:phone":"+32 11 59 91 70",
    "sg:postcode":"3530",
    "sg:province":"Limburg",
    "sg:tags":[
        "roofing",
        "material",
        "-"
    ],
    "wof:name":"Onduline Benelux",
    "wof:placetype":"venue"
},
  "geometry": {"coordinates":[5.3667750359,51.0225105286],"type":"Point"}
}