{
  "type": "Feature",
  "properties": {
    "addr:full":"Diepstraat 67 Hasselt (kuringen) Limburg 3511",
    "addr:housenumber":"67",
    "addr:postcode":"3511",
    "addr:street":"Diepstraat",
    "iso:country":"BE",
    "sg:address":"Diepstraat 67",
    "sg:city":"Hasselt (kuringen)",
    "sg:classifiers":[
        {
            "category":"Personal",
            "subcategory":"Beauty Salon",
            "type":"Services"
        }
    ],
    "sg:phone":"+32 11 25 10 03",
    "sg:postcode":"3511",
    "sg:province":"Limburg",
    "wof:name":"Atelier De Beaute-vanreppelen",
    "wof:placetype":"venue"
},
  "geometry": {"coordinates":[5.3043560982,50.9438438416],"type":"Point"}
}