{
  "type": "Feature",
  "properties": {
    "addr:full":"Rue Abb\u00e9 Pollart 20 Flobecq Hainaut 7880",
    "addr:housenumber":"20",
    "addr:postcode":"7880",
    "addr:street":"Rue Abbe\u0301 Pollart;Hainaut",
    "iso:country":"BE",
    "sg:address":"Rue Abb\u00e9 Pollart 20",
    "sg:city":"Flobecq",
    "sg:classifiers":[
        {
            "category":"Home & Garden",
            "subcategory":"Hardware",
            "type":"Retail Goods"
        }
    ],
    "sg:phone":"+32 68 44 88 89",
    "sg:postcode":"7880",
    "sg:province":"Hainaut",
    "sg:tags":[
        "gate",
        "opener",
        "door",
        "automatic"
    ],
    "wof:name":"E.m.t.",
    "wof:placetype":"venue"
},
  "geometry": {"coordinates":[3.7391319275,50.7386283875],"type":"Point"}
}