{
  "type": "Feature",
  "properties": {
    "addr:full":"Rue De L'ancienne Place 3 Brunehaut (laplaigne) Hainaut 7622",
    "addr:housenumber":"3",
    "addr:postcode":"7622",
    "addr:street":"Rue De L'Ancienne Place;Laplaigne Hainaut",
    "iso:country":"BE",
    "sg:address":"Rue De L'ancienne Place 3",
    "sg:city":"Brunehaut (laplaigne)",
    "sg:classifiers":[
        {
            "category":"Health Services",
            "subcategory":"Nursing And Care Facility",
            "type":"Services"
        }
    ],
    "sg:phone":"+32 69 34 67 67",
    "sg:postcode":"7622",
    "sg:province":"Hainaut",
    "sg:tags":[
        "home"
    ],
    "wof:name":"Wilfart Nathalie",
    "wof:placetype":"venue"
},
  "geometry": {"coordinates":[3.4467000961,50.5229797363],"type":"Point"}
}