{
  "type": "Feature",
  "properties": {
    "iso:country":"BE",
    "sg:address":"Rue Du Haut Bois 46",
    "sg:city":"Mons",
    "sg:classifiers":[
        {
            "category":"Professional",
            "subcategory":"Lawyer & Legal Services",
            "type":"Services"
        }
    ],
    "sg:phone":"+32 65 31 79 55",
    "sg:postcode":"7000",
    "sg:province":"Hainaut",
    "wof:name":"Sipido Y",
    "wof:placetype":"venue"
},
  "geometry": {"coordinates":[3.9553411007,50.4532470703],"type":"Point"}
}