{
  "type": "Feature",
  "properties": {
    "iso:country":"BE",
    "sg:address":"Rijksweg 568",
    "sg:city":"Maasmechelen",
    "sg:classifiers":[
        {
            "category":"Bars & Pubs",
            "subcategory":"Nightclub",
            "type":"Food & Drink"
        }
    ],
    "sg:phone":"+32 89 76 32 80",
    "sg:postcode":"3630",
    "sg:province":"Limburg",
    "wof:name":"Diamonds Club",
    "wof:placetype":"venue"
},
  "geometry": {"coordinates":[5.6942400932,50.956161499],"type":"Point"}
}