{
  "type": "Feature",
  "properties": {
    "addr:full":"Chauss\u00c9e De March\u00c9 940 Namur Namur 5100",
    "addr:housenumber":"940",
    "addr:postcode":"5100",
    "addr:street":"Chausse\u0301E De Marche\u0301",
    "iso:country":"BE",
    "sg:address":"Chauss\u00c9e De March\u00c9 940",
    "sg:city":"Namur",
    "sg:orig_category":"Stations-service and carburants. V\u00e9hicules automobiles",
    "sg:phone":"+32 81 40 27 67",
    "sg:postcode":"5100",
    "sg:province":"Namur",
    "wof:name":"C.w.a.",
    "wof:placetype":"venue"
},
  "geometry": {"coordinates":[4.8713750839,50.4566345215],"type":"Point"}
}