{
  "type": "Feature",
  "properties": {
    "addr:full":"Rue De Bettincourt 86 Waremme Li\u00e8ge 4300",
    "addr:housenumber":"86",
    "addr:postcode":"4300",
    "addr:street":"Rue De Bettincourt",
    "iso:country":"BE",
    "sg:address":"Rue De Bettincourt 86",
    "sg:city":"Waremme",
    "sg:orig_category":"Location de v\u00e9hicules sauf voitures. D\u00e9taillants en pi\u00e8ces and accessoires de voitures",
    "sg:phone":"+32 19 32 33 47",
    "sg:postcode":"4300",
    "sg:province":"Li\u00e8ge",
    "wof:name":"Lejeune",
    "wof:placetype":"venue"
},
  "geometry": {"coordinates":[5.2344927788,50.7130012512],"type":"Point"}
}