{
  "type": "Feature",
  "properties": {
    "addr:full":"Assenedesteenweg 136 Zelzate Oost-Vlaanderen 9060",
    "addr:housenumber":"136",
    "addr:postcode":"9060",
    "addr:street":"Assenedesteenweg",
    "iso:country":"BE",
    "sg:address":"Assenedesteenweg 136",
    "sg:city":"Zelzate",
    "sg:orig_category":"Parfumeries. Instituts de beaut\u00e9",
    "sg:phone":"+32 9 344 72 64",
    "sg:postcode":"9060",
    "sg:province":"Oost-Vlaanderen",
    "wof:name":"Instituut Lady",
    "wof:placetype":"venue"
},
  "geometry": {"coordinates":[3.7864561081,51.2018432617],"type":"Point"}
}