{
  "type": "Feature",
  "properties": {
    "iso:country":"BE",
    "sg:address":"Kasteelstraat 25",
    "sg:city":"Antwerpen",
    "sg:classifiers":[
        {
            "category":"Health Services",
            "subcategory":"Health Practitioner",
            "type":"Services"
        }
    ],
    "sg:phone":"+32 3 237 93 23",
    "sg:postcode":"2000",
    "sg:province":"Antwerpen",
    "sg:tags":[
        "physiotherapist"
    ],
    "wof:name":"Boelen Erwin",
    "wof:placetype":"venue"
},
  "geometry": {"coordinates":[4.3905072212,51.2074928284],"type":"Point"}
}