{
  "type": "Feature",
  "properties": {
    "addr:full":"St-amandsesteenweg 44 Bornem Antwerpen 2880",
    "addr:housenumber":"44",
    "addr:postcode":"2880",
    "addr:street":"St-Amandsesteenweg",
    "iso:country":"BE",
    "sg:address":"St-amandsesteenweg 44",
    "sg:city":"Bornem",
    "sg:classifiers":[
        {
            "category":"Fast Food",
            "type":"Food & Drink"
        }
    ],
    "sg:phone":"+32 3 889 71 63",
    "sg:postcode":"2880",
    "sg:province":"Antwerpen",
    "sg:tags":[
        "\u00c0",
        "emporter",
        "restaurants"
    ],
    "wof:name":"Frituur Denis",
    "wof:placetype":"venue"
},
  "geometry": {"coordinates":[4.2313609123,51.0944595337],"type":"Point"}
}