{
  "type": "Feature",
  "properties": {
    "iso:country":"BE",
    "sg:address":"Zonienwoudlaan 8",
    "sg:city":"Beersel",
    "sg:classifiers":[
        {
            "category":"Arena",
            "subcategory":"Sports Club",
            "type":"Entertainment"
        }
    ],
    "sg:phone":"+32 2 381 08 59",
    "sg:postcode":"1452",
    "sg:tags":[
        "terrain",
        "hors",
        "de",
        "installation",
        "sportifs"
    ],
    "wof:name":"S V Alsemberg",
    "wof:placetype":"venue"
},
  "geometry": {"coordinates":[4.6712799072,51.0575218201],"type":"Point"}
}