{
  "type": "Feature",
  "properties": {
    "addr:full":"Peperstraat 6 Kortrijk (heule) West-Vlaanderen 8501",
    "addr:housenumber":"6",
    "addr:postcode":"8501",
    "addr:street":"Peperstraat",
    "iso:country":"BE",
    "sg:address":"Peperstraat 6",
    "sg:city":"Kortrijk (heule)",
    "sg:classifiers":[
        {
            "category":"Cafe",
            "type":"Food & Drink"
        }
    ],
    "sg:phone":"+32 56 37 47 07",
    "sg:postcode":"8501",
    "sg:province":"West-Vlaanderen",
    "sg:tags":[
        "snack-bars"
    ],
    "wof:name":"Matton",
    "wof:placetype":"venue"
},
  "geometry": {"coordinates":[3.2345559597,50.8428421021],"type":"Point"}
}