{
  "type": "Feature",
  "properties": {
    "addr:full":"Millesteenstraat 26 Moorslede (dadizele) West-Vlaanderen 8890",
    "addr:housenumber":"26",
    "addr:postcode":"8890",
    "addr:street":"Millesteenstraat",
    "iso:country":"BE",
    "sg:address":"Millesteenstraat 26",
    "sg:city":"Moorslede (dadizele)",
    "sg:classifiers":[
        {
            "category":"Personal",
            "subcategory":"Nail Salon",
            "type":"Services"
        }
    ],
    "sg:phone":"+32 56 50 61 33",
    "sg:postcode":"8890",
    "sg:province":"West-Vlaanderen",
    "sg:tags":[
        "pedicure"
    ],
    "wof:name":"Roelens K",
    "wof:placetype":"venue"
},
  "geometry": {"coordinates":[3.1047389507,50.8486289978],"type":"Point"}
}