{
  "type": "Feature",
  "properties": {
    "addr:full":"Koning Albertlaan 198 Brussel/bruxelles Bruxelles-Capitale 1120",
    "addr:housenumber":"198",
    "addr:postcode":"1120",
    "addr:street":"Koning Albertlaan;/",
    "iso:country":"BE",
    "sg:address":"Koning Albertlaan 198",
    "sg:city":"Brussel/bruxelles",
    "sg:orig_category":"Schoonheidssalons",
    "sg:phone":"+32 2 268 48 67",
    "sg:postcode":"1120",
    "sg:province":"Bruxelles-Capitale",
    "wof:name":"P\u00c9dic. Le Thi Ngoc Suong",
    "wof:placetype":"venue"
},
  "geometry": {"coordinates":[4.3982248306,50.9002685547],"type":"Point"}
}