{
  "type": "Feature",
  "properties": {
    "addr:full":"Rue De Verviers 9 Bruxelles Bruxelles-Capitale 1000",
    "addr:housenumber":"9",
    "addr:postcode":"1000",
    "addr:street":"Rue De Verviers",
    "iso:country":"BE",
    "sg:address":"Rue De Verviers 9",
    "sg:city":"Bruxelles",
    "sg:classifiers":[
        {
            "category":"Health Services",
            "subcategory":"Doctor",
            "type":"Services"
        }
    ],
    "sg:phone":"+32 2 230 82 34",
    "sg:postcode":"1000",
    "sg:province":"Bruxelles-Capitale",
    "sg:tags":[
        "medicinephysicians",
        "surgeon"
    ],
    "wof:name":"Debauche M",
    "wof:placetype":"venue"
},
  "geometry": {"coordinates":[4.3740501404,50.8477401733],"type":"Point"}
}