{
  "type": "Feature",
  "properties": {
    "addr:full":"Stationsstraat 4b2 De Panne West-Vlaanderen 8660",
    "addr:housenumber":"4b2",
    "addr:postcode":"8660",
    "addr:street":"Stationsstraat",
    "iso:country":"BE",
    "sg:address":"Stationsstraat 4b2",
    "sg:city":"De Panne",
    "sg:classifiers":[
        {
            "category":"Personal",
            "subcategory":"Beauty Salon",
            "type":"Services"
        }
    ],
    "sg:phone":"+32 58 41 19 38",
    "sg:postcode":"8660",
    "sg:province":"West-Vlaanderen",
    "sg:tags":[
        "de",
        "coiffure"
    ],
    "wof:name":"Katrien Calcoen",
    "wof:placetype":"venue"
},
  "geometry": {"coordinates":[2.6015679836,51.0777244568],"type":"Point"}
}