{
  "type": "Feature",
  "properties": {
    "addr:full":"Itali\u00eblei 223 Antwerpen Antwerpen 2000",
    "addr:housenumber":"223",
    "addr:postcode":"2000",
    "addr:street":"Italie\u0308Lei",
    "iso:country":"BE",
    "sg:address":"Itali\u00eblei 223",
    "sg:city":"Antwerpen",
    "sg:classifiers":[
        {
            "category":"Personal",
            "subcategory":"Beauty Salon",
            "type":"Services"
        }
    ],
    "sg:phone":"+32 3 233 40 89",
    "sg:postcode":"2000",
    "sg:province":"Antwerpen",
    "wof:name":"Biodroga",
    "wof:placetype":"venue"
},
  "geometry": {"coordinates":[4.4171519279,51.2210578918],"type":"Point"}
}