{
  "type": "Feature",
  "properties": {
    "iso:country":"BE",
    "sg:address":"Kapelleberg 60",
    "sg:city":"Laakdal (eindhout)",
    "sg:classifiers":[
        {
            "category":"Fast Food",
            "type":"Food & Drink"
        }
    ],
    "sg:phone":"+32 14 86 60 03",
    "sg:postcode":"2430",
    "sg:province":"Antwerpen",
    "sg:tags":[
        "fried",
        "stand",
        "potato"
    ],
    "wof:name":"Door En Dora",
    "wof:placetype":"venue"
},
  "geometry": {"coordinates":[5.0007429123,51.0994338989],"type":"Point"}
}