{
  "type": "Feature",
  "properties": {
    "iso:country":"BE",
    "sg:address":"Grootbroekstraat 46",
    "sg:city":"Kinrooi",
    "sg:orig_category":"Vakantiedorpen",
    "sg:phone":"+32 89 70 17 94",
    "sg:postcode":"3640",
    "sg:province":"Limburg",
    "wof:name":"Woutershof-de Welp",
    "wof:placetype":"venue"
},
  "geometry": {"coordinates":[5.6990399361,51.1601448059],"type":"Point"}
}