{
  "type": "Feature",
  "properties": {
    "iso:country":"BE",
    "sg:address":"A. Bliecklaan 36",
    "sg:city":"Koksijde",
    "sg:classifiers":[
        {
            "category":"Banks & Credit Unions",
            "subcategory":"Investment Brokerage",
            "type":"Services"
        }
    ],
    "sg:phone":"+32 58 51 83 87",
    "sg:postcode":"8670",
    "sg:province":"West-Vlaanderen",
    "sg:tags":[
        "pension"
    ],
    "wof:name":"Denise Claes-hooghe",
    "wof:placetype":"venue"
},
  "geometry": {"coordinates":[2.6320919991,51.1158752441],"type":"Point"}
}