{
  "type": "Feature",
  "properties": {
    "iso:country":"BE",
    "sg:address":"Rue De Najauge 39",
    "sg:city":"Viroinval (maz\u00e9e)",
    "sg:classifiers":[
        {
            "category":"Autos & Motor Vehicles",
            "subcategory":"Fuel & Gas Station",
            "type":"Retail Goods"
        }
    ],
    "sg:phone":"+32 60 39 10 03",
    "sg:postcode":"5670",
    "sg:province":"Namur",
    "wof:name":"Station Du Viroin",
    "wof:placetype":"venue"
},
  "geometry": {"coordinates":[4.6987771988,50.0937042236],"type":"Point"}
}