{
  "type": "Feature",
  "properties": {
    "iso:country":"BE",
    "sg:address":"Volaardestraat 59",
    "sg:city":"Dendermonde",
    "sg:orig_category":"Rundveehouders",
    "sg:phone":"+32 52 41 44 63",
    "sg:postcode":"9200",
    "sg:province":"Oost-Vlaanderen",
    "wof:name":"Hedwig De Visscher",
    "wof:placetype":"venue"
},
  "geometry": {"coordinates":[4.1321802139,51.0199699402],"type":"Point"}
}