{
  "type": "Feature",
  "properties": {
    "iso:country":"BE",
    "sg:address":"Geluwestraat 2",
    "sg:city":"Moorslede (dadizele)",
    "sg:classifiers":[
        {
            "category":"Juice Bar",
            "subcategory":"None",
            "type":"Food & Drink"
        }
    ],
    "sg:phone":"+32 56 50 94 51",
    "sg:postcode":"8890",
    "sg:province":"West-Vlaanderen",
    "sg:tags":[
        "fruit",
        "syrup"
    ],
    "wof:name":"Eco Apple",
    "wof:placetype":"venue"
},
  "geometry": {"coordinates":[3.0901710987,50.847278595],"type":"Point"}
}