{
  "type": "Feature",
  "properties": {
    "iso:country":"BE",
    "sg:address":"Rue De Boingt 6",
    "sg:city":"Heron",
    "sg:orig_category":"Eleveurs de bovins",
    "sg:phone":"+32 85 71 11 57",
    "sg:postcode":"4217",
    "sg:province":"Li\u00e8ge",
    "wof:name":"Lucienne Bourgeois",
    "wof:placetype":"venue"
},
  "geometry": {"coordinates":[5.0950379372,50.5626411438],"type":"Point"}
}