{
  "type": "Feature",
  "properties": {
    "addr:full":"Moerdijkstraat 17 Gistel (moere) West-Vlaanderen 8470",
    "addr:housenumber":"17",
    "addr:postcode":"8470",
    "addr:street":"Moerdijkstraat",
    "iso:country":"BE",
    "sg:address":"Moerdijkstraat 17",
    "sg:city":"Gistel (moere)",
    "sg:classifiers":[
        {
            "category":"Building & Trades",
            "subcategory":"Landscaping Services",
            "type":"Services"
        }
    ],
    "sg:phone":"+32 59 27 81 89",
    "sg:postcode":"8470",
    "sg:province":"West-Vlaanderen",
    "sg:tags":[
        "nurseryman"
    ],
    "wof:name":"De Moerdijk",
    "wof:placetype":"venue"
},
  "geometry": {"coordinates":[2.9863090515,51.1337966919],"type":"Point"}
}