{
  "type": "Feature",
  "properties": {
    "addr:full":"Stoofstraat 32 Brussel/bruxelles Bruxelles-Capitale 1000",
    "addr:housenumber":"32",
    "addr:postcode":"1000",
    "addr:street":"Stoofstraat;/",
    "iso:country":"BE",
    "sg:address":"Stoofstraat 32",
    "sg:city":"Brussel/bruxelles",
    "sg:orig_category":"Geschenken and souvenirs Verlichting and huishoudartikelen",
    "sg:phone":"+32 2 512 63 58",
    "sg:postcode":"1000",
    "sg:province":"Bruxelles-Capitale",
    "wof:name":"Bettary Shop",
    "wof:placetype":"venue"
},
  "geometry": {"coordinates":[4.3505110741,50.8452072144],"type":"Point"}
}