{
  "type": "Feature",
  "properties": {
    "addr:full":"Kasteellaan 445 Gent Oost-Vlaanderen 9000",
    "addr:housenumber":"445",
    "addr:postcode":"9000",
    "addr:street":"Kasteellaan;Oost-Vlaanderen",
    "iso:country":"BE",
    "sg:address":"Kasteellaan 445",
    "sg:city":"Gent",
    "sg:classifiers":[
        {
            "category":"Food & Beverages",
            "subcategory":"Specialty",
            "type":"Retail Goods"
        }
    ],
    "sg:phone":"+32 9 233 16 43",
    "sg:postcode":"9000",
    "sg:province":"Oost-Vlaanderen",
    "sg:tags":[
        "health",
        "dietary",
        "-",
        "biological"
    ],
    "wof:name":"Eurohemp",
    "wof:placetype":"venue"
},
  "geometry": {"coordinates":[3.7386620045,51.0556488037],"type":"Point"}
}