{
  "type": "Feature",
  "properties": {
    "iso:country":"BE",
    "sg:address":"Rue Des P\u00c9pini\u00c8res 22",
    "sg:city":"Brunehaut",
    "sg:classifiers":[
        {
            "category":"Fast Food",
            "type":"Food & Drink"
        }
    ],
    "sg:phone":"+32 69 34 54 96",
    "sg:postcode":"7621",
    "sg:province":"Hainaut",
    "sg:tags":[
        "meeneem",
        "restaurant"
    ],
    "wof:name":"Pizza Maison",
    "wof:placetype":"venue"
},
  "geometry": {"coordinates":[3.3889729977,50.520778656],"type":"Point"}
}