{
  "type": "Feature",
  "properties": {
    "addr:full":"Chemin Des Vignerons 78 Namur (w\u00e9pion) Namur 5100",
    "addr:housenumber":"78",
    "addr:postcode":"5100",
    "addr:street":"Chemin Des Vignerons",
    "iso:country":"BE",
    "sg:address":"Chemin Des Vignerons 78",
    "sg:city":"Namur (w\u00e9pion)",
    "sg:classifiers":[
        {
            "category":"Professional",
            "subcategory":"Accounting & Tax Preparation",
            "type":"Services"
        }
    ],
    "sg:phone":"+32 81 21 55 91",
    "sg:postcode":"5100",
    "sg:province":"Namur",
    "sg:tags":[
        "accountant"
    ],
    "wof:name":"Smal F",
    "wof:placetype":"venue"
},
  "geometry": {"coordinates":[4.8567881584,50.4237174988],"type":"Point"}
}