{
  "type": "Feature",
  "properties": {
    "iso:country":"BE",
    "sg:address":"Rue Paul Reuter 17",
    "sg:city":"Arlon",
    "sg:classifiers":[
        {
            "category":"Bars & Pubs",
            "type":"Food & Drink"
        }
    ],
    "sg:phone":"+32 63 22 93 62",
    "sg:postcode":"6700",
    "sg:province":"Luxembourg",
    "wof:name":"Argana",
    "wof:placetype":"venue"
},
  "geometry": {"coordinates":[5.8173599243,49.6832809448],"type":"Point"}
}