{
  "type": "Feature",
  "properties": {
    "iso:country":"BE",
    "sg:address":"Eug. De Grootelaan 48",
    "sg:city":"Houthulst",
    "sg:classifiers":[
        {
            "category":"Home & Garden",
            "subcategory":"Household Appliances",
            "type":"Retail Goods"
        }
    ],
    "sg:phone":"+32 51 70 19 68",
    "sg:postcode":"8650",
    "sg:province":"West-Vlaanderen",
    "sg:tags":[
        "housewares",
        "-"
    ],
    "wof:name":"Amc Bvba",
    "wof:placetype":"venue"
},
  "geometry": {"coordinates":[2.953715086,50.9759101868],"type":"Point"}
}