{
  "type": "Feature",
  "properties": {
    "iso:country":"BE",
    "sg:address":"Chauss\u00e9e De Bruxelles 90-96",
    "sg:city":"Charleroi (jumet)",
    "sg:classifiers":[
        {
            "category":"Shopping",
            "subcategory":"Bicycles & Sporting Goods",
            "type":"Retail Goods"
        }
    ],
    "sg:phone":"+32 71 34 13 96",
    "sg:postcode":"6040",
    "sg:province":"Hainaut",
    "sg:tags":[
        "tyre"
    ],
    "wof:name":"Pecheny Pneus",
    "wof:placetype":"venue"
},
  "geometry": {"coordinates":[4.4392590523,50.4379959106],"type":"Point"}
}