{
  "type": "Feature",
  "properties": {
    "iso:country":"BE",
    "sg:address":"Rue De L'aun\u00e9e 18",
    "sg:city":"Nassogne (forri\u00e8res)",
    "sg:classifiers":[
        {
            "category":"Freight",
            "type":"Transportation"
        }
    ],
    "sg:phone":"+32 84 21 35 17",
    "sg:postcode":"6953",
    "sg:province":"Luxembourg",
    "sg:tags":[
        "-",
        "transport"
    ],
    "wof:name":"Pierard Sprl",
    "wof:placetype":"venue"
},
  "geometry": {"coordinates":[5.2948379517,50.1346588135],"type":"Point"}
}