{
  "type": "Feature",
  "properties": {
    "addr:full":"Rue Du Pairay 105 Seraing Li\u00e8ge 4100",
    "addr:housenumber":"105",
    "addr:postcode":"4100",
    "addr:street":"Rue Du Pairay",
    "iso:country":"BE",
    "sg:address":"Rue Du Pairay 105",
    "sg:city":"Seraing",
    "sg:classifiers":[
        {
            "category":"Personal",
            "subcategory":"Beauty Salon",
            "type":"Services"
        }
    ],
    "sg:phone":"+32 4 338 29 51",
    "sg:postcode":"4100",
    "sg:province":"Li\u00e8ge",
    "sg:tags":[
        "lady",
        "-",
        "hairdressing"
    ],
    "wof:name":"Sabine Coiffure",
    "wof:placetype":"venue"
},
  "geometry": {"coordinates":[5.5105118752,50.5962104797],"type":"Point"}
}