{
  "type": "Feature",
  "properties": {
    "iso:country":"BE",
    "sg:address":"Albert Serreynstraat 28",
    "sg:city":"Brugge",
    "sg:orig_category":"Verhuisdiensten",
    "sg:phone":"+32 50 38 72 54",
    "sg:postcode":"8200",
    "sg:province":"West-Vlaanderen",
    "wof:name":"Watteeuw Fernand",
    "wof:placetype":"venue"
},
  "geometry": {"coordinates":[3.2009658813,51.194934845],"type":"Point"}
}