{
  "type": "Feature",
  "properties": {
    "iso:country":"BE",
    "sg:address":"Vinkenbaan 21",
    "sg:city":"Steenokkerzeel",
    "sg:orig_category":"Gespecialiseerde residenti\u00eble bouw",
    "sg:phone":"+32 2 751 92 52",
    "sg:postcode":"1820",
    "sg:province":"Vlaams-Brabant",
    "wof:name":"Hedi Bey",
    "wof:placetype":"venue"
},
  "geometry": {"coordinates":[4.4931650162,50.9288635254],"type":"Point"}
}