{
  "type": "Feature",
  "properties": {
    "iso:country":"BE",
    "sg:address":"Statiestraat 129",
    "sg:city":"Zwijndrecht",
    "sg:classifiers":[
        {
            "category":"Cafe",
            "type":"Food & Drink"
        }
    ],
    "sg:phone":"+32 3 254 02 71",
    "sg:postcode":"2070",
    "sg:province":"Antwerpen",
    "sg:tags":[
        "snack-bars"
    ],
    "wof:name":"Peronneke ('t)",
    "wof:placetype":"venue"
},
  "geometry": {"coordinates":[4.3292031288,51.215171814],"type":"Point"}
}