{
  "type": "Feature",
  "properties": {
    "iso:country":"BE",
    "sg:address":"Kapel Ter Rustestraat 32",
    "sg:city":"Deerlijk",
    "sg:classifiers":[
        {
            "category":"Manufacturing",
            "subcategory":"Tools & Machinery",
            "type":"Manufacturing & Wholesale Goods"
        }
    ],
    "sg:phone":"+32 56 70 15 76",
    "sg:postcode":"8540",
    "sg:province":"West-Vlaanderen",
    "sg:tags":[
        "diamond"
    ],
    "wof:name":"Lefebre Technics",
    "wof:placetype":"venue"
},
  "geometry": {"coordinates":[3.3531479836,50.8511428833],"type":"Point"}
}