{
  "type": "Feature",
  "properties": {
    "iso:country":"BE",
    "sg:address":"Parc Industriel 27",
    "sg:city":"Braine-le-ch\u00e2teau (wauthier-braine)",
    "sg:orig_category":"Non-Classified Establishments",
    "sg:phone":"+32 2 367 86 15",
    "sg:postcode":"1440",
    "sg:province":"Brabant Wallon",
    "wof:name":"Lignes & Profils",
    "wof:placetype":"venue"
},
  "geometry": {"coordinates":[4.318198204,50.6881065369],"type":"Point"}
}