{
  "type": "Feature",
  "properties": {
    "iso:country":"BE",
    "sg:address":"Hauptstrasse 8",
    "sg:city":"Sankt Vith",
    "sg:classifiers":[
        {
            "category":"Shopping",
            "subcategory":"Florist",
            "type":"Retail Goods"
        }
    ],
    "sg:phone":"+32 80 22 61 95",
    "sg:postcode":"4780",
    "sg:province":"Li\u00e8ge",
    "wof:name":"Blumenhaus A Pip",
    "wof:placetype":"venue"
},
  "geometry": {"coordinates":[6.1271810532,50.2794532776],"type":"Point"}
}