{
  "type": "Feature",
  "properties": {
    "addr:full":"Rue Fontaine D'amour 23 Bruxelles (schaerbeek) Bruxelles-Capitale 1030",
    "addr:housenumber":"23",
    "addr:postcode":"1030",
    "addr:street":"Rue Fontaine D'Amour",
    "iso:country":"BE",
    "sg:address":"Rue Fontaine D'amour 23",
    "sg:city":"Bruxelles (schaerbeek)",
    "sg:classifiers":[
        {
            "category":"Real Estate",
            "subcategory":"Architect",
            "type":"Services"
        }
    ],
    "sg:phone":"+32 2 243 05 29",
    "sg:postcode":"1030",
    "sg:province":"Bruxelles-Capitale",
    "wof:name":"Scheldeman T",
    "wof:placetype":"venue"
},
  "geometry": {"coordinates":[4.3830947876,50.8604660034],"type":"Point"}
}