{
  "type": "Feature",
  "properties": {
    "addr:full":"Mechelsesteenweg 358 Dendermonde Oost-Vlaanderen 9200",
    "addr:housenumber":"358",
    "addr:postcode":"9200",
    "addr:street":"Mechelsesteenweg;Oost-Vlaanderen",
    "iso:country":"BE",
    "sg:address":"Mechelsesteenweg 358",
    "sg:city":"Dendermonde",
    "sg:classifiers":[
        {
            "category":"Professional",
            "subcategory":"Lawyer & Legal Services",
            "type":"Services"
        }
    ],
    "sg:phone":"+32 52 22 13 68",
    "sg:postcode":"9200",
    "sg:province":"Oost-Vlaanderen",
    "wof:name":"Baro K",
    "wof:placetype":"venue"
},
  "geometry": {"coordinates":[4.1206498146,51.0363006592],"type":"Point"}
}