{
  "type": "Feature",
  "properties": {
    "addr:full":"Route De Wavre 131 Hannut Li\u00e8ge 4280",
    "addr:housenumber":"131",
    "addr:postcode":"4280",
    "addr:street":"Route De Wavre",
    "iso:country":"BE",
    "sg:address":"Route De Wavre 131",
    "sg:city":"Hannut",
    "sg:orig_category":"Artsen and specialisten",
    "sg:phone":"+32 19 51 17 68",
    "sg:postcode":"4280",
    "sg:province":"Li\u00e8ge",
    "wof:name":"Jean-fr\u00c9d\u00c9ric De Schrynmakers",
    "wof:placetype":"venue"
},
  "geometry": {"coordinates":[5.0427150726,50.6707382202],"type":"Point"}
}