{
  "type": "Feature",
  "properties": {
    "addr:full":"Quai De Flandre 6 Charleroi Hainaut 6000",
    "addr:housenumber":"6",
    "addr:postcode":"6000",
    "addr:street":"Quai De Flandre;Hainaut",
    "iso:country":"BE",
    "sg:address":"Quai De Flandre 6",
    "sg:city":"Charleroi",
    "sg:orig_category":"Ordinateurs and \u00e9quipement informatique",
    "sg:phone":"+32 71 70 23 62",
    "sg:postcode":"6000",
    "sg:province":"Hainaut",
    "wof:name":"Fe. Interactive",
    "wof:placetype":"venue"
},
  "geometry": {"coordinates":[4.4381780624,50.4064064026],"type":"Point"}
}