{
  "type": "Feature",
  "properties": {
    "iso:country":"BE",
    "sg:address":"Rue Des Juifs 47",
    "sg:city":"Chievres",
    "sg:orig_category":"Tuinen",
    "sg:phone":"+32 69 68 60 35",
    "sg:postcode":"7950",
    "sg:province":"Hainaut",
    "wof:name":"Etablissement Clement Gery",
    "wof:placetype":"venue"
},
  "geometry": {"coordinates":[3.7605600357,50.5427856445],"type":"Point"}
}