{
  "type": "Feature",
  "properties": {
    "iso:country":"BE",
    "sg:address":"Houthulstseweg 57",
    "sg:city":"Langemark-poelkapelle",
    "sg:orig_category":"GROENTEN AND FRUIT Groententeelt",
    "sg:phone":"+32 57 48 86 85",
    "sg:postcode":"8920",
    "sg:province":"West-Vlaanderen",
    "wof:name":"Andre Hoste",
    "wof:placetype":"venue"
},
  "geometry": {"coordinates":[2.9435329437,50.9305801392],"type":"Point"}
}