{
  "type": "Feature",
  "properties": {
    "iso:country":"BE",
    "sg:address":"Winkelstraat 7",
    "sg:city":"Kortenaken",
    "sg:orig_category":"Rundveehouders",
    "sg:phone":"+32 11 58 76 59",
    "sg:postcode":"3470",
    "sg:province":"Vlaams-Brabant",
    "wof:name":"Guido Roosen",
    "wof:placetype":"venue"
},
  "geometry": {"coordinates":[5.048058033,50.8608398438],"type":"Point"}
}