{
  "type": "Feature",
  "properties": {
    "iso:country":"BE",
    "sg:address":"Rue Des Clarisses 32",
    "sg:city":"Li\u00e8ge 1",
    "sg:classifiers":[
        {
            "category":"Fast Food",
            "type":"Food & Drink"
        }
    ],
    "sg:phone":"+32 4 223 33 33",
    "sg:postcode":"4000",
    "sg:province":"Li\u00e8ge",
    "sg:tags":[
        "fried",
        "stand",
        "potato"
    ],
    "wof:name":"Yildiz (chez)",
    "wof:placetype":"venue"
},
  "geometry": {"coordinates":[5.5716118813,50.6389541626],"type":"Point"}
}