{
  "type": "Feature",
  "properties": {
    "iso:country":"BE",
    "sg:address":"Rue Bay Bonnet 32",
    "sg:city":"Fl\u00e9ron",
    "sg:classifiers":[
        {
            "category":"Building & Trades",
            "subcategory":"Construction",
            "type":"Services"
        }
    ],
    "sg:phone":"+32 4 355 17 84",
    "sg:postcode":"4620",
    "sg:province":"Li\u00e8ge",
    "sg:tags":[
        "ecological"
    ],
    "wof:name":"Etudes & Vie-benoit Louppe",
    "wof:placetype":"venue"
},
  "geometry": {"coordinates":[5.6928682327,50.606552124],"type":"Point"}
}