{
  "type": "Feature",
  "properties": {
    "addr:full":"Bril 14 Lier Antwerpen 2500",
    "addr:housenumber":"14",
    "addr:postcode":"2500",
    "addr:street":"Bril",
    "iso:country":"BE",
    "sg:address":"Bril 14",
    "sg:city":"Lier",
    "sg:classifiers":[
        {
            "category":"Health Services",
            "subcategory":"Dentist",
            "type":"Services"
        }
    ],
    "sg:phone":"+32 3 489 29 74",
    "sg:postcode":"2500",
    "sg:province":"Antwerpen",
    "wof:name":"Garmyn Ellen",
    "wof:placetype":"venue"
},
  "geometry": {"coordinates":[4.5725169182,51.1290779114],"type":"Point"}
}