{
  "type": "Feature",
  "properties": {
    "addr:full":"Geelsebaan 60 Tessenderlo Limburg 3980",
    "addr:housenumber":"60",
    "addr:postcode":"3980",
    "addr:street":"Geelsebaan",
    "iso:country":"BE",
    "sg:address":"Geelsebaan 60",
    "sg:city":"Tessenderlo",
    "sg:orig_category":"Art and fournitures artistiques",
    "sg:phone":"+32 13 66 17 26",
    "sg:postcode":"3980",
    "sg:province":"Limburg",
    "wof:name":"Kadra",
    "wof:placetype":"venue"
},
  "geometry": {"coordinates":[5.0842862129,51.0722541809],"type":"Point"}
}