{
  "type": "Feature",
  "properties": {
    "addr:full":"Marktstraat 46 Nieuwpoort West-Vlaanderen 8620",
    "addr:housenumber":"46",
    "addr:postcode":"8620",
    "addr:street":"Marktstraat",
    "iso:country":"BE",
    "sg:address":"Marktstraat 46",
    "sg:city":"Nieuwpoort",
    "sg:classifiers":[
        {
            "category":"Shopping",
            "subcategory":"Florist",
            "type":"Retail Goods"
        }
    ],
    "sg:phone":"+32 58 23 67 40",
    "sg:postcode":"8620",
    "sg:province":"West-Vlaanderen",
    "wof:name":"Markant",
    "wof:placetype":"venue"
},
  "geometry": {"coordinates":[2.7521779537,51.1301841736],"type":"Point"}
}