{
  "type": "Feature",
  "properties": {
    "addr:full":"Edmond Laponstraat 54 Oostende West-Vlaanderen 8400",
    "addr:housenumber":"54",
    "addr:postcode":"8400",
    "addr:street":"Edmond Laponstraat",
    "iso:country":"BE",
    "sg:address":"Edmond Laponstraat 54",
    "sg:city":"Oostende",
    "sg:orig_category":"Boucheries",
    "sg:phone":"+32 59 70 67 85",
    "sg:postcode":"8400",
    "sg:province":"West-Vlaanderen",
    "wof:name":"Slagerij Vanhullebusch",
    "wof:placetype":"venue"
},
  "geometry": {"coordinates":[2.9073638916,51.2257385254],"type":"Point"}
}