{
  "type": "Feature",
  "properties": {
    "addr:full":"Vlaamse Gaaistraat 2 Lommel Limburg 3920",
    "addr:housenumber":"2",
    "addr:postcode":"3920",
    "addr:street":"Vlaamse Gaaistraat",
    "iso:country":"BE",
    "sg:address":"Vlaamse Gaaistraat 2",
    "sg:city":"Lommel",
    "sg:orig_category":"Woningbouw",
    "sg:phone":"+32 11 55 10 41",
    "sg:postcode":"3920",
    "sg:province":"Limburg",
    "wof:name":"Samenaankoop & Bouwco\u00d6rd. Profit",
    "wof:placetype":"venue"
},
  "geometry": {"coordinates":[5.2971220016,51.2184677124],"type":"Point"}
}