{
  "type": "Feature",
  "properties": {
    "iso:country":"BE",
    "sg:address":"J. Demolderlaan 16",
    "sg:city":"De Panne",
    "sg:orig_category":"Installation \u00e9lectrique industrielle. Location d'appareils audio-visuels. Electrom\u00e9nager, t\u00e9l\u00e9vision",
    "sg:phone":"+32 58 41 35 92",
    "sg:postcode":"8660",
    "sg:province":"West-Vlaanderen",
    "wof:name":"Inter West Alarm",
    "wof:placetype":"venue"
},
  "geometry": {"coordinates":[2.5933420658,51.1005325317],"type":"Point"}
}