{
  "type": "Feature",
  "properties": {
    "addr:full":"Sint-rochusstraat 42 Halle Vlaams-Brabant 1500",
    "addr:housenumber":"42",
    "addr:postcode":"1500",
    "addr:street":"Sint-Rochusstraat",
    "iso:country":"BE",
    "sg:address":"Sint-rochusstraat 42",
    "sg:city":"Halle",
    "sg:classifiers":[
        {
            "category":"Health Services",
            "subcategory":"Health Practitioner",
            "type":"Services"
        }
    ],
    "sg:phone":"+32 2 361 16 66",
    "sg:postcode":"1500",
    "sg:province":"Vlaams-Brabant",
    "sg:tags":[
        "physiotherapist"
    ],
    "wof:name":"Laus Peter",
    "wof:placetype":"venue"
},
  "geometry": {"coordinates":[4.2395009995,50.7312431335],"type":"Point"}
}