{
  "type": "Feature",
  "properties": {
    "iso:country":"BE",
    "sg:address":"Rollebeekstraat 10",
    "sg:city":"Wommelgem",
    "sg:orig_category":"Emballages en plastique Fab",
    "sg:phone":"+32 3 354 14 42",
    "sg:postcode":"2160",
    "sg:province":"Antwerpen",
    "wof:name":"Euralpack",
    "wof:placetype":"venue"
},
  "geometry": {"coordinates":[4.5108242035,51.20495224],"type":"Point"}
}