{
  "type": "Feature",
  "properties": {
    "addr:full":"Nijverheidsstraat 10 Malle Antwerpen 2390",
    "addr:housenumber":"10",
    "addr:postcode":"2390",
    "addr:street":"Nijverheidsstraat",
    "iso:country":"BE",
    "sg:address":"Nijverheidsstraat 10",
    "sg:city":"Malle",
    "sg:orig_category":"Tijdelijke werkgelegenheid and uitzendkantoren",
    "sg:phone":"+32 3 312 52 96",
    "sg:postcode":"2390",
    "sg:province":"Antwerpen",
    "wof:name":"Computing Van Assche",
    "wof:placetype":"venue"
},
  "geometry": {"coordinates":[4.7121119499,51.2944908142],"type":"Point"}
}