{
  "type": "Feature",
  "properties": {
    "addr:full":"Kerkstraat 25 Schilde ('s Gravenwezel) Antwerpen 2970",
    "addr:housenumber":"25",
    "addr:postcode":"2970",
    "addr:street":"Kerkstraat;S",
    "iso:country":"BE",
    "sg:address":"Kerkstraat 25",
    "sg:city":"Schilde ('s Gravenwezel)",
    "sg:classifiers":[
        {
            "category":"Cafe",
            "type":"Food & Drink"
        }
    ],
    "sg:phone":"+32 3 658 41 77",
    "sg:postcode":"2970",
    "sg:province":"Antwerpen",
    "sg:tags":[
        "snack-bars"
    ],
    "wof:name":"Tom",
    "wof:placetype":"venue"
},
  "geometry": {"coordinates":[4.5832710266,51.2394866943],"type":"Point"}
}