{
  "type": "Feature",
  "properties": {
    "iso:country":"BE",
    "sg:address":"Diestersteenweg 11",
    "sg:city":"Maaseik (neeroeteren)",
    "sg:classifiers":[
        {
            "category":"Home & Garden",
            "subcategory":"Carpets & Floor Coverings",
            "type":"Retail Goods"
        }
    ],
    "sg:phone":"+32 89 86 56 58",
    "sg:postcode":"3680",
    "sg:province":"Limburg",
    "sg:tags":[
        "-"
    ],
    "wof:name":"Dija Bvba",
    "wof:placetype":"venue"
},
  "geometry": {"coordinates":[5.7717900276,51.0992393494],"type":"Point"}
}