{
  "type": "Feature",
  "properties": {
    "iso:country":"BE",
    "sg:address":"Pothoekstraat 28",
    "sg:city":"Antwerpen",
    "sg:orig_category":"Auto-\u00e9coles",
    "sg:phone":"+32 3 236 97 21",
    "sg:postcode":"2060",
    "sg:province":"Antwerpen",
    "wof:name":"Rijschool Sanderus",
    "wof:placetype":"venue"
},
  "geometry": {"coordinates":[4.4366087914,51.2210655212],"type":"Point"}
}