{
  "type": "Feature",
  "properties": {
    "iso:country":"BE",
    "sg:address":"Brasschaatsteenweg 308",
    "sg:city":"Kalmthout",
    "sg:orig_category":"Krantenuitgeverijen Tijdschriftenuitgeverijen",
    "sg:phone":"+32 3 620 02 11",
    "sg:postcode":"2920",
    "sg:province":"Antwerpen",
    "wof:name":"Uitgeverij Balans",
    "wof:placetype":"venue"
},
  "geometry": {"coordinates":[4.5063509941,51.3605690002],"type":"Point"}
}