{
  "type": "Feature",
  "properties": {
    "iso:country":"BE",
    "sg:address":"Avenue Dailly 137",
    "sg:city":"Bruxelles (schaerbeek)",
    "sg:classifiers":[
        {
            "category":"Social Services",
            "type":"Services"
        }
    ],
    "sg:phone":"+32 2 732 31 30",
    "sg:postcode":"1030",
    "sg:province":"Bruxelles-Capitale",
    "wof:name":"Emmanuel S O S Adoption",
    "wof:placetype":"venue"
},
  "geometry": {"coordinates":[4.3841848373,50.8552017212],"type":"Point"}
}