{
  "type": "Feature",
  "properties": {
    "addr:full":"Hezewijk 2 Herentals (noorderwijk) Antwerpen 2200",
    "addr:housenumber":"2",
    "addr:postcode":"2200",
    "addr:street":"Hezewijk",
    "iso:country":"BE",
    "sg:address":"Hezewijk 2",
    "sg:city":"Herentals (noorderwijk)",
    "sg:classifiers":[
        {
            "category":"Building & Trades",
            "subcategory":"Landscaping Services",
            "type":"Services"
        }
    ],
    "sg:phone":"+32 477 25 87 08",
    "sg:postcode":"2200",
    "sg:province":"Antwerpen",
    "sg:tags":[
        "gardening",
        "garden",
        "maintenance"
    ],
    "wof:name":"Van Turnhout A",
    "wof:placetype":"venue"
},
  "geometry": {"coordinates":[4.8404760361,51.1569976807],"type":"Point"}
}