{
  "type": "Feature",
  "properties": {
    "addr:full":"\u00b4t Angereelstraat 71 Ninove Oost-Vlaanderen 9400",
    "addr:housenumber":"71",
    "addr:postcode":"9400",
    "addr:street":"Angereelstraat",
    "iso:country":"BE",
    "sg:address":"\u00b4t Angereelstraat 71",
    "sg:city":"Ninove",
    "sg:orig_category":"Tuinen",
    "sg:phone":"+32 54 33 80 14",
    "sg:postcode":"9400",
    "sg:province":"Oost-Vlaanderen",
    "wof:name":"Frederik D\u00b4hauwer",
    "wof:placetype":"venue"
},
  "geometry": {"coordinates":[4.0232000351,50.8349113464],"type":"Point"}
}