{
  "type": "Feature",
  "properties": {
    "addr:full":"Rue Pav\u00c9 Du Gosson 250 Saint-nicolas Li\u00e8ge 4420",
    "addr:housenumber":"250",
    "addr:postcode":"4420",
    "addr:street":"Rue Pave\u0301 Du Gosson",
    "iso:country":"BE",
    "sg:address":"Rue Pav\u00c9 Du Gosson 250",
    "sg:city":"Saint-nicolas",
    "sg:orig_category":"Boucheries",
    "sg:phone":"+32 4 226 87 22",
    "sg:postcode":"4420",
    "sg:province":"Li\u00e8ge",
    "wof:name":"Alain Clabots",
    "wof:placetype":"venue"
},
  "geometry": {"coordinates":[5.5272941589,50.6362609863],"type":"Point"}
}