{
  "type": "Feature",
  "properties": {
    "iso:country":"BE",
    "sg:address":"217 Chaussee De Vleurgat -",
    "sg:city":"Brussels",
    "sg:classifiers":[
        {
            "category":"Professional",
            "subcategory":"Art Services",
            "type":"Services"
        }
    ],
    "sg:phone":"+32 2 640 91 40",
    "sg:postcode":"1050",
    "sg:province":"Bruxelles-Capitale",
    "sg:tags":[
        "export-import"
    ],
    "wof:name":"India Embassy",
    "wof:placetype":"venue"
},
  "geometry": {"coordinates":[4.3686699867,50.8246307373],"type":"Point"}
}