{
  "type": "Feature",
  "properties": {
    "iso:country":"BE",
    "sg:address":"Nieuwburgstraat 46",
    "sg:city":"Sint-gillis/saint-gilles",
    "sg:orig_category":"Diverse grafische activiteiten",
    "sg:phone":"+32 2 538 30 62",
    "sg:postcode":"1060",
    "sg:province":"Bruxelles-Capitale",
    "wof:name":"Maurice Bock",
    "wof:placetype":"venue"
},
  "geometry": {"coordinates":[4.3532891273,50.8276100159],"type":"Point"}
}