{
  "type": "Feature",
  "properties": {
    "iso:country":"BE",
    "sg:address":"Avenue Du Bosquet 39",
    "sg:city":"Huy",
    "sg:classifiers":[
        {
            "category":"Communications",
            "subcategory":"Television Station",
            "type":"Services"
        }
    ],
    "sg:phone":"+32 85 21 36 01",
    "sg:postcode":"4500",
    "sg:province":"Li\u00e8ge",
    "sg:tags":[
        "video",
        "audio",
        "verhuur"
    ],
    "wof:name":"Vid\u00c9oth\u00c8que Image",
    "wof:placetype":"venue"
},
  "geometry": {"coordinates":[5.2173500061,50.5250892639],"type":"Point"}
}