{
  "type": "Feature",
  "properties": {
    "addr:full":"Diestsestraat 141 Leuven Vlaams-Brabant 3000",
    "addr:housenumber":"141",
    "addr:postcode":"3000",
    "addr:street":"Diestsestraat",
    "iso:country":"BE",
    "sg:address":"Diestsestraat 141",
    "sg:city":"Leuven",
    "sg:classifiers":[
        {
            "category":"Professional",
            "subcategory":"Art Services",
            "type":"Services"
        }
    ],
    "sg:phone":"+32 16 22 32 22",
    "sg:postcode":"3000",
    "sg:province":"Vlaams-Brabant",
    "sg:tags":[
        "photographer"
    ],
    "wof:name":"Fotokar Nv",
    "wof:placetype":"venue"
},
  "geometry": {"coordinates":[4.7080421448,50.8811416626],"type":"Point"}
}