{
  "type": "Feature",
  "properties": {
    "addr:full":"Petergensfeld 20 Raeren Li\u00e8ge 4730",
    "addr:housenumber":"20",
    "addr:postcode":"4730",
    "addr:street":"Petergensfeld",
    "iso:country":"BE",
    "sg:address":"Petergensfeld 20",
    "sg:city":"Raeren",
    "sg:classifiers":[
        {
            "category":"Building & Trades",
            "subcategory":"Electrical",
            "type":"Services"
        }
    ],
    "sg:phone":"+32 87 85 04 69",
    "sg:postcode":"4730",
    "sg:province":"Li\u00e8ge",
    "sg:tags":[
        "-",
        "electric",
        "contractor"
    ],
    "wof:name":"Electricite Louis P Sa",
    "wof:placetype":"venue"
},
  "geometry": {"coordinates":[6.1730351448,50.652217865],"type":"Point"}
}