{
  "type": "Feature",
  "properties": {
    "iso:country":"BE",
    "sg:address":"Bouwelsesteenweg 104",
    "sg:city":"Nijlen",
    "sg:orig_category":"Charpentes and couvertures",
    "sg:phone":"+32 3 411 24 85",
    "sg:postcode":"2560",
    "sg:province":"Antwerpen",
    "wof:name":"Kurt Hermans",
    "wof:placetype":"venue"
},
  "geometry": {"coordinates":[4.6821050644,51.1652297974],"type":"Point"}
}