{
  "type": "Feature",
  "properties": {
    "addr:full":"Rue Pierre Timmermans 28 Bruxelles (jette) Bruxelles-Capitale 1090",
    "addr:housenumber":"28",
    "addr:postcode":"1090",
    "addr:street":"Rue Pierre Timmermans",
    "iso:country":"BE",
    "sg:address":"Rue Pierre Timmermans 28",
    "sg:city":"Bruxelles (jette)",
    "sg:classifiers":[
        {
            "category":"Personal",
            "subcategory":"Barber",
            "type":"Services"
        }
    ],
    "sg:phone":"+32 2 427 86 57",
    "sg:postcode":"1090",
    "sg:province":"Bruxelles-Capitale",
    "sg:tags":[
        "gentleman",
        "salon",
        "-",
        "hairdressing"
    ],
    "wof:name":"Daniel",
    "wof:placetype":"venue"
},
  "geometry": {"coordinates":[4.3239002228,50.8734512329],"type":"Point"}
}