{
  "type": "Feature",
  "properties": {
    "addr:full":"Oud-dorpsstraat 44 Wuustwezel Antwerpen 2990",
    "addr:housenumber":"44",
    "addr:postcode":"2990",
    "addr:street":"Oud-Dorpsstraat",
    "iso:country":"BE",
    "sg:address":"Oud-dorpsstraat 44",
    "sg:city":"Wuustwezel",
    "sg:classifiers":[
        {
            "category":"Cafe",
            "type":"Food & Drink"
        }
    ],
    "sg:phone":"+32 3 669 68 88",
    "sg:postcode":"2990",
    "sg:province":"Antwerpen",
    "sg:tags":[
        "caf\u00e9s"
    ],
    "wof:name":"Caf\u00c9 Farwest",
    "wof:placetype":"venue"
},
  "geometry": {"coordinates":[4.6413421631,51.4021568298],"type":"Point"}
}