{
  "type": "Feature",
  "properties": {
    "iso:country":"BE",
    "sg:address":"Kazerneweg 23b",
    "sg:city":"Kruishoutem",
    "sg:classifiers":[
        {
            "category":"Government",
            "subcategory":"Customs House",
            "type":"Public Place"
        }
    ],
    "sg:phone":"+32 9 383 01 10",
    "sg:postcode":"9770",
    "sg:province":"Oost-Vlaanderen",
    "sg:tags":[
        "packing"
    ],
    "wof:name":"Eksfill Bvba",
    "wof:placetype":"venue"
},
  "geometry": {"coordinates":[3.527919054,50.9200515747],"type":"Point"}
}