{
  "type": "Feature",
  "properties": {
    "addr:full":"Louis Bertrandlaan 99 Schaarbeek/schaerbeek Bruxelles-Capitale 1030",
    "addr:housenumber":"99",
    "addr:postcode":"1030",
    "addr:street":"Louis Bertrandlaan",
    "iso:country":"BE",
    "sg:address":"Louis Bertrandlaan 99",
    "sg:city":"Schaarbeek/schaerbeek",
    "sg:orig_category":"Kapsalons",
    "sg:phone":"+32 2 242 01 86",
    "sg:postcode":"1030",
    "sg:province":"Bruxelles-Capitale",
    "wof:name":"Coiffure Laroche",
    "wof:placetype":"venue"
},
  "geometry": {"coordinates":[4.3785910606,50.8633651733],"type":"Point"}
}