{
  "type": "Feature",
  "properties": {
    "addr:full":"Camille Huysmanslaan 103 Antwerpen Antwerpen 2020",
    "addr:housenumber":"103",
    "addr:postcode":"2020",
    "addr:street":"Camille Huysmanslaan",
    "iso:country":"BE",
    "sg:address":"Camille Huysmanslaan 103",
    "sg:city":"Antwerpen",
    "sg:classifiers":[
        {
            "category":"Real Estate",
            "subcategory":"Architect",
            "type":"Services"
        }
    ],
    "sg:phone":"+32 3 288 91 34",
    "sg:postcode":"2020",
    "sg:province":"Antwerpen",
    "wof:name":"Fierens J",
    "wof:placetype":"venue"
},
  "geometry": {"coordinates":[4.3900618553,51.1904602051],"type":"Point"}
}