{
  "type": "Feature",
  "properties": {
    "iso:country":"BE",
    "sg:address":"Spinstersstraat 129",
    "sg:city":"Ronse/renaix",
    "sg:orig_category":"Kapsalons",
    "sg:phone":"+32 55 21 99 15",
    "sg:postcode":"9600",
    "sg:province":"Oost-Vlaanderen",
    "wof:name":"Coiffure Anne",
    "wof:placetype":"venue"
},
  "geometry": {"coordinates":[3.5863280296,50.7501373291],"type":"Point"}
}