{
  "type": "Feature",
  "properties": {
    "addr:full":"Avenue Cardinal Mercier 49 Namur Namur 5000",
    "addr:housenumber":"49",
    "addr:postcode":"5000",
    "addr:street":"Avenue Cardinal Mercier",
    "iso:country":"BE",
    "sg:address":"Avenue Cardinal Mercier 49",
    "sg:city":"Namur",
    "sg:classifiers":[
        {
            "category":"Health Services",
            "subcategory":"Doctor",
            "type":"Services"
        }
    ],
    "sg:phone":"+32 81 74 21 11",
    "sg:postcode":"5000",
    "sg:province":"Namur",
    "sg:tags":[
        "medicinephysicians",
        "surgeon"
    ],
    "wof:name":"Gillet Beno\u00eet",
    "wof:placetype":"venue"
},
  "geometry": {"coordinates":[4.8510842323,50.4651794434],"type":"Point"}
}