{
  "type": "Feature",
  "properties": {
    "iso:country":"BE",
    "sg:address":"Brouwerijstraat 6",
    "sg:city":"Scherpenheuvel-zichem (scherpenheuvel)",
    "sg:classifiers":[
        {
            "category":"Shopping",
            "subcategory":"Bicycles & Sporting Goods",
            "type":"Retail Goods"
        }
    ],
    "sg:phone":"+32 13 77 73 12",
    "sg:postcode":"3270",
    "sg:province":"Vlaams-Brabant",
    "sg:tags":[
        "sport",
        "-"
    ],
    "wof:name":"Sport 2000 Cv",
    "wof:placetype":"venue"
},
  "geometry": {"coordinates":[4.9772348404,50.9792327881],"type":"Point"}
}