{
  "type": "Feature",
  "properties": {
    "iso:country":"BE",
    "sg:address":"Rue Bel-air 39",
    "sg:city":"Ecaussinnes",
    "sg:orig_category":"Installatie van houten of kunststof schrijnwerk Woningbouw",
    "sg:phone":"+32 67 44 23 79",
    "sg:postcode":"7190",
    "sg:province":"Hainaut",
    "wof:name":"Ren\u00c9 Lambert",
    "wof:placetype":"venue"
},
  "geometry": {"coordinates":[4.1606788635,50.5643386841],"type":"Point"}
}