{
  "type": "Feature",
  "properties": {
    "iso:country":"BE",
    "sg:address":"Schaluinstraat 79",
    "sg:city":"Tremelo (baal)",
    "sg:classifiers":[
        {
            "category":"Building & Trades",
            "subcategory":"Landscaping Services",
            "type":"Services"
        }
    ],
    "sg:phone":"+32 16 53 57 27",
    "sg:postcode":"3128",
    "sg:province":"Vlaams-Brabant",
    "sg:tags":[
        "equipment",
        "swimming",
        "-",
        "pool",
        "contractor"
    ],
    "wof:name":"P.l. Sales Bvba",
    "wof:placetype":"venue"
},
  "geometry": {"coordinates":[4.7362318039,51.0027885437],"type":"Point"}
}