{
  "type": "Feature",
  "properties": {
    "addr:full":"Gaverstraat 9 Zonnebeke (zandvoorde) West-Vlaanderen 8980",
    "addr:housenumber":"9",
    "addr:postcode":"8980",
    "addr:street":"Gaverstraat",
    "iso:country":"BE",
    "sg:address":"Gaverstraat 9",
    "sg:city":"Zonnebeke (zandvoorde)",
    "sg:classifiers":[
        {
            "category":"Building & Trades",
            "subcategory":"Landscaping Services",
            "type":"Services"
        }
    ],
    "sg:phone":"+32 57 46 78 85",
    "sg:postcode":"8980",
    "sg:province":"West-Vlaanderen",
    "sg:tags":[
        "gardening",
        "garden",
        "maintenance"
    ],
    "wof:name":"Demolder L",
    "wof:placetype":"venue"
},
  "geometry": {"coordinates":[2.9872550964,50.8730812073],"type":"Point"}
}