{
  "type": "Feature",
  "properties": {
    "addr:full":"Chauss\u00c9e De Lille 401 Moeskroen/mouscron Hainaut 7700",
    "addr:housenumber":"401",
    "addr:postcode":"7700",
    "addr:street":"Chausse\u0301E De Lille",
    "iso:country":"BE",
    "sg:address":"Chauss\u00c9e De Lille 401",
    "sg:city":"Moeskroen/mouscron",
    "sg:orig_category":"Banques and organismes de cr\u00e9dit",
    "sg:phone":"+32 56 33 61 18",
    "sg:postcode":"7700",
    "sg:province":"Hainaut",
    "wof:name":"Bbl",
    "wof:placetype":"venue"
},
  "geometry": {"coordinates":[3.2323200703,50.7400932312],"type":"Point"}
}