{
  "type": "Feature",
  "properties": {
    "addr:full":"Rue L\u00c9on Bernus 14 Charleroi Hainaut 6000",
    "addr:housenumber":"14",
    "addr:postcode":"6000",
    "addr:street":"Rue Le\u0301On Bernus;Hainaut",
    "iso:country":"BE",
    "sg:address":"Rue L\u00c9on Bernus 14",
    "sg:city":"Charleroi",
    "sg:orig_category":"Assistances juridiques",
    "sg:phone":"+32 71 31 30 60",
    "sg:postcode":"6000",
    "sg:province":"Hainaut",
    "wof:name":"Infor Famille Charleroi",
    "wof:placetype":"venue"
},
  "geometry": {"coordinates":[4.4489469528,50.4142074585],"type":"Point"}
}