{
  "type": "Feature",
  "properties": {
    "addr:full":"Rue De Gemine 441 Andenne Namur 5300",
    "addr:housenumber":"441",
    "addr:postcode":"5300",
    "addr:street":"Rue De Gemine",
    "iso:country":"BE",
    "sg:address":"Rue De Gemine 441",
    "sg:city":"Andenne",
    "sg:orig_category":"Epiceries",
    "sg:phone":"+32 85 82 51 52",
    "sg:postcode":"5300",
    "sg:province":"Namur",
    "wof:name":"Hector Bourguignon Jean-etienne",
    "wof:placetype":"venue"
},
  "geometry": {"coordinates":[5.0982642174,50.4863739014],"type":"Point"}
}