{
  "type": "Feature",
  "properties": {
    "iso:country":"BE",
    "sg:address":"Mellenstraat 61",
    "sg:city":"Borgloon",
    "sg:orig_category":"Rundveehouders",
    "sg:phone":"+32 12 74 23 49",
    "sg:postcode":"3840",
    "sg:province":"Limburg",
    "wof:name":"Landry Gielen",
    "wof:placetype":"venue"
},
  "geometry": {"coordinates":[5.3441700935,50.8012466431],"type":"Point"}
}