{
  "type": "Feature",
  "properties": {
    "addr:full":"Hoogstraat 341 Duffel Antwerpen 2570",
    "addr:housenumber":"341",
    "addr:postcode":"2570",
    "addr:street":"Hoogstraat",
    "iso:country":"BE",
    "sg:address":"Hoogstraat 341",
    "sg:city":"Duffel",
    "sg:orig_category":"Groententeelt",
    "sg:phone":"+32 15 31 24 27",
    "sg:postcode":"2570",
    "sg:province":"Antwerpen",
    "wof:name":"Jamarko",
    "wof:placetype":"venue"
},
  "geometry": {"coordinates":[4.542383194,51.0931549072],"type":"Point"}
}