{
  "type": "Feature",
  "properties": {
    "addr:full":"Rue Remikette 41 Celles (les Waleffes) Li\u00e8ge 4317",
    "addr:housenumber":"41",
    "addr:postcode":"4317",
    "addr:street":"Rue Remikette",
    "iso:country":"BE",
    "sg:address":"Rue Remikette 41",
    "sg:city":"Celles (les Waleffes)",
    "sg:classifiers":[
        {
            "category":"Health Services",
            "subcategory":"Doctor",
            "type":"Services"
        }
    ],
    "sg:phone":"+32 19 56 73 06",
    "sg:postcode":"4317",
    "sg:province":"Li\u00e8ge",
    "sg:tags":[
        "medicinephysicians",
        "surgeon"
    ],
    "wof:name":"Ledent J-f",
    "wof:placetype":"venue"
},
  "geometry": {"coordinates":[5.2618951797,50.6657218933],"type":"Point"}
}