{
  "type": "Feature",
  "properties": {
    "addr:full":"R A M 3 Braine-l`alleud Brabant Wallon 1421",
    "addr:housenumber":"3;1421",
    "addr:street":"R A M;Brabant Wallon",
    "iso:country":"BE",
    "sg:address":"R A M 3",
    "sg:city":"Braine-l`alleud",
    "sg:orig_category":"Ruimtes voor conferenties, recepties and feesten",
    "sg:phone":"+32 67 84 07 10",
    "sg:postcode":"1421",
    "sg:province":"Brabant Wallon",
    "wof:name":"C B-s-i",
    "wof:placetype":"venue"
},
  "geometry": {"coordinates":[1.2029399872,47.4052200317],"type":"Point"}
}