{
  "type": "Feature",
  "properties": {
    "iso:country":"BE",
    "sg:address":"Rue De Hombroux 21",
    "sg:city":"Ans",
    "sg:orig_category":"Elektrische installaties voor woningen",
    "sg:phone":"+32 4 263 47 62",
    "sg:postcode":"4432",
    "sg:province":"Li\u00e8ge",
    "wof:name":"Raphael Virzi",
    "wof:placetype":"venue"
},
  "geometry": {"coordinates":[5.5192022324,50.6778907776],"type":"Point"}
}