{
  "type": "Feature",
  "properties": {
    "addr:full":"Avenue Charles Quint 177 Bruxelles (ganshoren) Bruxelles-Capitale 1083",
    "addr:housenumber":"177",
    "addr:postcode":"1083",
    "addr:street":"Avenue Charles Quint",
    "iso:country":"BE",
    "sg:address":"Avenue Charles Quint 177",
    "sg:city":"Bruxelles (ganshoren)",
    "sg:classifiers":[
        {
            "category":"Food & Beverages",
            "subcategory":"Groceries & Convenience Stores",
            "type":"Retail Goods"
        }
    ],
    "sg:phone":"+32 2 465 52 16",
    "sg:postcode":"1083",
    "sg:province":"Bruxelles-Capitale",
    "sg:tags":[
        "grocer"
    ],
    "wof:name":"Shakil",
    "wof:placetype":"venue"
},
  "geometry": {"coordinates":[4.3078289032,50.8695411682],"type":"Point"}
}