{
  "type": "Feature",
  "properties": {
    "addr:full":"Vianderstraat 9 Tienen Vlaams-Brabant 3300",
    "addr:housenumber":"9",
    "addr:postcode":"3300",
    "addr:street":"Vianderstraat",
    "iso:country":"BE",
    "sg:address":"Vianderstraat 9",
    "sg:city":"Tienen",
    "sg:orig_category":"Postkantoren Verzekeringsmakelaars and experts",
    "sg:phone":"+32 16 81 49 86",
    "sg:postcode":"3300",
    "sg:province":"Vlaams-Brabant",
    "wof:name":"De Post",
    "wof:placetype":"venue"
},
  "geometry": {"coordinates":[4.9448060989,50.8126449585],"type":"Point"}
}