{
  "type": "Feature",
  "properties": {
    "iso:country":"BE",
    "sg:address":"Rue Hoyoux 96",
    "sg:city":"Herstal",
    "sg:classifiers":[
        {
            "category":"Health Services",
            "subcategory":"Health Practitioner",
            "type":"Services"
        }
    ],
    "sg:phone":"+32 4 264 38 48",
    "sg:postcode":"4040",
    "sg:province":"Li\u00e8ge",
    "sg:tags":[
        "physiotherapist"
    ],
    "wof:name":"Simon Michele",
    "wof:placetype":"venue"
},
  "geometry": {"coordinates":[5.6261072159,50.661277771],"type":"Point"}
}