{
  "type": "Feature",
  "properties": {
    "addr:full":"Dijk 56 Hamont-achel Limburg 3930",
    "addr:housenumber":"56",
    "addr:postcode":"3930",
    "addr:street":"Dijk",
    "iso:country":"BE",
    "sg:address":"Dijk 56",
    "sg:city":"Hamont-achel",
    "sg:orig_category":"Antiquit\u00e9s",
    "sg:phone":"+32 11 62 27 41",
    "sg:postcode":"3930",
    "sg:province":"Limburg",
    "wof:name":"H. Slegers",
    "wof:placetype":"venue"
},
  "geometry": {"coordinates":[5.5450549126,51.2511863708],"type":"Point"}
}