{
  "type": "Feature",
  "properties": {
    "iso:country":"BE",
    "sg:address":"Scheldestraat 85",
    "sg:city":"Zele",
    "sg:classifiers":[
        {
            "category":"Building & Trades",
            "subcategory":"Construction",
            "type":"Services"
        }
    ],
    "sg:phone":"+32 52 44 43 64",
    "sg:postcode":"9240",
    "sg:province":"Oost-Vlaanderen",
    "sg:tags":[
        "en",
        "la",
        "el\u00e9ments",
        "pour",
        "fab",
        "b\u00e9ton"
    ],
    "wof:name":"Cementbouw",
    "wof:placetype":"venue"
},
  "geometry": {"coordinates":[4.0382528305,51.0496444702],"type":"Point"}
}