{
  "type": "Feature",
  "properties": {
    "iso:country":"BE",
    "sg:address":"Bosstraat 24",
    "sg:city":"Laarne",
    "sg:orig_category":"Woningbouw",
    "sg:phone":"+32 9 369 34 58",
    "sg:postcode":"9270",
    "sg:province":"Oost-Vlaanderen",
    "wof:name":"Versluys Andre En Zonen",
    "wof:placetype":"venue"
},
  "geometry": {"coordinates":[3.8566539288,51.0397949219],"type":"Point"}
}