{
  "type": "Feature",
  "properties": {
    "addr:full":"Tichelarijstraat 74 Turnhout Antwerpen 2300",
    "addr:housenumber":"74",
    "addr:postcode":"2300",
    "addr:street":"Tichelarijstraat",
    "iso:country":"BE",
    "sg:address":"Tichelarijstraat 74",
    "sg:city":"Turnhout",
    "sg:classifiers":[
        {
            "category":"Arena",
            "subcategory":"Sports Club",
            "type":"Entertainment"
        }
    ],
    "sg:phone":"+32 479 72 85 34",
    "sg:postcode":"2300",
    "sg:province":"Antwerpen",
    "wof:name":"T.c. Den Bremt",
    "wof:placetype":"venue"
},
  "geometry": {"coordinates":[4.9375281334,51.328792572],"type":"Point"}
}