{
  "type": "Feature",
  "properties": {
    "addr:full":"Sint-denijsstraat 266 Vorst/forest Bruxelles-Capitale 1190",
    "addr:housenumber":"266",
    "addr:postcode":"1190",
    "addr:street":"Sint-Denijsstraat;/ Forest",
    "iso:country":"BE",
    "sg:address":"Sint-denijsstraat 266",
    "sg:city":"Vorst/forest",
    "sg:orig_category":"Dranken Verhuur cateringmateriaal and evenementuitrusting Winkelinrichting and handelsuitrusting Gh",
    "sg:phone":"+32 2 344 39 04",
    "sg:postcode":"1190",
    "sg:province":"Bruxelles-Capitale",
    "wof:name":"Drive-in",
    "wof:placetype":"venue"
},
  "geometry": {"coordinates":[4.3207268715,50.820098877],"type":"Point"}
}