{
  "type": "Feature",
  "properties": {
    "iso:country":"BE",
    "sg:address":"Blauwepoortstraat 9",
    "sg:city":"Heuvelland (westouter)",
    "sg:classifiers":[
        {
            "category":"Manufacturing",
            "subcategory":"Glass & Minerals",
            "type":"Manufacturing & Wholesale Goods"
        }
    ],
    "sg:phone":"+32 476 20 09 68",
    "sg:postcode":"8954",
    "sg:province":"West-Vlaanderen",
    "sg:tags":[
        "stained",
        "glazier",
        "-"
    ],
    "wof:name":"Barbry J",
    "wof:placetype":"venue"
},
  "geometry": {"coordinates":[2.7504498959,50.7995185852],"type":"Point"}
}