{
  "type": "Feature",
  "properties": {
    "iso:country":"BE",
    "sg:address":"Wampestraat 16",
    "sg:city":"Arendonk",
    "sg:orig_category":"Reclamebureaus",
    "sg:phone":"+32 14 67 83 92",
    "sg:postcode":"2370",
    "sg:province":"Antwerpen",
    "wof:name":"C.t. Design",
    "wof:placetype":"venue"
},
  "geometry": {"coordinates":[5.0957298279,51.3295059204],"type":"Point"}
}