{
  "type": "Feature",
  "properties": {
    "iso:country":"BE",
    "sg:address":"Gebroeders De Winterstraat 25",
    "sg:city":"Lille (wechelderzande)",
    "sg:classifiers":[
        {
            "category":"Health Services",
            "subcategory":"Health Practitioner",
            "type":"Services"
        }
    ],
    "sg:phone":"+32 3 309 11 29",
    "sg:postcode":"2275",
    "sg:province":"Antwerpen",
    "sg:tags":[
        "physiotherapist"
    ],
    "wof:name":"Leys Lisbeth",
    "wof:placetype":"venue"
},
  "geometry": {"coordinates":[4.7888021469,51.262260437],"type":"Point"}
}