{
  "type": "Feature",
  "properties": {
    "iso:country":"BE",
    "sg:address":"Aachener Strasse 51",
    "sg:city":"Eupen",
    "sg:classifiers":[
        {
            "category":"Professional",
            "subcategory":"Management & Consulting",
            "type":"Services"
        }
    ],
    "sg:phone":"+32 87 59 83 70",
    "sg:postcode":"4700",
    "sg:province":"Li\u00e8ge",
    "sg:tags":[
        "consultant"
    ],
    "wof:name":"Iton Pgmba",
    "wof:placetype":"venue"
},
  "geometry": {"coordinates":[6.0330271721,50.6333618164],"type":"Point"}
}