{
  "type": "Feature",
  "properties": {
    "iso:country":"BE",
    "sg:address":"Watermolendreef 128",
    "sg:city":"Sint-niklaas",
    "sg:classifiers":[
        {
            "category":"Cafe",
            "type":"Food & Drink"
        }
    ],
    "sg:phone":"+32 3 776 20 06",
    "sg:postcode":"9100",
    "sg:province":"Oost-Vlaanderen",
    "sg:tags":[
        "caf\u00e9s"
    ],
    "wof:name":"Caf\u00c9 De Sportkringer",
    "wof:placetype":"venue"
},
  "geometry": {"coordinates":[4.1232390404,51.1670379639],"type":"Point"}
}