{
  "type": "Feature",
  "properties": {
    "iso:country":"BE",
    "sg:address":"Rue Du Noir Chien 11",
    "sg:city":"Ham-sur-heure-nalinnes",
    "sg:orig_category":"Artsen and specialisten",
    "sg:phone":"+32 71 21 55 20",
    "sg:postcode":"6120",
    "sg:province":"Hainaut",
    "wof:name":"Hugues Fichefet",
    "wof:placetype":"venue"
},
  "geometry": {"coordinates":[4.448387146,50.3472366333],"type":"Point"}
}