{
  "type": "Feature",
  "properties": {
    "addr:full":"Generaal Eenensstraat 12 Schaarbeek/schaerbeek Bruxelles-Capitale 1030",
    "addr:housenumber":"12",
    "addr:postcode":"1030",
    "addr:street":"Generaal Eenensstraat",
    "iso:country":"BE",
    "sg:address":"Generaal Eenensstraat 12",
    "sg:city":"Schaarbeek/schaerbeek",
    "sg:orig_category":"Brood, gebak and snoepgoed",
    "sg:phone":"+32 2 215 23 75",
    "sg:postcode":"1030",
    "sg:province":"Bruxelles-Capitale",
    "wof:name":"P\u00c2tisserie Defever",
    "wof:placetype":"venue"
},
  "geometry": {"coordinates":[4.3748178482,50.8681144714],"type":"Point"}
}