{
  "type": "Feature",
  "properties": {
    "iso:country":"BE",
    "sg:address":"Klein Vilvoordestraat 2",
    "sg:city":"Kortenberg",
    "sg:orig_category":"Eleveurs de bovins. Producteurs de l\u00e9gumes",
    "sg:phone":"+32 2 759 94 29",
    "sg:postcode":"3078",
    "sg:province":"Vlaams-Brabant",
    "wof:name":"Jozef Steurs",
    "wof:placetype":"venue"
},
  "geometry": {"coordinates":[4.5707449913,50.8783035278],"type":"Point"}
}