{
  "type": "Feature",
  "properties": {
    "iso:country":"BE",
    "sg:address":"Steenweg Op Kleine Brogel 16",
    "sg:city":"Bocholt (kaulille)",
    "sg:classifiers":[
        {
            "category":"Health Services",
            "subcategory":"Dentist",
            "type":"Services"
        }
    ],
    "sg:phone":"+32 11 44 78 29",
    "sg:postcode":"3950",
    "sg:province":"Limburg",
    "wof:name":"Leunen An",
    "wof:placetype":"venue"
},
  "geometry": {"coordinates":[5.5137162209,51.1917495728],"type":"Point"}
}