{
  "type": "Feature",
  "properties": {
    "addr:full":"Clos Des Lys Sauvages 4 Namur Namur 5000",
    "addr:housenumber":"4",
    "addr:postcode":"5000",
    "addr:street":"Clos Des Lys Sauvages",
    "iso:country":"BE",
    "sg:address":"Clos Des Lys Sauvages 4",
    "sg:city":"Namur",
    "sg:classifiers":[
        {
            "category":"Health Services",
            "subcategory":"Doctor",
            "type":"Services"
        }
    ],
    "sg:phone":"+32 81 73 59 00",
    "sg:postcode":"5000",
    "sg:province":"Namur",
    "sg:tags":[
        "medicinephysicians",
        "surgeon"
    ],
    "wof:name":"Guislain Marie-christine",
    "wof:placetype":"venue"
},
  "geometry": {"coordinates":[4.8399047852,50.4433555603],"type":"Point"}
}