{
  "type": "Feature",
  "properties": {
    "addr:full":"Hillarestraat 23 Lokeren Oost-Vlaanderen 9160",
    "addr:housenumber":"23",
    "addr:postcode":"9160",
    "addr:street":"Hillarestraat",
    "iso:country":"BE",
    "sg:address":"Hillarestraat 23",
    "sg:city":"Lokeren",
    "sg:orig_category":"Dierenartsen",
    "sg:phone":"+32 9 348 55 24",
    "sg:postcode":"9160",
    "sg:province":"Oost-Vlaanderen",
    "wof:name":"Luc Coppieters",
    "wof:placetype":"venue"
},
  "geometry": {"coordinates":[3.9658300877,51.092250824],"type":"Point"}
}