{
  "type": "Feature",
  "properties": {
    "addr:full":"Rue Lesbroussart 59 Elsene/ixelles Bruxelles-Capitale 1050",
    "addr:housenumber":"59",
    "addr:postcode":"1050",
    "addr:street":"Rue Lesbroussart",
    "iso:country":"BE",
    "sg:address":"Rue Lesbroussart 59",
    "sg:city":"Elsene/ixelles",
    "sg:orig_category":"Studios photographiques. Equipement photographique",
    "sg:phone":"+32 2 648 60 88",
    "sg:postcode":"1050",
    "sg:province":"Bruxelles-Capitale",
    "wof:name":"Photo Alexandre",
    "wof:placetype":"venue"
},
  "geometry": {"coordinates":[4.3677048683,50.8278045654],"type":"Point"}
}