{
  "type": "Feature",
  "properties": {
    "iso:country":"BE",
    "sg:address":"Rue De Fize 22",
    "sg:city":"Crisn\u00e9e",
    "sg:classifiers":[
        {
            "category":"Home & Garden",
            "subcategory":"Carpets & Floor Coverings",
            "type":"Retail Goods"
        }
    ],
    "sg:phone":"+32 19 67 60 08",
    "sg:postcode":"4367",
    "sg:province":"Li\u00e8ge",
    "sg:tags":[
        "tile"
    ],
    "wof:name":"Sonema Sa",
    "wof:placetype":"venue"
},
  "geometry": {"coordinates":[5.3930449486,50.7115097046],"type":"Point"}
}