{
  "type": "Feature",
  "properties": {
    "addr:full":"Stationsstraat 251 Lommel Limburg 3920",
    "addr:housenumber":"251",
    "addr:postcode":"3920",
    "addr:street":"Stationsstraat",
    "iso:country":"BE",
    "sg:address":"Stationsstraat 251",
    "sg:city":"Lommel",
    "sg:classifiers":[
        {
            "category":"Health Services",
            "subcategory":"Health Practitioner",
            "type":"Services"
        }
    ],
    "sg:phone":"+32 11 54 27 77",
    "sg:postcode":"3920",
    "sg:province":"Limburg",
    "sg:tags":[
        "physiotherapist"
    ],
    "wof:name":"Mertens Albina",
    "wof:placetype":"venue"
},
  "geometry": {"coordinates":[5.3131799698,51.2154808044],"type":"Point"}
}