{
  "type": "Feature",
  "properties": {
    "iso:country":"BE",
    "sg:address":"Groenstraat 17",
    "sg:city":"De Pinte",
    "sg:classifiers":[
        {
            "category":"Health Services",
            "subcategory":"Dentist",
            "type":"Services"
        }
    ],
    "sg:phone":"+32 9 281 02 53",
    "sg:postcode":"9840",
    "sg:province":"Oost-Vlaanderen",
    "wof:name":"Van Beveren Anneke",
    "wof:placetype":"venue"
},
  "geometry": {"coordinates":[3.6456439495,50.9935913086],"type":"Point"}
}