{
  "type": "Feature",
  "properties": {
    "addr:full":"Lozijde 24 Lille Antwerpen 2275",
    "addr:housenumber":"24",
    "addr:postcode":"2275",
    "addr:street":"Lozijde",
    "iso:country":"BE",
    "sg:address":"Lozijde 24",
    "sg:city":"Lille",
    "sg:orig_category":"Gespecialiseerde residenti\u00eble bouw Loodgieterij, verwarming and sanitaire installaties Zwembadinstal",
    "sg:phone":"+32 14 55 58 92",
    "sg:postcode":"2275",
    "sg:province":"Antwerpen",
    "wof:name":"Louis Vervoort",
    "wof:placetype":"venue"
},
  "geometry": {"coordinates":[4.8731350899,51.2746505737],"type":"Point"}
}