{
  "type": "Feature",
  "properties": {
    "addr:full":"Rue De Goz\u00e9e 28 Montigny-le-tilleul Hainaut 6110",
    "addr:housenumber":"28",
    "addr:postcode":"6110",
    "addr:street":"Rue De Goze\u0301E",
    "iso:country":"BE",
    "sg:address":"Rue De Goz\u00e9e 28",
    "sg:city":"Montigny-le-tilleul",
    "sg:classifiers":[
        {
            "category":"Building & Trades",
            "subcategory":"Pest Control",
            "type":"Services"
        }
    ],
    "sg:phone":"+32 71 51 53 25",
    "sg:postcode":"6110",
    "sg:province":"Hainaut",
    "sg:tags":[
        "painting",
        "contractor"
    ],
    "wof:name":"Goffaux E",
    "wof:placetype":"venue"
},
  "geometry": {"coordinates":[4.3859028816,50.3900527954],"type":"Point"}
}