{
  "type": "Feature",
  "properties": {
    "iso:country":"BE",
    "sg:address":"Rue De La Maison Du Bois 26",
    "sg:city":"Jodoigne (m\u00e9lin)",
    "sg:classifiers":[
        {
            "category":"Farming",
            "subcategory":"Livestock Farm",
            "type":"Manufacturing & Wholesale Goods"
        }
    ],
    "sg:phone":"+32 10 81 21 11",
    "sg:postcode":"1370",
    "sg:province":"Brabant Wallon",
    "sg:tags":[
        "buyer"
    ],
    "wof:name":"Janmart-gauthier V",
    "wof:placetype":"venue"
},
  "geometry": {"coordinates":[4.8251729012,50.7424736023],"type":"Point"}
}