{
  "type": "Feature",
  "properties": {
    "addr:full":"Rue Val\u00c8re Mabille 51 Morlanwelz Hainaut 7140",
    "addr:housenumber":"51",
    "addr:postcode":"7140",
    "addr:street":"Rue Vale\u0300Re Mabille",
    "iso:country":"BE",
    "sg:address":"Rue Val\u00c8re Mabille 51",
    "sg:city":"Morlanwelz",
    "sg:orig_category":"Herstellingen and onderhoud van auto's",
    "sg:phone":"+32 64 26 58 50",
    "sg:postcode":"7140",
    "sg:province":"Hainaut",
    "wof:name":"Carrosserie Des Hayettes",
    "wof:placetype":"venue"
},
  "geometry": {"coordinates":[4.2483000755,50.4520645142],"type":"Point"}
}