{
  "type": "Feature",
  "properties": {
    "iso:country":"BE",
    "sg:address":"Rue Les Br\u00dbl\u00c9s 33",
    "sg:city":"Braine-l'alleud",
    "sg:orig_category":"Services de Nettoyage and de D\u00e9sinfection",
    "sg:phone":"+32 2 384 98 76",
    "sg:postcode":"1421",
    "sg:province":"Brabant Wallon",
    "wof:name":"Clean Up",
    "wof:placetype":"venue"
},
  "geometry": {"coordinates":[1.0551710129,48.7570610046],"type":"Point"}
}