{
  "type": "Feature",
  "properties": {
    "iso:country":"BE",
    "sg:address":"Rue De Maredret 20ba",
    "sg:city":"Mettet",
    "sg:orig_category":"Woningbouw",
    "sg:phone":"+32 71 72 64 84",
    "sg:postcode":"5644",
    "sg:province":"Namur",
    "wof:name":"Jean-pol Hotelet",
    "wof:placetype":"venue"
},
  "geometry": {"coordinates":[4.7311320305,50.3010292053],"type":"Point"}
}