{
  "type": "Feature",
  "properties": {
    "iso:country":"BE",
    "sg:address":"Molenhoek 30",
    "sg:city":"Dessel",
    "sg:orig_category":"Eleveurs de bovins",
    "sg:phone":"+32 14 37 89 95",
    "sg:postcode":"2480",
    "sg:province":"Antwerpen",
    "wof:name":"Gustaaf Nijs",
    "wof:placetype":"venue"
},
  "geometry": {"coordinates":[5.1127400398,51.2521896362],"type":"Point"}
}