{
  "type": "Feature",
  "properties": {
    "addr:full":"Nukkerstraat 3 Bredene West-Vlaanderen 8450",
    "addr:housenumber":"3",
    "addr:postcode":"8450",
    "addr:street":"Nukkerstraat",
    "iso:country":"BE",
    "sg:address":"Nukkerstraat 3",
    "sg:city":"Bredene",
    "sg:orig_category":"Fotografen and fotostudio's",
    "sg:phone":"+32 59 33 18 33",
    "sg:postcode":"8450",
    "sg:province":"West-Vlaanderen",
    "wof:name":"Foto-studio Marc",
    "wof:placetype":"venue"
},
  "geometry": {"coordinates":[2.9571681023,51.2210769653],"type":"Point"}
}