{
  "type": "Feature",
  "properties": {
    "iso:country":"BE",
    "sg:address":"Place Vaxelaire 8 Box 1",
    "sg:city":"Anh\u00e9e (bioul)",
    "sg:classifiers":[
        {
            "category":"Organizations",
            "subcategory":"Labor Organization",
            "type":"Services"
        }
    ],
    "sg:phone":"+32 71 53 53 22",
    "sg:postcode":"5537",
    "sg:province":"Namur",
    "sg:tags":[
        "harness",
        "maker",
        "saddler"
    ],
    "wof:name":"Le Pied \u00e0 L'etrier",
    "wof:placetype":"venue"
},
  "geometry": {"coordinates":[4.7967672348,50.3343467712],"type":"Point"}
}