{
  "type": "Feature",
  "properties": {
    "addr:full":"Rue De Tailfer 11 Assesse Namur 5330",
    "addr:housenumber":"11",
    "addr:postcode":"5330",
    "addr:street":"Rue De Tailfer",
    "iso:country":"BE",
    "sg:address":"Rue De Tailfer 11",
    "sg:city":"Assesse",
    "sg:classifiers":[
        {
            "category":"Arena",
            "subcategory":"Sports Club",
            "type":"Entertainment"
        }
    ],
    "sg:phone":"+32 83 65 58 31",
    "sg:postcode":"5330",
    "sg:province":"Namur",
    "sg:tags":[
        "de"
    ],
    "wof:name":"Club De Plong\u00c9e",
    "wof:placetype":"venue"
},
  "geometry": {"coordinates":[4.9719109535,50.3842048645],"type":"Point"}
}