{
  "type": "Feature",
  "properties": {
    "iso:country":"BE",
    "sg:address":"Place Des Alli\u00c9s 3",
    "sg:city":"Mons",
    "sg:orig_category":"Herstellingen and onderhoud van auto's Telecommunicatieapparaten Voertuigen",
    "sg:phone":"+32 65 40 20 77",
    "sg:postcode":"7000",
    "sg:province":"Hainaut",
    "wof:name":"A.b. Mons",
    "wof:placetype":"venue"
},
  "geometry": {"coordinates":[3.9393320084,50.4489746094],"type":"Point"}
}