{
  "type": "Feature",
  "properties": {
    "iso:country":"BE",
    "sg:address":"Rue Des Alli\u00c9s 47",
    "sg:city":"Frameries",
    "sg:classifiers":[
        {
            "category":"Cinema",
            "subcategory":"Movie Rental",
            "type":"Entertainment"
        }
    ],
    "sg:phone":"+32 65 66 17 23",
    "sg:postcode":"7080",
    "sg:province":"Hainaut",
    "sg:tags":[
        "de",
        "cassette",
        "location",
        "vid\u00e9o",
        "audio"
    ],
    "wof:name":"The Best Vid\u00c9o",
    "wof:placetype":"venue"
},
  "geometry": {"coordinates":[3.8945789337,50.4091186523],"type":"Point"}
}