{
  "type": "Feature",
  "properties": {
    "iso:country":"BE",
    "sg:address":"Skaldenstraat 58",
    "sg:city":"Gent",
    "sg:orig_category":"Forge, Moulage and Profilage des M\u00e9taux",
    "sg:phone":"+32 9 259 13 14",
    "sg:postcode":"9042",
    "sg:province":"Oost-Vlaanderen",
    "wof:name":"Atelier De Vuurhaard",
    "wof:placetype":"venue"
},
  "geometry": {"coordinates":[3.7816700935,51.1223831177],"type":"Point"}
}