{
  "type": "Feature",
  "properties": {
    "iso:country":"BE",
    "sg:address":"Rue De France 39a",
    "sg:city":"Hastiere",
    "sg:orig_category":"Chaussures",
    "sg:phone":"+32 82 64 49 92",
    "sg:postcode":"5543",
    "sg:province":"Namur",
    "wof:name":"Jusnot Dumont",
    "wof:placetype":"venue"
},
  "geometry": {"coordinates":[4.823764801,50.1709327698],"type":"Point"}
}