{
  "type": "Feature",
  "properties": {
    "addr:full":"Rue De France 37 Philippeville Namur 5600",
    "addr:housenumber":"37",
    "addr:postcode":"5600",
    "addr:street":"Rue De France",
    "iso:country":"BE",
    "sg:address":"Rue De France 37",
    "sg:city":"Philippeville",
    "sg:orig_category":"Studios photographiques",
    "sg:phone":"+32 71 66 62 15",
    "sg:postcode":"5600",
    "sg:province":"Namur",
    "wof:name":"Bints Photos",
    "wof:placetype":"venue"
},
  "geometry": {"coordinates":[4.5385761261,50.1963882446],"type":"Point"}
}