{
  "type": "Feature",
  "properties": {
    "addr:full":"Negenbonderstraat 25 Kortessem Limburg 3724",
    "addr:housenumber":"25",
    "addr:postcode":"3724",
    "addr:street":"Negenbonderstraat;Limburg",
    "iso:country":"BE",
    "sg:address":"Negenbonderstraat 25",
    "sg:city":"Kortessem",
    "sg:orig_category":"Rundveehouders",
    "sg:phone":"+32 12 23 36 86",
    "sg:postcode":"3724",
    "sg:province":"Limburg",
    "wof:name":"Gerard Grommen",
    "wof:placetype":"venue"
},
  "geometry": {"coordinates":[5.4180297852,50.8302307129],"type":"Point"}
}