{
  "type": "Feature",
  "properties": {
    "iso:country":"BE",
    "sg:address":"Brusselsesteenweg 363",
    "sg:city":"Asse",
    "sg:orig_category":"Erotische Etablissementen",
    "sg:phone":"+32 2 466 62 11",
    "sg:postcode":"1731",
    "sg:province":"Vlaams-Brabant",
    "wof:name":"Le Kobbegem",
    "wof:placetype":"venue"
},
  "geometry": {"coordinates":[4.2467207909,50.8936843872],"type":"Point"}
}