{
  "type": "Feature",
  "properties": {
    "iso:country":"BE",
    "sg:address":"Steenweg Op Turnhout 45",
    "sg:city":"Oud-turnhout",
    "sg:classifiers":[
        {
            "category":"Bars & Pubs",
            "type":"Food & Drink"
        }
    ],
    "sg:phone":"+32 14 45 14 91",
    "sg:postcode":"2360",
    "sg:province":"Antwerpen",
    "wof:name":"Liereman",
    "wof:placetype":"venue"
},
  "geometry": {"coordinates":[4.9777359962,51.3195304871],"type":"Point"}
}