{
  "type": "Feature",
  "properties": {
    "iso:country":"BE",
    "sg:address":"Maria-theresiastraat 83",
    "sg:city":"Leuven",
    "sg:orig_category":"Loodgieterij, verwarming and sanitaire installaties",
    "sg:phone":"+32 16 23 35 12",
    "sg:postcode":"3000",
    "sg:province":"Vlaams-Brabant",
    "wof:name":"Groep Driesmans",
    "wof:placetype":"venue"
},
  "geometry": {"coordinates":[4.7130317688,50.8794326782],"type":"Point"}
}