{
  "type": "Feature",
  "properties": {
    "iso:country":"BE",
    "sg:address":"Sint-simonstraat 34",
    "sg:city":"Gent (gentbrugge)",
    "sg:classifiers":[
        {
            "category":"Arts & Performance",
            "subcategory":"Symphony",
            "type":"Entertainment"
        }
    ],
    "sg:phone":"+32 9 232 34 43",
    "sg:postcode":"9050",
    "sg:province":"Oost-Vlaanderen",
    "sg:tags":[
        "orchestra"
    ],
    "wof:name":"Jazzfun Vzw",
    "wof:placetype":"venue"
},
  "geometry": {"coordinates":[3.7570040226,51.0444068909],"type":"Point"}
}