{
  "type": "Feature",
  "properties": {
    "iso:country":"BE",
    "sg:address":"Square Des H\u00c9ros 2-4",
    "sg:city":"Ukkel/uccle",
    "sg:orig_category":"Salles de conf\u00e9rences and de r\u00e9ceptions",
    "sg:phone":"+32 2 375 44 20",
    "sg:postcode":"1180",
    "sg:province":"Bruxelles-Capitale",
    "wof:name":"Manotel",
    "wof:placetype":"venue"
},
  "geometry": {"coordinates":[4.3422341347,50.8037185669],"type":"Point"}
}