{
  "type": "Feature",
  "properties": {
    "addr:full":"Pieter Breughellaan 1 Gent Oost-Vlaanderen 9051",
    "addr:housenumber":"1",
    "addr:postcode":"9051",
    "addr:street":"Pieter Breughellaan;Oost-Vlaanderen",
    "iso:country":"BE",
    "sg:address":"Pieter Breughellaan 1",
    "sg:city":"Gent",
    "sg:orig_category":"Sportclubs",
    "sg:phone":"+32 9 221 13 27",
    "sg:postcode":"9051",
    "sg:province":"Oost-Vlaanderen",
    "wof:name":"T.c. Indiana",
    "wof:placetype":"venue"
},
  "geometry": {"coordinates":[3.684803009,51.018497467],"type":"Point"}
}