{
  "type": "Feature",
  "properties": {
    "iso:country":"BE",
    "sg:address":"Avenue De La D\u00c9livrance 104",
    "sg:city":"Moeskroen/mouscron",
    "sg:classifiers":[
        {
            "category":"Arena",
            "subcategory":"Sports Club",
            "type":"Entertainment"
        }
    ],
    "sg:phone":"+32 56 48 81 65",
    "sg:postcode":"7711",
    "sg:province":"Hainaut",
    "sg:tags":[
        "de"
    ],
    "wof:name":"Tournai Biking Raiders",
    "wof:placetype":"venue"
},
  "geometry": {"coordinates":[3.3041160107,50.7192764282],"type":"Point"}
}