{
  "type": "Feature",
  "properties": {
    "iso:country":"BE",
    "sg:address":"Rue Courri\u00c8re-lez-ville 7",
    "sg:city":"Ecaussinnes",
    "sg:classifiers":[
        {
            "category":"Food & Beverages",
            "subcategory":"Meat & Fish",
            "type":"Retail Goods"
        }
    ],
    "sg:phone":"+32 67 44 37 18",
    "sg:postcode":"7190",
    "sg:province":"Hainaut",
    "sg:tags":[
        "vi",
        "zeevruchten"
    ],
    "wof:name":"Jean-pierre Martin",
    "wof:placetype":"venue"
},
  "geometry": {"coordinates":[4.1900629997,50.5430717468],"type":"Point"}
}