{
  "type": "Feature",
  "properties": {
    "addr:full":"Zaffelaredorp 61 Lochristi Oost-Vlaanderen 9080",
    "addr:housenumber":"61",
    "addr:postcode":"9080",
    "addr:street":"Zaffelaredorp",
    "iso:country":"BE",
    "sg:address":"Zaffelaredorp 61",
    "sg:city":"Lochristi",
    "sg:orig_category":"Boucheries",
    "sg:phone":"+32 9 356 94 36",
    "sg:postcode":"9080",
    "sg:province":"Oost-Vlaanderen",
    "wof:name":"Slagerij Marc & Martine",
    "wof:placetype":"venue"
},
  "geometry": {"coordinates":[3.8607931137,51.1320037842],"type":"Point"}
}