{
  "type": "Feature",
  "properties": {
    "iso:country":"BE",
    "sg:address":"Zoning Industriel D'achene",
    "sg:city":"Ciney",
    "sg:classifiers":[
        {
            "category":"Utilities",
            "subcategory":"Refuse",
            "type":"Services"
        }
    ],
    "sg:phone":"+32 83 21 50 98",
    "sg:postcode":"5590",
    "sg:province":"Namur",
    "sg:tags":[
        "management",
        "waste"
    ],
    "wof:name":"Achene Recyclage Sprl",
    "wof:placetype":"venue"
},
  "geometry": {"coordinates":[5.0457901955,50.2667007446],"type":"Point"}
}