{
  "type": "Feature",
  "properties": {
    "iso:country":"BE",
    "sg:address":"Rue De La Rh\u00c9torique 13",
    "sg:city":"Sint-gillis/saint-gilles",
    "sg:orig_category":"Enseignement maternel and primaire",
    "sg:phone":"+32 2 536 03 55",
    "sg:postcode":"1060",
    "sg:province":"Bruxelles-Capitale",
    "wof:name":"E.f.c. Peter Pan",
    "wof:placetype":"venue"
},
  "geometry": {"coordinates":[4.345998764,50.8276290894],"type":"Point"}
}