{
  "type": "Feature",
  "properties": {
    "addr:full":"Rue Traversi\u00c8re 26 Moeskroen/mouscron Hainaut 7712",
    "addr:housenumber":"26",
    "addr:postcode":"7712",
    "addr:street":"Rue Traversie\u0300Re",
    "iso:country":"BE",
    "sg:address":"Rue Traversi\u00c8re 26",
    "sg:city":"Moeskroen/mouscron",
    "sg:classifiers":[
        {
            "category":"Personal",
            "subcategory":"Beauty Salon",
            "type":"Services"
        }
    ],
    "sg:phone":"+32 56 33 37 49",
    "sg:postcode":"7712",
    "sg:province":"Hainaut",
    "sg:tags":[
        "de",
        "coiffure"
    ],
    "wof:name":"Coiffure Jocelyne",
    "wof:placetype":"venue"
},
  "geometry": {"coordinates":[3.2535879612,50.714931488],"type":"Point"}
}