{
  "type": "Feature",
  "properties": {
    "iso:country":"BE",
    "sg:address":"Rue Leon Houtart 9",
    "sg:city":"La Louviere",
    "sg:orig_category":"Slagers",
    "sg:phone":"+32 64 26 34 74",
    "sg:postcode":"7110",
    "sg:province":"Hainaut",
    "wof:name":"Dure",
    "wof:placetype":"venue"
},
  "geometry": {"coordinates":[4.1567101479,50.4836235046],"type":"Point"}
}