{
  "type": "Feature",
  "properties": {
    "iso:country":"BE",
    "sg:address":"Lutselusstraat 136",
    "sg:city":"Diepenbeek",
    "sg:orig_category":"Plaatsen van vloer- and muurbekleding Schilders",
    "sg:phone":"+32 11 33 25 49",
    "sg:postcode":"3590",
    "sg:province":"Limburg",
    "wof:name":"Bernard Sinnaeve",
    "wof:placetype":"venue"
},
  "geometry": {"coordinates":[5.457930088,50.9132499695],"type":"Point"}
}