{
  "type": "Feature",
  "properties": {
    "addr:full":"Pottelberg 4 Kortrijk West-Vlaanderen 8500",
    "addr:housenumber":"4",
    "addr:postcode":"8500",
    "addr:street":"Pottelberg",
    "iso:country":"BE",
    "sg:address":"Pottelberg 4",
    "sg:city":"Kortrijk",
    "sg:classifiers":[
        {
            "category":"Education",
            "subcategory":"School",
            "type":"Public Place"
        }
    ],
    "sg:phone":"+32 56 22 25 33",
    "sg:postcode":"8500",
    "sg:province":"West-Vlaanderen",
    "sg:tags":[
        "boarding"
    ],
    "wof:name":"Koninklijk Atheneum",
    "wof:placetype":"venue"
},
  "geometry": {"coordinates":[3.2570660114,50.8190345764],"type":"Point"}
}