{
  "type": "Feature",
  "properties": {
    "addr:full":"Grote Baan 549 Houthalen-helchteren Limburg 3530",
    "addr:housenumber":"549",
    "addr:postcode":"3530",
    "addr:street":"Grote Baan",
    "iso:country":"BE",
    "sg:address":"Grote Baan 549",
    "sg:city":"Houthalen-helchteren",
    "sg:classifiers":[
        {
            "category":"Cafe",
            "type":"Food & Drink"
        }
    ],
    "sg:phone":"+32 11 52 11 28",
    "sg:postcode":"3530",
    "sg:province":"Limburg",
    "sg:tags":[
        "caf\u00e9s"
    ],
    "wof:name":"Jacques Michaux",
    "wof:placetype":"venue"
},
  "geometry": {"coordinates":[5.3800802231,51.0446815491],"type":"Point"}
}