{
  "type": "Feature",
  "properties": {
    "addr:full":"Fasbinderstraat 7 Tremelo Vlaams-Brabant 3128",
    "addr:housenumber":"7",
    "addr:postcode":"3128",
    "addr:street":"Fasbinderstraat",
    "iso:country":"BE",
    "sg:address":"Fasbinderstraat 7",
    "sg:city":"Tremelo",
    "sg:classifiers":[
        {
            "category":"Cafe",
            "type":"Food & Drink"
        }
    ],
    "sg:phone":"+32 16 53 37 84",
    "sg:postcode":"3128",
    "sg:province":"Vlaams-Brabant",
    "sg:tags":[
        "caf\u00e9s"
    ],
    "wof:name":"Kon. Football Club Baal",
    "wof:placetype":"venue"
},
  "geometry": {"coordinates":[4.7509050369,50.9975852966],"type":"Point"}
}