{
  "type": "Feature",
  "properties": {
    "iso:country":"BE",
    "sg:address":"Provincialeweg 13",
    "sg:city":"Sint-amands",
    "sg:classifiers":[
        {
            "category":"Banks & Credit Unions",
            "subcategory":"Financial Services",
            "type":"Services"
        }
    ],
    "sg:phone":"+32 52 33 46 10",
    "sg:postcode":"2890",
    "sg:province":"Antwerpen",
    "sg:tags":[
        "loan",
        "mortgage"
    ],
    "wof:name":"De Cock-van Den Eynde-claude Bvba",
    "wof:placetype":"venue"
},
  "geometry": {"coordinates":[4.2161779404,51.038105011],"type":"Point"}
}