{
  "type": "Feature",
  "properties": {
    "iso:country":"BE",
    "sg:address":"Klijthofstraat 5",
    "sg:city":"Kortrijk",
    "sg:orig_category":"Rundveehouders",
    "sg:phone":"+32 56 22 44 05",
    "sg:postcode":"8510",
    "sg:province":"West-Vlaanderen",
    "wof:name":"Jean Samain",
    "wof:placetype":"venue"
},
  "geometry": {"coordinates":[3.3183140755,50.7817077637],"type":"Point"}
}