{
  "type": "Feature",
  "properties": {
    "iso:country":"BE",
    "sg:address":"Kerkstraat 43",
    "sg:city":"Lille",
    "sg:classifiers":[
        {
            "category":"Bars & Pubs",
            "type":"Food & Drink"
        }
    ],
    "sg:phone":"+32 14 88 30 09",
    "sg:postcode":"2275",
    "sg:province":"Antwerpen",
    "wof:name":"Wieter (de)",
    "wof:placetype":"venue"
},
  "geometry": {"coordinates":[4.820939064,51.2380599976],"type":"Point"}
}