{
  "type": "Feature",
  "properties": {
    "iso:country":"BE",
    "sg:address":"Dilbeekstraat 3",
    "sg:city":"Anderlecht",
    "sg:orig_category":"Woningbouw",
    "sg:phone":"+32 2 410 70 73",
    "sg:postcode":"1070",
    "sg:province":"Bruxelles-Capitale",
    "wof:name":"Cardoso",
    "wof:placetype":"venue"
},
  "geometry": {"coordinates":[4.3151011467,50.8486175537],"type":"Point"}
}