{
  "type": "Feature",
  "properties": {
    "iso:country":"BE",
    "sg:address":"Eug\u00c8ne Plaskylaan 149",
    "sg:city":"Schaarbeek/schaerbeek",
    "sg:orig_category":"Fotogravure and zetwerk Secretariaatsdiensten",
    "sg:phone":"+32 2 735 82 44",
    "sg:postcode":"1030",
    "sg:province":"Bruxelles-Capitale",
    "wof:name":"Scripprint",
    "wof:placetype":"venue"
},
  "geometry": {"coordinates":[4.3974552155,50.8523750305],"type":"Point"}
}