{
  "type": "Feature",
  "properties": {
    "addr:full":"Rue Alexandre-daoust 50 Dinant Namur 5500",
    "addr:housenumber":"50",
    "addr:postcode":"5500",
    "addr:street":"Rue Alexandre-Daoust",
    "iso:country":"BE",
    "sg:address":"Rue Alexandre-daoust 50",
    "sg:city":"Dinant",
    "sg:orig_category":"Biens d'occasion",
    "sg:phone":"+32 82 22 41 35",
    "sg:postcode":"5500",
    "sg:province":"Namur",
    "wof:name":"Maison Abracadabra",
    "wof:placetype":"venue"
},
  "geometry": {"coordinates":[4.9175949097,50.2520256042],"type":"Point"}
}