{
  "type": "Feature",
  "properties": {
    "addr:full":"Dokter De Moorstraat 102 Aalst Oost-Vlaanderen 9300",
    "addr:housenumber":"102",
    "addr:postcode":"9300",
    "addr:street":"Dokter De Moorstraat",
    "iso:country":"BE",
    "sg:address":"Dokter De Moorstraat 102",
    "sg:city":"Aalst",
    "sg:classifiers":[
        {
            "category":"Health Services",
            "subcategory":"Health Practitioner",
            "type":"Services"
        }
    ],
    "sg:phone":"+32 53 79 07 19",
    "sg:postcode":"9300",
    "sg:province":"Oost-Vlaanderen",
    "sg:tags":[
        "therapist",
        "speech"
    ],
    "wof:name":"Eemans V",
    "wof:placetype":"venue"
},
  "geometry": {"coordinates":[4.0450482368,50.946559906],"type":"Point"}
}