{
  "type": "Feature",
  "properties": {
    "iso:country":"BE",
    "sg:address":"Rozendaalstraat 42",
    "sg:city":"Alveringem",
    "sg:orig_category":"Royal Canin. Souvenirs and objets artisanaux. Animaux domestiques and accessoires. Articles de jardi",
    "sg:phone":"+32 58 28 82 18",
    "sg:postcode":"8890",
    "sg:province":"West-Vlaanderen",
    "wof:name":"Chaerel Gerdy",
    "wof:placetype":"venue"
},
  "geometry": {"coordinates":[2.7208609581,51.013923645],"type":"Point"}
}