{
  "type": "Feature",
  "properties": {
    "iso:country":"BE",
    "sg:address":"Moerstraat 8",
    "sg:city":"Zele",
    "sg:classifiers":[
        {
            "category":"Communications",
            "subcategory":"Film & Video Production",
            "type":"Services"
        }
    ],
    "sg:phone":"+32 52 45 18 80",
    "sg:postcode":"9240",
    "sg:province":"Oost-Vlaanderen",
    "sg:tags":[
        "mirror"
    ],
    "wof:name":"Famglas",
    "wof:placetype":"venue"
},
  "geometry": {"coordinates":[4.0410971642,51.0718307495],"type":"Point"}
}