{
  "type": "Feature",
  "properties": {
    "addr:full":"Mechelsesteenweg 63 Lier Antwerpen 2500",
    "addr:housenumber":"63",
    "addr:postcode":"2500",
    "addr:street":"Mechelsesteenweg",
    "iso:country":"BE",
    "sg:address":"Mechelsesteenweg 63",
    "sg:city":"Lier",
    "sg:classifiers":[
        {
            "category":"Building & Trades",
            "subcategory":"Construction",
            "type":"Services"
        }
    ],
    "sg:phone":"+32 3 475 95 19",
    "sg:postcode":"2500",
    "sg:province":"Antwerpen",
    "sg:tags":[
        "asphalt",
        "contractor"
    ],
    "wof:name":"Redac Nv",
    "wof:placetype":"venue"
},
  "geometry": {"coordinates":[4.5600700378,51.1296234131],"type":"Point"}
}