{
  "type": "Feature",
  "properties": {
    "iso:country":"BE",
    "sg:address":"Bookmolenstraat 1",
    "sg:city":"Hamme",
    "sg:orig_category":"Woningbouw",
    "sg:phone":"+32 52 47 39 47",
    "sg:postcode":"9220",
    "sg:province":"Oost-Vlaanderen",
    "wof:name":"Algemene Onderneming De Zogse Bouwwerken",
    "wof:placetype":"venue"
},
  "geometry": {"coordinates":[4.0905179977,51.0719947815],"type":"Point"}
}