{
  "type": "Feature",
  "properties": {
    "iso:country":"BE",
    "sg:address":"Dennendreef 18",
    "sg:city":"Nevele",
    "sg:orig_category":"Artsen and specialisten",
    "sg:phone":"+32 9 371 80 78",
    "sg:postcode":"9850",
    "sg:province":"Oost-Vlaanderen",
    "wof:name":"Marianne Bogaert",
    "wof:placetype":"venue"
},
  "geometry": {"coordinates":[3.5756049156,51.05991745],"type":"Point"}
}