{
  "type": "Feature",
  "properties": {
    "iso:country":"BE",
    "sg:address":"Jozef Balstraat 10",
    "sg:city":"Beveren",
    "sg:orig_category":"Installatie van houten of kunststof schrijnwerk",
    "sg:phone":"+32 3 755 52 62",
    "sg:postcode":"9120",
    "sg:province":"Oost-Vlaanderen",
    "wof:name":"Chris Colman",
    "wof:placetype":"venue"
},
  "geometry": {"coordinates":[4.2805190086,51.2169761658],"type":"Point"}
}