{
  "type": "Feature",
  "properties": {
    "iso:country":"BE",
    "sg:address":"Voskenslaan 5",
    "sg:city":"Gent",
    "sg:orig_category":"M\u00e9decins and sp\u00e9cialistes",
    "sg:phone":"+32 9 222 70 59",
    "sg:postcode":"9000",
    "sg:province":"Oost-Vlaanderen",
    "wof:name":"Eric Lacroix",
    "wof:placetype":"venue"
},
  "geometry": {"coordinates":[3.7084031105,51.0348587036],"type":"Point"}
}