{
  "type": "Feature",
  "properties": {
    "addr:full":"Rue Du Try Coquiat 5 Villers-la-ville Brabant Wallon 1495",
    "addr:housenumber":"5",
    "addr:postcode":"1495",
    "addr:street":"Rue Du Try Coquiat",
    "iso:country":"BE",
    "sg:address":"Rue Du Try Coquiat 5",
    "sg:city":"Villers-la-ville",
    "sg:orig_category":"Art and fournitures artistiques",
    "sg:phone":"+32 71 87 65 47",
    "sg:postcode":"1495",
    "sg:province":"Brabant Wallon",
    "wof:name":"Henri Segers",
    "wof:placetype":"venue"
},
  "geometry": {"coordinates":[4.4982690811,50.5618209839],"type":"Point"}
}