{
  "type": "Feature",
  "properties": {
    "iso:country":"BE",
    "sg:address":"Huivelde 67b1",
    "sg:city":"Zele",
    "sg:orig_category":"Eleveurs de bovins",
    "sg:phone":"+32 52 45 11 24",
    "sg:postcode":"9240",
    "sg:province":"Oost-Vlaanderen",
    "wof:name":"Paula Cleemput",
    "wof:placetype":"venue"
},
  "geometry": {"coordinates":[4.0611457825,51.0622215271],"type":"Point"}
}