{
  "type": "Feature",
  "properties": {
    "addr:full":"Rue Grande 146 Dinant Namur 5500",
    "addr:housenumber":"146",
    "addr:postcode":"5500",
    "addr:street":"Rue Grande",
    "iso:country":"BE",
    "sg:address":"Rue Grande 146",
    "sg:city":"Dinant",
    "sg:classifiers":[
        {
            "category":"Shopping",
            "subcategory":"Jewelry",
            "type":"Retail Goods"
        }
    ],
    "sg:phone":"+32 82 22 94 60",
    "sg:postcode":"5500",
    "sg:province":"Namur",
    "sg:tags":[
        "jeweller",
        "-"
    ],
    "wof:name":"Fontinoy (maison)/gelinne Mireille",
    "wof:placetype":"venue"
},
  "geometry": {"coordinates":[4.9129700661,50.260219574],"type":"Point"}
}