{
  "type": "Feature",
  "properties": {
    "iso:country":"BE",
    "sg:address":"Rue De L' Armistice 6",
    "sg:city":"Li\u00c8ge",
    "sg:orig_category":"Artsen and specialisten",
    "sg:phone":"+32 4 341 11 35",
    "sg:postcode":"4020",
    "sg:province":"Li\u00e8ge",
    "wof:name":"Duy Tri Tran",
    "wof:placetype":"venue"
},
  "geometry": {"coordinates":[5.5930609703,50.6401367188],"type":"Point"}
}