{
  "type": "Feature",
  "properties": {
    "iso:country":"BE",
    "sg:address":"Chemin De La Procession 5",
    "sg:city":"Mons",
    "sg:orig_category":"Boucheries",
    "sg:phone":"+32 65 33 91 95",
    "sg:postcode":"7000",
    "sg:province":"Hainaut",
    "wof:name":"Boucherie St.lazare",
    "wof:placetype":"venue"
},
  "geometry": {"coordinates":[3.9579880238,50.4655952454],"type":"Point"}
}