{
  "type": "Feature",
  "properties": {
    "iso:country":"BE",
    "sg:address":"Rue Des Ecoles 28",
    "sg:city":"Braives (ciplet)",
    "sg:classifiers":[
        {
            "category":"Communications",
            "type":"Services"
        }
    ],
    "sg:phone":"+32 19 54 64 49",
    "sg:postcode":"4260",
    "sg:province":"Li\u00e8ge",
    "sg:tags":[
        "translator"
    ],
    "wof:name":"Austrums L",
    "wof:placetype":"venue"
},
  "geometry": {"coordinates":[5.0893578529,50.6167106628],"type":"Point"}
}