{
  "type": "Feature",
  "properties": {
    "addr:full":"Rue Heyvaert 18 Bruxelles (molenbeek-saint-jean) Bruxelles-Capitale 1080",
    "addr:housenumber":"18",
    "addr:postcode":"1080",
    "addr:street":"Rue Heyvaert",
    "iso:country":"BE",
    "sg:address":"Rue Heyvaert 18",
    "sg:city":"Bruxelles (molenbeek-saint-jean)",
    "sg:classifiers":[
        {
            "category":"Retail",
            "subcategory":"Auto Repair",
            "type":"Services"
        }
    ],
    "sg:phone":"+32 2 523 23 41",
    "sg:postcode":"1080",
    "sg:province":"Bruxelles-Capitale",
    "sg:tags":[
        "garage"
    ],
    "wof:name":"Osman (auto)",
    "wof:placetype":"venue"
},
  "geometry": {"coordinates":[4.3348231316,50.8485908508],"type":"Point"}
}