{
  "type": "Feature",
  "properties": {
    "addr:full":"Chauss\u00c9e D'alsemberg 318 Vorst/forest Bruxelles-Capitale 1190",
    "addr:housenumber":"318",
    "addr:postcode":"1190",
    "addr:street":"Chausse\u0301E D'Alsemberg;/ Forest",
    "iso:country":"BE",
    "sg:address":"Chauss\u00c9e D'alsemberg 318",
    "sg:city":"Vorst/forest",
    "sg:orig_category":"Pharmaciens",
    "sg:phone":"+32 2 344 99 77",
    "sg:postcode":"1190",
    "sg:province":"Bruxelles-Capitale",
    "wof:name":"Pascale Vanhees",
    "wof:placetype":"venue"
},
  "geometry": {"coordinates":[4.3405508995,50.8170623779],"type":"Point"}
}