{
  "type": "Feature",
  "properties": {
    "addr:full":"Grondwetlaan 76 Gent Oost-Vlaanderen 9040",
    "addr:housenumber":"76",
    "addr:postcode":"9040",
    "addr:street":"Grondwetlaan;Oost-Vlaanderen",
    "iso:country":"BE",
    "sg:address":"Grondwetlaan 76",
    "sg:city":"Gent",
    "sg:orig_category":"Plomberie, chauffage and installations sanitaires. Charpentes and couvertures",
    "sg:phone":"+32 9 259 80 54",
    "sg:postcode":"9040",
    "sg:province":"Oost-Vlaanderen",
    "wof:name":"Algemene Aannemingen House Care",
    "wof:placetype":"venue"
},
  "geometry": {"coordinates":[3.7513380051,51.0673408508],"type":"Point"}
}