{
  "type": "Feature",
  "properties": {
    "addr:full":"Hageland 1 De Pinte Oost-Vlaanderen 9840",
    "addr:housenumber":"1",
    "addr:postcode":"9840",
    "addr:street":"Hageland",
    "iso:country":"BE",
    "sg:address":"Hageland 1",
    "sg:city":"De Pinte",
    "sg:classifiers":[
        {
            "category":"Real Estate",
            "subcategory":"Real Estate Services",
            "type":"Services"
        }
    ],
    "sg:phone":"+32 475 67 41 94",
    "sg:postcode":"9840",
    "sg:province":"Oost-Vlaanderen",
    "wof:name":"Vastgoed J Van Hoecke Bvba",
    "wof:placetype":"venue"
},
  "geometry": {"coordinates":[3.6644129753,50.9847259521],"type":"Point"}
}