{
  "type": "Feature",
  "properties": {
    "iso:country":"BE",
    "sg:address":"Grote Markt",
    "sg:city":"Zoutleeuw",
    "sg:orig_category":"Toeristische diensten",
    "sg:phone":"+32 11 78 12 88",
    "sg:postcode":"3440",
    "sg:province":"Vlaams-Brabant",
    "wof:name":"Dienst Voor Toerisme Zoutleeuw",
    "wof:placetype":"venue"
},
  "geometry": {"coordinates":[5.1037402153,50.8335494995],"type":"Point"}
}