{
  "type": "Feature",
  "properties": {
    "iso:country":"BE",
    "sg:address":"Plezantstraat 266",
    "sg:city":"Sint-niklaas",
    "sg:orig_category":"Krantenuitgeverijen Tijdschriftenuitgeverijen",
    "sg:phone":"+32 3 777 32 80",
    "sg:postcode":"9100",
    "sg:province":"Oost-Vlaanderen",
    "wof:name":"Instit. Voor Sportbeheer",
    "wof:placetype":"venue"
},
  "geometry": {"coordinates":[4.1274061203,51.1709671021],"type":"Point"}
}