{
  "type": "Feature",
  "properties": {
    "iso:country":"BE",
    "sg:address":"Avenue De L'observatoire 44",
    "sg:city":"Li\u00c8ge",
    "sg:orig_category":"M\u00e9decins and sp\u00e9cialistes",
    "sg:phone":"+32 4 253 29 89",
    "sg:postcode":"4000",
    "sg:province":"Li\u00e8ge",
    "wof:name":"Serge Mozin",
    "wof:placetype":"venue"
},
  "geometry": {"coordinates":[5.5617570877,50.6280136108],"type":"Point"}
}