{
  "type": "Feature",
  "properties": {
    "addr:full":"Goerenstraat 47 Lummen Limburg 3560",
    "addr:housenumber":"47",
    "addr:postcode":"3560",
    "addr:street":"Goerenstraat",
    "iso:country":"BE",
    "sg:address":"Goerenstraat 47",
    "sg:city":"Lummen",
    "sg:orig_category":"Non-Classified Establishments",
    "sg:phone":"+32 13 46 16 14",
    "sg:postcode":"3560",
    "sg:province":"Limburg",
    "wof:name":"G T C",
    "wof:placetype":"venue"
},
  "geometry": {"coordinates":[5.1579399109,50.9734611511],"type":"Point"}
}