{
  "type": "Feature",
  "properties": {
    "iso:country":"BE",
    "sg:address":"Rue N. D. D\u00c9bonnaire 16",
    "sg:city":"Mons",
    "sg:orig_category":"Advocaten and juridische adviseurs",
    "sg:phone":"+32 65 40 04 13",
    "sg:postcode":"7000",
    "sg:province":"Hainaut",
    "wof:name":"Nathalie Poncin",
    "wof:placetype":"venue"
},
  "geometry": {"coordinates":[3.9478709698,50.4547271729],"type":"Point"}
}