{
  "type": "Feature",
  "properties": {
    "iso:country":"BE",
    "sg:address":"Hougoumontlaan 17ba",
    "sg:city":"Ukkel/uccle",
    "sg:classifiers":[
        {
            "category":"Insurance",
            "subcategory":"Insurance Agent",
            "type":"Services"
        }
    ],
    "sg:phone":"+32 2 375 30 86",
    "sg:postcode":"1180",
    "sg:province":"Bruxelles-Capitale",
    "sg:tags":[
        "verzekeringsmakelaars",
        "expert"
    ],
    "wof:name":"Cetisa",
    "wof:placetype":"venue"
},
  "geometry": {"coordinates":[4.3809738159,50.7726593018],"type":"Point"}
}