{
  "type": "Feature",
  "properties": {
    "addr:full":"Emiel Caluslaan 1a Zelzate Oost-Vlaanderen 9060",
    "addr:housenumber":"1a",
    "addr:postcode":"9060",
    "addr:street":"Emiel Caluslaan",
    "iso:country":"BE",
    "sg:address":"Emiel Caluslaan 1a",
    "sg:city":"Zelzate",
    "sg:classifiers":[
        {
            "category":"Professional",
            "subcategory":"Accounting & Tax Preparation",
            "type":"Services"
        }
    ],
    "sg:phone":"+32 9 344 58 04",
    "sg:postcode":"9060",
    "sg:province":"Oost-Vlaanderen",
    "sg:tags":[
        "bookkeeper"
    ],
    "wof:name":"De Colvenaer L",
    "wof:placetype":"venue"
},
  "geometry": {"coordinates":[3.7947590351,51.2000770569],"type":"Point"}
}