{
  "type": "Feature",
  "properties": {
    "iso:country":"BE",
    "sg:address":"Rue Ren\u00c9 Delbrouck 55",
    "sg:city":"Seraing",
    "sg:classifiers":[
        {
            "category":"Personal",
            "subcategory":"Beauty Salon",
            "type":"Services"
        }
    ],
    "sg:phone":"+32 4 336 95 90",
    "sg:postcode":"4102",
    "sg:province":"Li\u00e8ge",
    "sg:tags":[
        "de",
        "coiffure"
    ],
    "wof:name":"Coiffure Infini'tif",
    "wof:placetype":"venue"
},
  "geometry": {"coordinates":[5.5345039368,50.5998916626],"type":"Point"}
}