{
  "type": "Feature",
  "properties": {
    "iso:country":"BE",
    "sg:address":"Route De L'ambleve 88",
    "sg:city":"Stoumont",
    "sg:orig_category":"Enseignement secondaire g\u00e9n\u00e9ral",
    "sg:phone":"+32 80 78 51 47",
    "sg:postcode":"4987",
    "sg:province":"Li\u00e8ge",
    "wof:name":"Ecole St.edouard",
    "wof:placetype":"venue"
},
  "geometry": {"coordinates":[5.808298111,50.4072151184],"type":"Point"}
}