{
  "type": "Feature",
  "properties": {
    "iso:country":"BE",
    "sg:address":"Blarenberglaan 21a",
    "sg:city":"Mechelen",
    "sg:classifiers":[
        {
            "category":"Home & Garden",
            "subcategory":"Carpets & Floor Coverings",
            "type":"Retail Goods"
        }
    ],
    "sg:phone":"+32 15 21 99 02",
    "sg:postcode":"2800",
    "sg:province":"Antwerpen",
    "sg:tags":[
        "industrial",
        "-"
    ],
    "wof:name":"Spectron Nv",
    "wof:placetype":"venue"
},
  "geometry": {"coordinates":[4.4509840012,51.0521621704],"type":"Point"}
}