{
  "type": "Feature",
  "properties": {
    "iso:country":"BE",
    "sg:address":"Avenue Des Combattants 94",
    "sg:city":"Gembloux-sur-orneau (gembloux)",
    "sg:classifiers":[
        {
            "category":"Health Services",
            "subcategory":"Nursing And Care Facility",
            "type":"Services"
        }
    ],
    "sg:phone":"+32 81 61 15 40",
    "sg:postcode":"5030",
    "sg:province":"Namur",
    "sg:tags":[
        "home",
        "rest"
    ],
    "wof:name":"Chanterelle (la)",
    "wof:placetype":"venue"
},
  "geometry": {"coordinates":[4.7034921646,50.5559082031],"type":"Point"}
}