{
  "type": "Feature",
  "properties": {
    "iso:country":"BE",
    "sg:address":"Coron-des-trys 24",
    "sg:city":"Anhee",
    "sg:orig_category":"Epiceries",
    "sg:phone":"+32 82 61 13 42",
    "sg:postcode":"5537",
    "sg:province":"Namur",
    "wof:name":"Marcelle Prumont",
    "wof:placetype":"venue"
},
  "geometry": {"coordinates":[4.8422241211,50.3063735962],"type":"Point"}
}