{
  "type": "Feature",
  "properties": {
    "iso:country":"BE",
    "sg:address":"Wapenmakerstraat 9",
    "sg:city":"Brugge",
    "sg:orig_category":"Antiek",
    "sg:phone":"+32 50 33 31 72",
    "sg:postcode":"8000",
    "sg:province":"West-Vlaanderen",
    "wof:name":"Frou-frou",
    "wof:placetype":"venue"
},
  "geometry": {"coordinates":[3.2264089584,51.2100105286],"type":"Point"}
}