{
  "type": "Feature",
  "properties": {
    "addr:full":"Kleine Schoolstraat 11 Huldenberg Vlaams-Brabant 3040",
    "addr:housenumber":"11",
    "addr:postcode":"3040",
    "addr:street":"Kleine Schoolstraat",
    "iso:country":"BE",
    "sg:address":"Kleine Schoolstraat 11",
    "sg:city":"Huldenberg",
    "sg:orig_category":"Woningbouw",
    "sg:phone":"+32 16 47 09 05",
    "sg:postcode":"3040",
    "sg:province":"Vlaams-Brabant",
    "wof:name":"Alain Fluyt",
    "wof:placetype":"venue"
},
  "geometry": {"coordinates":[4.6132411957,50.7497444153],"type":"Point"}
}