{
  "type": "Feature",
  "properties": {
    "addr:full":"Rue De Leumont 118 Wanze Li\u00e8ge 4520",
    "addr:housenumber":"118",
    "addr:postcode":"4520",
    "addr:street":"Rue De Leumont",
    "iso:country":"BE",
    "sg:address":"Rue De Leumont 118",
    "sg:city":"Wanze",
    "sg:orig_category":"Non-Classified Establishments",
    "sg:phone":"+32 85 21 48 78",
    "sg:postcode":"4520",
    "sg:province":"Li\u00e8ge",
    "wof:name":"Airlux Electromenager Sa",
    "wof:placetype":"venue"
},
  "geometry": {"coordinates":[5.2229790688,50.5348472595],"type":"Point"}
}