{
  "type": "Feature",
  "properties": {
    "iso:country":"BE",
    "sg:address":"Industrieterrein 1169",
    "sg:city":"Opglabbeek",
    "sg:orig_category":"Installation de menuiserie en bois and plastique",
    "sg:phone":"+32 89 85 53 62",
    "sg:postcode":"3660",
    "sg:province":"Limburg",
    "wof:name":"Amand",
    "wof:placetype":"venue"
},
  "geometry": {"coordinates":[5.5554099083,51.040813446],"type":"Point"}
}