{
  "type": "Feature",
  "properties": {
    "addr:full":"Rue Bruy\u00c8re 98 Andenne Namur 5300",
    "addr:housenumber":"98",
    "addr:postcode":"5300",
    "addr:street":"Rue Bruye\u0300Re",
    "iso:country":"BE",
    "sg:address":"Rue Bruy\u00c8re 98",
    "sg:city":"Andenne",
    "sg:orig_category":"Medische apparatuur, orthopedische artikelen and prothesen Fab",
    "sg:phone":"+32 81 58 21 11",
    "sg:postcode":"5300",
    "sg:province":"Namur",
    "wof:name":"Cabosart S.",
    "wof:placetype":"venue"
},
  "geometry": {"coordinates":[5.0297408104,50.4697647095],"type":"Point"}
}