{
  "type": "Feature",
  "properties": {
    "iso:country":"BE",
    "sg:address":"Dr.-vandeperrestraat 15",
    "sg:city":"Geel",
    "sg:orig_category":"Bloemen and planten Boomkwekerijen Tuinen",
    "sg:phone":"+32 14 58 81 27",
    "sg:postcode":"2440",
    "sg:province":"Antwerpen",
    "wof:name":"Andreas Vranckx",
    "wof:placetype":"venue"
},
  "geometry": {"coordinates":[4.9881777763,51.1699790955],"type":"Point"}
}