{
  "type": "Feature",
  "properties": {
    "addr:full":"Hoogstraat 75 Denderleeuw Oost-Vlaanderen 9472",
    "addr:housenumber":"75",
    "addr:postcode":"9472",
    "addr:street":"Hoogstraat",
    "iso:country":"BE",
    "sg:address":"Hoogstraat 75",
    "sg:city":"Denderleeuw",
    "sg:orig_category":"Eleveurs de bovins",
    "sg:phone":"+32 53 66 16 85",
    "sg:postcode":"9472",
    "sg:province":"Oost-Vlaanderen",
    "wof:name":"Emiel Van Den Haute",
    "wof:placetype":"venue"
},
  "geometry": {"coordinates":[4.0472698212,50.8755073547],"type":"Point"}
}