{
  "type": "Feature",
  "properties": {
    "addr:full":"Brederodestraat 2 Antwerpen Antwerpen 2018",
    "addr:housenumber":"2",
    "addr:postcode":"2018",
    "addr:street":"Brederodestraat",
    "iso:country":"BE",
    "sg:address":"Brederodestraat 2",
    "sg:city":"Antwerpen",
    "sg:orig_category":"Bloemen and planten",
    "sg:phone":"+32 3 237 73 34",
    "sg:postcode":"2018",
    "sg:province":"Antwerpen",
    "wof:name":"Frivoli",
    "wof:placetype":"venue"
},
  "geometry": {"coordinates":[4.3967051506,51.2068214417],"type":"Point"}
}