{
  "type": "Feature",
  "properties": {
    "addr:full":"Albert Giraudlaan 95 Schaarbeek/schaerbeek Bruxelles-Capitale 1030",
    "addr:housenumber":"95",
    "addr:postcode":"1030",
    "addr:street":"Albert Giraudlaan",
    "iso:country":"BE",
    "sg:address":"Albert Giraudlaan 95",
    "sg:city":"Schaarbeek/schaerbeek",
    "sg:orig_category":"Boekenuitgeverijen Platenmaatschappijen",
    "sg:phone":"+32 2 245 03 20",
    "sg:postcode":"1030",
    "sg:province":"Bruxelles-Capitale",
    "wof:name":"Emi Music Publish. Belg.",
    "wof:placetype":"venue"
},
  "geometry": {"coordinates":[4.3814201355,50.8751869202],"type":"Point"}
}