{
  "type": "Feature",
  "properties": {
    "iso:country":"BE",
    "sg:address":"Rue Albert Asou 14-16",
    "sg:city":"Tournai",
    "sg:classifiers":[
        {
            "category":"Professional",
            "subcategory":"Printing & Photocopies",
            "type":"Services"
        }
    ],
    "sg:phone":"+32 69 23 25 92",
    "sg:postcode":"7500",
    "sg:province":"Hainaut",
    "sg:tags":[
        "-",
        "offset"
    ],
    "wof:name":"Dransart M",
    "wof:placetype":"venue"
},
  "geometry": {"coordinates":[3.3954789639,50.6013183594],"type":"Point"}
}