{
  "type": "Feature",
  "properties": {
    "iso:country":"BE",
    "sg:address":"Grote Baan 57",
    "sg:city":"Beersel",
    "sg:orig_category":"Articles de jardin. Souvenirs and objets artisanaux. P\u00e9pini\u00e9ristes. Fleurs and plantes",
    "sg:phone":"+32 2 380 33 72",
    "sg:postcode":"1650",
    "sg:province":"Vlaams-Brabant",
    "wof:name":"Goldie Garden Center",
    "wof:placetype":"venue"
},
  "geometry": {"coordinates":[4.3094258308,50.7592277527],"type":"Point"}
}