{
  "type": "Feature",
  "properties": {
    "iso:country":"BE",
    "sg:address":"Chemin Du Bois Du Cur\u00e9 30",
    "sg:city":"Namur (w\u00e9pion)",
    "sg:classifiers":[
        {
            "category":"Insurance",
            "subcategory":"Insurance Agent",
            "type":"Services"
        }
    ],
    "sg:phone":"+32 81 46 08 99",
    "sg:postcode":"5100",
    "sg:province":"Namur",
    "sg:tags":[
        "broker"
    ],
    "wof:name":"Guilmot-dervaux",
    "wof:placetype":"venue"
},
  "geometry": {"coordinates":[4.8471641541,50.4177970886],"type":"Point"}
}