{
  "type": "Feature",
  "properties": {
    "addr:full":"Dorsel 46 Nijlen Antwerpen 2560",
    "addr:housenumber":"46",
    "addr:postcode":"2560",
    "addr:street":"Dorsel",
    "iso:country":"BE",
    "sg:address":"Dorsel 46",
    "sg:city":"Nijlen",
    "sg:orig_category":"Plaatsen van vloer- and muurbekleding",
    "sg:phone":"+32 3 481 92 05",
    "sg:postcode":"2560",
    "sg:province":"Antwerpen",
    "wof:name":"Franciscus Rombouts",
    "wof:placetype":"venue"
},
  "geometry": {"coordinates":[4.6828870773,51.1632575989],"type":"Point"}
}