{
  "type": "Feature",
  "properties": {
    "iso:country":"BE",
    "sg:address":"Molenstraat 40b",
    "sg:city":"Aalst",
    "sg:orig_category":"Medische and orthopedische apparaten Opticiens",
    "sg:phone":"+32 53 21 64 65",
    "sg:postcode":"9300",
    "sg:province":"Oost-Vlaanderen",
    "wof:name":"Optiek Lambert",
    "wof:placetype":"venue"
},
  "geometry": {"coordinates":[4.041364193,50.939239502],"type":"Point"}
}