{
  "type": "Feature",
  "properties": {
    "iso:country":"BE",
    "sg:address":"Rue Marchenal 8",
    "sg:city":"Ferri\u00e8res (xhoris)",
    "sg:classifiers":[
        {
            "category":"Wholesale",
            "subcategory":"Scrap",
            "type":"Manufacturing & Wholesale Goods"
        }
    ],
    "sg:phone":"+32 4 369 32 59",
    "sg:postcode":"4190",
    "sg:province":"Li\u00e8ge",
    "sg:tags":[
        "metal"
    ],
    "wof:name":"Balhan A",
    "wof:placetype":"venue"
},
  "geometry": {"coordinates":[5.608561039,50.4449081421],"type":"Point"}
}