{
  "type": "Feature",
  "properties": {
    "addr:full":"Galerie Regina 3 Liege Li\u00e8ge 4000",
    "addr:housenumber":"3",
    "addr:postcode":"4000",
    "iso:country":"BE",
    "sg:address":"Galerie Regina 3",
    "sg:city":"Liege",
    "sg:classifiers":[
        {
            "category":"Restaurant",
            "type":"Food & Drink"
        }
    ],
    "sg:phone":"+32 4 222 20 08",
    "sg:postcode":"4000",
    "sg:province":"Li\u00e8ge",
    "wof:name":"Le Nouvel Orient",
    "wof:placetype":"venue"
},
  "geometry": {"coordinates":[5.541164875,50.6114616394],"type":"Point"}
}