{
  "type": "Feature",
  "properties": {
    "iso:country":"BE",
    "sg:address":"Avenue Eug\u00c8ne Mascaux 517",
    "sg:city":"Charleroi",
    "sg:orig_category":"Brood, gebak and snoepgoed",
    "sg:phone":"+32 71 36 26 32",
    "sg:postcode":"6001",
    "sg:province":"Hainaut",
    "wof:name":"Le Fournil Du Bon Grain",
    "wof:placetype":"venue"
},
  "geometry": {"coordinates":[4.4350547791,50.3885040283],"type":"Point"}
}