{
  "type": "Feature",
  "properties": {
    "iso:country":"BE",
    "sg:address":"Wouwendonkstraat 213",
    "sg:city":"Duffel",
    "sg:orig_category":"D\u00e9chets and d\u00e9bris Gr",
    "sg:phone":"+32 15 31 34 53",
    "sg:postcode":"2570",
    "sg:province":"Antwerpen",
    "wof:name":"Frans Wynants",
    "wof:placetype":"venue"
},
  "geometry": {"coordinates":[4.4917149544,51.0996131897],"type":"Point"}
}