{
  "type": "Feature",
  "properties": {
    "addr:full":"Chauss\u00e9e De Gand 565 Bruxelles (molenbeek-saint-jean) Bruxelles-Capitale 1080",
    "addr:housenumber":"565",
    "addr:postcode":"1080",
    "addr:street":"Chausse\u0301E De Gand",
    "iso:country":"BE",
    "sg:address":"Chauss\u00e9e De Gand 565",
    "sg:city":"Bruxelles (molenbeek-saint-jean)",
    "sg:classifiers":[
        {
            "category":"Organizations",
            "subcategory":"Professional Association",
            "type":"Services"
        }
    ],
    "sg:phone":"+32 2 465 26 50",
    "sg:postcode":"1080",
    "sg:province":"Bruxelles-Capitale",
    "sg:tags":[
        "trade-union",
        "federation"
    ],
    "wof:name":"Patronale Brood- & Banketbakkersvereniging Van Brussel",
    "wof:placetype":"venue"
},
  "geometry": {"coordinates":[4.3082227707,50.8599433899],"type":"Point"}
}