{
  "type": "Feature",
  "properties": {
    "iso:country":"BE",
    "sg:address":"Kasteelstraat 201",
    "sg:city":"Buggenhout",
    "sg:classifiers":[
        {
            "category":"Real Estate",
            "subcategory":"Architect",
            "type":"Services"
        }
    ],
    "sg:phone":"+32 52 33 42 52",
    "sg:postcode":"9255",
    "sg:province":"Oost-Vlaanderen",
    "wof:name":"Achtergael W",
    "wof:placetype":"venue"
},
  "geometry": {"coordinates":[4.2136349678,50.9914894104],"type":"Point"}
}