{
  "type": "Feature",
  "properties": {
    "iso:country":"BE",
    "sg:address":"Puursesteenweg 325",
    "sg:city":"Bornem",
    "sg:orig_category":"Travaux de pl\u00e2trage. D\u00e9molition d\u00b4immeubles and terrassements",
    "sg:phone":"+32 3 889 30 41",
    "sg:postcode":"2880",
    "sg:province":"Antwerpen",
    "wof:name":"Spiessens Bruno",
    "wof:placetype":"venue"
},
  "geometry": {"coordinates":[4.2588629723,51.0858039856],"type":"Point"}
}