{
  "type": "Feature",
  "properties": {
    "addr:full":"'t Hasseltkiezel 32ba Bree Limburg 3960",
    "addr:housenumber":"32ba",
    "addr:postcode":"3960",
    "addr:street":"' T Hasseltkiezel",
    "iso:country":"BE",
    "sg:address":"'t Hasseltkiezel 32ba",
    "sg:city":"Bree",
    "sg:classifiers":[
        {
            "category":"Fast Food",
            "type":"Food & Drink"
        }
    ],
    "sg:phone":"+32 89 70 27 17",
    "sg:postcode":"3960",
    "sg:province":"Limburg",
    "sg:tags":[
        "meeneem",
        "restaurant"
    ],
    "wof:name":"Elvire Hermans",
    "wof:placetype":"venue"
},
  "geometry": {"coordinates":[5.6901140213,51.1436576843],"type":"Point"}
}