{
  "type": "Feature",
  "properties": {
    "iso:country":"BE",
    "sg:address":"Aalterseweg 62",
    "sg:city":"Knesselare",
    "sg:orig_category":"Mat\u00e9riaux de construction Gr",
    "sg:phone":"+32 9 374 46 68",
    "sg:postcode":"9910",
    "sg:province":"Oost-Vlaanderen",
    "wof:name":"Huis De Meyer W.",
    "wof:placetype":"venue"
},
  "geometry": {"coordinates":[3.4169530869,51.1313285828],"type":"Point"}
}