{
  "type": "Feature",
  "properties": {
    "addr:full":"Rijselsestraat 51 Ieper West-Vlaanderen 8900",
    "addr:housenumber":"51",
    "addr:postcode":"8900",
    "addr:street":"Rijselsestraat",
    "iso:country":"BE",
    "sg:address":"Rijselsestraat 51",
    "sg:city":"Ieper",
    "sg:orig_category":"R\u00e9alisation de programmes and logiciels",
    "sg:phone":"+32 57 22 61 60",
    "sg:postcode":"8900",
    "sg:province":"West-Vlaanderen",
    "wof:name":"Voxtron Flanders",
    "wof:placetype":"venue"
},
  "geometry": {"coordinates":[2.8873739243,50.8488235474],"type":"Point"}
}