{
  "type": "Feature",
  "properties": {
    "iso:country":"BE",
    "sg:address":"Rue De La Gare 12",
    "sg:city":"Vaux-sur-sure",
    "sg:orig_category":"Installation de menuiserie en bois and plastique. Fabrication and montage de mobilier",
    "sg:phone":"+32 61 26 60 71",
    "sg:postcode":"6640",
    "sg:province":"Luxembourg",
    "wof:name":"Lucien Dufour",
    "wof:placetype":"venue"
},
  "geometry": {"coordinates":[5.5671000481,49.91065979],"type":"Point"}
}