{
  "type": "Feature",
  "properties": {
    "iso:country":"BE",
    "sg:address":"Rue Pierre Michaux 31",
    "sg:city":"Oupeye (vivegnis)",
    "sg:classifiers":[
        {
            "category":"Health Services",
            "subcategory":"Health Practitioner",
            "type":"Services"
        }
    ],
    "sg:phone":"+32 497 60 42 24",
    "sg:postcode":"4683",
    "sg:province":"Li\u00e8ge",
    "sg:tags":[
        "physiotherapist"
    ],
    "wof:name":"Heens Bernard",
    "wof:placetype":"venue"
},
  "geometry": {"coordinates":[5.6483769417,50.6931419373],"type":"Point"}
}