{
  "type": "Feature",
  "properties": {
    "iso:country":"BE",
    "sg:address":"Hendrik Van Veldekesingel 150 Box 61",
    "sg:city":"Hasselt",
    "sg:classifiers":[
        {
            "category":"Building & Trades",
            "subcategory":"Plumbing",
            "type":"Services"
        }
    ],
    "sg:phone":"+32 800 99 913",
    "sg:postcode":"3500",
    "sg:province":"Limburg",
    "sg:tags":[
        "pipe",
        "drain",
        "unblocking"
    ],
    "wof:name":"Algemene Aanneming Rrs Bvba",
    "wof:placetype":"venue"
},
  "geometry": {"coordinates":[5.3152570724,50.9355430603],"type":"Point"}
}