{
  "type": "Feature",
  "properties": {
    "addr:full":"Hundelgemsesteenweg 192 Gent (ledeberg) Oost-Vlaanderen 9050",
    "addr:housenumber":"192",
    "addr:postcode":"9050",
    "addr:street":"Hundelgemsesteenweg",
    "iso:country":"BE",
    "sg:address":"Hundelgemsesteenweg 192",
    "sg:city":"Gent (ledeberg)",
    "sg:classifiers":[
        {
            "category":"Food & Beverages",
            "subcategory":"Groceries & Convenience Stores",
            "type":"Retail Goods"
        }
    ],
    "sg:phone":"+32 9 230 70 62",
    "sg:postcode":"9050",
    "sg:province":"Oost-Vlaanderen",
    "sg:tags":[
        "grocer"
    ],
    "wof:name":"Fruithof",
    "wof:placetype":"venue"
},
  "geometry": {"coordinates":[3.7589480877,51.0448532104],"type":"Point"}
}