{
  "type": "Feature",
  "properties": {
    "addr:full":"Torenvenstraat 25 Nijlen (kessel) Antwerpen 2560",
    "addr:housenumber":"25",
    "addr:postcode":"2560",
    "addr:street":"Torenvenstraat",
    "iso:country":"BE",
    "sg:address":"Torenvenstraat 25",
    "sg:city":"Nijlen (kessel)",
    "sg:classifiers":[
        {
            "category":"Building & Trades",
            "subcategory":"Electrical",
            "type":"Services"
        }
    ],
    "sg:phone":"+32 3 489 03 24",
    "sg:postcode":"2560",
    "sg:province":"Antwerpen",
    "sg:tags":[
        "electric",
        "-",
        "housewiring",
        "contractor"
    ],
    "wof:name":"Elvaco",
    "wof:placetype":"venue"
},
  "geometry": {"coordinates":[4.6125531197,51.1507415771],"type":"Point"}
}