{
  "type": "Feature",
  "properties": {
    "addr:full":"Chauss\u00c9e De Bruxelles 1b1 Nivelles Brabant Wallon 1400",
    "addr:postcode":"1b1;1400",
    "addr:street":"Chausse\u0301E De Bruxelles",
    "iso:country":"BE",
    "sg:address":"Chauss\u00c9e De Bruxelles 1b1",
    "sg:city":"Nivelles",
    "sg:orig_category":"Assistances juridiques. Conseillers fiscaux",
    "sg:phone":"+32 67 21 70 40",
    "sg:postcode":"1400",
    "sg:province":"Brabant Wallon",
    "wof:name":"Kirsch & Fils",
    "wof:placetype":"venue"
},
  "geometry": {"coordinates":[4.3262071609,50.6004371643],"type":"Point"}
}