{
  "type": "Feature",
  "properties": {
    "iso:country":"BE",
    "sg:address":"Neerwaastensestraat 19",
    "sg:city":"Ieper",
    "sg:orig_category":"Airconditioning and ventilatie Elektrische installaties voor woningen Loodgieterij, verwarming and s",
    "sg:phone":"+32 57 20 32 75",
    "sg:postcode":"8902",
    "sg:province":"West-Vlaanderen",
    "wof:name":"Rene Goudezeune",
    "wof:placetype":"venue"
},
  "geometry": {"coordinates":[2.9366559982,50.7966079712],"type":"Point"}
}