{
  "type": "Feature",
  "properties": {
    "addr:full":"Wijnheuvelenstraat 128 Schaarbeek/schaerbeek Bruxelles-Capitale 1030",
    "addr:housenumber":"128",
    "addr:postcode":"1030",
    "addr:street":"Wijnheuvelenstraat",
    "iso:country":"BE",
    "sg:address":"Wijnheuvelenstraat 128",
    "sg:city":"Schaarbeek/schaerbeek",
    "sg:orig_category":"Industri\u00eble wasserijen and droogkuis",
    "sg:phone":"+32 2 216 56 06",
    "sg:postcode":"1030",
    "sg:province":"Bruxelles-Capitale",
    "wof:name":"Quick-wash",
    "wof:placetype":"venue"
},
  "geometry": {"coordinates":[4.3765377998,50.8580093384],"type":"Point"}
}