{
  "type": "Feature",
  "properties": {
    "iso:country":"BE",
    "sg:address":"Rue Du Duc 67",
    "sg:city":"Sint-pieters-woluwe/woluwe-saint-pierre",
    "sg:orig_category":"Quincailleries",
    "sg:phone":"+32 2 772 00 47",
    "sg:postcode":"1150",
    "sg:province":"Bruxelles-Capitale",
    "wof:name":"Hydro-services",
    "wof:placetype":"venue"
},
  "geometry": {"coordinates":[4.4134092331,50.8378601074],"type":"Point"}
}