{
  "type": "Feature",
  "properties": {
    "iso:country":"BE",
    "sg:address":"Sweigers-zuid 12",
    "sg:city":"Temse",
    "sg:orig_category":"Eleveurs and marchands de porcs",
    "sg:phone":"+32 3 771 43 35",
    "sg:postcode":"9140",
    "sg:province":"Oost-Vlaanderen",
    "wof:name":"Heynro",
    "wof:placetype":"venue"
},
  "geometry": {"coordinates":[4.2062249184,51.1506767273],"type":"Point"}
}