{
  "type": "Feature",
  "properties": {
    "iso:country":"BE",
    "sg:address":"Venlosesteenweg 375",
    "sg:city":"Kinrooi",
    "sg:orig_category":"Meubles D\u00e9taillants, Am\u00e9nagement de B\u00e2timents et de Cuisines",
    "sg:phone":"+32 89 56 52 37",
    "sg:postcode":"3640",
    "sg:province":"Limburg",
    "wof:name":"T. Meubel",
    "wof:placetype":"venue"
},
  "geometry": {"coordinates":[5.8054800034,51.1356201172],"type":"Point"}
}