{
  "type": "Feature",
  "properties": {
    "iso:country":"BE",
    "sg:address":"Rue Des M\u00fbriers 16",
    "sg:city":"Bl\u00e9gny (saive)",
    "sg:classifiers":[
        {
            "category":"Food & Beverages",
            "subcategory":"Meat & Fish",
            "type":"Retail Goods"
        }
    ],
    "sg:phone":"+32 4 370 06 48",
    "sg:postcode":"4671",
    "sg:province":"Li\u00e8ge",
    "sg:tags":[
        "-",
        "livestock"
    ],
    "wof:name":"Dorimait Sc",
    "wof:placetype":"venue"
},
  "geometry": {"coordinates":[5.6713762283,50.6447067261],"type":"Point"}
}