{
  "type": "Feature",
  "properties": {
    "iso:country":"BE",
    "sg:address":"Waterstraat 18",
    "sg:city":"Tongeren",
    "sg:orig_category":"Blanchisseries and teintureries",
    "sg:phone":"+32 12 23 19 22",
    "sg:postcode":"3700",
    "sg:province":"Limburg",
    "wof:name":"Jekershop",
    "wof:placetype":"venue"
},
  "geometry": {"coordinates":[5.5292201042,50.7669830322],"type":"Point"}
}