{
  "type": "Feature",
  "properties": {
    "addr:full":"Korenbloemstraat 92b Torhout West-Vlaanderen 8820",
    "addr:housenumber":"92b",
    "addr:postcode":"8820",
    "addr:street":"Korenbloemstraat",
    "iso:country":"BE",
    "sg:address":"Korenbloemstraat 92b",
    "sg:city":"Torhout",
    "sg:classifiers":[
        {
            "category":"Freight",
            "type":"Transportation"
        }
    ],
    "sg:phone":"+32 50 21 58 43",
    "sg:postcode":"8820",
    "sg:province":"West-Vlaanderen",
    "sg:tags":[
        "-",
        "transport"
    ],
    "wof:name":"Vanhove Lieven Bvba",
    "wof:placetype":"venue"
},
  "geometry": {"coordinates":[3.1455130577,51.0827674866],"type":"Point"}
}