{
  "type": "Feature",
  "properties": {
    "addr:full":"Salvialei 110 Schoten Antwerpen 2900",
    "addr:housenumber":"110",
    "addr:postcode":"2900",
    "addr:street":"Salvialei",
    "iso:country":"BE",
    "sg:address":"Salvialei 110",
    "sg:city":"Schoten",
    "sg:orig_category":"Secr\u00e9tariats",
    "sg:phone":"+32 3 645 37 77",
    "sg:postcode":"2900",
    "sg:province":"Antwerpen",
    "wof:name":"Marianne Borm",
    "wof:placetype":"venue"
},
  "geometry": {"coordinates":[4.4584589005,51.2452087402],"type":"Point"}
}