{
  "type": "Feature",
  "properties": {
    "iso:country":"BE",
    "sg:address":"Rue Du Ch\u00c2telet 8",
    "sg:city":"Stavelot",
    "sg:orig_category":"D\u00e9molition d\u00b4immeubles and terrassements",
    "sg:phone":"+32 80 88 07 81",
    "sg:postcode":"4970",
    "sg:province":"Li\u00e8ge",
    "wof:name":"Desmedt P & P",
    "wof:placetype":"venue"
},
  "geometry": {"coordinates":[5.9309740067,50.3932151794],"type":"Point"}
}