{
  "type": "Feature",
  "properties": {
    "addr:full":"Rue Du Reigersvliet 7 Bruxelles (etterbeek) Bruxelles-Capitale 1040",
    "addr:housenumber":"7",
    "addr:postcode":"1040",
    "addr:street":"Rue Du Reigersvliet",
    "iso:country":"BE",
    "sg:address":"Rue Du Reigersvliet 7",
    "sg:city":"Bruxelles (etterbeek)",
    "sg:classifiers":[
        {
            "category":"Real Estate",
            "subcategory":"Architect",
            "type":"Services"
        }
    ],
    "sg:phone":"+32 2 649 42 38",
    "sg:postcode":"1040",
    "sg:province":"Bruxelles-Capitale",
    "wof:name":"M\u00e9dori Sprl - Atelier D'architecture Pottier-roba",
    "wof:placetype":"venue"
},
  "geometry": {"coordinates":[4.3883118629,50.8263244629],"type":"Point"}
}