{
  "type": "Feature",
  "properties": {
    "addr:full":"Polderstraat 5 Tielt West-Vlaanderen 8700",
    "addr:housenumber":"5",
    "addr:postcode":"8700",
    "addr:street":"Polderstraat",
    "iso:country":"BE",
    "sg:address":"Polderstraat 5",
    "sg:city":"Tielt",
    "sg:classifiers":[
        {
            "category":"Animal Shelter",
            "type":"Public Place"
        }
    ],
    "sg:phone":"+32 51 68 69 29",
    "sg:postcode":"8700",
    "sg:province":"West-Vlaanderen",
    "sg:tags":[
        "construction",
        "installation",
        "stable"
    ],
    "wof:name":"Callens L",
    "wof:placetype":"venue"
},
  "geometry": {"coordinates":[3.3599750996,51.0254058838],"type":"Point"}
}