{
  "type": "Feature",
  "properties": {
    "iso:country":"BE",
    "sg:address":"Rue Du Repos 41",
    "sg:city":"Bruxelles (uccle)",
    "sg:classifiers":[
        {
            "category":"Social Services",
            "subcategory":"Job Training",
            "type":"Services"
        }
    ],
    "sg:phone":"+32 2 375 99 00",
    "sg:postcode":"1180",
    "sg:province":"Bruxelles-Capitale",
    "sg:tags":[
        "interpreter"
    ],
    "wof:name":"Vandenplas I",
    "wof:placetype":"venue"
},
  "geometry": {"coordinates":[4.344315052,50.796672821],"type":"Point"}
}