{
  "type": "Feature",
  "properties": {
    "addr:full":"Wielsbekestraat 20 Oostrozebeke West-Vlaanderen 8780",
    "addr:housenumber":"20",
    "addr:postcode":"8780",
    "addr:street":"Wielsbekestraat",
    "iso:country":"BE",
    "sg:address":"Wielsbekestraat 20",
    "sg:city":"Oostrozebeke",
    "sg:classifiers":[
        {
            "category":"Utilities",
            "subcategory":"Cable",
            "type":"Services"
        }
    ],
    "sg:phone":"+32 56 66 62 60",
    "sg:postcode":"8780",
    "sg:province":"West-Vlaanderen",
    "sg:tags":[
        "rope",
        "twine"
    ],
    "wof:name":"Vanoutrive Nv",
    "wof:placetype":"venue"
},
  "geometry": {"coordinates":[3.3369350433,50.9204101562],"type":"Point"}
}