{
  "type": "Feature",
  "properties": {
    "iso:country":"BE",
    "sg:address":"Lange Nieuwstraat 74",
    "sg:city":"Antwerpen",
    "sg:orig_category":"Enseignement secondaire g\u00e9n\u00e9ral. Enseignement maternel and primaire",
    "sg:phone":"+32 3 234 02 68",
    "sg:postcode":"2000",
    "sg:province":"Antwerpen",
    "wof:name":"Vrije Basisschool",
    "wof:placetype":"venue"
},
  "geometry": {"coordinates":[4.4108529091,51.2193984985],"type":"Point"}
}