{
  "type": "Feature",
  "properties": {
    "addr:full":"Molenstraat 21 Nieuwerkerken Limburg 3850",
    "addr:housenumber":"21",
    "addr:postcode":"3850",
    "addr:street":"Molenstraat",
    "iso:country":"BE",
    "sg:address":"Molenstraat 21",
    "sg:city":"Nieuwerkerken",
    "sg:orig_category":"Eleveurs de bovins. Producteurs de fruits",
    "sg:phone":"+32 11 68 48 87",
    "sg:postcode":"3850",
    "sg:province":"Limburg",
    "wof:name":"Frans Vanrusselt",
    "wof:placetype":"venue"
},
  "geometry": {"coordinates":[5.1931529045,50.8640937805],"type":"Point"}
}