{
  "type": "Feature",
  "properties": {
    "iso:country":"BE",
    "sg:address":"Square Des Primev\u00c8res 19",
    "sg:city":"Seraing",
    "sg:orig_category":"Boekenuitgeverijen",
    "sg:phone":"+32 4 338 24 65",
    "sg:postcode":"4100",
    "sg:province":"Li\u00e8ge",
    "wof:name":"Editions Custers Eric",
    "wof:placetype":"venue"
},
  "geometry": {"coordinates":[5.5152587891,50.5815658569],"type":"Point"}
}