{
  "type": "Feature",
  "properties": {
    "iso:country":"BE",
    "sg:address":"Karel Nerinckxlaan 145",
    "sg:city":"Halle",
    "sg:classifiers":[
        {
            "category":"Personal",
            "subcategory":"Beauty Salon",
            "type":"Services"
        }
    ],
    "sg:phone":"+32 2 356 48 15",
    "sg:postcode":"1500",
    "sg:province":"Vlaams-Brabant",
    "sg:tags":[
        "de",
        "coiffure"
    ],
    "wof:name":"Johan Lories",
    "wof:placetype":"venue"
},
  "geometry": {"coordinates":[4.2490792274,50.734249115],"type":"Point"}
}