{
  "type": "Feature",
  "properties": {
    "iso:country":"BE",
    "sg:address":"Jules G\u00c9nicotlaan 4b14",
    "sg:city":"Oudergem/auderghem",
    "sg:orig_category":"Artsen and specialisten",
    "sg:phone":"+32 2 673 12 55",
    "sg:postcode":"1160",
    "sg:province":"Bruxelles-Capitale",
    "wof:name":"Mohammed Issam Al-kahhale Al-kahhal",
    "wof:placetype":"venue"
},
  "geometry": {"coordinates":[4.4281878471,50.8204269409],"type":"Point"}
}