{
  "type": "Feature",
  "properties": {
    "iso:country":"BE",
    "sg:address":"Avenue Du Marouset 23",
    "sg:city":"Braine-le-comte",
    "sg:orig_category":"Artsen and specialisten",
    "sg:phone":"+32 67 56 06 02",
    "sg:postcode":"7090",
    "sg:province":"Hainaut",
    "wof:name":"Jean-louis Ricour",
    "wof:placetype":"venue"
},
  "geometry": {"coordinates":[4.1494679451,50.6066436768],"type":"Point"}
}