{
  "type": "Feature",
  "properties": {
    "iso:country":"BE",
    "sg:address":"Magerakkerlaan 14",
    "sg:city":"Lochristi",
    "sg:orig_category":"Cr\u00e9meries",
    "sg:phone":"+32 9 355 68 59",
    "sg:postcode":"9080",
    "sg:province":"Oost-Vlaanderen",
    "wof:name":"Paul Van Wanzeele",
    "wof:placetype":"venue"
},
  "geometry": {"coordinates":[3.8565449715,51.0971374512],"type":"Point"}
}