{
  "type": "Feature",
  "properties": {
    "iso:country":"BE",
    "sg:address":"Salmch\u00e2teau",
    "sg:city":"Vielsalm",
    "sg:classifiers":[
        {
            "category":"Health Services",
            "subcategory":"Health Practitioner",
            "type":"Services"
        }
    ],
    "sg:phone":"+32 80 21 47 92",
    "sg:postcode":"6690",
    "sg:province":"Luxembourg",
    "sg:tags":[
        "physiotherapist"
    ],
    "wof:name":"Lecomte Anne-fran\u00e7oise",
    "wof:placetype":"venue"
},
  "geometry": {"coordinates":[5.9167118073,50.28540802],"type":"Point"}
}