{
  "type": "Feature",
  "properties": {
    "iso:country":"BE",
    "sg:address":"Rue Fran\u00c7ois-paquay 21",
    "sg:city":"Li\u00c8ge",
    "sg:orig_category":"Instituts de beaut\u00e9",
    "sg:phone":"+32 4 343 50 94",
    "sg:postcode":"4031",
    "sg:province":"Li\u00e8ge",
    "wof:name":"Jeanine Hanoset",
    "wof:placetype":"venue"
},
  "geometry": {"coordinates":[5.599583149,50.6115036011],"type":"Point"}
}