{
  "type": "Feature",
  "properties": {
    "iso:country":"BE",
    "sg:address":"Veldegemsestraat 13",
    "sg:city":"Oostkamp",
    "sg:orig_category":"Afbraak- and draineerwerken Antiek Hout and afgeleiden Gh IJzerwaren, bouw- and verfmaterialen",
    "sg:phone":"+32 50 27 71 96",
    "sg:postcode":"8020",
    "sg:province":"West-Vlaanderen",
    "wof:name":"Van Haelemeesch",
    "wof:placetype":"venue"
},
  "geometry": {"coordinates":[3.1883459091,51.1015586853],"type":"Point"}
}