{
  "type": "Feature",
  "properties": {
    "iso:country":"BE",
    "sg:address":"Landsdijk 116",
    "sg:city":"Assenede",
    "sg:orig_category":"Eleveurs de bovins",
    "sg:phone":"+32 9 373 63 13",
    "sg:postcode":"9968",
    "sg:province":"Oost-Vlaanderen",
    "wof:name":"Xavier Claeys",
    "wof:placetype":"venue"
},
  "geometry": {"coordinates":[3.6450600624,51.2526741028],"type":"Point"}
}