{
  "type": "Feature",
  "properties": {
    "addr:full":"Scheldestraat 29 Gavere Oost-Vlaanderen 9890",
    "addr:housenumber":"29",
    "addr:postcode":"9890",
    "addr:street":"Scheldestraat",
    "iso:country":"BE",
    "sg:address":"Scheldestraat 29",
    "sg:city":"Gavere",
    "sg:classifiers":[
        {
            "category":"Shopping",
            "subcategory":"Clothing, Apparel, & Fashions",
            "type":"Retail Goods"
        }
    ],
    "sg:phone":"+32 9 384 12 32",
    "sg:postcode":"9890",
    "sg:province":"Oost-Vlaanderen",
    "sg:tags":[
        "clothing",
        "-",
        "gentleman"
    ],
    "wof:name":"Derbysport",
    "wof:placetype":"venue"
},
  "geometry": {"coordinates":[3.6570060253,50.9300537109],"type":"Point"}
}