{
  "type": "Feature",
  "properties": {
    "addr:full":"Markt 28 Deinze Oost-Vlaanderen 9800",
    "addr:housenumber":"28",
    "addr:postcode":"9800",
    "addr:street":"Markt",
    "iso:country":"BE",
    "sg:address":"Markt 28",
    "sg:city":"Deinze",
    "sg:orig_category":"Pain, p\u00e2tisseries and confiseries",
    "sg:phone":"+32 9 386 59 01",
    "sg:postcode":"9800",
    "sg:province":"Oost-Vlaanderen",
    "wof:name":"Boutique D\u00c9lifrance",
    "wof:placetype":"venue"
},
  "geometry": {"coordinates":[3.5267400742,50.9836425781],"type":"Point"}
}