{
  "type": "Feature",
  "properties": {
    "iso:country":"BE",
    "sg:address":"Laar 28",
    "sg:city":"Mol",
    "sg:classifiers":[
        {
            "category":"Home & Garden",
            "subcategory":"Household Appliances",
            "type":"Retail Goods"
        }
    ],
    "sg:phone":"+32 14 31 51 33",
    "sg:postcode":"2400",
    "sg:province":"Antwerpen",
    "sg:tags":[
        "housewares",
        "-"
    ],
    "wof:name":"Blokker Nv",
    "wof:placetype":"venue"
},
  "geometry": {"coordinates":[5.1191000938,51.1867790222],"type":"Point"}
}