{
  "type": "Feature",
  "properties": {
    "addr:full":"Leybos 5 Rotselaar Vlaams-Brabant 3118",
    "addr:housenumber":"5",
    "addr:postcode":"3118",
    "addr:street":"Leybos",
    "iso:country":"BE",
    "sg:address":"Leybos 5",
    "sg:city":"Rotselaar",
    "sg:orig_category":"Installation \u00e9lectrique r\u00e9sidentielle",
    "sg:phone":"+32 16 53 76 19",
    "sg:postcode":"3118",
    "sg:province":"Vlaams-Brabant",
    "wof:name":"Eldotech",
    "wof:placetype":"venue"
},
  "geometry": {"coordinates":[4.6940898895,50.970489502],"type":"Point"}
}