{
  "type": "Feature",
  "properties": {
    "iso:country":"BE",
    "sg:address":"Rue De Mons 47",
    "sg:city":"Tubize",
    "sg:orig_category":"Instituts de beaut\u00e9. Articles de jardin. Drogueries",
    "sg:phone":"+32 2 355 65 58",
    "sg:postcode":"1480",
    "sg:province":"Brabant Wallon",
    "wof:name":"Lenaerts",
    "wof:placetype":"venue"
},
  "geometry": {"coordinates":[4.203318119,50.6915245056],"type":"Point"}
}