{
  "type": "Feature",
  "properties": {
    "iso:country":"BE",
    "sg:address":"Faliestraat 1",
    "sg:city":"Zottegem",
    "sg:orig_category":"Enseignement maternel and primaire",
    "sg:phone":"+32 9 360 23 51",
    "sg:postcode":"9620",
    "sg:province":"Oost-Vlaanderen",
    "wof:name":"Vrije Basisschool",
    "wof:placetype":"venue"
},
  "geometry": {"coordinates":[3.7977519035,50.8324890137],"type":"Point"}
}