{
  "type": "Feature",
  "properties": {
    "addr:full":"Hernestraat 38 Edingen/enghien Hainaut 7850",
    "addr:housenumber":"38",
    "addr:postcode":"7850",
    "addr:street":"Hernestraat",
    "iso:country":"BE",
    "sg:address":"Hernestraat 38",
    "sg:city":"Edingen/enghien",
    "sg:orig_category":"Apotheken",
    "sg:phone":"+32 2 395 30 63",
    "sg:postcode":"7850",
    "sg:province":"Hainaut",
    "wof:name":"R. Duwijn",
    "wof:placetype":"venue"
},
  "geometry": {"coordinates":[4.0384960175,50.6944618225],"type":"Point"}
}