{
  "type": "Feature",
  "properties": {
    "iso:country":"BE",
    "sg:address":"Klijtstraat 61",
    "sg:city":"Anzegem (ingooigem)",
    "sg:classifiers":[
        {
            "category":"Building & Trades",
            "subcategory":"Electrical",
            "type":"Services"
        }
    ],
    "sg:phone":"+32 56 77 84 02",
    "sg:postcode":"8570",
    "sg:province":"West-Vlaanderen",
    "sg:tags":[
        "industrial",
        "-",
        "electric",
        "contractor"
    ],
    "wof:name":"Lanneau-mollet Nv",
    "wof:placetype":"venue"
},
  "geometry": {"coordinates":[3.4223370552,50.8369750977],"type":"Point"}
}