{
  "type": "Feature",
  "properties": {
    "iso:country":"BE",
    "sg:address":"Kapelsestraat 90",
    "sg:city":"Kapellen",
    "sg:orig_category":"M\u00e9decins and sp\u00e9cialistes",
    "sg:phone":"+32 3 664 09 99",
    "sg:postcode":"2950",
    "sg:province":"Antwerpen",
    "wof:name":"L. Janssens",
    "wof:placetype":"venue"
},
  "geometry": {"coordinates":[4.4189209938,51.3259811401],"type":"Point"}
}