{
  "type": "Feature",
  "properties": {
    "addr:full":"Boulevard De L'h\u00f4pital 6 Ath Hainaut 7800",
    "addr:housenumber":"6",
    "addr:postcode":"7800",
    "addr:street":"Boulevard De L'Ho \u0302Pital",
    "iso:country":"BE",
    "sg:address":"Boulevard De L'h\u00f4pital 6",
    "sg:city":"Ath",
    "sg:classifiers":[
        {
            "category":"Sports & Exercise",
            "subcategory":"Gym",
            "type":"Entertainment"
        }
    ],
    "sg:phone":"+32 475 71 07 87",
    "sg:postcode":"7800",
    "sg:province":"Hainaut",
    "sg:tags":[
        "fitness"
    ],
    "wof:name":"Universal Gym",
    "wof:placetype":"venue"
},
  "geometry": {"coordinates":[3.7847900391,50.6294555664],"type":"Point"}
}