{
  "type": "Feature",
  "properties": {
    "iso:country":"BE",
    "sg:address":"Chauss\u00c9e De Charleroi 21",
    "sg:city":"Jodoigne",
    "sg:orig_category":"Traitements param\u00e9dicaux",
    "sg:phone":"+32 10 81 42 77",
    "sg:postcode":"1370",
    "sg:province":"Brabant Wallon",
    "wof:name":"De Riemaecker",
    "wof:placetype":"venue"
},
  "geometry": {"coordinates":[4.8684010506,50.7189941406],"type":"Point"}
}