{
  "type": "Feature",
  "properties": {
    "iso:country":"BE",
    "sg:address":"Schoonderbeukenweg 352",
    "sg:city":"Aarschot",
    "sg:orig_category":"Loodgieterij, verwarming and sanitaire installaties",
    "sg:phone":"+32 16 50 13 93",
    "sg:postcode":"3202",
    "sg:province":"Vlaams-Brabant",
    "wof:name":"Fa. Vos M. & Zn",
    "wof:placetype":"venue"
},
  "geometry": {"coordinates":[4.9285650253,50.9690132141],"type":"Point"}
}