{
  "type": "Feature",
  "properties": {
    "addr:full":"Magerhoek 1 Destelbergen Oost-Vlaanderen 9070",
    "addr:housenumber":"1",
    "addr:postcode":"9070",
    "addr:street":"Magerhoek",
    "iso:country":"BE",
    "sg:address":"Magerhoek 1",
    "sg:city":"Destelbergen",
    "sg:orig_category":"Bloemen and planten Gh",
    "sg:phone":"+32 9 230 89 17",
    "sg:postcode":"9070",
    "sg:province":"Oost-Vlaanderen",
    "wof:name":"Van Eeckhaute M",
    "wof:placetype":"venue"
},
  "geometry": {"coordinates":[3.8136401176,51.0252799988],"type":"Point"}
}