{
  "type": "Feature",
  "properties": {
    "addr:full":"Fabriekweg 38 Ichtegem West-Vlaanderen 8480",
    "addr:housenumber":"38",
    "addr:postcode":"8480",
    "addr:street":"Fabriekweg",
    "iso:country":"BE",
    "sg:address":"Fabriekweg 38",
    "sg:city":"Ichtegem",
    "sg:orig_category":"Loodgieterij, verwarming and sanitaire installaties",
    "sg:phone":"+32 59 29 02 52",
    "sg:postcode":"8480",
    "sg:province":"West-Vlaanderen",
    "wof:name":"Dirk Vierstraete",
    "wof:placetype":"venue"
},
  "geometry": {"coordinates":[3.0181109905,51.1256103516],"type":"Point"}
}