{
  "type": "Feature",
  "properties": {
    "iso:country":"BE",
    "sg:address":"Stationsstraat 32",
    "sg:city":"Harelbeke",
    "sg:classifiers":[
        {
            "category":"Cafe",
            "type":"Food & Drink"
        }
    ],
    "sg:phone":"+32 56 71 20 27",
    "sg:postcode":"8530",
    "sg:province":"West-Vlaanderen",
    "sg:tags":[
        "caf\u00e9s"
    ],
    "wof:name":"Caf\u00c9 't Postje",
    "wof:placetype":"venue"
},
  "geometry": {"coordinates":[3.3130390644,50.8560409546],"type":"Point"}
}