{
  "type": "Feature",
  "properties": {
    "iso:country":"BE",
    "sg:address":"Rue Des Cul\u00e9es 8",
    "sg:city":"Fleurus (wanferc\u00e9e-baulet)",
    "sg:classifiers":[
        {
            "category":"Fast Food",
            "type":"Food & Drink"
        }
    ],
    "sg:phone":"+32 71 81 92 96",
    "sg:postcode":"6224",
    "sg:province":"Hainaut",
    "sg:tags":[
        "fried",
        "stand",
        "potato"
    ],
    "wof:name":"Chez Beatrice",
    "wof:placetype":"venue"
},
  "geometry": {"coordinates":[4.5867700577,50.4627838135],"type":"Point"}
}