{
  "type": "Feature",
  "properties": {
    "addr:full":"Avenue Reine Louise-marie 3 Mouscron Hainaut 7700",
    "addr:housenumber":"3",
    "addr:postcode":"7700",
    "addr:street":"Avenue Reine Louise-Marie",
    "iso:country":"BE",
    "sg:address":"Avenue Reine Louise-marie 3",
    "sg:city":"Mouscron",
    "sg:classifiers":[
        {
            "category":"Deli",
            "type":"Food & Drink"
        }
    ],
    "sg:phone":"+32 56 84 71 14",
    "sg:postcode":"7700",
    "sg:province":"Hainaut",
    "sg:tags":[
        "delicatessen"
    ],
    "wof:name":"Escargot Frais (l')",
    "wof:placetype":"venue"
},
  "geometry": {"coordinates":[3.1856911182,50.7570457458],"type":"Point"}
}