{
  "type": "Feature",
  "properties": {
    "addr:full":"Mechelsesteenweg 73 Lier Antwerpen 2500",
    "addr:housenumber":"73",
    "addr:postcode":"2500",
    "addr:street":"Mechelsesteenweg",
    "iso:country":"BE",
    "sg:address":"Mechelsesteenweg 73",
    "sg:city":"Lier",
    "sg:classifiers":[
        {
            "category":"Home & Garden",
            "subcategory":"Home Furnishings",
            "type":"Retail Goods"
        }
    ],
    "sg:phone":"+32 3 488 11 61",
    "sg:postcode":"2500",
    "sg:province":"Antwerpen",
    "sg:tags":[
        "interior",
        "decoration"
    ],
    "wof:name":"Bd Style",
    "wof:placetype":"venue"
},
  "geometry": {"coordinates":[4.559650898,51.1293144226],"type":"Point"}
}