{
  "type": "Feature",
  "properties": {
    "iso:country":"BE",
    "sg:address":"Rue De La R\u00c9gence 2",
    "sg:city":"Li\u00c8ge",
    "sg:orig_category":"Boucheries",
    "sg:phone":"+32 4 232 01 59",
    "sg:postcode":"4000",
    "sg:province":"Li\u00e8ge",
    "wof:name":"Boucherie Maurice",
    "wof:placetype":"venue"
},
  "geometry": {"coordinates":[5.572619915,50.6428871155],"type":"Point"}
}