{
  "type": "Feature",
  "properties": {
    "iso:country":"BE",
    "sg:address":"Oogststraat 19",
    "sg:city":"Mol",
    "sg:orig_category":"Eleveurs de bovins",
    "sg:phone":"+32 14 31 91 58",
    "sg:postcode":"2400",
    "sg:province":"Antwerpen",
    "wof:name":"Marie-therese Willems",
    "wof:placetype":"venue"
},
  "geometry": {"coordinates":[5.0964050293,51.2002105713],"type":"Point"}
}