{
  "type": "Feature",
  "properties": {
    "iso:country":"BE",
    "sg:address":"Krommestraat 12",
    "sg:city":"Heuvelland",
    "sg:orig_category":"Rundveehouders",
    "sg:phone":"+32 57 44 50 74",
    "sg:postcode":"8953",
    "sg:province":"West-Vlaanderen",
    "wof:name":"Bernard Goudezeune",
    "wof:placetype":"venue"
},
  "geometry": {"coordinates":[2.9005610943,50.7760047913],"type":"Point"}
}