{
  "type": "Feature",
  "properties": {
    "addr:full":"Boulevard Mairaux 29 La Louvi\u00e8re Hainaut 7100",
    "addr:housenumber":"29",
    "addr:postcode":"7100",
    "addr:street":"Boulevard Mairaux",
    "iso:country":"BE",
    "sg:address":"Boulevard Mairaux 29",
    "sg:city":"La Louvi\u00e8re",
    "sg:classifiers":[
        {
            "category":"Personal",
            "type":"Services"
        }
    ],
    "sg:phone":"+32 64 22 14 92",
    "sg:postcode":"7100",
    "sg:province":"Hainaut",
    "sg:tags":[
        "clothing",
        "men's",
        "tailor",
        "-"
    ],
    "wof:name":"Obinu",
    "wof:placetype":"venue"
},
  "geometry": {"coordinates":[4.1878519058,50.4785919189],"type":"Point"}
}