{
  "type": "Feature",
  "properties": {
    "iso:country":"BE",
    "sg:address":"Hokken 65",
    "sg:city":"Arendonk",
    "sg:classifiers":[
        {
            "category":"Personal",
            "subcategory":"Beauty Salon",
            "type":"Services"
        }
    ],
    "sg:phone":"+32 14 67 12 58",
    "sg:postcode":"2370",
    "sg:province":"Antwerpen",
    "sg:tags":[
        "de",
        "coiffure"
    ],
    "wof:name":"D-coiffure",
    "wof:placetype":"venue"
},
  "geometry": {"coordinates":[5.0880842209,51.3262557983],"type":"Point"}
}