{
  "type": "Feature",
  "properties": {
    "iso:country":"BE",
    "sg:address":"Buissestraat 51",
    "sg:city":"Kluisbergen",
    "sg:orig_category":"Diensten voor huisdieren",
    "sg:phone":"+32 55 38 72 79",
    "sg:postcode":"9690",
    "sg:province":"Oost-Vlaanderen",
    "wof:name":"Hondenschool Kluisbos",
    "wof:placetype":"venue"
},
  "geometry": {"coordinates":[3.4857349396,50.7654151917],"type":"Point"}
}