{
  "type": "Feature",
  "properties": {
    "addr:full":"Prinsdomlaan 28 Izegem West-Vlaanderen 8870",
    "addr:housenumber":"28",
    "addr:postcode":"8870",
    "addr:street":"Prinsdomlaan",
    "iso:country":"BE",
    "sg:address":"Prinsdomlaan 28",
    "sg:city":"Izegem",
    "sg:orig_category":"Electrom\u00e9nager, t\u00e9l\u00e9visions and radios",
    "sg:phone":"+32 51 31 21 23",
    "sg:postcode":"8870",
    "sg:province":"West-Vlaanderen",
    "wof:name":"Libbrecht-sat Tv",
    "wof:placetype":"venue"
},
  "geometry": {"coordinates":[3.2257549763,50.9099388123],"type":"Point"}
}