{
  "type": "Feature",
  "properties": {
    "iso:country":"BE",
    "sg:address":"Avenue D'oppem 63",
    "sg:city":"Kraainem",
    "sg:classifiers":[
        {
            "category":"Health Services",
            "subcategory":"Dentist",
            "type":"Services"
        }
    ],
    "sg:phone":"+32 2 731 12 38",
    "sg:postcode":"1950",
    "sg:province":"Vlaams-Brabant",
    "wof:name":"Vansteenbrugge Marie-rose",
    "wof:placetype":"venue"
},
  "geometry": {"coordinates":[4.469648838,50.8419799805],"type":"Point"}
}