{
  "type": "Feature",
  "properties": {
    "addr:full":"Boulevard Louis Mettewie 87b6 Sint-jans-molenbeek/molenbeek-saint-jean Bruxelles-Capitale 1080",
    "addr:housenumber":"87b6",
    "addr:postcode":"1080",
    "addr:street":"Boulevard Louis Mettewie",
    "iso:country":"BE",
    "sg:address":"Boulevard Louis Mettewie 87b6",
    "sg:city":"Sint-jans-molenbeek/molenbeek-saint-jean",
    "sg:classifiers":[
        {
            "category":"Arena",
            "subcategory":"Sports Club",
            "type":"Entertainment"
        }
    ],
    "sg:phone":"+32 2 469 23 74",
    "sg:postcode":"1080",
    "sg:province":"Bruxelles-Capitale",
    "sg:tags":[
        "de"
    ],
    "wof:name":"B.b.c. Electrabel Sport",
    "wof:placetype":"venue"
},
  "geometry": {"coordinates":[4.302230835,50.8538246155],"type":"Point"}
}