{
  "type": "Feature",
  "properties": {
    "addr:full":"Nieuwstraat 34 Lede Oost-Vlaanderen 9340",
    "addr:housenumber":"34",
    "addr:postcode":"9340",
    "addr:street":"Nieuwstraat",
    "iso:country":"BE",
    "sg:address":"Nieuwstraat 34",
    "sg:city":"Lede",
    "sg:orig_category":"Cr\u00e8ches and garderies d'enfants",
    "sg:phone":"+32 53 80 88 40",
    "sg:postcode":"9340",
    "sg:province":"Oost-Vlaanderen",
    "wof:name":"Kribbe 't Sloeberken",
    "wof:placetype":"venue"
},
  "geometry": {"coordinates":[3.9822840691,50.9657096863],"type":"Point"}
}