{
  "type": "Feature",
  "properties": {
    "addr:full":"Diestersteenweg 66 Halen Limburg 3545",
    "addr:housenumber":"66",
    "addr:postcode":"3545",
    "addr:street":"Diestersteenweg",
    "iso:country":"BE",
    "sg:address":"Diestersteenweg 66",
    "sg:city":"Halen",
    "sg:classifiers":[
        {
            "category":"Professional",
            "subcategory":"Engineering",
            "type":"Services"
        }
    ],
    "sg:phone":"+32 13 44 11 50",
    "sg:postcode":"3545",
    "sg:province":"Limburg",
    "sg:tags":[
        "brick",
        "clinker"
    ],
    "wof:name":"Eggen Nv",
    "wof:placetype":"venue"
},
  "geometry": {"coordinates":[5.1055340767,50.950969696],"type":"Point"}
}