{
  "type": "Feature",
  "properties": {
    "iso:country":"BE",
    "sg:address":"Sint-agatha-berchemlaan 68",
    "sg:city":"Koekelberg",
    "sg:orig_category":"Immobili\u00ebnkantoren",
    "sg:phone":"+32 2 411 79 11",
    "sg:postcode":"1081",
    "sg:province":"Bruxelles-Capitale",
    "wof:name":"Immo Landa International",
    "wof:placetype":"venue"
},
  "geometry": {"coordinates":[4.3132591248,50.8643226624],"type":"Point"}
}