{
  "type": "Feature",
  "properties": {
    "addr:full":"Bammestraat 20bn Bilzen Limburg 3740",
    "addr:postcode":"3740",
    "addr:street":"Bammestraat",
    "iso:country":"BE",
    "sg:address":"Bammestraat 20bn",
    "sg:city":"Bilzen",
    "sg:orig_category":"Sportclubs Sportterreinen and installaties behalve sportcentra",
    "sg:phone":"+32 89 51 16 26",
    "sg:postcode":"3740",
    "sg:province":"Limburg",
    "wof:name":"Rapid Spouwen",
    "wof:placetype":"venue"
},
  "geometry": {"coordinates":[5.5156478882,50.8292617798],"type":"Point"}
}