{
  "type": "Feature",
  "properties": {
    "iso:country":"BE",
    "sg:address":"Chauss\u00c9e De Soignies 44",
    "sg:city":"Le Roeulx",
    "sg:orig_category":"Eleveurs de bovins",
    "sg:phone":"+32 64 66 21 70",
    "sg:postcode":"7070",
    "sg:province":"Hainaut",
    "wof:name":"Marc Baudoux",
    "wof:placetype":"venue"
},
  "geometry": {"coordinates":[4.1071019173,50.5094032288],"type":"Point"}
}