{
  "type": "Feature",
  "properties": {
    "iso:country":"BE",
    "sg:address":".",
    "sg:city":"Ciney",
    "sg:orig_category":"Chemicali\u00ebn Gh",
    "sg:phone":"+32 83 21 40 02",
    "sg:postcode":"5590",
    "sg:province":"Namur",
    "wof:name":"Aquapro",
    "wof:placetype":"venue"
},
  "geometry": {"coordinates":[5.1022520065,50.297088623],"type":"Point"}
}