{
  "type": "Feature",
  "properties": {
    "iso:country":"BE",
    "sg:address":"Hendrikstraat 110",
    "sg:city":"Alken",
    "sg:orig_category":"Peinture. Rev\u00eatements pour sols and murs",
    "sg:phone":"+32 11 59 19 55",
    "sg:postcode":"3570",
    "sg:province":"Limburg",
    "wof:name":"Putzeys",
    "wof:placetype":"venue"
},
  "geometry": {"coordinates":[5.27186203,50.8777046204],"type":"Point"}
}