{
  "type": "Feature",
  "properties": {
    "addr:full":"Bosstraat 189 Hamont-achel (hamont) Limburg 3930",
    "addr:housenumber":"189",
    "addr:postcode":"3930",
    "addr:street":"Bosstraat",
    "iso:country":"BE",
    "sg:address":"Bosstraat 189",
    "sg:city":"Hamont-achel (hamont)",
    "sg:classifiers":[
        {
            "category":"Shopping",
            "subcategory":"Stationery & Office Supplies",
            "type":"Retail Goods"
        }
    ],
    "sg:phone":"+32 11 44 04 40",
    "sg:postcode":"3930",
    "sg:province":"Limburg",
    "sg:tags":[
        "fixture"
    ],
    "wof:name":"Delta-v Lucas Nv",
    "wof:placetype":"venue"
},
  "geometry": {"coordinates":[5.5450549126,51.2511863708],"type":"Point"}
}