{
  "type": "Feature",
  "properties": {
    "addr:full":"Tongersesteenweg 149 Riemst Limburg 3770",
    "addr:housenumber":"149",
    "addr:postcode":"3770",
    "addr:street":"Tongersesteenweg",
    "iso:country":"BE",
    "sg:address":"Tongersesteenweg 149",
    "sg:city":"Riemst",
    "sg:classifiers":[
        {
            "category":"Professional",
            "subcategory":"Computer Services",
            "type":"Services"
        }
    ],
    "sg:phone":"+32 12 44 10 75",
    "sg:postcode":"3770",
    "sg:province":"Limburg",
    "sg:tags":[
        "-",
        "processing",
        "data",
        "software"
    ],
    "wof:name":"Giga Computershop",
    "wof:placetype":"venue"
},
  "geometry": {"coordinates":[5.5895900726,50.8097305298],"type":"Point"}
}