{
  "type": "Feature",
  "properties": {
    "addr:full":"Mendonkdorp 19 Gent (desteldonk) Oost-Vlaanderen 9042",
    "addr:housenumber":"19",
    "addr:postcode":"9042",
    "addr:street":"Mendonkdorp",
    "iso:country":"BE",
    "sg:address":"Mendonkdorp 19",
    "sg:city":"Gent (desteldonk)",
    "sg:classifiers":[
        {
            "category":"Personal",
            "type":"Services"
        }
    ],
    "sg:phone":"+32 9 345 94 30",
    "sg:postcode":"9042",
    "sg:province":"Oost-Vlaanderen",
    "sg:tags":[
        "clothing",
        "men's",
        "tailor",
        "-"
    ],
    "wof:name":"De Visscher E",
    "wof:placetype":"venue"
},
  "geometry": {"coordinates":[3.8163700104,51.1442298889],"type":"Point"}
}