{
  "type": "Feature",
  "properties": {
    "iso:country":"BE",
    "sg:address":"Rue De Velroux 29",
    "sg:city":"Grace-hollogne",
    "sg:orig_category":"Drogueries",
    "sg:phone":"+32 4 250 43 83",
    "sg:postcode":"4460",
    "sg:province":"Li\u00e8ge",
    "wof:name":"Michel Philippe",
    "wof:placetype":"venue"
},
  "geometry": {"coordinates":[5.444797039,50.6518478394],"type":"Point"}
}