{
  "type": "Feature",
  "properties": {
    "addr:full":"Rue De J\u00e9rusalem 34 Bruxelles (schaerbeek) Bruxelles-Capitale 1030",
    "addr:housenumber":"34",
    "addr:postcode":"1030",
    "addr:street":"Rue De Je\u0301Rusalem",
    "iso:country":"BE",
    "sg:address":"Rue De J\u00e9rusalem 34",
    "sg:city":"Bruxelles (schaerbeek)",
    "sg:classifiers":[
        {
            "category":"Shopping",
            "subcategory":"Discount & Variety Stores",
            "type":"Retail Goods"
        }
    ],
    "sg:phone":"+32 2 215 27 86",
    "sg:postcode":"1030",
    "sg:province":"Bruxelles-Capitale",
    "sg:tags":[
        "shop",
        "clearers",
        "curiosity",
        "furniture"
    ],
    "wof:name":"Geenis G",
    "wof:placetype":"venue"
},
  "geometry": {"coordinates":[4.3779602051,50.8664779663],"type":"Point"}
}