{
  "type": "Feature",
  "properties": {
    "addr:full":"Rue Ferrer 147 Manage (la Hestre) Hainaut 7170",
    "addr:housenumber":"147",
    "addr:postcode":"7170",
    "addr:street":"Rue Ferrer;La;Hainaut",
    "iso:country":"BE",
    "sg:address":"Rue Ferrer 147",
    "sg:city":"Manage (la Hestre)",
    "sg:classifiers":[
        {
            "category":"Shopping",
            "subcategory":"Pets & Pet Supplies",
            "type":"Retail Goods"
        }
    ],
    "sg:phone":"+32 64 28 43 30",
    "sg:postcode":"7170",
    "sg:province":"Hainaut",
    "sg:tags":[
        "bird"
    ],
    "wof:name":"Aux Nids D Oiseaux",
    "wof:placetype":"venue"
},
  "geometry": {"coordinates":[4.2347941399,50.4734725952],"type":"Point"}
}