{
  "type": "Feature",
  "properties": {
    "iso:country":"BE",
    "sg:address":"Neerbeekstraat 32",
    "sg:city":"Wevelgem",
    "sg:orig_category":"Installation de menuiserie en bois and plastique. Installation de menuiserie m\u00e9tallique",
    "sg:phone":"+32 56 41 49 73",
    "sg:postcode":"8560",
    "sg:province":"West-Vlaanderen",
    "wof:name":"Luc Deswarte",
    "wof:placetype":"venue"
},
  "geometry": {"coordinates":[3.1906449795,50.8139152527],"type":"Point"}
}