{
  "type": "Feature",
  "properties": {
    "addr:full":"Sint-amandsesteenweg 199 Bornem Antwerpen 2880",
    "addr:housenumber":"199",
    "addr:postcode":"2880",
    "addr:street":"Bornem Antwerpen",
    "iso:country":"BE",
    "sg:address":"Sint-amandsesteenweg 199",
    "sg:city":"Bornem",
    "sg:classifiers":[
        {
            "category":"Banks & Credit Unions",
            "subcategory":"Financial Services",
            "type":"Services"
        }
    ],
    "sg:phone":"+32 3 899 11 22",
    "sg:postcode":"2880",
    "sg:province":"Antwerpen",
    "sg:tags":[
        "loan",
        "mortgage"
    ],
    "wof:name":"Van Doorslaer Nv",
    "wof:placetype":"venue"
},
  "geometry": {"coordinates":[4.2238020897,51.0863647461],"type":"Point"}
}