{
  "type": "Feature",
  "properties": {
    "iso:country":"BE",
    "sg:address":"Rue Des Cahottes 34",
    "sg:city":"Flemalle",
    "sg:orig_category":"M\u00e9decins and sp\u00e9cialistes",
    "sg:phone":"+32 4 250 17 57",
    "sg:postcode":"4400",
    "sg:province":"Li\u00e8ge",
    "wof:name":"Alain Lefebvre",
    "wof:placetype":"venue"
},
  "geometry": {"coordinates":[5.4323430061,50.6210632324],"type":"Point"}
}