{
  "type": "Feature",
  "properties": {
    "addr:full":"Brugsesteenweg 84 Kortrijk West-Vlaanderen 8500",
    "addr:housenumber":"84",
    "addr:postcode":"8500",
    "addr:street":"Brugsesteenweg",
    "iso:country":"BE",
    "sg:address":"Brugsesteenweg 84",
    "sg:city":"Kortrijk",
    "sg:orig_category":"Dranken Geschenken and souvenirs",
    "sg:phone":"+32 56 35 88 14",
    "sg:postcode":"8500",
    "sg:province":"West-Vlaanderen",
    "wof:name":"Paul Lawaese",
    "wof:placetype":"venue"
},
  "geometry": {"coordinates":[3.263231039,50.8386192322],"type":"Point"}
}