{
  "type": "Feature",
  "properties": {
    "iso:country":"BE",
    "sg:address":"Nieuwstraat 5",
    "sg:city":"Torhout",
    "sg:orig_category":"Meubles D\u00e9taillants, Am\u00e9nagement de B\u00e2timents et de Cuisines. Eclairage et \u00e9quipements du foyer",
    "sg:phone":"+32 50 21 70 80",
    "sg:postcode":"8820",
    "sg:province":"West-Vlaanderen",
    "wof:name":"Ma Maison",
    "wof:placetype":"venue"
},
  "geometry": {"coordinates":[3.1003470421,51.0647621155],"type":"Point"}
}