{
  "type": "Feature",
  "properties": {
    "iso:country":"BE",
    "sg:address":"Deureindsedijk 16",
    "sg:city":"Wuustwezel",
    "sg:orig_category":"Rundveehouders",
    "sg:phone":"+32 3 669 96 25",
    "sg:postcode":"2990",
    "sg:province":"Antwerpen",
    "wof:name":"Leenaerts",
    "wof:placetype":"venue"
},
  "geometry": {"coordinates":[4.564863205,51.3731117249],"type":"Point"}
}