{
  "type": "Feature",
  "properties": {
    "addr:full":"Grand'rue 12 Charleroi (montignies-sur-sambre) Hainaut 6061",
    "addr:housenumber":"12",
    "addr:postcode":"6061",
    "addr:street":"Grand'Rue",
    "iso:country":"BE",
    "sg:address":"Grand'rue 12",
    "sg:city":"Charleroi (montignies-sur-sambre)",
    "sg:classifiers":[
        {
            "category":"Health Services",
            "subcategory":"Health Practitioner",
            "type":"Services"
        }
    ],
    "sg:phone":"+32 71 31 56 16",
    "sg:postcode":"6061",
    "sg:province":"Hainaut",
    "sg:tags":[
        "physiotherapist"
    ],
    "wof:name":"Noiret Myriam",
    "wof:placetype":"venue"
},
  "geometry": {"coordinates":[4.459209919,50.4121246338],"type":"Point"}
}