{
  "type": "Feature",
  "properties": {
    "iso:country":"BE",
    "sg:address":"Pijpelarestraat 6",
    "sg:city":"Ternat (wambeek)",
    "sg:classifiers":[
        {
            "category":"Personal",
            "subcategory":"Beauty Salon",
            "type":"Services"
        }
    ],
    "sg:phone":"+32 2 466 79 83",
    "sg:postcode":"1741",
    "sg:province":"Vlaams-Brabant",
    "sg:tags":[
        "lady",
        "-",
        "hairdressing"
    ],
    "wof:name":"Natuursalon Haarkunst",
    "wof:placetype":"venue"
},
  "geometry": {"coordinates":[4.1716771126,50.8535118103],"type":"Point"}
}