{
  "type": "Feature",
  "properties": {
    "iso:country":"BE",
    "sg:address":"Kapelstraat 7",
    "sg:city":"Zoersel",
    "sg:orig_category":"Schoonheidssalons",
    "sg:phone":"+32 3 311 57 21",
    "sg:postcode":"2980",
    "sg:province":"Antwerpen",
    "wof:name":"Haest",
    "wof:placetype":"venue"
},
  "geometry": {"coordinates":[4.7139081955,51.2658615112],"type":"Point"}
}