{
  "type": "Feature",
  "properties": {
    "iso:country":"BE",
    "sg:address":"Avenue De La Gare 28",
    "sg:city":"Nivelles (baulers)",
    "sg:classifiers":[
        {
            "category":"Building & Trades",
            "subcategory":"Cleaning & Sanitation",
            "type":"Services"
        }
    ],
    "sg:phone":"+32 67 21 81 62",
    "sg:postcode":"1401",
    "sg:province":"Brabant Wallon",
    "sg:tags":[
        "blast"
    ],
    "wof:name":"Van Cauter A (ets)",
    "wof:placetype":"venue"
},
  "geometry": {"coordinates":[4.3468971252,50.6080741882],"type":"Point"}
}