{
  "type": "Feature",
  "properties": {
    "addr:full":"Avenue Maurice Destenay 13 Li\u00e8ge 1 Li\u00e8ge 4000",
    "addr:housenumber":"13;1",
    "addr:postcode":"4000",
    "addr:street":"Avenue Maurice Destenay",
    "iso:country":"BE",
    "sg:address":"Avenue Maurice Destenay 13",
    "sg:city":"Li\u00e8ge 1",
    "sg:classifiers":[
        {
            "category":"Banks & Credit Unions",
            "subcategory":"Investment Brokerage",
            "type":"Services"
        }
    ],
    "sg:phone":"+32 4 221 98 11",
    "sg:postcode":"4000",
    "sg:province":"Li\u00e8ge",
    "wof:name":"S.r.i.w.",
    "wof:placetype":"venue"
},
  "geometry": {"coordinates":[5.5691590309,50.6379890442],"type":"Point"}
}