{
  "type": "Feature",
  "properties": {
    "addr:full":"Rue Lambert Vandervelde 2bb Watermaal-bosvoorde/watermael-boitsfort Bruxelles-Capitale 1170",
    "addr:housenumber":"2bb",
    "addr:postcode":"1170",
    "addr:street":"Rue Lambert Vandervelde",
    "iso:country":"BE",
    "sg:address":"Rue Lambert Vandervelde 2bb",
    "sg:city":"Watermaal-bosvoorde/watermael-boitsfort",
    "sg:classifiers":[
        {
            "category":"Arena",
            "subcategory":"Sports Club",
            "type":"Entertainment"
        }
    ],
    "sg:phone":"+32 2 672 77 41",
    "sg:postcode":"1170",
    "sg:province":"Bruxelles-Capitale",
    "sg:tags":[
        "de"
    ],
    "wof:name":"H.c. Quirinal",
    "wof:placetype":"venue"
},
  "geometry": {"coordinates":[4.3976998329,50.8102340698],"type":"Point"}
}