{
  "type": "Feature",
  "properties": {
    "addr:full":"Nieuwstraat 61 Leuven (wijgmaal) Vlaams-Brabant 3018",
    "addr:housenumber":"61",
    "addr:postcode":"3018",
    "addr:street":"Nieuwstraat",
    "iso:country":"BE",
    "sg:address":"Nieuwstraat 61",
    "sg:city":"Leuven (wijgmaal)",
    "sg:classifiers":[
        {
            "category":"Bakery",
            "type":"Food & Drink"
        }
    ],
    "sg:phone":"+32 16 44 52 88",
    "sg:postcode":"3018",
    "sg:province":"Vlaams-Brabant",
    "sg:tags":[
        "confectioner",
        "baker"
    ],
    "wof:name":"De Vos",
    "wof:placetype":"venue"
},
  "geometry": {"coordinates":[4.6970338821,50.9250984192],"type":"Point"}
}