{
  "type": "Feature",
  "properties": {
    "addr:full":"Turnhoutsebaan 362 Schilde Antwerpen 2970",
    "addr:housenumber":"362",
    "addr:postcode":"2970",
    "addr:street":"Turnhoutsebaan",
    "iso:country":"BE",
    "sg:address":"Turnhoutsebaan 362",
    "sg:city":"Schilde",
    "sg:orig_category":"Slagers",
    "sg:phone":"+32 3 383 08 08",
    "sg:postcode":"2970",
    "sg:province":"Antwerpen",
    "wof:name":"Fa. De Laet",
    "wof:placetype":"venue"
},
  "geometry": {"coordinates":[4.5869688988,51.2421264648],"type":"Point"}
}