{
  "type": "Feature",
  "properties": {
    "addr:full":"Vredelaan 8 Diepenbeek Limburg 3590",
    "addr:housenumber":"8",
    "addr:postcode":"3590",
    "addr:street":"Vredelaan",
    "iso:country":"BE",
    "sg:address":"Vredelaan 8",
    "sg:city":"Diepenbeek",
    "sg:classifiers":[
        {
            "category":"Organizations",
            "subcategory":"Community Association",
            "type":"Services"
        }
    ],
    "sg:phone":"+32 11 32 14 72",
    "sg:postcode":"3590",
    "sg:province":"Limburg",
    "sg:tags":[
        "work",
        "assembly"
    ],
    "wof:name":"Montage Service Diepenbeek",
    "wof:placetype":"venue"
},
  "geometry": {"coordinates":[5.4132761955,50.9026222229],"type":"Point"}
}