{
  "type": "Feature",
  "properties": {
    "addr:full":"Rue Du Tilleul 323 Bruxelles (evere) Bruxelles-Capitale 1140",
    "addr:housenumber":"323",
    "addr:postcode":"1140",
    "addr:street":"Rue Du Tilleul",
    "iso:country":"BE",
    "sg:address":"Rue Du Tilleul 323",
    "sg:city":"Bruxelles (evere)",
    "sg:orig_category":"Non-Classified Establishments",
    "sg:phone":"+32 2 216 83 42",
    "sg:postcode":"1140",
    "sg:province":"Bruxelles-Capitale",
    "wof:name":"Alter Ego International",
    "wof:placetype":"venue"
},
  "geometry": {"coordinates":[4.3959679604,50.8693733215],"type":"Point"}
}