{
  "type": "Feature",
  "properties": {
    "addr:full":"Grote Markt 10 Wevelgem West-Vlaanderen 8560",
    "addr:housenumber":"10",
    "addr:postcode":"8560",
    "addr:street":"Grote Markt",
    "iso:country":"BE",
    "sg:address":"Grote Markt 10",
    "sg:city":"Wevelgem",
    "sg:orig_category":"Banques and organismes de cr\u00e9dit",
    "sg:phone":"+32 56 40 36 71",
    "sg:postcode":"8560",
    "sg:province":"West-Vlaanderen",
    "wof:name":"Dexia",
    "wof:placetype":"venue"
},
  "geometry": {"coordinates":[3.1841309071,50.808719635],"type":"Point"}
}