{
  "type": "Feature",
  "properties": {
    "addr:full":"Kiezelstraat 42 Heers Limburg 3870",
    "addr:housenumber":"42",
    "addr:postcode":"3870",
    "addr:street":"Kiezelstraat",
    "iso:country":"BE",
    "sg:address":"Kiezelstraat 42",
    "sg:city":"Heers",
    "sg:orig_category":"Herstellingen and onderhoud van auto's",
    "sg:phone":"+32 11 48 23 88",
    "sg:postcode":"3870",
    "sg:province":"Limburg",
    "wof:name":"Jozef Heeren",
    "wof:placetype":"venue"
},
  "geometry": {"coordinates":[5.2770910263,50.7658195496],"type":"Point"}
}