{
  "type": "Feature",
  "properties": {
    "iso:country":"BE",
    "sg:address":"Rue Grand Bru 24",
    "sg:city":"Sprimont",
    "sg:orig_category":"Tuinen",
    "sg:phone":"+32 4 382 34 61",
    "sg:postcode":"4140",
    "sg:province":"Li\u00e8ge",
    "wof:name":"Herzet Jean-paul",
    "wof:placetype":"venue"
},
  "geometry": {"coordinates":[5.6573262215,50.5231933594],"type":"Point"}
}