{
  "type": "Feature",
  "properties": {
    "addr:full":"Gentsesteenweg 1310 Sint-agatha-berchem Bruxelles-Capitale 1082",
    "addr:housenumber":"1310",
    "addr:postcode":"1082",
    "addr:street":"Gentsesteenweg",
    "iso:country":"BE",
    "sg:address":"Gentsesteenweg 1310",
    "sg:city":"Sint-agatha-berchem",
    "sg:orig_category":"Papierwaren and schoolbenodigdheden Gh",
    "sg:phone":"+32 2 465 70 58",
    "sg:postcode":"1082",
    "sg:province":"Bruxelles-Capitale",
    "wof:name":"Ixo",
    "wof:placetype":"venue"
},
  "geometry": {"coordinates":[4.2928729057,50.8682899475],"type":"Point"}
}