{
  "type": "Feature",
  "properties": {
    "iso:country":"BE",
    "sg:address":"Jasmijnstr 5",
    "sg:city":"Antwerpen",
    "sg:orig_category":"Rijscholen",
    "sg:phone":"+32 3 248 29 32",
    "sg:postcode":"2020",
    "sg:province":"Antwerpen",
    "wof:name":"Top Line Driving Courses",
    "wof:placetype":"venue"
},
  "geometry": {"coordinates":[4.3941068649,51.1868553162],"type":"Point"}
}