{
  "type": "Feature",
  "properties": {
    "addr:full":"Herbesthaler Strasse 146 Eupen Li\u00e8ge 4700",
    "addr:housenumber":"146",
    "addr:postcode":"4700",
    "addr:street":"Herbesthaler Strasse",
    "iso:country":"BE",
    "sg:address":"Herbesthaler Strasse 146",
    "sg:city":"Eupen",
    "sg:classifiers":[
        {
            "category":"Airport",
            "subcategory":"International",
            "type":"Transportation"
        }
    ],
    "sg:phone":"+32 87 30 56 11",
    "sg:postcode":"4700",
    "sg:province":"Li\u00e8ge",
    "sg:tags":[
        "-",
        "transport"
    ],
    "wof:name":"Ghemar Sa",
    "wof:placetype":"venue"
},
  "geometry": {"coordinates":[6.0125341415,50.6415939331],"type":"Point"}
}