{
  "type": "Feature",
  "properties": {
    "iso:country":"BE",
    "sg:address":"Rue De Favarcq 40",
    "sg:city":"Beloeil",
    "sg:classifiers":[
        {
            "category":"Shopping",
            "subcategory":"Clothing, Apparel, & Fashions",
            "type":"Retail Goods"
        }
    ],
    "sg:phone":"+32 69 68 60 45",
    "sg:postcode":"7970",
    "sg:province":"Hainaut",
    "sg:tags":[
        "clothing",
        "-",
        "gentleman"
    ],
    "wof:name":"Dany",
    "wof:placetype":"venue"
},
  "geometry": {"coordinates":[3.7284100056,50.546875],"type":"Point"}
}