{
  "type": "Feature",
  "properties": {
    "iso:country":"BE",
    "sg:address":"Galgestraat 1a",
    "sg:city":"Waregem",
    "sg:classifiers":[
        {
            "category":"Wholesale",
            "subcategory":"Fruits & Vegetables",
            "type":"Manufacturing & Wholesale Goods"
        }
    ],
    "sg:phone":"+32 56 61 33 33",
    "sg:postcode":"8790",
    "sg:province":"West-Vlaanderen",
    "sg:tags":[
        "whol",
        "-",
        "potato"
    ],
    "wof:name":"Bruwier Potatoes",
    "wof:placetype":"venue"
},
  "geometry": {"coordinates":[3.4488470554,50.8818397522],"type":"Point"}
}