{
  "type": "Feature",
  "properties": {
    "addr:full":"Lindestr 24 Melle Oost-Vlaanderen 9230",
    "addr:housenumber":"24",
    "addr:postcode":"9230",
    "addr:street":"Lindestr",
    "iso:country":"BE",
    "sg:address":"Lindestr 24",
    "sg:city":"Melle",
    "sg:classifiers":[
        {
            "category":"Banks & Credit Unions",
            "subcategory":"Bank",
            "type":"Services"
        }
    ],
    "sg:phone":"+32 52 52 12 10",
    "sg:postcode":"9230",
    "sg:province":"Oost-Vlaanderen",
    "wof:name":"Krediet Nuverheid",
    "wof:placetype":"venue"
},
  "geometry": {"coordinates":[3.8355689049,51.0089302063],"type":"Point"}
}