{
  "type": "Feature",
  "properties": {
    "addr:full":"Avenue Auguste Jassogne 29 Waterloo Brabant Wallon 1410",
    "addr:housenumber":"29",
    "addr:postcode":"1410",
    "addr:street":"Avenue Auguste Jassogne",
    "iso:country":"BE",
    "sg:address":"Avenue Auguste Jassogne 29",
    "sg:city":"Waterloo",
    "sg:classifiers":[
        {
            "category":"Health Services",
            "subcategory":"Doctor",
            "type":"Services"
        }
    ],
    "sg:phone":"+32 2 354 49 60",
    "sg:postcode":"1410",
    "sg:province":"Brabant Wallon",
    "sg:tags":[
        "medicinephysicians",
        "surgeon"
    ],
    "wof:name":"Joyeux Philippe",
    "wof:placetype":"venue"
},
  "geometry": {"coordinates":[4.3800349236,50.7102584839],"type":"Point"}
}