{
  "type": "Feature",
  "properties": {
    "iso:country":"BE",
    "sg:address":"Nederlandlaan 14",
    "sg:city":"Geel",
    "sg:classifiers":[
        {
            "category":"Health Services",
            "subcategory":"Doctor",
            "type":"Services"
        }
    ],
    "sg:phone":"+32 14 59 20 01",
    "sg:postcode":"2440",
    "sg:province":"Antwerpen",
    "sg:tags":[
        "medicinephysicians",
        "surgeon"
    ],
    "wof:name":"Franssens Y",
    "wof:placetype":"venue"
},
  "geometry": {"coordinates":[5.0332918167,51.193271637],"type":"Point"}
}