{
  "type": "Feature",
  "properties": {
    "addr:full":"Rijmenamseweg 128 Bonheiden Antwerpen 2820",
    "addr:housenumber":"128",
    "addr:postcode":"2820",
    "addr:street":"Rijmenamseweg",
    "iso:country":"BE",
    "sg:address":"Rijmenamseweg 128",
    "sg:city":"Bonheiden",
    "sg:classifiers":[
        {
            "category":"Health Services",
            "subcategory":"Doctor",
            "type":"Services"
        }
    ],
    "sg:phone":"+32 15 51 68 00",
    "sg:postcode":"2820",
    "sg:province":"Antwerpen",
    "sg:tags":[
        "medicinephysicians",
        "surgeon"
    ],
    "wof:name":"Dammekens E Hendrik",
    "wof:placetype":"venue"
},
  "geometry": {"coordinates":[4.5667271614,51.0186157227],"type":"Point"}
}