{
  "type": "Feature",
  "properties": {
    "iso:country":"BE",
    "sg:address":"Antoon Van Brabantstraat 9b2",
    "sg:city":"Aartselaar",
    "sg:orig_category":"Boekhouders",
    "sg:phone":"+32 3 877 06 79",
    "sg:postcode":"2630",
    "sg:province":"Antwerpen",
    "wof:name":"Dani\u00cbl Debaere",
    "wof:placetype":"venue"
},
  "geometry": {"coordinates":[4.3892230988,51.134563446],"type":"Point"}
}