{
  "type": "Feature",
  "properties": {
    "iso:country":"BE",
    "sg:address":"Kerkstraat 2",
    "sg:city":"Ranst",
    "sg:orig_category":"Advocaten and juridische adviseurs",
    "sg:phone":"+32 3 383 47 57",
    "sg:postcode":"2520",
    "sg:province":"Antwerpen",
    "wof:name":"Jean Van Damme",
    "wof:placetype":"venue"
},
  "geometry": {"coordinates":[4.5622401237,51.1892051697],"type":"Point"}
}