{
  "type": "Feature",
  "properties": {
    "addr:full":"Nijverheidsstraat 5 Pittem West-Vlaanderen 8740",
    "addr:housenumber":"5",
    "addr:postcode":"8740",
    "addr:street":"Nijverheidsstraat",
    "iso:country":"BE",
    "sg:address":"Nijverheidsstraat 5",
    "sg:city":"Pittem",
    "sg:orig_category":"Installatie van houten of kunststof schrijnwerk",
    "sg:phone":"+32 51 46 73 47",
    "sg:postcode":"8740",
    "sg:province":"West-Vlaanderen",
    "wof:name":"Monserez",
    "wof:placetype":"venue"
},
  "geometry": {"coordinates":[3.2537140846,50.992061615],"type":"Point"}
}