{
  "type": "Feature",
  "properties": {
    "addr:full":"Lambrechtshoekenlaan 339 Antwerpen Antwerpen 2170",
    "addr:housenumber":"339",
    "addr:postcode":"2170",
    "addr:street":"Lambrechtshoekenlaan",
    "iso:country":"BE",
    "sg:address":"Lambrechtshoekenlaan 339",
    "sg:city":"Antwerpen",
    "sg:orig_category":"Diverse kredietdiensten",
    "sg:postcode":"2170",
    "sg:province":"Antwerpen",
    "wof:name":"Bancontact-mister Cash",
    "wof:placetype":"venue"
},
  "geometry": {"coordinates":[4.4505147934,51.246723175],"type":"Point"}
}