{
  "type": "Feature",
  "properties": {
    "addr:full":"Korte Zoutstraat 50 Aalst Oost-Vlaanderen 9300",
    "addr:housenumber":"50",
    "addr:postcode":"9300",
    "addr:street":"Korte Zoutstraat",
    "iso:country":"BE",
    "sg:address":"Korte Zoutstraat 50",
    "sg:city":"Aalst",
    "sg:orig_category":"Kapsalons",
    "sg:phone":"+32 53 77 55 47",
    "sg:postcode":"9300",
    "sg:province":"Oost-Vlaanderen",
    "wof:name":"Kreatos",
    "wof:placetype":"venue"
},
  "geometry": {"coordinates":[4.0383849144,50.9352836609],"type":"Point"}
}