{
  "type": "Feature",
  "properties": {
    "iso:country":"BE",
    "sg:address":"Mechelsesteenweg 301",
    "sg:city":"Willebroek",
    "sg:orig_category":"Software ontwikkeling and ontwerp",
    "sg:phone":"+32 3 860 92 92",
    "sg:postcode":"2830",
    "sg:province":"Antwerpen",
    "wof:name":"Imvemaco",
    "wof:placetype":"venue"
},
  "geometry": {"coordinates":[4.3759441376,51.0488777161],"type":"Point"}
}