{
  "type": "Feature",
  "properties": {
    "addr:full":"Boulevard L\u00c9opold Ii 149 Sint-jans-molenbeek/molenbeek-saint-jean Bruxelles-Capitale 1080",
    "addr:housenumber":"149;/",
    "addr:postcode":"1080",
    "addr:street":"Boulevard Le\u0301Opold Ii;Sint-Jans-Molenbeek",
    "iso:country":"BE",
    "sg:address":"Boulevard L\u00c9opold Ii 149",
    "sg:city":"Sint-jans-molenbeek/molenbeek-saint-jean",
    "sg:orig_category":"Entretien and r\u00e9parations de machines de bureau and ordinateurs. Ordinateurs and \u00e9quipement informat",
    "sg:phone":"+32 2 420 39 70",
    "sg:postcode":"1080",
    "sg:province":"Bruxelles-Capitale",
    "wof:name":"Nordata Belgium Corp.",
    "wof:placetype":"venue"
},
  "geometry": {"coordinates":[4.3376669884,50.86145401],"type":"Point"}
}