{
  "type": "Feature",
  "properties": {
    "addr:full":"Chauss\u00e9e De Waterloo 868-870 Bruxelles (uccle) Bruxelles-Capitale 1180",
    "addr:postcode":"868-870;1180",
    "addr:street":"Chausse\u0301E De Waterloo",
    "iso:country":"BE",
    "sg:address":"Chauss\u00e9e De Waterloo 868-870",
    "sg:city":"Bruxelles (uccle)",
    "sg:classifiers":[
        {
            "category":"Real Estate",
            "subcategory":"Real Estate Agent",
            "type":"Services"
        }
    ],
    "sg:phone":"+32 2 373 51 10",
    "sg:postcode":"1180",
    "sg:province":"Bruxelles-Capitale",
    "sg:tags":[
        "importer",
        "champagne",
        "-"
    ],
    "wof:name":"Champagne Ruinart Belgium Sa",
    "wof:placetype":"venue"
},
  "geometry": {"coordinates":[4.3828048706,50.7666282654],"type":"Point"}
}