{
  "type": "Feature",
  "properties": {
    "iso:country":"BE",
    "sg:address":"Avenue De Heppignies",
    "sg:city":"Fleurus (heppignies)",
    "sg:classifiers":[
        {
            "category":"Professional",
            "subcategory":"Advertising",
            "type":"Services"
        }
    ],
    "sg:phone":"+32 71 37 80 30",
    "sg:postcode":"6220",
    "sg:province":"Hainaut",
    "sg:tags":[
        "clothes"
    ],
    "wof:name":"Action Tee Sprl",
    "wof:placetype":"venue"
},
  "geometry": {"coordinates":[4.4937701225,50.48204422],"type":"Point"}
}