{
  "type": "Feature",
  "properties": {
    "iso:country":"BE",
    "sg:address":"Monnikenwerve 99-101",
    "sg:city":"Brugge",
    "sg:classifiers":[
        {
            "category":"Bakery",
            "type":"Food & Drink"
        }
    ],
    "sg:phone":"+32 50 31 53 85",
    "sg:postcode":"8000",
    "sg:province":"West-Vlaanderen",
    "sg:tags":[
        "confectioner",
        "baker"
    ],
    "wof:name":"Sint Paulus",
    "wof:placetype":"venue"
},
  "geometry": {"coordinates":[3.2011809349,51.2489814758],"type":"Point"}
}