{
  "type": "Feature",
  "properties": {
    "iso:country":"BE",
    "sg:address":"Ooststraat 4",
    "sg:city":"Moerbeke",
    "sg:orig_category":"Eleveurs de bovins",
    "sg:phone":"+32 9 346 87 66",
    "sg:postcode":"9180",
    "sg:province":"Oost-Vlaanderen",
    "wof:name":"Robert De Decker",
    "wof:placetype":"venue"
},
  "geometry": {"coordinates":[3.9757680893,51.1783065796],"type":"Point"}
}