{
  "type": "Feature",
  "properties": {
    "addr:full":"Sittardlaan 12 Hasselt Limburg 3500",
    "addr:housenumber":"12",
    "addr:postcode":"3500",
    "addr:street":"Sittardlaan",
    "iso:country":"BE",
    "sg:address":"Sittardlaan 12",
    "sg:city":"Hasselt",
    "sg:orig_category":"Reclamebureaus",
    "sg:phone":"+32 11 22 26 59",
    "sg:postcode":"3500",
    "sg:province":"Limburg",
    "wof:name":"Bureau Vandenborn Consult",
    "wof:placetype":"venue"
},
  "geometry": {"coordinates":[5.3622322083,50.9442176819],"type":"Point"}
}