{
  "type": "Feature",
  "properties": {
    "iso:country":"BE",
    "sg:address":"Hooistraat 10",
    "sg:city":"Laarne",
    "sg:orig_category":"Koffie, thee, cacao and specerijen Gh",
    "sg:phone":"+32 9 367 58 15",
    "sg:postcode":"9270",
    "sg:province":"Oost-Vlaanderen",
    "wof:name":"Zoutbedrijf Van Damme",
    "wof:placetype":"venue"
},
  "geometry": {"coordinates":[3.9249970913,51.0354690552],"type":"Point"}
}