{
  "type": "Feature",
  "properties": {
    "iso:country":"BE",
    "sg:address":"Baron-holvoetlaan 64",
    "sg:city":"Moorslede",
    "sg:classifiers":[
        {
            "category":"Personal",
            "subcategory":"Beauty Salon",
            "type":"Services"
        }
    ],
    "sg:phone":"+32 56 50 08 02",
    "sg:postcode":"8890",
    "sg:province":"West-Vlaanderen",
    "sg:tags":[
        "de",
        "coiffure"
    ],
    "wof:name":"Coiffure Jacqueline",
    "wof:placetype":"venue"
},
  "geometry": {"coordinates":[3.1044158936,50.8470802307],"type":"Point"}
}