{
  "type": "Feature",
  "properties": {
    "addr:full":"Chauss\u00c9e De Waterloo 1253 Ukkel/uccle Bruxelles-Capitale 1180",
    "addr:postcode":"1253;1180",
    "addr:street":"Chausse\u0301E De Waterloo",
    "iso:country":"BE",
    "sg:address":"Chauss\u00c9e De Waterloo 1253",
    "sg:city":"Ukkel/uccle",
    "sg:orig_category":"Textiles. Meubles D\u00e9taillants, Am\u00e9nagement de B\u00e2timents et de Cuisines",
    "sg:phone":"+32 2 374 96 19",
    "sg:postcode":"1180",
    "sg:province":"Bruxelles-Capitale",
    "wof:name":"Ligne De Maison Am\u00c9lie",
    "wof:placetype":"venue"
},
  "geometry": {"coordinates":[4.373729229,50.7934303284],"type":"Point"}
}