{
  "type": "Feature",
  "properties": {
    "iso:country":"BE",
    "sg:address":"Sint-lambertuskerkstraat 29",
    "sg:city":"Maaseik (neeroeteren)",
    "sg:classifiers":[
        {
            "category":"Bars & Pubs",
            "type":"Food & Drink"
        }
    ],
    "sg:phone":"+32 89 86 70 08",
    "sg:postcode":"3680",
    "sg:province":"Limburg",
    "wof:name":"Oetergalm",
    "wof:placetype":"venue"
},
  "geometry": {"coordinates":[5.7039661407,51.0884056091],"type":"Point"}
}