{
  "type": "Feature",
  "properties": {
    "addr:full":"Quai De La Vesdre 41 Verviers Li\u00e8ge 4800",
    "addr:housenumber":"41",
    "addr:postcode":"4800",
    "addr:street":"Quai De La Vesdre",
    "iso:country":"BE",
    "sg:address":"Quai De La Vesdre 41",
    "sg:city":"Verviers",
    "sg:classifiers":[
        {
            "category":"Education",
            "subcategory":"Dance Studio",
            "type":"Public Place"
        }
    ],
    "sg:phone":"+32 87 22 35 73",
    "sg:postcode":"4800",
    "sg:province":"Li\u00e8ge",
    "sg:tags":[
        "school",
        "dancing"
    ],
    "wof:name":"Teller D & J",
    "wof:placetype":"venue"
},
  "geometry": {"coordinates":[5.8478798866,50.5859489441],"type":"Point"}
}