{
  "type": "Feature",
  "properties": {
    "addr:full":"Predikherenberg 37 Leuven Vlaams-Brabant 3010",
    "addr:housenumber":"37",
    "addr:postcode":"3010",
    "addr:street":"Predikherenberg",
    "iso:country":"BE",
    "sg:address":"Predikherenberg 37",
    "sg:city":"Leuven",
    "sg:orig_category":"Artiesten and kunstenaars",
    "sg:phone":"+32 16 25 25 51",
    "sg:postcode":"3010",
    "sg:province":"Vlaams-Brabant",
    "wof:name":"Vanlangendonck",
    "wof:placetype":"venue"
},
  "geometry": {"coordinates":[4.7304501534,50.889755249],"type":"Point"}
}