{
  "type": "Feature",
  "properties": {
    "iso:country":"BE",
    "sg:address":"Mandemakerstraat 66",
    "sg:city":"Hamme",
    "sg:classifiers":[
        {
            "category":"Food & Beverages",
            "subcategory":"Groceries & Convenience Stores",
            "type":"Retail Goods"
        }
    ],
    "sg:phone":"+32 52 47 16 17",
    "sg:postcode":"9220",
    "sg:province":"Oost-Vlaanderen",
    "sg:tags":[
        "grocer"
    ],
    "wof:name":"Fijnproeverke ('t)",
    "wof:placetype":"venue"
},
  "geometry": {"coordinates":[4.1404190063,51.0995483398],"type":"Point"}
}