{
  "type": "Feature",
  "properties": {
    "iso:country":"BE",
    "sg:address":"Grand Rue 27",
    "sg:city":"Tellin (resteigne)",
    "sg:classifiers":[
        {
            "category":"Home & Garden",
            "subcategory":"Building Materials",
            "type":"Retail Goods"
        }
    ],
    "sg:phone":"+32 84 38 82 93",
    "sg:postcode":"6927",
    "sg:province":"Luxembourg",
    "sg:tags":[
        "window"
    ],
    "wof:name":"Roynet F",
    "wof:placetype":"venue"
},
  "geometry": {"coordinates":[5.1778421402,50.0824241638],"type":"Point"}
}