{
  "type": "Feature",
  "properties": {
    "iso:country":"BE",
    "sg:address":"Rue De La Station 20",
    "sg:city":"Havelange",
    "sg:orig_category":"Brood, gebak and snoepgoed",
    "sg:phone":"+32 83 63 46 34",
    "sg:postcode":"5370",
    "sg:province":"Namur",
    "wof:name":"P\u00c2tisserie Debras",
    "wof:placetype":"venue"
},
  "geometry": {"coordinates":[5.2403240204,50.3887290955],"type":"Point"}
}