{
  "type": "Feature",
  "properties": {
    "addr:full":"Rue Albert I 122 Mettet Namur 5640",
    "addr:housenumber":"122",
    "addr:postcode":"5640",
    "addr:street":"Rue Albert I",
    "iso:country":"BE",
    "sg:address":"Rue Albert I 122",
    "sg:city":"Mettet",
    "sg:orig_category":"Non-Classified Establishments",
    "sg:phone":"+32 71 72 79 03",
    "sg:postcode":"5640",
    "sg:province":"Namur",
    "wof:name":"Ittelet",
    "wof:placetype":"venue"
},
  "geometry": {"coordinates":[4.6555128098,50.3277854919],"type":"Point"}
}