{
  "type": "Feature",
  "properties": {
    "addr:full":"Prins Albertlaan 72 De Panne West-Vlaanderen 8660",
    "addr:housenumber":"72",
    "addr:postcode":"8660",
    "addr:street":"Prins Albertlaan",
    "iso:country":"BE",
    "sg:address":"Prins Albertlaan 72",
    "sg:city":"De Panne",
    "sg:orig_category":"Dierenartsen",
    "sg:phone":"+32 58 41 25 80",
    "sg:postcode":"8660",
    "sg:province":"West-Vlaanderen",
    "wof:name":"Etienne Debeerst",
    "wof:placetype":"venue"
},
  "geometry": {"coordinates":[2.595801115,51.1013183594],"type":"Point"}
}