{
  "type": "Feature",
  "properties": {
    "iso:country":"BE",
    "sg:address":"Rue Du Bois Des Fiefs 4a",
    "sg:city":"Ciney",
    "sg:classifiers":[
        {
            "category":"Real Estate",
            "subcategory":"Architect",
            "type":"Services"
        }
    ],
    "sg:phone":"+32 83 21 37 43",
    "sg:postcode":"5590",
    "sg:province":"Namur",
    "wof:name":"Rouelle A",
    "wof:placetype":"venue"
},
  "geometry": {"coordinates":[5.1136131287,50.3049087524],"type":"Point"}
}