{
  "type": "Feature",
  "properties": {
    "addr:full":"Rue Eug\u00e8ne Cattoir 11 Bruxelles (ixelles) Bruxelles-Capitale 1050",
    "addr:housenumber":"11",
    "addr:postcode":"1050",
    "addr:street":"Rue Euge\u0300Ne Cattoir",
    "iso:country":"BE",
    "sg:address":"Rue Eug\u00e8ne Cattoir 11",
    "sg:city":"Bruxelles (ixelles)",
    "sg:classifiers":[
        {
            "category":"Professional",
            "subcategory":"Management & Consulting",
            "type":"Services"
        }
    ],
    "sg:phone":"+32 2 644 12 60",
    "sg:postcode":"1050",
    "sg:province":"Bruxelles-Capitale",
    "sg:tags":[
        "consultant",
        "agency",
        "advertising"
    ],
    "wof:name":"Mp & Vh Communication",
    "wof:placetype":"venue"
},
  "geometry": {"coordinates":[4.3869419098,50.820640564],"type":"Point"}
}