{
  "type": "Feature",
  "properties": {
    "addr:full":"Brouwerijstraat 48 Kortenberg Vlaams-Brabant 3070",
    "addr:housenumber":"48",
    "addr:postcode":"3070",
    "addr:street":"Brouwerijstraat;Vlaams-Brabant",
    "iso:country":"BE",
    "sg:address":"Brouwerijstraat 48",
    "sg:city":"Kortenberg",
    "sg:orig_category":"Non-Classified Establishments",
    "sg:phone":"+32 2 759 61 50",
    "sg:postcode":"3070",
    "sg:province":"Vlaams-Brabant",
    "wof:name":"Vclb Medische Diensten",
    "wof:placetype":"venue"
},
  "geometry": {"coordinates":[4.5429081917,50.8860778809],"type":"Point"}
}