{
  "type": "Feature",
  "properties": {
    "addr:full":"Industriezone 2 Bus 5 Diest Vlaams-Brabant 3290",
    "addr:housenumber":"2 bus 5",
    "addr:postcode":"3290",
    "addr:street":"Industriezone",
    "iso:country":"BE",
    "sg:address":"Industriezone 2 Bus 5",
    "sg:city":"Diest",
    "sg:orig_category":"Ecoles de pilotage de bateaux and d\u00b4avions. Transports a\u00e9riens non-r\u00e9guliers",
    "sg:phone":"+32 13 32 33 44",
    "sg:postcode":"3290",
    "sg:province":"Vlaams-Brabant",
    "wof:name":"Paramount Helicopters Diest",
    "wof:placetype":"venue"
},
  "geometry": {"coordinates":[5.0511350632,50.9845848083],"type":"Point"}
}