{
  "type": "Feature",
  "properties": {
    "iso:country":"BE",
    "sg:address":"Europalaan 57",
    "sg:city":"Tielt",
    "sg:classifiers":[
        {
            "category":"Retail",
            "subcategory":"Veterinary Services",
            "type":"Services"
        }
    ],
    "sg:phone":"+32 51 40 39 97",
    "sg:postcode":"8700",
    "sg:province":"West-Vlaanderen",
    "sg:tags":[
        "veterinarian"
    ],
    "wof:name":"Van Peteghem A",
    "wof:placetype":"venue"
},
  "geometry": {"coordinates":[3.3330259323,50.9993438721],"type":"Point"}
}