{
  "type": "Feature",
  "properties": {
    "iso:country":"BE",
    "sg:address":"Kiezel 44",
    "sg:city":"Meerhout",
    "sg:classifiers":[
        {
            "category":"Professional",
            "subcategory":"Art Services",
            "type":"Services"
        }
    ],
    "sg:phone":"+32 14 30 12 17",
    "sg:postcode":"2450",
    "sg:province":"Antwerpen",
    "sg:tags":[
        "interior",
        "designer"
    ],
    "wof:name":"Deckers Jos",
    "wof:placetype":"venue"
},
  "geometry": {"coordinates":[5.0274391174,51.1314926147],"type":"Point"}
}