{
  "type": "Feature",
  "properties": {
    "addr:full":"Rue De Fosses 15 Mettet Namur 5640",
    "addr:housenumber":"15",
    "addr:postcode":"5640",
    "addr:street":"Rue De Fosses",
    "iso:country":"BE",
    "sg:address":"Rue De Fosses 15",
    "sg:city":"Mettet",
    "sg:classifiers":[
        {
            "category":"Shopping",
            "subcategory":"Antiques",
            "type":"Retail Goods"
        }
    ],
    "sg:phone":"+32 71 72 95 47",
    "sg:postcode":"5640",
    "sg:province":"Namur",
    "wof:name":"Charme Du Pass\u00e9 (au)",
    "wof:placetype":"venue"
},
  "geometry": {"coordinates":[4.6552500725,50.3367614746],"type":"Point"}
}