{
  "type": "Feature",
  "properties": {
    "addr:full":"Kloosterstraat 32 Opwijk Vlaams-Brabant 1745",
    "addr:housenumber":"32",
    "addr:postcode":"1745",
    "addr:street":"Kloosterstraat",
    "iso:country":"BE",
    "sg:address":"Kloosterstraat 32",
    "sg:city":"Opwijk",
    "sg:classifiers":[
        {
            "category":"Bars & Pubs",
            "type":"Food & Drink"
        }
    ],
    "sg:phone":"+32 52 35 52 77",
    "sg:postcode":"1745",
    "sg:province":"Vlaams-Brabant",
    "wof:name":"Eendracht (caf\u00e9)",
    "wof:placetype":"venue"
},
  "geometry": {"coordinates":[4.183863163,50.9671592712],"type":"Point"}
}