{
  "type": "Feature",
  "properties": {
    "addr:full":"Rue Vert Vinave 106 Herstal Li\u00e8ge 4041",
    "addr:housenumber":"106",
    "addr:postcode":"4041",
    "addr:street":"Rue Vert Vinave",
    "iso:country":"BE",
    "sg:address":"Rue Vert Vinave 106",
    "sg:city":"Herstal",
    "sg:orig_category":"IJzerwaren, bouw- and verfmaterialen Verlichting and huishoudartikelen",
    "sg:phone":"+32 4 227 34 51",
    "sg:postcode":"4041",
    "sg:province":"Li\u00e8ge",
    "wof:name":"J.m. Boussard",
    "wof:placetype":"venue"
},
  "geometry": {"coordinates":[5.5909352303,50.6730079651],"type":"Point"}
}