{
  "type": "Feature",
  "properties": {
    "iso:country":"BE",
    "sg:address":"Petrus Bogaertslaan 34",
    "sg:city":"Schilde",
    "sg:classifiers":[
        {
            "category":"Insurance",
            "subcategory":"Life Insurance",
            "type":"Services"
        }
    ],
    "sg:phone":"+32 3 385 11 52",
    "sg:postcode":"2970",
    "sg:province":"Antwerpen",
    "sg:tags":[
        "assurance"
    ],
    "wof:name":"Vermeylen S.",
    "wof:placetype":"venue"
},
  "geometry": {"coordinates":[4.5779538155,51.2353935242],"type":"Point"}
}