{
  "type": "Feature",
  "properties": {
    "addr:full":"Pamelstraat 334 Ninove Oost-Vlaanderen 9400",
    "addr:housenumber":"334",
    "addr:postcode":"9400",
    "addr:street":"Pamelstraat",
    "iso:country":"BE",
    "sg:address":"Pamelstraat 334",
    "sg:city":"Ninove",
    "sg:classifiers":[
        {
            "category":"Personal",
            "subcategory":"Beauty Salon",
            "type":"Services"
        }
    ],
    "sg:phone":"+32 54 33 12 45",
    "sg:postcode":"9400",
    "sg:province":"Oost-Vlaanderen",
    "sg:tags":[
        "de",
        "coiffure"
    ],
    "wof:name":"Coiffure Nancy",
    "wof:placetype":"venue"
},
  "geometry": {"coordinates":[4.0360760689,50.8400802612],"type":"Point"}
}