{
  "type": "Feature",
  "properties": {
    "addr:full":"Sartlaan 46 Oostende West-Vlaanderen 8400",
    "addr:housenumber":"46",
    "addr:postcode":"8400",
    "addr:street":"Sartlaan",
    "iso:country":"BE",
    "sg:address":"Sartlaan 46",
    "sg:city":"Oostende",
    "sg:orig_category":"Dakwerken Loodgieterij, verwarming and sanitaire installaties Woningbouw",
    "sg:phone":"+32 496 37 70 96",
    "sg:postcode":"8400",
    "sg:province":"West-Vlaanderen",
    "wof:name":"Verhelst-verde",
    "wof:placetype":"venue"
},
  "geometry": {"coordinates":[2.9126999378,51.2312583923],"type":"Point"}
}