{
  "type": "Feature",
  "properties": {
    "iso:country":"BE",
    "sg:address":"Gistelsteenweg 306",
    "sg:city":"Jabbeke",
    "sg:orig_category":"Supermarch\u00e9s",
    "sg:phone":"+32 50 81 27 55",
    "sg:postcode":"8490",
    "sg:province":"West-Vlaanderen",
    "wof:name":"Alvo",
    "wof:placetype":"venue"
},
  "geometry": {"coordinates":[3.092633009,51.1804924011],"type":"Point"}
}