{
  "type": "Feature",
  "properties": {
    "iso:country":"BE",
    "sg:address":"All\u00e9e Des Artisans 29",
    "sg:city":"Ciney",
    "sg:classifiers":[
        {
            "category":"Building & Trades",
            "subcategory":"Equipment Rental",
            "type":"Services"
        }
    ],
    "sg:phone":"+32 83 23 40 08",
    "sg:postcode":"5590",
    "sg:province":"Namur",
    "sg:tags":[
        "tableware",
        "-"
    ],
    "wof:name":"Loca Horeca",
    "wof:placetype":"venue"
},
  "geometry": {"coordinates":[5.1070361137,50.3111114502],"type":"Point"}
}