{
  "type": "Feature",
  "properties": {
    "addr:full":"Blauwe Stap 10 Herent Vlaams-Brabant 3020",
    "addr:housenumber":"10",
    "addr:postcode":"3020",
    "addr:street":"Blauwe Stap",
    "iso:country":"BE",
    "sg:address":"Blauwe Stap 10",
    "sg:city":"Herent",
    "sg:orig_category":"Advocaten and juridische adviseurs",
    "sg:phone":"+32 16 29 37 59",
    "sg:postcode":"3020",
    "sg:province":"Vlaams-Brabant",
    "wof:name":"Johan Liesenborghs",
    "wof:placetype":"venue"
},
  "geometry": {"coordinates":[4.6871991158,50.9147911072],"type":"Point"}
}