{
  "type": "Feature",
  "properties": {
    "addr:full":"Deerlijkseweg 207b8 Waregem West-Vlaanderen 8790",
    "addr:housenumber":"207b8",
    "addr:postcode":"8790",
    "addr:street":"Deerlijkseweg",
    "iso:country":"BE",
    "sg:address":"Deerlijkseweg 207b8",
    "sg:city":"Waregem",
    "sg:orig_category":"Pain, p\u00e2tisseries and confiseries",
    "sg:phone":"+32 56 60 10 38",
    "sg:postcode":"8790",
    "sg:province":"West-Vlaanderen",
    "wof:name":"Stefaan Vereecke",
    "wof:placetype":"venue"
},
  "geometry": {"coordinates":[3.4079899788,50.869178772],"type":"Point"}
}