{
  "type": "Feature",
  "properties": {
    "iso:country":"BE",
    "sg:address":"Marie-jos\u00c9laan 33",
    "sg:city":"Berchem",
    "sg:orig_category":"Bloemen and planten Fleurop Interflora",
    "sg:phone":"+32 3 239 18 59",
    "sg:postcode":"2600",
    "sg:province":"Antwerpen",
    "wof:name":"Pvba Florival",
    "wof:placetype":"venue"
},
  "geometry": {"coordinates":[4.4249582291,51.1869926453],"type":"Point"}
}