{
  "type": "Feature",
  "properties": {
    "iso:country":"BE",
    "sg:address":"Herseltseweg 24",
    "sg:city":"Laakdal (veerle)",
    "sg:classifiers":[
        {
            "category":"Community Center",
            "subcategory":"Youth",
            "type":"Public Place"
        }
    ],
    "sg:phone":"+32 14 84 25 42",
    "sg:postcode":"2431",
    "sg:province":"Antwerpen",
    "sg:tags":[
        "club"
    ],
    "wof:name":"Ooievaarsnest (kinderboerderij)",
    "wof:placetype":"venue"
},
  "geometry": {"coordinates":[4.9489388466,51.0678939819],"type":"Point"}
}