{
  "type": "Feature",
  "properties": {
    "iso:country":"BE",
    "sg:address":"Kromstraat 61",
    "sg:city":"Dessel",
    "sg:classifiers":[
        {
            "category":"Health Services",
            "subcategory":"Doctor",
            "type":"Services"
        }
    ],
    "sg:phone":"+32 14 37 17 60",
    "sg:postcode":"2480",
    "sg:province":"Antwerpen",
    "sg:tags":[
        "orthopedist"
    ],
    "wof:name":"Van Dyck Consulting",
    "wof:placetype":"venue"
},
  "geometry": {"coordinates":[5.1370811462,51.2378768921],"type":"Point"}
}