{
  "type": "Feature",
  "properties": {
    "addr:full":"Dorp-west 66 Lochristi Oost-Vlaanderen 9080",
    "addr:housenumber":"66",
    "addr:postcode":"9080",
    "addr:street":"Dorp-West",
    "iso:country":"BE",
    "sg:address":"Dorp-west 66",
    "sg:city":"Lochristi",
    "sg:orig_category":"Banken and kredietinstellingen",
    "sg:phone":"+32 9 355 15 60",
    "sg:postcode":"9080",
    "sg:province":"Oost-Vlaanderen",
    "wof:name":"V.d.k. Spaarbank",
    "wof:placetype":"venue"
},
  "geometry": {"coordinates":[3.8300330639,51.0956802368],"type":"Point"}
}