{
  "type": "Feature",
  "properties": {
    "iso:country":"BE",
    "sg:address":"Hugo Lef\u00e8vrestraat 16",
    "sg:city":"Aalst",
    "sg:classifiers":[
        {
            "category":"Education",
            "subcategory":"Special Training",
            "type":"Public Place"
        }
    ],
    "sg:phone":"+32 53 21 58 97",
    "sg:postcode":"9300",
    "sg:province":"Oost-Vlaanderen",
    "sg:tags":[
        "school",
        "language"
    ],
    "wof:name":"Cunningham Bvba",
    "wof:placetype":"venue"
},
  "geometry": {"coordinates":[4.037817955,50.9315185547],"type":"Point"}
}