{
  "type": "Feature",
  "properties": {
    "addr:full":"Rue Du Mouton Blanc 1bb Li\u00c8ge Li\u00e8ge 4000",
    "addr:housenumber":"1bb",
    "addr:postcode":"4000",
    "addr:street":"Rue Du Mouton Blanc",
    "iso:country":"BE",
    "sg:address":"Rue Du Mouton Blanc 1bb",
    "sg:city":"Li\u00c8ge",
    "sg:classifiers":[
        {
            "category":"Restaurant",
            "type":"Food & Drink"
        }
    ],
    "sg:phone":"+32 4 232 14 46",
    "sg:postcode":"4000",
    "sg:province":"Li\u00e8ge",
    "wof:name":"Le Qu\u00b4en Dira-t-on ?",
    "wof:placetype":"venue"
},
  "geometry": {"coordinates":[5.5701208115,50.6416931152],"type":"Point"}
}