{
  "type": "Feature",
  "properties": {
    "addr:full":"Nieuwstraat 11 Opwijk Vlaams-Brabant 1745",
    "addr:housenumber":"11",
    "addr:postcode":"1745",
    "addr:street":"Nieuwstraat",
    "iso:country":"BE",
    "sg:address":"Nieuwstraat 11",
    "sg:city":"Opwijk",
    "sg:classifiers":[
        {
            "category":"Communications",
            "type":"Services"
        }
    ],
    "sg:phone":"+32 52 35 55 26",
    "sg:postcode":"1745",
    "sg:province":"Vlaams-Brabant",
    "sg:tags":[
        "translator"
    ],
    "wof:name":"Degee J",
    "wof:placetype":"venue"
},
  "geometry": {"coordinates":[4.1778860092,50.9692306519],"type":"Point"}
}