{
  "type": "Feature",
  "properties": {
    "addr:full":"Kapellestraat 9 Laakdal Antwerpen 2431",
    "addr:housenumber":"9",
    "addr:postcode":"2431",
    "addr:street":"Kapellestraat",
    "iso:country":"BE",
    "sg:address":"Kapellestraat 9",
    "sg:city":"Laakdal",
    "sg:orig_category":"Enseignement maternel and primaire",
    "sg:phone":"+32 14 84 12 02",
    "sg:postcode":"2431",
    "sg:province":"Antwerpen",
    "wof:name":"B.s.g.o. De Wissel",
    "wof:placetype":"venue"
},
  "geometry": {"coordinates":[4.9864192009,51.0678482056],"type":"Point"}
}