{
  "type": "Feature",
  "properties": {
    "addr:full":"Biesweg 20 Lanaken Limburg 3620",
    "addr:housenumber":"20",
    "addr:postcode":"3620",
    "addr:street":"Biesweg",
    "iso:country":"BE",
    "sg:address":"Biesweg 20",
    "sg:city":"Lanaken",
    "sg:orig_category":"Kunstonderwijs",
    "sg:phone":"+32 89 71 22 10",
    "sg:postcode":"3620",
    "sg:province":"Limburg",
    "wof:name":"Gemeentelijke Muziekacademie Lanaken",
    "wof:placetype":"venue"
},
  "geometry": {"coordinates":[5.6071071625,50.8852653503],"type":"Point"}
}