{
  "type": "Feature",
  "properties": {
    "iso:country":"BE",
    "sg:address":"Oostdreef 48",
    "sg:city":"Dentergem (wakken)",
    "sg:classifiers":[
        {
            "category":"Education",
            "subcategory":"Library",
            "type":"Public Place"
        }
    ],
    "sg:phone":"+32 56 61 39 98",
    "sg:postcode":"8720",
    "sg:province":"West-Vlaanderen",
    "wof:name":"Bibliotheek Dentergem",
    "wof:placetype":"venue"
},
  "geometry": {"coordinates":[3.3999180794,50.9326400757],"type":"Point"}
}