{
  "type": "Feature",
  "properties": {
    "addr:full":"Eindestraat 137 Leopoldsburg Limburg 3971",
    "addr:housenumber":"137",
    "addr:postcode":"3971",
    "addr:street":"Eindestraat",
    "iso:country":"BE",
    "sg:address":"Eindestraat 137",
    "sg:city":"Leopoldsburg",
    "sg:orig_category":"Zuivelproducten",
    "sg:phone":"+32 11 34 40 65",
    "sg:postcode":"3971",
    "sg:province":"Limburg",
    "wof:name":"La Verona",
    "wof:placetype":"venue"
},
  "geometry": {"coordinates":[5.2173128128,51.1032104492],"type":"Point"}
}