{
  "type": "Feature",
  "properties": {
    "iso:country":"BE",
    "sg:address":"Beemont 10",
    "sg:city":"Ouffet",
    "sg:orig_category":"Vakantiehuizen",
    "sg:phone":"+32 86 36 60 03",
    "sg:postcode":"4590",
    "sg:province":"Li\u00e8ge",
    "wof:name":"Halleux-marcotty",
    "wof:placetype":"venue"
},
  "geometry": {"coordinates":[5.4040360451,50.4466018677],"type":"Point"}
}