{
  "type": "Feature",
  "properties": {
    "iso:country":"BE",
    "sg:address":"All\u00e9e Des Noisetiers 91",
    "sg:city":"Gerpinnes",
    "sg:classifiers":[
        {
            "category":"Health Services",
            "subcategory":"Nursing And Care Facility",
            "type":"Services"
        }
    ],
    "sg:phone":"+32 71 22 03 59",
    "sg:postcode":"6280",
    "sg:province":"Hainaut",
    "sg:tags":[
        "home",
        "rest"
    ],
    "wof:name":"Coudraie (la)",
    "wof:placetype":"venue"
},
  "geometry": {"coordinates":[4.4755501747,50.347038269],"type":"Point"}
}