{
  "type": "Feature",
  "properties": {
    "iso:country":"BE",
    "sg:address":"Rechtstraat 1",
    "sg:city":"Lokeren (eksaarde)",
    "sg:classifiers":[
        {
            "category":"Bakery",
            "type":"Food & Drink"
        }
    ],
    "sg:phone":"+32 9 346 81 97",
    "sg:postcode":"9160",
    "sg:province":"Oost-Vlaanderen",
    "sg:tags":[
        "confectioner",
        "baker"
    ],
    "wof:name":"Dirinck G",
    "wof:placetype":"venue"
},
  "geometry": {"coordinates":[3.9540760517,51.145904541],"type":"Point"}
}