{
  "type": "Feature",
  "properties": {
    "addr:full":"Gentweg 26 Gavere Oost-Vlaanderen 9890",
    "addr:housenumber":"26",
    "addr:postcode":"9890",
    "addr:street":"Gentweg",
    "iso:country":"BE",
    "sg:address":"Gentweg 26",
    "sg:city":"Gavere",
    "sg:orig_category":"Non-Classified Establishments",
    "sg:phone":"+32 9 384 40 69",
    "sg:postcode":"9890",
    "sg:province":"Oost-Vlaanderen",
    "wof:name":"Van Meirhaeghe J-c",
    "wof:placetype":"venue"
},
  "geometry": {"coordinates":[3.6837909222,50.9464874268],"type":"Point"}
}