{
  "type": "Feature",
  "properties": {
    "addr:full":"Smoutakker 1 Stabroek Antwerpen 2940",
    "addr:housenumber":"1",
    "addr:postcode":"2940",
    "addr:street":"Smoutakker",
    "iso:country":"BE",
    "sg:address":"Smoutakker 1",
    "sg:city":"Stabroek",
    "sg:orig_category":"Meubles D\u00e9taillants, Am\u00e9nagement de B\u00e2timents et de Cuisines",
    "sg:phone":"+32 3 568 61 36",
    "sg:postcode":"2940",
    "sg:province":"Antwerpen",
    "wof:name":"Mariette Piron",
    "wof:placetype":"venue"
},
  "geometry": {"coordinates":[4.3676562309,51.3327331543],"type":"Point"}
}