{
  "type": "Feature",
  "properties": {
    "iso:country":"BE",
    "sg:address":"Kapucijnenstraat 4",
    "sg:city":"Oostende",
    "sg:classifiers":[
        {
            "category":"Food & Beverages",
            "subcategory":"Meat & Fish",
            "type":"Retail Goods"
        }
    ],
    "sg:phone":"+32 59 70 23 94",
    "sg:postcode":"8400",
    "sg:province":"West-Vlaanderen",
    "sg:tags":[
        "poultry",
        "whol",
        "game",
        "-"
    ],
    "wof:name":"Laleman",
    "wof:placetype":"venue"
},
  "geometry": {"coordinates":[2.9190900326,51.2326087952],"type":"Point"}
}