{
  "type": "Feature",
  "properties": {
    "addr:full":"Chemin Des Postes 29 Waterloo Brabant Wallon 1410",
    "addr:housenumber":"29",
    "addr:postcode":"1410",
    "addr:street":"Chemin Des Postes",
    "iso:country":"BE",
    "sg:address":"Chemin Des Postes 29",
    "sg:city":"Waterloo",
    "sg:classifiers":[
        {
            "category":"Personal",
            "subcategory":"Nail Salon",
            "type":"Services"
        }
    ],
    "sg:phone":"+32 2 384 06 03",
    "sg:postcode":"1410",
    "sg:province":"Brabant Wallon",
    "sg:tags":[
        "pedicure"
    ],
    "wof:name":"Depr\u00e9 F",
    "wof:placetype":"venue"
},
  "geometry": {"coordinates":[4.3721990585,50.7037467957],"type":"Point"}
}