{
  "type": "Feature",
  "properties": {
    "iso:country":"BE",
    "sg:address":".",
    "sg:city":"Kortenberg",
    "sg:orig_category":"Overheidsdiensten",
    "sg:phone":"+32 2 755 22 00",
    "sg:postcode":"3078",
    "sg:province":"Vlaams-Brabant",
    "wof:name":"Gemeentebestuur Meerbeek",
    "wof:placetype":"venue"
},
  "geometry": {"coordinates":[4.5707449913,50.8783035278],"type":"Point"}
}