{
  "type": "Feature",
  "properties": {
    "addr:full":"Franklin Rooseveltplaats 1 Antwerpen Antwerpen 2060",
    "addr:housenumber":"1",
    "addr:postcode":"2060",
    "iso:country":"BE",
    "sg:address":"Franklin Rooseveltplaats 1",
    "sg:city":"Antwerpen",
    "sg:classifiers":[
        {
            "category":"Cafe",
            "type":"Food & Drink"
        }
    ],
    "sg:phone":"+32 3 234 04 99",
    "sg:postcode":"2060",
    "sg:province":"Antwerpen",
    "sg:tags":[
        "caf\u00e9s"
    ],
    "wof:name":"Caf\u00c9 Victoria",
    "wof:placetype":"venue"
},
  "geometry": {"coordinates":[4.41685009,51.220287323],"type":"Point"}
}