{
  "type": "Feature",
  "properties": {
    "addr:full":"Vlamertingsestraat 23 Ieper (vlamertinge) West-Vlaanderen 8908",
    "addr:housenumber":"23",
    "addr:postcode":"8908",
    "addr:street":"Vlamertingsestraat",
    "iso:country":"BE",
    "sg:address":"Vlamertingsestraat 23",
    "sg:city":"Ieper (vlamertinge)",
    "sg:classifiers":[
        {
            "category":"Real Estate",
            "subcategory":"Architect",
            "type":"Services"
        }
    ],
    "sg:phone":"+32 57 20 50 50",
    "sg:postcode":"8908",
    "sg:province":"West-Vlaanderen",
    "wof:name":"Leleu L",
    "wof:placetype":"venue"
},
  "geometry": {"coordinates":[2.8271679878,50.8574066162],"type":"Point"}
}