{
  "type": "Feature",
  "properties": {
    "addr:full":"Rue De Poix 103 Libin Luxembourg 6890",
    "addr:housenumber":"103",
    "addr:postcode":"6890",
    "addr:street":"Rue De Poix",
    "iso:country":"BE",
    "sg:address":"Rue De Poix 103",
    "sg:city":"Libin",
    "sg:classifiers":[
        {
            "category":"Building & Trades",
            "subcategory":"Landscaping Services",
            "type":"Services"
        }
    ],
    "sg:phone":"+32 61 65 55 13",
    "sg:postcode":"6890",
    "sg:province":"Luxembourg",
    "sg:tags":[
        "nurseryman"
    ],
    "wof:name":"Denis M",
    "wof:placetype":"venue"
},
  "geometry": {"coordinates":[5.2568268776,49.9835548401],"type":"Point"}
}