{
  "type": "Feature",
  "properties": {
    "iso:country":"BE",
    "sg:address":"Steenweg Op Dendermonde 127-130",
    "sg:city":"Opwijk",
    "sg:classifiers":[
        {
            "category":"Home & Garden",
            "subcategory":"Building Materials",
            "type":"Retail Goods"
        }
    ],
    "sg:phone":"+32 52 35 60 78",
    "sg:postcode":"1745",
    "sg:province":"Vlaams-Brabant",
    "sg:tags":[
        "-",
        "fireplace",
        "open",
        "ornamental"
    ],
    "wof:name":"Stassijns Bvba",
    "wof:placetype":"venue"
},
  "geometry": {"coordinates":[4.1559500694,50.96118927],"type":"Point"}
}