{
  "type": "Feature",
  "properties": {
    "addr:full":"Molenstraat 19 Brecht Antwerpen 2960",
    "addr:housenumber":"19",
    "addr:postcode":"2960",
    "addr:street":"Molenstraat",
    "iso:country":"BE",
    "sg:address":"Molenstraat 19",
    "sg:city":"Brecht",
    "sg:classifiers":[
        {
            "category":"Health Services",
            "subcategory":"Health Practitioner",
            "type":"Services"
        }
    ],
    "sg:phone":"+32 3 313 09 64",
    "sg:postcode":"2960",
    "sg:province":"Antwerpen",
    "sg:tags":[
        "physiotherapist"
    ],
    "wof:name":"Marynen B",
    "wof:placetype":"venue"
},
  "geometry": {"coordinates":[4.6370592117,51.3476982117],"type":"Point"}
}