{
  "type": "Feature",
  "properties": {
    "iso:country":"BE",
    "sg:address":"Duifhoekstraat 2",
    "sg:city":"Lichtervelde",
    "sg:orig_category":"Installatie van houten of kunststof schrijnwerk",
    "sg:phone":"+32 51 72 66 76",
    "sg:postcode":"8810",
    "sg:province":"West-Vlaanderen",
    "wof:name":"Demeulenaere",
    "wof:placetype":"venue"
},
  "geometry": {"coordinates":[3.1337890625,51.0173149109],"type":"Point"}
}