{
  "type": "Feature",
  "properties": {
    "addr:full":"Brusselsestw 41a Mechelen Antwerpen 2800",
    "addr:housenumber":"41a",
    "addr:postcode":"2800",
    "addr:street":"Brusselsestw",
    "iso:country":"BE",
    "sg:address":"Brusselsestw 41a",
    "sg:city":"Mechelen",
    "sg:classifiers":[
        {
            "category":"Banks & Credit Unions",
            "subcategory":"Bank",
            "type":"Services"
        }
    ],
    "sg:phone":"+32 15 42 36 58",
    "sg:postcode":"2800",
    "sg:province":"Antwerpen",
    "wof:name":"Banque Bruxelles Lambert Sa",
    "wof:placetype":"venue"
},
  "geometry": {"coordinates":[4.4728331566,51.0194282532],"type":"Point"}
}