{
  "type": "Feature",
  "properties": {
    "addr:full":"Avenue De Ninove 109 Rochefort (jemelle) Namur 5580",
    "addr:housenumber":"109",
    "addr:postcode":"5580",
    "addr:street":"Avenue De Ninove",
    "iso:country":"BE",
    "sg:address":"Avenue De Ninove 109",
    "sg:city":"Rochefort (jemelle)",
    "sg:classifiers":[
        {
            "category":"Bars & Pubs",
            "type":"Food & Drink"
        }
    ],
    "sg:phone":"+32 84 22 17 58",
    "sg:postcode":"5580",
    "sg:province":"Namur",
    "wof:name":"Must (le)",
    "wof:placetype":"venue"
},
  "geometry": {"coordinates":[5.2597098351,50.1634864807],"type":"Point"}
}