{
  "type": "Feature",
  "properties": {
    "iso:country":"BE",
    "sg:address":"Rue Albert I 240",
    "sg:city":"Erquelinnes",
    "sg:classifiers":[
        {
            "category":"Shopping",
            "subcategory":"Luggage & Leather Goods",
            "type":"Retail Goods"
        }
    ],
    "sg:phone":"+32 71 59 65 09",
    "sg:postcode":"6560",
    "sg:province":"Hainaut",
    "sg:tags":[
        "-"
    ],
    "wof:name":"Val'fashion",
    "wof:placetype":"venue"
},
  "geometry": {"coordinates":[4.1207499504,50.3097915649],"type":"Point"}
}