{
  "type": "Feature",
  "properties": {
    "addr:full":"Maastrichterstraat 92 Hasselt Limburg 3500",
    "addr:housenumber":"92",
    "addr:postcode":"3500",
    "addr:street":"Maastrichterstraat",
    "iso:country":"BE",
    "sg:address":"Maastrichterstraat 92",
    "sg:city":"Hasselt",
    "sg:classifiers":[
        {
            "category":"Fast Food",
            "type":"Food & Drink"
        }
    ],
    "sg:phone":"+32 11 24 26 93",
    "sg:postcode":"3500",
    "sg:province":"Limburg",
    "sg:tags":[
        "\u00c0",
        "emporter",
        "restaurants"
    ],
    "wof:name":"Frituur Mec-minute",
    "wof:placetype":"venue"
},
  "geometry": {"coordinates":[5.3492188454,50.9300193787],"type":"Point"}
}