{
  "type": "Feature",
  "properties": {
    "addr:full":"Breedstraat 97 Sint-niklaas Oost-Vlaanderen 9100",
    "addr:housenumber":"97",
    "addr:postcode":"9100",
    "addr:street":"Breedstraat",
    "iso:country":"BE",
    "sg:address":"Breedstraat 97",
    "sg:city":"Sint-niklaas",
    "sg:classifiers":[
        {
            "category":"Education",
            "subcategory":"Dance Studio",
            "type":"Public Place"
        }
    ],
    "sg:phone":"+32 3 776 62 18",
    "sg:postcode":"9100",
    "sg:province":"Oost-Vlaanderen",
    "sg:tags":[
        "ballet",
        "school"
    ],
    "wof:name":"Clapaja Bvba",
    "wof:placetype":"venue"
},
  "geometry": {"coordinates":[4.1613168716,51.1676292419],"type":"Point"}
}