{
  "type": "Feature",
  "properties": {
    "iso:country":"BE",
    "sg:address":"Torhoutse Steenweg 298",
    "sg:city":"Brugge",
    "sg:orig_category":"Diverse juridische dienstverlening",
    "sg:phone":"+32 50 39 33 05",
    "sg:postcode":"8200",
    "sg:province":"West-Vlaanderen",
    "wof:name":"D. Gevaert",
    "wof:placetype":"venue"
},
  "geometry": {"coordinates":[3.1987290382,51.1943092346],"type":"Point"}
}