{
  "type": "Feature",
  "properties": {
    "addr:full":"Eeckbergstraat 56 Sint-gillis-waas Oost-Vlaanderen 9170",
    "addr:housenumber":"56",
    "addr:postcode":"9170",
    "addr:street":"Eeckbergstraat",
    "iso:country":"BE",
    "sg:address":"Eeckbergstraat 56",
    "sg:city":"Sint-gillis-waas",
    "sg:orig_category":"Zuivelproducten",
    "sg:phone":"+32 3 707 08 90",
    "sg:postcode":"9170",
    "sg:province":"Oost-Vlaanderen",
    "wof:name":"Rudi Hillaert",
    "wof:placetype":"venue"
},
  "geometry": {"coordinates":[4.1197018623,51.2397460938],"type":"Point"}
}