{
  "type": "Feature",
  "properties": {
    "addr:full":"Haut-vent 177 Herve Li\u00e8ge 4654",
    "addr:housenumber":"177",
    "addr:postcode":"4654",
    "addr:street":"Haut-Vent",
    "iso:country":"BE",
    "sg:address":"Haut-vent 177",
    "sg:city":"Herve",
    "sg:orig_category":"Rundveehouders",
    "sg:phone":"+32 87 67 47 89",
    "sg:postcode":"4654",
    "sg:province":"Li\u00e8ge",
    "wof:name":"Joseph Corman",
    "wof:placetype":"venue"
},
  "geometry": {"coordinates":[5.7966737747,50.6572570801],"type":"Point"}
}