{
  "type": "Feature",
  "properties": {
    "iso:country":"BE",
    "sg:address":"Lillerbaan 77",
    "sg:city":"Peer (kleine Brogel)",
    "sg:orig_category":"Autombile concessionaires",
    "sg:phone":"+32 11 63 23 70",
    "sg:postcode":"3990",
    "sg:province":"Limburg",
    "wof:name":"Gar Cooreman E",
    "wof:placetype":"venue"
},
  "geometry": {"coordinates":[5.4533009529,51.1329536438],"type":"Point"}
}