{
  "type": "Feature",
  "properties": {
    "addr:full":"Rue \u00c0 Blanc Pain 10 Beloeil Hainaut 7973",
    "addr:housenumber":"10",
    "addr:postcode":"7973",
    "addr:street":"Rue A\u0300 Blanc Pain",
    "iso:country":"BE",
    "sg:address":"Rue \u00c0 Blanc Pain 10",
    "sg:city":"Beloeil",
    "sg:orig_category":"Installatie van houten of kunststof schrijnwerk",
    "sg:phone":"+32 69 56 06 24",
    "sg:postcode":"7973",
    "sg:province":"Hainaut",
    "wof:name":"Jules Bral",
    "wof:placetype":"venue"
},
  "geometry": {"coordinates":[3.7196578979,50.5115814209],"type":"Point"}
}