{
  "type": "Feature",
  "properties": {
    "addr:full":"Sint-laurentiusstraat 70 Maasmechelen Limburg 3630",
    "addr:housenumber":"70",
    "addr:postcode":"3630",
    "addr:street":"Sint-Laurentiusstraat",
    "iso:country":"BE",
    "sg:address":"Sint-laurentiusstraat 70",
    "sg:city":"Maasmechelen",
    "sg:orig_category":"D\u00e9chets and d\u00e9bris Eleveurs de bovins",
    "sg:phone":"+32 89 75 56 95",
    "sg:postcode":"3630",
    "sg:province":"Limburg",
    "wof:name":"Henri Venken",
    "wof:placetype":"venue"
},
  "geometry": {"coordinates":[5.7463889122,51.0048103333],"type":"Point"}
}