{
  "type": "Feature",
  "properties": {
    "iso:country":"BE",
    "sg:address":"Liersesteenweg 4",
    "sg:city":"Berlaar",
    "sg:classifiers":[
        {
            "category":"Health Services",
            "subcategory":"Health Practitioner",
            "type":"Services"
        }
    ],
    "sg:phone":"+32 3 482 13 61",
    "sg:postcode":"2590",
    "sg:province":"Antwerpen",
    "sg:tags":[
        "physiotherapist"
    ],
    "wof:name":"Smeets H",
    "wof:placetype":"venue"
},
  "geometry": {"coordinates":[4.6502408981,51.1172485352],"type":"Point"}
}