{
  "type": "Feature",
  "properties": {
    "iso:country":"BE",
    "sg:address":"Aim\u00c9 Liebaertstraat 27",
    "sg:city":"Oostende",
    "sg:orig_category":"Chaussures",
    "sg:phone":"+32 59 32 31 10",
    "sg:postcode":"8400",
    "sg:province":"West-Vlaanderen",
    "wof:name":"Huis Rammant",
    "wof:placetype":"venue"
},
  "geometry": {"coordinates":[2.942579031,51.2298278809],"type":"Point"}
}