{
  "type": "Feature",
  "properties": {
    "iso:country":"BE",
    "sg:address":"Rue Du Vivier 108",
    "sg:city":"Marche-en-famenne",
    "sg:orig_category":"Artsen and specialisten",
    "sg:phone":"+32 84 31 55 77",
    "sg:postcode":"6900",
    "sg:province":"Luxembourg",
    "wof:name":"Violaine Sevrin",
    "wof:placetype":"venue"
},
  "geometry": {"coordinates":[5.3271999359,50.2289581299],"type":"Point"}
}