{
  "type": "Feature",
  "properties": {
    "addr:full":"Rue Basse Voye 64 Doische (vodel\u00e9e) Namur 5680",
    "addr:housenumber":"64",
    "addr:postcode":"5680",
    "addr:street":"Rue Basse Voye",
    "iso:country":"BE",
    "sg:address":"Rue Basse Voye 64",
    "sg:city":"Doische (vodel\u00e9e)",
    "sg:classifiers":[
        {
            "category":"Home & Garden",
            "subcategory":"Carpets & Floor Coverings",
            "type":"Retail Goods"
        }
    ],
    "sg:phone":"+32 82 67 76 26",
    "sg:postcode":"5680",
    "sg:province":"Namur",
    "sg:tags":[
        "delivery",
        "-",
        "van"
    ],
    "wof:name":"Radelet Sprl",
    "wof:placetype":"venue"
},
  "geometry": {"coordinates":[4.7328739166,50.1701431274],"type":"Point"}
}