{
  "type": "Feature",
  "properties": {
    "addr:full":"Avenue Rodolphe Gossia 12 Orp-jauche (jauche) Brabant Wallon 1350",
    "addr:housenumber":"12",
    "addr:postcode":"1350",
    "addr:street":"Avenue Rodolphe Gossia;Wallon",
    "iso:country":"BE",
    "sg:address":"Avenue Rodolphe Gossia 12",
    "sg:city":"Orp-jauche (jauche)",
    "sg:classifiers":[
        {
            "category":"Social Services",
            "type":"Services"
        }
    ],
    "sg:phone":"+32 19 63 01 00",
    "sg:postcode":"1350",
    "sg:province":"Brabant Wallon",
    "wof:name":"Marc & Corine Asbl",
    "wof:placetype":"venue"
},
  "geometry": {"coordinates":[4.9699501991,50.676815033],"type":"Point"}
}