{
  "type": "Feature",
  "properties": {
    "iso:country":"BE",
    "sg:address":"Spinolarei 6bis",
    "sg:city":"Brugge",
    "sg:classifiers":[
        {
            "category":"Food & Beverages",
            "subcategory":"Specialty",
            "type":"Retail Goods"
        }
    ],
    "sg:phone":"+32 497 29 16 64",
    "sg:postcode":"8000",
    "sg:province":"West-Vlaanderen",
    "sg:tags":[
        "health",
        "dietary",
        "-",
        "biological"
    ],
    "wof:name":"Naprodis",
    "wof:placetype":"venue"
},
  "geometry": {"coordinates":[3.2273581028,51.2116775513],"type":"Point"}
}