{
  "type": "Feature",
  "properties": {
    "iso:country":"BE",
    "sg:address":"Schepen J. Ceulemansstr. 12",
    "sg:city":"Tremelo",
    "sg:orig_category":"Producteurs de l\u00e9gumes",
    "sg:phone":"+32 15 23 45 75",
    "sg:postcode":"3128",
    "sg:province":"Vlaams-Brabant",
    "wof:name":"Raymond Van Woensel",
    "wof:placetype":"venue"
},
  "geometry": {"coordinates":[4.7393140793,51.0225334167],"type":"Point"}
}