{
  "type": "Feature",
  "properties": {
    "addr:full":"Wijnstraat 68 Ronse/renaix Oost-Vlaanderen 9600",
    "addr:housenumber":"68",
    "addr:postcode":"9600",
    "addr:street":"Wijnstraat",
    "iso:country":"BE",
    "sg:address":"Wijnstraat 68",
    "sg:city":"Ronse/renaix",
    "sg:orig_category":"Brood, gebak and snoepgoed",
    "sg:phone":"+32 55 21 26 09",
    "sg:postcode":"9600",
    "sg:province":"Oost-Vlaanderen",
    "wof:name":"Jan Drossens",
    "wof:placetype":"venue"
},
  "geometry": {"coordinates":[3.5967619419,50.7498283386],"type":"Point"}
}