{
  "type": "Feature",
  "properties": {
    "addr:full":"All\u00e9e Des Moutons 30 Bruxelles Bruxelles-Capitale 1020",
    "addr:housenumber":"30",
    "addr:postcode":"1020",
    "addr:street":"Alle\u0301E Des Moutons",
    "iso:country":"BE",
    "sg:address":"All\u00e9e Des Moutons 30",
    "sg:city":"Bruxelles",
    "sg:classifiers":[
        {
            "category":"Bakery",
            "type":"Food & Drink"
        }
    ],
    "sg:phone":"+32 2 720 22 28",
    "sg:postcode":"1020",
    "sg:province":"Bruxelles-Capitale",
    "sg:tags":[
        "confectioner",
        "baker"
    ],
    "wof:name":"Panem Nostrum Scrl",
    "wof:placetype":"venue"
},
  "geometry": {"coordinates":[4.3651270866,50.9005584717],"type":"Point"}
}