{
  "type": "Feature",
  "properties": {
    "iso:country":"BE",
    "sg:address":"Kerkplein 7b6",
    "sg:city":"Lanaken",
    "sg:orig_category":"Imprimeries and copyshops",
    "sg:phone":"+32 89 72 21 01",
    "sg:postcode":"3620",
    "sg:province":"Limburg",
    "wof:name":"Bureau Steco",
    "wof:placetype":"venue"
},
  "geometry": {"coordinates":[5.6335458755,50.8637809753],"type":"Point"}
}