{
  "type": "Feature",
  "properties": {
    "addr:full":"Klein Zottegem 53 Sint-lievens-houtem Oost-Vlaanderen 9520",
    "addr:housenumber":"53",
    "addr:postcode":"9520",
    "addr:street":"Klein Zottegem;Oost-Vlaanderen",
    "iso:country":"BE",
    "sg:address":"Klein Zottegem 53",
    "sg:city":"Sint-lievens-houtem",
    "sg:orig_category":"Herstellingen and onderhoud van auto's Voertuigen",
    "sg:phone":"+32 53 62 26 79",
    "sg:postcode":"9520",
    "sg:province":"Oost-Vlaanderen",
    "wof:name":"Garage Vliera",
    "wof:placetype":"venue"
},
  "geometry": {"coordinates":[3.8887939453,50.9274482727],"type":"Point"}
}