{
  "type": "Feature",
  "properties": {
    "addr:full":"Burgemeester Van Gilsestraat 5 Baarle-hertog Antwerpen 2387",
    "addr:housenumber":"5",
    "addr:postcode":"2387",
    "addr:street":"Burgemeester Van Gilsestraat",
    "iso:country":"BE",
    "sg:address":"Burgemeester Van Gilsestraat 5",
    "sg:city":"Baarle-hertog",
    "sg:classifiers":[
        {
            "category":"Health Services",
            "subcategory":"Doctor",
            "type":"Services"
        }
    ],
    "sg:phone":"+32 14 69 91 20",
    "sg:postcode":"2387",
    "sg:province":"Antwerpen",
    "sg:tags":[
        "medicinephysicians",
        "surgeon"
    ],
    "wof:name":"Bloem J",
    "wof:placetype":"venue"
},
  "geometry": {"coordinates":[4.9228658676,51.4437065125],"type":"Point"}
}