{
  "type": "Feature",
  "properties": {
    "addr:full":"Rue De La Clawenne 92 Herstal Li\u00e8ge 4040",
    "addr:housenumber":"92",
    "addr:postcode":"4040",
    "addr:street":"Rue De La Clawenne",
    "iso:country":"BE",
    "sg:address":"Rue De La Clawenne 92",
    "sg:city":"Herstal",
    "sg:classifiers":[
        {
            "category":"Bars & Pubs",
            "type":"Food & Drink"
        }
    ],
    "sg:phone":"+32 4 248 19 31",
    "sg:postcode":"4040",
    "sg:province":"Li\u00e8ge",
    "wof:name":"A Vix Bon D'ju",
    "wof:placetype":"venue"
},
  "geometry": {"coordinates":[5.6372661591,50.6746673584],"type":"Point"}
}