{
  "type": "Feature",
  "properties": {
    "addr:full":"Rue De L'h\u00f4tel Communal 71 Saint-nicolas Li\u00e8ge 4420",
    "addr:housenumber":"71",
    "addr:postcode":"4420",
    "addr:street":"Rue De L'Ho \u0302Tel Communal",
    "iso:country":"BE",
    "sg:address":"Rue De L'h\u00f4tel Communal 71",
    "sg:city":"Saint-nicolas",
    "sg:classifiers":[
        {
            "category":"Real Estate",
            "subcategory":"Architect",
            "type":"Services"
        }
    ],
    "sg:phone":"+32 4 253 54 74",
    "sg:postcode":"4420",
    "sg:province":"Li\u00e8ge",
    "wof:name":"Agnello Bureau D'architecture",
    "wof:placetype":"venue"
},
  "geometry": {"coordinates":[5.5391907692,50.6321258545],"type":"Point"}
}