{
  "type": "Feature",
  "properties": {
    "addr:full":"Veldmaarschalk Montgomerystraat 136 Kuurne West-Vlaanderen 8520",
    "addr:housenumber":"136",
    "addr:postcode":"8520",
    "addr:street":"Veldmaarschalk Montgomerystraat",
    "iso:country":"BE",
    "sg:address":"Veldmaarschalk Montgomerystraat 136",
    "sg:city":"Kuurne",
    "sg:classifiers":[
        {
            "category":"Utilities",
            "subcategory":"Natural Gas",
            "type":"Services"
        }
    ],
    "sg:phone":"+32 56 71 98 69",
    "sg:postcode":"8520",
    "sg:province":"West-Vlaanderen",
    "sg:tags":[
        "firework"
    ],
    "wof:name":"Arlekino",
    "wof:placetype":"venue"
},
  "geometry": {"coordinates":[3.2784249783,50.8533935547],"type":"Point"}
}