{
  "type": "Feature",
  "properties": {
    "iso:country":"BE",
    "sg:address":"Grote Molenstraat 110",
    "sg:city":"Menen (lauwe)",
    "sg:classifiers":[
        {
            "category":"Freight",
            "type":"Transportation"
        }
    ],
    "sg:phone":"+32 56 41 25 49",
    "sg:postcode":"8930",
    "sg:province":"West-Vlaanderen",
    "sg:tags":[
        "-",
        "transport"
    ],
    "wof:name":"Brille Bvba",
    "wof:placetype":"venue"
},
  "geometry": {"coordinates":[3.188683033,50.790512085],"type":"Point"}
}