{
  "type": "Feature",
  "properties": {
    "addr:full":"Bunderstraat 22 Wervik West-Vlaanderen 8940",
    "addr:housenumber":"22",
    "addr:postcode":"8940",
    "addr:street":"Bunderstraat",
    "iso:country":"BE",
    "sg:address":"Bunderstraat 22",
    "sg:city":"Wervik",
    "sg:orig_category":"Souvenirs and objets artisanaux",
    "sg:phone":"+32 56 51 88 09",
    "sg:postcode":"8940",
    "sg:province":"West-Vlaanderen",
    "wof:name":"Heinz Vandendriessche",
    "wof:placetype":"venue"
},
  "geometry": {"coordinates":[3.0807759762,50.8127708435],"type":"Point"}
}