{
  "type": "Feature",
  "properties": {
    "iso:country":"BE",
    "sg:address":"Sint-genovevaplein 8",
    "sg:city":"Tienen",
    "sg:orig_category":"Enseignement maternel and primaire",
    "sg:phone":"+32 16 82 14 58",
    "sg:postcode":"3300",
    "sg:province":"Vlaams-Brabant",
    "wof:name":"Vrije Basisschool",
    "wof:placetype":"venue"
},
  "geometry": {"coordinates":[4.9887671471,50.8293190002],"type":"Point"}
}