{
  "type": "Feature",
  "properties": {
    "addr:full":"6 Papaverstraat 8300 Knokke-heist 6",
    "addr:housenumber":"6",
    "addr:postcode":"8300",
    "addr:street":"Papaverstraat",
    "iso:country":"BE",
    "sg:address":"6",
    "sg:city":"Papaverstraat 8300 Knokke-heist",
    "sg:classifiers":[
        {
            "category":"Wholesale",
            "subcategory":"Machinery & Supplies",
            "type":"Manufacturing & Wholesale Goods"
        }
    ],
    "sg:phone":"+32 50 60 88 79",
    "sg:postcode":"6",
    "sg:tags":[
        "handling",
        "material",
        "-",
        "machine",
        "equipment",
        "engineering",
        "mechanical"
    ],
    "wof:name":"Herbo Bvba",
    "wof:placetype":"venue"
},
  "geometry": {"coordinates":[3.287694931,51.3467254639],"type":"Point"}
}