{
  "type": "Feature",
  "properties": {
    "addr:full":"Katteveldstraat 28 Hoeselt Limburg 3730",
    "addr:housenumber":"28",
    "addr:postcode":"3730",
    "addr:street":"Katteveldstraat",
    "iso:country":"BE",
    "sg:address":"Katteveldstraat 28",
    "sg:city":"Hoeselt",
    "sg:classifiers":[
        {
            "category":"Home & Garden",
            "subcategory":"Home Furnishings",
            "type":"Retail Goods"
        }
    ],
    "sg:phone":"+32 12 26 10 07",
    "sg:postcode":"3730",
    "sg:province":"Limburg",
    "sg:tags":[
        "curtain",
        "-",
        "fixture"
    ],
    "wof:name":"Goffin R",
    "wof:placetype":"venue"
},
  "geometry": {"coordinates":[5.4806790352,50.8339576721],"type":"Point"}
}