{
  "type": "Feature",
  "properties": {
    "iso:country":"BE",
    "sg:address":"Wulvestraat 1ba",
    "sg:city":"Ieper",
    "sg:orig_category":"M\u00e9decins and sp\u00e9cialistes",
    "sg:phone":"+32 57 20 03 38",
    "sg:postcode":"8902",
    "sg:province":"West-Vlaanderen",
    "wof:name":"Robert Demyttenaere",
    "wof:placetype":"venue"
},
  "geometry": {"coordinates":[2.9222719669,50.8374633789],"type":"Point"}
}