{
  "type": "Feature",
  "properties": {
    "addr:full":"Rue Emile-matelart 119 Jemeppe-sur-sambre Namur 5190",
    "addr:housenumber":"119",
    "addr:postcode":"jemeppe-sur-sambre;5190",
    "addr:street":"Rue Emile-Matelart",
    "iso:country":"BE",
    "sg:address":"Rue Emile-matelart 119",
    "sg:city":"Jemeppe-sur-sambre",
    "sg:orig_category":"Installation de menuiserie en bois and plastique. Installation de menuiserie m\u00e9tallique",
    "sg:phone":"+32 81 63 40 43",
    "sg:postcode":"5190",
    "sg:province":"Namur",
    "wof:name":"Jean-luc Remy",
    "wof:placetype":"venue"
},
  "geometry": {"coordinates":[4.6490797997,50.5014305115],"type":"Point"}
}