{
  "type": "Feature",
  "properties": {
    "addr:full":"Rue De La Cayauderie 80 Charleroi Hainaut 6000",
    "addr:housenumber":"80",
    "addr:postcode":"6000",
    "addr:street":"Rue De La Cayauderie;Hainaut",
    "iso:country":"BE",
    "sg:address":"Rue De La Cayauderie 80",
    "sg:city":"Charleroi",
    "sg:classifiers":[
        {
            "category":"Personal",
            "subcategory":"Beauty Salon",
            "type":"Services"
        }
    ],
    "sg:phone":"+32 71 41 06 01",
    "sg:postcode":"6000",
    "sg:province":"Hainaut",
    "sg:tags":[
        "lady",
        "-",
        "hairdressing"
    ],
    "wof:name":"Cr\u00e9ation Natacha",
    "wof:placetype":"venue"
},
  "geometry": {"coordinates":[4.457903862,50.4236984253],"type":"Point"}
}