{
  "type": "Feature",
  "properties": {
    "iso:country":"BE",
    "sg:address":"Hulsestraat 10",
    "sg:city":"Nijlen",
    "sg:classifiers":[
        {
            "category":"Banks & Credit Unions",
            "subcategory":"Bank",
            "type":"Services"
        }
    ],
    "sg:phone":"+32 3 881 82 74",
    "sg:postcode":"2260",
    "sg:province":"Antwerpen",
    "wof:name":"Caisse Nationale De, Cr\u00e9dit Professionnel",
    "wof:placetype":"venue"
},
  "geometry": {"coordinates":[4.9112768173,51.0883636475],"type":"Point"}
}