{
  "type": "Feature",
  "properties": {
    "iso:country":"BE",
    "sg:address":"Gistelsteenweg 328",
    "sg:city":"Jabbeke",
    "sg:orig_category":"Tuinbenodigdheden",
    "sg:phone":"+32 50 81 12 74",
    "sg:postcode":"8490",
    "sg:province":"West-Vlaanderen",
    "wof:name":"Denoyette",
    "wof:placetype":"venue"
},
  "geometry": {"coordinates":[3.0882968903,51.1810760498],"type":"Point"}
}