{
  "type": "Feature",
  "properties": {
    "iso:country":"BE",
    "sg:address":"Rue Jean Delange 3",
    "sg:city":"Hannut",
    "sg:orig_category":"V\u00eatements sur mesure Fab",
    "sg:phone":"+32 19 51 10 45",
    "sg:postcode":"4280",
    "sg:province":"Li\u00e8ge",
    "wof:name":"Marie Thirion",
    "wof:placetype":"venue"
},
  "geometry": {"coordinates":[5.0949339867,50.6922492981],"type":"Point"}
}