{
  "type": "Feature",
  "properties": {
    "addr:full":"Geldmunt 60 Gent Oost-Vlaanderen 9000",
    "addr:housenumber":"60",
    "addr:postcode":"9000",
    "addr:street":"Geldmunt;Oost-Vlaanderen",
    "iso:country":"BE",
    "sg:address":"Geldmunt 60",
    "sg:city":"Gent",
    "sg:orig_category":"Pharmaciens",
    "sg:phone":"+32 9 225 95 62",
    "sg:postcode":"9000",
    "sg:province":"Oost-Vlaanderen",
    "wof:name":"Nathalie Ovaert",
    "wof:placetype":"venue"
},
  "geometry": {"coordinates":[3.7212760448,51.0577201843],"type":"Point"}
}