{
  "type": "Feature",
  "properties": {
    "addr:full":"Pollarestraat 52 Ninove Oost-Vlaanderen 9400",
    "addr:housenumber":"52",
    "addr:postcode":"9400",
    "addr:street":"Pollarestraat",
    "iso:country":"BE",
    "sg:address":"Pollarestraat 52",
    "sg:city":"Ninove",
    "sg:classifiers":[
        {
            "category":"Insurance",
            "subcategory":"Insurance Agent",
            "type":"Services"
        }
    ],
    "sg:phone":"+32 54 32 01 82",
    "sg:postcode":"9400",
    "sg:province":"Oost-Vlaanderen",
    "sg:tags":[
        "-",
        "representative"
    ],
    "wof:name":"Schoonjans G",
    "wof:placetype":"venue"
},
  "geometry": {"coordinates":[4.0227389336,50.8282051086],"type":"Point"}
}