{
  "type": "Feature",
  "properties": {
    "iso:country":"BE",
    "sg:address":"Leedsesteenweg 117",
    "sg:city":"Erpe-mere",
    "sg:orig_category":"V\u00e9hicules automobiles",
    "sg:phone":"+32 53 80 92 75",
    "sg:postcode":"9420",
    "sg:province":"Oost-Vlaanderen",
    "wof:name":"Autohandel Patrick",
    "wof:placetype":"venue"
},
  "geometry": {"coordinates":[3.9837460518,50.9500541687],"type":"Point"}
}