{
  "type": "Feature",
  "properties": {
    "iso:country":"BE",
    "sg:address":"Tervaetestraat 37",
    "sg:city":"Diksmuide",
    "sg:orig_category":"Eleveurs de bovins. Eleveurs and marchands de porcs",
    "sg:phone":"+32 51 50 09 48",
    "sg:postcode":"8600",
    "sg:province":"West-Vlaanderen",
    "wof:name":"Pol Colaert",
    "wof:placetype":"venue"
},
  "geometry": {"coordinates":[2.8554809093,51.0823936462],"type":"Point"}
}