{
  "type": "Feature",
  "properties": {
    "addr:full":"Runkstersteenweg 154 Hasselt Limburg 3500",
    "addr:housenumber":"154",
    "addr:postcode":"3500",
    "addr:street":"Runkstersteenweg",
    "iso:country":"BE",
    "sg:address":"Runkstersteenweg 154",
    "sg:city":"Hasselt",
    "sg:orig_category":"Pharmaciens",
    "sg:phone":"+32 11 27 01 06",
    "sg:postcode":"3500",
    "sg:province":"Limburg",
    "wof:name":"Apotheek De Voorzorg",
    "wof:placetype":"venue"
},
  "geometry": {"coordinates":[5.3257308006,50.9262313843],"type":"Point"}
}