{
  "type": "Feature",
  "properties": {
    "iso:country":"BE",
    "sg:address":"Warmestraat 50",
    "sg:city":"Maldegem",
    "sg:orig_category":"Varkenskwekers",
    "sg:phone":"+32 50 71 78 14",
    "sg:postcode":"9990",
    "sg:province":"Oost-Vlaanderen",
    "wof:name":"Pia Keirse",
    "wof:placetype":"venue"
},
  "geometry": {"coordinates":[3.4815759659,51.2147521973],"type":"Point"}
}