{
  "type": "Feature",
  "properties": {
    "iso:country":"BE",
    "sg:address":"Kapellensteenweg 255 Box 56",
    "sg:city":"Kalmthout",
    "sg:classifiers":[
        {
            "category":"Education",
            "subcategory":"Dance Studio",
            "type":"Public Place"
        }
    ],
    "sg:phone":"+32 3 666 56 90",
    "sg:postcode":"2920",
    "sg:province":"Antwerpen",
    "sg:tags":[
        "pallet"
    ],
    "wof:name":"Muller C-m",
    "wof:placetype":"venue"
},
  "geometry": {"coordinates":[4.4748120308,51.3780975342],"type":"Point"}
}