{
  "type": "Feature",
  "properties": {
    "addr:full":"Bukkersstraat 27 Ieper West-Vlaanderen 8900",
    "addr:housenumber":"27",
    "addr:postcode":"8900",
    "addr:street":"Bukkersstraat",
    "iso:country":"BE",
    "sg:address":"Bukkersstraat 27",
    "sg:city":"Ieper",
    "sg:classifiers":[
        {
            "category":"Real Estate",
            "subcategory":"Architect",
            "type":"Services"
        }
    ],
    "sg:phone":"+32 57 20 86 94",
    "sg:postcode":"8900",
    "sg:province":"West-Vlaanderen",
    "wof:name":"Verhaeghe P",
    "wof:placetype":"venue"
},
  "geometry": {"coordinates":[2.8907420635,50.8468055725],"type":"Point"}
}