{
  "type": "Feature",
  "properties": {
    "addr:full":"Hertogstraat 42 Leuven Vlaams-Brabant 3001",
    "addr:housenumber":"42",
    "addr:postcode":"3001",
    "addr:street":"Hertogstraat",
    "iso:country":"BE",
    "sg:address":"Hertogstraat 42",
    "sg:city":"Leuven",
    "sg:orig_category":"Traitement and fa\u00e7onnage de la pierre. Rev\u00eatements de sols and murs",
    "sg:phone":"+32 16 39 51 80",
    "sg:postcode":"3001",
    "sg:province":"Vlaams-Brabant",
    "wof:name":"Celis-willemans",
    "wof:placetype":"venue"
},
  "geometry": {"coordinates":[4.6928682327,50.8618392944],"type":"Point"}
}