{
  "type": "Feature",
  "properties": {
    "iso:country":"BE",
    "sg:address":"Wezenstraat 8bc",
    "sg:city":"Edingen/enghien",
    "sg:orig_category":"Installatie van houten of kunststof schrijnwerk",
    "sg:phone":"+32 2 395 58 60",
    "sg:postcode":"7850",
    "sg:province":"Hainaut",
    "wof:name":"Jean-louis Vincart",
    "wof:placetype":"venue"
},
  "geometry": {"coordinates":[4.0391898155,50.6954116821],"type":"Point"}
}