{
  "type": "Feature",
  "properties": {
    "addr:full":"Rue Sous L'haye 16 La Louvi\u00e8re (haine-saint-pierre) Hainaut 7100",
    "addr:housenumber":"16",
    "addr:postcode":"7100",
    "addr:street":"Rue Sous L'Haye",
    "iso:country":"BE",
    "sg:address":"Rue Sous L'haye 16",
    "sg:city":"La Louvi\u00e8re (haine-saint-pierre)",
    "sg:classifiers":[
        {
            "category":"Communications",
            "subcategory":"Film & Video Production",
            "type":"Services"
        }
    ],
    "sg:phone":"+32 64 21 38 94",
    "sg:postcode":"7100",
    "sg:province":"Hainaut",
    "sg:tags":[
        "sound",
        "recording",
        "studio"
    ],
    "wof:name":"E.g.s.",
    "wof:placetype":"venue"
},
  "geometry": {"coordinates":[4.2267169952,50.4771957397],"type":"Point"}
}