{
  "type": "Feature",
  "properties": {
    "iso:country":"BE",
    "sg:address":"Vroonbaan 80",
    "sg:city":"Kapelle-op-den-bos",
    "sg:orig_category":"Producteurs de l\u00e9gumes",
    "sg:phone":"+32 15 71 21 02",
    "sg:postcode":"1880",
    "sg:province":"Vlaams-Brabant",
    "wof:name":"Daniel De Prins",
    "wof:placetype":"venue"
},
  "geometry": {"coordinates":[4.3623890877,50.9855270386],"type":"Point"}
}