{
  "type": "Feature",
  "properties": {
    "iso:country":"BE",
    "sg:address":"R. Vander Bruggenlaan 28",
    "sg:city":"Anderlecht",
    "sg:orig_category":"Supermarkten",
    "sg:phone":"+32 2 522 10 40",
    "sg:postcode":"1070",
    "sg:province":"Bruxelles-Capitale",
    "wof:name":"Colruyt",
    "wof:placetype":"venue"
},
  "geometry": {"coordinates":[4.3157281876,50.8372039795],"type":"Point"}
}