{
  "type": "Feature",
  "properties": {
    "addr:full":"Rue Tienne-galop 23 Chastre Brabant Wallon 1450",
    "addr:housenumber":"23",
    "addr:postcode":"1450",
    "addr:street":"Rue Tienne-Galop",
    "iso:country":"BE",
    "sg:address":"Rue Tienne-galop 23",
    "sg:city":"Chastre",
    "sg:orig_category":"Boekhouders",
    "sg:phone":"+32 10 65 09 30",
    "sg:postcode":"1450",
    "sg:province":"Brabant Wallon",
    "wof:name":"J.p. Dewaele",
    "wof:placetype":"venue"
},
  "geometry": {"coordinates":[4.6430082321,50.6159324646],"type":"Point"}
}