{
  "type": "Feature",
  "properties": {
    "iso:country":"BE",
    "sg:address":"Hogebrug 28",
    "sg:city":"Lebbeke",
    "sg:orig_category":"Bouwmaterialen Gh Installatie van houten of kunststof schrijnwerk MEUBELONTWERP AND -INSTALLATIE Meu",
    "sg:phone":"+32 52 21 19 06",
    "sg:postcode":"9280",
    "sg:province":"Oost-Vlaanderen",
    "wof:name":"Meubelen Moernaut",
    "wof:placetype":"venue"
},
  "geometry": {"coordinates":[4.1456890106,50.9956703186],"type":"Point"}
}