{
  "type": "Feature",
  "properties": {
    "addr:full":"Avenue De La Paix 18 Rixensart Brabant Wallon 1330",
    "addr:housenumber":"18",
    "addr:postcode":"1330",
    "addr:street":"Avenue De La Paix;Wallon",
    "iso:country":"BE",
    "sg:address":"Avenue De La Paix 18",
    "sg:city":"Rixensart",
    "sg:classifiers":[
        {
            "category":"Professional",
            "subcategory":"Lawyer & Legal Services",
            "type":"Services"
        }
    ],
    "sg:phone":"+32 2 653 45 45",
    "sg:postcode":"1330",
    "sg:province":"Brabant Wallon",
    "wof:name":"Descamps Thomas",
    "wof:placetype":"venue"
},
  "geometry": {"coordinates":[4.5346479416,50.7117652893],"type":"Point"}
}