{
  "type": "Feature",
  "properties": {
    "addr:full":"Leugenberg 181 Antwerpen Antwerpen 2180",
    "addr:housenumber":"181",
    "addr:postcode":"2180",
    "addr:street":"Leugenberg",
    "iso:country":"BE",
    "sg:address":"Leugenberg 181",
    "sg:city":"Antwerpen",
    "sg:orig_category":"Dierenartsen",
    "sg:phone":"+32 3 605 36 30",
    "sg:postcode":"2180",
    "sg:province":"Antwerpen",
    "wof:name":"Paul Wijnen",
    "wof:placetype":"venue"
},
  "geometry": {"coordinates":[4.410490036,51.3021583557],"type":"Point"}
}