{
  "type": "Feature",
  "properties": {
    "addr:full":"Rue Pont \u00e0 Nole 110 Charleroi (mont-sur-marchienne) Hainaut 6032",
    "addr:housenumber":"110",
    "addr:postcode":"6032",
    "addr:street":"Rue Pont A\u0300 Nole",
    "iso:country":"BE",
    "sg:address":"Rue Pont \u00e0 Nole 110",
    "sg:city":"Charleroi (mont-sur-marchienne)",
    "sg:classifiers":[
        {
            "category":"Airport",
            "subcategory":"General Aviation",
            "type":"Transportation"
        }
    ],
    "sg:phone":"+32 71 47 15 13",
    "sg:postcode":"6032",
    "sg:province":"Hainaut",
    "sg:tags":[
        "transport"
    ],
    "wof:name":"Bourgeois-airport Service",
    "wof:placetype":"venue"
},
  "geometry": {"coordinates":[4.3953790665,50.3848686218],"type":"Point"}
}