{
  "type": "Feature",
  "properties": {
    "iso:country":"BE",
    "sg:address":"Chaus\u00c9e D'aalbeke 248",
    "sg:city":"Moeskroen",
    "sg:orig_category":"Souvenirs and objets artisanaux",
    "sg:phone":"+32 56 33 13 61",
    "sg:postcode":"7700",
    "sg:province":"Hainaut",
    "wof:name":"Artcre - Gros",
    "wof:placetype":"venue"
},
  "geometry": {"coordinates":[3.2223639488,50.7573432922],"type":"Point"}
}