{
  "type": "Feature",
  "properties": {
    "addr:full":"Holstraat 3 Londerzeel (malderen) Vlaams-Brabant 1840",
    "addr:housenumber":"3",
    "addr:postcode":"1840",
    "addr:street":"Holstraat",
    "iso:country":"BE",
    "sg:address":"Holstraat 3",
    "sg:city":"Londerzeel (malderen)",
    "sg:classifiers":[
        {
            "category":"Health Services",
            "subcategory":"Dentist",
            "type":"Services"
        }
    ],
    "sg:phone":"+32 52 33 25 77",
    "sg:postcode":"1840",
    "sg:province":"Vlaams-Brabant",
    "wof:name":"Heymans M",
    "wof:placetype":"venue"
},
  "geometry": {"coordinates":[4.2381072044,51.0158882141],"type":"Point"}
}