{
  "type": "Feature",
  "properties": {
    "addr:full":"Rue En Bois 248 Herstal Li\u00e8ge 4040",
    "addr:housenumber":"248",
    "addr:postcode":"4040",
    "addr:street":"Rue En Bois",
    "iso:country":"BE",
    "sg:address":"Rue En Bois 248",
    "sg:city":"Herstal",
    "sg:classifiers":[
        {
            "category":"Personal",
            "subcategory":"Beauty Salon",
            "type":"Services"
        }
    ],
    "sg:phone":"+32 4 264 12 96",
    "sg:postcode":"4040",
    "sg:province":"Li\u00e8ge",
    "sg:tags":[
        "de",
        "coiffure"
    ],
    "wof:name":"Jenny Cox Benaets Matray",
    "wof:placetype":"venue"
},
  "geometry": {"coordinates":[5.6354579926,50.6834220886],"type":"Point"}
}