{
  "type": "Feature",
  "properties": {
    "addr:full":"Ambachtstr 19 Tessenderlo Limburg 3980",
    "addr:housenumber":"19",
    "addr:postcode":"3980",
    "addr:street":"Ambachtstr",
    "iso:country":"BE",
    "sg:address":"Ambachtstr 19",
    "sg:city":"Tessenderlo",
    "sg:classifiers":[
        {
            "category":"Autos & Motor Vehicles",
            "subcategory":"Automobile Sales",
            "type":"Retail Goods"
        }
    ],
    "sg:phone":"+32 13 67 36 00",
    "sg:postcode":"3980",
    "sg:province":"Limburg",
    "sg:tags":[
        "equipment",
        "transport"
    ],
    "wof:name":"Race-productions Nv",
    "wof:placetype":"venue"
},
  "geometry": {"coordinates":[5.1516180038,51.0760917664],"type":"Point"}
}