{
  "type": "Feature",
  "properties": {
    "addr:full":"March\u00e9 Au B\u00e9tail 20 Renaix Oost-Vlaanderen 9600",
    "addr:housenumber":"20",
    "addr:postcode":"9600",
    "addr:street":"Renaix Oost-Vlaanderen",
    "iso:country":"BE",
    "sg:address":"March\u00e9 Au B\u00e9tail 20",
    "sg:city":"Renaix",
    "sg:classifiers":[
        {
            "category":"Banks & Credit Unions",
            "subcategory":"Investment Brokerage",
            "type":"Services"
        }
    ],
    "sg:phone":"+32 55 21 14 14",
    "sg:postcode":"9600",
    "sg:province":"Oost-Vlaanderen",
    "sg:tags":[
        "repair",
        "-",
        "installation",
        "sanitary",
        "article"
    ],
    "wof:name":"Blomme-vanderswalm",
    "wof:placetype":"venue"
},
  "geometry": {"coordinates":[3.6046319008,50.749294281],"type":"Point"}
}