{
  "type": "Feature",
  "properties": {
    "iso:country":"BE",
    "sg:address":"Rue Des Laids Bideaux 26",
    "sg:city":"Bertrix (orgeo)",
    "sg:classifiers":[
        {
            "category":"Farming",
            "subcategory":"Livestock Farm",
            "type":"Manufacturing & Wholesale Goods"
        }
    ],
    "sg:phone":"+32 61 41 16 72",
    "sg:postcode":"6880",
    "sg:province":"Luxembourg",
    "sg:tags":[
        "buyer"
    ],
    "wof:name":"Mernier R",
    "wof:placetype":"venue"
},
  "geometry": {"coordinates":[5.3387699127,49.8485603333],"type":"Point"}
}