{
  "type": "Feature",
  "properties": {
    "addr:full":"Rue Du Chemin Vert 35 Charleroi Hainaut 6001",
    "addr:housenumber":"35",
    "addr:postcode":"6001",
    "addr:street":"Rue Du Chemin Vert;Hainaut",
    "iso:country":"BE",
    "sg:address":"Rue Du Chemin Vert 35",
    "sg:city":"Charleroi",
    "sg:orig_category":"Editeurs de journaux. Editeurs de revues and p\u00e9riodiques",
    "sg:phone":"+32 71 43 85 72",
    "sg:postcode":"6001",
    "sg:province":"Hainaut",
    "wof:name":"Ado-livres",
    "wof:placetype":"venue"
},
  "geometry": {"coordinates":[4.4389281273,50.3903312683],"type":"Point"}
}