{
  "type": "Feature",
  "properties": {
    "addr:full":"Dr\u00c8ve Richelle 167 Waterloo Brabant Wallon 1410",
    "addr:housenumber":"167",
    "addr:postcode":"1410",
    "addr:street":"Dre\u0300Ve Richelle",
    "iso:country":"BE",
    "sg:address":"Dr\u00c8ve Richelle 167",
    "sg:city":"Waterloo",
    "sg:orig_category":"Plaatsen van vloer- and muurbekleding Pleisterwerk Schilders Verhuur diversen",
    "sg:phone":"+32 2 354 23 56",
    "sg:postcode":"1410",
    "sg:province":"Brabant Wallon",
    "wof:name":"Landscape Designers Y.d.",
    "wof:placetype":"venue"
},
  "geometry": {"coordinates":[4.4116549492,50.7070922852],"type":"Point"}
}