{
  "type": "Feature",
  "properties": {
    "iso:country":"BE",
    "sg:address":"Baan 33",
    "sg:city":"Lille (poederlee)",
    "sg:classifiers":[
        {
            "category":"Real Estate",
            "subcategory":"Architect",
            "type":"Services"
        }
    ],
    "sg:phone":"+32 14 88 06 58",
    "sg:postcode":"2275",
    "sg:province":"Antwerpen",
    "wof:name":"Sas E",
    "wof:placetype":"venue"
},
  "geometry": {"coordinates":[4.840400219,51.2353782654],"type":"Point"}
}