{
  "type": "Feature",
  "properties": {
    "addr:full":"Rue Pav\u00c9 Du Gosson 294 Saint-nicolas Li\u00e8ge 4420",
    "addr:housenumber":"294",
    "addr:postcode":"4420",
    "addr:street":"Rue Pave\u0301 Du Gosson;Saint-Nicolas Lie\u0300Ge",
    "iso:country":"BE",
    "sg:address":"Rue Pav\u00c9 Du Gosson 294",
    "sg:city":"Saint-nicolas",
    "sg:orig_category":"Epiceries",
    "sg:phone":"+32 4 226 42 92",
    "sg:postcode":"4420",
    "sg:province":"Li\u00e8ge",
    "wof:name":"Petrella",
    "wof:placetype":"venue"
},
  "geometry": {"coordinates":[5.5257248878,50.6354827881],"type":"Point"}
}