{
  "type": "Feature",
  "properties": {
    "addr:full":"Pasteur 33 Charleroi Hainaut 6032",
    "addr:housenumber":"33",
    "addr:postcode":"6032",
    "addr:street":"Pasteur;Hainaut",
    "iso:country":"BE",
    "sg:address":"Pasteur 33",
    "sg:city":"Charleroi",
    "sg:orig_category":"Instituts de beaut\u00e9. M\u00e9decines alternatives. Centres de relaxation and bien-\u00eatre",
    "sg:phone":"+32 71 43 26 41",
    "sg:postcode":"6032",
    "sg:province":"Hainaut",
    "wof:name":"Institut Silhouette",
    "wof:placetype":"venue"
},
  "geometry": {"coordinates":[4.4100961685,50.3890075684],"type":"Point"}
}