{
  "type": "Feature",
  "properties": {
    "iso:country":"BE",
    "sg:address":"Antwerpsestraat 34b4",
    "sg:city":"Boom",
    "sg:classifiers":[
        {
            "category":"Arena",
            "subcategory":"Sports Club",
            "type":"Entertainment"
        }
    ],
    "sg:phone":"+32 3 888 31 64",
    "sg:postcode":"2850",
    "sg:province":"Antwerpen",
    "sg:tags":[
        "terrain",
        "hors",
        "de",
        "installation",
        "sportifs"
    ],
    "wof:name":"K. Rupel-boom F.c.",
    "wof:placetype":"venue"
},
  "geometry": {"coordinates":[4.3660101891,51.0872535706],"type":"Point"}
}