{
  "type": "Feature",
  "properties": {
    "addr:full":"Avenue De L'observatoire 278 Li\u00c8ge Li\u00e8ge 4000",
    "addr:housenumber":"278",
    "addr:postcode":"4000",
    "addr:street":"Avenue De L'Observatoire",
    "iso:country":"BE",
    "sg:address":"Avenue De L'observatoire 278",
    "sg:city":"Li\u00c8ge",
    "sg:orig_category":"Banques and organismes de cr\u00e9dit",
    "sg:phone":"+32 4 252 33 45",
    "sg:postcode":"4000",
    "sg:province":"Li\u00e8ge",
    "wof:name":"Fortis",
    "wof:placetype":"venue"
},
  "geometry": {"coordinates":[5.5649089813,50.6202926636],"type":"Point"}
}