{
  "type": "Feature",
  "properties": {
    "addr:full":"Molenbaan 125 Kalmthout Antwerpen 2920",
    "addr:housenumber":"125",
    "addr:postcode":"2920",
    "addr:street":"Molenbaan",
    "iso:country":"BE",
    "sg:address":"Molenbaan 125",
    "sg:city":"Kalmthout",
    "sg:orig_category":"Tuinbenodigdheden",
    "sg:phone":"+32 3 666 84 08",
    "sg:postcode":"2920",
    "sg:province":"Antwerpen",
    "wof:name":"Briton",
    "wof:placetype":"venue"
},
  "geometry": {"coordinates":[4.4860949516,51.3710784912],"type":"Point"}
}