{
  "type": "Feature",
  "properties": {
    "addr:full":"Veldstraat 8 Eeklo Oost-Vlaanderen 9900",
    "addr:housenumber":"8",
    "addr:postcode":"9900",
    "addr:street":"Veldstraat",
    "iso:country":"BE",
    "sg:address":"Veldstraat 8",
    "sg:city":"Eeklo",
    "sg:classifiers":[
        {
            "category":"Building & Trades",
            "subcategory":"Pest Control",
            "type":"Services"
        }
    ],
    "sg:phone":"+32 9 377 81 81",
    "sg:postcode":"9900",
    "sg:province":"Oost-Vlaanderen",
    "sg:tags":[
        "painting",
        "contractor"
    ],
    "wof:name":"De Sutter G",
    "wof:placetype":"venue"
},
  "geometry": {"coordinates":[3.5867381096,51.1838989258],"type":"Point"}
}