{
  "type": "Feature",
  "properties": {
    "iso:country":"BE",
    "sg:address":"Bruggesteenweg 13",
    "sg:city":"Hooglede (gits)",
    "sg:classifiers":[
        {
            "category":"Farming",
            "subcategory":"Livestock Farm",
            "type":"Manufacturing & Wholesale Goods"
        }
    ],
    "sg:phone":"+32 51 72 21 44",
    "sg:postcode":"8830",
    "sg:province":"West-Vlaanderen",
    "sg:tags":[
        "buyer"
    ],
    "wof:name":"Gardin R",
    "wof:placetype":"venue"
},
  "geometry": {"coordinates":[3.083687067,50.9790687561],"type":"Point"}
}