{
  "type": "Feature",
  "properties": {
    "addr:full":"Rue De Toernich 25 Messancy (wolkrange) Luxembourg 6780",
    "addr:housenumber":"25",
    "addr:postcode":"6780",
    "addr:street":"Rue De Toernich",
    "iso:country":"BE",
    "sg:address":"Rue De Toernich 25",
    "sg:city":"Messancy (wolkrange)",
    "sg:classifiers":[
        {
            "category":"Health Services",
            "subcategory":"Doctor",
            "type":"Services"
        }
    ],
    "sg:phone":"+32 63 23 95 35",
    "sg:postcode":"6780",
    "sg:province":"Luxembourg",
    "sg:tags":[
        "medicinephysicians",
        "surgeon"
    ],
    "wof:name":"Marchand B",
    "wof:placetype":"venue"
},
  "geometry": {"coordinates":[5.8153700829,49.5921859741],"type":"Point"}
}