{
  "type": "Feature",
  "properties": {
    "iso:country":"BE",
    "sg:address":"Rue Chavannes 16",
    "sg:city":"Charleroi",
    "sg:classifiers":[
        {
            "category":"Restaurant",
            "type":"Food & Drink"
        }
    ],
    "sg:phone":"+32 71 30 96 00",
    "sg:postcode":"6000",
    "sg:province":"Hainaut",
    "wof:name":"Sole Mio",
    "wof:placetype":"venue"
},
  "geometry": {"coordinates":[4.4447321892,50.4139137268],"type":"Point"}
}