{
  "type": "Feature",
  "properties": {
    "iso:country":"BE",
    "sg:address":"Place Verte 28c",
    "sg:city":"Florennes",
    "sg:orig_category":"Ordinateurs and \u00e9quipement informatique. Mat\u00e9riel de T\u00e9l\u00e9communication. Electrom\u00e9nager, t\u00e9l\u00e9visions ",
    "sg:phone":"+32 71 68 71 57",
    "sg:postcode":"5620",
    "sg:province":"Namur",
    "wof:name":"Technodel Sprl.",
    "wof:placetype":"venue"
},
  "geometry": {"coordinates":[4.6053462029,50.2500686646],"type":"Point"}
}