{
  "type": "Feature",
  "properties": {
    "addr:full":"Kortrijksestraat 295 Izegem West-Vlaanderen 8870",
    "addr:housenumber":"295",
    "addr:postcode":"8870",
    "addr:street":"Kortrijksestraat",
    "iso:country":"BE",
    "sg:address":"Kortrijksestraat 295",
    "sg:city":"Izegem",
    "sg:orig_category":"Messageries",
    "sg:phone":"+32 51 31 24 51",
    "sg:postcode":"8870",
    "sg:province":"West-Vlaanderen",
    "wof:name":"Transport Jonak",
    "wof:placetype":"venue"
},
  "geometry": {"coordinates":[3.2204420567,50.9073562622],"type":"Point"}
}