{
  "type": "Feature",
  "properties": {
    "iso:country":"BE",
    "sg:address":"Knesselarestraat 99",
    "sg:city":"Beernem",
    "sg:classifiers":[
        {
            "category":"Personal",
            "subcategory":"Beauty Salon",
            "type":"Services"
        }
    ],
    "sg:phone":"+32 50 78 91 74",
    "sg:postcode":"8730",
    "sg:province":"West-Vlaanderen",
    "sg:tags":[
        "de",
        "coiffure"
    ],
    "wof:name":"Coiffure Rose-anne",
    "wof:placetype":"venue"
},
  "geometry": {"coordinates":[3.3503069878,51.1674575806],"type":"Point"}
}