{
  "type": "Feature",
  "properties": {
    "addr:full":"Chauss\u00c9e D'audenarde 46 Pecq Hainaut 7742",
    "addr:housenumber":"46",
    "addr:postcode":"7742",
    "addr:street":"Chausse\u0301E D'Audenarde",
    "iso:country":"BE",
    "sg:address":"Chauss\u00c9e D'audenarde 46",
    "sg:city":"Pecq",
    "sg:orig_category":"Beautyfarms, relaxatie and lichamelijk welzijn Schoonheidssalons",
    "sg:phone":"+32 69 55 71 57",
    "sg:postcode":"7742",
    "sg:province":"Hainaut",
    "wof:name":"Institut Belle Star",
    "wof:placetype":"venue"
},
  "geometry": {"coordinates":[3.3586440086,50.6781234741],"type":"Point"}
}