{
  "type": "Feature",
  "properties": {
    "iso:country":"BE",
    "sg:address":"Adriaan Brouwerstraat 81",
    "sg:city":"Schoten",
    "sg:orig_category":"Parfumeries",
    "sg:phone":"+32 3 646 06 01",
    "sg:postcode":"2900",
    "sg:province":"Antwerpen",
    "wof:name":"Christiane Vanderheyden",
    "wof:placetype":"venue"
},
  "geometry": {"coordinates":[4.4805841446,51.2437858582],"type":"Point"}
}