{
  "type": "Feature",
  "properties": {
    "addr:full":"Jakob Vandervaetstraat 156 Kortrijk West-Vlaanderen 8500",
    "addr:housenumber":"156",
    "addr:postcode":"8500",
    "addr:street":"Jakob Vandervaetstraat",
    "iso:country":"BE",
    "sg:address":"Jakob Vandervaetstraat 156",
    "sg:city":"Kortrijk",
    "sg:orig_category":"Installation de menuiserie m\u00e9tallique",
    "sg:phone":"+32 56 37 24 95",
    "sg:postcode":"8500",
    "sg:province":"West-Vlaanderen",
    "wof:name":"Luc Labaere",
    "wof:placetype":"venue"
},
  "geometry": {"coordinates":[3.2553238869,50.8348388672],"type":"Point"}
}