{
  "type": "Feature",
  "properties": {
    "iso:country":"BE",
    "sg:address":"Avenue Brugmann 185",
    "sg:city":"Bruxelles (forest)",
    "sg:classifiers":[
        {
            "category":"Building & Trades",
            "subcategory":"Landscaping Services",
            "type":"Services"
        }
    ],
    "sg:phone":"+32 2 347 04 31",
    "sg:postcode":"1190",
    "sg:province":"Bruxelles-Capitale",
    "sg:tags":[
        "architect",
        "landscape"
    ],
    "wof:name":"Belgium Association Of Garden And Landscape Architects-bvtl-abajp",
    "wof:placetype":"venue"
},
  "geometry": {"coordinates":[4.3494839668,50.816444397],"type":"Point"}
}