{
  "type": "Feature",
  "properties": {
    "iso:country":"BE",
    "sg:address":"Brusselsesteenweg 305",
    "sg:city":"Mechelen",
    "sg:orig_category":"Pr\u00eats hypoth\u00e9caires and cr\u00e9dits immobiliers",
    "sg:phone":"+32 15 43 50 49",
    "sg:postcode":"2800",
    "sg:province":"Antwerpen",
    "wof:name":"Advisa",
    "wof:placetype":"venue"
},
  "geometry": {"coordinates":[4.4746699333,51.0077896118],"type":"Point"}
}