{
  "type": "Feature",
  "properties": {
    "iso:country":"BE",
    "sg:address":"Place Saint-etienne 2ba",
    "sg:city":"Habay",
    "sg:orig_category":"Enseignement maternel and primaire",
    "sg:phone":"+32 63 42 31 21",
    "sg:postcode":"6723",
    "sg:province":"Luxembourg",
    "wof:name":"Ecole Fond. Communale",
    "wof:placetype":"venue"
},
  "geometry": {"coordinates":[5.6187200546,49.7232704163],"type":"Point"}
}