{
  "type": "Feature",
  "properties": {
    "iso:country":"BE",
    "sg:address":"Route De Lessines 12",
    "sg:city":"Frasnes-lez-anvaing (frasnes - Lez - Buissenal)",
    "sg:classifiers":[
        {
            "category":"Health Services",
            "subcategory":"Dentist",
            "type":"Services"
        }
    ],
    "sg:phone":"+32 69 86 76 45",
    "sg:postcode":"7911",
    "sg:province":"Hainaut",
    "wof:name":"Corbisier-baland Guy",
    "wof:placetype":"venue"
},
  "geometry": {"coordinates":[3.6259319782,50.6700973511],"type":"Point"}
}