{
  "type": "Feature",
  "properties": {
    "addr:full":"Kerkdreef 8 Waregem West-Vlaanderen 8791",
    "addr:housenumber":"8",
    "addr:postcode":"8791",
    "addr:street":"Kerkdreef",
    "iso:country":"BE",
    "sg:address":"Kerkdreef 8",
    "sg:city":"Waregem",
    "sg:orig_category":"S\u00e9curit\u00e9 sociale",
    "sg:phone":"+32 56 62 71 71",
    "sg:postcode":"8791",
    "sg:province":"West-Vlaanderen",
    "wof:name":"Christelijke Mutualiteit",
    "wof:placetype":"venue"
},
  "geometry": {"coordinates":[3.3459460735,50.874671936],"type":"Point"}
}