{
  "type": "Feature",
  "properties": {
    "addr:full":"Rue C\u00e9lestin Demblon 152 Herstal Li\u00e8ge 4040",
    "addr:housenumber":"152",
    "addr:postcode":"4040",
    "addr:street":"Rue Ce\u0301Lestin Demblon",
    "iso:country":"BE",
    "sg:address":"Rue C\u00e9lestin Demblon 152",
    "sg:city":"Herstal",
    "sg:classifiers":[
        {
            "category":"Freight",
            "type":"Transportation"
        }
    ],
    "sg:phone":"+32 4 240 27 27",
    "sg:postcode":"4040",
    "sg:province":"Li\u00e8ge",
    "sg:tags":[
        "express",
        "transport"
    ],
    "wof:name":"European Services Express Sprl",
    "wof:placetype":"venue"
},
  "geometry": {"coordinates":[5.63164711,50.6752586365],"type":"Point"}
}