{
  "type": "Feature",
  "properties": {
    "iso:country":"BE",
    "sg:address":"In De Bus 14",
    "sg:city":"Ham (grand)",
    "sg:orig_category":"Loodgieterij, verwarming and sanitaire installaties",
    "sg:phone":"+32 11 34 54 35",
    "sg:postcode":"3945",
    "sg:province":"Limburg",
    "wof:name":"Vama-c",
    "wof:placetype":"venue"
},
  "geometry": {"coordinates":[5.198996067,51.1082038879],"type":"Point"}
}