{
  "type": "Feature",
  "properties": {
    "addr:full":"Rue Fulton 16 Bruxelles Bruxelles-Capitale 1000",
    "addr:housenumber":"16",
    "addr:postcode":"1000",
    "addr:street":"Rue Fulton",
    "iso:country":"BE",
    "sg:address":"Rue Fulton 16",
    "sg:city":"Bruxelles",
    "sg:classifiers":[
        {
            "category":"Health Services",
            "subcategory":"Doctor",
            "type":"Services"
        }
    ],
    "sg:phone":"+32 2 736 95 04",
    "sg:postcode":"1000",
    "sg:province":"Bruxelles-Capitale",
    "sg:tags":[
        "medicinephysicians",
        "surgeon"
    ],
    "wof:name":"Godet J-l",
    "wof:placetype":"venue"
},
  "geometry": {"coordinates":[4.3912949562,50.8458251953],"type":"Point"}
}