{
  "type": "Feature",
  "properties": {
    "addr:full":"Vichtesteenweg 72 Deerlijk West-Vlaanderen 8540",
    "addr:housenumber":"72",
    "addr:postcode":"8540",
    "addr:street":"Vichtesteenweg",
    "iso:country":"BE",
    "sg:address":"Vichtesteenweg 72",
    "sg:city":"Deerlijk",
    "sg:orig_category":"Benzinestations and brandstoffen",
    "sg:phone":"+32 56 77 82 62",
    "sg:postcode":"8540",
    "sg:province":"West-Vlaanderen",
    "wof:name":"Texaco",
    "wof:placetype":"venue"
},
  "geometry": {"coordinates":[3.3657450676,50.8507423401],"type":"Point"}
}