{
  "type": "Feature",
  "properties": {
    "addr:full":"Rue Gontran Bachy 32 Mons Hainaut 7032",
    "addr:housenumber":"32",
    "addr:postcode":"7032",
    "addr:street":"Rue Gontran Bachy;Hainaut",
    "iso:country":"BE",
    "sg:address":"Rue Gontran Bachy 32",
    "sg:city":"Mons",
    "sg:orig_category":"Paramedische behandelingen",
    "sg:phone":"+32 65 31 18 70",
    "sg:postcode":"7032",
    "sg:province":"Hainaut",
    "wof:name":"M. Duby",
    "wof:placetype":"venue"
},
  "geometry": {"coordinates":[3.9869709015,50.4255142212],"type":"Point"}
}