{
  "type": "Feature",
  "properties": {
    "addr:full":"Rue Vieille 13 Beauraing Namur 5570",
    "addr:housenumber":"13",
    "addr:postcode":"5570",
    "addr:street":"Rue Vieille",
    "iso:country":"BE",
    "sg:address":"Rue Vieille 13",
    "sg:city":"Beauraing",
    "sg:orig_category":"Peinture. Rev\u00eatements pour sols and murs",
    "sg:phone":"+32 82 71 23 31",
    "sg:postcode":"5570",
    "sg:province":"Namur",
    "wof:name":"Baronville Design",
    "wof:placetype":"venue"
},
  "geometry": {"coordinates":[4.9492177963,50.1247901917],"type":"Point"}
}