{
  "type": "Feature",
  "properties": {
    "addr:full":"Frans Nensstraat 5 Leuven Vlaams-Brabant 3000",
    "addr:housenumber":"5",
    "addr:postcode":"3000",
    "addr:street":"Frans Nensstraat",
    "iso:country":"BE",
    "sg:address":"Frans Nensstraat 5",
    "sg:city":"Leuven",
    "sg:classifiers":[
        {
            "category":"Professional",
            "subcategory":"Computer Services",
            "type":"Services"
        }
    ],
    "sg:phone":"+32 16 29 36 11",
    "sg:postcode":"3000",
    "sg:province":"Vlaams-Brabant",
    "sg:tags":[
        "-",
        "processing",
        "data",
        "software"
    ],
    "wof:name":"Four'sys Nv",
    "wof:placetype":"venue"
},
  "geometry": {"coordinates":[4.702434063,50.8715133667],"type":"Point"}
}