{
  "type": "Feature",
  "properties": {
    "addr:full":"Grunselborrestraat 1 Galmaarden Vlaams-Brabant 1570",
    "addr:housenumber":"1",
    "addr:postcode":"1570",
    "addr:street":"Grunselborrestraat",
    "iso:country":"BE",
    "sg:address":"Grunselborrestraat 1",
    "sg:city":"Galmaarden",
    "sg:orig_category":"Eleveurs de bovins",
    "sg:phone":"+32 54 58 85 31",
    "sg:postcode":"1570",
    "sg:province":"Vlaams-Brabant",
    "wof:name":"Theophile Bombaert",
    "wof:placetype":"venue"
},
  "geometry": {"coordinates":[3.9949140549,50.765663147],"type":"Point"}
}