{
  "type": "Feature",
  "properties": {
    "addr:full":"Grand\u00b4route 158 Braine-l\u00b4alleud Brabant Wallon 1428",
    "addr:housenumber":"158",
    "addr:postcode":"1428",
    "addr:street":"Braine-L\u00b4Alleud Brabant Wallon",
    "iso:country":"BE",
    "sg:address":"Grand\u00b4route 158",
    "sg:city":"Braine-l\u00b4alleud",
    "sg:classifiers":[
        {
            "category":"Insurance",
            "subcategory":"Life Insurance",
            "type":"Services"
        }
    ],
    "sg:phone":"+32 2 387 48 61",
    "sg:postcode":"1428",
    "sg:province":"Brabant Wallon",
    "sg:tags":[
        "assurance"
    ],
    "wof:name":"Bureau Gilbert",
    "wof:placetype":"venue"
},
  "geometry": {"coordinates":[4.3644099236,50.6426200867],"type":"Point"}
}