{
  "type": "Feature",
  "properties": {
    "iso:country":"BE",
    "sg:address":"Basculestraat 11",
    "sg:city":"Ieper",
    "sg:orig_category":"Advocaten and juridische adviseurs",
    "sg:phone":"+32 57 20 27 35",
    "sg:postcode":"8900",
    "sg:province":"West-Vlaanderen",
    "wof:name":"Luc Vanryckeghem",
    "wof:placetype":"venue"
},
  "geometry": {"coordinates":[2.8943560123,50.8535385132],"type":"Point"}
}