{
  "type": "Feature",
  "properties": {
    "addr:full":"Gemeenteplein 20 Box 4 Keerbergen Vlaams-Brabant 3140",
    "addr:housenumber":"20;4",
    "addr:postcode":"3140",
    "addr:street":"Gemeenteplein;Box",
    "iso:country":"BE",
    "sg:address":"Gemeenteplein 20 Box 4",
    "sg:city":"Keerbergen",
    "sg:classifiers":[
        {
            "category":"Professional",
            "subcategory":"Computer Services",
            "type":"Services"
        }
    ],
    "sg:phone":"+32 15 52 00 46",
    "sg:postcode":"3140",
    "sg:province":"Vlaams-Brabant",
    "sg:tags":[
        "-",
        "processing",
        "data"
    ],
    "wof:name":"Mod Software Bvba",
    "wof:placetype":"venue"
},
  "geometry": {"coordinates":[4.6292519569,51.0027427673],"type":"Point"}
}