{
  "type": "Feature",
  "properties": {
    "addr:full":"Avenue Rogier 30a Li\u00c8ge Li\u00e8ge 4000",
    "addr:housenumber":"30a",
    "addr:postcode":"4000",
    "addr:street":"Avenue Rogier",
    "iso:country":"BE",
    "sg:address":"Avenue Rogier 30a",
    "sg:city":"Li\u00c8ge",
    "sg:orig_category":"Drukkerijen and copyshops",
    "sg:phone":"+32 4 252 77 25",
    "sg:postcode":"4000",
    "sg:province":"Li\u00e8ge",
    "wof:name":"Id\u00c9copy",
    "wof:placetype":"venue"
},
  "geometry": {"coordinates":[5.5693650246,50.6310958862],"type":"Point"}
}