{
  "type": "Feature",
  "properties": {
    "addr:full":"Avenue Des Marteleurs 59 Seraing Li\u00e8ge 4100",
    "addr:housenumber":"59",
    "addr:postcode":"4100",
    "addr:street":"Avenue Des Marteleurs",
    "iso:country":"BE",
    "sg:address":"Avenue Des Marteleurs 59",
    "sg:city":"Seraing",
    "sg:orig_category":"Peinture. Rev\u00eatements pour sols and murs",
    "sg:phone":"+32 4 337 01 38",
    "sg:postcode":"4100",
    "sg:province":"Li\u00e8ge",
    "wof:name":"Guy Meschke",
    "wof:placetype":"venue"
},
  "geometry": {"coordinates":[5.4810647964,50.5822601318],"type":"Point"}
}