{
  "type": "Feature",
  "properties": {
    "iso:country":"BE",
    "sg:address":"Victor Nonnemanstraat 4",
    "sg:city":"Sint-pieters-leeuw",
    "sg:classifiers":[
        {
            "category":"Professional",
            "subcategory":"Accounting & Tax Preparation",
            "type":"Services"
        }
    ],
    "sg:phone":"+32 2 377 74 43",
    "sg:postcode":"1600",
    "sg:province":"Vlaams-Brabant",
    "sg:tags":[
        "accountant"
    ],
    "wof:name":"Christian Collignon",
    "wof:placetype":"venue"
},
  "geometry": {"coordinates":[4.2448430061,50.781539917],"type":"Point"}
}