{
  "type": "Feature",
  "properties": {
    "iso:country":"BE",
    "sg:address":"Kerkdreef 1",
    "sg:city":"Waregem",
    "sg:orig_category":"Catering and organisatie van feesten Voedingsspeciaalzaken",
    "sg:phone":"+32 56 71 95 85",
    "sg:postcode":"8791",
    "sg:province":"West-Vlaanderen",
    "wof:name":"De Kokkerelle Traiteur",
    "wof:placetype":"venue"
},
  "geometry": {"coordinates":[3.3461060524,50.8740272522],"type":"Point"}
}