{
  "type": "Feature",
  "properties": {
    "addr:full":"Vaartstraat 87 Grimbergen Vlaams-Brabant 1850",
    "addr:housenumber":"87",
    "addr:postcode":"1850",
    "addr:street":"Vaartstraat",
    "iso:country":"BE",
    "sg:address":"Vaartstraat 87",
    "sg:city":"Grimbergen",
    "sg:classifiers":[
        {
            "category":"Cafe",
            "type":"Food & Drink"
        }
    ],
    "sg:phone":"+32 2 251 39 58",
    "sg:postcode":"1850",
    "sg:province":"Vlaams-Brabant",
    "sg:tags":[
        "caf\u00e9s"
    ],
    "wof:name":"Marie Van Herp",
    "wof:placetype":"venue"
},
  "geometry": {"coordinates":[4.4046897888,50.9456863403],"type":"Point"}
}