{
  "type": "Feature",
  "properties": {
    "iso:country":"BE",
    "sg:address":"Rue De La Taille Loquet 12",
    "sg:city":"Villers-la-ville",
    "sg:orig_category":"Artsen and specialisten",
    "sg:phone":"+32 71 87 75 98",
    "sg:postcode":"1495",
    "sg:province":"Brabant Wallon",
    "wof:name":"H\u00c9l\u00c8ne Dumont",
    "wof:placetype":"venue"
},
  "geometry": {"coordinates":[4.4881920815,50.5725402832],"type":"Point"}
}