{
  "type": "Feature",
  "properties": {
    "addr:full":"Koning Leopold Iii Plein Blankenberge West-Vlaanderen 8370",
    "addr:postcode":"8370",
    "addr:street":"Koning Leopold Iii Plein",
    "iso:country":"BE",
    "sg:address":"Koning Leopold Iii Plein",
    "sg:city":"Blankenberge",
    "sg:classifiers":[
        {
            "category":"Government",
            "subcategory":"Office",
            "type":"Public Place"
        }
    ],
    "sg:phone":"+32 50 41 22 27",
    "sg:postcode":"8370",
    "sg:province":"West-Vlaanderen",
    "sg:tags":[
        "-",
        "tourism",
        "federation"
    ],
    "wof:name":"Blankenberge Dienst Toerisme",
    "wof:placetype":"venue"
},
  "geometry": {"coordinates":[3.1322300434,51.3126335144],"type":"Point"}
}