{
  "type": "Feature",
  "properties": {
    "iso:country":"BE",
    "sg:address":"Ijzerenmolenstraat 105",
    "sg:city":"Leuven",
    "sg:orig_category":"Avocats and conseillers juridiques",
    "sg:phone":"+32 16 31 04 20",
    "sg:postcode":"3001",
    "sg:province":"Vlaams-Brabant",
    "wof:name":"G. De Doncker",
    "wof:placetype":"venue"
},
  "geometry": {"coordinates":[4.6817178726,50.8686637878],"type":"Point"}
}