{
  "type": "Feature",
  "properties": {
    "addr:full":"Rue Gridlet 78 Gedinne Namur 5575",
    "addr:housenumber":"78",
    "addr:postcode":"5575",
    "addr:street":"Rue Gridlet",
    "iso:country":"BE",
    "sg:address":"Rue Gridlet 78",
    "sg:city":"Gedinne",
    "sg:orig_category":"Traitement and fa\u00e7onnage de la pierre",
    "sg:phone":"+32 61 58 81 07",
    "sg:postcode":"5575",
    "sg:province":"Namur",
    "wof:name":"Delebel & Fils",
    "wof:placetype":"venue"
},
  "geometry": {"coordinates":[4.956389904,49.982673645],"type":"Point"}
}