{
  "type": "Feature",
  "properties": {
    "iso:country":"BE",
    "sg:address":"Karel Du Boislaan 3b2l",
    "sg:city":"Antwerpen",
    "sg:orig_category":"Sportclubs",
    "sg:phone":"+32 3 828 41 46",
    "sg:postcode":"2660",
    "sg:province":"Antwerpen",
    "wof:name":"K.c. Royal Mercurius",
    "wof:placetype":"venue"
},
  "geometry": {"coordinates":[4.4143791199,51.2287826538],"type":"Point"}
}