{
  "type": "Feature",
  "properties": {
    "addr:full":"Terhulpensesteenweg 172 Overijse Vlaams-Brabant 3090",
    "addr:housenumber":"172",
    "addr:postcode":"3090",
    "addr:street":"Terhulpensesteenweg",
    "iso:country":"BE",
    "sg:address":"Terhulpensesteenweg 172",
    "sg:city":"Overijse",
    "sg:orig_category":"Banques and organismes de cr\u00e9dit",
    "sg:phone":"+32 2 687 42 49",
    "sg:postcode":"3090",
    "sg:province":"Vlaams-Brabant",
    "wof:name":"Ippa",
    "wof:placetype":"venue"
},
  "geometry": {"coordinates":[4.5386300087,50.7634010315],"type":"Point"}
}