{
  "type": "Feature",
  "properties": {
    "iso:country":"BE",
    "sg:address":"Duffelsesteenweg 150-152",
    "sg:city":"Lint",
    "sg:classifiers":[
        {
            "category":"Retail",
            "subcategory":"Laundry & Dry Cleaning",
            "type":"Services"
        }
    ],
    "sg:phone":"+32 3 455 26 53",
    "sg:postcode":"2547",
    "sg:province":"Antwerpen",
    "sg:tags":[
        "dyer",
        "cleaner"
    ],
    "wof:name":"Herman Bvba",
    "wof:placetype":"venue"
},
  "geometry": {"coordinates":[4.4922528267,51.1220588684],"type":"Point"}
}