{
  "type": "Feature",
  "properties": {
    "addr:full":"Tempelhofstraat 16 Gistel West-Vlaanderen 8470",
    "addr:housenumber":"16",
    "addr:postcode":"8470",
    "addr:street":"Tempelhofstraat",
    "iso:country":"BE",
    "sg:address":"Tempelhofstraat 16",
    "sg:city":"Gistel",
    "sg:classifiers":[
        {
            "category":"Insurance",
            "subcategory":"Insurance Agent",
            "type":"Services"
        }
    ],
    "sg:phone":"+32 59 27 83 85",
    "sg:postcode":"8470",
    "sg:province":"West-Vlaanderen",
    "sg:tags":[
        "verzekeringsmakelaars",
        "expert"
    ],
    "wof:name":"Bureau Depuydt",
    "wof:placetype":"venue"
},
  "geometry": {"coordinates":[2.9618170261,51.1561126709],"type":"Point"}
}