{
  "type": "Feature",
  "properties": {
    "addr:full":"Rue Saint-laurent 45 Bassenge Li\u00e8ge 4690",
    "addr:housenumber":"45",
    "addr:postcode":"4690",
    "addr:street":"Rue Saint-Laurent",
    "iso:country":"BE",
    "sg:address":"Rue Saint-laurent 45",
    "sg:city":"Bassenge",
    "sg:orig_category":"Algemeen secundair onderwijs Kleuter- en basisonderwijs",
    "sg:phone":"+32 4 286 18 21",
    "sg:postcode":"4690",
    "sg:province":"Li\u00e8ge",
    "wof:name":"Ecole Fondamentale",
    "wof:placetype":"venue"
},
  "geometry": {"coordinates":[5.5425601006,50.7529792786],"type":"Point"}
}