{
  "type": "Feature",
  "properties": {
    "iso:country":"BE",
    "sg:address":"Lentestraat 4",
    "sg:city":"Meeuwen-gruitrode (meeuwen)",
    "sg:classifiers":[
        {
            "category":"Retail",
            "subcategory":"Funeral Services",
            "type":"Services"
        }
    ],
    "sg:phone":"+32 11 79 24 70",
    "sg:postcode":"3670",
    "sg:province":"Limburg",
    "sg:tags":[
        "director"
    ],
    "wof:name":"Witters-paesen",
    "wof:placetype":"venue"
},
  "geometry": {"coordinates":[5.5236020088,51.0954093933],"type":"Point"}
}