{
  "type": "Feature",
  "properties": {
    "addr:full":"Rue Du Stade 37 Verviers (stembert) Li\u00e8ge 4801",
    "addr:housenumber":"37",
    "addr:postcode":"4801",
    "addr:street":"Rue Du Stade",
    "iso:country":"BE",
    "sg:address":"Rue Du Stade 37",
    "sg:city":"Verviers (stembert)",
    "sg:classifiers":[
        {
            "category":"Real Estate",
            "subcategory":"Architect",
            "type":"Services"
        }
    ],
    "sg:phone":"+32 87 31 45 66",
    "sg:postcode":"4801",
    "sg:province":"Li\u00e8ge",
    "wof:name":"Toussaint C",
    "wof:placetype":"venue"
},
  "geometry": {"coordinates":[5.8807940483,50.5909805298],"type":"Point"}
}