{
  "type": "Feature",
  "properties": {
    "iso:country":"BE",
    "sg:address":"Deliestraat 51",
    "sg:city":"Balen",
    "sg:orig_category":"Sportclubs",
    "sg:phone":"+32 14 81 39 74",
    "sg:postcode":"2490",
    "sg:province":"Antwerpen",
    "wof:name":"P.c Mol",
    "wof:placetype":"venue"
},
  "geometry": {"coordinates":[5.1678190231,51.1754646301],"type":"Point"}
}