{
  "type": "Feature",
  "properties": {
    "addr:full":"Rue G\u00c9ron 40 Andenne Namur 5300",
    "addr:housenumber":"40",
    "addr:postcode":"5300",
    "addr:street":"Rue Ge\u0301Ron",
    "iso:country":"BE",
    "sg:address":"Rue G\u00c9ron 40",
    "sg:city":"Andenne",
    "sg:orig_category":"Loodgieterij, verwarming and sanitaire installaties",
    "sg:phone":"+32 85 82 73 37",
    "sg:postcode":"5300",
    "sg:province":"Namur",
    "wof:name":"Techno M\u00c9tal Industrie",
    "wof:placetype":"venue"
},
  "geometry": {"coordinates":[5.0982642174,50.4863739014],"type":"Point"}
}