{
  "type": "Feature",
  "properties": {
    "addr:full":"Rue St-nicolas 365 Saint-nicolas Li\u00e8ge 4420",
    "addr:housenumber":"365",
    "addr:postcode":"4420",
    "addr:street":"Rue St-Nicolas",
    "iso:country":"BE",
    "sg:address":"Rue St-nicolas 365",
    "sg:city":"Saint-nicolas",
    "sg:classifiers":[
        {
            "category":"Bars & Pubs",
            "type":"Food & Drink"
        }
    ],
    "sg:phone":"+32 4 226 10 12",
    "sg:postcode":"4420",
    "sg:province":"Li\u00e8ge",
    "wof:name":"Abruzzes (des)",
    "wof:placetype":"venue"
},
  "geometry": {"coordinates":[5.5363178253,50.6395683289],"type":"Point"}
}