{
  "type": "Feature",
  "properties": {
    "addr:full":"Rue De Moresnet 75 Kelmis Li\u00e8ge 4720",
    "addr:housenumber":"75",
    "addr:postcode":"4720",
    "addr:street":"Rue De Moresnet",
    "iso:country":"BE",
    "sg:address":"Rue De Moresnet 75",
    "sg:city":"Kelmis",
    "sg:orig_category":"D\u00e9taillants en pi\u00e8ces and accessoires de voitures",
    "sg:phone":"+32 87 65 38 10",
    "sg:postcode":"4720",
    "sg:province":"Li\u00e8ge",
    "wof:name":"Bernd Beno\u00cet",
    "wof:placetype":"venue"
},
  "geometry": {"coordinates":[6.0095658302,50.7211608887],"type":"Point"}
}