{
  "type": "Feature",
  "properties": {
    "iso:country":"BE",
    "sg:address":"Kleine Rijstraat 15",
    "sg:city":"Ninove (denderwindeke)",
    "sg:classifiers":[
        {
            "category":"Building & Trades",
            "subcategory":"Electrical",
            "type":"Services"
        }
    ],
    "sg:phone":"+32 54 32 19 10",
    "sg:postcode":"9400",
    "sg:province":"Oost-Vlaanderen",
    "sg:tags":[
        "electric",
        "-",
        "housewiring",
        "contractor"
    ],
    "wof:name":"Desert E",
    "wof:placetype":"venue"
},
  "geometry": {"coordinates":[4.0234332085,50.783908844],"type":"Point"}
}