{
  "type": "Feature",
  "properties": {
    "addr:full":"Rue Des D\u00c9port\u00c9s 19 Courcelles Hainaut 6180",
    "addr:housenumber":"19",
    "addr:postcode":"6180",
    "addr:street":"Rue Des De\u0301Porte\u0301S",
    "iso:country":"BE",
    "sg:address":"Rue Des D\u00c9port\u00c9s 19",
    "sg:city":"Courcelles",
    "sg:orig_category":"Installation \u00e9lectrique r\u00e9sidentielle",
    "sg:phone":"+32 71 45 05 64",
    "sg:postcode":"6180",
    "sg:province":"Hainaut",
    "wof:name":"Fuselec",
    "wof:placetype":"venue"
},
  "geometry": {"coordinates":[4.3732471466,50.463924408],"type":"Point"}
}