{
  "type": "Feature",
  "properties": {
    "addr:full":"Coupure Rechts 178 Gent Oost-Vlaanderen 9000",
    "addr:housenumber":"178",
    "addr:postcode":"9000",
    "addr:street":"Coupure Rechts;Oost-Vlaanderen",
    "iso:country":"BE",
    "sg:address":"Coupure Rechts 178",
    "sg:city":"Gent",
    "sg:classifiers":[
        {
            "category":"Real Estate",
            "subcategory":"Architect",
            "type":"Services"
        }
    ],
    "sg:phone":"+32 9 232 05 08",
    "sg:postcode":"9000",
    "sg:province":"Oost-Vlaanderen",
    "wof:name":"Archipro",
    "wof:placetype":"venue"
},
  "geometry": {"coordinates":[3.7135360241,51.0486984253],"type":"Point"}
}