{
  "type": "Feature",
  "properties": {
    "iso:country":"BE",
    "sg:address":"Lijsterstraat 14",
    "sg:city":"Ardooie",
    "sg:orig_category":"Kantoormateriaal",
    "sg:phone":"+32 51 31 77 82",
    "sg:postcode":"8850",
    "sg:province":"West-Vlaanderen",
    "wof:name":"Marleen Masschelein",
    "wof:placetype":"venue"
},
  "geometry": {"coordinates":[3.2076311111,50.9450645447],"type":"Point"}
}