{
  "type": "Feature",
  "properties": {
    "addr:full":"Cour De La Taillette 5/101 Ottignies-louvain-la-neuve Brabant Wallon 1348",
    "addr:housenumber":"5 / 101",
    "addr:postcode":"1348",
    "addr:street":"Cour De La Taillette",
    "iso:country":"BE",
    "sg:address":"Cour De La Taillette 5/101",
    "sg:city":"Ottignies-louvain-la-neuve",
    "sg:orig_category":"Pr\u00eats hypoth\u00e9caires and cr\u00e9dits immobiliers. Assurances",
    "sg:phone":"+32 10 45 69 01",
    "sg:postcode":"1348",
    "sg:province":"Brabant Wallon",
    "wof:name":"Finacth",
    "wof:placetype":"venue"
},
  "geometry": {"coordinates":[4.567553997,50.6661262512],"type":"Point"}
}