{
  "type": "Feature",
  "properties": {
    "addr:full":"Herseauxplein 4 Moeskroen/mouscron Hainaut 7712",
    "addr:housenumber":"4",
    "addr:postcode":"7712",
    "addr:street":"Herseauxplein",
    "iso:country":"BE",
    "sg:address":"Herseauxplein 4",
    "sg:city":"Moeskroen/mouscron",
    "sg:orig_category":"Brood, gebak and snoepgoed",
    "sg:phone":"+32 56 33 09 55",
    "sg:postcode":"7712",
    "sg:province":"Hainaut",
    "wof:name":"Christophe Wille",
    "wof:placetype":"venue"
},
  "geometry": {"coordinates":[3.2535879612,50.714931488],"type":"Point"}
}