{
  "type": "Feature",
  "properties": {
    "addr:full":"Sint-truidensesteenweg 229 Tienen Vlaams-Brabant 3300",
    "addr:housenumber":"229",
    "addr:postcode":"3300",
    "addr:street":"Sint-Truidensesteenweg",
    "iso:country":"BE",
    "sg:address":"Sint-truidensesteenweg 229",
    "sg:city":"Tienen",
    "sg:classifiers":[
        {
            "category":"Cafe",
            "type":"Food & Drink"
        }
    ],
    "sg:phone":"+32 16 82 39 06",
    "sg:postcode":"3300",
    "sg:province":"Vlaams-Brabant",
    "sg:tags":[
        "caf\u00e9s"
    ],
    "wof:name":"S O R T",
    "wof:placetype":"venue"
},
  "geometry": {"coordinates":[4.9629268646,50.8000144958],"type":"Point"}
}