{
  "type": "Feature",
  "properties": {
    "iso:country":"BE",
    "sg:address":"Lekedorpsstraat 133",
    "sg:city":"Diksmuide",
    "sg:orig_category":"Installatie van houten of kunststof schrijnwerk",
    "sg:phone":"+32 51 51 01 86",
    "sg:postcode":"8600",
    "sg:province":"West-Vlaanderen",
    "wof:name":"Geert Deseure",
    "wof:placetype":"venue"
},
  "geometry": {"coordinates":[2.8657801151,51.0334663391],"type":"Point"}
}