{
  "type": "Feature",
  "properties": {
    "iso:country":"BE",
    "sg:address":"Hof Ten Boesdaallaan 7",
    "sg:city":"Beersel (alsemberg)",
    "sg:classifiers":[
        {
            "category":"Real Estate",
            "subcategory":"Real Estate Services",
            "type":"Services"
        }
    ],
    "sg:phone":"+32 2 306 01 66",
    "sg:postcode":"1652",
    "sg:province":"Vlaams-Brabant",
    "wof:name":"Immo Marckx Bvba",
    "wof:placetype":"venue"
},
  "geometry": {"coordinates":[4.3536567688,50.7563209534],"type":"Point"}
}