{
  "type": "Feature",
  "properties": {
    "iso:country":"BE",
    "sg:address":"Lange Kievitstraat 85",
    "sg:city":"Antwerpen",
    "sg:classifiers":[
        {
            "category":"Farming",
            "subcategory":"Fish & Marine Products",
            "type":"Manufacturing & Wholesale Goods"
        }
    ],
    "sg:phone":"+32 3 232 87 87",
    "sg:postcode":"2018",
    "sg:province":"Antwerpen",
    "sg:tags":[
        "retail",
        "-",
        "shellfish"
    ],
    "wof:name":"Hoffmann Bvba",
    "wof:placetype":"venue"
},
  "geometry": {"coordinates":[4.4205298424,51.2130126953],"type":"Point"}
}