{
  "type": "Feature",
  "properties": {
    "iso:country":"BE",
    "sg:address":"Kortrijksestraat 85",
    "sg:city":"Oostkamp",
    "sg:orig_category":"M\u00e9decins and sp\u00e9cialistes",
    "sg:phone":"+32 50 82 37 70",
    "sg:postcode":"8020",
    "sg:province":"West-Vlaanderen",
    "wof:name":"Jan Smolders",
    "wof:placetype":"venue"
},
  "geometry": {"coordinates":[3.2335269451,51.1501846313],"type":"Point"}
}