{
  "type": "Feature",
  "properties": {
    "addr:full":"Zangvogellaan 18 Gent Oost-Vlaanderen 9041",
    "addr:housenumber":"18",
    "addr:postcode":"9041",
    "addr:street":"Zangvogellaan;Oost-Vlaanderen",
    "iso:country":"BE",
    "sg:address":"Zangvogellaan 18",
    "sg:city":"Gent",
    "sg:orig_category":"Boekhouders",
    "sg:phone":"+32 9 228 20 86",
    "sg:postcode":"9041",
    "sg:province":"Oost-Vlaanderen",
    "wof:name":"Eddy Deville",
    "wof:placetype":"venue"
},
  "geometry": {"coordinates":[3.7711629868,51.076461792],"type":"Point"}
}