{
  "type": "Feature",
  "properties": {
    "addr:full":"Kalverstraat 27 Kruibeke Oost-Vlaanderen 9150",
    "addr:housenumber":"27",
    "addr:postcode":"9150",
    "addr:street":"Kalverstraat",
    "iso:country":"BE",
    "sg:address":"Kalverstraat 27",
    "sg:city":"Kruibeke",
    "sg:orig_category":"Rundveehouders Zuivelproducten",
    "sg:phone":"+32 3 774 24 26",
    "sg:postcode":"9150",
    "sg:province":"Oost-Vlaanderen",
    "wof:name":"Marcel Van Hoyweghen",
    "wof:placetype":"venue"
},
  "geometry": {"coordinates":[4.2902679443,51.133518219],"type":"Point"}
}