{
  "type": "Feature",
  "properties": {
    "iso:country":"BE",
    "sg:address":"Mieregemstraat 29a",
    "sg:city":"Merchtem",
    "sg:orig_category":"Non-Classified Establishments",
    "sg:phone":"+32 52 37 38 61",
    "sg:postcode":"1785",
    "sg:province":"Vlaams-Brabant",
    "wof:name":"I.h.t. Belgium Bvba",
    "wof:placetype":"venue"
},
  "geometry": {"coordinates":[4.2315649986,50.9569206238],"type":"Point"}
}