{
  "type": "Feature",
  "properties": {
    "addr:full":"Chauss\u00c9e De Nivelles 19 Charleroi Hainaut 6041",
    "addr:housenumber":"19",
    "addr:postcode":"6041",
    "addr:street":"Chausse\u0301E De Nivelles;Hainaut",
    "iso:country":"BE",
    "sg:address":"Chauss\u00c9e De Nivelles 19",
    "sg:city":"Charleroi",
    "sg:classifiers":[
        {
            "category":"Cafe",
            "type":"Food & Drink"
        }
    ],
    "sg:phone":"+32 71 35 64 32",
    "sg:postcode":"6041",
    "sg:province":"Hainaut",
    "sg:tags":[
        "caf\u00e9s"
    ],
    "wof:name":"Caf\u00c9 La Vend\u00c9e",
    "wof:placetype":"venue"
},
  "geometry": {"coordinates":[4.4314317703,50.4685935974],"type":"Point"}
}