{
  "type": "Feature",
  "properties": {
    "addr:full":"Rue D'arlon 75-77 Etterbeek Bruxelles-Capitale 1040",
    "addr:postcode":"75-77;1040",
    "addr:street":"Rue D'Arlon",
    "iso:country":"BE",
    "sg:address":"Rue D'arlon 75-77",
    "sg:city":"Etterbeek",
    "sg:classifiers":[
        {
            "category":"Health Services",
            "subcategory":"Nursing And Care Facility",
            "type":"Services"
        }
    ],
    "sg:phone":"+32 2 286 82 11",
    "sg:postcode":"1040",
    "sg:province":"Bruxelles-Capitale",
    "sg:tags":[
        "public"
    ],
    "wof:name":"Sabam",
    "wof:placetype":"venue"
},
  "geometry": {"coordinates":[4.3745031357,50.8433303833],"type":"Point"}
}