{
  "type": "Feature",
  "properties": {
    "addr:full":"Knesselarestraat 148 Beernem West-Vlaanderen 8730",
    "addr:housenumber":"148",
    "addr:postcode":"8730",
    "addr:street":"Knesselarestraat",
    "iso:country":"BE",
    "sg:address":"Knesselarestraat 148",
    "sg:city":"Beernem",
    "sg:orig_category":"Eleveurs de bovins",
    "sg:phone":"+32 50 78 84 23",
    "sg:postcode":"8730",
    "sg:province":"West-Vlaanderen",
    "wof:name":"Idesbald Keerman",
    "wof:placetype":"venue"
},
  "geometry": {"coordinates":[3.3629610538,51.1626548767],"type":"Point"}
}