{
  "type": "Feature",
  "properties": {
    "iso:country":"BE",
    "sg:address":"Egemsestraat 2ba",
    "sg:city":"Wingene",
    "sg:orig_category":"Artsen and specialisten",
    "sg:phone":"+32 51 65 57 90",
    "sg:postcode":"8750",
    "sg:province":"West-Vlaanderen",
    "wof:name":"J. Depamelaere",
    "wof:placetype":"venue"
},
  "geometry": {"coordinates":[3.2730178833,51.0570144653],"type":"Point"}
}