{
  "type": "Feature",
  "properties": {
    "iso:country":"BE",
    "sg:address":"Leuvensestraat 72",
    "sg:city":"Tienen",
    "sg:orig_category":"V\u00eatements pour Hommes",
    "sg:phone":"+32 16 81 43 23",
    "sg:postcode":"3300",
    "sg:province":"Vlaams-Brabant",
    "wof:name":"Contrast",
    "wof:placetype":"venue"
},
  "geometry": {"coordinates":[4.933409214,50.80909729],"type":"Point"}
}