{
  "type": "Feature",
  "properties": {
    "iso:country":"BE",
    "sg:address":"Retiesebaan 81",
    "sg:city":"Kasterlee",
    "sg:orig_category":"Banques and organismes de cr\u00e9dit",
    "sg:phone":"+32 14 85 01 79",
    "sg:postcode":"2460",
    "sg:province":"Antwerpen",
    "wof:name":"Landbouwkrediet",
    "wof:placetype":"venue"
},
  "geometry": {"coordinates":[4.9782099724,51.2424850464],"type":"Point"}
}