{
  "type": "Feature",
  "properties": {
    "iso:country":"BE",
    "sg:address":"Stationsstraat 51a",
    "sg:city":"Sint-katelijne-waver",
    "sg:classifiers":[
        {
            "category":"Retail",
            "subcategory":"Repair Shop",
            "type":"Services"
        }
    ],
    "sg:phone":"+32 15 32 00 32",
    "sg:postcode":"2860",
    "sg:province":"Antwerpen",
    "sg:tags":[
        "-",
        "mainten",
        "watch",
        "clock"
    ],
    "wof:name":"Helsen J",
    "wof:placetype":"venue"
},
  "geometry": {"coordinates":[4.5282068253,51.070514679],"type":"Point"}
}