{
  "type": "Feature",
  "properties": {
    "iso:country":"BE",
    "sg:address":"Magdalenastraat 2",
    "sg:city":"Antwerpen",
    "sg:orig_category":"Fotografen and fotostudio's Persagentschappen",
    "sg:phone":"+32 475 95 33 67",
    "sg:postcode":"2018",
    "sg:province":"Antwerpen",
    "wof:name":"Chris Sel",
    "wof:placetype":"venue"
},
  "geometry": {"coordinates":[4.4268121719,51.2087745667],"type":"Point"}
}