{
  "type": "Feature",
  "properties": {
    "addr:full":"Hoveniersstraat 19 Antwerpen Antwerpen 2018",
    "addr:housenumber":"19",
    "addr:postcode":"2018",
    "addr:street":"Hoveniersstraat",
    "iso:country":"BE",
    "sg:address":"Hoveniersstraat 19",
    "sg:city":"Antwerpen",
    "sg:orig_category":"Diverse intermediaire producten Gh Juwelen and edelstenen Fab",
    "sg:phone":"+32 3 233 72 95",
    "sg:postcode":"2018",
    "sg:province":"Antwerpen",
    "wof:name":"Vets Alphi Diam. Manuf.",
    "wof:placetype":"venue"
},
  "geometry": {"coordinates":[4.4189400673,51.2153816223],"type":"Point"}
}