{
  "type": "Feature",
  "properties": {
    "addr:full":"Stationsstraat 15 Avelgem West-Vlaanderen 8580",
    "addr:housenumber":"15",
    "addr:postcode":"8580",
    "addr:street":"Stationsstraat",
    "iso:country":"BE",
    "sg:address":"Stationsstraat 15",
    "sg:city":"Avelgem",
    "sg:orig_category":"Meubelzaken, woning- and keukeninrichting",
    "sg:phone":"+32 56 64 54 38",
    "sg:postcode":"8580",
    "sg:province":"West-Vlaanderen",
    "wof:name":"Meubelen Comfort",
    "wof:placetype":"venue"
},
  "geometry": {"coordinates":[3.4432299137,50.7714233398],"type":"Point"}
}