{
  "type": "Feature",
  "properties": {
    "iso:country":"BE",
    "sg:address":"Heidestr 43-45",
    "sg:city":"Middelkerke",
    "sg:classifiers":[
        {
            "category":"Building & Trades",
            "subcategory":"Construction",
            "type":"Services"
        }
    ],
    "sg:phone":"+32 58 23 34 21",
    "sg:postcode":"8434",
    "sg:province":"West-Vlaanderen",
    "sg:tags":[
        "work",
        "public"
    ],
    "wof:name":"Algemene Ondernemingen Soetaert Nv",
    "wof:placetype":"venue"
},
  "geometry": {"coordinates":[2.7569050789,51.1488685608],"type":"Point"}
}