{
  "type": "Feature",
  "properties": {
    "addr:full":"Blauwen Draaiboom 4 Hoogstraten Antwerpen 2322",
    "addr:housenumber":"4",
    "addr:postcode":"2322",
    "addr:street":"Blauwen Draaiboom",
    "iso:country":"BE",
    "sg:address":"Blauwen Draaiboom 4",
    "sg:city":"Hoogstraten",
    "sg:orig_category":"Eleveurs de bovins",
    "sg:phone":"+32 3 314 78 63",
    "sg:postcode":"2322",
    "sg:province":"Antwerpen",
    "wof:name":"Leopold Verhoeven",
    "wof:placetype":"venue"
},
  "geometry": {"coordinates":[4.720500946,51.4131240845],"type":"Point"}
}