{
  "type": "Feature",
  "properties": {
    "addr:full":"Gierlestraat 37 Baarle-hertog Antwerpen 2387",
    "addr:housenumber":"37",
    "addr:postcode":"2387",
    "addr:street":"Gierlestraat",
    "iso:country":"BE",
    "sg:address":"Gierlestraat 37",
    "sg:city":"Baarle-hertog",
    "sg:orig_category":"Eleveurs de bovins",
    "sg:phone":"+32 14 69 91 30",
    "sg:postcode":"2387",
    "sg:province":"Antwerpen",
    "wof:name":"Adrianus Nooijens",
    "wof:placetype":"venue"
},
  "geometry": {"coordinates":[4.9356322289,51.431930542],"type":"Point"}
}