{
  "type": "Feature",
  "properties": {
    "addr:full":"Rue Du Bois 13 Charleroi Hainaut 6040",
    "addr:housenumber":"13",
    "addr:postcode":"6040",
    "addr:street":"Rue Du Bois;Hainaut",
    "iso:country":"BE",
    "sg:address":"Rue Du Bois 13",
    "sg:city":"Charleroi",
    "sg:orig_category":"Sportclubs Sportterreinen and installaties behalve sportcentra",
    "sg:phone":"+32 71 35 15 55",
    "sg:postcode":"6040",
    "sg:province":"Hainaut",
    "wof:name":"E.s. Frasnoise",
    "wof:placetype":"venue"
},
  "geometry": {"coordinates":[4.4557781219,50.4433021545],"type":"Point"}
}