{
  "type": "Feature",
  "properties": {
    "addr:full":"Hoogstraat 202 Zaventem Vlaams-Brabant 1930",
    "addr:housenumber":"202",
    "addr:postcode":"1930",
    "addr:street":"Hoogstraat",
    "iso:country":"BE",
    "sg:address":"Hoogstraat 202",
    "sg:city":"Zaventem",
    "sg:orig_category":"Winkelinrichting and handelsuitrusting Gh",
    "sg:phone":"+32 2 720 72 03",
    "sg:postcode":"1930",
    "sg:province":"Vlaams-Brabant",
    "wof:name":"New John Nissen Company",
    "wof:placetype":"venue"
},
  "geometry": {"coordinates":[4.4648799896,50.8824691772],"type":"Point"}
}