{
  "type": "Feature",
  "properties": {
    "addr:full":"Rue De France 14 Box 5 Braine-le-comte Hainaut 7090",
    "addr:housenumber":"14;5",
    "addr:postcode":"7090",
    "addr:street":"Rue De France;Box",
    "iso:country":"BE",
    "sg:address":"Rue De France 14 Box 5",
    "sg:city":"Braine-le-comte",
    "sg:classifiers":[
        {
            "category":"Insurance",
            "subcategory":"Insurance Agent",
            "type":"Services"
        }
    ],
    "sg:phone":"+32 67 55 65 65",
    "sg:postcode":"7090",
    "sg:province":"Hainaut",
    "sg:tags":[
        "broker"
    ],
    "wof:name":"F.i.c. Assurances Sprl",
    "wof:placetype":"venue"
},
  "geometry": {"coordinates":[4.1335320473,50.604598999],"type":"Point"}
}