{
  "type": "Feature",
  "properties": {
    "iso:country":"BE",
    "sg:address":"Luikersteenweg 277-2",
    "sg:city":"Tongeren",
    "sg:classifiers":[
        {
            "category":"Building & Trades",
            "subcategory":"Landscaping Services",
            "type":"Services"
        }
    ],
    "sg:phone":"+32 12 39 13 24",
    "sg:postcode":"3700",
    "sg:province":"Limburg",
    "sg:tags":[
        "architect",
        "landscape"
    ],
    "wof:name":"Timmermans Eric",
    "wof:placetype":"venue"
},
  "geometry": {"coordinates":[5.4717998505,50.7643508911],"type":"Point"}
}