{
  "type": "Feature",
  "properties": {
    "addr:full":"Elizabetlaan 141 Knokke-heist West-Vlaanderen 8300",
    "addr:housenumber":"141",
    "addr:postcode":"8300",
    "addr:street":"Elizabetlaan",
    "iso:country":"BE",
    "sg:address":"Elizabetlaan 141",
    "sg:city":"Knokke-heist",
    "sg:orig_category":"Sociale secretariaten",
    "sg:phone":"+32 50 62 28 28",
    "sg:postcode":"8300",
    "sg:province":"West-Vlaanderen",
    "wof:name":"Admb",
    "wof:placetype":"venue"
},
  "geometry": {"coordinates":[3.287694931,51.3467254639],"type":"Point"}
}