{
  "type": "Feature",
  "properties": {
    "iso:country":"BE",
    "sg:address":"Kerkstraat 2",
    "sg:city":"Aarschot",
    "sg:orig_category":"Pain, p\u00e2tisseries and confiseries",
    "sg:phone":"+32 16 57 16 17",
    "sg:postcode":"3200",
    "sg:province":"Vlaams-Brabant",
    "wof:name":"Resade",
    "wof:placetype":"venue"
},
  "geometry": {"coordinates":[4.8364510536,51.0053253174],"type":"Point"}
}