{
  "type": "Feature",
  "properties": {
    "iso:country":"BE",
    "sg:address":"Rue De Rosi\u00c8res 19",
    "sg:city":"Rixensart",
    "sg:orig_category":"Agences immobili\u00e8res. Assurances",
    "sg:phone":"+32 2 654 19 55",
    "sg:postcode":"1332",
    "sg:province":"Brabant Wallon",
    "wof:name":"Assurance Jacobs Fran\u00c7ois",
    "wof:placetype":"venue"
},
  "geometry": {"coordinates":[4.5162849426,50.7246322632],"type":"Point"}
}