{
  "type": "Feature",
  "properties": {
    "addr:full":"Groenstraat 76bb Aalst Oost-Vlaanderen 9320",
    "addr:housenumber":"76bb",
    "addr:postcode":"9320",
    "addr:street":"Groenstraat",
    "iso:country":"BE",
    "sg:address":"Groenstraat 76bb",
    "sg:city":"Aalst",
    "sg:orig_category":"Charpentes and couvertures. Constructions r\u00e9sidentielles sp\u00e9cifiques. Mat\u00e9riaux de construction Gr",
    "sg:phone":"+32 53 21 32 63",
    "sg:postcode":"9320",
    "sg:province":"Oost-Vlaanderen",
    "wof:name":"Dierick",
    "wof:placetype":"venue"
},
  "geometry": {"coordinates":[4.0511431694,50.9436531067],"type":"Point"}
}