{
  "type": "Feature",
  "properties": {
    "iso:country":"BE",
    "sg:address":"Felix Beernaertsplein 57",
    "sg:city":"Wetteren",
    "sg:classifiers":[
        {
            "category":"Health Services",
            "subcategory":"Health Practitioner",
            "type":"Services"
        }
    ],
    "sg:phone":"+32 9 369 17 26",
    "sg:postcode":"9230",
    "sg:province":"Oost-Vlaanderen",
    "sg:tags":[
        "physiotherapist"
    ],
    "wof:name":"Van Damme Renaat",
    "wof:placetype":"venue"
},
  "geometry": {"coordinates":[3.8792610168,51.003036499],"type":"Point"}
}