{
  "type": "Feature",
  "properties": {
    "iso:country":"BE",
    "sg:address":"Pastorijveld 92c",
    "sg:city":"Antwerpen",
    "sg:classifiers":[
        {
            "category":"Professional",
            "type":"Services"
        }
    ],
    "sg:phone":"+32 495 51 15 84",
    "sg:postcode":"2030",
    "sg:province":"Antwerpen",
    "sg:tags":[
        "entertainer"
    ],
    "wof:name":"De Bont C",
    "wof:placetype":"venue"
},
  "geometry": {"coordinates":[4.412498951,51.2744216919],"type":"Point"}
}