{
  "type": "Feature",
  "properties": {
    "addr:full":"Guido Gezellestraat 122-1 Denderleeuw Oost-Vlaanderen 9470",
    "addr:housenumber":"122-1",
    "addr:postcode":"9470",
    "addr:street":"Guido Gezellestraat",
    "iso:country":"BE",
    "sg:address":"Guido Gezellestraat 122-1",
    "sg:city":"Denderleeuw",
    "sg:classifiers":[
        {
            "category":"Bars & Pubs",
            "subcategory":"Sports Bar",
            "type":"Food & Drink"
        }
    ],
    "sg:phone":"+32 53 64 89 40",
    "sg:postcode":"9470",
    "sg:province":"Oost-Vlaanderen",
    "wof:name":"Paridaens Sportsfood",
    "wof:placetype":"venue"
},
  "geometry": {"coordinates":[4.0767011642,50.8885536194],"type":"Point"}
}