{
  "type": "Feature",
  "properties": {
    "iso:country":"BE",
    "sg:address":"Stuiversvelden 142",
    "sg:city":"Brasschaat",
    "sg:orig_category":"Travaux d'isolation. Charpentes and couvertures",
    "sg:phone":"+32 3 651 65 90",
    "sg:postcode":"2930",
    "sg:province":"Antwerpen",
    "wof:name":"Walter De Cuyper",
    "wof:placetype":"venue"
},
  "geometry": {"coordinates":[4.4727520943,51.3026885986],"type":"Point"}
}