{
  "type": "Feature",
  "properties": {
    "addr:full":"Dantestraat 75 Anderlecht/anderlecht Bruxelles-Capitale 1070",
    "addr:housenumber":"75",
    "addr:postcode":"1070",
    "addr:street":"Dantestraat",
    "iso:country":"BE",
    "sg:address":"Dantestraat 75",
    "sg:city":"Anderlecht/anderlecht",
    "sg:orig_category":"Farmaceutische bereidingen and geneesmiddelen Fab",
    "sg:phone":"+32 2 525 82 11",
    "sg:postcode":"1070",
    "sg:province":"Bruxelles-Capitale",
    "wof:name":"Roche",
    "wof:placetype":"venue"
},
  "geometry": {"coordinates":[4.3191761971,50.8329467773],"type":"Point"}
}