{
  "type": "Feature",
  "properties": {
    "addr:full":". Gouvy Luxembourg 6670",
    "addr:postcode":"6670",
    "iso:country":"BE",
    "sg:address":".",
    "sg:city":"Gouvy",
    "sg:orig_category":"Apotheken",
    "sg:phone":"+32 900 10 500",
    "sg:postcode":"6670",
    "sg:province":"Luxembourg",
    "wof:name":"Apothekers Van Wacht",
    "wof:placetype":"venue"
},
  "geometry": {"coordinates":[5.9401988983,50.1855697632],"type":"Point"}
}