{
  "type": "Feature",
  "properties": {
    "addr:full":"Rue Claire Fontaine 28 Charleroi (marcinelle) Hainaut 6001",
    "addr:housenumber":"28",
    "addr:postcode":"6001",
    "addr:street":"Rue Claire Fontaine",
    "iso:country":"BE",
    "sg:address":"Rue Claire Fontaine 28",
    "sg:city":"Charleroi (marcinelle)",
    "sg:classifiers":[
        {
            "category":"Health Services",
            "subcategory":"Health Practitioner",
            "type":"Services"
        }
    ],
    "sg:phone":"+32 71 36 33 57",
    "sg:postcode":"6001",
    "sg:province":"Hainaut",
    "sg:tags":[
        "physiotherapist"
    ],
    "wof:name":"Maerschalcke Philippe",
    "wof:placetype":"venue"
},
  "geometry": {"coordinates":[4.4333472252,50.3621788025],"type":"Point"}
}