{
  "type": "Feature",
  "properties": {
    "addr:full":"Tienbunder 30ba Aarschot Vlaams-Brabant 3202",
    "addr:housenumber":"30ba",
    "addr:postcode":"3202",
    "addr:street":"Tienbunder",
    "iso:country":"BE",
    "sg:address":"Tienbunder 30ba",
    "sg:city":"Aarschot",
    "sg:classifiers":[
        {
            "category":"Cafe",
            "type":"Food & Drink"
        }
    ],
    "sg:phone":"+32 16 50 14 06",
    "sg:postcode":"3202",
    "sg:province":"Vlaams-Brabant",
    "sg:tags":[
        "caf\u00e9s"
    ],
    "wof:name":"Chantal Serre",
    "wof:placetype":"venue"
},
  "geometry": {"coordinates":[4.8806619644,50.9602508545],"type":"Point"}
}