{
  "type": "Feature",
  "properties": {
    "iso:country":"BE",
    "sg:address":"Binnendijkstraat 1",
    "sg:city":"Bornem",
    "sg:classifiers":[
        {
            "category":"Fast Food",
            "type":"Food & Drink"
        }
    ],
    "sg:phone":"+32 3 889 19 49",
    "sg:postcode":"2880",
    "sg:province":"Antwerpen",
    "sg:tags":[
        "\u00c0",
        "restaurants",
        "emporter",
        "restaurant"
    ],
    "wof:name":"'t Vissertje",
    "wof:placetype":"venue"
},
  "geometry": {"coordinates":[4.1984171867,51.1044921875],"type":"Point"}
}