{
  "type": "Feature",
  "properties": {
    "addr:full":"Stramproyerweg 37 Bocholt Limburg 3950",
    "addr:housenumber":"37",
    "addr:postcode":"3950",
    "addr:street":"Stramproyerweg",
    "iso:country":"BE",
    "sg:address":"Stramproyerweg 37",
    "sg:city":"Bocholt",
    "sg:orig_category":"Enseignement maternel and primaire",
    "sg:phone":"+32 89 46 56 92",
    "sg:postcode":"3950",
    "sg:province":"Limburg",
    "wof:name":"Vrije Basisschool",
    "wof:placetype":"venue"
},
  "geometry": {"coordinates":[5.6084990501,51.1833534241],"type":"Point"}
}