{
  "type": "Feature",
  "properties": {
    "addr:full":"Zandkapelweg 21 Herentals Antwerpen 2200",
    "addr:housenumber":"21",
    "addr:postcode":"2200",
    "addr:street":"Zandkapelweg",
    "iso:country":"BE",
    "sg:address":"Zandkapelweg 21",
    "sg:city":"Herentals",
    "sg:orig_category":"Enseignement maternel and primaire",
    "sg:phone":"+32 14 26 15 77",
    "sg:postcode":"2200",
    "sg:province":"Antwerpen",
    "wof:name":"Vrije Basisschool",
    "wof:placetype":"venue"
},
  "geometry": {"coordinates":[4.830739975,51.1241912842],"type":"Point"}
}