{
  "type": "Feature",
  "properties": {
    "addr:full":"Nederstraat 62 Oudenaarde Oost-Vlaanderen 9700",
    "addr:housenumber":"62",
    "addr:postcode":"9700",
    "addr:street":"Nederstraat",
    "iso:country":"BE",
    "sg:address":"Nederstraat 62",
    "sg:city":"Oudenaarde",
    "sg:orig_category":"Antiquit\u00e9s",
    "sg:phone":"+32 55 31 83 53",
    "sg:postcode":"9700",
    "sg:province":"Oost-Vlaanderen",
    "wof:name":"Huis 't Oud Pandje",
    "wof:placetype":"venue"
},
  "geometry": {"coordinates":[3.6024460793,50.845539093],"type":"Point"}
}