{
  "type": "Feature",
  "properties": {
    "iso:country":"BE",
    "sg:address":"Route De La Hesbaye 81",
    "sg:city":"Eghez\u00e9e (noville-sur-m\u00e9haigne)",
    "sg:classifiers":[
        {
            "category":"Communications",
            "type":"Services"
        }
    ],
    "sg:phone":"+32 81 81 23 45",
    "sg:postcode":"5310",
    "sg:province":"Namur",
    "sg:tags":[
        "translator"
    ],
    "wof:name":"Medicom Sprl",
    "wof:placetype":"venue"
},
  "geometry": {"coordinates":[4.903181076,50.6122627258],"type":"Point"}
}