{
  "type": "Feature",
  "properties": {
    "addr:full":"Pamelseklei 52 Roosdaal Vlaams-Brabant 1760",
    "addr:housenumber":"52",
    "addr:postcode":"1760",
    "addr:street":"Pamelseklei",
    "iso:country":"BE",
    "sg:address":"Pamelseklei 52",
    "sg:city":"Roosdaal",
    "sg:orig_category":"Banques and organismes de cr\u00e9dit",
    "sg:phone":"+32 54 32 52 95",
    "sg:postcode":"1760",
    "sg:province":"Vlaams-Brabant",
    "wof:name":"Bacob",
    "wof:placetype":"venue"
},
  "geometry": {"coordinates":[4.0744271278,50.8435707092],"type":"Point"}
}