{
  "type": "Feature",
  "properties": {
    "iso:country":"BE",
    "sg:address":"Molderdijk 173",
    "sg:city":"Mol",
    "sg:classifiers":[
        {
            "category":"Autos & Motor Vehicles",
            "subcategory":"Automobile Sales",
            "type":"Retail Goods"
        }
    ],
    "sg:phone":"+32 14 31 91 69",
    "sg:postcode":"2400",
    "sg:province":"Antwerpen",
    "sg:tags":[
        "car",
        "used",
        "-"
    ],
    "wof:name":"Goelen",
    "wof:placetype":"venue"
},
  "geometry": {"coordinates":[5.1174788475,51.1829185486],"type":"Point"}
}