{
  "type": "Feature",
  "properties": {
    "iso:country":"BE",
    "sg:address":"Rue Du Chatelet 46",
    "sg:city":"Dison",
    "sg:orig_category":"Tuinen",
    "sg:phone":"+32 87 35 34 75",
    "sg:postcode":"4821",
    "sg:province":"Li\u00e8ge",
    "wof:name":"Condez W.",
    "wof:placetype":"venue"
},
  "geometry": {"coordinates":[5.8593192101,50.6000938416],"type":"Point"}
}