{
  "type": "Feature",
  "properties": {
    "addr:full":"Grand'place 10 Lessines Hainaut 7860",
    "addr:housenumber":"10",
    "addr:postcode":"7860",
    "addr:street":"Grand'Place;Hainaut",
    "iso:country":"BE",
    "sg:address":"Grand'place 10",
    "sg:city":"Lessines",
    "sg:orig_category":"Banques and organismes de cr\u00e9dit",
    "sg:phone":"+32 68 33 37 56",
    "sg:postcode":"7860",
    "sg:province":"Hainaut",
    "wof:name":"Fortis",
    "wof:placetype":"venue"
},
  "geometry": {"coordinates":[3.8290889263,50.7124633789],"type":"Point"}
}