{
  "type": "Feature",
  "properties": {
    "addr:full":"Rue Joseph Quevit 26 Andenne Namur 5300",
    "addr:housenumber":"26",
    "addr:postcode":"5300",
    "addr:street":"Rue Joseph Quevit",
    "iso:country":"BE",
    "sg:address":"Rue Joseph Quevit 26",
    "sg:city":"Andenne",
    "sg:orig_category":"Installation de menuiserie en bois and plastique. Travaux d'isolation",
    "sg:phone":"+32 85 84 26 75",
    "sg:postcode":"5300",
    "sg:province":"Namur",
    "wof:name":"Menuiserie Franckinioulle",
    "wof:placetype":"venue"
},
  "geometry": {"coordinates":[5.0878357887,50.4880867004],"type":"Point"}
}