{
  "type": "Feature",
  "properties": {
    "iso:country":"BE",
    "sg:address":"Malibranstraat 114",
    "sg:city":"Elsene/ixelles",
    "sg:orig_category":"Reisbureaus",
    "sg:phone":"+32 2 649 41 04",
    "sg:postcode":"1050",
    "sg:province":"Bruxelles-Capitale",
    "wof:name":"Comanav",
    "wof:placetype":"venue"
},
  "geometry": {"coordinates":[4.3742461205,50.8323326111],"type":"Point"}
}