{
  "type": "Feature",
  "properties": {
    "iso:country":"BE",
    "sg:address":"Bist 12",
    "sg:city":"Aartselaar",
    "sg:classifiers":[
        {
            "category":"Retail",
            "subcategory":"Auto Repair",
            "type":"Services"
        }
    ],
    "sg:phone":"+32 3 870 81 20",
    "sg:postcode":"2630",
    "sg:province":"Antwerpen",
    "sg:tags":[
        "automobile-body"
    ],
    "wof:name":"Bodyrepair Nv",
    "wof:placetype":"venue"
},
  "geometry": {"coordinates":[4.3711447716,51.1243476868],"type":"Point"}
}