{
  "type": "Feature",
  "properties": {
    "iso:country":"BE",
    "sg:address":"Najaarsweg 32",
    "sg:city":"Kuurne",
    "sg:orig_category":"Installation \u00e9lectrique r\u00e9sidentielle",
    "sg:phone":"+32 56 70 56 17",
    "sg:postcode":"8520",
    "sg:province":"West-Vlaanderen",
    "wof:name":"Elektro Melsens G.",
    "wof:placetype":"venue"
},
  "geometry": {"coordinates":[3.2848989964,50.8605308533],"type":"Point"}
}