{
  "type": "Feature",
  "properties": {
    "iso:country":"BE",
    "sg:address":"Het Ven",
    "sg:city":"Zandhoven",
    "sg:classifiers":[
        {
            "category":"Shopping",
            "subcategory":"Clothing, Apparel, & Fashions",
            "type":"Retail Goods"
        }
    ],
    "sg:phone":"+32 3 484 59 60",
    "sg:postcode":"2240",
    "sg:province":"Antwerpen",
    "sg:tags":[
        "-",
        "clothing",
        "child"
    ],
    "wof:name":"Benickel",
    "wof:placetype":"venue"
},
  "geometry": {"coordinates":[4.6564598083,51.2056159973],"type":"Point"}
}