{
  "type": "Feature",
  "properties": {
    "addr:full":"Rue Valise 26 Beauvechain (tourinnes-la-grosse) Brabant Wallon 1320",
    "addr:housenumber":"26",
    "addr:postcode":"1320",
    "addr:street":"Rue Valise;Wallon",
    "iso:country":"BE",
    "sg:address":"Rue Valise 26",
    "sg:city":"Beauvechain (tourinnes-la-grosse)",
    "sg:classifiers":[
        {
            "category":"Retail",
            "subcategory":"Animal Services",
            "type":"Services"
        }
    ],
    "sg:phone":"+32 10 86 66 49",
    "sg:postcode":"1320",
    "sg:province":"Brabant Wallon",
    "sg:tags":[
        "training",
        "dog"
    ],
    "wof:name":"Dog City",
    "wof:placetype":"venue"
},
  "geometry": {"coordinates":[4.7466101646,50.7767906189],"type":"Point"}
}