{
  "type": "Feature",
  "properties": {
    "addr:full":"Chausse\u00c9 De Mons 857 Brussel/bruxelles Bruxelles-Capitale 1070",
    "addr:housenumber":"857",
    "addr:postcode":"1070",
    "addr:street":"Mons;/",
    "iso:country":"BE",
    "sg:address":"Chausse\u00c9 De Mons 857",
    "sg:city":"Brussel/bruxelles",
    "sg:orig_category":"Fleurs and plantes",
    "sg:phone":"+32 2 527 50 20",
    "sg:postcode":"1070",
    "sg:province":"Bruxelles-Capitale",
    "wof:name":"Bebha Flower",
    "wof:placetype":"venue"
},
  "geometry": {"coordinates":[4.3030400276,50.8285560608],"type":"Point"}
}