{
  "type": "Feature",
  "properties": {
    "iso:country":"BE",
    "sg:address":"Steenweg Op Deinze 63",
    "sg:city":"Aalter",
    "sg:orig_category":"Rundveehouders Varkenskwekers",
    "sg:phone":"+32 9 374 44 04",
    "sg:postcode":"9880",
    "sg:province":"Oost-Vlaanderen",
    "wof:name":"Maurice Blancke",
    "wof:placetype":"venue"
},
  "geometry": {"coordinates":[3.4578430653,51.0585899353],"type":"Point"}
}