{
  "type": "Feature",
  "properties": {
    "iso:country":"BE",
    "sg:address":"Kiezelweg 112",
    "sg:city":"Lanaken (veldwezelt)",
    "sg:classifiers":[
        {
            "category":"Fast Food",
            "type":"Food & Drink"
        }
    ],
    "sg:phone":"+32 89 71 71 70",
    "sg:postcode":"3620",
    "sg:province":"Limburg",
    "sg:tags":[
        "fried",
        "stand",
        "potato"
    ],
    "wof:name":"Palm (de)",
    "wof:placetype":"venue"
},
  "geometry": {"coordinates":[5.6303129196,50.8812713623],"type":"Point"}
}