{
  "type": "Feature",
  "properties": {
    "addr:full":"Dam 50 Waarschoot Oost-Vlaanderen 9950",
    "addr:housenumber":"50",
    "addr:postcode":"9950",
    "addr:street":"Dam",
    "iso:country":"BE",
    "sg:address":"Dam 50",
    "sg:city":"Waarschoot",
    "sg:orig_category":"V\u00e9hicules automobiles. Entretien and r\u00e9parations de voitures",
    "sg:phone":"+32 9 377 11 92",
    "sg:postcode":"9950",
    "sg:province":"Oost-Vlaanderen",
    "wof:name":"Verhaeghe",
    "wof:placetype":"venue"
},
  "geometry": {"coordinates":[3.5848140717,51.1704139709],"type":"Point"}
}