{
  "type": "Feature",
  "properties": {
    "addr:full":"Tienne-jean-pierre 12 Floreffe Namur 5150",
    "addr:housenumber":"12",
    "addr:postcode":"5150",
    "addr:street":"Tienne-Jean-Pierre",
    "iso:country":"BE",
    "sg:address":"Tienne-jean-pierre 12",
    "sg:city":"Floreffe",
    "sg:orig_category":"Boekhouders",
    "sg:phone":"+32 81 44 11 93",
    "sg:postcode":"5150",
    "sg:province":"Namur",
    "wof:name":"Paul Orban",
    "wof:placetype":"venue"
},
  "geometry": {"coordinates":[4.7603869438,50.4191627502],"type":"Point"}
}