{
  "type": "Feature",
  "properties": {
    "addr:full":"Auguste Demaeghtlaan 227 Halle Vlaams-Brabant 1500",
    "addr:housenumber":"227",
    "addr:postcode":"1500",
    "addr:street":"Demaeghtlaan",
    "iso:country":"BE",
    "sg:address":"Auguste Demaeghtlaan 227",
    "sg:city":"Halle",
    "sg:classifiers":[
        {
            "category":"Bakery",
            "type":"Food & Drink"
        }
    ],
    "sg:phone":"+32 2 361 86 82",
    "sg:postcode":"1500",
    "sg:province":"Vlaams-Brabant",
    "sg:tags":[
        "confectioner",
        "baker"
    ],
    "wof:name":"Halatel",
    "wof:placetype":"venue"
},
  "geometry": {"coordinates":[4.2309608459,50.7366218567],"type":"Point"}
}