{
  "type": "Feature",
  "properties": {
    "addr:full":"Bloemfonteinstraat 28 Turnhout Antwerpen 2300",
    "addr:housenumber":"28",
    "addr:postcode":"2300",
    "addr:street":"Bloemfonteinstraat",
    "iso:country":"BE",
    "sg:address":"Bloemfonteinstraat 28",
    "sg:city":"Turnhout",
    "sg:orig_category":"Installation \u00e9lectrique r\u00e9sidentielle",
    "sg:phone":"+32 14 42 51 83",
    "sg:postcode":"2300",
    "sg:province":"Antwerpen",
    "wof:name":"Elektro Luyckx",
    "wof:placetype":"venue"
},
  "geometry": {"coordinates":[4.9542508125,51.3291816711],"type":"Point"}
}