{
  "type": "Feature",
  "properties": {
    "iso:country":"BE",
    "sg:address":"Bld Emile De Laveleye 199",
    "sg:city":"Li\u00c8ge",
    "sg:orig_category":"Installation de menuiserie en bois and plastique",
    "sg:phone":"+32 4 343 98 83",
    "sg:postcode":"4020",
    "sg:province":"Li\u00e8ge",
    "wof:name":"Mobijou",
    "wof:placetype":"venue"
},
  "geometry": {"coordinates":[5.5919890404,50.6194229126],"type":"Point"}
}