{
  "type": "Feature",
  "properties": {
    "addr:full":"Mechelsesteenweg 217 Dendermonde Oost-Vlaanderen 9200",
    "addr:housenumber":"217",
    "addr:postcode":"9200",
    "addr:street":"Mechelsesteenweg;Oost-Vlaanderen",
    "iso:country":"BE",
    "sg:address":"Mechelsesteenweg 217",
    "sg:city":"Dendermonde",
    "sg:classifiers":[
        {
            "category":"Cafe",
            "type":"Food & Drink"
        }
    ],
    "sg:phone":"+32 52 21 38 82",
    "sg:postcode":"9200",
    "sg:province":"Oost-Vlaanderen",
    "sg:tags":[
        "caf\u00e9s"
    ],
    "wof:name":"Caf\u00c9 't Eiland",
    "wof:placetype":"venue"
},
  "geometry": {"coordinates":[4.1227798462,51.0367012024],"type":"Point"}
}