{
  "type": "Feature",
  "properties": {
    "addr:full":"Lage Rielen 20 Kasterlee Antwerpen 2460",
    "addr:housenumber":"20",
    "addr:postcode":"2460",
    "addr:street":"Lage Rielen",
    "iso:country":"BE",
    "sg:address":"Lage Rielen 20",
    "sg:city":"Kasterlee",
    "sg:orig_category":"M\u00e9decins and sp\u00e9cialistes",
    "sg:phone":"+32 14 85 34 44",
    "sg:postcode":"2460",
    "sg:province":"Antwerpen",
    "wof:name":"L. Hofkens",
    "wof:placetype":"venue"
},
  "geometry": {"coordinates":[4.9404420853,51.2551002502],"type":"Point"}
}