{
  "type": "Feature",
  "properties": {
    "addr:full":"Boniverlei 28 Box 1 Edegem Antwerpen 2650",
    "addr:housenumber":"28;1",
    "addr:postcode":"2650",
    "addr:street":"Boniverlei;Box",
    "iso:country":"BE",
    "sg:address":"Boniverlei 28 Box 1",
    "sg:city":"Edegem",
    "sg:classifiers":[
        {
            "category":"Professional",
            "subcategory":"Management & Consulting",
            "type":"Services"
        }
    ],
    "sg:phone":"+32 3 457 51 73",
    "sg:postcode":"2650",
    "sg:province":"Antwerpen",
    "sg:tags":[
        "consultant",
        "law"
    ],
    "wof:name":"Adjura Belgi\u00eb Bvba",
    "wof:placetype":"venue"
},
  "geometry": {"coordinates":[4.4555568695,51.1565208435],"type":"Point"}
}