{
  "type": "Feature",
  "properties": {
    "addr:full":"Stevoortse Kiezel 360 Hasselt (stevoort) Limburg 3512",
    "addr:housenumber":"360",
    "addr:postcode":"3512",
    "addr:street":"Stevoortse Kiezel",
    "iso:country":"BE",
    "sg:address":"Stevoortse Kiezel 360",
    "sg:city":"Hasselt (stevoort)",
    "sg:classifiers":[
        {
            "category":"Food & Beverages",
            "subcategory":"Groceries & Convenience Stores",
            "type":"Retail Goods"
        }
    ],
    "sg:phone":"+32 11 59 27 42",
    "sg:postcode":"3512",
    "sg:province":"Limburg",
    "sg:tags":[
        "grocer"
    ],
    "wof:name":"Reekmans-libens M",
    "wof:placetype":"venue"
},
  "geometry": {"coordinates":[5.2547950745,50.9251251221],"type":"Point"}
}