{
  "type": "Feature",
  "properties": {
    "iso:country":"BE",
    "sg:address":"All\u00c9e Des Aubepines 2",
    "sg:city":"Nivelles",
    "sg:orig_category":"Fujitsu Siemens. Conseils en syst\u00e8mes informatiques. R\u00e9alisation de programmes and logiciels. Ordina",
    "sg:phone":"+32 67 88 27 00",
    "sg:postcode":"1400",
    "sg:province":"Brabant Wallon",
    "wof:name":"Pheniks",
    "wof:placetype":"venue"
},
  "geometry": {"coordinates":[4.3495731354,50.6037368774],"type":"Point"}
}