{
  "type": "Feature",
  "properties": {
    "addr:full":"Jodenstraat 2-101 Mechelen Antwerpen 2800",
    "addr:postcode":"2-101;2800",
    "addr:street":"Jodenstraat",
    "iso:country":"BE",
    "sg:address":"Jodenstraat 2-101",
    "sg:city":"Mechelen",
    "sg:classifiers":[
        {
            "category":"Health Services",
            "subcategory":"Doctor",
            "type":"Services"
        }
    ],
    "sg:phone":"+32 15 21 27 69",
    "sg:postcode":"2800",
    "sg:province":"Antwerpen",
    "sg:tags":[
        "medicinephysicians",
        "surgeon"
    ],
    "wof:name":"Maris Esther",
    "wof:placetype":"venue"
},
  "geometry": {"coordinates":[4.4830870628,51.0322380066],"type":"Point"}
}