{
  "type": "Feature",
  "properties": {
    "addr:full":"Vandrommelaan 9 Oudergem/auderghem Bruxelles-Capitale 1160",
    "addr:housenumber":"9",
    "addr:postcode":"1160",
    "addr:street":"Vandrommelaan;/",
    "iso:country":"BE",
    "sg:address":"Vandrommelaan 9",
    "sg:city":"Oudergem/auderghem",
    "sg:orig_category":"Artiesten and kunstenaars",
    "sg:phone":"+32 2 672 60 99",
    "sg:postcode":"1160",
    "sg:province":"Bruxelles-Capitale",
    "wof:name":"Marc Herouet",
    "wof:placetype":"venue"
},
  "geometry": {"coordinates":[4.4151639938,50.8185005188],"type":"Point"}
}