{
  "type": "Feature",
  "properties": {
    "addr:full":"Stationsstraat 52 Kapellen Antwerpen 2950",
    "addr:housenumber":"52",
    "addr:postcode":"2950",
    "addr:street":"Stationsstraat",
    "iso:country":"BE",
    "sg:address":"Stationsstraat 52",
    "sg:city":"Kapellen",
    "sg:classifiers":[
        {
            "category":"Food & Beverages",
            "subcategory":"Chocolate",
            "type":"Retail Goods"
        }
    ],
    "sg:phone":"+32 3 665 31 26",
    "sg:postcode":"2950",
    "sg:province":"Antwerpen",
    "sg:tags":[
        "confectionery",
        "-"
    ],
    "wof:name":"Marie-anne",
    "wof:placetype":"venue"
},
  "geometry": {"coordinates":[4.4320039749,51.3138084412],"type":"Point"}
}