{
  "type": "Feature",
  "properties": {
    "addr:full":"Koningsstraat 139 Brussel/bruxelles Bruxelles-Capitale 1000",
    "addr:housenumber":"139",
    "addr:postcode":"1000",
    "addr:street":"Koningsstraat;/",
    "iso:country":"BE",
    "sg:address":"Koningsstraat 139",
    "sg:city":"Brussel/bruxelles",
    "sg:orig_category":"Rusthuizen and serviceflats",
    "sg:phone":"+32 2 227 63 00",
    "sg:postcode":"1000",
    "sg:province":"Bruxelles-Capitale",
    "wof:name":"I.n.i.g.",
    "wof:placetype":"venue"
},
  "geometry": {"coordinates":[4.3656840324,50.8526268005],"type":"Point"}
}