{
  "type": "Feature",
  "properties": {
    "iso:country":"BE",
    "sg:address":"Leuvensesteenweg 41",
    "sg:city":"Mechelen",
    "sg:orig_category":"Enseignement maternel and primaire",
    "sg:phone":"+32 15 41 54 18",
    "sg:postcode":"2800",
    "sg:province":"Antwerpen",
    "wof:name":"Stedelijke Basisschool",
    "wof:placetype":"venue"
},
  "geometry": {"coordinates":[4.4914422035,51.0205955505],"type":"Point"}
}