{
  "type": "Feature",
  "properties": {
    "addr:full":"Rue Piret-pauchet 49 Namur Namur 5000",
    "addr:housenumber":"49",
    "addr:postcode":"5000",
    "addr:street":"Rue Piret-Pauchet",
    "iso:country":"BE",
    "sg:address":"Rue Piret-pauchet 49",
    "sg:city":"Namur",
    "sg:classifiers":[
        {
            "category":"Farming",
            "subcategory":"Fish & Marine Products",
            "type":"Manufacturing & Wholesale Goods"
        }
    ],
    "sg:phone":"+32 81 22 25 64",
    "sg:postcode":"5000",
    "sg:province":"Namur",
    "sg:tags":[
        "schaaldierenkwekers",
        "vis-"
    ],
    "wof:name":"Pisciculture Du Tintia",
    "wof:placetype":"venue"
},
  "geometry": {"coordinates":[4.8642029762,50.4716567993],"type":"Point"}
}