{
  "type": "Feature",
  "properties": {
    "addr:full":"Leuvense Steenweg 41 Boortmeerbeek (hever) Vlaams-Brabant 3191",
    "addr:housenumber":"41",
    "addr:postcode":"3191",
    "addr:street":"Leuvense Steenweg",
    "iso:country":"BE",
    "sg:address":"Leuvense Steenweg 41",
    "sg:city":"Boortmeerbeek (hever)",
    "sg:classifiers":[
        {
            "category":"Shopping",
            "subcategory":"Bicycles & Sporting Goods",
            "type":"Retail Goods"
        }
    ],
    "sg:phone":"+32 15 51 70 68",
    "sg:postcode":"3191",
    "sg:province":"Vlaams-Brabant",
    "sg:tags":[
        "tyre"
    ],
    "wof:name":"Michel",
    "wof:placetype":"venue"
},
  "geometry": {"coordinates":[4.535545826,50.9925498962],"type":"Point"}
}