{
  "type": "Feature",
  "properties": {
    "iso:country":"BE",
    "sg:address":"Rue De Marchienne 47",
    "sg:city":"Charleroi (jumet)",
    "sg:classifiers":[
        {
            "category":"Shopping",
            "subcategory":"Books",
            "type":"Retail Goods"
        }
    ],
    "sg:phone":"+32 71 37 43 30",
    "sg:postcode":"6040",
    "sg:province":"Hainaut",
    "sg:tags":[
        "bookseller"
    ],
    "wof:name":"Gohyssart (librairie De)",
    "wof:placetype":"venue"
},
  "geometry": {"coordinates":[4.4151301384,50.4326248169],"type":"Point"}
}