{
  "type": "Feature",
  "properties": {
    "iso:country":"BE",
    "sg:address":"Houtum 39",
    "sg:city":"Kasterlee",
    "sg:classifiers":[
        {
            "category":"Retail",
            "subcategory":"Event Space",
            "type":"Services"
        }
    ],
    "sg:phone":"+32 14 85 23 65",
    "sg:postcode":"2460",
    "sg:province":"Antwerpen",
    "sg:tags":[
        "organisation"
    ],
    "wof:name":"Den Eyck",
    "wof:placetype":"venue"
},
  "geometry": {"coordinates":[4.9776911736,51.232635498],"type":"Point"}
}