{
  "type": "Feature",
  "properties": {
    "iso:country":"BE",
    "sg:address":"Grand Chemin De Messines 5",
    "sg:city":"Komen-waasten/comines-warneton",
    "sg:orig_category":"Rev\u00eatements de sols and murs. Rev\u00eatements pour sols and murs",
    "sg:phone":"+32 56 55 59 42",
    "sg:postcode":"7780",
    "sg:province":"Hainaut",
    "wof:name":"Bonte",
    "wof:placetype":"venue"
},
  "geometry": {"coordinates":[2.9984300137,50.7863311768],"type":"Point"}
}