{
  "type": "Feature",
  "properties": {
    "iso:country":"BE",
    "sg:address":"Rue Dartois 40",
    "sg:city":"Li\u00c8ge",
    "sg:classifiers":[
        {
            "category":"Fast Food",
            "type":"Food & Drink"
        }
    ],
    "sg:phone":"+32 4 252 99 59",
    "sg:postcode":"4000",
    "sg:province":"Li\u00e8ge",
    "sg:tags":[
        "\u00c0",
        "restaurants",
        "emporter",
        "restaurant"
    ],
    "wof:name":"La Porte De Tha\u00cflande",
    "wof:placetype":"venue"
},
  "geometry": {"coordinates":[5.5662641525,50.6275520325],"type":"Point"}
}