{
  "type": "Feature",
  "properties": {
    "addr:full":"Hurdumont 2 Vloesberg/flobecq Hainaut 7880",
    "addr:housenumber":"2",
    "addr:postcode":"7880",
    "addr:street":"Hurdumont",
    "iso:country":"BE",
    "sg:address":"Hurdumont 2",
    "sg:city":"Vloesberg/flobecq",
    "sg:orig_category":"Artistes ind\u00e9pendants",
    "sg:phone":"+32 68 44 77 63",
    "sg:postcode":"7880",
    "sg:province":"Hainaut",
    "wof:name":"Georges Vandevelde",
    "wof:placetype":"venue"
},
  "geometry": {"coordinates":[3.7384300232,50.7368011475],"type":"Point"}
}