{
  "type": "Feature",
  "properties": {
    "addr:full":"Kapelstraat 99 Bornem Antwerpen 2880",
    "addr:housenumber":"99",
    "addr:postcode":"2880",
    "addr:street":"Kapelstraat",
    "iso:country":"BE",
    "sg:address":"Kapelstraat 99",
    "sg:city":"Bornem",
    "sg:orig_category":"Telecommunicatieapparaten",
    "sg:phone":"+32 3 889 04 74",
    "sg:postcode":"2880",
    "sg:province":"Antwerpen",
    "wof:name":"Van Gucht",
    "wof:placetype":"venue"
},
  "geometry": {"coordinates":[4.2354040146,51.0957183838],"type":"Point"}
}