{
  "type": "Feature",
  "properties": {
    "iso:country":"BE",
    "sg:address":"Woluweveld 66",
    "sg:city":"Zaventem",
    "sg:orig_category":"Diverse bedrijfsbeheeradviesbureaus",
    "sg:phone":"+32 2 721 32 49",
    "sg:postcode":"1932",
    "sg:province":"Vlaams-Brabant",
    "wof:name":"Sc2 Consultants",
    "wof:placetype":"venue"
},
  "geometry": {"coordinates":[4.4544582367,50.874835968],"type":"Point"}
}