{
  "type": "Feature",
  "properties": {
    "iso:country":"BE",
    "sg:address":"Achiel Cleynhenslaan 44",
    "sg:city":"Keerbergen",
    "sg:orig_category":"V\u00e9t\u00e9rinaires",
    "sg:phone":"+32 15 23 55 55",
    "sg:postcode":"3140",
    "sg:province":"Vlaams-Brabant",
    "wof:name":"Johan Vanhemelryck",
    "wof:placetype":"venue"
},
  "geometry": {"coordinates":[4.6529011726,51.0063858032],"type":"Point"}
}