{
  "type": "Feature",
  "properties": {
    "addr:full":"Bld De Smet De Naeyer 145 Jette/jette Bruxelles-Capitale 1090",
    "addr:housenumber":"145",
    "addr:postcode":"1090",
    "addr:street":"Bld De Smet De Naeyer",
    "iso:country":"BE",
    "sg:address":"Bld De Smet De Naeyer 145",
    "sg:city":"Jette/jette",
    "sg:orig_category":"Biblioth\u00e8ques and archives publiques. Organisations and associations",
    "sg:phone":"+32 2 426 64 39",
    "sg:postcode":"1090",
    "sg:province":"Bruxelles-Capitale",
    "wof:name":"Jouons En Famille",
    "wof:placetype":"venue"
},
  "geometry": {"coordinates":[4.328359127,50.8746261597],"type":"Point"}
}