{
  "type": "Feature",
  "properties": {
    "iso:country":"BE",
    "sg:address":"Tramstraat 28",
    "sg:city":"Destelbergen",
    "sg:orig_category":"Boucheries",
    "sg:phone":"+32 9 231 32 53",
    "sg:postcode":"9070",
    "sg:province":"Oost-Vlaanderen",
    "wof:name":"Danny Auman",
    "wof:placetype":"venue"
},
  "geometry": {"coordinates":[3.8019111156,51.0303916931],"type":"Point"}
}