{
  "type": "Feature",
  "properties": {
    "iso:country":"BE",
    "sg:address":"Veldstraat 46",
    "sg:city":"Gand",
    "sg:orig_category":"V\u00eatements",
    "sg:phone":"+32 9 233 89 42",
    "sg:postcode":"9000",
    "sg:province":"Oost-Vlaanderen",
    "wof:name":"Cactus",
    "wof:placetype":"venue"
},
  "geometry": {"coordinates":[3.7219929695,51.0520019531],"type":"Point"}
}