{
  "type": "Feature",
  "properties": {
    "addr:full":"Arkstraat 49 Meeuwen-gruitrode Limburg 3670",
    "addr:housenumber":"49",
    "addr:postcode":"3670",
    "addr:street":"Arkstraat",
    "iso:country":"BE",
    "sg:address":"Arkstraat 49",
    "sg:city":"Meeuwen-gruitrode",
    "sg:orig_category":"Gespecialiseerde residenti\u00eble bouw Woningbouw",
    "sg:phone":"+32 11 79 34 57",
    "sg:postcode":"3670",
    "sg:province":"Limburg",
    "wof:name":"Ronny Janssen",
    "wof:placetype":"venue"
},
  "geometry": {"coordinates":[5.5284500122,51.0941047668],"type":"Point"}
}