{
  "type": "Feature",
  "properties": {
    "addr:full":"Kerkveld 20 Berlare Oost-Vlaanderen 9290",
    "addr:housenumber":"20",
    "addr:postcode":"9290",
    "addr:street":"Kerkveld",
    "iso:country":"BE",
    "sg:address":"Kerkveld 20",
    "sg:city":"Berlare",
    "sg:orig_category":"Rev\u00eatements pour sols and murs",
    "sg:phone":"+32 52 42 68 99",
    "sg:postcode":"9290",
    "sg:province":"Oost-Vlaanderen",
    "wof:name":"Van Langenhove Ulrich",
    "wof:placetype":"venue"
},
  "geometry": {"coordinates":[4.0016617775,51.0277862549],"type":"Point"}
}