{
  "type": "Feature",
  "properties": {
    "addr:full":"Alsembergse Steenweg 303b3/1 Vorst/forest Bruxelles-Capitale 1190",
    "addr:housenumber":"303b3 / 1",
    "addr:postcode":"1190",
    "addr:street":"Alsembergse Steenweg;/ Forest",
    "iso:country":"BE",
    "sg:address":"Alsembergse Steenweg 303b3/1",
    "sg:city":"Vorst/forest",
    "sg:orig_category":"Technische studies and ingenieursactiviteiten",
    "sg:phone":"+32 2 343 83 00",
    "sg:postcode":"1190",
    "sg:province":"Bruxelles-Capitale",
    "wof:name":"Setecsa & Lipe",
    "wof:placetype":"venue"
},
  "geometry": {"coordinates":[4.3401341438,50.8170890808],"type":"Point"}
}