{
  "type": "Feature",
  "properties": {
    "iso:country":"BE",
    "sg:address":"Het Geleeg 48",
    "sg:city":"Wuustwezel",
    "sg:orig_category":"Non-Classified Establishments",
    "sg:phone":"+32 3 633 09 48",
    "sg:postcode":"2990",
    "sg:province":"Antwerpen",
    "wof:name":"Raitech Bvba",
    "wof:placetype":"venue"
},
  "geometry": {"coordinates":[4.5500278473,51.3617286682],"type":"Point"}
}