{
  "type": "Feature",
  "properties": {
    "iso:country":"BE",
    "sg:address":"Gouverneur Verwilghensingel Z/n",
    "sg:city":"Hasselt",
    "sg:classifiers":[
        {
            "category":"Sports & Exercise",
            "subcategory":"Sports Center",
            "type":"Entertainment"
        }
    ],
    "sg:phone":"+32 11 23 94 55",
    "sg:postcode":"3500",
    "sg:province":"Limburg",
    "sg:tags":[
        "terrain",
        "hors",
        "de",
        "installation",
        "sportifs"
    ],
    "wof:name":"Klimmuur Stad Hasselt",
    "wof:placetype":"venue"
},
  "geometry": {"coordinates":[5.3597159386,50.9282722473],"type":"Point"}
}