{
  "type": "Feature",
  "properties": {
    "addr:full":"Rue Tenbosch 102 Elsene/ixelles Bruxelles-Capitale 1050",
    "addr:housenumber":"102",
    "addr:postcode":"1050",
    "addr:street":"Rue Tenbosch",
    "iso:country":"BE",
    "sg:address":"Rue Tenbosch 102",
    "sg:city":"Elsene/ixelles",
    "sg:classifiers":[
        {
            "category":"Professional",
            "subcategory":"Art Services",
            "type":"Services"
        }
    ],
    "sg:phone":"+32 2 346 64 88",
    "sg:postcode":"1050",
    "sg:province":"Bruxelles-Capitale",
    "sg:tags":[
        "designer",
        "cr\u00e9ateurs"
    ],
    "wof:name":"Perciers Paris",
    "wof:placetype":"venue"
},
  "geometry": {"coordinates":[4.3616061211,50.8210487366],"type":"Point"}
}