{
  "type": "Feature",
  "properties": {
    "addr:full":"Rue Jules Destr\u00c9e 309 Quaregnon Hainaut 7390",
    "addr:housenumber":"309",
    "addr:postcode":"7390",
    "addr:street":"Rue Jules Destre\u0301E",
    "iso:country":"BE",
    "sg:address":"Rue Jules Destr\u00c9e 309",
    "sg:city":"Quaregnon",
    "sg:orig_category":"Benzinestations and brandstoffen",
    "sg:phone":"+32 65 78 64 59",
    "sg:postcode":"7390",
    "sg:province":"Hainaut",
    "wof:name":"Q8",
    "wof:placetype":"venue"
},
  "geometry": {"coordinates":[3.8601500988,50.4436073303],"type":"Point"}
}