{
  "type": "Feature",
  "properties": {
    "addr:full":"Wannegem-ledestraat 19 Kruishoutem Oost-Vlaanderen 9772",
    "addr:housenumber":"19",
    "addr:postcode":"9772",
    "addr:street":"Wannegem-Ledestraat",
    "iso:country":"BE",
    "sg:address":"Wannegem-ledestraat 19",
    "sg:city":"Kruishoutem",
    "sg:orig_category":"Charpentes and couvertures",
    "sg:phone":"+32 9 383 65 51",
    "sg:postcode":"9772",
    "sg:province":"Oost-Vlaanderen",
    "wof:name":"Yvan De Visscher",
    "wof:placetype":"venue"
},
  "geometry": {"coordinates":[3.5554940701,50.8903236389],"type":"Point"}
}