{
  "type": "Feature",
  "properties": {
    "addr:full":"Am Waisenbuschchen 22 Eupen/eupen Li\u00e8ge 4700",
    "addr:housenumber":"22",
    "addr:postcode":"4700",
    "addr:street":"Am Waisenbuschchen",
    "iso:country":"BE",
    "sg:address":"Am Waisenbuschchen 22",
    "sg:city":"Eupen/eupen",
    "sg:orig_category":"Bloemen and planten",
    "sg:phone":"+32 87 74 20 22",
    "sg:postcode":"4700",
    "sg:province":"Li\u00e8ge",
    "wof:name":"Brigitte Den Tandt",
    "wof:placetype":"venue"
},
  "geometry": {"coordinates":[6.0261797905,50.6208190918],"type":"Point"}
}