{
  "type": "Feature",
  "properties": {
    "addr:full":"Auguste Demaeghtlaan 40 Halle Vlaams-Brabant 1500",
    "addr:housenumber":"40",
    "addr:postcode":"1500",
    "addr:street":"Demaeghtlaan",
    "iso:country":"BE",
    "sg:address":"Auguste Demaeghtlaan 40",
    "sg:city":"Halle",
    "sg:orig_category":"Enseignement maternel and primaire",
    "sg:phone":"+32 2 356 55 63",
    "sg:postcode":"1500",
    "sg:province":"Vlaams-Brabant",
    "wof:name":"Basisschool",
    "wof:placetype":"venue"
},
  "geometry": {"coordinates":[4.2368369102,50.7394714355],"type":"Point"}
}