{
  "type": "Feature",
  "properties": {
    "addr:full":"Groenstraat 71 Vilvoorde Vlaams-Brabant 1800",
    "addr:housenumber":"71",
    "addr:postcode":"1800",
    "addr:street":"Groenstraat",
    "iso:country":"BE",
    "sg:address":"Groenstraat 71",
    "sg:city":"Vilvoorde",
    "sg:classifiers":[
        {
            "category":"Organizations",
            "subcategory":"Political Organization",
            "type":"Services"
        }
    ],
    "sg:phone":"+32 2 252 39 96",
    "sg:postcode":"1800",
    "sg:province":"Vlaams-Brabant",
    "sg:tags":[
        "charitable",
        "organisation"
    ],
    "wof:name":"Poudri\u00e8re Gemeenschap Vzw",
    "wof:placetype":"venue"
},
  "geometry": {"coordinates":[4.4314069748,50.931098938],"type":"Point"}
}