{
  "type": "Feature",
  "properties": {
    "iso:country":"BE",
    "sg:address":"Rue Molinvaux 136",
    "sg:city":"Li\u00e8ge 1",
    "sg:classifiers":[
        {
            "category":"Professional",
            "subcategory":"Testing Lab",
            "type":"Services"
        }
    ],
    "sg:phone":"+32 4 226 44 13",
    "sg:postcode":"4000",
    "sg:province":"Li\u00e8ge",
    "sg:tags":[
        "chemist"
    ],
    "wof:name":"Ista",
    "wof:placetype":"venue"
},
  "geometry": {"coordinates":[5.5533800125,50.6530647278],"type":"Point"}
}