{
  "type": "Feature",
  "properties": {
    "addr:full":"Rue Edouard Colson 73 Ans Li\u00e8ge 4431",
    "addr:housenumber":"73",
    "addr:postcode":"4431",
    "addr:street":"Rue Edouard Colson",
    "iso:country":"BE",
    "sg:address":"Rue Edouard Colson 73",
    "sg:city":"Ans",
    "sg:orig_category":"D\u00e9taillants en pi\u00e8ces and accessoires de voitures",
    "sg:phone":"+32 4 247 44 24",
    "sg:postcode":"4431",
    "sg:province":"Li\u00e8ge",
    "wof:name":"Espace-mobile",
    "wof:placetype":"venue"
},
  "geometry": {"coordinates":[5.5036468506,50.6667480469],"type":"Point"}
}