{
  "type": "Feature",
  "properties": {
    "addr:full":"Kuringenstraat 11 Hasselt Limburg 3511",
    "addr:housenumber":"11",
    "addr:postcode":"3511",
    "addr:street":"Kuringenstraat",
    "iso:country":"BE",
    "sg:address":"Kuringenstraat 11",
    "sg:city":"Hasselt",
    "sg:orig_category":"Avocats and conseillers juridiques",
    "sg:phone":"+32 11 25 06 88",
    "sg:postcode":"3511",
    "sg:province":"Limburg",
    "wof:name":"Bureau Corthouts Adv.",
    "wof:placetype":"venue"
},
  "geometry": {"coordinates":[5.29829216,50.9385414124],"type":"Point"}
}