{
  "type": "Feature",
  "properties": {
    "addr:full":"Roomstraat 19 Lokeren Oost-Vlaanderen 9160",
    "addr:housenumber":"19",
    "addr:postcode":"9160",
    "addr:street":"Roomstraat",
    "iso:country":"BE",
    "sg:address":"Roomstraat 19",
    "sg:city":"Lokeren",
    "sg:classifiers":[
        {
            "category":"Shopping",
            "subcategory":"Bicycles & Sporting Goods",
            "type":"Retail Goods"
        }
    ],
    "sg:phone":"+32 9 348 11 73",
    "sg:postcode":"9160",
    "sg:province":"Oost-Vlaanderen",
    "sg:tags":[
        "article",
        "de",
        "sport",
        "camping"
    ],
    "wof:name":"Caravelle Sport",
    "wof:placetype":"venue"
},
  "geometry": {"coordinates":[3.9875791073,51.1027297974],"type":"Point"}
}