{
  "type": "Feature",
  "properties": {
    "iso:country":"BE",
    "sg:address":"115",
    "sg:city":"Rue Arthur Pouplier 7190 Ecaussinnes",
    "sg:classifiers":[
        {
            "category":"Shopping",
            "subcategory":"Hobbies, Toys, & Games",
            "type":"Retail Goods"
        }
    ],
    "sg:phone":"+32 67 44 41 80",
    "sg:postcode":"115",
    "sg:tags":[
        "product",
        "miscellaneous",
        "entertainment"
    ],
    "wof:name":"Entreprises Generales Romain Sprl",
    "wof:placetype":"venue"
},
  "geometry": {"coordinates":[4.1515097618,50.562664032],"type":"Point"}
}