{
  "type": "Feature",
  "properties": {
    "iso:country":"BE",
    "sg:address":"Avenue De La M\u00c9trologie 2",
    "sg:city":"Brussel/bruxelles",
    "sg:orig_category":"Pr\u00eats hypoth\u00e9caires and cr\u00e9dits immobiliers. Assurances. Assurances habitation compagnies. Assurance",
    "sg:phone":"+32 2 244 22 11",
    "sg:postcode":"1130",
    "sg:province":"Bruxelles-Capitale",
    "wof:name":"Corona",
    "wof:placetype":"venue"
},
  "geometry": {"coordinates":[4.4294981956,50.8939285278],"type":"Point"}
}