{
  "type": "Feature",
  "properties": {
    "addr:full":"Rue Bosquet 47 Box 35 Bruxelles (saint-gilles) Bruxelles-Capitale 1060",
    "addr:housenumber":"47 box 35",
    "addr:postcode":"1060",
    "addr:street":"Rue Bosquet",
    "iso:country":"BE",
    "sg:address":"Rue Bosquet 47 Box 35",
    "sg:city":"Bruxelles (saint-gilles)",
    "sg:classifiers":[
        {
            "category":"Health Services",
            "subcategory":"Doctor",
            "type":"Services"
        }
    ],
    "sg:phone":"+32 2 537 05 89",
    "sg:postcode":"1060",
    "sg:province":"Bruxelles-Capitale",
    "sg:tags":[
        "medicinephysicians",
        "surgeon"
    ],
    "wof:name":"Foucart A",
    "wof:placetype":"venue"
},
  "geometry": {"coordinates":[4.353823185,50.8336334229],"type":"Point"}
}