{
  "type": "Feature",
  "properties": {
    "addr:full":"Avenue De La Plante 54b6 Namur Namur 5000",
    "addr:housenumber":"54b6",
    "addr:postcode":"5000",
    "addr:street":"Avenue De La Plante",
    "iso:country":"BE",
    "sg:address":"Avenue De La Plante 54b6",
    "sg:city":"Namur",
    "sg:orig_category":"Sportclubs",
    "sg:phone":"+32 81 22 80 59",
    "sg:postcode":"5000",
    "sg:province":"Namur",
    "wof:name":"R.h.c. Namurois",
    "wof:placetype":"venue"
},
  "geometry": {"coordinates":[4.8605279922,50.4530754089],"type":"Point"}
}