{
  "type": "Feature",
  "properties": {
    "addr:full":"Markt 38 Gavere Oost-Vlaanderen 9890",
    "addr:housenumber":"38",
    "addr:postcode":"9890",
    "addr:street":"Markt",
    "iso:country":"BE",
    "sg:address":"Markt 38",
    "sg:city":"Gavere",
    "sg:orig_category":"Eclairage et \u00e9quipements du foyer",
    "sg:phone":"+32 9 384 13 84",
    "sg:postcode":"9890",
    "sg:province":"Oost-Vlaanderen",
    "wof:name":"Nestor Demanet",
    "wof:placetype":"venue"
},
  "geometry": {"coordinates":[3.6593298912,50.9298744202],"type":"Point"}
}