{
  "type": "Feature",
  "properties": {
    "iso:country":"BE",
    "sg:address":"Hauptstrasse 53-55",
    "sg:city":"Sankt Vith/saint-vith",
    "sg:orig_category":"Meubelzaken, woning- and keukeninrichting Verlichting and huishoudartikelen",
    "sg:phone":"+32 80 22 80 99",
    "sg:postcode":"4780",
    "sg:province":"Li\u00e8ge",
    "wof:name":"Lentz-linnartz",
    "wof:placetype":"venue"
},
  "geometry": {"coordinates":[6.0429549217,50.3349761963],"type":"Point"}
}