{
  "type": "Feature",
  "properties": {
    "addr:full":"Rue Des Fran\u00e7ais 389 Ans Li\u00e8ge 4430",
    "addr:housenumber":"389",
    "addr:postcode":"4430",
    "addr:street":"Rue Des Franc\u0327Ais",
    "iso:country":"BE",
    "sg:address":"Rue Des Fran\u00e7ais 389",
    "sg:city":"Ans",
    "sg:classifiers":[
        {
            "category":"Autos & Motor Vehicles",
            "subcategory":"Boat Sales",
            "type":"Retail Goods"
        }
    ],
    "sg:phone":"+32 4 263 66 69",
    "sg:postcode":"4430",
    "sg:province":"Li\u00e8ge",
    "sg:tags":[
        "automobile",
        "sunroof",
        "-",
        "roof"
    ],
    "wof:name":"Autovitre & Glascar",
    "wof:placetype":"venue"
},
  "geometry": {"coordinates":[5.5383481979,50.6665039062],"type":"Point"}
}