{
  "type": "Feature",
  "properties": {
    "addr:full":"Jeugdstraat 18 Hamont-achel Limburg 3930",
    "addr:housenumber":"18",
    "addr:postcode":"3930",
    "addr:street":"Jeugdstraat",
    "iso:country":"BE",
    "sg:address":"Jeugdstraat 18",
    "sg:city":"Hamont-achel",
    "sg:orig_category":"Woningbouw",
    "sg:phone":"+32 11 62 13 38",
    "sg:postcode":"3930",
    "sg:province":"Limburg",
    "wof:name":"Braeken T",
    "wof:placetype":"venue"
},
  "geometry": {"coordinates":[5.5450549126,51.2511863708],"type":"Point"}
}