{
  "type": "Feature",
  "properties": {
    "iso:country":"BE",
    "sg:address":"Koning Albertlaan 62",
    "sg:city":"Maaseik",
    "sg:orig_category":"M\u00e9decins and sp\u00e9cialistes",
    "sg:phone":"+32 89 56 85 41",
    "sg:postcode":"3680",
    "sg:province":"Limburg",
    "wof:name":"W. Smits",
    "wof:placetype":"venue"
},
  "geometry": {"coordinates":[5.7824559212,51.0972862244],"type":"Point"}
}