{
  "type": "Feature",
  "properties": {
    "addr:full":"Zoning Industriel 4 Chimay Hainaut 6464",
    "addr:housenumber":"4",
    "addr:postcode":"6464",
    "addr:street":"Zoning Industriel",
    "iso:country":"BE",
    "sg:address":"Zoning Industriel 4",
    "sg:city":"Chimay",
    "sg:orig_category":"Centres sportifs. Installations and terrains de sport hors centres sportifs",
    "sg:phone":"+32 60 21 44 37",
    "sg:postcode":"6464",
    "sg:province":"Hainaut",
    "wof:name":"Scanlog",
    "wof:placetype":"venue"
},
  "geometry": {"coordinates":[4.3209447861,50.0234336853],"type":"Point"}
}