{
  "type": "Feature",
  "properties": {
    "addr:full":"Avelgemstraat 39 Zwevegem West-Vlaanderen 8550",
    "addr:housenumber":"39",
    "addr:postcode":"8550",
    "addr:street":"Avelgemstraat",
    "iso:country":"BE",
    "sg:address":"Avelgemstraat 39",
    "sg:city":"Zwevegem",
    "sg:orig_category":"V\u00eatements sur mesure Fab",
    "sg:phone":"+32 56 75 57 92",
    "sg:postcode":"8550",
    "sg:province":"West-Vlaanderen",
    "wof:name":"Henri Prevost",
    "wof:placetype":"venue"
},
  "geometry": {"coordinates":[3.3350260258,50.8107223511],"type":"Point"}
}