{
  "type": "Feature",
  "properties": {
    "iso:country":"BE",
    "sg:address":"Boulevard D'avroy 18",
    "sg:city":"Li\u00c8ge",
    "sg:orig_category":"V\u00eatements pour Dames. Biens d'occasion",
    "sg:phone":"+32 4 223 70 78",
    "sg:postcode":"4000",
    "sg:province":"Li\u00e8ge",
    "wof:name":"Maison La Gerabotte",
    "wof:placetype":"venue"
},
  "geometry": {"coordinates":[5.568253994,50.6392173767],"type":"Point"}
}