{
  "type": "Feature",
  "properties": {
    "iso:country":"BE",
    "sg:address":"Rue Fran\u00c7ois Dons 21",
    "sg:city":"Elsene/ixelles",
    "sg:orig_category":"Boucheries",
    "sg:phone":"+32 2 647 10 67",
    "sg:postcode":"1050",
    "sg:province":"Bruxelles-Capitale",
    "wof:name":"Benedict Van Parys",
    "wof:placetype":"venue"
},
  "geometry": {"coordinates":[4.3897089958,50.8115959167],"type":"Point"}
}