{
  "type": "Feature",
  "properties": {
    "addr:full":"Gemeenteplein 11 Melle Oost-Vlaanderen 9090",
    "addr:housenumber":"11",
    "addr:postcode":"9090",
    "addr:street":"Gemeenteplein",
    "iso:country":"BE",
    "sg:address":"Gemeenteplein 11",
    "sg:city":"Melle",
    "sg:classifiers":[
        {
            "category":"Shopping",
            "subcategory":"Clothing, Apparel, & Fashions",
            "type":"Retail Goods"
        }
    ],
    "sg:phone":"+32 9 252 36 65",
    "sg:postcode":"9090",
    "sg:province":"Oost-Vlaanderen",
    "sg:tags":[
        "underwear",
        "lingerie",
        "-"
    ],
    "wof:name":"Amelie",
    "wof:placetype":"venue"
},
  "geometry": {"coordinates":[3.7991058826,51.0028495789],"type":"Point"}
}