{
  "type": "Feature",
  "properties": {
    "iso:country":"BE",
    "sg:address":"Rue Des Haies 16",
    "sg:city":"Arlon",
    "sg:classifiers":[
        {
            "category":"Professional",
            "subcategory":"Computer Services",
            "type":"Services"
        }
    ],
    "sg:phone":"+32 63 22 34 44",
    "sg:postcode":"6700",
    "sg:province":"Luxembourg",
    "sg:tags":[
        "-",
        "processing",
        "data",
        "software"
    ],
    "wof:name":"Image Filer Sprl",
    "wof:placetype":"venue"
},
  "geometry": {"coordinates":[5.8147778511,49.6872024536],"type":"Point"}
}