{
  "type": "Feature",
  "properties": {
    "addr:full":"Verrekijker 15 Wingene West-Vlaanderen 8750",
    "addr:housenumber":"15",
    "addr:postcode":"8750",
    "addr:street":"Verrekijker",
    "iso:country":"BE",
    "sg:address":"Verrekijker 15",
    "sg:city":"Wingene",
    "sg:classifiers":[
        {
            "category":"Retail",
            "subcategory":"Car Wash",
            "type":"Services"
        }
    ],
    "sg:phone":"+32 51 69 40 20",
    "sg:postcode":"8750",
    "sg:province":"West-Vlaanderen",
    "sg:tags":[
        "system",
        "accessory"
    ],
    "wof:name":"Akwa Plus B.v.b.a.",
    "wof:placetype":"venue"
},
  "geometry": {"coordinates":[3.2825009823,51.0533905029],"type":"Point"}
}