{
  "type": "Feature",
  "properties": {
    "iso:country":"BE",
    "sg:address":"Burchtdam 15",
    "sg:city":"Ninove",
    "sg:classifiers":[
        {
            "category":"Food & Beverages",
            "subcategory":"Fruits & Vegetables",
            "type":"Retail Goods"
        }
    ],
    "sg:phone":"+32 54 32 63 20",
    "sg:postcode":"9400",
    "sg:province":"Oost-Vlaanderen",
    "sg:tags":[
        "l\u00e9gumes"
    ],
    "wof:name":"Mattevel",
    "wof:placetype":"venue"
},
  "geometry": {"coordinates":[4.0228710175,50.8343582153],"type":"Point"}
}