{
  "type": "Feature",
  "properties": {
    "iso:country":"BE",
    "sg:address":"De Merodestraat 89",
    "sg:city":"Grimbergen",
    "sg:classifiers":[
        {
            "category":"Utilities",
            "subcategory":"Refuse",
            "type":"Services"
        }
    ],
    "sg:phone":"+32 2 253 23 68",
    "sg:postcode":"1850",
    "sg:province":"Vlaams-Brabant",
    "sg:tags":[
        "boiler",
        "-",
        "heating",
        "steam"
    ],
    "wof:name":"Serkobras Nv",
    "wof:placetype":"venue"
},
  "geometry": {"coordinates":[4.3683099747,50.9273910522],"type":"Point"}
}