{
  "type": "Feature",
  "properties": {
    "iso:country":"BE",
    "sg:address":"Rue De Mons 47",
    "sg:city":"Soignies",
    "sg:orig_category":"Dameskledingzaken Herenkledingzaken Lingerie and ondergoed",
    "sg:phone":"+32 67 33 30 73",
    "sg:postcode":"7060",
    "sg:province":"Hainaut",
    "wof:name":"Maison Au Mimosa",
    "wof:placetype":"venue"
},
  "geometry": {"coordinates":[4.0714569092,50.5775871277],"type":"Point"}
}