{
  "type": "Feature",
  "properties": {
    "addr:full":"Ringlaan 1 Menen West-Vlaanderen 8930",
    "addr:housenumber":"1",
    "addr:postcode":"8930",
    "addr:street":"Ringlaan",
    "iso:country":"BE",
    "sg:address":"Ringlaan 1",
    "sg:city":"Menen",
    "sg:classifiers":[
        {
            "category":"Building & Trades",
            "subcategory":"Plumbing",
            "type":"Services"
        }
    ],
    "sg:phone":"+32 56 53 21 37",
    "sg:postcode":"8930",
    "sg:province":"West-Vlaanderen",
    "sg:tags":[
        "pipe",
        "cardboard",
        "-"
    ],
    "wof:name":"Ecotube Nv",
    "wof:placetype":"venue"
},
  "geometry": {"coordinates":[3.0839180946,50.8001823425],"type":"Point"}
}