{
  "type": "Feature",
  "properties": {
    "iso:country":"BE",
    "sg:address":"Rumbeeksesteenweg 127",
    "sg:city":"Roeselare",
    "sg:classifiers":[
        {
            "category":"Professional",
            "subcategory":"Testing Lab",
            "type":"Services"
        }
    ],
    "sg:phone":"+32 51 20 01 83",
    "sg:postcode":"8800",
    "sg:province":"West-Vlaanderen",
    "sg:tags":[
        "chemist"
    ],
    "wof:name":"Verbelen",
    "wof:placetype":"venue"
},
  "geometry": {"coordinates":[3.1300070286,50.9399414062],"type":"Point"}
}