{
  "type": "Feature",
  "properties": {
    "addr:full":"Mottestraat 22 Meise Vlaams-Brabant 1861",
    "addr:housenumber":"22",
    "addr:postcode":"1861",
    "addr:street":"Mottestraat",
    "iso:country":"BE",
    "sg:address":"Mottestraat 22",
    "sg:city":"Meise",
    "sg:orig_category":"Woningbouw",
    "sg:phone":"+32 2 269 12 59",
    "sg:postcode":"1861",
    "sg:province":"Vlaams-Brabant",
    "wof:name":"Wolbouw",
    "wof:placetype":"venue"
},
  "geometry": {"coordinates":[4.3070459366,50.9522285461],"type":"Point"}
}