{
  "type": "Feature",
  "properties": {
    "addr:full":"Zeedijk 25 De Panne West-Vlaanderen 8660",
    "addr:housenumber":"25",
    "addr:postcode":"8660",
    "addr:street":"Zeedijk",
    "iso:country":"BE",
    "sg:address":"Zeedijk 25",
    "sg:city":"De Panne",
    "sg:classifiers":[
        {
            "category":"Fast Food",
            "type":"Food & Drink"
        }
    ],
    "sg:phone":"+32 58 41 38 62",
    "sg:postcode":"8660",
    "sg:province":"West-Vlaanderen",
    "sg:tags":[
        "fried",
        "stand",
        "potato"
    ],
    "wof:name":"Quick Snack",
    "wof:placetype":"venue"
},
  "geometry": {"coordinates":[2.5883779526,51.1026153564],"type":"Point"}
}