{
  "type": "Feature",
  "properties": {
    "addr:full":"Chauss\u00e9e De Bruxelles 236a Tournai Hainaut 7500",
    "addr:housenumber":"236a",
    "addr:postcode":"7500",
    "addr:street":"Chausse\u0301E De Bruxelles",
    "iso:country":"BE",
    "sg:address":"Chauss\u00e9e De Bruxelles 236a",
    "sg:city":"Tournai",
    "sg:classifiers":[
        {
            "category":"Autos & Motor Vehicles",
            "subcategory":"Automobile Sales",
            "type":"Retail Goods"
        }
    ],
    "sg:phone":"+32 69 23 68 10",
    "sg:postcode":"7500",
    "sg:province":"Hainaut",
    "sg:tags":[
        "car",
        "used",
        "-"
    ],
    "wof:name":"Xavier Auto",
    "wof:placetype":"venue"
},
  "geometry": {"coordinates":[3.4399039745,50.6004257202],"type":"Point"}
}