{
  "type": "Feature",
  "properties": {
    "iso:country":"BE",
    "sg:address":"Avenue Herbert Hoover 259",
    "sg:city":"Sint-lambrechts-woluwe/woluwe-saint-lambert",
    "sg:orig_category":"Pain, p\u00e2tisseries and confiseries",
    "sg:phone":"+32 2 735 45 76",
    "sg:postcode":"1200",
    "sg:province":"Bruxelles-Capitale",
    "wof:name":"Boulangerie Allemeersch",
    "wof:placetype":"venue"
},
  "geometry": {"coordinates":[4.4110178947,50.8493843079],"type":"Point"}
}