{
  "type": "Feature",
  "properties": {
    "addr:full":"Riddersstraat 5 Brugge West-Vlaanderen 8000",
    "addr:housenumber":"5",
    "addr:postcode":"8000",
    "addr:street":"Riddersstraat",
    "iso:country":"BE",
    "sg:address":"Riddersstraat 5",
    "sg:city":"Brugge",
    "sg:classifiers":[
        {
            "category":"Organizations",
            "subcategory":"Community Association",
            "type":"Services"
        }
    ],
    "sg:phone":"+32 50 33 79 42",
    "sg:postcode":"8000",
    "sg:province":"West-Vlaanderen",
    "sg:tags":[
        "organisation"
    ],
    "wof:name":"J.a. Octopus",
    "wof:placetype":"venue"
},
  "geometry": {"coordinates":[3.2285749912,51.2106246948],"type":"Point"}
}