{
  "type": "Feature",
  "properties": {
    "addr:full":"Chauss\u00c9e Des Forges 39 Marchin Li\u00e8ge 4570",
    "addr:housenumber":"39",
    "addr:postcode":"4570",
    "addr:street":"Chausse\u0301E Des Forges",
    "iso:country":"BE",
    "sg:address":"Chauss\u00c9e Des Forges 39",
    "sg:city":"Marchin",
    "sg:orig_category":"Herstellingen and onderhoud van auto's",
    "sg:phone":"+32 85 24 01 78",
    "sg:postcode":"4570",
    "sg:province":"Li\u00e8ge",
    "wof:name":"Jean-michel Deman",
    "wof:placetype":"venue"
},
  "geometry": {"coordinates":[5.2374668121,50.4967803955],"type":"Point"}
}