{
  "type": "Feature",
  "properties": {
    "addr:full":"Rue Des Culots 9 Chapelle-lez-herlaimont (godarville) Hainaut 7160",
    "addr:housenumber":"9",
    "addr:postcode":"7160",
    "addr:street":"Rue Des Culots;Hainaut",
    "iso:country":"BE",
    "sg:address":"Rue Des Culots 9",
    "sg:city":"Chapelle-lez-herlaimont (godarville)",
    "sg:classifiers":[
        {
            "category":"Health Services",
            "subcategory":"Health Practitioner",
            "type":"Services"
        }
    ],
    "sg:phone":"+32 64 44 26 76",
    "sg:postcode":"7160",
    "sg:province":"Hainaut",
    "sg:tags":[
        "physiotherapist"
    ],
    "wof:name":"Gillet Nathalie",
    "wof:placetype":"venue"
},
  "geometry": {"coordinates":[4.2881641388,50.4963226318],"type":"Point"}
}