{
  "type": "Feature",
  "properties": {
    "addr:full":"Rue Schimtz 18 Koekelberg Bruxelles-Capitale 1081",
    "addr:housenumber":"18",
    "addr:postcode":"1081",
    "addr:street":"Rue Schimtz",
    "iso:country":"BE",
    "sg:address":"Rue Schimtz 18",
    "sg:city":"Koekelberg",
    "sg:orig_category":"Agences d'exp\u00e9dition",
    "sg:phone":"+32 2 414 21 41",
    "sg:postcode":"1081",
    "sg:province":"Bruxelles-Capitale",
    "wof:name":"Danydan Trading Consult",
    "wof:placetype":"venue"
},
  "geometry": {"coordinates":[4.3319959641,50.8575401306],"type":"Point"}
}