{
  "type": "Feature",
  "properties": {
    "addr:full":"Jules Van Biesbroeckstraat 7 Gent (gentbrugge) Oost-Vlaanderen 9050",
    "addr:housenumber":"7",
    "addr:postcode":"9050",
    "addr:street":"Jules Van Biesbroeckstraat",
    "iso:country":"BE",
    "sg:address":"Jules Van Biesbroeckstraat 7",
    "sg:city":"Gent (gentbrugge)",
    "sg:classifiers":[
        {
            "category":"Health Services",
            "subcategory":"Doctor",
            "type":"Services"
        }
    ],
    "sg:phone":"+32 9 231 97 84",
    "sg:postcode":"9050",
    "sg:province":"Oost-Vlaanderen",
    "sg:tags":[
        "medicinephysicians",
        "surgeon"
    ],
    "wof:name":"De Laat M",
    "wof:placetype":"venue"
},
  "geometry": {"coordinates":[3.7658600807,51.0467643738],"type":"Point"}
}