{
  "type": "Feature",
  "properties": {
    "iso:country":"BE",
    "sg:address":"Boomstraat 88",
    "sg:city":"Bornem",
    "sg:classifiers":[
        {
            "category":"Home & Garden",
            "subcategory":"Home Furnishings",
            "type":"Retail Goods"
        }
    ],
    "sg:phone":"+32 3 899 41 21",
    "sg:postcode":"2880",
    "sg:province":"Antwerpen",
    "sg:tags":[
        "interior",
        "decoration"
    ],
    "wof:name":"Maes Interieur",
    "wof:placetype":"venue"
},
  "geometry": {"coordinates":[4.2328572273,51.096950531],"type":"Point"}
}