{
  "type": "Feature",
  "properties": {
    "addr:full":"Bergstrasse 142 Lontzen/lontzen Li\u00e8ge 4710",
    "addr:housenumber":"142",
    "addr:postcode":"4710",
    "addr:street":"Bergstrasse",
    "iso:country":"BE",
    "sg:address":"Bergstrasse 142",
    "sg:city":"Lontzen/lontzen",
    "sg:orig_category":"Rundveehouders",
    "sg:phone":"+32 87 65 63 77",
    "sg:postcode":"4710",
    "sg:province":"Li\u00e8ge",
    "wof:name":"Hildegard Ramakers",
    "wof:placetype":"venue"
},
  "geometry": {"coordinates":[6.0170907974,50.6889762878],"type":"Point"}
}