{
  "type": "Feature",
  "properties": {
    "addr:full":"Sint-sebastiaanslaan 41-11 Kortrijk West-Vlaanderen 8500",
    "addr:postcode":"41-11;8500",
    "iso:country":"BE",
    "sg:address":"Sint-sebastiaanslaan 41-11",
    "sg:city":"Kortrijk",
    "sg:classifiers":[
        {
            "category":"Real Estate",
            "subcategory":"Architect",
            "type":"Services"
        }
    ],
    "sg:phone":"+32 56 21 39 09",
    "sg:postcode":"8500",
    "sg:province":"West-Vlaanderen",
    "wof:name":"Descamps S",
    "wof:placetype":"venue"
},
  "geometry": {"coordinates":[3.2629189491,50.8209991455],"type":"Point"}
}