{
  "type": "Feature",
  "properties": {
    "iso:country":"BE",
    "sg:address":"Avenue De Grunne 99",
    "sg:city":"Wezembeek-oppem",
    "sg:orig_category":"R\u00e9alisation de programmes and logiciels. Ordinateurs and \u00e9quipement informatique",
    "sg:phone":"+32 2 731 47 98",
    "sg:postcode":"1970",
    "sg:province":"Vlaams-Brabant",
    "wof:name":"Infor-analyse",
    "wof:placetype":"venue"
},
  "geometry": {"coordinates":[4.4767899513,50.8386993408],"type":"Point"}
}