{
  "type": "Feature",
  "properties": {
    "addr:full":"Avenue Georges Henri 293 Sint-lambrechts-woluwe/woluwe-saint-lambert Bruxelles-Capitale 1200",
    "addr:housenumber":"293;/",
    "addr:postcode":"1200",
    "addr:street":"Avenue Georges Henri;Sint-Lambrechts-Woluwe",
    "iso:country":"BE",
    "sg:address":"Avenue Georges Henri 293",
    "sg:city":"Sint-lambrechts-woluwe/woluwe-saint-lambert",
    "sg:orig_category":"Entretien and r\u00e9parations de voitures",
    "sg:phone":"+32 2 734 60 54",
    "sg:postcode":"1200",
    "sg:province":"Bruxelles-Capitale",
    "wof:name":"C. D.",
    "wof:placetype":"venue"
},
  "geometry": {"coordinates":[4.4125590324,50.8436775208],"type":"Point"}
}