{
  "type": "Feature",
  "properties": {
    "iso:country":"BE",
    "sg:address":"Louizalaan 240b5",
    "sg:city":"Brussel/bruxelles",
    "sg:orig_category":"Advocaten and juridische adviseurs",
    "sg:phone":"+32 2 626 05 00",
    "sg:postcode":"1050",
    "sg:province":"Bruxelles-Capitale",
    "wof:name":"Beno\u00cet Taymans",
    "wof:placetype":"venue"
},
  "geometry": {"coordinates":[4.356962204,50.8341941833],"type":"Point"}
}