{
  "type": "Feature",
  "properties": {
    "iso:country":"BE",
    "sg:address":"Korenveld 7",
    "sg:city":"Borsbeek",
    "sg:orig_category":"Kapsalons",
    "sg:phone":"+32 3 321 41 71",
    "sg:postcode":"2150",
    "sg:province":"Antwerpen",
    "wof:name":"Coiffure Jozef",
    "wof:placetype":"venue"
},
  "geometry": {"coordinates":[4.49538517,51.1951828003],"type":"Point"}
}