{
  "type": "Feature",
  "properties": {
    "iso:country":"BE",
    "sg:address":"Lange Wegel 120",
    "sg:city":"Wetteren",
    "sg:classifiers":[
        {
            "category":"Cafe",
            "type":"Food & Drink"
        }
    ],
    "sg:phone":"+32 9 369 89 48",
    "sg:postcode":"9230",
    "sg:province":"Oost-Vlaanderen",
    "sg:tags":[
        "caf\u00e9s"
    ],
    "wof:name":"Kim Bracke",
    "wof:placetype":"venue"
},
  "geometry": {"coordinates":[3.9065189362,51.0086517334],"type":"Point"}
}