{
  "type": "Feature",
  "properties": {
    "addr:full":"Rue Masson 31 Seraing Li\u00e8ge 4100",
    "addr:housenumber":"31",
    "addr:postcode":"4100",
    "addr:street":"Rue Masson",
    "iso:country":"BE",
    "sg:address":"Rue Masson 31",
    "sg:city":"Seraing",
    "sg:orig_category":"Marketingbureaus",
    "sg:phone":"+32 4 338 05 64",
    "sg:postcode":"4100",
    "sg:province":"Li\u00e8ge",
    "wof:name":"Pecoraro",
    "wof:placetype":"venue"
},
  "geometry": {"coordinates":[5.4851360321,50.5956611633],"type":"Point"}
}