{
  "type": "Feature",
  "properties": {
    "iso:country":"BE",
    "sg:address":"Avenue De L'h\u00f4pital Fran\u00e7ais 15",
    "sg:city":"Bruxelles (koekelberg)",
    "sg:classifiers":[
        {
            "category":"Banks & Credit Unions",
            "subcategory":"Financial Services",
            "type":"Services"
        }
    ],
    "sg:phone":"+32 2 420 30 04",
    "sg:postcode":"1081",
    "sg:province":"Bruxelles-Capitale",
    "sg:tags":[
        "loan",
        "mortgage"
    ],
    "wof:name":"Argenta Gheysen Koen",
    "wof:placetype":"venue"
},
  "geometry": {"coordinates":[4.3140377998,50.8669433594],"type":"Point"}
}