{
  "type": "Feature",
  "properties": {
    "addr:full":"Brugsesteenweg 205 Kortrijk West-Vlaanderen 8500",
    "addr:housenumber":"205",
    "addr:postcode":"8500",
    "addr:street":"Brugsesteenweg",
    "iso:country":"BE",
    "sg:address":"Brugsesteenweg 205",
    "sg:city":"Kortrijk",
    "sg:classifiers":[
        {
            "category":"Shopping",
            "subcategory":"Florist",
            "type":"Retail Goods"
        }
    ],
    "sg:phone":"+32 56 37 38 27",
    "sg:postcode":"8500",
    "sg:province":"West-Vlaanderen",
    "wof:name":"Verstuyf J",
    "wof:placetype":"venue"
},
  "geometry": {"coordinates":[3.2645339966,50.8408622742],"type":"Point"}
}