{
  "type": "Feature",
  "properties": {
    "addr:full":"Werfstraat 1 Brugge West-Vlaanderen 8000",
    "addr:housenumber":"1",
    "addr:postcode":"8000",
    "addr:street":"Werfstraat",
    "iso:country":"BE",
    "sg:address":"Werfstraat 1",
    "sg:city":"Brugge",
    "sg:classifiers":[
        {
            "category":"Shopping",
            "subcategory":"Florist",
            "type":"Retail Goods"
        }
    ],
    "sg:phone":"+32 50 34 76 35",
    "sg:postcode":"8000",
    "sg:province":"West-Vlaanderen",
    "wof:name":"Palladio",
    "wof:placetype":"venue"
},
  "geometry": {"coordinates":[3.2151629925,51.2159423828],"type":"Point"}
}