{
  "type": "Feature",
  "properties": {
    "addr:full":". Ardooie (groot) West-Vlaanderen 8850",
    "addr:postcode":"8850",
    "addr:street":"Groot West-Vlaanderen",
    "iso:country":"BE",
    "sg:address":".",
    "sg:city":"Ardooie (groot)",
    "sg:orig_category":"Apotheken",
    "sg:phone":"+32 900 10 500",
    "sg:postcode":"8850",
    "sg:province":"West-Vlaanderen",
    "wof:name":"Apothekers Van Wacht",
    "wof:placetype":"venue"
},
  "geometry": {"coordinates":[3.1982800961,50.9782142639],"type":"Point"}
}