{
  "type": "Feature",
  "properties": {
    "addr:full":"Vrijheid 235 Hoogstraten Antwerpen 2320",
    "addr:housenumber":"235",
    "addr:postcode":"2320",
    "addr:street":"Vrijheid",
    "iso:country":"BE",
    "sg:address":"Vrijheid 235",
    "sg:city":"Hoogstraten",
    "sg:classifiers":[
        {
            "category":"Shopping",
            "subcategory":"Clothing, Apparel, & Fashions",
            "type":"Retail Goods"
        }
    ],
    "sg:phone":"+32 3 314 20 49",
    "sg:postcode":"2320",
    "sg:province":"Antwerpen",
    "sg:tags":[
        "lady",
        "clothing",
        "-"
    ],
    "wof:name":"Steps Fashion Bvba",
    "wof:placetype":"venue"
},
  "geometry": {"coordinates":[4.7594618797,51.3979797363],"type":"Point"}
}