{
  "type": "Feature",
  "properties": {
    "addr:full":"Route De Ciney 15 Houyet (custinne) Namur 5562",
    "addr:housenumber":"15",
    "addr:postcode":"5562",
    "addr:street":"Route De Ciney",
    "iso:country":"BE",
    "sg:address":"Route De Ciney 15",
    "sg:city":"Houyet (custinne)",
    "sg:classifiers":[
        {
            "category":"Wholesale",
            "subcategory":"Beer",
            "type":"Manufacturing & Wholesale Goods"
        }
    ],
    "sg:phone":"+32 82 66 61 71",
    "sg:postcode":"5562",
    "sg:province":"Namur",
    "sg:tags":[
        "ale",
        "-"
    ],
    "wof:name":"Hardy Ph",
    "wof:placetype":"venue"
},
  "geometry": {"coordinates":[5.0559868813,50.1968383789],"type":"Point"}
}