{
  "type": "Feature",
  "properties": {
    "addr:full":"Leopold Iii-laan 18 Ieper West-Vlaanderen 8900",
    "addr:housenumber":"18",
    "addr:postcode":"8900",
    "addr:street":"Leopold Iii-Laan",
    "iso:country":"BE",
    "sg:address":"Leopold Iii-laan 18",
    "sg:city":"Ieper",
    "sg:classifiers":[
        {
            "category":"Bars & Pubs",
            "type":"Food & Drink"
        }
    ],
    "sg:phone":"+32 57 21 89 21",
    "sg:postcode":"8900",
    "sg:province":"West-Vlaanderen",
    "wof:name":"Cafetaria Zwembad",
    "wof:placetype":"venue"
},
  "geometry": {"coordinates":[2.8940219879,50.8439826965],"type":"Point"}
}