{
  "type": "Feature",
  "properties": {
    "iso:country":"BE",
    "sg:address":"Chauss\u00e9e De La Croix 56",
    "sg:city":"Ottignies-louvain-la-neuve (ottignies)",
    "sg:classifiers":[
        {
            "category":"Shopping",
            "subcategory":"Bicycles & Sporting Goods",
            "type":"Retail Goods"
        }
    ],
    "sg:phone":"+32 10 41 25 74",
    "sg:postcode":"1340",
    "sg:province":"Brabant Wallon",
    "sg:tags":[
        "sport",
        "-"
    ],
    "wof:name":"Seeonee Sprl",
    "wof:placetype":"venue"
},
  "geometry": {"coordinates":[4.5764069557,50.6687355042],"type":"Point"}
}