{
  "type": "Feature",
  "properties": {
    "iso:country":"BE",
    "sg:address":"Dijkstraat 120",
    "sg:city":"Dendermonde",
    "sg:classifiers":[
        {
            "category":"Cafe",
            "type":"Food & Drink"
        }
    ],
    "sg:phone":"+32 52 22 36 50",
    "sg:postcode":"9200",
    "sg:province":"Oost-Vlaanderen",
    "sg:tags":[
        "caf\u00e9s"
    ],
    "wof:name":"Caf\u00c9 Den Artiest",
    "wof:placetype":"venue"
},
  "geometry": {"coordinates":[4.103181839,51.0306663513],"type":"Point"}
}