{
  "type": "Feature",
  "properties": {
    "iso:country":"BE",
    "sg:address":"Cours D'orval 6",
    "sg:city":"Ottignies-louvain-la-neuve (louvain-la-neuve)",
    "sg:classifiers":[
        {
            "category":"Health Services",
            "subcategory":"Health Practitioner",
            "type":"Services"
        }
    ],
    "sg:phone":"+32 10 45 05 14",
    "sg:postcode":"1348",
    "sg:province":"Brabant Wallon",
    "sg:tags":[
        "physiotherapist"
    ],
    "wof:name":"Taymans Anne",
    "wof:placetype":"venue"
},
  "geometry": {"coordinates":[4.615459919,50.6742858887],"type":"Point"}
}