{
  "type": "Feature",
  "properties": {
    "addr:full":"7387 Honnelles Hainaut 7387",
    "addr:housenumber":"7387",
    "addr:postcode":"7387",
    "addr:street":"Hainaut",
    "iso:country":"BE",
    "sg:address":"7387",
    "sg:city":"Honnelles",
    "sg:orig_category":"Pharmaciens",
    "sg:phone":"+32 900 10 500",
    "sg:postcode":"7387",
    "sg:province":"Hainaut",
    "wof:name":"Pharmacies De Garde",
    "wof:placetype":"venue"
},
  "geometry": {"coordinates":[3.7046101093,50.3438186646],"type":"Point"}
}