{
  "type": "Feature",
  "properties": {
    "iso:country":"BE",
    "sg:address":"Rue Du Veneur 54",
    "sg:city":"Silly",
    "sg:orig_category":"Eleveurs de bovins",
    "sg:phone":"+32 67 45 84 51",
    "sg:postcode":"7830",
    "sg:province":"Hainaut",
    "wof:name":"Max Delvaux",
    "wof:placetype":"venue"
},
  "geometry": {"coordinates":[3.9881129265,50.6386871338],"type":"Point"}
}