{
  "type": "Feature",
  "properties": {
    "iso:country":"BE",
    "sg:address":"Sint-martinusweg 195",
    "sg:city":"Zaventem",
    "sg:classifiers":[
        {
            "category":"Retail",
            "subcategory":"Auto Repair",
            "type":"Services"
        }
    ],
    "sg:phone":"+32 2 720 83 70",
    "sg:postcode":"1930",
    "sg:province":"Vlaams-Brabant",
    "sg:tags":[
        "automobile-body"
    ],
    "wof:name":"Ricker Services Bvba",
    "wof:placetype":"venue"
},
  "geometry": {"coordinates":[4.491964817,50.879940033],"type":"Point"}
}