{
  "type": "Feature",
  "properties": {
    "iso:country":"BE",
    "sg:address":"Gistelsesteenweg 26 C",
    "sg:city":"Brugge",
    "sg:orig_category":"Randstad",
    "sg:phone":"+32 50 45 62 80",
    "sg:postcode":"8200",
    "sg:province":"West-Vlaanderen",
    "wof:name":"Randstad",
    "wof:placetype":"venue"
},
  "geometry": {"coordinates":[3.1904699802,51.1992111206],"type":"Point"}
}