{
  "type": "Feature",
  "properties": {
    "iso:country":"BE",
    "sg:address":"Rue Du Moulin 19",
    "sg:city":"Perwez",
    "sg:orig_category":"Eleveurs de bovins",
    "sg:phone":"+32 81 65 53 46",
    "sg:postcode":"1360",
    "sg:province":"Brabant Wallon",
    "wof:name":"Eric Baele-lepage",
    "wof:placetype":"venue"
},
  "geometry": {"coordinates":[4.7859320641,50.6362113953],"type":"Point"}
}