{
  "type": "Feature",
  "properties": {
    "addr:full":"Place De La Licourt 19 Herstal Li\u00e8ge 4040",
    "addr:housenumber":"19",
    "addr:postcode":"4040",
    "addr:street":"Place De La Licourt",
    "iso:country":"BE",
    "sg:address":"Place De La Licourt 19",
    "sg:city":"Herstal",
    "sg:orig_category":"Pain, p\u00e2tisseries and confiseries",
    "sg:phone":"+32 4 264 15 30",
    "sg:postcode":"4040",
    "sg:province":"Li\u00e8ge",
    "wof:name":"Pulsard",
    "wof:placetype":"venue"
},
  "geometry": {"coordinates":[5.6391701698,50.6698760986],"type":"Point"}
}