{
  "type": "Feature",
  "properties": {
    "iso:country":"BE",
    "sg:address":"Pav\u00c9 De Warquignies 137",
    "sg:city":"Colfontaine",
    "sg:orig_category":"Fotografen and fotostudio's",
    "sg:phone":"+32 65 63 21 42",
    "sg:postcode":"7340",
    "sg:province":"Hainaut",
    "wof:name":"Espace Photo",
    "wof:placetype":"venue"
},
  "geometry": {"coordinates":[3.8210630417,50.3992462158],"type":"Point"}
}