{
  "type": "Feature",
  "properties": {
    "iso:country":"BE",
    "sg:address":"Steenweg Op Nieuwrode 127",
    "sg:city":"Rotselaar",
    "sg:orig_category":"Bloemen and planten HUISBRANDOLIE Huisdieren and benodigdheden Tuinbenodigdheden",
    "sg:phone":"+32 16 58 07 56",
    "sg:postcode":"3111",
    "sg:province":"Vlaams-Brabant",
    "wof:name":"Vannerum",
    "wof:placetype":"venue"
},
  "geometry": {"coordinates":[4.7707109451,50.9437141418],"type":"Point"}
}