{
  "type": "Feature",
  "properties": {
    "addr:full":"Grote Steenweg 112 Zulte Oost-Vlaanderen 9870",
    "addr:housenumber":"112",
    "addr:postcode":"9870",
    "addr:street":"Grote Steenweg",
    "iso:country":"BE",
    "sg:address":"Grote Steenweg 112",
    "sg:city":"Zulte",
    "sg:orig_category":"Banken and kredietinstellingen",
    "sg:phone":"+32 9 388 88 27",
    "sg:postcode":"9870",
    "sg:province":"Oost-Vlaanderen",
    "wof:name":"Kbc",
    "wof:placetype":"venue"
},
  "geometry": {"coordinates":[3.4436409473,50.921661377],"type":"Point"}
}