{
  "type": "Feature",
  "properties": {
    "iso:country":"BE",
    "sg:address":"Place Docteur Edouard Lodewijckx 12",
    "sg:city":"Jodoigne",
    "sg:classifiers":[
        {
            "category":"Education",
            "subcategory":"Special Training",
            "type":"Public Place"
        }
    ],
    "sg:phone":"+32 10 84 36 94",
    "sg:postcode":"1370",
    "sg:province":"Brabant Wallon",
    "sg:tags":[
        "-",
        "processing",
        "data"
    ],
    "wof:name":"Irka",
    "wof:placetype":"venue"
},
  "geometry": {"coordinates":[4.8690052032,50.7250747681],"type":"Point"}
}