{
  "type": "Feature",
  "properties": {
    "addr:full":"T'serclaesstraat 6 Ternat Vlaams-Brabant 1740",
    "addr:housenumber":"6",
    "addr:postcode":"1740",
    "addr:street":"T'Serclaesstraat",
    "iso:country":"BE",
    "sg:address":"T'serclaesstraat 6",
    "sg:city":"Ternat",
    "sg:orig_category":"Dierenartsen",
    "sg:phone":"+32 2 582 37 53",
    "sg:postcode":"1740",
    "sg:province":"Vlaams-Brabant",
    "wof:name":"Ilse Van Vlaenderen",
    "wof:placetype":"venue"
},
  "geometry": {"coordinates":[4.1717371941,50.8691635132],"type":"Point"}
}