{
  "type": "Feature",
  "properties": {
    "addr:full":"Saturnelaan 46 Ukkel/uccle Bruxelles-Capitale 1180",
    "addr:housenumber":"46",
    "addr:postcode":"1180",
    "addr:street":"Saturnelaan;/",
    "iso:country":"BE",
    "sg:address":"Saturnelaan 46",
    "sg:city":"Ukkel/uccle",
    "sg:orig_category":"Artsen and specialisten",
    "sg:phone":"+32 2 372 01 23",
    "sg:postcode":"1180",
    "sg:province":"Bruxelles-Capitale",
    "wof:name":"Philippe Unger",
    "wof:placetype":"venue"
},
  "geometry": {"coordinates":[4.361207962,50.79920578],"type":"Point"}
}