{
  "type": "Feature",
  "properties": {
    "iso:country":"BE",
    "sg:address":"Place 10",
    "sg:city":"Bever/bievene",
    "sg:classifiers":[
        {
            "category":"Government",
            "subcategory":"Police Station",
            "type":"Public Place"
        }
    ],
    "sg:phone":"+32 54 58 09 61",
    "sg:postcode":"1547",
    "sg:province":"Vlaams-Brabant",
    "sg:tags":[
        "gendarmerie"
    ],
    "wof:name":"Federale Politie/ Police F\u00c9d\u00c9rale",
    "wof:placetype":"venue"
},
  "geometry": {"coordinates":[3.9448969364,50.7172966003],"type":"Point"}
}