{
  "type": "Feature",
  "properties": {
    "iso:country":"BE",
    "sg:address":"Place De L'eglise 12",
    "sg:city":"Weismes",
    "sg:classifiers":[
        {
            "category":"Bars & Pubs",
            "type":"Food & Drink"
        }
    ],
    "sg:phone":"+32 80 67 99 62",
    "sg:postcode":"4950",
    "sg:province":"Li\u00e8ge",
    "wof:name":"Angelo (caf\u00e9)",
    "wof:placetype":"venue"
},
  "geometry": {"coordinates":[6.1110200882,50.4149017334],"type":"Point"}
}