{
  "type": "Feature",
  "properties": {
    "iso:country":"BE",
    "sg:address":"Seestrasse 11",
    "sg:city":"B\u00fctgenbach",
    "sg:classifiers":[
        {
            "category":"Home & Garden",
            "subcategory":"Building Materials",
            "type":"Retail Goods"
        }
    ],
    "sg:phone":"+32 80 44 51 34",
    "sg:postcode":"4750",
    "sg:province":"Li\u00e8ge",
    "sg:tags":[
        "-",
        "fireplace",
        "open",
        "ornamental"
    ],
    "wof:name":"Kessler L",
    "wof:placetype":"venue"
},
  "geometry": {"coordinates":[6.2072768211,50.4262428284],"type":"Point"}
}