{
  "type": "Feature",
  "properties": {
    "addr:full":"Rue Francois-lefebvre 210 Li\u00c8ge Li\u00e8ge 4000",
    "addr:housenumber":"210",
    "addr:postcode":"4000",
    "addr:street":"Rue Francois-Lefebvre",
    "iso:country":"BE",
    "sg:address":"Rue Francois-lefebvre 210",
    "sg:city":"Li\u00c8ge",
    "sg:classifiers":[
        {
            "category":"Restaurant",
            "type":"Food & Drink"
        }
    ],
    "sg:phone":"+32 4 246 38 61",
    "sg:postcode":"4000",
    "sg:province":"Li\u00e8ge",
    "wof:name":"Caf\u00c9taria St.vincent",
    "wof:placetype":"venue"
},
  "geometry": {"coordinates":[5.5504088402,50.6847763062],"type":"Point"}
}