{
  "type": "Feature",
  "properties": {
    "iso:country":"BE",
    "sg:address":"Kleine Lage 21",
    "sg:city":"Zottegem (strijpen)",
    "sg:classifiers":[
        {
            "category":"Home & Garden",
            "subcategory":"Carpets & Floor Coverings",
            "type":"Retail Goods"
        }
    ],
    "sg:phone":"+32 475 41 16 33",
    "sg:postcode":"9620",
    "sg:province":"Oost-Vlaanderen",
    "sg:tags":[
        "layer",
        "mosaicists"
    ],
    "wof:name":"Baele P",
    "wof:placetype":"venue"
},
  "geometry": {"coordinates":[3.8065590858,50.8772506714],"type":"Point"}
}