{
  "type": "Feature",
  "properties": {
    "iso:country":"BE",
    "sg:address":"Wiesenbachstrasse 6",
    "sg:city":"Sankt Vith",
    "sg:classifiers":[
        {
            "category":"Retail",
            "subcategory":"Veterinary Services",
            "type":"Services"
        }
    ],
    "sg:phone":"+32 80 22 62 15",
    "sg:postcode":"4780",
    "sg:province":"Li\u00e8ge",
    "sg:tags":[
        "veterinarian"
    ],
    "wof:name":"Arens M",
    "wof:placetype":"venue"
},
  "geometry": {"coordinates":[6.1315059662,50.2776832581],"type":"Point"}
}