{
  "type": "Feature",
  "properties": {
    "addr:full":"Plaats 12 Ledegem West-Vlaanderen 8880",
    "addr:housenumber":"12",
    "addr:postcode":"8880",
    "addr:street":"Plaats",
    "iso:country":"BE",
    "sg:address":"Plaats 12",
    "sg:city":"Ledegem",
    "sg:orig_category":"Banques and organismes de cr\u00e9dit",
    "sg:phone":"+32 56 50 06 55",
    "sg:postcode":"8880",
    "sg:province":"West-Vlaanderen",
    "wof:name":"Kbc",
    "wof:placetype":"venue"
},
  "geometry": {"coordinates":[3.1263968945,50.8531761169],"type":"Point"}
}