{
  "type": "Feature",
  "properties": {
    "addr:full":"Hoogbuul 32 Olen Antwerpen 2250",
    "addr:housenumber":"32",
    "addr:postcode":"2250",
    "addr:street":"Hoogbuul",
    "iso:country":"BE",
    "sg:address":"Hoogbuul 32",
    "sg:city":"Olen",
    "sg:classifiers":[
        {
            "category":"Farming",
            "subcategory":"Farm & Veterinary Services",
            "type":"Manufacturing & Wholesale Goods"
        }
    ],
    "sg:phone":"+32 14 24 85 10",
    "sg:postcode":"2250",
    "sg:province":"Antwerpen",
    "sg:tags":[
        "food",
        "product",
        "breeding",
        "animal",
        "related"
    ],
    "wof:name":"Nukamel",
    "wof:placetype":"venue"
},
  "geometry": {"coordinates":[4.8863859177,51.1489562988],"type":"Point"}
}