{
  "type": "Feature",
  "properties": {
    "addr:full":"Rue De Houdremont 64 Bievre Namur 5555",
    "addr:housenumber":"64",
    "addr:postcode":"5555",
    "addr:street":"Rue De Houdremont",
    "iso:country":"BE",
    "sg:address":"Rue De Houdremont 64",
    "sg:city":"Bievre",
    "sg:orig_category":"Artsen and specialisten",
    "sg:phone":"+32 61 51 16 51",
    "sg:postcode":"5555",
    "sg:province":"Namur",
    "wof:name":"Jean-pierre Libouton",
    "wof:placetype":"venue"
},
  "geometry": {"coordinates":[5.0037579536,49.9399528503],"type":"Point"}
}