{
  "type": "Feature",
  "properties": {
    "iso:country":"BE",
    "sg:address":"Chemin De Tenre 77",
    "sg:city":"Ath",
    "sg:orig_category":"Dranken",
    "sg:phone":"+32 68 28 21 75",
    "sg:postcode":"7800",
    "sg:province":"Hainaut",
    "wof:name":"Drink Market Hilaire",
    "wof:placetype":"venue"
},
  "geometry": {"coordinates":[3.7901599407,50.651222229],"type":"Point"}
}