{
  "type": "Feature",
  "properties": {
    "iso:country":"BE",
    "sg:address":"Wittogstraat 14a",
    "sg:city":"Zwevegem",
    "sg:orig_category":"Kapsalons",
    "sg:phone":"+32 56 45 54 00",
    "sg:postcode":"8554",
    "sg:province":"West-Vlaanderen",
    "wof:name":"An Naessens",
    "wof:placetype":"venue"
},
  "geometry": {"coordinates":[3.3706920147,50.7496185303],"type":"Point"}
}