{
  "type": "Feature",
  "properties": {
    "iso:country":"BE",
    "sg:address":"Avenue Neef 15",
    "sg:city":"Tilff",
    "sg:classifiers":[
        {
            "category":"Building & Trades",
            "subcategory":"Construction",
            "type":"Services"
        }
    ],
    "sg:phone":"+32 4 388 14 96",
    "sg:postcode":"4130",
    "sg:province":"Li\u00e8ge",
    "sg:tags":[
        "boom",
        "hoisting"
    ],
    "wof:name":"Lemmens S.a.",
    "wof:placetype":"venue"
},
  "geometry": {"coordinates":[5.5890412331,50.5696907043],"type":"Point"}
}