{
  "type": "Feature",
  "properties": {
    "addr:full":"Charly Des Bois 44a Braine-le-comte (ronqui\u00e8res) Hainaut 7090",
    "addr:housenumber":"44a",
    "addr:postcode":"7090",
    "addr:street":"Des Bois",
    "iso:country":"BE",
    "sg:address":"Charly Des Bois 44a",
    "sg:city":"Braine-le-comte (ronqui\u00e8res)",
    "sg:classifiers":[
        {
            "category":"Wholesale",
            "subcategory":"Office Equipment",
            "type":"Manufacturing & Wholesale Goods"
        }
    ],
    "sg:phone":"+32 495 74 54 17",
    "sg:postcode":"7090",
    "sg:province":"Hainaut",
    "sg:tags":[
        "dust",
        "removing"
    ],
    "wof:name":"Tami Filtration Sprl",
    "wof:placetype":"venue"
},
  "geometry": {"coordinates":[4.2179470062,50.6171417236],"type":"Point"}
}