{
  "type": "Feature",
  "properties": {
    "iso:country":"BE",
    "sg:address":"Aarschotsestraat 123",
    "sg:city":"Vilvoorde (peutie)",
    "sg:classifiers":[
        {
            "category":"Parking",
            "subcategory":"Lot",
            "type":"Transportation"
        }
    ],
    "sg:phone":"+32 2 251 06 75",
    "sg:postcode":"1800",
    "sg:province":"Vlaams-Brabant",
    "sg:tags":[
        "parking-places",
        "laying-out"
    ],
    "wof:name":"Vande Merk (oud Huis)",
    "wof:placetype":"venue"
},
  "geometry": {"coordinates":[4.4577898979,50.9261703491],"type":"Point"}
}