{
  "type": "Feature",
  "properties": {
    "addr:full":"Leuvensesteenweg 344 Boortmeerbeek Vlaams-Brabant 3190",
    "addr:housenumber":"344",
    "addr:postcode":"3190",
    "addr:street":"Leuvensesteenweg",
    "iso:country":"BE",
    "sg:address":"Leuvensesteenweg 344",
    "sg:city":"Boortmeerbeek",
    "sg:orig_category":"Entretien and r\u00e9parations de voitures. V\u00e9hicules automobiles",
    "sg:phone":"+32 15 51 10 25",
    "sg:postcode":"3190",
    "sg:province":"Vlaams-Brabant",
    "wof:name":"Garage Maertens",
    "wof:placetype":"venue"
},
  "geometry": {"coordinates":[4.5728349686,50.9683685303],"type":"Point"}
}