{
  "type": "Feature",
  "properties": {
    "addr:full":"Rue De La Pr\u00c9voyance 50 Brussel/bruxelles Bruxelles-Capitale 1000",
    "addr:housenumber":"50",
    "addr:postcode":"1000",
    "addr:street":"Rue De La Pre\u0301Voyance;/",
    "iso:country":"BE",
    "sg:address":"Rue De La Pr\u00c9voyance 50",
    "sg:city":"Brussel/bruxelles",
    "sg:classifiers":[
        {
            "category":"Restaurant",
            "type":"Food & Drink"
        }
    ],
    "sg:phone":"+32 2 512 41 77",
    "sg:postcode":"1000",
    "sg:province":"Bruxelles-Capitale",
    "wof:name":"La Mie Du Coin",
    "wof:placetype":"venue"
},
  "geometry": {"coordinates":[4.3507289886,50.8349075317],"type":"Point"}
}