{
  "type": "Feature",
  "properties": {
    "addr:full":"Schuttersvest 71 Mechelen Antwerpen 2800",
    "addr:housenumber":"71",
    "addr:postcode":"2800",
    "addr:street":"Schuttersvest",
    "iso:country":"BE",
    "sg:address":"Schuttersvest 71",
    "sg:city":"Mechelen",
    "sg:classifiers":[
        {
            "category":"Personal",
            "subcategory":"Barber",
            "type":"Services"
        }
    ],
    "sg:phone":"+32 15 41 56 80",
    "sg:postcode":"2800",
    "sg:province":"Antwerpen",
    "sg:tags":[
        "gentleman",
        "salon",
        "-",
        "hairdressing"
    ],
    "wof:name":"Manuel",
    "wof:placetype":"venue"
},
  "geometry": {"coordinates":[4.4879498482,51.0079917908],"type":"Point"}
}