{
  "type": "Feature",
  "properties": {
    "addr:full":"Toekomststraat 21 Liedekerke Vlaams-Brabant 1770",
    "addr:housenumber":"21",
    "addr:postcode":"1770",
    "addr:street":"Toekomststraat;Vlaams-Brabant",
    "iso:country":"BE",
    "sg:address":"Toekomststraat 21",
    "sg:city":"Liedekerke",
    "sg:classifiers":[
        {
            "category":"Cafe",
            "type":"Food & Drink"
        }
    ],
    "sg:phone":"+32 53 67 10 63",
    "sg:postcode":"1770",
    "sg:province":"Vlaams-Brabant",
    "sg:tags":[
        "caf\u00e9s"
    ],
    "wof:name":"Vertongen M. & Baetens D.",
    "wof:placetype":"venue"
},
  "geometry": {"coordinates":[4.0835418701,50.8662872314],"type":"Point"}
}