{
  "type": "Feature",
  "properties": {
    "addr:full":"Wijgmaalbroek 49 Leuven (wijgmaal) Vlaams-Brabant 3018",
    "addr:housenumber":"49",
    "addr:postcode":"3018",
    "addr:street":"Wijgmaalbroek",
    "iso:country":"BE",
    "sg:address":"Wijgmaalbroek 49",
    "sg:city":"Leuven (wijgmaal)",
    "sg:classifiers":[
        {
            "category":"Home & Garden",
            "subcategory":"Building Materials",
            "type":"Retail Goods"
        }
    ],
    "sg:phone":"+32 16 44 45 32",
    "sg:postcode":"3018",
    "sg:province":"Vlaams-Brabant",
    "sg:tags":[
        "window"
    ],
    "wof:name":"Beullens Bvba",
    "wof:placetype":"venue"
},
  "geometry": {"coordinates":[4.7063951492,50.9293327332],"type":"Point"}
}