{
  "type": "Feature",
  "properties": {
    "addr:full":"Achterstraat 140 Zoersel Antwerpen 2980",
    "addr:housenumber":"140",
    "addr:postcode":"2980",
    "addr:street":"Achterstraat",
    "iso:country":"BE",
    "sg:address":"Achterstraat 140",
    "sg:city":"Zoersel",
    "sg:classifiers":[
        {
            "category":"Shopping",
            "subcategory":"Stationery & Office Supplies",
            "type":"Retail Goods"
        }
    ],
    "sg:phone":"+32 3 294 32 50",
    "sg:postcode":"2980",
    "sg:province":"Antwerpen",
    "sg:tags":[
        "machine",
        "repair",
        "mainten",
        "-"
    ],
    "wof:name":"Office Technical Support",
    "wof:placetype":"venue"
},
  "geometry": {"coordinates":[4.713435173,51.269985199],"type":"Point"}
}