{
  "type": "Feature",
  "properties": {
    "addr:full":"Lindestraat 89 Zedelgem West-Vlaanderen 8210",
    "addr:housenumber":"89",
    "addr:postcode":"8210",
    "addr:street":"Lindestraat",
    "iso:country":"BE",
    "sg:address":"Lindestraat 89",
    "sg:city":"Zedelgem",
    "sg:classifiers":[
        {
            "category":"Building & Trades",
            "subcategory":"Cleaning & Sanitation",
            "type":"Services"
        }
    ],
    "sg:phone":"+32 496 55 12 84",
    "sg:postcode":"8210",
    "sg:province":"West-Vlaanderen",
    "sg:tags":[
        "fa\u00e7ade",
        "maintenance"
    ],
    "wof:name":"Auto & Truckcleaning C\u00fcrd",
    "wof:placetype":"venue"
},
  "geometry": {"coordinates":[3.1428599358,51.1358108521],"type":"Point"}
}