{
  "type": "Feature",
  "properties": {
    "addr:full":"Poekevoetweg 2-1 Ruiselede West-Vlaanderen 8755",
    "addr:housenumber":"2-1",
    "addr:postcode":"8755",
    "addr:street":"Poekevoetweg",
    "iso:country":"BE",
    "sg:address":"Poekevoetweg 2-1",
    "sg:city":"Ruiselede",
    "sg:classifiers":[
        {
            "category":"Building & Trades",
            "subcategory":"Landscaping Services",
            "type":"Services"
        }
    ],
    "sg:phone":"+32 51 46 75 05",
    "sg:postcode":"8755",
    "sg:province":"West-Vlaanderen",
    "sg:tags":[
        "architect",
        "landscape"
    ],
    "wof:name":"Mattheeuws F",
    "wof:placetype":"venue"
},
  "geometry": {"coordinates":[3.3999359608,51.0418968201],"type":"Point"}
}