{
  "type": "Feature",
  "properties": {
    "iso:country":"BE",
    "sg:address":"Europakruispunt 3",
    "sg:city":"Brussel",
    "sg:classifiers":[
        {
            "category":"Restaurant",
            "type":"Food & Drink"
        }
    ],
    "sg:phone":"+32 2 548 47 16",
    "sg:postcode":"1000",
    "sg:province":"Bruxelles-Capitale",
    "wof:name":"L' Epicerie",
    "wof:placetype":"venue"
},
  "geometry": {"coordinates":[4.3560490608,50.8458518982],"type":"Point"}
}