{
  "type": "Feature",
  "properties": {
    "addr:full":"Avenue Andr\u00e9 Guillaume 19 Spa Li\u00e8ge 4900",
    "addr:housenumber":"19",
    "addr:postcode":"4900",
    "addr:street":"Avenue Andre\u0301 Guillaume",
    "iso:country":"BE",
    "sg:address":"Avenue Andr\u00e9 Guillaume 19",
    "sg:city":"Spa",
    "sg:classifiers":[
        {
            "category":"Insurance",
            "subcategory":"Insurance Agent",
            "type":"Services"
        }
    ],
    "sg:phone":"+32 87 77 23 07",
    "sg:postcode":"4900",
    "sg:province":"Li\u00e8ge",
    "sg:tags":[
        "broker"
    ],
    "wof:name":"Marcotty J",
    "wof:placetype":"venue"
},
  "geometry": {"coordinates":[5.8460707664,50.4697113037],"type":"Point"}
}