{
  "type": "Feature",
  "properties": {
    "iso:country":"BE",
    "sg:address":"Chauss\u00c9e De Roosevelt 65",
    "sg:city":"Amay",
    "sg:orig_category":"Kunstonderwijs",
    "sg:phone":"+32 85 31 20 11",
    "sg:postcode":"4540",
    "sg:province":"Li\u00e8ge",
    "wof:name":"L'acad\u00c9mie Marcel D\u00c9siron",
    "wof:placetype":"venue"
},
  "geometry": {"coordinates":[5.3150200844,50.54637146],"type":"Point"}
}