{
  "type": "Feature",
  "properties": {
    "addr:full":"Rue Du Pairay 8 Seraing Li\u00e8ge 4100",
    "addr:housenumber":"8",
    "addr:postcode":"4100",
    "addr:street":"Rue Du Pairay",
    "iso:country":"BE",
    "sg:address":"Rue Du Pairay 8",
    "sg:city":"Seraing",
    "sg:orig_category":"R\u00e9parations d'appareils \u00e9lectrom\u00e9nagers. Electrom\u00e9nager, t\u00e9l\u00e9visions and radios. Mat\u00e9riel de T\u00e9l\u00e9com",
    "sg:phone":"+32 4 337 44 86",
    "sg:postcode":"4100",
    "sg:province":"Li\u00e8ge",
    "wof:name":"Jp Service",
    "wof:placetype":"venue"
},
  "geometry": {"coordinates":[5.5110731125,50.598274231],"type":"Point"}
}