{
  "type": "Feature",
  "properties": {
    "addr:full":"Flanders Language Valley 63 Ieper West-Vlaanderen 8900",
    "addr:housenumber":"63",
    "addr:postcode":"8900",
    "iso:country":"BE",
    "sg:address":"Flanders Language Valley 63",
    "sg:city":"Ieper",
    "sg:classifiers":[
        {
            "category":"Banks & Credit Unions",
            "subcategory":"Investment Brokerage",
            "type":"Services"
        }
    ],
    "sg:phone":"+32 57 22 94 30",
    "sg:postcode":"8900",
    "sg:province":"West-Vlaanderen",
    "wof:name":"Flv Fund & Management",
    "wof:placetype":"venue"
},
  "geometry": {"coordinates":[2.8878269196,50.8513641357],"type":"Point"}
}