{
  "type": "Feature",
  "properties": {
    "iso:country":"BE",
    "sg:address":"Rue De Bouillon 411",
    "sg:city":"Beauraing",
    "sg:orig_category":"Alimentation sp\u00e9cialis\u00e9e",
    "sg:phone":"+32 82 71 26 99",
    "sg:postcode":"5570",
    "sg:province":"Namur",
    "wof:name":"Le Magasin De La Ferme",
    "wof:placetype":"venue"
},
  "geometry": {"coordinates":[4.9803199768,50.1055488586],"type":"Point"}
}