{
  "type": "Feature",
  "properties": {
    "addr:full":"Jan Baptist Paulusstraat 21 Machelen (diegem) Vlaams-Brabant 1831",
    "addr:housenumber":"21",
    "addr:postcode":"1831",
    "addr:street":"Jan Baptist Paulusstraat",
    "iso:country":"BE",
    "sg:address":"Jan Baptist Paulusstraat 21",
    "sg:city":"Machelen (diegem)",
    "sg:classifiers":[
        {
            "category":"Real Estate",
            "subcategory":"Architect",
            "type":"Services"
        }
    ],
    "sg:phone":"+32 2 725 37 79",
    "sg:postcode":"1831",
    "sg:province":"Vlaams-Brabant",
    "wof:name":"Delendeker M",
    "wof:placetype":"venue"
},
  "geometry": {"coordinates":[4.4355301857,50.8858909607],"type":"Point"}
}