{
  "type": "Feature",
  "properties": {
    "addr:full":"Lepelstraat 24 Temse Oost-Vlaanderen 9140",
    "addr:housenumber":"24",
    "addr:postcode":"9140",
    "addr:street":"Lepelstraat",
    "iso:country":"BE",
    "sg:address":"Lepelstraat 24",
    "sg:city":"Temse",
    "sg:classifiers":[
        {
            "category":"Personal",
            "subcategory":"Beauty Salon",
            "type":"Services"
        }
    ],
    "sg:phone":"+32 3 774 20 13",
    "sg:postcode":"9140",
    "sg:province":"Oost-Vlaanderen",
    "sg:tags":[
        "de",
        "coiffure"
    ],
    "wof:name":"Coiffure Marie-h\u00c9l\u00c8ne",
    "wof:placetype":"venue"
},
  "geometry": {"coordinates":[4.2143149376,51.1247558594],"type":"Point"}
}