{
  "type": "Feature",
  "properties": {
    "addr:full":"Drapstraat 107 Nazareth Oost-Vlaanderen 9810",
    "addr:housenumber":"107",
    "addr:postcode":"9810",
    "addr:street":"Drapstraat",
    "iso:country":"BE",
    "sg:address":"Drapstraat 107",
    "sg:city":"Nazareth",
    "sg:classifiers":[
        {
            "category":"Shopping",
            "subcategory":"Florist",
            "type":"Retail Goods"
        }
    ],
    "sg:phone":"+32 9 385 50 71",
    "sg:postcode":"9810",
    "sg:province":"Oost-Vlaanderen",
    "wof:name":"Bloemen Oase",
    "wof:placetype":"venue"
},
  "geometry": {"coordinates":[3.6102099419,50.9585609436],"type":"Point"}
}