{
  "type": "Feature",
  "properties": {
    "addr:full":"Rue Des Sabli\u00e8res 57-65 Ch\u00e2telet Hainaut 6200",
    "addr:housenumber":"57-65",
    "addr:postcode":"6200",
    "addr:street":"Rue Des Sablie\u0300Res",
    "iso:country":"BE",
    "sg:address":"Rue Des Sabli\u00e8res 57-65",
    "sg:city":"Ch\u00e2telet",
    "sg:classifiers":[
        {
            "category":"Building & Trades",
            "subcategory":"Construction",
            "type":"Services"
        }
    ],
    "sg:phone":"+32 71 38 26 42",
    "sg:postcode":"6200",
    "sg:province":"Hainaut",
    "sg:tags":[
        "installation",
        "-",
        "central",
        "heating"
    ],
    "wof:name":"Hoogstoel",
    "wof:placetype":"venue"
},
  "geometry": {"coordinates":[4.5311069489,50.3984413147],"type":"Point"}
}