{
  "type": "Feature",
  "properties": {
    "addr:full":"Rue Du Progr\u00e8s 49 Bruxelles (saint-josse-ten-noode) Bruxelles-Capitale 1210",
    "addr:housenumber":"49",
    "addr:postcode":"1210",
    "addr:street":"Rue Du Progre\u0300S",
    "iso:country":"BE",
    "sg:address":"Rue Du Progr\u00e8s 49",
    "sg:city":"Bruxelles (saint-josse-ten-noode)",
    "sg:classifiers":[
        {
            "category":"Bars & Pubs",
            "type":"Food & Drink"
        }
    ],
    "sg:phone":"+32 2 203 60 06",
    "sg:postcode":"1210",
    "sg:province":"Bruxelles-Capitale",
    "sg:tags":[
        "tavern"
    ],
    "wof:name":"Omnibus",
    "wof:placetype":"venue"
},
  "geometry": {"coordinates":[4.3593702316,50.8578948975],"type":"Point"}
}