{
  "type": "Feature",
  "properties": {
    "iso:country":"BE",
    "sg:address":"Schoolstraat 34ba",
    "sg:city":"Retie",
    "sg:orig_category":"M\u00e9decins and sp\u00e9cialistes",
    "sg:phone":"+32 14 67 03 67",
    "sg:postcode":"2470",
    "sg:province":"Antwerpen",
    "wof:name":"Michel Robeyns",
    "wof:placetype":"venue"
},
  "geometry": {"coordinates":[5.0561060905,51.2871017456],"type":"Point"}
}