{
  "type": "Feature",
  "properties": {
    "addr:full":"Oplinterstraat 48 Linter Vlaams-Brabant 3350",
    "addr:housenumber":"48",
    "addr:postcode":"3350",
    "addr:street":"Oplinterstraat;Vlaams-Brabant",
    "iso:country":"BE",
    "sg:address":"Oplinterstraat 48",
    "sg:city":"Linter",
    "sg:orig_category":"Services fun\u00e9raires",
    "sg:phone":"+32 11 88 55 85",
    "sg:postcode":"3350",
    "sg:province":"Vlaams-Brabant",
    "wof:name":"Louis Permentier",
    "wof:placetype":"venue"
},
  "geometry": {"coordinates":[5.0131721497,50.8107032776],"type":"Point"}
}