{
  "type": "Feature",
  "properties": {
    "iso:country":"BE",
    "sg:address":"Industrieweg 2",
    "sg:city":"Malle",
    "sg:orig_category":"Travaux de pl\u00e2trage",
    "sg:phone":"+32 3 312 45 65",
    "sg:postcode":"2390",
    "sg:province":"Antwerpen",
    "wof:name":"Duchene",
    "wof:placetype":"venue"
},
  "geometry": {"coordinates":[4.7178168297,51.2962417603],"type":"Point"}
}