{
  "type": "Feature",
  "properties": {
    "iso:country":"BE",
    "sg:address":"Armand Verheydenstraat 15a",
    "sg:city":"Oud-heverlee",
    "sg:orig_category":"Plomberie, chauffage and installations sanitaires",
    "sg:phone":"+32 16 40 32 77",
    "sg:postcode":"3053",
    "sg:province":"Vlaams-Brabant",
    "wof:name":"Sani-job",
    "wof:placetype":"venue"
},
  "geometry": {"coordinates":[4.7312002182,50.8345184326],"type":"Point"}
}