{
  "type": "Feature",
  "properties": {
    "addr:full":"Klein Hoogveld 2 Vilvoorde Vlaams-Brabant 1800",
    "addr:housenumber":"2",
    "addr:postcode":"1800",
    "addr:street":"Klein Hoogveld",
    "iso:country":"BE",
    "sg:address":"Klein Hoogveld 2",
    "sg:city":"Vilvoorde",
    "sg:classifiers":[
        {
            "category":"Health Services",
            "subcategory":"Nursing And Care Facility",
            "type":"Services"
        }
    ],
    "sg:phone":"+32 2 267 66 97",
    "sg:postcode":"1800",
    "sg:province":"Vlaams-Brabant",
    "sg:tags":[
        "home"
    ],
    "wof:name":"De Schakel",
    "wof:placetype":"venue"
},
  "geometry": {"coordinates":[4.3792901039,50.9139518738],"type":"Point"}
}