{
  "type": "Feature",
  "properties": {
    "addr:full":"Hendrik I Lei 57 Vilvoorde Vlaams-Brabant 1800",
    "addr:housenumber":"57",
    "addr:postcode":"1800",
    "addr:street":"Hendrik I Lei",
    "iso:country":"BE",
    "sg:address":"Hendrik I Lei 57",
    "sg:city":"Vilvoorde",
    "sg:orig_category":"Avocats and conseillers juridiques",
    "sg:phone":"+32 2 252 02 46",
    "sg:postcode":"1800",
    "sg:province":"Vlaams-Brabant",
    "wof:name":"B. Maertens",
    "wof:placetype":"venue"
},
  "geometry": {"coordinates":[4.402985096,50.9195861816],"type":"Point"}
}