{
  "type": "Feature",
  "properties": {
    "addr:full":"Rue Henri Evenepoel 102 Bruxelles (schaerbeek) Bruxelles-Capitale 1030",
    "addr:housenumber":"102",
    "addr:postcode":"1030",
    "addr:street":"Rue Henri Evenepoel",
    "iso:country":"BE",
    "sg:address":"Rue Henri Evenepoel 102",
    "sg:city":"Bruxelles (schaerbeek)",
    "sg:classifiers":[
        {
            "category":"Autos & Motor Vehicles",
            "subcategory":"Automobile Sales",
            "type":"Retail Goods"
        }
    ],
    "sg:phone":"+32 2 702 94 20",
    "sg:postcode":"1030",
    "sg:province":"Bruxelles-Capitale",
    "sg:tags":[
        "car",
        "used",
        "-"
    ],
    "wof:name":"Cegeac Used Cars",
    "wof:placetype":"venue"
},
  "geometry": {"coordinates":[4.4066748619,50.8552017212],"type":"Point"}
}