{
  "type": "Feature",
  "properties": {
    "addr:full":"Noorderlaan133 Bp 7 Antwerpen Antwerpen 2030",
    "addr:housenumber":"7",
    "addr:postcode":"2030",
    "iso:country":"BE",
    "sg:address":"Noorderlaan133 Bp 7",
    "sg:city":"Antwerpen",
    "sg:classifiers":[
        {
            "category":"Professional",
            "subcategory":"Business Services",
            "type":"Services"
        }
    ],
    "sg:phone":"+32 3 544 72 85",
    "sg:postcode":"2030",
    "sg:province":"Antwerpen",
    "sg:tags":[
        "training",
        "advice"
    ],
    "wof:name":"Achieveglobal Nv",
    "wof:placetype":"venue"
},
  "geometry": {"coordinates":[4.3637099266,51.2742385864],"type":"Point"}
}