{
  "type": "Feature",
  "properties": {
    "addr:full":"Leopold Ii-laan 20 Sint-niklaas Oost-Vlaanderen 9100",
    "addr:housenumber":"20",
    "addr:postcode":"9100",
    "addr:street":"Leopold Ii-Laan",
    "iso:country":"BE",
    "sg:address":"Leopold Ii-laan 20",
    "sg:city":"Sint-niklaas",
    "sg:classifiers":[
        {
            "category":"Social Services",
            "type":"Services"
        }
    ],
    "sg:phone":"+32 3 760 36 36",
    "sg:postcode":"9100",
    "sg:province":"Oost-Vlaanderen",
    "wof:name":"Gezins- & Bejaardenhulp S.v.v.",
    "wof:placetype":"venue"
},
  "geometry": {"coordinates":[4.1492490768,51.1724853516],"type":"Point"}
}