{
  "type": "Feature",
  "properties": {
    "iso:country":"BE",
    "sg:address":"Rue Albert I 17",
    "sg:city":"Saint-georges-sur-meuse",
    "sg:classifiers":[
        {
            "category":"Health Services",
            "subcategory":"Dentist",
            "type":"Services"
        }
    ],
    "sg:phone":"+32 4 259 62 11",
    "sg:postcode":"4470",
    "sg:province":"Li\u00e8ge",
    "wof:name":"Degroote Louis",
    "wof:placetype":"venue"
},
  "geometry": {"coordinates":[5.3563289642,50.6003341675],"type":"Point"}
}