{
  "type": "Feature",
  "properties": {
    "addr:full":"Atherstrasse 4 Kelmis/la Calamine Li\u00e8ge 4728",
    "addr:housenumber":"4",
    "addr:postcode":"4728",
    "addr:street":"Atherstrasse",
    "iso:country":"BE",
    "sg:address":"Atherstrasse 4",
    "sg:city":"Kelmis/la Calamine",
    "sg:orig_category":"Herstellingen and onderhoud van auto's Onderdelen and accessoires voor auto's Voertuigen",
    "sg:phone":"+32 87 65 93 20",
    "sg:postcode":"4728",
    "sg:province":"Li\u00e8ge",
    "wof:name":"B.l.s.",
    "wof:placetype":"venue"
},
  "geometry": {"coordinates":[6.0364089012,50.716835022],"type":"Point"}
}