{
  "type": "Feature",
  "properties": {
    "iso:country":"BE",
    "sg:address":"Peperstraat 46",
    "sg:city":"Kortrijk",
    "sg:orig_category":"Kinderopvang",
    "sg:phone":"+32 56 35 28 83",
    "sg:postcode":"8501",
    "sg:province":"West-Vlaanderen",
    "wof:name":"\u00b4t Kwetternestje",
    "wof:placetype":"venue"
},
  "geometry": {"coordinates":[3.2334840298,50.8423576355],"type":"Point"}
}