{
  "type": "Feature",
  "properties": {
    "addr:full":"Rue Victor Libert 36b Marche-en-famenne Luxembourg 6900",
    "addr:housenumber":"36b",
    "addr:postcode":"6900",
    "addr:street":"Rue Victor Libert",
    "iso:country":"BE",
    "sg:address":"Rue Victor Libert 36b",
    "sg:city":"Marche-en-famenne",
    "sg:classifiers":[
        {
            "category":"Shopping",
            "subcategory":"Clothing, Apparel, & Fashions",
            "type":"Retail Goods"
        }
    ],
    "sg:phone":"+32 84 31 54 75",
    "sg:postcode":"6900",
    "sg:province":"Luxembourg",
    "sg:tags":[
        "purchase",
        "clothing",
        "-",
        "sale",
        "second-hand"
    ],
    "wof:name":"Halle Aux Fringues (la)",
    "wof:placetype":"venue"
},
  "geometry": {"coordinates":[5.3364229202,50.228477478],"type":"Point"}
}