{
  "type": "Feature",
  "properties": {
    "addr:full":"Jozef Meganckstraat 30 Aalst Oost-Vlaanderen 9300",
    "addr:housenumber":"30",
    "addr:postcode":"9300",
    "addr:street":"Jozef Meganckstraat",
    "iso:country":"BE",
    "sg:address":"Jozef Meganckstraat 30",
    "sg:city":"Aalst",
    "sg:classifiers":[
        {
            "category":"Real Estate",
            "subcategory":"Architect",
            "type":"Services"
        }
    ],
    "sg:phone":"+32 53 78 99 63",
    "sg:postcode":"9300",
    "sg:province":"Oost-Vlaanderen",
    "wof:name":"Van Der Perre W",
    "wof:placetype":"venue"
},
  "geometry": {"coordinates":[4.0300278664,50.943561554],"type":"Point"}
}