{
  "type": "Feature",
  "properties": {
    "addr:full":"Hoogstraat 10 Brussel/bruxelles Bruxelles-Capitale 1000",
    "addr:housenumber":"10",
    "addr:postcode":"1000",
    "addr:street":"Hoogstraat;/",
    "iso:country":"BE",
    "sg:address":"Hoogstraat 10",
    "sg:city":"Brussel/bruxelles",
    "sg:orig_category":"Technisch and beroeps secundair onderwijs",
    "sg:phone":"+32 2 506 43 10",
    "sg:postcode":"1000",
    "sg:province":"Bruxelles-Capitale",
    "wof:name":"Institut Diderot",
    "wof:placetype":"venue"
},
  "geometry": {"coordinates":[4.3521780968,50.8418273926],"type":"Point"}
}