{
  "type": "Feature",
  "properties": {
    "iso:country":"BE",
    "sg:address":"Bekedijkstraat 1",
    "sg:city":"Jabbeke",
    "sg:classifiers":[
        {
            "category":"Home & Garden",
            "subcategory":"Kitchen Supply",
            "type":"Retail Goods"
        }
    ],
    "sg:phone":"+32 50 81 15 73",
    "sg:postcode":"8490",
    "sg:province":"West-Vlaanderen",
    "sg:tags":[
        "installation"
    ],
    "wof:name":"Diapal",
    "wof:placetype":"venue"
},
  "geometry": {"coordinates":[3.078635931,51.194442749],"type":"Point"}
}