{
  "type": "Feature",
  "properties": {
    "iso:country":"BE",
    "sg:address":"Steenovenstraat 14",
    "sg:city":"Malle",
    "sg:orig_category":"Rundveehouders",
    "sg:phone":"+32 3 312 13 46",
    "sg:postcode":"2390",
    "sg:province":"Antwerpen",
    "wof:name":"Constant Grootjans",
    "wof:placetype":"venue"
},
  "geometry": {"coordinates":[4.7067131996,51.3143463135],"type":"Point"}
}