{
  "type": "Feature",
  "properties": {
    "iso:country":"BE",
    "sg:address":"Rue Vandervelde 11",
    "sg:city":"Beloeil (quevaucamps)",
    "sg:classifiers":[
        {
            "category":"Real Estate",
            "subcategory":"Architect",
            "type":"Services"
        }
    ],
    "sg:phone":"+32 69 57 86 97",
    "sg:postcode":"7972",
    "sg:province":"Hainaut",
    "wof:name":"Simon O",
    "wof:placetype":"venue"
},
  "geometry": {"coordinates":[3.6921050549,50.5274238586],"type":"Point"}
}