{
  "type": "Feature",
  "properties": {
    "addr:full":"Rue Du Philosophe 3 Charleroi Hainaut 6040",
    "addr:housenumber":"3",
    "addr:postcode":"6040",
    "addr:street":"Rue Du Philosophe;Hainaut",
    "iso:country":"BE",
    "sg:address":"Rue Du Philosophe 3",
    "sg:city":"Charleroi",
    "sg:orig_category":"Pleisterwerk",
    "sg:phone":"+32 71 37 23 86",
    "sg:postcode":"6040",
    "sg:province":"Hainaut",
    "wof:name":"P.c.t. Dury Et Cie",
    "wof:placetype":"venue"
},
  "geometry": {"coordinates":[4.4629030228,50.4570541382],"type":"Point"}
}