{
  "type": "Feature",
  "properties": {
    "iso:country":"BE",
    "sg:address":"Sulferbergstraat 38",
    "sg:city":"Brugge",
    "sg:orig_category":"Pensions de famille",
    "sg:phone":"+32 50 34 88 67",
    "sg:postcode":"8000",
    "sg:province":"West-Vlaanderen",
    "wof:name":"Koetshuis",
    "wof:placetype":"venue"
},
  "geometry": {"coordinates":[3.227602005,51.199924469],"type":"Point"}
}