{
  "type": "Feature",
  "properties": {
    "addr:full":"Avenue Gounod 15 Bruxelles (anderlecht) Bruxelles-Capitale 1070",
    "addr:housenumber":"15",
    "addr:postcode":"1070",
    "addr:street":"Avenue Gounod",
    "iso:country":"BE",
    "sg:address":"Avenue Gounod 15",
    "sg:city":"Bruxelles (anderlecht)",
    "sg:classifiers":[
        {
            "category":"Health Services",
            "subcategory":"Doctor",
            "type":"Services"
        }
    ],
    "sg:phone":"+32 2 428 79 55",
    "sg:postcode":"1070",
    "sg:province":"Bruxelles-Capitale",
    "sg:tags":[
        "medicinephysicians",
        "surgeon"
    ],
    "wof:name":"Lebouchard Marie-philippe",
    "wof:placetype":"venue"
},
  "geometry": {"coordinates":[4.3016119003,50.8318328857],"type":"Point"}
}