{
  "type": "Feature",
  "properties": {
    "addr:full":"Begoniastraat 12 Nazareth Oost-Vlaanderen 9810",
    "addr:housenumber":"12",
    "addr:postcode":"9810",
    "addr:street":"Begoniastraat",
    "iso:country":"BE",
    "sg:address":"Begoniastraat 12",
    "sg:city":"Nazareth",
    "sg:orig_category":"Location de voitures",
    "sg:phone":"+32 9 385 65 46",
    "sg:postcode":"9810",
    "sg:province":"Oost-Vlaanderen",
    "wof:name":"Willy Verhuur Delta Cars",
    "wof:placetype":"venue"
},
  "geometry": {"coordinates":[3.6560459137,50.9723739624],"type":"Point"}
}