{
  "type": "Feature",
  "properties": {
    "iso:country":"BE",
    "sg:address":"Hendrik Consciencestraat 28b1",
    "sg:city":"Leuven",
    "sg:orig_category":"Artsen and specialisten",
    "sg:phone":"+32 16 29 50 78",
    "sg:postcode":"3000",
    "sg:province":"Vlaams-Brabant",
    "wof:name":"Frans Missotten",
    "wof:placetype":"venue"
},
  "geometry": {"coordinates":[4.7008018494,50.8713951111],"type":"Point"}
}