{
  "type": "Feature",
  "properties": {
    "iso:country":"BE",
    "sg:address":"Meelstraat 31",
    "sg:city":"Gent",
    "sg:classifiers":[
        {
            "category":"Home & Garden",
            "subcategory":"Carpets & Floor Coverings",
            "type":"Retail Goods"
        }
    ],
    "sg:phone":"+32 9 233 19 63",
    "sg:postcode":"9000",
    "sg:province":"Oost-Vlaanderen",
    "sg:tags":[
        "repair",
        "restoration",
        "-",
        "rug"
    ],
    "wof:name":"Tamsin Textielconservatie",
    "wof:placetype":"venue"
},
  "geometry": {"coordinates":[3.7172329426,51.0606956482],"type":"Point"}
}