{
  "type": "Feature",
  "properties": {
    "addr:full":"Avenue Van Volxem 80-82 Bruxelles Bruxelles-Capitale 1190",
    "addr:housenumber":"80-82",
    "addr:postcode":"1190",
    "addr:street":"Avenue Van Volxem",
    "iso:country":"BE",
    "sg:address":"Avenue Van Volxem 80-82",
    "sg:city":"Bruxelles",
    "sg:classifiers":[
        {
            "category":"Utilities",
            "subcategory":"Natural Gas",
            "type":"Services"
        }
    ],
    "sg:phone":"+32 2 343 39 32",
    "sg:postcode":"1190",
    "sg:province":"Bruxelles-Capitale",
    "sg:tags":[
        "pyrometer"
    ],
    "wof:name":"Fabritius Ets. S.p.r.l.",
    "wof:placetype":"venue"
},
  "geometry": {"coordinates":[4.3247818947,50.8158874512],"type":"Point"}
}