{
  "type": "Feature",
  "properties": {
    "iso:country":"BE",
    "sg:address":"Katteknok 7",
    "sg:city":"Dentergem",
    "sg:classifiers":[
        {
            "category":"Professional",
            "subcategory":"Management & Consulting",
            "type":"Services"
        }
    ],
    "sg:phone":"+32 51 63 41 04",
    "sg:postcode":"8720",
    "sg:province":"West-Vlaanderen",
    "sg:tags":[
        "consultant"
    ],
    "wof:name":"Demias Bvba",
    "wof:placetype":"venue"
},
  "geometry": {"coordinates":[3.3867959976,50.972442627],"type":"Point"}
}