{
  "type": "Feature",
  "properties": {
    "addr:full":"Vaartdijk 1 Leuven Vlaams-Brabant 3018",
    "addr:housenumber":"1",
    "addr:postcode":"3018",
    "addr:street":"Vaartdijk",
    "iso:country":"BE",
    "sg:address":"Vaartdijk 1",
    "sg:city":"Leuven",
    "sg:orig_category":"Services de Nettoyage and de D\u00e9sinfection",
    "sg:phone":"+32 16 44 75 60",
    "sg:postcode":"3018",
    "sg:province":"Vlaams-Brabant",
    "wof:name":"Vadeca",
    "wof:placetype":"venue"
},
  "geometry": {"coordinates":[4.7011098862,50.9208602905],"type":"Point"}
}