{
  "type": "Feature",
  "properties": {
    "addr:full":"Aartrijkestraat 5 Ichtegem West-Vlaanderen 8480",
    "addr:housenumber":"5",
    "addr:postcode":"8480",
    "addr:street":"Aartrijkestraat",
    "iso:country":"BE",
    "sg:address":"Aartrijkestraat 5",
    "sg:city":"Ichtegem",
    "sg:orig_category":"Pain, p\u00e2tisseries and confiseries",
    "sg:phone":"+32 59 29 94 64",
    "sg:postcode":"8480",
    "sg:province":"West-Vlaanderen",
    "wof:name":"Stefaan Goethals",
    "wof:placetype":"venue"
},
  "geometry": {"coordinates":[3.0276739597,51.1293411255],"type":"Point"}
}