{
  "type": "Feature",
  "properties": {
    "addr:full":"Avenue De Tervueren 313 Bruxelles (woluwe-saint-pierre) Bruxelles-Capitale 1150",
    "addr:housenumber":"313",
    "addr:postcode":"1150",
    "addr:street":"Avenue De Tervueren",
    "iso:country":"BE",
    "sg:address":"Avenue De Tervueren 313",
    "sg:city":"Bruxelles (woluwe-saint-pierre)",
    "sg:classifiers":[
        {
            "category":"Banks & Credit Unions",
            "subcategory":"Investment Brokerage",
            "type":"Services"
        }
    ],
    "sg:phone":"+32 2 772 03 30",
    "sg:postcode":"1150",
    "sg:province":"Bruxelles-Capitale",
    "sg:tags":[
        "auditor"
    ],
    "wof:name":"Theunissen B",
    "wof:placetype":"venue"
},
  "geometry": {"coordinates":[4.4183111191,50.8348731995],"type":"Point"}
}