{
  "type": "Feature",
  "properties": {
    "addr:full":"Rue Sabar\u00c9 124 Vise Li\u00e8ge 4602",
    "addr:housenumber":"124",
    "addr:postcode":"vise;4602",
    "addr:street":"Rue Sabare\u0301",
    "iso:country":"BE",
    "sg:address":"Rue Sabar\u00c9 124",
    "sg:city":"Vise",
    "sg:orig_category":"Epiceries",
    "sg:phone":"+32 4 362 74 60",
    "sg:postcode":"4602",
    "sg:province":"Li\u00e8ge",
    "wof:name":"Pierre Demathieu",
    "wof:placetype":"venue"
},
  "geometry": {"coordinates":[5.683218956,50.6844673157],"type":"Point"}
}