{
  "type": "Feature",
  "properties": {
    "addr:full":"Emile De Becolaan 92 Elsene/ixelles Bruxelles-Capitale 1050",
    "addr:housenumber":"92",
    "addr:postcode":"1050",
    "addr:street":"Emile De Becolaan",
    "iso:country":"BE",
    "sg:address":"Emile De Becolaan 92",
    "sg:city":"Elsene/ixelles",
    "sg:orig_category":"Artsen and specialisten",
    "sg:phone":"+32 2 644 98 86",
    "sg:postcode":"1050",
    "sg:province":"Bruxelles-Capitale",
    "wof:name":"Anne Freart",
    "wof:placetype":"venue"
},
  "geometry": {"coordinates":[4.3838281631,50.821521759],"type":"Point"}
}