{
  "type": "Feature",
  "properties": {
    "addr:full":"Gentstraat 114 Sint-niklaas Oost-Vlaanderen 9111",
    "addr:housenumber":"114",
    "addr:postcode":"9111",
    "addr:street":"Gentstraat",
    "iso:country":"BE",
    "sg:address":"Gentstraat 114",
    "sg:city":"Sint-niklaas",
    "sg:orig_category":"Eleveurs de bovins",
    "sg:phone":"+32 3 776 09 25",
    "sg:postcode":"9111",
    "sg:province":"Oost-Vlaanderen",
    "wof:name":"Achiel Verbeke",
    "wof:placetype":"venue"
},
  "geometry": {"coordinates":[4.0897397995,51.1463394165],"type":"Point"}
}