{
  "type": "Feature",
  "properties": {
    "iso:country":"BE",
    "sg:address":"Vredelaan 75",
    "sg:city":"Kortrijk",
    "sg:classifiers":[
        {
            "category":"Social Services",
            "subcategory":"Child Care",
            "type":"Services"
        }
    ],
    "sg:phone":"+32 56 22 30 34",
    "sg:postcode":"8500",
    "sg:province":"West-Vlaanderen",
    "sg:tags":[
        "children's",
        "nightwear",
        "pyjama"
    ],
    "wof:name":"Excello Nv",
    "wof:placetype":"venue"
},
  "geometry": {"coordinates":[3.2882499695,50.8268051147],"type":"Point"}
}