{
  "type": "Feature",
  "properties": {
    "addr:full":"Vanderveldenlaan 48 Beersel Vlaams-Brabant 1652",
    "addr:housenumber":"48",
    "addr:postcode":"1652",
    "addr:street":"Vanderveldenlaan",
    "iso:country":"BE",
    "sg:address":"Vanderveldenlaan 48",
    "sg:city":"Beersel",
    "sg:orig_category":"Boekhouders",
    "sg:phone":"+32 2 380 65 07",
    "sg:postcode":"1652",
    "sg:province":"Vlaams-Brabant",
    "wof:name":"Nadine Daniel",
    "wof:placetype":"venue"
},
  "geometry": {"coordinates":[4.3394899368,50.7426376343],"type":"Point"}
}