{
  "type": "Feature",
  "properties": {
    "iso:country":"BE",
    "sg:address":"Clos Des Gen\u00eats 17",
    "sg:city":"Chaumont-gistoux",
    "sg:classifiers":[
        {
            "category":"Government",
            "subcategory":"Embassy",
            "type":"Public Place"
        }
    ],
    "sg:phone":"+32 10 68 92 12",
    "sg:postcode":"1325",
    "sg:province":"Brabant Wallon",
    "sg:tags":[
        "consulate"
    ],
    "wof:name":"Maldives (consulat)",
    "wof:placetype":"venue"
},
  "geometry": {"coordinates":[4.7108922005,50.6883926392],"type":"Point"}
}