{
  "type": "Feature",
  "properties": {
    "addr:full":"Kareelveld 6 Halle Vlaams-Brabant 1500",
    "addr:housenumber":"6",
    "addr:postcode":"1500",
    "addr:street":"Kareelveld",
    "iso:country":"BE",
    "sg:address":"Kareelveld 6",
    "sg:city":"Halle",
    "sg:classifiers":[
        {
            "category":"Insurance",
            "subcategory":"Insurance Agent",
            "type":"Services"
        }
    ],
    "sg:phone":"+32 2 361 00 52",
    "sg:postcode":"1500",
    "sg:province":"Vlaams-Brabant",
    "sg:tags":[
        "broker"
    ],
    "wof:name":"Vallverass Cv",
    "wof:placetype":"venue"
},
  "geometry": {"coordinates":[4.2167568207,50.7398109436],"type":"Point"}
}