{
  "type": "Feature",
  "properties": {
    "addr:full":"Place Polydore Beaufaux 10 Wavre Brabant Wallon 1300",
    "addr:housenumber":"10;1300",
    "addr:street":"Place Polydore Beaufaux",
    "iso:country":"BE",
    "sg:address":"Place Polydore Beaufaux 10",
    "sg:city":"Wavre",
    "sg:classifiers":[
        {
            "category":"Shopping",
            "subcategory":"Crafts & Fabrics",
            "type":"Retail Goods"
        }
    ],
    "sg:phone":"+32 10 24 81 09",
    "sg:postcode":"1300",
    "sg:province":"Brabant Wallon",
    "sg:tags":[
        "upholstery",
        "-"
    ],
    "wof:name":"Maison D'elodie (la)",
    "wof:placetype":"venue"
},
  "geometry": {"coordinates":[4.6247019768,50.7218055725],"type":"Point"}
}