{
  "type": "Feature",
  "properties": {
    "iso:country":"BE",
    "sg:address":"Brugsebaan 5ba",
    "sg:city":"Lichtervelde",
    "sg:orig_category":"Producteurs de l\u00e9gumes",
    "sg:phone":"+32 51 72 39 41",
    "sg:postcode":"8810",
    "sg:province":"West-Vlaanderen",
    "wof:name":"Dirk Vanbelle",
    "wof:placetype":"venue"
},
  "geometry": {"coordinates":[3.1110959053,51.0250358582],"type":"Point"}
}