{
  "type": "Feature",
  "properties": {
    "addr:full":"Bevrijdingsstraat 7 Ham (oostham) Limburg 3945",
    "addr:housenumber":"7",
    "addr:postcode":"oostham;3945",
    "addr:street":"Bevrijdingsstraat",
    "iso:country":"BE",
    "sg:address":"Bevrijdingsstraat 7",
    "sg:city":"Ham (oostham)",
    "sg:classifiers":[
        {
            "category":"Health Services",
            "subcategory":"Doctor",
            "type":"Services"
        }
    ],
    "sg:phone":"+32 11 34 17 31",
    "sg:postcode":"3945",
    "sg:province":"Limburg",
    "sg:tags":[
        "medicinephysicians",
        "surgeon"
    ],
    "wof:name":"Denayer J",
    "wof:placetype":"venue"
},
  "geometry": {"coordinates":[5.1776199341,51.1046104431],"type":"Point"}
}