{
  "type": "Feature",
  "properties": {
    "iso:country":"BE",
    "sg:address":"Grand Route 245",
    "sg:city":"Verlaine",
    "sg:orig_category":"Woningbouw",
    "sg:phone":"+32 4 259 64 76",
    "sg:postcode":"4537",
    "sg:province":"Li\u00e8ge",
    "wof:name":"Ets Cabert Construct",
    "wof:placetype":"venue"
},
  "geometry": {"coordinates":[5.3370060921,50.6063156128],"type":"Point"}
}