{
  "type": "Feature",
  "properties": {
    "addr:full":"Antwerpsesteenweg 271-1a Kapellen Antwerpen 2950",
    "addr:housenumber":"271-1a",
    "addr:postcode":"2950",
    "addr:street":"Antwerpsesteenweg",
    "iso:country":"BE",
    "sg:address":"Antwerpsesteenweg 271-1a",
    "sg:city":"Kapellen",
    "sg:classifiers":[
        {
            "category":"Health Services",
            "subcategory":"Doctor",
            "type":"Services"
        }
    ],
    "sg:phone":"+32 3 664 21 08",
    "sg:postcode":"2950",
    "sg:province":"Antwerpen",
    "sg:tags":[
        "medicinephysicians",
        "surgeon"
    ],
    "wof:name":"De Ridder G",
    "wof:placetype":"venue"
},
  "geometry": {"coordinates":[4.4375982285,51.3015632629],"type":"Point"}
}