{
  "type": "Feature",
  "properties": {
    "addr:full":"Warnach 9 Fauvillers Luxembourg 6637",
    "addr:housenumber":"9",
    "addr:postcode":"6637",
    "addr:street":"Warnach",
    "iso:country":"BE",
    "sg:address":"Warnach 9",
    "sg:city":"Fauvillers",
    "sg:orig_category":"Eleveurs and marchands de porcs. Eleveurs de bovins. Installation de menuiserie en bois and plastiqu",
    "sg:phone":"+32 63 60 14 49",
    "sg:postcode":"6637",
    "sg:province":"Luxembourg",
    "wof:name":"Martial Brassel",
    "wof:placetype":"venue"
},
  "geometry": {"coordinates":[5.6638197899,49.8519592285],"type":"Point"}
}