{
  "type": "Feature",
  "properties": {
    "addr:full":"Harelbeeksestraat 50 Kuurne West-Vlaanderen 8520",
    "addr:housenumber":"50",
    "addr:postcode":"8520",
    "addr:street":"Harelbeeksestraat",
    "iso:country":"BE",
    "sg:address":"Harelbeeksestraat 50",
    "sg:city":"Kuurne",
    "sg:orig_category":"Plaatsen van vloer- and muurbekleding Schilders",
    "sg:phone":"+32 56 71 13 27",
    "sg:postcode":"8520",
    "sg:province":"West-Vlaanderen",
    "wof:name":"Matton Interieur",
    "wof:placetype":"venue"
},
  "geometry": {"coordinates":[3.2930591106,50.8500862122],"type":"Point"}
}