{
  "type": "Feature",
  "properties": {
    "iso:country":"BE",
    "sg:address":"Egemveldweg 4",
    "sg:city":"Pittem (egem)",
    "sg:classifiers":[
        {
            "category":"Farming",
            "subcategory":"Farm & Veterinary Services",
            "type":"Manufacturing & Wholesale Goods"
        }
    ],
    "sg:phone":"+32 51 61 13 59",
    "sg:postcode":"8740",
    "sg:province":"West-Vlaanderen",
    "sg:tags":[
        "agricultural",
        "contractor"
    ],
    "wof:name":"Van Bruwaene Roger",
    "wof:placetype":"venue"
},
  "geometry": {"coordinates":[3.2592189312,51.0314598083],"type":"Point"}
}