{
  "type": "Feature",
  "properties": {
    "addr:full":"Kapellestraat 19 Lokeren Oost-Vlaanderen 9160",
    "addr:housenumber":"19",
    "addr:postcode":"9160",
    "addr:street":"Kapellestraat",
    "iso:country":"BE",
    "sg:address":"Kapellestraat 19",
    "sg:city":"Lokeren",
    "sg:orig_category":"Herstellingen and onderhoud van auto's Voertuigen",
    "sg:phone":"+32 9 349 59 01",
    "sg:postcode":"9160",
    "sg:province":"Oost-Vlaanderen",
    "wof:name":"Garage K-motors",
    "wof:placetype":"venue"
},
  "geometry": {"coordinates":[3.9857909679,51.1016654968],"type":"Point"}
}