{
  "type": "Feature",
  "properties": {
    "addr:full":"Sinteldreef 6-1 Turnhout Antwerpen 2300",
    "addr:housenumber":"6-1",
    "addr:postcode":"2300",
    "addr:street":"Sinteldreef",
    "iso:country":"BE",
    "sg:address":"Sinteldreef 6-1",
    "sg:city":"Turnhout",
    "sg:classifiers":[
        {
            "category":"Building & Trades",
            "subcategory":"Construction",
            "type":"Services"
        }
    ],
    "sg:phone":"+32 14 43 34 07",
    "sg:postcode":"2300",
    "sg:province":"Antwerpen",
    "sg:tags":[
        "carpenter"
    ],
    "wof:name":"Roja",
    "wof:placetype":"venue"
},
  "geometry": {"coordinates":[4.9362912178,51.3077507019],"type":"Point"}
}