{
  "type": "Feature",
  "properties": {
    "iso:country":"BE",
    "sg:address":"Weemstraat 5",
    "sg:city":"Hoeilaart",
    "sg:classifiers":[
        {
            "category":"Utilities",
            "subcategory":"Fuel Oil & Lpg",
            "type":"Services"
        }
    ],
    "sg:phone":"+32 2 657 11 80",
    "sg:postcode":"1560",
    "sg:province":"Vlaams-Brabant",
    "wof:name":"Containers & Vervoer Soret",
    "wof:placetype":"venue"
},
  "geometry": {"coordinates":[4.4795231819,50.7661972046],"type":"Point"}
}