{
  "type": "Feature",
  "properties": {
    "iso:country":"BE",
    "sg:address":"Stationsstraat 51",
    "sg:city":"Eeklo",
    "sg:orig_category":"Diverse kredietdiensten",
    "sg:postcode":"9900",
    "sg:province":"Oost-Vlaanderen",
    "wof:name":"Postomat Eeklo",
    "wof:placetype":"venue"
},
  "geometry": {"coordinates":[3.5700769424,51.183139801],"type":"Point"}
}