{
  "type": "Feature",
  "properties": {
    "addr:full":"Klipgaardestraat 24 Kortenaken (waanrode) Vlaams-Brabant 3473",
    "addr:housenumber":"24",
    "addr:postcode":"3473",
    "addr:street":"Klipgaardestraat",
    "iso:country":"BE",
    "sg:address":"Klipgaardestraat 24",
    "sg:city":"Kortenaken (waanrode)",
    "sg:classifiers":[
        {
            "category":"Bakery",
            "type":"Food & Drink"
        }
    ],
    "sg:phone":"+32 16 77 03 93",
    "sg:postcode":"3473",
    "sg:province":"Vlaams-Brabant",
    "sg:tags":[
        "confectioner",
        "baker"
    ],
    "wof:name":"Broodhuisje (het)",
    "wof:placetype":"venue"
},
  "geometry": {"coordinates":[4.9851899147,50.9183807373],"type":"Point"}
}