{
  "type": "Feature",
  "properties": {
    "addr:full":"Rue Du Onze Novembre 22 Grace-hollogne Li\u00e8ge 4460",
    "addr:housenumber":"22",
    "addr:postcode":"4460",
    "addr:street":"Rue Du Onze Novembre",
    "iso:country":"BE",
    "sg:address":"Rue Du Onze Novembre 22",
    "sg:city":"Grace-hollogne",
    "sg:orig_category":"Enseignement maternel and primaire",
    "sg:phone":"+32 4 250 44 04",
    "sg:postcode":"4460",
    "sg:province":"Li\u00e8ge",
    "wof:name":"Ecole Fondamentale Libre",
    "wof:placetype":"venue"
},
  "geometry": {"coordinates":[5.3980221748,50.6249313354],"type":"Point"}
}