{
  "type": "Feature",
  "properties": {
    "iso:country":"BE",
    "sg:address":"Brusselsesteenweg 88",
    "sg:city":"Halle",
    "sg:orig_category":"Medische and orthopedische apparaten",
    "sg:phone":"+32 2 356 67 47",
    "sg:postcode":"1500",
    "sg:province":"Vlaams-Brabant",
    "wof:name":"Jean Louis",
    "wof:placetype":"venue"
},
  "geometry": {"coordinates":[4.2385878563,50.7394752502],"type":"Point"}
}