{
  "type": "Feature",
  "properties": {
    "addr:full":"Avenue De Norv\u00e8ge 29 Malmedy Li\u00e8ge 4960",
    "addr:housenumber":"29",
    "addr:postcode":"4960",
    "addr:street":"Avenue De Norve\u0300Ge",
    "iso:country":"BE",
    "sg:address":"Avenue De Norv\u00e8ge 29",
    "sg:city":"Malmedy",
    "sg:classifiers":[
        {
            "category":"Wholesale",
            "subcategory":"Machinery & Supplies",
            "type":"Manufacturing & Wholesale Goods"
        }
    ],
    "sg:phone":"+32 80 77 13 27",
    "sg:postcode":"4960",
    "sg:province":"Li\u00e8ge",
    "sg:tags":[
        "refrigeration",
        "-",
        "industrial",
        "commercial",
        "equipment"
    ],
    "wof:name":"Geltech Sprl",
    "wof:placetype":"venue"
},
  "geometry": {"coordinates":[5.9995751381,50.4141921997],"type":"Point"}
}