{
  "type": "Feature",
  "properties": {
    "addr:full":"Basiliekstraat 17 Halle Vlaams-Brabant 1500",
    "addr:housenumber":"17",
    "addr:postcode":"1500",
    "addr:street":"Basiliekstraat",
    "iso:country":"BE",
    "sg:address":"Basiliekstraat 17",
    "sg:city":"Halle",
    "sg:orig_category":"S\u00e9curit\u00e9 sociale",
    "sg:phone":"+32 2 360 30 39",
    "sg:postcode":"1500",
    "sg:province":"Vlaams-Brabant",
    "wof:name":"Socialist. Mutualiteit",
    "wof:placetype":"venue"
},
  "geometry": {"coordinates":[4.2369990349,50.7356033325],"type":"Point"}
}