{
  "type": "Feature",
  "properties": {
    "iso:country":"BE",
    "sg:address":"Derde Industriezone 6",
    "sg:city":"Aalst",
    "sg:orig_category":"Installation de serres, double vitrage and fen\u00eatres. Installation de menuiserie m\u00e9tallique. Rev\u00eateme",
    "sg:phone":"+32 53 83 95 45",
    "sg:postcode":"9320",
    "sg:province":"Oost-Vlaanderen",
    "wof:name":"De Geyndt T.",
    "wof:placetype":"venue"
},
  "geometry": {"coordinates":[4.0553851128,50.9209976196],"type":"Point"}
}