{
  "type": "Feature",
  "properties": {
    "addr:full":"Ringshoppingcenter 120 Kortrijk West-Vlaanderen 8500",
    "addr:housenumber":"120",
    "addr:postcode":"8500",
    "iso:country":"BE",
    "sg:address":"Ringshoppingcenter 120",
    "sg:city":"Kortrijk",
    "sg:classifiers":[
        {
            "category":"Shopping",
            "subcategory":"Jewelry",
            "type":"Retail Goods"
        }
    ],
    "sg:phone":"+32 56 37 31 59",
    "sg:postcode":"8500",
    "sg:province":"West-Vlaanderen",
    "sg:tags":[
        "-",
        "imitation"
    ],
    "wof:name":"Bijoux",
    "wof:placetype":"venue"
},
  "geometry": {"coordinates":[3.2650549412,50.827999115],"type":"Point"}
}