{
  "type": "Feature",
  "properties": {
    "addr:full":"Kruisstraat 134 Kortenberg Vlaams-Brabant 3070",
    "addr:housenumber":"134",
    "addr:postcode":"3070",
    "addr:street":"Kruisstraat;Vlaams-Brabant",
    "iso:country":"BE",
    "sg:address":"Kruisstraat 134",
    "sg:city":"Kortenberg",
    "sg:orig_category":"Huisdieren and benodigdheden",
    "sg:phone":"+32 2 759 31 13",
    "sg:postcode":"3070",
    "sg:province":"Vlaams-Brabant",
    "wof:name":"Ronsmans",
    "wof:placetype":"venue"
},
  "geometry": {"coordinates":[4.5457181931,50.8773384094],"type":"Point"}
}