{
  "type": "Feature",
  "properties": {
    "addr:full":"Watermolenstraat 8 Essen Antwerpen 2910",
    "addr:housenumber":"8",
    "addr:postcode":"2910",
    "addr:street":"Watermolenstraat",
    "iso:country":"BE",
    "sg:address":"Watermolenstraat 8",
    "sg:city":"Essen",
    "sg:classifiers":[
        {
            "category":"Personal",
            "subcategory":"Beauty Salon",
            "type":"Services"
        }
    ],
    "sg:phone":"+32 3 677 03 80",
    "sg:postcode":"2910",
    "sg:province":"Antwerpen",
    "sg:tags":[
        "lady",
        "-",
        "hairdressing"
    ],
    "wof:name":"Snit & Style",
    "wof:placetype":"venue"
},
  "geometry": {"coordinates":[4.4744949341,51.4652481079],"type":"Point"}
}