{
  "type": "Feature",
  "properties": {
    "addr:full":"Essenhoutstraat 292 Kapellen Antwerpen 2950",
    "addr:housenumber":"292",
    "addr:postcode":"2950",
    "addr:street":"Essenhoutstraat",
    "iso:country":"BE",
    "sg:address":"Essenhoutstraat 292",
    "sg:city":"Kapellen",
    "sg:orig_category":"Installatie van houten of kunststof schrijnwerk",
    "sg:phone":"+32 3 665 37 59",
    "sg:postcode":"2950",
    "sg:province":"Antwerpen",
    "wof:name":"Luc Baeten",
    "wof:placetype":"venue"
},
  "geometry": {"coordinates":[4.4175171852,51.3073616028],"type":"Point"}
}