{
  "type": "Feature",
  "properties": {
    "iso:country":"BE",
    "sg:address":"Kammerstraat 23",
    "sg:city":"Gent",
    "sg:classifiers":[
        {
            "category":"Bars & Pubs",
            "type":"Food & Drink"
        }
    ],
    "sg:phone":"+32 475 58 96 20",
    "sg:postcode":"9000",
    "sg:province":"Oost-Vlaanderen",
    "wof:name":"Gents Geestenrijk ('t)",
    "wof:placetype":"venue"
},
  "geometry": {"coordinates":[3.7271590233,51.0559768677],"type":"Point"}
}