{
  "type": "Feature",
  "properties": {
    "addr:full":"Rue Du Ch\u00c2telain 49 Elsene/ixelles Bruxelles-Capitale 1050",
    "addr:housenumber":"49",
    "addr:postcode":"1050",
    "addr:street":"Rue Du Cha\u0302Telain",
    "iso:country":"BE",
    "sg:address":"Rue Du Ch\u00c2telain 49",
    "sg:city":"Elsene/ixelles",
    "sg:classifiers":[
        {
            "category":"Professional",
            "subcategory":"Business Services",
            "type":"Services"
        }
    ],
    "sg:phone":"+32 2 649 15 29",
    "sg:postcode":"1050",
    "sg:province":"Bruxelles-Capitale",
    "sg:tags":[
        "aux",
        "diver",
        "entreprises"
    ],
    "wof:name":"Bazelaire & Partners",
    "wof:placetype":"venue"
},
  "geometry": {"coordinates":[4.3618998528,50.8256263733],"type":"Point"}
}