{
  "type": "Feature",
  "properties": {
    "addr:full":"Romeinse Steenweg 754 Wemmel Vlaams-Brabant 1780",
    "addr:housenumber":"754",
    "addr:postcode":"1780",
    "addr:street":"Romeinse Steenweg;Vlaams-Brabant",
    "iso:country":"BE",
    "sg:address":"Romeinse Steenweg 754",
    "sg:city":"Wemmel",
    "sg:orig_category":"Dakwerken",
    "sg:phone":"+32 2 460 67 04",
    "sg:postcode":"1780",
    "sg:province":"Vlaams-Brabant",
    "wof:name":"Dumebati",
    "wof:placetype":"venue"
},
  "geometry": {"coordinates":[4.3192830086,50.8952407837],"type":"Point"}
}