{
  "type": "Feature",
  "properties": {
    "iso:country":"BE",
    "sg:address":"Moeresteenweg 9",
    "sg:city":"Veurne (houtem)",
    "sg:classifiers":[
        {
            "category":"Freight",
            "type":"Transportation"
        }
    ],
    "sg:phone":"+32 58 29 93 47",
    "sg:postcode":"8630",
    "sg:province":"West-Vlaanderen",
    "sg:tags":[
        "-",
        "transport"
    ],
    "wof:name":"Coopman",
    "wof:placetype":"venue"
},
  "geometry": {"coordinates":[2.6111080647,51.0111427307],"type":"Point"}
}