{
  "type": "Feature",
  "properties": {
    "iso:country":"BE",
    "sg:address":"Tombroekmolenstraat 4",
    "sg:city":"Kortrijk",
    "sg:orig_category":"Boucheries",
    "sg:phone":"+32 56 21 52 81",
    "sg:postcode":"8510",
    "sg:province":"West-Vlaanderen",
    "wof:name":"Luc Christiaens",
    "wof:placetype":"venue"
},
  "geometry": {"coordinates":[3.2646050453,50.7508392334],"type":"Point"}
}