{
  "type": "Feature",
  "properties": {
    "iso:country":"BE",
    "sg:address":"Egemstraat 21",
    "sg:city":"Erpe-mere",
    "sg:orig_category":"Woningbouw",
    "sg:phone":"+32 53 62 10 14",
    "sg:postcode":"9420",
    "sg:province":"Oost-Vlaanderen",
    "wof:name":"Patrick Neerinckx",
    "wof:placetype":"venue"
},
  "geometry": {"coordinates":[3.930216074,50.9235992432],"type":"Point"}
}