{
  "type": "Feature",
  "properties": {
    "addr:full":"Bruggesteenweg 98 Meulebeke West-Vlaanderen 8760",
    "addr:housenumber":"98",
    "addr:postcode":"8760",
    "addr:street":"Bruggesteenweg",
    "iso:country":"BE",
    "sg:address":"Bruggesteenweg 98",
    "sg:city":"Meulebeke",
    "sg:orig_category":"Entretien and r\u00e9parations de voitures. Stations-service and carburants",
    "sg:phone":"+32 51 48 86 19",
    "sg:postcode":"8760",
    "sg:province":"West-Vlaanderen",
    "wof:name":"Texaco",
    "wof:placetype":"venue"
},
  "geometry": {"coordinates":[3.2450199127,50.95885849],"type":"Point"}
}