{
  "type": "Feature",
  "properties": {
    "addr:full":"Oudestraat 28 Peer Limburg 3990",
    "addr:housenumber":"28",
    "addr:postcode":"3990",
    "addr:street":"Oudestraat",
    "iso:country":"BE",
    "sg:address":"Oudestraat 28",
    "sg:city":"Peer",
    "sg:orig_category":"Epiceries",
    "sg:phone":"+32 11 63 62 98",
    "sg:postcode":"3990",
    "sg:province":"Limburg",
    "wof:name":"Huis 't Soetleven",
    "wof:placetype":"venue"
},
  "geometry": {"coordinates":[5.4586501122,51.131149292],"type":"Point"}
}