{
  "type": "Feature",
  "properties": {
    "iso:country":"BE",
    "sg:address":"Deinsesteenweg 88",
    "sg:city":"Kruishoutem",
    "sg:classifiers":[
        {
            "category":"Building & Trades",
            "subcategory":"Construction",
            "type":"Services"
        }
    ],
    "sg:phone":"+32 9 386 70 29",
    "sg:postcode":"9770",
    "sg:province":"Oost-Vlaanderen",
    "sg:tags":[
        "carpenter"
    ],
    "wof:name":"Balcaen F",
    "wof:placetype":"venue"
},
  "geometry": {"coordinates":[3.5316209793,50.9228973389],"type":"Point"}
}