{
  "type": "Feature",
  "properties": {
    "iso:country":"BE",
    "sg:address":"Rue Des Grottes 2-6",
    "sg:city":"Rochefort",
    "sg:classifiers":[
        {
            "category":"Travel",
            "subcategory":"Hotels & Motels",
            "type":"Entertainment"
        }
    ],
    "sg:phone":"+32 84 37 72 20",
    "sg:postcode":"5580",
    "sg:province":"Namur",
    "sg:tags":[
        "restaurant"
    ],
    "wof:name":"H\u00d4tel Des Ardennes",
    "wof:placetype":"venue"
},
  "geometry": {"coordinates":[5.2231431007,50.1608505249],"type":"Point"}
}