{
  "type": "Feature",
  "properties": {
    "iso:country":"BE",
    "sg:address":"Chauss\u00c9e De Bruxelles 346",
    "sg:city":"Vorst/forest",
    "sg:orig_category":"Artistes ind\u00e9pendants",
    "sg:phone":"+32 2 345 88 53",
    "sg:postcode":"1190",
    "sg:province":"Bruxelles-Capitale",
    "wof:name":"Liliane Broes",
    "wof:placetype":"venue"
},
  "geometry": {"coordinates":[4.3299617767,50.8196334839],"type":"Point"}
}