{
  "type": "Feature",
  "properties": {
    "iso:country":"BE",
    "sg:address":"Rue Des Artisans 10ba",
    "sg:city":"Anhee",
    "sg:orig_category":"Musea and historische gebouwen",
    "sg:phone":"+32 82 69 90 62",
    "sg:postcode":"5537",
    "sg:province":"Namur",
    "wof:name":"Mus\u00c9e Bois & Mus\u00c9e Rural",
    "wof:placetype":"venue"
},
  "geometry": {"coordinates":[4.7533659935,50.2997703552],"type":"Point"}
}