{
  "type": "Feature",
  "properties": {
    "addr:full":"Rue Auguste-hock 12 Li\u00e8ge 1 (li\u00e8ge 2) Li\u00e8ge 4020",
    "addr:housenumber":"12;1;2",
    "addr:postcode":"4020",
    "addr:street":"Rue Auguste-Hock",
    "iso:country":"BE",
    "sg:address":"Rue Auguste-hock 12",
    "sg:city":"Li\u00e8ge 1 (li\u00e8ge 2)",
    "sg:classifiers":[
        {
            "category":"Health Services",
            "subcategory":"Health Practitioner",
            "type":"Services"
        }
    ],
    "sg:phone":"+32 4 342 04 25",
    "sg:postcode":"4020",
    "sg:province":"Li\u00e8ge",
    "sg:tags":[
        "psychologist"
    ],
    "wof:name":"Chapelier M",
    "wof:placetype":"venue"
},
  "geometry": {"coordinates":[5.5803160667,50.6268768311],"type":"Point"}
}