{
  "type": "Feature",
  "properties": {
    "addr:full":"Duffelshoek 80-82 Kontich Antwerpen 2550",
    "addr:postcode":"80-82;2550",
    "addr:street":"Duffelshoek",
    "iso:country":"BE",
    "sg:address":"Duffelshoek 80-82",
    "sg:city":"Kontich",
    "sg:classifiers":[
        {
            "category":"Home & Garden",
            "subcategory":"Carpets & Floor Coverings",
            "type":"Retail Goods"
        }
    ],
    "sg:phone":"+32 3 290 07 66",
    "sg:postcode":"2550",
    "sg:province":"Antwerpen",
    "sg:tags":[
        "layer",
        "mosaicists"
    ],
    "wof:name":"Tegelbedrijf Taelemans Bvba",
    "wof:placetype":"venue"
},
  "geometry": {"coordinates":[4.4762821198,51.1229667664],"type":"Point"}
}