{
  "type": "Feature",
  "properties": {
    "addr:full":"Avenue Emile Rousseaux 40 Charleroi (marcinelle) Hainaut 6001",
    "addr:housenumber":"40",
    "addr:postcode":"6001",
    "addr:street":"Avenue Emile Rousseaux",
    "iso:country":"BE",
    "sg:address":"Avenue Emile Rousseaux 40",
    "sg:city":"Charleroi (marcinelle)",
    "sg:classifiers":[
        {
            "category":"Building & Trades",
            "subcategory":"Construction",
            "type":"Services"
        }
    ],
    "sg:phone":"+32 71 44 01 50",
    "sg:postcode":"6001",
    "sg:province":"Hainaut",
    "sg:tags":[
        "scaffolding"
    ],
    "wof:name":"E.a.p. Nv",
    "wof:placetype":"venue"
},
  "geometry": {"coordinates":[4.4274878502,50.4021644592],"type":"Point"}
}