{
  "type": "Feature",
  "properties": {
    "addr:full":"Slagmolenstraat 46 Turnhout Antwerpen 2300",
    "addr:housenumber":"46",
    "addr:postcode":"2300",
    "addr:street":"Slagmolenstraat",
    "iso:country":"BE",
    "sg:address":"Slagmolenstraat 46",
    "sg:city":"Turnhout",
    "sg:classifiers":[
        {
            "category":"Fast Food",
            "type":"Food & Drink"
        }
    ],
    "sg:phone":"+32 14 42 57 49",
    "sg:postcode":"2300",
    "sg:province":"Antwerpen",
    "sg:tags":[
        "fried",
        "stand",
        "potato"
    ],
    "wof:name":"Slagmolen (de)",
    "wof:placetype":"venue"
},
  "geometry": {"coordinates":[4.9581289291,51.3023376465],"type":"Point"}
}