{
  "type": "Feature",
  "properties": {
    "iso:country":"BE",
    "sg:address":"Leon Corthalsstraat 4",
    "sg:city":"Temse",
    "sg:classifiers":[
        {
            "category":"Real Estate",
            "subcategory":"Developer",
            "type":"Services"
        }
    ],
    "sg:phone":"+32 3 771 94 56",
    "sg:postcode":"9140",
    "sg:province":"Oost-Vlaanderen",
    "sg:tags":[
        "project"
    ],
    "wof:name":"Rocade Bvba",
    "wof:placetype":"venue"
},
  "geometry": {"coordinates":[4.234307766,51.134979248],"type":"Point"}
}