{
  "type": "Feature",
  "properties": {
    "iso:country":"BE",
    "sg:address":"Bredabaan 55bb",
    "sg:city":"Wuustwezel",
    "sg:orig_category":"D\u00e9molition d\u00b4immeubles and terrassements. Construction de rev\u00eatements routiers and sportifs",
    "sg:phone":"+32 3 669 95 55",
    "sg:postcode":"2990",
    "sg:province":"Antwerpen",
    "wof:name":"Hens",
    "wof:placetype":"venue"
},
  "geometry": {"coordinates":[4.6205711365,51.4214057922],"type":"Point"}
}