{
  "type": "Feature",
  "properties": {
    "addr:full":"Rue De La Glacerie 122 Courcelles Hainaut 6180",
    "addr:housenumber":"122",
    "addr:postcode":"6180",
    "addr:street":"Rue De La Glacerie",
    "iso:country":"BE",
    "sg:address":"Rue De La Glacerie 122",
    "sg:city":"Courcelles",
    "sg:classifiers":[
        {
            "category":"Transit Center",
            "subcategory":"Freight",
            "type":"Transportation"
        }
    ],
    "sg:phone":"+32 71 45 90 10",
    "sg:postcode":"6180",
    "sg:province":"Hainaut",
    "sg:tags":[
        "tanker",
        "-",
        "transport"
    ],
    "wof:name":"Transports Dennis-buxant Sa",
    "wof:placetype":"venue"
},
  "geometry": {"coordinates":[4.3974509239,50.4664993286],"type":"Point"}
}