{
  "type": "Feature",
  "properties": {
    "iso:country":"BE",
    "sg:address":"Oratori\u00ebnlaan 12",
    "sg:city":"Meise",
    "sg:classifiers":[
        {
            "category":"Health Services",
            "subcategory":"Doctor",
            "type":"Services"
        }
    ],
    "sg:phone":"+32 2 270 32 91",
    "sg:postcode":"1860",
    "sg:province":"Vlaams-Brabant",
    "sg:tags":[
        "medicinephysicians",
        "surgeon"
    ],
    "wof:name":"Jansens J-l",
    "wof:placetype":"venue"
},
  "geometry": {"coordinates":[4.3350391388,50.9376602173],"type":"Point"}
}