{
  "type": "Feature",
  "properties": {
    "iso:country":"BE",
    "sg:address":"Grensstraat 18",
    "sg:city":"Hechtel-eksel",
    "sg:orig_category":"Pleisterwerk",
    "sg:phone":"+32 11 73 35 39",
    "sg:postcode":"3941",
    "sg:province":"Limburg",
    "wof:name":"Joannes Van De Perre",
    "wof:placetype":"venue"
},
  "geometry": {"coordinates":[5.3998789787,51.1626396179],"type":"Point"}
}