{
  "type": "Feature",
  "properties": {
    "iso:country":"BE",
    "sg:address":"Beersebaan 110",
    "sg:city":"Lille",
    "sg:orig_category":"Mat\u00e9riaux de construction Gr",
    "sg:phone":"+32 14 55 62 19",
    "sg:postcode":"2275",
    "sg:province":"Antwerpen",
    "wof:name":"Wuyts Ludo",
    "wof:placetype":"venue"
},
  "geometry": {"coordinates":[4.8641638756,51.2765045166],"type":"Point"}
}