{
  "type": "Feature",
  "properties": {
    "addr:full":"Rue De Moha 17 Gembloux Namur 5030",
    "addr:housenumber":"17",
    "addr:postcode":"5030",
    "addr:street":"Rue De Moha;Namur",
    "iso:country":"BE",
    "sg:address":"Rue De Moha 17",
    "sg:city":"Gembloux",
    "sg:classifiers":[
        {
            "category":"Manufacturing",
            "subcategory":"Rubber & Plastics",
            "type":"Manufacturing & Wholesale Goods"
        }
    ],
    "sg:phone":"+32 3 324 78 75",
    "sg:postcode":"5030",
    "sg:province":"Namur",
    "sg:tags":[
        "item",
        "household",
        "made"
    ],
    "wof:name":"Plastinova Nv",
    "wof:placetype":"venue"
},
  "geometry": {"coordinates":[4.4662871361,51.2373924255],"type":"Point"}
}