{
  "type": "Feature",
  "properties": {
    "addr:full":"Frenet 1125 Bertogne Luxembourg 6686",
    "addr:postcode":"1125;6686",
    "addr:street":"Frenet",
    "iso:country":"BE",
    "sg:address":"Frenet 1125",
    "sg:city":"Bertogne",
    "sg:orig_category":"Rundveehouders",
    "sg:phone":"+32 61 21 14 72",
    "sg:postcode":"6686",
    "sg:province":"Luxembourg",
    "wof:name":"Jules Peche",
    "wof:placetype":"venue"
},
  "geometry": {"coordinates":[5.6269741058,50.0493125916],"type":"Point"}
}