{
  "type": "Feature",
  "properties": {
    "addr:full":"Tournebride 53 Lanaken Limburg 3620",
    "addr:housenumber":"53",
    "addr:postcode":"3620",
    "addr:street":"Tournebride",
    "iso:country":"BE",
    "sg:address":"Tournebride 53",
    "sg:city":"Lanaken",
    "sg:classifiers":[
        {
            "category":"Restaurant",
            "type":"Food & Drink"
        }
    ],
    "sg:phone":"+32 89 72 19 86",
    "sg:postcode":"3620",
    "sg:province":"Limburg",
    "wof:name":"Filling Station",
    "wof:placetype":"venue"
},
  "geometry": {"coordinates":[5.6784629822,50.9032897949],"type":"Point"}
}