{
  "type": "Feature",
  "properties": {
    "addr:full":"Rue De L'industrie 75 Binche Hainaut 7134",
    "addr:housenumber":"75",
    "addr:postcode":"7134",
    "addr:street":"Rue De L'Industrie",
    "iso:country":"BE",
    "sg:address":"Rue De L'industrie 75",
    "sg:city":"Binche",
    "sg:orig_category":"Plaatsen van vloer- and muurbekleding Woningbouw",
    "sg:phone":"+32 64 34 02 20",
    "sg:postcode":"7134",
    "sg:province":"Hainaut",
    "wof:name":"G.a.c.e.",
    "wof:placetype":"venue"
},
  "geometry": {"coordinates":[4.190320015,50.4274864197],"type":"Point"}
}