{
  "type": "Feature",
  "properties": {
    "iso:country":"BE",
    "sg:address":"Kuregemstraat 18",
    "sg:city":"Machelen",
    "sg:classifiers":[
        {
            "category":"Restaurant",
            "type":"Food & Drink"
        }
    ],
    "sg:phone":"+32 2 720 40 49",
    "sg:postcode":"1831",
    "sg:province":"Vlaams-Brabant",
    "sg:tags":[
        "caf\u00e9s"
    ],
    "wof:name":"'t Stopsel",
    "wof:placetype":"venue"
},
  "geometry": {"coordinates":[4.4312200546,50.8955192566],"type":"Point"}
}