{
  "type": "Feature",
  "properties": {
    "iso:country":"BE",
    "sg:address":"Slotlaan 2b4",
    "sg:city":"Sint-lambrechts-woluwe/woluwe-saint-lambert",
    "sg:orig_category":"Advocaten and juridische adviseurs",
    "sg:phone":"+32 2 734 58 80",
    "sg:postcode":"1200",
    "sg:province":"Bruxelles-Capitale",
    "wof:name":"M.t. Hanotiau",
    "wof:placetype":"venue"
},
  "geometry": {"coordinates":[4.413877964,50.8419952393],"type":"Point"}
}