{
  "type": "Feature",
  "properties": {
    "iso:country":"BE",
    "sg:address":"Rue Pasquier Grenier 4",
    "sg:city":"Tournai",
    "sg:classifiers":[
        {
            "category":"Shopping",
            "subcategory":"Stationery & Office Supplies",
            "type":"Retail Goods"
        }
    ],
    "sg:phone":"+32 69 89 51 77",
    "sg:postcode":"7500",
    "sg:province":"Hainaut",
    "wof:name":"Sofures.com",
    "wof:placetype":"venue"
},
  "geometry": {"coordinates":[3.3780989647,50.6196899414],"type":"Point"}
}