{
  "type": "Feature",
  "properties": {
    "addr:full":"Quai Des Vennes 1 Liege Li\u00e8ge 4020",
    "addr:housenumber":"1",
    "addr:postcode":"4020",
    "addr:street":"Quai Des Vennes",
    "iso:country":"BE",
    "sg:address":"Quai Des Vennes 1",
    "sg:city":"Liege",
    "sg:orig_category":"Speelgoed",
    "sg:phone":"+32 4 342 89 00",
    "sg:postcode":"4020",
    "sg:province":"Li\u00e8ge",
    "wof:name":"Christiaensen",
    "wof:placetype":"venue"
},
  "geometry": {"coordinates":[5.5938649178,50.6163520813],"type":"Point"}
}