{
  "type": "Feature",
  "properties": {
    "iso:country":"BE",
    "sg:address":"Rijmenamseweg 126",
    "sg:city":"Bonheiden",
    "sg:classifiers":[
        {
            "category":"Shopping",
            "subcategory":"Bicycles & Sporting Goods",
            "type":"Retail Goods"
        }
    ],
    "sg:phone":"+32 15 51 30 80",
    "sg:postcode":"2820",
    "sg:province":"Antwerpen",
    "sg:tags":[
        "-"
    ],
    "wof:name":"Schelkens F",
    "wof:placetype":"venue"
},
  "geometry": {"coordinates":[4.5664701462,51.018661499],"type":"Point"}
}