{
  "type": "Feature",
  "properties": {
    "addr:full":"Rue Des Morseux 9 Gouvy Luxembourg 6670",
    "addr:housenumber":"9",
    "addr:postcode":"6670",
    "addr:street":"Rue Des Morseux",
    "iso:country":"BE",
    "sg:address":"Rue Des Morseux 9",
    "sg:city":"Gouvy",
    "sg:orig_category":"Mat\u00e9riaux de construction Gr",
    "sg:phone":"+32 80 51 70 73",
    "sg:postcode":"6670",
    "sg:province":"Luxembourg",
    "wof:name":"Hengrotherm",
    "wof:placetype":"venue"
},
  "geometry": {"coordinates":[5.9507598877,50.1924514771],"type":"Point"}
}