{
  "type": "Feature",
  "properties": {
    "iso:country":"BE",
    "sg:address":"Stationstraat 1",
    "sg:city":"Puurs",
    "sg:classifiers":[
        {
            "category":"Shopping",
            "subcategory":"Clothing, Apparel, & Fashions",
            "type":"Retail Goods"
        }
    ],
    "sg:postcode":"2870",
    "sg:province":"Antwerpen",
    "sg:tags":[
        "purchase",
        "clothing",
        "-",
        "sale",
        "second-hand"
    ],
    "wof:name":"De Schakel Vzw",
    "wof:placetype":"venue"
},
  "geometry": {"coordinates":[4.279364109,51.0762367249],"type":"Point"}
}