{
  "type": "Feature",
  "properties": {
    "addr:full":"Van Schoonbekestraat 111 Antwerpen Antwerpen 2018",
    "addr:housenumber":"111",
    "addr:postcode":"2018",
    "addr:street":"Van Schoonbekestraat",
    "iso:country":"BE",
    "sg:address":"Van Schoonbekestraat 111",
    "sg:city":"Antwerpen",
    "sg:orig_category":"Sportclubs",
    "sg:phone":"+32 3 237 32 13",
    "sg:postcode":"2018",
    "sg:province":"Antwerpen",
    "wof:name":"Simone Moorthamer",
    "wof:placetype":"venue"
},
  "geometry": {"coordinates":[4.4055018425,51.2007255554],"type":"Point"}
}