{
  "type": "Feature",
  "properties": {
    "addr:full":"Chauss\u00e9e Brunehaut 379 Juprelle Li\u00e8ge 4450",
    "addr:housenumber":"379",
    "addr:postcode":"4450",
    "addr:street":"Chausse\u0301E Brunehaut",
    "iso:country":"BE",
    "sg:address":"Chauss\u00e9e Brunehaut 379",
    "sg:city":"Juprelle",
    "sg:classifiers":[
        {
            "category":"Professional",
            "subcategory":"Computer Services",
            "type":"Services"
        }
    ],
    "sg:phone":"+32 4 278 69 93",
    "sg:postcode":"4450",
    "sg:province":"Li\u00e8ge",
    "sg:tags":[
        "-",
        "processing",
        "data",
        "software"
    ],
    "wof:name":"Cga Conseil G\u00e9n\u00e9ral Assistance",
    "wof:placetype":"venue"
},
  "geometry": {"coordinates":[5.5376701355,50.7117881775],"type":"Point"}
}