{
  "type": "Feature",
  "properties": {
    "iso:country":"BE",
    "sg:address":"Rue L\u00c9opold 54",
    "sg:city":"Li\u00c8ge",
    "sg:orig_category":"Production de films, t\u00e9l\u00e9films and vid\u00e9os",
    "sg:phone":"+32 4 223 25 20",
    "sg:postcode":"4000",
    "sg:province":"Li\u00e8ge",
    "wof:name":"Caracas",
    "wof:placetype":"venue"
},
  "geometry": {"coordinates":[5.5776000023,50.6437759399],"type":"Point"}
}