{
  "type": "Feature",
  "properties": {
    "iso:country":"BE",
    "sg:address":"Edmond Depraterestraat 6",
    "sg:city":"Kortrijk",
    "sg:orig_category":"Avocats and conseillers juridiques",
    "sg:phone":"+32 56 22 04 56",
    "sg:postcode":"8500",
    "sg:province":"West-Vlaanderen",
    "wof:name":"Fabienne Mathys",
    "wof:placetype":"venue"
},
  "geometry": {"coordinates":[3.2578370571,50.8278694153],"type":"Point"}
}