{
  "type": "Feature",
  "properties": {
    "iso:country":"BE",
    "sg:address":"Franslaan 29",
    "sg:city":"Nieuwpoort",
    "sg:classifiers":[
        {
            "category":"Health Services",
            "subcategory":"Hospital",
            "type":"Services"
        }
    ],
    "sg:phone":"+32 58 23 36 33",
    "sg:postcode":"8620",
    "sg:province":"West-Vlaanderen",
    "sg:tags":[
        "ambulance"
    ],
    "wof:name":"Ambulance Nieuwpoort",
    "wof:placetype":"venue"
},
  "geometry": {"coordinates":[2.7191069126,51.1490783691],"type":"Point"}
}