{
  "type": "Feature",
  "properties": {
    "addr:full":"Donk 4 Oud-turnhout Antwerpen 2360",
    "addr:housenumber":"4",
    "addr:postcode":"2360",
    "addr:street":"Donk",
    "iso:country":"BE",
    "sg:address":"Donk 4",
    "sg:city":"Oud-turnhout",
    "sg:classifiers":[
        {
            "category":"Home & Garden",
            "subcategory":"Building Materials",
            "type":"Retail Goods"
        }
    ],
    "sg:phone":"+32 14 45 06 21",
    "sg:postcode":"2360",
    "sg:province":"Antwerpen",
    "sg:tags":[
        "house"
    ],
    "wof:name":"Kempische Draadcentrale Bvba",
    "wof:placetype":"venue"
},
  "geometry": {"coordinates":[5.0207891464,51.3018455505],"type":"Point"}
}