{
  "type": "Feature",
  "properties": {
    "iso:country":"BE",
    "sg:address":"Lembeke Dorp 25",
    "sg:city":"Kaprijke (lembeke)",
    "sg:orig_category":"Newspapers, magazines, periodicals - Distribution",
    "sg:phone":"+32 9 377 60 91",
    "sg:postcode":"9971",
    "sg:province":"Oost-Vlaanderen",
    "wof:name":"Van De Keere",
    "wof:placetype":"venue"
},
  "geometry": {"coordinates":[3.6316959858,51.1951179504],"type":"Point"}
}