{
  "type": "Feature",
  "properties": {
    "addr:full":"Hyacinthenstraat 50 Aalst Oost-Vlaanderen 9300",
    "addr:housenumber":"50",
    "addr:postcode":"9300",
    "addr:street":"Hyacinthenstraat",
    "iso:country":"BE",
    "sg:address":"Hyacinthenstraat 50",
    "sg:city":"Aalst",
    "sg:classifiers":[
        {
            "category":"Building & Trades",
            "subcategory":"Pest Control",
            "type":"Services"
        }
    ],
    "sg:phone":"+32 53 70 47 04",
    "sg:postcode":"9300",
    "sg:province":"Oost-Vlaanderen",
    "sg:tags":[
        "painting",
        "contractor"
    ],
    "wof:name":"Wobben Bvba",
    "wof:placetype":"venue"
},
  "geometry": {"coordinates":[4.0806798935,50.9330787659],"type":"Point"}
}