{
  "type": "Feature",
  "properties": {
    "iso:country":"BE",
    "sg:address":"Lipsestraat 144",
    "sg:city":"Haacht (tildonk)",
    "sg:classifiers":[
        {
            "category":"Professional",
            "subcategory":"Accounting & Tax Preparation",
            "type":"Services"
        }
    ],
    "sg:phone":"+32 16 35 05 80",
    "sg:postcode":"3150",
    "sg:province":"Vlaams-Brabant",
    "sg:tags":[
        "bookkeeper"
    ],
    "wof:name":"Wauters E",
    "wof:placetype":"venue"
},
  "geometry": {"coordinates":[4.6578598022,50.9337425232],"type":"Point"}
}