{
  "type": "Feature",
  "properties": {
    "iso:country":"BE",
    "sg:address":"Vanderkinderestraat 506",
    "sg:city":"Ukkel/uccle",
    "sg:orig_category":"Artsen and specialisten",
    "sg:phone":"+32 2 344 66 83",
    "sg:postcode":"1180",
    "sg:province":"Bruxelles-Capitale",
    "wof:name":"Chantal Gonze",
    "wof:placetype":"venue"
},
  "geometry": {"coordinates":[4.3637452126,50.8146018982],"type":"Point"}
}