{
  "type": "Feature",
  "properties": {
    "addr:full":"Place Albert Ier 17b1 Charleroi Hainaut 6041",
    "addr:housenumber":"17b1",
    "addr:postcode":"6041",
    "addr:street":"Place Albert Ier;Hainaut",
    "iso:country":"BE",
    "sg:address":"Place Albert Ier 17b1",
    "sg:city":"Charleroi",
    "sg:orig_category":"Centres de relaxation and bien-\u00eatre",
    "sg:phone":"+32 71 37 07 77",
    "sg:postcode":"6041",
    "sg:province":"Hainaut",
    "wof:name":"Solarium L'et\u00c9 Indien",
    "wof:placetype":"venue"
},
  "geometry": {"coordinates":[4.4427828789,50.4078826904],"type":"Point"}
}