{
  "type": "Feature",
  "properties": {
    "iso:country":"BE",
    "sg:address":"Rue Du Pont 38b",
    "sg:city":"Ellezelles",
    "sg:classifiers":[
        {
            "category":"Retail",
            "subcategory":"Car Wash",
            "type":"Services"
        }
    ],
    "sg:phone":"+32 68 57 03 47",
    "sg:postcode":"7890",
    "sg:province":"Hainaut",
    "sg:tags":[
        "automobile",
        "washing",
        "-",
        "truck"
    ],
    "wof:name":"X-wash Sprl",
    "wof:placetype":"venue"
},
  "geometry": {"coordinates":[3.6824500561,50.7322807312],"type":"Point"}
}