{
  "type": "Feature",
  "properties": {
    "iso:country":"BE",
    "sg:address":"Steenbeukstraat 20b",
    "sg:city":"Genk (waterschei)",
    "sg:classifiers":[
        {
            "category":"Arena",
            "subcategory":"Sports Club",
            "type":"Entertainment"
        }
    ],
    "sg:phone":"+32 89 38 53 09",
    "sg:postcode":"3600",
    "sg:province":"Limburg",
    "wof:name":"U.d. Barcelona",
    "wof:placetype":"venue"
},
  "geometry": {"coordinates":[5.5173020363,51.0046005249],"type":"Point"}
}