{
  "type": "Feature",
  "properties": {
    "addr:full":"La Ch\u00eanaie 17 Grez-doiceau Brabant Wallon 1390",
    "addr:housenumber":"17",
    "addr:postcode":"1390",
    "addr:street":"La Che\u0302Naie",
    "iso:country":"BE",
    "sg:address":"La Ch\u00eanaie 17",
    "sg:city":"Grez-doiceau",
    "sg:classifiers":[
        {
            "category":"Real Estate",
            "subcategory":"Surveying",
            "type":"Services"
        }
    ],
    "sg:phone":"+32 10 84 26 18",
    "sg:postcode":"1390",
    "sg:province":"Brabant Wallon",
    "sg:tags":[
        "surveyor",
        "land"
    ],
    "wof:name":"Bertrand J-m",
    "wof:placetype":"venue"
},
  "geometry": {"coordinates":[4.6737098694,50.7209091187],"type":"Point"}
}