{
  "type": "Feature",
  "properties": {
    "iso:country":"BE",
    "sg:address":"Peperstraat 10",
    "sg:city":"Herzele",
    "sg:orig_category":"Installatie van houten of kunststof schrijnwerk",
    "sg:phone":"+32 53 62 50 56",
    "sg:postcode":"9550",
    "sg:province":"Oost-Vlaanderen",
    "wof:name":"De Cooman",
    "wof:placetype":"venue"
},
  "geometry": {"coordinates":[3.8937809467,50.8843421936],"type":"Point"}
}