{
  "type": "Feature",
  "properties": {
    "addr:full":"Rue Saint-vincent 21 Walhain Brabant Wallon 1457",
    "addr:housenumber":"21;1457",
    "addr:street":"Rue Saint-Vincent",
    "iso:country":"BE",
    "sg:address":"Rue Saint-vincent 21",
    "sg:city":"Walhain",
    "sg:orig_category":"Elektrische installaties voor woningen",
    "sg:phone":"+32 10 65 01 27",
    "sg:postcode":"1457",
    "sg:province":"Brabant Wallon",
    "wof:name":"Electricit\u00c9 Meyers A.",
    "wof:placetype":"venue"
},
  "geometry": {"coordinates":[4.6716189384,50.6395645142],"type":"Point"}
}