{
  "type": "Feature",
  "properties": {
    "iso:country":"BE",
    "sg:address":"Rue Du Moulin 3",
    "sg:city":"Erez\u00e9e (soy)",
    "sg:classifiers":[
        {
            "category":"Health Services",
            "subcategory":"Doctor",
            "type":"Services"
        }
    ],
    "sg:phone":"+32 84 46 68 21",
    "sg:postcode":"6997",
    "sg:province":"Luxembourg",
    "sg:tags":[
        "medicinephysicians",
        "surgeon"
    ],
    "wof:name":"Haquinet Claudy",
    "wof:placetype":"venue"
},
  "geometry": {"coordinates":[5.4976038933,50.2759971619],"type":"Point"}
}