{
  "type": "Feature",
  "properties": {
    "iso:country":"BE",
    "sg:address":"Rue Saint-denis 16ba",
    "sg:city":"Vorst/forest",
    "sg:classifiers":[
        {
            "category":"Arena",
            "subcategory":"Sports Club",
            "type":"Entertainment"
        }
    ],
    "sg:phone":"+32 2 343 18 93",
    "sg:postcode":"1190",
    "sg:province":"Bruxelles-Capitale",
    "sg:tags":[
        "de"
    ],
    "wof:name":"P.c. Espoir Forestois",
    "wof:placetype":"venue"
},
  "geometry": {"coordinates":[4.31873703,50.8127746582],"type":"Point"}
}