{
  "type": "Feature",
  "properties": {
    "addr:full":"Veldstraat 2 A Brasschaat Antwerpen 2930",
    "addr:housenumber":"2 a",
    "addr:postcode":"2930",
    "addr:street":"Veldstraat",
    "iso:country":"BE",
    "sg:address":"Veldstraat 2 A",
    "sg:city":"Brasschaat",
    "sg:orig_category":"Quincailleries. Electrom\u00e9nager, t\u00e9l\u00e9visions and radios",
    "sg:phone":"+32 3 651 83 40",
    "sg:postcode":"2930",
    "sg:province":"Antwerpen",
    "wof:name":"Eyckerman Gereedschappen Ijzerwaren",
    "wof:placetype":"venue"
},
  "geometry": {"coordinates":[4.4885721207,51.2891311646],"type":"Point"}
}