{
  "type": "Feature",
  "properties": {
    "iso:country":"BE",
    "sg:address":"Rue Neuve 12",
    "sg:city":"Grace-hollogne",
    "sg:orig_category":"M\u00e9decins and sp\u00e9cialistes",
    "sg:phone":"+32 4 233 38 42",
    "sg:postcode":"4460",
    "sg:province":"Li\u00e8ge",
    "wof:name":"B. Daffe",
    "wof:placetype":"venue"
},
  "geometry": {"coordinates":[5.4750552177,50.6301231384],"type":"Point"}
}