{
  "type": "Feature",
  "properties": {
    "iso:country":"BE",
    "sg:address":"Brusselsesteenweg 324",
    "sg:city":"Gent",
    "sg:orig_category":"Divers amusement Diverse zakelijke dienstverlening",
    "sg:phone":"+32 9 232 19 26",
    "sg:postcode":"9050",
    "sg:province":"Oost-Vlaanderen",
    "wof:name":"Yves Rosseel",
    "wof:placetype":"venue"
},
  "geometry": {"coordinates":[3.7423648834,51.0407371521],"type":"Point"}
}