{
  "type": "Feature",
  "properties": {
    "addr:full":"Antoon Catriestraat 91 Gent Oost-Vlaanderen 9031",
    "addr:housenumber":"91",
    "addr:postcode":"9031",
    "addr:street":"Antoon Catriestraat;Oost-Vlaanderen",
    "iso:country":"BE",
    "sg:address":"Antoon Catriestraat 91",
    "sg:city":"Gent",
    "sg:orig_category":"Woningbouw",
    "sg:phone":"+32 9 227 58 84",
    "sg:postcode":"9031",
    "sg:province":"Oost-Vlaanderen",
    "wof:name":"Philippe Schietecatte",
    "wof:placetype":"venue"
},
  "geometry": {"coordinates":[3.6446120739,51.056186676],"type":"Point"}
}