{
  "type": "Feature",
  "properties": {
    "addr:full":"Maastrichtersteenweg 182 Riemst Limburg 3770",
    "addr:housenumber":"182",
    "addr:postcode":"3770",
    "addr:street":"Maastrichtersteenweg",
    "iso:country":"BE",
    "sg:address":"Maastrichtersteenweg 182",
    "sg:city":"Riemst",
    "sg:classifiers":[
        {
            "category":"Health Services",
            "subcategory":"Health Practitioner",
            "type":"Services"
        }
    ],
    "sg:phone":"+32 12 45 17 08",
    "sg:postcode":"3770",
    "sg:province":"Limburg",
    "sg:tags":[
        "physiotherapist"
    ],
    "wof:name":"Thysen K",
    "wof:placetype":"venue"
},
  "geometry": {"coordinates":[5.612569809,50.8188209534],"type":"Point"}
}