{
  "type": "Feature",
  "properties": {
    "iso:country":"BE",
    "sg:address":"Van Evenstraat 2b",
    "sg:city":"Leuven",
    "sg:orig_category":"Activit\u00e9s d\u00b4action sociale sans h\u00e9bergement",
    "sg:phone":"+32 16 23 65 07",
    "sg:postcode":"3000",
    "sg:province":"Vlaams-Brabant",
    "wof:name":"Trefpunt Zelfhulp",
    "wof:placetype":"venue"
},
  "geometry": {"coordinates":[4.7033238411,50.8739852905],"type":"Point"}
}