{
  "type": "Feature",
  "properties": {
    "iso:country":"BE",
    "sg:address":"Korenstraat 14",
    "sg:city":"Sint-katelijne-waver",
    "sg:orig_category":"Sportclubs",
    "sg:phone":"+32 15 75 21 15",
    "sg:postcode":"2861",
    "sg:province":"Antwerpen",
    "wof:name":"Voba",
    "wof:placetype":"venue"
},
  "geometry": {"coordinates":[4.5814929008,51.0589294434],"type":"Point"}
}