{
  "type": "Feature",
  "properties": {
    "iso:country":"BE",
    "sg:address":"Rue De La Vall\u00e9e 16",
    "sg:city":"Ham-sur-heure-nalinnes (nalinnes)",
    "sg:classifiers":[
        {
            "category":"Real Estate",
            "subcategory":"Real Estate Services",
            "type":"Services"
        }
    ],
    "sg:phone":"+32 71 21 46 72",
    "sg:postcode":"6120",
    "sg:province":"Hainaut",
    "wof:name":"Courtage Immobilier (le)",
    "wof:placetype":"venue"
},
  "geometry": {"coordinates":[4.4686088562,50.3434143066],"type":"Point"}
}