{
  "type": "Feature",
  "properties": {
    "iso:country":"BE",
    "sg:address":"Kerkstraat 72",
    "sg:city":"Ninove",
    "sg:orig_category":"Epiceries",
    "sg:phone":"+32 54 33 44 48",
    "sg:postcode":"9406",
    "sg:province":"Oost-Vlaanderen",
    "wof:name":"A Scheerlinck",
    "wof:placetype":"venue"
},
  "geometry": {"coordinates":[3.996860981,50.8439674377],"type":"Point"}
}