{
  "type": "Feature",
  "properties": {
    "iso:country":"BE",
    "sg:address":"Pastoriestraat 6",
    "sg:city":"Kortrijk",
    "sg:orig_category":"V\u00eatements pour b\u00e9b\u00e9s and enfants",
    "sg:phone":"+32 56 35 50 89",
    "sg:postcode":"8501",
    "sg:province":"West-Vlaanderen",
    "wof:name":"Tatie For Kids",
    "wof:placetype":"venue"
},
  "geometry": {"coordinates":[3.2336709499,50.8435592651],"type":"Point"}
}