{
  "type": "Feature",
  "properties": {
    "iso:country":"BE",
    "sg:address":"Rue Roc Saint-nicaise 18",
    "sg:city":"Tournai",
    "sg:orig_category":"Kantoormateriaal Meubelzaken, woning- and keukeninrichting",
    "sg:phone":"+32 69 21 59 70",
    "sg:postcode":"7500",
    "sg:province":"Hainaut",
    "wof:name":"Best Technology Of Design",
    "wof:placetype":"venue"
},
  "geometry": {"coordinates":[3.3863921165,50.6043128967],"type":"Point"}
}