{
  "type": "Feature",
  "properties": {
    "iso:country":"BE",
    "sg:address":"Wolfstraat 88",
    "sg:city":"Liezele",
    "sg:classifiers":[
        {
            "category":"Transit Center",
            "subcategory":"Freight",
            "type":"Transportation"
        }
    ],
    "sg:phone":"+32 3 889 01 02",
    "sg:postcode":"2870",
    "sg:province":"Antwerpen",
    "sg:tags":[
        "hazardous",
        "material"
    ],
    "wof:name":"Liezele Transport Nv",
    "wof:placetype":"venue"
},
  "geometry": {"coordinates":[4.2973217964,51.0522460938],"type":"Point"}
}