{
  "type": "Feature",
  "properties": {
    "iso:country":"BE",
    "sg:address":"Grote Puttingbaan 22",
    "sg:city":"Nijlen",
    "sg:orig_category":"Kapsalons Loodgieterij, verwarming and sanitaire installaties",
    "sg:phone":"+32 3 480 63 77",
    "sg:postcode":"2560",
    "sg:province":"Antwerpen",
    "wof:name":"Kabola Heating Systems",
    "wof:placetype":"venue"
},
  "geometry": {"coordinates":[4.6293911934,51.147354126],"type":"Point"}
}