{
  "type": "Feature",
  "properties": {
    "iso:country":"BE",
    "sg:address":"Hoekstraat 50",
    "sg:city":"Neerpelt",
    "sg:orig_category":"Diverse opleidingen and onderwijs Volwassenenonderwijs Werk and personeelsselectie",
    "sg:phone":"+32 11 64 26 63",
    "sg:postcode":"3910",
    "sg:province":"Limburg",
    "wof:name":"C.m.o.-opleidingscentrum",
    "wof:placetype":"venue"
},
  "geometry": {"coordinates":[5.4263510704,51.228061676],"type":"Point"}
}