{
  "type": "Feature",
  "properties": {
    "addr:full":"En Neuvice 6 Li\u00e8ge 1 Li\u00e8ge 4000",
    "addr:housenumber":"6;1",
    "addr:postcode":"4000",
    "addr:street":"En Neuvice",
    "iso:country":"BE",
    "sg:address":"En Neuvice 6",
    "sg:city":"Li\u00e8ge 1",
    "sg:classifiers":[
        {
            "category":"Building & Trades",
            "subcategory":"Equipment Rental",
            "type":"Services"
        }
    ],
    "sg:phone":"+32 4 222 25 79",
    "sg:postcode":"4000",
    "sg:province":"Li\u00e8ge",
    "sg:tags":[
        "safety",
        "collective",
        "individual",
        "-"
    ],
    "wof:name":"Colporteuse (a La)",
    "wof:placetype":"venue"
},
  "geometry": {"coordinates":[5.5762658119,50.645488739],"type":"Point"}
}