{
  "type": "Feature",
  "properties": {
    "iso:country":"BE",
    "sg:address":"1 Rue Albert",
    "sg:city":"Binche",
    "sg:classifiers":[
        {
            "category":"Communications",
            "subcategory":"Newspaper",
            "type":"Services"
        }
    ],
    "sg:phone":"+32 64 31 11 00",
    "sg:postcode":"7134",
    "sg:province":"Hainaut",
    "sg:tags":[
        "material",
        "-",
        "packaging",
        "raw",
        "paper",
        "cardboard"
    ],
    "wof:name":"Emballage Industrielle Sa",
    "wof:placetype":"venue"
},
  "geometry": {"coordinates":[4.2113847733,50.4300308228],"type":"Point"}
}