{
  "type": "Feature",
  "properties": {
    "iso:country":"BE",
    "sg:address":"Wittestraat 20",
    "sg:city":"Tielt",
    "sg:orig_category":"Animaux domestiques and accessoires",
    "sg:phone":"+32 51 40 44 03",
    "sg:postcode":"8700",
    "sg:province":"West-Vlaanderen",
    "wof:name":"Oisellerie",
    "wof:placetype":"venue"
},
  "geometry": {"coordinates":[3.3239340782,50.9919929504],"type":"Point"}
}