{
  "type": "Feature",
  "properties": {
    "iso:country":"BE",
    "sg:address":"Adegem Dorp 40-42",
    "sg:city":"Maldegem (adegem)",
    "sg:orig_category":"Non-Classified Establishments",
    "sg:phone":"+32 50 71 26 91",
    "sg:postcode":"9991",
    "sg:province":"Oost-Vlaanderen",
    "wof:name":"Tricojoca De Kesel Bvba",
    "wof:placetype":"venue"
},
  "geometry": {"coordinates":[3.486880064,51.2046394348],"type":"Point"}
}