{
  "type": "Feature",
  "properties": {
    "iso:country":"BE",
    "sg:address":"Place Josse Goffin 18",
    "sg:city":"Tubize (clabecq)",
    "sg:classifiers":[
        {
            "category":"Insurance",
            "subcategory":"Insurance Agent",
            "type":"Services"
        }
    ],
    "sg:phone":"+32 2 390 90 46",
    "sg:postcode":"1480",
    "sg:province":"Brabant Wallon",
    "sg:tags":[
        "broker"
    ],
    "wof:name":"'t Kindt Assurances",
    "wof:placetype":"venue"
},
  "geometry": {"coordinates":[4.2217578888,50.6895141602],"type":"Point"}
}