{
  "type": "Feature",
  "properties": {
    "addr:full":"Rue Place 37 Merbes-le-ch\u00c2teau Hainaut 6567",
    "addr:housenumber":"37",
    "addr:postcode":"6567",
    "addr:street":"Rue Place",
    "iso:country":"BE",
    "sg:address":"Rue Place 37",
    "sg:city":"Merbes-le-ch\u00c2teau",
    "sg:orig_category":"Notarissen",
    "sg:phone":"+32 71 55 53 92",
    "sg:postcode":"6567",
    "sg:province":"Hainaut",
    "wof:name":"Mourue F.",
    "wof:placetype":"venue"
},
  "geometry": {"coordinates":[4.1655550003,50.323474884],"type":"Point"}
}