{
  "type": "Feature",
  "properties": {
    "iso:country":"BE",
    "sg:address":"Sint-pietersplein 7",
    "sg:city":"Oostkamp",
    "sg:classifiers":[
        {
            "category":"Professional",
            "subcategory":"Lawyer & Legal Services",
            "type":"Services"
        }
    ],
    "sg:phone":"+32 50 83 20 34",
    "sg:postcode":"8020",
    "sg:province":"West-Vlaanderen",
    "wof:name":"Claeys Hilde",
    "wof:placetype":"venue"
},
  "geometry": {"coordinates":[3.2386939526,51.1550369263],"type":"Point"}
}