{
  "type": "Feature",
  "properties": {
    "iso:country":"BE",
    "sg:address":"Zamenhoflaan 28 Box 2",
    "sg:city":"Schoten",
    "sg:classifiers":[
        {
            "category":"Health Services",
            "subcategory":"Doctor",
            "type":"Services"
        }
    ],
    "sg:phone":"+32 3 658 22 88",
    "sg:postcode":"2900",
    "sg:province":"Antwerpen",
    "sg:tags":[
        "medicinephysicians",
        "surgeon"
    ],
    "wof:name":"Aerts Nora",
    "wof:placetype":"venue"
},
  "geometry": {"coordinates":[4.5001468658,51.2531013489],"type":"Point"}
}