{
  "type": "Feature",
  "properties": {
    "iso:country":"BE",
    "sg:address":"Avenue Jules Bordet 131c",
    "sg:city":"Renaix",
    "sg:classifiers":[
        {
            "category":"Parking",
            "subcategory":"Lot",
            "type":"Transportation"
        }
    ],
    "sg:phone":"+32 55 20 64 90",
    "sg:postcode":"9600",
    "sg:province":"Oost-Vlaanderen",
    "sg:tags":[
        "parking-places",
        "laying-out"
    ],
    "wof:name":"De Bock J-l-imotep",
    "wof:placetype":"venue"
},
  "geometry": {"coordinates":[3.5997951031,50.7394104004],"type":"Point"}
}