{
  "type": "Feature",
  "properties": {
    "addr:full":"Oudenaardsesteenweg 168 Kortrijk West-Vlaanderen 8500",
    "addr:housenumber":"168",
    "addr:postcode":"8500",
    "addr:street":"Oudenaardsesteenweg",
    "iso:country":"BE",
    "sg:address":"Oudenaardsesteenweg 168",
    "sg:city":"Kortrijk",
    "sg:orig_category":"Technisch and beroeps secundair onderwijs",
    "sg:phone":"+32 56 21 23 01",
    "sg:postcode":"8500",
    "sg:province":"West-Vlaanderen",
    "wof:name":"Vrij Techn. Instituut 2",
    "wof:placetype":"venue"
},
  "geometry": {"coordinates":[3.2860589027,50.8204689026],"type":"Point"}
}