{
  "type": "Feature",
  "properties": {
    "iso:country":"BE",
    "sg:address":"Avenue De Norv\u00c8ge 32",
    "sg:city":"Malmedy",
    "sg:orig_category":"Ramassage and traitement des d\u00e9chets m\u00e9nagers",
    "sg:phone":"+32 80 33 92 33",
    "sg:postcode":"4960",
    "sg:province":"Li\u00e8ge",
    "wof:name":"Solheid Location",
    "wof:placetype":"venue"
},
  "geometry": {"coordinates":[5.9989418983,50.4139099121],"type":"Point"}
}