{
  "type": "Feature",
  "properties": {
    "addr:full":"Koolstraat 2 Box 1 Mechelen Antwerpen 2800",
    "addr:housenumber":"2;1",
    "addr:postcode":"2800",
    "addr:street":"Koolstraat;Box",
    "iso:country":"BE",
    "sg:address":"Koolstraat 2 Box 1",
    "sg:city":"Mechelen",
    "sg:classifiers":[
        {
            "category":"Personal",
            "subcategory":"Nail Salon",
            "type":"Services"
        }
    ],
    "sg:phone":"+32 15 26 09 26",
    "sg:postcode":"2800",
    "sg:province":"Antwerpen",
    "sg:tags":[
        "pedicure"
    ],
    "wof:name":"No\u00ebth S",
    "wof:placetype":"venue"
},
  "geometry": {"coordinates":[4.4643602371,51.0281105042],"type":"Point"}
}