{
  "type": "Feature",
  "properties": {
    "iso:country":"BE",
    "sg:address":"Kerkweg 10",
    "sg:city":"Willebroek (heindonk)",
    "sg:classifiers":[
        {
            "category":"Professional",
            "subcategory":"Management & Consulting",
            "type":"Services"
        }
    ],
    "sg:phone":"+32 3 866 41 55",
    "sg:postcode":"2830",
    "sg:province":"Antwerpen",
    "sg:tags":[
        "-",
        "processing",
        "data",
        "consultant"
    ],
    "wof:name":"Van Dam D",
    "wof:placetype":"venue"
},
  "geometry": {"coordinates":[4.3604459763,51.0646591187],"type":"Point"}
}