{
  "type": "Feature",
  "properties": {
    "iso:country":"BE",
    "sg:address":"Bagnolsstraat 1",
    "sg:city":"Eeklo",
    "sg:classifiers":[
        {
            "category":"Arena",
            "subcategory":"Sports Club",
            "type":"Entertainment"
        }
    ],
    "sg:phone":"+32 9 377 27 47",
    "sg:postcode":"9900",
    "sg:province":"Oost-Vlaanderen",
    "wof:name":"Eeklose Watervereniging",
    "wof:placetype":"venue"
},
  "geometry": {"coordinates":[3.5838170052,51.1767425537],"type":"Point"}
}