{
  "type": "Feature",
  "properties": {
    "addr:full":"Brusselsesteenweg 179 Lebbeke Oost-Vlaanderen 9280",
    "addr:housenumber":"179",
    "addr:postcode":"9280",
    "addr:street":"Brusselsesteenweg",
    "iso:country":"BE",
    "sg:address":"Brusselsesteenweg 179",
    "sg:city":"Lebbeke",
    "sg:classifiers":[
        {
            "category":"Building & Trades",
            "subcategory":"Equipment Rental",
            "type":"Services"
        }
    ],
    "sg:phone":"+32 52 41 32 22",
    "sg:postcode":"9280",
    "sg:province":"Oost-Vlaanderen",
    "sg:tags":[
        "use",
        "apparatus",
        "tool",
        "-",
        "professional",
        "machines"
    ],
    "wof:name":"Lambrechts Verhuur Bvba",
    "wof:placetype":"venue"
},
  "geometry": {"coordinates":[4.1338448524,50.9917030334],"type":"Point"}
}