{
  "type": "Feature",
  "properties": {
    "addr:full":"Rue Des Etangs Noirs 44 Bruxelles (molenbeek-saint-jean) Bruxelles-Capitale 1080",
    "addr:housenumber":"44",
    "addr:postcode":"1080",
    "addr:street":"Rue Des Etangs Noirs",
    "iso:country":"BE",
    "sg:address":"Rue Des Etangs Noirs 44",
    "sg:city":"Bruxelles (molenbeek-saint-jean)",
    "sg:classifiers":[
        {
            "category":"Shopping",
            "subcategory":"Bicycles & Sporting Goods",
            "type":"Retail Goods"
        }
    ],
    "sg:phone":"+32 2 411 63 15",
    "sg:postcode":"1080",
    "sg:province":"Bruxelles-Capitale",
    "sg:tags":[
        "tyre"
    ],
    "wof:name":"Turbo Tyres",
    "wof:placetype":"venue"
},
  "geometry": {"coordinates":[4.3310399055,50.8563308716],"type":"Point"}
}