{
  "type": "Feature",
  "properties": {
    "addr:full":"Kleine Koestraat 24 Evergem Oost-Vlaanderen 9940",
    "addr:housenumber":"24",
    "addr:postcode":"9940",
    "addr:street":"Kleine Koestraat;Oost-Vlaanderen",
    "iso:country":"BE",
    "sg:address":"Kleine Koestraat 24",
    "sg:city":"Evergem",
    "sg:classifiers":[
        {
            "category":"Health Services",
            "subcategory":"Doctor",
            "type":"Services"
        }
    ],
    "sg:phone":"+32 9 253 29 69",
    "sg:postcode":"9940",
    "sg:province":"Oost-Vlaanderen",
    "sg:tags":[
        "medicinephysicians",
        "surgeon"
    ],
    "wof:name":"De Mol Annick",
    "wof:placetype":"venue"
},
  "geometry": {"coordinates":[3.715487957,51.1173286438],"type":"Point"}
}