{
  "type": "Feature",
  "properties": {
    "iso:country":"BE",
    "sg:address":"Hemelsbreedte 6",
    "sg:city":"Sint-niklaas",
    "sg:orig_category":"Herstellingen and onderhoud van auto's",
    "sg:phone":"+32 3 772 56 86",
    "sg:postcode":"9112",
    "sg:province":"Oost-Vlaanderen",
    "wof:name":"Rudiger Zaman",
    "wof:placetype":"venue"
},
  "geometry": {"coordinates":[4.0607700348,51.1450195312],"type":"Point"}
}