{
  "type": "Feature",
  "properties": {
    "addr:full":"Rue L'agent 9 Durbuy Luxembourg 6941",
    "addr:housenumber":"9",
    "addr:postcode":"6941",
    "addr:street":"Rue L'Agent",
    "iso:country":"BE",
    "sg:address":"Rue L'agent 9",
    "sg:city":"Durbuy",
    "sg:classifiers":[
        {
            "category":"Arena",
            "subcategory":"Sports Club",
            "type":"Entertainment"
        }
    ],
    "sg:phone":"+32 86 40 11 68",
    "sg:postcode":"6941",
    "sg:province":"Luxembourg",
    "sg:tags":[
        "terrain",
        "hors",
        "de",
        "installation",
        "sportifs"
    ],
    "wof:name":"E.s. Izier",
    "wof:placetype":"venue"
},
  "geometry": {"coordinates":[5.5788741112,50.3854293823],"type":"Point"}
}