{
  "type": "Feature",
  "properties": {
    "addr:full":"Oudburg 20 Gent Oost-Vlaanderen 9000",
    "addr:housenumber":"20",
    "addr:postcode":"9000",
    "addr:street":"Oudburg;Oost-Vlaanderen",
    "iso:country":"BE",
    "sg:address":"Oudburg 20",
    "sg:city":"Gent",
    "sg:classifiers":[
        {
            "category":"Bars & Pubs",
            "type":"Food & Drink"
        }
    ],
    "sg:phone":"+32 9 234 07 29",
    "sg:postcode":"9000",
    "sg:province":"Oost-Vlaanderen",
    "wof:name":"Aba-jour (brasserie)",
    "wof:placetype":"venue"
},
  "geometry": {"coordinates":[3.7242100239,51.0580444336],"type":"Point"}
}