{
  "type": "Feature",
  "properties": {
    "addr:full":"Nationalestraat 122 Antwerpen Antwerpen 2000",
    "addr:housenumber":"122",
    "addr:postcode":"2000",
    "addr:street":"Nationalestraat",
    "iso:country":"BE",
    "sg:address":"Nationalestraat 122",
    "sg:city":"Antwerpen",
    "sg:orig_category":"Diverse kredietdiensten",
    "sg:postcode":"2000",
    "sg:province":"Antwerpen",
    "wof:name":"Bancontact-mister Cash",
    "wof:placetype":"venue"
},
  "geometry": {"coordinates":[4.3977150917,51.2136268616],"type":"Point"}
}