{
  "type": "Feature",
  "properties": {
    "addr:full":"Rue De La Poste 17 Spa Li\u00e8ge 4900",
    "addr:housenumber":"17",
    "addr:postcode":"4900",
    "addr:street":"Rue De La Poste",
    "iso:country":"BE",
    "sg:address":"Rue De La Poste 17",
    "sg:city":"Spa",
    "sg:classifiers":[
        {
            "category":"Cafe",
            "type":"Food & Drink"
        }
    ],
    "sg:phone":"+32 87 77 47 55",
    "sg:postcode":"4900",
    "sg:province":"Li\u00e8ge",
    "sg:tags":[
        "caf\u00e9s"
    ],
    "wof:name":"Manuela Dahmoun",
    "wof:placetype":"venue"
},
  "geometry": {"coordinates":[5.8636960983,50.4917221069],"type":"Point"}
}