{
  "type": "Feature",
  "properties": {
    "iso:country":"BE",
    "sg:address":"Pensionaatstraat 12",
    "sg:city":"Ruiselede",
    "sg:classifiers":[
        {
            "category":"Retail",
            "subcategory":"Auto Repair",
            "type":"Services"
        }
    ],
    "sg:phone":"+32 51 68 65 28",
    "sg:postcode":"8755",
    "sg:province":"West-Vlaanderen",
    "sg:tags":[
        "garage"
    ],
    "wof:name":"Desmet G",
    "wof:placetype":"venue"
},
  "geometry": {"coordinates":[3.3930740356,51.0422477722],"type":"Point"}
}