{
  "type": "Feature",
  "properties": {
    "addr:full":"Rommelaerelaan 17 Brussel/bruxelles Bruxelles-Capitale 1020",
    "addr:housenumber":"17",
    "addr:postcode":"1020",
    "addr:street":"Rommelaerelaan;/",
    "iso:country":"BE",
    "sg:address":"Rommelaerelaan 17",
    "sg:city":"Brussel/bruxelles",
    "sg:orig_category":"Organisatie van beurzen, congressen and tentoonstellingen",
    "sg:phone":"+32 2 474 85 55",
    "sg:postcode":"1020",
    "sg:province":"Bruxelles-Capitale",
    "wof:name":"Fair Line",
    "wof:placetype":"venue"
},
  "geometry": {"coordinates":[4.3349061012,50.889213562],"type":"Point"}
}