{
  "type": "Feature",
  "properties": {
    "iso:country":"BE",
    "sg:address":"Kromstraat 66",
    "sg:city":"Retie",
    "sg:classifiers":[
        {
            "category":"Real Estate",
            "subcategory":"Architect",
            "type":"Services"
        }
    ],
    "sg:phone":"+32 14 37 22 40",
    "sg:postcode":"2470",
    "sg:province":"Antwerpen",
    "wof:name":"Donneux K",
    "wof:placetype":"venue"
},
  "geometry": {"coordinates":[5.0960450172,51.273651123],"type":"Point"}
}