{
  "type": "Feature",
  "properties": {
    "iso:country":"BE",
    "sg:address":"Vaartstraat 7",
    "sg:city":"Lo-reninge (pollinkhove)",
    "sg:orig_category":"Non-Classified Establishments",
    "sg:phone":"+32 58 28 80 30",
    "sg:postcode":"8647",
    "sg:province":"West-Vlaanderen",
    "wof:name":"Voeders Nollet Nv",
    "wof:placetype":"venue"
},
  "geometry": {"coordinates":[2.7332110405,50.9713592529],"type":"Point"}
}