{
  "type": "Feature",
  "properties": {
    "iso:country":"BE",
    "sg:address":"Alsembergse Steenweg 1185",
    "sg:city":"Ukkel/uccle",
    "sg:orig_category":"CD's, cassettes and platen Herstellingswinkels voor diverse persoonlijke and huishoudartikelen",
    "sg:phone":"+32 2 376 04 28",
    "sg:postcode":"1180",
    "sg:province":"Bruxelles-Capitale",
    "wof:name":"Maison Pierard",
    "wof:placetype":"venue"
},
  "geometry": {"coordinates":[4.3291578293,50.7865371704],"type":"Point"}
}