{
  "type": "Feature",
  "properties": {
    "addr:full":"Gebanne Groezenstraat 75 Hasselt Limburg 3500",
    "addr:housenumber":"75",
    "addr:postcode":"3500",
    "addr:street":"Groezenstraat",
    "iso:country":"BE",
    "sg:address":"Gebanne Groezenstraat 75",
    "sg:city":"Hasselt",
    "sg:orig_category":"Tuinen",
    "sg:phone":"+32 11 23 49 90",
    "sg:postcode":"3500",
    "sg:province":"Limburg",
    "wof:name":"Theunis J.",
    "wof:placetype":"venue"
},
  "geometry": {"coordinates":[5.3724031448,50.9464149475],"type":"Point"}
}