{
  "type": "Feature",
  "properties": {
    "addr:full":"Rue Basse Campagne 35 Herstal Li\u00e8ge 4040",
    "addr:housenumber":"35",
    "addr:postcode":"4040",
    "addr:street":"Rue Basse Campagne",
    "iso:country":"BE",
    "sg:address":"Rue Basse Campagne 35",
    "sg:city":"Herstal",
    "sg:orig_category":"V\u00e9hicules automobiles",
    "sg:phone":"+32 4 264 31 42",
    "sg:postcode":"4040",
    "sg:province":"Li\u00e8ge",
    "wof:name":"Roberto Motor",
    "wof:placetype":"venue"
},
  "geometry": {"coordinates":[5.6450009346,50.6869773865],"type":"Point"}
}