{
  "type": "Feature",
  "properties": {
    "addr:full":"Hasenvenn 1 B\u00fcllingen (manderfeld) Li\u00e8ge 4760",
    "addr:housenumber":"1",
    "addr:postcode":"4760",
    "addr:street":"Hasenvenn;Manderfeld",
    "iso:country":"BE",
    "sg:address":"Hasenvenn 1",
    "sg:city":"B\u00fcllingen (manderfeld)",
    "sg:classifiers":[
        {
            "category":"Personal",
            "subcategory":"Beauty Salon",
            "type":"Services"
        }
    ],
    "sg:phone":"+32 80 54 82 04",
    "sg:postcode":"4760",
    "sg:province":"Li\u00e8ge",
    "wof:name":"Maus S",
    "wof:placetype":"venue"
},
  "geometry": {"coordinates":[6.2557492256,50.4061813354],"type":"Point"}
}