{
  "type": "Feature",
  "properties": {
    "addr:full":"Dr\u00e8ve De Chil\u00e9e 19 Villers-la-ville Brabant Wallon 1495",
    "addr:housenumber":"19",
    "addr:postcode":"1495",
    "addr:street":"Dre\u0300Ve De Chile\u0301E",
    "iso:country":"BE",
    "sg:address":"Dr\u00e8ve De Chil\u00e9e 19",
    "sg:city":"Villers-la-ville",
    "sg:classifiers":[
        {
            "category":"Health Services",
            "subcategory":"Dentist",
            "type":"Services"
        }
    ],
    "sg:phone":"+32 71 87 90 41",
    "sg:postcode":"1495",
    "sg:province":"Brabant Wallon",
    "wof:name":"Pigeolet B",
    "wof:placetype":"venue"
},
  "geometry": {"coordinates":[4.5390658379,50.5774726868],"type":"Point"}
}