{
  "type": "Feature",
  "properties": {
    "iso:country":"BE",
    "sg:address":"Molenberglei 32",
    "sg:city":"Schelle",
    "sg:orig_category":"Diverse machines voor de nijverheid Gh",
    "sg:phone":"+32 3 880 87 40",
    "sg:postcode":"2627",
    "sg:province":"Antwerpen",
    "wof:name":"Witmetaal Belgium",
    "wof:placetype":"venue"
},
  "geometry": {"coordinates":[4.3683099747,51.1193618774],"type":"Point"}
}