{
  "type": "Feature",
  "properties": {
    "addr:full":"Arkstraat 13 Lanaken Limburg 3620",
    "addr:housenumber":"13",
    "addr:postcode":"3620",
    "addr:street":"Arkstraat",
    "iso:country":"BE",
    "sg:address":"Arkstraat 13",
    "sg:city":"Lanaken",
    "sg:classifiers":[
        {
            "category":"Shopping",
            "subcategory":"Pets & Pet Supplies",
            "type":"Retail Goods"
        }
    ],
    "sg:phone":"+32 89 71 33 41",
    "sg:postcode":"3620",
    "sg:province":"Limburg",
    "sg:tags":[
        "shop",
        "-"
    ],
    "wof:name":"Dier- En Tuincenter de Ark",
    "wof:placetype":"venue"
},
  "geometry": {"coordinates":[5.6486039162,50.891040802],"type":"Point"}
}