{
  "type": "Feature",
  "properties": {
    "addr:full":"Route De Coo 52 Trois-ponts Li\u00e8ge 4980",
    "addr:housenumber":"52",
    "addr:postcode":"4980",
    "addr:street":"Route De Coo",
    "iso:country":"BE",
    "sg:address":"Route De Coo 52",
    "sg:city":"Trois-ponts",
    "sg:orig_category":"Installation \u00e9lectrique r\u00e9sidentielle",
    "sg:phone":"+32 80 31 80 29",
    "sg:postcode":"4980",
    "sg:province":"Li\u00e8ge",
    "wof:name":"Fe. 3 E",
    "wof:placetype":"venue"
},
  "geometry": {"coordinates":[5.8726758957,50.3747749329],"type":"Point"}
}