{
  "type": "Feature",
  "properties": {
    "addr:full":"Colmanstraat 65 Laarne (kalken) Oost-Vlaanderen 9270",
    "addr:housenumber":"65",
    "addr:postcode":"9270",
    "addr:street":"Colmanstraat",
    "iso:country":"BE",
    "sg:address":"Colmanstraat 65",
    "sg:city":"Laarne (kalken)",
    "sg:classifiers":[
        {
            "category":"Professional",
            "subcategory":"Accounting & Tax Preparation",
            "type":"Services"
        }
    ],
    "sg:phone":"+32 9 366 24 41",
    "sg:postcode":"9270",
    "sg:province":"Oost-Vlaanderen",
    "sg:tags":[
        "bookkeeper"
    ],
    "wof:name":"De Smet C",
    "wof:placetype":"venue"
},
  "geometry": {"coordinates":[3.8921630383,51.0380897522],"type":"Point"}
}