{
  "type": "Feature",
  "properties": {
    "addr:full":"Dampoortstraat 98 Gent Oost-Vlaanderen 9000",
    "addr:housenumber":"98",
    "addr:postcode":"9000",
    "addr:street":"Dampoortstraat;Oost-Vlaanderen",
    "iso:country":"BE",
    "sg:address":"Dampoortstraat 98",
    "sg:city":"Gent",
    "sg:classifiers":[
        {
            "category":"Bars & Pubs",
            "type":"Food & Drink"
        }
    ],
    "sg:phone":"+32 9 233 68 40",
    "sg:postcode":"9000",
    "sg:province":"Oost-Vlaanderen",
    "sg:tags":[
        "tavern"
    ],
    "wof:name":"Zevende Hemel (de)",
    "wof:placetype":"venue"
},
  "geometry": {"coordinates":[3.7386600971,51.0571212769],"type":"Point"}
}