{
  "type": "Feature",
  "properties": {
    "iso:country":"BE",
    "sg:address":"Koningstraat 12",
    "sg:city":"Menen",
    "sg:orig_category":"Kapsalons",
    "sg:phone":"+32 56 51 64 84",
    "sg:postcode":"8930",
    "sg:province":"West-Vlaanderen",
    "wof:name":"Coiffure Linda",
    "wof:placetype":"venue"
},
  "geometry": {"coordinates":[3.11895895,50.7968597412],"type":"Point"}
}