{
  "type": "Feature",
  "properties": {
    "iso:country":"BE",
    "sg:address":"Kattestraat 5bd",
    "sg:city":"Olen",
    "sg:orig_category":"Peinture. Rev\u00eatements pour sols and murs",
    "sg:phone":"+32 14 26 78 02",
    "sg:postcode":"2250",
    "sg:province":"Antwerpen",
    "wof:name":"Decoraties Peeters",
    "wof:placetype":"venue"
},
  "geometry": {"coordinates":[4.8589267731,51.1405258179],"type":"Point"}
}