{
  "type": "Feature",
  "properties": {
    "iso:country":"BE",
    "sg:address":"Ruisbroeksesteenweg 65",
    "sg:city":"Sint-pieters-leeuw",
    "sg:orig_category":"Banques and organismes de cr\u00e9dit",
    "sg:phone":"+32 2 378 24 65",
    "sg:postcode":"1600",
    "sg:province":"Vlaams-Brabant",
    "wof:name":"Fortis",
    "wof:placetype":"venue"
},
  "geometry": {"coordinates":[4.2848591805,50.788646698],"type":"Point"}
}