{
  "type": "Feature",
  "properties": {
    "addr:full":"Mechelsesteenweg 85 Dendermonde Oost-Vlaanderen 9200",
    "addr:housenumber":"85",
    "addr:postcode":"9200",
    "addr:street":"Mechelsesteenweg;Oost-Vlaanderen",
    "iso:country":"BE",
    "sg:address":"Mechelsesteenweg 85",
    "sg:city":"Dendermonde",
    "sg:orig_category":"Supermarkten",
    "sg:postcode":"9200",
    "sg:province":"Oost-Vlaanderen",
    "wof:name":"Aldi",
    "wof:placetype":"venue"
},
  "geometry": {"coordinates":[4.1166782379,51.0357055664],"type":"Point"}
}