{
  "type": "Feature",
  "properties": {
    "iso:country":"BE",
    "sg:address":"Quai Andre\u00ef Sakharov 9",
    "sg:city":"Tournai",
    "sg:classifiers":[
        {
            "category":"Social Services",
            "type":"Services"
        }
    ],
    "sg:phone":"+32 69 21 40 76",
    "sg:postcode":"7500",
    "sg:province":"Hainaut",
    "wof:name":"Centre De Consultation Conjug",
    "wof:placetype":"venue"
},
  "geometry": {"coordinates":[3.3838539124,50.6139411926],"type":"Point"}
}