{
  "type": "Feature",
  "properties": {
    "addr:full":"Rue De La Petite Gaichel 16 Arlon Luxembourg 6700",
    "addr:housenumber":"16",
    "addr:postcode":"6700",
    "addr:street":"Rue De La Petite Gaichel",
    "iso:country":"BE",
    "sg:address":"Rue De La Petite Gaichel 16",
    "sg:city":"Arlon",
    "sg:orig_category":"Mat\u00e9riel m\u00e9dical and orthop\u00e9dique and proth\u00e8ses Fab",
    "sg:phone":"+32 63 21 72 57",
    "sg:postcode":"6700",
    "sg:province":"Luxembourg",
    "wof:name":"Labo Merveille & Charles",
    "wof:placetype":"venue"
},
  "geometry": {"coordinates":[5.8431830406,49.6895713806],"type":"Point"}
}