{
  "type": "Feature",
  "properties": {
    "iso:country":"BE",
    "sg:address":"Gen. Baron Jacquesstraat 1414",
    "sg:city":"Diksmuide",
    "sg:orig_category":"Opticiens",
    "sg:phone":"+32 51 50 15 84",
    "sg:postcode":"8600",
    "sg:province":"West-Vlaanderen",
    "wof:name":"Serry-optie",
    "wof:placetype":"venue"
},
  "geometry": {"coordinates":[2.8587899208,51.0326881409],"type":"Point"}
}