{
  "type": "Feature",
  "properties": {
    "iso:country":"BE",
    "sg:address":"Clos Stijn Streuvels 6",
    "sg:city":"Wezembeek-oppem",
    "sg:orig_category":"M\u00e9decines alternatives",
    "sg:phone":"+32 2 784 28 98",
    "sg:postcode":"1970",
    "sg:province":"Vlaams-Brabant",
    "wof:name":"Erpicum Blaise",
    "wof:placetype":"venue"
},
  "geometry": {"coordinates":[4.4962000847,50.8379745483],"type":"Point"}
}