{
  "type": "Feature",
  "properties": {
    "iso:country":"BE",
    "sg:address":"Meerhem 5",
    "sg:city":"Evergem",
    "sg:orig_category":"Eleveurs and marchands de porcs. Eleveurs de bovins",
    "sg:phone":"+32 9 357 38 43",
    "sg:postcode":"9940",
    "sg:province":"Oost-Vlaanderen",
    "wof:name":"Jackie Wittoek",
    "wof:placetype":"venue"
},
  "geometry": {"coordinates":[3.7306981087,51.1452026367],"type":"Point"}
}