{
  "type": "Feature",
  "properties": {
    "iso:country":"BE",
    "sg:address":"Broekelken 21bb",
    "sg:city":"Maldegem",
    "sg:orig_category":"Sportclubs Sportterreinen and installaties behalve sportcentra",
    "sg:phone":"+32 50 71 82 75",
    "sg:postcode":"9991",
    "sg:province":"Oost-Vlaanderen",
    "wof:name":"Voetbalklub Adegem",
    "wof:placetype":"venue"
},
  "geometry": {"coordinates":[3.4898650646,51.210735321],"type":"Point"}
}