{
  "type": "Feature",
  "properties": {
    "iso:country":"BE",
    "sg:address":"Veldstraat 5",
    "sg:city":"Etterbeek/etterbeek",
    "sg:orig_category":"Non-foodwinkels Verlichting and huishoudartikelen",
    "sg:phone":"+32 2 646 27 88",
    "sg:postcode":"1040",
    "sg:province":"Bruxelles-Capitale",
    "wof:name":"Maison Ad Hoc",
    "wof:placetype":"venue"
},
  "geometry": {"coordinates":[4.3906002045,50.8301315308],"type":"Point"}
}