{
  "type": "Feature",
  "properties": {
    "iso:country":"BE",
    "sg:address":"De Theuxstr 81",
    "sg:city":"Brussel",
    "sg:classifiers":[
        {
            "category":"Bakery",
            "type":"Food & Drink"
        }
    ],
    "sg:phone":"+32 2 648 31 93",
    "sg:postcode":"1050",
    "sg:province":"Bruxelles-Capitale",
    "sg:tags":[
        "cake",
        "product",
        "related",
        "bread"
    ],
    "wof:name":"Bakkerij Allemeersch Bvba",
    "wof:placetype":"venue"
},
  "geometry": {"coordinates":[4.3817129135,50.8324165344],"type":"Point"}
}