{
  "type": "Feature",
  "properties": {
    "iso:country":"BE",
    "sg:address":"Hodonk 63",
    "sg:city":"Retie",
    "sg:classifiers":[
        {
            "category":"Cafe",
            "type":"Food & Drink"
        }
    ],
    "sg:phone":"+32 14 37 10 61",
    "sg:postcode":"2470",
    "sg:province":"Antwerpen",
    "sg:tags":[
        "caf\u00e9s"
    ],
    "wof:name":"Mariette Scheveneels",
    "wof:placetype":"venue"
},
  "geometry": {"coordinates":[5.1192650795,51.2688179016],"type":"Point"}
}