{
  "type": "Feature",
  "properties": {
    "addr:full":"Avenue Numa-ensch-tesch 63 Arlon Luxembourg 6700",
    "addr:housenumber":"63",
    "addr:postcode":"6700",
    "addr:street":"Avenue Numa-Ensch-Tesch",
    "iso:country":"BE",
    "sg:address":"Avenue Numa-ensch-tesch 63",
    "sg:city":"Arlon",
    "sg:classifiers":[
        {
            "category":"Banks & Credit Unions",
            "subcategory":"Investment Brokerage",
            "type":"Services"
        }
    ],
    "sg:phone":"+32 63 22 64 09",
    "sg:postcode":"6700",
    "sg:province":"Luxembourg",
    "sg:tags":[
        "coil",
        "electric",
        "winding"
    ],
    "wof:name":"Hutting Ets",
    "wof:placetype":"venue"
},
  "geometry": {"coordinates":[5.8014369011,49.6895446777],"type":"Point"}
}