{
  "type": "Feature",
  "properties": {
    "iso:country":"BE",
    "sg:address":"Avenue Pr\u00c9sident Roosevelt 1",
    "sg:city":"Sambreville",
    "sg:orig_category":"RESTAURANTS: PAIN, P\u00c2TISSERIES AND CONFISERIES",
    "sg:phone":"+32 71 74 42 07",
    "sg:postcode":"5060",
    "sg:province":"Namur",
    "wof:name":"Au Croissant D'or",
    "wof:placetype":"venue"
},
  "geometry": {"coordinates":[4.6285200119,50.4448738098],"type":"Point"}
}