{
  "type": "Feature",
  "properties": {
    "addr:full":"Rue Petro Ferrero 12 Arlon Luxembourg 6700",
    "addr:housenumber":"12",
    "addr:postcode":"6700",
    "addr:street":"Rue Petro Ferrero",
    "iso:country":"BE",
    "sg:address":"Rue Petro Ferrero 12",
    "sg:city":"Arlon",
    "sg:classifiers":[
        {
            "category":"Government",
            "subcategory":"Department Of Motor Vehicles",
            "type":"Public Place"
        }
    ],
    "sg:phone":"+32 63 22 05 90",
    "sg:postcode":"6700",
    "sg:province":"Luxembourg",
    "sg:tags":[
        "equipment",
        "industrial",
        "transport",
        "motor-cars"
    ],
    "wof:name":"Sogalux",
    "wof:placetype":"venue"
},
  "geometry": {"coordinates":[5.8192138672,49.6740837097],"type":"Point"}
}