{
  "type": "Feature",
  "properties": {
    "addr:full":"Fond De Bondry 115 Ottignies-louvain-la-neuve Brabant Wallon 1342",
    "addr:housenumber":"115",
    "addr:postcode":"1342",
    "addr:street":"Ottignies-Louvain-La-Neuve Brabant",
    "iso:country":"BE",
    "sg:address":"Fond De Bondry 115",
    "sg:city":"Ottignies-louvain-la-neuve",
    "sg:orig_category":"Sportclubs",
    "sg:phone":"+32 10 41 45 69",
    "sg:postcode":"1342",
    "sg:province":"Brabant Wallon",
    "wof:name":"B.c. Speedy Mt-st.guibert",
    "wof:placetype":"venue"
},
  "geometry": {"coordinates":[4.5708270073,50.6812934875],"type":"Point"}
}