{
  "type": "Feature",
  "properties": {
    "iso:country":"BE",
    "sg:address":"Ommegangstraat 2c",
    "sg:city":"Nazareth",
    "sg:classifiers":[
        {
            "category":"Manufacturing",
            "subcategory":"Building Materials",
            "type":"Manufacturing & Wholesale Goods"
        }
    ],
    "sg:phone":"+32 477 88 68 67",
    "sg:postcode":"9810",
    "sg:province":"Oost-Vlaanderen",
    "sg:tags":[
        "wig",
        "hairworks"
    ],
    "wof:name":"Beauty-hairconcept",
    "wof:placetype":"venue"
},
  "geometry": {"coordinates":[3.6048769951,50.9564933777],"type":"Point"}
}