{
  "type": "Feature",
  "properties": {
    "addr:full":"Steengroevenlaan 5b3b1 Leuven Vlaams-Brabant 3001",
    "addr:housenumber":"5b3b1",
    "addr:postcode":"3001",
    "addr:street":"Steengroevenlaan",
    "iso:country":"BE",
    "sg:address":"Steengroevenlaan 5b3b1",
    "sg:city":"Leuven",
    "sg:orig_category":"Diverse informatica-activiteiten Informaticaconsulenten Software ontwikkeling and ontwerp",
    "sg:phone":"+32 495 45 30 97",
    "sg:postcode":"3001",
    "sg:province":"Vlaams-Brabant",
    "wof:name":"Root Services",
    "wof:placetype":"venue"
},
  "geometry": {"coordinates":[4.6959400177,50.8633499146],"type":"Point"}
}