{
  "type": "Feature",
  "properties": {
    "iso:country":"BE",
    "sg:address":"Moeresteenweg 7",
    "sg:city":"De Panne (adinkerke)",
    "sg:classifiers":[
        {
            "category":"Manufacturing",
            "subcategory":"Textiles",
            "type":"Manufacturing & Wholesale Goods"
        }
    ],
    "sg:phone":"+32 58 41 57 65",
    "sg:postcode":"8660",
    "sg:province":"West-Vlaanderen",
    "sg:tags":[
        "retail",
        "-"
    ],
    "wof:name":"'t Naaikorfje",
    "wof:placetype":"venue"
},
  "geometry": {"coordinates":[2.5873420238,51.0627746582],"type":"Point"}
}