{
  "type": "Feature",
  "properties": {
    "addr:full":"Ekkergemstraat 32 Gent Oost-Vlaanderen 9000",
    "addr:housenumber":"32",
    "addr:postcode":"9000",
    "addr:street":"Ekkergemstraat;Oost-Vlaanderen",
    "iso:country":"BE",
    "sg:address":"Ekkergemstraat 32",
    "sg:city":"Gent",
    "sg:classifiers":[
        {
            "category":"Personal",
            "subcategory":"Barber",
            "type":"Services"
        }
    ],
    "sg:phone":"+32 9 225 98 28",
    "sg:postcode":"9000",
    "sg:province":"Oost-Vlaanderen",
    "sg:tags":[
        "gentleman",
        "salon",
        "-",
        "hairdressing"
    ],
    "wof:name":"Omer",
    "wof:placetype":"venue"
},
  "geometry": {"coordinates":[3.6984848976,51.0534210205],"type":"Point"}
}