{
  "type": "Feature",
  "properties": {
    "addr:full":"Rodestraat 34a Ternat (sint-katherina-lombeek) Vlaams-Brabant 1742",
    "addr:housenumber":"34a",
    "addr:postcode":"1742",
    "addr:street":"Rodestraat",
    "iso:country":"BE",
    "sg:address":"Rodestraat 34a",
    "sg:city":"Ternat (sint-katherina-lombeek)",
    "sg:classifiers":[
        {
            "category":"Insurance",
            "subcategory":"Insurance Agent",
            "type":"Services"
        }
    ],
    "sg:phone":"+32 2 582 26 86",
    "sg:postcode":"1742",
    "sg:province":"Vlaams-Brabant",
    "sg:tags":[
        "broker"
    ],
    "wof:name":"Servranckx J",
    "wof:placetype":"venue"
},
  "geometry": {"coordinates":[4.1501288414,50.8730278015],"type":"Point"}
}