{
  "type": "Feature",
  "properties": {
    "addr:full":"Rue Aulichamps 40 Grace-hollogne Li\u00e8ge 4460",
    "addr:housenumber":"40",
    "addr:postcode":"4460",
    "addr:street":"Rue Aulichamps",
    "iso:country":"BE",
    "sg:address":"Rue Aulichamps 40",
    "sg:city":"Grace-hollogne",
    "sg:orig_category":"Traitements param\u00e9dicaux",
    "sg:phone":"+32 4 233 45 80",
    "sg:postcode":"4460",
    "sg:province":"Li\u00e8ge",
    "wof:name":"D. Pottel",
    "wof:placetype":"venue"
},
  "geometry": {"coordinates":[5.4809741974,50.6358146667],"type":"Point"}
}