{
  "type": "Feature",
  "properties": {
    "iso:country":"BE",
    "sg:address":"Gammel 2",
    "sg:city":"Rijkevorsel",
    "sg:classifiers":[
        {
            "category":"Shopping",
            "subcategory":"Bicycles & Sporting Goods",
            "type":"Retail Goods"
        }
    ],
    "sg:phone":"+32 3 314 63 05",
    "sg:postcode":"2310",
    "sg:province":"Antwerpen",
    "sg:tags":[
        "tyre"
    ],
    "wof:name":"Peeters G",
    "wof:placetype":"venue"
},
  "geometry": {"coordinates":[4.7577900887,51.3700256348],"type":"Point"}
}