{
  "type": "Feature",
  "properties": {
    "addr:full":"Vredelaan 90 Kortrijk West-Vlaanderen 8500",
    "addr:housenumber":"90",
    "addr:postcode":"8500",
    "addr:street":"Vredelaan",
    "iso:country":"BE",
    "sg:address":"Vredelaan 90",
    "sg:city":"Kortrijk",
    "sg:classifiers":[
        {
            "category":"Mining & Drilling",
            "type":"Manufacturing & Wholesale Goods"
        }
    ],
    "sg:phone":"+32 56 20 60 01",
    "sg:postcode":"8500",
    "sg:province":"West-Vlaanderen",
    "sg:tags":[
        "concrete",
        "reinforced",
        "sawing"
    ],
    "wof:name":"Derveaux Diamond",
    "wof:placetype":"venue"
},
  "geometry": {"coordinates":[3.2880890369,50.8261795044],"type":"Point"}
}