{
  "type": "Feature",
  "properties": {
    "iso:country":"BE",
    "sg:address":"Dorpsstraat 32ba",
    "sg:city":"Houthalen-helchteren",
    "sg:orig_category":"Elektrische installaties voor woningen",
    "sg:phone":"+32 11 60 27 50",
    "sg:postcode":"3530",
    "sg:province":"Limburg",
    "wof:name":"Alg.elektr.werken J. & P.",
    "wof:placetype":"venue"
},
  "geometry": {"coordinates":[5.3731942177,51.0310440063],"type":"Point"}
}