{
  "type": "Feature",
  "properties": {
    "iso:country":"BE",
    "sg:address":"Constant Permekelaan 59",
    "sg:city":"Jabbeke",
    "sg:classifiers":[
        {
            "category":"Banks & Credit Unions",
            "subcategory":"Bank",
            "type":"Services"
        }
    ],
    "sg:phone":"+32 50 81 32 52",
    "sg:postcode":"8490",
    "sg:province":"West-Vlaanderen",
    "sg:tags":[
        "savings-banks"
    ],
    "wof:name":"Krediet A/d Nijverheid",
    "wof:placetype":"venue"
},
  "geometry": {"coordinates":[3.0980739594,51.1809997559],"type":"Point"}
}