{
  "type": "Feature",
  "properties": {
    "iso:country":"BE",
    "sg:address":"Molenstraat 14",
    "sg:city":"Genk",
    "sg:classifiers":[
        {
            "category":"Shopping",
            "subcategory":"Optician",
            "type":"Retail Goods"
        }
    ],
    "sg:phone":"+32 89 35 24 34",
    "sg:postcode":"3600",
    "sg:province":"Limburg",
    "sg:tags":[
        "-"
    ],
    "wof:name":"Brouns K",
    "wof:placetype":"venue"
},
  "geometry": {"coordinates":[5.5010972023,50.964263916],"type":"Point"}
}