{
  "type": "Feature",
  "properties": {
    "addr:full":"Immerseelstraat 47 Wommelgem Antwerpen 2160",
    "addr:housenumber":"47",
    "addr:postcode":"2160",
    "addr:street":"Immerseelstraat",
    "iso:country":"BE",
    "sg:address":"Immerseelstraat 47",
    "sg:city":"Wommelgem",
    "sg:orig_category":"Locations de machines and \u00e9quipement pour la construction. Location de machines-outils and de mat\u00e9ri",
    "sg:phone":"+32 3 353 39 79",
    "sg:postcode":"2160",
    "sg:province":"Antwerpen",
    "wof:name":"Wommelgems Verhuurcenter",
    "wof:placetype":"venue"
},
  "geometry": {"coordinates":[4.4955849648,51.2105827332],"type":"Point"}
}