{
  "type": "Feature",
  "properties": {
    "addr:full":"Industriepark Opdeberg 1307 Maasmechelen Limburg 3630",
    "addr:housenumber":"1307",
    "addr:postcode":"3630",
    "addr:street":"Industriepark Opdeberg",
    "iso:country":"BE",
    "sg:address":"Industriepark Opdeberg 1307",
    "sg:city":"Maasmechelen",
    "sg:orig_category":"Office, Building, Fa\u00e7ade, Industry, Hospital Cleaning Services",
    "sg:phone":"+32 89 65 75 77",
    "sg:postcode":"3630",
    "sg:province":"Limburg",
    "wof:name":"Tlj Schoonmaakbedrijf Nv",
    "wof:placetype":"venue"
},
  "geometry": {"coordinates":[5.6961350441,50.963848114],"type":"Point"}
}