{
  "type": "Feature",
  "properties": {
    "iso:country":"BE",
    "sg:address":"Abeelstraat 23",
    "sg:city":"Ruiselede",
    "sg:orig_category":"Rundveehouders Varkenskwekers",
    "sg:phone":"+32 51 68 82 76",
    "sg:postcode":"8755",
    "sg:province":"West-Vlaanderen",
    "wof:name":"Vandaele-desimpel",
    "wof:placetype":"venue"
},
  "geometry": {"coordinates":[3.3732481003,51.0452232361],"type":"Point"}
}