{
  "type": "Feature",
  "properties": {
    "iso:country":"BE",
    "sg:address":"Rue De La Basse-sambre Boig. 20",
    "sg:city":"Sombreffe",
    "sg:classifiers":[
        {
            "category":"Wholesale",
            "subcategory":"Home Furnishings",
            "type":"Manufacturing & Wholesale Goods"
        }
    ],
    "sg:phone":"+32 71 81 54 44",
    "sg:postcode":"5140",
    "sg:province":"Namur",
    "sg:tags":[
        "house",
        "paint"
    ],
    "wof:name":"Iris S.a.",
    "wof:placetype":"venue"
},
  "geometry": {"coordinates":[4.593375206,50.4918823242],"type":"Point"}
}