{
  "type": "Feature",
  "properties": {
    "addr:full":"Place De Trivi\u00c8res 5 La Louvi\u00c8re Hainaut 7100",
    "addr:housenumber":"5",
    "addr:postcode":"7100",
    "addr:street":"Place De Trivie\u0300Res",
    "iso:country":"BE",
    "sg:address":"Place De Trivi\u00c8res 5",
    "sg:city":"La Louvi\u00c8re",
    "sg:orig_category":"Herstellingen and onderhoud van auto's",
    "sg:phone":"+32 64 21 61 76",
    "sg:postcode":"7100",
    "sg:province":"Hainaut",
    "wof:name":"Rosario Lodico",
    "wof:placetype":"venue"
},
  "geometry": {"coordinates":[4.1850848198,50.4748649597],"type":"Point"}
}