{
  "type": "Feature",
  "properties": {
    "iso:country":"BE",
    "sg:address":"Veinderstraat 10",
    "sg:city":"Dessel",
    "sg:classifiers":[
        {
            "category":"Farming",
            "subcategory":"Livestock Farm",
            "type":"Manufacturing & Wholesale Goods"
        }
    ],
    "sg:phone":"+32 14 37 05 75",
    "sg:postcode":"2480",
    "sg:province":"Antwerpen",
    "sg:tags":[
        "buyer"
    ],
    "wof:name":"Goris D",
    "wof:placetype":"venue"
},
  "geometry": {"coordinates":[5.1390938759,51.2499427795],"type":"Point"}
}