{
  "type": "Feature",
  "properties": {
    "addr:full":"Amerikalei 20b220 Antwerpen Antwerpen 2000",
    "addr:housenumber":"20b220",
    "addr:postcode":"2000",
    "addr:street":"Amerikalei",
    "iso:country":"BE",
    "sg:address":"Amerikalei 20b220",
    "sg:city":"Antwerpen",
    "sg:orig_category":"Agences d'exp\u00e9dition",
    "sg:phone":"+32 3 238 99 98",
    "sg:postcode":"2000",
    "sg:province":"Antwerpen",
    "wof:name":"K F Traders",
    "wof:placetype":"venue"
},
  "geometry": {"coordinates":[4.4010128975,51.2087860107],"type":"Point"}
}