{
  "type": "Feature",
  "properties": {
    "iso:country":"BE",
    "sg:address":"Rue De Soignies 16",
    "sg:city":"Brussel/bruxelles",
    "sg:orig_category":"Ordinateurs and \u00e9quipement informatique. Entretien and r\u00e9parations de machines de bureau and ordinat",
    "sg:phone":"+32 2 548 78 18",
    "sg:postcode":"1000",
    "sg:province":"Bruxelles-Capitale",
    "wof:name":"Info Occases",
    "wof:placetype":"venue"
},
  "geometry": {"coordinates":[4.344689846,50.8444671631],"type":"Point"}
}