{
  "type": "Feature",
  "properties": {
    "iso:country":"BE",
    "sg:address":"Ruandadreef 8",
    "sg:city":"Keerbergen",
    "sg:orig_category":"Ordinateurs and \u00e9quipement informatique",
    "sg:phone":"+32 16 53 56 46",
    "sg:postcode":"3140",
    "sg:province":"Vlaams-Brabant",
    "wof:name":"Group 5",
    "wof:placetype":"venue"
},
  "geometry": {"coordinates":[4.692595005,50.9960250854],"type":"Point"}
}