{
  "type": "Feature",
  "properties": {
    "iso:country":"BE",
    "sg:address":"Beauvoislaan 7",
    "sg:city":"Kalmthout",
    "sg:orig_category":"M\u00e9decins and sp\u00e9cialistes",
    "sg:phone":"+32 3 666 46 46",
    "sg:postcode":"2920",
    "sg:province":"Antwerpen",
    "wof:name":"Jan Renier",
    "wof:placetype":"venue"
},
  "geometry": {"coordinates":[4.4697618484,51.3670845032],"type":"Point"}
}