{
  "type": "Feature",
  "properties": {
    "iso:country":"BE",
    "sg:address":"Rue Des Combattants 108",
    "sg:city":"La Hulpe",
    "sg:classifiers":[
        {
            "category":"Shopping",
            "subcategory":"Clothing, Apparel, & Fashions",
            "type":"Retail Goods"
        }
    ],
    "sg:phone":"+32 2 653 43 17",
    "sg:postcode":"1310",
    "sg:province":"Brabant Wallon",
    "sg:tags":[
        "-",
        "clothing",
        "child"
    ],
    "wof:name":"Arthur & Zo\u00e9",
    "wof:placetype":"venue"
},
  "geometry": {"coordinates":[4.4863348007,50.7309684753],"type":"Point"}
}