{
  "type": "Feature",
  "properties": {
    "addr:full":"Tervuursesteenweg 45 Zemst (hofstade) Vlaams-Brabant 1981",
    "addr:housenumber":"45",
    "addr:postcode":"1981",
    "addr:street":"Tervuursesteenweg",
    "iso:country":"BE",
    "sg:address":"Tervuursesteenweg 45",
    "sg:city":"Zemst (hofstade)",
    "sg:classifiers":[
        {
            "category":"Health Services",
            "subcategory":"Health Practitioner",
            "type":"Services"
        }
    ],
    "sg:phone":"+32 15 41 93 01",
    "sg:postcode":"1981",
    "sg:province":"Vlaams-Brabant",
    "sg:tags":[
        "physiotherapist"
    ],
    "wof:name":"Mu\u00ebs C",
    "wof:placetype":"venue"
},
  "geometry": {"coordinates":[4.4885430336,50.9971733093],"type":"Point"}
}