{
  "type": "Feature",
  "properties": {
    "iso:country":"BE",
    "sg:address":"Van Aertselaerstraat 67",
    "sg:city":"Hoogstraten",
    "sg:orig_category":"R\u00e9parations de chaussures and articles en cuir",
    "sg:phone":"+32 3 314 67 07",
    "sg:postcode":"2322",
    "sg:province":"Antwerpen",
    "wof:name":"Jan Van De Looverbosch",
    "wof:placetype":"venue"
},
  "geometry": {"coordinates":[4.7635521889,51.4135894775],"type":"Point"}
}