{
  "type": "Feature",
  "properties": {
    "addr:full":"Place D\u00b4irchonwelz 2 Ath Hainaut 7801",
    "addr:housenumber":"2",
    "addr:postcode":"7801",
    "addr:street":"Place D\u00b4Irchonwelz",
    "iso:country":"BE",
    "sg:address":"Place D\u00b4irchonwelz 2",
    "sg:city":"Ath",
    "sg:orig_category":"Enseignement maternel and primaire",
    "sg:phone":"+32 68 28 64 92",
    "sg:postcode":"7801",
    "sg:province":"Hainaut",
    "wof:name":"Ecole Fondamentale Libre",
    "wof:placetype":"venue"
},
  "geometry": {"coordinates":[3.7528979778,50.6169166565],"type":"Point"}
}