{
  "type": "Feature",
  "properties": {
    "iso:country":"BE",
    "sg:address":"Chauss\u00e9e De Bruxelles 644",
    "sg:city":"Waterloo",
    "sg:classifiers":[
        {
            "category":"Real Estate",
            "subcategory":"Real Estate Services",
            "type":"Services"
        }
    ],
    "sg:phone":"+32 2 351 11 29",
    "sg:postcode":"1410",
    "sg:province":"Brabant Wallon",
    "wof:name":"A. Gestion Sa",
    "wof:placetype":"venue"
},
  "geometry": {"coordinates":[4.4023189545,50.6972541809],"type":"Point"}
}