{
  "type": "Feature",
  "properties": {
    "iso:country":"BE",
    "sg:address":"Eerste Aardstraat 5a",
    "sg:city":"Harelbeke (bavikhove)",
    "sg:orig_category":"Non-Classified Establishments",
    "sg:phone":"+32 56 71 06 13",
    "sg:postcode":"8531",
    "sg:province":"West-Vlaanderen",
    "wof:name":"Coorevtis Etienne Bvba",
    "wof:placetype":"venue"
},
  "geometry": {"coordinates":[3.3195090294,50.8882217407],"type":"Point"}
}