{
  "type": "Feature",
  "properties": {
    "addr:full":"Chauss\u00e9e Bara 68 Braine L'alleud (braine-l'alleud) Brabant Wallon 1420",
    "addr:housenumber":"68",
    "addr:postcode":"1420",
    "addr:street":"Chausse\u0301E Bara",
    "iso:country":"BE",
    "sg:address":"Chauss\u00e9e Bara 68",
    "sg:city":"Braine L'alleud (braine-l'alleud)",
    "sg:classifiers":[
        {
            "category":"Professional",
            "subcategory":"Business Services",
            "type":"Services"
        }
    ],
    "sg:phone":"+32 2 386 43 80",
    "sg:postcode":"1420",
    "sg:province":"Brabant Wallon",
    "sg:tags":[
        "firm"
    ],
    "wof:name":"Bwos Center Sa",
    "wof:placetype":"venue"
},
  "geometry": {"coordinates":[-0.7711730003,47.3931159973],"type":"Point"}
}