{
  "type": "Feature",
  "properties": {
    "addr:full":"Sint-kristoffelstraat 15-17 Londerzeel Vlaams-Brabant 1840",
    "addr:housenumber":"15-17",
    "addr:postcode":"1840",
    "addr:street":"Sint-Kristoffelstraat",
    "iso:country":"BE",
    "sg:address":"Sint-kristoffelstraat 15-17",
    "sg:city":"Londerzeel",
    "sg:classifiers":[
        {
            "category":"Insurance",
            "subcategory":"Insurance Agent",
            "type":"Services"
        }
    ],
    "sg:phone":"+32 52 30 06 10",
    "sg:postcode":"1840",
    "sg:province":"Vlaams-Brabant",
    "sg:tags":[
        "broker"
    ],
    "wof:name":"De Dobbeleer L Bvba",
    "wof:placetype":"venue"
},
  "geometry": {"coordinates":[4.309196949,51.0064964294],"type":"Point"}
}