{
  "type": "Feature",
  "properties": {
    "iso:country":"BE",
    "sg:address":"Hingenesteenweg 57b2",
    "sg:city":"Bornem",
    "sg:orig_category":"Articles de jardin. Art and fournitures artistiques",
    "sg:phone":"+32 3 889 12 39",
    "sg:postcode":"2880",
    "sg:province":"Antwerpen",
    "wof:name":"Codefa Kaderfabriek",
    "wof:placetype":"venue"
},
  "geometry": {"coordinates":[4.2468929291,51.1005821228],"type":"Point"}
}