{
  "type": "Feature",
  "properties": {
    "addr:full":"Langestr 111 Houtvenne Antwerpen 2235",
    "addr:housenumber":"111",
    "addr:postcode":"2235",
    "iso:country":"BE",
    "sg:address":"Langestr 111",
    "sg:city":"Houtvenne",
    "sg:classifiers":[
        {
            "category":"Professional",
            "type":"Services"
        }
    ],
    "sg:phone":"+32 16 69 87 80",
    "sg:postcode":"2235",
    "sg:province":"Antwerpen",
    "sg:tags":[
        "transport",
        "road"
    ],
    "wof:name":"Verrycken Vervoer Bvba",
    "wof:placetype":"venue"
},
  "geometry": {"coordinates":[4.8012151718,51.0350532532],"type":"Point"}
}