{
  "type": "Feature",
  "properties": {
    "addr:full":"Pater Verschuerenstraat 52 Turnhout Antwerpen 2300",
    "addr:housenumber":"52",
    "addr:postcode":"2300",
    "addr:street":"Pater Verschuerenstraat",
    "iso:country":"BE",
    "sg:address":"Pater Verschuerenstraat 52",
    "sg:city":"Turnhout",
    "sg:classifiers":[
        {
            "category":"Arena",
            "subcategory":"Sports Club",
            "type":"Entertainment"
        }
    ],
    "sg:phone":"+32 14 41 27 92",
    "sg:postcode":"2300",
    "sg:province":"Antwerpen",
    "wof:name":"Nova Keurturngroep Vzw",
    "wof:placetype":"venue"
},
  "geometry": {"coordinates":[4.9328570366,51.3153305054],"type":"Point"}
}