{
  "type": "Feature",
  "properties": {
    "iso:country":"BE",
    "sg:address":"Herentalsesteenweg 33",
    "sg:city":"Lille",
    "sg:classifiers":[
        {
            "category":"Personal",
            "subcategory":"Beauty Salon",
            "type":"Services"
        }
    ],
    "sg:phone":"+32 14 88 24 39",
    "sg:postcode":"2275",
    "sg:province":"Antwerpen",
    "sg:tags":[
        "de",
        "coiffure"
    ],
    "wof:name":"Coiffure Rita",
    "wof:placetype":"venue"
},
  "geometry": {"coordinates":[4.8336691856,51.2247276306],"type":"Point"}
}