{
  "type": "Feature",
  "properties": {
    "addr:full":"Bevrijdingsplein 6 Menen West-Vlaanderen 8930",
    "addr:housenumber":"6",
    "addr:postcode":"8930",
    "addr:street":"Bevrijdingsplein",
    "iso:country":"BE",
    "sg:address":"Bevrijdingsplein 6",
    "sg:city":"Menen",
    "sg:orig_category":"Gespecialiseerde residenti\u00eble bouw",
    "sg:phone":"+32 56 53 01 19",
    "sg:postcode":"8930",
    "sg:province":"West-Vlaanderen",
    "wof:name":"Kurt Christiaens",
    "wof:placetype":"venue"
},
  "geometry": {"coordinates":[3.1141629219,50.7988357544],"type":"Point"}
}