{
  "type": "Feature",
  "properties": {
    "iso:country":"BE",
    "sg:address":"Rue Jean Jaur\u00c8s 7",
    "sg:city":"Ecaussinnes",
    "sg:classifiers":[
        {
            "category":"Cafe",
            "type":"Food & Drink"
        }
    ],
    "sg:phone":"+32 67 44 38 15",
    "sg:postcode":"7190",
    "sg:province":"Hainaut",
    "sg:tags":[
        "caf\u00e9s"
    ],
    "wof:name":"Maison Des Ouvriers",
    "wof:placetype":"venue"
},
  "geometry": {"coordinates":[4.1655678749,50.5676689148],"type":"Point"}
}