{
  "type": "Feature",
  "properties": {
    "addr:full":"Rue De Hamme-mille 94 Grez-doiceau Brabant Wallon 1390",
    "addr:housenumber":"94",
    "addr:postcode":"1390",
    "addr:street":"Rue De Hamme-Mille",
    "iso:country":"BE",
    "sg:address":"Rue De Hamme-mille 94",
    "sg:city":"Grez-doiceau",
    "sg:orig_category":"Mat\u00e9riaux de construction Gr",
    "sg:phone":"+32 10 86 64 35",
    "sg:postcode":"1390",
    "sg:province":"Brabant Wallon",
    "wof:name":"Emile Motte",
    "wof:placetype":"venue"
},
  "geometry": {"coordinates":[4.681951046,50.7835121155],"type":"Point"}
}