{
  "type": "Feature",
  "properties": {
    "iso:country":"BE",
    "sg:address":"Auf'm Rain 21a",
    "sg:city":"Eupen",
    "sg:orig_category":"Installation de menuiserie en bois and plastique",
    "sg:phone":"+32 87 74 46 66",
    "sg:postcode":"4700",
    "sg:province":"Li\u00e8ge",
    "wof:name":"Nyssen Franz",
    "wof:placetype":"venue"
},
  "geometry": {"coordinates":[6.0405111313,50.6298408508],"type":"Point"}
}