{
  "type": "Feature",
  "properties": {
    "iso:country":"BE",
    "sg:address":"Rue Grande 70",
    "sg:city":"Quievrain",
    "sg:orig_category":"Dameskledingzaken",
    "sg:phone":"+32 65 43 01 65",
    "sg:postcode":"7380",
    "sg:province":"Hainaut",
    "wof:name":"New Cr\u00c9olle",
    "wof:placetype":"venue"
},
  "geometry": {"coordinates":[3.6826660633,50.4053993225],"type":"Point"}
}