{
  "type": "Feature",
  "properties": {
    "addr:full":"Place Albert Ier 26 Froidchapelle Hainaut 6440",
    "addr:housenumber":"26",
    "addr:postcode":"6440",
    "addr:street":"Place Albert Ier",
    "iso:country":"BE",
    "sg:address":"Place Albert Ier 26",
    "sg:city":"Froidchapelle",
    "sg:orig_category":"Jeux de hasard",
    "sg:phone":"+32 60 41 10 20",
    "sg:postcode":"6440",
    "sg:province":"Hainaut",
    "wof:name":"Ladbrokes",
    "wof:placetype":"venue"
},
  "geometry": {"coordinates":[4.3285031319,50.1511001587],"type":"Point"}
}