{
  "type": "Feature",
  "properties": {
    "addr:full":"Fraterstraat 114 Merelbeke Oost-Vlaanderen 9820",
    "addr:housenumber":"114",
    "addr:postcode":"9820",
    "addr:street":"Fraterstraat",
    "iso:country":"BE",
    "sg:address":"Fraterstraat 114",
    "sg:city":"Merelbeke",
    "sg:classifiers":[
        {
            "category":"Bars & Pubs",
            "type":"Food & Drink"
        }
    ],
    "sg:phone":"+32 9 231 94 02",
    "sg:postcode":"9820",
    "sg:province":"Oost-Vlaanderen",
    "sg:tags":[
        "tavern"
    ],
    "wof:name":"Picasso",
    "wof:placetype":"venue"
},
  "geometry": {"coordinates":[3.7611238956,51.0113983154],"type":"Point"}
}