{
  "type": "Feature",
  "properties": {
    "addr:full":"Liebaardstraat 50 Waregem West-Vlaanderen 8792",
    "addr:housenumber":"50",
    "addr:postcode":"8792",
    "addr:street":"Liebaardstraat",
    "iso:country":"BE",
    "sg:address":"Liebaardstraat 50",
    "sg:city":"Waregem",
    "sg:orig_category":"Meubelzaken, woning- and keukeninrichting Vloer- and muurbekleding",
    "sg:phone":"+32 56 71 32 72",
    "sg:postcode":"8792",
    "sg:province":"West-Vlaanderen",
    "wof:name":"Meubelen Tassaert",
    "wof:placetype":"venue"
},
  "geometry": {"coordinates":[3.3511149883,50.8852043152],"type":"Point"}
}