{
  "type": "Feature",
  "properties": {
    "addr:full":"Chauss\u00c9e De Louvain 38 Eghez\u00c9e Namur 5310",
    "addr:housenumber":"38",
    "addr:postcode":"5310",
    "addr:street":"Chausse\u0301E De Louvain",
    "iso:country":"BE",
    "sg:address":"Chauss\u00c9e De Louvain 38",
    "sg:city":"Eghez\u00c9e",
    "sg:orig_category":"Paramedische behandelingen",
    "sg:phone":"+32 81 81 33 68",
    "sg:postcode":"5310",
    "sg:province":"Namur",
    "wof:name":"N. Biatour",
    "wof:placetype":"venue"
},
  "geometry": {"coordinates":[4.9090771675,50.5953140259],"type":"Point"}
}