{
  "type": "Feature",
  "properties": {
    "addr:full":"Zwartestraat 5 Vleteren West-Vlaanderen 8640",
    "addr:housenumber":"5",
    "addr:postcode":"8640",
    "addr:street":"Zwartestraat",
    "iso:country":"BE",
    "sg:address":"Zwartestraat 5",
    "sg:city":"Vleteren",
    "sg:orig_category":"Varkenskwekers",
    "sg:phone":"+32 57 42 26 25",
    "sg:postcode":"8640",
    "sg:province":"West-Vlaanderen",
    "wof:name":"Johan Vandael",
    "wof:placetype":"venue"
},
  "geometry": {"coordinates":[2.8033120632,50.8996429443],"type":"Point"}
}