{
  "type": "Feature",
  "properties": {
    "iso:country":"BE",
    "sg:address":"Motestraat 35",
    "sg:city":"Ardooie",
    "sg:classifiers":[
        {
            "category":"Professional",
            "subcategory":"Testing Lab",
            "type":"Services"
        }
    ],
    "sg:phone":"+32 51 74 73 61",
    "sg:postcode":"8850",
    "sg:province":"West-Vlaanderen",
    "sg:tags":[
        "laboratory",
        "medical"
    ],
    "wof:name":"Klinisch Labo Termote-declerck",
    "wof:placetype":"venue"
},
  "geometry": {"coordinates":[3.1967699528,50.9727745056],"type":"Point"}
}