{
  "type": "Feature",
  "properties": {
    "addr:full":"Alo\u00efs Joosstraat 102 Gent Oost-Vlaanderen 9000",
    "addr:housenumber":"102",
    "addr:postcode":"9000",
    "addr:street":"Joosstraat;Oost-Vlaanderen",
    "iso:country":"BE",
    "sg:address":"Alo\u00efs Joosstraat 102",
    "sg:city":"Gent",
    "sg:classifiers":[
        {
            "category":"Professional",
            "subcategory":"Accounting & Tax Preparation",
            "type":"Services"
        }
    ],
    "sg:phone":"+32 9 223 99 82",
    "sg:postcode":"9000",
    "sg:province":"Oost-Vlaanderen",
    "sg:tags":[
        "bookkeeper"
    ],
    "wof:name":"Fiscaal & Boekhoudingskantoor Serbruyns",
    "wof:placetype":"venue"
},
  "geometry": {"coordinates":[3.7068870068,51.0618400574],"type":"Point"}
}