{
  "type": "Feature",
  "properties": {
    "iso:country":"BE",
    "sg:address":"Rue Entre Deux Portes 110",
    "sg:city":"Huy",
    "sg:classifiers":[
        {
            "category":"Real Estate",
            "subcategory":"Surveying",
            "type":"Services"
        }
    ],
    "sg:phone":"+32 85 23 00 73",
    "sg:postcode":"4500",
    "sg:province":"Li\u00e8ge",
    "sg:tags":[
        "lettering",
        "letter"
    ],
    "wof:name":"Bernard J-m",
    "wof:placetype":"venue"
},
  "geometry": {"coordinates":[5.2306399345,50.524974823],"type":"Point"}
}