{
  "type": "Feature",
  "properties": {
    "addr:full":"Rue Duc D' Arenberg 9 Rebecq Brabant Wallon 1430",
    "addr:housenumber":"9",
    "addr:postcode":"1430",
    "addr:street":"Rue Duc D ' Arenberg",
    "iso:country":"BE",
    "sg:address":"Rue Duc D' Arenberg 9",
    "sg:city":"Rebecq",
    "sg:orig_category":"Schoonheidssalons",
    "sg:phone":"+32 2 395 88 60",
    "sg:postcode":"1430",
    "sg:province":"Brabant Wallon",
    "wof:name":"Stevens N.",
    "wof:placetype":"venue"
},
  "geometry": {"coordinates":[4.1231732368,50.6913642883],"type":"Point"}
}