{
  "type": "Feature",
  "properties": {
    "iso:country":"BE",
    "sg:address":"Markt 24",
    "sg:city":"Berlaar",
    "sg:orig_category":"Enseignement secondaire technique and professionnel. Enseignement secondaire g\u00e9n\u00e9ral",
    "sg:phone":"+32 3 482 41 94",
    "sg:postcode":"2590",
    "sg:province":"Antwerpen",
    "wof:name":"Inst. H.-hart Van Maria",
    "wof:placetype":"venue"
},
  "geometry": {"coordinates":[4.6615190506,51.1184997559],"type":"Point"}
}