{
  "type": "Feature",
  "properties": {
    "iso:country":"BE",
    "sg:address":"Rue Ferrer 204",
    "sg:city":"La Louviere",
    "sg:orig_category":"Services fun\u00e9raires. Fleurs and plantes",
    "sg:phone":"+32 64 22 77 18",
    "sg:postcode":"7100",
    "sg:province":"Hainaut",
    "wof:name":"Fun\u00c9railles Jolimontoises",
    "wof:placetype":"venue"
},
  "geometry": {"coordinates":[4.2158098221,50.4753799438],"type":"Point"}
}