{
  "type": "Feature",
  "properties": {
    "iso:country":"BE",
    "sg:address":"Dorpstraat 57",
    "sg:city":"Koksijde",
    "sg:orig_category":"HERSTELLING ELEKTRISCHE HUISHOUDAPPARATEN Onderhoud van kantoor- and computeruitrusting",
    "sg:phone":"+32 58 52 37 94",
    "sg:postcode":"8670",
    "sg:province":"West-Vlaanderen",
    "wof:name":"Service Center Pauwels",
    "wof:placetype":"venue"
},
  "geometry": {"coordinates":[2.6809830666,51.1146583557],"type":"Point"}
}