{
  "type": "Feature",
  "properties": {
    "addr:full":"Grand Rue 39 Fontaine-l'ev\u00eaque Hainaut 6140",
    "addr:housenumber":"39",
    "addr:postcode":"6140",
    "addr:street":"Grand Rue;\u0302Que Hainaut",
    "iso:country":"BE",
    "sg:address":"Grand Rue 39",
    "sg:city":"Fontaine-l'ev\u00eaque",
    "sg:classifiers":[
        {
            "category":"Professional",
            "subcategory":"Testing Lab",
            "type":"Services"
        }
    ],
    "sg:phone":"+32 71 52 31 88",
    "sg:postcode":"6140",
    "sg:province":"Hainaut",
    "sg:tags":[
        "chemist"
    ],
    "wof:name":"Cassivelan",
    "wof:placetype":"venue"
},
  "geometry": {"coordinates":[-111.9644622803,46.2507972717],"type":"Point"}
}