{
  "type": "Feature",
  "properties": {
    "addr:full":"Rue Des C\u00e9lestines 11 Li\u00e8ge 1 Li\u00e8ge 4000",
    "addr:housenumber":"11;1",
    "addr:postcode":"4000",
    "addr:street":"Rue Des Ce\u0301Lestines",
    "iso:country":"BE",
    "sg:address":"Rue Des C\u00e9lestines 11",
    "sg:city":"Li\u00e8ge 1",
    "sg:classifiers":[
        {
            "category":"Bars & Pubs",
            "type":"Food & Drink"
        }
    ],
    "sg:phone":"+32 4 223 71 23",
    "sg:postcode":"4000",
    "sg:province":"Li\u00e8ge",
    "wof:name":"Carr\u00e9 Du Roy (le)",
    "wof:placetype":"venue"
},
  "geometry": {"coordinates":[5.5685329437,50.641784668],"type":"Point"}
}