{
  "type": "Feature",
  "properties": {
    "iso:country":"BE",
    "sg:address":"Rumstsestraat 82",
    "sg:city":"Rumst",
    "sg:classifiers":[
        {
            "category":"Food & Beverages",
            "subcategory":"Fruits & Vegetables",
            "type":"Retail Goods"
        }
    ],
    "sg:phone":"+32 3 888 42 21",
    "sg:postcode":"2840",
    "sg:province":"Antwerpen",
    "sg:tags":[
        "groenten"
    ],
    "wof:name":"Fa. De Laet",
    "wof:placetype":"venue"
},
  "geometry": {"coordinates":[4.4157390594,51.0986251831],"type":"Point"}
}