{
  "type": "Feature",
  "properties": {
    "addr:full":"Bondgenotenlaan 50 Leuven Vlaams-Brabant 3000",
    "addr:housenumber":"50",
    "addr:postcode":"3000",
    "addr:street":"Bondgenotenlaan",
    "iso:country":"BE",
    "sg:address":"Bondgenotenlaan 50",
    "sg:city":"Leuven",
    "sg:orig_category":"Slagers",
    "sg:phone":"+32 16 22 72 48",
    "sg:postcode":"3000",
    "sg:province":"Vlaams-Brabant",
    "wof:name":"Fa. Aelbrecht",
    "wof:placetype":"venue"
},
  "geometry": {"coordinates":[4.7064762115,50.879699707],"type":"Point"}
}