{
  "type": "Feature",
  "properties": {
    "iso:country":"BE",
    "sg:address":"Rue Du Fourneau 60",
    "sg:city":"Florennes (saint-aubin)",
    "sg:classifiers":[
        {
            "category":"Arts & Performance",
            "subcategory":"Music",
            "type":"Entertainment"
        }
    ],
    "sg:phone":"+32 71 68 55 52",
    "sg:postcode":"5620",
    "sg:province":"Namur",
    "sg:tags":[
        "disc-jockeys"
    ],
    "wof:name":"Noctambules (les)",
    "wof:placetype":"venue"
},
  "geometry": {"coordinates":[4.5677819252,50.2448692322],"type":"Point"}
}