{
  "type": "Feature",
  "properties": {
    "addr:full":"Handelslei 270 Zoersel Antwerpen 2980",
    "addr:housenumber":"270",
    "addr:postcode":"2980",
    "iso:country":"BE",
    "sg:address":"Handelslei 270",
    "sg:city":"Zoersel",
    "sg:orig_category":"Verlichting and huishoudartikelen",
    "sg:phone":"+32 3 383 03 76",
    "sg:postcode":"2980",
    "sg:province":"Antwerpen",
    "wof:name":"Cado Stuyts",
    "wof:placetype":"venue"
},
  "geometry": {"coordinates":[4.6485280991,51.2734375],"type":"Point"}
}