{
  "type": "Feature",
  "properties": {
    "addr:full":"Rue De La Ville 16 Couvin Namur 5660",
    "addr:housenumber":"16",
    "addr:postcode":"5660",
    "addr:street":"Rue De La Ville",
    "iso:country":"BE",
    "sg:address":"Rue De La Ville 16",
    "sg:city":"Couvin",
    "sg:classifiers":[
        {
            "category":"Utilities",
            "subcategory":"Fuel Oil & Lpg",
            "type":"Services"
        }
    ],
    "sg:phone":"+32 60 34 46 75",
    "sg:postcode":"5660",
    "sg:province":"Namur",
    "sg:tags":[
        "stations-service",
        "combustible",
        "carburants"
    ],
    "wof:name":"Patigny",
    "wof:placetype":"venue"
},
  "geometry": {"coordinates":[4.4961900711,50.0521278381],"type":"Point"}
}