{
  "type": "Feature",
  "properties": {
    "iso:country":"BE",
    "sg:address":"Rue Wiertz 2",
    "sg:city":"Dinant",
    "sg:orig_category":"M\u00e9decins and sp\u00e9cialistes",
    "sg:phone":"+32 82 22 41 12",
    "sg:postcode":"5500",
    "sg:province":"Namur",
    "wof:name":"Fernand Briquemont",
    "wof:placetype":"venue"
},
  "geometry": {"coordinates":[4.9134440422,50.2573814392],"type":"Point"}
}