{
  "type": "Feature",
  "properties": {
    "addr:full":"Bruul 94 Geel Antwerpen 2440",
    "addr:housenumber":"94",
    "addr:postcode":"2440",
    "addr:street":"Bruul",
    "iso:country":"BE",
    "sg:address":"Bruul 94",
    "sg:city":"Geel",
    "sg:classifiers":[
        {
            "category":"Transit Center",
            "subcategory":"Freight",
            "type":"Transportation"
        }
    ],
    "sg:phone":"+32 14 59 00 46",
    "sg:postcode":"2440",
    "sg:province":"Antwerpen",
    "sg:tags":[
        "glue"
    ],
    "wof:name":"K N K Trading Bvba",
    "wof:placetype":"venue"
},
  "geometry": {"coordinates":[5.0489997864,51.1650886536],"type":"Point"}
}