{
  "type": "Feature",
  "properties": {
    "addr:full":"Avenue Des Combattants 56ba Gembloux Namur 5030",
    "addr:housenumber":"56ba",
    "addr:postcode":"5030",
    "addr:street":"Avenue Des Combattants;Namur",
    "iso:country":"BE",
    "sg:address":"Avenue Des Combattants 56ba",
    "sg:city":"Gembloux",
    "sg:orig_category":"Agences immobili\u00e8res",
    "sg:phone":"+32 81 61 05 30",
    "sg:postcode":"5030",
    "sg:province":"Namur",
    "wof:name":"Immo Protect",
    "wof:placetype":"venue"
},
  "geometry": {"coordinates":[4.7011351585,50.5582046509],"type":"Point"}
}