{
  "type": "Feature",
  "properties": {
    "iso:country":"BE",
    "sg:address":"Rue De L'ath\u00e9n\u00e9e 9",
    "sg:city":"Charleroi",
    "sg:classifiers":[
        {
            "category":"Professional",
            "subcategory":"Lawyer & Legal Services",
            "type":"Services"
        }
    ],
    "sg:phone":"+32 71 70 24 76",
    "sg:postcode":"6000",
    "sg:province":"Hainaut",
    "wof:name":"Janssens Anne",
    "wof:placetype":"venue"
},
  "geometry": {"coordinates":[4.4488067627,50.4072990417],"type":"Point"}
}