{
  "type": "Feature",
  "properties": {
    "addr:full":"Rue De Bruxelles 5 Mouscron Hainaut 7700",
    "addr:housenumber":"5",
    "addr:postcode":"7700",
    "addr:street":"Rue De Bruxelles",
    "iso:country":"BE",
    "sg:address":"Rue De Bruxelles 5",
    "sg:city":"Mouscron",
    "sg:classifiers":[
        {
            "category":"Home & Garden",
            "subcategory":"Home Furnishings",
            "type":"Retail Goods"
        }
    ],
    "sg:phone":"+32 56 33 47 16",
    "sg:postcode":"7700",
    "sg:province":"Hainaut",
    "sg:tags":[
        "interior",
        "decoration"
    ],
    "wof:name":"Ateliers 5",
    "wof:placetype":"venue"
},
  "geometry": {"coordinates":[3.2122449875,50.7446556091],"type":"Point"}
}