{
  "type": "Feature",
  "properties": {
    "iso:country":"BE",
    "sg:address":"Henisstraat 32",
    "sg:city":"Tongeren",
    "sg:classifiers":[
        {
            "category":"Fast Food",
            "type":"Food & Drink"
        }
    ],
    "sg:phone":"+32 12 26 34 98",
    "sg:postcode":"3700",
    "sg:province":"Limburg",
    "sg:tags":[
        "fried",
        "stand",
        "potato"
    ],
    "wof:name":"Knabbel En Babbel",
    "wof:placetype":"venue"
},
  "geometry": {"coordinates":[5.4695820808,50.7863197327],"type":"Point"}
}