{
  "type": "Feature",
  "properties": {
    "addr:full":"Rue De La Barque 3 Bernissart Hainaut 7321",
    "addr:housenumber":"3",
    "addr:postcode":"7321",
    "addr:street":"Rue De La Barque",
    "iso:country":"BE",
    "sg:address":"Rue De La Barque 3",
    "sg:city":"Bernissart",
    "sg:orig_category":"Epiceries",
    "sg:phone":"+32 69 57 88 46",
    "sg:postcode":"7321",
    "sg:province":"Hainaut",
    "wof:name":"Maison Cricri",
    "wof:placetype":"venue"
},
  "geometry": {"coordinates":[3.6534349918,50.5032424927],"type":"Point"}
}