{
  "type": "Feature",
  "properties": {
    "addr:full":"Rue De Crahiat 8 Ciney Namur 5590",
    "addr:housenumber":"8",
    "addr:postcode":"5590",
    "addr:street":"Rue De Crahiat",
    "iso:country":"BE",
    "sg:address":"Rue De Crahiat 8",
    "sg:city":"Ciney",
    "sg:classifiers":[
        {
            "category":"Shopping",
            "subcategory":"Bicycles & Sporting Goods",
            "type":"Retail Goods"
        }
    ],
    "sg:phone":"+32 83 63 69 69",
    "sg:postcode":"5590",
    "sg:province":"Namur",
    "sg:tags":[
        "sport",
        "-"
    ],
    "wof:name":"Twinner Sa",
    "wof:placetype":"venue"
},
  "geometry": {"coordinates":[5.0916061401,50.2895736694],"type":"Point"}
}