{
  "type": "Feature",
  "properties": {
    "addr:full":"Rue Victor-croisier 148 Li\u00e8ge 1 (rocourt) Li\u00e8ge 4000",
    "addr:housenumber":"148;1",
    "addr:postcode":"4000",
    "addr:street":"Rue Victor-Croisier",
    "iso:country":"BE",
    "sg:address":"Rue Victor-croisier 148",
    "sg:city":"Li\u00e8ge 1 (rocourt)",
    "sg:classifiers":[
        {
            "category":"Health Services",
            "subcategory":"Health Practitioner",
            "type":"Services"
        }
    ],
    "sg:phone":"+32 4 225 11 62",
    "sg:postcode":"4000",
    "sg:province":"Li\u00e8ge",
    "sg:tags":[
        "physiotherapist"
    ],
    "wof:name":"Chaumont L",
    "wof:placetype":"venue"
},
  "geometry": {"coordinates":[5.5664057732,50.6678886414],"type":"Point"}
}