{
  "type": "Feature",
  "properties": {
    "iso:country":"BE",
    "sg:address":"Rue Du Grand Pr\u00c9 25",
    "sg:city":"Comblain-au-pont",
    "sg:classifiers":[
        {
            "category":"Government",
            "subcategory":"Police Station",
            "type":"Public Place"
        }
    ],
    "sg:phone":"+32 4 369 99 77",
    "sg:postcode":"4170",
    "sg:province":"Li\u00e8ge",
    "sg:tags":[
        "gendarmerie"
    ],
    "wof:name":"Police F\u00c9d\u00c9rale/federale Politie",
    "wof:placetype":"venue"
},
  "geometry": {"coordinates":[5.5807828903,50.4710464478],"type":"Point"}
}