{
  "type": "Feature",
  "properties": {
    "addr:full":"La Falize 4 La Bruy\u00e8re (rhisnes) Namur 5080",
    "addr:housenumber":"4",
    "addr:postcode":"5080",
    "addr:street":"La Falize",
    "iso:country":"BE",
    "sg:address":"La Falize 4",
    "sg:city":"La Bruy\u00e8re (rhisnes)",
    "sg:classifiers":[
        {
            "category":"Government",
            "subcategory":"Post Office",
            "type":"Public Place"
        }
    ],
    "sg:phone":"+32 81 56 85 05",
    "sg:postcode":"5080",
    "sg:province":"Namur",
    "sg:tags":[
        "picture",
        "restoring"
    ],
    "wof:name":"De Baere Ateliers Sprl",
    "wof:placetype":"venue"
},
  "geometry": {"coordinates":[4.804828167,50.5020637512],"type":"Point"}
}