{
  "type": "Feature",
  "properties": {
    "addr:full":"Walstraat 21 Zwijndrecht Antwerpen 2070",
    "addr:housenumber":"21",
    "addr:postcode":"2070",
    "addr:street":"Walstraat",
    "iso:country":"BE",
    "sg:address":"Walstraat 21",
    "sg:city":"Zwijndrecht",
    "sg:orig_category":"Elektrische installaties voor woningen",
    "sg:phone":"+32 3 252 53 07",
    "sg:postcode":"2070",
    "sg:province":"Antwerpen",
    "wof:name":"Gunther Van Holewinckel",
    "wof:placetype":"venue"
},
  "geometry": {"coordinates":[4.3146967888,51.214717865],"type":"Point"}
}