{
  "type": "Feature",
  "properties": {
    "iso:country":"BE",
    "sg:address":"Pater Eudore Devroyestr. 185",
    "sg:city":"Sint-pieters-woluwe/woluwe-saint-pierre",
    "sg:orig_category":"Boekhouders",
    "sg:phone":"+32 2 772 35 75",
    "sg:postcode":"1150",
    "sg:province":"Bruxelles-Capitale",
    "wof:name":"Edouard De Vaucleroy",
    "wof:placetype":"venue"
},
  "geometry": {"coordinates":[4.4101438522,50.8328895569],"type":"Point"}
}