{
  "type": "Feature",
  "properties": {
    "iso:country":"BE",
    "sg:address":"De Ribaucourtdreef 5",
    "sg:city":"Steenokkerzeel",
    "sg:orig_category":"M\u00e9decins and sp\u00e9cialistes",
    "sg:phone":"+32 16 65 13 33",
    "sg:postcode":"1820",
    "sg:province":"Vlaams-Brabant",
    "wof:name":"Anne-marie De Meirsman",
    "wof:placetype":"venue"
},
  "geometry": {"coordinates":[4.5138912201,50.930141449],"type":"Point"}
}