{
  "type": "Feature",
  "properties": {
    "addr:full":"Ballingstraat 15 Kortrijk (bellegem) West-Vlaanderen 8510",
    "addr:housenumber":"15",
    "addr:postcode":"8510",
    "addr:street":"Ballingstraat",
    "iso:country":"BE",
    "sg:address":"Ballingstraat 15",
    "sg:city":"Kortrijk (bellegem)",
    "sg:classifiers":[
        {
            "category":"Retail",
            "subcategory":"Auto Repair",
            "type":"Services"
        }
    ],
    "sg:phone":"+32 56 21 37 83",
    "sg:postcode":"8510",
    "sg:province":"West-Vlaanderen",
    "sg:tags":[
        "automobile-body"
    ],
    "wof:name":"De Keyzer G",
    "wof:placetype":"venue"
},
  "geometry": {"coordinates":[3.3141150475,50.7662315369],"type":"Point"}
}