{
  "type": "Feature",
  "properties": {
    "addr:full":"Grand'route 85b1 Mont-saint-guibert Brabant Wallon 1435",
    "addr:housenumber":"85b1",
    "addr:postcode":"1435",
    "addr:street":"Grand'Route",
    "iso:country":"BE",
    "sg:address":"Grand'route 85b1",
    "sg:city":"Mont-saint-guibert",
    "sg:orig_category":"Herstelling and restauratie van meubelen Stoelen and zitmeubelen Fab",
    "sg:phone":"+32 10 65 80 29",
    "sg:postcode":"1435",
    "sg:province":"Brabant Wallon",
    "wof:name":"Garnitex",
    "wof:placetype":"venue"
},
  "geometry": {"coordinates":[4.6107521057,50.6339874268],"type":"Point"}
}