{
  "type": "Feature",
  "properties": {
    "addr:full":"Heirbrugstraat 301 Lokeren Oost-Vlaanderen 9160",
    "addr:housenumber":"301",
    "addr:postcode":"9160",
    "addr:street":"Heirbrugstraat",
    "iso:country":"BE",
    "sg:address":"Heirbrugstraat 301",
    "sg:city":"Lokeren",
    "sg:orig_category":"Pain, p\u00e2tisseries and confiseries",
    "sg:phone":"+32 9 348 36 29",
    "sg:postcode":"9160",
    "sg:province":"Oost-Vlaanderen",
    "wof:name":"Ronald Huybrecht",
    "wof:placetype":"venue"
},
  "geometry": {"coordinates":[3.9741830826,51.1076278687],"type":"Point"}
}