{
  "type": "Feature",
  "properties": {
    "iso:country":"BE",
    "sg:address":"Quai Aux Pierres De Taille 34",
    "sg:city":"Bruxelles",
    "sg:classifiers":[
        {
            "category":"Banks & Credit Unions",
            "subcategory":"Investment Brokerage",
            "type":"Services"
        }
    ],
    "sg:phone":"+32 2 219 01 12",
    "sg:postcode":"1000",
    "sg:province":"Bruxelles-Capitale",
    "sg:tags":[
        "transfusion",
        "blood"
    ],
    "wof:name":"Centre De Transfusion Sanguine L Steens Asbl",
    "wof:placetype":"venue"
},
  "geometry": {"coordinates":[4.3484201431,50.8552932739],"type":"Point"}
}