{
  "type": "Feature",
  "properties": {
    "iso:country":"BE",
    "sg:address":"Grand-rue 33",
    "sg:city":"Martelange",
    "sg:orig_category":"Enseignement maternel and primaire",
    "sg:phone":"+32 63 60 08 49",
    "sg:postcode":"6630",
    "sg:province":"Luxembourg",
    "wof:name":"Ecole Fondamentale Libre",
    "wof:placetype":"venue"
},
  "geometry": {"coordinates":[5.7383022308,49.8312416077],"type":"Point"}
}