{
  "type": "Feature",
  "properties": {
    "iso:country":"BE",
    "sg:address":"Faubourg De Bruxelles 146c",
    "sg:city":"Charleroi",
    "sg:orig_category":"Passagiersvervoer over de weg Reisbureaus",
    "sg:phone":"+32 71 35 33 15",
    "sg:postcode":"6041",
    "sg:province":"Hainaut",
    "wof:name":"Voyages L'elan",
    "wof:placetype":"venue"
},
  "geometry": {"coordinates":[4.4314317703,50.4685935974],"type":"Point"}
}