{
  "type": "Feature",
  "properties": {
    "iso:country":"BE",
    "sg:address":"Sint-jansstraat 161",
    "sg:city":"Essen",
    "sg:orig_category":"Eleveurs de bovins",
    "sg:phone":"+32 3 677 22 89",
    "sg:postcode":"2910",
    "sg:province":"Antwerpen",
    "wof:name":"Jan Van Looveren",
    "wof:placetype":"venue"
},
  "geometry": {"coordinates":[4.4755568504,51.424331665],"type":"Point"}
}