{
  "type": "Feature",
  "properties": {
    "addr:full":"Place De L'universit\u00e9 3-8 Ottignies-louvain-la-neuve (louvain-la-neuve) Brabant Wallon 1348",
    "addr:housenumber":"3-8",
    "addr:postcode":"1348",
    "addr:street":"Place De L'Universite \u0301",
    "iso:country":"BE",
    "sg:address":"Place De L'universit\u00e9 3-8",
    "sg:city":"Ottignies-louvain-la-neuve (louvain-la-neuve)",
    "sg:classifiers":[
        {
            "category":"Bars & Pubs",
            "type":"Food & Drink"
        }
    ],
    "sg:phone":"+32 10 45 13 10",
    "sg:postcode":"1348",
    "sg:province":"Brabant Wallon",
    "wof:name":"Gambrinus",
    "wof:placetype":"venue"
},
  "geometry": {"coordinates":[4.6156167984,50.6698684692],"type":"Point"}
}