{
  "type": "Feature",
  "properties": {
    "iso:country":"BE",
    "sg:address":"Avenue De Bouillon 11",
    "sg:city":"Libramont-chevigny (libramont)",
    "sg:classifiers":[
        {
            "category":"Building & Trades",
            "subcategory":"Equipment Rental",
            "type":"Services"
        }
    ],
    "sg:phone":"+32 61 22 23 32",
    "sg:postcode":"6800",
    "sg:province":"Luxembourg",
    "sg:tags":[
        "crane",
        "-"
    ],
    "wof:name":"Arnould O-volvo",
    "wof:placetype":"venue"
},
  "geometry": {"coordinates":[5.3762121201,49.9198265076],"type":"Point"}
}