{
  "type": "Feature",
  "properties": {
    "iso:country":"BE",
    "sg:address":"Rue De La Bruy\u00e8re 108",
    "sg:city":"Rixensart (genval)",
    "sg:classifiers":[
        {
            "category":"Professional",
            "subcategory":"Advertising",
            "type":"Services"
        }
    ],
    "sg:phone":"+32 2 652 26 07",
    "sg:postcode":"1332",
    "sg:province":"Brabant Wallon",
    "sg:tags":[
        "telemarketing"
    ],
    "wof:name":"Lassimon & Partners Bvba",
    "wof:placetype":"venue"
},
  "geometry": {"coordinates":[4.4926018715,50.7227554321],"type":"Point"}
}