{
  "type": "Feature",
  "properties": {
    "iso:country":"BE",
    "sg:address":"Rue De L'eglise 4",
    "sg:city":"Gembloux-sur-orneau (gembloux)",
    "sg:classifiers":[
        {
            "category":"Banks & Credit Unions",
            "subcategory":"Bureau De Change",
            "type":"Services"
        }
    ],
    "sg:phone":"+32 81 60 16 43",
    "sg:postcode":"5030",
    "sg:province":"Namur",
    "sg:tags":[
        "regulating",
        "system"
    ],
    "wof:name":"Buelen E",
    "wof:placetype":"venue"
},
  "geometry": {"coordinates":[4.7163519859,50.5484809875],"type":"Point"}
}