{
  "type": "Feature",
  "properties": {
    "addr:full":"Kemmelbergstraat 38 Antwerpen Antwerpen 2600",
    "addr:housenumber":"38",
    "addr:postcode":"2600",
    "addr:street":"Kemmelbergstraat",
    "iso:country":"BE",
    "sg:address":"Kemmelbergstraat 38",
    "sg:city":"Antwerpen",
    "sg:orig_category":"Plaatsen van vloer- and muurbekleding Schilders",
    "sg:phone":"+32 3 230 86 56",
    "sg:postcode":"2600",
    "sg:province":"Antwerpen",
    "wof:name":"Pieter Van Mensel",
    "wof:placetype":"venue"
},
  "geometry": {"coordinates":[4.4174151421,51.1974411011],"type":"Point"}
}