{
  "type": "Feature",
  "properties": {
    "addr:full":"Kazernstraat 48 Zottegem Oost-Vlaanderen 9620",
    "addr:housenumber":"48",
    "addr:postcode":"9620",
    "addr:street":"Kazernstraat",
    "iso:country":"BE",
    "sg:address":"Kazernstraat 48",
    "sg:city":"Zottegem",
    "sg:orig_category":"Industri\u00eble wasserijen and droogkuis Wasserijen, Reiniging and Droogkuis",
    "sg:phone":"+32 9 360 07 71",
    "sg:postcode":"9620",
    "sg:province":"Oost-Vlaanderen",
    "wof:name":"American Shop",
    "wof:placetype":"venue"
},
  "geometry": {"coordinates":[3.8118810654,50.8674087524],"type":"Point"}
}