{
  "type": "Feature",
  "properties": {
    "addr:full":"Place Albert I 2 Thuin Hainaut 6530",
    "addr:housenumber":"2",
    "addr:postcode":"6530",
    "addr:street":"Place Albert I",
    "iso:country":"BE",
    "sg:address":"Place Albert I 2",
    "sg:city":"Thuin",
    "sg:classifiers":[
        {
            "category":"Government",
            "subcategory":"Office",
            "type":"Public Place"
        }
    ],
    "sg:phone":"+32 71 59 54 54",
    "sg:postcode":"6530",
    "sg:province":"Hainaut",
    "sg:tags":[
        "-",
        "tourism",
        "federation"
    ],
    "wof:name":"Office Tourisme De Thuin Asbl",
    "wof:placetype":"venue"
},
  "geometry": {"coordinates":[4.286719799,50.3396530151],"type":"Point"}
}