{
  "type": "Feature",
  "properties": {
    "iso:country":"BE",
    "sg:address":"Rue Joseph Wauters 49",
    "sg:city":"Erquelinnes (grand-reng)",
    "sg:classifiers":[
        {
            "category":"Health Services",
            "subcategory":"Health Practitioner",
            "type":"Services"
        }
    ],
    "sg:phone":"+32 64 77 14 90",
    "sg:postcode":"6560",
    "sg:province":"Hainaut",
    "sg:tags":[
        "physiotherapist"
    ],
    "wof:name":"Beukens S",
    "wof:placetype":"venue"
},
  "geometry": {"coordinates":[4.0723509789,50.325969696],"type":"Point"}
}