{
  "type": "Feature",
  "properties": {
    "iso:country":"BE",
    "sg:address":"Rue De L'etoile 6",
    "sg:city":"Morlanwelz (morlanwelz-mariemont)",
    "sg:classifiers":[
        {
            "category":"Professional",
            "subcategory":"Accounting & Tax Preparation",
            "type":"Services"
        }
    ],
    "sg:phone":"+32 64 46 04 45",
    "sg:postcode":"7140",
    "sg:province":"Hainaut",
    "sg:tags":[
        "bookkeeper"
    ],
    "wof:name":"Informatique Et Gestion Sc",
    "wof:placetype":"venue"
},
  "geometry": {"coordinates":[4.2578821182,50.4677085876],"type":"Point"}
}