{
  "type": "Feature",
  "properties": {
    "iso:country":"BE",
    "sg:address":"Rue De Bienne 29",
    "sg:city":"Buvrinnes",
    "sg:classifiers":[
        {
            "category":"Health Services",
            "subcategory":"Hospital",
            "type":"Services"
        }
    ],
    "sg:phone":"+32 71 55 55 55",
    "sg:postcode":"7133",
    "sg:province":"Hainaut",
    "sg:tags":[
        "ambulance"
    ],
    "wof:name":"Hainaut Samu",
    "wof:placetype":"venue"
},
  "geometry": {"coordinates":[4.1816248894,50.3790893555],"type":"Point"}
}