{
  "type": "Feature",
  "properties": {
    "iso:country":"BE",
    "sg:address":"Edmond Van Hoofstraat 12",
    "sg:city":"Mol",
    "sg:classifiers":[
        {
            "category":"Health Services",
            "subcategory":"Dentist",
            "type":"Services"
        }
    ],
    "sg:phone":"+32 14 32 65 18",
    "sg:postcode":"2400",
    "sg:province":"Antwerpen",
    "wof:name":"Swinnen K Mevr",
    "wof:placetype":"venue"
},
  "geometry": {"coordinates":[5.1158561707,51.1856765747],"type":"Point"}
}