{
  "type": "Feature",
  "properties": {
    "addr:full":"Rue Du Moulin Paradis 2 Mons (ghlin) Hainaut 7011",
    "addr:housenumber":"2",
    "addr:postcode":"7011",
    "addr:street":"Rue Du Moulin Paradis",
    "iso:country":"BE",
    "sg:address":"Rue Du Moulin Paradis 2",
    "sg:city":"Mons (ghlin)",
    "sg:classifiers":[
        {
            "category":"Real Estate",
            "subcategory":"Surveying",
            "type":"Services"
        }
    ],
    "sg:phone":"+32 65 35 28 03",
    "sg:postcode":"7011",
    "sg:province":"Hainaut",
    "sg:tags":[
        "surveyor",
        "land"
    ],
    "wof:name":"Van Derton B",
    "wof:placetype":"venue"
},
  "geometry": {"coordinates":[3.912539959,50.4712982178],"type":"Point"}
}