{
  "type": "Feature",
  "properties": {
    "iso:country":"BE",
    "sg:address":"Meensesteenweg 420",
    "sg:city":"Roeselare",
    "sg:orig_category":"Epiceries. Fruits and l\u00e9gumes",
    "sg:phone":"+32 51 20 56 84",
    "sg:postcode":"8800",
    "sg:province":"West-Vlaanderen",
    "wof:name":"Zelfbediening Rita",
    "wof:placetype":"venue"
},
  "geometry": {"coordinates":[3.1169230938,50.9205055237],"type":"Point"}
}