{
  "type": "Feature",
  "properties": {
    "addr:full":"Rue Du March\u00e9-au-beurre 15 Arlon Luxembourg 6700",
    "addr:housenumber":"15",
    "addr:postcode":"6700",
    "addr:street":"Rue Du Marche\u0301-Au-Beurre",
    "iso:country":"BE",
    "sg:address":"Rue Du March\u00e9-au-beurre 15",
    "sg:city":"Arlon",
    "sg:classifiers":[
        {
            "category":"Place Of Worship",
            "subcategory":"Church",
            "type":"Public Place"
        }
    ],
    "sg:phone":"+32 63 23 31 31",
    "sg:postcode":"6700",
    "sg:province":"Luxembourg",
    "sg:tags":[
        "article",
        "baptismal"
    ],
    "wof:name":"Palais D'ang\u00e9line (le)",
    "wof:placetype":"venue"
},
  "geometry": {"coordinates":[5.815308094,49.683467865],"type":"Point"}
}