{
  "type": "Feature",
  "properties": {
    "addr:full":"Donk 45 Oud-turnhout Antwerpen 2360",
    "addr:housenumber":"45",
    "addr:postcode":"2360",
    "addr:street":"Donk",
    "iso:country":"BE",
    "sg:address":"Donk 45",
    "sg:city":"Oud-turnhout",
    "sg:classifiers":[
        {
            "category":"Cafe",
            "type":"Food & Drink"
        }
    ],
    "sg:phone":"+32 14 45 06 06",
    "sg:postcode":"2360",
    "sg:province":"Antwerpen",
    "sg:tags":[
        "caf\u00e9s"
    ],
    "wof:name":"I.m.n.",
    "wof:placetype":"venue"
},
  "geometry": {"coordinates":[4.982629776,51.3177986145],"type":"Point"}
}