{
  "type": "Feature",
  "properties": {
    "addr:full":"Louizastraat 34 Mechelen Antwerpen 2800",
    "addr:housenumber":"34",
    "addr:postcode":"2800",
    "addr:street":"Louizastraat",
    "iso:country":"BE",
    "sg:address":"Louizastraat 34",
    "sg:city":"Mechelen",
    "sg:classifiers":[
        {
            "category":"Health Services",
            "subcategory":"Doctor",
            "type":"Services"
        }
    ],
    "sg:phone":"+32 15 41 55 89",
    "sg:postcode":"2800",
    "sg:province":"Antwerpen",
    "sg:tags":[
        "medicinephysicians",
        "surgeon"
    ],
    "wof:name":"Daems L",
    "wof:placetype":"venue"
},
  "geometry": {"coordinates":[4.4774031639,51.0214385986],"type":"Point"}
}