{
  "type": "Feature",
  "properties": {
    "iso:country":"BE",
    "sg:address":"Itali\u00eblei 2",
    "sg:city":"Antwerpen",
    "sg:classifiers":[
        {
            "category":"Harbor",
            "type":"Transportation"
        }
    ],
    "sg:phone":"+32 3 205 23 22",
    "sg:postcode":"2000",
    "sg:province":"Antwerpen",
    "sg:tags":[
        "port",
        "facility"
    ],
    "wof:name":"Apec-antwerp/flanders Port Training Center Vzw",
    "wof:placetype":"venue"
},
  "geometry": {"coordinates":[4.4126749039,51.2299003601],"type":"Point"}
}