{
  "type": "Feature",
  "properties": {
    "iso:country":"BE",
    "sg:address":"Ninoofsesteenweg 11",
    "sg:city":"Dilbeek",
    "sg:orig_category":"Benzinestations and brandstoffen",
    "sg:phone":"+32 2 466 21 32",
    "sg:postcode":"1700",
    "sg:province":"Vlaams-Brabant",
    "wof:name":"Jet",
    "wof:placetype":"venue"
},
  "geometry": {"coordinates":[4.2785201073,50.8451881409],"type":"Point"}
}