{
  "type": "Feature",
  "properties": {
    "addr:full":"Guido Gezellestraat 1 Ichtegem West-Vlaanderen 8480",
    "addr:housenumber":"1",
    "addr:postcode":"8480",
    "addr:street":"Guido Gezellestraat",
    "iso:country":"BE",
    "sg:address":"Guido Gezellestraat 1",
    "sg:city":"Ichtegem",
    "sg:orig_category":"Plaatsen van vloer- and muurbekleding Vloer- and muurbekleding",
    "sg:phone":"+32 59 29 06 15",
    "sg:postcode":"8480",
    "sg:province":"West-Vlaanderen",
    "wof:name":"Bouwwerken Strubbe Rik",
    "wof:placetype":"venue"
},
  "geometry": {"coordinates":[3.013078928,51.1269760132],"type":"Point"}
}