{
  "type": "Feature",
  "properties": {
    "iso:country":"BE",
    "sg:address":"Beernemstraat 21",
    "sg:city":"Wingene",
    "sg:orig_category":"Installatie van houten of kunststof schrijnwerk MEUBELONTWERP AND -INSTALLATIE",
    "sg:phone":"+32 51 65 60 27",
    "sg:postcode":"8750",
    "sg:province":"West-Vlaanderen",
    "wof:name":"Gero Keukens",
    "wof:placetype":"venue"
},
  "geometry": {"coordinates":[3.2757730484,51.0602416992],"type":"Point"}
}