{
  "type": "Feature",
  "properties": {
    "iso:country":"BE",
    "sg:address":"Roeselarestraat 31",
    "sg:city":"Hooglede",
    "sg:orig_category":"Voedingsspeciaalzaken",
    "sg:phone":"+32 51 22 20 29",
    "sg:postcode":"8830",
    "sg:province":"West-Vlaanderen",
    "wof:name":"De Komboe-cha",
    "wof:placetype":"venue"
},
  "geometry": {"coordinates":[3.0838990211,50.9766273499],"type":"Point"}
}