{
  "type": "Feature",
  "properties": {
    "addr:full":"Rue Limnander 20 Bruxelles (anderlecht) Bruxelles-Capitale 1070",
    "addr:housenumber":"20",
    "addr:postcode":"1070",
    "addr:street":"Rue Limnander",
    "iso:country":"BE",
    "sg:address":"Rue Limnander 20",
    "sg:city":"Bruxelles (anderlecht)",
    "sg:orig_category":"Non-Classified Establishments",
    "sg:phone":"+32 2 520 42 07",
    "sg:postcode":"1070",
    "sg:province":"Bruxelles-Capitale",
    "wof:name":"S.b.f. Sprl",
    "wof:placetype":"venue"
},
  "geometry": {"coordinates":[4.3368010521,50.8400611877],"type":"Point"}
}