{
  "type": "Feature",
  "properties": {
    "iso:country":"BE",
    "sg:address":"Alfred Cluysenaarstraat 24",
    "sg:city":"Sint-gillis/saint-gilles",
    "sg:orig_category":"Diverse grafische activiteiten",
    "sg:phone":"+32 2 538 34 25",
    "sg:postcode":"1060",
    "sg:province":"Bruxelles-Capitale",
    "wof:name":"Dominique Goor",
    "wof:placetype":"venue"
},
  "geometry": {"coordinates":[4.3419218063,50.8249473572],"type":"Point"}
}