{
  "type": "Feature",
  "properties": {
    "iso:country":"BE",
    "sg:address":"Grintweg 32bb",
    "sg:city":"Oostkamp",
    "sg:orig_category":"Installation \u00e9lectrique r\u00e9sidentielle",
    "sg:phone":"+32 59 26 79 68",
    "sg:postcode":"8400",
    "sg:province":"West-Vlaanderen",
    "wof:name":"Electro Vantyghem",
    "wof:placetype":"venue"
},
  "geometry": {"coordinates":[2.9126999378,51.2312583923],"type":"Point"}
}