{
  "type": "Feature",
  "properties": {
    "iso:country":"BE",
    "sg:address":"Schoendalestraat 221",
    "sg:city":"Sint-eloois-vijve",
    "sg:classifiers":[
        {
            "category":"Wholesale",
            "subcategory":"Tobacco Products",
            "type":"Manufacturing & Wholesale Goods"
        }
    ],
    "sg:phone":"+32 56 62 27 00",
    "sg:postcode":"8793",
    "sg:province":"West-Vlaanderen",
    "sg:tags":[
        "potato"
    ],
    "wof:name":"Primeur Nv",
    "wof:placetype":"venue"
},
  "geometry": {"coordinates":[3.3852899075,50.8964576721],"type":"Point"}
}