{
  "type": "Feature",
  "properties": {
    "addr:full":"Bekstraat 6 Oudenaarde Oost-Vlaanderen 9700",
    "addr:housenumber":"6",
    "addr:postcode":"9700",
    "addr:street":"Bekstraat",
    "iso:country":"BE",
    "sg:address":"Bekstraat 6",
    "sg:city":"Oudenaarde",
    "sg:orig_category":"Koerierbedrijven",
    "sg:phone":"+32 55 30 17 87",
    "sg:postcode":"9700",
    "sg:province":"Oost-Vlaanderen",
    "wof:name":"Taxipost-e.m.s.",
    "wof:placetype":"venue"
},
  "geometry": {"coordinates":[3.6032669544,50.8813018799],"type":"Point"}
}