{
  "type": "Feature",
  "properties": {
    "addr:full":"Hochstrasse 143 Eupen/eupen Li\u00e8ge 4700",
    "addr:housenumber":"143",
    "addr:postcode":"4700",
    "addr:street":"Hochstrasse",
    "iso:country":"BE",
    "sg:address":"Hochstrasse 143",
    "sg:city":"Eupen/eupen",
    "sg:orig_category":"Sportclubs",
    "sg:phone":"+32 87 74 00 88",
    "sg:postcode":"4700",
    "sg:province":"Li\u00e8ge",
    "wof:name":"L.a.c. Eupen",
    "wof:placetype":"venue"
},
  "geometry": {"coordinates":[6.0227241516,50.6418876648],"type":"Point"}
}