{
  "type": "Feature",
  "properties": {
    "addr:full":"Chauss\u00e9e De Ch\u00e2telet 93 Charleroi (gilly) Hainaut 6060",
    "addr:housenumber":"93",
    "addr:postcode":"6060",
    "addr:street":"Chausse\u0301E De Cha\u0302Telet",
    "iso:country":"BE",
    "sg:address":"Chauss\u00e9e De Ch\u00e2telet 93",
    "sg:city":"Charleroi (gilly)",
    "sg:classifiers":[
        {
            "category":"Professional",
            "subcategory":"Art Services",
            "type":"Services"
        }
    ],
    "sg:phone":"+32 71 41 67 48",
    "sg:postcode":"6060",
    "sg:province":"Hainaut",
    "sg:tags":[
        "realization",
        "audio-visual"
    ],
    "wof:name":"Comsat",
    "wof:placetype":"venue"
},
  "geometry": {"coordinates":[4.4880981445,50.4251937866],"type":"Point"}
}