{
  "type": "Feature",
  "properties": {
    "addr:full":"Rue Albert I 14 Gerpinnes Hainaut 6280",
    "addr:housenumber":"14",
    "addr:postcode":"6280",
    "addr:street":"Rue Albert I;Hainaut",
    "iso:country":"BE",
    "sg:address":"Rue Albert I 14",
    "sg:city":"Gerpinnes",
    "sg:classifiers":[
        {
            "category":"Bars & Pubs",
            "type":"Food & Drink"
        }
    ],
    "sg:phone":"+32 71 50 14 41",
    "sg:postcode":"6280",
    "sg:province":"Hainaut",
    "wof:name":"Destrucguepes",
    "wof:placetype":"venue"
},
  "geometry": {"coordinates":[4.5286870003,50.3354110718],"type":"Point"}
}