{
  "type": "Feature",
  "properties": {
    "iso:country":"BE",
    "sg:address":"Bredastraat 72-78",
    "sg:city":"Antwerpen",
    "sg:classifiers":[
        {
            "category":"Home & Garden",
            "subcategory":"Carpets & Floor Coverings",
            "type":"Retail Goods"
        }
    ],
    "sg:phone":"+32 3 232 79 88",
    "sg:postcode":"2060",
    "sg:province":"Antwerpen",
    "sg:tags":[
        "tile"
    ],
    "wof:name":"Merksemse Tegelhallen Bvba",
    "wof:placetype":"venue"
},
  "geometry": {"coordinates":[4.4228110313,51.2335472107],"type":"Point"}
}