{
  "type": "Feature",
  "properties": {
    "iso:country":"BE",
    "sg:address":"Brugsesteenweg 584",
    "sg:city":"Roeselare",
    "sg:orig_category":"Entretien and r\u00e9parations de voitures",
    "sg:phone":"+32 51 24 72 48",
    "sg:postcode":"8800",
    "sg:province":"West-Vlaanderen",
    "wof:name":"Auto-wash 't Rondpunt",
    "wof:placetype":"venue"
},
  "geometry": {"coordinates":[3.1191909313,50.9768829346],"type":"Point"}
}