{
  "type": "Feature",
  "properties": {
    "addr:full":"Rue Colonel Bourg 118 Evere Bruxelles-Capitale 1140",
    "addr:housenumber":"118",
    "addr:postcode":"1140",
    "addr:street":"Rue Colonel Bourg",
    "iso:country":"BE",
    "sg:address":"Rue Colonel Bourg 118",
    "sg:city":"Evere",
    "sg:orig_category":"Auto-\u00e9coles. Contr\u00f4le technique automobile",
    "sg:phone":"+32 2 726 91 52",
    "sg:postcode":"1140",
    "sg:province":"Bruxelles-Capitale",
    "wof:name":"Contr\u00d4le Technique Automobile",
    "wof:placetype":"venue"
},
  "geometry": {"coordinates":[4.412648201,50.8538627625],"type":"Point"}
}