{
  "type": "Feature",
  "properties": {
    "addr:full":"Sint-gerolflaan 1 Box 3a Aalter Oost-Vlaanderen 9880",
    "addr:housenumber":"1",
    "addr:postcode":"9880",
    "addr:street":"Sint-Gerolflaan;Box 3A",
    "iso:country":"BE",
    "sg:address":"Sint-gerolflaan 1 Box 3a",
    "sg:city":"Aalter",
    "sg:classifiers":[
        {
            "category":"Building & Trades",
            "subcategory":"Landscaping Services",
            "type":"Services"
        }
    ],
    "sg:phone":"+32 9 375 29 30",
    "sg:postcode":"9880",
    "sg:province":"Oost-Vlaanderen",
    "sg:tags":[
        "architect",
        "landscape"
    ],
    "wof:name":"Van De Cotte F",
    "wof:placetype":"venue"
},
  "geometry": {"coordinates":[3.4482300282,51.0872917175],"type":"Point"}
}