{
  "type": "Feature",
  "properties": {
    "iso:country":"BE",
    "sg:address":"De Vloot 6",
    "sg:city":"Houthalen-helchteren",
    "sg:orig_category":"Slagers",
    "sg:phone":"+32 11 60 24 86",
    "sg:postcode":"3530",
    "sg:province":"Limburg",
    "wof:name":"Budgetslager",
    "wof:placetype":"venue"
},
  "geometry": {"coordinates":[5.3747267723,51.0217552185],"type":"Point"}
}