{
  "type": "Feature",
  "properties": {
    "iso:country":"BE",
    "sg:address":"Rue Hemricourt 11",
    "sg:city":"Li\u00c8ge",
    "sg:orig_category":"Advocaten and juridische adviseurs",
    "sg:phone":"+32 4 252 00 60",
    "sg:postcode":"4000",
    "sg:province":"Li\u00e8ge",
    "wof:name":"S. Zenobi",
    "wof:placetype":"venue"
},
  "geometry": {"coordinates":[5.564496994,50.631275177],"type":"Point"}
}