{
  "type": "Feature",
  "properties": {
    "addr:full":"Rue De Givet 21 Beauraing Namur 5570",
    "addr:housenumber":"21",
    "addr:postcode":"5570",
    "addr:street":"Rue De Givet",
    "iso:country":"BE",
    "sg:address":"Rue De Givet 21",
    "sg:city":"Beauraing",
    "sg:orig_category":"Algemeen secundair onderwijs Technisch and beroeps secundair onderwijs",
    "sg:phone":"+32 82 71 12 76",
    "sg:postcode":"5570",
    "sg:province":"Namur",
    "wof:name":"Institut Notre-dame",
    "wof:placetype":"venue"
},
  "geometry": {"coordinates":[4.9538750648,50.1108207703],"type":"Point"}
}