{
  "type": "Feature",
  "properties": {
    "iso:country":"BE",
    "sg:address":"Bieststraat 191",
    "sg:city":"Boortmeerbeek (hever)",
    "sg:classifiers":[
        {
            "category":"Food & Beverages",
            "subcategory":"Specialty",
            "type":"Retail Goods"
        }
    ],
    "sg:phone":"+32 15 62 06 30",
    "sg:postcode":"3191",
    "sg:province":"Vlaams-Brabant",
    "sg:tags":[
        "sinking",
        "groundwater"
    ],
    "wof:name":"De Venter I",
    "wof:placetype":"venue"
},
  "geometry": {"coordinates":[4.5490899086,50.9831085205],"type":"Point"}
}