{
  "type": "Feature",
  "properties": {
    "iso:country":"BE",
    "sg:address":"Brankardierstraat 46",
    "sg:city":"Gent",
    "sg:orig_category":"Gespecialiseerde residenti\u00eble bouw",
    "sg:phone":"+32 9 225 36 64",
    "sg:postcode":"9000",
    "sg:province":"Oost-Vlaanderen",
    "wof:name":"De Block M",
    "wof:placetype":"venue"
},
  "geometry": {"coordinates":[3.7044808865,51.0520095825],"type":"Point"}
}