{
  "type": "Feature",
  "properties": {
    "iso:country":"BE",
    "sg:address":"Sterstraat 33",
    "sg:city":"Lommel",
    "sg:orig_category":"G\u00e9om\u00e8tres",
    "sg:phone":"+32 11 54 29 54",
    "sg:postcode":"3920",
    "sg:province":"Limburg",
    "wof:name":"Jean-pierre Hamblok",
    "wof:placetype":"venue"
},
  "geometry": {"coordinates":[5.295153141,51.231212616],"type":"Point"}
}