{
  "type": "Feature",
  "properties": {
    "iso:country":"BE",
    "sg:address":"De Merodedreef 21",
    "sg:city":"Westerlo",
    "sg:classifiers":[
        {
            "category":"Cafe",
            "type":"Food & Drink"
        }
    ],
    "sg:phone":"+32 14 54 51 02",
    "sg:postcode":"2260",
    "sg:province":"Antwerpen",
    "sg:tags":[
        "caf\u00e9s"
    ],
    "wof:name":"West-invest",
    "wof:placetype":"venue"
},
  "geometry": {"coordinates":[4.9123220444,51.083240509],"type":"Point"}
}