{
  "type": "Feature",
  "properties": {
    "iso:country":"BE",
    "sg:address":"Avenue De L'opale 69",
    "sg:city":"Schaarbeek/schaerbeek",
    "sg:orig_category":"Architectes",
    "sg:phone":"+32 2 736 19 39",
    "sg:postcode":"1030",
    "sg:province":"Bruxelles-Capitale",
    "wof:name":"Van Moorsel",
    "wof:placetype":"venue"
},
  "geometry": {"coordinates":[4.3978190422,50.8490104675],"type":"Point"}
}