{
  "type": "Feature",
  "properties": {
    "iso:country":"BE",
    "sg:address":"Rue Hawis 37",
    "sg:city":"Soumagne",
    "sg:classifiers":[
        {
            "category":"Health Services",
            "subcategory":"Health Practitioner",
            "type":"Services"
        }
    ],
    "sg:phone":"+32 4 377 28 71",
    "sg:postcode":"4630",
    "sg:province":"Li\u00e8ge",
    "sg:tags":[
        "physiotherapist"
    ],
    "wof:name":"Colleye C",
    "wof:placetype":"venue"
},
  "geometry": {"coordinates":[5.7284350395,50.6185646057],"type":"Point"}
}