{
  "type": "Feature",
  "properties": {
    "addr:full":"Haagstraat 38a Beveren (vrasene) Oost-Vlaanderen 9120",
    "addr:housenumber":"38a",
    "addr:postcode":"9120",
    "addr:street":"Haagstraat",
    "iso:country":"BE",
    "sg:address":"Haagstraat 38a",
    "sg:city":"Beveren (vrasene)",
    "sg:classifiers":[
        {
            "category":"Building & Trades",
            "subcategory":"Electrical",
            "type":"Services"
        }
    ],
    "sg:phone":"+32 3 296 76 11",
    "sg:postcode":"9120",
    "sg:province":"Oost-Vlaanderen",
    "sg:tags":[
        "electric",
        "-",
        "housewiring",
        "contractor"
    ],
    "wof:name":"Doffijn W Elektriciteitswerken",
    "wof:placetype":"venue"
},
  "geometry": {"coordinates":[4.1863517761,51.2232551575],"type":"Point"}
}