{
  "type": "Feature",
  "properties": {
    "iso:country":"BE",
    "sg:address":"Schuiteplasstraat 59",
    "sg:city":"Dendermonde (schoonaarde)",
    "sg:classifiers":[
        {
            "category":"Utilities",
            "subcategory":"Fuel Oil & Lpg",
            "type":"Services"
        }
    ],
    "sg:phone":"+32 52 42 33 92",
    "sg:postcode":"9200",
    "sg:province":"Oost-Vlaanderen",
    "wof:name":"Govaert P",
    "wof:placetype":"venue"
},
  "geometry": {"coordinates":[4.0214400291,50.995464325],"type":"Point"}
}