{
  "type": "Feature",
  "properties": {
    "addr:full":"Izegemseaardeweg 159a Roeselare West-Vlaanderen 8800",
    "addr:housenumber":"159a",
    "addr:postcode":"8800",
    "addr:street":"Izegemseaardeweg",
    "iso:country":"BE",
    "sg:address":"Izegemseaardeweg 159a",
    "sg:city":"Roeselare",
    "sg:classifiers":[
        {
            "category":"Food & Beverages",
            "subcategory":"Meat & Fish",
            "type":"Retail Goods"
        }
    ],
    "sg:phone":"+32 51 24 89 72",
    "sg:postcode":"8800",
    "sg:province":"West-Vlaanderen",
    "sg:tags":[
        "poultry",
        "whol",
        "game",
        "-"
    ],
    "wof:name":"Noppe N",
    "wof:placetype":"venue"
},
  "geometry": {"coordinates":[3.1564519405,50.9583320618],"type":"Point"}
}