{
  "type": "Feature",
  "properties": {
    "iso:country":"BE",
    "sg:address":"Moleneind 13",
    "sg:city":"Wuustwezel",
    "sg:orig_category":"Rundveehouders",
    "sg:phone":"+32 3 669 63 39",
    "sg:postcode":"2990",
    "sg:province":"Antwerpen",
    "wof:name":"Leo Raats",
    "wof:placetype":"venue"
},
  "geometry": {"coordinates":[4.580083847,51.4018630981],"type":"Point"}
}