{
  "type": "Feature",
  "properties": {
    "iso:country":"BE",
    "sg:address":"Chauss\u00e9e Des Collines 54",
    "sg:city":"Wavre",
    "sg:classifiers":[
        {
            "category":"Science Facility",
            "type":"Public Place"
        }
    ],
    "sg:phone":"+32 10 23 73 11",
    "sg:postcode":"1300",
    "sg:province":"Brabant Wallon",
    "sg:tags":[
        "-",
        "management",
        "data",
        "processing"
    ],
    "wof:name":"Gfi Benelux",
    "wof:placetype":"venue"
},
  "geometry": {"coordinates":[4.5872402191,50.7315864563],"type":"Point"}
}