{
  "type": "Feature",
  "properties": {
    "iso:country":"BE",
    "sg:address":"Rue Fontaine-gilles 109",
    "sg:city":"Florennes",
    "sg:orig_category":"Sportclubs Sportterreinen and installaties behalve sportcentra",
    "sg:phone":"+32 71 68 11 37",
    "sg:postcode":"5620",
    "sg:province":"Namur",
    "wof:name":"Florennes World Team",
    "wof:placetype":"venue"
},
  "geometry": {"coordinates":[4.5759248734,50.2474021912],"type":"Point"}
}