{
  "type": "Feature",
  "properties": {
    "addr:full":"Kloosterstraat 21 Bornem Antwerpen 2880",
    "addr:housenumber":"21",
    "addr:postcode":"2880",
    "addr:street":"Kloosterstraat",
    "iso:country":"BE",
    "sg:address":"Kloosterstraat 21",
    "sg:city":"Bornem",
    "sg:classifiers":[
        {
            "category":"Food & Beverages",
            "subcategory":"Fruits & Vegetables",
            "type":"Retail Goods"
        }
    ],
    "sg:phone":"+32 3 889 59 10",
    "sg:postcode":"2880",
    "sg:province":"Antwerpen",
    "sg:tags":[
        "l\u00e9gumes"
    ],
    "wof:name":"Dirk Van Oost",
    "wof:placetype":"venue"
},
  "geometry": {"coordinates":[4.2314090729,51.0958862305],"type":"Point"}
}