{
  "type": "Feature",
  "properties": {
    "addr:full":"Tervatestraat 6 Etterbeek/etterbeek Bruxelles-Capitale 1040",
    "addr:housenumber":"6",
    "addr:postcode":"1040",
    "addr:street":"Tervatestraat",
    "iso:country":"BE",
    "sg:address":"Tervatestraat 6",
    "sg:city":"Etterbeek/etterbeek",
    "sg:orig_category":"Maatkleding Fab",
    "sg:phone":"+32 2 736 89 05",
    "sg:postcode":"1040",
    "sg:province":"Bruxelles-Capitale",
    "wof:name":"Acar Verjin",
    "wof:placetype":"venue"
},
  "geometry": {"coordinates":[4.3995370865,50.8320808411],"type":"Point"}
}