{
  "type": "Feature",
  "properties": {
    "iso:country":"BE",
    "sg:address":"Oostkaai 18",
    "sg:city":"Menen",
    "sg:classifiers":[
        {
            "category":"Home & Garden",
            "subcategory":"Garden Supply",
            "type":"Retail Goods"
        }
    ],
    "sg:phone":"+32 56 51 98 20",
    "sg:postcode":"8930",
    "sg:province":"West-Vlaanderen",
    "wof:name":"Fournier Vijver Center Nv",
    "wof:placetype":"venue"
},
  "geometry": {"coordinates":[3.1276988983,50.7910346985],"type":"Point"}
}