{
  "type": "Feature",
  "properties": {
    "addr:full":"Rue Longue Haie 20 Herve Li\u00e8ge 4650",
    "addr:housenumber":"20",
    "addr:postcode":"4650",
    "addr:street":"Rue Longue Haie",
    "iso:country":"BE",
    "sg:address":"Rue Longue Haie 20",
    "sg:city":"Herve",
    "sg:orig_category":"Mat\u00e9riel m\u00e9dical and orthop\u00e9dique and proth\u00e8ses Fab",
    "sg:phone":"+32 87 33 58 17",
    "sg:postcode":"4650",
    "sg:province":"Li\u00e8ge",
    "wof:name":"Michelle Masson",
    "wof:placetype":"venue"
},
  "geometry": {"coordinates":[5.8070969582,50.6043052673],"type":"Point"}
}