{
  "type": "Feature",
  "properties": {
    "iso:country":"BE",
    "sg:address":"Rue Bris\u00e9e 218",
    "sg:city":"Mons (obourg)",
    "sg:classifiers":[
        {
            "category":"Education",
            "subcategory":"School",
            "type":"Public Place"
        }
    ],
    "sg:phone":"+32 65 72 83 33",
    "sg:postcode":"7034",
    "sg:province":"Hainaut",
    "sg:tags":[
        "-",
        "private"
    ],
    "wof:name":"Tomatis-belge Asbl",
    "wof:placetype":"venue"
},
  "geometry": {"coordinates":[4.0086159706,50.4765396118],"type":"Point"}
}