{
  "type": "Feature",
  "properties": {
    "addr:full":"Dorpsplein 13 Herent (veltem-beisem) Vlaams-Brabant 3020",
    "addr:housenumber":"13",
    "addr:postcode":"3020",
    "addr:street":"Dorpsplein",
    "iso:country":"BE",
    "sg:address":"Dorpsplein 13",
    "sg:city":"Herent (veltem-beisem)",
    "sg:classifiers":[
        {
            "category":"Bakery",
            "type":"Food & Drink"
        }
    ],
    "sg:phone":"+32 16 48 82 16",
    "sg:postcode":"3020",
    "sg:province":"Vlaams-Brabant",
    "sg:tags":[
        "confectioner",
        "baker"
    ],
    "wof:name":"Lonnoy J C",
    "wof:placetype":"venue"
},
  "geometry": {"coordinates":[4.6749200821,50.9079055786],"type":"Point"}
}