{
  "type": "Feature",
  "properties": {
    "addr:full":"Rue De La Station 38-40 Ans Li\u00e8ge 4430",
    "addr:postcode":"38-40;4430",
    "addr:street":"Rue De La Station",
    "iso:country":"BE",
    "sg:address":"Rue De La Station 38-40",
    "sg:city":"Ans",
    "sg:orig_category":"Restaurants Zuivelproducten",
    "sg:phone":"+32 4 263 63 03",
    "sg:postcode":"4430",
    "sg:province":"Li\u00e8ge",
    "wof:name":"Tutti Frutti",
    "wof:placetype":"venue"
},
  "geometry": {"coordinates":[5.5104379654,50.6627235413],"type":"Point"}
}