{
  "type": "Feature",
  "properties": {
    "iso:country":"BE",
    "sg:address":"Oudstrijdersstraat 20",
    "sg:city":"Knokke-heist",
    "sg:orig_category":"Loodgieterij, verwarming and sanitaire installaties",
    "sg:phone":"+32 50 51 55 70",
    "sg:postcode":"8301",
    "sg:province":"West-Vlaanderen",
    "wof:name":"Herman De Prince",
    "wof:placetype":"venue"
},
  "geometry": {"coordinates":[3.2639000416,51.3396911621],"type":"Point"}
}