{
  "type": "Feature",
  "properties": {
    "iso:country":"BE",
    "sg:address":"Vrijheidstraat 94",
    "sg:city":"Oostende",
    "sg:orig_category":"Oldtimers",
    "sg:phone":"+32 59 80 59 55",
    "sg:postcode":"8400",
    "sg:province":"West-Vlaanderen",
    "wof:name":"American Prestige Cars",
    "wof:placetype":"venue"
},
  "geometry": {"coordinates":[2.9050490856,51.2134017944],"type":"Point"}
}