{
  "type": "Feature",
  "properties": {
    "addr:full":"Zandvoordestraat 35 Oostende West-Vlaanderen 8400",
    "addr:housenumber":"35",
    "addr:postcode":"8400",
    "addr:street":"Zandvoordestraat",
    "iso:country":"BE",
    "sg:address":"Zandvoordestraat 35",
    "sg:city":"Oostende",
    "sg:classifiers":[
        {
            "category":"Home & Garden",
            "subcategory":"Building Materials",
            "type":"Retail Goods"
        }
    ],
    "sg:phone":"+32 59 50 51 43",
    "sg:postcode":"8400",
    "sg:province":"West-Vlaanderen",
    "sg:tags":[
        "window"
    ],
    "wof:name":"De Bruycker Hugo",
    "wof:placetype":"venue"
},
  "geometry": {"coordinates":[2.9375450611,51.2165184021],"type":"Point"}
}