{
  "type": "Feature",
  "properties": {
    "iso:country":"BE",
    "sg:address":"De Villegas Clercampstr. 178",
    "sg:city":"Grimbergen",
    "sg:orig_category":"Entretien and r\u00e9parations de voitures",
    "sg:phone":"+32 2 267 83 63",
    "sg:postcode":"1853",
    "sg:province":"Vlaams-Brabant",
    "wof:name":"Soft Car",
    "wof:placetype":"venue"
},
  "geometry": {"coordinates":[4.346473217,50.9088745117],"type":"Point"}
}