{
  "type": "Feature",
  "properties": {
    "iso:country":"BE",
    "sg:address":"Bosdel 46",
    "sg:city":"Genk",
    "sg:classifiers":[
        {
            "category":"Home & Garden",
            "subcategory":"Building Materials",
            "type":"Retail Goods"
        }
    ],
    "sg:phone":"+32 89 35 29 22",
    "sg:postcode":"3600",
    "sg:province":"Limburg",
    "sg:tags":[
        "granite",
        "stone",
        "natural",
        "marble"
    ],
    "wof:name":"Genker Natuursteenbedrijf Gregoor",
    "wof:placetype":"venue"
},
  "geometry": {"coordinates":[5.4795742035,50.9512634277],"type":"Point"}
}