{
  "type": "Feature",
  "properties": {
    "addr:full":"Quai March\u00c9 Au Poisson 22 Tournai Hainaut 7500",
    "addr:housenumber":"22",
    "addr:postcode":"7500",
    "addr:street":"Quai Marche\u0301 Au Poisson",
    "iso:country":"BE",
    "sg:address":"Quai March\u00c9 Au Poisson 22",
    "sg:city":"Tournai",
    "sg:orig_category":"Poissonniers and \u00e9caillers",
    "sg:phone":"+32 69 22 10 84",
    "sg:postcode":"7500",
    "sg:province":"Hainaut",
    "wof:name":"Poissonnerie Fran\u00c7ois",
    "wof:placetype":"venue"
},
  "geometry": {"coordinates":[3.3920230865,50.6070709229],"type":"Point"}
}