{
  "type": "Feature",
  "properties": {
    "iso:country":"BE",
    "sg:address":"Everdongenlaan 15 Box 6",
    "sg:city":"Turnhout",
    "sg:orig_category":"Non-Classified Establishments",
    "sg:phone":"+32 14 43 48 84",
    "sg:postcode":"2300",
    "sg:province":"Antwerpen",
    "wof:name":"Bio Essentials",
    "wof:placetype":"venue"
},
  "geometry": {"coordinates":[4.9420437813,51.3000679016],"type":"Point"}
}