{
  "type": "Feature",
  "properties": {
    "addr:full":"Lerenveld 8 Lint Antwerpen 2547",
    "addr:housenumber":"8",
    "addr:postcode":"2547",
    "addr:street":"Lerenveld",
    "iso:country":"BE",
    "sg:address":"Lerenveld 8",
    "sg:city":"Lint",
    "sg:classifiers":[
        {
            "category":"Parking",
            "subcategory":"Lot",
            "type":"Transportation"
        }
    ],
    "sg:phone":"+32 3 488 09 29",
    "sg:postcode":"2547",
    "sg:province":"Antwerpen",
    "sg:tags":[
        "parking-places",
        "laying-out"
    ],
    "wof:name":"Archiflora Bvba",
    "wof:placetype":"venue"
},
  "geometry": {"coordinates":[4.5158138275,51.1275558472],"type":"Point"}
}