{
  "type": "Feature",
  "properties": {
    "addr:full":"Rue Du Commerce 20 Wavre Brabant Wallon 1300",
    "addr:housenumber":"20;1300",
    "addr:street":"Rue Du Commerce",
    "iso:country":"BE",
    "sg:address":"Rue Du Commerce 20",
    "sg:city":"Wavre",
    "sg:classifiers":[
        {
            "category":"Shopping",
            "subcategory":"Computers & Home Electronics",
            "type":"Retail Goods"
        }
    ],
    "sg:phone":"+32 10 22 38 11",
    "sg:postcode":"1300",
    "sg:province":"Brabant Wallon",
    "sg:tags":[
        "shop",
        "base",
        "telecommunicatieapparaten"
    ],
    "wof:name":"Base Wavre",
    "wof:placetype":"venue"
},
  "geometry": {"coordinates":[4.6103749275,50.71641922],"type":"Point"}
}