{
  "type": "Feature",
  "properties": {
    "iso:country":"BE",
    "sg:address":"Sint-jansstraat 16",
    "sg:city":"Herentals",
    "sg:orig_category":"Banken and kredietinstellingen",
    "sg:phone":"+32 14 21 14 75",
    "sg:postcode":"2200",
    "sg:province":"Antwerpen",
    "wof:name":"Groep Argenta",
    "wof:placetype":"venue"
},
  "geometry": {"coordinates":[4.8294019699,51.1763381958],"type":"Point"}
}