{
  "type": "Feature",
  "properties": {
    "addr:full":"Kapellestraat 6 Hooglede West-Vlaanderen 8830",
    "addr:housenumber":"6",
    "addr:postcode":"8830",
    "addr:street":"Kapellestraat",
    "iso:country":"BE",
    "sg:address":"Kapellestraat 6",
    "sg:city":"Hooglede",
    "sg:orig_category":"Baby- and kinderkleding",
    "sg:phone":"+32 51 21 16 73",
    "sg:postcode":"8830",
    "sg:province":"West-Vlaanderen",
    "wof:name":"Huis Laurens Kid\u00b4s",
    "wof:placetype":"venue"
},
  "geometry": {"coordinates":[3.0967190266,50.9965782166],"type":"Point"}
}