{
  "type": "Feature",
  "properties": {
    "addr:full":"Kleinhoefstraat 6 Geel Antwerpen 2440",
    "addr:housenumber":"6",
    "addr:postcode":"2440",
    "addr:street":"Kleinhoefstraat",
    "iso:country":"BE",
    "sg:address":"Kleinhoefstraat 6",
    "sg:city":"Geel",
    "sg:classifiers":[
        {
            "category":"Professional",
            "subcategory":"Management & Consulting",
            "type":"Services"
        }
    ],
    "sg:phone":"+32 14 57 96 42",
    "sg:postcode":"2440",
    "sg:province":"Antwerpen",
    "sg:tags":[
        "-",
        "processing",
        "data",
        "consultant"
    ],
    "wof:name":"Symbiotic",
    "wof:placetype":"venue"
},
  "geometry": {"coordinates":[4.9633450508,51.1628417969],"type":"Point"}
}