{
  "type": "Feature",
  "properties": {
    "addr:full":"Bld S. Dupuis 353 (westland Shop.center) Anderlecht Bruxelles-Capitale 1070",
    "addr:housenumber":"353",
    "addr:postcode":"1070",
    "addr:street":"Bld S. Dupuis;Westland Shop.Center",
    "iso:country":"BE",
    "sg:address":"Bld S. Dupuis 353 (westland Shop.center)",
    "sg:city":"Anderlecht",
    "sg:orig_category":"Fotogravure and zetwerk Herstelling leer and schoeisel Herstellingswinkels voor diverse persoonlijke",
    "sg:phone":"+32 2 522 01 29",
    "sg:postcode":"1070",
    "sg:province":"Bruxelles-Capitale",
    "wof:name":"Sjoeki",
    "wof:placetype":"venue"
},
  "geometry": {"coordinates":[4.2876291275,50.8379516602],"type":"Point"}
}