{
  "type": "Feature",
  "properties": {
    "iso:country":"BE",
    "sg:address":"Rue De La Bach\u00e9e 42",
    "sg:city":"Lasne (plancenoit)",
    "sg:classifiers":[
        {
            "category":"Manufacturing",
            "subcategory":"Tools & Machinery",
            "type":"Manufacturing & Wholesale Goods"
        }
    ],
    "sg:phone":"+32 2 633 21 43",
    "sg:postcode":"1380",
    "sg:province":"Brabant Wallon",
    "sg:tags":[
        "builder"
    ],
    "wof:name":"Geerts L",
    "wof:placetype":"venue"
},
  "geometry": {"coordinates":[4.4267749786,50.6598930359],"type":"Point"}
}