{
  "type": "Feature",
  "properties": {
    "addr:full":"Rue Des P\u00eacheries 33 Bruxelles (watermael-boitsfort) Bruxelles-Capitale 1170",
    "addr:housenumber":"33",
    "addr:postcode":"1170",
    "addr:street":"Rue Des Pe\u0302Cheries",
    "iso:country":"BE",
    "sg:address":"Rue Des P\u00eacheries 33",
    "sg:city":"Bruxelles (watermael-boitsfort)",
    "sg:classifiers":[
        {
            "category":"Shopping",
            "subcategory":"Bicycles & Sporting Goods",
            "type":"Retail Goods"
        }
    ],
    "sg:phone":"+32 2 660 46 06",
    "sg:postcode":"1170",
    "sg:province":"Bruxelles-Capitale",
    "sg:tags":[
        "sport",
        "-"
    ],
    "wof:name":"Passion",
    "wof:placetype":"venue"
},
  "geometry": {"coordinates":[4.4069042206,50.8122634888],"type":"Point"}
}