{
  "type": "Feature",
  "properties": {
    "iso:country":"BE",
    "sg:address":"Schaapsdreef 5",
    "sg:city":"Wingene",
    "sg:orig_category":"Varkenskwekers",
    "sg:phone":"+32 51 65 56 29",
    "sg:postcode":"8750",
    "sg:province":"West-Vlaanderen",
    "wof:name":"Ludwina Allaert",
    "wof:placetype":"venue"
},
  "geometry": {"coordinates":[3.2919631004,51.0784416199],"type":"Point"}
}