{
  "type": "Feature",
  "properties": {
    "addr:full":"Poederleeseweg 28 Herentals Antwerpen 2200",
    "addr:housenumber":"28",
    "addr:postcode":"2200",
    "addr:street":"Poederleeseweg",
    "iso:country":"BE",
    "sg:address":"Poederleeseweg 28",
    "sg:city":"Herentals",
    "sg:classifiers":[
        {
            "category":"Home & Garden",
            "subcategory":"Garden Supply",
            "type":"Retail Goods"
        }
    ],
    "sg:phone":"+32 14 23 23 84",
    "sg:postcode":"2200",
    "sg:province":"Antwerpen",
    "wof:name":"Willems Peter",
    "wof:placetype":"venue"
},
  "geometry": {"coordinates":[4.8365831375,51.187877655],"type":"Point"}
}