{
  "type": "Feature",
  "properties": {
    "addr:full":"Rue De L'h\u00f4tel Des Monnaies 52 Bruxelles (saint-gilles) Bruxelles-Capitale 1060",
    "addr:housenumber":"52",
    "addr:postcode":"1060",
    "addr:street":"Rue De L'Ho;Des Monnaies",
    "iso:country":"BE",
    "sg:address":"Rue De L'h\u00f4tel Des Monnaies 52",
    "sg:city":"Bruxelles (saint-gilles)",
    "sg:orig_category":"Newspapers, magazines, periodicals - Publishers",
    "sg:phone":"+32 2 543 02 80",
    "sg:postcode":"1060",
    "sg:province":"Bruxelles-Capitale",
    "wof:name":"Regards",
    "wof:placetype":"venue"
},
  "geometry": {"coordinates":[4.3489451408,50.8313598633],"type":"Point"}
}