{
  "type": "Feature",
  "properties": {
    "iso:country":"BE",
    "sg:address":"Chauss\u00e9e De Neerstalle 417",
    "sg:city":"Bruxelles (uccle)",
    "sg:classifiers":[
        {
            "category":"Food & Beverages",
            "subcategory":"Groceries & Convenience Stores",
            "type":"Retail Goods"
        }
    ],
    "sg:phone":"+32 2 332 57 31",
    "sg:postcode":"1180",
    "sg:province":"Bruxelles-Capitale",
    "sg:tags":[
        "grocer"
    ],
    "wof:name":"Wah International",
    "wof:placetype":"venue"
},
  "geometry": {"coordinates":[4.31919384,50.7989616394],"type":"Point"}
}