{
  "type": "Feature",
  "properties": {
    "addr:full":"Sint-rochusstraat 40 Kasterlee Antwerpen 2460",
    "addr:housenumber":"40",
    "addr:postcode":"2460",
    "addr:street":"Sint-Rochusstraat",
    "iso:country":"BE",
    "sg:address":"Sint-rochusstraat 40",
    "sg:city":"Kasterlee",
    "sg:orig_category":"Pleisterwerk",
    "sg:phone":"+32 14 55 36 13",
    "sg:postcode":"2460",
    "sg:province":"Antwerpen",
    "wof:name":"Allure-design",
    "wof:placetype":"venue"
},
  "geometry": {"coordinates":[4.9196782112,51.2226295471],"type":"Point"}
}