{
  "type": "Feature",
  "properties": {
    "iso:country":"BE",
    "sg:address":"Kortrijksesteenweg 59",
    "sg:city":"Sint-martens-latem (groot)",
    "sg:orig_category":"Opticiens",
    "sg:phone":"+32 9 281 26 31",
    "sg:postcode":"9830",
    "sg:province":"Oost-Vlaanderen",
    "wof:name":"Dirickx Jo",
    "wof:placetype":"venue"
},
  "geometry": {"coordinates":[3.6444458961,51.0128936768],"type":"Point"}
}