{
  "type": "Feature",
  "properties": {
    "iso:country":"BE",
    "sg:address":"Tomberg 245",
    "sg:city":"Bruxelles (woluwe-saint-lambert)",
    "sg:classifiers":[
        {
            "category":"Shopping",
            "subcategory":"Florist",
            "type":"Retail Goods"
        }
    ],
    "sg:phone":"+32 2 762 38 78",
    "sg:postcode":"1200",
    "sg:province":"Bruxelles-Capitale",
    "wof:name":"Tomberg En Fleur (le)",
    "wof:placetype":"venue"
},
  "geometry": {"coordinates":[4.4210019112,50.843963623],"type":"Point"}
}