{
  "type": "Feature",
  "properties": {
    "addr:full":"Grand'rue 130 Tintigny Luxembourg 6730",
    "addr:housenumber":"130",
    "addr:postcode":"6730",
    "addr:street":"Grand'Rue",
    "iso:country":"BE",
    "sg:address":"Grand'rue 130",
    "sg:city":"Tintigny",
    "sg:classifiers":[
        {
            "category":"Retail",
            "subcategory":"Veterinary Services",
            "type":"Services"
        }
    ],
    "sg:phone":"+32 63 44 42 55",
    "sg:postcode":"6730",
    "sg:province":"Luxembourg",
    "sg:tags":[
        "veterinarian"
    ],
    "wof:name":"Maitrejean A Jr",
    "wof:placetype":"venue"
},
  "geometry": {"coordinates":[5.519217968,49.6826286316],"type":"Point"}
}