{
  "type": "Feature",
  "properties": {
    "addr:full":"Rue Alphonse Briart 77 Chapelle-lez-herlaimont Hainaut 7160",
    "addr:housenumber":"77",
    "addr:postcode":"7160",
    "addr:street":"Rue Alphonse Briart;Hainaut",
    "iso:country":"BE",
    "sg:address":"Rue Alphonse Briart 77",
    "sg:city":"Chapelle-lez-herlaimont",
    "sg:orig_category":"M\u00e9decins and sp\u00e9cialistes",
    "sg:phone":"+32 64 44 26 71",
    "sg:postcode":"7160",
    "sg:province":"Hainaut",
    "wof:name":"J. Van Cauter",
    "wof:placetype":"venue"
},
  "geometry": {"coordinates":[4.2848911285,50.4726829529],"type":"Point"}
}