{
  "type": "Feature",
  "properties": {
    "addr:full":"Duffelsesteenweg 145 Kontich Antwerpen 2550",
    "addr:housenumber":"145",
    "addr:postcode":"2550",
    "addr:street":"Duffelsesteenweg",
    "iso:country":"BE",
    "sg:address":"Duffelsesteenweg 145",
    "sg:city":"Kontich",
    "sg:orig_category":"Sportclubs",
    "sg:phone":"+32 3 457 98 03",
    "sg:postcode":"2550",
    "sg:province":"Antwerpen",
    "wof:name":"Antwerp Badminton Club",
    "wof:placetype":"venue"
},
  "geometry": {"coordinates":[4.4533901215,51.1281967163],"type":"Point"}
}