{
  "type": "Feature",
  "properties": {
    "iso:country":"BE",
    "sg:address":"Oostereindestraat 14",
    "sg:city":"Lummen",
    "sg:orig_category":"Installation \u00e9lectrique r\u00e9sidentielle",
    "sg:phone":"+32 13 52 14 17",
    "sg:postcode":"3560",
    "sg:province":"Limburg",
    "wof:name":"Automatisatie Vanlook",
    "wof:placetype":"venue"
},
  "geometry": {"coordinates":[5.1970629692,50.9879074097],"type":"Point"}
}