{
  "type": "Feature",
  "properties": {
    "addr:full":"Avenue Albert I 2 Enghien Hainaut 7850",
    "addr:housenumber":"2",
    "addr:postcode":"7850",
    "addr:street":"Avenue Albert I",
    "iso:country":"BE",
    "sg:address":"Avenue Albert I 2",
    "sg:city":"Enghien",
    "sg:classifiers":[
        {
            "category":"Personal",
            "subcategory":"Beauty Salon",
            "type":"Services"
        }
    ],
    "sg:phone":"+32 2 395 43 58",
    "sg:postcode":"7850",
    "sg:province":"Hainaut",
    "sg:tags":[
        "lady",
        "-",
        "hairdressing"
    ],
    "wof:name":"Bigouderie (la)",
    "wof:placetype":"venue"
},
  "geometry": {"coordinates":[4.043214798,50.6939659119],"type":"Point"}
}