{
  "type": "Feature",
  "properties": {
    "addr:full":"Rue Du Faubourg 6 Chimay Hainaut 6460",
    "addr:housenumber":"6",
    "addr:postcode":"6460",
    "addr:street":"Rue Du Faubourg",
    "iso:country":"BE",
    "sg:address":"Rue Du Faubourg 6",
    "sg:city":"Chimay",
    "sg:classifiers":[
        {
            "category":"Retail",
            "subcategory":"Veterinary Services",
            "type":"Services"
        }
    ],
    "sg:phone":"+32 60 21 43 92",
    "sg:postcode":"6460",
    "sg:province":"Hainaut",
    "sg:tags":[
        "veterinarian"
    ],
    "wof:name":"Stavaux V",
    "wof:placetype":"venue"
},
  "geometry": {"coordinates":[4.3121538162,50.0472183228],"type":"Point"}
}