{
  "type": "Feature",
  "properties": {
    "addr:full":"Maastrichterstraat 89 Tongeren Limburg 3700",
    "addr:housenumber":"89",
    "addr:postcode":"3700",
    "addr:street":"Maastrichterstraat",
    "iso:country":"BE",
    "sg:address":"Maastrichterstraat 89",
    "sg:city":"Tongeren",
    "sg:classifiers":[
        {
            "category":"Food & Beverages",
            "subcategory":"Specialty",
            "type":"Retail Goods"
        }
    ],
    "sg:phone":"+32 12 23 62 13",
    "sg:postcode":"3700",
    "sg:province":"Limburg",
    "sg:tags":[
        "health",
        "dietary",
        "-",
        "biological"
    ],
    "wof:name":"Kruidentuin (de)",
    "wof:placetype":"venue"
},
  "geometry": {"coordinates":[5.4674210548,50.7823486328],"type":"Point"}
}