{
  "type": "Feature",
  "properties": {
    "addr:full":"Avenue De Nancy 29 Li\u00c8ge Li\u00e8ge 4020",
    "addr:housenumber":"29",
    "addr:postcode":"4020",
    "addr:street":"Avenue De Nancy",
    "iso:country":"BE",
    "sg:address":"Avenue De Nancy 29",
    "sg:city":"Li\u00c8ge",
    "sg:orig_category":"Tabac. Journaux",
    "sg:phone":"+32 4 341 01 64",
    "sg:postcode":"4020",
    "sg:province":"Li\u00e8ge",
    "wof:name":"Press Shop",
    "wof:placetype":"venue"
},
  "geometry": {"coordinates":[5.6010308266,50.6456947327],"type":"Point"}
}