{
  "type": "Feature",
  "properties": {
    "iso:country":"BE",
    "sg:address":"Avenue Du Bois D\u00b4arlon 21",
    "sg:city":"Arlon",
    "sg:classifiers":[
        {
            "category":"Insurance",
            "subcategory":"Insurance Agent",
            "type":"Services"
        }
    ],
    "sg:phone":"+32 63 23 51 76",
    "sg:postcode":"6700",
    "sg:province":"Luxembourg",
    "sg:tags":[
        "verzekeringsmakelaars",
        "expert"
    ],
    "wof:name":"Paul Barrea",
    "wof:placetype":"venue"
},
  "geometry": {"coordinates":[5.8033871651,49.6607933044],"type":"Point"}
}