{
  "type": "Feature",
  "properties": {
    "addr:full":"Sint-jobstraat 47 Box 4 Antwerpen Antwerpen 2060",
    "addr:housenumber":"47;4",
    "addr:postcode":"2060",
    "addr:street":"Sint-Jobstraat;Box",
    "iso:country":"BE",
    "sg:address":"Sint-jobstraat 47 Box 4",
    "sg:city":"Antwerpen",
    "sg:classifiers":[
        {
            "category":"Social Services",
            "type":"Services"
        }
    ],
    "sg:phone":"+32 3 235 00 34",
    "sg:postcode":"2060",
    "sg:province":"Antwerpen",
    "wof:name":"Kamers Met Aandacht Vzw",
    "wof:placetype":"venue"
},
  "geometry": {"coordinates":[4.4243741035,51.2285041809],"type":"Point"}
}