{
  "type": "Feature",
  "properties": {
    "addr:full":"Rue Buisseret 8 Mons Hainaut 7000",
    "addr:housenumber":"8",
    "addr:postcode":"7000",
    "addr:street":"Rue Buisseret;Hainaut",
    "iso:country":"BE",
    "sg:address":"Rue Buisseret 8",
    "sg:city":"Mons",
    "sg:classifiers":[
        {
            "category":"Health Services",
            "subcategory":"Dentist",
            "type":"Services"
        }
    ],
    "sg:phone":"+32 65 33 71 53",
    "sg:postcode":"7000",
    "sg:province":"Hainaut",
    "wof:name":"Mercier Florence",
    "wof:placetype":"venue"
},
  "geometry": {"coordinates":[3.9442660809,50.448928833],"type":"Point"}
}