{
  "type": "Feature",
  "properties": {
    "addr:full":"Rue Langhaag 25 Plombieres/plombieres Li\u00e8ge 4850",
    "addr:housenumber":"25",
    "addr:postcode":"4850",
    "addr:street":"Rue Langhaag",
    "iso:country":"BE",
    "sg:address":"Rue Langhaag 25",
    "sg:city":"Plombieres/plombieres",
    "sg:orig_category":"Herstellingen and onderhoud van auto's",
    "sg:phone":"+32 87 78 49 52",
    "sg:postcode":"4850",
    "sg:province":"Li\u00e8ge",
    "wof:name":"Roger Xhonneux",
    "wof:placetype":"venue"
},
  "geometry": {"coordinates":[5.9626002312,50.7068138123],"type":"Point"}
}