{
  "type": "Feature",
  "properties": {
    "addr:full":"Rempart Des Arbal\u00c9triers 10 Vise Li\u00e8ge 4600",
    "addr:housenumber":"10",
    "addr:postcode":"4600",
    "addr:street":"Rempart Des Arbale\u0301Triers",
    "iso:country":"BE",
    "sg:address":"Rempart Des Arbal\u00c9triers 10",
    "sg:city":"Vise",
    "sg:orig_category":"M\u00e9decins and sp\u00e9cialistes",
    "sg:phone":"+32 4 379 34 02",
    "sg:postcode":"4600",
    "sg:province":"Li\u00e8ge",
    "wof:name":"Genevi\u00c8ve De Fize",
    "wof:placetype":"venue"
},
  "geometry": {"coordinates":[5.6959438324,50.736240387],"type":"Point"}
}