{
  "type": "Feature",
  "properties": {
    "addr:full":"Dorpsstraat 42 Kalmthout Antwerpen 2920",
    "addr:housenumber":"42",
    "addr:postcode":"2920",
    "addr:street":"Dorpsstraat",
    "iso:country":"BE",
    "sg:address":"Dorpsstraat 42",
    "sg:city":"Kalmthout",
    "sg:orig_category":"Entretien and r\u00e9parations de voitures. V\u00e9hicules automobiles",
    "sg:phone":"+32 3 666 93 06",
    "sg:postcode":"2920",
    "sg:province":"Antwerpen",
    "wof:name":"Herman Clissen",
    "wof:placetype":"venue"
},
  "geometry": {"coordinates":[4.4741840363,51.3956794739],"type":"Point"}
}