{
  "type": "Feature",
  "properties": {
    "addr:full":"Oostendelaan 272 Middelkerke West-Vlaanderen 8430",
    "addr:housenumber":"272",
    "addr:postcode":"8430",
    "addr:street":"Oostendelaan",
    "iso:country":"BE",
    "sg:address":"Oostendelaan 272",
    "sg:city":"Middelkerke",
    "sg:classifiers":[
        {
            "category":"Wholesale",
            "subcategory":"Beer",
            "type":"Manufacturing & Wholesale Goods"
        }
    ],
    "sg:phone":"+32 59 31 15 15",
    "sg:postcode":"8430",
    "sg:province":"West-Vlaanderen",
    "sg:tags":[
        "ale",
        "-"
    ],
    "wof:name":"Vanhoutte Depot Nv",
    "wof:placetype":"venue"
},
  "geometry": {"coordinates":[2.8382198811,51.1928291321],"type":"Point"}
}