{
  "type": "Feature",
  "properties": {
    "iso:country":"BE",
    "sg:address":"Rrue Victor Rauter 69",
    "sg:city":"Anderlecht/anderlecht",
    "sg:orig_category":"Quincailleries. Air conditionn\u00e9 and ventilation. Equipement divers pour commerces Gr",
    "sg:phone":"+32 2 521 39 70",
    "sg:postcode":"1070",
    "sg:province":"Bruxelles-Capitale",
    "wof:name":"Prodfroid",
    "wof:placetype":"venue"
},
  "geometry": {"coordinates":[4.3109378815,50.8352203369],"type":"Point"}
}