{
  "type": "Feature",
  "properties": {
    "iso:country":"BE",
    "sg:address":"Rue De L'abbaye De Dieleghem 8",
    "sg:city":"Bruxelles (jette)",
    "sg:classifiers":[
        {
            "category":"Professional",
            "subcategory":"Accounting & Tax Preparation",
            "type":"Services"
        }
    ],
    "sg:phone":"+32 477 75 29 90",
    "sg:postcode":"1090",
    "sg:province":"Bruxelles-Capitale",
    "sg:tags":[
        "bookkeeper"
    ],
    "wof:name":"Heynderickx E",
    "wof:placetype":"venue"
},
  "geometry": {"coordinates":[4.3216190338,50.8825073242],"type":"Point"}
}