{
  "type": "Feature",
  "properties": {
    "iso:country":"BE",
    "sg:address":"Statiestraat 80",
    "sg:city":"Kalmthout",
    "sg:classifiers":[
        {
            "category":"Home & Garden",
            "subcategory":"Home Furnishings",
            "type":"Retail Goods"
        }
    ],
    "sg:phone":"+32 3 666 14 00",
    "sg:postcode":"2920",
    "sg:province":"Antwerpen",
    "sg:tags":[
        "decoration"
    ],
    "wof:name":"Decoland Nv",
    "wof:placetype":"venue"
},
  "geometry": {"coordinates":[4.467414856,51.3921394348],"type":"Point"}
}