{
  "type": "Feature",
  "properties": {
    "addr:full":"Lindenhofstraat 39 Landen Vlaams-Brabant 3400",
    "addr:housenumber":"39",
    "addr:postcode":"3400",
    "addr:street":"Lindenhofstraat",
    "iso:country":"BE",
    "sg:address":"Lindenhofstraat 39",
    "sg:city":"Landen",
    "sg:orig_category":"Antiek",
    "sg:phone":"+32 11 88 66 19",
    "sg:postcode":"3400",
    "sg:province":"Vlaams-Brabant",
    "wof:name":"'t Spinnewebke",
    "wof:placetype":"venue"
},
  "geometry": {"coordinates":[5.0390620232,50.7483139038],"type":"Point"}
}