{
  "type": "Feature",
  "properties": {
    "iso:country":"BE",
    "sg:address":"Rue Bizette 41",
    "sg:city":"Herstal",
    "sg:orig_category":"Instituts de beaut\u00e9. Centres de relaxation and bien-\u00eatre",
    "sg:phone":"+32 4 227 91 74",
    "sg:postcode":"4041",
    "sg:province":"Li\u00e8ge",
    "wof:name":"Institut Lady Quartz",
    "wof:placetype":"venue"
},
  "geometry": {"coordinates":[5.5849199295,50.6724891663],"type":"Point"}
}