{
  "type": "Feature",
  "properties": {
    "addr:full":"Zavelstraat 8 Peer Limburg 3990",
    "addr:housenumber":"8",
    "addr:postcode":"3990",
    "addr:street":"Zavelstraat",
    "iso:country":"BE",
    "sg:address":"Zavelstraat 8",
    "sg:city":"Peer",
    "sg:orig_category":"Installatie van metalen schrijnwerk Pleisterwerk Woningbouw",
    "sg:phone":"+32 11 63 64 21",
    "sg:postcode":"3990",
    "sg:province":"Limburg",
    "wof:name":"Vandael",
    "wof:placetype":"venue"
},
  "geometry": {"coordinates":[5.4533009529,51.1329536438],"type":"Point"}
}