{
  "type": "Feature",
  "properties": {
    "addr:full":"Rue Terre L'oreye 25 Charleroi (mont-sur-marchienne) Hainaut 6032",
    "addr:housenumber":"25",
    "addr:postcode":"6032",
    "addr:street":"Rue Terre L'Oreye",
    "iso:country":"BE",
    "sg:address":"Rue Terre L'oreye 25",
    "sg:city":"Charleroi (mont-sur-marchienne)",
    "sg:classifiers":[
        {
            "category":"Social Services",
            "subcategory":"Job Training",
            "type":"Services"
        }
    ],
    "sg:phone":"+32 71 43 57 43",
    "sg:postcode":"6032",
    "sg:province":"Hainaut",
    "sg:tags":[
        "personnel"
    ],
    "wof:name":"Ensemble",
    "wof:placetype":"venue"
},
  "geometry": {"coordinates":[4.4085550308,50.3944015503],"type":"Point"}
}