{
  "type": "Feature",
  "properties": {
    "addr:full":"Rue Nicolas Lambercy 24 Aywaille Li\u00e8ge 4920",
    "addr:housenumber":"24",
    "addr:postcode":"4920",
    "addr:street":"Rue Nicolas Lambercy",
    "iso:country":"BE",
    "sg:address":"Rue Nicolas Lambercy 24",
    "sg:city":"Aywaille",
    "sg:orig_category":"Benzinestations and brandstoffen Herstellingen and onderhoud van auto's Voertuigen",
    "sg:phone":"+32 4 384 40 10",
    "sg:postcode":"4920",
    "sg:province":"Li\u00e8ge",
    "wof:name":"Grolet",
    "wof:placetype":"venue"
},
  "geometry": {"coordinates":[5.6759052277,50.4715003967],"type":"Point"}
}