{
  "type": "Feature",
  "properties": {
    "addr:full":"Rozenstraat 30 Opglabbeek Limburg 3660",
    "addr:housenumber":"30",
    "addr:postcode":"3660",
    "addr:street":"Rozenstraat",
    "iso:country":"BE",
    "sg:address":"Rozenstraat 30",
    "sg:city":"Opglabbeek",
    "sg:orig_category":"Sportclubs",
    "sg:phone":"+32 89 85 57 44",
    "sg:postcode":"3660",
    "sg:province":"Limburg",
    "wof:name":"V.c. Ovoc Dames",
    "wof:placetype":"venue"
},
  "geometry": {"coordinates":[5.5776281357,51.0432128906],"type":"Point"}
}