{
  "type": "Feature",
  "properties": {
    "iso:country":"BE",
    "sg:address":"Ringlaan 87",
    "sg:city":"Koekelare",
    "sg:orig_category":"Entretien and r\u00e9parations de voitures",
    "sg:phone":"+32 51 58 03 76",
    "sg:postcode":"8680",
    "sg:province":"West-Vlaanderen",
    "wof:name":"Carwash Lootens",
    "wof:placetype":"venue"
},
  "geometry": {"coordinates":[2.9691450596,51.09034729],"type":"Point"}
}