{
  "type": "Feature",
  "properties": {
    "addr:full":"Oudstrijdersstraat 23 Ranst (oelegem) Antwerpen 2520",
    "addr:housenumber":"23",
    "addr:postcode":"2520",
    "addr:street":"Oudstrijdersstraat",
    "iso:country":"BE",
    "sg:address":"Oudstrijdersstraat 23",
    "sg:city":"Ranst (oelegem)",
    "sg:classifiers":[
        {
            "category":"Home & Garden",
            "subcategory":"Carpets & Floor Coverings",
            "type":"Retail Goods"
        }
    ],
    "sg:phone":"+32 3 383 31 29",
    "sg:postcode":"2520",
    "sg:province":"Antwerpen",
    "sg:tags":[
        "armoring"
    ],
    "wof:name":"Sebreghts",
    "wof:placetype":"venue"
},
  "geometry": {"coordinates":[4.5945820808,51.2117004395],"type":"Point"}
}