{
  "type": "Feature",
  "properties": {
    "addr:full":"Hoogkamerstraat 292 Temse Oost-Vlaanderen 9140",
    "addr:housenumber":"292",
    "addr:postcode":"9140",
    "addr:street":"Hoogkamerstraat",
    "iso:country":"BE",
    "sg:address":"Hoogkamerstraat 292",
    "sg:city":"Temse",
    "sg:orig_category":"Benzinestations and brandstoffen Herstellingen and onderhoud van auto's",
    "sg:phone":"+32 3 771 33 33",
    "sg:postcode":"9140",
    "sg:province":"Oost-Vlaanderen",
    "wof:name":"Shell",
    "wof:placetype":"venue"
},
  "geometry": {"coordinates":[4.1860089302,51.1373405457],"type":"Point"}
}