{
  "type": "Feature",
  "properties": {
    "iso:country":"BE",
    "sg:address":"Weg Naar As 202",
    "sg:city":"Genk",
    "sg:classifiers":[
        {
            "category":"Insurance",
            "subcategory":"Insurance Agent",
            "type":"Services"
        }
    ],
    "sg:phone":"+32 89 36 78 79",
    "sg:postcode":"3600",
    "sg:province":"Limburg",
    "sg:tags":[
        "broker"
    ],
    "wof:name":"Gvk Bvba",
    "wof:placetype":"venue"
},
  "geometry": {"coordinates":[5.5212621689,50.9750022888],"type":"Point"}
}