{
  "type": "Feature",
  "properties": {
    "iso:country":"BE",
    "sg:address":"Rue De Fragn\u00c9e 165",
    "sg:city":"Li\u00c8ge",
    "sg:orig_category":"Entretien and r\u00e9parations de voitures",
    "sg:phone":"+32 4 252 63 46",
    "sg:postcode":"4000",
    "sg:province":"Li\u00e8ge",
    "wof:name":"Carrosserie Alex",
    "wof:placetype":"venue"
},
  "geometry": {"coordinates":[5.5734357834,50.6213378906],"type":"Point"}
}