{
  "type": "Feature",
  "properties": {
    "addr:full":"Koolmijnlaan 251 Beringen Limburg 3582",
    "addr:housenumber":"251",
    "addr:postcode":"3582",
    "addr:street":"Koolmijnlaan",
    "iso:country":"BE",
    "sg:address":"Koolmijnlaan 251",
    "sg:city":"Beringen",
    "sg:orig_category":"Supermarch\u00e9s",
    "sg:phone":"+32 11 42 32 88",
    "sg:postcode":"3582",
    "sg:province":"Limburg",
    "wof:name":"Gb Contact",
    "wof:placetype":"venue"
},
  "geometry": {"coordinates":[5.2202811241,51.0738601685],"type":"Point"}
}