{
  "type": "Feature",
  "properties": {
    "addr:full":"Rue De La Gironde 27-3 Lincent (racour) Li\u00e8ge 4287",
    "addr:housenumber":"27-3",
    "addr:postcode":"4287",
    "addr:street":"Rue De La Gironde;Racour",
    "iso:country":"BE",
    "sg:address":"Rue De La Gironde 27-3",
    "sg:city":"Lincent (racour)",
    "sg:classifiers":[
        {
            "category":"Building & Trades",
            "subcategory":"Cleaning & Sanitation",
            "type":"Services"
        }
    ],
    "sg:phone":"+32 496 62 22 56",
    "sg:postcode":"4287",
    "sg:province":"Li\u00e8ge",
    "sg:tags":[
        "janitor"
    ],
    "wof:name":"Net-impec",
    "wof:placetype":"venue"
},
  "geometry": {"coordinates":[5.0272140503,50.7375259399],"type":"Point"}
}