{
  "type": "Feature",
  "properties": {
    "addr:full":"Avenue Des Marronniers 156 Saint-nicolas (tilleur) Li\u00e8ge 4420",
    "addr:housenumber":"156",
    "addr:postcode":"4420",
    "addr:street":"Avenue Des Marronniers;Tilleur",
    "iso:country":"BE",
    "sg:address":"Avenue Des Marronniers 156",
    "sg:city":"Saint-nicolas (tilleur)",
    "sg:classifiers":[
        {
            "category":"Professional",
            "subcategory":"Testing Lab",
            "type":"Services"
        }
    ],
    "sg:phone":"+32 4 233 82 52",
    "sg:postcode":"4420",
    "sg:province":"Li\u00e8ge",
    "sg:tags":[
        "chemist"
    ],
    "wof:name":"Vos",
    "wof:placetype":"venue"
},
  "geometry": {"coordinates":[5.5417990685,50.623210907],"type":"Point"}
}