{
  "type": "Feature",
  "properties": {
    "addr:full":"Wildertse Duintjes 18 Essen Antwerpen 2910",
    "addr:housenumber":"18",
    "addr:postcode":"2910",
    "addr:street":"Wildertse Duintjes",
    "iso:country":"BE",
    "sg:address":"Wildertse Duintjes 18",
    "sg:city":"Essen",
    "sg:orig_category":"Mus\u00e9es and patrimoine culturel",
    "sg:phone":"+32 3 667 24 40",
    "sg:postcode":"2910",
    "sg:province":"Antwerpen",
    "wof:name":"Museum Wildertse Duintjes",
    "wof:placetype":"venue"
},
  "geometry": {"coordinates":[4.4527401924,51.4413604736],"type":"Point"}
}