{
  "type": "Feature",
  "properties": {
    "addr:full":"Gentstraat 11 Sint-gillis-waas Oost-Vlaanderen 9170",
    "addr:housenumber":"11",
    "addr:postcode":"9170",
    "addr:street":"Gentstraat",
    "iso:country":"BE",
    "sg:address":"Gentstraat 11",
    "sg:city":"Sint-gillis-waas",
    "sg:classifiers":[
        {
            "category":"Insurance",
            "subcategory":"Life Insurance",
            "type":"Services"
        }
    ],
    "sg:phone":"+32 3 766 58 58",
    "sg:postcode":"9170",
    "sg:province":"Oost-Vlaanderen",
    "sg:tags":[
        "assurance"
    ],
    "wof:name":"Vitas Groep",
    "wof:placetype":"venue"
},
  "geometry": {"coordinates":[4.0973992348,51.1922531128],"type":"Point"}
}