{
  "type": "Feature",
  "properties": {
    "addr:full":"Tiensestraat 41 Leuven Vlaams-Brabant 3000",
    "addr:housenumber":"41",
    "addr:postcode":"3000",
    "addr:street":"Tiensestraat",
    "iso:country":"BE",
    "sg:address":"Tiensestraat 41",
    "sg:city":"Leuven",
    "sg:orig_category":"Hoger onderwijs",
    "sg:phone":"+32 16 32 51 01",
    "sg:postcode":"3000",
    "sg:province":"Vlaams-Brabant",
    "wof:name":"K.u.l.-fac.rechtsgeleerd.",
    "wof:placetype":"venue"
},
  "geometry": {"coordinates":[4.7041082382,50.8777313232],"type":"Point"}
}