{
  "type": "Feature",
  "properties": {
    "addr:full":"Rue De Dinant 49 Tinlot (ab\u00e9e) Li\u00e8ge 4557",
    "addr:housenumber":"49",
    "addr:postcode":"4557",
    "addr:street":"Rue De Dinant;Abe\u0301E",
    "iso:country":"BE",
    "sg:address":"Rue De Dinant 49",
    "sg:city":"Tinlot (ab\u00e9e)",
    "sg:classifiers":[
        {
            "category":"Health Services",
            "subcategory":"Doctor",
            "type":"Services"
        }
    ],
    "sg:phone":"+32 85 51 21 43",
    "sg:postcode":"4557",
    "sg:province":"Li\u00e8ge",
    "sg:tags":[
        "medicinephysicians",
        "surgeon"
    ],
    "wof:name":"Deno\u00ebl Ch",
    "wof:placetype":"venue"
},
  "geometry": {"coordinates":[5.3739848137,50.4988136292],"type":"Point"}
}