{
  "type": "Feature",
  "properties": {
    "iso:country":"BE",
    "sg:address":"Rue Du Bois De Broux 6",
    "sg:city":"Rixensart",
    "sg:classifiers":[
        {
            "category":"Arena",
            "subcategory":"Sports Club",
            "type":"Entertainment"
        }
    ],
    "sg:phone":"+32 2 652 02 27",
    "sg:postcode":"1331",
    "sg:province":"Brabant Wallon",
    "sg:tags":[
        "de"
    ],
    "wof:name":"Classic Racing Motorcycle",
    "wof:placetype":"venue"
},
  "geometry": {"coordinates":[4.5320749283,50.7337379456],"type":"Point"}
}