{
  "type": "Feature",
  "properties": {
    "iso:country":"BE",
    "sg:address":"Molenbergstraat 15",
    "sg:city":"Lanaken",
    "sg:orig_category":"Entretien and r\u00e9parations de voitures",
    "sg:phone":"+32 89 72 11 61",
    "sg:postcode":"3620",
    "sg:province":"Limburg",
    "wof:name":"Garage Thijs",
    "wof:placetype":"venue"
},
  "geometry": {"coordinates":[5.6129522324,50.9226493835],"type":"Point"}
}