{
  "type": "Feature",
  "properties": {
    "iso:country":"BE",
    "sg:address":"Geraardsbergsesteenweg 39",
    "sg:city":"Herne",
    "sg:orig_category":"Rundveehouders",
    "sg:phone":"+32 2 396 27 54",
    "sg:postcode":"1541",
    "sg:province":"Vlaams-Brabant",
    "wof:name":"Jean Muysewinckel",
    "wof:placetype":"venue"
},
  "geometry": {"coordinates":[4.0218148232,50.7066955566],"type":"Point"}
}