{
  "type": "Feature",
  "properties": {
    "iso:country":"BE",
    "sg:address":"Rue Des Colonies 24",
    "sg:city":"Namur (saint-marc)",
    "sg:classifiers":[
        {
            "category":"Building & Trades",
            "subcategory":"Electrical",
            "type":"Services"
        }
    ],
    "sg:postcode":"5003",
    "sg:province":"Namur",
    "sg:tags":[
        "electric",
        "-",
        "housewiring",
        "contractor"
    ],
    "wof:name":"Bodart Vincent",
    "wof:placetype":"venue"
},
  "geometry": {"coordinates":[4.8473348618,50.4915008545],"type":"Point"}
}