{
  "type": "Feature",
  "properties": {
    "iso:country":"BE",
    "sg:address":"Kerktorenstraat 14",
    "sg:city":"Machelen (diegem)",
    "sg:classifiers":[
        {
            "category":"Health Services",
            "subcategory":"Doctor",
            "type":"Services"
        }
    ],
    "sg:phone":"+32 2 720 47 72",
    "sg:postcode":"1831",
    "sg:province":"Vlaams-Brabant",
    "sg:tags":[
        "medicinephysicians",
        "surgeon"
    ],
    "wof:name":"Houthuys Christel",
    "wof:placetype":"venue"
},
  "geometry": {"coordinates":[4.4349131584,50.8943862915],"type":"Point"}
}