{
  "type": "Feature",
  "properties": {
    "addr:full":"Kortrijksesteenweg 323 Harelbeke West-Vlaanderen 8530",
    "addr:housenumber":"323",
    "addr:postcode":"8530",
    "addr:street":"Kortrijksesteenweg",
    "iso:country":"BE",
    "sg:address":"Kortrijksesteenweg 323",
    "sg:city":"Harelbeke",
    "sg:orig_category":"Produits pharmaceutiques Fab",
    "sg:phone":"+32 56 72 64 81",
    "sg:postcode":"8530",
    "sg:province":"West-Vlaanderen",
    "wof:name":"Farmabel",
    "wof:placetype":"venue"
},
  "geometry": {"coordinates":[3.2913169861,50.8424415588],"type":"Point"}
}