{
  "type": "Feature",
  "properties": {
    "addr:full":"Kuiperskaai 19 Gent Oost-Vlaanderen 9000",
    "addr:housenumber":"19",
    "addr:postcode":"9000",
    "addr:street":"Kuiperskaai;Oost-Vlaanderen",
    "iso:country":"BE",
    "sg:address":"Kuiperskaai 19",
    "sg:city":"Gent",
    "sg:classifiers":[
        {
            "category":"Cinema",
            "subcategory":"Movie Rental",
            "type":"Entertainment"
        }
    ],
    "sg:phone":"+32 9 233 29 50",
    "sg:postcode":"9000",
    "sg:province":"Oost-Vlaanderen",
    "sg:tags":[
        "de",
        "cassette",
        "location",
        "vid\u00e9o",
        "audio"
    ],
    "wof:name":"A.b.c.d.",
    "wof:placetype":"venue"
},
  "geometry": {"coordinates":[3.7297000885,51.0489997864],"type":"Point"}
}