{
  "type": "Feature",
  "properties": {
    "addr:full":"Borghthoevestraat 18 Brecht Antwerpen 2960",
    "addr:housenumber":"18",
    "addr:postcode":"2960",
    "addr:street":"Borghthoevestraat",
    "iso:country":"BE",
    "sg:address":"Borghthoevestraat 18",
    "sg:city":"Brecht",
    "sg:orig_category":"Bouwmaterialen Gh Dakwerken Installatie van houten of kunststof schrijnwerk Installatie van metalen ",
    "sg:phone":"+32 3 313 83 11",
    "sg:postcode":"2960",
    "sg:province":"Antwerpen",
    "wof:name":"S - Bouw",
    "wof:placetype":"venue"
},
  "geometry": {"coordinates":[4.6389250755,51.3523674011],"type":"Point"}
}