{
  "type": "Feature",
  "properties": {
    "addr:full":"Rue Du Vicinal 9 Libramont-chevigny Luxembourg 6800",
    "addr:housenumber":"9",
    "addr:postcode":"6800",
    "addr:street":"Rue Du Vicinal",
    "iso:country":"BE",
    "sg:address":"Rue Du Vicinal 9",
    "sg:city":"Libramont-chevigny",
    "sg:classifiers":[
        {
            "category":"Fast Food",
            "type":"Food & Drink"
        }
    ],
    "sg:phone":"+32 61 22 50 52",
    "sg:postcode":"6800",
    "sg:province":"Luxembourg",
    "sg:tags":[
        "\u00c0",
        "restaurants",
        "emporter",
        "restaurant"
    ],
    "wof:name":"Le Vicinal",
    "wof:placetype":"venue"
},
  "geometry": {"coordinates":[5.3761348724,49.9199943542],"type":"Point"}
}