{
  "type": "Feature",
  "properties": {
    "iso:country":"BE",
    "sg:address":"Marktplein 1",
    "sg:city":"Moeskroen/mouscron",
    "sg:orig_category":"Overheidsdiensten",
    "sg:phone":"+32 56 86 02 00",
    "sg:postcode":"7700",
    "sg:province":"Hainaut",
    "wof:name":"Administration Communale",
    "wof:placetype":"venue"
},
  "geometry": {"coordinates":[3.2323200703,50.7400932312],"type":"Point"}
}