{
  "type": "Feature",
  "properties": {
    "iso:country":"BE",
    "sg:address":"Doornveld 1 Bus 2",
    "sg:city":"Zellik",
    "sg:classifiers":[
        {
            "category":"Wholesale",
            "subcategory":"Machinery & Supplies",
            "type":"Manufacturing & Wholesale Goods"
        }
    ],
    "sg:phone":"+32 2 466 34 40",
    "sg:postcode":"1731",
    "sg:province":"Vlaams-Brabant",
    "sg:tags":[
        "food",
        "processing",
        "-",
        "machine",
        "equipment",
        "engineering",
        "mechanical"
    ],
    "wof:name":"Sgm Machine Technology Nv",
    "wof:placetype":"venue"
},
  "geometry": {"coordinates":[4.2581400871,50.8911552429],"type":"Point"}
}