{
  "type": "Feature",
  "properties": {
    "iso:country":"BE",
    "sg:address":"Leopold I Esplanade 3",
    "sg:city":"De Panne",
    "sg:classifiers":[
        {
            "category":"Real Estate",
            "subcategory":"Real Estate Services",
            "type":"Services"
        }
    ],
    "sg:phone":"+32 58 41 12 08",
    "sg:postcode":"8660",
    "sg:province":"West-Vlaanderen",
    "wof:name":"Agence Esplanade",
    "wof:placetype":"venue"
},
  "geometry": {"coordinates":[2.5821449757,51.097858429],"type":"Point"}
}