{
  "type": "Feature",
  "properties": {
    "addr:full":"Dorpsstraat 98 Overpelt Limburg 3900",
    "addr:housenumber":"98",
    "addr:postcode":"3900",
    "addr:street":"Dorpsstraat",
    "iso:country":"BE",
    "sg:address":"Dorpsstraat 98",
    "sg:city":"Overpelt",
    "sg:orig_category":"Newspapers, magazines, periodicals - Distribution",
    "sg:phone":"+32 11 66 18 13",
    "sg:postcode":"3900",
    "sg:province":"Limburg",
    "wof:name":"Yoma Bvba",
    "wof:placetype":"venue"
},
  "geometry": {"coordinates":[5.4228768349,51.2119026184],"type":"Point"}
}