{
  "type": "Feature",
  "properties": {
    "iso:country":"BE",
    "sg:address":"Antwerpsesteenweg 34",
    "sg:city":"Ranst (broechem)",
    "sg:classifiers":[
        {
            "category":"Building & Trades",
            "subcategory":"Landscaping Services",
            "type":"Services"
        }
    ],
    "sg:phone":"+32 3 475 08 53",
    "sg:postcode":"2520",
    "sg:province":"Antwerpen",
    "sg:tags":[
        "gardening",
        "garden",
        "maintenance"
    ],
    "wof:name":"Mast R",
    "wof:placetype":"venue"
},
  "geometry": {"coordinates":[4.5885100365,51.1845588684],"type":"Point"}
}