{
  "type": "Feature",
  "properties": {
    "addr:full":". Schilde (groot) Antwerpen 2970",
    "addr:postcode":"2970",
    "addr:street":"Groot Antwerpen",
    "iso:country":"BE",
    "sg:address":".",
    "sg:city":"Schilde (groot)",
    "sg:orig_category":"Apotheken",
    "sg:phone":"+32 900 10 500",
    "sg:postcode":"2970",
    "sg:province":"Antwerpen",
    "wof:name":"Apothekers Van Wacht",
    "wof:placetype":"venue"
},
  "geometry": {"coordinates":[4.5798120499,51.2392082214],"type":"Point"}
}