{
  "type": "Feature",
  "properties": {
    "iso:country":"BE",
    "sg:address":"Verlorenkost 5",
    "sg:city":"Gistel",
    "sg:orig_category":"Eleveurs and marchands de porcs. Eleveurs de bovins",
    "sg:phone":"+32 59 70 96 33",
    "sg:postcode":"8470",
    "sg:province":"West-Vlaanderen",
    "wof:name":"Freddy T'jonck",
    "wof:placetype":"venue"
},
  "geometry": {"coordinates":[2.9396948814,51.1793746948],"type":"Point"}
}