{
  "type": "Feature",
  "properties": {
    "iso:country":"BE",
    "sg:address":"Oude Baan 27",
    "sg:city":"Bertem",
    "sg:orig_category":"Plaatsen van vloer- and muurbekleding Schilders",
    "sg:phone":"+32 16 49 09 21",
    "sg:postcode":"3060",
    "sg:province":"Vlaams-Brabant",
    "wof:name":"Philippe Bertrand",
    "wof:placetype":"venue"
},
  "geometry": {"coordinates":[4.6324520111,50.8706932068],"type":"Point"}
}