{
  "type": "Feature",
  "properties": {
    "iso:country":"BE",
    "sg:address":"Grand'rue 9",
    "sg:city":"Walcourt (somz\u00e9e)",
    "sg:classifiers":[
        {
            "category":"Professional",
            "subcategory":"Art Services",
            "type":"Services"
        }
    ],
    "sg:phone":"+32 71 21 56 13",
    "sg:postcode":"5651",
    "sg:province":"Namur",
    "sg:tags":[
        "photographer"
    ],
    "wof:name":"Antoine J M (photo)",
    "wof:placetype":"venue"
},
  "geometry": {"coordinates":[4.4332799911,50.2857818604],"type":"Point"}
}