{
  "type": "Feature",
  "properties": {
    "iso:country":"BE",
    "sg:address":"Ouderdomseweg 3",
    "sg:city":"Poperinge",
    "sg:orig_category":"Sportcentra",
    "sg:phone":"+32 57 33 89 42",
    "sg:postcode":"8970",
    "sg:province":"West-Vlaanderen",
    "wof:name":"Stedelijke Sporthal",
    "wof:placetype":"venue"
},
  "geometry": {"coordinates":[2.7398331165,50.847328186],"type":"Point"}
}