{
  "type": "Feature",
  "properties": {
    "iso:country":"BE",
    "sg:address":"Nieuwe Baan 50",
    "sg:city":"Sint-niklaas (belsele)",
    "sg:classifiers":[
        {
            "category":"Personal",
            "subcategory":"Beauty Salon",
            "type":"Services"
        }
    ],
    "sg:phone":"+32 3 772 54 29",
    "sg:postcode":"9111",
    "sg:province":"Oost-Vlaanderen",
    "sg:tags":[
        "lady",
        "-",
        "hairdressing"
    ],
    "wof:name":"Eddy New Hair",
    "wof:placetype":"venue"
},
  "geometry": {"coordinates":[4.0893158913,51.1429786682],"type":"Point"}
}