{
  "type": "Feature",
  "properties": {
    "addr:full":"Drongensesteenweg 4 Gent Oost-Vlaanderen 9000",
    "addr:housenumber":"4",
    "addr:postcode":"9000",
    "addr:street":"Drongensesteenweg;Oost-Vlaanderen",
    "iso:country":"BE",
    "sg:address":"Drongensesteenweg 4",
    "sg:city":"Gent",
    "sg:orig_category":"Electrom\u00e9nager, t\u00e9l\u00e9visions and radios",
    "sg:phone":"+32 9 227 87 56",
    "sg:postcode":"9000",
    "sg:province":"Oost-Vlaanderen",
    "wof:name":"T V Service Eric Slos",
    "wof:placetype":"venue"
},
  "geometry": {"coordinates":[3.7018249035,51.0578041077],"type":"Point"}
}