{
  "type": "Feature",
  "properties": {
    "addr:full":"2800 Mechelen (groot) Antwerpen 2800",
    "addr:postcode":"2800;2800",
    "addr:street":"Groot Antwerpen",
    "iso:country":"BE",
    "sg:address":"2800",
    "sg:city":"Mechelen (groot)",
    "sg:orig_category":"Pharmaciens",
    "sg:phone":"+32 900 10 500",
    "sg:postcode":"2800",
    "sg:province":"Antwerpen",
    "wof:name":"Pharmacies De Garde",
    "wof:placetype":"venue"
},
  "geometry": {"coordinates":[4.4678602219,51.0348815918],"type":"Point"}
}