{
  "type": "Feature",
  "properties": {
    "addr:full":"4790 Burg-reuland Li\u00e8ge 4790",
    "addr:postcode":"4790;4790",
    "addr:street":"Burg-Reuland",
    "iso:country":"BE",
    "sg:address":"4790",
    "sg:city":"Burg-reuland",
    "sg:orig_category":"Pharmaciens",
    "sg:phone":"+32 900 10 500",
    "sg:postcode":"4790",
    "sg:province":"Li\u00e8ge",
    "wof:name":"Pharmacies De Garde",
    "wof:placetype":"venue"
},
  "geometry": {"coordinates":[6.1315770149,50.1943702698],"type":"Point"}
}