{
  "type": "Feature",
  "properties": {
    "iso:country":"BE",
    "sg:address":"Steenstraat 94",
    "sg:city":"Kortemark",
    "sg:classifiers":[
        {
            "category":"Education",
            "subcategory":"Music School",
            "type":"Public Place"
        }
    ],
    "sg:phone":"+32 51 58 82 15",
    "sg:postcode":"8610",
    "sg:province":"West-Vlaanderen",
    "sg:tags":[
        "breeding",
        "cattle"
    ],
    "wof:name":"Planquette Michel-bonny B.v.b.a.",
    "wof:placetype":"venue"
},
  "geometry": {"coordinates":[2.9971210957,51.056224823],"type":"Point"}
}