{
  "type": "Feature",
  "properties": {
    "addr:full":"Driesstraat 116 Affligem Vlaams-Brabant 1790",
    "addr:housenumber":"116",
    "addr:postcode":"1790",
    "addr:street":"Driesstraat",
    "iso:country":"BE",
    "sg:address":"Driesstraat 116",
    "sg:city":"Affligem",
    "sg:orig_category":"Producteurs de l\u00e9gumes",
    "sg:phone":"+32 53 66 13 49",
    "sg:postcode":"1790",
    "sg:province":"Vlaams-Brabant",
    "wof:name":"Steven Anckaert",
    "wof:placetype":"venue"
},
  "geometry": {"coordinates":[4.105984211,50.9132232666],"type":"Point"}
}