{
  "type": "Feature",
  "properties": {
    "addr:full":"Koninklijke Baan 62 Koksijde West-Vlaanderen 8670",
    "addr:housenumber":"62",
    "addr:postcode":"8670",
    "addr:street":"Koninklijke Baan",
    "iso:country":"BE",
    "sg:address":"Koninklijke Baan 62",
    "sg:city":"Koksijde",
    "sg:classifiers":[
        {
            "category":"Travel",
            "subcategory":"Hotels & Motels",
            "type":"Entertainment"
        }
    ],
    "sg:phone":"+32 58 51 27 63",
    "sg:postcode":"8670",
    "sg:province":"West-Vlaanderen",
    "sg:tags":[
        "van",
        "restaurant",
        "food",
        "aan",
        "fast",
        "feesten",
        "levering",
        "meeneem",
        "organisatie",
        "rest",
        "catering",
        "huis"
    ],
    "wof:name":"Carnac",
    "wof:placetype":"venue"
},
  "geometry": {"coordinates":[2.6407749653,51.1216506958],"type":"Point"}
}