{
  "type": "Feature",
  "properties": {
    "addr:full":"Schriekweg 36 Zandhoven Antwerpen 2240",
    "addr:housenumber":"36",
    "addr:postcode":"2240",
    "addr:street":"Schriekweg",
    "iso:country":"BE",
    "sg:address":"Schriekweg 36",
    "sg:city":"Zandhoven",
    "sg:classifiers":[
        {
            "category":"Airport",
            "subcategory":"International",
            "type":"Transportation"
        }
    ],
    "sg:phone":"+32 3 484 52 81",
    "sg:postcode":"2240",
    "sg:province":"Antwerpen",
    "sg:tags":[
        "-",
        "transport"
    ],
    "wof:name":"Van Winckel H",
    "wof:placetype":"venue"
},
  "geometry": {"coordinates":[4.6637659073,51.2210273743],"type":"Point"}
}