{
  "type": "Feature",
  "properties": {
    "addr:full":"Rue Chapelle St.-germain 6ba Lasne Brabant Wallon 1380",
    "addr:housenumber":"6ba",
    "addr:postcode":"1380",
    "addr:street":"Rue Chapelle St.-Germain",
    "iso:country":"BE",
    "sg:address":"Rue Chapelle St.-germain 6ba",
    "sg:city":"Lasne",
    "sg:classifiers":[
        {
            "category":"Insurance",
            "subcategory":"Insurance Agent",
            "type":"Services"
        }
    ],
    "sg:phone":"+32 2 633 32 72",
    "sg:postcode":"1380",
    "sg:province":"Brabant Wallon",
    "sg:tags":[
        "verzekeringsmakelaars",
        "expert"
    ],
    "wof:name":"Bureau Keustermans",
    "wof:placetype":"venue"
},
  "geometry": {"coordinates":[4.479031086,50.6739997864],"type":"Point"}
}