{
  "type": "Feature",
  "properties": {
    "addr:full":"Belikstraat 14 Heusden-zolder (zolder) Limburg 3550",
    "addr:housenumber":"14",
    "addr:postcode":"3550",
    "addr:street":"Belikstraat",
    "iso:country":"BE",
    "sg:address":"Belikstraat 14",
    "sg:city":"Heusden-zolder (zolder)",
    "sg:classifiers":[
        {
            "category":"Personal",
            "subcategory":"Beauty Salon",
            "type":"Services"
        }
    ],
    "sg:phone":"+32 11 53 68 62",
    "sg:postcode":"3550",
    "sg:province":"Limburg",
    "wof:name":"Prodessa",
    "wof:placetype":"venue"
},
  "geometry": {"coordinates":[5.2982230186,51.0105514526],"type":"Point"}
}