{
  "type": "Feature",
  "properties": {
    "iso:country":"BE",
    "sg:address":"Brusselsesteenweg 74",
    "sg:city":"Herent",
    "sg:classifiers":[
        {
            "category":"Autos & Motor Vehicles",
            "subcategory":"Automobile Sales",
            "type":"Retail Goods"
        }
    ],
    "sg:phone":"+32 16 49 04 90",
    "sg:postcode":"3020",
    "sg:province":"Vlaams-Brabant",
    "sg:tags":[
        "car",
        "used",
        "-"
    ],
    "wof:name":"Walton Garage Keustermans Bvba",
    "wof:placetype":"venue"
},
  "geometry": {"coordinates":[4.6603598595,50.8882598877],"type":"Point"}
}