{
  "type": "Feature",
  "properties": {
    "addr:full":"Smisstraat 36 Lanaken Limburg 3620",
    "addr:housenumber":"36",
    "addr:postcode":"3620",
    "addr:street":"Smisstraat",
    "iso:country":"BE",
    "sg:address":"Smisstraat 36",
    "sg:city":"Lanaken",
    "sg:orig_category":"Sportclubs Sportterreinen and installaties behalve sportcentra",
    "sg:phone":"+32 12 45 21 37",
    "sg:postcode":"3620",
    "sg:province":"Limburg",
    "wof:name":"V.c. Kesselt",
    "wof:placetype":"venue"
},
  "geometry": {"coordinates":[5.6290721893,50.8413352966],"type":"Point"}
}