{
  "type": "Feature",
  "properties": {
    "iso:country":"BE",
    "sg:address":"Kraanstraat 21",
    "sg:city":"Overpelt",
    "sg:orig_category":"Artsen and specialisten",
    "sg:phone":"+32 11 64 33 77",
    "sg:postcode":"3900",
    "sg:province":"Limburg",
    "wof:name":"Jozef Thys",
    "wof:placetype":"venue"
},
  "geometry": {"coordinates":[5.4059047699,51.1918296814],"type":"Point"}
}