{
  "type": "Feature",
  "properties": {
    "addr:full":"Rue Joirkin 10 Donceel Li\u00e8ge 4357",
    "addr:housenumber":"10",
    "addr:postcode":"4357",
    "addr:street":"Rue Joirkin",
    "iso:country":"BE",
    "sg:address":"Rue Joirkin 10",
    "sg:city":"Donceel",
    "sg:orig_category":"Drukkerijen and copyshops",
    "sg:phone":"+32 19 54 44 25",
    "sg:postcode":"4357",
    "sg:province":"Li\u00e8ge",
    "wof:name":"Hibou",
    "wof:placetype":"venue"
},
  "geometry": {"coordinates":[5.3201231956,50.6497001648],"type":"Point"}
}