{
  "type": "Feature",
  "properties": {
    "iso:country":"BE",
    "sg:address":"Nesteveldstraat 13",
    "sg:city":"Erpe-mere",
    "sg:orig_category":"Tuinen",
    "sg:phone":"+32 53 83 07 37",
    "sg:postcode":"9420",
    "sg:province":"Oost-Vlaanderen",
    "wof:name":"Martin Coppens",
    "wof:placetype":"venue"
},
  "geometry": {"coordinates":[3.9657659531,50.9259033203],"type":"Point"}
}