{
  "type": "Feature",
  "properties": {
    "iso:country":"BE",
    "sg:address":"Impasse Des Capucins 2 Box 2",
    "sg:city":"Namur",
    "sg:classifiers":[
        {
            "category":"Social Services",
            "type":"Services"
        }
    ],
    "sg:phone":"+32 81 22 89 11",
    "sg:postcode":"5000",
    "sg:province":"Namur",
    "wof:name":"Service Droit Des Jeunes",
    "wof:placetype":"venue"
},
  "geometry": {"coordinates":[4.866230011,50.4650001526],"type":"Point"}
}