{
  "type": "Feature",
  "properties": {
    "addr:full":"Binnenstraat 199-201 Aalst Oost-Vlaanderen 9300",
    "addr:housenumber":"199-201",
    "addr:postcode":"9300",
    "addr:street":"Binnenstraat",
    "iso:country":"BE",
    "sg:address":"Binnenstraat 199-201",
    "sg:city":"Aalst",
    "sg:classifiers":[
        {
            "category":"Bakery",
            "type":"Food & Drink"
        }
    ],
    "sg:phone":"+32 53 70 55 80",
    "sg:postcode":"9300",
    "sg:province":"Oost-Vlaanderen",
    "sg:tags":[
        "confectioner",
        "baker"
    ],
    "wof:name":"Koekestutje ('t)",
    "wof:placetype":"venue"
},
  "geometry": {"coordinates":[4.052503109,50.9479179382],"type":"Point"}
}