{
  "type": "Feature",
  "properties": {
    "addr:full":"Hendrik Consciencestraat 18 Mechelen Antwerpen 2800",
    "addr:housenumber":"18",
    "addr:postcode":"2800",
    "addr:street":"Hendrik Consciencestraat",
    "iso:country":"BE",
    "sg:address":"Hendrik Consciencestraat 18",
    "sg:city":"Mechelen",
    "sg:classifiers":[
        {
            "category":"Personal",
            "subcategory":"Beauty Salon",
            "type":"Services"
        }
    ],
    "sg:phone":"+32 15 27 81 81",
    "sg:postcode":"2800",
    "sg:province":"Antwerpen",
    "sg:tags":[
        "equipment",
        "hairdressing",
        "-",
        "supply"
    ],
    "wof:name":"Intercosmo Bvba",
    "wof:placetype":"venue"
},
  "geometry": {"coordinates":[4.4821839333,51.0194358826],"type":"Point"}
}