{
  "type": "Feature",
  "properties": {
    "iso:country":"BE",
    "sg:address":"Victorlaan 50",
    "sg:city":"Nieuwpoort",
    "sg:orig_category":"Eleveurs and marchands de porcs. Eleveurs de bovins",
    "sg:phone":"+32 58 23 40 79",
    "sg:postcode":"8620",
    "sg:province":"West-Vlaanderen",
    "wof:name":"Depotter-cloet",
    "wof:placetype":"venue"
},
  "geometry": {"coordinates":[2.7212450504,51.1369895935],"type":"Point"}
}