{
  "type": "Feature",
  "properties": {
    "addr:full":"Hoogmolenlaan 2 Kontich Antwerpen 2550",
    "addr:housenumber":"2",
    "addr:postcode":"2550",
    "addr:street":"Hoogmolenlaan",
    "iso:country":"BE",
    "sg:address":"Hoogmolenlaan 2",
    "sg:city":"Kontich",
    "sg:orig_category":"Artiesten and kunstenaars",
    "sg:phone":"+32 3 457 03 22",
    "sg:postcode":"2550",
    "sg:province":"Antwerpen",
    "wof:name":"Rudi Delhem",
    "wof:placetype":"venue"
},
  "geometry": {"coordinates":[4.4509677887,51.1419677734],"type":"Point"}
}