{
  "type": "Feature",
  "properties": {
    "addr:full":"Botermarkt 36-38 Diest Vlaams-Brabant 3290",
    "addr:postcode":"36-38;3290",
    "addr:street":"Botermarkt",
    "iso:country":"BE",
    "sg:address":"Botermarkt 36-38",
    "sg:city":"Diest",
    "sg:classifiers":[
        {
            "category":"Shopping",
            "subcategory":"Clothing, Apparel, & Fashions",
            "type":"Retail Goods"
        }
    ],
    "sg:phone":"+32 13 53 18 85",
    "sg:postcode":"3290",
    "sg:province":"Vlaams-Brabant",
    "sg:tags":[
        "lady",
        "clothing",
        "-"
    ],
    "wof:name":"Cassis Nv",
    "wof:placetype":"venue"
},
  "geometry": {"coordinates":[5.0518579483,50.9836387634],"type":"Point"}
}