{
  "type": "Feature",
  "properties": {
    "addr:full":"Chemin Des Meuniers 58 Walcourt (thy-le-ch\u00e2teau) Namur 5651",
    "addr:housenumber":"58",
    "addr:postcode":"5651",
    "addr:street":"Chemin Des Meuniers",
    "iso:country":"BE",
    "sg:address":"Chemin Des Meuniers 58",
    "sg:city":"Walcourt (thy-le-ch\u00e2teau)",
    "sg:classifiers":[
        {
            "category":"Airport",
            "subcategory":"International",
            "type":"Transportation"
        }
    ],
    "sg:phone":"+32 71 61 23 39",
    "sg:postcode":"5651",
    "sg:province":"Namur",
    "sg:tags":[
        "-",
        "transport"
    ],
    "wof:name":"Transtar Sc",
    "wof:placetype":"venue"
},
  "geometry": {"coordinates":[4.4262080193,50.2824401855],"type":"Point"}
}