{
  "type": "Feature",
  "properties": {
    "iso:country":"BE",
    "sg:address":"Prinsenmeers 2",
    "sg:city":"Dendermonde",
    "sg:orig_category":"Artsen and specialisten",
    "sg:phone":"+32 52 21 01 34",
    "sg:postcode":"9200",
    "sg:province":"Oost-Vlaanderen",
    "wof:name":"Marie-jeanne Van Biesen",
    "wof:placetype":"venue"
},
  "geometry": {"coordinates":[4.0932412148,51.0357971191],"type":"Point"}
}