{
  "type": "Feature",
  "properties": {
    "addr:full":"Rue Charnoy 28 Charleroi Hainaut 6000",
    "addr:housenumber":"28",
    "addr:postcode":"6000",
    "addr:street":"Rue Charnoy;Hainaut",
    "iso:country":"BE",
    "sg:address":"Rue Charnoy 28",
    "sg:city":"Charleroi",
    "sg:classifiers":[
        {
            "category":"Personal",
            "subcategory":"Beauty Salon",
            "type":"Services"
        }
    ],
    "sg:phone":"+32 71 31 32 34",
    "sg:postcode":"6000",
    "sg:province":"Hainaut",
    "sg:tags":[
        "product",
        "-",
        "apparatus"
    ],
    "wof:name":"Maison Du Coiffeur (la) Sprl",
    "wof:placetype":"venue"
},
  "geometry": {"coordinates":[4.4459581375,50.4119224548],"type":"Point"}
}