{
  "type": "Feature",
  "properties": {
    "iso:country":"BE",
    "sg:address":"Chauss\u00c9e De Couvin 41",
    "sg:city":"Chimay",
    "sg:orig_category":"Paramedische behandelingen",
    "sg:phone":"+32 60 21 43 55",
    "sg:postcode":"6460",
    "sg:province":"Hainaut",
    "wof:name":"A.s.d.",
    "wof:placetype":"venue"
},
  "geometry": {"coordinates":[4.3240971565,50.0465278625],"type":"Point"}
}