{
  "type": "Feature",
  "properties": {
    "addr:full":"Chauss\u00e9e Brunehault 130 Binche (p\u00e9ronnes-lez-binche) Hainaut 7134",
    "addr:housenumber":"130",
    "addr:postcode":"7134",
    "addr:street":"Chausse\u0301E Brunehault",
    "iso:country":"BE",
    "sg:address":"Chauss\u00e9e Brunehault 130",
    "sg:city":"Binche (p\u00e9ronnes-lez-binche)",
    "sg:classifiers":[
        {
            "category":"Utilities",
            "subcategory":"Fuel Oil & Lpg",
            "type":"Services"
        }
    ],
    "sg:phone":"+32 64 36 73 72",
    "sg:postcode":"7134",
    "sg:province":"Hainaut",
    "wof:name":"Superma Sprl",
    "wof:placetype":"venue"
},
  "geometry": {"coordinates":[4.1797719002,50.4269294739],"type":"Point"}
}