{
  "type": "Feature",
  "properties": {
    "addr:full":"Goubaudreef 5 Beveren (beveren-waas) Oost-Vlaanderen 9120",
    "addr:housenumber":"5",
    "addr:postcode":"9120",
    "addr:street":"Goubaudreef;Oost-Vlaanderen",
    "iso:country":"BE",
    "sg:address":"Goubaudreef 5",
    "sg:city":"Beveren (beveren-waas)",
    "sg:classifiers":[
        {
            "category":"Retail",
            "subcategory":"Repair Shop",
            "type":"Services"
        }
    ],
    "sg:phone":"+32 3 755 38 81",
    "sg:postcode":"9120",
    "sg:province":"Oost-Vlaanderen",
    "sg:tags":[
        "upholsterer"
    ],
    "wof:name":"Baert Gebr",
    "wof:placetype":"venue"
},
  "geometry": {"coordinates":[4.2639188766,51.2114067078],"type":"Point"}
}