{
  "type": "Feature",
  "properties": {
    "addr:full":"Rue Hoyoux 118 Herstal Li\u00e8ge 4040",
    "addr:housenumber":"118",
    "addr:postcode":"4040",
    "addr:street":"Rue Hoyoux",
    "iso:country":"BE",
    "sg:address":"Rue Hoyoux 118",
    "sg:city":"Herstal",
    "sg:orig_category":"Yamaha. R\u00e9parations and entretien de motos. Motos",
    "sg:phone":"+32 4 264 16 35",
    "sg:postcode":"4040",
    "sg:province":"Li\u00e8ge",
    "wof:name":"J.v.m. Moto S.a.",
    "wof:placetype":"venue"
},
  "geometry": {"coordinates":[5.6255970001,50.6610031128],"type":"Point"}
}