{
  "type": "Feature",
  "properties": {
    "addr:full":"Avenue Du Ch\u00c2teau 65 Sint-jans-molenbeek/molenbeek-saint-jean Bruxelles-Capitale 1080",
    "addr:housenumber":"65",
    "addr:postcode":"1080",
    "addr:street":"Avenue Du Cha\u0302Teau",
    "iso:country":"BE",
    "sg:address":"Avenue Du Ch\u00c2teau 65",
    "sg:city":"Sint-jans-molenbeek/molenbeek-saint-jean",
    "sg:orig_category":"Enseignement maternel and primaire",
    "sg:phone":"+32 2 468 16 16",
    "sg:postcode":"1080",
    "sg:province":"Bruxelles-Capitale",
    "wof:name":"Basisschool",
    "wof:placetype":"venue"
},
  "geometry": {"coordinates":[4.3126702309,50.8638381958],"type":"Point"}
}