{
  "type": "Feature",
  "properties": {
    "iso:country":"BE",
    "sg:address":"Aartrijksesteenweg 167",
    "sg:city":"Jabbeke",
    "sg:classifiers":[
        {
            "category":"Bars & Pubs",
            "type":"Food & Drink"
        }
    ],
    "sg:phone":"+32 50 81 43 66",
    "sg:postcode":"8490",
    "sg:province":"West-Vlaanderen",
    "wof:name":"Le Papillon",
    "wof:placetype":"venue"
},
  "geometry": {"coordinates":[3.0846300125,51.163860321],"type":"Point"}
}