{
  "type": "Feature",
  "properties": {
    "iso:country":"BE",
    "sg:address":"Diepestraat 113",
    "sg:city":"Antwerpen",
    "sg:orig_category":"Banques and organismes de cr\u00e9dit",
    "sg:phone":"+32 3 235 58 36",
    "sg:postcode":"2060",
    "sg:province":"Antwerpen",
    "wof:name":"Bbl",
    "wof:placetype":"venue"
},
  "geometry": {"coordinates":[4.4259281158,51.2227592468],"type":"Point"}
}