{
  "type": "Feature",
  "properties": {
    "addr:full":"Julius Hostestraat 47 Schaarbeek/schaerbeek Bruxelles-Capitale 1030",
    "addr:housenumber":"47",
    "addr:postcode":"1030",
    "addr:street":"Julius Hostestraat",
    "iso:country":"BE",
    "sg:address":"Julius Hostestraat 47",
    "sg:city":"Schaarbeek/schaerbeek",
    "sg:orig_category":"Boekhouders",
    "sg:phone":"+32 2 215 03 31",
    "sg:postcode":"1030",
    "sg:province":"Bruxelles-Capitale",
    "wof:name":"Leopold Schiemsky",
    "wof:placetype":"venue"
},
  "geometry": {"coordinates":[4.3944740295,50.8673286438],"type":"Point"}
}