{
  "type": "Feature",
  "properties": {
    "iso:country":"BE",
    "sg:address":"Rue Henri Francotte 52",
    "sg:city":"Dalhem",
    "sg:orig_category":"Traitements param\u00e9dicaux",
    "sg:phone":"+32 4 379 65 39",
    "sg:postcode":"4607",
    "sg:province":"Li\u00e8ge",
    "wof:name":"L. Gordos",
    "wof:placetype":"venue"
},
  "geometry": {"coordinates":[5.720307827,50.715549469],"type":"Point"}
}