{
  "type": "Feature",
  "properties": {
    "addr:full":"Koning Albertlei 141 Kapellen Antwerpen 2950",
    "addr:housenumber":"141",
    "addr:postcode":"2950",
    "addr:street":"Koning Albertlei",
    "iso:country":"BE",
    "sg:address":"Koning Albertlei 141",
    "sg:city":"Kapellen",
    "sg:orig_category":"Mat\u00e9riel m\u00e9dical and orthop\u00e9dique and proth\u00e8ses Fab",
    "sg:phone":"+32 3 605 59 79",
    "sg:postcode":"2950",
    "sg:province":"Antwerpen",
    "wof:name":"A.b.dental",
    "wof:placetype":"venue"
},
  "geometry": {"coordinates":[4.4365200996,51.3196296692],"type":"Point"}
}