{
  "type": "Feature",
  "properties": {
    "iso:country":"BE",
    "sg:address":"Machelenstraat 169",
    "sg:city":"Deinze",
    "sg:orig_category":"Traitement and rev\u00eatement des m\u00e9taux. Entreprises de travail adapt\u00e9",
    "sg:phone":"+32 9 386 33 29",
    "sg:postcode":"9800",
    "sg:province":"Oost-Vlaanderen",
    "wof:name":"Besch. Werkplaats Demival",
    "wof:placetype":"venue"
},
  "geometry": {"coordinates":[3.5242800713,50.9765892029],"type":"Point"}
}