{
  "type": "Feature",
  "properties": {
    "iso:country":"BE",
    "sg:address":"Warandelaan 145",
    "sg:city":"Vilvoorde",
    "sg:orig_category":"Woningbouw",
    "sg:phone":"+32 2 267 92 64",
    "sg:postcode":"1800",
    "sg:province":"Vlaams-Brabant",
    "wof:name":"Mecawat",
    "wof:placetype":"venue"
},
  "geometry": {"coordinates":[4.3684201241,50.9020500183],"type":"Point"}
}