{
  "type": "Feature",
  "properties": {
    "addr:full":"Eichemstraat 76a Ninove Oost-Vlaanderen 9400",
    "addr:housenumber":"76a",
    "addr:postcode":"9400",
    "addr:street":"Eichemstraat",
    "iso:country":"BE",
    "sg:address":"Eichemstraat 76a",
    "sg:city":"Ninove",
    "sg:classifiers":[
        {
            "category":"Personal",
            "subcategory":"Beauty Salon",
            "type":"Services"
        }
    ],
    "sg:phone":"+32 54 34 35 67",
    "sg:postcode":"9400",
    "sg:province":"Oost-Vlaanderen",
    "sg:tags":[
        "de",
        "coiffure"
    ],
    "wof:name":"Ykara",
    "wof:placetype":"venue"
},
  "geometry": {"coordinates":[4.0232000351,50.8349113464],"type":"Point"}
}