{
  "type": "Feature",
  "properties": {
    "iso:country":"BE",
    "sg:address":"Gierlesteenweg 113",
    "sg:city":"Turnhout",
    "sg:classifiers":[
        {
            "category":"Restaurant",
            "type":"Food & Drink"
        }
    ],
    "sg:phone":"+32 14 43 55 30",
    "sg:postcode":"2300",
    "sg:province":"Antwerpen",
    "wof:name":"De Rekruut",
    "wof:placetype":"venue"
},
  "geometry": {"coordinates":[4.9316749573,51.3157272339],"type":"Point"}
}