{
  "type": "Feature",
  "properties": {
    "addr:full":"Kammerstraat 43 Gent Oost-Vlaanderen 9000",
    "addr:housenumber":"43",
    "addr:postcode":"9000",
    "addr:street":"Kammerstraat;Oost-Vlaanderen",
    "iso:country":"BE",
    "sg:address":"Kammerstraat 43",
    "sg:city":"Gent",
    "sg:orig_category":"Binnenhuisarchitecten",
    "sg:phone":"+32 9 223 69 23",
    "sg:postcode":"9000",
    "sg:province":"Oost-Vlaanderen",
    "wof:name":"Yves De Moor",
    "wof:placetype":"venue"
},
  "geometry": {"coordinates":[3.7277300358,51.0556945801],"type":"Point"}
}