{
  "type": "Feature",
  "properties": {
    "iso:country":"BE",
    "sg:address":"Slakweidestraat 16",
    "sg:city":"Maasmechelen",
    "sg:orig_category":"Loodgieterij, verwarming and sanitaire installaties",
    "sg:phone":"+32 89 77 72 36",
    "sg:postcode":"3630",
    "sg:province":"Limburg",
    "wof:name":"Brouwers Zink",
    "wof:placetype":"venue"
},
  "geometry": {"coordinates":[5.7029619217,50.950428009],"type":"Point"}
}