{
  "type": "Feature",
  "properties": {
    "addr:full":"Avenue Du Globe 41 Bruxelles (forest) Bruxelles-Capitale 1190",
    "addr:housenumber":"41",
    "addr:postcode":"1190",
    "addr:street":"Avenue Du Globe",
    "iso:country":"BE",
    "sg:address":"Avenue Du Globe 41",
    "sg:city":"Bruxelles (forest)",
    "sg:classifiers":[
        {
            "category":"Professional",
            "subcategory":"Management & Consulting",
            "type":"Services"
        }
    ],
    "sg:phone":"+32 2 347 12 72",
    "sg:postcode":"1190",
    "sg:province":"Bruxelles-Capitale",
    "sg:tags":[
        "consultant",
        "promotion",
        "-",
        "sale"
    ],
    "wof:name":"Rhino Promotion",
    "wof:placetype":"venue"
},
  "geometry": {"coordinates":[4.3247637749,50.8095855713],"type":"Point"}
}