{
  "type": "Feature",
  "properties": {
    "iso:country":"BE",
    "sg:address":"Brugstraat 41",
    "sg:city":"Brecht (sint-job-in-'t Goor)",
    "sg:classifiers":[
        {
            "category":"Travel",
            "subcategory":"Hotels & Motels",
            "type":"Entertainment"
        }
    ],
    "sg:phone":"+32 3 353 67 03",
    "sg:postcode":"2960",
    "sg:province":"Antwerpen",
    "sg:tags":[
        "supply",
        "hotels",
        "catering"
    ],
    "wof:name":"Kima Bvba",
    "wof:placetype":"venue"
},
  "geometry": {"coordinates":[4.5757980347,51.2943496704],"type":"Point"}
}