{
  "type": "Feature",
  "properties": {
    "iso:country":"BE",
    "sg:address":"Molenhofstraat 25",
    "sg:city":"Pepingen (heikruis)",
    "sg:classifiers":[
        {
            "category":"Health Services",
            "subcategory":"Nursing And Care Facility",
            "type":"Services"
        }
    ],
    "sg:phone":"+32 2 396 12 60",
    "sg:postcode":"1670",
    "sg:province":"Vlaams-Brabant",
    "sg:tags":[
        "home",
        "rest"
    ],
    "wof:name":"Mater Dei Vzw",
    "wof:placetype":"venue"
},
  "geometry": {"coordinates":[4.1136307716,50.7334365845],"type":"Point"}
}