{
  "type": "Feature",
  "properties": {
    "iso:country":"BE",
    "sg:address":"Duisburgstraat 7ba",
    "sg:city":"Overijse",
    "sg:orig_category":"Rev\u00eatements pour sols and murs. Peinture",
    "sg:phone":"+32 2 687 20 06",
    "sg:postcode":"3090",
    "sg:province":"Vlaams-Brabant",
    "wof:name":"Gudeco",
    "wof:placetype":"venue"
},
  "geometry": {"coordinates":[4.5507698059,50.8021430969],"type":"Point"}
}