{
  "type": "Feature",
  "properties": {
    "addr:full":"August De Boeckstraat 9 Merchtem Vlaams-Brabant 1785",
    "addr:housenumber":"9",
    "addr:postcode":"1785",
    "addr:street":"August De Boeckstraat",
    "iso:country":"BE",
    "sg:address":"August De Boeckstraat 9",
    "sg:city":"Merchtem",
    "sg:orig_category":"Journaux",
    "sg:phone":"+32 52 37 08 12",
    "sg:postcode":"1785",
    "sg:province":"Vlaams-Brabant",
    "wof:name":"Press Shop",
    "wof:placetype":"venue"
},
  "geometry": {"coordinates":[4.2281661034,50.9596443176],"type":"Point"}
}