{
  "type": "Feature",
  "properties": {
    "addr:full":"Rue Fernand Stilman Farciennes Hainaut 6240",
    "addr:postcode":"6240",
    "addr:street":"Rue Fernand Stilman;Hainaut",
    "iso:country":"BE",
    "sg:address":"Rue Fernand Stilman",
    "sg:city":"Farciennes",
    "sg:orig_category":"V\u00e9los",
    "sg:phone":"+32 71 38 58 32",
    "sg:postcode":"6240",
    "sg:province":"Hainaut",
    "wof:name":"Robert Janssens",
    "wof:placetype":"venue"
},
  "geometry": {"coordinates":[4.5293421745,50.4221611023],"type":"Point"}
}