{
  "type": "Feature",
  "properties": {
    "addr:full":"Antwerpsesteenweg 28 Mechelen Antwerpen 2800",
    "addr:housenumber":"28",
    "addr:postcode":"2800",
    "addr:street":"Antwerpsesteenweg",
    "iso:country":"BE",
    "sg:address":"Antwerpsesteenweg 28",
    "sg:city":"Mechelen",
    "sg:orig_category":"Boekhouders",
    "sg:phone":"+32 15 20 46 55",
    "sg:postcode":"2800",
    "sg:province":"Antwerpen",
    "wof:name":"Pieter Goovaerts",
    "wof:placetype":"venue"
},
  "geometry": {"coordinates":[4.4710979462,51.0420761108],"type":"Point"}
}