{
  "type": "Feature",
  "properties": {
    "addr:full":"Centrumlaan 44 Ninove Oost-Vlaanderen 9400",
    "addr:housenumber":"44",
    "addr:postcode":"9400",
    "addr:street":"Centrumlaan",
    "iso:country":"BE",
    "sg:address":"Centrumlaan 44",
    "sg:city":"Ninove",
    "sg:classifiers":[
        {
            "category":"Shopping",
            "subcategory":"Clothing, Apparel, & Fashions",
            "type":"Retail Goods"
        }
    ],
    "sg:phone":"+32 54 33 82 12",
    "sg:postcode":"9400",
    "sg:province":"Oost-Vlaanderen",
    "sg:tags":[
        "sportswear"
    ],
    "wof:name":"Extra Time Sport",
    "wof:placetype":"venue"
},
  "geometry": {"coordinates":[4.0213398933,50.8344306946],"type":"Point"}
}