{
  "type": "Feature",
  "properties": {
    "addr:full":"Chemin Pont De Briques 1 Namur Namur 5100",
    "addr:housenumber":"1",
    "addr:postcode":"5100",
    "addr:street":"Chemin Pont De Briques",
    "iso:country":"BE",
    "sg:address":"Chemin Pont De Briques 1",
    "sg:city":"Namur",
    "sg:orig_category":"Sportclubs Sportterreinen and installaties behalve sportcentra",
    "sg:phone":"+32 81 23 04 92",
    "sg:postcode":"5100",
    "sg:province":"Namur",
    "wof:name":"G\u00c9ronsart F.c.",
    "wof:placetype":"venue"
},
  "geometry": {"coordinates":[4.8713750839,50.4566345215],"type":"Point"}
}