{
  "type": "Feature",
  "properties": {
    "iso:country":"BE",
    "sg:address":"Jacques Pasturlaan 114",
    "sg:city":"Ukkel/uccle",
    "sg:orig_category":"Landmeters and schatters",
    "sg:phone":"+32 2 375 50 02",
    "sg:postcode":"1180",
    "sg:province":"Bruxelles-Capitale",
    "wof:name":"Roland & Ass.",
    "wof:placetype":"venue"
},
  "geometry": {"coordinates":[4.3646512032,50.7850494385],"type":"Point"}
}