{
  "type": "Feature",
  "properties": {
    "addr:full":"Rue De Snaye 18 Beauraing Namur 5574",
    "addr:housenumber":"18",
    "addr:postcode":"5574",
    "addr:street":"Rue De Snaye",
    "iso:country":"BE",
    "sg:address":"Rue De Snaye 18",
    "sg:city":"Beauraing",
    "sg:orig_category":"Kapsalons",
    "sg:phone":"+32 82 71 35 16",
    "sg:postcode":"5574",
    "sg:province":"Namur",
    "wof:name":"Lurkin C",
    "wof:placetype":"venue"
},
  "geometry": {"coordinates":[5.0073828697,50.0972633362],"type":"Point"}
}