{
  "type": "Feature",
  "properties": {
    "iso:country":"BE",
    "sg:address":"Rue De La Station 65",
    "sg:city":"Le Roeulx",
    "sg:classifiers":[
        {
            "category":"Real Estate",
            "subcategory":"Architect",
            "type":"Services"
        }
    ],
    "sg:phone":"+32 64 67 72 81",
    "sg:postcode":"7070",
    "sg:province":"Hainaut",
    "wof:name":"D'hondt V",
    "wof:placetype":"venue"
},
  "geometry": {"coordinates":[4.1149148941,50.5060195923],"type":"Point"}
}