{
  "type": "Feature",
  "properties": {
    "iso:country":"BE",
    "sg:address":"Geelsebaan 155",
    "sg:city":"Tessenderlo",
    "sg:classifiers":[
        {
            "category":"Shopping",
            "subcategory":"Bicycles & Sporting Goods",
            "type":"Retail Goods"
        }
    ],
    "sg:phone":"+32 13 66 74 60",
    "sg:postcode":"3980",
    "sg:province":"Limburg",
    "sg:tags":[
        "sport",
        "-"
    ],
    "wof:name":"Ren-sport",
    "wof:placetype":"venue"
},
  "geometry": {"coordinates":[5.0773730278,51.0777359009],"type":"Point"}
}