{
  "type": "Feature",
  "properties": {
    "addr:full":"Dendermondsesteenweg 17 Willebroek Antwerpen 2830",
    "addr:housenumber":"17",
    "addr:postcode":"2830",
    "addr:street":"Dendermondsesteenweg",
    "iso:country":"BE",
    "sg:address":"Dendermondsesteenweg 17",
    "sg:city":"Willebroek",
    "sg:orig_category":"Diverse kredietdiensten",
    "sg:postcode":"2830",
    "sg:province":"Antwerpen",
    "wof:name":"Bancontact-mister Cash",
    "wof:placetype":"venue"
},
  "geometry": {"coordinates":[4.3592071533,51.0604019165],"type":"Point"}
}