{
  "type": "Feature",
  "properties": {
    "iso:country":"BE",
    "sg:address":"Rue De L'avenir 5",
    "sg:city":"Gr\u00e2ce-hollogne (gr\u00e2ce-berleur)",
    "sg:classifiers":[
        {
            "category":"Building & Trades",
            "subcategory":"Construction",
            "type":"Services"
        }
    ],
    "sg:phone":"+32 4 263 32 47",
    "sg:postcode":"4460",
    "sg:province":"Li\u00e8ge",
    "sg:tags":[
        "installation",
        "-",
        "central",
        "heating"
    ],
    "wof:name":"Energies & Maintenance Service Sa",
    "wof:placetype":"venue"
},
  "geometry": {"coordinates":[5.4945192337,50.6541366577],"type":"Point"}
}