{
  "type": "Feature",
  "properties": {
    "iso:country":"BE",
    "sg:address":"Leenstraat 110",
    "sg:city":"Izegem",
    "sg:orig_category":"Enseignement maternel and primaire",
    "sg:phone":"+32 51 30 21 26",
    "sg:postcode":"8870",
    "sg:province":"West-Vlaanderen",
    "wof:name":"Vrije Basisschool",
    "wof:placetype":"venue"
},
  "geometry": {"coordinates":[3.193516016,50.9041061401],"type":"Point"}
}