{
  "type": "Feature",
  "properties": {
    "addr:full":"Aarlenstraat 53 Box 4 Bruxelles (etterbeek) Bruxelles-Capitale 1040",
    "addr:housenumber":"53;4",
    "addr:postcode":"1040",
    "addr:street":"Aarlenstraat;Box",
    "iso:country":"BE",
    "sg:address":"Aarlenstraat 53 Box 4",
    "sg:city":"Bruxelles (etterbeek)",
    "sg:classifiers":[
        {
            "category":"Utilities",
            "subcategory":"Telephone",
            "type":"Services"
        }
    ],
    "sg:phone":"+32 2 233 31 43",
    "sg:postcode":"1040",
    "sg:province":"Bruxelles-Capitale",
    "sg:tags":[
        "addressing",
        "mailing"
    ],
    "wof:name":"Pinakes Nv",
    "wof:placetype":"venue"
},
  "geometry": {"coordinates":[4.373691082,50.8418617249],"type":"Point"}
}