{
  "type": "Feature",
  "properties": {
    "iso:country":"BE",
    "sg:address":"Grande Route De Ciney 43",
    "sg:city":"Dinant",
    "sg:orig_category":"Entretien and r\u00e9parations de voitures",
    "sg:phone":"+32 82 22 35 56",
    "sg:postcode":"5500",
    "sg:province":"Namur",
    "wof:name":"Garage Ophrey",
    "wof:placetype":"venue"
},
  "geometry": {"coordinates":[4.9119329453,50.2604866028],"type":"Point"}
}