{
  "type": "Feature",
  "properties": {
    "iso:country":"BE",
    "sg:address":"Beernegemstraat 43",
    "sg:city":"Tielt",
    "sg:classifiers":[
        {
            "category":"Food & Beverages",
            "subcategory":"Groceries & Convenience Stores",
            "type":"Retail Goods"
        }
    ],
    "sg:phone":"+32 51 40 51 23",
    "sg:postcode":"8700",
    "sg:province":"West-Vlaanderen",
    "sg:tags":[
        "grocer"
    ],
    "wof:name":"Vers Hoeksken ('t)",
    "wof:placetype":"venue"
},
  "geometry": {"coordinates":[3.3333499432,50.994556427],"type":"Point"}
}