{
  "type": "Feature",
  "properties": {
    "iso:country":"BE",
    "sg:address":"Hoog Heultje 1",
    "sg:city":"Heultje",
    "sg:orig_category":"Entretien and r\u00e9parations de voitures. V\u00e9hicules automobiles",
    "sg:phone":"+32 16 69 83 70",
    "sg:postcode":"2260",
    "sg:province":"Antwerpen",
    "wof:name":"Garage Aerts",
    "wof:placetype":"venue"
},
  "geometry": {"coordinates":[4.8356451988,51.0725898743],"type":"Point"}
}