{
  "type": "Feature",
  "properties": {
    "addr:full":"Vleeshouwersstraat 17 Antwerpen Antwerpen 2000",
    "addr:housenumber":"17",
    "addr:postcode":"2000",
    "addr:street":"Vleeshouwersstraat",
    "iso:country":"BE",
    "sg:address":"Vleeshouwersstraat 17",
    "sg:city":"Antwerpen",
    "sg:classifiers":[
        {
            "category":"Bars & Pubs",
            "type":"Food & Drink"
        }
    ],
    "sg:phone":"+32 3 232 89 96",
    "sg:postcode":"2000",
    "sg:province":"Antwerpen",
    "wof:name":"Ruckers",
    "wof:placetype":"venue"
},
  "geometry": {"coordinates":[4.3999361992,51.2230606079],"type":"Point"}
}