{
  "type": "Feature",
  "properties": {
    "addr:full":"Lochtingstraat 4 Evergem Oost-Vlaanderen 9940",
    "addr:housenumber":"4",
    "addr:postcode":"9940",
    "addr:street":"Lochtingstraat;Oost-Vlaanderen",
    "iso:country":"BE",
    "sg:address":"Lochtingstraat 4",
    "sg:city":"Evergem",
    "sg:orig_category":"Peinture. Rev\u00eatements pour sols and murs",
    "sg:phone":"+32 9 253 27 46",
    "sg:postcode":"9940",
    "sg:province":"Oost-Vlaanderen",
    "wof:name":"Luc Brenders",
    "wof:placetype":"venue"
},
  "geometry": {"coordinates":[3.7620620728,51.1388282776],"type":"Point"}
}