{
  "type": "Feature",
  "properties": {
    "addr:full":"Noordschoteplein 13 Lo-reninge West-Vlaanderen 8647",
    "addr:housenumber":"13",
    "addr:postcode":"8647",
    "addr:street":"Noordschoteplein",
    "iso:country":"BE",
    "sg:address":"Noordschoteplein 13",
    "sg:city":"Lo-reninge",
    "sg:orig_category":"Rundveehouders",
    "sg:phone":"+32 51 54 42 27",
    "sg:postcode":"8647",
    "sg:province":"West-Vlaanderen",
    "wof:name":"Martial Deraedt",
    "wof:placetype":"venue"
},
  "geometry": {"coordinates":[2.810863018,50.9546203613],"type":"Point"}
}