{
  "type": "Feature",
  "properties": {
    "addr:full":"Akkerstraat 36 Dessel Antwerpen 2480",
    "addr:housenumber":"36",
    "addr:postcode":"2480",
    "addr:street":"Akkerstraat",
    "iso:country":"BE",
    "sg:address":"Akkerstraat 36",
    "sg:city":"Dessel",
    "sg:orig_category":"Rundveehouders",
    "sg:phone":"+32 14 37 02 80",
    "sg:postcode":"2480",
    "sg:province":"Antwerpen",
    "wof:name":"Karel Mertens",
    "wof:placetype":"venue"
},
  "geometry": {"coordinates":[5.1175560951,51.2482337952],"type":"Point"}
}