{
  "type": "Feature",
  "properties": {
    "iso:country":"BE",
    "sg:address":"Heikantstraat 152",
    "sg:city":"Schoten",
    "sg:classifiers":[
        {
            "category":"Cafe",
            "type":"Food & Drink"
        }
    ],
    "sg:phone":"+32 3 658 36 72",
    "sg:postcode":"2900",
    "sg:province":"Antwerpen",
    "sg:tags":[
        "caf\u00e9s"
    ],
    "wof:name":"Caf\u00c9 Wenduyne",
    "wof:placetype":"venue"
},
  "geometry": {"coordinates":[4.5105128288,51.2574996948],"type":"Point"}
}