{
  "type": "Feature",
  "properties": {
    "iso:country":"BE",
    "sg:address":"Chauss\u00e9e De Mons 436",
    "sg:city":"La Louvi\u00e8re (haine-saint-paul)",
    "sg:classifiers":[
        {
            "category":"Home & Garden",
            "subcategory":"Building Materials",
            "type":"Retail Goods"
        }
    ],
    "sg:phone":"+32 64 22 00 95",
    "sg:postcode":"7100",
    "sg:province":"Hainaut",
    "sg:tags":[
        "window"
    ],
    "wof:name":"Gosset Ent Sprl",
    "wof:placetype":"venue"
},
  "geometry": {"coordinates":[4.1995410919,50.4645805359],"type":"Point"}
}