{
  "type": "Feature",
  "properties": {
    "addr:full":"Rue Galliot 22 Namur Namur 5000",
    "addr:housenumber":"22",
    "addr:postcode":"5000",
    "addr:street":"Rue Galliot",
    "iso:country":"BE",
    "sg:address":"Rue Galliot 22",
    "sg:city":"Namur",
    "sg:classifiers":[
        {
            "category":"Health Services",
            "subcategory":"Doctor",
            "type":"Services"
        }
    ],
    "sg:phone":"+32 81 22 52 34",
    "sg:postcode":"5000",
    "sg:province":"Namur",
    "sg:tags":[
        "medicinephysicians",
        "surgeon"
    ],
    "wof:name":"Dubois J",
    "wof:placetype":"venue"
},
  "geometry": {"coordinates":[4.8677530289,50.4681816101],"type":"Point"}
}