{
  "type": "Feature",
  "properties": {
    "iso:country":"BE",
    "sg:address":"Roeselarestraat 9",
    "sg:city":"Hooglede",
    "sg:orig_category":"Reisbureaus",
    "sg:phone":"+32 51 22 30 31",
    "sg:postcode":"8830",
    "sg:province":"West-Vlaanderen",
    "wof:name":"Reizen Lefever",
    "wof:placetype":"venue"
},
  "geometry": {"coordinates":[3.0834109783,50.9774093628],"type":"Point"}
}