{
  "type": "Feature",
  "properties": {
    "iso:country":"BE",
    "sg:address":"Kerkstraat 36",
    "sg:city":"Diest (schaffen)",
    "sg:classifiers":[
        {
            "category":"Health Services",
            "subcategory":"Health Practitioner",
            "type":"Services"
        }
    ],
    "sg:phone":"+32 13 32 57 34",
    "sg:postcode":"3290",
    "sg:province":"Vlaams-Brabant",
    "sg:tags":[
        "physiotherapist"
    ],
    "wof:name":"Courant Cath\u00e9rine",
    "wof:placetype":"venue"
},
  "geometry": {"coordinates":[5.0811347961,51.0025634766],"type":"Point"}
}