{
  "type": "Feature",
  "properties": {
    "iso:country":"BE",
    "sg:address":"Avenue Wilmart 78",
    "sg:city":"Perwez",
    "sg:orig_category":"Kapsalons",
    "sg:phone":"+32 81 65 82 25",
    "sg:postcode":"1360",
    "sg:province":"Brabant Wallon",
    "wof:name":"Isabelle Coiffure",
    "wof:placetype":"venue"
},
  "geometry": {"coordinates":[4.8224749565,50.625541687],"type":"Point"}
}