{
  "type": "Feature",
  "properties": {
    "iso:country":"BE",
    "sg:address":"Eekhoornlaan 43",
    "sg:city":"Dilsen-stokkem",
    "sg:classifiers":[
        {
            "category":"Building & Trades",
            "subcategory":"Landscaping Services",
            "type":"Services"
        }
    ],
    "sg:phone":"+32 89 79 14 21",
    "sg:postcode":"3650",
    "sg:province":"Limburg",
    "sg:tags":[
        "forestry"
    ],
    "wof:name":"Jeurissen",
    "wof:placetype":"venue"
},
  "geometry": {"coordinates":[5.7202119827,51.0664978027],"type":"Point"}
}