{
  "type": "Feature",
  "properties": {
    "iso:country":"BE",
    "sg:address":"Van Hesedreef 51",
    "sg:city":"Zele",
    "sg:classifiers":[
        {
            "category":"Personal",
            "subcategory":"Psychics & Astrologers",
            "type":"Services"
        }
    ],
    "sg:phone":"+32 52 44 53 26",
    "sg:postcode":"9240",
    "sg:province":"Oost-Vlaanderen",
    "sg:tags":[
        "astrology"
    ],
    "wof:name":"Nicole",
    "wof:placetype":"venue"
},
  "geometry": {"coordinates":[4.0292730331,51.0637245178],"type":"Point"}
}