{
  "type": "Feature",
  "properties": {
    "addr:full":"Rue L\u00e9on Delacroix 33-35 Bruxelles (anderlecht) Bruxelles-Capitale 1070",
    "addr:housenumber":"33-35",
    "addr:postcode":"1070",
    "addr:street":"Rue Le\u0301On Delacroix",
    "iso:country":"BE",
    "sg:address":"Rue L\u00e9on Delacroix 33-35",
    "sg:city":"Bruxelles (anderlecht)",
    "sg:classifiers":[
        {
            "category":"Building & Trades",
            "subcategory":"Construction",
            "type":"Services"
        }
    ],
    "sg:phone":"+32 2 411 53 49",
    "sg:postcode":"1070",
    "sg:province":"Bruxelles-Capitale",
    "sg:tags":[
        "installation",
        "-",
        "central",
        "heating"
    ],
    "wof:name":"A G A Services",
    "wof:placetype":"venue"
},
  "geometry": {"coordinates":[4.3292479515,50.8432617188],"type":"Point"}
}