{
  "type": "Feature",
  "properties": {
    "addr:full":"Kapellei 68 Zoersel Antwerpen 2980",
    "addr:housenumber":"68",
    "addr:postcode":"2980",
    "addr:street":"Kapellei",
    "iso:country":"BE",
    "sg:address":"Kapellei 68",
    "sg:city":"Zoersel",
    "sg:orig_category":"Entretien and r\u00e9parations de voitures",
    "sg:phone":"+32 3 383 14 50",
    "sg:postcode":"2980",
    "sg:province":"Antwerpen",
    "wof:name":"Carrosserie Vandijck",
    "wof:placetype":"venue"
},
  "geometry": {"coordinates":[4.6316270828,51.2616882324],"type":"Point"}
}