{
  "type": "Feature",
  "properties": {
    "addr:full":"Route Charlemagne 8 Chimay (baileux) Hainaut 6464",
    "addr:housenumber":"8",
    "addr:postcode":"6464",
    "addr:street":"Route Charlemagne",
    "iso:country":"BE",
    "sg:address":"Route Charlemagne 8",
    "sg:city":"Chimay (baileux)",
    "sg:classifiers":[
        {
            "category":"Brewery",
            "type":"Food & Drink"
        }
    ],
    "sg:phone":"+32 60 21 03 11",
    "sg:postcode":"6464",
    "sg:province":"Hainaut",
    "wof:name":"Bi\u00e8res De Chimay Sa",
    "wof:placetype":"venue"
},
  "geometry": {"coordinates":[4.3802218437,50.0355911255],"type":"Point"}
}