{
  "type": "Feature",
  "properties": {
    "iso:country":"BE",
    "sg:address":"Mont Saint-martin 92",
    "sg:city":"Li\u00c8ge",
    "sg:orig_category":"Instituts de beaut\u00e9",
    "sg:phone":"+32 4 226 36 66",
    "sg:postcode":"4000",
    "sg:province":"Li\u00e8ge",
    "wof:name":"Centre St.martin",
    "wof:placetype":"venue"
},
  "geometry": {"coordinates":[5.5657191277,50.619430542],"type":"Point"}
}