{
  "type": "Feature",
  "properties": {
    "iso:country":"BE",
    "sg:address":"Rue De Monsville 99",
    "sg:city":"Quaregnon",
    "sg:classifiers":[
        {
            "category":"Bakery",
            "type":"Food & Drink"
        }
    ],
    "sg:phone":"+32 65 78 63 85",
    "sg:postcode":"7390",
    "sg:province":"Hainaut",
    "sg:tags":[
        "confectioner",
        "baker"
    ],
    "wof:name":"Chambord",
    "wof:placetype":"venue"
},
  "geometry": {"coordinates":[3.8656380177,50.4388389587],"type":"Point"}
}