{
  "type": "Feature",
  "properties": {
    "addr:full":"Kleindokkaai 19 Gent Oost-Vlaanderen 9000",
    "addr:housenumber":"19",
    "addr:postcode":"9000",
    "addr:street":"Kleindokkaai;Oost-Vlaanderen",
    "iso:country":"BE",
    "sg:address":"Kleindokkaai 19",
    "sg:city":"Gent",
    "sg:classifiers":[
        {
            "category":"Professional",
            "subcategory":"Management & Consulting",
            "type":"Services"
        }
    ],
    "sg:phone":"+32 9 233 94 74",
    "sg:postcode":"9000",
    "sg:province":"Oost-Vlaanderen",
    "sg:tags":[
        "consultant",
        "agency",
        "advertising"
    ],
    "wof:name":"Claeys Consult",
    "wof:placetype":"venue"
},
  "geometry": {"coordinates":[3.7390100956,51.0597000122],"type":"Point"}
}