{
  "type": "Feature",
  "properties": {
    "addr:full":"Heuvelstraat 57b Tielt-winge Vlaams-Brabant 3390",
    "addr:housenumber":"57b",
    "addr:postcode":"3390",
    "addr:street":"Heuvelstraat",
    "iso:country":"BE",
    "sg:address":"Heuvelstraat 57b",
    "sg:city":"Tielt-winge",
    "sg:orig_category":"Banques and organismes de cr\u00e9dit",
    "sg:phone":"+32 16 63 16 75",
    "sg:postcode":"3390",
    "sg:province":"Vlaams-Brabant",
    "wof:name":"Groep Argenta",
    "wof:placetype":"venue"
},
  "geometry": {"coordinates":[4.9451799393,50.942150116],"type":"Point"}
}