{
  "type": "Feature",
  "properties": {
    "iso:country":"BE",
    "sg:address":"Kortemarkstraat 140",
    "sg:city":"Torhout",
    "sg:classifiers":[
        {
            "category":"Cafe",
            "type":"Food & Drink"
        }
    ],
    "sg:phone":"+32 50 21 18 42",
    "sg:postcode":"8820",
    "sg:province":"West-Vlaanderen",
    "sg:tags":[
        "caf\u00e9s"
    ],
    "wof:name":"Kurt Taillieu",
    "wof:placetype":"venue"
},
  "geometry": {"coordinates":[3.0898249149,51.0583572388],"type":"Point"}
}