{
  "type": "Feature",
  "properties": {
    "iso:country":"BE",
    "sg:address":"Tervuursesteenweg 582",
    "sg:city":"Bertem (leefdaal)",
    "sg:classifiers":[
        {
            "category":"Taxi",
            "type":"Transportation"
        }
    ],
    "sg:phone":"+32 2 767 11 01",
    "sg:postcode":"3061",
    "sg:province":"Vlaams-Brabant",
    "sg:tags":[
        "taxicab"
    ],
    "wof:name":"Speedy Taxi Services",
    "wof:placetype":"venue"
},
  "geometry": {"coordinates":[4.5762882233,50.850692749],"type":"Point"}
}