{
  "type": "Feature",
  "properties": {
    "addr:full":"Hilda Ramstraat 56 Antwerpen (berchem) Antwerpen 2600",
    "addr:housenumber":"56",
    "addr:postcode":"2600",
    "addr:street":"Ramstraat;Antwerpen",
    "iso:country":"BE",
    "sg:address":"Hilda Ramstraat 56",
    "sg:city":"Antwerpen (berchem)",
    "sg:classifiers":[
        {
            "category":"Professional",
            "subcategory":"Management & Consulting",
            "type":"Services"
        }
    ],
    "sg:phone":"+32 3 281 29 71",
    "sg:postcode":"2600",
    "sg:province":"Antwerpen",
    "sg:tags":[
        "consultant"
    ],
    "wof:name":"Maerten T & Partners",
    "wof:placetype":"venue"
},
  "geometry": {"coordinates":[4.4174151421,51.1974411011],"type":"Point"}
}