{
  "type": "Feature",
  "properties": {
    "iso:country":"BE",
    "sg:address":"Nieuwstraat 115",
    "sg:city":"Stekene",
    "sg:orig_category":"Installatie van houten of kunststof schrijnwerk Woningbouw",
    "sg:phone":"+32 3 779 88 73",
    "sg:postcode":"9190",
    "sg:province":"Oost-Vlaanderen",
    "wof:name":"Vercauteren Tony",
    "wof:placetype":"venue"
},
  "geometry": {"coordinates":[4.0560898781,51.2041549683],"type":"Point"}
}