{
  "type": "Feature",
  "properties": {
    "iso:country":"BE",
    "sg:address":"Rue Malibran 27",
    "sg:city":"Bruxelles (ixelles)",
    "sg:classifiers":[
        {
            "category":"Shopping",
            "subcategory":"Used Merchandise",
            "type":"Retail Goods"
        }
    ],
    "sg:phone":"+32 2 648 47 60",
    "sg:postcode":"1050",
    "sg:province":"Bruxelles-Capitale",
    "sg:tags":[
        "salvage",
        "surplus"
    ],
    "wof:name":"Uni Fad Sprl",
    "wof:placetype":"venue"
},
  "geometry": {"coordinates":[4.3729457855,50.8294754028],"type":"Point"}
}