{
  "type": "Feature",
  "properties": {
    "addr:full":"Lange Herentalsestraat 48 Box 4 Antwerpen Antwerpen 2018",
    "addr:housenumber":"48;4",
    "addr:postcode":"2018",
    "addr:street":"Lange Herentalsestraat;Box",
    "iso:country":"BE",
    "sg:address":"Lange Herentalsestraat 48 Box 4",
    "sg:city":"Antwerpen",
    "sg:classifiers":[
        {
            "category":"Shopping",
            "subcategory":"Jewelry",
            "type":"Retail Goods"
        }
    ],
    "sg:phone":"+32 3 232 69 67",
    "sg:postcode":"2018",
    "sg:province":"Antwerpen",
    "sg:tags":[
        "diamond",
        "-"
    ],
    "wof:name":"Ok\u00e9 Diamonds",
    "wof:placetype":"venue"
},
  "geometry": {"coordinates":[4.4173059464,51.214881897],"type":"Point"}
}