{
  "type": "Feature",
  "properties": {
    "iso:country":"BE",
    "sg:address":"Chauss\u00e9e D'enghien 158",
    "sg:city":"Tubize (saintes)",
    "sg:classifiers":[
        {
            "category":"Health Services",
            "subcategory":"Health Practitioner",
            "type":"Services"
        }
    ],
    "sg:phone":"+32 2 355 04 30",
    "sg:postcode":"1480",
    "sg:province":"Brabant Wallon",
    "sg:tags":[
        "physiotherapist"
    ],
    "wof:name":"Mazid Sa\u00efd",
    "wof:placetype":"venue"
},
  "geometry": {"coordinates":[4.165995121,50.7089233398],"type":"Point"}
}