{
  "type": "Feature",
  "properties": {
    "iso:country":"BE",
    "sg:address":"Oostveldstraat 276",
    "sg:city":"Eeklo",
    "sg:classifiers":[
        {
            "category":"Retail",
            "subcategory":"Veterinary Services",
            "type":"Services"
        }
    ],
    "sg:phone":"+32 9 377 05 77",
    "sg:postcode":"9900",
    "sg:province":"Oost-Vlaanderen",
    "sg:tags":[
        "veterinarian"
    ],
    "wof:name":"Geeraerts Ch Mevr",
    "wof:placetype":"venue"
},
  "geometry": {"coordinates":[3.5937099457,51.1821327209],"type":"Point"}
}