{
  "type": "Feature",
  "properties": {
    "addr:full":"Rue Des Zolos 11 Fosses-la-ville Namur 5070",
    "addr:housenumber":"11",
    "addr:postcode":"5070",
    "addr:street":"Rue Des Zolos",
    "iso:country":"BE",
    "sg:address":"Rue Des Zolos 11",
    "sg:city":"Fosses-la-ville",
    "sg:orig_category":"V\u00e9hicules automobiles. Entretien and r\u00e9parations de voitures",
    "sg:phone":"+32 71 71 30 65",
    "sg:postcode":"5070",
    "sg:province":"Namur",
    "wof:name":"Carrosserie Populaire",
    "wof:placetype":"venue"
},
  "geometry": {"coordinates":[4.6992378235,50.3970184326],"type":"Point"}
}