{
  "type": "Feature",
  "properties": {
    "addr:full":"Jan De Cerfstraat 54 Ieper (vlamertinge) West-Vlaanderen 8908",
    "addr:housenumber":"54",
    "addr:postcode":"8908",
    "addr:street":"Jan De Cerfstraat",
    "iso:country":"BE",
    "sg:address":"Jan De Cerfstraat 54",
    "sg:city":"Ieper (vlamertinge)",
    "sg:classifiers":[
        {
            "category":"Autos & Motor Vehicles",
            "subcategory":"Automobile Sales",
            "type":"Retail Goods"
        }
    ],
    "sg:phone":"+32 57 20 67 79",
    "sg:postcode":"8908",
    "sg:province":"West-Vlaanderen",
    "sg:tags":[
        "car",
        "used",
        "-"
    ],
    "wof:name":"Podevijn",
    "wof:placetype":"venue"
},
  "geometry": {"coordinates":[2.8237280846,50.8557052612],"type":"Point"}
}