{
  "type": "Feature",
  "properties": {
    "addr:full":"Ernest Claeslaan 44 Torhout West-Vlaanderen 8820",
    "addr:housenumber":"44",
    "addr:postcode":"8820",
    "addr:street":"Ernest Claeslaan",
    "iso:country":"BE",
    "sg:address":"Ernest Claeslaan 44",
    "sg:city":"Torhout",
    "sg:classifiers":[
        {
            "category":"Professional",
            "subcategory":"Art Services",
            "type":"Services"
        }
    ],
    "sg:phone":"+32 496 26 33 96",
    "sg:postcode":"8820",
    "sg:province":"West-Vlaanderen",
    "sg:tags":[
        "designer",
        "display"
    ],
    "wof:name":"Sheila",
    "wof:placetype":"venue"
},
  "geometry": {"coordinates":[3.1179189682,51.0707969666],"type":"Point"}
}