{
  "type": "Feature",
  "properties": {
    "iso:country":"BE",
    "sg:address":"Oude Heirweg 18",
    "sg:city":"Moorslede",
    "sg:orig_category":"Eleveurs de bovins",
    "sg:phone":"+32 56 50 90 77",
    "sg:postcode":"8890",
    "sg:province":"West-Vlaanderen",
    "wof:name":"Geert Goddeeris",
    "wof:placetype":"venue"
},
  "geometry": {"coordinates":[3.1061630249,50.8895378113],"type":"Point"}
}