{
  "type": "Feature",
  "properties": {
    "iso:country":"BE",
    "sg:address":"Jacob Jordaensstraat 118",
    "sg:city":"Antwerpen",
    "sg:classifiers":[
        {
            "category":"Communications",
            "subcategory":"Film & Video Production",
            "type":"Services"
        }
    ],
    "sg:phone":"+32 475 31 41 93",
    "sg:postcode":"2018",
    "sg:province":"Antwerpen",
    "sg:tags":[
        "multimedia",
        "-",
        "system"
    ],
    "wof:name":"Jara Productions Bvba",
    "wof:placetype":"venue"
},
  "geometry": {"coordinates":[4.4131088257,51.2081565857],"type":"Point"}
}