{
  "type": "Feature",
  "properties": {
    "iso:country":"BE",
    "sg:address":"Avenue De La Foret 190",
    "sg:city":"Bruxelles",
    "sg:classifiers":[
        {
            "category":"Personal",
            "subcategory":"Skin Care",
            "type":"Services"
        }
    ],
    "sg:phone":"+32 2 672 63 98",
    "sg:postcode":"1000",
    "sg:province":"Bruxelles-Capitale",
    "sg:tags":[
        "personnel",
        "recruitment"
    ],
    "wof:name":"Lecl\u00e8re M. & Consultants S.a.",
    "wof:placetype":"venue"
},
  "geometry": {"coordinates":[4.3958740234,50.7980690002],"type":"Point"}
}