{
  "type": "Feature",
  "properties": {
    "addr:full":"Vliegveldlaan 65 Sint-truiden Limburg 3800",
    "addr:housenumber":"65",
    "addr:postcode":"3800",
    "addr:street":"Vliegveldlaan",
    "iso:country":"BE",
    "sg:address":"Vliegveldlaan 65",
    "sg:city":"Sint-truiden",
    "sg:orig_category":"Installatie van metalen schrijnwerk",
    "sg:phone":"+32 11 68 56 54",
    "sg:postcode":"3800",
    "sg:province":"Limburg",
    "wof:name":"Grommen-vandenborne",
    "wof:placetype":"venue"
},
  "geometry": {"coordinates":[5.2144551277,50.8030052185],"type":"Point"}
}