{
  "type": "Feature",
  "properties": {
    "addr:full":"Holstraat 8 Londerzeel Vlaams-Brabant 1840",
    "addr:housenumber":"8",
    "addr:postcode":"1840",
    "addr:street":"Holstraat",
    "iso:country":"BE",
    "sg:address":"Holstraat 8",
    "sg:city":"Londerzeel",
    "sg:orig_category":"Agences d'exp\u00e9dition",
    "sg:phone":"+32 52 34 06 01",
    "sg:postcode":"1840",
    "sg:province":"Vlaams-Brabant",
    "wof:name":"Jansen Ex-tra",
    "wof:placetype":"venue"
},
  "geometry": {"coordinates":[4.2384848595,51.016166687],"type":"Point"}
}