{
  "type": "Feature",
  "properties": {
    "iso:country":"BE",
    "sg:address":"Karperstraat 12",
    "sg:city":"Machelen-zulte",
    "sg:orig_category":"Balie van Gent. Avocats and conseillers juridiques. Avocats and conseillers juridiques",
    "sg:phone":"+32 9 386 02 56",
    "sg:postcode":"9870",
    "sg:province":"Oost-Vlaanderen",
    "wof:name":"Claus Inge",
    "wof:placetype":"venue"
},
  "geometry": {"coordinates":[3.4436409473,50.921661377],"type":"Point"}
}