{
  "type": "Feature",
  "properties": {
    "iso:country":"BE",
    "sg:address":"Lannois 80",
    "sg:city":"Celles",
    "sg:orig_category":"Artiesten and kunstenaars Dierenartsen",
    "sg:phone":"+32 69 45 62 22",
    "sg:postcode":"7760",
    "sg:province":"Hainaut",
    "wof:name":"Helene Quairiat",
    "wof:placetype":"venue"
},
  "geometry": {"coordinates":[3.3799901009,50.7163505554],"type":"Point"}
}