{
  "type": "Feature",
  "properties": {
    "iso:country":"BE",
    "sg:address":"Jan Baptist Denayerstraat 17",
    "sg:city":"Hoeilaart",
    "sg:classifiers":[
        {
            "category":"Professional",
            "subcategory":"Accounting & Tax Preparation",
            "type":"Services"
        }
    ],
    "sg:phone":"+32 2 657 67 52",
    "sg:postcode":"1560",
    "sg:province":"Vlaams-Brabant",
    "sg:tags":[
        "underwater",
        "work"
    ],
    "wof:name":"Cmb Van Der Esch",
    "wof:placetype":"venue"
},
  "geometry": {"coordinates":[4.4792947769,50.761844635],"type":"Point"}
}