{
  "type": "Feature",
  "properties": {
    "iso:country":"BE",
    "sg:address":"Dorpsstraat 15 Box 2",
    "sg:city":"Gooik",
    "sg:classifiers":[
        {
            "category":"Professional",
            "type":"Services"
        }
    ],
    "sg:phone":"+32 475 94 04 29",
    "sg:postcode":"1755",
    "sg:province":"Vlaams-Brabant",
    "sg:tags":[
        "entertainer"
    ],
    "wof:name":"Muziek Op Maat Vzw",
    "wof:placetype":"venue"
},
  "geometry": {"coordinates":[4.1174921989,50.7953033447],"type":"Point"}
}