{
  "type": "Feature",
  "properties": {
    "iso:country":"BE",
    "sg:address":"Kompveldstraat 9",
    "sg:city":"Lanaken (veldwezelt)",
    "sg:classifiers":[
        {
            "category":"Structure",
            "subcategory":"Building",
            "type":"Public Place"
        }
    ],
    "sg:phone":"+32 89 71 69 41",
    "sg:postcode":"3620",
    "sg:province":"Limburg",
    "sg:tags":[
        "door"
    ],
    "wof:name":"Geijselaars Ramenbedrijf/lanaken Nv",
    "wof:placetype":"venue"
},
  "geometry": {"coordinates":[5.6551351547,50.8912277222],"type":"Point"}
}