{
  "type": "Feature",
  "properties": {
    "iso:country":"BE",
    "sg:address":"Heirstraat 482",
    "sg:city":"Maasmechelen (opgrimbie)",
    "sg:classifiers":[
        {
            "category":"Food & Beverages",
            "subcategory":"Supermarket",
            "type":"Retail Goods"
        }
    ],
    "sg:phone":"+32 89 77 27 20",
    "sg:postcode":"3630",
    "sg:province":"Limburg",
    "sg:tags":[
        "department",
        "store"
    ],
    "wof:name":"Bastings-delhaize Nv",
    "wof:placetype":"venue"
},
  "geometry": {"coordinates":[5.6846699715,50.9509391785],"type":"Point"}
}