{
  "type": "Feature",
  "properties": {
    "addr:full":"Statiestraat 26 Aalst Oost-Vlaanderen 9310",
    "addr:housenumber":"26",
    "addr:postcode":"9310",
    "addr:street":"Statiestraat",
    "iso:country":"BE",
    "sg:address":"Statiestraat 26",
    "sg:city":"Aalst",
    "sg:orig_category":"Dranken Zuivelproducten",
    "sg:phone":"+32 53 77 77 15",
    "sg:postcode":"9310",
    "sg:province":"Oost-Vlaanderen",
    "wof:name":"Interwoning",
    "wof:placetype":"venue"
},
  "geometry": {"coordinates":[4.0393190384,50.9421920776],"type":"Point"}
}