{
  "type": "Feature",
  "properties": {
    "addr:full":"Beiaardlaan 20 Grimbergen Vlaams-Brabant 1850",
    "addr:housenumber":"20",
    "addr:postcode":"1850",
    "addr:street":"Beiaardlaan",
    "iso:country":"BE",
    "sg:address":"Beiaardlaan 20",
    "sg:city":"Grimbergen",
    "sg:classifiers":[
        {
            "category":"Health Services",
            "subcategory":"Doctor",
            "type":"Services"
        }
    ],
    "sg:phone":"+32 2 270 00 25",
    "sg:postcode":"1850",
    "sg:province":"Vlaams-Brabant",
    "sg:tags":[
        "medicinephysicians",
        "surgeon"
    ],
    "wof:name":"Decraene P",
    "wof:placetype":"venue"
},
  "geometry": {"coordinates":[4.3670978546,50.9338989258],"type":"Point"}
}