{
  "type": "Feature",
  "properties": {
    "iso:country":"BE",
    "sg:address":"Vaartdijk 136",
    "sg:city":"Zemst",
    "sg:orig_category":"Artistes ind\u00e9pendants",
    "sg:phone":"+32 15 61 13 45",
    "sg:postcode":"1981",
    "sg:province":"Vlaams-Brabant",
    "wof:name":"Marc Coessens",
    "wof:placetype":"venue"
},
  "geometry": {"coordinates":[4.499434948,51.0053634644],"type":"Point"}
}