{
  "type": "Feature",
  "properties": {
    "addr:full":"Meiweg 47 Zwevegem West-Vlaanderen 8550",
    "addr:housenumber":"47",
    "addr:postcode":"8550",
    "addr:street":"Meiweg",
    "iso:country":"BE",
    "sg:address":"Meiweg 47",
    "sg:city":"Zwevegem",
    "sg:orig_category":"Drogisterijen",
    "sg:phone":"+32 56 75 61 43",
    "sg:postcode":"8550",
    "sg:province":"West-Vlaanderen",
    "wof:name":"Huis Ergo-reflex",
    "wof:placetype":"venue"
},
  "geometry": {"coordinates":[3.3580610752,50.81224823],"type":"Point"}
}