{
  "type": "Feature",
  "properties": {
    "addr:full":"Fraikinstr 68 Herentals (groot) Antwerpen 2200",
    "addr:housenumber":"68",
    "addr:postcode":"2200",
    "addr:street":"Fraikinstr;Groot Antwerpen",
    "iso:country":"BE",
    "sg:address":"Fraikinstr 68",
    "sg:city":"Herentals (groot)",
    "sg:classifiers":[
        {
            "category":"Personal",
            "subcategory":"Beauty Salon",
            "type":"Services"
        }
    ],
    "sg:phone":"+32 14 21 49 36",
    "sg:postcode":"2200",
    "sg:province":"Antwerpen",
    "sg:tags":[
        "de",
        "coiffure"
    ],
    "wof:name":"Fraikin",
    "wof:placetype":"venue"
},
  "geometry": {"coordinates":[4.8354058266,51.1817817688],"type":"Point"}
}