{
  "type": "Feature",
  "properties": {
    "iso:country":"BE",
    "sg:address":"Eeuwfeestlaan 11",
    "sg:city":"Keerbergen",
    "sg:classifiers":[
        {
            "category":"Insurance",
            "subcategory":"Insurance Agent",
            "type":"Services"
        }
    ],
    "sg:phone":"+32 15 51 12 21",
    "sg:postcode":"3140",
    "sg:province":"Vlaams-Brabant",
    "sg:tags":[
        "broker"
    ],
    "wof:name":"Cornelis Theo Bvba",
    "wof:placetype":"venue"
},
  "geometry": {"coordinates":[4.636092186,51.0001373291],"type":"Point"}
}