{
  "type": "Feature",
  "properties": {
    "addr:full":"Rue De La Cath\u00e9drale 53 Li\u00e8ge 1 Li\u00e8ge 4000",
    "addr:housenumber":"53;1",
    "addr:postcode":"4000",
    "addr:street":"Rue De La Cathe\u0301Drale",
    "iso:country":"BE",
    "sg:address":"Rue De La Cath\u00e9drale 53",
    "sg:city":"Li\u00e8ge 1",
    "sg:classifiers":[
        {
            "category":"Cafe",
            "type":"Food & Drink"
        }
    ],
    "sg:phone":"+32 4 223 10 12",
    "sg:postcode":"4000",
    "sg:province":"Li\u00e8ge",
    "sg:tags":[
        "snack-bars"
    ],
    "wof:name":"Pita Cath\u00e9drale",
    "wof:placetype":"venue"
},
  "geometry": {"coordinates":[5.5749158859,50.64245224],"type":"Point"}
}