{
  "type": "Feature",
  "properties": {
    "iso:country":"BE",
    "sg:address":"Haachtsesteenweg 1192",
    "sg:city":"Haren",
    "sg:orig_category":"Herstellingen and onderhoud van auto's",
    "sg:phone":"+32 2 241 53 83",
    "sg:postcode":"1130",
    "sg:province":"Bruxelles-Capitale",
    "wof:name":"Barberie Garage",
    "wof:placetype":"venue"
},
  "geometry": {"coordinates":[4.4209470749,50.8927154541],"type":"Point"}
}