{
  "type": "Feature",
  "properties": {
    "addr:full":"Burchtlaan 90 Merchtem Vlaams-Brabant 1785",
    "addr:housenumber":"90",
    "addr:postcode":"1785",
    "addr:street":"Burchtlaan",
    "iso:country":"BE",
    "sg:address":"Burchtlaan 90",
    "sg:city":"Merchtem",
    "sg:classifiers":[
        {
            "category":"Banks & Credit Unions",
            "subcategory":"Bank",
            "type":"Services"
        }
    ],
    "sg:phone":"+32 52 37 55 40",
    "sg:postcode":"1785",
    "sg:province":"Vlaams-Brabant",
    "sg:tags":[
        "savings-banks"
    ],
    "wof:name":"Heremans Andr\u00e9 (kantoor)",
    "wof:placetype":"venue"
},
  "geometry": {"coordinates":[4.2355980873,50.9605445862],"type":"Point"}
}