{
  "type": "Feature",
  "properties": {
    "iso:country":"BE",
    "sg:address":"Rue De La Victoire 25",
    "sg:city":"Fernelmont",
    "sg:orig_category":"Administration d'immeubles",
    "sg:phone":"+32 81 83 41 02",
    "sg:postcode":"5380",
    "sg:province":"Namur",
    "wof:name":"Jean-claude Nihoul",
    "wof:placetype":"venue"
},
  "geometry": {"coordinates":[4.9586200714,50.5488739014],"type":"Point"}
}