{
  "type": "Feature",
  "properties": {
    "addr:full":"Molenstraat 111 Sint-laureins Oost-Vlaanderen 9988",
    "addr:housenumber":"111",
    "addr:postcode":"9988",
    "addr:street":"Molenstraat",
    "iso:country":"BE",
    "sg:address":"Molenstraat 111",
    "sg:city":"Sint-laureins",
    "sg:orig_category":"Studios photographiques",
    "sg:phone":"+32 9 379 99 31",
    "sg:postcode":"9988",
    "sg:province":"Oost-Vlaanderen",
    "wof:name":"Peter Van Waes",
    "wof:placetype":"venue"
},
  "geometry": {"coordinates":[3.6267449856,51.2890396118],"type":"Point"}
}