{
  "type": "Feature",
  "properties": {
    "addr:full":"Battelsesteenweg 28b5 Mechelen Antwerpen 2800",
    "addr:housenumber":"28b5",
    "addr:postcode":"2800",
    "addr:street":"Battelsesteenweg",
    "iso:country":"BE",
    "sg:address":"Battelsesteenweg 28b5",
    "sg:city":"Mechelen",
    "sg:orig_category":"Bouwmaterialen Gh",
    "sg:phone":"+32 15 28 73 60",
    "sg:postcode":"2800",
    "sg:province":"Antwerpen",
    "wof:name":"Cape Boards Belgium",
    "wof:placetype":"venue"
},
  "geometry": {"coordinates":[4.4693288803,51.0287666321],"type":"Point"}
}