{
  "type": "Feature",
  "properties": {
    "iso:country":"BE",
    "sg:address":"Nieuwdorpstraat 12",
    "sg:city":"Genk",
    "sg:orig_category":"Herstellingen and onderhoud van auto's",
    "sg:phone":"+32 89 38 04 77",
    "sg:postcode":"3600",
    "sg:province":"Limburg",
    "wof:name":"Garage Foesters",
    "wof:placetype":"venue"
},
  "geometry": {"coordinates":[5.5242772102,50.9898452759],"type":"Point"}
}