{
  "type": "Feature",
  "properties": {
    "addr:full":"Louizalaan 207b10 Elsene/ixelles Bruxelles-Capitale 1050",
    "addr:housenumber":"207b10",
    "addr:postcode":"1050",
    "addr:street":"Louizalaan",
    "iso:country":"BE",
    "sg:address":"Louizalaan 207b10",
    "sg:city":"Elsene/ixelles",
    "sg:orig_category":"Incassobureaus and kredietcontrole",
    "sg:phone":"+32 2 646 91 12",
    "sg:postcode":"1050",
    "sg:province":"Bruxelles-Capitale",
    "wof:name":"Euro Encaissement",
    "wof:placetype":"venue"
},
  "geometry": {"coordinates":[4.3573069572,50.8343505859],"type":"Point"}
}