{
  "type": "Feature",
  "properties": {
    "addr:full":"Lutticher Strasse 198 Kelmis/la Calamine Li\u00e8ge 4720",
    "addr:housenumber":"198",
    "addr:postcode":"4720",
    "addr:street":"Lutticher Strasse",
    "iso:country":"BE",
    "sg:address":"Lutticher Strasse 198",
    "sg:city":"Kelmis/la Calamine",
    "sg:orig_category":"Banken and kredietinstellingen",
    "sg:phone":"+32 87 63 03 09",
    "sg:postcode":"4720",
    "sg:province":"Li\u00e8ge",
    "wof:name":"Anhyp",
    "wof:placetype":"venue"
},
  "geometry": {"coordinates":[6.0147500038,50.731098175],"type":"Point"}
}