{
  "type": "Feature",
  "properties": {
    "addr:full":"Osselstraat 50 Zonnebeke West-Vlaanderen 8980",
    "addr:housenumber":"50",
    "addr:postcode":"8980",
    "addr:street":"Osselstraat",
    "iso:country":"BE",
    "sg:address":"Osselstraat 50",
    "sg:city":"Zonnebeke",
    "sg:orig_category":"Producteurs de l\u00e9gumes",
    "sg:phone":"+32 51 77 13 60",
    "sg:postcode":"8980",
    "sg:province":"West-Vlaanderen",
    "wof:name":"Luc Hessel",
    "wof:placetype":"venue"
},
  "geometry": {"coordinates":[2.9872550964,50.8730812073],"type":"Point"}
}