{
  "type": "Feature",
  "properties": {
    "iso:country":"BE",
    "sg:address":"Het Innemen 76",
    "sg:city":"Brasschaat",
    "sg:orig_category":"Installation de menuiserie en bois and plastique",
    "sg:phone":"+32 3 651 41 88",
    "sg:postcode":"2930",
    "sg:province":"Antwerpen",
    "wof:name":"Meubelmakerij Haagdorens",
    "wof:placetype":"venue"
},
  "geometry": {"coordinates":[4.4982972145,51.3072929382],"type":"Point"}
}