{
  "type": "Feature",
  "properties": {
    "iso:country":"BE",
    "sg:address":"Rue 't Serstevens 2a",
    "sg:city":"Thuin",
    "sg:classifiers":[
        {
            "category":"Shopping",
            "subcategory":"Clothing, Apparel, & Fashions",
            "type":"Retail Goods"
        }
    ],
    "sg:phone":"+32 71 59 81 75",
    "sg:postcode":"6530",
    "sg:province":"Hainaut",
    "sg:tags":[
        "clothing",
        "-",
        "gentleman"
    ],
    "wof:name":"All Men",
    "wof:placetype":"venue"
},
  "geometry": {"coordinates":[4.286552906,50.3411521912],"type":"Point"}
}