{
  "type": "Feature",
  "properties": {
    "addr:full":"Place Eug\u00e8ne Keym 79 Bruxelles (watermael-boitsfort) Bruxelles-Capitale 1170",
    "addr:housenumber":"79",
    "addr:postcode":"1170",
    "addr:street":"Place Euge\u0300Ne Keym",
    "iso:country":"BE",
    "sg:address":"Place Eug\u00e8ne Keym 79",
    "sg:city":"Bruxelles (watermael-boitsfort)",
    "sg:classifiers":[
        {
            "category":"Shopping",
            "subcategory":"Clothing, Apparel, & Fashions",
            "type":"Retail Goods"
        }
    ],
    "sg:phone":"+32 2 675 26 50",
    "sg:postcode":"1170",
    "sg:province":"Bruxelles-Capitale",
    "sg:tags":[
        "clothing",
        "-",
        "gentleman"
    ],
    "wof:name":"Cucaracha Fashion",
    "wof:placetype":"venue"
},
  "geometry": {"coordinates":[4.4032530785,50.8094177246],"type":"Point"}
}