{
  "type": "Feature",
  "properties": {
    "addr:full":"Rue Grande 4 Couvin Namur 5660",
    "addr:housenumber":"4",
    "addr:postcode":"5660",
    "addr:street":"Rue Grande",
    "iso:country":"BE",
    "sg:address":"Rue Grande 4",
    "sg:city":"Couvin",
    "sg:orig_category":"Artsen and specialisten",
    "sg:phone":"+32 60 37 70 77",
    "sg:postcode":"5660",
    "sg:province":"Namur",
    "wof:name":"Micheline Amand",
    "wof:placetype":"venue"
},
  "geometry": {"coordinates":[4.524928093,49.9697113037],"type":"Point"}
}