{
  "type": "Feature",
  "properties": {
    "addr:full":"Sint-augustinusstraat 29 Lanaken (gellik) Limburg 3620",
    "addr:housenumber":"29",
    "addr:postcode":"3620",
    "addr:street":"Sint-Augustinusstraat",
    "iso:country":"BE",
    "sg:address":"Sint-augustinusstraat 29",
    "sg:city":"Lanaken (gellik)",
    "sg:classifiers":[
        {
            "category":"Home & Garden",
            "subcategory":"Building Materials",
            "type":"Retail Goods"
        }
    ],
    "sg:phone":"+32 89 71 69 17",
    "sg:postcode":"3620",
    "sg:province":"Limburg",
    "sg:tags":[
        "window"
    ],
    "wof:name":"Vos F",
    "wof:placetype":"venue"
},
  "geometry": {"coordinates":[5.6092300415,50.8856735229],"type":"Point"}
}