{
  "type": "Feature",
  "properties": {
    "addr:full":"Wafelstraat 54 Zwalm Oost-Vlaanderen 9630",
    "addr:housenumber":"54",
    "addr:postcode":"9630",
    "addr:street":"Wafelstraat;Oost-Vlaanderen",
    "iso:country":"BE",
    "sg:address":"Wafelstraat 54",
    "sg:city":"Zwalm",
    "sg:orig_category":"Banques and organismes de cr\u00e9dit",
    "sg:phone":"+32 55 49 94 89",
    "sg:postcode":"9630",
    "sg:province":"Oost-Vlaanderen",
    "wof:name":"Landbouwkrediet",
    "wof:placetype":"venue"
},
  "geometry": {"coordinates":[3.7146201134,50.8804397583],"type":"Point"}
}