{
  "type": "Feature",
  "properties": {
    "addr:full":"Keetbergln 5 Kallo Oost-Vlaanderen 9120",
    "addr:housenumber":"5",
    "addr:postcode":"9120",
    "addr:street":"Keetbergln;Oost-Vlaanderen",
    "iso:country":"BE",
    "sg:address":"Keetbergln 5",
    "sg:city":"Kallo",
    "sg:classifiers":[
        {
            "category":"Professional",
            "subcategory":"Engineering",
            "type":"Services"
        }
    ],
    "sg:phone":"+32 3 575 14 14",
    "sg:postcode":"9120",
    "sg:province":"Oost-Vlaanderen",
    "sg:tags":[
        "machine",
        "-",
        "mechanical"
    ],
    "wof:name":"Rob Montagebedrijf Nv",
    "wof:placetype":"venue"
},
  "geometry": {"coordinates":[4.2594051361,51.2448158264],"type":"Point"}
}