{
  "type": "Feature",
  "properties": {
    "iso:country":"BE",
    "sg:address":"Nieuwenrodesteenweg 32",
    "sg:city":"Grimbergen",
    "sg:orig_category":"Charpentes and couvertures. Constructions r\u00e9sidentielles sp\u00e9cifiques. Travaux de finition and nettoy",
    "sg:phone":"+32 2 270 48 13",
    "sg:postcode":"1851",
    "sg:province":"Vlaams-Brabant",
    "wof:name":"Van Der Trappen",
    "wof:placetype":"venue"
},
  "geometry": {"coordinates":[4.3622531891,50.9734840393],"type":"Point"}
}