{
  "type": "Feature",
  "properties": {
    "addr:full":"Rue Charles Hansez 32 Soumagne (micheroux) Li\u00e8ge 4630",
    "addr:housenumber":"32",
    "addr:postcode":"4630",
    "addr:street":"Rue Charles Hansez",
    "iso:country":"BE",
    "sg:address":"Rue Charles Hansez 32",
    "sg:city":"Soumagne (micheroux)",
    "sg:classifiers":[
        {
            "category":"Communications",
            "type":"Services"
        }
    ],
    "sg:phone":"+32 4 377 43 84",
    "sg:postcode":"4630",
    "sg:province":"Li\u00e8ge",
    "sg:tags":[
        "telecommunication"
    ],
    "wof:name":"Mattina F",
    "wof:placetype":"venue"
},
  "geometry": {"coordinates":[5.722427845,50.628993988],"type":"Point"}
}