{
  "type": "Feature",
  "properties": {
    "addr:full":"Werthplatz 6 Eupen Li\u00e8ge 4700",
    "addr:housenumber":"6",
    "addr:postcode":"4700",
    "addr:street":"Werthplatz",
    "iso:country":"BE",
    "sg:address":"Werthplatz 6",
    "sg:city":"Eupen",
    "sg:classifiers":[
        {
            "category":"Shopping",
            "subcategory":"Pets & Pet Supplies",
            "type":"Retail Goods"
        }
    ],
    "sg:phone":"+32 87 55 62 60",
    "sg:postcode":"4700",
    "sg:province":"Li\u00e8ge",
    "sg:tags":[
        "shop",
        "-"
    ],
    "wof:name":"Animal Planet Belgium",
    "wof:placetype":"venue"
},
  "geometry": {"coordinates":[6.0386109352,50.6328964233],"type":"Point"}
}