{
  "type": "Feature",
  "properties": {
    "addr:full":"Broekstraat 17 Zoutleeuw Vlaams-Brabant 3440",
    "addr:housenumber":"17",
    "addr:postcode":"3440",
    "addr:street":"Broekstraat;Vlaams-Brabant",
    "iso:country":"BE",
    "sg:address":"Broekstraat 17",
    "sg:city":"Zoutleeuw",
    "sg:orig_category":"Mat\u00e9riaux de construction Rev\u00eatements de sols and murs",
    "sg:phone":"+32 11 78 03 55",
    "sg:postcode":"3440",
    "sg:province":"Vlaams-Brabant",
    "wof:name":"Santeco",
    "wof:placetype":"venue"
},
  "geometry": {"coordinates":[5.0926837921,50.8026161194],"type":"Point"}
}