{
  "type": "Feature",
  "properties": {
    "addr:full":"Kammenstraat 70a Antwerpen Antwerpen 2000",
    "addr:housenumber":"70a",
    "addr:postcode":"2000",
    "addr:street":"Kammenstraat",
    "iso:country":"BE",
    "sg:address":"Kammenstraat 70a",
    "sg:city":"Antwerpen",
    "sg:classifiers":[
        {
            "category":"Insurance",
            "subcategory":"Insurance Agent",
            "type":"Services"
        }
    ],
    "sg:phone":"+32 3 232 02 49",
    "sg:postcode":"2000",
    "sg:province":"Antwerpen",
    "sg:tags":[
        "verzekeringsmakelaars",
        "expert"
    ],
    "wof:name":"Huverko",
    "wof:placetype":"venue"
},
  "geometry": {"coordinates":[4.4015097618,51.2162399292],"type":"Point"}
}