{
  "type": "Feature",
  "properties": {
    "iso:country":"BE",
    "sg:address":"Avenue Jupiter 5",
    "sg:city":"Waterloo",
    "sg:orig_category":"Diverse bedrijfsbeheeradviesbureaus",
    "sg:phone":"+32 2 353 22 18",
    "sg:postcode":"1410",
    "sg:province":"Brabant Wallon",
    "wof:name":"Belhib Management",
    "wof:placetype":"venue"
},
  "geometry": {"coordinates":[4.4183011055,50.7069549561],"type":"Point"}
}