{
  "type": "Feature",
  "properties": {
    "addr:full":"Zi De Weyler Arlon Luxembourg 6700",
    "addr:postcode":"6700",
    "addr:street":"Zi De Weyler",
    "iso:country":"BE",
    "sg:address":"Zi De Weyler",
    "sg:city":"Arlon",
    "sg:classifiers":[
        {
            "category":"Utilities",
            "subcategory":"Electric",
            "type":"Services"
        }
    ],
    "sg:phone":"+32 63 42 02 20",
    "sg:postcode":"6700",
    "sg:province":"Luxembourg",
    "sg:tags":[
        "electricity",
        "electronic",
        "electrical",
        "equipment"
    ],
    "wof:name":"Rexel Sa",
    "wof:placetype":"venue"
},
  "geometry": {"coordinates":[5.8126749992,49.6823234558],"type":"Point"}
}