{
  "type": "Feature",
  "properties": {
    "addr:full":"Chauss\u00e9e Fernand Deli\u00e8ge 45 Beaumont Hainaut 6500",
    "addr:housenumber":"45",
    "addr:postcode":"6500",
    "addr:street":"Chausse\u0301E Fernand Delie\u0300Ge;Hainaut",
    "iso:country":"BE",
    "sg:address":"Chauss\u00e9e Fernand Deli\u00e8ge 45",
    "sg:city":"Beaumont",
    "sg:classifiers":[
        {
            "category":"Insurance",
            "subcategory":"Insurance Agent",
            "type":"Services"
        }
    ],
    "sg:phone":"+32 71 58 94 54",
    "sg:postcode":"6500",
    "sg:province":"Hainaut",
    "sg:tags":[
        "broker"
    ],
    "wof:name":"Dorignaux J-f",
    "wof:placetype":"venue"
},
  "geometry": {"coordinates":[4.2548570633,50.2381515503],"type":"Point"}
}