{
  "type": "Feature",
  "properties": {
    "addr:full":"Burgweg 33 Vleteren West-Vlaanderen 8640",
    "addr:housenumber":"33",
    "addr:postcode":"8640",
    "addr:street":"Burgweg",
    "iso:country":"BE",
    "sg:address":"Burgweg 33",
    "sg:city":"Vleteren",
    "sg:orig_category":"Tuinen",
    "sg:phone":"+32 57 42 13 78",
    "sg:postcode":"8640",
    "sg:province":"West-Vlaanderen",
    "wof:name":"Vandewoude",
    "wof:placetype":"venue"
},
  "geometry": {"coordinates":[2.7423648834,50.9328651428],"type":"Point"}
}