{
  "type": "Feature",
  "properties": {
    "iso:country":"BE",
    "sg:address":"Rue Du Mont 1",
    "sg:city":"Saint-hubert",
    "sg:orig_category":"Fleurs and plantes",
    "sg:phone":"+32 61 61 28 14",
    "sg:postcode":"6870",
    "sg:province":"Luxembourg",
    "wof:name":"L\u00b4orchid\u00c9e",
    "wof:placetype":"venue"
},
  "geometry": {"coordinates":[5.3744077682,50.0251998901],"type":"Point"}
}