{
  "type": "Feature",
  "properties": {
    "addr:full":"Rue De La Flani\u00e8re 44 Charleroi (ransart) Hainaut 6043",
    "addr:housenumber":"44",
    "addr:postcode":"6043",
    "addr:street":"Rue De La Flanie\u0300Re",
    "iso:country":"BE",
    "sg:address":"Rue De La Flani\u00e8re 44",
    "sg:city":"Charleroi (ransart)",
    "sg:classifiers":[
        {
            "category":"Health Services",
            "subcategory":"Doctor",
            "type":"Services"
        }
    ],
    "sg:phone":"+32 71 35 19 91",
    "sg:postcode":"6043",
    "sg:province":"Hainaut",
    "sg:tags":[
        "medicinephysicians",
        "surgeon"
    ],
    "wof:name":"Decorte Florence",
    "wof:placetype":"venue"
},
  "geometry": {"coordinates":[4.4839549065,50.4479637146],"type":"Point"}
}