{
  "type": "Feature",
  "properties": {
    "iso:country":"BE",
    "sg:address":"Wilde Kastanjelaan 23",
    "sg:city":"Genk",
    "sg:classifiers":[
        {
            "category":"Travel",
            "subcategory":"Hotels & Motels",
            "type":"Entertainment"
        }
    ],
    "sg:phone":"+32 89 30 47 70",
    "sg:postcode":"3600",
    "sg:province":"Limburg",
    "wof:name":"De Venne",
    "wof:placetype":"venue"
},
  "geometry": {"coordinates":[5.4886379242,50.9796524048],"type":"Point"}
}