{
  "type": "Feature",
  "properties": {
    "addr:full":"Ambachtenstraat 5 Westerlo Antwerpen 2260",
    "addr:housenumber":"5",
    "addr:postcode":"2260",
    "addr:street":"Ambachtenstraat",
    "iso:country":"BE",
    "sg:address":"Ambachtenstraat 5",
    "sg:city":"Westerlo",
    "sg:classifiers":[
        {
            "category":"Home & Garden",
            "subcategory":"Kitchen Supply",
            "type":"Retail Goods"
        }
    ],
    "sg:phone":"+32 14 54 15 05",
    "sg:postcode":"2260",
    "sg:province":"Antwerpen",
    "sg:tags":[
        "plate",
        "-",
        "miscellaneous"
    ],
    "wof:name":"Postform",
    "wof:placetype":"venue"
},
  "geometry": {"coordinates":[4.9341821671,51.095035553],"type":"Point"}
}