{
  "type": "Feature",
  "properties": {
    "iso:country":"BE",
    "sg:address":"Rue Des R\u00c9collets 14",
    "sg:city":"Ath",
    "sg:orig_category":"Enseignement secondaire g\u00e9n\u00e9ral. Enseignement secondaire technique and professionnel",
    "sg:phone":"+32 68 26 46 50",
    "sg:postcode":"7800",
    "sg:province":"Hainaut",
    "wof:name":"Inst. Prov. Enseign. Sec.",
    "wof:placetype":"venue"
},
  "geometry": {"coordinates":[3.7804100513,50.6288299561],"type":"Point"}
}