{
  "type": "Feature",
  "properties": {
    "addr:full":"Nerumweg 10 Lede Oost-Vlaanderen 9340",
    "addr:housenumber":"10",
    "addr:postcode":"9340",
    "addr:street":"Nerumweg",
    "iso:country":"BE",
    "sg:address":"Nerumweg 10",
    "sg:city":"Lede",
    "sg:orig_category":"Dakwerken Woningbouw",
    "sg:phone":"+32 53 80 86 18",
    "sg:postcode":"9340",
    "sg:province":"Oost-Vlaanderen",
    "wof:name":"Van Den Abbeele",
    "wof:placetype":"venue"
},
  "geometry": {"coordinates":[3.9951760769,50.9612770081],"type":"Point"}
}