{
  "type": "Feature",
  "properties": {
    "addr:full":"Rue Jean Jaur\u00c8s 43bc Charleroi Hainaut 6044",
    "addr:postcode":"43bc;6044",
    "addr:street":"Rue Jean Jaure\u0300S;Hainaut",
    "iso:country":"BE",
    "sg:address":"Rue Jean Jaur\u00c8s 43bc",
    "sg:city":"Charleroi",
    "sg:orig_category":"M\u00e9decins and sp\u00e9cialistes",
    "sg:phone":"+32 71 46 17 81",
    "sg:postcode":"6044",
    "sg:province":"Hainaut",
    "wof:name":"Edwige Emegenbirn",
    "wof:placetype":"venue"
},
  "geometry": {"coordinates":[4.3865199089,50.4439964294],"type":"Point"}
}