{
  "type": "Feature",
  "properties": {
    "iso:country":"BE",
    "sg:address":"Papenbergstraat 116",
    "sg:city":"Liedekerke",
    "sg:orig_category":"Plaatsen van vloer- and muurbekleding",
    "sg:phone":"+32 53 66 01 87",
    "sg:postcode":"1770",
    "sg:province":"Vlaams-Brabant",
    "wof:name":"Maurits Van Snick",
    "wof:placetype":"venue"
},
  "geometry": {"coordinates":[4.0876178741,50.8728218079],"type":"Point"}
}