{
  "type": "Feature",
  "properties": {
    "iso:country":"BE",
    "sg:address":"Stationsstraat 1",
    "sg:city":"Ronse",
    "sg:classifiers":[
        {
            "category":"Building & Trades",
            "subcategory":"Construction",
            "type":"Services"
        }
    ],
    "sg:phone":"+32 55 21 07 75",
    "sg:postcode":"9600",
    "sg:province":"Oost-Vlaanderen",
    "sg:tags":[
        "siemens",
        "fujitsu"
    ],
    "wof:name":"Derco Systems",
    "wof:placetype":"venue"
},
  "geometry": {"coordinates":[3.6005868912,50.7441864014],"type":"Point"}
}