{
  "type": "Feature",
  "properties": {
    "addr:full":"Denen 161 Lochristi Oost-Vlaanderen 9080",
    "addr:housenumber":"161",
    "addr:postcode":"9080",
    "addr:street":"Denen",
    "iso:country":"BE",
    "sg:address":"Denen 161",
    "sg:city":"Lochristi",
    "sg:classifiers":[
        {
            "category":"Restaurant",
            "type":"Food & Drink"
        }
    ],
    "sg:phone":"+32 9 356 92 93",
    "sg:postcode":"9080",
    "sg:province":"Oost-Vlaanderen",
    "sg:tags":[
        "caf\u00e9s"
    ],
    "wof:name":"Taverne Denia",
    "wof:placetype":"venue"
},
  "geometry": {"coordinates":[3.8685359955,51.1056518555],"type":"Point"}
}