{
  "type": "Feature",
  "properties": {
    "addr:full":"Oudestraat 61 Antwerpen Antwerpen 2610",
    "addr:housenumber":"61",
    "addr:postcode":"2610",
    "addr:street":"Oudestraat",
    "iso:country":"BE",
    "sg:address":"Oudestraat 61",
    "sg:city":"Antwerpen",
    "sg:classifiers":[
        {
            "category":"Arena",
            "subcategory":"Sports Club",
            "type":"Entertainment"
        }
    ],
    "sg:phone":"+32 3 827 60 39",
    "sg:postcode":"2610",
    "sg:province":"Antwerpen",
    "sg:tags":[
        "de"
    ],
    "wof:name":"T.c. Ter Linden",
    "wof:placetype":"venue"
},
  "geometry": {"coordinates":[4.4205708504,51.2263526917],"type":"Point"}
}