{
  "type": "Feature",
  "properties": {
    "addr:full":"Westernieuwweg 89 Jabbeke West-Vlaanderen 8490",
    "addr:housenumber":"89",
    "addr:postcode":"8490",
    "addr:street":"Westernieuwweg",
    "iso:country":"BE",
    "sg:address":"Westernieuwweg 89",
    "sg:city":"Jabbeke",
    "sg:orig_category":"Eleveurs de bovins",
    "sg:phone":"+32 50 39 59 89",
    "sg:postcode":"8490",
    "sg:province":"West-Vlaanderen",
    "wof:name":"Carlos Lootens",
    "wof:placetype":"venue"
},
  "geometry": {"coordinates":[3.1274349689,51.2025222778],"type":"Point"}
}