{
  "type": "Feature",
  "properties": {
    "addr:full":"Aartshertogstraat 1a Oostende West-Vlaanderen 8400",
    "addr:housenumber":"1a",
    "addr:postcode":"8400",
    "addr:street":"Aartshertogstraat",
    "iso:country":"BE",
    "sg:address":"Aartshertogstraat 1a",
    "sg:city":"Oostende",
    "sg:classifiers":[
        {
            "category":"Personal",
            "subcategory":"Beauty Salon",
            "type":"Services"
        }
    ],
    "sg:phone":"+32 59 80 16 58",
    "sg:postcode":"8400",
    "sg:province":"West-Vlaanderen",
    "sg:tags":[
        "lady",
        "-",
        "hairdressing"
    ],
    "wof:name":"Wilfried",
    "wof:placetype":"venue"
},
  "geometry": {"coordinates":[2.9170100689,51.2300491333],"type":"Point"}
}