{
  "type": "Feature",
  "properties": {
    "iso:country":"BE",
    "sg:address":"Harelbekestraat 17-19",
    "sg:city":"Deerlijk",
    "sg:classifiers":[
        {
            "category":"Retail",
            "subcategory":"Repair Shop",
            "type":"Services"
        }
    ],
    "sg:phone":"+32 56 71 41 39",
    "sg:postcode":"8540",
    "sg:province":"West-Vlaanderen",
    "sg:tags":[
        "machine",
        "sewing",
        "-"
    ],
    "wof:name":"Vanden Broucke A",
    "wof:placetype":"venue"
},
  "geometry": {"coordinates":[3.3532400131,50.8523597717],"type":"Point"}
}