{
  "type": "Feature",
  "properties": {
    "iso:country":"BE",
    "sg:address":"Rue De La Centrale 32",
    "sg:city":"Jemeppe-sur-sambre",
    "sg:classifiers":[
        {
            "category":"Fast Food",
            "type":"Food & Drink"
        }
    ],
    "sg:phone":"+32 71 78 30 90",
    "sg:postcode":"5190",
    "sg:province":"Namur",
    "sg:tags":[
        "meeneem",
        "restaurant"
    ],
    "wof:name":"Fit-services",
    "wof:placetype":"venue"
},
  "geometry": {"coordinates":[4.6998381615,50.4584732056],"type":"Point"}
}