{
  "type": "Feature",
  "properties": {
    "iso:country":"BE",
    "sg:address":"Route De Philippeville 472",
    "sg:city":"Charleroi (couillet)",
    "sg:classifiers":[
        {
            "category":"Health Services",
            "subcategory":"Nursing And Care Facility",
            "type":"Services"
        }
    ],
    "sg:phone":"+32 71 47 09 83",
    "sg:postcode":"6010",
    "sg:province":"Hainaut",
    "sg:tags":[
        "home"
    ],
    "wof:name":"Sauvage C Sprl",
    "wof:placetype":"venue"
},
  "geometry": {"coordinates":[4.4660601616,50.3791694641],"type":"Point"}
}