{
  "type": "Feature",
  "properties": {
    "addr:full":"Rue Des Goutteaux 45 Charleroi Hainaut 6032",
    "addr:housenumber":"45",
    "addr:postcode":"6032",
    "addr:street":"Rue Des Goutteaux;Hainaut",
    "iso:country":"BE",
    "sg:address":"Rue Des Goutteaux 45",
    "sg:city":"Charleroi",
    "sg:orig_category":"Rev\u00eatements pour sols and murs. Peinture",
    "sg:phone":"+32 71 47 38 92",
    "sg:postcode":"6032",
    "sg:province":"Hainaut",
    "wof:name":"Henrivaux D\u00c9coration",
    "wof:placetype":"venue"
},
  "geometry": {"coordinates":[4.4083647728,50.3888320923],"type":"Point"}
}