{
  "type": "Feature",
  "properties": {
    "iso:country":"BE",
    "sg:address":"Chauss\u00c9e D\u00b4ixelles 154",
    "sg:city":"Elsene/ixelles",
    "sg:orig_category":"Electrom\u00e9nager, t\u00e9l\u00e9visions and radios. Machines \u00e0 coudre and tricoter",
    "sg:phone":"+32 2 511 48 75",
    "sg:postcode":"1050",
    "sg:province":"Bruxelles-Capitale",
    "wof:name":"Singer & Pfaff",
    "wof:placetype":"venue"
},
  "geometry": {"coordinates":[4.3661980629,50.8336181641],"type":"Point"}
}