{
  "type": "Feature",
  "properties": {
    "iso:country":"BE",
    "sg:address":"Kruishoutemseweg 40",
    "sg:city":"Waregem",
    "sg:orig_category":"Epiceries",
    "sg:phone":"+32 56 61 20 55",
    "sg:postcode":"8790",
    "sg:province":"West-Vlaanderen",
    "wof:name":"'t Kruideniertje",
    "wof:placetype":"venue"
},
  "geometry": {"coordinates":[3.4477920532,50.8915367126],"type":"Point"}
}