{
  "type": "Feature",
  "properties": {
    "iso:country":"BE",
    "sg:address":"Rodekruisstraat 13",
    "sg:city":"Lommel",
    "sg:orig_category":"V\u00eatements pour Hommes",
    "sg:phone":"+32 11 54 41 18",
    "sg:postcode":"3920",
    "sg:province":"Limburg",
    "wof:name":"Michael Vanhoof",
    "wof:placetype":"venue"
},
  "geometry": {"coordinates":[5.311841011,51.2291870117],"type":"Point"}
}