{
  "type": "Feature",
  "properties": {
    "iso:country":"BE",
    "sg:address":"Kortemarkstraat 124",
    "sg:city":"Lichtervelde",
    "sg:classifiers":[
        {
            "category":"Bars & Pubs",
            "type":"Food & Drink"
        }
    ],
    "sg:phone":"+32 51 72 51 56",
    "sg:postcode":"8810",
    "sg:province":"West-Vlaanderen",
    "sg:tags":[
        "tavern"
    ],
    "wof:name":"Romantica",
    "wof:placetype":"venue"
},
  "geometry": {"coordinates":[3.1107890606,51.0237808228],"type":"Point"}
}