{
  "type": "Feature",
  "properties": {
    "addr:full":"Kl\u00f6tzerbahn 10 Eupen Li\u00e8ge 4700",
    "addr:housenumber":"10",
    "addr:postcode":"4700",
    "addr:street":"Kloetzerbahn",
    "iso:country":"BE",
    "sg:address":"Kl\u00f6tzerbahn 10",
    "sg:city":"Eupen",
    "sg:classifiers":[
        {
            "category":"Professional",
            "subcategory":"Testing Lab",
            "type":"Services"
        }
    ],
    "sg:phone":"+32 87 55 38 63",
    "sg:postcode":"4700",
    "sg:province":"Li\u00e8ge",
    "sg:tags":[
        "chemist"
    ],
    "wof:name":"Martinus",
    "wof:placetype":"venue"
},
  "geometry": {"coordinates":[6.0338931084,50.6303901672],"type":"Point"}
}