{
  "type": "Feature",
  "properties": {
    "iso:country":"BE",
    "sg:address":"Koebosstraat 14",
    "sg:city":"Dendermonde (appels)",
    "sg:classifiers":[
        {
            "category":"Building & Trades",
            "subcategory":"Construction",
            "type":"Services"
        }
    ],
    "sg:phone":"+32 52 21 35 54",
    "sg:postcode":"9200",
    "sg:province":"Oost-Vlaanderen",
    "sg:tags":[
        "carpenter"
    ],
    "wof:name":"Cool W",
    "wof:placetype":"venue"
},
  "geometry": {"coordinates":[4.0643057823,51.0306396484],"type":"Point"}
}