{
  "type": "Feature",
  "properties": {
    "addr:full":"Budingenweg 25 Zoutleeuw Vlaams-Brabant 3440",
    "addr:housenumber":"25",
    "addr:postcode":"3440",
    "addr:street":"Budingenweg;Vlaams-Brabant",
    "iso:country":"BE",
    "sg:address":"Budingenweg 25",
    "sg:city":"Zoutleeuw",
    "sg:classifiers":[
        {
            "category":"Utilities",
            "subcategory":"Fuel Oil & Lpg",
            "type":"Services"
        }
    ],
    "sg:phone":"+32 11 78 01 01",
    "sg:postcode":"3440",
    "sg:province":"Vlaams-Brabant",
    "wof:name":"Degof Desard W",
    "wof:placetype":"venue"
},
  "geometry": {"coordinates":[5.1129779816,50.8476905823],"type":"Point"}
}