{
  "type": "Feature",
  "properties": {
    "iso:country":"BE",
    "sg:address":"Kolonel Dusartplein 1b1",
    "sg:city":"Hasselt",
    "sg:orig_category":"Artsen and specialisten",
    "sg:phone":"+32 11 22 64 06",
    "sg:postcode":"3500",
    "sg:province":"Limburg",
    "wof:name":"Ronny Favoreel",
    "wof:placetype":"venue"
},
  "geometry": {"coordinates":[5.3446497917,50.9308891296],"type":"Point"}
}