{
  "type": "Feature",
  "properties": {
    "addr:full":"Zoning Industriel 23 Wanze Li\u00e8ge 4520",
    "addr:housenumber":"23",
    "addr:postcode":"4520",
    "addr:street":"Zoning Industriel",
    "iso:country":"BE",
    "sg:address":"Zoning Industriel 23",
    "sg:city":"Wanze",
    "sg:orig_category":"Meubles D\u00e9taillants, Am\u00e9nagement de B\u00e2timents et de Cuisines",
    "sg:phone":"+32 85 25 00 65",
    "sg:postcode":"4520",
    "sg:province":"Li\u00e8ge",
    "wof:name":"Codefco International (handy Seat)",
    "wof:placetype":"venue"
},
  "geometry": {"coordinates":[5.2139430046,50.5367546082],"type":"Point"}
}