{
  "type": "Feature",
  "properties": {
    "iso:country":"BE",
    "sg:address":"Provinciebaan 141",
    "sg:city":"Zottegem",
    "sg:classifiers":[
        {
            "category":"Insurance",
            "subcategory":"Insurance Agent",
            "type":"Services"
        }
    ],
    "sg:phone":"+32 9 360 34 86",
    "sg:postcode":"9620",
    "sg:province":"Oost-Vlaanderen",
    "sg:tags":[
        "verzekeringsmakelaars",
        "expert"
    ],
    "wof:name":"De Schamphelaere",
    "wof:placetype":"venue"
},
  "geometry": {"coordinates":[3.8112111092,50.871181488],"type":"Point"}
}