{
  "type": "Feature",
  "properties": {
    "iso:country":"BE",
    "sg:address":"Avenue De L'europe 102",
    "sg:city":"Charleroi",
    "sg:classifiers":[
        {
            "category":"Bars & Pubs",
            "type":"Food & Drink"
        }
    ],
    "sg:phone":"+32 71 50 01 92",
    "sg:postcode":"6000",
    "sg:province":"Hainaut",
    "sg:tags":[
        "tavern"
    ],
    "wof:name":"Maracas (le)",
    "wof:placetype":"venue"
},
  "geometry": {"coordinates":[4.4363341331,50.40990448],"type":"Point"}
}