{
  "type": "Feature",
  "properties": {
    "addr:full":"De Hutten 2 Meerhout Antwerpen 2450",
    "addr:housenumber":"2",
    "addr:postcode":"2450",
    "addr:street":"De Hutten",
    "iso:country":"BE",
    "sg:address":"De Hutten 2",
    "sg:city":"Meerhout",
    "sg:orig_category":"Bouwmaterialen Gh",
    "sg:phone":"+32 14 30 24 40",
    "sg:postcode":"2450",
    "sg:province":"Antwerpen",
    "wof:name":"Fa. Boons",
    "wof:placetype":"venue"
},
  "geometry": {"coordinates":[5.0528030396,51.1427345276],"type":"Point"}
}