{
  "type": "Feature",
  "properties": {
    "addr:full":"Rue Pasquier Grenier 12 Tournai Hainaut 7500",
    "addr:housenumber":"12",
    "addr:postcode":"7500",
    "addr:street":"Rue Pasquier Grenier",
    "iso:country":"BE",
    "sg:address":"Rue Pasquier Grenier 12",
    "sg:city":"Tournai",
    "sg:orig_category":"Production and transformation de viande",
    "sg:phone":"+32 69 22 20 36",
    "sg:postcode":"7500",
    "sg:province":"Hainaut",
    "wof:name":"Tournai Meat Industrye E",
    "wof:placetype":"venue"
},
  "geometry": {"coordinates":[3.3780989647,50.6196899414],"type":"Point"}
}