{
  "type": "Feature",
  "properties": {
    "addr:full":"Avenue De Philippeville 244 Charleroi Hainaut 6001",
    "addr:housenumber":"244",
    "addr:postcode":"6001",
    "addr:street":"Avenue De Philippeville;Hainaut",
    "iso:country":"BE",
    "sg:address":"Avenue De Philippeville 244",
    "sg:city":"Charleroi",
    "sg:orig_category":"Onderdelen and accessoires voor auto's",
    "sg:phone":"+32 71 47 31 50",
    "sg:postcode":"6001",
    "sg:province":"Hainaut",
    "wof:name":"Auto Alarm Service",
    "wof:placetype":"venue"
},
  "geometry": {"coordinates":[4.4543647766,50.3975028992],"type":"Point"}
}