{
  "type": "Feature",
  "properties": {
    "addr:full":"Kempische Kaai 43b1 Hasselt Limburg 3500",
    "addr:housenumber":"43b1",
    "addr:postcode":"3500",
    "addr:street":"Kempische Kaai",
    "iso:country":"BE",
    "sg:address":"Kempische Kaai 43b1",
    "sg:city":"Hasselt",
    "sg:orig_category":"Boekenuitgeverijen",
    "sg:phone":"+32 11 72 47 05",
    "sg:postcode":"3500",
    "sg:province":"Limburg",
    "wof:name":"Uitgeverij Sms Music",
    "wof:placetype":"venue"
},
  "geometry": {"coordinates":[5.3372597694,50.9374046326],"type":"Point"}
}