{
  "type": "Feature",
  "properties": {
    "iso:country":"BE",
    "sg:address":"Avenue Des Tilleuls 20",
    "sg:city":"Durbuy (barvaux-sur-ourthe)",
    "sg:classifiers":[
        {
            "category":"Manufacturing",
            "subcategory":"Metals",
            "type":"Manufacturing & Wholesale Goods"
        }
    ],
    "sg:phone":"+32 86 21 16 97",
    "sg:postcode":"6940",
    "sg:province":"Luxembourg",
    "sg:tags":[
        "working"
    ],
    "wof:name":"Marechal L",
    "wof:placetype":"venue"
},
  "geometry": {"coordinates":[5.4543361664,50.3515777588],"type":"Point"}
}