{
  "type": "Feature",
  "properties": {
    "addr:full":"Daalstraat 61 Wevelgem West-Vlaanderen 8560",
    "addr:housenumber":"61",
    "addr:postcode":"8560",
    "addr:street":"Daalstraat",
    "iso:country":"BE",
    "sg:address":"Daalstraat 61",
    "sg:city":"Wevelgem",
    "sg:orig_category":"Producteurs de l\u00e9gumes",
    "sg:phone":"+32 56 42 59 49",
    "sg:postcode":"8560",
    "sg:province":"West-Vlaanderen",
    "wof:name":"Thermote-hoflack Marc",
    "wof:placetype":"venue"
},
  "geometry": {"coordinates":[3.1961131096,50.8543014526],"type":"Point"}
}