{
  "type": "Feature",
  "properties": {
    "iso:country":"BE",
    "sg:address":"Donkstraat 106",
    "sg:city":"Maldegem",
    "sg:classifiers":[
        {
            "category":"Social Services",
            "subcategory":"Retirement Home",
            "type":"Services"
        }
    ],
    "sg:phone":"+32 486 88 49 85",
    "sg:postcode":"9990",
    "sg:province":"Oost-Vlaanderen",
    "sg:tags":[
        "society",
        "protection",
        "animal"
    ],
    "wof:name":"Pet's Friends Vzw",
    "wof:placetype":"venue"
},
  "geometry": {"coordinates":[3.3835599422,51.2139816284],"type":"Point"}
}