{
  "type": "Feature",
  "properties": {
    "addr:full":"Rue Abb\u00c9 Pollart 6 Aiseau-presles Hainaut 6250",
    "addr:housenumber":"6",
    "addr:postcode":"6250",
    "addr:street":"Rue Abbe\u0301 Pollart;Hainaut",
    "iso:country":"BE",
    "sg:address":"Rue Abb\u00c9 Pollart 6",
    "sg:city":"Aiseau-presles",
    "sg:orig_category":"Apotheken",
    "sg:phone":"+32 71 77 25 19",
    "sg:postcode":"6250",
    "sg:province":"Hainaut",
    "wof:name":"Pharmaclaire",
    "wof:placetype":"venue"
},
  "geometry": {"coordinates":[4.5715508461,50.4275970459],"type":"Point"}
}