{
  "type": "Feature",
  "properties": {
    "iso:country":"BE",
    "sg:address":"Molenerf 3",
    "sg:city":"Nijlen",
    "sg:classifiers":[
        {
            "category":"Building & Trades",
            "subcategory":"Construction",
            "type":"Services"
        }
    ],
    "sg:phone":"+32 3 481 80 35",
    "sg:postcode":"2560",
    "sg:province":"Antwerpen",
    "sg:tags":[
        "stucco",
        "contractor"
    ],
    "wof:name":"Verhaegen G",
    "wof:placetype":"venue"
},
  "geometry": {"coordinates":[4.6604590416,51.1580696106],"type":"Point"}
}