{
  "type": "Feature",
  "properties": {
    "addr:full":"Rue Richard Vandevelde 36 Bruxelles (schaerbeek) Bruxelles-Capitale 1030",
    "addr:housenumber":"36",
    "addr:postcode":"1030",
    "addr:street":"Rue Richard Vandevelde",
    "iso:country":"BE",
    "sg:address":"Rue Richard Vandevelde 36",
    "sg:city":"Bruxelles (schaerbeek)",
    "sg:classifiers":[
        {
            "category":"Manufacturing",
            "subcategory":"Textiles",
            "type":"Manufacturing & Wholesale Goods"
        }
    ],
    "sg:phone":"+32 2 215 10 02",
    "sg:postcode":"1030",
    "sg:province":"Bruxelles-Capitale",
    "sg:tags":[
        "retail",
        "-"
    ],
    "wof:name":"Au Profit",
    "wof:placetype":"venue"
},
  "geometry": {"coordinates":[4.3883490562,50.8731575012],"type":"Point"}
}