{
  "type": "Feature",
  "properties": {
    "addr:full":"Breydelhofstraat 35 Ieper West-Vlaanderen 8900",
    "addr:housenumber":"35",
    "addr:postcode":"8900",
    "addr:street":"Breydelhofstraat",
    "iso:country":"BE",
    "sg:address":"Breydelhofstraat 35",
    "sg:city":"Ieper",
    "sg:orig_category":"Instituts de beaut\u00e9",
    "sg:phone":"+32 57 21 81 18",
    "sg:postcode":"8900",
    "sg:province":"West-Vlaanderen",
    "wof:name":"Regine Thery",
    "wof:placetype":"venue"
},
  "geometry": {"coordinates":[2.8433749676,50.86743927],"type":"Point"}
}