{
  "type": "Feature",
  "properties": {
    "addr:full":"Rue De Nimy 60 Mons Hainaut 7000",
    "addr:housenumber":"60",
    "addr:postcode":"7000",
    "addr:street":"Rue De Nimy;Hainaut",
    "iso:country":"BE",
    "sg:address":"Rue De Nimy 60",
    "sg:city":"Mons",
    "sg:classifiers":[
        {
            "category":"Shopping",
            "subcategory":"Florist",
            "type":"Retail Goods"
        }
    ],
    "sg:phone":"+32 65 84 92 51",
    "sg:postcode":"7000",
    "sg:province":"Hainaut",
    "wof:name":"Privileges",
    "wof:placetype":"venue"
},
  "geometry": {"coordinates":[3.9552459717,50.4571113586],"type":"Point"}
}