{
  "type": "Feature",
  "properties": {
    "iso:country":"BE",
    "sg:address":"Chemin Des Bois 43",
    "sg:city":"Fleurus",
    "sg:classifiers":[
        {
            "category":"Food & Beverages",
            "subcategory":"Meat & Fish",
            "type":"Retail Goods"
        }
    ],
    "sg:phone":"+32 71 81 49 98",
    "sg:postcode":"6220",
    "sg:province":"Hainaut",
    "sg:tags":[
        "-",
        "livestock"
    ],
    "wof:name":"Oli'vert",
    "wof:placetype":"venue"
},
  "geometry": {"coordinates":[4.54317379,50.4785919189],"type":"Point"}
}