{
  "type": "Feature",
  "properties": {
    "iso:country":"BE",
    "sg:address":"Square Drouet D'erlon 53",
    "sg:city":"Braine-l'alleud",
    "sg:classifiers":[
        {
            "category":"Arena",
            "subcategory":"Sports Club",
            "type":"Entertainment"
        }
    ],
    "sg:phone":"+32 2 385 04 72",
    "sg:postcode":"1420",
    "sg:province":"Brabant Wallon",
    "sg:tags":[
        "de"
    ],
    "wof:name":"Royal Brussels Poseidon",
    "wof:placetype":"venue"
},
  "geometry": {"coordinates":[-0.6284090281,47.4790840149],"type":"Point"}
}