{
  "type": "Feature",
  "properties": {
    "iso:country":"BE",
    "sg:address":"Parc Saint-job 11",
    "sg:city":"Wavre",
    "sg:orig_category":"Immobili\u00ebnkantoren",
    "sg:phone":"+32 10 24 10 50",
    "sg:postcode":"1300",
    "sg:province":"Brabant Wallon",
    "wof:name":"Exclusif Immo",
    "wof:placetype":"venue"
},
  "geometry": {"coordinates":[4.6240382195,50.7210998535],"type":"Point"}
}