{
  "type": "Feature",
  "properties": {
    "addr:full":"Place Saint-lambert 11 Bruxelles Bruxelles-Capitale 1020",
    "addr:housenumber":"11",
    "addr:postcode":"1020",
    "addr:street":"Place Saint-Lambert",
    "iso:country":"BE",
    "sg:address":"Place Saint-lambert 11",
    "sg:city":"Bruxelles",
    "sg:classifiers":[
        {
            "category":"Shopping",
            "subcategory":"Books",
            "type":"Retail Goods"
        }
    ],
    "sg:phone":"+32 2 476 22 62",
    "sg:postcode":"1020",
    "sg:province":"Bruxelles-Capitale",
    "sg:tags":[
        "bookseller"
    ],
    "wof:name":"Forum Presse",
    "wof:placetype":"venue"
},
  "geometry": {"coordinates":[4.3440189362,50.8902816772],"type":"Point"}
}