{
  "type": "Feature",
  "properties": {
    "iso:country":"BE",
    "sg:address":"Rue Du Grillon 30",
    "sg:city":"Seraing",
    "sg:orig_category":"Installation \u00e9lectrique r\u00e9sidentielle",
    "sg:phone":"+32 4 337 88 60",
    "sg:postcode":"4100",
    "sg:province":"Li\u00e8ge",
    "wof:name":"M.e.i. Engineering",
    "wof:placetype":"venue"
},
  "geometry": {"coordinates":[5.4961719513,50.5832061768],"type":"Point"}
}