{
  "type": "Feature",
  "properties": {
    "addr:full":"Waterloose Steenweg 579 Elsene/ixelles Bruxelles-Capitale 1050",
    "addr:housenumber":"579",
    "addr:postcode":"1050",
    "addr:street":"Waterloose Steenweg",
    "iso:country":"BE",
    "sg:address":"Waterloose Steenweg 579",
    "sg:city":"Elsene/ixelles",
    "sg:orig_category":"Herenkledingzaken",
    "sg:phone":"+32 2 347 49 84",
    "sg:postcode":"1050",
    "sg:province":"Bruxelles-Capitale",
    "wof:name":"Parachute Jump",
    "wof:placetype":"venue"
},
  "geometry": {"coordinates":[4.362929821,50.8185997009],"type":"Point"}
}