{
  "type": "Feature",
  "properties": {
    "addr:full":"Place De Waressaix 12a Estinnes (haulchin) Hainaut 7120",
    "addr:housenumber":"12a",
    "addr:postcode":"7120",
    "addr:street":"Place De Waressaix",
    "iso:country":"BE",
    "sg:address":"Place De Waressaix 12a",
    "sg:city":"Estinnes (haulchin)",
    "sg:classifiers":[
        {
            "category":"Retail",
            "subcategory":"Funeral Services",
            "type":"Services"
        }
    ],
    "sg:phone":"+32 65 58 65 32",
    "sg:postcode":"7120",
    "sg:province":"Hainaut",
    "sg:tags":[
        "director"
    ],
    "wof:name":"Catherine Rene Sprl",
    "wof:placetype":"venue"
},
  "geometry": {"coordinates":[4.0862698555,50.386264801],"type":"Point"}
}