{
  "type": "Feature",
  "properties": {
    "addr:full":"Chauss\u00e9e De Marche 1017 Namur (wierde) Namur 5100",
    "addr:postcode":"1017;5100",
    "addr:street":"Chausse\u0301E De Marche",
    "iso:country":"BE",
    "sg:address":"Chauss\u00e9e De Marche 1017",
    "sg:city":"Namur (wierde)",
    "sg:classifiers":[
        {
            "category":"Home & Garden",
            "subcategory":"Home Furnishings",
            "type":"Retail Goods"
        }
    ],
    "sg:phone":"+32 81 43 52 42",
    "sg:postcode":"5100",
    "sg:province":"Namur",
    "sg:tags":[
        "-",
        "bed",
        "mattress"
    ],
    "wof:name":"Belgique Literie",
    "wof:placetype":"venue"
},
  "geometry": {"coordinates":[4.8713750839,50.4566345215],"type":"Point"}
}