{
  "type": "Feature",
  "properties": {
    "addr:full":"Av. De Woluwe-st-lambert 52 Sint-lambrechts-woluwe/woluwe-saint-lambert Bruxelles-Capitale 1200",
    "addr:housenumber":"52",
    "addr:postcode":"1200",
    "addr:street":"Av. De Woluwe-St-Lambert",
    "iso:country":"BE",
    "sg:address":"Av. De Woluwe-st-lambert 52",
    "sg:city":"Sint-lambrechts-woluwe/woluwe-saint-lambert",
    "sg:orig_category":"Rev\u00eatements pour sols and murs. Peinture",
    "sg:phone":"+32 2 742 06 41",
    "sg:postcode":"1200",
    "sg:province":"Bruxelles-Capitale",
    "wof:name":"K.v.j. Invest",
    "wof:placetype":"venue"
},
  "geometry": {"coordinates":[4.4094829559,50.8398513794],"type":"Point"}
}