{
  "type": "Feature",
  "properties": {
    "iso:country":"BE",
    "sg:address":"Rue De Nivelles 18",
    "sg:city":"Wavre",
    "sg:classifiers":[
        {
            "category":"Insurance",
            "subcategory":"Insurance Agent",
            "type":"Services"
        }
    ],
    "sg:phone":"+32 10 22 63 97",
    "sg:postcode":"1300",
    "sg:province":"Brabant Wallon",
    "sg:tags":[
        "broker"
    ],
    "wof:name":"Axa Banque Sa",
    "wof:placetype":"venue"
},
  "geometry": {"coordinates":[4.6087441444,50.715877533],"type":"Point"}
}