{
  "type": "Feature",
  "properties": {
    "addr:full":"Rue De Petit-wasmes 69 Colfontaine Hainaut 7340",
    "addr:housenumber":"69",
    "addr:postcode":"7340",
    "addr:street":"Rue De Petit-Wasmes",
    "iso:country":"BE",
    "sg:address":"Rue De Petit-wasmes 69",
    "sg:city":"Colfontaine",
    "sg:orig_category":"Epiceries",
    "sg:phone":"+32 65 66 38 50",
    "sg:postcode":"7340",
    "sg:province":"Hainaut",
    "wof:name":"Courtheoux",
    "wof:placetype":"venue"
},
  "geometry": {"coordinates":[3.8338620663,50.4074554443],"type":"Point"}
}