{
  "type": "Feature",
  "properties": {
    "iso:country":"BE",
    "sg:address":"Jan Breydellaan 7",
    "sg:city":"Wingene",
    "sg:orig_category":"Loodgieterij, verwarming and sanitaire installaties",
    "sg:phone":"+32 51 61 28 59",
    "sg:postcode":"8750",
    "sg:province":"West-Vlaanderen",
    "wof:name":"Loose Francky",
    "wof:placetype":"venue"
},
  "geometry": {"coordinates":[3.2235720158,51.0462760925],"type":"Point"}
}