{
  "type": "Feature",
  "properties": {
    "addr:full":"Rue Du Couvent 12 La Louviere Hainaut 7100",
    "addr:housenumber":"12",
    "addr:postcode":"7100",
    "addr:street":"Rue Du Couvent",
    "iso:country":"BE",
    "sg:address":"Rue Du Couvent 12",
    "sg:city":"La Louviere",
    "sg:orig_category":"D\u00e9taillants en pi\u00e8ces and accessoires de voitures",
    "sg:phone":"+32 64 28 54 87",
    "sg:postcode":"7100",
    "sg:province":"Hainaut",
    "wof:name":"Express Radiateurs",
    "wof:placetype":"venue"
},
  "geometry": {"coordinates":[4.204100132,50.4712600708],"type":"Point"}
}