{
  "type": "Feature",
  "properties": {
    "addr:full":"August Van Ackerstr 19 Eeklo Oost-Vlaanderen 9900",
    "addr:housenumber":"19",
    "addr:postcode":"9900",
    "addr:street":"August;Ackerstr",
    "iso:country":"BE",
    "sg:address":"August Van Ackerstr 19",
    "sg:city":"Eeklo",
    "sg:classifiers":[
        {
            "category":"Professional",
            "subcategory":"Business Services",
            "type":"Services"
        }
    ],
    "sg:phone":"+32 9 377 34 39",
    "sg:postcode":"9900",
    "sg:province":"Oost-Vlaanderen",
    "sg:tags":[
        "travel",
        "fair"
    ],
    "wof:name":"Hanssens Beatrijs Eg Clarebout M.",
    "wof:placetype":"venue"
},
  "geometry": {"coordinates":[3.5648200512,51.1876564026],"type":"Point"}
}