{
  "type": "Feature",
  "properties": {
    "addr:full":"Beukenlaan 36 Boom Antwerpen 2850",
    "addr:housenumber":"36",
    "addr:postcode":"2850",
    "addr:street":"Beukenlaan",
    "iso:country":"BE",
    "sg:address":"Beukenlaan 36",
    "sg:city":"Boom",
    "sg:orig_category":"Banken and kredietinstellingen",
    "sg:phone":"+32 3 844 83 63",
    "sg:postcode":"2850",
    "sg:province":"Antwerpen",
    "wof:name":"Groep Argenta",
    "wof:placetype":"venue"
},
  "geometry": {"coordinates":[4.3681731224,51.0967712402],"type":"Point"}
}