{
  "type": "Feature",
  "properties": {
    "iso:country":"BE",
    "sg:address":"Woestijnstraat 23",
    "sg:city":"Bornem",
    "sg:orig_category":"Craneway Rails",
    "sg:phone":"+32 3 889 72 19",
    "sg:postcode":"2880",
    "sg:province":"Antwerpen",
    "wof:name":"Siro Construct Nv",
    "wof:placetype":"venue"
},
  "geometry": {"coordinates":[4.2713608742,51.0936775208],"type":"Point"}
}