{
  "type": "Feature",
  "properties": {
    "addr:full":"Warande 12 Kortrijk West-Vlaanderen 8501",
    "addr:housenumber":"12",
    "addr:postcode":"8501",
    "addr:street":"Warande",
    "iso:country":"BE",
    "sg:address":"Warande 12",
    "sg:city":"Kortrijk",
    "sg:orig_category":"Installation de menuiserie en bois and plastique",
    "sg:phone":"+32 56 35 94 50",
    "sg:postcode":"8501",
    "sg:province":"West-Vlaanderen",
    "wof:name":"Frank Casselein",
    "wof:placetype":"venue"
},
  "geometry": {"coordinates":[3.2406110764,50.8391914368],"type":"Point"}
}