{
  "type": "Feature",
  "properties": {
    "addr:full":"Rue Juliette Wytsman 57 Bruxelles (ixelles) Bruxelles-Capitale 1050",
    "addr:housenumber":"57",
    "addr:postcode":"1050",
    "addr:street":"Rue Juliette Wytsman",
    "iso:country":"BE",
    "sg:address":"Rue Juliette Wytsman 57",
    "sg:city":"Bruxelles (ixelles)",
    "sg:classifiers":[
        {
            "category":"Bakery",
            "type":"Food & Drink"
        }
    ],
    "sg:phone":"+32 2 647 52 81",
    "sg:postcode":"1050",
    "sg:province":"Bruxelles-Capitale",
    "sg:tags":[
        "confectioner",
        "baker"
    ],
    "wof:name":"Ghebresillasie",
    "wof:placetype":"venue"
},
  "geometry": {"coordinates":[4.3822488785,50.8236961365],"type":"Point"}
}