{
  "type": "Feature",
  "properties": {
    "addr:full":"Avenue Des Missionnaires 5 Anderlecht Bruxelles-Capitale 1070",
    "addr:housenumber":"5",
    "addr:postcode":"1070",
    "addr:street":"Avenue Des Missionnaires",
    "iso:country":"BE",
    "sg:address":"Avenue Des Missionnaires 5",
    "sg:city":"Anderlecht",
    "sg:orig_category":"Maroquinerie Fab",
    "sg:phone":"+32 2 414 85 07",
    "sg:postcode":"1070",
    "sg:province":"Bruxelles-Capitale",
    "wof:name":"Mommens",
    "wof:placetype":"venue"
},
  "geometry": {"coordinates":[4.3080420494,50.8480224609],"type":"Point"}
}