{
  "type": "Feature",
  "properties": {
    "iso:country":"BE",
    "sg:address":"Kriekelaarstraat 4",
    "sg:city":"Beveren",
    "sg:classifiers":[
        {
            "category":"Food & Beverages",
            "subcategory":"Fruits & Vegetables",
            "type":"Retail Goods"
        }
    ],
    "sg:phone":"+32 3 775 44 59",
    "sg:postcode":"9120",
    "sg:province":"Oost-Vlaanderen",
    "sg:tags":[
        "l\u00e9gumes"
    ],
    "wof:name":"Roger De Vleeschhauwer",
    "wof:placetype":"venue"
},
  "geometry": {"coordinates":[4.1994791031,51.2042999268],"type":"Point"}
}