{
  "type": "Feature",
  "properties": {
    "addr:full":"Leopoldlaan 103 Middelkerke West-Vlaanderen 8430",
    "addr:housenumber":"103",
    "addr:postcode":"8430",
    "addr:street":"Leopoldlaan",
    "iso:country":"BE",
    "sg:address":"Leopoldlaan 103",
    "sg:city":"Middelkerke",
    "sg:classifiers":[
        {
            "category":"Restaurant",
            "type":"Food & Drink"
        }
    ],
    "sg:phone":"+32 59 30 52 68",
    "sg:postcode":"8430",
    "sg:province":"West-Vlaanderen",
    "wof:name":"Sirene",
    "wof:placetype":"venue"
},
  "geometry": {"coordinates":[2.8117160797,51.1861305237],"type":"Point"}
}