{
  "type": "Feature",
  "properties": {
    "addr:full":"Rue Du Haut-pav\u00e9 76 Li\u00e8ge 1 Li\u00e8ge 4000",
    "addr:housenumber":"76;1",
    "addr:postcode":"4000",
    "addr:street":"Rue Du Haut-Pave\u0301",
    "iso:country":"BE",
    "sg:address":"Rue Du Haut-pav\u00e9 76",
    "sg:city":"Li\u00e8ge 1",
    "sg:classifiers":[
        {
            "category":"Personal",
            "subcategory":"Beauty Salon",
            "type":"Services"
        }
    ],
    "sg:phone":"+32 4 227 06 73",
    "sg:postcode":"4000",
    "sg:province":"Li\u00e8ge",
    "sg:tags":[
        "lady",
        "-",
        "hairdressing"
    ],
    "wof:name":"Alphonsine",
    "wof:placetype":"venue"
},
  "geometry": {"coordinates":[5.5966191292,50.6651611328],"type":"Point"}
}