{
  "type": "Feature",
  "properties": {
    "addr:full":"Ronkenburgstraat 7 Lede Oost-Vlaanderen 9340",
    "addr:housenumber":"7",
    "addr:postcode":"9340",
    "addr:street":"Ronkenburgstraat",
    "iso:country":"BE",
    "sg:address":"Ronkenburgstraat 7",
    "sg:city":"Lede",
    "sg:classifiers":[
        {
            "category":"Personal",
            "subcategory":"Beauty Salon",
            "type":"Services"
        }
    ],
    "sg:phone":"+32 53 80 48 32",
    "sg:postcode":"9340",
    "sg:province":"Oost-Vlaanderen",
    "sg:tags":[
        "lady",
        "-",
        "hairdressing"
    ],
    "wof:name":"Christine/hair Styliste",
    "wof:placetype":"venue"
},
  "geometry": {"coordinates":[3.9954020977,50.9751548767],"type":"Point"}
}