{
  "type": "Feature",
  "properties": {
    "addr:full":"Route De France 7ba Somme-leuze Namur 5377",
    "addr:postcode":"7ba;5377",
    "addr:street":"Route De France",
    "iso:country":"BE",
    "sg:address":"Route De France 7ba",
    "sg:city":"Somme-leuze",
    "sg:classifiers":[
        {
            "category":"Health Services",
            "subcategory":"Nursing And Care Facility",
            "type":"Services"
        }
    ],
    "sg:phone":"+32 86 32 31 73",
    "sg:postcode":"5377",
    "sg:province":"Namur",
    "sg:tags":[
        "public"
    ],
    "wof:name":"C.p.a.s.",
    "wof:placetype":"venue"
},
  "geometry": {"coordinates":[5.3402528763,50.290058136],"type":"Point"}
}