{
  "type": "Feature",
  "properties": {
    "iso:country":"BE",
    "sg:address":"Langendamdreef 8",
    "sg:city":"Aalter",
    "sg:classifiers":[
        {
            "category":"Real Estate",
            "subcategory":"Architect",
            "type":"Services"
        }
    ],
    "sg:phone":"+32 9 374 23 61",
    "sg:postcode":"9880",
    "sg:province":"Oost-Vlaanderen",
    "wof:name":"Vandeginste Y",
    "wof:placetype":"venue"
},
  "geometry": {"coordinates":[3.4591739178,51.0745811462],"type":"Point"}
}