{
  "type": "Feature",
  "properties": {
    "addr:full":"Oostenstraat 26-27 Antwerpen Antwerpen 2018",
    "addr:postcode":"26-27;2018",
    "addr:street":"Oostenstraat",
    "iso:country":"BE",
    "sg:address":"Oostenstraat 26-27",
    "sg:city":"Antwerpen",
    "sg:classifiers":[
        {
            "category":"Wholesale",
            "subcategory":"Wine & Distilled Alcoholic Beverages",
            "type":"Manufacturing & Wholesale Goods"
        }
    ],
    "sg:phone":"+32 3 218 84 25",
    "sg:postcode":"2018",
    "sg:province":"Antwerpen",
    "sg:tags":[
        "whol",
        "-",
        "spirit",
        "mfg"
    ],
    "wof:name":"Penen Wijnen",
    "wof:placetype":"venue"
},
  "geometry": {"coordinates":[4.4250469208,51.208114624],"type":"Point"}
}