{
  "type": "Feature",
  "properties": {
    "addr:full":"Rue Van Huynegem 22b5 Jette Bruxelles-Capitale 1090",
    "addr:housenumber":"22b5",
    "addr:postcode":"1090",
    "addr:street":"Rue Van Huynegem",
    "iso:country":"BE",
    "sg:address":"Rue Van Huynegem 22b5",
    "sg:city":"Jette",
    "sg:orig_category":"Boekhouders",
    "sg:phone":"+32 2 425 66 08",
    "sg:postcode":"1090",
    "sg:province":"Bruxelles-Capitale",
    "wof:name":"Mayo Andr\u00c9",
    "wof:placetype":"venue"
},
  "geometry": {"coordinates":[4.3279027939,50.8786239624],"type":"Point"}
}