{
  "type": "Feature",
  "properties": {
    "addr:full":"Heilig Bloedlaan 265 Hoogstraten Antwerpen 2320",
    "addr:housenumber":"265",
    "addr:postcode":"2320",
    "addr:street":"Heilig Bloedlaan",
    "iso:country":"BE",
    "sg:address":"Heilig Bloedlaan 265",
    "sg:city":"Hoogstraten",
    "sg:classifiers":[
        {
            "category":"Shopping",
            "subcategory":"Clothing, Apparel, & Fashions",
            "type":"Retail Goods"
        }
    ],
    "sg:phone":"+32 3 314 11 40",
    "sg:postcode":"2320",
    "sg:province":"Antwerpen",
    "sg:tags":[
        "lady",
        "clothing",
        "-"
    ],
    "wof:name":"Kalisto",
    "wof:placetype":"venue"
},
  "geometry": {"coordinates":[4.7594161034,51.3973121643],"type":"Point"}
}