{
  "type": "Feature",
  "properties": {
    "addr:full":"Borgerweert 9 Zwijndrecht Antwerpen 2070",
    "addr:housenumber":"9",
    "addr:postcode":"2070",
    "addr:street":"Borgerweert",
    "iso:country":"BE",
    "sg:address":"Borgerweert 9",
    "sg:city":"Zwijndrecht",
    "sg:orig_category":"Binnenhuisarchitecten",
    "sg:phone":"+32 3 252 92 16",
    "sg:postcode":"2070",
    "sg:province":"Antwerpen",
    "wof:name":"Caroline Guiette",
    "wof:placetype":"venue"
},
  "geometry": {"coordinates":[4.3478832245,51.2096939087],"type":"Point"}
}