{
  "type": "Feature",
  "properties": {
    "iso:country":"BE",
    "sg:address":"Rue Limnander 22",
    "sg:city":"Bruxelles (anderlecht)",
    "sg:orig_category":"Non-Classified Establishments",
    "sg:phone":"+32 2 523 66 56",
    "sg:postcode":"1070",
    "sg:province":"Bruxelles-Capitale",
    "wof:name":"Martine Samoun Sprl",
    "wof:placetype":"venue"
},
  "geometry": {"coordinates":[4.3368339539,50.8399810791],"type":"Point"}
}