{
  "type": "Feature",
  "properties": {
    "addr:full":"Sledderlo 63 Genk Limburg 3600",
    "addr:housenumber":"63",
    "addr:postcode":"3600",
    "addr:street":"Sledderlo",
    "iso:country":"BE",
    "sg:address":"Sledderlo 63",
    "sg:city":"Genk",
    "sg:classifiers":[
        {
            "category":"Restaurant",
            "type":"Food & Drink"
        }
    ],
    "sg:phone":"+32 89 61 28 03",
    "sg:postcode":"3600",
    "sg:province":"Limburg",
    "wof:name":"Hoeve- Restaurant Balkan - Grill",
    "wof:placetype":"venue"
},
  "geometry": {"coordinates":[5.5148539543,50.9483718872],"type":"Point"}
}