{
  "type": "Feature",
  "properties": {
    "iso:country":"BE",
    "sg:address":"August Wautersstraat 23",
    "sg:city":"Temse",
    "sg:orig_category":"Non-Classified Establishments",
    "sg:phone":"+32 3 771 01 38",
    "sg:postcode":"9140",
    "sg:province":"Oost-Vlaanderen",
    "wof:name":"Kockelbergh",
    "wof:placetype":"venue"
},
  "geometry": {"coordinates":[4.2184691429,51.1273841858],"type":"Point"}
}