{
  "type": "Feature",
  "properties": {
    "addr:full":"Infanteriestraat 3 Roeselare West-Vlaanderen 8800",
    "addr:housenumber":"3",
    "addr:postcode":"8800",
    "addr:street":"Infanteriestraat",
    "iso:country":"BE",
    "sg:address":"Infanteriestraat 3",
    "sg:city":"Roeselare",
    "sg:orig_category":"Meubles D\u00e9taillants, Am\u00e9nagement de B\u00e2timents et de Cuisines",
    "sg:phone":"+32 51 24 48 40",
    "sg:postcode":"8800",
    "sg:province":"West-Vlaanderen",
    "wof:name":"A. En C. Decor",
    "wof:placetype":"venue"
},
  "geometry": {"coordinates":[3.1071240902,50.9498176575],"type":"Point"}
}