{
  "type": "Feature",
  "properties": {
    "addr:full":"Daalmstraat 18a Zomergem (ronsele) Oost-Vlaanderen 9932",
    "addr:housenumber":"18a",
    "addr:postcode":"9932",
    "addr:street":"Daalmstraat",
    "iso:country":"BE",
    "sg:address":"Daalmstraat 18a",
    "sg:city":"Zomergem (ronsele)",
    "sg:classifiers":[
        {
            "category":"Building & Trades",
            "subcategory":"Landscaping Services",
            "type":"Services"
        }
    ],
    "sg:phone":"+32 9 372 83 08",
    "sg:postcode":"9932",
    "sg:province":"Oost-Vlaanderen",
    "sg:tags":[
        "gardening",
        "garden",
        "maintenance"
    ],
    "wof:name":"Trenson E",
    "wof:placetype":"venue"
},
  "geometry": {"coordinates":[3.5526299477,51.126121521],"type":"Point"}
}