{
  "type": "Feature",
  "properties": {
    "addr:full":"Rue De La Barge 114 Li\u00e8ge 1 (sclessin) Li\u00e8ge 4000",
    "addr:housenumber":"114;1",
    "addr:postcode":"4000",
    "addr:street":"Rue De La Barge;Sclessin Lie\u0300Ge",
    "iso:country":"BE",
    "sg:address":"Rue De La Barge 114",
    "sg:city":"Li\u00e8ge 1 (sclessin)",
    "sg:classifiers":[
        {
            "category":"Building & Trades",
            "subcategory":"Construction",
            "type":"Services"
        }
    ],
    "sg:phone":"+32 4 246 29 98",
    "sg:postcode":"4000",
    "sg:province":"Li\u00e8ge",
    "sg:tags":[
        "ceiling"
    ],
    "wof:name":"Fuliano S",
    "wof:placetype":"venue"
},
  "geometry": {"coordinates":[5.5376648903,50.6109275818],"type":"Point"}
}