{
  "type": "Feature",
  "properties": {
    "addr:full":"Karreweg 38a Maldegem Oost-Vlaanderen 9990",
    "addr:housenumber":"38a",
    "addr:postcode":"9990",
    "addr:street":"Karreweg",
    "iso:country":"BE",
    "sg:address":"Karreweg 38a",
    "sg:city":"Maldegem",
    "sg:classifiers":[
        {
            "category":"Building & Trades",
            "subcategory":"Landscaping Services",
            "type":"Services"
        }
    ],
    "sg:phone":"+32 50 71 98 26",
    "sg:postcode":"9990",
    "sg:province":"Oost-Vlaanderen",
    "sg:tags":[
        "slaughterer"
    ],
    "wof:name":"Bruggeman M",
    "wof:placetype":"venue"
},
  "geometry": {"coordinates":[3.4391689301,51.2104797363],"type":"Point"}
}