{
  "type": "Feature",
  "properties": {
    "addr:full":"Bilzerbaan 1 Lanaken Limburg 3620",
    "addr:housenumber":"1",
    "addr:postcode":"3620",
    "addr:street":"Bilzerbaan",
    "iso:country":"BE",
    "sg:address":"Bilzerbaan 1",
    "sg:city":"Lanaken",
    "sg:orig_category":"Plaatsen van vloer- and muurbekleding Schilders",
    "sg:phone":"+32 89 71 41 72",
    "sg:postcode":"3620",
    "sg:province":"Limburg",
    "wof:name":"Lambert Jorissen",
    "wof:placetype":"venue"
},
  "geometry": {"coordinates":[5.6551351547,50.8912277222],"type":"Point"}
}