{
  "type": "Feature",
  "properties": {
    "addr:full":"Stationsstraat 54 Peer Limburg 3990",
    "addr:housenumber":"54",
    "addr:postcode":"3990",
    "addr:street":"Stationsstraat",
    "iso:country":"BE",
    "sg:address":"Stationsstraat 54",
    "sg:city":"Peer",
    "sg:classifiers":[
        {
            "category":"Personal",
            "subcategory":"Beauty Salon",
            "type":"Services"
        }
    ],
    "sg:phone":"+32 11 63 28 65",
    "sg:postcode":"3990",
    "sg:province":"Limburg",
    "sg:tags":[
        "de",
        "coiffure"
    ],
    "wof:name":"Coiffure Margo",
    "wof:placetype":"venue"
},
  "geometry": {"coordinates":[5.4072508812,51.1287727356],"type":"Point"}
}