{
  "type": "Feature",
  "properties": {
    "addr:full":"Beverensestraat 33 Ardooie West-Vlaanderen 8850",
    "addr:housenumber":"33",
    "addr:postcode":"8850",
    "addr:street":"Beverensestraat",
    "iso:country":"BE",
    "sg:address":"Beverensestraat 33",
    "sg:city":"Ardooie",
    "sg:classifiers":[
        {
            "category":"Professional",
            "subcategory":"Art Services",
            "type":"Services"
        }
    ],
    "sg:phone":"+32 51 74 79 53",
    "sg:postcode":"8850",
    "sg:province":"West-Vlaanderen",
    "sg:tags":[
        "installation",
        "cafe",
        "-",
        "equipment"
    ],
    "wof:name":"Eurochair Projects Nv",
    "wof:placetype":"venue"
},
  "geometry": {"coordinates":[3.1932070255,50.9764328003],"type":"Point"}
}