{
  "type": "Feature",
  "properties": {
    "iso:country":"BE",
    "sg:address":"Tinstraat 44",
    "sg:city":"Putte",
    "sg:orig_category":"Eleveurs de bovins. Producteurs de l\u00e9gumes",
    "sg:phone":"+32 15 75 69 10",
    "sg:postcode":"2580",
    "sg:province":"Antwerpen",
    "wof:name":"Jos Van Hove",
    "wof:placetype":"venue"
},
  "geometry": {"coordinates":[4.6273121834,51.0401306152],"type":"Point"}
}