{
  "type": "Feature",
  "properties": {
    "addr:full":"Noordstraat 32 Assenede Oost-Vlaanderen 9961",
    "addr:housenumber":"32",
    "addr:postcode":"9961",
    "addr:street":"Noordstraat",
    "iso:country":"BE",
    "sg:address":"Noordstraat 32",
    "sg:city":"Assenede",
    "sg:orig_category":"Kapsalons",
    "sg:phone":"+32 9 373 66 04",
    "sg:postcode":"9961",
    "sg:province":"Oost-Vlaanderen",
    "wof:name":"Hubert Bral",
    "wof:placetype":"venue"
},
  "geometry": {"coordinates":[3.7533829212,51.2274360657],"type":"Point"}
}