{
  "type": "Feature",
  "properties": {
    "iso:country":"BE",
    "sg:address":"Cokaifagne 49",
    "sg:city":"Jalhay (sart)",
    "sg:classifiers":[
        {
            "category":"Sports & Exercise",
            "subcategory":"Swimming Pool",
            "type":"Entertainment"
        }
    ],
    "sg:phone":"+32 87 47 50 16",
    "sg:postcode":"4845",
    "sg:province":"Li\u00e8ge",
    "sg:tags":[
        "cover",
        "-"
    ],
    "wof:name":"Piscine D'almar",
    "wof:placetype":"venue"
},
  "geometry": {"coordinates":[5.9655108452,50.4871177673],"type":"Point"}
}