{
  "type": "Feature",
  "properties": {
    "iso:country":"BE",
    "sg:address":"Driesstraat 120",
    "sg:city":"Sint-lambrechts-woluwe/woluwe-saint-lambert",
    "sg:orig_category":"Schoonheidssalons",
    "sg:phone":"+32 2 772 93 70",
    "sg:postcode":"1200",
    "sg:province":"Bruxelles-Capitale",
    "wof:name":"Antoinette Chiarot",
    "wof:placetype":"venue"
},
  "geometry": {"coordinates":[4.4248142242,50.8462562561],"type":"Point"}
}