{
  "type": "Feature",
  "properties": {
    "addr:full":"Avenue Montjoie 3 Ukkel/uccle Bruxelles-Capitale 1180",
    "addr:housenumber":"3",
    "addr:postcode":"1180",
    "addr:street":"Avenue Montjoie;/",
    "iso:country":"BE",
    "sg:address":"Avenue Montjoie 3",
    "sg:city":"Ukkel/uccle",
    "sg:orig_category":"Artistes ind\u00e9pendants",
    "sg:phone":"+32 2 343 81 96",
    "sg:postcode":"1180",
    "sg:province":"Bruxelles-Capitale",
    "wof:name":"Tamara Diatchenko",
    "wof:placetype":"venue"
},
  "geometry": {"coordinates":[4.3684329987,50.8107147217],"type":"Point"}
}