{
  "type": "Feature",
  "properties": {
    "addr:full":"Zomerstraat 108 Elsene/ixelles Bruxelles-Capitale 1050",
    "addr:housenumber":"108",
    "addr:postcode":"1050",
    "addr:street":"Zomerstraat",
    "iso:country":"BE",
    "sg:address":"Zomerstraat 108",
    "sg:city":"Elsene/ixelles",
    "sg:orig_category":"Databanken Drukkerijen and copyshops Secretariaatsdiensten Software ontwikkeling and ontwerp",
    "sg:phone":"+32 2 626 28 10",
    "sg:postcode":"1050",
    "sg:province":"Bruxelles-Capitale",
    "wof:name":"Poly Plans Micro Repro",
    "wof:placetype":"venue"
},
  "geometry": {"coordinates":[4.3899312019,50.8181381226],"type":"Point"}
}