{
  "type": "Feature",
  "properties": {
    "iso:country":"BE",
    "sg:address":"Bovelingenstraat 204",
    "sg:city":"Heers",
    "sg:classifiers":[
        {
            "category":"Arena",
            "subcategory":"Sports Club",
            "type":"Entertainment"
        }
    ],
    "sg:phone":"+32 11 48 61 82",
    "sg:postcode":"3870",
    "sg:province":"Limburg",
    "sg:tags":[
        "de"
    ],
    "wof:name":"T.c. Heers",
    "wof:placetype":"venue"
},
  "geometry": {"coordinates":[5.2581949234,50.7392425537],"type":"Point"}
}