{
  "type": "Feature",
  "properties": {
    "addr:full":"Rue Du Vivier 8 Marche-en-famenne (aye) Luxembourg 6900",
    "addr:housenumber":"8",
    "addr:postcode":"6900",
    "addr:street":"Rue Du Vivier",
    "iso:country":"BE",
    "sg:address":"Rue Du Vivier 8",
    "sg:city":"Marche-en-famenne (aye)",
    "sg:classifiers":[
        {
            "category":"Home & Garden",
            "subcategory":"Household Appliances",
            "type":"Retail Goods"
        }
    ],
    "sg:phone":"+32 84 32 17 11",
    "sg:postcode":"6900",
    "sg:province":"Luxembourg",
    "sg:tags":[
        "repair",
        "mainten",
        "-",
        "electric"
    ],
    "wof:name":"Eldi",
    "wof:placetype":"venue"
},
  "geometry": {"coordinates":[5.3275151253,50.2291488647],"type":"Point"}
}