{
  "type": "Feature",
  "properties": {
    "iso:country":"BE",
    "sg:address":"Dorpstraat 34",
    "sg:city":"Koekelare",
    "sg:classifiers":[
        {
            "category":"Shopping",
            "subcategory":"Shoes",
            "type":"Retail Goods"
        }
    ],
    "sg:phone":"+32 51 58 81 02",
    "sg:postcode":"8680",
    "sg:province":"West-Vlaanderen",
    "sg:tags":[
        "slipper",
        "-"
    ],
    "wof:name":"Awa Schoenen",
    "wof:placetype":"venue"
},
  "geometry": {"coordinates":[2.9750800133,51.0895805359],"type":"Point"}
}