{
  "type": "Feature",
  "properties": {
    "iso:country":"BE",
    "sg:address":"Rue Albert 1er 78",
    "sg:city":"Hannut",
    "sg:orig_category":"Bloemen and planten",
    "sg:phone":"+32 19 51 47 35",
    "sg:postcode":"4280",
    "sg:province":"Li\u00e8ge",
    "wof:name":"Anthos",
    "wof:placetype":"venue"
},
  "geometry": {"coordinates":[5.0835189819,50.6692047119],"type":"Point"}
}