{
  "type": "Feature",
  "properties": {
    "iso:country":"BE",
    "sg:address":"Chauss\u00e9e D'aelbeke 238",
    "sg:city":"Mouscron",
    "sg:classifiers":[
        {
            "category":"Health Services",
            "subcategory":"Doctor",
            "type":"Services"
        }
    ],
    "sg:phone":"+32 56 34 51 07",
    "sg:postcode":"7700",
    "sg:province":"Hainaut",
    "sg:tags":[
        "medicinephysicians",
        "surgeon"
    ],
    "wof:name":"Gadisseux Ph",
    "wof:placetype":"venue"
},
  "geometry": {"coordinates":[3.22239995,50.7571372986],"type":"Point"}
}