{
  "type": "Feature",
  "properties": {
    "iso:country":"BE",
    "sg:address":"Regenboogstraat 1",
    "sg:city":"Bree",
    "sg:orig_category":"Fietsen HERSTELLING ELEKTRISCHE HUISHOUDAPPARATEN Huishoudapparaten, televisies and radio's",
    "sg:phone":"+32 89 46 13 49",
    "sg:postcode":"3960",
    "sg:province":"Limburg",
    "wof:name":"Lemmens",
    "wof:placetype":"venue"
},
  "geometry": {"coordinates":[5.6026449203,51.1400566101],"type":"Point"}
}