{
  "type": "Feature",
  "properties": {
    "addr:full":"Rue Arthur Descamps 125 Colfontaine Hainaut 7340",
    "addr:housenumber":"125",
    "addr:postcode":"7340",
    "addr:street":"Rue Arthur Descamps",
    "iso:country":"BE",
    "sg:address":"Rue Arthur Descamps 125",
    "sg:city":"Colfontaine",
    "sg:orig_category":"Rusthuizen and serviceflats",
    "sg:phone":"+32 65 67 44 71",
    "sg:postcode":"7340",
    "sg:province":"Hainaut",
    "wof:name":"R\u00c9sidence Joli Bois",
    "wof:placetype":"venue"
},
  "geometry": {"coordinates":[3.843405962,50.4191017151],"type":"Point"}
}