{
  "type": "Feature",
  "properties": {
    "iso:country":"BE",
    "sg:address":"Kerkstraat 11",
    "sg:city":"Schilde ('s Gravenwezel)",
    "sg:classifiers":[
        {
            "category":"Bakery",
            "type":"Food & Drink"
        }
    ],
    "sg:phone":"+32 3 658 28 76",
    "sg:postcode":"2970",
    "sg:province":"Antwerpen",
    "sg:tags":[
        "confectioner",
        "baker"
    ],
    "wof:name":"Vets J Bvba",
    "wof:placetype":"venue"
},
  "geometry": {"coordinates":[4.5830979347,51.2399864197],"type":"Point"}
}