{
  "type": "Feature",
  "properties": {
    "addr:full":"Route De Bastogne 17 Tenneville Luxembourg 6970",
    "addr:housenumber":"17",
    "addr:postcode":"6970",
    "addr:street":"Route De Bastogne",
    "iso:country":"BE",
    "sg:address":"Route De Bastogne 17",
    "sg:city":"Tenneville",
    "sg:orig_category":"Banques and organismes de cr\u00e9dit",
    "sg:phone":"+32 84 45 55 11",
    "sg:postcode":"6970",
    "sg:province":"Luxembourg",
    "wof:name":"Fortis",
    "wof:placetype":"venue"
},
  "geometry": {"coordinates":[5.5240907669,50.0920448303],"type":"Point"}
}