{
  "type": "Feature",
  "properties": {
    "iso:country":"BE",
    "sg:address":"Horstebaan 95",
    "sg:city":"Schoten",
    "sg:classifiers":[
        {
            "category":"Professional",
            "subcategory":"Accounting & Tax Preparation",
            "type":"Services"
        }
    ],
    "sg:phone":"+32 3 680 24 21",
    "sg:postcode":"2900",
    "sg:province":"Antwerpen",
    "sg:tags":[
        "bookkeeper"
    ],
    "wof:name":"Lelieur M",
    "wof:placetype":"venue"
},
  "geometry": {"coordinates":[4.4847640991,51.2582740784],"type":"Point"}
}