{
  "type": "Feature",
  "properties": {
    "addr:full":"Place F\u00e9lix Moinnil 247 Andenne (landenne) Namur 5300",
    "addr:housenumber":"247",
    "addr:postcode":"5300",
    "addr:street":"Place Fe\u0301Lix Moinnil",
    "iso:country":"BE",
    "sg:address":"Place F\u00e9lix Moinnil 247",
    "sg:city":"Andenne (landenne)",
    "sg:classifiers":[
        {
            "category":"Food & Beverages",
            "subcategory":"Groceries & Convenience Stores",
            "type":"Retail Goods"
        }
    ],
    "sg:phone":"+32 85 82 56 21",
    "sg:postcode":"5300",
    "sg:province":"Namur",
    "sg:tags":[
        "grocer"
    ],
    "wof:name":"Alidel Sprl",
    "wof:placetype":"venue"
},
  "geometry": {"coordinates":[5.0982642174,50.4863739014],"type":"Point"}
}