{
  "type": "Feature",
  "properties": {
    "addr:full":"Rue D'alsace Lorraine 30 Bruxelles (ixelles) Bruxelles-Capitale 1050",
    "addr:housenumber":"30",
    "addr:postcode":"1050",
    "addr:street":"Rue D'Alsace Lorraine",
    "iso:country":"BE",
    "sg:address":"Rue D'alsace Lorraine 30",
    "sg:city":"Bruxelles (ixelles)",
    "sg:classifiers":[
        {
            "category":"Building & Trades",
            "subcategory":"Electrical",
            "type":"Services"
        }
    ],
    "sg:phone":"+32 2 512 56 21",
    "sg:postcode":"1050",
    "sg:province":"Bruxelles-Capitale",
    "sg:tags":[
        "-",
        "electric",
        "contractor"
    ],
    "wof:name":"Cosyns Cie",
    "wof:placetype":"venue"
},
  "geometry": {"coordinates":[4.3798799515,50.8206710815],"type":"Point"}
}