{
  "type": "Feature",
  "properties": {
    "iso:country":"BE",
    "sg:address":"Rue Ferrer 32 Box A",
    "sg:city":"Hensies (thulin)",
    "sg:classifiers":[
        {
            "category":"Retail",
            "subcategory":"Event Space",
            "type":"Services"
        }
    ],
    "sg:phone":"+32 65 63 16 41",
    "sg:postcode":"7350",
    "sg:province":"Hainaut",
    "sg:tags":[
        "rental",
        "-",
        "hall"
    ],
    "wof:name":"La Concorde",
    "wof:placetype":"venue"
},
  "geometry": {"coordinates":[3.684994936,50.4326210022],"type":"Point"}
}