{
  "type": "Feature",
  "properties": {
    "addr:full":"Gruitroderlaan 78 Maaseik Limburg 3680",
    "addr:housenumber":"78",
    "addr:postcode":"3680",
    "addr:street":"Gruitroderlaan",
    "iso:country":"BE",
    "sg:address":"Gruitroderlaan 78",
    "sg:city":"Maaseik",
    "sg:orig_category":"Dakwerken",
    "sg:phone":"+32 89 86 41 45",
    "sg:postcode":"3680",
    "sg:province":"Limburg",
    "wof:name":"Verheyen & Meus",
    "wof:placetype":"venue"
},
  "geometry": {"coordinates":[5.791285038,51.0954208374],"type":"Point"}
}