{
  "type": "Feature",
  "properties": {
    "addr:full":"Rue Jean Van Lierde 105 Bruxelles (anderlecht) Bruxelles-Capitale 1070",
    "addr:housenumber":"105",
    "addr:postcode":"1070",
    "addr:street":"Rue Jean Van Lierde",
    "iso:country":"BE",
    "sg:address":"Rue Jean Van Lierde 105",
    "sg:city":"Bruxelles (anderlecht)",
    "sg:orig_category":"Non-Classified Establishments",
    "sg:phone":"+32 475 32 40 13",
    "sg:postcode":"1070",
    "sg:province":"Bruxelles-Capitale",
    "wof:name":"Ws Sales & Marketing Sprl",
    "wof:placetype":"venue"
},
  "geometry": {"coordinates":[4.3004422188,50.8447761536],"type":"Point"}
}