{
  "type": "Feature",
  "properties": {
    "addr:full":"Cardijnlaan 17 Diksmuide West-Vlaanderen 8600",
    "addr:housenumber":"17",
    "addr:postcode":"8600",
    "addr:street":"Cardijnlaan",
    "iso:country":"BE",
    "sg:address":"Cardijnlaan 17",
    "sg:city":"Diksmuide",
    "sg:orig_category":"Gestion des d\u00e9charges and sites d\u00e9finitifs de stockage",
    "sg:phone":"+32 51 50 30 01",
    "sg:postcode":"8600",
    "sg:province":"West-Vlaanderen",
    "wof:name":"Containerpark Diksmuide",
    "wof:placetype":"venue"
},
  "geometry": {"coordinates":[2.8534739017,51.0213470459],"type":"Point"}
}