{
  "type": "Feature",
  "properties": {
    "iso:country":"BE",
    "sg:address":"Groenlaan 15",
    "sg:city":"Tervuren",
    "sg:orig_category":"Agences immobili\u00e8res",
    "sg:phone":"+32 2 768 22 71",
    "sg:postcode":"3080",
    "sg:province":"Vlaams-Brabant",
    "wof:name":"Barnes & Clayton",
    "wof:placetype":"venue"
},
  "geometry": {"coordinates":[4.5422649384,50.8528633118],"type":"Point"}
}