{
  "type": "Feature",
  "properties": {
    "iso:country":"BE",
    "sg:address":"Caignaardstraat 8",
    "sg:city":"Wielsbeke (sint-baafs-vijve)",
    "sg:classifiers":[
        {
            "category":"Ice Cream",
            "type":"Food & Drink"
        }
    ],
    "sg:phone":"+32 56 66 73 62",
    "sg:postcode":"8710",
    "sg:province":"West-Vlaanderen",
    "wof:name":"Haerinck",
    "wof:placetype":"venue"
},
  "geometry": {"coordinates":[3.3813960552,50.9224052429],"type":"Point"}
}