{
  "type": "Feature",
  "properties": {
    "iso:country":"BE",
    "sg:address":"Macharius Rheynstraat 26",
    "sg:city":"Sint-gillis-waas (de Klinge)",
    "sg:classifiers":[
        {
            "category":"Personal",
            "subcategory":"Beauty Salon",
            "type":"Services"
        }
    ],
    "sg:phone":"+32 3 707 14 64",
    "sg:postcode":"9170",
    "sg:province":"Oost-Vlaanderen",
    "sg:tags":[
        "lady",
        "-",
        "hairdressing"
    ],
    "wof:name":"De Roos C",
    "wof:placetype":"venue"
},
  "geometry": {"coordinates":[4.0822100639,51.2534141541],"type":"Point"}
}