{
  "type": "Feature",
  "properties": {
    "addr:full":"Beddenstraat 2b40 Antwerpen Antwerpen 2000",
    "addr:housenumber":"2b40",
    "addr:postcode":"2000",
    "addr:street":"Beddenstraat",
    "iso:country":"BE",
    "sg:address":"Beddenstraat 2b40",
    "sg:city":"Antwerpen",
    "sg:orig_category":"Opticiens",
    "sg:phone":"+32 3 232 64 11",
    "sg:postcode":"2000",
    "sg:province":"Antwerpen",
    "wof:name":"Hans Anders Optiek",
    "wof:placetype":"venue"
},
  "geometry": {"coordinates":[4.4034647942,51.2188110352],"type":"Point"}
}