{
  "type": "Feature",
  "properties": {
    "iso:country":"BE",
    "sg:address":"Lepelvormweg 24",
    "sg:city":"Lanaken",
    "sg:orig_category":"Herstellingen and onderhoud aan huis voor voertuigen Herstellingen and onderhoud van auto's Metaalaf",
    "sg:phone":"+32 89 71 71 95",
    "sg:postcode":"3620",
    "sg:province":"Limburg",
    "wof:name":"Nico Houben",
    "wof:placetype":"venue"
},
  "geometry": {"coordinates":[5.6358561516,50.9023933411],"type":"Point"}
}