{
  "type": "Feature",
  "properties": {
    "addr:full":"Rue Des Argili\u00c8res 47 Li\u00c8ge Li\u00e8ge 4020",
    "addr:housenumber":"47",
    "addr:postcode":"4020",
    "addr:street":"Rue Des Argilie\u0300Res",
    "iso:country":"BE",
    "sg:address":"Rue Des Argili\u00c8res 47",
    "sg:city":"Li\u00c8ge",
    "sg:orig_category":"Electrom\u00e9nager, t\u00e9l\u00e9visions and radios. R\u00e9parations d'appareils \u00e9lectrom\u00e9nagers",
    "sg:phone":"+32 4 362 86 29",
    "sg:postcode":"4020",
    "sg:province":"Li\u00e8ge",
    "wof:name":"Michel Vandeneede",
    "wof:placetype":"venue"
},
  "geometry": {"coordinates":[5.6346750259,50.6462516785],"type":"Point"}
}