{
  "type": "Feature",
  "properties": {
    "addr:full":"Rue De La Cul\u00c9e 35 Daverdisse Luxembourg 6929",
    "addr:housenumber":"35",
    "addr:postcode":"6929",
    "addr:street":"Rue De La Cule\u0301E",
    "iso:country":"BE",
    "sg:address":"Rue De La Cul\u00c9e 35",
    "sg:city":"Daverdisse",
    "sg:orig_category":"Woningbouw",
    "sg:phone":"+32 61 51 24 08",
    "sg:postcode":"6929",
    "sg:province":"Luxembourg",
    "wof:name":"Pierre Merny",
    "wof:placetype":"venue"
},
  "geometry": {"coordinates":[5.0633311272,49.9977645874],"type":"Point"}
}