{
  "type": "Feature",
  "properties": {
    "iso:country":"BE",
    "sg:address":"Gilliswinhof 1",
    "sg:city":"Tongeren",
    "sg:orig_category":"V\u00eatements pour Hommes",
    "sg:phone":"+32 12 39 15 00",
    "sg:postcode":"3700",
    "sg:province":"Limburg",
    "wof:name":"Vossen Young Men",
    "wof:placetype":"venue"
},
  "geometry": {"coordinates":[5.4636240005,50.7807197571],"type":"Point"}
}