{
  "type": "Feature",
  "properties": {
    "iso:country":"BE",
    "sg:address":"Fonteintje 2",
    "sg:city":"Lebbeke (denderbelle)",
    "sg:orig_category":"Non-Classified Establishments",
    "sg:phone":"+32 52 41 28 94",
    "sg:postcode":"9280",
    "sg:province":"Oost-Vlaanderen",
    "wof:name":"U.p.",
    "wof:placetype":"venue"
},
  "geometry": {"coordinates":[4.1281151772,51.0004501343],"type":"Point"}
}