{
  "type": "Feature",
  "properties": {
    "iso:country":"BE",
    "sg:address":"Dorpweg 88",
    "sg:city":"Zuienkerke (meetkerke)",
    "sg:classifiers":[
        {
            "category":"Cafe",
            "type":"Food & Drink"
        }
    ],
    "sg:phone":"+32 50 31 21 16",
    "sg:postcode":"8377",
    "sg:province":"West-Vlaanderen",
    "sg:tags":[
        "snack-bars"
    ],
    "wof:name":"Het Mortierken",
    "wof:placetype":"venue"
},
  "geometry": {"coordinates":[3.1523880959,51.235496521],"type":"Point"}
}