{
  "type": "Feature",
  "properties": {
    "iso:country":"BE",
    "sg:address":"Koning Leopold Iii Laan 20",
    "sg:city":"Zomergem",
    "sg:orig_category":"Experts-comptables",
    "sg:phone":"+32 9 372 73 84",
    "sg:postcode":"9930",
    "sg:province":"Oost-Vlaanderen",
    "wof:name":"Willy Raes",
    "wof:placetype":"venue"
},
  "geometry": {"coordinates":[3.5496640205,51.1176185608],"type":"Point"}
}