{
  "type": "Feature",
  "properties": {
    "iso:country":"BE",
    "sg:address":"Rue De La R\u00e9sistance 32",
    "sg:city":"Remicourt",
    "sg:classifiers":[
        {
            "category":"Professional",
            "subcategory":"Business Services",
            "type":"Services"
        }
    ],
    "sg:phone":"+32 19 54 56 91",
    "sg:postcode":"4350",
    "sg:province":"Li\u00e8ge",
    "sg:tags":[
        "firm"
    ],
    "wof:name":"Didion P",
    "wof:placetype":"venue"
},
  "geometry": {"coordinates":[5.3262271881,50.6846046448],"type":"Point"}
}