{
  "type": "Feature",
  "properties": {
    "addr:full":"Terninckgang 2 Antwerpen Antwerpen 2000",
    "addr:housenumber":"2",
    "addr:postcode":"2000",
    "addr:street":"Terninckgang",
    "iso:country":"BE",
    "sg:address":"Terninckgang 2",
    "sg:city":"Antwerpen",
    "sg:orig_category":"Diverse grafische activiteiten",
    "sg:phone":"+32 3 234 04 46",
    "sg:postcode":"2000",
    "sg:province":"Antwerpen",
    "wof:name":"Bart Debaveye",
    "wof:placetype":"venue"
},
  "geometry": {"coordinates":[4.401553154,51.2113113403],"type":"Point"}
}