{
  "type": "Feature",
  "properties": {
    "addr:full":"Rue De Namur 153 Nivelles Brabant Wallon 1400",
    "addr:housenumber":"153",
    "addr:postcode":"1400",
    "addr:street":"Rue De Namur",
    "iso:country":"BE",
    "sg:address":"Rue De Namur 153",
    "sg:city":"Nivelles",
    "sg:classifiers":[
        {
            "category":"Real Estate",
            "subcategory":"Architect",
            "type":"Services"
        }
    ],
    "sg:phone":"+32 67 22 01 33",
    "sg:postcode":"1400",
    "sg:province":"Brabant Wallon",
    "wof:name":"Ahn C",
    "wof:placetype":"venue"
},
  "geometry": {"coordinates":[4.3323178291,50.5996284485],"type":"Point"}
}