{
  "type": "Feature",
  "properties": {
    "addr:full":"Rue De La Marli\u00c8re 25 Mouscron Hainaut 7700",
    "addr:housenumber":"25",
    "addr:postcode":"7700",
    "addr:street":"Rue De La Marlie\u0300Re",
    "iso:country":"BE",
    "sg:address":"Rue De La Marli\u00c8re 25",
    "sg:city":"Mouscron",
    "sg:orig_category":"Services de t\u00e9l\u00e9communications. Production and distribution d'\u00e9lectricit\u00e9",
    "sg:phone":"+32 78 78 78 78",
    "sg:postcode":"7700",
    "sg:province":"Hainaut",
    "wof:name":"Electrabel",
    "wof:placetype":"venue"
},
  "geometry": {"coordinates":[3.2028799057,50.7419204712],"type":"Point"}
}