{
  "type": "Feature",
  "properties": {
    "addr:full":"Sint-hubertuslaan 4ba Tervuren Vlaams-Brabant 3080",
    "addr:housenumber":"4ba",
    "addr:postcode":"3080",
    "addr:street":"Sint-Hubertuslaan",
    "iso:country":"BE",
    "sg:address":"Sint-hubertuslaan 4ba",
    "sg:city":"Tervuren",
    "sg:orig_category":"Dameskledingzaken",
    "sg:phone":"+32 2 767 02 20",
    "sg:postcode":"3080",
    "sg:province":"Vlaams-Brabant",
    "wof:name":"Orient Fashion",
    "wof:placetype":"venue"
},
  "geometry": {"coordinates":[4.5410017967,50.8365745544],"type":"Point"}
}