{
  "type": "Feature",
  "properties": {
    "iso:country":"BE",
    "sg:address":"Rue De Campine 207",
    "sg:city":"Li\u00c8ge",
    "sg:orig_category":"Artsen and specialisten",
    "sg:phone":"+32 4 226 59 84",
    "sg:postcode":"4000",
    "sg:province":"Li\u00e8ge",
    "wof:name":"Bailly",
    "wof:placetype":"venue"
},
  "geometry": {"coordinates":[5.5680937767,50.6530227661],"type":"Point"}
}