{
  "type": "Feature",
  "properties": {
    "addr:full":"Rue Picard 50-52 Bruxelles (molenbeek-saint-jean) Bruxelles-Capitale 1080",
    "addr:postcode":"50-52;molenbeek-saint-jean;1080",
    "addr:street":"Rue Picard",
    "iso:country":"BE",
    "sg:address":"Rue Picard 50-52",
    "sg:city":"Bruxelles (molenbeek-saint-jean)",
    "sg:classifiers":[
        {
            "category":"Professional",
            "subcategory":"Business Services",
            "type":"Services"
        }
    ],
    "sg:phone":"+32 2 420 72 60",
    "sg:postcode":"1080",
    "sg:province":"Bruxelles-Capitale",
    "sg:tags":[
        "consultant",
        "custom"
    ],
    "wof:name":"Shenkira Sa",
    "wof:placetype":"venue"
},
  "geometry": {"coordinates":[4.345913887,50.863319397],"type":"Point"}
}