{
  "type": "Feature",
  "properties": {
    "addr:full":"Boseind 23 Neerpelt Limburg 3910",
    "addr:housenumber":"23",
    "addr:postcode":"3910",
    "addr:street":"Boseind",
    "iso:country":"BE",
    "sg:address":"Boseind 23",
    "sg:city":"Neerpelt",
    "sg:orig_category":"R\u00e9parations and entretien de motos",
    "sg:phone":"+32 11 66 20 34",
    "sg:postcode":"3910",
    "sg:province":"Limburg",
    "wof:name":"Huis O. & O.",
    "wof:placetype":"venue"
},
  "geometry": {"coordinates":[5.4387350082,51.2262039185],"type":"Point"}
}