{
  "type": "Feature",
  "properties": {
    "addr:full":"Ortolanenlaan 54 Watermaal-bosvoorde/watermael-boitsfort Bruxelles-Capitale 1170",
    "addr:housenumber":"54",
    "addr:postcode":"1170",
    "addr:street":"Ortolanenlaan",
    "iso:country":"BE",
    "sg:address":"Ortolanenlaan 54",
    "sg:city":"Watermaal-bosvoorde/watermael-boitsfort",
    "sg:orig_category":"Artsen and specialisten",
    "sg:phone":"+32 2 675 52 26",
    "sg:postcode":"1170",
    "sg:province":"Bruxelles-Capitale",
    "wof:name":"J.p. Tassignon",
    "wof:placetype":"venue"
},
  "geometry": {"coordinates":[4.4072070122,50.8030738831],"type":"Point"}
}