{
  "type": "Feature",
  "properties": {
    "iso:country":"BE",
    "sg:address":"Rue De Henri-chapelle 24",
    "sg:city":"Herve",
    "sg:orig_category":"Openbare veiligheid",
    "sg:phone":"+32 87 67 48 66",
    "sg:postcode":"4651",
    "sg:province":"Li\u00e8ge",
    "wof:name":"Police F\u00c9d\u00c9rale/federale Politie",
    "wof:placetype":"venue"
},
  "geometry": {"coordinates":[5.8270401955,50.6451034546],"type":"Point"}
}