{
  "type": "Feature",
  "properties": {
    "iso:country":"BE",
    "sg:address":"Les Hauts Du Ry Ternel 6",
    "sg:city":"Itter",
    "sg:orig_category":"Sportclubs",
    "sg:phone":"+32 67 21 42 40",
    "sg:postcode":"1461",
    "sg:province":"Brabant Wallon",
    "wof:name":"Palette Ry Ternel",
    "wof:placetype":"venue"
},
  "geometry": {"coordinates":[4.2943959236,50.653968811],"type":"Point"}
}