{
  "type": "Feature",
  "properties": {
    "addr:full":"Hanneusestraat 32 Box 2 Blankenberge West-Vlaanderen 8370",
    "addr:housenumber":"32;2",
    "addr:postcode":"8370",
    "addr:street":"Hanneusestraat;Box",
    "iso:country":"BE",
    "sg:address":"Hanneusestraat 32 Box 2",
    "sg:city":"Blankenberge",
    "sg:classifiers":[
        {
            "category":"Social Services",
            "type":"Services"
        }
    ],
    "sg:phone":"+32 50 41 60 19",
    "sg:postcode":"8370",
    "sg:province":"West-Vlaanderen",
    "wof:name":"Lindenhof (het)",
    "wof:placetype":"venue"
},
  "geometry": {"coordinates":[3.1357250214,51.3141098022],"type":"Point"}
}