{
  "type": "Feature",
  "properties": {
    "iso:country":"BE",
    "sg:address":"Rue Louis Franson 17",
    "sg:city":"La Louviere",
    "sg:orig_category":"Traitements param\u00e9dicaux",
    "sg:phone":"+32 64 26 63 36",
    "sg:postcode":"7100",
    "sg:province":"Hainaut",
    "wof:name":"Debelle",
    "wof:placetype":"venue"
},
  "geometry": {"coordinates":[4.1811208725,50.4708518982],"type":"Point"}
}