{
  "type": "Feature",
  "properties": {
    "iso:country":"BE",
    "sg:address":"Rue Bouillenne 24",
    "sg:city":"Fleron",
    "sg:orig_category":"Services pour animaux domestiques",
    "sg:phone":"+32 4 358 81 83",
    "sg:postcode":"4620",
    "sg:province":"Li\u00e8ge",
    "wof:name":"Les Aristochiens-davister",
    "wof:placetype":"venue"
},
  "geometry": {"coordinates":[5.6797719002,50.6155471802],"type":"Point"}
}