{
  "type": "Feature",
  "properties": {
    "iso:country":"BE",
    "sg:address":"Avenue Du Douaire 2",
    "sg:city":"Ottignies-louvain-la-neuve",
    "sg:orig_category":"Zuivelproducten",
    "sg:phone":"+32 10 41 83 37",
    "sg:postcode":"1340",
    "sg:province":"Brabant Wallon",
    "wof:name":"La Cornette",
    "wof:placetype":"venue"
},
  "geometry": {"coordinates":[4.5672249794,50.6636390686],"type":"Point"}
}