{
  "type": "Feature",
  "properties": {
    "iso:country":"BE",
    "sg:address":"Zoning Industriel 1\u00e8re Rue",
    "sg:city":"Charleroi (jumet)",
    "sg:orig_category":"Non-Classified Establishments",
    "sg:phone":"+32 71 37 49 15",
    "sg:postcode":"6040",
    "sg:province":"Hainaut",
    "wof:name":"San-europe",
    "wof:placetype":"venue"
},
  "geometry": {"coordinates":[4.4549150467,50.4562835693],"type":"Point"}
}