{
  "type": "Feature",
  "properties": {
    "addr:full":"Rue Ren\u00c9-gobert 1 Sombreffe Namur 5140",
    "addr:housenumber":"1",
    "addr:postcode":"5140",
    "addr:street":"Rue Rene\u0301-Gobert",
    "iso:country":"BE",
    "sg:address":"Rue Ren\u00c9-gobert 1",
    "sg:city":"Sombreffe",
    "sg:orig_category":"Charpentes and couvertures. Plomberie, chauffage and installations sanitaires",
    "sg:phone":"+32 71 88 81 43",
    "sg:postcode":"5140",
    "sg:province":"Namur",
    "wof:name":"Lamoline",
    "wof:placetype":"venue"
},
  "geometry": {"coordinates":[4.5754070282,50.5143432617],"type":"Point"}
}