{
  "type": "Feature",
  "properties": {
    "iso:country":"BE",
    "sg:address":"Stationsstraat 58",
    "sg:city":"Deinze",
    "sg:orig_category":"Banken and kredietinstellingen Verzekeringsmakelaars and experts",
    "sg:phone":"+32 9 386 92 19",
    "sg:postcode":"9800",
    "sg:province":"Oost-Vlaanderen",
    "wof:name":"Bank J. Van Breda & Co",
    "wof:placetype":"venue"
},
  "geometry": {"coordinates":[3.5328099728,50.9779396057],"type":"Point"}
}