{
  "type": "Feature",
  "properties": {
    "addr:full":"Rue Joseph Dufrane 3 Frameries Hainaut 7080",
    "addr:housenumber":"3",
    "addr:postcode":"7080",
    "addr:street":"Rue Joseph Dufrane",
    "iso:country":"BE",
    "sg:address":"Rue Joseph Dufrane 3",
    "sg:city":"Frameries",
    "sg:orig_category":"Banques and organismes de cr\u00e9dit",
    "sg:phone":"+32 65 67 43 86",
    "sg:postcode":"7080",
    "sg:province":"Hainaut",
    "wof:name":"Dexia",
    "wof:placetype":"venue"
},
  "geometry": {"coordinates":[3.8881669044,50.4077911377],"type":"Point"}
}