{
  "type": "Feature",
  "properties": {
    "addr:full":"Retiesebaan 15 Kasterlee Antwerpen 2460",
    "addr:housenumber":"15",
    "addr:postcode":"2460",
    "addr:street":"Retiesebaan",
    "iso:country":"BE",
    "sg:address":"Retiesebaan 15",
    "sg:city":"Kasterlee",
    "sg:classifiers":[
        {
            "category":"Building & Trades",
            "subcategory":"Pest Control",
            "type":"Services"
        }
    ],
    "sg:phone":"+32 14 55 72 79",
    "sg:postcode":"2460",
    "sg:province":"Antwerpen",
    "sg:tags":[
        "painting",
        "contractor"
    ],
    "wof:name":"Peinen Nv",
    "wof:placetype":"venue"
},
  "geometry": {"coordinates":[4.9704351425,51.2413139343],"type":"Point"}
}