{
  "type": "Feature",
  "properties": {
    "addr:full":"Rue Griange 16a Huy Li\u00e8ge 4500",
    "addr:housenumber":"16a",
    "addr:postcode":"4500",
    "addr:street":"Rue Griange",
    "iso:country":"BE",
    "sg:address":"Rue Griange 16a",
    "sg:city":"Huy",
    "sg:classifiers":[
        {
            "category":"Shopping",
            "subcategory":"Clothing, Apparel, & Fashions",
            "type":"Retail Goods"
        }
    ],
    "sg:phone":"+32 85 23 50 48",
    "sg:postcode":"4500",
    "sg:province":"Li\u00e8ge",
    "sg:tags":[
        "lady",
        "clothing",
        "-"
    ],
    "wof:name":"Zakar'in",
    "wof:placetype":"venue"
},
  "geometry": {"coordinates":[5.2416701317,50.5174102783],"type":"Point"}
}