{
  "type": "Feature",
  "properties": {
    "iso:country":"BE",
    "sg:address":"Rue De L'eglise 16",
    "sg:city":"La Hulpe",
    "sg:classifiers":[
        {
            "category":"Building & Trades",
            "subcategory":"Construction",
            "type":"Services"
        }
    ],
    "sg:phone":"+32 2 653 78 65",
    "sg:postcode":"1310",
    "sg:province":"Brabant Wallon",
    "sg:tags":[
        "duct",
        "underground",
        "ducting"
    ],
    "wof:name":"Adi-controles Non Destructifs",
    "wof:placetype":"venue"
},
  "geometry": {"coordinates":[4.4902968407,50.730846405],"type":"Point"}
}