{
  "type": "Feature",
  "properties": {
    "iso:country":"BE",
    "sg:address":"Generaal Lemanstraat 38",
    "sg:city":"Menen",
    "sg:classifiers":[
        {
            "category":"Professional",
            "subcategory":"Testing Lab",
            "type":"Services"
        }
    ],
    "sg:phone":"+32 56 51 34 51",
    "sg:postcode":"8930",
    "sg:province":"West-Vlaanderen",
    "sg:tags":[
        "chemist"
    ],
    "wof:name":"Baert L",
    "wof:placetype":"venue"
},
  "geometry": {"coordinates":[3.1085178852,50.7981758118],"type":"Point"}
}