{
  "type": "Feature",
  "properties": {
    "addr:full":"Molenweg 93 Zonhoven Limburg 3520",
    "addr:housenumber":"93",
    "addr:postcode":"3520",
    "addr:street":"Molenweg",
    "iso:country":"BE",
    "sg:address":"Molenweg 93",
    "sg:city":"Zonhoven",
    "sg:classifiers":[
        {
            "category":"Restaurant",
            "type":"Food & Drink"
        }
    ],
    "sg:phone":"+32 11 81 76 60",
    "sg:postcode":"3520",
    "sg:province":"Limburg",
    "sg:tags":[
        "\u00c0",
        "domicile",
        "fast",
        "emporter",
        "livraison",
        "restaurants"
    ],
    "wof:name":"Marijke",
    "wof:placetype":"venue"
},
  "geometry": {"coordinates":[5.4135541916,50.9866485596],"type":"Point"}
}