{
  "type": "Feature",
  "properties": {
    "iso:country":"BE",
    "sg:address":"Rue Lambert Dewonck 105",
    "sg:city":"Ans",
    "sg:orig_category":"Advocaten and juridische adviseurs",
    "sg:phone":"+32 4 247 22 24",
    "sg:postcode":"4432",
    "sg:province":"Li\u00e8ge",
    "wof:name":"X. Windels",
    "wof:placetype":"venue"
},
  "geometry": {"coordinates":[5.5136198997,50.6676940918],"type":"Point"}
}