{
  "type": "Feature",
  "properties": {
    "addr:full":"Nijverheidsweg 5 Merelbeke Oost-Vlaanderen 9820",
    "addr:housenumber":"5",
    "addr:postcode":"9820",
    "addr:street":"Nijverheidsweg",
    "iso:country":"BE",
    "sg:address":"Nijverheidsweg 5",
    "sg:city":"Merelbeke",
    "sg:classifiers":[
        {
            "category":"Government",
            "subcategory":"Court House",
            "type":"Public Place"
        }
    ],
    "sg:phone":"+32 9 236 61 71",
    "sg:postcode":"9820",
    "sg:province":"Oost-Vlaanderen",
    "sg:tags":[
        "administration",
        "central"
    ],
    "wof:name":"Duvall B.v.b.a.",
    "wof:placetype":"venue"
},
  "geometry": {"coordinates":[3.731867075,51.0018615723],"type":"Point"}
}