{
  "type": "Feature",
  "properties": {
    "iso:country":"BE",
    "sg:address":"Minervastraat 6",
    "sg:city":"Zaventem",
    "sg:classifiers":[
        {
            "category":"Professional",
            "subcategory":"Computer Services",
            "type":"Services"
        }
    ],
    "sg:phone":"+32 2 711 00 10",
    "sg:postcode":"1930",
    "sg:province":"Vlaams-Brabant",
    "sg:tags":[
        "-",
        "processing",
        "data",
        "software"
    ],
    "wof:name":"Niuu Corporation Bv",
    "wof:placetype":"venue"
},
  "geometry": {"coordinates":[4.4510960579,50.8802375793],"type":"Point"}
}