{
  "type": "Feature",
  "properties": {
    "addr:full":"Markt 39 Eeklo Oost-Vlaanderen 9900",
    "addr:housenumber":"39",
    "addr:postcode":"9900",
    "addr:street":"Markt",
    "iso:country":"BE",
    "sg:address":"Markt 39",
    "sg:city":"Eeklo",
    "sg:classifiers":[
        {
            "category":"Home & Garden",
            "subcategory":"Household Appliances",
            "type":"Retail Goods"
        }
    ],
    "sg:phone":"+32 9 377 10 68",
    "sg:postcode":"9900",
    "sg:province":"Oost-Vlaanderen",
    "sg:tags":[
        "heating",
        "apparatus"
    ],
    "wof:name":"Van Den Berghe U",
    "wof:placetype":"venue"
},
  "geometry": {"coordinates":[3.5660579205,51.1841087341],"type":"Point"}
}