{
  "type": "Feature",
  "properties": {
    "iso:country":"BE",
    "sg:address":"Rue D'haine 51-65",
    "sg:city":"Binche (leval-trahegnies)",
    "sg:classifiers":[
        {
            "category":"Building & Trades",
            "subcategory":"Construction",
            "type":"Services"
        }
    ],
    "sg:phone":"+32 64 33 27 85",
    "sg:postcode":"7134",
    "sg:province":"Hainaut",
    "sg:tags":[
        "carpenter"
    ],
    "wof:name":"Menuiserie Marcoux Et Fils",
    "wof:placetype":"venue"
},
  "geometry": {"coordinates":[4.2210288048,50.4294509888],"type":"Point"}
}