{
  "type": "Feature",
  "properties": {
    "iso:country":"BE",
    "sg:address":"Oudenaardsestraat 215",
    "sg:city":"Geraardsbergen",
    "sg:classifiers":[
        {
            "category":"Social Services",
            "type":"Services"
        }
    ],
    "sg:phone":"+32 54 41 54 54",
    "sg:postcode":"9500",
    "sg:province":"Oost-Vlaanderen",
    "sg:tags":[
        "handicapped",
        "-"
    ],
    "wof:name":"Horizon Vzw",
    "wof:placetype":"venue"
},
  "geometry": {"coordinates":[3.8688800335,50.7724113464],"type":"Point"}
}