{
  "type": "Feature",
  "properties": {
    "addr:full":"Prinsessestraat 34 Izegem West-Vlaanderen 8870",
    "addr:housenumber":"34",
    "addr:postcode":"8870",
    "addr:street":"Prinsessestraat",
    "iso:country":"BE",
    "sg:address":"Prinsessestraat 34",
    "sg:city":"Izegem",
    "sg:classifiers":[
        {
            "category":"Real Estate",
            "subcategory":"Architect",
            "type":"Services"
        }
    ],
    "sg:phone":"+32 51 30 32 87",
    "sg:postcode":"8870",
    "sg:province":"West-Vlaanderen",
    "wof:name":"Renier J",
    "wof:placetype":"venue"
},
  "geometry": {"coordinates":[3.2277300358,50.9225997925],"type":"Point"}
}