{
  "type": "Feature",
  "properties": {
    "iso:country":"BE",
    "sg:address":"Chauss\u00c9e D\u00b4argenteau 42",
    "sg:city":"Vis\u00c9",
    "sg:orig_category":"Meubles D\u00e9taillants, Am\u00e9nagement de B\u00e2timents et de Cuisines",
    "sg:phone":"+32 4 379 14 94",
    "sg:postcode":"4601",
    "sg:province":"Li\u00e8ge",
    "wof:name":"Meubles Parall\u00c8le",
    "wof:placetype":"venue"
},
  "geometry": {"coordinates":[5.6874017715,50.6957092285],"type":"Point"}
}