{
  "type": "Feature",
  "properties": {
    "iso:country":"BE",
    "sg:address":"Vaux 50",
    "sg:city":"Bastogne",
    "sg:orig_category":"Verhuur cateringmateriaal and evenementuitrusting Winkelinrichting and handelsuitrusting Gh",
    "sg:phone":"+32 61 21 53 43",
    "sg:postcode":"6600",
    "sg:province":"Luxembourg",
    "wof:name":"C.t.f.",
    "wof:placetype":"venue"
},
  "geometry": {"coordinates":[5.7593097687,50.0746154785],"type":"Point"}
}