{
  "type": "Feature",
  "properties": {
    "iso:country":"BE",
    "sg:address":"Rue Provinciale 262",
    "sg:city":"Celles",
    "sg:orig_category":"Artistes ind\u00e9pendants",
    "sg:phone":"+32 69 45 64 04",
    "sg:postcode":"7760",
    "sg:province":"Hainaut",
    "wof:name":"Arnold Decock",
    "wof:placetype":"venue"
},
  "geometry": {"coordinates":[3.455329895,50.7194595337],"type":"Point"}
}