{
  "type": "Feature",
  "properties": {
    "addr:full":"Koningin Astridlaan 370 Kraainem/kraainem Vlaams-Brabant 1950",
    "addr:housenumber":"370",
    "addr:postcode":"1950",
    "addr:street":"Koningin Astridlaan",
    "iso:country":"BE",
    "sg:address":"Koningin Astridlaan 370",
    "sg:city":"Kraainem/kraainem",
    "sg:orig_category":"Rechtbanken",
    "sg:phone":"+32 2 731 12 40",
    "sg:postcode":"1950",
    "sg:province":"Vlaams-Brabant",
    "wof:name":"Vredegerecht/justice De Paix",
    "wof:placetype":"venue"
},
  "geometry": {"coordinates":[4.4692511559,50.8430023193],"type":"Point"}
}