{
  "type": "Feature",
  "properties": {
    "iso:country":"BE",
    "sg:address":"Poelvoordestraat 8",
    "sg:city":"Tielt",
    "sg:orig_category":"Rundveehouders",
    "sg:phone":"+32 51 65 55 45",
    "sg:postcode":"8700",
    "sg:province":"West-Vlaanderen",
    "wof:name":"Sylvere Depypere",
    "wof:placetype":"venue"
},
  "geometry": {"coordinates":[3.3195459843,51.0334701538],"type":"Point"}
}