{
  "type": "Feature",
  "properties": {
    "addr:full":"Grand'rue D'acren 20 Lessines Hainaut 7864",
    "addr:housenumber":"20",
    "addr:postcode":"7864",
    "addr:street":"Grand'Rue D'Acren;Hainaut",
    "iso:country":"BE",
    "sg:address":"Grand'rue D'acren 20",
    "sg:city":"Lessines",
    "sg:orig_category":"Boucheries",
    "sg:phone":"+32 68 33 33 59",
    "sg:postcode":"7864",
    "sg:province":"Hainaut",
    "wof:name":"Hall De Viande D'acren",
    "wof:placetype":"venue"
},
  "geometry": {"coordinates":[3.8712720871,50.7258300781],"type":"Point"}
}