{
  "type": "Feature",
  "properties": {
    "addr:full":"Stationlaan 19 Box 1 Bilzen Limburg 3740",
    "addr:housenumber":"19;1",
    "addr:postcode":"3740",
    "addr:street":"Stationlaan;Box",
    "iso:country":"BE",
    "sg:address":"Stationlaan 19 Box 1",
    "sg:city":"Bilzen",
    "sg:classifiers":[
        {
            "category":"Professional",
            "subcategory":"Lawyer & Legal Services",
            "type":"Services"
        }
    ],
    "sg:phone":"+32 89 50 20 30",
    "sg:postcode":"3740",
    "sg:province":"Limburg",
    "wof:name":"Schellingen Erik",
    "wof:placetype":"venue"
},
  "geometry": {"coordinates":[5.5122699738,50.8697319031],"type":"Point"}
}