{
  "type": "Feature",
  "properties": {
    "addr:full":"Rue D'herchies 16 Mons (baudour) Hainaut 7331",
    "addr:housenumber":"16",
    "addr:postcode":"7331",
    "addr:street":"Rue D'Herchies",
    "iso:country":"BE",
    "sg:address":"Rue D'herchies 16",
    "sg:city":"Mons (baudour)",
    "sg:classifiers":[
        {
            "category":"Professional",
            "subcategory":"Lawyer & Legal Services",
            "type":"Services"
        }
    ],
    "sg:phone":"+32 65 64 13 98",
    "sg:postcode":"7331",
    "sg:province":"Hainaut",
    "sg:tags":[
        "notary"
    ],
    "wof:name":"Derbaix Ch",
    "wof:placetype":"venue"
},
  "geometry": {"coordinates":[3.8318629265,50.4857292175],"type":"Point"}
}