{
  "type": "Feature",
  "properties": {
    "addr:full":"Zoning Industriel Verviers (stembert) Li\u00e8ge 4801",
    "addr:postcode":"4801",
    "addr:street":"Zoning Industriel",
    "iso:country":"BE",
    "sg:address":"Zoning Industriel",
    "sg:city":"Verviers (stembert)",
    "sg:classifiers":[
        {
            "category":"Animal Shelter",
            "type":"Public Place"
        }
    ],
    "sg:phone":"+32 87 33 47 56",
    "sg:postcode":"4801",
    "sg:province":"Li\u00e8ge",
    "wof:name":"Soc Vervi\u00e9toise Pr La Protection Des Animaux",
    "wof:placetype":"venue"
},
  "geometry": {"coordinates":[5.8930549622,50.5922393799],"type":"Point"}
}