{
  "type": "Feature",
  "properties": {
    "iso:country":"BE",
    "sg:address":"Rue De L'etoile 65",
    "sg:city":"Morlanwelz",
    "sg:orig_category":"Elektrische installaties voor woningen",
    "sg:phone":"+32 64 44 72 12",
    "sg:postcode":"7140",
    "sg:province":"Hainaut",
    "wof:name":"Michel Lheureux",
    "wof:placetype":"venue"
},
  "geometry": {"coordinates":[4.2572360039,50.4689407349],"type":"Point"}
}