{
  "type": "Feature",
  "properties": {
    "addr:full":"Koxberg 38 Huldenberg Vlaams-Brabant 3040",
    "addr:housenumber":"38",
    "addr:postcode":"3040",
    "addr:street":"Koxberg",
    "iso:country":"BE",
    "sg:address":"Koxberg 38",
    "sg:city":"Huldenberg",
    "sg:classifiers":[
        {
            "category":"Retail",
            "subcategory":"Veterinary Services",
            "type":"Services"
        }
    ],
    "sg:phone":"+32 2 688 29 08",
    "sg:postcode":"3040",
    "sg:province":"Vlaams-Brabant",
    "sg:tags":[
        "veterinarian"
    ],
    "wof:name":"Clarysse M",
    "wof:placetype":"venue"
},
  "geometry": {"coordinates":[4.584171772,50.7834625244],"type":"Point"}
}