{
  "type": "Feature",
  "properties": {
    "addr:full":"Gulcherstrasse 7 Eupen Li\u00e8ge 4700",
    "addr:housenumber":"7",
    "addr:postcode":"4700",
    "addr:street":"Gulcherstrasse",
    "iso:country":"BE",
    "sg:address":"Gulcherstrasse 7",
    "sg:city":"Eupen",
    "sg:classifiers":[
        {
            "category":"Shopping",
            "subcategory":"Hobbies, Toys, & Games",
            "type":"Retail Goods"
        }
    ],
    "sg:phone":"+32 87 74 27 02",
    "sg:postcode":"4700",
    "sg:province":"Li\u00e8ge",
    "sg:tags":[
        "hobby",
        "handicraft",
        "supply"
    ],
    "wof:name":"Himaco S.p.r.l.",
    "wof:placetype":"venue"
},
  "geometry": {"coordinates":[6.0427589417,50.6197128296],"type":"Point"}
}