{
  "type": "Feature",
  "properties": {
    "iso:country":"BE",
    "sg:address":"Van Benedenlaan 67",
    "sg:city":"Mechelen",
    "sg:orig_category":"Notarissen",
    "sg:phone":"+32 15 41 22 53",
    "sg:postcode":"2800",
    "sg:province":"Antwerpen",
    "wof:name":"Marc De Backer",
    "wof:placetype":"venue"
},
  "geometry": {"coordinates":[4.4767370224,51.0212135315],"type":"Point"}
}