{
  "type": "Feature",
  "properties": {
    "iso:country":"BE",
    "sg:address":"Neuville 122",
    "sg:city":"Vielsalm",
    "sg:classifiers":[
        {
            "category":"Real Estate",
            "subcategory":"Architect",
            "type":"Services"
        }
    ],
    "sg:phone":"+32 80 21 61 19",
    "sg:postcode":"6690",
    "sg:province":"Luxembourg",
    "wof:name":"Hermann M",
    "wof:placetype":"venue"
},
  "geometry": {"coordinates":[5.9435100555,50.2818183899],"type":"Point"}
}