{
  "type": "Feature",
  "properties": {
    "iso:country":"BE",
    "sg:address":"Wemmelsesteenweg 164",
    "sg:city":"Brussel",
    "sg:classifiers":[
        {
            "category":"Restaurant",
            "type":"Food & Drink"
        }
    ],
    "sg:phone":"+32 2 420 56 10",
    "sg:postcode":"1090",
    "sg:province":"Bruxelles-Capitale",
    "sg:tags":[
        "organisatie",
        "feesten",
        "van",
        "catering"
    ],
    "wof:name":"La Ferme Du Wilg",
    "wof:placetype":"venue"
},
  "geometry": {"coordinates":[4.3234248161,50.8779907227],"type":"Point"}
}