{
  "type": "Feature",
  "properties": {
    "addr:full":"Boonstraat 15 Hamme Oost-Vlaanderen 9220",
    "addr:housenumber":"15",
    "addr:postcode":"9220",
    "addr:street":"Boonstraat",
    "iso:country":"BE",
    "sg:address":"Boonstraat 15",
    "sg:city":"Hamme",
    "sg:orig_category":"Sportclubs",
    "sg:phone":"+32 52 47 32 53",
    "sg:postcode":"9220",
    "sg:province":"Oost-Vlaanderen",
    "wof:name":"Vlaamse Pedaalridders - Moerzeke",
    "wof:placetype":"venue"
},
  "geometry": {"coordinates":[4.146094799,51.0701179504],"type":"Point"}
}