{
  "type": "Feature",
  "properties": {
    "addr:full":"Meirhoekstraat 2ba Laarne Oost-Vlaanderen 9270",
    "addr:postcode":"9270",
    "addr:street":"Meirhoekstraat;Oost-Vlaanderen",
    "iso:country":"BE",
    "sg:address":"Meirhoekstraat 2ba",
    "sg:city":"Laarne",
    "sg:orig_category":"Eleveurs de bovins",
    "sg:phone":"+32 9 369 09 00",
    "sg:postcode":"9270",
    "sg:province":"Oost-Vlaanderen",
    "wof:name":"Maurits Pypaert",
    "wof:placetype":"venue"
},
  "geometry": {"coordinates":[3.8634939194,51.0256385803],"type":"Point"}
}