{
  "type": "Feature",
  "properties": {
    "addr:full":"Distelstraat 10 Gent Oost-Vlaanderen 9000",
    "addr:housenumber":"10",
    "addr:postcode":"9000",
    "addr:street":"Distelstraat;Oost-Vlaanderen",
    "iso:country":"BE",
    "sg:address":"Distelstraat 10",
    "sg:city":"Gent",
    "sg:orig_category":"Centres de relaxation and bien-\u00eatre. Instituts de beaut\u00e9",
    "sg:phone":"+32 9 221 52 24",
    "sg:postcode":"9000",
    "sg:province":"Oost-Vlaanderen",
    "wof:name":"Rosita De Clercq",
    "wof:placetype":"venue"
},
  "geometry": {"coordinates":[3.7081038952,51.0392913818],"type":"Point"}
}