{
  "type": "Feature",
  "properties": {
    "addr:full":"Naamsestraat 11 Leuven Vlaams-Brabant 3000",
    "addr:housenumber":"11",
    "addr:postcode":"3000",
    "addr:street":"Naamsestraat",
    "iso:country":"BE",
    "sg:address":"Naamsestraat 11",
    "sg:city":"Leuven",
    "sg:orig_category":"Diverse kredietdiensten",
    "sg:postcode":"3000",
    "sg:province":"Vlaams-Brabant",
    "wof:name":"Bancontact-mister Cash",
    "wof:placetype":"venue"
},
  "geometry": {"coordinates":[4.7007660866,50.8779640198],"type":"Point"}
}