{
  "type": "Feature",
  "properties": {
    "addr:full":"Nieuwpoortsesteenweg 540 Oostende West-Vlaanderen 8400",
    "addr:housenumber":"540",
    "addr:postcode":"8400",
    "addr:street":"Nieuwpoortsesteenweg",
    "iso:country":"BE",
    "sg:address":"Nieuwpoortsesteenweg 540",
    "sg:city":"Oostende",
    "sg:orig_category":"Benzinestations and brandstoffen",
    "sg:phone":"+32 59 70 69 79",
    "sg:postcode":"8400",
    "sg:province":"West-Vlaanderen",
    "wof:name":"Jet",
    "wof:placetype":"venue"
},
  "geometry": {"coordinates":[2.8620610237,51.2036514282],"type":"Point"}
}