{
  "type": "Feature",
  "properties": {
    "iso:country":"BE",
    "sg:address":"Oude Boekhoutestraat 18",
    "sg:city":"Assenede (bassevelde)",
    "sg:classifiers":[
        {
            "category":"Travel",
            "subcategory":"Hotels & Motels",
            "type":"Entertainment"
        }
    ],
    "sg:phone":"+32 9 373 82 92",
    "sg:postcode":"9968",
    "sg:province":"Oost-Vlaanderen",
    "wof:name":"Westkanterhof ('t) ***",
    "wof:placetype":"venue"
},
  "geometry": {"coordinates":[3.6729199886,51.2358856201],"type":"Point"}
}