{
  "type": "Feature",
  "properties": {
    "addr:full":"Heilrimont 6 Stoumont (la Gleize) Li\u00e8ge 4987",
    "addr:housenumber":"6",
    "addr:postcode":"4987",
    "addr:street":"Heilrimont;La Gleize",
    "iso:country":"BE",
    "sg:address":"Heilrimont 6",
    "sg:city":"Stoumont (la Gleize)",
    "sg:classifiers":[
        {
            "category":"Real Estate",
            "subcategory":"Architect",
            "type":"Services"
        }
    ],
    "sg:phone":"+32 80 78 61 91",
    "sg:postcode":"4987",
    "sg:province":"Li\u00e8ge",
    "wof:name":"Dumez Ph",
    "wof:placetype":"venue"
},
  "geometry": {"coordinates":[5.8098897934,50.4056663513],"type":"Point"}
}