{
  "type": "Feature",
  "properties": {
    "iso:country":"BE",
    "sg:address":"Tienne Petite Bilande 67",
    "sg:city":"Wavre",
    "sg:orig_category":"Paramedische behandelingen",
    "sg:phone":"+32 10 22 94 30",
    "sg:postcode":"1300",
    "sg:province":"Brabant Wallon",
    "wof:name":"M. De Bie",
    "wof:placetype":"venue"
},
  "geometry": {"coordinates":[4.589908123,50.7406044006],"type":"Point"}
}