{
  "type": "Feature",
  "properties": {
    "addr:full":"Gebr.van Raemdonckstraat 15 Roeselare West-Vlaanderen 8800",
    "addr:housenumber":"15",
    "addr:postcode":"8800",
    "addr:street":"Raemdonckstraat",
    "iso:country":"BE",
    "sg:address":"Gebr.van Raemdonckstraat 15",
    "sg:city":"Roeselare",
    "sg:orig_category":"Traitement and rev\u00eatement des m\u00e9taux",
    "sg:phone":"+32 51 22 90 85",
    "sg:postcode":"8800",
    "sg:province":"West-Vlaanderen",
    "wof:name":"Kerkhof-vandewalle",
    "wof:placetype":"venue"
},
  "geometry": {"coordinates":[3.1657440662,50.9285163879],"type":"Point"}
}