{
  "type": "Feature",
  "properties": {
    "addr:full":"Rue Du Vine 28 Musson Luxembourg 6750",
    "addr:housenumber":"28",
    "addr:postcode":"6750",
    "addr:street":"Rue Du Vine",
    "iso:country":"BE",
    "sg:address":"Rue Du Vine 28",
    "sg:city":"Musson",
    "sg:orig_category":"Woningbouw",
    "sg:phone":"+32 63 67 81 68",
    "sg:postcode":"6750",
    "sg:province":"Luxembourg",
    "wof:name":"Fabrice Gavroy",
    "wof:placetype":"venue"
},
  "geometry": {"coordinates":[5.6593608856,49.5703239441],"type":"Point"}
}