{
  "type": "Feature",
  "properties": {
    "iso:country":"BE",
    "sg:address":"Rue Des Hamendes 99",
    "sg:city":"Charleroi (jumet)",
    "sg:classifiers":[
        {
            "category":"Manufacturing",
            "subcategory":"Tools & Machinery",
            "type":"Manufacturing & Wholesale Goods"
        }
    ],
    "sg:phone":"+32 71 41 41 89",
    "sg:postcode":"6040",
    "sg:province":"Hainaut",
    "sg:tags":[
        "machine"
    ],
    "wof:name":"Betech Sprl",
    "wof:placetype":"venue"
},
  "geometry": {"coordinates":[4.4709057808,50.4462738037],"type":"Point"}
}