{
  "type": "Feature",
  "properties": {
    "iso:country":"BE",
    "sg:address":"Rue Gr\u00e9at 34",
    "sg:city":"Chastre (cortil-noirmont)",
    "sg:classifiers":[
        {
            "category":"Health Services",
            "subcategory":"Health Practitioner",
            "type":"Services"
        }
    ],
    "sg:phone":"+32 81 60 01 51",
    "sg:postcode":"1450",
    "sg:province":"Brabant Wallon",
    "sg:tags":[
        "physiotherapist"
    ],
    "wof:name":"Clotuche Damien",
    "wof:placetype":"venue"
},
  "geometry": {"coordinates":[4.6480112076,50.5824890137],"type":"Point"}
}