{
  "type": "Feature",
  "properties": {
    "addr:full":"Stationsstraat 192 Liedekerke Vlaams-Brabant 1770",
    "addr:housenumber":"192",
    "addr:postcode":"1770",
    "addr:street":"Stationsstraat;Vlaams-Brabant",
    "iso:country":"BE",
    "sg:address":"Stationsstraat 192",
    "sg:city":"Liedekerke",
    "sg:orig_category":"Voertuigen",
    "sg:phone":"+32 475 77 38 90",
    "sg:postcode":"1770",
    "sg:province":"Vlaams-Brabant",
    "wof:name":"Autohandel De Witte",
    "wof:placetype":"venue"
},
  "geometry": {"coordinates":[4.0908927917,50.8759498596],"type":"Point"}
}