{
  "type": "Feature",
  "properties": {
    "addr:full":"Chauss\u00c9e De Renaix 72b1 Tournai Hainaut 7540",
    "addr:housenumber":"72b1",
    "addr:postcode":"7540",
    "addr:street":"Chausse\u0301E De Renaix",
    "iso:country":"BE",
    "sg:address":"Chauss\u00c9e De Renaix 72b1",
    "sg:city":"Tournai",
    "sg:orig_category":"Herstellingen and onderhoud van auto's Voertuigen",
    "sg:phone":"+32 69 22 11 42",
    "sg:postcode":"7540",
    "sg:province":"Hainaut",
    "wof:name":"Garage Choquet & Janssens",
    "wof:placetype":"venue"
},
  "geometry": {"coordinates":[3.4063010216,50.6139793396],"type":"Point"}
}