{
  "type": "Feature",
  "properties": {
    "addr:full":"I. Van Kerrebroeckstraat 34 Nazareth Oost-Vlaanderen 9810",
    "addr:housenumber":"34",
    "addr:postcode":"9810",
    "addr:street":"I.;Kerrebroeckstraat",
    "iso:country":"BE",
    "sg:address":"I. Van Kerrebroeckstraat 34",
    "sg:city":"Nazareth",
    "sg:orig_category":"Plaatsen van vloer- and muurbekleding Woningbouw",
    "sg:phone":"+32 9 385 60 79",
    "sg:postcode":"9810",
    "sg:province":"Oost-Vlaanderen",
    "wof:name":"Tom Vander Elstraeten",
    "wof:placetype":"venue"
},
  "geometry": {"coordinates":[3.641283989,50.9586410522],"type":"Point"}
}