{
  "type": "Feature",
  "properties": {
    "iso:country":"BE",
    "sg:address":"Stationsstraat 52-3",
    "sg:city":"Neerpelt",
    "sg:classifiers":[
        {
            "category":"Professional",
            "subcategory":"Computer Services",
            "type":"Services"
        }
    ],
    "sg:phone":"+32 11 66 25 96",
    "sg:postcode":"3910",
    "sg:province":"Limburg",
    "sg:tags":[
        "-",
        "processing",
        "data",
        "software"
    ],
    "wof:name":"Interware",
    "wof:placetype":"venue"
},
  "geometry": {"coordinates":[5.4368858337,51.2249832153],"type":"Point"}
}