{
  "type": "Feature",
  "properties": {
    "addr:full":"Grote Markt 8 Mechelen Antwerpen 2800",
    "addr:housenumber":"8",
    "addr:postcode":"2800",
    "addr:street":"Grote Markt",
    "iso:country":"BE",
    "sg:address":"Grote Markt 8",
    "sg:city":"Mechelen",
    "sg:classifiers":[
        {
            "category":"Cafe",
            "type":"Food & Drink"
        }
    ],
    "sg:phone":"+32 15 20 72 38",
    "sg:postcode":"2800",
    "sg:province":"Antwerpen",
    "sg:tags":[
        "caf\u00e9s"
    ],
    "wof:name":"Andre Feremans",
    "wof:placetype":"venue"
},
  "geometry": {"coordinates":[4.4803371429,51.0284538269],"type":"Point"}
}