{
  "type": "Feature",
  "properties": {
    "iso:country":"BE",
    "sg:address":"Avenue Albert L 17",
    "sg:city":"Paliseul",
    "sg:orig_category":"Tuinbenodigdheden",
    "sg:phone":"+32 61 65 55 42",
    "sg:postcode":"6852",
    "sg:province":"Luxembourg",
    "wof:name":"Bourguignon J",
    "wof:placetype":"venue"
},
  "geometry": {"coordinates":[5.1785240173,49.9646186829],"type":"Point"}
}