{
  "type": "Feature",
  "properties": {
    "addr:full":"Rue Emile Delva 57-59 Bruxelles Bruxelles-Capitale 1020",
    "addr:housenumber":"57-59",
    "addr:postcode":"1020",
    "addr:street":"Rue Emile Delva",
    "iso:country":"BE",
    "sg:address":"Rue Emile Delva 57-59",
    "sg:city":"Bruxelles",
    "sg:classifiers":[
        {
            "category":"Manufacturing",
            "subcategory":"Jewelry",
            "type":"Manufacturing & Wholesale Goods"
        }
    ],
    "sg:phone":"+32 2 428 73 51",
    "sg:postcode":"1020",
    "sg:province":"Bruxelles-Capitale",
    "sg:tags":[
        "plating",
        "silver",
        "gold"
    ],
    "wof:name":"Presto Pack Sprl",
    "wof:placetype":"venue"
},
  "geometry": {"coordinates":[4.3429307938,50.8789710999],"type":"Point"}
}