{
  "type": "Feature",
  "properties": {
    "iso:country":"BE",
    "sg:address":"Italielei 205",
    "sg:city":"Antwerpen",
    "sg:orig_category":"Foto-uitrusting",
    "sg:phone":"+32 3 231 19 53",
    "sg:postcode":"2000",
    "sg:province":"Antwerpen",
    "wof:name":"Bonus Pool",
    "wof:placetype":"venue"
},
  "geometry": {"coordinates":[4.4167399406,51.2220077515],"type":"Point"}
}