{
  "type": "Feature",
  "properties": {
    "addr:full":"Andrimontlaan 35 Ukkel/uccle Bruxelles-Capitale 1180",
    "addr:housenumber":"35",
    "addr:postcode":"1180",
    "addr:street":"Andrimontlaan;/",
    "iso:country":"BE",
    "sg:address":"Andrimontlaan 35",
    "sg:city":"Ukkel/uccle",
    "sg:orig_category":"Architecten",
    "sg:phone":"+32 2 374 01 62",
    "sg:postcode":"1180",
    "sg:province":"Bruxelles-Capitale",
    "wof:name":"Michel Desmet",
    "wof:placetype":"venue"
},
  "geometry": {"coordinates":[4.3672361374,50.789276123],"type":"Point"}
}