{
  "type": "Feature",
  "properties": {
    "addr:full":"Gustaaf Breynaertstraat 26 Lennik (sint-kwintens-lennik) Vlaams-Brabant 1750",
    "addr:housenumber":"26",
    "addr:postcode":"1750",
    "addr:street":"Gustaaf Breynaertstraat",
    "iso:country":"BE",
    "sg:address":"Gustaaf Breynaertstraat 26",
    "sg:city":"Lennik (sint-kwintens-lennik)",
    "sg:classifiers":[
        {
            "category":"Building & Trades",
            "subcategory":"Electrical",
            "type":"Services"
        }
    ],
    "sg:phone":"+32 2 532 40 57",
    "sg:postcode":"1750",
    "sg:province":"Vlaams-Brabant",
    "sg:tags":[
        "electric",
        "-",
        "housewiring",
        "contractor"
    ],
    "wof:name":"Puttaert R",
    "wof:placetype":"venue"
},
  "geometry": {"coordinates":[4.1493668556,50.8247032166],"type":"Point"}
}