{
  "type": "Feature",
  "properties": {
    "iso:country":"BE",
    "sg:address":"Slachthuislaan 78",
    "sg:city":"Antwerpen",
    "sg:classifiers":[
        {
            "category":"Shopping",
            "subcategory":"Bicycles & Sporting Goods",
            "type":"Retail Goods"
        }
    ],
    "sg:phone":"+32 3 235 00 16",
    "sg:postcode":"2060",
    "sg:province":"Antwerpen",
    "sg:tags":[
        "tyre"
    ],
    "wof:name":"Abc Lucky Banden Nv",
    "wof:placetype":"venue"
},
  "geometry": {"coordinates":[4.4391341209,51.2282180786],"type":"Point"}
}