{
  "type": "Feature",
  "properties": {
    "addr:full":"Breendonkstraat 209 Willebroek Antwerpen 2830",
    "addr:housenumber":"209",
    "addr:postcode":"2830",
    "addr:street":"Breendonkstraat",
    "iso:country":"BE",
    "sg:address":"Breendonkstraat 209",
    "sg:city":"Willebroek",
    "sg:classifiers":[
        {
            "category":"Building & Trades",
            "subcategory":"Plumbing",
            "type":"Services"
        }
    ],
    "sg:phone":"+32 3 886 44 13",
    "sg:postcode":"2830",
    "sg:province":"Antwerpen",
    "sg:tags":[
        "pipe",
        "drain",
        "unblocking"
    ],
    "wof:name":"Lathouwers-jansegers",
    "wof:placetype":"venue"
},
  "geometry": {"coordinates":[4.3440051079,51.0486068726],"type":"Point"}
}