{
  "type": "Feature",
  "properties": {
    "addr:full":"Zoning Gembloux-sur-orneau (isnes) Namur 5032",
    "addr:postcode":"5032",
    "addr:street":"Namur",
    "iso:country":"BE",
    "sg:address":"Zoning",
    "sg:city":"Gembloux-sur-orneau (isnes)",
    "sg:classifiers":[
        {
            "category":"Professional",
            "subcategory":"Art Services",
            "type":"Services"
        }
    ],
    "sg:phone":"+32 81 56 82 77",
    "sg:postcode":"5032",
    "sg:province":"Namur",
    "sg:tags":[
        "-",
        "mailing",
        "lettershops",
        "direct",
        "mail"
    ],
    "wof:name":"Barbier Routage",
    "wof:placetype":"venue"
},
  "geometry": {"coordinates":[4.738424778,50.5091285706],"type":"Point"}
}