{
  "type": "Feature",
  "properties": {
    "iso:country":"BE",
    "sg:address":"Leuvensestraat 110",
    "sg:city":"Tienen",
    "sg:orig_category":"Bloemen and planten",
    "sg:phone":"+32 16 81 19 73",
    "sg:postcode":"3300",
    "sg:province":"Vlaams-Brabant",
    "wof:name":"Phalaenopses",
    "wof:placetype":"venue"
},
  "geometry": {"coordinates":[4.9313459396,50.8095664978],"type":"Point"}
}