{
  "type": "Feature",
  "properties": {
    "addr:full":"Rue Charles Bouvier 132 Namur Namur 5004",
    "addr:housenumber":"132",
    "addr:postcode":"5004",
    "addr:street":"Rue Charles Bouvier",
    "iso:country":"BE",
    "sg:address":"Rue Charles Bouvier 132",
    "sg:city":"Namur",
    "sg:orig_category":"Artistes ind\u00e9pendants",
    "sg:phone":"+32 81 21 12 02",
    "sg:postcode":"5004",
    "sg:province":"Namur",
    "wof:name":"Godfroid",
    "wof:placetype":"venue"
},
  "geometry": {"coordinates":[4.8746480942,50.4780158997],"type":"Point"}
}