{
  "type": "Feature",
  "properties": {
    "addr:full":"Zevekotestraat 32 Poperinge West-Vlaanderen 8970",
    "addr:housenumber":"32",
    "addr:postcode":"8970",
    "addr:street":"Zevekotestraat",
    "iso:country":"BE",
    "sg:address":"Zevekotestraat 32",
    "sg:city":"Poperinge",
    "sg:orig_category":"Banques and organismes de cr\u00e9dit",
    "sg:phone":"+32 57 33 30 13",
    "sg:postcode":"8970",
    "sg:province":"West-Vlaanderen",
    "wof:name":"Fortis",
    "wof:placetype":"venue"
},
  "geometry": {"coordinates":[2.7657821178,50.8146858215],"type":"Point"}
}