{
  "type": "Feature",
  "properties": {
    "iso:country":"BE",
    "sg:address":"Nassaustraat 14",
    "sg:city":"Antwerpen",
    "sg:classifiers":[
        {
            "category":"Wholesale",
            "subcategory":"Sporting Goods",
            "type":"Manufacturing & Wholesale Goods"
        }
    ],
    "sg:phone":"+32 3 226 20 99",
    "sg:postcode":"2000",
    "sg:province":"Antwerpen",
    "sg:tags":[
        "sport-",
        "kampeermateriaal"
    ],
    "wof:name":"Hans Christian",
    "wof:placetype":"venue"
},
  "geometry": {"coordinates":[4.405020237,51.2307128906],"type":"Point"}
}