{
  "type": "Feature",
  "properties": {
    "addr:full":"Heilig Sakramentstraat 17 Knesselare Oost-Vlaanderen 9910",
    "addr:housenumber":"17",
    "addr:postcode":"9910",
    "addr:street":"Sakramentstraat;Oost-Vlaanderen",
    "iso:country":"BE",
    "sg:address":"Heilig Sakramentstraat 17",
    "sg:city":"Knesselare",
    "sg:classifiers":[
        {
            "category":"Banks & Credit Unions",
            "subcategory":"Investment Brokerage",
            "type":"Services"
        }
    ],
    "sg:phone":"+32 9 374 21 37",
    "sg:postcode":"9910",
    "sg:province":"Oost-Vlaanderen",
    "sg:tags":[
        "repair",
        "-",
        "installation",
        "sanitary",
        "article"
    ],
    "wof:name":"Schelstraete R-werrebrouck Vof",
    "wof:placetype":"venue"
},
  "geometry": {"coordinates":[3.4196109772,51.1426544189],"type":"Point"}
}