{
  "type": "Feature",
  "properties": {
    "iso:country":"BE",
    "sg:address":"Grand Place 1",
    "sg:city":"Vise",
    "sg:orig_category":"Kruideniers Voedingsspeciaalzaken",
    "sg:phone":"+32 4 362 04 65",
    "sg:postcode":"4602",
    "sg:province":"Li\u00e8ge",
    "wof:name":"Baser Hamsa",
    "wof:placetype":"venue"
},
  "geometry": {"coordinates":[5.6671900749,50.6828651428],"type":"Point"}
}