{
  "type": "Feature",
  "properties": {
    "iso:country":"BE",
    "sg:address":"Place De L'etang 11",
    "sg:city":"Marche-en-famenne",
    "sg:orig_category":"Boekhouders",
    "sg:phone":"+32 84 31 11 15",
    "sg:postcode":"6900",
    "sg:province":"Luxembourg",
    "wof:name":"Jo\u00cbl Gerard",
    "wof:placetype":"venue"
},
  "geometry": {"coordinates":[5.3430099487,50.2273483276],"type":"Point"}
}