{
  "type": "Feature",
  "properties": {
    "addr:full":"Kriekenstraat 10 Brugge West-Vlaanderen 8310",
    "addr:housenumber":"10",
    "addr:postcode":"8310",
    "addr:street":"Kriekenstraat",
    "iso:country":"BE",
    "sg:address":"Kriekenstraat 10",
    "sg:city":"Brugge",
    "sg:classifiers":[
        {
            "category":"Cafe",
            "type":"Food & Drink"
        }
    ],
    "sg:phone":"+32 50 36 35 70",
    "sg:postcode":"8310",
    "sg:province":"West-Vlaanderen",
    "sg:tags":[
        "caf\u00e9s"
    ],
    "wof:name":"Francisca Maes",
    "wof:placetype":"venue"
},
  "geometry": {"coordinates":[3.2442829609,51.1982650757],"type":"Point"}
}