{
  "type": "Feature",
  "properties": {
    "addr:full":"Eekhout 18b4 Gent Oost-Vlaanderen 9000",
    "addr:housenumber":"18b4",
    "addr:postcode":"9000",
    "addr:street":"Eekhout;Oost-Vlaanderen",
    "iso:country":"BE",
    "sg:address":"Eekhout 18b4",
    "sg:city":"Gent",
    "sg:orig_category":"Kapsalons",
    "sg:phone":"+32 9 223 02 48",
    "sg:postcode":"9000",
    "sg:province":"Oost-Vlaanderen",
    "wof:name":"Coiffure Paul",
    "wof:placetype":"venue"
},
  "geometry": {"coordinates":[3.7216649055,51.0415802002],"type":"Point"}
}