{
  "type": "Feature",
  "properties": {
    "addr:full":"Vanderborghtstraat 22 Steenokkerzeel (melsbroek) Vlaams-Brabant 1820",
    "addr:housenumber":"22",
    "addr:postcode":"1820",
    "addr:street":"Vanderborghtstraat",
    "iso:country":"BE",
    "sg:address":"Vanderborghtstraat 22",
    "sg:city":"Steenokkerzeel (melsbroek)",
    "sg:classifiers":[
        {
            "category":"Professional",
            "subcategory":"Business Services",
            "type":"Services"
        }
    ],
    "sg:phone":"+32 2 751 42 67",
    "sg:postcode":"1820",
    "sg:province":"Vlaams-Brabant",
    "sg:tags":[
        "bookkeeping"
    ],
    "wof:name":"Weckhuysen P",
    "wof:placetype":"venue"
},
  "geometry": {"coordinates":[4.4839282036,50.9137878418],"type":"Point"}
}