{
  "type": "Feature",
  "properties": {
    "addr:full":"Haachtsesteenweg 389 Kampenhout Vlaams-Brabant 1910",
    "addr:housenumber":"389",
    "addr:postcode":"1910",
    "addr:street":"Haachtsesteenweg",
    "iso:country":"BE",
    "sg:address":"Haachtsesteenweg 389",
    "sg:city":"Kampenhout",
    "sg:orig_category":"Elektrische installaties voor woningen Industri\u00eble elektrische installaties",
    "sg:phone":"+32 16 65 52 89",
    "sg:postcode":"1910",
    "sg:province":"Vlaams-Brabant",
    "wof:name":"Heymbeeck-feremans",
    "wof:placetype":"venue"
},
  "geometry": {"coordinates":[4.5655522346,50.9439544678],"type":"Point"}
}