{
  "type": "Feature",
  "properties": {
    "addr:full":"Rue Ravenstein 36 Bruxelles Bruxelles-Capitale 1000",
    "addr:housenumber":"36",
    "addr:postcode":"1000",
    "addr:street":"Rue Ravenstein",
    "iso:country":"BE",
    "sg:address":"Rue Ravenstein 36",
    "sg:city":"Bruxelles",
    "sg:classifiers":[
        {
            "category":"Professional",
            "subcategory":"Engineering",
            "type":"Services"
        }
    ],
    "sg:phone":"+32 2 289 21 11",
    "sg:postcode":"1000",
    "sg:province":"Bruxelles-Capitale",
    "sg:tags":[
        "environmental",
        "technique",
        "-"
    ],
    "wof:name":"Agence F\u00e9d\u00e9rale De Contr\u00f4le Nucl\u00e9aire (afcn)",
    "wof:placetype":"venue"
},
  "geometry": {"coordinates":[4.3594450951,50.844833374],"type":"Point"}
}