{
  "type": "Feature",
  "properties": {
    "addr:full":"Kerkhovensesteenweg 408 Lommel Limburg 3920",
    "addr:housenumber":"408",
    "addr:postcode":"3920",
    "addr:street":"Kerkhovensesteenweg",
    "iso:country":"BE",
    "sg:address":"Kerkhovensesteenweg 408",
    "sg:city":"Lommel",
    "sg:orig_category":"Elektrische and elektronische apparatuur Gh",
    "sg:phone":"+32 11 40 11 16",
    "sg:postcode":"3920",
    "sg:province":"Limburg",
    "wof:name":"E.i.g. Benelux",
    "wof:placetype":"venue"
},
  "geometry": {"coordinates":[5.2670469284,51.1624565125],"type":"Point"}
}