{
  "type": "Feature",
  "properties": {
    "addr:full":"Edingsesteenweg 131 Ninove Oost-Vlaanderen 9402",
    "addr:housenumber":"131",
    "addr:postcode":"9402",
    "addr:street":"Edingsesteenweg",
    "iso:country":"BE",
    "sg:address":"Edingsesteenweg 131",
    "sg:city":"Ninove",
    "sg:orig_category":"Gespecialiseerde residenti\u00eble bouw",
    "sg:phone":"+32 54 33 85 96",
    "sg:postcode":"9402",
    "sg:province":"Oost-Vlaanderen",
    "wof:name":"Jan Van Vaerenbergh",
    "wof:placetype":"venue"
},
  "geometry": {"coordinates":[4.0395750999,50.8249015808],"type":"Point"}
}