{
  "type": "Feature",
  "properties": {
    "addr:full":"Staatsbaan 76 Zulte Oost-Vlaanderen 9870",
    "addr:housenumber":"76",
    "addr:postcode":"9870",
    "addr:street":"Staatsbaan",
    "iso:country":"BE",
    "sg:address":"Staatsbaan 76",
    "sg:city":"Zulte",
    "sg:orig_category":"Slagers",
    "sg:phone":"+32 9 388 83 25",
    "sg:postcode":"9870",
    "sg:province":"Oost-Vlaanderen",
    "wof:name":"Kipdiscount",
    "wof:placetype":"venue"
},
  "geometry": {"coordinates":[3.4473109245,50.9241447449],"type":"Point"}
}