{
  "type": "Feature",
  "properties": {
    "addr:full":"Rue De La P\u00c9pini\u00c8re 9 Juprelle Li\u00e8ge 4450",
    "addr:housenumber":"9",
    "addr:postcode":"4450",
    "addr:street":"Rue De La Pe\u0301Pinie\u0300Re",
    "iso:country":"BE",
    "sg:address":"Rue De La P\u00c9pini\u00c8re 9",
    "sg:city":"Juprelle",
    "sg:orig_category":"Banques and organismes de cr\u00e9dit",
    "sg:phone":"+32 4 289 02 90",
    "sg:postcode":"4450",
    "sg:province":"Li\u00e8ge",
    "wof:name":"Dipo",
    "wof:placetype":"venue"
},
  "geometry": {"coordinates":[5.527659893,50.7088737488],"type":"Point"}
}