{
  "type": "Feature",
  "properties": {
    "addr:full":"F. Van Marnixstraat 34 Gent-centrum Oost-Vlaanderen 9000",
    "addr:housenumber":"34",
    "addr:postcode":"9000",
    "addr:street":"F. Van Marnixstraat;Oost-Vlaanderen",
    "iso:country":"BE",
    "sg:address":"F. Van Marnixstraat 34",
    "sg:city":"Gent-centrum",
    "sg:orig_category":"Balie van Gent. Avocats and conseillers juridiques. Avocats and conseillers juridiques",
    "sg:phone":"+32 9 222 80 36",
    "sg:postcode":"9000",
    "sg:province":"Oost-Vlaanderen",
    "wof:name":"Van Den Sype Andre",
    "wof:placetype":"venue"
},
  "geometry": {"coordinates":[3.7181169987,51.0403938293],"type":"Point"}
}