{
  "type": "Feature",
  "properties": {
    "addr:full":"Rue De Stassart 76 Elsene/ixelles Bruxelles-Capitale 1050",
    "addr:housenumber":"76",
    "addr:postcode":"1050",
    "addr:street":"Rue De Stassart",
    "iso:country":"BE",
    "sg:address":"Rue De Stassart 76",
    "sg:city":"Elsene/ixelles",
    "sg:classifiers":[
        {
            "category":"Cafe",
            "type":"Food & Drink"
        }
    ],
    "sg:phone":"+32 2 512 61 97",
    "sg:postcode":"1050",
    "sg:province":"Bruxelles-Capitale",
    "sg:tags":[
        "caf\u00e9s"
    ],
    "wof:name":"Anne-marie Avignon",
    "wof:placetype":"venue"
},
  "geometry": {"coordinates":[4.3598327637,50.8355865479],"type":"Point"}
}