{
  "type": "Feature",
  "properties": {
    "addr:full":"Rue Emile Vandervelde 15 Ans Li\u00e8ge 4431",
    "addr:housenumber":"15",
    "addr:postcode":"4431",
    "addr:street":"Rue Emile Vandervelde",
    "iso:country":"BE",
    "sg:address":"Rue Emile Vandervelde 15",
    "sg:city":"Ans",
    "sg:classifiers":[
        {
            "category":"Sports & Exercise",
            "subcategory":"Sports Center",
            "type":"Entertainment"
        }
    ],
    "sg:phone":"+32 4 246 58 35",
    "sg:postcode":"4431",
    "sg:province":"Li\u00e8ge",
    "sg:tags":[
        "installation",
        "sportifs",
        "club",
        "de",
        "terrain",
        "hors",
        "caf\u00e9s"
    ],
    "wof:name":"F.c. Loncin",
    "wof:placetype":"venue"
},
  "geometry": {"coordinates":[5.5024499893,50.6604309082],"type":"Point"}
}