{
  "type": "Feature",
  "properties": {
    "addr:full":"Diegemstraat 55 Machelen Vlaams-Brabant 1830",
    "addr:housenumber":"55",
    "addr:postcode":"1830",
    "addr:street":"Diegemstraat",
    "iso:country":"BE",
    "sg:address":"Diegemstraat 55",
    "sg:city":"Machelen",
    "sg:orig_category":"Pain, p\u00e2tisseries and confiseries. Librairies. Journaux. Tabac",
    "sg:phone":"+32 2 251 41 56",
    "sg:postcode":"1830",
    "sg:province":"Vlaams-Brabant",
    "wof:name":"Dagbladhandel Sven",
    "wof:placetype":"venue"
},
  "geometry": {"coordinates":[4.4356207848,50.9071464539],"type":"Point"}
}