{
  "type": "Feature",
  "properties": {
    "addr:full":"Merenloopweg 6 Rijkevorsel Antwerpen 2310",
    "addr:housenumber":"6",
    "addr:postcode":"2310",
    "addr:street":"Merenloopweg",
    "iso:country":"BE",
    "sg:address":"Merenloopweg 6",
    "sg:city":"Rijkevorsel",
    "sg:orig_category":"Eleveurs and marchands de porcs",
    "sg:phone":"+32 3 314 86 68",
    "sg:postcode":"2310",
    "sg:province":"Antwerpen",
    "wof:name":"Jan Adriaensen",
    "wof:placetype":"venue"
},
  "geometry": {"coordinates":[4.7790532112,51.3514823914],"type":"Point"}
}