{
  "type": "Feature",
  "properties": {
    "addr:full":"Rode Kruisstraat 9 Bocholt Limburg 3950",
    "addr:housenumber":"9",
    "addr:postcode":"3950",
    "addr:street":"Rode Kruisstraat",
    "iso:country":"BE",
    "sg:address":"Rode Kruisstraat 9",
    "sg:city":"Bocholt",
    "sg:classifiers":[
        {
            "category":"Cafe",
            "type":"Food & Drink"
        }
    ],
    "sg:phone":"+32 11 44 61 37",
    "sg:postcode":"3950",
    "sg:province":"Limburg",
    "sg:tags":[
        "caf\u00e9s"
    ],
    "wof:name":"Vorming Sport Ontspan.kwb",
    "wof:placetype":"venue"
},
  "geometry": {"coordinates":[5.506084919,51.1926803589],"type":"Point"}
}