{
  "type": "Feature",
  "properties": {
    "iso:country":"BE",
    "sg:address":"Rue Forseilles 11",
    "sg:city":"Heron",
    "sg:orig_category":"SMEEDWERK, METAALBEWERKING AND POEDERMETALLURGIE",
    "sg:phone":"+32 85 71 18 25",
    "sg:postcode":"4217",
    "sg:province":"Li\u00e8ge",
    "wof:name":"Thirion",
    "wof:placetype":"venue"
},
  "geometry": {"coordinates":[5.0784277916,50.5380249023],"type":"Point"}
}