{
  "type": "Feature",
  "properties": {
    "addr:full":"Spoorwegstraat 45 Brugge West-Vlaanderen 8200",
    "addr:housenumber":"45",
    "addr:postcode":"8200",
    "addr:street":"Spoorwegstraat",
    "iso:country":"BE",
    "sg:address":"Spoorwegstraat 45",
    "sg:city":"Brugge",
    "sg:orig_category":"Kapsalons Schoonheidssalons",
    "sg:phone":"+32 50 38 50 58",
    "sg:postcode":"8200",
    "sg:province":"West-Vlaanderen",
    "wof:name":"Coiffure Nicole",
    "wof:placetype":"venue"
},
  "geometry": {"coordinates":[3.2225170135,51.1868782043],"type":"Point"}
}