{
  "type": "Feature",
  "properties": {
    "iso:country":"BE",
    "sg:address":"Chauss\u00c9e De Boondael 447-449",
    "sg:city":"Elsene",
    "sg:orig_category":"Natuursteenbewerking",
    "sg:phone":"+32 2 648 29 05",
    "sg:postcode":"1050",
    "sg:province":"Bruxelles-Capitale",
    "wof:name":"Buelens",
    "wof:placetype":"venue"
},
  "geometry": {"coordinates":[4.3889250755,50.8166160583],"type":"Point"}
}