{
  "type": "Feature",
  "properties": {
    "iso:country":"BE",
    "sg:address":"Boeschepestraat 23",
    "sg:city":"Heuvelland",
    "sg:classifiers":[
        {
            "category":"Cafe",
            "type":"Food & Drink"
        }
    ],
    "sg:phone":"+32 57 44 44 35",
    "sg:postcode":"8954",
    "sg:province":"West-Vlaanderen",
    "sg:tags":[
        "caf\u00e9s"
    ],
    "wof:name":"Alfons Hardeman",
    "wof:placetype":"venue"
},
  "geometry": {"coordinates":[2.7258870602,50.7965698242],"type":"Point"}
}