{
  "type": "Feature",
  "properties": {
    "iso:country":"BE",
    "sg:address":"Rue Du Cimeti\u00e8re 44",
    "sg:city":"Esneux",
    "sg:classifiers":[
        {
            "category":"Professional",
            "subcategory":"Computer Services",
            "type":"Services"
        }
    ],
    "sg:phone":"+32 4 380 27 56",
    "sg:postcode":"4130",
    "sg:province":"Li\u00e8ge",
    "sg:tags":[
        "-",
        "processing",
        "data"
    ],
    "wof:name":"Mentor",
    "wof:placetype":"venue"
},
  "geometry": {"coordinates":[5.5811638832,50.5359725952],"type":"Point"}
}