{
  "type": "Feature",
  "properties": {
    "iso:country":"BE",
    "sg:address":"Grotestraat 389",
    "sg:city":"Maasmechelen",
    "sg:orig_category":"Eleveurs de bovins",
    "sg:phone":"+32 89 76 03 92",
    "sg:postcode":"3631",
    "sg:province":"Limburg",
    "wof:name":"Gerard Penders",
    "wof:placetype":"venue"
},
  "geometry": {"coordinates":[5.7239232063,50.9423713684],"type":"Point"}
}