{
  "type": "Feature",
  "properties": {
    "iso:country":"BE",
    "sg:address":"Rue Des Francais 370",
    "sg:city":"Liege",
    "sg:orig_category":"Verhuisdiensten",
    "sg:phone":"+32 4 361 63 90",
    "sg:postcode":"4000",
    "sg:province":"Li\u00e8ge",
    "wof:name":"Shurgard Self-storage",
    "wof:placetype":"venue"
},
  "geometry": {"coordinates":[5.539329052,50.6671485901],"type":"Point"}
}