{
  "type": "Feature",
  "properties": {
    "iso:country":"BE",
    "sg:address":"Rue Des Ecoles 9",
    "sg:city":"Ans",
    "sg:orig_category":"Enseignement maternel and primaire",
    "sg:phone":"+32 4 263 57 01",
    "sg:postcode":"4430",
    "sg:province":"Li\u00e8ge",
    "wof:name":"E.f.c.",
    "wof:placetype":"venue"
},
  "geometry": {"coordinates":[5.5195879936,50.6600875854],"type":"Point"}
}