{
  "type": "Feature",
  "properties": {
    "addr:full":"Rue De L'yser 409 Ans Li\u00e8ge 4300",
    "addr:housenumber":"409",
    "addr:postcode":"4300",
    "addr:street":"Rue De L'Yser",
    "iso:country":"BE",
    "sg:address":"Rue De L'yser 409",
    "sg:city":"Ans",
    "sg:classifiers":[
        {
            "category":"Banks & Credit Unions",
            "subcategory":"Bank",
            "type":"Services"
        }
    ],
    "sg:phone":"+32 41610639",
    "sg:postcode":"4300",
    "sg:province":"Li\u00e8ge",
    "wof:name":"Banque Nagelmackers",
    "wof:placetype":"venue"
},
  "geometry": {"coordinates":[-8.5916004181,41.1602516174],"type":"Point"}
}