{
  "type": "Feature",
  "properties": {
    "addr:full":"Rue De Dave 566 Namur Namur 5100",
    "addr:housenumber":"566",
    "addr:postcode":"5100",
    "addr:street":"Rue De Dave",
    "iso:country":"BE",
    "sg:address":"Rue De Dave 566",
    "sg:city":"Namur",
    "sg:orig_category":"Charpentes and couvertures",
    "sg:phone":"+32 81 30 05 10",
    "sg:postcode":"5100",
    "sg:province":"Namur",
    "wof:name":"Edwin Toussaint",
    "wof:placetype":"venue"
},
  "geometry": {"coordinates":[4.8713750839,50.4566345215],"type":"Point"}
}