{
  "type": "Feature",
  "properties": {
    "addr:full":"Plein 4 Laakdal Antwerpen 2430",
    "addr:housenumber":"4",
    "addr:postcode":"2430",
    "addr:street":"Plein",
    "iso:country":"BE",
    "sg:address":"Plein 4",
    "sg:city":"Laakdal",
    "sg:orig_category":"Artsen and specialisten",
    "sg:phone":"+32 14 86 66 66",
    "sg:postcode":"2430",
    "sg:province":"Antwerpen",
    "wof:name":"Franciscus Pauwels",
    "wof:placetype":"venue"
},
  "geometry": {"coordinates":[4.9951839447,51.0967178345],"type":"Point"}
}