{
  "type": "Feature",
  "properties": {
    "addr:full":"Westerlaan 3 Box 4 Waregem West-Vlaanderen 8790",
    "addr:housenumber":"3;4",
    "addr:postcode":"8790",
    "addr:street":"Westerlaan;Box",
    "iso:country":"BE",
    "sg:address":"Westerlaan 3 Box 4",
    "sg:city":"Waregem",
    "sg:orig_category":"Solariums",
    "sg:phone":"+32 56 61 70 17",
    "sg:postcode":"8790",
    "sg:province":"West-Vlaanderen",
    "wof:name":"Euro Body",
    "wof:placetype":"venue"
},
  "geometry": {"coordinates":[3.4247970581,50.8833045959],"type":"Point"}
}