{
  "type": "Feature",
  "properties": {
    "iso:country":"BE",
    "sg:address":"Route De Verviers 54a",
    "sg:city":"Jalhay",
    "sg:classifiers":[
        {
            "category":"Home & Garden",
            "subcategory":"Home Furnishings",
            "type":"Retail Goods"
        }
    ],
    "sg:phone":"+32 87 64 78 72",
    "sg:postcode":"4845",
    "sg:province":"Li\u00e8ge",
    "sg:tags":[
        "-",
        "furniture"
    ],
    "wof:name":"Paulypin Sa",
    "wof:placetype":"venue"
},
  "geometry": {"coordinates":[5.9506092072,50.5589065552],"type":"Point"}
}