{
  "type": "Feature",
  "properties": {
    "iso:country":"BE",
    "sg:address":"Rue Champs-la-haut 3",
    "sg:city":"Morlanwelz",
    "sg:orig_category":"Journaux. Tabac. Librairies",
    "sg:phone":"+32 64 44 59 78",
    "sg:postcode":"7141",
    "sg:province":"Hainaut",
    "wof:name":"O.v. Distribution",
    "wof:placetype":"venue"
},
  "geometry": {"coordinates":[4.2745671272,50.4434738159],"type":"Point"}
}