{
  "type": "Feature",
  "properties": {
    "addr:full":"Koning Albert Ii-laan 27 Bruxelles (schaerbeek) Bruxelles-Capitale 1030",
    "addr:housenumber":"27",
    "addr:postcode":"1030",
    "addr:street":"Koning Albert Ii-Laan",
    "iso:country":"BE",
    "sg:address":"Koning Albert Ii-laan 27",
    "sg:city":"Bruxelles (schaerbeek)",
    "sg:classifiers":[
        {
            "category":"Communications",
            "type":"Services"
        }
    ],
    "sg:phone":"+32 2 202 41 11",
    "sg:postcode":"1030",
    "sg:province":"Bruxelles-Capitale",
    "sg:tags":[
        "telecommunication"
    ],
    "wof:name":"Belgacom Spb/dis (andre Michotte)",
    "wof:placetype":"venue"
},
  "geometry": {"coordinates":[4.3573651314,50.8603782654],"type":"Point"}
}