{
  "type": "Feature",
  "properties": {
    "iso:country":"BE",
    "sg:address":"Rue Saucelle 40",
    "sg:city":"Erquelinnes",
    "sg:orig_category":"Landmeters",
    "sg:phone":"+32 71 55 65 46",
    "sg:postcode":"6560",
    "sg:province":"Hainaut",
    "wof:name":"Jean-marie Lemaire",
    "wof:placetype":"venue"
},
  "geometry": {"coordinates":[4.1181721687,50.3107414246],"type":"Point"}
}