{
  "type": "Feature",
  "properties": {
    "iso:country":"BE",
    "sg:address":"Porte D'anderlecht 1",
    "sg:city":"Brussel/bruxelles",
    "sg:orig_category":"Mus\u00e9es and patrimoine culturel",
    "sg:phone":"+32 2 513 85 87",
    "sg:postcode":"1000",
    "sg:province":"Bruxelles-Capitale",
    "wof:name":"Riolenmuseum",
    "wof:placetype":"venue"
},
  "geometry": {"coordinates":[4.3457350731,50.8451538086],"type":"Point"}
}