{
  "type": "Feature",
  "properties": {
    "addr:full":"Rue Rogier 6 Mons Hainaut 7000",
    "addr:housenumber":"6",
    "addr:postcode":"7000",
    "addr:street":"Rue Rogier;Hainaut",
    "iso:country":"BE",
    "sg:address":"Rue Rogier 6",
    "sg:city":"Mons",
    "sg:classifiers":[
        {
            "category":"Utilities",
            "subcategory":"Mobile Phone",
            "type":"Services"
        }
    ],
    "sg:phone":"+32 65 40 37 00",
    "sg:postcode":"7000",
    "sg:province":"Hainaut",
    "sg:tags":[
        "access",
        "gsm",
        "-",
        "apparatus"
    ],
    "wof:name":"Mons Photo-action Shop",
    "wof:placetype":"venue"
},
  "geometry": {"coordinates":[3.9447050095,50.4520378113],"type":"Point"}
}