{
  "type": "Feature",
  "properties": {
    "addr:full":"P.d.vanhautestraat 4 Kortemark West-Vlaanderen 8610",
    "addr:housenumber":"4",
    "addr:postcode":"8610",
    "addr:street":"P.D.Vanhautestraat",
    "iso:country":"BE",
    "sg:address":"P.d.vanhautestraat 4",
    "sg:city":"Kortemark",
    "sg:classifiers":[
        {
            "category":"Arena",
            "subcategory":"Sports Club",
            "type":"Entertainment"
        }
    ],
    "sg:phone":"+32 51 56 80 56",
    "sg:postcode":"8610",
    "sg:province":"West-Vlaanderen",
    "sg:tags":[
        "de"
    ],
    "wof:name":"Klein Maar Moedig Edewalle - Kortemark",
    "wof:placetype":"venue"
},
  "geometry": {"coordinates":[3.0424449444,51.028503418],"type":"Point"}
}