{
  "type": "Feature",
  "properties": {
    "iso:country":"BE",
    "sg:address":"Kunstlaan 20",
    "sg:city":"Hasselt",
    "sg:classifiers":[
        {
            "category":"Professional",
            "subcategory":"Management & Consulting",
            "type":"Services"
        }
    ],
    "sg:phone":"+32 11 22 21 81",
    "sg:postcode":"3500",
    "sg:province":"Limburg",
    "sg:tags":[
        "consultant",
        "-",
        "legislation",
        "social"
    ],
    "wof:name":"Kinderbijslagfonds K.b.l. Vzw",
    "wof:placetype":"venue"
},
  "geometry": {"coordinates":[5.3448848724,50.9274291992],"type":"Point"}
}