{
  "type": "Feature",
  "properties": {
    "iso:country":"BE",
    "sg:address":"Leuvensesteenweg 282",
    "sg:city":"Kortenberg",
    "sg:orig_category":"Herenkledingzaken",
    "sg:phone":"+32 2 759 63 13",
    "sg:postcode":"3070",
    "sg:province":"Vlaams-Brabant",
    "wof:name":"Huis Fannes",
    "wof:placetype":"venue"
},
  "geometry": {"coordinates":[4.5433568954,50.8880462646],"type":"Point"}
}