{
  "type": "Feature",
  "properties": {
    "iso:country":"BE",
    "sg:address":"Kon. Boudewijnstraat 12",
    "sg:city":"Merelbeke",
    "sg:orig_category":"Dranken",
    "sg:phone":"+32 9 210 85 97",
    "sg:postcode":"9820",
    "sg:province":"Oost-Vlaanderen",
    "wof:name":"Kaapse Kelder",
    "wof:placetype":"venue"
},
  "geometry": {"coordinates":[3.7606499195,51.0180206299],"type":"Point"}
}