{
  "type": "Feature",
  "properties": {
    "addr:full":"Brakelsesteenweg 716 Ninove Oost-Vlaanderen 9400",
    "addr:housenumber":"716",
    "addr:postcode":"9400",
    "addr:street":"Brakelsesteenweg",
    "iso:country":"BE",
    "sg:address":"Brakelsesteenweg 716",
    "sg:city":"Ninove",
    "sg:orig_category":"P\u00e9pini\u00e9ristes",
    "sg:phone":"+32 54 50 41 44",
    "sg:postcode":"9400",
    "sg:province":"Oost-Vlaanderen",
    "wof:name":"Provoost Tuinen",
    "wof:placetype":"venue"
},
  "geometry": {"coordinates":[4.0039701462,50.8359107971],"type":"Point"}
}