{
  "type": "Feature",
  "properties": {
    "addr:full":"Veldstraat 25 Oostrozebeke West-Vlaanderen 8780",
    "addr:housenumber":"25",
    "addr:postcode":"8780",
    "addr:street":"Veldstraat",
    "iso:country":"BE",
    "sg:address":"Veldstraat 25",
    "sg:city":"Oostrozebeke",
    "sg:orig_category":"Installatie van houten of kunststof schrijnwerk",
    "sg:phone":"+32 56 66 91 35",
    "sg:postcode":"8780",
    "sg:province":"West-Vlaanderen",
    "wof:name":"Ludwig Desmet",
    "wof:placetype":"venue"
},
  "geometry": {"coordinates":[3.3406178951,50.9221916199],"type":"Point"}
}