{
  "type": "Feature",
  "properties": {
    "iso:country":"BE",
    "sg:address":"Parc M\u00c9nobu 503",
    "sg:city":"Theux",
    "sg:orig_category":"Artiesten and kunstenaars",
    "sg:phone":"+32 87 37 69 43",
    "sg:postcode":"4910",
    "sg:province":"Li\u00e8ge",
    "wof:name":"Pascale Bonnarens",
    "wof:placetype":"venue"
},
  "geometry": {"coordinates":[5.7701950073,50.4953842163],"type":"Point"}
}