{
  "type": "Feature",
  "properties": {
    "iso:country":"BE",
    "sg:address":"Voie De L'ardenne 62",
    "sg:city":"Chaudfontaine (embourg)",
    "sg:classifiers":[
        {
            "category":"Personal",
            "subcategory":"Barber",
            "type":"Services"
        }
    ],
    "sg:phone":"+32 4 367 78 76",
    "sg:postcode":"4053",
    "sg:province":"Li\u00e8ge",
    "sg:tags":[
        "gentleman",
        "salon",
        "-",
        "hairdressing"
    ],
    "wof:name":"Patrice (chez)",
    "wof:placetype":"venue"
},
  "geometry": {"coordinates":[5.6061401367,50.5930709839],"type":"Point"}
}