{
  "type": "Feature",
  "properties": {
    "addr:full":"Jozef Ii Straat 37 Oostende West-Vlaanderen 8400",
    "addr:housenumber":"37",
    "addr:postcode":"8400",
    "addr:street":"Jozef Ii Straat",
    "iso:country":"BE",
    "sg:address":"Jozef Ii Straat 37",
    "sg:city":"Oostende",
    "sg:classifiers":[
        {
            "category":"Food & Beverages",
            "subcategory":"Fruits & Vegetables",
            "type":"Retail Goods"
        }
    ],
    "sg:phone":"+32 59 70 04 42",
    "sg:postcode":"8400",
    "sg:province":"West-Vlaanderen",
    "sg:tags":[
        "l\u00e9gumes",
        "gr"
    ],
    "wof:name":"Erletin",
    "wof:placetype":"venue"
},
  "geometry": {"coordinates":[2.9203300476,51.2289886475],"type":"Point"}
}