{
  "type": "Feature",
  "properties": {
    "iso:country":"BE",
    "sg:address":"Lommersweiler 66a",
    "sg:city":"Sankt Vith/saint-vith",
    "sg:orig_category":"Gespecialiseerde residenti\u00eble bouw",
    "sg:phone":"+32 80 22 18 88",
    "sg:postcode":"4783",
    "sg:province":"Li\u00e8ge",
    "wof:name":"Manfred Arens",
    "wof:placetype":"venue"
},
  "geometry": {"coordinates":[6.1624298096,50.2378082275],"type":"Point"}
}