{
  "type": "Feature",
  "properties": {
    "iso:country":"BE",
    "sg:address":"J.-b. Vanp\u00c9straat 44",
    "sg:city":"Vorst/forest",
    "sg:orig_category":"Industri\u00eble wasserijen and droogkuis",
    "sg:phone":"+32 2 376 03 63",
    "sg:postcode":"1190",
    "sg:province":"Bruxelles-Capitale",
    "wof:name":"St.denis-clean",
    "wof:placetype":"venue"
},
  "geometry": {"coordinates":[4.3189001083,50.8097991943],"type":"Point"}
}