{
  "type": "Feature",
  "properties": {
    "iso:country":"BE",
    "sg:address":"Oostendelaan 292",
    "sg:city":"Middelkerke",
    "sg:classifiers":[
        {
            "category":"Fast Food",
            "type":"Food & Drink"
        }
    ],
    "sg:phone":"+32 59 31 33 35",
    "sg:postcode":"8430",
    "sg:province":"West-Vlaanderen",
    "sg:tags":[
        "meeneem",
        "restaurant"
    ],
    "wof:name":"Quick",
    "wof:placetype":"venue"
},
  "geometry": {"coordinates":[2.8382198811,51.1928291321],"type":"Point"}
}