{
  "type": "Feature",
  "properties": {
    "addr:full":"Boomgaardstraat 39ba Antwerpen Antwerpen 2018",
    "addr:housenumber":"39ba",
    "addr:postcode":"2018",
    "addr:street":"Boomgaardstraat",
    "iso:country":"BE",
    "sg:address":"Boomgaardstraat 39ba",
    "sg:city":"Antwerpen",
    "sg:orig_category":"Instituts pour enfants en difficult\u00e9. Orphelinats",
    "sg:phone":"+32 3 286 97 25",
    "sg:postcode":"2018",
    "sg:province":"Antwerpen",
    "wof:name":"Home Good Engels",
    "wof:placetype":"venue"
},
  "geometry": {"coordinates":[4.4201049805,51.2001609802],"type":"Point"}
}