{
  "type": "Feature",
  "properties": {
    "iso:country":"BE",
    "sg:address":"Atrebatenstraat 19",
    "sg:city":"Etterbeek/etterbeek",
    "sg:orig_category":"Public-relationsbureaus",
    "sg:phone":"+32 2 733 96 98",
    "sg:postcode":"1040",
    "sg:province":"Bruxelles-Capitale",
    "wof:name":"J. Ponzi",
    "wof:placetype":"venue"
},
  "geometry": {"coordinates":[4.405506134,50.8372116089],"type":"Point"}
}