{
  "type": "Feature",
  "properties": {
    "addr:full":"Grand Rue 32 Martelange Luxembourg 6630",
    "addr:housenumber":"32",
    "addr:postcode":"6630",
    "addr:street":"Grand Rue",
    "iso:country":"BE",
    "sg:address":"Grand Rue 32",
    "sg:city":"Martelange",
    "sg:classifiers":[
        {
            "category":"Health Services",
            "subcategory":"Doctor",
            "type":"Services"
        }
    ],
    "sg:phone":"+32 63 60 17 77",
    "sg:postcode":"6630",
    "sg:province":"Luxembourg",
    "sg:tags":[
        "medicinephysicians",
        "surgeon"
    ],
    "wof:name":"Chidiac Tania",
    "wof:placetype":"venue"
},
  "geometry": {"coordinates":[5.7386841774,49.8317871094],"type":"Point"}
}