{
  "type": "Feature",
  "properties": {
    "addr:full":"Chauss\u00c9e D\u00b4alsemberg 1043 Uccle Bruxelles-Capitale 1180",
    "addr:housenumber":"1043",
    "addr:postcode":"1180",
    "addr:street":"Chausse\u0301E D\u00b4Alsemberg",
    "iso:country":"BE",
    "sg:address":"Chauss\u00c9e D\u00b4alsemberg 1043",
    "sg:city":"Uccle",
    "sg:classifiers":[
        {
            "category":"Restaurant",
            "type":"Food & Drink"
        }
    ],
    "sg:phone":"+32 2 332 03 00",
    "sg:postcode":"1180",
    "sg:province":"Bruxelles-Capitale",
    "sg:tags":[
        "organisation",
        "de",
        "f\u00eates",
        "catering"
    ],
    "wof:name":"Le Village",
    "wof:placetype":"venue"
},
  "geometry": {"coordinates":[4.3329939842,50.7925491333],"type":"Point"}
}