{
  "type": "Feature",
  "properties": {
    "iso:country":"BE",
    "sg:address":"Rue De Liboichant 12",
    "sg:city":"Vresse-sur-semois",
    "sg:classifiers":[
        {
            "category":"Professional",
            "type":"Services"
        }
    ],
    "sg:phone":"+32 61 50 80 70",
    "sg:postcode":"5550",
    "sg:province":"Namur",
    "sg:tags":[
        "organisation",
        "de",
        "restaurants",
        "f\u00cates",
        "catering"
    ],
    "wof:name":"Le Charme De La Semois",
    "wof:placetype":"venue"
},
  "geometry": {"coordinates":[4.9336900711,49.8729820251],"type":"Point"}
}