{
  "type": "Feature",
  "properties": {
    "addr:full":"Square De L'atomium 0 Brussel/bruxelles Bruxelles-Capitale 1020",
    "addr:housenumber":"0",
    "addr:postcode":"1020",
    "addr:street":"Square De L'Atomium;/",
    "iso:country":"BE",
    "sg:address":"Square De L'atomium 0",
    "sg:city":"Brussel/bruxelles",
    "sg:orig_category":"V\u00eatements",
    "sg:phone":"+32 2 478 73 22",
    "sg:postcode":"1020",
    "sg:province":"Bruxelles-Capitale",
    "wof:name":"Maison Khan Pace",
    "wof:placetype":"venue"
},
  "geometry": {"coordinates":[4.3462300301,50.8855514526],"type":"Point"}
}