{
  "type": "Feature",
  "properties": {
    "iso:country":"BE",
    "sg:address":"Rue Neuve 50",
    "sg:city":"Brussel/bruxelles",
    "sg:orig_category":"Articles de camping and de sport. Maroquinerie and articles de voyage. Chaussures",
    "sg:phone":"+32 2 218 82 78",
    "sg:postcode":"1000",
    "sg:province":"Bruxelles-Capitale",
    "wof:name":"Mach 3",
    "wof:placetype":"venue"
},
  "geometry": {"coordinates":[4.3549852371,50.8520240784],"type":"Point"}
}