{
  "type": "Feature",
  "properties": {
    "addr:full":"Kempischdok (kaai 33) Antwerpen Antwerpen 2030",
    "addr:housenumber":"33",
    "addr:postcode":"2030",
    "addr:street":"Kaai",
    "iso:country":"BE",
    "sg:address":"Kempischdok (kaai 33)",
    "sg:city":"Antwerpen",
    "sg:classifiers":[
        {
            "category":"Government",
            "subcategory":"Department Of Motor Vehicles",
            "type":"Public Place"
        }
    ],
    "sg:phone":"+32 3 254 11 06",
    "sg:postcode":"2030",
    "sg:province":"Antwerpen",
    "sg:tags":[
        "regulator",
        "reducer",
        "speed"
    ],
    "wof:name":"Crane Repair-siei",
    "wof:placetype":"venue"
},
  "geometry": {"coordinates":[4.4133310318,51.2346000671],"type":"Point"}
}