{
  "type": "Feature",
  "properties": {
    "addr:full":"Molenstraat 2be Tessenderlo Limburg 3980",
    "addr:housenumber":"2be",
    "addr:postcode":"3980",
    "addr:street":"Molenstraat",
    "iso:country":"BE",
    "sg:address":"Molenstraat 2be",
    "sg:city":"Tessenderlo",
    "sg:orig_category":"Ziekenvervoer",
    "sg:phone":"+32 476 49 82 34",
    "sg:postcode":"3980",
    "sg:province":"Limburg",
    "wof:name":"Het Vlaamse Kruis",
    "wof:placetype":"venue"
},
  "geometry": {"coordinates":[5.0915198326,51.0599899292],"type":"Point"}
}