{
  "type": "Feature",
  "properties": {
    "iso:country":"BE",
    "sg:address":"Place Joseph Willem 2-4",
    "sg:city":"Li\u00e8ge 1 (ch\u00ean\u00e9e)",
    "sg:classifiers":[
        {
            "category":"Professional",
            "subcategory":"Art Services",
            "type":"Services"
        }
    ],
    "sg:phone":"+32 4 365 11 22",
    "sg:postcode":"4032",
    "sg:province":"Li\u00e8ge",
    "sg:tags":[
        "photographer"
    ],
    "wof:name":"Erfachrome Sprl",
    "wof:placetype":"venue"
},
  "geometry": {"coordinates":[5.615418911,50.611114502],"type":"Point"}
}