{
  "type": "Feature",
  "properties": {
    "addr:full":"Antwerpsesteenweg 489 Brussel/bruxelles Bruxelles-Capitale 1000",
    "addr:housenumber":"489",
    "addr:postcode":"1000",
    "addr:street":"Antwerpsesteenweg;/",
    "iso:country":"BE",
    "sg:address":"Antwerpsesteenweg 489",
    "sg:city":"Brussel/bruxelles",
    "sg:classifiers":[
        {
            "category":"Restaurant",
            "type":"Food & Drink"
        }
    ],
    "sg:phone":"+32 2 203 35 46",
    "sg:postcode":"1000",
    "sg:province":"Bruxelles-Capitale",
    "sg:tags":[
        "caf\u00e9s"
    ],
    "wof:name":"Taverne Chez Les Amis",
    "wof:placetype":"venue"
},
  "geometry": {"coordinates":[4.3608899117,50.8712730408],"type":"Point"}
}