{
  "type": "Feature",
  "properties": {
    "iso:country":"BE",
    "sg:address":"Claventweg 49",
    "sg:city":"Gistel",
    "sg:classifiers":[
        {
            "category":"Shopping",
            "subcategory":"Clothing, Apparel, & Fashions",
            "type":"Retail Goods"
        }
    ],
    "sg:phone":"+32 59 27 75 34",
    "sg:postcode":"8470",
    "sg:province":"West-Vlaanderen",
    "sg:tags":[
        "underwear",
        "lingerie",
        "-"
    ],
    "wof:name":"Dewaco Bvba",
    "wof:placetype":"venue"
},
  "geometry": {"coordinates":[2.9433829784,51.1480026245],"type":"Point"}
}