{
  "type": "Feature",
  "properties": {
    "addr:full":"Nwe Jeukstraat 72 Gingelom (groot) Limburg 3890",
    "addr:housenumber":"72",
    "addr:postcode":"3890",
    "addr:street":"Jeukstraat;Groot Limburg",
    "iso:country":"BE",
    "sg:address":"Nwe Jeukstraat 72",
    "sg:city":"Gingelom (groot)",
    "sg:classifiers":[
        {
            "category":"Personal",
            "subcategory":"Beauty Salon",
            "type":"Services"
        }
    ],
    "sg:phone":"+32 11 48 11 59",
    "sg:postcode":"3890",
    "sg:province":"Limburg",
    "sg:tags":[
        "de",
        "coiffure"
    ],
    "wof:name":"Coiffure Nora",
    "wof:placetype":"venue"
},
  "geometry": {"coordinates":[5.1322197914,50.7487831116],"type":"Point"}
}