{
  "type": "Feature",
  "properties": {
    "iso:country":"BE",
    "sg:address":"Oude Brugstraat 16",
    "sg:city":"Dendermonde",
    "sg:classifiers":[
        {
            "category":"Restaurant",
            "type":"Food & Drink"
        }
    ],
    "sg:phone":"+32 52 42 32 46",
    "sg:postcode":"9200",
    "sg:province":"Oost-Vlaanderen",
    "wof:name":"Het Palinghuis Aan De Schelde",
    "wof:placetype":"venue"
},
  "geometry": {"coordinates":[4.0113978386,51.0047416687],"type":"Point"}
}