{
  "type": "Feature",
  "properties": {
    "addr:full":"Jules Soenenstraat 10 Deinze Oost-Vlaanderen 9800",
    "addr:housenumber":"10",
    "addr:postcode":"9800",
    "addr:street":"Soenenstraat",
    "iso:country":"BE",
    "sg:address":"Jules Soenenstraat 10",
    "sg:city":"Deinze",
    "sg:orig_category":"Imprimeries and copyshops",
    "sg:phone":"+32 9 386 94 19",
    "sg:postcode":"9800",
    "sg:province":"Oost-Vlaanderen",
    "wof:name":"Luc Van Damme",
    "wof:placetype":"venue"
},
  "geometry": {"coordinates":[3.5338089466,50.9858016968],"type":"Point"}
}