{
  "type": "Feature",
  "properties": {
    "addr:full":"Avenue De L'abbaye 7ba Anthisnes Li\u00e8ge 4160",
    "addr:housenumber":"7ba",
    "addr:postcode":"4160",
    "addr:street":"Avenue De L'Abbaye",
    "iso:country":"BE",
    "sg:address":"Avenue De L'abbaye 7ba",
    "sg:city":"Anthisnes",
    "sg:orig_category":"Herstellingen and onderhoud van auto's",
    "sg:phone":"+32 4 383 63 28",
    "sg:postcode":"4160",
    "sg:province":"Li\u00e8ge",
    "wof:name":"Garage Deroua",
    "wof:placetype":"venue"
},
  "geometry": {"coordinates":[5.5209069252,50.4795379639],"type":"Point"}
}