{
  "type": "Feature",
  "properties": {
    "iso:country":"BE",
    "sg:address":"Kerkomtrek 8-2",
    "sg:city":"Menen",
    "sg:classifiers":[
        {
            "category":"Professional",
            "subcategory":"Accounting & Tax Preparation",
            "type":"Services"
        }
    ],
    "sg:phone":"+32 56 51 40 90",
    "sg:postcode":"8930",
    "sg:province":"West-Vlaanderen",
    "sg:tags":[
        "bookkeeper"
    ],
    "wof:name":"Ad Finance",
    "wof:placetype":"venue"
},
  "geometry": {"coordinates":[3.1228699684,50.7943496704],"type":"Point"}
}