{
  "type": "Feature",
  "properties": {
    "addr:full":"Pathoekeweg 18-20 Brugge West-Vlaanderen 8000",
    "addr:housenumber":"18-20",
    "addr:postcode":"8000",
    "addr:street":"Pathoekeweg",
    "iso:country":"BE",
    "sg:address":"Pathoekeweg 18-20",
    "sg:city":"Brugge",
    "sg:classifiers":[
        {
            "category":"Building & Trades",
            "subcategory":"Construction",
            "type":"Services"
        }
    ],
    "sg:phone":"+32 50 31 31 41",
    "sg:postcode":"8000",
    "sg:province":"West-Vlaanderen",
    "sg:tags":[
        "installation",
        "-",
        "central",
        "heating"
    ],
    "wof:name":"Vanneste Bvba",
    "wof:placetype":"venue"
},
  "geometry": {"coordinates":[3.210203886,51.2460136414],"type":"Point"}
}