{
  "type": "Feature",
  "properties": {
    "addr:full":"Grand Place 14 Haine-saint-pierre Hainaut 7100",
    "addr:housenumber":"14",
    "addr:postcode":"7100",
    "addr:street":"Grand Place",
    "iso:country":"BE",
    "sg:address":"Grand Place 14",
    "sg:city":"Haine-saint-pierre",
    "sg:orig_category":"Eclairage et \u00e9quipements du foyer",
    "sg:phone":"+32 64 22 55 97",
    "sg:postcode":"7100",
    "sg:province":"Hainaut",
    "wof:name":"Horlux- Cadolux",
    "wof:placetype":"venue"
},
  "geometry": {"coordinates":[4.2016019821,50.4606437683],"type":"Point"}
}