{
  "type": "Feature",
  "properties": {
    "addr:full":"Rue De Velaine 136 Sambreville Namur 5060",
    "addr:housenumber":"136",
    "addr:postcode":"5060",
    "addr:street":"Rue De Velaine",
    "iso:country":"BE",
    "sg:address":"Rue De Velaine 136",
    "sg:city":"Sambreville",
    "sg:orig_category":"Divers amusement Huishoudapparaten, televisies and radio's Verlichting and huishoudartikelen",
    "sg:phone":"+32 82 22 94 97",
    "sg:postcode":"5060",
    "sg:province":"Namur",
    "wof:name":"Sono les Noctambules",
    "wof:placetype":"venue"
},
  "geometry": {"coordinates":[4.6285200119,50.4448738098],"type":"Point"}
}