{
  "type": "Feature",
  "properties": {
    "addr:full":"Stefaniastraat 90 Brussel/bruxelles Bruxelles-Capitale 1020",
    "addr:housenumber":"90",
    "addr:postcode":"1020",
    "addr:street":"Stefaniastraat;/",
    "iso:country":"BE",
    "sg:address":"Stefaniastraat 90",
    "sg:city":"Brussel/bruxelles",
    "sg:orig_category":"Paramedische behandelingen",
    "sg:phone":"+32 2 427 48 25",
    "sg:postcode":"1020",
    "sg:province":"Bruxelles-Capitale",
    "wof:name":"P. Schmidt",
    "wof:placetype":"venue"
},
  "geometry": {"coordinates":[4.3526391983,50.8771438599],"type":"Point"}
}