{
  "type": "Feature",
  "properties": {
    "iso:country":"BE",
    "sg:address":"Keltenlaan 61",
    "sg:city":"Etterbeek/etterbeek",
    "sg:orig_category":"Restaurants Zuivelproducten",
    "sg:phone":"+32 2 736 07 88",
    "sg:postcode":"1040",
    "sg:province":"Bruxelles-Capitale",
    "wof:name":"Glacier Le Cervin",
    "wof:placetype":"venue"
},
  "geometry": {"coordinates":[4.396214962,50.8374404907],"type":"Point"}
}