{
  "type": "Feature",
  "properties": {
    "addr:full":"Looi 6a Hoogstraten Antwerpen 2321",
    "addr:housenumber":"6a",
    "addr:postcode":"2321",
    "addr:street":"Looi",
    "iso:country":"BE",
    "sg:address":"Looi 6a",
    "sg:city":"Hoogstraten",
    "sg:orig_category":"Tuinen",
    "sg:phone":"+32 3 315 71 83",
    "sg:postcode":"2321",
    "sg:province":"Antwerpen",
    "wof:name":"Pauwels",
    "wof:placetype":"venue"
},
  "geometry": {"coordinates":[4.7517747879,51.4476661682],"type":"Point"}
}