{
  "type": "Feature",
  "properties": {
    "iso:country":"BE",
    "sg:address":"Steenstraat 96",
    "sg:city":"Brugge",
    "sg:classifiers":[
        {
            "category":"Restaurant",
            "type":"Food & Drink"
        }
    ],
    "sg:phone":"+32 50 33 47 99",
    "sg:postcode":"8000",
    "sg:province":"West-Vlaanderen",
    "sg:tags":[
        "organisation",
        "de",
        "f\u00eates",
        "catering"
    ],
    "wof:name":"De Brugse Hanze",
    "wof:placetype":"venue"
},
  "geometry": {"coordinates":[3.2208189964,51.2058868408],"type":"Point"}
}