{
  "type": "Feature",
  "properties": {
    "addr:full":"Pontweg 10b1 Haaltert Oost-Vlaanderen 9450",
    "addr:housenumber":"10b1",
    "addr:postcode":"9450",
    "addr:street":"Pontweg",
    "iso:country":"BE",
    "sg:address":"Pontweg 10b1",
    "sg:city":"Haaltert",
    "sg:orig_category":"Architectes",
    "sg:phone":"+32 53 83 86 25",
    "sg:postcode":"9450",
    "sg:province":"Oost-Vlaanderen",
    "wof:name":"Ewoud Saey",
    "wof:placetype":"venue"
},
  "geometry": {"coordinates":[3.9879169464,50.8956375122],"type":"Point"}
}