{
  "type": "Feature",
  "properties": {
    "addr:full":"Rue Colonel Piron 89 Fleron Li\u00e8ge 4624",
    "addr:housenumber":"89",
    "addr:postcode":"4624",
    "addr:street":"Rue Colonel Piron",
    "iso:country":"BE",
    "sg:address":"Rue Colonel Piron 89",
    "sg:city":"Fleron",
    "sg:orig_category":"Sportclubs Sportterreinen and installaties behalve sportcentra",
    "sg:phone":"+32 4 361 22 68",
    "sg:postcode":"4624",
    "sg:province":"Li\u00e8ge",
    "wof:name":"R. Star F.c. Romsee",
    "wof:placetype":"venue"
},
  "geometry": {"coordinates":[5.6696162224,50.60987854],"type":"Point"}
}