{
  "type": "Feature",
  "properties": {
    "addr:full":"Vrasenestraat 56 Beveren Oost-Vlaanderen 9120",
    "addr:housenumber":"56",
    "addr:postcode":"9120",
    "addr:street":"Vrasenestraat",
    "iso:country":"BE",
    "sg:address":"Vrasenestraat 56",
    "sg:city":"Beveren",
    "sg:orig_category":"Boucheries",
    "sg:phone":"+32 3 775 71 13",
    "sg:postcode":"9120",
    "sg:province":"Oost-Vlaanderen",
    "wof:name":"Freddy Joris",
    "wof:placetype":"venue"
},
  "geometry": {"coordinates":[4.2547149658,51.2136116028],"type":"Point"}
}