{
  "type": "Feature",
  "properties": {
    "addr:full":"Rue Des Cyclistes Fronti\u00e8re 24 Vis\u00e9 Li\u00e8ge 4600",
    "addr:housenumber":"24",
    "addr:postcode":"4600",
    "addr:street":"Rue Des Cyclistes Frontie\u0300Re",
    "iso:country":"BE",
    "sg:address":"Rue Des Cyclistes Fronti\u00e8re 24",
    "sg:city":"Vis\u00e9",
    "sg:classifiers":[
        {
            "category":"Professional",
            "subcategory":"Advertising",
            "type":"Services"
        }
    ],
    "sg:phone":"+32 4 374 86 19",
    "sg:postcode":"4600",
    "sg:province":"Li\u00e8ge",
    "sg:tags":[
        "clothes"
    ],
    "wof:name":"A.m.f. Impression Snc",
    "wof:placetype":"venue"
},
  "geometry": {"coordinates":[5.7067060471,50.74609375],"type":"Point"}
}