{
  "type": "Feature",
  "properties": {
    "addr:full":"Pl. Chap.\u00c0 Wattines 1 Leuze-en-hainaut Hainaut 7903",
    "addr:housenumber":"1",
    "addr:postcode":"7903",
    "addr:street":"Pl.;\u0300 Wattines",
    "iso:country":"BE",
    "sg:address":"Pl. Chap.\u00c0 Wattines 1",
    "sg:city":"Leuze-en-hainaut",
    "sg:orig_category":"Enseignement maternel and primaire",
    "sg:phone":"+32 69 66 30 54",
    "sg:postcode":"7903",
    "sg:province":"Hainaut",
    "wof:name":"Ecole Fond. Communale",
    "wof:placetype":"venue"
},
  "geometry": {"coordinates":[3.6553399563,50.6128311157],"type":"Point"}
}