{
  "type": "Feature",
  "properties": {
    "addr:full":"Kerkstraat 8 Pittem West-Vlaanderen 8740",
    "addr:housenumber":"8",
    "addr:postcode":"8740",
    "addr:street":"Kerkstraat",
    "iso:country":"BE",
    "sg:address":"Kerkstraat 8",
    "sg:city":"Pittem",
    "sg:classifiers":[
        {
            "category":"Professional",
            "subcategory":"Art Services",
            "type":"Services"
        }
    ],
    "sg:phone":"+32 51 46 60 79",
    "sg:postcode":"8740",
    "sg:province":"West-Vlaanderen",
    "sg:tags":[
        "technical",
        "photographer",
        "industrial",
        "-"
    ],
    "wof:name":"Roygens Foto - & Videoateljee",
    "wof:placetype":"venue"
},
  "geometry": {"coordinates":[3.2668559551,50.9937057495],"type":"Point"}
}