{
  "type": "Feature",
  "properties": {
    "addr:full":"Beerstraat 5 Kruishoutem Oost-Vlaanderen 9770",
    "addr:housenumber":"5",
    "addr:postcode":"9770",
    "addr:street":"Beerstraat",
    "iso:country":"BE",
    "sg:address":"Beerstraat 5",
    "sg:city":"Kruishoutem",
    "sg:classifiers":[
        {
            "category":"Home & Garden",
            "subcategory":"Carpets & Floor Coverings",
            "type":"Retail Goods"
        }
    ],
    "sg:phone":"+32 9 383 85 04",
    "sg:postcode":"9770",
    "sg:province":"Oost-Vlaanderen",
    "sg:tags":[
        "layer",
        "mosaicists"
    ],
    "wof:name":"Derammelaere B",
    "wof:placetype":"venue"
},
  "geometry": {"coordinates":[3.5084600449,50.892791748],"type":"Point"}
}