{
  "type": "Feature",
  "properties": {
    "iso:country":"BE",
    "sg:address":"Walenstraat 35",
    "sg:city":"Hasselt",
    "sg:orig_category":"Plomberie, chauffage and installations sanitaires",
    "sg:phone":"+32 11 21 17 83",
    "sg:postcode":"3500",
    "sg:province":"Limburg",
    "wof:name":"Rogier Hiemeleers",
    "wof:placetype":"venue"
},
  "geometry": {"coordinates":[5.3543171883,50.9558830261],"type":"Point"}
}