{
  "type": "Feature",
  "properties": {
    "addr:full":"Geeraard De Cremerstraat 22 Kruibeke Oost-Vlaanderen 9150",
    "addr:housenumber":"22",
    "addr:postcode":"9150",
    "addr:street":"Geeraard De Cremerstraat",
    "iso:country":"BE",
    "sg:address":"Geeraard De Cremerstraat 22",
    "sg:city":"Kruibeke",
    "sg:orig_category":"Banques and organismes de cr\u00e9dit",
    "sg:phone":"+32 3 740 03 00",
    "sg:postcode":"9150",
    "sg:province":"Oost-Vlaanderen",
    "wof:name":"Kbc",
    "wof:placetype":"venue"
},
  "geometry": {"coordinates":[4.2908701897,51.1279067993],"type":"Point"}
}