{
  "type": "Feature",
  "properties": {
    "iso:country":"BE",
    "sg:address":"Otegemstraat 4",
    "sg:city":"Anzegem",
    "sg:orig_category":"Eleveurs de bovins. Installation \u00e9lectrique r\u00e9sidentielle. Eleveurs and marchands de porcs",
    "sg:phone":"+32 56 77 52 34",
    "sg:postcode":"8570",
    "sg:province":"West-Vlaanderen",
    "wof:name":"Henk Vandenbogaerde",
    "wof:placetype":"venue"
},
  "geometry": {"coordinates":[3.4058060646,50.8319320679],"type":"Point"}
}