{
  "type": "Feature",
  "properties": {
    "iso:country":"BE",
    "sg:address":"Nijvelsesteenweg 615",
    "sg:city":"Halle",
    "sg:orig_category":"Stations-service and carburants. Entretien and r\u00e9parations de voitures",
    "sg:phone":"+32 2 356 61 76",
    "sg:postcode":"1500",
    "sg:province":"Vlaams-Brabant",
    "wof:name":"Vankerkhoven A",
    "wof:placetype":"venue"
},
  "geometry": {"coordinates":[4.2585802078,50.7090415955],"type":"Point"}
}