{
  "type": "Feature",
  "properties": {
    "addr:full":"Pamelstr-oost 429 Ninove Oost-Vlaanderen 9400",
    "addr:housenumber":"429",
    "addr:postcode":"9400",
    "iso:country":"BE",
    "sg:address":"Pamelstr-oost 429",
    "sg:city":"Ninove",
    "sg:classifiers":[
        {
            "category":"Professional",
            "type":"Services"
        }
    ],
    "sg:phone":"+32 54 33 27 97",
    "sg:postcode":"9400",
    "sg:province":"Oost-Vlaanderen",
    "sg:tags":[
        "transport",
        "road"
    ],
    "wof:name":"Suntrans Nv",
    "wof:placetype":"venue"
},
  "geometry": {"coordinates":[4.0149002075,50.8392601013],"type":"Point"}
}