{
  "type": "Feature",
  "properties": {
    "addr:full":"Avenue Du Bois Jacques 0 Mouscron Hainaut 7711",
    "addr:housenumber":"0",
    "addr:postcode":"7711",
    "addr:street":"Avenue Du Bois Jacques",
    "iso:country":"BE",
    "sg:address":"Avenue Du Bois Jacques 0",
    "sg:city":"Mouscron",
    "sg:orig_category":"Gestion des d\u00e9charges and sites d\u00e9finitifs de stockage",
    "sg:phone":"+32 56 48 44 58",
    "sg:postcode":"7711",
    "sg:province":"Hainaut",
    "wof:name":"Parcs A Conteneurs Dottignies",
    "wof:placetype":"venue"
},
  "geometry": {"coordinates":[3.3178079128,50.7265472412],"type":"Point"}
}