{
  "type": "Feature",
  "properties": {
    "addr:full":"Jef Lambeauxlaan 20 Koksijde West-Vlaanderen 8670",
    "addr:housenumber":"20",
    "addr:postcode":"8670",
    "addr:street":"Jef Lambeauxlaan",
    "iso:country":"BE",
    "sg:address":"Jef Lambeauxlaan 20",
    "sg:city":"Koksijde",
    "sg:orig_category":"Producteurs de fruits",
    "sg:phone":"+32 58 51 07 87",
    "sg:postcode":"8670",
    "sg:province":"West-Vlaanderen",
    "wof:name":"Andre Devos",
    "wof:placetype":"venue"
},
  "geometry": {"coordinates":[2.6225221157,51.1050796509],"type":"Point"}
}