{
  "type": "Feature",
  "properties": {
    "iso:country":"BE",
    "sg:address":"Rue Charles Sambon 28",
    "sg:city":"Wavre",
    "sg:orig_category":"Dameskledingzaken Herenkledingzaken",
    "sg:phone":"+32 10 24 27 13",
    "sg:postcode":"1300",
    "sg:province":"Brabant Wallon",
    "wof:name":"Roussel",
    "wof:placetype":"venue"
},
  "geometry": {"coordinates":[4.6113810539,50.7161254883],"type":"Point"}
}