{
  "type": "Feature",
  "properties": {
    "addr:full":"Spoorwegstraat 14 Brugge (sint-michiels) West-Vlaanderen 8200",
    "addr:housenumber":"14",
    "addr:postcode":"8200",
    "addr:street":"Spoorwegstraat",
    "iso:country":"BE",
    "sg:address":"Spoorwegstraat 14",
    "sg:city":"Brugge (sint-michiels)",
    "sg:classifiers":[
        {
            "category":"Education",
            "subcategory":"School",
            "type":"Public Place"
        }
    ],
    "sg:phone":"+32 50 40 30 20",
    "sg:postcode":"8200",
    "sg:province":"West-Vlaanderen",
    "sg:tags":[
        "secondary"
    ],
    "wof:name":"Ter Groene Poorte Bakkerij-, Slagerij-, Hotelschool",
    "wof:placetype":"venue"
},
  "geometry": {"coordinates":[3.2166919708,51.195640564],"type":"Point"}
}