{
  "type": "Feature",
  "properties": {
    "iso:country":"BE",
    "sg:address":"Rue Chauss\u00c9e 56",
    "sg:city":"Awans",
    "sg:orig_category":"Openbare veiligheid",
    "sg:phone":"+32 4 246 13 92",
    "sg:postcode":"4342",
    "sg:province":"Li\u00e8ge",
    "wof:name":"Police F\u00c9d\u00c9rale",
    "wof:placetype":"venue"
},
  "geometry": {"coordinates":[5.4607429504,50.6841392517],"type":"Point"}
}