{
  "type": "Feature",
  "properties": {
    "addr:full":"Rue De L'ath\u00c9n\u00c9e Royal 75 Sint-lambrechts-woluwe/woluwe-saint-lambert Bruxelles-Capitale 1200",
    "addr:housenumber":"75",
    "addr:postcode":"1200",
    "addr:street":"Rue De L'Athe;Royal",
    "iso:country":"BE",
    "sg:address":"Rue De L'ath\u00c9n\u00c9e Royal 75",
    "sg:city":"Sint-lambrechts-woluwe/woluwe-saint-lambert",
    "sg:orig_category":"Enseignement maternel and primaire",
    "sg:phone":"+32 2 770 99 23",
    "sg:postcode":"1200",
    "sg:province":"Bruxelles-Capitale",
    "wof:name":"Ecole Fondamentale",
    "wof:placetype":"venue"
},
  "geometry": {"coordinates":[4.4388599396,50.8501777649],"type":"Point"}
}