{
  "type": "Feature",
  "properties": {
    "addr:full":"Kapellestraat 20 Aartselaar Antwerpen 2630",
    "addr:housenumber":"20",
    "addr:postcode":"2630",
    "addr:street":"Kapellestraat",
    "iso:country":"BE",
    "sg:address":"Kapellestraat 20",
    "sg:city":"Aartselaar",
    "sg:orig_category":"Opticiens",
    "sg:phone":"+32 3 887 96 49",
    "sg:postcode":"2630",
    "sg:province":"Antwerpen",
    "wof:name":"Optiek Van Grootven",
    "wof:placetype":"venue"
},
  "geometry": {"coordinates":[4.3883538246,51.132850647],"type":"Point"}
}