{
  "type": "Feature",
  "properties": {
    "iso:country":"BE",
    "sg:address":"Posthoornstraat 16",
    "sg:city":"Beringen (koersel)",
    "sg:classifiers":[
        {
            "category":"Shopping",
            "subcategory":"Florist",
            "type":"Retail Goods"
        }
    ],
    "sg:phone":"+32 11 42 37 12",
    "sg:postcode":"3582",
    "sg:province":"Limburg",
    "wof:name":"Bloemenhal Lemmens",
    "wof:placetype":"venue"
},
  "geometry": {"coordinates":[5.2708749771,51.0595359802],"type":"Point"}
}