{
  "type": "Feature",
  "properties": {
    "iso:country":"BE",
    "sg:address":"Krewinkel 45",
    "sg:city":"Manderfeld",
    "sg:classifiers":[
        {
            "category":"Professional",
            "subcategory":"Art Services",
            "type":"Services"
        }
    ],
    "sg:phone":"+32 80 54 81 64",
    "sg:postcode":"4760",
    "sg:province":"Li\u00e8ge",
    "sg:tags":[
        "metalwork"
    ],
    "wof:name":"Werner Leuther",
    "wof:placetype":"venue"
},
  "geometry": {"coordinates":[6.3772931099,50.3314857483],"type":"Point"}
}