{
  "type": "Feature",
  "properties": {
    "iso:country":"BE",
    "sg:address":"Koning Albertstraat 58",
    "sg:city":"Hasselt",
    "sg:orig_category":"Journaux. Tabac",
    "sg:phone":"+32 11 22 27 54",
    "sg:postcode":"3500",
    "sg:province":"Limburg",
    "wof:name":"Huis Infolim",
    "wof:placetype":"venue"
},
  "geometry": {"coordinates":[5.3366408348,50.9275588989],"type":"Point"}
}