{
  "type": "Feature",
  "properties": {
    "addr:full":"Roeselaarsestraat 81 Moorslede West-Vlaanderen 8890",
    "addr:housenumber":"81",
    "addr:postcode":"8890",
    "addr:street":"Roeselaarsestraat",
    "iso:country":"BE",
    "sg:address":"Roeselaarsestraat 81",
    "sg:city":"Moorslede",
    "sg:orig_category":"Kapsalons",
    "sg:phone":"+32 51 77 86 53",
    "sg:postcode":"8890",
    "sg:province":"West-Vlaanderen",
    "wof:name":"Coiffure Chantal",
    "wof:placetype":"venue"
},
  "geometry": {"coordinates":[3.064825058,50.893863678],"type":"Point"}
}