{
  "type": "Feature",
  "properties": {
    "addr:full":"Gentstraat 14ba Sint-gillis-waas Oost-Vlaanderen 9170",
    "addr:housenumber":"14ba",
    "addr:postcode":"9170",
    "addr:street":"Gentstraat",
    "iso:country":"BE",
    "sg:address":"Gentstraat 14ba",
    "sg:city":"Sint-gillis-waas",
    "sg:orig_category":"M\u00e9decins and sp\u00e9cialistes",
    "sg:phone":"+32 3 777 20 29",
    "sg:postcode":"9170",
    "sg:province":"Oost-Vlaanderen",
    "wof:name":"A. Meul",
    "wof:placetype":"venue"
},
  "geometry": {"coordinates":[4.0984330177,51.1916046143],"type":"Point"}
}