{
  "type": "Feature",
  "properties": {
    "iso:country":"BE",
    "sg:address":"Krijgsbaan 31",
    "sg:city":"Wijnegem",
    "sg:classifiers":[
        {
            "category":"Autos & Motor Vehicles",
            "subcategory":"Automobile Sales",
            "type":"Retail Goods"
        }
    ],
    "sg:phone":"+32 3 353 45 35",
    "sg:postcode":"2110",
    "sg:province":"Antwerpen",
    "sg:tags":[
        "car",
        "used",
        "-"
    ],
    "wof:name":"Chicos Cars Bvba",
    "wof:placetype":"venue"
},
  "geometry": {"coordinates":[4.4977779388,51.2203865051],"type":"Point"}
}