{
  "type": "Feature",
  "properties": {
    "iso:country":"BE",
    "sg:address":"Lange Schipstraat 99",
    "sg:city":"Mechelen",
    "sg:orig_category":"Chaussures",
    "sg:phone":"+32 15 20 08 25",
    "sg:postcode":"2800",
    "sg:province":"Antwerpen",
    "wof:name":"Huis Buffalo",
    "wof:placetype":"venue"
},
  "geometry": {"coordinates":[4.4817180634,51.0234489441],"type":"Point"}
}