{
  "type": "Feature",
  "properties": {
    "iso:country":"BE",
    "sg:address":"Campinaweg 5",
    "sg:city":"Brecht",
    "sg:orig_category":"Travaux de pl\u00e2trage",
    "sg:phone":"+32 3 636 04 41",
    "sg:postcode":"2960",
    "sg:province":"Antwerpen",
    "wof:name":"Mondo",
    "wof:placetype":"venue"
},
  "geometry": {"coordinates":[4.5711607933,51.304397583],"type":"Point"}
}