{
  "type": "Feature",
  "properties": {
    "iso:country":"BE",
    "sg:address":"Rue Des Peupliers 2a",
    "sg:city":"Jemeppe-sur-sambre",
    "sg:orig_category":"Royal Canin. Fleurs and plantes. Plantes and fleurs Gr",
    "sg:phone":"+32 71 78 59 71",
    "sg:postcode":"5190",
    "sg:province":"Namur",
    "wof:name":"Aveve Hobby Vert",
    "wof:placetype":"venue"
},
  "geometry": {"coordinates":[4.676399231,50.4758796692],"type":"Point"}
}