{
  "type": "Feature",
  "properties": {
    "iso:country":"BE",
    "sg:address":"Oosterring 17",
    "sg:city":"Genk",
    "sg:orig_category":"Autoverhuur Taxi's",
    "sg:phone":"+32 89 62 01 62",
    "sg:postcode":"3600",
    "sg:province":"Limburg",
    "wof:name":"Autobusbedrijf Bronckaers",
    "wof:placetype":"venue"
},
  "geometry": {"coordinates":[5.5184497833,50.9423713684],"type":"Point"}
}