{
  "type": "Feature",
  "properties": {
    "addr:full":"Maastrichterstraat 25 As Limburg 3665",
    "addr:housenumber":"25",
    "addr:postcode":"3665",
    "addr:street":"Maastrichterstraat",
    "iso:country":"BE",
    "sg:address":"Maastrichterstraat 25",
    "sg:city":"As",
    "sg:orig_category":"Installatie van houten of kunststof schrijnwerk Installatie van metalen schrijnwerk",
    "sg:phone":"+32 89 65 86 87",
    "sg:postcode":"3665",
    "sg:province":"Limburg",
    "wof:name":"Immo Appeltans-vaes",
    "wof:placetype":"venue"
},
  "geometry": {"coordinates":[5.5867781639,51.002532959],"type":"Point"}
}