{
  "type": "Feature",
  "properties": {
    "addr:full":"Thier M\u00e8re Dieu 7 Verviers Li\u00e8ge 4800",
    "addr:housenumber":"7",
    "addr:postcode":"4800",
    "addr:street":"Thier Me\u0300Re Dieu",
    "iso:country":"BE",
    "sg:address":"Thier M\u00e8re Dieu 7",
    "sg:city":"Verviers",
    "sg:classifiers":[
        {
            "category":"Shopping",
            "subcategory":"Department Store",
            "type":"Retail Goods"
        }
    ],
    "sg:phone":"+32 87 33 89 18",
    "sg:postcode":"4800",
    "sg:province":"Li\u00e8ge",
    "sg:tags":[
        "surplus",
        "army"
    ],
    "wof:name":"Am\u00e9ricaine (maison)",
    "wof:placetype":"venue"
},
  "geometry": {"coordinates":[5.8680610657,50.5930023193],"type":"Point"}
}