{
  "type": "Feature",
  "properties": {
    "addr:full":"Broekveldstraat 34 Herent Vlaams-Brabant 3020",
    "addr:housenumber":"34",
    "addr:postcode":"3020",
    "addr:street":"Broekveldstraat",
    "iso:country":"BE",
    "sg:address":"Broekveldstraat 34",
    "sg:city":"Herent",
    "sg:classifiers":[
        {
            "category":"Park",
            "subcategory":"National",
            "type":"Public Place"
        }
    ],
    "sg:phone":"+32 16 29 13 87",
    "sg:postcode":"3020",
    "sg:province":"Vlaams-Brabant",
    "sg:tags":[
        "recreation"
    ],
    "wof:name":"Lunch Broekveld",
    "wof:placetype":"venue"
},
  "geometry": {"coordinates":[4.6740717888,50.9106292725],"type":"Point"}
}