{
  "type": "Feature",
  "properties": {
    "addr:full":"Vrijheidslaan 103 Sint-jans-molenbeek/molenbeek-saint-jean Bruxelles-Capitale 1080",
    "addr:housenumber":"103",
    "addr:postcode":"1080",
    "addr:street":"Vrijheidslaan",
    "iso:country":"BE",
    "sg:address":"Vrijheidslaan 103",
    "sg:city":"Sint-jans-molenbeek/molenbeek-saint-jean",
    "sg:orig_category":"Artsen and specialisten",
    "sg:phone":"+32 2 414 72 97",
    "sg:postcode":"1080",
    "sg:province":"Bruxelles-Capitale",
    "wof:name":"Ma\u00cft\u00c9 Carbety",
    "wof:placetype":"venue"
},
  "geometry": {"coordinates":[4.3216090202,50.861541748],"type":"Point"}
}