{
  "type": "Feature",
  "properties": {
    "addr:full":"Vissersstraat 56 Blankenberge West-Vlaanderen 8370",
    "addr:housenumber":"56",
    "addr:postcode":"8370",
    "addr:street":"Vissersstraat",
    "iso:country":"BE",
    "sg:address":"Vissersstraat 56",
    "sg:city":"Blankenberge",
    "sg:classifiers":[
        {
            "category":"Fast Food",
            "type":"Food & Drink"
        }
    ],
    "sg:phone":"+32 50 41 29 27",
    "sg:postcode":"8370",
    "sg:province":"West-Vlaanderen",
    "sg:tags":[
        "\u00c0",
        "restaurants",
        "emporter",
        "restaurant"
    ],
    "wof:name":"Da Sergio /giardino Di Roma",
    "wof:placetype":"venue"
},
  "geometry": {"coordinates":[3.1280550957,51.3157653809],"type":"Point"}
}