{
  "type": "Feature",
  "properties": {
    "iso:country":"BE",
    "sg:address":"Putsesteenweg 225",
    "sg:city":"Bonheiden",
    "sg:orig_category":"Epiceries",
    "sg:phone":"+32 15 55 12 72",
    "sg:postcode":"2820",
    "sg:province":"Antwerpen",
    "wof:name":"Bij Maria",
    "wof:placetype":"venue"
},
  "geometry": {"coordinates":[4.5352702141,51.0358886719],"type":"Point"}
}