{
  "type": "Feature",
  "properties": {
    "addr:full":"Brouwerijstraat 11 Aalter Oost-Vlaanderen 9880",
    "addr:housenumber":"11",
    "addr:postcode":"9880",
    "addr:street":"Brouwerijstraat",
    "iso:country":"BE",
    "sg:address":"Brouwerijstraat 11",
    "sg:city":"Aalter",
    "sg:classifiers":[
        {
            "category":"Banks & Credit Unions",
            "subcategory":"Financial Services",
            "type":"Services"
        }
    ],
    "sg:phone":"+32 9 375 03 18",
    "sg:postcode":"9880",
    "sg:province":"Oost-Vlaanderen",
    "sg:tags":[
        "loan",
        "mortgage"
    ],
    "wof:name":"Kantoor Christiaens Nv",
    "wof:placetype":"venue"
},
  "geometry": {"coordinates":[3.4470338821,51.0839500427],"type":"Point"}
}