{
  "type": "Feature",
  "properties": {
    "iso:country":"BE",
    "sg:address":"Rue Des Marcha\u00ees 4",
    "sg:city":"Walcourt (somz\u00e9e)",
    "sg:classifiers":[
        {
            "category":"Freight",
            "type":"Transportation"
        }
    ],
    "sg:phone":"+32 71 21 38 72",
    "sg:postcode":"5651",
    "sg:province":"Namur",
    "sg:tags":[
        "-",
        "transport"
    ],
    "wof:name":"Delgoffe Fr\u00e8res",
    "wof:placetype":"venue"
},
  "geometry": {"coordinates":[4.4262080193,50.2824401855],"type":"Point"}
}