{
  "type": "Feature",
  "properties": {
    "iso:country":"BE",
    "sg:address":"Rue Des Vieilles Fermes 58",
    "sg:city":"Doische (vodel\u00e9e)",
    "sg:classifiers":[
        {
            "category":"Real Estate",
            "subcategory":"Architect",
            "type":"Services"
        }
    ],
    "sg:phone":"+32 475 96 14 45",
    "sg:postcode":"5680",
    "sg:province":"Namur",
    "wof:name":"Catrin J",
    "wof:placetype":"venue"
},
  "geometry": {"coordinates":[4.7340140343,50.1704940796],"type":"Point"}
}