{
  "type": "Feature",
  "properties": {
    "addr:full":"Place Aux Foires 17 Marche 5400",
    "addr:housenumber":"17",
    "addr:postcode":"5400",
    "addr:street":"Place Aux Foires",
    "iso:country":"BE",
    "sg:address":"Place Aux Foires 17",
    "sg:city":"Marche",
    "sg:classifiers":[
        {
            "category":"Banks & Credit Unions",
            "subcategory":"Bank",
            "type":"Services"
        }
    ],
    "sg:phone":"+32 84 31 24 44",
    "sg:postcode":"5400",
    "wof:name":"Aslk-cger Bank",
    "wof:placetype":"venue"
},
  "geometry": {"coordinates":[7.6613459587,45.6205673218],"type":"Point"}
}