{
  "type": "Feature",
  "properties": {
    "addr:full":"Drie Eikenstraat 113 Edegem Antwerpen 2650",
    "addr:housenumber":"113",
    "addr:postcode":"2650",
    "addr:street":"Drie Eikenstraat",
    "iso:country":"BE",
    "sg:address":"Drie Eikenstraat 113",
    "sg:city":"Edegem",
    "sg:orig_category":"Woningbouw",
    "sg:phone":"+32 3 457 09 44",
    "sg:postcode":"2650",
    "sg:province":"Antwerpen",
    "wof:name":"Laureyn E.",
    "wof:placetype":"venue"
},
  "geometry": {"coordinates":[4.4379320145,51.1560897827],"type":"Point"}
}