{
  "type": "Feature",
  "properties": {
    "addr:full":"Rue De Bruxelles 38 Edingen/enghien Hainaut 7850",
    "addr:housenumber":"38",
    "addr:postcode":"7850",
    "addr:street":"Rue De Bruxelles",
    "iso:country":"BE",
    "sg:address":"Rue De Bruxelles 38",
    "sg:city":"Edingen/enghien",
    "sg:orig_category":"Banques and organismes de cr\u00e9dit",
    "sg:phone":"+32 2 395 53 68",
    "sg:postcode":"7850",
    "sg:province":"Hainaut",
    "wof:name":"Kbc",
    "wof:placetype":"venue"
},
  "geometry": {"coordinates":[4.0409297943,50.6945152283],"type":"Point"}
}