{
  "type": "Feature",
  "properties": {
    "addr:full":"Processiestraat 12 Meerhout Antwerpen 2450",
    "addr:housenumber":"12",
    "addr:postcode":"2450",
    "addr:street":"Processiestraat",
    "iso:country":"BE",
    "sg:address":"Processiestraat 12",
    "sg:city":"Meerhout",
    "sg:classifiers":[
        {
            "category":"Taxi",
            "type":"Transportation"
        }
    ],
    "sg:phone":"+32 14 30 15 25",
    "sg:postcode":"2450",
    "sg:province":"Antwerpen",
    "sg:tags":[
        "delivery",
        "van",
        "-"
    ],
    "wof:name":"Meerhout Taxi Service Cvba",
    "wof:placetype":"venue"
},
  "geometry": {"coordinates":[5.073472023,51.132396698],"type":"Point"}
}