{
  "type": "Feature",
  "properties": {
    "iso:country":"BE",
    "sg:address":"Oude Dendermondsebaan 82",
    "sg:city":"Asse",
    "sg:orig_category":"Producteurs de l\u00e9gumes. Fruits and l\u00e9gumes Gr",
    "sg:phone":"+32 2 452 70 30",
    "sg:postcode":"1730",
    "sg:province":"Vlaams-Brabant",
    "wof:name":"Marcel Moyson",
    "wof:placetype":"venue"
},
  "geometry": {"coordinates":[4.1853160858,50.92578125],"type":"Point"}
}