{
  "type": "Feature",
  "properties": {
    "addr:full":"Kolonel Bourgstraat 128b4 Evere Bruxelles-Capitale 1140",
    "addr:housenumber":"128b4",
    "addr:postcode":"1140",
    "addr:street":"Kolonel Bourgstraat",
    "iso:country":"BE",
    "sg:address":"Kolonel Bourgstraat 128b4",
    "sg:city":"Evere",
    "sg:orig_category":"Luchtvaart volgens dienstregeling",
    "sg:phone":"+32 2 753 22 22",
    "sg:postcode":"1140",
    "sg:province":"Bruxelles-Capitale",
    "wof:name":"Delta Air Lines",
    "wof:placetype":"venue"
},
  "geometry": {"coordinates":[4.416205883,50.8553314209],"type":"Point"}
}