{
  "type": "Feature",
  "properties": {
    "iso:country":"BE",
    "sg:address":"Rue Bossontienne 16",
    "sg:city":"Profondeville",
    "sg:orig_category":"M\u00e9decins and sp\u00e9cialistes",
    "sg:phone":"+32 81 43 34 58",
    "sg:postcode":"5170",
    "sg:province":"Namur",
    "wof:name":"Gustave Boeur",
    "wof:placetype":"venue"
},
  "geometry": {"coordinates":[4.7837481499,50.3702278137],"type":"Point"}
}