{
  "type": "Feature",
  "properties": {
    "addr:full":"Kerkstraat 21 Herk-de-stad Limburg 3540",
    "addr:housenumber":"21",
    "addr:postcode":"3540",
    "addr:street":"Kerkstraat",
    "iso:country":"BE",
    "sg:address":"Kerkstraat 21",
    "sg:city":"Herk-de-stad",
    "sg:orig_category":"Artsen and specialisten",
    "sg:phone":"+32 13 55 10 77",
    "sg:postcode":"3540",
    "sg:province":"Limburg",
    "wof:name":"Nestor Dufrane",
    "wof:placetype":"venue"
},
  "geometry": {"coordinates":[5.1790690422,50.9578933716],"type":"Point"}
}