{
  "type": "Feature",
  "properties": {
    "iso:country":"BE",
    "sg:address":"Rue De Fer 54",
    "sg:city":"Namen (groot)",
    "sg:orig_category":"Cr\u00e9dit \u00e0 la consommation",
    "sg:phone":"+32 81 26 18 50",
    "sg:postcode":"5000",
    "sg:province":"Namur",
    "wof:name":"Deutsche Bank",
    "wof:placetype":"venue"
},
  "geometry": {"coordinates":[4.8656139374,50.4664802551],"type":"Point"}
}