{
  "type": "Feature",
  "properties": {
    "iso:country":"BE",
    "sg:address":"Rue Carli 13",
    "sg:city":"Bruxelles",
    "sg:classifiers":[
        {
            "category":"Manufacturing",
            "subcategory":"Tools & Machinery",
            "type":"Manufacturing & Wholesale Goods"
        }
    ],
    "sg:phone":"+32 2 248 06 00",
    "sg:postcode":"1140",
    "sg:province":"Bruxelles-Capitale",
    "sg:tags":[
        "equipment",
        "measurement",
        "-",
        "precision",
        "instrument"
    ],
    "wof:name":"Endress + Hauser Sa",
    "wof:placetype":"venue"
},
  "geometry": {"coordinates":[4.3910250664,50.8801307678],"type":"Point"}
}