{
  "type": "Feature",
  "properties": {
    "addr:full":"Gitsbergstraat 17 Hooglede West-Vlaanderen 8830",
    "addr:housenumber":"17",
    "addr:postcode":"8830",
    "addr:street":"Gitsbergstraat",
    "iso:country":"BE",
    "sg:address":"Gitsbergstraat 17",
    "sg:city":"Hooglede",
    "sg:orig_category":"Rusthuizen and serviceflats",
    "sg:phone":"+32 51 20 20 50",
    "sg:postcode":"8830",
    "sg:province":"West-Vlaanderen",
    "wof:name":"Zusters H. Vincentius",
    "wof:placetype":"venue"
},
  "geometry": {"coordinates":[3.0965850353,50.9954452515],"type":"Point"}
}