{
  "type": "Feature",
  "properties": {
    "iso:country":"BE",
    "sg:address":"Tervuursesteenweg 22",
    "sg:city":"Zemst",
    "sg:orig_category":"Herstelling and restauratie van meubelen",
    "sg:phone":"+32 15 42 24 65",
    "sg:postcode":"1981",
    "sg:province":"Vlaams-Brabant",
    "wof:name":"De Naakte Kast",
    "wof:placetype":"venue"
},
  "geometry": {"coordinates":[4.4885430336,50.9971733093],"type":"Point"}
}