{
  "type": "Feature",
  "properties": {
    "iso:country":"BE",
    "sg:address":"Chauss\u00e9e De Fleurus 111a",
    "sg:city":"Charleroi (gosselies)",
    "sg:classifiers":[
        {
            "category":"Landmark",
            "subcategory":"Memorial",
            "type":"Public Place"
        }
    ],
    "sg:phone":"+32 71 34 10 63",
    "sg:postcode":"6041",
    "sg:province":"Hainaut",
    "sg:tags":[
        "-",
        "monument"
    ],
    "wof:name":"Guns Jean Ets",
    "wof:placetype":"venue"
},
  "geometry": {"coordinates":[4.4314317703,50.4685935974],"type":"Point"}
}