{
  "type": "Feature",
  "properties": {
    "iso:country":"BE",
    "sg:address":"Koning Albertlaan 224",
    "sg:city":"Gent",
    "sg:classifiers":[
        {
            "category":"Communications",
            "subcategory":"Film & Video Production",
            "type":"Services"
        }
    ],
    "sg:phone":"+32 9 220 76 32",
    "sg:postcode":"9000",
    "sg:province":"Oost-Vlaanderen",
    "sg:tags":[
        "sound",
        "recording",
        "studio"
    ],
    "wof:name":"Verbeiren W",
    "wof:placetype":"venue"
},
  "geometry": {"coordinates":[3.7104101181,51.0388908386],"type":"Point"}
}