{
  "type": "Feature",
  "properties": {
    "iso:country":"BE",
    "sg:address":"Andries Pevernagestraat 28",
    "sg:city":"Harelbeke",
    "sg:orig_category":"Plaatsen van vloer- and muurbekleding",
    "sg:phone":"+32 56 70 62 44",
    "sg:postcode":"8530",
    "sg:province":"West-Vlaanderen",
    "wof:name":"Kets Eddy",
    "wof:placetype":"venue"
},
  "geometry": {"coordinates":[3.3082549572,50.8529129028],"type":"Point"}
}