{
  "type": "Feature",
  "properties": {
    "addr:full":"Avenue Du Roi Albert 58b1 Sint-agatha-berchem/berchem-sainte-agathe Bruxelles-Capitale 1082",
    "addr:housenumber":"58b1",
    "addr:postcode":"1082",
    "addr:street":"Avenue Du Roi Albert;/",
    "iso:country":"BE",
    "sg:address":"Avenue Du Roi Albert 58b1",
    "sg:city":"Sint-agatha-berchem/berchem-sainte-agathe",
    "sg:orig_category":"M\u00e9decins and sp\u00e9cialistes",
    "sg:phone":"+32 2 465 52 96",
    "sg:postcode":"1082",
    "sg:province":"Bruxelles-Capitale",
    "wof:name":"Hans Roth",
    "wof:placetype":"venue"
},
  "geometry": {"coordinates":[4.2932710648,50.865020752],"type":"Point"}
}