{
  "type": "Feature",
  "properties": {
    "addr:full":"Beversesteenweg 523 Roeselare West-Vlaanderen 8800",
    "addr:housenumber":"523",
    "addr:postcode":"8800",
    "addr:street":"Beversesteenweg",
    "iso:country":"BE",
    "sg:address":"Beversesteenweg 523",
    "sg:city":"Roeselare",
    "sg:classifiers":[
        {
            "category":"Wholesale",
            "subcategory":"Poultry",
            "type":"Manufacturing & Wholesale Goods"
        }
    ],
    "sg:phone":"+32 51 20 23 03",
    "sg:postcode":"8800",
    "sg:province":"West-Vlaanderen",
    "sg:tags":[
        "whol",
        "-",
        "egg"
    ],
    "wof:name":"Cnudde S",
    "wof:placetype":"venue"
},
  "geometry": {"coordinates":[3.1597049236,50.9739112854],"type":"Point"}
}