{
  "type": "Feature",
  "properties": {
    "iso:country":"BE",
    "sg:address":"Overhemsestraat 33",
    "sg:city":"Heers",
    "sg:orig_category":"Rundveehouders",
    "sg:phone":"+32 11 48 59 05",
    "sg:postcode":"3870",
    "sg:province":"Limburg",
    "wof:name":"Joseph Rossillion",
    "wof:placetype":"venue"
},
  "geometry": {"coordinates":[5.3346438408,50.7609786987],"type":"Point"}
}