{
  "type": "Feature",
  "properties": {
    "addr:full":"Luikersteenweg 197 Hasselt Limburg 3500",
    "addr:housenumber":"197",
    "addr:postcode":"3500",
    "addr:street":"Luikersteenweg",
    "iso:country":"BE",
    "sg:address":"Luikersteenweg 197",
    "sg:city":"Hasselt",
    "sg:classifiers":[
        {
            "category":"Insurance",
            "subcategory":"Insurance Agent",
            "type":"Services"
        }
    ],
    "sg:phone":"+32 11 28 09 60",
    "sg:postcode":"3500",
    "sg:province":"Limburg",
    "sg:tags":[
        "verzekeringsmakelaars",
        "expert"
    ],
    "wof:name":"A.z.v.",
    "wof:placetype":"venue"
},
  "geometry": {"coordinates":[5.3466200829,50.9167633057],"type":"Point"}
}