{
  "type": "Feature",
  "properties": {
    "iso:country":"BE",
    "sg:address":"Place Mac-auliffe 22",
    "sg:city":"Bastogne",
    "sg:orig_category":"Slagers",
    "sg:phone":"+32 61 21 10 67",
    "sg:postcode":"6600",
    "sg:province":"Luxembourg",
    "wof:name":"Boucherie Huskin",
    "wof:placetype":"venue"
},
  "geometry": {"coordinates":[5.7144007683,50.0013427734],"type":"Point"}
}