{
  "type": "Feature",
  "properties": {
    "iso:country":"BE",
    "sg:address":"R. L\u00b4h\u00d4tel Des Monnaies 66",
    "sg:city":"Sint-gillis/saint-gilles",
    "sg:classifiers":[
        {
            "category":"Social Services",
            "subcategory":"Retirement Home",
            "type":"Services"
        }
    ],
    "sg:phone":"+32 2 537 60 14",
    "sg:postcode":"1060",
    "sg:province":"Bruxelles-Capitale",
    "sg:tags":[
        "compagnies",
        "vie",
        "assurance",
        "habitation"
    ],
    "wof:name":"Hamburg Mannheimer/hamburg-mannheimer",
    "wof:placetype":"venue"
},
  "geometry": {"coordinates":[4.3486289978,50.8309822083],"type":"Point"}
}