{
  "type": "Feature",
  "properties": {
    "addr:full":"Moestoemaatheide 4 Westerlo (tongerlo) Antwerpen 2260",
    "addr:housenumber":"4",
    "addr:postcode":"2260",
    "addr:street":"Moestoemaatheide",
    "iso:country":"BE",
    "sg:address":"Moestoemaatheide 4",
    "sg:city":"Westerlo (tongerlo)",
    "sg:classifiers":[
        {
            "category":"Farming",
            "subcategory":"Farm & Veterinary Services",
            "type":"Manufacturing & Wholesale Goods"
        }
    ],
    "sg:phone":"+32 14 58 24 09",
    "sg:postcode":"2260",
    "sg:province":"Antwerpen",
    "sg:tags":[
        "agricultural",
        "contractor"
    ],
    "wof:name":"Clissen-peetermans Bvba",
    "wof:placetype":"venue"
},
  "geometry": {"coordinates":[4.9389681816,51.1209831238],"type":"Point"}
}