{
  "type": "Feature",
  "properties": {
    "iso:country":"BE",
    "sg:address":"Rue Reine Astrid 86",
    "sg:city":"Engis",
    "sg:orig_category":"Herenkledingzaken",
    "sg:phone":"+32 4 275 17 63",
    "sg:postcode":"4480",
    "sg:province":"Li\u00e8ge",
    "wof:name":"Cricket & Co",
    "wof:placetype":"venue"
},
  "geometry": {"coordinates":[5.4017457962,50.5861968994],"type":"Point"}
}