{
  "type": "Feature",
  "properties": {
    "iso:country":"BE",
    "sg:address":"Rue De Mi\u00c9cret 58",
    "sg:city":"Hamois",
    "sg:orig_category":"Artistes ind\u00e9pendants",
    "sg:phone":"+32 83 61 17 49",
    "sg:postcode":"5360",
    "sg:province":"Namur",
    "wof:name":"Albert De Villeroux",
    "wof:placetype":"venue"
},
  "geometry": {"coordinates":[5.1735057831,50.3429145813],"type":"Point"}
}