{
  "type": "Feature",
  "properties": {
    "addr:full":"Clos Chapelle Aux Champs 41 Box 3960 Bruxelles (woluwe-saint-lambert) Bruxelles-Capitale 1200",
    "addr:housenumber":"41 box",
    "addr:postcode":"3960;1200",
    "addr:street":"Clos Chapelle Aux Champs",
    "iso:country":"BE",
    "sg:address":"Clos Chapelle Aux Champs 41 Box 3960",
    "sg:city":"Bruxelles (woluwe-saint-lambert)",
    "sg:classifiers":[
        {
            "category":"Education",
            "subcategory":"University",
            "type":"Public Place"
        }
    ],
    "sg:phone":"+32 2 764 39 60",
    "sg:postcode":"1200",
    "sg:province":"Bruxelles-Capitale",
    "sg:tags":[
        "higher"
    ],
    "wof:name":"Inst. Sup\u00e9rieur D'enseignement Infirmier (i.s.e.i.)",
    "wof:placetype":"venue"
},
  "geometry": {"coordinates":[4.4501447678,50.8488006592],"type":"Point"}
}