{
  "type": "Feature",
  "properties": {
    "addr:full":"Strandstraat 1b16 Knokke-heist West-Vlaanderen 8300",
    "addr:housenumber":"1b16",
    "addr:postcode":"8300",
    "addr:street":"Strandstraat",
    "iso:country":"BE",
    "sg:address":"Strandstraat 1b16",
    "sg:city":"Knokke-heist",
    "sg:orig_category":"Loodgieterij, verwarming and sanitaire installaties",
    "sg:phone":"+32 50 60 86 10",
    "sg:postcode":"8300",
    "sg:province":"West-Vlaanderen",
    "wof:name":"Emile Swaelens",
    "wof:placetype":"venue"
},
  "geometry": {"coordinates":[3.287694931,51.3467254639],"type":"Point"}
}