{
  "type": "Feature",
  "properties": {
    "addr:full":"Avenue Maistriaux 84 Mons Hainaut 7000",
    "addr:housenumber":"84",
    "addr:postcode":"7000",
    "addr:street":"Avenue Maistriaux;Hainaut",
    "iso:country":"BE",
    "sg:address":"Avenue Maistriaux 84",
    "sg:city":"Mons",
    "sg:orig_category":"Schoonmaakbedrijven and ongediertebestrijding",
    "sg:phone":"+32 477 32 62 43",
    "sg:postcode":"7000",
    "sg:province":"Hainaut",
    "wof:name":"Aire Service",
    "wof:placetype":"venue"
},
  "geometry": {"coordinates":[3.9582479,50.4642982483],"type":"Point"}
}