{
  "type": "Feature",
  "properties": {
    "addr:full":"Rue De La Pens\u00e9e 43 Charleroi (montignies-sur-sambre) Hainaut 6061",
    "addr:housenumber":"43",
    "addr:postcode":"6061",
    "addr:street":"Rue De La Pense\u0301E",
    "iso:country":"BE",
    "sg:address":"Rue De La Pens\u00e9e 43",
    "sg:city":"Charleroi (montignies-sur-sambre)",
    "sg:classifiers":[
        {
            "category":"Professional",
            "subcategory":"Art Services",
            "type":"Services"
        }
    ],
    "sg:phone":"+32 478 25 62 33",
    "sg:postcode":"6061",
    "sg:province":"Hainaut",
    "sg:tags":[
        "photography",
        "reporting",
        "-"
    ],
    "wof:name":"Haute Definition",
    "wof:placetype":"venue"
},
  "geometry": {"coordinates":[4.4704089165,50.4051589966],"type":"Point"}
}