{
  "type": "Feature",
  "properties": {
    "addr:full":"Winston Churchilllaan 3 Ukkel/uccle Bruxelles-Capitale 1180",
    "addr:housenumber":"3",
    "addr:postcode":"1180",
    "addr:street":"Winston Churchilllaan;/",
    "iso:country":"BE",
    "sg:address":"Winston Churchilllaan 3",
    "sg:city":"Ukkel/uccle",
    "sg:orig_category":"Boekhouders",
    "sg:phone":"+32 2 344 39 36",
    "sg:postcode":"1180",
    "sg:province":"Bruxelles-Capitale",
    "wof:name":"Philippe Sepulchre",
    "wof:placetype":"venue"
},
  "geometry": {"coordinates":[4.3480610847,50.8131484985],"type":"Point"}
}