{
  "type": "Feature",
  "properties": {
    "iso:country":"BE",
    "sg:address":"Zultseweg 163",
    "sg:city":"Waregem",
    "sg:classifiers":[
        {
            "category":"Banks & Credit Unions",
            "subcategory":"Financial Services",
            "type":"Services"
        }
    ],
    "sg:phone":"+32 56 60 83 40",
    "sg:postcode":"8790",
    "sg:province":"West-Vlaanderen",
    "sg:tags":[
        "debt",
        "recovery"
    ],
    "wof:name":"Waelkens-barbary",
    "wof:placetype":"venue"
},
  "geometry": {"coordinates":[3.4434080124,50.899307251],"type":"Point"}
}