{
  "type": "Feature",
  "properties": {
    "iso:country":"BE",
    "sg:address":"Rue Eug\u00c8ne Defraire 50",
    "sg:city":"Viroinval",
    "sg:orig_category":"Boekhandels Krantenwinkels",
    "sg:phone":"+32 60 39 91 82",
    "sg:postcode":"5670",
    "sg:province":"Namur",
    "wof:name":"Desthieu",
    "wof:placetype":"venue"
},
  "geometry": {"coordinates":[4.6678128242,50.092880249],"type":"Point"}
}