{
  "type": "Feature",
  "properties": {
    "addr:full":"Kortrijksesteenweg 185 Gent Oost-Vlaanderen 9000",
    "addr:housenumber":"185",
    "addr:postcode":"9000",
    "addr:street":"Kortrijksesteenweg;Oost-Vlaanderen",
    "iso:country":"BE",
    "sg:address":"Kortrijksesteenweg 185",
    "sg:city":"Gent",
    "sg:classifiers":[
        {
            "category":"Health Services",
            "subcategory":"Hospital",
            "type":"Services"
        }
    ],
    "sg:phone":"+32 9 245 38 98",
    "sg:postcode":"9000",
    "sg:province":"Oost-Vlaanderen",
    "wof:name":"De Kiem Therapeutische Gemeenschap",
    "wof:placetype":"venue"
},
  "geometry": {"coordinates":[3.7170169353,51.0397605896],"type":"Point"}
}