{
  "type": "Feature",
  "properties": {
    "addr:full":"Rue Du Poirier 116 Charleroi Hainaut 6061",
    "addr:housenumber":"116",
    "addr:postcode":"6061",
    "addr:street":"Rue Du Poirier;Hainaut",
    "iso:country":"BE",
    "sg:address":"Rue Du Poirier 116",
    "sg:city":"Charleroi",
    "sg:orig_category":"M\u00e9decins and sp\u00e9cialistes",
    "sg:phone":"+32 71 32 93 10",
    "sg:postcode":"6061",
    "sg:province":"Hainaut",
    "wof:name":"Marie-louise Vancopenolle",
    "wof:placetype":"venue"
},
  "geometry": {"coordinates":[4.4658298492,50.4063110352],"type":"Point"}
}