{
  "type": "Feature",
  "properties": {
    "addr:full":"Rue De L'enseignement 102 Seraing Li\u00e8ge 4102",
    "addr:housenumber":"102",
    "addr:postcode":"4102",
    "addr:street":"Rue De L'Enseignement",
    "iso:country":"BE",
    "sg:address":"Rue De L'enseignement 102",
    "sg:city":"Seraing",
    "sg:orig_category":"Enseignement maternel and primaire",
    "sg:phone":"+32 4 337 65 03",
    "sg:postcode":"4102",
    "sg:province":"Li\u00e8ge",
    "wof:name":"Ecole Fond. Communale",
    "wof:placetype":"venue"
},
  "geometry": {"coordinates":[5.5385351181,50.602394104],"type":"Point"}
}