{
  "type": "Feature",
  "properties": {
    "addr:full":"Breugelstraat 9 Schelle Antwerpen 2627",
    "addr:housenumber":"9",
    "addr:postcode":"2627",
    "addr:street":"Breugelstraat",
    "iso:country":"BE",
    "sg:address":"Breugelstraat 9",
    "sg:city":"Schelle",
    "sg:classifiers":[
        {
            "category":"Military Area",
            "subcategory":"Air Force Base",
            "type":"Public Place"
        }
    ],
    "sg:phone":"+32 3 877 29 86",
    "sg:postcode":"2627",
    "sg:province":"Antwerpen",
    "sg:tags":[
        "commerce",
        "gr",
        "equipement",
        "de",
        "\u00e9v\u00e9nements",
        "pour",
        "diver",
        "mat\u00e9riel",
        "location",
        "banquet"
    ],
    "wof:name":"Spring Is In The Air",
    "wof:placetype":"venue"
},
  "geometry": {"coordinates":[4.3437538147,51.1287612915],"type":"Point"}
}