{
  "type": "Feature",
  "properties": {
    "addr:full":"Warmoesstraat 9 Diksmuide West-Vlaanderen 8600",
    "addr:housenumber":"9",
    "addr:postcode":"8600",
    "addr:street":"Warmoesstraat",
    "iso:country":"BE",
    "sg:address":"Warmoesstraat 9",
    "sg:city":"Diksmuide",
    "sg:orig_category":"Eleveurs de bovins. Eleveurs and marchands de porcs",
    "sg:phone":"+32 51 50 00 47",
    "sg:postcode":"8600",
    "sg:province":"West-Vlaanderen",
    "wof:name":"Danny Bonte",
    "wof:placetype":"venue"
},
  "geometry": {"coordinates":[2.8657801151,51.0334663391],"type":"Point"}
}