{
  "type": "Feature",
  "properties": {
    "iso:country":"BE",
    "sg:address":"Meensesteenweg 434",
    "sg:city":"Roeselare",
    "sg:orig_category":"V\u00e9hicules automobiles",
    "sg:phone":"+32 51 22 92 65",
    "sg:postcode":"8800",
    "sg:province":"West-Vlaanderen",
    "wof:name":"Vangheluwe Bart",
    "wof:placetype":"venue"
},
  "geometry": {"coordinates":[3.1166949272,50.9197044373],"type":"Point"}
}