{
  "type": "Feature",
  "properties": {
    "addr:full":"Avenue De La Lib\u00e9ration 4 Aywaille Li\u00e8ge 4920",
    "addr:housenumber":"4",
    "addr:postcode":"4920",
    "addr:street":"Avenue De La Libe\u0301Ration",
    "iso:country":"BE",
    "sg:address":"Avenue De La Lib\u00e9ration 4",
    "sg:city":"Aywaille",
    "sg:classifiers":[
        {
            "category":"Travel",
            "subcategory":"Hotels & Motels",
            "type":"Entertainment"
        }
    ],
    "sg:phone":"+32 4 384 42 36",
    "sg:postcode":"4920",
    "sg:province":"Li\u00e8ge",
    "wof:name":"Villa Des Roses Sa",
    "wof:placetype":"venue"
},
  "geometry": {"coordinates":[5.6746940613,50.4767608643],"type":"Point"}
}