{
  "type": "Feature",
  "properties": {
    "addr:full":"Dr. Frans Hemeryckxlaan 5 Edegem Antwerpen 2650",
    "addr:housenumber":"5",
    "addr:postcode":"2650",
    "addr:street":"Hemeryckxlaan",
    "iso:country":"BE",
    "sg:address":"Dr. Frans Hemeryckxlaan 5",
    "sg:city":"Edegem",
    "sg:orig_category":"Peinture. Rev\u00eatements pour sols and murs. Eclairage et \u00e9quipements du foyer",
    "sg:phone":"+32 3 457 33 44",
    "sg:postcode":"2650",
    "sg:province":"Antwerpen",
    "wof:name":"Joseph Moons",
    "wof:placetype":"venue"
},
  "geometry": {"coordinates":[4.4527821541,51.1507072449],"type":"Point"}
}