{
  "type": "Feature",
  "properties": {
    "iso:country":"BE",
    "sg:address":"Amerikalei 150",
    "sg:city":"Antwerpen",
    "sg:classifiers":[
        {
            "category":"Professional",
            "subcategory":"Accounting & Tax Preparation",
            "type":"Services"
        }
    ],
    "sg:phone":"+32 3 248 06 11",
    "sg:postcode":"2000",
    "sg:province":"Antwerpen",
    "sg:tags":[
        "accountant"
    ],
    "wof:name":"De Vries W",
    "wof:placetype":"venue"
},
  "geometry": {"coordinates":[4.3936648369,51.2063980103],"type":"Point"}
}