{
  "type": "Feature",
  "properties": {
    "iso:country":"BE",
    "sg:address":"Sint-jorisstraat 12",
    "sg:city":"Lommel",
    "sg:orig_category":"Loodgieterij, verwarming and sanitaire installaties",
    "sg:phone":"+32 11 66 13 82",
    "sg:postcode":"3920",
    "sg:province":"Limburg",
    "wof:name":"Herman Geboers",
    "wof:placetype":"venue"
},
  "geometry": {"coordinates":[5.3701891899,51.2541351318],"type":"Point"}
}