{
  "type": "Feature",
  "properties": {
    "iso:country":"BE",
    "sg:address":"Rue De Bastogne 23",
    "sg:city":"Sainte-ode (lavacherie)",
    "sg:classifiers":[
        {
            "category":"Bakery",
            "type":"Food & Drink"
        }
    ],
    "sg:phone":"+32 61 68 82 02",
    "sg:postcode":"6681",
    "sg:province":"Luxembourg",
    "sg:tags":[
        "confectioner",
        "baker"
    ],
    "wof:name":"Sauvage-goosse",
    "wof:placetype":"venue"
},
  "geometry": {"coordinates":[5.5168437958,50.0540924072],"type":"Point"}
}