{
  "type": "Feature",
  "properties": {
    "iso:country":"BE",
    "sg:address":"Rue Des Poulets 8",
    "sg:city":"Bruxelles (anderlecht)",
    "sg:classifiers":[
        {
            "category":"Food & Beverages",
            "subcategory":"Meat & Fish",
            "type":"Retail Goods"
        }
    ],
    "sg:phone":"+32 2 567 20 36",
    "sg:postcode":"1070",
    "sg:province":"Bruxelles-Capitale",
    "sg:tags":[
        "-",
        "livestock"
    ],
    "wof:name":"Drafhandel Decuyper Nv",
    "wof:placetype":"venue"
},
  "geometry": {"coordinates":[4.2694702148,50.8243141174],"type":"Point"}
}