{
  "type": "Feature",
  "properties": {
    "addr:full":"Broekstraat 38 Sint-martens-latem Oost-Vlaanderen 9831",
    "addr:housenumber":"38",
    "addr:postcode":"9831",
    "addr:street":"Broekstraat",
    "iso:country":"BE",
    "sg:address":"Broekstraat 38",
    "sg:city":"Sint-martens-latem",
    "sg:orig_category":"Artistes ind\u00e9pendants",
    "sg:phone":"+32 9 282 67 44",
    "sg:postcode":"9831",
    "sg:province":"Oost-Vlaanderen",
    "wof:name":"Bassez",
    "wof:placetype":"venue"
},
  "geometry": {"coordinates":[3.6178460121,50.9964675903],"type":"Point"}
}