{
  "type": "Feature",
  "properties": {
    "addr:full":"Rue Des Ecoliers 79-81 Seraing Li\u00e8ge 4100",
    "addr:postcode":"79-81;4100",
    "addr:street":"Rue Des Ecoliers",
    "iso:country":"BE",
    "sg:address":"Rue Des Ecoliers 79-81",
    "sg:city":"Seraing",
    "sg:classifiers":[
        {
            "category":"Insurance",
            "subcategory":"Insurance Agent",
            "type":"Services"
        }
    ],
    "sg:phone":"+32 4 338 88 88",
    "sg:postcode":"4100",
    "sg:province":"Li\u00e8ge",
    "sg:tags":[
        "verzekeringsmakelaars",
        "expert"
    ],
    "wof:name":"Direct Line Assistance & Company",
    "wof:placetype":"venue"
},
  "geometry": {"coordinates":[5.5084199905,50.5970039368],"type":"Point"}
}