{
  "type": "Feature",
  "properties": {
    "addr:full":"Onze-lieve-vrouwstraat 36 Hoeselt Limburg 3730",
    "addr:housenumber":"36",
    "addr:postcode":"3730",
    "addr:street":"Onze-Lieve-Vrouwstraat",
    "iso:country":"BE",
    "sg:address":"Onze-lieve-vrouwstraat 36",
    "sg:city":"Hoeselt",
    "sg:classifiers":[
        {
            "category":"Building & Trades",
            "subcategory":"Landscaping Services",
            "type":"Services"
        }
    ],
    "sg:phone":"+32 89 41 33 55",
    "sg:postcode":"3730",
    "sg:province":"Limburg",
    "sg:tags":[
        "gardening",
        "garden",
        "maintenance"
    ],
    "wof:name":"Rampen J",
    "wof:placetype":"venue"
},
  "geometry": {"coordinates":[5.492372036,50.8454551697],"type":"Point"}
}