{
  "type": "Feature",
  "properties": {
    "iso:country":"BE",
    "sg:address":"Citadellaan 30",
    "sg:city":"Gent-centrum",
    "sg:orig_category":"Balie van Gent. Avocats and conseillers juridiques",
    "sg:phone":"+32 9 222 51 95",
    "sg:postcode":"9000",
    "sg:province":"Oost-Vlaanderen",
    "wof:name":"Duquet Frank",
    "wof:placetype":"venue"
},
  "geometry": {"coordinates":[3.7273240089,51.0383529663],"type":"Point"}
}