{
  "type": "Feature",
  "properties": {
    "iso:country":"BE",
    "sg:address":"Rue Bonne-femme 14",
    "sg:city":"Grivegnee",
    "sg:classifiers":[
        {
            "category":"Real Estate",
            "subcategory":"Real Estate Services",
            "type":"Services"
        }
    ],
    "sg:phone":"+32 4 344 47 44",
    "sg:postcode":"4030",
    "sg:province":"Li\u00e8ge",
    "wof:name":"B.a.i.",
    "wof:placetype":"venue"
},
  "geometry": {"coordinates":[5.5882668495,50.6281547546],"type":"Point"}
}