{
  "type": "Feature",
  "properties": {
    "addr:full":"Boulevard De La Constitution 59 Li\u00e8ge 1 (li\u00e8ge 2) Li\u00e8ge 4020",
    "addr:housenumber":"59;1;2",
    "addr:postcode":"4020",
    "addr:street":"Boulevard De La Constitution",
    "iso:country":"BE",
    "sg:address":"Boulevard De La Constitution 59",
    "sg:city":"Li\u00e8ge 1 (li\u00e8ge 2)",
    "sg:classifiers":[
        {
            "category":"Health Services",
            "subcategory":"Nursing And Care Facility",
            "type":"Services"
        }
    ],
    "sg:phone":"+32 4 341 14 34",
    "sg:postcode":"4020",
    "sg:province":"Li\u00e8ge",
    "sg:tags":[
        "home",
        "rest"
    ],
    "wof:name":"Baviere (residence)",
    "wof:placetype":"venue"
},
  "geometry": {"coordinates":[5.5877861977,50.6442146301],"type":"Point"}
}