{
  "type": "Feature",
  "properties": {
    "iso:country":"BE",
    "sg:address":"Torhoutsesteenweg 220",
    "sg:city":"Oostende",
    "sg:classifiers":[
        {
            "category":"Food & Beverages",
            "subcategory":"Fruits & Vegetables",
            "type":"Retail Goods"
        }
    ],
    "sg:phone":"+32 59 50 94 32",
    "sg:postcode":"8400",
    "sg:province":"West-Vlaanderen",
    "sg:tags":[
        "-"
    ],
    "wof:name":"Frederic & Rebecca",
    "wof:placetype":"venue"
},
  "geometry": {"coordinates":[2.9076759815,51.2181816101],"type":"Point"}
}