{
  "type": "Feature",
  "properties": {
    "iso:country":"BE",
    "sg:address":"Bijlokevest 157",
    "sg:city":"Gent",
    "sg:orig_category":"Studios photographiques",
    "sg:phone":"+32 9 225 44 97",
    "sg:postcode":"9000",
    "sg:province":"Oost-Vlaanderen",
    "wof:name":"Lieven Vandenabeele",
    "wof:placetype":"venue"
},
  "geometry": {"coordinates":[3.7100980282,51.0482521057],"type":"Point"}
}