{
  "type": "Feature",
  "properties": {
    "addr:full":"Polderstraat 7 Koksijde (oostduinkerke) West-Vlaanderen 8670",
    "addr:housenumber":"7",
    "addr:postcode":"8670",
    "addr:street":"Polderstraat",
    "iso:country":"BE",
    "sg:address":"Polderstraat 7",
    "sg:city":"Koksijde (oostduinkerke)",
    "sg:classifiers":[
        {
            "category":"Home & Garden",
            "subcategory":"Carpets & Floor Coverings",
            "type":"Retail Goods"
        }
    ],
    "sg:phone":"+32 58 51 58 75",
    "sg:postcode":"8670",
    "sg:province":"West-Vlaanderen",
    "sg:tags":[
        "tile"
    ],
    "wof:name":"Tegelhuis Vandenabeele-sierschouwen",
    "wof:placetype":"venue"
},
  "geometry": {"coordinates":[2.684887886,51.1181945801],"type":"Point"}
}