{
  "type": "Feature",
  "properties": {
    "addr:full":"Burg. Heymansplein 14 Beringen Limburg 3581",
    "addr:housenumber":"14",
    "addr:postcode":"3581",
    "addr:street":"Burg. Heymansplein",
    "iso:country":"BE",
    "sg:address":"Burg. Heymansplein 14",
    "sg:city":"Beringen",
    "sg:orig_category":"Overheidsdiensten",
    "sg:phone":"+32 11 34 03 70",
    "sg:postcode":"3581",
    "sg:province":"Limburg",
    "wof:name":"O.c.m.w.",
    "wof:placetype":"venue"
},
  "geometry": {"coordinates":[5.2228298187,51.0881996155],"type":"Point"}
}