{
  "type": "Feature",
  "properties": {
    "iso:country":"BE",
    "sg:address":"Roosbeekstraat 53",
    "sg:city":"Sint-truiden",
    "sg:orig_category":"Producteurs de fruits",
    "sg:phone":"+32 11 68 75 89",
    "sg:postcode":"3800",
    "sg:province":"Limburg",
    "wof:name":"Rene Mombaerts",
    "wof:placetype":"venue"
},
  "geometry": {"coordinates":[5.2623229027,50.832660675],"type":"Point"}
}