{
  "type": "Feature",
  "properties": {
    "addr:full":"Roterijstr 145 Waregem West-Vlaanderen 8790",
    "addr:housenumber":"145",
    "addr:postcode":"8790",
    "iso:country":"BE",
    "sg:address":"Roterijstr 145",
    "sg:city":"Waregem",
    "sg:classifiers":[
        {
            "category":"Food & Beverages",
            "subcategory":"Fruits & Vegetables",
            "type":"Retail Goods"
        }
    ],
    "sg:phone":"+32 56 61 11 55",
    "sg:postcode":"8790",
    "sg:province":"West-Vlaanderen",
    "sg:tags":[
        "frozen",
        "product",
        "related"
    ],
    "wof:name":"Spuntini-snacks Bvba",
    "wof:placetype":"venue"
},
  "geometry": {"coordinates":[3.4057700634,50.8949432373],"type":"Point"}
}