{
  "type": "Feature",
  "properties": {
    "iso:country":"BE",
    "sg:address":"Rue De La Station 77",
    "sg:city":"Chatelet",
    "sg:orig_category":"Fleurs and plantes",
    "sg:phone":"+32 71 38 99 28",
    "sg:postcode":"6200",
    "sg:province":"Hainaut",
    "wof:name":"Dewez",
    "wof:placetype":"venue"
},
  "geometry": {"coordinates":[4.5295891762,50.4032020569],"type":"Point"}
}