{
  "type": "Feature",
  "properties": {
    "addr:full":"Rue Du Palais 58 Verviers Li\u00e8ge 4800",
    "addr:housenumber":"58",
    "addr:postcode":"4800",
    "addr:street":"Rue Du Palais",
    "iso:country":"BE",
    "sg:address":"Rue Du Palais 58",
    "sg:city":"Verviers",
    "sg:classifiers":[
        {
            "category":"Professional",
            "subcategory":"Lawyer & Legal Services",
            "type":"Services"
        }
    ],
    "sg:phone":"+32 87 22 45 33",
    "sg:postcode":"4800",
    "sg:province":"Li\u00e8ge",
    "wof:name":"Tasquin B",
    "wof:placetype":"venue"
},
  "geometry": {"coordinates":[5.8613619804,50.5901260376],"type":"Point"}
}