{
  "type": "Feature",
  "properties": {
    "iso:country":"BE",
    "sg:address":"Nieuwstraat 12",
    "sg:city":"Galmaarden",
    "sg:orig_category":"MEUBELONTWERP AND -INSTALLATIE Matrassen Fab Meubelzaken, woning- and keukeninrichting",
    "sg:phone":"+32 54 58 82 58",
    "sg:postcode":"1570",
    "sg:province":"Vlaams-Brabant",
    "wof:name":"Demomeubel",
    "wof:placetype":"venue"
},
  "geometry": {"coordinates":[3.9711070061,50.7513313293],"type":"Point"}
}