{
  "type": "Feature",
  "properties": {
    "iso:country":"BE",
    "sg:address":"Schrieksebaan 172",
    "sg:city":"Keerbergen",
    "sg:orig_category":"Oldtimers",
    "sg:phone":"+32 15 73 08 73",
    "sg:postcode":"3140",
    "sg:province":"Vlaams-Brabant",
    "wof:name":"L.e.i. Bvba",
    "wof:placetype":"venue"
},
  "geometry": {"coordinates":[4.6689047813,51.0146713257],"type":"Point"}
}