{
  "type": "Feature",
  "properties": {
    "addr:full":"Nalonsart 2 Marchin Li\u00e8ge 4570",
    "addr:housenumber":"2",
    "addr:postcode":"4570",
    "addr:street":"Nalonsart",
    "iso:country":"BE",
    "sg:address":"Nalonsart 2",
    "sg:city":"Marchin",
    "sg:classifiers":[
        {
            "category":"Health Services",
            "subcategory":"Health Practitioner",
            "type":"Services"
        }
    ],
    "sg:phone":"+32 85 21 66 85",
    "sg:postcode":"4570",
    "sg:province":"Li\u00e8ge",
    "sg:tags":[
        "physiotherapist"
    ],
    "wof:name":"Halut Pierre",
    "wof:placetype":"venue"
},
  "geometry": {"coordinates":[5.2238807678,50.4998016357],"type":"Point"}
}