{
  "type": "Feature",
  "properties": {
    "addr:full":"Avenue Reine Astrid 49 Waterloo Brabant Wallon 1410",
    "addr:housenumber":"49",
    "addr:postcode":"1410",
    "addr:street":"Avenue Reine Astrid",
    "iso:country":"BE",
    "sg:address":"Avenue Reine Astrid 49",
    "sg:city":"Waterloo",
    "sg:classifiers":[
        {
            "category":"Organizations",
            "subcategory":"Professional Association",
            "type":"Services"
        }
    ],
    "sg:phone":"+32 2 357 00 63",
    "sg:postcode":"1410",
    "sg:province":"Brabant Wallon",
    "sg:tags":[
        "trade-union",
        "federation"
    ],
    "wof:name":"Espace Ind\u00e9pendant Brabant Wallon Asbl",
    "wof:placetype":"venue"
},
  "geometry": {"coordinates":[4.4010548592,50.718208313],"type":"Point"}
}