{
  "type": "Feature",
  "properties": {
    "addr:full":"Vinkenbosstraat 25 Oud-heverlee Vlaams-Brabant 3053",
    "addr:housenumber":"25",
    "addr:postcode":"3053",
    "addr:street":"Vinkenbosstraat",
    "iso:country":"BE",
    "sg:address":"Vinkenbosstraat 25",
    "sg:city":"Oud-heverlee",
    "sg:orig_category":"Sportclubs",
    "sg:phone":"+32 16 40 23 22",
    "sg:postcode":"3053",
    "sg:province":"Vlaams-Brabant",
    "wof:name":"V.c. Kbc Haasrode-leuven",
    "wof:placetype":"venue"
},
  "geometry": {"coordinates":[4.7275500298,50.8341712952],"type":"Point"}
}