{
  "type": "Feature",
  "properties": {
    "addr:full":"Hazelnotedreef 14 Wingene West-Vlaanderen 8750",
    "addr:housenumber":"14",
    "addr:postcode":"8750",
    "addr:street":"Hazelnotedreef",
    "iso:country":"BE",
    "sg:address":"Hazelnotedreef 14",
    "sg:city":"Wingene",
    "sg:classifiers":[
        {
            "category":"Food & Beverages",
            "subcategory":"Fruits & Vegetables",
            "type":"Retail Goods"
        }
    ],
    "sg:phone":"+32 50 28 05 88",
    "sg:postcode":"8750",
    "sg:province":"West-Vlaanderen",
    "sg:tags":[
        "l\u00e9gumes"
    ],
    "wof:name":"Gino Poppe",
    "wof:placetype":"venue"
},
  "geometry": {"coordinates":[3.2970540524,51.0976982117],"type":"Point"}
}