{
  "type": "Feature",
  "properties": {
    "addr:full":"Bronstraat 3 Mol Antwerpen 2400",
    "addr:housenumber":"3",
    "addr:postcode":"2400",
    "addr:street":"Bronstraat",
    "iso:country":"BE",
    "sg:address":"Bronstraat 3",
    "sg:city":"Mol",
    "sg:orig_category":"M\u00e9decins and sp\u00e9cialistes",
    "sg:phone":"+32 14 31 57 10",
    "sg:postcode":"2400",
    "sg:province":"Antwerpen",
    "wof:name":"P. Coursier",
    "wof:placetype":"venue"
},
  "geometry": {"coordinates":[5.0796289444,51.1883735657],"type":"Point"}
}