{
  "type": "Feature",
  "properties": {
    "addr:full":"Place D'hyon 2 Mons Hainaut 7022",
    "addr:housenumber":"2",
    "addr:postcode":"7022",
    "addr:street":"Place D'Hyon;Hainaut",
    "iso:country":"BE",
    "sg:address":"Place D'hyon 2",
    "sg:city":"Mons",
    "sg:orig_category":"Entretien and r\u00e9parations de voitures",
    "sg:phone":"+32 65 36 30 40",
    "sg:postcode":"7022",
    "sg:province":"Hainaut",
    "wof:name":"Ateliers Des Calandres",
    "wof:placetype":"venue"
},
  "geometry": {"coordinates":[3.961566925,50.4292144775],"type":"Point"}
}