{
  "type": "Feature",
  "properties": {
    "addr:full":"Rue Franz Merjay 203 Bruxelles (ixelles) Bruxelles-Capitale 1050",
    "addr:housenumber":"203",
    "addr:postcode":"1050",
    "addr:street":"Rue Franz Merjay",
    "iso:country":"BE",
    "sg:address":"Rue Franz Merjay 203",
    "sg:city":"Bruxelles (ixelles)",
    "sg:classifiers":[
        {
            "category":"Health Services",
            "subcategory":"Doctor",
            "type":"Services"
        }
    ],
    "sg:phone":"+32 2 344 11 14",
    "sg:postcode":"1050",
    "sg:province":"Bruxelles-Capitale",
    "sg:tags":[
        "medicinephysicians",
        "surgeon"
    ],
    "wof:name":"Laurent Yvette",
    "wof:placetype":"venue"
},
  "geometry": {"coordinates":[4.3512201309,50.8150939941],"type":"Point"}
}