{
  "type": "Feature",
  "properties": {
    "iso:country":"BE",
    "sg:address":"Schuurkouter 17",
    "sg:city":"Dendermonde",
    "sg:orig_category":"G\u00e9om\u00e8tres",
    "sg:phone":"+32 52 33 27 25",
    "sg:postcode":"9200",
    "sg:province":"Oost-Vlaanderen",
    "wof:name":"G. De Boeck",
    "wof:placetype":"venue"
},
  "geometry": {"coordinates":[4.0983099937,51.0315208435],"type":"Point"}
}