{
  "type": "Feature",
  "properties": {
    "addr:full":"Liersesteenweg 230 Mechelen Antwerpen 2800",
    "addr:housenumber":"230",
    "addr:postcode":"2800",
    "addr:street":"Liersesteenweg",
    "iso:country":"BE",
    "sg:address":"Liersesteenweg 230",
    "sg:city":"Mechelen",
    "sg:classifiers":[
        {
            "category":"Shopping",
            "subcategory":"Bicycles & Sporting Goods",
            "type":"Retail Goods"
        }
    ],
    "sg:phone":"+32 15 20 32 54",
    "sg:postcode":"2800",
    "sg:province":"Antwerpen",
    "sg:tags":[
        "-"
    ],
    "wof:name":"Velolux",
    "wof:placetype":"venue"
},
  "geometry": {"coordinates":[4.4786958694,51.0399475098],"type":"Point"}
}