{
  "type": "Feature",
  "properties": {
    "iso:country":"BE",
    "sg:address":"Rue De La Gare 48",
    "sg:city":"Ronse/renaix",
    "sg:classifiers":[
        {
            "category":"Restaurant",
            "type":"Food & Drink"
        }
    ],
    "sg:phone":"+32 55 21 43 86",
    "sg:postcode":"9600",
    "sg:province":"Oost-Vlaanderen",
    "wof:name":"Mc Loomy",
    "wof:placetype":"venue"
},
  "geometry": {"coordinates":[3.6016271114,50.7428512573],"type":"Point"}
}