{
  "type": "Feature",
  "properties": {
    "addr:full":"Ijzerstraat 3-1 Oostende West-Vlaanderen 8400",
    "addr:housenumber":"3-1",
    "addr:postcode":"8400",
    "addr:street":"Ijzerstraat",
    "iso:country":"BE",
    "sg:address":"Ijzerstraat 3-1",
    "sg:city":"Oostende",
    "sg:classifiers":[
        {
            "category":"Building & Trades",
            "subcategory":"Construction",
            "type":"Services"
        }
    ],
    "sg:phone":"+32 59 50 94 15",
    "sg:postcode":"8400",
    "sg:province":"West-Vlaanderen",
    "sg:tags":[
        "surveyor",
        "-"
    ],
    "wof:name":"Bogaerts M",
    "wof:placetype":"venue"
},
  "geometry": {"coordinates":[2.9130470753,51.2293243408],"type":"Point"}
}