{
  "type": "Feature",
  "properties": {
    "iso:country":"BE",
    "sg:address":"Albrecht Rodenbachstraat 5",
    "sg:city":"Hasselt",
    "sg:classifiers":[
        {
            "category":"Sports & Exercise",
            "subcategory":"Playing Field",
            "type":"Entertainment"
        }
    ],
    "sg:phone":"+32 89 51 86 70",
    "sg:postcode":"3500",
    "sg:province":"Limburg",
    "sg:tags":[
        "temporary",
        "employment",
        "software",
        "leasing",
        "staff"
    ],
    "wof:name":"Prato",
    "wof:placetype":"venue"
},
  "geometry": {"coordinates":[5.3401799202,50.9250640869],"type":"Point"}
}