{
  "type": "Feature",
  "properties": {
    "iso:country":"BE",
    "sg:address":"Paul Dejaerlaan 33",
    "sg:city":"Sint-gillis/saint-gilles",
    "sg:orig_category":"Begrafeniswezen",
    "sg:phone":"+32 2 537 83 99",
    "sg:postcode":"1060",
    "sg:province":"Bruxelles-Capitale",
    "wof:name":"Fun\u00c9railles Melchior",
    "wof:placetype":"venue"
},
  "geometry": {"coordinates":[4.3448839188,50.8256225586],"type":"Point"}
}