{
  "type": "Feature",
  "properties": {
    "addr:full":"Rue Alphonse Robert 60 Incourt Brabant Wallon 1315",
    "addr:housenumber":"60",
    "addr:postcode":"1315",
    "addr:street":"Rue Alphonse Robert",
    "iso:country":"BE",
    "sg:address":"Rue Alphonse Robert 60",
    "sg:city":"Incourt",
    "sg:orig_category":"Elektrische installaties voor woningen",
    "sg:phone":"+32 10 88 94 15",
    "sg:postcode":"1315",
    "sg:province":"Brabant Wallon",
    "wof:name":"Maurice Pelsmaekers",
    "wof:placetype":"venue"
},
  "geometry": {"coordinates":[4.7628059387,50.6798706055],"type":"Point"}
}