{
  "type": "Feature",
  "properties": {
    "addr:full":"Ieperstraat 40 Staden West-Vlaanderen 8840",
    "addr:housenumber":"40",
    "addr:postcode":"8840",
    "addr:street":"Ieperstraat",
    "iso:country":"BE",
    "sg:address":"Ieperstraat 40",
    "sg:city":"Staden",
    "sg:classifiers":[
        {
            "category":"Arena",
            "subcategory":"Sports Club",
            "type":"Entertainment"
        }
    ],
    "sg:phone":"+32 51 70 19 52",
    "sg:postcode":"8840",
    "sg:province":"West-Vlaanderen",
    "sg:tags":[
        "terrain",
        "hors",
        "de",
        "installation",
        "sportifs"
    ],
    "wof:name":"F.c. Bouwstof.masschelein",
    "wof:placetype":"venue"
},
  "geometry": {"coordinates":[3.013406992,50.9726524353],"type":"Point"}
}