{
  "type": "Feature",
  "properties": {
    "addr:full":"Joseph Cardijnstraat 8 Erpe-mere (erpe) Oost-Vlaanderen 9420",
    "addr:housenumber":"8",
    "addr:postcode":"9420",
    "addr:street":"Joseph Cardijnstraat",
    "iso:country":"BE",
    "sg:address":"Joseph Cardijnstraat 8",
    "sg:city":"Erpe-mere (erpe)",
    "sg:classifiers":[
        {
            "category":"Structure",
            "subcategory":"Building",
            "type":"Public Place"
        }
    ],
    "sg:phone":"+32 53 80 23 49",
    "sg:postcode":"9420",
    "sg:province":"Oost-Vlaanderen",
    "sg:tags":[
        "door"
    ],
    "wof:name":"Dubo Nv",
    "wof:placetype":"venue"
},
  "geometry": {"coordinates":[3.9618179798,50.9316139221],"type":"Point"}
}