{
  "type": "Feature",
  "properties": {
    "iso:country":"BE",
    "sg:address":"Oosthoekstraat 11",
    "sg:city":"Ardooie",
    "sg:orig_category":"Varkenskwekers",
    "sg:phone":"+32 51 74 41 13",
    "sg:postcode":"8850",
    "sg:province":"West-Vlaanderen",
    "wof:name":"Etienne Demeulenaere",
    "wof:placetype":"venue"
},
  "geometry": {"coordinates":[3.2203800678,50.9869232178],"type":"Point"}
}