{
  "type": "Feature",
  "properties": {
    "addr:full":"Steenovenstraat 74 Meulebeke West-Vlaanderen 8760",
    "addr:housenumber":"74",
    "addr:postcode":"8760",
    "addr:street":"Steenovenstraat",
    "iso:country":"BE",
    "sg:address":"Steenovenstraat 74",
    "sg:city":"Meulebeke",
    "sg:classifiers":[
        {
            "category":"Airport",
            "subcategory":"International",
            "type":"Transportation"
        }
    ],
    "sg:phone":"+32 51 48 72 47",
    "sg:postcode":"8760",
    "sg:province":"West-Vlaanderen",
    "sg:tags":[
        "-",
        "transport"
    ],
    "wof:name":"De Meyere Bvba",
    "wof:placetype":"venue"
},
  "geometry": {"coordinates":[3.3291270733,50.9518241882],"type":"Point"}
}