{
  "type": "Feature",
  "properties": {
    "addr:full":"Bosdreef Lochristi Oost-Vlaanderen 9080",
    "addr:postcode":"9080",
    "addr:street":"Bosdreef",
    "iso:country":"BE",
    "sg:address":"Bosdreef",
    "sg:city":"Lochristi",
    "sg:orig_category":"Sportclubs Sportterreinen and installaties behalve sportcentra",
    "sg:phone":"+32 9 355 02 52",
    "sg:postcode":"9080",
    "sg:province":"Oost-Vlaanderen",
    "wof:name":"Sporting Club Begonia Lochristi",
    "wof:placetype":"venue"
},
  "geometry": {"coordinates":[3.8384349346,51.0956344604],"type":"Point"}
}