{
  "type": "Feature",
  "properties": {
    "iso:country":"BE",
    "sg:address":"Groenstraat 54a",
    "sg:city":"Hoeselt",
    "sg:orig_category":"HERSTELLING ELEKTRISCHE HUISHOUDAPPARATEN Huishoudapparaten, televisies and radio's",
    "sg:phone":"+32 89 41 22 01",
    "sg:postcode":"3730",
    "sg:province":"Limburg",
    "wof:name":"Elza Vangossum",
    "wof:placetype":"venue"
},
  "geometry": {"coordinates":[5.4790878296,50.8645935059],"type":"Point"}
}