{
  "type": "Feature",
  "properties": {
    "addr:full":"Revinzestraat 39 Torhout West-Vlaanderen 8820",
    "addr:housenumber":"39",
    "addr:postcode":"8820",
    "addr:street":"Revinzestraat",
    "iso:country":"BE",
    "sg:address":"Revinzestraat 39",
    "sg:city":"Torhout",
    "sg:orig_category":"Installation de menuiserie en bois and plastique",
    "sg:phone":"+32 50 21 32 10",
    "sg:postcode":"8820",
    "sg:province":"West-Vlaanderen",
    "wof:name":"Deketelaere Gebrs",
    "wof:placetype":"venue"
},
  "geometry": {"coordinates":[3.0859770775,51.0668067932],"type":"Point"}
}