{
  "type": "Feature",
  "properties": {
    "addr:full":"Weggevoerdenstraat 128 Ninove Oost-Vlaanderen 9400",
    "addr:housenumber":"128",
    "addr:postcode":"9400",
    "addr:street":"Weggevoerdenstraat",
    "iso:country":"BE",
    "sg:address":"Weggevoerdenstraat 128",
    "sg:city":"Ninove",
    "sg:orig_category":"Slagers",
    "sg:phone":"+32 54 33 29 25",
    "sg:postcode":"9400",
    "sg:province":"Oost-Vlaanderen",
    "wof:name":"Slagerij Ludo & Sylvie",
    "wof:placetype":"venue"
},
  "geometry": {"coordinates":[4.0214829445,50.8410110474],"type":"Point"}
}