{
  "type": "Feature",
  "properties": {
    "iso:country":"BE",
    "sg:address":"Sint- Salvatorstraat 1b",
    "sg:city":"Hoogstraten",
    "sg:orig_category":"Diverse bedrijfsbeheeradviesbureaus",
    "sg:phone":"+32 3 315 07 95",
    "sg:postcode":"2328",
    "sg:province":"Antwerpen",
    "wof:name":"Doerrleben Management & Co",
    "wof:placetype":"venue"
},
  "geometry": {"coordinates":[4.7996301651,51.4718894958],"type":"Point"}
}