{
  "type": "Feature",
  "properties": {
    "iso:country":"BE",
    "sg:address":"Brusselsesteenweg 339",
    "sg:city":"Asse (kobbegem)",
    "sg:classifiers":[
        {
            "category":"Social Services",
            "subcategory":"Child Care",
            "type":"Services"
        }
    ],
    "sg:phone":"+32 2 452 51 38",
    "sg:postcode":"1730",
    "sg:province":"Vlaams-Brabant",
    "sg:tags":[
        "boy",
        "scout",
        "equipment"
    ],
    "wof:name":"Stockoma Bvba",
    "wof:placetype":"venue"
},
  "geometry": {"coordinates":[4.2377400398,50.8961982727],"type":"Point"}
}