{
  "type": "Feature",
  "properties": {
    "addr:full":"Bruegheldreef 15 Overijse Vlaams-Brabant 3090",
    "addr:housenumber":"15",
    "addr:postcode":"3090",
    "addr:street":"Bruegheldreef",
    "iso:country":"BE",
    "sg:address":"Bruegheldreef 15",
    "sg:city":"Overijse",
    "sg:orig_category":"Belastingconsulenten Diverse juridische dienstverlening",
    "sg:phone":"+32 2 687 64 42",
    "sg:postcode":"3090",
    "sg:province":"Vlaams-Brabant",
    "wof:name":"Paul Bourlon",
    "wof:placetype":"venue"
},
  "geometry": {"coordinates":[4.5024409294,50.7866401672],"type":"Point"}
}