{
  "type": "Feature",
  "properties": {
    "addr:full":"Tempelhofstraat 32 Gistel West-Vlaanderen 8470",
    "addr:housenumber":"32",
    "addr:postcode":"8470",
    "addr:street":"Tempelhofstraat",
    "iso:country":"BE",
    "sg:address":"Tempelhofstraat 32",
    "sg:city":"Gistel",
    "sg:orig_category":"Boucheries",
    "sg:phone":"+32 59 27 89 35",
    "sg:postcode":"8470",
    "sg:province":"West-Vlaanderen",
    "wof:name":"Beenhouwerij Lieven",
    "wof:placetype":"venue"
},
  "geometry": {"coordinates":[2.9606900215,51.1559333801],"type":"Point"}
}