{
  "type": "Feature",
  "properties": {
    "iso:country":"BE",
    "sg:address":"Pater Damiaanlaan 76",
    "sg:city":"Sint-pieters-woluwe/woluwe-saint-pierre",
    "sg:orig_category":"Kinderopvang",
    "sg:phone":"+32 2 770 88 56",
    "sg:postcode":"1150",
    "sg:province":"Bruxelles-Capitale",
    "wof:name":"Farandoline (la)",
    "wof:placetype":"venue"
},
  "geometry": {"coordinates":[4.4194941521,50.8381996155],"type":"Point"}
}