{
  "type": "Feature",
  "properties": {
    "addr:full":"Hameau De G\u00c9ronsart 20 Couvin Namur 5660",
    "addr:housenumber":"20",
    "addr:postcode":"5660",
    "addr:street":"Hameau De Ge\u0301Ronsart",
    "iso:country":"BE",
    "sg:address":"Hameau De G\u00c9ronsart 20",
    "sg:city":"Couvin",
    "sg:orig_category":"Antiek",
    "sg:phone":"+32 60 31 16 66",
    "sg:postcode":"5660",
    "sg:province":"Namur",
    "wof:name":"Maison Cosse Petuna",
    "wof:placetype":"venue"
},
  "geometry": {"coordinates":[4.4567899704,50.1050415039],"type":"Point"}
}