{
  "type": "Feature",
  "properties": {
    "addr:full":"Langenberg 13 Kasterlee Antwerpen 2460",
    "addr:housenumber":"13",
    "addr:postcode":"2460",
    "addr:street":"Langenberg",
    "iso:country":"BE",
    "sg:address":"Langenberg 13",
    "sg:city":"Kasterlee",
    "sg:orig_category":"Instituts de beaut\u00e9",
    "sg:phone":"+32 14 55 31 79",
    "sg:postcode":"2460",
    "sg:province":"Antwerpen",
    "wof:name":"Instituut Pascale",
    "wof:placetype":"venue"
},
  "geometry": {"coordinates":[4.9458122253,51.2192153931],"type":"Point"}
}