{
  "type": "Feature",
  "properties": {
    "addr:full":"Bevingen-centrum 39 Sint-truiden Limburg 3800",
    "addr:housenumber":"39",
    "addr:postcode":"3800",
    "addr:street":"Bevingen-Centrum",
    "iso:country":"BE",
    "sg:address":"Bevingen-centrum 39",
    "sg:city":"Sint-truiden",
    "sg:classifiers":[
        {
            "category":"Health Services",
            "subcategory":"Nursing And Care Facility",
            "type":"Services"
        }
    ],
    "sg:phone":"+32 11 68 80 55",
    "sg:postcode":"3800",
    "sg:province":"Limburg",
    "sg:tags":[
        "home"
    ],
    "wof:name":"Boudin Patricia Bvba",
    "wof:placetype":"venue"
},
  "geometry": {"coordinates":[5.1863641739,50.8153343201],"type":"Point"}
}