{
  "type": "Feature",
  "properties": {
    "iso:country":"BE",
    "sg:address":"Koebaan 5",
    "sg:city":"Keerbergen",
    "sg:classifiers":[
        {
            "category":"Home & Garden",
            "subcategory":"Carpets & Floor Coverings",
            "type":"Retail Goods"
        }
    ],
    "sg:phone":"+32 15 23 30 80",
    "sg:postcode":"3140",
    "sg:province":"Vlaams-Brabant",
    "sg:tags":[
        "-"
    ],
    "wof:name":"Piot R",
    "wof:placetype":"venue"
},
  "geometry": {"coordinates":[4.6632699966,51.0087623596],"type":"Point"}
}