{
  "type": "Feature",
  "properties": {
    "iso:country":"BE",
    "sg:address":"Barrierestraat 55",
    "sg:city":"Wervik",
    "sg:orig_category":"Artiesten and kunstenaars",
    "sg:phone":"+32 56 31 37 57",
    "sg:postcode":"8940",
    "sg:province":"West-Vlaanderen",
    "wof:name":"Jim Vermeulen",
    "wof:placetype":"venue"
},
  "geometry": {"coordinates":[3.0311229229,50.7775764465],"type":"Point"}
}