{
  "type": "Feature",
  "properties": {
    "addr:full":"Singel 7 Kontich Antwerpen 2550",
    "addr:housenumber":"7",
    "addr:postcode":"2550",
    "addr:street":"Singel",
    "iso:country":"BE",
    "sg:address":"Singel 7",
    "sg:city":"Kontich",
    "sg:classifiers":[
        {
            "category":"Wholesale",
            "subcategory":"Machinery & Supplies",
            "type":"Manufacturing & Wholesale Goods"
        }
    ],
    "sg:phone":"+32 3 451 34 90",
    "sg:postcode":"2550",
    "sg:province":"Antwerpen",
    "sg:tags":[
        "refrigeration",
        "-",
        "industrial",
        "commercial",
        "equipment"
    ],
    "wof:name":"Airclima Bvba",
    "wof:placetype":"venue"
},
  "geometry": {"coordinates":[4.4559259415,51.1239967346],"type":"Point"}
}