{
  "type": "Feature",
  "properties": {
    "addr:full":"Brillat-savarinlaan 70 Elsene/ixelles Bruxelles-Capitale 1050",
    "addr:housenumber":"70",
    "addr:postcode":"1050",
    "addr:street":"Brillat-Savarinlaan",
    "iso:country":"BE",
    "sg:address":"Brillat-savarinlaan 70",
    "sg:city":"Elsene/ixelles",
    "sg:orig_category":"Zalen voor culturele evenementen",
    "sg:phone":"+32 2 644 64 90",
    "sg:postcode":"1050",
    "sg:province":"Bruxelles-Capitale",
    "wof:name":"Aleph",
    "wof:placetype":"venue"
},
  "geometry": {"coordinates":[4.3851618767,50.816116333],"type":"Point"}
}