{
  "type": "Feature",
  "properties": {
    "addr:full":"Sint-pietersmolenstraat 15 Brugge West-Vlaanderen 8000",
    "addr:housenumber":"15",
    "addr:postcode":"8000",
    "addr:street":"Sint-Pietersmolenstraat",
    "iso:country":"BE",
    "sg:address":"Sint-pietersmolenstraat 15",
    "sg:city":"Brugge",
    "sg:classifiers":[
        {
            "category":"Building & Trades",
            "subcategory":"Landscaping Services",
            "type":"Services"
        }
    ],
    "sg:phone":"+32 50 32 30 35",
    "sg:postcode":"8000",
    "sg:province":"West-Vlaanderen",
    "sg:tags":[
        "gardening",
        "garden",
        "maintenance"
    ],
    "wof:name":"Botte Jean-pierre",
    "wof:placetype":"venue"
},
  "geometry": {"coordinates":[3.2019050121,51.2331085205],"type":"Point"}
}