{
  "type": "Feature",
  "properties": {
    "addr:full":"Rue De Beaumont 495 Charleroi Hainaut 6030",
    "addr:housenumber":"495",
    "addr:postcode":"6030",
    "addr:street":"Rue De Beaumont;Hainaut",
    "iso:country":"BE",
    "sg:address":"Rue De Beaumont 495",
    "sg:city":"Charleroi",
    "sg:orig_category":"M\u00e9decins and sp\u00e9cialistes",
    "sg:phone":"+32 71 51 56 79",
    "sg:postcode":"6030",
    "sg:province":"Hainaut",
    "wof:name":"Guy Votquenne",
    "wof:placetype":"venue"
},
  "geometry": {"coordinates":[4.3871321678,50.3921203613],"type":"Point"}
}