{
  "type": "Feature",
  "properties": {
    "iso:country":"BE",
    "sg:address":"Chauss\u00c9e De Brunehault 161",
    "sg:city":"Herstal",
    "sg:classifiers":[
        {
            "category":"Insurance",
            "subcategory":"Life Insurance",
            "type":"Services"
        }
    ],
    "sg:phone":"+32 4 227 05 12",
    "sg:postcode":"4041",
    "sg:province":"Li\u00e8ge",
    "sg:tags":[
        "assurance"
    ],
    "wof:name":"T. Demany",
    "wof:placetype":"venue"
},
  "geometry": {"coordinates":[5.5828299522,50.6791114807],"type":"Point"}
}