{
  "type": "Feature",
  "properties": {
    "iso:country":"BE",
    "sg:address":"Rue Des Eglantiers 19",
    "sg:city":"Andenne (sclayn)",
    "sg:classifiers":[
        {
            "category":"Professional",
            "subcategory":"Accounting & Tax Preparation",
            "type":"Services"
        }
    ],
    "sg:phone":"+32 81 58 13 20",
    "sg:postcode":"5300",
    "sg:province":"Namur",
    "sg:tags":[
        "bookkeeper"
    ],
    "wof:name":"Hardy Bureau Comptables",
    "wof:placetype":"venue"
},
  "geometry": {"coordinates":[5.0344147682,50.4858093262],"type":"Point"}
}