{
  "type": "Feature",
  "properties": {
    "addr:full":"Gelindendorp 14 Sint-truiden Limburg 3800",
    "addr:housenumber":"14",
    "addr:postcode":"3800",
    "addr:street":"Gelindendorp",
    "iso:country":"BE",
    "sg:address":"Gelindendorp 14",
    "sg:city":"Sint-truiden",
    "sg:orig_category":"V\u00e9t\u00e9rinaires",
    "sg:phone":"+32 11 48 50 75",
    "sg:postcode":"3800",
    "sg:province":"Limburg",
    "wof:name":"A. Aerts",
    "wof:placetype":"venue"
},
  "geometry": {"coordinates":[5.1863641739,50.8153343201],"type":"Point"}
}