{
  "type": "Feature",
  "properties": {
    "iso:country":"BE",
    "sg:address":"Richter 25",
    "sg:city":"Genk",
    "sg:classifiers":[
        {
            "category":"Education",
            "subcategory":"School",
            "type":"Public Place"
        }
    ],
    "sg:phone":"+32 89 35 40 92",
    "sg:postcode":"3600",
    "sg:province":"Limburg",
    "sg:tags":[
        "primary"
    ],
    "wof:name":"Medisch Pedagogische Instituten Van De Gemeenschap",
    "wof:placetype":"venue"
},
  "geometry": {"coordinates":[5.5217399597,50.9722328186],"type":"Point"}
}