{
  "type": "Feature",
  "properties": {
    "addr:full":"Duinenlaan 98 Middelkerke (westende) West-Vlaanderen 8434",
    "addr:housenumber":"98",
    "addr:postcode":"8434",
    "addr:street":"Duinenlaan",
    "iso:country":"BE",
    "sg:address":"Duinenlaan 98",
    "sg:city":"Middelkerke (westende)",
    "sg:classifiers":[
        {
            "category":"Bars & Pubs",
            "type":"Food & Drink"
        }
    ],
    "sg:phone":"+32 59 31 36 67",
    "sg:postcode":"8434",
    "sg:province":"West-Vlaanderen",
    "sg:tags":[
        "tavern"
    ],
    "wof:name":"Boondyck",
    "wof:placetype":"venue"
},
  "geometry": {"coordinates":[2.7708508968,51.1648445129],"type":"Point"}
}