{
  "type": "Feature",
  "properties": {
    "iso:country":"BE",
    "sg:address":"Rue De La Ladrerie 6",
    "sg:city":"Brunehaut",
    "sg:orig_category":"Tuinen",
    "sg:phone":"+32 69 44 16 02",
    "sg:postcode":"7620",
    "sg:province":"Hainaut",
    "wof:name":"Regniez P.",
    "wof:placetype":"venue"
},
  "geometry": {"coordinates":[3.4070839882,50.5542488098],"type":"Point"}
}