{
  "type": "Feature",
  "properties": {
    "addr:full":"Desselgemse Steenweg 47 Deerlijk West-Vlaanderen 8540",
    "addr:housenumber":"47",
    "addr:postcode":"8540",
    "addr:street":"Steenweg",
    "iso:country":"BE",
    "sg:address":"Desselgemse Steenweg 47",
    "sg:city":"Deerlijk",
    "sg:classifiers":[
        {
            "category":"Building & Trades",
            "subcategory":"Landscaping Services",
            "type":"Services"
        }
    ],
    "sg:phone":"+32 56 71 76 88",
    "sg:postcode":"8540",
    "sg:province":"West-Vlaanderen",
    "sg:tags":[
        "gardening",
        "garden",
        "maintenance"
    ],
    "wof:name":"Deplancke D",
    "wof:placetype":"venue"
},
  "geometry": {"coordinates":[3.3764159679,50.8616142273],"type":"Point"}
}