{
  "type": "Feature",
  "properties": {
    "addr:full":"Rue Franklin 80 Brussel/bruxelles Bruxelles-Capitale 1000",
    "addr:housenumber":"80",
    "addr:postcode":"1000",
    "addr:street":"Rue Franklin;/",
    "iso:country":"BE",
    "sg:address":"Rue Franklin 80",
    "sg:city":"Brussel/bruxelles",
    "sg:orig_category":"Machines and mat\u00e9riel de bureau Ordinateurs and \u00e9quipement informatique",
    "sg:phone":"+32 2 735 51 62",
    "sg:postcode":"1000",
    "sg:province":"Bruxelles-Capitale",
    "wof:name":"Impuls Computer Shop",
    "wof:placetype":"venue"
},
  "geometry": {"coordinates":[4.387485981,50.8457374573],"type":"Point"}
}