{
  "type": "Feature",
  "properties": {
    "addr:full":"Lendeleedsestraat 126 Izegem West-Vlaanderen 8870",
    "addr:housenumber":"126",
    "addr:postcode":"8870",
    "addr:street":"Lendeleedsestraat",
    "iso:country":"BE",
    "sg:address":"Lendeleedsestraat 126",
    "sg:city":"Izegem",
    "sg:orig_category":"Entretien and r\u00e9parations de voitures",
    "sg:phone":"+32 51 30 11 12",
    "sg:postcode":"8870",
    "sg:province":"West-Vlaanderen",
    "wof:name":"Eric Vanhuyse",
    "wof:placetype":"venue"
},
  "geometry": {"coordinates":[3.2308709621,50.9102668762],"type":"Point"}
}