{
  "type": "Feature",
  "properties": {
    "addr:full":"Chauss\u00c9e De Haecht 68 Sint-joost-ten-node/saint-josse-ten-noode Bruxelles-Capitale 1210",
    "addr:housenumber":"68",
    "addr:postcode":"1210",
    "addr:street":"Chausse\u0301E De Haecht",
    "iso:country":"BE",
    "sg:address":"Chauss\u00c9e De Haecht 68",
    "sg:city":"Sint-joost-ten-node/saint-josse-ten-noode",
    "sg:orig_category":"Enseignement secondaire g\u00e9n\u00e9ral. Enseignement secondaire technique and professionnel",
    "sg:phone":"+32 2 217 67 47",
    "sg:postcode":"1210",
    "sg:province":"Bruxelles-Capitale",
    "wof:name":"C.s. Dames Marie Haecht",
    "wof:placetype":"venue"
},
  "geometry": {"coordinates":[4.3693928719,50.8567733765],"type":"Point"}
}