{
  "type": "Feature",
  "properties": {
    "iso:country":"BE",
    "sg:address":"Dijkstraat 22",
    "sg:city":"Lokeren",
    "sg:classifiers":[
        {
            "category":"Military Area",
            "subcategory":"Coast Guard Base",
            "type":"Public Place"
        }
    ],
    "sg:phone":"+32 9 348 48 53",
    "sg:postcode":"9160",
    "sg:province":"Oost-Vlaanderen",
    "sg:tags":[
        "cleaner",
        "industrial",
        "vacuum"
    ],
    "wof:name":"Clarke",
    "wof:placetype":"venue"
},
  "geometry": {"coordinates":[4.0240149498,51.0926704407],"type":"Point"}
}