{
  "type": "Feature",
  "properties": {
    "addr:full":"Grote Baan 5 Hasselt Limburg 3511",
    "addr:housenumber":"5",
    "addr:postcode":"3511",
    "addr:street":"Grote Baan",
    "iso:country":"BE",
    "sg:address":"Grote Baan 5",
    "sg:city":"Hasselt",
    "sg:orig_category":"Banques and organismes de cr\u00e9dit",
    "sg:phone":"+32 11 87 26 89",
    "sg:postcode":"3511",
    "sg:province":"Limburg",
    "wof:name":"Centea",
    "wof:placetype":"venue"
},
  "geometry": {"coordinates":[5.3076381683,50.9399414062],"type":"Point"}
}