{
  "type": "Feature",
  "properties": {
    "addr:full":"Lombardsijdelaan 1 Middelkerke (westende) West-Vlaanderen 8434",
    "addr:housenumber":"1",
    "addr:postcode":"8434",
    "addr:street":"Lombardsijdelaan",
    "iso:country":"BE",
    "sg:address":"Lombardsijdelaan 1",
    "sg:city":"Middelkerke (westende)",
    "sg:classifiers":[
        {
            "category":"Food & Beverages",
            "subcategory":"Groceries & Convenience Stores",
            "type":"Retail Goods"
        }
    ],
    "sg:phone":"+32 58 23 03 64",
    "sg:postcode":"8434",
    "sg:province":"West-Vlaanderen",
    "sg:tags":[
        "grocer"
    ],
    "wof:name":"Beukels C",
    "wof:placetype":"venue"
},
  "geometry": {"coordinates":[2.7593801022,51.1512184143],"type":"Point"}
}