{
  "type": "Feature",
  "properties": {
    "iso:country":"BE",
    "sg:address":"Grootzand 144",
    "sg:city":"Dendermonde",
    "sg:orig_category":"Dameskledingzaken",
    "sg:phone":"+32 52 22 52 53",
    "sg:postcode":"9200",
    "sg:province":"Oost-Vlaanderen",
    "wof:name":"Kleding Karin",
    "wof:placetype":"venue"
},
  "geometry": {"coordinates":[4.1046471596,51.0432243347],"type":"Point"}
}