{
  "type": "Feature",
  "properties": {
    "addr:full":"Wambeekstraat 27 Steenokkerzeel Vlaams-Brabant 1820",
    "addr:housenumber":"27",
    "addr:postcode":"1820",
    "addr:street":"Wambeekstraat",
    "iso:country":"BE",
    "sg:address":"Wambeekstraat 27",
    "sg:city":"Steenokkerzeel",
    "sg:classifiers":[
        {
            "category":"Cafe",
            "type":"Food & Drink"
        }
    ],
    "sg:phone":"+32 2 751 80 38",
    "sg:postcode":"1820",
    "sg:province":"Vlaams-Brabant",
    "sg:tags":[
        "caf\u00e9s"
    ],
    "wof:name":"Andy Verteerstraeten",
    "wof:placetype":"venue"
},
  "geometry": {"coordinates":[4.5069308281,50.917388916],"type":"Point"}
}