{
  "type": "Feature",
  "properties": {
    "addr:full":"Kortrijkse Heerweg 199 Deerlijk West-Vlaanderen 8540",
    "addr:housenumber":"199",
    "addr:postcode":"8540",
    "addr:street":"Heerweg",
    "iso:country":"BE",
    "sg:address":"Kortrijkse Heerweg 199",
    "sg:city":"Deerlijk",
    "sg:orig_category":"Eleveurs de bovins. Eleveurs and marchands de porcs",
    "sg:phone":"+32 56 71 18 69",
    "sg:postcode":"8540",
    "sg:province":"West-Vlaanderen",
    "wof:name":"Ignace Benoit",
    "wof:placetype":"venue"
},
  "geometry": {"coordinates":[3.3336179256,50.8509788513],"type":"Point"}
}