{
  "type": "Feature",
  "properties": {
    "iso:country":"BE",
    "sg:address":"Haelinckstraat 3",
    "sg:city":"Gistel",
    "sg:orig_category":"Rundveehouders Varkenskwekers",
    "sg:phone":"+32 59 27 86 59",
    "sg:postcode":"8470",
    "sg:province":"West-Vlaanderen",
    "wof:name":"Rik Deschoemaeker",
    "wof:placetype":"venue"
},
  "geometry": {"coordinates":[2.9070539474,51.1272125244],"type":"Point"}
}