{
  "type": "Feature",
  "properties": {
    "iso:country":"BE",
    "sg:address":"Dreefstraat 50",
    "sg:city":"Ninove",
    "sg:orig_category":"Epiceries",
    "sg:phone":"+32 54 32 48 15",
    "sg:postcode":"9400",
    "sg:province":"Oost-Vlaanderen",
    "wof:name":"Mich De Jonge",
    "wof:placetype":"venue"
},
  "geometry": {"coordinates":[4.0247721672,50.8376617432],"type":"Point"}
}