{
  "type": "Feature",
  "properties": {
    "addr:full":"Heulestraat 51 Wevelgem (gullegem) West-Vlaanderen 8560",
    "addr:housenumber":"51",
    "addr:postcode":"8560",
    "addr:street":"Heulestraat",
    "iso:country":"BE",
    "sg:address":"Heulestraat 51",
    "sg:city":"Wevelgem (gullegem)",
    "sg:classifiers":[
        {
            "category":"Autos & Motor Vehicles",
            "subcategory":"Auto Supplies",
            "type":"Retail Goods"
        }
    ],
    "sg:phone":"+32 56 43 52 00",
    "sg:postcode":"8560",
    "sg:province":"West-Vlaanderen",
    "sg:tags":[
        "machine",
        "laundry",
        "-"
    ],
    "wof:name":"Primus Nv",
    "wof:placetype":"venue"
},
  "geometry": {"coordinates":[3.2122879028,50.842754364],"type":"Point"}
}