{
  "type": "Feature",
  "properties": {
    "addr:full":"Lintsesteenweg 68 Duffel Antwerpen 2570",
    "addr:housenumber":"68",
    "addr:postcode":"2570",
    "addr:street":"Lintsesteenweg",
    "iso:country":"BE",
    "sg:address":"Lintsesteenweg 68",
    "sg:city":"Duffel",
    "sg:classifiers":[
        {
            "category":"Personal",
            "subcategory":"Beauty Salon",
            "type":"Services"
        }
    ],
    "sg:phone":"+32 15 31 82 55",
    "sg:postcode":"2570",
    "sg:province":"Antwerpen",
    "sg:tags":[
        "de",
        "coiffure"
    ],
    "wof:name":"Haarmode",
    "wof:placetype":"venue"
},
  "geometry": {"coordinates":[4.5044159889,51.1014595032],"type":"Point"}
}