{
  "type": "Feature",
  "properties": {
    "iso:country":"BE",
    "sg:address":"Goesdamstraat 23",
    "sg:city":"Ieper",
    "sg:classifiers":[
        {
            "category":"Shopping",
            "subcategory":"Bicycles & Sporting Goods",
            "type":"Retail Goods"
        }
    ],
    "sg:phone":"+32 57 20 13 97",
    "sg:postcode":"8900",
    "sg:province":"West-Vlaanderen",
    "sg:tags":[
        "-"
    ],
    "wof:name":"Noyelle Sport",
    "wof:placetype":"venue"
},
  "geometry": {"coordinates":[2.8748459816,50.8504486084],"type":"Point"}
}