{
  "type": "Feature",
  "properties": {
    "iso:country":"BE",
    "sg:address":"Katteknok 11",
    "sg:city":"Dentergem",
    "sg:orig_category":"R\u00e9alisation de programmes and logiciels",
    "sg:phone":"+32 51 63 47 87",
    "sg:postcode":"8720",
    "sg:province":"West-Vlaanderen",
    "wof:name":"Bouwburo-vano",
    "wof:placetype":"venue"
},
  "geometry": {"coordinates":[3.3858370781,50.971912384],"type":"Point"}
}