{
  "type": "Feature",
  "properties": {
    "iso:country":"BE",
    "sg:address":"Wontergemstraat 8",
    "sg:city":"Dentergem",
    "sg:classifiers":[
        {
            "category":"Personal",
            "subcategory":"Barber",
            "type":"Services"
        }
    ],
    "sg:phone":"+32 51 63 49 01",
    "sg:postcode":"8720",
    "sg:province":"West-Vlaanderen",
    "sg:tags":[
        "gentleman",
        "salon",
        "-",
        "hairdressing"
    ],
    "wof:name":"Vandewalle H",
    "wof:placetype":"venue"
},
  "geometry": {"coordinates":[3.41959095,50.9636383057],"type":"Point"}
}