{
  "type": "Feature",
  "properties": {
    "addr:full":"Wouwersdreef 45 Schoten Antwerpen 2900",
    "addr:housenumber":"45",
    "addr:postcode":"2900",
    "addr:street":"Wouwersdreef",
    "iso:country":"BE",
    "sg:address":"Wouwersdreef 45",
    "sg:city":"Schoten",
    "sg:orig_category":"Experts-comptables",
    "sg:phone":"+32 3 658 95 59",
    "sg:postcode":"2900",
    "sg:province":"Antwerpen",
    "wof:name":"Willy Coninx",
    "wof:placetype":"venue"
},
  "geometry": {"coordinates":[4.542509079,51.27135849],"type":"Point"}
}