{
  "type": "Feature",
  "properties": {
    "iso:country":"BE",
    "sg:address":"Kemzekedorp 6",
    "sg:city":"Stekene (kemzeke)",
    "sg:classifiers":[
        {
            "category":"Bars & Pubs",
            "type":"Food & Drink"
        }
    ],
    "sg:phone":"+32 3 789 22 60",
    "sg:postcode":"9190",
    "sg:province":"Oost-Vlaanderen",
    "wof:name":"Bij Astrid",
    "wof:placetype":"venue"
},
  "geometry": {"coordinates":[4.0761609077,51.2064056396],"type":"Point"}
}