{
  "type": "Feature",
  "properties": {
    "addr:full":"All\u00e9e Le Cavalier 10 Genappe (ways) Brabant Wallon 1474",
    "addr:housenumber":"10",
    "addr:postcode":"1474",
    "addr:street":"Alle\u0301E Le Cavalier;Ways",
    "iso:country":"BE",
    "sg:address":"All\u00e9e Le Cavalier 10",
    "sg:city":"Genappe (ways)",
    "sg:classifiers":[
        {
            "category":"Building & Trades",
            "subcategory":"Landscaping Services",
            "type":"Services"
        }
    ],
    "sg:phone":"+32 67 79 03 21",
    "sg:postcode":"1474",
    "sg:province":"Brabant Wallon",
    "sg:tags":[
        "nurseryman"
    ],
    "wof:name":"Schroder D & P",
    "wof:placetype":"venue"
},
  "geometry": {"coordinates":[4.4630827904,50.6126594543],"type":"Point"}
}