{
  "type": "Feature",
  "properties": {
    "iso:country":"BE",
    "sg:address":"Rue De Bomer\u00e9e 61a",
    "sg:city":"Charleroi (mont-sur-marchienne)",
    "sg:classifiers":[
        {
            "category":"Retail",
            "subcategory":"Veterinary Services",
            "type":"Services"
        }
    ],
    "sg:phone":"+32 71 43 10 73",
    "sg:postcode":"6032",
    "sg:province":"Hainaut",
    "sg:tags":[
        "veterinarian"
    ],
    "wof:name":"Marion H",
    "wof:placetype":"venue"
},
  "geometry": {"coordinates":[4.4023828506,50.3834037781],"type":"Point"}
}