{
  "type": "Feature",
  "properties": {
    "addr:full":"Rue D'audenarde 14c Ellezelles Hainaut 7890",
    "addr:housenumber":"14c",
    "addr:postcode":"7890",
    "addr:street":"Rue D'Audenarde",
    "iso:country":"BE",
    "sg:address":"Rue D'audenarde 14c",
    "sg:city":"Ellezelles",
    "sg:classifiers":[
        {
            "category":"Insurance",
            "subcategory":"Insurance Agent",
            "type":"Services"
        }
    ],
    "sg:phone":"+32 68 54 29 00",
    "sg:postcode":"7890",
    "sg:province":"Hainaut",
    "sg:tags":[
        "broker"
    ],
    "wof:name":"Assurances Fagnard Sc",
    "wof:placetype":"venue"
},
  "geometry": {"coordinates":[3.6811800003,50.7345314026],"type":"Point"}
}