{
  "type": "Feature",
  "properties": {
    "iso:country":"BE",
    "sg:address":"Rue Chaudthier 243",
    "sg:city":"Chaudfontaine",
    "sg:classifiers":[
        {
            "category":"Insurance",
            "subcategory":"Insurance Agent",
            "type":"Services"
        }
    ],
    "sg:phone":"+32 4 367 17 50",
    "sg:postcode":"4051",
    "sg:province":"Li\u00e8ge",
    "sg:tags":[
        "verzekeringsmakelaars",
        "expert"
    ],
    "wof:name":"Michel Lecrenier",
    "wof:placetype":"venue"
},
  "geometry": {"coordinates":[5.6347718239,50.6133995056],"type":"Point"}
}