{
  "type": "Feature",
  "properties": {
    "iso:country":"BE",
    "sg:address":"Weg Nr. Ellikom 258",
    "sg:city":"Meeuwen-gruitrode (meeuwen)",
    "sg:classifiers":[
        {
            "category":"Home & Garden",
            "subcategory":"Household Appliances",
            "type":"Retail Goods"
        }
    ],
    "sg:phone":"+32 11 63 39 75",
    "sg:postcode":"3670",
    "sg:province":"Limburg",
    "sg:tags":[
        "repair",
        "mainten",
        "-",
        "electric"
    ],
    "wof:name":"Elektro Smeets-conings",
    "wof:placetype":"venue"
},
  "geometry": {"coordinates":[5.5205497742,51.0963516235],"type":"Point"}
}