{
  "type": "Feature",
  "properties": {
    "iso:country":"BE",
    "sg:address":"Kieldrechtstraat 2",
    "sg:city":"Sint-gillis-waas",
    "sg:orig_category":"Moteurs, transformateurs and groupes \u00e9lectrog\u00e8nes Fab. Entretien and r\u00e9parations de voitures. Electr",
    "sg:phone":"+32 3 707 19 51",
    "sg:postcode":"9170",
    "sg:province":"Oost-Vlaanderen",
    "wof:name":"Bracke Elektro",
    "wof:placetype":"venue"
},
  "geometry": {"coordinates":[4.090367794,51.2562561035],"type":"Point"}
}