{
  "type": "Feature",
  "properties": {
    "addr:full":"Spoorweglaan 178 Beveren Oost-Vlaanderen 9120",
    "addr:housenumber":"178",
    "addr:postcode":"9120",
    "addr:street":"Spoorweglaan",
    "iso:country":"BE",
    "sg:address":"Spoorweglaan 178",
    "sg:city":"Beveren",
    "sg:classifiers":[
        {
            "category":"Personal",
            "subcategory":"Beauty Salon",
            "type":"Services"
        }
    ],
    "sg:phone":"+32 3 775 85 92",
    "sg:postcode":"9120",
    "sg:province":"Oost-Vlaanderen",
    "sg:tags":[
        "de",
        "coiffure"
    ],
    "wof:name":"R. De Coninck",
    "wof:placetype":"venue"
},
  "geometry": {"coordinates":[4.2834701538,51.2126922607],"type":"Point"}
}