{
  "type": "Feature",
  "properties": {
    "addr:full":"Rue Du Centenaire 17 Erquelinnes Hainaut 6560",
    "addr:housenumber":"17",
    "addr:postcode":"6560",
    "addr:street":"Rue Du Centenaire",
    "iso:country":"BE",
    "sg:address":"Rue Du Centenaire 17",
    "sg:city":"Erquelinnes",
    "sg:orig_category":"Enseignement maternel and primaire",
    "sg:phone":"+32 64 77 17 26",
    "sg:postcode":"6560",
    "sg:province":"Hainaut",
    "wof:name":"Ecole Fond. Communale",
    "wof:placetype":"venue"
},
  "geometry": {"coordinates":[4.06939888,50.3284950256],"type":"Point"}
}