{
  "type": "Feature",
  "properties": {
    "iso:country":"BE",
    "sg:address":"Rue Sylvain Guyaux 43",
    "sg:city":"La Louvi\u00e8re",
    "sg:classifiers":[
        {
            "category":"Shopping",
            "subcategory":"Clothing, Apparel, & Fashions",
            "type":"Retail Goods"
        }
    ],
    "sg:phone":"+32 64 84 86 80",
    "sg:postcode":"7100",
    "sg:province":"Hainaut",
    "sg:tags":[
        "boutique"
    ],
    "wof:name":"Vice Versa",
    "wof:placetype":"venue"
},
  "geometry": {"coordinates":[4.1839971542,50.4755706787],"type":"Point"}
}