{
  "type": "Feature",
  "properties": {
    "addr:full":"Goethalsplaats 15 Meulebeke West-Vlaanderen 8760",
    "addr:housenumber":"15",
    "addr:postcode":"8760",
    "addr:street":"Goethalsplaats",
    "iso:country":"BE",
    "sg:address":"Goethalsplaats 15",
    "sg:city":"Meulebeke",
    "sg:orig_category":"Epiceries",
    "sg:phone":"+32 51 48 85 77",
    "sg:postcode":"8760",
    "sg:province":"West-Vlaanderen",
    "wof:name":"Spar",
    "wof:placetype":"venue"
},
  "geometry": {"coordinates":[3.2869560719,50.9506645203],"type":"Point"}
}