{
  "type": "Feature",
  "properties": {
    "addr:full":"Stenebrugstraat 72 Ternat (wambeek) Vlaams-Brabant 1741",
    "addr:housenumber":"72",
    "addr:postcode":"1741",
    "addr:street":"Stenebrugstraat",
    "iso:country":"BE",
    "sg:address":"Stenebrugstraat 72",
    "sg:city":"Ternat (wambeek)",
    "sg:classifiers":[
        {
            "category":"Home & Garden",
            "subcategory":"Household Appliances",
            "type":"Retail Goods"
        }
    ],
    "sg:phone":"+32 2 582 26 46",
    "sg:postcode":"1741",
    "sg:province":"Vlaams-Brabant",
    "sg:tags":[
        "repair",
        "mainten",
        "-",
        "electric"
    ],
    "wof:name":"Van Den Bossche O",
    "wof:placetype":"venue"
},
  "geometry": {"coordinates":[4.1545982361,50.855381012],"type":"Point"}
}