{
  "type": "Feature",
  "properties": {
    "addr:full":"Avenue Henri Jaspar 125 Sint-gillis/saint-gilles Bruxelles-Capitale 1060",
    "addr:housenumber":"125",
    "addr:postcode":"1060",
    "addr:street":"Avenue Henri Jaspar",
    "iso:country":"BE",
    "sg:address":"Avenue Henri Jaspar 125",
    "sg:city":"Sint-gillis/saint-gilles",
    "sg:orig_category":"M\u00e9decins and sp\u00e9cialistes",
    "sg:phone":"+32 2 537 74 89",
    "sg:postcode":"1060",
    "sg:province":"Bruxelles-Capitale",
    "wof:name":"R. Goffin",
    "wof:placetype":"venue"
},
  "geometry": {"coordinates":[4.3465561867,50.8325195312],"type":"Point"}
}