{
  "type": "Feature",
  "properties": {
    "iso:country":"BE",
    "sg:address":"Rue De Tilff - Centre Commercial Gb",
    "sg:city":"Boncelles",
    "sg:orig_category":"Marca. V\u00eatements pour b\u00e9b\u00e9s and enfants. V\u00eatements pour Dames. V\u00eatements pour Hommes",
    "sg:phone":"+32 4 336 89 81",
    "sg:postcode":"4100",
    "sg:province":"Li\u00e8ge",
    "wof:name":"Marca Boncelles",
    "wof:placetype":"venue"
},
  "geometry": {"coordinates":[5.5135030746,50.6105766296],"type":"Point"}
}