{
  "type": "Feature",
  "properties": {
    "iso:country":"BE",
    "sg:address":"Chauss\u00c9e De Dinant 145",
    "sg:city":"Profondeville",
    "sg:classifiers":[
        {
            "category":"Cafe",
            "type":"Food & Drink"
        }
    ],
    "sg:phone":"+32 81 41 46 47",
    "sg:postcode":"5170",
    "sg:province":"Namur",
    "sg:tags":[
        "caf\u00e9s"
    ],
    "wof:name":"Isabelle Daxhelet",
    "wof:placetype":"venue"
},
  "geometry": {"coordinates":[4.8701601028,50.3611717224],"type":"Point"}
}