{
  "type": "Feature",
  "properties": {
    "addr:full":"Gillegomstraat 34 Boechout Antwerpen 2530",
    "addr:housenumber":"34",
    "addr:postcode":"2530",
    "addr:street":"Gillegomstraat",
    "iso:country":"BE",
    "sg:address":"Gillegomstraat 34",
    "sg:city":"Boechout",
    "sg:classifiers":[
        {
            "category":"Building & Trades",
            "subcategory":"Electrical",
            "type":"Services"
        }
    ],
    "sg:phone":"+32 3 455 01 20",
    "sg:postcode":"2530",
    "sg:province":"Antwerpen",
    "sg:tags":[
        "electric",
        "-",
        "housewiring",
        "contractor"
    ],
    "wof:name":"Helimex V.m. Bvba",
    "wof:placetype":"venue"
},
  "geometry": {"coordinates":[4.4989209175,51.1666069031],"type":"Point"}
}