{
  "type": "Feature",
  "properties": {
    "iso:country":"BE",
    "sg:address":"Burggravenlaan 10",
    "sg:city":"Evergem",
    "sg:classifiers":[
        {
            "category":"Restaurant",
            "type":"Food & Drink"
        }
    ],
    "sg:phone":"+32 9 258 03 10",
    "sg:postcode":"9940",
    "sg:province":"Oost-Vlaanderen",
    "wof:name":"De Esdoorn",
    "wof:placetype":"venue"
},
  "geometry": {"coordinates":[3.7397389412,51.1168632507],"type":"Point"}
}