{
  "type": "Feature",
  "properties": {
    "addr:full":"Mechelsesteenweg 107 Antwerpen Antwerpen 2018",
    "addr:housenumber":"107",
    "addr:postcode":"2018",
    "addr:street":"Mechelsesteenweg",
    "iso:country":"BE",
    "sg:address":"Mechelsesteenweg 107",
    "sg:city":"Antwerpen",
    "sg:orig_category":"Textiel",
    "sg:phone":"+32 3 230 29 40",
    "sg:postcode":"2018",
    "sg:province":"Antwerpen",
    "wof:name":"Huis Van Sittert",
    "wof:placetype":"venue"
},
  "geometry": {"coordinates":[4.410033226,51.206817627],"type":"Point"}
}