{
  "type": "Feature",
  "properties": {
    "iso:country":"BE",
    "sg:address":"Clos Des Trotteurs 2",
    "sg:city":"Wezembeek-oppem",
    "sg:classifiers":[
        {
            "category":"Health Services",
            "subcategory":"Health Practitioner",
            "type":"Services"
        }
    ],
    "sg:phone":"+32 2 731 09 97",
    "sg:postcode":"1970",
    "sg:province":"Vlaams-Brabant",
    "sg:tags":[
        "physiotherapist"
    ],
    "wof:name":"Plas Marie-claire",
    "wof:placetype":"venue"
},
  "geometry": {"coordinates":[4.5001020432,50.8545303345],"type":"Point"}
}