{
  "type": "Feature",
  "properties": {
    "iso:country":"BE",
    "sg:address":"Gaston Roelandtsstraat 46",
    "sg:city":"Oostkamp",
    "sg:classifiers":[
        {
            "category":"Retail",
            "subcategory":"Auto Repair",
            "type":"Services"
        }
    ],
    "sg:phone":"+32 50 39 39 44",
    "sg:postcode":"8020",
    "sg:province":"West-Vlaanderen",
    "sg:tags":[
        "garage"
    ],
    "wof:name":"Lebbe C",
    "wof:placetype":"venue"
},
  "geometry": {"coordinates":[3.2338609695,51.1770782471],"type":"Point"}
}