{
  "type": "Feature",
  "properties": {
    "addr:full":"Rue De L'eglise 163 Amel/ambleve Li\u00e8ge 4770",
    "addr:housenumber":"163",
    "addr:postcode":"4770",
    "addr:street":"Rue De L'Eglise",
    "iso:country":"BE",
    "sg:address":"Rue De L'eglise 163",
    "sg:city":"Amel/ambleve",
    "sg:orig_category":"Epiceries",
    "sg:phone":"+32 80 34 90 36",
    "sg:postcode":"4770",
    "sg:province":"Li\u00e8ge",
    "wof:name":"Petra Heinen",
    "wof:placetype":"venue"
},
  "geometry": {"coordinates":[6.1777601242,50.3447608948],"type":"Point"}
}