{
  "type": "Feature",
  "properties": {
    "iso:country":"BE",
    "sg:address":"Ketsstraat 17",
    "sg:city":"Antwerpen",
    "sg:classifiers":[
        {
            "category":"Health Services",
            "subcategory":"Hospital",
            "type":"Services"
        }
    ],
    "sg:phone":"+32 3 235 21 74",
    "sg:postcode":"2018",
    "sg:province":"Antwerpen",
    "wof:name":"Vagga Vzw - Vestiging Altox",
    "wof:placetype":"venue"
},
  "geometry": {"coordinates":[4.4266529083,51.214805603],"type":"Point"}
}