{
  "type": "Feature",
  "properties": {
    "addr:full":"Oudenaardsestraat 91 Geraardsbergen Oost-Vlaanderen 9500",
    "addr:housenumber":"91",
    "addr:postcode":"9500",
    "addr:street":"Oudenaardsestraat",
    "iso:country":"BE",
    "sg:address":"Oudenaardsestraat 91",
    "sg:city":"Geraardsbergen",
    "sg:classifiers":[
        {
            "category":"Personal",
            "subcategory":"Beauty Salon",
            "type":"Services"
        }
    ],
    "sg:phone":"+32 54 41 58 89",
    "sg:postcode":"9500",
    "sg:province":"Oost-Vlaanderen",
    "sg:tags":[
        "de",
        "coiffure"
    ],
    "wof:name":"Coiffure Carine",
    "wof:placetype":"venue"
},
  "geometry": {"coordinates":[3.8709609509,50.7725296021],"type":"Point"}
}