{
  "type": "Feature",
  "properties": {
    "iso:country":"BE",
    "sg:address":"Bollestraat 16",
    "sg:city":"Hooglede",
    "sg:orig_category":"Groententeelt",
    "sg:phone":"+32 51 72 24 81",
    "sg:postcode":"8830",
    "sg:province":"West-Vlaanderen",
    "wof:name":"Willy Hostens",
    "wof:placetype":"venue"
},
  "geometry": {"coordinates":[3.120732069,51.0025367737],"type":"Point"}
}