{
  "type": "Feature",
  "properties": {
    "iso:country":"BE",
    "sg:address":"Avenue De L'industrie 24",
    "sg:city":"Huy (tihange)",
    "sg:classifiers":[
        {
            "category":"Retail",
            "subcategory":"Auto Repair",
            "type":"Services"
        }
    ],
    "sg:phone":"+32 85 23 69 00",
    "sg:postcode":"4500",
    "sg:province":"Li\u00e8ge",
    "sg:tags":[
        "garage"
    ],
    "wof:name":"Mercedes-centretoile",
    "wof:placetype":"venue"
},
  "geometry": {"coordinates":[5.261300087,50.5341072083],"type":"Point"}
}