{
  "type": "Feature",
  "properties": {
    "addr:full":"Place Bonne-nouvelle 3 Li\u00c8ge Li\u00e8ge 4000",
    "addr:housenumber":"3",
    "addr:postcode":"4000",
    "addr:street":"Place Bonne-Nouvelle",
    "iso:country":"BE",
    "sg:address":"Place Bonne-nouvelle 3",
    "sg:city":"Li\u00c8ge",
    "sg:orig_category":"Journaux. Tabac. Librairies",
    "sg:phone":"+32 4 227 67 17",
    "sg:postcode":"4000",
    "sg:province":"Li\u00e8ge",
    "wof:name":"Les Bonnes Nouvelles",
    "wof:placetype":"venue"
},
  "geometry": {"coordinates":[5.595831871,50.6522102356],"type":"Point"}
}