{
  "type": "Feature",
  "properties": {
    "iso:country":"BE",
    "sg:address":"Brusselsesteenweg 71a",
    "sg:city":"Tervuren",
    "sg:classifiers":[
        {
            "category":"Professional",
            "subcategory":"Management & Consulting",
            "type":"Services"
        }
    ],
    "sg:phone":"+32 2 768 05 00",
    "sg:postcode":"3080",
    "sg:province":"Vlaams-Brabant",
    "sg:tags":[
        "marketing",
        "-",
        "consultant"
    ],
    "wof:name":"Linx Bvba",
    "wof:placetype":"venue"
},
  "geometry": {"coordinates":[4.5083231926,50.8244018555],"type":"Point"}
}