{
  "type": "Feature",
  "properties": {
    "addr:full":"Chauss\u00e9e De Marche 601 Namur (erpent) Namur 5101",
    "addr:housenumber":"601",
    "addr:postcode":"5101",
    "addr:street":"Chausse\u0301E De Marche",
    "iso:country":"BE",
    "sg:address":"Chauss\u00e9e De Marche 601",
    "sg:city":"Namur (erpent)",
    "sg:classifiers":[
        {
            "category":"Retail",
            "subcategory":"Auto Repair",
            "type":"Services"
        }
    ],
    "sg:phone":"+32 81 31 13 70",
    "sg:postcode":"5101",
    "sg:province":"Namur",
    "sg:tags":[
        "automobile-body"
    ],
    "wof:name":"Carrosserie Evrard Eric Sprl",
    "wof:placetype":"venue"
},
  "geometry": {"coordinates":[4.9087619781,50.4395065308],"type":"Point"}
}