{
  "type": "Feature",
  "properties": {
    "iso:country":"BE",
    "sg:address":"Berchemstraat 123",
    "sg:city":"Kluisbergen (berchem)",
    "sg:classifiers":[
        {
            "category":"Building & Trades",
            "subcategory":"Construction",
            "type":"Services"
        }
    ],
    "sg:phone":"+32 55 39 01 61",
    "sg:postcode":"9690",
    "sg:province":"Oost-Vlaanderen",
    "sg:tags":[
        "stair"
    ],
    "wof:name":"Coorevits Bvba",
    "wof:placetype":"venue"
},
  "geometry": {"coordinates":[3.5165669918,50.7926673889],"type":"Point"}
}