{
  "type": "Feature",
  "properties": {
    "addr:full":"Hendrik Consciencestraat 41 Knokke-heist West-Vlaanderen 8301",
    "addr:housenumber":"41",
    "addr:postcode":"8301",
    "addr:street":"Hendrik Consciencestraat",
    "iso:country":"BE",
    "sg:address":"Hendrik Consciencestraat 41",
    "sg:city":"Knokke-heist",
    "sg:classifiers":[
        {
            "category":"Home & Garden",
            "subcategory":"Hardware",
            "type":"Retail Goods"
        }
    ],
    "sg:phone":"+32 50 51 15 53",
    "sg:postcode":"8301",
    "sg:province":"West-Vlaanderen",
    "sg:tags":[
        "quincailleries",
        "bois",
        "gr"
    ],
    "wof:name":"Hubo",
    "wof:placetype":"venue"
},
  "geometry": {"coordinates":[3.2639000416,51.3396911621],"type":"Point"}
}