{
  "type": "Feature",
  "properties": {
    "addr:full":"Rue Insebois 15 Mettet (biesme) Namur 5640",
    "addr:housenumber":"15",
    "addr:postcode":"5640",
    "addr:street":"Rue Insebois;Biesme",
    "iso:country":"BE",
    "sg:address":"Rue Insebois 15",
    "sg:city":"Mettet (biesme)",
    "sg:orig_category":"Non-Classified Establishments",
    "sg:phone":"+32 71 72 51 14",
    "sg:postcode":"5640",
    "sg:province":"Namur",
    "wof:name":"Aquascience",
    "wof:placetype":"venue"
},
  "geometry": {"coordinates":[4.6578397751,50.3198051453],"type":"Point"}
}