{
  "type": "Feature",
  "properties": {
    "addr:full":"Adhemar Borinstraat 59 Zwijndrecht Antwerpen 2070",
    "addr:housenumber":"59",
    "addr:postcode":"2070",
    "addr:street":"Borinstraat",
    "iso:country":"BE",
    "sg:address":"Adhemar Borinstraat 59",
    "sg:city":"Zwijndrecht",
    "sg:orig_category":"Instituts de beaut\u00e9",
    "sg:phone":"+32 3 252 80 57",
    "sg:postcode":"2070",
    "sg:province":"Antwerpen",
    "wof:name":"Marleen Van Duyse",
    "wof:placetype":"venue"
},
  "geometry": {"coordinates":[4.3233261108,51.2163696289],"type":"Point"}
}