{
  "type": "Feature",
  "properties": {
    "addr:full":"Nieuwe Steenweg 4 Asse Vlaams-Brabant 1731",
    "addr:housenumber":"4",
    "addr:postcode":"1731",
    "addr:street":"Nieuwe Steenweg",
    "iso:country":"BE",
    "sg:address":"Nieuwe Steenweg 4",
    "sg:city":"Asse",
    "sg:orig_category":"Installation de serres, double vitrage and fen\u00eatres. Installation de menuiserie en bois and plastiqu",
    "sg:phone":"+32 2 466 40 17",
    "sg:postcode":"1731",
    "sg:province":"Vlaams-Brabant",
    "wof:name":"Aluplastics",
    "wof:placetype":"venue"
},
  "geometry": {"coordinates":[4.1990671158,50.9108657837],"type":"Point"}
}