{
  "type": "Feature",
  "properties": {
    "addr:full":"Dr Haekstr 50 Grembergen Oost-Vlaanderen 9150",
    "addr:housenumber":"50",
    "addr:postcode":"9150",
    "addr:street":"Oost-Vlaanderen",
    "iso:country":"BE",
    "sg:address":"Dr Haekstr 50",
    "sg:city":"Grembergen",
    "sg:classifiers":[
        {
            "category":"Banks & Credit Unions",
            "subcategory":"Bank",
            "type":"Services"
        }
    ],
    "sg:phone":"+32 52 21 91 91",
    "sg:postcode":"9150",
    "sg:province":"Oost-Vlaanderen",
    "wof:name":"Aslk-cger Bank",
    "wof:placetype":"venue"
},
  "geometry": {"coordinates":[4.431883812,51.2060203552],"type":"Point"}
}