{
  "type": "Feature",
  "properties": {
    "iso:country":"BE",
    "sg:address":"Sint-pieterskaai 40",
    "sg:city":"Brugge",
    "sg:classifiers":[
        {
            "category":"Communications",
            "subcategory":"Newspaper",
            "type":"Services"
        }
    ],
    "sg:phone":"+32 50 31 61 65",
    "sg:postcode":"8000",
    "sg:province":"West-Vlaanderen",
    "sg:tags":[
        "paper",
        "local",
        "free"
    ],
    "wof:name":"Publishop Bvba",
    "wof:placetype":"venue"
},
  "geometry": {"coordinates":[3.2168359756,51.222568512],"type":"Point"}
}