{
  "type": "Feature",
  "properties": {
    "addr:full":"Rode-rokstraat 100 Hasselt (kuringen) Limburg 3511",
    "addr:housenumber":"100",
    "addr:postcode":"3511",
    "iso:country":"BE",
    "sg:address":"Rode-rokstraat 100",
    "sg:city":"Hasselt (kuringen)",
    "sg:classifiers":[
        {
            "category":"Building & Trades",
            "subcategory":"Landscaping Services",
            "type":"Services"
        }
    ],
    "sg:phone":"+32 11 87 12 33",
    "sg:postcode":"3511",
    "sg:province":"Limburg",
    "sg:tags":[
        "-",
        "lopping",
        "work",
        "tree",
        "felling"
    ],
    "wof:name":"Schouterden S",
    "wof:placetype":"venue"
},
  "geometry": {"coordinates":[5.2979950905,50.948184967],"type":"Point"}
}