{
  "type": "Feature",
  "properties": {
    "iso:country":"BE",
    "sg:address":"Rue De Jollain 26",
    "sg:city":"Brunehaut",
    "sg:classifiers":[
        {
            "category":"Cafe",
            "type":"Food & Drink"
        }
    ],
    "sg:phone":"+32 69 34 45 36",
    "sg:postcode":"7620",
    "sg:province":"Hainaut",
    "sg:tags":[
        "caf\u00e9s"
    ],
    "wof:name":"Caf\u00c9 Chez Cecile",
    "wof:placetype":"venue"
},
  "geometry": {"coordinates":[3.4150800705,50.5410194397],"type":"Point"}
}