{
  "type": "Feature",
  "properties": {
    "addr:full":"Rue Alnoir 1 Jemeppe-sur-sambre Namur 5190",
    "addr:housenumber":"1",
    "addr:postcode":"5190",
    "addr:street":"Rue Alnoir",
    "iso:country":"BE",
    "sg:address":"Rue Alnoir 1",
    "sg:city":"Jemeppe-sur-sambre",
    "sg:classifiers":[
        {
            "category":"Professional",
            "subcategory":"Management & Consulting",
            "type":"Services"
        }
    ],
    "sg:phone":"+32 71 78 97 89",
    "sg:postcode":"5190",
    "sg:province":"Namur",
    "sg:tags":[
        "consultant",
        "law"
    ],
    "wof:name":"Cabinet Juridique M-v",
    "wof:placetype":"venue"
},
  "geometry": {"coordinates":[4.6647639275,50.4687957764],"type":"Point"}
}