{
  "type": "Feature",
  "properties": {
    "addr:full":"Bruggestraat 512 Menen West-Vlaanderen 8930",
    "addr:housenumber":"512",
    "addr:postcode":"8930",
    "addr:street":"Bruggestraat",
    "iso:country":"BE",
    "sg:address":"Bruggestraat 512",
    "sg:city":"Menen",
    "sg:classifiers":[
        {
            "category":"Freight",
            "type":"Transportation"
        }
    ],
    "sg:phone":"+32 56 51 33 74",
    "sg:postcode":"8930",
    "sg:province":"West-Vlaanderen",
    "sg:tags":[
        "-",
        "transport"
    ],
    "wof:name":"Debels R",
    "wof:placetype":"venue"
},
  "geometry": {"coordinates":[3.1214671135,50.8107032776],"type":"Point"}
}