{
  "type": "Feature",
  "properties": {
    "addr:full":"Rue Lebeau 39 Bruxelles Bruxelles-Capitale 1000",
    "addr:housenumber":"39",
    "addr:postcode":"1000",
    "addr:street":"Rue Lebeau",
    "iso:country":"BE",
    "sg:address":"Rue Lebeau 39",
    "sg:city":"Bruxelles",
    "sg:classifiers":[
        {
            "category":"Organizations",
            "subcategory":"Community Association",
            "type":"Services"
        }
    ],
    "sg:phone":"+32 2 502 56 49",
    "sg:postcode":"1000",
    "sg:province":"Bruxelles-Capitale",
    "sg:tags":[
        "cultural"
    ],
    "wof:name":"Maison Des Musiques",
    "wof:placetype":"venue"
},
  "geometry": {"coordinates":[4.3539638519,50.8424682617],"type":"Point"}
}