{
  "type": "Feature",
  "properties": {
    "addr:full":". Borgloon (groot) Limburg 3840",
    "addr:postcode":"3840",
    "addr:street":"Groot Limburg",
    "iso:country":"BE",
    "sg:address":".",
    "sg:city":"Borgloon (groot)",
    "sg:orig_category":"Apotheken",
    "sg:phone":"+32 900 10 500",
    "sg:postcode":"3840",
    "sg:province":"Limburg",
    "wof:name":"Apothekers Van Wacht",
    "wof:placetype":"venue"
},
  "geometry": {"coordinates":[5.3441700935,50.8012466431],"type":"Point"}
}