{
  "type": "Feature",
  "properties": {
    "addr:full":"Constant Verhulststraat 29 Berlaar Antwerpen 2590",
    "addr:housenumber":"29",
    "addr:postcode":"2590",
    "addr:street":"Constant Verhulststraat",
    "iso:country":"BE",
    "sg:address":"Constant Verhulststraat 29",
    "sg:city":"Berlaar",
    "sg:orig_category":"Pleisterwerk",
    "sg:phone":"+32 3 482 27 49",
    "sg:postcode":"2590",
    "sg:province":"Antwerpen",
    "wof:name":"Thijs Gebroeders",
    "wof:placetype":"venue"
},
  "geometry": {"coordinates":[4.6695709229,51.1146316528],"type":"Point"}
}