{
  "type": "Feature",
  "properties": {
    "iso:country":"BE",
    "sg:address":"Maastrichtersteenweg 29-31",
    "sg:city":"Tongeren",
    "sg:classifiers":[
        {
            "category":"Wholesale",
            "subcategory":"Books, Periodicals, & Newspapers",
            "type":"Manufacturing & Wholesale Goods"
        }
    ],
    "sg:phone":"+32 12 45 87 92",
    "sg:postcode":"3700",
    "sg:province":"Limburg",
    "sg:tags":[
        "publisher"
    ],
    "wof:name":"Neghuy & Co",
    "wof:placetype":"venue"
},
  "geometry": {"coordinates":[5.474506855,50.7838401794],"type":"Point"}
}