{
  "type": "Feature",
  "properties": {
    "iso:country":"BE",
    "sg:address":"Socialestraat 6",
    "sg:city":"Genk",
    "sg:orig_category":"Artsen and specialisten",
    "sg:phone":"+32 89 38 21 35",
    "sg:postcode":"3600",
    "sg:province":"Limburg",
    "wof:name":"Buurtgezondheidscentrum",
    "wof:placetype":"venue"
},
  "geometry": {"coordinates":[5.5094079971,51.0119476318],"type":"Point"}
}