{
  "type": "Feature",
  "properties": {
    "iso:country":"BE",
    "sg:address":"Firmin Lecharlierlaan 35",
    "sg:city":"Jette/jette",
    "sg:orig_category":"Woningbouw",
    "sg:phone":"+32 2 425 61 10",
    "sg:postcode":"1090",
    "sg:province":"Bruxelles-Capitale",
    "wof:name":"Entr. Watticant Et Fils",
    "wof:placetype":"venue"
},
  "geometry": {"coordinates":[4.329518795,50.8716125488],"type":"Point"}
}