{
  "type": "Feature",
  "properties": {
    "iso:country":"BE",
    "sg:address":"Leegaardsdijk 8",
    "sg:city":"Oostende",
    "sg:classifiers":[
        {
            "category":"Government",
            "subcategory":"Fire Station",
            "type":"Public Place"
        }
    ],
    "sg:phone":"+32 59 80 04 07",
    "sg:postcode":"8400",
    "sg:province":"West-Vlaanderen",
    "sg:tags":[
        "leather",
        "watch",
        "strap"
    ],
    "wof:name":"Lic Nv",
    "wof:placetype":"venue"
},
  "geometry": {"coordinates":[2.9477980137,51.211643219],"type":"Point"}
}