{
  "type": "Feature",
  "properties": {
    "addr:full":"Avenue Carton De Wiart 128 Bruxelles (jette) Bruxelles-Capitale 1090",
    "addr:housenumber":"128",
    "addr:postcode":"1090",
    "addr:street":"Avenue Carton De Wiart",
    "iso:country":"BE",
    "sg:address":"Avenue Carton De Wiart 128",
    "sg:city":"Bruxelles (jette)",
    "sg:classifiers":[
        {
            "category":"Professional",
            "subcategory":"Computer Services",
            "type":"Services"
        }
    ],
    "sg:phone":"+32 2 421 45 11",
    "sg:postcode":"1090",
    "sg:province":"Bruxelles-Capitale",
    "sg:tags":[
        "-",
        "processing",
        "data",
        "software"
    ],
    "wof:name":"Gfdi Asbl",
    "wof:placetype":"venue"
},
  "geometry": {"coordinates":[4.3283901215,50.8675231934],"type":"Point"}
}