{
  "type": "Feature",
  "properties": {
    "addr:full":"Rosi\u00c8re-la-grande 75 Vaux-sur-sure Luxembourg 6640",
    "addr:housenumber":"75",
    "addr:postcode":"6640",
    "addr:street":"Rosie\u0300Re-La-Grande",
    "iso:country":"BE",
    "sg:address":"Rosi\u00c8re-la-grande 75",
    "sg:city":"Vaux-sur-sure",
    "sg:orig_category":"Eleveurs de bovins",
    "sg:phone":"+32 61 26 62 85",
    "sg:postcode":"6640",
    "sg:province":"Luxembourg",
    "wof:name":"Ghislain Chenot",
    "wof:placetype":"venue"
},
  "geometry": {"coordinates":[5.5719690323,49.925365448],"type":"Point"}
}