{
  "type": "Feature",
  "properties": {
    "addr:full":"Rue Du Tilleul 325 Bruxelles (evere) Bruxelles-Capitale 1140",
    "addr:housenumber":"325",
    "addr:postcode":"1140",
    "addr:street":"Rue Du Tilleul",
    "iso:country":"BE",
    "sg:address":"Rue Du Tilleul 325",
    "sg:city":"Bruxelles (evere)",
    "sg:classifiers":[
        {
            "category":"Bakery",
            "type":"Food & Drink"
        }
    ],
    "sg:phone":"+32 2 215 42 62",
    "sg:postcode":"1140",
    "sg:province":"Bruxelles-Capitale",
    "sg:tags":[
        "confectioner",
        "baker"
    ],
    "wof:name":"Patisserie Martin",
    "wof:placetype":"venue"
},
  "geometry": {"coordinates":[4.3959851265,50.8693237305],"type":"Point"}
}