{
  "type": "Feature",
  "properties": {
    "addr:full":"Konkelstraat 174 Sint-lambrechts-woluwe/woluwe-saint-lambert Bruxelles-Capitale 1200",
    "addr:housenumber":"174;/",
    "addr:postcode":"1200",
    "addr:street":"Konkelstraat;Sint-Lambrechts-Woluwe",
    "iso:country":"BE",
    "sg:address":"Konkelstraat 174",
    "sg:city":"Sint-lambrechts-woluwe/woluwe-saint-lambert",
    "sg:orig_category":"Artiesten and kunstenaars",
    "sg:phone":"+32 2 772 31 14",
    "sg:postcode":"1200",
    "sg:province":"Bruxelles-Capitale",
    "wof:name":"Brigitte Geerinckx",
    "wof:placetype":"venue"
},
  "geometry": {"coordinates":[4.4454011917,50.8387489319],"type":"Point"}
}