{
  "type": "Feature",
  "properties": {
    "iso:country":"BE",
    "sg:address":"Schopstraat 40",
    "sg:city":"Herk-de-stad",
    "sg:classifiers":[
        {
            "category":"Personal",
            "subcategory":"Beauty Salon",
            "type":"Services"
        }
    ],
    "sg:phone":"+32 13 55 34 28",
    "sg:postcode":"3540",
    "sg:province":"Limburg",
    "sg:tags":[
        "de",
        "coiffure"
    ],
    "wof:name":"Valere Reekmans",
    "wof:placetype":"venue"
},
  "geometry": {"coordinates":[5.1928710938,50.9066963196],"type":"Point"}
}