{
  "type": "Feature",
  "properties": {
    "addr:full":"Chauss\u00c9e De Charleroi 81 Sint-gillis/saint-gilles Bruxelles-Capitale 1060",
    "addr:housenumber":"81",
    "addr:postcode":"1060",
    "addr:street":"Chausse\u0301E De Charleroi",
    "iso:country":"BE",
    "sg:address":"Chauss\u00c9e De Charleroi 81",
    "sg:city":"Sint-gillis/saint-gilles",
    "sg:orig_category":"Enseignement maternel and primaire",
    "sg:phone":"+32 2 538 54 52",
    "sg:postcode":"1060",
    "sg:province":"Bruxelles-Capitale",
    "wof:name":"Basisschool",
    "wof:placetype":"venue"
},
  "geometry": {"coordinates":[4.3559651375,50.8306922913],"type":"Point"}
}