{
  "type": "Feature",
  "properties": {
    "addr:full":"Rue Jean Lorette 16 Pont-a-celles Hainaut 6230",
    "addr:housenumber":"16",
    "addr:postcode":"6230",
    "addr:street":"Rue Jean Lorette",
    "iso:country":"BE",
    "sg:address":"Rue Jean Lorette 16",
    "sg:city":"Pont-a-celles",
    "sg:orig_category":"Sportclubs",
    "sg:phone":"+32 71 35 40 76",
    "sg:postcode":"6230",
    "sg:province":"Hainaut",
    "wof:name":"Roman V.c. Arquennes",
    "wof:placetype":"venue"
},
  "geometry": {"coordinates":[4.429336071,50.4874229431],"type":"Point"}
}