{
  "type": "Feature",
  "properties": {
    "addr:full":"Burg.chalmetlaan 62 Zelzate Oost-Vlaanderen 9060",
    "addr:housenumber":"62",
    "addr:postcode":"9060",
    "addr:street":"Burg.Chalmetlaan",
    "iso:country":"BE",
    "sg:address":"Burg.chalmetlaan 62",
    "sg:city":"Zelzate",
    "sg:orig_category":"Advocaten and juridische adviseurs Balie van Gent",
    "sg:phone":"+32 9 345 51 70",
    "sg:postcode":"9060",
    "sg:province":"Oost-Vlaanderen",
    "wof:name":"Delmeire Guy",
    "wof:placetype":"venue"
},
  "geometry": {"coordinates":[3.8182880878,51.1962394714],"type":"Point"}
}