{
  "type": "Feature",
  "properties": {
    "addr:full":"Hazepad 6 Rotselaar Vlaams-Brabant 3118",
    "addr:housenumber":"6",
    "addr:postcode":"3118",
    "addr:street":"Hazepad",
    "iso:country":"BE",
    "sg:address":"Hazepad 6",
    "sg:city":"Rotselaar",
    "sg:orig_category":"Centres de relaxation and bien-\u00eatre. Instituts de beaut\u00e9",
    "sg:phone":"+32 16 60 48 68",
    "sg:postcode":"3118",
    "sg:province":"Vlaams-Brabant",
    "wof:name":"Lutgarde De Ryck",
    "wof:placetype":"venue"
},
  "geometry": {"coordinates":[4.6940898895,50.970489502],"type":"Point"}
}