{
  "type": "Feature",
  "properties": {
    "iso:country":"BE",
    "sg:address":"Hoogstraat 22",
    "sg:city":"Antwerpen",
    "sg:classifiers":[
        {
            "category":"Bars & Pubs",
            "type":"Food & Drink"
        }
    ],
    "sg:phone":"+32 3 231 34 48",
    "sg:postcode":"2000",
    "sg:province":"Antwerpen",
    "wof:name":"Billekletser (den)",
    "wof:placetype":"venue"
},
  "geometry": {"coordinates":[4.3986711502,51.220287323],"type":"Point"}
}