{
  "type": "Feature",
  "properties": {
    "iso:country":"BE",
    "sg:address":"Rue De L'institut 209",
    "sg:city":"Blegny",
    "sg:orig_category":"Kapsalons",
    "sg:phone":"+32 4 387 72 08",
    "sg:postcode":"4670",
    "sg:province":"Li\u00e8ge",
    "wof:name":"Infantino Croce",
    "wof:placetype":"venue"
},
  "geometry": {"coordinates":[5.7149181366,50.6777153015],"type":"Point"}
}