{
  "type": "Feature",
  "properties": {
    "iso:country":"BE",
    "sg:address":"Kerkstraat 3",
    "sg:city":"Herent (veltem-beisem)",
    "sg:classifiers":[
        {
            "category":"Shopping",
            "subcategory":"Jewelry",
            "type":"Retail Goods"
        }
    ],
    "sg:phone":"+32 16 48 06 10",
    "sg:postcode":"3020",
    "sg:province":"Vlaams-Brabant",
    "sg:tags":[
        "-",
        "imitation"
    ],
    "wof:name":"Audenaert D",
    "wof:placetype":"venue"
},
  "geometry": {"coordinates":[4.6697502136,50.9095497131],"type":"Point"}
}