{
  "type": "Feature",
  "properties": {
    "iso:country":"BE",
    "sg:address":"Spiedamstraat 26",
    "sg:city":"Evergem",
    "sg:orig_category":"Installation \u00e9lectrique r\u00e9sidentielle",
    "sg:phone":"+32 9 344 42 00",
    "sg:postcode":"9940",
    "sg:province":"Oost-Vlaanderen",
    "wof:name":"Patrick Baeke",
    "wof:placetype":"venue"
},
  "geometry": {"coordinates":[3.7681269646,51.1711044312],"type":"Point"}
}