{
  "type": "Feature",
  "properties": {
    "iso:country":"BE",
    "sg:address":"Aalstersesteenweg 304",
    "sg:city":"Ninove",
    "sg:classifiers":[
        {
            "category":"Real Estate",
            "subcategory":"Architect",
            "type":"Services"
        }
    ],
    "sg:phone":"+32 54 33 63 98",
    "sg:postcode":"9400",
    "sg:province":"Oost-Vlaanderen",
    "wof:name":"De Nutte N",
    "wof:placetype":"venue"
},
  "geometry": {"coordinates":[4.0331411362,50.8517341614],"type":"Point"}
}