{
  "type": "Feature",
  "properties": {
    "iso:country":"BE",
    "sg:address":"Stationsstraat 36",
    "sg:city":"Nevele",
    "sg:orig_category":"Maroquinerie and articles de voyage. Emballages en plastique Fab",
    "sg:phone":"+32 9 371 64 70",
    "sg:postcode":"9850",
    "sg:province":"Oost-Vlaanderen",
    "wof:name":"Quatropack",
    "wof:placetype":"venue"
},
  "geometry": {"coordinates":[3.5745179653,51.0605583191],"type":"Point"}
}