{
  "type": "Feature",
  "properties": {
    "addr:full":"Koestraat 94 Wervik West-Vlaanderen 8940",
    "addr:housenumber":"94",
    "addr:postcode":"8940",
    "addr:street":"Koestraat",
    "iso:country":"BE",
    "sg:address":"Koestraat 94",
    "sg:city":"Wervik",
    "sg:classifiers":[
        {
            "category":"Cafe",
            "type":"Food & Drink"
        }
    ],
    "sg:phone":"+32 56 31 32 66",
    "sg:postcode":"8940",
    "sg:province":"West-Vlaanderen",
    "sg:tags":[
        "caf\u00e9s"
    ],
    "wof:name":"De Brikke",
    "wof:placetype":"venue"
},
  "geometry": {"coordinates":[3.0320959091,50.7758598328],"type":"Point"}
}