{
  "type": "Feature",
  "properties": {
    "iso:country":"BE",
    "sg:address":"Rue Giguellerie 28",
    "sg:city":"Mettet (saint-g\u00e9rard)",
    "sg:classifiers":[
        {
            "category":"Food & Beverages",
            "subcategory":"Fruits & Vegetables",
            "type":"Retail Goods"
        }
    ],
    "sg:phone":"+32 71 79 98 86",
    "sg:postcode":"5640",
    "sg:province":"Namur",
    "sg:tags":[
        "-"
    ],
    "wof:name":"Ledoux J",
    "wof:placetype":"venue"
},
  "geometry": {"coordinates":[4.7086958885,50.3667678833],"type":"Point"}
}