{
  "type": "Feature",
  "properties": {
    "addr:full":"Avenue L\u00e9on Jourez 3 Braine L'alleud (braine-l'alleud) Brabant Wallon 1420",
    "addr:housenumber":"3",
    "addr:postcode":"1420",
    "addr:street":"Avenue Le\u0301On Jourez",
    "iso:country":"BE",
    "sg:address":"Avenue L\u00e9on Jourez 3",
    "sg:city":"Braine L'alleud (braine-l'alleud)",
    "sg:classifiers":[
        {
            "category":"Real Estate",
            "subcategory":"Real Estate Services",
            "type":"Services"
        }
    ],
    "sg:phone":"+32 2 387 02 02",
    "sg:postcode":"1420",
    "sg:province":"Brabant Wallon",
    "wof:name":"Bureau Immobilier Brainois",
    "wof:placetype":"venue"
},
  "geometry": {"coordinates":[-0.7004899979,47.369140625],"type":"Point"}
}