{
  "type": "Feature",
  "properties": {
    "iso:country":"BE",
    "sg:address":"33",
    "sg:city":"Rue Saint-nicolas 7110 La Louvi\u00e8re",
    "sg:classifiers":[
        {
            "category":"Bakery",
            "type":"Food & Drink"
        }
    ],
    "sg:phone":"+32 64 22 22 76",
    "sg:postcode":"33",
    "sg:tags":[
        "cake",
        "product",
        "related",
        "bread"
    ],
    "wof:name":"Boulangerie-patisserie Van Belle Sa",
    "wof:placetype":"venue"
},
  "geometry": {"coordinates":[4.159886837,50.4803962708],"type":"Point"}
}