{
  "type": "Feature",
  "properties": {
    "iso:country":"BE",
    "sg:address":"Rue De La Justice 241",
    "sg:city":"Ch\u00e2telet",
    "sg:orig_category":"Non-Classified Establishments",
    "sg:phone":"+32 71 54 08 86",
    "sg:postcode":"6200",
    "sg:province":"Hainaut",
    "wof:name":"Coppens A",
    "wof:placetype":"venue"
},
  "geometry": {"coordinates":[4.5388150215,50.3938446045],"type":"Point"}
}