{
  "type": "Feature",
  "properties": {
    "addr:full":"Avenue Du Manoir 45 Bruxelles (uccle) Bruxelles-Capitale 1180",
    "addr:housenumber":"45",
    "addr:postcode":"1180",
    "addr:street":"Avenue Du Manoir",
    "iso:country":"BE",
    "sg:address":"Avenue Du Manoir 45",
    "sg:city":"Bruxelles (uccle)",
    "sg:classifiers":[
        {
            "category":"Health Services",
            "subcategory":"Doctor",
            "type":"Services"
        }
    ],
    "sg:phone":"+32 2 340 40 40",
    "sg:postcode":"1180",
    "sg:province":"Bruxelles-Capitale",
    "sg:tags":[
        "medicinephysicians",
        "surgeon"
    ],
    "wof:name":"Dunham F",
    "wof:placetype":"venue"
},
  "geometry": {"coordinates":[4.3465981483,50.802116394],"type":"Point"}
}