{
  "type": "Feature",
  "properties": {
    "addr:full":"Brugstraat 65a Brecht Antwerpen 2960",
    "addr:housenumber":"65a",
    "addr:postcode":"2960",
    "addr:street":"Brugstraat",
    "iso:country":"BE",
    "sg:address":"Brugstraat 65a",
    "sg:city":"Brecht",
    "sg:classifiers":[
        {
            "category":"Personal",
            "subcategory":"Beauty Salon",
            "type":"Services"
        }
    ],
    "sg:phone":"+32 3 636 13 78",
    "sg:postcode":"2960",
    "sg:province":"Antwerpen",
    "sg:tags":[
        "de",
        "coiffure"
    ],
    "wof:name":"Coiffure Graz",
    "wof:placetype":"venue"
},
  "geometry": {"coordinates":[4.5750570297,51.2953643799],"type":"Point"}
}