{
  "type": "Feature",
  "properties": {
    "iso:country":"BE",
    "sg:address":"Rue Aux Fleurs 14",
    "sg:city":"Brussel/bruxelles",
    "sg:orig_category":"Enregistrements sonores. Editeurs de livres",
    "sg:phone":"+32 2 219 71 14",
    "sg:postcode":"1000",
    "sg:province":"Bruxelles-Capitale",
    "wof:name":"Studio D.e.s.",
    "wof:placetype":"venue"
},
  "geometry": {"coordinates":[4.3523468971,50.8529052734],"type":"Point"}
}