{
  "type": "Feature",
  "properties": {
    "addr:full":"Rue G Maisier 36 Limbourg Li\u00e8ge 4830",
    "addr:housenumber":"36",
    "addr:postcode":"4830",
    "addr:street":"Rue G Maisier",
    "iso:country":"BE",
    "sg:address":"Rue G Maisier 36",
    "sg:city":"Limbourg",
    "sg:orig_category":"Kapsalons",
    "sg:phone":"+32 87 76 46 46",
    "sg:postcode":"4830",
    "sg:province":"Li\u00e8ge",
    "wof:name":"Coiffure Le Gentleman",
    "wof:placetype":"venue"
},
  "geometry": {"coordinates":[5.9407401085,50.6112518311],"type":"Point"}
}