{
  "type": "Feature",
  "properties": {
    "addr:full":"Rue L\u00e9opold 242 Charleroi (montignies-sur-sambre) Hainaut 6061",
    "addr:housenumber":"242",
    "addr:postcode":"6061",
    "addr:street":"Rue Le\u0301Opold",
    "iso:country":"BE",
    "sg:address":"Rue L\u00e9opold 242",
    "sg:city":"Charleroi (montignies-sur-sambre)",
    "sg:classifiers":[
        {
            "category":"Travel",
            "subcategory":"Travel Agent",
            "type":"Entertainment"
        }
    ],
    "sg:phone":"+32 71 30 81 84",
    "sg:postcode":"6061",
    "sg:province":"Hainaut",
    "sg:tags":[
        "agency"
    ],
    "wof:name":"Logan Tours",
    "wof:placetype":"venue"
},
  "geometry": {"coordinates":[4.4927420616,50.4091835022],"type":"Point"}
}