{
  "type": "Feature",
  "properties": {
    "addr:full":"Iepersestraat 35 Moorslede West-Vlaanderen 8890",
    "addr:housenumber":"35",
    "addr:postcode":"8890",
    "addr:street":"Iepersestraat",
    "iso:country":"BE",
    "sg:address":"Iepersestraat 35",
    "sg:city":"Moorslede",
    "sg:orig_category":"Installatie van houten of kunststof schrijnwerk MEUBELONTWERP AND -INSTALLATIE",
    "sg:phone":"+32 51 77 79 49",
    "sg:postcode":"8890",
    "sg:province":"West-Vlaanderen",
    "wof:name":"Verholle Willy En Zoon",
    "wof:placetype":"venue"
},
  "geometry": {"coordinates":[3.0573348999,50.8888435364],"type":"Point"}
}