{
  "type": "Feature",
  "properties": {
    "iso:country":"BE",
    "sg:address":"St Jansstr 2",
    "sg:city":"Werchter",
    "sg:classifiers":[
        {
            "category":"Banks & Credit Unions",
            "subcategory":"Bank",
            "type":"Services"
        }
    ],
    "sg:phone":"+32 16 60 41 06",
    "sg:postcode":"3118",
    "sg:province":"Vlaams-Brabant",
    "wof:name":"Aslk-cger Bank",
    "wof:placetype":"venue"
},
  "geometry": {"coordinates":[4.6946930885,50.971206665],"type":"Point"}
}