{
  "type": "Feature",
  "properties": {
    "addr:full":"Leenmolenstraat 9 Wingene West-Vlaanderen 8750",
    "addr:housenumber":"9",
    "addr:postcode":"8750",
    "addr:street":"Leenmolenstraat",
    "iso:country":"BE",
    "sg:address":"Leenmolenstraat 9",
    "sg:city":"Wingene",
    "sg:classifiers":[
        {
            "category":"Farming",
            "subcategory":"Poultry Farm",
            "type":"Manufacturing & Wholesale Goods"
        }
    ],
    "sg:phone":"+32 51 65 50 15",
    "sg:postcode":"8750",
    "sg:province":"West-Vlaanderen",
    "sg:tags":[
        "rabbit",
        "slaughterhouse"
    ],
    "wof:name":"Verhaest R",
    "wof:placetype":"venue"
},
  "geometry": {"coordinates":[3.2755470276,51.0617790222],"type":"Point"}
}