{
  "type": "Feature",
  "properties": {
    "iso:country":"BE",
    "sg:address":"Brogniezstraat 179",
    "sg:city":"Anderlecht/anderlecht",
    "sg:orig_category":"Artsen and specialisten",
    "sg:phone":"+32 2 523 80 04",
    "sg:postcode":"1070",
    "sg:province":"Bruxelles-Capitale",
    "wof:name":"Santina Accardi",
    "wof:placetype":"venue"
},
  "geometry": {"coordinates":[4.3312559128,50.8378982544],"type":"Point"}
}