{
  "type": "Feature",
  "properties": {
    "addr:full":"Boulevard De Waterloo 39 Bruxelles Bruxelles-Capitale 1000",
    "addr:housenumber":"39",
    "addr:postcode":"1000",
    "addr:street":"Boulevard De Waterloo",
    "iso:country":"BE",
    "sg:address":"Boulevard De Waterloo 39",
    "sg:city":"Bruxelles",
    "sg:classifiers":[
        {
            "category":"Utilities",
            "subcategory":"Fuel Oil & Lpg",
            "type":"Services"
        }
    ],
    "sg:phone":"+32 2 548 97 10",
    "sg:postcode":"1000",
    "sg:province":"Bruxelles-Capitale",
    "sg:tags":[
        "product"
    ],
    "wof:name":"Petresa International Nv",
    "wof:placetype":"venue"
},
  "geometry": {"coordinates":[4.3498620987,50.8339347839],"type":"Point"}
}