{
  "type": "Feature",
  "properties": {
    "iso:country":"BE",
    "sg:address":"Mariengasse 7",
    "sg:city":"B\u00dctgenbach/butgenbach",
    "sg:orig_category":"Openbare veiligheid",
    "sg:phone":"+32 80 44 48 11",
    "sg:postcode":"4750",
    "sg:province":"Li\u00e8ge",
    "wof:name":"Polizei",
    "wof:placetype":"venue"
},
  "geometry": {"coordinates":[6.2206501961,50.457408905],"type":"Point"}
}