{
  "type": "Feature",
  "properties": {
    "addr:full":"Av. Du Pont De Luttre 74b Bruxelles Bruxelles-Capitale 1190",
    "addr:housenumber":"74b",
    "addr:postcode":"1190",
    "addr:street":"Av. Du Pont De Luttre",
    "iso:country":"BE",
    "sg:address":"Av. Du Pont De Luttre 74b",
    "sg:city":"Bruxelles",
    "sg:classifiers":[
        {
            "category":"Manufacturing",
            "subcategory":"Metals",
            "type":"Manufacturing & Wholesale Goods"
        }
    ],
    "sg:phone":"+32 2 348 34 23",
    "sg:postcode":"1190",
    "sg:province":"Bruxelles-Capitale",
    "sg:tags":[
        "-",
        "machine",
        "equipment",
        "engineering",
        "machinery",
        "mechanical"
    ],
    "wof:name":"Wendt Boart Sa",
    "wof:placetype":"venue"
},
  "geometry": {"coordinates":[4.3223800659,50.822517395],"type":"Point"}
}