{
  "type": "Feature",
  "properties": {
    "addr:full":"Haachtsesteenweg 23 Machelen (diegem) Vlaams-Brabant 1831",
    "addr:housenumber":"23",
    "addr:postcode":"1831",
    "addr:street":"Haachtsesteenweg",
    "iso:country":"BE",
    "sg:address":"Haachtsesteenweg 23",
    "sg:city":"Machelen (diegem)",
    "sg:classifiers":[
        {
            "category":"Bars & Pubs",
            "type":"Food & Drink"
        }
    ],
    "sg:phone":"+32 2 720 86 36",
    "sg:postcode":"1831",
    "sg:province":"Vlaams-Brabant",
    "sg:tags":[
        "tavern"
    ],
    "wof:name":"Woluwedal",
    "wof:placetype":"venue"
},
  "geometry": {"coordinates":[4.4336352348,50.8971481323],"type":"Point"}
}