{
  "type": "Feature",
  "properties": {
    "iso:country":"BE",
    "sg:address":"Rue De La Brasserie 24",
    "sg:city":"Bertrix",
    "sg:classifiers":[
        {
            "category":"Retail",
            "subcategory":"Veterinary Services",
            "type":"Services"
        }
    ],
    "sg:phone":"+32 61 41 17 84",
    "sg:postcode":"6880",
    "sg:province":"Luxembourg",
    "sg:tags":[
        "veterinarian"
    ],
    "wof:name":"Arnould R",
    "wof:placetype":"venue"
},
  "geometry": {"coordinates":[5.2498440742,49.8584289551],"type":"Point"}
}