{
  "type": "Feature",
  "properties": {
    "iso:country":"BE",
    "sg:address":"Rue Emile Delva 95",
    "sg:city":"Bruxelles",
    "sg:classifiers":[
        {
            "category":"Professional",
            "subcategory":"Art Services",
            "type":"Services"
        }
    ],
    "sg:phone":"+32 2 424 32 92",
    "sg:postcode":"1020",
    "sg:province":"Bruxelles-Capitale",
    "sg:tags":[
        "designer",
        "display"
    ],
    "wof:name":"Van Der Meer F",
    "wof:placetype":"venue"
},
  "geometry": {"coordinates":[4.3424749374,50.8795051575],"type":"Point"}
}