{
  "type": "Feature",
  "properties": {
    "iso:country":"BE",
    "sg:address":"Jaagpad 5",
    "sg:city":"Ieper",
    "sg:orig_category":"Herstellingen and onderhoud van auto's Voertuigen",
    "sg:phone":"+32 57 20 45 33",
    "sg:postcode":"8900",
    "sg:province":"West-Vlaanderen",
    "wof:name":"J. P. C.",
    "wof:placetype":"venue"
},
  "geometry": {"coordinates":[2.8832700253,50.8700408936],"type":"Point"}
}