{
  "type": "Feature",
  "properties": {
    "iso:country":"BE",
    "sg:address":"Tiensesteenweg 343",
    "sg:city":"Leuven (kessel-lo)",
    "sg:classifiers":[
        {
            "category":"Personal",
            "type":"Services"
        }
    ],
    "sg:phone":"+32 477 34 22 86",
    "sg:postcode":"3010",
    "sg:province":"Vlaams-Brabant",
    "sg:tags":[
        "party",
        "planning"
    ],
    "wof:name":"De Bunswyck (kasteel)",
    "wof:placetype":"venue"
},
  "geometry": {"coordinates":[4.7422437668,50.8673286438],"type":"Point"}
}