{
  "type": "Feature",
  "properties": {
    "iso:country":"BE",
    "sg:address":"Rue De Virelles 56",
    "sg:city":"Froidchapelle",
    "sg:classifiers":[
        {
            "category":"Autos & Motor Vehicles",
            "subcategory":"Fuel & Gas Station",
            "type":"Retail Goods"
        }
    ],
    "sg:phone":"+32 60 41 18 14",
    "sg:postcode":"6440",
    "sg:province":"Hainaut",
    "sg:tags":[
        "stations-service",
        "carburants"
    ],
    "wof:name":"Madeleine Hardy",
    "wof:placetype":"venue"
},
  "geometry": {"coordinates":[4.328453064,50.1313934326],"type":"Point"}
}