{
  "type": "Feature",
  "properties": {
    "addr:full":"Burg. De Lausnaystraat 8 Berlare Oost-Vlaanderen 9290",
    "addr:housenumber":"8",
    "addr:postcode":"9290",
    "addr:street":"Burg.;Lausnaystraat",
    "iso:country":"BE",
    "sg:address":"Burg. De Lausnaystraat 8",
    "sg:city":"Berlare",
    "sg:classifiers":[
        {
            "category":"Cafe",
            "type":"Food & Drink"
        }
    ],
    "sg:phone":"+32 9 367 73 38",
    "sg:postcode":"9290",
    "sg:province":"Oost-Vlaanderen",
    "sg:tags":[
        "caf\u00e9s"
    ],
    "wof:name":"Angela Van Driessche",
    "wof:placetype":"venue"
},
  "geometry": {"coordinates":[4.005710125,51.0165214539],"type":"Point"}
}