{
  "type": "Feature",
  "properties": {
    "iso:country":"BE",
    "sg:address":"Hofeinde 175",
    "sg:city":"Vosselaar",
    "sg:orig_category":"Non-Classified Establishments",
    "sg:phone":"+32 14 61 67 09",
    "sg:postcode":"2350",
    "sg:province":"Antwerpen",
    "wof:name":"Arti-choc",
    "wof:placetype":"venue"
},
  "geometry": {"coordinates":[4.8773059845,51.3240356445],"type":"Point"}
}