{
  "type": "Feature",
  "properties": {
    "addr:full":"Stationswal 19 Bree Limburg 3960",
    "addr:housenumber":"19",
    "addr:postcode":"3960",
    "addr:street":"Stationswal",
    "iso:country":"BE",
    "sg:address":"Stationswal 19",
    "sg:city":"Bree",
    "sg:classifiers":[
        {
            "category":"Banks & Credit Unions",
            "subcategory":"Investment Brokerage",
            "type":"Services"
        }
    ],
    "sg:phone":"+32 89 46 13 58",
    "sg:postcode":"3960",
    "sg:province":"Limburg",
    "sg:tags":[
        "printing",
        "-"
    ],
    "wof:name":"Peeters J",
    "wof:placetype":"venue"
},
  "geometry": {"coordinates":[5.6006650925,51.141456604],"type":"Point"}
}