{
  "type": "Feature",
  "properties": {
    "addr:full":"Brusselsestraat 16 Londerzeel Vlaams-Brabant 1840",
    "addr:housenumber":"16",
    "addr:postcode":"1840",
    "addr:street":"Brusselsestraat",
    "iso:country":"BE",
    "sg:address":"Brusselsestraat 16",
    "sg:city":"Londerzeel",
    "sg:classifiers":[
        {
            "category":"Government",
            "subcategory":"Police Station",
            "type":"Public Place"
        }
    ],
    "sg:phone":"+32 52 30 36 87",
    "sg:postcode":"1840",
    "sg:province":"Vlaams-Brabant",
    "sg:tags":[
        "gendarmerie"
    ],
    "wof:name":"Federale Politie",
    "wof:placetype":"venue"
},
  "geometry": {"coordinates":[4.3023490906,51.000453949],"type":"Point"}
}