{
  "type": "Feature",
  "properties": {
    "iso:country":"BE",
    "sg:address":"Rue St Hadelin 12",
    "sg:city":"Celles",
    "sg:orig_category":"Musea and historische gebouwen",
    "sg:phone":"+32 82 66 62 67",
    "sg:postcode":"5561",
    "sg:province":"Namur",
    "wof:name":"Eglise Romane",
    "wof:placetype":"venue"
},
  "geometry": {"coordinates":[5.0065808296,50.229259491],"type":"Point"}
}