{
  "type": "Feature",
  "properties": {
    "iso:country":"BE",
    "sg:address":"Rue Notre-dame 18",
    "sg:city":"Binche",
    "sg:orig_category":"Opticiens",
    "sg:phone":"+32 64 33 20 08",
    "sg:postcode":"7130",
    "sg:province":"Hainaut",
    "wof:name":"Visoptic",
    "wof:placetype":"venue"
},
  "geometry": {"coordinates":[4.1653518677,50.4112319946],"type":"Point"}
}