{
  "type": "Feature",
  "properties": {
    "iso:country":"BE",
    "sg:address":"Rue Des Chapelles 1",
    "sg:city":"Mont-de-l'enclus (russeignies)",
    "sg:classifiers":[
        {
            "category":"Building & Trades",
            "subcategory":"Landscaping Services",
            "type":"Services"
        }
    ],
    "sg:phone":"+32 69 76 61 08",
    "sg:postcode":"7750",
    "sg:province":"Hainaut",
    "sg:tags":[
        "gardening",
        "garden",
        "maintenance"
    ],
    "wof:name":"Cnockaert A",
    "wof:placetype":"venue"
},
  "geometry": {"coordinates":[5.0023469925,50.3222923279],"type":"Point"}
}