{
  "type": "Feature",
  "properties": {
    "iso:country":"BE",
    "sg:address":"Rue Dr\u00e8ve D'envoz 15a",
    "sg:city":"H\u00e9ron (couthuin)",
    "sg:classifiers":[
        {
            "category":"Health Services",
            "subcategory":"Health Practitioner",
            "type":"Services"
        }
    ],
    "sg:phone":"+32 85 71 14 75",
    "sg:postcode":"4218",
    "sg:province":"Li\u00e8ge",
    "sg:tags":[
        "physiotherapist"
    ],
    "wof:name":"Wanzoul Bernard",
    "wof:placetype":"venue"
},
  "geometry": {"coordinates":[5.1438360214,50.5304412842],"type":"Point"}
}