{
  "type": "Feature",
  "properties": {
    "addr:full":"Avenue Champ De Bataille 438ba Mons Hainaut 7012",
    "addr:postcode":"7012",
    "addr:street":"Avenue Champ De Bataille 438Ba;Hainaut",
    "iso:country":"BE",
    "sg:address":"Avenue Champ De Bataille 438ba",
    "sg:city":"Mons",
    "sg:classifiers":[
        {
            "category":"Cinema",
            "subcategory":"Movie Rental",
            "type":"Entertainment"
        }
    ],
    "sg:phone":"+32 65 88 45 15",
    "sg:postcode":"7012",
    "sg:province":"Hainaut",
    "sg:tags":[
        "de",
        "cassette",
        "location",
        "vid\u00e9o",
        "audio"
    ],
    "wof:name":"Vid\u00c9oth\u00c8que Favart",
    "wof:placetype":"venue"
},
  "geometry": {"coordinates":[3.8894600868,50.4481964111],"type":"Point"}
}