{
  "type": "Feature",
  "properties": {
    "iso:country":"BE",
    "sg:address":"Derde Industriezone 21",
    "sg:city":"Aalst",
    "sg:orig_category":"Imprimeries and copyshops. Bureaux d'\u00e9tudes de march\u00e9",
    "sg:phone":"+32 53 85 09 11",
    "sg:postcode":"9320",
    "sg:province":"Oost-Vlaanderen",
    "wof:name":"Bureau Moore Lithorex",
    "wof:placetype":"venue"
},
  "geometry": {"coordinates":[4.0553851128,50.9209976196],"type":"Point"}
}