{
  "type": "Feature",
  "properties": {
    "iso:country":"BE",
    "sg:address":"Rue Victorien Ergot 105",
    "sg:city":"La Louvi\u00e8re (str\u00e9py-bracquegnies)",
    "sg:classifiers":[
        {
            "category":"Bakery",
            "type":"Food & Drink"
        }
    ],
    "sg:phone":"+32 64 67 36 37",
    "sg:postcode":"7110",
    "sg:province":"Hainaut",
    "sg:tags":[
        "confectioner",
        "baker"
    ],
    "wof:name":"Artisanale (l') Sprl",
    "wof:placetype":"venue"
},
  "geometry": {"coordinates":[4.1505050659,50.4826698303],"type":"Point"}
}