{
  "type": "Feature",
  "properties": {
    "iso:country":"BE",
    "sg:address":"Rue De Belle Vue 32",
    "sg:city":"Tubize",
    "sg:classifiers":[
        {
            "category":"Professional",
            "subcategory":"Art Services",
            "type":"Services"
        }
    ],
    "sg:phone":"+32 475 37 29 01",
    "sg:postcode":"1480",
    "sg:province":"Brabant Wallon",
    "sg:tags":[
        "realization",
        "audio-visual"
    ],
    "wof:name":"Maltesse F",
    "wof:placetype":"venue"
},
  "geometry": {"coordinates":[4.1887187958,50.6953544617],"type":"Point"}
}