{
  "type": "Feature",
  "properties": {
    "iso:country":"BE",
    "sg:address":"Rue Du Village 69",
    "sg:city":"Tinlot",
    "sg:orig_category":"Diverse opleidingen and onderwijs Informaticaconsulenten Software ontwikkeling and ontwerp",
    "sg:phone":"+32 85 41 21 98",
    "sg:postcode":"4557",
    "sg:province":"Li\u00e8ge",
    "wof:name":"B.n. & C.g. Consult",
    "wof:placetype":"venue"
},
  "geometry": {"coordinates":[5.3239469528,50.4634857178],"type":"Point"}
}