{
  "type": "Feature",
  "properties": {
    "addr:full":"Mechelbaan 2 Box 7 Lier (koningshooikt) Antwerpen 2500",
    "addr:housenumber":"2;7",
    "addr:postcode":"2500",
    "addr:street":"Mechelbaan;Box",
    "iso:country":"BE",
    "sg:address":"Mechelbaan 2 Box 7",
    "sg:city":"Lier (koningshooikt)",
    "sg:classifiers":[
        {
            "category":"Professional",
            "subcategory":"Accounting & Tax Preparation",
            "type":"Services"
        }
    ],
    "sg:phone":"+32 3 482 37 77",
    "sg:postcode":"2500",
    "sg:province":"Antwerpen",
    "sg:tags":[
        "accountant"
    ],
    "wof:name":"Schotsmans D",
    "wof:placetype":"venue"
},
  "geometry": {"coordinates":[4.6112990379,51.0932922363],"type":"Point"}
}