{
  "type": "Feature",
  "properties": {
    "iso:country":"BE",
    "sg:address":"Vieille-route-de-li\u00c8ge 17",
    "sg:city":"Marche-en-famenne",
    "sg:orig_category":"Verplichte sociale verzekeringen",
    "sg:phone":"+32 84 31 41 31",
    "sg:postcode":"6900",
    "sg:province":"Luxembourg",
    "wof:name":"Mutualit\u00c9 Neutre",
    "wof:placetype":"venue"
},
  "geometry": {"coordinates":[5.3427071571,50.2329483032],"type":"Point"}
}