{
  "type": "Feature",
  "properties": {
    "addr:full":"Chemin De La Sapini\u00e8re 12 Weismes (robertville) Li\u00e8ge 4950",
    "addr:housenumber":"12",
    "addr:postcode":"4950",
    "addr:street":"Chemin De La Sapinie\u0300Re;Robertville",
    "iso:country":"BE",
    "sg:address":"Chemin De La Sapini\u00e8re 12",
    "sg:city":"Weismes (robertville)",
    "sg:orig_category":"Fiduciairies",
    "sg:phone":"+32 80 44 69 58",
    "sg:postcode":"4950",
    "sg:province":"Li\u00e8ge",
    "wof:name":"Jost C",
    "wof:placetype":"venue"
},
  "geometry": {"coordinates":[6.0984921455,50.46717453],"type":"Point"}
}