{
  "type": "Feature",
  "properties": {
    "addr:full":"Petite Ruelle 1 Tinlot Li\u00e8ge 4557",
    "addr:housenumber":"1",
    "addr:postcode":"4557",
    "addr:street":"Petite Ruelle",
    "iso:country":"BE",
    "sg:address":"Petite Ruelle 1",
    "sg:city":"Tinlot",
    "sg:classifiers":[
        {
            "category":"Manufacturing",
            "subcategory":"Textiles",
            "type":"Manufacturing & Wholesale Goods"
        }
    ],
    "sg:phone":"+32 85 51 27 19",
    "sg:postcode":"4557",
    "sg:province":"Li\u00e8ge",
    "wof:name":"Carmen Leonard",
    "wof:placetype":"venue"
},
  "geometry": {"coordinates":[5.3754611015,50.499420166],"type":"Point"}
}