{
  "type": "Feature",
  "properties": {
    "iso:country":"BE",
    "sg:address":"Jan-baptist Courtmansstraat 1",
    "sg:city":"Berlare",
    "sg:classifiers":[
        {
            "category":"Professional",
            "subcategory":"Accounting & Tax Preparation",
            "type":"Services"
        }
    ],
    "sg:phone":"+32 52 42 20 62",
    "sg:postcode":"9290",
    "sg:province":"Oost-Vlaanderen",
    "sg:tags":[
        "bookkeeper"
    ],
    "wof:name":"Langbeen W",
    "wof:placetype":"venue"
},
  "geometry": {"coordinates":[4.0083608627,51.0156211853],"type":"Point"}
}