{
  "type": "Feature",
  "properties": {
    "iso:country":"BE",
    "sg:address":"Pont D'amercoeur 3",
    "sg:city":"Li\u00e8ge 1 (li\u00e8ge 2)",
    "sg:classifiers":[
        {
            "category":"Insurance",
            "subcategory":"Insurance Agent",
            "type":"Services"
        }
    ],
    "sg:phone":"+32 4 342 49 49",
    "sg:postcode":"4020",
    "sg:province":"Li\u00e8ge",
    "sg:tags":[
        "broker"
    ],
    "wof:name":"B\u00e9gasse & Cie",
    "wof:placetype":"venue"
},
  "geometry": {"coordinates":[5.5890779495,50.6375999451],"type":"Point"}
}