{
  "type": "Feature",
  "properties": {
    "addr:full":"Albert L Laan 50 Veurne West-Vlaanderen 8630",
    "addr:housenumber":"50",
    "addr:postcode":"8630",
    "addr:street":"Albert L Laan",
    "iso:country":"BE",
    "sg:address":"Albert L Laan 50",
    "sg:city":"Veurne",
    "sg:orig_category":"Onderdelen and accessoires voertuigen Gh Tuinbenodigdheden",
    "sg:phone":"+32 58 31 45 31",
    "sg:postcode":"8630",
    "sg:province":"West-Vlaanderen",
    "wof:name":"Dekeyser",
    "wof:placetype":"venue"
},
  "geometry": {"coordinates":[2.679224968,51.0631141663],"type":"Point"}
}