{
  "type": "Feature",
  "properties": {
    "iso:country":"BE",
    "sg:address":"Uilenbaan 84",
    "sg:city":"Wommelgem",
    "sg:orig_category":"Non-Classified Establishments",
    "sg:phone":"+32 3 270 99 30",
    "sg:postcode":"2160",
    "sg:province":"Antwerpen",
    "wof:name":"Loewe Opta Benelux Nv",
    "wof:placetype":"venue"
},
  "geometry": {"coordinates":[4.5116219521,51.2132377625],"type":"Point"}
}