{
  "type": "Feature",
  "properties": {
    "addr:full":"Z.a. De La Rivierette Saint-ghislain Hainaut 7330",
    "addr:postcode":"7330",
    "addr:street":"Z.A. De La Rivierette;Hainaut",
    "iso:country":"BE",
    "sg:address":"Z.a. De La Rivierette",
    "sg:city":"Saint-ghislain",
    "sg:orig_category":"Fabrication and montage de mobilier",
    "sg:phone":"+32 65 64 16 86",
    "sg:postcode":"7330",
    "sg:province":"Hainaut",
    "wof:name":"Alno",
    "wof:placetype":"venue"
},
  "geometry": {"coordinates":[3.8227250576,50.4473495483],"type":"Point"}
}