{
  "type": "Feature",
  "properties": {
    "addr:full":"Zandstraat 13 Herentals Antwerpen 2200",
    "addr:housenumber":"13",
    "addr:postcode":"2200",
    "addr:street":"Zandstraat",
    "iso:country":"BE",
    "sg:address":"Zandstraat 13",
    "sg:city":"Herentals",
    "sg:classifiers":[
        {
            "category":"Shopping",
            "subcategory":"Shoes",
            "type":"Retail Goods"
        }
    ],
    "sg:phone":"+32 14 23 37 18",
    "sg:postcode":"2200",
    "sg:province":"Antwerpen",
    "sg:tags":[
        "slipper",
        "-"
    ],
    "wof:name":"Schoenen Torfs",
    "wof:placetype":"venue"
},
  "geometry": {"coordinates":[4.8350439072,51.1767120361],"type":"Point"}
}