{
  "type": "Feature",
  "properties": {
    "iso:country":"BE",
    "sg:address":"Avenue Des Bouleaux 20",
    "sg:city":"Esneux",
    "sg:orig_category":"D\u00e9corateurs d'int\u00e9rieur",
    "sg:phone":"+32 4 388 16 31",
    "sg:postcode":"4130",
    "sg:province":"Li\u00e8ge",
    "wof:name":"G. Legrand",
    "wof:placetype":"venue"
},
  "geometry": {"coordinates":[5.6070828438,50.5626792908],"type":"Point"}
}