{
  "type": "Feature",
  "properties": {
    "iso:country":"BE",
    "sg:address":"Molenbergstraat 29",
    "sg:city":"Dilbeek",
    "sg:classifiers":[
        {
            "category":"Real Estate",
            "subcategory":"Surveying",
            "type":"Services"
        }
    ],
    "sg:phone":"+32 2 569 27 09",
    "sg:postcode":"1700",
    "sg:province":"Vlaams-Brabant",
    "sg:tags":[
        "surveyor",
        "land"
    ],
    "wof:name":"Van Ginderachter Ch",
    "wof:placetype":"venue"
},
  "geometry": {"coordinates":[4.2553300858,50.8439712524],"type":"Point"}
}