{
  "type": "Feature",
  "properties": {
    "addr:full":"Antwerpsesteenweg 124 Aartselaar Antwerpen 2630",
    "addr:housenumber":"124",
    "addr:postcode":"2630",
    "addr:street":"Antwerpsesteenweg",
    "iso:country":"BE",
    "sg:address":"Antwerpsesteenweg 124",
    "sg:city":"Aartselaar",
    "sg:orig_category":"Air conditionn\u00e9 and ventilation. Plomberie, chauffage and installations sanitaires",
    "sg:phone":"+32 3 877 49 52",
    "sg:postcode":"2630",
    "sg:province":"Antwerpen",
    "wof:name":"B.c.c.",
    "wof:placetype":"venue"
},
  "geometry": {"coordinates":[4.380616188,51.1446647644],"type":"Point"}
}