{
  "type": "Feature",
  "properties": {
    "iso:country":"BE",
    "sg:address":"Balgerhoeke 10",
    "sg:city":"Eeklo",
    "sg:classifiers":[
        {
            "category":"Communications",
            "subcategory":"Television Station",
            "type":"Services"
        }
    ],
    "sg:phone":"+32 9 377 31 04",
    "sg:postcode":"9900",
    "sg:province":"Oost-Vlaanderen",
    "sg:tags":[
        "antenna"
    ],
    "wof:name":"Wiegand S",
    "wof:placetype":"venue"
},
  "geometry": {"coordinates":[3.529061079,51.1993026733],"type":"Point"}
}