{
  "type": "Feature",
  "properties": {
    "addr:full":"Rue Du March\u00e9 Aux Porcs 30 Bruxelles Bruxelles-Capitale 1000",
    "addr:housenumber":"30",
    "addr:postcode":"1000",
    "addr:street":"Rue Du Marche\u0301 Aux Porcs",
    "iso:country":"BE",
    "sg:address":"Rue Du March\u00e9 Aux Porcs 30",
    "sg:city":"Bruxelles",
    "sg:classifiers":[
        {
            "category":"Health Services",
            "subcategory":"Doctor",
            "type":"Services"
        }
    ],
    "sg:phone":"+32 2 219 04 97",
    "sg:postcode":"1000",
    "sg:province":"Bruxelles-Capitale",
    "sg:tags":[
        "medicinephysicians",
        "surgeon"
    ],
    "wof:name":"De Clercq P",
    "wof:placetype":"venue"
},
  "geometry": {"coordinates":[4.3458328247,50.8536643982],"type":"Point"}
}