{
  "type": "Feature",
  "properties": {
    "iso:country":"BE",
    "sg:address":"Stationslaan 23",
    "sg:city":"Brugge",
    "sg:orig_category":"Editeurs de livres",
    "sg:phone":"+32 50 38 38 98",
    "sg:postcode":"8200",
    "sg:province":"West-Vlaanderen",
    "wof:name":"Uitgeverij Vanden Broele",
    "wof:placetype":"venue"
},
  "geometry": {"coordinates":[3.2110309601,51.2021331787],"type":"Point"}
}