{
  "type": "Feature",
  "properties": {
    "addr:full":"Rte D'herbesthal 120 Eupen Li\u00e8ge 4700",
    "addr:housenumber":"120",
    "addr:postcode":"4700",
    "addr:street":"Rte D'Herbesthal",
    "iso:country":"BE",
    "sg:address":"Rte D'herbesthal 120",
    "sg:city":"Eupen",
    "sg:classifiers":[
        {
            "category":"Autos & Motor Vehicles",
            "subcategory":"Automobile Sales",
            "type":"Retail Goods"
        }
    ],
    "sg:phone":"+32 87 56 00 56",
    "sg:postcode":"4700",
    "sg:province":"Li\u00e8ge",
    "sg:tags":[
        "equipment",
        "motor-cars",
        "transport"
    ],
    "wof:name":"Ohn Pierre Sa",
    "wof:placetype":"venue"
},
  "geometry": {"coordinates":[6.0180969238,50.6380805969],"type":"Point"}
}