{
  "type": "Feature",
  "properties": {
    "addr:full":"Tiensestw 115 Korbeek Vlaams-Brabant 3040",
    "addr:housenumber":"115",
    "addr:postcode":"3040",
    "addr:street":"Korbeek Vlaams-Brabant",
    "iso:country":"BE",
    "sg:address":"Tiensestw 115",
    "sg:city":"Korbeek",
    "sg:classifiers":[
        {
            "category":"Banks & Credit Unions",
            "subcategory":"Bank",
            "type":"Services"
        }
    ],
    "sg:phone":"+32 16 46 06 38",
    "sg:postcode":"3040",
    "sg:province":"Vlaams-Brabant",
    "wof:name":"Gemeentekrediet",
    "wof:placetype":"venue"
},
  "geometry": {"coordinates":[144.90606689449999,-37.7515602112],"type":"Point"}
}