{
  "type": "Feature",
  "properties": {
    "addr:full":"Avenue Du Castel 72a Bruxelles (woluwe-saint-lambert) Bruxelles-Capitale 1200",
    "addr:housenumber":"72a",
    "addr:postcode":"1200",
    "addr:street":"Avenue Du Castel",
    "iso:country":"BE",
    "sg:address":"Avenue Du Castel 72a",
    "sg:city":"Bruxelles (woluwe-saint-lambert)",
    "sg:classifiers":[
        {
            "category":"Banks & Credit Unions",
            "subcategory":"Financial Services",
            "type":"Services"
        }
    ],
    "sg:phone":"+32 2 733 22 89",
    "sg:postcode":"1200",
    "sg:province":"Bruxelles-Capitale",
    "sg:tags":[
        "debt",
        "recovery"
    ],
    "wof:name":"Dekibert & Associ\u00e9s Scrl",
    "wof:placetype":"venue"
},
  "geometry": {"coordinates":[4.4100399017,50.8411216736],"type":"Point"}
}