{
  "type": "Feature",
  "properties": {
    "addr:full":"Rumbeeksesteenweg 230 Roeselare West-Vlaanderen 8800",
    "addr:housenumber":"230",
    "addr:postcode":"8800",
    "addr:street":"Rumbeeksesteenweg",
    "iso:country":"BE",
    "sg:address":"Rumbeeksesteenweg 230",
    "sg:city":"Roeselare",
    "sg:classifiers":[
        {
            "category":"Personal",
            "subcategory":"Beauty Salon",
            "type":"Services"
        }
    ],
    "sg:phone":"+32 51 24 56 23",
    "sg:postcode":"8800",
    "sg:province":"West-Vlaanderen",
    "sg:tags":[
        "lady",
        "-",
        "hairdressing"
    ],
    "wof:name":"Kathleen Coiffure",
    "wof:placetype":"venue"
},
  "geometry": {"coordinates":[3.135144949,50.9381561279],"type":"Point"}
}