{
  "type": "Feature",
  "properties": {
    "iso:country":"BE",
    "sg:address":"Bevrijdingslaan 2",
    "sg:city":"Tielt",
    "sg:orig_category":"Industrial vehicles Metallurgy and Metalworking Vehicles and Transport Equipment",
    "sg:phone":"+32 51 40 32 33",
    "sg:postcode":"8700",
    "sg:province":"West-Vlaanderen",
    "wof:name":"Kerkhove Bvba",
    "wof:placetype":"venue"
},
  "geometry": {"coordinates":[3.3495779037,50.9986610413],"type":"Point"}
}