{
  "type": "Feature",
  "properties": {
    "addr:full":"Berlaarsestraat 42 Lier Antwerpen 2500",
    "addr:housenumber":"42",
    "addr:postcode":"2500",
    "addr:street":"Berlaarsestraat",
    "iso:country":"BE",
    "sg:address":"Berlaarsestraat 42",
    "sg:city":"Lier",
    "sg:classifiers":[
        {
            "category":"Shopping",
            "subcategory":"Gifts & Souvenirs",
            "type":"Retail Goods"
        }
    ],
    "sg:phone":"+32 3 480 07 86",
    "sg:postcode":"2500",
    "sg:province":"Antwerpen",
    "sg:tags":[
        "-"
    ],
    "wof:name":"Krinkel",
    "wof:placetype":"venue"
},
  "geometry": {"coordinates":[4.5772380829,51.1292228699],"type":"Point"}
}