{
  "type": "Feature",
  "properties": {
    "iso:country":"BE",
    "sg:address":"Stierstraat 10",
    "sg:city":"Antwerpen",
    "sg:classifiers":[
        {
            "category":"Real Estate",
            "subcategory":"Architect",
            "type":"Services"
        }
    ],
    "sg:phone":"+32 3 272 01 48",
    "sg:postcode":"2018",
    "sg:province":"Antwerpen",
    "wof:name":"Van De Poel P",
    "wof:placetype":"venue"
},
  "geometry": {"coordinates":[4.4301438332,51.207988739],"type":"Point"}
}