{
  "type": "Feature",
  "properties": {
    "iso:country":"BE",
    "sg:address":"Blokstraat 13",
    "sg:city":"Geel",
    "sg:orig_category":"Eleveurs de bovins",
    "sg:phone":"+32 14 58 80 07",
    "sg:postcode":"2440",
    "sg:province":"Antwerpen",
    "wof:name":"Louis Vrins",
    "wof:placetype":"venue"
},
  "geometry": {"coordinates":[5.0184130669,51.2122383118],"type":"Point"}
}