{
  "type": "Feature",
  "properties": {
    "iso:country":"BE",
    "sg:address":"Rue Commandant Naessens 22",
    "sg:city":"Ans (loncin)",
    "sg:classifiers":[
        {
            "category":"Education",
            "subcategory":"Music School",
            "type":"Public Place"
        }
    ],
    "sg:phone":"+32 4 247 07 18",
    "sg:postcode":"4431",
    "sg:province":"Li\u00e8ge",
    "sg:tags":[
        "rental",
        "grandstand",
        "stage",
        "-",
        "mfg"
    ],
    "wof:name":"Regicler",
    "wof:placetype":"venue"
},
  "geometry": {"coordinates":[5.5024528503,50.6639785767],"type":"Point"}
}