{
  "type": "Feature",
  "properties": {
    "iso:country":"BE",
    "sg:address":"Edmond Machtenssquare 18",
    "sg:city":"Sint-jans-molenbeek/molenbeek-saint-jean",
    "sg:orig_category":"Kapsalons",
    "sg:phone":"+32 2 410 58 72",
    "sg:postcode":"1080",
    "sg:province":"Bruxelles-Capitale",
    "wof:name":"Hair Pastel",
    "wof:placetype":"venue"
},
  "geometry": {"coordinates":[4.3212189674,50.8530311584],"type":"Point"}
}