{
  "type": "Feature",
  "properties": {
    "iso:country":"BE",
    "sg:address":"Chauss\u00c9e De Ninove 414",
    "sg:city":"Ronse/renaix",
    "sg:classifiers":[
        {
            "category":"Insurance",
            "subcategory":"Life Insurance",
            "type":"Services"
        }
    ],
    "sg:phone":"+32 55 21 27 81",
    "sg:postcode":"9600",
    "sg:province":"Oost-Vlaanderen",
    "sg:tags":[
        "assurance"
    ],
    "wof:name":"O.v.k.",
    "wof:placetype":"venue"
},
  "geometry": {"coordinates":[3.6493849754,50.7543449402],"type":"Point"}
}