{
  "type": "Feature",
  "properties": {
    "iso:country":"BE",
    "sg:address":"Dr De Wolfplein 4",
    "sg:city":"Oudenaarde",
    "sg:orig_category":"Epiceries. Cr\u00e9meries",
    "sg:phone":"+32 55 31 88 09",
    "sg:postcode":"9700",
    "sg:province":"Oost-Vlaanderen",
    "wof:name":"Huis De Fijnproever",
    "wof:placetype":"venue"
},
  "geometry": {"coordinates":[3.6085999012,50.842590332],"type":"Point"}
}