{
  "type": "Feature",
  "properties": {
    "iso:country":"BE",
    "sg:address":"Lammekensknokstraat 19",
    "sg:city":"Ingelmunster",
    "sg:orig_category":"Diverse bedrijfsbeheeradviesbureaus",
    "sg:phone":"+32 51 30 13 52",
    "sg:postcode":"8770",
    "sg:province":"West-Vlaanderen",
    "wof:name":"B.-consulting",
    "wof:placetype":"venue"
},
  "geometry": {"coordinates":[3.2610759735,50.9329299927],"type":"Point"}
}