{
  "type": "Feature",
  "properties": {
    "addr:full":"Rue Du Warichet 19-2 Perwez Brabant Wallon 1360",
    "addr:housenumber":"19-2",
    "addr:postcode":"1360",
    "addr:street":"Rue Du Warichet",
    "iso:country":"BE",
    "sg:address":"Rue Du Warichet 19-2",
    "sg:city":"Perwez",
    "sg:classifiers":[
        {
            "category":"Organizations",
            "subcategory":"Community Association",
            "type":"Services"
        }
    ],
    "sg:phone":"+32 81 65 53 65",
    "sg:postcode":"1360",
    "sg:province":"Brabant Wallon",
    "sg:tags":[
        "cultural"
    ],
    "wof:name":"Ateliers Du Bout Du Monde (les)",
    "wof:placetype":"venue"
},
  "geometry": {"coordinates":[4.8193860054,50.6269607544],"type":"Point"}
}