{
  "type": "Feature",
  "properties": {
    "iso:country":"BE",
    "sg:address":"Rue Grande 44",
    "sg:city":"Boussu (hornu)",
    "sg:classifiers":[
        {
            "category":"Home & Garden",
            "subcategory":"Kitchen Supply",
            "type":"Retail Goods"
        }
    ],
    "sg:phone":"+32 65 79 23 18",
    "sg:postcode":"7301",
    "sg:province":"Hainaut",
    "sg:tags":[
        "installation"
    ],
    "wof:name":"Interno Studio Boffi",
    "wof:placetype":"venue"
},
  "geometry": {"coordinates":[3.8257451057,50.4362258911],"type":"Point"}
}