{
  "type": "Feature",
  "properties": {
    "iso:country":"BE",
    "sg:address":"Ereffe 30a",
    "sg:city":"Marchin",
    "sg:classifiers":[
        {
            "category":"Mining & Drilling",
            "type":"Manufacturing & Wholesale Goods"
        }
    ],
    "sg:phone":"+32 85 41 11 91",
    "sg:postcode":"4570",
    "sg:province":"Li\u00e8ge",
    "sg:tags":[
        "quarry"
    ],
    "wof:name":"Carri\u00e8res D'ereffe Sa",
    "wof:placetype":"venue"
},
  "geometry": {"coordinates":[5.2616882324,50.4705352783],"type":"Point"}
}