{
  "type": "Feature",
  "properties": {
    "addr:full":"Avenue Brugmann 512 Bruxelles (uccle) Bruxelles-Capitale 1180",
    "addr:housenumber":"512",
    "addr:postcode":"1180",
    "addr:street":"Avenue Brugmann",
    "iso:country":"BE",
    "sg:address":"Avenue Brugmann 512",
    "sg:city":"Bruxelles (uccle)",
    "sg:classifiers":[
        {
            "category":"Communications",
            "subcategory":"Film & Video Production",
            "type":"Services"
        }
    ],
    "sg:phone":"+32 2 346 05 42",
    "sg:postcode":"1180",
    "sg:province":"Bruxelles-Capitale",
    "sg:tags":[
        "hiring",
        "-"
    ],
    "wof:name":"Globus Vid\u00e9oclub",
    "wof:placetype":"venue"
},
  "geometry": {"coordinates":[4.3388772011,50.8010902405],"type":"Point"}
}