{
  "type": "Feature",
  "properties": {
    "addr:full":"Winterstraat 70 Bilzen Limburg 3740",
    "addr:housenumber":"70",
    "addr:postcode":"3740",
    "addr:street":"Winterstraat",
    "iso:country":"BE",
    "sg:address":"Winterstraat 70",
    "sg:city":"Bilzen",
    "sg:classifiers":[
        {
            "category":"Health Services",
            "subcategory":"Health Practitioner",
            "type":"Services"
        }
    ],
    "sg:phone":"+32 89 51 53 29",
    "sg:postcode":"3740",
    "sg:province":"Limburg",
    "sg:tags":[
        "physiotherapist"
    ],
    "wof:name":"Stiller Geoffrey",
    "wof:placetype":"venue"
},
  "geometry": {"coordinates":[5.5150508881,50.8788757324],"type":"Point"}
}