{
  "type": "Feature",
  "properties": {
    "addr:full":"Nieuwkerkenstraat 12 Sint-niklaas (nieuwkerken-waas) Oost-Vlaanderen 9100",
    "addr:housenumber":"12",
    "addr:postcode":"9100",
    "addr:street":"Nieuwkerkenstraat;Nieuwkerken-Waas",
    "iso:country":"BE",
    "sg:address":"Nieuwkerkenstraat 12",
    "sg:city":"Sint-niklaas (nieuwkerken-waas)",
    "sg:classifiers":[
        {
            "category":"Professional",
            "subcategory":"Testing Lab",
            "type":"Services"
        }
    ],
    "sg:phone":"+32 3 776 02 59",
    "sg:postcode":"9100",
    "sg:province":"Oost-Vlaanderen",
    "sg:tags":[
        "chemist"
    ],
    "wof:name":"Boone R",
    "wof:placetype":"venue"
},
  "geometry": {"coordinates":[4.1783537865,51.1926956177],"type":"Point"}
}