{
  "type": "Feature",
  "properties": {
    "iso:country":"BE",
    "sg:address":"Chauss\u00c9e De Waterloo 1347",
    "sg:city":"Ukkel/uccle",
    "sg:orig_category":"Agences de voyages",
    "sg:phone":"+32 2 373 09 09",
    "sg:postcode":"1180",
    "sg:province":"Bruxelles-Capitale",
    "wof:name":"Stopover Travel",
    "wof:placetype":"venue"
},
  "geometry": {"coordinates":[4.3745098114,50.7902870178],"type":"Point"}
}