{
  "type": "Feature",
  "properties": {
    "iso:country":"BE",
    "sg:address":"Hippodroomlaan 99",
    "sg:city":"Zaventem (sterrebeek)",
    "sg:classifiers":[
        {
            "category":"Professional",
            "subcategory":"Art Services",
            "type":"Services"
        }
    ],
    "sg:phone":"+32 2 731 59 88",
    "sg:postcode":"1933",
    "sg:province":"Vlaams-Brabant",
    "sg:tags":[
        "graphic",
        "designer"
    ],
    "wof:name":"De Backer N Bion Graphics",
    "wof:placetype":"venue"
},
  "geometry": {"coordinates":[4.5081391335,50.8473014832],"type":"Point"}
}