{
  "type": "Feature",
  "properties": {
    "addr:full":"Marcel De Thirylaan 216 Brussel/bruxelles Bruxelles-Capitale 1200",
    "addr:housenumber":"216",
    "addr:postcode":"1200",
    "addr:street":"Marcel De Thirylaan;/",
    "iso:country":"BE",
    "sg:address":"Marcel De Thirylaan 216",
    "sg:city":"Brussel/bruxelles",
    "sg:orig_category":"Agences immobili\u00e8res",
    "sg:phone":"+32 2 710 79 44",
    "sg:postcode":"1200",
    "sg:province":"Bruxelles-Capitale",
    "wof:name":"Plant Location International",
    "wof:placetype":"venue"
},
  "geometry": {"coordinates":[4.4321532249,50.8567886353],"type":"Point"}
}