{
  "type": "Feature",
  "properties": {
    "iso:country":"BE",
    "sg:address":"Kapellevelden 5",
    "sg:city":"Putte",
    "sg:classifiers":[
        {
            "category":"Wholesale",
            "subcategory":"Beer",
            "type":"Manufacturing & Wholesale Goods"
        }
    ],
    "sg:phone":"+32 15 75 41 81",
    "sg:postcode":"2580",
    "sg:province":"Antwerpen",
    "sg:tags":[
        "ale",
        "-"
    ],
    "wof:name":"Bierhandel Corluy Nv",
    "wof:placetype":"venue"
},
  "geometry": {"coordinates":[4.6239089966,51.0632286072],"type":"Point"}
}