{
  "type": "Feature",
  "properties": {
    "addr:full":"De Fr\u00c9laan 263b1 Ukkel/uccle Bruxelles-Capitale 1180",
    "addr:housenumber":"263b1",
    "addr:postcode":"1180",
    "addr:street":"De Fre\u0301Laan;/",
    "iso:country":"BE",
    "sg:address":"De Fr\u00c9laan 263b1",
    "sg:city":"Ukkel/uccle",
    "sg:orig_category":"Immobili\u00ebnkantoren",
    "sg:phone":"+32 2 374 42 02",
    "sg:postcode":"1180",
    "sg:province":"Bruxelles-Capitale",
    "wof:name":"Le Belier",
    "wof:placetype":"venue"
},
  "geometry": {"coordinates":[4.3682999611,50.8047103882],"type":"Point"}
}