{
  "type": "Feature",
  "properties": {
    "addr:full":"Gemeenteplein 2 Spiere-helkijn/espierres-helchin West-Vlaanderen 8587",
    "addr:housenumber":"2",
    "addr:postcode":"8587",
    "addr:street":"Gemeenteplein",
    "iso:country":"BE",
    "sg:address":"Gemeenteplein 2",
    "sg:city":"Spiere-helkijn/espierres-helchin",
    "sg:orig_category":"Levering aan huis restaurants Restaurants",
    "sg:phone":"+32 56 45 62 75",
    "sg:postcode":"8587",
    "sg:province":"West-Vlaanderen",
    "wof:name":"La Descente Du Pont",
    "wof:placetype":"venue"
},
  "geometry": {"coordinates":[3.3832380772,50.7302856445],"type":"Point"}
}