{
  "type": "Feature",
  "properties": {
    "addr:full":"Rue Bois-l'ev\u00caque 14 Li\u00c8ge Li\u00e8ge 4000",
    "addr:housenumber":"14",
    "addr:postcode":"4000",
    "addr:street":"Rue Bois-L'Eve \u0302Que",
    "iso:country":"BE",
    "sg:address":"Rue Bois-l'ev\u00caque 14",
    "sg:city":"Li\u00c8ge",
    "sg:orig_category":"Artsen and specialisten",
    "sg:phone":"+32 4 253 53 08",
    "sg:postcode":"4000",
    "sg:province":"Li\u00e8ge",
    "wof:name":"Patricia Forget",
    "wof:placetype":"venue"
},
  "geometry": {"coordinates":[5.5610737801,50.6290512085],"type":"Point"}
}