{
  "type": "Feature",
  "properties": {
    "iso:country":"BE",
    "sg:address":"Rue Des H\u00c9ros 54",
    "sg:city":"Liege",
    "sg:orig_category":"Goederenvervoer over de weg",
    "sg:phone":"+32 4 247 27 07",
    "sg:postcode":"4000",
    "sg:province":"Li\u00e8ge",
    "wof:name":"Braeckman",
    "wof:placetype":"venue"
},
  "geometry": {"coordinates":[5.5528850555,50.6825141907],"type":"Point"}
}