{
  "type": "Feature",
  "properties": {
    "iso:country":"BE",
    "sg:address":"Moerstraat 11",
    "sg:city":"Beveren",
    "sg:orig_category":"Afbraak- and draineerwerken",
    "sg:phone":"+32 3 775 07 19",
    "sg:postcode":"9120",
    "sg:province":"Oost-Vlaanderen",
    "wof:name":"Van Hal",
    "wof:placetype":"venue"
},
  "geometry": {"coordinates":[4.2108931541,51.2145843506],"type":"Point"}
}