{
  "type": "Feature",
  "properties": {
    "addr:full":"Boslaan 11 Meerhout Antwerpen 2450",
    "addr:housenumber":"11",
    "addr:postcode":"2450",
    "addr:street":"Boslaan",
    "iso:country":"BE",
    "sg:address":"Boslaan 11",
    "sg:city":"Meerhout",
    "sg:classifiers":[
        {
            "category":"Real Estate",
            "subcategory":"Architect",
            "type":"Services"
        }
    ],
    "sg:phone":"+32 14 30 00 53",
    "sg:postcode":"2450",
    "sg:province":"Antwerpen",
    "wof:name":"Vandervoort W",
    "wof:placetype":"venue"
},
  "geometry": {"coordinates":[5.0702619553,51.1283569336],"type":"Point"}
}