{
  "type": "Feature",
  "properties": {
    "iso:country":"BE",
    "sg:address":"Rue Th\u00e9odore Verhaegen 128",
    "sg:city":"Bruxelles (saint-gilles)",
    "sg:classifiers":[
        {
            "category":"Home & Garden",
            "subcategory":"Carpets & Floor Coverings",
            "type":"Retail Goods"
        }
    ],
    "sg:phone":"+32 2 534 11 20",
    "sg:postcode":"1060",
    "sg:province":"Bruxelles-Capitale",
    "sg:tags":[
        "-",
        "rug"
    ],
    "wof:name":"Ugur Tapis",
    "wof:placetype":"venue"
},
  "geometry": {"coordinates":[4.3380007744,50.8296890259],"type":"Point"}
}