{
  "type": "Feature",
  "properties": {
    "iso:country":"BE",
    "sg:address":"Rue De Lassus 19",
    "sg:city":"Peruwelz",
    "sg:orig_category":"Eleveurs de bovins",
    "sg:phone":"+32 69 77 28 39",
    "sg:postcode":"7602",
    "sg:province":"Hainaut",
    "wof:name":"Payelle Freres",
    "wof:placetype":"venue"
},
  "geometry": {"coordinates":[3.6008810997,50.5426750183],"type":"Point"}
}