{
  "type": "Feature",
  "properties": {
    "iso:country":"BE",
    "sg:address":"Rue Bonwez 49",
    "sg:city":"La Bruy\u00e8re (rhisnes)",
    "sg:classifiers":[
        {
            "category":"Health Services",
            "subcategory":"Health Practitioner",
            "type":"Services"
        }
    ],
    "sg:phone":"+32 81 56 96 63",
    "sg:postcode":"5080",
    "sg:province":"Namur",
    "sg:tags":[
        "psychologist"
    ],
    "wof:name":"Dessauvages-lagos",
    "wof:placetype":"venue"
},
  "geometry": {"coordinates":[4.8051228523,50.5112342834],"type":"Point"}
}