{
  "type": "Feature",
  "properties": {
    "iso:country":"BE",
    "sg:address":"Rue De Roubaix 25",
    "sg:city":"Tournai",
    "sg:orig_category":"Kapsalons",
    "sg:phone":"+32 69 35 28 38",
    "sg:postcode":"7520",
    "sg:province":"Hainaut",
    "wof:name":"Coiffure Michel",
    "wof:placetype":"venue"
},
  "geometry": {"coordinates":[3.2810149193,50.6443519592],"type":"Point"}
}