{
  "type": "Feature",
  "properties": {
    "addr:full":"Driesstraat 8 Bilzen Limburg 3740",
    "addr:housenumber":"8",
    "addr:postcode":"3740",
    "addr:street":"Driesstraat",
    "iso:country":"BE",
    "sg:address":"Driesstraat 8",
    "sg:city":"Bilzen",
    "sg:orig_category":"Plaatsen van vloer- and muurbekleding Schilders",
    "sg:phone":"+32 89 41 59 83",
    "sg:postcode":"3740",
    "sg:province":"Limburg",
    "wof:name":"Gerard Loverix",
    "wof:placetype":"venue"
},
  "geometry": {"coordinates":[5.5133070946,50.8699760437],"type":"Point"}
}