{
  "type": "Feature",
  "properties": {
    "addr:full":"Tieltsebaan 1 Scherpenheuvel-zichem Vlaams-Brabant 3272",
    "addr:housenumber":"1",
    "addr:postcode":"3272",
    "addr:street":"Tieltsebaan",
    "iso:country":"BE",
    "sg:address":"Tieltsebaan 1",
    "sg:city":"Scherpenheuvel-zichem",
    "sg:orig_category":"Banken and kredietinstellingen",
    "sg:phone":"+32 13 77 26 01",
    "sg:postcode":"3272",
    "sg:province":"Vlaams-Brabant",
    "wof:name":"Fortis",
    "wof:placetype":"venue"
},
  "geometry": {"coordinates":[4.9398789406,50.9959945679],"type":"Point"}
}