{
  "type": "Feature",
  "properties": {
    "iso:country":"BE",
    "sg:address":"Overstraat 38",
    "sg:city":"Herent",
    "sg:orig_category":"Quincailleries. Plomberie, chauffage and installations sanitaires",
    "sg:phone":"+32 16 48 88 20",
    "sg:postcode":"3020",
    "sg:province":"Vlaams-Brabant",
    "wof:name":"Pardon En Zoon",
    "wof:placetype":"venue"
},
  "geometry": {"coordinates":[4.6749200821,50.9079055786],"type":"Point"}
}