{
  "type": "Feature",
  "properties": {
    "addr:full":"Rue Joseph Wauters 20 Saint-georges-sur-meuse Li\u00e8ge 4470",
    "addr:housenumber":"20",
    "addr:postcode":"4470",
    "addr:street":"Rue Joseph Wauters",
    "iso:country":"BE",
    "sg:address":"Rue Joseph Wauters 20",
    "sg:city":"Saint-georges-sur-meuse",
    "sg:classifiers":[
        {
            "category":"Professional",
            "subcategory":"Engineering",
            "type":"Services"
        }
    ],
    "sg:phone":"+32 4 273 70 10",
    "sg:postcode":"4470",
    "sg:province":"Li\u00e8ge",
    "sg:tags":[
        "industrial",
        "-",
        "automation"
    ],
    "wof:name":"Ipc Europe Sprl",
    "wof:placetype":"venue"
},
  "geometry": {"coordinates":[5.3610901833,50.578289032],"type":"Point"}
}