{
  "type": "Feature",
  "properties": {
    "iso:country":"BE",
    "sg:address":"Rue De Bouillon 1",
    "sg:city":"Bi\u00e8vre",
    "sg:orig_category":"Autombile concessionaires",
    "sg:phone":"+32 61 51 10 22",
    "sg:postcode":"5555",
    "sg:province":"Namur",
    "wof:name":"Gar New Nemery Sprl",
    "wof:placetype":"venue"
},
  "geometry": {"coordinates":[5.0194959641,49.9405899048],"type":"Point"}
}