{
  "type": "Feature",
  "properties": {
    "addr:full":"Rue Louis Thys 3-5 Bruxelles (woluwe-saint-pierre) Bruxelles-Capitale 1150",
    "addr:housenumber":"3-5",
    "addr:postcode":"1150",
    "addr:street":"Rue Louis Thys",
    "iso:country":"BE",
    "sg:address":"Rue Louis Thys 3-5",
    "sg:city":"Bruxelles (woluwe-saint-pierre)",
    "sg:classifiers":[
        {
            "category":"Shopping",
            "subcategory":"Antiques",
            "type":"Retail Goods"
        }
    ],
    "sg:phone":"+32 2 771 08 75",
    "sg:postcode":"1150",
    "sg:province":"Bruxelles-Capitale",
    "sg:tags":[
        "restoration"
    ],
    "wof:name":"Clinique Du Cristal Sartenaer",
    "wof:placetype":"venue"
},
  "geometry": {"coordinates":[4.4321627617,50.8370132446],"type":"Point"}
}