{
  "type": "Feature",
  "properties": {
    "iso:country":"BE",
    "sg:address":"Selteschlag 13",
    "sg:city":"Eupen",
    "sg:orig_category":"Transports routiers de marchandises",
    "sg:phone":"+32 87 55 50 03",
    "sg:postcode":"4700",
    "sg:province":"Li\u00e8ge",
    "wof:name":"Interliner Belgium",
    "wof:placetype":"venue"
},
  "geometry": {"coordinates":[6.0388622284,50.6212501526],"type":"Point"}
}