{
  "type": "Feature",
  "properties": {
    "addr:full":"Leeuwenstraat 1 Antwerpen Antwerpen 2000",
    "addr:housenumber":"1",
    "addr:postcode":"2000",
    "addr:street":"Leeuwenstraat",
    "iso:country":"BE",
    "sg:address":"Leeuwenstraat 1",
    "sg:city":"Antwerpen",
    "sg:classifiers":[
        {
            "category":"Restaurant",
            "type":"Food & Drink"
        }
    ],
    "sg:phone":"+32 3 226 26 70",
    "sg:postcode":"2000",
    "sg:province":"Antwerpen",
    "wof:name":"De Koraal",
    "wof:placetype":"venue"
},
  "geometry": {"coordinates":[4.3995828629,51.2189598083],"type":"Point"}
}