{
  "type": "Feature",
  "properties": {
    "addr:full":"Waterkasteelstraat 5 Tongeren Limburg 3700",
    "addr:housenumber":"5",
    "addr:postcode":"3700",
    "addr:street":"Waterkasteelstraat",
    "iso:country":"BE",
    "sg:address":"Waterkasteelstraat 5",
    "sg:city":"Tongeren",
    "sg:classifiers":[
        {
            "category":"Cafe",
            "type":"Food & Drink"
        }
    ],
    "sg:phone":"+32 12 23 35 73",
    "sg:postcode":"3700",
    "sg:province":"Limburg",
    "sg:tags":[
        "caf\u00e9s"
    ],
    "wof:name":"Christel Vanherf",
    "wof:placetype":"venue"
},
  "geometry": {"coordinates":[5.5273938179,50.7670135498],"type":"Point"}
}