{
  "type": "Feature",
  "properties": {
    "iso:country":"BE",
    "sg:address":"Gouverneur Roppesingel 165",
    "sg:city":"Hasselt",
    "sg:classifiers":[
        {
            "category":"Utilities",
            "subcategory":"Telephone",
            "type":"Services"
        }
    ],
    "sg:phone":"+32 11 28 33 33",
    "sg:postcode":"3500",
    "sg:province":"Limburg",
    "sg:tags":[
        "-",
        "internet"
    ],
    "wof:name":"Kantoorinrichting Stulens",
    "wof:placetype":"venue"
},
  "geometry": {"coordinates":[5.3496599197,50.9173202515],"type":"Point"}
}