{
  "type": "Feature",
  "properties": {
    "addr:full":"Industriestrasse 7 Eupen/eupen Li\u00e8ge 4700",
    "addr:housenumber":"7",
    "addr:postcode":"4700",
    "addr:street":"Industriestrasse",
    "iso:country":"BE",
    "sg:address":"Industriestrasse 7",
    "sg:city":"Eupen/eupen",
    "sg:orig_category":"Onderdelen and accessoires voertuigen Gh",
    "sg:phone":"+32 87 56 02 63",
    "sg:postcode":"4700",
    "sg:province":"Li\u00e8ge",
    "wof:name":"Verviers Freins",
    "wof:placetype":"venue"
},
  "geometry": {"coordinates":[6.0086779594,50.6416969299],"type":"Point"}
}