{
  "type": "Feature",
  "properties": {
    "addr:full":"Maria-hendrikastraat 20 Elsene/ixelles Bruxelles-Capitale 1050",
    "addr:housenumber":"20",
    "addr:postcode":"1050",
    "addr:street":"Maria-Hendrikastraat",
    "iso:country":"BE",
    "sg:address":"Maria-hendrikastraat 20",
    "sg:city":"Elsene/ixelles",
    "sg:orig_category":"Artiesten and kunstenaars",
    "sg:phone":"+32 2 648 15 80",
    "sg:postcode":"1050",
    "sg:province":"Bruxelles-Capitale",
    "wof:name":"Suzane Vanina",
    "wof:placetype":"venue"
},
  "geometry": {"coordinates":[4.3747739792,50.8309516907],"type":"Point"}
}