{
  "type": "Feature",
  "properties": {
    "iso:country":"BE",
    "sg:address":"Rue Alban Poulet 18",
    "sg:city":"Li\u00e8ge 1 (ch\u00ean\u00e9e)",
    "sg:classifiers":[
        {
            "category":"Real Estate",
            "subcategory":"Architect",
            "type":"Services"
        }
    ],
    "sg:phone":"+32 4 365 26 94",
    "sg:postcode":"4032",
    "sg:province":"Li\u00e8ge",
    "wof:name":"Schindfessel P",
    "wof:placetype":"venue"
},
  "geometry": {"coordinates":[5.6135931015,50.606262207],"type":"Point"}
}