{
  "type": "Feature",
  "properties": {
    "addr:full":"Kapellestraat 87ba Oostende West-Vlaanderen 8400",
    "addr:housenumber":"87ba",
    "addr:postcode":"8400",
    "addr:street":"Kapellestraat",
    "iso:country":"BE",
    "sg:address":"Kapellestraat 87ba",
    "sg:city":"Oostende",
    "sg:orig_category":"V\u00eatements pour b\u00e9b\u00e9s and enfants",
    "sg:phone":"+32 59 50 81 55",
    "sg:postcode":"8400",
    "sg:province":"West-Vlaanderen",
    "wof:name":"Huis Folieke",
    "wof:placetype":"venue"
},
  "geometry": {"coordinates":[2.9199440479,51.2290878296],"type":"Point"}
}