{
  "type": "Feature",
  "properties": {
    "iso:country":"BE",
    "sg:address":"Zur Lehmkaul 8",
    "sg:city":"B\u00fcllingen",
    "sg:classifiers":[
        {
            "category":"Freight",
            "type":"Transportation"
        }
    ],
    "sg:phone":"+32 80 64 72 50",
    "sg:postcode":"4760",
    "sg:province":"Li\u00e8ge",
    "sg:tags":[
        "-",
        "transport"
    ],
    "wof:name":"Hepp Transport Sprl",
    "wof:placetype":"venue"
},
  "geometry": {"coordinates":[6.2557492256,50.4061813354],"type":"Point"}
}