{
  "type": "Feature",
  "properties": {
    "addr:full":"Place Roi Albert I 5 Rochefort Namur 5580",
    "addr:housenumber":"5",
    "addr:postcode":"5580",
    "addr:street":"Place Roi Albert I",
    "iso:country":"BE",
    "sg:address":"Place Roi Albert I 5",
    "sg:city":"Rochefort",
    "sg:classifiers":[
        {
            "category":"Food & Beverages",
            "subcategory":"Chocolate",
            "type":"Retail Goods"
        }
    ],
    "sg:phone":"+32 84 21 25 98",
    "sg:postcode":"5580",
    "sg:province":"Namur",
    "sg:tags":[
        "confectionery",
        "-"
    ],
    "wof:name":"Friandise (la)",
    "wof:placetype":"venue"
},
  "geometry": {"coordinates":[5.2228631973,50.1577644348],"type":"Point"}
}