{
  "type": "Feature",
  "properties": {
    "addr:full":"Waalsestraat 18 Brugge West-Vlaanderen 8000",
    "addr:housenumber":"18",
    "addr:postcode":"8000",
    "addr:street":"Waalsestraat",
    "iso:country":"BE",
    "sg:address":"Waalsestraat 18",
    "sg:city":"Brugge",
    "sg:classifiers":[
        {
            "category":"Building & Trades",
            "subcategory":"Landscaping Services",
            "type":"Services"
        }
    ],
    "sg:phone":"+32 50 34 09 24",
    "sg:postcode":"8000",
    "sg:province":"West-Vlaanderen",
    "sg:tags":[
        "architect",
        "landscape"
    ],
    "wof:name":"Goormachtigh M",
    "wof:placetype":"venue"
},
  "geometry": {"coordinates":[3.2295620441,51.2072944641],"type":"Point"}
}