{
  "type": "Feature",
  "properties": {
    "addr:full":"Chauss\u00e9e De Charleroi 2e Bruxelles (saint-gilles) Bruxelles-Capitale 1060",
    "addr:housenumber":"2e",
    "addr:postcode":"1060",
    "addr:street":"Chausse\u0301E De Charleroi",
    "iso:country":"BE",
    "sg:address":"Chauss\u00e9e De Charleroi 2e",
    "sg:city":"Bruxelles (saint-gilles)",
    "sg:classifiers":[
        {
            "category":"Utilities",
            "subcategory":"Mobile Phone",
            "type":"Services"
        }
    ],
    "sg:phone":"+32 2 534 17 70",
    "sg:postcode":"1060",
    "sg:province":"Bruxelles-Capitale",
    "sg:tags":[
        "access",
        "gsm",
        "-",
        "apparatus"
    ],
    "wof:name":"Ericsson Store",
    "wof:placetype":"venue"
},
  "geometry": {"coordinates":[4.3569779396,50.8327522278],"type":"Point"}
}