{
  "type": "Feature",
  "properties": {
    "iso:country":"BE",
    "sg:address":"L. Vandenhovenstraat 29",
    "sg:city":"Evere",
    "sg:orig_category":"Boekhouders",
    "sg:phone":"+32 2 215 02 95",
    "sg:postcode":"1140",
    "sg:province":"Bruxelles-Capitale",
    "wof:name":"Andr\u00c9 Vandevelde",
    "wof:placetype":"venue"
},
  "geometry": {"coordinates":[4.404733181,50.8821487427],"type":"Point"}
}