{
  "type": "Feature",
  "properties": {
    "iso:country":"BE",
    "sg:address":"Zwarteweg 26",
    "sg:city":"Middelkerke (mannekensvere)",
    "sg:classifiers":[
        {
            "category":"Farming",
            "subcategory":"Farm & Veterinary Services",
            "type":"Manufacturing & Wholesale Goods"
        }
    ],
    "sg:phone":"+32 58 23 91 66",
    "sg:postcode":"8433",
    "sg:province":"West-Vlaanderen",
    "sg:tags":[
        "agricultural",
        "contractor"
    ],
    "wof:name":"Soete D",
    "wof:placetype":"venue"
},
  "geometry": {"coordinates":[2.834954977,51.1293640137],"type":"Point"}
}