{
  "type": "Feature",
  "properties": {
    "iso:country":"BE",
    "sg:address":"Molenhoek 119",
    "sg:city":"Lede (smetlede)",
    "sg:classifiers":[
        {
            "category":"Freight",
            "type":"Transportation"
        }
    ],
    "sg:phone":"+32 9 365 08 45",
    "sg:postcode":"9340",
    "sg:province":"Oost-Vlaanderen",
    "sg:tags":[
        "-",
        "transport"
    ],
    "wof:name":"Transka Bvba",
    "wof:placetype":"venue"
},
  "geometry": {"coordinates":[3.9170629978,50.963886261],"type":"Point"}
}