{
  "type": "Feature",
  "properties": {
    "iso:country":"BE",
    "sg:address":"Steenweg Op Deinze 68a",
    "sg:city":"Nazareth",
    "sg:orig_category":"Royal Canin Slagers",
    "sg:phone":"+32 9 386 15 72",
    "sg:postcode":"9810",
    "sg:province":"Oost-Vlaanderen",
    "wof:name":"Nachtergaele",
    "wof:placetype":"venue"
},
  "geometry": {"coordinates":[3.5759251118,50.9498443604],"type":"Point"}
}