{
  "type": "Feature",
  "properties": {
    "addr:full":"Grote Steenweg 34 Zoutleeuw Vlaams-Brabant 3440",
    "addr:housenumber":"34",
    "addr:postcode":"3440",
    "addr:street":"Grote Steenweg;Vlaams-Brabant",
    "iso:country":"BE",
    "sg:address":"Grote Steenweg 34",
    "sg:city":"Zoutleeuw",
    "sg:orig_category":"Herstellingen and onderhoud van auto's Voertuigen",
    "sg:phone":"+32 11 78 21 42",
    "sg:postcode":"3440",
    "sg:province":"Vlaams-Brabant",
    "wof:name":"Carrosserie Vonckx Rony",
    "wof:placetype":"venue"
},
  "geometry": {"coordinates":[5.0927500725,50.8064613342],"type":"Point"}
}