{
  "type": "Feature",
  "properties": {
    "addr:full":"Fortbekeweg 11 Brugge West-Vlaanderen 8000",
    "addr:housenumber":"11",
    "addr:postcode":"8000",
    "addr:street":"Fortbekeweg",
    "iso:country":"BE",
    "sg:address":"Fortbekeweg 11",
    "sg:city":"Brugge",
    "sg:orig_category":"Woningbouw",
    "sg:phone":"+32 50 34 18 39",
    "sg:postcode":"8000",
    "sg:province":"West-Vlaanderen",
    "wof:name":"Floreal",
    "wof:placetype":"venue"
},
  "geometry": {"coordinates":[3.2524039745,51.2335968018],"type":"Point"}
}