{
  "type": "Feature",
  "properties": {
    "addr:full":"Jan Moonsstraat 19 Wommelgem Antwerpen 2160",
    "addr:housenumber":"19",
    "addr:postcode":"2160",
    "addr:street":"Jan Moonsstraat",
    "iso:country":"BE",
    "sg:address":"Jan Moonsstraat 19",
    "sg:city":"Wommelgem",
    "sg:orig_category":"Sportclubs",
    "sg:phone":"+32 3 353 90 61",
    "sg:postcode":"2160",
    "sg:province":"Antwerpen",
    "wof:name":"Wafiwo",
    "wof:placetype":"venue"
},
  "geometry": {"coordinates":[4.5239567757,51.2058677673],"type":"Point"}
}