{
  "type": "Feature",
  "properties": {
    "addr:full":"Oude Vierschaarstraat 23 Sint-martens-latem (deurle) Oost-Vlaanderen 9831",
    "addr:housenumber":"23",
    "addr:postcode":"9831",
    "addr:street":"Oude Vierschaarstraat;Deurle",
    "iso:country":"BE",
    "sg:address":"Oude Vierschaarstraat 23",
    "sg:city":"Sint-martens-latem (deurle)",
    "sg:classifiers":[
        {
            "category":"Health Services",
            "subcategory":"Dentist",
            "type":"Services"
        }
    ],
    "sg:phone":"+32 9 282 79 29",
    "sg:postcode":"9831",
    "sg:province":"Oost-Vlaanderen",
    "wof:name":"Dechamps C",
    "wof:placetype":"venue"
},
  "geometry": {"coordinates":[3.6115679741,51.0033798218],"type":"Point"}
}