{
  "type": "Feature",
  "properties": {
    "addr:full":"Sint-bavoweg 2 Erpe-mere Oost-Vlaanderen 9420",
    "addr:housenumber":"2",
    "addr:postcode":"9420",
    "addr:street":"Sint-Bavoweg",
    "iso:country":"BE",
    "sg:address":"Sint-bavoweg 2",
    "sg:city":"Erpe-mere",
    "sg:orig_category":"Huishoudapparaten, televisies and radio's",
    "sg:phone":"+32 53 83 36 21",
    "sg:postcode":"9420",
    "sg:province":"Oost-Vlaanderen",
    "wof:name":"Elesan",
    "wof:placetype":"venue"
},
  "geometry": {"coordinates":[3.9715900421,50.9222984314],"type":"Point"}
}