{
  "type": "Feature",
  "properties": {
    "addr:full":"Kruishuisstraat 18 Turnhout Antwerpen 2300",
    "addr:housenumber":"18",
    "addr:postcode":"2300",
    "addr:street":"Kruishuisstraat",
    "iso:country":"BE",
    "sg:address":"Kruishuisstraat 18",
    "sg:city":"Turnhout",
    "sg:orig_category":"Jeux and jouets",
    "sg:phone":"+32 14 41 19 36",
    "sg:postcode":"2300",
    "sg:province":"Antwerpen",
    "wof:name":"Bazarke",
    "wof:placetype":"venue"
},
  "geometry": {"coordinates":[4.9406638145,51.3210525513],"type":"Point"}
}