{
  "type": "Feature",
  "properties": {
    "addr:full":"Schamprood 24 Lommel Limburg 3920",
    "addr:housenumber":"24",
    "addr:postcode":"3920",
    "addr:street":"Schamprood",
    "iso:country":"BE",
    "sg:address":"Schamprood 24",
    "sg:city":"Lommel",
    "sg:classifiers":[
        {
            "category":"Health Services",
            "subcategory":"Health Practitioner",
            "type":"Services"
        }
    ],
    "sg:phone":"+32 11 54 09 66",
    "sg:postcode":"3920",
    "sg:province":"Limburg",
    "sg:tags":[
        "physiotherapist"
    ],
    "wof:name":"Spooren R",
    "wof:placetype":"venue"
},
  "geometry": {"coordinates":[5.3410258293,51.2299003601],"type":"Point"}
}