{
  "type": "Feature",
  "properties": {
    "iso:country":"BE",
    "sg:address":"Pastorijstraat 60",
    "sg:city":"Tremelo",
    "sg:orig_category":"Apotheken",
    "sg:phone":"+32 16 53 00 42",
    "sg:postcode":"3128",
    "sg:province":"Vlaams-Brabant",
    "wof:name":"Francis Frenay",
    "wof:placetype":"venue"
},
  "geometry": {"coordinates":[4.7517261505,50.9981040955],"type":"Point"}
}