{
  "type": "Feature",
  "properties": {
    "iso:country":"BE",
    "sg:address":"Rue Jules Destr\u00e9e 74",
    "sg:city":"Charleroi (ransart)",
    "sg:classifiers":[
        {
            "category":"Professional",
            "subcategory":"Accounting & Tax Preparation",
            "type":"Services"
        }
    ],
    "sg:phone":"+32 71 35 46 58",
    "sg:postcode":"6043",
    "sg:province":"Hainaut",
    "sg:tags":[
        "bookkeeper"
    ],
    "wof:name":"Renzetti B",
    "wof:placetype":"venue"
},
  "geometry": {"coordinates":[4.4514741898,50.4204559326],"type":"Point"}
}