{
  "type": "Feature",
  "properties": {
    "addr:full":"Rue De Vise 506 Li\u00c8ge Li\u00e8ge 4020",
    "addr:housenumber":"506",
    "addr:postcode":"4020",
    "addr:street":"Rue De Vise",
    "iso:country":"BE",
    "sg:address":"Rue De Vise 506",
    "sg:city":"Li\u00c8ge",
    "sg:orig_category":"Elektrische installaties voor woningen",
    "sg:phone":"+32 4 362 54 28",
    "sg:postcode":"4020",
    "sg:province":"Li\u00e8ge",
    "wof:name":"Daniel Filee",
    "wof:placetype":"venue"
},
  "geometry": {"coordinates":[5.6463298798,50.6544799805],"type":"Point"}
}