{
  "type": "Feature",
  "properties": {
    "addr:full":"Rue Africaine 92 Bruxelles Bruxelles-Capitale 1060",
    "addr:housenumber":"92",
    "addr:postcode":"1060",
    "addr:street":"Rue Africaine",
    "iso:country":"BE",
    "sg:address":"Rue Africaine 92",
    "sg:city":"Bruxelles",
    "sg:classifiers":[
        {
            "category":"Real Estate",
            "subcategory":"Real Estate Operator",
            "type":"Services"
        }
    ],
    "sg:phone":"+32 2 537 20 70",
    "sg:postcode":"1060",
    "sg:province":"Bruxelles-Capitale",
    "sg:tags":[
        "technical",
        "documentation"
    ],
    "wof:name":"Dsdb S.a.",
    "wof:placetype":"venue"
},
  "geometry": {"coordinates":[4.3574352264,50.8251228333],"type":"Point"}
}