{
  "type": "Feature",
  "properties": {
    "addr:full":"Avenue Des Platanes 31 Herve (grand-rechain) Li\u00e8ge 4650",
    "addr:housenumber":"31",
    "addr:postcode":"4650",
    "addr:street":"Avenue Des Platanes;Grand-Rechain",
    "iso:country":"BE",
    "sg:address":"Avenue Des Platanes 31",
    "sg:city":"Herve (grand-rechain)",
    "sg:classifiers":[
        {
            "category":"Manufacturing",
            "subcategory":"Furniture",
            "type":"Manufacturing & Wholesale Goods"
        }
    ],
    "sg:phone":"+32 87 33 82 06",
    "sg:postcode":"4650",
    "sg:province":"Li\u00e8ge",
    "sg:tags":[
        "design",
        "-"
    ],
    "wof:name":"Leroy T",
    "wof:placetype":"venue"
},
  "geometry": {"coordinates":[5.8165788651,50.6099205017],"type":"Point"}
}