{
  "type": "Feature",
  "properties": {
    "addr:full":"Rue Grande 5 Saint-ghislain Hainaut 7330",
    "addr:housenumber":"5",
    "addr:postcode":"7330",
    "addr:street":"Rue Grande;Hainaut",
    "iso:country":"BE",
    "sg:address":"Rue Grande 5",
    "sg:city":"Saint-ghislain",
    "sg:orig_category":"Banques and organismes de cr\u00e9dit",
    "sg:phone":"+32 65 78 11 35",
    "sg:postcode":"7330",
    "sg:province":"Hainaut",
    "wof:name":"Cbc",
    "wof:placetype":"venue"
},
  "geometry": {"coordinates":[3.820235014,50.4468612671],"type":"Point"}
}