{
  "type": "Feature",
  "properties": {
    "addr:full":"Chauss\u00c9e De Dinant 1 Anhee Namur 5537",
    "addr:housenumber":"1",
    "addr:postcode":"5537",
    "addr:street":"Chausse\u0301E De Dinant;Namur",
    "iso:country":"BE",
    "sg:address":"Chauss\u00c9e De Dinant 1",
    "sg:city":"Anhee",
    "sg:orig_category":"Entretien and r\u00e9parations de voitures",
    "sg:phone":"+32 82 61 38 47",
    "sg:postcode":"5537",
    "sg:province":"Namur",
    "wof:name":"Anh\u00c9e Motor",
    "wof:placetype":"venue"
},
  "geometry": {"coordinates":[4.8806300163,50.308631897],"type":"Point"}
}