{
  "type": "Feature",
  "properties": {
    "iso:country":"BE",
    "sg:address":"Mierdsedijk 64",
    "sg:city":"Ravels (poppel)",
    "sg:orig_category":"Non-Classified Establishments",
    "sg:phone":"+32 14 65 53 37",
    "sg:postcode":"2382",
    "sg:province":"Antwerpen",
    "wof:name":"Nooyens M",
    "wof:placetype":"venue"
},
  "geometry": {"coordinates":[5.041768074,51.4469108582],"type":"Point"}
}