{
  "type": "Feature",
  "properties": {
    "addr:full":"Kortrijkstraat 359 Menen West-Vlaanderen 8930",
    "addr:housenumber":"359",
    "addr:postcode":"8930",
    "addr:street":"Kortrijkstraat",
    "iso:country":"BE",
    "sg:address":"Kortrijkstraat 359",
    "sg:city":"Menen",
    "sg:orig_category":"Charpentes and couvertures",
    "sg:phone":"+32 56 53 16 85",
    "sg:postcode":"8930",
    "sg:province":"West-Vlaanderen",
    "wof:name":"Bermalux Dakwerken",
    "wof:placetype":"venue"
},
  "geometry": {"coordinates":[3.1379699707,50.7988395691],"type":"Point"}
}