{
  "type": "Feature",
  "properties": {
    "iso:country":"BE",
    "sg:address":"Beukenlaan 1",
    "sg:city":"Neerpelt",
    "sg:orig_category":"Installation \u00e9lectrique r\u00e9sidentielle",
    "sg:phone":"+32 11 64 15 84",
    "sg:postcode":"3910",
    "sg:province":"Limburg",
    "wof:name":"Electro Technics Beckers",
    "wof:placetype":"venue"
},
  "geometry": {"coordinates":[5.4414048195,51.2174568176],"type":"Point"}
}