{
  "type": "Feature",
  "properties": {
    "addr:full":"Rue Hubert Streel 115 Ans Li\u00e8ge 4432",
    "addr:housenumber":"115",
    "addr:postcode":"4432",
    "addr:street":"Rue Hubert Streel",
    "iso:country":"BE",
    "sg:address":"Rue Hubert Streel 115",
    "sg:city":"Ans",
    "sg:orig_category":"Avocats and conseillers juridiques",
    "sg:phone":"+32 4 247 48 20",
    "sg:postcode":"4432",
    "sg:province":"Li\u00e8ge",
    "wof:name":"G\u00c9raldine Constantinou",
    "wof:placetype":"venue"
},
  "geometry": {"coordinates":[5.5169520378,50.6679458618],"type":"Point"}
}