{
  "type": "Feature",
  "properties": {
    "iso:country":"BE",
    "sg:address":"Amsterdamstraat 36",
    "sg:city":"Oostende",
    "sg:classifiers":[
        {
            "category":"Building & Trades",
            "subcategory":"Cleaning & Sanitation",
            "type":"Services"
        }
    ],
    "sg:phone":"+32 59 51 61 00",
    "sg:postcode":"8400",
    "sg:province":"West-Vlaanderen",
    "sg:tags":[
        "fa\u00e7ade",
        "maintenance"
    ],
    "wof:name":"Pierloot G",
    "wof:placetype":"venue"
},
  "geometry": {"coordinates":[2.9155580997,51.2252464294],"type":"Point"}
}