{
  "type": "Feature",
  "properties": {
    "iso:country":"BE",
    "sg:address":"Rue Hocheporte 107",
    "sg:city":"Li\u00e8ge 1",
    "sg:classifiers":[
        {
            "category":"Shopping",
            "subcategory":"Books",
            "type":"Retail Goods"
        }
    ],
    "sg:phone":"+32 4 225 17 87",
    "sg:postcode":"4000",
    "sg:province":"Li\u00e8ge",
    "sg:tags":[
        "bookseller"
    ],
    "wof:name":"Librairie Hocheporte",
    "wof:placetype":"venue"
},
  "geometry": {"coordinates":[5.5640897751,50.6483345032],"type":"Point"}
}