{
  "type": "Feature",
  "properties": {
    "addr:full":"Chemin Des Bosses 1 Ath Hainaut 7810",
    "addr:housenumber":"1",
    "addr:postcode":"7810",
    "addr:street":"Chemin Des Bosses",
    "iso:country":"BE",
    "sg:address":"Chemin Des Bosses 1",
    "sg:city":"Ath",
    "sg:orig_category":"Sportclubs",
    "sg:phone":"+32 68 28 54 38",
    "sg:postcode":"7810",
    "sg:province":"Hainaut",
    "wof:name":"B.s.c. Hedgehogs",
    "wof:placetype":"venue"
},
  "geometry": {"coordinates":[3.8022899628,50.6149749756],"type":"Point"}
}