{
  "type": "Feature",
  "properties": {
    "iso:country":"BE",
    "sg:address":"Chauss\u00e9e De Namur 53-55",
    "sg:city":"Gembloux-sur-orneau (gembloux)",
    "sg:orig_category":"Vibrationdampers",
    "sg:phone":"+32 81 61 13 59",
    "sg:postcode":"5030",
    "sg:province":"Namur",
    "wof:name":"Chaput M Ets",
    "wof:placetype":"venue"
},
  "geometry": {"coordinates":[4.7038412094,50.5600318909],"type":"Point"}
}