{
  "type": "Feature",
  "properties": {
    "iso:country":"BE",
    "sg:address":"Av H Conscience 191",
    "sg:city":"Evere (bruxelles)",
    "sg:classifiers":[
        {
            "category":"Personal",
            "subcategory":"Beauty Salon",
            "type":"Services"
        }
    ],
    "sg:phone":"+32 2 242 03 74",
    "sg:postcode":"1140",
    "sg:province":"Bruxelles-Capitale",
    "sg:tags":[
        "de",
        "coiffure"
    ],
    "wof:name":"Cr\u00c9atif",
    "wof:placetype":"venue"
},
  "geometry": {"coordinates":[4.4005560875,50.8729133606],"type":"Point"}
}