{
  "type": "Feature",
  "properties": {
    "addr:full":"Sint-amandsstraat 5 Grimbergen Vlaams-Brabant 1853",
    "addr:housenumber":"5",
    "addr:postcode":"1853",
    "addr:street":"Sint-Amandsstraat",
    "iso:country":"BE",
    "sg:address":"Sint-amandsstraat 5",
    "sg:city":"Grimbergen",
    "sg:orig_category":"Fournitures de bureau",
    "sg:phone":"+32 2 267 14 23",
    "sg:postcode":"1853",
    "sg:province":"Vlaams-Brabant",
    "wof:name":"Vervueren",
    "wof:placetype":"venue"
},
  "geometry": {"coordinates":[4.3573918343,50.9096984863],"type":"Point"}
}