{
  "type": "Feature",
  "properties": {
    "iso:country":"BE",
    "sg:address":"St.-truidersteenweg 536",
    "sg:city":"Borgloon",
    "sg:classifiers":[
        {
            "category":"Manufacturing",
            "subcategory":"Food",
            "type":"Manufacturing & Wholesale Goods"
        }
    ],
    "sg:phone":"+32 11 68 30 50",
    "sg:postcode":"3840",
    "sg:province":"Limburg",
    "sg:tags":[
        "machine",
        "fruit",
        "processing"
    ],
    "wof:name":"Jammaers B.v.b.a.",
    "wof:placetype":"venue"
},
  "geometry": {"coordinates":[5.259185791,50.8082199097],"type":"Point"}
}