{
  "type": "Feature",
  "properties": {
    "iso:country":"BE",
    "sg:address":"Aarschotsesteenweg 136",
    "sg:city":"Begijnendijk",
    "sg:orig_category":"Pharmaciens",
    "sg:phone":"+32 16 56 95 74",
    "sg:postcode":"3130",
    "sg:province":"Vlaams-Brabant",
    "wof:name":"Maria Dillen",
    "wof:placetype":"venue"
},
  "geometry": {"coordinates":[4.7943630219,50.9888839722],"type":"Point"}
}