{
  "type": "Feature",
  "properties": {
    "addr:full":"Rue De Charleroi 93 Fontaine-l'ev\u00eaque Hainaut 6140",
    "addr:housenumber":"93",
    "addr:postcode":"6140",
    "addr:street":"Rue De Charleroi;\u0302Que Hainaut",
    "iso:country":"BE",
    "sg:address":"Rue De Charleroi 93",
    "sg:city":"Fontaine-l'ev\u00eaque",
    "sg:classifiers":[
        {
            "category":"Home & Garden",
            "subcategory":"Garden Supply",
            "type":"Retail Goods"
        }
    ],
    "sg:phone":"+32 71 52 96 96",
    "sg:postcode":"6140",
    "sg:province":"Hainaut",
    "wof:name":"Feron Jardins Sa",
    "wof:placetype":"venue"
},
  "geometry": {"coordinates":[4.335340023,50.4065132141],"type":"Point"}
}