{
  "type": "Feature",
  "properties": {
    "iso:country":"BE",
    "sg:address":"Stationsstraat 23",
    "sg:city":"Lanaken",
    "sg:orig_category":"Administration d'immeubles. Agences immobili\u00e8res",
    "sg:phone":"+32 89 71 21 56",
    "sg:postcode":"3620",
    "sg:province":"Limburg",
    "wof:name":"Studio D.m.c.",
    "wof:placetype":"venue"
},
  "geometry": {"coordinates":[5.650551796,50.888469696],"type":"Point"}
}