{
  "type": "Feature",
  "properties": {
    "iso:country":"BE",
    "sg:address":"Vaartstraat-west 28",
    "sg:city":"Evergem",
    "sg:orig_category":"Rundveehouders Varkenskwekers",
    "sg:phone":"+32 9 344 64 07",
    "sg:postcode":"9940",
    "sg:province":"Oost-Vlaanderen",
    "wof:name":"Antoine Bauwens",
    "wof:placetype":"venue"
},
  "geometry": {"coordinates":[3.6767830849,51.1314620972],"type":"Point"}
}