{
  "type": "Feature",
  "properties": {
    "addr:full":"Nieuwpoortsesteenweg 887 Oostende West-Vlaanderen 8400",
    "addr:housenumber":"887",
    "addr:postcode":"8400",
    "addr:street":"Nieuwpoortsesteenweg",
    "iso:country":"BE",
    "sg:address":"Nieuwpoortsesteenweg 887",
    "sg:city":"Oostende",
    "sg:classifiers":[
        {
            "category":"Government",
            "subcategory":"Police Station",
            "type":"Public Place"
        }
    ],
    "sg:phone":"+32 59 80 12 70",
    "sg:postcode":"8400",
    "sg:province":"West-Vlaanderen",
    "sg:tags":[
        "gendarmerie"
    ],
    "wof:name":"Federale Politie",
    "wof:placetype":"venue"
},
  "geometry": {"coordinates":[2.8524999619,51.1990623474],"type":"Point"}
}