{
  "type": "Feature",
  "properties": {
    "iso:country":"BE",
    "sg:address":"Liersesteenweg 47",
    "sg:city":"Mortsel",
    "sg:orig_category":"M\u00e9decins and sp\u00e9cialistes",
    "sg:phone":"+32 3 449 87 12",
    "sg:postcode":"2640",
    "sg:province":"Antwerpen",
    "wof:name":"W. Meir",
    "wof:placetype":"venue"
},
  "geometry": {"coordinates":[4.4606561661,51.1698074341],"type":"Point"}
}