{
  "type": "Feature",
  "properties": {
    "iso:country":"BE",
    "sg:address":"Boomstraat 28",
    "sg:city":"Bornem",
    "sg:orig_category":"Juwelen and horloges",
    "sg:phone":"+32 3 889 02 14",
    "sg:postcode":"2880",
    "sg:province":"Antwerpen",
    "wof:name":"Marc Bongaerts",
    "wof:placetype":"venue"
},
  "geometry": {"coordinates":[4.233716011,51.0989532471],"type":"Point"}
}