{
  "type": "Feature",
  "properties": {
    "iso:country":"BE",
    "sg:address":"Gansbroekstraat 24",
    "sg:city":"Puurs (ruisbroek)",
    "sg:classifiers":[
        {
            "category":"Banks & Credit Unions",
            "subcategory":"Investment Brokerage",
            "type":"Services"
        }
    ],
    "sg:phone":"+32 3 866 23 50",
    "sg:postcode":"2870",
    "sg:province":"Antwerpen",
    "sg:tags":[
        "-",
        "sale",
        "yachts",
        "accessory",
        "pleasure",
        "boat"
    ],
    "wof:name":"Stu-wahr Yachting",
    "wof:placetype":"venue"
},
  "geometry": {"coordinates":[4.33288908,51.0882797241],"type":"Point"}
}