{
  "type": "Feature",
  "properties": {
    "addr:full":"Rue Vivegnis 393 Li\u00c8ge Li\u00e8ge 4000",
    "addr:housenumber":"393",
    "addr:postcode":"4000",
    "addr:street":"Rue Vivegnis",
    "iso:country":"BE",
    "sg:address":"Rue Vivegnis 393",
    "sg:city":"Li\u00c8ge",
    "sg:orig_category":"Paramedische behandelingen",
    "sg:phone":"+32 4 227 62 67",
    "sg:postcode":"4000",
    "sg:province":"Li\u00e8ge",
    "wof:name":"M. Luyten",
    "wof:placetype":"venue"
},
  "geometry": {"coordinates":[5.5944209099,50.654384613],"type":"Point"}
}