{
  "type": "Feature",
  "properties": {
    "addr:full":"Chemin Du Cheneux 23 Weismes (robertville) Li\u00e8ge 4950",
    "addr:housenumber":"23",
    "addr:postcode":"4950",
    "addr:street":"Chemin Du Cheneux;Robertville",
    "iso:country":"BE",
    "sg:address":"Chemin Du Cheneux 23",
    "sg:city":"Weismes (robertville)",
    "sg:orig_category":"Non-Classified Establishments",
    "sg:phone":"+32 80 44 02 50",
    "sg:postcode":"4950",
    "sg:province":"Li\u00e8ge",
    "wof:name":"Probisco",
    "wof:placetype":"venue"
},
  "geometry": {"coordinates":[6.104640007,50.4600296021],"type":"Point"}
}