{
  "type": "Feature",
  "properties": {
    "iso:country":"BE",
    "sg:address":"Avenue Jean-baptiste Nothomb 10",
    "sg:city":"Arlon",
    "sg:classifiers":[
        {
            "category":"Banks & Credit Unions",
            "subcategory":"Financial Services",
            "type":"Services"
        }
    ],
    "sg:phone":"+32 61 32 80 64",
    "sg:postcode":"6700",
    "sg:province":"Luxembourg",
    "sg:tags":[
        "loan",
        "mortgage"
    ],
    "wof:name":"Lemaire Y",
    "wof:placetype":"venue"
},
  "geometry": {"coordinates":[5.8113899231,49.6821327209],"type":"Point"}
}