{
  "type": "Feature",
  "properties": {
    "iso:country":"BE",
    "sg:address":"Hamerstraat 10",
    "sg:city":"Stekene",
    "sg:classifiers":[
        {
            "category":"Health Services",
            "subcategory":"Nursing And Care Facility",
            "type":"Services"
        }
    ],
    "sg:phone":"+32 3 779 93 48",
    "sg:postcode":"9190",
    "sg:province":"Oost-Vlaanderen",
    "sg:tags":[
        "home"
    ],
    "wof:name":"Hesters C",
    "wof:placetype":"venue"
},
  "geometry": {"coordinates":[4.026515007,51.2128601074],"type":"Point"}
}