{
  "type": "Feature",
  "properties": {
    "iso:country":"BE",
    "sg:address":"Grand Rue 108",
    "sg:city":"Mons",
    "sg:classifiers":[
        {
            "category":"Personal",
            "subcategory":"Barber",
            "type":"Services"
        }
    ],
    "sg:phone":"+32 65 84 41 26",
    "sg:postcode":"7000",
    "sg:province":"Hainaut",
    "sg:tags":[
        "gentleman",
        "salon",
        "-",
        "hairdressing"
    ],
    "wof:name":"Toch Bruno",
    "wof:placetype":"venue"
},
  "geometry": {"coordinates":[3.9492800236,50.4496002197],"type":"Point"}
}