{
  "type": "Feature",
  "properties": {
    "addr:full":"Rue De Hiettine 1ba Havelange Namur 5370",
    "addr:housenumber":"1ba",
    "addr:postcode":"5370",
    "addr:street":"Rue De Hiettine",
    "iso:country":"BE",
    "sg:address":"Rue De Hiettine 1ba",
    "sg:city":"Havelange",
    "sg:orig_category":"Enseignement maternel and primaire",
    "sg:phone":"+32 83 63 39 00",
    "sg:postcode":"5370",
    "sg:province":"Namur",
    "wof:name":"Ecole Fondamentale Libre",
    "wof:placetype":"venue"
},
  "geometry": {"coordinates":[5.2421050072,50.3873748779],"type":"Point"}
}