{
  "type": "Feature",
  "properties": {
    "addr:full":"Kerkstraat 41 Boutersem (kerkom) Vlaams-Brabant 3370",
    "addr:housenumber":"41",
    "addr:postcode":"3370",
    "addr:street":"Kerkstraat",
    "iso:country":"BE",
    "sg:address":"Kerkstraat 41",
    "sg:city":"Boutersem (kerkom)",
    "sg:classifiers":[
        {
            "category":"Insurance",
            "subcategory":"Insurance Agent",
            "type":"Services"
        }
    ],
    "sg:phone":"+32 16 73 35 56",
    "sg:postcode":"3370",
    "sg:province":"Vlaams-Brabant",
    "sg:tags":[
        "broker"
    ],
    "wof:name":"Wouters Jos Zakenkantoor Nv",
    "wof:placetype":"venue"
},
  "geometry": {"coordinates":[4.8305220604,50.8304786682],"type":"Point"}
}