{
  "type": "Feature",
  "properties": {
    "iso:country":"BE",
    "sg:address":"Lebonstraat 104",
    "sg:city":"Geel",
    "sg:classifiers":[
        {
            "category":"Health Services",
            "subcategory":"Health Practitioner",
            "type":"Services"
        }
    ],
    "sg:phone":"+32 14 58 08 34",
    "sg:postcode":"2440",
    "sg:province":"Antwerpen",
    "sg:tags":[
        "physiotherapist"
    ],
    "wof:name":"Swerts E",
    "wof:placetype":"venue"
},
  "geometry": {"coordinates":[4.9865088463,51.1631736755],"type":"Point"}
}