{
  "type": "Feature",
  "properties": {
    "addr:full":"Prins Boudewijnlaan 62 Schilde Antwerpen 2970",
    "addr:housenumber":"62",
    "addr:postcode":"2970",
    "addr:street":"Prins Boudewijnlaan",
    "iso:country":"BE",
    "sg:address":"Prins Boudewijnlaan 62",
    "sg:city":"Schilde",
    "sg:classifiers":[
        {
            "category":"Health Services",
            "subcategory":"Health Practitioner",
            "type":"Services"
        }
    ],
    "sg:phone":"+32 3 385 04 65",
    "sg:postcode":"2970",
    "sg:province":"Antwerpen",
    "sg:tags":[
        "physiotherapist"
    ],
    "wof:name":"De Roeck A",
    "wof:placetype":"venue"
},
  "geometry": {"coordinates":[4.5917201042,51.2523002625],"type":"Point"}
}