{
  "type": "Feature",
  "properties": {
    "addr:full":"Avenue Marie De Hongrie 125 Bruxelles (ganshoren) Bruxelles-Capitale 1083",
    "addr:housenumber":"125",
    "addr:postcode":"1083",
    "addr:street":"Avenue Marie De Hongrie",
    "iso:country":"BE",
    "sg:address":"Avenue Marie De Hongrie 125",
    "sg:city":"Bruxelles (ganshoren)",
    "sg:classifiers":[
        {
            "category":"Health Services",
            "subcategory":"Health Practitioner",
            "type":"Services"
        }
    ],
    "sg:phone":"+32 2 468 34 28",
    "sg:postcode":"1083",
    "sg:province":"Bruxelles-Capitale",
    "sg:tags":[
        "physiotherapist"
    ],
    "wof:name":"Hizette J",
    "wof:placetype":"venue"
},
  "geometry": {"coordinates":[4.3006100655,50.8725891113],"type":"Point"}
}