{
  "type": "Feature",
  "properties": {
    "addr:full":"Rue Georges Delporte 4 Mons Hainaut 7000",
    "addr:housenumber":"4",
    "addr:postcode":"7000",
    "addr:street":"Rue Georges Delporte;Hainaut",
    "iso:country":"BE",
    "sg:address":"Rue Georges Delporte 4",
    "sg:city":"Mons",
    "sg:classifiers":[
        {
            "category":"Airport",
            "subcategory":"General Aviation",
            "type":"Transportation"
        }
    ],
    "sg:phone":"+32 65 84 24 06",
    "sg:postcode":"7000",
    "sg:province":"Hainaut",
    "sg:tags":[
        "transport"
    ],
    "wof:name":"Taxi Top Mons",
    "wof:placetype":"venue"
},
  "geometry": {"coordinates":[3.9437460899,50.4466018677],"type":"Point"}
}