{
  "type": "Feature",
  "properties": {
    "addr:full":"Rue De Hennin 16 Elsene/ixelles Bruxelles-Capitale 1050",
    "addr:housenumber":"16",
    "addr:postcode":"1050",
    "addr:street":"Rue De Hennin",
    "iso:country":"BE",
    "sg:address":"Rue De Hennin 16",
    "sg:city":"Elsene/ixelles",
    "sg:orig_category":"Rev\u00eatements pour sols and murs. Peinture",
    "sg:phone":"+32 2 647 42 20",
    "sg:postcode":"1050",
    "sg:province":"Bruxelles-Capitale",
    "wof:name":"Thierry Aughuet",
    "wof:placetype":"venue"
},
  "geometry": {"coordinates":[4.3689250946,50.8292503357],"type":"Point"}
}