{
  "type": "Feature",
  "properties": {
    "addr:full":"'s Gravendriesschelaan 29 Ichtegem West-Vlaanderen 8480",
    "addr:housenumber":"29",
    "addr:postcode":"8480",
    "addr:street":"';Gravendriesschelaan",
    "iso:country":"BE",
    "sg:address":"'s Gravendriesschelaan 29",
    "sg:city":"Ichtegem",
    "sg:classifiers":[
        {
            "category":"Personal",
            "subcategory":"Beauty Salon",
            "type":"Services"
        }
    ],
    "sg:phone":"+32 59 29 06 06",
    "sg:postcode":"8480",
    "sg:province":"West-Vlaanderen",
    "sg:tags":[
        "de",
        "coiffure"
    ],
    "wof:name":"Coiffure Raya",
    "wof:placetype":"venue"
},
  "geometry": {"coordinates":[3.0307919979,51.1338348389],"type":"Point"}
}