{
  "type": "Feature",
  "properties": {
    "addr:full":"Gulden-sporenlaan 1 Elsene/ixelles Bruxelles-Capitale 1050",
    "addr:housenumber":"1",
    "addr:postcode":"1050",
    "addr:street":"Gulden-Sporenlaan",
    "iso:country":"BE",
    "sg:address":"Gulden-sporenlaan 1",
    "sg:city":"Elsene/ixelles",
    "sg:orig_category":"Artsen and specialisten",
    "sg:phone":"+32 2 649 73 31",
    "sg:postcode":"1050",
    "sg:province":"Bruxelles-Capitale",
    "wof:name":"Monique Humblet",
    "wof:placetype":"venue"
},
  "geometry": {"coordinates":[4.3728861809,50.8255157471],"type":"Point"}
}