{
  "type": "Feature",
  "properties": {
    "iso:country":"BE",
    "sg:address":"Rue Bodarw\u00e9 5",
    "sg:city":"Weismes (faymonville)",
    "sg:classifiers":[
        {
            "category":"Building & Trades",
            "subcategory":"Cleaning & Sanitation",
            "type":"Services"
        }
    ],
    "sg:phone":"+32 80 67 96 74",
    "sg:postcode":"4950",
    "sg:province":"Li\u00e8ge",
    "sg:tags":[
        "janitor"
    ],
    "wof:name":"Margraff Nettoyage",
    "wof:placetype":"venue"
},
  "geometry": {"coordinates":[6.1353778839,50.407371521],"type":"Point"}
}