{
  "type": "Feature",
  "properties": {
    "addr:full":"Wolstraat 16 Antwerpen Antwerpen 2000",
    "addr:housenumber":"16",
    "addr:postcode":"2000",
    "addr:street":"Wolstraat",
    "iso:country":"BE",
    "sg:address":"Wolstraat 16",
    "sg:city":"Antwerpen",
    "sg:orig_category":"Zalen voor culturele evenementen",
    "sg:phone":"+32 3 213 37 41",
    "sg:postcode":"2000",
    "sg:province":"Antwerpen",
    "wof:name":"Amma African Art",
    "wof:placetype":"venue"
},
  "geometry": {"coordinates":[4.4033260345,51.2214813232],"type":"Point"}
}