{
  "type": "Feature",
  "properties": {
    "iso:country":"BE",
    "sg:address":"Ten Berg 1",
    "sg:city":"Aalst",
    "sg:classifiers":[
        {
            "category":"Cafe",
            "type":"Food & Drink"
        }
    ],
    "sg:phone":"+32 53 70 54 78",
    "sg:postcode":"9300",
    "sg:province":"Oost-Vlaanderen",
    "sg:tags":[
        "caf\u00e9s"
    ],
    "wof:name":"Frans Matthieu",
    "wof:placetype":"venue"
},
  "geometry": {"coordinates":[4.0642490387,50.9354438782],"type":"Point"}
}