{
  "type": "Feature",
  "properties": {
    "addr:full":"Avenue De La Gare 92 Aubange Luxembourg 6790",
    "addr:housenumber":"92",
    "addr:postcode":"6790",
    "addr:street":"Avenue De La Gare",
    "iso:country":"BE",
    "sg:address":"Avenue De La Gare 92",
    "sg:city":"Aubange",
    "sg:classifiers":[
        {
            "category":"Bars & Pubs",
            "type":"Food & Drink"
        }
    ],
    "sg:phone":"+32 63 38 31 42",
    "sg:postcode":"6790",
    "sg:province":"Luxembourg",
    "wof:name":"Caf\u00e9 Des Sports",
    "wof:placetype":"venue"
},
  "geometry": {"coordinates":[5.8032398224,49.5674247742],"type":"Point"}
}