{
  "type": "Feature",
  "properties": {
    "iso:country":"BE",
    "sg:address":"Steenweg Op Duisburg 15",
    "sg:city":"Overijse",
    "sg:orig_category":"Agences de publicit\u00e9. Imprimeries and copyshops",
    "sg:phone":"+32 2 687 43 05",
    "sg:postcode":"3090",
    "sg:province":"Vlaams-Brabant",
    "wof:name":"Signmaking Co V",
    "wof:placetype":"venue"
},
  "geometry": {"coordinates":[4.5370950699,50.7876167297],"type":"Point"}
}