{
  "type": "Feature",
  "properties": {
    "addr:full":"Wagenaarstraat 100 Waregem (beveren-leie) West-Vlaanderen 8791",
    "addr:housenumber":"100",
    "addr:postcode":"8791",
    "addr:street":"Wagenaarstraat",
    "iso:country":"BE",
    "sg:address":"Wagenaarstraat 100",
    "sg:city":"Waregem (beveren-leie)",
    "sg:classifiers":[
        {
            "category":"Building & Trades",
            "subcategory":"Construction",
            "type":"Services"
        }
    ],
    "sg:phone":"+32 56 72 42 33",
    "sg:postcode":"8791",
    "sg:province":"West-Vlaanderen",
    "sg:tags":[
        "ceiling"
    ],
    "wof:name":"Houtstudio De Meyere",
    "wof:placetype":"venue"
},
  "geometry": {"coordinates":[3.3500161171,50.8643569946],"type":"Point"}
}