{
  "type": "Feature",
  "properties": {
    "addr:full":"Bavinkhovebosstraat 2 Ardooie West-Vlaanderen 8850",
    "addr:housenumber":"2",
    "addr:postcode":"8850",
    "addr:street":"Bavinkhovebosstraat",
    "iso:country":"BE",
    "sg:address":"Bavinkhovebosstraat 2",
    "sg:city":"Ardooie",
    "sg:orig_category":"Groententeelt",
    "sg:phone":"+32 51 74 46 68",
    "sg:postcode":"8850",
    "sg:province":"West-Vlaanderen",
    "wof:name":"Jean Degroote",
    "wof:placetype":"venue"
},
  "geometry": {"coordinates":[3.2070279121,50.9551467896],"type":"Point"}
}