{
  "type": "Feature",
  "properties": {
    "iso:country":"BE",
    "sg:address":"Rue De La Gare 8",
    "sg:city":"Ronse/renaix",
    "sg:orig_category":"Equipement photographique",
    "sg:phone":"+32 55 21 88 24",
    "sg:postcode":"9600",
    "sg:province":"Oost-Vlaanderen",
    "wof:name":"Photo Luc/luc Photo Cine",
    "wof:placetype":"venue"
},
  "geometry": {"coordinates":[3.6009569168,50.7441177368],"type":"Point"}
}