{
  "type": "Feature",
  "properties": {
    "addr:full":"Magretstraat 51 Lochristi Oost-Vlaanderen 9080",
    "addr:housenumber":"51",
    "addr:postcode":"9080",
    "addr:street":"Magretstraat",
    "iso:country":"BE",
    "sg:address":"Magretstraat 51",
    "sg:city":"Lochristi",
    "sg:orig_category":"Artistes ind\u00e9pendants",
    "sg:phone":"+32 9 355 75 93",
    "sg:postcode":"9080",
    "sg:province":"Oost-Vlaanderen",
    "wof:name":"Rita Willems",
    "wof:placetype":"venue"
},
  "geometry": {"coordinates":[3.8734951019,51.0681991577],"type":"Point"}
}