{
  "type": "Feature",
  "properties": {
    "iso:country":"BE",
    "sg:address":"Melkerijstraat 1",
    "sg:city":"Linter",
    "sg:orig_category":"Goederenvervoer over de weg",
    "sg:phone":"+32 16 78 89 73",
    "sg:postcode":"3350",
    "sg:province":"Vlaams-Brabant",
    "wof:name":"Arnauts Marc",
    "wof:placetype":"venue"
},
  "geometry": {"coordinates":[5.0519380569,50.7943305969],"type":"Point"}
}