{
  "type": "Feature",
  "properties": {
    "iso:country":"BE",
    "sg:address":"Arendsstraat 101",
    "sg:city":"Harelbeke",
    "sg:orig_category":"Pain, p\u00e2tisseries and confiseries",
    "sg:phone":"+32 56 71 81 79",
    "sg:postcode":"8530",
    "sg:province":"West-Vlaanderen",
    "wof:name":"Bakkerij 't Molentje",
    "wof:placetype":"venue"
},
  "geometry": {"coordinates":[3.3223910332,50.8543014526],"type":"Point"}
}