{
  "type": "Feature",
  "properties": {
    "addr:full":"Truierweg 10 Borgloon Limburg 3840",
    "addr:housenumber":"10",
    "addr:postcode":"3840",
    "addr:street":"Truierweg",
    "iso:country":"BE",
    "sg:address":"Truierweg 10",
    "sg:city":"Borgloon",
    "sg:orig_category":"Tuinbenodigdheden",
    "sg:phone":"+32 12 74 15 44",
    "sg:postcode":"3840",
    "sg:province":"Limburg",
    "wof:name":"Rohnny Marchal",
    "wof:placetype":"venue"
},
  "geometry": {"coordinates":[5.292016983,50.8130073547],"type":"Point"}
}