{
  "type": "Feature",
  "properties": {
    "iso:country":"BE",
    "sg:address":"Rue De La Cath\u00c9drale 114",
    "sg:city":"Li\u00c8ge",
    "sg:orig_category":"Chaussures",
    "sg:phone":"+32 4 232 41 43",
    "sg:postcode":"4000",
    "sg:province":"Li\u00e8ge",
    "wof:name":"Maison Liverdi De Juliette Verlaine",
    "wof:placetype":"venue"
},
  "geometry": {"coordinates":[5.5716261864,50.6414070129],"type":"Point"}
}