{
  "type": "Feature",
  "properties": {
    "addr:full":"Stockholmstraat 27 Oostende West-Vlaanderen 8400",
    "addr:housenumber":"27",
    "addr:postcode":"8400",
    "addr:street":"Stockholmstraat",
    "iso:country":"BE",
    "sg:address":"Stockholmstraat 27",
    "sg:city":"Oostende",
    "sg:orig_category":"Avocats and conseillers juridiques",
    "sg:phone":"+32 59 70 60 85",
    "sg:postcode":"8400",
    "sg:province":"West-Vlaanderen",
    "wof:name":"Marianne Van Gheluwe",
    "wof:placetype":"venue"
},
  "geometry": {"coordinates":[2.9166889191,51.2262458801],"type":"Point"}
}