{
  "type": "Feature",
  "properties": {
    "addr:full":"Klaprozenweg 16 Linkebeek Vlaams-Brabant 1630",
    "addr:housenumber":"16",
    "addr:postcode":"1630",
    "addr:street":"Klaprozenweg",
    "iso:country":"BE",
    "sg:address":"Klaprozenweg 16",
    "sg:city":"Linkebeek",
    "sg:orig_category":"Artsen and specialisten",
    "sg:phone":"+32 2 381 20 96",
    "sg:postcode":"1630",
    "sg:province":"Vlaams-Brabant",
    "wof:name":"Caroline Dubois",
    "wof:placetype":"venue"
},
  "geometry": {"coordinates":[4.3477430344,50.7717552185],"type":"Point"}
}