{
  "type": "Feature",
  "properties": {
    "addr:full":"Avenue Hanlet 51 Verviers Li\u00e8ge 4802",
    "addr:housenumber":"51",
    "addr:postcode":"4802",
    "addr:street":"Avenue Hanlet",
    "iso:country":"BE",
    "sg:address":"Avenue Hanlet 51",
    "sg:city":"Verviers",
    "sg:orig_category":"Papeterie and fournitures de bureau Imprimeries and copyshops",
    "sg:phone":"+32 87 22 90 25",
    "sg:postcode":"4802",
    "sg:province":"Li\u00e8ge",
    "wof:name":"Data Product Supplies",
    "wof:placetype":"venue"
},
  "geometry": {"coordinates":[5.8671250343,50.5714111328],"type":"Point"}
}