{
  "type": "Feature",
  "properties": {
    "addr:full":"Wissenstraat 22 Dendermonde (groot) Oost-Vlaanderen 9200",
    "addr:housenumber":"22",
    "addr:postcode":"9200",
    "addr:street":"Wissenstraat;Groot Oost-Vlaanderen",
    "iso:country":"BE",
    "sg:address":"Wissenstraat 22",
    "sg:city":"Dendermonde (groot)",
    "sg:orig_category":"Agences d'exp\u00e9dition. Biens d'occasion",
    "sg:phone":"+32 52 21 73 43",
    "sg:postcode":"9200",
    "sg:province":"Oost-Vlaanderen",
    "wof:name":"I R C E B",
    "wof:placetype":"venue"
},
  "geometry": {"coordinates":[4.1465559006,51.0257911682],"type":"Point"}
}