{
  "type": "Feature",
  "properties": {
    "addr:full":"Dorpsstraat 16 Diepenbeek Limburg 3590",
    "addr:housenumber":"16",
    "addr:postcode":"3590",
    "addr:street":"Dorpsstraat",
    "iso:country":"BE",
    "sg:address":"Dorpsstraat 16",
    "sg:city":"Diepenbeek",
    "sg:orig_category":"Maroquinerie and articles de voyage. Chaussures",
    "sg:phone":"+32 11 32 33 40",
    "sg:postcode":"3590",
    "sg:province":"Limburg",
    "wof:name":"Schoenen Auwerx",
    "wof:placetype":"venue"
},
  "geometry": {"coordinates":[5.4205579758,50.9085540771],"type":"Point"}
}