{
  "type": "Feature",
  "properties": {
    "iso:country":"BE",
    "sg:address":"Ninovestraat 139",
    "sg:city":"Haaltert",
    "sg:classifiers":[
        {
            "category":"Health Services",
            "subcategory":"Health Practitioner",
            "type":"Services"
        }
    ],
    "sg:phone":"+32 53 83 42 01",
    "sg:postcode":"9450",
    "sg:province":"Oost-Vlaanderen",
    "sg:tags":[
        "physiotherapist"
    ],
    "wof:name":"Decoene Jacques",
    "wof:placetype":"venue"
},
  "geometry": {"coordinates":[4.024834156,50.897983551],"type":"Point"}
}