{
  "type": "Feature",
  "properties": {
    "addr:full":"Rue Des Peupliers 23 Estaimpuis Hainaut 7730",
    "addr:housenumber":"23",
    "addr:postcode":"7730",
    "addr:street":"Rue Des Peupliers;Hainaut",
    "iso:country":"BE",
    "sg:address":"Rue Des Peupliers 23",
    "sg:city":"Estaimpuis",
    "sg:orig_category":"Installation \u00e9lectrique r\u00e9sidentielle",
    "sg:phone":"+32 56 48 99 91",
    "sg:postcode":"7730",
    "sg:province":"Hainaut",
    "wof:name":"Roger Watthez",
    "wof:placetype":"venue"
},
  "geometry": {"coordinates":[3.2809309959,50.7110977173],"type":"Point"}
}