{
  "type": "Feature",
  "properties": {
    "iso:country":"BE",
    "sg:address":"Mevrouw Courtmansstraat 76",
    "sg:city":"Dendermonde",
    "sg:orig_category":"Boekenuitgeverijen Krantenuitgeverijen Tijdschriftenuitgeverijen",
    "sg:phone":"+32 52 21 13 54",
    "sg:postcode":"9200",
    "sg:province":"Oost-Vlaanderen",
    "wof:name":"Uitgeverij Velo",
    "wof:placetype":"venue"
},
  "geometry": {"coordinates":[4.0983099937,51.0315208435],"type":"Point"}
}