{
  "type": "Feature",
  "properties": {
    "addr:full":"Rue En Grande Foxhalle 60 Herstal Li\u00e8ge 4040",
    "addr:housenumber":"60",
    "addr:postcode":"4040",
    "addr:street":"Rue En Grande Foxhalle",
    "iso:country":"BE",
    "sg:address":"Rue En Grande Foxhalle 60",
    "sg:city":"Herstal",
    "sg:classifiers":[
        {
            "category":"Autos & Motor Vehicles",
            "subcategory":"Auto Supplies",
            "type":"Retail Goods"
        }
    ],
    "sg:phone":"+32 4 240 21 32",
    "sg:postcode":"4040",
    "sg:province":"Li\u00e8ge",
    "sg:tags":[
        "access",
        "automobile",
        "part",
        "-"
    ],
    "wof:name":"Ken Automobiles Sprl",
    "wof:placetype":"venue"
},
  "geometry": {"coordinates":[5.6225738525,50.6628570557],"type":"Point"}
}