{
  "type": "Feature",
  "properties": {
    "iso:country":"BE",
    "sg:address":"Handzamestraat 106",
    "sg:city":"Kortemark",
    "sg:classifiers":[
        {
            "category":"Autos & Motor Vehicles",
            "subcategory":"Recreational Vehicle Sales",
            "type":"Retail Goods"
        }
    ],
    "sg:phone":"+32 51 56 60 15",
    "sg:postcode":"8610",
    "sg:province":"West-Vlaanderen",
    "sg:tags":[
        "caravan",
        "accessory"
    ],
    "wof:name":"Maekelberg J.c.",
    "wof:placetype":"venue"
},
  "geometry": {"coordinates":[3.0248110294,51.0287513733],"type":"Point"}
}