{
  "type": "Feature",
  "properties": {
    "addr:full":"Molenstraat 6 Mortsel Antwerpen 2640",
    "addr:housenumber":"6",
    "addr:postcode":"2640",
    "addr:street":"Molenstraat",
    "iso:country":"BE",
    "sg:address":"Molenstraat 6",
    "sg:city":"Mortsel",
    "sg:classifiers":[
        {
            "category":"Personal",
            "type":"Services"
        }
    ],
    "sg:phone":"+32 3 440 37 39",
    "sg:postcode":"2640",
    "sg:province":"Antwerpen",
    "sg:tags":[
        "party",
        "planning"
    ],
    "wof:name":"Misselyn C",
    "wof:placetype":"venue"
},
  "geometry": {"coordinates":[4.4617261887,51.1656761169],"type":"Point"}
}