{
  "type": "Feature",
  "properties": {
    "addr:full":"Daalstraat 5 Beveren (vrasene) Oost-Vlaanderen 9120",
    "addr:housenumber":"5",
    "addr:postcode":"9120",
    "addr:street":"Daalstraat",
    "iso:country":"BE",
    "sg:address":"Daalstraat 5",
    "sg:city":"Beveren (vrasene)",
    "sg:classifiers":[
        {
            "category":"Retail",
            "subcategory":"Veterinary Services",
            "type":"Services"
        }
    ],
    "sg:phone":"+32 3 775 62 40",
    "sg:postcode":"9120",
    "sg:province":"Oost-Vlaanderen",
    "sg:tags":[
        "veterinarian"
    ],
    "wof:name":"Bogaert T",
    "wof:placetype":"venue"
},
  "geometry": {"coordinates":[4.1966710091,51.2175445557],"type":"Point"}
}