{
  "type": "Feature",
  "properties": {
    "addr:full":"Rue Taill\u00c9e Voie 2 Pont-a-celles Hainaut 6230",
    "addr:housenumber":"2",
    "addr:postcode":"6230",
    "addr:street":"Rue Taille\u0301E Voie",
    "iso:country":"BE",
    "sg:address":"Rue Taill\u00c9e Voie 2",
    "sg:city":"Pont-a-celles",
    "sg:orig_category":"Rundveehouders",
    "sg:phone":"+32 67 21 36 15",
    "sg:postcode":"6230",
    "sg:province":"Hainaut",
    "wof:name":"Christian Duchemin",
    "wof:placetype":"venue"
},
  "geometry": {"coordinates":[4.3582201004,50.5571670532],"type":"Point"}
}