{
  "type": "Feature",
  "properties": {
    "addr:full":"Heurstraat 97 Tongeren Limburg 3700",
    "addr:housenumber":"97",
    "addr:postcode":"3700",
    "addr:street":"Heurstraat",
    "iso:country":"BE",
    "sg:address":"Heurstraat 97",
    "sg:city":"Tongeren",
    "sg:orig_category":"Services pour animaux domestiques",
    "sg:phone":"+32 12 26 16 23",
    "sg:postcode":"3700",
    "sg:province":"Limburg",
    "wof:name":"Dierensalon Trudy",
    "wof:placetype":"venue"
},
  "geometry": {"coordinates":[5.4832210541,50.7441864014],"type":"Point"}
}