{
  "type": "Feature",
  "properties": {
    "iso:country":"BE",
    "sg:address":"Rue Du Mont Falise 105",
    "sg:city":"Huy",
    "sg:classifiers":[
        {
            "category":"Retail",
            "subcategory":"Auto Repair",
            "type":"Services"
        }
    ],
    "sg:phone":"+32 85 21 70 70",
    "sg:postcode":"4500",
    "sg:province":"Li\u00e8ge",
    "sg:tags":[
        "breakdown",
        "automobile",
        "-",
        "recovery"
    ],
    "wof:name":"Mont Falise D\u00e9pannage Scrl",
    "wof:placetype":"venue"
},
  "geometry": {"coordinates":[5.2386131287,50.5345535278],"type":"Point"}
}