{
  "type": "Feature",
  "properties": {
    "iso:country":"BE",
    "sg:address":"Baron De Gieylaan 73",
    "sg:city":"De Pinte",
    "sg:classifiers":[
        {
            "category":"Health Services",
            "subcategory":"Health Practitioner",
            "type":"Services"
        }
    ],
    "sg:phone":"+32 9 282 69 98",
    "sg:postcode":"9840",
    "sg:province":"Oost-Vlaanderen",
    "sg:tags":[
        "physiotherapist"
    ],
    "wof:name":"Coppens Danny",
    "wof:placetype":"venue"
},
  "geometry": {"coordinates":[3.6565029621,50.9937744141],"type":"Point"}
}