{
  "type": "Feature",
  "properties": {
    "iso:country":"BE",
    "sg:address":"Rue Des Fripiers 55",
    "sg:city":"Brussel/bruxelles",
    "sg:classifiers":[
        {
            "category":"Banks & Credit Unions",
            "subcategory":"Financial Services",
            "type":"Services"
        }
    ],
    "sg:phone":"+32 2 218 07 17",
    "sg:postcode":"1000",
    "sg:province":"Bruxelles-Capitale",
    "sg:tags":[
        "financier"
    ],
    "wof:name":"Soc. G\u00c9n\u00c9rale De Change",
    "wof:placetype":"venue"
},
  "geometry": {"coordinates":[4.35287714,50.8493499756],"type":"Point"}
}