{
  "type": "Feature",
  "properties": {
    "iso:country":"BE",
    "sg:address":"Kapelstraat 85",
    "sg:city":"Wommelgem",
    "sg:orig_category":"Herstellingen and onderhoud van auto's",
    "sg:phone":"+32 3 353 67 50",
    "sg:postcode":"2160",
    "sg:province":"Antwerpen",
    "wof:name":"Carrosserie Bertels",
    "wof:placetype":"venue"
},
  "geometry": {"coordinates":[4.5238509178,51.2087669373],"type":"Point"}
}