{
  "type": "Feature",
  "properties": {
    "addr:full":"9910 Knesselare (groot) Oost-Vlaanderen 9910",
    "addr:postcode":"9910;9910",
    "addr:street":"Groot Oost-Vlaanderen",
    "iso:country":"BE",
    "sg:address":"9910",
    "sg:city":"Knesselare (groot)",
    "sg:orig_category":"Pharmaciens",
    "sg:phone":"+32 900 10 500",
    "sg:postcode":"9910",
    "sg:province":"Oost-Vlaanderen",
    "wof:name":"Pharmacies De Garde",
    "wof:placetype":"venue"
},
  "geometry": {"coordinates":[3.4122149944,51.1392288208],"type":"Point"}
}