{
  "type": "Feature",
  "properties": {
    "addr:full":"Brugstraat 1 Knesselare Oost-Vlaanderen 9910",
    "addr:housenumber":"1",
    "addr:postcode":"9910",
    "addr:street":"Brugstraat;Oost-Vlaanderen",
    "iso:country":"BE",
    "sg:address":"Brugstraat 1",
    "sg:city":"Knesselare",
    "sg:orig_category":"Gespecialiseerde residenti\u00eble bouw",
    "sg:phone":"+32 9 375 30 28",
    "sg:postcode":"9910",
    "sg:province":"Oost-Vlaanderen",
    "wof:name":"Mario Ardeel",
    "wof:placetype":"venue"
},
  "geometry": {"coordinates":[3.4971818924,51.1410942078],"type":"Point"}
}