{
  "type": "Feature",
  "properties": {
    "addr:full":"Rue De La Sucrerie 9 Ath Hainaut 7800",
    "addr:housenumber":"9",
    "addr:postcode":"7800",
    "addr:street":"Rue De La Sucrerie",
    "iso:country":"BE",
    "sg:address":"Rue De La Sucrerie 9",
    "sg:city":"Ath",
    "sg:orig_category":"Woningbouw",
    "sg:phone":"+32 68 28 27 06",
    "sg:postcode":"7800",
    "sg:province":"Hainaut",
    "wof:name":"Herchuel",
    "wof:placetype":"venue"
},
  "geometry": {"coordinates":[3.7761909962,50.6243972778],"type":"Point"}
}