{
  "type": "Feature",
  "properties": {
    "iso:country":"BE",
    "sg:address":"Rue Charles Sambon 19",
    "sg:city":"Wavre",
    "sg:orig_category":"Dameskledingzaken",
    "sg:phone":"+32 10 22 94 15",
    "sg:postcode":"1300",
    "sg:province":"Brabant Wallon",
    "wof:name":"Basic Clothing",
    "wof:placetype":"venue"
},
  "geometry": {"coordinates":[4.6108198166,50.7160835266],"type":"Point"}
}