{
  "type": "Feature",
  "properties": {
    "addr:full":"Rue Des Fermes 2 Nassogne Luxembourg 6950",
    "addr:housenumber":"2",
    "addr:postcode":"6950",
    "addr:street":"Rue Des Fermes",
    "iso:country":"BE",
    "sg:address":"Rue Des Fermes 2",
    "sg:city":"Nassogne",
    "sg:classifiers":[
        {
            "category":"Insurance",
            "subcategory":"Life Insurance",
            "type":"Services"
        }
    ],
    "sg:phone":"+32 84 34 49 47",
    "sg:postcode":"6950",
    "sg:province":"Luxembourg",
    "sg:tags":[
        "assurance"
    ],
    "wof:name":"Nicolas Sarlet",
    "wof:placetype":"venue"
},
  "geometry": {"coordinates":[5.3774719238,50.1819076538],"type":"Point"}
}