{
  "type": "Feature",
  "properties": {
    "addr:full":"Nestor De Ti\u00c8restraat 197 Oudenaarde Oost-Vlaanderen 9700",
    "addr:housenumber":"197",
    "addr:postcode":"9700",
    "addr:street":"Nestor De Tie\u0300Restraat",
    "iso:country":"BE",
    "sg:address":"Nestor De Ti\u00c8restraat 197",
    "sg:city":"Oudenaarde",
    "sg:orig_category":"Rev\u00eatements pour sols and murs. Rev\u00eatements de sols and murs",
    "sg:phone":"+32 55 31 40 36",
    "sg:postcode":"9700",
    "sg:province":"Oost-Vlaanderen",
    "wof:name":"Deepafloor",
    "wof:placetype":"venue"
},
  "geometry": {"coordinates":[3.6210160255,50.8692131042],"type":"Point"}
}