{
  "type": "Feature",
  "properties": {
    "iso:country":"BE",
    "sg:address":"Rue Du Point De Vue 11",
    "sg:city":"Bi\u00e8vre (monceau-en-ardenne)",
    "sg:classifiers":[
        {
            "category":"Retail",
            "subcategory":"Auto Repair",
            "type":"Services"
        }
    ],
    "sg:phone":"+32 61 51 13 39",
    "sg:postcode":"5555",
    "sg:province":"Namur",
    "sg:tags":[
        "garage"
    ],
    "wof:name":"Petitjean",
    "wof:placetype":"venue"
},
  "geometry": {"coordinates":[4.9856309891,49.9044723511],"type":"Point"}
}