{
  "type": "Feature",
  "properties": {
    "addr:full":"Aven Ackers 1 Verrebroek Oost-Vlaanderen 9130",
    "addr:housenumber":"1",
    "addr:postcode":"9130",
    "addr:street":"Aven Ackers;Oost-Vlaanderen",
    "iso:country":"BE",
    "sg:address":"Aven Ackers 1",
    "sg:city":"Verrebroek",
    "sg:classifiers":[
        {
            "category":"Building & Trades",
            "subcategory":"Pest Control",
            "type":"Services"
        }
    ],
    "sg:phone":"+32 3 210 99 70",
    "sg:postcode":"9130",
    "sg:province":"Oost-Vlaanderen",
    "sg:tags":[
        "bleacher",
        "construction"
    ],
    "wof:name":"Euroscaff Nv",
    "wof:placetype":"venue"
},
  "geometry": {"coordinates":[4.1907539368,51.2505264282],"type":"Point"}
}