{
  "type": "Feature",
  "properties": {
    "iso:country":"BE",
    "sg:address":"Avenue Albert Ier 11",
    "sg:city":"Charleroi",
    "sg:orig_category":"Artsen and specialisten",
    "sg:phone":"+32 71 47 70 65",
    "sg:postcode":"6032",
    "sg:province":"Hainaut",
    "wof:name":"Dragan Salovic",
    "wof:placetype":"venue"
},
  "geometry": {"coordinates":[4.4252748489,50.3987808228],"type":"Point"}
}