{
  "type": "Feature",
  "properties": {
    "addr:full":"Rue Colonel Bourg 135 Evere/evere Bruxelles-Capitale 1140",
    "addr:housenumber":"135",
    "addr:postcode":"1140",
    "addr:street":"Rue Colonel Bourg",
    "iso:country":"BE",
    "sg:address":"Rue Colonel Bourg 135",
    "sg:city":"Evere/evere",
    "sg:classifiers":[
        {
            "category":"Social Services",
            "subcategory":"Retirement Home",
            "type":"Services"
        }
    ],
    "sg:phone":"+32 2 730 12 11",
    "sg:postcode":"1140",
    "sg:province":"Bruxelles-Capitale",
    "sg:tags":[
        "compagnies",
        "vie",
        "assurance",
        "habitation"
    ],
    "wof:name":"Assurances Groupe Josi",
    "wof:placetype":"venue"
},
  "geometry": {"coordinates":[4.4186749458,50.8560714722],"type":"Point"}
}