{
  "type": "Feature",
  "properties": {
    "addr:full":"Vilvoordelaan 4 - 8 Machelen Vlaams-Brabant 1830",
    "addr:housenumber":"4 8",
    "addr:postcode":"1830",
    "addr:street":"Vilvoordelaan",
    "iso:country":"BE",
    "sg:address":"Vilvoordelaan 4 - 8",
    "sg:city":"Machelen",
    "sg:orig_category":"HERSTELLING ELEKTRISCHE HUISHOUDAPPARATEN Huishoudapparaten, televisies and radio's Verhuur video an",
    "sg:phone":"+32 2 251 03 04",
    "sg:postcode":"1830",
    "sg:province":"Vlaams-Brabant",
    "wof:name":"Minnebo Nadine Electro",
    "wof:placetype":"venue"
},
  "geometry": {"coordinates":[4.4369888306,50.9138565063],"type":"Point"}
}