{
  "type": "Feature",
  "properties": {
    "addr:full":"Rue De Waremme 7 Geer (hollogne-sur-geer) Li\u00e8ge 4250",
    "addr:housenumber":"7",
    "addr:postcode":"4250",
    "addr:street":"Rue De Waremme;Hollogne-Sur-Geer",
    "iso:country":"BE",
    "sg:address":"Rue De Waremme 7",
    "sg:city":"Geer (hollogne-sur-geer)",
    "sg:classifiers":[
        {
            "category":"Health Services",
            "subcategory":"Health Practitioner",
            "type":"Services"
        }
    ],
    "sg:phone":"+32 19 32 20 75",
    "sg:postcode":"4250",
    "sg:province":"Li\u00e8ge",
    "sg:tags":[
        "physiotherapist"
    ],
    "wof:name":"Dubois N",
    "wof:placetype":"venue"
},
  "geometry": {"coordinates":[5.2133169174,50.6738586426],"type":"Point"}
}