{
  "type": "Feature",
  "properties": {
    "addr:full":"Rue Des Combattants 4 Vielsalm Luxembourg 6690",
    "addr:housenumber":"4",
    "addr:postcode":"6690",
    "addr:street":"Rue Des Combattants",
    "iso:country":"BE",
    "sg:address":"Rue Des Combattants 4",
    "sg:city":"Vielsalm",
    "sg:orig_category":"Travail and traitement du bois",
    "sg:phone":"+32 80 21 70 36",
    "sg:postcode":"6690",
    "sg:province":"Luxembourg",
    "wof:name":"Jean-henri Fourgon",
    "wof:placetype":"venue"
},
  "geometry": {"coordinates":[5.9188351631,50.2843284607],"type":"Point"}
}