{
  "type": "Feature",
  "properties": {
    "addr:full":"Hulsdonk 20b5 Gent Oost-Vlaanderen 9042",
    "addr:housenumber":"20b5",
    "addr:postcode":"9042",
    "addr:street":"Hulsdonk;Oost-Vlaanderen",
    "iso:country":"BE",
    "sg:address":"Hulsdonk 20b5",
    "sg:city":"Gent",
    "sg:orig_category":"Agences d'exp\u00e9dition",
    "sg:phone":"+32 9 345 63 23",
    "sg:postcode":"9042",
    "sg:province":"Oost-Vlaanderen",
    "wof:name":"Verstraeten En Verbrugge",
    "wof:placetype":"venue"
},
  "geometry": {"coordinates":[3.7816700935,51.1223831177],"type":"Point"}
}