{
  "type": "Feature",
  "properties": {
    "addr:full":"Populierenlaan 68 Bredene West-Vlaanderen 8450",
    "addr:housenumber":"68",
    "addr:postcode":"8450",
    "addr:street":"Populierenlaan",
    "iso:country":"BE",
    "sg:address":"Populierenlaan 68",
    "sg:city":"Bredene",
    "sg:classifiers":[
        {
            "category":"Utilities",
            "subcategory":"Telephone",
            "type":"Services"
        }
    ],
    "sg:phone":"+32 59 51 78 79",
    "sg:postcode":"8450",
    "sg:province":"West-Vlaanderen",
    "sg:tags":[
        "-",
        "internet"
    ],
    "wof:name":"Cybercom.be Bvba",
    "wof:placetype":"venue"
},
  "geometry": {"coordinates":[2.9653069973,51.2421264648],"type":"Point"}
}