{
  "type": "Feature",
  "properties": {
    "addr:full":"Markt 13 Tervuren Vlaams-Brabant 3080",
    "addr:housenumber":"13",
    "addr:postcode":"3080",
    "addr:street":"Markt",
    "iso:country":"BE",
    "sg:address":"Markt 13",
    "sg:city":"Tervuren",
    "sg:orig_category":"Bijouteries and horlogeries",
    "sg:phone":"+32 2 767 43 49",
    "sg:postcode":"3080",
    "sg:province":"Vlaams-Brabant",
    "wof:name":"Juwelen Sterckx",
    "wof:placetype":"venue"
},
  "geometry": {"coordinates":[4.5138421059,50.8245391846],"type":"Point"}
}