{
  "type": "Feature",
  "properties": {
    "iso:country":"BE",
    "sg:address":"Place Du Vingt Ao\u00dbt 3b41",
    "sg:city":"Li\u00c8ge",
    "sg:orig_category":"Schoonheidssalons",
    "sg:phone":"+32 4 223 43 16",
    "sg:postcode":"4000",
    "sg:province":"Li\u00e8ge",
    "wof:name":"Marie-th\u00c9r\u00c8se Lecomte",
    "wof:placetype":"venue"
},
  "geometry": {"coordinates":[5.5747551918,50.6412200928],"type":"Point"}
}