{
  "type": "Feature",
  "properties": {
    "iso:country":"BE",
    "sg:address":"Boulevard Winston Churchill 7",
    "sg:city":"Mons",
    "sg:classifiers":[
        {
            "category":"Health Services",
            "subcategory":"Health Practitioner",
            "type":"Services"
        }
    ],
    "sg:phone":"+32 65 34 04 23",
    "sg:postcode":"7000",
    "sg:province":"Hainaut",
    "sg:tags":[
        "physiotherapist"
    ],
    "wof:name":"Beugnies J",
    "wof:placetype":"venue"
},
  "geometry": {"coordinates":[3.9550640583,50.460559845],"type":"Point"}
}