{
  "type": "Feature",
  "properties": {
    "iso:country":"BE",
    "sg:address":"Begijnhofstraat 2",
    "sg:city":"Kortrijk",
    "sg:classifiers":[
        {
            "category":"Shopping",
            "subcategory":"Antiques",
            "type":"Retail Goods"
        }
    ],
    "sg:phone":"+32 56 21 77 15",
    "sg:postcode":"8500",
    "sg:province":"West-Vlaanderen",
    "wof:name":"Oud Cortrijcke",
    "wof:placetype":"venue"
},
  "geometry": {"coordinates":[3.2673530579,50.8279266357],"type":"Point"}
}