{
  "type": "Feature",
  "properties": {
    "addr:full":"Rue De La Logette 15 Sambreville Namur 5060",
    "addr:housenumber":"15",
    "addr:postcode":"5060",
    "addr:street":"Rue De La Logette",
    "iso:country":"BE",
    "sg:address":"Rue De La Logette 15",
    "sg:city":"Sambreville",
    "sg:orig_category":"Entretien and r\u00e9parations de voitures",
    "sg:phone":"+32 71 74 02 86",
    "sg:postcode":"5060",
    "sg:province":"Namur",
    "wof:name":"Benoit Henriet",
    "wof:placetype":"venue"
},
  "geometry": {"coordinates":[4.6285200119,50.4448738098],"type":"Point"}
}