{
  "type": "Feature",
  "properties": {
    "addr:full":"Houtemstraat 176 Tienen Vlaams-Brabant 3300",
    "addr:housenumber":"176",
    "addr:postcode":"3300",
    "addr:street":"Houtemstraat",
    "iso:country":"BE",
    "sg:address":"Houtemstraat 176",
    "sg:city":"Tienen",
    "sg:orig_category":"Artsen and specialisten",
    "sg:phone":"+32 16 81 22 56",
    "sg:postcode":"3300",
    "sg:province":"Vlaams-Brabant",
    "wof:name":"Jacques Brasseur",
    "wof:placetype":"venue"
},
  "geometry": {"coordinates":[4.9424009323,50.8172416687],"type":"Point"}
}