{
  "type": "Feature",
  "properties": {
    "addr:full":"Rue De Neufchateau 97 Bastogne Luxembourg 6600",
    "addr:housenumber":"97",
    "addr:postcode":"6600",
    "addr:street":"Rue De Neufchateau",
    "iso:country":"BE",
    "sg:address":"Rue De Neufchateau 97",
    "sg:city":"Bastogne",
    "sg:orig_category":"HUISBRANDOLIE",
    "sg:phone":"+32 61 21 12 14",
    "sg:postcode":"6600",
    "sg:province":"Luxembourg",
    "wof:name":"Esso",
    "wof:placetype":"venue"
},
  "geometry": {"coordinates":[5.7076668739,49.9959373474],"type":"Point"}
}