{
  "type": "Feature",
  "properties": {
    "addr:full":"Koutermolenstraat 67 Kortemark West-Vlaanderen 8610",
    "addr:housenumber":"67",
    "addr:postcode":"8610",
    "addr:street":"Koutermolenstraat",
    "iso:country":"BE",
    "sg:address":"Koutermolenstraat 67",
    "sg:city":"Kortemark",
    "sg:orig_category":"Eleveurs de bovins",
    "sg:phone":"+32 51 56 68 41",
    "sg:postcode":"8610",
    "sg:province":"West-Vlaanderen",
    "wof:name":"Michel Cappelle",
    "wof:placetype":"venue"
},
  "geometry": {"coordinates":[3.0407259464,51.0375785828],"type":"Point"}
}