{
  "type": "Feature",
  "properties": {
    "iso:country":"BE",
    "sg:address":"Ooststatiestraat 95",
    "sg:city":"Kontich",
    "sg:orig_category":"Kapsalons Mobiele kappers",
    "sg:phone":"+32 3 458 29 81",
    "sg:postcode":"2550",
    "sg:province":"Antwerpen",
    "wof:name":"Coiffure Marina",
    "wof:placetype":"venue"
},
  "geometry": {"coordinates":[4.4517011642,51.1344032288],"type":"Point"}
}