{
  "type": "Feature",
  "properties": {
    "iso:country":"BE",
    "sg:address":"Leemstraat 46",
    "sg:city":"Lochristi",
    "sg:orig_category":"Eleveurs de bovins",
    "sg:phone":"+32 9 355 57 50",
    "sg:postcode":"9080",
    "sg:province":"Oost-Vlaanderen",
    "wof:name":"Godelieve Verstraeten",
    "wof:placetype":"venue"
},
  "geometry": {"coordinates":[3.8796770573,51.1297531128],"type":"Point"}
}