{
  "type": "Feature",
  "properties": {
    "addr:full":"Kleine Lostraat 9 Roosdaal Vlaams-Brabant 1760",
    "addr:housenumber":"9",
    "addr:postcode":"1760",
    "addr:street":"Kleine Lostraat",
    "iso:country":"BE",
    "sg:address":"Kleine Lostraat 9",
    "sg:city":"Roosdaal",
    "sg:orig_category":"Rev\u00eatements de sols and murs",
    "sg:phone":"+32 54 33 07 44",
    "sg:postcode":"1760",
    "sg:province":"Vlaams-Brabant",
    "wof:name":"Van Snick-de Pever",
    "wof:placetype":"venue"
},
  "geometry": {"coordinates":[4.0915942192,50.8421592712],"type":"Point"}
}