{
  "type": "Feature",
  "properties": {
    "addr:full":"Aubettestraat 35 Kortrijk (bellegem) West-Vlaanderen 8510",
    "addr:housenumber":"35",
    "addr:postcode":"8510",
    "addr:street":"Aubettestraat",
    "iso:country":"BE",
    "sg:address":"Aubettestraat 35",
    "sg:city":"Kortrijk (bellegem)",
    "sg:classifiers":[
        {
            "category":"Retail",
            "subcategory":"Veterinary Services",
            "type":"Services"
        }
    ],
    "sg:phone":"+32 56 20 47 90",
    "sg:postcode":"8510",
    "sg:province":"West-Vlaanderen",
    "sg:tags":[
        "veterinarian"
    ],
    "wof:name":"Dewit I",
    "wof:placetype":"venue"
},
  "geometry": {"coordinates":[3.2855329514,50.7879829407],"type":"Point"}
}