{
  "type": "Feature",
  "properties": {
    "addr:full":"Kerkplein 1 Roeselare (rumbeke) West-Vlaanderen 8800",
    "addr:housenumber":"1",
    "addr:postcode":"8800",
    "addr:street":"Kerkplein",
    "iso:country":"BE",
    "sg:address":"Kerkplein 1",
    "sg:city":"Roeselare (rumbeke)",
    "sg:classifiers":[
        {
            "category":"Bars & Pubs",
            "type":"Food & Drink"
        }
    ],
    "sg:phone":"+32 51 24 62 73",
    "sg:postcode":"8800",
    "sg:province":"West-Vlaanderen",
    "sg:tags":[
        "tavern"
    ],
    "wof:name":"Tonne (de)",
    "wof:placetype":"venue"
},
  "geometry": {"coordinates":[3.1541221142,50.9334640503],"type":"Point"}
}