{
  "type": "Feature",
  "properties": {
    "addr:full":"Amerikastraat 25 Sint-gillis/saint-gilles Bruxelles-Capitale 1060",
    "addr:housenumber":"25",
    "addr:postcode":"1060",
    "addr:street":"Amerikastraat",
    "iso:country":"BE",
    "sg:address":"Amerikastraat 25",
    "sg:city":"Sint-gillis/saint-gilles",
    "sg:orig_category":"Musea and historische gebouwen",
    "sg:phone":"+32 2 543 04 90",
    "sg:postcode":"1060",
    "sg:province":"Bruxelles-Capitale",
    "wof:name":"Les Amis Du Mus\u00c9e Horta",
    "wof:placetype":"venue"
},
  "geometry": {"coordinates":[4.3554778099,50.8241691589],"type":"Point"}
}