{
  "type": "Feature",
  "properties": {
    "addr:full":"Rue De La Bont\u00e9 3 Bruxelles Bruxelles-Capitale 1000",
    "addr:housenumber":"3",
    "addr:postcode":"1000",
    "addr:street":"Rue De La Bonte\u0301",
    "iso:country":"BE",
    "sg:address":"Rue De La Bont\u00e9 3",
    "sg:city":"Bruxelles",
    "sg:classifiers":[
        {
            "category":"Personal",
            "subcategory":"Beauty Salon",
            "type":"Services"
        }
    ],
    "sg:phone":"+32 2 538 69 73",
    "sg:postcode":"1000",
    "sg:province":"Bruxelles-Capitale",
    "sg:tags":[
        "product",
        "-",
        "apparatus"
    ],
    "wof:name":"Mary'n Center Sprl",
    "wof:placetype":"venue"
},
  "geometry": {"coordinates":[4.3582758904,50.8316993713],"type":"Point"}
}