{
  "type": "Feature",
  "properties": {
    "addr:full":"Karrewegstraat 150-154 Deinze Oost-Vlaanderen 9800",
    "addr:housenumber":"150-154",
    "addr:postcode":"9800",
    "addr:street":"Karrewegstraat",
    "iso:country":"BE",
    "sg:address":"Karrewegstraat 150-154",
    "sg:city":"Deinze",
    "sg:classifiers":[
        {
            "category":"Manufacturing",
            "subcategory":"Rubber & Plastics",
            "type":"Manufacturing & Wholesale Goods"
        }
    ],
    "sg:phone":"+32 9 386 32 32",
    "sg:postcode":"9800",
    "sg:province":"Oost-Vlaanderen",
    "wof:name":"Generale Maatschappij Voor Plastiek Nv",
    "wof:placetype":"venue"
},
  "geometry": {"coordinates":[3.530174017,50.9863166809],"type":"Point"}
}