{
  "type": "Feature",
  "properties": {
    "iso:country":"BE",
    "sg:address":"Steenweg Op Brussel 84",
    "sg:city":"Opwijk",
    "sg:orig_category":"Herstellingen and onderhoud van auto's Onderdelen and accessoires voor auto's Voertuigen",
    "sg:phone":"+32 52 35 73 66",
    "sg:postcode":"1745",
    "sg:province":"Vlaams-Brabant",
    "wof:name":"Autohandel Vereeken",
    "wof:placetype":"venue"
},
  "geometry": {"coordinates":[4.1627178192,50.9516410828],"type":"Point"}
}