{
  "type": "Feature",
  "properties": {
    "iso:country":"BE",
    "sg:address":"Chauss\u00c9e De Namur 135",
    "sg:city":"Villers-la-ville",
    "sg:classifiers":[
        {
            "category":"Food & Beverages",
            "subcategory":"Fruits & Vegetables",
            "type":"Retail Goods"
        }
    ],
    "sg:phone":"+32 71 87 97 60",
    "sg:postcode":"1495",
    "sg:province":"Brabant Wallon",
    "sg:tags":[
        "groenten"
    ],
    "wof:name":"Moise Maton",
    "wof:placetype":"venue"
},
  "geometry": {"coordinates":[4.5008349419,50.5528259277],"type":"Point"}
}