{
  "type": "Feature",
  "properties": {
    "iso:country":"BE",
    "sg:address":"Spoorweglei 56",
    "sg:city":"Lier",
    "sg:classifiers":[
        {
            "category":"Arena",
            "subcategory":"Sports Club",
            "type":"Entertainment"
        }
    ],
    "sg:phone":"+32 3 480 03 73",
    "sg:postcode":"2500",
    "sg:province":"Antwerpen",
    "sg:tags":[
        "de"
    ],
    "wof:name":"A.c. Lierse",
    "wof:placetype":"venue"
},
  "geometry": {"coordinates":[4.5677199364,51.1370887756],"type":"Point"}
}