{
  "type": "Feature",
  "properties": {
    "addr:full":"18 Beverenstraat 8540 Deerlijk 18",
    "addr:housenumber":"18;18",
    "addr:postcode":"8540",
    "addr:street":"Beverenstraat;Deerlijk",
    "iso:country":"BE",
    "sg:address":"18",
    "sg:city":"Beverenstraat 8540 Deerlijk",
    "sg:classifiers":[
        {
            "category":"Manufacturing",
            "subcategory":"Textiles",
            "type":"Manufacturing & Wholesale Goods"
        }
    ],
    "sg:phone":"+32 56 71 71 71",
    "sg:postcode":"18",
    "sg:tags":[
        "linen",
        "clothing",
        "fabric"
    ],
    "wof:name":"V & V Textiles Nv",
    "wof:placetype":"venue"
},
  "geometry": {"coordinates":[3.350030899,50.8557701111],"type":"Point"}
}