{
  "type": "Feature",
  "properties": {
    "addr:full":"Oude Gentbaan 247 Aalst Oost-Vlaanderen 9300",
    "addr:housenumber":"247",
    "addr:postcode":"9300",
    "addr:street":"Oude Gentbaan",
    "iso:country":"BE",
    "sg:address":"Oude Gentbaan 247",
    "sg:city":"Aalst",
    "sg:classifiers":[
        {
            "category":"Shopping",
            "subcategory":"Computers & Home Electronics",
            "type":"Retail Goods"
        }
    ],
    "sg:phone":"+32 53 70 44 00",
    "sg:postcode":"9300",
    "sg:province":"Oost-Vlaanderen",
    "sg:tags":[
        "plate",
        "name"
    ],
    "wof:name":"Van Der Heyden P Cvba",
    "wof:placetype":"venue"
},
  "geometry": {"coordinates":[4.0027837753,50.9426651001],"type":"Point"}
}