{
  "type": "Feature",
  "properties": {
    "iso:country":"BE",
    "sg:address":"Rue Des Raines 46",
    "sg:city":"Verviers",
    "sg:classifiers":[
        {
            "category":"Social Services",
            "type":"Services"
        }
    ],
    "sg:phone":"+32 87 78 62 16",
    "sg:postcode":"4800",
    "sg:province":"Li\u00e8ge",
    "wof:name":"Funambule Asbl",
    "wof:placetype":"venue"
},
  "geometry": {"coordinates":[5.868268013,50.5946884155],"type":"Point"}
}