{
  "type": "Feature",
  "properties": {
    "addr:full":"Ooststraat 4 Lo-reninge West-Vlaanderen 8647",
    "addr:housenumber":"4",
    "addr:postcode":"8647",
    "addr:street":"Ooststraat",
    "iso:country":"BE",
    "sg:address":"Ooststraat 4",
    "sg:city":"Lo-reninge",
    "sg:orig_category":"Traducteurs and interpr\u00e8tes",
    "sg:phone":"+32 58 28 96 82",
    "sg:postcode":"8647",
    "sg:province":"West-Vlaanderen",
    "wof:name":"Slambrouck D. Cbtip/bkvtf",
    "wof:placetype":"venue"
},
  "geometry": {"coordinates":[2.7490820885,50.9808425903],"type":"Point"}
}