{
  "type": "Feature",
  "properties": {
    "iso:country":"BE",
    "sg:address":"Erabelstraat 3",
    "sg:city":"Genk",
    "sg:classifiers":[
        {
            "category":"Cafe",
            "type":"Food & Drink"
        }
    ],
    "sg:phone":"+32 89 35 68 03",
    "sg:postcode":"3600",
    "sg:province":"Limburg",
    "sg:tags":[
        "caf\u00e9s"
    ],
    "wof:name":"Salvatore Caltabellotta",
    "wof:placetype":"venue"
},
  "geometry": {"coordinates":[5.4634990692,50.9748878479],"type":"Point"}
}