{
  "type": "Feature",
  "properties": {
    "iso:country":"BE",
    "sg:address":"Voie Du Ch\u00cane 21",
    "sg:city":"Herve",
    "sg:orig_category":"Epiceries",
    "sg:phone":"+32 87 67 58 65",
    "sg:postcode":"4650",
    "sg:province":"Li\u00e8ge",
    "wof:name":"Englebert",
    "wof:placetype":"venue"
},
  "geometry": {"coordinates":[5.7841701508,50.6383895874],"type":"Point"}
}