{
  "type": "Feature",
  "properties": {
    "addr:full":"Grand'route 42 Crisn\u00e9e Li\u00e8ge 4367",
    "addr:housenumber":"42",
    "addr:postcode":"4367",
    "addr:street":"Grand'Route",
    "iso:country":"BE",
    "sg:address":"Grand'route 42",
    "sg:city":"Crisn\u00e9e",
    "sg:classifiers":[
        {
            "category":"Bakery",
            "type":"Food & Drink"
        }
    ],
    "sg:phone":"+32 4 257 63 34",
    "sg:postcode":"4367",
    "sg:province":"Li\u00e8ge",
    "sg:tags":[
        "confectioner",
        "baker"
    ],
    "wof:name":"Horten S",
    "wof:placetype":"venue"
},
  "geometry": {"coordinates":[5.3976302147,50.7166290283],"type":"Point"}
}