{
  "type": "Feature",
  "properties": {
    "addr:full":"Oude Pittemstraat 23 Meulebeke West-Vlaanderen 8760",
    "addr:housenumber":"23",
    "addr:postcode":"8760",
    "addr:street":"Oude Pittemstraat",
    "iso:country":"BE",
    "sg:address":"Oude Pittemstraat 23",
    "sg:city":"Meulebeke",
    "sg:classifiers":[
        {
            "category":"Professional",
            "subcategory":"Art Services",
            "type":"Services"
        }
    ],
    "sg:phone":"+32 51 40 83 37",
    "sg:postcode":"8760",
    "sg:province":"West-Vlaanderen",
    "sg:tags":[
        "interior",
        "designer"
    ],
    "wof:name":"Van Hulle K",
    "wof:placetype":"venue"
},
  "geometry": {"coordinates":[3.2875740528,50.9520874023],"type":"Point"}
}