{
  "type": "Feature",
  "properties": {
    "addr:full":"Lozijde 71 Lille Antwerpen 2275",
    "addr:housenumber":"71",
    "addr:postcode":"2275",
    "addr:street":"Lozijde",
    "iso:country":"BE",
    "sg:address":"Lozijde 71",
    "sg:city":"Lille",
    "sg:orig_category":"Traitements param\u00e9dicaux",
    "sg:phone":"+32 14 55 56 97",
    "sg:postcode":"2275",
    "sg:province":"Antwerpen",
    "wof:name":"Rita Nuyts",
    "wof:placetype":"venue"
},
  "geometry": {"coordinates":[4.8702440262,51.2765922546],"type":"Point"}
}