{
  "type": "Feature",
  "properties": {
    "iso:country":"BE",
    "sg:address":"Nieuwstraat 4",
    "sg:city":"Herzele",
    "sg:orig_category":"Epiceries",
    "sg:phone":"+32 53 62 88 79",
    "sg:postcode":"9552",
    "sg:province":"Oost-Vlaanderen",
    "wof:name":"Hilde Leus",
    "wof:placetype":"venue"
},
  "geometry": {"coordinates":[3.8928079605,50.9034156799],"type":"Point"}
}