{
  "type": "Feature",
  "properties": {
    "iso:country":"BE",
    "sg:address":"Markt 16a",
    "sg:city":"Zele",
    "sg:classifiers":[
        {
            "category":"Bakery",
            "type":"Food & Drink"
        }
    ],
    "sg:phone":"+32 52 44 42 00",
    "sg:postcode":"9240",
    "sg:province":"Oost-Vlaanderen",
    "sg:tags":[
        "confectioner",
        "baker"
    ],
    "wof:name":"D'hont W",
    "wof:placetype":"venue"
},
  "geometry": {"coordinates":[4.0392799377,51.0680007935],"type":"Point"}
}