{
  "type": "Feature",
  "properties": {
    "addr:full":"Eikevelden 1a Geel Antwerpen 2440",
    "addr:housenumber":"1a",
    "addr:postcode":"2440",
    "addr:street":"Eikevelden",
    "iso:country":"BE",
    "sg:address":"Eikevelden 1a",
    "sg:city":"Geel",
    "sg:classifiers":[
        {
            "category":"Health Services",
            "subcategory":"Doctor",
            "type":"Services"
        }
    ],
    "sg:phone":"+32 14 72 63 25",
    "sg:postcode":"2440",
    "sg:province":"Antwerpen",
    "sg:tags":[
        "medicinephysicians",
        "surgeon"
    ],
    "wof:name":"Lafullarde T",
    "wof:placetype":"venue"
},
  "geometry": {"coordinates":[4.9944372177,51.1543235779],"type":"Point"}
}