{
  "type": "Feature",
  "properties": {
    "iso:country":"BE",
    "sg:address":"Frans Beirenslaan 187",
    "sg:city":"Borsbeek",
    "sg:classifiers":[
        {
            "category":"Autos & Motor Vehicles",
            "subcategory":"Fuel & Gas Station",
            "type":"Retail Goods"
        }
    ],
    "sg:phone":"+32 3 322 75 96",
    "sg:postcode":"2150",
    "sg:province":"Antwerpen",
    "sg:tags":[
        "stations-service",
        "carburants"
    ],
    "wof:name":"Gedimar",
    "wof:placetype":"venue"
},
  "geometry": {"coordinates":[4.4824151993,51.1989860535],"type":"Point"}
}