{
  "type": "Feature",
  "properties": {
    "addr:full":"Heerbaan 54 Kortenaken Vlaams-Brabant 3472",
    "addr:housenumber":"54",
    "addr:postcode":"3472",
    "addr:street":"Heerbaan",
    "iso:country":"BE",
    "sg:address":"Heerbaan 54",
    "sg:city":"Kortenaken",
    "sg:orig_category":"Plaatsen van vloer- and muurbekleding Schilders Verlichting and huishoudartikelen",
    "sg:phone":"+32 16 77 72 26",
    "sg:postcode":"3472",
    "sg:province":"Vlaams-Brabant",
    "wof:name":"Peetermans & Van Welde",
    "wof:placetype":"venue"
},
  "geometry": {"coordinates":[5.0105490685,50.8926315308],"type":"Point"}
}