{
  "type": "Feature",
  "properties": {
    "iso:country":"BE",
    "sg:address":"Boulevard Pr\u00c9sident Kennedy 135",
    "sg:city":"Mons",
    "sg:orig_category":"Entretien and r\u00e9parations de voitures. D\u00e9taillants en pi\u00e8ces and accessoires de voitures",
    "sg:phone":"+32 65 33 93 51",
    "sg:postcode":"7000",
    "sg:province":"Hainaut",
    "wof:name":"Roueaux",
    "wof:placetype":"venue"
},
  "geometry": {"coordinates":[3.9571149349,50.4603347778],"type":"Point"}
}