{
  "type": "Feature",
  "properties": {
    "addr:full":"R. De L'ancien Velodrome 4 Esneux Li\u00e8ge 4130",
    "addr:housenumber":"4",
    "addr:postcode":"4130",
    "addr:street":"Velodrome",
    "iso:country":"BE",
    "sg:address":"R. De L'ancien Velodrome 4",
    "sg:city":"Esneux",
    "sg:classifiers":[
        {
            "category":"Professional",
            "subcategory":"Accounting & Tax Preparation",
            "type":"Services"
        }
    ],
    "sg:phone":"+32 4 388 33 51",
    "sg:postcode":"4130",
    "sg:province":"Li\u00e8ge",
    "sg:tags":[
        "accountant"
    ],
    "wof:name":"Martine Henrot",
    "wof:placetype":"venue"
},
  "geometry": {"coordinates":[5.5762238503,50.5638275146],"type":"Point"}
}