{
  "type": "Feature",
  "properties": {
    "addr:full":"Rue De Fafchamps 51 Blegny Li\u00e8ge 4670",
    "addr:housenumber":"51",
    "addr:postcode":"4670",
    "addr:street":"Rue De Fafchamps",
    "iso:country":"BE",
    "sg:address":"Rue De Fafchamps 51",
    "sg:city":"Blegny",
    "sg:orig_category":"Artsen and specialisten",
    "sg:phone":"+32 4 387 55 33",
    "sg:postcode":"4670",
    "sg:province":"Li\u00e8ge",
    "wof:name":"G. Delcroix",
    "wof:placetype":"venue"
},
  "geometry": {"coordinates":[5.7232341766,50.6691360474],"type":"Point"}
}