{
  "type": "Feature",
  "properties": {
    "addr:full":"Grand'place 31 Jodoigne Brabant Wallon 1370",
    "addr:housenumber":"31",
    "addr:postcode":"1370",
    "addr:street":"Grand'Place",
    "iso:country":"BE",
    "sg:address":"Grand'place 31",
    "sg:city":"Jodoigne",
    "sg:classifiers":[
        {
            "category":"Shopping",
            "subcategory":"Bicycles & Sporting Goods",
            "type":"Retail Goods"
        }
    ],
    "sg:phone":"+32 10 81 01 33",
    "sg:postcode":"1370",
    "sg:province":"Brabant Wallon",
    "sg:tags":[
        "sport",
        "-"
    ],
    "wof:name":"Macadam Rider",
    "wof:placetype":"venue"
},
  "geometry": {"coordinates":[4.8666749001,50.7255744934],"type":"Point"}
}