{
  "type": "Feature",
  "properties": {
    "addr:full":"Rijselseweg 62c Ieper West-Vlaanderen 8900",
    "addr:housenumber":"62c",
    "addr:postcode":"8900",
    "addr:street":"Rijselseweg",
    "iso:country":"BE",
    "sg:address":"Rijselseweg 62c",
    "sg:city":"Ieper",
    "sg:orig_category":"Installation de menuiserie en bois and plastique",
    "sg:phone":"+32 57 20 73 83",
    "sg:postcode":"8900",
    "sg:province":"West-Vlaanderen",
    "wof:name":"Gilbert Caesteker",
    "wof:placetype":"venue"
},
  "geometry": {"coordinates":[2.888835907,50.8412857056],"type":"Point"}
}