{
  "type": "Feature",
  "properties": {
    "iso:country":"BE",
    "sg:address":"Jacques Pasturlaan 8",
    "sg:city":"Ukkel/uccle",
    "sg:orig_category":"Boekhouders",
    "sg:phone":"+32 2 374 90 44",
    "sg:postcode":"1180",
    "sg:province":"Bruxelles-Capitale",
    "wof:name":"Fr\u00c9deric Goffard",
    "wof:placetype":"venue"
},
  "geometry": {"coordinates":[4.3744220734,50.7880859375],"type":"Point"}
}