{
  "type": "Feature",
  "properties": {
    "addr:full":"Rue Tout-vent 3ba Charleroi Hainaut 6041",
    "addr:housenumber":"3ba",
    "addr:postcode":"6041",
    "addr:street":"Rue Tout-Vent;Hainaut",
    "iso:country":"BE",
    "sg:address":"Rue Tout-vent 3ba",
    "sg:city":"Charleroi",
    "sg:orig_category":"Boekhouders",
    "sg:phone":"+32 71 35 09 42",
    "sg:postcode":"6041",
    "sg:province":"Hainaut",
    "wof:name":"Valerie Binet",
    "wof:placetype":"venue"
},
  "geometry": {"coordinates":[4.4290928841,50.4735565186],"type":"Point"}
}