{
  "type": "Feature",
  "properties": {
    "addr:full":"Steenakkerstraat 6 Tielt West-Vlaanderen 8700",
    "addr:housenumber":"6",
    "addr:postcode":"8700",
    "addr:street":"Steenakkerstraat",
    "iso:country":"BE",
    "sg:address":"Steenakkerstraat 6",
    "sg:city":"Tielt",
    "sg:classifiers":[
        {
            "category":"Cafe",
            "type":"Food & Drink"
        }
    ],
    "sg:phone":"+32 51 40 50 52",
    "sg:postcode":"8700",
    "sg:province":"West-Vlaanderen",
    "sg:tags":[
        "caf\u00e9s"
    ],
    "wof:name":"Peter Van Doorne",
    "wof:placetype":"venue"
},
  "geometry": {"coordinates":[3.329843998,51.0237846375],"type":"Point"}
}