{
  "type": "Feature",
  "properties": {
    "iso:country":"BE",
    "sg:address":"Rue De La Fonderie 6bc/5",
    "sg:city":"Nivelles",
    "sg:classifiers":[
        {
            "category":"Cafe",
            "type":"Food & Drink"
        }
    ],
    "sg:phone":"+32 67 84 05 22",
    "sg:postcode":"1400",
    "sg:province":"Brabant Wallon",
    "sg:tags":[
        "caf\u00e9s"
    ],
    "wof:name":"Pascal Van Kerckhoven",
    "wof:placetype":"venue"
},
  "geometry": {"coordinates":[4.3345761299,50.5986862183],"type":"Point"}
}