{
  "type": "Feature",
  "properties": {
    "iso:country":"BE",
    "sg:address":"Neustrasse 106",
    "sg:city":"Eupen",
    "sg:classifiers":[
        {
            "category":"Insurance",
            "subcategory":"Insurance Agent",
            "type":"Services"
        }
    ],
    "sg:phone":"+32 87 74 45 36",
    "sg:postcode":"4700",
    "sg:province":"Li\u00e8ge",
    "sg:tags":[
        "broker"
    ],
    "wof:name":"Assipex",
    "wof:placetype":"venue"
},
  "geometry": {"coordinates":[6.0306019783,50.6249351501],"type":"Point"}
}