{
  "type": "Feature",
  "properties": {
    "addr:full":"Westvleterenstraat 22 Vleteren West-Vlaanderen 8640",
    "addr:housenumber":"22",
    "addr:postcode":"8640",
    "addr:street":"Westvleterenstraat",
    "iso:country":"BE",
    "sg:address":"Westvleterenstraat 22",
    "sg:city":"Vleteren",
    "sg:orig_category":"Installatie van metalen schrijnwerk Isolatiewerk",
    "sg:phone":"+32 57 40 04 83",
    "sg:postcode":"8640",
    "sg:province":"West-Vlaanderen",
    "wof:name":"Delhaye",
    "wof:placetype":"venue"
},
  "geometry": {"coordinates":[2.733716011,50.9300003052],"type":"Point"}
}