{
  "type": "Feature",
  "properties": {
    "addr:full":"Quai De Mariemont 22 Sint-jans-molenbeek Bruxelles-Capitale 1080",
    "addr:housenumber":"22",
    "addr:postcode":"1080",
    "addr:street":"Quai De Mariemont",
    "iso:country":"BE",
    "sg:address":"Quai De Mariemont 22",
    "sg:city":"Sint-jans-molenbeek",
    "sg:orig_category":"Diverse voedingsmiddelen Gh",
    "sg:phone":"+32 2 410 51 80",
    "sg:postcode":"1080",
    "sg:province":"Bruxelles-Capitale",
    "wof:name":"Mar Products",
    "wof:placetype":"venue"
},
  "geometry": {"coordinates":[4.3313560486,50.8486061096],"type":"Point"}
}