{
  "type": "Feature",
  "properties": {
    "iso:country":"BE",
    "sg:address":"Evangeliestraat 218bb",
    "sg:city":"Hamme",
    "sg:orig_category":"Artsen and specialisten",
    "sg:phone":"+32 52 47 67 63",
    "sg:postcode":"9220",
    "sg:province":"Oost-Vlaanderen",
    "wof:name":"Herman Nagels",
    "wof:placetype":"venue"
},
  "geometry": {"coordinates":[4.1174788475,51.0866127014],"type":"Point"}
}