{
  "type": "Feature",
  "properties": {
    "addr:full":"Rue Du Pont De La Cure 16b Leuze-en-hainaut Hainaut 7900",
    "addr:housenumber":"16b",
    "addr:postcode":"7900",
    "addr:street":"Rue Du Pont De La Cure",
    "iso:country":"BE",
    "sg:address":"Rue Du Pont De La Cure 16b",
    "sg:city":"Leuze-en-hainaut",
    "sg:classifiers":[
        {
            "category":"Building & Trades",
            "subcategory":"Construction",
            "type":"Services"
        }
    ],
    "sg:phone":"+32 69 66 43 21",
    "sg:postcode":"7900",
    "sg:province":"Hainaut",
    "sg:tags":[
        "installation",
        "-",
        "central",
        "heating"
    ],
    "wof:name":"Lequeue M",
    "wof:placetype":"venue"
},
  "geometry": {"coordinates":[3.6127378941,50.5982666016],"type":"Point"}
}