{
  "type": "Feature",
  "properties": {
    "iso:country":"BE",
    "sg:address":"Rue Jean-de-boheme 7",
    "sg:city":"Marche-en-famenne",
    "sg:classifiers":[
        {
            "category":"Shopping",
            "subcategory":"Clothing, Apparel, & Fashions",
            "type":"Retail Goods"
        }
    ],
    "sg:phone":"+32 84 31 13 75",
    "sg:postcode":"6900",
    "sg:province":"Luxembourg",
    "sg:tags":[
        "v\u00eatements",
        "pour",
        "dame"
    ],
    "wof:name":"Maison Lieutenant",
    "wof:placetype":"venue"
},
  "geometry": {"coordinates":[5.3442659378,50.228099823],"type":"Point"}
}