{
  "type": "Feature",
  "properties": {
    "iso:country":"BE",
    "sg:address":"Stokberg 6b4",
    "sg:city":"Laakdal",
    "sg:classifiers":[
        {
            "category":"Building & Trades",
            "subcategory":"Construction",
            "type":"Services"
        }
    ],
    "sg:phone":"+32 14 86 70 23",
    "sg:postcode":"2430",
    "sg:province":"Antwerpen",
    "sg:tags":[
        "gr",
        "la",
        "de",
        "\u00e9quipement",
        "pour",
        "machine",
        "location",
        "equipements"
    ],
    "wof:name":"H.n.b.",
    "wof:placetype":"venue"
},
  "geometry": {"coordinates":[5.0687851906,51.0857543945],"type":"Point"}
}