{
  "type": "Feature",
  "properties": {
    "addr:full":"Dorpsstraat 29 Zonhoven Limburg 3520",
    "addr:housenumber":"29",
    "addr:postcode":"3520",
    "addr:street":"Dorpsstraat",
    "iso:country":"BE",
    "sg:address":"Dorpsstraat 29",
    "sg:city":"Zonhoven",
    "sg:classifiers":[
        {
            "category":"Real Estate",
            "subcategory":"Architect",
            "type":"Services"
        }
    ],
    "sg:phone":"+32 11 81 21 10",
    "sg:postcode":"3520",
    "sg:province":"Limburg",
    "wof:name":"Tholen D",
    "wof:placetype":"venue"
},
  "geometry": {"coordinates":[5.3678050041,50.9930381775],"type":"Point"}
}