{
  "type": "Feature",
  "properties": {
    "addr:full":"Rue Des P\u00e9tralis 18 Sprimont Li\u00e8ge 4140",
    "addr:housenumber":"18",
    "addr:postcode":"4140",
    "addr:street":"Rue Des Pe\u0301Tralis",
    "iso:country":"BE",
    "sg:address":"Rue Des P\u00e9tralis 18",
    "sg:city":"Sprimont",
    "sg:classifiers":[
        {
            "category":"Building & Trades",
            "subcategory":"Landscaping Services",
            "type":"Services"
        }
    ],
    "sg:phone":"+32 4 382 13 63",
    "sg:postcode":"4140",
    "sg:province":"Li\u00e8ge",
    "sg:tags":[
        "-",
        "lopping",
        "work",
        "tree",
        "felling"
    ],
    "wof:name":"Pirard J",
    "wof:placetype":"venue"
},
  "geometry": {"coordinates":[5.6801681519,50.5058479309],"type":"Point"}
}