{
  "type": "Feature",
  "properties": {
    "iso:country":"BE",
    "sg:address":"Rue Marlet 16",
    "sg:city":"Nivelles",
    "sg:orig_category":"Belastingconsulenten Diverse juridische dienstverlening",
    "sg:phone":"+32 67 21 94 00",
    "sg:postcode":"1400",
    "sg:province":"Brabant Wallon",
    "wof:name":"Nadia Finet",
    "wof:placetype":"venue"
},
  "geometry": {"coordinates":[4.3201270103,50.5963401794],"type":"Point"}
}