{
  "type": "Feature",
  "properties": {
    "addr:full":"Houtkerkestraat 7 Poperinge West-Vlaanderen 8978",
    "addr:housenumber":"7",
    "addr:postcode":"8978",
    "addr:street":"Houtkerkestraat",
    "iso:country":"BE",
    "sg:address":"Houtkerkestraat 7",
    "sg:city":"Poperinge",
    "sg:orig_category":"Eleveurs and marchands de porcs",
    "sg:phone":"+32 57 38 81 07",
    "sg:postcode":"8978",
    "sg:province":"West-Vlaanderen",
    "wof:name":"Martin Vandenbussche",
    "wof:placetype":"venue"
},
  "geometry": {"coordinates":[2.6206049919,50.8592453003],"type":"Point"}
}