{
  "type": "Feature",
  "properties": {
    "addr:full":"Steenweg Op Meerhout 14 Laakdal Antwerpen 2430",
    "addr:housenumber":"14",
    "addr:postcode":"2430",
    "addr:street":"Steenweg Op Meerhout",
    "iso:country":"BE",
    "sg:address":"Steenweg Op Meerhout 14",
    "sg:city":"Laakdal",
    "sg:orig_category":"Brood, gebak and snoepgoed",
    "sg:phone":"+32 14 86 65 77",
    "sg:postcode":"2430",
    "sg:province":"Antwerpen",
    "wof:name":"Dirk En Lief",
    "wof:placetype":"venue"
},
  "geometry": {"coordinates":[5.0478382111,51.0870246887],"type":"Point"}
}