{
  "type": "Feature",
  "properties": {
    "addr:full":"Otterkant 58 Herzele (ressegem) Oost-Vlaanderen 9551",
    "addr:housenumber":"58",
    "addr:postcode":"9551",
    "addr:street":"Otterkant;Ressegem Oost-Vlaanderen",
    "iso:country":"BE",
    "sg:address":"Otterkant 58",
    "sg:city":"Herzele (ressegem)",
    "sg:classifiers":[
        {
            "category":"Retail",
            "subcategory":"Animal Services",
            "type":"Services"
        }
    ],
    "sg:phone":"+32 53 62 34 49",
    "sg:postcode":"9551",
    "sg:province":"Oost-Vlaanderen",
    "sg:tags":[
        "breeding",
        "selling",
        "-",
        "dog"
    ],
    "wof:name":"Sienaert-baude R",
    "wof:placetype":"venue"
},
  "geometry": {"coordinates":[3.9152240753,50.8835678101],"type":"Point"}
}