{
  "type": "Feature",
  "properties": {
    "addr:full":"Rue Albert 123 Tournai Hainaut 7540",
    "addr:housenumber":"123",
    "addr:postcode":"7540",
    "addr:street":"Rue Albert",
    "iso:country":"BE",
    "sg:address":"Rue Albert 123",
    "sg:city":"Tournai",
    "sg:orig_category":"Pain, p\u00e2tisseries and confiseries",
    "sg:phone":"+32 69 22 60 48",
    "sg:postcode":"7540",
    "sg:province":"Hainaut",
    "wof:name":"Boulangerie L'epi D'or",
    "wof:placetype":"venue"
},
  "geometry": {"coordinates":[3.3921399117,50.6216697693],"type":"Point"}
}