{
  "type": "Feature",
  "properties": {
    "addr:full":"Avenue Du Laerbeek 119 Bruxelles (jette) Bruxelles-Capitale 1090",
    "addr:housenumber":"119",
    "addr:postcode":"1090",
    "addr:street":"Avenue Du Laerbeek",
    "iso:country":"BE",
    "sg:address":"Avenue Du Laerbeek 119",
    "sg:city":"Bruxelles (jette)",
    "sg:classifiers":[
        {
            "category":"Social Services",
            "subcategory":"Job Training",
            "type":"Services"
        }
    ],
    "sg:phone":"+32 2 537 34 74",
    "sg:postcode":"1090",
    "sg:province":"Bruxelles-Capitale",
    "sg:tags":[
        "personnel"
    ],
    "wof:name":"Interuniversitair Instituut Voor Vorming & Ontwikkeling",
    "wof:placetype":"venue"
},
  "geometry": {"coordinates":[4.3077001572,50.8832206726],"type":"Point"}
}