{
  "type": "Feature",
  "properties": {
    "iso:country":"BE",
    "sg:address":"Rue Des Fran\u00c7ais 58",
    "sg:city":"Aiseau-presles",
    "sg:orig_category":"Kapsalons",
    "sg:phone":"+32 71 76 02 52",
    "sg:postcode":"6250",
    "sg:province":"Hainaut",
    "wof:name":"Coiffure Myriam",
    "wof:placetype":"venue"
},
  "geometry": {"coordinates":[4.5760707855,50.4269180298],"type":"Point"}
}