{
  "type": "Feature",
  "properties": {
    "iso:country":"BE",
    "sg:address":"Benedenstraat 32",
    "sg:city":"Bornem",
    "sg:classifiers":[
        {
            "category":"Professional",
            "subcategory":"Management & Consulting",
            "type":"Services"
        }
    ],
    "sg:phone":"+32 3 899 36 39",
    "sg:postcode":"2880",
    "sg:province":"Antwerpen",
    "sg:tags":[
        "-",
        "processing",
        "data",
        "consultant"
    ],
    "wof:name":"Odin Projects Bvba",
    "wof:placetype":"venue"
},
  "geometry": {"coordinates":[4.1953501701,51.0788040161],"type":"Point"}
}