{
  "type": "Feature",
  "properties": {
    "addr:full":"Avenue Du Roi 95 Bruxelles (forest) Bruxelles-Capitale 1190",
    "addr:housenumber":"95",
    "addr:postcode":"1190",
    "addr:street":"Avenue Du Roi",
    "iso:country":"BE",
    "sg:address":"Avenue Du Roi 95",
    "sg:city":"Bruxelles (forest)",
    "sg:classifiers":[
        {
            "category":"Health Services",
            "subcategory":"Doctor",
            "type":"Services"
        }
    ],
    "sg:phone":"+32 2 537 37 58",
    "sg:postcode":"1190",
    "sg:province":"Bruxelles-Capitale",
    "sg:tags":[
        "medicinephysicians",
        "surgeon"
    ],
    "wof:name":"Mahieux A",
    "wof:placetype":"venue"
},
  "geometry": {"coordinates":[4.333753109,50.8278884888],"type":"Point"}
}