{
  "type": "Feature",
  "properties": {
    "iso:country":"BE",
    "sg:address":"Route De Bastogne 47",
    "sg:city":"Tenneville",
    "sg:classifiers":[
        {
            "category":"Personal",
            "subcategory":"Beauty Salon",
            "type":"Services"
        }
    ],
    "sg:phone":"+32 84 45 55 96",
    "sg:postcode":"6970",
    "sg:province":"Luxembourg",
    "sg:tags":[
        "lady",
        "-",
        "hairdressing"
    ],
    "wof:name":"Agn\u00e8s (coiffure)",
    "wof:placetype":"venue"
},
  "geometry": {"coordinates":[5.5334920883,50.0854759216],"type":"Point"}
}