{
  "type": "Feature",
  "properties": {
    "iso:country":"BE",
    "sg:address":"Nieuwenrodestraat 53",
    "sg:city":"Wolvertem",
    "sg:classifiers":[
        {
            "category":"Building & Trades",
            "subcategory":"Construction",
            "type":"Services"
        }
    ],
    "sg:phone":"+32 15 71 12 88",
    "sg:postcode":"1861",
    "sg:province":"Vlaams-Brabant",
    "sg:tags":[
        "drawing",
        "cad"
    ],
    "wof:name":"Van Eeckhoudt B.v.b.a.",
    "wof:placetype":"venue"
},
  "geometry": {"coordinates":[4.3382310867,50.9955596924],"type":"Point"}
}