{
  "type": "Feature",
  "properties": {
    "addr:full":"Europalaan 11 Overpelt Limburg 3900",
    "addr:housenumber":"11",
    "addr:postcode":"3900",
    "addr:street":"Europalaan",
    "iso:country":"BE",
    "sg:address":"Europalaan 11",
    "sg:city":"Overpelt",
    "sg:orig_category":"R\u00e9alisation de programmes and logiciels",
    "sg:phone":"+32 11 66 00 52",
    "sg:postcode":"3900",
    "sg:province":"Limburg",
    "wof:name":"Xlnc Software Engineering",
    "wof:placetype":"venue"
},
  "geometry": {"coordinates":[5.3817682266,51.216583252],"type":"Point"}
}