{
  "type": "Feature",
  "properties": {
    "iso:country":"BE",
    "sg:address":"Bosstraat 154",
    "sg:city":"Boom",
    "sg:orig_category":"Installatie van houten of kunststof schrijnwerk",
    "sg:phone":"+32 3 844 57 90",
    "sg:postcode":"2850",
    "sg:province":"Antwerpen",
    "wof:name":"Van Roy G",
    "wof:placetype":"venue"
},
  "geometry": {"coordinates":[4.3879899979,51.0865707397],"type":"Point"}
}