{
  "type": "Feature",
  "properties": {
    "addr:full":"Scheldestraat 11 Gavere Oost-Vlaanderen 9890",
    "addr:housenumber":"11",
    "addr:postcode":"9890",
    "addr:street":"Scheldestraat",
    "iso:country":"BE",
    "sg:address":"Scheldestraat 11",
    "sg:city":"Gavere",
    "sg:classifiers":[
        {
            "category":"Professional",
            "subcategory":"Art Services",
            "type":"Services"
        }
    ],
    "sg:phone":"+32 9 384 81 91",
    "sg:postcode":"9890",
    "sg:province":"Oost-Vlaanderen",
    "sg:tags":[
        "designer",
        "display"
    ],
    "wof:name":"Vermeiren I",
    "wof:placetype":"venue"
},
  "geometry": {"coordinates":[3.6579089165,50.9302711487],"type":"Point"}
}