{
  "type": "Feature",
  "properties": {
    "iso:country":"BE",
    "sg:address":"Kuringersteenweg 439",
    "sg:city":"Hasselt",
    "sg:orig_category":"Fabrication and montage de mobilier",
    "sg:phone":"+32 11 25 56 58",
    "sg:postcode":"3511",
    "sg:province":"Limburg",
    "wof:name":"Euro-cash",
    "wof:placetype":"venue"
},
  "geometry": {"coordinates":[5.2920398712,50.9425086975],"type":"Point"}
}