{
  "type": "Feature",
  "properties": {
    "iso:country":"BE",
    "sg:address":"Hasseltsesteenweg 159",
    "sg:city":"Beringen",
    "sg:orig_category":"V\u00e9hicules automobiles",
    "sg:phone":"+32 11 42 53 52",
    "sg:postcode":"3580",
    "sg:province":"Limburg",
    "wof:name":"Kenis Andr\u00c9",
    "wof:placetype":"venue"
},
  "geometry": {"coordinates":[5.2371602058,51.0399894714],"type":"Point"}
}