{
  "type": "Feature",
  "properties": {
    "addr:full":"Route De Spa 138a Stavelot Li\u00e8ge 4970",
    "addr:housenumber":"138a",
    "addr:postcode":"4970",
    "addr:street":"Route De Spa",
    "iso:country":"BE",
    "sg:address":"Route De Spa 138a",
    "sg:city":"Stavelot",
    "sg:orig_category":"Quincailleries. Plomberie, chauffage and installations sanitaires. Forge, Moulage and Profilage des ",
    "sg:phone":"+32 87 27 58 21",
    "sg:postcode":"4970",
    "sg:province":"Li\u00e8ge",
    "wof:name":"Saint Georges",
    "wof:placetype":"venue"
},
  "geometry": {"coordinates":[5.9525780678,50.4549217224],"type":"Point"}
}