{
  "type": "Feature",
  "properties": {
    "addr:full":"Dorpsstr 15 Londerzeel Antwerpen 2900",
    "addr:housenumber":"15",
    "addr:postcode":"2900",
    "addr:street":"Dorpsstr",
    "iso:country":"BE",
    "sg:address":"Dorpsstr 15",
    "sg:city":"Londerzeel",
    "sg:classifiers":[
        {
            "category":"Banks & Credit Unions",
            "subcategory":"Bank",
            "type":"Services"
        }
    ],
    "sg:phone":"+32 52 30 95 06",
    "sg:postcode":"2900",
    "sg:province":"Antwerpen",
    "wof:name":"Kredietbank",
    "wof:placetype":"venue"
},
  "geometry": {"coordinates":[4.3026051521,51.0034866333],"type":"Point"}
}