{
  "type": "Feature",
  "properties": {
    "iso:country":"BE",
    "sg:address":"Kerklei 18",
    "sg:city":"Brecht (sint-job-in-'t Goor)",
    "sg:classifiers":[
        {
            "category":"Bars & Pubs",
            "type":"Food & Drink"
        }
    ],
    "sg:phone":"+32 3 636 03 73",
    "sg:postcode":"2960",
    "sg:province":"Antwerpen",
    "wof:name":"'t Goorhof",
    "wof:placetype":"venue"
},
  "geometry": {"coordinates":[4.5743432045,51.2922744751],"type":"Point"}
}