{
  "type": "Feature",
  "properties": {
    "iso:country":"BE",
    "sg:address":"Groenlarenstraat 80",
    "sg:city":"Lummen",
    "sg:orig_category":"Artsen and specialisten",
    "sg:phone":"+32 13 52 12 82",
    "sg:postcode":"3560",
    "sg:province":"Limburg",
    "wof:name":"Paul Hobin",
    "wof:placetype":"venue"
},
  "geometry": {"coordinates":[5.19562006,51.0053215027],"type":"Point"}
}