{
  "type": "Feature",
  "properties": {
    "iso:country":"BE",
    "sg:address":"Rue De La Rivierette 100",
    "sg:city":"Saint-ghislain",
    "sg:orig_category":"Bouwmaterialen Gh",
    "sg:phone":"+32 65 76 42 11",
    "sg:postcode":"7330",
    "sg:province":"Hainaut",
    "wof:name":"Hepworth Refractories",
    "wof:placetype":"venue"
},
  "geometry": {"coordinates":[3.8127410412,50.4578742981],"type":"Point"}
}