{
  "type": "Feature",
  "properties": {
    "addr:full":"Rue De Philippeville 22 Dinant Namur 5500",
    "addr:housenumber":"22",
    "addr:postcode":"5500",
    "addr:street":"Rue De Philippeville",
    "iso:country":"BE",
    "sg:address":"Rue De Philippeville 22",
    "sg:city":"Dinant",
    "sg:classifiers":[
        {
            "category":"Personal",
            "subcategory":"Nail Salon",
            "type":"Services"
        }
    ],
    "sg:phone":"+32 82 22 70 98",
    "sg:postcode":"5500",
    "sg:province":"Namur",
    "sg:tags":[
        "pedicure"
    ],
    "wof:name":"Fastrez B",
    "wof:placetype":"venue"
},
  "geometry": {"coordinates":[4.9093580246,50.2581710815],"type":"Point"}
}