{
  "type": "Feature",
  "properties": {
    "addr:full":"Rue De Juplet 1 Hamois Namur 5360",
    "addr:housenumber":"1",
    "addr:postcode":"5360",
    "addr:street":"Rue De Juplet",
    "iso:country":"BE",
    "sg:address":"Rue De Juplet 1",
    "sg:city":"Hamois",
    "sg:orig_category":"Administration d'immeubles",
    "sg:phone":"+32 83 65 65 72",
    "sg:postcode":"5360",
    "sg:province":"Namur",
    "wof:name":"Fe. Batnat",
    "wof:placetype":"venue"
},
  "geometry": {"coordinates":[5.0455079079,50.3514213562],"type":"Point"}
}