{
  "type": "Feature",
  "properties": {
    "addr:full":"Bruggestraat 7b Kluisbergen (berchem) Oost-Vlaanderen 9690",
    "addr:housenumber":"7b",
    "addr:postcode":"9690",
    "addr:street":"Bruggestraat",
    "iso:country":"BE",
    "sg:address":"Bruggestraat 7b",
    "sg:city":"Kluisbergen (berchem)",
    "sg:classifiers":[
        {
            "category":"Building & Trades",
            "subcategory":"Construction",
            "type":"Services"
        }
    ],
    "sg:phone":"+32 55 38 71 01",
    "sg:postcode":"9690",
    "sg:province":"Oost-Vlaanderen",
    "sg:tags":[
        "installation",
        "-",
        "central",
        "heating"
    ],
    "wof:name":"Lacompte N",
    "wof:placetype":"venue"
},
  "geometry": {"coordinates":[3.5266470909,50.790561676],"type":"Point"}
}