{
  "type": "Feature",
  "properties": {
    "addr:full":"Koekoekstraat 3 Bilzen Limburg 3740",
    "addr:housenumber":"3",
    "addr:postcode":"3740",
    "addr:street":"Koekoekstraat",
    "iso:country":"BE",
    "sg:address":"Koekoekstraat 3",
    "sg:city":"Bilzen",
    "sg:classifiers":[
        {
            "category":"Cafe",
            "type":"Food & Drink"
        }
    ],
    "sg:phone":"+32 89 41 31 83",
    "sg:postcode":"3740",
    "sg:province":"Limburg",
    "sg:tags":[
        "caf\u00e9s"
    ],
    "wof:name":"Marcel Baeten",
    "wof:placetype":"venue"
},
  "geometry": {"coordinates":[5.5296931267,50.8901176453],"type":"Point"}
}