{
  "type": "Feature",
  "properties": {
    "addr:full":"Gentsesteenweg 336 Aalst Oost-Vlaanderen 9300",
    "addr:housenumber":"336",
    "addr:postcode":"9300",
    "addr:street":"Gentsesteenweg",
    "iso:country":"BE",
    "sg:address":"Gentsesteenweg 336",
    "sg:city":"Aalst",
    "sg:orig_category":"Banques and organismes de cr\u00e9dit",
    "sg:phone":"+32 53 73 06 50",
    "sg:postcode":"9300",
    "sg:province":"Oost-Vlaanderen",
    "wof:name":"Kbc",
    "wof:placetype":"venue"
},
  "geometry": {"coordinates":[4.0137991905,50.9400177002],"type":"Point"}
}