{
  "type": "Feature",
  "properties": {
    "addr:full":"Memlingstraat 13 Anderlecht Bruxelles-Capitale 1070",
    "addr:housenumber":"13",
    "addr:postcode":"1070",
    "addr:street":"Memlingstraat",
    "iso:country":"BE",
    "sg:address":"Memlingstraat 13",
    "sg:city":"Anderlecht",
    "sg:orig_category":"Loodgieterij, verwarming and sanitaire installaties",
    "sg:phone":"+32 2 524 29 25",
    "sg:postcode":"1070",
    "sg:province":"Bruxelles-Capitale",
    "wof:name":"Abdelouahid Boulaioun",
    "wof:placetype":"venue"
},
  "geometry": {"coordinates":[4.3341598511,50.8413009644],"type":"Point"}
}