{
  "type": "Feature",
  "properties": {
    "addr:full":"Rue La Fagnet 57 Gerpinnes Hainaut 6280",
    "addr:housenumber":"57",
    "addr:postcode":"6280",
    "addr:street":"Rue La Fagnet;Hainaut",
    "iso:country":"BE",
    "sg:address":"Rue La Fagnet 57",
    "sg:city":"Gerpinnes",
    "sg:orig_category":"Keukens and Keukenapparatuur MEUBELONTWERP AND -INSTALLATIE Meubelzaken, woning- and keukeninrichtin",
    "sg:phone":"+32 71 50 18 02",
    "sg:postcode":"6280",
    "sg:province":"Hainaut",
    "wof:name":"Eric Gerards Sprl",
    "wof:placetype":"venue"
},
  "geometry": {"coordinates":[4.508398056,50.3463554382],"type":"Point"}
}