{
  "type": "Feature",
  "properties": {
    "addr:full":"Rue De La Sabli\u00e8re 8 Rixensart (genval) Brabant Wallon 1332",
    "addr:housenumber":"8",
    "addr:postcode":"1332",
    "addr:street":"Rue De La Sablie\u0300Re",
    "iso:country":"BE",
    "sg:address":"Rue De La Sabli\u00e8re 8",
    "sg:city":"Rixensart (genval)",
    "sg:classifiers":[
        {
            "category":"Real Estate",
            "subcategory":"Architect",
            "type":"Services"
        }
    ],
    "sg:phone":"+32 2 653 09 60",
    "sg:postcode":"1332",
    "sg:province":"Brabant Wallon",
    "wof:name":"Atelier D'architecture De Genval",
    "wof:placetype":"venue"
},
  "geometry": {"coordinates":[4.5130720139,50.7250404358],"type":"Point"}
}