{
  "type": "Feature",
  "properties": {
    "addr:full":"Taxanderlei 45 Schoten Antwerpen 2900",
    "addr:housenumber":"45",
    "addr:postcode":"2900",
    "addr:street":"Taxanderlei",
    "iso:country":"BE",
    "sg:address":"Taxanderlei 45",
    "sg:city":"Schoten",
    "sg:classifiers":[
        {
            "category":"Health Services",
            "subcategory":"Doctor",
            "type":"Services"
        }
    ],
    "sg:phone":"+32 3 658 00 50",
    "sg:postcode":"2900",
    "sg:province":"Antwerpen",
    "sg:tags":[
        "medicinephysicians",
        "surgeon"
    ],
    "wof:name":"De Maeyer P",
    "wof:placetype":"venue"
},
  "geometry": {"coordinates":[4.5214319229,51.2494049072],"type":"Point"}
}