{
  "type": "Feature",
  "properties": {
    "iso:country":"BE",
    "sg:address":"Stationsstraat 39",
    "sg:city":"Genk",
    "sg:orig_category":"Dameskledingzaken",
    "sg:phone":"+32 89 35 93 69",
    "sg:postcode":"3600",
    "sg:province":"Limburg",
    "wof:name":"Andres",
    "wof:placetype":"venue"
},
  "geometry": {"coordinates":[5.5007820129,50.9651222229],"type":"Point"}
}