{
  "type": "Feature",
  "properties": {
    "iso:country":"BE",
    "sg:address":"Hageputstraat 2ba",
    "sg:city":"Houthulst",
    "sg:orig_category":"Installatie van houten of kunststof schrijnwerk MEUBELONTWERP AND -INSTALLATIE",
    "sg:phone":"+32 51 54 55 14",
    "sg:postcode":"8650",
    "sg:province":"West-Vlaanderen",
    "wof:name":"Crea Design",
    "wof:placetype":"venue"
},
  "geometry": {"coordinates":[2.9509439468,50.9778862],"type":"Point"}
}