{
  "type": "Feature",
  "properties": {
    "addr:full":"Golden Hope 34 Drogenbos Vlaams-Brabant 1620",
    "addr:housenumber":"34",
    "addr:postcode":"1620",
    "iso:country":"BE",
    "sg:address":"Golden Hope 34",
    "sg:city":"Drogenbos",
    "sg:classifiers":[
        {
            "category":"Taxi",
            "type":"Transportation"
        }
    ],
    "sg:phone":"+32 2 331 31 31",
    "sg:postcode":"1620",
    "sg:province":"Vlaams-Brabant",
    "sg:tags":[
        "sp\u00e9ciaux",
        "taxis"
    ],
    "wof:name":"Abl Limousine Services",
    "wof:placetype":"venue"
},
  "geometry": {"coordinates":[4.2922711372,50.7977256775],"type":"Point"}
}