{
  "type": "Feature",
  "properties": {
    "iso:country":"BE",
    "sg:address":"Kruibekesteenweg 193",
    "sg:city":"Beveren",
    "sg:classifiers":[
        {
            "category":"Sports & Exercise",
            "subcategory":"Sports Center",
            "type":"Entertainment"
        }
    ],
    "sg:phone":"+32 3 755 01 20",
    "sg:postcode":"9120",
    "sg:province":"Oost-Vlaanderen",
    "sg:tags":[
        "terrain",
        "hors",
        "de",
        "installation",
        "sportifs"
    ],
    "wof:name":"Manege Impens",
    "wof:placetype":"venue"
},
  "geometry": {"coordinates":[4.2750911713,51.1866111755],"type":"Point"}
}