{
  "type": "Feature",
  "properties": {
    "iso:country":"BE",
    "sg:address":"Stationsstraat 106",
    "sg:city":"Houthalen-helchteren (houthalen)",
    "sg:classifiers":[
        {
            "category":"Shopping",
            "subcategory":"Used Merchandise",
            "type":"Retail Goods"
        }
    ],
    "sg:phone":"+32 495 46 49 78",
    "sg:postcode":"3530",
    "sg:province":"Limburg",
    "sg:tags":[
        "salvage",
        "surplus"
    ],
    "wof:name":"Origamma Partijhandel",
    "wof:placetype":"venue"
},
  "geometry": {"coordinates":[5.3544688225,51.0259628296],"type":"Point"}
}