{
  "type": "Feature",
  "properties": {
    "iso:country":"BE",
    "sg:address":"Rue Des Stanges 38",
    "sg:city":"Verlaine",
    "sg:classifiers":[
        {
            "category":"Insurance",
            "subcategory":"Insurance Agent",
            "type":"Services"
        }
    ],
    "sg:phone":"+32 4 259 64 87",
    "sg:postcode":"4537",
    "sg:province":"Li\u00e8ge",
    "sg:tags":[
        "verzekeringsmakelaars",
        "expert"
    ],
    "wof:name":"Bailly W. & Cie",
    "wof:placetype":"venue"
},
  "geometry": {"coordinates":[5.3226699829,50.5984725952],"type":"Point"}
}