{
  "type": "Feature",
  "properties": {
    "iso:country":"BE",
    "sg:address":"Steenweg 20",
    "sg:city":"Zwalm",
    "sg:orig_category":"Dameskledingzaken Herenkledingzaken",
    "sg:phone":"+32 55 49 80 88",
    "sg:postcode":"9630",
    "sg:province":"Oost-Vlaanderen",
    "wof:name":"Marc De Clercq",
    "wof:placetype":"venue"
},
  "geometry": {"coordinates":[3.7405230999,50.893283844],"type":"Point"}
}