{
  "type": "Feature",
  "properties": {
    "addr:full":"Place De Wasmes 29 Colfontaine Hainaut 7340",
    "addr:housenumber":"29",
    "addr:postcode":"7340",
    "addr:street":"Place De Wasmes",
    "iso:country":"BE",
    "sg:address":"Place De Wasmes 29",
    "sg:city":"Colfontaine",
    "sg:orig_category":"Jeux de hasard",
    "sg:phone":"+32 65 78 64 78",
    "sg:postcode":"7340",
    "sg:province":"Hainaut",
    "wof:name":"Ladbroke",
    "wof:placetype":"venue"
},
  "geometry": {"coordinates":[3.8435909748,50.4226837158],"type":"Point"}
}