{
  "type": "Feature",
  "properties": {
    "iso:country":"BE",
    "sg:address":"Zeeweg 152",
    "sg:city":"Oudenburg (roksem)",
    "sg:classifiers":[
        {
            "category":"Autos & Motor Vehicles",
            "subcategory":"Automobile Sales",
            "type":"Retail Goods"
        }
    ],
    "sg:phone":"+32 59 26 58 75",
    "sg:postcode":"8460",
    "sg:province":"West-Vlaanderen",
    "sg:tags":[
        "car",
        "used",
        "-"
    ],
    "wof:name":"Maene G",
    "wof:placetype":"venue"
},
  "geometry": {"coordinates":[3.0273180008,51.167755127],"type":"Point"}
}