{
  "type": "Feature",
  "properties": {
    "addr:full":"Chauss\u00e9e De Waterloo 1069 Bruxelles (uccle) Bruxelles-Capitale 1180",
    "addr:postcode":"1069;1180",
    "addr:street":"Chausse\u0301E De Waterloo",
    "iso:country":"BE",
    "sg:address":"Chauss\u00e9e De Waterloo 1069",
    "sg:city":"Bruxelles (uccle)",
    "sg:classifiers":[
        {
            "category":"Home & Garden",
            "subcategory":"Home Furnishings",
            "type":"Retail Goods"
        }
    ],
    "sg:phone":"+32 2 374 68 13",
    "sg:postcode":"1180",
    "sg:province":"Bruxelles-Capitale",
    "sg:tags":[
        "interior",
        "decoration"
    ],
    "wof:name":"Terrachiara Sprl",
    "wof:placetype":"venue"
},
  "geometry": {"coordinates":[4.372563839,50.8029098511],"type":"Point"}
}