{
  "type": "Feature",
  "properties": {
    "iso:country":"BE",
    "sg:address":"Filips Van Kleefstraat 1",
    "sg:city":"Torhout",
    "sg:classifiers":[
        {
            "category":"Building & Trades",
            "subcategory":"Electrical",
            "type":"Services"
        }
    ],
    "sg:phone":"+32 50 21 25 88",
    "sg:postcode":"8820",
    "sg:province":"West-Vlaanderen",
    "sg:tags":[
        "plants",
        "plant",
        "industrial",
        "buildings",
        "construction"
    ],
    "wof:name":"De Wandeler Nv",
    "wof:placetype":"venue"
},
  "geometry": {"coordinates":[3.0974910259,51.0753326416],"type":"Point"}
}