{
  "type": "Feature",
  "properties": {
    "addr:full":"Koninginnelaan 21 Oostende West-Vlaanderen 8400",
    "addr:housenumber":"21",
    "addr:postcode":"8400",
    "addr:street":"Koninginnelaan",
    "iso:country":"BE",
    "sg:address":"Koninginnelaan 21",
    "sg:city":"Oostende",
    "sg:classifiers":[
        {
            "category":"Fast Food",
            "type":"Food & Drink"
        }
    ],
    "sg:phone":"+32 59 50 23 06",
    "sg:postcode":"8400",
    "sg:province":"West-Vlaanderen",
    "sg:tags":[
        "meeneem",
        "restaurant"
    ],
    "wof:name":"Restaurant Les Cygnes",
    "wof:placetype":"venue"
},
  "geometry": {"coordinates":[2.9063899517,51.2255363464],"type":"Point"}
}