{
  "type": "Feature",
  "properties": {
    "iso:country":"BE",
    "sg:address":"Dadizelestraat 15",
    "sg:city":"Menen",
    "sg:orig_category":"Plaatsen van vloer- and muurbekleding Vloer- and muurbekleding Woningbouw",
    "sg:phone":"+32 56 51 44 93",
    "sg:postcode":"8930",
    "sg:province":"West-Vlaanderen",
    "wof:name":"Deleu",
    "wof:placetype":"venue"
},
  "geometry": {"coordinates":[3.1121199131,50.8069229126],"type":"Point"}
}