{
  "type": "Feature",
  "properties": {
    "addr:full":"Ketelstraat 32 Zoutleeuw Vlaams-Brabant 3440",
    "addr:housenumber":"32",
    "addr:postcode":"3440",
    "addr:street":"Ketelstraat;Vlaams-Brabant",
    "iso:country":"BE",
    "sg:address":"Ketelstraat 32",
    "sg:city":"Zoutleeuw",
    "sg:orig_category":"Fruitteelt",
    "sg:phone":"+32 11 58 28 00",
    "sg:postcode":"3440",
    "sg:province":"Vlaams-Brabant",
    "wof:name":"Luc Andries",
    "wof:placetype":"venue"
},
  "geometry": {"coordinates":[5.0611310005,50.8811759949],"type":"Point"}
}