{
  "type": "Feature",
  "properties": {
    "addr:full":"Heirstraat 19 Mechelen Antwerpen 2801",
    "addr:housenumber":"19",
    "addr:postcode":"2801",
    "addr:street":"Heirstraat",
    "iso:country":"BE",
    "sg:address":"Heirstraat 19",
    "sg:city":"Mechelen",
    "sg:classifiers":[
        {
            "category":"Food & Beverages",
            "subcategory":"Fruits & Vegetables",
            "type":"Retail Goods"
        }
    ],
    "sg:phone":"+32 3 866 06 08",
    "sg:postcode":"2801",
    "sg:province":"Antwerpen",
    "sg:tags":[
        "l\u00e9gumes"
    ],
    "wof:name":"Yvo Mees",
    "wof:placetype":"venue"
},
  "geometry": {"coordinates":[4.3958778381,51.0429000854],"type":"Point"}
}