{
  "type": "Feature",
  "properties": {
    "iso:country":"BE",
    "sg:address":"Rue Du Grand Puits 47",
    "sg:city":"Herstal",
    "sg:orig_category":"Cliniques and h\u00f4pitaux",
    "sg:phone":"+32 4 240 59 00",
    "sg:postcode":"4040",
    "sg:province":"Li\u00e8ge",
    "wof:name":"C.h. R\u00c9g. De La Citadelle",
    "wof:placetype":"venue"
},
  "geometry": {"coordinates":[5.6400327682,50.6722297668],"type":"Point"}
}