{
  "type": "Feature",
  "properties": {
    "addr:full":"Amand De Vosstraat 1 Lokeren (eksaarde) Oost-Vlaanderen 9160",
    "addr:housenumber":"1",
    "addr:postcode":"9160",
    "addr:street":"Amand De Vosstraat;Lokeren Eksaarde Oost-Vlaanderen",
    "iso:country":"BE",
    "sg:address":"Amand De Vosstraat 1",
    "sg:city":"Lokeren (eksaarde)",
    "sg:orig_category":"Newspapers, magazines, periodicals - Distribution",
    "sg:phone":"+32 9 326 05 75",
    "sg:postcode":"9160",
    "sg:province":"Oost-Vlaanderen",
    "wof:name":"'t Letterhuis Bvba",
    "wof:placetype":"venue"
},
  "geometry": {"coordinates":[3.9864850044,51.1047401428],"type":"Point"}
}