{
  "type": "Feature",
  "properties": {
    "addr:full":"Avenue F\u00c9n\u00c9lon 220 Colfontaine Hainaut 7340",
    "addr:housenumber":"220",
    "addr:postcode":"7340",
    "addr:street":"Avenue Fe\u0301Ne\u0301Lon",
    "iso:country":"BE",
    "sg:address":"Avenue F\u00c9n\u00c9lon 220",
    "sg:city":"Colfontaine",
    "sg:orig_category":"G\u00e9om\u00e8tres",
    "sg:phone":"+32 65 67 31 51",
    "sg:postcode":"7340",
    "sg:province":"Hainaut",
    "wof:name":"Emile Vansthertem",
    "wof:placetype":"venue"
},
  "geometry": {"coordinates":[3.8630540371,50.4013671875],"type":"Point"}
}