{
  "type": "Feature",
  "properties": {
    "addr:full":"Esplanade Du Heysel Pointe 50 Bruxelles Bruxelles-Capitale 1020",
    "addr:housenumber":"50",
    "addr:postcode":"1020",
    "addr:street":"Esplanade Du Heysel Pointe",
    "iso:country":"BE",
    "sg:address":"Esplanade Du Heysel Pointe 50",
    "sg:city":"Bruxelles",
    "sg:classifiers":[
        {
            "category":"Manufacturing",
            "subcategory":"Tools & Machinery",
            "type":"Manufacturing & Wholesale Goods"
        }
    ],
    "sg:phone":"+32 2 479 42 42",
    "sg:postcode":"1020",
    "sg:province":"Bruxelles-Capitale",
    "sg:tags":[
        "metallurgy",
        "metalworking"
    ],
    "wof:name":"Bruynzeel Storage System Sa",
    "wof:placetype":"venue"
},
  "geometry": {"coordinates":[4.3414740562,50.8911476135],"type":"Point"}
}