{
  "type": "Feature",
  "properties": {
    "iso:country":"BE",
    "sg:address":"Chauss\u00c9e De Jodoigne 17",
    "sg:city":"Grez-doiceau",
    "sg:orig_category":"Produits surgel\u00e9s Gr",
    "sg:phone":"+32 10 84 43 24",
    "sg:postcode":"1390",
    "sg:province":"Brabant Wallon",
    "wof:name":"Beatrice Arnold",
    "wof:placetype":"venue"
},
  "geometry": {"coordinates":[4.6989707947,50.7382659912],"type":"Point"}
}