{
  "type": "Feature",
  "properties": {
    "iso:country":"BE",
    "sg:address":"Briscol 26a",
    "sg:city":"Erez\u00e9e",
    "sg:classifiers":[
        {
            "category":"Wholesale",
            "subcategory":"Beer",
            "type":"Manufacturing & Wholesale Goods"
        }
    ],
    "sg:phone":"+32 86 47 77 18",
    "sg:postcode":"6997",
    "sg:province":"Luxembourg",
    "sg:tags":[
        "ale",
        "-"
    ],
    "wof:name":"Ponsard M",
    "wof:placetype":"venue"
},
  "geometry": {"coordinates":[5.5979337692,50.2945175171],"type":"Point"}
}