{
  "type": "Feature",
  "properties": {
    "addr:full":"Warandestraat 13 Liedekerke Vlaams-Brabant 1770",
    "addr:housenumber":"13",
    "addr:postcode":"1770",
    "addr:street":"Warandestraat;Vlaams-Brabant",
    "iso:country":"BE",
    "sg:address":"Warandestraat 13",
    "sg:city":"Liedekerke",
    "sg:classifiers":[
        {
            "category":"Cafe",
            "type":"Food & Drink"
        }
    ],
    "sg:phone":"+32 53 66 13 66",
    "sg:postcode":"1770",
    "sg:province":"Vlaams-Brabant",
    "sg:tags":[
        "caf\u00e9s"
    ],
    "wof:name":"Caf\u00c9 In Den Appel",
    "wof:placetype":"venue"
},
  "geometry": {"coordinates":[4.0819940567,50.8702774048],"type":"Point"}
}