{
  "type": "Feature",
  "properties": {
    "iso:country":"BE",
    "sg:address":"Voie De La Hayette 61",
    "sg:city":"Bl\u00e9gny (saive)",
    "sg:classifiers":[
        {
            "category":"Building & Trades",
            "subcategory":"Plumbing",
            "type":"Services"
        }
    ],
    "sg:phone":"+32 4 362 12 16",
    "sg:postcode":"4671",
    "sg:province":"Li\u00e8ge",
    "sg:tags":[
        "repair",
        "mainten",
        "-",
        "central",
        "heating"
    ],
    "wof:name":"Laboureur H",
    "wof:placetype":"venue"
},
  "geometry": {"coordinates":[5.6780328751,50.6397476196],"type":"Point"}
}