{
  "type": "Feature",
  "properties": {
    "addr:full":"Keizerstraat 11 Antwerpen Antwerpen 2000",
    "addr:housenumber":"11",
    "addr:postcode":"2000",
    "addr:street":"Keizerstraat",
    "iso:country":"BE",
    "sg:address":"Keizerstraat 11",
    "sg:city":"Antwerpen",
    "sg:orig_category":"Artistes ind\u00e9pendants",
    "sg:phone":"+32 3 231 70 94",
    "sg:postcode":"2000",
    "sg:province":"Antwerpen",
    "wof:name":"Rikkert Van Dijck",
    "wof:placetype":"venue"
},
  "geometry": {"coordinates":[4.4065570831,51.221912384],"type":"Point"}
}