{
  "type": "Feature",
  "properties": {
    "addr:full":"Rue De Hussompont 39a Jodoigne (m\u00e9lin) Brabant Wallon 1370",
    "addr:housenumber":"39a",
    "addr:postcode":"1370",
    "addr:street":"Rue De Hussompont;Wallon",
    "iso:country":"BE",
    "sg:address":"Rue De Hussompont 39a",
    "sg:city":"Jodoigne (m\u00e9lin)",
    "sg:classifiers":[
        {
            "category":"Home & Garden",
            "subcategory":"Home Furnishings",
            "type":"Retail Goods"
        }
    ],
    "sg:phone":"+32 10 81 10 12",
    "sg:postcode":"1370",
    "sg:province":"Brabant Wallon",
    "sg:tags":[
        "interior",
        "decoration"
    ],
    "wof:name":"Au Grenier De Gobertrange",
    "wof:placetype":"venue"
},
  "geometry": {"coordinates":[4.8414011002,50.7376594543],"type":"Point"}
}