{
  "type": "Feature",
  "properties": {
    "iso:country":"BE",
    "sg:address":"Kerkstraat 10",
    "sg:city":"Mesen/messines",
    "sg:classifiers":[
        {
            "category":"Restaurant",
            "type":"Food & Drink"
        }
    ],
    "sg:phone":"+32 57 44 75 15",
    "sg:postcode":"8957",
    "sg:province":"West-Vlaanderen",
    "wof:name":"Tearoom Vivaldi",
    "wof:placetype":"venue"
},
  "geometry": {"coordinates":[2.8978021145,50.76379776],"type":"Point"}
}