{
  "type": "Feature",
  "properties": {
    "iso:country":"BE",
    "sg:address":"Hazewindstraat 2",
    "sg:city":"Kortemark",
    "sg:orig_category":"Eleveurs and marchands de porcs. Eleveurs de bovins",
    "sg:phone":"+32 51 57 04 12",
    "sg:postcode":"8610",
    "sg:province":"West-Vlaanderen",
    "wof:name":"Luc Vandewalle",
    "wof:placetype":"venue"
},
  "geometry": {"coordinates":[2.9925661087,51.0036888123],"type":"Point"}
}