{
  "type": "Feature",
  "properties": {
    "addr:full":"Markt 7 Kasterlee Antwerpen 2460",
    "addr:housenumber":"7",
    "addr:postcode":"2460",
    "addr:street":"Markt",
    "iso:country":"BE",
    "sg:address":"Markt 7",
    "sg:city":"Kasterlee",
    "sg:classifiers":[
        {
            "category":"Professional",
            "subcategory":"Lawyer & Legal Services",
            "type":"Services"
        }
    ],
    "sg:phone":"+32 14 85 07 70",
    "sg:postcode":"2460",
    "sg:province":"Antwerpen",
    "wof:name":"Aerden G & Michielsen J",
    "wof:placetype":"venue"
},
  "geometry": {"coordinates":[4.9675521851,51.2406921387],"type":"Point"}
}