{
  "type": "Feature",
  "properties": {
    "addr:full":"Avenue Des Flandres 30 Leuze-en-hainaut Hainaut 7900",
    "addr:housenumber":"30",
    "addr:postcode":"7900",
    "addr:street":"Avenue Des Flandres",
    "iso:country":"BE",
    "sg:address":"Avenue Des Flandres 30",
    "sg:city":"Leuze-en-hainaut",
    "sg:orig_category":"Non-Classified Establishments",
    "sg:phone":"+32 69 66 31 29",
    "sg:postcode":"7900",
    "sg:province":"Hainaut",
    "wof:name":"Aroxa Sprl",
    "wof:placetype":"venue"
},
  "geometry": {"coordinates":[3.6159720421,50.6094894409],"type":"Point"}
}