{
  "type": "Feature",
  "properties": {
    "addr:full":"Bruggesteenweg 127 Hooglede (gits) West-Vlaanderen 8830",
    "addr:housenumber":"127",
    "addr:postcode":"8830",
    "addr:street":"Bruggesteenweg",
    "iso:country":"BE",
    "sg:address":"Bruggesteenweg 127",
    "sg:city":"Hooglede (gits)",
    "sg:classifiers":[
        {
            "category":"Autos & Motor Vehicles",
            "subcategory":"Automobile Sales",
            "type":"Retail Goods"
        }
    ],
    "sg:phone":"+32 51 22 65 51",
    "sg:postcode":"8830",
    "sg:province":"West-Vlaanderen",
    "sg:tags":[
        "delivery",
        "-",
        "used",
        "van",
        "truck"
    ],
    "wof:name":"Magyar",
    "wof:placetype":"venue"
},
  "geometry": {"coordinates":[3.0929589272,50.9822273254],"type":"Point"}
}