{
  "type": "Feature",
  "properties": {
    "iso:country":"BE",
    "sg:address":"Rue Du Tilloi 9",
    "sg:city":"Heppignies",
    "sg:orig_category":"Ramassage and traitement des d\u00e9chets m\u00e9nagers. Mat\u00e9riaux de construction Construction de maisons. Tr",
    "sg:phone":"+32 71 25 35 25",
    "sg:postcode":"6220",
    "sg:province":"Hainaut",
    "wof:name":"Cattafesta Construction",
    "wof:placetype":"venue"
},
  "geometry": {"coordinates":[4.5031251907,50.4665336609],"type":"Point"}
}