{
  "type": "Feature",
  "properties": {
    "iso:country":"BE",
    "sg:address":"Kasteelstraat 6",
    "sg:city":"Sint-niklaas",
    "sg:classifiers":[
        {
            "category":"Education",
            "subcategory":"School",
            "type":"Public Place"
        }
    ],
    "sg:phone":"+32 3 776 75 21",
    "sg:postcode":"9100",
    "sg:province":"Oost-Vlaanderen",
    "sg:tags":[
        "primary"
    ],
    "wof:name":"Jonatanschool",
    "wof:placetype":"venue"
},
  "geometry": {"coordinates":[4.1349887848,51.1651916504],"type":"Point"}
}