{
  "type": "Feature",
  "properties": {
    "iso:country":"BE",
    "sg:address":"Boulevard Du R\u00c9gent 50",
    "sg:city":"Brussel/bruxelles",
    "sg:orig_category":"Banques and organismes de cr\u00e9dit",
    "sg:phone":"+32 2 500 89 90",
    "sg:postcode":"1000",
    "sg:province":"Bruxelles-Capitale",
    "wof:name":"Argentaria-b.b.v.a.",
    "wof:placetype":"venue"
},
  "geometry": {"coordinates":[4.3689088821,50.8475341797],"type":"Point"}
}