{
  "type": "Feature",
  "properties": {
    "iso:country":"BE",
    "sg:address":"Steenweg Op Zevendonk 23",
    "sg:city":"Turnhout",
    "sg:orig_category":"Brood, gebak and snoepgoed",
    "sg:phone":"+32 14 41 97 44",
    "sg:postcode":"2300",
    "sg:province":"Antwerpen",
    "wof:name":"Fa. Johan",
    "wof:placetype":"venue"
},
  "geometry": {"coordinates":[4.9488182068,51.3118476868],"type":"Point"}
}