{
  "type": "Feature",
  "properties": {
    "iso:country":"BE",
    "sg:address":"Boulevard De L'h\u00f4pital 6",
    "sg:city":"Ath",
    "sg:classifiers":[
        {
            "category":"Professional",
            "subcategory":"Detective & Security Services",
            "type":"Services"
        }
    ],
    "sg:phone":"+32 475 71 07 87",
    "sg:postcode":"7800",
    "sg:province":"Hainaut",
    "sg:tags":[
        "guard"
    ],
    "wof:name":"Activ Vigilis",
    "wof:placetype":"venue"
},
  "geometry": {"coordinates":[3.7847900391,50.6294555664],"type":"Point"}
}