{
  "type": "Feature",
  "properties": {
    "addr:full":"Fr\u00c8re-orbanstraat 6 Oostende West-Vlaanderen 8400",
    "addr:housenumber":"6",
    "addr:postcode":"8400",
    "addr:street":"Fre\u0300Re-Orbanstraat",
    "iso:country":"BE",
    "sg:address":"Fr\u00c8re-orbanstraat 6",
    "sg:city":"Oostende",
    "sg:classifiers":[
        {
            "category":"Personal",
            "subcategory":"Beauty Salon",
            "type":"Services"
        }
    ],
    "sg:phone":"+32 59 70 78 75",
    "sg:postcode":"8400",
    "sg:province":"West-Vlaanderen",
    "sg:tags":[
        "de",
        "coiffure"
    ],
    "wof:name":"Coiffure Carmen",
    "wof:placetype":"venue"
},
  "geometry": {"coordinates":[2.9088330269,51.2215499878],"type":"Point"}
}