{
  "type": "Feature",
  "properties": {
    "addr:full":"Eksterstraat 56 Geel Antwerpen 2440",
    "addr:housenumber":"56",
    "addr:postcode":"2440",
    "addr:street":"Eksterstraat",
    "iso:country":"BE",
    "sg:address":"Eksterstraat 56",
    "sg:city":"Geel",
    "sg:classifiers":[
        {
            "category":"Insurance",
            "subcategory":"Insurance Agent",
            "type":"Services"
        }
    ],
    "sg:phone":"+32 14 58 33 86",
    "sg:postcode":"2440",
    "sg:province":"Antwerpen",
    "sg:tags":[
        "verzekeringsmakelaars",
        "expert"
    ],
    "wof:name":"Van Den Broeck",
    "wof:placetype":"venue"
},
  "geometry": {"coordinates":[4.9708409309,51.1749420166],"type":"Point"}
}