{
  "type": "Feature",
  "properties": {
    "iso:country":"BE",
    "sg:address":"Stationsstraat 20",
    "sg:city":"Duffel",
    "sg:orig_category":"Rookartikelen",
    "sg:phone":"+32 15 31 05 26",
    "sg:postcode":"2570",
    "sg:province":"Antwerpen",
    "wof:name":"Gilbert Pierrard",
    "wof:placetype":"venue"
},
  "geometry": {"coordinates":[4.4979767799,51.0918769836],"type":"Point"}
}