{
  "type": "Feature",
  "properties": {
    "addr:full":"Chauss\u00c9e De Vleurgat 322 Elsene/ixelles Bruxelles-Capitale 1050",
    "addr:housenumber":"322",
    "addr:postcode":"1050",
    "addr:street":"Chausse\u0301E De Vleurgat",
    "iso:country":"BE",
    "sg:address":"Chauss\u00c9e De Vleurgat 322",
    "sg:city":"Elsene/ixelles",
    "sg:classifiers":[
        {
            "category":"Personal",
            "subcategory":"Beauty Salon",
            "type":"Services"
        }
    ],
    "sg:phone":"+32 2 649 16 87",
    "sg:postcode":"1050",
    "sg:province":"Bruxelles-Capitale",
    "sg:tags":[
        "de",
        "coiffure"
    ],
    "wof:name":"Coiffure Branko",
    "wof:placetype":"venue"
},
  "geometry": {"coordinates":[4.3667960167,50.817325592],"type":"Point"}
}