{
  "type": "Feature",
  "properties": {
    "iso:country":"BE",
    "sg:address":"Kersbeekdorp 1",
    "sg:city":"Kortenaken",
    "sg:orig_category":"Producteurs de fruits",
    "sg:phone":"+32 16 77 19 52",
    "sg:postcode":"3472",
    "sg:province":"Vlaams-Brabant",
    "wof:name":"David Peeters",
    "wof:placetype":"venue"
},
  "geometry": {"coordinates":[4.9954328537,50.8857841492],"type":"Point"}
}