{
  "type": "Feature",
  "properties": {
    "iso:country":"BE",
    "sg:address":"Rot 12",
    "sg:city":"Sint-lievens-houtem",
    "sg:orig_category":"Eleveurs and marchands de porcs. Eleveurs de bovins",
    "sg:phone":"+32 53 62 41 99",
    "sg:postcode":"9521",
    "sg:province":"Oost-Vlaanderen",
    "wof:name":"Godelieve Lagaert",
    "wof:placetype":"venue"
},
  "geometry": {"coordinates":[3.8826060295,50.9239730835],"type":"Point"}
}