{
  "type": "Feature",
  "properties": {
    "addr:full":"Schoolstraat 48 Gent Oost-Vlaanderen 9040",
    "addr:housenumber":"48",
    "addr:postcode":"9040",
    "addr:street":"Schoolstraat;Oost-Vlaanderen",
    "iso:country":"BE",
    "sg:address":"Schoolstraat 48",
    "sg:city":"Gent",
    "sg:orig_category":"Apotheken",
    "sg:phone":"+32 9 228 35 18",
    "sg:postcode":"9040",
    "sg:province":"Oost-Vlaanderen",
    "wof:name":"Rita Galle",
    "wof:placetype":"venue"
},
  "geometry": {"coordinates":[3.7490200996,51.0592002869],"type":"Point"}
}