{
  "type": "Feature",
  "properties": {
    "addr:full":"Klaverbladstraat 7/28 Lummen Limburg 3560",
    "addr:housenumber":"7 / 28",
    "addr:postcode":"3560",
    "addr:street":"Klaverbladstraat",
    "iso:country":"BE",
    "sg:address":"Klaverbladstraat 7/28",
    "sg:city":"Lummen",
    "sg:orig_category":"Chemicali\u00ebn Gh",
    "sg:phone":"+32 13 53 19 19",
    "sg:postcode":"3560",
    "sg:province":"Limburg",
    "wof:name":"Chemproha Chemische Producten Handel",
    "wof:placetype":"venue"
},
  "geometry": {"coordinates":[5.2274580002,50.9971885681],"type":"Point"}
}