{
  "type": "Feature",
  "properties": {
    "iso:country":"BE",
    "sg:address":"Rue De Mons 61",
    "sg:city":"Charleroi (marchienne-au-pont)",
    "sg:classifiers":[
        {
            "category":"Retail",
            "subcategory":"Auto Repair",
            "type":"Services"
        }
    ],
    "sg:phone":"+32 71 70 12 91",
    "sg:postcode":"6030",
    "sg:province":"Hainaut",
    "sg:tags":[
        "garage"
    ],
    "wof:name":"Karauto Sprl",
    "wof:placetype":"venue"
},
  "geometry": {"coordinates":[4.389770031,50.4096679688],"type":"Point"}
}