{
  "type": "Feature",
  "properties": {
    "addr:full":"Gudrunstraat 3bd Hooglede West-Vlaanderen 8830",
    "addr:postcode":"8830",
    "addr:street":"Gudrunstraat",
    "iso:country":"BE",
    "sg:address":"Gudrunstraat 3bd",
    "sg:city":"Hooglede",
    "sg:classifiers":[
        {
            "category":"Professional",
            "subcategory":"Accounting & Tax Preparation",
            "type":"Services"
        }
    ],
    "sg:phone":"+32 51 22 15 03",
    "sg:postcode":"8830",
    "sg:province":"West-Vlaanderen",
    "sg:tags":[
        "accountant"
    ],
    "wof:name":"Patrick Vanden Weghe",
    "wof:placetype":"venue"
},
  "geometry": {"coordinates":[3.108659029,50.9970932007],"type":"Point"}
}