{
  "type": "Feature",
  "properties": {
    "addr:full":"Chauss\u00e9e De Waterloo 152 Rhode-saint-gen\u00e8se Vlaams-Brabant 1640",
    "addr:housenumber":"152",
    "addr:postcode":"rhode-saint-gene\u0300se;1640",
    "addr:street":"Chausse\u0301E De Waterloo",
    "iso:country":"BE",
    "sg:address":"Chauss\u00e9e De Waterloo 152",
    "sg:city":"Rhode-saint-gen\u00e8se",
    "sg:classifiers":[
        {
            "category":"Government",
            "subcategory":"Fire Station",
            "type":"Public Place"
        }
    ],
    "sg:phone":"+32 2 358 28 35",
    "sg:postcode":"1640",
    "sg:province":"Vlaams-Brabant",
    "sg:tags":[
        "installation",
        "-",
        "air conditioning"
    ],
    "wof:name":"G.m.t.f.",
    "wof:placetype":"venue"
},
  "geometry": {"coordinates":[4.3931879997,50.7494621277],"type":"Point"}
}