{
  "type": "Feature",
  "properties": {
    "iso:country":"BE",
    "sg:address":"A. Bastinstraat 39",
    "sg:city":"Leuven",
    "sg:classifiers":[
        {
            "category":"Arena",
            "subcategory":"Sports Club",
            "type":"Entertainment"
        }
    ],
    "sg:phone":"+32 16 20 08 04",
    "sg:postcode":"3000",
    "sg:province":"Vlaams-Brabant",
    "sg:tags":[
        "de"
    ],
    "wof:name":"Kon. Rolta Rhc",
    "wof:placetype":"venue"
},
  "geometry": {"coordinates":[4.6890349388,50.8735580444],"type":"Point"}
}