{
  "type": "Feature",
  "properties": {
    "addr:full":"Rue De La R\u00c9sistance 15 Esneux Li\u00e8ge 4130",
    "addr:housenumber":"15",
    "addr:postcode":"4130",
    "addr:street":"Rue De La Re\u0301Sistance",
    "iso:country":"BE",
    "sg:address":"Rue De La R\u00c9sistance 15",
    "sg:city":"Esneux",
    "sg:orig_category":"Afvalwaterverwerking and ontstoppingsdiensten Herstelling aan huis van huishoudartikelen Herstelling",
    "sg:phone":"+32 4 223 12 34",
    "sg:postcode":"4130",
    "sg:province":"Li\u00e8ge",
    "wof:name":"Guy Evrard",
    "wof:placetype":"venue"
},
  "geometry": {"coordinates":[5.5713891983,50.5387268066],"type":"Point"}
}