{
  "type": "Feature",
  "properties": {
    "addr:full":"2160 Wommelgem (grand) Antwerpen 2160",
    "addr:postcode":"2160;2160",
    "iso:country":"BE",
    "sg:address":"2160",
    "sg:city":"Wommelgem (grand)",
    "sg:orig_category":"Pharmaciens",
    "sg:phone":"+32 900 10 500",
    "sg:postcode":"2160",
    "sg:province":"Antwerpen",
    "wof:name":"Pharmacies De Garde",
    "wof:placetype":"venue"
},
  "geometry": {"coordinates":[4.5230050087,51.2034759521],"type":"Point"}
}