{
  "type": "Feature",
  "properties": {
    "addr:full":"Beringenbaan 15 Diest Vlaams-Brabant 3290",
    "addr:housenumber":"15",
    "addr:postcode":"3290",
    "addr:street":"Beringenbaan",
    "iso:country":"BE",
    "sg:address":"Beringenbaan 15",
    "sg:city":"Diest",
    "sg:orig_category":"Schoonheidssalons",
    "sg:phone":"+32 13 33 31 56",
    "sg:postcode":"3290",
    "sg:province":"Vlaams-Brabant",
    "wof:name":"Annie Gielen",
    "wof:placetype":"venue"
},
  "geometry": {"coordinates":[5.0511350632,50.9845848083],"type":"Point"}
}