{
  "type": "Feature",
  "properties": {
    "iso:country":"BE",
    "sg:address":"Tiensesteenweg 384",
    "sg:city":"Leuven",
    "sg:orig_category":"Marca. V\u00eatements pour Dames. V\u00eatements pour Hommes. V\u00eatements pour b\u00e9b\u00e9s and enfants",
    "sg:phone":"+32 16 25 30 96",
    "sg:postcode":"3000",
    "sg:province":"Vlaams-Brabant",
    "wof:name":"Marca Korbeek-lo",
    "wof:placetype":"venue"
},
  "geometry": {"coordinates":[4.7406740189,50.8675117493],"type":"Point"}
}