{
  "type": "Feature",
  "properties": {
    "addr:full":"Kasteelstraat 34 Retie Antwerpen 2470",
    "addr:housenumber":"34",
    "addr:postcode":"2470",
    "addr:street":"Kasteelstraat",
    "iso:country":"BE",
    "sg:address":"Kasteelstraat 34",
    "sg:city":"Retie",
    "sg:classifiers":[
        {
            "category":"Food & Beverages",
            "subcategory":"Fruits & Vegetables",
            "type":"Retail Goods"
        }
    ],
    "sg:phone":"+32 14 37 76 43",
    "sg:postcode":"2470",
    "sg:province":"Antwerpen",
    "sg:tags":[
        "l\u00e9gumes"
    ],
    "wof:name":"'t Vitamientje",
    "wof:placetype":"venue"
},
  "geometry": {"coordinates":[5.0781888962,51.2659873962],"type":"Point"}
}