{
  "type": "Feature",
  "properties": {
    "addr:full":"Rue Des Fermes 10 H\u00e9ron (couthuin) Li\u00e8ge 4218",
    "addr:housenumber":"10",
    "addr:postcode":"4218",
    "addr:street":"Rue Des Fermes",
    "iso:country":"BE",
    "sg:address":"Rue Des Fermes 10",
    "sg:city":"H\u00e9ron (couthuin)",
    "sg:classifiers":[
        {
            "category":"Farming",
            "subcategory":"Livestock Farm",
            "type":"Manufacturing & Wholesale Goods"
        }
    ],
    "sg:phone":"+32 85 71 17 31",
    "sg:postcode":"4218",
    "sg:province":"Li\u00e8ge",
    "sg:tags":[
        "buyer"
    ],
    "wof:name":"Desmedt P",
    "wof:placetype":"venue"
},
  "geometry": {"coordinates":[5.1502628326,50.5308647156],"type":"Point"}
}