{
  "type": "Feature",
  "properties": {
    "addr:full":"Stationstraat 90b2 Heist-op-den-berg Antwerpen 2220",
    "addr:housenumber":"90b2",
    "addr:postcode":"2220",
    "addr:street":"Stationstraat",
    "iso:country":"BE",
    "sg:address":"Stationstraat 90b2",
    "sg:city":"Heist-op-den-berg",
    "sg:orig_category":"Bagage and lederwaren Schoenen",
    "sg:phone":"+32 15 24 14 78",
    "sg:postcode":"2220",
    "sg:province":"Antwerpen",
    "wof:name":"Shoe Discount",
    "wof:placetype":"venue"
},
  "geometry": {"coordinates":[4.7091598511,51.0750617981],"type":"Point"}
}