{
  "type": "Feature",
  "properties": {
    "addr:full":"Langestraat 159 Gent Oost-Vlaanderen 9050",
    "addr:housenumber":"159",
    "addr:postcode":"9050",
    "addr:street":"Langestraat;Oost-Vlaanderen",
    "iso:country":"BE",
    "sg:address":"Langestraat 159",
    "sg:city":"Gent",
    "sg:classifiers":[
        {
            "category":"Cafe",
            "type":"Food & Drink"
        }
    ],
    "sg:phone":"+32 9 231 09 64",
    "sg:postcode":"9050",
    "sg:province":"Oost-Vlaanderen",
    "sg:tags":[
        "caf\u00e9s"
    ],
    "wof:name":"Ingrid Van Bellegem",
    "wof:placetype":"venue"
},
  "geometry": {"coordinates":[3.7433099747,51.0349578857],"type":"Point"}
}