{
  "type": "Feature",
  "properties": {
    "addr:full":"Rue De Bouillon 272 Beauraing (pondr\u00f4me) Namur 5574",
    "addr:housenumber":"272",
    "addr:postcode":"5574",
    "addr:street":"Rue De Bouillon",
    "iso:country":"BE",
    "sg:address":"Rue De Bouillon 272",
    "sg:city":"Beauraing (pondr\u00f4me)",
    "sg:orig_category":"Fiduciairies",
    "sg:phone":"+32 82 71 11 55",
    "sg:postcode":"5574",
    "sg:province":"Namur",
    "wof:name":"Remy C",
    "wof:placetype":"venue"
},
  "geometry": {"coordinates":[4.9919400215,50.099281311],"type":"Point"}
}