{
  "type": "Feature",
  "properties": {
    "iso:country":"BE",
    "sg:address":"Chauss\u00c9e De Bruxelles 165-167",
    "sg:city":"Waterloo",
    "sg:orig_category":"Maroquinerie and articles de voyage",
    "sg:phone":"+32 2 354 28 67",
    "sg:postcode":"1410",
    "sg:province":"Brabant Wallon",
    "wof:name":"Delvaux Cr\u00c9ateur",
    "wof:placetype":"venue"
},
  "geometry": {"coordinates":[4.3982839584,50.7172241211],"type":"Point"}
}