{
  "type": "Feature",
  "properties": {
    "iso:country":"BE",
    "sg:address":"Vierstraat 41",
    "sg:city":"Heuvelland",
    "sg:orig_category":"Betonnen bouwelementen Fab Industri\u00eble and commerci\u00eble bouw",
    "sg:phone":"+32 57 44 48 33",
    "sg:postcode":"8950",
    "sg:province":"West-Vlaanderen",
    "wof:name":"Goudezeune",
    "wof:placetype":"venue"
},
  "geometry": {"coordinates":[2.8516829014,50.8015136719],"type":"Point"}
}