{
  "type": "Feature",
  "properties": {
    "iso:country":"BE",
    "sg:address":"Hoogstraat 18",
    "sg:city":"Bree",
    "sg:orig_category":"Pain, p\u00e2tisseries and confiseries",
    "sg:phone":"+32 89 46 17 56",
    "sg:postcode":"3960",
    "sg:province":"Limburg",
    "wof:name":"Bakkerij Prinsenhof",
    "wof:placetype":"venue"
},
  "geometry": {"coordinates":[5.5987281799,51.1412353516],"type":"Point"}
}