{
  "type": "Feature",
  "properties": {
    "addr:full":"Bredabaan 694 Brasschaat Antwerpen 2930",
    "addr:housenumber":"694",
    "addr:postcode":"2930",
    "addr:street":"Bredabaan",
    "iso:country":"BE",
    "sg:address":"Bredabaan 694",
    "sg:city":"Brasschaat",
    "sg:orig_category":"V\u00e9hicules automobiles",
    "sg:phone":"+32 3 633 27 28",
    "sg:postcode":"2930",
    "sg:province":"Antwerpen",
    "wof:name":"D.m.g.",
    "wof:placetype":"venue"
},
  "geometry": {"coordinates":[4.5161662102,51.3160629272],"type":"Point"}
}