{
  "type": "Feature",
  "properties": {
    "addr:full":"Ninoofsesteenweg 71 Pepingen Vlaams-Brabant 1670",
    "addr:housenumber":"71",
    "addr:postcode":"1670",
    "addr:street":"Ninoofsesteenweg",
    "iso:country":"BE",
    "sg:address":"Ninoofsesteenweg 71",
    "sg:city":"Pepingen",
    "sg:orig_category":"Caf\u00e9s Ruimtes voor conferenties, recepties and feesten",
    "sg:phone":"+32 2 360 08 49",
    "sg:postcode":"1670",
    "sg:province":"Vlaams-Brabant",
    "wof:name":"Limbourg",
    "wof:placetype":"venue"
},
  "geometry": {"coordinates":[4.1680049896,50.7570800781],"type":"Point"}
}