{
  "type": "Feature",
  "properties": {
    "addr:full":"Lichterstraat 4 Puurs Antwerpen 2870",
    "addr:housenumber":"4",
    "addr:postcode":"2870",
    "addr:street":"Lichterstraat",
    "iso:country":"BE",
    "sg:address":"Lichterstraat 4",
    "sg:city":"Puurs",
    "sg:classifiers":[
        {
            "category":"Personal",
            "subcategory":"Beauty Salon",
            "type":"Services"
        }
    ],
    "sg:phone":"+32 3 889 21 91",
    "sg:postcode":"2870",
    "sg:province":"Antwerpen",
    "sg:tags":[
        "lady",
        "-",
        "hairdressing"
    ],
    "wof:name":"Hair Fashion",
    "wof:placetype":"venue"
},
  "geometry": {"coordinates":[4.3129968643,51.0622253418],"type":"Point"}
}