{
  "type": "Feature",
  "properties": {
    "iso:country":"BE",
    "sg:address":"Sikambrenstraat 3",
    "sg:city":"Etterbeek/etterbeek",
    "sg:orig_category":"Artsen and specialisten",
    "sg:phone":"+32 2 736 80 07",
    "sg:postcode":"1040",
    "sg:province":"Bruxelles-Capitale",
    "wof:name":"Do Dinh Thanh",
    "wof:placetype":"venue"
},
  "geometry": {"coordinates":[4.4033260345,50.8325119019],"type":"Point"}
}