{
  "type": "Feature",
  "properties": {
    "addr:full":"Hansbekedorp 73 Nevele (hansbeke) Oost-Vlaanderen 9850",
    "addr:housenumber":"73",
    "addr:postcode":"9850",
    "addr:street":"Hansbekedorp",
    "iso:country":"BE",
    "sg:address":"Hansbekedorp 73",
    "sg:city":"Nevele (hansbeke)",
    "sg:classifiers":[
        {
            "category":"Retail",
            "subcategory":"Auto Repair",
            "type":"Services"
        }
    ],
    "sg:phone":"+32 9 371 56 29",
    "sg:postcode":"9850",
    "sg:province":"Oost-Vlaanderen",
    "sg:tags":[
        "garage"
    ],
    "wof:name":"Opel/d'haenens",
    "wof:placetype":"venue"
},
  "geometry": {"coordinates":[3.5348041058,51.0793457031],"type":"Point"}
}