{
  "type": "Feature",
  "properties": {
    "addr:full":"Koninginnelaan 37 Gent (drongen) Oost-Vlaanderen 9031",
    "addr:housenumber":"37",
    "addr:postcode":"9031",
    "addr:street":"Koninginnelaan",
    "iso:country":"BE",
    "sg:address":"Koninginnelaan 37",
    "sg:city":"Gent (drongen)",
    "sg:classifiers":[
        {
            "category":"Health Services",
            "subcategory":"Health Practitioner",
            "type":"Services"
        }
    ],
    "sg:phone":"+32 9 217 06 98",
    "sg:postcode":"9031",
    "sg:province":"Oost-Vlaanderen",
    "sg:tags":[
        "physiotherapist"
    ],
    "wof:name":"Nuytten Christophe",
    "wof:placetype":"venue"
},
  "geometry": {"coordinates":[3.6625859737,51.0545082092],"type":"Point"}
}