{
  "type": "Feature",
  "properties": {
    "iso:country":"BE",
    "sg:address":"Posterijlaan 47a",
    "sg:city":"Pittem",
    "sg:orig_category":"Charpentes and couvertures. Mat\u00e9riaux de construction Gr",
    "sg:phone":"+32 51 46 71 86",
    "sg:postcode":"8740",
    "sg:province":"West-Vlaanderen",
    "wof:name":"Alg Dakwerken Vandaele",
    "wof:placetype":"venue"
},
  "geometry": {"coordinates":[3.2471950054,50.990020752],"type":"Point"}
}