{
  "type": "Feature",
  "properties": {
    "iso:country":"BE",
    "sg:address":"Zoerleberg 18",
    "sg:city":"Westerlo",
    "sg:orig_category":"Secretariaatsdiensten",
    "sg:phone":"+32 14 54 73 00",
    "sg:postcode":"2260",
    "sg:province":"Antwerpen",
    "wof:name":"Phaedra Creative Communications",
    "wof:placetype":"venue"
},
  "geometry": {"coordinates":[4.8830480576,51.0854415894],"type":"Point"}
}