{
  "type": "Feature",
  "properties": {
    "iso:country":"BE",
    "sg:address":"Ambacht. Zone Balendijk 2444",
    "sg:city":"Lommel",
    "sg:orig_category":"Installatie van metalen schrijnwerk",
    "sg:phone":"+32 11 54 43 53",
    "sg:postcode":"3920",
    "sg:province":"Limburg",
    "wof:name":"Charles Van Den Eynde",
    "wof:placetype":"venue"
},
  "geometry": {"coordinates":[5.2645001411,51.2141990662],"type":"Point"}
}