{
  "type": "Feature",
  "properties": {
    "iso:country":"BE",
    "sg:address":"Kanaaldijk",
    "sg:city":"Puurs (ruisbroek)",
    "sg:orig_category":"Malthouses",
    "sg:phone":"+32 3 860 04 11",
    "sg:postcode":"2870",
    "sg:province":"Antwerpen",
    "wof:name":"Mouterij Albert Nv",
    "wof:placetype":"venue"
},
  "geometry": {"coordinates":[4.3418831825,51.0905036926],"type":"Point"}
}