{
  "type": "Feature",
  "properties": {
    "iso:country":"BE",
    "sg:address":"Heidekasteeldreef 26",
    "sg:city":"Berlare",
    "sg:orig_category":"Eleveurs de volaille. Production and transformation de viande",
    "sg:phone":"+32 52 42 33 66",
    "sg:postcode":"9290",
    "sg:province":"Oost-Vlaanderen",
    "wof:name":"Serafin Apers",
    "wof:placetype":"venue"
},
  "geometry": {"coordinates":[4.0026888847,51.015045166],"type":"Point"}
}