{
  "type": "Feature",
  "properties": {
    "iso:country":"BE",
    "sg:address":"Rue De La Maillebotte 6",
    "sg:city":"Nivelles",
    "sg:orig_category":"Schoonheidssalons",
    "sg:phone":"+32 67 21 02 27",
    "sg:postcode":"1400",
    "sg:province":"Brabant Wallon",
    "wof:name":"Cecile Brohee",
    "wof:placetype":"venue"
},
  "geometry": {"coordinates":[4.3387889862,50.6047668457],"type":"Point"}
}