{
  "type": "Feature",
  "properties": {
    "iso:country":"BE",
    "sg:address":"Ferdinand Lousbergskaai 105-1",
    "sg:city":"Gent",
    "sg:classifiers":[
        {
            "category":"Professional",
            "subcategory":"Printing & Photocopies",
            "type":"Services"
        }
    ],
    "sg:phone":"+32 9 265 85 75",
    "sg:postcode":"9000",
    "sg:province":"Oost-Vlaanderen",
    "sg:tags":[
        "-",
        "publishing",
        "desktop"
    ],
    "wof:name":"Mediactief Bvba",
    "wof:placetype":"venue"
},
  "geometry": {"coordinates":[3.7396099567,51.0468177795],"type":"Point"}
}