{
  "type": "Feature",
  "properties": {
    "addr:full":"Gentsesteenweg 376 Zele Oost-Vlaanderen 9240",
    "addr:housenumber":"376",
    "addr:postcode":"9240",
    "addr:street":"Gentsesteenweg",
    "iso:country":"BE",
    "sg:address":"Gentsesteenweg 376",
    "sg:city":"Zele",
    "sg:orig_category":"Rundveehouders",
    "sg:phone":"+32 9 367 68 83",
    "sg:postcode":"9240",
    "sg:province":"Oost-Vlaanderen",
    "wof:name":"Jose Hanselaer",
    "wof:placetype":"venue"
},
  "geometry": {"coordinates":[3.9812870026,51.0541534424],"type":"Point"}
}