{
  "type": "Feature",
  "properties": {
    "iso:country":"BE",
    "sg:address":"Rue De L'eglise 39",
    "sg:city":"Drogenbos",
    "sg:classifiers":[
        {
            "category":"Health Services",
            "subcategory":"Dentist",
            "type":"Services"
        }
    ],
    "sg:phone":"+32 2 331 31 05",
    "sg:postcode":"1620",
    "sg:province":"Vlaams-Brabant",
    "wof:name":"Peeters Sylvia",
    "wof:placetype":"venue"
},
  "geometry": {"coordinates":[4.3178291321,50.7887191772],"type":"Point"}
}