{
  "type": "Feature",
  "properties": {
    "iso:country":"BE",
    "sg:address":"Grand'rue 171",
    "sg:city":"Charleroi",
    "sg:classifiers":[
        {
            "category":"Cafe",
            "type":"Food & Drink"
        }
    ],
    "sg:phone":"+32 71 41 98 88",
    "sg:postcode":"6000",
    "sg:province":"Hainaut",
    "sg:tags":[
        "caf\u00e9s"
    ],
    "wof:name":"Caf\u00c9 Le Lion",
    "wof:placetype":"venue"
},
  "geometry": {"coordinates":[4.4527988434,50.4181480408],"type":"Point"}
}