{
  "type": "Feature",
  "properties": {
    "iso:country":"BE",
    "sg:address":"Rue Albert Ier 77",
    "sg:city":"Hannut",
    "sg:orig_category":"Voertuigen",
    "sg:phone":"+32 19 51 27 70",
    "sg:postcode":"4280",
    "sg:province":"Li\u00e8ge",
    "wof:name":"T.c. Motor",
    "wof:placetype":"venue"
},
  "geometry": {"coordinates":[5.0823459625,50.6702346802],"type":"Point"}
}