{
  "type": "Feature",
  "properties": {
    "addr:full":"Rue De L'institut 5 Rixensart Brabant Wallon 1330",
    "addr:housenumber":"5",
    "addr:postcode":"1330",
    "addr:street":"Rue De L'Institut;Wallon",
    "iso:country":"BE",
    "sg:address":"Rue De L'institut 5",
    "sg:city":"Rixensart",
    "sg:orig_category":"Fotogravure and zetwerk Secretariaatsdiensten",
    "sg:phone":"+32 2 653 72 03",
    "sg:postcode":"1330",
    "sg:province":"Brabant Wallon",
    "wof:name":"J.p. Production",
    "wof:placetype":"venue"
},
  "geometry": {"coordinates":[4.5307149887,50.7160148621],"type":"Point"}
}