{
  "type": "Feature",
  "properties": {
    "iso:country":"BE",
    "sg:address":"Rue Joseph Joirkin 37",
    "sg:city":"Donceel",
    "sg:classifiers":[
        {
            "category":"Wholesale",
            "subcategory":"Fruits & Vegetables",
            "type":"Manufacturing & Wholesale Goods"
        }
    ],
    "sg:phone":"+32 19 54 43 82",
    "sg:postcode":"4357",
    "sg:province":"Li\u00e8ge",
    "sg:tags":[
        "whol",
        "-"
    ],
    "wof:name":"Frudelco Sprl",
    "wof:placetype":"venue"
},
  "geometry": {"coordinates":[5.3194651604,50.6516227722],"type":"Point"}
}