{
  "type": "Feature",
  "properties": {
    "iso:country":"BE",
    "sg:address":"Industrieweg-noord 1110",
    "sg:city":"Opglabbeek",
    "sg:orig_category":"RESTAURANTS: POUR COLLECTIVIT\u00c9S",
    "sg:phone":"+32 89 61 42 44",
    "sg:postcode":"3660",
    "sg:province":"Limburg",
    "wof:name":"T.a.s. Koffie Service",
    "wof:placetype":"venue"
},
  "geometry": {"coordinates":[5.5340771675,51.03465271],"type":"Point"}
}