{
  "type": "Feature",
  "properties": {
    "addr:full":"Honor\u00c9 Borgersstraat 72bb Oostende West-Vlaanderen 8400",
    "addr:postcode":"8400",
    "addr:street":"Borgersstraat",
    "iso:country":"BE",
    "sg:address":"Honor\u00c9 Borgersstraat 72bb",
    "sg:city":"Oostende",
    "sg:orig_category":"Diverse machines voor de nijverheid Gh HUISBRANDOLIE",
    "sg:phone":"+32 59 70 03 62",
    "sg:postcode":"8400",
    "sg:province":"West-Vlaanderen",
    "wof:name":"Alvolas Du Gardein",
    "wof:placetype":"venue"
},
  "geometry": {"coordinates":[2.9021708965,51.2155036926],"type":"Point"}
}