{
  "type": "Feature",
  "properties": {
    "iso:country":"BE",
    "sg:address":"Westlaan 191",
    "sg:city":"Heusden-zolder",
    "sg:orig_category":"Enseignement maternel and primaire",
    "sg:phone":"+32 11 42 66 64",
    "sg:postcode":"3550",
    "sg:province":"Limburg",
    "wof:name":"B.s.b.o. Heideland",
    "wof:placetype":"venue"
},
  "geometry": {"coordinates":[5.2493658066,50.9987640381],"type":"Point"}
}