{
  "type": "Feature",
  "properties": {
    "addr:full":"Rue Dautzenberg 60 Bruxelles (ixelles) Bruxelles-Capitale 1050",
    "addr:housenumber":"60",
    "addr:postcode":"1050",
    "addr:street":"Rue Dautzenberg",
    "iso:country":"BE",
    "sg:address":"Rue Dautzenberg 60",
    "sg:city":"Bruxelles (ixelles)",
    "sg:classifiers":[
        {
            "category":"Health Services",
            "subcategory":"Dentist",
            "type":"Services"
        }
    ],
    "sg:phone":"+32 2 644 58 70",
    "sg:postcode":"1050",
    "sg:province":"Bruxelles-Capitale",
    "wof:name":"Paquet Michel",
    "wof:placetype":"venue"
},
  "geometry": {"coordinates":[4.3672699928,50.8264198303],"type":"Point"}
}