{
  "type": "Feature",
  "properties": {
    "addr:full":"Broekestraat 6 Horebeke Oost-Vlaanderen 9667",
    "addr:housenumber":"6",
    "addr:postcode":"9667",
    "addr:street":"Broekestraat",
    "iso:country":"BE",
    "sg:address":"Broekestraat 6",
    "sg:city":"Horebeke",
    "sg:orig_category":"Naai- and breimachines",
    "sg:phone":"+32 55 49 92 08",
    "sg:postcode":"9667",
    "sg:province":"Oost-Vlaanderen",
    "wof:name":"Vandenberghe Naaimachines",
    "wof:placetype":"venue"
},
  "geometry": {"coordinates":[3.6967220306,50.843963623],"type":"Point"}
}