{
  "type": "Feature",
  "properties": {
    "addr:full":"Route De Philippeville 127 Charleroi (marcinelle) Hainaut 6001",
    "addr:housenumber":"127",
    "addr:postcode":"6001",
    "addr:street":"Route De Philippeville",
    "iso:country":"BE",
    "sg:address":"Route De Philippeville 127",
    "sg:city":"Charleroi (marcinelle)",
    "sg:classifiers":[
        {
            "category":"Banks & Credit Unions",
            "subcategory":"Investment Brokerage",
            "type":"Services"
        }
    ],
    "sg:phone":"+32 71 47 93 00",
    "sg:postcode":"6001",
    "sg:province":"Hainaut",
    "sg:tags":[
        "jean",
        "casual",
        "wear"
    ],
    "wof:name":"Fashion Store",
    "wof:placetype":"venue"
},
  "geometry": {"coordinates":[4.4603209496,50.3898124695],"type":"Point"}
}