{
  "type": "Feature",
  "properties": {
    "addr:full":"Krommekeerstraat 21 Ruiselede West-Vlaanderen 8755",
    "addr:housenumber":"21",
    "addr:postcode":"8755",
    "addr:street":"Krommekeerstraat",
    "iso:country":"BE",
    "sg:address":"Krommekeerstraat 21",
    "sg:city":"Ruiselede",
    "sg:classifiers":[
        {
            "category":"Brewery",
            "type":"Food & Drink"
        }
    ],
    "sg:phone":"+32 51 68 89 99",
    "sg:postcode":"8755",
    "sg:province":"West-Vlaanderen",
    "wof:name":"De Leyerth Bvba",
    "wof:placetype":"venue"
},
  "geometry": {"coordinates":[3.3686408997,51.0814323425],"type":"Point"}
}