{
  "type": "Feature",
  "properties": {
    "iso:country":"BE",
    "sg:address":"Hoogstraat 4",
    "sg:city":"Assenede",
    "sg:orig_category":"Salles de spectacles",
    "sg:phone":"+32 9 344 50 57",
    "sg:postcode":"9960",
    "sg:province":"Oost-Vlaanderen",
    "wof:name":"Galerij Pim De Rudder",
    "wof:placetype":"venue"
},
  "geometry": {"coordinates":[3.7538239956,51.2276039124],"type":"Point"}
}