{
  "type": "Feature",
  "properties": {
    "addr:full":"Avenue Fernand Desonay 73 Verviers (stembert) Li\u00e8ge 4801",
    "addr:housenumber":"73",
    "addr:postcode":"4801",
    "addr:street":"Avenue Fernand Desonay",
    "iso:country":"BE",
    "sg:address":"Avenue Fernand Desonay 73",
    "sg:city":"Verviers (stembert)",
    "sg:classifiers":[
        {
            "category":"Health Services",
            "subcategory":"Dentist",
            "type":"Services"
        }
    ],
    "sg:phone":"+32 87 22 73 23",
    "sg:postcode":"4801",
    "sg:province":"Li\u00e8ge",
    "wof:name":"Magermans F",
    "wof:placetype":"venue"
},
  "geometry": {"coordinates":[5.8895659447,50.5888442993],"type":"Point"}
}