{
  "type": "Feature",
  "properties": {
    "iso:country":"BE",
    "sg:address":"Kortrijkstraat 292",
    "sg:city":"Wevelgem",
    "sg:orig_category":"Solar protection - Outside",
    "sg:phone":"+32 56 42 22 86",
    "sg:postcode":"8560",
    "sg:province":"West-Vlaanderen",
    "wof:name":"Holstra Bvba",
    "wof:placetype":"venue"
},
  "geometry": {"coordinates":[3.2000579834,50.8136138916],"type":"Point"}
}