{
  "type": "Feature",
  "properties": {
    "iso:country":"BE",
    "sg:address":"Paalstraat 25",
    "sg:city":"Heist-op-den-berg (schriek)",
    "sg:orig_category":"Accumulators",
    "sg:phone":"+32 16 53 80 69",
    "sg:postcode":"2223",
    "sg:province":"Antwerpen",
    "wof:name":"Janssens Stefan",
    "wof:placetype":"venue"
},
  "geometry": {"coordinates":[4.6935648918,51.0282707214],"type":"Point"}
}