{
  "type": "Feature",
  "properties": {
    "addr:full":"Industrieterrein Oude Bunders 2046 Maasmechelen Limburg 3630",
    "addr:postcode":"2046 maasmechelen;3630",
    "addr:street":"Industrieterrein Oude Bunders",
    "iso:country":"BE",
    "sg:address":"Industrieterrein Oude Bunders 2046",
    "sg:city":"Maasmechelen",
    "sg:classifiers":[
        {
            "category":"Manufacturing",
            "subcategory":"Metals",
            "type":"Manufacturing & Wholesale Goods"
        }
    ],
    "sg:phone":"+32 89 77 04 50",
    "sg:postcode":"3630",
    "sg:province":"Limburg",
    "sg:tags":[
        "profile"
    ],
    "wof:name":"Profiel Service Nv",
    "wof:placetype":"venue"
},
  "geometry": {"coordinates":[5.7027478218,50.9504241943],"type":"Point"}
}