{
  "type": "Feature",
  "properties": {
    "addr:full":"Stationsstraat 235 Deerlijk West-Vlaanderen 8540",
    "addr:housenumber":"235",
    "addr:postcode":"8540",
    "addr:street":"Stationsstraat",
    "iso:country":"BE",
    "sg:address":"Stationsstraat 235",
    "sg:city":"Deerlijk",
    "sg:orig_category":"Producteurs de l\u00e9gumes",
    "sg:phone":"+32 56 77 75 53",
    "sg:postcode":"8540",
    "sg:province":"West-Vlaanderen",
    "wof:name":"Maurice Bekaert",
    "wof:placetype":"venue"
},
  "geometry": {"coordinates":[3.3496360779,50.8393211365],"type":"Point"}
}