{
  "type": "Feature",
  "properties": {
    "iso:country":"BE",
    "sg:address":"Turnhoutsebaan 58",
    "sg:city":"Antwerpen",
    "sg:orig_category":"Opticiens",
    "sg:phone":"+32 3 235 29 91",
    "sg:postcode":"2140",
    "sg:province":"Antwerpen",
    "wof:name":"Optiek Center",
    "wof:placetype":"venue"
},
  "geometry": {"coordinates":[4.4332199097,51.2137565613],"type":"Point"}
}