{
  "type": "Feature",
  "properties": {
    "addr:full":"Rue Du Calvaire 18 Aiseau-presles Hainaut 6250",
    "addr:housenumber":"18",
    "addr:postcode":"6250",
    "addr:street":"Rue Du Calvaire;Hainaut",
    "iso:country":"BE",
    "sg:address":"Rue Du Calvaire 18",
    "sg:city":"Aiseau-presles",
    "sg:orig_category":"Elektrische installaties voor woningen",
    "sg:phone":"+32 71 40 12 28",
    "sg:postcode":"6250",
    "sg:province":"Hainaut",
    "wof:name":"Pascal Bay",
    "wof:placetype":"venue"
},
  "geometry": {"coordinates":[4.5863847733,50.40990448],"type":"Point"}
}