{
  "type": "Feature",
  "properties": {
    "iso:country":"BE",
    "sg:address":"Oosthelling 0",
    "sg:city":"Oostende",
    "sg:orig_category":"Services divers aux entreprises. Organisation de salons, expositions and bourses. Jeux de hasard. Re",
    "sg:phone":"+32 59 70 51 11",
    "sg:postcode":"8400",
    "sg:province":"West-Vlaanderen",
    "wof:name":"Casino Kursaal",
    "wof:placetype":"venue"
},
  "geometry": {"coordinates":[2.9356749058,51.2230796814],"type":"Point"}
}