{
  "type": "Feature",
  "properties": {
    "iso:country":"BE",
    "sg:address":"Moerheide 93",
    "sg:city":"Hamme",
    "sg:orig_category":"Boissons",
    "sg:phone":"+32 52 47 21 37",
    "sg:postcode":"9220",
    "sg:province":"Oost-Vlaanderen",
    "wof:name":"Traiteur De Kreeftenboer",
    "wof:placetype":"venue"
},
  "geometry": {"coordinates":[4.1115241051,51.0923576355],"type":"Point"}
}