{
  "type": "Feature",
  "properties": {
    "iso:country":"BE",
    "sg:address":"Chauss\u00c9e De Namur 485",
    "sg:city":"Gembloux",
    "sg:classifiers":[
        {
            "category":"Cafe",
            "type":"Food & Drink"
        }
    ],
    "sg:phone":"+32 81 56 67 01",
    "sg:postcode":"5030",
    "sg:province":"Namur",
    "sg:tags":[
        "caf\u00e9s"
    ],
    "wof:name":"Marinette Wynants",
    "wof:placetype":"venue"
},
  "geometry": {"coordinates":[4.7088198662,50.5527381897],"type":"Point"}
}