{
  "type": "Feature",
  "properties": {
    "addr:full":"Rue De Charleroi 24 Genappe Brabant Wallon 1470",
    "addr:housenumber":"24",
    "addr:postcode":"1470",
    "addr:street":"Rue De Charleroi;Wallon",
    "iso:country":"BE",
    "sg:address":"Rue De Charleroi 24",
    "sg:city":"Genappe",
    "sg:orig_category":"Supermarch\u00e9s",
    "sg:phone":"+32 67 77 28 58",
    "sg:postcode":"1470",
    "sg:province":"Brabant Wallon",
    "wof:name":"Unic",
    "wof:placetype":"venue"
},
  "geometry": {"coordinates":[4.4504947662,50.6099090576],"type":"Point"}
}