{
  "type": "Feature",
  "properties": {
    "iso:country":"BE",
    "sg:address":"Rue De L'avedelle 135",
    "sg:city":"Ecaussinnes (ecaussinnes-d'enghien)",
    "sg:classifiers":[
        {
            "category":"Building & Trades",
            "subcategory":"Plumbing",
            "type":"Services"
        }
    ],
    "sg:phone":"+32 67 44 39 16",
    "sg:postcode":"7190",
    "sg:province":"Hainaut",
    "sg:tags":[
        "repair",
        "mainten",
        "-",
        "central",
        "heating"
    ],
    "wof:name":"Chauffage Clean Service",
    "wof:placetype":"venue"
},
  "geometry": {"coordinates":[4.1783390045,50.556678772],"type":"Point"}
}