{
  "type": "Feature",
  "properties": {
    "addr:full":"Rue De Hennin 18 Elsene/ixelles Bruxelles-Capitale 1050",
    "addr:housenumber":"18",
    "addr:postcode":"1050",
    "addr:street":"Rue De Hennin",
    "iso:country":"BE",
    "sg:address":"Rue De Hennin 18",
    "sg:city":"Elsene/ixelles",
    "sg:orig_category":"Supermarch\u00e9s",
    "sg:phone":"+32 2 648 58 38",
    "sg:postcode":"1050",
    "sg:province":"Bruxelles-Capitale",
    "wof:name":"Delhaize",
    "wof:placetype":"venue"
},
  "geometry": {"coordinates":[4.368847847,50.8295478821],"type":"Point"}
}