{
  "type": "Feature",
  "properties": {
    "addr:full":"Avenue Du Roi Albert 670b1 Mons Hainaut 7012",
    "addr:housenumber":"670b1",
    "addr:postcode":"7012",
    "addr:street":"Avenue Du Roi Albert;Hainaut",
    "iso:country":"BE",
    "sg:address":"Avenue Du Roi Albert 670b1",
    "sg:city":"Mons",
    "sg:classifiers":[
        {
            "category":"Insurance",
            "subcategory":"Insurance Agent",
            "type":"Services"
        }
    ],
    "sg:phone":"+32 65 88 49 99",
    "sg:postcode":"7012",
    "sg:province":"Hainaut",
    "sg:tags":[
        "verzekeringsmakelaars",
        "expert"
    ],
    "wof:name":"Glineur Bernard",
    "wof:placetype":"venue"
},
  "geometry": {"coordinates":[3.8894600868,50.4481964111],"type":"Point"}
}