{
  "type": "Feature",
  "properties": {
    "addr:full":"Ommegangstraat 15 Horebeke (sint-kornelis-horebeke) Oost-Vlaanderen 9667",
    "addr:housenumber":"15",
    "addr:postcode":"9667",
    "addr:street":"Ommegangstraat",
    "iso:country":"BE",
    "sg:address":"Ommegangstraat 15",
    "sg:city":"Horebeke (sint-kornelis-horebeke)",
    "sg:classifiers":[
        {
            "category":"Building & Trades",
            "subcategory":"Electrical",
            "type":"Services"
        }
    ],
    "sg:phone":"+32 477 20 07 31",
    "sg:postcode":"9667",
    "sg:province":"Oost-Vlaanderen",
    "sg:tags":[
        "-",
        "electric",
        "contractor"
    ],
    "wof:name":"Dr Products Automation",
    "wof:placetype":"venue"
},
  "geometry": {"coordinates":[3.6990849972,50.8373947144],"type":"Point"}
}