{
  "type": "Feature",
  "properties": {
    "addr:full":"La Batte 10 Li\u00c8ge Li\u00e8ge 4000",
    "addr:housenumber":"10",
    "addr:postcode":"4000",
    "addr:street":"Batte",
    "iso:country":"BE",
    "sg:address":"La Batte 10",
    "sg:city":"Li\u00c8ge",
    "sg:orig_category":"Immobili\u00ebnkantoren",
    "sg:phone":"+32 4 221 91 42",
    "sg:postcode":"4000",
    "sg:province":"Li\u00e8ge",
    "wof:name":"Li\u00c8ge Logement",
    "wof:placetype":"venue"
},
  "geometry": {"coordinates":[5.5801968575,50.6456336975],"type":"Point"}
}