{
  "type": "Feature",
  "properties": {
    "iso:country":"BE",
    "sg:address":"Lange Steenstraat 69",
    "sg:city":"Gent",
    "sg:classifiers":[
        {
            "category":"Cafe",
            "type":"Food & Drink"
        }
    ],
    "sg:phone":"+32 9 224 31 18",
    "sg:postcode":"9000",
    "sg:province":"Oost-Vlaanderen",
    "sg:tags":[
        "caf\u00e9s"
    ],
    "wof:name":"Jacques Verdegem",
    "wof:placetype":"venue"
},
  "geometry": {"coordinates":[3.7226080894,51.0594596863],"type":"Point"}
}