{
  "type": "Feature",
  "properties": {
    "iso:country":"BE",
    "sg:address":"Wakkerzeelsebaan 93b4",
    "sg:city":"Leuven",
    "sg:orig_category":"M\u00e9decins and sp\u00e9cialistes",
    "sg:phone":"+32 16 23 72 35",
    "sg:postcode":"3012",
    "sg:province":"Vlaams-Brabant",
    "wof:name":"Filip Lanssens",
    "wof:placetype":"venue"
},
  "geometry": {"coordinates":[4.69871521,50.8927688599],"type":"Point"}
}