{
  "type": "Feature",
  "properties": {
    "addr:full":"Bosschelweg 48 Bocholt Limburg 3950",
    "addr:housenumber":"48",
    "addr:postcode":"3950",
    "addr:street":"Bosschelweg",
    "iso:country":"BE",
    "sg:address":"Bosschelweg 48",
    "sg:city":"Bocholt",
    "sg:orig_category":"Sportclubs Sportterreinen and installaties behalve sportcentra",
    "sg:phone":"+32 11 44 15 48",
    "sg:postcode":"3950",
    "sg:province":"Limburg",
    "wof:name":"Kaulille F.c.",
    "wof:placetype":"venue"
},
  "geometry": {"coordinates":[5.5170779228,51.18516922],"type":"Point"}
}