{
  "type": "Feature",
  "properties": {
    "addr:full":"Valerius De Saedeleerstraat 93 Aalst Oost-Vlaanderen 9300",
    "addr:housenumber":"93",
    "addr:postcode":"9300",
    "addr:street":"Valerius De Saedeleerstraat",
    "iso:country":"BE",
    "sg:address":"Valerius De Saedeleerstraat 93",
    "sg:city":"Aalst",
    "sg:classifiers":[
        {
            "category":"Retail",
            "subcategory":"Auto Repair",
            "type":"Services"
        }
    ],
    "sg:phone":"+32 53 77 04 98",
    "sg:postcode":"9300",
    "sg:province":"Oost-Vlaanderen",
    "sg:tags":[
        "garage"
    ],
    "wof:name":"Daihatsu/garage Energie",
    "wof:placetype":"venue"
},
  "geometry": {"coordinates":[4.0303277969,50.9440498352],"type":"Point"}
}