{
  "type": "Feature",
  "properties": {
    "addr:full":"Isabellalei 51 Antwerpen Antwerpen 2018",
    "addr:housenumber":"51",
    "addr:postcode":"2018",
    "addr:street":"Isabellalei",
    "iso:country":"BE",
    "sg:address":"Isabellalei 51",
    "sg:city":"Antwerpen",
    "sg:orig_category":"GROENTEN AND FRUIT Groenten and fruit Gh",
    "sg:phone":"+32 3 218 89 68",
    "sg:postcode":"2018",
    "sg:province":"Antwerpen",
    "wof:name":"Mechelse Groentenmarkt",
    "wof:placetype":"venue"
},
  "geometry": {"coordinates":[4.4165859222,51.2052993774],"type":"Point"}
}