{
  "type": "Feature",
  "properties": {
    "addr:full":"Square Fran\u00e7ois Riga 18 Bruxelles (schaerbeek) Bruxelles-Capitale 1030",
    "addr:housenumber":"18",
    "addr:postcode":"1030",
    "addr:street":"Square Franc\u0327Ois Riga",
    "iso:country":"BE",
    "sg:address":"Square Fran\u00e7ois Riga 18",
    "sg:city":"Bruxelles (schaerbeek)",
    "sg:classifiers":[
        {
            "category":"Health Services",
            "subcategory":"Nursing And Care Facility",
            "type":"Services"
        }
    ],
    "sg:phone":"+32 2 503 56 90",
    "sg:postcode":"1030",
    "sg:province":"Bruxelles-Capitale",
    "sg:tags":[
        "home"
    ],
    "wof:name":"Infimedic Asbl",
    "wof:placetype":"venue"
},
  "geometry": {"coordinates":[4.3841109276,50.873550415],"type":"Point"}
}