{
  "type": "Feature",
  "properties": {
    "iso:country":"BE",
    "sg:address":"Zwijnaardsesteenweg 710",
    "sg:city":"Gent",
    "sg:classifiers":[
        {
            "category":"Arena",
            "subcategory":"Sports Club",
            "type":"Entertainment"
        }
    ],
    "sg:phone":"+32 9 222 55 59",
    "sg:postcode":"9000",
    "sg:province":"Oost-Vlaanderen",
    "sg:tags":[
        "de"
    ],
    "wof:name":"De Lieve Bc Fv",
    "wof:placetype":"venue"
},
  "geometry": {"coordinates":[3.7201778889,51.0212631226],"type":"Point"}
}