{
  "type": "Feature",
  "properties": {
    "iso:country":"BE",
    "sg:address":"Chauss\u00e9e De Perwez 466",
    "sg:city":"Namur (saint-marc)",
    "sg:classifiers":[
        {
            "category":"Wholesale",
            "subcategory":"Meat",
            "type":"Manufacturing & Wholesale Goods"
        }
    ],
    "sg:phone":"+32 81 73 31 55",
    "sg:postcode":"5003",
    "sg:province":"Namur",
    "sg:tags":[
        "whol",
        "-"
    ],
    "wof:name":"Reveillon A",
    "wof:placetype":"venue"
},
  "geometry": {"coordinates":[4.8473348618,50.4915008545],"type":"Point"}
}