{
  "type": "Feature",
  "properties": {
    "iso:country":"BE",
    "sg:address":"Rue De Bernifa 10",
    "sg:city":"Bertrix",
    "sg:orig_category":"Afbraak- and draineerwerken",
    "sg:phone":"+32 61 53 35 28",
    "sg:postcode":"6880",
    "sg:province":"Luxembourg",
    "wof:name":"Collot",
    "wof:placetype":"venue"
},
  "geometry": {"coordinates":[5.2535948753,49.8544845581],"type":"Point"}
}