{
  "type": "Feature",
  "properties": {
    "addr:full":"Kapucinessenstraat 29-2 Antwerpen Antwerpen 2000",
    "addr:housenumber":"29-2",
    "addr:postcode":"2000",
    "addr:street":"Kapucinessenstraat",
    "iso:country":"BE",
    "sg:address":"Kapucinessenstraat 29-2",
    "sg:city":"Antwerpen",
    "sg:classifiers":[
        {
            "category":"Real Estate",
            "subcategory":"Architect",
            "type":"Services"
        }
    ],
    "sg:phone":"+32 476 31 09 68",
    "sg:postcode":"2000",
    "sg:province":"Antwerpen",
    "wof:name":"Heysse N",
    "wof:placetype":"venue"
},
  "geometry": {"coordinates":[4.4042448997,51.2109985352],"type":"Point"}
}