{
  "type": "Feature",
  "properties": {
    "iso:country":"BE",
    "sg:address":"Provenplein 58a",
    "sg:city":"Poperinge (proven)",
    "sg:classifiers":[
        {
            "category":"Building & Trades",
            "subcategory":"Electrical",
            "type":"Services"
        }
    ],
    "sg:phone":"+32 57 30 08 19",
    "sg:postcode":"8972",
    "sg:province":"West-Vlaanderen",
    "sg:tags":[
        "-",
        "electric",
        "contractor"
    ],
    "wof:name":"Dedelec Bvba",
    "wof:placetype":"venue"
},
  "geometry": {"coordinates":[2.6230740547,50.9200134277],"type":"Point"}
}