{
  "type": "Feature",
  "properties": {
    "iso:country":"BE",
    "sg:address":"F\u00c9ronstr\u00c9e 73",
    "sg:city":"Li\u00c8ge",
    "sg:classifiers":[
        {
            "category":"Shopping",
            "subcategory":"Clothing, Apparel, & Fashions",
            "type":"Retail Goods"
        }
    ],
    "sg:phone":"+32 4 222 01 58",
    "sg:postcode":"4000",
    "sg:province":"Li\u00e8ge",
    "sg:tags":[
        "v\u00eatements",
        "pour",
        "dame"
    ],
    "wof:name":"Maison Mody's",
    "wof:placetype":"venue"
},
  "geometry": {"coordinates":[5.5790438652,50.6465454102],"type":"Point"}
}