{
  "type": "Feature",
  "properties": {
    "iso:country":"BE",
    "sg:address":"Melaan 28",
    "sg:city":"Mechelen",
    "sg:orig_category":"Advocaten and juridische adviseurs",
    "sg:phone":"+32 15 20 51 75",
    "sg:postcode":"2800",
    "sg:province":"Antwerpen",
    "wof:name":"M. Schuurmans",
    "wof:placetype":"venue"
},
  "geometry": {"coordinates":[4.4755501747,51.027885437],"type":"Point"}
}