{
  "type": "Feature",
  "properties": {
    "addr:full":"Schoolstraat 4a Wijnegem Antwerpen 2110",
    "addr:housenumber":"4a",
    "addr:postcode":"2110",
    "addr:street":"Schoolstraat",
    "iso:country":"BE",
    "sg:address":"Schoolstraat 4a",
    "sg:city":"Wijnegem",
    "sg:classifiers":[
        {
            "category":"Personal",
            "subcategory":"Barber",
            "type":"Services"
        }
    ],
    "sg:phone":"+32 3 353 22 99",
    "sg:postcode":"2110",
    "sg:province":"Antwerpen",
    "sg:tags":[
        "gentleman",
        "salon",
        "-",
        "hairdressing"
    ],
    "wof:name":"Chris",
    "wof:placetype":"venue"
},
  "geometry": {"coordinates":[4.5214099884,51.2277755737],"type":"Point"}
}