{
  "type": "Feature",
  "properties": {
    "addr:full":"Kerkstraat 59 Dendermonde Oost-Vlaanderen 9200",
    "addr:housenumber":"59",
    "addr:postcode":"9200",
    "addr:street":"Kerkstraat;Oost-Vlaanderen",
    "iso:country":"BE",
    "sg:address":"Kerkstraat 59",
    "sg:city":"Dendermonde",
    "sg:classifiers":[
        {
            "category":"Shopping",
            "subcategory":"Hobbies, Toys, & Games",
            "type":"Retail Goods"
        }
    ],
    "sg:phone":"+32 52 20 34 28",
    "sg:postcode":"9200",
    "sg:province":"Oost-Vlaanderen",
    "sg:tags":[
        "computer",
        "video"
    ],
    "wof:name":"Cybernetic",
    "wof:placetype":"venue"
},
  "geometry": {"coordinates":[4.0956802368,51.0315132141],"type":"Point"}
}