{
  "type": "Feature",
  "properties": {
    "addr:full":"Pont Au Moulin 2 Malmedy (bellevaux-lignueville) Li\u00e8ge 4960",
    "addr:housenumber":"2",
    "addr:postcode":"4960",
    "addr:street":"Pont Au Moulin",
    "iso:country":"BE",
    "sg:address":"Pont Au Moulin 2",
    "sg:city":"Malmedy (bellevaux-lignueville)",
    "sg:classifiers":[
        {
            "category":"Building & Trades",
            "subcategory":"Landscaping Services",
            "type":"Services"
        }
    ],
    "sg:phone":"+32 80 57 01 10",
    "sg:postcode":"4960",
    "sg:province":"Li\u00e8ge",
    "sg:tags":[
        "forestry"
    ],
    "wof:name":"Renier D",
    "wof:placetype":"venue"
},
  "geometry": {"coordinates":[6.0425329208,50.3696174622],"type":"Point"}
}