{
  "type": "Feature",
  "properties": {
    "addr:full":"Fraterstraat 222 Merelbeke Oost-Vlaanderen 9820",
    "addr:housenumber":"222",
    "addr:postcode":"9820",
    "addr:street":"Fraterstraat",
    "iso:country":"BE",
    "sg:address":"Fraterstraat 222",
    "sg:city":"Merelbeke",
    "sg:classifiers":[
        {
            "category":"Professional",
            "subcategory":"Computer Services",
            "type":"Services"
        }
    ],
    "sg:phone":"+32 9 365 72 60",
    "sg:postcode":"9820",
    "sg:province":"Oost-Vlaanderen",
    "sg:tags":[
        "-",
        "processing",
        "data",
        "software"
    ],
    "wof:name":"Teledata Systems Nv",
    "wof:placetype":"venue"
},
  "geometry": {"coordinates":[3.7605500221,51.0046615601],"type":"Point"}
}