{
  "type": "Feature",
  "properties": {
    "addr:full":"Schapenbaan 20 Asse (relegem) Vlaams-Brabant 1731",
    "addr:housenumber":"20",
    "addr:postcode":"1731",
    "addr:street":"Schapenbaan",
    "iso:country":"BE",
    "sg:address":"Schapenbaan 20",
    "sg:city":"Asse (relegem)",
    "sg:classifiers":[
        {
            "category":"Structure",
            "subcategory":"Building",
            "type":"Public Place"
        }
    ],
    "sg:phone":"+32 2 460 38 16",
    "sg:postcode":"1731",
    "sg:province":"Vlaams-Brabant",
    "sg:tags":[
        "door"
    ],
    "wof:name":"Treetex Acoustics Nv",
    "wof:placetype":"venue"
},
  "geometry": {"coordinates":[4.2799139023,50.8928565979],"type":"Point"}
}