{
  "type": "Feature",
  "properties": {
    "addr:full":"Rue Henri Monfort 28b Herve Li\u00e8ge 4650",
    "addr:housenumber":"28b",
    "addr:postcode":"4650",
    "addr:street":"Rue Henri Monfort",
    "iso:country":"BE",
    "sg:address":"Rue Henri Monfort 28b",
    "sg:city":"Herve",
    "sg:orig_category":"Woningbouw",
    "sg:phone":"+32 87 35 33 23",
    "sg:postcode":"4650",
    "sg:province":"Li\u00e8ge",
    "wof:name":"Doneux Philippe",
    "wof:placetype":"venue"
},
  "geometry": {"coordinates":[5.7930240631,50.6071777344],"type":"Point"}
}