{
  "type": "Feature",
  "properties": {
    "iso:country":"BE",
    "sg:address":"Schelkenshof 14",
    "sg:city":"Ranst (broechem)",
    "sg:classifiers":[
        {
            "category":"Professional",
            "subcategory":"Accounting & Tax Preparation",
            "type":"Services"
        }
    ],
    "sg:phone":"+32 3 485 68 56",
    "sg:postcode":"2520",
    "sg:province":"Antwerpen",
    "sg:tags":[
        "bookkeeper"
    ],
    "wof:name":"Acludan Bvba",
    "wof:placetype":"venue"
},
  "geometry": {"coordinates":[4.5981659889,51.180393219],"type":"Point"}
}