{
  "type": "Feature",
  "properties": {
    "iso:country":"BE",
    "sg:address":"Professor Devochtstraat 45",
    "sg:city":"Turnhout",
    "sg:orig_category":"Sportclubs",
    "sg:phone":"+32 14 41 50 06",
    "sg:postcode":"2300",
    "sg:province":"Antwerpen",
    "wof:name":"T.c. Taxandria",
    "wof:placetype":"venue"
},
  "geometry": {"coordinates":[4.9616098404,51.3194694519],"type":"Point"}
}