{
  "type": "Feature",
  "properties": {
    "addr:full":"Batterijstraat 36 De Haan West-Vlaanderen 8420",
    "addr:housenumber":"36",
    "addr:postcode":"8420",
    "addr:street":"Batterijstraat",
    "iso:country":"BE",
    "sg:address":"Batterijstraat 36",
    "sg:city":"De Haan",
    "sg:orig_category":"SMEEDWERK, METAALBEWERKING AND POEDERMETALLURGIE",
    "sg:phone":"+32 59 23 50 51",
    "sg:postcode":"8420",
    "sg:province":"West-Vlaanderen",
    "wof:name":"Vermeire M.",
    "wof:placetype":"venue"
},
  "geometry": {"coordinates":[3.0006270409,51.250667572],"type":"Point"}
}