{
  "type": "Feature",
  "properties": {
    "addr:full":"Rue Du Presbyt\u00c8re 54 Sint-jans-molenbeek/molenbeek-saint-jean Bruxelles-Capitale 1080",
    "addr:housenumber":"54",
    "addr:postcode":"1080",
    "addr:street":"Rue Du Presbyte\u0300Re",
    "iso:country":"BE",
    "sg:address":"Rue Du Presbyt\u00c8re 54",
    "sg:city":"Sint-jans-molenbeek/molenbeek-saint-jean",
    "sg:classifiers":[
        {
            "category":"Cafe",
            "type":"Food & Drink"
        }
    ],
    "sg:phone":"+32 2 410 39 35",
    "sg:postcode":"1080",
    "sg:province":"Bruxelles-Capitale",
    "sg:tags":[
        "caf\u00e9s"
    ],
    "wof:name":"Savas Fotoglou",
    "wof:placetype":"venue"
},
  "geometry": {"coordinates":[4.3375530243,50.857131958],"type":"Point"}
}