{
  "type": "Feature",
  "properties": {
    "iso:country":"BE",
    "sg:address":"Rue Sanson 8",
    "sg:city":"Eghez\u00c9e",
    "sg:orig_category":"Drukkerijen and copyshops",
    "sg:phone":"+32 81 51 28 06",
    "sg:postcode":"5310",
    "sg:province":"Namur",
    "wof:name":"Imprimerie Sanson",
    "wof:placetype":"venue"
},
  "geometry": {"coordinates":[4.8951358795,50.573184967],"type":"Point"}
}