{
  "type": "Feature",
  "properties": {
    "iso:country":"BE",
    "sg:address":"Hameau De Ster 390",
    "sg:city":"Stavelot (francorchamps)",
    "sg:classifiers":[
        {
            "category":"Recreation",
            "subcategory":"Campground",
            "type":"Entertainment"
        }
    ],
    "sg:phone":"+32 87 27 50 99",
    "sg:postcode":"4970",
    "sg:province":"Li\u00e8ge",
    "sg:tags":[
        "site",
        "camping"
    ],
    "wof:name":"Francopole Asbl",
    "wof:placetype":"venue"
},
  "geometry": {"coordinates":[5.9006500244,50.3922386169],"type":"Point"}
}