{
  "type": "Feature",
  "properties": {
    "iso:country":"BE",
    "sg:address":"Turflaan 2",
    "sg:city":"Sint-laureins",
    "sg:classifiers":[
        {
            "category":"Professional",
            "subcategory":"Engineering",
            "type":"Services"
        }
    ],
    "sg:phone":"+32 9 379 09 82",
    "sg:postcode":"9980",
    "sg:province":"Oost-Vlaanderen",
    "sg:tags":[
        "technical",
        "equipment",
        "offices-"
    ],
    "wof:name":"Lanicad-cadburo Bvba",
    "wof:placetype":"venue"
},
  "geometry": {"coordinates":[3.5255138874,51.2395744324],"type":"Point"}
}