{
  "type": "Feature",
  "properties": {
    "iso:country":"BE",
    "sg:address":"Brusselsesteenweg 629",
    "sg:city":"Overijse",
    "sg:classifiers":[
        {
            "category":"Bars & Pubs",
            "type":"Food & Drink"
        }
    ],
    "sg:phone":"+32 2 657 42 86",
    "sg:postcode":"3090",
    "sg:province":"Vlaams-Brabant",
    "sg:tags":[
        "tavern"
    ],
    "wof:name":"Jachthof ('t)",
    "wof:placetype":"venue"
},
  "geometry": {"coordinates":[4.5082998276,50.7829399109],"type":"Point"}
}