{
  "type": "Feature",
  "properties": {
    "iso:country":"BE",
    "sg:address":"Rue De Bray 181",
    "sg:city":"La Louvi\u00e8re (maurage)",
    "sg:classifiers":[
        {
            "category":"Health Services",
            "subcategory":"Health Practitioner",
            "type":"Services"
        }
    ],
    "sg:phone":"+32 64 33 42 57",
    "sg:postcode":"7110",
    "sg:province":"Hainaut",
    "sg:tags":[
        "physiotherapist"
    ],
    "wof:name":"Dumont P",
    "wof:placetype":"venue"
},
  "geometry": {"coordinates":[4.0997700691,50.4453582764],"type":"Point"}
}