{
  "type": "Feature",
  "properties": {
    "addr:full":"Chauss\u00c9e De Louvain 320 Brussel/bruxelles Bruxelles-Capitale 1000",
    "addr:housenumber":"320",
    "addr:postcode":"1000",
    "addr:street":"Chausse\u0301E De Louvain;/",
    "iso:country":"BE",
    "sg:address":"Chauss\u00c9e De Louvain 320",
    "sg:city":"Brussel/bruxelles",
    "sg:orig_category":"M\u00e9decins and sp\u00e9cialistes",
    "sg:phone":"+32 2 734 61 57",
    "sg:postcode":"1000",
    "sg:province":"Bruxelles-Capitale",
    "wof:name":"Daniel Wallaert",
    "wof:placetype":"venue"
},
  "geometry": {"coordinates":[4.3837351799,50.8511772156],"type":"Point"}
}