{
  "type": "Feature",
  "properties": {
    "addr:full":"Klaverheide 199 Brasschaat Antwerpen 2930",
    "addr:housenumber":"199",
    "addr:postcode":"2930",
    "addr:street":"Klaverheide",
    "iso:country":"BE",
    "sg:address":"Klaverheide 199",
    "sg:city":"Brasschaat",
    "sg:classifiers":[
        {
            "category":"Insurance",
            "subcategory":"Life Insurance",
            "type":"Services"
        }
    ],
    "sg:phone":"+32 3 663 41 03",
    "sg:postcode":"2930",
    "sg:province":"Antwerpen",
    "sg:tags":[
        "assurance"
    ],
    "wof:name":"Assuro",
    "wof:placetype":"venue"
},
  "geometry": {"coordinates":[4.495593071,51.3211174011],"type":"Point"}
}