{
  "type": "Feature",
  "properties": {
    "addr:full":"Kasteelstraat 2c Linter (neerlinter) Vlaams-Brabant 3350",
    "addr:housenumber":"2c",
    "addr:postcode":"3350",
    "addr:street":"Kasteelstraat",
    "iso:country":"BE",
    "sg:address":"Kasteelstraat 2c",
    "sg:city":"Linter (neerlinter)",
    "sg:classifiers":[
        {
            "category":"Insurance",
            "subcategory":"Insurance Agent",
            "type":"Services"
        }
    ],
    "sg:phone":"+32 11 78 06 73",
    "sg:postcode":"3350",
    "sg:province":"Vlaams-Brabant",
    "sg:tags":[
        "broker"
    ],
    "wof:name":"Beelen O",
    "wof:placetype":"venue"
},
  "geometry": {"coordinates":[5.0643911362,50.8061676025],"type":"Point"}
}