{
  "type": "Feature",
  "properties": {
    "addr:full":"Rue Des Iguanodons 11c Bernissart Hainaut 7320",
    "addr:housenumber":"11c",
    "addr:postcode":"7320",
    "addr:street":"Rue Des Iguanodons",
    "iso:country":"BE",
    "sg:address":"Rue Des Iguanodons 11c",
    "sg:city":"Bernissart",
    "sg:orig_category":"Travaux de finition and nettoyage de b\u00e2timents",
    "sg:phone":"+32 479 49 20 37",
    "sg:postcode":"7320",
    "sg:province":"Hainaut",
    "wof:name":"Degroote Christophe",
    "wof:placetype":"venue"
},
  "geometry": {"coordinates":[3.6586880684,50.4896316528],"type":"Point"}
}