{
  "type": "Feature",
  "properties": {
    "iso:country":"BE",
    "sg:address":"Gebroeders Tassetstraat 4",
    "sg:city":"Leuven",
    "sg:orig_category":"Paramedische behandelingen",
    "sg:phone":"+32 16 44 50 62",
    "sg:postcode":"3018",
    "sg:province":"Vlaams-Brabant",
    "wof:name":"Court",
    "wof:placetype":"venue"
},
  "geometry": {"coordinates":[4.6941142082,50.9239616394],"type":"Point"}
}