{
  "type": "Feature",
  "properties": {
    "iso:country":"BE",
    "sg:address":"Blommeke 16",
    "sg:city":"Beernem",
    "sg:orig_category":"Agences d'exp\u00e9dition",
    "sg:phone":"+32 50 78 88 66",
    "sg:postcode":"8730",
    "sg:province":"West-Vlaanderen",
    "wof:name":"Fredotrans",
    "wof:placetype":"venue"
},
  "geometry": {"coordinates":[3.3056321144,51.1240882874],"type":"Point"}
}