{
  "type": "Feature",
  "properties": {
    "iso:country":"BE",
    "sg:address":"Wakkenstraat 6",
    "sg:city":"Dentergem (markegem)",
    "sg:classifiers":[
        {
            "category":"Bars & Pubs",
            "type":"Food & Drink"
        }
    ],
    "sg:phone":"+32 51 63 32 73",
    "sg:postcode":"8720",
    "sg:province":"West-Vlaanderen",
    "sg:tags":[
        "tavern"
    ],
    "wof:name":"Harlekijn (de)",
    "wof:placetype":"venue"
},
  "geometry": {"coordinates":[3.4022660255,50.9455604553],"type":"Point"}
}