{
  "type": "Feature",
  "properties": {
    "addr:full":"Winkelomseheide 0 Geel Antwerpen 2440",
    "addr:housenumber":"0",
    "addr:postcode":"2440",
    "addr:street":"Winkelomseheide",
    "iso:country":"BE",
    "sg:address":"Winkelomseheide 0",
    "sg:city":"Geel",
    "sg:classifiers":[
        {
            "category":"Fast Food",
            "type":"Food & Drink"
        }
    ],
    "sg:phone":"+32 14 59 31 09",
    "sg:postcode":"2440",
    "sg:province":"Antwerpen",
    "sg:tags":[
        "\u00c0",
        "restaurants",
        "emporter",
        "restaurant"
    ],
    "wof:name":"Snackbar 't Pleintje",
    "wof:placetype":"venue"
},
  "geometry": {"coordinates":[5.0246391296,51.1194152832],"type":"Point"}
}