{
  "type": "Feature",
  "properties": {
    "addr:full":"Kasteeldreef 2 Roeselare West-Vlaanderen 8800",
    "addr:housenumber":"2",
    "addr:postcode":"8800",
    "addr:street":"Kasteeldreef",
    "iso:country":"BE",
    "sg:address":"Kasteeldreef 2",
    "sg:city":"Roeselare",
    "sg:classifiers":[
        {
            "category":"Banks & Credit Unions",
            "subcategory":"Bank",
            "type":"Services"
        }
    ],
    "sg:phone":"+32 51 20 41 68",
    "sg:postcode":"8800",
    "sg:province":"West-Vlaanderen",
    "wof:name":"Caisse Nationale De, Cr\u00e9dit Professionnel",
    "wof:placetype":"venue"
},
  "geometry": {"coordinates":[3.1294050217,50.9345588684],"type":"Point"}
}