{
  "type": "Feature",
  "properties": {
    "iso:country":"BE",
    "sg:address":"Hoge Bokstraat 55",
    "sg:city":"Sint-niklaas",
    "sg:orig_category":"Artiesten and kunstenaars",
    "sg:phone":"+32 3 776 02 39",
    "sg:postcode":"9111",
    "sg:province":"Oost-Vlaanderen",
    "wof:name":"Raf Coorevits",
    "wof:placetype":"venue"
},
  "geometry": {"coordinates":[4.1138520241,51.1628074646],"type":"Point"}
}