{
  "type": "Feature",
  "properties": {
    "addr:full":"Dubbelhofstraat 19 Sint-niklaas Oost-Vlaanderen 9111",
    "addr:housenumber":"19",
    "addr:postcode":"9111",
    "addr:street":"Dubbelhofstraat",
    "iso:country":"BE",
    "sg:address":"Dubbelhofstraat 19",
    "sg:city":"Sint-niklaas",
    "sg:orig_category":"D\u00e9m\u00e9nagements",
    "sg:phone":"+32 3 772 10 32",
    "sg:postcode":"9111",
    "sg:province":"Oost-Vlaanderen",
    "wof:name":"Traverik",
    "wof:placetype":"venue"
},
  "geometry": {"coordinates":[4.078979969,51.141910553],"type":"Point"}
}