{
  "type": "Feature",
  "properties": {
    "addr:full":"Leuvenselaan 146 Tienen Vlaams-Brabant 3300",
    "addr:housenumber":"146",
    "addr:postcode":"3300",
    "addr:street":"Leuvenselaan",
    "iso:country":"BE",
    "sg:address":"Leuvenselaan 146",
    "sg:city":"Tienen",
    "sg:orig_category":"Apotheken",
    "sg:phone":"+32 16 81 16 64",
    "sg:postcode":"3300",
    "sg:province":"Vlaams-Brabant",
    "wof:name":"Dominique Devadder",
    "wof:placetype":"venue"
},
  "geometry": {"coordinates":[4.92395401,50.8114128113],"type":"Point"}
}