{
  "type": "Feature",
  "properties": {
    "iso:country":"BE",
    "sg:address":"All\u00c9e Verte 99",
    "sg:city":"Brussel/bruxelles",
    "sg:classifiers":[
        {
            "category":"Cafe",
            "type":"Food & Drink"
        }
    ],
    "sg:phone":"+32 2 203 57 53",
    "sg:postcode":"1000",
    "sg:province":"Bruxelles-Capitale",
    "sg:tags":[
        "caf\u00e9s"
    ],
    "wof:name":"Caf\u00c9 Olympos",
    "wof:placetype":"venue"
},
  "geometry": {"coordinates":[4.3599162102,50.8704681396],"type":"Point"}
}