{
  "type": "Feature",
  "properties": {
    "iso:country":"BE",
    "sg:address":"Rue Charles Magnette 5",
    "sg:city":"Li\u00e8ge 1",
    "sg:classifiers":[
        {
            "category":"Wholesale",
            "subcategory":"Music Publishers",
            "type":"Manufacturing & Wholesale Goods"
        }
    ],
    "sg:phone":"+32 4 221 23 75",
    "sg:postcode":"4000",
    "sg:province":"Li\u00e8ge",
    "wof:name":"Musique En Wallonie Asbl",
    "wof:placetype":"venue"
},
  "geometry": {"coordinates":[5.5742478371,50.64087677],"type":"Point"}
}