{
  "type": "Feature",
  "properties": {
    "iso:country":"BE",
    "sg:address":"Oblatenstraat 19",
    "sg:city":"Waregem",
    "sg:classifiers":[
        {
            "category":"Personal",
            "subcategory":"Beauty Salon",
            "type":"Services"
        }
    ],
    "sg:phone":"+32 56 60 05 96",
    "sg:postcode":"8790",
    "sg:province":"West-Vlaanderen",
    "sg:tags":[
        "de",
        "coiffure"
    ],
    "wof:name":"Coiffure Eddy",
    "wof:placetype":"venue"
},
  "geometry": {"coordinates":[3.3994190693,50.8635253906],"type":"Point"}
}