{
  "type": "Feature",
  "properties": {
    "addr:full":"Zuidlaan 220 Zwalm Oost-Vlaanderen 9630",
    "addr:housenumber":"220",
    "addr:postcode":"9630",
    "addr:street":"Zuidlaan;Oost-Vlaanderen",
    "iso:country":"BE",
    "sg:address":"Zuidlaan 220",
    "sg:city":"Zwalm",
    "sg:orig_category":"Persagentschappen",
    "sg:phone":"+32 55 49 53 11",
    "sg:postcode":"9630",
    "sg:province":"Oost-Vlaanderen",
    "wof:name":"Guido Swillen",
    "wof:placetype":"venue"
},
  "geometry": {"coordinates":[3.7340230942,50.8645324707],"type":"Point"}
}