{
  "type": "Feature",
  "properties": {
    "addr:full":"Rue Sous L'haye 51 La Louviere Hainaut 7100",
    "addr:housenumber":"51",
    "addr:postcode":"7100",
    "addr:street":"Rue Sous L'Haye",
    "iso:country":"BE",
    "sg:address":"Rue Sous L'haye 51",
    "sg:city":"La Louviere",
    "sg:orig_category":"Enseignement maternel and primaire",
    "sg:phone":"+32 64 22 76 19",
    "sg:postcode":"7100",
    "sg:province":"Hainaut",
    "wof:name":"Ecole Fond. Communale",
    "wof:placetype":"venue"
},
  "geometry": {"coordinates":[4.2242650986,50.4765777588],"type":"Point"}
}