{
  "type": "Feature",
  "properties": {
    "iso:country":"BE",
    "sg:address":"Avenue Des Marteleurs 12",
    "sg:city":"Seraing",
    "sg:orig_category":"Gespecialiseerde residenti\u00eble bouw",
    "sg:phone":"+32 4 336 00 02",
    "sg:postcode":"4100",
    "sg:province":"Li\u00e8ge",
    "wof:name":"Fe. Fontaine",
    "wof:placetype":"venue"
},
  "geometry": {"coordinates":[5.4888768196,50.5841903687],"type":"Point"}
}