{
  "type": "Feature",
  "properties": {
    "iso:country":"BE",
    "sg:address":"Coupure Links 103",
    "sg:city":"Gent",
    "sg:orig_category":"S\u00e9curit\u00e9 sociale",
    "sg:phone":"+32 9 225 13 02",
    "sg:postcode":"9000",
    "sg:province":"Oost-Vlaanderen",
    "wof:name":"Vlaams Neutraal Ziekenf.",
    "wof:placetype":"venue"
},
  "geometry": {"coordinates":[3.717056036,51.0464515686],"type":"Point"}
}