{
  "type": "Feature",
  "properties": {
    "addr:full":"Bouwelsesteenweg 140 Nijlen Antwerpen 2560",
    "addr:housenumber":"140",
    "addr:postcode":"2560",
    "addr:street":"Bouwelsesteenweg",
    "iso:country":"BE",
    "sg:address":"Bouwelsesteenweg 140",
    "sg:city":"Nijlen",
    "sg:orig_category":"Supermarch\u00e9s",
    "sg:postcode":"2560",
    "sg:province":"Antwerpen",
    "wof:name":"Aldi",
    "wof:placetype":"venue"
},
  "geometry": {"coordinates":[4.6862368584,51.1655349731],"type":"Point"}
}