{
  "type": "Feature",
  "properties": {
    "iso:country":"BE",
    "sg:address":"Eug. De Grootelaan 32",
    "sg:city":"Houthulst",
    "sg:classifiers":[
        {
            "category":"Bars & Pubs",
            "type":"Food & Drink"
        }
    ],
    "sg:phone":"+32 51 70 31 06",
    "sg:postcode":"8650",
    "sg:province":"West-Vlaanderen",
    "wof:name":"Dambert ('t)",
    "wof:placetype":"venue"
},
  "geometry": {"coordinates":[2.951695919,50.9759979248],"type":"Point"}
}