{
  "type": "Feature",
  "properties": {
    "iso:country":"BE",
    "sg:address":"Place Jean-baptiste Guisset 2",
    "sg:city":"Renaix",
    "sg:classifiers":[
        {
            "category":"Banks & Credit Unions",
            "subcategory":"Investment Brokerage",
            "type":"Services"
        }
    ],
    "sg:phone":"+32 55 20 72 67",
    "sg:postcode":"9600",
    "sg:province":"Oost-Vlaanderen",
    "sg:tags":[
        "printing",
        "-"
    ],
    "wof:name":"Maes Philippe-phimtec",
    "wof:placetype":"venue"
},
  "geometry": {"coordinates":[3.6004920006,50.7444763184],"type":"Point"}
}