{
  "type": "Feature",
  "properties": {
    "iso:country":"BE",
    "sg:address":"Grote Steenweg 467",
    "sg:city":"Linter",
    "sg:orig_category":"Catering and organisation de f\u00eates",
    "sg:phone":"+32 11 78 22 95",
    "sg:postcode":"3350",
    "sg:province":"Vlaams-Brabant",
    "wof:name":"Winnen Kok-traiteur",
    "wof:placetype":"venue"
},
  "geometry": {"coordinates":[5.0604419708,50.8524284363],"type":"Point"}
}