{
  "type": "Feature",
  "properties": {
    "iso:country":"BE",
    "sg:address":"Uilekot 15",
    "sg:city":"Lubbeek",
    "sg:orig_category":"Producteurs de fruits",
    "sg:phone":"+32 16 63 33 93",
    "sg:postcode":"3210",
    "sg:province":"Vlaams-Brabant",
    "wof:name":"Marcel Vangilbergen",
    "wof:placetype":"venue"
},
  "geometry": {"coordinates":[4.8360309601,50.8737182617],"type":"Point"}
}