{
  "type": "Feature",
  "properties": {
    "iso:country":"BE",
    "sg:address":"Grote Baan 303",
    "sg:city":"Drogenbos",
    "sg:orig_category":"Kapsalons",
    "sg:phone":"+32 2 331 61 69",
    "sg:postcode":"1620",
    "sg:province":"Vlaams-Brabant",
    "wof:name":"Wendy",
    "wof:placetype":"venue"
},
  "geometry": {"coordinates":[4.3172898293,50.7870788574],"type":"Point"}
}