{
  "type": "Feature",
  "properties": {
    "iso:country":"BE",
    "sg:address":"Holestraat 71",
    "sg:city":"Borsbeke",
    "sg:classifiers":[
        {
            "category":"Professional",
            "subcategory":"Computer Services",
            "type":"Services"
        }
    ],
    "sg:phone":"+32 495 31 52 64",
    "sg:postcode":"9552",
    "sg:province":"Oost-Vlaanderen",
    "sg:tags":[
        "informaticaconsule",
        "informatica-activiteiten",
        "siemens",
        "diverse",
        "computerapparatuur",
        "fujitsu"
    ],
    "wof:name":"Comprosoft Bvba",
    "wof:placetype":"venue"
},
  "geometry": {"coordinates":[3.8923199177,50.9047431946],"type":"Point"}
}