{
  "type": "Feature",
  "properties": {
    "addr:full":"Putsebaan 2 Keerbergen Vlaams-Brabant 3140",
    "addr:housenumber":"2",
    "addr:postcode":"3140",
    "addr:street":"Putsebaan",
    "iso:country":"BE",
    "sg:address":"Putsebaan 2",
    "sg:city":"Keerbergen",
    "sg:orig_category":"Banques and organismes de cr\u00e9dit",
    "sg:phone":"+32 15 51 65 97",
    "sg:postcode":"3140",
    "sg:province":"Vlaams-Brabant",
    "wof:name":"Bacob",
    "wof:placetype":"venue"
},
  "geometry": {"coordinates":[4.6279478073,51.0044708252],"type":"Point"}
}