{
  "type": "Feature",
  "properties": {
    "addr:full":"Bierstal 31 Lovendegem Oost-Vlaanderen 9920",
    "addr:housenumber":"31",
    "addr:postcode":"9920",
    "addr:street":"Bierstal",
    "iso:country":"BE",
    "sg:address":"Bierstal 31",
    "sg:city":"Lovendegem",
    "sg:orig_category":"Assurances. Evaluation and estimation de biens immobiliers",
    "sg:phone":"+32 9 372 90 84",
    "sg:postcode":"9920",
    "sg:province":"Oost-Vlaanderen",
    "wof:name":"Edwin Verbeke",
    "wof:placetype":"venue"
},
  "geometry": {"coordinates":[3.6431200504,51.0950698853],"type":"Point"}
}