{
  "type": "Feature",
  "properties": {
    "iso:country":"BE",
    "sg:address":"Tijmlaan 16",
    "sg:city":"Waregem",
    "sg:classifiers":[
        {
            "category":"Professional",
            "subcategory":"Advertising",
            "type":"Services"
        }
    ],
    "sg:phone":"+32 56 60 34 17",
    "sg:postcode":"8790",
    "sg:province":"West-Vlaanderen",
    "sg:tags":[
        "clothes"
    ],
    "wof:name":"Liratex Nv",
    "wof:placetype":"venue"
},
  "geometry": {"coordinates":[3.4150500298,50.8937988281],"type":"Point"}
}