{
  "type": "Feature",
  "properties": {
    "addr:full":"Lakensestraat 2 Grimbergen Vlaams-Brabant 1853",
    "addr:housenumber":"2",
    "addr:postcode":"1853",
    "addr:street":"Lakensestraat",
    "iso:country":"BE",
    "sg:address":"Lakensestraat 2",
    "sg:city":"Grimbergen",
    "sg:orig_category":"RESTAURANTS: RESTAURANTS LIVRAISON \u00c0 DOMICILE",
    "sg:phone":"+32 2 267 75 80",
    "sg:postcode":"1853",
    "sg:province":"Vlaams-Brabant",
    "wof:name":"Toast",
    "wof:placetype":"venue"
},
  "geometry": {"coordinates":[4.3526501656,50.9068489075],"type":"Point"}
}