{
  "type": "Feature",
  "properties": {
    "iso:country":"BE",
    "sg:address":"Rue D'oth\u00e9e 73",
    "sg:city":"Ans",
    "sg:classifiers":[
        {
            "category":"Military Area",
            "subcategory":"Air Force Base",
            "type":"Public Place"
        }
    ],
    "sg:phone":"+32 4 263 73 73",
    "sg:postcode":"4430",
    "sg:province":"Li\u00e8ge",
    "sg:tags":[
        "fire",
        "protection"
    ],
    "wof:name":"Collignon & Fils",
    "wof:placetype":"venue"
},
  "geometry": {"coordinates":[5.532201767,50.6647911072],"type":"Point"}
}