{
  "type": "Feature",
  "properties": {
    "iso:country":"BE",
    "sg:address":"Schotelstraat 69",
    "sg:city":"Hasselt",
    "sg:orig_category":"Herstellingen and onderhoud van auto's",
    "sg:phone":"+32 11 25 49 55",
    "sg:postcode":"3511",
    "sg:province":"Limburg",
    "wof:name":"P.m.p. Cars",
    "wof:placetype":"venue"
},
  "geometry": {"coordinates":[5.2856907845,50.977722168],"type":"Point"}
}