{
  "type": "Feature",
  "properties": {
    "iso:country":"BE",
    "sg:address":"Heirstraat 8",
    "sg:city":"Aalter (lotenhulle)",
    "sg:classifiers":[
        {
            "category":"Professional",
            "subcategory":"Art Services",
            "type":"Services"
        }
    ],
    "sg:phone":"+32 51 68 91 81",
    "sg:postcode":"9880",
    "sg:province":"Oost-Vlaanderen",
    "sg:tags":[
        "photographer"
    ],
    "wof:name":"Artifo Fotografie Van Oyen I",
    "wof:placetype":"venue"
},
  "geometry": {"coordinates":[3.4744949341,51.1095848083],"type":"Point"}
}