{
  "type": "Feature",
  "properties": {
    "addr:full":"Dorp Oost 88 Zwijndrecht Antwerpen 2070",
    "addr:housenumber":"88",
    "addr:postcode":"2070",
    "addr:street":"Dorp Oost",
    "iso:country":"BE",
    "sg:address":"Dorp Oost 88",
    "sg:city":"Zwijndrecht",
    "sg:orig_category":"Foto-uitrusting Fotografen and fotostudio's Herstellingen and onderhoud van auto's",
    "sg:phone":"+32 3 252 75 71",
    "sg:postcode":"2070",
    "sg:province":"Antwerpen",
    "wof:name":"Hugo Heynen",
    "wof:placetype":"venue"
},
  "geometry": {"coordinates":[4.3291101456,51.2192001343],"type":"Point"}
}