{
  "type": "Feature",
  "properties": {
    "addr:full":"Kasteelstraat 1 Dilbeek Vlaams-Brabant 1700",
    "addr:housenumber":"1",
    "addr:postcode":"1700",
    "addr:street":"Kasteelstraat",
    "iso:country":"BE",
    "sg:address":"Kasteelstraat 1",
    "sg:city":"Dilbeek",
    "sg:classifiers":[
        {
            "category":"Insurance",
            "subcategory":"Insurance Agent",
            "type":"Services"
        }
    ],
    "sg:phone":"+32 2 567 77 86",
    "sg:postcode":"1700",
    "sg:province":"Vlaams-Brabant",
    "sg:tags":[
        "broker"
    ],
    "wof:name":"Wauterecht M",
    "wof:placetype":"venue"
},
  "geometry": {"coordinates":[4.2640318871,50.8451423645],"type":"Point"}
}