{
  "type": "Feature",
  "properties": {
    "addr:full":"Champs Elys\u00c9es 12 Ciney Namur 5590",
    "addr:housenumber":"12",
    "addr:postcode":"5590",
    "iso:country":"BE",
    "sg:address":"Champs Elys\u00c9es 12",
    "sg:city":"Ciney",
    "sg:orig_category":"Eleveurs de bovins",
    "sg:phone":"+32 83 21 29 48",
    "sg:postcode":"5590",
    "sg:province":"Namur",
    "wof:name":"Centre S\u00c9lection Bovine",
    "wof:placetype":"venue"
},
  "geometry": {"coordinates":[5.0996251106,50.3148384094],"type":"Point"}
}