{
  "type": "Feature",
  "properties": {
    "iso:country":"BE",
    "sg:address":"Kattendansstraat 79",
    "sg:city":"Hasselt",
    "sg:orig_category":"Herstelling leer and schoeisel Kleding",
    "sg:phone":"+32 11 27 42 33",
    "sg:postcode":"3500",
    "sg:province":"Limburg",
    "wof:name":"Monica Bolinius",
    "wof:placetype":"venue"
},
  "geometry": {"coordinates":[5.3319301605,50.8996963501],"type":"Point"}
}