{
  "type": "Feature",
  "properties": {
    "iso:country":"BE",
    "sg:address":"Gewerbezone Kaiserbarack 2",
    "sg:city":"Amel/ambleve",
    "sg:orig_category":"Herstellingen and onderhoud van auto's Voertuigen",
    "sg:phone":"+32 80 57 09 20",
    "sg:postcode":"4770",
    "sg:province":"Li\u00e8ge",
    "wof:name":"Truck Center Jost",
    "wof:placetype":"venue"
},
  "geometry": {"coordinates":[6.1876211166,50.3251914978],"type":"Point"}
}