{
  "type": "Feature",
  "properties": {
    "addr:full":"Doornpannestraat 1 Koksijde West-Vlaanderen 8670",
    "addr:housenumber":"1",
    "addr:postcode":"8670",
    "addr:street":"Doornpannestraat",
    "iso:country":"BE",
    "sg:address":"Doornpannestraat 1",
    "sg:city":"Koksijde",
    "sg:orig_category":"Plomberie, chauffage and installations sanitaires",
    "sg:phone":"+32 58 52 16 17",
    "sg:postcode":"8670",
    "sg:province":"West-Vlaanderen",
    "wof:name":"Hauweele Ides",
    "wof:placetype":"venue"
},
  "geometry": {"coordinates":[2.6601641178,51.122592926],"type":"Point"}
}