{
  "type": "Feature",
  "properties": {
    "iso:country":"BE",
    "sg:address":"Veldstraat 109",
    "sg:city":"Harelbeke",
    "sg:orig_category":"Isolatiewerk",
    "sg:phone":"+32 56 70 21 77",
    "sg:postcode":"8530",
    "sg:province":"West-Vlaanderen",
    "wof:name":"Isoschol",
    "wof:placetype":"venue"
},
  "geometry": {"coordinates":[3.3124918938,50.8521118164],"type":"Point"}
}