{
  "type": "Feature",
  "properties": {
    "iso:country":"BE",
    "sg:address":"Smidstraat 17",
    "sg:city":"Gingelom",
    "sg:orig_category":"Fruitteelt",
    "sg:phone":"+32 11 48 45 17",
    "sg:postcode":"3891",
    "sg:province":"Limburg",
    "wof:name":"Danny Vranken",
    "wof:placetype":"venue"
},
  "geometry": {"coordinates":[5.2163109779,50.761100769],"type":"Point"}
}