{
  "type": "Feature",
  "properties": {
    "iso:country":"BE",
    "sg:address":"Terschurenstraat 50",
    "sg:city":"Tervuren",
    "sg:orig_category":"Producteurs de fruits",
    "sg:phone":"+32 2 767 98 54",
    "sg:postcode":"3080",
    "sg:province":"Vlaams-Brabant",
    "wof:name":"Charles Wauters",
    "wof:placetype":"venue"
},
  "geometry": {"coordinates":[4.537124157,50.8089904785],"type":"Point"}
}