{
  "type": "Feature",
  "properties": {
    "addr:full":"Amelbergastraat 29 Zandhoven Antwerpen 2240",
    "addr:housenumber":"29",
    "addr:postcode":"2240",
    "addr:street":"Amelbergastraat",
    "iso:country":"BE",
    "sg:address":"Amelbergastraat 29",
    "sg:city":"Zandhoven",
    "sg:orig_category":"Banken and kredietinstellingen",
    "sg:phone":"+32 3 484 46 19",
    "sg:postcode":"2240",
    "sg:province":"Antwerpen",
    "wof:name":"Bacob",
    "wof:placetype":"venue"
},
  "geometry": {"coordinates":[4.6626791954,51.2162780762],"type":"Point"}
}