{
  "type": "Feature",
  "properties": {
    "addr:full":"Noorderlaan 208 Antwerpen Antwerpen 2030",
    "addr:housenumber":"208",
    "addr:postcode":"2030",
    "addr:street":"Noorderlaan",
    "iso:country":"BE",
    "sg:address":"Noorderlaan 208",
    "sg:city":"Antwerpen",
    "sg:orig_category":"Apotheken",
    "sg:phone":"+32 3 541 18 70",
    "sg:postcode":"2030",
    "sg:province":"Antwerpen",
    "wof:name":"Multipharma",
    "wof:placetype":"venue"
},
  "geometry": {"coordinates":[4.4204850197,51.255405426],"type":"Point"}
}