{
  "type": "Feature",
  "properties": {
    "iso:country":"BE",
    "sg:address":"Noorderlaan 208",
    "sg:city":"Antwerpen",
    "sg:orig_category":"Apotheken",
    "sg:phone":"+32 3 541 18 70",
    "sg:postcode":"2030",
    "sg:province":"Antwerpen",
    "wof:name":"Multipharma",
    "wof:placetype":"venue"
},
  "geometry": {"coordinates":[4.4204850197,51.255405426],"type":"Point"}
}