{
  "type": "Feature",
  "properties": {
    "iso:country":"BE",
    "sg:address":"Sint-damiaanstraat 85",
    "sg:city":"Wommelgem",
    "sg:orig_category":"Installation \u00e9lectrique r\u00e9sidentielle",
    "sg:phone":"+32 3 353 16 92",
    "sg:postcode":"2160",
    "sg:province":"Antwerpen",
    "wof:name":"Gopro",
    "wof:placetype":"venue"
},
  "geometry": {"coordinates":[4.5206627846,51.2005081177],"type":"Point"}
}