{
  "type": "Feature",
  "properties": {
    "iso:country":"BE",
    "sg:address":"Ry Del Praile 87",
    "sg:city":"Walcourt",
    "sg:classifiers":[
        {
            "category":"Arena",
            "subcategory":"Sports Club",
            "type":"Entertainment"
        }
    ],
    "sg:phone":"+32 71 65 00 65",
    "sg:postcode":"5651",
    "sg:province":"Namur",
    "sg:tags":[
        "terrain",
        "hors",
        "de",
        "installation",
        "sportifs"
    ],
    "wof:name":"F.c. Somzee",
    "wof:placetype":"venue"
},
  "geometry": {"coordinates":[4.4262080193,50.2824401855],"type":"Point"}
}