{
  "type": "Feature",
  "properties": {
    "addr:full":"Delportestraat 55 Tienen Vlaams-Brabant 3300",
    "addr:housenumber":"55",
    "addr:postcode":"3300",
    "addr:street":"Delportestraat",
    "iso:country":"BE",
    "sg:address":"Delportestraat 55",
    "sg:city":"Tienen",
    "sg:orig_category":"Advocaten and juridische adviseurs",
    "sg:phone":"+32 16 82 06 85",
    "sg:postcode":"3300",
    "sg:province":"Vlaams-Brabant",
    "wof:name":"Kris Fourie",
    "wof:placetype":"venue"
},
  "geometry": {"coordinates":[4.9319138527,50.8087387085],"type":"Point"}
}