{
  "type": "Feature",
  "properties": {
    "addr:full":"Tervuursesteenweg 38 Zemst Vlaams-Brabant 1981",
    "addr:housenumber":"38",
    "addr:postcode":"1981",
    "addr:street":"Tervuursesteenweg;Vlaams-Brabant",
    "iso:country":"BE",
    "sg:address":"Tervuursesteenweg 38",
    "sg:city":"Zemst",
    "sg:classifiers":[
        {
            "category":"Food & Beverages",
            "subcategory":"Fruits & Vegetables",
            "type":"Retail Goods"
        }
    ],
    "sg:phone":"+32 15 42 16 57",
    "sg:postcode":"1981",
    "sg:province":"Vlaams-Brabant",
    "sg:tags":[
        "groenten"
    ],
    "wof:name":"De Werfheide",
    "wof:placetype":"venue"
},
  "geometry": {"coordinates":[4.4885430336,50.9971733093],"type":"Point"}
}