{
  "type": "Feature",
  "properties": {
    "iso:country":"BE",
    "sg:address":"Montagne Sainte-walburge 257",
    "sg:city":"Li\u00e8ge 1",
    "sg:classifiers":[
        {
            "category":"Real Estate",
            "subcategory":"Architect",
            "type":"Services"
        }
    ],
    "sg:phone":"+32 4 224 24 48",
    "sg:postcode":"4000",
    "sg:province":"Li\u00e8ge",
    "wof:name":"Lismonde L",
    "wof:placetype":"venue"
},
  "geometry": {"coordinates":[5.5732221603,50.6533126831],"type":"Point"}
}