{
  "type": "Feature",
  "properties": {
    "iso:country":"BE",
    "sg:address":"Vlaanderenstraat 17",
    "sg:city":"Brussel/bruxelles",
    "sg:orig_category":"Slagers",
    "sg:phone":"+32 2 512 15 93",
    "sg:postcode":"1000",
    "sg:province":"Bruxelles-Capitale",
    "wof:name":"Fra\u00dclein Schmitt",
    "wof:placetype":"venue"
},
  "geometry": {"coordinates":[4.3513898849,50.8584594727],"type":"Point"}
}