{
  "type": "Feature",
  "properties": {
    "addr:full":"Dieleghemse Steenweg 56 Jette Bruxelles-Capitale 1090",
    "addr:housenumber":"56",
    "addr:postcode":"1090",
    "addr:street":"Dieleghemse Steenweg",
    "iso:country":"BE",
    "sg:address":"Dieleghemse Steenweg 56",
    "sg:city":"Jette",
    "sg:orig_category":"Plaatsen van vloer- and muurbekleding Schilders",
    "sg:phone":"+32 2 478 93 64",
    "sg:postcode":"1090",
    "sg:province":"Bruxelles-Capitale",
    "wof:name":"Stand-expo",
    "wof:placetype":"venue"
},
  "geometry": {"coordinates":[4.3204350471,50.8831596375],"type":"Point"}
}