{
  "type": "Feature",
  "properties": {
    "addr:full":"Rue Craesborn 43 Dalhem Li\u00e8ge 4608",
    "addr:housenumber":"43",
    "addr:postcode":"4608",
    "addr:street":"Rue Craesborn",
    "iso:country":"BE",
    "sg:address":"Rue Craesborn 43",
    "sg:city":"Dalhem",
    "sg:classifiers":[
        {
            "category":"Food & Beverages",
            "subcategory":"Fruits & Vegetables",
            "type":"Retail Goods"
        }
    ],
    "sg:phone":"+32 4 376 63 88",
    "sg:postcode":"4608",
    "sg:province":"Li\u00e8ge",
    "sg:tags":[
        "l\u00e9gumes",
        "gr"
    ],
    "wof:name":"Armand Spits",
    "wof:placetype":"venue"
},
  "geometry": {"coordinates":[5.7779669762,50.7188148499],"type":"Point"}
}