{
  "type": "Feature",
  "properties": {
    "iso:country":"BE",
    "sg:address":"Rue Saint-georges 2",
    "sg:city":"Couvin",
    "sg:orig_category":"Artsen and specialisten",
    "sg:phone":"+32 60 34 59 46",
    "sg:postcode":"5660",
    "sg:province":"Namur",
    "wof:name":"J. Courty",
    "wof:placetype":"venue"
},
  "geometry": {"coordinates":[4.4236698151,50.0370063782],"type":"Point"}
}