{
  "type": "Feature",
  "properties": {
    "iso:country":"BE",
    "sg:address":"Anton Philipsweg 2",
    "sg:city":"Lommel",
    "sg:classifiers":[
        {
            "category":"Government",
            "subcategory":"Post Office",
            "type":"Public Place"
        }
    ],
    "sg:phone":"+32 11 55 06 13",
    "sg:postcode":"3920",
    "sg:province":"Limburg",
    "sg:tags":[
        "spare",
        "television",
        "set",
        "radio",
        "part"
    ],
    "wof:name":"Matino Metals Nv",
    "wof:placetype":"venue"
},
  "geometry": {"coordinates":[5.2916197777,51.2163200378],"type":"Point"}
}