{
  "type": "Feature",
  "properties": {
    "addr:full":"Erasmuslaan 30 Hasselt Limburg 3500",
    "addr:housenumber":"30",
    "addr:postcode":"3500",
    "addr:street":"Erasmuslaan",
    "iso:country":"BE",
    "sg:address":"Erasmuslaan 30",
    "sg:city":"Hasselt",
    "sg:orig_category":"Decoratiestoffen and buitenhuistextiel Fab Diverse producten Gh Fantasieartikelen Sport- and kampeer",
    "sg:phone":"+32 11 21 21 20",
    "sg:postcode":"3500",
    "sg:province":"Limburg",
    "wof:name":"Anima Carlo",
    "wof:placetype":"venue"
},
  "geometry": {"coordinates":[5.3541908264,50.9491615295],"type":"Point"}
}