{
  "type": "Feature",
  "properties": {
    "iso:country":"BE",
    "sg:address":"Ledebergstraat 89",
    "sg:city":"Zottegem",
    "sg:orig_category":"HUISBRANDOLIE Schoonmaakbedrijven and ongediertebestrijding",
    "sg:phone":"+32 9 360 58 99",
    "sg:postcode":"9620",
    "sg:province":"Oost-Vlaanderen",
    "wof:name":"Jonny Goessens",
    "wof:placetype":"venue"
},
  "geometry": {"coordinates":[3.8039729595,50.8669395447],"type":"Point"}
}