{
  "type": "Feature",
  "properties": {
    "iso:country":"BE",
    "sg:address":"Rue Fran\u00e7ois Libert 10",
    "sg:city":"Waterloo",
    "sg:classifiers":[
        {
            "category":"Shopping",
            "subcategory":"Gifts & Souvenirs",
            "type":"Retail Goods"
        }
    ],
    "sg:phone":"+32 2 353 25 26",
    "sg:postcode":"1410",
    "sg:province":"Brabant Wallon",
    "sg:tags":[
        "-"
    ],
    "wof:name":"Flamant-mardaga Eric",
    "wof:placetype":"venue"
},
  "geometry": {"coordinates":[4.3961100578,50.7174530029],"type":"Point"}
}