{
  "type": "Feature",
  "properties": {
    "iso:country":"BE",
    "sg:address":"Onderstraat 15",
    "sg:city":"Hoeselt",
    "sg:orig_category":"Imprimeries and copyshops",
    "sg:phone":"+32 12 23 55 73",
    "sg:postcode":"3730",
    "sg:province":"Limburg",
    "wof:name":"Drukkerij Jansen",
    "wof:placetype":"venue"
},
  "geometry": {"coordinates":[5.4778671265,50.8352165222],"type":"Point"}
}