{
  "type": "Feature",
  "properties": {
    "addr:full":"Lebeaustraat 33 Brussel/bruxelles Bruxelles-Capitale 1000",
    "addr:housenumber":"33",
    "addr:postcode":"1000",
    "addr:street":"Lebeaustraat;/",
    "iso:country":"BE",
    "sg:address":"Lebeaustraat 33",
    "sg:city":"Brussel/bruxelles",
    "sg:orig_category":"Warenhuizen",
    "sg:phone":"+32 2 512 62 42",
    "sg:postcode":"1000",
    "sg:province":"Bruxelles-Capitale",
    "wof:name":"Artimo",
    "wof:placetype":"venue"
},
  "geometry": {"coordinates":[4.3540167809,50.8425598145],"type":"Point"}
}