{
  "type": "Feature",
  "properties": {
    "iso:country":"BE",
    "sg:address":"Buiten Singel 50",
    "sg:city":"Lommel",
    "sg:classifiers":[
        {
            "category":"Fast Food",
            "type":"Food & Drink"
        }
    ],
    "sg:phone":"+32 11 55 29 80",
    "sg:postcode":"3920",
    "sg:province":"Limburg",
    "sg:tags":[
        "\u00c0",
        "emporter",
        "restaurants"
    ],
    "wof:name":"Mcdonald's",
    "wof:placetype":"venue"
},
  "geometry": {"coordinates":[5.3154859543,51.2217597961],"type":"Point"}
}