{
  "type": "Feature",
  "properties": {
    "iso:country":"BE",
    "sg:address":"Rue De Merckhof 20",
    "sg:city":"Aubel",
    "sg:classifiers":[
        {
            "category":"Real Estate",
            "subcategory":"Architect",
            "type":"Services"
        }
    ],
    "sg:phone":"+32 87 68 78 77",
    "sg:postcode":"4880",
    "sg:province":"Li\u00e8ge",
    "wof:name":"Piret M",
    "wof:placetype":"venue"
},
  "geometry": {"coordinates":[5.8674879074,50.7030792236],"type":"Point"}
}