{
  "type": "Feature",
  "properties": {
    "addr:full":"Oudenaardsestraat 16 Geraardsbergen Oost-Vlaanderen 9500",
    "addr:housenumber":"16",
    "addr:postcode":"9500",
    "addr:street":"Oudenaardsestraat",
    "iso:country":"BE",
    "sg:address":"Oudenaardsestraat 16",
    "sg:city":"Geraardsbergen",
    "sg:orig_category":"Baby- and kinderkleding",
    "sg:phone":"+32 54 41 45 03",
    "sg:postcode":"9500",
    "sg:province":"Oost-Vlaanderen",
    "wof:name":"De Padt - Meert",
    "wof:placetype":"venue"
},
  "geometry": {"coordinates":[3.8754119873,50.7716674805],"type":"Point"}
}