{
  "type": "Feature",
  "properties": {
    "iso:country":"BE",
    "sg:address":"Rue Du Goza 6",
    "sg:city":"Aywaille",
    "sg:orig_category":"Quincailleries. Plomberie, chauffage and installations sanitaires. Charpentes and couvertures. R\u00e9par",
    "sg:phone":"+32 4 384 61 46",
    "sg:postcode":"4920",
    "sg:province":"Li\u00e8ge",
    "wof:name":"Henri Leonard Et Fils",
    "wof:placetype":"venue"
},
  "geometry": {"coordinates":[5.6782069206,50.4738540649],"type":"Point"}
}