{
  "type": "Feature",
  "properties": {
    "addr:full":"Winkelstraat 34 Zwevegem West-Vlaanderen 8550",
    "addr:housenumber":"34",
    "addr:postcode":"8550",
    "addr:street":"Winkelstraat",
    "iso:country":"BE",
    "sg:address":"Winkelstraat 34",
    "sg:city":"Zwevegem",
    "sg:classifiers":[
        {
            "category":"Personal",
            "subcategory":"Beauty Salon",
            "type":"Services"
        }
    ],
    "sg:phone":"+32 56 75 41 16",
    "sg:postcode":"8550",
    "sg:province":"West-Vlaanderen",
    "sg:tags":[
        "de",
        "coiffure"
    ],
    "wof:name":"Nancy",
    "wof:placetype":"venue"
},
  "geometry": {"coordinates":[3.3207960129,50.8095550537],"type":"Point"}
}