{
  "type": "Feature",
  "properties": {
    "addr:full":"Vuldersstraat 88 Brugge West-Vlaanderen 8000",
    "addr:housenumber":"88",
    "addr:postcode":"8000",
    "addr:street":"Vuldersstraat",
    "iso:country":"BE",
    "sg:address":"Vuldersstraat 88",
    "sg:city":"Brugge",
    "sg:classifiers":[
        {
            "category":"Real Estate",
            "subcategory":"Real Estate Services",
            "type":"Services"
        }
    ],
    "sg:phone":"+32 50 44 49 49",
    "sg:postcode":"8000",
    "sg:province":"West-Vlaanderen",
    "wof:name":"Kleysinvest",
    "wof:placetype":"venue"
},
  "geometry": {"coordinates":[3.2382819653,51.2090454102],"type":"Point"}
}