{
  "type": "Feature",
  "properties": {
    "addr:full":"Honsfeld 29 B\u00dcllingen/bullange Li\u00e8ge 4760",
    "addr:housenumber":"29",
    "addr:postcode":"4760",
    "addr:street":"Honsfeld",
    "iso:country":"BE",
    "sg:address":"Honsfeld 29",
    "sg:city":"B\u00dcllingen/bullange",
    "sg:classifiers":[
        {
            "category":"Cafe",
            "type":"Food & Drink"
        }
    ],
    "sg:phone":"+32 80 64 71 40",
    "sg:postcode":"4760",
    "sg:province":"Li\u00e8ge",
    "sg:tags":[
        "caf\u00e9s"
    ],
    "wof:name":"Magnzy Caf\u00c9",
    "wof:placetype":"venue"
},
  "geometry": {"coordinates":[6.2842960358,50.3823547363],"type":"Point"}
}