{
  "type": "Feature",
  "properties": {
    "addr:full":"Rue Grand Route 566 Beyne-heusay (groot) Li\u00e8ge 4610",
    "addr:postcode":"4610",
    "addr:street":"Rue Grand Route 566;Groot Lie\u0300Ge",
    "iso:country":"BE",
    "sg:address":"Rue Grand Route 566",
    "sg:city":"Beyne-heusay (groot)",
    "sg:orig_category":"Airconditioning and ventilatie Loodgieterij, verwarming and sanitaire installaties",
    "sg:phone":"+32 4 355 00 16",
    "sg:postcode":"4610",
    "sg:province":"Li\u00e8ge",
    "wof:name":"Creffier B\u00c2timent",
    "wof:placetype":"venue"
},
  "geometry": {"coordinates":[5.664285183,50.6182556152],"type":"Point"}
}