{
  "type": "Feature",
  "properties": {
    "iso:country":"BE",
    "sg:address":"Grand'place 32",
    "sg:city":"Perwez",
    "sg:orig_category":"Zalen voor culturele evenementen",
    "sg:phone":"+32 81 65 61 04",
    "sg:postcode":"1360",
    "sg:province":"Brabant Wallon",
    "wof:name":"Foyer Culturel",
    "wof:placetype":"venue"
},
  "geometry": {"coordinates":[4.8015341759,50.6268501282],"type":"Point"}
}