{
  "type": "Feature",
  "properties": {
    "addr:full":"Morinnegoed 44 Kortrijk West-Vlaanderen 8500",
    "addr:housenumber":"44",
    "addr:postcode":"8500",
    "addr:street":"Morinnegoed",
    "iso:country":"BE",
    "sg:address":"Morinnegoed 44",
    "sg:city":"Kortrijk",
    "sg:classifiers":[
        {
            "category":"Professional",
            "subcategory":"Management & Consulting",
            "type":"Services"
        }
    ],
    "sg:phone":"+32 56 20 15 03",
    "sg:postcode":"8500",
    "sg:province":"West-Vlaanderen",
    "sg:tags":[
        "-",
        "processing",
        "data",
        "consultant"
    ],
    "wof:name":"Stormsoft",
    "wof:placetype":"venue"
},
  "geometry": {"coordinates":[3.3040499687,50.8092842102],"type":"Point"}
}