{
  "type": "Feature",
  "properties": {
    "addr:full":"Rue De La Ferme Blanche 4 Court-saint-etienne Brabant Wallon 1490",
    "addr:housenumber":"4;1490",
    "addr:street":"Rue De La Ferme Blanche",
    "iso:country":"BE",
    "sg:address":"Rue De La Ferme Blanche 4",
    "sg:city":"Court-saint-etienne",
    "sg:classifiers":[
        {
            "category":"Shopping",
            "subcategory":"Crafts & Fabrics",
            "type":"Retail Goods"
        }
    ],
    "sg:phone":"+32 10 61 78 50",
    "sg:postcode":"1490",
    "sg:province":"Brabant Wallon",
    "sg:tags":[
        "pleating",
        "embroidery"
    ],
    "wof:name":"Printphil Sprl",
    "wof:placetype":"venue"
},
  "geometry": {"coordinates":[4.5907959938,50.6460113525],"type":"Point"}
}