{
  "type": "Feature",
  "properties": {
    "iso:country":"BE",
    "sg:address":"Ketterijstraat 65",
    "sg:city":"Sint-laureins (watervliet)",
    "sg:classifiers":[
        {
            "category":"Farming",
            "subcategory":"Livestock Farm",
            "type":"Manufacturing & Wholesale Goods"
        }
    ],
    "sg:phone":"+32 9 379 89 66",
    "sg:postcode":"9988",
    "sg:province":"Oost-Vlaanderen",
    "sg:tags":[
        "stud"
    ],
    "wof:name":"Vereecke L",
    "wof:placetype":"venue"
},
  "geometry": {"coordinates":[3.613918066,51.2540740967],"type":"Point"}
}