{
  "type": "Feature",
  "properties": {
    "iso:country":"BE",
    "sg:address":"Rue Haute Voie 63",
    "sg:city":"Verlaine",
    "sg:classifiers":[
        {
            "category":"Food & Beverages",
            "subcategory":"Fruits & Vegetables",
            "type":"Retail Goods"
        }
    ],
    "sg:phone":"+32 4 259 54 70",
    "sg:postcode":"4537",
    "sg:province":"Li\u00e8ge",
    "sg:tags":[
        "-"
    ],
    "wof:name":"Destexhe & Fils",
    "wof:placetype":"venue"
},
  "geometry": {"coordinates":[5.3043398857,50.5966415405],"type":"Point"}
}