{
  "type": "Feature",
  "properties": {
    "addr:full":"Rue Du Qu\u00e9niau 206 La Louvi\u00e8re (haine-saint-paul) Hainaut 7100",
    "addr:housenumber":"206",
    "addr:postcode":"7100",
    "addr:street":"Rue Du Que\u0301Niau",
    "iso:country":"BE",
    "sg:address":"Rue Du Qu\u00e9niau 206",
    "sg:city":"La Louvi\u00e8re (haine-saint-paul)",
    "sg:classifiers":[
        {
            "category":"Professional",
            "subcategory":"Management & Consulting",
            "type":"Services"
        }
    ],
    "sg:phone":"+32 64 28 28 94",
    "sg:postcode":"7100",
    "sg:province":"Hainaut",
    "sg:tags":[
        "consultant",
        "law"
    ],
    "wof:name":"De Weeze Jm",
    "wof:placetype":"venue"
},
  "geometry": {"coordinates":[4.1829891205,50.4584465027],"type":"Point"}
}