{
  "type": "Feature",
  "properties": {
    "addr:full":"Otterstraat 35 Turnhout Antwerpen 2300",
    "addr:housenumber":"35",
    "addr:postcode":"2300",
    "addr:street":"Otterstraat",
    "iso:country":"BE",
    "sg:address":"Otterstraat 35",
    "sg:city":"Turnhout",
    "sg:orig_category":"Rev\u00eatements de sols and murs. Installation de menuiserie en bois and plastique. Locations de machine",
    "sg:phone":"+32 14 41 22 41",
    "sg:postcode":"2300",
    "sg:province":"Antwerpen",
    "wof:name":"Broeckx F & S",
    "wof:placetype":"venue"
},
  "geometry": {"coordinates":[4.9516201019,51.3224105835],"type":"Point"}
}