{
  "type": "Feature",
  "properties": {
    "iso:country":"BE",
    "sg:address":"Victor Allardstraat 66",
    "sg:city":"Uccle",
    "sg:orig_category":"Informaticaconsulenten",
    "sg:phone":"+32 2 332 05 12",
    "sg:postcode":"1180",
    "sg:province":"Bruxelles-Capitale",
    "wof:name":"Modern Solutions Business",
    "wof:placetype":"venue"
},
  "geometry": {"coordinates":[4.3335208893,50.8018341064],"type":"Point"}
}