{
  "type": "Feature",
  "properties": {
    "iso:country":"BE",
    "sg:address":"Portaelsstraat 10",
    "sg:city":"Schaarbeek/schaerbeek",
    "sg:orig_category":"Etalage- and showroomontwerpers Verlichting and huishoudartikelen",
    "sg:phone":"+32 2 241 34 21",
    "sg:postcode":"1030",
    "sg:province":"Bruxelles-Capitale",
    "wof:name":"Patricia Van Hamme",
    "wof:placetype":"venue"
},
  "geometry": {"coordinates":[4.3754649162,50.8721199036],"type":"Point"}
}