{
  "type": "Feature",
  "properties": {
    "addr:full":"Rue Au Vin 60 Ronse/renaix Oost-Vlaanderen 9600",
    "addr:housenumber":"60",
    "addr:postcode":"9600",
    "addr:street":"Rue Au Vin",
    "iso:country":"BE",
    "sg:address":"Rue Au Vin 60",
    "sg:city":"Ronse/renaix",
    "sg:classifiers":[
        {
            "category":"Personal",
            "subcategory":"Beauty Salon",
            "type":"Services"
        }
    ],
    "sg:phone":"+32 55 21 37 80",
    "sg:postcode":"9600",
    "sg:province":"Oost-Vlaanderen",
    "sg:tags":[
        "de",
        "coiffure"
    ],
    "wof:name":"Coiffure Christiane",
    "wof:placetype":"venue"
},
  "geometry": {"coordinates":[3.5970048904,50.749546051],"type":"Point"}
}