{
  "type": "Feature",
  "properties": {
    "addr:full":"Brusselbaan 6 Herzele (steenhuize-wijnhuize) Oost-Vlaanderen 9550",
    "addr:housenumber":"6",
    "addr:postcode":"9550",
    "addr:street":"Brusselbaan;Steenhuize-Wijnhuize Oost-Vlaanderen",
    "iso:country":"BE",
    "sg:address":"Brusselbaan 6",
    "sg:city":"Herzele (steenhuize-wijnhuize)",
    "sg:classifiers":[
        {
            "category":"Utilities",
            "subcategory":"Natural Gas",
            "type":"Services"
        }
    ],
    "sg:phone":"+32 54 50 37 00",
    "sg:postcode":"9550",
    "sg:province":"Oost-Vlaanderen",
    "sg:tags":[
        "blacksmith"
    ],
    "wof:name":"De Coppel L",
    "wof:placetype":"venue"
},
  "geometry": {"coordinates":[3.9102110863,50.8256111145],"type":"Point"}
}