{
  "type": "Feature",
  "properties": {
    "iso:country":"BE",
    "sg:address":"Corenteweg 2",
    "sg:city":"Aalst",
    "sg:orig_category":"Rev\u00eatements pour sols and murs. Construction de maisons",
    "sg:phone":"+32 53 78 47 38",
    "sg:postcode":"9310",
    "sg:province":"Oost-Vlaanderen",
    "wof:name":"Peter Wille",
    "wof:placetype":"venue"
},
  "geometry": {"coordinates":[4.099187851,50.9412307739],"type":"Point"}
}