{
  "type": "Feature",
  "properties": {
    "addr:full":"Zandstraat 163 Sint-gillis-waas (sint-pauwels) Oost-Vlaanderen 9170",
    "addr:housenumber":"163",
    "addr:postcode":"9170",
    "addr:street":"Zandstraat;Sint-Gillis-Waas Sint-Pauwels Oost-Vlaanderen",
    "iso:country":"BE",
    "sg:address":"Zandstraat 163",
    "sg:city":"Sint-gillis-waas (sint-pauwels)",
    "sg:orig_category":"Non-Classified Establishments",
    "sg:phone":"+32 3 779 51 71",
    "sg:postcode":"9170",
    "sg:province":"Oost-Vlaanderen",
    "wof:name":"Fancy, Hania En Rene",
    "wof:placetype":"venue"
},
  "geometry": {"coordinates":[4.1255750656,51.2189941406],"type":"Point"}
}