{
  "type": "Feature",
  "properties": {
    "addr:full":"Mechelsestraat 70 Leuven Vlaams-Brabant 3000",
    "addr:housenumber":"70",
    "addr:postcode":"3000",
    "addr:street":"Mechelsestraat",
    "iso:country":"BE",
    "sg:address":"Mechelsestraat 70",
    "sg:city":"Leuven",
    "sg:orig_category":"S\u00e9curit\u00e9 sociale",
    "sg:phone":"+32 16 22 57 04",
    "sg:postcode":"3000",
    "sg:province":"Vlaams-Brabant",
    "wof:name":"Socialist. Mutualiteit",
    "wof:placetype":"venue"
},
  "geometry": {"coordinates":[4.6992211342,50.8820381165],"type":"Point"}
}