{
  "type": "Feature",
  "properties": {
    "iso:country":"BE",
    "sg:address":"Rue Arthur Warocqu\u00e9 27",
    "sg:city":"La Louvi\u00e8re",
    "sg:classifiers":[
        {
            "category":"Government",
            "subcategory":"Post Office",
            "type":"Public Place"
        }
    ],
    "sg:phone":"+32 64 28 17 72",
    "sg:postcode":"7100",
    "sg:province":"Hainaut",
    "sg:tags":[
        "stamp"
    ],
    "wof:name":"Ducene",
    "wof:placetype":"venue"
},
  "geometry": {"coordinates":[4.1911988258,50.4776306152],"type":"Point"}
}