{
  "type": "Feature",
  "properties": {
    "addr:full":"Kempische Kaai 13 Hasselt Limburg 3500",
    "addr:housenumber":"13",
    "addr:postcode":"3500",
    "addr:street":"Kempische Kaai",
    "iso:country":"BE",
    "sg:address":"Kempische Kaai 13",
    "sg:city":"Hasselt",
    "sg:classifiers":[
        {
            "category":"Fast Food",
            "type":"Food & Drink"
        }
    ],
    "sg:phone":"+32 11 24 21 22",
    "sg:postcode":"3500",
    "sg:province":"Limburg",
    "sg:tags":[
        "meeneem",
        "restaurant"
    ],
    "wof:name":"Frituur Kanaalkom",
    "wof:placetype":"venue"
},
  "geometry": {"coordinates":[5.3380441666,50.9359474182],"type":"Point"}
}