{
  "type": "Feature",
  "properties": {
    "iso:country":"BE",
    "sg:address":"Saint-patrice 2b",
    "sg:city":"La Louvi\u00e8re (houdeng-goegnies)",
    "sg:classifiers":[
        {
            "category":"Museum",
            "type":"Entertainment"
        }
    ],
    "sg:phone":"+32 64 28 20 00",
    "sg:postcode":"7110",
    "sg:province":"Hainaut",
    "wof:name":"Ecomus\u00e9e R\u00e9gional Du Centre Asbl",
    "wof:placetype":"venue"
},
  "geometry": {"coordinates":[4.1505050659,50.4826698303],"type":"Point"}
}