{
  "type": "Feature",
  "properties": {
    "iso:country":"BE",
    "sg:address":"Kortrijkstraat 127",
    "sg:city":"Ingelmunster",
    "sg:orig_category":"Supermarch\u00e9s",
    "sg:postcode":"8770",
    "sg:province":"West-Vlaanderen",
    "wof:name":"Aldi",
    "wof:placetype":"venue"
},
  "geometry": {"coordinates":[3.2616479397,50.9062385559],"type":"Point"}
}