{
  "type": "Feature",
  "properties": {
    "addr:full":"Rue Du Calvaire 35 Walcourt Namur 5650",
    "addr:housenumber":"35",
    "addr:postcode":"5650",
    "addr:street":"Rue Du Calvaire",
    "iso:country":"BE",
    "sg:address":"Rue Du Calvaire 35",
    "sg:city":"Walcourt",
    "sg:classifiers":[
        {
            "category":"Health Services",
            "subcategory":"Nursing And Care Facility",
            "type":"Services"
        }
    ],
    "sg:phone":"+32 71 61 20 29",
    "sg:postcode":"5650",
    "sg:province":"Namur",
    "sg:tags":[
        "home"
    ],
    "wof:name":"Marlier M G",
    "wof:placetype":"venue"
},
  "geometry": {"coordinates":[4.4352121353,50.2485618591],"type":"Point"}
}