{
  "type": "Feature",
  "properties": {
    "iso:country":"BE",
    "sg:address":"Rue Tr\u00e9mouroux 119",
    "sg:city":"Perwez (orbais)",
    "sg:classifiers":[
        {
            "category":"Education",
            "subcategory":"School",
            "type":"Public Place"
        }
    ],
    "sg:phone":"+32 81 65 71 76",
    "sg:postcode":"1360",
    "sg:province":"Brabant Wallon",
    "sg:tags":[
        "primary"
    ],
    "wof:name":"Croque La Vie",
    "wof:placetype":"venue"
},
  "geometry": {"coordinates":[4.7624731064,50.6358375549],"type":"Point"}
}