{
  "type": "Feature",
  "properties": {
    "iso:country":"BE",
    "sg:address":"Koning Albertstraat 32",
    "sg:city":"Hasselt",
    "sg:classifiers":[
        {
            "category":"Shopping",
            "subcategory":"Clothing, Apparel, & Fashions",
            "type":"Retail Goods"
        }
    ],
    "sg:phone":"+32 11 22 23 33",
    "sg:postcode":"3500",
    "sg:province":"Limburg",
    "sg:tags":[
        "clothing",
        "-",
        "gentleman"
    ],
    "wof:name":"Gary Herenmode",
    "wof:placetype":"venue"
},
  "geometry": {"coordinates":[5.3371648788,50.9285202026],"type":"Point"}
}