{
  "type": "Feature",
  "properties": {
    "addr:full":"Kabei 81 Sint-truiden Limburg 3800",
    "addr:housenumber":"81",
    "addr:postcode":"3800",
    "addr:street":"Kabei",
    "iso:country":"BE",
    "sg:address":"Kabei 81",
    "sg:city":"Sint-truiden",
    "sg:orig_category":"Fruitteelt",
    "sg:phone":"+32 11 68 74 80",
    "sg:postcode":"3800",
    "sg:province":"Limburg",
    "wof:name":"Gerda Luykx",
    "wof:placetype":"venue"
},
  "geometry": {"coordinates":[5.2320389748,50.8298187256],"type":"Point"}
}