{
  "type": "Feature",
  "properties": {
    "iso:country":"BE",
    "sg:address":"Kerkstraat 4",
    "sg:city":"Beveren",
    "sg:orig_category":"Pharmaciens",
    "sg:phone":"+32 3 775 97 19",
    "sg:postcode":"9120",
    "sg:province":"Oost-Vlaanderen",
    "wof:name":"Willy Wynter",
    "wof:placetype":"venue"
},
  "geometry": {"coordinates":[4.1945061684,51.2190971375],"type":"Point"}
}