{
  "type": "Feature",
  "properties": {
    "iso:country":"BE",
    "sg:address":"Openveldstraat 54",
    "sg:city":"Sint-agatha-berchem/berchem-sainte-agathe",
    "sg:orig_category":"Artsen and specialisten",
    "sg:phone":"+32 2 465 84 75",
    "sg:postcode":"1082",
    "sg:province":"Bruxelles-Capitale",
    "wof:name":"Muriel Baert",
    "wof:placetype":"venue"
},
  "geometry": {"coordinates":[4.2977871895,50.866230011],"type":"Point"}
}