{
  "type": "Feature",
  "properties": {
    "addr:full":"Hypolite Limbourglaan 48 Anderlecht Bruxelles-Capitale 1070",
    "addr:housenumber":"48",
    "addr:postcode":"1070",
    "addr:street":"Limbourglaan",
    "iso:country":"BE",
    "sg:address":"Hypolite Limbourglaan 48",
    "sg:city":"Anderlecht",
    "sg:orig_category":"Rusthuizen and serviceflats",
    "sg:phone":"+32 2 524 21 27",
    "sg:postcode":"1070",
    "sg:province":"Bruxelles-Capitale",
    "wof:name":"Debemas",
    "wof:placetype":"venue"
},
  "geometry": {"coordinates":[4.3032951355,50.8323745728],"type":"Point"}
}