{
  "type": "Feature",
  "properties": {
    "addr:full":"Steegstraat 29 Maasmechelen Limburg 3630",
    "addr:housenumber":"29",
    "addr:postcode":"3630",
    "addr:street":"Steegstraat",
    "iso:country":"BE",
    "sg:address":"Steegstraat 29",
    "sg:city":"Maasmechelen",
    "sg:orig_category":"Kapsalons",
    "sg:phone":"+32 89 76 21 33",
    "sg:postcode":"3630",
    "sg:province":"Limburg",
    "wof:name":"Coiffure Donato",
    "wof:placetype":"venue"
},
  "geometry": {"coordinates":[5.6961350441,50.963848114],"type":"Point"}
}