{
  "type": "Feature",
  "properties": {
    "addr:full":"Doorniksesteenweg 27 Avelgem West-Vlaanderen 8580",
    "addr:housenumber":"27",
    "addr:postcode":"8580",
    "addr:street":"Doorniksesteenweg",
    "iso:country":"BE",
    "sg:address":"Doorniksesteenweg 27",
    "sg:city":"Avelgem",
    "sg:orig_category":"V\u00eatements pour b\u00e9b\u00e9s and enfants",
    "sg:phone":"+32 56 64 79 80",
    "sg:postcode":"8580",
    "sg:province":"West-Vlaanderen",
    "wof:name":"Huis Balloe",
    "wof:placetype":"venue"
},
  "geometry": {"coordinates":[3.4443581104,50.7747955322],"type":"Point"}
}