{
  "type": "Feature",
  "properties": {
    "iso:country":"BE",
    "sg:address":"Heirbaan 152",
    "sg:city":"Machelen",
    "sg:orig_category":"Groententeelt",
    "sg:phone":"+32 2 251 56 12",
    "sg:postcode":"1830",
    "sg:province":"Vlaams-Brabant",
    "wof:name":"Jan Vranckx",
    "wof:placetype":"venue"
},
  "geometry": {"coordinates":[4.447412014,50.9150428772],"type":"Point"}
}