{
  "type": "Feature",
  "properties": {
    "addr:full":"Korte Altaarstraat 19 Antwerpen Antwerpen 2018",
    "addr:housenumber":"19",
    "addr:postcode":"2018",
    "addr:street":"Korte Altaarstraat",
    "iso:country":"BE",
    "sg:address":"Korte Altaarstraat 19",
    "sg:city":"Antwerpen",
    "sg:classifiers":[
        {
            "category":"Education",
            "subcategory":"School",
            "type":"Public Place"
        }
    ],
    "sg:phone":"+32 3 271 09 43",
    "sg:postcode":"2018",
    "sg:province":"Antwerpen",
    "sg:tags":[
        "-",
        "private"
    ],
    "wof:name":"Antwerp British School",
    "wof:placetype":"venue"
},
  "geometry": {"coordinates":[4.4318270683,51.2069320679],"type":"Point"}
}