{
  "type": "Feature",
  "properties": {
    "addr:full":"Kruisken 28 Maldegem (adegem) Oost-Vlaanderen 9991",
    "addr:housenumber":"28",
    "addr:postcode":"9991",
    "addr:street":"Kruisken",
    "iso:country":"BE",
    "sg:address":"Kruisken 28",
    "sg:city":"Maldegem (adegem)",
    "sg:classifiers":[
        {
            "category":"Freight",
            "type":"Transportation"
        }
    ],
    "sg:phone":"+32 496 53 53 67",
    "sg:postcode":"9991",
    "sg:province":"Oost-Vlaanderen",
    "sg:tags":[
        "-",
        "transport"
    ],
    "wof:name":"Crul J Bvba",
    "wof:placetype":"venue"
},
  "geometry": {"coordinates":[3.4955260754,51.1888465881],"type":"Point"}
}