{
  "type": "Feature",
  "properties": {
    "iso:country":"BE",
    "sg:address":"Hendrik Consciencelaan 137",
    "sg:city":"Evere/evere",
    "sg:orig_category":"Industri\u00eble wasserijen and droogkuis",
    "sg:phone":"+32 2 241 39 77",
    "sg:postcode":"1140",
    "sg:province":"Bruxelles-Capitale",
    "wof:name":"Nettoyage \u00c0 Sec Clean",
    "wof:placetype":"venue"
},
  "geometry": {"coordinates":[4.3998961449,50.8708114624],"type":"Point"}
}