{
  "type": "Feature",
  "properties": {
    "iso:country":"BE",
    "sg:address":"Rue Du Tige 44",
    "sg:city":"Rochefort",
    "sg:orig_category":"Herstelling leer and schoeisel Herstellingen and onderhoud van auto's Industri\u00eble wasserijen and dro",
    "sg:phone":"+32 84 21 17 77",
    "sg:postcode":"5580",
    "sg:province":"Namur",
    "wof:name":"Atelier St.vincent",
    "wof:placetype":"venue"
},
  "geometry": {"coordinates":[5.2162799835,50.1629219055],"type":"Point"}
}