{
  "type": "Feature",
  "properties": {
    "addr:full":"Aalstersesteenweg 66 Ninove Oost-Vlaanderen 9400",
    "addr:housenumber":"66",
    "addr:postcode":"9400",
    "addr:street":"Aalstersesteenweg",
    "iso:country":"BE",
    "sg:address":"Aalstersesteenweg 66",
    "sg:city":"Ninove",
    "sg:classifiers":[
        {
            "category":"Health Services",
            "subcategory":"Health Practitioner",
            "type":"Services"
        }
    ],
    "sg:phone":"+32 54 33 48 78",
    "sg:postcode":"9400",
    "sg:province":"Oost-Vlaanderen",
    "sg:tags":[
        "physiotherapist"
    ],
    "wof:name":"De Coppel A",
    "wof:placetype":"venue"
},
  "geometry": {"coordinates":[4.0244178772,50.8420181274],"type":"Point"}
}