{
  "type": "Feature",
  "properties": {
    "iso:country":"BE",
    "sg:address":"Bredestraat 29",
    "sg:city":"Putte",
    "sg:classifiers":[
        {
            "category":"Bakery",
            "type":"Food & Drink"
        }
    ],
    "sg:phone":"+32 15 75 68 19",
    "sg:postcode":"2580",
    "sg:province":"Antwerpen",
    "sg:tags":[
        "confectioner",
        "baker"
    ],
    "wof:name":"Kristof",
    "wof:placetype":"venue"
},
  "geometry": {"coordinates":[4.6342592239,51.06224823],"type":"Point"}
}