{
  "type": "Feature",
  "properties": {
    "iso:country":"BE",
    "sg:address":"Avenue De La Gare 11",
    "sg:city":"Wavre",
    "sg:orig_category":"Eclairage et \u00e9quipements du foyer. Drogueries. Peinture. Rev\u00eatements pour sols and murs",
    "sg:phone":"+32 10 41 47 67",
    "sg:postcode":"1300",
    "sg:province":"Brabant Wallon",
    "wof:name":"Newman Decoration",
    "wof:placetype":"venue"
},
  "geometry": {"coordinates":[4.5753130913,50.6922149658],"type":"Point"}
}