{
  "type": "Feature",
  "properties": {
    "iso:country":"BE",
    "sg:address":"Rue Walth\u00e8re Jamar 279b",
    "sg:city":"Ans",
    "sg:classifiers":[
        {
            "category":"Professional",
            "subcategory":"Computer Services",
            "type":"Services"
        }
    ],
    "sg:phone":"+32 4 247 35 05",
    "sg:postcode":"4430",
    "sg:province":"Li\u00e8ge",
    "sg:tags":[
        "repair",
        "processing",
        "-",
        "maintenance",
        "data"
    ],
    "wof:name":"Comtronic",
    "wof:placetype":"venue"
},
  "geometry": {"coordinates":[5.5341300964,50.6545143127],"type":"Point"}
}