{
  "type": "Feature",
  "properties": {
    "addr:full":"Oude Baan 55 Brasschaat Antwerpen 2930",
    "addr:housenumber":"55",
    "addr:postcode":"2930",
    "addr:street":"Oude Baan",
    "iso:country":"BE",
    "sg:address":"Oude Baan 55",
    "sg:city":"Brasschaat",
    "sg:classifiers":[
        {
            "category":"Organizations",
            "subcategory":"Community Association",
            "type":"Services"
        }
    ],
    "sg:phone":"+32 3 652 15 69",
    "sg:postcode":"2930",
    "sg:province":"Antwerpen",
    "sg:tags":[
        "cultural"
    ],
    "wof:name":"Koninklijke Brasschaatse Duivenbond Vzw",
    "wof:placetype":"venue"
},
  "geometry": {"coordinates":[4.4874382019,51.2872962952],"type":"Point"}
}