{
  "type": "Feature",
  "properties": {
    "iso:country":"BE",
    "sg:address":"Statiestraat 32a",
    "sg:city":"Mol",
    "sg:classifiers":[
        {
            "category":"Cinema",
            "subcategory":"Movie Theater",
            "type":"Entertainment"
        }
    ],
    "sg:phone":"+32 14 31 38 77",
    "sg:postcode":"2400",
    "sg:province":"Antwerpen",
    "wof:name":"Cultureel Centrum Cinerex",
    "wof:placetype":"venue"
},
  "geometry": {"coordinates":[5.1182022095,51.1898498535],"type":"Point"}
}