{
  "type": "Feature",
  "properties": {
    "addr:full":"Rue Du Parc 35 Kelmis/la Calamine Li\u00e8ge 4720",
    "addr:housenumber":"35",
    "addr:postcode":"4720",
    "addr:street":"Rue Du Parc",
    "iso:country":"BE",
    "sg:address":"Rue Du Parc 35",
    "sg:city":"Kelmis/la Calamine",
    "sg:classifiers":[
        {
            "category":"Food & Beverages",
            "subcategory":"Fruits & Vegetables",
            "type":"Retail Goods"
        }
    ],
    "sg:phone":"+32 87 65 94 88",
    "sg:postcode":"4720",
    "sg:province":"Li\u00e8ge",
    "sg:tags":[
        "l\u00e9gumes",
        "gr"
    ],
    "wof:name":"Radermacher",
    "wof:placetype":"venue"
},
  "geometry": {"coordinates":[6.0062952042,50.7148742676],"type":"Point"}
}