{
  "type": "Feature",
  "properties": {
    "addr:full":"Hazeveld 2 Sint-pieters-leeuw (oudenaken) Vlaams-Brabant 1600",
    "addr:housenumber":"2;1600",
    "addr:street":"Hazeveld;Vlaams-Brabant",
    "iso:country":"BE",
    "sg:address":"Hazeveld 2",
    "sg:city":"Sint-pieters-leeuw (oudenaken)",
    "sg:classifiers":[
        {
            "category":"Professional",
            "subcategory":"Art Services",
            "type":"Services"
        }
    ],
    "sg:phone":"+32 2 532 57 50",
    "sg:postcode":"1600",
    "sg:province":"Vlaams-Brabant",
    "sg:tags":[
        "design",
        "packing",
        "-",
        "realization"
    ],
    "wof:name":"Idepack Design",
    "wof:placetype":"venue"
},
  "geometry": {"coordinates":[4.2080640793,50.7829093933],"type":"Point"}
}