{
  "type": "Feature",
  "properties": {
    "addr:full":"Rue Du Congo 15 Mouscron Hainaut 7700",
    "addr:housenumber":"15",
    "addr:postcode":"7700",
    "addr:street":"Rue Du Congo",
    "iso:country":"BE",
    "sg:address":"Rue Du Congo 15",
    "sg:city":"Mouscron",
    "sg:orig_category":"Autombile concessionaires",
    "sg:phone":"+32 56 84 40 77",
    "sg:postcode":"7700",
    "sg:province":"Hainaut",
    "wof:name":"Baert",
    "wof:placetype":"venue"
},
  "geometry": {"coordinates":[3.1994240284,50.7370758057],"type":"Point"}
}