{
  "type": "Feature",
  "properties": {
    "addr:full":"Place De L' H\u00d4tel De Ville 9 Frasnes-lez-anvaing Hainaut 7911",
    "addr:housenumber":"9;7911",
    "addr:street":"Place De L ' Ho\u0302Tel;Frasnes-Lez-Anvaing Hainaut",
    "iso:country":"BE",
    "sg:address":"Place De L' H\u00d4tel De Ville 9",
    "sg:city":"Frasnes-lez-anvaing",
    "sg:orig_category":"Banken and kredietinstellingen",
    "sg:phone":"+32 69 86 65 31",
    "sg:postcode":"7911",
    "sg:province":"Hainaut",
    "wof:name":"Cr\u00c9dit G\u00c9n\u00c9ral De Banque",
    "wof:placetype":"venue"
},
  "geometry": {"coordinates":[3.6214199066,50.6650161743],"type":"Point"}
}