{
  "type": "Feature",
  "properties": {
    "iso:country":"BE",
    "sg:address":"Sint-niklaasstraat 11",
    "sg:city":"Kortrijk",
    "sg:classifiers":[
        {
            "category":"Real Estate",
            "subcategory":"Architect",
            "type":"Services"
        }
    ],
    "sg:phone":"+32 56 22 46 39",
    "sg:postcode":"8500",
    "sg:province":"West-Vlaanderen",
    "wof:name":"Baekelandt M",
    "wof:placetype":"venue"
},
  "geometry": {"coordinates":[3.2709670067,50.8284835815],"type":"Point"}
}