{
  "type": "Feature",
  "properties": {
    "iso:country":"BE",
    "sg:address":"Britse Lei 1a",
    "sg:city":"Antwerpen",
    "sg:classifiers":[
        {
            "category":"Home & Garden",
            "subcategory":"Home Furnishings",
            "type":"Retail Goods"
        }
    ],
    "sg:phone":"+32 3 216 33 88",
    "sg:postcode":"2000",
    "sg:province":"Antwerpen",
    "sg:tags":[
        "lighting",
        "fixture",
        "-"
    ],
    "wof:name":"Deco Cap",
    "wof:placetype":"venue"
},
  "geometry": {"coordinates":[4.407761097,51.2107810974],"type":"Point"}
}