{
  "type": "Feature",
  "properties": {
    "iso:country":"BE",
    "sg:address":"Veeweidekaai 33",
    "sg:city":"Anderlecht/anderlecht",
    "sg:classifiers":[
        {
            "category":"Cafe",
            "type":"Food & Drink"
        }
    ],
    "sg:phone":"+32 2 520 03 74",
    "sg:postcode":"1070",
    "sg:province":"Bruxelles-Capitale",
    "sg:tags":[
        "caf\u00e9s"
    ],
    "wof:name":"Caf\u00c9 Du Pont",
    "wof:placetype":"venue"
},
  "geometry": {"coordinates":[4.3017458916,50.8201332092],"type":"Point"}
}