{
  "type": "Feature",
  "properties": {
    "addr:full":"Hoekskensstraat 134-136 Lochristi Oost-Vlaanderen 9080",
    "addr:housenumber":"134-136",
    "addr:postcode":"9080",
    "addr:street":"Hoekskensstraat",
    "iso:country":"BE",
    "sg:address":"Hoekskensstraat 134-136",
    "sg:city":"Lochristi",
    "sg:orig_category":"Bloemen and planten Gh",
    "sg:phone":"+32 9 355 71 02",
    "sg:postcode":"9080",
    "sg:province":"Oost-Vlaanderen",
    "wof:name":"Taghon A",
    "wof:placetype":"venue"
},
  "geometry": {"coordinates":[3.8367478848,51.1143913269],"type":"Point"}
}