{
  "type": "Feature",
  "properties": {
    "iso:country":"BE",
    "sg:address":"Liersesteenweg 182",
    "sg:city":"Mechelen",
    "sg:orig_category":"Notaires",
    "sg:phone":"+32 15 20 01 44",
    "sg:postcode":"2800",
    "sg:province":"Antwerpen",
    "wof:name":"Dirk Luyten",
    "wof:placetype":"venue"
},
  "geometry": {"coordinates":[4.479929924,51.0392227173],"type":"Point"}
}