{
  "type": "Feature",
  "properties": {
    "addr:full":"Avenue Winston Churchill 195 Box 10 Bruxelles (uccle) Bruxelles-Capitale 1180",
    "addr:housenumber":"195 box 10",
    "addr:postcode":"1180",
    "addr:street":"Avenue Winston Churchill",
    "iso:country":"BE",
    "sg:address":"Avenue Winston Churchill 195 Box 10",
    "sg:city":"Bruxelles (uccle)",
    "sg:classifiers":[
        {
            "category":"Professional",
            "subcategory":"Management & Consulting",
            "type":"Services"
        }
    ],
    "sg:phone":"+32 2 344 21 17",
    "sg:postcode":"1180",
    "sg:province":"Bruxelles-Capitale",
    "sg:tags":[
        "consultant"
    ],
    "wof:name":"Ad Formation Sprl",
    "wof:placetype":"venue"
},
  "geometry": {"coordinates":[4.3643889427,50.811378479],"type":"Point"}
}