{
  "type": "Feature",
  "properties": {
    "addr:full":"Stationsstraat 10 Temse Oost-Vlaanderen 9140",
    "addr:housenumber":"10",
    "addr:postcode":"9140",
    "addr:street":"Stationsstraat",
    "iso:country":"BE",
    "sg:address":"Stationsstraat 10",
    "sg:city":"Temse",
    "sg:classifiers":[
        {
            "category":"Retail",
            "subcategory":"Funeral Services",
            "type":"Services"
        }
    ],
    "sg:phone":"+32 3 771 04 41",
    "sg:postcode":"9140",
    "sg:province":"Oost-Vlaanderen",
    "sg:tags":[
        "director"
    ],
    "wof:name":"Gyselinck Bvba",
    "wof:placetype":"venue"
},
  "geometry": {"coordinates":[4.2189497948,51.1242218018],"type":"Point"}
}