{
  "type": "Feature",
  "properties": {
    "addr:full":"Diestersesteenweg 31 Beringen Limburg 3583",
    "addr:housenumber":"31",
    "addr:postcode":"3583",
    "addr:street":"Diestersesteenweg",
    "iso:country":"BE",
    "sg:address":"Diestersesteenweg 31",
    "sg:city":"Beringen",
    "sg:orig_category":"Avocats and conseillers juridiques",
    "sg:phone":"+32 11 45 26 15",
    "sg:postcode":"3583",
    "sg:province":"Limburg",
    "wof:name":"Nancy Vandervoort",
    "wof:placetype":"venue"
},
  "geometry": {"coordinates":[5.1706700325,51.0389442444],"type":"Point"}
}