{
  "type": "Feature",
  "properties": {
    "addr:full":"Roeselaarsestraat 173 Ardooie West-Vlaanderen 8850",
    "addr:housenumber":"173",
    "addr:postcode":"8850",
    "addr:street":"Roeselaarsestraat",
    "iso:country":"BE",
    "sg:address":"Roeselaarsestraat 173",
    "sg:city":"Ardooie",
    "sg:orig_category":"Boucheries",
    "sg:phone":"+32 51 20 25 43",
    "sg:postcode":"8850",
    "sg:province":"West-Vlaanderen",
    "wof:name":"Ivan Bonte",
    "wof:placetype":"venue"
},
  "geometry": {"coordinates":[3.1826601028,50.9670181274],"type":"Point"}
}