{
  "type": "Feature",
  "properties": {
    "iso:country":"BE",
    "sg:address":"Petit March\u00c9 8",
    "sg:city":"Ronse/renaix",
    "sg:classifiers":[
        {
            "category":"Cafe",
            "type":"Food & Drink"
        }
    ],
    "sg:phone":"+32 55 21 23 64",
    "sg:postcode":"9600",
    "sg:province":"Oost-Vlaanderen",
    "sg:tags":[
        "caf\u00e9s"
    ],
    "wof:name":"Caf\u00c9 Centrum",
    "wof:placetype":"venue"
},
  "geometry": {"coordinates":[3.5989561081,50.7487297058],"type":"Point"}
}