{
  "type": "Feature",
  "properties": {
    "addr:full":"Place Du Jardins Aux Fleurs 21 Bruxelles Bruxelles-Capitale 1000",
    "addr:housenumber":"21",
    "addr:postcode":"1000",
    "addr:street":"Place Du Jardins Aux Fleurs",
    "iso:country":"BE",
    "sg:address":"Place Du Jardins Aux Fleurs 21",
    "sg:city":"Bruxelles",
    "sg:classifiers":[
        {
            "category":"Personal",
            "subcategory":"Beauty Salon",
            "type":"Services"
        }
    ],
    "sg:phone":"+32 2 511 55 29",
    "sg:postcode":"1000",
    "sg:province":"Bruxelles-Capitale",
    "sg:tags":[
        "de",
        "coiffure"
    ],
    "wof:name":"Luna Torres",
    "wof:placetype":"venue"
},
  "geometry": {"coordinates":[4.3437209129,50.8479614258],"type":"Point"}
}