{
  "type": "Feature",
  "properties": {
    "iso:country":"BE",
    "sg:address":"Avenue Fran\u00e7ois Cornesse 6",
    "sg:city":"Aywaille",
    "sg:classifiers":[
        {
            "category":"Shopping",
            "subcategory":"Clothing, Apparel, & Fashions",
            "type":"Retail Goods"
        }
    ],
    "sg:phone":"+32 4 384 68 45",
    "sg:postcode":"4920",
    "sg:province":"Li\u00e8ge",
    "sg:tags":[
        "-",
        "haberdashery"
    ],
    "wof:name":"Mercerie (la)",
    "wof:placetype":"venue"
},
  "geometry": {"coordinates":[5.6746778488,50.4746932983],"type":"Point"}
}