{
  "type": "Feature",
  "properties": {
    "iso:country":"BE",
    "sg:address":"Denderdreve 26ba",
    "sg:city":"Zelzate",
    "sg:orig_category":"Sportclubs",
    "sg:phone":"+32 9 222 65 66",
    "sg:postcode":"9060",
    "sg:province":"Oost-Vlaanderen",
    "wof:name":"Skischool Blanchaer",
    "wof:placetype":"venue"
},
  "geometry": {"coordinates":[3.7976920605,51.2100105286],"type":"Point"}
}