{
  "type": "Feature",
  "properties": {
    "addr:full":"Bosrandstraat 6 Genk (waterschei) Limburg 3600",
    "addr:housenumber":"6",
    "addr:postcode":"3600",
    "addr:street":"Bosrandstraat",
    "iso:country":"BE",
    "sg:address":"Bosrandstraat 6",
    "sg:city":"Genk (waterschei)",
    "sg:classifiers":[
        {
            "category":"Personal",
            "subcategory":"Shoe Repair & Shine",
            "type":"Services"
        }
    ],
    "sg:phone":"+32 89 84 15 57",
    "sg:postcode":"3600",
    "sg:province":"Limburg",
    "sg:tags":[
        "shoemaker"
    ],
    "wof:name":"Shoe Lux",
    "wof:placetype":"venue"
},
  "geometry": {"coordinates":[5.5154891014,50.9995803833],"type":"Point"}
}