{
  "type": "Feature",
  "properties": {
    "iso:country":"BE",
    "sg:address":"Vennestraat 5",
    "sg:city":"Lokeren",
    "sg:orig_category":"Eleveurs de bovins",
    "sg:phone":"+32 9 348 78 12",
    "sg:postcode":"9160",
    "sg:province":"Oost-Vlaanderen",
    "wof:name":"Rosgo",
    "wof:placetype":"venue"
},
  "geometry": {"coordinates":[3.9447550774,51.1063995361],"type":"Point"}
}