{
  "type": "Feature",
  "properties": {
    "iso:country":"BE",
    "sg:address":"Steenweg Op Waarloos 31",
    "sg:city":"Rumst",
    "sg:orig_category":"Installation de menuiserie m\u00e9tallique",
    "sg:phone":"+32 3 888 04 71",
    "sg:postcode":"2840",
    "sg:province":"Antwerpen",
    "wof:name":"Serco Stoffels",
    "wof:placetype":"venue"
},
  "geometry": {"coordinates":[4.4227218628,51.0800132751],"type":"Point"}
}