{
  "type": "Feature",
  "properties": {
    "iso:country":"BE",
    "sg:address":"Avenue Du Ch\u00cane 28",
    "sg:city":"Ottignies-louvain-la-neuve",
    "sg:orig_category":"M\u00e9decins and sp\u00e9cialistes",
    "sg:phone":"+32 10 41 29 47",
    "sg:postcode":"1340",
    "sg:province":"Brabant Wallon",
    "wof:name":"Chantal Maillet",
    "wof:placetype":"venue"
},
  "geometry": {"coordinates":[4.5795679092,50.672454834],"type":"Point"}
}