{
  "type": "Feature",
  "properties": {
    "iso:country":"BE",
    "sg:address":"Kromstraat 54",
    "sg:city":"Ranst",
    "sg:classifiers":[
        {
            "category":"Manufacturing",
            "subcategory":"Motor Vehicles & Parts",
            "type":"Manufacturing & Wholesale Goods"
        }
    ],
    "sg:phone":"+32 3 485 81 91",
    "sg:postcode":"2520",
    "sg:province":"Antwerpen",
    "sg:tags":[
        "machine",
        "lubricating",
        "oil",
        "oils"
    ],
    "wof:name":"Denicol Motor Oils Nv",
    "wof:placetype":"venue"
},
  "geometry": {"coordinates":[4.5522241592,51.1928977966],"type":"Point"}
}