{
  "type": "Feature",
  "properties": {
    "addr:full":"Brusselsesteenweg 170 Grimbergen Vlaams-Brabant 1850",
    "addr:housenumber":"170",
    "addr:postcode":"1850",
    "addr:street":"Brusselsesteenweg",
    "iso:country":"BE",
    "sg:address":"Brusselsesteenweg 170",
    "sg:city":"Grimbergen",
    "sg:classifiers":[
        {
            "category":"Manufacturing",
            "subcategory":"Glass & Minerals",
            "type":"Manufacturing & Wholesale Goods"
        }
    ],
    "sg:phone":"+32 2 269 57 58",
    "sg:postcode":"1850",
    "sg:province":"Vlaams-Brabant",
    "sg:tags":[
        "stained",
        "glazier",
        "-"
    ],
    "wof:name":"Atelier Lucas",
    "wof:placetype":"venue"
},
  "geometry": {"coordinates":[4.3661990166,50.9276199341],"type":"Point"}
}