{
  "type": "Feature",
  "properties": {
    "addr:full":"Rue De La Grande Sambresse 7 Namur (temploux) Namur 5020",
    "addr:housenumber":"7",
    "addr:postcode":"5020",
    "addr:street":"Rue De La Grande Sambresse",
    "iso:country":"BE",
    "sg:address":"Rue De La Grande Sambresse 7",
    "sg:city":"Namur (temploux)",
    "sg:classifiers":[
        {
            "category":"Professional",
            "subcategory":"Accounting & Tax Preparation",
            "type":"Services"
        }
    ],
    "sg:phone":"+32 81 55 94 14",
    "sg:postcode":"5020",
    "sg:province":"Namur",
    "sg:tags":[
        "bookkeeper"
    ],
    "wof:name":"Delvaux J-j",
    "wof:placetype":"venue"
},
  "geometry": {"coordinates":[4.7952418327,50.4352035522],"type":"Point"}
}