{
  "type": "Feature",
  "properties": {
    "iso:country":"BE",
    "sg:address":"Eynestraat 95",
    "sg:city":"Sint-truiden",
    "sg:orig_category":"Banken and kredietinstellingen",
    "sg:phone":"+32 11 68 36 13",
    "sg:postcode":"3800",
    "sg:province":"Limburg",
    "wof:name":"Kbc",
    "wof:placetype":"venue"
},
  "geometry": {"coordinates":[5.2582278252,50.8308601379],"type":"Point"}
}