{
  "type": "Feature",
  "properties": {
    "iso:country":"BE",
    "sg:address":"Stasegemsestraat 87",
    "sg:city":"Kortrijk",
    "sg:orig_category":"Charpentes and couvertures. Plomberie, chauffage and installations sanitaires",
    "sg:phone":"+32 56 22 55 64",
    "sg:postcode":"8500",
    "sg:province":"West-Vlaanderen",
    "wof:name":"Jean-claude Cottignies",
    "wof:placetype":"venue"
},
  "geometry": {"coordinates":[3.2795100212,50.83152771],"type":"Point"}
}