{
  "type": "Feature",
  "properties": {
    "iso:country":"BE",
    "sg:address":"Taille Th\u00c9r\u00c8se 8",
    "sg:city":"Chaumont-gistoux",
    "sg:classifiers":[
        {
            "category":"Sports & Exercise",
            "subcategory":"Sports Center",
            "type":"Entertainment"
        }
    ],
    "sg:phone":"+32 10 68 11 88",
    "sg:postcode":"1325",
    "sg:province":"Brabant Wallon",
    "sg:tags":[
        "terrain",
        "hors",
        "de",
        "installation",
        "sportifs"
    ],
    "wof:name":"Horse\u00b4s Valley Property",
    "wof:placetype":"venue"
},
  "geometry": {"coordinates":[4.6666097641,50.6950416565],"type":"Point"}
}