{
  "type": "Feature",
  "properties": {
    "iso:country":"BE",
    "sg:address":"Schuiferskapellestraat 80",
    "sg:city":"Pittem",
    "sg:orig_category":"D\u00e9molition d\u00b4immeubles and terrassements",
    "sg:phone":"+32 51 46 71 86",
    "sg:postcode":"8740",
    "sg:province":"West-Vlaanderen",
    "wof:name":"Dedeurwaerder",
    "wof:placetype":"venue"
},
  "geometry": {"coordinates":[3.27739501,51.0044670105],"type":"Point"}
}