{
  "type": "Feature",
  "properties": {
    "addr:full":"Place Delcour 17 Li\u00c8ge Li\u00e8ge 4020",
    "addr:housenumber":"17",
    "addr:postcode":"4020",
    "addr:street":"Place Delcour",
    "iso:country":"BE",
    "sg:address":"Place Delcour 17",
    "sg:city":"Li\u00c8ge",
    "sg:orig_category":"M\u00e9decins and sp\u00e9cialistes",
    "sg:phone":"+32 4 343 11 43",
    "sg:postcode":"4020",
    "sg:province":"Li\u00e8ge",
    "wof:name":"Anny Fossion",
    "wof:placetype":"venue"
},
  "geometry": {"coordinates":[5.5810089111,50.638381958],"type":"Point"}
}