{
  "type": "Feature",
  "properties": {
    "addr:full":"Chauss\u00c9e De Bruxelles 720 Waterloo Brabant Wallon 1410",
    "addr:housenumber":"720",
    "addr:postcode":"1410",
    "addr:street":"Chausse\u0301E De Bruxelles",
    "iso:country":"BE",
    "sg:address":"Chauss\u00c9e De Bruxelles 720",
    "sg:city":"Waterloo",
    "sg:orig_category":"Speelgoed",
    "sg:phone":"+32 2 387 09 79",
    "sg:postcode":"1410",
    "sg:province":"Brabant Wallon",
    "wof:name":"Maxi-toys",
    "wof:placetype":"venue"
},
  "geometry": {"coordinates":[4.4055390358,50.6914215088],"type":"Point"}
}