{
  "type": "Feature",
  "properties": {
    "iso:country":"BE",
    "sg:address":"Droefstraat 28",
    "sg:city":"Tongeren",
    "sg:orig_category":"Varkenskwekers",
    "sg:phone":"+32 12 23 26 38",
    "sg:postcode":"3700",
    "sg:province":"Limburg",
    "wof:name":"Marc Renard",
    "wof:placetype":"venue"
},
  "geometry": {"coordinates":[5.4922828674,50.7517051697],"type":"Point"}
}