{
  "type": "Feature",
  "properties": {
    "addr:full":"Jeugdstraat 48 Beringen (paal) Limburg 3583",
    "addr:housenumber":"48",
    "addr:postcode":"3583",
    "addr:street":"Jeugdstraat",
    "iso:country":"BE",
    "sg:address":"Jeugdstraat 48",
    "sg:city":"Beringen (paal)",
    "sg:classifiers":[
        {
            "category":"Personal",
            "subcategory":"Nail Salon",
            "type":"Services"
        }
    ],
    "sg:phone":"+32 11 43 22 57",
    "sg:postcode":"3583",
    "sg:province":"Limburg",
    "sg:tags":[
        "pedicure"
    ],
    "wof:name":"Karina",
    "wof:placetype":"venue"
},
  "geometry": {"coordinates":[5.1706700325,51.0389442444],"type":"Point"}
}