{
  "type": "Feature",
  "properties": {
    "addr:full":"Abbaye De Maredsous Anhee Namur 5537",
    "addr:postcode":"5537",
    "iso:country":"BE",
    "sg:address":"Abbaye De Maredsous",
    "sg:city":"Anhee",
    "sg:orig_category":"Mus\u00e9es and patrimoine culturel",
    "sg:phone":"+32 82 69 82 11",
    "sg:postcode":"5537",
    "sg:province":"Namur",
    "wof:name":"Abbaye Et Centre D'accueil",
    "wof:placetype":"venue"
},
  "geometry": {"coordinates":[4.7578082085,50.316078186],"type":"Point"}
}