{
  "type": "Feature",
  "properties": {
    "addr:full":"Avenue Mar\u00c9chal Foch 764 Mons Hainaut 7012",
    "addr:housenumber":"764",
    "addr:postcode":"7012",
    "addr:street":"Avenue Mare\u0301Chal Foch;Hainaut",
    "iso:country":"BE",
    "sg:address":"Avenue Mar\u00c9chal Foch 764",
    "sg:city":"Mons",
    "sg:orig_category":"Banques and organismes de cr\u00e9dit",
    "sg:phone":"+32 65 88 21 11",
    "sg:postcode":"7012",
    "sg:province":"Hainaut",
    "wof:name":"Citibank",
    "wof:placetype":"venue"
},
  "geometry": {"coordinates":[3.8894600868,50.4481964111],"type":"Point"}
}