{
  "type": "Feature",
  "properties": {
    "addr:full":"Kinderstraat 157 Lint Antwerpen 2547",
    "addr:housenumber":"157",
    "addr:postcode":"2547",
    "addr:street":"Kinderstraat",
    "iso:country":"BE",
    "sg:address":"Kinderstraat 157",
    "sg:city":"Lint",
    "sg:orig_category":"Cr\u00e9meries",
    "sg:phone":"+32 3 455 77 06",
    "sg:postcode":"2547",
    "sg:province":"Antwerpen",
    "wof:name":"Lintse Paardenmelkerij",
    "wof:placetype":"venue"
},
  "geometry": {"coordinates":[4.5045928955,51.1180763245],"type":"Point"}
}