{
  "type": "Feature",
  "properties": {
    "iso:country":"BE",
    "sg:address":"Aandorenstraat 30",
    "sg:city":"Tienen",
    "sg:orig_category":"Installation de menuiserie en bois and plastique",
    "sg:phone":"+32 16 81 14 40",
    "sg:postcode":"3300",
    "sg:province":"Vlaams-Brabant",
    "wof:name":"Decor & Advies",
    "wof:placetype":"venue"
},
  "geometry": {"coordinates":[4.9509758949,50.8019943237],"type":"Point"}
}