{
  "type": "Feature",
  "properties": {
    "addr:full":"Leest 59 Merksplas Antwerpen 2330",
    "addr:housenumber":"59",
    "addr:postcode":"2330",
    "addr:street":"Leest",
    "iso:country":"BE",
    "sg:address":"Leest 59",
    "sg:city":"Merksplas",
    "sg:orig_category":"Animaux domestiques and accessoires",
    "sg:phone":"+32 14 63 47 10",
    "sg:postcode":"2330",
    "sg:province":"Antwerpen",
    "wof:name":"August Verstricht",
    "wof:placetype":"venue"
},
  "geometry": {"coordinates":[4.8595709801,51.355796814],"type":"Point"}
}