{
  "type": "Feature",
  "properties": {
    "iso:country":"BE",
    "sg:address":"Rue De La Sablonni\u00c8re 125",
    "sg:city":"Seraing",
    "sg:classifiers":[
        {
            "category":"Cafe",
            "type":"Food & Drink"
        }
    ],
    "sg:phone":"+32 4 337 96 41",
    "sg:postcode":"4102",
    "sg:province":"Li\u00e8ge",
    "sg:tags":[
        "caf\u00e9s"
    ],
    "wof:name":"Claude Rondaxhe",
    "wof:placetype":"venue"
},
  "geometry": {"coordinates":[5.5415048599,50.5881538391],"type":"Point"}
}