{
  "type": "Feature",
  "properties": {
    "addr:full":"Rue De La Surface 13a Engis Li\u00e8ge 4480",
    "addr:housenumber":"13a",
    "addr:postcode":"4480",
    "addr:street":"Rue De La Surface",
    "iso:country":"BE",
    "sg:address":"Rue De La Surface 13a",
    "sg:city":"Engis",
    "sg:orig_category":"Agences d'exp\u00e9dition",
    "sg:phone":"+32 4 275 51 81",
    "sg:postcode":"4480",
    "sg:province":"Li\u00e8ge",
    "wof:name":"Luxcar International",
    "wof:placetype":"venue"
},
  "geometry": {"coordinates":[5.3783349991,50.5732307434],"type":"Point"}
}