{
  "type": "Feature",
  "properties": {
    "addr:full":"Yzerhand 67b1 Beveren Oost-Vlaanderen 9120",
    "addr:housenumber":"67b1",
    "addr:postcode":"9120",
    "addr:street":"Yzerhand",
    "iso:country":"BE",
    "sg:address":"Yzerhand 67b1",
    "sg:city":"Beveren",
    "sg:classifiers":[
        {
            "category":"Insurance",
            "subcategory":"Insurance Agent",
            "type":"Services"
        }
    ],
    "sg:phone":"+32 3 775 69 26",
    "sg:postcode":"9120",
    "sg:province":"Oost-Vlaanderen",
    "sg:tags":[
        "verzekeringsmakelaars",
        "expert"
    ],
    "wof:name":"Zakenkantoor Druyts Eric",
    "wof:placetype":"venue"
},
  "geometry": {"coordinates":[4.2512850761,51.2163887024],"type":"Point"}
}