{
  "type": "Feature",
  "properties": {
    "addr:full":"Antwerpsesteenweg 461 Malle Antwerpen 2390",
    "addr:housenumber":"461",
    "addr:postcode":"2390",
    "addr:street":"Antwerpsesteenweg",
    "iso:country":"BE",
    "sg:address":"Antwerpsesteenweg 461",
    "sg:city":"Malle",
    "sg:orig_category":"Ordinateurs and \u00e9quipement informatique",
    "sg:phone":"+32 3 312 93 70",
    "sg:postcode":"2390",
    "sg:province":"Antwerpen",
    "wof:name":"Ecotopia Bedrijvencentrum",
    "wof:placetype":"venue"
},
  "geometry": {"coordinates":[4.6700329781,51.2871246338],"type":"Point"}
}