{
  "type": "Feature",
  "properties": {
    "addr:full":"Avenue Du Roi Soldat 102 Bruxelles (anderlecht) Bruxelles-Capitale 1070",
    "addr:housenumber":"102",
    "addr:postcode":"1070",
    "addr:street":"Avenue Du Roi Soldat",
    "iso:country":"BE",
    "sg:address":"Avenue Du Roi Soldat 102",
    "sg:city":"Bruxelles (anderlecht)",
    "sg:classifiers":[
        {
            "category":"Social Services",
            "subcategory":"Child Care",
            "type":"Services"
        }
    ],
    "sg:phone":"+32 2 523 30 08",
    "sg:postcode":"1070",
    "sg:province":"Bruxelles-Capitale",
    "sg:tags":[
        "baby",
        "nursery",
        "day",
        "sitting"
    ],
    "wof:name":"Isadou Sprl",
    "wof:placetype":"venue"
},
  "geometry": {"coordinates":[4.2955532074,50.8297653198],"type":"Point"}
}