{
  "type": "Feature",
  "properties": {
    "addr:full":"Korte Zoutstraat 38 Aalst Oost-Vlaanderen 9300",
    "addr:housenumber":"38",
    "addr:postcode":"9300",
    "addr:street":"Korte Zoutstraat",
    "iso:country":"BE",
    "sg:address":"Korte Zoutstraat 38",
    "sg:city":"Aalst",
    "sg:orig_category":"Bagage and lederwaren",
    "sg:phone":"+32 53 70 62 30",
    "sg:postcode":"9300",
    "sg:province":"Oost-Vlaanderen",
    "wof:name":"Lederlux",
    "wof:placetype":"venue"
},
  "geometry": {"coordinates":[4.0388960838,50.9355125427],"type":"Point"}
}