{
  "type": "Feature",
  "properties": {
    "iso:country":"BE",
    "sg:address":"Veldbosstraat 1",
    "sg:city":"Roeselare",
    "sg:orig_category":"Eleveurs and marchands de porcs",
    "sg:phone":"+32 51 20 43 94",
    "sg:postcode":"8800",
    "sg:province":"West-Vlaanderen",
    "wof:name":"Marc Bisschop",
    "wof:placetype":"venue"
},
  "geometry": {"coordinates":[3.0932099819,50.9409942627],"type":"Point"}
}