{
  "type": "Feature",
  "properties": {
    "iso:country":"BE",
    "sg:address":"Boulevard Leopold Ii 23",
    "sg:city":"Bruxelles (molenbeek-saint-jean)",
    "sg:classifiers":[
        {
            "category":"Communications",
            "subcategory":"Radio Station",
            "type":"Services"
        }
    ],
    "sg:phone":"+32 2 428 30 90",
    "sg:postcode":"1080",
    "sg:province":"Bruxelles-Capitale",
    "sg:tags":[
        "medium",
        "broker"
    ],
    "wof:name":"Trevi",
    "wof:placetype":"venue"
},
  "geometry": {"coordinates":[4.3450250626,50.8593788147],"type":"Point"}
}