{
  "type": "Feature",
  "properties": {
    "addr:full":"Sint-amandusstraat 22 Roeselare West-Vlaanderen 8800",
    "addr:housenumber":"22",
    "addr:postcode":"8800",
    "addr:street":"Sint-Amandusstraat",
    "iso:country":"BE",
    "sg:address":"Sint-amandusstraat 22",
    "sg:city":"Roeselare",
    "sg:orig_category":"Agences de voyages",
    "sg:phone":"+32 51 24 46 45",
    "sg:postcode":"8800",
    "sg:province":"West-Vlaanderen",
    "wof:name":"Lotus Reizen",
    "wof:placetype":"venue"
},
  "geometry": {"coordinates":[3.1226329803,50.9479866028],"type":"Point"}
}