{
  "type": "Feature",
  "properties": {
    "iso:country":"BE",
    "sg:address":"Klaverbladstraat 17",
    "sg:city":"Lummen",
    "sg:orig_category":"Pi\u00e8ces and accessoires de v\u00e9hicules automobiles Entretien and r\u00e9parations de voitures",
    "sg:phone":"+32 13 52 15 12",
    "sg:postcode":"3560",
    "sg:province":"Limburg",
    "wof:name":"Fa. Schafer S.b.",
    "wof:placetype":"venue"
},
  "geometry": {"coordinates":[5.2290492058,50.9965515137],"type":"Point"}
}