{
  "type": "Feature",
  "properties": {
    "addr:full":"Sint-damiaanstraat 142 Wommelgem Antwerpen 2160",
    "addr:housenumber":"142",
    "addr:postcode":"2160",
    "addr:street":"Sint-Damiaanstraat",
    "iso:country":"BE",
    "sg:address":"Sint-damiaanstraat 142",
    "sg:city":"Wommelgem",
    "sg:classifiers":[
        {
            "category":"Building & Trades",
            "subcategory":"Electrical",
            "type":"Services"
        }
    ],
    "sg:phone":"+32 3 354 28 83",
    "sg:postcode":"2160",
    "sg:province":"Antwerpen",
    "sg:tags":[
        "electric",
        "-",
        "housewiring",
        "contractor"
    ],
    "wof:name":"De Corre",
    "wof:placetype":"venue"
},
  "geometry": {"coordinates":[4.5178050995,51.1993103027],"type":"Point"}
}