{
  "type": "Feature",
  "properties": {
    "addr:full":"Schoolstraat 41 Lochristi Oost-Vlaanderen 9080",
    "addr:housenumber":"41",
    "addr:postcode":"9080",
    "addr:street":"Schoolstraat",
    "iso:country":"BE",
    "sg:address":"Schoolstraat 41",
    "sg:city":"Lochristi",
    "sg:classifiers":[
        {
            "category":"Health Services",
            "subcategory":"Health Practitioner",
            "type":"Services"
        }
    ],
    "sg:phone":"+32 9 355 05 20",
    "sg:postcode":"9080",
    "sg:province":"Oost-Vlaanderen",
    "sg:tags":[
        "physiotherapist"
    ],
    "wof:name":"Cauterman Jacques",
    "wof:placetype":"venue"
},
  "geometry": {"coordinates":[3.8263800144,51.0990333557],"type":"Point"}
}