{
  "type": "Feature",
  "properties": {
    "iso:country":"BE",
    "sg:address":"Place Hubert Delrez 2",
    "sg:city":"Verviers (heusy)",
    "sg:classifiers":[
        {
            "category":"Health Services",
            "subcategory":"Doctor",
            "type":"Services"
        }
    ],
    "sg:phone":"+32 87 22 28 21",
    "sg:postcode":"4802",
    "sg:province":"Li\u00e8ge",
    "sg:tags":[
        "medicinephysicians",
        "surgeon"
    ],
    "wof:name":"Lapiere D",
    "wof:placetype":"venue"
},
  "geometry": {"coordinates":[5.8671250343,50.5714111328],"type":"Point"}
}