{
  "type": "Feature",
  "properties": {
    "iso:country":"BE",
    "sg:address":"Rue De Longueville 18",
    "sg:city":"Incourt",
    "sg:orig_category":"Eleveurs de bovins",
    "sg:phone":"+32 10 88 81 12",
    "sg:postcode":"1315",
    "sg:province":"Brabant Wallon",
    "wof:name":"Jean-joseph Albert",
    "wof:placetype":"venue"
},
  "geometry": {"coordinates":[4.7519931793,50.685218811],"type":"Point"}
}