{
  "type": "Feature",
  "properties": {
    "iso:country":"BE",
    "sg:address":"Rue Hoyoux 11",
    "sg:city":"Herstal",
    "sg:classifiers":[
        {
            "category":"Shopping",
            "subcategory":"Clothing, Apparel, & Fashions",
            "type":"Retail Goods"
        }
    ],
    "sg:phone":"+32 4 240 23 29",
    "sg:postcode":"4040",
    "sg:province":"Li\u00e8ge",
    "sg:tags":[
        "-",
        "clothing",
        "child"
    ],
    "wof:name":"Myrtille-fraise",
    "wof:placetype":"venue"
},
  "geometry": {"coordinates":[5.6272802353,50.6618881226],"type":"Point"}
}