{
  "type": "Feature",
  "properties": {
    "addr:full":"Pastoor Pypestraat 3a Koksijde West-Vlaanderen 8670",
    "addr:housenumber":"3a",
    "addr:postcode":"8670",
    "addr:street":"Pastoor Pypestraat",
    "iso:country":"BE",
    "sg:address":"Pastoor Pypestraat 3a",
    "sg:city":"Koksijde",
    "sg:orig_category":"Plaatsen van vloer- and muurbekleding Schilders",
    "sg:phone":"+32 58 23 91 01",
    "sg:postcode":"8670",
    "sg:province":"West-Vlaanderen",
    "wof:name":"Geert Decorte",
    "wof:placetype":"venue"
},
  "geometry": {"coordinates":[2.6972720623,51.1280822754],"type":"Point"}
}