{
  "type": "Feature",
  "properties": {
    "addr:full":"Sterkbosstraat 2 Wichelen (schellebelle) Oost-Vlaanderen 9260",
    "addr:housenumber":"2",
    "addr:postcode":"9260",
    "addr:street":"Sterkbosstraat",
    "iso:country":"BE",
    "sg:address":"Sterkbosstraat 2",
    "sg:city":"Wichelen (schellebelle)",
    "sg:classifiers":[
        {
            "category":"Farming",
            "subcategory":"Livestock Farm",
            "type":"Manufacturing & Wholesale Goods"
        }
    ],
    "sg:phone":"+32 9 369 15 58",
    "sg:postcode":"9260",
    "sg:province":"Oost-Vlaanderen",
    "sg:tags":[
        "buyer"
    ],
    "wof:name":"De Rycke J",
    "wof:placetype":"venue"
},
  "geometry": {"coordinates":[3.9274179935,50.9989395142],"type":"Point"}
}