{
  "type": "Feature",
  "properties": {
    "iso:country":"BE",
    "sg:address":"Rue Grande 34-36",
    "sg:city":"Tellin",
    "sg:classifiers":[
        {
            "category":"Health Services",
            "subcategory":"Nursing And Care Facility",
            "type":"Services"
        }
    ],
    "sg:phone":"+32 84 36 67 44",
    "sg:postcode":"6927",
    "sg:province":"Luxembourg",
    "sg:tags":[
        "home",
        "rest"
    ],
    "wof:name":"Alouins (les) Sa",
    "wof:placetype":"venue"
},
  "geometry": {"coordinates":[5.2207717896,50.0816955566],"type":"Point"}
}