{
  "type": "Feature",
  "properties": {
    "addr:full":"Bijkhoevelaan 32c Wijnegem Antwerpen 2110",
    "addr:housenumber":"32c",
    "addr:postcode":"2110",
    "addr:street":"Bijkhoevelaan",
    "iso:country":"BE",
    "sg:address":"Bijkhoevelaan 32c",
    "sg:city":"Wijnegem",
    "sg:orig_category":"Farmaceutische producten Gh",
    "sg:phone":"+32 3 326 23 23",
    "sg:postcode":"2110",
    "sg:province":"Antwerpen",
    "wof:name":"Toshiba Medical Systems",
    "wof:placetype":"venue"
},
  "geometry": {"coordinates":[4.4951272011,51.2307815552],"type":"Point"}
}