{
  "type": "Feature",
  "properties": {
    "iso:country":"BE",
    "sg:address":"Ettenhoven 1",
    "sg:city":"Stabroek",
    "sg:orig_category":"Eleveurs de bovins",
    "sg:phone":"+32 3 665 36 57",
    "sg:postcode":"2940",
    "sg:province":"Antwerpen",
    "wof:name":"August Van Wallendael",
    "wof:placetype":"venue"
},
  "geometry": {"coordinates":[4.3770298958,51.3224411011],"type":"Point"}
}