{
  "type": "Feature",
  "properties": {
    "iso:country":"BE",
    "sg:address":"Boulevard Charlemagne 1",
    "sg:city":"Bruxelles",
    "sg:orig_category":"Foto-uitrusting Fotografen and fotostudio's Sportterreinen and installaties behalve sportcentra Tele",
    "sg:phone":"+32 2 285 09 27",
    "sg:postcode":"1041",
    "wof:name":"Positif Les Ann\u00c9es Lumi\u00c8res",
    "wof:placetype":"venue"
},
  "geometry": {"coordinates":[4.3823270798,50.8445777893],"type":"Point"}
}