{
  "type": "Feature",
  "properties": {
    "addr:full":"Rue Joseph Wauters 89 Binche Hainaut 7134",
    "addr:housenumber":"89",
    "addr:postcode":"7134",
    "addr:street":"Rue Joseph Wauters",
    "iso:country":"BE",
    "sg:address":"Rue Joseph Wauters 89",
    "sg:city":"Binche",
    "sg:orig_category":"Installatie van houten of kunststof schrijnwerk",
    "sg:phone":"+32 64 34 07 97",
    "sg:postcode":"7134",
    "sg:province":"Hainaut",
    "wof:name":"R\u00c9tro-style",
    "wof:placetype":"venue"
},
  "geometry": {"coordinates":[4.1804261208,50.4301452637],"type":"Point"}
}