{
  "type": "Feature",
  "properties": {
    "iso:country":"BE",
    "sg:address":"Ottr\u00e9 19",
    "sg:city":"Vielsalm (bihain)",
    "sg:classifiers":[
        {
            "category":"Real Estate",
            "subcategory":"Real Estate Services",
            "type":"Services"
        }
    ],
    "sg:phone":"+32 80 41 87 52",
    "sg:postcode":"6690",
    "sg:province":"Luxembourg",
    "wof:name":"Cimoroy",
    "wof:placetype":"venue"
},
  "geometry": {"coordinates":[5.8352618217,50.2487449646],"type":"Point"}
}