{
  "type": "Feature",
  "properties": {
    "iso:country":"BE",
    "sg:address":"Zwijnaardsesteenweg 61",
    "sg:city":"Merelbeke",
    "sg:classifiers":[
        {
            "category":"Retail",
            "subcategory":"Auto Repair",
            "type":"Services"
        }
    ],
    "sg:phone":"+32 9 230 64 11",
    "sg:postcode":"9820",
    "sg:province":"Oost-Vlaanderen",
    "sg:tags":[
        "garage"
    ],
    "wof:name":"Dhont Gracien En Zonen Bvba",
    "wof:placetype":"venue"
},
  "geometry": {"coordinates":[3.7427079678,50.9978256226],"type":"Point"}
}