{
  "type": "Feature",
  "properties": {
    "addr:full":"Grimbergsesteenweg 55 Zemst (eppegem) Vlaams-Brabant 1980",
    "addr:housenumber":"55",
    "addr:postcode":"1980",
    "addr:street":"Grimbergsesteenweg",
    "iso:country":"BE",
    "sg:address":"Grimbergsesteenweg 55",
    "sg:city":"Zemst (eppegem)",
    "sg:classifiers":[
        {
            "category":"Building & Trades",
            "subcategory":"Plumbing",
            "type":"Services"
        }
    ],
    "sg:phone":"+32 2 538 51 46",
    "sg:postcode":"1980",
    "sg:province":"Vlaams-Brabant",
    "sg:tags":[
        "contractor"
    ],
    "wof:name":"Egp",
    "wof:placetype":"venue"
},
  "geometry": {"coordinates":[4.451543808,50.9609985352],"type":"Point"}
}