{
  "type": "Feature",
  "properties": {
    "addr:full":"Rue Alphonse Hottat 16b10 Elsene Bruxelles-Capitale 1050",
    "addr:housenumber":"16b10",
    "addr:postcode":"1050",
    "addr:street":"Rue Alphonse Hottat",
    "iso:country":"BE",
    "sg:address":"Rue Alphonse Hottat 16b10",
    "sg:city":"Elsene",
    "sg:orig_category":"Boekhouders Diverse bedrijfsbeheeradviesbureaus",
    "sg:phone":"+32 2 644 38 82",
    "sg:postcode":"1050",
    "sg:province":"Bruxelles-Capitale",
    "wof:name":"Carbonez Olivier",
    "wof:placetype":"venue"
},
  "geometry": {"coordinates":[4.3787879944,50.8282279968],"type":"Point"}
}