{
  "type": "Feature",
  "properties": {
    "iso:country":"BE",
    "sg:address":"Dr\u00c8ve Ch\u00c2teau De Motte 1",
    "sg:city":"Genappe",
    "sg:orig_category":"Reclamebureaus",
    "sg:phone":"+32 10 61 49 22",
    "sg:postcode":"1470",
    "sg:province":"Brabant Wallon",
    "wof:name":"Bureau Bernard Bertrude",
    "wof:placetype":"venue"
},
  "geometry": {"coordinates":[4.5310969353,50.6370353699],"type":"Point"}
}