{
  "type": "Feature",
  "properties": {
    "addr:full":"Verviers Li\u00e8ge 4800",
    "addr:postcode":"4800",
    "iso:country":"BE",
    "sg:city":"Verviers",
    "sg:classifiers":[
        {
            "category":"Building & Trades",
            "subcategory":"Locksmith",
            "type":"Services"
        }
    ],
    "sg:phone":"+32 495 10 62 91",
    "sg:postcode":"4800",
    "sg:province":"Li\u00e8ge",
    "sg:tags":[
        "lock",
        "key"
    ],
    "wof:name":"Serrurier Beck",
    "wof:placetype":"venue"
},
  "geometry": {"coordinates":[5.8594508171,50.5917663574],"type":"Point"}
}