{
  "type": "Feature",
  "properties": {
    "iso:country":"BE",
    "sg:address":"Luchthavenlaan 29",
    "sg:city":"Vilvoorde",
    "sg:orig_category":"Onderdelen and accessoires voor auto's",
    "sg:phone":"+32 2 251 25 27",
    "sg:postcode":"1800",
    "sg:province":"Vlaams-Brabant",
    "wof:name":"Amret",
    "wof:placetype":"venue"
},
  "geometry": {"coordinates":[4.4425902367,50.9230270386],"type":"Point"}
}