{
  "type": "Feature",
  "properties": {
    "iso:country":"BE",
    "sg:address":"Deinsesteenweg 21",
    "sg:city":"Tielt",
    "sg:orig_category":"Voertuigen",
    "sg:phone":"+32 51 40 03 20",
    "sg:postcode":"8700",
    "sg:province":"West-Vlaanderen",
    "wof:name":"Garage Vande Vijvere",
    "wof:placetype":"venue"
},
  "geometry": {"coordinates":[3.3582770824,50.9965057373],"type":"Point"}
}