{
  "type": "Feature",
  "properties": {
    "addr:full":"Maalse Steenweg 90 Brugge West-Vlaanderen 8310",
    "addr:housenumber":"90",
    "addr:postcode":"8310",
    "addr:street":"Maalse Steenweg",
    "iso:country":"BE",
    "sg:address":"Maalse Steenweg 90",
    "sg:city":"Brugge",
    "sg:classifiers":[
        {
            "category":"Insurance",
            "subcategory":"Life Insurance",
            "type":"Services"
        }
    ],
    "sg:phone":"+32 50 37 47 95",
    "sg:postcode":"8310",
    "sg:province":"West-Vlaanderen",
    "sg:tags":[
        "assurance"
    ],
    "wof:name":"Fabian Leysen",
    "wof:placetype":"venue"
},
  "geometry": {"coordinates":[3.2459740639,51.2106285095],"type":"Point"}
}