{
  "type": "Feature",
  "properties": {
    "addr:full":"Boomsesteenweg 400 Antwerpen (wilrijk) Antwerpen 2610",
    "addr:housenumber":"400",
    "addr:postcode":"2610",
    "addr:street":"Boomsesteenweg;Antwerpen",
    "iso:country":"BE",
    "sg:address":"Boomsesteenweg 400",
    "sg:city":"Antwerpen (wilrijk)",
    "sg:classifiers":[
        {
            "category":"Retail",
            "subcategory":"Auto Rental",
            "type":"Services"
        }
    ],
    "sg:phone":"+32 3 828 80 80",
    "sg:postcode":"2610",
    "sg:province":"Antwerpen",
    "sg:tags":[
        "van",
        "hire",
        "-",
        "truck"
    ],
    "wof:name":"Dockx Nv",
    "wof:placetype":"venue"
},
  "geometry": {"coordinates":[4.3946051598,51.1691131592],"type":"Point"}
}