{
  "type": "Feature",
  "properties": {
    "addr:full":"Bullange 310 B\u00dcllingen/bullange Li\u00e8ge 4760",
    "addr:housenumber":"310",
    "addr:postcode":"4760",
    "addr:street":"Bullange",
    "iso:country":"BE",
    "sg:address":"Bullange 310",
    "sg:city":"B\u00dcllingen/bullange",
    "sg:orig_category":"Installation \u00e9lectrique r\u00e9sidentielle",
    "sg:phone":"+32 80 64 79 67",
    "sg:postcode":"4760",
    "sg:province":"Li\u00e8ge",
    "wof:name":"Fe. Genten",
    "wof:placetype":"venue"
},
  "geometry": {"coordinates":[6.304910183,50.4083137512],"type":"Point"}
}