{
  "type": "Feature",
  "properties": {
    "iso:country":"BE",
    "sg:address":"Gasthuisstraat 10",
    "sg:city":"Turnhout",
    "sg:classifiers":[
        {
            "category":"Restaurant",
            "type":"Food & Drink"
        }
    ],
    "sg:phone":"+32 14 41 03 77",
    "sg:postcode":"2300",
    "sg:province":"Antwerpen",
    "wof:name":"La Cantina",
    "wof:placetype":"venue"
},
  "geometry": {"coordinates":[4.947368145,51.3225822449],"type":"Point"}
}