{
  "type": "Feature",
  "properties": {
    "iso:country":"BE",
    "sg:address":"Chauss\u00c9e De Wavre 1378",
    "sg:city":"Oudergem/auderghem",
    "sg:orig_category":"Pi\u00e8ces and accessoires de v\u00e9hicules automobiles Entretien and r\u00e9parations de voitures",
    "sg:phone":"+32 2 660 00 62",
    "sg:postcode":"1160",
    "sg:province":"Bruxelles-Capitale",
    "wof:name":"Garage Vander Plaetsen",
    "wof:placetype":"venue"
},
  "geometry": {"coordinates":[4.4143028259,50.8194007874],"type":"Point"}
}