{
  "type": "Feature",
  "properties": {
    "addr:full":"Rue De La Brasserie 12 Ath Hainaut 7812",
    "addr:housenumber":"12",
    "addr:postcode":"7812",
    "addr:street":"Rue De La Brasserie",
    "iso:country":"BE",
    "sg:address":"Rue De La Brasserie 12",
    "sg:city":"Ath",
    "sg:orig_category":"Banques and organismes de cr\u00e9dit",
    "sg:phone":"+32 68 28 54 32",
    "sg:postcode":"7812",
    "sg:province":"Hainaut",
    "wof:name":"Dexia",
    "wof:placetype":"venue"
},
  "geometry": {"coordinates":[3.7031350136,50.6253395081],"type":"Point"}
}