{
  "type": "Feature",
  "properties": {
    "iso:country":"BE",
    "sg:address":"Chauss\u00c9e De Boondael 152",
    "sg:city":"Elsene/ixelles",
    "sg:orig_category":"Location de mat\u00e9riel pour banquets and \u00e9v\u00e9nements. V\u00eatements, chaussures and accessoires Location d'",
    "sg:phone":"+32 2 640 41 40",
    "sg:postcode":"1050",
    "sg:province":"Bruxelles-Capitale",
    "wof:name":"Michel Regnier",
    "wof:placetype":"venue"
},
  "geometry": {"coordinates":[4.378554821,50.8234291077],"type":"Point"}
}