{
  "type": "Feature",
  "properties": {
    "iso:country":"BE",
    "sg:address":"Rue De La Burdinale 20",
    "sg:city":"Burdinne",
    "sg:orig_category":"V\u00e9t\u00e9rinaires",
    "sg:phone":"+32 85 71 11 99",
    "sg:postcode":"4210",
    "sg:province":"Li\u00e8ge",
    "wof:name":"Bernard Depry",
    "wof:placetype":"venue"
},
  "geometry": {"coordinates":[5.0810618401,50.5829467773],"type":"Point"}
}