{
  "type": "Feature",
  "properties": {
    "addr:full":"Hoeledensebaan 159 Kortenaken Vlaams-Brabant 3471",
    "addr:housenumber":"159",
    "addr:postcode":"3471",
    "iso:country":"BE",
    "sg:address":"Hoeledensebaan 159",
    "sg:city":"Kortenaken",
    "sg:orig_category":"Producteurs de fruits",
    "sg:phone":"+32 16 77 78 19",
    "sg:postcode":"3471",
    "sg:province":"Vlaams-Brabant",
    "wof:name":"Dirk Wouters",
    "wof:placetype":"venue"
},
  "geometry": {"coordinates":[4.9962301254,50.8731689453],"type":"Point"}
}