{
  "type": "Feature",
  "properties": {
    "addr:full":"Rue Ferrer 39 Manage Hainaut 7170",
    "addr:housenumber":"39",
    "addr:postcode":"7170",
    "addr:street":"Rue Ferrer",
    "iso:country":"BE",
    "sg:address":"Rue Ferrer 39",
    "sg:city":"Manage",
    "sg:orig_category":"Kapsalons",
    "sg:phone":"+32 64 22 82 97",
    "sg:postcode":"7170",
    "sg:province":"Hainaut",
    "wof:name":"Coiffure Danielle",
    "wof:placetype":"venue"
},
  "geometry": {"coordinates":[4.2392029762,50.4767189026],"type":"Point"}
}