{
  "type": "Feature",
  "properties": {
    "iso:country":"BE",
    "sg:address":"Verenigde-natieslaan 9",
    "sg:city":"Oostende",
    "sg:orig_category":"Woningbouw",
    "sg:phone":"+32 59 50 01 69",
    "sg:postcode":"8400",
    "sg:province":"West-Vlaanderen",
    "wof:name":"Bouwonderneming Declerck",
    "wof:placetype":"venue"
},
  "geometry": {"coordinates":[2.9175000191,51.2226295471],"type":"Point"}
}