{
  "type": "Feature",
  "properties": {
    "iso:country":"BE",
    "sg:address":"Hoekstraat 83",
    "sg:city":"Overpelt",
    "sg:classifiers":[
        {
            "category":"Real Estate",
            "subcategory":"Surveying",
            "type":"Services"
        }
    ],
    "sg:phone":"+32 11 66 39 59",
    "sg:postcode":"3900",
    "sg:province":"Limburg",
    "sg:tags":[
        "surveyor",
        "land"
    ],
    "wof:name":"Dewitz V",
    "wof:placetype":"venue"
},
  "geometry": {"coordinates":[5.4173221588,51.2280235291],"type":"Point"}
}