{
  "type": "Feature",
  "properties": {
    "addr:full":"Neerhofstraat 48 Wevelgem West-Vlaanderen 8560",
    "addr:housenumber":"48",
    "addr:postcode":"8560",
    "addr:street":"Neerhofstraat",
    "iso:country":"BE",
    "sg:address":"Neerhofstraat 48",
    "sg:city":"Wevelgem",
    "sg:classifiers":[
        {
            "category":"Food & Beverages",
            "subcategory":"Groceries & Convenience Stores",
            "type":"Retail Goods"
        }
    ],
    "sg:phone":"+32 56 40 25 62",
    "sg:postcode":"8560",
    "sg:province":"West-Vlaanderen",
    "sg:tags":[
        "grocer"
    ],
    "wof:name":"Neerhof",
    "wof:placetype":"venue"
},
  "geometry": {"coordinates":[3.1858398914,50.8137931824],"type":"Point"}
}