{
  "type": "Feature",
  "properties": {
    "iso:country":"BE",
    "sg:address":"Rue Du Sud 43",
    "sg:city":"Boussu",
    "sg:orig_category":"Fabrication and montage de mobilier",
    "sg:phone":"+32 65 63 39 62",
    "sg:postcode":"7300",
    "sg:province":"Hainaut",
    "wof:name":"Design Interieurs",
    "wof:placetype":"venue"
},
  "geometry": {"coordinates":[3.7824039459,50.4096298218],"type":"Point"}
}