{
  "type": "Feature",
  "properties": {
    "iso:country":"BE",
    "sg:address":"Generaal Wahislaan 228",
    "sg:city":"Schaarbeek/schaerbeek",
    "sg:orig_category":"Kapsalons",
    "sg:phone":"+32 2 705 44 78",
    "sg:postcode":"1030",
    "sg:province":"Bruxelles-Capitale",
    "wof:name":"Coiffure R. & G.",
    "wof:placetype":"venue"
},
  "geometry": {"coordinates":[4.3982329369,50.8567428589],"type":"Point"}
}