{
  "type": "Feature",
  "properties": {
    "iso:country":"BE",
    "sg:address":"Rue De La Station 123",
    "sg:city":"Soignies",
    "sg:classifiers":[
        {
            "category":"Health Services",
            "subcategory":"Health Practitioner",
            "type":"Services"
        }
    ],
    "sg:phone":"+32 2 395 77 40",
    "sg:postcode":"7060",
    "sg:province":"Hainaut",
    "sg:tags":[
        "dietitian"
    ],
    "wof:name":"Kleensang I",
    "wof:placetype":"venue"
},
  "geometry": {"coordinates":[4.0675702095,50.5732040405],"type":"Point"}
}