{
  "type": "Feature",
  "properties": {
    "addr:full":"Parc Ind.-ch\u00c9e De Wavre 1 Perwez Brabant Wallon 1360",
    "addr:housenumber":"1",
    "addr:postcode":"1360",
    "iso:country":"BE",
    "sg:address":"Parc Ind.-ch\u00c9e De Wavre 1",
    "sg:city":"Perwez",
    "sg:orig_category":"Journaux. Librairies",
    "sg:phone":"+32 81 65 82 32",
    "sg:postcode":"1360",
    "sg:province":"Brabant Wallon",
    "wof:name":"Apostrophe Perwez",
    "wof:placetype":"venue"
},
  "geometry": {"coordinates":[4.8103327751,50.6256523132],"type":"Point"}
}