{
  "type": "Feature",
  "properties": {
    "iso:country":"BE",
    "sg:address":"Houwaartseberg 193bb",
    "sg:city":"Tielt-winge",
    "sg:orig_category":"M\u00e9decins and sp\u00e9cialistes",
    "sg:phone":"+32 16 63 36 66",
    "sg:postcode":"3390",
    "sg:province":"Vlaams-Brabant",
    "wof:name":"Anne-marie Joniaux",
    "wof:placetype":"venue"
},
  "geometry": {"coordinates":[4.8655600548,50.9444198608],"type":"Point"}
}