{
  "type": "Feature",
  "properties": {
    "iso:country":"BE",
    "sg:address":"Place Sainte-marguerite",
    "sg:city":"Rochefort (jemelle)",
    "sg:classifiers":[
        {
            "category":"Education",
            "subcategory":"School",
            "type":"Public Place"
        }
    ],
    "sg:phone":"+32 84 21 19 91",
    "sg:postcode":"5580",
    "sg:province":"Namur",
    "sg:tags":[
        "primary"
    ],
    "wof:name":"Ecole Communale",
    "wof:placetype":"venue"
},
  "geometry": {"coordinates":[5.2621250153,50.1626815796],"type":"Point"}
}