{
  "type": "Feature",
  "properties": {
    "iso:country":"BE",
    "sg:address":"Rue De L'industrie 1ba",
    "sg:city":"Bernissart",
    "sg:orig_category":"Schoonmaakbedrijven and ongediertebestrijding Woningbouw",
    "sg:phone":"+32 69 59 04 59",
    "sg:postcode":"7321",
    "sg:province":"Hainaut",
    "wof:name":"Fusiref",
    "wof:placetype":"venue"
},
  "geometry": {"coordinates":[3.6999359131,50.4838676453],"type":"Point"}
}