{
  "type": "Feature",
  "properties": {
    "addr:full":"Brugsesteenweg 340 Roeselare West-Vlaanderen 8800",
    "addr:housenumber":"340",
    "addr:postcode":"8800",
    "addr:street":"Brugsesteenweg",
    "iso:country":"BE",
    "sg:address":"Brugsesteenweg 340",
    "sg:city":"Roeselare",
    "sg:classifiers":[
        {
            "category":"Autos & Motor Vehicles",
            "subcategory":"Fuel & Gas Station",
            "type":"Retail Goods"
        }
    ],
    "sg:phone":"+32 51 24 81 50",
    "sg:postcode":"8800",
    "sg:province":"West-Vlaanderen",
    "wof:name":"Deal",
    "wof:placetype":"venue"
},
  "geometry": {"coordinates":[3.1206889153,50.965587616],"type":"Point"}
}