{
  "type": "Feature",
  "properties": {
    "iso:country":"BE",
    "sg:address":"Rue D'anthisnes 8",
    "sg:city":"Li\u00c8ge",
    "sg:classifiers":[
        {
            "category":"Taxi",
            "type":"Transportation"
        }
    ],
    "sg:phone":"+32 4 253 44 62",
    "sg:postcode":"4000",
    "sg:province":"Li\u00e8ge",
    "wof:name":"Marc Vancleve",
    "wof:placetype":"venue"
},
  "geometry": {"coordinates":[5.5567650795,50.611530304],"type":"Point"}
}