{
  "type": "Feature",
  "properties": {
    "iso:country":"BE",
    "sg:address":"Dr\u00e8ve De Nivelles 48",
    "sg:city":"Bruxelles (woluwe-saint-pierre)",
    "sg:classifiers":[
        {
            "category":"Professional",
            "subcategory":"Art Services",
            "type":"Services"
        }
    ],
    "sg:phone":"+32 2 770 89 15",
    "sg:postcode":"1150",
    "sg:province":"Bruxelles-Capitale",
    "sg:tags":[
        "realization",
        "audio-visual"
    ],
    "wof:name":"Synchro 2000",
    "wof:placetype":"venue"
},
  "geometry": {"coordinates":[4.4156727791,50.8289909363],"type":"Point"}
}