{
  "type": "Feature",
  "properties": {
    "addr:full":"Kortrijksesteenweg 1210 Gent (sint-denijs-westrem - Afsnee) Oost-Vlaanderen 9051",
    "addr:postcode":"1210;9051",
    "addr:street":"Kortrijksesteenweg",
    "iso:country":"BE",
    "sg:address":"Kortrijksesteenweg 1210",
    "sg:city":"Gent (sint-denijs-westrem - Afsnee)",
    "sg:classifiers":[
        {
            "category":"Food & Beverages",
            "subcategory":"Meat & Fish",
            "type":"Retail Goods"
        }
    ],
    "sg:phone":"+32 9 220 28 28",
    "sg:postcode":"9051",
    "sg:province":"Oost-Vlaanderen",
    "sg:tags":[
        "bedspread",
        "blanket",
        "-"
    ],
    "wof:name":"Top Sleep Bvba",
    "wof:placetype":"venue"
},
  "geometry": {"coordinates":[3.6514649391,51.0148277283],"type":"Point"}
}