{
  "type": "Feature",
  "properties": {
    "iso:country":"BE",
    "sg:address":"Albert Panisstraat 4 Box 101",
    "sg:city":"Beveren (beveren-waas)",
    "sg:classifiers":[
        {
            "category":"Professional",
            "type":"Services"
        }
    ],
    "sg:phone":"+32 3 570 01 30",
    "sg:postcode":"9120",
    "sg:province":"Oost-Vlaanderen",
    "sg:tags":[
        "forwarding",
        "agency"
    ],
    "wof:name":"Euro Nordic Belgium Logist-x Nv",
    "wof:placetype":"venue"
},
  "geometry": {"coordinates":[4.2487530708,51.2095527649],"type":"Point"}
}