{
  "type": "Feature",
  "properties": {
    "addr:full":"Rue Archim\u00e8de 93 Bruxelles Bruxelles-Capitale 1000",
    "addr:housenumber":"93",
    "addr:postcode":"1000",
    "addr:street":"Rue Archime\u0300De",
    "iso:country":"BE",
    "sg:address":"Rue Archim\u00e8de 93",
    "sg:city":"Bruxelles",
    "sg:classifiers":[
        {
            "category":"Freight",
            "type":"Transportation"
        }
    ],
    "sg:phone":"+32 2 732 43 48",
    "sg:postcode":"1000",
    "sg:province":"Bruxelles-Capitale",
    "sg:tags":[
        "-",
        "transport"
    ],
    "wof:name":"Venus Belgium",
    "wof:placetype":"venue"
},
  "geometry": {"coordinates":[4.3838801384,50.846031189],"type":"Point"}
}