{
  "type": "Feature",
  "properties": {
    "iso:country":"BE",
    "sg:address":"Misseweg 46",
    "sg:city":"Balen",
    "sg:classifiers":[
        {
            "category":"Food & Beverages",
            "subcategory":"Specialty",
            "type":"Retail Goods"
        }
    ],
    "sg:phone":"+32 14 81 42 43",
    "sg:postcode":"2490",
    "sg:province":"Antwerpen",
    "sg:tags":[
        "sinking",
        "groundwater"
    ],
    "wof:name":"Winters J",
    "wof:placetype":"venue"
},
  "geometry": {"coordinates":[5.1867980957,51.1740684509],"type":"Point"}
}