{
  "type": "Feature",
  "properties": {
    "addr:full":"Kapelstraat 34bb Lummen Limburg 3560",
    "addr:housenumber":"34bb",
    "addr:postcode":"3560",
    "addr:street":"Kapelstraat",
    "iso:country":"BE",
    "sg:address":"Kapelstraat 34bb",
    "sg:city":"Lummen",
    "sg:orig_category":"Groententeelt",
    "sg:phone":"+32 13 44 49 97",
    "sg:postcode":"3560",
    "sg:province":"Limburg",
    "wof:name":"Gert Reijnders",
    "wof:placetype":"venue"
},
  "geometry": {"coordinates":[5.1376709938,50.9730567932],"type":"Point"}
}