{
  "type": "Feature",
  "properties": {
    "iso:country":"BE",
    "sg:address":"Engsbergseweg 173",
    "sg:city":"Tessenderlo",
    "sg:orig_category":"Herstellingen and onderhoud van auto's Voertuigen",
    "sg:phone":"+32 13 77 69 85",
    "sg:postcode":"3980",
    "sg:province":"Limburg",
    "wof:name":"Van Haelst Gust",
    "wof:placetype":"venue"
},
  "geometry": {"coordinates":[5.0283551216,51.0254211426],"type":"Point"}
}