{
  "type": "Feature",
  "properties": {
    "addr:full":"Grote Baan 228 Haacht (wespelaar) Vlaams-Brabant 3150",
    "addr:housenumber":"228",
    "addr:postcode":"3150",
    "addr:street":"Grote Baan",
    "iso:country":"BE",
    "sg:address":"Grote Baan 228",
    "sg:city":"Haacht (wespelaar)",
    "sg:classifiers":[
        {
            "category":"Building & Trades",
            "subcategory":"Landscaping Services",
            "type":"Services"
        }
    ],
    "sg:phone":"+32 16 60 71 63",
    "sg:postcode":"3150",
    "sg:province":"Vlaams-Brabant",
    "sg:tags":[
        "gardening",
        "garden",
        "maintenance"
    ],
    "wof:name":"Coosemans K",
    "wof:placetype":"venue"
},
  "geometry": {"coordinates":[4.6180410385,50.9613037109],"type":"Point"}
}