{
  "type": "Feature",
  "properties": {
    "addr:full":"Avenue De La Ram\u00c9e 17 Ukkel/uccle Bruxelles-Capitale 1180",
    "addr:housenumber":"17",
    "addr:postcode":"1180",
    "addr:street":"Avenue De La Rame\u0301E;/",
    "iso:country":"BE",
    "sg:address":"Avenue De La Ram\u00c9e 17",
    "sg:city":"Ukkel/uccle",
    "sg:classifiers":[
        {
            "category":"Insurance",
            "subcategory":"Life Insurance",
            "type":"Services"
        }
    ],
    "sg:phone":"+32 2 345 95 54",
    "sg:postcode":"1180",
    "sg:province":"Bruxelles-Capitale",
    "sg:tags":[
        "assurance"
    ],
    "wof:name":"L. Depauw",
    "wof:placetype":"venue"
},
  "geometry": {"coordinates":[4.3444361687,50.8055076599],"type":"Point"}
}