{
  "type": "Feature",
  "properties": {
    "iso:country":"BE",
    "sg:address":"Rue Piraumont 49",
    "sg:city":"Villers-la-ville",
    "sg:orig_category":"Air conditionn\u00e9 and ventilation. Plomberie, chauffage and installations sanitaires",
    "sg:phone":"+32 71 85 03 42",
    "sg:postcode":"1495",
    "sg:province":"Brabant Wallon",
    "wof:name":"Alta Services",
    "wof:placetype":"venue"
},
  "geometry": {"coordinates":[4.4730992317,50.5573501587],"type":"Point"}
}