{
  "type": "Feature",
  "properties": {
    "iso:country":"BE",
    "sg:address":"Kongostraat 2",
    "sg:city":"Gent",
    "sg:classifiers":[
        {
            "category":"Cafe",
            "type":"Food & Drink"
        }
    ],
    "sg:phone":"+32 9 233 55 20",
    "sg:postcode":"9000",
    "sg:province":"Oost-Vlaanderen",
    "sg:tags":[
        "caf\u00e9s"
    ],
    "wof:name":"Boudjem Internat. Trading",
    "wof:placetype":"venue"
},
  "geometry": {"coordinates":[3.7304890156,51.0601043701],"type":"Point"}
}