{
  "type": "Feature",
  "properties": {
    "addr:full":"Rue Haute 91 Bruxelles Bruxelles-Capitale 1000",
    "addr:housenumber":"91",
    "addr:postcode":"1000",
    "addr:street":"Rue Haute",
    "iso:country":"BE",
    "sg:address":"Rue Haute 91",
    "sg:city":"Bruxelles",
    "sg:classifiers":[
        {
            "category":"Home & Garden",
            "subcategory":"Home Furnishings",
            "type":"Retail Goods"
        }
    ],
    "sg:phone":"+32 2 511 10 18",
    "sg:postcode":"1000",
    "sg:province":"Bruxelles-Capitale",
    "sg:tags":[
        "-",
        "furniture"
    ],
    "wof:name":"New De Wolf Nv",
    "wof:placetype":"venue"
},
  "geometry": {"coordinates":[4.3506879807,50.8397102356],"type":"Point"}
}