{
  "type": "Feature",
  "properties": {
    "addr:full":"Rue De Menin 406 Mouscron Hainaut 7700",
    "addr:housenumber":"406",
    "addr:postcode":"7700",
    "addr:street":"Rue De Menin",
    "iso:country":"BE",
    "sg:address":"Rue De Menin 406",
    "sg:city":"Mouscron",
    "sg:classifiers":[
        {
            "category":"Education",
            "subcategory":"Music School",
            "type":"Public Place"
        }
    ],
    "sg:phone":"+32 56 33 13 44",
    "sg:postcode":"7700",
    "sg:province":"Hainaut",
    "sg:tags":[
        "rental",
        "grandstand",
        "stage",
        "-",
        "mfg"
    ],
    "wof:name":"Touartube-tat Sa",
    "wof:placetype":"venue"
},
  "geometry": {"coordinates":[3.2036919594,50.7531661987],"type":"Point"}
}