{
  "type": "Feature",
  "properties": {
    "addr:full":"Rue Ten-eycken 5 Plombieres Li\u00e8ge 4850",
    "addr:housenumber":"5",
    "addr:postcode":"4850",
    "addr:street":"Rue Ten-Eycken",
    "iso:country":"BE",
    "sg:address":"Rue Ten-eycken 5",
    "sg:city":"Plombieres",
    "sg:orig_category":"Enseignement maternel and primaire",
    "sg:phone":"+32 87 78 44 80",
    "sg:postcode":"4850",
    "sg:province":"Li\u00e8ge",
    "wof:name":"Ecole Fond. Communale",
    "wof:placetype":"venue"
},
  "geometry": {"coordinates":[5.9573187828,50.7243499756],"type":"Point"}
}