{
  "type": "Feature",
  "properties": {
    "iso:country":"BE",
    "sg:address":"Grote Markt 7b101",
    "sg:city":"Sint-truiden",
    "sg:orig_category":"RESTAURANTS: CAF\u00c9S",
    "sg:phone":"+32 11 68 20 29",
    "sg:postcode":"3800",
    "sg:province":"Limburg",
    "wof:name":"'t Hert",
    "wof:placetype":"venue"
},
  "geometry": {"coordinates":[5.1862120628,50.8150749207],"type":"Point"}
}