{
  "type": "Feature",
  "properties": {
    "addr:full":"Avenue Jean-fran\u00e7ois Leemans 20 Bruxelles (auderghem) Bruxelles-Capitale 1160",
    "addr:housenumber":"20",
    "addr:postcode":"1160",
    "addr:street":"Avenue Jean-Franc\u0327Ois Leemans",
    "iso:country":"BE",
    "sg:address":"Avenue Jean-fran\u00e7ois Leemans 20",
    "sg:city":"Bruxelles (auderghem)",
    "sg:classifiers":[
        {
            "category":"Building & Trades",
            "subcategory":"Construction",
            "type":"Services"
        }
    ],
    "sg:phone":"+32 2 660 97 56",
    "sg:postcode":"1160",
    "sg:province":"Bruxelles-Capitale",
    "sg:tags":[
        "surveyor",
        "-"
    ],
    "wof:name":"Christiaens W",
    "wof:placetype":"venue"
},
  "geometry": {"coordinates":[4.4329891205,50.8025512695],"type":"Point"}
}