{
  "type": "Feature",
  "properties": {
    "iso:country":"BE",
    "sg:address":"Route De Philippeville 57",
    "sg:city":"Charleroi",
    "sg:orig_category":"Fleurs and plantes",
    "sg:phone":"+32 71 43 99 72",
    "sg:postcode":"6010",
    "sg:province":"Hainaut",
    "wof:name":"La Maison Fleurie",
    "wof:placetype":"venue"
},
  "geometry": {"coordinates":[4.4588880539,50.3918266296],"type":"Point"}
}