{
  "type": "Feature",
  "properties": {
    "addr:full":"Frans Massystraat 24 Hasselt Limburg 3500",
    "addr:housenumber":"24",
    "addr:postcode":"3500",
    "addr:street":"Frans Massystraat",
    "iso:country":"BE",
    "sg:address":"Frans Massystraat 24",
    "sg:city":"Hasselt",
    "sg:orig_category":"Disneyland Paris. Agences de voyages",
    "sg:phone":"+32 11 22 23 45",
    "sg:postcode":"3500",
    "sg:province":"Limburg",
    "wof:name":"Ttc Hasselt",
    "wof:placetype":"venue"
},
  "geometry": {"coordinates":[5.3283691406,50.931312561],"type":"Point"}
}