{
  "type": "Feature",
  "properties": {
    "iso:country":"BE",
    "sg:address":"Rue De La Chapelle 11",
    "sg:city":"Florennes",
    "sg:orig_category":"M\u00e9decins and sp\u00e9cialistes",
    "sg:phone":"+32 71 61 55 15",
    "sg:postcode":"5620",
    "sg:province":"Namur",
    "wof:name":"V\u00c9ronique Rorive",
    "wof:placetype":"venue"
},
  "geometry": {"coordinates":[4.6066641808,50.2530441284],"type":"Point"}
}