{
  "type": "Feature",
  "properties": {
    "iso:country":"BE",
    "sg:address":"Golfweg 1",
    "sg:city":"Gent",
    "sg:orig_category":"Orphelinats. Instituts pour enfants en difficult\u00e9. Activit\u00e9s d\u00b4action sociale sans h\u00e9bergement",
    "sg:phone":"+32 9 222 73 76",
    "sg:postcode":"9000",
    "sg:province":"Oost-Vlaanderen",
    "wof:name":"Lionshulp Gent",
    "wof:placetype":"venue"
},
  "geometry": {"coordinates":[3.7022120953,51.0418395996],"type":"Point"}
}