{
  "type": "Feature",
  "properties": {
    "iso:country":"BE",
    "sg:address":"Mechelsesteenweg 1149",
    "sg:city":"Winksele",
    "sg:orig_category":"Herstellingen and onderhoud van auto's Metaalafval, schrootrecyclage and sloperijen Voertuigen",
    "sg:phone":"+32 16 26 26 00",
    "sg:postcode":"3020",
    "sg:province":"Vlaams-Brabant",
    "wof:name":"Auto-moto Vermeulen",
    "wof:placetype":"venue"
},
  "geometry": {"coordinates":[4.6343431473,50.9289855957],"type":"Point"}
}