{
  "type": "Feature",
  "properties": {
    "addr:full":"Vlimmersendijk 34 Malle Antwerpen 2390",
    "addr:housenumber":"34",
    "addr:postcode":"2390",
    "addr:street":"Vlimmersendijk",
    "iso:country":"BE",
    "sg:address":"Vlimmersendijk 34",
    "sg:city":"Malle",
    "sg:orig_category":"Traitement and rev\u00eatement des m\u00e9taux",
    "sg:phone":"+32 3 312 16 28",
    "sg:postcode":"2390",
    "sg:province":"Antwerpen",
    "wof:name":"Verloy",
    "wof:placetype":"venue"
},
  "geometry": {"coordinates":[4.7648849487,51.2975082397],"type":"Point"}
}