{
  "type": "Feature",
  "properties": {
    "addr:full":"Sint-laureysplein 5 Hove Antwerpen 2540",
    "addr:housenumber":"5",
    "addr:postcode":"2540",
    "addr:street":"Sint-Laureysplein",
    "iso:country":"BE",
    "sg:address":"Sint-laureysplein 5",
    "sg:city":"Hove",
    "sg:orig_category":"Epiceries",
    "sg:phone":"+32 3 455 66 70",
    "sg:postcode":"2540",
    "sg:province":"Antwerpen",
    "wof:name":"Brandt Food",
    "wof:placetype":"venue"
},
  "geometry": {"coordinates":[4.4719018936,51.1542243958],"type":"Point"}
}