{
  "type": "Feature",
  "properties": {
    "iso:country":"BE",
    "sg:address":"Winterslagstraat 151",
    "sg:city":"Genk",
    "sg:orig_category":"Fotografen and fotostudio's",
    "sg:phone":"+32 89 38 01 16",
    "sg:postcode":"3600",
    "sg:province":"Limburg",
    "wof:name":"Leon Auwers",
    "wof:placetype":"venue"
},
  "geometry": {"coordinates":[5.5009441376,50.9735336304],"type":"Point"}
}