{
  "type": "Feature",
  "properties": {
    "addr:full":"Rue De Sart Dames Avelines 24 Les Bons Villers (frasnes-lez-gosselies) Hainaut 6210",
    "addr:housenumber":"24",
    "addr:postcode":"6210",
    "addr:street":"Rue De Sart Dames Avelines",
    "iso:country":"BE",
    "sg:address":"Rue De Sart Dames Avelines 24",
    "sg:city":"Les Bons Villers (frasnes-lez-gosselies)",
    "sg:classifiers":[
        {
            "category":"Wholesale",
            "subcategory":"Machinery & Supplies",
            "type":"Manufacturing & Wholesale Goods"
        }
    ],
    "sg:phone":"+32 71 85 17 94",
    "sg:postcode":"6210",
    "sg:province":"Hainaut",
    "sg:tags":[
        "agricultural",
        "tractor"
    ],
    "wof:name":"Quenon-bauwens Sprl",
    "wof:placetype":"venue"
},
  "geometry": {"coordinates":[4.4511561394,50.5378227234],"type":"Point"}
}