{
  "type": "Feature",
  "properties": {
    "iso:country":"BE",
    "sg:address":"Rue Julien Mullie 8",
    "sg:city":"Mouscron (dottignies)",
    "sg:classifiers":[
        {
            "category":"Bars & Pubs",
            "type":"Food & Drink"
        }
    ],
    "sg:phone":"+32 56 48 83 35",
    "sg:postcode":"7711",
    "sg:province":"Hainaut",
    "wof:name":"Metropole",
    "wof:placetype":"venue"
},
  "geometry": {"coordinates":[3.3034260273,50.7292861938],"type":"Point"}
}