{
  "type": "Feature",
  "properties": {
    "addr:full":"Rue Croix Andre 10 Nandrin Li\u00e8ge 4550",
    "addr:housenumber":"10",
    "addr:postcode":"4550",
    "addr:street":"Rue Croix Andre",
    "iso:country":"BE",
    "sg:address":"Rue Croix Andre 10",
    "sg:city":"Nandrin",
    "sg:classifiers":[
        {
            "category":"Professional",
            "subcategory":"Accounting & Tax Preparation",
            "type":"Services"
        }
    ],
    "sg:phone":"+32 4 371 58 10",
    "sg:postcode":"4550",
    "sg:province":"Li\u00e8ge",
    "sg:tags":[
        "bookkeeper"
    ],
    "wof:name":"Poulain G",
    "wof:placetype":"venue"
},
  "geometry": {"coordinates":[5.4463248253,50.5174102783],"type":"Point"}
}