{
  "type": "Feature",
  "properties": {
    "addr:full":"Nekkersputstraat 189 Gent Oost-Vlaanderen 9000",
    "addr:housenumber":"189",
    "addr:postcode":"9000",
    "addr:street":"Nekkersputstraat;Oost-Vlaanderen",
    "iso:country":"BE",
    "sg:address":"Nekkersputstraat 189",
    "sg:city":"Gent",
    "sg:orig_category":"Mat\u00e9riaux de construction Gr",
    "sg:phone":"+32 9 216 88 70",
    "sg:postcode":"9000",
    "sg:province":"Oost-Vlaanderen",
    "wof:name":"Oxyplast Belgium",
    "wof:placetype":"venue"
},
  "geometry": {"coordinates":[3.690392971,51.0608406067],"type":"Point"}
}