{
  "type": "Feature",
  "properties": {
    "iso:country":"BE",
    "sg:address":"J. Creytensstraat 4",
    "sg:city":"Beernem",
    "sg:classifiers":[
        {
            "category":"Cafe",
            "type":"Food & Drink"
        }
    ],
    "sg:phone":"+32 50 78 85 26",
    "sg:postcode":"8730",
    "sg:province":"West-Vlaanderen",
    "sg:tags":[
        "caf\u00e9s"
    ],
    "wof:name":"Parochiale Werken",
    "wof:placetype":"venue"
},
  "geometry": {"coordinates":[3.3382840157,51.169670105],"type":"Point"}
}