{
  "type": "Feature",
  "properties": {
    "iso:country":"BE",
    "sg:address":"Rue Ren\u00e9 Nicolas 37",
    "sg:city":"Musson",
    "sg:classifiers":[
        {
            "category":"Health Services",
            "subcategory":"Doctor",
            "type":"Services"
        }
    ],
    "sg:phone":"+32 63 67 81 42",
    "sg:postcode":"6750",
    "sg:province":"Luxembourg",
    "sg:tags":[
        "medicinephysicians",
        "surgeon"
    ],
    "wof:name":"Ambroise Vincent",
    "wof:placetype":"venue"
},
  "geometry": {"coordinates":[5.7098550797,49.559223175],"type":"Point"}
}