{
  "type": "Feature",
  "properties": {
    "addr:full":"Hogesteenweg 2 Grimbergen Vlaams-Brabant 1850",
    "addr:housenumber":"2",
    "addr:postcode":"1850",
    "addr:street":"Hogesteenweg",
    "iso:country":"BE",
    "sg:address":"Hogesteenweg 2",
    "sg:city":"Grimbergen",
    "sg:orig_category":"M\u00e9decins and sp\u00e9cialistes",
    "sg:phone":"+32 2 270 20 60",
    "sg:postcode":"1850",
    "sg:province":"Vlaams-Brabant",
    "wof:name":"Kristel Mertens",
    "wof:placetype":"venue"
},
  "geometry": {"coordinates":[4.3714680672,50.932975769],"type":"Point"}
}