{
  "type": "Feature",
  "properties": {
    "addr:full":"Rue De La Bataille-d'arlon 14 Arlon Luxembourg 6700",
    "addr:housenumber":"14",
    "addr:postcode":"6700",
    "addr:street":"Rue De La Bataille-D'Arlon",
    "iso:country":"BE",
    "sg:address":"Rue De La Bataille-d'arlon 14",
    "sg:city":"Arlon",
    "sg:classifiers":[
        {
            "category":"Social Services",
            "subcategory":"Child Care",
            "type":"Services"
        }
    ],
    "sg:phone":"+32 63 21 63 18",
    "sg:postcode":"6700",
    "sg:province":"Luxembourg",
    "sg:tags":[
        "baby",
        "nursery",
        "day",
        "sitting"
    ],
    "wof:name":"Ecole Buissonni\u00e8re (a L')",
    "wof:placetype":"venue"
},
  "geometry": {"coordinates":[5.7963199615,49.6770744324],"type":"Point"}
}