{
  "type": "Feature",
  "properties": {
    "addr:full":"Hoefsmidstraat 4 Olen Antwerpen 2250",
    "addr:housenumber":"4",
    "addr:postcode":"2250",
    "addr:street":"Hoefsmidstraat",
    "iso:country":"BE",
    "sg:address":"Hoefsmidstraat 4",
    "sg:city":"Olen",
    "sg:orig_category":"Banques and organismes de cr\u00e9dit",
    "sg:phone":"+32 14 21 45 94",
    "sg:postcode":"2250",
    "sg:province":"Antwerpen",
    "wof:name":"Groep Argenta",
    "wof:placetype":"venue"
},
  "geometry": {"coordinates":[4.8854842186,51.1594276428],"type":"Point"}
}