{
  "type": "Feature",
  "properties": {
    "addr:full":"Rue Du Grand Pont 8 Ath Hainaut 7800",
    "addr:housenumber":"8",
    "addr:postcode":"7800",
    "addr:street":"Rue Du Grand Pont",
    "iso:country":"BE",
    "sg:address":"Rue Du Grand Pont 8",
    "sg:city":"Ath",
    "sg:classifiers":[
        {
            "category":"Health Services",
            "subcategory":"Dentist",
            "type":"Services"
        }
    ],
    "sg:phone":"+32 68 28 19 33",
    "sg:postcode":"7800",
    "sg:province":"Hainaut",
    "wof:name":"Dhamen Alain",
    "wof:placetype":"venue"
},
  "geometry": {"coordinates":[3.7710659504,50.6263542175],"type":"Point"}
}