{
  "type": "Feature",
  "properties": {
    "addr:full":"Chauss\u00e9e De Jodoigne 29 Grez-doiceau Brabant Wallon 1390",
    "addr:housenumber":"29",
    "addr:postcode":"1390",
    "addr:street":"Chausse\u0301E De Jodoigne",
    "iso:country":"BE",
    "sg:address":"Chauss\u00e9e De Jodoigne 29",
    "sg:city":"Grez-doiceau",
    "sg:classifiers":[
        {
            "category":"Real Estate",
            "subcategory":"Real Estate Services",
            "type":"Services"
        }
    ],
    "sg:phone":"+32 10 68 18 90",
    "sg:postcode":"1390",
    "sg:province":"Brabant Wallon",
    "wof:name":"Modifa Sa",
    "wof:placetype":"venue"
},
  "geometry": {"coordinates":[4.6997938156,50.7379302979],"type":"Point"}
}