{
  "type": "Feature",
  "properties": {
    "iso:country":"BE",
    "sg:address":"Place Jules Mansart 6",
    "sg:city":"La Louviere",
    "sg:orig_category":"Reisbureaus",
    "sg:phone":"+32 64 28 35 35",
    "sg:postcode":"7100",
    "sg:province":"Hainaut",
    "wof:name":"Club Loisirs & Vacances",
    "wof:placetype":"venue"
},
  "geometry": {"coordinates":[4.1847500801,50.4744796753],"type":"Point"}
}