{
  "type": "Feature",
  "properties": {
    "iso:country":"BE",
    "sg:address":"Lauwstraat 31",
    "sg:city":"Gent",
    "sg:classifiers":[
        {
            "category":"Arena",
            "subcategory":"Sports Club",
            "type":"Entertainment"
        }
    ],
    "sg:phone":"+32 9 222 38 13",
    "sg:postcode":"9051",
    "sg:province":"Oost-Vlaanderen",
    "sg:tags":[
        "de"
    ],
    "wof:name":"Onder Ons",
    "wof:placetype":"venue"
},
  "geometry": {"coordinates":[3.6658489704,51.0229377747],"type":"Point"}
}