{
  "type": "Feature",
  "properties": {
    "iso:country":"BE",
    "sg:address":"Heistlaan 442",
    "sg:city":"Knokke-heist",
    "sg:orig_category":"Installation de menuiserie en bois and plastique",
    "sg:phone":"+32 50 51 37 96",
    "sg:postcode":"8300",
    "sg:province":"West-Vlaanderen",
    "wof:name":"Pottier Jean-pierre",
    "wof:placetype":"venue"
},
  "geometry": {"coordinates":[3.246958971,51.3150787354],"type":"Point"}
}