{
  "type": "Feature",
  "properties": {
    "addr:full":"Zeelaan 141 De Panne West-Vlaanderen 8660",
    "addr:housenumber":"141",
    "addr:postcode":"8660",
    "addr:street":"Zeelaan",
    "iso:country":"BE",
    "sg:address":"Zeelaan 141",
    "sg:city":"De Panne",
    "sg:orig_category":"Chaussures. Maroquinerie and articles de voyage",
    "sg:phone":"+32 58 42 19 84",
    "sg:postcode":"8660",
    "sg:province":"West-Vlaanderen",
    "wof:name":"Red Shoe",
    "wof:placetype":"venue"
},
  "geometry": {"coordinates":[2.5914111137,51.1020202637],"type":"Point"}
}