{
  "type": "Feature",
  "properties": {
    "iso:country":"BE",
    "sg:address":"Mechelbaan 681",
    "sg:city":"Putte",
    "sg:orig_category":"GROENTEN AND FRUIT Groenten and fruit Gh",
    "sg:phone":"+32 15 76 08 21",
    "sg:postcode":"2580",
    "sg:province":"Antwerpen",
    "wof:name":"Van Loock",
    "wof:placetype":"venue"
},
  "geometry": {"coordinates":[4.6029691696,51.0444946289],"type":"Point"}
}