{
  "type": "Feature",
  "properties": {
    "addr:full":"Eikenstraat 3 Hove Antwerpen 2540",
    "addr:housenumber":"3",
    "addr:postcode":"2540",
    "addr:street":"Eikenstraat",
    "iso:country":"BE",
    "sg:address":"Eikenstraat 3",
    "sg:city":"Hove",
    "sg:orig_category":"Non-Classified Establishments",
    "sg:phone":"+32 3 288 97 72",
    "sg:postcode":"2540",
    "sg:province":"Antwerpen",
    "wof:name":"Sels Chris-sanisel",
    "wof:placetype":"venue"
},
  "geometry": {"coordinates":[4.4620451927,51.1428909302],"type":"Point"}
}