{
  "type": "Feature",
  "properties": {
    "addr:full":"Halensebaan 23 Tielt-winge Vlaams-Brabant 3390",
    "addr:housenumber":"23",
    "addr:postcode":"3390",
    "addr:street":"Halensebaan",
    "iso:country":"BE",
    "sg:address":"Halensebaan 23",
    "sg:city":"Tielt-winge",
    "sg:orig_category":"Sportclubs",
    "sg:phone":"+32 16 63 27 41",
    "sg:postcode":"3390",
    "sg:province":"Vlaams-Brabant",
    "wof:name":"De Sterke Duif",
    "wof:placetype":"venue"
},
  "geometry": {"coordinates":[4.885653019,50.9085578918],"type":"Point"}
}