{
  "type": "Feature",
  "properties": {
    "addr:full":"Rue De Nivelles 31 Rixensart Brabant Wallon 1330",
    "addr:housenumber":"31",
    "addr:postcode":"1330",
    "addr:street":"Rue De Nivelles;Wallon",
    "iso:country":"BE",
    "sg:address":"Rue De Nivelles 31",
    "sg:city":"Rixensart",
    "sg:classifiers":[
        {
            "category":"Professional",
            "subcategory":"Engineering",
            "type":"Services"
        }
    ],
    "sg:phone":"+32 2 653 00 25",
    "sg:postcode":"1330",
    "sg:province":"Brabant Wallon",
    "sg:tags":[
        "technical",
        "equipment",
        "offices-"
    ],
    "wof:name":"Std Consulting",
    "wof:placetype":"venue"
},
  "geometry": {"coordinates":[4.5174298286,50.7022781372],"type":"Point"}
}