{
  "type": "Feature",
  "properties": {
    "iso:country":"BE",
    "sg:address":"Langenberg 18",
    "sg:city":"Kasterlee",
    "sg:orig_category":"V\u00e9t\u00e9rinaires",
    "sg:phone":"+32 14 55 18 80",
    "sg:postcode":"2460",
    "sg:province":"Antwerpen",
    "wof:name":"Dani\u00cbl Goovaerts",
    "wof:placetype":"venue"
},
  "geometry": {"coordinates":[4.9458122253,51.2192153931],"type":"Point"}
}