{
  "type": "Feature",
  "properties": {
    "addr:full":"Rue Pasteur 2 Charleroi Hainaut 6032",
    "addr:housenumber":"2",
    "addr:postcode":"6032",
    "addr:street":"Rue Pasteur;Hainaut",
    "iso:country":"BE",
    "sg:address":"Rue Pasteur 2",
    "sg:city":"Charleroi",
    "sg:classifiers":[
        {
            "category":"Cafe",
            "type":"Food & Drink"
        }
    ],
    "sg:phone":"+32 71 43 13 83",
    "sg:postcode":"6032",
    "sg:province":"Hainaut",
    "sg:tags":[
        "caf\u00e9s"
    ],
    "wof:name":"Caf\u00c9 Le Pasteur",
    "wof:placetype":"venue"
},
  "geometry": {"coordinates":[4.4085488319,50.3894538879],"type":"Point"}
}