{
  "type": "Feature",
  "properties": {
    "iso:country":"BE",
    "sg:address":"Jan Delvinlaan 98b99",
    "sg:city":"Gent",
    "sg:orig_category":"G\u00e2teaux, p\u00e2tisserie and biscuits Fab",
    "sg:phone":"+32 9 228 27 49",
    "sg:postcode":"9000",
    "sg:province":"Oost-Vlaanderen",
    "wof:name":"Biscuiterie Le Vesuve",
    "wof:placetype":"venue"
},
  "geometry": {"coordinates":[3.7496979237,51.0476989746],"type":"Point"}
}