{
  "type": "Feature",
  "properties": {
    "addr:full":"Rue Du Berceau 4 Binche (waudrez) Hainaut 7131",
    "addr:housenumber":"4",
    "addr:postcode":"7131",
    "addr:street":"Rue Du Berceau",
    "iso:country":"BE",
    "sg:address":"Rue Du Berceau 4",
    "sg:city":"Binche (waudrez)",
    "sg:classifiers":[
        {
            "category":"Health Services",
            "subcategory":"Health Practitioner",
            "type":"Services"
        }
    ],
    "sg:phone":"+32 64 33 58 51",
    "sg:postcode":"7131",
    "sg:province":"Hainaut",
    "sg:tags":[
        "psychologist"
    ],
    "wof:name":"Moreau J M",
    "wof:placetype":"venue"
},
  "geometry": {"coordinates":[4.1517601013,50.4148521423],"type":"Point"}
}