{
  "type": "Feature",
  "properties": {
    "addr:full":"Nieuwstraat 7 Geel Antwerpen 2440",
    "addr:housenumber":"7",
    "addr:postcode":"2440",
    "addr:street":"Nieuwstraat",
    "iso:country":"BE",
    "sg:address":"Nieuwstraat 7",
    "sg:city":"Geel",
    "sg:orig_category":"Articles de camping and de sport. V\u00eatements. Chaussures",
    "sg:phone":"+32 14 58 82 44",
    "sg:postcode":"2440",
    "sg:province":"Antwerpen",
    "wof:name":"Pm United Brands",
    "wof:placetype":"venue"
},
  "geometry": {"coordinates":[4.9915671349,51.1625328064],"type":"Point"}
}