{
  "type": "Feature",
  "properties": {
    "addr:full":"Kempstraat 6 Gent Oost-Vlaanderen 9000",
    "addr:housenumber":"6",
    "addr:postcode":"9000",
    "addr:street":"Kempstraat;Oost-Vlaanderen",
    "iso:country":"BE",
    "sg:address":"Kempstraat 6",
    "sg:city":"Gent",
    "sg:orig_category":"Banques and organismes de cr\u00e9dit",
    "sg:phone":"+32 9 236 27 84",
    "sg:postcode":"9000",
    "sg:province":"Oost-Vlaanderen",
    "wof:name":"V.d.k. Spaarbank",
    "wof:placetype":"venue"
},
  "geometry": {"coordinates":[3.6890718937,51.0662727356],"type":"Point"}
}