{
  "type": "Feature",
  "properties": {
    "addr:full":"Monseigneur Ladeuzeplein 1 Leuven Vlaams-Brabant 3000",
    "addr:housenumber":"1",
    "addr:postcode":"3000",
    "addr:street":"Monseigneur Ladeuzeplein",
    "iso:country":"BE",
    "sg:address":"Monseigneur Ladeuzeplein 1",
    "sg:city":"Leuven",
    "sg:classifiers":[
        {
            "category":"Bars & Pubs",
            "type":"Food & Drink"
        }
    ],
    "sg:phone":"+32 16 20 07 05",
    "sg:postcode":"3000",
    "sg:province":"Vlaams-Brabant",
    "sg:tags":[
        "tavern"
    ],
    "wof:name":"Picasso",
    "wof:placetype":"venue"
},
  "geometry": {"coordinates":[4.7055239677,50.8786582947],"type":"Point"}
}