{
  "type": "Feature",
  "properties": {
    "addr:full":"Place Saint-arnould 4 Bouillon Luxembourg 6830",
    "addr:housenumber":"4",
    "addr:postcode":"6830",
    "addr:street":"Place Saint-Arnould",
    "iso:country":"BE",
    "sg:address":"Place Saint-arnould 4",
    "sg:city":"Bouillon",
    "sg:classifiers":[
        {
            "category":"Bars & Pubs",
            "type":"Food & Drink"
        }
    ],
    "sg:phone":"+32 61 27 07 69",
    "sg:postcode":"6830",
    "sg:province":"Luxembourg",
    "wof:name":"Palace (le)",
    "wof:placetype":"venue"
},
  "geometry": {"coordinates":[5.0704917908,49.7945289612],"type":"Point"}
}