{
  "type": "Feature",
  "properties": {
    "addr:full":"Langerechtestraat 42 Tremelo Vlaams-Brabant 3120",
    "addr:housenumber":"42",
    "addr:postcode":"3120",
    "addr:street":"Langerechtestraat",
    "iso:country":"BE",
    "sg:address":"Langerechtestraat 42",
    "sg:city":"Tremelo",
    "sg:orig_category":"Woningbouw",
    "sg:phone":"+32 16 53 38 66",
    "sg:postcode":"3120",
    "sg:province":"Vlaams-Brabant",
    "wof:name":"Van De Velde",
    "wof:placetype":"venue"
},
  "geometry": {"coordinates":[4.7311840057,50.9981002808],"type":"Point"}
}