{
  "type": "Feature",
  "properties": {
    "iso:country":"BE",
    "sg:address":"Diestersteenweg 103",
    "sg:city":"Maaseik",
    "sg:classifiers":[
        {
            "category":"Autos & Motor Vehicles",
            "subcategory":"Auto Supplies",
            "type":"Retail Goods"
        }
    ],
    "sg:phone":"+32 89 86 54 26",
    "sg:postcode":"3680",
    "sg:province":"Limburg",
    "sg:tags":[
        "access",
        "automobile",
        "part",
        "-"
    ],
    "wof:name":"Vastec",
    "wof:placetype":"venue"
},
  "geometry": {"coordinates":[5.7717900276,51.0992393494],"type":"Point"}
}