{
  "type": "Feature",
  "properties": {
    "addr:full":"Kwijtveldstraat 36 Boortmeerbeek Vlaams-Brabant 3190",
    "addr:housenumber":"36",
    "addr:postcode":"3190",
    "addr:street":"Kwijtveldstraat",
    "iso:country":"BE",
    "sg:address":"Kwijtveldstraat 36",
    "sg:city":"Boortmeerbeek",
    "sg:classifiers":[
        {
            "category":"Home & Garden",
            "subcategory":"Building Materials",
            "type":"Retail Goods"
        }
    ],
    "sg:phone":"+32 15 51 18 93",
    "sg:postcode":"3190",
    "sg:province":"Vlaams-Brabant",
    "sg:tags":[
        "aluminium",
        "construction",
        "-"
    ],
    "wof:name":"Saenen-dekeyser Bvba",
    "wof:placetype":"venue"
},
  "geometry": {"coordinates":[4.579228878,50.9749450684],"type":"Point"}
}