{
  "type": "Feature",
  "properties": {
    "addr:full":"Alt Herbesthalerstrasse 27 Lontzen Li\u00e8ge 4710",
    "addr:housenumber":"27",
    "addr:postcode":"4710",
    "addr:street":"Alt Herbesthalerstrasse",
    "iso:country":"BE",
    "sg:address":"Alt Herbesthalerstrasse 27",
    "sg:city":"Lontzen",
    "sg:classifiers":[
        {
            "category":"Health Services",
            "subcategory":"Nursing And Care Facility",
            "type":"Services"
        }
    ],
    "sg:phone":"+32 87 88 38 09",
    "sg:postcode":"4710",
    "sg:province":"Li\u00e8ge",
    "sg:tags":[
        "home"
    ],
    "wof:name":"Muller E",
    "wof:placetype":"venue"
},
  "geometry": {"coordinates":[5.991669178,50.659526825],"type":"Point"}
}