{
  "type": "Feature",
  "properties": {
    "iso:country":"BE",
    "sg:address":"Violettenstraat 8",
    "sg:city":"Harelbeke",
    "sg:orig_category":"Sportclubs",
    "sg:phone":"+32 56 71 75 83",
    "sg:postcode":"8530",
    "sg:province":"West-Vlaanderen",
    "wof:name":"Eerlijk D/h Langst",
    "wof:placetype":"venue"
},
  "geometry": {"coordinates":[3.304224968,50.8622245789],"type":"Point"}
}