{
  "type": "Feature",
  "properties": {
    "addr:full":"Rue De La P\u00e9pini\u00e8re 1 Bruxelles Bruxelles-Capitale 1000",
    "addr:housenumber":"1",
    "addr:postcode":"1000",
    "addr:street":"Rue De La Pe\u0301Pinie\u0300Re",
    "iso:country":"BE",
    "sg:address":"Rue De La P\u00e9pini\u00e8re 1",
    "sg:city":"Bruxelles",
    "sg:classifiers":[
        {
            "category":"Government",
            "subcategory":"Office",
            "type":"Public Place"
        }
    ],
    "sg:phone":"+32 2 512 86 87",
    "sg:postcode":"1000",
    "sg:province":"Bruxelles-Capitale",
    "sg:tags":[
        "chamber",
        "industry",
        "commerce"
    ],
    "wof:name":"State Of Ohio-european Office",
    "wof:placetype":"venue"
},
  "geometry": {"coordinates":[4.361456871,50.8392601013],"type":"Point"}
}