{
  "type": "Feature",
  "properties": {
    "iso:country":"BE",
    "sg:address":"Grotestraat 65",
    "sg:city":"Geraardsbergen",
    "sg:orig_category":"Herstelling horloges and juwelen Juwelen and horloges",
    "sg:phone":"+32 54 41 27 42",
    "sg:postcode":"9500",
    "sg:province":"Oost-Vlaanderen",
    "wof:name":"Colin-allert",
    "wof:placetype":"venue"
},
  "geometry": {"coordinates":[3.8770151138,50.7719268799],"type":"Point"}
}