{
  "type": "Feature",
  "properties": {
    "addr:full":"Rue Du Prol 6 Ronse/renaix Oost-Vlaanderen 9600",
    "addr:housenumber":"6",
    "addr:postcode":"9600",
    "addr:street":"Rue Du Prol",
    "iso:country":"BE",
    "sg:address":"Rue Du Prol 6",
    "sg:city":"Ronse/renaix",
    "sg:orig_category":"Experts-comptables",
    "sg:phone":"+32 55 21 54 79",
    "sg:postcode":"9600",
    "sg:province":"Oost-Vlaanderen",
    "wof:name":"Andre De Bruycker",
    "wof:placetype":"venue"
},
  "geometry": {"coordinates":[3.6355540752,50.7599220276],"type":"Point"}
}