{
  "type": "Feature",
  "properties": {
    "addr:full":"Warchestrasse 32 B\u00fctgenbach Li\u00e8ge 4750",
    "addr:housenumber":"32",
    "addr:postcode":"4750",
    "addr:street":"Warchestrasse",
    "iso:country":"BE",
    "sg:address":"Warchestrasse 32",
    "sg:city":"B\u00fctgenbach",
    "sg:classifiers":[
        {
            "category":"Professional",
            "type":"Services"
        }
    ],
    "sg:phone":"+32 80 44 52 17",
    "sg:postcode":"4750",
    "sg:province":"Li\u00e8ge",
    "sg:tags":[
        "equipment",
        "installation",
        "restaurants"
    ],
    "wof:name":"D\u00e9cor Blum Edgar",
    "wof:placetype":"venue"
},
  "geometry": {"coordinates":[6.2043948174,50.4263038635],"type":"Point"}
}