{
  "type": "Feature",
  "properties": {
    "addr:full":"Appelkantstraat 54 Boechout Antwerpen 2530",
    "addr:housenumber":"54",
    "addr:postcode":"2530",
    "addr:street":"Appelkantstraat",
    "iso:country":"BE",
    "sg:address":"Appelkantstraat 54",
    "sg:city":"Boechout",
    "sg:classifiers":[
        {
            "category":"Community Center",
            "subcategory":"Youth",
            "type":"Public Place"
        }
    ],
    "sg:phone":"+32 3 454 11 44",
    "sg:postcode":"2530",
    "sg:province":"Antwerpen",
    "sg:tags":[
        "club"
    ],
    "wof:name":"Jeugddienst Bisdom Antwerpen",
    "wof:placetype":"venue"
},
  "geometry": {"coordinates":[4.4860401154,51.1589202881],"type":"Point"}
}