{
  "type": "Feature",
  "properties": {
    "addr:full":"Bo\u00eete Postale 11 Mont-saint-guibert Brabant Wallon 1435",
    "addr:housenumber":"11",
    "addr:postcode":"1435",
    "addr:street":"Mont-Saint-Guibert Brabant",
    "iso:country":"BE",
    "sg:address":"Bo\u00eete Postale 11",
    "sg:city":"Mont-saint-guibert",
    "sg:classifiers":[
        {
            "category":"Shopping",
            "subcategory":"Photographic Equipment",
            "type":"Retail Goods"
        }
    ],
    "sg:phone":"+32 15 27 03 35",
    "sg:postcode":"1435",
    "sg:province":"Brabant Wallon",
    "sg:tags":[
        "whol",
        "-",
        "mfg&",
        "accessory"
    ],
    "wof:name":"Sigma Benelux Bv",
    "wof:placetype":"venue"
},
  "geometry": {"coordinates":[4.6142549515,50.6351242065],"type":"Point"}
}