{
  "type": "Feature",
  "properties": {
    "addr:full":"Sint-jobsesteenweg 771b Ukkel/uccle Bruxelles-Capitale 1180",
    "addr:housenumber":"771b",
    "addr:postcode":"1180",
    "addr:street":"Sint-Jobsesteenweg;/",
    "iso:country":"BE",
    "sg:address":"Sint-jobsesteenweg 771b",
    "sg:city":"Ukkel/uccle",
    "sg:orig_category":"Kapsalons",
    "sg:phone":"+32 2 374 23 02",
    "sg:postcode":"1180",
    "sg:province":"Bruxelles-Capitale",
    "wof:name":"Coiffure M\u00cache De Coeur",
    "wof:placetype":"venue"
},
  "geometry": {"coordinates":[4.3650999069,50.7945861816],"type":"Point"}
}