{
  "type": "Feature",
  "properties": {
    "iso:country":"BE",
    "sg:address":"Rue De La Tasni\u00c8re 20",
    "sg:city":"Perwez",
    "sg:orig_category":"Fotografen and fotostudio's",
    "sg:phone":"+32 81 65 50 24",
    "sg:postcode":"1360",
    "sg:province":"Brabant Wallon",
    "wof:name":"Nathalie Bidoul",
    "wof:placetype":"venue"
},
  "geometry": {"coordinates":[4.7544770241,50.644077301],"type":"Point"}
}