{
  "type": "Feature",
  "properties": {
    "iso:country":"BE",
    "sg:address":"Doortstraat 6",
    "sg:city":"Opwijk",
    "sg:classifiers":[
        {
            "category":"Retail",
            "subcategory":"Repair Shop",
            "type":"Services"
        }
    ],
    "sg:phone":"+32 52 36 93 11",
    "sg:postcode":"1745",
    "sg:province":"Vlaams-Brabant",
    "sg:tags":[
        "duct",
        "ducts",
        "ventilation",
        "air conditioning"
    ],
    "wof:name":"Abb-asea Brown Boveri Elve Nv",
    "wof:placetype":"venue"
},
  "geometry": {"coordinates":[4.1948328018,50.9741859436],"type":"Point"}
}