{
  "type": "Feature",
  "properties": {
    "addr:full":"Grote Baan 226 Lovendegem Oost-Vlaanderen 9920",
    "addr:housenumber":"226",
    "addr:postcode":"9920",
    "addr:street":"Grote Baan",
    "iso:country":"BE",
    "sg:address":"Grote Baan 226",
    "sg:city":"Lovendegem",
    "sg:classifiers":[
        {
            "category":"Travel",
            "subcategory":"Resort",
            "type":"Entertainment"
        }
    ],
    "sg:phone":"+32 9 362 24 55",
    "sg:postcode":"9920",
    "sg:province":"Oost-Vlaanderen",
    "sg:tags":[
        "health"
    ],
    "wof:name":"Body To Body Massages",
    "wof:placetype":"venue"
},
  "geometry": {"coordinates":[3.6161990166,51.1084403992],"type":"Point"}
}