{
  "type": "Feature",
  "properties": {
    "addr:full":"Rue De Behogne 36 Rochefort Namur 5580",
    "addr:housenumber":"36",
    "addr:postcode":"5580",
    "addr:street":"Rue De Behogne",
    "iso:country":"BE",
    "sg:address":"Rue De Behogne 36",
    "sg:city":"Rochefort",
    "sg:classifiers":[
        {
            "category":"Professional",
            "subcategory":"Art Services",
            "type":"Services"
        }
    ],
    "sg:phone":"+32 84 21 37 92",
    "sg:postcode":"5580",
    "sg:province":"Namur",
    "sg:tags":[
        "picture",
        "framer"
    ],
    "wof:name":"Jacquemin E",
    "wof:placetype":"venue"
},
  "geometry": {"coordinates":[5.2230138779,50.1606788635],"type":"Point"}
}