{
  "type": "Feature",
  "properties": {
    "addr:full":"Place D'houtaing 7 Ath (houtaing) Hainaut 7812",
    "addr:housenumber":"7",
    "addr:postcode":"7812",
    "addr:street":"Place D'Houtaing",
    "iso:country":"BE",
    "sg:address":"Place D'houtaing 7",
    "sg:city":"Ath (houtaing)",
    "sg:classifiers":[
        {
            "category":"Home & Garden",
            "subcategory":"Garden Supply",
            "type":"Retail Goods"
        }
    ],
    "sg:phone":"+32 68 64 52 23",
    "sg:postcode":"7812",
    "sg:province":"Hainaut",
    "sg:tags":[
        "machine",
        "agricultural",
        "-"
    ],
    "wof:name":"Faignart",
    "wof:placetype":"venue"
},
  "geometry": {"coordinates":[3.7050700188,50.6317214966],"type":"Point"}
}