{
  "type": "Feature",
  "properties": {
    "iso:country":"BE",
    "sg:address":"Hovenierstr 53",
    "sg:city":"Antwerpen",
    "sg:classifiers":[
        {
            "category":"Manufacturing",
            "subcategory":"Jewelry",
            "type":"Manufacturing & Wholesale Goods"
        }
    ],
    "sg:phone":"+32 3 234 36 06",
    "sg:postcode":"2018",
    "sg:province":"Antwerpen",
    "sg:tags":[
        "product",
        "miscellaneous",
        "jewellery"
    ],
    "wof:name":"Diamex Manufacturing Nv",
    "wof:placetype":"venue"
},
  "geometry": {"coordinates":[4.4188599586,51.2144813538],"type":"Point"}
}