{
  "type": "Feature",
  "properties": {
    "addr:full":"Avenue Louise 500 Bruxelles 1051",
    "addr:housenumber":"500",
    "addr:postcode":"1051",
    "addr:street":"Avenue Louise",
    "iso:country":"BE",
    "sg:address":"Avenue Louise 500",
    "sg:city":"Bruxelles",
    "sg:classifiers":[
        {
            "category":"Professional",
            "subcategory":"Business Services",
            "type":"Services"
        }
    ],
    "sg:phone":"+32 2 648 50 02",
    "sg:postcode":"1051",
    "sg:tags":[
        "consulting",
        "export"
    ],
    "wof:name":"Chambre De Commerce Et D'industrie De Bruxelles A.s.b.l.",
    "wof:placetype":"venue"
},
  "geometry": {"coordinates":[4.3723797798,50.8163948059],"type":"Point"}
}