{
  "type": "Feature",
  "properties": {
    "iso:country":"BE",
    "sg:address":"Rue Royale 19",
    "sg:city":"Tournai",
    "sg:orig_category":"Speelgoed",
    "sg:phone":"+32 69 21 42 22",
    "sg:postcode":"7500",
    "sg:province":"Hainaut",
    "wof:name":"Playland Christiaensen",
    "wof:placetype":"venue"
},
  "geometry": {"coordinates":[3.3918430805,50.6089668274],"type":"Point"}
}