{
  "type": "Feature",
  "properties": {
    "addr:full":"Roesbruggestraat 5 Poperinge (proven) West-Vlaanderen 8972",
    "addr:housenumber":"5",
    "addr:postcode":"8972",
    "addr:street":"Roesbruggestraat",
    "iso:country":"BE",
    "sg:address":"Roesbruggestraat 5",
    "sg:city":"Poperinge (proven)",
    "sg:classifiers":[
        {
            "category":"Manufacturing",
            "subcategory":"Lumber",
            "type":"Manufacturing & Wholesale Goods"
        }
    ],
    "sg:phone":"+32 57 30 05 61",
    "sg:postcode":"8972",
    "sg:province":"West-Vlaanderen",
    "sg:tags":[
        "timber"
    ],
    "wof:name":"Decadt Daniel Nv",
    "wof:placetype":"venue"
},
  "geometry": {"coordinates":[2.64944911,50.894908905],"type":"Point"}
}