{
  "type": "Feature",
  "properties": {
    "addr:full":"Rue Grande 30 Dinant Namur 5500",
    "addr:housenumber":"30",
    "addr:postcode":"5500",
    "addr:street":"Rue Grande",
    "iso:country":"BE",
    "sg:address":"Rue Grande 30",
    "sg:city":"Dinant",
    "sg:orig_category":"Banken and kredietinstellingen",
    "sg:phone":"+32 82 22 43 07",
    "sg:postcode":"5500",
    "sg:province":"Namur",
    "wof:name":"Cr\u00c9dit Agricole",
    "wof:placetype":"venue"
},
  "geometry": {"coordinates":[4.9152498245,50.2570381165],"type":"Point"}
}