{
  "type": "Feature",
  "properties": {
    "addr:full":"Rue Souveraine 91 Ixelles Bruxelles-Capitale 1050",
    "addr:housenumber":"91",
    "addr:postcode":"1050",
    "addr:street":"Rue Souveraine",
    "iso:country":"BE",
    "sg:address":"Rue Souveraine 91",
    "sg:city":"Ixelles",
    "sg:orig_category":"Diverse bedrijfsbeheeradviesbureaus",
    "sg:phone":"+32 2 513 80 78",
    "sg:postcode":"1050",
    "sg:province":"Bruxelles-Capitale",
    "wof:name":"Sogespar",
    "wof:placetype":"venue"
},
  "geometry": {"coordinates":[4.3623552322,50.8313789368],"type":"Point"}
}