{
  "type": "Feature",
  "properties": {
    "addr:full":"Chemin De La Malaise 37 Ham-sur-heure-nalinnes Hainaut 6120",
    "addr:housenumber":"37",
    "addr:postcode":"6120",
    "addr:street":"Chemin De La Malaise;Hainaut",
    "iso:country":"BE",
    "sg:address":"Chemin De La Malaise 37",
    "sg:city":"Ham-sur-heure-nalinnes",
    "sg:orig_category":"Diensten voor huisdieren",
    "sg:phone":"+32 71 21 79 15",
    "sg:postcode":"6120",
    "sg:province":"Hainaut",
    "wof:name":"La Passion Des Chiens",
    "wof:placetype":"venue"
},
  "geometry": {"coordinates":[4.3872900009,50.3219146729],"type":"Point"}
}