{
  "type": "Feature",
  "properties": {
    "addr:full":"Kiezel Kleine Brogel 57 Peer Limburg 3990",
    "addr:housenumber":"57",
    "addr:postcode":"3990",
    "addr:street":"Kiezel Kleine Brogel",
    "iso:country":"BE",
    "sg:address":"Kiezel Kleine Brogel 57",
    "sg:city":"Peer",
    "sg:classifiers":[
        {
            "category":"Home & Garden",
            "subcategory":"Hardware",
            "type":"Retail Goods"
        }
    ],
    "sg:phone":"+32 11 61 01 30",
    "sg:postcode":"3990",
    "sg:province":"Limburg",
    "sg:tags":[
        "quincailleries",
        "bois",
        "gr"
    ],
    "wof:name":"H.d.m.",
    "wof:placetype":"venue"
},
  "geometry": {"coordinates":[5.4524102211,51.1436576843],"type":"Point"}
}