{
  "type": "Feature",
  "properties": {
    "iso:country":"BE",
    "sg:address":"Grotestraat 30",
    "sg:city":"Geraardsbergen",
    "sg:classifiers":[
        {
            "category":"Shopping",
            "subcategory":"Jewelry",
            "type":"Retail Goods"
        }
    ],
    "sg:phone":"+32 54 41 97 88",
    "sg:postcode":"9500",
    "sg:province":"Oost-Vlaanderen",
    "sg:tags":[
        "-",
        "imitation"
    ],
    "wof:name":"De Verbeelding",
    "wof:placetype":"venue"
},
  "geometry": {"coordinates":[3.8767869473,50.7716560364],"type":"Point"}
}