{
  "type": "Feature",
  "properties": {
    "iso:country":"BE",
    "sg:address":"Gentstraat 23b4",
    "sg:city":"Waasmunster",
    "sg:orig_category":"Banken and kredietinstellingen",
    "sg:phone":"+32 52 46 22 31",
    "sg:postcode":"9250",
    "sg:province":"Oost-Vlaanderen",
    "wof:name":"Kbc",
    "wof:placetype":"venue"
},
  "geometry": {"coordinates":[4.0820450783,51.1094284058],"type":"Point"}
}