{
  "type": "Feature",
  "properties": {
    "iso:country":"BE",
    "sg:address":"14",
    "sg:city":"Minderbroedersstraat 2000 Antwerpen",
    "sg:classifiers":[
        {
            "category":"Professional",
            "subcategory":"Business Services",
            "type":"Services"
        }
    ],
    "sg:phone":"+32 3 203 53 00",
    "sg:postcode":"14",
    "sg:tags":[
        "advice",
        "clothes"
    ],
    "wof:name":"Enthoven Associates Design Consultants",
    "wof:placetype":"venue"
},
  "geometry": {"coordinates":[4.4051198959,51.2228279114],"type":"Point"}
}