{
  "type": "Feature",
  "properties": {
    "iso:country":"BE",
    "sg:address":"Bois De Virelles 4",
    "sg:city":"Chimay",
    "sg:orig_category":"Rundveehouders",
    "sg:phone":"+32 60 21 90 30",
    "sg:postcode":"6461",
    "sg:province":"Hainaut",
    "wof:name":"Roger Bouillet",
    "wof:placetype":"venue"
},
  "geometry": {"coordinates":[4.3301701546,50.0856704712],"type":"Point"}
}