{
  "type": "Feature",
  "properties": {
    "addr:full":"Bankelindeweg 24 Poperinge (groot) West-Vlaanderen 8972",
    "addr:housenumber":"24",
    "addr:postcode":"8972",
    "addr:street":"Bankelindeweg;Groot West-Vlaanderen",
    "iso:country":"BE",
    "sg:address":"Bankelindeweg 24",
    "sg:city":"Poperinge (groot)",
    "sg:classifiers":[
        {
            "category":"Personal",
            "subcategory":"Beauty Salon",
            "type":"Services"
        }
    ],
    "sg:phone":"+32 57 40 18 82",
    "sg:postcode":"8972",
    "sg:province":"West-Vlaanderen",
    "sg:tags":[
        "de",
        "coiffure"
    ],
    "wof:name":"Els",
    "wof:placetype":"venue"
},
  "geometry": {"coordinates":[2.6888830662,50.9108505249],"type":"Point"}
}