{
  "type": "Feature",
  "properties": {
    "iso:country":"BE",
    "sg:address":"Oosthamsesteenweg 27",
    "sg:city":"Balen",
    "sg:orig_category":"R\u00e9parations d'appareils \u00e9lectrom\u00e9nagers. Electrom\u00e9nager, t\u00e9l\u00e9visions and radios",
    "sg:phone":"+32 14 30 11 35",
    "sg:postcode":"2491",
    "sg:province":"Antwerpen",
    "wof:name":"K\u00d6nig Electronic",
    "wof:placetype":"venue"
},
  "geometry": {"coordinates":[5.1578769684,51.1299667358],"type":"Point"}
}