{
  "type": "Feature",
  "properties": {
    "addr:full":"Jan Mioenstraat 10 Kortemark West-Vlaanderen 8610",
    "addr:housenumber":"10",
    "addr:postcode":"8610",
    "addr:street":"Mioenstraat",
    "iso:country":"BE",
    "sg:address":"Jan Mioenstraat 10",
    "sg:city":"Kortemark",
    "sg:orig_category":"Dakwerken Installatie van houten of kunststof schrijnwerk",
    "sg:phone":"+32 51 56 70 01",
    "sg:postcode":"8610",
    "sg:province":"West-Vlaanderen",
    "wof:name":"Maertens",
    "wof:placetype":"venue"
},
  "geometry": {"coordinates":[3.0284531116,51.0174674988],"type":"Point"}
}