{
  "type": "Feature",
  "properties": {
    "iso:country":"BE",
    "sg:address":"Vijverwegel 85",
    "sg:city":"Melle",
    "sg:orig_category":"Non-Classified Establishments",
    "sg:phone":"+32 475 66 64 62",
    "sg:postcode":"9090",
    "sg:province":"Oost-Vlaanderen",
    "wof:name":"Ddeff Sound Systems Bvba",
    "wof:placetype":"venue"
},
  "geometry": {"coordinates":[3.7702460289,51.0165214539],"type":"Point"}
}