{
  "type": "Feature",
  "properties": {
    "addr:full":"Rue Des Mays 18 Fontaine-l'ev\u00eaque Hainaut 6140",
    "addr:housenumber":"18",
    "addr:postcode":"6140",
    "addr:street":"Rue Des Mays;\u0302Que Hainaut",
    "iso:country":"BE",
    "sg:address":"Rue Des Mays 18",
    "sg:city":"Fontaine-l'ev\u00eaque",
    "sg:classifiers":[
        {
            "category":"Health Services",
            "subcategory":"Dentist",
            "type":"Services"
        }
    ],
    "sg:phone":"+32 71 52 28 29",
    "sg:postcode":"6140",
    "sg:province":"Hainaut",
    "wof:name":"Genin T",
    "wof:placetype":"venue"
},
  "geometry": {"coordinates":[-111.9644622803,46.2507972717],"type":"Point"}
}