{
  "type": "Feature",
  "properties": {
    "addr:full":"Rue D'anethan 29 Bruxelles Bruxelles-Capitale 1030",
    "addr:housenumber":"29",
    "addr:postcode":"1030",
    "addr:street":"Rue D'Anethan",
    "iso:country":"BE",
    "sg:address":"Rue D'anethan 29",
    "sg:city":"Bruxelles",
    "sg:orig_category":"Photo-Engraving Services",
    "sg:phone":"+32 2 245 79 70",
    "sg:postcode":"1030",
    "sg:province":"Bruxelles-Capitale",
    "wof:name":"Dppc Digital Pre-press Center S.p.r.l.",
    "wof:placetype":"venue"
},
  "geometry": {"coordinates":[4.3742799759,50.8727416992],"type":"Point"}
}