{
  "type": "Feature",
  "properties": {
    "addr:full":"Brusselsesteenweg 606 Overijse Vlaams-Brabant 3090",
    "addr:housenumber":"606",
    "addr:postcode":"3090",
    "addr:street":"Brusselsesteenweg",
    "iso:country":"BE",
    "sg:address":"Brusselsesteenweg 606",
    "sg:city":"Overijse",
    "sg:classifiers":[
        {
            "category":"Health Services",
            "subcategory":"Dentist",
            "type":"Services"
        }
    ],
    "sg:phone":"+32 2 657 32 46",
    "sg:postcode":"3090",
    "sg:province":"Vlaams-Brabant",
    "wof:name":"De Rijcke Christine",
    "wof:placetype":"venue"
},
  "geometry": {"coordinates":[4.5077381134,50.7832832336],"type":"Point"}
}