{
  "type": "Feature",
  "properties": {
    "addr:full":"Helena Wijnantslaan 26 Heers Limburg 3870",
    "addr:housenumber":"26",
    "addr:postcode":"3870",
    "addr:street":"Wijnantslaan",
    "iso:country":"BE",
    "sg:address":"Helena Wijnantslaan 26",
    "sg:city":"Heers",
    "sg:classifiers":[
        {
            "category":"Arena",
            "subcategory":"Sports Club",
            "type":"Entertainment"
        }
    ],
    "sg:phone":"+32 11 48 42 95",
    "sg:postcode":"3870",
    "sg:province":"Limburg",
    "sg:tags":[
        "de"
    ],
    "wof:name":"V.c. Hevoc",
    "wof:placetype":"venue"
},
  "geometry": {"coordinates":[5.3060908318,50.7513198853],"type":"Point"}
}