{
  "type": "Feature",
  "properties": {
    "iso:country":"BE",
    "sg:address":"Place Houwaert 5",
    "sg:city":"Bruxelles (saint-josse-ten-noode)",
    "sg:classifiers":[
        {
            "category":"Shopping",
            "subcategory":"Gifts & Souvenirs",
            "type":"Retail Goods"
        }
    ],
    "sg:phone":"+32 2 219 70 52",
    "sg:postcode":"1210",
    "sg:province":"Bruxelles-Capitale",
    "sg:tags":[
        "-"
    ],
    "wof:name":"3 G",
    "wof:placetype":"venue"
},
  "geometry": {"coordinates":[4.3733549118,50.8530960083],"type":"Point"}
}