{
  "type": "Feature",
  "properties": {
    "addr:full":"Geelsebaan 42 Kasterlee Antwerpen 2460",
    "addr:housenumber":"42",
    "addr:postcode":"2460",
    "addr:street":"Geelsebaan",
    "iso:country":"BE",
    "sg:address":"Geelsebaan 42",
    "sg:city":"Kasterlee",
    "sg:classifiers":[
        {
            "category":"Health Services",
            "subcategory":"Dentist",
            "type":"Services"
        }
    ],
    "sg:phone":"+32 14 85 22 07",
    "sg:postcode":"2460",
    "sg:province":"Antwerpen",
    "wof:name":"Moubax Jef",
    "wof:placetype":"venue"
},
  "geometry": {"coordinates":[4.968515873,51.2378768921],"type":"Point"}
}