{
  "type": "Feature",
  "properties": {
    "addr:full":"Hoelbeekstraat 142 Bilzen Limburg 3746",
    "addr:housenumber":"142",
    "addr:postcode":"3746",
    "addr:street":"Hoelbeekstraat",
    "iso:country":"BE",
    "sg:address":"Hoelbeekstraat 142",
    "sg:city":"Bilzen",
    "sg:classifiers":[
        {
            "category":"Sports & Exercise",
            "subcategory":"Sports Center",
            "type":"Entertainment"
        }
    ],
    "sg:phone":"+32 89 41 82 14",
    "sg:postcode":"3746",
    "sg:province":"Limburg",
    "sg:tags":[
        "terrain",
        "hors",
        "de",
        "installation",
        "sportifs"
    ],
    "wof:name":"Lanaker Watersportveren.",
    "wof:placetype":"venue"
},
  "geometry": {"coordinates":[5.5609722137,50.8776245117],"type":"Point"}
}