{
  "type": "Feature",
  "properties": {
    "iso:country":"BE",
    "sg:address":"Rue De La Loi 12",
    "sg:city":"Chatelet",
    "sg:orig_category":"Caf\u00e9s Dakwerken Schoonmaakbedrijven and ongediertebestrijding",
    "sg:phone":"+32 71 40 08 86",
    "sg:postcode":"6200",
    "sg:province":"Hainaut",
    "wof:name":"Vanderhaeghe",
    "wof:placetype":"venue"
},
  "geometry": {"coordinates":[4.512234211,50.4122238159],"type":"Point"}
}