{
  "type": "Feature",
  "properties": {
    "iso:country":"BE",
    "sg:address":"Cyriel Verschaevestraat 13",
    "sg:city":"Kortrijk (marke)",
    "sg:classifiers":[
        {
            "category":"Professional",
            "subcategory":"Art Services",
            "type":"Services"
        }
    ],
    "sg:phone":"+32 56 20 23 41",
    "sg:postcode":"8510",
    "sg:province":"West-Vlaanderen",
    "sg:tags":[
        "designer",
        "display"
    ],
    "wof:name":"Tant H",
    "wof:placetype":"venue"
},
  "geometry": {"coordinates":[3.2389290333,50.7866401672],"type":"Point"}
}