{
  "type": "Feature",
  "properties": {
    "addr:full":"Rue De La Ville 12 Le Roeulx (ville-sur-haine) Hainaut 7070",
    "addr:housenumber":"12",
    "addr:postcode":"7070",
    "addr:street":"Rue De La Ville",
    "iso:country":"BE",
    "sg:address":"Rue De La Ville 12",
    "sg:city":"Le Roeulx (ville-sur-haine)",
    "sg:classifiers":[
        {
            "category":"Utilities",
            "subcategory":"Refuse",
            "type":"Services"
        }
    ],
    "sg:phone":"+32 64 66 25 28",
    "sg:postcode":"7070",
    "sg:province":"Hainaut",
    "sg:tags":[
        "miller"
    ],
    "wof:name":"Cereali\u00e8re De Gottignies",
    "wof:placetype":"venue"
},
  "geometry": {"coordinates":[4.1093950272,50.5003242493],"type":"Point"}
}