{
  "type": "Feature",
  "properties": {
    "addr:full":"Rue Emile Vandervelde 125 Courcelles (souvret) Hainaut 6182",
    "addr:housenumber":"125",
    "addr:postcode":"6182",
    "addr:street":"Rue Emile Vandervelde",
    "iso:country":"BE",
    "sg:address":"Rue Emile Vandervelde 125",
    "sg:city":"Courcelles (souvret)",
    "sg:classifiers":[
        {
            "category":"Retail",
            "subcategory":"Auto Repair",
            "type":"Services"
        }
    ],
    "sg:phone":"+32 71 46 13 68",
    "sg:postcode":"6182",
    "sg:province":"Hainaut",
    "sg:tags":[
        "garage"
    ],
    "wof:name":"Quattro Sprl",
    "wof:placetype":"venue"
},
  "geometry": {"coordinates":[4.3565211296,50.4436645508],"type":"Point"}
}