{
  "type": "Feature",
  "properties": {
    "iso:country":"BE",
    "sg:address":"Rue Paquot 4c",
    "sg:city":"Florennes",
    "sg:classifiers":[
        {
            "category":"Food & Beverages",
            "subcategory":"Specialty",
            "type":"Retail Goods"
        }
    ],
    "sg:phone":"+32 71 68 92 07",
    "sg:postcode":"5620",
    "sg:province":"Namur",
    "sg:tags":[
        "health",
        "dietary",
        "-",
        "biological"
    ],
    "wof:name":"Nature Au Fil Des Jours",
    "wof:placetype":"venue"
},
  "geometry": {"coordinates":[4.6041898727,50.2509651184],"type":"Point"}
}