{
  "type": "Feature",
  "properties": {
    "iso:country":"BE",
    "sg:address":"Kortrijksesteenseg 83",
    "sg:city":"Sint-martens-latem",
    "sg:orig_category":"Bloemen and planten Gh",
    "sg:phone":"+32 9 282 44 43",
    "sg:postcode":"9830",
    "sg:province":"Oost-Vlaanderen",
    "wof:name":"Van Wassenhove D",
    "wof:placetype":"venue"
},
  "geometry": {"coordinates":[3.6436200142,51.0126457214],"type":"Point"}
}