{
  "type": "Feature",
  "properties": {
    "iso:country":"BE",
    "sg:address":"Ernest Claesstraat 22 Box B",
    "sg:city":"Herentals",
    "sg:classifiers":[
        {
            "category":"Wholesale",
            "subcategory":"Meat",
            "type":"Manufacturing & Wholesale Goods"
        }
    ],
    "sg:phone":"+32 14 21 10 94",
    "sg:postcode":"2200",
    "sg:province":"Antwerpen",
    "sg:tags":[
        "abattoir"
    ],
    "wof:name":"De Groof",
    "wof:placetype":"venue"
},
  "geometry": {"coordinates":[4.8416781425,51.1721611023],"type":"Point"}
}