{
  "type": "Feature",
  "properties": {
    "addr:full":"Leuvenselaan 47 Tienen Vlaams-Brabant 3300",
    "addr:housenumber":"47",
    "addr:postcode":"3300",
    "addr:street":"Leuvenselaan",
    "iso:country":"BE",
    "sg:address":"Leuvenselaan 47",
    "sg:city":"Tienen",
    "sg:orig_category":"Artsen and specialisten",
    "sg:phone":"+32 16 81 34 16",
    "sg:postcode":"3300",
    "sg:province":"Vlaams-Brabant",
    "wof:name":"Cecile Drossart",
    "wof:placetype":"venue"
},
  "geometry": {"coordinates":[4.9280571938,50.8103523254],"type":"Point"}
}