{
  "type": "Feature",
  "properties": {
    "addr:full":"De Wautierstraat 41 Brussel/bruxelles Bruxelles-Capitale 1020",
    "addr:housenumber":"41",
    "addr:postcode":"1020",
    "addr:street":"De Wautierstraat;/",
    "iso:country":"BE",
    "sg:address":"De Wautierstraat 41",
    "sg:city":"Brussel/bruxelles",
    "sg:orig_category":"Decoratiestoffen and buitenhuistextiel Fab Installatie van houten of kunststof schrijnwerk Installat",
    "sg:phone":"+32 2 426 54 77",
    "sg:postcode":"1020",
    "sg:province":"Bruxelles-Capitale",
    "wof:name":"Maetens N\u00c9on",
    "wof:placetype":"venue"
},
  "geometry": {"coordinates":[4.3562312126,50.8735923767],"type":"Point"}
}