{
  "type": "Feature",
  "properties": {
    "iso:country":"BE",
    "sg:address":"Fonteinstraat 7",
    "sg:city":"Zulte (olsene)",
    "sg:classifiers":[
        {
            "category":"Freight",
            "type":"Transportation"
        }
    ],
    "sg:phone":"+32 9 388 73 13",
    "sg:postcode":"9870",
    "sg:province":"Oost-Vlaanderen",
    "sg:tags":[
        "-",
        "transport"
    ],
    "wof:name":"Bogaert Ronald Bvba",
    "wof:placetype":"venue"
},
  "geometry": {"coordinates":[3.465086937,50.9442176819],"type":"Point"}
}