{
  "type": "Feature",
  "properties": {
    "iso:country":"BE",
    "sg:address":"Karrestraat 83",
    "sg:city":"Wevelgem (moorsele)",
    "sg:classifiers":[
        {
            "category":"Retail",
            "subcategory":"Event Space",
            "type":"Services"
        }
    ],
    "sg:phone":"+32 56 43 00 70",
    "sg:postcode":"8560",
    "sg:province":"West-Vlaanderen",
    "sg:tags":[
        "product",
        "snack",
        "speciality",
        "potato",
        "stand",
        "fried"
    ],
    "wof:name":"Swann",
    "wof:placetype":"venue"
},
  "geometry": {"coordinates":[3.1679840088,50.836807251],"type":"Point"}
}