{
  "type": "Feature",
  "properties": {
    "iso:country":"BE",
    "sg:address":"Rue Lebeau 3",
    "sg:city":"Li\u00e8ge",
    "sg:classifiers":[
        {
            "category":"Banks & Credit Unions",
            "subcategory":"Bank",
            "type":"Services"
        }
    ],
    "sg:postcode":"4000",
    "sg:province":"Li\u00e8ge",
    "wof:name":"Gesfin (rv Finance)",
    "wof:placetype":"venue"
},
  "geometry": {"coordinates":[5.5789031982,50.616317749],"type":"Point"}
}