{
  "type": "Feature",
  "properties": {
    "addr:full":"Blijstraat 4 Lebbeke Oost-Vlaanderen 9280",
    "addr:housenumber":"4",
    "addr:postcode":"9280",
    "addr:street":"Blijstraat",
    "iso:country":"BE",
    "sg:address":"Blijstraat 4",
    "sg:city":"Lebbeke",
    "sg:orig_category":"Rundveehouders",
    "sg:phone":"+32 52 41 06 68",
    "sg:postcode":"9280",
    "sg:province":"Oost-Vlaanderen",
    "wof:name":"Marc Pollijn",
    "wof:placetype":"venue"
},
  "geometry": {"coordinates":[4.1039481163,50.9916648865],"type":"Point"}
}