{
  "type": "Feature",
  "properties": {
    "addr:full":"Antwerpseweg 6 Geel Antwerpen 2440",
    "addr:housenumber":"6",
    "addr:postcode":"2440",
    "addr:street":"Antwerpseweg",
    "iso:country":"BE",
    "sg:address":"Antwerpseweg 6",
    "sg:city":"Geel",
    "sg:classifiers":[
        {
            "category":"Autos & Motor Vehicles",
            "subcategory":"Auto Supplies",
            "type":"Retail Goods"
        }
    ],
    "sg:phone":"+32 14 58 73 74",
    "sg:postcode":"2440",
    "sg:province":"Antwerpen",
    "sg:tags":[
        "access",
        "automobile",
        "part",
        "-"
    ],
    "wof:name":"Oke-auto-geel Nv",
    "wof:placetype":"venue"
},
  "geometry": {"coordinates":[4.9739160538,51.1521492004],"type":"Point"}
}