{
  "type": "Feature",
  "properties": {
    "addr:full":"Van Putlei 77 Lint Antwerpen 2547",
    "addr:housenumber":"77",
    "addr:postcode":"2547",
    "iso:country":"BE",
    "sg:address":"Van Putlei 77",
    "sg:city":"Lint",
    "sg:orig_category":"Enseignement maternel and primaire",
    "sg:phone":"+32 3 455 94 17",
    "sg:postcode":"2547",
    "sg:province":"Antwerpen",
    "wof:name":"Vrije Kleuterschool",
    "wof:placetype":"venue"
},
  "geometry": {"coordinates":[4.4887909889,51.1277351379],"type":"Point"}
}