{
  "type": "Feature",
  "properties": {
    "addr:full":"Rode Beukendreef 21 Zedelgem West-Vlaanderen 8210",
    "addr:housenumber":"21",
    "addr:postcode":"8210",
    "addr:street":"Rode Beukendreef",
    "iso:country":"BE",
    "sg:address":"Rode Beukendreef 21",
    "sg:city":"Zedelgem",
    "sg:orig_category":"Rev\u00eatements pour sols and murs. Peinture",
    "sg:phone":"+32 50 82 44 81",
    "sg:postcode":"8210",
    "sg:province":"West-Vlaanderen",
    "wof:name":"Marc Tierenteyn",
    "wof:placetype":"venue"
},
  "geometry": {"coordinates":[3.1458399296,51.1376457214],"type":"Point"}
}