{
  "type": "Feature",
  "properties": {
    "iso:country":"BE",
    "sg:address":"Kortrijksestraat 197",
    "sg:city":"Moorslede",
    "sg:orig_category":"Installation de menuiserie en bois and plastique",
    "sg:phone":"+32 56 50 14 56",
    "sg:postcode":"8890",
    "sg:province":"West-Vlaanderen",
    "wof:name":"Reginald Bruneel",
    "wof:placetype":"venue"
},
  "geometry": {"coordinates":[3.1300370693,50.844619751],"type":"Point"}
}