{
  "type": "Feature",
  "properties": {
    "addr:full":"Rue Du Couvent 87 Li\u00e8ge 1 (jupille-sur-meuse) Li\u00e8ge 4020",
    "addr:housenumber":"87;1",
    "addr:postcode":"4020",
    "addr:street":"Rue Du Couvent;Jupille-Sur-Meuse Lie\u0300Ge",
    "iso:country":"BE",
    "sg:address":"Rue Du Couvent 87",
    "sg:city":"Li\u00e8ge 1 (jupille-sur-meuse)",
    "sg:classifiers":[
        {
            "category":"Farming",
            "subcategory":"Farm & Veterinary Services",
            "type":"Manufacturing & Wholesale Goods"
        }
    ],
    "sg:phone":"+32 4 370 91 01",
    "sg:postcode":"4020",
    "sg:province":"Li\u00e8ge",
    "sg:tags":[
        "-",
        "supply",
        "veterinarian",
        "instrument"
    ],
    "wof:name":"M\u00e9dical-lux Sprl",
    "wof:placetype":"venue"
},
  "geometry": {"coordinates":[5.6446199417,50.642829895],"type":"Point"}
}