{
  "type": "Feature",
  "properties": {
    "addr:full":"Rue Vaudr\u00e9e 240 Li\u00e8ge 1 (angleur) Li\u00e8ge 4031",
    "addr:housenumber":"240;1",
    "addr:postcode":"4031",
    "addr:street":"Rue Vaudre\u0301E",
    "iso:country":"BE",
    "sg:address":"Rue Vaudr\u00e9e 240",
    "sg:city":"Li\u00e8ge 1 (angleur)",
    "sg:classifiers":[
        {
            "category":"Shopping",
            "subcategory":"Florist",
            "type":"Retail Goods"
        }
    ],
    "sg:phone":"+32 4 365 24 62",
    "sg:postcode":"4031",
    "sg:province":"Li\u00e8ge",
    "wof:name":"Ecrin Fleuri (l')",
    "wof:placetype":"venue"
},
  "geometry": {"coordinates":[5.587348938,50.6136436462],"type":"Point"}
}