{
  "type": "Feature",
  "properties": {
    "addr:full":"Grote Markt 10 Veurne West-Vlaanderen 8630",
    "addr:housenumber":"10",
    "addr:postcode":"8630",
    "addr:street":"Grote Markt",
    "iso:country":"BE",
    "sg:address":"Grote Markt 10",
    "sg:city":"Veurne",
    "sg:classifiers":[
        {
            "category":"Restaurant",
            "type":"Food & Drink"
        }
    ],
    "sg:phone":"+32 58 31 37 00",
    "sg:postcode":"8630",
    "sg:province":"West-Vlaanderen",
    "wof:name":"Ibis",
    "wof:placetype":"venue"
},
  "geometry": {"coordinates":[2.6628110409,51.0724334717],"type":"Point"}
}