{
  "type": "Feature",
  "properties": {
    "addr:full":"Doorniksesteenweg 349 Avelgem West-Vlaanderen 8580",
    "addr:housenumber":"349",
    "addr:postcode":"8580",
    "addr:street":"Doorniksesteenweg",
    "iso:country":"BE",
    "sg:address":"Doorniksesteenweg 349",
    "sg:city":"Avelgem",
    "sg:classifiers":[
        {
            "category":"Bars & Pubs",
            "type":"Food & Drink"
        }
    ],
    "sg:phone":"+32 56 64 50 17",
    "sg:postcode":"8580",
    "sg:province":"West-Vlaanderen",
    "wof:name":"Welkom (de)",
    "wof:placetype":"venue"
},
  "geometry": {"coordinates":[3.4408800602,50.7650718689],"type":"Point"}
}