{
  "type": "Feature",
  "properties": {
    "addr:full":"Mechelsesteenweg 13 Mortsel Antwerpen 2640",
    "addr:housenumber":"13",
    "addr:postcode":"2640",
    "addr:street":"Mechelsesteenweg",
    "iso:country":"BE",
    "sg:address":"Mechelsesteenweg 13",
    "sg:city":"Mortsel",
    "sg:orig_category":"Bloemen and planten",
    "sg:phone":"+32 3 448 22 11",
    "sg:postcode":"2640",
    "sg:province":"Antwerpen",
    "wof:name":"Wilde Wingerd",
    "wof:placetype":"venue"
},
  "geometry": {"coordinates":[4.4509410858,51.1695556641],"type":"Point"}
}