{
  "type": "Feature",
  "properties": {
    "addr:full":"Cardijnlaan 33 Knesselare Oost-Vlaanderen 9910",
    "addr:housenumber":"33",
    "addr:postcode":"9910",
    "addr:street":"Cardijnlaan;Oost-Vlaanderen",
    "iso:country":"BE",
    "sg:address":"Cardijnlaan 33",
    "sg:city":"Knesselare",
    "sg:orig_category":"Plaatsen van vloer- and muurbekleding Schilders",
    "sg:phone":"+32 9 375 02 15",
    "sg:postcode":"9910",
    "sg:province":"Oost-Vlaanderen",
    "wof:name":"Diederik Ryserhove",
    "wof:placetype":"venue"
},
  "geometry": {"coordinates":[3.4869029522,51.130317688],"type":"Point"}
}