{
  "type": "Feature",
  "properties": {
    "iso:country":"BE",
    "sg:address":"Galerie De L'auberge",
    "sg:city":"Spa",
    "sg:orig_category":"Kapsalons",
    "sg:phone":"+32 87 77 47 15",
    "sg:postcode":"4900",
    "sg:province":"Li\u00e8ge",
    "wof:name":"Coiffure Sculpture",
    "wof:placetype":"venue"
},
  "geometry": {"coordinates":[5.8635501862,50.4911689758],"type":"Point"}
}