{
  "type": "Feature",
  "properties": {
    "addr:full":"Chauss\u00e9e De Wervicq 394 Comines-warneton (comines) Hainaut 7780",
    "addr:housenumber":"394",
    "addr:postcode":"7780",
    "addr:street":"Chausse\u0301E De Wervicq",
    "iso:country":"BE",
    "sg:address":"Chauss\u00e9e De Wervicq 394",
    "sg:city":"Comines-warneton (comines)",
    "sg:orig_category":"Non-Classified Establishments",
    "sg:phone":"+32 56 55 90 20",
    "sg:postcode":"7780",
    "sg:province":"Hainaut",
    "wof:name":"Eleven Group Belgium Sprl",
    "wof:placetype":"venue"
},
  "geometry": {"coordinates":[3.0177650452,50.7766265869],"type":"Point"}
}