{
  "type": "Feature",
  "properties": {
    "addr:full":"Arendsstraat 62bb Harelbeke West-Vlaanderen 8530",
    "addr:housenumber":"62bb",
    "addr:postcode":"8530",
    "addr:street":"Arendsstraat",
    "iso:country":"BE",
    "sg:address":"Arendsstraat 62bb",
    "sg:city":"Harelbeke",
    "sg:orig_category":"Enseignement maternel and primaire",
    "sg:phone":"+32 56 71 92 22",
    "sg:postcode":"8530",
    "sg:province":"West-Vlaanderen",
    "wof:name":"Basisschool",
    "wof:placetype":"venue"
},
  "geometry": {"coordinates":[3.3205718994,50.8551063538],"type":"Point"}
}