{
  "type": "Feature",
  "properties": {
    "addr:full":"Rimeir 105 Wichelen Oost-Vlaanderen 9260",
    "addr:housenumber":"105",
    "addr:postcode":"9260",
    "addr:street":"Rimeir",
    "iso:country":"BE",
    "sg:address":"Rimeir 105",
    "sg:city":"Wichelen",
    "sg:classifiers":[
        {
            "category":"Retail",
            "subcategory":"Event Space",
            "type":"Services"
        }
    ],
    "sg:phone":"+32 475 76 36 30",
    "sg:postcode":"9260",
    "sg:province":"Oost-Vlaanderen",
    "sg:tags":[
        "product",
        "snack",
        "speciality",
        "potato",
        "stand",
        "fried"
    ],
    "wof:name":"Atravet Bvba",
    "wof:placetype":"venue"
},
  "geometry": {"coordinates":[3.9978759289,50.9910545349],"type":"Point"}
}