{
  "type": "Feature",
  "properties": {
    "iso:country":"BE",
    "sg:address":"Haachtsebaan 47",
    "sg:city":"Putte",
    "sg:classifiers":[
        {
            "category":"Building & Trades",
            "subcategory":"Landscaping Services",
            "type":"Services"
        }
    ],
    "sg:phone":"+32 15 23 39 39",
    "sg:postcode":"2580",
    "sg:province":"Antwerpen",
    "sg:tags":[
        "etude",
        "technique",
        "ing\u00e9nierie"
    ],
    "wof:name":"Serneels G",
    "wof:placetype":"venue"
},
  "geometry": {"coordinates":[4.6645598412,51.0289001465],"type":"Point"}
}