{
  "type": "Feature",
  "properties": {
    "addr:full":"Rue De La Reine 1 Philippeville Namur 5600",
    "addr:housenumber":"1",
    "addr:postcode":"5600",
    "addr:street":"Rue De La Reine",
    "iso:country":"BE",
    "sg:address":"Rue De La Reine 1",
    "sg:city":"Philippeville",
    "sg:orig_category":"Banken and kredietinstellingen",
    "sg:phone":"+32 71 66 68 24",
    "sg:postcode":"5600",
    "sg:province":"Namur",
    "wof:name":"Fortis",
    "wof:placetype":"venue"
},
  "geometry": {"coordinates":[4.5436468124,50.195728302],"type":"Point"}
}