{
  "type": "Feature",
  "properties": {
    "addr:full":"Weertersteenweg 107 Maaseik Limburg 3680",
    "addr:housenumber":"107",
    "addr:postcode":"3680",
    "addr:street":"Weertersteenweg",
    "iso:country":"BE",
    "sg:address":"Weertersteenweg 107",
    "sg:city":"Maaseik",
    "sg:classifiers":[
        {
            "category":"Retail",
            "subcategory":"Repair Shop",
            "type":"Services"
        }
    ],
    "sg:phone":"+32 89 56 84 14",
    "sg:postcode":"3680",
    "sg:province":"Limburg",
    "sg:tags":[
        "mainten",
        "-",
        "parquet"
    ],
    "wof:name":"Smits L",
    "wof:placetype":"venue"
},
  "geometry": {"coordinates":[5.7799139023,51.1032752991],"type":"Point"}
}