{
  "type": "Feature",
  "properties": {
    "iso:country":"BE",
    "sg:address":"Baksteenkaai 26",
    "sg:city":"Brussel/bruxelles",
    "sg:orig_category":"Artsen and specialisten",
    "sg:phone":"+32 2 513 73 34",
    "sg:postcode":"1000",
    "sg:province":"Bruxelles-Capitale",
    "wof:name":"Cl\u00c9ment Moray",
    "wof:placetype":"venue"
},
  "geometry": {"coordinates":[4.3477258682,50.8515548706],"type":"Point"}
}