{
  "type": "Feature",
  "properties": {
    "iso:country":"BE",
    "sg:address":"Chauss\u00c9e De Bruxelles 64",
    "sg:city":"Charleroi",
    "sg:orig_category":"Installation \u00e9lectrique industrielle. Installation \u00e9lectrique r\u00e9sidentielle. Magasins de r\u00e9parations",
    "sg:phone":"+32 71 32 06 44",
    "sg:postcode":"6020",
    "sg:province":"Hainaut",
    "wof:name":"Miranda",
    "wof:placetype":"venue"
},
  "geometry": {"coordinates":[4.4378871918,50.4149703979],"type":"Point"}
}