{
  "type": "Feature",
  "properties": {
    "addr:full":"Rue Champ Rodange 88 Waterloo Brabant Wallon 1410",
    "addr:housenumber":"88",
    "addr:postcode":"1410",
    "addr:street":"Rue Champ Rodange",
    "iso:country":"BE",
    "sg:address":"Rue Champ Rodange 88",
    "sg:city":"Waterloo",
    "sg:orig_category":"Plaatsen van vloer- and muurbekleding Schilders",
    "sg:phone":"+32 2 354 14 40",
    "sg:postcode":"1410",
    "sg:province":"Brabant Wallon",
    "wof:name":"Gerard Hancq",
    "wof:placetype":"venue"
},
  "geometry": {"coordinates":[4.3689460754,50.7122383118],"type":"Point"}
}