{
  "type": "Feature",
  "properties": {
    "addr:full":"Rue Docteur Jeanty 15 Virton Luxembourg 6760",
    "addr:housenumber":"15",
    "addr:postcode":"6760",
    "addr:street":"Rue Docteur Jeanty",
    "iso:country":"BE",
    "sg:address":"Rue Docteur Jeanty 15",
    "sg:city":"Virton",
    "sg:orig_category":"Schoenen",
    "sg:phone":"+32 63 57 80 10",
    "sg:postcode":"6760",
    "sg:province":"Luxembourg",
    "wof:name":"Shoes In The Box",
    "wof:placetype":"venue"
},
  "geometry": {"coordinates":[5.5309329033,49.5677642822],"type":"Point"}
}