{
  "type": "Feature",
  "properties": {
    "addr:full":"Stationsstraat 1 Sint-truiden Limburg 3800",
    "addr:housenumber":"1",
    "addr:postcode":"3800",
    "addr:street":"Stationsstraat",
    "iso:country":"BE",
    "sg:address":"Stationsstraat 1",
    "sg:city":"Sint-truiden",
    "sg:classifiers":[
        {
            "category":"Bars & Pubs",
            "type":"Food & Drink"
        }
    ],
    "sg:phone":"+32 11 70 77 57",
    "sg:postcode":"3800",
    "sg:province":"Limburg",
    "wof:name":"De Steppe",
    "wof:placetype":"venue"
},
  "geometry": {"coordinates":[5.1799669266,50.8158454895],"type":"Point"}
}