{
  "type": "Feature",
  "properties": {
    "iso:country":"BE",
    "sg:address":"Heldenpln 28",
    "sg:city":"Oostham",
    "sg:classifiers":[
        {
            "category":"Banks & Credit Unions",
            "subcategory":"Bank",
            "type":"Services"
        }
    ],
    "sg:phone":"+32 11 34 44 90",
    "sg:postcode":"3969",
    "wof:name":"Gemeentekrediet",
    "wof:placetype":"venue"
},
  "geometry": {"coordinates":[32.143699646,-27.3739700317],"type":"Point"}
}