{
  "type": "Feature",
  "properties": {
    "iso:country":"BE",
    "sg:address":"Geverslaan 16",
    "sg:city":"Dilsen-stokkem",
    "sg:orig_category":"M\u00e9decins and sp\u00e9cialistes",
    "sg:phone":"+32 89 75 49 71",
    "sg:postcode":"3650",
    "sg:province":"Limburg",
    "wof:name":"Annemie Claes",
    "wof:placetype":"venue"
},
  "geometry": {"coordinates":[5.727396965,51.0364189148],"type":"Point"}
}