{
  "type": "Feature",
  "properties": {
    "iso:country":"BE",
    "sg:address":"Noordkaai 34",
    "sg:city":"Izegem",
    "sg:orig_category":"Non-Classified Establishments",
    "sg:phone":"+32 51 31 20 24",
    "sg:postcode":"8870",
    "sg:province":"West-Vlaanderen",
    "wof:name":"Decof Borstelfabrieken",
    "wof:placetype":"venue"
},
  "geometry": {"coordinates":[3.1849400997,50.9305114746],"type":"Point"}
}