{
  "type": "Feature",
  "properties": {
    "addr:full":"Avenue De La Chasse 109 Bruxelles (etterbeek) Bruxelles-Capitale 1040",
    "addr:housenumber":"109",
    "addr:postcode":"1040",
    "addr:street":"Avenue De La Chasse",
    "iso:country":"BE",
    "sg:address":"Avenue De La Chasse 109",
    "sg:city":"Bruxelles (etterbeek)",
    "sg:classifiers":[
        {
            "category":"Manufacturing",
            "subcategory":"Musical Instruments",
            "type":"Manufacturing & Wholesale Goods"
        }
    ],
    "sg:phone":"+32 2 736 33 23",
    "sg:postcode":"1040",
    "sg:province":"Bruxelles-Capitale",
    "sg:tags":[
        "piano"
    ],
    "wof:name":"Janssens Piano's",
    "wof:placetype":"venue"
},
  "geometry": {"coordinates":[4.3926529884,50.8332443237],"type":"Point"}
}