{
  "type": "Feature",
  "properties": {
    "addr:full":"Stationsstraat 162 Gavere Oost-Vlaanderen 9890",
    "addr:housenumber":"162",
    "addr:postcode":"9890",
    "addr:street":"Stationsstraat",
    "iso:country":"BE",
    "sg:address":"Stationsstraat 162",
    "sg:city":"Gavere",
    "sg:orig_category":"Boucheries",
    "sg:phone":"+32 9 384 79 49",
    "sg:postcode":"9890",
    "sg:province":"Oost-Vlaanderen",
    "wof:name":"Raphael Tronquo",
    "wof:placetype":"venue"
},
  "geometry": {"coordinates":[3.6481471062,50.9294776917],"type":"Point"}
}