{
  "type": "Feature",
  "properties": {
    "iso:country":"BE",
    "sg:address":"Weldadigheidstraat 25",
    "sg:city":"Zomergem",
    "sg:classifiers":[
        {
            "category":"Social Services",
            "subcategory":"Child Care",
            "type":"Services"
        }
    ],
    "sg:phone":"+32 9 372 45 31",
    "sg:postcode":"9930",
    "sg:province":"Oost-Vlaanderen",
    "sg:tags":[
        "baby",
        "nursery",
        "day",
        "sitting"
    ],
    "wof:name":"'t Fr\u00f6belke",
    "wof:placetype":"venue"
},
  "geometry": {"coordinates":[3.5658049583,51.1159706116],"type":"Point"}
}