{
  "type": "Feature",
  "properties": {
    "addr:full":"August Wautersstraat 20 Temse Oost-Vlaanderen 9140",
    "addr:housenumber":"20",
    "addr:postcode":"9140",
    "addr:street":"August Wautersstraat",
    "iso:country":"BE",
    "sg:address":"August Wautersstraat 20",
    "sg:city":"Temse",
    "sg:classifiers":[
        {
            "category":"Cafe",
            "type":"Food & Drink"
        }
    ],
    "sg:phone":"+32 3 711 00 03",
    "sg:postcode":"9140",
    "sg:province":"Oost-Vlaanderen",
    "sg:tags":[
        "snack-bars"
    ],
    "wof:name":"Tempolunch",
    "wof:placetype":"venue"
},
  "geometry": {"coordinates":[4.2189440727,51.1275367737],"type":"Point"}
}