{
  "type": "Feature",
  "properties": {
    "addr:full":"Vageweenstraat 8 Izegem West-Vlaanderen 8870",
    "addr:housenumber":"8",
    "addr:postcode":"8870",
    "addr:street":"Vageweenstraat",
    "iso:country":"BE",
    "sg:address":"Vageweenstraat 8",
    "sg:city":"Izegem",
    "sg:orig_category":"Producteurs de l\u00e9gumes",
    "sg:phone":"+32 51 30 34 56",
    "sg:postcode":"8870",
    "sg:province":"West-Vlaanderen",
    "wof:name":"Antoon Verhelle",
    "wof:placetype":"venue"
},
  "geometry": {"coordinates":[3.2002809048,50.9340515137],"type":"Point"}
}