{
  "type": "Feature",
  "properties": {
    "addr:full":"Chauss\u00c9e De Bruxelles 69 Nivelles Brabant Wallon 1400",
    "addr:housenumber":"69",
    "addr:postcode":"1400",
    "addr:street":"Chausse\u0301E De Bruxelles",
    "iso:country":"BE",
    "sg:address":"Chauss\u00c9e De Bruxelles 69",
    "sg:city":"Nivelles",
    "sg:orig_category":"M\u00e9decins and sp\u00e9cialistes",
    "sg:phone":"+32 67 21 28 09",
    "sg:postcode":"1400",
    "sg:province":"Brabant Wallon",
    "wof:name":"Carine Mahieu",
    "wof:placetype":"venue"
},
  "geometry": {"coordinates":[4.3307948112,50.604850769],"type":"Point"}
}