{
  "type": "Feature",
  "properties": {
    "iso:country":"BE",
    "sg:address":"Route De La Roche 17",
    "sg:city":"Rendeux",
    "sg:classifiers":[
        {
            "category":"Restaurant",
            "type":"Food & Drink"
        }
    ],
    "sg:phone":"+32 84 47 71 92",
    "sg:postcode":"6987",
    "sg:province":"Luxembourg",
    "wof:name":"L'entrecote",
    "wof:placetype":"venue"
},
  "geometry": {"coordinates":[5.5129008293,50.2328643799],"type":"Point"}
}