{
  "type": "Feature",
  "properties": {
    "iso:country":"BE",
    "sg:address":"Jan Baptist Guinardstraat 32",
    "sg:city":"Gent",
    "sg:orig_category":"Persagentschappen",
    "sg:phone":"+32 9 233 60 05",
    "sg:postcode":"9000",
    "sg:province":"Oost-Vlaanderen",
    "wof:name":"Annick Roetynck",
    "wof:placetype":"venue"
},
  "geometry": {"coordinates":[3.724613905,51.0464859009],"type":"Point"}
}