{
  "type": "Feature",
  "properties": {
    "addr:full":"Ch De Wavre 504 Grez-doiceau Brabant Wallon 1390",
    "addr:housenumber":"504",
    "addr:postcode":"1390",
    "addr:street":"Ch De Wavre",
    "iso:country":"BE",
    "sg:address":"Ch De Wavre 504",
    "sg:city":"Grez-doiceau",
    "sg:classifiers":[
        {
            "category":"Professional",
            "subcategory":"Engineering",
            "type":"Services"
        }
    ],
    "sg:phone":"+32 10 84 26 69",
    "sg:postcode":"1390",
    "sg:province":"Brabant Wallon",
    "sg:tags":[
        "machine",
        "-",
        "environment",
        "equipment",
        "machinery",
        "mechanical"
    ],
    "wof:name":"Aqua Vital Sa",
    "wof:placetype":"venue"
},
  "geometry": {"coordinates":[4.6466069221,50.7328109741],"type":"Point"}
}