{
  "type": "Feature",
  "properties": {
    "iso:country":"BE",
    "sg:address":"Chauss\u00c9e De Namur 307",
    "sg:city":"Gembloux",
    "sg:classifiers":[
        {
            "category":"Restaurant",
            "type":"Food & Drink"
        }
    ],
    "sg:phone":"+32 81 60 00 46",
    "sg:postcode":"5030",
    "sg:province":"Namur",
    "wof:name":"Le Chalet",
    "wof:placetype":"venue"
},
  "geometry": {"coordinates":[4.7088198662,50.5527381897],"type":"Point"}
}