{
  "type": "Feature",
  "properties": {
    "iso:country":"BE",
    "sg:address":"Avenue L\u00c9on Debatty 18",
    "sg:city":"Anderlecht",
    "sg:orig_category":"Plaatsen van vloer- and muurbekleding Schilders",
    "sg:phone":"+32 2 411 89 84",
    "sg:postcode":"1070",
    "sg:province":"Bruxelles-Capitale",
    "wof:name":"Curtains",
    "wof:placetype":"venue"
},
  "geometry": {"coordinates":[4.3132147789,50.8447418213],"type":"Point"}
}