{
  "type": "Feature",
  "properties": {
    "iso:country":"BE",
    "sg:address":"Abelenstraat 11",
    "sg:city":"Kuurne",
    "sg:classifiers":[
        {
            "category":"Personal",
            "subcategory":"Beauty Salon",
            "type":"Services"
        }
    ],
    "sg:phone":"+32 56 71 97 17",
    "sg:postcode":"8520",
    "sg:province":"West-Vlaanderen",
    "sg:tags":[
        "lady",
        "-",
        "hairdressing"
    ],
    "wof:name":"Caresse",
    "wof:placetype":"venue"
},
  "geometry": {"coordinates":[3.2942099571,50.8584327698],"type":"Point"}
}