{
  "type": "Feature",
  "properties": {
    "addr:full":"Brederodestr 21 Brussel Bruxelles-Capitale 1000",
    "addr:housenumber":"21",
    "addr:postcode":"1000",
    "addr:street":"Brederodestr",
    "iso:country":"BE",
    "sg:address":"Brederodestr 21",
    "sg:city":"Brussel",
    "sg:classifiers":[
        {
            "category":"Professional",
            "subcategory":"Business Services",
            "type":"Services"
        }
    ],
    "sg:phone":"+32 2 511 18 40",
    "sg:postcode":"1000",
    "sg:province":"Bruxelles-Capitale",
    "sg:tags":[
        "body",
        "advice"
    ],
    "wof:name":"Fondation Roi Baudouin",
    "wof:placetype":"venue"
},
  "geometry": {"coordinates":[4.3620419502,50.8403358459],"type":"Point"}
}