{
  "type": "Feature",
  "properties": {
    "iso:country":"BE",
    "sg:address":"Phoenixstraat 41",
    "sg:city":"Gent",
    "sg:classifiers":[
        {
            "category":"Bakery",
            "type":"Food & Drink"
        }
    ],
    "sg:phone":"+32 9 226 18 52",
    "sg:postcode":"9000",
    "sg:province":"Oost-Vlaanderen",
    "sg:tags":[
        "confectioner",
        "baker"
    ],
    "wof:name":"Baert W",
    "wof:placetype":"venue"
},
  "geometry": {"coordinates":[3.7061779499,51.0578613281],"type":"Point"}
}