{
  "type": "Feature",
  "properties": {
    "addr:full":"Albert Decockstraat 22 Avelgem West-Vlaanderen 8580",
    "addr:housenumber":"22",
    "addr:postcode":"8580",
    "addr:street":"Albert Decockstraat",
    "iso:country":"BE",
    "sg:address":"Albert Decockstraat 22",
    "sg:city":"Avelgem",
    "sg:orig_category":"Fietsen",
    "sg:phone":"+32 56 64 77 10",
    "sg:postcode":"8580",
    "sg:province":"West-Vlaanderen",
    "wof:name":"Ronny Houttequiet",
    "wof:placetype":"venue"
},
  "geometry": {"coordinates":[3.4368851185,50.7822608948],"type":"Point"}
}