{
  "type": "Feature",
  "properties": {
    "addr:full":"Place Jean Jaur\u00c8s 24 Herstal Li\u00e8ge 4040",
    "addr:housenumber":"24",
    "addr:postcode":"4040",
    "addr:street":"Place Jean Jaure\u0300S",
    "iso:country":"BE",
    "sg:address":"Place Jean Jaur\u00c8s 24",
    "sg:city":"Herstal",
    "sg:classifiers":[
        {
            "category":"Restaurant",
            "type":"Food & Drink"
        }
    ],
    "sg:phone":"+32 4 240 01 76",
    "sg:postcode":"4040",
    "sg:province":"Li\u00e8ge",
    "sg:tags":[
        "caf\u00e9s"
    ],
    "wof:name":"Taverne Invest",
    "wof:placetype":"venue"
},
  "geometry": {"coordinates":[5.6300039291,50.6655921936],"type":"Point"}
}