{
  "type": "Feature",
  "properties": {
    "addr:full":"Gauwelstraat 13 Zwevegem (heestert) West-Vlaanderen 8551",
    "addr:housenumber":"13",
    "addr:postcode":"8551",
    "addr:street":"Gauwelstraat",
    "iso:country":"BE",
    "sg:address":"Gauwelstraat 13",
    "sg:city":"Zwevegem (heestert)",
    "sg:classifiers":[
        {
            "category":"Shopping",
            "subcategory":"Florist",
            "type":"Retail Goods"
        }
    ],
    "sg:phone":"+32 56 64 87 28",
    "sg:postcode":"8551",
    "sg:province":"West-Vlaanderen",
    "wof:name":"Ann-rosi",
    "wof:placetype":"venue"
},
  "geometry": {"coordinates":[3.40949893,50.7819404602],"type":"Point"}
}