{
  "type": "Feature",
  "properties": {
    "iso:country":"BE",
    "sg:address":"Sprietestraat 176",
    "sg:city":"Waregem",
    "sg:orig_category":"Gespecialiseerde niet-residenti\u00eble bouw SMEEDWERK, METAALBEWERKING AND POEDERMETALLURGIE",
    "sg:phone":"+32 56 71 26 86",
    "sg:postcode":"8792",
    "sg:province":"West-Vlaanderen",
    "wof:name":"Luco",
    "wof:placetype":"venue"
},
  "geometry": {"coordinates":[3.3663299084,50.8743057251],"type":"Point"}
}