{
  "type": "Feature",
  "properties": {
    "iso:country":"BE",
    "sg:address":"Aardenburgkalseide 254",
    "sg:city":"Maldegem",
    "sg:orig_category":"Services de publipostage",
    "sg:phone":"+32 50 71 84 00",
    "sg:postcode":"9990",
    "sg:province":"Oost-Vlaanderen",
    "wof:name":"New Communications Concept",
    "wof:placetype":"venue"
},
  "geometry": {"coordinates":[3.4467310905,51.2226448059],"type":"Point"}
}