{
  "type": "Feature",
  "properties": {
    "addr:full":"Zand 49 Brasschaat Antwerpen 2930",
    "addr:housenumber":"49",
    "addr:postcode":"2930",
    "addr:street":"Zand",
    "iso:country":"BE",
    "sg:address":"Zand 49",
    "sg:city":"Brasschaat",
    "sg:classifiers":[
        {
            "category":"Arena",
            "subcategory":"Sports Club",
            "type":"Entertainment"
        }
    ],
    "sg:phone":"+32 3 651 75 26",
    "sg:postcode":"2930",
    "sg:province":"Antwerpen",
    "sg:tags":[
        "de"
    ],
    "wof:name":"Heide Vrienden",
    "wof:placetype":"venue"
},
  "geometry": {"coordinates":[4.5026531219,51.2959365845],"type":"Point"}
}