{
  "type": "Feature",
  "properties": {
    "addr:full":"Rue Hamaide 53b Redu Luxembourg 6890",
    "addr:housenumber":"53b",
    "addr:postcode":"6890",
    "addr:street":"Rue Hamaide",
    "iso:country":"BE",
    "sg:address":"Rue Hamaide 53b",
    "sg:city":"Redu",
    "sg:orig_category":"Biens d'occasion. Librairies. Librairies. Biens d'occasion",
    "sg:phone":"+32 61 65 60 34",
    "sg:postcode":"6890",
    "sg:province":"Luxembourg",
    "wof:name":"Livre Et Passion",
    "wof:placetype":"venue"
},
  "geometry": {"coordinates":[5.1595039368,50.0076828003],"type":"Point"}
}