{
  "type": "Feature",
  "properties": {
    "iso:country":"BE",
    "sg:address":"Rue Labouxhe 38",
    "sg:city":"Soumagne",
    "sg:orig_category":"Entretien and r\u00e9parations de voitures",
    "sg:phone":"+32 4 377 23 24",
    "sg:postcode":"4633",
    "sg:province":"Li\u00e8ge",
    "wof:name":"Victor Colson",
    "wof:placetype":"venue"
},
  "geometry": {"coordinates":[5.7387871742,50.6371040344],"type":"Point"}
}