{
  "type": "Feature",
  "properties": {
    "addr:full":"Steenbrugstraat 84 Harelbeke West-Vlaanderen 8530",
    "addr:housenumber":"84",
    "addr:postcode":"8530",
    "addr:street":"Steenbrugstraat",
    "iso:country":"BE",
    "sg:address":"Steenbrugstraat 84",
    "sg:city":"Harelbeke",
    "sg:orig_category":"Woningbouw",
    "sg:phone":"+32 56 21 75 65",
    "sg:postcode":"8530",
    "sg:province":"West-Vlaanderen",
    "wof:name":"Marnix Bouckaert",
    "wof:placetype":"venue"
},
  "geometry": {"coordinates":[3.3245649338,50.8337173462],"type":"Point"}
}