{
  "type": "Feature",
  "properties": {
    "iso:country":"BE",
    "sg:address":"Kapelstraat 58",
    "sg:city":"Keerbergen",
    "sg:classifiers":[
        {
            "category":"Social Services",
            "type":"Services"
        }
    ],
    "sg:phone":"+32 15 23 59 61",
    "sg:postcode":"3140",
    "sg:province":"Vlaams-Brabant",
    "wof:name":"De Sluis",
    "wof:placetype":"venue"
},
  "geometry": {"coordinates":[4.7084407806,51.0127220154],"type":"Point"}
}