{
  "type": "Feature",
  "properties": {
    "addr:full":"Nieuwstraat 8 Aalst Oost-Vlaanderen 9300",
    "addr:housenumber":"8",
    "addr:postcode":"9300",
    "addr:street":"Nieuwstraat",
    "iso:country":"BE",
    "sg:address":"Nieuwstraat 8",
    "sg:city":"Aalst",
    "sg:orig_category":"Gespecialiseerde residenti\u00eble bouw",
    "sg:phone":"+32 53 70 97 29",
    "sg:postcode":"9300",
    "sg:province":"Oost-Vlaanderen",
    "wof:name":"Aqua-tech",
    "wof:placetype":"venue"
},
  "geometry": {"coordinates":[4.0366401672,50.9384689331],"type":"Point"}
}