{
  "type": "Feature",
  "properties": {
    "addr:full":"Rubensstraat 45 Boom Antwerpen 2850",
    "addr:housenumber":"45",
    "addr:postcode":"2850",
    "addr:street":"Rubensstraat",
    "iso:country":"BE",
    "sg:address":"Rubensstraat 45",
    "sg:city":"Boom",
    "sg:classifiers":[
        {
            "category":"Insurance",
            "subcategory":"Insurance Agent",
            "type":"Services"
        }
    ],
    "sg:phone":"+32 3 888 95 59",
    "sg:postcode":"2850",
    "sg:province":"Antwerpen",
    "sg:tags":[
        "broker"
    ],
    "wof:name":"Bankverzekeren Van Camp L",
    "wof:placetype":"venue"
},
  "geometry": {"coordinates":[4.3707208633,51.096950531],"type":"Point"}
}