{
  "type": "Feature",
  "properties": {
    "addr:full":"Liezele Dorp 12b Puurs (liezele) Antwerpen 2870",
    "addr:housenumber":"12b",
    "addr:postcode":"2870",
    "addr:street":"Liezele Dorp",
    "iso:country":"BE",
    "sg:address":"Liezele Dorp 12b",
    "sg:city":"Puurs (liezele)",
    "sg:classifiers":[
        {
            "category":"Professional",
            "subcategory":"Management & Consulting",
            "type":"Services"
        }
    ],
    "sg:phone":"+32 3 899 67 48",
    "sg:postcode":"2870",
    "sg:province":"Antwerpen",
    "sg:tags":[
        "consultant"
    ],
    "wof:name":"Verstry Adviesgroep Bvba",
    "wof:placetype":"venue"
},
  "geometry": {"coordinates":[4.2796697617,51.0661506653],"type":"Point"}
}