{
  "type": "Feature",
  "properties": {
    "addr:full":"Rue Emile Vandervelde 68bb Charleroi Hainaut 6030",
    "addr:housenumber":"68bb",
    "addr:postcode":"6030",
    "addr:street":"Rue Emile Vandervelde;Hainaut",
    "iso:country":"BE",
    "sg:address":"Rue Emile Vandervelde 68bb",
    "sg:city":"Charleroi",
    "sg:orig_category":"Verplichte sociale verzekeringen",
    "sg:phone":"+32 71 32 86 92",
    "sg:postcode":"6030",
    "sg:province":"Hainaut",
    "wof:name":"Mutualit\u00c9 Profes. & Libre",
    "wof:placetype":"venue"
},
  "geometry": {"coordinates":[4.3935260773,50.4101104736],"type":"Point"}
}