{
  "type": "Feature",
  "properties": {
    "addr:full":"Rue De L'harmonie 22 Arlon Luxembourg 6700",
    "addr:housenumber":"22",
    "addr:postcode":"6700",
    "addr:street":"Rue De L'Harmonie",
    "iso:country":"BE",
    "sg:address":"Rue De L'harmonie 22",
    "sg:city":"Arlon",
    "sg:orig_category":"Pain, p\u00e2tisseries and confiseries",
    "sg:phone":"+32 63 22 14 75",
    "sg:postcode":"6700",
    "sg:province":"Luxembourg",
    "wof:name":"Jacques Wiltgen",
    "wof:placetype":"venue"
},
  "geometry": {"coordinates":[5.7703080177,49.6859512329],"type":"Point"}
}