{
  "type": "Feature",
  "properties": {
    "addr:full":"Dorpsstraat 18 Lubbeek Vlaams-Brabant 3210",
    "addr:housenumber":"18",
    "addr:postcode":"3210",
    "addr:street":"Dorpsstraat",
    "iso:country":"BE",
    "sg:address":"Dorpsstraat 18",
    "sg:city":"Lubbeek",
    "sg:orig_category":"Enseignement maternel and primaire",
    "sg:phone":"+32 16 63 42 78",
    "sg:postcode":"3210",
    "sg:province":"Vlaams-Brabant",
    "wof:name":"Vrije Basisschool",
    "wof:placetype":"venue"
},
  "geometry": {"coordinates":[4.8436188698,50.8793869019],"type":"Point"}
}