{
  "type": "Feature",
  "properties": {
    "iso:country":"BE",
    "sg:address":"Rue D'haine 19",
    "sg:city":"Morlanwelz (mont-sainte-aldegonde)",
    "sg:classifiers":[
        {
            "category":"Food & Beverages",
            "subcategory":"Groceries & Convenience Stores",
            "type":"Retail Goods"
        }
    ],
    "sg:phone":"+32 64 33 24 04",
    "sg:postcode":"7141",
    "sg:province":"Hainaut",
    "sg:tags":[
        "grocer"
    ],
    "wof:name":"Degroote M",
    "wof:placetype":"venue"
},
  "geometry": {"coordinates":[4.221031189,50.4307403564],"type":"Point"}
}