{
  "type": "Feature",
  "properties": {
    "addr:full":"Overleiestraat 23 Kortrijk West-Vlaanderen 8500",
    "addr:housenumber":"23",
    "addr:postcode":"8500",
    "addr:street":"Overleiestraat",
    "iso:country":"BE",
    "sg:address":"Overleiestraat 23",
    "sg:city":"Kortrijk",
    "sg:orig_category":"Banques and organismes de cr\u00e9dit",
    "sg:phone":"+32 56 35 39 77",
    "sg:postcode":"8500",
    "sg:province":"West-Vlaanderen",
    "wof:name":"Fortis",
    "wof:placetype":"venue"
},
  "geometry": {"coordinates":[3.2604300976,50.8324508667],"type":"Point"}
}