{
  "type": "Feature",
  "properties": {
    "iso:country":"BE",
    "sg:address":"Rue De Bricgniot 63",
    "sg:city":"Namur (saint-servais)",
    "sg:classifiers":[
        {
            "category":"Real Estate",
            "subcategory":"Architect",
            "type":"Services"
        }
    ],
    "sg:phone":"+32 497 41 48 85",
    "sg:postcode":"5002",
    "sg:province":"Namur",
    "wof:name":"Bister F",
    "wof:placetype":"venue"
},
  "geometry": {"coordinates":[4.8462319374,50.4782791138],"type":"Point"}
}