{
  "type": "Feature",
  "properties": {
    "addr:full":"Fotsesteenweg 30 St-katelijne-waver Antwerpen 2860",
    "addr:housenumber":"30",
    "addr:postcode":"2860",
    "addr:street":"Fotsesteenweg",
    "iso:country":"BE",
    "sg:address":"Fotsesteenweg 30",
    "sg:city":"St-katelijne-waver",
    "sg:classifiers":[
        {
            "category":"Farming",
            "subcategory":"Farm",
            "type":"Manufacturing & Wholesale Goods"
        }
    ],
    "sg:phone":"+32 15 31 22 57",
    "sg:postcode":"2860",
    "sg:province":"Antwerpen",
    "sg:tags":[
        "horticulture",
        "agriculture",
        "livestock"
    ],
    "wof:name":"De Ceuster Nv",
    "wof:placetype":"venue"
},
  "geometry": {"coordinates":[4.5073280334,51.0656814575],"type":"Point"}
}