{
  "type": "Feature",
  "properties": {
    "addr:full":"Menenstraat 312 Wevelgem West-Vlaanderen 8560",
    "addr:housenumber":"312",
    "addr:postcode":"8560",
    "addr:street":"Menenstraat",
    "iso:country":"BE",
    "sg:address":"Menenstraat 312",
    "sg:city":"Wevelgem",
    "sg:classifiers":[
        {
            "category":"Retail",
            "subcategory":"Auto Repair",
            "type":"Services"
        }
    ],
    "sg:phone":"+32 56 42 39 94",
    "sg:postcode":"8560",
    "sg:province":"West-Vlaanderen",
    "sg:tags":[
        "automobile",
        "-",
        "wrecking"
    ],
    "wof:name":"Kleine Staarman",
    "wof:placetype":"venue"
},
  "geometry": {"coordinates":[3.1617410183,50.803768158],"type":"Point"}
}