{
  "type": "Feature",
  "properties": {
    "addr:full":"Jozef Cardijnlaan 2 Gent Oost-Vlaanderen 9041",
    "addr:housenumber":"2",
    "addr:postcode":"9041",
    "addr:street":"Jozef Cardijnlaan;Oost-Vlaanderen",
    "iso:country":"BE",
    "sg:address":"Jozef Cardijnlaan 2",
    "sg:city":"Gent",
    "sg:orig_category":"M\u00e9decins and sp\u00e9cialistes",
    "sg:phone":"+32 9 251 21 51",
    "sg:postcode":"9041",
    "sg:province":"Oost-Vlaanderen",
    "wof:name":"Hubert Vermeersch",
    "wof:placetype":"venue"
},
  "geometry": {"coordinates":[3.7679879665,51.0988922119],"type":"Point"}
}