{
  "type": "Feature",
  "properties": {
    "addr:full":"Boekweykoekstraat 4 Steenokkerzeel Vlaams-Brabant 1820",
    "addr:housenumber":"4",
    "addr:postcode":"1820",
    "addr:street":"Boekweykoekstraat",
    "iso:country":"BE",
    "sg:address":"Boekweykoekstraat 4",
    "sg:city":"Steenokkerzeel",
    "sg:classifiers":[
        {
            "category":"Arena",
            "subcategory":"Sports Club",
            "type":"Entertainment"
        }
    ],
    "sg:phone":"+32 2 759 42 03",
    "sg:postcode":"1820",
    "sg:province":"Vlaams-Brabant",
    "sg:tags":[
        "de"
    ],
    "wof:name":"T.c. Het Zeen Sterrebeek",
    "wof:placetype":"venue"
},
  "geometry": {"coordinates":[4.5108327866,50.9096374512],"type":"Point"}
}