{
  "type": "Feature",
  "properties": {
    "iso:country":"BE",
    "sg:address":"Velle 75",
    "sg:city":"Temse",
    "sg:orig_category":"Non-Classified Establishments",
    "sg:phone":"+32 3 771 32 69",
    "sg:postcode":"9140",
    "sg:province":"Oost-Vlaanderen",
    "wof:name":"Vercauteren J.",
    "wof:placetype":"venue"
},
  "geometry": {"coordinates":[4.2052359581,51.1585960388],"type":"Point"}
}