{
  "type": "Feature",
  "properties": {
    "addr:full":"Bruggesteenweg 143 Hooglede (gits) West-Vlaanderen 8830",
    "addr:housenumber":"143",
    "addr:postcode":"8830",
    "addr:street":"Bruggesteenweg",
    "iso:country":"BE",
    "sg:address":"Bruggesteenweg 143",
    "sg:city":"Hooglede (gits)",
    "sg:classifiers":[
        {
            "category":"Manufacturing",
            "subcategory":"Rubber & Plastics",
            "type":"Manufacturing & Wholesale Goods"
        }
    ],
    "sg:phone":"+32 51 26 83 68",
    "sg:postcode":"8830",
    "sg:province":"West-Vlaanderen",
    "sg:tags":[
        "industrial",
        "-"
    ],
    "wof:name":"Seynhaeve Plastics Bvba",
    "wof:placetype":"venue"
},
  "geometry": {"coordinates":[3.0943670273,50.9829139709],"type":"Point"}
}