{
  "type": "Feature",
  "properties": {
    "iso:country":"BE",
    "sg:address":"Route Du Val 0",
    "sg:city":"Clavier",
    "sg:orig_category":"Gestion des d\u00e9charges and sites d\u00e9finitifs de stockage",
    "sg:phone":"+32 85 41 36 32",
    "sg:postcode":"4560",
    "sg:province":"Li\u00e8ge",
    "wof:name":"Parcs A Conteneurs Clavier",
    "wof:placetype":"venue"
},
  "geometry": {"coordinates":[5.3121237755,50.4263381958],"type":"Point"}
}