{
  "type": "Feature",
  "properties": {
    "addr:full":"Tessenstraat 1a Leuven Vlaams-Brabant 3000",
    "addr:housenumber":"1a",
    "addr:postcode":"3000",
    "addr:street":"Tessenstraat",
    "iso:country":"BE",
    "sg:address":"Tessenstraat 1a",
    "sg:city":"Leuven",
    "sg:classifiers":[
        {
            "category":"Personal",
            "subcategory":"Barber",
            "type":"Services"
        }
    ],
    "sg:phone":"+32 16 23 87 17",
    "sg:postcode":"3000",
    "sg:province":"Vlaams-Brabant",
    "sg:tags":[
        "gentleman",
        "salon",
        "-",
        "hairdressing"
    ],
    "wof:name":"Gentleman",
    "wof:placetype":"venue"
},
  "geometry": {"coordinates":[4.6932239532,50.8811302185],"type":"Point"}
}