{
  "type": "Feature",
  "properties": {
    "iso:country":"BE",
    "sg:address":"Ter Stratenweg 52",
    "sg:city":"Ranst",
    "sg:orig_category":"Installation de menuiserie en bois and plastique",
    "sg:phone":"+32 3 470 11 41",
    "sg:postcode":"2520",
    "sg:province":"Antwerpen",
    "wof:name":"Pelka Renovatie",
    "wof:placetype":"venue"
},
  "geometry": {"coordinates":[4.5781769753,51.2113189697],"type":"Point"}
}