{
  "type": "Feature",
  "properties": {
    "addr:full":"Avenue Mar\u00e9chal Joffre 50 Bruxelles (forest) Bruxelles-Capitale 1190",
    "addr:housenumber":"50",
    "addr:postcode":"1190",
    "addr:street":"Avenue Mare\u0301Chal Joffre",
    "iso:country":"BE",
    "sg:address":"Avenue Mar\u00e9chal Joffre 50",
    "sg:city":"Bruxelles (forest)",
    "sg:classifiers":[
        {
            "category":"Professional",
            "subcategory":"Lawyer & Legal Services",
            "type":"Services"
        }
    ],
    "sg:phone":"+32 2 345 59 57",
    "sg:postcode":"1190",
    "sg:province":"Bruxelles-Capitale",
    "wof:name":"Brat Solange",
    "wof:placetype":"venue"
},
  "geometry": {"coordinates":[4.333837986,50.8143234253],"type":"Point"}
}