{
  "type": "Feature",
  "properties": {
    "addr:full":"Crapaurue 28 Verviers Li\u00e8ge 4800",
    "addr:housenumber":"28",
    "addr:postcode":"4800",
    "addr:street":"Crapaurue",
    "iso:country":"BE",
    "sg:address":"Crapaurue 28",
    "sg:city":"Verviers",
    "sg:orig_category":"Industri\u00eble wasserijen and droogkuis",
    "sg:phone":"+32 87 33 73 51",
    "sg:postcode":"4800",
    "sg:province":"Li\u00e8ge",
    "wof:name":"Teinturerie Fr\u00c8res",
    "wof:placetype":"venue"
},
  "geometry": {"coordinates":[5.8657751083,50.592918396],"type":"Point"}
}