{
  "type": "Feature",
  "properties": {
    "iso:country":"BE",
    "sg:address":"Darwinstraat 52",
    "sg:city":"Elsene/ixelles",
    "sg:orig_category":"Dameskledingzaken",
    "sg:phone":"+32 2 346 49 05",
    "sg:postcode":"1050",
    "sg:province":"Bruxelles-Capitale",
    "wof:name":"Maison Sam Harys",
    "wof:placetype":"venue"
},
  "geometry": {"coordinates":[4.3536429405,50.8178405762],"type":"Point"}
}