{
  "type": "Feature",
  "properties": {
    "iso:country":"BE",
    "sg:address":"Rue Valles 25",
    "sg:city":"Seraing",
    "sg:orig_category":"R\u00e9cup\u00e9ration de mati\u00e8res m\u00e9talliques recyclables and d\u00e9molisseurs de voitures",
    "sg:phone":"+32 4 234 60 00",
    "sg:postcode":"4101",
    "sg:province":"Li\u00e8ge",
    "wof:name":"Fe. Gallea-tonucci",
    "wof:placetype":"venue"
},
  "geometry": {"coordinates":[5.492456913,50.6109924316],"type":"Point"}
}