{
  "type": "Feature",
  "properties": {
    "iso:country":"BE",
    "sg:address":"Avenue Lamarche 90",
    "sg:city":"Chapelle-lez-herlaimont",
    "sg:orig_category":"Traitements param\u00e9dicaux",
    "sg:phone":"+32 64 44 35 26",
    "sg:postcode":"7160",
    "sg:province":"Hainaut",
    "wof:name":"M. Van Passenhove",
    "wof:placetype":"venue"
},
  "geometry": {"coordinates":[4.2737579346,50.4731750488],"type":"Point"}
}