{
  "type": "Feature",
  "properties": {
    "iso:country":"BE",
    "sg:address":"Emiel Van Winckellaan 15",
    "sg:city":"Dendermonde",
    "sg:classifiers":[
        {
            "category":"Insurance",
            "subcategory":"Insurance Agent",
            "type":"Services"
        }
    ],
    "sg:phone":"+32 52 20 20 97",
    "sg:postcode":"9200",
    "sg:province":"Oost-Vlaanderen",
    "sg:tags":[
        "verzekeringsmakelaars",
        "expert"
    ],
    "wof:name":"H. Pien",
    "wof:placetype":"venue"
},
  "geometry": {"coordinates":[4.0969290733,51.0299453735],"type":"Point"}
}