{
  "type": "Feature",
  "properties": {
    "iso:country":"BE",
    "sg:address":"Rue Favauge 95",
    "sg:city":"Mettet (saint-g\u00e9rard)",
    "sg:classifiers":[
        {
            "category":"Professional",
            "subcategory":"Management & Consulting",
            "type":"Services"
        }
    ],
    "sg:phone":"+32 71 21 40 95",
    "sg:postcode":"5640",
    "sg:province":"Namur",
    "sg:tags":[
        "consultant"
    ],
    "wof:name":"Capri-pmei",
    "wof:placetype":"venue"
},
  "geometry": {"coordinates":[4.6863808632,50.3501052856],"type":"Point"}
}