{
  "type": "Feature",
  "properties": {
    "addr:full":"Alphonse Nijsstraat 5a Oud-heverlee (blanden) Vlaams-Brabant 3052",
    "addr:housenumber":"5a",
    "addr:postcode":"3052",
    "addr:street":"Alphonse Nijsstraat",
    "iso:country":"BE",
    "sg:address":"Alphonse Nijsstraat 5a",
    "sg:city":"Oud-heverlee (blanden)",
    "sg:classifiers":[
        {
            "category":"Health Services",
            "subcategory":"Doctor",
            "type":"Services"
        }
    ],
    "sg:phone":"+32 16 40 20 99",
    "sg:postcode":"3052",
    "sg:province":"Vlaams-Brabant",
    "sg:tags":[
        "medicinephysicians",
        "surgeon"
    ],
    "wof:name":"Dillemans N",
    "wof:placetype":"venue"
},
  "geometry": {"coordinates":[4.7206139565,50.8199615479],"type":"Point"}
}