{
  "type": "Feature",
  "properties": {
    "iso:country":"BE",
    "sg:address":"Kuringersteenweg 189",
    "sg:city":"Hasselt",
    "sg:orig_category":"Non-Classified Establishments",
    "sg:phone":"+32 11 20 16 80",
    "sg:postcode":"3500",
    "sg:province":"Limburg",
    "wof:name":"Ice Shell Bvba",
    "wof:placetype":"venue"
},
  "geometry": {"coordinates":[5.3204188347,50.93542099],"type":"Point"}
}