{
  "type": "Feature",
  "properties": {
    "iso:country":"BE",
    "sg:address":"Rue Du Pensionnat 21",
    "sg:city":"La Louvi\u00e8re (houdeng-aimeries)",
    "sg:classifiers":[
        {
            "category":"Shopping",
            "subcategory":"Shoes",
            "type":"Retail Goods"
        }
    ],
    "sg:phone":"+32 64 22 34 06",
    "sg:postcode":"7110",
    "sg:province":"Hainaut",
    "sg:tags":[
        "slipper",
        "-"
    ],
    "wof:name":"Mar\u00e9chal A",
    "wof:placetype":"venue"
},
  "geometry": {"coordinates":[4.1505050659,50.4826698303],"type":"Point"}
}