{
  "type": "Feature",
  "properties": {
    "iso:country":"BE",
    "sg:address":"Lange Leemstraat 75",
    "sg:city":"Antwerpen",
    "sg:orig_category":"Instruments de musique. Services divers aux entreprises. Art and fournitures artistiques. Eclairage ",
    "sg:phone":"+32 3 232 08 08",
    "sg:postcode":"2018",
    "sg:province":"Antwerpen",
    "wof:name":"Aankoop Adviesbur. Antiq.",
    "wof:placetype":"venue"
},
  "geometry": {"coordinates":[4.4119820595,51.2087211609],"type":"Point"}
}