{
  "type": "Feature",
  "properties": {
    "addr:full":"Rue Provinciale 15 Herstal (liers) Li\u00e8ge 4042",
    "addr:housenumber":"15",
    "addr:postcode":"4042",
    "addr:street":"Rue Provinciale",
    "iso:country":"BE",
    "sg:address":"Rue Provinciale 15",
    "sg:city":"Herstal (liers)",
    "sg:classifiers":[
        {
            "category":"Health Services",
            "subcategory":"Dentist",
            "type":"Services"
        }
    ],
    "sg:phone":"+32 4 278 20 47",
    "sg:postcode":"4042",
    "sg:province":"Li\u00e8ge",
    "wof:name":"Hardy Jean-claude",
    "wof:placetype":"venue"
},
  "geometry": {"coordinates":[5.559928894,50.6915206909],"type":"Point"}
}