{
  "type": "Feature",
  "properties": {
    "addr:full":"Meeuwerweg 14 Houthalen-helchteren Limburg 3530",
    "addr:housenumber":"14",
    "addr:postcode":"3530",
    "addr:street":"Meeuwerweg",
    "iso:country":"BE",
    "sg:address":"Meeuwerweg 14",
    "sg:city":"Houthalen-helchteren",
    "sg:orig_category":"Gespecialiseerde residenti\u00eble bouw",
    "sg:phone":"+32 11 52 53 78",
    "sg:postcode":"3530",
    "sg:province":"Limburg",
    "wof:name":"Maurice Eerdekens",
    "wof:placetype":"venue"
},
  "geometry": {"coordinates":[5.3969650269,51.0344085693],"type":"Point"}
}