{
  "type": "Feature",
  "properties": {
    "addr:full":"Avenue Dossin De St-georges 54b6 Elsene Bruxelles-Capitale 1050",
    "addr:housenumber":"54b6",
    "addr:postcode":"1050",
    "addr:street":"Avenue Dossin De St-Georges",
    "iso:country":"BE",
    "sg:address":"Avenue Dossin De St-georges 54b6",
    "sg:city":"Elsene",
    "sg:orig_category":"Agences d'exp\u00e9dition",
    "sg:phone":"+32 2 649 93 08",
    "sg:postcode":"1050",
    "sg:province":"Bruxelles-Capitale",
    "wof:name":"E.d.i.c.",
    "wof:placetype":"venue"
},
  "geometry": {"coordinates":[4.368625164,50.8177452087],"type":"Point"}
}