{
  "type": "Feature",
  "properties": {
    "addr:full":"Rue Basse Campagne 1 Braives Li\u00e8ge 4260",
    "addr:housenumber":"1",
    "addr:postcode":"4260",
    "addr:street":"Rue Basse Campagne",
    "iso:country":"BE",
    "sg:address":"Rue Basse Campagne 1",
    "sg:city":"Braives",
    "sg:orig_category":"V\u00e9t\u00e9rinaires",
    "sg:phone":"+32 19 69 73 07",
    "sg:postcode":"4260",
    "sg:province":"Li\u00e8ge",
    "wof:name":"Barbara Van Royen",
    "wof:placetype":"venue"
},
  "geometry": {"coordinates":[5.0934581757,50.6228408813],"type":"Point"}
}