{
  "type": "Feature",
  "properties": {
    "iso:country":"BE",
    "sg:address":"Bosdijkstraat 22",
    "sg:city":"Meeuwen-gruitrode",
    "sg:orig_category":"Experts-comptables",
    "sg:phone":"+32 89 46 12 38",
    "sg:postcode":"3670",
    "sg:province":"Limburg",
    "wof:name":"R. Nullens",
    "wof:placetype":"venue"
},
  "geometry": {"coordinates":[5.5577111244,51.1088867188],"type":"Point"}
}