{
  "type": "Feature",
  "properties": {
    "addr:full":"Rue Grand-vin\u00c2ve 11 Seraing Li\u00e8ge 4101",
    "addr:housenumber":"11",
    "addr:postcode":"4101",
    "addr:street":"Rue Grand-Vina\u0302Ve",
    "iso:country":"BE",
    "sg:address":"Rue Grand-vin\u00c2ve 11",
    "sg:city":"Seraing",
    "sg:orig_category":"Disquaires",
    "sg:phone":"+32 4 233 91 75",
    "sg:postcode":"4101",
    "sg:province":"Li\u00e8ge",
    "wof:name":"Maison Renier",
    "wof:placetype":"venue"
},
  "geometry": {"coordinates":[5.504942894,50.6162490845],"type":"Point"}
}