{
  "type": "Feature",
  "properties": {
    "addr:full":"Zwarte Molenstraat 40 Pepingen (elingen) Vlaams-Brabant 1671",
    "addr:housenumber":"40",
    "addr:postcode":"1671",
    "addr:street":"Zwarte Molenstraat",
    "iso:country":"BE",
    "sg:address":"Zwarte Molenstraat 40",
    "sg:city":"Pepingen (elingen)",
    "sg:classifiers":[
        {
            "category":"Professional",
            "subcategory":"Art Services",
            "type":"Services"
        }
    ],
    "sg:phone":"+32 2 532 13 34",
    "sg:postcode":"1671",
    "sg:province":"Vlaams-Brabant",
    "sg:tags":[
        "interior",
        "designer"
    ],
    "wof:name":"Troucheau L",
    "wof:placetype":"venue"
},
  "geometry": {"coordinates":[4.1769590378,50.7830848694],"type":"Point"}
}