{
  "type": "Feature",
  "properties": {
    "addr:full":"Tinnenhoekstraat 6 Aalst (moorsel) Oost-Vlaanderen 9310",
    "addr:housenumber":"6",
    "addr:postcode":"9310",
    "addr:street":"Tinnenhoekstraat;Moorsel Oost-Vlaanderen",
    "iso:country":"BE",
    "sg:address":"Tinnenhoekstraat 6",
    "sg:city":"Aalst (moorsel)",
    "sg:classifiers":[
        {
            "category":"Structure",
            "subcategory":"Office Building",
            "type":"Public Place"
        }
    ],
    "sg:phone":"+32 53 70 57 84",
    "sg:postcode":"9310",
    "sg:province":"Oost-Vlaanderen",
    "sg:tags":[
        "-",
        "type",
        "door",
        "sliding",
        "overhead"
    ],
    "wof:name":"Derimo Bvba",
    "wof:placetype":"venue"
},
  "geometry": {"coordinates":[4.0983958244,50.9637756348],"type":"Point"}
}