{
  "type": "Feature",
  "properties": {
    "iso:country":"BE",
    "sg:address":"Stefaniestraat 37",
    "sg:city":"Antwerpen",
    "sg:classifiers":[
        {
            "category":"Insurance",
            "subcategory":"Insurance Agent",
            "type":"Services"
        }
    ],
    "sg:phone":"+32 3 248 09 83",
    "sg:postcode":"2018",
    "sg:province":"Antwerpen",
    "sg:tags":[
        "broker"
    ],
    "wof:name":"Arka Verzekeringen Bvba",
    "wof:placetype":"venue"
},
  "geometry": {"coordinates":[4.40294981,51.2045593262],"type":"Point"}
}