{
  "type": "Feature",
  "properties": {
    "addr:full":"Markt 1 Assenede Oost-Vlaanderen 9960",
    "addr:housenumber":"1",
    "addr:postcode":"9960",
    "addr:street":"Markt",
    "iso:country":"BE",
    "sg:address":"Markt 1",
    "sg:city":"Assenede",
    "sg:classifiers":[
        {
            "category":"Restaurant",
            "type":"Food & Drink"
        }
    ],
    "sg:phone":"+32 9 344 09 35",
    "sg:postcode":"9960",
    "sg:province":"Oost-Vlaanderen",
    "wof:name":"Klein Assenede",
    "wof:placetype":"venue"
},
  "geometry": {"coordinates":[3.7536389828,51.2274894714],"type":"Point"}
}