{
  "type": "Feature",
  "properties": {
    "iso:country":"BE",
    "sg:address":"Rue Grande 12",
    "sg:city":"Jurbise",
    "sg:orig_category":"Rundveehouders",
    "sg:phone":"+32 65 22 99 22",
    "sg:postcode":"7050",
    "sg:province":"Hainaut",
    "wof:name":"Cowez Jules Et Fils",
    "wof:placetype":"venue"
},
  "geometry": {"coordinates":[3.8503739834,50.5306243896],"type":"Point"}
}