{
  "type": "Feature",
  "properties": {
    "addr:full":"Wimpelbergstraat 76 Brussel/bruxelles Bruxelles-Capitale 1120",
    "addr:housenumber":"76",
    "addr:postcode":"1120",
    "addr:street":"Wimpelbergstraat;/",
    "iso:country":"BE",
    "sg:address":"Wimpelbergstraat 76",
    "sg:city":"Brussel/bruxelles",
    "sg:orig_category":"Loodgieterij, verwarming and sanitaire installaties",
    "sg:phone":"+32 2 262 11 12",
    "sg:postcode":"1120",
    "sg:province":"Bruxelles-Capitale",
    "wof:name":"Claude Doclot",
    "wof:placetype":"venue"
},
  "geometry": {"coordinates":[4.3904018402,50.8979797363],"type":"Point"}
}