{
  "type": "Feature",
  "properties": {
    "iso:country":"BE",
    "sg:address":"Heilanders 36",
    "sg:city":"Vosselaar",
    "sg:classifiers":[
        {
            "category":"Health Services",
            "subcategory":"Health Practitioner",
            "type":"Services"
        }
    ],
    "sg:phone":"+32 14 61 33 01",
    "sg:postcode":"2350",
    "sg:province":"Antwerpen",
    "sg:tags":[
        "physiotherapist"
    ],
    "wof:name":"Peeters-dubois",
    "wof:placetype":"venue"
},
  "geometry": {"coordinates":[4.880879879,51.3051643372],"type":"Point"}
}