{
  "type": "Feature",
  "properties": {
    "addr:full":"Uitbreidingslaan 8 Lokeren Oost-Vlaanderen 9160",
    "addr:housenumber":"8",
    "addr:postcode":"9160",
    "addr:street":"Uitbreidingslaan",
    "iso:country":"BE",
    "sg:address":"Uitbreidingslaan 8",
    "sg:city":"Lokeren",
    "sg:classifiers":[
        {
            "category":"Home & Garden",
            "subcategory":"Building Materials",
            "type":"Retail Goods"
        }
    ],
    "sg:phone":"+32 9 340 56 56",
    "sg:postcode":"9160",
    "sg:province":"Oost-Vlaanderen",
    "sg:tags":[
        "insect",
        "screen"
    ],
    "wof:name":"Van Laere",
    "wof:placetype":"venue"
},
  "geometry": {"coordinates":[4.0104928017,51.1172676086],"type":"Point"}
}