{
  "type": "Feature",
  "properties": {
    "iso:country":"BE",
    "sg:address":"Avenue Marius Renard 17bis",
    "sg:city":"Anderlecht/anderlecht",
    "sg:classifiers":[
        {
            "category":"Personal",
            "subcategory":"Beauty Salon",
            "type":"Services"
        }
    ],
    "sg:phone":"+32 2 527 83 71",
    "sg:postcode":"1070",
    "sg:province":"Bruxelles-Capitale",
    "sg:tags":[
        "de",
        "coiffure"
    ],
    "wof:name":"Daniel Capelle",
    "wof:placetype":"venue"
},
  "geometry": {"coordinates":[4.2880830765,50.8270988464],"type":"Point"}
}