{
  "type": "Feature",
  "properties": {
    "addr:full":"Adegemstraat 43 Mechelen Antwerpen 2800",
    "addr:housenumber":"43",
    "addr:postcode":"2800",
    "addr:street":"Adegemstraat",
    "iso:country":"BE",
    "sg:address":"Adegemstraat 43",
    "sg:city":"Mechelen",
    "sg:classifiers":[
        {
            "category":"Restaurant",
            "type":"Food & Drink"
        }
    ],
    "sg:phone":"+32 15 34 60 02",
    "sg:postcode":"2800",
    "sg:province":"Antwerpen",
    "wof:name":"De Kok & De Proever",
    "wof:placetype":"venue"
},
  "geometry": {"coordinates":[4.474864006,51.0257415771],"type":"Point"}
}