{
  "type": "Feature",
  "properties": {
    "iso:country":"BE",
    "sg:address":"Rue Joseph Wauters 115",
    "sg:city":"Chapelle-lez-herlaimont",
    "sg:classifiers":[
        {
            "category":"Manufacturing",
            "subcategory":"Signs",
            "type":"Manufacturing & Wholesale Goods"
        }
    ],
    "sg:phone":"+32 64 45 13 46",
    "sg:postcode":"7160",
    "sg:province":"Hainaut",
    "sg:tags":[
        "-",
        "illuminated"
    ],
    "wof:name":"M.s. Image",
    "wof:placetype":"venue"
},
  "geometry": {"coordinates":[4.2843818665,50.4772644043],"type":"Point"}
}