{
  "type": "Feature",
  "properties": {
    "iso:country":"BE",
    "sg:address":"Rue Des Pr\u00e9s Du Roy 3",
    "sg:city":"Ath",
    "sg:classifiers":[
        {
            "category":"Building & Trades",
            "subcategory":"Construction",
            "type":"Services"
        }
    ],
    "sg:phone":"+32 68 28 60 07",
    "sg:postcode":"7800",
    "sg:province":"Hainaut",
    "sg:tags":[
        "work",
        "public"
    ],
    "wof:name":"C.b.d. Sa",
    "wof:placetype":"venue"
},
  "geometry": {"coordinates":[3.7834711075,50.6387405396],"type":"Point"}
}