{
  "type": "Feature",
  "properties": {
    "iso:country":"BE",
    "sg:address":"Bergensesteenweg 20",
    "sg:city":"Halle",
    "sg:orig_category":"Voedingsspeciaalzaken",
    "sg:phone":"+32 496 30 64 40",
    "sg:postcode":"1500",
    "sg:province":"Vlaams-Brabant",
    "wof:name":"Traiteur Cantucci",
    "wof:placetype":"venue"
},
  "geometry": {"coordinates":[4.2350702286,50.7342987061],"type":"Point"}
}