{
  "type": "Feature",
  "properties": {
    "iso:country":"BE",
    "sg:address":"Roosbloemstraat 4",
    "sg:city":"Oosterzele",
    "sg:classifiers":[
        {
            "category":"Professional",
            "subcategory":"Lawyer & Legal Services",
            "type":"Services"
        }
    ],
    "sg:phone":"+32 9 362 28 08",
    "sg:postcode":"9860",
    "sg:province":"Oost-Vlaanderen",
    "wof:name":"De Dijcker Vera",
    "wof:placetype":"venue"
},
  "geometry": {"coordinates":[3.819108963,50.9447250366],"type":"Point"}
}