{
  "type": "Feature",
  "properties": {
    "addr:full":"Avenue Louise 83 Elsene/ixelles Bruxelles-Capitale 1050",
    "addr:housenumber":"83",
    "addr:postcode":"1050",
    "addr:street":"Avenue Louise",
    "iso:country":"BE",
    "sg:address":"Avenue Louise 83",
    "sg:city":"Elsene/ixelles",
    "sg:orig_category":"Editeurs de revues and p\u00e9riodiques. Editeurs de journaux",
    "sg:phone":"+32 2 646 29 99",
    "sg:postcode":"1050",
    "sg:province":"Bruxelles-Capitale",
    "wof:name":"Travelling News-guide",
    "wof:placetype":"venue"
},
  "geometry": {"coordinates":[4.355919838,50.8357810974],"type":"Point"}
}