{
  "type": "Feature",
  "properties": {
    "addr:full":"Churchilllaan 80 Box 2 Schoten Antwerpen 2900",
    "addr:housenumber":"80;2",
    "addr:postcode":"2900",
    "addr:street":"Churchilllaan;Box",
    "iso:country":"BE",
    "sg:address":"Churchilllaan 80 Box 2",
    "sg:city":"Schoten",
    "sg:classifiers":[
        {
            "category":"Professional",
            "subcategory":"Lawyer & Legal Services",
            "type":"Services"
        }
    ],
    "sg:phone":"+32 3 658 99 94",
    "sg:postcode":"2900",
    "sg:province":"Antwerpen",
    "wof:name":"Adriaensen Gerd",
    "wof:placetype":"venue"
},
  "geometry": {"coordinates":[4.4925951958,51.2503852844],"type":"Point"}
}