{
  "type": "Feature",
  "properties": {
    "addr:full":"Groenemeersen 2 Laarne Oost-Vlaanderen 9270",
    "addr:housenumber":"2",
    "addr:postcode":"9270",
    "addr:street":"Groenemeersen",
    "iso:country":"BE",
    "sg:address":"Groenemeersen 2",
    "sg:city":"Laarne",
    "sg:orig_category":"Brood, gebak and snoepgoed",
    "sg:phone":"+32 9 367 73 07",
    "sg:postcode":"9270",
    "sg:province":"Oost-Vlaanderen",
    "wof:name":"Ria Baert",
    "wof:placetype":"venue"
},
  "geometry": {"coordinates":[3.910449028,51.0332489014],"type":"Point"}
}