{
  "type": "Feature",
  "properties": {
    "addr:full":"Golflaan 26 Sint-genesius-rode/rhode-saint-gen\u00c8se Vlaams-Brabant 1640",
    "addr:housenumber":"26",
    "addr:postcode":"1640",
    "addr:street":"Golflaan",
    "iso:country":"BE",
    "sg:address":"Golflaan 26",
    "sg:city":"Sint-genesius-rode/rhode-saint-gen\u00c8se",
    "sg:orig_category":"Artsen and specialisten",
    "sg:phone":"+32 2 358 24 31",
    "sg:postcode":"1640",
    "sg:province":"Vlaams-Brabant",
    "wof:name":"Ga\u00cbtan Willemart",
    "wof:placetype":"venue"
},
  "geometry": {"coordinates":[4.3978300095,50.7416381836],"type":"Point"}
}