{
  "type": "Feature",
  "properties": {
    "iso:country":"BE",
    "sg:address":"Tieltstraat 10ba",
    "sg:city":"Wingene",
    "sg:orig_category":"Parfumeries",
    "sg:phone":"+32 51 65 69 19",
    "sg:postcode":"8750",
    "sg:province":"West-Vlaanderen",
    "wof:name":"Parfumerie Katrien",
    "wof:placetype":"venue"
},
  "geometry": {"coordinates":[3.2792971134,51.0572166443],"type":"Point"}
}