{
  "type": "Feature",
  "properties": {
    "addr:full":"Rue Godfroid Kurth 125 Bruxelles (evere) Bruxelles-Capitale 1140",
    "addr:housenumber":"125",
    "addr:postcode":"1140",
    "addr:street":"Rue Godfroid Kurth",
    "iso:country":"BE",
    "sg:address":"Rue Godfroid Kurth 125",
    "sg:city":"Bruxelles (evere)",
    "sg:classifiers":[
        {
            "category":"Professional",
            "subcategory":"Computer Services",
            "type":"Services"
        }
    ],
    "sg:phone":"+32 2 705 63 11",
    "sg:postcode":"1140",
    "sg:province":"Bruxelles-Capitale",
    "sg:tags":[
        "repair",
        "processing",
        "-",
        "maintenance",
        "data"
    ],
    "wof:name":"Pc Doctors Services",
    "wof:placetype":"venue"
},
  "geometry": {"coordinates":[4.4005289078,50.8679885864],"type":"Point"}
}