{
  "type": "Feature",
  "properties": {
    "addr:full":"Rue Du Pont 63 Rebecq Brabant Wallon 1430",
    "addr:housenumber":"63",
    "addr:postcode":"1430",
    "addr:street":"Rue Du Pont",
    "iso:country":"BE",
    "sg:address":"Rue Du Pont 63",
    "sg:city":"Rebecq",
    "sg:orig_category":"Traitements param\u00e9dicaux",
    "sg:phone":"+32 67 67 00 76",
    "sg:postcode":"1430",
    "sg:province":"Brabant Wallon",
    "wof:name":"C. Lenclud",
    "wof:placetype":"venue"
},
  "geometry": {"coordinates":[4.1333241463,50.6614494324],"type":"Point"}
}