{
  "type": "Feature",
  "properties": {
    "addr:full":"Chauss\u00e9e De Boondael 276 Bruxelles (ixelles) Bruxelles-Capitale 1050",
    "addr:housenumber":"276",
    "addr:postcode":"1050",
    "addr:street":"Chausse\u0301E De Boondael",
    "iso:country":"BE",
    "sg:address":"Chauss\u00e9e De Boondael 276",
    "sg:city":"Bruxelles (ixelles)",
    "sg:classifiers":[
        {
            "category":"Food & Beverages",
            "subcategory":"Groceries & Convenience Stores",
            "type":"Retail Goods"
        }
    ],
    "sg:phone":"+32 2 647 34 07",
    "sg:postcode":"1050",
    "sg:province":"Bruxelles-Capitale",
    "sg:tags":[
        "grocer"
    ],
    "wof:name":"Vanly Night Shop",
    "wof:placetype":"venue"
},
  "geometry": {"coordinates":[4.3829498291,50.8195610046],"type":"Point"}
}