{
  "type": "Feature",
  "properties": {
    "addr:full":"Larenbroekstraat 21 Haaltert Oost-Vlaanderen 9450",
    "addr:housenumber":"21",
    "addr:postcode":"9450",
    "addr:street":"Larenbroekstraat",
    "iso:country":"BE",
    "sg:address":"Larenbroekstraat 21",
    "sg:city":"Haaltert",
    "sg:classifiers":[
        {
            "category":"Farming",
            "subcategory":"Farm & Veterinary Services",
            "type":"Manufacturing & Wholesale Goods"
        }
    ],
    "sg:phone":"+32 53 83 90 71",
    "sg:postcode":"9450",
    "sg:province":"Oost-Vlaanderen",
    "sg:tags":[
        "agricultural",
        "contractor"
    ],
    "wof:name":"Leeman L",
    "wof:placetype":"venue"
},
  "geometry": {"coordinates":[4.0004639626,50.9081535339],"type":"Point"}
}