{
  "type": "Feature",
  "properties": {
    "addr:full":"Leopoldlaan 115 Overpelt Limburg 3900",
    "addr:housenumber":"115",
    "addr:postcode":"3900",
    "addr:street":"Leopoldlaan",
    "iso:country":"BE",
    "sg:address":"Leopoldlaan 115",
    "sg:city":"Overpelt",
    "sg:orig_category":"Slagers",
    "sg:phone":"+32 11 64 60 66",
    "sg:postcode":"3900",
    "sg:province":"Limburg",
    "wof:name":"Budgetslager",
    "wof:placetype":"venue"
},
  "geometry": {"coordinates":[5.4293818474,51.2269248962],"type":"Point"}
}