{
  "type": "Feature",
  "properties": {
    "iso:country":"BE",
    "sg:address":"Bronweg 14",
    "sg:city":"Houthalen-helchteren",
    "sg:orig_category":"Landmeters",
    "sg:phone":"+32 11 52 31 83",
    "sg:postcode":"3530",
    "sg:province":"Limburg",
    "wof:name":"Ludovicus Poelmans",
    "wof:placetype":"venue"
},
  "geometry": {"coordinates":[5.3801307678,51.0310134888],"type":"Point"}
}