{
  "type": "Feature",
  "properties": {
    "addr:full":"Hagewindestraat 93 Menen West-Vlaanderen 8930",
    "addr:housenumber":"93",
    "addr:postcode":"8930",
    "addr:street":"Hagewindestraat",
    "iso:country":"BE",
    "sg:address":"Hagewindestraat 93",
    "sg:city":"Menen",
    "sg:orig_category":"Herstellingen and onderhoud van auto's",
    "sg:phone":"+32 56 51 01 15",
    "sg:postcode":"8930",
    "sg:province":"West-Vlaanderen",
    "wof:name":"Garage Braekeveldt",
    "wof:placetype":"venue"
},
  "geometry": {"coordinates":[3.1269528866,50.8028793335],"type":"Point"}
}