{
  "type": "Feature",
  "properties": {
    "iso:country":"BE",
    "sg:address":"Grote Heerweg 141",
    "sg:city":"Waregem",
    "sg:orig_category":"Landmeters",
    "sg:phone":"+32 56 71 48 16",
    "sg:postcode":"8791",
    "sg:province":"West-Vlaanderen",
    "wof:name":"Jan Balduck",
    "wof:placetype":"venue"
},
  "geometry": {"coordinates":[3.3358709812,50.8792877197],"type":"Point"}
}