{
  "type": "Feature",
  "properties": {
    "iso:country":"BE",
    "sg:address":"Leuvense Steenweg 245",
    "sg:city":"Sint-joost-ten-node/saint-josse-ten-noode",
    "sg:orig_category":"Boekhandels",
    "sg:phone":"+32 2 735 83 75",
    "sg:postcode":"1210",
    "sg:province":"Bruxelles-Capitale",
    "wof:name":"France Bede",
    "wof:placetype":"venue"
},
  "geometry": {"coordinates":[4.3830199242,50.8512039185],"type":"Point"}
}