{
  "type": "Feature",
  "properties": {
    "addr:full":"Kempische Steenweg 412b2 Hasselt Limburg 3500",
    "addr:housenumber":"412b2",
    "addr:postcode":"3500",
    "addr:street":"Kempische Steenweg",
    "iso:country":"BE",
    "sg:address":"Kempische Steenweg 412b2",
    "sg:city":"Hasselt",
    "sg:classifiers":[
        {
            "category":"Professional",
            "subcategory":"Engineering",
            "type":"Services"
        }
    ],
    "sg:phone":"+32 11 21 24 82",
    "sg:postcode":"3500",
    "sg:province":"Limburg",
    "sg:tags":[
        "automotive",
        "expert"
    ],
    "wof:name":"Limbex Nv",
    "wof:placetype":"venue"
},
  "geometry": {"coordinates":[5.3410902023,50.9396095276],"type":"Point"}
}