{
  "type": "Feature",
  "properties": {
    "addr:full":"Vlasmarkt 29 Dendermonde Oost-Vlaanderen 9200",
    "addr:housenumber":"29",
    "addr:postcode":"9200",
    "addr:street":"Vlasmarkt;Oost-Vlaanderen",
    "iso:country":"BE",
    "sg:address":"Vlasmarkt 29",
    "sg:city":"Dendermonde",
    "sg:orig_category":"Maatschappelijke dienstverlening",
    "sg:phone":"+32 52 21 23 38",
    "sg:postcode":"9200",
    "sg:province":"Oost-Vlaanderen",
    "wof:name":"Vclb-centrum",
    "wof:placetype":"venue"
},
  "geometry": {"coordinates":[4.099260807,51.0293884277],"type":"Point"}
}