{
  "type": "Feature",
  "properties": {
    "iso:country":"BE",
    "sg:address":"Brugstraat 7",
    "sg:city":"Neeroeteren",
    "sg:orig_category":"Installatie van houten of kunststof schrijnwerk",
    "sg:phone":"+32 495 56 65 28",
    "sg:postcode":"3680",
    "sg:province":"Limburg",
    "wof:name":"Algemene Schrijnwerkerij Davy Swennen",
    "wof:placetype":"venue"
},
  "geometry": {"coordinates":[5.6907410622,51.0885543823],"type":"Point"}
}