{
  "type": "Feature",
  "properties": {
    "iso:country":"BE",
    "sg:address":"Rue Du Bailli 17",
    "sg:city":"La Bruy\u00e8re (warisoulx)",
    "sg:classifiers":[
        {
            "category":"Building & Trades",
            "subcategory":"Construction",
            "type":"Services"
        }
    ],
    "sg:phone":"+32 81 51 34 28",
    "sg:postcode":"5080",
    "sg:province":"Namur",
    "sg:tags":[
        "carpenter"
    ],
    "wof:name":"Decoux J-c",
    "wof:placetype":"venue"
},
  "geometry": {"coordinates":[4.8618588448,50.531539917],"type":"Point"}
}