{
  "type": "Feature",
  "properties": {
    "iso:country":"BE",
    "sg:address":"Suikerrui 6",
    "sg:city":"Antwerpen",
    "sg:orig_category":"Pharmaciens",
    "sg:phone":"+32 3 233 17 91",
    "sg:postcode":"2000",
    "sg:province":"Antwerpen",
    "wof:name":"Hugo Wyttens",
    "wof:placetype":"venue"
},
  "geometry": {"coordinates":[4.3973407745,51.2210578918],"type":"Point"}
}