{
  "type": "Feature",
  "properties": {
    "iso:country":"BE",
    "sg:address":"Avenue Des H\u00c9ros 10",
    "sg:city":"Wezembeek-oppem",
    "sg:orig_category":"Cr\u00e8ches and garderies d'enfants",
    "sg:phone":"+32 2 731 63 11",
    "sg:postcode":"1970",
    "sg:province":"Vlaams-Brabant",
    "wof:name":"Doremi",
    "wof:placetype":"venue"
},
  "geometry": {"coordinates":[4.4935498238,50.8433837891],"type":"Point"}
}