{
  "type": "Feature",
  "properties": {
    "iso:country":"BE",
    "sg:address":"Rue Des Praules 1a",
    "sg:city":"Gembloux-sur-orneau (gembloux)",
    "sg:classifiers":[
        {
            "category":"Building & Trades",
            "subcategory":"Equipment Rental",
            "type":"Services"
        }
    ],
    "sg:phone":"+32 81 62 55 35",
    "sg:postcode":"5030",
    "sg:province":"Namur",
    "sg:tags":[
        "use",
        "apparatus",
        "tool",
        "-",
        "professional",
        "machines"
    ],
    "wof:name":"Job Center",
    "wof:placetype":"venue"
},
  "geometry": {"coordinates":[4.7116861343,50.5779037476],"type":"Point"}
}