{
  "type": "Feature",
  "properties": {
    "addr:full":"Chauss\u00e9e De Bruxelles 531a Waterloo Brabant Wallon 1410",
    "addr:housenumber":"531a",
    "addr:postcode":"1410",
    "addr:street":"Chausse\u0301E De Bruxelles",
    "iso:country":"BE",
    "sg:address":"Chauss\u00e9e De Bruxelles 531a",
    "sg:city":"Waterloo",
    "sg:classifiers":[
        {
            "category":"Utilities",
            "subcategory":"Water",
            "type":"Services"
        }
    ],
    "sg:phone":"+32 2 384 40 00",
    "sg:postcode":"1410",
    "sg:province":"Brabant Wallon",
    "sg:tags":[
        "warm",
        "-",
        "heating",
        "air"
    ],
    "wof:name":"Automatic'gaz Brink",
    "wof:placetype":"venue"
},
  "geometry": {"coordinates":[4.4057941437,50.6917114258],"type":"Point"}
}