{
  "type": "Feature",
  "properties": {
    "addr:full":"Chauss\u00e9e De Tournai 104 Ath Hainaut 7800",
    "addr:housenumber":"104",
    "addr:postcode":"7800",
    "addr:street":"Chausse\u0301E De Tournai",
    "iso:country":"BE",
    "sg:address":"Chauss\u00e9e De Tournai 104",
    "sg:city":"Ath",
    "sg:classifiers":[
        {
            "category":"Autos & Motor Vehicles",
            "subcategory":"Auto Supplies",
            "type":"Retail Goods"
        }
    ],
    "sg:phone":"+32 68 26 90 10",
    "sg:postcode":"7800",
    "sg:province":"Hainaut",
    "sg:tags":[
        "access",
        "automobile",
        "part",
        "-"
    ],
    "wof:name":"Centrauto-pi\u00e8ces Sprl",
    "wof:placetype":"venue"
},
  "geometry": {"coordinates":[3.7628059387,50.6323890686],"type":"Point"}
}