{
  "type": "Feature",
  "properties": {
    "addr:full":"Gerard Davidstraat 15 Kortrijk (marke) West-Vlaanderen 8510",
    "addr:housenumber":"15",
    "addr:postcode":"8510",
    "addr:street":"Gerard Davidstraat",
    "iso:country":"BE",
    "sg:address":"Gerard Davidstraat 15",
    "sg:city":"Kortrijk (marke)",
    "sg:classifiers":[
        {
            "category":"Home & Garden",
            "subcategory":"Hardware",
            "type":"Retail Goods"
        }
    ],
    "sg:phone":"+32 56 22 40 02",
    "sg:postcode":"8510",
    "sg:province":"West-Vlaanderen",
    "sg:tags":[
        "builders'",
        "-",
        "furniture"
    ],
    "wof:name":"B-mat",
    "wof:placetype":"venue"
},
  "geometry": {"coordinates":[3.2556810379,50.8037414551],"type":"Point"}
}