{
  "type": "Feature",
  "properties": {
    "addr:full":"Rue Des Ecaussinnes 162 Le Roeulx Hainaut 7070",
    "addr:housenumber":"162",
    "addr:postcode":"7070",
    "addr:street":"Rue Des Ecaussinnes",
    "iso:country":"BE",
    "sg:address":"Rue Des Ecaussinnes 162",
    "sg:city":"Le Roeulx",
    "sg:orig_category":"Production de films, t\u00e9l\u00e9films and vid\u00e9os",
    "sg:phone":"+32 67 49 05 60",
    "sg:postcode":"7070",
    "sg:province":"Hainaut",
    "wof:name":"Kerckhofs C Et V",
    "wof:placetype":"venue"
},
  "geometry": {"coordinates":[4.1168498993,50.531829834],"type":"Point"}
}