{
  "type": "Feature",
  "properties": {
    "addr:full":"Leliestraat 23 Lovendegem Oost-Vlaanderen 9920",
    "addr:housenumber":"23",
    "addr:postcode":"9920",
    "addr:street":"Leliestraat",
    "iso:country":"BE",
    "sg:address":"Leliestraat 23",
    "sg:city":"Lovendegem",
    "sg:classifiers":[
        {
            "category":"Real Estate",
            "subcategory":"Real Estate Services",
            "type":"Services"
        }
    ],
    "sg:phone":"+32 9 372 46 80",
    "sg:postcode":"9920",
    "sg:province":"Oost-Vlaanderen",
    "wof:name":"Ghent Home Invest Nv",
    "wof:placetype":"venue"
},
  "geometry": {"coordinates":[3.633482933,51.1046066284],"type":"Point"}
}