{
  "type": "Feature",
  "properties": {
    "addr:full":"Rue D\u00b4ans 103 Li\u00c8ge Li\u00e8ge 4000",
    "addr:housenumber":"103",
    "addr:postcode":"4000",
    "addr:street":"Rue D\u00b4Ans",
    "iso:country":"BE",
    "sg:address":"Rue D\u00b4ans 103",
    "sg:city":"Li\u00c8ge",
    "sg:orig_category":"Fietsen Speelgoed, sport- and kampeermateriaal Gh",
    "sg:phone":"+32 4 247 34 15",
    "sg:postcode":"4000",
    "sg:province":"Li\u00e8ge",
    "wof:name":"Cycle One",
    "wof:placetype":"venue"
},
  "geometry": {"coordinates":[5.5423288345,50.6710166931],"type":"Point"}
}