{
  "type": "Feature",
  "properties": {
    "iso:country":"BE",
    "sg:address":"Rue Trieu Bernard 28",
    "sg:city":"Fleurus (wanferc\u00e9e-baulet)",
    "sg:classifiers":[
        {
            "category":"Retail",
            "subcategory":"Storage",
            "type":"Services"
        }
    ],
    "sg:phone":"+32 71 81 51 70",
    "sg:postcode":"6224",
    "sg:province":"Hainaut",
    "sg:tags":[
        "access",
        "-",
        "pigeon",
        "fancier"
    ],
    "wof:name":"Pigeon (le)",
    "wof:placetype":"venue"
},
  "geometry": {"coordinates":[4.5747327805,50.4646186829],"type":"Point"}
}