{
  "type": "Feature",
  "properties": {
    "iso:country":"BE",
    "sg:address":"Polderstraat 50",
    "sg:city":"Knokke-heist",
    "sg:orig_category":"Woningbouw",
    "sg:phone":"+32 50 51 56 68",
    "sg:postcode":"8301",
    "sg:province":"West-Vlaanderen",
    "wof:name":"Albert Slabbinck",
    "wof:placetype":"venue"
},
  "geometry": {"coordinates":[3.2639000416,51.3396911621],"type":"Point"}
}