{
  "type": "Feature",
  "properties": {
    "iso:country":"BE",
    "sg:address":"Avenue Du Monde 128",
    "sg:city":"Nivelles",
    "sg:classifiers":[
        {
            "category":"Personal",
            "subcategory":"Beauty Salon",
            "type":"Services"
        }
    ],
    "sg:phone":"+32 67 21 24 77",
    "sg:postcode":"1400",
    "sg:province":"Brabant Wallon",
    "sg:tags":[
        "de",
        "coiffure"
    ],
    "wof:name":"Liliane Bosquet",
    "wof:placetype":"venue"
},
  "geometry": {"coordinates":[4.3161897659,50.5874977112],"type":"Point"}
}