{
  "type": "Feature",
  "properties": {
    "addr:full":"Grand\u00b4route 36 P\u00c9ruwelz Hainaut 7604",
    "addr:housenumber":"36",
    "addr:postcode":"7604",
    "addr:street":"Grand\u00b4Route",
    "iso:country":"BE",
    "sg:address":"Grand\u00b4route 36",
    "sg:city":"P\u00c9ruwelz",
    "sg:orig_category":"Entretien and r\u00e9parations de voitures",
    "sg:phone":"+32 69 66 33 64",
    "sg:postcode":"7604",
    "sg:province":"Hainaut",
    "wof:name":"Patrick Dhaeyer",
    "wof:placetype":"venue"
},
  "geometry": {"coordinates":[3.5708110332,50.568271637],"type":"Point"}
}