{
  "type": "Feature",
  "properties": {
    "addr:full":"Stationsstraat 103 Berlaar Antwerpen 2590",
    "addr:housenumber":"103",
    "addr:postcode":"2590",
    "addr:street":"Stationsstraat",
    "iso:country":"BE",
    "sg:address":"Stationsstraat 103",
    "sg:city":"Berlaar",
    "sg:orig_category":"Juwelen and edelstenen Fab",
    "sg:phone":"+32 3 482 34 36",
    "sg:postcode":"2590",
    "sg:province":"Antwerpen",
    "wof:name":"Roland Van Den Broeck",
    "wof:placetype":"venue"
},
  "geometry": {"coordinates":[4.6452307701,51.1149177551],"type":"Point"}
}