{
  "type": "Feature",
  "properties": {
    "iso:country":"BE",
    "sg:address":"Vlaamsekunstlaan 65",
    "sg:city":"Antwerpen",
    "sg:orig_category":"Epiceries",
    "sg:phone":"+32 3 238 07 59",
    "sg:postcode":"2020",
    "sg:province":"Antwerpen",
    "wof:name":"Ecofood",
    "wof:placetype":"venue"
},
  "geometry": {"coordinates":[4.3891739845,51.1901473999],"type":"Point"}
}