{
  "type": "Feature",
  "properties": {
    "addr:full":"Dudzeelse Steenweg 309 Brugge West-Vlaanderen 8000",
    "addr:housenumber":"309",
    "addr:postcode":"8000",
    "addr:street":"Dudzeelse Steenweg",
    "iso:country":"BE",
    "sg:address":"Dudzeelse Steenweg 309",
    "sg:city":"Brugge",
    "sg:classifiers":[
        {
            "category":"Shopping",
            "subcategory":"Discount & Variety Stores",
            "type":"Retail Goods"
        }
    ],
    "sg:phone":"+32 50 71 97 21",
    "sg:postcode":"8000",
    "sg:province":"West-Vlaanderen",
    "sg:tags":[
        "shop",
        "clearers",
        "curiosity",
        "furniture"
    ],
    "wof:name":"Chris",
    "wof:placetype":"venue"
},
  "geometry": {"coordinates":[3.2320148945,51.2399024963],"type":"Point"}
}