{
  "type": "Feature",
  "properties": {
    "iso:country":"BE",
    "sg:address":"Kasteelstraat 7",
    "sg:city":"Ardooie",
    "sg:classifiers":[
        {
            "category":"Farming",
            "subcategory":"Poultry Farm",
            "type":"Manufacturing & Wholesale Goods"
        }
    ],
    "sg:phone":"+32 51 74 44 96",
    "sg:postcode":"8850",
    "sg:province":"West-Vlaanderen",
    "wof:name":"Benoot B.v.b.a.",
    "wof:placetype":"venue"
},
  "geometry": {"coordinates":[3.2382099628,50.9661407471],"type":"Point"}
}