{
  "type": "Feature",
  "properties": {
    "iso:country":"BE",
    "sg:address":"De Libotton 16",
    "sg:city":"Hasselt",
    "sg:orig_category":"Dakwerken",
    "sg:phone":"+32 11 59 14 26",
    "sg:postcode":"3512",
    "sg:province":"Limburg",
    "wof:name":"Patrick Liesens",
    "wof:placetype":"venue"
},
  "geometry": {"coordinates":[5.2575440407,50.9201622009],"type":"Point"}
}