{
  "type": "Feature",
  "properties": {
    "iso:country":"BE",
    "sg:address":"Tieltstraat 82",
    "sg:city":"Meulebeke",
    "sg:orig_category":"Plomberie, chauffage and installations sanitaires",
    "sg:phone":"+32 51 48 90 11",
    "sg:postcode":"8760",
    "sg:province":"West-Vlaanderen",
    "wof:name":"Paul Vanhalewyn",
    "wof:placetype":"venue"
},
  "geometry": {"coordinates":[3.2936830521,50.9542427063],"type":"Point"}
}