{
  "type": "Feature",
  "properties": {
    "iso:country":"BE",
    "sg:address":"Rue Des P\u00c2turages 21",
    "sg:city":"Colfontaine",
    "sg:orig_category":"Textiel",
    "sg:phone":"+32 65 67 67 40",
    "sg:postcode":"7340",
    "sg:province":"Hainaut",
    "wof:name":"La Boutonni\u00c8re",
    "wof:placetype":"venue"
},
  "geometry": {"coordinates":[3.8474030495,50.4136276245],"type":"Point"}
}