{
  "type": "Feature",
  "properties": {
    "addr:full":"Mechelsesteenweg 227/1 Sint-katelijne-waver Antwerpen 2860",
    "addr:housenumber":"227 / 1",
    "addr:postcode":"2860",
    "addr:street":"Mechelsesteenweg",
    "iso:country":"BE",
    "sg:address":"Mechelsesteenweg 227/1",
    "sg:city":"Sint-katelijne-waver",
    "sg:orig_category":"Benzinestations and brandstoffen Herstellingen and onderhoud van auto's Voertuigen",
    "sg:phone":"+32 15 55 27 36",
    "sg:postcode":"2860",
    "sg:province":"Antwerpen",
    "wof:name":"Garage Brouwers",
    "wof:placetype":"venue"
},
  "geometry": {"coordinates":[4.5189990997,51.0513191223],"type":"Point"}
}