{
  "type": "Feature",
  "properties": {
    "addr:full":"Avenue Reine Astrid 18 Braine-l\u00b4alleud Brabant Wallon 1420",
    "addr:housenumber":"18",
    "addr:postcode":"1420",
    "addr:street":"Avenue Reine Astrid;Brabant Wallon",
    "iso:country":"BE",
    "sg:address":"Avenue Reine Astrid 18",
    "sg:city":"Braine-l\u00b4alleud",
    "sg:orig_category":"Herstelling aan huis van huishoudartikelen Herstellingswinkels voor diverse persoonlijke and huishou",
    "sg:phone":"+32 67 84 32 23",
    "sg:postcode":"1420",
    "sg:province":"Brabant Wallon",
    "wof:name":"J.l. - Belleflamme",
    "wof:placetype":"venue"
},
  "geometry": {"coordinates":[4.3782739639,50.6854248047],"type":"Point"}
}