{
  "type": "Feature",
  "properties": {
    "iso:country":"BE",
    "sg:address":"Rivage De Boubier 25",
    "sg:city":"Ch\u00e2telet",
    "sg:orig_category":"Non-Classified Establishments",
    "sg:phone":"+32 71 24 38 53",
    "sg:postcode":"6200",
    "sg:province":"Hainaut",
    "wof:name":"Aciers Grosjean Sa",
    "wof:placetype":"venue"
},
  "geometry": {"coordinates":[4.512720108,50.4036216736],"type":"Point"}
}