{
  "type": "Feature",
  "properties": {
    "addr:full":"Ave Charles Quint 7 Ganshoren Bruxelles-Capitale 1080",
    "addr:housenumber":"7",
    "addr:postcode":"1080",
    "addr:street":"Ave Charles Quint",
    "iso:country":"BE",
    "sg:address":"Ave Charles Quint 7",
    "sg:city":"Ganshoren",
    "sg:classifiers":[
        {
            "category":"Banks & Credit Unions",
            "subcategory":"Bank",
            "type":"Services"
        }
    ],
    "sg:phone":"+32 2 426 82 67",
    "sg:postcode":"1080",
    "sg:province":"Bruxelles-Capitale",
    "wof:name":"Banque Bruxelles Lambert Sa",
    "wof:placetype":"venue"
},
  "geometry": {"coordinates":[4.3146219254,50.8676338196],"type":"Point"}
}