{
  "type": "Feature",
  "properties": {
    "iso:country":"BE",
    "sg:address":"Deken Darraslaan 78",
    "sg:city":"Tielt",
    "sg:orig_category":"Schoenen",
    "sg:phone":"+32 51 40 17 61",
    "sg:postcode":"8700",
    "sg:province":"West-Vlaanderen",
    "wof:name":"Huis Giovanni",
    "wof:placetype":"venue"
},
  "geometry": {"coordinates":[3.3169360161,50.9977607727],"type":"Point"}
}