{
  "type": "Feature",
  "properties": {
    "addr:full":"Potterijstraat 162 Tienen Vlaams-Brabant 3300",
    "addr:housenumber":"162",
    "addr:postcode":"3300",
    "addr:street":"Potterijstraat",
    "iso:country":"BE",
    "sg:address":"Potterijstraat 162",
    "sg:city":"Tienen",
    "sg:orig_category":"Fietsen",
    "sg:phone":"+32 16 81 25 95",
    "sg:postcode":"3300",
    "sg:province":"Vlaams-Brabant",
    "wof:name":"Francois Govaerts",
    "wof:placetype":"venue"
},
  "geometry": {"coordinates":[4.9374728203,50.7987785339],"type":"Point"}
}