{
  "type": "Feature",
  "properties": {
    "iso:country":"BE",
    "sg:address":"Albert I-promenade 79",
    "sg:city":"Oostende",
    "sg:classifiers":[
        {
            "category":"Train Station",
            "subcategory":"Rail",
            "type":"Transportation"
        }
    ],
    "sg:phone":"+32 59 50 76 19",
    "sg:postcode":"8400",
    "sg:province":"West-Vlaanderen",
    "sg:tags":[
        "transfer",
        "sticker"
    ],
    "wof:name":"Publi - Hugo",
    "wof:placetype":"venue"
},
  "geometry": {"coordinates":[2.9080440998,51.229221344],"type":"Point"}
}