{
  "type": "Feature",
  "properties": {
    "addr:full":"Leuvenselaan 191 Tienen Vlaams-Brabant 3300",
    "addr:housenumber":"191",
    "addr:postcode":"3300",
    "addr:street":"Leuvenselaan",
    "iso:country":"BE",
    "sg:address":"Leuvenselaan 191",
    "sg:city":"Tienen",
    "sg:classifiers":[
        {
            "category":"Social Services",
            "subcategory":"Child Care",
            "type":"Services"
        }
    ],
    "sg:phone":"+32 16 82 11 38",
    "sg:postcode":"3300",
    "sg:province":"Vlaams-Brabant",
    "sg:tags":[
        "consulting",
        "management"
    ],
    "wof:name":"Sb Marketing",
    "wof:placetype":"venue"
},
  "geometry": {"coordinates":[4.9226322174,50.8121490479],"type":"Point"}
}