{
  "type": "Feature",
  "properties": {
    "iso:country":"BE",
    "sg:address":"Jordaanskaai 24",
    "sg:city":"Antwerpen",
    "sg:orig_category":"Installatie van houten of kunststof schrijnwerk Woningbouw",
    "sg:phone":"+32 3 234 05 25",
    "sg:postcode":"2000",
    "sg:province":"Antwerpen",
    "wof:name":"M & M Bouw Antwerpen",
    "wof:placetype":"venue"
},
  "geometry": {"coordinates":[4.39833498,51.2228317261],"type":"Point"}
}