{
  "type": "Feature",
  "properties": {
    "iso:country":"BE",
    "sg:address":"Rue Haute 65",
    "sg:city":"Bassenge",
    "sg:orig_category":"Cr\u00e8ches and garderies d'enfants",
    "sg:phone":"+32 4 286 51 91",
    "sg:postcode":"4690",
    "sg:province":"Li\u00e8ge",
    "wof:name":"Cr\u00c8che Des Orchid\u00c9es",
    "wof:placetype":"venue"
},
  "geometry": {"coordinates":[5.66401577,50.7892227173],"type":"Point"}
}