{
  "type": "Feature",
  "properties": {
    "iso:country":"BE",
    "sg:address":"Steenakkerstraat 30",
    "sg:city":"Diepenbeek",
    "sg:classifiers":[
        {
            "category":"Science Facility",
            "type":"Public Place"
        }
    ],
    "sg:phone":"+32 11 35 10 61",
    "sg:postcode":"3590",
    "sg:province":"Limburg",
    "sg:tags":[
        "industrial",
        "-",
        "robot"
    ],
    "wof:name":"Ciratec Bvba",
    "wof:placetype":"venue"
},
  "geometry": {"coordinates":[5.4454269409,50.9261512756],"type":"Point"}
}