{
  "type": "Feature",
  "properties": {
    "iso:country":"BE",
    "sg:address":"Rue Hanni\u00c8res Decock 2",
    "sg:city":"Beauvechain",
    "sg:orig_category":"Vakantiehuizen",
    "sg:phone":"+32 10 86 08 09",
    "sg:postcode":"1320",
    "sg:province":"Brabant Wallon",
    "wof:name":"Bvs Vacances",
    "wof:placetype":"venue"
},
  "geometry": {"coordinates":[4.7401461601,50.7646827698],"type":"Point"}
}