{
  "type": "Feature",
  "properties": {
    "addr:full":"Metalenstraat 8 Etterbeek/etterbeek Bruxelles-Capitale 1040",
    "addr:housenumber":"8",
    "addr:postcode":"1040",
    "addr:street":"Metalenstraat",
    "iso:country":"BE",
    "sg:address":"Metalenstraat 8",
    "sg:city":"Etterbeek/etterbeek",
    "sg:orig_category":"Beautyfarms, relaxatie and lichamelijk welzijn",
    "sg:phone":"+32 2 649 79 46",
    "sg:postcode":"1040",
    "sg:province":"Bruxelles-Capitale",
    "wof:name":"Kawada Yuichi",
    "wof:placetype":"venue"
},
  "geometry": {"coordinates":[4.3849458694,50.8356666565],"type":"Point"}
}