{
  "type": "Feature",
  "properties": {
    "iso:country":"BE",
    "sg:address":"Grote Kerkstraat 3",
    "sg:city":"Maaseik",
    "sg:classifiers":[
        {
            "category":"Restaurant",
            "type":"Food & Drink"
        }
    ],
    "sg:phone":"+32 89 56 68 94",
    "sg:postcode":"3680",
    "sg:province":"Limburg",
    "sg:tags":[
        "caf\u00e9s"
    ],
    "wof:name":"Taverne Merijntje",
    "wof:placetype":"venue"
},
  "geometry": {"coordinates":[5.7927451134,51.0947723389],"type":"Point"}
}