{
  "type": "Feature",
  "properties": {
    "addr:full":"Koningin Astridlaan 14 Willebroek Antwerpen 2830",
    "addr:housenumber":"14",
    "addr:postcode":"2830",
    "addr:street":"Koningin Astridlaan",
    "iso:country":"BE",
    "sg:address":"Koningin Astridlaan 14",
    "sg:city":"Willebroek",
    "sg:classifiers":[
        {
            "category":"Structure",
            "subcategory":"Office Building",
            "type":"Public Place"
        }
    ],
    "sg:phone":"+32 3 449 06 61",
    "sg:postcode":"2830",
    "sg:province":"Antwerpen",
    "sg:tags":[
        "door",
        "automatic",
        "actuator"
    ],
    "wof:name":"Boreco Nv",
    "wof:placetype":"venue"
},
  "geometry": {"coordinates":[4.3946051598,51.1691131592],"type":"Point"}
}