{
  "type": "Feature",
  "properties": {
    "addr:full":"Klinkstraat 61 Alken Limburg 3570",
    "addr:housenumber":"61",
    "addr:postcode":"3570",
    "addr:street":"Klinkstraat",
    "iso:country":"BE",
    "sg:address":"Klinkstraat 61",
    "sg:city":"Alken",
    "sg:orig_category":"Eleveurs de bovins",
    "sg:phone":"+32 11 31 38 56",
    "sg:postcode":"3570",
    "sg:province":"Limburg",
    "wof:name":"Albert Gerrits",
    "wof:placetype":"venue"
},
  "geometry": {"coordinates":[5.3318080902,50.8818473816],"type":"Point"}
}