{
  "type": "Feature",
  "properties": {
    "addr:full":"Raafstraat 53 Bilzen Limburg 3740",
    "addr:housenumber":"53",
    "addr:postcode":"3740",
    "addr:street":"Raafstraat",
    "iso:country":"BE",
    "sg:address":"Raafstraat 53",
    "sg:city":"Bilzen",
    "sg:orig_category":"Loodgieterij, verwarming and sanitaire installaties",
    "sg:phone":"+32 89 41 45 74",
    "sg:postcode":"3740",
    "sg:province":"Limburg",
    "wof:name":"Strauven Stijn",
    "wof:placetype":"venue"
},
  "geometry": {"coordinates":[5.4689760208,50.8874664307],"type":"Point"}
}