{
  "type": "Feature",
  "properties": {
    "iso:country":"BE",
    "sg:address":"Rue Du Congr\u00c8s 43",
    "sg:city":"Brussel",
    "sg:orig_category":"Medische and orthopedische apparaten",
    "sg:phone":"+32 2 217 57 44",
    "sg:postcode":"1000",
    "sg:province":"Bruxelles-Capitale",
    "wof:name":"Audio-medica International",
    "wof:placetype":"venue"
},
  "geometry": {"coordinates":[4.367000103,50.8492050171],"type":"Point"}
}