{
  "type": "Feature",
  "properties": {
    "addr:full":"Sint-annaplein 34 Gent Oost-Vlaanderen 9000",
    "addr:housenumber":"34",
    "addr:postcode":"9000",
    "addr:street":"Sint-Annaplein;Oost-Vlaanderen",
    "iso:country":"BE",
    "sg:address":"Sint-annaplein 34",
    "sg:city":"Gent",
    "sg:classifiers":[
        {
            "category":"Professional",
            "subcategory":"Lawyer & Legal Services",
            "type":"Services"
        }
    ],
    "sg:phone":"+32 9 266 10 50",
    "sg:postcode":"9000",
    "sg:province":"Oost-Vlaanderen",
    "wof:name":"Van Asch Veronique",
    "wof:placetype":"venue"
},
  "geometry": {"coordinates":[3.7351100445,51.0493507385],"type":"Point"}
}