{
  "type": "Feature",
  "properties": {
    "iso:country":"BE",
    "sg:address":"Zandstraat 77",
    "sg:city":"Brugge",
    "sg:orig_category":"Kapsalons",
    "sg:phone":"+32 50 31 49 33",
    "sg:postcode":"8200",
    "sg:province":"West-Vlaanderen",
    "wof:name":"Coiffure Miranda",
    "wof:placetype":"venue"
},
  "geometry": {"coordinates":[3.2013781071,51.2026405334],"type":"Point"}
}