{
  "type": "Feature",
  "properties": {
    "addr:full":"Naamsestraat 34 Leuven Vlaams-Brabant 3000",
    "addr:housenumber":"34",
    "addr:postcode":"3000",
    "addr:street":"Naamsestraat",
    "iso:country":"BE",
    "sg:address":"Naamsestraat 34",
    "sg:city":"Leuven",
    "sg:classifiers":[
        {
            "category":"Bars & Pubs",
            "type":"Food & Drink"
        }
    ],
    "sg:phone":"+32 16 23 24 29",
    "sg:postcode":"3000",
    "sg:province":"Vlaams-Brabant",
    "wof:name":"Murphy's Rock Caf\u00e9",
    "wof:placetype":"venue"
},
  "geometry": {"coordinates":[4.7003059387,50.8772697449],"type":"Point"}
}