{
  "type": "Feature",
  "properties": {
    "addr:full":"Nijverheidslaan 2 Strombeek-bever Vlaams-Brabant 1853",
    "addr:housenumber":"2;1853",
    "addr:street":"Nijverheidslaan;Vlaams-Brabant",
    "iso:country":"BE",
    "sg:address":"Nijverheidslaan 2",
    "sg:city":"Strombeek-bever",
    "sg:classifiers":[
        {
            "category":"Shopping",
            "subcategory":"Clothing, Apparel, & Fashions",
            "type":"Retail Goods"
        }
    ],
    "sg:phone":"+32 3 322 64 29",
    "sg:postcode":"1853",
    "sg:province":"Vlaams-Brabant",
    "sg:tags":[
        "children's",
        "clothing"
    ],
    "wof:name":"Swynen B.v.b.a.",
    "wof:placetype":"venue"
},
  "geometry": {"coordinates":[4.4624657631,51.2088546753],"type":"Point"}
}