{
  "type": "Feature",
  "properties": {
    "addr:full":"Rue Du Moulin 76 Etalle (groot) Luxembourg 6740",
    "addr:housenumber":"76",
    "addr:postcode":"6740",
    "addr:street":"Rue Du Moulin;Groot Luxembourg",
    "iso:country":"BE",
    "sg:address":"Rue Du Moulin 76",
    "sg:city":"Etalle (groot)",
    "sg:orig_category":"Autokeuringen",
    "sg:phone":"+32 63 45 52 04",
    "sg:postcode":"6740",
    "sg:province":"Luxembourg",
    "wof:name":"Contr\u00d4le Technique Automobile",
    "wof:placetype":"venue"
},
  "geometry": {"coordinates":[5.5935559273,49.6731452942],"type":"Point"}
}