{
  "type": "Feature",
  "properties": {
    "iso:country":"BE",
    "sg:address":"Hoogstraat 23",
    "sg:city":"Brugge",
    "sg:orig_category":"S\u00e9curit\u00e9 sociale",
    "sg:phone":"+32 50 33 56 74",
    "sg:postcode":"8000",
    "sg:province":"West-Vlaanderen",
    "wof:name":"Vl. Neutraal Ziekenfonds",
    "wof:placetype":"venue"
},
  "geometry": {"coordinates":[3.2293930054,51.2097473145],"type":"Point"}
}