{
  "type": "Feature",
  "properties": {
    "iso:country":"BE",
    "sg:address":"Pont D'erez\u00c9e 0",
    "sg:city":"Erezee",
    "sg:orig_category":"Gestion des d\u00e9charges and sites d\u00e9finitifs de stockage",
    "sg:phone":"+32 86 47 76 32",
    "sg:postcode":"6997",
    "sg:province":"Luxembourg",
    "wof:name":"Parcs A Conteneurs Erez\u00c9e",
    "wof:placetype":"venue"
},
  "geometry": {"coordinates":[5.5468268394,50.2923736572],"type":"Point"}
}