{
  "type": "Feature",
  "properties": {
    "iso:country":"BE",
    "sg:address":"Rue Jules Houssi\u00c8re 61ba",
    "sg:city":"Charleroi",
    "sg:orig_category":"Herstellingen and onderhoud van auto's",
    "sg:phone":"+32 71 32 34 72",
    "sg:postcode":"6020",
    "sg:province":"Hainaut",
    "wof:name":"Carrosserie Terrana",
    "wof:placetype":"venue"
},
  "geometry": {"coordinates":[4.4373550415,50.4196548462],"type":"Point"}
}