{
  "type": "Feature",
  "properties": {
    "iso:country":"BE",
    "sg:address":"Leuvensesteenweg 415",
    "sg:city":"Schaarbeek/schaerbeek",
    "sg:orig_category":"Artsen and specialisten",
    "sg:phone":"+32 2 733 59 86",
    "sg:postcode":"1030",
    "sg:province":"Bruxelles-Capitale",
    "wof:name":"Anastassios Ambatzis",
    "wof:placetype":"venue"
},
  "geometry": {"coordinates":[4.3927140236,50.8537826538],"type":"Point"}
}