{
  "type": "Feature",
  "properties": {
    "iso:country":"BE",
    "sg:address":"Avenue Reine Astrid 320bb",
    "sg:city":"Seneffe",
    "sg:orig_category":"Equipement photographique. Studios photographiques",
    "sg:phone":"+32 64 54 18 06",
    "sg:postcode":"7180",
    "sg:province":"Hainaut",
    "wof:name":"Claude Delbruyere",
    "wof:placetype":"venue"
},
  "geometry": {"coordinates":[4.255961895,50.5314903259],"type":"Point"}
}