{
  "type": "Feature",
  "properties": {
    "iso:country":"BE",
    "sg:address":"Terweidenstraat 34",
    "sg:city":"Zoutleeuw (budingen)",
    "sg:classifiers":[
        {
            "category":"Health Services",
            "subcategory":"Dentist",
            "type":"Services"
        }
    ],
    "sg:phone":"+32 11 58 84 21",
    "sg:postcode":"3440",
    "sg:province":"Vlaams-Brabant",
    "wof:name":"Journee Bart",
    "wof:placetype":"venue"
},
  "geometry": {"coordinates":[5.1035709381,50.863243103],"type":"Point"}
}