{
  "type": "Feature",
  "properties": {
    "addr:full":"Burgemeester Philipslaan 9 Maaseik Limburg 3680",
    "addr:housenumber":"9",
    "addr:postcode":"3680",
    "addr:street":"Burgemeester Philipslaan",
    "iso:country":"BE",
    "sg:address":"Burgemeester Philipslaan 9",
    "sg:city":"Maaseik",
    "sg:classifiers":[
        {
            "category":"Health Services",
            "subcategory":"Health Practitioner",
            "type":"Services"
        }
    ],
    "sg:phone":"+32 89 56 74 42",
    "sg:postcode":"3680",
    "sg:province":"Limburg",
    "sg:tags":[
        "physiotherapist"
    ],
    "wof:name":"Ruttens M",
    "wof:placetype":"venue"
},
  "geometry": {"coordinates":[5.7928361893,51.097240448],"type":"Point"}
}