{
  "type": "Feature",
  "properties": {
    "addr:full":"Parc Scientifique Fleming Louvain-la-neuve Brabant Wallon 1348",
    "addr:postcode":"1348",
    "iso:country":"BE",
    "sg:address":"Parc Scientifique Fleming",
    "sg:city":"Louvain-la-neuve",
    "sg:classifiers":[
        {
            "category":"Government",
            "subcategory":"Fire Station",
            "type":"Public Place"
        }
    ],
    "sg:phone":"+32 10 47 52 11",
    "sg:postcode":"1348",
    "sg:province":"Brabant Wallon",
    "sg:tags":[
        "consulting",
        "protection"
    ],
    "wof:name":"Anpi - Nvbb A.s.b.l.",
    "wof:placetype":"venue"
},
  "geometry": {"coordinates":[4.6374001503,50.6631660461],"type":"Point"}
}