{
  "type": "Feature",
  "properties": {
    "addr:full":"Onze-lieve-vrouwestraat 94 Mechelen Antwerpen 2800",
    "addr:housenumber":"94",
    "addr:postcode":"2800",
    "addr:street":"Onze-Lieve-Vrouwestraat",
    "iso:country":"BE",
    "sg:address":"Onze-lieve-vrouwestraat 94",
    "sg:city":"Mechelen",
    "sg:orig_category":"Hoger onderwijs",
    "sg:phone":"+32 15 45 92 00",
    "sg:postcode":"2800",
    "sg:province":"Antwerpen",
    "wof:name":"K.h.m.-campus Vijfhoek",
    "wof:placetype":"venue"
},
  "geometry": {"coordinates":[4.4808368683,51.0226020813],"type":"Point"}
}