{
  "type": "Feature",
  "properties": {
    "iso:country":"BE",
    "sg:address":"Broekstraat 22",
    "sg:city":"Tienen",
    "sg:orig_category":"Traitements param\u00e9dicaux",
    "sg:phone":"+32 16 82 18 04",
    "sg:postcode":"3300",
    "sg:province":"Vlaams-Brabant",
    "wof:name":"P. Metten",
    "wof:placetype":"venue"
},
  "geometry": {"coordinates":[4.935997963,50.8058357239],"type":"Point"}
}