{
  "type": "Feature",
  "properties": {
    "addr:full":"Grand-route 19 Bassenge Li\u00e8ge 4690",
    "addr:housenumber":"19",
    "addr:postcode":"4690",
    "addr:street":"Grand-Route",
    "iso:country":"BE",
    "sg:address":"Grand-route 19",
    "sg:city":"Bassenge",
    "sg:orig_category":"Maisons de repos and r\u00e9sidences",
    "sg:phone":"+32 4 286 43 24",
    "sg:postcode":"4690",
    "sg:province":"Li\u00e8ge",
    "wof:name":"Home Les Saules",
    "wof:placetype":"venue"
},
  "geometry": {"coordinates":[5.6180701256,50.7608184814],"type":"Point"}
}