{
  "type": "Feature",
  "properties": {
    "iso:country":"BE",
    "sg:address":"Heirbaan 22",
    "sg:city":"Zwijndrecht",
    "sg:orig_category":"Eclairage et \u00e9quipements du foyer. R\u00e9parations \u00e0 domicile d'articles divers",
    "sg:phone":"+32 3 252 70 25",
    "sg:postcode":"2070",
    "sg:province":"Antwerpen",
    "wof:name":"Guido Blyweert",
    "wof:placetype":"venue"
},
  "geometry": {"coordinates":[4.3373031616,51.2011642456],"type":"Point"}
}