{
  "type": "Feature",
  "properties": {
    "iso:country":"BE",
    "sg:address":"Kouter 1",
    "sg:city":"Lochristi",
    "sg:classifiers":[
        {
            "category":"Freight",
            "type":"Transportation"
        }
    ],
    "sg:phone":"+32 9 355 34 31",
    "sg:postcode":"9080",
    "sg:province":"Oost-Vlaanderen",
    "sg:tags":[
        "-",
        "refrigerated",
        "transport"
    ],
    "wof:name":"Damtrans Bvba",
    "wof:placetype":"venue"
},
  "geometry": {"coordinates":[3.826980114,51.1039047241],"type":"Point"}
}