{
  "type": "Feature",
  "properties": {
    "addr:full":"Rijksweg 189 Dilsen-stokkem Limburg 3650",
    "addr:housenumber":"189",
    "addr:postcode":"3650",
    "addr:street":"Rijksweg",
    "iso:country":"BE",
    "sg:address":"Rijksweg 189",
    "sg:city":"Dilsen-stokkem",
    "sg:classifiers":[
        {
            "category":"Real Estate",
            "subcategory":"Real Estate Services",
            "type":"Services"
        }
    ],
    "sg:phone":"+32 89 36 49 39",
    "sg:postcode":"3650",
    "sg:province":"Limburg",
    "wof:name":"Landi Projektontwikkeling",
    "wof:placetype":"venue"
},
  "geometry": {"coordinates":[5.7266697884,51.0228614807],"type":"Point"}
}