{
  "type": "Feature",
  "properties": {
    "iso:country":"BE",
    "sg:address":"Konijnstraat 6",
    "sg:city":"Zwevegem",
    "sg:orig_category":"Traitements param\u00e9dicaux",
    "sg:phone":"+32 56 64 46 14",
    "sg:postcode":"8551",
    "sg:province":"West-Vlaanderen",
    "wof:name":"M. Lateur",
    "wof:placetype":"venue"
},
  "geometry": {"coordinates":[3.4109840393,50.782283783],"type":"Point"}
}