{
  "type": "Feature",
  "properties": {
    "iso:country":"BE",
    "sg:address":"Kromme Heistraat 9",
    "sg:city":"Zele",
    "sg:orig_category":"Rev\u00eatements pour sols and murs. Peinture",
    "sg:phone":"+32 9 367 55 44",
    "sg:postcode":"9240",
    "sg:province":"Oost-Vlaanderen",
    "wof:name":"Depick",
    "wof:placetype":"venue"
},
  "geometry": {"coordinates":[3.9815909863,51.0606307983],"type":"Point"}
}