{
  "type": "Feature",
  "properties": {
    "addr:full":"Dorpsstraat 30 Zulte Oost-Vlaanderen 9870",
    "addr:housenumber":"30",
    "addr:postcode":"9870",
    "addr:street":"Dorpsstraat",
    "iso:country":"BE",
    "sg:address":"Dorpsstraat 30",
    "sg:city":"Zulte",
    "sg:orig_category":"Woningbouw",
    "sg:phone":"+32 9 386 97 29",
    "sg:postcode":"9870",
    "sg:province":"Oost-Vlaanderen",
    "wof:name":"Jacques Lapauw",
    "wof:placetype":"venue"
},
  "geometry": {"coordinates":[3.4923141003,50.9569549561],"type":"Point"}
}