{
  "type": "Feature",
  "properties": {
    "addr:full":"Place Abb\u00c9 Joseph Andr\u00c9 7 Namur Namur 5000",
    "addr:housenumber":"7",
    "addr:postcode":"5000",
    "addr:street":"Place Abbe\u0301 Joseph Andre\u0301",
    "iso:country":"BE",
    "sg:address":"Place Abb\u00c9 Joseph Andr\u00c9 7",
    "sg:city":"Namur",
    "sg:classifiers":[
        {
            "category":"Government",
            "subcategory":"Prison",
            "type":"Public Place"
        }
    ],
    "sg:phone":"+32 81 74 00 44",
    "sg:postcode":"5000",
    "sg:province":"Namur",
    "wof:name":"Prison",
    "wof:placetype":"venue"
},
  "geometry": {"coordinates":[4.8583030701,50.4653015137],"type":"Point"}
}