{
  "type": "Feature",
  "properties": {
    "iso:country":"BE",
    "sg:address":"Korenmarkt 41",
    "sg:city":"Mechelen",
    "sg:orig_category":"Antiek",
    "sg:phone":"+32 15 42 14 21",
    "sg:postcode":"2800",
    "sg:province":"Antwerpen",
    "wof:name":"Adelin",
    "wof:placetype":"venue"
},
  "geometry": {"coordinates":[4.4760251045,51.0244102478],"type":"Point"}
}