{
  "type": "Feature",
  "properties": {
    "addr:full":"Huttegem 71 Oudenaarde Oost-Vlaanderen 9700",
    "addr:housenumber":"71",
    "addr:postcode":"9700",
    "addr:street":"Huttegem",
    "iso:country":"BE",
    "sg:address":"Huttegem 71",
    "sg:city":"Oudenaarde",
    "sg:orig_category":"Boekhouders",
    "sg:phone":"+32 55 30 38 66",
    "sg:postcode":"9700",
    "sg:province":"Oost-Vlaanderen",
    "wof:name":"Patrick Dossche",
    "wof:placetype":"venue"
},
  "geometry": {"coordinates":[3.5838589668,50.8470191956],"type":"Point"}
}