{
  "type": "Feature",
  "properties": {
    "addr:full":"Van Steenestraat 15 Brugge West-Vlaanderen 8310",
    "addr:housenumber":"15",
    "addr:postcode":"8310",
    "addr:street":"Steenestraat",
    "iso:country":"BE",
    "sg:address":"Van Steenestraat 15",
    "sg:city":"Brugge",
    "sg:orig_category":"Verhuur diversen",
    "sg:phone":"+32 50 35 85 78",
    "sg:postcode":"8310",
    "sg:province":"West-Vlaanderen",
    "wof:name":"Coene Michel & Dominique",
    "wof:placetype":"venue"
},
  "geometry": {"coordinates":[3.2414560318,51.1999015808],"type":"Point"}
}