{
  "type": "Feature",
  "properties": {
    "addr:full":"Vlaamsekaai 11 Antwerpen Antwerpen 2000",
    "addr:housenumber":"11",
    "addr:postcode":"2000",
    "addr:street":"Vlaamsekaai",
    "iso:country":"BE",
    "sg:address":"Vlaamsekaai 11",
    "sg:city":"Antwerpen",
    "sg:orig_category":"Imitation jewelry - Mfg.& Whol.",
    "sg:phone":"+32 3 257 23 05",
    "sg:postcode":"2000",
    "sg:province":"Antwerpen",
    "wof:name":"Nicole Rako Bvba",
    "wof:placetype":"venue"
},
  "geometry": {"coordinates":[4.393228054,51.2115516663],"type":"Point"}
}