{
  "type": "Feature",
  "properties": {
    "addr:full":"Harpstraat 26 Hasselt Limburg 3500",
    "addr:housenumber":"26",
    "addr:postcode":"3500",
    "addr:street":"Harpstraat",
    "iso:country":"BE",
    "sg:address":"Harpstraat 26",
    "sg:city":"Hasselt",
    "sg:orig_category":"Imprimeries and copyshops. Reliure and finition",
    "sg:phone":"+32 11 22 60 74",
    "sg:postcode":"3500",
    "sg:province":"Limburg",
    "wof:name":"Dicla",
    "wof:placetype":"venue"
},
  "geometry": {"coordinates":[5.3531570435,50.9279403687],"type":"Point"}
}