{
  "type": "Feature",
  "properties": {
    "iso:country":"BE",
    "sg:address":"Bolderstraat 56",
    "sg:city":"Riemst (zichen-zussen-bolder)",
    "sg:classifiers":[
        {
            "category":"Communications",
            "subcategory":"Film & Video Production",
            "type":"Services"
        }
    ],
    "sg:phone":"+32 12 45 48 15",
    "sg:postcode":"3770",
    "sg:province":"Limburg",
    "sg:tags":[
        "hiring",
        "-"
    ],
    "wof:name":"Videotheek Bm",
    "wof:placetype":"venue"
},
  "geometry": {"coordinates":[5.6003341675,50.7908248901],"type":"Point"}
}