{
  "type": "Feature",
  "properties": {
    "iso:country":"BE",
    "sg:address":"De Fr\u00c9laan 206",
    "sg:city":"Ukkel/uccle",
    "sg:orig_category":"Ziekenhuizen and zorginstellingen Ziekenvervoer",
    "sg:phone":"+32 2 373 16 11",
    "sg:postcode":"1180",
    "sg:province":"Bruxelles-Capitale",
    "wof:name":"Ziekenhuis St.elisabeth/clinique St.elisabeth",
    "wof:placetype":"venue"
},
  "geometry": {"coordinates":[4.3716959953,50.805393219],"type":"Point"}
}