{
  "type": "Feature",
  "properties": {
    "iso:country":"BE",
    "sg:address":"Roger De Backerstraat 10",
    "sg:city":"Waregem",
    "sg:orig_category":"Kapsalons",
    "sg:phone":"+32 56 61 26 44",
    "sg:postcode":"8790",
    "sg:province":"West-Vlaanderen",
    "wof:name":"Pascal",
    "wof:placetype":"venue"
},
  "geometry": {"coordinates":[3.4402859211,50.8924751282],"type":"Point"}
}