{
  "type": "Feature",
  "properties": {
    "iso:country":"BE",
    "sg:address":"Rue Rodolphe Delval 50",
    "sg:city":"Courcelles",
    "sg:orig_category":"Bagage and lederwaren Schoenen",
    "sg:phone":"+32 71 45 70 87",
    "sg:postcode":"6183",
    "sg:province":"Hainaut",
    "wof:name":"Eram",
    "wof:placetype":"venue"
},
  "geometry": {"coordinates":[4.3293838501,50.4633407593],"type":"Point"}
}