{
  "type": "Feature",
  "properties": {
    "iso:country":"BE",
    "sg:address":"Steenberg 1",
    "sg:city":"Bekkevoort",
    "sg:orig_category":"Entretien and r\u00e9parations de voitures. V\u00e9hicules automobiles",
    "sg:phone":"+32 13 32 10 36",
    "sg:postcode":"3460",
    "sg:province":"Vlaams-Brabant",
    "wof:name":"Tom\u00b4s Car",
    "wof:placetype":"venue"
},
  "geometry": {"coordinates":[4.9800758362,50.9512710571],"type":"Point"}
}