{
  "type": "Feature",
  "properties": {
    "addr:full":"Avenue Rommelaere 1 Bruxelles Bruxelles-Capitale 1020",
    "addr:housenumber":"1",
    "addr:postcode":"1020",
    "addr:street":"Avenue Rommelaere",
    "iso:country":"BE",
    "sg:address":"Avenue Rommelaere 1",
    "sg:city":"Bruxelles",
    "sg:classifiers":[
        {
            "category":"Professional",
            "subcategory":"Computer Services",
            "type":"Services"
        }
    ],
    "sg:phone":"+32 2 474 30 90",
    "sg:postcode":"1020",
    "sg:province":"Bruxelles-Capitale",
    "sg:tags":[
        "repair",
        "processing",
        "-",
        "maintenance",
        "data"
    ],
    "wof:name":"Alpha-chrome",
    "wof:placetype":"venue"
},
  "geometry": {"coordinates":[4.3359479904,50.8889083862],"type":"Point"}
}