{
  "type": "Feature",
  "properties": {
    "addr:full":"Neerpedestraat 861 Anderlecht Bruxelles-Capitale 1070",
    "addr:housenumber":"861",
    "addr:postcode":"1070",
    "addr:street":"Neerpedestraat",
    "iso:country":"BE",
    "sg:address":"Neerpedestraat 861",
    "sg:city":"Anderlecht",
    "sg:orig_category":"Architecten",
    "sg:phone":"+32 2 344 39 49",
    "sg:postcode":"1070",
    "sg:province":"Bruxelles-Capitale",
    "wof:name":"Yves De Windt",
    "wof:placetype":"venue"
},
  "geometry": {"coordinates":[4.2653980255,50.8268356323],"type":"Point"}
}