{
  "type": "Feature",
  "properties": {
    "iso:country":"BE",
    "sg:address":"Stormestraat 152",
    "sg:city":"Waregem",
    "sg:orig_category":"Equipement photographique. Studios photographiques",
    "sg:phone":"+32 56 60 08 80",
    "sg:postcode":"8790",
    "sg:province":"West-Vlaanderen",
    "wof:name":"Foto Ateljee",
    "wof:placetype":"venue"
},
  "geometry": {"coordinates":[3.426568985,50.8848190308],"type":"Point"}
}