{
  "type": "Feature",
  "properties": {
    "addr:full":"Albert Van Heckelaan 4a Hamme Oost-Vlaanderen 9220",
    "addr:housenumber":"4a",
    "addr:postcode":"9220",
    "addr:street":"Albert Van Heckelaan",
    "iso:country":"BE",
    "sg:address":"Albert Van Heckelaan 4a",
    "sg:city":"Hamme",
    "sg:classifiers":[
        {
            "category":"Home & Garden",
            "subcategory":"Carpets & Floor Coverings",
            "type":"Retail Goods"
        }
    ],
    "sg:phone":"+32 52 47 76 85",
    "sg:postcode":"9220",
    "sg:province":"Oost-Vlaanderen",
    "sg:tags":[
        "layer",
        "mosaicists"
    ],
    "wof:name":"Van Moerzeke D",
    "wof:placetype":"venue"
},
  "geometry": {"coordinates":[4.1296858788,51.0845565796],"type":"Point"}
}