{
  "type": "Feature",
  "properties": {
    "iso:country":"BE",
    "sg:address":"Route D'ath 223",
    "sg:city":"Jurbise",
    "sg:orig_category":"Woningbouw",
    "sg:phone":"+32 65 22 92 52",
    "sg:postcode":"7050",
    "sg:province":"Hainaut",
    "wof:name":"Henri Cambier",
    "wof:placetype":"venue"
},
  "geometry": {"coordinates":[3.9184501171,50.5198974609],"type":"Point"}
}