{
  "type": "Feature",
  "properties": {
    "addr:full":"Rue Ernest Mo\u00ebns 42 Namur (marche-les-dames) Namur 5024",
    "addr:housenumber":"42",
    "addr:postcode":"5024",
    "addr:street":"Rue Ernest Moe\u0308Ns",
    "iso:country":"BE",
    "sg:address":"Rue Ernest Mo\u00ebns 42",
    "sg:city":"Namur (marche-les-dames)",
    "sg:classifiers":[
        {
            "category":"Home & Garden",
            "subcategory":"Home Furnishings",
            "type":"Retail Goods"
        }
    ],
    "sg:phone":"+32 81 21 09 55",
    "sg:postcode":"5024",
    "sg:province":"Namur",
    "sg:tags":[
        "-",
        "bed",
        "mattress"
    ],
    "wof:name":"Comaprex Sa",
    "wof:placetype":"venue"
},
  "geometry": {"coordinates":[4.9728078842,50.493221283],"type":"Point"}
}