{
  "type": "Feature",
  "properties": {
    "iso:country":"BE",
    "sg:address":"Zwijnaardsesteenweg 27",
    "sg:city":"Gent",
    "sg:classifiers":[
        {
            "category":"Shopping",
            "subcategory":"Luggage & Leather Goods",
            "type":"Retail Goods"
        }
    ],
    "sg:phone":"+32 9 220 11 11",
    "sg:postcode":"9000",
    "sg:province":"Oost-Vlaanderen",
    "sg:tags":[
        "-"
    ],
    "wof:name":"Diego",
    "wof:placetype":"venue"
},
  "geometry": {"coordinates":[3.7265429497,51.0363311768],"type":"Point"}
}