{
  "type": "Feature",
  "properties": {
    "iso:country":"BE",
    "sg:address":"Leistraat 35",
    "sg:city":"Kasterlee",
    "sg:classifiers":[
        {
            "category":"Fast Food",
            "type":"Food & Drink"
        }
    ],
    "sg:phone":"+32 14 55 54 73",
    "sg:postcode":"2460",
    "sg:province":"Antwerpen",
    "sg:tags":[
        "meeneem",
        "restaurant"
    ],
    "wof:name":"Torenhof",
    "wof:placetype":"venue"
},
  "geometry": {"coordinates":[4.9176039696,51.2243881226],"type":"Point"}
}