{
  "type": "Feature",
  "properties": {
    "addr:full":"Karnemelkstraat 5 Roeselare West-Vlaanderen 8800",
    "addr:housenumber":"5",
    "addr:postcode":"8800",
    "addr:street":"Karnemelkstraat",
    "iso:country":"BE",
    "sg:address":"Karnemelkstraat 5",
    "sg:city":"Roeselare",
    "sg:classifiers":[
        {
            "category":"Professional",
            "subcategory":"Lawyer & Legal Services",
            "type":"Services"
        }
    ],
    "sg:phone":"+32 51 24 32 99",
    "sg:postcode":"8800",
    "sg:province":"West-Vlaanderen",
    "wof:name":"Tack Pieter-paul",
    "wof:placetype":"venue"
},
  "geometry": {"coordinates":[3.1219909191,50.9447746277],"type":"Point"}
}