{
  "type": "Feature",
  "properties": {
    "addr:full":"Steenakkersdreef 4 Destelbergen Oost-Vlaanderen 9070",
    "addr:housenumber":"4",
    "addr:postcode":"9070",
    "addr:street":"Steenakkersdreef",
    "iso:country":"BE",
    "sg:address":"Steenakkersdreef 4",
    "sg:city":"Destelbergen",
    "sg:orig_category":"Banques and organismes de cr\u00e9dit",
    "sg:phone":"+32 9 228 34 14",
    "sg:postcode":"9070",
    "sg:province":"Oost-Vlaanderen",
    "wof:name":"Citibank",
    "wof:placetype":"venue"
},
  "geometry": {"coordinates":[3.7794270515,51.0532684326],"type":"Point"}
}