{
  "type": "Feature",
  "properties": {
    "addr:full":"Nikelaan 19 Laakdal (forest) Antwerpen 2430",
    "addr:housenumber":"19",
    "addr:postcode":"2430",
    "addr:street":"Nikelaan",
    "iso:country":"BE",
    "sg:address":"Nikelaan 19",
    "sg:city":"Laakdal (forest)",
    "sg:classifiers":[
        {
            "category":"Utilities",
            "subcategory":"Natural Gas",
            "type":"Services"
        }
    ],
    "sg:phone":"+32 13 66 71 78",
    "sg:postcode":"2430",
    "sg:province":"Antwerpen",
    "sg:tags":[
        "industrial",
        "-"
    ],
    "wof:name":"Ceunen Alfons",
    "wof:placetype":"venue"
},
  "geometry": {"coordinates":[5.0823841095,51.0998725891],"type":"Point"}
}