{
  "type": "Feature",
  "properties": {
    "iso:country":"BE",
    "sg:address":"Overwinningsstraat 163",
    "sg:city":"Willebroek",
    "sg:classifiers":[
        {
            "category":"Cafe",
            "type":"Food & Drink"
        }
    ],
    "sg:phone":"+32 3 886 55 72",
    "sg:postcode":"2830",
    "sg:province":"Antwerpen",
    "sg:tags":[
        "caf\u00e9s"
    ],
    "wof:name":"Caf\u00c9 Arel",
    "wof:placetype":"venue"
},
  "geometry": {"coordinates":[4.3578767776,51.0560531616],"type":"Point"}
}