{
  "type": "Feature",
  "properties": {
    "iso:country":"BE",
    "sg:address":"Oudemanstraat 40",
    "sg:city":"Kapelle-op-den-bos",
    "sg:orig_category":"Rundveehouders",
    "sg:phone":"+32 52 30 97 68",
    "sg:postcode":"1880",
    "sg:province":"Vlaams-Brabant",
    "wof:name":"Emiel Van Ranst",
    "wof:placetype":"venue"
},
  "geometry": {"coordinates":[4.3216772079,51.0186233521],"type":"Point"}
}