{
  "type": "Feature",
  "properties": {
    "iso:country":"BE",
    "sg:address":"Rue Roland Vanoverschelde 130",
    "sg:city":"Mouscron",
    "sg:classifiers":[
        {
            "category":"Shopping",
            "subcategory":"Books",
            "type":"Retail Goods"
        }
    ],
    "sg:phone":"+32 56 84 11 91",
    "sg:postcode":"7700",
    "sg:province":"Hainaut",
    "sg:tags":[
        "bookseller"
    ],
    "wof:name":"Nouveau Monde (du)",
    "wof:placetype":"venue"
},
  "geometry": {"coordinates":[3.1980109215,50.7493667603],"type":"Point"}
}