{
  "type": "Feature",
  "properties": {
    "addr:full":"Dreefpad 48 Anderlecht Bruxelles-Capitale 1070",
    "addr:housenumber":"48",
    "addr:postcode":"1070",
    "addr:street":"Dreefpad",
    "iso:country":"BE",
    "sg:address":"Dreefpad 48",
    "sg:city":"Anderlecht",
    "sg:orig_category":"Artsen and specialisten",
    "sg:phone":"+32 2 526 70 16",
    "sg:postcode":"1070",
    "sg:province":"Bruxelles-Capitale",
    "wof:name":"Steven Bessemans",
    "wof:placetype":"venue"
},
  "geometry": {"coordinates":[4.29190588,50.8143196106],"type":"Point"}
}