{
  "type": "Feature",
  "properties": {
    "iso:country":"BE",
    "sg:address":"Rue Sous-le-ch\u00e2teau 53",
    "sg:city":"Huy",
    "sg:classifiers":[
        {
            "category":"Professional",
            "subcategory":"Lawyer & Legal Services",
            "type":"Services"
        }
    ],
    "sg:phone":"+32 85 27 07 47",
    "sg:postcode":"4500",
    "sg:province":"Li\u00e8ge",
    "wof:name":"Seinlet Jean-marie",
    "wof:placetype":"venue"
},
  "geometry": {"coordinates":[5.238658905,50.5164604187],"type":"Point"}
}