{
  "type": "Feature",
  "properties": {
    "addr:full":"Guido Gezellestraat 60 Denderleeuw Oost-Vlaanderen 9470",
    "addr:housenumber":"60",
    "addr:postcode":"9470",
    "addr:street":"Guido Gezellestraat",
    "iso:country":"BE",
    "sg:address":"Guido Gezellestraat 60",
    "sg:city":"Denderleeuw",
    "sg:classifiers":[
        {
            "category":"Professional",
            "subcategory":"Computer Services",
            "type":"Services"
        }
    ],
    "sg:phone":"+32 53 68 23 02",
    "sg:postcode":"9470",
    "sg:province":"Oost-Vlaanderen",
    "sg:tags":[
        "-",
        "processing",
        "data"
    ],
    "wof:name":"Dcs Computers",
    "wof:placetype":"venue"
},
  "geometry": {"coordinates":[4.0783009529,50.8862266541],"type":"Point"}
}