{
  "type": "Feature",
  "properties": {
    "iso:country":"BE",
    "sg:address":"Hekkerstraat 12",
    "sg:city":"Wetteren",
    "sg:classifiers":[
        {
            "category":"Shopping",
            "subcategory":"Clothing, Apparel, & Fashions",
            "type":"Retail Goods"
        }
    ],
    "sg:phone":"+32 9 368 11 65",
    "sg:postcode":"9230",
    "sg:province":"Oost-Vlaanderen",
    "sg:tags":[
        "lingerie",
        "sous-v\u00eatements"
    ],
    "wof:name":"Huis Isabelle",
    "wof:placetype":"venue"
},
  "geometry": {"coordinates":[3.8858718872,51.0053367615],"type":"Point"}
}