{
  "type": "Feature",
  "properties": {
    "iso:country":"BE",
    "sg:address":"Neerhonderd 13",
    "sg:city":"Wetteren",
    "sg:classifiers":[
        {
            "category":"Wholesale",
            "subcategory":"Construction Materials",
            "type":"Manufacturing & Wholesale Goods"
        }
    ],
    "sg:phone":"+32 9 365 01 69",
    "sg:postcode":"9230",
    "sg:province":"Oost-Vlaanderen",
    "sg:tags":[
        "adhesive"
    ],
    "wof:name":"Triton, Divisie Van Epacar",
    "wof:placetype":"venue"
},
  "geometry": {"coordinates":[3.8437759876,50.9890403748],"type":"Point"}
}