{
  "type": "Feature",
  "properties": {
    "addr:full":"Serpentstraat 100 Oudenaarde Oost-Vlaanderen 9700",
    "addr:housenumber":"100",
    "addr:postcode":"9700",
    "addr:street":"Serpentstraat",
    "iso:country":"BE",
    "sg:address":"Serpentstraat 100",
    "sg:city":"Oudenaarde",
    "sg:classifiers":[
        {
            "category":"Manufacturing",
            "subcategory":"Textiles",
            "type":"Manufacturing & Wholesale Goods"
        }
    ],
    "sg:phone":"+32 55 30 49 99",
    "sg:postcode":"9700",
    "sg:province":"Oost-Vlaanderen",
    "sg:tags":[
        "finishing"
    ],
    "wof:name":"Belteinka Nv",
    "wof:placetype":"venue"
},
  "geometry": {"coordinates":[3.6081850529,50.8716087341],"type":"Point"}
}