{
  "type": "Feature",
  "properties": {
    "iso:country":"BE",
    "sg:address":"Antwerpsesteenweg 58",
    "sg:city":"Lier",
    "sg:orig_category":"M\u00e9decins and sp\u00e9cialistes",
    "sg:phone":"+32 3 480 15 28",
    "sg:postcode":"2500",
    "sg:province":"Antwerpen",
    "wof:name":"J. Van Kerckhoven",
    "wof:placetype":"venue"
},
  "geometry": {"coordinates":[4.5597581863,51.137802124],"type":"Point"}
}