{
  "type": "Feature",
  "properties": {
    "iso:country":"BE",
    "sg:address":"Antwerpsestraat 170",
    "sg:city":"Boom",
    "sg:classifiers":[
        {
            "category":"Professional",
            "subcategory":"Detective & Security Services",
            "type":"Services"
        }
    ],
    "sg:phone":"+32 3 888 31 13",
    "sg:postcode":"2850",
    "sg:province":"Antwerpen",
    "sg:tags":[
        "consultant"
    ],
    "wof:name":"Npa Security Consulting",
    "wof:placetype":"venue"
},
  "geometry": {"coordinates":[4.3662848473,51.0941047668],"type":"Point"}
}