{
  "type": "Feature",
  "properties": {
    "iso:country":"BE",
    "sg:address":"Westenwindstraat 44",
    "sg:city":"Sint-lambrechts-woluwe/woluwe-saint-lambert",
    "sg:orig_category":"Herstellingen and onderhoud van auto's",
    "sg:phone":"+32 2 762 17 57",
    "sg:postcode":"1200",
    "sg:province":"Bruxelles-Capitale",
    "wof:name":"Garage Vanderstappen",
    "wof:placetype":"venue"
},
  "geometry": {"coordinates":[4.4192118645,50.8466567993],"type":"Point"}
}