{
  "type": "Feature",
  "properties": {
    "iso:country":"BE",
    "sg:address":"Klijtstraat 20",
    "sg:city":"Wervik",
    "sg:orig_category":"Eleveurs de bovins",
    "sg:phone":"+32 56 31 21 23",
    "sg:postcode":"8940",
    "sg:province":"West-Vlaanderen",
    "wof:name":"Dirk D'hallewin",
    "wof:placetype":"venue"
},
  "geometry": {"coordinates":[3.0348680019,50.805015564],"type":"Point"}
}