{
  "type": "Feature",
  "properties": {
    "addr:full":"Kloosterstraat 23 Gooik (oetingen) Vlaams-Brabant 1755",
    "addr:housenumber":"23",
    "addr:postcode":"1755",
    "addr:street":"Kloosterstraat",
    "iso:country":"BE",
    "sg:address":"Kloosterstraat 23",
    "sg:city":"Gooik (oetingen)",
    "sg:classifiers":[
        {
            "category":"Bakery",
            "type":"Food & Drink"
        }
    ],
    "sg:phone":"+32 54 56 80 71",
    "sg:postcode":"1755",
    "sg:province":"Vlaams-Brabant",
    "sg:tags":[
        "confectioner",
        "baker"
    ],
    "wof:name":"De Kegel D",
    "wof:placetype":"venue"
},
  "geometry": {"coordinates":[4.0609388351,50.773601532],"type":"Point"}
}