{
  "type": "Feature",
  "properties": {
    "iso:country":"BE",
    "sg:address":"Romeinse Straat 10 Box 1",
    "sg:city":"Leuven (heverlee)",
    "sg:orig_category":"Non-Classified Establishments",
    "sg:phone":"+32 16 39 31 40",
    "sg:postcode":"3001",
    "sg:province":"Vlaams-Brabant",
    "wof:name":"Sodiaal Benelux Nv",
    "wof:placetype":"venue"
},
  "geometry": {"coordinates":[4.7374110222,50.8444290161],"type":"Point"}
}