{
  "type": "Feature",
  "properties": {
    "addr:full":"Kleine Rijstraat 24 Ninove Oost-Vlaanderen 9400",
    "addr:housenumber":"24",
    "addr:postcode":"9400",
    "addr:street":"Kleine Rijstraat",
    "iso:country":"BE",
    "sg:address":"Kleine Rijstraat 24",
    "sg:city":"Ninove",
    "sg:orig_category":"Plomberie, chauffage and installations sanitaires. Charpentes and couvertures",
    "sg:phone":"+32 54 34 23 31",
    "sg:postcode":"9400",
    "sg:province":"Oost-Vlaanderen",
    "wof:name":"Pagi Dak",
    "wof:placetype":"venue"
},
  "geometry": {"coordinates":[4.0241670609,50.7837142944],"type":"Point"}
}