{
  "type": "Feature",
  "properties": {
    "iso:country":"BE",
    "sg:address":"Bovenstraat 20",
    "sg:city":"Horebeke",
    "sg:orig_category":"Installation de menuiserie en bois and plastique",
    "sg:phone":"+32 55 45 52 26",
    "sg:postcode":"9667",
    "sg:province":"Oost-Vlaanderen",
    "wof:name":"Bourdeaud'huy-thienpont",
    "wof:placetype":"venue"
},
  "geometry": {"coordinates":[3.6946659088,50.8319778442],"type":"Point"}
}