{
  "type": "Feature",
  "properties": {
    "iso:country":"BE",
    "sg:address":"Rue Gilles Dagneau 14",
    "sg:city":"Grez-doiceau",
    "sg:orig_category":"Schoonheidssalons",
    "sg:phone":"+32 10 84 18 50",
    "sg:postcode":"1390",
    "sg:province":"Brabant Wallon",
    "wof:name":"Sandrine Chantrain",
    "wof:placetype":"venue"
},
  "geometry": {"coordinates":[4.7211799622,50.7172737122],"type":"Point"}
}