{
  "type": "Feature",
  "properties": {
    "addr:full":"Heldenlaan 21 Zottegem Oost-Vlaanderen 9620",
    "addr:housenumber":"21",
    "addr:postcode":"9620",
    "addr:street":"Heldenlaan",
    "iso:country":"BE",
    "sg:address":"Heldenlaan 21",
    "sg:city":"Zottegem",
    "sg:orig_category":"Supermarkten",
    "sg:phone":"+32 9 360 02 85",
    "sg:postcode":"9620",
    "sg:province":"Oost-Vlaanderen",
    "wof:name":"Unic",
    "wof:placetype":"venue"
},
  "geometry": {"coordinates":[3.8104290962,50.8708076477],"type":"Point"}
}