{
  "type": "Feature",
  "properties": {
    "addr:full":"Kappaertstraat 88bb Zwevegem West-Vlaanderen 8550",
    "addr:housenumber":"88bb",
    "addr:postcode":"8550",
    "addr:street":"Kappaertstraat",
    "iso:country":"BE",
    "sg:address":"Kappaertstraat 88bb",
    "sg:city":"Zwevegem",
    "sg:orig_category":"Dakwerken",
    "sg:phone":"+32 56 77 43 50",
    "sg:postcode":"8550",
    "sg:province":"West-Vlaanderen",
    "wof:name":"Fa. Vandemeulebroecke",
    "wof:placetype":"venue"
},
  "geometry": {"coordinates":[3.3618159294,50.8117980957],"type":"Point"}
}