{
  "type": "Feature",
  "properties": {
    "addr:full":"Waterloose Steenweg 104 Sint-gillis/saint-gilles Bruxelles-Capitale 1060",
    "addr:housenumber":"104",
    "addr:postcode":"1060",
    "addr:street":"Waterloose Steenweg",
    "iso:country":"BE",
    "sg:address":"Waterloose Steenweg 104",
    "sg:city":"Sint-gillis/saint-gilles",
    "sg:orig_category":"Slagers",
    "sg:phone":"+32 2 537 03 34",
    "sg:postcode":"1060",
    "sg:province":"Bruxelles-Capitale",
    "wof:name":"Carina Vrijsen",
    "wof:placetype":"venue"
},
  "geometry": {"coordinates":[4.3445959091,50.8291473389],"type":"Point"}
}