{
  "type": "Feature",
  "properties": {
    "addr:full":"Avenue Des D\u00c9port\u00c9s 48 Ramillies Brabant Wallon 1367",
    "addr:housenumber":"48",
    "addr:postcode":"1367",
    "addr:street":"Avenue Des De\u0301Porte\u0301S",
    "iso:country":"BE",
    "sg:address":"Avenue Des D\u00c9port\u00c9s 48",
    "sg:city":"Ramillies",
    "sg:classifiers":[
        {
            "category":"Government",
            "subcategory":"Police Station",
            "type":"Public Place"
        }
    ],
    "sg:phone":"+32 81 87 82 95",
    "sg:postcode":"1367",
    "sg:province":"Brabant Wallon",
    "sg:tags":[
        "gendarmerie"
    ],
    "wof:name":"Police F\u00c9d\u00c9rale/federale Politie",
    "wof:placetype":"venue"
},
  "geometry": {"coordinates":[4.9146900177,50.636631012],"type":"Point"}
}