{
  "type": "Feature",
  "properties": {
    "iso:country":"BE",
    "sg:address":"Rue Royale 7",
    "sg:city":"Tournai",
    "sg:classifiers":[
        {
            "category":"Restaurant",
            "type":"Food & Drink"
        }
    ],
    "sg:phone":"+32 69 21 36 36",
    "sg:postcode":"7500",
    "sg:province":"Hainaut",
    "wof:name":"Restaurant Lo Fook King",
    "wof:placetype":"venue"
},
  "geometry": {"coordinates":[3.3917000294,50.608921051],"type":"Point"}
}