{
  "type": "Feature",
  "properties": {
    "iso:country":"BE",
    "sg:address":"Vaartstraat 1",
    "sg:city":"Balen",
    "sg:classifiers":[
        {
            "category":"Cafe",
            "type":"Food & Drink"
        }
    ],
    "sg:phone":"+32 14 81 07 31",
    "sg:postcode":"2490",
    "sg:province":"Antwerpen",
    "sg:tags":[
        "snack-bars"
    ],
    "wof:name":"Snack Mollenium",
    "wof:placetype":"venue"
},
  "geometry": {"coordinates":[5.167113781,51.170425415],"type":"Point"}
}