{
  "type": "Feature",
  "properties": {
    "iso:country":"BE",
    "sg:address":"Kontichsesteenweg 50",
    "sg:city":"Aartselaar",
    "sg:classifiers":[
        {
            "category":"Professional",
            "subcategory":"Art Services",
            "type":"Services"
        }
    ],
    "sg:phone":"+32 3 870 40 40",
    "sg:postcode":"2630",
    "sg:province":"Antwerpen",
    "sg:tags":[
        "technical",
        "photographer",
        "industrial",
        "-"
    ],
    "wof:name":"Fotostudio Van Den Bosch",
    "wof:placetype":"venue"
},
  "geometry": {"coordinates":[4.3903841972,51.1441688538],"type":"Point"}
}