{
  "type": "Feature",
  "properties": {
    "iso:country":"BE",
    "sg:address":"Centrumlaan 9",
    "sg:city":"Ninove",
    "sg:orig_category":"Tijdelijke werkgelegenheid and uitzendkantoren",
    "sg:phone":"+32 54 32 90 89",
    "sg:postcode":"9400",
    "sg:province":"Oost-Vlaanderen",
    "wof:name":"Vedior Interim",
    "wof:placetype":"venue"
},
  "geometry": {"coordinates":[4.0219159126,50.8348197937],"type":"Point"}
}