{
  "type": "Feature",
  "properties": {
    "iso:country":"BE",
    "sg:address":"Oosterbeekstraat 11",
    "sg:city":"Hasselt (sint-lambrechts-herk)",
    "sg:classifiers":[
        {
            "category":"Building & Trades",
            "subcategory":"Landscaping Services",
            "type":"Services"
        }
    ],
    "sg:phone":"+32 11 59 68 86",
    "sg:postcode":"3500",
    "sg:province":"Limburg",
    "sg:tags":[
        "gardening",
        "garden",
        "maintenance"
    ],
    "wof:name":"Schreurs J",
    "wof:placetype":"venue"
},
  "geometry": {"coordinates":[5.2938981056,50.9051361084],"type":"Point"}
}