{
  "type": "Feature",
  "properties": {
    "addr:full":"F Bogaertstr 16 Zottegem Oost-Vlaanderen 9620",
    "addr:housenumber":"16",
    "addr:postcode":"9620",
    "iso:country":"BE",
    "sg:address":"F Bogaertstr 16",
    "sg:city":"Zottegem",
    "sg:classifiers":[
        {
            "category":"Banks & Credit Unions",
            "subcategory":"Bank",
            "type":"Services"
        }
    ],
    "sg:phone":"+32 52 60 00 65",
    "sg:postcode":"9620",
    "sg:province":"Oost-Vlaanderen",
    "wof:name":"Kredietbank",
    "wof:placetype":"venue"
},
  "geometry": {"coordinates":[3.80843997,50.8692626953],"type":"Point"}
}