{
  "type": "Feature",
  "properties": {
    "iso:country":"BE",
    "sg:address":"Alsembergsesteenweg 87",
    "sg:city":"Halle",
    "sg:orig_category":"Brood, gebak and snoepgoed",
    "sg:phone":"+32 2 356 59 90",
    "sg:postcode":"1501",
    "sg:province":"Vlaams-Brabant",
    "wof:name":"Bakkerij Eddy",
    "wof:placetype":"venue"
},
  "geometry": {"coordinates":[4.2615461349,50.7486076355],"type":"Point"}
}