{
  "type": "Feature",
  "properties": {
    "addr:full":"Dendermondsesteenweg 2 Lebbeke Oost-Vlaanderen 9280",
    "addr:housenumber":"2",
    "addr:postcode":"9280",
    "addr:street":"Dendermondsesteenweg",
    "iso:country":"BE",
    "sg:address":"Dendermondsesteenweg 2",
    "sg:city":"Lebbeke",
    "sg:orig_category":"Peinture. Drogueries. Eclairage et \u00e9quipements du foyer. Rev\u00eatements pour sols and murs. Rev\u00eatements",
    "sg:phone":"+32 52 41 02 70",
    "sg:postcode":"9280",
    "sg:province":"Oost-Vlaanderen",
    "wof:name":"Uyttenhove Jo",
    "wof:placetype":"venue"
},
  "geometry": {"coordinates":[4.1277599335,51.0013084412],"type":"Point"}
}