{
  "type": "Feature",
  "properties": {
    "addr:full":"Molenstraat 38ba Oosterzele Oost-Vlaanderen 9860",
    "addr:housenumber":"38ba",
    "addr:postcode":"9860",
    "addr:street":"Molenstraat;Oost-Vlaanderen",
    "iso:country":"BE",
    "sg:address":"Molenstraat 38ba",
    "sg:city":"Oosterzele",
    "sg:classifiers":[
        {
            "category":"Cafe",
            "type":"Food & Drink"
        }
    ],
    "sg:phone":"+32 9 362 02 79",
    "sg:postcode":"9860",
    "sg:province":"Oost-Vlaanderen",
    "sg:tags":[
        "caf\u00e9s"
    ],
    "wof:name":"Vrij En Vlug Balegem",
    "wof:placetype":"venue"
},
  "geometry": {"coordinates":[3.8002789021,50.9238166809],"type":"Point"}
}