{
  "type": "Feature",
  "properties": {
    "iso:country":"BE",
    "sg:address":"Waterloosesteenweg 1587",
    "sg:city":"Brussel",
    "sg:orig_category":"Onderdelen and accessoires voor auto's Telecommunicatieapparaten",
    "sg:phone":"+32 2 374 58 21",
    "sg:postcode":"1180",
    "sg:province":"Bruxelles-Capitale",
    "wof:name":"Musical Car ( Arc )",
    "wof:placetype":"venue"
},
  "geometry": {"coordinates":[4.3824949265,50.7764472961],"type":"Point"}
}