{
  "type": "Feature",
  "properties": {
    "addr:full":"Rue Edmond Delcourt 64 Bruxelles (anderlecht) Bruxelles-Capitale 1070",
    "addr:housenumber":"64",
    "addr:postcode":"1070",
    "addr:street":"Rue Edmond Delcourt",
    "iso:country":"BE",
    "sg:address":"Rue Edmond Delcourt 64",
    "sg:city":"Bruxelles (anderlecht)",
    "sg:classifiers":[
        {
            "category":"Building & Trades",
            "subcategory":"Electrical",
            "type":"Services"
        }
    ],
    "sg:phone":"+32 2 522 07 78",
    "sg:postcode":"1070",
    "sg:province":"Bruxelles-Capitale",
    "sg:tags":[
        "electric",
        "-",
        "housewiring",
        "contractor"
    ],
    "wof:name":"Deltechnics Sprl",
    "wof:placetype":"venue"
},
  "geometry": {"coordinates":[4.307197094,50.8388137817],"type":"Point"}
}