{
  "type": "Feature",
  "properties": {
    "addr:full":"Abdijstraat 24 Oudenaarde Oost-Vlaanderen 9700",
    "addr:housenumber":"24",
    "addr:postcode":"9700",
    "addr:street":"Abdijstraat",
    "iso:country":"BE",
    "sg:address":"Abdijstraat 24",
    "sg:city":"Oudenaarde",
    "sg:classifiers":[
        {
            "category":"Shopping",
            "subcategory":"Florist",
            "type":"Retail Goods"
        }
    ],
    "sg:phone":"+32 55 30 09 50",
    "sg:postcode":"9700",
    "sg:province":"Oost-Vlaanderen",
    "wof:name":"Blomme (in De)",
    "wof:placetype":"venue"
},
  "geometry": {"coordinates":[3.6326889992,50.8576812744],"type":"Point"}
}