{
  "type": "Feature",
  "properties": {
    "addr:full":"Lage Kaart 622 Brasschaat Antwerpen 2930",
    "addr:housenumber":"622",
    "addr:postcode":"2930",
    "addr:street":"Lage Kaart",
    "iso:country":"BE",
    "sg:address":"Lage Kaart 622",
    "sg:city":"Brasschaat",
    "sg:classifiers":[
        {
            "category":"Shopping",
            "subcategory":"Florist",
            "type":"Retail Goods"
        }
    ],
    "sg:phone":"+32 3 663 19 70",
    "sg:postcode":"2930",
    "sg:province":"Antwerpen",
    "wof:name":"Bloemendiscount 't Betanieke",
    "wof:placetype":"venue"
},
  "geometry": {"coordinates":[4.4987201691,51.3124198914],"type":"Point"}
}