{
  "type": "Feature",
  "properties": {
    "addr:full":"Izegemsestraat 11a Lendelede West-Vlaanderen 8860",
    "addr:housenumber":"11a",
    "addr:postcode":"8860",
    "addr:street":"Izegemsestraat",
    "iso:country":"BE",
    "sg:address":"Izegemsestraat 11a",
    "sg:city":"Lendelede",
    "sg:classifiers":[
        {
            "category":"Tea Room",
            "subcategory":"None",
            "type":"Food & Drink"
        }
    ],
    "sg:phone":"+32 51 31 49 98",
    "sg:postcode":"8860",
    "sg:province":"West-Vlaanderen",
    "wof:name":"Speelvogel (de)",
    "wof:placetype":"venue"
},
  "geometry": {"coordinates":[3.237251997,50.8874778748],"type":"Point"}
}