{
  "type": "Feature",
  "properties": {
    "addr:full":"Chauss\u00c9e De Louvain 523 Bruxelles-ixelles Bruxelles-Capitale 1050",
    "addr:housenumber":"523",
    "addr:postcode":"1050",
    "addr:street":"Chausse\u0301E De Louvain",
    "iso:country":"BE",
    "sg:address":"Chauss\u00c9e De Louvain 523",
    "sg:city":"Bruxelles-ixelles",
    "sg:orig_category":"Microsoft. Ordinateurs and \u00e9quipement informatique",
    "sg:phone":"+32 2 646 25 58",
    "sg:postcode":"1050",
    "sg:province":"Bruxelles-Capitale",
    "wof:name":"Goldtronics Micro System",
    "wof:placetype":"venue"
},
  "geometry": {"coordinates":[4.3667850494,50.8326339722],"type":"Point"}
}