{
  "type": "Feature",
  "properties": {
    "addr:full":"Pl. De Masnuy-st.-pierre 22 Jurbise Hainaut 7050",
    "addr:housenumber":"22",
    "addr:postcode":"7050",
    "iso:country":"BE",
    "sg:address":"Pl. De Masnuy-st.-pierre 22",
    "sg:city":"Jurbise",
    "sg:orig_category":"Dierenartsen",
    "sg:phone":"+32 65 22 57 26",
    "sg:postcode":"7050",
    "sg:province":"Hainaut",
    "wof:name":"Bernard Van Den Noortgate",
    "wof:placetype":"venue"
},
  "geometry": {"coordinates":[3.9598970413,50.5368118286],"type":"Point"}
}