{
  "type": "Feature",
  "properties": {
    "iso:country":"BE",
    "sg:address":"Amerikastraat 3",
    "sg:city":"Sint-gillis/saint-gilles",
    "sg:orig_category":"Artsen and specialisten",
    "sg:phone":"+32 2 544 09 57",
    "sg:postcode":"1060",
    "sg:province":"Bruxelles-Capitale",
    "wof:name":"Catherine Meunier",
    "wof:placetype":"venue"
},
  "geometry": {"coordinates":[4.3545827866,50.8244361877],"type":"Point"}
}