{
  "type": "Feature",
  "properties": {
    "iso:country":"BE",
    "sg:address":"Laan Op Heusden 18",
    "sg:city":"Koersel",
    "sg:orig_category":"Auto-\u00e9coles",
    "sg:phone":"+32 11 43 19 04",
    "sg:postcode":"3582",
    "sg:province":"Limburg",
    "wof:name":"Rijschool De Schepper",
    "wof:placetype":"venue"
},
  "geometry": {"coordinates":[5.2745838165,51.0527763367],"type":"Point"}
}