{
  "type": "Feature",
  "properties": {
    "addr:full":"Mieregemstraat 60a Merchtem Vlaams-Brabant 1785",
    "addr:housenumber":"60a",
    "addr:postcode":"1785",
    "addr:street":"Mieregemstraat",
    "iso:country":"BE",
    "sg:address":"Mieregemstraat 60a",
    "sg:city":"Merchtem",
    "sg:classifiers":[
        {
            "category":"Health Services",
            "subcategory":"Doctor",
            "type":"Services"
        }
    ],
    "sg:phone":"+32 52 37 10 53",
    "sg:postcode":"1785",
    "sg:province":"Vlaams-Brabant",
    "sg:tags":[
        "medicinephysicians",
        "surgeon"
    ],
    "wof:name":"De Block Maggie",
    "wof:placetype":"venue"
},
  "geometry": {"coordinates":[4.2309908867,50.9559822083],"type":"Point"}
}