{
  "type": "Feature",
  "properties": {
    "iso:country":"BE",
    "sg:address":"Pontstraat 14",
    "sg:city":"Aalst",
    "sg:classifiers":[
        {
            "category":"Shopping",
            "subcategory":"Optician",
            "type":"Retail Goods"
        }
    ],
    "sg:phone":"+32 53 21 24 09",
    "sg:postcode":"9300",
    "sg:province":"Oost-Vlaanderen",
    "sg:tags":[
        "-"
    ],
    "wof:name":"De Vijlder Optiek",
    "wof:placetype":"venue"
},
  "geometry": {"coordinates":[4.0418438911,50.9370422363],"type":"Point"}
}