{
  "type": "Feature",
  "properties": {
    "addr:full":"Zuidlaan 7 Hoeilaart Vlaams-Brabant 1560",
    "addr:housenumber":"7",
    "addr:postcode":"1560",
    "addr:street":"Zuidlaan",
    "iso:country":"BE",
    "sg:address":"Zuidlaan 7",
    "sg:city":"Hoeilaart",
    "sg:classifiers":[
        {
            "category":"Health Services",
            "subcategory":"Doctor",
            "type":"Services"
        }
    ],
    "sg:phone":"+32 2 657 67 50",
    "sg:postcode":"1560",
    "sg:province":"Vlaams-Brabant",
    "sg:tags":[
        "medicinephysicians",
        "surgeon"
    ],
    "wof:name":"Abramow M",
    "wof:placetype":"venue"
},
  "geometry": {"coordinates":[4.4975218773,50.7673492432],"type":"Point"}
}