{
  "type": "Feature",
  "properties": {
    "addr:full":"Blauwhofdreef 28 Berlare Oost-Vlaanderen 9290",
    "addr:housenumber":"28",
    "addr:postcode":"9290",
    "addr:street":"Blauwhofdreef",
    "iso:country":"BE",
    "sg:address":"Blauwhofdreef 28",
    "sg:city":"Berlare",
    "sg:orig_category":"Diverse producten Gh",
    "sg:phone":"+32 9 367 54 82",
    "sg:postcode":"9290",
    "sg:province":"Oost-Vlaanderen",
    "wof:name":"Jartazi Sport- En Promotieartikelen",
    "wof:placetype":"venue"
},
  "geometry": {"coordinates":[3.9880800247,51.0304718018],"type":"Point"}
}