{
  "type": "Feature",
  "properties": {
    "addr:full":"Tillet 52 Sainte-ode Luxembourg 6680",
    "addr:housenumber":"52",
    "addr:postcode":"6680",
    "addr:street":"Tillet",
    "iso:country":"BE",
    "sg:address":"Tillet 52",
    "sg:city":"Sainte-ode",
    "sg:orig_category":"Enseignement maternel and primaire",
    "sg:phone":"+32 61 68 91 19",
    "sg:postcode":"6680",
    "sg:province":"Luxembourg",
    "wof:name":"Ecole Fond. Communale",
    "wof:placetype":"venue"
},
  "geometry": {"coordinates":[5.519302845,50.0202293396],"type":"Point"}
}