{
  "type": "Feature",
  "properties": {
    "iso:country":"BE",
    "sg:address":"Rue Sous-le-ch\u00c2teau 10",
    "sg:city":"Huy",
    "sg:orig_category":"Fleurs and plantes",
    "sg:phone":"+32 85 23 54 74",
    "sg:postcode":"4500",
    "sg:province":"Li\u00e8ge",
    "wof:name":"Chlorophyl",
    "wof:placetype":"venue"
},
  "geometry": {"coordinates":[5.2391571999,50.518196106],"type":"Point"}
}