{
  "type": "Feature",
  "properties": {
    "addr:full":"Chauss\u00c9e De Wavre 84 Jodoigne Brabant Wallon 1370",
    "addr:housenumber":"84",
    "addr:postcode":"1370",
    "addr:street":"Chausse\u0301E De Wavre",
    "iso:country":"BE",
    "sg:address":"Chauss\u00c9e De Wavre 84",
    "sg:city":"Jodoigne",
    "sg:orig_category":"Traitement and fa\u00e7onnage de la pierre. Traitement and fa\u00e7onnage de la pierre",
    "sg:phone":"+32 10 81 20 56",
    "sg:postcode":"1370",
    "sg:province":"Brabant Wallon",
    "wof:name":"Liesse Stone S.a.",
    "wof:placetype":"venue"
},
  "geometry": {"coordinates":[4.8581109047,50.7242736816],"type":"Point"}
}