{
  "type": "Feature",
  "properties": {
    "addr:full":"Place De Blaton 23 Bernissart Hainaut 7321",
    "addr:housenumber":"23",
    "addr:postcode":"7321",
    "addr:street":"Place De Blaton",
    "iso:country":"BE",
    "sg:address":"Place De Blaton 23",
    "sg:city":"Bernissart",
    "sg:classifiers":[
        {
            "category":"Cafe",
            "type":"Food & Drink"
        }
    ],
    "sg:phone":"+32 69 57 58 86",
    "sg:postcode":"7321",
    "sg:province":"Hainaut",
    "sg:tags":[
        "caf\u00e9s"
    ],
    "wof:name":"Caf\u00c9 Au Maquis",
    "wof:placetype":"venue"
},
  "geometry": {"coordinates":[3.6568610668,50.4869003296],"type":"Point"}
}