{
  "type": "Feature",
  "properties": {
    "addr:full":"Chauss\u00e9e De Waterloo 182 Namur (saint-servais) Namur 5002",
    "addr:housenumber":"182",
    "addr:postcode":"5002",
    "addr:street":"Chausse\u0301E De Waterloo",
    "iso:country":"BE",
    "sg:address":"Chauss\u00e9e De Waterloo 182",
    "sg:city":"Namur (saint-servais)",
    "sg:classifiers":[
        {
            "category":"Communications",
            "subcategory":"Film & Video Production",
            "type":"Services"
        }
    ],
    "sg:phone":"+32 81 72 92 67",
    "sg:postcode":"5002",
    "sg:province":"Namur",
    "sg:tags":[
        "hiring",
        "-"
    ],
    "wof:name":"Maison Des Jeunes",
    "wof:placetype":"venue"
},
  "geometry": {"coordinates":[4.8462319374,50.4782791138],"type":"Point"}
}