{
  "type": "Feature",
  "properties": {
    "iso:country":"BE",
    "sg:address":"Hamonterweg 103",
    "sg:city":"Hamont-achel",
    "sg:classifiers":[
        {
            "category":"Manufacturing",
            "subcategory":"Metals",
            "type":"Manufacturing & Wholesale Goods"
        }
    ],
    "sg:phone":"+32 11 64 07 51",
    "sg:postcode":"3930",
    "sg:province":"Limburg",
    "sg:tags":[
        "alloy",
        "construction",
        "lightweight"
    ],
    "wof:name":"Csm Nv",
    "wof:placetype":"venue"
},
  "geometry": {"coordinates":[5.4719958305,51.2399482727],"type":"Point"}
}