{
  "type": "Feature",
  "properties": {
    "addr:full":"Route De Blaimont 18 Hasti\u00e8re (hasti\u00e8re-par-del\u00e0) Namur 5541",
    "addr:housenumber":"18",
    "addr:postcode":"5541",
    "addr:street":"Route De Blaimont",
    "iso:country":"BE",
    "sg:address":"Route De Blaimont 18",
    "sg:city":"Hasti\u00e8re (hasti\u00e8re-par-del\u00e0)",
    "sg:classifiers":[
        {
            "category":"Shopping",
            "subcategory":"Crafts & Fabrics",
            "type":"Retail Goods"
        }
    ],
    "sg:phone":"+32 82 64 59 65",
    "sg:postcode":"5541",
    "sg:province":"Namur",
    "sg:tags":[
        "ceramic"
    ],
    "wof:name":"Thiran B",
    "wof:placetype":"venue"
},
  "geometry": {"coordinates":[4.8296298981,50.2147407532],"type":"Point"}
}