{
  "type": "Feature",
  "properties": {
    "addr:full":"De Schaaf 6 Malle Antwerpen 2390",
    "addr:housenumber":"6",
    "addr:postcode":"2390",
    "addr:street":"De Schaaf",
    "iso:country":"BE",
    "sg:address":"De Schaaf 6",
    "sg:city":"Malle",
    "sg:orig_category":"Huisdieren and benodigdheden",
    "sg:phone":"+32 3 309 95 94",
    "sg:postcode":"2390",
    "sg:province":"Antwerpen",
    "wof:name":"Het Honinghuis Van Malle",
    "wof:placetype":"venue"
},
  "geometry": {"coordinates":[4.7172899246,51.2886199951],"type":"Point"}
}