{
  "type": "Feature",
  "properties": {
    "iso:country":"BE",
    "sg:address":"Populierstraat 75",
    "sg:city":"Roeselare",
    "sg:classifiers":[
        {
            "category":"Retail",
            "subcategory":"Repair Shop",
            "type":"Services"
        }
    ],
    "sg:phone":"+32 51 20 75 34",
    "sg:postcode":"8800",
    "sg:province":"West-Vlaanderen",
    "sg:tags":[
        "sharpening",
        "workshop",
        "saw"
    ],
    "wof:name":"Leitz Service Nv",
    "wof:placetype":"venue"
},
  "geometry": {"coordinates":[3.158700943,50.9483222961],"type":"Point"}
}