{
  "type": "Feature",
  "properties": {
    "iso:country":"BE",
    "sg:address":"Rue Fran\u00e7ois Sarteel 311",
    "sg:city":"Sambreville (auvelais)",
    "sg:classifiers":[
        {
            "category":"Bakery",
            "type":"Food & Drink"
        }
    ],
    "sg:phone":"+32 71 76 10 41",
    "sg:postcode":"5060",
    "sg:province":"Namur",
    "sg:tags":[
        "confectioner",
        "baker"
    ],
    "wof:name":"Lacroix & Cie Sprl",
    "wof:placetype":"venue"
},
  "geometry": {"coordinates":[4.6285200119,50.4448738098],"type":"Point"}
}