{
  "type": "Feature",
  "properties": {
    "addr:full":"Rue Keuterre 5 Sombreffe Namur 5140",
    "addr:housenumber":"5",
    "addr:postcode":"5140",
    "addr:street":"Rue Keuterre",
    "iso:country":"BE",
    "sg:address":"Rue Keuterre 5",
    "sg:city":"Sombreffe",
    "sg:orig_category":"Boucheries",
    "sg:phone":"+32 71 88 83 65",
    "sg:postcode":"5140",
    "sg:province":"Namur",
    "wof:name":"Hubert Delfosse",
    "wof:placetype":"venue"
},
  "geometry": {"coordinates":[4.6014790535,50.5253448486],"type":"Point"}
}