{
  "type": "Feature",
  "properties": {
    "addr:full":"Parklaan 60 Aalst Oost-Vlaanderen 9300",
    "addr:housenumber":"60",
    "addr:postcode":"9300",
    "addr:street":"Parklaan",
    "iso:country":"BE",
    "sg:address":"Parklaan 60",
    "sg:city":"Aalst",
    "sg:classifiers":[
        {
            "category":"Bars & Pubs",
            "type":"Food & Drink"
        }
    ],
    "sg:phone":"+32 53 77 43 46",
    "sg:postcode":"9300",
    "sg:province":"Oost-Vlaanderen",
    "wof:name":"The Fox Pub",
    "wof:placetype":"venue"
},
  "geometry": {"coordinates":[4.0426998138,50.931060791],"type":"Point"}
}