{
  "type": "Feature",
  "properties": {
    "iso:country":"BE",
    "sg:address":"Rue De Philippeville 8",
    "sg:city":"Nalinnes",
    "sg:orig_category":"Packard Bell Nec. Ordinateurs and \u00e9quipement informatique",
    "sg:phone":"+32 71 22 06 51",
    "sg:postcode":"6120",
    "sg:province":"Hainaut",
    "wof:name":"Photo-hall Nalinnes",
    "wof:placetype":"venue"
},
  "geometry": {"coordinates":[4.4731721878,50.3425292969],"type":"Point"}
}