{
  "type": "Feature",
  "properties": {
    "addr:full":"Rostenne 1 Onhaye Namur 5523",
    "addr:housenumber":"1",
    "addr:postcode":"5523",
    "addr:street":"Rostenne",
    "iso:country":"BE",
    "sg:address":"Rostenne 1",
    "sg:city":"Onhaye",
    "sg:orig_category":"Rundveehouders",
    "sg:phone":"+32 82 22 34 15",
    "sg:postcode":"5523",
    "sg:province":"Namur",
    "wof:name":"De Rostenne",
    "wof:placetype":"venue"
},
  "geometry": {"coordinates":[4.8271818161,50.260597229],"type":"Point"}
}