{
  "type": "Feature",
  "properties": {
    "iso:country":"BE",
    "sg:address":"Rue F\u00e9lix-paulsen 5",
    "sg:city":"Li\u00e8ge 1 (angleur)",
    "sg:classifiers":[
        {
            "category":"Professional",
            "subcategory":"Secretarial Services",
            "type":"Services"
        }
    ],
    "sg:phone":"+32 4 365 88 55",
    "sg:postcode":"4031",
    "sg:province":"Li\u00e8ge",
    "sg:tags":[
        "-",
        "wordprocessing"
    ],
    "wof:name":"Az Secr\u00e9tariat",
    "wof:placetype":"venue"
},
  "geometry": {"coordinates":[5.586810112,50.6133766174],"type":"Point"}
}