{
  "type": "Feature",
  "properties": {
    "iso:country":"BE",
    "sg:address":"Markt 46",
    "sg:city":"Deinze",
    "sg:orig_category":"Secr\u00e9tariats sociaux",
    "sg:phone":"+32 9 386 50 56",
    "sg:postcode":"9800",
    "sg:province":"Oost-Vlaanderen",
    "wof:name":"Sociale Werkgeverscentr.",
    "wof:placetype":"venue"
},
  "geometry": {"coordinates":[3.5266559124,50.98387146],"type":"Point"}
}