{
  "type": "Feature",
  "properties": {
    "addr:full":"Steppestede 51 Gent (sint-denijs-westrem - Afsnee) Oost-Vlaanderen 9051",
    "addr:housenumber":"51",
    "addr:postcode":"9051",
    "addr:street":"Steppestede;Oost-Vlaanderen",
    "iso:country":"BE",
    "sg:address":"Steppestede 51",
    "sg:city":"Gent (sint-denijs-westrem - Afsnee)",
    "sg:classifiers":[
        {
            "category":"Professional",
            "subcategory":"Accounting & Tax Preparation",
            "type":"Services"
        }
    ],
    "sg:phone":"+32 9 221 64 21",
    "sg:postcode":"9051",
    "sg:province":"Oost-Vlaanderen",
    "sg:tags":[
        "bookkeeper"
    ],
    "wof:name":"Goem\u00e9 J",
    "wof:placetype":"venue"
},
  "geometry": {"coordinates":[3.6666369438,51.0145187378],"type":"Point"}
}