{
  "type": "Feature",
  "properties": {
    "iso:country":"BE",
    "sg:address":"Lindestraat 1",
    "sg:city":"Alveringem (hoogstade)",
    "sg:classifiers":[
        {
            "category":"Professional",
            "subcategory":"Engineering",
            "type":"Services"
        }
    ],
    "sg:phone":"+32 57 30 13 24",
    "sg:postcode":"8690",
    "sg:province":"West-Vlaanderen",
    "sg:tags":[
        "technical",
        "industrial",
        "-",
        "subcontracting"
    ],
    "wof:name":"P.i.d.e. Bvba",
    "wof:placetype":"venue"
},
  "geometry": {"coordinates":[2.7127139568,51.0079917908],"type":"Point"}
}