{
  "type": "Feature",
  "properties": {
    "addr:full":"Rue Du Petit Audenarde 33-35 Mouscron (herseaux) Hainaut 7712",
    "addr:housenumber":"33-35",
    "addr:postcode":"7712",
    "addr:street":"Rue Du Petit Audenarde",
    "iso:country":"BE",
    "sg:address":"Rue Du Petit Audenarde 33-35",
    "sg:city":"Mouscron (herseaux)",
    "sg:classifiers":[
        {
            "category":"Shopping",
            "subcategory":"Florist",
            "type":"Retail Goods"
        }
    ],
    "sg:phone":"+32 56 33 13 53",
    "sg:postcode":"7712",
    "sg:province":"Hainaut",
    "wof:name":"Bernadette (fleurs)",
    "wof:placetype":"venue"
},
  "geometry": {"coordinates":[3.2387700081,50.7119102478],"type":"Point"}
}