{
  "type": "Feature",
  "properties": {
    "addr:full":"Gentsestraat 81 Aalst Oost-Vlaanderen 9300",
    "addr:housenumber":"81",
    "addr:postcode":"9300",
    "addr:street":"Gentsestraat",
    "iso:country":"BE",
    "sg:address":"Gentsestraat 81",
    "sg:city":"Aalst",
    "sg:classifiers":[
        {
            "category":"Bakery",
            "type":"Food & Drink"
        }
    ],
    "sg:phone":"+32 53 77 55 84",
    "sg:postcode":"9300",
    "sg:province":"Oost-Vlaanderen",
    "sg:tags":[
        "confectioner",
        "baker"
    ],
    "wof:name":"Edelweiss",
    "wof:placetype":"venue"
},
  "geometry": {"coordinates":[4.03018713,50.9377822876],"type":"Point"}
}