{
  "type": "Feature",
  "properties": {
    "addr:full":"Rue Brouck Au Tilleul 15ba3 Bassenge Li\u00e8ge 4690",
    "addr:postcode":"4690",
    "addr:street":"Rue Brouck Au Tilleul 15Ba3",
    "iso:country":"BE",
    "sg:address":"Rue Brouck Au Tilleul 15ba3",
    "sg:city":"Bassenge",
    "sg:orig_category":"Boissons",
    "sg:phone":"+32 4 286 15 54",
    "sg:postcode":"4690",
    "sg:province":"Li\u00e8ge",
    "wof:name":"Jacques Maloir Et Fils",
    "wof:placetype":"venue"
},
  "geometry": {"coordinates":[5.5446481705,50.75548172],"type":"Point"}
}