{
  "type": "Feature",
  "properties": {
    "addr:full":"Plantin Moretuslei 156 Antwerpen Antwerpen 2018",
    "addr:housenumber":"156",
    "addr:postcode":"2018",
    "addr:street":"Plantin Moretuslei",
    "iso:country":"BE",
    "sg:address":"Plantin Moretuslei 156",
    "sg:city":"Antwerpen",
    "sg:orig_category":"Mobistar Centres",
    "sg:phone":"+32 3 235 51 15",
    "sg:postcode":"2018",
    "sg:province":"Antwerpen",
    "wof:name":"Mobistar Center Mtc Antwerpen",
    "wof:placetype":"venue"
},
  "geometry": {"coordinates":[4.4322562218,51.2090110779],"type":"Point"}
}