{
  "type": "Feature",
  "properties": {
    "addr:full":"Kruisstraat 16 Herentals Antwerpen 2200",
    "addr:housenumber":"16",
    "addr:postcode":"2200",
    "addr:street":"Kruisstraat",
    "iso:country":"BE",
    "sg:address":"Kruisstraat 16",
    "sg:city":"Herentals",
    "sg:orig_category":"Huisdieren and benodigdheden",
    "sg:phone":"+32 14 22 29 38",
    "sg:postcode":"2200",
    "sg:province":"Antwerpen",
    "wof:name":"Albatros",
    "wof:placetype":"venue"
},
  "geometry": {"coordinates":[4.835477829,51.1722564697],"type":"Point"}
}