{
  "type": "Feature",
  "properties": {
    "addr:full":"Chauss\u00c9e De Ninove 548 Anderlecht/anderlecht Bruxelles-Capitale 1070",
    "addr:housenumber":"548",
    "addr:postcode":"1070",
    "addr:street":"Chausse\u0301E De Ninove",
    "iso:country":"BE",
    "sg:address":"Chauss\u00c9e De Ninove 548",
    "sg:city":"Anderlecht/anderlecht",
    "sg:orig_category":"Mus\u00e9es and patrimoine culturel",
    "sg:phone":"+32 2 521 47 29",
    "sg:postcode":"1070",
    "sg:province":"Bruxelles-Capitale",
    "wof:name":"Mus\u00c9e De Chine",
    "wof:placetype":"venue"
},
  "geometry": {"coordinates":[4.305316925,50.8473205566],"type":"Point"}
}