{
  "type": "Feature",
  "properties": {
    "addr:full":"Oude Sluissedijk 62ba Damme West-Vlaanderen 8340",
    "addr:housenumber":"62ba",
    "addr:postcode":"8340",
    "addr:street":"Oude Sluissedijk",
    "iso:country":"BE",
    "sg:address":"Oude Sluissedijk 62ba",
    "sg:city":"Damme",
    "sg:orig_category":"Rundveehouders Varkenskwekers",
    "sg:phone":"+32 50 50 04 93",
    "sg:postcode":"8340",
    "sg:province":"West-Vlaanderen",
    "wof:name":"Danny Stroo",
    "wof:placetype":"venue"
},
  "geometry": {"coordinates":[3.3155629635,51.2618713379],"type":"Point"}
}