{
  "type": "Feature",
  "properties": {
    "iso:country":"BE",
    "sg:address":"J. B. Michielsstraat 21",
    "sg:city":"Hoeilaart",
    "sg:classifiers":[
        {
            "category":"Food & Beverages",
            "subcategory":"Fruits & Vegetables",
            "type":"Retail Goods"
        }
    ],
    "sg:phone":"+32 2 657 15 92",
    "sg:postcode":"1560",
    "sg:province":"Vlaams-Brabant",
    "sg:tags":[
        "l\u00e9gumes",
        "gr"
    ],
    "wof:name":"Christian Vanhaeght",
    "wof:placetype":"venue"
},
  "geometry": {"coordinates":[4.467651844,50.7655982971],"type":"Point"}
}