{
  "type": "Feature",
  "properties": {
    "addr:full":"Chauss\u00c9e De Mons 26 Nivelles Brabant Wallon 1400",
    "addr:housenumber":"26",
    "addr:postcode":"1400",
    "addr:street":"Chausse\u0301E De Mons",
    "iso:country":"BE",
    "sg:address":"Chauss\u00c9e De Mons 26",
    "sg:city":"Nivelles",
    "sg:orig_category":"Quincailleries",
    "sg:phone":"+32 67 21 61 18",
    "sg:postcode":"1400",
    "sg:province":"Brabant Wallon",
    "wof:name":"Superbois",
    "wof:placetype":"venue"
},
  "geometry": {"coordinates":[4.3185691833,50.5938568115],"type":"Point"}
}