{
  "type": "Feature",
  "properties": {
    "addr:full":"Clos Des Palombes 11 Waterloo Brabant Wallon 1410",
    "addr:housenumber":"11",
    "addr:postcode":"1410",
    "addr:street":"Clos Des Palombes",
    "iso:country":"BE",
    "sg:address":"Clos Des Palombes 11",
    "sg:city":"Waterloo",
    "sg:orig_category":"Koerierbedrijven",
    "sg:phone":"+32 2 351 48 50",
    "sg:postcode":"1410",
    "sg:province":"Brabant Wallon",
    "wof:name":"Transp. Zenith Intern.",
    "wof:placetype":"venue"
},
  "geometry": {"coordinates":[4.4233841896,50.7065353394],"type":"Point"}
}