{
  "type": "Feature",
  "properties": {
    "addr:full":"Lindelsebaan 234 Overpelt Limburg 3900",
    "addr:housenumber":"234",
    "addr:postcode":"3900",
    "addr:street":"Lindelsebaan",
    "iso:country":"BE",
    "sg:address":"Lindelsebaan 234",
    "sg:city":"Overpelt",
    "sg:classifiers":[
        {
            "category":"Insurance",
            "subcategory":"Insurance Agent",
            "type":"Services"
        }
    ],
    "sg:phone":"+32 11 64 54 88",
    "sg:postcode":"3900",
    "sg:province":"Limburg",
    "sg:tags":[
        "verzekeringsmakelaars",
        "expert"
    ],
    "wof:name":"Gielen",
    "wof:placetype":"venue"
},
  "geometry": {"coordinates":[5.4034051895,51.2007408142],"type":"Point"}
}