{
  "type": "Feature",
  "properties": {
    "addr:full":"Neringenstraat 43 Tielt West-Vlaanderen 8700",
    "addr:housenumber":"43",
    "addr:postcode":"8700",
    "addr:street":"Neringenstraat",
    "iso:country":"BE",
    "sg:address":"Neringenstraat 43",
    "sg:city":"Tielt",
    "sg:orig_category":"Boucheries",
    "sg:phone":"+32 51 63 65 16",
    "sg:postcode":"8700",
    "sg:province":"West-Vlaanderen",
    "wof:name":"Kurt Declercq",
    "wof:placetype":"venue"
},
  "geometry": {"coordinates":[3.4100599289,51.0066795349],"type":"Point"}
}