{
  "type": "Feature",
  "properties": {
    "addr:full":"Rijmenstraat 16 Overpelt Limburg 3900",
    "addr:housenumber":"16",
    "addr:postcode":"3900",
    "addr:street":"Rijmenstraat",
    "iso:country":"BE",
    "sg:address":"Rijmenstraat 16",
    "sg:city":"Overpelt",
    "sg:orig_category":"Non-Classified Establishments",
    "sg:phone":"+32 11 80 35 91",
    "sg:postcode":"3900",
    "sg:province":"Limburg",
    "wof:name":"Depolim Bvba",
    "wof:placetype":"venue"
},
  "geometry": {"coordinates":[5.414691925,51.2096405029],"type":"Point"}
}