{
  "type": "Feature",
  "properties": {
    "addr:full":"Sint-lendriksborre 11 Mercator Science Park Brussel Bruxelles-Capitale 1120",
    "addr:housenumber":"11",
    "addr:postcode":"1120",
    "addr:street":"Sint-Lendriksborre;Science Park",
    "iso:country":"BE",
    "sg:address":"Sint-lendriksborre 11 Mercator Science Park",
    "sg:city":"Brussel",
    "sg:classifiers":[
        {
            "category":"Manufacturing",
            "subcategory":"Metals",
            "type":"Manufacturing & Wholesale Goods"
        }
    ],
    "sg:phone":"+32 71 51 84 22",
    "sg:postcode":"1120",
    "sg:province":"Bruxelles-Capitale",
    "sg:tags":[
        "metallurgy",
        "metalworking",
        "processing"
    ],
    "wof:name":"Bodycote Belgium",
    "wof:placetype":"venue"
},
  "geometry": {"coordinates":[3.2783899307,50.4083709717],"type":"Point"}
}