{
  "type": "Feature",
  "properties": {
    "addr:full":"Libomont 1 Weismes Li\u00e8ge 4950",
    "addr:housenumber":"1",
    "addr:postcode":"4950",
    "addr:street":"Libomont",
    "iso:country":"BE",
    "sg:address":"Libomont 1",
    "sg:city":"Weismes",
    "sg:classifiers":[
        {
            "category":"Professional",
            "subcategory":"Art Services",
            "type":"Services"
        }
    ],
    "sg:phone":"+32 80 67 84 68",
    "sg:postcode":"4950",
    "sg:province":"Li\u00e8ge",
    "sg:tags":[
        "interior",
        "designer"
    ],
    "wof:name":"Rosen-wey",
    "wof:placetype":"venue"
},
  "geometry": {"coordinates":[6.0968198776,50.4279899597],"type":"Point"}
}