{
  "type": "Feature",
  "properties": {
    "iso:country":"BE",
    "sg:address":"Rue Grandgagnage 28",
    "sg:city":"Namur",
    "sg:classifiers":[
        {
            "category":"Professional",
            "subcategory":"Lawyer & Legal Services",
            "type":"Services"
        }
    ],
    "sg:phone":"+32 81 22 91 14",
    "sg:postcode":"5000",
    "sg:province":"Namur",
    "wof:name":"Ledoux E",
    "wof:placetype":"venue"
},
  "geometry": {"coordinates":[4.8577809334,50.4649085999],"type":"Point"}
}