{
  "type": "Feature",
  "properties": {
    "addr:full":"Brugsesteenweg 71 Gent Oost-Vlaanderen 9000",
    "addr:housenumber":"71",
    "addr:postcode":"9000",
    "addr:street":"Brugsesteenweg;Oost-Vlaanderen",
    "iso:country":"BE",
    "sg:address":"Brugsesteenweg 71",
    "sg:city":"Gent",
    "sg:orig_category":"Tabac. Journaux",
    "sg:phone":"+32 9 226 56 52",
    "sg:postcode":"9000",
    "sg:province":"Oost-Vlaanderen",
    "wof:name":"\u00b4t Pelikaantje",
    "wof:placetype":"venue"
},
  "geometry": {"coordinates":[3.695389986,51.0636711121],"type":"Point"}
}