{
  "type": "Feature",
  "properties": {
    "addr:full":"Rue De La Bruy\u00e8re 20 Tournai (kain) Hainaut 7540",
    "addr:housenumber":"20",
    "addr:postcode":"7540",
    "addr:street":"Rue De La Bruye\u0300Re",
    "iso:country":"BE",
    "sg:address":"Rue De La Bruy\u00e8re 20",
    "sg:city":"Tournai (kain)",
    "sg:classifiers":[
        {
            "category":"Health Services",
            "subcategory":"Medical Lab",
            "type":"Services"
        }
    ],
    "sg:phone":"+32 69 23 34 81",
    "sg:postcode":"7540",
    "sg:province":"Hainaut",
    "sg:tags":[
        "laboratory",
        "dental"
    ],
    "wof:name":"Ducobu S",
    "wof:placetype":"venue"
},
  "geometry": {"coordinates":[3.3659830093,50.6491279602],"type":"Point"}
}