{
  "type": "Feature",
  "properties": {
    "addr:full":"Pulsebaan 50 Box 1 Zandhoven (pulderbos) Antwerpen 2242",
    "addr:housenumber":"50;1",
    "addr:postcode":"2242",
    "addr:street":"Pulsebaan;Box",
    "iso:country":"BE",
    "sg:address":"Pulsebaan 50 Box 1",
    "sg:city":"Zandhoven (pulderbos)",
    "sg:orig_category":"Newspapers, magazines, periodicals - Publishers",
    "sg:phone":"+32 3 466 00 66",
    "sg:postcode":"2242",
    "sg:province":"Antwerpen",
    "wof:name":"Epn. Int. Nv",
    "wof:placetype":"venue"
},
  "geometry": {"coordinates":[4.6940460205,51.2122764587],"type":"Point"}
}