{
  "type": "Feature",
  "properties": {
    "iso:country":"BE",
    "sg:address":"Befferstraat 5",
    "sg:city":"Mechelen",
    "sg:classifiers":[
        {
            "category":"Shopping",
            "subcategory":"Books",
            "type":"Retail Goods"
        }
    ],
    "sg:phone":"+32 15 20 18 32",
    "sg:postcode":"2800",
    "sg:province":"Antwerpen",
    "sg:tags":[
        "bookseller"
    ],
    "wof:name":"Salvator Boekhandel",
    "wof:placetype":"venue"
},
  "geometry": {"coordinates":[4.481315136,51.0283164978],"type":"Point"}
}