{
  "type": "Feature",
  "properties": {
    "addr:full":"Pastoor Dergentstraat 105 Aarschot (gelrode) Vlaams-Brabant 3200",
    "addr:housenumber":"105",
    "addr:postcode":"3200",
    "addr:street":"Pastoor Dergentstraat",
    "iso:country":"BE",
    "sg:address":"Pastoor Dergentstraat 105",
    "sg:city":"Aarschot (gelrode)",
    "sg:classifiers":[
        {
            "category":"Health Services",
            "subcategory":"Dentist",
            "type":"Services"
        }
    ],
    "sg:phone":"+32 16 56 58 95",
    "sg:postcode":"3200",
    "sg:province":"Vlaams-Brabant",
    "wof:name":"Geyskens - Claes G",
    "wof:placetype":"venue"
},
  "geometry": {"coordinates":[4.7980999947,50.964389801],"type":"Point"}
}