{
  "type": "Feature",
  "properties": {
    "addr:full":"Rue Paquay 22 Seraing Li\u00e8ge 4100",
    "addr:housenumber":"22",
    "addr:postcode":"4100",
    "addr:street":"Rue Paquay",
    "iso:country":"BE",
    "sg:address":"Rue Paquay 22",
    "sg:city":"Seraing",
    "sg:classifiers":[
        {
            "category":"Structure",
            "subcategory":"Building",
            "type":"Public Place"
        }
    ],
    "sg:phone":"+32 4 336 22 97",
    "sg:postcode":"4100",
    "sg:province":"Li\u00e8ge",
    "sg:tags":[
        "door"
    ],
    "wof:name":"Delvoie M",
    "wof:placetype":"venue"
},
  "geometry": {"coordinates":[5.5210189819,50.6020431519],"type":"Point"}
}