{
  "type": "Feature",
  "properties": {
    "iso:country":"BE",
    "sg:address":"Cuvelierstraat 48",
    "sg:city":"Rijkhoven",
    "sg:classifiers":[
        {
            "category":"Farming",
            "subcategory":"Livestock Farm",
            "type":"Manufacturing & Wholesale Goods"
        }
    ],
    "sg:phone":"+32 89 41 37 80",
    "sg:postcode":"3740",
    "sg:province":"Limburg",
    "sg:tags":[
        "breeding",
        "agriculture",
        "animal"
    ],
    "wof:name":"Mevr Nathalia Vandebeek",
    "wof:placetype":"venue"
},
  "geometry": {"coordinates":[5.5133070946,50.8699760437],"type":"Point"}
}