{
  "type": "Feature",
  "properties": {
    "iso:country":"BE",
    "sg:address":"Herentalsebaan 10",
    "sg:city":"Zandhoven",
    "sg:classifiers":[
        {
            "category":"Autos & Motor Vehicles",
            "subcategory":"Motorcycle Sales",
            "type":"Retail Goods"
        }
    ],
    "sg:phone":"+32 3 475 91 95",
    "sg:postcode":"2240",
    "sg:province":"Antwerpen",
    "sg:tags":[
        "motorbike"
    ],
    "wof:name":"Jecomoto",
    "wof:placetype":"venue"
},
  "geometry": {"coordinates":[4.6325960159,51.1881828308],"type":"Point"}
}