{
  "type": "Feature",
  "properties": {
    "iso:country":"BE",
    "sg:address":"Stationsstraat 69",
    "sg:city":"Heist-op-den-berg",
    "sg:orig_category":"Epiceries",
    "sg:phone":"+32 15 25 17 67",
    "sg:postcode":"2220",
    "sg:province":"Antwerpen",
    "wof:name":"Huis Pelgrims",
    "wof:placetype":"venue"
},
  "geometry": {"coordinates":[4.7104687691,51.0753326416],"type":"Point"}
}