{
  "type": "Feature",
  "properties": {
    "addr:full":"Verbindingsstraat 59 Essen Antwerpen 2910",
    "addr:housenumber":"59",
    "addr:postcode":"2910",
    "addr:street":"Verbindingsstraat",
    "iso:country":"BE",
    "sg:address":"Verbindingsstraat 59",
    "sg:city":"Essen",
    "sg:orig_category":"Eleveurs de bovins",
    "sg:phone":"+32 3 677 34 52",
    "sg:postcode":"2910",
    "sg:province":"Antwerpen",
    "wof:name":"Van Thillo Jan & Maria",
    "wof:placetype":"venue"
},
  "geometry": {"coordinates":[4.4114098549,51.4314994812],"type":"Point"}
}