{
  "type": "Feature",
  "properties": {
    "iso:country":"BE",
    "sg:address":"Charles Thielemanslaan 22",
    "sg:city":"Sint-pieters-woluwe/woluwe-saint-pierre",
    "sg:orig_category":"Postkantoren Verzekeringsmakelaars and experts",
    "sg:phone":"+32 2 771 98 00",
    "sg:postcode":"1150",
    "sg:province":"Bruxelles-Capitale",
    "wof:name":"De Post",
    "wof:placetype":"venue"
},
  "geometry": {"coordinates":[4.43100214,50.8369216919],"type":"Point"}
}