{
  "type": "Feature",
  "properties": {
    "addr:full":"Zeedijk 279 Koksijde West-Vlaanderen 8670",
    "addr:housenumber":"279",
    "addr:postcode":"8670",
    "addr:street":"Zeedijk",
    "iso:country":"BE",
    "sg:address":"Zeedijk 279",
    "sg:city":"Koksijde",
    "sg:classifiers":[
        {
            "category":"Restaurant",
            "type":"Food & Drink"
        }
    ],
    "sg:phone":"+32 58 51 35 92",
    "sg:postcode":"8670",
    "sg:province":"West-Vlaanderen",
    "wof:name":"Atlanta",
    "wof:placetype":"venue"
},
  "geometry": {"coordinates":[2.6310739517,51.1197776794],"type":"Point"}
}