{
  "type": "Feature",
  "properties": {
    "addr:full":"Koning Albertstraat 88 Diest Vlaams-Brabant 3290",
    "addr:housenumber":"88",
    "addr:postcode":"3290",
    "addr:street":"Koning Albertstraat",
    "iso:country":"BE",
    "sg:address":"Koning Albertstraat 88",
    "sg:city":"Diest",
    "sg:orig_category":"Agences de voyages",
    "sg:phone":"+32 13 31 28 49",
    "sg:postcode":"3290",
    "sg:province":"Vlaams-Brabant",
    "wof:name":"Oranjetours",
    "wof:placetype":"venue"
},
  "geometry": {"coordinates":[5.055603981,50.9874649048],"type":"Point"}
}