{
  "type": "Feature",
  "properties": {
    "addr:full":"Kafhoek 41 Wevelgem West-Vlaanderen 8560",
    "addr:housenumber":"41",
    "addr:postcode":"8560",
    "addr:street":"Kafhoek",
    "iso:country":"BE",
    "sg:address":"Kafhoek 41",
    "sg:city":"Wevelgem",
    "sg:orig_category":"Activit\u00e9s diverses d'imprimerie",
    "sg:phone":"+32 56 42 17 42",
    "sg:postcode":"8560",
    "sg:province":"West-Vlaanderen",
    "wof:name":"Helga Lust",
    "wof:placetype":"venue"
},
  "geometry": {"coordinates":[3.16563797,50.8419303894],"type":"Point"}
}