{
  "type": "Feature",
  "properties": {
    "addr:full":"Gasthuisstraat 29 Poperinge West-Vlaanderen 8970",
    "addr:housenumber":"29",
    "addr:postcode":"8970",
    "addr:street":"Gasthuisstraat",
    "iso:country":"BE",
    "sg:address":"Gasthuisstraat 29",
    "sg:city":"Poperinge",
    "sg:classifiers":[
        {
            "category":"Real Estate",
            "subcategory":"Surveying",
            "type":"Services"
        }
    ],
    "sg:phone":"+32 57 33 97 24",
    "sg:postcode":"8970",
    "sg:province":"West-Vlaanderen",
    "sg:tags":[
        "lettering",
        "letter"
    ],
    "wof:name":"Italiek",
    "wof:placetype":"venue"
},
  "geometry": {"coordinates":[2.723954916,50.856098175],"type":"Point"}
}