{
  "type": "Feature",
  "properties": {
    "addr:full":"Avenue Des Gloires Nationales 99 Bruxelles (ganshoren) Bruxelles-Capitale 1083",
    "addr:housenumber":"99",
    "addr:postcode":"1083",
    "addr:street":"Avenue Des Gloires Nationales",
    "iso:country":"BE",
    "sg:address":"Avenue Des Gloires Nationales 99",
    "sg:city":"Bruxelles (ganshoren)",
    "sg:classifiers":[
        {
            "category":"Real Estate",
            "subcategory":"Architect",
            "type":"Services"
        }
    ],
    "sg:phone":"+32 2 726 66 21",
    "sg:postcode":"1083",
    "sg:province":"Bruxelles-Capitale",
    "wof:name":"Amiri Lamraski",
    "wof:placetype":"venue"
},
  "geometry": {"coordinates":[4.3159871101,50.8684082031],"type":"Point"}
}