{
  "type": "Feature",
  "properties": {
    "iso:country":"BE",
    "sg:address":"Attenrodestraat 68",
    "sg:city":"Tielt-winge",
    "sg:orig_category":"HUISBRANDOLIE",
    "sg:phone":"+32 16 77 78 47",
    "sg:postcode":"3391",
    "sg:province":"Vlaams-Brabant",
    "wof:name":"De Putter",
    "wof:placetype":"venue"
},
  "geometry": {"coordinates":[4.9243388176,50.8866882324],"type":"Point"}
}