{
  "type": "Feature",
  "properties": {
    "iso:country":"BE",
    "sg:address":"Zegersdreef 83",
    "sg:city":"Brasschaat",
    "sg:orig_category":"DIVERSE RECREATIEVE ACTIVITEITEN",
    "sg:phone":"+32 3 651 38 02",
    "sg:postcode":"2930",
    "sg:province":"Antwerpen",
    "wof:name":"Bridge Club Nobele Donk",
    "wof:placetype":"venue"
},
  "geometry": {"coordinates":[4.4763879776,51.2925567627],"type":"Point"}
}