{
  "type": "Feature",
  "properties": {
    "iso:country":"BE",
    "sg:address":"Richard Vandeveldestraat 139",
    "sg:city":"Schaarbeek/schaerbeek",
    "sg:orig_category":"Krantenwinkels Rookartikelen",
    "sg:phone":"+32 2 216 89 88",
    "sg:postcode":"1030",
    "sg:province":"Bruxelles-Capitale",
    "wof:name":"Librairie Marie Maris",
    "wof:placetype":"venue"
},
  "geometry": {"coordinates":[4.3938961029,50.8718757629],"type":"Point"}
}