{
  "type": "Feature",
  "properties": {
    "addr:full":"Hoogstraat 42 Lokeren Oost-Vlaanderen 9160",
    "addr:housenumber":"42",
    "addr:postcode":"9160",
    "addr:street":"Hoogstraat",
    "iso:country":"BE",
    "sg:address":"Hoogstraat 42",
    "sg:city":"Lokeren",
    "sg:classifiers":[
        {
            "category":"Sports & Exercise",
            "subcategory":"Gym",
            "type":"Entertainment"
        }
    ],
    "sg:phone":"+32 9 348 18 52",
    "sg:postcode":"9160",
    "sg:province":"Oost-Vlaanderen",
    "sg:tags":[
        "fitness"
    ],
    "wof:name":"Hugo's Sportcentrum",
    "wof:placetype":"venue"
},
  "geometry": {"coordinates":[3.9716880322,51.1062965393],"type":"Point"}
}