{
  "type": "Feature",
  "properties": {
    "iso:country":"BE",
    "sg:address":"Assesteenweg 282",
    "sg:city":"Lennik (sint-kwintens-lennik)",
    "sg:classifiers":[
        {
            "category":"Building & Trades",
            "subcategory":"Construction",
            "type":"Services"
        }
    ],
    "sg:phone":"+32 2 582 34 41",
    "sg:postcode":"1750",
    "sg:province":"Vlaams-Brabant",
    "sg:tags":[
        "flue"
    ],
    "wof:name":"Van Assche A",
    "wof:placetype":"venue"
},
  "geometry": {"coordinates":[4.1457290649,50.8378982544],"type":"Point"}
}