{
  "type": "Feature",
  "properties": {
    "iso:country":"BE",
    "sg:address":"Torhoutsestraat 182",
    "sg:city":"Ruddervoorde",
    "sg:classifiers":[
        {
            "category":"Home & Garden",
            "subcategory":"Furniture",
            "type":"Retail Goods"
        }
    ],
    "sg:phone":"+32 50 27 64 56",
    "sg:postcode":"8020",
    "sg:province":"West-Vlaanderen",
    "sg:tags":[
        "household",
        "wood"
    ],
    "wof:name":"Fenestra",
    "wof:placetype":"venue"
},
  "geometry": {"coordinates":[3.1928770542,51.0853691101],"type":"Point"}
}