{
  "type": "Feature",
  "properties": {
    "iso:country":"BE",
    "sg:address":"Rue De Warcoing 4b",
    "sg:city":"Estaimpuis (saint-l\u00e9ger)",
    "sg:classifiers":[
        {
            "category":"Professional",
            "subcategory":"Accounting & Tax Preparation",
            "type":"Services"
        }
    ],
    "sg:phone":"+32 56 48 83 24",
    "sg:postcode":"7730",
    "sg:province":"Hainaut",
    "sg:tags":[
        "bookkeeper"
    ],
    "wof:name":"Wagon J-j",
    "wof:placetype":"venue"
},
  "geometry": {"coordinates":[3.315351963,50.7056427002],"type":"Point"}
}