{
  "type": "Feature",
  "properties": {
    "addr:full":"Bosstraat 24 Merksplas Antwerpen 2330",
    "addr:housenumber":"24",
    "addr:postcode":"2330",
    "addr:street":"Bosstraat",
    "iso:country":"BE",
    "sg:address":"Bosstraat 24",
    "sg:city":"Merksplas",
    "sg:orig_category":"Eleveurs and marchands de porcs",
    "sg:phone":"+32 14 63 34 73",
    "sg:postcode":"2330",
    "sg:province":"Antwerpen",
    "wof:name":"Adrianus Severijns",
    "wof:placetype":"venue"
},
  "geometry": {"coordinates":[4.9136362076,51.3546104431],"type":"Point"}
}