{
  "type": "Feature",
  "properties": {
    "iso:country":"BE",
    "sg:address":"Rue Grande 16",
    "sg:city":"Beloeil (bas\u00e8cles)",
    "sg:classifiers":[
        {
            "category":"Personal",
            "subcategory":"Beauty Salon",
            "type":"Services"
        }
    ],
    "sg:phone":"+32 69 57 60 92",
    "sg:postcode":"7971",
    "sg:province":"Hainaut",
    "sg:tags":[
        "lady",
        "-",
        "hairdressing"
    ],
    "wof:name":"Marilyn Coiff'",
    "wof:placetype":"venue"
},
  "geometry": {"coordinates":[3.6485660076,50.5256843567],"type":"Point"}
}