{
  "type": "Feature",
  "properties": {
    "iso:country":"BE",
    "sg:address":"Rue Du Prince 28",
    "sg:city":"Verviers",
    "sg:orig_category":"Caf\u00e9s Sportclubs Sportterreinen and installaties behalve sportcentra",
    "sg:phone":"+32 87 31 14 47",
    "sg:postcode":"4800",
    "sg:province":"Li\u00e8ge",
    "wof:name":"F.c. Hougnes",
    "wof:placetype":"venue"
},
  "geometry": {"coordinates":[5.8754239082,50.5979347229],"type":"Point"}
}