{
  "type": "Feature",
  "properties": {
    "iso:country":"BE",
    "sg:address":"Kruisstraat 1ba",
    "sg:city":"Ternat",
    "sg:orig_category":"Architecten",
    "sg:phone":"+32 2 582 18 68",
    "sg:postcode":"1740",
    "sg:province":"Vlaams-Brabant",
    "wof:name":"Marguerite Vermeire",
    "wof:placetype":"venue"
},
  "geometry": {"coordinates":[4.1657919884,50.8653144836],"type":"Point"}
}