{
  "type": "Feature",
  "properties": {
    "addr:full":"Rue L\u00e9on Montulet 13 Eghez\u00e9e (saint-germain) Namur 5310",
    "addr:housenumber":"13",
    "addr:postcode":"5310",
    "addr:street":"Rue Le\u0301On Montulet",
    "iso:country":"BE",
    "sg:address":"Rue L\u00e9on Montulet 13",
    "sg:city":"Eghez\u00e9e (saint-germain)",
    "sg:classifiers":[
        {
            "category":"Shopping",
            "subcategory":"Baby Store",
            "type":"Retail Goods"
        }
    ],
    "sg:phone":"+32 81 61 56 01",
    "sg:postcode":"5310",
    "sg:province":"Namur",
    "sg:tags":[
        "midwife"
    ],
    "wof:name":"Georges J",
    "wof:placetype":"venue"
},
  "geometry": {"coordinates":[4.8381538391,50.5689277649],"type":"Point"}
}