{
  "type": "Feature",
  "properties": {
    "addr:full":"Houba De Strooperlaan 23 Brussel/bruxelles Bruxelles-Capitale 1020",
    "addr:housenumber":"23",
    "addr:postcode":"1020",
    "addr:street":"Houba De Strooperlaan;/",
    "iso:country":"BE",
    "sg:address":"Houba De Strooperlaan 23",
    "sg:city":"Brussel/bruxelles",
    "sg:classifiers":[
        {
            "category":"Fast Food",
            "type":"Food & Drink"
        }
    ],
    "sg:phone":"+32 2 476 05 39",
    "sg:postcode":"1020",
    "sg:province":"Bruxelles-Capitale",
    "sg:tags":[
        "voedingsspeciaalzaken",
        "meeneem",
        "restaurant"
    ],
    "wof:name":"Restaurant Wen Chang",
    "wof:placetype":"venue"
},
  "geometry": {"coordinates":[4.3417692184,50.8864517212],"type":"Point"}
}