{
  "type": "Feature",
  "properties": {
    "iso:country":"BE",
    "sg:address":"Koninklijkestraat 16",
    "sg:city":"Kortrijk",
    "sg:orig_category":"Dierenartsen",
    "sg:phone":"+32 56 45 74 56",
    "sg:postcode":"8510",
    "sg:province":"West-Vlaanderen",
    "wof:name":"Bjorn Roelens",
    "wof:placetype":"venue"
},
  "geometry": {"coordinates":[3.330051899,50.7390022278],"type":"Point"}
}