{
  "type": "Feature",
  "properties": {
    "addr:full":"Koophandelsplein 31 Gent Oost-Vlaanderen 9000",
    "addr:housenumber":"31",
    "addr:postcode":"9000",
    "addr:street":"Koophandelsplein;Oost-Vlaanderen",
    "iso:country":"BE",
    "sg:address":"Koophandelsplein 31",
    "sg:city":"Gent",
    "sg:orig_category":"Blanchisseries and teintureries",
    "sg:phone":"+32 9 223 51 48",
    "sg:postcode":"9000",
    "sg:province":"Oost-Vlaanderen",
    "wof:name":"Press Shop",
    "wof:placetype":"venue"
},
  "geometry": {"coordinates":[3.7211689949,51.0494689941],"type":"Point"}
}