{
  "type": "Feature",
  "properties": {
    "addr:full":"Eigenlostraat 29 Sint-niklaas Oost-Vlaanderen 9100",
    "addr:housenumber":"29",
    "addr:postcode":"9100",
    "addr:street":"Eigenlostraat",
    "iso:country":"BE",
    "sg:address":"Eigenlostraat 29",
    "sg:city":"Sint-niklaas",
    "sg:classifiers":[
        {
            "category":"Building & Trades",
            "subcategory":"Construction",
            "type":"Services"
        }
    ],
    "sg:phone":"+32 3 777 15 35",
    "sg:postcode":"9100",
    "sg:province":"Oost-Vlaanderen",
    "sg:tags":[
        "carpenter"
    ],
    "wof:name":"Ramovit Bvba",
    "wof:placetype":"venue"
},
  "geometry": {"coordinates":[4.1843152046,51.1484603882],"type":"Point"}
}