{
  "type": "Feature",
  "properties": {
    "iso:country":"BE",
    "sg:address":"Citadelpark 1",
    "sg:city":"Gent",
    "sg:orig_category":"Musea and historische gebouwen",
    "sg:phone":"+32 9 222 17 03",
    "sg:postcode":"9000",
    "sg:province":"Oost-Vlaanderen",
    "wof:name":"Museum Voor Schone Kunsten",
    "wof:placetype":"venue"
},
  "geometry": {"coordinates":[3.7262899876,51.0386314392],"type":"Point"}
}