{
  "type": "Feature",
  "properties": {
    "addr:full":"Oude Stationstraat 8 Tielt West-Vlaanderen 8700",
    "addr:housenumber":"8",
    "addr:postcode":"8700",
    "addr:street":"Oude Stationstraat",
    "iso:country":"BE",
    "sg:address":"Oude Stationstraat 8",
    "sg:city":"Tielt",
    "sg:orig_category":"Verplichte sociale verzekeringen",
    "sg:phone":"+32 51 42 38 00",
    "sg:postcode":"8700",
    "sg:province":"West-Vlaanderen",
    "wof:name":"Christelijke Mutualiteit",
    "wof:placetype":"venue"
},
  "geometry": {"coordinates":[3.3263840675,50.9955444336],"type":"Point"}
}