{
  "type": "Feature",
  "properties": {
    "addr:full":"Basse-comm\u00c8ne 2 Durbuy Luxembourg 6940",
    "addr:housenumber":"2",
    "addr:postcode":"6940",
    "addr:street":"Basse-Comme\u0300Ne",
    "iso:country":"BE",
    "sg:address":"Basse-comm\u00c8ne 2",
    "sg:city":"Durbuy",
    "sg:orig_category":"Enseignement maternel and primaire",
    "sg:phone":"+32 86 21 28 05",
    "sg:postcode":"6940",
    "sg:province":"Luxembourg",
    "wof:name":"Ecole Fond. Communale",
    "wof:placetype":"venue"
},
  "geometry": {"coordinates":[5.4942131042,50.3534660339],"type":"Point"}
}