{
  "type": "Feature",
  "properties": {
    "iso:country":"BE",
    "sg:address":"Velveken 25",
    "sg:city":"Geel",
    "sg:orig_category":"Epiceries",
    "sg:phone":"+32 14 58 49 54",
    "sg:postcode":"2440",
    "sg:province":"Antwerpen",
    "wof:name":"Olga Goor",
    "wof:placetype":"venue"
},
  "geometry": {"coordinates":[4.9434571266,51.1614227295],"type":"Point"}
}