{
  "type": "Feature",
  "properties": {
    "addr:full":"Route De Ramillies 6 Eghezee Namur 5310",
    "addr:housenumber":"6",
    "addr:postcode":"5310",
    "addr:street":"Route De Ramillies;Namur",
    "iso:country":"BE",
    "sg:address":"Route De Ramillies 6",
    "sg:city":"Eghezee",
    "sg:orig_category":"Benzinestations and brandstoffen",
    "sg:phone":"+32 81 81 15 08",
    "sg:postcode":"5310",
    "sg:province":"Namur",
    "wof:name":"Finaflam And Partners",
    "wof:placetype":"venue"
},
  "geometry": {"coordinates":[4.9129528999,50.5924682617],"type":"Point"}
}