{
  "type": "Feature",
  "properties": {
    "iso:country":"BE",
    "sg:address":"Meerstraat 34",
    "sg:city":"Waregem",
    "sg:orig_category":"Banques and organismes de cr\u00e9dit",
    "sg:phone":"+32 56 60 30 91",
    "sg:postcode":"8790",
    "sg:province":"West-Vlaanderen",
    "wof:name":"Mercator Bank",
    "wof:placetype":"venue"
},
  "geometry": {"coordinates":[3.4291489124,50.8850898743],"type":"Point"}
}