{
  "type": "Feature",
  "properties": {
    "addr:full":"Rijselsestraat 53 Kortrijk West-Vlaanderen 8500",
    "addr:housenumber":"53",
    "addr:postcode":"8500",
    "addr:street":"Rijselsestraat",
    "iso:country":"BE",
    "sg:address":"Rijselsestraat 53",
    "sg:city":"Kortrijk",
    "sg:orig_category":"Evaluation and estimation de biens immobiliers. Assurances",
    "sg:phone":"+32 56 21 30 60",
    "sg:postcode":"8500",
    "sg:province":"West-Vlaanderen",
    "wof:name":"Patrick Bevernage",
    "wof:placetype":"venue"
},
  "geometry": {"coordinates":[3.2619919777,50.8271522522],"type":"Point"}
}