{
  "type": "Feature",
  "properties": {
    "addr:full":"Rue De La Madeleine 41 Tournai Hainaut 7500",
    "addr:housenumber":"41",
    "addr:postcode":"7500",
    "addr:street":"Rue De La Madeleine",
    "iso:country":"BE",
    "sg:address":"Rue De La Madeleine 41",
    "sg:city":"Tournai",
    "sg:classifiers":[
        {
            "category":"Shopping",
            "subcategory":"Computers & Home Electronics",
            "type":"Retail Goods"
        }
    ],
    "sg:phone":"+32 69 22 23 30",
    "sg:postcode":"7500",
    "sg:province":"Hainaut",
    "sg:tags":[
        "-",
        "television",
        "radio"
    ],
    "wof:name":"Futura",
    "wof:placetype":"venue"
},
  "geometry": {"coordinates":[3.3822491169,50.6103401184],"type":"Point"}
}