{
  "type": "Feature",
  "properties": {
    "addr:full":"Boshuisweg 2 Zoersel Antwerpen 2980",
    "addr:housenumber":"2",
    "addr:postcode":"2980",
    "addr:street":"Boshuisweg",
    "iso:country":"BE",
    "sg:address":"Boshuisweg 2",
    "sg:city":"Zoersel",
    "sg:classifiers":[
        {
            "category":"Organizations",
            "subcategory":"Community Association",
            "type":"Services"
        }
    ],
    "sg:phone":"+32 3 384 05 12",
    "sg:postcode":"2980",
    "sg:province":"Antwerpen",
    "sg:tags":[
        "environment",
        "organisation",
        "-"
    ],
    "wof:name":"Bezoekerscentrum Zoerselbos",
    "wof:placetype":"venue"
},
  "geometry": {"coordinates":[4.6760468483,51.2433433533],"type":"Point"}
}