{
  "type": "Feature",
  "properties": {
    "iso:country":"BE",
    "sg:address":"Kapellekensstraat 2",
    "sg:city":"Olen",
    "sg:orig_category":"Boucheries",
    "sg:phone":"+32 14 21 12 95",
    "sg:postcode":"2250",
    "sg:province":"Antwerpen",
    "wof:name":"Tony Verberne",
    "wof:placetype":"venue"
},
  "geometry": {"coordinates":[4.8987689018,51.1783714294],"type":"Point"}
}