{
  "type": "Feature",
  "properties": {
    "addr:full":"Schom 49 Zemst Vlaams-Brabant 1980",
    "addr:housenumber":"49",
    "addr:postcode":"1980",
    "addr:street":"Schom;Vlaams-Brabant",
    "iso:country":"BE",
    "sg:address":"Schom 49",
    "sg:city":"Zemst",
    "sg:classifiers":[
        {
            "category":"Professional",
            "subcategory":"Management & Consulting",
            "type":"Services"
        }
    ],
    "sg:phone":"+32 15 61 63 59",
    "sg:postcode":"1980",
    "sg:province":"Vlaams-Brabant",
    "sg:tags":[
        "consultant",
        "promotion",
        "-",
        "sale"
    ],
    "wof:name":"Btb Consult Bvba",
    "wof:placetype":"venue"
},
  "geometry": {"coordinates":[4.4645547867,50.9849433899],"type":"Point"}
}