{
  "type": "Feature",
  "properties": {
    "addr:full":"Chauss\u00e9e De Lannoy 22 Tournai (froyennes) Hainaut 7503",
    "addr:housenumber":"22",
    "addr:postcode":"7503",
    "addr:street":"Chausse\u0301E De Lannoy",
    "iso:country":"BE",
    "sg:address":"Chauss\u00e9e De Lannoy 22",
    "sg:city":"Tournai (froyennes)",
    "sg:classifiers":[
        {
            "category":"Personal",
            "subcategory":"Beauty Salon",
            "type":"Services"
        }
    ],
    "sg:phone":"+32 69 22 83 72",
    "sg:postcode":"7503",
    "sg:province":"Hainaut",
    "wof:name":"France-beaute",
    "wof:placetype":"venue"
},
  "geometry": {"coordinates":[3.3606441021,50.6192512512],"type":"Point"}
}