{
  "type": "Feature",
  "properties": {
    "addr:full":"Persoonstraat 18 Geetbets (rummen) Vlaams-Brabant 3454",
    "addr:housenumber":"18",
    "addr:postcode":"3454",
    "addr:street":"Persoonstraat",
    "iso:country":"BE",
    "sg:address":"Persoonstraat 18",
    "sg:city":"Geetbets (rummen)",
    "sg:orig_category":"Non-Classified Establishments",
    "sg:phone":"+32 11 58 60 80",
    "sg:postcode":"3454",
    "sg:province":"Vlaams-Brabant",
    "wof:name":"Sane Bvba",
    "wof:placetype":"venue"
},
  "geometry": {"coordinates":[5.1656899452,50.8911514282],"type":"Point"}
}