{
  "type": "Feature",
  "properties": {
    "addr:full":"Mechelsesteenweg 122 Sint-katelijne-waver Antwerpen 2860",
    "addr:housenumber":"122",
    "addr:postcode":"2860",
    "addr:street":"Mechelsesteenweg",
    "iso:country":"BE",
    "sg:address":"Mechelsesteenweg 122",
    "sg:city":"Sint-katelijne-waver",
    "sg:orig_category":"Kunststofrecipi\u00ebnten and -verpakkingen Fab",
    "sg:phone":"+32 15 55 68 10",
    "sg:postcode":"2860",
    "sg:province":"Antwerpen",
    "wof:name":"L.c. Packaging",
    "wof:placetype":"venue"
},
  "geometry": {"coordinates":[4.5246901512,51.0563774109],"type":"Point"}
}