{
  "type": "Feature",
  "properties": {
    "addr:full":"Avenue Du Port 100 Bruxelles Bruxelles-Capitale 1000",
    "addr:housenumber":"100",
    "addr:postcode":"1000",
    "addr:street":"Avenue Du Port",
    "iso:country":"BE",
    "sg:address":"Avenue Du Port 100",
    "sg:city":"Bruxelles",
    "sg:classifiers":[
        {
            "category":"Railroad",
            "type":"Transportation"
        }
    ],
    "sg:phone":"+32 2 421 12 11",
    "sg:postcode":"1000",
    "sg:province":"Bruxelles-Capitale",
    "sg:tags":[
        "-",
        "combined",
        "transport"
    ],
    "wof:name":"T.r.w.",
    "wof:placetype":"venue"
},
  "geometry": {"coordinates":[4.3521609306,50.8675994873],"type":"Point"}
}