{
  "type": "Feature",
  "properties": {
    "addr:full":"Rue Xhrouet 43 Spa Li\u00e8ge 4900",
    "addr:housenumber":"43",
    "addr:postcode":"4900",
    "addr:street":"Rue Xhrouet",
    "iso:country":"BE",
    "sg:address":"Rue Xhrouet 43",
    "sg:city":"Spa",
    "sg:orig_category":"Advocaten and juridische adviseurs",
    "sg:phone":"+32 87 77 22 53",
    "sg:postcode":"4900",
    "sg:province":"Li\u00e8ge",
    "wof:name":"M. Ossena-cantara",
    "wof:placetype":"venue"
},
  "geometry": {"coordinates":[5.8679847717,50.4911193848],"type":"Point"}
}