{
  "type": "Feature",
  "properties": {
    "addr:full":"Bloemendalestraat 137 Beernem West-Vlaanderen 8730",
    "addr:housenumber":"137",
    "addr:postcode":"8730",
    "addr:street":"Bloemendalestraat",
    "iso:country":"BE",
    "sg:address":"Bloemendalestraat 137",
    "sg:city":"Beernem",
    "sg:orig_category":"Boucheries",
    "sg:phone":"+32 50 78 10 31",
    "sg:postcode":"8730",
    "sg:province":"West-Vlaanderen",
    "wof:name":"Slagerij Patrick",
    "wof:placetype":"venue"
},
  "geometry": {"coordinates":[3.33228302,51.1392707825],"type":"Point"}
}