{
  "type": "Feature",
  "properties": {
    "iso:country":"BE",
    "sg:address":"Rue Du Poncia 12",
    "sg:city":"Gembloux",
    "sg:orig_category":"Boissons",
    "sg:phone":"+32 81 61 29 79",
    "sg:postcode":"5030",
    "sg:province":"Namur",
    "wof:name":"Daniel Mary",
    "wof:placetype":"venue"
},
  "geometry": {"coordinates":[4.6795840263,50.5573005676],"type":"Point"}
}