{
  "type": "Feature",
  "properties": {
    "addr:full":"Chauss\u00c9e De Charleroi 17 Lasne Brabant Wallon 1380",
    "addr:housenumber":"17",
    "addr:postcode":"1380",
    "addr:street":"Chausse\u0301E De Charleroi",
    "iso:country":"BE",
    "sg:address":"Chauss\u00c9e De Charleroi 17",
    "sg:city":"Lasne",
    "sg:classifiers":[
        {
            "category":"Autos & Motor Vehicles",
            "subcategory":"Fuel & Gas Station",
            "type":"Retail Goods"
        }
    ],
    "sg:phone":"+32 2 384 54 91",
    "sg:postcode":"1380",
    "sg:province":"Brabant Wallon",
    "sg:tags":[
        "stations-service",
        "carburants"
    ],
    "wof:name":"Fina",
    "wof:placetype":"venue"
},
  "geometry": {"coordinates":[4.4135489464,50.6614532471],"type":"Point"}
}