{
  "type": "Feature",
  "properties": {
    "iso:country":"BE",
    "sg:address":"Kloosterstraat 2",
    "sg:city":"Zedelgem",
    "sg:orig_category":"Enseignement maternel and primaire",
    "sg:phone":"+32 50 27 62 12",
    "sg:postcode":"8210",
    "sg:province":"West-Vlaanderen",
    "wof:name":"Vrije Basisschool",
    "wof:placetype":"venue"
},
  "geometry": {"coordinates":[3.1458399296,51.1376457214],"type":"Point"}
}