{
  "type": "Feature",
  "properties": {
    "addr:full":"Lessensestraat 71 Geraardsbergen Oost-Vlaanderen 9500",
    "addr:housenumber":"71",
    "addr:postcode":"9500",
    "addr:street":"Lessensestraat",
    "iso:country":"BE",
    "sg:address":"Lessensestraat 71",
    "sg:city":"Geraardsbergen",
    "sg:classifiers":[
        {
            "category":"Food & Beverages",
            "subcategory":"Fruits & Vegetables",
            "type":"Retail Goods"
        }
    ],
    "sg:phone":"+32 54 41 40 25",
    "sg:postcode":"9500",
    "sg:province":"Oost-Vlaanderen",
    "sg:tags":[
        "-"
    ],
    "wof:name":"Limoentje ('t)",
    "wof:placetype":"venue"
},
  "geometry": {"coordinates":[3.8742671013,50.7697296143],"type":"Point"}
}