{
  "type": "Feature",
  "properties": {
    "addr:full":"Rue Belle Vue 7 Fontaine-l'ev\u00eaque (forchies-la-marche) Hainaut 6141",
    "addr:housenumber":"7",
    "addr:postcode":"6141",
    "addr:street":"Rue Belle Vue;Hainaut",
    "iso:country":"BE",
    "sg:address":"Rue Belle Vue 7",
    "sg:city":"Fontaine-l'ev\u00eaque (forchies-la-marche)",
    "sg:classifiers":[
        {
            "category":"Wholesale",
            "subcategory":"Wine & Distilled Alcoholic Beverages",
            "type":"Manufacturing & Wholesale Goods"
        }
    ],
    "sg:phone":"+32 71 52 30 55",
    "sg:postcode":"6141",
    "sg:province":"Hainaut",
    "sg:tags":[
        "whol",
        "-",
        "spirit",
        "mfg"
    ],
    "wof:name":"Bailly M",
    "wof:placetype":"venue"
},
  "geometry": {"coordinates":[-75.60595703120001,37.7877616882],"type":"Point"}
}