{
  "type": "Feature",
  "properties": {
    "addr:full":"Eikenstraat 202 Rumst Antwerpen 2840",
    "addr:housenumber":"202",
    "addr:postcode":"2840",
    "addr:street":"Eikenstraat",
    "iso:country":"BE",
    "sg:address":"Eikenstraat 202",
    "sg:city":"Rumst",
    "sg:orig_category":"Producteurs de l\u00e9gumes",
    "sg:phone":"+32 3 888 68 55",
    "sg:postcode":"2840",
    "sg:province":"Antwerpen",
    "wof:name":"Leo Rynders",
    "wof:placetype":"venue"
},
  "geometry": {"coordinates":[4.4064440727,51.1141738892],"type":"Point"}
}