{
  "type": "Feature",
  "properties": {
    "iso:country":"BE",
    "sg:address":"Gentsesteenweg 138",
    "sg:city":"Zele",
    "sg:classifiers":[
        {
            "category":"Bars & Pubs",
            "type":"Food & Drink"
        }
    ],
    "sg:phone":"+32 52 45 32 91",
    "sg:postcode":"9240",
    "sg:province":"Oost-Vlaanderen",
    "wof:name":"De Veurleste",
    "wof:placetype":"venue"
},
  "geometry": {"coordinates":[4.0196938515,51.0593261719],"type":"Point"}
}