{
  "type": "Feature",
  "properties": {
    "addr:full":"Sentier De La Bruy\u00c8re 8 Ittre Brabant Wallon 1461",
    "addr:housenumber":"8;1461",
    "addr:street":"Sentier De La Bruye\u0300Re",
    "iso:country":"BE",
    "sg:address":"Sentier De La Bruy\u00c8re 8",
    "sg:city":"Ittre",
    "sg:orig_category":"Woningbouw",
    "sg:phone":"+32 2 366 09 48",
    "sg:postcode":"1461",
    "sg:province":"Brabant Wallon",
    "wof:name":"Smb",
    "wof:placetype":"venue"
},
  "geometry": {"coordinates":[4.290749073,50.6645584106],"type":"Point"}
}