{
  "type": "Feature",
  "properties": {
    "addr:full":"Rue De Genleau 6a Lasne Brabant Wallon 1380",
    "addr:housenumber":"6a",
    "addr:postcode":"1380",
    "addr:street":"Rue De Genleau",
    "iso:country":"BE",
    "sg:address":"Rue De Genleau 6a",
    "sg:city":"Lasne",
    "sg:orig_category":"Notarissen",
    "sg:phone":"+32 2 633 51 97",
    "sg:postcode":"1380",
    "sg:province":"Brabant Wallon",
    "wof:name":"Beno\u00cet Le Maire",
    "wof:placetype":"venue"
},
  "geometry": {"coordinates":[4.4818711281,50.6851119995],"type":"Point"}
}