{
  "type": "Feature",
  "properties": {
    "iso:country":"BE",
    "sg:address":"Monseigneur De Haernelaan 31",
    "sg:city":"Kortrijk",
    "sg:classifiers":[
        {
            "category":"Professional",
            "subcategory":"Art Services",
            "type":"Services"
        }
    ],
    "sg:phone":"+32 56 22 02 86",
    "sg:postcode":"8500",
    "sg:province":"West-Vlaanderen",
    "sg:tags":[
        "-",
        "painter",
        "artist"
    ],
    "wof:name":"Windels N",
    "wof:placetype":"venue"
},
  "geometry": {"coordinates":[3.2594790459,50.8214874268],"type":"Point"}
}