{
  "type": "Feature",
  "properties": {
    "addr:full":"Place D'hertain 8b Blandain - Hertain Hainaut 7522",
    "addr:housenumber":"8b",
    "addr:postcode":"7522",
    "addr:street":"Place D'Hertain;Hertain Hainaut",
    "iso:country":"BE",
    "sg:address":"Place D'hertain 8b",
    "sg:city":"Blandain - Hertain",
    "sg:classifiers":[
        {
            "category":"Health Services",
            "subcategory":"Health Practitioner",
            "type":"Services"
        }
    ],
    "sg:phone":"+32 69 84 04 86",
    "sg:postcode":"7522",
    "sg:province":"Hainaut",
    "sg:tags":[
        "physiotherapist"
    ],
    "wof:name":"Macquet Cyprien",
    "wof:placetype":"venue"
},
  "geometry": {"coordinates":[3.288654089,50.6135292053],"type":"Point"}
}