{
  "type": "Feature",
  "properties": {
    "iso:country":"BE",
    "sg:address":"Vrijweide 24",
    "sg:city":"Bilzen",
    "sg:orig_category":"Dakwerken Loodgieterij, verwarming and sanitaire installaties",
    "sg:phone":"+32 89 41 69 28",
    "sg:postcode":"3740",
    "sg:province":"Limburg",
    "wof:name":"Gilbert Steegen",
    "wof:placetype":"venue"
},
  "geometry": {"coordinates":[5.5076999664,50.8958854675],"type":"Point"}
}