{
  "type": "Feature",
  "properties": {
    "addr:full":"Rue De Grammont 98 Ronse/renaix Oost-Vlaanderen 9600",
    "addr:housenumber":"98",
    "addr:postcode":"9600",
    "addr:street":"Rue De Grammont",
    "iso:country":"BE",
    "sg:address":"Rue De Grammont 98",
    "sg:city":"Ronse/renaix",
    "sg:classifiers":[
        {
            "category":"Insurance",
            "subcategory":"Life Insurance",
            "type":"Services"
        }
    ],
    "sg:phone":"+32 55 20 90 96",
    "sg:postcode":"9600",
    "sg:province":"Oost-Vlaanderen",
    "sg:tags":[
        "assurance"
    ],
    "wof:name":"Bureau Dekegeleer",
    "wof:placetype":"venue"
},
  "geometry": {"coordinates":[3.6212151051,50.7496795654],"type":"Point"}
}