{
  "type": "Feature",
  "properties": {
    "iso:country":"BE",
    "sg:address":"Dorp 12b2",
    "sg:city":"Lovendegem",
    "sg:orig_category":"Bloemen and planten",
    "sg:phone":"+32 9 372 00 24",
    "sg:postcode":"9920",
    "sg:province":"Oost-Vlaanderen",
    "wof:name":"Rene Hoste",
    "wof:placetype":"venue"
},
  "geometry": {"coordinates":[3.6065409184,51.0956573486],"type":"Point"}
}