{
  "type": "Feature",
  "properties": {
    "addr:full":"Wallemolenstraat 1 Zonnebeke West-Vlaanderen 8980",
    "addr:housenumber":"1",
    "addr:postcode":"8980",
    "addr:street":"Wallemolenstraat",
    "iso:country":"BE",
    "sg:address":"Wallemolenstraat 1",
    "sg:city":"Zonnebeke",
    "sg:orig_category":"Varkenskwekers",
    "sg:phone":"+32 51 77 79 73",
    "sg:postcode":"8980",
    "sg:province":"West-Vlaanderen",
    "wof:name":"Willy Cardoen",
    "wof:placetype":"venue"
},
  "geometry": {"coordinates":[2.9872550964,50.8730812073],"type":"Point"}
}