{
  "type": "Feature",
  "properties": {
    "iso:country":"BE",
    "sg:address":"Kattespoelstraat 7",
    "sg:city":"Beerse",
    "sg:classifiers":[
        {
            "category":"Real Estate",
            "subcategory":"Surveying",
            "type":"Services"
        }
    ],
    "sg:phone":"+32 14 61 05 04",
    "sg:postcode":"2340",
    "sg:province":"Antwerpen",
    "sg:tags":[
        "lettering",
        "letter"
    ],
    "wof:name":"Color It",
    "wof:placetype":"venue"
},
  "geometry": {"coordinates":[4.8692631721,51.3193740845],"type":"Point"}
}