{
  "type": "Feature",
  "properties": {
    "addr:full":"Statiestraat 28 Aarschot Vlaams-Brabant 3200",
    "addr:housenumber":"28",
    "addr:postcode":"3200",
    "addr:street":"Statiestraat",
    "iso:country":"BE",
    "sg:address":"Statiestraat 28",
    "sg:city":"Aarschot",
    "sg:orig_category":"Dameskledingzaken",
    "sg:phone":"+32 16 56 73 30",
    "sg:postcode":"3200",
    "sg:province":"Vlaams-Brabant",
    "wof:name":"In Het Wevenitekorfje",
    "wof:placetype":"venue"
},
  "geometry": {"coordinates":[4.825881958,50.9848823547],"type":"Point"}
}