{
  "type": "Feature",
  "properties": {
    "iso:country":"BE",
    "sg:address":"Gijmelbergstraat 40",
    "sg:city":"Aarschot",
    "sg:classifiers":[
        {
            "category":"Manufacturing",
            "subcategory":"Textiles",
            "type":"Manufacturing & Wholesale Goods"
        }
    ],
    "sg:phone":"+32 16 56 46 23",
    "sg:postcode":"3201",
    "sg:province":"Vlaams-Brabant",
    "wof:name":"Wouters",
    "wof:placetype":"venue"
},
  "geometry": {"coordinates":[4.8477611542,51.0079841614],"type":"Point"}
}