{
  "type": "Feature",
  "properties": {
    "iso:country":"BE",
    "sg:address":"Markt 26",
    "sg:city":"Herenthout",
    "sg:orig_category":"V\u00eatements. Textiles",
    "sg:phone":"+32 14 51 26 26",
    "sg:postcode":"2270",
    "sg:province":"Antwerpen",
    "wof:name":"Phildar",
    "wof:placetype":"venue"
},
  "geometry": {"coordinates":[4.7563581467,51.1392440796],"type":"Point"}
}