{
  "type": "Feature",
  "properties": {
    "addr:full":"Sint-michielskaai 26 Antwerpen Antwerpen 2000",
    "addr:housenumber":"26",
    "addr:postcode":"2000",
    "addr:street":"Sint-Michielskaai",
    "iso:country":"BE",
    "sg:address":"Sint-michielskaai 26",
    "sg:city":"Antwerpen",
    "sg:classifiers":[
        {
            "category":"Professional",
            "subcategory":"Art Services",
            "type":"Services"
        }
    ],
    "sg:phone":"+32 3 257 34 34",
    "sg:postcode":"2000",
    "sg:province":"Antwerpen",
    "sg:tags":[
        "photographer"
    ],
    "wof:name":"Shoot To Kill Studios",
    "wof:placetype":"venue"
},
  "geometry": {"coordinates":[4.3924069405,51.2144050598],"type":"Point"}
}