{
  "type": "Feature",
  "properties": {
    "addr:full":"Steenweg Deinze 101 Nazareth Oost-Vlaanderen 9810",
    "addr:housenumber":"101",
    "addr:postcode":"9810",
    "addr:street":"Steenweg Deinze",
    "iso:country":"BE",
    "sg:address":"Steenweg Deinze 101",
    "sg:city":"Nazareth",
    "sg:classifiers":[
        {
            "category":"Building & Trades",
            "subcategory":"Plumbing",
            "type":"Services"
        }
    ],
    "sg:phone":"+32 9 384 47 67",
    "sg:postcode":"9810",
    "sg:province":"Oost-Vlaanderen",
    "sg:tags":[
        "pipe",
        "drain",
        "unblocking"
    ],
    "wof:name":"Van Parys Ruimdienst",
    "wof:placetype":"venue"
},
  "geometry": {"coordinates":[3.5875160694,50.9447212219],"type":"Point"}
}