{
  "type": "Feature",
  "properties": {
    "addr:full":"Rue Capitaine Gilles 10 Awans Li\u00e8ge 4340",
    "addr:housenumber":"10",
    "addr:postcode":"4340",
    "addr:street":"Rue Capitaine Gilles",
    "iso:country":"BE",
    "sg:address":"Rue Capitaine Gilles 10",
    "sg:city":"Awans",
    "sg:classifiers":[
        {
            "category":"Health Services",
            "subcategory":"Health Practitioner",
            "type":"Services"
        }
    ],
    "sg:phone":"+32 4 246 30 04",
    "sg:postcode":"4340",
    "sg:province":"Li\u00e8ge",
    "sg:tags":[
        "physiotherapist"
    ],
    "wof:name":"Bernard C",
    "wof:placetype":"venue"
},
  "geometry": {"coordinates":[5.4620018005,50.663772583],"type":"Point"}
}