{
  "type": "Feature",
  "properties": {
    "iso:country":"BE",
    "sg:address":"Rue Des Alouettes 5",
    "sg:city":"Oupeye (herm\u00e9e)",
    "sg:classifiers":[
        {
            "category":"Structure",
            "subcategory":"Office Building",
            "type":"Public Place"
        }
    ],
    "sg:phone":"+32 4 278 44 25",
    "sg:postcode":"4680",
    "sg:province":"Li\u00e8ge",
    "sg:tags":[
        "drawing"
    ],
    "wof:name":"Masson L",
    "wof:placetype":"venue"
},
  "geometry": {"coordinates":[5.6217441559,50.7032394409],"type":"Point"}
}