{
  "type": "Feature",
  "properties": {
    "iso:country":"BE",
    "sg:address":"Dorpsplein 10",
    "sg:city":"Tervuren (vossem)",
    "sg:orig_category":"Non-Classified Establishments",
    "sg:phone":"+32 2 767 35 60",
    "sg:postcode":"3080",
    "sg:province":"Vlaams-Brabant",
    "wof:name":"Kumps Agro Bvba",
    "wof:placetype":"venue"
},
  "geometry": {"coordinates":[4.5584859848,50.8350639343],"type":"Point"}
}