{
  "type": "Feature",
  "properties": {
    "addr:full":"Schoterheide 26 Tessenderlo Limburg 3980",
    "addr:housenumber":"26",
    "addr:postcode":"3980",
    "addr:street":"Schoterheide",
    "iso:country":"BE",
    "sg:address":"Schoterheide 26",
    "sg:city":"Tessenderlo",
    "sg:classifiers":[
        {
            "category":"Food & Beverages",
            "subcategory":"Liquor & Beverages",
            "type":"Retail Goods"
        }
    ],
    "sg:phone":"+32 13 67 67 20",
    "sg:postcode":"3980",
    "sg:province":"Limburg",
    "sg:tags":[
        "-",
        "spirit",
        "wine"
    ],
    "wof:name":"Euro-vin",
    "wof:placetype":"venue"
},
  "geometry": {"coordinates":[5.013217926,51.0591392517],"type":"Point"}
}