{
  "type": "Feature",
  "properties": {
    "addr:full":"Daverlostraat 315 Brugge West-Vlaanderen 8310",
    "addr:housenumber":"315",
    "addr:postcode":"8310",
    "addr:street":"Daverlostraat",
    "iso:country":"BE",
    "sg:address":"Daverlostraat 315",
    "sg:city":"Brugge",
    "sg:orig_category":"Paramedische behandelingen",
    "sg:phone":"+32 50 37 50 58",
    "sg:postcode":"8310",
    "sg:province":"West-Vlaanderen",
    "wof:name":"Rik Maene",
    "wof:placetype":"venue"
},
  "geometry": {"coordinates":[3.2486739159,51.1945991516],"type":"Point"}
}