{
  "type": "Feature",
  "properties": {
    "iso:country":"BE",
    "sg:address":"Stationstraat 34",
    "sg:city":"Lokeren",
    "sg:classifiers":[
        {
            "category":"Government",
            "subcategory":"Fire Station",
            "type":"Public Place"
        }
    ],
    "sg:phone":"+32 9 348 31 00",
    "sg:postcode":"9160",
    "sg:province":"Oost-Vlaanderen",
    "sg:tags":[
        "packard",
        "nec",
        "bell"
    ],
    "wof:name":"Ac & T Lokeren",
    "wof:placetype":"venue"
},
  "geometry": {"coordinates":[3.9871060848,51.1065864563],"type":"Point"}
}