{
  "type": "Feature",
  "properties": {
    "addr:full":"Rue Fabry 42 Sint-lambrechts-woluwe/woluwe-saint-lambert Bruxelles-Capitale 1200",
    "addr:housenumber":"42",
    "addr:postcode":"1200",
    "addr:street":"Rue Fabry",
    "iso:country":"BE",
    "sg:address":"Rue Fabry 42",
    "sg:city":"Sint-lambrechts-woluwe/woluwe-saint-lambert",
    "sg:orig_category":"Cr\u00e8ches and garderies d'enfants",
    "sg:phone":"+32 2 762 20 97",
    "sg:postcode":"1200",
    "sg:province":"Bruxelles-Capitale",
    "wof:name":"Cr\u00c8che Petite Esperance",
    "wof:placetype":"venue"
},
  "geometry": {"coordinates":[4.4369931221,50.8385238647],"type":"Point"}
}