{
  "type": "Feature",
  "properties": {
    "iso:country":"BE",
    "sg:address":"Brugsevaart 50",
    "sg:city":"Gent (mariakerke)",
    "sg:classifiers":[
        {
            "category":"Health Services",
            "subcategory":"Nursing And Care Facility",
            "type":"Services"
        }
    ],
    "sg:phone":"+32 9 227 05 48",
    "sg:postcode":"9030",
    "sg:province":"Oost-Vlaanderen",
    "sg:tags":[
        "home"
    ],
    "wof:name":"Haeck M",
    "wof:placetype":"venue"
},
  "geometry": {"coordinates":[3.6795139313,51.0774459839],"type":"Point"}
}