{
  "type": "Feature",
  "properties": {
    "addr:full":"Klein Schrijnbroekstraat 89 Hasselt Limburg 3500",
    "addr:housenumber":"89",
    "addr:postcode":"3500",
    "addr:street":"Klein Schrijnbroekstraat",
    "iso:country":"BE",
    "sg:address":"Klein Schrijnbroekstraat 89",
    "sg:city":"Hasselt",
    "sg:classifiers":[
        {
            "category":"Arts & Performance",
            "subcategory":"Music",
            "type":"Entertainment"
        }
    ],
    "sg:phone":"+32 474 99 78 27",
    "sg:postcode":"3500",
    "sg:province":"Limburg",
    "sg:tags":[
        "freelance",
        "musician"
    ],
    "wof:name":"The Pianist",
    "wof:placetype":"venue"
},
  "geometry": {"coordinates":[5.3498821259,50.9521942139],"type":"Point"}
}