{
  "type": "Feature",
  "properties": {
    "iso:country":"BE",
    "sg:address":"Ambachtsstraat 5",
    "sg:city":"Mol",
    "sg:classifiers":[
        {
            "category":"Food & Beverages",
            "subcategory":"Fruits & Vegetables",
            "type":"Retail Goods"
        }
    ],
    "sg:phone":"+32 14 31 78 11",
    "sg:postcode":"2400",
    "sg:province":"Antwerpen",
    "sg:tags":[
        "dried"
    ],
    "wof:name":"Jan Gevers Bvba",
    "wof:placetype":"venue"
},
  "geometry": {"coordinates":[5.1005911827,51.190788269],"type":"Point"}
}