{
  "type": "Feature",
  "properties": {
    "addr:full":"Wakkensesteenweg 40 Tielt West-Vlaanderen 8700",
    "addr:housenumber":"40",
    "addr:postcode":"8700",
    "addr:street":"Wakkensesteenweg",
    "iso:country":"BE",
    "sg:address":"Wakkensesteenweg 40",
    "sg:city":"Tielt",
    "sg:orig_category":"Eleveurs and marchands de porcs",
    "sg:phone":"+32 51 40 73 96",
    "sg:postcode":"8700",
    "sg:province":"West-Vlaanderen",
    "wof:name":"Luc De Coninck",
    "wof:placetype":"venue"
},
  "geometry": {"coordinates":[3.3405730724,50.9842033386],"type":"Point"}
}