{
  "type": "Feature",
  "properties": {
    "addr:full":"Stationsstraat 36 Maaseik Limburg 3680",
    "addr:housenumber":"36",
    "addr:postcode":"3680",
    "addr:street":"Stationsstraat",
    "iso:country":"BE",
    "sg:address":"Stationsstraat 36",
    "sg:city":"Maaseik",
    "sg:orig_category":"Taxi's speciale diensten",
    "sg:phone":"+32 89 57 25 93",
    "sg:postcode":"3680",
    "sg:province":"Limburg",
    "wof:name":"Matt Vossen",
    "wof:placetype":"venue"
},
  "geometry": {"coordinates":[5.7808690071,51.0960273743],"type":"Point"}
}