{
  "type": "Feature",
  "properties": {
    "iso:country":"BE",
    "sg:address":"Chauss\u00e9e Du Roi Baudouin 87a",
    "sg:city":"Mons (saint-symphorien)",
    "sg:classifiers":[
        {
            "category":"Professional",
            "subcategory":"Detective & Security Services",
            "type":"Services"
        }
    ],
    "sg:phone":"+32 64 26 51 41",
    "sg:postcode":"7030",
    "sg:province":"Hainaut",
    "sg:tags":[
        "installation",
        "alarm",
        "-",
        "system"
    ],
    "wof:name":"A.c.e.",
    "wof:placetype":"venue"
},
  "geometry": {"coordinates":[4.0108299255,50.4393882751],"type":"Point"}
}