{
  "type": "Feature",
  "properties": {
    "addr:full":"Avenue Notre-dame De Foy 81 Florennes Namur 5620",
    "addr:housenumber":"81",
    "addr:postcode":"5620",
    "addr:street":"Avenue Notre-Dame De Foy",
    "iso:country":"BE",
    "sg:address":"Avenue Notre-dame De Foy 81",
    "sg:city":"Florennes",
    "sg:classifiers":[
        {
            "category":"Professional",
            "subcategory":"Engineering",
            "type":"Services"
        }
    ],
    "sg:phone":"+32 71 68 75 15",
    "sg:postcode":"5620",
    "sg:province":"Namur",
    "sg:tags":[
        "industrial",
        "-",
        "automation"
    ],
    "wof:name":"Boury D Bei",
    "wof:placetype":"venue"
},
  "geometry": {"coordinates":[4.6111888885,50.2467956543],"type":"Point"}
}