{
  "type": "Feature",
  "properties": {
    "iso:country":"BE",
    "sg:address":"Clos Des P\u00c2querettes 1",
    "sg:city":"Ans",
    "sg:orig_category":"Graphologues, astrologues, voyants and radiesth\u00e9sistes",
    "sg:phone":"+32 4 246 25 19",
    "sg:postcode":"4432",
    "sg:province":"Li\u00e8ge",
    "wof:name":"C.e.r.e.b.",
    "wof:placetype":"venue"
},
  "geometry": {"coordinates":[5.5041131973,50.6758117676],"type":"Point"}
}