{
  "type": "Feature",
  "properties": {
    "addr:full":"Brusselsesteenweg 39 Lebbeke Oost-Vlaanderen 9280",
    "addr:housenumber":"39",
    "addr:postcode":"9280",
    "addr:street":"Brusselsesteenweg",
    "iso:country":"BE",
    "sg:address":"Brusselsesteenweg 39",
    "sg:city":"Lebbeke",
    "sg:classifiers":[
        {
            "category":"Health Services",
            "subcategory":"Health Practitioner",
            "type":"Services"
        }
    ],
    "sg:phone":"+32 52 41 01 34",
    "sg:postcode":"9280",
    "sg:province":"Oost-Vlaanderen",
    "sg:tags":[
        "physiotherapist"
    ],
    "wof:name":"Halet A",
    "wof:placetype":"venue"
},
  "geometry": {"coordinates":[4.1283922195,50.999294281],"type":"Point"}
}