{
  "type": "Feature",
  "properties": {
    "iso:country":"BE",
    "sg:address":"Oude Westtragel 7a",
    "sg:city":"Zelzate",
    "sg:classifiers":[
        {
            "category":"Retail",
            "subcategory":"Car Wash",
            "type":"Services"
        }
    ],
    "sg:phone":"+32 9 345 57 63",
    "sg:postcode":"9060",
    "sg:province":"Oost-Vlaanderen",
    "sg:tags":[
        "automobile",
        "-",
        "washing",
        "truck",
        "equipment"
    ],
    "wof:name":"Hanp\u00f6 Carwash Industrie",
    "wof:placetype":"venue"
},
  "geometry": {"coordinates":[3.8105199337,51.1968154907],"type":"Point"}
}