{
  "type": "Feature",
  "properties": {
    "iso:country":"BE",
    "sg:address":"Montagne D'hastedon 1",
    "sg:city":"Namur",
    "sg:orig_category":"Journaux. Tabac",
    "sg:phone":"+32 81 73 25 76",
    "sg:postcode":"5002",
    "sg:province":"Namur",
    "wof:name":"Gerard",
    "wof:placetype":"venue"
},
  "geometry": {"coordinates":[4.8432559967,50.4786224365],"type":"Point"}
}