{
  "type": "Feature",
  "properties": {
    "iso:country":"BE",
    "sg:address":"Diepestraat 113",
    "sg:city":"Antwerpen",
    "sg:orig_category":"Cr\u00e9dits divers",
    "sg:postcode":"2060",
    "sg:province":"Antwerpen",
    "wof:name":"Bancontact-mister Cash",
    "wof:placetype":"venue"
},
  "geometry": {"coordinates":[4.4259281158,51.2227592468],"type":"Point"}
}