{
  "type": "Feature",
  "properties": {
    "iso:country":"BE",
    "sg:address":"Dorpsstraat 58",
    "sg:city":"Tielt-winge",
    "sg:orig_category":"Bouwmaterialen Gh Hout and afgeleiden Gh Houtbewerking and -behandeling IJzerwaren, bouw- and verfma",
    "sg:phone":"+32 16 50 11 15",
    "sg:postcode":"3390",
    "sg:province":"Vlaams-Brabant",
    "wof:name":"Houtzagerij Jos Broos",
    "wof:placetype":"venue"
},
  "geometry": {"coordinates":[4.9125900269,50.9441719055],"type":"Point"}
}