{
  "type": "Feature",
  "properties": {
    "addr:full":"Molenstraat 70 Schilde Antwerpen 2970",
    "addr:housenumber":"70",
    "addr:postcode":"2970",
    "addr:street":"Molenstraat",
    "iso:country":"BE",
    "sg:address":"Molenstraat 70",
    "sg:city":"Schilde",
    "sg:classifiers":[
        {
            "category":"Social Services",
            "subcategory":"Retirement Home",
            "type":"Services"
        }
    ],
    "sg:phone":"+32 3 385 33 90",
    "sg:postcode":"2970",
    "sg:province":"Antwerpen",
    "sg:tags":[
        "residence"
    ],
    "wof:name":"Molenerf Serviceflats",
    "wof:placetype":"venue"
},
  "geometry": {"coordinates":[4.5800600052,51.2438049316],"type":"Point"}
}