{
  "type": "Feature",
  "properties": {
    "addr:full":"Minderbroedersrui 32 Antwerpen Antwerpen 2000",
    "addr:housenumber":"32",
    "addr:postcode":"2000",
    "addr:street":"Minderbroedersrui",
    "iso:country":"BE",
    "sg:address":"Minderbroedersrui 32",
    "sg:city":"Antwerpen",
    "sg:classifiers":[
        {
            "category":"Professional",
            "subcategory":"Art Services",
            "type":"Services"
        }
    ],
    "sg:phone":"+32 3 227 41 97",
    "sg:postcode":"2000",
    "sg:province":"Antwerpen",
    "sg:tags":[
        "good",
        "-",
        "transport"
    ],
    "wof:name":"Art & Exhibition Services Nv",
    "wof:placetype":"venue"
},
  "geometry": {"coordinates":[4.4042420387,51.2224311829],"type":"Point"}
}