{
  "type": "Feature",
  "properties": {
    "iso:country":"BE",
    "sg:address":"Belseledorp 189",
    "sg:city":"Sint-niklaas",
    "sg:orig_category":"Installation de menuiserie en bois and plastique",
    "sg:phone":"+32 3 772 28 18",
    "sg:postcode":"9111",
    "sg:province":"Oost-Vlaanderen",
    "wof:name":"Roger Rooms",
    "wof:placetype":"venue"
},
  "geometry": {"coordinates":[4.0814418793,51.144329071],"type":"Point"}
}