{
  "type": "Feature",
  "properties": {
    "iso:country":"BE",
    "sg:address":"Rue Albert Ier 42a",
    "sg:city":"Mettet",
    "sg:orig_category":"Installatie van houten of kunststof schrijnwerk",
    "sg:phone":"+32 71 72 85 75",
    "sg:postcode":"5640",
    "sg:province":"Namur",
    "wof:name":"Sansone J.",
    "wof:placetype":"venue"
},
  "geometry": {"coordinates":[4.6578159332,50.322883606],"type":"Point"}
}