{
  "type": "Feature",
  "properties": {
    "iso:country":"BE",
    "sg:address":"Caatsweg 9",
    "sg:city":"Sint-laureins",
    "sg:orig_category":"Rundveehouders Varkenskwekers",
    "sg:phone":"+32 9 379 85 04",
    "sg:postcode":"9980",
    "sg:province":"Oost-Vlaanderen",
    "wof:name":"Roger Buysse",
    "wof:placetype":"venue"
},
  "geometry": {"coordinates":[3.5324718952,51.2312698364],"type":"Point"}
}