{
  "type": "Feature",
  "properties": {
    "iso:country":"BE",
    "sg:address":"Rue De Porcheresse 54",
    "sg:city":"Daverdisse",
    "sg:orig_category":"Zuivelproducten",
    "sg:phone":"+32 61 51 20 01",
    "sg:postcode":"6929",
    "sg:province":"Luxembourg",
    "wof:name":"Madeleine Mohy",
    "wof:placetype":"venue"
},
  "geometry": {"coordinates":[5.0627980232,49.995426178],"type":"Point"}
}