{
  "type": "Feature",
  "properties": {
    "addr:full":"Noordhoutstraat 44 Gent (drongen) Oost-Vlaanderen 9031",
    "addr:housenumber":"44",
    "addr:postcode":"9031",
    "addr:street":"Noordhoutstraat",
    "iso:country":"BE",
    "sg:address":"Noordhoutstraat 44",
    "sg:city":"Gent (drongen)",
    "sg:classifiers":[
        {
            "category":"Building & Trades",
            "subcategory":"Plumbing",
            "type":"Services"
        }
    ],
    "sg:phone":"+32 9 282 94 74",
    "sg:postcode":"9031",
    "sg:province":"Oost-Vlaanderen",
    "sg:tags":[
        "repair",
        "mainten",
        "-",
        "central",
        "heating"
    ],
    "wof:name":"Haenebalcke D",
    "wof:placetype":"venue"
},
  "geometry": {"coordinates":[3.5954499245,51.0308609009],"type":"Point"}
}