{
  "type": "Feature",
  "properties": {
    "iso:country":"BE",
    "sg:address":"Bergstraat 119",
    "sg:city":"Kampenhout",
    "sg:orig_category":"Plomberie, chauffage and installations sanitaires. Installation de piscines",
    "sg:phone":"+32 16 65 15 83",
    "sg:postcode":"1910",
    "sg:province":"Vlaams-Brabant",
    "wof:name":"Pool Construct",
    "wof:placetype":"venue"
},
  "geometry": {"coordinates":[4.5451078415,50.9305725098],"type":"Point"}
}