{
  "type": "Feature",
  "properties": {
    "iso:country":"BE",
    "sg:address":"Mechelsesteenweg 8",
    "sg:city":"Willebroek",
    "sg:orig_category":"V\u00e9los",
    "sg:phone":"+32 3 886 62 70",
    "sg:postcode":"2830",
    "sg:province":"Antwerpen",
    "wof:name":"Hublin M. & Claessens D.",
    "wof:placetype":"venue"
},
  "geometry": {"coordinates":[4.3643078804,51.0596923828],"type":"Point"}
}