{
  "type": "Feature",
  "properties": {
    "addr:full":"Meerstraat 235 Londerzeel Vlaams-Brabant 1840",
    "addr:housenumber":"235",
    "addr:postcode":"1840",
    "addr:street":"Meerstraat",
    "iso:country":"BE",
    "sg:address":"Meerstraat 235",
    "sg:city":"Londerzeel",
    "sg:orig_category":"R\u00e9parations \u00e0 domicile d'appareils \u00e9lectriques. Location d'appareils audio-visuels. Electrom\u00e9nager, ",
    "sg:phone":"+32 52 30 32 62",
    "sg:postcode":"1840",
    "sg:province":"Vlaams-Brabant",
    "wof:name":"Videlro",
    "wof:placetype":"venue"
},
  "geometry": {"coordinates":[4.31524086,51.0156860352],"type":"Point"}
}