{
  "type": "Feature",
  "properties": {
    "iso:country":"BE",
    "sg:address":"Amsterdamstraat 44",
    "sg:city":"Meer",
    "sg:classifiers":[
        {
            "category":"Structure",
            "subcategory":"Tower",
            "type":"Public Place"
        }
    ],
    "sg:phone":"+32 3 541 76 92",
    "sg:postcode":"2321",
    "sg:province":"Antwerpen",
    "sg:tags":[
        "laboratory",
        "clinical",
        "system",
        "analysis"
    ],
    "wof:name":"Sarstedt B.v.b.a.",
    "wof:placetype":"venue"
},
  "geometry": {"coordinates":[4.7310400009,51.4836540222],"type":"Point"}
}