{
  "type": "Feature",
  "properties": {
    "iso:country":"BE",
    "sg:address":"Rue De L'argot\u00c9 32",
    "sg:city":"Durbuy",
    "sg:orig_category":"Boucheries",
    "sg:phone":"+32 86 40 08 01",
    "sg:postcode":"6941",
    "sg:province":"Luxembourg",
    "wof:name":"Chez Guy",
    "wof:placetype":"venue"
},
  "geometry": {"coordinates":[5.5860772133,50.3822517395],"type":"Point"}
}