{
  "type": "Feature",
  "properties": {
    "addr:full":"Avenue G\u00c9n\u00c9ral-jacques 30 Nivelles Brabant Wallon 1400",
    "addr:housenumber":"30",
    "addr:postcode":"1400",
    "addr:street":"Avenue Ge\u0301Ne\u0301Ral-Jacques",
    "iso:country":"BE",
    "sg:address":"Avenue G\u00c9n\u00c9ral-jacques 30",
    "sg:city":"Nivelles",
    "sg:orig_category":"Sportclubs",
    "sg:phone":"+32 67 21 61 83",
    "sg:postcode":"1400",
    "sg:province":"Brabant Wallon",
    "wof:name":"A.r.b.a. Sports",
    "wof:placetype":"venue"
},
  "geometry": {"coordinates":[4.3301749229,50.594543457],"type":"Point"}
}