{
  "type": "Feature",
  "properties": {
    "addr:full":"Rijksweg 13 Maasmechelen Limburg 3630",
    "addr:housenumber":"13",
    "addr:postcode":"3630",
    "addr:street":"Rijksweg",
    "iso:country":"BE",
    "sg:address":"Rijksweg 13",
    "sg:city":"Maasmechelen",
    "sg:orig_category":"Boissons",
    "sg:phone":"+32 89 75 62 55",
    "sg:postcode":"3630",
    "sg:province":"Limburg",
    "wof:name":"Dranken Corstjens-venken",
    "wof:placetype":"venue"
},
  "geometry": {"coordinates":[5.6989679337,50.9720573425],"type":"Point"}
}