{
  "type": "Feature",
  "properties": {
    "addr:full":"Kruisstraat 6 Lebbeke (denderbelle) Oost-Vlaanderen 9280",
    "addr:housenumber":"6",
    "addr:postcode":"9280",
    "addr:street":"Kruisstraat",
    "iso:country":"BE",
    "sg:address":"Kruisstraat 6",
    "sg:city":"Lebbeke (denderbelle)",
    "sg:classifiers":[
        {
            "category":"Building & Trades",
            "subcategory":"Electrical",
            "type":"Services"
        }
    ],
    "sg:phone":"+32 52 41 40 98",
    "sg:postcode":"9280",
    "sg:province":"Oost-Vlaanderen",
    "sg:tags":[
        "electric",
        "-",
        "housewiring",
        "contractor"
    ],
    "wof:name":"Bisschop F",
    "wof:placetype":"venue"
},
  "geometry": {"coordinates":[4.0920138359,51.003868103],"type":"Point"}
}