{
  "type": "Feature",
  "properties": {
    "iso:country":"BE",
    "sg:address":"Filips Van De Elzaslaan 83",
    "sg:city":"Kortrijk",
    "sg:classifiers":[
        {
            "category":"Health Services",
            "subcategory":"Dentist",
            "type":"Services"
        }
    ],
    "sg:phone":"+32 56 22 30 53",
    "sg:postcode":"8500",
    "sg:province":"West-Vlaanderen",
    "wof:name":"Mattelaer Anton",
    "wof:placetype":"venue"
},
  "geometry": {"coordinates":[3.2767961025,50.8219680786],"type":"Point"}
}