{
  "type": "Feature",
  "properties": {
    "iso:country":"BE",
    "sg:address":"Keibergstraat 82",
    "sg:city":"Torhout",
    "sg:orig_category":"Non-Classified Establishments",
    "sg:phone":"+32 50 22 08 31",
    "sg:postcode":"8820",
    "sg:province":"West-Vlaanderen",
    "wof:name":"Voltex Nv",
    "wof:placetype":"venue"
},
  "geometry": {"coordinates":[3.1150801182,51.0746078491],"type":"Point"}
}