{
  "type": "Feature",
  "properties": {
    "iso:country":"BE",
    "sg:address":"Rue De Nivelles 4",
    "sg:city":"Tubize",
    "sg:orig_category":"Autoverhuur",
    "sg:phone":"+32 2 355 80 06",
    "sg:postcode":"1480",
    "sg:province":"Brabant Wallon",
    "wof:name":"Avis",
    "wof:placetype":"venue"
},
  "geometry": {"coordinates":[4.2054200172,50.6943664551],"type":"Point"}
}