{
  "type": "Feature",
  "properties": {
    "addr:full":"Bergstrasse 45 Eupen Li\u00e8ge 4700",
    "addr:housenumber":"45",
    "addr:postcode":"4700",
    "addr:street":"Bergstrasse",
    "iso:country":"BE",
    "sg:address":"Bergstrasse 45",
    "sg:city":"Eupen",
    "sg:classifiers":[
        {
            "category":"Shopping",
            "subcategory":"Gifts & Souvenirs",
            "type":"Retail Goods"
        }
    ],
    "sg:phone":"+32 87 74 03 73",
    "sg:postcode":"4700",
    "sg:province":"Li\u00e8ge",
    "sg:tags":[
        "-"
    ],
    "wof:name":"Weltladen",
    "wof:placetype":"venue"
},
  "geometry": {"coordinates":[6.0333361626,50.628944397],"type":"Point"}
}