{
  "type": "Feature",
  "properties": {
    "iso:country":"BE",
    "sg:address":"Spreet 36",
    "sg:city":"Lier",
    "sg:classifiers":[
        {
            "category":"Travel",
            "subcategory":"Travel Agent",
            "type":"Entertainment"
        }
    ],
    "sg:phone":"+32 3 482 24 15",
    "sg:postcode":"2500",
    "sg:province":"Antwerpen",
    "sg:tags":[
        "agency"
    ],
    "wof:name":"Asatours-mundicolor Belgica Nv",
    "wof:placetype":"venue"
},
  "geometry": {"coordinates":[4.6025619507,51.1097679138],"type":"Point"}
}