{
  "type": "Feature",
  "properties": {
    "iso:country":"BE",
    "sg:address":"Hogeweg 6",
    "sg:city":"Stabroek",
    "sg:orig_category":"Pharmaciens",
    "sg:phone":"+32 3 664 74 86",
    "sg:postcode":"2940",
    "sg:province":"Antwerpen",
    "wof:name":"Francis Nagels",
    "wof:placetype":"venue"
},
  "geometry": {"coordinates":[4.3906998634,51.3196907043],"type":"Point"}
}