{
  "type": "Feature",
  "properties": {
    "addr:full":"Wijzemanstraat 6 Gent Oost-Vlaanderen 9000",
    "addr:housenumber":"6",
    "addr:postcode":"9000",
    "addr:street":"Wijzemanstraat;Oost-Vlaanderen",
    "iso:country":"BE",
    "sg:address":"Wijzemanstraat 6",
    "sg:city":"Gent",
    "sg:classifiers":[
        {
            "category":"Real Estate",
            "subcategory":"Architect",
            "type":"Services"
        }
    ],
    "sg:phone":"+32 9 223 42 77",
    "sg:postcode":"9000",
    "sg:province":"Oost-Vlaanderen",
    "wof:name":"Platel A",
    "wof:placetype":"venue"
},
  "geometry": {"coordinates":[3.7266991138,51.0568199158],"type":"Point"}
}