{
  "type": "Feature",
  "properties": {
    "addr:full":"Rue Des Oeillets 21 Binche (ressaix) Hainaut 7134",
    "addr:housenumber":"21",
    "addr:postcode":"7134",
    "addr:street":"Rue Des Oeillets",
    "iso:country":"BE",
    "sg:address":"Rue Des Oeillets 21",
    "sg:city":"Binche (ressaix)",
    "sg:classifiers":[
        {
            "category":"Health Services",
            "subcategory":"Health Practitioner",
            "type":"Services"
        }
    ],
    "sg:phone":"+32 64 36 67 87",
    "sg:postcode":"7134",
    "sg:province":"Hainaut",
    "sg:tags":[
        "physiotherapist"
    ],
    "wof:name":"Lugowoj Carine",
    "wof:placetype":"venue"
},
  "geometry": {"coordinates":[4.1919250488,50.4304656982],"type":"Point"}
}