{
  "type": "Feature",
  "properties": {
    "iso:country":"BE",
    "sg:address":"Dadizeelsestraat 36",
    "sg:city":"Moorslede",
    "sg:orig_category":"Elektrische installaties voor woningen Loodgieterij, verwarming and sanitaire installaties",
    "sg:phone":"+32 51 78 02 20",
    "sg:postcode":"8890",
    "sg:province":"West-Vlaanderen",
    "wof:name":"Vincent Stockman",
    "wof:placetype":"venue"
},
  "geometry": {"coordinates":[3.060503006,50.889919281],"type":"Point"}
}