{
  "type": "Feature",
  "properties": {
    "addr:full":"Molenstraat 86 Wetteren Oost-Vlaanderen 9230",
    "addr:housenumber":"86",
    "addr:postcode":"9230",
    "addr:street":"Molenstraat",
    "iso:country":"BE",
    "sg:address":"Molenstraat 86",
    "sg:city":"Wetteren",
    "sg:orig_category":"Banken and kredietinstellingen",
    "sg:phone":"+32 9 365 00 18",
    "sg:postcode":"9230",
    "sg:province":"Oost-Vlaanderen",
    "wof:name":"Groep Argenta",
    "wof:placetype":"venue"
},
  "geometry": {"coordinates":[3.8886899948,51.0038414001],"type":"Point"}
}