{
  "type": "Feature",
  "properties": {
    "addr:full":"Koningin Astridlaan 440 Kraainem/kraainem Vlaams-Brabant 1950",
    "addr:housenumber":"440",
    "addr:postcode":"1950",
    "addr:street":"Koningin Astridlaan",
    "iso:country":"BE",
    "sg:address":"Koningin Astridlaan 440",
    "sg:city":"Kraainem/kraainem",
    "sg:orig_category":"Kinderopvang",
    "sg:phone":"+32 2 731 08 13",
    "sg:postcode":"1950",
    "sg:province":"Vlaams-Brabant",
    "wof:name":"Garderie Reine Astrid",
    "wof:placetype":"venue"
},
  "geometry": {"coordinates":[4.4689297676,50.8391189575],"type":"Point"}
}