{
  "type": "Feature",
  "properties": {
    "iso:country":"BE",
    "sg:address":"Marktplein 8",
    "sg:city":"Landen",
    "sg:orig_category":"Disquaires",
    "sg:phone":"+32 11 88 74 50",
    "sg:postcode":"3400",
    "sg:province":"Vlaams-Brabant",
    "wof:name":"M.p. Multimedia Shop",
    "wof:placetype":"venue"
},
  "geometry": {"coordinates":[5.0807719231,50.7528762817],"type":"Point"}
}