{
  "type": "Feature",
  "properties": {
    "iso:country":"BE",
    "sg:address":"Nieuwstraat 64",
    "sg:city":"Geel",
    "sg:classifiers":[
        {
            "category":"Bars & Pubs",
            "type":"Food & Drink"
        }
    ],
    "sg:phone":"+32 14 58 80 08",
    "sg:postcode":"2440",
    "sg:province":"Antwerpen",
    "wof:name":"Volkshuis Geel Sm",
    "wof:placetype":"venue"
},
  "geometry": {"coordinates":[4.9932041168,51.1632003784],"type":"Point"}
}