{
  "type": "Feature",
  "properties": {
    "iso:country":"BE",
    "sg:address":"De Kemmeterlaan 23",
    "sg:city":"Gent",
    "sg:classifiers":[
        {
            "category":"Arena",
            "subcategory":"Sports Club",
            "type":"Entertainment"
        }
    ],
    "sg:phone":"+32 9 227 48 38",
    "sg:postcode":"9031",
    "sg:province":"Oost-Vlaanderen",
    "sg:tags":[
        "terrain",
        "hors",
        "de",
        "installation",
        "sportifs"
    ],
    "wof:name":"K.v.v. Drongen Sport",
    "wof:placetype":"venue"
},
  "geometry": {"coordinates":[3.6511790752,51.0489425659],"type":"Point"}
}