{
  "type": "Feature",
  "properties": {
    "addr:full":"Heerstraat 8 Neerpelt Limburg 3910",
    "addr:housenumber":"8",
    "addr:postcode":"3910",
    "addr:street":"Heerstraat",
    "iso:country":"BE",
    "sg:address":"Heerstraat 8",
    "sg:city":"Neerpelt",
    "sg:orig_category":"Artiesten and kunstenaars",
    "sg:phone":"+32 11 64 11 73",
    "sg:postcode":"3910",
    "sg:province":"Limburg",
    "wof:name":"Douven",
    "wof:placetype":"venue"
},
  "geometry": {"coordinates":[5.4350380898,51.2285003662],"type":"Point"}
}