{
  "type": "Feature",
  "properties": {
    "iso:country":"BE",
    "sg:address":"Vredesplein 17",
    "sg:city":"Zwalm",
    "sg:orig_category":"Maisons de repos and r\u00e9sidences",
    "sg:phone":"+32 55 49 79 10",
    "sg:postcode":"9630",
    "sg:province":"Oost-Vlaanderen",
    "wof:name":"De Verpleeg Service",
    "wof:placetype":"venue"
},
  "geometry": {"coordinates":[3.7122850418,50.8654823303],"type":"Point"}
}