{
  "type": "Feature",
  "properties": {
    "iso:country":"BE",
    "sg:address":"Berlaarsesteenweg 42",
    "sg:city":"Lier",
    "sg:orig_category":"Artsen and specialisten",
    "sg:phone":"+32 3 480 09 50",
    "sg:postcode":"2500",
    "sg:province":"Antwerpen",
    "wof:name":"Dirk Vanmeert",
    "wof:placetype":"venue"
},
  "geometry": {"coordinates":[4.5852818489,51.1282234192],"type":"Point"}
}