{
  "type": "Feature",
  "properties": {
    "iso:country":"BE",
    "sg:address":"Grotstraat 4",
    "sg:city":"Herk-de-stad",
    "sg:classifiers":[
        {
            "category":"Cafe",
            "type":"Food & Drink"
        }
    ],
    "sg:phone":"+32 13 55 19 87",
    "sg:postcode":"3540",
    "sg:province":"Limburg",
    "sg:tags":[
        "caf\u00e9s"
    ],
    "wof:name":"Peter Vos",
    "wof:placetype":"venue"
},
  "geometry": {"coordinates":[5.2118678093,50.9549102783],"type":"Point"}
}