{
  "type": "Feature",
  "properties": {
    "addr:full":"Brusselsesteenweg 317b Overijse Vlaams-Brabant 3090",
    "addr:housenumber":"317b",
    "addr:postcode":"3090",
    "addr:street":"Brusselsesteenweg",
    "iso:country":"BE",
    "sg:address":"Brusselsesteenweg 317b",
    "sg:city":"Overijse",
    "sg:classifiers":[
        {
            "category":"Retail",
            "subcategory":"Auto Repair",
            "type":"Services"
        }
    ],
    "sg:phone":"+32 2 688 11 90",
    "sg:postcode":"3090",
    "sg:province":"Vlaams-Brabant",
    "sg:tags":[
        "garage"
    ],
    "wof:name":"Nitramcar",
    "wof:placetype":"venue"
},
  "geometry": {"coordinates":[4.5129361153,50.7811584473],"type":"Point"}
}