{
  "type": "Feature",
  "properties": {
    "iso:country":"BE",
    "sg:address":"Grand'rue D'acren 63",
    "sg:city":"Lessines (deux-acren)",
    "sg:classifiers":[
        {
            "category":"Personal",
            "subcategory":"Beauty Salon",
            "type":"Services"
        }
    ],
    "sg:phone":"+32 68 33 48 00",
    "sg:postcode":"7864",
    "sg:province":"Hainaut",
    "sg:tags":[
        "lady",
        "-",
        "hairdressing"
    ],
    "wof:name":"Anne (coiffure)",
    "wof:placetype":"venue"
},
  "geometry": {"coordinates":[3.8542039394,50.7285804749],"type":"Point"}
}