{
  "type": "Feature",
  "properties": {
    "iso:country":"BE",
    "sg:address":"R De Breuze 9bis",
    "sg:city":"Kain",
    "sg:classifiers":[
        {
            "category":"Education",
            "subcategory":"School",
            "type":"Public Place"
        }
    ],
    "sg:phone":"+32 69 22 97 24",
    "sg:postcode":"7540",
    "sg:province":"Hainaut",
    "sg:tags":[
        "boarding"
    ],
    "wof:name":"Internat Home D'accueil De La Communation Fran\u00e7ais",
    "wof:placetype":"venue"
},
  "geometry": {"coordinates":[3.404517889,50.6270484924],"type":"Point"}
}