{
  "type": "Feature",
  "properties": {
    "addr:full":"Place D'herquegies 10 Frasnes-lez-anvaing (herquegies) Hainaut 7911",
    "addr:housenumber":"10",
    "addr:postcode":"7911",
    "addr:street":"Place D'Herquegies;Hainaut",
    "iso:country":"BE",
    "sg:address":"Place D'herquegies 10",
    "sg:city":"Frasnes-lez-anvaing (herquegies)",
    "sg:classifiers":[
        {
            "category":"Real Estate",
            "subcategory":"Architect",
            "type":"Services"
        }
    ],
    "sg:phone":"+32 69 86 82 25",
    "sg:postcode":"7911",
    "sg:province":"Hainaut",
    "wof:name":"Olivier S",
    "wof:placetype":"venue"
},
  "geometry": {"coordinates":[3.5790550709,50.6350517273],"type":"Point"}
}