{
  "type": "Feature",
  "properties": {
    "iso:country":"BE",
    "sg:address":"Chaus\u00c9e D'asse",
    "sg:city":"Edingen/enghien",
    "sg:orig_category":"Plomberie, chauffage and installations sanitaires",
    "sg:phone":"+32 2 397 03 90",
    "sg:postcode":"7850",
    "sg:province":"Hainaut",
    "wof:name":"Ceba Confort",
    "wof:placetype":"venue"
},
  "geometry": {"coordinates":[4.0455379486,50.698474884],"type":"Point"}
}