{
  "type": "Feature",
  "properties": {
    "addr:full":"Heirbaan 251 Hamme Oost-Vlaanderen 9220",
    "addr:housenumber":"251",
    "addr:postcode":"9220",
    "addr:street":"Heirbaan",
    "iso:country":"BE",
    "sg:address":"Heirbaan 251",
    "sg:city":"Hamme",
    "sg:orig_category":"Catering and organisatie van feesten Fast food and meeneem restaurants Restaurants",
    "sg:phone":"+32 52 48 11 96",
    "sg:postcode":"9220",
    "sg:province":"Oost-Vlaanderen",
    "wof:name":"Restaurant 't Hofstedeke",
    "wof:placetype":"venue"
},
  "geometry": {"coordinates":[4.0982208252,51.070602417],"type":"Point"}
}