{
  "type": "Feature",
  "properties": {
    "addr:full":"Rue F Hals 77 Anderlecht Bruxelles-Capitale 1070",
    "addr:housenumber":"77",
    "addr:postcode":"1070",
    "addr:street":"Rue F Hals",
    "iso:country":"BE",
    "sg:address":"Rue F Hals 77",
    "sg:city":"Anderlecht",
    "sg:orig_category":"Rev\u00eatements de sols and murs",
    "sg:phone":"+32 2 520 25 82",
    "sg:postcode":"1070",
    "sg:province":"Bruxelles-Capitale",
    "wof:name":"Spinnoy Pierre",
    "wof:placetype":"venue"
},
  "geometry": {"coordinates":[4.2953438759,50.8240661621],"type":"Point"}
}