{
  "type": "Feature",
  "properties": {
    "iso:country":"BE",
    "sg:address":"Rue Haute 3",
    "sg:city":"Morlanwelz (mont-sainte-aldegonde)",
    "sg:classifiers":[
        {
            "category":"Banks & Credit Unions",
            "subcategory":"Financial Services",
            "type":"Services"
        }
    ],
    "sg:phone":"+32 64 33 84 71",
    "sg:postcode":"7141",
    "sg:province":"Hainaut",
    "sg:tags":[
        "loan",
        "mortgage"
    ],
    "wof:name":"M D Finances",
    "wof:placetype":"venue"
},
  "geometry": {"coordinates":[4.2335572243,50.4290084839],"type":"Point"}
}