{
  "type": "Feature",
  "properties": {
    "addr:full":"Stee 24 Sint-laureins Oost-Vlaanderen 9988",
    "addr:housenumber":"24",
    "addr:postcode":"9988",
    "addr:street":"Stee",
    "iso:country":"BE",
    "sg:address":"Stee 24",
    "sg:city":"Sint-laureins",
    "sg:orig_category":"Installatie van houten of kunststof schrijnwerk Installatie van metalen schrijnwerk",
    "sg:phone":"+32 9 379 84 07",
    "sg:postcode":"9988",
    "sg:province":"Oost-Vlaanderen",
    "wof:name":"Van De Velde",
    "wof:placetype":"venue"
},
  "geometry": {"coordinates":[3.6264441013,51.2762031555],"type":"Point"}
}