{
  "type": "Feature",
  "properties": {
    "addr:full":"Begoniastraat 36 Watermaal-bosvoorde/watermael-boitsfort Bruxelles-Capitale 1170",
    "addr:housenumber":"36",
    "addr:postcode":"1170",
    "addr:street":"Begoniastraat",
    "iso:country":"BE",
    "sg:address":"Begoniastraat 36",
    "sg:city":"Watermaal-bosvoorde/watermael-boitsfort",
    "sg:orig_category":"Woningbouw",
    "sg:phone":"+32 2 672 67 58",
    "sg:postcode":"1170",
    "sg:province":"Bruxelles-Capitale",
    "wof:name":"Les Entreprises Sansterre",
    "wof:placetype":"venue"
},
  "geometry": {"coordinates":[4.4042859077,50.8113861084],"type":"Point"}
}