{
  "type": "Feature",
  "properties": {
    "addr:full":"Karel De Grotelaan 46-48 International Press Center 1041",
    "addr:housenumber":"46-48;1041",
    "addr:street":"Karel De Grotelaan;International",
    "iso:country":"BE",
    "sg:address":"Karel De Grotelaan 46-48",
    "sg:city":"International Press Center",
    "sg:classifiers":[
        {
            "category":"Professional",
            "subcategory":"Art Services",
            "type":"Services"
        }
    ],
    "sg:phone":"+32 2 230 01 47",
    "sg:postcode":"1041",
    "sg:tags":[
        "realization",
        "audio-visual"
    ],
    "wof:name":"Tv Connections",
    "wof:placetype":"venue"
},
  "geometry": {"coordinates":[-106.1669540405,37.7696647644],"type":"Point"}
}