{
  "type": "Feature",
  "properties": {
    "iso:country":"BE",
    "sg:address":"Place Du Sablon 45",
    "sg:city":"Dison",
    "sg:classifiers":[
        {
            "category":"Retail",
            "subcategory":"Laundry & Dry Cleaning",
            "type":"Services"
        }
    ],
    "sg:phone":"+32 87 35 13 45",
    "sg:postcode":"4820",
    "sg:province":"Li\u00e8ge",
    "sg:tags":[
        "self",
        "-"
    ],
    "wof:name":"Lavoir Du Sablon Sprl",
    "wof:placetype":"venue"
},
  "geometry": {"coordinates":[5.8548159599,50.6104431152],"type":"Point"}
}