{
  "type": "Feature",
  "properties": {
    "iso:country":"BE",
    "sg:address":"Lauwbergstraat 148",
    "sg:city":"Menen",
    "sg:orig_category":"Installation de menuiserie en bois and plastique",
    "sg:phone":"+32 56 40 29 07",
    "sg:postcode":"8930",
    "sg:province":"West-Vlaanderen",
    "wof:name":"Geert Pattyn",
    "wof:placetype":"venue"
},
  "geometry": {"coordinates":[3.1209149361,50.7961845398],"type":"Point"}
}