{
  "type": "Feature",
  "properties": {
    "iso:country":"BE",
    "sg:address":"Marcel F\u00e9lic\u00e9straat 8",
    "sg:city":"Hoeilaart",
    "sg:classifiers":[
        {
            "category":"Professional",
            "subcategory":"Accounting & Tax Preparation",
            "type":"Services"
        }
    ],
    "sg:phone":"+32 2 657 93 23",
    "sg:postcode":"1560",
    "sg:province":"Vlaams-Brabant",
    "sg:tags":[
        "bookkeeper"
    ],
    "wof:name":"Vanderlinden W",
    "wof:placetype":"venue"
},
  "geometry": {"coordinates":[4.4706339836,50.7686004639],"type":"Point"}
}