{
  "type": "Feature",
  "properties": {
    "addr:full":"Sint-truidersteenweg 93 Hasselt Limburg 3500",
    "addr:housenumber":"93",
    "addr:postcode":"3500",
    "addr:street":"Sint-Truidersteenweg",
    "iso:country":"BE",
    "sg:address":"Sint-truidersteenweg 93",
    "sg:city":"Hasselt",
    "sg:orig_category":"Banques and organismes de cr\u00e9dit",
    "sg:phone":"+32 11 27 26 44",
    "sg:postcode":"3500",
    "sg:province":"Limburg",
    "wof:name":"Landbouwkrediet",
    "wof:placetype":"venue"
},
  "geometry": {"coordinates":[5.3327531815,50.9238777161],"type":"Point"}
}