{
  "type": "Feature",
  "properties": {
    "iso:country":"BE",
    "sg:address":"Eynestraat 1",
    "sg:city":"Sint-truiden (zepperen)",
    "sg:classifiers":[
        {
            "category":"Health Services",
            "subcategory":"Dentist",
            "type":"Services"
        }
    ],
    "sg:phone":"+32 11 69 23 53",
    "sg:postcode":"3800",
    "sg:province":"Limburg",
    "wof:name":"Roggen Karina",
    "wof:placetype":"venue"
},
  "geometry": {"coordinates":[5.2572999001,50.8239402771],"type":"Point"}
}