{
  "type": "Feature",
  "properties": {
    "iso:country":"BE",
    "sg:address":"Schrieksebaan 85",
    "sg:city":"Keerbergen",
    "sg:classifiers":[
        {
            "category":"Bars & Pubs",
            "type":"Food & Drink"
        }
    ],
    "sg:phone":"+32 15 23 38 79",
    "sg:postcode":"3140",
    "sg:province":"Vlaams-Brabant",
    "wof:name":"De Koebaan",
    "wof:placetype":"venue"
},
  "geometry": {"coordinates":[4.6607580185,51.0109558105],"type":"Point"}
}