{
  "type": "Feature",
  "properties": {
    "iso:country":"BE",
    "sg:address":"James Ensorlaan 47",
    "sg:city":"Aartselaar",
    "sg:classifiers":[
        {
            "category":"Professional",
            "subcategory":"Management & Consulting",
            "type":"Services"
        }
    ],
    "sg:phone":"+32 3 326 56 40",
    "sg:postcode":"2630",
    "sg:province":"Antwerpen",
    "sg:tags":[
        "consultant",
        "-",
        "legislation",
        "social"
    ],
    "wof:name":"M-proconsult",
    "wof:placetype":"venue"
},
  "geometry": {"coordinates":[4.3806171417,51.1415710449],"type":"Point"}
}