{
  "type": "Feature",
  "properties": {
    "addr:full":"Leopold I-laan 87 Brugge West-Vlaanderen 8000",
    "addr:housenumber":"87",
    "addr:postcode":"8000",
    "addr:street":"Leopold I-Laan",
    "iso:country":"BE",
    "sg:address":"Leopold I-laan 87",
    "sg:city":"Brugge",
    "sg:classifiers":[
        {
            "category":"Insurance",
            "subcategory":"Insurance Agent",
            "type":"Services"
        }
    ],
    "sg:phone":"+32 50 31 47 77",
    "sg:postcode":"8000",
    "sg:province":"West-Vlaanderen",
    "sg:tags":[
        "broker"
    ],
    "wof:name":"Delbecque G",
    "wof:placetype":"venue"
},
  "geometry": {"coordinates":[3.2089390755,51.2150039673],"type":"Point"}
}