{
  "type": "Feature",
  "properties": {
    "iso:country":"BE",
    "sg:address":"Scheldeweg 3",
    "sg:city":"Boom",
    "sg:classifiers":[
        {
            "category":"Transit Center",
            "subcategory":"Freight",
            "type":"Transportation"
        }
    ],
    "sg:phone":"+32 3 880 56 50",
    "sg:postcode":"2850",
    "sg:province":"Antwerpen",
    "sg:tags":[
        "forwarding",
        "agency"
    ],
    "wof:name":"Wm-belgium Nv",
    "wof:placetype":"venue"
},
  "geometry": {"coordinates":[4.3608322144,51.0981483459],"type":"Point"}
}