{
  "type": "Feature",
  "properties": {
    "iso:country":"BE",
    "sg:address":"Pastorijstraat 10",
    "sg:city":"Houthalen-helchteren (houthalen)",
    "sg:classifiers":[
        {
            "category":"Bakery",
            "type":"Food & Drink"
        }
    ],
    "sg:phone":"+32 11 52 40 33",
    "sg:postcode":"3530",
    "sg:province":"Limburg",
    "sg:tags":[
        "confectioner",
        "baker"
    ],
    "wof:name":"Snoks Ludo",
    "wof:placetype":"venue"
},
  "geometry": {"coordinates":[5.3721389771,51.0302619934],"type":"Point"}
}