{
  "type": "Feature",
  "properties": {
    "iso:country":"BE",
    "sg:address":"Nellekenstraat 32",
    "sg:city":"Lennik (sint-kwintens-lennik)",
    "sg:classifiers":[
        {
            "category":"Food & Beverages",
            "subcategory":"Fruits & Vegetables",
            "type":"Retail Goods"
        }
    ],
    "sg:phone":"+32 478 94 18 10",
    "sg:postcode":"1750",
    "sg:province":"Vlaams-Brabant",
    "sg:tags":[
        "-"
    ],
    "wof:name":"Mand Vol (een)",
    "wof:placetype":"venue"
},
  "geometry": {"coordinates":[4.1327381134,50.8204612732],"type":"Point"}
}