{
  "type": "Feature",
  "properties": {
    "addr:full":"Binnenheide 3 Oud-turnhout Antwerpen 2360",
    "addr:housenumber":"3",
    "addr:postcode":"2360",
    "addr:street":"Binnenheide",
    "iso:country":"BE",
    "sg:address":"Binnenheide 3",
    "sg:city":"Oud-turnhout",
    "sg:classifiers":[
        {
            "category":"Personal",
            "subcategory":"Beauty Salon",
            "type":"Services"
        }
    ],
    "sg:phone":"+32 14 45 00 36",
    "sg:postcode":"2360",
    "sg:province":"Antwerpen",
    "sg:tags":[
        "lady",
        "-",
        "hairdressing"
    ],
    "wof:name":"Peggy",
    "wof:placetype":"venue"
},
  "geometry": {"coordinates":[5.0263118744,51.2977561951],"type":"Point"}
}