{
  "type": "Feature",
  "properties": {
    "addr:full":"Burgstraat 122 Gent Oost-Vlaanderen 9000",
    "addr:housenumber":"122",
    "addr:postcode":"9000",
    "addr:street":"Burgstraat;Oost-Vlaanderen",
    "iso:country":"BE",
    "sg:address":"Burgstraat 122",
    "sg:city":"Gent",
    "sg:classifiers":[
        {
            "category":"Professional",
            "subcategory":"Lawyer & Legal Services",
            "type":"Services"
        }
    ],
    "sg:phone":"+32 9 225 28 33",
    "sg:postcode":"9000",
    "sg:province":"Oost-Vlaanderen",
    "sg:tags":[
        "notary"
    ],
    "wof:name":"Neve F",
    "wof:placetype":"venue"
},
  "geometry": {"coordinates":[3.7157111168,51.0564193726],"type":"Point"}
}