{
  "type": "Feature",
  "properties": {
    "iso:country":"BE",
    "sg:address":"Beverstraat 34 Box 6",
    "sg:city":"Ninove",
    "sg:classifiers":[
        {
            "category":"Professional",
            "subcategory":"Computer Services",
            "type":"Services"
        }
    ],
    "sg:phone":"+32 54 34 42 87",
    "sg:postcode":"9400",
    "sg:province":"Oost-Vlaanderen",
    "sg:tags":[
        "-",
        "processing",
        "data",
        "software"
    ],
    "wof:name":"F V S Bvba",
    "wof:placetype":"venue"
},
  "geometry": {"coordinates":[4.0213418007,50.8363571167],"type":"Point"}
}