{
  "type": "Feature",
  "properties": {
    "addr:full":"Lodorp 10 Aalter Oost-Vlaanderen 9880",
    "addr:housenumber":"10",
    "addr:postcode":"9880",
    "addr:street":"Lodorp",
    "iso:country":"BE",
    "sg:address":"Lodorp 10",
    "sg:city":"Aalter",
    "sg:orig_category":"Banken and kredietinstellingen",
    "sg:phone":"+32 51 68 88 51",
    "sg:postcode":"9880",
    "sg:province":"Oost-Vlaanderen",
    "wof:name":"Kbc",
    "wof:placetype":"venue"
},
  "geometry": {"coordinates":[3.4645929337,51.0486831665],"type":"Point"}
}