{
  "type": "Feature",
  "properties": {
    "addr:full":"Brusselse Steenweg 2b Aalst Oost-Vlaanderen 9300",
    "addr:housenumber":"2b",
    "addr:postcode":"9300",
    "addr:street":"Brusselse Steenweg",
    "iso:country":"BE",
    "sg:address":"Brusselse Steenweg 2b",
    "sg:city":"Aalst",
    "sg:classifiers":[
        {
            "category":"Professional",
            "subcategory":"Business Services",
            "type":"Services"
        }
    ],
    "sg:phone":"+32 53 77 03 18",
    "sg:postcode":"9300",
    "sg:province":"Oost-Vlaanderen",
    "sg:tags":[
        "consultant",
        "custom"
    ],
    "wof:name":"Thames Dender Service",
    "wof:placetype":"venue"
},
  "geometry": {"coordinates":[4.0543141365,50.9333267212],"type":"Point"}
}