{
  "type": "Feature",
  "properties": {
    "iso:country":"BE",
    "sg:address":"Perreveld 11",
    "sg:city":"Opwijk",
    "sg:orig_category":"V\u00e9hicules automobiles",
    "sg:phone":"+32 52 35 66 11",
    "sg:postcode":"1745",
    "sg:province":"Vlaams-Brabant",
    "wof:name":"Pasi Cars",
    "wof:placetype":"venue"
},
  "geometry": {"coordinates":[4.1705651283,50.9646110535],"type":"Point"}
}