{
  "type": "Feature",
  "properties": {
    "addr:full":"Avenue Bel Air 84 Box 15 Bruxelles (uccle) Bruxelles-Capitale 1180",
    "addr:housenumber":"84 box 15",
    "addr:postcode":"1180",
    "addr:street":"Avenue Bel Air",
    "iso:country":"BE",
    "sg:address":"Avenue Bel Air 84 Box 15",
    "sg:city":"Bruxelles (uccle)",
    "sg:classifiers":[
        {
            "category":"Building & Trades",
            "subcategory":"Plumbing",
            "type":"Services"
        }
    ],
    "sg:postcode":"1180",
    "sg:province":"Bruxelles-Capitale",
    "sg:tags":[
        "relocation"
    ],
    "wof:name":"Real Real Estate Company Sprl",
    "wof:placetype":"venue"
},
  "geometry": {"coordinates":[4.3628220558,50.8125801086],"type":"Point"}
}