{
  "type": "Feature",
  "properties": {
    "addr:full":"Toevluchtweg 13 Nieuwpoort (sint-joris) West-Vlaanderen 8620",
    "addr:housenumber":"13",
    "addr:postcode":"8620",
    "addr:street":"Toevluchtweg",
    "iso:country":"BE",
    "sg:address":"Toevluchtweg 13",
    "sg:city":"Nieuwpoort (sint-joris)",
    "sg:classifiers":[
        {
            "category":"Social Services",
            "type":"Services"
        }
    ],
    "sg:phone":"+32 58 24 37 82",
    "sg:postcode":"8620",
    "sg:province":"West-Vlaanderen",
    "wof:name":"Dukdalf",
    "wof:placetype":"venue"
},
  "geometry": {"coordinates":[2.7626299858,51.1271286011],"type":"Point"}
}