{
  "type": "Feature",
  "properties": {
    "iso:country":"BE",
    "sg:address":"Brassoi 3",
    "sg:city":"Berlaar",
    "sg:orig_category":"Non-Classified Establishments",
    "sg:phone":"+32 3 422 53 06",
    "sg:postcode":"2590",
    "sg:province":"Antwerpen",
    "wof:name":"Tiffanies Bvba",
    "wof:placetype":"venue"
},
  "geometry": {"coordinates":[4.6576948166,51.1151504517],"type":"Point"}
}