{
  "type": "Feature",
  "properties": {
    "addr:full":"Voorspoedstraat 23 Essen Antwerpen 2910",
    "addr:housenumber":"23",
    "addr:postcode":"2910",
    "addr:street":"Voorspoedstraat",
    "iso:country":"BE",
    "sg:address":"Voorspoedstraat 23",
    "sg:city":"Essen",
    "sg:classifiers":[
        {
            "category":"Manufacturing",
            "subcategory":"Furniture",
            "type":"Manufacturing & Wholesale Goods"
        }
    ],
    "sg:phone":"+32 475 73 65 57",
    "sg:postcode":"2910",
    "sg:province":"Antwerpen",
    "sg:tags":[
        "made",
        "-",
        "custom"
    ],
    "wof:name":"Dd",
    "wof:placetype":"venue"
},
  "geometry": {"coordinates":[4.4485697746,51.4518890381],"type":"Point"}
}