{
  "type": "Feature",
  "properties": {
    "iso:country":"BE",
    "sg:address":"Avenue Montjoie 293b1",
    "sg:city":"Ukkel",
    "sg:orig_category":"Agences d'exp\u00e9dition",
    "sg:phone":"+32 2 343 21 91",
    "sg:postcode":"1180",
    "sg:province":"Bruxelles-Capitale",
    "wof:name":"Capdeville",
    "wof:placetype":"venue"
},
  "geometry": {"coordinates":[4.3549289703,50.8112373352],"type":"Point"}
}