{
  "type": "Feature",
  "properties": {
    "addr:full":"Verenigingstraat 17-3 Oostende West-Vlaanderen 8400",
    "addr:housenumber":"17-3",
    "addr:postcode":"8400",
    "addr:street":"Verenigingstraat",
    "iso:country":"BE",
    "sg:address":"Verenigingstraat 17-3",
    "sg:city":"Oostende",
    "sg:classifiers":[
        {
            "category":"Banks & Credit Unions",
            "subcategory":"Investment Brokerage",
            "type":"Services"
        }
    ],
    "sg:phone":"+32 495 64 25 35",
    "sg:postcode":"8400",
    "sg:province":"West-Vlaanderen",
    "sg:tags":[
        "ladies'",
        "tailor",
        "tailoresses",
        "-",
        "clothing"
    ],
    "wof:name":"Maatwerk Nicole",
    "wof:placetype":"venue"
},
  "geometry": {"coordinates":[2.8990740776,51.2198982239],"type":"Point"}
}