{
  "type": "Feature",
  "properties": {
    "addr:full":"Aarschotsesteenweg 145 Leuven (wilsele) Vlaams-Brabant 3012",
    "addr:housenumber":"145",
    "addr:postcode":"3012",
    "addr:street":"Aarschotsesteenweg",
    "iso:country":"BE",
    "sg:address":"Aarschotsesteenweg 145",
    "sg:city":"Leuven (wilsele)",
    "sg:classifiers":[
        {
            "category":"Home & Garden",
            "subcategory":"Building Materials",
            "type":"Retail Goods"
        }
    ],
    "sg:phone":"+32 16 44 55 15",
    "sg:postcode":"3012",
    "sg:province":"Vlaams-Brabant",
    "sg:tags":[
        "window"
    ],
    "wof:name":"Deuraco Bvba",
    "wof:placetype":"venue"
},
  "geometry": {"coordinates":[4.7167801857,50.9162712097],"type":"Point"}
}