{
  "type": "Feature",
  "properties": {
    "iso:country":"BE",
    "sg:address":"Kasteelstraat 6",
    "sg:city":"Buggenhout",
    "sg:classifiers":[
        {
            "category":"Bakery",
            "type":"Food & Drink"
        }
    ],
    "sg:phone":"+32 52 33 20 76",
    "sg:postcode":"9255",
    "sg:province":"Oost-Vlaanderen",
    "sg:tags":[
        "confectioner",
        "baker"
    ],
    "wof:name":"Hugo & Karin",
    "wof:placetype":"venue"
},
  "geometry": {"coordinates":[4.2020058632,51.0130386353],"type":"Point"}
}