{
  "type": "Feature",
  "properties": {
    "addr:full":"Beundreef 16 Oostkamp West-Vlaanderen 8020",
    "addr:housenumber":"16",
    "addr:postcode":"8020",
    "addr:street":"Beundreef",
    "iso:country":"BE",
    "sg:address":"Beundreef 16",
    "sg:city":"Oostkamp",
    "sg:orig_category":"Produits interm\u00e9diaires Gr",
    "sg:phone":"+32 50 27 90 01",
    "sg:postcode":"8020",
    "sg:province":"West-Vlaanderen",
    "wof:name":"Beldiamond",
    "wof:placetype":"venue"
},
  "geometry": {"coordinates":[3.2181789875,51.1225776672],"type":"Point"}
}