{
  "type": "Feature",
  "properties": {
    "iso:country":"BE",
    "sg:address":"Rue Blaes 64",
    "sg:city":"Bruxelles",
    "sg:classifiers":[
        {
            "category":"Shopping",
            "subcategory":"Books",
            "type":"Retail Goods"
        }
    ],
    "sg:phone":"+32 2 343 82 57",
    "sg:postcode":"1000",
    "sg:province":"Bruxelles-Capitale",
    "sg:tags":[
        "antiquarian",
        "trade"
    ],
    "wof:name":"Dardenne D",
    "wof:placetype":"venue"
},
  "geometry": {"coordinates":[4.3495140076,50.8395767212],"type":"Point"}
}