{
  "type": "Feature",
  "properties": {
    "iso:country":"BE",
    "sg:address":"Rue Hongr\u00e9e 9",
    "sg:city":"Aywaille",
    "sg:classifiers":[
        {
            "category":"Taxi",
            "type":"Transportation"
        }
    ],
    "sg:phone":"+32 4 384 45 28",
    "sg:postcode":"4920",
    "sg:province":"Li\u00e8ge",
    "sg:tags":[
        "taxicab"
    ],
    "wof:name":"Taxi Aywaille",
    "wof:placetype":"venue"
},
  "geometry": {"coordinates":[5.6757698059,50.4738883972],"type":"Point"}
}