{
  "type": "Feature",
  "properties": {
    "addr:full":"Chauss\u00c9e De R\u00c9demont 16 La Louviere Hainaut 7100",
    "addr:housenumber":"16",
    "addr:postcode":"7100",
    "addr:street":"Chausse\u0301E De Re\u0301Demont",
    "iso:country":"BE",
    "sg:address":"Chauss\u00c9e De R\u00c9demont 16",
    "sg:city":"La Louviere",
    "sg:orig_category":"Locations de machines and \u00e9quipement pour la construction. Location de machines-outils and de mat\u00e9ri",
    "sg:phone":"+32 64 21 16 32",
    "sg:postcode":"7100",
    "sg:province":"Hainaut",
    "wof:name":"Paul Lietar",
    "wof:placetype":"venue"
},
  "geometry": {"coordinates":[4.2093777657,50.4682579041],"type":"Point"}
}