{
  "type": "Feature",
  "properties": {
    "addr:full":"Four \u00e0 Chaux 12 Onhaye Namur 5520",
    "addr:housenumber":"12",
    "addr:postcode":"5520",
    "addr:street":"A\u0300 Chaux",
    "iso:country":"BE",
    "sg:address":"Four \u00e0 Chaux 12",
    "sg:city":"Onhaye",
    "sg:classifiers":[
        {
            "category":"Arts & Performance",
            "subcategory":"Arts Center",
            "type":"Entertainment"
        }
    ],
    "sg:phone":"+32 82 64 32 00",
    "sg:postcode":"5520",
    "sg:province":"Namur",
    "sg:tags":[
        "inspection",
        "automobile",
        "-",
        "examination"
    ],
    "wof:name":"Contr\u00d4le Technique Sa",
    "wof:placetype":"venue"
},
  "geometry": {"coordinates":[4.8398251534,50.2400093079],"type":"Point"}
}