{
  "type": "Feature",
  "properties": {
    "iso:country":"BE",
    "sg:address":"Stationsstraat 17",
    "sg:city":"Denderleeuw",
    "sg:classifiers":[
        {
            "category":"Bakery",
            "type":"Food & Drink"
        }
    ],
    "sg:phone":"+32 53 66 60 69",
    "sg:postcode":"9470",
    "sg:province":"Oost-Vlaanderen",
    "sg:tags":[
        "confectioner",
        "baker"
    ],
    "wof:name":"Meert R",
    "wof:placetype":"venue"
},
  "geometry": {"coordinates":[4.0741639137,50.891040802],"type":"Point"}
}