{
  "type": "Feature",
  "properties": {
    "iso:country":"BE",
    "sg:address":"Schatakker 20",
    "sg:city":"Oudenaarde",
    "sg:orig_category":"Mat\u00e9riaux de construction Gr",
    "sg:phone":"+32 55 31 43 67",
    "sg:postcode":"9700",
    "sg:province":"Oost-Vlaanderen",
    "wof:name":"Rudy Eeckhout",
    "wof:placetype":"venue"
},
  "geometry": {"coordinates":[3.6392819881,50.860042572],"type":"Point"}
}