{
  "type": "Feature",
  "properties": {
    "iso:country":"BE",
    "sg:address":"Rue Haut-husquet 12",
    "sg:city":"Verviers",
    "sg:classifiers":[
        {
            "category":"Professional",
            "subcategory":"Accounting & Tax Preparation",
            "type":"Services"
        }
    ],
    "sg:phone":"+32 87 31 66 79",
    "sg:postcode":"4800",
    "sg:province":"Li\u00e8ge",
    "sg:tags":[
        "accountant"
    ],
    "wof:name":"Pascal Fabry",
    "wof:placetype":"venue"
},
  "geometry": {"coordinates":[5.8355879784,50.6035308838],"type":"Point"}
}