{
  "type": "Feature",
  "properties": {
    "addr:full":"Avenue Alfred Madoux 129 Bruxelles (woluwe-saint-pierre) Bruxelles-Capitale 1150",
    "addr:housenumber":"129",
    "addr:postcode":"1150",
    "addr:street":"Avenue Alfred Madoux",
    "iso:country":"BE",
    "sg:address":"Avenue Alfred Madoux 129",
    "sg:city":"Bruxelles (woluwe-saint-pierre)",
    "sg:classifiers":[
        {
            "category":"Professional",
            "subcategory":"Lawyer & Legal Services",
            "type":"Services"
        }
    ],
    "sg:phone":"+32 2 770 60 34",
    "sg:postcode":"1150",
    "sg:province":"Bruxelles-Capitale",
    "sg:tags":[
        "notary"
    ],
    "wof:name":"Panneels L",
    "wof:placetype":"venue"
},
  "geometry": {"coordinates":[4.4502911568,50.8298912048],"type":"Point"}
}