{
  "type": "Feature",
  "properties": {
    "addr:full":"Guldensporenlaan 7 Koksijde West-Vlaanderen 8670",
    "addr:housenumber":"7",
    "addr:postcode":"8670",
    "addr:street":"Guldensporenlaan",
    "iso:country":"BE",
    "sg:address":"Guldensporenlaan 7",
    "sg:city":"Koksijde",
    "sg:orig_category":"Dakwerken Loodgieterij, verwarming and sanitaire installaties",
    "sg:phone":"+32 58 51 41 95",
    "sg:postcode":"8670",
    "sg:province":"West-Vlaanderen",
    "wof:name":"Sirjacobs M.",
    "wof:placetype":"venue"
},
  "geometry": {"coordinates":[2.6935760975,51.1261825562],"type":"Point"}
}