{
  "type": "Feature",
  "properties": {
    "iso:country":"BE",
    "sg:address":"Lozermolenstraat 10",
    "sg:city":"Kruishoutem",
    "sg:orig_category":"Pain, p\u00e2tisseries and confiseries",
    "sg:phone":"+32 9 386 17 39",
    "sg:postcode":"9770",
    "sg:province":"Oost-Vlaanderen",
    "wof:name":"Erve Vandenberghe",
    "wof:placetype":"venue"
},
  "geometry": {"coordinates":[3.5394079685,50.9336433411],"type":"Point"}
}