{
  "type": "Feature",
  "properties": {
    "iso:country":"BE",
    "sg:address":"Rue Bois Frion 101",
    "sg:city":"Montigny-le-tilleul",
    "sg:classifiers":[
        {
            "category":"Social Services",
            "type":"Services"
        }
    ],
    "sg:phone":"+32 71 51 70 42",
    "sg:postcode":"6110",
    "sg:province":"Hainaut",
    "wof:name":"Institut M\u00e9dico-p\u00e9dagogique Le Baucory",
    "wof:placetype":"venue"
},
  "geometry": {"coordinates":[4.367099762,50.3794784546],"type":"Point"}
}