{
  "type": "Feature",
  "properties": {
    "addr:full":"Korte Gasthuisstraat 4 Turnhout Antwerpen 2300",
    "addr:housenumber":"4",
    "addr:postcode":"2300",
    "addr:street":"Korte Gasthuisstraat",
    "iso:country":"BE",
    "sg:address":"Korte Gasthuisstraat 4",
    "sg:city":"Turnhout",
    "sg:orig_category":"Herstelling horloges and juwelen Juwelen and horloges",
    "sg:phone":"+32 14 41 43 05",
    "sg:postcode":"2300",
    "sg:province":"Antwerpen",
    "wof:name":"Andreas Van Bruggen",
    "wof:placetype":"venue"
},
  "geometry": {"coordinates":[4.9477949142,51.3226661682],"type":"Point"}
}