{
  "type": "Feature",
  "properties": {
    "addr:full":"Sint-maartensberg 18 Bonheiden (rijmenam) Antwerpen 2820",
    "addr:housenumber":"18",
    "addr:postcode":"2820",
    "addr:street":"Sint-Maartensberg",
    "iso:country":"BE",
    "sg:address":"Sint-maartensberg 18",
    "sg:city":"Bonheiden (rijmenam)",
    "sg:classifiers":[
        {
            "category":"Bars & Pubs",
            "type":"Food & Drink"
        }
    ],
    "sg:phone":"+32 15 51 83 73",
    "sg:postcode":"2820",
    "sg:province":"Antwerpen",
    "sg:tags":[
        "tavern"
    ],
    "wof:name":"Bleekhofke",
    "wof:placetype":"venue"
},
  "geometry": {"coordinates":[4.5496602058,51.0218009949],"type":"Point"}
}