{
  "type": "Feature",
  "properties": {
    "addr:full":"Zuidstraat 50 Veurne West-Vlaanderen 8630",
    "addr:housenumber":"50",
    "addr:postcode":"8630",
    "addr:street":"Zuidstraat",
    "iso:country":"BE",
    "sg:address":"Zuidstraat 50",
    "sg:city":"Veurne",
    "sg:orig_category":"Agences de voyages",
    "sg:phone":"+32 58 31 34 57",
    "sg:postcode":"8630",
    "sg:province":"West-Vlaanderen",
    "wof:name":"Reisbureau Bruneel",
    "wof:placetype":"venue"
},
  "geometry": {"coordinates":[2.66238904,51.0700759888],"type":"Point"}
}