{
  "type": "Feature",
  "properties": {
    "addr:full":"Patronaatstraat 9 Erpe-mere (mere) Oost-Vlaanderen 9420",
    "addr:housenumber":"9",
    "addr:postcode":"9420",
    "addr:street":"Patronaatstraat;Mere Oost-Vlaanderen",
    "iso:country":"BE",
    "sg:address":"Patronaatstraat 9",
    "sg:city":"Erpe-mere (mere)",
    "sg:classifiers":[
        {
            "category":"Bars & Pubs",
            "type":"Food & Drink"
        }
    ],
    "sg:phone":"+32 53 83 44 16",
    "sg:postcode":"9420",
    "sg:province":"Oost-Vlaanderen",
    "wof:name":"Partronaat",
    "wof:placetype":"venue"
},
  "geometry": {"coordinates":[3.9695560932,50.923324585],"type":"Point"}
}