{
  "type": "Feature",
  "properties": {
    "addr:full":"Chauss\u00e9e De Helmet 62 Bruxelles (schaerbeek) Bruxelles-Capitale 1030",
    "addr:housenumber":"62",
    "addr:postcode":"1030",
    "addr:street":"Chausse\u0301E De Helmet",
    "iso:country":"BE",
    "sg:address":"Chauss\u00e9e De Helmet 62",
    "sg:city":"Bruxelles (schaerbeek)",
    "sg:classifiers":[
        {
            "category":"Banks & Credit Unions",
            "subcategory":"Investment Brokerage",
            "type":"Services"
        }
    ],
    "sg:phone":"+32 2 215 51 22",
    "sg:postcode":"1030",
    "sg:province":"Bruxelles-Capitale",
    "sg:tags":[
        "coil",
        "electric",
        "winding"
    ],
    "wof:name":"Bobelec Sprl",
    "wof:placetype":"venue"
},
  "geometry": {"coordinates":[4.382393837,50.8700485229],"type":"Point"}
}