{
  "type": "Feature",
  "properties": {
    "addr:full":"Koestaartstraat 7 Kortrijk West-Vlaanderen 8500",
    "addr:housenumber":"7",
    "addr:postcode":"8500",
    "addr:street":"Koestaartstraat",
    "iso:country":"BE",
    "sg:address":"Koestaartstraat 7",
    "sg:city":"Kortrijk",
    "sg:classifiers":[
        {
            "category":"Professional",
            "subcategory":"Printing & Photocopies",
            "type":"Services"
        }
    ],
    "sg:phone":"+32 56 21 09 86",
    "sg:postcode":"8500",
    "sg:province":"West-Vlaanderen",
    "sg:tags":[
        "engraving"
    ],
    "wof:name":"Im Press-colop",
    "wof:placetype":"venue"
},
  "geometry": {"coordinates":[3.2655339241,50.8287734985],"type":"Point"}
}