{
  "type": "Feature",
  "properties": {
    "addr:full":"Diestsesteenweg 20 Tienen Vlaams-Brabant 3300",
    "addr:housenumber":"20",
    "addr:postcode":"3300",
    "addr:street":"Diestsesteenweg",
    "iso:country":"BE",
    "sg:address":"Diestsesteenweg 20",
    "sg:city":"Tienen",
    "sg:classifiers":[
        {
            "category":"Real Estate",
            "subcategory":"Real Estate Services",
            "type":"Services"
        }
    ],
    "sg:phone":"+32 16 78 00 87",
    "sg:postcode":"3300",
    "sg:province":"Vlaams-Brabant",
    "wof:name":"Brabant Immo",
    "wof:placetype":"venue"
},
  "geometry": {"coordinates":[4.9351391792,50.8141975403],"type":"Point"}
}