{
  "type": "Feature",
  "properties": {
    "addr:full":"Watering 11 Arendonk Antwerpen 2370",
    "addr:housenumber":"11",
    "addr:postcode":"2370",
    "addr:street":"Watering",
    "iso:country":"BE",
    "sg:address":"Watering 11",
    "sg:city":"Arendonk",
    "sg:orig_category":"Tankcleaning",
    "sg:phone":"+32 3 440 12 86",
    "sg:postcode":"2370",
    "sg:province":"Antwerpen",
    "wof:name":"Liekens Nv",
    "wof:placetype":"venue"
},
  "geometry": {"coordinates":[5.125702858,51.3120269775],"type":"Point"}
}