{
  "type": "Feature",
  "properties": {
    "iso:country":"BE",
    "sg:address":"Kouter 42",
    "sg:city":"Zedelgem",
    "sg:orig_category":"Travaux de pl\u00e2trage",
    "sg:phone":"+32 50 20 86 60",
    "sg:postcode":"8211",
    "sg:province":"West-Vlaanderen",
    "wof:name":"Van Grieken",
    "wof:placetype":"venue"
},
  "geometry": {"coordinates":[3.081649065,51.1193008423],"type":"Point"}
}