{
  "type": "Feature",
  "properties": {
    "addr:full":"Chauss\u00e9e De Mons 29 La Louvi\u00e8re (haine-saint-pierre) Hainaut 7100",
    "addr:housenumber":"29",
    "addr:postcode":"7100",
    "addr:street":"Chausse\u0301E De Mons",
    "iso:country":"BE",
    "sg:address":"Chauss\u00e9e De Mons 29",
    "sg:city":"La Louvi\u00e8re (haine-saint-pierre)",
    "sg:classifiers":[
        {
            "category":"Bakery",
            "type":"Food & Drink"
        }
    ],
    "sg:phone":"+32 64 21 48 43",
    "sg:postcode":"7100",
    "sg:province":"Hainaut",
    "sg:tags":[
        "confectioner",
        "baker"
    ],
    "wof:name":"P'tit Boulanger (au)",
    "wof:placetype":"venue"
},
  "geometry": {"coordinates":[4.1995410919,50.4645805359],"type":"Point"}
}