{
  "type": "Feature",
  "properties": {
    "addr:full":"Avenue Emile Herman 58 Manage (fayt-lez-manage) Hainaut 7170",
    "addr:housenumber":"58",
    "addr:postcode":"7170",
    "addr:street":"Avenue Emile Herman",
    "iso:country":"BE",
    "sg:address":"Avenue Emile Herman 58",
    "sg:city":"Manage (fayt-lez-manage)",
    "sg:classifiers":[
        {
            "category":"Shopping",
            "subcategory":"Books",
            "type":"Retail Goods"
        }
    ],
    "sg:phone":"+32 64 54 81 71",
    "sg:postcode":"7170",
    "sg:province":"Hainaut",
    "sg:tags":[
        "bookseller"
    ],
    "wof:name":"Faytoise (librairie)",
    "wof:placetype":"venue"
},
  "geometry": {"coordinates":[4.2265582085,50.4899711609],"type":"Point"}
}