{
  "type": "Feature",
  "properties": {
    "addr:full":"Rue Des Br\u00dbl\u00c9s 12 Quevy Hainaut 7040",
    "addr:housenumber":"12",
    "addr:postcode":"7040",
    "addr:street":"Rue Des Bru\u0302Le\u0301S;Hainaut",
    "iso:country":"BE",
    "sg:address":"Rue Des Br\u00dbl\u00c9s 12",
    "sg:city":"Quevy",
    "sg:orig_category":"Brood, gebak and snoepgoed",
    "sg:phone":"+32 65 56 83 26",
    "sg:postcode":"7040",
    "sg:province":"Hainaut",
    "wof:name":"Ghislain Devos",
    "wof:placetype":"venue"
},
  "geometry": {"coordinates":[3.9365570545,50.3688201904],"type":"Point"}
}