{
  "type": "Feature",
  "properties": {
    "addr:full":"Rue Des Combattants 191ba Oreye Li\u00e8ge 4360",
    "addr:postcode":"4360",
    "addr:street":"Rue Des Combattants 191Ba",
    "iso:country":"BE",
    "sg:address":"Rue Des Combattants 191ba",
    "sg:city":"Oreye",
    "sg:orig_category":"Herstellingen and onderhoud van auto's",
    "sg:phone":"+32 19 67 82 07",
    "sg:postcode":"4360",
    "sg:province":"Li\u00e8ge",
    "wof:name":"Dany Lemaire",
    "wof:placetype":"venue"
},
  "geometry": {"coordinates":[5.3682498932,50.7317695618],"type":"Point"}
}