{
  "type": "Feature",
  "properties": {
    "addr:full":"Ambachtstr 6 Londerzeel Vlaams-Brabant 1840",
    "addr:housenumber":"6",
    "addr:postcode":"1840",
    "addr:street":"Ambachtstr",
    "iso:country":"BE",
    "sg:address":"Ambachtstr 6",
    "sg:city":"Londerzeel",
    "sg:classifiers":[
        {
            "category":"Food & Beverages",
            "subcategory":"Groceries & Convenience Stores",
            "type":"Retail Goods"
        }
    ],
    "sg:phone":"+32 52 31 95 24",
    "sg:postcode":"1840",
    "sg:province":"Vlaams-Brabant",
    "sg:tags":[
        "product",
        "grain",
        "cereal",
        "related"
    ],
    "wof:name":"Orffa Belgium Nv",
    "wof:placetype":"venue"
},
  "geometry": {"coordinates":[4.3216228485,51.0160255432],"type":"Point"}
}