{
  "type": "Feature",
  "properties": {
    "iso:country":"BE",
    "sg:address":"Goorlei 19b",
    "sg:city":"Heist-op-den-berg",
    "sg:classifiers":[
        {
            "category":"Building & Trades",
            "subcategory":"Construction",
            "type":"Services"
        }
    ],
    "sg:phone":"+32 15 22 22 07",
    "sg:postcode":"2220",
    "sg:province":"Antwerpen",
    "sg:tags":[
        "stucco",
        "contractor"
    ],
    "wof:name":"Van Dyck K",
    "wof:placetype":"venue"
},
  "geometry": {"coordinates":[4.7373218536,51.042137146],"type":"Point"}
}