{
  "type": "Feature",
  "properties": {
    "addr:full":"Rue Henin 69 Farciennes Hainaut 6240",
    "addr:housenumber":"69",
    "addr:postcode":"6240",
    "addr:street":"Rue Henin",
    "iso:country":"BE",
    "sg:address":"Rue Henin 69",
    "sg:city":"Farciennes",
    "sg:classifiers":[
        {
            "category":"Retail",
            "subcategory":"Funeral Services",
            "type":"Services"
        }
    ],
    "sg:phone":"+32 71 38 06 26",
    "sg:postcode":"6240",
    "sg:province":"Hainaut",
    "sg:tags":[
        "director"
    ],
    "wof:name":"Ureel Sprl",
    "wof:placetype":"venue"
},
  "geometry": {"coordinates":[4.5456199646,50.4273376465],"type":"Point"}
}