{
  "type": "Feature",
  "properties": {
    "addr:full":"Gaversesteenweg 644 Merelbeke Oost-Vlaanderen 9820",
    "addr:housenumber":"644",
    "addr:postcode":"9820",
    "addr:street":"Gaversesteenweg",
    "iso:country":"BE",
    "sg:address":"Gaversesteenweg 644",
    "sg:city":"Merelbeke",
    "sg:orig_category":"Eleveurs de bovins",
    "sg:phone":"+32 9 384 16 80",
    "sg:postcode":"9820",
    "sg:province":"Oost-Vlaanderen",
    "wof:name":"Steyaert",
    "wof:placetype":"venue"
},
  "geometry": {"coordinates":[3.719219923,50.9737091064],"type":"Point"}
}