{
  "type": "Feature",
  "properties": {
    "iso:country":"BE",
    "sg:address":"Stationsstraat 19",
    "sg:city":"Ieper",
    "sg:orig_category":"Equipement photographique. Mat\u00e9riel de T\u00e9l\u00e9communication. Studios photographiques",
    "sg:phone":"+32 57 21 54 33",
    "sg:postcode":"8900",
    "sg:province":"West-Vlaanderen",
    "wof:name":"Top Camera De Witte Fotografie",
    "wof:placetype":"venue"
},
  "geometry": {"coordinates":[2.8809039593,50.8489151001],"type":"Point"}
}