{
  "type": "Feature",
  "properties": {
    "iso:country":"BE",
    "sg:address":"Jos Coveliersstraat 52",
    "sg:city":"Hove",
    "sg:classifiers":[
        {
            "category":"Professional",
            "subcategory":"Computer Services",
            "type":"Services"
        }
    ],
    "sg:phone":"+32 3 455 87 18",
    "sg:postcode":"2540",
    "sg:province":"Antwerpen",
    "sg:tags":[
        "-",
        "processing",
        "data",
        "software"
    ],
    "wof:name":"Task",
    "wof:placetype":"venue"
},
  "geometry": {"coordinates":[4.4844269753,51.1530456543],"type":"Point"}
}