{
  "type": "Feature",
  "properties": {
    "addr:full":"Leeuw Van Vlaanderenlaan 13 Waarschoot Oost-Vlaanderen 9950",
    "addr:housenumber":"13",
    "addr:postcode":"9950",
    "addr:street":"Leeuw Van Vlaanderenlaan",
    "iso:country":"BE",
    "sg:address":"Leeuw Van Vlaanderenlaan 13",
    "sg:city":"Waarschoot",
    "sg:classifiers":[
        {
            "category":"Autos & Motor Vehicles",
            "subcategory":"Automobile Sales",
            "type":"Retail Goods"
        }
    ],
    "sg:phone":"+32 495 22 96 70",
    "sg:postcode":"9950",
    "sg:province":"Oost-Vlaanderen",
    "sg:tags":[
        "car",
        "used",
        "-"
    ],
    "wof:name":"Cdr Cars",
    "wof:placetype":"venue"
},
  "geometry": {"coordinates":[3.6069009304,51.1312332153],"type":"Point"}
}