{
  "type": "Feature",
  "properties": {
    "addr:full":"Genendries 38 Riemst (millen) Limburg 3770",
    "addr:housenumber":"38",
    "addr:postcode":"3770",
    "addr:street":"Genendries",
    "iso:country":"BE",
    "sg:address":"Genendries 38",
    "sg:city":"Riemst (millen)",
    "sg:classifiers":[
        {
            "category":"Retail",
            "subcategory":"Veterinary Services",
            "type":"Services"
        }
    ],
    "sg:phone":"+32 12 23 34 48",
    "sg:postcode":"3770",
    "sg:province":"Limburg",
    "sg:tags":[
        "veterinarian"
    ],
    "wof:name":"Beckers J",
    "wof:placetype":"venue"
},
  "geometry": {"coordinates":[5.555398941,50.7865753174],"type":"Point"}
}