{
  "type": "Feature",
  "properties": {
    "addr:full":"Rue De La Pr\u00c9voyance 48 Namur Namur 5000",
    "addr:housenumber":"48",
    "addr:postcode":"5000",
    "addr:street":"Rue De La Pre\u0301Voyance",
    "iso:country":"BE",
    "sg:address":"Rue De La Pr\u00c9voyance 48",
    "sg:city":"Namur",
    "sg:orig_category":"Elektrische installaties voor woningen",
    "sg:phone":"+32 81 73 76 45",
    "sg:postcode":"5000",
    "sg:province":"Namur",
    "wof:name":"Etienne Delbaen",
    "wof:placetype":"venue"
},
  "geometry": {"coordinates":[4.8425450325,50.4645309448],"type":"Point"}
}