{
  "type": "Feature",
  "properties": {
    "iso:country":"BE",
    "sg:address":"Rue Charles Perin 1c",
    "sg:city":"Mons (ghlin)",
    "sg:classifiers":[
        {
            "category":"Taxi",
            "type":"Transportation"
        }
    ],
    "sg:postcode":"7011",
    "sg:province":"Hainaut",
    "sg:tags":[
        "taxicab"
    ],
    "wof:name":"Taxis Milie Scrl",
    "wof:placetype":"venue"
},
  "geometry": {"coordinates":[3.912539959,50.4712982178],"type":"Point"}
}