{
  "type": "Feature",
  "properties": {
    "addr:full":"Rue De La Vieille Forge 27ba Tinlot Li\u00e8ge 4557",
    "addr:housenumber":"27ba",
    "addr:postcode":"4557",
    "addr:street":"Rue De La Vieille Forge",
    "iso:country":"BE",
    "sg:address":"Rue De La Vieille Forge 27ba",
    "sg:city":"Tinlot",
    "sg:orig_category":"Landmeters",
    "sg:phone":"+32 85 51 15 83",
    "sg:postcode":"4557",
    "sg:province":"Li\u00e8ge",
    "wof:name":"Marcel Ponthier",
    "wof:placetype":"venue"
},
  "geometry": {"coordinates":[5.4168038368,50.4771499634],"type":"Point"}
}