{
  "type": "Feature",
  "properties": {
    "iso:country":"BE",
    "sg:address":"73",
    "sg:city":"Demeurslaan 1654 Huizingen",
    "sg:orig_category":"Miscellaneous Products",
    "sg:phone":"+32 2 356 57 08",
    "sg:postcode":"73",
    "wof:name":"Etabl. H. Vanzeebroeck",
    "wof:placetype":"venue"
},
  "geometry": {"coordinates":[4.2667608261,50.7532844543],"type":"Point"}
}