{
  "type": "Feature",
  "properties": {
    "iso:country":"BE",
    "sg:address":"Kortrijkstraat 107",
    "sg:city":"Ingelmunster",
    "sg:classifiers":[
        {
            "category":"Building & Trades",
            "subcategory":"Construction",
            "type":"Services"
        }
    ],
    "sg:phone":"+32 51 30 40 78",
    "sg:postcode":"8770",
    "sg:province":"West-Vlaanderen",
    "sg:tags":[
        "carpenter"
    ],
    "wof:name":"Mommerency N",
    "wof:placetype":"venue"
},
  "geometry": {"coordinates":[3.2605659962,50.9078407288],"type":"Point"}
}