{
  "type": "Feature",
  "properties": {
    "iso:country":"BE",
    "sg:address":"Sint-jakobsstraat 34c",
    "sg:city":"Brugge",
    "sg:orig_category":"Instituts de beaut\u00e9. Pensions de famille. Centres de relaxation and bien-\u00eatre",
    "sg:phone":"+32 50 33 09 37",
    "sg:postcode":"8000",
    "sg:province":"West-Vlaanderen",
    "wof:name":"Beauty Shop",
    "wof:placetype":"venue"
},
  "geometry": {"coordinates":[3.2215681076,51.2100410461],"type":"Point"}
}