{
  "type": "Feature",
  "properties": {
    "addr:full":"Rue Des Tongres 8 Bruxelles (etterbeek) Bruxelles-Capitale 1040",
    "addr:housenumber":"8",
    "addr:postcode":"1040",
    "addr:street":"Rue Des Tongres",
    "iso:country":"BE",
    "sg:address":"Rue Des Tongres 8",
    "sg:city":"Bruxelles (etterbeek)",
    "sg:classifiers":[
        {
            "category":"Professional",
            "subcategory":"Testing Lab",
            "type":"Services"
        }
    ],
    "sg:phone":"+32 2 733 09 19",
    "sg:postcode":"1040",
    "sg:province":"Bruxelles-Capitale",
    "sg:tags":[
        "chemist"
    ],
    "wof:name":"Cinquantenaire",
    "wof:placetype":"venue"
},
  "geometry": {"coordinates":[4.3992037773,50.8396110535],"type":"Point"}
}