{
  "type": "Feature",
  "properties": {
    "addr:full":"Rue Du Bemel 168 Bruxelles (woluwe-saint-pierre) Bruxelles-Capitale 1150",
    "addr:housenumber":"168",
    "addr:postcode":"1150",
    "addr:street":"Rue Du Bemel",
    "iso:country":"BE",
    "sg:address":"Rue Du Bemel 168",
    "sg:city":"Bruxelles (woluwe-saint-pierre)",
    "sg:classifiers":[
        {
            "category":"Travel",
            "subcategory":"Hotels & Motels",
            "type":"Entertainment"
        }
    ],
    "sg:phone":"+32 2 771 71 30",
    "sg:postcode":"1150",
    "sg:province":"Bruxelles-Capitale",
    "sg:tags":[
        "supply",
        "hotels",
        "catering"
    ],
    "wof:name":"Europe M\u00e9nager Sprl",
    "wof:placetype":"venue"
},
  "geometry": {"coordinates":[4.4131641388,50.8303947449],"type":"Point"}
}