{
  "type": "Feature",
  "properties": {
    "addr:full":"Koolskampstraat 28 Pittem West-Vlaanderen 8740",
    "addr:housenumber":"28",
    "addr:postcode":"8740",
    "addr:street":"Koolskampstraat",
    "iso:country":"BE",
    "sg:address":"Koolskampstraat 28",
    "sg:city":"Pittem",
    "sg:orig_category":"Entretien and r\u00e9parations de voitures",
    "sg:phone":"+32 51 46 68 48",
    "sg:postcode":"8740",
    "sg:province":"West-Vlaanderen",
    "wof:name":"Erik Vande Vyvere",
    "wof:placetype":"venue"
},
  "geometry": {"coordinates":[3.2585549355,50.9952850342],"type":"Point"}
}