{
  "type": "Feature",
  "properties": {
    "addr:full":"Voskenslaan 362 Gent Oost-Vlaanderen 9000",
    "addr:housenumber":"362",
    "addr:postcode":"9000",
    "addr:street":"Voskenslaan;Oost-Vlaanderen",
    "iso:country":"BE",
    "sg:address":"Voskenslaan 362",
    "sg:city":"Gent",
    "sg:orig_category":"Enseignement secondaire g\u00e9n\u00e9ral",
    "sg:phone":"+32 9 220 08 66",
    "sg:postcode":"9000",
    "sg:province":"Oost-Vlaanderen",
    "wof:name":"S.b.s.o.",
    "wof:placetype":"venue"
},
  "geometry": {"coordinates":[3.7060370445,51.0289039612],"type":"Point"}
}