{
  "type": "Feature",
  "properties": {
    "addr:full":"Basilieklaan 78 Sint-agatha-berchem/berchem-sainte-agathe Bruxelles-Capitale 1082",
    "addr:housenumber":"78",
    "addr:postcode":"1082",
    "addr:street":"Basilieklaan;/",
    "iso:country":"BE",
    "sg:address":"Basilieklaan 78",
    "sg:city":"Sint-agatha-berchem/berchem-sainte-agathe",
    "sg:orig_category":"Deurwaarders",
    "sg:phone":"+32 2 465 91 98",
    "sg:postcode":"1082",
    "sg:province":"Bruxelles-Capitale",
    "wof:name":"Fr\u00c9d\u00c9ric De Mulder",
    "wof:placetype":"venue"
},
  "geometry": {"coordinates":[4.3046631813,50.8640441895],"type":"Point"}
}