{
  "type": "Feature",
  "properties": {
    "iso:country":"BE",
    "sg:address":"Rue Sous La Vaux 37",
    "sg:city":"Eghezee",
    "sg:orig_category":"Woningbouw",
    "sg:phone":"+32 81 81 17 50",
    "sg:postcode":"5310",
    "sg:province":"Namur",
    "wof:name":"A. Louis",
    "wof:placetype":"venue"
},
  "geometry": {"coordinates":[4.8990688324,50.6090431213],"type":"Point"}
}