{
  "type": "Feature",
  "properties": {
    "addr:full":"Grand-rue 107 Tintigny Luxembourg 6730",
    "addr:housenumber":"107",
    "addr:postcode":"6730",
    "addr:street":"Grand-Rue",
    "iso:country":"BE",
    "sg:address":"Grand-rue 107",
    "sg:city":"Tintigny",
    "sg:orig_category":"Eleveurs de bovins",
    "sg:phone":"+32 63 44 48 83",
    "sg:postcode":"6730",
    "sg:province":"Luxembourg",
    "wof:name":"Pierre Ansay",
    "wof:placetype":"venue"
},
  "geometry": {"coordinates":[5.5108327866,49.6835517883],"type":"Point"}
}