{
  "type": "Feature",
  "properties": {
    "addr:full":"Dendermondsesteenweg 769 Destelbergen Oost-Vlaanderen 9070",
    "addr:housenumber":"769",
    "addr:postcode":"9070",
    "addr:street":"Dendermondsesteenweg",
    "iso:country":"BE",
    "sg:address":"Dendermondsesteenweg 769",
    "sg:city":"Destelbergen",
    "sg:orig_category":"Animaux domestiques and accessoires",
    "sg:phone":"+32 475 36 68 50",
    "sg:postcode":"9070",
    "sg:province":"Oost-Vlaanderen",
    "wof:name":"Van Watermeulen",
    "wof:placetype":"venue"
},
  "geometry": {"coordinates":[3.8206439018,51.059299469],"type":"Point"}
}