{
  "type": "Feature",
  "properties": {
    "addr:full":"Grote Markt 12 Blankenberge West-Vlaanderen 8370",
    "addr:housenumber":"12",
    "addr:postcode":"8370",
    "addr:street":"Grote Markt",
    "iso:country":"BE",
    "sg:address":"Grote Markt 12",
    "sg:city":"Blankenberge",
    "sg:classifiers":[
        {
            "category":"Cafe",
            "type":"Food & Drink"
        }
    ],
    "sg:phone":"+32 50 41 19 78",
    "sg:postcode":"8370",
    "sg:province":"West-Vlaanderen",
    "sg:tags":[
        "caf\u00e9s"
    ],
    "wof:name":"Caf\u00c9 De La Bourse",
    "wof:placetype":"venue"
},
  "geometry": {"coordinates":[3.1250970364,51.3134803772],"type":"Point"}
}