{
  "type": "Feature",
  "properties": {
    "addr:full":"Viconiastraat 8 Diksmuide West-Vlaanderen 8600",
    "addr:housenumber":"8",
    "addr:postcode":"8600",
    "addr:street":"Viconiastraat",
    "iso:country":"BE",
    "sg:address":"Viconiastraat 8",
    "sg:city":"Diksmuide",
    "sg:orig_category":"Eleveurs de volaille",
    "sg:phone":"+32 51 55 55 65",
    "sg:postcode":"8600",
    "sg:province":"West-Vlaanderen",
    "wof:name":"Martin Rebry",
    "wof:placetype":"venue"
},
  "geometry": {"coordinates":[2.8275530338,51.0591430664],"type":"Point"}
}