{
  "type": "Feature",
  "properties": {
    "iso:country":"BE",
    "sg:address":"Groenplein 6",
    "sg:city":"Hasselt",
    "sg:classifiers":[
        {
            "category":"Education",
            "subcategory":"School",
            "type":"Public Place"
        }
    ],
    "sg:phone":"+32 11 29 43 20",
    "sg:postcode":"3500",
    "sg:province":"Limburg",
    "sg:tags":[
        "secondary"
    ],
    "wof:name":"Vrij Technisch Instituut",
    "wof:placetype":"venue"
},
  "geometry": {"coordinates":[5.3365311623,50.931312561],"type":"Point"}
}