{
  "type": "Feature",
  "properties": {
    "addr:full":"Peerderbaan 45 Meeuwen-gruitrode (meeuwen) Limburg 3670",
    "addr:housenumber":"45",
    "addr:postcode":"3670",
    "addr:street":"Peerderbaan",
    "iso:country":"BE",
    "sg:address":"Peerderbaan 45",
    "sg:city":"Meeuwen-gruitrode (meeuwen)",
    "sg:classifiers":[
        {
            "category":"Home & Garden",
            "subcategory":"Carpets & Floor Coverings",
            "type":"Retail Goods"
        }
    ],
    "sg:phone":"+32 11 79 16 62",
    "sg:postcode":"3670",
    "sg:province":"Limburg",
    "sg:tags":[
        "parquet"
    ],
    "wof:name":"Jansen Doe-het-zelf Nv",
    "wof:placetype":"venue"
},
  "geometry": {"coordinates":[5.501262188,51.1115341187],"type":"Point"}
}