{
  "type": "Feature",
  "properties": {
    "iso:country":"BE",
    "sg:address":"Chauss\u00c9e Roi Baudouin 239",
    "sg:city":"Mons",
    "sg:classifiers":[
        {
            "category":"Insurance",
            "subcategory":"Insurance Agent",
            "type":"Services"
        }
    ],
    "sg:phone":"+32 65 87 46 45",
    "sg:postcode":"7031",
    "sg:province":"Hainaut",
    "sg:tags":[
        "verzekeringsmakelaars",
        "expert"
    ],
    "wof:name":"Fiscomas",
    "wof:placetype":"venue"
},
  "geometry": {"coordinates":[4.0398697853,50.4295654297],"type":"Point"}
}