{
  "type": "Feature",
  "properties": {
    "iso:country":"BE",
    "sg:address":"Bosdellestraat 71",
    "sg:city":"Zaventem",
    "sg:classifiers":[
        {
            "category":"Recreation",
            "type":"Entertainment"
        }
    ],
    "sg:phone":"+32 2 731 10 18",
    "sg:postcode":"1933",
    "sg:province":"Vlaams-Brabant",
    "sg:tags":[
        "diver",
        "amusement"
    ],
    "wof:name":"Momo",
    "wof:placetype":"venue"
},
  "geometry": {"coordinates":[4.5206608772,50.8648147583],"type":"Point"}
}