{
  "type": "Feature",
  "properties": {
    "iso:country":"BE",
    "sg:address":"Chemin Des Wallants 1",
    "sg:city":"Dour",
    "sg:orig_category":"Non-Classified Establishments",
    "sg:phone":"+32 65 63 35 49",
    "sg:postcode":"7370",
    "sg:province":"Hainaut",
    "wof:name":"la Province Salart Sprl",
    "wof:placetype":"venue"
},
  "geometry": {"coordinates":[3.7906448841,50.4054031372],"type":"Point"}
}