{
  "type": "Feature",
  "properties": {
    "addr:full":"Bissegemsestraat 147 Kortrijk (bissegem) West-Vlaanderen 8501",
    "addr:housenumber":"147",
    "addr:postcode":"8501",
    "addr:street":"Bissegemsestraat",
    "iso:country":"BE",
    "sg:address":"Bissegemsestraat 147",
    "sg:city":"Kortrijk (bissegem)",
    "sg:classifiers":[
        {
            "category":"Building & Trades",
            "subcategory":"Construction",
            "type":"Services"
        }
    ],
    "sg:phone":"+32 56 35 84 74",
    "sg:postcode":"8501",
    "sg:province":"West-Vlaanderen",
    "sg:tags":[
        "installation",
        "-",
        "central",
        "heating"
    ],
    "wof:name":"Elsys Engineering Bvba",
    "wof:placetype":"venue"
},
  "geometry": {"coordinates":[3.2345840931,50.8268013],"type":"Point"}
}