{
  "type": "Feature",
  "properties": {
    "addr:full":"Pav\u00c9 Du Roeulx 0 La Louviere Hainaut 7110",
    "addr:housenumber":"0",
    "addr:postcode":"7110",
    "iso:country":"BE",
    "sg:address":"Pav\u00c9 Du Roeulx 0",
    "sg:city":"La Louviere",
    "sg:orig_category":"Dameskledingzaken",
    "sg:phone":"+32 64 67 15 00",
    "sg:postcode":"7110",
    "sg:province":"Hainaut",
    "wof:name":"Thermibel",
    "wof:placetype":"venue"
},
  "geometry": {"coordinates":[4.1505050659,50.4826698303],"type":"Point"}
}