{
  "type": "Feature",
  "properties": {
    "addr:full":"Tieltsesteenweg 197 Eeklo Oost-Vlaanderen 9900",
    "addr:housenumber":"197",
    "addr:postcode":"9900",
    "addr:street":"Tieltsesteenweg",
    "iso:country":"BE",
    "sg:address":"Tieltsesteenweg 197",
    "sg:city":"Eeklo",
    "sg:classifiers":[
        {
            "category":"Manufacturing",
            "subcategory":"Metals",
            "type":"Manufacturing & Wholesale Goods"
        }
    ],
    "sg:phone":"+32 9 377 65 49",
    "sg:postcode":"9900",
    "sg:province":"Oost-Vlaanderen",
    "sg:tags":[
        "work",
        "pressing",
        "stamping"
    ],
    "wof:name":"A N C Bvba",
    "wof:placetype":"venue"
},
  "geometry": {"coordinates":[3.5501520634,51.1784286499],"type":"Point"}
}