{
  "type": "Feature",
  "properties": {
    "addr:full":"Rue Des Argili\u00e8res Li\u00e8ge 1 (jupille-sur-meuse) Li\u00e8ge 4020",
    "addr:housenumber":"1",
    "addr:postcode":"4020",
    "addr:street":"Rue Des Argilie\u0300Res Lie\u0300Ge",
    "iso:country":"BE",
    "sg:address":"Rue Des Argili\u00e8res",
    "sg:city":"Li\u00e8ge 1 (jupille-sur-meuse)",
    "sg:classifiers":[
        {
            "category":"Arena",
            "subcategory":"Sports Club",
            "type":"Entertainment"
        }
    ],
    "sg:phone":"+32 4 370 63 31",
    "sg:postcode":"4020",
    "sg:province":"Li\u00e8ge",
    "wof:name":"Royal Avenir Jupille Bc",
    "wof:placetype":"venue"
},
  "geometry": {"coordinates":[5.6333642006,50.64402771],"type":"Point"}
}