{
  "type": "Feature",
  "properties": {
    "addr:full":"Deinsesteenweg 256 Tielt West-Vlaanderen 8700",
    "addr:housenumber":"256",
    "addr:postcode":"8700",
    "addr:street":"Deinsesteenweg",
    "iso:country":"BE",
    "sg:address":"Deinsesteenweg 256",
    "sg:city":"Tielt",
    "sg:orig_category":"Pharmaciens",
    "sg:phone":"+32 51 63 47 93",
    "sg:postcode":"8700",
    "sg:province":"West-Vlaanderen",
    "wof:name":"Apotheek Vandenhende",
    "wof:placetype":"venue"
},
  "geometry": {"coordinates":[3.3780350685,50.9952201843],"type":"Point"}
}