{
  "type": "Feature",
  "properties": {
    "addr:full":"Rijksweg 314 Wielsbeke West-Vlaanderen 8710",
    "addr:housenumber":"314",
    "addr:postcode":"8710",
    "addr:street":"Rijksweg;West-Vlaanderen",
    "iso:country":"BE",
    "sg:address":"Rijksweg 314",
    "sg:city":"Wielsbeke",
    "sg:classifiers":[
        {
            "category":"Government",
            "subcategory":"Police Station",
            "type":"Public Place"
        }
    ],
    "sg:phone":"+32 56 66 47 57",
    "sg:postcode":"8710",
    "sg:province":"West-Vlaanderen",
    "sg:tags":[
        "gendarmerie"
    ],
    "wof:name":"Federale Politie",
    "wof:placetype":"venue"
},
  "geometry": {"coordinates":[3.3737509251,50.9109611511],"type":"Point"}
}