{
  "type": "Feature",
  "properties": {
    "iso:country":"BE",
    "sg:address":"Dilsenweg 7",
    "sg:city":"Opoeteren",
    "sg:orig_category":"Royal Canin. Fleurs and plantes. Animaux domestiques and accessoires. Articles de jardin. Souvenirs ",
    "sg:phone":"+32 89 86 47 43",
    "sg:postcode":"3680",
    "sg:province":"Limburg",
    "wof:name":"Garden Center Mulders Nv",
    "wof:placetype":"venue"
},
  "geometry": {"coordinates":[5.791285038,51.0954208374],"type":"Point"}
}