{
  "type": "Feature",
  "properties": {
    "iso:country":"BE",
    "sg:address":"Voortstraat 78",
    "sg:city":"Heusden-zolder (heusden)",
    "sg:classifiers":[
        {
            "category":"Shopping",
            "subcategory":"Florist",
            "type":"Retail Goods"
        }
    ],
    "sg:phone":"+32 11 43 62 89",
    "sg:postcode":"3550",
    "sg:province":"Limburg",
    "sg:tags":[
        "-",
        "supply"
    ],
    "wof:name":"Jori",
    "wof:placetype":"venue"
},
  "geometry": {"coordinates":[5.3139648438,51.0231018066],"type":"Point"}
}