{
  "type": "Feature",
  "properties": {
    "iso:country":"BE",
    "sg:address":"Schanker 25",
    "sg:city":"Essen",
    "sg:orig_category":"Woningbouw",
    "sg:phone":"+32 3 667 55 90",
    "sg:postcode":"2910",
    "sg:province":"Antwerpen",
    "wof:name":"Lambregts",
    "wof:placetype":"venue"
},
  "geometry": {"coordinates":[4.4852547646,51.46118927],"type":"Point"}
}