{
  "type": "Feature",
  "properties": {
    "addr:full":"Vlasbloemstraat 69 Sint-niklaas Oost-Vlaanderen 9100",
    "addr:housenumber":"69",
    "addr:postcode":"9100",
    "addr:street":"Vlasbloemstraat",
    "iso:country":"BE",
    "sg:address":"Vlasbloemstraat 69",
    "sg:city":"Sint-niklaas",
    "sg:classifiers":[
        {
            "category":"Insurance",
            "subcategory":"Life Insurance",
            "type":"Services"
        }
    ],
    "sg:phone":"+32 3 776 50 27",
    "sg:postcode":"9100",
    "sg:province":"Oost-Vlaanderen",
    "sg:tags":[
        "assurance"
    ],
    "wof:name":"Assuwaas",
    "wof:placetype":"venue"
},
  "geometry": {"coordinates":[4.1845607758,51.1933364868],"type":"Point"}
}