{
  "type": "Feature",
  "properties": {
    "addr:full":"Route Du Val 11 Clavier Li\u00e8ge 4560",
    "addr:housenumber":"11",
    "addr:postcode":"4560",
    "addr:street":"Route Du Val",
    "iso:country":"BE",
    "sg:address":"Route Du Val 11",
    "sg:city":"Clavier",
    "sg:classifiers":[
        {
            "category":"Professional",
            "subcategory":"Lawyer & Legal Services",
            "type":"Services"
        }
    ],
    "sg:phone":"+32 85 41 30 92",
    "sg:postcode":"4560",
    "sg:province":"Li\u00e8ge",
    "wof:name":"Brisbois Michel",
    "wof:placetype":"venue"
},
  "geometry": {"coordinates":[5.3166952133,50.4274215698],"type":"Point"}
}