{
  "type": "Feature",
  "properties": {
    "addr:full":"Boekhoutstraat 14 Oosterzele Oost-Vlaanderen 9860",
    "addr:housenumber":"14",
    "addr:postcode":"9860",
    "addr:street":"Boekhoutstraat;Oost-Vlaanderen",
    "iso:country":"BE",
    "sg:address":"Boekhoutstraat 14",
    "sg:city":"Oosterzele",
    "sg:orig_category":"Groententeelt",
    "sg:phone":"+32 9 362 55 94",
    "sg:postcode":"9860",
    "sg:province":"Oost-Vlaanderen",
    "wof:name":"Albert Leus",
    "wof:placetype":"venue"
},
  "geometry": {"coordinates":[3.8472919464,50.9430236816],"type":"Point"}
}