{
  "type": "Feature",
  "properties": {
    "addr:full":"Brouwersstraat 2 Beringen Limburg 3580",
    "addr:housenumber":"2",
    "addr:postcode":"3580",
    "addr:street":"Brouwersstraat",
    "iso:country":"BE",
    "sg:address":"Brouwersstraat 2",
    "sg:city":"Beringen",
    "sg:orig_category":"Avocats and conseillers juridiques",
    "sg:phone":"+32 11 42 84 47",
    "sg:postcode":"3580",
    "sg:province":"Limburg",
    "wof:name":"Luc Savelkoul",
    "wof:placetype":"venue"
},
  "geometry": {"coordinates":[5.2231721878,51.0478858948],"type":"Point"}
}