{
  "type": "Feature",
  "properties": {
    "iso:country":"BE",
    "sg:address":"89a Lindestraat (iz Snepbeek 5a)",
    "sg:city":"Waregem",
    "sg:classifiers":[
        {
            "category":"Utilities",
            "subcategory":"Electric",
            "type":"Services"
        }
    ],
    "sg:phone":"+32 56 61 79 77",
    "sg:postcode":"8790",
    "sg:province":"West-Vlaanderen",
    "sg:tags":[
        "electricity",
        "electronic",
        "electrical",
        "equipment"
    ],
    "wof:name":"Dyno Europe",
    "wof:placetype":"venue"
},
  "geometry": {"coordinates":[3.4123549461,50.894115448],"type":"Point"}
}