{
  "type": "Feature",
  "properties": {
    "iso:country":"BE",
    "sg:address":"Ambachtstraat 9",
    "sg:city":"Hoogstraten",
    "sg:classifiers":[
        {
            "category":"Industrial Area",
            "type":"Public Place"
        }
    ],
    "sg:phone":"+32 3 314 76 84",
    "sg:postcode":"2320",
    "sg:province":"Antwerpen",
    "sg:tags":[
        "shed"
    ],
    "wof:name":"Spranco B.v.b.a.",
    "wof:placetype":"venue"
},
  "geometry": {"coordinates":[4.7613801956,51.4013137817],"type":"Point"}
}