{
  "type": "Feature",
  "properties": {
    "iso:country":"BE",
    "sg:address":"Jf Willemsstraat 79",
    "sg:city":"Boechout",
    "sg:orig_category":"Artsen and specialisten",
    "sg:phone":"+32 3 454 42 88",
    "sg:postcode":"2530",
    "sg:province":"Antwerpen",
    "wof:name":"Sabine Dobbelaere",
    "wof:placetype":"venue"
},
  "geometry": {"coordinates":[4.4960570335,51.1604309082],"type":"Point"}
}