{
  "type": "Feature",
  "properties": {
    "iso:country":"BE",
    "sg:address":"Rue De La Station 27",
    "sg:city":"Viroinval",
    "sg:orig_category":"Woningbouw",
    "sg:phone":"+32 60 31 15 08",
    "sg:postcode":"5670",
    "sg:province":"Namur",
    "wof:name":"Dechief Archange",
    "wof:placetype":"venue"
},
  "geometry": {"coordinates":[4.5514001846,50.0807380676],"type":"Point"}
}