{
  "type": "Feature",
  "properties": {
    "addr:full":"Wilgenlaan 6 Oudenburg West-Vlaanderen 8460",
    "addr:housenumber":"6",
    "addr:postcode":"8460",
    "addr:street":"Wilgenlaan",
    "iso:country":"BE",
    "sg:address":"Wilgenlaan 6",
    "sg:city":"Oudenburg",
    "sg:orig_category":"Dakwerken",
    "sg:phone":"+32 59 26 71 62",
    "sg:postcode":"8460",
    "sg:province":"West-Vlaanderen",
    "wof:name":"Fa. Verhamme",
    "wof:placetype":"venue"
},
  "geometry": {"coordinates":[3.0146229267,51.1860542297],"type":"Point"}
}