{
  "type": "Feature",
  "properties": {
    "addr:full":"Stuiverstraat 204 Oostende West-Vlaanderen 8400",
    "addr:housenumber":"204",
    "addr:postcode":"8400",
    "addr:street":"Stuiverstraat",
    "iso:country":"BE",
    "sg:address":"Stuiverstraat 204",
    "sg:city":"Oostende",
    "sg:orig_category":"Pain, p\u00e2tisseries and confiseries",
    "sg:phone":"+32 59 70 42 01",
    "sg:postcode":"8400",
    "sg:province":"West-Vlaanderen",
    "wof:name":"Desmedt",
    "wof:placetype":"venue"
},
  "geometry": {"coordinates":[2.9085440636,51.2149620056],"type":"Point"}
}