{
  "type": "Feature",
  "properties": {
    "iso:country":"BE",
    "sg:address":"Vosberg 62",
    "sg:city":"Wezembeek-oppem",
    "sg:orig_category":"Landmeters",
    "sg:phone":"+32 2 731 66 63",
    "sg:postcode":"1970",
    "sg:province":"Vlaams-Brabant",
    "wof:name":"Frans Van Schepdael",
    "wof:placetype":"venue"
},
  "geometry": {"coordinates":[4.5006651878,50.8407707214],"type":"Point"}
}