{
  "type": "Feature",
  "properties": {
    "addr:full":"Villalaan 32 Sint-gillis/saint-gilles Bruxelles-Capitale 1060",
    "addr:housenumber":"32",
    "addr:postcode":"1060",
    "addr:street":"Villalaan",
    "iso:country":"BE",
    "sg:address":"Villalaan 32",
    "sg:city":"Sint-gillis/saint-gilles",
    "sg:orig_category":"Artsen and specialisten",
    "sg:phone":"+32 2 538 32 31",
    "sg:postcode":"1060",
    "sg:province":"Bruxelles-Capitale",
    "wof:name":"Emmanuel D'hoore/e. D'hoore",
    "wof:placetype":"venue"
},
  "geometry": {"coordinates":[4.341753006,50.8243598938],"type":"Point"}
}