{
  "type": "Feature",
  "properties": {
    "addr:full":"Rue Jean Stas 24 Bruxelles (saint-gilles) Bruxelles-Capitale 1060",
    "addr:housenumber":"24",
    "addr:postcode":"1060",
    "addr:street":"Rue Jean Stas",
    "iso:country":"BE",
    "sg:address":"Rue Jean Stas 24",
    "sg:city":"Bruxelles (saint-gilles)",
    "sg:classifiers":[
        {
            "category":"Bars & Pubs",
            "type":"Food & Drink"
        }
    ],
    "sg:phone":"+32 2 534 47 41",
    "sg:postcode":"1060",
    "sg:province":"Bruxelles-Capitale",
    "sg:tags":[
        "tavern"
    ],
    "wof:name":"Macsweeneys Irish Pub",
    "wof:placetype":"venue"
},
  "geometry": {"coordinates":[4.3553352356,50.8339233398],"type":"Point"}
}