{
  "type": "Feature",
  "properties": {
    "iso:country":"BE",
    "sg:address":"Rue De Ch\u00e9zy 24",
    "sg:city":"Aywaille (harz\u00e9)",
    "sg:classifiers":[
        {
            "category":"Health Services",
            "subcategory":"Dentist",
            "type":"Services"
        }
    ],
    "sg:phone":"+32 4 384 60 20",
    "sg:postcode":"4920",
    "sg:province":"Li\u00e8ge",
    "wof:name":"Aarts Francine",
    "wof:placetype":"venue"
},
  "geometry": {"coordinates":[5.6782069206,50.4738540649],"type":"Point"}
}