{
  "type": "Feature",
  "properties": {
    "addr:full":"Zoning Industriel 32 Bastogne Luxembourg 6600",
    "addr:housenumber":"32",
    "addr:postcode":"6600",
    "addr:street":"Zoning Industriel",
    "iso:country":"BE",
    "sg:address":"Zoning Industriel 32",
    "sg:city":"Bastogne",
    "sg:classifiers":[
        {
            "category":"Utilities",
            "subcategory":"Cable",
            "type":"Services"
        }
    ],
    "sg:phone":"+32 61 21 12 02",
    "sg:postcode":"6600",
    "sg:province":"Luxembourg",
    "sg:tags":[
        "wire",
        "electric"
    ],
    "wof:name":"Rexel Belgium Sa (matelgro)",
    "wof:placetype":"venue"
},
  "geometry": {"coordinates":[5.70789814,49.9883842468],"type":"Point"}
}