{
  "type": "Feature",
  "properties": {
    "addr:full":"Stationsstraat 31 Beveren Oost-Vlaanderen 9120",
    "addr:housenumber":"31",
    "addr:postcode":"9120",
    "addr:street":"Stationsstraat",
    "iso:country":"BE",
    "sg:address":"Stationsstraat 31",
    "sg:city":"Beveren",
    "sg:orig_category":"Pain, p\u00e2tisseries and confiseries",
    "sg:phone":"+32 3 775 76 46",
    "sg:postcode":"9120",
    "sg:province":"Oost-Vlaanderen",
    "wof:name":"Chocolaterie Bosman-cool",
    "wof:placetype":"venue"
},
  "geometry": {"coordinates":[4.2579040527,51.2102165222],"type":"Point"}
}