{
  "type": "Feature",
  "properties": {
    "addr:full":"Rue Jacquet 4 Rochefort Namur 5580",
    "addr:housenumber":"4",
    "addr:postcode":"5580",
    "addr:street":"Rue Jacquet",
    "iso:country":"BE",
    "sg:address":"Rue Jacquet 4",
    "sg:city":"Rochefort",
    "sg:orig_category":"Epiceries. Boucheries. Cr\u00e9meries",
    "sg:phone":"+32 84 21 20 14",
    "sg:postcode":"5580",
    "sg:province":"Namur",
    "wof:name":"Au Fin Bec",
    "wof:placetype":"venue"
},
  "geometry": {"coordinates":[5.2225618362,50.1572189331],"type":"Point"}
}