{
  "type": "Feature",
  "properties": {
    "addr:full":"Groeningestraat 13 Oudenburg West-Vlaanderen 8460",
    "addr:housenumber":"13",
    "addr:postcode":"8460",
    "addr:street":"Groeningestraat",
    "iso:country":"BE",
    "sg:address":"Groeningestraat 13",
    "sg:city":"Oudenburg",
    "sg:orig_category":"Electrom\u00e9nager, t\u00e9l\u00e9visions and radios",
    "sg:phone":"+32 59 26 85 00",
    "sg:postcode":"8460",
    "sg:province":"West-Vlaanderen",
    "wof:name":"Roland Descamps",
    "wof:placetype":"venue"
},
  "geometry": {"coordinates":[3.0062611103,51.1818695068],"type":"Point"}
}