{
  "type": "Feature",
  "properties": {
    "addr:full":"Savoyestraat 11 Leuven Vlaams-Brabant 3000",
    "addr:housenumber":"11",
    "addr:postcode":"3000",
    "addr:street":"Savoyestraat",
    "iso:country":"BE",
    "sg:address":"Savoyestraat 11",
    "sg:city":"Leuven",
    "sg:orig_category":"Catering and organisatie van feesten Fast food and meeneem restaurants Restaurants",
    "sg:phone":"+32 16 22 67 09",
    "sg:postcode":"3000",
    "sg:province":"Vlaams-Brabant",
    "wof:name":"Ristorante Italia",
    "wof:placetype":"venue"
},
  "geometry": {"coordinates":[4.7036762238,50.8790512085],"type":"Point"}
}