{
  "type": "Feature",
  "properties": {
    "iso:country":"BE",
    "sg:address":"Delportestraat 73",
    "sg:city":"Tienen",
    "sg:orig_category":"M\u00e9decins and sp\u00e9cialistes",
    "sg:phone":"+32 16 81 68 12",
    "sg:postcode":"3300",
    "sg:province":"Vlaams-Brabant",
    "wof:name":"Eddy Betrains",
    "wof:placetype":"venue"
},
  "geometry": {"coordinates":[4.9306139946,50.8096199036],"type":"Point"}
}