{
  "type": "Feature",
  "properties": {
    "addr:full":"Martelaarslaan 182 Gent Oost-Vlaanderen 9000",
    "addr:housenumber":"182",
    "addr:postcode":"9000",
    "addr:street":"Martelaarslaan;Oost-Vlaanderen",
    "iso:country":"BE",
    "sg:address":"Martelaarslaan 182",
    "sg:city":"Gent",
    "sg:orig_category":"Maisons de repos and r\u00e9sidences",
    "sg:phone":"+32 9 225 27 87",
    "sg:postcode":"9000",
    "sg:province":"Oost-Vlaanderen",
    "wof:name":"Home La Lys",
    "wof:placetype":"venue"
},
  "geometry": {"coordinates":[3.7124760151,51.04662323],"type":"Point"}
}