{
  "type": "Feature",
  "properties": {
    "iso:country":"BE",
    "sg:address":"Monseigneur De Haerneln 78",
    "sg:city":"Kortrijk",
    "sg:classifiers":[
        {
            "category":"Arena",
            "subcategory":"Sports Club",
            "type":"Entertainment"
        }
    ],
    "sg:phone":"+32 56 20 49 84",
    "sg:postcode":"8500",
    "sg:province":"West-Vlaanderen",
    "sg:tags":[
        "de"
    ],
    "wof:name":"T.c. Wikings",
    "wof:placetype":"venue"
},
  "geometry": {"coordinates":[3.2618210316,50.8213043213],"type":"Point"}
}