{
  "type": "Feature",
  "properties": {
    "iso:country":"BE",
    "sg:address":"Postweg 140",
    "sg:city":"Sint-pieters-leeuw",
    "sg:orig_category":"Postkantoren Verzekeringsmakelaars and experts",
    "sg:phone":"+32 2 569 09 30",
    "sg:postcode":"1602",
    "sg:province":"Vlaams-Brabant",
    "wof:name":"De Post",
    "wof:placetype":"venue"
},
  "geometry": {"coordinates":[4.2311840057,50.8075561523],"type":"Point"}
}