{
  "type": "Feature",
  "properties": {
    "iso:country":"BE",
    "sg:address":"Vagevuurstraat 6",
    "sg:city":"Kortrijk",
    "sg:orig_category":"Geschenken and souvenirs Verlichting and huishoudartikelen",
    "sg:phone":"+32 56 22 97 59",
    "sg:postcode":"8510",
    "sg:province":"West-Vlaanderen",
    "wof:name":"Huis Accento",
    "wof:placetype":"venue"
},
  "geometry": {"coordinates":[3.2335400581,50.8066139221],"type":"Point"}
}