{
  "type": "Feature",
  "properties": {
    "iso:country":"BE",
    "sg:address":"Augustuslaan 12",
    "sg:city":"Sint-lambrechts-woluwe/woluwe-saint-lambert",
    "sg:orig_category":"Artsen and specialisten",
    "sg:phone":"+32 2 736 41 22",
    "sg:postcode":"1200",
    "sg:province":"Bruxelles-Capitale",
    "wof:name":"E. Mauclet",
    "wof:placetype":"venue"
},
  "geometry": {"coordinates":[4.4128417969,50.8469161987],"type":"Point"}
}