{
  "type": "Feature",
  "properties": {
    "addr:full":"Ijzerenleen 59 Mechelen Antwerpen 2800",
    "addr:housenumber":"59",
    "addr:postcode":"2800",
    "addr:street":"Ijzerenleen",
    "iso:country":"BE",
    "sg:address":"Ijzerenleen 59",
    "sg:city":"Mechelen",
    "sg:classifiers":[
        {
            "category":"Shopping",
            "subcategory":"Clothing, Apparel, & Fashions",
            "type":"Retail Goods"
        }
    ],
    "sg:phone":"+32 15 46 08 72",
    "sg:postcode":"2800",
    "sg:province":"Antwerpen",
    "sg:tags":[
        "-",
        "clothing",
        "child"
    ],
    "wof:name":"Pure",
    "wof:placetype":"venue"
},
  "geometry": {"coordinates":[4.4783067703,51.0260543823],"type":"Point"}
}