{
  "type": "Feature",
  "properties": {
    "addr:full":"Clemenceaustraat 27 Sint-katelijne-waver Antwerpen 2860",
    "addr:housenumber":"27",
    "addr:postcode":"2860",
    "addr:street":"Clemenceaustraat",
    "iso:country":"BE",
    "sg:address":"Clemenceaustraat 27",
    "sg:city":"Sint-katelijne-waver",
    "sg:orig_category":"Herstelling aan huis van huishoudartikelen Loodgieterij, verwarming and sanitaire installaties",
    "sg:phone":"+32 15 21 74 97",
    "sg:postcode":"2860",
    "sg:province":"Antwerpen",
    "wof:name":"Verschueren",
    "wof:placetype":"venue"
},
  "geometry": {"coordinates":[4.488629818,51.0621414185],"type":"Point"}
}