{
  "type": "Feature",
  "properties": {
    "addr:full":"Avenue Paul De Merten 14 Bruxelles (jette) Bruxelles-Capitale 1090",
    "addr:housenumber":"14",
    "addr:postcode":"1090",
    "addr:street":"Avenue Paul De Merten",
    "iso:country":"BE",
    "sg:address":"Avenue Paul De Merten 14",
    "sg:city":"Bruxelles (jette)",
    "sg:classifiers":[
        {
            "category":"Insurance",
            "subcategory":"Insurance Agent",
            "type":"Services"
        }
    ],
    "sg:phone":"+32 2 426 78 85",
    "sg:postcode":"1090",
    "sg:province":"Bruxelles-Capitale",
    "sg:tags":[
        "broker"
    ],
    "wof:name":"Massart (bureau) Sa",
    "wof:placetype":"venue"
},
  "geometry": {"coordinates":[4.3259382248,50.8701133728],"type":"Point"}
}