{
  "type": "Feature",
  "properties": {
    "iso:country":"BE",
    "sg:address":"Rue Adolphe P\u00e9cher 28",
    "sg:city":"Mons",
    "sg:classifiers":[
        {
            "category":"Real Estate",
            "subcategory":"Architect",
            "type":"Services"
        }
    ],
    "sg:phone":"+32 65 34 66 59",
    "sg:postcode":"7000",
    "sg:province":"Hainaut",
    "wof:name":"Renaud J",
    "wof:placetype":"venue"
},
  "geometry": {"coordinates":[3.9429299831,50.4503593445],"type":"Point"}
}