{
  "type": "Feature",
  "properties": {
    "addr:full":"Zwartzustersstraat 28 Antwerpen Antwerpen 2000",
    "addr:housenumber":"28",
    "addr:postcode":"2000",
    "addr:street":"Zwartzustersstraat",
    "iso:country":"BE",
    "sg:address":"Zwartzustersstraat 28",
    "sg:city":"Antwerpen",
    "sg:classifiers":[
        {
            "category":"Marine",
            "type":"Transportation"
        }
    ],
    "sg:phone":"+32 3 213 07 95",
    "sg:postcode":"2000",
    "sg:province":"Antwerpen",
    "sg:tags":[
        "agency",
        "sea",
        "shipping"
    ],
    "wof:name":"Coli Shipping & Transport Nv",
    "wof:placetype":"venue"
},
  "geometry": {"coordinates":[4.4018697739,51.2233886719],"type":"Point"}
}