{
  "type": "Feature",
  "properties": {
    "iso:country":"BE",
    "sg:address":"Rue De Gramptinne 4",
    "sg:city":"Andenne (thon)",
    "sg:classifiers":[
        {
            "category":"Real Estate",
            "subcategory":"Real Estate Services",
            "type":"Services"
        }
    ],
    "sg:phone":"+32 81 58 99 87",
    "sg:postcode":"5300",
    "sg:province":"Namur",
    "wof:name":"Godot Sa",
    "wof:placetype":"venue"
},
  "geometry": {"coordinates":[4.9932599068,50.4667854309],"type":"Point"}
}