{
  "type": "Feature",
  "properties": {
    "iso:country":"BE",
    "sg:address":"Rue De Ch\u00c2teaumont 12",
    "sg:city":"Bouillon",
    "sg:orig_category":"Musea and historische gebouwen",
    "sg:phone":"+32 61 46 69 56",
    "sg:postcode":"6833",
    "sg:province":"Luxembourg",
    "wof:name":"Mus\u00c9e En Plein Air",
    "wof:placetype":"venue"
},
  "geometry": {"coordinates":[5.0515799522,49.8228187561],"type":"Point"}
}