{
  "type": "Feature",
  "properties": {
    "iso:country":"BE",
    "sg:address":"Schureveld 10 Box 1",
    "sg:city":"Bilzen",
    "sg:classifiers":[
        {
            "category":"Social Services",
            "type":"Services"
        }
    ],
    "sg:phone":"+32 89 50 41 83",
    "sg:postcode":"3740",
    "sg:province":"Limburg",
    "wof:name":"Jeugdzorg In Gezin Vzw",
    "wof:placetype":"venue"
},
  "geometry": {"coordinates":[5.518032074,50.8742370605],"type":"Point"}
}