{
  "type": "Feature",
  "properties": {
    "iso:country":"BE",
    "sg:address":"Edith Cavellstraat 157",
    "sg:city":"Ukkel/uccle",
    "sg:orig_category":"Brood, gebak and snoepgoed",
    "sg:phone":"+32 2 375 55 07",
    "sg:postcode":"1180",
    "sg:province":"Bruxelles-Capitale",
    "wof:name":"Didier Chainniaux",
    "wof:placetype":"venue"
},
  "geometry": {"coordinates":[4.3578400612,50.8058242798],"type":"Point"}
}