{
  "type": "Feature",
  "properties": {
    "addr:full":"Olieslagerijstraat 19 Boechout Antwerpen 2530",
    "addr:housenumber":"19",
    "addr:postcode":"2530",
    "addr:street":"Olieslagerijstraat",
    "iso:country":"BE",
    "sg:address":"Olieslagerijstraat 19",
    "sg:city":"Boechout",
    "sg:orig_category":"Sportclubs Sportterreinen and installaties behalve sportcentra",
    "sg:phone":"+32 3 455 21 00",
    "sg:postcode":"2530",
    "sg:province":"Antwerpen",
    "wof:name":"T.c. J. Vanlangendonck",
    "wof:placetype":"venue"
},
  "geometry": {"coordinates":[4.5045599937,51.1796684265],"type":"Point"}
}