{
  "type": "Feature",
  "properties": {
    "addr:full":"Zandstraat 6be Hoogstraten Antwerpen 2323",
    "addr:housenumber":"6be",
    "addr:postcode":"2323",
    "addr:street":"Zandstraat",
    "iso:country":"BE",
    "sg:address":"Zandstraat 6be",
    "sg:city":"Hoogstraten",
    "sg:orig_category":"Woningbouw",
    "sg:phone":"+32 3 314 64 70",
    "sg:postcode":"2323",
    "sg:province":"Antwerpen",
    "wof:name":"Fransen-herrijgers",
    "wof:placetype":"venue"
},
  "geometry": {"coordinates":[4.7942008972,51.3939857483],"type":"Point"}
}