{
  "type": "Feature",
  "properties": {
    "iso:country":"BE",
    "sg:address":"Termurenlaan 14",
    "sg:city":"Aalst (erembodegem)",
    "sg:classifiers":[
        {
            "category":"Social Services",
            "type":"Services"
        }
    ],
    "sg:phone":"+32 53 78 44 82",
    "sg:postcode":"9320",
    "sg:province":"Oost-Vlaanderen",
    "wof:name":"Ter Muren",
    "wof:placetype":"venue"
},
  "geometry": {"coordinates":[4.0553851128,50.9209976196],"type":"Point"}
}