{
  "type": "Feature",
  "properties": {
    "addr:full":"Rue Du Petit-audenarde 77 Moeskroen/mouscron Hainaut 7712",
    "addr:housenumber":"77",
    "addr:postcode":"7712",
    "addr:street":"Rue Du Petit-Audenarde",
    "iso:country":"BE",
    "sg:address":"Rue Du Petit-audenarde 77",
    "sg:city":"Moeskroen/mouscron",
    "sg:orig_category":"Mus\u00e9es and patrimoine culturel. Comptables",
    "sg:phone":"+32 56 34 30 76",
    "sg:postcode":"7712",
    "sg:province":"Hainaut",
    "wof:name":"Claude Nicolas",
    "wof:placetype":"venue"
},
  "geometry": {"coordinates":[3.2535879612,50.714931488],"type":"Point"}
}