{
  "type": "Feature",
  "properties": {
    "iso:country":"BE",
    "sg:address":"Nieuwstraat 10",
    "sg:city":"Knesselare",
    "sg:orig_category":"Peinture. Rev\u00eatements pour sols and murs",
    "sg:phone":"+32 9 374 32 77",
    "sg:postcode":"9910",
    "sg:province":"Oost-Vlaanderen",
    "wof:name":"Peter Schrans",
    "wof:placetype":"venue"
},
  "geometry": {"coordinates":[3.4156179428,51.1415023804],"type":"Point"}
}