{
  "type": "Feature",
  "properties": {
    "addr:full":"Gen.geneesheer Deracheln 5b1 Elsene/ixelles Bruxelles-Capitale 1050",
    "addr:housenumber":"5b1",
    "addr:postcode":"1050",
    "addr:street":"Deracheln",
    "iso:country":"BE",
    "sg:address":"Gen.geneesheer Deracheln 5b1",
    "sg:city":"Elsene/ixelles",
    "sg:orig_category":"Kapsalons",
    "sg:phone":"+32 2 649 33 51",
    "sg:postcode":"1050",
    "sg:province":"Bruxelles-Capitale",
    "wof:name":"Coiff. Jeanine Et Robert",
    "wof:placetype":"venue"
},
  "geometry": {"coordinates":[4.3853168488,50.8173027039],"type":"Point"}
}