{
  "type": "Feature",
  "properties": {
    "addr:full":"Noordeind 44 Kalmthout Antwerpen 2920",
    "addr:housenumber":"44",
    "addr:postcode":"2920",
    "addr:street":"Noordeind",
    "iso:country":"BE",
    "sg:address":"Noordeind 44",
    "sg:city":"Kalmthout",
    "sg:classifiers":[
        {
            "category":"Manufacturing",
            "subcategory":"Metals",
            "type":"Manufacturing & Wholesale Goods"
        }
    ],
    "sg:phone":"+32 3 666 01 19",
    "sg:postcode":"2920",
    "sg:province":"Antwerpen",
    "sg:tags":[
        "working"
    ],
    "wof:name":"Artemis Bvba",
    "wof:placetype":"venue"
},
  "geometry": {"coordinates":[4.4678058624,51.4028129578],"type":"Point"}
}