{
  "type": "Feature",
  "properties": {
    "iso:country":"BE",
    "sg:address":"Karnemelkstraat 1",
    "sg:city":"Roeselare",
    "sg:orig_category":"Juwelen and horloges",
    "sg:phone":"+32 51 24 18 19",
    "sg:postcode":"8800",
    "sg:province":"West-Vlaanderen",
    "wof:name":"Huis Becoe",
    "wof:placetype":"venue"
},
  "geometry": {"coordinates":[3.1221671104,50.9447555542],"type":"Point"}
}