{
  "type": "Feature",
  "properties": {
    "addr:full":"Rue De Bousti\u00e8re 1 Merbes-le-ch\u00e2teau (labuissi\u00e8re) Hainaut 6567",
    "addr:housenumber":"1",
    "addr:postcode":"6567",
    "addr:street":"Rue De Boustie\u0300Re",
    "iso:country":"BE",
    "sg:address":"Rue De Bousti\u00e8re 1",
    "sg:city":"Merbes-le-ch\u00e2teau (labuissi\u00e8re)",
    "sg:classifiers":[
        {
            "category":"Real Estate",
            "subcategory":"Architect",
            "type":"Services"
        }
    ],
    "sg:phone":"+32 71 55 35 47",
    "sg:postcode":"6567",
    "sg:province":"Hainaut",
    "wof:name":"Ameels S",
    "wof:placetype":"venue"
},
  "geometry": {"coordinates":[4.1979980469,50.3271942139],"type":"Point"}
}