{
  "type": "Feature",
  "properties": {
    "iso:country":"BE",
    "sg:address":"Kasteelpleinstraat 64",
    "sg:city":"Antwerpen",
    "sg:classifiers":[
        {
            "category":"Deli",
            "type":"Food & Drink"
        }
    ],
    "sg:phone":"+32 3 237 07 86",
    "sg:postcode":"2000",
    "sg:province":"Antwerpen",
    "sg:tags":[
        "delicatessen"
    ],
    "wof:name":"Panna Cotta",
    "wof:placetype":"venue"
},
  "geometry": {"coordinates":[4.4022541046,51.2092056274],"type":"Point"}
}