{
  "type": "Feature",
  "properties": {
    "iso:country":"BE",
    "sg:address":"Vleminckstraat 13",
    "sg:city":"Antwerpen",
    "sg:classifiers":[
        {
            "category":"Professional",
            "subcategory":"Printing & Photocopies",
            "type":"Services"
        }
    ],
    "sg:phone":"+32 3 232 56 37",
    "sg:postcode":"2000",
    "sg:province":"Antwerpen",
    "sg:tags":[
        "-",
        "publishing",
        "desktop"
    ],
    "wof:name":"Printshop",
    "wof:placetype":"venue"
},
  "geometry": {"coordinates":[4.4039449692,51.2199516296],"type":"Point"}
}