{
  "type": "Feature",
  "properties": {
    "iso:country":"BE",
    "sg:address":"Waverse Steenweg 1338b11",
    "sg:city":"Oudergem/auderghem",
    "sg:orig_category":"Artiesten and kunstenaars",
    "sg:phone":"+32 2 675 31 56",
    "sg:postcode":"1160",
    "sg:province":"Bruxelles-Capitale",
    "wof:name":"Z\u00c9ana",
    "wof:placetype":"venue"
},
  "geometry": {"coordinates":[4.4130520821,50.8197479248],"type":"Point"}
}