{
  "type": "Feature",
  "properties": {
    "iso:country":"BE",
    "sg:address":"Hoogbeverenstraat 20",
    "sg:city":"Ardooie",
    "sg:classifiers":[
        {
            "category":"Food & Beverages",
            "subcategory":"Meat & Fish",
            "type":"Retail Goods"
        }
    ],
    "sg:phone":"+32 51 74 42 65",
    "sg:postcode":"8850",
    "sg:province":"West-Vlaanderen",
    "sg:tags":[
        "-",
        "livestock"
    ],
    "wof:name":"Debusschere L",
    "wof:placetype":"venue"
},
  "geometry": {"coordinates":[3.1743280888,50.9810180664],"type":"Point"}
}