{
  "type": "Feature",
  "properties": {
    "iso:country":"BE",
    "sg:address":"Paardenkerkhofstraat 120",
    "sg:city":"Mechelen",
    "sg:orig_category":"Herstelling leer and schoeisel",
    "sg:phone":"+32 15 55 56 94",
    "sg:postcode":"2800",
    "sg:province":"Antwerpen",
    "wof:name":"Hugo Eyckmans",
    "wof:placetype":"venue"
},
  "geometry": {"coordinates":[4.4983348846,51.0330886841],"type":"Point"}
}