{
  "type": "Feature",
  "properties": {
    "iso:country":"BE",
    "sg:address":"Madeliefjesstraat 17",
    "sg:city":"Grimbergen",
    "sg:classifiers":[
        {
            "category":"Insurance",
            "subcategory":"Insurance Agent",
            "type":"Services"
        }
    ],
    "sg:phone":"+32 2 270 82 78",
    "sg:postcode":"1850",
    "sg:province":"Vlaams-Brabant",
    "sg:tags":[
        "verzekeringsmakelaars",
        "expert"
    ],
    "wof:name":"Bureau Jacques Moiny",
    "wof:placetype":"venue"
},
  "geometry": {"coordinates":[4.387611866,50.9340133667],"type":"Point"}
}