{
  "type": "Feature",
  "properties": {
    "iso:country":"BE",
    "sg:address":"Brusselsesteenweg 126",
    "sg:city":"Leuven",
    "sg:classifiers":[
        {
            "category":"Bakery",
            "type":"Food & Drink"
        }
    ],
    "sg:phone":"+32 16 22 62 35",
    "sg:postcode":"3000",
    "sg:province":"Vlaams-Brabant",
    "sg:tags":[
        "confectioner",
        "baker"
    ],
    "wof:name":"Krokantje ('t)",
    "wof:placetype":"venue"
},
  "geometry": {"coordinates":[4.694475174,50.8806800842],"type":"Point"}
}