{
  "type": "Feature",
  "properties": {
    "addr:full":"Heist-goorstraat 50 Heist-op-den-berg Antwerpen 2220",
    "addr:housenumber":"50",
    "addr:postcode":"2220",
    "addr:street":"Heist-Goorstraat",
    "iso:country":"BE",
    "sg:address":"Heist-goorstraat 50",
    "sg:city":"Heist-op-den-berg",
    "sg:orig_category":"Postkantoren Verzekeringsmakelaars and experts",
    "sg:phone":"+32 15 22 06 95",
    "sg:postcode":"2220",
    "sg:province":"Antwerpen",
    "wof:name":"De Post",
    "wof:placetype":"venue"
},
  "geometry": {"coordinates":[4.7276301384,51.0509300232],"type":"Point"}
}