{
  "type": "Feature",
  "properties": {
    "iso:country":"BE",
    "sg:address":"Mijl 31",
    "sg:city":"Lier",
    "sg:orig_category":"Antiquit\u00e9s",
    "sg:phone":"+32 3 489 02 93",
    "sg:postcode":"2500",
    "sg:province":"Antwerpen",
    "wof:name":"Paul Willems",
    "wof:placetype":"venue"
},
  "geometry": {"coordinates":[4.5915880203,51.1230583191],"type":"Point"}
}