{
  "type": "Feature",
  "properties": {
    "addr:full":"Casselstraat 216 Poperinge West-Vlaanderen 8970",
    "addr:housenumber":"216",
    "addr:postcode":"8970",
    "addr:street":"Casselstraat",
    "iso:country":"BE",
    "sg:address":"Casselstraat 216",
    "sg:city":"Poperinge",
    "sg:orig_category":"Meubles D\u00e9taillants, Am\u00e9nagement de B\u00e2timents et de Cuisines. Quincailleries",
    "sg:phone":"+32 57 33 32 86",
    "sg:postcode":"8970",
    "sg:province":"West-Vlaanderen",
    "wof:name":"Beernaert",
    "wof:placetype":"venue"
},
  "geometry": {"coordinates":[2.7177538872,50.8480682373],"type":"Point"}
}