{
  "type": "Feature",
  "properties": {
    "addr:full":"Rue Du Pr\u00c9 \u00c0 L'aune 8 Assesse Namur 5330",
    "addr:housenumber":"8",
    "addr:postcode":"5330",
    "addr:street":"Rue Du Pre\u0301 A\u0300 L'Aune",
    "iso:country":"BE",
    "sg:address":"Rue Du Pr\u00c9 \u00c0 L'aune 8",
    "sg:city":"Assesse",
    "sg:orig_category":"Rundveehouders",
    "sg:phone":"+32 83 65 52 16",
    "sg:postcode":"5330",
    "sg:province":"Namur",
    "wof:name":"A. Lelievre",
    "wof:placetype":"venue"
},
  "geometry": {"coordinates":[5.0096349716,50.35546875],"type":"Point"}
}