{
  "type": "Feature",
  "properties": {
    "iso:country":"BE",
    "sg:address":"Bruggestraat 279",
    "sg:city":"Ingelmunster",
    "sg:orig_category":"Rev\u00eatements de sols and murs",
    "sg:phone":"+32 51 48 74 47",
    "sg:postcode":"8770",
    "sg:province":"West-Vlaanderen",
    "wof:name":"Ron Parket",
    "wof:placetype":"venue"
},
  "geometry": {"coordinates":[3.2493391037,50.9380989075],"type":"Point"}
}