{
  "type": "Feature",
  "properties": {
    "iso:country":"BE",
    "sg:address":"Avenue Des Cerisiers 29",
    "sg:city":"Chapelle-lez-herlaimont",
    "sg:classifiers":[
        {
            "category":"Landmark",
            "subcategory":"Memorial",
            "type":"Public Place"
        }
    ],
    "sg:phone":"+32 64 44 46 86",
    "sg:postcode":"7160",
    "sg:province":"Hainaut",
    "sg:tags":[
        "-",
        "monument"
    ],
    "wof:name":"Vanden Bossche",
    "wof:placetype":"venue"
},
  "geometry": {"coordinates":[4.2769961357,50.475025177],"type":"Point"}
}