{
  "type": "Feature",
  "properties": {
    "addr:full":"Boulevard Joseph Tirou 32 Charleroi Hainaut 6000",
    "addr:housenumber":"32",
    "addr:postcode":"6000",
    "addr:street":"Boulevard Joseph Tirou;Hainaut",
    "iso:country":"BE",
    "sg:address":"Boulevard Joseph Tirou 32",
    "sg:city":"Charleroi",
    "sg:classifiers":[
        {
            "category":"Shopping",
            "subcategory":"Bicycles & Sporting Goods",
            "type":"Retail Goods"
        }
    ],
    "sg:phone":"+32 71 30 55 44",
    "sg:postcode":"6000",
    "sg:province":"Hainaut",
    "sg:tags":[
        "sport",
        "-"
    ],
    "wof:name":"Sport Flash",
    "wof:placetype":"venue"
},
  "geometry": {"coordinates":[4.4400248528,50.408367157],"type":"Point"}
}