{
  "type": "Feature",
  "properties": {
    "iso:country":"BE",
    "sg:address":"Clos Des Pommiers 7",
    "sg:city":"Braine-l'alleud",
    "sg:orig_category":"Installatie van houten of kunststof schrijnwerk Installatie van metalen schrijnwerk Serres and speci",
    "sg:phone":"+32 2 384 94 69",
    "sg:postcode":"1420",
    "sg:province":"Brabant Wallon",
    "wof:name":"Goossens R.",
    "wof:placetype":"venue"
},
  "geometry": {"coordinates":[-0.6790779829,47.3779411316],"type":"Point"}
}