{
  "type": "Feature",
  "properties": {
    "addr:full":"Mercatorlaan 21 Oostende West-Vlaanderen 8400",
    "addr:housenumber":"21",
    "addr:postcode":"8400",
    "addr:street":"Mercatorlaan",
    "iso:country":"BE",
    "sg:address":"Mercatorlaan 21",
    "sg:city":"Oostende",
    "sg:classifiers":[
        {
            "category":"Travel",
            "subcategory":"Hotels & Motels",
            "type":"Entertainment"
        }
    ],
    "sg:phone":"+32 59 80 72 72",
    "sg:postcode":"8400",
    "sg:province":"West-Vlaanderen",
    "wof:name":"Melinda Hotel",
    "wof:placetype":"venue"
},
  "geometry": {"coordinates":[2.9204161167,51.2253112793],"type":"Point"}
}