{
  "type": "Feature",
  "properties": {
    "addr:full":"Meulenbroekstraat 22 Hamme Oost-Vlaanderen 9220",
    "addr:housenumber":"22",
    "addr:postcode":"9220",
    "addr:street":"Meulenbroekstraat",
    "iso:country":"BE",
    "sg:address":"Meulenbroekstraat 22",
    "sg:city":"Hamme",
    "sg:classifiers":[
        {
            "category":"Government",
            "subcategory":"Police Station",
            "type":"Public Place"
        }
    ],
    "sg:phone":"+32 52 47 70 13",
    "sg:postcode":"9220",
    "sg:province":"Oost-Vlaanderen",
    "sg:tags":[
        "gendarmerie"
    ],
    "wof:name":"Federale Politie",
    "wof:placetype":"venue"
},
  "geometry": {"coordinates":[4.1339712143,51.1009788513],"type":"Point"}
}