{
  "type": "Feature",
  "properties": {
    "iso:country":"BE",
    "sg:address":"Bervoetstraat 40",
    "sg:city":"Antwerpen",
    "sg:classifiers":[
        {
            "category":"Shopping",
            "subcategory":"Books",
            "type":"Retail Goods"
        }
    ],
    "sg:phone":"+32 3 233 80 86",
    "sg:postcode":"2000",
    "sg:province":"Antwerpen",
    "sg:tags":[
        "antiquarian",
        "trade"
    ],
    "wof:name":"Roses B",
    "wof:placetype":"venue"
},
  "geometry": {"coordinates":[4.4028410912,51.2119064331],"type":"Point"}
}