{
  "type": "Feature",
  "properties": {
    "addr:full":"Rue Fransmann 24 Bruxelles Bruxelles-Capitale 1020",
    "addr:housenumber":"24",
    "addr:postcode":"1020",
    "addr:street":"Rue Fransmann",
    "iso:country":"BE",
    "sg:address":"Rue Fransmann 24",
    "sg:city":"Bruxelles",
    "sg:orig_category":"Kapsalons",
    "sg:phone":"+32 2 425 11 22",
    "sg:postcode":"1020",
    "sg:province":"Bruxelles-Capitale",
    "wof:name":"Top Mode",
    "wof:placetype":"venue"
},
  "geometry": {"coordinates":[4.3459849358,50.8779678345],"type":"Point"}
}