{
  "type": "Feature",
  "properties": {
    "addr:full":"Chauss\u00c9e D'arlon 24 Bastogne Luxembourg 6600",
    "addr:housenumber":"24",
    "addr:postcode":"6600",
    "addr:street":"Chausse\u0301E D'Arlon",
    "iso:country":"BE",
    "sg:address":"Chauss\u00c9e D'arlon 24",
    "sg:city":"Bastogne",
    "sg:orig_category":"Slagers",
    "sg:phone":"+32 61 21 70 37",
    "sg:postcode":"6600",
    "sg:province":"Luxembourg",
    "wof:name":"Renmans",
    "wof:placetype":"venue"
},
  "geometry": {"coordinates":[5.7186799049,49.9958152771],"type":"Point"}
}