{
  "type": "Feature",
  "properties": {
    "addr:full":"Rue D'anth\u00e9e 54 Mettet (ermeton-sur-biert) Namur 5644",
    "addr:housenumber":"54",
    "addr:postcode":"5644",
    "addr:street":"Rue D'Anthe \u0301E;Ermeton-Sur-Biert",
    "iso:country":"BE",
    "sg:address":"Rue D'anth\u00e9e 54",
    "sg:city":"Mettet (ermeton-sur-biert)",
    "sg:classifiers":[
        {
            "category":"Bars & Pubs",
            "type":"Food & Drink"
        }
    ],
    "sg:phone":"+32 71 72 72 70",
    "sg:postcode":"5644",
    "sg:province":"Namur",
    "wof:name":"Chaumi\u00e8re (la)",
    "wof:placetype":"venue"
},
  "geometry": {"coordinates":[4.7189698219,50.2966918945],"type":"Point"}
}