{
  "type": "Feature",
  "properties": {
    "iso:country":"BE",
    "sg:address":"Rue Moulin En Rhuyff 3",
    "sg:city":"Limbourg",
    "sg:classifiers":[
        {
            "category":"Food & Beverages",
            "subcategory":"Fruits & Vegetables",
            "type":"Retail Goods"
        }
    ],
    "sg:phone":"+32 87 76 47 74",
    "sg:postcode":"4831",
    "sg:province":"Li\u00e8ge",
    "sg:tags":[
        "l\u00e9gumes"
    ],
    "wof:name":"L'etal",
    "wof:placetype":"venue"
},
  "geometry": {"coordinates":[5.9380497932,50.6228752136],"type":"Point"}
}