{
  "type": "Feature",
  "properties": {
    "addr:full":"Rue De Longtain 20-30 La Louviere Hainaut 7100",
    "addr:housenumber":"20-30",
    "addr:postcode":"7100",
    "addr:street":"Rue De Longtain",
    "iso:country":"BE",
    "sg:address":"Rue De Longtain 20-30",
    "sg:city":"La Louviere",
    "sg:orig_category":"Sportclubs",
    "sg:phone":"+32 64 21 29 10",
    "sg:postcode":"7100",
    "sg:province":"Hainaut",
    "wof:name":"Aikido",
    "wof:placetype":"venue"
},
  "geometry": {"coordinates":[4.2034578323,50.4801216125],"type":"Point"}
}