{
  "type": "Feature",
  "properties": {
    "addr:full":"Steenweg Naar Neeroeteren 21a Dilsen-stokkem (elen) Limburg 3650",
    "addr:housenumber":"21a",
    "addr:postcode":"3650",
    "addr:street":"Steenweg Naar Neeroeteren;Elen Limburg",
    "iso:country":"BE",
    "sg:address":"Steenweg Naar Neeroeteren 21a",
    "sg:city":"Dilsen-stokkem (elen)",
    "sg:classifiers":[
        {
            "category":"Bars & Pubs",
            "type":"Food & Drink"
        }
    ],
    "sg:phone":"+32 89 86 14 54",
    "sg:postcode":"3650",
    "sg:province":"Limburg",
    "wof:name":"Caf\u00e9 De Zwarte Kat",
    "wof:placetype":"venue"
},
  "geometry": {"coordinates":[5.7261199951,51.0690307617],"type":"Point"}
}