{
  "type": "Feature",
  "properties": {
    "addr:full":"Jan Jeliestraat 20 Aalst Oost-Vlaanderen 9300",
    "addr:housenumber":"20",
    "addr:postcode":"9300",
    "addr:street":"Jeliestraat",
    "iso:country":"BE",
    "sg:address":"Jan Jeliestraat 20",
    "sg:city":"Aalst",
    "sg:classifiers":[
        {
            "category":"Banks & Credit Unions",
            "subcategory":"Investment Brokerage",
            "type":"Services"
        }
    ],
    "sg:phone":"+32 53 21 19 07",
    "sg:postcode":"9300",
    "sg:province":"Oost-Vlaanderen",
    "sg:tags":[
        "repair",
        "-",
        "installation",
        "sanitary",
        "article"
    ],
    "wof:name":"De Craemer Roger",
    "wof:placetype":"venue"
},
  "geometry": {"coordinates":[4.0432882309,50.9524383545],"type":"Point"}
}