{
  "type": "Feature",
  "properties": {
    "iso:country":"BE",
    "sg:address":"Chauss\u00c9e De Louvain 49",
    "sg:city":"Sint-joost-ten-node/saint-josse-ten-noode",
    "sg:orig_category":"Souvenirs and objets artisanaux",
    "sg:phone":"+32 2 218 53 28",
    "sg:postcode":"1210",
    "sg:province":"Bruxelles-Capitale",
    "wof:name":"Maison Privil\u00c8ge",
    "wof:placetype":"venue"
},
  "geometry": {"coordinates":[4.3722448349,50.8497276306],"type":"Point"}
}