{
  "type": "Feature",
  "properties": {
    "iso:country":"BE",
    "sg:address":"Heuveldal 36bus 10",
    "sg:city":"Strombeek-bever",
    "sg:classifiers":[
        {
            "category":"Professional",
            "subcategory":"Accounting & Tax Preparation",
            "type":"Services"
        }
    ],
    "sg:phone":"+32 2 267 22 28",
    "sg:postcode":"1853",
    "sg:province":"Vlaams-Brabant",
    "sg:tags":[
        "bookkeeping"
    ],
    "wof:name":"Bureau Marcel Gillet S.a.",
    "wof:placetype":"venue"
},
  "geometry": {"coordinates":[4.351556778,50.9020271301],"type":"Point"}
}