{
  "type": "Feature",
  "properties": {
    "addr:full":"Kleine Bruanestraat 16 Roeselare West-Vlaanderen 8800",
    "addr:housenumber":"16",
    "addr:postcode":"8800",
    "addr:street":"Bruanestraat",
    "iso:country":"BE",
    "sg:address":"Kleine Bruanestraat 16",
    "sg:city":"Roeselare",
    "sg:classifiers":[
        {
            "category":"Home & Garden",
            "subcategory":"Household Appliances",
            "type":"Retail Goods"
        }
    ],
    "sg:phone":"+32 51 20 76 30",
    "sg:postcode":"8800",
    "sg:province":"West-Vlaanderen",
    "sg:tags":[
        "repair",
        "mainten",
        "-",
        "electric"
    ],
    "wof:name":"Deseck R",
    "wof:placetype":"venue"
},
  "geometry": {"coordinates":[3.1361429691,50.948261261],"type":"Point"}
}