{
  "type": "Feature",
  "properties": {
    "addr:full":"Tessenderloseweg 53 Geel Antwerpen 2440",
    "addr:housenumber":"53",
    "addr:postcode":"2440",
    "addr:street":"Tessenderloseweg",
    "iso:country":"BE",
    "sg:address":"Tessenderloseweg 53",
    "sg:city":"Geel",
    "sg:orig_category":"Schoenen",
    "sg:phone":"+32 14 58 84 36",
    "sg:postcode":"2440",
    "sg:province":"Antwerpen",
    "wof:name":"Alfons Victor Geys",
    "wof:placetype":"venue"
},
  "geometry": {"coordinates":[5.0186038017,51.1376152039],"type":"Point"}
}