{
  "type": "Feature",
  "properties": {
    "addr:full":"Kasteelwegel 24 Gent Oost-Vlaanderen 9040",
    "addr:housenumber":"24",
    "addr:postcode":"9040",
    "addr:street":"Kasteelwegel;Oost-Vlaanderen",
    "iso:country":"BE",
    "sg:address":"Kasteelwegel 24",
    "sg:city":"Gent",
    "sg:orig_category":"Meubles D\u00e9taillants, Am\u00e9nagement de B\u00e2timents et de Cuisines. Articles de jardin. Jardinage",
    "sg:phone":"+32 9 228 23 90",
    "sg:postcode":"9040",
    "sg:province":"Oost-Vlaanderen",
    "wof:name":"Alfa's Evergreens",
    "wof:placetype":"venue"
},
  "geometry": {"coordinates":[3.7816030979,51.0674362183],"type":"Point"}
}