{
  "type": "Feature",
  "properties": {
    "iso:country":"BE",
    "sg:address":"Avenue De Tervueren 300b4",
    "sg:city":"Sint-pieters-woluwe",
    "sg:orig_category":"Agences d'exp\u00e9dition",
    "sg:phone":"+32 2 778 99 50",
    "sg:postcode":"1150",
    "sg:province":"Bruxelles-Capitale",
    "wof:name":"Saint-gobain Exprover",
    "wof:placetype":"venue"
},
  "geometry": {"coordinates":[4.4289522171,50.8350372314],"type":"Point"}
}