{
  "type": "Feature",
  "properties": {
    "addr:full":"Avenue Ives-sabin Magherman 70 Renaix Oost-Vlaanderen 9600",
    "addr:housenumber":"70",
    "addr:postcode":"9600",
    "addr:street":"Avenue Ives-Sabin Magherman",
    "iso:country":"BE",
    "sg:address":"Avenue Ives-sabin Magherman 70",
    "sg:city":"Renaix",
    "sg:classifiers":[
        {
            "category":"Banks & Credit Unions",
            "subcategory":"Investment Brokerage",
            "type":"Services"
        }
    ],
    "sg:phone":"+32 55 21 17 70",
    "sg:postcode":"9600",
    "sg:province":"Oost-Vlaanderen",
    "sg:tags":[
        "printing",
        "-"
    ],
    "wof:name":"Mastin Bvba",
    "wof:placetype":"venue"
},
  "geometry": {"coordinates":[3.5888299942,50.7472991943],"type":"Point"}
}