{
  "type": "Feature",
  "properties": {
    "addr:full":"Steenweg Hulst-lessen 38 Temse Oost-Vlaanderen 9140",
    "addr:housenumber":"38",
    "addr:postcode":"9140",
    "addr:street":"Steenweg Hulst-Lessen",
    "iso:country":"BE",
    "sg:address":"Steenweg Hulst-lessen 38",
    "sg:city":"Temse",
    "sg:orig_category":"Experts-comptables",
    "sg:phone":"+32 3 766 58 24",
    "sg:postcode":"9140",
    "sg:province":"Oost-Vlaanderen",
    "wof:name":"Roger Bracke",
    "wof:placetype":"venue"
},
  "geometry": {"coordinates":[4.14920187,51.1330680847],"type":"Point"}
}