{
  "type": "Feature",
  "properties": {
    "addr:full":"Rue Grande Couture 8 Tournai Hainaut 7500",
    "addr:housenumber":"8",
    "addr:postcode":"7500",
    "addr:street":"Rue Grande Couture",
    "iso:country":"BE",
    "sg:address":"Rue Grande Couture 8",
    "sg:city":"Tournai",
    "sg:classifiers":[
        {
            "category":"Professional",
            "subcategory":"Detective & Security Services",
            "type":"Services"
        }
    ],
    "sg:phone":"+32 69 84 08 88",
    "sg:postcode":"7500",
    "sg:province":"Hainaut",
    "sg:tags":[
        "access",
        "control",
        "ac",
        "system"
    ],
    "wof:name":"Adt Security Services",
    "wof:placetype":"venue"
},
  "geometry": {"coordinates":[3.3715209961,50.6039352417],"type":"Point"}
}