{
  "type": "Feature",
  "properties": {
    "addr:full":"Rue Laoureux 17 Verviers Li\u00e8ge 4800",
    "addr:housenumber":"17",
    "addr:postcode":"4800",
    "addr:street":"Rue Laoureux",
    "iso:country":"BE",
    "sg:address":"Rue Laoureux 17",
    "sg:city":"Verviers",
    "sg:orig_category":"Artsen and specialisten",
    "sg:phone":"+32 87 31 08 37",
    "sg:postcode":"4800",
    "sg:province":"Li\u00e8ge",
    "wof:name":"Daniele Desmedt",
    "wof:placetype":"venue"
},
  "geometry": {"coordinates":[5.8644299507,50.5921096802],"type":"Point"}
}