{
  "type": "Feature",
  "properties": {
    "addr:full":"Chauss\u00c9e De Huy 212 C Chaumont-gistoux Brabant Wallon 1325",
    "addr:housenumber":"212 c;1325",
    "addr:street":"Chausse\u0301E De Huy;Chaumont-Gistoux Brabant",
    "iso:country":"BE",
    "sg:address":"Chauss\u00c9e De Huy 212 C",
    "sg:city":"Chaumont-gistoux",
    "sg:orig_category":"Eclairage et \u00e9quipements du foyer. Fleurs and plantes",
    "sg:phone":"+32 495 24 96 79",
    "sg:postcode":"1325",
    "sg:province":"Brabant Wallon",
    "wof:name":"Flory-de-mille",
    "wof:placetype":"venue"
},
  "geometry": {"coordinates":[4.6932210922,50.6852874756],"type":"Point"}
}