{
  "type": "Feature",
  "properties": {
    "addr:full":"Peetersstraat 14 Diest Vlaams-Brabant 3290",
    "addr:housenumber":"14",
    "addr:postcode":"3290",
    "addr:street":"Peetersstraat",
    "iso:country":"BE",
    "sg:address":"Peetersstraat 14",
    "sg:city":"Diest",
    "sg:orig_category":"Enseignement maternel and primaire",
    "sg:phone":"+32 13 31 20 16",
    "sg:postcode":"3290",
    "sg:province":"Vlaams-Brabant",
    "wof:name":"Vrije Basisschool",
    "wof:placetype":"venue"
},
  "geometry": {"coordinates":[5.0549840927,50.9828948975],"type":"Point"}
}