{
  "type": "Feature",
  "properties": {
    "iso:country":"BE",
    "sg:address":"Rue De L'industrie 89",
    "sg:city":"Namur",
    "sg:classifiers":[
        {
            "category":"Structure",
            "subcategory":"Factory",
            "type":"Public Place"
        }
    ],
    "sg:phone":"+32 81 73 14 77",
    "sg:postcode":"5002",
    "sg:province":"Namur",
    "sg:tags":[
        "metaalwaren",
        "fab",
        "diverse"
    ],
    "wof:name":"Somasign",
    "wof:placetype":"venue"
},
  "geometry": {"coordinates":[4.8507738113,50.4752502441],"type":"Point"}
}