{
  "type": "Feature",
  "properties": {
    "addr:full":"Lindestraat 5 Heist-op-den-berg (wiekevorst) Antwerpen 2222",
    "addr:housenumber":"5",
    "addr:postcode":"2222",
    "addr:street":"Lindestraat",
    "iso:country":"BE",
    "sg:address":"Lindestraat 5",
    "sg:city":"Heist-op-den-berg (wiekevorst)",
    "sg:classifiers":[
        {
            "category":"Home & Garden",
            "subcategory":"Household Appliances",
            "type":"Retail Goods"
        }
    ],
    "sg:phone":"+32 14 26 04 21",
    "sg:postcode":"2222",
    "sg:province":"Antwerpen",
    "sg:tags":[
        "repair",
        "stove",
        "-"
    ],
    "wof:name":"De Heide Bvba",
    "wof:placetype":"venue"
},
  "geometry": {"coordinates":[4.7292399406,51.1032218933],"type":"Point"}
}