{
  "type": "Feature",
  "properties": {
    "iso:country":"BE",
    "sg:address":"Chauss\u00e9e De Soignies 81",
    "sg:city":"Le Roeulx",
    "sg:classifiers":[
        {
            "category":"Building & Trades",
            "subcategory":"Landscaping Services",
            "type":"Services"
        }
    ],
    "sg:phone":"+32 64 66 53 74",
    "sg:postcode":"7070",
    "sg:province":"Hainaut",
    "sg:tags":[
        "gardening",
        "garden",
        "maintenance"
    ],
    "wof:name":"Vm Construct",
    "wof:placetype":"venue"
},
  "geometry": {"coordinates":[4.1014938354,50.5122032166],"type":"Point"}
}