{
  "type": "Feature",
  "properties": {
    "addr:full":"Rue Georges Cl\u00c9menceau 13 Li\u00c8ge Li\u00e8ge 4000",
    "addr:housenumber":"13",
    "addr:postcode":"4000",
    "addr:street":"Rue Georges Cle\u0301Menceau",
    "iso:country":"BE",
    "sg:address":"Rue Georges Cl\u00c9menceau 13",
    "sg:city":"Li\u00c8ge",
    "sg:orig_category":"Cr\u00e9dits divers",
    "sg:postcode":"4000",
    "sg:province":"Li\u00e8ge",
    "wof:name":"Bancontact-mister Cash",
    "wof:placetype":"venue"
},
  "geometry": {"coordinates":[5.5708050728,50.6428184509],"type":"Point"}
}