{
  "type": "Feature",
  "properties": {
    "iso:country":"BE",
    "sg:address":"Assesteenweg 22",
    "sg:city":"Asse",
    "sg:orig_category":"Pi\u00e8ces and accessoires de v\u00e9hicules automobiles Gr",
    "sg:phone":"+32 2 452 63 04",
    "sg:postcode":"1730",
    "sg:province":"Vlaams-Brabant",
    "wof:name":"Auto-onderdelen Wielant",
    "wof:placetype":"venue"
},
  "geometry": {"coordinates":[4.1645951271,50.9137229919],"type":"Point"}
}