{
  "type": "Feature",
  "properties": {
    "addr:full":"Gemeneweidestraat 31 Brugge West-Vlaanderen 8000",
    "addr:housenumber":"31",
    "addr:postcode":"8000",
    "addr:street":"Gemeneweidestraat",
    "iso:country":"BE",
    "sg:address":"Gemeneweidestraat 31",
    "sg:city":"Brugge",
    "sg:orig_category":"M\u00e9decins and sp\u00e9cialistes",
    "sg:phone":"+32 50 33 76 74",
    "sg:postcode":"8000",
    "sg:province":"West-Vlaanderen",
    "wof:name":"Paul Coucke",
    "wof:placetype":"venue"
},
  "geometry": {"coordinates":[3.2475349903,51.23670578],"type":"Point"}
}