{
  "type": "Feature",
  "properties": {
    "addr:full":"Stationsstraat 116 Beveren Oost-Vlaanderen 9120",
    "addr:housenumber":"116",
    "addr:postcode":"9120",
    "addr:street":"Stationsstraat",
    "iso:country":"BE",
    "sg:address":"Stationsstraat 116",
    "sg:city":"Beveren",
    "sg:orig_category":"D\u00e9corateurs d'int\u00e9rieur. Enregistrements sonores",
    "sg:phone":"+32 3 775 25 79",
    "sg:postcode":"9120",
    "sg:province":"Oost-Vlaanderen",
    "wof:name":"Daft Records",
    "wof:placetype":"venue"
},
  "geometry": {"coordinates":[4.2583827972,51.2084579468],"type":"Point"}
}