{
  "type": "Feature",
  "properties": {
    "iso:country":"BE",
    "sg:address":"Bergense Steenweg 673",
    "sg:city":"Anderlecht",
    "sg:orig_category":"Geschenken and souvenirs IJzerwaren, bouw- and verfmaterialen",
    "sg:phone":"+32 2 520 02 94",
    "sg:postcode":"1070",
    "sg:province":"Bruxelles-Capitale",
    "wof:name":"Iacono Sanitaire",
    "wof:placetype":"venue"
},
  "geometry": {"coordinates":[4.3094887733,50.8312110901],"type":"Point"}
}