{
  "type": "Feature",
  "properties": {
    "addr:full":"Kerkstraat 54 Middelkerke West-Vlaanderen 8430",
    "addr:housenumber":"54",
    "addr:postcode":"8430",
    "addr:street":"Kerkstraat",
    "iso:country":"BE",
    "sg:address":"Kerkstraat 54",
    "sg:city":"Middelkerke",
    "sg:orig_category":"Banques and organismes de cr\u00e9dit",
    "sg:phone":"+32 59 30 08 55",
    "sg:postcode":"8430",
    "sg:province":"West-Vlaanderen",
    "wof:name":"Beroepskrediet",
    "wof:placetype":"venue"
},
  "geometry": {"coordinates":[2.8203859329,51.18592453],"type":"Point"}
}