{
  "type": "Feature",
  "properties": {
    "iso:country":"BE",
    "sg:address":"Rosalialaan 5",
    "sg:city":"Lichtervelde",
    "sg:classifiers":[
        {
            "category":"Professional",
            "subcategory":"Lawyer & Legal Services",
            "type":"Services"
        }
    ],
    "sg:phone":"+32 51 72 52 37",
    "sg:postcode":"8810",
    "sg:province":"West-Vlaanderen",
    "wof:name":"Vanwalleghem R",
    "wof:placetype":"venue"
},
  "geometry": {"coordinates":[3.1463890076,51.0263061523],"type":"Point"}
}