{
  "type": "Feature",
  "properties": {
    "addr:full":"Blauwstraat 16 Boom Antwerpen 2850",
    "addr:housenumber":"16",
    "addr:postcode":"2850",
    "addr:street":"Blauwstraat",
    "iso:country":"BE",
    "sg:address":"Blauwstraat 16",
    "sg:city":"Boom",
    "sg:orig_category":"Textiel Verlichting and huishoudartikelen",
    "sg:phone":"+32 3 888 64 13",
    "sg:postcode":"2850",
    "sg:province":"Antwerpen",
    "wof:name":"Huis Wendy",
    "wof:placetype":"venue"
},
  "geometry": {"coordinates":[4.3669247627,51.0862236023],"type":"Point"}
}