{
  "type": "Feature",
  "properties": {
    "iso:country":"BE",
    "sg:address":"Tiensestraat 19",
    "sg:city":"Leuven",
    "sg:orig_category":"Opticiens. Opticiens. Articles m\u00e9dicaux and orthop\u00e9diques",
    "sg:phone":"+32 16 58 38 48",
    "sg:postcode":"3000",
    "sg:province":"Vlaams-Brabant",
    "wof:name":"Oogcontact Contactlenscentrum",
    "wof:placetype":"venue"
},
  "geometry": {"coordinates":[4.7036318779,50.8783111572],"type":"Point"}
}