{
  "type": "Feature",
  "properties": {
    "addr:full":"Leuvensesteenweg 104 Aarschot Vlaams-Brabant 3200",
    "addr:housenumber":"104",
    "addr:postcode":"3200",
    "addr:street":"Leuvensesteenweg",
    "iso:country":"BE",
    "sg:address":"Leuvensesteenweg 104",
    "sg:city":"Aarschot",
    "sg:orig_category":"Fietsen Herstellingen motorfietsen Motorfietsen",
    "sg:phone":"+32 16 56 80 23",
    "sg:postcode":"3200",
    "sg:province":"Vlaams-Brabant",
    "wof:name":"Huis Beynaerts",
    "wof:placetype":"venue"
},
  "geometry": {"coordinates":[4.830286026,50.9829750061],"type":"Point"}
}