{
  "type": "Feature",
  "properties": {
    "iso:country":"BE",
    "sg:address":"Van Schoonbekestraat 56",
    "sg:city":"Antwerpen",
    "sg:orig_category":"Artiesten and kunstenaars",
    "sg:phone":"+32 3 237 60 98",
    "sg:postcode":"2018",
    "sg:province":"Antwerpen",
    "wof:name":"Charles Szukalski",
    "wof:placetype":"venue"
},
  "geometry": {"coordinates":[4.4072060585,51.2025794983],"type":"Point"}
}