{
  "type": "Feature",
  "properties": {
    "addr:full":"Rue Du Vieux-moulin 2c Bastogne Luxembourg 6600",
    "addr:housenumber":"2c",
    "addr:postcode":"6600",
    "addr:street":"Rue Du Vieux-Moulin",
    "iso:country":"BE",
    "sg:address":"Rue Du Vieux-moulin 2c",
    "sg:city":"Bastogne",
    "sg:orig_category":"Elektrische installaties voor woningen HERSTELLING ELEKTRISCHE HUISHOUDAPPARATEN Huishoudapparaten, ",
    "sg:phone":"+32 61 21 45 86",
    "sg:postcode":"6600",
    "sg:province":"Luxembourg",
    "wof:name":"Bouchez-moreau & Fils",
    "wof:placetype":"venue"
},
  "geometry": {"coordinates":[5.7194261551,50.0019454956],"type":"Point"}
}