{
  "type": "Feature",
  "properties": {
    "addr:full":"Avenue De L'etang 23 Mont-saint-guibert Brabant Wallon 1435",
    "addr:housenumber":"23",
    "addr:postcode":"1435",
    "addr:street":"Avenue De L'Etang",
    "iso:country":"BE",
    "sg:address":"Avenue De L'etang 23",
    "sg:city":"Mont-saint-guibert",
    "sg:orig_category":"Herstelling leer and schoeisel",
    "sg:phone":"+32 10 65 82 96",
    "sg:postcode":"1435",
    "sg:province":"Brabant Wallon",
    "wof:name":"Marc Bulinckx",
    "wof:placetype":"venue"
},
  "geometry": {"coordinates":[4.6171741486,50.6369094849],"type":"Point"}
}