{
  "type": "Feature",
  "properties": {
    "addr:full":"Overleiestraat 37 Kortrijk West-Vlaanderen 8500",
    "addr:housenumber":"37",
    "addr:postcode":"8500",
    "addr:street":"Overleiestraat",
    "iso:country":"BE",
    "sg:address":"Overleiestraat 37",
    "sg:city":"Kortrijk",
    "sg:classifiers":[
        {
            "category":"Personal",
            "subcategory":"Beauty Salon",
            "type":"Services"
        }
    ],
    "sg:phone":"+32 56 35 09 47",
    "sg:postcode":"8500",
    "sg:province":"West-Vlaanderen",
    "sg:tags":[
        "lady",
        "-",
        "hairdressing"
    ],
    "wof:name":"Evelyne",
    "wof:placetype":"venue"
},
  "geometry": {"coordinates":[3.2599709034,50.8326721191],"type":"Point"}
}