{
  "type": "Feature",
  "properties": {
    "iso:country":"BE",
    "sg:address":"Avenue De La Lib\u00e9ration 44",
    "sg:city":"Sambreville (auvelais)",
    "sg:classifiers":[
        {
            "category":"Shopping",
            "subcategory":"Jewelry",
            "type":"Retail Goods"
        }
    ],
    "sg:phone":"+32 71 74 05 72",
    "sg:postcode":"5060",
    "sg:province":"Namur",
    "sg:tags":[
        "jeweller",
        "-"
    ],
    "wof:name":"Vandermeulen Bijouterie Sprl",
    "wof:placetype":"venue"
},
  "geometry": {"coordinates":[4.6285200119,50.4448738098],"type":"Point"}
}