{
  "type": "Feature",
  "properties": {
    "addr:full":"Jubileumlaan 51 Gent Oost-Vlaanderen 9000",
    "addr:housenumber":"51",
    "addr:postcode":"9000",
    "addr:street":"Jubileumlaan;Oost-Vlaanderen",
    "iso:country":"BE",
    "sg:address":"Jubileumlaan 51",
    "sg:city":"Gent",
    "sg:orig_category":"Antiek",
    "sg:phone":"+32 9 223 19 38",
    "sg:postcode":"9000",
    "sg:province":"Oost-Vlaanderen",
    "wof:name":"Herbert Biliet",
    "wof:placetype":"venue"
},
  "geometry": {"coordinates":[3.7074949741,51.0470314026],"type":"Point"}
}