{
  "type": "Feature",
  "properties": {
    "addr:full":"Krijgsbaan 154 Mortsel Antwerpen 2640",
    "addr:housenumber":"154",
    "addr:postcode":"2640",
    "addr:street":"Krijgsbaan",
    "iso:country":"BE",
    "sg:address":"Krijgsbaan 154",
    "sg:city":"Mortsel",
    "sg:classifiers":[
        {
            "category":"Bakery",
            "type":"Food & Drink"
        }
    ],
    "sg:phone":"+32 3 440 15 21",
    "sg:postcode":"2640",
    "sg:province":"Antwerpen",
    "sg:tags":[
        "confectioner",
        "baker"
    ],
    "wof:name":"Van Nooten F",
    "wof:placetype":"venue"
},
  "geometry": {"coordinates":[4.4547510147,51.1753578186],"type":"Point"}
}