{
  "type": "Feature",
  "properties": {
    "iso:country":"BE",
    "sg:address":"Paniswijerstraat 92",
    "sg:city":"Genk",
    "sg:classifiers":[
        {
            "category":"Manufacturing",
            "subcategory":"Rubber & Plastics",
            "type":"Manufacturing & Wholesale Goods"
        }
    ],
    "sg:phone":"+32 89 30 05 11",
    "sg:postcode":"3600",
    "sg:province":"Limburg",
    "sg:tags":[
        "industrial",
        "-"
    ],
    "wof:name":"Dsm Specialty Compounds Nv",
    "wof:placetype":"venue"
},
  "geometry": {"coordinates":[5.4738807678,50.938911438],"type":"Point"}
}