{
  "type": "Feature",
  "properties": {
    "addr:full":"Menenstraat 50 Wevelgem West-Vlaanderen 8560",
    "addr:housenumber":"50",
    "addr:postcode":"8560",
    "addr:street":"Menenstraat",
    "iso:country":"BE",
    "sg:address":"Menenstraat 50",
    "sg:city":"Wevelgem",
    "sg:classifiers":[
        {
            "category":"Insurance",
            "subcategory":"Life Insurance",
            "type":"Services"
        }
    ],
    "sg:phone":"+32 56 42 34 60",
    "sg:postcode":"8560",
    "sg:province":"West-Vlaanderen",
    "sg:tags":[
        "assurance"
    ],
    "wof:name":"Bureau Vanassur-vandoorne",
    "wof:placetype":"venue"
},
  "geometry": {"coordinates":[3.1747970581,50.8074111938],"type":"Point"}
}