{
  "type": "Feature",
  "properties": {
    "iso:country":"BE",
    "sg:address":"Oostendestraat 29",
    "sg:city":"Torhout",
    "sg:classifiers":[
        {
            "category":"Cinema",
            "subcategory":"Movie Rental",
            "type":"Entertainment"
        }
    ],
    "sg:phone":"+32 50 22 17 67",
    "sg:postcode":"8820",
    "sg:province":"West-Vlaanderen",
    "sg:tags":[
        "de",
        "cassette",
        "location",
        "vid\u00e9o",
        "audio"
    ],
    "wof:name":"Video Palace",
    "wof:placetype":"venue"
},
  "geometry": {"coordinates":[3.0988049507,51.0656814575],"type":"Point"}
}