{
  "type": "Feature",
  "properties": {
    "iso:country":"BE",
    "sg:address":"Paleisstraat 1bb",
    "sg:city":"Kortrijk",
    "sg:orig_category":"Experts-comptables",
    "sg:phone":"+32 56 20 17 58",
    "sg:postcode":"8500",
    "sg:province":"West-Vlaanderen",
    "wof:name":"J. De Leenheer",
    "wof:placetype":"venue"
},
  "geometry": {"coordinates":[3.2578499317,50.828453064],"type":"Point"}
}