{
  "type": "Feature",
  "properties": {
    "addr:full":"Bosstraat 40 Lochristi Oost-Vlaanderen 9080",
    "addr:housenumber":"40",
    "addr:postcode":"9080",
    "addr:street":"Bosstraat",
    "iso:country":"BE",
    "sg:address":"Bosstraat 40",
    "sg:city":"Lochristi",
    "sg:orig_category":"Eleveurs de bovins",
    "sg:phone":"+32 9 355 54 02",
    "sg:postcode":"9080",
    "sg:province":"Oost-Vlaanderen",
    "wof:name":"Marcel De Baets",
    "wof:placetype":"venue"
},
  "geometry": {"coordinates":[3.846916914,51.1073875427],"type":"Point"}
}