{
  "type": "Feature",
  "properties": {
    "addr:full":"Mechelbaan 182 Putte (beerzel) Antwerpen 2580",
    "addr:housenumber":"182",
    "addr:postcode":"2580",
    "addr:street":"Mechelbaan",
    "iso:country":"BE",
    "sg:address":"Mechelbaan 182",
    "sg:city":"Putte (beerzel)",
    "sg:classifiers":[
        {
            "category":"Professional",
            "subcategory":"Testing Lab",
            "type":"Services"
        }
    ],
    "sg:phone":"+32 15 75 64 31",
    "sg:postcode":"2580",
    "sg:province":"Antwerpen",
    "sg:tags":[
        "chemist"
    ],
    "wof:name":"De Bauw K",
    "wof:placetype":"venue"
},
  "geometry": {"coordinates":[4.6413798332,51.0592308044],"type":"Point"}
}