{
  "type": "Feature",
  "properties": {
    "iso:country":"BE",
    "sg:address":"Antwerpsesteenweg 139",
    "sg:city":"Lochristi",
    "sg:orig_category":"Avocats and conseillers juridiques. Balie van Gent",
    "sg:phone":"+32 9 356 89 00",
    "sg:postcode":"9080",
    "sg:province":"Oost-Vlaanderen",
    "wof:name":"De Coninck Linda",
    "wof:placetype":"venue"
},
  "geometry": {"coordinates":[3.8008840084,51.0857963562],"type":"Point"}
}