{
  "type": "Feature",
  "properties": {
    "iso:country":"BE",
    "sg:address":"Stoofstraat 3-5",
    "sg:city":"Brugge",
    "sg:classifiers":[
        {
            "category":"Restaurant",
            "type":"Food & Drink"
        }
    ],
    "sg:phone":"+32 50 33 69 24",
    "sg:postcode":"8000",
    "sg:province":"West-Vlaanderen",
    "wof:name":"Males Herbes",
    "wof:placetype":"venue"
},
  "geometry": {"coordinates":[3.2247860432,51.2031784058],"type":"Point"}
}