{
  "type": "Feature",
  "properties": {
    "addr:full":"Hugo Verrieststraat 30 Sint-niklaas Oost-Vlaanderen 9100",
    "addr:housenumber":"30",
    "addr:postcode":"9100",
    "addr:street":"Hugo Verrieststraat",
    "iso:country":"BE",
    "sg:address":"Hugo Verrieststraat 30",
    "sg:city":"Sint-niklaas",
    "sg:orig_category":"Postkantoren Verzekeringsmakelaars and experts",
    "sg:phone":"+32 3 776 34 97",
    "sg:postcode":"9100",
    "sg:province":"Oost-Vlaanderen",
    "wof:name":"De Post",
    "wof:placetype":"venue"
},
  "geometry": {"coordinates":[4.1289801598,51.1673698425],"type":"Point"}
}