{
  "type": "Feature",
  "properties": {
    "iso:country":"BE",
    "sg:address":"Hugo Verrieststraat 30",
    "sg:city":"Sint-niklaas",
    "sg:orig_category":"Postkantoren Verzekeringsmakelaars and experts",
    "sg:phone":"+32 3 776 34 97",
    "sg:postcode":"9100",
    "sg:province":"Oost-Vlaanderen",
    "wof:name":"De Post",
    "wof:placetype":"venue"
},
  "geometry": {"coordinates":[4.1289801598,51.1673698425],"type":"Point"}
}