{
  "type": "Feature",
  "properties": {
    "iso:country":"BE",
    "sg:address":"Simon Stevinplein 12",
    "sg:city":"Brugge",
    "sg:classifiers":[
        {
            "category":"Arts & Performance",
            "subcategory":"Art Gallery",
            "type":"Entertainment"
        }
    ],
    "sg:phone":"+32 50 33 37 74",
    "sg:postcode":"8000",
    "sg:province":"West-Vlaanderen",
    "wof:name":"Broes K",
    "wof:placetype":"venue"
},
  "geometry": {"coordinates":[3.2227139473,51.2062721252],"type":"Point"}
}