{
  "type": "Feature",
  "properties": {
    "iso:country":"BE",
    "sg:address":"Rue Des Mesanges 6",
    "sg:city":"Viroinval",
    "sg:orig_category":"Kampeerterreinen",
    "sg:phone":"+32 60 39 94 34",
    "sg:postcode":"5670",
    "sg:province":"Namur",
    "wof:name":"Sabine Colot",
    "wof:placetype":"venue"
},
  "geometry": {"coordinates":[4.6085600853,50.0741271973],"type":"Point"}
}