{
  "type": "Feature",
  "properties": {
    "iso:country":"BE",
    "sg:address":"Stationsstraat 58 Box 12",
    "sg:city":"Lanaken",
    "sg:classifiers":[
        {
            "category":"Insurance",
            "subcategory":"Insurance Agent",
            "type":"Services"
        }
    ],
    "sg:phone":"+32 89 72 23 86",
    "sg:postcode":"3620",
    "sg:province":"Limburg",
    "sg:tags":[
        "broker"
    ],
    "wof:name":"Fripont",
    "wof:placetype":"venue"
},
  "geometry": {"coordinates":[5.6487631798,50.8878974915],"type":"Point"}
}