{
  "type": "Feature",
  "properties": {
    "addr:full":"52 Genkersteenweg 3500 Hasselt 52",
    "addr:housenumber":"52;52",
    "addr:postcode":"3500",
    "addr:street":"Genkersteenweg",
    "iso:country":"BE",
    "sg:address":"52",
    "sg:city":"Genkersteenweg 3500 Hasselt",
    "sg:classifiers":[
        {
            "category":"Travel",
            "subcategory":"Hotels & Motels",
            "type":"Entertainment"
        }
    ],
    "sg:phone":"+32 11 24 11 83",
    "sg:postcode":"52",
    "sg:tags":[
        "hotels",
        "business",
        "restaurant"
    ],
    "wof:name":"Sombrero Hasselt Nv",
    "wof:placetype":"venue"
},
  "geometry": {"coordinates":[5.3818202019,50.9449386597],"type":"Point"}
}