{
  "type": "Feature",
  "properties": {
    "addr:full":"Plein 117 Kaprijke Oost-Vlaanderen 9970",
    "addr:housenumber":"117",
    "addr:postcode":"9970",
    "addr:street":"Plein",
    "iso:country":"BE",
    "sg:address":"Plein 117",
    "sg:city":"Kaprijke",
    "sg:orig_category":"Belastingconsulenten Diverse juridische dienstverlening",
    "sg:phone":"+32 9 373 58 56",
    "sg:postcode":"9970",
    "sg:province":"Oost-Vlaanderen",
    "wof:name":"Leentje Jongbloet",
    "wof:placetype":"venue"
},
  "geometry": {"coordinates":[3.6179549694,51.2161941528],"type":"Point"}
}