{
  "type": "Feature",
  "properties": {
    "iso:country":"BE",
    "sg:address":"Verbindingsstraat 39",
    "sg:city":"Nijlen",
    "sg:classifiers":[
        {
            "category":"Building & Trades",
            "subcategory":"Electrical",
            "type":"Services"
        }
    ],
    "sg:phone":"+32 3 411 26 54",
    "sg:postcode":"2560",
    "sg:province":"Antwerpen",
    "sg:tags":[
        "electric",
        "-",
        "housewiring",
        "contractor"
    ],
    "wof:name":"Capelle K",
    "wof:placetype":"venue"
},
  "geometry": {"coordinates":[4.6913518906,51.1682662964],"type":"Point"}
}