{
  "type": "Feature",
  "properties": {
    "addr:full":"Av. Du G\u00c9n\u00c9ral De Gaulle 102 Mons Hainaut 7000",
    "addr:housenumber":"102",
    "addr:postcode":"7000",
    "addr:street":"Av. Du Ge\u0301Ne\u0301Ral De Gaulle;Hainaut",
    "iso:country":"BE",
    "sg:address":"Av. Du G\u00c9n\u00c9ral De Gaulle 102",
    "sg:city":"Mons",
    "sg:orig_category":"Maatschappelijke dienstverlening",
    "sg:phone":"+32 65 38 22 45",
    "sg:postcode":"7000",
    "sg:province":"Hainaut",
    "wof:name":"Centre P.m.s.",
    "wof:placetype":"venue"
},
  "geometry": {"coordinates":[3.9463100433,50.4432487488],"type":"Point"}
}