{
  "type": "Feature",
  "properties": {
    "addr:full":"Rue De L'h\u00f4tel Des Monnaies 88 Bruxelles (saint-gilles) Bruxelles-Capitale 1060",
    "addr:housenumber":"88",
    "addr:postcode":"1060",
    "addr:street":"Rue De L'Ho;Des Monnaies",
    "iso:country":"BE",
    "sg:address":"Rue De L'h\u00f4tel Des Monnaies 88",
    "sg:city":"Bruxelles (saint-gilles)",
    "sg:classifiers":[
        {
            "category":"Retail",
            "subcategory":"Event Space",
            "type":"Services"
        }
    ],
    "sg:phone":"+32 2 538 65 80",
    "sg:postcode":"1060",
    "sg:province":"Bruxelles-Capitale",
    "sg:tags":[
        "organisation"
    ],
    "wof:name":"Compagnons Du Soir Asbl",
    "wof:placetype":"venue"
},
  "geometry": {"coordinates":[4.3479399681,50.8302650452],"type":"Point"}
}