{
  "type": "Feature",
  "properties": {
    "iso:country":"BE",
    "sg:address":"Achterheide 2",
    "sg:city":"Puurs",
    "sg:orig_category":"Slagers",
    "sg:phone":"+32 3 889 75 94",
    "sg:postcode":"2870",
    "sg:province":"Antwerpen",
    "wof:name":"Franky Meert",
    "wof:placetype":"venue"
},
  "geometry": {"coordinates":[4.266726017,51.0567016602],"type":"Point"}
}