{
  "type": "Feature",
  "properties": {
    "addr:full":"Torhoutsesteenweg 408 Oostende West-Vlaanderen 8400",
    "addr:housenumber":"408",
    "addr:postcode":"8400",
    "addr:street":"Torhoutsesteenweg",
    "iso:country":"BE",
    "sg:address":"Torhoutsesteenweg 408",
    "sg:city":"Oostende",
    "sg:orig_category":"Fietsen Motorfietsen",
    "sg:phone":"+32 59 70 01 04",
    "sg:postcode":"8400",
    "sg:province":"West-Vlaanderen",
    "wof:name":"Brackx",
    "wof:placetype":"venue"
},
  "geometry": {"coordinates":[2.9057509899,51.2124557495],"type":"Point"}
}