{
  "type": "Feature",
  "properties": {
    "addr:full":"De Robianostraat 56 Borsbeek Antwerpen 2150",
    "addr:housenumber":"56",
    "addr:postcode":"2150",
    "addr:street":"De Robianostraat",
    "iso:country":"BE",
    "sg:address":"De Robianostraat 56",
    "sg:city":"Borsbeek",
    "sg:orig_category":"Assurances. Bureaux de poste",
    "sg:phone":"+32 3 321 07 10",
    "sg:postcode":"2150",
    "sg:province":"Antwerpen",
    "wof:name":"De Post",
    "wof:placetype":"venue"
},
  "geometry": {"coordinates":[4.4851331711,51.1942977905],"type":"Point"}
}