{
  "type": "Feature",
  "properties": {
    "iso:country":"BE",
    "sg:address":"Deuzeldlaan 89",
    "sg:city":"Schoten",
    "sg:orig_category":"Mobiele kappers",
    "sg:phone":"+32 3 646 43 76",
    "sg:postcode":"2900",
    "sg:province":"Antwerpen",
    "wof:name":"Haartooi Aan Huis",
    "wof:placetype":"venue"
},
  "geometry": {"coordinates":[4.4651198387,51.2448234558],"type":"Point"}
}