{
  "type": "Feature",
  "properties": {
    "iso:country":"BE",
    "sg:address":"Dweersstraat 41",
    "sg:city":"Izegem",
    "sg:classifiers":[
        {
            "category":"Building & Trades",
            "subcategory":"Cleaning & Sanitation",
            "type":"Services"
        }
    ],
    "sg:phone":"+32 51 31 52 36",
    "sg:postcode":"8870",
    "sg:province":"West-Vlaanderen",
    "sg:tags":[
        "cleaner",
        "window"
    ],
    "wof:name":"Trish Schoonmaakbedrijf",
    "wof:placetype":"venue"
},
  "geometry": {"coordinates":[3.2120840549,50.9152374268],"type":"Point"}
}