{
  "type": "Feature",
  "properties": {
    "addr:full":"Koning Albertstraat 171 Ravels (weelde) Antwerpen 2381",
    "addr:housenumber":"171",
    "addr:postcode":"2381",
    "addr:street":"Koning Albertstraat",
    "iso:country":"BE",
    "sg:address":"Koning Albertstraat 171",
    "sg:city":"Ravels (weelde)",
    "sg:classifiers":[
        {
            "category":"Health Services",
            "subcategory":"Health Practitioner",
            "type":"Services"
        }
    ],
    "sg:phone":"+32 14 65 68 16",
    "sg:postcode":"2381",
    "sg:province":"Antwerpen",
    "sg:tags":[
        "physiotherapist"
    ],
    "wof:name":"Frijters I",
    "wof:placetype":"venue"
},
  "geometry": {"coordinates":[4.9941730499,51.4098396301],"type":"Point"}
}