{
  "type": "Feature",
  "properties": {
    "iso:country":"BE",
    "sg:address":"Geldenaaksebaan 442",
    "sg:city":"Leuven",
    "sg:orig_category":"Banken and kredietinstellingen",
    "sg:phone":"+32 16 40 21 88",
    "sg:postcode":"3001",
    "sg:province":"Vlaams-Brabant",
    "wof:name":"Fortis",
    "wof:placetype":"venue"
},
  "geometry": {"coordinates":[4.7226810455,50.8500175476],"type":"Point"}
}