{
  "type": "Feature",
  "properties": {
    "addr:full":"Augustijnenstraat 18 Oud-turnhout Antwerpen 2360",
    "addr:housenumber":"18",
    "addr:postcode":"2360",
    "addr:street":"Augustijnenstraat",
    "iso:country":"BE",
    "sg:address":"Augustijnenstraat 18",
    "sg:city":"Oud-turnhout",
    "sg:classifiers":[
        {
            "category":"Cafe",
            "type":"Food & Drink"
        }
    ],
    "sg:phone":"+32 14 45 28 29",
    "sg:postcode":"2360",
    "sg:province":"Antwerpen",
    "sg:tags":[
        "caf\u00e9s"
    ],
    "wof:name":"Jozef Stevens",
    "wof:placetype":"venue"
},
  "geometry": {"coordinates":[4.9937400818,51.3101387024],"type":"Point"}
}