{
  "type": "Feature",
  "properties": {
    "addr:full":"Dolezlaan 125 Ukkel/uccle Bruxelles-Capitale 1180",
    "addr:housenumber":"125",
    "addr:postcode":"1180",
    "addr:street":"Dolezlaan;/",
    "iso:country":"BE",
    "sg:address":"Dolezlaan 125",
    "sg:city":"Ukkel/uccle",
    "sg:orig_category":"Meubelzaken, woning- and keukeninrichting Tweedehandsgoederen",
    "sg:phone":"+32 2 375 69 70",
    "sg:postcode":"1180",
    "sg:province":"Bruxelles-Capitale",
    "wof:name":"Tant Qu'il Y Aura Des Anges",
    "wof:placetype":"venue"
},
  "geometry": {"coordinates":[4.3567008972,50.7824897766],"type":"Point"}
}