{
  "type": "Feature",
  "properties": {
    "iso:country":"BE",
    "sg:address":"Rocherath 34",
    "sg:city":"Bullingen",
    "sg:orig_category":"Goederenvervoer over de weg",
    "sg:phone":"+32 80 64 71 74",
    "sg:postcode":"4761",
    "sg:province":"Li\u00e8ge",
    "wof:name":"Rauw M.a. Transports",
    "wof:placetype":"venue"
},
  "geometry": {"coordinates":[6.2963399887,50.4319496155],"type":"Point"}
}