{
  "type": "Feature",
  "properties": {
    "iso:country":"BE",
    "sg:address":"Essenlaan 5 Box 4",
    "sg:city":"Genk (waterschei)",
    "sg:classifiers":[
        {
            "category":"Juice Bar",
            "subcategory":"None",
            "type":"Food & Drink"
        }
    ],
    "sg:phone":"+32 89 84 51 74",
    "sg:postcode":"3600",
    "sg:province":"Limburg",
    "sg:tags":[
        "fruit",
        "syrup"
    ],
    "wof:name":"Oranka Jus De Fruits Bvba",
    "wof:placetype":"venue"
},
  "geometry": {"coordinates":[5.4878101349,51.0077934265],"type":"Point"}
}