{
  "type": "Feature",
  "properties": {
    "iso:country":"BE",
    "sg:address":"Place Xavier-neujean 36",
    "sg:city":"Li\u00e8ge 1",
    "sg:classifiers":[
        {
            "category":"Social Services",
            "type":"Services"
        }
    ],
    "sg:phone":"+32 4 223 18 26",
    "sg:postcode":"4000",
    "sg:province":"Li\u00e8ge",
    "wof:name":"Icar Wallonie Asbl",
    "wof:placetype":"venue"
},
  "geometry": {"coordinates":[5.5670771599,50.6428642273],"type":"Point"}
}