{
  "type": "Feature",
  "properties": {
    "addr:full":"Kapelstraat 135 Boom Antwerpen 2850",
    "addr:housenumber":"135",
    "addr:postcode":"2850",
    "addr:street":"Kapelstraat",
    "iso:country":"BE",
    "sg:address":"Kapelstraat 135",
    "sg:city":"Boom",
    "sg:classifiers":[
        {
            "category":"Health Services",
            "subcategory":"Dentist",
            "type":"Services"
        }
    ],
    "sg:phone":"+32 3 844 32 60",
    "sg:postcode":"2850",
    "sg:province":"Antwerpen",
    "wof:name":"De Raeymaecker V",
    "wof:placetype":"venue"
},
  "geometry": {"coordinates":[4.380302906,51.0855560303],"type":"Point"}
}