{
  "type": "Feature",
  "properties": {
    "iso:country":"BE",
    "sg:address":"Van Cromphoutstraat 24",
    "sg:city":"Wetteren",
    "sg:orig_category":"Schoonheidssalons Tatoeages and piercings",
    "sg:phone":"+32 9 369 67 99",
    "sg:postcode":"9230",
    "sg:province":"Oost-Vlaanderen",
    "wof:name":"Tatoo Gino",
    "wof:placetype":"venue"
},
  "geometry": {"coordinates":[3.8835499287,51.0072174072],"type":"Point"}
}