{
  "type": "Feature",
  "properties": {
    "addr:full":"Aarlenstraat 82 Bruxelles (etterbeek) Bruxelles-Capitale 1040",
    "addr:housenumber":"82",
    "addr:postcode":"1040",
    "addr:street":"Aarlenstraat",
    "iso:country":"BE",
    "sg:address":"Aarlenstraat 82",
    "sg:city":"Bruxelles (etterbeek)",
    "sg:classifiers":[
        {
            "category":"Retail",
            "subcategory":"Event Space",
            "type":"Services"
        }
    ],
    "sg:phone":"+32 2 286 41 51",
    "sg:postcode":"1040",
    "sg:province":"Bruxelles-Capitale",
    "sg:tags":[
        "rental",
        "-",
        "hall"
    ],
    "wof:name":"Concert Noble Nv",
    "wof:placetype":"venue"
},
  "geometry": {"coordinates":[4.3732891083,50.8419494629],"type":"Point"}
}