{
  "type": "Feature",
  "properties": {
    "addr:full":"Bois Ten Bosse 22 Flobecq Hainaut 7880",
    "addr:housenumber":"22",
    "addr:postcode":"7880",
    "addr:street":"Bois Ten Bosse;Hainaut",
    "iso:country":"BE",
    "sg:address":"Bois Ten Bosse 22",
    "sg:city":"Flobecq",
    "sg:classifiers":[
        {
            "category":"Food & Beverages",
            "subcategory":"Groceries & Convenience Stores",
            "type":"Retail Goods"
        }
    ],
    "sg:phone":"+32 68 44 71 75",
    "sg:postcode":"7880",
    "sg:province":"Hainaut",
    "sg:tags":[
        "grocer"
    ],
    "wof:name":"Austraete A",
    "wof:placetype":"venue"
},
  "geometry": {"coordinates":[3.7315649986,50.7681045532],"type":"Point"}
}