{
  "type": "Feature",
  "properties": {
    "addr:full":"108 Stasegemsesteenweg 8500 Kortrijk 108",
    "addr:housenumber":"108;108",
    "addr:postcode":"8500",
    "addr:street":"Stasegemsesteenweg;Kortrijk",
    "iso:country":"BE",
    "sg:address":"108",
    "sg:city":"Stasegemsesteenweg 8500 Kortrijk",
    "sg:classifiers":[
        {
            "category":"Wholesale",
            "subcategory":"Meat",
            "type":"Manufacturing & Wholesale Goods"
        }
    ],
    "sg:phone":"+32 56 22 00 07",
    "sg:postcode":"108",
    "sg:tags":[
        "food",
        "cooked",
        "product",
        "related"
    ],
    "wof:name":"Vleeshalle Cps Nv",
    "wof:placetype":"venue"
},
  "geometry": {"coordinates":[3.295030117,50.8292198181],"type":"Point"}
}