{
  "type": "Feature",
  "properties": {
    "iso:country":"BE",
    "sg:address":"Lessensestraat 36",
    "sg:city":"Geraardsbergen",
    "sg:classifiers":[
        {
            "category":"Travel",
            "subcategory":"Hotels & Motels",
            "type":"Entertainment"
        }
    ],
    "sg:phone":"+32 54 41 20 73",
    "sg:postcode":"9500",
    "sg:province":"Oost-Vlaanderen",
    "wof:name":"Geeraard",
    "wof:placetype":"venue"
},
  "geometry": {"coordinates":[3.8756639957,50.7707710266],"type":"Point"}
}