{
  "type": "Feature",
  "properties": {
    "addr:full":"Kapelstraat 48 Baarle-hertog Antwerpen 2387",
    "addr:housenumber":"48",
    "addr:postcode":"2387",
    "addr:street":"Kapelstraat",
    "iso:country":"BE",
    "sg:address":"Kapelstraat 48",
    "sg:city":"Baarle-hertog",
    "sg:orig_category":"Varkenskwekers",
    "sg:phone":"+32 14 69 90 29",
    "sg:postcode":"2387",
    "sg:province":"Antwerpen",
    "wof:name":"Josephus Klaasen",
    "wof:placetype":"venue"
},
  "geometry": {"coordinates":[4.9362998009,51.4420013428],"type":"Point"}
}