{
  "type": "Feature",
  "properties": {
    "iso:country":"BE",
    "sg:address":"Place Fontainas 18-20",
    "sg:city":"Bruxelles",
    "sg:orig_category":"H\u00f4tels",
    "sg:phone":"+32 2 511 19 72",
    "sg:postcode":"1000",
    "sg:province":"Bruxelles-Capitale",
    "wof:name":"Mirabeau",
    "wof:placetype":"venue"
},
  "geometry": {"coordinates":[4.3467612267,50.8449554443],"type":"Point"}
}