{
  "type": "Feature",
  "properties": {
    "iso:country":"BE",
    "sg:address":"Place Jules Francq 1",
    "sg:city":"Charleroi (jumet)",
    "sg:classifiers":[
        {
            "category":"Bars & Pubs",
            "type":"Food & Drink"
        }
    ],
    "sg:phone":"+32 71 35 14 28",
    "sg:postcode":"6040",
    "sg:province":"Hainaut",
    "wof:name":"Vy Heigne (au)",
    "wof:placetype":"venue"
},
  "geometry": {"coordinates":[4.4103999138,50.4448204041],"type":"Point"}
}