{
  "type": "Feature",
  "properties": {
    "iso:country":"BE",
    "sg:address":"Kerkstraat 46",
    "sg:city":"Sint-lievens-houtem (letterhoutem)",
    "sg:classifiers":[
        {
            "category":"Farming",
            "subcategory":"Crops",
            "type":"Manufacturing & Wholesale Goods"
        }
    ],
    "sg:phone":"+32 53 62 29 85",
    "sg:postcode":"9521",
    "sg:province":"Oost-Vlaanderen",
    "sg:tags":[
        "vegetable",
        "fruit",
        "-",
        "grower"
    ],
    "wof:name":"Erauw J",
    "wof:placetype":"venue"
},
  "geometry": {"coordinates":[3.8810091019,50.9290313721],"type":"Point"}
}