{
  "type": "Feature",
  "properties": {
    "iso:country":"BE",
    "sg:address":"Maloulaan 35",
    "sg:city":"Ieper",
    "sg:orig_category":"Imprimeries and copyshops",
    "sg:phone":"+32 57 20 15 51",
    "sg:postcode":"8900",
    "sg:province":"West-Vlaanderen",
    "wof:name":"Deleye",
    "wof:placetype":"venue"
},
  "geometry": {"coordinates":[2.8765919209,50.8506355286],"type":"Point"}
}