{
  "type": "Feature",
  "properties": {
    "iso:country":"BE",
    "sg:address":"Avenue Prof. Henrijean 14",
    "sg:city":"Spa",
    "sg:orig_category":"Rusthuizen and serviceflats",
    "sg:phone":"+32 87 77 46 91",
    "sg:postcode":"4900",
    "sg:province":"Li\u00e8ge",
    "wof:name":"Les Bleuets",
    "wof:placetype":"venue"
},
  "geometry": {"coordinates":[5.8591389656,50.4871711731],"type":"Point"}
}