{
  "type": "Feature",
  "properties": {
    "addr:full":"Rue Des Bas Champs 12 Espierres-helchin (helchin) West-Vlaanderen 8587",
    "addr:housenumber":"12",
    "addr:postcode":"8587",
    "addr:street":"Rue Des Bas Champs;Helchin",
    "iso:country":"BE",
    "sg:address":"Rue Des Bas Champs 12",
    "sg:city":"Espierres-helchin (helchin)",
    "sg:classifiers":[
        {
            "category":"Personal",
            "subcategory":"Beauty Salon",
            "type":"Services"
        }
    ],
    "sg:phone":"+32 56 45 58 90",
    "sg:postcode":"8587",
    "sg:province":"West-Vlaanderen",
    "sg:tags":[
        "lady",
        "-",
        "hairdressing"
    ],
    "wof:name":"Nadine",
    "wof:placetype":"venue"
},
  "geometry": {"coordinates":[3.3850839138,50.7310562134],"type":"Point"}
}