{
  "type": "Feature",
  "properties": {
    "addr:full":"Sint-servaesstraat 90 Kampenhout Vlaams-Brabant 1910",
    "addr:housenumber":"90",
    "addr:postcode":"1910",
    "addr:street":"Sint-Servaesstraat",
    "iso:country":"BE",
    "sg:address":"Sint-servaesstraat 90",
    "sg:city":"Kampenhout",
    "sg:orig_category":"Groententeelt",
    "sg:phone":"+32 16 65 62 25",
    "sg:postcode":"1910",
    "sg:province":"Vlaams-Brabant",
    "wof:name":"Borremans Dany & Stefaan",
    "wof:placetype":"venue"
},
  "geometry": {"coordinates":[4.5208668709,50.9488182068],"type":"Point"}
}