{
  "type": "Feature",
  "properties": {
    "iso:country":"BE",
    "sg:address":"Steenweg 160",
    "sg:city":"Lanaken",
    "sg:classifiers":[
        {
            "category":"Cafe",
            "type":"Food & Drink"
        }
    ],
    "sg:phone":"+32 89 71 62 15",
    "sg:postcode":"3621",
    "sg:province":"Limburg",
    "sg:tags":[
        "caf\u00e9s"
    ],
    "wof:name":"Caf\u00c9 Palace",
    "wof:placetype":"venue"
},
  "geometry": {"coordinates":[5.6863508224,50.9233436584],"type":"Point"}
}