{
  "type": "Feature",
  "properties": {
    "addr:full":"Rue D\u00c9sir\u00c9 Streel 8 Hannut Li\u00e8ge 4280",
    "addr:housenumber":"8",
    "addr:postcode":"4280",
    "addr:street":"Rue De\u0301Sire\u0301 Streel",
    "iso:country":"BE",
    "sg:address":"Rue D\u00c9sir\u00c9 Streel 8",
    "sg:city":"Hannut",
    "sg:orig_category":"Entretien and r\u00e9parations de voitures",
    "sg:phone":"+32 19 51 36 92",
    "sg:postcode":"4280",
    "sg:province":"Li\u00e8ge",
    "wof:name":"Carrosserie Rethy",
    "wof:placetype":"venue"
},
  "geometry": {"coordinates":[5.1262078285,50.6974334717],"type":"Point"}
}