{
  "type": "Feature",
  "properties": {
    "iso:country":"BE",
    "sg:address":"Goudbergstraat 28",
    "sg:city":"Wevelgem",
    "sg:classifiers":[
        {
            "category":"Health Services",
            "subcategory":"Doctor",
            "type":"Services"
        }
    ],
    "sg:phone":"+32 56 41 11 40",
    "sg:postcode":"8560",
    "sg:province":"West-Vlaanderen",
    "sg:tags":[
        "medicinephysicians",
        "surgeon"
    ],
    "wof:name":"Deloose Koen",
    "wof:placetype":"venue"
},
  "geometry": {"coordinates":[3.1858239174,50.8048629761],"type":"Point"}
}