{
  "type": "Feature",
  "properties": {
    "iso:country":"BE",
    "sg:address":"Wantestraat 26",
    "sg:city":"Oostrozebeke",
    "sg:orig_category":"Ramassage and traitement des d\u00e9chets m\u00e9nagers",
    "sg:phone":"+32 56 66 64 90",
    "sg:postcode":"8780",
    "sg:province":"West-Vlaanderen",
    "wof:name":"Destotrans",
    "wof:placetype":"venue"
},
  "geometry": {"coordinates":[3.2883501053,50.9126853943],"type":"Point"}
}