{
  "type": "Feature",
  "properties": {
    "addr:full":"Ganzenstraat 28 Brugge West-Vlaanderen 8000",
    "addr:housenumber":"28",
    "addr:postcode":"8000",
    "addr:street":"Ganzenstraat",
    "iso:country":"BE",
    "sg:address":"Ganzenstraat 28",
    "sg:city":"Brugge",
    "sg:classifiers":[
        {
            "category":"Health Services",
            "subcategory":"Health Practitioner",
            "type":"Services"
        }
    ],
    "sg:phone":"+32 50 33 07 20",
    "sg:postcode":"8000",
    "sg:province":"West-Vlaanderen",
    "sg:tags":[
        "physiotherapist"
    ],
    "wof:name":"Vandendriessche Inge",
    "wof:placetype":"venue"
},
  "geometry": {"coordinates":[3.2347431183,51.2089500427],"type":"Point"}
}