{
  "type": "Feature",
  "properties": {
    "addr:full":"Leestsesteenweg 2 Mechelen Antwerpen 2800",
    "addr:housenumber":"2",
    "addr:postcode":"2800",
    "addr:street":"Leestsesteenweg",
    "iso:country":"BE",
    "sg:address":"Leestsesteenweg 2",
    "sg:city":"Mechelen",
    "sg:classifiers":[
        {
            "category":"Fast Food",
            "type":"Food & Drink"
        }
    ],
    "sg:phone":"+32 15 20 51 21",
    "sg:postcode":"2800",
    "sg:province":"Antwerpen",
    "sg:tags":[
        "meeneem",
        "restaurant"
    ],
    "wof:name":"Dynasty Garden",
    "wof:placetype":"venue"
},
  "geometry": {"coordinates":[4.4403419495,51.0401420593],"type":"Point"}
}