{
  "type": "Feature",
  "properties": {
    "addr:full":"Rue Du Centre 6 Anthisnes Li\u00e8ge 4160",
    "addr:housenumber":"6",
    "addr:postcode":"4160",
    "addr:street":"Rue Du Centre",
    "iso:country":"BE",
    "sg:address":"Rue Du Centre 6",
    "sg:city":"Anthisnes",
    "sg:orig_category":"Warenhuizen",
    "sg:phone":"+32 4 383 62 63",
    "sg:postcode":"4160",
    "sg:province":"Li\u00e8ge",
    "wof:name":"Caes D.-resimont & Dodet",
    "wof:placetype":"venue"
},
  "geometry": {"coordinates":[5.5203819275,50.4800567627],"type":"Point"}
}