{
  "type": "Feature",
  "properties": {
    "addr:full":"Kerkstr 95 St. Gilles Oost-Vlaanderen 9170",
    "addr:housenumber":"95",
    "addr:postcode":"9170",
    "addr:street":"Kerkstr",
    "iso:country":"BE",
    "sg:address":"Kerkstr 95",
    "sg:city":"St. Gilles",
    "sg:classifiers":[
        {
            "category":"Banks & Credit Unions",
            "subcategory":"Bank",
            "type":"Services"
        }
    ],
    "sg:phone":"+32 3 770 69 93",
    "sg:postcode":"9170",
    "sg:province":"Oost-Vlaanderen",
    "wof:name":"G\u00e9n\u00e9rale De Banque Sa",
    "wof:placetype":"venue"
},
  "geometry": {"coordinates":[4.125934124,51.21900177],"type":"Point"}
}