{
  "type": "Feature",
  "properties": {
    "addr:full":"Scheldestraat 49 Otegem West-Vlaanderen 8553",
    "addr:housenumber":"49",
    "addr:postcode":"8553",
    "addr:street":"Scheldestraat",
    "iso:country":"BE",
    "sg:address":"Scheldestraat 49",
    "sg:city":"Otegem",
    "sg:classifiers":[
        {
            "category":"Shopping",
            "subcategory":"Crafts & Fabrics",
            "type":"Retail Goods"
        }
    ],
    "sg:phone":"+32 56 77 85 08",
    "sg:postcode":"8553",
    "sg:province":"West-Vlaanderen",
    "sg:tags":[
        "decorative"
    ],
    "wof:name":"Jozef Defoor Nv",
    "wof:placetype":"venue"
},
  "geometry": {"coordinates":[3.4278149605,50.8031234741],"type":"Point"}
}