{
  "type": "Feature",
  "properties": {
    "addr:full":"Flinkstraat 40 Hasselt (stevoort) Limburg 3512",
    "addr:housenumber":"40",
    "addr:postcode":"3512",
    "addr:street":"Flinkstraat",
    "iso:country":"BE",
    "sg:address":"Flinkstraat 40",
    "sg:city":"Hasselt (stevoort)",
    "sg:classifiers":[
        {
            "category":"Health Services",
            "subcategory":"Health Practitioner",
            "type":"Services"
        }
    ],
    "sg:phone":"+32 11 31 33 89",
    "sg:postcode":"3512",
    "sg:province":"Limburg",
    "sg:tags":[
        "physiotherapist"
    ],
    "wof:name":"Philtjens Fabian",
    "wof:placetype":"venue"
},
  "geometry": {"coordinates":[5.2540922165,50.9221839905],"type":"Point"}
}