{
  "type": "Feature",
  "properties": {
    "addr:full":"Rue Du S\u00c9woir 52 Lens Hainaut 7870",
    "addr:housenumber":"52",
    "addr:postcode":"7870",
    "addr:street":"Rue Du Se\u0301Woir",
    "iso:country":"BE",
    "sg:address":"Rue Du S\u00c9woir 52",
    "sg:city":"Lens",
    "sg:orig_category":"Eleveurs de bovins",
    "sg:phone":"+32 65 22 56 03",
    "sg:postcode":"7870",
    "sg:province":"Hainaut",
    "wof:name":"Paul Fourmois",
    "wof:placetype":"venue"
},
  "geometry": {"coordinates":[3.9010300636,50.5534095764],"type":"Point"}
}