{
  "type": "Feature",
  "properties": {
    "addr:full":"Ericalaan 1 Sint-genesius-rode/rhode-saint-genese Vlaams-Brabant 1640",
    "addr:housenumber":"1",
    "addr:postcode":"1640",
    "addr:street":"Ericalaan",
    "iso:country":"BE",
    "sg:address":"Ericalaan 1",
    "sg:city":"Sint-genesius-rode/rhode-saint-genese",
    "sg:orig_category":"Beheer onroerend goed",
    "sg:phone":"+32 2 358 26 66",
    "sg:postcode":"1640",
    "sg:province":"Vlaams-Brabant",
    "wof:name":"Ren\u00c9 De Biolley",
    "wof:placetype":"venue"
},
  "geometry": {"coordinates":[4.3769302368,50.7668838501],"type":"Point"}
}