{
  "type": "Feature",
  "properties": {
    "iso:country":"BE",
    "sg:address":"Sint-jansstraat 6",
    "sg:city":"Rotselaar (werchter)",
    "sg:classifiers":[
        {
            "category":"Professional",
            "subcategory":"Printing & Photocopies",
            "type":"Services"
        }
    ],
    "sg:phone":"+32 16 60 22 69",
    "sg:postcode":"3118",
    "sg:province":"Vlaams-Brabant",
    "sg:tags":[
        "trophy",
        "medal"
    ],
    "wof:name":"Shopping Nicole",
    "wof:placetype":"venue"
},
  "geometry": {"coordinates":[4.694961071,50.9713287354],"type":"Point"}
}