{
  "type": "Feature",
  "properties": {
    "iso:country":"BE",
    "sg:address":"Route Napol\u00c9on 49",
    "sg:city":"Flemalle",
    "sg:orig_category":"Benzinestations and brandstoffen",
    "sg:phone":"+32 4 337 05 51",
    "sg:postcode":"4400",
    "sg:province":"Li\u00e8ge",
    "wof:name":"Texaco",
    "wof:placetype":"venue"
},
  "geometry": {"coordinates":[5.4576430321,50.5693130493],"type":"Point"}
}