{
  "type": "Feature",
  "properties": {
    "addr:full":"Generaal Thysstraat 12 Elsene/ixelles Bruxelles-Capitale 1050",
    "addr:housenumber":"12",
    "addr:postcode":"1050",
    "addr:street":"Generaal Thysstraat",
    "iso:country":"BE",
    "sg:address":"Generaal Thysstraat 12",
    "sg:city":"Elsene/ixelles",
    "sg:orig_category":"Sportclubs",
    "sg:phone":"+32 2 673 52 51",
    "sg:postcode":"1050",
    "sg:province":"Bruxelles-Capitale",
    "wof:name":"Budo Club Samourai",
    "wof:placetype":"venue"
},
  "geometry": {"coordinates":[4.3932981491,50.8179016113],"type":"Point"}
}