{
  "type": "Feature",
  "properties": {
    "addr:full":"Rue L\u00e9opold I 308 Bruxelles (jette) Bruxelles-Capitale 1090",
    "addr:housenumber":"308",
    "addr:postcode":"1090",
    "addr:street":"Rue Le\u0301Opold I",
    "iso:country":"BE",
    "sg:address":"Rue L\u00e9opold I 308",
    "sg:city":"Bruxelles (jette)",
    "sg:classifiers":[
        {
            "category":"Real Estate",
            "subcategory":"Architect",
            "type":"Services"
        }
    ],
    "sg:phone":"+32 2 425 10 66",
    "sg:postcode":"1090",
    "sg:province":"Bruxelles-Capitale",
    "wof:name":"Caekelbergh D",
    "wof:placetype":"venue"
},
  "geometry": {"coordinates":[4.3364019394,50.8756256104],"type":"Point"}
}