{
  "type": "Feature",
  "properties": {
    "addr:full":"Rue Des M\u00c9sanges 13 Tournai Hainaut 7540",
    "addr:housenumber":"13",
    "addr:postcode":"7540",
    "addr:street":"Rue Des Me\u0301Sanges",
    "iso:country":"BE",
    "sg:address":"Rue Des M\u00c9sanges 13",
    "sg:city":"Tournai",
    "sg:orig_category":"M\u00e9decins and sp\u00e9cialistes",
    "sg:phone":"+32 69 21 40 93",
    "sg:postcode":"7540",
    "sg:province":"Hainaut",
    "wof:name":"B. De Keyser",
    "wof:placetype":"venue"
},
  "geometry": {"coordinates":[3.3858180046,50.6237335205],"type":"Point"}
}