{
  "type": "Feature",
  "properties": {
    "addr:full":"Winketkaai 6b7 Mechelen Antwerpen 2800",
    "addr:housenumber":"6b7",
    "addr:postcode":"2800",
    "addr:street":"Winketkaai",
    "iso:country":"BE",
    "sg:address":"Winketkaai 6b7",
    "sg:city":"Mechelen",
    "sg:orig_category":"Meubles D\u00e9taillants, Am\u00e9nagement de B\u00e2timents et de Cuisines. R\u00e9paration and restauration de meubles",
    "sg:phone":"+32 15 26 06 06",
    "sg:postcode":"2800",
    "sg:province":"Antwerpen",
    "wof:name":"Clubmeubelfabriek Cammers",
    "wof:placetype":"venue"
},
  "geometry": {"coordinates":[4.4707131386,51.0304641724],"type":"Point"}
}