{
  "type": "Feature",
  "properties": {
    "iso:country":"BE",
    "sg:address":"Square Des Braves 3",
    "sg:city":"Linkebeek",
    "sg:classifiers":[
        {
            "category":"Personal",
            "subcategory":"Beauty Salon",
            "type":"Services"
        }
    ],
    "sg:phone":"+32 2 380 75 37",
    "sg:postcode":"1630",
    "sg:province":"Vlaams-Brabant",
    "sg:tags":[
        "lady",
        "-",
        "hairdressing"
    ],
    "wof:name":"H\u00e9l\u00e8ne Coiffure",
    "wof:placetype":"venue"
},
  "geometry": {"coordinates":[4.3351149559,50.7736244202],"type":"Point"}
}