{
  "type": "Feature",
  "properties": {
    "iso:country":"BE",
    "sg:address":"Rozebeeksestraat 76",
    "sg:city":"Lendelede",
    "sg:orig_category":"Woningbouw",
    "sg:phone":"+32 51 31 90 59",
    "sg:postcode":"8860",
    "sg:province":"West-Vlaanderen",
    "wof:name":"Batico",
    "wof:placetype":"venue"
},
  "geometry": {"coordinates":[3.2477669716,50.8896713257],"type":"Point"}
}