{
  "type": "Feature",
  "properties": {
    "iso:country":"BE",
    "sg:address":"Doffen 25",
    "sg:city":"Olen",
    "sg:orig_category":"Eleveurs and marchands de porcs",
    "sg:phone":"+32 14 21 43 14",
    "sg:postcode":"2250",
    "sg:province":"Antwerpen",
    "wof:name":"Modest Van Turnhout",
    "wof:placetype":"venue"
},
  "geometry": {"coordinates":[4.8759942055,51.1646118164],"type":"Point"}
}