{
  "type": "Feature",
  "properties": {
    "iso:country":"BE",
    "sg:address":"Industrielaan 31",
    "sg:city":"Menen",
    "sg:classifiers":[
        {
            "category":"Farming",
            "subcategory":"Poultry Farm",
            "type":"Manufacturing & Wholesale Goods"
        }
    ],
    "sg:phone":"+32 56 52 14 21",
    "sg:postcode":"8930",
    "sg:province":"West-Vlaanderen",
    "sg:tags":[
        "rabbit",
        "slaughterhouse"
    ],
    "wof:name":"Hofkip Kipspecialiteiten",
    "wof:placetype":"venue"
},
  "geometry": {"coordinates":[3.1025879383,50.7902526855],"type":"Point"}
}