{
  "type": "Feature",
  "properties": {
    "iso:country":"BE",
    "sg:address":"Avenue De La Croix Rouge 17 Box 5",
    "sg:city":"Bruxelles",
    "sg:orig_category":"Non-Classified Establishments",
    "sg:phone":"+32 2 262 45 75",
    "sg:postcode":"1020",
    "sg:province":"Bruxelles-Capitale",
    "wof:name":"D & D",
    "wof:placetype":"venue"
},
  "geometry": {"coordinates":[4.3551168442,50.8962783813],"type":"Point"}
}