{
  "type": "Feature",
  "properties": {
    "iso:country":"BE",
    "sg:address":"Pl St-michel 8",
    "sg:city":"Li\u00c8ge (grand)",
    "sg:orig_category":"Banques and organismes de cr\u00e9dit",
    "sg:phone":"+32 4 230 32 11",
    "sg:postcode":"4000",
    "sg:province":"Li\u00e8ge",
    "wof:name":"Artesia",
    "wof:placetype":"venue"
},
  "geometry": {"coordinates":[5.5714850426,50.6441993713],"type":"Point"}
}