{
  "type": "Feature",
  "properties": {
    "iso:country":"BE",
    "sg:address":"Torhoutse Steenweg 9",
    "sg:city":"Brugge (sint-andries)",
    "sg:classifiers":[
        {
            "category":"Social Services",
            "subcategory":"Child Care",
            "type":"Services"
        }
    ],
    "sg:phone":"+32 50 38 28 68",
    "sg:postcode":"8200",
    "sg:province":"West-Vlaanderen",
    "sg:tags":[
        "baby",
        "nursery",
        "day",
        "sitting"
    ],
    "wof:name":"De Poppenkast",
    "wof:placetype":"venue"
},
  "geometry": {"coordinates":[3.2085568905,51.2033691406],"type":"Point"}
}