{
  "type": "Feature",
  "properties": {
    "iso:country":"BE",
    "sg:address":"Rue Fran\u00c7ois 17",
    "sg:city":"Court-saint-etienne",
    "sg:orig_category":"Travaux de pl\u00e2trage. Constructions r\u00e9sidentielles sp\u00e9cifiques",
    "sg:phone":"+32 10 61 61 77",
    "sg:postcode":"1490",
    "sg:province":"Brabant Wallon",
    "wof:name":"Bilali Besim",
    "wof:placetype":"venue"
},
  "geometry": {"coordinates":[4.5638699532,50.6458587646],"type":"Point"}
}