{
  "type": "Feature",
  "properties": {
    "addr:full":"Chauss\u00e9e Reine Astrid 37 Braine L'alleud (braine-l'alleud) Brabant Wallon 1420",
    "addr:housenumber":"37",
    "addr:postcode":"1420",
    "addr:street":"Chausse\u0301E Reine Astrid",
    "iso:country":"BE",
    "sg:address":"Chauss\u00e9e Reine Astrid 37",
    "sg:city":"Braine L'alleud (braine-l'alleud)",
    "sg:classifiers":[
        {
            "category":"Professional",
            "subcategory":"Testing Lab",
            "type":"Services"
        }
    ],
    "sg:phone":"+32 2 384 20 62",
    "sg:postcode":"1420",
    "sg:province":"Brabant Wallon",
    "sg:tags":[
        "chemist"
    ],
    "wof:name":"Vall\u00e9e Bailly",
    "wof:placetype":"venue"
},
  "geometry": {"coordinates":[-0.7711730003,47.3931159973],"type":"Point"}
}