{
  "type": "Feature",
  "properties": {
    "iso:country":"BE",
    "sg:address":"Avenue John-fitzgerald Kennedy 32",
    "sg:city":"Rixensart",
    "sg:classifiers":[
        {
            "category":"Retail",
            "subcategory":"Auto Repair",
            "type":"Services"
        }
    ],
    "sg:phone":"+32 2 653 36 33",
    "sg:postcode":"1330",
    "sg:province":"Brabant Wallon",
    "sg:tags":[
        "garage"
    ],
    "wof:name":"Abs Motors",
    "wof:placetype":"venue"
},
  "geometry": {"coordinates":[4.5229330063,50.7060317993],"type":"Point"}
}