{
  "type": "Feature",
  "properties": {
    "addr:full":"Muldersweg 1 Kuurne West-Vlaanderen 8520",
    "addr:housenumber":"1",
    "addr:postcode":"8520",
    "addr:street":"Muldersweg",
    "iso:country":"BE",
    "sg:address":"Muldersweg 1",
    "sg:city":"Kuurne",
    "sg:classifiers":[
        {
            "category":"Quarry",
            "type":"Physical Feature"
        }
    ],
    "sg:phone":"+32 56 72 42 22",
    "sg:postcode":"8520",
    "sg:province":"West-Vlaanderen",
    "sg:tags":[
        "granite",
        "work",
        "marble"
    ],
    "wof:name":"Vandenbroucke Bvba",
    "wof:placetype":"venue"
},
  "geometry": {"coordinates":[3.2762870789,50.8677101135],"type":"Point"}
}