{
  "type": "Feature",
  "properties": {
    "addr:full":"Rue As Pois 61 Tournai Hainaut 7500",
    "addr:housenumber":"61",
    "addr:postcode":"7500",
    "addr:street":"Rue As Pois",
    "iso:country":"BE",
    "sg:address":"Rue As Pois 61",
    "sg:city":"Tournai",
    "sg:classifiers":[
        {
            "category":"Real Estate",
            "subcategory":"Architect",
            "type":"Services"
        }
    ],
    "sg:phone":"+32 69 84 53 92",
    "sg:postcode":"7500",
    "sg:province":"Hainaut",
    "wof:name":"Van Corselis T",
    "wof:placetype":"venue"
},
  "geometry": {"coordinates":[3.3827600479,50.604839325],"type":"Point"}
}