{
  "type": "Feature",
  "properties": {
    "addr:full":"Vrijheidstraat 13 Oostende West-Vlaanderen 8400",
    "addr:housenumber":"13",
    "addr:postcode":"8400",
    "addr:street":"Vrijheidstraat",
    "iso:country":"BE",
    "sg:address":"Vrijheidstraat 13",
    "sg:city":"Oostende",
    "sg:classifiers":[
        {
            "category":"Retail",
            "subcategory":"Animal Services",
            "type":"Services"
        }
    ],
    "sg:phone":"+32 59 70 56 84",
    "sg:postcode":"8400",
    "sg:province":"West-Vlaanderen",
    "sg:tags":[
        "grooming",
        "-",
        "dog"
    ],
    "wof:name":"Hond- & Katsalon",
    "wof:placetype":"venue"
},
  "geometry": {"coordinates":[2.9053690434,51.2161712646],"type":"Point"}
}