{
  "type": "Feature",
  "properties": {
    "iso:country":"BE",
    "sg:address":"Riche Rue 1",
    "sg:city":"Komen-waasten/comines-warneton",
    "sg:orig_category":"Services divers aux personnes. Alimentation sp\u00e9cialis\u00e9e",
    "sg:phone":"+32 56 58 82 44",
    "sg:postcode":"7784",
    "sg:province":"Hainaut",
    "wof:name":"Gourmandises De Campagnac - Christophe Debacker",
    "wof:placetype":"venue"
},
  "geometry": {"coordinates":[2.9385099411,50.738319397],"type":"Point"}
}