{
  "type": "Feature",
  "properties": {
    "iso:country":"BE",
    "sg:address":"Sint-janstraat 20",
    "sg:city":"Wevelgem",
    "sg:orig_category":"Artsen and specialisten",
    "sg:phone":"+32 56 42 54 75",
    "sg:postcode":"8560",
    "sg:province":"West-Vlaanderen",
    "wof:name":"Yves Schoutetens",
    "wof:placetype":"venue"
},
  "geometry": {"coordinates":[3.1641581059,50.8389205933],"type":"Point"}
}