{
  "type": "Feature",
  "properties": {
    "addr:full":"Malmedyer Strasse 22 B\u00fcllingen Li\u00e8ge 4760",
    "addr:housenumber":"22",
    "addr:postcode":"4760",
    "addr:street":"Malmedyer Strasse",
    "iso:country":"BE",
    "sg:address":"Malmedyer Strasse 22",
    "sg:city":"B\u00fcllingen",
    "sg:classifiers":[
        {
            "category":"Insurance",
            "subcategory":"Insurance Agent",
            "type":"Services"
        }
    ],
    "sg:phone":"+32 80 64 71 95",
    "sg:postcode":"4760",
    "sg:province":"Li\u00e8ge",
    "sg:tags":[
        "broker"
    ],
    "wof:name":"Masson Pgmbh",
    "wof:placetype":"venue"
},
  "geometry": {"coordinates":[6.2496409416,50.405796051],"type":"Point"}
}