{
  "type": "Feature",
  "properties": {
    "addr:full":"Rue De Mettet 204 Florennes Namur 5620",
    "addr:housenumber":"204",
    "addr:postcode":"5620",
    "addr:street":"Rue De Mettet",
    "iso:country":"BE",
    "sg:address":"Rue De Mettet 204",
    "sg:city":"Florennes",
    "sg:orig_category":"Warenhuizen",
    "sg:phone":"+32 71 68 12 00",
    "sg:postcode":"5620",
    "sg:province":"Namur",
    "wof:name":"Trafiba",
    "wof:placetype":"venue"
},
  "geometry": {"coordinates":[4.6219978333,50.2691383362],"type":"Point"}
}