{
  "type": "Feature",
  "properties": {
    "addr:full":"Slagmolen 2 Bilzen Limburg 3740",
    "addr:housenumber":"2",
    "addr:postcode":"3740",
    "addr:street":"Slagmolen",
    "iso:country":"BE",
    "sg:address":"Slagmolen 2",
    "sg:city":"Bilzen",
    "sg:classifiers":[
        {
            "category":"Home & Garden",
            "subcategory":"Furniture",
            "type":"Retail Goods"
        }
    ],
    "sg:phone":"+32 89 41 14 24",
    "sg:postcode":"3740",
    "sg:province":"Limburg",
    "sg:tags":[
        "wood"
    ],
    "wof:name":"De Slagmolen Bvba",
    "wof:placetype":"venue"
},
  "geometry": {"coordinates":[5.5076680183,50.8843765259],"type":"Point"}
}