{
  "type": "Feature",
  "properties": {
    "iso:country":"BE",
    "sg:address":"Rue De Renaumont 129",
    "sg:city":"Bertrix",
    "sg:orig_category":"Sportclubs",
    "sg:phone":"+32 61 41 18 65",
    "sg:postcode":"6880",
    "sg:province":"Luxembourg",
    "wof:name":"Badminton Club Bertrix",
    "wof:placetype":"venue"
},
  "geometry": {"coordinates":[5.2324409485,49.8537635803],"type":"Point"}
}