{
  "type": "Feature",
  "properties": {
    "addr:full":"Rue Des Bleuets 11 Neufchateau Luxembourg 6840",
    "addr:housenumber":"11",
    "addr:postcode":"6840",
    "addr:street":"Rue Des Bleuets",
    "iso:country":"BE",
    "sg:address":"Rue Des Bleuets 11",
    "sg:city":"Neufchateau",
    "sg:orig_category":"Boekhouders",
    "sg:phone":"+32 61 27 82 60",
    "sg:postcode":"6840",
    "sg:province":"Luxembourg",
    "wof:name":"Lambeau Raymonde",
    "wof:placetype":"venue"
},
  "geometry": {"coordinates":[5.4532570839,49.8441734314],"type":"Point"}
}