{
  "type": "Feature",
  "properties": {
    "iso:country":"BE",
    "sg:address":"Chauss\u00e9e De Namur 279-281",
    "sg:city":"Eghez\u00e9e",
    "sg:classifiers":[
        {
            "category":"Banks & Credit Unions",
            "subcategory":"Investment Brokerage",
            "type":"Services"
        }
    ],
    "sg:phone":"+32 81 51 27 94",
    "sg:postcode":"5310",
    "sg:province":"Namur",
    "sg:tags":[
        "wreath",
        "mourning"
    ],
    "wof:name":"Green World-locaflor",
    "wof:placetype":"venue"
},
  "geometry": {"coordinates":[4.9103899002,50.5753898621],"type":"Point"}
}