{
  "type": "Feature",
  "properties": {
    "addr:full":"Tongerenstraat 33 Etterbeek Bruxelles-Capitale 1040",
    "addr:housenumber":"33",
    "addr:postcode":"1040",
    "addr:street":"Tongerenstraat",
    "iso:country":"BE",
    "sg:address":"Tongerenstraat 33",
    "sg:city":"Etterbeek",
    "sg:orig_category":"Zalen voor culturele evenementen",
    "sg:phone":"+32 2 736 96 81",
    "sg:postcode":"1040",
    "sg:province":"Bruxelles-Capitale",
    "wof:name":"Groupe Aussi",
    "wof:placetype":"venue"
},
  "geometry": {"coordinates":[4.4001131058,50.8397865295],"type":"Point"}
}