{
  "type": "Feature",
  "properties": {
    "addr:full":"Rue Basse 18 Frasnes-lez-anvaing Hainaut 7911",
    "addr:housenumber":"18",
    "addr:postcode":"7911",
    "addr:street":"Rue Basse",
    "iso:country":"BE",
    "sg:address":"Rue Basse 18",
    "sg:city":"Frasnes-lez-anvaing",
    "sg:orig_category":"Plomberie, chauffage and installations sanitaires",
    "sg:phone":"+32 69 86 63 47",
    "sg:postcode":"7911",
    "sg:province":"Hainaut",
    "wof:name":"Delhaye",
    "wof:placetype":"venue"
},
  "geometry": {"coordinates":[3.6201529503,50.6681404114],"type":"Point"}
}