{
  "type": "Feature",
  "properties": {
    "addr:full":"Grote Baan 70 Lovendegem (groot) Oost-Vlaanderen 9920",
    "addr:housenumber":"70",
    "addr:postcode":"9920",
    "addr:street":"Grote Baan;Groot Oost-Vlaanderen",
    "iso:country":"BE",
    "sg:address":"Grote Baan 70",
    "sg:city":"Lovendegem (groot)",
    "sg:classifiers":[
        {
            "category":"Bars & Pubs",
            "type":"Food & Drink"
        }
    ],
    "sg:phone":"+32 475 58 96 20",
    "sg:postcode":"9920",
    "sg:province":"Oost-Vlaanderen",
    "wof:name":"\u00b4t Hemelrijk",
    "wof:placetype":"venue"
},
  "geometry": {"coordinates":[3.6379110813,51.0982513428],"type":"Point"}
}