{
  "type": "Feature",
  "properties": {
    "addr:full":"Dirixstraat 12 Bree Limburg 3960",
    "addr:housenumber":"12",
    "addr:postcode":"3960",
    "addr:street":"Dirixstraat",
    "iso:country":"BE",
    "sg:address":"Dirixstraat 12",
    "sg:city":"Bree",
    "sg:orig_category":"Woningbouw",
    "sg:phone":"+32 89 46 60 53",
    "sg:postcode":"3960",
    "sg:province":"Limburg",
    "wof:name":"Patrick Meus",
    "wof:placetype":"venue"
},
  "geometry": {"coordinates":[5.6065621376,51.1554222107],"type":"Point"}
}