{
  "type": "Feature",
  "properties": {
    "iso:country":"BE",
    "sg:address":"Stationsstraat 10",
    "sg:city":"Sint-truiden",
    "sg:orig_category":"Banques and organismes de cr\u00e9dit",
    "sg:phone":"+32 11 68 31 03",
    "sg:postcode":"3800",
    "sg:province":"Limburg",
    "wof:name":"Groep Argenta",
    "wof:placetype":"venue"
},
  "geometry": {"coordinates":[5.1786298752,50.816204071],"type":"Point"}
}