{
  "type": "Feature",
  "properties": {
    "iso:country":"BE",
    "sg:address":"Pres. Kennedypark 18",
    "sg:city":"Kortrijk",
    "sg:classifiers":[
        {
            "category":"Transit Center",
            "subcategory":"Freight",
            "type":"Transportation"
        }
    ],
    "sg:phone":"+32 56 23 05 11",
    "sg:postcode":"8500",
    "sg:province":"West-Vlaanderen",
    "sg:tags":[
        "metallurgy",
        "pipe",
        "metalworking",
        "sheet"
    ],
    "wof:name":"Nv Bekaert Sa",
    "wof:placetype":"venue"
},
  "geometry": {"coordinates":[3.2715198994,50.7987709045],"type":"Point"}
}