{
  "type": "Feature",
  "properties": {
    "addr:full":"Rue Du M\u00e9ry 14a Li\u00e8ge 1 Li\u00e8ge 4000",
    "addr:housenumber":"14a;1",
    "addr:postcode":"4000",
    "addr:street":"Rue Du Me\u0301Ry",
    "iso:country":"BE",
    "sg:address":"Rue Du M\u00e9ry 14a",
    "sg:city":"Li\u00e8ge 1",
    "sg:classifiers":[
        {
            "category":"Personal",
            "subcategory":"Beauty Salon",
            "type":"Services"
        }
    ],
    "sg:phone":"+32 4 222 12 20",
    "sg:postcode":"4000",
    "sg:province":"Li\u00e8ge",
    "wof:name":"Herboristerie (l')",
    "wof:placetype":"venue"
},
  "geometry": {"coordinates":[5.5747318268,50.6396446228],"type":"Point"}
}