{
  "type": "Feature",
  "properties": {
    "addr:full":"Provinciebaan 108 Laarne (kalken) Oost-Vlaanderen 9270",
    "addr:housenumber":"108",
    "addr:postcode":"9270",
    "addr:street":"Provinciebaan",
    "iso:country":"BE",
    "sg:address":"Provinciebaan 108",
    "sg:city":"Laarne (kalken)",
    "sg:classifiers":[
        {
            "category":"Banks & Credit Unions",
            "subcategory":"Investment Brokerage",
            "type":"Services"
        }
    ],
    "sg:phone":"+32 9 368 20 58",
    "sg:postcode":"9270",
    "sg:province":"Oost-Vlaanderen",
    "sg:tags":[
        "repair",
        "-",
        "installation",
        "sanitary",
        "article"
    ],
    "wof:name":"Beyst Gerard En Zn",
    "wof:placetype":"venue"
},
  "geometry": {"coordinates":[3.8921399117,51.0278739929],"type":"Point"}
}