{
  "type": "Feature",
  "properties": {
    "addr:full":"Torhoutsesteenweg 160 Zedelgem West-Vlaanderen 8210",
    "addr:housenumber":"160",
    "addr:postcode":"8210",
    "addr:street":"Torhoutsesteenweg",
    "iso:country":"BE",
    "sg:address":"Torhoutsesteenweg 160",
    "sg:city":"Zedelgem",
    "sg:classifiers":[
        {
            "category":"Autos & Motor Vehicles",
            "subcategory":"Auto Supplies",
            "type":"Retail Goods"
        }
    ],
    "sg:phone":"+32 50 24 06 01",
    "sg:postcode":"8210",
    "sg:province":"West-Vlaanderen",
    "sg:tags":[
        "automobile",
        "-",
        "radio"
    ],
    "wof:name":"Cmc-car Music Center",
    "wof:placetype":"venue"
},
  "geometry": {"coordinates":[3.1576468945,51.1365127563],"type":"Point"}
}