{
  "type": "Feature",
  "properties": {
    "addr:full":"Rue De Wazimont 1 Huy Li\u00e8ge 4500",
    "addr:housenumber":"1",
    "addr:postcode":"4500",
    "addr:street":"Rue De Wazimont",
    "iso:country":"BE",
    "sg:address":"Rue De Wazimont 1",
    "sg:city":"Huy",
    "sg:orig_category":"Activit\u00e9s r\u00e9cr\u00e9atives diverses",
    "sg:phone":"+32 85 84 30 64",
    "sg:postcode":"4500",
    "sg:province":"Li\u00e8ge",
    "wof:name":"Piper Club",
    "wof:placetype":"venue"
},
  "geometry": {"coordinates":[5.1552648544,50.5011100769],"type":"Point"}
}