{
  "type": "Feature",
  "properties": {
    "addr:full":"Tieltsesteenweg 203-205 Eeklo Oost-Vlaanderen 9900",
    "addr:housenumber":"203-205",
    "addr:postcode":"9900",
    "addr:street":"Tieltsesteenweg",
    "iso:country":"BE",
    "sg:address":"Tieltsesteenweg 203-205",
    "sg:city":"Eeklo",
    "sg:classifiers":[
        {
            "category":"Shopping",
            "subcategory":"Pets & Pet Supplies",
            "type":"Retail Goods"
        }
    ],
    "sg:phone":"+32 9 377 67 63",
    "sg:postcode":"9900",
    "sg:province":"Oost-Vlaanderen",
    "sg:tags":[
        "telecopiers"
    ],
    "wof:name":"Egm Elektro Grh Meetjesland",
    "wof:placetype":"venue"
},
  "geometry": {"coordinates":[3.549808979,51.1781044006],"type":"Point"}
}