{
  "type": "Feature",
  "properties": {
    "iso:country":"BE",
    "sg:address":"Rue De Fraiture 22",
    "sg:city":"Sprimont",
    "sg:orig_category":"Loodgieterij, verwarming and sanitaire installaties Pleisterwerk",
    "sg:phone":"+32 4 369 18 45",
    "sg:postcode":"4140",
    "sg:province":"Li\u00e8ge",
    "wof:name":"Ets. Paglia",
    "wof:placetype":"venue"
},
  "geometry": {"coordinates":[5.6003298759,50.4841499329],"type":"Point"}
}