{
  "type": "Feature",
  "properties": {
    "addr:full":"Rue Jean Jaur\u00e8s 12 Gr\u00e2ce-hollogne (gr\u00e2ce-berleur) Li\u00e8ge 4460",
    "addr:housenumber":"12",
    "addr:postcode":"4460",
    "addr:street":"Rue Jean Jaure\u0300S;Gra\u0302Ce-Berleur",
    "iso:country":"BE",
    "sg:address":"Rue Jean Jaur\u00e8s 12",
    "sg:city":"Gr\u00e2ce-hollogne (gr\u00e2ce-berleur)",
    "sg:classifiers":[
        {
            "category":"Health Services",
            "subcategory":"Health Practitioner",
            "type":"Services"
        }
    ],
    "sg:phone":"+32 4 231 31 85",
    "sg:postcode":"4460",
    "sg:province":"Li\u00e8ge",
    "sg:tags":[
        "therapist",
        "speech"
    ],
    "wof:name":"Perizonius K",
    "wof:placetype":"venue"
},
  "geometry": {"coordinates":[5.5053610802,50.6436653137],"type":"Point"}
}