{
  "type": "Feature",
  "properties": {
    "addr:full":"Lippenslaan 46 Knokke-heist (knokke) West-Vlaanderen 8300",
    "addr:housenumber":"46",
    "addr:postcode":"8300",
    "addr:street":"Lippenslaan",
    "iso:country":"BE",
    "sg:address":"Lippenslaan 46",
    "sg:city":"Knokke-heist (knokke)",
    "sg:classifiers":[
        {
            "category":"Shopping",
            "subcategory":"Florist",
            "type":"Retail Goods"
        }
    ],
    "sg:phone":"+32 50 60 20 46",
    "sg:postcode":"8300",
    "sg:province":"West-Vlaanderen",
    "wof:name":"Baes",
    "wof:placetype":"venue"
},
  "geometry": {"coordinates":[3.2878410816,51.3425979614],"type":"Point"}
}