{
  "type": "Feature",
  "properties": {
    "addr:full":"Beukendreef 51 Moerbeke (moerbeke-waas) Oost-Vlaanderen 9180",
    "addr:housenumber":"51",
    "addr:postcode":"9180",
    "addr:street":"Beukendreef",
    "iso:country":"BE",
    "sg:address":"Beukendreef 51",
    "sg:city":"Moerbeke (moerbeke-waas)",
    "sg:classifiers":[
        {
            "category":"Food & Beverages",
            "subcategory":"Specialty",
            "type":"Retail Goods"
        }
    ],
    "sg:phone":"+32 3 789 09 59",
    "sg:postcode":"9180",
    "sg:province":"Oost-Vlaanderen",
    "sg:tags":[
        "health",
        "dietary",
        "-",
        "biological"
    ],
    "wof:name":"Energetica Natura",
    "wof:placetype":"venue"
},
  "geometry": {"coordinates":[3.9611039162,51.2181663513],"type":"Point"}
}