{
  "type": "Feature",
  "properties": {
    "addr:full":"Rue Du Gard 21 Sivry-rance (sivry) Hainaut 6470",
    "addr:housenumber":"21",
    "addr:postcode":"6470",
    "addr:street":"Rue Du Gard",
    "iso:country":"BE",
    "sg:address":"Rue Du Gard 21",
    "sg:city":"Sivry-rance (sivry)",
    "sg:classifiers":[
        {
            "category":"Travel",
            "subcategory":"Resort",
            "type":"Entertainment"
        }
    ],
    "sg:phone":"+32 60 45 56 23",
    "sg:postcode":"6470",
    "sg:province":"Hainaut",
    "sg:tags":[
        "farm",
        "house",
        "holiday",
        "guest"
    ],
    "wof:name":"Gite Ferme Du Gard",
    "wof:placetype":"venue"
},
  "geometry": {"coordinates":[4.1915779114,50.1721916199],"type":"Point"}
}