{
  "type": "Feature",
  "properties": {
    "iso:country":"BE",
    "sg:address":"Rue De Rodange 59",
    "sg:city":"Aubange (athus)",
    "sg:classifiers":[
        {
            "category":"Shopping",
            "subcategory":"Books",
            "type":"Retail Goods"
        }
    ],
    "sg:phone":"+32 63 38 81 19",
    "sg:postcode":"6791",
    "sg:province":"Luxembourg",
    "sg:tags":[
        "bookseller"
    ],
    "wof:name":"Boon C",
    "wof:placetype":"venue"
},
  "geometry": {"coordinates":[5.8368301392,49.5627288818],"type":"Point"}
}