{
  "type": "Feature",
  "properties": {
    "addr:full":"Grand-rue 10 Martelange Luxembourg 6630",
    "addr:housenumber":"10",
    "addr:postcode":"6630",
    "addr:street":"Grand-Rue",
    "iso:country":"BE",
    "sg:address":"Grand-rue 10",
    "sg:city":"Martelange",
    "sg:orig_category":"Journaux",
    "sg:phone":"+32 63 60 03 14",
    "sg:postcode":"6630",
    "sg:province":"Luxembourg",
    "wof:name":"Prom Marcel",
    "wof:placetype":"venue"
},
  "geometry": {"coordinates":[5.7406840324,49.832862854],"type":"Point"}
}