{
  "type": "Feature",
  "properties": {
    "addr:full":"Beekstraat 18 Beringen Limburg 3580",
    "addr:housenumber":"18",
    "addr:postcode":"3580",
    "addr:street":"Beekstraat",
    "iso:country":"BE",
    "sg:address":"Beekstraat 18",
    "sg:city":"Beringen",
    "sg:orig_category":"Rundveehouders",
    "sg:phone":"+32 11 42 40 77",
    "sg:postcode":"3580",
    "sg:province":"Limburg",
    "wof:name":"Maria Theunis",
    "wof:placetype":"venue"
},
  "geometry": {"coordinates":[5.2073640823,51.0442962646],"type":"Point"}
}