{
  "type": "Feature",
  "properties": {
    "addr:full":"Rue De Neufch\u00e2teau 2 Martelange Luxembourg 6630",
    "addr:housenumber":"2",
    "addr:postcode":"6630",
    "addr:street":"Rue De Neufcha\u0302Teau",
    "iso:country":"BE",
    "sg:address":"Rue De Neufch\u00e2teau 2",
    "sg:city":"Martelange",
    "sg:classifiers":[
        {
            "category":"Bars & Pubs",
            "type":"Food & Drink"
        }
    ],
    "sg:phone":"+32 63 60 01 21",
    "sg:postcode":"6630",
    "sg:province":"Luxembourg",
    "wof:name":"Pr\u00e9 Fleuri",
    "wof:placetype":"venue"
},
  "geometry": {"coordinates":[5.7211380005,49.8355903625],"type":"Point"}
}