{
  "type": "Feature",
  "properties": {
    "iso:country":"BE",
    "sg:address":"Leeuwenhof 15",
    "sg:city":"Gent",
    "sg:orig_category":"Koerierbedrijven",
    "sg:phone":"+32 9 236 12 31",
    "sg:postcode":"9031",
    "sg:province":"Oost-Vlaanderen",
    "wof:name":"Collitax Express",
    "wof:placetype":"venue"
},
  "geometry": {"coordinates":[3.6538200378,51.0682296753],"type":"Point"}
}