{
  "type": "Feature",
  "properties": {
    "addr:full":"Ernest Feysplein 16 Oostende West-Vlaanderen 8400",
    "addr:housenumber":"16",
    "addr:postcode":"8400",
    "iso:country":"BE",
    "sg:address":"Ernest Feysplein 16",
    "sg:city":"Oostende",
    "sg:orig_category":"Agences d\u00b4interim and personnel temporaire",
    "sg:phone":"+32 59 56 40 56",
    "sg:postcode":"8400",
    "sg:province":"West-Vlaanderen",
    "wof:name":"Admb Interim",
    "wof:placetype":"venue"
},
  "geometry": {"coordinates":[2.9231870174,51.2265625],"type":"Point"}
}