{
  "type": "Feature",
  "properties": {
    "addr:full":"P. De Smet De Naeyerstr. 30 Middelkerke West-Vlaanderen 8430",
    "addr:housenumber":"30",
    "addr:postcode":"8430",
    "addr:street":"P. De Smet De Naeyerstr.",
    "iso:country":"BE",
    "sg:address":"P. De Smet De Naeyerstr. 30",
    "sg:city":"Middelkerke",
    "sg:orig_category":"Supermarkten",
    "sg:phone":"+32 59 30 14 91",
    "sg:postcode":"8430",
    "sg:province":"West-Vlaanderen",
    "wof:name":"Unic",
    "wof:placetype":"venue"
},
  "geometry": {"coordinates":[2.8186399937,51.1875267029],"type":"Point"}
}