{
  "type": "Feature",
  "properties": {
    "addr:full":"Brusselsestraat 66 Leuven Vlaams-Brabant 3000",
    "addr:housenumber":"66",
    "addr:postcode":"3000",
    "addr:street":"Brusselsestraat",
    "iso:country":"BE",
    "sg:address":"Brusselsestraat 66",
    "sg:city":"Leuven",
    "sg:classifiers":[
        {
            "category":"Health Services",
            "subcategory":"Doctor",
            "type":"Services"
        }
    ],
    "sg:phone":"+32 16 20 31 31",
    "sg:postcode":"3000",
    "sg:province":"Vlaams-Brabant",
    "sg:tags":[
        "psychotherapist",
        "psychoanalyst"
    ],
    "wof:name":"Vercaeren P",
    "wof:placetype":"venue"
},
  "geometry": {"coordinates":[4.6970348358,50.8803405762],"type":"Point"}
}