{
  "type": "Feature",
  "properties": {
    "addr:full":"Grenadiersstraat 14 Roeselare West-Vlaanderen 8800",
    "addr:housenumber":"14",
    "addr:postcode":"8800",
    "addr:street":"Grenadiersstraat",
    "iso:country":"BE",
    "sg:address":"Grenadiersstraat 14",
    "sg:city":"Roeselare",
    "sg:orig_category":"Baby- and kinderkleding",
    "sg:phone":"+32 51 20 62 13",
    "sg:postcode":"8800",
    "sg:province":"West-Vlaanderen",
    "wof:name":"Carine Beltrami",
    "wof:placetype":"venue"
},
  "geometry": {"coordinates":[3.142729044,50.9239616394],"type":"Point"}
}