{
  "type": "Feature",
  "properties": {
    "iso:country":"BE",
    "sg:address":"Kasteelweg 22",
    "sg:city":"Vleteren (oostvleteren)",
    "sg:classifiers":[
        {
            "category":"Community Center",
            "subcategory":"Youth",
            "type":"Public Place"
        }
    ],
    "sg:phone":"+32 57 40 17 47",
    "sg:postcode":"8640",
    "sg:province":"West-Vlaanderen",
    "sg:tags":[
        "club"
    ],
    "wof:name":"De Zonnegloed Natuurhoeve",
    "wof:placetype":"venue"
},
  "geometry": {"coordinates":[2.7508010864,50.9393768311],"type":"Point"}
}