{
  "type": "Feature",
  "properties": {
    "iso:country":"BE",
    "sg:address":"Boulevard De Smet De Naeyer 578",
    "sg:city":"Bruxelles",
    "sg:classifiers":[
        {
            "category":"Animal Shelter",
            "type":"Public Place"
        }
    ],
    "sg:phone":"+32 2 479 99 90",
    "sg:postcode":"1020",
    "sg:province":"Bruxelles-Capitale",
    "sg:tags":[
        "clinic"
    ],
    "wof:name":"Service De Garde V\u00e9t\u00e9rinaire De La R\u00e9gion Bruxelloise",
    "wof:placetype":"venue"
},
  "geometry": {"coordinates":[4.3415589333,50.8856964111],"type":"Point"}
}