{
  "type": "Feature",
  "properties": {
    "iso:country":"BE",
    "sg:address":"Kortrijkstraat 134",
    "sg:city":"Oudenaarde",
    "sg:classifiers":[
        {
            "category":"Cafe",
            "type":"Food & Drink"
        }
    ],
    "sg:phone":"+32 55 31 46 71",
    "sg:postcode":"9700",
    "sg:province":"Oost-Vlaanderen",
    "sg:tags":[
        "caf\u00e9s"
    ],
    "wof:name":"Francine Collaert",
    "wof:placetype":"venue"
},
  "geometry": {"coordinates":[3.5938498974,50.8505096436],"type":"Point"}
}