{
  "type": "Feature",
  "properties": {
    "addr:full":"Rue Des Sandrinettes 3 Mons (cuesmes) Hainaut 7033",
    "addr:housenumber":"3",
    "addr:postcode":"7033",
    "addr:street":"Rue Des Sandrinettes",
    "iso:country":"BE",
    "sg:address":"Rue Des Sandrinettes 3",
    "sg:city":"Mons (cuesmes)",
    "sg:classifiers":[
        {
            "category":"Insurance",
            "subcategory":"Insurance Agent",
            "type":"Services"
        }
    ],
    "sg:phone":"+32 65 36 18 82",
    "sg:postcode":"7033",
    "sg:province":"Hainaut",
    "sg:tags":[
        "-",
        "representative"
    ],
    "wof:name":"Nieto Moreno J",
    "wof:placetype":"venue"
},
  "geometry": {"coordinates":[3.9253261089,50.4366378784],"type":"Point"}
}