{
  "type": "Feature",
  "properties": {
    "addr:full":"Belliardstraat 97 Brussel/bruxelles 1047",
    "addr:housenumber":"97",
    "addr:postcode":"1047",
    "addr:street":"Belliardstraat;/ Bruxelles",
    "iso:country":"BE",
    "sg:address":"Belliardstraat 97",
    "sg:city":"Brussel/bruxelles",
    "sg:orig_category":"Banken and kredietinstellingen",
    "sg:phone":"+32 2 230 58 40",
    "sg:postcode":"1047",
    "wof:name":"Kbc",
    "wof:placetype":"venue"
},
  "geometry": {"coordinates":[4.3812599182,50.8415908813],"type":"Point"}
}