{
  "type": "Feature",
  "properties": {
    "addr:full":"Rue Basse Voie 2 Burdinne Li\u00e8ge 4210",
    "addr:housenumber":"2",
    "addr:postcode":"4210",
    "addr:street":"Rue Basse Voie",
    "iso:country":"BE",
    "sg:address":"Rue Basse Voie 2",
    "sg:city":"Burdinne",
    "sg:orig_category":"Charpentes and couvertures",
    "sg:phone":"+32 85 71 34 84",
    "sg:postcode":"4210",
    "sg:province":"Li\u00e8ge",
    "wof:name":"Fe. Christiaens",
    "wof:placetype":"venue"
},
  "geometry": {"coordinates":[5.0912361145,50.583442688],"type":"Point"}
}