{
  "type": "Feature",
  "properties": {
    "iso:country":"BE",
    "sg:address":"Chauss\u00c9e De W\u00c9gimont 306",
    "sg:city":"Soumagne",
    "sg:classifiers":[
        {
            "category":"Insurance",
            "subcategory":"Life Insurance",
            "type":"Services"
        }
    ],
    "sg:phone":"+32 4 355 19 20",
    "sg:postcode":"4630",
    "sg:province":"Li\u00e8ge",
    "sg:tags":[
        "assurance"
    ],
    "wof:name":"Foubert Francis",
    "wof:placetype":"venue"
},
  "geometry": {"coordinates":[5.7390799522,50.6112098694],"type":"Point"}
}