{
  "type": "Feature",
  "properties": {
    "iso:country":"BE",
    "sg:address":"Moenebroekstraat 7",
    "sg:city":"Geraardsbergen",
    "sg:classifiers":[
        {
            "category":"Cafe",
            "type":"Food & Drink"
        }
    ],
    "sg:phone":"+32 54 41 21 65",
    "sg:postcode":"9506",
    "sg:province":"Oost-Vlaanderen",
    "sg:tags":[
        "caf\u00e9s"
    ],
    "wof:name":"Caf\u00c9 Alpina",
    "wof:placetype":"venue"
},
  "geometry": {"coordinates":[3.8985300064,50.7987060547],"type":"Point"}
}