{
  "type": "Feature",
  "properties": {
    "iso:country":"BE",
    "sg:address":"Staatsbaan 10",
    "sg:city":"Maldegem",
    "sg:orig_category":"V\u00eatements",
    "sg:phone":"+32 50 71 51 33",
    "sg:postcode":"9991",
    "sg:province":"Oost-Vlaanderen",
    "wof:name":"Leder Palace",
    "wof:placetype":"venue"
},
  "geometry": {"coordinates":[3.4742689133,51.2045974731],"type":"Point"}
}