{
  "type": "Feature",
  "properties": {
    "iso:country":"BE",
    "sg:address":"Oombergenstraat 15",
    "sg:city":"Zottegem",
    "sg:orig_category":"Banques and organismes de cr\u00e9dit",
    "sg:phone":"+32 9 360 15 23",
    "sg:postcode":"9620",
    "sg:province":"Oost-Vlaanderen",
    "wof:name":"Ippa",
    "wof:placetype":"venue"
},
  "geometry": {"coordinates":[3.8112111092,50.871181488],"type":"Point"}
}