{
  "type": "Feature",
  "properties": {
    "iso:country":"BE",
    "sg:address":"Rue D'ollignies 17a",
    "sg:city":"Lessines (bois-de-lessines)",
    "sg:classifiers":[
        {
            "category":"Health Services",
            "subcategory":"Health Practitioner",
            "type":"Services"
        }
    ],
    "sg:phone":"+32 68 33 58 38",
    "sg:postcode":"7866",
    "sg:province":"Hainaut",
    "sg:tags":[
        "physiotherapist"
    ],
    "wof:name":"Van Keymeulen Th",
    "wof:placetype":"venue"
},
  "geometry": {"coordinates":[3.8841838837,50.6952896118],"type":"Point"}
}