{
  "type": "Feature",
  "properties": {
    "iso:country":"BE",
    "sg:address":"Leeweg 4",
    "sg:city":"Laarne",
    "sg:classifiers":[
        {
            "category":"Manufacturing",
            "subcategory":"Metals",
            "type":"Manufacturing & Wholesale Goods"
        }
    ],
    "sg:phone":"+32 9 369 93 72",
    "sg:postcode":"9270",
    "sg:province":"Oost-Vlaanderen",
    "sg:tags":[
        "working"
    ],
    "wof:name":"Beernaert Fijnmechaniek",
    "wof:placetype":"venue"
},
  "geometry": {"coordinates":[3.8741490841,51.0296363831],"type":"Point"}
}