{
  "type": "Feature",
  "properties": {
    "addr:full":"Rue Diguette 1 Li\u00e8ge 1 (angleur) Li\u00e8ge 4031",
    "addr:housenumber":"1;1",
    "addr:postcode":"4031",
    "addr:street":"Rue Diguette",
    "iso:country":"BE",
    "sg:address":"Rue Diguette 1",
    "sg:city":"Li\u00e8ge 1 (angleur)",
    "sg:classifiers":[
        {
            "category":"Building & Trades",
            "subcategory":"Electrical",
            "type":"Services"
        }
    ],
    "sg:phone":"+32 4 366 00 31",
    "sg:postcode":"4031",
    "sg:province":"Li\u00e8ge",
    "sg:tags":[
        "electric",
        "-",
        "housewiring",
        "contractor"
    ],
    "wof:name":"Klinkenberg Michel & Fils Sa",
    "wof:placetype":"venue"
},
  "geometry": {"coordinates":[5.6061639786,50.6101875305],"type":"Point"}
}