{
  "type": "Feature",
  "properties": {
    "iso:country":"BE",
    "sg:address":"Vlasbloemstraat 26",
    "sg:city":"Izegem",
    "sg:orig_category":"Sportclubs",
    "sg:phone":"+32 51 31 31 69",
    "sg:postcode":"8870",
    "sg:province":"West-Vlaanderen",
    "wof:name":"Schuttersvereniging Sint-pieter-wakkem",
    "wof:placetype":"venue"
},
  "geometry": {"coordinates":[3.2193179131,50.9075889587],"type":"Point"}
}