{
  "type": "Feature",
  "properties": {
    "addr:full":"Zeedijk-knokke 640 Knokke-heist West-Vlaanderen 8300",
    "addr:housenumber":"640",
    "addr:postcode":"8300",
    "iso:country":"BE",
    "sg:address":"Zeedijk-knokke 640",
    "sg:city":"Knokke-heist",
    "sg:orig_category":"Location d'articles de sport, de sport nautique and de camping",
    "sg:phone":"+32 50 62 56 08",
    "sg:postcode":"8300",
    "sg:province":"West-Vlaanderen",
    "wof:name":"Huis Pinte Martin",
    "wof:placetype":"venue"
},
  "geometry": {"coordinates":[3.2814400196,51.3407287598],"type":"Point"}
}