{
  "type": "Feature",
  "properties": {
    "addr:full":"Rue De La Lorraine 77 Messancy Luxembourg 6780",
    "addr:housenumber":"77",
    "addr:postcode":"6780",
    "addr:street":"Rue De La Lorraine",
    "iso:country":"BE",
    "sg:address":"Rue De La Lorraine 77",
    "sg:city":"Messancy",
    "sg:classifiers":[
        {
            "category":"Health Services",
            "subcategory":"Dentist",
            "type":"Services"
        }
    ],
    "sg:phone":"+32 63 38 89 55",
    "sg:postcode":"6780",
    "sg:province":"Luxembourg",
    "wof:name":"Toppazzini Patricia",
    "wof:placetype":"venue"
},
  "geometry": {"coordinates":[5.8203001022,49.6001396179],"type":"Point"}
}