{
  "type": "Feature",
  "properties": {
    "iso:country":"BE",
    "sg:address":"Industriepark Rostijne 6",
    "sg:city":"Zelzate",
    "sg:classifiers":[
        {
            "category":"Professional",
            "subcategory":"Detective & Security Services",
            "type":"Services"
        }
    ],
    "sg:phone":"+32 9 342 27 70",
    "sg:postcode":"9060",
    "sg:province":"Oost-Vlaanderen",
    "sg:tags":[
        "installation",
        "alarm",
        "-",
        "system"
    ],
    "wof:name":"Security & Protection Systems",
    "wof:placetype":"venue"
},
  "geometry": {"coordinates":[3.830053091,51.1889381409],"type":"Point"}
}