{
  "type": "Feature",
  "properties": {
    "addr:full":"Rue Des Aisnes 21 Hannut Li\u00e8ge 4280",
    "addr:housenumber":"21",
    "addr:postcode":"4280",
    "addr:street":"Rue Des Aisnes",
    "iso:country":"BE",
    "sg:address":"Rue Des Aisnes 21",
    "sg:city":"Hannut",
    "sg:orig_category":"Artsen and specialisten",
    "sg:phone":"+32 19 51 26 64",
    "sg:postcode":"4280",
    "sg:province":"Li\u00e8ge",
    "wof:name":"M. Courtoy",
    "wof:placetype":"venue"
},
  "geometry": {"coordinates":[5.0746479034,50.6765556335],"type":"Point"}
}