{
  "type": "Feature",
  "properties": {
    "addr:full":"Onderstraat 106b1 Gavere Oost-Vlaanderen 9890",
    "addr:housenumber":"106b1",
    "addr:postcode":"9890",
    "addr:street":"Onderstraat",
    "iso:country":"BE",
    "sg:address":"Onderstraat 106b1",
    "sg:city":"Gavere",
    "sg:orig_category":"Banken and kredietinstellingen Verzekeringsmakelaars and experts",
    "sg:phone":"+32 9 384 78 36",
    "sg:postcode":"9890",
    "sg:province":"Oost-Vlaanderen",
    "wof:name":"Groep Argenta",
    "wof:placetype":"venue"
},
  "geometry": {"coordinates":[3.661000967,50.9305763245],"type":"Point"}
}