{
  "type": "Feature",
  "properties": {
    "addr:full":"Patersstraat 92 Turnhout Antwerpen 2300",
    "addr:housenumber":"92",
    "addr:postcode":"2300",
    "addr:street":"Patersstraat",
    "iso:country":"BE",
    "sg:address":"Patersstraat 92",
    "sg:city":"Turnhout",
    "sg:classifiers":[
        {
            "category":"Health Services",
            "subcategory":"Dentist",
            "type":"Services"
        }
    ],
    "sg:phone":"+32 14 43 76 24",
    "sg:postcode":"2300",
    "sg:province":"Antwerpen",
    "wof:name":"De Zutter G",
    "wof:placetype":"venue"
},
  "geometry": {"coordinates":[4.9496731758,51.3267288208],"type":"Point"}
}