{
  "type": "Feature",
  "properties": {
    "iso:country":"BE",
    "sg:address":"Antwerpse Steenweg 161",
    "sg:city":"Lochristi",
    "sg:orig_category":"Agences de publicit\u00e9. R\u00e9paration and restauration de meubles",
    "sg:phone":"+32 9 355 88 90",
    "sg:postcode":"9080",
    "sg:province":"Oost-Vlaanderen",
    "wof:name":"Luc Vervaet",
    "wof:placetype":"venue"
},
  "geometry": {"coordinates":[3.79956007,51.0853614807],"type":"Point"}
}