{
  "type": "Feature",
  "properties": {
    "iso:country":"BE",
    "sg:address":"Gistelse Steenweg 432",
    "sg:city":"Brugge (sint-andries)",
    "sg:classifiers":[
        {
            "category":"Travel",
            "subcategory":"Travel Agent",
            "type":"Entertainment"
        }
    ],
    "sg:phone":"+32 50 39 20 00",
    "sg:postcode":"8200",
    "sg:province":"West-Vlaanderen",
    "sg:tags":[
        "agency"
    ],
    "wof:name":"Holiday Land P-travel",
    "wof:placetype":"venue"
},
  "geometry": {"coordinates":[3.1950199604,51.2001304626],"type":"Point"}
}