{
  "type": "Feature",
  "properties": {
    "iso:country":"BE",
    "sg:address":"Hoogkouterbaan 31",
    "sg:city":"Haaltert",
    "sg:classifiers":[
        {
            "category":"Real Estate",
            "subcategory":"Architect",
            "type":"Services"
        }
    ],
    "sg:phone":"+32 53 83 89 91",
    "sg:postcode":"9450",
    "sg:province":"Oost-Vlaanderen",
    "wof:name":"Van Praet M",
    "wof:placetype":"venue"
},
  "geometry": {"coordinates":[3.9843709469,50.9000816345],"type":"Point"}
}