{
  "type": "Feature",
  "properties": {
    "iso:country":"BE",
    "sg:address":"Bergstraat 49ba",
    "sg:city":"Heist-op-den-berg",
    "sg:classifiers":[
        {
            "category":"Shopping",
            "subcategory":"Clothing, Apparel, & Fashions",
            "type":"Retail Goods"
        }
    ],
    "sg:phone":"+32 15 24 16 52",
    "sg:postcode":"2220",
    "sg:province":"Antwerpen",
    "sg:tags":[
        "lingerie",
        "sous-v\u00eatements"
    ],
    "wof:name":"Huis Christiann",
    "wof:placetype":"venue"
},
  "geometry": {"coordinates":[4.723277092,51.0757522583],"type":"Point"}
}