{
  "type": "Feature",
  "properties": {
    "addr:full":"Frankrijklei 12 Antwerpen Antwerpen 2000",
    "addr:housenumber":"12",
    "addr:postcode":"2000",
    "addr:street":"Frankrijklei",
    "iso:country":"BE",
    "sg:address":"Frankrijklei 12",
    "sg:city":"Antwerpen",
    "sg:classifiers":[
        {
            "category":"Professional",
            "subcategory":"Employment Agencies",
            "type":"Services"
        }
    ],
    "sg:phone":"+32 3 232 25 50",
    "sg:postcode":"2000",
    "sg:province":"Antwerpen",
    "sg:tags":[
        "temping",
        "-",
        "manual"
    ],
    "wof:name":"Ritmo Interim",
    "wof:placetype":"venue"
},
  "geometry": {"coordinates":[4.415353775,51.219127655],"type":"Point"}
}