{
  "type": "Feature",
  "properties": {
    "iso:country":"BE",
    "sg:address":"Nieuwbaan 29ba",
    "sg:city":"Ternat",
    "sg:orig_category":"Licht metalen verpakkingen Fab",
    "sg:phone":"+32 53 64 70 20",
    "sg:postcode":"1742",
    "sg:province":"Vlaams-Brabant",
    "wof:name":"Tubes Souples",
    "wof:placetype":"venue"
},
  "geometry": {"coordinates":[4.1238517761,50.880065918],"type":"Point"}
}