{
  "type": "Feature",
  "properties": {
    "iso:country":"BE",
    "sg:address":"Rennevoortstraat 44",
    "sg:city":"Ledegem",
    "sg:orig_category":"Rundveehouders Varkenskwekers",
    "sg:phone":"+32 56 50 92 23",
    "sg:postcode":"8880",
    "sg:province":"West-Vlaanderen",
    "wof:name":"Marc Verhelst",
    "wof:placetype":"venue"
},
  "geometry": {"coordinates":[3.1587300301,50.8838768005],"type":"Point"}
}