{
  "type": "Feature",
  "properties": {
    "addr:full":"Vijverweg 3 Haacht Vlaams-Brabant 3150",
    "addr:housenumber":"3",
    "addr:postcode":"3150",
    "addr:street":"Vijverweg",
    "iso:country":"BE",
    "sg:address":"Vijverweg 3",
    "sg:city":"Haacht",
    "sg:classifiers":[
        {
            "category":"Wholesale",
            "subcategory":"Computers",
            "type":"Manufacturing & Wholesale Goods"
        }
    ],
    "sg:phone":"+32 16 60 29 61",
    "sg:postcode":"3150",
    "sg:province":"Vlaams-Brabant",
    "sg:tags":[
        "cabling",
        "processing",
        "-",
        "data"
    ],
    "wof:name":"A.w.s.",
    "wof:placetype":"venue"
},
  "geometry": {"coordinates":[4.6150999069,50.9827957153],"type":"Point"}
}