{
  "type": "Feature",
  "properties": {
    "iso:country":"BE",
    "sg:address":"Avenue Guillaume De Greef 53",
    "sg:city":"Bruxelles (jette)",
    "sg:classifiers":[
        {
            "category":"Shopping",
            "subcategory":"Books",
            "type":"Retail Goods"
        }
    ],
    "sg:phone":"+32 2 479 88 56",
    "sg:postcode":"1090",
    "sg:province":"Bruxelles-Capitale",
    "sg:tags":[
        "bookseller"
    ],
    "wof:name":"Florair 3000 Sa",
    "wof:placetype":"venue"
},
  "geometry": {"coordinates":[4.3337230682,50.8852844238],"type":"Point"}
}