{
  "type": "Feature",
  "properties": {
    "addr:full":"Chauss\u00c9e De Louvain 430 Schaarbeek/schaerbeek Bruxelles-Capitale 1030",
    "addr:housenumber":"430",
    "addr:postcode":"1030",
    "addr:street":"Chausse\u0301E De Louvain",
    "iso:country":"BE",
    "sg:address":"Chauss\u00c9e De Louvain 430",
    "sg:city":"Schaarbeek/schaerbeek",
    "sg:orig_category":"Imprimeries and copyshops. Secr\u00e9tariats",
    "sg:phone":"+32 2 733 32 65",
    "sg:postcode":"1030",
    "sg:province":"Bruxelles-Capitale",
    "wof:name":"Clap Copy 2000",
    "wof:placetype":"venue"
},
  "geometry": {"coordinates":[4.3893609047,50.8526268005],"type":"Point"}
}