{
  "type": "Feature",
  "properties": {
    "iso:country":"BE",
    "sg:address":"Volksv. De Jaegerelaan 70b61",
    "sg:city":"Kortrijk",
    "sg:classifiers":[
        {
            "category":"Cafe",
            "type":"Food & Drink"
        }
    ],
    "sg:phone":"+32 56 21 96 22",
    "sg:postcode":"8500",
    "sg:province":"West-Vlaanderen",
    "sg:tags":[
        "caf\u00e9s"
    ],
    "wof:name":"Marcel Delaere",
    "wof:placetype":"venue"
},
  "geometry": {"coordinates":[3.2650549412,50.827999115],"type":"Point"}
}