{
  "type": "Feature",
  "properties": {
    "iso:country":"BE",
    "sg:address":"Hoge Dreef 36",
    "sg:city":"Zoersel",
    "sg:orig_category":"Installatie van houten of kunststof schrijnwerk",
    "sg:phone":"+32 3 383 10 98",
    "sg:postcode":"2980",
    "sg:province":"Antwerpen",
    "wof:name":"Van Dooren",
    "wof:placetype":"venue"
},
  "geometry": {"coordinates":[4.6433148384,51.2612075806],"type":"Point"}
}