{
  "type": "Feature",
  "properties": {
    "iso:country":"BE",
    "sg:address":"Quai Timmermans 44",
    "sg:city":"Li\u00e8ge",
    "sg:orig_category":"Black-Out Shades For Skylights And Rooflights",
    "sg:phone":"+32 4 252 98 70",
    "sg:postcode":"4000",
    "sg:province":"Li\u00e8ge",
    "wof:name":"Superplastic S.a.",
    "wof:placetype":"venue"
},
  "geometry": {"coordinates":[5.5667228699,50.6093788147],"type":"Point"}
}