{
  "type": "Feature",
  "properties": {
    "iso:country":"BE",
    "sg:address":"Poorterijstraat 37bc",
    "sg:city":"Zedelgem",
    "sg:orig_category":"Traitements param\u00e9dicaux",
    "sg:phone":"+32 50 21 70 48",
    "sg:postcode":"8211",
    "sg:province":"West-Vlaanderen",
    "wof:name":"D. Debaeke",
    "wof:placetype":"venue"
},
  "geometry": {"coordinates":[3.0889649391,51.1200408936],"type":"Point"}
}