{
  "type": "Feature",
  "properties": {
    "iso:country":"BE",
    "sg:address":"Rue Alfred Henno 163-2",
    "sg:city":"Mouscron",
    "sg:classifiers":[
        {
            "category":"Real Estate",
            "subcategory":"Architect",
            "type":"Services"
        }
    ],
    "sg:phone":"+32 56 33 46 04",
    "sg:postcode":"7700",
    "sg:province":"Hainaut",
    "wof:name":"Deschuytere P",
    "wof:placetype":"venue"
},
  "geometry": {"coordinates":[3.1955521107,50.7422370911],"type":"Point"}
}