{
  "type": "Feature",
  "properties": {
    "addr:full":"Stationsstraat 58b1 Beveren Oost-Vlaanderen 9120",
    "addr:housenumber":"58b1",
    "addr:postcode":"9120",
    "addr:street":"Stationsstraat",
    "iso:country":"BE",
    "sg:address":"Stationsstraat 58b1",
    "sg:city":"Beveren",
    "sg:orig_category":"S\u00e9lection de personnel and placement",
    "sg:phone":"+32 3 775 86 71",
    "sg:postcode":"9120",
    "sg:province":"Oost-Vlaanderen",
    "wof:name":"Vdab",
    "wof:placetype":"venue"
},
  "geometry": {"coordinates":[4.2575678825,51.2101631165],"type":"Point"}
}