{
  "type": "Feature",
  "properties": {
    "addr:full":"Avenue De L'universit\u00e9 61 Bruxelles (ixelles) Bruxelles-Capitale 1050",
    "addr:housenumber":"61",
    "addr:postcode":"1050",
    "addr:street":"Avenue De L'Universite \u0301",
    "iso:country":"BE",
    "sg:address":"Avenue De L'universit\u00e9 61",
    "sg:city":"Bruxelles (ixelles)",
    "sg:classifiers":[
        {
            "category":"Real Estate",
            "subcategory":"Architect",
            "type":"Services"
        }
    ],
    "sg:phone":"+32 2 646 97 84",
    "sg:postcode":"1050",
    "sg:province":"Bruxelles-Capitale",
    "wof:name":"Culot D",
    "wof:placetype":"venue"
},
  "geometry": {"coordinates":[4.3866457939,50.8146629333],"type":"Point"}
}