{
  "type": "Feature",
  "properties": {
    "iso:country":"BE",
    "sg:address":"Rue Du Redeau 44",
    "sg:city":"Yvoir",
    "sg:orig_category":"Pain, p\u00e2tisseries and confiseries. Caf\u00e9s",
    "sg:phone":"+32 82 61 22 11",
    "sg:postcode":"5530",
    "sg:province":"Namur",
    "wof:name":"Albert Lacroix",
    "wof:placetype":"venue"
},
  "geometry": {"coordinates":[4.8967819214,50.3320388794],"type":"Point"}
}