{
  "type": "Feature",
  "properties": {
    "iso:country":"BE",
    "sg:address":"Bullange 239ba",
    "sg:city":"B\u00dcllingen/bullange",
    "sg:classifiers":[
        {
            "category":"Shopping",
            "subcategory":"Clothing, Apparel, & Fashions",
            "type":"Retail Goods"
        }
    ],
    "sg:phone":"+32 80 64 22 42",
    "sg:postcode":"4760",
    "sg:province":"Li\u00e8ge",
    "sg:tags":[
        "v\u00eatements",
        "pour",
        "dame"
    ],
    "wof:name":"Maison Kathy's El\u00c9gance",
    "wof:placetype":"venue"
},
  "geometry": {"coordinates":[6.3118200302,50.3753318787],"type":"Point"}
}