{
  "type": "Feature",
  "properties": {
    "iso:country":"BE",
    "sg:address":"Woluwe Shopping Center",
    "sg:city":"Bruxelles (woluwe-saint-lambert)",
    "sg:classifiers":[
        {
            "category":"Personal",
            "subcategory":"Barber",
            "type":"Services"
        }
    ],
    "sg:phone":"+32 2 770 04 01",
    "sg:postcode":"1200",
    "sg:province":"Bruxelles-Capitale",
    "sg:tags":[
        "gentleman",
        "salon",
        "-",
        "hairdressing"
    ],
    "wof:name":"Barbershop Cy",
    "wof:placetype":"venue"
},
  "geometry": {"coordinates":[4.4168701172,50.8531761169],"type":"Point"}
}