{
  "type": "Feature",
  "properties": {
    "addr:full":"Avenue Des Martyrs 283 Fl\u00c9ron Li\u00e8ge 4620",
    "addr:housenumber":"283",
    "addr:postcode":"4620",
    "addr:street":"Avenue Des Martyrs",
    "iso:country":"BE",
    "sg:address":"Avenue Des Martyrs 283",
    "sg:city":"Fl\u00c9ron",
    "sg:orig_category":"Equipement photographique. Jeux and jouets. Eclairage et \u00e9quipements du foyer. Souvenirs and objets ",
    "sg:phone":"+32 4 358 75 40",
    "sg:postcode":"4620",
    "sg:province":"Li\u00e8ge",
    "wof:name":"Blokker",
    "wof:placetype":"venue"
},
  "geometry": {"coordinates":[5.6860442162,50.6147499084],"type":"Point"}
}