{
  "type": "Feature",
  "properties": {
    "iso:country":"BE",
    "sg:address":"Nieuwpoortsesteenweg 393",
    "sg:city":"Oostende",
    "sg:orig_category":"Animations diverses",
    "sg:phone":"+32 59 80 93 03",
    "sg:postcode":"8400",
    "sg:province":"West-Vlaanderen",
    "wof:name":"Coast To Coast",
    "wof:placetype":"venue"
},
  "geometry": {"coordinates":[2.8927719593,51.2171401978],"type":"Point"}
}