{
  "type": "Feature",
  "properties": {
    "iso:country":"BE",
    "sg:address":"Veldekensstraat 61",
    "sg:city":"Lochristi",
    "sg:classifiers":[
        {
            "category":"Wholesale",
            "subcategory":"Plants",
            "type":"Manufacturing & Wholesale Goods"
        }
    ],
    "sg:phone":"+32 9 355 82 68",
    "sg:postcode":"9080",
    "sg:province":"Oost-Vlaanderen",
    "sg:tags":[
        "whol",
        "flower",
        "-",
        "grower"
    ],
    "wof:name":"De Graeve F",
    "wof:placetype":"venue"
},
  "geometry": {"coordinates":[3.8147900105,51.0760307312],"type":"Point"}
}