{
  "type": "Feature",
  "properties": {
    "addr:full":"Blankenbergse Steenweg 13b Zuienkerke West-Vlaanderen 8377",
    "addr:housenumber":"13b",
    "addr:postcode":"8377",
    "addr:street":"Blankenbergse Steenweg",
    "iso:country":"BE",
    "sg:address":"Blankenbergse Steenweg 13b",
    "sg:city":"Zuienkerke",
    "sg:orig_category":"Non-Classified Establishments",
    "sg:phone":"+32 50 30 03 51",
    "sg:postcode":"8377",
    "sg:province":"West-Vlaanderen",
    "wof:name":"Centre Cosmetique",
    "wof:placetype":"venue"
},
  "geometry": {"coordinates":[3.1795630455,51.2694015503],"type":"Point"}
}