{
  "type": "Feature",
  "properties": {
    "iso:country":"BE",
    "sg:address":"Rue Reine Astrid 72",
    "sg:city":"Seraing",
    "sg:orig_category":"MEUBELONTWERP AND -INSTALLATIE",
    "sg:phone":"+32 4 336 38 88",
    "sg:postcode":"4100",
    "sg:province":"Li\u00e8ge",
    "wof:name":"L\u00b4amie De La Cuisine",
    "wof:placetype":"venue"
},
  "geometry": {"coordinates":[5.5397801399,50.5721588135],"type":"Point"}
}