{
  "type": "Feature",
  "properties": {
    "iso:country":"BE",
    "sg:address":"Rue Des Garennes 18-20",
    "sg:city":"Mouscron",
    "sg:classifiers":[
        {
            "category":"Wholesale",
            "subcategory":"Meat",
            "type":"Manufacturing & Wholesale Goods"
        }
    ],
    "sg:phone":"+32 56 84 11 94",
    "sg:postcode":"7700",
    "sg:province":"Hainaut",
    "sg:tags":[
        "whol",
        "-"
    ],
    "wof:name":"Barbe & Fils",
    "wof:placetype":"venue"
},
  "geometry": {"coordinates":[3.2332599163,50.7567138672],"type":"Point"}
}