{
  "type": "Feature",
  "properties": {
    "iso:country":"BE",
    "sg:address":"Opitterkiezel 84",
    "sg:city":"Bree",
    "sg:classifiers":[
        {
            "category":"Building & Trades",
            "subcategory":"Plumbing",
            "type":"Services"
        }
    ],
    "sg:phone":"+32 89 48 11 72",
    "sg:postcode":"3960",
    "sg:province":"Limburg",
    "sg:tags":[
        "repair",
        "mainten",
        "-",
        "central",
        "heating"
    ],
    "wof:name":"Sani-klima Bvba",
    "wof:placetype":"venue"
},
  "geometry": {"coordinates":[5.5944190025,51.1405677795],"type":"Point"}
}