{
  "type": "Feature",
  "properties": {
    "addr:full":"Blekerijweg 30 Poperinge West-Vlaanderen 8972",
    "addr:housenumber":"30",
    "addr:postcode":"8972",
    "addr:street":"Blekerijweg",
    "iso:country":"BE",
    "sg:address":"Blekerijweg 30",
    "sg:city":"Poperinge",
    "sg:orig_category":"Installatie van houten of kunststof schrijnwerk Meubelzaken, woning- and keukeninrichting",
    "sg:phone":"+32 57 30 09 50",
    "sg:postcode":"8972",
    "sg:province":"West-Vlaanderen",
    "wof:name":"Joseph Vandeputte",
    "wof:placetype":"venue"
},
  "geometry": {"coordinates":[2.6572289467,50.8866729736],"type":"Point"}
}