{
  "type": "Feature",
  "properties": {
    "addr:full":"Grand-place Baudouin Ier 6 Braine-l'alleud Brabant Wallon 1420",
    "addr:housenumber":"6",
    "addr:postcode":"1420",
    "addr:street":"Grand-Place Baudouin Ier",
    "iso:country":"BE",
    "sg:address":"Grand-place Baudouin Ier 6",
    "sg:city":"Braine-l'alleud",
    "sg:orig_category":"S\u00e9curit\u00e9 sociale",
    "sg:phone":"+32 2 384 57 63",
    "sg:postcode":"1420",
    "sg:province":"Brabant Wallon",
    "wof:name":"Mutualit\u00c9 Libre",
    "wof:placetype":"venue"
},
  "geometry": {"coordinates":[-0.7004899979,47.369140625],"type":"Point"}
}