{
  "type": "Feature",
  "properties": {
    "addr:full":"Rue Vivier Le Duc 2 Court-saint-etienne Brabant Wallon 1490",
    "addr:housenumber":"2;1490",
    "addr:street":"Rue Vivier Le Duc",
    "iso:country":"BE",
    "sg:address":"Rue Vivier Le Duc 2",
    "sg:city":"Court-saint-etienne",
    "sg:orig_category":"Installation de menuiserie en bois and plastique",
    "sg:phone":"+32 10 61 22 85",
    "sg:postcode":"1490",
    "sg:province":"Brabant Wallon",
    "wof:name":"Hugues Bulinckx",
    "wof:placetype":"venue"
},
  "geometry": {"coordinates":[4.5994410515,50.6442871094],"type":"Point"}
}