{
  "type": "Feature",
  "properties": {
    "addr:full":"Amsterdamstraat 55 Oostende West-Vlaanderen 8400",
    "addr:housenumber":"55",
    "addr:postcode":"8400",
    "addr:street":"Amsterdamstraat",
    "iso:country":"BE",
    "sg:address":"Amsterdamstraat 55",
    "sg:city":"Oostende",
    "sg:classifiers":[
        {
            "category":"Personal",
            "subcategory":"Tattoo Parlor",
            "type":"Services"
        }
    ],
    "sg:phone":"+32 59 70 70 22",
    "sg:postcode":"8400",
    "sg:province":"West-Vlaanderen",
    "sg:tags":[
        "tattooists"
    ],
    "wof:name":"Tattoo Bertje",
    "wof:placetype":"venue"
},
  "geometry": {"coordinates":[2.9130160809,51.2244720459],"type":"Point"}
}