{
  "type": "Feature",
  "properties": {
    "iso:country":"BE",
    "sg:address":"Rue De Soignies 231",
    "sg:city":"Ath",
    "sg:classifiers":[
        {
            "category":"Professional",
            "subcategory":"Accounting & Tax Preparation",
            "type":"Services"
        }
    ],
    "sg:phone":"+32 68 28 65 39",
    "sg:postcode":"7810",
    "sg:province":"Hainaut",
    "sg:tags":[
        "accountant"
    ],
    "wof:name":"Michel Salingret",
    "wof:placetype":"venue"
},
  "geometry": {"coordinates":[3.8022899628,50.6149749756],"type":"Point"}
}