{
  "type": "Feature",
  "properties": {
    "addr:full":"Place De La Victoire 3 Chatelet Hainaut 6200",
    "addr:housenumber":"3",
    "addr:postcode":"6200",
    "addr:street":"Place De La Victoire;Hainaut",
    "iso:country":"BE",
    "sg:address":"Place De La Victoire 3",
    "sg:city":"Chatelet",
    "sg:classifiers":[
        {
            "category":"Cafe",
            "type":"Food & Drink"
        }
    ],
    "sg:phone":"+32 71 39 61 59",
    "sg:postcode":"6200",
    "sg:province":"Hainaut",
    "sg:tags":[
        "caf\u00e9s"
    ],
    "wof:name":"M Van De Wiele",
    "wof:placetype":"venue"
},
  "geometry": {"coordinates":[4.5179800987,50.4041481018],"type":"Point"}
}