{
  "type": "Feature",
  "properties": {
    "addr:full":"Burg. Van Gansberghelaan 46 Merelbeke Oost-Vlaanderen 9820",
    "addr:housenumber":"46",
    "addr:postcode":"9820",
    "addr:street":"Burg.;Gansberghelaan",
    "iso:country":"BE",
    "sg:address":"Burg. Van Gansberghelaan 46",
    "sg:city":"Merelbeke",
    "sg:orig_category":"Rundveehouders",
    "sg:phone":"+32 9 362 65 40",
    "sg:postcode":"9820",
    "sg:province":"Oost-Vlaanderen",
    "wof:name":"Joel Brackman",
    "wof:placetype":"venue"
},
  "geometry": {"coordinates":[3.7737998962,50.9786186218],"type":"Point"}
}