{
  "type": "Feature",
  "properties": {
    "iso:country":"BE",
    "sg:address":"Arthur Scheirisstraat 16 Box 4",
    "sg:city":"Zottegem",
    "sg:classifiers":[
        {
            "category":"Real Estate",
            "subcategory":"Architect",
            "type":"Services"
        }
    ],
    "sg:phone":"+32 9 361 20 74",
    "sg:postcode":"9620",
    "sg:province":"Oost-Vlaanderen",
    "wof:name":"Van De Velde A",
    "wof:placetype":"venue"
},
  "geometry": {"coordinates":[3.8096420765,50.8694725037],"type":"Point"}
}