{
  "type": "Feature",
  "properties": {
    "addr:full":"Boulevard Barth\u00c9l\u00c9my 31 Brussel/bruxelles Bruxelles-Capitale 1000",
    "addr:housenumber":"31",
    "addr:postcode":"1000",
    "addr:street":"Boulevard Barthe\u0301Le\u0301My;/",
    "iso:country":"BE",
    "sg:address":"Boulevard Barth\u00c9l\u00c9my 31",
    "sg:city":"Brussel/bruxelles",
    "sg:orig_category":"Organisation de salons, expositions and bourses",
    "sg:phone":"+32 2 425 25 06",
    "sg:postcode":"1000",
    "sg:province":"Bruxelles-Capitale",
    "wof:name":"Tv Z Mister Light",
    "wof:placetype":"venue"
},
  "geometry": {"coordinates":[4.3399138451,50.8512573242],"type":"Point"}
}