{
  "type": "Feature",
  "properties": {
    "addr:full":"Muisvenstraat 96 Meeuwen-gruitrode Limburg 3670",
    "addr:housenumber":"96",
    "addr:postcode":"3670",
    "addr:street":"Muisvenstraat",
    "iso:country":"BE",
    "sg:address":"Muisvenstraat 96",
    "sg:city":"Meeuwen-gruitrode",
    "sg:orig_category":"Installation de menuiserie en bois and plastique",
    "sg:phone":"+32 89 85 58 65",
    "sg:postcode":"3670",
    "sg:province":"Limburg",
    "wof:name":"Jacobus Bullen",
    "wof:placetype":"venue"
},
  "geometry": {"coordinates":[5.5481090546,51.0950508118],"type":"Point"}
}