{
  "type": "Feature",
  "properties": {
    "addr:full":"Rue De L'ath\u00e9n\u00e9e 15 Charleroi Hainaut 6000",
    "addr:housenumber":"15",
    "addr:postcode":"6000",
    "addr:street":"Rue De L'Athe \u0301Ne\u0301E;Hainaut",
    "iso:country":"BE",
    "sg:address":"Rue De L'ath\u00e9n\u00e9e 15",
    "sg:city":"Charleroi",
    "sg:classifiers":[
        {
            "category":"Professional",
            "subcategory":"Lawyer & Legal Services",
            "type":"Services"
        }
    ],
    "sg:phone":"+32 71 32 10 98",
    "sg:postcode":"6000",
    "sg:province":"Hainaut",
    "wof:name":"Dehombreux X",
    "wof:placetype":"venue"
},
  "geometry": {"coordinates":[4.4490880966,50.4075546265],"type":"Point"}
}