{
  "type": "Feature",
  "properties": {
    "addr:full":"Grand Rue 108bis Mons Hainaut 7000",
    "addr:housenumber":"108bis",
    "addr:postcode":"7000",
    "addr:street":"Grand Rue;Hainaut",
    "iso:country":"BE",
    "sg:address":"Grand Rue 108bis",
    "sg:city":"Mons",
    "sg:classifiers":[
        {
            "category":"Retail",
            "subcategory":"Laundry & Dry Cleaning",
            "type":"Services"
        }
    ],
    "sg:phone":"+32 65 35 49 95",
    "sg:postcode":"7000",
    "sg:province":"Hainaut",
    "sg:tags":[
        "self",
        "-"
    ],
    "wof:name":"Lavoir Automatique De Messines Sc",
    "wof:placetype":"venue"
},
  "geometry": {"coordinates":[3.9492800236,50.4496002197],"type":"Point"}
}