{
  "type": "Feature",
  "properties": {
    "addr:full":"Stokstraat 54 Zele Oost-Vlaanderen 9240",
    "addr:housenumber":"54",
    "addr:postcode":"9240",
    "addr:street":"Stokstraat",
    "iso:country":"BE",
    "sg:address":"Stokstraat 54",
    "sg:city":"Zele",
    "sg:orig_category":"Installation de menuiserie en bois and plastique",
    "sg:phone":"+32 52 44 67 09",
    "sg:postcode":"9240",
    "sg:province":"Oost-Vlaanderen",
    "wof:name":"Andre De Vriese",
    "wof:placetype":"venue"
},
  "geometry": {"coordinates":[4.0267391205,51.0704841614],"type":"Point"}
}