{
  "type": "Feature",
  "properties": {
    "addr:full":"Peperstraat 5 Langemark-poelkapelle West-Vlaanderen 8920",
    "addr:housenumber":"5",
    "addr:postcode":"8920",
    "addr:street":"Peperstraat",
    "iso:country":"BE",
    "sg:address":"Peperstraat 5",
    "sg:city":"Langemark-poelkapelle",
    "sg:orig_category":"Eleveurs and marchands de porcs. Eleveurs de volaille",
    "sg:phone":"+32 57 48 82 30",
    "sg:postcode":"8920",
    "sg:province":"West-Vlaanderen",
    "wof:name":"Noel Lecointre",
    "wof:placetype":"venue"
},
  "geometry": {"coordinates":[2.919770956,50.9132423401],"type":"Point"}
}