{
  "type": "Feature",
  "properties": {
    "addr:full":"Cypriaan Verhavertstraat 12 Halle Vlaams-Brabant 1500",
    "addr:housenumber":"12",
    "addr:postcode":"1500",
    "addr:street":"Cypriaan Verhavertstraat",
    "iso:country":"BE",
    "sg:address":"Cypriaan Verhavertstraat 12",
    "sg:city":"Halle",
    "sg:classifiers":[
        {
            "category":"Fast Food",
            "type":"Food & Drink"
        }
    ],
    "sg:phone":"+32 2 361 33 41",
    "sg:postcode":"1500",
    "sg:province":"Vlaams-Brabant",
    "sg:tags":[
        "\u00c0",
        "emporter",
        "restaurants"
    ],
    "wof:name":"In De Fritketel",
    "wof:placetype":"venue"
},
  "geometry": {"coordinates":[4.2335100174,50.7385597229],"type":"Point"}
}