{
  "type": "Feature",
  "properties": {
    "addr:full":"Franz Guillaumelaan 33b1 Evere Bruxelles-Capitale 1140",
    "addr:housenumber":"33b1",
    "addr:postcode":"1140",
    "addr:street":"Franz Guillaumelaan",
    "iso:country":"BE",
    "sg:address":"Franz Guillaumelaan 33b1",
    "sg:city":"Evere",
    "sg:orig_category":"Krantenuitgeverijen Tijdschriftenuitgeverijen",
    "sg:phone":"+32 2 521 60 79",
    "sg:postcode":"1140",
    "sg:province":"Bruxelles-Capitale",
    "wof:name":"Bienbon Paul",
    "wof:placetype":"venue"
},
  "geometry": {"coordinates":[4.41563797,50.8621788025],"type":"Point"}
}