{
  "type": "Feature",
  "properties": {
    "iso:country":"BE",
    "sg:address":"Kardinaal Cardijnlaan 94",
    "sg:city":"Lint",
    "sg:orig_category":"Verhuur diversen Winkelinrichting and handelsuitrusting Gh",
    "sg:phone":"+32 3 454 01 17",
    "sg:postcode":"2547",
    "sg:province":"Antwerpen",
    "wof:name":"Funsport's Unlimited",
    "wof:placetype":"venue"
},
  "geometry": {"coordinates":[4.4873251915,51.1241455078],"type":"Point"}
}