{
  "type": "Feature",
  "properties": {
    "addr:full":"Scheepsdalelaan 10b1 Brugge West-Vlaanderen 8000",
    "addr:housenumber":"10b1",
    "addr:postcode":"8000",
    "addr:street":"Scheepsdalelaan",
    "iso:country":"BE",
    "sg:address":"Scheepsdalelaan 10b1",
    "sg:city":"Brugge",
    "sg:orig_category":"Banken and kredietinstellingen",
    "sg:phone":"+32 50 34 66 64",
    "sg:postcode":"8000",
    "sg:province":"West-Vlaanderen",
    "wof:name":"Fortis",
    "wof:placetype":"venue"
},
  "geometry": {"coordinates":[3.21459198,51.2161598206],"type":"Point"}
}