{
  "type": "Feature",
  "properties": {
    "iso:country":"BE",
    "sg:address":"Rue Solvay 8",
    "sg:city":"Chapelle-lez-herlaimont",
    "sg:classifiers":[
        {
            "category":"Banks & Credit Unions",
            "subcategory":"Bank",
            "type":"Services"
        }
    ],
    "sg:phone":"+32 64 46 07 57",
    "sg:postcode":"7160",
    "sg:province":"Hainaut",
    "sg:tags":[
        "savings-banks"
    ],
    "wof:name":"Centea B.a.c. Centre",
    "wof:placetype":"venue"
},
  "geometry": {"coordinates":[4.2801671028,50.4691085815],"type":"Point"}
}