{
  "type": "Feature",
  "properties": {
    "iso:country":"BE",
    "sg:address":"Rue Petite Chenevi\u00e8re 72",
    "sg:city":"Charleroi (marcinelle)",
    "sg:classifiers":[
        {
            "category":"Social Services",
            "type":"Services"
        }
    ],
    "sg:phone":"+32 71 56 05 90",
    "sg:postcode":"6001",
    "sg:province":"Hainaut",
    "wof:name":"Banque Alimentaire Du Pays De Charleroi Et Du Centre",
    "wof:placetype":"venue"
},
  "geometry": {"coordinates":[4.4411859512,50.3891105652],"type":"Point"}
}