{
  "type": "Feature",
  "properties": {
    "iso:country":"BE",
    "sg:address":"Tramstraat 35",
    "sg:city":"Destelbergen (heusden)",
    "sg:classifiers":[
        {
            "category":"Shopping",
            "subcategory":"Jewelry",
            "type":"Retail Goods"
        }
    ],
    "sg:phone":"+32 9 231 74 60",
    "sg:postcode":"9070",
    "sg:province":"Oost-Vlaanderen",
    "sg:tags":[
        "jeweller",
        "-"
    ],
    "wof:name":"Heylens K",
    "wof:placetype":"venue"
},
  "geometry": {"coordinates":[3.8019719124,51.0309753418],"type":"Point"}
}