{
  "type": "Feature",
  "properties": {
    "addr:full":"Rue Fran\u00c7ois Bovesse 74 Eghezee Namur 5310",
    "addr:housenumber":"74",
    "addr:postcode":"5310",
    "addr:street":"Rue Franc\u0327Ois Bovesse;Namur",
    "iso:country":"BE",
    "sg:address":"Rue Fran\u00c7ois Bovesse 74",
    "sg:city":"Eghezee",
    "sg:orig_category":"Epiceries",
    "sg:phone":"+32 81 51 18 41",
    "sg:postcode":"5310",
    "sg:province":"Namur",
    "wof:name":"Poids D'or",
    "wof:placetype":"venue"
},
  "geometry": {"coordinates":[4.8610219955,50.5528259277],"type":"Point"}
}