{
  "type": "Feature",
  "properties": {
    "iso:country":"BE",
    "sg:address":"Turnhoutsebaan 37",
    "sg:city":"Mol",
    "sg:classifiers":[
        {
            "category":"Home & Garden",
            "subcategory":"Home Furnishings",
            "type":"Retail Goods"
        }
    ],
    "sg:phone":"+32 14 31 96 09",
    "sg:postcode":"2400",
    "sg:province":"Antwerpen",
    "sg:tags":[
        "-",
        "bed",
        "mattress"
    ],
    "wof:name":"Matrassenhuis",
    "wof:placetype":"venue"
},
  "geometry": {"coordinates":[5.1153898239,51.1961212158],"type":"Point"}
}