{
  "type": "Feature",
  "properties": {
    "addr:full":"Rue Voie De Fer 17 Stavelot Li\u00e8ge 4970",
    "addr:housenumber":"17",
    "addr:postcode":"4970",
    "addr:street":"Rue Voie De Fer",
    "iso:country":"BE",
    "sg:address":"Rue Voie De Fer 17",
    "sg:city":"Stavelot",
    "sg:orig_category":"Woningbouw",
    "sg:phone":"+32 87 27 57 45",
    "sg:postcode":"4970",
    "sg:province":"Li\u00e8ge",
    "wof:name":"R.g. Constructions",
    "wof:placetype":"venue"
},
  "geometry": {"coordinates":[6.0002741814,50.4805107117],"type":"Point"}
}