{
  "type": "Feature",
  "properties": {
    "addr:full":"Rodestraat 92 Zottegem Oost-Vlaanderen 9620",
    "addr:housenumber":"92",
    "addr:postcode":"9620",
    "addr:street":"Rodestraat",
    "iso:country":"BE",
    "sg:address":"Rodestraat 92",
    "sg:city":"Zottegem",
    "sg:orig_category":"Sportclubs",
    "sg:phone":"+32 9 360 22 52",
    "sg:postcode":"9620",
    "sg:province":"Oost-Vlaanderen",
    "wof:name":"De Hert - Zottegem",
    "wof:placetype":"venue"
},
  "geometry": {"coordinates":[3.8373188972,50.8565406799],"type":"Point"}
}