{
  "type": "Feature",
  "properties": {
    "iso:country":"BE",
    "sg:address":"Maastrichterstraat 31a",
    "sg:city":"Riemst (herderen)",
    "sg:classifiers":[
        {
            "category":"Building & Trades",
            "subcategory":"Electrical",
            "type":"Services"
        }
    ],
    "sg:phone":"+32 12 45 75 50",
    "sg:postcode":"3770",
    "sg:province":"Limburg",
    "sg:tags":[
        "electric",
        "-",
        "housewiring",
        "contractor"
    ],
    "wof:name":"Husquet J",
    "wof:placetype":"venue"
},
  "geometry": {"coordinates":[5.6016187668,50.8145675659],"type":"Point"}
}