{
  "type": "Feature",
  "properties": {
    "addr:full":"Rue Bellevue 11 Musson Luxembourg 6750",
    "addr:housenumber":"11",
    "addr:postcode":"6750",
    "addr:street":"Rue Bellevue",
    "iso:country":"BE",
    "sg:address":"Rue Bellevue 11",
    "sg:city":"Musson",
    "sg:orig_category":"M\u00e9decins and sp\u00e9cialistes",
    "sg:phone":"+32 63 67 73 38",
    "sg:postcode":"6750",
    "sg:province":"Luxembourg",
    "wof:name":"J. Roth\u00c9",
    "wof:placetype":"venue"
},
  "geometry": {"coordinates":[5.6946001053,49.5574684143],"type":"Point"}
}