{
  "type": "Feature",
  "properties": {
    "iso:country":"BE",
    "sg:address":"Merelstraat 22",
    "sg:city":"Wachtebeke",
    "sg:classifiers":[
        {
            "category":"Arena",
            "subcategory":"Sports Club",
            "type":"Entertainment"
        }
    ],
    "sg:phone":"+32 9 345 97 31",
    "sg:postcode":"9185",
    "sg:province":"Oost-Vlaanderen",
    "sg:tags":[
        "de"
    ],
    "wof:name":"Wielercentrum",
    "wof:placetype":"venue"
},
  "geometry": {"coordinates":[3.8494009972,51.1659851074],"type":"Point"}
}