{
  "type": "Feature",
  "properties": {
    "addr:full":"Oude Luikerbaan 50 Hasselt Limburg 3500",
    "addr:housenumber":"50",
    "addr:postcode":"3500",
    "addr:street":"Oude Luikerbaan",
    "iso:country":"BE",
    "sg:address":"Oude Luikerbaan 50",
    "sg:city":"Hasselt",
    "sg:classifiers":[
        {
            "category":"Health Services",
            "subcategory":"Health Practitioner",
            "type":"Services"
        }
    ],
    "sg:phone":"+32 11 22 76 70",
    "sg:postcode":"3500",
    "sg:province":"Limburg",
    "sg:tags":[
        "physiotherapist"
    ],
    "wof:name":"Vanbekbergen A",
    "wof:placetype":"venue"
},
  "geometry": {"coordinates":[5.3444538116,50.9232025146],"type":"Point"}
}