{
  "type": "Feature",
  "properties": {
    "iso:country":"BE",
    "sg:address":"Voort 18",
    "sg:city":"Hoogstraten",
    "sg:orig_category":"Producteurs de fruits. Eleveurs de volaille",
    "sg:phone":"+32 3 315 73 11",
    "sg:postcode":"2328",
    "sg:province":"Antwerpen",
    "wof:name":"Willy Verheyen",
    "wof:placetype":"venue"
},
  "geometry": {"coordinates":[4.7949099541,51.4665756226],"type":"Point"}
}