{
  "type": "Feature",
  "properties": {
    "addr:full":"Burgemeester J. Van Aperenstraat 54-1 Hoogstraten Antwerpen 2320",
    "addr:housenumber":"54-1",
    "addr:postcode":"2320",
    "addr:street":"Burgemeester J. Van Aperenstraat",
    "iso:country":"BE",
    "sg:address":"Burgemeester J. Van Aperenstraat 54-1",
    "sg:city":"Hoogstraten",
    "sg:classifiers":[
        {
            "category":"Personal",
            "subcategory":"Nail Salon",
            "type":"Services"
        }
    ],
    "sg:phone":"+32 3 314 38 49",
    "sg:postcode":"2320",
    "sg:province":"Antwerpen",
    "sg:tags":[
        "pedicure"
    ],
    "wof:name":"Christianen B",
    "wof:placetype":"venue"
},
  "geometry": {"coordinates":[4.7504959106,51.4011764526],"type":"Point"}
}