{
  "type": "Feature",
  "properties": {
    "iso:country":"BE",
    "sg:address":"Melanedreef 15",
    "sg:city":"Houthulst",
    "sg:classifiers":[
        {
            "category":"Freight",
            "type":"Transportation"
        }
    ],
    "sg:phone":"+32 51 54 41 13",
    "sg:postcode":"8650",
    "sg:province":"West-Vlaanderen",
    "sg:tags":[
        "-",
        "transport"
    ],
    "wof:name":"Ametrans",
    "wof:placetype":"venue"
},
  "geometry": {"coordinates":[2.9137239456,50.9563293457],"type":"Point"}
}