{
  "type": "Feature",
  "properties": {
    "iso:country":"BE",
    "sg:address":"Pastoor Boelstraat 14",
    "sg:city":"Temse",
    "sg:classifiers":[
        {
            "category":"Retail",
            "subcategory":"Auto Repair",
            "type":"Services"
        }
    ],
    "sg:phone":"+32 3 771 01 22",
    "sg:postcode":"9140",
    "sg:province":"Oost-Vlaanderen",
    "sg:tags":[
        "automobile-body"
    ],
    "wof:name":"Garage Meeus",
    "wof:placetype":"venue"
},
  "geometry": {"coordinates":[4.2115092278,51.1271820068],"type":"Point"}
}