{
  "type": "Feature",
  "properties": {
    "iso:country":"BE",
    "sg:address":"Boulevard De Dixmude 9",
    "sg:city":"Brussel/bruxelles",
    "sg:orig_category":"Epiceries",
    "sg:phone":"+32 2 219 91 77",
    "sg:postcode":"1000",
    "sg:province":"Bruxelles-Capitale",
    "wof:name":"Axiome",
    "wof:placetype":"venue"
},
  "geometry": {"coordinates":[4.3451499939,50.8563117981],"type":"Point"}
}