{
  "type": "Feature",
  "properties": {
    "addr:full":"Renbaanlaan 152 Elsene/ixelles Bruxelles-Capitale 1050",
    "addr:housenumber":"152",
    "addr:postcode":"1050",
    "addr:street":"Renbaanlaan",
    "iso:country":"BE",
    "sg:address":"Renbaanlaan 152",
    "sg:city":"Elsene/ixelles",
    "sg:orig_category":"Telecommunicatieapparaten",
    "sg:phone":"+32 2 646 58 69",
    "sg:postcode":"1050",
    "sg:province":"Bruxelles-Capitale",
    "wof:name":"Informelec",
    "wof:placetype":"venue"
},
  "geometry": {"coordinates":[4.3777008057,50.8199462891],"type":"Point"}
}