{
  "type": "Feature",
  "properties": {
    "addr:full":"Gentsesteenweg 27 Erpe-mere Oost-Vlaanderen 9420",
    "addr:housenumber":"27",
    "addr:postcode":"9420",
    "addr:street":"Gentsesteenweg",
    "iso:country":"BE",
    "sg:address":"Gentsesteenweg 27",
    "sg:city":"Erpe-mere",
    "sg:orig_category":"Benzinestations and brandstoffen Verhuur voertuigen behalve auto's",
    "sg:phone":"+32 53 80 47 12",
    "sg:postcode":"9420",
    "sg:province":"Oost-Vlaanderen",
    "wof:name":"Trend - Rent",
    "wof:placetype":"venue"
},
  "geometry": {"coordinates":[3.9928529263,50.9423980713],"type":"Point"}
}