{
  "type": "Feature",
  "properties": {
    "iso:country":"BE",
    "sg:address":"Daalstraat 43",
    "sg:city":"Riemst",
    "sg:orig_category":"Installation \u00e9lectrique r\u00e9sidentielle",
    "sg:phone":"+32 12 45 42 72",
    "sg:postcode":"3770",
    "sg:province":"Limburg",
    "wof:name":"Fa. Reynders P.",
    "wof:placetype":"venue"
},
  "geometry": {"coordinates":[5.5703339577,50.8107681274],"type":"Point"}
}