{
  "type": "Feature",
  "properties": {
    "iso:country":"BE",
    "sg:address":"Nieuwstraat 50b",
    "sg:city":"Rumst",
    "sg:orig_category":"Prospectus Distribution Service",
    "sg:phone":"+32 3 880 72 60",
    "sg:postcode":"2840",
    "sg:province":"Antwerpen",
    "wof:name":"Opslag En Distributie Ter Haeghe Nv",
    "wof:placetype":"venue"
},
  "geometry": {"coordinates":[4.4105100632,51.0808601379],"type":"Point"}
}