{
  "type": "Feature",
  "properties": {
    "addr:full":"Wielmakerstraat 7 Tielt West-Vlaanderen 8700",
    "addr:housenumber":"7",
    "addr:postcode":"8700",
    "addr:street":"Wielmakerstraat",
    "iso:country":"BE",
    "sg:address":"Wielmakerstraat 7",
    "sg:city":"Tielt",
    "sg:orig_category":"Eleveurs and marchands de porcs",
    "sg:phone":"+32 51 40 27 37",
    "sg:postcode":"8700",
    "sg:province":"West-Vlaanderen",
    "wof:name":"Silveer Dejonckheere",
    "wof:placetype":"venue"
},
  "geometry": {"coordinates":[3.3613810539,50.9921035767],"type":"Point"}
}