{
  "type": "Feature",
  "properties": {
    "addr:full":"Stasegemdorp 65 Harelbeke West-Vlaanderen 8530",
    "addr:housenumber":"65",
    "addr:postcode":"8530",
    "addr:street":"Stasegemdorp",
    "iso:country":"BE",
    "sg:address":"Stasegemdorp 65",
    "sg:city":"Harelbeke",
    "sg:orig_category":"Journaux. Tabac",
    "sg:phone":"+32 56 20 16 90",
    "sg:postcode":"8530",
    "sg:province":"West-Vlaanderen",
    "wof:name":"'t Cartouchke",
    "wof:placetype":"venue"
},
  "geometry": {"coordinates":[3.3112299442,50.8310089111],"type":"Point"}
}