{
  "type": "Feature",
  "properties": {
    "iso:country":"BE",
    "sg:address":"Kapellestraat 70",
    "sg:city":"Assenede",
    "sg:orig_category":"Eleveurs and marchands de porcs. Eleveurs de bovins",
    "sg:phone":"+32 9 373 67 66",
    "sg:postcode":"9961",
    "sg:province":"Oost-Vlaanderen",
    "wof:name":"Odiel Hoorne",
    "wof:placetype":"venue"
},
  "geometry": {"coordinates":[3.7327699661,51.252281189],"type":"Point"}
}