{
  "type": "Feature",
  "properties": {
    "iso:country":"BE",
    "sg:address":"Camuselstraat 47",
    "sg:city":"Brussel/bruxelles",
    "sg:orig_category":"Artiesten and kunstenaars Etalage- and showroomontwerpers",
    "sg:phone":"+32 2 511 94 56",
    "sg:postcode":"1000",
    "sg:province":"Bruxelles-Capitale",
    "wof:name":"Jean-marc Collier",
    "wof:placetype":"venue"
},
  "geometry": {"coordinates":[4.3408799171,50.8468742371],"type":"Point"}
}