{
  "type": "Feature",
  "properties": {
    "addr:full":"Velodroomstraat 23 Herentals Antwerpen 2200",
    "addr:housenumber":"23",
    "addr:postcode":"2200",
    "addr:street":"Velodroomstraat",
    "iso:country":"BE",
    "sg:address":"Velodroomstraat 23",
    "sg:city":"Herentals",
    "sg:classifiers":[
        {
            "category":"Health Services",
            "subcategory":"Health Practitioner",
            "type":"Services"
        }
    ],
    "sg:phone":"+32 14 84 22 11",
    "sg:postcode":"2200",
    "sg:province":"Antwerpen",
    "sg:tags":[
        "physiotherapist"
    ],
    "wof:name":"Kilian",
    "wof:placetype":"venue"
},
  "geometry": {"coordinates":[4.8471980095,51.1742172241],"type":"Point"}
}