{
  "type": "Feature",
  "properties": {
    "iso:country":"BE",
    "sg:address":"Zeven Zillenerf 17",
    "sg:city":"Diest",
    "sg:orig_category":"Production de films, t\u00e9l\u00e9films and vid\u00e9os. R\u00e9alisation de programmes and logiciels",
    "sg:phone":"+32 13 32 68 82",
    "sg:postcode":"3293",
    "sg:province":"Vlaams-Brabant",
    "wof:name":"Diborsa",
    "wof:placetype":"venue"
},
  "geometry": {"coordinates":[5.0194377899,50.9773445129],"type":"Point"}
}