{
  "type": "Feature",
  "properties": {
    "addr:full":"Wilgestraat 78 Gent Oost-Vlaanderen 9000",
    "addr:housenumber":"78",
    "addr:postcode":"9000",
    "addr:street":"Wilgestraat;Oost-Vlaanderen",
    "iso:country":"BE",
    "sg:address":"Wilgestraat 78",
    "sg:city":"Gent",
    "sg:orig_category":"Activit\u00e9s diverses d'imprimerie",
    "sg:phone":"+32 9 225 69 38",
    "sg:postcode":"9000",
    "sg:province":"Oost-Vlaanderen",
    "wof:name":"Tastfull Design",
    "wof:placetype":"venue"
},
  "geometry": {"coordinates":[3.7110490799,51.0647621155],"type":"Point"}
}