{
  "type": "Feature",
  "properties": {
    "addr:full":"Eden City 19 Vorst/forest Bruxelles-Capitale 1190",
    "addr:housenumber":"19",
    "addr:postcode":"1190",
    "addr:street":"Eden City;/ Forest",
    "iso:country":"BE",
    "sg:address":"Eden City 19",
    "sg:city":"Vorst/forest",
    "sg:orig_category":"Artsen and specialisten",
    "sg:phone":"+32 2 374 43 88",
    "sg:postcode":"1190",
    "sg:province":"Bruxelles-Capitale",
    "wof:name":"F. De Greef",
    "wof:placetype":"venue"
},
  "geometry": {"coordinates":[4.3310408592,50.8212432861],"type":"Point"}
}