{
  "type": "Feature",
  "properties": {
    "addr:full":"Rue Duch\u00eane 18 Neupr\u00e9 (rotheux-rimi\u00e8re) Li\u00e8ge 4120",
    "addr:housenumber":"18",
    "addr:postcode":"4120",
    "addr:street":"Rue Duche\u0302Ne;Rotheux-Rimie\u0300Re",
    "iso:country":"BE",
    "sg:address":"Rue Duch\u00eane 18",
    "sg:city":"Neupr\u00e9 (rotheux-rimi\u00e8re)",
    "sg:classifiers":[
        {
            "category":"Professional",
            "subcategory":"Business Services",
            "type":"Services"
        }
    ],
    "sg:phone":"+32 4 371 22 36",
    "sg:postcode":"4120",
    "sg:province":"Li\u00e8ge",
    "sg:tags":[
        "firm"
    ],
    "wof:name":"Heynen A",
    "wof:placetype":"venue"
},
  "geometry": {"coordinates":[5.4850912094,50.5367126465],"type":"Point"}
}