{
  "type": "Feature",
  "properties": {
    "iso:country":"BE",
    "sg:address":"Wantestraat 30",
    "sg:city":"Ruiselede",
    "sg:orig_category":"Eleveurs and marchands de porcs",
    "sg:phone":"+32 51 68 83 73",
    "sg:postcode":"8755",
    "sg:province":"West-Vlaanderen",
    "wof:name":"Etienne Holvoet",
    "wof:placetype":"venue"
},
  "geometry": {"coordinates":[3.3966310024,51.0597457886],"type":"Point"}
}