{
  "type": "Feature",
  "properties": {
    "iso:country":"BE",
    "sg:address":"Wiedauwkaai 98-99",
    "sg:city":"Gent",
    "sg:orig_category":"Locations de machines and \u00e9quipement pour la construction. Equipements divers pour l\u00b4industrie Const",
    "sg:phone":"+32 9 253 24 96",
    "sg:postcode":"9000",
    "sg:province":"Oost-Vlaanderen",
    "wof:name":"Devos-debuck",
    "wof:placetype":"venue"
},
  "geometry": {"coordinates":[3.724905014,51.0842170715],"type":"Point"}
}