{
  "type": "Feature",
  "properties": {
    "addr:full":"Rue Joseph Ii 36-38 Box 12 Bruxelles Bruxelles-Capitale 1000",
    "addr:housenumber":"36-38 box 12",
    "addr:postcode":"1000",
    "addr:street":"Rue Joseph Ii",
    "iso:country":"BE",
    "sg:address":"Rue Joseph Ii 36-38 Box 12",
    "sg:city":"Bruxelles",
    "sg:classifiers":[
        {
            "category":"Banks & Credit Unions",
            "subcategory":"Financial Services",
            "type":"Services"
        }
    ],
    "sg:phone":"+32 2 460 03 81",
    "sg:postcode":"1000",
    "sg:province":"Bruxelles-Capitale",
    "sg:tags":[
        "loan",
        "mortgage"
    ],
    "wof:name":"Geeroms Makelaarskantoor Bvba",
    "wof:placetype":"venue"
},
  "geometry": {"coordinates":[4.3721108437,50.8459587097],"type":"Point"}
}