{
  "type": "Feature",
  "properties": {
    "addr:full":"Dottermansstr 34 Bertem Vlaams-Brabant 3060",
    "addr:housenumber":"34",
    "addr:postcode":"3060",
    "addr:street":"Dottermansstr",
    "iso:country":"BE",
    "sg:address":"Dottermansstr 34",
    "sg:city":"Bertem",
    "sg:classifiers":[
        {
            "category":"Banks & Credit Unions",
            "subcategory":"Bank",
            "type":"Services"
        }
    ],
    "sg:phone":"+32 16 48 07 49",
    "sg:postcode":"3060",
    "sg:province":"Vlaams-Brabant",
    "wof:name":"Aslk-cger Bank",
    "wof:placetype":"venue"
},
  "geometry": {"coordinates":[4.6290931702,50.8647651672],"type":"Point"}
}