{
  "type": "Feature",
  "properties": {
    "addr:full":"Renning 16 Waarschoot Oost-Vlaanderen 9950",
    "addr:housenumber":"16",
    "addr:postcode":"9950",
    "addr:street":"Renning",
    "iso:country":"BE",
    "sg:address":"Renning 16",
    "sg:city":"Waarschoot",
    "sg:orig_category":"Fietsen Motorfietsen",
    "sg:phone":"+32 9 377 21 02",
    "sg:postcode":"9950",
    "sg:province":"Oost-Vlaanderen",
    "wof:name":"Patrick Berth",
    "wof:placetype":"venue"
},
  "geometry": {"coordinates":[3.6036770344,51.1420555115],"type":"Point"}
}