{
  "type": "Feature",
  "properties": {
    "addr:full":"Molenstraat 59 Baarle-hertog Antwerpen 2387",
    "addr:housenumber":"59",
    "addr:postcode":"2387",
    "addr:street":"Molenstraat",
    "iso:country":"BE",
    "sg:address":"Molenstraat 59",
    "sg:city":"Baarle-hertog",
    "sg:classifiers":[
        {
            "category":"Professional",
            "subcategory":"Lawyer & Legal Services",
            "type":"Services"
        }
    ],
    "sg:phone":"+32 14 69 99 71",
    "sg:postcode":"2387",
    "sg:province":"Antwerpen",
    "wof:name":"Van Der Vloet Erik",
    "wof:placetype":"venue"
},
  "geometry": {"coordinates":[4.9326109886,51.4397544861],"type":"Point"}
}