{
  "type": "Feature",
  "properties": {
    "iso:country":"BE",
    "sg:address":"Chauss\u00e9e De Bruxelles 255",
    "sg:city":"Waterloo",
    "sg:classifiers":[
        {
            "category":"Shopping",
            "subcategory":"Bridal",
            "type":"Retail Goods"
        }
    ],
    "sg:phone":"+32 2 354 84 73",
    "sg:postcode":"1410",
    "sg:province":"Brabant Wallon",
    "sg:tags":[
        "list",
        "-",
        "present",
        "wedding"
    ],
    "wof:name":"Art-mena",
    "wof:placetype":"venue"
},
  "geometry": {"coordinates":[4.3997540474,50.7138671875],"type":"Point"}
}