{
  "type": "Feature",
  "properties": {
    "iso:country":"BE",
    "sg:address":"Wezenstraat 12",
    "sg:city":"Melle",
    "sg:orig_category":"Balie van Gent. Avocats and conseillers juridiques. Avocats and conseillers juridiques",
    "sg:phone":"+32 9 252 13 35",
    "sg:postcode":"9090",
    "sg:province":"Oost-Vlaanderen",
    "wof:name":"Vervaet Paul",
    "wof:placetype":"venue"
},
  "geometry": {"coordinates":[3.8002409935,51.0047569275],"type":"Point"}
}