{
  "type": "Feature",
  "properties": {
    "addr:full":"Roosbeeksestraat 32 Boutersem Vlaams-Brabant 3370",
    "addr:housenumber":"32",
    "addr:postcode":"3370",
    "addr:street":"Roosbeeksestraat",
    "iso:country":"BE",
    "sg:address":"Roosbeeksestraat 32",
    "sg:city":"Boutersem",
    "sg:orig_category":"Diverse zakelijke dienstverlening",
    "sg:phone":"+32 16 73 56 98",
    "sg:postcode":"3370",
    "sg:province":"Vlaams-Brabant",
    "wof:name":"J.v.r.-events",
    "wof:placetype":"venue"
},
  "geometry": {"coordinates":[4.8383450508,50.8313064575],"type":"Point"}
}