{
  "type": "Feature",
  "properties": {
    "addr:full":"Bilksken 10 Box 1 Lovendegem Oost-Vlaanderen 9920",
    "addr:housenumber":"10;1",
    "addr:postcode":"9920",
    "addr:street":"Bilksken;Box",
    "iso:country":"BE",
    "sg:address":"Bilksken 10 Box 1",
    "sg:city":"Lovendegem",
    "sg:orig_category":"Electric transformers, rectifiers, converters",
    "sg:phone":"+32 9 372 92 88",
    "sg:postcode":"9920",
    "sg:province":"Oost-Vlaanderen",
    "wof:name":"M.c.e. Nv",
    "wof:placetype":"venue"
},
  "geometry": {"coordinates":[3.6378970146,51.0934906006],"type":"Point"}
}