{
  "type": "Feature",
  "properties": {
    "iso:country":"BE",
    "sg:address":"Leuterweg 23",
    "sg:city":"Maasmechelen",
    "sg:classifiers":[
        {
            "category":"Insurance",
            "subcategory":"Life Insurance",
            "type":"Services"
        }
    ],
    "sg:phone":"+32 89 75 60 47",
    "sg:postcode":"3630",
    "sg:province":"Limburg",
    "sg:tags":[
        "assurance"
    ],
    "wof:name":"J. Kuypers",
    "wof:placetype":"venue"
},
  "geometry": {"coordinates":[5.6961350441,50.963848114],"type":"Point"}
}