{
  "type": "Feature",
  "properties": {
    "iso:country":"BE",
    "sg:address":"Waldstrasse 9",
    "sg:city":"Lontzen/lontzen",
    "sg:orig_category":"Rundveehouders",
    "sg:phone":"+32 87 65 94 21",
    "sg:postcode":"4710",
    "sg:province":"Li\u00e8ge",
    "wof:name":"Victor Chantraine",
    "wof:placetype":"venue"
},
  "geometry": {"coordinates":[5.9957399368,50.6875534058],"type":"Point"}
}