{
  "type": "Feature",
  "properties": {
    "addr:full":"Quai Winston Churchill 3b11 Li\u00c8ge Li\u00e8ge 4020",
    "addr:housenumber":"3b11",
    "addr:postcode":"4020",
    "addr:street":"Quai Winston Churchill",
    "iso:country":"BE",
    "sg:address":"Quai Winston Churchill 3b11",
    "sg:city":"Li\u00c8ge",
    "sg:orig_category":"Avocats and conseillers juridiques",
    "sg:phone":"+32 4 343 85 96",
    "sg:postcode":"4020",
    "sg:province":"Li\u00e8ge",
    "wof:name":"R. Neuroth",
    "wof:placetype":"venue"
},
  "geometry": {"coordinates":[5.5772299767,50.6367111206],"type":"Point"}
}