{
  "type": "Feature",
  "properties": {
    "addr:full":"Boven Vrijlegem 27 Asse Vlaams-Brabant 1730",
    "addr:housenumber":"27",
    "addr:postcode":"1730",
    "addr:street":"Boven Vrijlegem",
    "iso:country":"BE",
    "sg:address":"Boven Vrijlegem 27",
    "sg:city":"Asse",
    "sg:classifiers":[
        {
            "category":"Professional",
            "subcategory":"Computer Services",
            "type":"Services"
        }
    ],
    "sg:phone":"+32 2 454 86 70",
    "sg:postcode":"1730",
    "sg:province":"Vlaams-Brabant",
    "sg:tags":[
        "network"
    ],
    "wof:name":"Den Network Solutions Nv",
    "wof:placetype":"venue"
},
  "geometry": {"coordinates":[4.2102861404,50.9338111877],"type":"Point"}
}