{
  "type": "Feature",
  "properties": {
    "iso:country":"BE",
    "sg:address":"Lipsestraat 93",
    "sg:city":"Haacht",
    "sg:orig_category":"Installation de menuiserie en bois and plastique",
    "sg:phone":"+32 16 60 10 59",
    "sg:postcode":"3150",
    "sg:province":"Vlaams-Brabant",
    "wof:name":"Wilfried Coppens",
    "wof:placetype":"venue"
},
  "geometry": {"coordinates":[4.6522431374,50.9381141663],"type":"Point"}
}