{
  "type": "Feature",
  "properties": {
    "iso:country":"BE",
    "sg:address":"Gewerbestrasse 17",
    "sg:city":"Eupen",
    "sg:classifiers":[
        {
            "category":"Airport",
            "subcategory":"International",
            "type":"Transportation"
        }
    ],
    "sg:phone":"+32 87 56 01 55",
    "sg:postcode":"4700",
    "sg:province":"Li\u00e8ge",
    "sg:tags":[
        "-",
        "transport"
    ],
    "wof:name":"Eurotraction International",
    "wof:placetype":"venue"
},
  "geometry": {"coordinates":[6.0118188858,50.6363296509],"type":"Point"}
}