{
  "type": "Feature",
  "properties": {
    "addr:full":"Rue Du Limbourg 27 Mouscron Hainaut 7700",
    "addr:housenumber":"27",
    "addr:postcode":"7700",
    "addr:street":"Rue Du Limbourg",
    "iso:country":"BE",
    "sg:address":"Rue Du Limbourg 27",
    "sg:city":"Mouscron",
    "sg:orig_category":"Non-Classified Establishments",
    "sg:phone":"+32 56 48 34 34",
    "sg:postcode":"7700",
    "sg:province":"Hainaut",
    "wof:name":"Tisserand (le)",
    "wof:placetype":"venue"
},
  "geometry": {"coordinates":[3.2216119766,50.7364311218],"type":"Point"}
}