{
  "type": "Feature",
  "properties": {
    "addr:full":"Rue Eug\u00e8ne Jehaes 4a Fl\u00e9ron Li\u00e8ge 4620",
    "addr:housenumber":"4a",
    "addr:postcode":"4620",
    "addr:street":"Rue Euge\u0300Ne Jehaes",
    "iso:country":"BE",
    "sg:address":"Rue Eug\u00e8ne Jehaes 4a",
    "sg:city":"Fl\u00e9ron",
    "sg:classifiers":[
        {
            "category":"Health Services",
            "subcategory":"Doctor",
            "type":"Services"
        }
    ],
    "sg:phone":"+32 4 358 54 28",
    "sg:postcode":"4620",
    "sg:province":"Li\u00e8ge",
    "sg:tags":[
        "medicinephysicians",
        "surgeon"
    ],
    "wof:name":"Bonaventure R",
    "wof:placetype":"venue"
},
  "geometry": {"coordinates":[5.6851091385,50.6141700745],"type":"Point"}
}