{
  "type": "Feature",
  "properties": {
    "iso:country":"BE",
    "sg:address":"Place D'outre-biesme 7",
    "sg:city":"Chatelet",
    "sg:orig_category":"Instituts de beaut\u00e9",
    "sg:phone":"+32 71 39 13 62",
    "sg:postcode":"6200",
    "sg:province":"Hainaut",
    "wof:name":"The Nail's Compagny",
    "wof:placetype":"venue"
},
  "geometry": {"coordinates":[4.5191302299,50.3955459595],"type":"Point"}
}