{
  "type": "Feature",
  "properties": {
    "iso:country":"BE",
    "sg:address":"Chee.de Roodebeek 25",
    "sg:city":"Woluwe",
    "sg:orig_category":"Packard Bell Nec. Entretien and r\u00e9parations de machines de bureau and ordinateurs",
    "sg:phone":"+32 2 772 38 15",
    "sg:postcode":"1200",
    "sg:province":"Bruxelles-Capitale",
    "wof:name":"Computer Square Technique",
    "wof:placetype":"venue"
},
  "geometry": {"coordinates":[4.4349751472,50.8482513428],"type":"Point"}
}