{
  "type": "Feature",
  "properties": {
    "addr:full":"Naamsesteenweg 537 Box 2 Leuven (heverlee) Vlaams-Brabant 3001",
    "addr:housenumber":"537;2",
    "addr:postcode":"3001",
    "addr:street":"Naamsesteenweg;Box",
    "iso:country":"BE",
    "sg:address":"Naamsesteenweg 537 Box 2",
    "sg:city":"Leuven (heverlee)",
    "sg:classifiers":[
        {
            "category":"Professional",
            "subcategory":"Management & Consulting",
            "type":"Services"
        }
    ],
    "sg:phone":"+32 16 40 04 43",
    "sg:postcode":"3001",
    "sg:province":"Vlaams-Brabant",
    "sg:tags":[
        "-",
        "processing",
        "data",
        "consultant"
    ],
    "wof:name":"M-services & Sales",
    "wof:placetype":"venue"
},
  "geometry": {"coordinates":[4.6957588196,50.8492927551],"type":"Point"}
}