{
  "type": "Feature",
  "properties": {
    "addr:full":"Rue De Vieille Esp\u00c9rance 120 Seraing Li\u00e8ge 4100",
    "addr:housenumber":"120",
    "addr:postcode":"4100",
    "addr:street":"Rue De Vieille Espe\u0301Rance",
    "iso:country":"BE",
    "sg:address":"Rue De Vieille Esp\u00c9rance 120",
    "sg:city":"Seraing",
    "sg:orig_category":"Entretien and r\u00e9parations de voitures",
    "sg:phone":"+32 4 336 64 73",
    "sg:postcode":"4100",
    "sg:province":"Li\u00e8ge",
    "wof:name":"Jean-marie Radoes",
    "wof:placetype":"venue"
},
  "geometry": {"coordinates":[5.5056171417,50.6028594971],"type":"Point"}
}