{
  "type": "Feature",
  "properties": {
    "addr:full":"Markgravenstraat 21 Herentals Antwerpen 2200",
    "addr:housenumber":"21",
    "addr:postcode":"2200",
    "addr:street":"Markgravenstraat",
    "iso:country":"BE",
    "sg:address":"Markgravenstraat 21",
    "sg:city":"Herentals",
    "sg:orig_category":"Kapsalons",
    "sg:phone":"+32 14 22 25 94",
    "sg:postcode":"2200",
    "sg:province":"Antwerpen",
    "wof:name":"Jean Hannes",
    "wof:placetype":"venue"
},
  "geometry": {"coordinates":[4.8252592087,51.1783409119],"type":"Point"}
}