{
  "type": "Feature",
  "properties": {
    "iso:country":"BE",
    "sg:address":"Beigemsesteenweg 301",
    "sg:city":"Grimbergen (beigem)",
    "sg:orig_category":"Matrices",
    "sg:phone":"+32 2 269 08 88",
    "sg:postcode":"1852",
    "sg:province":"Vlaams-Brabant",
    "wof:name":"E.o.c Normalien Belgium Nv",
    "wof:placetype":"venue"
},
  "geometry": {"coordinates":[4.3661198616,50.9520721436],"type":"Point"}
}