{
  "type": "Feature",
  "properties": {
    "iso:country":"BE",
    "sg:address":"Mechelbaan 551b9",
    "sg:city":"Putte",
    "sg:orig_category":"Groententeelt",
    "sg:phone":"+32 15 75 58 34",
    "sg:postcode":"2580",
    "sg:province":"Antwerpen",
    "wof:name":"Tomimex",
    "wof:placetype":"venue"
},
  "geometry": {"coordinates":[4.6259260178,51.0531997681],"type":"Point"}
}