{
  "type": "Feature",
  "properties": {
    "iso:country":"BE",
    "sg:address":"Bollestraat 96",
    "sg:city":"Torhout",
    "sg:classifiers":[
        {
            "category":"Personal",
            "subcategory":"Beauty Salon",
            "type":"Services"
        }
    ],
    "sg:phone":"+32 50 21 39 69",
    "sg:postcode":"8820",
    "sg:province":"West-Vlaanderen",
    "sg:tags":[
        "de",
        "coiffure"
    ],
    "wof:name":"Coiffure Levana",
    "wof:placetype":"venue"
},
  "geometry": {"coordinates":[3.1178200245,51.0476493835],"type":"Point"}
}