{
  "type": "Feature",
  "properties": {
    "iso:country":"BE",
    "sg:address":"Avenue De Stalingrad 24",
    "sg:city":"Brussel/bruxelles",
    "sg:orig_category":"Editeurs de revues and p\u00e9riodiques. Editeurs de journaux. Salles de spectacles",
    "sg:phone":"+32 2 513 96 02",
    "sg:postcode":"1000",
    "sg:province":"Bruxelles-Capitale",
    "wof:name":"C.b.a.i.",
    "wof:placetype":"venue"
},
  "geometry": {"coordinates":[4.3449821472,50.8418655396],"type":"Point"}
}