{
  "type": "Feature",
  "properties": {
    "addr:full":"Barri\u00e8re De Fer 75 Espierres-helchin (espierres) West-Vlaanderen 8587",
    "addr:housenumber":"75",
    "addr:postcode":"8587",
    "addr:street":"Barrie\u0300Re;Espierres-Helchin Espierres West-Vlaanderen",
    "iso:country":"BE",
    "sg:address":"Barri\u00e8re De Fer 75",
    "sg:city":"Espierres-helchin (espierres)",
    "sg:classifiers":[
        {
            "category":"Shopping",
            "subcategory":"Discount & Variety Stores",
            "type":"Retail Goods"
        }
    ],
    "sg:phone":"+32 56 20 65 85",
    "sg:postcode":"8587",
    "sg:province":"West-Vlaanderen",
    "sg:tags":[
        "shop",
        "clearers",
        "curiosity",
        "furniture"
    ],
    "wof:name":"Skippy",
    "wof:placetype":"venue"
},
  "geometry": {"coordinates":[3.3308999538,50.7245903015],"type":"Point"}
}