{
  "type": "Feature",
  "properties": {
    "iso:country":"BE",
    "sg:address":"Rue Rond Du Roi Albert 14",
    "sg:city":"Awans",
    "sg:orig_category":"Enseignement maternel and primaire",
    "sg:phone":"+32 4 257 63 14",
    "sg:postcode":"4340",
    "sg:province":"Li\u00e8ge",
    "wof:name":"Ecole Fondamentale Libre",
    "wof:placetype":"venue"
},
  "geometry": {"coordinates":[5.4387960434,50.704788208],"type":"Point"}
}