{
  "type": "Feature",
  "properties": {
    "iso:country":"BE",
    "sg:address":"Moerhuizestraat 76",
    "sg:city":"Maldegem",
    "sg:orig_category":"Rundveehouders Varkenskwekers",
    "sg:phone":"+32 50 71 32 01",
    "sg:postcode":"9990",
    "sg:province":"Oost-Vlaanderen",
    "wof:name":"Marcel Vandycke",
    "wof:placetype":"venue"
},
  "geometry": {"coordinates":[3.4765779972,51.2337493896],"type":"Point"}
}