{
  "type": "Feature",
  "properties": {
    "addr:full":"Avenue Beau S\u00e9jour 28 Bruxelles (uccle) Bruxelles-Capitale 1180",
    "addr:housenumber":"28",
    "addr:postcode":"1180",
    "addr:street":"Avenue Beau Se\u0301Jour",
    "iso:country":"BE",
    "sg:address":"Avenue Beau S\u00e9jour 28",
    "sg:city":"Bruxelles (uccle)",
    "sg:classifiers":[
        {
            "category":"Health Services",
            "subcategory":"Health Practitioner",
            "type":"Services"
        }
    ],
    "sg:phone":"+32 2 375 13 00",
    "sg:postcode":"1180",
    "sg:province":"Bruxelles-Capitale",
    "sg:tags":[
        "physiotherapist"
    ],
    "wof:name":"Boland V",
    "wof:placetype":"venue"
},
  "geometry": {"coordinates":[4.368847847,50.8091125488],"type":"Point"}
}