{
  "type": "Feature",
  "properties": {
    "addr:full":"Rommelsweg 14 Sint-laureins Oost-Vlaanderen 9980",
    "addr:housenumber":"14",
    "addr:postcode":"9980",
    "addr:street":"Rommelsweg",
    "iso:country":"BE",
    "sg:address":"Rommelsweg 14",
    "sg:city":"Sint-laureins",
    "sg:orig_category":"Openbare veiligheid",
    "sg:phone":"+32 9 379 84 17",
    "sg:postcode":"9980",
    "sg:province":"Oost-Vlaanderen",
    "wof:name":"Federale Politie",
    "wof:placetype":"venue"
},
  "geometry": {"coordinates":[3.5198779106,51.2396965027],"type":"Point"}
}