{
  "type": "Feature",
  "properties": {
    "iso:country":"BE",
    "sg:address":"Rue Des Rappes 15",
    "sg:city":"Etalle",
    "sg:orig_category":"Pain, p\u00e2tisseries and confiseries",
    "sg:phone":"+32 63 45 58 63",
    "sg:postcode":"6740",
    "sg:province":"Luxembourg",
    "wof:name":"Boulangerie Rion Servais",
    "wof:placetype":"venue"
},
  "geometry": {"coordinates":[5.5594348907,49.6661605835],"type":"Point"}
}