{
  "type": "Feature",
  "properties": {
    "addr:full":"Avenue Du Haras 100 Bruxelles (woluwe-saint-pierre) Bruxelles-Capitale 1150",
    "addr:housenumber":"100",
    "addr:postcode":"1150",
    "addr:street":"Avenue Du Haras",
    "iso:country":"BE",
    "sg:address":"Avenue Du Haras 100",
    "sg:city":"Bruxelles (woluwe-saint-pierre)",
    "sg:classifiers":[
        {
            "category":"Education",
            "subcategory":"Library",
            "type":"Public Place"
        }
    ],
    "sg:phone":"+32 2 773 59 70",
    "sg:postcode":"1150",
    "sg:province":"Bruxelles-Capitale",
    "wof:name":"Biblioth\u00e8que Publique De Joli-bois",
    "wof:placetype":"venue"
},
  "geometry": {"coordinates":[4.4601788521,50.8292541504],"type":"Point"}
}