{
  "type": "Feature",
  "properties": {
    "iso:country":"BE",
    "sg:address":"Rue Des D\u00c9port\u00c9s 9",
    "sg:city":"Antoing",
    "sg:classifiers":[
        {
            "category":"Insurance",
            "subcategory":"Life Insurance",
            "type":"Services"
        }
    ],
    "sg:phone":"+32 69 44 17 15",
    "sg:postcode":"7641",
    "sg:province":"Hainaut",
    "sg:tags":[
        "assurance"
    ],
    "wof:name":"M. Mespreuve",
    "wof:placetype":"venue"
},
  "geometry": {"coordinates":[3.4277689457,50.5557327271],"type":"Point"}
}