{
  "type": "Feature",
  "properties": {
    "addr:full":"Populierenlaan 51 Lanaken (rekem) Limburg 3621",
    "addr:housenumber":"51",
    "addr:postcode":"3621",
    "addr:street":"Populierenlaan",
    "iso:country":"BE",
    "sg:address":"Populierenlaan 51",
    "sg:city":"Lanaken (rekem)",
    "sg:classifiers":[
        {
            "category":"Autos & Motor Vehicles",
            "subcategory":"Recreational Vehicle Sales",
            "type":"Retail Goods"
        }
    ],
    "sg:phone":"+32 89 71 31 29",
    "sg:postcode":"3621",
    "sg:province":"Limburg",
    "sg:tags":[
        "saw"
    ],
    "wof:name":"Cardinaels Bvba",
    "wof:placetype":"venue"
},
  "geometry": {"coordinates":[5.692097187,50.922832489],"type":"Point"}
}