{
  "type": "Feature",
  "properties": {
    "addr:full":"Vorstse Steenweg 87 Sint-gillis/saint-gilles Bruxelles-Capitale 1060",
    "addr:housenumber":"87",
    "addr:postcode":"1060",
    "addr:street":"Vorstse Steenweg",
    "iso:country":"BE",
    "sg:address":"Vorstse Steenweg 87",
    "sg:city":"Sint-gillis/saint-gilles",
    "sg:orig_category":"Artsen and specialisten",
    "sg:phone":"+32 2 539 28 79",
    "sg:postcode":"1060",
    "sg:province":"Bruxelles-Capitale",
    "wof:name":"Nordin Za\u00cfdi",
    "wof:placetype":"venue"
},
  "geometry": {"coordinates":[4.339056015,50.8311386108],"type":"Point"}
}