{
  "type": "Feature",
  "properties": {
    "addr:full":"Rijmsnoerstraat 44 Kortrijk (bissegem) West-Vlaanderen 8501",
    "addr:housenumber":"44",
    "addr:postcode":"8501",
    "addr:street":"Rijmsnoerstraat",
    "iso:country":"BE",
    "sg:address":"Rijmsnoerstraat 44",
    "sg:city":"Kortrijk (bissegem)",
    "sg:classifiers":[
        {
            "category":"Utilities",
            "subcategory":"Fuel Oil & Lpg",
            "type":"Services"
        }
    ],
    "sg:phone":"+32 56 35 41 99",
    "sg:postcode":"8501",
    "sg:province":"West-Vlaanderen",
    "wof:name":"Lapiere I",
    "wof:placetype":"venue"
},
  "geometry": {"coordinates":[3.2246630192,50.8268852234],"type":"Point"}
}