{
  "type": "Feature",
  "properties": {
    "addr:full":"Rue L\u00e9opold 35 Li\u00e8ge 1 Li\u00e8ge 4000",
    "addr:housenumber":"35;1",
    "addr:postcode":"4000",
    "addr:street":"Rue Le\u0301Opold",
    "iso:country":"BE",
    "sg:address":"Rue L\u00e9opold 35",
    "sg:city":"Li\u00e8ge 1",
    "sg:classifiers":[
        {
            "category":"Shopping",
            "subcategory":"Clothing, Apparel, & Fashions",
            "type":"Retail Goods"
        }
    ],
    "sg:phone":"+32 4 223 35 66",
    "sg:postcode":"4000",
    "sg:province":"Li\u00e8ge",
    "sg:tags":[
        "clothing",
        "-",
        "gentleman"
    ],
    "wof:name":"Maison Francaise",
    "wof:placetype":"venue"
},
  "geometry": {"coordinates":[5.5771260262,50.6442222595],"type":"Point"}
}