{
  "type": "Feature",
  "properties": {
    "iso:country":"BE",
    "sg:address":"Stationsstraat 7",
    "sg:city":"Deinze",
    "sg:orig_category":"Parfumeries. Centres de relaxation and bien-\u00eatre. Souvenirs and objets artisanaux",
    "sg:phone":"+32 9 386 18 82",
    "sg:postcode":"9800",
    "sg:province":"Oost-Vlaanderen",
    "wof:name":"Parfumerie Decaluwe",
    "wof:placetype":"venue"
},
  "geometry": {"coordinates":[3.5310370922,50.9788589478],"type":"Point"}
}