{
  "type": "Feature",
  "properties": {
    "iso:country":"BE",
    "sg:address":"Ovenstraat 6",
    "sg:city":"Roeselare",
    "sg:classifiers":[
        {
            "category":"Manufacturing",
            "subcategory":"Metals",
            "type":"Manufacturing & Wholesale Goods"
        }
    ],
    "sg:phone":"+32 51 22 31 31",
    "sg:postcode":"8800",
    "sg:province":"West-Vlaanderen",
    "sg:tags":[
        "steel",
        "stainless"
    ],
    "wof:name":"Cd Constructs Bvba",
    "wof:placetype":"venue"
},
  "geometry": {"coordinates":[3.0981938839,50.9483337402],"type":"Point"}
}