{
  "type": "Feature",
  "properties": {
    "iso:country":"BE",
    "sg:address":"Otegemstraat 269",
    "sg:city":"Zwevegem",
    "sg:orig_category":"Studios photographiques. Equipement photographique",
    "sg:phone":"+32 56 75 65 95",
    "sg:postcode":"8550",
    "sg:province":"West-Vlaanderen",
    "wof:name":"Odo Van Meenen",
    "wof:placetype":"venue"
},
  "geometry": {"coordinates":[3.3507020473,50.8167457581],"type":"Point"}
}