{
  "type": "Feature",
  "properties": {
    "addr:full":"Hotelstraat 1 Overpelt Limburg 3900",
    "addr:housenumber":"1",
    "addr:postcode":"3900",
    "addr:street":"Hotelstraat",
    "iso:country":"BE",
    "sg:address":"Hotelstraat 1",
    "sg:city":"Overpelt",
    "sg:orig_category":"Installation de menuiserie en bois and plastique",
    "sg:phone":"+32 11 66 47 92",
    "sg:postcode":"3900",
    "sg:province":"Limburg",
    "wof:name":"Cox F",
    "wof:placetype":"venue"
},
  "geometry": {"coordinates":[5.3956961632,51.2334327698],"type":"Point"}
}