{
  "type": "Feature",
  "properties": {
    "addr:full":"Populierenstraat 57 Houthalen-helchteren (houthalen) Limburg 3530",
    "addr:housenumber":"57",
    "addr:postcode":"3530",
    "addr:street":"Populierenstraat",
    "iso:country":"BE",
    "sg:address":"Populierenstraat 57",
    "sg:city":"Houthalen-helchteren (houthalen)",
    "sg:classifiers":[
        {
            "category":"Food & Beverages",
            "subcategory":"Groceries & Convenience Stores",
            "type":"Retail Goods"
        }
    ],
    "sg:phone":"+32 89 38 33 81",
    "sg:postcode":"3530",
    "sg:province":"Limburg",
    "sg:tags":[
        "grocer"
    ],
    "wof:name":"Hebda V",
    "wof:placetype":"venue"
},
  "geometry": {"coordinates":[5.4695267677,51.0198860168],"type":"Point"}
}