{
  "type": "Feature",
  "properties": {
    "addr:full":"Rue Mottiaux 77 Namur (jambes) Namur 5100",
    "addr:housenumber":"77",
    "addr:postcode":"5100",
    "addr:street":"Rue Mottiaux",
    "iso:country":"BE",
    "sg:address":"Rue Mottiaux 77",
    "sg:city":"Namur (jambes)",
    "sg:classifiers":[
        {
            "category":"Insurance",
            "subcategory":"Insurance Agent",
            "type":"Services"
        }
    ],
    "sg:phone":"+32 81 30 72 32",
    "sg:postcode":"5100",
    "sg:province":"Namur",
    "sg:tags":[
        "broker"
    ],
    "wof:name":"La Maison De L'assurance Sa",
    "wof:placetype":"venue"
},
  "geometry": {"coordinates":[4.8713750839,50.4566345215],"type":"Point"}
}