{
  "type": "Feature",
  "properties": {
    "addr:full":"Zandstraat 50 Mol Antwerpen 2400",
    "addr:housenumber":"50",
    "addr:postcode":"2400",
    "addr:street":"Zandstraat",
    "iso:country":"BE",
    "sg:address":"Zandstraat 50",
    "sg:city":"Mol",
    "sg:classifiers":[
        {
            "category":"Building & Trades",
            "subcategory":"Pest Control",
            "type":"Services"
        }
    ],
    "sg:phone":"+32 14 81 10 13",
    "sg:postcode":"2400",
    "sg:province":"Antwerpen",
    "sg:tags":[
        "painting",
        "contractor"
    ],
    "wof:name":"Maes Bvba",
    "wof:placetype":"venue"
},
  "geometry": {"coordinates":[5.2021541595,51.2214431763],"type":"Point"}
}