{
  "type": "Feature",
  "properties": {
    "addr:full":"Parkwijk 23 Nazareth Oost-Vlaanderen 9810",
    "addr:housenumber":"23",
    "addr:postcode":"9810",
    "addr:street":"Parkwijk",
    "iso:country":"BE",
    "sg:address":"Parkwijk 23",
    "sg:city":"Nazareth",
    "sg:orig_category":"Catering and organisatie van feesten",
    "sg:phone":"+32 9 385 57 97",
    "sg:postcode":"9810",
    "sg:province":"Oost-Vlaanderen",
    "wof:name":"Traiteur Passe-partout",
    "wof:placetype":"venue"
},
  "geometry": {"coordinates":[3.6334130764,50.9612350464],"type":"Point"}
}