{
  "type": "Feature",
  "properties": {
    "iso:country":"BE",
    "sg:address":"Rue Rouffa 68",
    "sg:city":"Fl\u00c9malle",
    "sg:orig_category":"Installation de menuiserie en bois and plastique",
    "sg:phone":"+32 4 337 06 68",
    "sg:postcode":"4400",
    "sg:province":"Li\u00e8ge",
    "wof:name":"G. Dardenne",
    "wof:placetype":"venue"
},
  "geometry": {"coordinates":[5.4576430321,50.5693130493],"type":"Point"}
}