{
  "type": "Feature",
  "properties": {
    "addr:full":"Avenue De Beaufort 28 Box A Huy (ben-ahin) Li\u00e8ge 4500",
    "addr:housenumber":"28",
    "addr:postcode":"4500",
    "addr:street":"Avenue De Beaufort;A",
    "iso:country":"BE",
    "sg:address":"Avenue De Beaufort 28 Box A",
    "sg:city":"Huy (ben-ahin)",
    "sg:classifiers":[
        {
            "category":"Professional",
            "subcategory":"Lawyer & Legal Services",
            "type":"Services"
        }
    ],
    "sg:phone":"+32 85 25 49 21",
    "sg:postcode":"4500",
    "sg:province":"Li\u00e8ge",
    "wof:name":"Pierre Sandra",
    "wof:placetype":"venue"
},
  "geometry": {"coordinates":[5.2400307655,50.5178337097],"type":"Point"}
}