{
  "type": "Feature",
  "properties": {
    "iso:country":"BE",
    "sg:address":"Overdemerstraat 24",
    "sg:city":"Hasselt",
    "sg:classifiers":[
        {
            "category":"Cafe",
            "type":"Food & Drink"
        }
    ],
    "sg:phone":"+32 11 25 40 30",
    "sg:postcode":"3511",
    "sg:province":"Limburg",
    "sg:tags":[
        "caf\u00e9s"
    ],
    "wof:name":"Caf\u00c9 't Squadenhof",
    "wof:placetype":"venue"
},
  "geometry": {"coordinates":[5.3087739944,50.9472999573],"type":"Point"}
}