{
  "type": "Feature",
  "properties": {
    "iso:country":"BE",
    "sg:address":"Schellekensberg 27",
    "sg:city":"Diest",
    "sg:orig_category":"Schoenen Sport- and kampeermateriaal",
    "sg:phone":"+32 13 32 10 92",
    "sg:postcode":"3290",
    "sg:province":"Vlaams-Brabant",
    "wof:name":"Huis Versaevel Sport",
    "wof:placetype":"venue"
},
  "geometry": {"coordinates":[5.1074428558,51.0184173584],"type":"Point"}
}