{
  "type": "Feature",
  "properties": {
    "iso:country":"BE",
    "sg:address":"Henri Christiaenlaan 20",
    "sg:city":"Koksijde",
    "sg:orig_category":"Slagers",
    "sg:phone":"+32 58 51 13 57",
    "sg:postcode":"8670",
    "sg:province":"West-Vlaanderen",
    "wof:name":"Patrick Maes",
    "wof:placetype":"venue"
},
  "geometry": {"coordinates":[2.6120009422,51.1097984314],"type":"Point"}
}