{
  "type": "Feature",
  "properties": {
    "iso:country":"BE",
    "sg:address":"De Wandstraat 18",
    "sg:city":"Brussel (brussel)",
    "sg:orig_category":"Slagers",
    "sg:phone":"+32 2 268 70 90",
    "sg:postcode":"1020",
    "sg:province":"Bruxelles-Capitale",
    "wof:name":"Delicatessen Bassens",
    "wof:placetype":"venue"
},
  "geometry": {"coordinates":[4.3577990532,50.8964538574],"type":"Point"}
}