{
  "type": "Feature",
  "properties": {
    "addr:full":"Handelsstraat 18 Veurne (steenkerke) West-Vlaanderen 8630",
    "addr:housenumber":"18",
    "addr:postcode":"8630",
    "addr:street":"Handelsstraat",
    "iso:country":"BE",
    "sg:address":"Handelsstraat 18",
    "sg:city":"Veurne (steenkerke)",
    "sg:orig_category":"Non-Classified Establishments",
    "sg:phone":"+32 58 31 50 31",
    "sg:postcode":"8630",
    "sg:province":"West-Vlaanderen",
    "wof:name":"Sobry",
    "wof:placetype":"venue"
},
  "geometry": {"coordinates":[2.6852200031,51.0669136047],"type":"Point"}
}