{
  "type": "Feature",
  "properties": {
    "iso:country":"BE",
    "sg:address":"Beeldhouwersstraat 12",
    "sg:city":"Antwerpen",
    "sg:classifiers":[
        {
            "category":"Professional",
            "subcategory":"Management & Consulting",
            "type":"Services"
        }
    ],
    "sg:phone":"+32 3 238 20 67",
    "sg:postcode":"2000",
    "sg:province":"Antwerpen",
    "sg:tags":[
        "marketing",
        "-",
        "consultant"
    ],
    "wof:name":"No Nonsense Marketing Bvba",
    "wof:placetype":"venue"
},
  "geometry": {"coordinates":[4.3933978081,51.208152771],"type":"Point"}
}