{
  "type": "Feature",
  "properties": {
    "addr:full":"Essendries 12b Puurs Antwerpen 2870",
    "addr:housenumber":"12b",
    "addr:postcode":"2870",
    "addr:street":"Essendries",
    "iso:country":"BE",
    "sg:address":"Essendries 12b",
    "sg:city":"Puurs",
    "sg:classifiers":[
        {
            "category":"Sports & Exercise",
            "subcategory":"Stables",
            "type":"Entertainment"
        }
    ],
    "sg:phone":"+32 3 889 43 68",
    "sg:postcode":"2870",
    "sg:province":"Antwerpen",
    "sg:tags":[
        "riding",
        "school"
    ],
    "wof:name":"Van Ingelgem S Bvba",
    "wof:placetype":"venue"
},
  "geometry": {"coordinates":[4.2954487801,51.0600357056],"type":"Point"}
}