{
  "type": "Feature",
  "properties": {
    "iso:country":"BE",
    "sg:address":"Universiteitslaan 1",
    "sg:city":"Hasselt",
    "sg:classifiers":[
        {
            "category":"Organizations",
            "subcategory":"Community Association",
            "type":"Services"
        }
    ],
    "sg:phone":"+32 11 23 75 12",
    "sg:postcode":"3500",
    "sg:province":"Limburg",
    "sg:tags":[
        "cultural"
    ],
    "wof:name":"Provincie Limburg Cultuur",
    "wof:placetype":"venue"
},
  "geometry": {"coordinates":[5.3632459641,50.9311904907],"type":"Point"}
}