{
  "type": "Feature",
  "properties": {
    "addr:full":"Kerrebroek 4 Nevele Oost-Vlaanderen 9850",
    "addr:housenumber":"4",
    "addr:postcode":"9850",
    "addr:street":"Kerrebroek",
    "iso:country":"BE",
    "sg:address":"Kerrebroek 4",
    "sg:city":"Nevele",
    "sg:classifiers":[
        {
            "category":"Insurance",
            "subcategory":"Insurance Agent",
            "type":"Services"
        }
    ],
    "sg:phone":"+32 9 371 51 92",
    "sg:postcode":"9850",
    "sg:province":"Oost-Vlaanderen",
    "sg:tags":[
        "-",
        "representative"
    ],
    "wof:name":"De Smet J",
    "wof:placetype":"venue"
},
  "geometry": {"coordinates":[3.544919014,51.0316047668],"type":"Point"}
}