{
  "type": "Feature",
  "properties": {
    "iso:country":"BE",
    "sg:address":"Gasthuisstraat 24",
    "sg:city":"Brecht",
    "sg:orig_category":"Brood, gebak and snoepgoed Verlichting and huishoudartikelen",
    "sg:phone":"+32 3 313 75 80",
    "sg:postcode":"2960",
    "sg:province":"Antwerpen",
    "wof:name":"Kristel Geerts",
    "wof:placetype":"venue"
},
  "geometry": {"coordinates":[4.6395831108,51.3502426147],"type":"Point"}
}