{
  "type": "Feature",
  "properties": {
    "iso:country":"BE",
    "sg:address":"Hendrik Schoofsstraat 6",
    "sg:city":"Brecht",
    "sg:classifiers":[
        {
            "category":"Restaurant",
            "type":"Food & Drink"
        }
    ],
    "sg:phone":"+32 3 290 06 56",
    "sg:postcode":"2960",
    "sg:province":"Antwerpen",
    "wof:name":"De Schandpael",
    "wof:placetype":"venue"
},
  "geometry": {"coordinates":[4.643599987,51.3492622375],"type":"Point"}
}