{
  "type": "Feature",
  "properties": {
    "iso:country":"BE",
    "sg:address":"Montenakenweg 32",
    "sg:city":"Sint-truiden",
    "sg:classifiers":[
        {
            "category":"Building & Trades",
            "subcategory":"Pest Control",
            "type":"Services"
        }
    ],
    "sg:phone":"+32 11 68 48 20",
    "sg:postcode":"3800",
    "sg:province":"Limburg",
    "sg:tags":[
        "painting",
        "contractor"
    ],
    "wof:name":"Vanzeer & Zn Nv",
    "wof:placetype":"venue"
},
  "geometry": {"coordinates":[5.1798272133,50.8146781921],"type":"Point"}
}