{
  "type": "Feature",
  "properties": {
    "iso:country":"BE",
    "sg:address":"Lieven Heerstraat 64",
    "sg:city":"Mol",
    "sg:orig_category":"Brood, gebak and snoepgoed",
    "sg:phone":"+32 14 37 80 82",
    "sg:postcode":"2400",
    "sg:province":"Antwerpen",
    "wof:name":"Erik Vanwaelderen",
    "wof:placetype":"venue"
},
  "geometry": {"coordinates":[5.1314377785,51.1808166504],"type":"Point"}
}