{
  "type": "Feature",
  "properties": {
    "addr:full":"Seppendijk 27 Geel Antwerpen 2440",
    "addr:housenumber":"27",
    "addr:postcode":"2440",
    "addr:street":"Seppendijk",
    "iso:country":"BE",
    "sg:address":"Seppendijk 27",
    "sg:city":"Geel",
    "sg:orig_category":"Rev\u00eatements de sols and murs. Travaux de pl\u00e2trage",
    "sg:phone":"+32 14 58 32 66",
    "sg:postcode":"2440",
    "sg:province":"Antwerpen",
    "wof:name":"Polidur",
    "wof:placetype":"venue"
},
  "geometry": {"coordinates":[4.9988408089,51.1484832764],"type":"Point"}
}