{
  "type": "Feature",
  "properties": {
    "iso:country":"BE",
    "sg:address":"Heikant 76",
    "sg:city":"Heusden-zolder (zolder)",
    "sg:classifiers":[
        {
            "category":"Personal",
            "subcategory":"Beauty Salon",
            "type":"Services"
        }
    ],
    "sg:phone":"+32 11 52 68 80",
    "sg:postcode":"3550",
    "sg:province":"Limburg",
    "wof:name":"Gently",
    "wof:placetype":"venue"
},
  "geometry": {"coordinates":[5.2974920273,51.0147895813],"type":"Point"}
}