{
  "type": "Feature",
  "properties": {
    "iso:country":"BE",
    "sg:address":"Stokthoekstraat 18",
    "sg:city":"Temse (elversele)",
    "sg:classifiers":[
        {
            "category":"Building & Trades",
            "subcategory":"Construction",
            "type":"Services"
        }
    ],
    "sg:phone":"+32 52 46 36 22",
    "sg:postcode":"9140",
    "sg:province":"Oost-Vlaanderen",
    "sg:tags":[
        "glazier"
    ],
    "wof:name":"Glas Ateljee",
    "wof:placetype":"venue"
},
  "geometry": {"coordinates":[4.1328821182,51.1270484924],"type":"Point"}
}