{
  "type": "Feature",
  "properties": {
    "addr:full":"Zeedijk 146 Oostende West-Vlaanderen 8400",
    "addr:housenumber":"146",
    "addr:postcode":"8400",
    "addr:street":"Zeedijk",
    "iso:country":"BE",
    "sg:address":"Zeedijk 146",
    "sg:city":"Oostende",
    "sg:classifiers":[
        {
            "category":"Real Estate",
            "subcategory":"Real Estate Services",
            "type":"Services"
        }
    ],
    "sg:phone":"+32 59 80 86 02",
    "sg:postcode":"8400",
    "sg:province":"West-Vlaanderen",
    "wof:name":"Beh.imm.exp.",
    "wof:placetype":"venue"
},
  "geometry": {"coordinates":[2.8583700657,51.2067070007],"type":"Point"}
}