{
  "type": "Feature",
  "properties": {
    "addr:full":"Leliestraat 93 Denderleeuw Oost-Vlaanderen 9472",
    "addr:housenumber":"93",
    "addr:postcode":"9472",
    "addr:street":"Leliestraat",
    "iso:country":"BE",
    "sg:address":"Leliestraat 93",
    "sg:city":"Denderleeuw",
    "sg:orig_category":"Enseignement maternel and primaire",
    "sg:phone":"+32 53 66 72 47",
    "sg:postcode":"9472",
    "sg:province":"Oost-Vlaanderen",
    "wof:name":"Gemeentelijke Basisschool",
    "wof:placetype":"venue"
},
  "geometry": {"coordinates":[4.0448198318,50.8732185364],"type":"Point"}
}