{
  "type": "Feature",
  "properties": {
    "iso:country":"BE",
    "sg:address":"Avenue Du Bois Jacquet 3 Zi Barriere De Fer",
    "sg:city":"Dottignies",
    "sg:classifiers":[
        {
            "category":"Manufacturing",
            "subcategory":"Chemicals & Compounds",
            "type":"Manufacturing & Wholesale Goods"
        }
    ],
    "sg:phone":"+32 56 48 91 64",
    "sg:postcode":"7711",
    "sg:province":"Hainaut",
    "sg:tags":[
        "pharmaceutical",
        "chemistry"
    ],
    "wof:name":"Tikom Nv",
    "wof:placetype":"venue"
},
  "geometry": {"coordinates":[3.3080399036,50.7282752991],"type":"Point"}
}