{
  "type": "Feature",
  "properties": {
    "iso:country":"BE",
    "sg:address":"Kapelstraat 51",
    "sg:city":"Knesselare",
    "sg:orig_category":"Bouwmaterialen Gh Installatie van metalen schrijnwerk",
    "sg:phone":"+32 9 374 16 37",
    "sg:postcode":"9910",
    "sg:province":"Oost-Vlaanderen",
    "wof:name":"K.w.r.",
    "wof:placetype":"venue"
},
  "geometry": {"coordinates":[3.4281840324,51.1232299805],"type":"Point"}
}