{
  "type": "Feature",
  "properties": {
    "addr:full":"Barletegemweg 11 Jabbeke West-Vlaanderen 8490",
    "addr:housenumber":"11",
    "addr:postcode":"8490",
    "addr:street":"Barletegemweg",
    "iso:country":"BE",
    "sg:address":"Barletegemweg 11",
    "sg:city":"Jabbeke",
    "sg:orig_category":"Producteurs de l\u00e9gumes",
    "sg:phone":"+32 50 81 41 35",
    "sg:postcode":"8490",
    "sg:province":"West-Vlaanderen",
    "wof:name":"Hein Claeys",
    "wof:placetype":"venue"
},
  "geometry": {"coordinates":[3.0764911175,51.1475143433],"type":"Point"}
}