{
  "type": "Feature",
  "properties": {
    "addr:full":"Sint-jansstraat 23 Hoegaarden Vlaams-Brabant 3320",
    "addr:housenumber":"23",
    "addr:postcode":"3320",
    "addr:street":"Sint-Jansstraat",
    "iso:country":"BE",
    "sg:address":"Sint-jansstraat 23",
    "sg:city":"Hoegaarden",
    "sg:orig_category":"Restaurants Ruimtes voor conferenties, recepties and feesten",
    "sg:phone":"+32 16 81 54 28",
    "sg:postcode":"3320",
    "sg:province":"Vlaams-Brabant",
    "wof:name":"De Waterval",
    "wof:placetype":"venue"
},
  "geometry": {"coordinates":[4.873529911,50.8025131226],"type":"Point"}
}