{
  "type": "Feature",
  "properties": {
    "addr:full":"Nieuwbaan 45 Grobbendonk Antwerpen 2288",
    "addr:housenumber":"45",
    "addr:postcode":"2288",
    "addr:street":"Nieuwbaan",
    "iso:country":"BE",
    "sg:address":"Nieuwbaan 45",
    "sg:city":"Grobbendonk",
    "sg:classifiers":[
        {
            "category":"Shopping",
            "subcategory":"Jewelry",
            "type":"Retail Goods"
        }
    ],
    "sg:phone":"+32 14 51 70 97",
    "sg:postcode":"2288",
    "sg:province":"Antwerpen",
    "sg:tags":[
        "fab",
        "bijou"
    ],
    "wof:name":"Walter Van Doninck",
    "wof:placetype":"venue"
},
  "geometry": {"coordinates":[4.7379097939,51.167678833],"type":"Point"}
}