{
  "type": "Feature",
  "properties": {
    "addr:full":"Rue De La Collectivit\u00c9 76 Saint-nicolas Li\u00e8ge 4420",
    "addr:housenumber":"76",
    "addr:postcode":"4420",
    "addr:street":"Rue De La Collectivite\u0301",
    "iso:country":"BE",
    "sg:address":"Rue De La Collectivit\u00c9 76",
    "sg:city":"Saint-nicolas",
    "sg:orig_category":"Advocaten and juridische adviseurs",
    "sg:phone":"+32 4 226 83 22",
    "sg:postcode":"4420",
    "sg:province":"Li\u00e8ge",
    "wof:name":"Bruno Philips",
    "wof:placetype":"venue"
},
  "geometry": {"coordinates":[5.5309739113,50.6384010315],"type":"Point"}
}