{
  "type": "Feature",
  "properties": {
    "addr:full":"Rue Tierne Carion 38 Colfontaine Hainaut 7340",
    "addr:housenumber":"38",
    "addr:postcode":"7340",
    "addr:street":"Rue Tierne Carion",
    "iso:country":"BE",
    "sg:address":"Rue Tierne Carion 38",
    "sg:city":"Colfontaine",
    "sg:classifiers":[
        {
            "category":"Arena",
            "subcategory":"Sports Club",
            "type":"Entertainment"
        }
    ],
    "sg:phone":"+32 65 66 77 86",
    "sg:postcode":"7340",
    "sg:province":"Hainaut",
    "sg:tags":[
        "de"
    ],
    "wof:name":"J.c. Blaregnies",
    "wof:placetype":"venue"
},
  "geometry": {"coordinates":[3.8408460617,50.4090042114],"type":"Point"}
}