{
  "type": "Feature",
  "properties": {
    "addr:full":"Rue De Hauster 9 Chaudfontaine (vaux-sous-ch\u00e8vremont) Li\u00e8ge 4051",
    "addr:housenumber":"9",
    "addr:postcode":"4051",
    "addr:street":"Rue De Hauster",
    "iso:country":"BE",
    "sg:address":"Rue De Hauster 9",
    "sg:city":"Chaudfontaine (vaux-sous-ch\u00e8vremont)",
    "sg:classifiers":[
        {
            "category":"Travel",
            "subcategory":"Resort",
            "type":"Entertainment"
        }
    ],
    "sg:phone":"+32 4 367 80 67",
    "sg:postcode":"4051",
    "sg:province":"Li\u00e8ge",
    "sg:tags":[
        "health"
    ],
    "wof:name":"Chateau Des Thermes Sprl",
    "wof:placetype":"venue"
},
  "geometry": {"coordinates":[5.6312727928,50.5908546448],"type":"Point"}
}