{
  "type": "Feature",
  "properties": {
    "iso:country":"BE",
    "sg:address":"Avenue Du Maelbeek 7",
    "sg:city":"Brussel/bruxelles",
    "sg:orig_category":"M\u00e9decins and sp\u00e9cialistes",
    "sg:phone":"+32 2 230 60 05",
    "sg:postcode":"1000",
    "sg:province":"Bruxelles-Capitale",
    "wof:name":"Claude Descamps",
    "wof:placetype":"venue"
},
  "geometry": {"coordinates":[4.3803048134,50.8376274109],"type":"Point"}
}