{
  "type": "Feature",
  "properties": {
    "addr:full":"Heivelden 25 Wuustwezel Antwerpen 2990",
    "addr:housenumber":"25",
    "addr:postcode":"2990",
    "addr:street":"Heivelden",
    "iso:country":"BE",
    "sg:address":"Heivelden 25",
    "sg:city":"Wuustwezel",
    "sg:orig_category":"Eleveurs and marchands de porcs",
    "sg:phone":"+32 3 669 62 46",
    "sg:postcode":"2990",
    "sg:province":"Antwerpen",
    "wof:name":"Van Gastel Marc",
    "wof:placetype":"venue"
},
  "geometry": {"coordinates":[4.6052589417,51.4265441895],"type":"Point"}
}