{
  "type": "Feature",
  "properties": {
    "addr:full":"Mechelsesteenweg 240 Zaventem Vlaams-Brabant 1933",
    "addr:housenumber":"240",
    "addr:postcode":"1933",
    "addr:street":"Mechelsesteenweg",
    "iso:country":"BE",
    "sg:address":"Mechelsesteenweg 240",
    "sg:city":"Zaventem",
    "sg:orig_category":"Epiceries",
    "sg:phone":"+32 2 731 23 74",
    "sg:postcode":"1933",
    "sg:province":"Vlaams-Brabant",
    "wof:name":"Marie-rose Vanhole",
    "wof:placetype":"venue"
},
  "geometry": {"coordinates":[4.5153708458,50.8628082275],"type":"Point"}
}