{
  "type": "Feature",
  "properties": {
    "addr:full":"Avenue Du Parc 35 Bruxelles (saint-gilles) Bruxelles-Capitale 1060",
    "addr:housenumber":"35",
    "addr:postcode":"1060",
    "addr:street":"Avenue Du Parc",
    "iso:country":"BE",
    "sg:address":"Avenue Du Parc 35",
    "sg:city":"Bruxelles (saint-gilles)",
    "sg:classifiers":[
        {
            "category":"Professional",
            "subcategory":"Lawyer & Legal Services",
            "type":"Services"
        }
    ],
    "sg:phone":"+32 2 538 01 22",
    "sg:postcode":"1060",
    "sg:province":"Bruxelles-Capitale",
    "wof:name":"Pegorer Jean-jacques",
    "wof:placetype":"venue"
},
  "geometry": {"coordinates":[4.341137886,50.8262443542],"type":"Point"}
}