{
  "type": "Feature",
  "properties": {
    "addr:full":"Poti\u00c9rue 29 Herve Li\u00e8ge 4650",
    "addr:housenumber":"29",
    "addr:postcode":"4650",
    "addr:street":"Potie\u0301Rue",
    "iso:country":"BE",
    "sg:address":"Poti\u00c9rue 29",
    "sg:city":"Herve",
    "sg:orig_category":"Pharmaciens",
    "sg:phone":"+32 87 67 44 43",
    "sg:postcode":"4650",
    "sg:province":"Li\u00e8ge",
    "wof:name":"Pharmacie Geron",
    "wof:placetype":"venue"
},
  "geometry": {"coordinates":[5.7941570282,50.6401329041],"type":"Point"}
}