{
  "type": "Feature",
  "properties": {
    "iso:country":"BE",
    "sg:address":"Rue Basse Cour 46",
    "sg:city":"Lessines",
    "sg:orig_category":"Kapsalons",
    "sg:phone":"+32 68 33 35 44",
    "sg:postcode":"7866",
    "sg:province":"Hainaut",
    "wof:name":"Coiffure Mich\u00c8le",
    "wof:placetype":"venue"
},
  "geometry": {"coordinates":[3.8547549248,50.693271637],"type":"Point"}
}