{
  "type": "Feature",
  "properties": {
    "iso:country":"BE",
    "sg:address":"Statiewegel 2",
    "sg:city":"Dendermonde",
    "sg:orig_category":"Boucheries",
    "sg:phone":"+32 52 42 37 84",
    "sg:postcode":"9200",
    "sg:province":"Oost-Vlaanderen",
    "wof:name":"R. Eeckhoudt",
    "wof:placetype":"venue"
},
  "geometry": {"coordinates":[4.0114841461,51.0035552979],"type":"Point"}
}