{
  "type": "Feature",
  "properties": {
    "addr:full":"Place Saint-lazare 1 Sint-joost-ten-node/saint-joss Bruxelles-Capitale 1210",
    "addr:housenumber":"1",
    "addr:postcode":"1210",
    "addr:street":"Place Saint-Lazare",
    "iso:country":"BE",
    "sg:address":"Place Saint-lazare 1",
    "sg:city":"Sint-joost-ten-node/saint-joss",
    "sg:orig_category":"Entretien and r\u00e9parations de voitures. D\u00e9taillants en pi\u00e8ces and accessoires de voitures",
    "sg:phone":"+32 2 217 09 55",
    "sg:postcode":"1210",
    "sg:province":"Bruxelles-Capitale",
    "wof:name":"Speedy",
    "wof:placetype":"venue"
},
  "geometry": {"coordinates":[4.3695149422,50.8509941101],"type":"Point"}
}