{
  "type": "Feature",
  "properties": {
    "addr:full":"Chauss\u00c9e De March\u00c9 511 Namur Namur 5101",
    "addr:housenumber":"511",
    "addr:postcode":"5101",
    "addr:street":"Chausse\u0301E De Marche\u0301",
    "iso:country":"BE",
    "sg:address":"Chauss\u00c9e De March\u00c9 511",
    "sg:city":"Namur",
    "sg:orig_category":"Recouvrement de factures and \u00e9valuation de solvabilit\u00e9",
    "sg:phone":"+32 81 30 12 58",
    "sg:postcode":"5101",
    "sg:province":"Namur",
    "wof:name":"Fiduciaire Du Sud-fidusud",
    "wof:placetype":"venue"
},
  "geometry": {"coordinates":[4.9014492035,50.4444847107],"type":"Point"}
}