{
  "type": "Feature",
  "properties": {
    "addr:full":"Avenue Des Traquets 148 Sint-pieters-woluwe/woluwe-saint-pierre Bruxelles-Capitale 1150",
    "addr:housenumber":"148",
    "addr:postcode":"1150",
    "addr:street":"Avenue Des Traquets;/",
    "iso:country":"BE",
    "sg:address":"Avenue Des Traquets 148",
    "sg:city":"Sint-pieters-woluwe/woluwe-saint-pierre",
    "sg:orig_category":"Imprimeries and copyshops",
    "sg:phone":"+32 2 672 26 46",
    "sg:postcode":"1150",
    "sg:province":"Bruxelles-Capitale",
    "wof:name":"Bureau 13",
    "wof:placetype":"venue"
},
  "geometry": {"coordinates":[4.4202699661,50.8222770691],"type":"Point"}
}