{
  "type": "Feature",
  "properties": {
    "iso:country":"BE",
    "sg:address":"Lammerendries 13",
    "sg:city":"Oudergem/auderghem",
    "sg:orig_category":"Woningbouw",
    "sg:phone":"+32 2 673 72 34",
    "sg:postcode":"1160",
    "sg:province":"Bruxelles-Capitale",
    "wof:name":"Garcia",
    "wof:placetype":"venue"
},
  "geometry": {"coordinates":[4.4223380089,50.8110275269],"type":"Point"}
}