{
  "type": "Feature",
  "properties": {
    "addr:full":"Imkerstraat 3 Bree Limburg 3960",
    "addr:housenumber":"3",
    "addr:postcode":"3960",
    "addr:street":"Imkerstraat",
    "iso:country":"BE",
    "sg:address":"Imkerstraat 3",
    "sg:city":"Bree",
    "sg:orig_category":"Woningbouw",
    "sg:phone":"+32 89 46 49 57",
    "sg:postcode":"3960",
    "sg:province":"Limburg",
    "wof:name":"Bouw-coordinat.& Adviesb.",
    "wof:placetype":"venue"
},
  "geometry": {"coordinates":[5.5939087868,51.1463470459],"type":"Point"}
}