{
  "type": "Feature",
  "properties": {
    "iso:country":"BE",
    "sg:address":"Rue Du Bois De Malette 5",
    "sg:city":"Grace-hollogne",
    "sg:orig_category":"Kapsalons",
    "sg:phone":"+32 4 233 44 67",
    "sg:postcode":"4460",
    "sg:province":"Li\u00e8ge",
    "wof:name":"Coiffure Josiane",
    "wof:placetype":"venue"
},
  "geometry": {"coordinates":[5.4941000938,50.6305236816],"type":"Point"}
}