{
  "type": "Feature",
  "properties": {
    "iso:country":"BE",
    "sg:address":"Rue Du Calvaire 23",
    "sg:city":"Charleroi",
    "sg:orig_category":"P\u00e9pini\u00e9ristes",
    "sg:phone":"+32 71 31 84 62",
    "sg:postcode":"6061",
    "sg:province":"Hainaut",
    "wof:name":"Olivier Byl",
    "wof:placetype":"venue"
},
  "geometry": {"coordinates":[4.4811329842,50.4023323059],"type":"Point"}
}