{
  "type": "Feature",
  "properties": {
    "addr:full":"Frans Van Ryhovelaan 83 Gent Oost-Vlaanderen 9000",
    "addr:housenumber":"83",
    "addr:postcode":"9000",
    "addr:street":"Frans Van Ryhovelaan;Oost-Vlaanderen",
    "iso:country":"BE",
    "sg:address":"Frans Van Ryhovelaan 83",
    "sg:city":"Gent",
    "sg:orig_category":"Kapsalons",
    "sg:phone":"+32 9 226 05 72",
    "sg:postcode":"9000",
    "sg:province":"Oost-Vlaanderen",
    "wof:name":"Kapper Voor Hem",
    "wof:placetype":"venue"
},
  "geometry": {"coordinates":[3.7074589729,51.0688247681],"type":"Point"}
}