{
  "type": "Feature",
  "properties": {
    "iso:country":"BE",
    "sg:address":"Place Du M\u00d4le 14",
    "sg:city":"Braine-l\u00b4alleud",
    "sg:classifiers":[
        {
            "category":"Restaurant",
            "type":"Food & Drink"
        }
    ],
    "sg:phone":"+32 2 385 01 81",
    "sg:postcode":"1420",
    "sg:province":"Brabant Wallon",
    "sg:tags":[
        "caf\u00e9s"
    ],
    "wof:name":"Taverne The Hill",
    "wof:placetype":"venue"
},
  "geometry": {"coordinates":[4.3708639145,50.6841850281],"type":"Point"}
}