{
  "type": "Feature",
  "properties": {
    "addr:full":"Schrijnstraat 22 Mechelen Antwerpen 2800",
    "addr:housenumber":"22",
    "addr:postcode":"2800",
    "addr:street":"Schrijnstraat",
    "iso:country":"BE",
    "sg:address":"Schrijnstraat 22",
    "sg:city":"Mechelen",
    "sg:classifiers":[
        {
            "category":"Professional",
            "subcategory":"Management & Consulting",
            "type":"Services"
        }
    ],
    "sg:phone":"+32 15 27 02 47",
    "sg:postcode":"2800",
    "sg:province":"Antwerpen",
    "sg:tags":[
        "consultant",
        "promotion",
        "-",
        "sale"
    ],
    "wof:name":"Proserco Bvba",
    "wof:placetype":"venue"
},
  "geometry": {"coordinates":[4.4747018814,51.0336418152],"type":"Point"}
}