{
  "type": "Feature",
  "properties": {
    "addr:full":"Chemin De Sn\u00c9viot 49 Bouillon Luxembourg 6830",
    "addr:housenumber":"49",
    "addr:postcode":"6830",
    "addr:street":"Chemin De Sne\u0301Viot",
    "iso:country":"BE",
    "sg:address":"Chemin De Sn\u00c9viot 49",
    "sg:city":"Bouillon",
    "sg:classifiers":[
        {
            "category":"Social Services",
            "subcategory":"Job Training",
            "type":"Services"
        }
    ],
    "sg:phone":"+32 61 46 73 15",
    "sg:postcode":"6830",
    "sg:province":"Luxembourg",
    "sg:tags":[
        "de",
        "terrain",
        "camping"
    ],
    "wof:name":"Camping D'houlifontaine",
    "wof:placetype":"venue"
},
  "geometry": {"coordinates":[5.0699849129,49.7954597473],"type":"Point"}
}