{
  "type": "Feature",
  "properties": {
    "iso:country":"BE",
    "sg:address":"Carnotstraat 30b",
    "sg:city":"Antwerpen",
    "sg:classifiers":[
        {
            "category":"Travel",
            "subcategory":"Travel Agent",
            "type":"Entertainment"
        }
    ],
    "sg:phone":"+32 3 213 58 80",
    "sg:postcode":"2060",
    "sg:province":"Antwerpen",
    "sg:tags":[
        "agency"
    ],
    "wof:name":"Atb Reizen Cvba",
    "wof:placetype":"venue"
},
  "geometry": {"coordinates":[4.4234609604,51.2186431885],"type":"Point"}
}