{
  "type": "Feature",
  "properties": {
    "iso:country":"BE",
    "sg:address":"Jagersweg 65",
    "sg:city":"Malle (westmalle)",
    "sg:classifiers":[
        {
            "category":"Professional",
            "subcategory":"Advertising",
            "type":"Services"
        }
    ],
    "sg:phone":"+32 3 384 04 00",
    "sg:postcode":"2390",
    "sg:province":"Antwerpen",
    "sg:tags":[
        "item",
        "-",
        "business",
        "gift",
        "promotional"
    ],
    "wof:name":"Elite Reclaam",
    "wof:placetype":"venue"
},
  "geometry": {"coordinates":[4.6458802223,51.2748985291],"type":"Point"}
}