{
  "type": "Feature",
  "properties": {
    "addr:full":"Maastrichterstraat 21-22 Tongeren Limburg 3700",
    "addr:postcode":"21-22 tongeren;3700",
    "addr:street":"Maastrichterstraat",
    "iso:country":"BE",
    "sg:address":"Maastrichterstraat 21-22",
    "sg:city":"Tongeren",
    "sg:orig_category":"Schoenen",
    "sg:phone":"+32 12 23 65 74",
    "sg:postcode":"3700",
    "sg:province":"Limburg",
    "wof:name":"Huis Gilissen Junior",
    "wof:placetype":"venue"
},
  "geometry": {"coordinates":[5.4650287628,50.7815704346],"type":"Point"}
}