{
  "type": "Feature",
  "properties": {
    "iso:country":"BE",
    "sg:address":"Kalverberg 8",
    "sg:city":"Raeren",
    "sg:classifiers":[
        {
            "category":"Insurance",
            "subcategory":"Insurance Agent",
            "type":"Services"
        }
    ],
    "sg:phone":"+32 87 85 15 32",
    "sg:postcode":"4730",
    "sg:province":"Li\u00e8ge",
    "sg:tags":[
        "verzekeringsmakelaars",
        "expert"
    ],
    "wof:name":"B\u00dcro Schumacher-hochs",
    "wof:placetype":"venue"
},
  "geometry": {"coordinates":[6.1089720726,50.6658821106],"type":"Point"}
}