{
  "type": "Feature",
  "properties": {
    "addr:full":"Vilvoordsesteenweg 57b5 Grimbergen Vlaams-Brabant 1850",
    "addr:housenumber":"57b5",
    "addr:postcode":"1850",
    "addr:street":"Vilvoordsesteenweg",
    "iso:country":"BE",
    "sg:address":"Vilvoordsesteenweg 57b5",
    "sg:city":"Grimbergen",
    "sg:classifiers":[
        {
            "category":"Professional",
            "subcategory":"Accounting & Tax Preparation",
            "type":"Services"
        }
    ],
    "sg:phone":"+32 2 270 14 55",
    "sg:postcode":"1850",
    "sg:province":"Vlaams-Brabant",
    "sg:tags":[
        "accountant"
    ],
    "wof:name":"Lena Plas",
    "wof:placetype":"venue"
},
  "geometry": {"coordinates":[4.3770308495,50.9313583374],"type":"Point"}
}