{
  "type": "Feature",
  "properties": {
    "iso:country":"BE",
    "sg:address":"Grand'rue 67",
    "sg:city":"Trooz",
    "sg:orig_category":"Jeux de hasard",
    "sg:phone":"+32 4 351 73 22",
    "sg:postcode":"4870",
    "sg:province":"Li\u00e8ge",
    "wof:name":"Tierc\u00c9 Franco Belge",
    "wof:placetype":"venue"
},
  "geometry": {"coordinates":[5.6895260811,50.5719566345],"type":"Point"}
}