{
  "type": "Feature",
  "properties": {
    "iso:country":"BE",
    "sg:address":"Rue Moister 28",
    "sg:city":"Fleron",
    "sg:orig_category":"Industri\u00eble and commerci\u00eble bouw",
    "sg:phone":"+32 4 358 97 97",
    "sg:postcode":"4624",
    "sg:province":"Li\u00e8ge",
    "wof:name":"Rent",
    "wof:placetype":"venue"
},
  "geometry": {"coordinates":[5.6749720573,50.6007080078],"type":"Point"}
}