{
  "type": "Feature",
  "properties": {
    "iso:country":"BE",
    "sg:address":"Avenue Du Condor 10",
    "sg:city":"Bruxelles (molenbeek-saint-jean)",
    "sg:classifiers":[
        {
            "category":"Building & Trades",
            "subcategory":"Cleaning & Sanitation",
            "type":"Services"
        }
    ],
    "sg:phone":"+32 2 411 74 79",
    "sg:postcode":"1080",
    "sg:province":"Bruxelles-Capitale",
    "sg:tags":[
        "janitor"
    ],
    "wof:name":"Multiclean",
    "wof:placetype":"venue"
},
  "geometry": {"coordinates":[4.3063130379,50.8525619507],"type":"Point"}
}