{
  "type": "Feature",
  "properties": {
    "iso:country":"BE",
    "sg:address":"Maarschalk Haiglaan 23",
    "sg:city":"Ieper",
    "sg:orig_category":"Produits surgel\u00e9s Gr",
    "sg:phone":"+32 57 20 17 00",
    "sg:postcode":"8900",
    "sg:province":"West-Vlaanderen",
    "wof:name":"Dumortier",
    "wof:placetype":"venue"
},
  "geometry": {"coordinates":[2.875371933,50.8522224426],"type":"Point"}
}