{
  "type": "Feature",
  "properties": {
    "iso:country":"BE",
    "sg:address":"Hogeweg 118",
    "sg:city":"Menen",
    "sg:classifiers":[
        {
            "category":"Personal",
            "subcategory":"Beauty Salon",
            "type":"Services"
        }
    ],
    "sg:phone":"+32 56 51 54 83",
    "sg:postcode":"8930",
    "sg:province":"West-Vlaanderen",
    "sg:tags":[
        "lady",
        "-",
        "hairdressing"
    ],
    "wof:name":"Marijke",
    "wof:placetype":"venue"
},
  "geometry": {"coordinates":[3.1059401035,50.7964401245],"type":"Point"}
}