{
  "type": "Feature",
  "properties": {
    "addr:full":"Fr\u00e8re-orbanstraat 60 Oostende West-Vlaanderen 8400",
    "addr:housenumber":"60",
    "addr:postcode":"8400",
    "addr:street":"Fre\u0300Re-Orbanstraat",
    "iso:country":"BE",
    "sg:address":"Fr\u00e8re-orbanstraat 60",
    "sg:city":"Oostende",
    "sg:classifiers":[
        {
            "category":"Real Estate",
            "subcategory":"Architect",
            "type":"Services"
        }
    ],
    "sg:phone":"+32 478 39 99 15",
    "sg:postcode":"8400",
    "sg:province":"West-Vlaanderen",
    "wof:name":"Dehaene V",
    "wof:placetype":"venue"
},
  "geometry": {"coordinates":[2.9110980034,51.2202911377],"type":"Point"}
}