{
  "type": "Feature",
  "properties": {
    "addr:full":"Veurnseweg 538 Ieper (elverdinge) West-Vlaanderen 8906",
    "addr:housenumber":"538",
    "addr:postcode":"8906",
    "addr:street":"Veurnseweg",
    "iso:country":"BE",
    "sg:address":"Veurnseweg 538",
    "sg:city":"Ieper (elverdinge)",
    "sg:classifiers":[
        {
            "category":"Health Services",
            "subcategory":"Nursing And Care Facility",
            "type":"Services"
        }
    ],
    "sg:phone":"+32 57 42 36 01",
    "sg:postcode":"8906",
    "sg:province":"West-Vlaanderen",
    "sg:tags":[
        "home"
    ],
    "wof:name":"Home Vrijzicht Vzw",
    "wof:placetype":"venue"
},
  "geometry": {"coordinates":[2.8182311058,50.8858337402],"type":"Point"}
}