{
  "type": "Feature",
  "properties": {
    "addr:full":"Vinkenstraat 2 Ingelmunster West-Vlaanderen 8770",
    "addr:housenumber":"2",
    "addr:postcode":"8770",
    "addr:street":"Vinkenstraat",
    "iso:country":"BE",
    "sg:address":"Vinkenstraat 2",
    "sg:city":"Ingelmunster",
    "sg:classifiers":[
        {
            "category":"Personal",
            "subcategory":"Beauty Salon",
            "type":"Services"
        }
    ],
    "sg:phone":"+32 51 30 65 90",
    "sg:postcode":"8770",
    "sg:province":"West-Vlaanderen",
    "sg:tags":[
        "de",
        "coiffure"
    ],
    "wof:name":"Coiffure 't Lokje",
    "wof:placetype":"venue"
},
  "geometry": {"coordinates":[3.2521851063,50.9113426208],"type":"Point"}
}