{
  "type": "Feature",
  "properties": {
    "iso:country":"BE",
    "sg:address":"Nieuwpoortsesteenweg 196",
    "sg:city":"Oostende",
    "sg:orig_category":"Bars. Mat\u00e9riel de T\u00e9l\u00e9communication",
    "sg:phone":"+32 59 51 91 81",
    "sg:postcode":"8400",
    "sg:province":"West-Vlaanderen",
    "wof:name":"Cyberia",
    "wof:placetype":"venue"
},
  "geometry": {"coordinates":[2.9008529186,51.2207603455],"type":"Point"}
}