{
  "type": "Feature",
  "properties": {
    "iso:country":"BE",
    "sg:address":"Holvenscheide 7",
    "sg:city":"Geel",
    "sg:classifiers":[
        {
            "category":"Health Services",
            "subcategory":"Health Practitioner",
            "type":"Services"
        }
    ],
    "sg:phone":"+32 14 58 40 08",
    "sg:postcode":"2440",
    "sg:province":"Antwerpen",
    "sg:tags":[
        "physiotherapist"
    ],
    "wof:name":"Van Cauter C",
    "wof:placetype":"venue"
},
  "geometry": {"coordinates":[4.9930438995,51.1815109253],"type":"Point"}
}