{
  "type": "Feature",
  "properties": {
    "addr:full":"Cour Palant 22 Thimister-clermont (clermont) Li\u00e8ge 4890",
    "addr:housenumber":"22",
    "addr:postcode":"4890",
    "addr:street":"Cour Palant",
    "iso:country":"BE",
    "sg:address":"Cour Palant 22",
    "sg:city":"Thimister-clermont (clermont)",
    "sg:classifiers":[
        {
            "category":"Communications",
            "type":"Services"
        }
    ],
    "sg:phone":"+32 87 68 86 56",
    "sg:postcode":"4890",
    "sg:province":"Li\u00e8ge",
    "sg:tags":[
        "translator"
    ],
    "wof:name":"Foret M",
    "wof:placetype":"venue"
},
  "geometry": {"coordinates":[5.8556199074,50.6794509888],"type":"Point"}
}