{
  "type": "Feature",
  "properties": {
    "iso:country":"BE",
    "sg:address":"Kerkstraat 64",
    "sg:city":"Lokeren",
    "sg:orig_category":"Advocaten and juridische adviseurs",
    "sg:phone":"+32 9 348 39 17",
    "sg:postcode":"9160",
    "sg:province":"Oost-Vlaanderen",
    "wof:name":"Marylin Daelemans",
    "wof:placetype":"venue"
},
  "geometry": {"coordinates":[3.9939920902,51.1029472351],"type":"Point"}
}