{
  "type": "Feature",
  "properties": {
    "addr:full":"Beenhouwerstraat 1 Willebroek (heindonk) Antwerpen 2830",
    "addr:housenumber":"1",
    "addr:postcode":"2830",
    "addr:street":"Beenhouwerstraat",
    "iso:country":"BE",
    "sg:address":"Beenhouwerstraat 1",
    "sg:city":"Willebroek (heindonk)",
    "sg:classifiers":[
        {
            "category":"Home & Garden",
            "subcategory":"Building Materials",
            "type":"Retail Goods"
        }
    ],
    "sg:phone":"+32 3 860 95 80",
    "sg:postcode":"2830",
    "sg:province":"Antwerpen",
    "sg:tags":[
        "granite",
        "stone",
        "natural",
        "marble"
    ],
    "wof:name":"Inter-minerals Nv",
    "wof:placetype":"venue"
},
  "geometry": {"coordinates":[4.4062871933,51.0656471252],"type":"Point"}
}