{
  "type": "Feature",
  "properties": {
    "iso:country":"BE",
    "sg:address":"Cit\u00c9 Des D\u00c9rod\u00c9s 24",
    "sg:city":"Lobbes",
    "sg:orig_category":"Immobili\u00ebnkantoren Landmeters and schatters",
    "sg:phone":"+32 71 59 23 67",
    "sg:postcode":"6540",
    "sg:province":"Hainaut",
    "wof:name":"Thudimmo",
    "wof:placetype":"venue"
},
  "geometry": {"coordinates":[4.2710261345,50.373336792],"type":"Point"}
}