{
  "type": "Feature",
  "properties": {
    "iso:country":"BE",
    "sg:address":"Avenue De Waterloo 63",
    "sg:city":"Charleroi",
    "sg:classifiers":[
        {
            "category":"Retail",
            "subcategory":"Repair Shop",
            "type":"Services"
        }
    ],
    "sg:phone":"+32 71 32 25 30",
    "sg:postcode":"6000",
    "sg:province":"Hainaut",
    "sg:tags":[
        "machine",
        "sewing",
        "-"
    ],
    "wof:name":"Brother St-marie",
    "wof:placetype":"venue"
},
  "geometry": {"coordinates":[4.4490618706,50.4157028198],"type":"Point"}
}