{
  "type": "Feature",
  "properties": {
    "addr:full":"Heilanders 25 Vosselaar Antwerpen 2350",
    "addr:housenumber":"25",
    "addr:postcode":"2350",
    "addr:street":"Heilanders",
    "iso:country":"BE",
    "sg:address":"Heilanders 25",
    "sg:city":"Vosselaar",
    "sg:classifiers":[
        {
            "category":"Professional",
            "subcategory":"Testing Lab",
            "type":"Services"
        }
    ],
    "sg:phone":"+32 14 61 22 29",
    "sg:postcode":"2350",
    "sg:province":"Antwerpen",
    "sg:tags":[
        "chemist"
    ],
    "wof:name":"Roelants J",
    "wof:placetype":"venue"
},
  "geometry": {"coordinates":[4.8800568581,51.3040313721],"type":"Point"}
}