{
  "type": "Feature",
  "properties": {
    "addr:full":"Koningsstraat 10 Brussel/bruxelles Bruxelles-Capitale 1000",
    "addr:housenumber":"10",
    "addr:postcode":"1000",
    "addr:street":"Koningsstraat;/",
    "iso:country":"BE",
    "sg:address":"Koningsstraat 10",
    "sg:city":"Brussel/bruxelles",
    "sg:orig_category":"Divers amusement Diverse zakelijke dienstverlening Krantenuitgeverijen Tijdschriftenuitgeverijen",
    "sg:phone":"+32 2 507 85 20",
    "sg:postcode":"1000",
    "sg:province":"Bruxelles-Capitale",
    "wof:name":"Adac",
    "wof:placetype":"venue"
},
  "geometry": {"coordinates":[4.3593540192,50.8425483704],"type":"Point"}
}