{
  "type": "Feature",
  "properties": {
    "addr:full":"Heuveneindeweg 9bb Zonhoven Limburg 3520",
    "addr:postcode":"3520",
    "addr:street":"Limburg",
    "iso:country":"BE",
    "sg:address":"Heuveneindeweg 9bb",
    "sg:city":"Zonhoven",
    "sg:classifiers":[
        {
            "category":"Insurance",
            "subcategory":"Life Insurance",
            "type":"Services"
        }
    ],
    "sg:phone":"+32 11 81 89 31",
    "sg:postcode":"3520",
    "sg:province":"Limburg",
    "sg:tags":[
        "assurance"
    ],
    "wof:name":"K. Beelen",
    "wof:placetype":"venue"
},
  "geometry": {"coordinates":[5.3611478806,50.9711074829],"type":"Point"}
}