{
  "type": "Feature",
  "properties": {
    "addr:full":"Sint-jansstraat 20 Hoegaarden Vlaams-Brabant 3320",
    "addr:housenumber":"20",
    "addr:postcode":"3320",
    "addr:street":"Sint-Jansstraat",
    "iso:country":"BE",
    "sg:address":"Sint-jansstraat 20",
    "sg:city":"Hoegaarden",
    "sg:orig_category":"Eleveurs and marchands de porcs. Eleveurs de bovins",
    "sg:phone":"+32 16 81 30 50",
    "sg:postcode":"3320",
    "sg:province":"Vlaams-Brabant",
    "wof:name":"Willy Smets",
    "wof:placetype":"venue"
},
  "geometry": {"coordinates":[4.8729729652,50.8022766113],"type":"Point"}
}