{
  "type": "Feature",
  "properties": {
    "iso:country":"BE",
    "sg:address":"Reningheersdijkstraat 10",
    "sg:city":"Veurne",
    "sg:orig_category":"Varkenskwekers",
    "sg:phone":"+32 58 29 94 28",
    "sg:postcode":"8630",
    "sg:province":"West-Vlaanderen",
    "wof:name":"Daniel Moeyaert",
    "wof:placetype":"venue"
},
  "geometry": {"coordinates":[2.6215379238,50.9976005554],"type":"Point"}
}