{
  "type": "Feature",
  "properties": {
    "addr:full":"St-jobstraat 238 Herentals Antwerpen 2200",
    "addr:housenumber":"238",
    "addr:postcode":"2200",
    "iso:country":"BE",
    "sg:address":"St-jobstraat 238",
    "sg:city":"Herentals",
    "sg:orig_category":"Voertuigen",
    "sg:phone":"+32 14 21 33 86",
    "sg:postcode":"2200",
    "sg:province":"Antwerpen",
    "wof:name":"Smolders",
    "wof:placetype":"venue"
},
  "geometry": {"coordinates":[4.8590312004,51.1819343567],"type":"Point"}
}