{
  "type": "Feature",
  "properties": {
    "iso:country":"BE",
    "sg:address":"Route Du Grand Peuplier 19",
    "sg:city":"La Louvi\u00c8re",
    "sg:orig_category":"Syst\u00e8mes de t\u00e9l\u00e9communications. Ordinateurs and \u00e9quipement informatique",
    "sg:phone":"+32 64 67 10 80",
    "sg:postcode":"7110",
    "sg:province":"Hainaut",
    "wof:name":"B.c.m.",
    "wof:placetype":"venue"
},
  "geometry": {"coordinates":[4.1505050659,50.4826698303],"type":"Point"}
}