{
  "type": "Feature",
  "properties": {
    "addr:full":"Bieststraat 243 Heusden-zolder Limburg 3550",
    "addr:housenumber":"243",
    "addr:postcode":"3550",
    "addr:street":"Bieststraat",
    "iso:country":"BE",
    "sg:address":"Bieststraat 243",
    "sg:city":"Heusden-zolder",
    "sg:classifiers":[
        {
            "category":"Cafe",
            "type":"Food & Drink"
        }
    ],
    "sg:phone":"+32 11 53 35 15",
    "sg:postcode":"3550",
    "sg:province":"Limburg",
    "sg:tags":[
        "caf\u00e9s"
    ],
    "wof:name":"Robs Pub",
    "wof:placetype":"venue"
},
  "geometry": {"coordinates":[5.288380146,51.0168685913],"type":"Point"}
}