{
  "type": "Feature",
  "properties": {
    "addr:full":"Avenue Du Houx 17 Bruxelles (watermael-boitsfort) Bruxelles-Capitale 1170",
    "addr:housenumber":"17",
    "addr:postcode":"1170",
    "addr:street":"Avenue Du Houx",
    "iso:country":"BE",
    "sg:address":"Avenue Du Houx 17",
    "sg:city":"Bruxelles (watermael-boitsfort)",
    "sg:classifiers":[
        {
            "category":"Health Services",
            "subcategory":"Doctor",
            "type":"Services"
        }
    ],
    "sg:phone":"+32 2 673 01 00",
    "sg:postcode":"1170",
    "sg:province":"Bruxelles-Capitale",
    "sg:tags":[
        "medicinephysicians",
        "surgeon"
    ],
    "wof:name":"Langenus Luc",
    "wof:placetype":"venue"
},
  "geometry": {"coordinates":[4.4250721931,50.8047523499],"type":"Point"}
}