{
  "type": "Feature",
  "properties": {
    "addr:full":"Kattestraat 67 Haaltert Oost-Vlaanderen 9450",
    "addr:housenumber":"67",
    "addr:postcode":"9450",
    "addr:street":"Kattestraat",
    "iso:country":"BE",
    "sg:address":"Kattestraat 67",
    "sg:city":"Haaltert",
    "sg:orig_category":"Diensten voor huisdieren",
    "sg:phone":"+32 53 83 66 25",
    "sg:postcode":"9450",
    "sg:province":"Oost-Vlaanderen",
    "wof:name":"Hondenkapsalon Sibel",
    "wof:placetype":"venue"
},
  "geometry": {"coordinates":[3.99801898,50.9028587341],"type":"Point"}
}