{
  "type": "Feature",
  "properties": {
    "addr:full":"Luxor Parc 20 Oudergem/auderghem Bruxelles-Capitale 1160",
    "addr:housenumber":"20",
    "addr:postcode":"1160",
    "addr:street":"Luxor;/",
    "iso:country":"BE",
    "sg:address":"Luxor Parc 20",
    "sg:city":"Oudergem/auderghem",
    "sg:orig_category":"Diverse bedrijfsbeheeradviesbureaus",
    "sg:phone":"+32 2 660 98 59",
    "sg:postcode":"1160",
    "sg:province":"Bruxelles-Capitale",
    "wof:name":"Id\u00c9actions",
    "wof:placetype":"venue"
},
  "geometry": {"coordinates":[4.4299311638,50.8246383667],"type":"Point"}
}