{
  "type": "Feature",
  "properties": {
    "iso:country":"BE",
    "sg:address":"Chauss\u00c9e De Waterloo 305",
    "sg:city":"Sint-gillis/saint-gilles",
    "sg:orig_category":"Architectes",
    "sg:phone":"+32 2 537 94 67",
    "sg:postcode":"1060",
    "sg:province":"Bruxelles-Capitale",
    "wof:name":"Franck Hollevoet",
    "wof:placetype":"venue"
},
  "geometry": {"coordinates":[4.3509588242,50.8238716125],"type":"Point"}
}