{
  "type": "Feature",
  "properties": {
    "iso:country":"BE",
    "sg:address":"Rue Duquesnoy 5",
    "sg:city":"Bruxelles",
    "sg:classifiers":[
        {
            "category":"Recreation",
            "subcategory":"Dance Hall",
            "type":"Entertainment"
        }
    ],
    "sg:phone":"+32 2 505 55 55",
    "sg:postcode":"1000",
    "sg:province":"Bruxelles-Capitale",
    "sg:tags":[
        "discotheque"
    ],
    "wof:name":"Hotel Royal Windsor",
    "wof:placetype":"venue"
},
  "geometry": {"coordinates":[4.3543319702,50.8452148438],"type":"Point"}
}