{
  "type": "Feature",
  "properties": {
    "addr:full":"Sint-damiaanstraat 43 Wommelgem Antwerpen 2160",
    "addr:housenumber":"43",
    "addr:postcode":"2160",
    "addr:street":"Sint-Damiaanstraat",
    "iso:country":"BE",
    "sg:address":"Sint-damiaanstraat 43",
    "sg:city":"Wommelgem",
    "sg:classifiers":[
        {
            "category":"Food & Beverages",
            "subcategory":"Groceries & Convenience Stores",
            "type":"Retail Goods"
        }
    ],
    "sg:phone":"+32 3 354 56 59",
    "sg:postcode":"2160",
    "sg:province":"Antwerpen",
    "sg:tags":[
        "grocer"
    ],
    "wof:name":"Kruidenier (de)",
    "wof:placetype":"venue"
},
  "geometry": {"coordinates":[4.5218458176,51.20154953],"type":"Point"}
}