{
  "type": "Feature",
  "properties": {
    "iso:country":"BE",
    "sg:address":"Rue Stanley 51",
    "sg:city":"Bruxelles (uccle)",
    "sg:classifiers":[
        {
            "category":"Health Services",
            "subcategory":"Health Practitioner",
            "type":"Services"
        }
    ],
    "sg:phone":"+32 2 344 83 33",
    "sg:postcode":"1180",
    "sg:province":"Bruxelles-Capitale",
    "sg:tags":[
        "osteopath"
    ],
    "wof:name":"Goubau Ph",
    "wof:placetype":"venue"
},
  "geometry": {"coordinates":[4.3649377823,50.8156547546],"type":"Point"}
}