{
  "type": "Feature",
  "properties": {
    "iso:country":"BE",
    "sg:address":"Statiestraat 205 Box 4",
    "sg:city":"Lichtervelde",
    "sg:classifiers":[
        {
            "category":"Health Services",
            "subcategory":"Nursing And Care Facility",
            "type":"Services"
        }
    ],
    "sg:phone":"+32 51 72 28 04",
    "sg:postcode":"8810",
    "sg:province":"West-Vlaanderen",
    "sg:tags":[
        "home"
    ],
    "wof:name":"D'hulster Janis Thuisverpleging Bvba",
    "wof:placetype":"venue"
},
  "geometry": {"coordinates":[3.1287100315,51.0244903564],"type":"Point"}
}