{
  "type": "Feature",
  "properties": {
    "iso:country":"BE",
    "sg:address":"Rue G\u00e9n\u00e9ral Leman 36",
    "sg:city":"Tournai (vezon)",
    "sg:classifiers":[
        {
            "category":"Health Services",
            "subcategory":"Nursing And Care Facility",
            "type":"Services"
        }
    ],
    "sg:phone":"+32 69 44 30 59",
    "sg:postcode":"7538",
    "sg:province":"Hainaut",
    "sg:tags":[
        "home"
    ],
    "wof:name":"Sousa Da Rosa Ana",
    "wof:placetype":"venue"
},
  "geometry": {"coordinates":[3.4960610867,50.5682983398],"type":"Point"}
}