{
  "type": "Feature",
  "properties": {
    "iso:country":"BE",
    "sg:address":"Lostraat 48",
    "sg:city":"Heist-op-den-berg",
    "sg:classifiers":[
        {
            "category":"Sports & Exercise",
            "subcategory":"Sports Center",
            "type":"Entertainment"
        }
    ],
    "sg:phone":"+32 15 24 48 93",
    "sg:postcode":"2220",
    "sg:province":"Antwerpen",
    "sg:tags":[
        "terrain",
        "hors",
        "de",
        "installation",
        "sportifs"
    ],
    "wof:name":"Gemeentelijk Zwembad",
    "wof:placetype":"venue"
},
  "geometry": {"coordinates":[4.7359509468,51.0674247742],"type":"Point"}
}