{
  "type": "Feature",
  "properties": {
    "addr:full":"Rue Du Marais 17 Silly Hainaut 7830",
    "addr:housenumber":"17",
    "addr:postcode":"7830",
    "addr:street":"Rue Du Marais",
    "iso:country":"BE",
    "sg:address":"Rue Du Marais 17",
    "sg:city":"Silly",
    "sg:classifiers":[
        {
            "category":"Professional",
            "subcategory":"Management & Consulting",
            "type":"Services"
        }
    ],
    "sg:phone":"+32 477 23 65 43",
    "sg:postcode":"7830",
    "sg:province":"Hainaut",
    "sg:tags":[
        "-",
        "processing",
        "data",
        "consultant"
    ],
    "wof:name":"Cornet",
    "wof:placetype":"venue"
},
  "geometry": {"coordinates":[3.9264669418,50.6464996338],"type":"Point"}
}