{
  "type": "Feature",
  "properties": {
    "iso:country":"BE",
    "sg:address":"Rue Du Mazy 15",
    "sg:city":"Binche",
    "sg:orig_category":"Boucheries",
    "sg:phone":"+32 64 33 57 07",
    "sg:postcode":"7134",
    "sg:province":"Hainaut",
    "wof:name":"Boucherie Urbain",
    "wof:placetype":"venue"
},
  "geometry": {"coordinates":[4.2175779343,50.4159622192],"type":"Point"}
}