{
  "type": "Feature",
  "properties": {
    "iso:country":"BE",
    "sg:address":"Mesesstraat 61",
    "sg:city":"Turnhout",
    "sg:classifiers":[
        {
            "category":"Building & Trades",
            "subcategory":"Cleaning & Sanitation",
            "type":"Services"
        }
    ],
    "sg:phone":"+32 14 42 22 15",
    "sg:postcode":"2300",
    "sg:province":"Antwerpen",
    "sg:tags":[
        "janitor"
    ],
    "wof:name":"Team Service",
    "wof:placetype":"venue"
},
  "geometry": {"coordinates":[4.9509749413,51.3322219849],"type":"Point"}
}