{
  "type": "Feature",
  "properties": {
    "iso:country":"BE",
    "sg:address":"Clos Des Tulipes 9",
    "sg:city":"Waterloo",
    "sg:classifiers":[
        {
            "category":"Professional",
            "type":"Services"
        }
    ],
    "sg:phone":"+32 2 354 93 11",
    "sg:postcode":"1410",
    "sg:province":"Brabant Wallon",
    "sg:tags":[
        "surveyor",
        "-",
        "valuer"
    ],
    "wof:name":"Coppens H",
    "wof:placetype":"venue"
},
  "geometry": {"coordinates":[4.3814520836,50.728843689],"type":"Point"}
}