{
  "type": "Feature",
  "properties": {
    "addr:full":"Hoogstraat 27 Ninove (pollare) Oost-Vlaanderen 9401",
    "addr:housenumber":"27",
    "addr:postcode":"9401",
    "addr:street":"Hoogstraat",
    "iso:country":"BE",
    "sg:address":"Hoogstraat 27",
    "sg:city":"Ninove (pollare)",
    "sg:classifiers":[
        {
            "category":"Real Estate",
            "subcategory":"Architect",
            "type":"Services"
        }
    ],
    "sg:phone":"+32 54 34 10 87",
    "sg:postcode":"9401",
    "sg:province":"Oost-Vlaanderen",
    "wof:name":"Meganck B",
    "wof:placetype":"venue"
},
  "geometry": {"coordinates":[4.0013818741,50.819984436],"type":"Point"}
}