{
  "type": "Feature",
  "properties": {
    "addr:full":"Kwadamstraat 44 Knesselare Oost-Vlaanderen 9910",
    "addr:housenumber":"44",
    "addr:postcode":"9910",
    "addr:street":"Kwadamstraat;Oost-Vlaanderen",
    "iso:country":"BE",
    "sg:address":"Kwadamstraat 44",
    "sg:city":"Knesselare",
    "sg:orig_category":"Woningbouw",
    "sg:phone":"+32 9 374 26 60",
    "sg:postcode":"9910",
    "sg:province":"Oost-Vlaanderen",
    "wof:name":"Romain Almey",
    "wof:placetype":"venue"
},
  "geometry": {"coordinates":[3.4017729759,51.131111145],"type":"Point"}
}