{
  "type": "Feature",
  "properties": {
    "addr:full":"Edingsesteenweg 233 Gooik Vlaams-Brabant 1755",
    "addr:housenumber":"233",
    "addr:postcode":"1755",
    "addr:street":"Edingsesteenweg",
    "iso:country":"BE",
    "sg:address":"Edingsesteenweg 233",
    "sg:city":"Gooik",
    "sg:orig_category":"MEUBELONTWERP AND -INSTALLATIE",
    "sg:phone":"+32 2 532 26 77",
    "sg:postcode":"1755",
    "sg:province":"Vlaams-Brabant",
    "wof:name":"Fa. Cochez-heymans",
    "wof:placetype":"venue"
},
  "geometry": {"coordinates":[4.1230998039,50.7871284485],"type":"Point"}
}