{
  "type": "Feature",
  "properties": {
    "addr:full":"Astridlaan 128 Brugge West-Vlaanderen 8310",
    "addr:housenumber":"128",
    "addr:postcode":"8310",
    "addr:street":"Astridlaan",
    "iso:country":"BE",
    "sg:address":"Astridlaan 128",
    "sg:city":"Brugge",
    "sg:orig_category":"V\u00e9hicules automobiles",
    "sg:phone":"+32 50 35 66 85",
    "sg:postcode":"8310",
    "sg:province":"West-Vlaanderen",
    "wof:name":"Freddy Verhaeghe",
    "wof:placetype":"venue"
},
  "geometry": {"coordinates":[3.252120018,51.1971168518],"type":"Point"}
}