{
  "type": "Feature",
  "properties": {
    "addr:full":"Kerkstraat 10 Oostrozebeke West-Vlaanderen 8780",
    "addr:housenumber":"10",
    "addr:postcode":"8780",
    "addr:street":"Kerkstraat",
    "iso:country":"BE",
    "sg:address":"Kerkstraat 10",
    "sg:city":"Oostrozebeke",
    "sg:classifiers":[
        {
            "category":"Bakery",
            "type":"Food & Drink"
        }
    ],
    "sg:phone":"+32 56 66 61 45",
    "sg:postcode":"8780",
    "sg:province":"West-Vlaanderen",
    "sg:tags":[
        "confectioner",
        "baker"
    ],
    "wof:name":"De Smet A",
    "wof:placetype":"venue"
},
  "geometry": {"coordinates":[3.3358659744,50.9209098816],"type":"Point"}
}