{
  "type": "Feature",
  "properties": {
    "iso:country":"BE",
    "sg:address":"Koning Albertstraat 37-1",
    "sg:city":"Kortrijk",
    "sg:classifiers":[
        {
            "category":"Professional",
            "subcategory":"Lawyer & Legal Services",
            "type":"Services"
        }
    ],
    "sg:phone":"+32 56 21 02 49",
    "sg:postcode":"8500",
    "sg:province":"West-Vlaanderen",
    "wof:name":"Gheysen G",
    "wof:placetype":"venue"
},
  "geometry": {"coordinates":[3.2615270615,50.8262786865],"type":"Point"}
}