{
  "type": "Feature",
  "properties": {
    "addr:full":"Oude Tiensebaan 23 Tielt-winge Vlaams-Brabant 3390",
    "addr:housenumber":"23",
    "addr:postcode":"3390",
    "addr:street":"Oude Tiensebaan",
    "iso:country":"BE",
    "sg:address":"Oude Tiensebaan 23",
    "sg:city":"Tielt-winge",
    "sg:orig_category":"Travaux de pl\u00e2trage",
    "sg:phone":"+32 16 63 37 92",
    "sg:postcode":"3390",
    "sg:province":"Vlaams-Brabant",
    "wof:name":"Home-repair",
    "wof:placetype":"venue"
},
  "geometry": {"coordinates":[4.8683981895,50.9044647217],"type":"Point"}
}