{
  "type": "Feature",
  "properties": {
    "addr:full":"Route De Lennik 790 Anderlecht Bruxelles-Capitale 1070",
    "addr:housenumber":"790",
    "addr:postcode":"1070",
    "addr:street":"Route De Lennik",
    "iso:country":"BE",
    "sg:address":"Route De Lennik 790",
    "sg:city":"Anderlecht",
    "sg:orig_category":"H\u00f4tels. Restaurants",
    "sg:phone":"+32 2 523 62 82",
    "sg:postcode":"1070",
    "sg:province":"Bruxelles-Capitale",
    "wof:name":"Hotel Comfort Inn",
    "wof:placetype":"venue"
},
  "geometry": {"coordinates":[4.2718892097,50.8151855469],"type":"Point"}
}