{
  "type": "Feature",
  "properties": {
    "addr:full":"Avenue Des Aub\u00e9pines 111 Bruxelles (uccle) Bruxelles-Capitale 1180",
    "addr:housenumber":"111",
    "addr:postcode":"1180",
    "addr:street":"Avenue Des Aube\u0301Pines",
    "iso:country":"BE",
    "sg:address":"Avenue Des Aub\u00e9pines 111",
    "sg:city":"Bruxelles (uccle)",
    "sg:classifiers":[
        {
            "category":"Transit Center",
            "subcategory":"Freight",
            "type":"Transportation"
        }
    ],
    "sg:phone":"+32 2 375 65 75",
    "sg:postcode":"1180",
    "sg:province":"Bruxelles-Capitale",
    "sg:tags":[
        "import",
        "export",
        "-"
    ],
    "wof:name":"Vergeels Ets",
    "wof:placetype":"venue"
},
  "geometry": {"coordinates":[4.3717980385,50.7742462158],"type":"Point"}
}