{
  "type": "Feature",
  "properties": {
    "addr:full":"Chauss\u00c9e De Dinant 323 Namur Namur 5000",
    "addr:housenumber":"323",
    "addr:postcode":"5000",
    "addr:street":"Chausse\u0301E De Dinant",
    "iso:country":"BE",
    "sg:address":"Chauss\u00c9e De Dinant 323",
    "sg:city":"Namur",
    "sg:orig_category":"Advocaten and juridische adviseurs",
    "sg:phone":"+32 81 22 41 68",
    "sg:postcode":"5000",
    "sg:province":"Namur",
    "wof:name":"Th. Botton",
    "wof:placetype":"venue"
},
  "geometry": {"coordinates":[4.8584852219,50.4409675598],"type":"Point"}
}