{
  "type": "Feature",
  "properties": {
    "iso:country":"BE",
    "sg:address":"Kruiskalsijdestraat 24",
    "sg:city":"Diksmuide (leke)",
    "sg:classifiers":[
        {
            "category":"Animal Shelter",
            "type":"Public Place"
        }
    ],
    "sg:phone":"+32 51 50 00 66",
    "sg:postcode":"8600",
    "sg:province":"West-Vlaanderen",
    "wof:name":"'t Kwispelhof",
    "wof:placetype":"venue"
},
  "geometry": {"coordinates":[2.8657801151,51.0334663391],"type":"Point"}
}