{
  "type": "Feature",
  "properties": {
    "iso:country":"BE",
    "sg:address":"Place P. Delannoy 78",
    "sg:city":"Edingen/enghien",
    "sg:orig_category":"Eclairage et \u00e9quipements du foyer",
    "sg:phone":"+32 2 395 38 17",
    "sg:postcode":"7850",
    "sg:province":"Hainaut",
    "wof:name":"Maison I.d. Wielant",
    "wof:placetype":"venue"
},
  "geometry": {"coordinates":[4.0334601402,50.6914787292],"type":"Point"}
}