{
  "type": "Feature",
  "properties": {
    "addr:full":"Binnensingel 5 Lommel Limburg 3920",
    "addr:housenumber":"5",
    "addr:postcode":"3920",
    "addr:street":"Binnensingel",
    "iso:country":"BE",
    "sg:address":"Binnensingel 5",
    "sg:city":"Lommel",
    "sg:orig_category":"MEUBELONTWERP AND -INSTALLATIE",
    "sg:phone":"+32 11 54 45 90",
    "sg:postcode":"3920",
    "sg:province":"Limburg",
    "wof:name":"De Groof A.",
    "wof:placetype":"venue"
},
  "geometry": {"coordinates":[5.3039979935,51.223033905],"type":"Point"}
}