{
  "type": "Feature",
  "properties": {
    "addr:full":"Boulevard De La Sauveni\u00c8re 117 Li\u00c8ge Li\u00e8ge 4000",
    "addr:housenumber":"117",
    "addr:postcode":"4000",
    "addr:street":"Boulevard De La Sauvenie\u0300Re",
    "iso:country":"BE",
    "sg:address":"Boulevard De La Sauveni\u00c8re 117",
    "sg:city":"Li\u00c8ge",
    "sg:orig_category":"Artsen and specialisten Ziekenhuizen and zorginstellingen",
    "sg:phone":"+32 4 221 23 32",
    "sg:postcode":"4000",
    "sg:province":"Li\u00e8ge",
    "wof:name":"C.h.u.policliniques Sauveni\u00c8re",
    "wof:placetype":"venue"
},
  "geometry": {"coordinates":[5.5670151711,50.6417427063],"type":"Point"}
}