{
  "type": "Feature",
  "properties": {
    "addr:full":"Porte De Tr\u00e8ves 1 Bastogne Luxembourg 6600",
    "addr:housenumber":"1",
    "addr:postcode":"6600",
    "addr:street":"Tre\u0300Ves",
    "iso:country":"BE",
    "sg:address":"Porte De Tr\u00e8ves 1",
    "sg:city":"Bastogne",
    "sg:classifiers":[
        {
            "category":"Shopping",
            "subcategory":"Catalog Store",
            "type":"Retail Goods"
        }
    ],
    "sg:phone":"+32 61 21 79 48",
    "sg:postcode":"6600",
    "sg:province":"Luxembourg",
    "sg:tags":[
        "mail",
        "order",
        "house"
    ],
    "wof:name":"Damart",
    "wof:placetype":"venue"
},
  "geometry": {"coordinates":[5.7224497795,50.0050735474],"type":"Point"}
}