{
  "type": "Feature",
  "properties": {
    "addr:full":"Eikenlaan 1 Bocholt Limburg 3950",
    "addr:housenumber":"1",
    "addr:postcode":"3950",
    "addr:street":"Eikenlaan",
    "iso:country":"BE",
    "sg:address":"Eikenlaan 1",
    "sg:city":"Bocholt",
    "sg:classifiers":[
        {
            "category":"Professional",
            "subcategory":"Lawyer & Legal Services",
            "type":"Services"
        }
    ],
    "sg:phone":"+32 89 46 42 68",
    "sg:postcode":"3950",
    "sg:province":"Limburg",
    "sg:tags":[
        "notary"
    ],
    "wof:name":"Roels Van Kerckvoorde B",
    "wof:placetype":"venue"
},
  "geometry": {"coordinates":[5.5704898834,51.1679267883],"type":"Point"}
}