{
  "type": "Feature",
  "properties": {
    "iso:country":"BE",
    "sg:address":"Meersstraat 32",
    "sg:city":"Geraardsbergen",
    "sg:classifiers":[
        {
            "category":"Professional",
            "subcategory":"Lawyer & Legal Services",
            "type":"Services"
        }
    ],
    "sg:phone":"+32 54 41 47 85",
    "sg:postcode":"9500",
    "sg:province":"Oost-Vlaanderen",
    "wof:name":"Thienpont M",
    "wof:placetype":"venue"
},
  "geometry": {"coordinates":[3.8768310547,50.7682037354],"type":"Point"}
}