{
  "type": "Feature",
  "properties": {
    "addr:full":"Rue Gabrielle Petit 32 Bruxelles (molenbeek-saint-jean) Bruxelles-Capitale 1080",
    "addr:housenumber":"32",
    "addr:postcode":"1080",
    "addr:street":"Rue Gabrielle Petit",
    "iso:country":"BE",
    "sg:address":"Rue Gabrielle Petit 32",
    "sg:city":"Bruxelles (molenbeek-saint-jean)",
    "sg:classifiers":[
        {
            "category":"Professional",
            "subcategory":"Management & Consulting",
            "type":"Services"
        }
    ],
    "sg:phone":"+32 2 421 21 01",
    "sg:postcode":"1080",
    "sg:province":"Bruxelles-Capitale",
    "sg:tags":[
        "consultant",
        "agency",
        "advertising"
    ],
    "wof:name":"Ftp Belgium",
    "wof:placetype":"venue"
},
  "geometry": {"coordinates":[4.340031147,50.8689575195],"type":"Point"}
}