{
  "type": "Feature",
  "properties": {
    "addr:full":"Kwakkelstraat 50 Turnhout Antwerpen 2300",
    "addr:housenumber":"50",
    "addr:postcode":"2300",
    "addr:street":"Kwakkelstraat",
    "iso:country":"BE",
    "sg:address":"Kwakkelstraat 50",
    "sg:city":"Turnhout",
    "sg:classifiers":[
        {
            "category":"Bars & Pubs",
            "type":"Food & Drink"
        }
    ],
    "sg:phone":"+32 14 88 80 27",
    "sg:postcode":"2300",
    "sg:province":"Antwerpen",
    "wof:name":"Vraagteken ('t)",
    "wof:placetype":"venue"
},
  "geometry": {"coordinates":[4.9540719986,51.3209190369],"type":"Point"}
}