{
  "type": "Feature",
  "properties": {
    "iso:country":"BE",
    "sg:address":"Zoning Industriel",
    "sg:city":"Virton (ruette)",
    "sg:classifiers":[
        {
            "category":"Professional",
            "subcategory":"Engineering",
            "type":"Services"
        }
    ],
    "sg:phone":"+32 63 58 33 15",
    "sg:postcode":"6760",
    "sg:province":"Luxembourg",
    "sg:tags":[
        "industrial",
        "-",
        "automation"
    ],
    "wof:name":"F & J Automation Sprl",
    "wof:placetype":"venue"
},
  "geometry": {"coordinates":[5.5347180367,49.5672607422],"type":"Point"}
}