{
  "type": "Feature",
  "properties": {
    "addr:full":"Houba De Strooperlaan 36 Brussel/bruxelles Bruxelles-Capitale 1020",
    "addr:housenumber":"36",
    "addr:postcode":"1020",
    "addr:street":"Houba De Strooperlaan;/",
    "iso:country":"BE",
    "sg:address":"Houba De Strooperlaan 36",
    "sg:city":"Brussel/bruxelles",
    "sg:classifiers":[
        {
            "category":"Restaurant",
            "type":"Food & Drink"
        }
    ],
    "sg:phone":"+32 2 478 20 88",
    "sg:postcode":"1020",
    "sg:province":"Bruxelles-Capitale",
    "wof:name":"Restaurant Le Beaulieu",
    "wof:placetype":"venue"
},
  "geometry": {"coordinates":[4.3462300301,50.8855514526],"type":"Point"}
}