{
  "type": "Feature",
  "properties": {
    "addr:full":"Haenhoutstraat 229 Destelbergen Oost-Vlaanderen 9070",
    "addr:housenumber":"229",
    "addr:postcode":"9070",
    "addr:street":"Haenhoutstraat",
    "iso:country":"BE",
    "sg:address":"Haenhoutstraat 229",
    "sg:city":"Destelbergen",
    "sg:classifiers":[
        {
            "category":"Bakery",
            "type":"Food & Drink"
        }
    ],
    "sg:phone":"+32 9 355 72 62",
    "sg:postcode":"9070",
    "sg:province":"Oost-Vlaanderen",
    "sg:tags":[
        "confectioner",
        "baker"
    ],
    "wof:name":"Gansbeke E",
    "wof:placetype":"venue"
},
  "geometry": {"coordinates":[3.841137886,51.0747108459],"type":"Point"}
}