{
  "type": "Feature",
  "properties": {
    "addr:full":"Molendal 24 Dilbeek Vlaams-Brabant 1700",
    "addr:housenumber":"24",
    "addr:postcode":"1700",
    "addr:street":"Molendal",
    "iso:country":"BE",
    "sg:address":"Molendal 24",
    "sg:city":"Dilbeek",
    "sg:classifiers":[
        {
            "category":"Recreation",
            "subcategory":"Amusement Park",
            "type":"Entertainment"
        }
    ],
    "sg:phone":"+32 476 20 15 53",
    "sg:postcode":"1700",
    "sg:province":"Vlaams-Brabant",
    "sg:tags":[
        "artiestenbureaus",
        "diver"
    ],
    "wof:name":"Star Light",
    "wof:placetype":"venue"
},
  "geometry": {"coordinates":[4.2515411377,50.8435783386],"type":"Point"}
}