{
  "type": "Feature",
  "properties": {
    "iso:country":"BE",
    "sg:address":"Chauss\u00e9e De La Hulpe 334",
    "sg:city":"Bruxelles (watermael-boitsfort)",
    "sg:classifiers":[
        {
            "category":"Professional",
            "subcategory":"Art Services",
            "type":"Services"
        }
    ],
    "sg:phone":"+32 477 79 82 97",
    "sg:postcode":"1170",
    "sg:province":"Bruxelles-Capitale",
    "sg:tags":[
        "photographer"
    ],
    "wof:name":"Van Steensel L",
    "wof:placetype":"venue"
},
  "geometry": {"coordinates":[4.4226617813,50.7905502319],"type":"Point"}
}