{
  "type": "Feature",
  "properties": {
    "iso:country":"BE",
    "sg:address":"Borgerhoutsendijk 11",
    "sg:city":"Mol",
    "sg:orig_category":"Non-Classified Establishments",
    "sg:phone":"+32 14 31 15 18",
    "sg:postcode":"2400",
    "sg:province":"Antwerpen",
    "wof:name":"Al-tri-bo Nv",
    "wof:placetype":"venue"
},
  "geometry": {"coordinates":[5.1074409485,51.1768608093],"type":"Point"}
}