{
  "type": "Feature",
  "properties": {
    "addr:full":"Rosalie Uyttenhovenstraat 71-73 Bruxelles Bruxelles-Capitale 1090",
    "addr:postcode":"71-73;1090",
    "addr:street":"Uyttenhovenstraat",
    "iso:country":"BE",
    "sg:address":"Rosalie Uyttenhovenstraat 71-73",
    "sg:city":"Bruxelles",
    "sg:classifiers":[
        {
            "category":"Farming",
            "subcategory":"Fish & Marine Products",
            "type":"Manufacturing & Wholesale Goods"
        }
    ],
    "sg:phone":"+32 2 425 92 20",
    "sg:postcode":"1090",
    "sg:province":"Bruxelles-Capitale",
    "sg:tags":[
        "caviar",
        "roe"
    ],
    "wof:name":"Maison Vendsyssel S.a.",
    "wof:placetype":"venue"
},
  "geometry": {"coordinates":[4.3393249512,50.8714065552],"type":"Point"}
}