{
  "type": "Feature",
  "properties": {
    "iso:country":"BE",
    "sg:address":"Van Iseghemlaan 107",
    "sg:city":"Oostende",
    "sg:classifiers":[
        {
            "category":"Food & Beverages",
            "subcategory":"Groceries & Convenience Stores",
            "type":"Retail Goods"
        }
    ],
    "sg:phone":"+32 59 70 13 94",
    "sg:postcode":"8400",
    "sg:province":"West-Vlaanderen",
    "sg:tags":[
        "grocer"
    ],
    "wof:name":"Annick's Broodmandje",
    "wof:placetype":"venue"
},
  "geometry": {"coordinates":[2.9116640091,51.2300567627],"type":"Point"}
}