{
  "type": "Feature",
  "properties": {
    "addr:full":"Rue De La Croix Rouge 31 Montigny-le-tilleul Hainaut 6110",
    "addr:housenumber":"31",
    "addr:postcode":"6110",
    "addr:street":"Rue De La Croix Rouge",
    "iso:country":"BE",
    "sg:address":"Rue De La Croix Rouge 31",
    "sg:city":"Montigny-le-tilleul",
    "sg:classifiers":[
        {
            "category":"Utilities",
            "subcategory":"Fuel Oil & Lpg",
            "type":"Services"
        }
    ],
    "sg:phone":"+32 71 56 03 52",
    "sg:postcode":"6110",
    "sg:province":"Hainaut",
    "wof:name":"Lefran Mazout",
    "wof:placetype":"venue"
},
  "geometry": {"coordinates":[4.3609027863,50.3655014038],"type":"Point"}
}