{
  "type": "Feature",
  "properties": {
    "addr:full":"Rue De Fexhe 76 Herstal Li\u00e8ge 4041",
    "addr:housenumber":"76",
    "addr:postcode":"4041",
    "addr:street":"Rue De Fexhe",
    "iso:country":"BE",
    "sg:address":"Rue De Fexhe 76",
    "sg:city":"Herstal",
    "sg:orig_category":"Enseignement maternel and primaire",
    "sg:phone":"+32 4 278 56 99",
    "sg:postcode":"4041",
    "sg:province":"Li\u00e8ge",
    "wof:name":"E.p.e.s.c.f. H. Rikir",
    "wof:placetype":"venue"
},
  "geometry": {"coordinates":[5.5857338905,50.6928024292],"type":"Point"}
}