{
  "type": "Feature",
  "properties": {
    "iso:country":"BE",
    "sg:address":"Wagenmakersstraat 56",
    "sg:city":"Mechelen",
    "sg:orig_category":"Groententeelt",
    "sg:phone":"+32 15 21 65 64",
    "sg:postcode":"2811",
    "sg:province":"Antwerpen",
    "wof:name":"Frans Jacobs",
    "wof:placetype":"venue"
},
  "geometry": {"coordinates":[4.4443998337,51.014541626],"type":"Point"}
}