{
  "type": "Feature",
  "properties": {
    "iso:country":"BE",
    "sg:address":"Schoutput 13",
    "sg:city":"Sint-martens-latem",
    "sg:orig_category":"Agences immobili\u00e8res",
    "sg:phone":"+32 9 282 67 64",
    "sg:postcode":"9830",
    "sg:province":"Oost-Vlaanderen",
    "wof:name":"Codimmo",
    "wof:placetype":"venue"
},
  "geometry": {"coordinates":[3.6309430599,50.9966964722],"type":"Point"}
}