{
  "type": "Feature",
  "properties": {
    "addr:full":"Heidestraat 36a Sint-katherina-lombeek Vlaams-Brabant 1742",
    "addr:housenumber":"36a",
    "addr:postcode":"1742",
    "addr:street":"Heidestraat",
    "iso:country":"BE",
    "sg:address":"Heidestraat 36a",
    "sg:city":"Sint-katherina-lombeek",
    "sg:classifiers":[
        {
            "category":"Manufacturing",
            "subcategory":"Chemicals & Compounds",
            "type":"Manufacturing & Wholesale Goods"
        }
    ],
    "sg:phone":"+32 2 582 66 10",
    "sg:postcode":"1742",
    "sg:province":"Vlaams-Brabant",
    "sg:tags":[
        "pharmaceutical",
        "chemistry",
        "-",
        "by-product"
    ],
    "wof:name":"Ch Jonckheere Nv",
    "wof:placetype":"venue"
},
  "geometry": {"coordinates":[4.1459288597,50.8711662292],"type":"Point"}
}