{
  "type": "Feature",
  "properties": {
    "iso:country":"BE",
    "sg:address":"Marktplein 27",
    "sg:city":"Wingene",
    "sg:orig_category":"Dameskledingzaken",
    "sg:phone":"+32 51 61 28 35",
    "sg:postcode":"8750",
    "sg:province":"West-Vlaanderen",
    "wof:name":"Fa. Yvi",
    "wof:placetype":"venue"
},
  "geometry": {"coordinates":[3.2115249634,51.0356407166],"type":"Point"}
}