{
  "type": "Feature",
  "properties": {
    "iso:country":"BE",
    "sg:address":"Diepestraat 6ba",
    "sg:city":"Bilzen",
    "sg:orig_category":"Epiceries",
    "sg:phone":"+32 12 45 40 75",
    "sg:postcode":"3740",
    "sg:province":"Limburg",
    "wof:name":"Bart Lieben",
    "wof:placetype":"venue"
},
  "geometry": {"coordinates":[5.5133070946,50.8699760437],"type":"Point"}
}