{
  "type": "Feature",
  "properties": {
    "iso:country":"BE",
    "sg:address":"Molenstraat 83",
    "sg:city":"Brecht",
    "sg:orig_category":"Agences immobili\u00e8res",
    "sg:phone":"+32 3 313 50 40",
    "sg:postcode":"2960",
    "sg:province":"Antwerpen",
    "wof:name":"Bureau Alko",
    "wof:placetype":"venue"
},
  "geometry": {"coordinates":[4.6265678406,51.3436851501],"type":"Point"}
}