{
  "type": "Feature",
  "properties": {
    "addr:full":"Rue De Roucourt 85 Peruwelz Hainaut 7600",
    "addr:housenumber":"85",
    "addr:postcode":"7600",
    "addr:street":"Rue De Roucourt;Hainaut",
    "iso:country":"BE",
    "sg:address":"Rue De Roucourt 85",
    "sg:city":"Peruwelz",
    "sg:orig_category":"Overheidsdiensten",
    "sg:phone":"+32 69 77 90 10",
    "sg:postcode":"7600",
    "sg:province":"Hainaut",
    "wof:name":"C.p.a.s.",
    "wof:placetype":"venue"
},
  "geometry": {"coordinates":[3.587857008,50.5117645264],"type":"Point"}
}