{
  "type": "Feature",
  "properties": {
    "addr:full":"Autostrade 2 Londerzeel Vlaams-Brabant 1840",
    "addr:housenumber":"2",
    "addr:postcode":"1840",
    "addr:street":"Autostrade",
    "iso:country":"BE",
    "sg:address":"Autostrade 2",
    "sg:city":"Londerzeel",
    "sg:orig_category":"Voertuigen",
    "sg:phone":"+32 52 30 50 30",
    "sg:postcode":"1840",
    "sg:province":"Vlaams-Brabant",
    "wof:name":"Garage Pol",
    "wof:placetype":"venue"
},
  "geometry": {"coordinates":[4.3159461021,50.9978752136],"type":"Point"}
}