{
  "type": "Feature",
  "properties": {
    "addr:full":"Rue Belle-vue 2 Lasne Brabant Wallon 1380",
    "addr:housenumber":"2",
    "addr:postcode":"1380",
    "addr:street":"Rue Belle-Vue",
    "iso:country":"BE",
    "sg:address":"Rue Belle-vue 2",
    "sg:city":"Lasne",
    "sg:orig_category":"HUISBRANDOLIE",
    "sg:phone":"+32 2 633 53 86",
    "sg:postcode":"1380",
    "sg:province":"Brabant Wallon",
    "wof:name":"Fran\u00c7ois De Broc",
    "wof:placetype":"venue"
},
  "geometry": {"coordinates":[4.4797811508,50.6534957886],"type":"Point"}
}