{
  "type": "Feature",
  "properties": {
    "iso:country":"BE",
    "sg:address":"Chauss\u00c9e De Tirlemont 98",
    "sg:city":"Jodoigne",
    "sg:orig_category":"Sportclubs",
    "sg:phone":"+32 10 81 28 56",
    "sg:postcode":"1370",
    "sg:province":"Brabant Wallon",
    "wof:name":"J.c. A-b-w Team",
    "wof:placetype":"venue"
},
  "geometry": {"coordinates":[4.876666069,50.7285118103],"type":"Point"}
}