{
  "type": "Feature",
  "properties": {
    "iso:country":"BE",
    "sg:address":"Boulevard De Smet De Naeyer 145",
    "sg:city":"Bruxelles (jette)",
    "sg:classifiers":[
        {
            "category":"Organizations",
            "subcategory":"Community Association",
            "type":"Services"
        }
    ],
    "sg:phone":"+32 2 426 64 39",
    "sg:postcode":"1090",
    "sg:province":"Bruxelles-Capitale",
    "sg:tags":[
        "cultural"
    ],
    "wof:name":"Centre Culturel De Jette",
    "wof:placetype":"venue"
},
  "geometry": {"coordinates":[4.328359127,50.8746261597],"type":"Point"}
}