{
  "type": "Feature",
  "properties": {
    "addr:full":"Rue Du Douyet 15 Hotton Luxembourg 6990",
    "addr:housenumber":"15",
    "addr:postcode":"6990",
    "addr:street":"Rue Du Douyet",
    "iso:country":"BE",
    "sg:address":"Rue Du Douyet 15",
    "sg:city":"Hotton",
    "sg:orig_category":"Installation de menuiserie en bois and plastique. Charpentes and couvertures. Installation de menuis",
    "sg:phone":"+32 84 46 67 77",
    "sg:postcode":"6990",
    "sg:province":"Luxembourg",
    "wof:name":"G. Renard",
    "wof:placetype":"venue"
},
  "geometry": {"coordinates":[5.4813871384,50.2864646912],"type":"Point"}
}