{
  "type": "Feature",
  "properties": {
    "iso:country":"BE",
    "sg:address":"Parallelweg 10",
    "sg:city":"Kapelle-op-den-bos",
    "sg:classifiers":[
        {
            "category":"Health Services",
            "subcategory":"Nursing And Care Facility",
            "type":"Services"
        }
    ],
    "sg:phone":"+32 15 71 50 20",
    "sg:postcode":"1880",
    "sg:province":"Vlaams-Brabant",
    "sg:tags":[
        "home",
        "rest"
    ],
    "wof:name":"Akapella Woon- & Zorgcentrum Voor Ouderen",
    "wof:placetype":"venue"
},
  "geometry": {"coordinates":[4.3541331291,51.0141525269],"type":"Point"}
}