{
  "type": "Feature",
  "properties": {
    "addr:full":"Museumstraat 3 Antwerpen Antwerpen 2000",
    "addr:housenumber":"3",
    "addr:postcode":"2000",
    "addr:street":"Museumstraat",
    "iso:country":"BE",
    "sg:address":"Museumstraat 3",
    "sg:city":"Antwerpen",
    "sg:classifiers":[
        {
            "category":"Wholesale",
            "subcategory":"Plants",
            "type":"Manufacturing & Wholesale Goods"
        }
    ],
    "sg:phone":"+32 3 248 39 33",
    "sg:postcode":"2000",
    "sg:province":"Antwerpen",
    "sg:tags":[
        "decoration",
        "flower",
        "-"
    ],
    "wof:name":"Groengaard Van Zeebroeck",
    "wof:placetype":"venue"
},
  "geometry": {"coordinates":[4.3917660713,51.2101364136],"type":"Point"}
}