{
  "type": "Feature",
  "properties": {
    "iso:country":"BE",
    "sg:address":"Munkelostraat 18",
    "sg:city":"Wingene",
    "sg:orig_category":"Eleveurs and marchands de porcs. D\u00e9molition d\u00b4immeubles and terrassements",
    "sg:phone":"+32 51 65 50 92",
    "sg:postcode":"8750",
    "sg:province":"West-Vlaanderen",
    "wof:name":"Jozef Loontjens",
    "wof:placetype":"venue"
},
  "geometry": {"coordinates":[3.2397019863,51.0657119751],"type":"Point"}
}