{
  "type": "Feature",
  "properties": {
    "iso:country":"BE",
    "sg:address":"Gouddallaan 121",
    "sg:city":"Sint-lambrechts-woluwe/woluwe-saint-lambert",
    "sg:orig_category":"Artsen and specialisten",
    "sg:phone":"+32 2 771 42 99",
    "sg:postcode":"1200",
    "sg:province":"Bruxelles-Capitale",
    "wof:name":"Th\u00c9odore Gillet",
    "wof:placetype":"venue"
},
  "geometry": {"coordinates":[4.4237728119,50.8395271301],"type":"Point"}
}