{
  "type": "Feature",
  "properties": {
    "addr:full":"Kuipersstraat 14 Waregem West-Vlaanderen 8790",
    "addr:housenumber":"14",
    "addr:postcode":"8790",
    "addr:street":"Kuipersstraat",
    "iso:country":"BE",
    "sg:address":"Kuipersstraat 14",
    "sg:city":"Waregem",
    "sg:classifiers":[
        {
            "category":"Arena",
            "subcategory":"Sports Club",
            "type":"Entertainment"
        }
    ],
    "sg:phone":"+32 56 60 87 59",
    "sg:postcode":"8790",
    "sg:province":"West-Vlaanderen",
    "sg:tags":[
        "de"
    ],
    "wof:name":"K.s. Waregem",
    "wof:placetype":"venue"
},
  "geometry": {"coordinates":[3.4262809753,50.8762817383],"type":"Point"}
}