{
  "type": "Feature",
  "properties": {
    "addr:full":"Isabella Brantstraat 64 Antwerpen Antwerpen 2018",
    "addr:housenumber":"64",
    "addr:postcode":"2018",
    "addr:street":"Brantstraat",
    "iso:country":"BE",
    "sg:address":"Isabella Brantstraat 64",
    "sg:city":"Antwerpen",
    "sg:classifiers":[
        {
            "category":"Shopping",
            "subcategory":"Discount & Variety Stores",
            "type":"Retail Goods"
        }
    ],
    "sg:phone":"+32 3 257 35 86",
    "sg:postcode":"2018",
    "sg:province":"Antwerpen",
    "sg:tags":[
        "shop",
        "night"
    ],
    "wof:name":"Lekker Voedingshop",
    "wof:placetype":"venue"
},
  "geometry": {"coordinates":[4.4045538902,51.2050094604],"type":"Point"}
}