{
  "type": "Feature",
  "properties": {
    "addr:full":"Schoolstraat Meerhout Antwerpen 2450",
    "addr:postcode":"2450",
    "addr:street":"Schoolstraat",
    "iso:country":"BE",
    "sg:address":"Schoolstraat",
    "sg:city":"Meerhout",
    "sg:classifiers":[
        {
            "category":"Fast Food",
            "type":"Food & Drink"
        }
    ],
    "sg:phone":"+32 14 30 37 30",
    "sg:postcode":"2450",
    "sg:province":"Antwerpen",
    "sg:tags":[
        "fried",
        "stand",
        "potato"
    ],
    "wof:name":"Cram (de)",
    "wof:placetype":"venue"
},
  "geometry": {"coordinates":[5.0781049728,51.1269798279],"type":"Point"}
}