{
  "type": "Feature",
  "properties": {
    "iso:country":"BE",
    "sg:address":"Rue Du Ch\u00eanois 196",
    "sg:city":"Charleroi (lodelinsart)",
    "sg:classifiers":[
        {
            "category":"Professional",
            "subcategory":"Accounting & Tax Preparation",
            "type":"Services"
        }
    ],
    "sg:phone":"+32 71 30 98 13",
    "sg:postcode":"6042",
    "sg:province":"Hainaut",
    "sg:tags":[
        "bookkeeper"
    ],
    "wof:name":"Fabiocchi C",
    "wof:placetype":"venue"
},
  "geometry": {"coordinates":[4.4436650276,50.4257469177],"type":"Point"}
}