{
  "type": "Feature",
  "properties": {
    "iso:country":"BE",
    "sg:address":"Geinsteindestraat 3",
    "sg:city":"Sint-gillis-waas",
    "sg:orig_category":"Eleveurs and marchands de porcs",
    "sg:phone":"+32 3 776 88 46",
    "sg:postcode":"9170",
    "sg:province":"Oost-Vlaanderen",
    "wof:name":"Rene Buys",
    "wof:placetype":"venue"
},
  "geometry": {"coordinates":[4.1245989799,51.1952590942],"type":"Point"}
}