{
  "type": "Feature",
  "properties": {
    "iso:country":"BE",
    "sg:address":"Rue De Velroux 340",
    "sg:city":"Gr\u00c2ce-hollogne",
    "sg:orig_category":"Benzinestations and brandstoffen",
    "sg:phone":"+32 4 250 31 97",
    "sg:postcode":"4460",
    "sg:province":"Li\u00e8ge",
    "wof:name":"Jean-baptiste Guglielmi",
    "wof:placetype":"venue"
},
  "geometry": {"coordinates":[5.4264068604,50.6394767761],"type":"Point"}
}