{
  "type": "Feature",
  "properties": {
    "addr:full":"Rue De Locht 77 Box 7 Bruxelles (schaerbeek) Bruxelles-Capitale 1030",
    "addr:housenumber":"77;7",
    "addr:postcode":"1030",
    "addr:street":"Rue De Locht;Box",
    "iso:country":"BE",
    "sg:address":"Rue De Locht 77 Box 7",
    "sg:city":"Bruxelles (schaerbeek)",
    "sg:classifiers":[
        {
            "category":"Professional",
            "subcategory":"Art Services",
            "type":"Services"
        }
    ],
    "sg:phone":"+32 2 241 32 66",
    "sg:postcode":"1030",
    "sg:province":"Bruxelles-Capitale",
    "sg:tags":[
        "graphic",
        "designer"
    ],
    "wof:name":"Swennen J",
    "wof:placetype":"venue"
},
  "geometry": {"coordinates":[4.3708519936,50.8638877869],"type":"Point"}
}