{
  "type": "Feature",
  "properties": {
    "iso:country":"BE",
    "sg:address":"Reharmont 4",
    "sg:city":"Lierneux",
    "sg:classifiers":[
        {
            "category":"Government",
            "subcategory":"Department Of Motor Vehicles",
            "type":"Public Place"
        }
    ],
    "sg:phone":"+32 80 68 47 43",
    "sg:postcode":"4990",
    "sg:province":"Li\u00e8ge",
    "sg:tags":[
        "planing",
        "wood",
        "sawing"
    ],
    "wof:name":"Hebert G",
    "wof:placetype":"venue"
},
  "geometry": {"coordinates":[5.7939682007,50.2831878662],"type":"Point"}
}