{
  "type": "Feature",
  "properties": {
    "addr:full":"Jan Vanderghotelaan 5 Ieper West-Vlaanderen 8900",
    "addr:housenumber":"5",
    "addr:postcode":"8900",
    "addr:street":"Vanderghotelaan",
    "iso:country":"BE",
    "sg:address":"Jan Vanderghotelaan 5",
    "sg:city":"Ieper",
    "sg:orig_category":"Advocaten and juridische adviseurs",
    "sg:phone":"+32 57 20 16 48",
    "sg:postcode":"8900",
    "sg:province":"West-Vlaanderen",
    "wof:name":"M. Snick",
    "wof:placetype":"venue"
},
  "geometry": {"coordinates":[2.8803520203,50.8555107117],"type":"Point"}
}