{
  "type": "Feature",
  "properties": {
    "addr:full":"Markt 15 Gistel West-Vlaanderen 8470",
    "addr:housenumber":"15",
    "addr:postcode":"8470",
    "addr:street":"Markt",
    "iso:country":"BE",
    "sg:address":"Markt 15",
    "sg:city":"Gistel",
    "sg:orig_category":"Supermarkten",
    "sg:phone":"+32 59 27 94 38",
    "sg:postcode":"8470",
    "sg:province":"West-Vlaanderen",
    "wof:name":"Unic",
    "wof:placetype":"venue"
},
  "geometry": {"coordinates":[2.9678709507,51.1561698914],"type":"Point"}
}