{
  "type": "Feature",
  "properties": {
    "addr:full":"Markt 79 Eeklo Oost-Vlaanderen 9900",
    "addr:housenumber":"79",
    "addr:postcode":"9900",
    "addr:street":"Markt",
    "iso:country":"BE",
    "sg:address":"Markt 79",
    "sg:city":"Eeklo",
    "sg:orig_category":"Disquaires. Instruments de musique",
    "sg:phone":"+32 9 377 35 73",
    "sg:postcode":"9900",
    "sg:province":"Oost-Vlaanderen",
    "wof:name":"Matthys Music",
    "wof:placetype":"venue"
},
  "geometry": {"coordinates":[3.5643110275,51.1848716736],"type":"Point"}
}