{
  "type": "Feature",
  "properties": {
    "addr:full":"Avenue Centrale 60 Charleroi Hainaut 6001",
    "addr:housenumber":"60",
    "addr:postcode":"6001",
    "addr:street":"Avenue Centrale;Hainaut",
    "iso:country":"BE",
    "sg:address":"Avenue Centrale 60",
    "sg:city":"Charleroi",
    "sg:orig_category":"Plomberie, chauffage and installations sanitaires",
    "sg:phone":"+32 71 43 28 15",
    "sg:postcode":"6001",
    "sg:province":"Hainaut",
    "wof:name":"Andre Cultiaux",
    "wof:placetype":"venue"
},
  "geometry": {"coordinates":[4.4358248711,50.3532981873],"type":"Point"}
}