{
  "type": "Feature",
  "properties": {
    "iso:country":"BE",
    "sg:address":"Baanstknokstraat 76",
    "sg:city":"Waregem",
    "sg:orig_category":"Pain, p\u00e2tisseries and confiseries",
    "sg:phone":"+32 56 60 66 18",
    "sg:postcode":"8790",
    "sg:province":"West-Vlaanderen",
    "wof:name":"Claudine Duchi",
    "wof:placetype":"venue"
},
  "geometry": {"coordinates":[3.4107980728,50.8920974731],"type":"Point"}
}