{
  "type": "Feature",
  "properties": {
    "addr:full":"Jardin-de-bruges 15 Bastogne Luxembourg 6600",
    "addr:housenumber":"15",
    "addr:postcode":"6600",
    "addr:street":"Jardin-De-Bruges",
    "iso:country":"BE",
    "sg:address":"Jardin-de-bruges 15",
    "sg:city":"Bastogne",
    "sg:orig_category":"Radioproductie and uitzendingen",
    "sg:phone":"+32 61 21 33 69",
    "sg:postcode":"6600",
    "sg:province":"Luxembourg",
    "wof:name":"Radio Nostalgie",
    "wof:placetype":"venue"
},
  "geometry": {"coordinates":[5.724905014,50.0089874268],"type":"Point"}
}