{
  "type": "Feature",
  "properties": {
    "addr:full":"Rue De Bois-de-breux 565 Li\u00e8ge 1 (jupille-sur-meuse) Li\u00e8ge 4020",
    "addr:housenumber":"565;1",
    "addr:postcode":"4020",
    "addr:street":"Rue De Bois-De-Breux;Jupille-Sur-Meuse Lie\u0300Ge",
    "iso:country":"BE",
    "sg:address":"Rue De Bois-de-breux 565",
    "sg:city":"Li\u00e8ge 1 (jupille-sur-meuse)",
    "sg:classifiers":[
        {
            "category":"Banks & Credit Unions",
            "subcategory":"Investment Brokerage",
            "type":"Services"
        }
    ],
    "sg:phone":"+32 4 365 42 53",
    "sg:postcode":"4020",
    "sg:province":"Li\u00e8ge",
    "sg:tags":[
        "fence"
    ],
    "wof:name":"Fellen G",
    "wof:placetype":"venue"
},
  "geometry": {"coordinates":[5.6286492348,50.6353416443],"type":"Point"}
}