{
  "type": "Feature",
  "properties": {
    "addr:full":"Kerkstraat 37 Sint-lievens-houtem (letterhoutem) Oost-Vlaanderen 9521",
    "addr:housenumber":"37",
    "addr:postcode":"9521",
    "addr:street":"Kerkstraat",
    "iso:country":"BE",
    "sg:address":"Kerkstraat 37",
    "sg:city":"Sint-lievens-houtem (letterhoutem)",
    "sg:classifiers":[
        {
            "category":"Health Services",
            "subcategory":"Health Practitioner",
            "type":"Services"
        }
    ],
    "sg:phone":"+32 478 34 22 80",
    "sg:postcode":"9521",
    "sg:province":"Oost-Vlaanderen",
    "sg:tags":[
        "physiotherapist"
    ],
    "wof:name":"Van Geert Isabel",
    "wof:placetype":"venue"
},
  "geometry": {"coordinates":[3.880753994,50.9286193848],"type":"Point"}
}