{
  "type": "Feature",
  "properties": {
    "addr:full":"Opheersstraat 89 Heers (groot) Limburg 3870",
    "addr:housenumber":"89",
    "addr:postcode":"3870",
    "addr:street":"Opheersstraat;Groot Limburg",
    "iso:country":"BE",
    "sg:address":"Opheersstraat 89",
    "sg:city":"Heers (groot)",
    "sg:classifiers":[
        {
            "category":"Travel",
            "subcategory":"Hotels & Motels",
            "type":"Entertainment"
        }
    ],
    "sg:phone":"+32 11 48 24 94",
    "sg:postcode":"3870",
    "sg:province":"Limburg",
    "wof:name":"Emporium Antiquum",
    "wof:placetype":"venue"
},
  "geometry": {"coordinates":[5.2985401154,50.7415885925],"type":"Point"}
}