{
  "type": "Feature",
  "properties": {
    "iso:country":"BE",
    "sg:address":"Major-long-strasse 1",
    "sg:city":"Sankt Vith",
    "sg:orig_category":"Non-Classified Establishments",
    "sg:phone":"+32 80 22 85 23",
    "sg:postcode":"4780",
    "sg:province":"Li\u00e8ge",
    "wof:name":"Centres Pms Provinciaux",
    "wof:placetype":"venue"
},
  "geometry": {"coordinates":[6.1269021034,50.279800415],"type":"Point"}
}