{
  "type": "Feature",
  "properties": {
    "addr:full":"Rue Neuville 33 Olne Li\u00e8ge 4877",
    "addr:housenumber":"33",
    "addr:postcode":"4877",
    "addr:street":"Rue Neuville",
    "iso:country":"BE",
    "sg:address":"Rue Neuville 33",
    "sg:city":"Olne",
    "sg:classifiers":[
        {
            "category":"Health Services",
            "subcategory":"Health Practitioner",
            "type":"Services"
        }
    ],
    "sg:phone":"+32 4 358 74 76",
    "sg:postcode":"4877",
    "sg:province":"Li\u00e8ge",
    "sg:tags":[
        "physiotherapist"
    ],
    "wof:name":"Garin Jean-pierre",
    "wof:placetype":"venue"
},
  "geometry": {"coordinates":[5.7172050476,50.5970687866],"type":"Point"}
}