{
  "type": "Feature",
  "properties": {
    "iso:country":"BE",
    "sg:address":"Sint-niklaasdreef 5",
    "sg:city":"Menen (rekkem)",
    "sg:classifiers":[
        {
            "category":"Food & Beverages",
            "subcategory":"Dairy",
            "type":"Retail Goods"
        }
    ],
    "sg:phone":"+32 56 41 14 54",
    "sg:postcode":"8930",
    "sg:province":"West-Vlaanderen",
    "sg:tags":[
        "product",
        "-"
    ],
    "wof:name":"Wyseur P",
    "wof:placetype":"venue"
},
  "geometry": {"coordinates":[3.158010006,50.7839546204],"type":"Point"}
}