{
  "type": "Feature",
  "properties": {
    "addr:full":"Ieperstraat 190a Poperinge West-Vlaanderen 8970",
    "addr:housenumber":"190a",
    "addr:postcode":"8970",
    "addr:street":"Ieperstraat",
    "iso:country":"BE",
    "sg:address":"Ieperstraat 190a",
    "sg:city":"Poperinge",
    "sg:orig_category":"Notarissen",
    "sg:phone":"+32 57 33 32 70",
    "sg:postcode":"8970",
    "sg:province":"West-Vlaanderen",
    "wof:name":"Jean-marie Lahaye",
    "wof:placetype":"venue"
},
  "geometry": {"coordinates":[2.7396059036,50.8550453186],"type":"Point"}
}