{
  "type": "Feature",
  "properties": {
    "addr:full":"Kolmenstraat 1238 Alken Limburg 3570",
    "addr:housenumber":"1238",
    "addr:postcode":"3570",
    "addr:street":"Kolmenstraat",
    "iso:country":"BE",
    "sg:address":"Kolmenstraat 1238",
    "sg:city":"Alken",
    "sg:classifiers":[
        {
            "category":"Professional",
            "subcategory":"Art Services",
            "type":"Services"
        }
    ],
    "sg:phone":"+32 11 59 24 60",
    "sg:postcode":"3570",
    "sg:province":"Limburg",
    "sg:tags":[
        "shop",
        "paint",
        "spraying"
    ],
    "wof:name":"Pigment Bvba",
    "wof:placetype":"venue"
},
  "geometry": {"coordinates":[5.2973351479,50.8867645264],"type":"Point"}
}