{
  "type": "Feature",
  "properties": {
    "iso:country":"BE",
    "sg:address":"Chaussee Romaine 6",
    "sg:city":"Oreye",
    "sg:orig_category":"X-Ray Equipment For Physical X-Rays",
    "sg:phone":"+32 19 67 82 11",
    "sg:postcode":"4360",
    "sg:province":"Li\u00e8ge",
    "wof:name":"M.i.c. S.a.",
    "wof:placetype":"venue"
},
  "geometry": {"coordinates":[5.3468799591,50.7322616577],"type":"Point"}
}