{
  "type": "Feature",
  "properties": {
    "addr:full":"Avenue Bouvier 2 Virton Luxembourg 6760",
    "addr:housenumber":"2",
    "addr:postcode":"6760",
    "addr:street":"Avenue Bouvier",
    "iso:country":"BE",
    "sg:address":"Avenue Bouvier 2",
    "sg:city":"Virton",
    "sg:classifiers":[
        {
            "category":"Shopping",
            "subcategory":"Clothing, Apparel, & Fashions",
            "type":"Retail Goods"
        }
    ],
    "sg:phone":"+32 63 57 08 60",
    "sg:postcode":"6760",
    "sg:province":"Luxembourg",
    "sg:tags":[
        "lady",
        "clothing",
        "-"
    ],
    "wof:name":"Bonnie & Clyde",
    "wof:placetype":"venue"
},
  "geometry": {"coordinates":[5.530834198,49.5673103333],"type":"Point"}
}