{
  "type": "Feature",
  "properties": {
    "addr:full":"Rue De Rengies 72 Peruwelz Hainaut 7608",
    "addr:housenumber":"72",
    "addr:postcode":"7608",
    "addr:street":"Rue De Rengies;Hainaut",
    "iso:country":"BE",
    "sg:address":"Rue De Rengies 72",
    "sg:city":"Peruwelz",
    "sg:classifiers":[
        {
            "category":"Fast Food",
            "type":"Food & Drink"
        }
    ],
    "sg:phone":"+32 69 77 52 50",
    "sg:postcode":"7608",
    "sg:province":"Hainaut",
    "sg:tags":[
        "\u00c0",
        "emporter",
        "restaurants"
    ],
    "wof:name":"Pierre Marchandise",
    "wof:placetype":"venue"
},
  "geometry": {"coordinates":[3.5567679405,50.5002670288],"type":"Point"}
}