{
  "type": "Feature",
  "properties": {
    "iso:country":"BE",
    "sg:address":"Rue De Lodelinsart 6",
    "sg:city":"Charleroi (montignies-sur-sambre)",
    "sg:classifiers":[
        {
            "category":"Shopping",
            "subcategory":"Stationery & Office Supplies",
            "type":"Retail Goods"
        }
    ],
    "sg:phone":"+32 71 42 07 24",
    "sg:postcode":"6061",
    "sg:province":"Hainaut",
    "sg:tags":[
        "partition"
    ],
    "wof:name":"A. Gnoffo",
    "wof:placetype":"venue"
},
  "geometry": {"coordinates":[4.4684348106,50.4121170044],"type":"Point"}
}