{
  "type": "Feature",
  "properties": {
    "addr:full":"Rue Marcel Tonglet 7 Beaumont Hainaut 6500",
    "addr:housenumber":"7",
    "addr:postcode":"6500",
    "addr:street":"Rue Marcel Tonglet;Hainaut",
    "iso:country":"BE",
    "sg:address":"Rue Marcel Tonglet 7",
    "sg:city":"Beaumont",
    "sg:classifiers":[
        {
            "category":"Health Services",
            "subcategory":"Nursing And Care Facility",
            "type":"Services"
        }
    ],
    "sg:phone":"+32 71 58 81 37",
    "sg:postcode":"6500",
    "sg:province":"Hainaut",
    "sg:tags":[
        "home",
        "rest"
    ],
    "wof:name":"Home Saint-joseph",
    "wof:placetype":"venue"
},
  "geometry": {"coordinates":[4.2392339706,50.2340278625],"type":"Point"}
}