{
  "type": "Feature",
  "properties": {
    "addr:full":"Beernemstraat 5a Wingene West-Vlaanderen 8750",
    "addr:housenumber":"5a",
    "addr:postcode":"8750",
    "addr:street":"Beernemstraat",
    "iso:country":"BE",
    "sg:address":"Beernemstraat 5a",
    "sg:city":"Wingene",
    "sg:classifiers":[
        {
            "category":"Home & Garden",
            "subcategory":"Carpets & Floor Coverings",
            "type":"Retail Goods"
        }
    ],
    "sg:postcode":"8750",
    "sg:province":"West-Vlaanderen",
    "sg:tags":[
        "parquet"
    ],
    "wof:name":"Oosthout",
    "wof:placetype":"venue"
},
  "geometry": {"coordinates":[3.2751290798,51.0596122742],"type":"Point"}
}