{
  "type": "Feature",
  "properties": {
    "addr:full":"Houbaertstraat 1 Tienen (hakendover) Vlaams-Brabant 3300",
    "addr:housenumber":"1",
    "addr:postcode":"3300",
    "addr:street":"Houbaertstraat",
    "iso:country":"BE",
    "sg:address":"Houbaertstraat 1",
    "sg:city":"Tienen (hakendover)",
    "sg:classifiers":[
        {
            "category":"Insurance",
            "subcategory":"Insurance Agent",
            "type":"Services"
        }
    ],
    "sg:phone":"+32 16 78 86 00",
    "sg:postcode":"3300",
    "sg:province":"Vlaams-Brabant",
    "sg:tags":[
        "broker"
    ],
    "wof:name":"Grossen-vandenputte & Zn",
    "wof:placetype":"venue"
},
  "geometry": {"coordinates":[4.930077076,50.8096694946],"type":"Point"}
}