{
  "type": "Feature",
  "properties": {
    "addr:full":"Turnhoutsebaan 5b179 Wijnegem Antwerpen 2110",
    "addr:housenumber":"5b179",
    "addr:postcode":"2110",
    "addr:street":"Turnhoutsebaan",
    "iso:country":"BE",
    "sg:address":"Turnhoutsebaan 5b179",
    "sg:city":"Wijnegem",
    "sg:orig_category":"Pain, p\u00e2tisseries and confiseries",
    "sg:phone":"+32 3 353 39 71",
    "sg:postcode":"2110",
    "sg:province":"Antwerpen",
    "wof:name":"De Soeteninval",
    "wof:placetype":"venue"
},
  "geometry": {"coordinates":[4.5043401718,51.2240219116],"type":"Point"}
}