{
  "type": "Feature",
  "properties": {
    "addr:full":"Ieperseaardeweg 30 Roeselare West-Vlaanderen 8800",
    "addr:housenumber":"30",
    "addr:postcode":"8800",
    "addr:street":"Ieperseaardeweg",
    "iso:country":"BE",
    "sg:address":"Ieperseaardeweg 30",
    "sg:city":"Roeselare",
    "sg:orig_category":"Boucheries",
    "sg:phone":"+32 51 20 17 79",
    "sg:postcode":"8800",
    "sg:province":"West-Vlaanderen",
    "wof:name":"Robert Stols",
    "wof:placetype":"venue"
},
  "geometry": {"coordinates":[3.0891020298,50.9298553467],"type":"Point"}
}