{
  "type": "Feature",
  "properties": {
    "addr:full":"Hoeksken 37 Evergem Oost-Vlaanderen 9940",
    "addr:housenumber":"37",
    "addr:postcode":"9940",
    "addr:street":"Hoeksken;Oost-Vlaanderen",
    "iso:country":"BE",
    "sg:address":"Hoeksken 37",
    "sg:city":"Evergem",
    "sg:classifiers":[
        {
            "category":"Bars & Pubs",
            "type":"Food & Drink"
        }
    ],
    "sg:phone":"+32 9 253 00 44",
    "sg:postcode":"9940",
    "sg:province":"Oost-Vlaanderen",
    "wof:name":"Little Bighorn Saloon Vzw",
    "wof:placetype":"venue"
},
  "geometry": {"coordinates":[3.7051999569,51.1104927063],"type":"Point"}
}