{
  "type": "Feature",
  "properties": {
    "addr:full":"Begonialaan 7 Lebbeke Oost-Vlaanderen 9280",
    "addr:housenumber":"7",
    "addr:postcode":"9280",
    "addr:street":"Begonialaan",
    "iso:country":"BE",
    "sg:address":"Begonialaan 7",
    "sg:city":"Lebbeke",
    "sg:orig_category":"Administration d'immeubles",
    "sg:phone":"+32 52 41 17 84",
    "sg:postcode":"9280",
    "sg:province":"Oost-Vlaanderen",
    "wof:name":"Roland Van Den Borre",
    "wof:placetype":"venue"
},
  "geometry": {"coordinates":[4.1400098801,50.992477417],"type":"Point"}
}