{
  "type": "Feature",
  "properties": {
    "addr:full":"Vrijdagmarkt 14 Brugge West-Vlaanderen 8000",
    "addr:housenumber":"14",
    "addr:postcode":"8000",
    "addr:street":"Vrijdagmarkt",
    "iso:country":"BE",
    "sg:address":"Vrijdagmarkt 14",
    "sg:city":"Brugge",
    "sg:orig_category":"Banques and organismes de cr\u00e9dit",
    "sg:phone":"+32 50 34 18 34",
    "sg:postcode":"8000",
    "sg:province":"West-Vlaanderen",
    "wof:name":"Kbc",
    "wof:placetype":"venue"
},
  "geometry": {"coordinates":[3.2166879177,51.2053642273],"type":"Point"}
}