{
  "type": "Feature",
  "properties": {
    "iso:country":"BE",
    "sg:address":"Brusselsesteenweg 439",
    "sg:city":"Merchtem",
    "sg:orig_category":"Groententeelt",
    "sg:phone":"+32 2 460 26 47",
    "sg:postcode":"1785",
    "sg:province":"Vlaams-Brabant",
    "wof:name":"Franciscus Raes",
    "wof:placetype":"venue"
},
  "geometry": {"coordinates":[4.2854061127,50.9195365906],"type":"Point"}
}