{
  "type": "Feature",
  "properties": {
    "iso:country":"BE",
    "sg:address":"Brouwerijstraat 15",
    "sg:city":"Mechelen",
    "sg:orig_category":"Agences de publicit\u00e9",
    "sg:phone":"+32 15 27 37 77",
    "sg:postcode":"2801",
    "sg:province":"Antwerpen",
    "wof:name":"Grafisch Buro Paul Van Dijck",
    "wof:placetype":"venue"
},
  "geometry": {"coordinates":[4.4176468849,51.0474700928],"type":"Point"}
}