{
  "type": "Feature",
  "properties": {
    "iso:country":"BE",
    "sg:address":"La Bouchaille 236",
    "sg:city":"Ohey",
    "sg:orig_category":"Rundveehouders",
    "sg:phone":"+32 85 61 12 71",
    "sg:postcode":"5350",
    "sg:province":"Namur",
    "wof:name":"Leopold Dethier",
    "wof:placetype":"venue"
},
  "geometry": {"coordinates":[5.1410851479,50.4174385071],"type":"Point"}
}