{
  "type": "Feature",
  "properties": {
    "addr:full":"Chauss\u00e9e De Li\u00e8ge 166 Namur (jambes) Namur 5100",
    "addr:housenumber":"166",
    "addr:postcode":"5100",
    "addr:street":"Chausse\u0301E De Lie\u0300Ge",
    "iso:country":"BE",
    "sg:address":"Chauss\u00e9e De Li\u00e8ge 166",
    "sg:city":"Namur (jambes)",
    "sg:classifiers":[
        {
            "category":"Health Services",
            "subcategory":"Medical Lab",
            "type":"Services"
        }
    ],
    "sg:phone":"+32 81 30 35 58",
    "sg:postcode":"5100",
    "sg:province":"Namur",
    "sg:tags":[
        "laboratory",
        "dental"
    ],
    "wof:name":"Legat J",
    "wof:placetype":"venue"
},
  "geometry": {"coordinates":[4.8713750839,50.4566345215],"type":"Point"}
}