{
  "type": "Feature",
  "properties": {
    "iso:country":"BE",
    "sg:address":"Rue De Nieuwenhove 84",
    "sg:city":"Bruxelles",
    "sg:classifiers":[
        {
            "category":"Professional",
            "subcategory":"Advertising",
            "type":"Services"
        }
    ],
    "sg:phone":"+32 2 345 90 71",
    "sg:postcode":"1180",
    "sg:province":"Bruxelles-Capitale",
    "sg:tags":[
        "imprint"
    ],
    "wof:name":"Brodfactory S.p.r.l.",
    "wof:placetype":"venue"
},
  "geometry": {"coordinates":[4.3369841576,50.8008880615],"type":"Point"}
}