{
  "type": "Feature",
  "properties": {
    "addr:full":"Rue Alphonse De Witte 54 Bruxelles (ixelles) Bruxelles-Capitale 1050",
    "addr:housenumber":"54",
    "addr:postcode":"1050",
    "addr:street":"Rue Alphonse De Witte",
    "iso:country":"BE",
    "sg:address":"Rue Alphonse De Witte 54",
    "sg:city":"Bruxelles (ixelles)",
    "sg:classifiers":[
        {
            "category":"Professional",
            "subcategory":"Testing Lab",
            "type":"Services"
        }
    ],
    "sg:phone":"+32 2 647 00 42",
    "sg:postcode":"1050",
    "sg:province":"Bruxelles-Capitale",
    "sg:tags":[
        "chemist"
    ],
    "wof:name":"Goffin H",
    "wof:placetype":"venue"
},
  "geometry": {"coordinates":[4.3740258217,50.8254241943],"type":"Point"}
}