{
  "type": "Feature",
  "properties": {
    "iso:country":"BE",
    "sg:address":"Parc Industriel Cahottes 2",
    "sg:city":"Flemalle",
    "sg:orig_category":"Elektrische installaties voor woningen Industri\u00eble elektrische installaties Installatie van metalen ",
    "sg:phone":"+32 4 338 91 82",
    "sg:postcode":"4400",
    "sg:province":"Li\u00e8ge",
    "wof:name":"New Baron & Leveque Int.",
    "wof:placetype":"venue"
},
  "geometry": {"coordinates":[5.434276104,50.6219558716],"type":"Point"}
}