{
  "type": "Feature",
  "properties": {
    "addr:full":"Tennislaan 5 Genk Limburg 3600",
    "addr:housenumber":"5",
    "addr:postcode":"3600",
    "addr:street":"Tennislaan",
    "iso:country":"BE",
    "sg:address":"Tennislaan 5",
    "sg:city":"Genk",
    "sg:orig_category":"Kapsalons",
    "sg:phone":"+32 89 35 02 51",
    "sg:postcode":"3600",
    "sg:province":"Limburg",
    "wof:name":"Marti Coiffure",
    "wof:placetype":"venue"
},
  "geometry": {"coordinates":[5.4775900841,50.965927124],"type":"Point"}
}