{
  "type": "Feature",
  "properties": {
    "iso:country":"BE",
    "sg:address":"Route De Bastogne 41",
    "sg:city":"Martelange",
    "sg:classifiers":[
        {
            "category":"Health Services",
            "subcategory":"Health Practitioner",
            "type":"Services"
        }
    ],
    "sg:phone":"+32 63 60 04 69",
    "sg:postcode":"6630",
    "sg:province":"Luxembourg",
    "sg:tags":[
        "physiotherapist"
    ],
    "wof:name":"Bourdon J-l",
    "wof:placetype":"venue"
},
  "geometry": {"coordinates":[5.7380647659,49.836063385],"type":"Point"}
}