{
  "type": "Feature",
  "properties": {
    "iso:country":"BE",
    "sg:address":"Keizershoek 50",
    "sg:city":"Kontich",
    "sg:orig_category":"Woningbouw",
    "sg:phone":"+32 3 459 82 60",
    "sg:postcode":"2550",
    "sg:province":"Antwerpen",
    "wof:name":"Ben De Klusser",
    "wof:placetype":"venue"
},
  "geometry": {"coordinates":[4.4395470619,51.1297798157],"type":"Point"}
}