{
  "type": "Feature",
  "properties": {
    "addr:full":"Rue Du Sablon 195 Bastogne Luxembourg 6600",
    "addr:housenumber":"195",
    "addr:postcode":"6600",
    "addr:street":"Rue Du Sablon",
    "iso:country":"BE",
    "sg:address":"Rue Du Sablon 195",
    "sg:city":"Bastogne",
    "sg:classifiers":[
        {
            "category":"Bars & Pubs",
            "type":"Food & Drink"
        }
    ],
    "sg:phone":"+32 61 21 15 48",
    "sg:postcode":"6600",
    "sg:province":"Luxembourg",
    "wof:name":"Patton (le)",
    "wof:placetype":"venue"
},
  "geometry": {"coordinates":[5.7203397751,50.0047454834],"type":"Point"}
}