{
  "type": "Feature",
  "properties": {
    "iso:country":"BE",
    "sg:address":"Hooimanstraat 124",
    "sg:city":"Sint-niklaas",
    "sg:orig_category":"Diverse bedrijfsbeheeradviesbureaus",
    "sg:phone":"+32 3 722 00 30",
    "sg:postcode":"9112",
    "sg:province":"Oost-Vlaanderen",
    "wof:name":"Rvd Securities",
    "wof:placetype":"venue"
},
  "geometry": {"coordinates":[4.0568580627,51.1499137878],"type":"Point"}
}