{
  "type": "Feature",
  "properties": {
    "iso:country":"BE",
    "sg:address":"Canadalaan 47",
    "sg:city":"Mol",
    "sg:classifiers":[
        {
            "category":"Health Services",
            "subcategory":"Health Practitioner",
            "type":"Services"
        }
    ],
    "sg:phone":"+32 14 81 10 74",
    "sg:postcode":"2400",
    "sg:province":"Antwerpen",
    "sg:tags":[
        "physiotherapist"
    ],
    "wof:name":"Geenen Lisette",
    "wof:placetype":"venue"
},
  "geometry": {"coordinates":[5.2098221779,51.2194099426],"type":"Point"}
}