{
  "type": "Feature",
  "properties": {
    "addr:full":"Vilvoordsesteenweg 107 Steenokkerzeel (perk) Vlaams-Brabant 1820",
    "addr:housenumber":"107",
    "addr:postcode":"1820",
    "addr:street":"Vilvoordsesteenweg",
    "iso:country":"BE",
    "sg:address":"Vilvoordsesteenweg 107",
    "sg:city":"Steenokkerzeel (perk)",
    "sg:classifiers":[
        {
            "category":"Communications",
            "subcategory":"Television Station",
            "type":"Services"
        }
    ],
    "sg:phone":"+32 2 751 87 49",
    "sg:postcode":"1820",
    "sg:province":"Vlaams-Brabant",
    "sg:tags":[
        "organ"
    ],
    "wof:name":"Koekoekx G",
    "wof:placetype":"venue"
},
  "geometry": {"coordinates":[4.4877800941,50.9348106384],"type":"Point"}
}