{
  "type": "Feature",
  "properties": {
    "iso:country":"BE",
    "sg:address":"Mortierstraat 13a",
    "sg:city":"Nevele",
    "sg:orig_category":"Installation de menuiserie en bois and plastique",
    "sg:phone":"+32 9 371 67 90",
    "sg:postcode":"9850",
    "sg:province":"Oost-Vlaanderen",
    "wof:name":"Van Wonterghem",
    "wof:placetype":"venue"
},
  "geometry": {"coordinates":[3.5016229153,51.0310058594],"type":"Point"}
}