{
  "type": "Feature",
  "properties": {
    "addr:full":"Emiel Lossystraat 86 Gent Oost-Vlaanderen 9040",
    "addr:housenumber":"86",
    "addr:postcode":"9040",
    "addr:street":"Emiel Lossystraat;Oost-Vlaanderen",
    "iso:country":"BE",
    "sg:address":"Emiel Lossystraat 86",
    "sg:city":"Gent",
    "sg:orig_category":"Medische apparatuur, orthopedische artikelen and prothesen Fab",
    "sg:phone":"+32 9 228 60 97",
    "sg:postcode":"9040",
    "sg:province":"Oost-Vlaanderen",
    "wof:name":"Gilbert De Craene",
    "wof:placetype":"venue"
},
  "geometry": {"coordinates":[3.7597000599,51.0494499207],"type":"Point"}
}