{
  "type": "Feature",
  "properties": {
    "iso:country":"BE",
    "sg:address":"Petite Rue 43",
    "sg:city":"Mouscron",
    "sg:classifiers":[
        {
            "category":"Shopping",
            "subcategory":"Clothing, Apparel, & Fashions",
            "type":"Retail Goods"
        }
    ],
    "sg:phone":"+32 56 33 04 88",
    "sg:postcode":"7700",
    "sg:province":"Hainaut",
    "sg:tags":[
        "underwear",
        "lingerie",
        "-"
    ],
    "wof:name":"Celine (lingerie)",
    "wof:placetype":"venue"
},
  "geometry": {"coordinates":[3.211824894,50.7442893982],"type":"Point"}
}