{
  "type": "Feature",
  "properties": {
    "iso:country":"BE",
    "sg:address":"Chauss\u00c9e De Charleroi 7",
    "sg:city":"Lasne",
    "sg:orig_category":"Installation de piscines. Souvenirs and objets artisanaux. Articles de jardin. Plomberie, chauffage ",
    "sg:phone":"+32 2 384 36 36",
    "sg:postcode":"1380",
    "sg:province":"Brabant Wallon",
    "wof:name":"Jardinconfort",
    "wof:placetype":"venue"
},
  "geometry": {"coordinates":[4.413807869,50.6637611389],"type":"Point"}
}