{
  "type": "Feature",
  "properties": {
    "iso:country":"BE",
    "sg:address":"Switch Road 52",
    "sg:city":"Poperinge",
    "sg:orig_category":"Agences de presse",
    "sg:phone":"+32 57 33 61 43",
    "sg:postcode":"8970",
    "sg:province":"West-Vlaanderen",
    "wof:name":"Paul Samyn",
    "wof:placetype":"venue"
},
  "geometry": {"coordinates":[2.7383289337,50.8588142395],"type":"Point"}
}