{
  "type": "Feature",
  "properties": {
    "iso:country":"BE",
    "sg:address":"Stalingradlaan 58",
    "sg:city":"Brussel/bruxelles",
    "sg:orig_category":"Modellenbureaus",
    "sg:phone":"+32 2 511 69 10",
    "sg:postcode":"1000",
    "sg:province":"Bruxelles-Capitale",
    "wof:name":"Steff Model Management",
    "wof:placetype":"venue"
},
  "geometry": {"coordinates":[4.3439640999,50.8410644531],"type":"Point"}
}