{
  "type": "Feature",
  "properties": {
    "iso:country":"BE",
    "sg:address":"Waterstraat 18",
    "sg:city":"Geel",
    "sg:orig_category":"Bedrijfscatering",
    "sg:phone":"+32 14 59 32 93",
    "sg:postcode":"2440",
    "sg:province":"Antwerpen",
    "wof:name":"Meresto",
    "wof:placetype":"venue"
},
  "geometry": {"coordinates":[4.988202095,51.156917572],"type":"Point"}
}