{
  "type": "Feature",
  "properties": {
    "iso:country":"BE",
    "sg:address":"Moeresteenweg 18",
    "sg:city":"Veurne",
    "sg:orig_category":"Eleveurs and marchands de porcs. Eleveurs de bovins",
    "sg:phone":"+32 58 29 93 07",
    "sg:postcode":"8630",
    "sg:province":"West-Vlaanderen",
    "wof:name":"Walter Dekervel",
    "wof:placetype":"venue"
},
  "geometry": {"coordinates":[2.6196808815,51.0149879456],"type":"Point"}
}