{
  "type": "Feature",
  "properties": {
    "iso:country":"BE",
    "sg:address":"Rue Du Centre 24",
    "sg:city":"Waimes",
    "sg:orig_category":"Sportclubs Sportterreinen and installaties behalve sportcentra",
    "sg:phone":"+32 80 67 97 55",
    "sg:postcode":"4180",
    "sg:province":"Li\u00e8ge",
    "wof:name":"Tc Waimes",
    "wof:placetype":"venue"
},
  "geometry": {"coordinates":[5.531235218,50.4267807007],"type":"Point"}
}