{
  "type": "Feature",
  "properties": {
    "iso:country":"BE",
    "sg:address":"All\u00c9e De La Cense-rouge 19",
    "sg:city":"Li\u00c8ge",
    "sg:orig_category":"Artsen and specialisten",
    "sg:phone":"+32 4 365 48 02",
    "sg:postcode":"4031",
    "sg:province":"Li\u00e8ge",
    "wof:name":"Jacques Bertrand",
    "wof:placetype":"venue"
},
  "geometry": {"coordinates":[5.5658898354,50.5905418396],"type":"Point"}
}