{
  "type": "Feature",
  "properties": {
    "addr:full":"Avenue Du Bourget 40 Bruxelles Bruxelles-Capitale 1130",
    "addr:housenumber":"40",
    "addr:postcode":"1130",
    "addr:street":"Avenue Du Bourget",
    "iso:country":"BE",
    "sg:address":"Avenue Du Bourget 40",
    "sg:city":"Bruxelles",
    "sg:classifiers":[
        {
            "category":"Professional",
            "subcategory":"Management & Consulting",
            "type":"Services"
        }
    ],
    "sg:phone":"+32 2 708 43 00",
    "sg:postcode":"1130",
    "sg:province":"Bruxelles-Capitale",
    "sg:tags":[
        "consultant"
    ],
    "wof:name":"Kpmg",
    "wof:placetype":"venue"
},
  "geometry": {"coordinates":[4.4316191673,50.8777885437],"type":"Point"}
}