{
  "type": "Feature",
  "properties": {
    "iso:country":"BE",
    "sg:address":"Chauss\u00c9e Du Roeulx 47ba",
    "sg:city":"Mons",
    "sg:orig_category":"Boissons",
    "sg:phone":"+32 65 84 26 32",
    "sg:postcode":"7000",
    "sg:province":"Hainaut",
    "wof:name":"Drink\u00b4s Melchior",
    "wof:placetype":"venue"
},
  "geometry": {"coordinates":[3.9683299065,50.4549598694],"type":"Point"}
}