{
  "type": "Feature",
  "properties": {
    "iso:country":"BE",
    "sg:address":"Van Cauwenberghelaan 23a",
    "sg:city":"Herne",
    "sg:classifiers":[
        {
            "category":"Professional",
            "subcategory":"Management & Consulting",
            "type":"Services"
        }
    ],
    "sg:phone":"+32 2 396 23 58",
    "sg:postcode":"1540",
    "sg:province":"Vlaams-Brabant",
    "sg:tags":[
        "consultant",
        "agency",
        "advertising"
    ],
    "wof:name":"Ls Promotion",
    "wof:placetype":"venue"
},
  "geometry": {"coordinates":[4.0649080276,50.7092628479],"type":"Point"}
}