{
  "type": "Feature",
  "properties": {
    "iso:country":"BE",
    "sg:address":"Guido Gezellestraat 10",
    "sg:city":"Waregem",
    "sg:classifiers":[
        {
            "category":"Retail",
            "subcategory":"Event Space",
            "type":"Services"
        }
    ],
    "sg:phone":"+32 56 61 19 88",
    "sg:postcode":"8790",
    "sg:province":"West-Vlaanderen",
    "sg:tags":[
        "organisation"
    ],
    "wof:name":"Promove Bvba",
    "wof:placetype":"venue"
},
  "geometry": {"coordinates":[3.4360499382,50.8855857849],"type":"Point"}
}