{
  "type": "Feature",
  "properties": {
    "addr:full":"Sint-jozefstraat 66 Lokeren Oost-Vlaanderen 9160",
    "addr:housenumber":"66",
    "addr:postcode":"9160",
    "addr:street":"Sint-Jozefstraat",
    "iso:country":"BE",
    "sg:address":"Sint-jozefstraat 66",
    "sg:city":"Lokeren",
    "sg:orig_category":"Eleveurs and marchands de porcs. Eleveurs de bovins",
    "sg:phone":"+32 9 348 28 86",
    "sg:postcode":"9160",
    "sg:province":"Oost-Vlaanderen",
    "wof:name":"Louis Van Damme",
    "wof:placetype":"venue"
},
  "geometry": {"coordinates":[3.9677839279,51.0879898071],"type":"Point"}
}