{
  "type": "Feature",
  "properties": {
    "addr:full":"Louis Leynstraat 6 Roeselare West-Vlaanderen 8800",
    "addr:housenumber":"6",
    "addr:postcode":"8800",
    "addr:street":"Leynstraat",
    "iso:country":"BE",
    "sg:address":"Louis Leynstraat 6",
    "sg:city":"Roeselare",
    "sg:orig_category":"Plaatsen van vloer- and muurbekleding Woningbouw",
    "sg:phone":"+32 51 20 79 58",
    "sg:postcode":"8800",
    "sg:province":"West-Vlaanderen",
    "wof:name":"Bouwwerken Noel Debal",
    "wof:placetype":"venue"
},
  "geometry": {"coordinates":[3.1486580372,50.9340515137],"type":"Point"}
}