{
  "type": "Feature",
  "properties": {
    "addr:full":"Kalkhoevestraat 1 Waregem West-Vlaanderen 8790",
    "addr:housenumber":"1",
    "addr:postcode":"8790",
    "addr:street":"Kalkhoevestraat",
    "iso:country":"BE",
    "sg:address":"Kalkhoevestraat 1",
    "sg:city":"Waregem",
    "sg:orig_category":"S\u00e9lection de personnel and placement. Formation and enseignement. Bureaux-conseils divers",
    "sg:phone":"+32 56 62 02 56",
    "sg:postcode":"8790",
    "sg:province":"West-Vlaanderen",
    "wof:name":"C.p.o.",
    "wof:placetype":"venue"
},
  "geometry": {"coordinates":[3.4481890202,50.8727493286],"type":"Point"}
}