{
  "type": "Feature",
  "properties": {
    "addr:full":"Craenenbroekstraat 55 Glabbeek Vlaams-Brabant 3380",
    "addr:housenumber":"55",
    "addr:postcode":"3380",
    "addr:street":"Craenenbroekstraat",
    "iso:country":"BE",
    "sg:address":"Craenenbroekstraat 55",
    "sg:city":"Glabbeek",
    "sg:orig_category":"Motorfietsen",
    "sg:phone":"+32 16 77 90 21",
    "sg:postcode":"3380",
    "sg:province":"Vlaams-Brabant",
    "wof:name":"Scooter- En Motorshop Suttels",
    "wof:placetype":"venue"
},
  "geometry": {"coordinates":[4.9559822083,50.8636856079],"type":"Point"}
}