{
  "type": "Feature",
  "properties": {
    "addr:full":"Rue Des Parfums 9 Anderlecht Bruxelles-Capitale 1070",
    "addr:housenumber":"9",
    "addr:postcode":"1070",
    "addr:street":"Rue Des Parfums",
    "iso:country":"BE",
    "sg:address":"Rue Des Parfums 9",
    "sg:city":"Anderlecht",
    "sg:orig_category":"Blanchisseries and teintureries",
    "sg:phone":"+32 2 521 00 97",
    "sg:postcode":"1070",
    "sg:province":"Bruxelles-Capitale",
    "wof:name":"Okapi",
    "wof:placetype":"venue"
},
  "geometry": {"coordinates":[4.3076038361,50.839630127],"type":"Point"}
}