{
  "type": "Feature",
  "properties": {
    "addr:full":"Florimond Leirensstraat 24 Wetteren Oost-Vlaanderen 9230",
    "addr:housenumber":"24",
    "addr:postcode":"9230",
    "addr:street":"Florimond Leirensstraat",
    "iso:country":"BE",
    "sg:address":"Florimond Leirensstraat 24",
    "sg:city":"Wetteren",
    "sg:classifiers":[
        {
            "category":"Shopping",
            "subcategory":"Optician",
            "type":"Retail Goods"
        }
    ],
    "sg:phone":"+32 9 369 52 88",
    "sg:postcode":"9230",
    "sg:province":"Oost-Vlaanderen",
    "sg:tags":[
        "-"
    ],
    "wof:name":"Maudens K",
    "wof:placetype":"venue"
},
  "geometry": {"coordinates":[3.8840389252,51.0056304932],"type":"Point"}
}