{
  "type": "Feature",
  "properties": {
    "addr:full":"Avenue Du Bourgmestre Jean Materne 1 Namur (jambes) Namur 5100",
    "addr:housenumber":"1",
    "addr:postcode":"5100",
    "addr:street":"Avenue Du Bourgmestre Jean Materne",
    "iso:country":"BE",
    "sg:address":"Avenue Du Bourgmestre Jean Materne 1",
    "sg:city":"Namur (jambes)",
    "sg:classifiers":[
        {
            "category":"Recreation",
            "subcategory":"Fishing",
            "type":"Entertainment"
        }
    ],
    "sg:phone":"+32 81 30 51 10",
    "sg:postcode":"5100",
    "sg:province":"Namur",
    "sg:tags":[
        "tackle"
    ],
    "wof:name":"Coins Des Pecheurs",
    "wof:placetype":"venue"
},
  "geometry": {"coordinates":[4.8713750839,50.4566345215],"type":"Point"}
}