{
  "type": "Feature",
  "properties": {
    "iso:country":"BE",
    "sg:address":"Deinsesteenweg 87",
    "sg:city":"Gent (drongen)",
    "sg:classifiers":[
        {
            "category":"Retail",
            "subcategory":"Auto Repair",
            "type":"Services"
        }
    ],
    "sg:phone":"+32 9 226 66 23",
    "sg:postcode":"9031",
    "sg:province":"Oost-Vlaanderen",
    "sg:tags":[
        "breakdown",
        "automobile",
        "-",
        "recovery"
    ],
    "wof:name":"Danneels Marc Bvba",
    "wof:placetype":"venue"
},
  "geometry": {"coordinates":[3.6420819759,51.0417327881],"type":"Point"}
}