{
  "type": "Feature",
  "properties": {
    "addr:full":"Pauwstraat 154ba Lochristi Oost-Vlaanderen 9080",
    "addr:postcode":"9080",
    "addr:street":"Pauwstraat;Oost-Vlaanderen",
    "iso:country":"BE",
    "sg:address":"Pauwstraat 154ba",
    "sg:city":"Lochristi",
    "sg:orig_category":"Fleurs and plantes",
    "sg:phone":"+32 9 355 92 29",
    "sg:postcode":"9080",
    "sg:province":"Oost-Vlaanderen",
    "wof:name":"Blomflor",
    "wof:placetype":"venue"
},
  "geometry": {"coordinates":[3.8663599491,51.0942115784],"type":"Point"}
}