{
  "type": "Feature",
  "properties": {
    "iso:country":"BE",
    "sg:address":"Lozerbosstraat 10",
    "sg:city":"Kruishoutem",
    "sg:orig_category":"Electrom\u00e9nager, t\u00e9l\u00e9visions and radios. Installation \u00e9lectrique r\u00e9sidentielle",
    "sg:phone":"+32 9 383 66 00",
    "sg:postcode":"9770",
    "sg:province":"Oost-Vlaanderen",
    "wof:name":"Fa. Leyssens",
    "wof:placetype":"venue"
},
  "geometry": {"coordinates":[3.5626900196,50.9214172363],"type":"Point"}
}