{
  "type": "Feature",
  "properties": {
    "iso:country":"BE",
    "sg:address":"Den Bos 32",
    "sg:city":"Zingem (ouwegem)",
    "sg:classifiers":[
        {
            "category":"Shopping",
            "subcategory":"Clothing, Apparel, & Fashions",
            "type":"Retail Goods"
        }
    ],
    "sg:phone":"+32 9 384 33 84",
    "sg:postcode":"9750",
    "sg:province":"Oost-Vlaanderen",
    "sg:tags":[
        "supply",
        "material",
        "-",
        "access",
        "ready-made",
        "clothing"
    ],
    "wof:name":"Bandfabriek Devos Nv",
    "wof:placetype":"venue"
},
  "geometry": {"coordinates":[3.6178500652,50.922958374],"type":"Point"}
}