{
  "type": "Feature",
  "properties": {
    "iso:country":"BE",
    "sg:address":"J. Broerenstraat 40-42",
    "sg:city":"Anderlecht",
    "sg:orig_category":"Sportclubs",
    "sg:phone":"+32 2 522 18 16",
    "sg:postcode":"1070",
    "sg:province":"Bruxelles-Capitale",
    "wof:name":"Duiksportfederatie - N.e.l.o.s",
    "wof:placetype":"venue"
},
  "geometry": {"coordinates":[4.3086419106,50.8389854431],"type":"Point"}
}