{
  "type": "Feature",
  "properties": {
    "iso:country":"BE",
    "sg:address":"Rue \u00e0 Charrettes 68",
    "sg:city":"Quaregnon",
    "sg:classifiers":[
        {
            "category":"Health Services",
            "subcategory":"Nursing And Care Facility",
            "type":"Services"
        }
    ],
    "sg:phone":"+32 65 88 53 55",
    "sg:postcode":"7390",
    "sg:province":"Hainaut",
    "sg:tags":[
        "home"
    ],
    "wof:name":"Rousseau M",
    "wof:placetype":"venue"
},
  "geometry": {"coordinates":[3.877986908,50.4255256653],"type":"Point"}
}