{
  "type": "Feature",
  "properties": {
    "addr:full":"Boulevard De La Plaine 11 Bruxelles (ixelles) Bruxelles-Capitale 1050",
    "addr:housenumber":"11",
    "addr:postcode":"1050",
    "addr:street":"Boulevard De La Plaine",
    "iso:country":"BE",
    "sg:address":"Boulevard De La Plaine 11",
    "sg:city":"Bruxelles (ixelles)",
    "sg:classifiers":[
        {
            "category":"Insurance",
            "subcategory":"Insurance Agent",
            "type":"Services"
        }
    ],
    "sg:phone":"+32 2 739 90 00",
    "sg:postcode":"1050",
    "sg:province":"Bruxelles-Capitale",
    "sg:tags":[
        "-",
        "representative"
    ],
    "wof:name":"Aig Europe",
    "wof:placetype":"venue"
},
  "geometry": {"coordinates":[4.3926911354,50.8206596375],"type":"Point"}
}