{
  "type": "Feature",
  "properties": {
    "addr:full":"Nieshofstraat 4 Bree Limburg 3960",
    "addr:housenumber":"4",
    "addr:postcode":"3960",
    "addr:street":"Nieshofstraat",
    "iso:country":"BE",
    "sg:address":"Nieshofstraat 4",
    "sg:city":"Bree",
    "sg:classifiers":[
        {
            "category":"Manufacturing",
            "subcategory":"Furniture",
            "type":"Manufacturing & Wholesale Goods"
        }
    ],
    "sg:phone":"+32 3 772 33 34",
    "sg:postcode":"3960",
    "sg:province":"Limburg",
    "sg:tags":[
        "contract",
        "basis"
    ],
    "wof:name":"Jonckheere Hilaire Nv",
    "wof:placetype":"venue"
},
  "geometry": {"coordinates":[4.1084609032,51.1453819275],"type":"Point"}
}