{
  "type": "Feature",
  "properties": {
    "addr:full":"Karperweg 1ba Nijlen Antwerpen 2560",
    "addr:housenumber":"1ba",
    "addr:postcode":"2560",
    "addr:street":"Karperweg",
    "iso:country":"BE",
    "sg:address":"Karperweg 1ba",
    "sg:city":"Nijlen",
    "sg:orig_category":"Elektrische installaties voor woningen",
    "sg:phone":"+32 3 411 12 26",
    "sg:postcode":"2560",
    "sg:province":"Antwerpen",
    "wof:name":"Willems Gebrs",
    "wof:placetype":"venue"
},
  "geometry": {"coordinates":[4.6248898506,51.1498603821],"type":"Point"}
}