{
  "type": "Feature",
  "properties": {
    "iso:country":"BE",
    "sg:address":"Foerierstraat 3",
    "sg:city":"Brugge (sint-kruis)",
    "sg:classifiers":[
        {
            "category":"Insurance",
            "subcategory":"Insurance Agent",
            "type":"Services"
        }
    ],
    "sg:phone":"+32 50 47 07 20",
    "sg:postcode":"8310",
    "sg:province":"West-Vlaanderen",
    "sg:tags":[
        "broker"
    ],
    "wof:name":"Helix",
    "wof:placetype":"venue"
},
  "geometry": {"coordinates":[3.2796599865,51.2128486633],"type":"Point"}
}