{
  "type": "Feature",
  "properties": {
    "addr:full":"Rue Jacques 75 Messancy (habergy) Luxembourg 6782",
    "addr:housenumber":"75",
    "addr:postcode":"6782",
    "addr:street":"Rue Jacques",
    "iso:country":"BE",
    "sg:address":"Rue Jacques 75",
    "sg:city":"Messancy (habergy)",
    "sg:classifiers":[
        {
            "category":"Home & Garden",
            "subcategory":"Carpets & Floor Coverings",
            "type":"Retail Goods"
        }
    ],
    "sg:phone":"+32 63 67 70 58",
    "sg:postcode":"6782",
    "sg:province":"Luxembourg",
    "sg:tags":[
        "armoring"
    ],
    "wof:name":"Solideal Sprl",
    "wof:placetype":"venue"
},
  "geometry": {"coordinates":[5.7578558922,49.6096153259],"type":"Point"}
}