{
  "type": "Feature",
  "properties": {
    "addr:full":"Rue De Beaumont 41 Charleroi Hainaut 6030",
    "addr:housenumber":"41",
    "addr:postcode":"6030",
    "addr:street":"Rue De Beaumont;Hainaut",
    "iso:country":"BE",
    "sg:address":"Rue De Beaumont 41",
    "sg:city":"Charleroi",
    "sg:orig_category":"M\u00e9decins and sp\u00e9cialistes",
    "sg:phone":"+32 71 47 84 87",
    "sg:postcode":"6030",
    "sg:province":"Hainaut",
    "wof:name":"A. De Gregorio",
    "wof:placetype":"venue"
},
  "geometry": {"coordinates":[4.395731926,50.4050598145],"type":"Point"}
}