{
  "type": "Feature",
  "properties": {
    "iso:country":"BE",
    "sg:address":"Sint-amandswijk 73",
    "sg:city":"Avelgem",
    "sg:orig_category":"Kapsalons",
    "sg:phone":"+32 55 38 94 23",
    "sg:postcode":"8581",
    "sg:province":"West-Vlaanderen",
    "wof:name":"Els Van Steenbrugge",
    "wof:placetype":"venue"
},
  "geometry": {"coordinates":[3.5021800995,50.7976913452],"type":"Point"}
}