{
  "type": "Feature",
  "properties": {
    "addr:full":"Affligemdreef 11b Aalst Oost-Vlaanderen 9300",
    "addr:housenumber":"11b",
    "addr:postcode":"9300",
    "addr:street":"Affligemdreef",
    "iso:country":"BE",
    "sg:address":"Affligemdreef 11b",
    "sg:city":"Aalst",
    "sg:classifiers":[
        {
            "category":"Professional",
            "subcategory":"Art Services",
            "type":"Services"
        }
    ],
    "sg:phone":"+32 53 77 51 21",
    "sg:postcode":"9300",
    "sg:province":"Oost-Vlaanderen",
    "sg:tags":[
        "graphic",
        "designer"
    ],
    "wof:name":"Perplex",
    "wof:placetype":"venue"
},
  "geometry": {"coordinates":[4.0611009598,50.93176651],"type":"Point"}
}