{
  "type": "Feature",
  "properties": {
    "addr:full":"Kruisstraat 173 Tremelo Vlaams-Brabant 3120",
    "addr:housenumber":"173",
    "addr:postcode":"3120",
    "addr:street":"Kruisstraat",
    "iso:country":"BE",
    "sg:address":"Kruisstraat 173",
    "sg:city":"Tremelo",
    "sg:classifiers":[
        {
            "category":"Personal",
            "subcategory":"Barber",
            "type":"Services"
        }
    ],
    "sg:phone":"+32 16 53 21 77",
    "sg:postcode":"3120",
    "sg:province":"Vlaams-Brabant",
    "sg:tags":[
        "gentleman",
        "salon",
        "-",
        "hairdressing"
    ],
    "wof:name":"Hair & Beauty House",
    "wof:placetype":"venue"
},
  "geometry": {"coordinates":[4.6921000481,50.994758606],"type":"Point"}
}