{
  "type": "Feature",
  "properties": {
    "addr:full":"Generaal Lemanstraat 79 Antwerpen Antwerpen 2018",
    "addr:housenumber":"79",
    "addr:postcode":"2018",
    "addr:street":"Generaal Lemanstraat",
    "iso:country":"BE",
    "sg:address":"Generaal Lemanstraat 79",
    "sg:city":"Antwerpen",
    "sg:orig_category":"Syst\u00e8mes de t\u00e9l\u00e9communications",
    "sg:phone":"+32 3 242 96 20",
    "sg:postcode":"2018",
    "sg:province":"Antwerpen",
    "wof:name":"Belgacom Telebusiness",
    "wof:placetype":"venue"
},
  "geometry": {"coordinates":[4.4117670059,51.1935195923],"type":"Point"}
}