{
  "type": "Feature",
  "properties": {
    "iso:country":"BE",
    "sg:address":"Zwaantje 89ba",
    "sg:city":"Evergem",
    "sg:orig_category":"Varkenskwekers",
    "sg:phone":"+32 9 357 42 77",
    "sg:postcode":"9940",
    "sg:province":"Oost-Vlaanderen",
    "wof:name":"Julien Engels",
    "wof:placetype":"venue"
},
  "geometry": {"coordinates":[3.6745290756,51.1514892578],"type":"Point"}
}