{
  "type": "Feature",
  "properties": {
    "addr:full":"Roodborststraat 2 Zulte Oost-Vlaanderen 9870",
    "addr:housenumber":"2",
    "addr:postcode":"9870",
    "addr:street":"Roodborststraat",
    "iso:country":"BE",
    "sg:address":"Roodborststraat 2",
    "sg:city":"Zulte",
    "sg:classifiers":[
        {
            "category":"Professional",
            "subcategory":"Secretarial Services",
            "type":"Services"
        }
    ],
    "sg:phone":"+32 9 388 34 50",
    "sg:postcode":"9870",
    "sg:province":"Oost-Vlaanderen",
    "sg:tags":[
        "firm"
    ],
    "wof:name":"Distridor Bvba",
    "wof:placetype":"venue"
},
  "geometry": {"coordinates":[3.456496954,50.9232978821],"type":"Point"}
}