{
  "type": "Feature",
  "properties": {
    "addr:full":"Camille Van Der Cruyssenstraat 9 Nevele Oost-Vlaanderen 9850",
    "addr:housenumber":"9",
    "addr:postcode":"9850",
    "addr:street":"Camille Van Der Cruyssenstraat",
    "iso:country":"BE",
    "sg:address":"Camille Van Der Cruyssenstraat 9",
    "sg:city":"Nevele",
    "sg:classifiers":[
        {
            "category":"Banks & Credit Unions",
            "subcategory":"Investment Brokerage",
            "type":"Services"
        }
    ],
    "sg:phone":"+32 9 371 50 29",
    "sg:postcode":"9850",
    "sg:province":"Oost-Vlaanderen",
    "sg:tags":[
        "jean",
        "casual",
        "wear"
    ],
    "wof:name":"Jeans Store Junic",
    "wof:placetype":"venue"
},
  "geometry": {"coordinates":[3.5491809845,51.0339050293],"type":"Point"}
}