{
  "type": "Feature",
  "properties": {
    "iso:country":"BE",
    "sg:address":"Iepersestraat 54",
    "sg:city":"Moorslede",
    "sg:orig_category":"Eleveurs de bovins",
    "sg:phone":"+32 51 77 90 03",
    "sg:postcode":"8890",
    "sg:province":"West-Vlaanderen",
    "wof:name":"Marc Sioen",
    "wof:placetype":"venue"
},
  "geometry": {"coordinates":[3.0490109921,50.884727478],"type":"Point"}
}