{
  "type": "Feature",
  "properties": {
    "iso:country":"BE",
    "sg:address":"Vital Decosterstraat 83",
    "sg:city":"Leuven",
    "sg:classifiers":[
        {
            "category":"Professional",
            "subcategory":"Credit Reporting & Collection",
            "type":"Services"
        }
    ],
    "sg:phone":"+32 16 22 58 80",
    "sg:postcode":"3000",
    "sg:province":"Vlaams-Brabant",
    "sg:tags":[
        "bailiff"
    ],
    "wof:name":"Vanheukelen Ch",
    "wof:placetype":"venue"
},
  "geometry": {"coordinates":[4.7021479607,50.8825492859],"type":"Point"}
}