{
  "type": "Feature",
  "properties": {
    "iso:country":"BE",
    "sg:address":"Rue Gheudestraat 21-25",
    "sg:city":"Bruxelles-brussel",
    "sg:classifiers":[
        {
            "category":"Professional",
            "subcategory":"Advertising",
            "type":"Services"
        }
    ],
    "sg:phone":"+32 2 524 54 44",
    "sg:postcode":"1070",
    "sg:province":"Bruxelles-Capitale",
    "sg:tags":[
        "agency"
    ],
    "wof:name":"Tanagra Sprl/bvba",
    "wof:placetype":"venue"
},
  "geometry": {"coordinates":[4.3341531754,50.842628479],"type":"Point"}
}