{
  "type": "Feature",
  "properties": {
    "iso:country":"BE",
    "sg:address":"Waterstr 9",
    "sg:city":"Wielsbeke",
    "sg:classifiers":[
        {
            "category":"Professional",
            "type":"Services"
        }
    ],
    "sg:phone":"+32 56 66 81 03",
    "sg:postcode":"8710",
    "sg:province":"West-Vlaanderen",
    "sg:tags":[
        "transport",
        "road"
    ],
    "wof:name":"Decotrans Nv",
    "wof:placetype":"venue"
},
  "geometry": {"coordinates":[3.3714199066,50.9140625],"type":"Point"}
}