{
  "type": "Feature",
  "properties": {
    "addr:full":"Waregemstraat 103 Zulte Oost-Vlaanderen 9870",
    "addr:housenumber":"103",
    "addr:postcode":"9870",
    "addr:street":"Waregemstraat",
    "iso:country":"BE",
    "sg:address":"Waregemstraat 103",
    "sg:city":"Zulte",
    "sg:classifiers":[
        {
            "category":"Retail",
            "subcategory":"Auto Repair",
            "type":"Services"
        }
    ],
    "sg:phone":"+32 56 60 40 51",
    "sg:postcode":"9870",
    "sg:province":"Oost-Vlaanderen",
    "sg:tags":[
        "garage"
    ],
    "wof:name":"Ghijsels",
    "wof:placetype":"venue"
},
  "geometry": {"coordinates":[3.4501640797,50.9075393677],"type":"Point"}
}