{
  "type": "Feature",
  "properties": {
    "addr:full":"Rue De La Colline 83 Namur Namur 5000",
    "addr:housenumber":"83",
    "addr:postcode":"5000",
    "addr:street":"Rue De La Colline",
    "iso:country":"BE",
    "sg:address":"Rue De La Colline 83",
    "sg:city":"Namur",
    "sg:orig_category":"Artsen and specialisten",
    "sg:phone":"+32 81 74 32 74",
    "sg:postcode":"5000",
    "sg:province":"Namur",
    "wof:name":"Jacques Kummert",
    "wof:placetype":"venue"
},
  "geometry": {"coordinates":[4.8485941887,50.4607276917],"type":"Point"}
}