{
  "type": "Feature",
  "properties": {
    "iso:country":"BE",
    "sg:address":"Chemin De La Lib\u00e9ration 2",
    "sg:city":"Frasnes-lez-anvaing (hacquegnies)",
    "sg:classifiers":[
        {
            "category":"Farming",
            "subcategory":"Farm & Veterinary Services",
            "type":"Manufacturing & Wholesale Goods"
        }
    ],
    "sg:phone":"+32 69 86 77 76",
    "sg:postcode":"7911",
    "sg:province":"Hainaut",
    "sg:tags":[
        "agricultural",
        "contractor"
    ],
    "wof:name":"Druart & Fils Scris",
    "wof:placetype":"venue"
},
  "geometry": {"coordinates":[3.5914700031,50.6560783386],"type":"Point"}
}