{
  "type": "Feature",
  "properties": {
    "iso:country":"BE",
    "sg:address":"Vlamingstraat 2",
    "sg:city":"Wevelgem",
    "sg:classifiers":[
        {
            "category":"Autos & Motor Vehicles",
            "subcategory":"Automobile Sales",
            "type":"Retail Goods"
        }
    ],
    "sg:phone":"+32 56 41 87 74",
    "sg:postcode":"8560",
    "sg:province":"West-Vlaanderen",
    "sg:tags":[
        "car",
        "used",
        "-"
    ],
    "wof:name":"Vandenbulcke T",
    "wof:placetype":"venue"
},
  "geometry": {"coordinates":[3.2100069523,50.8159980774],"type":"Point"}
}