{
  "type": "Feature",
  "properties": {
    "addr:full":"Rue Du Pont 80bb Ciney Namur 5590",
    "addr:housenumber":"80bb",
    "addr:postcode":"5590",
    "addr:street":"Rue Du Pont",
    "iso:country":"BE",
    "sg:address":"Rue Du Pont 80bb",
    "sg:city":"Ciney",
    "sg:orig_category":"Rundveehouders",
    "sg:phone":"+32 83 21 20 97",
    "sg:postcode":"5590",
    "sg:province":"Namur",
    "wof:name":"Jean-michel Labar",
    "wof:placetype":"venue"
},
  "geometry": {"coordinates":[5.1022520065,50.297088623],"type":"Point"}
}