{
  "type": "Feature",
  "properties": {
    "iso:country":"BE",
    "sg:address":"Westernieuwweg 51",
    "sg:city":"Jabbeke",
    "sg:orig_category":"Installation de menuiserie en bois and plastique",
    "sg:phone":"+32 50 38 65 31",
    "sg:postcode":"8490",
    "sg:province":"West-Vlaanderen",
    "wof:name":"Eugene Snauwaert",
    "wof:placetype":"venue"
},
  "geometry": {"coordinates":[3.1364140511,51.1931228638],"type":"Point"}
}