{
  "type": "Feature",
  "properties": {
    "addr:full":"Gentstraat 333 Gent (oostakker) Oost-Vlaanderen 9041",
    "addr:housenumber":"333",
    "addr:postcode":"9041",
    "addr:street":"Gentstraat",
    "iso:country":"BE",
    "sg:address":"Gentstraat 333",
    "sg:city":"Gent (oostakker)",
    "sg:classifiers":[
        {
            "category":"Shopping",
            "subcategory":"Bicycles & Sporting Goods",
            "type":"Retail Goods"
        }
    ],
    "sg:phone":"+32 9 250 98 60",
    "sg:postcode":"9041",
    "sg:province":"Oost-Vlaanderen",
    "sg:tags":[
        "sport",
        "-"
    ],
    "wof:name":"Abby's",
    "wof:placetype":"venue"
},
  "geometry": {"coordinates":[3.7609739304,51.0967140198],"type":"Point"}
}