{
  "type": "Feature",
  "properties": {
    "iso:country":"BE",
    "sg:address":"Patersstraat 135",
    "sg:city":"Turnhout",
    "sg:orig_category":"Slagers",
    "sg:phone":"+32 14 41 85 05",
    "sg:postcode":"2300",
    "sg:province":"Antwerpen",
    "wof:name":"Jozef Staes",
    "wof:placetype":"venue"
},
  "geometry": {"coordinates":[4.9497900009,51.3276557922],"type":"Point"}
}