{
  "type": "Feature",
  "properties": {
    "addr:full":"De Lint 2 Oud-turnhout Antwerpen 2360",
    "addr:housenumber":"2",
    "addr:postcode":"2360",
    "addr:street":"De Lint",
    "iso:country":"BE",
    "sg:address":"De Lint 2",
    "sg:city":"Oud-turnhout",
    "sg:orig_category":"Travaux de pl\u00e2trage",
    "sg:phone":"+32 14 45 31 81",
    "sg:postcode":"2360",
    "sg:province":"Antwerpen",
    "wof:name":"John Johnson",
    "wof:placetype":"venue"
},
  "geometry": {"coordinates":[5.0151519775,51.312789917],"type":"Point"}
}