{
  "type": "Feature",
  "properties": {
    "addr:full":"Rue De La Gare 12 Andenne Namur 5300",
    "addr:housenumber":"12",
    "addr:postcode":"5300",
    "addr:street":"Rue De La Gare",
    "iso:country":"BE",
    "sg:address":"Rue De La Gare 12",
    "sg:city":"Andenne",
    "sg:orig_category":"Assurances. Bureaux de poste",
    "sg:phone":"+32 81 58 83 39",
    "sg:postcode":"5300",
    "sg:province":"Namur",
    "wof:name":"La Poste",
    "wof:placetype":"venue"
},
  "geometry": {"coordinates":[4.9962701797,50.4700698853],"type":"Point"}
}