{
  "type": "Feature",
  "properties": {
    "iso:country":"BE",
    "sg:address":"Dam 96",
    "sg:city":"Lochristi (zaffelare)",
    "sg:classifiers":[
        {
            "category":"Health Services",
            "subcategory":"Doctor",
            "type":"Services"
        }
    ],
    "sg:phone":"+32 9 355 86 42",
    "sg:postcode":"9080",
    "sg:province":"Oost-Vlaanderen",
    "sg:tags":[
        "psychotherapist",
        "psychoanalyst"
    ],
    "wof:name":"Muller Christine Bvba",
    "wof:placetype":"venue"
},
  "geometry": {"coordinates":[3.862678051,51.1452407837],"type":"Point"}
}