{
  "type": "Feature",
  "properties": {
    "iso:country":"BE",
    "sg:address":"Marktstraat 1",
    "sg:city":"Izegem",
    "sg:classifiers":[
        {
            "category":"Bakery",
            "type":"Food & Drink"
        }
    ],
    "sg:phone":"+32 51 31 72 41",
    "sg:postcode":"8870",
    "sg:province":"West-Vlaanderen",
    "sg:tags":[
        "confectioner",
        "baker"
    ],
    "wof:name":"Bakkerij Marijke",
    "wof:placetype":"venue"
},
  "geometry": {"coordinates":[3.2146439552,50.9179039001],"type":"Point"}
}