{
  "type": "Feature",
  "properties": {
    "iso:country":"BE",
    "sg:address":"Rue Du Progr\u00e8s 187 Box 21",
    "sg:city":"Bruxelles (schaerbeek)",
    "sg:classifiers":[
        {
            "category":"Building & Trades",
            "subcategory":"Cleaning & Sanitation",
            "type":"Services"
        }
    ],
    "sg:phone":"+32 2 203 77 30",
    "sg:postcode":"1030",
    "sg:province":"Bruxelles-Capitale",
    "sg:tags":[
        "janitor"
    ],
    "wof:name":"Fr\u00e9d\u00e9ric Vutera Services Scs",
    "wof:placetype":"venue"
},
  "geometry": {"coordinates":[4.3616299629,50.8628692627],"type":"Point"}
}