{
  "type": "Feature",
  "properties": {
    "iso:country":"BE",
    "sg:address":"Rue Auguste Delvaux 51",
    "sg:city":"Charleroi",
    "sg:orig_category":"Voertuigen",
    "sg:phone":"+32 71 31 82 74",
    "sg:postcode":"6040",
    "sg:province":"Hainaut",
    "wof:name":"Garage Laurent",
    "wof:placetype":"venue"
},
  "geometry": {"coordinates":[4.438958168,50.4495887756],"type":"Point"}
}