{
  "type": "Feature",
  "properties": {
    "addr:full":"Kapellensteenweg 66 Kalmthout Antwerpen 2920",
    "addr:housenumber":"66",
    "addr:postcode":"2920",
    "addr:street":"Kapellensteenweg",
    "iso:country":"BE",
    "sg:address":"Kapellensteenweg 66",
    "sg:city":"Kalmthout",
    "sg:classifiers":[
        {
            "category":"Professional",
            "subcategory":"Lawyer & Legal Services",
            "type":"Services"
        }
    ],
    "sg:phone":"+32 3 620 19 50",
    "sg:postcode":"2920",
    "sg:province":"Antwerpen",
    "wof:name":"Sauter F",
    "wof:placetype":"venue"
},
  "geometry": {"coordinates":[4.4744749069,51.3911056519],"type":"Point"}
}