{
  "type": "Feature",
  "properties": {
    "addr:full":"Keizer Karellaan 73a Ganshoren/ganshoren Bruxelles-Capitale 1083",
    "addr:housenumber":"73a",
    "addr:postcode":"1083",
    "addr:street":"Keizer Karellaan",
    "iso:country":"BE",
    "sg:address":"Keizer Karellaan 73a",
    "sg:city":"Ganshoren/ganshoren",
    "sg:orig_category":"Banken and kredietinstellingen",
    "sg:phone":"+32 2 427 63 68",
    "sg:postcode":"1083",
    "sg:province":"Bruxelles-Capitale",
    "wof:name":"Bacob",
    "wof:placetype":"venue"
},
  "geometry": {"coordinates":[4.3123650551,50.8683395386],"type":"Point"}
}