{
  "type": "Feature",
  "properties": {
    "addr:full":"Grote Baan 159 Waasmunster Oost-Vlaanderen 9250",
    "addr:housenumber":"159",
    "addr:postcode":"9250",
    "addr:street":"Grote Baan",
    "iso:country":"BE",
    "sg:address":"Grote Baan 159",
    "sg:city":"Waasmunster",
    "sg:classifiers":[
        {
            "category":"Travel",
            "subcategory":"Hotels & Motels",
            "type":"Entertainment"
        }
    ],
    "sg:phone":"+32 3 772 69 09",
    "sg:postcode":"9250",
    "sg:province":"Oost-Vlaanderen",
    "sg:tags":[
        "hotels",
        "business",
        "restaurant"
    ],
    "wof:name":"Ruiterhof Nv",
    "wof:placetype":"venue"
},
  "geometry": {"coordinates":[4.0473542213,51.1299514771],"type":"Point"}
}