{
  "type": "Feature",
  "properties": {
    "iso:country":"BE",
    "sg:address":"Rue Bruy\u00c8re 39",
    "sg:city":"Ellezelles",
    "sg:orig_category":"Eleveurs de bovins. Eleveurs and marchands de porcs",
    "sg:phone":"+32 68 54 26 56",
    "sg:postcode":"7890",
    "sg:province":"Hainaut",
    "wof:name":"Remi Craeye",
    "wof:placetype":"venue"
},
  "geometry": {"coordinates":[3.6948189735,50.7410240173],"type":"Point"}
}