{
  "type": "Feature",
  "properties": {
    "iso:country":"BE",
    "sg:address":"Gistelse Steenweg 36",
    "sg:city":"Brugge",
    "sg:orig_category":"Tijdelijke werkgelegenheid and uitzendkantoren",
    "sg:phone":"+32 50 31 13 49",
    "sg:postcode":"8200",
    "sg:province":"West-Vlaanderen",
    "wof:name":"Daoust Interim",
    "wof:placetype":"venue"
},
  "geometry": {"coordinates":[3.2080330849,51.2038116455],"type":"Point"}
}