{
  "type": "Feature",
  "properties": {
    "addr:full":"Rue De Gosselies 65 Charleroi (jumet) Hainaut 6040",
    "addr:housenumber":"65",
    "addr:postcode":"6040",
    "addr:street":"Rue De Gosselies",
    "iso:country":"BE",
    "sg:address":"Rue De Gosselies 65",
    "sg:city":"Charleroi (jumet)",
    "sg:classifiers":[
        {
            "category":"Bars & Pubs",
            "type":"Food & Drink"
        }
    ],
    "sg:phone":"+32 71 34 55 88",
    "sg:postcode":"6040",
    "sg:province":"Hainaut",
    "wof:name":"De La Chapelle (caf\u00e9)",
    "wof:placetype":"venue"
},
  "geometry": {"coordinates":[4.4280238152,50.4546470642],"type":"Point"}
}