{
  "type": "Feature",
  "properties": {
    "iso:country":"BE",
    "sg:address":"Schoolstraat 33",
    "sg:city":"Schilde",
    "sg:orig_category":"Enseignement maternel and primaire",
    "sg:phone":"+32 3 383 07 72",
    "sg:postcode":"2970",
    "sg:province":"Antwerpen",
    "wof:name":"Vrije Lagere School",
    "wof:placetype":"venue"
},
  "geometry": {"coordinates":[4.5808138847,51.2363395691],"type":"Point"}
}