{
  "type": "Feature",
  "properties": {
    "addr:full":"Hoevedreef 12 Kortrijk West-Vlaanderen 8510",
    "addr:housenumber":"12",
    "addr:postcode":"8510",
    "addr:street":"Hoevedreef",
    "iso:country":"BE",
    "sg:address":"Hoevedreef 12",
    "sg:city":"Kortrijk",
    "sg:orig_category":"Rundveehouders",
    "sg:phone":"+32 56 22 89 97",
    "sg:postcode":"8510",
    "sg:province":"West-Vlaanderen",
    "wof:name":"Ghislain Messiaen",
    "wof:placetype":"venue"
},
  "geometry": {"coordinates":[3.2691009045,50.7613754272],"type":"Point"}
}