{
  "type": "Feature",
  "properties": {
    "addr:full":"Italielei 72 Antwerpen Antwerpen 2000",
    "addr:housenumber":"72",
    "addr:postcode":"2000",
    "addr:street":"Italielei",
    "iso:country":"BE",
    "sg:address":"Italielei 72",
    "sg:city":"Antwerpen",
    "sg:orig_category":"Caf\u00e9s Maatschappelijke dienstverlening",
    "sg:phone":"+32 3 233 34 75",
    "sg:postcode":"2000",
    "sg:province":"Antwerpen",
    "wof:name":"Stella Maris",
    "wof:placetype":"venue"
},
  "geometry": {"coordinates":[4.4152169228,51.2231903076],"type":"Point"}
}