{
  "type": "Feature",
  "properties": {
    "addr:full":"Roeselaarsestraat 60b2 Izegem West-Vlaanderen 8870",
    "addr:housenumber":"60b2",
    "addr:postcode":"8870",
    "addr:street":"Roeselaarsestraat",
    "iso:country":"BE",
    "sg:address":"Roeselaarsestraat 60b2",
    "sg:city":"Izegem",
    "sg:orig_category":"Cr\u00e9dit \u00e0 la consommation. Pr\u00eats hypoth\u00e9caires and cr\u00e9dits immobiliers",
    "sg:phone":"+32 51 31 17 95",
    "sg:postcode":"8870",
    "sg:province":"West-Vlaanderen",
    "wof:name":"Eigen Huis",
    "wof:placetype":"venue"
},
  "geometry": {"coordinates":[3.2111260891,50.9188156128],"type":"Point"}
}