{
  "type": "Feature",
  "properties": {
    "iso:country":"BE",
    "sg:address":"Strijlandstraat 60",
    "sg:city":"Gooik",
    "sg:orig_category":"Installatie van houten of kunststof schrijnwerk MEUBELONTWERP AND -INSTALLATIE",
    "sg:phone":"+32 54 56 88 70",
    "sg:postcode":"1755",
    "sg:province":"Vlaams-Brabant",
    "wof:name":"De Weerdt",
    "wof:placetype":"venue"
},
  "geometry": {"coordinates":[4.080329895,50.7920188904],"type":"Point"}
}