{
  "type": "Feature",
  "properties": {
    "addr:full":"Florimond Leirensstraat 6 Wetteren Oost-Vlaanderen 9230",
    "addr:housenumber":"6",
    "addr:postcode":"9230",
    "addr:street":"Florimond Leirensstraat",
    "iso:country":"BE",
    "sg:address":"Florimond Leirensstraat 6",
    "sg:city":"Wetteren",
    "sg:orig_category":"Cosmetica and toiletartikelen Drogisterijen",
    "sg:phone":"+32 9 366 12 76",
    "sg:postcode":"9230",
    "sg:province":"Oost-Vlaanderen",
    "wof:name":"Kruidvat",
    "wof:placetype":"venue"
},
  "geometry": {"coordinates":[3.8843638897,51.0064544678],"type":"Point"}
}