{
  "type": "Feature",
  "properties": {
    "addr:full":"Avenue Prekelinden 138-140 Bruxelles (woluwe-saint-lambert) Bruxelles-Capitale 1200",
    "addr:postcode":"138-140;1200",
    "addr:street":"Avenue Prekelinden",
    "iso:country":"BE",
    "sg:address":"Avenue Prekelinden 138-140",
    "sg:city":"Bruxelles (woluwe-saint-lambert)",
    "sg:classifiers":[
        {
            "category":"Professional",
            "subcategory":"Management & Consulting",
            "type":"Services"
        }
    ],
    "sg:phone":"+32 2 736 52 65",
    "sg:postcode":"1200",
    "sg:province":"Bruxelles-Capitale",
    "sg:tags":[
        "tax-consultants"
    ],
    "wof:name":"Fischer C",
    "wof:placetype":"venue"
},
  "geometry": {"coordinates":[4.407515049,50.8453407288],"type":"Point"}
}