{
  "type": "Feature",
  "properties": {
    "addr:full":"Staalijzer 13 Maldegem Oost-Vlaanderen 9991",
    "addr:housenumber":"13",
    "addr:postcode":"9991",
    "addr:street":"Staalijzer",
    "iso:country":"BE",
    "sg:address":"Staalijzer 13",
    "sg:city":"Maldegem",
    "sg:orig_category":"Installatie van houten of kunststof schrijnwerk",
    "sg:phone":"+32 9 377 58 77",
    "sg:postcode":"9991",
    "sg:province":"Oost-Vlaanderen",
    "wof:name":"Guido Hertleer",
    "wof:placetype":"venue"
},
  "geometry": {"coordinates":[3.5072779655,51.1881866455],"type":"Point"}
}