{
  "type": "Feature",
  "properties": {
    "addr:full":"Avenue Du Manoir 105 Waterloo Brabant Wallon 1410",
    "addr:housenumber":"105",
    "addr:postcode":"1410",
    "addr:street":"Avenue Du Manoir",
    "iso:country":"BE",
    "sg:address":"Avenue Du Manoir 105",
    "sg:city":"Waterloo",
    "sg:orig_category":"Artsen and specialisten",
    "sg:phone":"+32 2 354 14 56",
    "sg:postcode":"1410",
    "sg:province":"Brabant Wallon",
    "wof:name":"Andr\u00c9 Van Oost",
    "wof:placetype":"venue"
},
  "geometry": {"coordinates":[4.408413887,50.731388092],"type":"Point"}
}