{
  "type": "Feature",
  "properties": {
    "addr:full":"Rue De Bruxelles 32 Wavre Brabant Wallon 1300",
    "addr:housenumber":"32;1300",
    "addr:street":"Rue De Bruxelles",
    "iso:country":"BE",
    "sg:address":"Rue De Bruxelles 32",
    "sg:city":"Wavre",
    "sg:classifiers":[
        {
            "category":"Manufacturing",
            "subcategory":"Electronics",
            "type":"Manufacturing & Wholesale Goods"
        }
    ],
    "sg:phone":"+32 10 24 24 27",
    "sg:postcode":"1300",
    "sg:province":"Brabant Wallon",
    "sg:tags":[
        "component",
        "-"
    ],
    "wof:name":"Eltric",
    "wof:placetype":"venue"
},
  "geometry": {"coordinates":[4.6119542122,50.71824646],"type":"Point"}
}