{
  "type": "Feature",
  "properties": {
    "addr:full":"Rue Albert I 57 La Louvi\u00e8re Hainaut 7100",
    "addr:housenumber":"57",
    "addr:postcode":"7100",
    "addr:street":"Rue Albert I",
    "iso:country":"BE",
    "sg:address":"Rue Albert I 57",
    "sg:city":"La Louvi\u00e8re",
    "sg:classifiers":[
        {
            "category":"Professional",
            "subcategory":"Testing Lab",
            "type":"Services"
        }
    ],
    "sg:phone":"+32 64 22 27 94",
    "sg:postcode":"7100",
    "sg:province":"Hainaut",
    "sg:tags":[
        "chemist"
    ],
    "wof:name":"Dumont M-f",
    "wof:placetype":"venue"
},
  "geometry": {"coordinates":[4.1858429909,50.4753684998],"type":"Point"}
}