{
  "type": "Feature",
  "properties": {
    "addr:full":"Blancefloerlaan 5 Antwerpen Antwerpen 2050",
    "addr:housenumber":"5",
    "addr:postcode":"2050",
    "addr:street":"Blancefloerlaan",
    "iso:country":"BE",
    "sg:address":"Blancefloerlaan 5",
    "sg:city":"Antwerpen",
    "sg:orig_category":"Blanchisseries and teintureries",
    "sg:phone":"+32 3 211 02 62",
    "sg:postcode":"2050",
    "sg:province":"Antwerpen",
    "wof:name":"Wasserij Don Bosco",
    "wof:placetype":"venue"
},
  "geometry": {"coordinates":[4.3853049278,51.2201385498],"type":"Point"}
}