{
  "type": "Feature",
  "properties": {
    "iso:country":"BE",
    "sg:address":"Winkelomstraat 4ba",
    "sg:city":"Bilzen",
    "sg:orig_category":"Eleveurs de bovins",
    "sg:phone":"+32 89 41 56 76",
    "sg:postcode":"3740",
    "sg:province":"Limburg",
    "wof:name":"Kamiel Jans",
    "wof:placetype":"venue"
},
  "geometry": {"coordinates":[5.5755410194,50.8746452332],"type":"Point"}
}