{
  "type": "Feature",
  "properties": {
    "iso:country":"BE",
    "sg:address":"Rue Pisseroule 57-61",
    "sg:city":"Dison",
    "sg:orig_category":"Peinture. Rev\u00eatements pour sols and murs",
    "sg:phone":"+32 87 33 69 41",
    "sg:postcode":"4820",
    "sg:province":"Li\u00e8ge",
    "wof:name":"Gilbert Voncken",
    "wof:placetype":"venue"
},
  "geometry": {"coordinates":[5.8553948402,50.6045341492],"type":"Point"}
}