{
  "type": "Feature",
  "properties": {
    "iso:country":"BE",
    "sg:address":"Rue Likenne 32",
    "sg:city":"Saint-nicolas",
    "sg:orig_category":"Woningbouw",
    "sg:phone":"+32 4 252 57 00",
    "sg:postcode":"4420",
    "sg:province":"Li\u00e8ge",
    "wof:name":"Delcomune & Lognoul",
    "wof:placetype":"venue"
},
  "geometry": {"coordinates":[5.5413069725,50.6295890808],"type":"Point"}
}