{
  "type": "Feature",
  "properties": {
    "iso:country":"BE",
    "sg:address":"Grand-route 248",
    "sg:city":"Mons",
    "sg:orig_category":"Entretien and r\u00e9parations de voitures",
    "sg:phone":"+32 65 84 41 78",
    "sg:postcode":"7000",
    "sg:province":"Hainaut",
    "wof:name":"Hugo Henrist",
    "wof:placetype":"venue"
},
  "geometry": {"coordinates":[3.94927001,50.4491996765],"type":"Point"}
}