{
  "type": "Feature",
  "properties": {
    "iso:country":"BE",
    "sg:address":"Sparrendreef 96",
    "sg:city":"Knokke-heist",
    "sg:orig_category":"Eclairage et \u00e9quipements du foyer",
    "sg:phone":"+32 50 61 21 09",
    "sg:postcode":"8300",
    "sg:province":"West-Vlaanderen",
    "wof:name":"Huis Sachilo",
    "wof:placetype":"venue"
},
  "geometry": {"coordinates":[3.3047449589,51.3499145508],"type":"Point"}
}