{
  "type": "Feature",
  "properties": {
    "addr:full":"Stationsstraat 2ba Bornem Antwerpen 2880",
    "addr:housenumber":"2ba",
    "addr:postcode":"2880",
    "addr:street":"Stationsstraat",
    "iso:country":"BE",
    "sg:address":"Stationsstraat 2ba",
    "sg:city":"Bornem",
    "sg:classifiers":[
        {
            "category":"Fast Food",
            "type":"Food & Drink"
        }
    ],
    "sg:phone":"+32 3 889 85 00",
    "sg:postcode":"2880",
    "sg:province":"Antwerpen",
    "sg:tags":[
        "\u00c0",
        "emporter",
        "restaurants"
    ],
    "wof:name":"Frituur De Zon",
    "wof:placetype":"venue"
},
  "geometry": {"coordinates":[4.235678196,51.0994033813],"type":"Point"}
}