{
  "type": "Feature",
  "properties": {
    "iso:country":"BE",
    "sg:address":"Rue Sur-la-fontaine 73",
    "sg:city":"Li\u00e8ge 1",
    "sg:classifiers":[
        {
            "category":"Retail",
            "subcategory":"Repair Shop",
            "type":"Services"
        }
    ],
    "sg:phone":"+32 4 223 32 37",
    "sg:postcode":"4000",
    "sg:province":"Li\u00e8ge",
    "sg:tags":[
        "denture"
    ],
    "wof:name":"R Wilkin",
    "wof:placetype":"venue"
},
  "geometry": {"coordinates":[5.5675988197,50.6405410767],"type":"Point"}
}