{
  "type": "Feature",
  "properties": {
    "addr:full":"Jan Broeckaertlaan 18 Box 12 Wetteren Oost-Vlaanderen 9230",
    "addr:housenumber":"18 box 12",
    "addr:postcode":"9230",
    "addr:street":"Broeckaertlaan",
    "iso:country":"BE",
    "sg:address":"Jan Broeckaertlaan 18 Box 12",
    "sg:city":"Wetteren",
    "sg:classifiers":[
        {
            "category":"Health Services",
            "subcategory":"Health Practitioner",
            "type":"Services"
        }
    ],
    "sg:phone":"+32 9 369 71 30",
    "sg:postcode":"9230",
    "sg:province":"Oost-Vlaanderen",
    "sg:tags":[
        "physiotherapist"
    ],
    "wof:name":"Janda Ilse",
    "wof:placetype":"venue"
},
  "geometry": {"coordinates":[3.8859360218,51.0024642944],"type":"Point"}
}