{
  "type": "Feature",
  "properties": {
    "addr:full":"Rue Bordia 10b H\u00e9ron (couthuin) Li\u00e8ge 4218",
    "addr:housenumber":"10b",
    "addr:postcode":"4218",
    "addr:street":"Rue Bordia",
    "iso:country":"BE",
    "sg:address":"Rue Bordia 10b",
    "sg:city":"H\u00e9ron (couthuin)",
    "sg:classifiers":[
        {
            "category":"Building & Trades",
            "subcategory":"Construction",
            "type":"Services"
        }
    ],
    "sg:phone":"+32 85 71 27 13",
    "sg:postcode":"4218",
    "sg:province":"Li\u00e8ge",
    "sg:tags":[
        "carpenter"
    ],
    "wof:name":"Malherbe J",
    "wof:placetype":"venue"
},
  "geometry": {"coordinates":[5.1154260635,50.5160293579],"type":"Point"}
}