{
  "type": "Feature",
  "properties": {
    "addr:full":"Acaciastraat 13 Merelbeke Oost-Vlaanderen 9820",
    "addr:housenumber":"13",
    "addr:postcode":"9820",
    "addr:street":"Acaciastraat",
    "iso:country":"BE",
    "sg:address":"Acaciastraat 13",
    "sg:city":"Merelbeke",
    "sg:classifiers":[
        {
            "category":"Building & Trades",
            "subcategory":"Plumbing",
            "type":"Services"
        }
    ],
    "sg:phone":"+32 9 230 59 10",
    "sg:postcode":"9820",
    "sg:province":"Oost-Vlaanderen",
    "sg:tags":[
        "repair",
        "mainten",
        "-",
        "central",
        "heating"
    ],
    "wof:name":"Balima Bvba",
    "wof:placetype":"venue"
},
  "geometry": {"coordinates":[3.7393569946,50.9862518311],"type":"Point"}
}