{
  "type": "Feature",
  "properties": {
    "iso:country":"BE",
    "sg:address":"Matenstraat 7",
    "sg:city":"Niel",
    "sg:classifiers":[
        {
            "category":"Animal Shelter",
            "type":"Public Place"
        }
    ],
    "sg:phone":"+32 3 888 60 78",
    "sg:postcode":"2845",
    "sg:province":"Antwerpen",
    "wof:name":"Kids-mephisto Hoeve",
    "wof:placetype":"venue"
},
  "geometry": {"coordinates":[4.3385548592,51.1123542786],"type":"Point"}
}