{
  "type": "Feature",
  "properties": {
    "addr:full":"Industriepark Noord 15 Beernem West-Vlaanderen 8730",
    "addr:housenumber":"15",
    "addr:postcode":"8730",
    "addr:street":"Industriepark Noord",
    "iso:country":"BE",
    "sg:address":"Industriepark Noord 15",
    "sg:city":"Beernem",
    "sg:classifiers":[
        {
            "category":"Manufacturing",
            "subcategory":"Metals",
            "type":"Manufacturing & Wholesale Goods"
        }
    ],
    "sg:phone":"+32 50 79 21 71",
    "sg:postcode":"8730",
    "sg:province":"West-Vlaanderen",
    "sg:tags":[
        "working"
    ],
    "wof:name":"Vlaeminck A Nv",
    "wof:placetype":"venue"
},
  "geometry": {"coordinates":[3.3413250446,51.1299667358],"type":"Point"}
}