{
  "type": "Feature",
  "properties": {
    "iso:country":"BE",
    "sg:address":"Kasteelstraat 85",
    "sg:city":"Heist-op-den-berg",
    "sg:classifiers":[
        {
            "category":"Wholesale",
            "subcategory":"Sporting Goods",
            "type":"Manufacturing & Wholesale Goods"
        }
    ],
    "sg:phone":"+32 15 24 26 67",
    "sg:postcode":"2220",
    "sg:province":"Antwerpen",
    "sg:tags":[
        "sport-",
        "kampeermateriaal"
    ],
    "wof:name":"Desoni Sport",
    "wof:placetype":"venue"
},
  "geometry": {"coordinates":[4.7160072327,51.0666236877],"type":"Point"}
}