{
  "type": "Feature",
  "properties": {
    "addr:full":"Sint-rochusstraat 13 Bilzen Limburg 3740",
    "addr:housenumber":"13",
    "addr:postcode":"3740",
    "addr:street":"Sint-Rochusstraat",
    "iso:country":"BE",
    "sg:address":"Sint-rochusstraat 13",
    "sg:city":"Bilzen",
    "sg:orig_category":"Bloemen and planten",
    "sg:phone":"+32 89 41 32 46",
    "sg:postcode":"3740",
    "sg:province":"Limburg",
    "wof:name":"Frans Daniels",
    "wof:placetype":"venue"
},
  "geometry": {"coordinates":[5.5321669579,50.8835258484],"type":"Point"}
}