{
  "type": "Feature",
  "properties": {
    "addr:full":"Rue Du Onze Novembre 31 Mons Hainaut 7000",
    "addr:housenumber":"31",
    "addr:postcode":"7000",
    "addr:street":"Rue Du Onze Novembre;Hainaut",
    "iso:country":"BE",
    "sg:address":"Rue Du Onze Novembre 31",
    "sg:city":"Mons",
    "sg:orig_category":"Avocats and conseillers juridiques",
    "sg:phone":"+32 65 35 26 78",
    "sg:postcode":"7000",
    "sg:province":"Hainaut",
    "wof:name":"Fran\u00c7oise Servais",
    "wof:placetype":"venue"
},
  "geometry": {"coordinates":[3.9516088963,50.4567565918],"type":"Point"}
}