{
  "type": "Feature",
  "properties": {
    "addr:full":"Tongersesteenweg 5 Kortessem Limburg 3720",
    "addr:housenumber":"5",
    "addr:postcode":"3720",
    "addr:street":"Tongersesteenweg",
    "iso:country":"BE",
    "sg:address":"Tongersesteenweg 5",
    "sg:city":"Kortessem",
    "sg:orig_category":"M\u00e9decins and sp\u00e9cialistes",
    "sg:phone":"+32 11 37 55 44",
    "sg:postcode":"3720",
    "sg:province":"Limburg",
    "wof:name":"Jan Van Oeteren",
    "wof:placetype":"venue"
},
  "geometry": {"coordinates":[5.3871130943,50.8570327759],"type":"Point"}
}