{
  "type": "Feature",
  "properties": {
    "addr:full":"Rue De Wanzoul 28 Wanze Li\u00e8ge 4520",
    "addr:housenumber":"28",
    "addr:postcode":"4520",
    "addr:street":"Rue De Wanzoul",
    "iso:country":"BE",
    "sg:address":"Rue De Wanzoul 28",
    "sg:city":"Wanze",
    "sg:orig_category":"M\u00e9decins and sp\u00e9cialistes",
    "sg:phone":"+32 85 21 22 56",
    "sg:postcode":"4520",
    "sg:province":"Li\u00e8ge",
    "wof:name":"P. Rihon",
    "wof:placetype":"venue"
},
  "geometry": {"coordinates":[5.2206559181,50.5659217834],"type":"Point"}
}