{
  "type": "Feature",
  "properties": {
    "addr:full":"Leeuwerikstraat 2 Lier Antwerpen 2500",
    "addr:housenumber":"2",
    "addr:postcode":"2500",
    "addr:street":"Leeuwerikstraat",
    "iso:country":"BE",
    "sg:address":"Leeuwerikstraat 2",
    "sg:city":"Lier",
    "sg:classifiers":[
        {
            "category":"Banks & Credit Unions",
            "subcategory":"Investment Brokerage",
            "type":"Services"
        }
    ],
    "sg:phone":"+32 15 32 05 39",
    "sg:postcode":"2500",
    "sg:province":"Antwerpen",
    "sg:tags":[
        "rental",
        "-",
        "yacht",
        "boat",
        "pleasure"
    ],
    "wof:name":"Sailing The North Sea Cv",
    "wof:placetype":"venue"
},
  "geometry": {"coordinates":[4.5100240707,51.1032867432],"type":"Point"}
}