{
  "type": "Feature",
  "properties": {
    "addr:full":"Rue Lambot 100 Aiseau-presles Hainaut 6250",
    "addr:housenumber":"100",
    "addr:postcode":"6250",
    "addr:street":"Rue Lambot;Hainaut",
    "iso:country":"BE",
    "sg:address":"Rue Lambot 100",
    "sg:city":"Aiseau-presles",
    "sg:orig_category":"Assurances. Bureaux de poste",
    "sg:phone":"+32 71 77 18 31",
    "sg:postcode":"6250",
    "sg:province":"Hainaut",
    "wof:name":"La Poste",
    "wof:placetype":"venue"
},
  "geometry": {"coordinates":[4.5880131721,50.4260292053],"type":"Point"}
}