{
  "type": "Feature",
  "properties": {
    "iso:country":"BE",
    "sg:address":"Rue Des Mauvaises-vignes 66",
    "sg:city":"Li\u00e8ge 1 (ch\u00ean\u00e9e)",
    "sg:orig_category":"Solar protection - Outside",
    "sg:phone":"+32 4 367 17 18",
    "sg:postcode":"4032",
    "sg:province":"Li\u00e8ge",
    "wof:name":"N\u00e9on-expert",
    "wof:placetype":"venue"
},
  "geometry": {"coordinates":[5.6184821129,50.6179046631],"type":"Point"}
}