{
  "type": "Feature",
  "properties": {
    "iso:country":"BE",
    "sg:address":"Rue Emile Godfrind 32c",
    "sg:city":"Andenne (seilles)",
    "sg:classifiers":[
        {
            "category":"Arena",
            "subcategory":"Sports Club",
            "type":"Entertainment"
        }
    ],
    "sg:phone":"+32 85 82 65 65",
    "sg:postcode":"5300",
    "sg:province":"Namur",
    "wof:name":"Fontenalle Tennis Club",
    "wof:placetype":"venue"
},
  "geometry": {"coordinates":[5.0982642174,50.4863739014],"type":"Point"}
}