{
  "type": "Feature",
  "properties": {
    "addr:full":"Square De Quinaux 12 Namur Namur 5100",
    "addr:housenumber":"12",
    "addr:postcode":"5100",
    "addr:street":"Square De Quinaux",
    "iso:country":"BE",
    "sg:address":"Square De Quinaux 12",
    "sg:city":"Namur",
    "sg:orig_category":"M\u00e9decins and sp\u00e9cialistes",
    "sg:phone":"+32 81 40 15 73",
    "sg:postcode":"5100",
    "sg:province":"Namur",
    "wof:name":"Danielle Bernard",
    "wof:placetype":"venue"
},
  "geometry": {"coordinates":[4.8713750839,50.4566345215],"type":"Point"}
}