{
  "type": "Feature",
  "properties": {
    "addr:full":"Marktstraat 4 Maldegem Oost-Vlaanderen 9990",
    "addr:housenumber":"4",
    "addr:postcode":"9990",
    "addr:street":"Marktstraat",
    "iso:country":"BE",
    "sg:address":"Marktstraat 4",
    "sg:city":"Maldegem",
    "sg:orig_category":"Centres de relaxation and bien-\u00eatre. Instituts de beaut\u00e9",
    "sg:phone":"+32 50 71 04 15",
    "sg:postcode":"9990",
    "sg:province":"Oost-Vlaanderen",
    "wof:name":"Instituut Finesse",
    "wof:placetype":"venue"
},
  "geometry": {"coordinates":[3.4445159435,51.2088775635],"type":"Point"}
}