{
  "type": "Feature",
  "properties": {
    "addr:full":"Steenstraat 1e Kortemark (werken) West-Vlaanderen 8610",
    "addr:housenumber":"1e",
    "addr:postcode":"8610",
    "addr:street":"Steenstraat",
    "iso:country":"BE",
    "sg:address":"Steenstraat 1e",
    "sg:city":"Kortemark (werken)",
    "sg:classifiers":[
        {
            "category":"Building & Trades",
            "subcategory":"Construction",
            "type":"Services"
        }
    ],
    "sg:phone":"+32 51 57 18 21",
    "sg:postcode":"8610",
    "sg:province":"West-Vlaanderen",
    "sg:tags":[
        "carpenter"
    ],
    "wof:name":"Beernaert J",
    "wof:placetype":"venue"
},
  "geometry": {"coordinates":[2.9553339481,51.029258728],"type":"Point"}
}