{
  "type": "Feature",
  "properties": {
    "iso:country":"BE",
    "sg:address":"Rue De La Florbecq 99c",
    "sg:city":"Lessines (ollignies)",
    "sg:classifiers":[
        {
            "category":"Home & Garden",
            "subcategory":"Home Furnishings",
            "type":"Retail Goods"
        }
    ],
    "sg:phone":"+32 68 33 47 78",
    "sg:postcode":"7866",
    "sg:province":"Hainaut",
    "sg:tags":[
        "interior",
        "decoration"
    ],
    "wof:name":"A. Der. Sol Scrl",
    "wof:placetype":"venue"
},
  "geometry": {"coordinates":[3.8455049992,50.6806221008],"type":"Point"}
}