{
  "type": "Feature",
  "properties": {
    "iso:country":"BE",
    "sg:address":"Torhoutsesteenweg 237",
    "sg:city":"Zedelgem",
    "sg:classifiers":[
        {
            "category":"Wholesale",
            "subcategory":"Meat",
            "type":"Manufacturing & Wholesale Goods"
        }
    ],
    "sg:phone":"+32 50 20 93 28",
    "sg:postcode":"8210",
    "sg:province":"West-Vlaanderen",
    "sg:tags":[
        "abattoir"
    ],
    "wof:name":"De Rese Nv",
    "wof:placetype":"venue"
},
  "geometry": {"coordinates":[3.1576468945,51.1365127563],"type":"Point"}
}