{
  "type": "Feature",
  "properties": {
    "iso:country":"BE",
    "sg:address":"Kersenboomlaan 9",
    "sg:city":"Sint-genesius-rode/rhode-saint-gen\u00c8se",
    "sg:orig_category":"Artiesten and kunstenaars",
    "sg:phone":"+32 2 358 59 13",
    "sg:postcode":"1640",
    "sg:province":"Vlaams-Brabant",
    "wof:name":"Pascale Greindl",
    "wof:placetype":"venue"
},
  "geometry": {"coordinates":[4.3709769249,50.7513504028],"type":"Point"}
}