{
  "type": "Feature",
  "properties": {
    "addr:full":"Reppelerweg 239 Bocholt Limburg 3950",
    "addr:housenumber":"239",
    "addr:postcode":"3950",
    "addr:street":"Reppelerweg",
    "iso:country":"BE",
    "sg:address":"Reppelerweg 239",
    "sg:city":"Bocholt",
    "sg:orig_category":"Diverse bouwinstallaties Gespecialiseerde niet-residenti\u00eble bouw",
    "sg:phone":"+32 89 47 15 76",
    "sg:postcode":"3950",
    "sg:province":"Limburg",
    "wof:name":"Vrolix",
    "wof:placetype":"venue"
},
  "geometry": {"coordinates":[5.5698099136,51.1633300781],"type":"Point"}
}