{
  "type": "Feature",
  "properties": {
    "addr:full":"Werviksestraat 216 Ieper (zillebeke) West-Vlaanderen 8902",
    "addr:housenumber":"216",
    "addr:postcode":"8902",
    "addr:street":"Werviksestraat",
    "iso:country":"BE",
    "sg:address":"Werviksestraat 216",
    "sg:city":"Ieper (zillebeke)",
    "sg:classifiers":[
        {
            "category":"Bars & Pubs",
            "type":"Food & Drink"
        }
    ],
    "sg:phone":"+32 57 20 38 40",
    "sg:postcode":"8902",
    "sg:province":"West-Vlaanderen",
    "wof:name":"Klein Zillebeke ('t)",
    "wof:placetype":"venue"
},
  "geometry": {"coordinates":[2.9402029514,50.8217201233],"type":"Point"}
}