{
  "type": "Feature",
  "properties": {
    "addr:full":"Rue De L'eglise 36 Vresse-sur-semois Namur 5550",
    "addr:housenumber":"36",
    "addr:postcode":"5550",
    "addr:street":"Rue De L'Eglise",
    "iso:country":"BE",
    "sg:address":"Rue De L'eglise 36",
    "sg:city":"Vresse-sur-semois",
    "sg:orig_category":"Postkantoren Verzekeringsmakelaars and experts",
    "sg:phone":"+32 61 50 01 64",
    "sg:postcode":"5550",
    "sg:province":"Namur",
    "wof:name":"La Poste",
    "wof:placetype":"venue"
},
  "geometry": {"coordinates":[4.9336800575,49.8729782104],"type":"Point"}
}