{
  "type": "Feature",
  "properties": {
    "addr:full":"Villerslei 97 Schoten Antwerpen 2900",
    "addr:housenumber":"97",
    "addr:postcode":"2900",
    "addr:street":"Villerslei",
    "iso:country":"BE",
    "sg:address":"Villerslei 97",
    "sg:city":"Schoten",
    "sg:orig_category":"Banken and kredietinstellingen",
    "sg:phone":"+32 3 680 14 00",
    "sg:postcode":"2900",
    "sg:province":"Antwerpen",
    "wof:name":"Dexia",
    "wof:placetype":"venue"
},
  "geometry": {"coordinates":[4.5130438805,51.2523422241],"type":"Point"}
}