{
  "type": "Feature",
  "properties": {
    "iso:country":"BE",
    "sg:address":"Kontichsesteenweg 47",
    "sg:city":"Aartselaar",
    "sg:classifiers":[
        {
            "category":"Wholesale",
            "subcategory":"Books, Periodicals, & Newspapers",
            "type":"Manufacturing & Wholesale Goods"
        }
    ],
    "sg:phone":"+32 3 887 22 16",
    "sg:postcode":"2630",
    "sg:province":"Antwerpen",
    "sg:tags":[
        "banner"
    ],
    "wof:name":"Blommaert Publiciteit Nv",
    "wof:placetype":"venue"
},
  "geometry": {"coordinates":[4.389649868,51.1441726685],"type":"Point"}
}