{
  "type": "Feature",
  "properties": {
    "iso:country":"BE",
    "sg:address":"Rue De La Chapelle 7",
    "sg:city":"Martelange",
    "sg:orig_category":"Sportclubs",
    "sg:phone":"+32 63 60 06 50",
    "sg:postcode":"6630",
    "sg:province":"Luxembourg",
    "wof:name":"Marcheurs D.l. Haute-s\u00dbre",
    "wof:placetype":"venue"
},
  "geometry": {"coordinates":[5.7376332283,49.8305625916],"type":"Point"}
}