{
  "type": "Feature",
  "properties": {
    "addr:full":"Doggenhoutstraat 57 Ranst Antwerpen 2520",
    "addr:housenumber":"57",
    "addr:postcode":"2520",
    "addr:street":"Doggenhoutstraat",
    "iso:country":"BE",
    "sg:address":"Doggenhoutstraat 57",
    "sg:city":"Ranst",
    "sg:classifiers":[
        {
            "category":"Building & Trades",
            "subcategory":"Landscaping Services",
            "type":"Services"
        }
    ],
    "sg:phone":"+32 3 475 19 91",
    "sg:postcode":"2520",
    "sg:province":"Antwerpen",
    "sg:tags":[
        "gardening",
        "garden",
        "maintenance"
    ],
    "wof:name":"Smeets & Partners Gcv",
    "wof:placetype":"venue"
},
  "geometry": {"coordinates":[4.5626449585,51.1879234314],"type":"Point"}
}