{
  "type": "Feature",
  "properties": {
    "iso:country":"BE",
    "sg:address":"Rue Du Centre 62",
    "sg:city":"Sprimont",
    "sg:orig_category":"Pain, p\u00e2tisseries and confiseries",
    "sg:phone":"+32 4 382 11 40",
    "sg:postcode":"4140",
    "sg:province":"Li\u00e8ge",
    "wof:name":"Boulangerie Remacle",
    "wof:placetype":"venue"
},
  "geometry": {"coordinates":[5.6623048782,50.502696991],"type":"Point"}
}