{
  "type": "Feature",
  "properties": {
    "iso:country":"BE",
    "sg:address":"Eupener Strasse 83",
    "sg:city":"Raeren (eynatten)",
    "sg:classifiers":[
        {
            "category":"Home & Garden",
            "subcategory":"Home Furnishings",
            "type":"Retail Goods"
        }
    ],
    "sg:phone":"+32 87 85 88 11",
    "sg:postcode":"4731",
    "sg:province":"Li\u00e8ge",
    "sg:tags":[
        "-",
        "furniture"
    ],
    "wof:name":"Meessen M\u00f6bel Ag Sa",
    "wof:placetype":"venue"
},
  "geometry": {"coordinates":[6.0797438622,50.6871757507],"type":"Point"}
}