{
  "type": "Feature",
  "properties": {
    "iso:country":"BE",
    "sg:address":"Halmaaldorp 11",
    "sg:city":"Sint-truiden",
    "sg:orig_category":"Bloemen and planten",
    "sg:phone":"+32 11 68 87 78",
    "sg:postcode":"3800",
    "sg:province":"Limburg",
    "wof:name":"Ghislain Breesch",
    "wof:placetype":"venue"
},
  "geometry": {"coordinates":[5.1544299126,50.8042488098],"type":"Point"}
}