{
  "type": "Feature",
  "properties": {
    "addr:full":"Bergense Steenweg 998 Anderlecht Bruxelles-Capitale 1070",
    "addr:housenumber":"998",
    "addr:postcode":"1070",
    "addr:street":"Bergense Steenweg",
    "iso:country":"BE",
    "sg:address":"Bergense Steenweg 998",
    "sg:city":"Anderlecht",
    "sg:orig_category":"Banken and kredietinstellingen",
    "sg:phone":"+32 2 523 63 06",
    "sg:postcode":"1070",
    "sg:province":"Bruxelles-Capitale",
    "wof:name":"Fortis",
    "wof:placetype":"venue"
},
  "geometry": {"coordinates":[4.2964267731,50.824420929],"type":"Point"}
}