{
  "type": "Feature",
  "properties": {
    "addr:full":"Rue Des Egyptiennes 40 Ch\u00e2telet (bouffioulx) Hainaut 6200",
    "addr:housenumber":"40",
    "addr:postcode":"6200",
    "addr:street":"Rue Des Egyptiennes",
    "iso:country":"BE",
    "sg:address":"Rue Des Egyptiennes 40",
    "sg:city":"Ch\u00e2telet (bouffioulx)",
    "sg:classifiers":[
        {
            "category":"Utilities",
            "subcategory":"Natural Gas",
            "type":"Services"
        }
    ],
    "sg:phone":"+32 71 38 33 98",
    "sg:postcode":"6200",
    "sg:province":"Hainaut",
    "sg:tags":[
        "welding"
    ],
    "wof:name":"Multi-soudures-services",
    "wof:placetype":"venue"
},
  "geometry": {"coordinates":[4.5187501907,50.3932800293],"type":"Point"}
}