{
  "type": "Feature",
  "properties": {
    "iso:country":"BE",
    "sg:address":"Rue De Branchon 66",
    "sg:city":"Fernelmont",
    "sg:classifiers":[
        {
            "category":"Insurance",
            "subcategory":"Life Insurance",
            "type":"Services"
        }
    ],
    "sg:phone":"+32 81 83 34 78",
    "sg:postcode":"5380",
    "sg:province":"Namur",
    "sg:tags":[
        "assurance"
    ],
    "wof:name":"Cavalier - Assurances",
    "wof:placetype":"venue"
},
  "geometry": {"coordinates":[4.9861078262,50.5531463623],"type":"Point"}
}