{
  "type": "Feature",
  "properties": {
    "iso:country":"BE",
    "sg:address":"D\u00b4helst 14ba",
    "sg:city":"Lebbeke",
    "sg:orig_category":"Entretien and r\u00e9parations de voitures",
    "sg:phone":"+32 52 41 56 78",
    "sg:postcode":"9280",
    "sg:province":"Oost-Vlaanderen",
    "wof:name":"Mattan Freddy",
    "wof:placetype":"venue"
},
  "geometry": {"coordinates":[4.1340780258,50.9856834412],"type":"Point"}
}