{
  "type": "Feature",
  "properties": {
    "addr:full":"Avenue De Navagne 2 Vise Li\u00e8ge 4600",
    "addr:housenumber":"2",
    "addr:postcode":"4600",
    "addr:street":"Avenue De Navagne",
    "iso:country":"BE",
    "sg:address":"Avenue De Navagne 2",
    "sg:city":"Vise",
    "sg:orig_category":"Dierenartsen",
    "sg:phone":"+32 4 379 12 09",
    "sg:postcode":"4600",
    "sg:province":"Li\u00e8ge",
    "wof:name":"Daniel Simon",
    "wof:placetype":"venue"
},
  "geometry": {"coordinates":[5.6941199303,50.7409210205],"type":"Point"}
}