{
  "type": "Feature",
  "properties": {
    "iso:country":"BE",
    "sg:address":"Hellestraat 54",
    "sg:city":"Wervik",
    "sg:orig_category":"Sportclubs",
    "sg:phone":"+32 56 31 49 88",
    "sg:postcode":"8940",
    "sg:province":"West-Vlaanderen",
    "wof:name":"Wielergroep Wervik",
    "wof:placetype":"venue"
},
  "geometry": {"coordinates":[3.0533189774,50.7839202881],"type":"Point"}
}