{
  "type": "Feature",
  "properties": {
    "addr:full":"Avenue Des Mille M\u00c8tres 83 Sint-pieters-woluwe/woluwe-saint-pierre Bruxelles-Capitale 1150",
    "addr:housenumber":"83",
    "addr:postcode":"1150",
    "addr:street":"Avenue Des Mille Me\u0300Tres;/",
    "iso:country":"BE",
    "sg:address":"Avenue Des Mille M\u00c8tres 83",
    "sg:city":"Sint-pieters-woluwe/woluwe-saint-pierre",
    "sg:orig_category":"Administration d'immeubles",
    "sg:phone":"+32 2 779 27 48",
    "sg:postcode":"1150",
    "sg:province":"Bruxelles-Capitale",
    "wof:name":"Marcel Vandermolen",
    "wof:placetype":"venue"
},
  "geometry": {"coordinates":[4.4633769989,50.8367080688],"type":"Point"}
}