{
  "type": "Feature",
  "properties": {
    "addr:full":"Auweg 25 Henri-chapelle Li\u00e8ge 4841",
    "addr:housenumber":"25",
    "addr:postcode":"4841",
    "addr:street":"Auweg;Henri-Chapelle Lie\u0300Ge",
    "iso:country":"BE",
    "sg:address":"Auweg 25",
    "sg:city":"Henri-chapelle",
    "sg:orig_category":"Verhuur bouwmachines",
    "sg:phone":"+32 495 32 81 97",
    "sg:postcode":"4841",
    "sg:province":"Li\u00e8ge",
    "wof:name":"Echafaudal",
    "wof:placetype":"venue"
},
  "geometry": {"coordinates":[5.9072971344,50.6513442993],"type":"Point"}
}