{
  "type": "Feature",
  "properties": {
    "iso:country":"BE",
    "sg:address":"Rue De Vogen\u00e9e 19",
    "sg:city":"Walcourt",
    "sg:classifiers":[
        {
            "category":"Retail",
            "subcategory":"Veterinary Services",
            "type":"Services"
        }
    ],
    "sg:phone":"+32 71 61 13 54",
    "sg:postcode":"5650",
    "sg:province":"Namur",
    "sg:tags":[
        "veterinarian"
    ],
    "wof:name":"Gouverneur A",
    "wof:placetype":"venue"
},
  "geometry": {"coordinates":[4.4410729408,50.2511062622],"type":"Point"}
}