{
  "type": "Feature",
  "properties": {
    "iso:country":"BE",
    "sg:address":"Klaverheide 41",
    "sg:city":"Brasschaat",
    "sg:classifiers":[
        {
            "category":"Personal",
            "subcategory":"Beauty Salon",
            "type":"Services"
        }
    ],
    "sg:phone":"+32 3 652 04 31",
    "sg:postcode":"2930",
    "sg:province":"Antwerpen",
    "wof:name":"Camby M",
    "wof:placetype":"venue"
},
  "geometry": {"coordinates":[4.5038428307,51.3139877319],"type":"Point"}
}