{
  "type": "Feature",
  "properties": {
    "iso:country":"BE",
    "sg:address":"Rue De Valenciennes 104",
    "sg:city":"Qui\u00e9vrain",
    "sg:classifiers":[
        {
            "category":"Bars & Pubs",
            "type":"Food & Drink"
        }
    ],
    "sg:phone":"+32 65 43 16 04",
    "sg:postcode":"7380",
    "sg:province":"Hainaut",
    "wof:name":"Fran\u00e7ais",
    "wof:placetype":"venue"
},
  "geometry": {"coordinates":[3.6762859821,50.4039916992],"type":"Point"}
}