{
  "type": "Feature",
  "properties": {
    "addr:full":"Rue De La Gare 73 Bertrix Luxembourg 6880",
    "addr:housenumber":"73",
    "addr:postcode":"6880",
    "addr:street":"Rue De La Gare",
    "iso:country":"BE",
    "sg:address":"Rue De La Gare 73",
    "sg:city":"Bertrix",
    "sg:orig_category":"Openbare bibliotheken and archieven",
    "sg:phone":"+32 61 41 50 19",
    "sg:postcode":"6880",
    "sg:province":"Luxembourg",
    "wof:name":"Biblioth\u00c8que Publique",
    "wof:placetype":"venue"
},
  "geometry": {"coordinates":[5.2586212158,49.8548240662],"type":"Point"}
}