{
  "type": "Feature",
  "properties": {
    "addr:full":"Warandestraat 4 Zele Oost-Vlaanderen 9240",
    "addr:housenumber":"4",
    "addr:postcode":"9240",
    "addr:street":"Warandestraat",
    "iso:country":"BE",
    "sg:address":"Warandestraat 4",
    "sg:city":"Zele",
    "sg:classifiers":[
        {
            "category":"Retail",
            "subcategory":"Auto Rental",
            "type":"Services"
        }
    ],
    "sg:phone":"+32 52 44 59 28",
    "sg:postcode":"9240",
    "sg:province":"Oost-Vlaanderen",
    "sg:tags":[
        "engine",
        "diesel",
        "-"
    ],
    "wof:name":"M.t.z.",
    "wof:placetype":"venue"
},
  "geometry": {"coordinates":[4.0474920273,51.0791320801],"type":"Point"}
}