{
  "type": "Feature",
  "properties": {
    "addr:full":"Horingstraat 14 Meldert-aalst Oost-Vlaanderen 9310",
    "addr:housenumber":"14",
    "addr:postcode":"9310",
    "addr:street":"Horingstraat;Oost-Vlaanderen",
    "iso:country":"BE",
    "sg:address":"Horingstraat 14",
    "sg:city":"Meldert-aalst",
    "sg:classifiers":[
        {
            "category":"Wholesale",
            "subcategory":"Vending Machines",
            "type":"Manufacturing & Wholesale Goods"
        }
    ],
    "sg:phone":"+32 53 67 07 89",
    "sg:postcode":"9310",
    "sg:province":"Oost-Vlaanderen",
    "sg:tags":[
        "packaging",
        "used",
        "machines"
    ],
    "wof:name":"Moriplas",
    "wof:placetype":"venue"
},
  "geometry": {"coordinates":[4.098400116,50.9477767944],"type":"Point"}
}