{
  "type": "Feature",
  "properties": {
    "addr:full":"Baarledorpstraat 60 Gent Oost-Vlaanderen 9031",
    "addr:housenumber":"60",
    "addr:postcode":"9031",
    "addr:street":"Baarledorpstraat;Oost-Vlaanderen",
    "iso:country":"BE",
    "sg:address":"Baarledorpstraat 60",
    "sg:city":"Gent",
    "sg:classifiers":[
        {
            "category":"Personal",
            "subcategory":"Beauty Salon",
            "type":"Services"
        }
    ],
    "sg:phone":"+32 9 282 49 45",
    "sg:postcode":"9031",
    "sg:province":"Oost-Vlaanderen",
    "sg:tags":[
        "de",
        "coiffure"
    ],
    "wof:name":"Barelse Hairshop",
    "wof:placetype":"venue"
},
  "geometry": {"coordinates":[3.620290041,51.0372390747],"type":"Point"}
}