{
  "type": "Feature",
  "properties": {
    "addr:full":"Rue Du Zenith 40 Bruxelles Bruxelles-Capitale 1082",
    "addr:housenumber":"40",
    "addr:postcode":"1082",
    "addr:street":"Rue Du Zenith",
    "iso:country":"BE",
    "sg:address":"Rue Du Zenith 40",
    "sg:city":"Bruxelles",
    "sg:classifiers":[
        {
            "category":"Manufacturing",
            "subcategory":"Textiles",
            "type":"Manufacturing & Wholesale Goods"
        }
    ],
    "sg:phone":"+32 2 465 10 88",
    "sg:postcode":"1082",
    "sg:province":"Bruxelles-Capitale",
    "sg:tags":[
        "fab",
        "diver"
    ],
    "wof:name":"A.a. Belgaprint",
    "wof:placetype":"venue"
},
  "geometry": {"coordinates":[4.2818422318,50.864074707],"type":"Point"}
}