{
  "type": "Feature",
  "properties": {
    "addr:full":"Den Geer 21 Antwerpen Antwerpen 2180",
    "addr:housenumber":"21",
    "addr:postcode":"2180",
    "addr:street":"Den Geer",
    "iso:country":"BE",
    "sg:address":"Den Geer 21",
    "sg:city":"Antwerpen",
    "sg:classifiers":[
        {
            "category":"Cafe",
            "type":"Food & Drink"
        }
    ],
    "sg:phone":"+32 3 541 42 28",
    "sg:postcode":"2180",
    "sg:province":"Antwerpen",
    "sg:tags":[
        "caf\u00e9s"
    ],
    "wof:name":"Caf\u00c9 \u00b4t Venneke",
    "wof:placetype":"venue"
},
  "geometry": {"coordinates":[4.4182572365,51.2778625488],"type":"Point"}
}