{
  "type": "Feature",
  "properties": {
    "iso:country":"BE",
    "sg:address":"Enclus Du Haut 35",
    "sg:city":"Mont-de-l'enclus",
    "sg:classifiers":[
        {
            "category":"Cafe",
            "type":"Food & Drink"
        }
    ],
    "sg:phone":"+32 69 45 45 54",
    "sg:postcode":"7750",
    "sg:province":"Hainaut",
    "sg:tags":[
        "caf\u00e9s"
    ],
    "wof:name":"Au Petit Coin",
    "wof:placetype":"venue"
},
  "geometry": {"coordinates":[5.7178230286,47.0204772949],"type":"Point"}
}