{
  "type": "Feature",
  "properties": {
    "iso:country":"BE",
    "sg:address":"Smedenstraat 90",
    "sg:city":"Knokke-heist",
    "sg:orig_category":"HERSTELLING ELEKTRISCHE HUISHOUDAPPARATEN Huishoudapparaten, televisies and radio's Telecommunicatie",
    "sg:phone":"+32 50 61 40 69",
    "sg:postcode":"8300",
    "sg:province":"West-Vlaanderen",
    "wof:name":"Kr\u00cbfel",
    "wof:placetype":"venue"
},
  "geometry": {"coordinates":[3.2894060612,51.3377952576],"type":"Point"}
}