{
  "type": "Feature",
  "properties": {
    "addr:full":"Rue Prince Albert 1 Welkenraedt Li\u00e8ge 4840",
    "addr:housenumber":"1",
    "addr:postcode":"4840",
    "addr:street":"Rue Prince Albert",
    "iso:country":"BE",
    "sg:address":"Rue Prince Albert 1",
    "sg:city":"Welkenraedt",
    "sg:classifiers":[
        {
            "category":"Professional",
            "subcategory":"Accounting & Tax Preparation",
            "type":"Services"
        }
    ],
    "sg:phone":"+32 87 88 05 53",
    "sg:postcode":"4840",
    "sg:province":"Li\u00e8ge",
    "sg:tags":[
        "bookkeeper"
    ],
    "wof:name":"Pirnay M",
    "wof:placetype":"venue"
},
  "geometry": {"coordinates":[5.9767618179,50.6609077454],"type":"Point"}
}