{
  "type": "Feature",
  "properties": {
    "addr:full":"Aarlenstraat 37ba Brussel/bruxelles Bruxelles-Capitale 1000",
    "addr:housenumber":"37ba",
    "addr:postcode":"1000",
    "addr:street":"Aarlenstraat;/",
    "iso:country":"BE",
    "sg:address":"Aarlenstraat 37ba",
    "sg:city":"Brussel/bruxelles",
    "sg:classifiers":[
        {
            "category":"Cafe",
            "type":"Food & Drink"
        }
    ],
    "sg:phone":"+32 2 230 47 47",
    "sg:postcode":"1000",
    "sg:province":"Bruxelles-Capitale",
    "sg:tags":[
        "caf\u00e9s"
    ],
    "wof:name":"C A R P E",
    "wof:placetype":"venue"
},
  "geometry": {"coordinates":[4.3730759621,50.8407440186],"type":"Point"}
}