{
  "type": "Feature",
  "properties": {
    "iso:country":"BE",
    "sg:address":"Rue De La Fenaison 25",
    "sg:city":"Ganshoren/ganshoren",
    "sg:classifiers":[
        {
            "category":"Personal",
            "subcategory":"Beauty Salon",
            "type":"Services"
        }
    ],
    "sg:phone":"+32 2 428 39 26",
    "sg:postcode":"1083",
    "sg:province":"Bruxelles-Capitale",
    "sg:tags":[
        "de",
        "coiffure"
    ],
    "wof:name":"Jacques Callens",
    "wof:placetype":"venue"
},
  "geometry": {"coordinates":[4.3199038506,50.8740768433],"type":"Point"}
}