{
  "type": "Feature",
  "properties": {
    "addr:full":"Lamorinierestraat 31-37 Antwerpen Antwerpen 2018",
    "addr:postcode":"31-37;2018",
    "addr:street":"Lamorinierestraat",
    "iso:country":"BE",
    "sg:address":"Lamorinierestraat 31-37",
    "sg:city":"Antwerpen",
    "sg:classifiers":[
        {
            "category":"Wholesale",
            "subcategory":"Books, Periodicals, & Newspapers",
            "type":"Manufacturing & Wholesale Goods"
        }
    ],
    "sg:phone":"+32 3 200 45 00",
    "sg:postcode":"2018",
    "sg:province":"Antwerpen",
    "sg:tags":[
        "publisher"
    ],
    "wof:name":"Uitgeverij De Boeck",
    "wof:placetype":"venue"
},
  "geometry": {"coordinates":[4.4234519005,51.2068595886],"type":"Point"}
}