{
  "type": "Feature",
  "properties": {
    "addr:full":"Kleine Dweersstraat 34e Temse Oost-Vlaanderen 9140",
    "addr:housenumber":"34e",
    "addr:postcode":"9140",
    "addr:street":"Kleine Dweersstraat",
    "iso:country":"BE",
    "sg:address":"Kleine Dweersstraat 34e",
    "sg:city":"Temse",
    "sg:classifiers":[
        {
            "category":"Professional",
            "subcategory":"Computer Services",
            "type":"Services"
        }
    ],
    "sg:phone":"+32 3 711 31 88",
    "sg:postcode":"9140",
    "sg:province":"Oost-Vlaanderen",
    "sg:tags":[
        "-",
        "processing",
        "data",
        "software"
    ],
    "wof:name":"H.c.p. Bvba",
    "wof:placetype":"venue"
},
  "geometry": {"coordinates":[4.2034702301,51.1366958618],"type":"Point"}
}