{
  "type": "Feature",
  "properties": {
    "iso:country":"BE",
    "sg:address":"Rue De La Sir\u00e8ne 16",
    "sg:city":"Li\u00e8ge 1",
    "sg:classifiers":[
        {
            "category":"Government",
            "subcategory":"Post Office",
            "type":"Public Place"
        }
    ],
    "sg:phone":"+32 4 222 01 26",
    "sg:postcode":"4000",
    "sg:province":"Li\u00e8ge",
    "sg:tags":[
        "stamp"
    ],
    "wof:name":"Philami",
    "wof:placetype":"venue"
},
  "geometry": {"coordinates":[5.5728259087,50.6409187317],"type":"Point"}
}