{
  "type": "Feature",
  "properties": {
    "addr:full":"Rode-kruisplein 9 Harelbeke West-Vlaanderen 8530",
    "addr:housenumber":"9",
    "addr:postcode":"8530",
    "addr:street":"Rode-Kruisplein",
    "iso:country":"BE",
    "sg:address":"Rode-kruisplein 9",
    "sg:city":"Harelbeke",
    "sg:orig_category":"Epiceries",
    "sg:phone":"+32 56 71 50 63",
    "sg:postcode":"8530",
    "sg:province":"West-Vlaanderen",
    "wof:name":"Supermarkt",
    "wof:placetype":"venue"
},
  "geometry": {"coordinates":[3.3078989983,50.8620262146],"type":"Point"}
}