{
  "type": "Feature",
  "properties": {
    "addr:full":"Avenue Adolphe Buyl 46 Bruxelles (ixelles) Bruxelles-Capitale 1050",
    "addr:housenumber":"46",
    "addr:postcode":"1050",
    "addr:street":"Avenue Adolphe Buyl",
    "iso:country":"BE",
    "sg:address":"Avenue Adolphe Buyl 46",
    "sg:city":"Bruxelles (ixelles)",
    "sg:classifiers":[
        {
            "category":"Retail",
            "subcategory":"Repair Shop",
            "type":"Services"
        }
    ],
    "sg:phone":"+32 2 640 97 21",
    "sg:postcode":"1050",
    "sg:province":"Bruxelles-Capitale",
    "sg:tags":[
        "-",
        "clothing",
        "alteration"
    ],
    "wof:name":"Ermis",
    "wof:placetype":"venue"
},
  "geometry": {"coordinates":[4.3811159134,50.8173522949],"type":"Point"}
}