{
  "type": "Feature",
  "properties": {
    "addr:full":"Rue Th\u00e9odore De Cuyper 38 Bruxelles (woluwe-saint-lambert) Bruxelles-Capitale 1200",
    "addr:housenumber":"38",
    "addr:postcode":"1200",
    "addr:street":"Rue The\u0301Odore De Cuyper",
    "iso:country":"BE",
    "sg:address":"Rue Th\u00e9odore De Cuyper 38",
    "sg:city":"Bruxelles (woluwe-saint-lambert)",
    "sg:classifiers":[
        {
            "category":"Health Services",
            "subcategory":"Health Practitioner",
            "type":"Services"
        }
    ],
    "sg:phone":"+32 2 779 41 58",
    "sg:postcode":"1200",
    "sg:province":"Bruxelles-Capitale",
    "sg:tags":[
        "physiotherapist"
    ],
    "wof:name":"Moraine H",
    "wof:placetype":"venue"
},
  "geometry": {"coordinates":[4.4323120117,50.8497848511],"type":"Point"}
}