{
  "type": "Feature",
  "properties": {
    "iso:country":"BE",
    "sg:address":"Molenstraat 14",
    "sg:city":"Brakel",
    "sg:orig_category":"MEUBELONTWERP AND -INSTALLATIE",
    "sg:phone":"+32 55 42 14 28",
    "sg:postcode":"9661",
    "sg:province":"Oost-Vlaanderen",
    "wof:name":"De Vleeschouwer Luc",
    "wof:placetype":"venue"
},
  "geometry": {"coordinates":[3.8031690121,50.7778816223],"type":"Point"}
}