{
  "type": "Feature",
  "properties": {
    "addr:full":"Welvaartstraat 157 Berlaar Antwerpen 2590",
    "addr:housenumber":"157",
    "addr:postcode":"2590",
    "addr:street":"Welvaartstraat",
    "iso:country":"BE",
    "sg:address":"Welvaartstraat 157",
    "sg:city":"Berlaar",
    "sg:orig_category":"Pleisterwerk",
    "sg:phone":"+32 3 482 17 65",
    "sg:postcode":"2590",
    "sg:province":"Antwerpen",
    "wof:name":"Dieltjens",
    "wof:placetype":"venue"
},
  "geometry": {"coordinates":[4.640581131,51.1050949097],"type":"Point"}
}