{
  "type": "Feature",
  "properties": {
    "iso:country":"BE",
    "sg:address":"Lochtemanweg 122",
    "sg:city":"Heusden-zolder (heusden)",
    "sg:classifiers":[
        {
            "category":"Real Estate",
            "subcategory":"Surveying",
            "type":"Services"
        }
    ],
    "sg:phone":"+32 11 37 88 09",
    "sg:postcode":"3550",
    "sg:province":"Limburg",
    "sg:tags":[
        "lettering",
        "letter"
    ],
    "wof:name":"Maris Events",
    "wof:placetype":"venue"
},
  "geometry": {"coordinates":[5.2335782051,51.0299034119],"type":"Point"}
}