{
  "type": "Feature",
  "properties": {
    "addr:full":"Langeveld 20 Holsbeek Vlaams-Brabant 3220",
    "addr:housenumber":"20",
    "addr:postcode":"3220",
    "addr:street":"Langeveld",
    "iso:country":"BE",
    "sg:address":"Langeveld 20",
    "sg:city":"Holsbeek",
    "sg:orig_category":"Travaux de pl\u00e2trage",
    "sg:phone":"+32 16 44 46 49",
    "sg:postcode":"3220",
    "sg:province":"Vlaams-Brabant",
    "wof:name":"Rene Van Bever",
    "wof:placetype":"venue"
},
  "geometry": {"coordinates":[4.748541832,50.9185752869],"type":"Point"}
}