{
  "type": "Feature",
  "properties": {
    "addr:full":"Rue Du Ch\u00cane 88 Liege Li\u00e8ge 4031",
    "addr:housenumber":"88",
    "addr:postcode":"4031",
    "addr:street":"Rue Du Che\u0302Ne",
    "iso:country":"BE",
    "sg:address":"Rue Du Ch\u00cane 88",
    "sg:city":"Liege",
    "sg:orig_category":"Installatie van houten of kunststof schrijnwerk",
    "sg:phone":"+32 4 344 20 94",
    "sg:postcode":"4031",
    "sg:province":"Li\u00e8ge",
    "wof:name":"Weyens M",
    "wof:placetype":"venue"
},
  "geometry": {"coordinates":[5.5801138878,50.611541748],"type":"Point"}
}