{
  "type": "Feature",
  "properties": {
    "iso:country":"BE",
    "sg:address":"Bergense Steenweg 1035ba",
    "sg:city":"Anderlecht/anderlecht",
    "sg:orig_category":"Banken and kredietinstellingen",
    "sg:phone":"+32 2 523 74 39",
    "sg:postcode":"1070",
    "sg:province":"Bruxelles-Capitale",
    "wof:name":"Bizet Finances",
    "wof:placetype":"venue"
},
  "geometry": {"coordinates":[4.2970571518,50.8250312805],"type":"Point"}
}