{
  "type": "Feature",
  "properties": {
    "iso:country":"BE",
    "sg:address":"Brugstraat 7",
    "sg:city":"Gingelom (montenaken)",
    "sg:classifiers":[
        {
            "category":"Professional",
            "subcategory":"Testing Lab",
            "type":"Services"
        }
    ],
    "sg:phone":"+32 11 88 18 85",
    "sg:postcode":"3890",
    "sg:province":"Limburg",
    "sg:tags":[
        "chemist"
    ],
    "wof:name":"Thierie",
    "wof:placetype":"venue"
},
  "geometry": {"coordinates":[5.1287379265,50.7209243774],"type":"Point"}
}