{
  "type": "Feature",
  "properties": {
    "addr:full":"Rue D'havr\u00e9 115 Mons Hainaut 7000",
    "addr:housenumber":"115",
    "addr:postcode":"7000",
    "addr:street":"Rue D'Havre \u0301;Hainaut",
    "iso:country":"BE",
    "sg:address":"Rue D'havr\u00e9 115",
    "sg:city":"Mons",
    "sg:classifiers":[
        {
            "category":"Communications",
            "subcategory":"Film & Video Production",
            "type":"Services"
        }
    ],
    "sg:phone":"+32 65 31 51 57",
    "sg:postcode":"7000",
    "sg:province":"Hainaut",
    "sg:tags":[
        "hiring",
        "-"
    ],
    "wof:name":"Game",
    "wof:placetype":"venue"
},
  "geometry": {"coordinates":[3.9576818943,50.4540481567],"type":"Point"}
}