{
  "type": "Feature",
  "properties": {
    "addr:full":"Oude Paanderstraat 37 Meulebeke West-Vlaanderen 8760",
    "addr:housenumber":"37",
    "addr:postcode":"8760",
    "addr:street":"Oude Paanderstraat",
    "iso:country":"BE",
    "sg:address":"Oude Paanderstraat 37",
    "sg:city":"Meulebeke",
    "sg:classifiers":[
        {
            "category":"Bakery",
            "type":"Food & Drink"
        }
    ],
    "sg:phone":"+32 51 48 87 35",
    "sg:postcode":"8760",
    "sg:province":"West-Vlaanderen",
    "sg:tags":[
        "confectioner",
        "baker"
    ],
    "wof:name":"Sintubin A",
    "wof:placetype":"venue"
},
  "geometry": {"coordinates":[3.3121778965,50.9413032532],"type":"Point"}
}