{
  "type": "Feature",
  "properties": {
    "addr:full":"Kardinaal Cardijnlaan 10 Beerse Antwerpen 2340",
    "addr:housenumber":"10",
    "addr:postcode":"2340",
    "addr:street":"Kardinaal Cardijnlaan",
    "iso:country":"BE",
    "sg:address":"Kardinaal Cardijnlaan 10",
    "sg:city":"Beerse",
    "sg:classifiers":[
        {
            "category":"Real Estate",
            "subcategory":"Architect",
            "type":"Services"
        }
    ],
    "sg:phone":"+32 14 61 37 03",
    "sg:postcode":"2340",
    "sg:province":"Antwerpen",
    "wof:name":"Van De Ven M",
    "wof:placetype":"venue"
},
  "geometry": {"coordinates":[4.827149868,51.3170204163],"type":"Point"}
}