{
  "type": "Feature",
  "properties": {
    "addr:full":". Oostende (groot) West-Vlaanderen 8400",
    "addr:postcode":"8400",
    "addr:street":"Oostende Groot West-Vlaanderen",
    "iso:country":"BE",
    "sg:address":".",
    "sg:city":"Oostende (groot)",
    "sg:orig_category":"Apotheken",
    "sg:phone":"+32 900 10 500",
    "sg:postcode":"8400",
    "sg:province":"West-Vlaanderen",
    "wof:name":"Apothekers Van Wacht",
    "wof:placetype":"venue"
},
  "geometry": {"coordinates":[2.9126999378,51.2312583923],"type":"Point"}
}