{
  "type": "Feature",
  "properties": {
    "addr:full":"Chauss\u00c9e De Bruxelles 527 Les Bons Villers Hainaut 6210",
    "addr:housenumber":"527",
    "addr:postcode":"6210",
    "addr:street":"Chausse\u0301E De Bruxelles",
    "iso:country":"BE",
    "sg:address":"Chauss\u00c9e De Bruxelles 527",
    "sg:city":"Les Bons Villers",
    "sg:orig_category":"Supermarch\u00e9s. Epiceries",
    "sg:phone":"+32 71 85 40 24",
    "sg:postcode":"6210",
    "sg:province":"Hainaut",
    "wof:name":"Ad Delhaize",
    "wof:placetype":"venue"
},
  "geometry": {"coordinates":[4.4511561394,50.5378227234],"type":"Point"}
}