{
  "type": "Feature",
  "properties": {
    "iso:country":"BE",
    "sg:address":"Abdijstraat 54",
    "sg:city":"Elsene/ixelles",
    "sg:orig_category":"Notarissen",
    "sg:phone":"+32 2 340 00 20",
    "sg:postcode":"1050",
    "sg:province":"Bruxelles-Capitale",
    "wof:name":"Ingeveld B.",
    "wof:placetype":"venue"
},
  "geometry": {"coordinates":[4.364361763,50.8185157776],"type":"Point"}
}