{
  "type": "Feature",
  "properties": {
    "addr:full":"Rue De L'eglise 3 Mont-de-l'enclus (amougies) Hainaut 7750",
    "addr:housenumber":"3",
    "addr:postcode":"7750",
    "addr:street":"Rue De L'Eglise;Amougies Hainaut",
    "iso:country":"BE",
    "sg:address":"Rue De L'eglise 3",
    "sg:city":"Mont-de-l'enclus (amougies)",
    "sg:classifiers":[
        {
            "category":"Home & Garden",
            "subcategory":"Furniture",
            "type":"Retail Goods"
        }
    ],
    "sg:phone":"+32 69 76 84 96",
    "sg:postcode":"7750",
    "sg:province":"Hainaut",
    "sg:tags":[
        "-"
    ],
    "wof:name":"S\u00e9lection Meubles Sprl",
    "wof:placetype":"venue"
},
  "geometry": {"coordinates":[6.4035139084,49.1109848022],"type":"Point"}
}