{
  "type": "Feature",
  "properties": {
    "addr:full":"Stuyvenbergbaan Willebroek Antwerpen 2830",
    "addr:postcode":"2830",
    "addr:street":"Stuyvenbergbaan",
    "iso:country":"BE",
    "sg:address":"Stuyvenbergbaan",
    "sg:city":"Willebroek",
    "sg:orig_category":"Mobilier and \u00e9quipement m\u00e9nager Gr",
    "sg:phone":"+32 3 886 08 83",
    "sg:postcode":"2830",
    "sg:province":"Antwerpen",
    "wof:name":"Wilrom",
    "wof:placetype":"venue"
},
  "geometry": {"coordinates":[4.3868670464,51.0705986023],"type":"Point"}
}