{
  "type": "Feature",
  "properties": {
    "addr:full":"17 Rue Rabelais 1348 Louvain-la-neuve 17",
    "addr:housenumber":"17;17",
    "addr:postcode":"1348",
    "addr:street":"Rue Rabelais;Louvain-La-Neuve",
    "iso:country":"BE",
    "sg:address":"17",
    "sg:city":"Rue Rabelais 1348 Louvain-la-neuve",
    "sg:classifiers":[
        {
            "category":"Professional",
            "subcategory":"Business Services",
            "type":"Services"
        }
    ],
    "sg:phone":"+32 10 45 28 46",
    "sg:postcode":"17",
    "sg:tags":[
        "training",
        "advice"
    ],
    "wof:name":"Bief Nv",
    "wof:placetype":"venue"
},
  "geometry": {"coordinates":[4.6131448746,50.6692504883],"type":"Point"}
}