{
  "type": "Feature",
  "properties": {
    "addr:full":"Victor Bocqu\u00c9straat 11 Aalst Oost-Vlaanderen 9300",
    "addr:housenumber":"11",
    "addr:postcode":"9300",
    "addr:street":"Victor Bocque\u0301Straat",
    "iso:country":"BE",
    "sg:address":"Victor Bocqu\u00c9straat 11",
    "sg:city":"Aalst",
    "sg:orig_category":"Bouwmaterialen Gh Bouwwerktuigen Gh Gespecialiseerde residenti\u00eble bouw",
    "sg:phone":"+32 53 77 48 28",
    "sg:postcode":"9300",
    "sg:province":"Oost-Vlaanderen",
    "wof:name":"Grout Techniek",
    "wof:placetype":"venue"
},
  "geometry": {"coordinates":[4.0380678177,50.9521141052],"type":"Point"}
}