{
  "type": "Feature",
  "properties": {
    "iso:country":"BE",
    "sg:address":"Rue G. De Lombaerde 41",
    "sg:city":"Bruxelles (evere)",
    "sg:classifiers":[
        {
            "category":"Manufacturing",
            "subcategory":"Furniture",
            "type":"Manufacturing & Wholesale Goods"
        }
    ],
    "sg:phone":"+32 2 726 04 40",
    "sg:postcode":"1140",
    "sg:province":"Bruxelles-Capitale",
    "sg:tags":[
        "made",
        "-",
        "custom"
    ],
    "wof:name":"Allan Furnitures",
    "wof:placetype":"venue"
},
  "geometry": {"coordinates":[4.4201860428,50.8588867188],"type":"Point"}
}