{
  "type": "Feature",
  "properties": {
    "iso:country":"BE",
    "sg:address":"Tervurenlaan 89",
    "sg:city":"Etterbeek/etterbeek",
    "sg:orig_category":"Baby- and kinderkleding Dameskledingzaken Herenkledingzaken",
    "sg:phone":"+32 2 734 50 95",
    "sg:postcode":"1040",
    "sg:province":"Bruxelles-Capitale",
    "wof:name":"M.l.b.",
    "wof:placetype":"venue"
},
  "geometry": {"coordinates":[4.4029722214,50.8380241394],"type":"Point"}
}