{
  "type": "Feature",
  "properties": {
    "iso:country":"BE",
    "sg:address":"Clos De La Couronne 29",
    "sg:city":"Mouscron (herseaux)",
    "sg:classifiers":[
        {
            "category":"Health Services",
            "subcategory":"Health Practitioner",
            "type":"Services"
        }
    ],
    "sg:phone":"+32 56 48 78 91",
    "sg:postcode":"7712",
    "sg:province":"Hainaut",
    "sg:tags":[
        "physiotherapist"
    ],
    "wof:name":"Graveline J",
    "wof:placetype":"venue"
},
  "geometry": {"coordinates":[3.266479969,50.7176246643],"type":"Point"}
}