{
  "type": "Feature",
  "properties": {
    "iso:country":"BE",
    "sg:address":"Tennislaan 4",
    "sg:city":"Overpelt",
    "sg:classifiers":[
        {
            "category":"Sports & Exercise",
            "subcategory":"Skate Park",
            "type":"Entertainment"
        }
    ],
    "sg:phone":"+32 11 66 11 54",
    "sg:postcode":"3900",
    "sg:province":"Limburg",
    "sg:tags":[
        "mushroom"
    ],
    "wof:name":"Becochamp Nv",
    "wof:placetype":"venue"
},
  "geometry": {"coordinates":[5.4028120041,51.2324867249],"type":"Point"}
}