{
  "type": "Feature",
  "properties": {
    "addr:full":"Papestraat 1 Alveringem West-Vlaanderen 8690",
    "addr:housenumber":"1",
    "addr:postcode":"8690",
    "addr:street":"Papestraat",
    "iso:country":"BE",
    "sg:address":"Papestraat 1",
    "sg:city":"Alveringem",
    "sg:orig_category":"Eleveurs and marchands de porcs. Eleveurs de bovins",
    "sg:phone":"+32 58 28 97 38",
    "sg:postcode":"8690",
    "sg:province":"West-Vlaanderen",
    "wof:name":"Gabriel Demaeght",
    "wof:placetype":"venue"
},
  "geometry": {"coordinates":[2.7025101185,51.0059967041],"type":"Point"}
}