{
  "type": "Feature",
  "properties": {
    "iso:country":"BE",
    "sg:address":"Rue Du Bosquet 3",
    "sg:city":"Ottignies-louvain-la-neuve (louvain-la-neuve)",
    "sg:classifiers":[
        {
            "category":"Professional",
            "subcategory":"Testing Lab",
            "type":"Services"
        }
    ],
    "sg:phone":"+32 10 43 70 60",
    "sg:postcode":"1348",
    "sg:province":"Brabant Wallon",
    "sg:tags":[
        "laboratory",
        "-",
        "machines",
        "apparatus",
        "supply"
    ],
    "wof:name":"Euro Biochem Scrl Scrl",
    "wof:placetype":"venue"
},
  "geometry": {"coordinates":[4.6317892075,50.6617698669],"type":"Point"}
}