{
  "type": "Feature",
  "properties": {
    "iso:country":"BE",
    "sg:address":"Nijverheidstraat 16",
    "sg:city":"Staden",
    "sg:classifiers":[
        {
            "category":"Professional",
            "subcategory":"Art Services",
            "type":"Services"
        }
    ],
    "sg:phone":"+32 51 70 01 23",
    "sg:postcode":"8840",
    "sg:province":"West-Vlaanderen",
    "sg:tags":[
        "designer",
        "display"
    ],
    "wof:name":"Segers A",
    "wof:placetype":"venue"
},
  "geometry": {"coordinates":[2.9978089333,50.9846878052],"type":"Point"}
}