{
  "type": "Feature",
  "properties": {
    "addr:full":"Schoolstraat 7 Assenede Oost-Vlaanderen 9960",
    "addr:housenumber":"7",
    "addr:postcode":"9960",
    "addr:street":"Schoolstraat",
    "iso:country":"BE",
    "sg:address":"Schoolstraat 7",
    "sg:city":"Assenede",
    "sg:classifiers":[
        {
            "category":"Personal",
            "subcategory":"Shoe Repair & Shine",
            "type":"Services"
        }
    ],
    "sg:phone":"+32 9 344 86 44",
    "sg:postcode":"9960",
    "sg:province":"Oost-Vlaanderen",
    "sg:tags":[
        "shoemaker"
    ],
    "wof:name":"Peter Schoen & Slotenmakerij",
    "wof:placetype":"venue"
},
  "geometry": {"coordinates":[3.7517299652,51.2253227234],"type":"Point"}
}