{
  "type": "Feature",
  "properties": {
    "addr:full":"De Berlaymontstraat 17 Hasselt (sint-lambrechts-herk) Limburg 3500",
    "addr:housenumber":"17",
    "addr:postcode":"3500",
    "addr:street":"Berlaymontstraat",
    "iso:country":"BE",
    "sg:address":"De Berlaymontstraat 17",
    "sg:city":"Hasselt (sint-lambrechts-herk)",
    "sg:classifiers":[
        {
            "category":"Personal",
            "subcategory":"Beauty Salon",
            "type":"Services"
        }
    ],
    "sg:phone":"+32 11 59 60 84",
    "sg:postcode":"3500",
    "sg:province":"Limburg",
    "sg:tags":[
        "lady",
        "-",
        "hairdressing"
    ],
    "wof:name":"Fasil",
    "wof:placetype":"venue"
},
  "geometry": {"coordinates":[5.3088788986,50.8980865479],"type":"Point"}
}