{
  "type": "Feature",
  "properties": {
    "iso:country":"BE",
    "sg:address":"Kronenburgstraat 84",
    "sg:city":"Antwerpen",
    "sg:orig_category":"Artistes ind\u00e9pendants",
    "sg:phone":"+32 3 248 15 01",
    "sg:postcode":"2000",
    "sg:province":"Antwerpen",
    "wof:name":"Pieter Van Der Sman",
    "wof:placetype":"venue"
},
  "geometry": {"coordinates":[4.3993821144,51.2116737366],"type":"Point"}
}