{
  "type": "Feature",
  "properties": {
    "addr:full":"Stationsstraat 21 Oostrozebeke West-Vlaanderen 8780",
    "addr:housenumber":"21",
    "addr:postcode":"8780",
    "addr:street":"Stationsstraat",
    "iso:country":"BE",
    "sg:address":"Stationsstraat 21",
    "sg:city":"Oostrozebeke",
    "sg:orig_category":"Banques and organismes de cr\u00e9dit",
    "sg:phone":"+32 56 66 66 79",
    "sg:postcode":"8780",
    "sg:province":"West-Vlaanderen",
    "wof:name":"Bank Van Roeselare",
    "wof:placetype":"venue"
},
  "geometry": {"coordinates":[3.3350510597,50.9190673828],"type":"Point"}
}