{
  "type": "Feature",
  "properties": {
    "addr:full":"Chauss\u00c9e Roi Baudouin 243 Mons Hainaut 7031",
    "addr:housenumber":"243",
    "addr:postcode":"7031",
    "addr:street":"Chausse\u0301E Roi Baudouin;Hainaut",
    "iso:country":"BE",
    "sg:address":"Chauss\u00c9e Roi Baudouin 243",
    "sg:city":"Mons",
    "sg:orig_category":"Installatie van houten of kunststof schrijnwerk",
    "sg:phone":"+32 65 87 26 76",
    "sg:postcode":"7031",
    "sg:province":"Hainaut",
    "wof:name":"Casagrande",
    "wof:placetype":"venue"
},
  "geometry": {"coordinates":[4.0398697853,50.4295654297],"type":"Point"}
}