{
  "type": "Feature",
  "properties": {
    "iso:country":"BE",
    "sg:address":"Pater Ver Eeckestraat 20-3",
    "sg:city":"Izegem (kachtem)",
    "sg:classifiers":[
        {
            "category":"Home & Garden",
            "subcategory":"Carpets & Floor Coverings",
            "type":"Retail Goods"
        }
    ],
    "sg:phone":"+32 51 30 14 01",
    "sg:postcode":"8870",
    "sg:province":"West-Vlaanderen",
    "sg:tags":[
        "-"
    ],
    "wof:name":"Deleu B & G",
    "wof:placetype":"venue"
},
  "geometry": {"coordinates":[3.1950590611,50.9350814819],"type":"Point"}
}