{
  "type": "Feature",
  "properties": {
    "addr:full":"Sint-salvatorstraat 139 Gent Oost-Vlaanderen 9000",
    "addr:housenumber":"139",
    "addr:postcode":"9000",
    "addr:street":"Oost-Vlaanderen",
    "iso:country":"BE",
    "sg:address":"Sint-salvatorstraat 139",
    "sg:city":"Gent",
    "sg:orig_category":"Plomberie, chauffage and installations sanitaires",
    "sg:phone":"+32 9 224 40 43",
    "sg:postcode":"9000",
    "sg:province":"Oost-Vlaanderen",
    "wof:name":"Fa. Siersach",
    "wof:placetype":"venue"
},
  "geometry": {"coordinates":[3.7289419174,51.066570282],"type":"Point"}
}