{
  "type": "Feature",
  "properties": {
    "iso:country":"BE",
    "sg:address":"Prins Boudewijnlaan 71",
    "sg:city":"Sint-niklaas",
    "sg:classifiers":[
        {
            "category":"Building & Trades",
            "subcategory":"Construction",
            "type":"Services"
        }
    ],
    "sg:phone":"+32 3 766 50 25",
    "sg:postcode":"9100",
    "sg:province":"Oost-Vlaanderen",
    "sg:tags":[
        "gr",
        "la",
        "de",
        "\u00e9quipement",
        "pour",
        "machine",
        "location",
        "mat\u00e9riaux"
    ],
    "wof:name":"Devogeleer",
    "wof:placetype":"venue"
},
  "geometry": {"coordinates":[4.1649880409,51.1613731384],"type":"Point"}
}