{
  "type": "Feature",
  "properties": {
    "iso:country":"BE",
    "sg:address":"Kattestraat 23",
    "sg:city":"Ternat (wambeek)",
    "sg:orig_category":"Non-Classified Establishments",
    "sg:phone":"+32 53 66 02 22",
    "sg:postcode":"1741",
    "sg:province":"Vlaams-Brabant",
    "wof:name":"Alphacom International Bvba",
    "wof:placetype":"venue"
},
  "geometry": {"coordinates":[4.1298270226,50.8644447327],"type":"Point"}
}