{
  "type": "Feature",
  "properties": {
    "addr:full":"Mechelbaan 3 Sint-katelijne-waver Antwerpen 2861",
    "addr:housenumber":"3",
    "addr:postcode":"2861",
    "addr:street":"Mechelbaan",
    "iso:country":"BE",
    "sg:address":"Mechelbaan 3",
    "sg:city":"Sint-katelijne-waver",
    "sg:orig_category":"Boucheries",
    "sg:phone":"+32 15 75 45 75",
    "sg:postcode":"2861",
    "sg:province":"Antwerpen",
    "wof:name":"Beenhouwerij Dirk",
    "wof:placetype":"venue"
},
  "geometry": {"coordinates":[4.5714998245,51.0549621582],"type":"Point"}
}