{
  "type": "Feature",
  "properties": {
    "iso:country":"BE",
    "sg:address":"Molenstraat 66",
    "sg:city":"Wetteren",
    "sg:classifiers":[
        {
            "category":"Manufacturing",
            "subcategory":"Textiles",
            "type":"Manufacturing & Wholesale Goods"
        }
    ],
    "sg:phone":"+32 9 369 16 88",
    "sg:postcode":"9230",
    "sg:province":"Oost-Vlaanderen",
    "sg:tags":[
        "retail",
        "-"
    ],
    "wof:name":"Moden Liba",
    "wof:placetype":"venue"
},
  "geometry": {"coordinates":[3.8884189129,51.0042266846],"type":"Point"}
}