{
  "type": "Feature",
  "properties": {
    "iso:country":"BE",
    "sg:address":"Kanteklaarpad 17",
    "sg:city":"Schoten",
    "sg:orig_category":"Activit\u00e9s r\u00e9cr\u00e9atives diverses",
    "sg:phone":"+32 3 658 52 53",
    "sg:postcode":"2900",
    "sg:province":"Antwerpen",
    "wof:name":"Bridge Club Den Brandt",
    "wof:placetype":"venue"
},
  "geometry": {"coordinates":[4.5193600655,51.2663574219],"type":"Point"}
}