{
  "type": "Feature",
  "properties": {
    "addr:full":"Chemin Vert 21 Ath Hainaut 7800",
    "addr:housenumber":"21",
    "addr:postcode":"7800",
    "addr:street":"Chemin Vert",
    "iso:country":"BE",
    "sg:address":"Chemin Vert 21",
    "sg:city":"Ath",
    "sg:classifiers":[
        {
            "category":"Real Estate",
            "subcategory":"Architect",
            "type":"Services"
        }
    ],
    "sg:phone":"+32 68 28 19 36",
    "sg:postcode":"7800",
    "sg:province":"Hainaut",
    "wof:name":"Wellens J-m",
    "wof:placetype":"venue"
},
  "geometry": {"coordinates":[3.7906680107,50.6222381592],"type":"Point"}
}