{
  "type": "Feature",
  "properties": {
    "addr:full":"Hondeskuilstraat 18 Genk Limburg 3600",
    "addr:housenumber":"18",
    "addr:postcode":"3600",
    "addr:street":"Hondeskuilstraat",
    "iso:country":"BE",
    "sg:address":"Hondeskuilstraat 18",
    "sg:city":"Genk",
    "sg:classifiers":[
        {
            "category":"Retail",
            "subcategory":"Auto Rental",
            "type":"Services"
        }
    ],
    "sg:phone":"+32 89 62 22 89",
    "sg:postcode":"3600",
    "sg:province":"Limburg",
    "sg:tags":[
        "van",
        "hire",
        "-",
        "truck"
    ],
    "wof:name":"Kebaku Nv",
    "wof:placetype":"venue"
},
  "geometry": {"coordinates":[5.4941840172,50.9499320984],"type":"Point"}
}