{
  "type": "Feature",
  "properties": {
    "addr:full":"Rue Des Pierres 29 Bruxelles Bruxelles-Capitale 1000",
    "addr:housenumber":"29",
    "addr:postcode":"1000",
    "addr:street":"Rue Des Pierres",
    "iso:country":"BE",
    "sg:address":"Rue Des Pierres 29",
    "sg:city":"Bruxelles",
    "sg:classifiers":[
        {
            "category":"Professional",
            "subcategory":"Management & Consulting",
            "type":"Services"
        }
    ],
    "sg:phone":"+32 2 502 54 66",
    "sg:postcode":"1000",
    "sg:province":"Bruxelles-Capitale",
    "sg:tags":[
        "consultant"
    ],
    "wof:name":"Pragma Consulting Nv",
    "wof:placetype":"venue"
},
  "geometry": {"coordinates":[4.3499550819,50.8471069336],"type":"Point"}
}