{
  "type": "Feature",
  "properties": {
    "iso:country":"BE",
    "sg:address":"Verbondstraat 49",
    "sg:city":"Antwerpen",
    "sg:orig_category":"Kapsalons",
    "sg:phone":"+32 3 237 36 66",
    "sg:postcode":"2000",
    "sg:province":"Antwerpen",
    "wof:name":"Coiffure Nicky",
    "wof:placetype":"venue"
},
  "geometry": {"coordinates":[4.4001460075,51.2098236084],"type":"Point"}
}