{
  "type": "Feature",
  "properties": {
    "iso:country":"BE",
    "sg:address":"Heiakker 23",
    "sg:city":"Kapellen (mariaburg)",
    "sg:classifiers":[
        {
            "category":"Health Services",
            "subcategory":"Health Practitioner",
            "type":"Services"
        }
    ],
    "sg:phone":"+32 3 605 04 36",
    "sg:postcode":"2950",
    "sg:province":"Antwerpen",
    "sg:tags":[
        "physiotherapist"
    ],
    "wof:name":"Johnson Veerle",
    "wof:placetype":"venue"
},
  "geometry": {"coordinates":[4.4332051277,51.3026199341],"type":"Point"}
}