{
  "type": "Feature",
  "properties": {
    "addr:full":"Huidevettersstraat 34 Antwerpen Antwerpen 2000",
    "addr:housenumber":"34",
    "addr:postcode":"2000",
    "addr:street":"Huidevettersstraat",
    "iso:country":"BE",
    "sg:address":"Huidevettersstraat 34",
    "sg:city":"Antwerpen",
    "sg:classifiers":[
        {
            "category":"Shopping",
            "subcategory":"Clothing, Apparel, & Fashions",
            "type":"Retail Goods"
        }
    ],
    "sg:phone":"+32 3 234 14 06",
    "sg:postcode":"2000",
    "sg:province":"Antwerpen",
    "sg:tags":[
        "v\u00eatements",
        "pour",
        "dame"
    ],
    "wof:name":"Caroline Biss",
    "wof:placetype":"venue"
},
  "geometry": {"coordinates":[4.4052639008,51.2171401978],"type":"Point"}
}