{
  "type": "Feature",
  "properties": {
    "addr:full":"Rue Royale 129 Pecq Hainaut 7740",
    "addr:housenumber":"129",
    "addr:postcode":"7740",
    "addr:street":"Rue Royale",
    "iso:country":"BE",
    "sg:address":"Rue Royale 129",
    "sg:city":"Pecq",
    "sg:orig_category":"Editeurs de livres",
    "sg:phone":"+32 69 55 91 29",
    "sg:postcode":"7740",
    "sg:province":"Hainaut",
    "wof:name":"Editions Ariane",
    "wof:placetype":"venue"
},
  "geometry": {"coordinates":[3.3425009251,50.7036437988],"type":"Point"}
}