{
  "type": "Feature",
  "properties": {
    "addr:full":"Broekstraat 1 Tienen Vlaams-Brabant 3300",
    "addr:housenumber":"1",
    "addr:postcode":"3300",
    "addr:street":"Broekstraat",
    "iso:country":"BE",
    "sg:address":"Broekstraat 1",
    "sg:city":"Tienen",
    "sg:classifiers":[
        {
            "category":"Bars & Pubs",
            "type":"Food & Drink"
        }
    ],
    "sg:phone":"+32 16 81 16 27",
    "sg:postcode":"3300",
    "sg:province":"Vlaams-Brabant",
    "wof:name":"Patria",
    "wof:placetype":"venue"
},
  "geometry": {"coordinates":[4.9368429184,50.8066101074],"type":"Point"}
}