{
  "type": "Feature",
  "properties": {
    "addr:full":"Rue De Monnel 17 Tournai Hainaut 7500",
    "addr:housenumber":"17",
    "addr:postcode":"7500",
    "addr:street":"Rue De Monnel",
    "iso:country":"BE",
    "sg:address":"Rue De Monnel 17",
    "sg:city":"Tournai",
    "sg:classifiers":[
        {
            "category":"Professional",
            "subcategory":"Lawyer & Legal Services",
            "type":"Services"
        }
    ],
    "sg:phone":"+32 476 79 12 77",
    "sg:postcode":"7500",
    "sg:province":"Hainaut",
    "wof:name":"Vandekerkove S\u00e9verine",
    "wof:placetype":"venue"
},
  "geometry": {"coordinates":[3.3945610523,50.6088256836],"type":"Point"}
}