{
  "type": "Feature",
  "properties": {
    "iso:country":"BE",
    "sg:address":"Hasseltsesteenweg 601",
    "sg:city":"Tongeren",
    "sg:classifiers":[
        {
            "category":"Cafe",
            "type":"Food & Drink"
        }
    ],
    "sg:phone":"+32 12 23 21 06",
    "sg:postcode":"3700",
    "sg:province":"Limburg",
    "sg:tags":[
        "caf\u00e9s"
    ],
    "wof:name":"Caf\u00c9 't Meuleke",
    "wof:placetype":"venue"
},
  "geometry": {"coordinates":[5.459335804,50.7829055786],"type":"Point"}
}