{
  "type": "Feature",
  "properties": {
    "iso:country":"BE",
    "sg:address":"Kerkhofstraat 69",
    "sg:city":"Diksmuide",
    "sg:orig_category":"Supermarkten",
    "sg:phone":"+32 51 50 02 96",
    "sg:postcode":"8600",
    "sg:province":"West-Vlaanderen",
    "wof:name":"Gb Contact",
    "wof:placetype":"venue"
},
  "geometry": {"coordinates":[2.8723509312,50.999874115],"type":"Point"}
}