{
  "type": "Feature",
  "properties": {
    "addr:full":"Place De St.-symphorien 2 Mons Hainaut 7030",
    "addr:housenumber":"2",
    "addr:postcode":"7030",
    "addr:street":"Place De St.-Symphorien;Hainaut",
    "iso:country":"BE",
    "sg:address":"Place De St.-symphorien 2",
    "sg:city":"Mons",
    "sg:orig_category":"Slagers",
    "sg:phone":"+32 65 34 92 32",
    "sg:postcode":"7030",
    "sg:province":"Hainaut",
    "wof:name":"Discount Boucherie",
    "wof:placetype":"venue"
},
  "geometry": {"coordinates":[4.0108299255,50.4393882751],"type":"Point"}
}