{
  "type": "Feature",
  "properties": {
    "addr:full":"Beselarestraat 171 Wervik West-Vlaanderen 8940",
    "addr:housenumber":"171",
    "addr:postcode":"8940",
    "addr:street":"Beselarestraat",
    "iso:country":"BE",
    "sg:address":"Beselarestraat 171",
    "sg:city":"Wervik",
    "sg:orig_category":"Paardenfokkers",
    "sg:phone":"+32 56 51 11 83",
    "sg:postcode":"8940",
    "sg:province":"West-Vlaanderen",
    "wof:name":"Combes J",
    "wof:placetype":"venue"
},
  "geometry": {"coordinates":[3.0459721088,50.791343689],"type":"Point"}
}