{
  "type": "Feature",
  "properties": {
    "addr:full":"Kuringersteenweg 170 Hasselt Limburg 3500",
    "addr:housenumber":"170",
    "addr:postcode":"3500",
    "addr:street":"Kuringersteenweg",
    "iso:country":"BE",
    "sg:address":"Kuringersteenweg 170",
    "sg:city":"Hasselt",
    "sg:orig_category":"Peinture. Rev\u00eatements pour sols and murs",
    "sg:phone":"+32 11 25 40 94",
    "sg:postcode":"3500",
    "sg:province":"Limburg",
    "wof:name":"Guido Sevenants",
    "wof:placetype":"venue"
},
  "geometry": {"coordinates":[5.3184299469,50.9357681274],"type":"Point"}
}