{
  "type": "Feature",
  "properties": {
    "iso:country":"BE",
    "sg:address":"Dorpsstraat 39",
    "sg:city":"Bocholt",
    "sg:orig_category":"Alternatieve geneeskunde",
    "sg:phone":"+32 89 46 70 70",
    "sg:postcode":"3950",
    "sg:province":"Limburg",
    "wof:name":"Bodystyling",
    "wof:placetype":"venue"
},
  "geometry": {"coordinates":[5.5794539452,51.172542572],"type":"Point"}
}