{
  "type": "Feature",
  "properties": {
    "iso:country":"BE",
    "sg:address":"Clos Saint-roch 2",
    "sg:city":"Oupeye",
    "sg:orig_category":"Marktonderzoekbureaus",
    "sg:phone":"+32 4 264 65 82",
    "sg:postcode":"4683",
    "sg:province":"Li\u00e8ge",
    "wof:name":"Bureau Lambda Plan",
    "wof:placetype":"venue"
},
  "geometry": {"coordinates":[5.6373782158,50.7031669617],"type":"Point"}
}