{
  "type": "Feature",
  "properties": {
    "addr:full":"Molsesteenweg 83 Balen Antwerpen 2490",
    "addr:housenumber":"83",
    "addr:postcode":"2490",
    "addr:street":"Molsesteenweg",
    "iso:country":"BE",
    "sg:address":"Molsesteenweg 83",
    "sg:city":"Balen",
    "sg:classifiers":[
        {
            "category":"Retail",
            "subcategory":"Auto Repair",
            "type":"Services"
        }
    ],
    "sg:phone":"+32 14 82 06 77",
    "sg:postcode":"2490",
    "sg:province":"Antwerpen",
    "sg:tags":[
        "automobile",
        "servic",
        "electrical",
        "-"
    ],
    "wof:name":"Stc Europe Bvba",
    "wof:placetype":"venue"
},
  "geometry": {"coordinates":[5.1429018974,51.1736068726],"type":"Point"}
}