{
  "type": "Feature",
  "properties": {
    "iso:country":"BE",
    "sg:address":"Oostmalsesteenweg 81",
    "sg:city":"Rijkevorsel",
    "sg:orig_category":"Woningbouw",
    "sg:phone":"+32 3 314 78 77",
    "sg:postcode":"2310",
    "sg:province":"Antwerpen",
    "wof:name":"Bogaerts A. & Zn",
    "wof:placetype":"venue"
},
  "geometry": {"coordinates":[4.7573680878,51.3441390991],"type":"Point"}
}