{
  "type": "Feature",
  "properties": {
    "addr:full":"Stalenstraat 175 Genk (waterschei) Limburg 3600",
    "addr:housenumber":"175",
    "addr:postcode":"3600",
    "addr:street":"Stalenstraat",
    "iso:country":"BE",
    "sg:address":"Stalenstraat 175",
    "sg:city":"Genk (waterschei)",
    "sg:classifiers":[
        {
            "category":"Shopping",
            "subcategory":"Clothing, Apparel, & Fashions",
            "type":"Retail Goods"
        }
    ],
    "sg:phone":"+32 89 38 13 40",
    "sg:postcode":"3600",
    "sg:province":"Limburg",
    "sg:tags":[
        "boutique"
    ],
    "wof:name":"Binky Shop",
    "wof:placetype":"venue"
},
  "geometry": {"coordinates":[5.5170221329,50.9925346375],"type":"Point"}
}