{
  "type": "Feature",
  "properties": {
    "iso:country":"BE",
    "sg:address":"Grote Bollostraat 1",
    "sg:city":"Tremelo",
    "sg:classifiers":[
        {
            "category":"Autos & Motor Vehicles",
            "subcategory":"Fuel & Gas Station",
            "type":"Retail Goods"
        }
    ],
    "sg:phone":"+32 16 53 00 17",
    "sg:postcode":"3120",
    "sg:province":"Vlaams-Brabant",
    "sg:tags":[
        "stations-service",
        "carburants"
    ],
    "wof:name":"Esso",
    "wof:placetype":"venue"
},
  "geometry": {"coordinates":[4.7073497772,50.9934883118],"type":"Point"}
}