{
  "type": "Feature",
  "properties": {
    "iso:country":"BE",
    "sg:address":"Mechelbaan 73",
    "sg:city":"Putte",
    "sg:orig_category":"Afval and schroot Gh",
    "sg:phone":"+32 15 25 10 87",
    "sg:postcode":"2580",
    "sg:province":"Antwerpen",
    "wof:name":"Victor Maeremans",
    "wof:placetype":"venue"
},
  "geometry": {"coordinates":[4.6525201797,51.0606994629],"type":"Point"}
}