{
  "type": "Feature",
  "properties": {
    "addr:full":"Brouwerijstraat 72 Aalter Oost-Vlaanderen 9880",
    "addr:housenumber":"72",
    "addr:postcode":"9880",
    "addr:street":"Brouwerijstraat",
    "iso:country":"BE",
    "sg:address":"Brouwerijstraat 72",
    "sg:city":"Aalter",
    "sg:classifiers":[
        {
            "category":"Personal",
            "subcategory":"Beauty Salon",
            "type":"Services"
        }
    ],
    "sg:phone":"+32 9 374 37 95",
    "sg:postcode":"9880",
    "sg:province":"Oost-Vlaanderen",
    "sg:tags":[
        "lady",
        "-",
        "hairdressing"
    ],
    "wof:name":"Dorine",
    "wof:placetype":"venue"
},
  "geometry": {"coordinates":[3.4386270046,51.0844154358],"type":"Point"}
}