{
  "type": "Feature",
  "properties": {
    "addr:full":"Markt 9 Geraardsbergen Oost-Vlaanderen 9500",
    "addr:housenumber":"9",
    "addr:postcode":"9500",
    "addr:street":"Markt",
    "iso:country":"BE",
    "sg:address":"Markt 9",
    "sg:city":"Geraardsbergen",
    "sg:classifiers":[
        {
            "category":"Arena",
            "subcategory":"Sports Club",
            "type":"Entertainment"
        }
    ],
    "sg:phone":"+32 54 41 82 80",
    "sg:postcode":"9500",
    "sg:province":"Oost-Vlaanderen",
    "sg:tags":[
        "de"
    ],
    "wof:name":"B.c. De Eendracht",
    "wof:placetype":"venue"
},
  "geometry": {"coordinates":[3.8827860355,50.7718811035],"type":"Point"}
}