{
  "type": "Feature",
  "properties": {
    "addr:full":"Rue Des M\u00e9l\u00e8zes 103 Bruxelles (ixelles) Bruxelles-Capitale 1050",
    "addr:housenumber":"103",
    "addr:postcode":"1050",
    "addr:street":"Rue Des Me\u0301Le\u0300Zes",
    "iso:country":"BE",
    "sg:address":"Rue Des M\u00e9l\u00e8zes 103",
    "sg:city":"Bruxelles (ixelles)",
    "sg:classifiers":[
        {
            "category":"Personal",
            "subcategory":"Barber",
            "type":"Services"
        }
    ],
    "sg:phone":"+32 2 347 24 98",
    "sg:postcode":"1050",
    "sg:province":"Bruxelles-Capitale",
    "sg:tags":[
        "gentleman",
        "salon",
        "-",
        "hairdressing"
    ],
    "wof:name":"Playman",
    "wof:placetype":"venue"
},
  "geometry": {"coordinates":[4.3615207672,50.819442749],"type":"Point"}
}