{
  "type": "Feature",
  "properties": {
    "addr:full":"Rassel 14 Wemmel Vlaams-Brabant 1780",
    "addr:housenumber":"14",
    "addr:postcode":"1780",
    "addr:street":"Rassel;Vlaams-Brabant",
    "iso:country":"BE",
    "sg:address":"Rassel 14",
    "sg:city":"Wemmel",
    "sg:orig_category":"Non-Classified Establishments",
    "sg:phone":"+32 2 461 01 28",
    "sg:postcode":"1780",
    "sg:province":"Vlaams-Brabant",
    "wof:name":"Van Hauteghem & Co",
    "wof:placetype":"venue"
},
  "geometry": {"coordinates":[4.3001651764,50.9100379944],"type":"Point"}
}