{
  "type": "Feature",
  "properties": {
    "iso:country":"BE",
    "sg:address":"Jacques Francksquare 2b4",
    "sg:city":"Sint-gillis/saint-gilles",
    "sg:orig_category":"Artiesten and kunstenaars",
    "sg:phone":"+32 2 538 72 69",
    "sg:postcode":"1060",
    "sg:province":"Bruxelles-Capitale",
    "wof:name":"S\u00c9bastien Radovitch",
    "wof:placetype":"venue"
},
  "geometry": {"coordinates":[4.342810154,50.8326644897],"type":"Point"}
}