{
  "type": "Feature",
  "properties": {
    "iso:country":"BE",
    "sg:address":"Lindestraat 8",
    "sg:city":"Riemst",
    "sg:orig_category":"Eleveurs and marchands de porcs",
    "sg:phone":"+32 12 45 19 22",
    "sg:postcode":"3770",
    "sg:province":"Limburg",
    "wof:name":"Jean Tans",
    "wof:placetype":"venue"
},
  "geometry": {"coordinates":[5.5969901085,50.8109016418],"type":"Point"}
}