{
  "type": "Feature",
  "properties": {
    "addr:full":"Bruggestraat 146 Hooglede West-Vlaanderen 8830",
    "addr:housenumber":"146",
    "addr:postcode":"8830",
    "addr:street":"Bruggestraat",
    "iso:country":"BE",
    "sg:address":"Bruggestraat 146",
    "sg:city":"Hooglede",
    "sg:orig_category":"Banken and kredietinstellingen",
    "sg:phone":"+32 51 22 77 26",
    "sg:postcode":"8830",
    "sg:province":"West-Vlaanderen",
    "wof:name":"Bankunie",
    "wof:placetype":"venue"
},
  "geometry": {"coordinates":[3.1114339828,50.9892883301],"type":"Point"}
}