{
  "type": "Feature",
  "properties": {
    "iso:country":"BE",
    "sg:address":"Dorp 70",
    "sg:city":"Bonheiden",
    "sg:classifiers":[
        {
            "category":"Real Estate",
            "subcategory":"Surveying",
            "type":"Services"
        }
    ],
    "sg:phone":"+32 15 51 25 20",
    "sg:postcode":"2820",
    "sg:province":"Antwerpen",
    "sg:tags":[
        "lettering",
        "letter"
    ],
    "wof:name":"Aria-tex",
    "wof:placetype":"venue"
},
  "geometry": {"coordinates":[4.5451998711,51.0233421326],"type":"Point"}
}