{
  "type": "Feature",
  "properties": {
    "addr:full":"Lavaux 5 Esneux Li\u00e8ge 4130",
    "addr:housenumber":"5",
    "addr:postcode":"4130",
    "addr:street":"Lavaux",
    "iso:country":"BE",
    "sg:address":"Lavaux 5",
    "sg:city":"Esneux",
    "sg:classifiers":[
        {
            "category":"Cafe",
            "type":"Food & Drink"
        }
    ],
    "sg:phone":"+32 4 380 24 77",
    "sg:postcode":"4130",
    "sg:province":"Li\u00e8ge",
    "sg:tags":[
        "caf\u00e9s"
    ],
    "wof:name":"Caf\u00c9taria Centre Sportif",
    "wof:placetype":"venue"
},
  "geometry": {"coordinates":[5.5647110939,50.5337982178],"type":"Point"}
}