{
  "type": "Feature",
  "properties": {
    "iso:country":"BE",
    "sg:address":"Vrijwilligerslaan 130",
    "sg:city":"Etterbeek/etterbeek",
    "sg:orig_category":"Immobili\u00ebnkantoren",
    "sg:phone":"+32 2 736 06 60",
    "sg:postcode":"1040",
    "sg:province":"Bruxelles-Capitale",
    "wof:name":"Zenith Immo",
    "wof:placetype":"venue"
},
  "geometry": {"coordinates":[4.4073200226,50.8284912109],"type":"Point"}
}