{
  "type": "Feature",
  "properties": {
    "addr:full":"Stoomtuigstraat 5 Hooglede West-Vlaanderen 8830",
    "addr:housenumber":"5",
    "addr:postcode":"8830",
    "addr:street":"Stoomtuigstraat",
    "iso:country":"BE",
    "sg:address":"Stoomtuigstraat 5",
    "sg:city":"Hooglede",
    "sg:orig_category":"Dranken",
    "sg:phone":"+32 51 20 23 55",
    "sg:postcode":"8830",
    "sg:province":"West-Vlaanderen",
    "wof:name":"Depla Drankcentrale",
    "wof:placetype":"venue"
},
  "geometry": {"coordinates":[3.1200900078,50.9836463928],"type":"Point"}
}