{
  "type": "Feature",
  "properties": {
    "addr:full":"Fraikinstraat 65 Herentals Antwerpen 2200",
    "addr:housenumber":"65",
    "addr:postcode":"2200",
    "addr:street":"Fraikinstraat",
    "iso:country":"BE",
    "sg:address":"Fraikinstraat 65",
    "sg:city":"Herentals",
    "sg:orig_category":"Textiel Verlichting and huishoudartikelen",
    "sg:phone":"+32 14 21 25 58",
    "sg:postcode":"2200",
    "sg:province":"Antwerpen",
    "wof:name":"L. Mols",
    "wof:placetype":"venue"
},
  "geometry": {"coordinates":[4.8349308968,51.1816673279],"type":"Point"}
}