{
  "type": "Feature",
  "properties": {
    "iso:country":"BE",
    "sg:address":"Bommelsrede 30",
    "sg:city":"Destelbergen (heusden)",
    "sg:classifiers":[
        {
            "category":"Professional",
            "subcategory":"Computer Services",
            "type":"Services"
        }
    ],
    "sg:phone":"+32 9 369 96 20",
    "sg:postcode":"9070",
    "sg:province":"Oost-Vlaanderen",
    "sg:tags":[
        "-",
        "processing",
        "data"
    ],
    "wof:name":"Tele 20 Electronics",
    "wof:placetype":"venue"
},
  "geometry": {"coordinates":[3.8247880936,51.0017280579],"type":"Point"}
}