{
  "type": "Feature",
  "properties": {
    "addr:full":"Stationsstraat 71 Halen Limburg 3545",
    "addr:housenumber":"71",
    "addr:postcode":"3545",
    "addr:street":"Stationsstraat",
    "iso:country":"BE",
    "sg:address":"Stationsstraat 71",
    "sg:city":"Halen",
    "sg:orig_category":"RESTAURANTS: RESTAURANTS LIVRAISON \u00c0 DOMICILE",
    "sg:phone":"+32 13 46 13 36",
    "sg:postcode":"3545",
    "sg:province":"Limburg",
    "wof:name":"\u00b4t Pistoleeke",
    "wof:placetype":"venue"
},
  "geometry": {"coordinates":[5.1188621521,50.9768409729],"type":"Point"}
}