{
  "type": "Feature",
  "properties": {
    "addr:full":"Molenvest 35 Herentals Antwerpen 2200",
    "addr:housenumber":"35",
    "addr:postcode":"2200",
    "addr:street":"Molenvest",
    "iso:country":"BE",
    "sg:address":"Molenvest 35",
    "sg:city":"Herentals",
    "sg:classifiers":[
        {
            "category":"Real Estate",
            "subcategory":"Architect",
            "type":"Services"
        }
    ],
    "sg:phone":"+32 14 21 41 74",
    "sg:postcode":"2200",
    "sg:province":"Antwerpen",
    "wof:name":"Van Loven E",
    "wof:placetype":"venue"
},
  "geometry": {"coordinates":[4.832493782,51.1754112244],"type":"Point"}
}