{
  "type": "Feature",
  "properties": {
    "iso:country":"BE",
    "sg:address":"Meeuwerbaan 33",
    "sg:city":"Peer",
    "sg:orig_category":"Herstellingen and onderhoud van auto's Onderdelen and accessoires voor auto's",
    "sg:phone":"+32 11 79 36 75",
    "sg:postcode":"3990",
    "sg:province":"Limburg",
    "wof:name":"Auto-motobanden Stef",
    "wof:placetype":"venue"
},
  "geometry": {"coordinates":[5.4510288239,51.0799865723],"type":"Point"}
}