{
  "type": "Feature",
  "properties": {
    "iso:country":"BE",
    "sg:address":"Auwegemvaart 156",
    "sg:city":"Mechelen",
    "sg:orig_category":"Artiesten and kunstenaars",
    "sg:phone":"+32 15 21 88 62",
    "sg:postcode":"2800",
    "sg:province":"Antwerpen",
    "wof:name":"Frans Van Den Brande",
    "wof:placetype":"venue"
},
  "geometry": {"coordinates":[4.4653568268,51.0266265869],"type":"Point"}
}