{
  "type": "Feature",
  "properties": {
    "iso:country":"BE",
    "sg:address":"Scheepstraat 12",
    "sg:city":"Maasmechelen (opgrimbie)",
    "sg:orig_category":"Non-Classified Establishments",
    "sg:phone":"+32 89 76 62 66",
    "sg:postcode":"3630",
    "sg:province":"Limburg",
    "wof:name":"World Cones Nv",
    "wof:placetype":"venue"
},
  "geometry": {"coordinates":[5.6972408295,50.9504623413],"type":"Point"}
}