{
  "type": "Feature",
  "properties": {
    "addr:full":"Moonensstraat 30 Sint-lambrechts-woluwe/woluwe-saint-lambert Bruxelles-Capitale 1200",
    "addr:housenumber":"30",
    "addr:postcode":"1200",
    "addr:street":"Moonensstraat",
    "iso:country":"BE",
    "sg:address":"Moonensstraat 30",
    "sg:city":"Sint-lambrechts-woluwe/woluwe-saint-lambert",
    "sg:orig_category":"Secretariaatsdiensten",
    "sg:phone":"+32 2 771 21 51",
    "sg:postcode":"1200",
    "sg:province":"Bruxelles-Capitale",
    "wof:name":"Business Solutions",
    "wof:placetype":"venue"
},
  "geometry": {"coordinates":[4.4282097816,50.8476295471],"type":"Point"}
}