{
  "type": "Feature",
  "properties": {
    "addr:full":"Struikheidestraat 12 Mechelen Antwerpen 2812",
    "addr:housenumber":"12",
    "addr:postcode":"2812",
    "addr:street":"Struikheidestraat",
    "iso:country":"BE",
    "sg:address":"Struikheidestraat 12",
    "sg:city":"Mechelen",
    "sg:orig_category":"Rundveehouders",
    "sg:phone":"+32 15 41 90 10",
    "sg:postcode":"2812",
    "sg:province":"Antwerpen",
    "wof:name":"Eduard Horckmans",
    "wof:placetype":"venue"
},
  "geometry": {"coordinates":[4.4971299171,51.0081367493],"type":"Point"}
}