{
  "type": "Feature",
  "properties": {
    "iso:country":"BE",
    "sg:address":"Keienveldlaan 11",
    "sg:city":"Beersel",
    "sg:orig_category":"Artsen and specialisten",
    "sg:phone":"+32 2 305 65 79",
    "sg:postcode":"1652",
    "sg:province":"Vlaams-Brabant",
    "wof:name":"A. Finn",
    "wof:placetype":"venue"
},
  "geometry": {"coordinates":[4.336783886,50.7530403137],"type":"Point"}
}