{
  "type": "Feature",
  "properties": {
    "iso:country":"BE",
    "sg:address":"Duitslandstraat 15",
    "sg:city":"Temse",
    "sg:classifiers":[
        {
            "category":"Manufacturing",
            "subcategory":"Metals",
            "type":"Manufacturing & Wholesale Goods"
        }
    ],
    "sg:phone":"+32 3 771 91 50",
    "sg:postcode":"9140",
    "sg:province":"Oost-Vlaanderen",
    "sg:tags":[
        "working"
    ],
    "wof:name":"Alu-tools Bvba",
    "wof:placetype":"venue"
},
  "geometry": {"coordinates":[4.1994462013,51.1432304382],"type":"Point"}
}