{
  "type": "Feature",
  "properties": {
    "addr:full":"Kerkhofstraat 19 Erpe-mere (mere) Oost-Vlaanderen 9420",
    "addr:housenumber":"19",
    "addr:postcode":"9420",
    "addr:street":"Kerkhofstraat;Mere Oost-Vlaanderen",
    "iso:country":"BE",
    "sg:address":"Kerkhofstraat 19",
    "sg:city":"Erpe-mere (mere)",
    "sg:classifiers":[
        {
            "category":"Professional",
            "subcategory":"Computer Services",
            "type":"Services"
        }
    ],
    "sg:phone":"+32 53 83 83 65",
    "sg:postcode":"9420",
    "sg:province":"Oost-Vlaanderen",
    "sg:tags":[
        "webdesign",
        "-",
        "internet"
    ],
    "wof:name":"Em Design",
    "wof:placetype":"venue"
},
  "geometry": {"coordinates":[3.972397089,50.9173812866],"type":"Point"}
}