{
  "type": "Feature",
  "properties": {
    "iso:country":"BE",
    "sg:address":"Zwingelaarsstraat 50",
    "sg:city":"Izegem",
    "sg:orig_category":"Produits surgel\u00e9s Gr",
    "sg:phone":"+32 51 31 93 13",
    "sg:postcode":"8870",
    "sg:province":"West-Vlaanderen",
    "wof:name":"Christophe Rigole",
    "wof:placetype":"venue"
},
  "geometry": {"coordinates":[3.2149779797,50.9099082947],"type":"Point"}
}