{
  "type": "Feature",
  "properties": {
    "addr:full":"Rue De La Montagne 7 Ittre Brabant Wallon 1460",
    "addr:housenumber":"7;1460",
    "addr:street":"Rue De La Montagne",
    "iso:country":"BE",
    "sg:address":"Rue De La Montagne 7",
    "sg:city":"Ittre",
    "sg:orig_category":"Domotics",
    "sg:phone":"+32 67 64 74 71",
    "sg:postcode":"1460",
    "sg:province":"Brabant Wallon",
    "wof:name":"Crossconnect",
    "wof:placetype":"venue"
},
  "geometry": {"coordinates":[4.2672190666,50.6514778137],"type":"Point"}
}