{
  "type": "Feature",
  "properties": {
    "iso:country":"BE",
    "sg:address":"Rue Albert I 31-33",
    "sg:city":"Farciennes",
    "sg:classifiers":[
        {
            "category":"Health Services",
            "subcategory":"Doctor",
            "type":"Services"
        }
    ],
    "sg:phone":"+32 71 38 03 78",
    "sg:postcode":"6240",
    "sg:province":"Hainaut",
    "sg:tags":[
        "medicinephysicians",
        "surgeon"
    ],
    "wof:name":"Bodart L",
    "wof:placetype":"venue"
},
  "geometry": {"coordinates":[4.5483598709,50.4265670776],"type":"Point"}
}