{
  "type": "Feature",
  "properties": {
    "iso:country":"BE",
    "sg:address":"Rue Haute 34",
    "sg:city":"Rixensart",
    "sg:orig_category":"Catering and organisatie van feesten Slagers Voedingsspeciaalzaken",
    "sg:phone":"+32 2 653 68 07",
    "sg:postcode":"1330",
    "sg:province":"Brabant Wallon",
    "wof:name":"Boucherie Pascal",
    "wof:placetype":"venue"
},
  "geometry": {"coordinates":[4.5135369301,50.70911026],"type":"Point"}
}