{
  "type": "Feature",
  "properties": {
    "iso:country":"BE",
    "sg:address":"Grand Rue 90",
    "sg:city":"Mons",
    "sg:classifiers":[
        {
            "category":"Bakery",
            "type":"Food & Drink"
        }
    ],
    "sg:phone":"+32 64 33 53 33",
    "sg:postcode":"7000",
    "sg:province":"Hainaut",
    "sg:tags":[
        "confectioner",
        "baker"
    ],
    "wof:name":"Thirion Et Fils",
    "wof:placetype":"venue"
},
  "geometry": {"coordinates":[3.9492259026,50.4501419067],"type":"Point"}
}