{
  "type": "Feature",
  "properties": {
    "addr:full":"Avenue Eug\u00c8ne Mascaux 135 Charleroi Hainaut 6001",
    "addr:housenumber":"135",
    "addr:postcode":"6001",
    "addr:street":"Avenue Euge\u0300Ne Mascaux;Hainaut",
    "iso:country":"BE",
    "sg:address":"Avenue Eug\u00c8ne Mascaux 135",
    "sg:city":"Charleroi",
    "sg:orig_category":"Opticiens",
    "sg:phone":"+32 71 36 48 45",
    "sg:postcode":"6001",
    "sg:province":"Hainaut",
    "wof:name":"Optique Ledoux",
    "wof:placetype":"venue"
},
  "geometry": {"coordinates":[4.4442358017,50.39661026],"type":"Point"}
}