{
  "type": "Feature",
  "properties": {
    "iso:country":"BE",
    "sg:address":"Rue De Hollogne 215",
    "sg:city":"Seraing",
    "sg:orig_category":"Epiceries",
    "sg:phone":"+32 4 233 88 29",
    "sg:postcode":"4101",
    "sg:province":"Li\u00e8ge",
    "wof:name":"Nathalie Pluem",
    "wof:placetype":"venue"
},
  "geometry": {"coordinates":[5.4892392159,50.6248245239],"type":"Point"}
}