{
  "type": "Feature",
  "properties": {
    "addr:full":"Rue Du Coucou 103 Charleroi Hainaut 6010",
    "addr:housenumber":"103",
    "addr:postcode":"6010",
    "addr:street":"Rue Du Coucou;Hainaut",
    "iso:country":"BE",
    "sg:address":"Rue Du Coucou 103",
    "sg:city":"Charleroi",
    "sg:classifiers":[
        {
            "category":"Cinema",
            "subcategory":"Movie Rental",
            "type":"Entertainment"
        }
    ],
    "sg:phone":"+32 71 43 72 20",
    "sg:postcode":"6010",
    "sg:province":"Hainaut",
    "sg:tags":[
        "de",
        "cassette",
        "location",
        "vid\u00e9o",
        "audio"
    ],
    "wof:name":"Gilberte Schoreels",
    "wof:placetype":"venue"
},
  "geometry": {"coordinates":[4.4633817673,50.3896102905],"type":"Point"}
}