{
  "type": "Feature",
  "properties": {
    "iso:country":"BE",
    "sg:address":"Kriekenputstraat 100",
    "sg:city":"Ukkel/uccle",
    "sg:orig_category":"Postorderbedrijven",
    "sg:phone":"+32 2 374 77 04",
    "sg:postcode":"1180",
    "sg:province":"Bruxelles-Capitale",
    "wof:name":"Didier Chevreuille",
    "wof:placetype":"venue"
},
  "geometry": {"coordinates":[4.3464560509,50.77891922],"type":"Point"}
}