{
  "type": "Feature",
  "properties": {
    "iso:country":"BE",
    "sg:address":"Avenue Du Pesage 31-33",
    "sg:city":"Elsene/ixelles",
    "sg:orig_category":"Computers and computerapparatuur Databeheer and gegevensverwerking Onderhoud van kantoor- and comput",
    "sg:phone":"+32 2 646 00 76",
    "sg:postcode":"1050",
    "sg:province":"Bruxelles-Capitale",
    "wof:name":"Adoc Services",
    "wof:placetype":"venue"
},
  "geometry": {"coordinates":[4.3867459297,50.8088989258],"type":"Point"}
}