{
  "type": "Feature",
  "properties": {
    "addr:full":"Neerstraat 56 Haacht (wespelaar) Vlaams-Brabant 3150",
    "addr:housenumber":"56",
    "addr:postcode":"3150",
    "addr:street":"Neerstraat",
    "iso:country":"BE",
    "sg:address":"Neerstraat 56",
    "sg:city":"Haacht (wespelaar)",
    "sg:classifiers":[
        {
            "category":"Food & Beverages",
            "subcategory":"Chocolate",
            "type":"Retail Goods"
        }
    ],
    "sg:phone":"+32 496 81 09 65",
    "sg:postcode":"3150",
    "sg:province":"Vlaams-Brabant",
    "sg:tags":[
        "confectionery",
        "-"
    ],
    "wof:name":"Bereke Natens B",
    "wof:placetype":"venue"
},
  "geometry": {"coordinates":[4.6271810532,50.9618339539],"type":"Point"}
}