{
  "type": "Feature",
  "properties": {
    "addr:full":"Av. Joseph Jean Gossiaux 10 Oudergem/auderghem Bruxelles-Capitale 1160",
    "addr:housenumber":"10",
    "addr:postcode":"1160",
    "addr:street":"Av. Joseph Jean Gossiaux;/",
    "iso:country":"BE",
    "sg:address":"Av. Joseph Jean Gossiaux 10",
    "sg:city":"Oudergem/auderghem",
    "sg:orig_category":"Agences de publicit\u00e9",
    "sg:phone":"+32 2 672 23 59",
    "sg:postcode":"1160",
    "sg:province":"Bruxelles-Capitale",
    "wof:name":"Bureau Paradigmes",
    "wof:placetype":"venue"
},
  "geometry": {"coordinates":[4.4087309837,50.8168258667],"type":"Point"}
}