{
  "type": "Feature",
  "properties": {
    "addr:full":"Hameau De La Taillette 4a Frasnes-lez-anvaing (frasnes - Lez - Buissenal) Hainaut 7911",
    "addr:housenumber":"4a",
    "addr:postcode":"7911",
    "addr:street":"Hameau De La Taillette",
    "iso:country":"BE",
    "sg:address":"Hameau De La Taillette 4a",
    "sg:city":"Frasnes-lez-anvaing (frasnes - Lez - Buissenal)",
    "sg:classifiers":[
        {
            "category":"Professional",
            "subcategory":"Management & Consulting",
            "type":"Services"
        }
    ],
    "sg:phone":"+32 69 87 50 38",
    "sg:postcode":"7911",
    "sg:province":"Hainaut",
    "sg:tags":[
        "consultant"
    ],
    "wof:name":"Bemof",
    "wof:placetype":"venue"
},
  "geometry": {"coordinates":[3.5966889858,50.6893424988],"type":"Point"}
}