{
  "type": "Feature",
  "properties": {
    "iso:country":"BE",
    "sg:address":"Wisembach 64bc",
    "sg:city":"Fauvillers",
    "sg:orig_category":"Installation \u00e9lectrique r\u00e9sidentielle. Collecte and \u00e9puration des eaux us\u00e9es. Services de Nettoyage ",
    "sg:phone":"+32 63 60 04 68",
    "sg:postcode":"6637",
    "sg:province":"Luxembourg",
    "wof:name":"A. Rigaux",
    "wof:placetype":"venue"
},
  "geometry": {"coordinates":[5.7063698769,49.8442687988],"type":"Point"}
}