{
  "type": "Feature",
  "properties": {
    "iso:country":"BE",
    "sg:address":"Rue Du Pironbolle 8",
    "sg:city":"Ans (loncin)",
    "sg:classifiers":[
        {
            "category":"Communications",
            "subcategory":"Film & Video Production",
            "type":"Services"
        }
    ],
    "sg:phone":"+32 4 263 86 40",
    "sg:postcode":"4431",
    "sg:province":"Li\u00e8ge",
    "sg:tags":[
        "material",
        "audio-visual"
    ],
    "wof:name":"Lumen",
    "wof:placetype":"venue"
},
  "geometry": {"coordinates":[5.4898571968,50.6627044678],"type":"Point"}
}