{
  "type": "Feature",
  "properties": {
    "addr:full":"Doorniksewijk 128 Kortrijk West-Vlaanderen 8500",
    "addr:housenumber":"128",
    "addr:postcode":"8500",
    "iso:country":"BE",
    "sg:address":"Doorniksewijk 128",
    "sg:city":"Kortrijk",
    "sg:orig_category":"Apotheken",
    "sg:phone":"+32 56 22 47 35",
    "sg:postcode":"8500",
    "sg:province":"West-Vlaanderen",
    "wof:name":"Olivia Van Marcke",
    "wof:placetype":"venue"
},
  "geometry": {"coordinates":[3.2692050934,50.8195915222],"type":"Point"}
}