{
  "type": "Feature",
  "properties": {
    "iso:country":"BE",
    "sg:address":"Ambiorixsquare 7",
    "sg:city":"Brussel/bruxelles",
    "sg:orig_category":"Film-, tv- and videoproductie",
    "sg:phone":"+32 2 735 55 53",
    "sg:postcode":"1000",
    "sg:province":"Bruxelles-Capitale",
    "wof:name":"Spa Mediaset",
    "wof:placetype":"venue"
},
  "geometry": {"coordinates":[4.3833851814,50.8477096558],"type":"Point"}
}