{
  "type": "Feature",
  "properties": {
    "addr:full":"Ontvangersstraat 14 Brugge West-Vlaanderen 8000",
    "addr:housenumber":"14",
    "addr:postcode":"8000",
    "addr:street":"Ontvangersstraat",
    "iso:country":"BE",
    "sg:address":"Ontvangersstraat 14",
    "sg:city":"Brugge",
    "sg:classifiers":[
        {
            "category":"Structure",
            "subcategory":"Office Building",
            "type":"Public Place"
        }
    ],
    "sg:phone":"+32 50 34 18 65",
    "sg:postcode":"8000",
    "sg:province":"West-Vlaanderen",
    "sg:tags":[
        "drawing"
    ],
    "wof:name":"Knockaert B",
    "wof:placetype":"venue"
},
  "geometry": {"coordinates":[3.2195730209,51.2084693909],"type":"Point"}
}