{
  "type": "Feature",
  "properties": {
    "iso:country":"BE",
    "sg:address":"Galerie St-hubert 1348",
    "sg:city":"Ottignies-louvain-la-neuve (louvain-la-neuve)",
    "sg:classifiers":[
        {
            "category":"Manufacturing",
            "subcategory":"Textiles",
            "type":"Manufacturing & Wholesale Goods"
        }
    ],
    "sg:phone":"+32 10 45 56 27",
    "sg:postcode":"1348",
    "sg:province":"Brabant Wallon",
    "sg:tags":[
        "retail",
        "-"
    ],
    "wof:name":"Boutique Jean's Deux Mille",
    "wof:placetype":"venue"
},
  "geometry": {"coordinates":[4.567553997,50.6661262512],"type":"Point"}
}