{
  "type": "Feature",
  "properties": {
    "iso:country":"BE",
    "sg:address":"Weynisbaan 185",
    "sg:city":"Putte",
    "sg:orig_category":"Pain, p\u00e2tisseries and confiseries",
    "sg:phone":"+32 15 75 51 01",
    "sg:postcode":"2580",
    "sg:province":"Antwerpen",
    "wof:name":"Bakkerij Vloeberghs",
    "wof:placetype":"venue"
},
  "geometry": {"coordinates":[4.5916337967,51.0350532532],"type":"Point"}
}