{
  "type": "Feature",
  "properties": {
    "iso:country":"BE",
    "sg:address":"Rue De La Franco-belge 28",
    "sg:city":"La Louviere",
    "sg:orig_category":"Bloemen and planten",
    "sg:phone":"+32 64 28 27 92",
    "sg:postcode":"7100",
    "sg:province":"Hainaut",
    "wof:name":"Chanelle",
    "wof:placetype":"venue"
},
  "geometry": {"coordinates":[4.206633091,50.4872627258],"type":"Point"}
}