{
  "type": "Feature",
  "properties": {
    "addr:full":"Rue Marianne 2 Ukkel/uccle Bruxelles-Capitale 1180",
    "addr:housenumber":"2",
    "addr:postcode":"1180",
    "addr:street":"Rue Marianne;/",
    "iso:country":"BE",
    "sg:address":"Rue Marianne 2",
    "sg:city":"Ukkel/uccle",
    "sg:orig_category":"M\u00e9decins and sp\u00e9cialistes",
    "sg:phone":"+32 2 344 42 67",
    "sg:postcode":"1180",
    "sg:province":"Bruxelles-Capitale",
    "wof:name":"Claude Quersin",
    "wof:placetype":"venue"
},
  "geometry": {"coordinates":[4.3518028259,50.8139419556],"type":"Point"}
}