{
  "type": "Feature",
  "properties": {
    "iso:country":"BE",
    "sg:address":"Stationsstraat 41b2",
    "sg:city":"Neerpelt",
    "sg:orig_category":"M\u00e9decins and sp\u00e9cialistes",
    "sg:phone":"+32 11 66 18 44",
    "sg:postcode":"3910",
    "sg:province":"Limburg",
    "wof:name":"C. Van De Venne",
    "wof:placetype":"venue"
},
  "geometry": {"coordinates":[5.4368782043,51.2255935669],"type":"Point"}
}