{
  "type": "Feature",
  "properties": {
    "iso:country":"BE",
    "sg:address":"Overbroekstraat 25bd",
    "sg:city":"Brecht",
    "sg:orig_category":"Rundveehouders",
    "sg:phone":"+32 3 663 15 99",
    "sg:postcode":"2960",
    "sg:province":"Antwerpen",
    "wof:name":"Monique Havermans",
    "wof:placetype":"venue"
},
  "geometry": {"coordinates":[4.5924391747,51.3462638855],"type":"Point"}
}