{
  "type": "Feature",
  "properties": {
    "addr:full":"Volkstraat 40 Antwerpen Antwerpen 2000",
    "addr:housenumber":"40",
    "addr:postcode":"2000",
    "addr:street":"Volkstraat",
    "iso:country":"BE",
    "sg:address":"Volkstraat 40",
    "sg:city":"Antwerpen",
    "sg:classifiers":[
        {
            "category":"Education",
            "subcategory":"School",
            "type":"Public Place"
        }
    ],
    "sg:phone":"+32 3 248 40 34",
    "sg:postcode":"2000",
    "sg:province":"Antwerpen",
    "sg:tags":[
        "secondary"
    ],
    "wof:name":"Steiner-hibernia School Vzw",
    "wof:placetype":"venue"
},
  "geometry": {"coordinates":[4.3955421448,51.2109222412],"type":"Point"}
}