{
  "type": "Feature",
  "properties": {
    "addr:full":"Rue Nestor-bouillon 8 Somme-leuze Namur 5377",
    "addr:housenumber":"8",
    "addr:postcode":"5377",
    "addr:street":"Rue Nestor-Bouillon",
    "iso:country":"BE",
    "sg:address":"Rue Nestor-bouillon 8",
    "sg:city":"Somme-leuze",
    "sg:orig_category":"Alimentation sp\u00e9cialis\u00e9e",
    "sg:phone":"+32 83 68 81 34",
    "sg:postcode":"5377",
    "sg:province":"Namur",
    "wof:name":"Andre Demeuse",
    "wof:placetype":"venue"
},
  "geometry": {"coordinates":[5.2502570152,50.2713317871],"type":"Point"}
}