{
  "type": "Feature",
  "properties": {
    "iso:country":"BE",
    "sg:address":"Rue Soeur Lutgardis 4",
    "sg:city":"Li\u00e8ge 1 (ch\u00ean\u00e9e)",
    "sg:classifiers":[
        {
            "category":"Education",
            "subcategory":"Dance Studio",
            "type":"Public Place"
        }
    ],
    "sg:phone":"+32 4 344 06 69",
    "sg:postcode":"4032",
    "sg:province":"Li\u00e8ge",
    "sg:tags":[
        "school",
        "dancing"
    ],
    "wof:name":"Ecole De Danse Marcelle Joliet",
    "wof:placetype":"venue"
},
  "geometry": {"coordinates":[5.618844986,50.6128005981],"type":"Point"}
}