{
  "type": "Feature",
  "properties": {
    "addr:full":"Paradis 17c Aywaille (harz\u00e9) Li\u00e8ge 4920",
    "addr:housenumber":"17c",
    "addr:postcode":"4920",
    "addr:street":"Paradis",
    "iso:country":"BE",
    "sg:address":"Paradis 17c",
    "sg:city":"Aywaille (harz\u00e9)",
    "sg:classifiers":[
        {
            "category":"Building & Trades",
            "subcategory":"Electrical",
            "type":"Services"
        }
    ],
    "sg:phone":"+32 86 43 47 47",
    "sg:postcode":"4920",
    "sg:province":"Li\u00e8ge",
    "sg:tags":[
        "electric",
        "-",
        "housewiring",
        "contractor"
    ],
    "wof:name":"Herman D",
    "wof:placetype":"venue"
},
  "geometry": {"coordinates":[5.6782069206,50.4738540649],"type":"Point"}
}