{
  "type": "Feature",
  "properties": {
    "addr:full":"Rue De L'expansion 3 Gr\u00e2ce-hollogne Li\u00e8ge 4460",
    "addr:housenumber":"3",
    "addr:postcode":"4460",
    "addr:street":"Rue De L'Expansion",
    "iso:country":"BE",
    "sg:address":"Rue De L'expansion 3",
    "sg:city":"Gr\u00e2ce-hollogne",
    "sg:classifiers":[
        {
            "category":"Home & Garden",
            "subcategory":"Furniture",
            "type":"Retail Goods"
        }
    ],
    "sg:phone":"+32 4 263 77 25",
    "sg:postcode":"4460",
    "sg:province":"Li\u00e8ge",
    "sg:tags":[
        "bathroom"
    ],
    "wof:name":"Ridmo S.a.",
    "wof:placetype":"venue"
},
  "geometry": {"coordinates":[5.4967079163,50.6530914307],"type":"Point"}
}