{
  "type": "Feature",
  "properties": {
    "iso:country":"BE",
    "sg:address":"Rue Charles Gantois 20",
    "sg:city":"Estinnes",
    "sg:orig_category":"Plomberie, chauffage and installations sanitaires",
    "sg:phone":"+32 64 77 15 76",
    "sg:postcode":"7120",
    "sg:province":"Hainaut",
    "wof:name":"Robert Mailleux",
    "wof:placetype":"venue"
},
  "geometry": {"coordinates":[4.115281105,50.3698120117],"type":"Point"}
}