{
  "type": "Feature",
  "properties": {
    "addr:full":"Rue De L'epine Pucelle 51 Braine-l'alleud Brabant Wallon 1428",
    "addr:housenumber":"51",
    "addr:postcode":"1428",
    "addr:street":"Rue De L'Epine Pucelle",
    "iso:country":"BE",
    "sg:address":"Rue De L'epine Pucelle 51",
    "sg:city":"Braine-l'alleud",
    "sg:orig_category":"Groenten and fruit Gh",
    "sg:phone":"+32 2 384 95 36",
    "sg:postcode":"1428",
    "sg:province":"Brabant Wallon",
    "wof:name":"La Coop D'assonville",
    "wof:placetype":"venue"
},
  "geometry": {"coordinates":[-75.60595703120001,37.7877616882],"type":"Point"}
}