{
  "type": "Feature",
  "properties": {
    "iso:country":"BE",
    "sg:address":"Kruisstraat 4",
    "sg:city":"Kortemark",
    "sg:orig_category":"Groenten and fruit Gh",
    "sg:phone":"+32 51 56 66 90",
    "sg:postcode":"8610",
    "sg:province":"West-Vlaanderen",
    "wof:name":"Flanders Quality Patat",
    "wof:placetype":"venue"
},
  "geometry": {"coordinates":[2.9551479816,51.0070266724],"type":"Point"}
}