{
  "type": "Feature",
  "properties": {
    "iso:country":"BE",
    "sg:address":"Chauss\u00e9e De Nivelles 12",
    "sg:city":"Braine L'alleud (braine-l'alleud)",
    "sg:classifiers":[
        {
            "category":"Building & Trades",
            "subcategory":"Construction",
            "type":"Services"
        }
    ],
    "sg:phone":"+32 2 387 49 22",
    "sg:postcode":"1420",
    "sg:province":"Brabant Wallon",
    "sg:tags":[
        "carpenter"
    ],
    "wof:name":"A.r.t. & Co",
    "wof:placetype":"venue"
},
  "geometry": {"coordinates":[-0.7711730003,47.3931159973],"type":"Point"}
}