{
  "type": "Feature",
  "properties": {
    "iso:country":"BE",
    "sg:address":"Rue Gr\u00c9goire Chapuis 145",
    "sg:city":"Seraing",
    "sg:orig_category":"M\u00e9decins and sp\u00e9cialistes",
    "sg:phone":"+32 4 337 38 95",
    "sg:postcode":"4100",
    "sg:province":"Li\u00e8ge",
    "wof:name":"Leon Bacquelaine",
    "wof:placetype":"venue"
},
  "geometry": {"coordinates":[5.5048499107,50.5989112854],"type":"Point"}
}