{
  "type": "Feature",
  "properties": {
    "addr:full":"Rue Al B\u00e2che 9a Amay (ampsin) Li\u00e8ge 4540",
    "addr:housenumber":"9a",
    "addr:postcode":"4540",
    "addr:street":"Rue Al Ba\u0302Che;Ampsin",
    "iso:country":"BE",
    "sg:address":"Rue Al B\u00e2che 9a",
    "sg:city":"Amay (ampsin)",
    "sg:classifiers":[
        {
            "category":"Airport",
            "subcategory":"General Aviation",
            "type":"Transportation"
        }
    ],
    "sg:phone":"+32 477 45 07 85",
    "sg:postcode":"4540",
    "sg:province":"Li\u00e8ge",
    "sg:tags":[
        "transport"
    ],
    "wof:name":"Navette Airport",
    "wof:placetype":"venue"
},
  "geometry": {"coordinates":[5.305355072,50.551322937],"type":"Point"}
}