{
  "type": "Feature",
  "properties": {
    "addr:full":"Hasseltsesteenweg 37 Sint-truiden Limburg 3800",
    "addr:housenumber":"37",
    "addr:postcode":"3800",
    "addr:street":"Hasseltsesteenweg",
    "iso:country":"BE",
    "sg:address":"Hasseltsesteenweg 37",
    "sg:city":"Sint-truiden",
    "sg:orig_category":"Mat\u00e9riel pour plomberie and chauffage Quincailleries. Mat\u00e9riaux de construction Gr",
    "sg:phone":"+32 11 69 39 79",
    "sg:postcode":"3800",
    "sg:province":"Limburg",
    "wof:name":"Lambrechts",
    "wof:placetype":"venue"
},
  "geometry": {"coordinates":[5.198756218,50.8260917664],"type":"Point"}
}