{
  "type": "Feature",
  "properties": {
    "addr:full":"Rue Du Marais 28 Silly Hainaut 7830",
    "addr:housenumber":"28",
    "addr:postcode":"7830",
    "addr:street":"Rue Du Marais",
    "iso:country":"BE",
    "sg:address":"Rue Du Marais 28",
    "sg:city":"Silly",
    "sg:orig_category":"Installatie van houten of kunststof schrijnwerk",
    "sg:phone":"+32 68 55 11 93",
    "sg:postcode":"7830",
    "sg:province":"Hainaut",
    "wof:name":"Claude Daubechies",
    "wof:placetype":"venue"
},
  "geometry": {"coordinates":[3.926858902,50.6460342407],"type":"Point"}
}