{
  "type": "Feature",
  "properties": {
    "addr:full":"Slangstraat 70 Hamme Oost-Vlaanderen 9220",
    "addr:housenumber":"70",
    "addr:postcode":"9220",
    "addr:street":"Slangstraat",
    "iso:country":"BE",
    "sg:address":"Slangstraat 70",
    "sg:city":"Hamme",
    "sg:orig_category":"Disneyland Parijs Reisbureaus",
    "sg:phone":"+32 52 48 09 24",
    "sg:postcode":"9220",
    "sg:province":"Oost-Vlaanderen",
    "wof:name":"Reizen Landtsheer",
    "wof:placetype":"venue"
},
  "geometry": {"coordinates":[4.1362719536,51.0928153992],"type":"Point"}
}