{
  "type": "Feature",
  "properties": {
    "iso:country":"BE",
    "sg:address":"Chauss\u00c9e De Haecht 194",
    "sg:city":"Schaarbeek/schaerbeek",
    "sg:orig_category":"Epiceries",
    "sg:phone":"+32 2 216 57 42",
    "sg:postcode":"1030",
    "sg:province":"Bruxelles-Capitale",
    "wof:name":"Courtheoux",
    "wof:placetype":"venue"
},
  "geometry": {"coordinates":[4.3718628883,50.8609085083],"type":"Point"}
}