{
  "type": "Feature",
  "properties": {
    "addr:full":"Fabriekslaan 13 Ledegem West-Vlaanderen 8880",
    "addr:housenumber":"13",
    "addr:postcode":"8880",
    "addr:street":"Fabriekslaan",
    "iso:country":"BE",
    "sg:address":"Fabriekslaan 13",
    "sg:city":"Ledegem",
    "sg:classifiers":[
        {
            "category":"Freight",
            "type":"Transportation"
        }
    ],
    "sg:phone":"+32 56 50 14 84",
    "sg:postcode":"8880",
    "sg:province":"West-Vlaanderen",
    "sg:tags":[
        "-",
        "transport"
    ],
    "wof:name":"Deleu Francky Bvba",
    "wof:placetype":"venue"
},
  "geometry": {"coordinates":[3.1181709766,50.8609542847],"type":"Point"}
}