{
  "type": "Feature",
  "properties": {
    "addr:full":"Vlaamsekaai 30-31 Antwerpen Antwerpen 2000",
    "addr:postcode":"30-31;2000",
    "addr:street":"Vlaamsekaai",
    "iso:country":"BE",
    "sg:address":"Vlaamsekaai 30-31",
    "sg:city":"Antwerpen",
    "sg:classifiers":[
        {
            "category":"Professional",
            "type":"Services"
        }
    ],
    "sg:phone":"+32 3 238 42 02",
    "sg:postcode":"2000",
    "sg:province":"Antwerpen",
    "sg:tags":[
        "auction",
        "room"
    ],
    "wof:name":"Campo Vlaamse Kaai",
    "wof:placetype":"venue"
},
  "geometry": {"coordinates":[4.3917207718,51.2103233337],"type":"Point"}
}