{
  "type": "Feature",
  "properties": {
    "iso:country":"BE",
    "sg:address":"Snoekstraat 3",
    "sg:city":"Anzegem",
    "sg:orig_category":"Eleveurs de bovins. Eleveurs and marchands de porcs",
    "sg:phone":"+32 56 77 73 48",
    "sg:postcode":"8570",
    "sg:province":"West-Vlaanderen",
    "wof:name":"Martin Taelman",
    "wof:placetype":"venue"
},
  "geometry": {"coordinates":[3.4014050961,50.8258094788],"type":"Point"}
}