{
  "type": "Feature",
  "properties": {
    "iso:country":"BE",
    "sg:address":"Tieltsteenweg 45",
    "sg:city":"Oostrozebeke",
    "sg:orig_category":"Rev\u00eatements de sols and murs",
    "sg:phone":"+32 56 66 64 67",
    "sg:postcode":"8780",
    "sg:province":"West-Vlaanderen",
    "wof:name":"Deco Floor",
    "wof:placetype":"venue"
},
  "geometry": {"coordinates":[3.3334600925,50.924331665],"type":"Point"}
}