{
  "type": "Feature",
  "properties": {
    "iso:country":"BE",
    "sg:address":"Opstalplein 22",
    "sg:city":"Dendermonde",
    "sg:orig_category":"Dranken Gedistilleerde dranken and aperitieven Fab Wijnen Fab",
    "sg:phone":"+32 52 42 73 73",
    "sg:postcode":"9200",
    "sg:province":"Oost-Vlaanderen",
    "wof:name":"Caves De France",
    "wof:placetype":"venue"
},
  "geometry": {"coordinates":[4.0305609703,51.0037345886],"type":"Point"}
}