{
  "type": "Feature",
  "properties": {
    "addr:full":"Leuvensesteenweg 448 Mechelen Antwerpen 2812",
    "addr:housenumber":"448",
    "addr:postcode":"2812",
    "addr:street":"Leuvensesteenweg",
    "iso:country":"BE",
    "sg:address":"Leuvensesteenweg 448",
    "sg:city":"Mechelen",
    "sg:orig_category":"Artistes ind\u00e9pendants",
    "sg:phone":"+32 15 41 51 09",
    "sg:postcode":"2812",
    "sg:province":"Antwerpen",
    "wof:name":"Hellemans",
    "wof:placetype":"venue"
},
  "geometry": {"coordinates":[4.5150761604,51.0108947754],"type":"Point"}
}