{
  "type": "Feature",
  "properties": {
    "addr:full":"Ijzerbron 69 Tongeren Limburg 3700",
    "addr:housenumber":"69",
    "addr:postcode":"3700",
    "addr:street":"Ijzerbron",
    "iso:country":"BE",
    "sg:address":"Ijzerbron 69",
    "sg:city":"Tongeren",
    "sg:orig_category":"Architectes",
    "sg:phone":"+32 12 26 33 30",
    "sg:postcode":"3700",
    "sg:province":"Limburg",
    "wof:name":"Architectenbureau Favoreel-meyvaert",
    "wof:placetype":"venue"
},
  "geometry": {"coordinates":[5.4580931664,50.7877464294],"type":"Point"}
}