{
  "type": "Feature",
  "properties": {
    "addr:full":"Rue Armand Heptia 1 Faimes Li\u00e8ge 4317",
    "addr:housenumber":"1",
    "addr:postcode":"4317",
    "addr:street":"Rue Armand Heptia",
    "iso:country":"BE",
    "sg:address":"Rue Armand Heptia 1",
    "sg:city":"Faimes",
    "sg:orig_category":"Varkenskwekers",
    "sg:phone":"+32 19 33 21 45",
    "sg:postcode":"4317",
    "sg:province":"Li\u00e8ge",
    "wof:name":"Francis Dubois",
    "wof:placetype":"venue"
},
  "geometry": {"coordinates":[5.2594671249,50.6624183655],"type":"Point"}
}