{
  "type": "Feature",
  "properties": {
    "addr:full":"Rue Des Vaucelles 96 Ch\u00e2telet (bouffioulx) Hainaut 6200",
    "addr:housenumber":"96",
    "addr:postcode":"6200",
    "addr:street":"Rue Des Vaucelles",
    "iso:country":"BE",
    "sg:address":"Rue Des Vaucelles 96",
    "sg:city":"Ch\u00e2telet (bouffioulx)",
    "sg:classifiers":[
        {
            "category":"Building & Trades",
            "subcategory":"Locksmith",
            "type":"Services"
        }
    ],
    "sg:phone":"+32 71 39 21 65",
    "sg:postcode":"6200",
    "sg:province":"Hainaut",
    "sg:tags":[
        "lock",
        "key"
    ],
    "wof:name":"Dahin P",
    "wof:placetype":"venue"
},
  "geometry": {"coordinates":[4.5147590637,50.3861618042],"type":"Point"}
}