{
  "type": "Feature",
  "properties": {
    "iso:country":"BE",
    "sg:address":"S. Vernieuwestraat 1",
    "sg:city":"Blankenberge",
    "sg:orig_category":"Poissonniers and \u00e9caillers",
    "sg:phone":"+32 50 41 24 96",
    "sg:postcode":"8370",
    "sg:province":"West-Vlaanderen",
    "wof:name":"Huis Berthe",
    "wof:placetype":"venue"
},
  "geometry": {"coordinates":[3.1262021065,51.3139343262],"type":"Point"}
}