{
  "type": "Feature",
  "properties": {
    "addr:full":"Rue De L'yser 1 Namur (vedrin - Daussoulx) Namur 5020",
    "addr:housenumber":"1",
    "addr:postcode":"5020",
    "addr:street":"Rue De L'Yser",
    "iso:country":"BE",
    "sg:address":"Rue De L'yser 1",
    "sg:city":"Namur (vedrin - Daussoulx)",
    "sg:classifiers":[
        {
            "category":"Bars & Pubs",
            "type":"Food & Drink"
        }
    ],
    "sg:phone":"+32 81 21 22 56",
    "sg:postcode":"5020",
    "sg:province":"Namur",
    "wof:name":"Sports (des)",
    "wof:placetype":"venue"
},
  "geometry": {"coordinates":[4.8880457878,50.4913253784],"type":"Point"}
}