{
  "type": "Feature",
  "properties": {
    "addr:full":"Mechelsesteenweg 64 Kontich Antwerpen 2550",
    "addr:housenumber":"64",
    "addr:postcode":"2550",
    "addr:street":"Mechelsesteenweg",
    "iso:country":"BE",
    "sg:address":"Mechelsesteenweg 64",
    "sg:city":"Kontich",
    "sg:orig_category":"Huishoudapparaten, televisies and radio's Speelgoed Sport- and kampeermateriaal Verlichting and huis",
    "sg:phone":"+32 3 457 96 31",
    "sg:postcode":"2550",
    "sg:province":"Antwerpen",
    "wof:name":"Blokker",
    "wof:placetype":"venue"
},
  "geometry": {"coordinates":[4.4459009171,51.1328086853],"type":"Point"}
}