{
  "type": "Feature",
  "properties": {
    "iso:country":"BE",
    "sg:address":"Bruggestraat 269",
    "sg:city":"Ingelmunster",
    "sg:classifiers":[
        {
            "category":"Wholesale",
            "subcategory":"Plants",
            "type":"Manufacturing & Wholesale Goods"
        }
    ],
    "sg:phone":"+32 51 48 72 29",
    "sg:postcode":"8770",
    "sg:province":"West-Vlaanderen",
    "sg:tags":[
        "whol",
        "flower",
        "-",
        "grower"
    ],
    "wof:name":"Vanacker Bloembollen",
    "wof:placetype":"venue"
},
  "geometry": {"coordinates":[3.2495930195,50.937286377],"type":"Point"}
}