{
  "type": "Feature",
  "properties": {
    "iso:country":"BE",
    "sg:address":"Rue Neuve-voie 67",
    "sg:city":"Engis",
    "sg:classifiers":[
        {
            "category":"Utilities",
            "subcategory":"Natural Gas",
            "type":"Services"
        }
    ],
    "sg:phone":"+32 4 273 80 73",
    "sg:postcode":"4480",
    "sg:province":"Li\u00e8ge",
    "sg:tags":[
        "firework"
    ],
    "wof:name":"Tristar Sd Sprl",
    "wof:placetype":"venue"
},
  "geometry": {"coordinates":[5.3963341713,50.5808639526],"type":"Point"}
}