{
  "type": "Feature",
  "properties": {
    "iso:country":"BE",
    "sg:address":"Lenniksebaan 1075",
    "sg:city":"Sint-pieters-leeuw",
    "sg:orig_category":"Elektrische installaties voor woningen Woningbouw",
    "sg:phone":"+32 2 567 15 81",
    "sg:postcode":"1602",
    "sg:province":"Vlaams-Brabant",
    "wof:name":"Erik Bellemans",
    "wof:placetype":"venue"
},
  "geometry": {"coordinates":[4.2278928757,50.8180732727],"type":"Point"}
}