{
  "type": "Feature",
  "properties": {
    "addr:full":"Rue Des Combattants 80 Wavre Brabant Wallon 1301",
    "addr:housenumber":"80;1301",
    "addr:street":"Rue Des Combattants",
    "iso:country":"BE",
    "sg:address":"Rue Des Combattants 80",
    "sg:city":"Wavre",
    "sg:orig_category":"Installatie van houten of kunststof schrijnwerk",
    "sg:phone":"+32 2 215 93 06",
    "sg:postcode":"1301",
    "sg:province":"Brabant Wallon",
    "wof:name":"Dardenne",
    "wof:placetype":"venue"
},
  "geometry": {"coordinates":[4.5826330185,50.711566925],"type":"Point"}
}