{
  "type": "Feature",
  "properties": {
    "iso:country":"BE",
    "sg:address":"Grote Baan 18",
    "sg:city":"Hasselt",
    "sg:orig_category":"M\u00e9decines alternatives. M\u00e9decins and sp\u00e9cialistes",
    "sg:phone":"+32 11 25 08 70",
    "sg:postcode":"3511",
    "sg:province":"Limburg",
    "wof:name":"Van Daele Paul",
    "wof:placetype":"venue"
},
  "geometry": {"coordinates":[5.3050618172,50.9404411316],"type":"Point"}
}