{
  "type": "Feature",
  "properties": {
    "addr:full":"Theo Verellenlaan 47 Wuustwezel Antwerpen 2990",
    "addr:housenumber":"47",
    "addr:postcode":"2990",
    "addr:street":"Theo Verellenlaan",
    "iso:country":"BE",
    "sg:address":"Theo Verellenlaan 47",
    "sg:city":"Wuustwezel",
    "sg:classifiers":[
        {
            "category":"Shopping",
            "subcategory":"Bicycles & Sporting Goods",
            "type":"Retail Goods"
        }
    ],
    "sg:phone":"+32 3 633 27 00",
    "sg:postcode":"2990",
    "sg:province":"Antwerpen",
    "sg:tags":[
        "-"
    ],
    "wof:name":"Rombouts",
    "wof:placetype":"venue"
},
  "geometry": {"coordinates":[4.5444140434,51.3563842773],"type":"Point"}
}