{
  "type": "Feature",
  "properties": {
    "addr:full":"Rue Bonne Nouvelle 9 Li\u00e8ge 1 Li\u00e8ge 4000",
    "addr:housenumber":"9;1",
    "addr:postcode":"4000",
    "addr:street":"Rue Bonne Nouvelle",
    "iso:country":"BE",
    "sg:address":"Rue Bonne Nouvelle 9",
    "sg:city":"Li\u00e8ge 1",
    "sg:classifiers":[
        {
            "category":"Building & Trades",
            "subcategory":"Landscaping Services",
            "type":"Services"
        }
    ],
    "sg:phone":"+32 4 227 20 91",
    "sg:postcode":"4000",
    "sg:province":"Li\u00e8ge",
    "sg:tags":[
        "access",
        "pond",
        "laying-out",
        "-"
    ],
    "wof:name":"Setransmat Sa",
    "wof:placetype":"venue"
},
  "geometry": {"coordinates":[5.5963110924,50.652961731],"type":"Point"}
}