{
  "type": "Feature",
  "properties": {
    "iso:country":"BE",
    "sg:address":"Markt 37",
    "sg:city":"Kasterlee",
    "sg:classifiers":[
        {
            "category":"Banks & Credit Unions",
            "subcategory":"Bank",
            "type":"Services"
        }
    ],
    "sg:phone":"+32 14 55 65 57",
    "sg:postcode":"2460",
    "sg:province":"Antwerpen",
    "wof:name":"Gemeentekrediet",
    "wof:placetype":"venue"
},
  "geometry": {"coordinates":[4.9667100906,51.2408905029],"type":"Point"}
}