{
  "type": "Feature",
  "properties": {
    "iso:country":"BE",
    "sg:address":"Boskant 5",
    "sg:city":"Zandhoven (groot)",
    "sg:classifiers":[
        {
            "category":"Building & Trades",
            "subcategory":"Construction",
            "type":"Services"
        }
    ],
    "sg:phone":"+32 3 466 02 20",
    "sg:postcode":"2242",
    "sg:province":"Antwerpen",
    "sg:tags":[
        "ventilation",
        "conditionn\u00e9",
        "air"
    ],
    "wof:name":"De Deckere Industries",
    "wof:placetype":"venue"
},
  "geometry": {"coordinates":[4.7080731392,51.2239952087],"type":"Point"}
}