{
  "type": "Feature",
  "properties": {
    "addr:full":"Rue Ferrer 78 Charleroi Hainaut 6031",
    "addr:housenumber":"78",
    "addr:postcode":"6031",
    "addr:street":"Rue Ferrer;Hainaut",
    "iso:country":"BE",
    "sg:address":"Rue Ferrer 78",
    "sg:city":"Charleroi",
    "sg:orig_category":"Tabac. Journaux",
    "sg:phone":"+32 71 30 85 71",
    "sg:postcode":"6031",
    "sg:province":"Hainaut",
    "wof:name":"Maison A La Une",
    "wof:placetype":"venue"
},
  "geometry": {"coordinates":[4.4093441963,50.4220809937],"type":"Point"}
}