{
  "type": "Feature",
  "properties": {
    "addr:full":"Borstelstraat Leuven Vlaams-Brabant 3010",
    "addr:postcode":"3010",
    "addr:street":"Borstelstraat",
    "iso:country":"BE",
    "sg:address":"Borstelstraat",
    "sg:city":"Leuven",
    "sg:orig_category":"Alternatieve geneeskunde",
    "sg:phone":"+32 15 43 66 76",
    "sg:postcode":"3010",
    "sg:province":"Vlaams-Brabant",
    "wof:name":"Anonieme Overeters",
    "wof:placetype":"venue"
},
  "geometry": {"coordinates":[4.7304501534,50.889755249],"type":"Point"}
}