{
  "type": "Feature",
  "properties": {
    "iso:country":"BE",
    "sg:address":"Mijnschoolstraat 46",
    "sg:city":"Beringen",
    "sg:classifiers":[
        {
            "category":"Building & Trades",
            "subcategory":"Plumbing",
            "type":"Services"
        }
    ],
    "sg:phone":"+32 11 42 15 66",
    "sg:postcode":"3580",
    "sg:province":"Limburg",
    "sg:tags":[
        "repair",
        "mainten",
        "-",
        "central",
        "heating"
    ],
    "wof:name":"E & L Services Bvba",
    "wof:placetype":"venue"
},
  "geometry": {"coordinates":[5.2143912315,51.061466217],"type":"Point"}
}