{
  "type": "Feature",
  "properties": {
    "iso:country":"BE",
    "sg:address":"Rue Georges-willame 26",
    "sg:city":"Nivelles",
    "sg:orig_category":"Artsen and specialisten Ziekenhuizen and zorginstellingen",
    "sg:phone":"+32 67 21 95 61",
    "sg:postcode":"1400",
    "sg:province":"Brabant Wallon",
    "wof:name":"Centre Psychiatriquetraversi\u00c8re",
    "wof:placetype":"venue"
},
  "geometry": {"coordinates":[4.3360109329,50.6014900208],"type":"Point"}
}