{
  "type": "Feature",
  "properties": {
    "addr:full":"R Du Balli 49 Bruxelles Bruxelles-Capitale 1050",
    "addr:housenumber":"49",
    "addr:postcode":"1050",
    "addr:street":"R",
    "iso:country":"BE",
    "sg:address":"R Du Balli 49",
    "sg:city":"Bruxelles",
    "sg:classifiers":[
        {
            "category":"Personal",
            "subcategory":"Beauty Salon",
            "type":"Services"
        }
    ],
    "sg:postcode":"1050",
    "sg:province":"Bruxelles-Capitale",
    "sg:tags":[
        "de",
        "coiffure"
    ],
    "wof:name":"Camille Albane",
    "wof:placetype":"venue"
},
  "geometry": {"coordinates":[4.3610877991,50.8263664246],"type":"Point"}
}