{
  "type": "Feature",
  "properties": {
    "addr:full":"Boelare 32 Box 3 Eeklo Oost-Vlaanderen 9900",
    "addr:housenumber":"32;3",
    "addr:postcode":"9900",
    "addr:street":"Boelare;Box",
    "iso:country":"BE",
    "sg:address":"Boelare 32 Box 3",
    "sg:city":"Eeklo",
    "sg:classifiers":[
        {
            "category":"Social Services",
            "type":"Services"
        }
    ],
    "sg:phone":"+32 9 378 22 77",
    "sg:postcode":"9900",
    "sg:province":"Oost-Vlaanderen",
    "wof:name":"Children In India Vzw",
    "wof:placetype":"venue"
},
  "geometry": {"coordinates":[3.5653169155,51.1861076355],"type":"Point"}
}