{
  "type": "Feature",
  "properties": {
    "addr:full":"Kriekelaerestraat 12 Pepingen (bellingen) Vlaams-Brabant 1674",
    "addr:housenumber":"12",
    "addr:postcode":"1674",
    "addr:street":"Kriekelaerestraat",
    "iso:country":"BE",
    "sg:address":"Kriekelaerestraat 12",
    "sg:city":"Pepingen (bellingen)",
    "sg:classifiers":[
        {
            "category":"Shopping",
            "type":"Retail Goods"
        }
    ],
    "sg:phone":"+32 2 360 16 57",
    "sg:postcode":"1674",
    "sg:province":"Vlaams-Brabant",
    "sg:tags":[
        "product",
        "cleaning",
        "maintenance"
    ],
    "wof:name":"Eurosun",
    "wof:placetype":"venue"
},
  "geometry": {"coordinates":[4.1522321701,50.7413444519],"type":"Point"}
}