{
  "type": "Feature",
  "properties": {
    "iso:country":"BE",
    "sg:address":"Treurenberg 11",
    "sg:city":"Brussel/bruxelles",
    "sg:orig_category":"Chaussures",
    "sg:phone":"+32 2 223 17 67",
    "sg:postcode":"1000",
    "sg:province":"Bruxelles-Capitale",
    "wof:name":"Huis Mezura",
    "wof:placetype":"venue"
},
  "geometry": {"coordinates":[4.3513898849,50.8584594727],"type":"Point"}
}