{
  "type": "Feature",
  "properties": {
    "iso:country":"BE",
    "sg:address":"Voermanstr 5",
    "sg:city":"Staden",
    "sg:classifiers":[
        {
            "category":"Food & Beverages",
            "subcategory":"Fruits & Vegetables",
            "type":"Retail Goods"
        }
    ],
    "sg:phone":"+32 51 70 82 70",
    "sg:postcode":"8840",
    "sg:province":"West-Vlaanderen",
    "sg:tags":[
        "frozen",
        "product",
        "related"
    ],
    "wof:name":"Horafrost Nv",
    "wof:placetype":"venue"
},
  "geometry": {"coordinates":[3.0317509174,50.9486122131],"type":"Point"}
}