{
  "type": "Feature",
  "properties": {
    "addr:full":"Patersstraat 57 Turnhout Antwerpen 2300",
    "addr:housenumber":"57",
    "addr:postcode":"2300",
    "addr:street":"Patersstraat",
    "iso:country":"BE",
    "sg:address":"Patersstraat 57",
    "sg:city":"Turnhout",
    "sg:orig_category":"Artsen and specialisten",
    "sg:phone":"+32 14 41 65 82",
    "sg:postcode":"2300",
    "sg:province":"Antwerpen",
    "wof:name":"Arnold De Vel",
    "wof:placetype":"venue"
},
  "geometry": {"coordinates":[4.9494700432,51.3257446289],"type":"Point"}
}