{
  "type": "Feature",
  "properties": {
    "iso:country":"BE",
    "sg:address":"Denderstraat 1",
    "sg:city":"Geraardsbergen",
    "sg:classifiers":[
        {
            "category":"Banks & Credit Unions",
            "subcategory":"Financial Services",
            "type":"Services"
        }
    ],
    "sg:phone":"+32 54 42 13 75",
    "sg:postcode":"9500",
    "sg:province":"Oost-Vlaanderen",
    "sg:tags":[
        "loan",
        "mortgage"
    ],
    "wof:name":"Hanssens R",
    "wof:placetype":"venue"
},
  "geometry": {"coordinates":[3.8824260235,50.7737541199],"type":"Point"}
}