{
  "type": "Feature",
  "properties": {
    "addr:full":"Rue Terraque 6 Lessines Hainaut 7861",
    "addr:housenumber":"6",
    "addr:postcode":"7861",
    "addr:street":"Rue Terraque;Hainaut",
    "iso:country":"BE",
    "sg:address":"Rue Terraque 6",
    "sg:city":"Lessines",
    "sg:orig_category":"Sportclubs",
    "sg:phone":"+32 68 33 49 10",
    "sg:postcode":"7861",
    "sg:province":"Hainaut",
    "wof:name":"Les Vaillants Acrenois",
    "wof:placetype":"venue"
},
  "geometry": {"coordinates":[3.8005371094,50.6949424744],"type":"Point"}
}