{
  "type": "Feature",
  "properties": {
    "iso:country":"BE",
    "sg:address":"Vijftien Augustusstraat 81",
    "sg:city":"Zutendaal",
    "sg:classifiers":[
        {
            "category":"Health Services",
            "subcategory":"Nursing And Care Facility",
            "type":"Services"
        }
    ],
    "sg:phone":"+32 89 61 37 79",
    "sg:postcode":"3690",
    "sg:province":"Limburg",
    "sg:tags":[
        "home"
    ],
    "wof:name":"Schellingen M-j",
    "wof:placetype":"venue"
},
  "geometry": {"coordinates":[5.5857930183,50.9319190979],"type":"Point"}
}