{
  "type": "Feature",
  "properties": {
    "addr:full":"Avenue De La Spirale 37 Sint-lambrechts-woluwe/woluwe-saint-lambert Bruxelles-Capitale 1200",
    "addr:housenumber":"37",
    "addr:postcode":"1200",
    "addr:street":"Avenue De La Spirale",
    "iso:country":"BE",
    "sg:address":"Avenue De La Spirale 37",
    "sg:city":"Sint-lambrechts-woluwe/woluwe-saint-lambert",
    "sg:orig_category":"Instituts de beaut\u00e9",
    "sg:phone":"+32 2 771 35 55",
    "sg:postcode":"1200",
    "sg:province":"Bruxelles-Capitale",
    "wof:name":"Michele Lambert",
    "wof:placetype":"venue"
},
  "geometry": {"coordinates":[4.4553461075,50.8452606201],"type":"Point"}
}