{
  "type": "Feature",
  "properties": {
    "iso:country":"BE",
    "sg:address":"Wiezeplein 2",
    "sg:city":"Lebbeke (wieze)",
    "sg:classifiers":[
        {
            "category":"Bars & Pubs",
            "type":"Food & Drink"
        }
    ],
    "sg:phone":"+32 53 70 44 22",
    "sg:postcode":"9280",
    "sg:province":"Oost-Vlaanderen",
    "wof:name":"Dikke Eik",
    "wof:placetype":"venue"
},
  "geometry": {"coordinates":[4.0799899101,50.9794998169],"type":"Point"}
}