{
  "type": "Feature",
  "properties": {
    "addr:full":"Rue De La Station 86 Enghien Hainaut 7850",
    "addr:housenumber":"86",
    "addr:postcode":"7850",
    "addr:street":"Rue De La Station",
    "iso:country":"BE",
    "sg:address":"Rue De La Station 86",
    "sg:city":"Enghien",
    "sg:orig_category":"Transports ferroviaires",
    "sg:phone":"+32 2 395 37 37",
    "sg:postcode":"7850",
    "sg:province":"Hainaut",
    "wof:name":"Gare Enghien",
    "wof:placetype":"venue"
},
  "geometry": {"coordinates":[4.0466170311,50.696975708],"type":"Point"}
}