{
  "type": "Feature",
  "properties": {
    "addr:full":"Mageleinstraat 7ba Gent Oost-Vlaanderen 9000",
    "addr:housenumber":"7ba",
    "addr:postcode":"9000",
    "addr:street":"Mageleinstraat;Oost-Vlaanderen",
    "iso:country":"BE",
    "sg:address":"Mageleinstraat 7ba",
    "sg:city":"Gent",
    "sg:orig_category":"Editeurs de livres",
    "sg:phone":"+32 9 233 38 23",
    "sg:postcode":"9000",
    "sg:province":"Oost-Vlaanderen",
    "wof:name":"Frank De Wulf Productions",
    "wof:placetype":"venue"
},
  "geometry": {"coordinates":[3.7247040272,51.0533447266],"type":"Point"}
}