{
  "type": "Feature",
  "properties": {
    "addr:full":"Kelmiser Heide 47 Kelmis (neu Moresnet) Li\u00e8ge 4721",
    "addr:housenumber":"47",
    "addr:postcode":"4721",
    "addr:street":"Kelmiser Heide;Neu",
    "iso:country":"BE",
    "sg:address":"Kelmiser Heide 47",
    "sg:city":"Kelmis (neu Moresnet)",
    "sg:classifiers":[
        {
            "category":"Community Center",
            "subcategory":"Ethnic",
            "type":"Public Place"
        }
    ],
    "sg:phone":"+32 87 65 71 96",
    "sg:postcode":"4721",
    "sg:province":"Li\u00e8ge",
    "sg:tags":[
        "industrial",
        "research"
    ],
    "wof:name":"Techinter Sprl",
    "wof:placetype":"venue"
},
  "geometry": {"coordinates":[6.0215802193,50.7182273865],"type":"Point"}
}