{
  "type": "Feature",
  "properties": {
    "iso:country":"BE",
    "sg:address":"Boulevard Du Jardin Botanique 6b1",
    "sg:city":"Brussel/bruxelles",
    "sg:orig_category":"Agences d\u00b4interim and personnel temporaire",
    "sg:phone":"+32 2 218 18 00",
    "sg:postcode":"1000",
    "sg:province":"Bruxelles-Capitale",
    "wof:name":"Daoust Interim",
    "wof:placetype":"venue"
},
  "geometry": {"coordinates":[4.3564658165,50.8554954529],"type":"Point"}
}