{
  "type": "Feature",
  "properties": {
    "addr:full":"Avenue De Mai 276 Bruxelles (woluwe-saint-lambert) Bruxelles-Capitale 1200",
    "addr:housenumber":"276",
    "addr:postcode":"1200",
    "addr:street":"Avenue De Mai",
    "iso:country":"BE",
    "sg:address":"Avenue De Mai 276",
    "sg:city":"Bruxelles (woluwe-saint-lambert)",
    "sg:classifiers":[
        {
            "category":"Real Estate",
            "subcategory":"Architect",
            "type":"Services"
        }
    ],
    "sg:phone":"+32 2 736 10 36",
    "sg:postcode":"1200",
    "sg:province":"Bruxelles-Capitale",
    "wof:name":"Parizel E",
    "wof:placetype":"venue"
},
  "geometry": {"coordinates":[4.4102859497,50.848197937],"type":"Point"}
}