{
  "type": "Feature",
  "properties": {
    "addr:full":"Langestraat 2 De Haan West-Vlaanderen 8420",
    "addr:housenumber":"2",
    "addr:postcode":"8420",
    "addr:street":"Langestraat",
    "iso:country":"BE",
    "sg:address":"Langestraat 2",
    "sg:city":"De Haan",
    "sg:orig_category":"Banques and organismes de cr\u00e9dit",
    "sg:phone":"+32 50 41 31 66",
    "sg:postcode":"8420",
    "sg:province":"West-Vlaanderen",
    "wof:name":"Bbl",
    "wof:placetype":"venue"
},
  "geometry": {"coordinates":[3.0802760124,51.3006134033],"type":"Point"}
}