{
  "type": "Feature",
  "properties": {
    "iso:country":"BE",
    "sg:address":"Chauss\u00e9e De Lannoy 80",
    "sg:city":"Tournai (froyennes)",
    "sg:classifiers":[
        {
            "category":"Health Services",
            "subcategory":"Dentist",
            "type":"Services"
        }
    ],
    "sg:phone":"+32 69 22 82 23",
    "sg:postcode":"7503",
    "sg:province":"Hainaut",
    "wof:name":"Lef\u00e8bvre Philippe",
    "wof:placetype":"venue"
},
  "geometry": {"coordinates":[3.3520989418,50.6202316284],"type":"Point"}
}