{
  "type": "Feature",
  "properties": {
    "addr:full":"De Bruwaan 14ba Oudenaarde Oost-Vlaanderen 9700",
    "addr:postcode":"9700",
    "addr:street":"Oost-Vlaanderen",
    "iso:country":"BE",
    "sg:address":"De Bruwaan 14ba",
    "sg:city":"Oudenaarde",
    "sg:orig_category":"Installation de menuiserie m\u00e9tallique. Installation de menuiserie en bois and plastique. Rev\u00eatements",
    "sg:phone":"+32 55 31 27 95",
    "sg:postcode":"9700",
    "sg:province":"Oost-Vlaanderen",
    "wof:name":"Sonobo",
    "wof:placetype":"venue"
},
  "geometry": {"coordinates":[3.6085999012,50.842590332],"type":"Point"}
}