{
  "type": "Feature",
  "properties": {
    "addr:full":"H. Consciencestraat 52 Blankenberge West-Vlaanderen 8370",
    "addr:housenumber":"52",
    "addr:postcode":"8370",
    "addr:street":"Consciencestraat",
    "iso:country":"BE",
    "sg:address":"H. Consciencestraat 52",
    "sg:city":"Blankenberge",
    "sg:orig_category":"Alternatieve geneeskunde Artsen and specialisten",
    "sg:phone":"+32 50 41 65 82",
    "sg:postcode":"8370",
    "sg:province":"West-Vlaanderen",
    "wof:name":"Dokter Vanhimbeeck Patrick",
    "wof:placetype":"venue"
},
  "geometry": {"coordinates":[3.125056982,51.3143348694],"type":"Point"}
}