{
  "type": "Feature",
  "properties": {
    "addr:full":"Kapelstraat 10 Temse (steendorp) Oost-Vlaanderen 9140",
    "addr:housenumber":"10",
    "addr:postcode":"9140",
    "addr:street":"Kapelstraat",
    "iso:country":"BE",
    "sg:address":"Kapelstraat 10",
    "sg:city":"Temse (steendorp)",
    "sg:classifiers":[
        {
            "category":"Banks & Credit Unions",
            "subcategory":"Investment Brokerage",
            "type":"Services"
        }
    ],
    "sg:phone":"+32 3 774 39 22",
    "sg:postcode":"9140",
    "sg:province":"Oost-Vlaanderen",
    "sg:tags":[
        "repair",
        "-",
        "installation",
        "sanitary",
        "article"
    ],
    "wof:name":"Foubert Diversa Nv",
    "wof:placetype":"venue"
},
  "geometry": {"coordinates":[4.2477002144,51.1289482117],"type":"Point"}
}