{
  "type": "Feature",
  "properties": {
    "addr:full":"Kapellensteenweg 365 Box 1 Kalmthout Antwerpen 2920",
    "addr:housenumber":"365;1",
    "addr:postcode":"2920",
    "addr:street":"Kapellensteenweg;Box",
    "iso:country":"BE",
    "sg:address":"Kapellensteenweg 365 Box 1",
    "sg:city":"Kalmthout",
    "sg:classifiers":[
        {
            "category":"Professional",
            "subcategory":"Accounting & Tax Preparation",
            "type":"Services"
        }
    ],
    "sg:phone":"+32 3 666 10 51",
    "sg:postcode":"2920",
    "sg:province":"Antwerpen",
    "sg:tags":[
        "accountant"
    ],
    "wof:name":"Destrooper A",
    "wof:placetype":"venue"
},
  "geometry": {"coordinates":[4.4724798203,51.3744773865],"type":"Point"}
}