{
  "type": "Feature",
  "properties": {
    "addr:full":"Rattendaal 3 Sint-pieters-leeuw Vlaams-Brabant 1600",
    "addr:housenumber":"3",
    "addr:postcode":"1600",
    "addr:street":"Rattendaal",
    "iso:country":"BE",
    "sg:address":"Rattendaal 3",
    "sg:city":"Sint-pieters-leeuw",
    "sg:orig_category":"Domotics",
    "sg:phone":"+32 2 377 51 61",
    "sg:postcode":"1600",
    "sg:province":"Vlaams-Brabant",
    "wof:name":"Calelec Bvba",
    "wof:placetype":"venue"
},
  "geometry": {"coordinates":[4.2551898956,50.801410675],"type":"Point"}
}