{
  "type": "Feature",
  "properties": {
    "iso:country":"BE",
    "sg:address":"Brusselsesteenweg 4",
    "sg:city":"Beersel (alsemberg)",
    "sg:classifiers":[
        {
            "category":"Health Services",
            "subcategory":"Doctor",
            "type":"Services"
        }
    ],
    "sg:phone":"+32 2 381 10 66",
    "sg:postcode":"1652",
    "sg:province":"Vlaams-Brabant",
    "sg:tags":[
        "medicinephysicians",
        "surgeon"
    ],
    "wof:name":"Lannoy H",
    "wof:placetype":"venue"
},
  "geometry": {"coordinates":[4.3372411728,50.7416610718],"type":"Point"}
}