{
  "type": "Feature",
  "properties": {
    "iso:country":"BE",
    "sg:address":"Blankenbergse Steenweg 21",
    "sg:city":"Zuienkerke",
    "sg:orig_category":"R\u00e9cup\u00e9ration de mati\u00e8res m\u00e9talliques recyclables and d\u00e9molisseurs de voitures. D\u00e9chets and d\u00e9bris Gr",
    "sg:phone":"+32 50 41 13 78",
    "sg:postcode":"8377",
    "sg:province":"West-Vlaanderen",
    "wof:name":"Romain Lapin",
    "wof:placetype":"venue"
},
  "geometry": {"coordinates":[3.176774025,51.2745246887],"type":"Point"}
}