{
  "type": "Feature",
  "properties": {
    "addr:full":"R\u00e9sidence De La Bascule 35 Mons Hainaut 7000",
    "addr:housenumber":"35",
    "addr:postcode":"7000",
    "addr:street":"Re\u0301Sidence De La Bascule;Hainaut",
    "iso:country":"BE",
    "sg:address":"R\u00e9sidence De La Bascule 35",
    "sg:city":"Mons",
    "sg:classifiers":[
        {
            "category":"Health Services",
            "subcategory":"Health Practitioner",
            "type":"Services"
        }
    ],
    "sg:phone":"+32 65 31 69 88",
    "sg:postcode":"7000",
    "sg:province":"Hainaut",
    "sg:tags":[
        "physiotherapist"
    ],
    "wof:name":"Sermon M",
    "wof:placetype":"venue"
},
  "geometry": {"coordinates":[3.9904389381,50.4511947632],"type":"Point"}
}