{
  "type": "Feature",
  "properties": {
    "addr:full":"Molenveld 58 Balen Antwerpen 2490",
    "addr:housenumber":"58",
    "addr:postcode":"2490",
    "addr:street":"Molenveld",
    "iso:country":"BE",
    "sg:address":"Molenveld 58",
    "sg:city":"Balen",
    "sg:classifiers":[
        {
            "category":"Personal",
            "subcategory":"Beauty Salon",
            "type":"Services"
        }
    ],
    "sg:phone":"+32 14 81 27 05",
    "sg:postcode":"2490",
    "sg:province":"Antwerpen",
    "sg:tags":[
        "de",
        "coiffure"
    ],
    "wof:name":"Lea Berckmans",
    "wof:placetype":"venue"
},
  "geometry": {"coordinates":[5.1777820587,51.1740646362],"type":"Point"}
}