{
  "type": "Feature",
  "properties": {
    "iso:country":"BE",
    "sg:address":"Chauss\u00e9e De Louvain 13",
    "sg:city":"Eghez\u00e9e",
    "sg:classifiers":[
        {
            "category":"Personal",
            "subcategory":"Beauty Salon",
            "type":"Services"
        }
    ],
    "sg:phone":"+32 81 74 75 95",
    "sg:postcode":"5310",
    "sg:province":"Namur",
    "wof:name":"Centre D'esthetique & Aromatherapie",
    "wof:placetype":"venue"
},
  "geometry": {"coordinates":[4.9111261368,50.5926589966],"type":"Point"}
}