{
  "type": "Feature",
  "properties": {
    "addr:full":"Chauss\u00c9e De Wavre 2045 Oudergem/auderghem Bruxelles-Capitale 1160",
    "addr:postcode":"2045;1160",
    "addr:street":"Chausse\u0301E De Wavre",
    "iso:country":"BE",
    "sg:address":"Chauss\u00c9e De Wavre 2045",
    "sg:city":"Oudergem/auderghem",
    "sg:classifiers":[
        {
            "category":"Fast Food",
            "type":"Food & Drink"
        }
    ],
    "sg:phone":"+32 2 672 34 76",
    "sg:postcode":"1160",
    "sg:province":"Bruxelles-Capitale",
    "sg:tags":[
        "restaurant",
        "\u00c0",
        "domicile",
        "emporter",
        "livraison",
        "restaurants"
    ],
    "wof:name":"Thai Express",
    "wof:placetype":"venue"
},
  "geometry": {"coordinates":[4.4421157837,50.8103027344],"type":"Point"}
}