{
  "type": "Feature",
  "properties": {
    "addr:full":"Rue Des M\u00c9sanges 3 Hamois Namur 5360",
    "addr:housenumber":"3",
    "addr:postcode":"5360",
    "addr:street":"Rue Des Me\u0301Sanges",
    "iso:country":"BE",
    "sg:address":"Rue Des M\u00c9sanges 3",
    "sg:city":"Hamois",
    "sg:orig_category":"Installation \u00e9lectrique r\u00e9sidentielle",
    "sg:phone":"+32 83 21 44 42",
    "sg:postcode":"5360",
    "sg:province":"Namur",
    "wof:name":"Ets. Dachelet Jos\u00c9",
    "wof:placetype":"venue"
},
  "geometry": {"coordinates":[5.0522170067,50.3394126892],"type":"Point"}
}