{
  "type": "Feature",
  "properties": {
    "addr:full":"Warden Oomlaan 11 Zonnebeke West-Vlaanderen 8980",
    "addr:housenumber":"11",
    "addr:postcode":"8980",
    "addr:street":"Oomlaan",
    "iso:country":"BE",
    "sg:address":"Warden Oomlaan 11",
    "sg:city":"Zonnebeke",
    "sg:orig_category":"Kapsalons",
    "sg:phone":"+32 57 46 80 17",
    "sg:postcode":"8980",
    "sg:province":"West-Vlaanderen",
    "wof:name":"Nancy Desomer",
    "wof:placetype":"venue"
},
  "geometry": {"coordinates":[3.0216031075,50.8477287292],"type":"Point"}
}