{
  "type": "Feature",
  "properties": {
    "iso:country":"BE",
    "sg:address":"Pleitstr 3",
    "sg:city":"Gent",
    "sg:classifiers":[
        {
            "category":"Marine",
            "type":"Transportation"
        }
    ],
    "sg:phone":"+32 9 342 20 19",
    "sg:postcode":"9042",
    "sg:province":"Oost-Vlaanderen",
    "sg:tags":[
        "transport",
        "sea"
    ],
    "wof:name":"Agro-minne Binnenscheepvaart Nv",
    "wof:placetype":"venue"
},
  "geometry": {"coordinates":[3.7928240299,51.1470489502],"type":"Point"}
}