{
  "type": "Feature",
  "properties": {
    "addr:full":"Chauss\u00e9e De Redemont 16 La Louvi\u00e8re (haine-saint-paul) Hainaut 7100",
    "addr:housenumber":"16",
    "addr:postcode":"7100",
    "addr:street":"Chausse\u0301E De Redemont",
    "iso:country":"BE",
    "sg:address":"Chauss\u00e9e De Redemont 16",
    "sg:city":"La Louvi\u00e8re (haine-saint-paul)",
    "sg:classifiers":[
        {
            "category":"Manufacturing",
            "subcategory":"Tools & Machinery",
            "type":"Manufacturing & Wholesale Goods"
        }
    ],
    "sg:phone":"+32 64 21 16 32",
    "sg:postcode":"7100",
    "sg:province":"Hainaut",
    "sg:tags":[
        "-"
    ],
    "wof:name":"Lietar P",
    "wof:placetype":"venue"
},
  "geometry": {"coordinates":[4.2093777657,50.4682579041],"type":"Point"}
}