{
  "type": "Feature",
  "properties": {
    "iso:country":"BE",
    "sg:address":"Mechelsesteenweg 59",
    "sg:city":"Antwerpen",
    "sg:orig_category":"Blanchisseries and teintureries",
    "sg:phone":"+32 3 232 75 34",
    "sg:postcode":"2018",
    "sg:province":"Antwerpen",
    "wof:name":"Droogkuis Van Osta",
    "wof:placetype":"venue"
},
  "geometry": {"coordinates":[4.4086308479,51.2087402344],"type":"Point"}
}