{
  "type": "Feature",
  "properties": {
    "addr:full":"Zavelstraat 2 Lille Antwerpen 2275",
    "addr:housenumber":"2",
    "addr:postcode":"2275",
    "addr:street":"Zavelstraat",
    "iso:country":"BE",
    "sg:address":"Zavelstraat 2",
    "sg:city":"Lille",
    "sg:classifiers":[
        {
            "category":"Retail",
            "subcategory":"Repair Shop",
            "type":"Services"
        }
    ],
    "sg:phone":"+32 14 88 24 06",
    "sg:postcode":"2275",
    "sg:province":"Antwerpen",
    "sg:tags":[
        "upholsterer"
    ],
    "wof:name":"Thibaut E",
    "wof:placetype":"venue"
},
  "geometry": {"coordinates":[4.8197321892,51.2307090759],"type":"Point"}
}