{
  "type": "Feature",
  "properties": {
    "addr:full":"Rue L\u00e9onard Lacroix 2e Geer (hollogne-sur-geer) Li\u00e8ge 4250",
    "addr:housenumber":"2e",
    "addr:postcode":"4250",
    "addr:street":"Rue Le\u0301Onard Lacroix;Hollogne-Sur-Geer",
    "iso:country":"BE",
    "sg:address":"Rue L\u00e9onard Lacroix 2e",
    "sg:city":"Geer (hollogne-sur-geer)",
    "sg:classifiers":[
        {
            "category":"Health Services",
            "subcategory":"Health Practitioner",
            "type":"Services"
        }
    ],
    "sg:phone":"+32 19 32 33 54",
    "sg:postcode":"4250",
    "sg:province":"Li\u00e8ge",
    "sg:tags":[
        "physiotherapist"
    ],
    "wof:name":"Degrez I",
    "wof:placetype":"venue"
},
  "geometry": {"coordinates":[5.2110991478,50.6786499023],"type":"Point"}
}