{
  "type": "Feature",
  "properties": {
    "addr:full":"Ganzendreef 3 Lokeren Oost-Vlaanderen 9160",
    "addr:housenumber":"3",
    "addr:postcode":"9160",
    "addr:street":"Ganzendreef",
    "iso:country":"BE",
    "sg:address":"Ganzendreef 3",
    "sg:city":"Lokeren",
    "sg:orig_category":"Varkenskwekers",
    "sg:phone":"+32 9 348 93 85",
    "sg:postcode":"9160",
    "sg:province":"Oost-Vlaanderen",
    "wof:name":"Jean Fiers",
    "wof:placetype":"venue"
},
  "geometry": {"coordinates":[3.9264919758,51.089805603],"type":"Point"}
}