{
  "type": "Feature",
  "properties": {
    "addr:full":"Hoogstraat 49 Puurs Antwerpen 2870",
    "addr:housenumber":"49",
    "addr:postcode":"2870",
    "addr:street":"Hoogstraat",
    "iso:country":"BE",
    "sg:address":"Hoogstraat 49",
    "sg:city":"Puurs",
    "sg:classifiers":[
        {
            "category":"Personal",
            "subcategory":"Beauty Salon",
            "type":"Services"
        }
    ],
    "sg:phone":"+32 3 889 42 65",
    "sg:postcode":"2870",
    "sg:province":"Antwerpen",
    "sg:tags":[
        "de",
        "coiffure"
    ],
    "wof:name":"Coiffure Terry",
    "wof:placetype":"venue"
},
  "geometry": {"coordinates":[4.2792878151,51.0761795044],"type":"Point"}
}