{
  "type": "Feature",
  "properties": {
    "addr:full":"Koning Leopoldlaan 81g Maldegem Oost-Vlaanderen 9990",
    "addr:housenumber":"81g",
    "addr:postcode":"9990",
    "addr:street":"Koning Leopoldlaan",
    "iso:country":"BE",
    "sg:address":"Koning Leopoldlaan 81g",
    "sg:city":"Maldegem",
    "sg:classifiers":[
        {
            "category":"Structure",
            "subcategory":"Warehouse",
            "type":"Public Place"
        }
    ],
    "sg:phone":"+32 50 71 84 44",
    "sg:postcode":"9990",
    "sg:province":"Oost-Vlaanderen",
    "sg:tags":[
        "chiller",
        "air-conditioning",
        "system"
    ],
    "wof:name":"Bral Chauffage B.v.b.a.",
    "wof:placetype":"venue"
},
  "geometry": {"coordinates":[3.4647979736,51.2040176392],"type":"Point"}
}