{
  "type": "Feature",
  "properties": {
    "addr:full":"Wassenhovestr. 1 Zottegem Oost-Vlaanderen 9620",
    "addr:housenumber":"1",
    "addr:postcode":"9620",
    "addr:street":"Wassenhovestr.",
    "iso:country":"BE",
    "sg:address":"Wassenhovestr. 1",
    "sg:city":"Zottegem",
    "sg:classifiers":[
        {
            "category":"Shopping",
            "subcategory":"Clothing, Apparel, & Fashions",
            "type":"Retail Goods"
        }
    ],
    "sg:phone":"+32 9 360 01 72",
    "sg:postcode":"9620",
    "sg:province":"Oost-Vlaanderen",
    "sg:tags":[
        "textile",
        "clothing",
        "clothes"
    ],
    "wof:name":"Intershirt Bvba",
    "wof:placetype":"venue"
},
  "geometry": {"coordinates":[3.8112111092,50.871181488],"type":"Point"}
}