{
  "type": "Feature",
  "properties": {
    "iso:country":"BE",
    "sg:address":"Th. De Beckerstraat 24 Box 6",
    "sg:city":"Aarschot",
    "sg:classifiers":[
        {
            "category":"Shopping",
            "subcategory":"Clothing, Apparel, & Fashions",
            "type":"Retail Goods"
        }
    ],
    "sg:phone":"+32 16 56 95 14",
    "sg:postcode":"3200",
    "sg:province":"Vlaams-Brabant",
    "sg:tags":[
        "boutique"
    ],
    "wof:name":"Bess",
    "wof:placetype":"venue"
},
  "geometry": {"coordinates":[4.837100029,50.9852027893],"type":"Point"}
}