{
  "type": "Feature",
  "properties": {
    "addr:full":"Kloosterstraat 37 Zemst Vlaams-Brabant 1980",
    "addr:housenumber":"37",
    "addr:postcode":"1980",
    "addr:street":"Kloosterstraat;Vlaams-Brabant",
    "iso:country":"BE",
    "sg:address":"Kloosterstraat 37",
    "sg:city":"Zemst",
    "sg:classifiers":[
        {
            "category":"Health Services",
            "subcategory":"Health Practitioner",
            "type":"Services"
        }
    ],
    "sg:phone":"+32 15 61 26 65",
    "sg:postcode":"1980",
    "sg:province":"Vlaams-Brabant",
    "sg:tags":[
        "physiotherapist"
    ],
    "wof:name":"Lauwers Kris",
    "wof:placetype":"venue"
},
  "geometry": {"coordinates":[4.4678668976,50.9844703674],"type":"Point"}
}