{
  "type": "Feature",
  "properties": {
    "addr:full":"Kapelstraat 100 Sint-niklaas Oost-Vlaanderen 9100",
    "addr:housenumber":"100",
    "addr:postcode":"9100",
    "addr:street":"Kapelstraat",
    "iso:country":"BE",
    "sg:address":"Kapelstraat 100",
    "sg:city":"Sint-niklaas",
    "sg:classifiers":[
        {
            "category":"Shopping",
            "subcategory":"Optician",
            "type":"Retail Goods"
        }
    ],
    "sg:phone":"+32 3 766 17 42",
    "sg:postcode":"9100",
    "sg:province":"Oost-Vlaanderen",
    "sg:tags":[
        "-"
    ],
    "wof:name":"Pearle Vision Center",
    "wof:placetype":"venue"
},
  "geometry": {"coordinates":[4.1548528671,51.1511993408],"type":"Point"}
}