{
  "type": "Feature",
  "properties": {
    "iso:country":"BE",
    "sg:address":"Serviestraat 88",
    "sg:city":"Vorst/forest",
    "sg:orig_category":"Slagers",
    "sg:phone":"+32 2 537 35 10",
    "sg:postcode":"1190",
    "sg:province":"Bruxelles-Capitale",
    "wof:name":"Boucherie Tony",
    "wof:placetype":"venue"
},
  "geometry": {"coordinates":[4.3316898346,50.828086853],"type":"Point"}
}