{
  "type": "Feature",
  "properties": {
    "addr:full":"Mgr. De Haernestraat 12 Roeselare West-Vlaanderen 8800",
    "addr:housenumber":"12",
    "addr:postcode":"8800",
    "addr:street":"Mgr. De Haernestraat",
    "iso:country":"BE",
    "sg:address":"Mgr. De Haernestraat 12",
    "sg:city":"Roeselare",
    "sg:orig_category":"Travaux de pl\u00e2trage",
    "sg:phone":"+32 51 24 77 46",
    "sg:postcode":"8800",
    "sg:province":"West-Vlaanderen",
    "wof:name":"Ignace Margodt",
    "wof:placetype":"venue"
},
  "geometry": {"coordinates":[3.1382799149,50.9327087402],"type":"Point"}
}