{
  "type": "Feature",
  "properties": {
    "addr:full":"Rue Du Vivier 132 Bastogne Luxembourg 6600",
    "addr:housenumber":"132",
    "addr:postcode":"6600",
    "addr:street":"Rue Du Vivier",
    "iso:country":"BE",
    "sg:address":"Rue Du Vivier 132",
    "sg:city":"Bastogne",
    "sg:classifiers":[
        {
            "category":"Shopping",
            "subcategory":"Clothing, Apparel, & Fashions",
            "type":"Retail Goods"
        }
    ],
    "sg:phone":"+32 61 21 36 14",
    "sg:postcode":"6600",
    "sg:province":"Luxembourg",
    "sg:tags":[
        "boutique"
    ],
    "wof:name":"Style 20",
    "wof:placetype":"venue"
},
  "geometry": {"coordinates":[5.7173857689,50.0019989014],"type":"Point"}
}