{
  "type": "Feature",
  "properties": {
    "iso:country":"BE",
    "sg:address":"Gustaaf Van Der Steenstr 92",
    "sg:city":"Lennik",
    "sg:classifiers":[
        {
            "category":"Professional",
            "type":"Services"
        }
    ],
    "sg:phone":"+32 2 532 13 32",
    "sg:postcode":"1750",
    "sg:province":"Vlaams-Brabant",
    "sg:tags":[
        "transport",
        "road"
    ],
    "wof:name":"Theo Van De Velde - Wijns Nv",
    "wof:placetype":"venue"
},
  "geometry": {"coordinates":[4.1552529335,50.8014678955],"type":"Point"}
}