{
  "type": "Feature",
  "properties": {
    "addr:full":"Steendam 53 Gent Oost-Vlaanderen 9000",
    "addr:housenumber":"53",
    "addr:postcode":"9000",
    "addr:street":"Steendam;Oost-Vlaanderen",
    "iso:country":"BE",
    "sg:address":"Steendam 53",
    "sg:city":"Gent",
    "sg:orig_category":"Boekhouders",
    "sg:phone":"+32 9 233 60 16",
    "sg:postcode":"9000",
    "sg:province":"Oost-Vlaanderen",
    "wof:name":"Catherine Tydgat",
    "wof:placetype":"venue"
},
  "geometry": {"coordinates":[3.7307729721,51.0572662354],"type":"Point"}
}