{
  "type": "Feature",
  "properties": {
    "addr:full":"Gratiekapelstraat 10 Antwerpen Antwerpen 2000",
    "addr:housenumber":"10",
    "addr:postcode":"2000",
    "addr:street":"Gratiekapelstraat",
    "iso:country":"BE",
    "sg:address":"Gratiekapelstraat 10",
    "sg:city":"Antwerpen",
    "sg:orig_category":"Agences d'exp\u00e9dition. Agences maritimes",
    "sg:phone":"+32 3 203 47 20",
    "sg:postcode":"2000",
    "sg:province":"Antwerpen",
    "wof:name":"Kennedy Hunter",
    "wof:placetype":"venue"
},
  "geometry": {"coordinates":[4.4082422256,51.2221565247],"type":"Point"}
}