{
  "type": "Feature",
  "properties": {
    "iso:country":"BE",
    "sg:address":"Catharinadal 5",
    "sg:city":"Hamont-achel",
    "sg:orig_category":"Rundveehouders",
    "sg:phone":"+32 11 64 13 09",
    "sg:postcode":"3930",
    "sg:province":"Limburg",
    "wof:name":"Pieter Boonen",
    "wof:placetype":"venue"
},
  "geometry": {"coordinates":[5.4844250679,51.2529067993],"type":"Point"}
}