{
  "type": "Feature",
  "properties": {
    "iso:country":"BE",
    "sg:address":"Chauss\u00e9e De Bruxelles 149",
    "sg:city":"Waterloo",
    "sg:classifiers":[
        {
            "category":"Government",
            "subcategory":"Office",
            "type":"Public Place"
        }
    ],
    "sg:phone":"+32 2 354 99 10",
    "sg:postcode":"1410",
    "sg:province":"Brabant Wallon",
    "sg:tags":[
        "-",
        "tourism",
        "federation"
    ],
    "wof:name":"Maison Du Tourisme De Waterloo",
    "wof:placetype":"venue"
},
  "geometry": {"coordinates":[4.3981971741,50.7176132202],"type":"Point"}
}