{
  "type": "Feature",
  "properties": {
    "addr:full":"Nachtegaalstraat 1 Merksplas Antwerpen 2330",
    "addr:housenumber":"1",
    "addr:postcode":"2330",
    "addr:street":"Nachtegaalstraat",
    "iso:country":"BE",
    "sg:address":"Nachtegaalstraat 1",
    "sg:city":"Merksplas",
    "sg:classifiers":[
        {
            "category":"Autos & Motor Vehicles",
            "subcategory":"Fuel & Gas Station",
            "type":"Retail Goods"
        }
    ],
    "sg:phone":"+32 14 63 30 49",
    "sg:postcode":"2330",
    "sg:province":"Antwerpen",
    "sg:tags":[
        "stations-service",
        "carburants"
    ],
    "wof:name":"Peeraer Belgium",
    "wof:placetype":"venue"
},
  "geometry": {"coordinates":[4.8605589867,51.3482513428],"type":"Point"}
}