{
  "type": "Feature",
  "properties": {
    "iso:country":"BE",
    "sg:address":"Leuvensesteenweg 613 Box 34",
    "sg:city":"Zaventem",
    "sg:classifiers":[
        {
            "category":"Banks & Credit Unions",
            "subcategory":"Investment Brokerage",
            "type":"Services"
        }
    ],
    "sg:phone":"+32 2 757 92 20",
    "sg:postcode":"1930",
    "sg:province":"Vlaams-Brabant",
    "sg:tags":[
        "pipe",
        "-"
    ],
    "wof:name":"Lone Star Steel International",
    "wof:placetype":"venue"
},
  "geometry": {"coordinates":[4.4972071648,50.8761253357],"type":"Point"}
}