{
  "type": "Feature",
  "properties": {
    "addr:full":"Gemeenveldstraat 3 Beersel (groot) Vlaams-Brabant 1652",
    "addr:housenumber":"3;1652",
    "addr:street":"Gemeenveldstraat;Groot Vlaams-Brabant",
    "iso:country":"BE",
    "sg:address":"Gemeenveldstraat 3",
    "sg:city":"Beersel (groot)",
    "sg:orig_category":"Supermarkten",
    "sg:phone":"+32 2 380 22 73",
    "sg:postcode":"1652",
    "sg:province":"Vlaams-Brabant",
    "wof:name":"Colruyt",
    "wof:placetype":"venue"
},
  "geometry": {"coordinates":[4.3319301605,50.7411193848],"type":"Point"}
}