{
  "type": "Feature",
  "properties": {
    "addr:full":"Avenue Maurice Destenay 3 Li\u00e8ge 1 Li\u00e8ge 4000",
    "addr:housenumber":"3;1",
    "addr:postcode":"4000",
    "addr:street":"Avenue Maurice Destenay",
    "iso:country":"BE",
    "sg:address":"Avenue Maurice Destenay 3",
    "sg:city":"Li\u00e8ge 1",
    "sg:classifiers":[
        {
            "category":"Community Center",
            "type":"Public Place"
        }
    ],
    "sg:phone":"+32 4 222 31 95",
    "sg:postcode":"4000",
    "sg:province":"Li\u00e8ge",
    "sg:tags":[
        "medical"
    ],
    "wof:name":"Clinique Andre Renard",
    "wof:placetype":"venue"
},
  "geometry": {"coordinates":[5.5728859901,50.6383781433],"type":"Point"}
}