{
  "type": "Feature",
  "properties": {
    "addr:full":"Rue Du Postienne 47 Philippeville Namur 5600",
    "addr:housenumber":"47",
    "addr:postcode":"5600",
    "addr:street":"Rue Du Postienne",
    "iso:country":"BE",
    "sg:address":"Rue Du Postienne 47",
    "sg:city":"Philippeville",
    "sg:orig_category":"Enseignement maternel and primaire",
    "sg:phone":"+32 71 66 83 39",
    "sg:postcode":"5600",
    "sg:province":"Namur",
    "wof:name":"Ecole Fond. Communale",
    "wof:placetype":"venue"
},
  "geometry": {"coordinates":[4.5602879524,50.1685676575],"type":"Point"}
}