{
  "type": "Feature",
  "properties": {
    "iso:country":"BE",
    "sg:address":"Rue Du Paradis 65",
    "sg:city":"Nivelles",
    "sg:classifiers":[
        {
            "category":"Personal",
            "subcategory":"Nail Salon",
            "type":"Services"
        }
    ],
    "sg:phone":"+32 67 22 01 77",
    "sg:postcode":"1400",
    "sg:province":"Brabant Wallon",
    "sg:tags":[
        "pedicure"
    ],
    "wof:name":"Chatelle P",
    "wof:placetype":"venue"
},
  "geometry": {"coordinates":[4.3253750801,50.6087341309],"type":"Point"}
}