{
  "type": "Feature",
  "properties": {
    "addr:full":"Rue Longue 19 Drogenbos/drogenbos Vlaams-Brabant 1620",
    "addr:housenumber":"19",
    "addr:postcode":"1620",
    "addr:street":"Rue Longue",
    "iso:country":"BE",
    "sg:address":"Rue Longue 19",
    "sg:city":"Drogenbos/drogenbos",
    "sg:orig_category":"Epiceries",
    "sg:phone":"+32 2 378 16 32",
    "sg:postcode":"1620",
    "sg:province":"Vlaams-Brabant",
    "wof:name":"Willens",
    "wof:placetype":"venue"
},
  "geometry": {"coordinates":[4.3168702126,50.7907142639],"type":"Point"}
}