{
  "type": "Feature",
  "properties": {
    "iso:country":"BE",
    "sg:address":"Huis Ten Halven 32",
    "sg:city":"Sint-niklaas",
    "sg:orig_category":"Entretien and r\u00e9parations de voitures",
    "sg:phone":"+32 3 777 57 07",
    "sg:postcode":"9100",
    "sg:province":"Oost-Vlaanderen",
    "wof:name":"Dirk Rombaut",
    "wof:placetype":"venue"
},
  "geometry": {"coordinates":[4.1649560928,51.1873016357],"type":"Point"}
}