{
  "type": "Feature",
  "properties": {
    "addr:full":"Leopold Ii Laan 25 Koksijde West-Vlaanderen 8670",
    "addr:housenumber":"25",
    "addr:postcode":"8670",
    "addr:street":"Leopold Ii Laan",
    "iso:country":"BE",
    "sg:address":"Leopold Ii Laan 25",
    "sg:city":"Koksijde",
    "sg:orig_category":"Baby- and kinderkleding",
    "sg:phone":"+32 58 51 47 39",
    "sg:postcode":"8670",
    "sg:province":"West-Vlaanderen",
    "wof:name":"Huis Filou",
    "wof:placetype":"venue"
},
  "geometry": {"coordinates":[2.6701500416,51.1121902466],"type":"Point"}
}