{
  "type": "Feature",
  "properties": {
    "addr:full":"Riemenstraat 14 Vorselaar Antwerpen 2290",
    "addr:housenumber":"14",
    "addr:postcode":"2290",
    "addr:street":"Riemenstraat",
    "iso:country":"BE",
    "sg:address":"Riemenstraat 14",
    "sg:city":"Vorselaar",
    "sg:orig_category":"Dameskledingzaken",
    "sg:phone":"+32 14 51 37 42",
    "sg:postcode":"2290",
    "sg:province":"Antwerpen",
    "wof:name":"Huis Petra",
    "wof:placetype":"venue"
},
  "geometry": {"coordinates":[4.7746720314,51.2031517029],"type":"Point"}
}