{
  "type": "Feature",
  "properties": {
    "addr:full":"Chauss\u00e9e De Jolimont 27 La Louvi\u00e8re (haine-saint-pierre) Hainaut 7100",
    "addr:housenumber":"27",
    "addr:postcode":"7100",
    "addr:street":"Chausse\u0301E De Jolimont",
    "iso:country":"BE",
    "sg:address":"Chauss\u00e9e De Jolimont 27",
    "sg:city":"La Louvi\u00e8re (haine-saint-pierre)",
    "sg:classifiers":[
        {
            "category":"Home & Garden",
            "subcategory":"Home Furnishings",
            "type":"Retail Goods"
        }
    ],
    "sg:phone":"+32 64 22 75 79",
    "sg:postcode":"7100",
    "sg:province":"Hainaut",
    "sg:tags":[
        "interior",
        "decoration"
    ],
    "wof:name":"Accent",
    "wof:placetype":"venue"
},
  "geometry": {"coordinates":[4.2157001495,50.4721488953],"type":"Point"}
}