{
  "type": "Feature",
  "properties": {
    "iso:country":"BE",
    "sg:address":"Rue Du Pilori 0",
    "sg:city":"Couvin",
    "sg:orig_category":"Zalen voor culturele evenementen",
    "sg:phone":"+32 60 34 59 56",
    "sg:postcode":"5660",
    "sg:province":"Namur",
    "wof:name":"Centre Culturel",
    "wof:placetype":"venue"
},
  "geometry": {"coordinates":[4.4966320992,50.0526695251],"type":"Point"}
}