{
  "type": "Feature",
  "properties": {
    "addr:full":"Rue Edouard Fiers 34 Bruxelles (schaerbeek) Bruxelles-Capitale 1030",
    "addr:housenumber":"34",
    "addr:postcode":"1030",
    "addr:street":"Rue Edouard Fiers",
    "iso:country":"BE",
    "sg:address":"Rue Edouard Fiers 34",
    "sg:city":"Bruxelles (schaerbeek)",
    "sg:classifiers":[
        {
            "category":"Health Services",
            "subcategory":"Doctor",
            "type":"Services"
        }
    ],
    "sg:phone":"+32 2 242 84 93",
    "sg:postcode":"1030",
    "sg:province":"Bruxelles-Capitale",
    "sg:tags":[
        "medicinephysicians",
        "surgeon"
    ],
    "wof:name":"Closset Marc",
    "wof:placetype":"venue"
},
  "geometry": {"coordinates":[4.378923893,50.8630256653],"type":"Point"}
}