{
  "type": "Feature",
  "properties": {
    "addr:full":"Pontweg 31 Aalter Oost-Vlaanderen 9880",
    "addr:housenumber":"31",
    "addr:postcode":"9880",
    "addr:street":"Pontweg",
    "iso:country":"BE",
    "sg:address":"Pontweg 31",
    "sg:city":"Aalter",
    "sg:orig_category":"Radioproductie and uitzendingen",
    "sg:phone":"+32 9 375 20 15",
    "sg:postcode":"9880",
    "sg:province":"Oost-Vlaanderen",
    "wof:name":"Radio Meteor",
    "wof:placetype":"venue"
},
  "geometry": {"coordinates":[3.4397959709,51.096622467],"type":"Point"}
}