{
  "type": "Feature",
  "properties": {
    "addr:full":"Opperstraat 68 Box 1 Liedekerke Vlaams-Brabant 1770",
    "addr:housenumber":"68;1",
    "addr:postcode":"1770",
    "addr:street":"Opperstraat;Box;Vlaams-Brabant",
    "iso:country":"BE",
    "sg:address":"Opperstraat 68 Box 1",
    "sg:city":"Liedekerke",
    "sg:classifiers":[
        {
            "category":"Health Services",
            "subcategory":"Dentist",
            "type":"Services"
        }
    ],
    "sg:phone":"+32 53 66 66 93",
    "sg:postcode":"1770",
    "sg:province":"Vlaams-Brabant",
    "wof:name":"De Cock Wim",
    "wof:placetype":"venue"
},
  "geometry": {"coordinates":[4.0872449875,50.8695831299],"type":"Point"}
}