{
  "type": "Feature",
  "properties": {
    "addr:full":"Achterbroeksteenweg 137 Kalmthout Antwerpen 2920",
    "addr:housenumber":"137",
    "addr:postcode":"2920",
    "addr:street":"Achterbroeksteenweg",
    "iso:country":"BE",
    "sg:address":"Achterbroeksteenweg 137",
    "sg:city":"Kalmthout",
    "sg:orig_category":"V\u00e9t\u00e9rinaires",
    "sg:phone":"+32 3 666 88 27",
    "sg:postcode":"2920",
    "sg:province":"Antwerpen",
    "wof:name":"Eugeen Van Loenhout",
    "wof:placetype":"venue"
},
  "geometry": {"coordinates":[4.4777498245,51.3942909241],"type":"Point"}
}