{
  "type": "Feature",
  "properties": {
    "addr:full":"Ganzenkuil 28 Malle Antwerpen 2390",
    "addr:housenumber":"28",
    "addr:postcode":"2390",
    "addr:street":"Ganzenkuil",
    "iso:country":"BE",
    "sg:address":"Ganzenkuil 28",
    "sg:city":"Malle",
    "sg:orig_category":"Installation de menuiserie m\u00e9tallique",
    "sg:phone":"+32 3 312 16 59",
    "sg:postcode":"2390",
    "sg:province":"Antwerpen",
    "wof:name":"Jan Smans",
    "wof:placetype":"venue"
},
  "geometry": {"coordinates":[4.700594902,51.2953224182],"type":"Point"}
}