{
  "type": "Feature",
  "properties": {
    "iso:country":"BE",
    "sg:address":"Prof. Scharp\u00c9laan 35",
    "sg:city":"Betekom",
    "sg:orig_category":"Messageries",
    "sg:phone":"+32 495 22 59 88",
    "sg:postcode":"3130",
    "sg:province":"Vlaams-Brabant",
    "wof:name":"Koerierdienst Goddevriendt",
    "wof:placetype":"venue"
},
  "geometry": {"coordinates":[4.7830247879,51.0193214417],"type":"Point"}
}