{
  "type": "Feature",
  "properties": {
    "iso:country":"BE",
    "sg:address":"Staleykerheide 2",
    "sg:city":"Beringen (beverlo)",
    "sg:classifiers":[
        {
            "category":"Bars & Pubs",
            "type":"Food & Drink"
        }
    ],
    "sg:phone":"+32 11 40 39 96",
    "sg:postcode":"3581",
    "sg:province":"Limburg",
    "wof:name":"Yzer (den) Gasterij",
    "wof:placetype":"venue"
},
  "geometry": {"coordinates":[5.2927660942,51.1027412415],"type":"Point"}
}