{
  "type": "Feature",
  "properties": {
    "iso:country":"BE",
    "sg:address":"Rue Montgomery 22",
    "sg:city":"Edingen/enghien",
    "sg:orig_category":"Instituts de beaut\u00e9",
    "sg:phone":"+32 2 395 72 22",
    "sg:postcode":"7850",
    "sg:province":"Hainaut",
    "wof:name":"Le Jardin De Marie",
    "wof:placetype":"venue"
},
  "geometry": {"coordinates":[4.0375170708,50.6929664612],"type":"Point"}
}