{
  "type": "Feature",
  "properties": {
    "iso:country":"BE",
    "sg:address":"Beukenstraat 83",
    "sg:city":"Buggenhout",
    "sg:orig_category":"Eleveurs de bovins. Collecte and \u00e9puration des eaux us\u00e9es",
    "sg:phone":"+32 52 33 49 80",
    "sg:postcode":"9255",
    "sg:province":"Oost-Vlaanderen",
    "wof:name":"Jozef Van Den Bossche",
    "wof:placetype":"venue"
},
  "geometry": {"coordinates":[4.1758818626,51.0186729431],"type":"Point"}
}