{
  "type": "Feature",
  "properties": {
    "addr:full":"Rue Goffart 20 Elsene/ixelles Bruxelles-Capitale 1050",
    "addr:housenumber":"20",
    "addr:postcode":"1050",
    "addr:street":"Rue Goffart",
    "iso:country":"BE",
    "sg:address":"Rue Goffart 20",
    "sg:city":"Elsene/ixelles",
    "sg:orig_category":"M\u00e9decins and sp\u00e9cialistes",
    "sg:phone":"+32 2 512 07 66",
    "sg:postcode":"1050",
    "sg:province":"Bruxelles-Capitale",
    "wof:name":"Anne Demanet",
    "wof:placetype":"venue"
},
  "geometry": {"coordinates":[4.3707442284,50.8350868225],"type":"Point"}
}