{
  "type": "Feature",
  "properties": {
    "iso:country":"BE",
    "sg:address":"Scheepsdalelaan 27",
    "sg:city":"Brugge",
    "sg:orig_category":"Pain, p\u00e2tisseries and confiseries",
    "sg:phone":"+32 50 31 57 78",
    "sg:postcode":"8000",
    "sg:province":"West-Vlaanderen",
    "wof:name":"Peter Vandeputte",
    "wof:placetype":"venue"
},
  "geometry": {"coordinates":[3.2118680477,51.2175445557],"type":"Point"}
}