{
  "type": "Feature",
  "properties": {
    "addr:full":"Rue Cayauderie 122b1 Charleroi Hainaut 6000",
    "addr:housenumber":"122b1",
    "addr:postcode":"6000",
    "addr:street":"Rue Cayauderie;Hainaut",
    "iso:country":"BE",
    "sg:address":"Rue Cayauderie 122b1",
    "sg:city":"Charleroi",
    "sg:orig_category":"Travaux d'isolation",
    "sg:phone":"+32 71 42 03 02",
    "sg:postcode":"6000",
    "sg:province":"Hainaut",
    "wof:name":"Lorenzo Sanfilippo",
    "wof:placetype":"venue"
},
  "geometry": {"coordinates":[4.4570598602,50.4246139526],"type":"Point"}
}