{
  "type": "Feature",
  "properties": {
    "addr:full":"Route Provinciale 47 Mont-de-l'enclus Hainaut 7750",
    "addr:postcode":"7750",
    "addr:street":"Route Provinciale 47;Hainaut",
    "iso:country":"BE",
    "sg:address":"Route Provinciale 47",
    "sg:city":"Mont-de-l'enclus",
    "sg:classifiers":[
        {
            "category":"Insurance",
            "subcategory":"Life Insurance",
            "type":"Services"
        }
    ],
    "sg:phone":"+32 69 76 81 34",
    "sg:postcode":"7750",
    "sg:province":"Hainaut",
    "sg:tags":[
        "assurance"
    ],
    "wof:name":"P. Bossu",
    "wof:placetype":"venue"
},
  "geometry": {"coordinates":[2.6025109291,46.3370933533],"type":"Point"}
}