{
  "type": "Feature",
  "properties": {
    "addr:full":"Rue Valduc 333 Bruxelles (auderghem) Bruxelles-Capitale 1160",
    "addr:housenumber":"333",
    "addr:postcode":"1160",
    "addr:street":"Rue Valduc",
    "iso:country":"BE",
    "sg:address":"Rue Valduc 333",
    "sg:city":"Bruxelles (auderghem)",
    "sg:classifiers":[
        {
            "category":"Health Services",
            "subcategory":"Dentist",
            "type":"Services"
        }
    ],
    "sg:phone":"+32 2 672 99 21",
    "sg:postcode":"1160",
    "sg:province":"Bruxelles-Capitale",
    "wof:name":"Bodson Anne",
    "wof:placetype":"venue"
},
  "geometry": {"coordinates":[4.4106850624,50.8210334778],"type":"Point"}
}