{
  "type": "Feature",
  "properties": {
    "addr:full":"Rue Joseph Renquin 29 Bastogne Luxembourg 6600",
    "addr:housenumber":"29",
    "addr:postcode":"6600",
    "addr:street":"Rue Joseph Renquin",
    "iso:country":"BE",
    "sg:address":"Rue Joseph Renquin 29",
    "sg:city":"Bastogne",
    "sg:classifiers":[
        {
            "category":"Real Estate",
            "subcategory":"Architect",
            "type":"Services"
        }
    ],
    "sg:phone":"+32 61 21 54 71",
    "sg:postcode":"6600",
    "sg:province":"Luxembourg",
    "wof:name":"Nizet D",
    "wof:placetype":"venue"
},
  "geometry": {"coordinates":[5.7157378197,49.9995384216],"type":"Point"}
}