{
  "type": "Feature",
  "properties": {
    "iso:country":"BE",
    "sg:address":"Rue De Nivelles 19",
    "sg:city":"Braine-le-comte",
    "sg:orig_category":"Rundveehouders",
    "sg:phone":"+32 67 64 72 34",
    "sg:postcode":"7090",
    "sg:province":"Hainaut",
    "wof:name":"Fe. Sirjacq-dumortier",
    "wof:placetype":"venue"
},
  "geometry": {"coordinates":[4.2308058739,50.6063995361],"type":"Point"}
}