{
  "type": "Feature",
  "properties": {
    "addr:full":"Salvacourt 11 Vaux-sur-s\u00fbre (hompr\u00e9) Luxembourg 6640",
    "addr:housenumber":"11",
    "addr:postcode":"6640",
    "addr:street":"Salvacourt",
    "iso:country":"BE",
    "sg:address":"Salvacourt 11",
    "sg:city":"Vaux-sur-s\u00fbre (hompr\u00e9)",
    "sg:classifiers":[
        {
            "category":"Health Services",
            "subcategory":"Nursing And Care Facility",
            "type":"Services"
        }
    ],
    "sg:phone":"+32 61 26 66 49",
    "sg:postcode":"6640",
    "sg:province":"Luxembourg",
    "sg:tags":[
        "home",
        "rest"
    ],
    "wof:name":"en Famille Sprl",
    "wof:placetype":"venue"
},
  "geometry": {"coordinates":[5.5671000481,49.91065979],"type":"Point"}
}