{
  "type": "Feature",
  "properties": {
    "addr:full":"Avenue Du Marouset 180 Braine-le-comte Hainaut 7090",
    "addr:housenumber":"180",
    "addr:postcode":"7090",
    "addr:street":"Avenue Du Marouset",
    "iso:country":"BE",
    "sg:address":"Avenue Du Marouset 180",
    "sg:city":"Braine-le-comte",
    "sg:classifiers":[
        {
            "category":"Professional",
            "type":"Services"
        }
    ],
    "sg:phone":"+32 67 55 34 57",
    "sg:postcode":"7090",
    "sg:province":"Hainaut",
    "sg:tags":[
        "surveyor",
        "-",
        "valuer"
    ],
    "wof:name":"Rodex Sprl",
    "wof:placetype":"venue"
},
  "geometry": {"coordinates":[4.1726551056,50.6092453003],"type":"Point"}
}