{
  "type": "Feature",
  "properties": {
    "addr:full":"Ambachtenlaan 7 Moorsele West-Vlaanderen 8560",
    "addr:housenumber":"7",
    "addr:postcode":"8560",
    "addr:street":"Ambachtenlaan",
    "iso:country":"BE",
    "sg:address":"Ambachtenlaan 7",
    "sg:city":"Moorsele",
    "sg:orig_category":"Lattice Masts",
    "sg:phone":"+32 2 251 25 85",
    "sg:postcode":"8560",
    "sg:province":"West-Vlaanderen",
    "wof:name":"La Construction Soud\u00e9e Nv",
    "wof:placetype":"venue"
},
  "geometry": {"coordinates":[4.4250388145,50.9034881592],"type":"Point"}
}