{
  "type": "Feature",
  "properties": {
    "iso:country":"BE",
    "sg:address":"Fietelstraat 112",
    "sg:city":"Oudenaarde",
    "sg:classifiers":[
        {
            "category":"Health Services",
            "subcategory":"Doctor",
            "type":"Services"
        }
    ],
    "sg:phone":"+32 55 31 21 82",
    "sg:postcode":"9700",
    "sg:province":"Oost-Vlaanderen",
    "sg:tags":[
        "medicinephysicians",
        "surgeon"
    ],
    "wof:name":"Decanni\u00e8re O",
    "wof:placetype":"venue"
},
  "geometry": {"coordinates":[3.6163098812,50.8706817627],"type":"Point"}
}