{
  "type": "Feature",
  "properties": {
    "iso:country":"BE",
    "sg:address":"Rue Des Wallons 8",
    "sg:city":"Louvain",
    "sg:orig_category":"Dameskledingzaken Herenkledingzaken",
    "sg:phone":"+32 10 45 26 26",
    "sg:postcode":"1348",
    "sg:province":"Brabant Wallon",
    "wof:name":"Harvard's",
    "wof:placetype":"venue"
},
  "geometry": {"coordinates":[4.6156468391,50.669303894],"type":"Point"}
}