{
  "type": "Feature",
  "properties": {
    "addr:full":"Klosterstrasse 29 Eupen/eupen Li\u00e8ge 4700",
    "addr:housenumber":"29",
    "addr:postcode":"4700",
    "addr:street":"Klosterstrasse",
    "iso:country":"BE",
    "sg:address":"Klosterstrasse 29",
    "sg:city":"Eupen/eupen",
    "sg:orig_category":"Bagage and lederwaren",
    "sg:phone":"+32 87 74 27 09",
    "sg:postcode":"4700",
    "sg:province":"Li\u00e8ge",
    "wof:name":"Lederwaren D.",
    "wof:placetype":"venue"
},
  "geometry": {"coordinates":[6.0312480927,50.6310997009],"type":"Point"}
}