{
  "type": "Feature",
  "properties": {
    "iso:country":"BE",
    "sg:address":"Kapelstraat 9",
    "sg:city":"Antwerpen",
    "sg:orig_category":"Agences immobili\u00e8res",
    "sg:phone":"+32 3 825 16 32",
    "sg:postcode":"2660",
    "sg:province":"Antwerpen",
    "wof:name":"Amber Vastgoed",
    "wof:placetype":"venue"
},
  "geometry": {"coordinates":[4.3272171021,51.350730896],"type":"Point"}
}