{
  "type": "Feature",
  "properties": {
    "iso:country":"BE",
    "sg:address":"Lindestraat 15",
    "sg:city":"Laakdal (forest)",
    "sg:classifiers":[
        {
            "category":"Arena",
            "subcategory":"Sports Club",
            "type":"Entertainment"
        }
    ],
    "sg:phone":"+32 13 66 66 82",
    "sg:postcode":"2430",
    "sg:province":"Antwerpen",
    "wof:name":"Tennisclub Laakdal",
    "wof:placetype":"venue"
},
  "geometry": {"coordinates":[5.0561499596,51.0798988342],"type":"Point"}
}