{
  "type": "Feature",
  "properties": {
    "iso:country":"BE",
    "sg:address":"Rue Albert De Cuyck 30",
    "sg:city":"Li\u00c8ge",
    "sg:orig_category":"Artsen and specialisten",
    "sg:phone":"+32 4 253 08 01",
    "sg:postcode":"4000",
    "sg:province":"Li\u00e8ge",
    "wof:name":"Ga\u00cbtan Garraux",
    "wof:placetype":"venue"
},
  "geometry": {"coordinates":[5.571308136,50.6249961853],"type":"Point"}
}