{
  "type": "Feature",
  "properties": {
    "addr:full":"Heuvelstraat 36a Hemiksem Antwerpen 2620",
    "addr:housenumber":"36a",
    "addr:postcode":"2620",
    "addr:street":"Heuvelstraat",
    "iso:country":"BE",
    "sg:address":"Heuvelstraat 36a",
    "sg:city":"Hemiksem",
    "sg:orig_category":"Agences immobili\u00e8res",
    "sg:phone":"+32 3 877 07 50",
    "sg:postcode":"2620",
    "sg:province":"Antwerpen",
    "wof:name":"Bureau Konfidens",
    "wof:placetype":"venue"
},
  "geometry": {"coordinates":[4.337621212,51.1406059265],"type":"Point"}
}