{
  "type": "Feature",
  "properties": {
    "addr:full":"Vlamingstraat 53 Brugge West-Vlaanderen 8000",
    "addr:housenumber":"53",
    "addr:postcode":"8000",
    "addr:street":"Vlamingstraat",
    "iso:country":"BE",
    "sg:address":"Vlamingstraat 53",
    "sg:city":"Brugge",
    "sg:orig_category":"Catering and organisatie van feesten Fast food and meeneem restaurants Levering aan huis restaurants",
    "sg:phone":"+32 50 34 61 78",
    "sg:postcode":"8000",
    "sg:province":"West-Vlaanderen",
    "wof:name":"\u00b4t Heerenhuys",
    "wof:placetype":"venue"
},
  "geometry": {"coordinates":[3.2233510017,51.2118034363],"type":"Point"}
}