{
  "type": "Feature",
  "properties": {
    "iso:country":"BE",
    "sg:address":"Rue Des Alli\u00e9s 7a",
    "sg:city":"Gr\u00e2ce-hollogne (gr\u00e2ce-berleur)",
    "sg:classifiers":[
        {
            "category":"Building & Trades",
            "subcategory":"Construction",
            "type":"Services"
        }
    ],
    "sg:phone":"+32 4 247 32 10",
    "sg:postcode":"4460",
    "sg:province":"Li\u00e8ge",
    "sg:tags":[
        "glazier"
    ],
    "wof:name":"Haudestaine H",
    "wof:placetype":"venue"
},
  "geometry": {"coordinates":[5.5043120384,50.6449737549],"type":"Point"}
}