{
  "type": "Feature",
  "properties": {
    "addr:full":"Chauss\u00e9e De Namur 57 Nivelles Brabant Wallon 1400",
    "addr:housenumber":"57",
    "addr:postcode":"1400",
    "addr:street":"Chausse\u0301E De Namur",
    "iso:country":"BE",
    "sg:address":"Chauss\u00e9e De Namur 57",
    "sg:city":"Nivelles",
    "sg:classifiers":[
        {
            "category":"Food & Beverages",
            "subcategory":"Groceries & Convenience Stores",
            "type":"Retail Goods"
        }
    ],
    "sg:phone":"+32 67 84 13 03",
    "sg:postcode":"1400",
    "sg:province":"Brabant Wallon",
    "sg:tags":[
        "disposable"
    ],
    "wof:name":"Sabert Corporation Sa",
    "wof:placetype":"venue"
},
  "geometry": {"coordinates":[4.3543272018,50.5984458923],"type":"Point"}
}