{
  "type": "Feature",
  "properties": {
    "addr:full":"Edingsesteenweg 304 Gooik (kester) Vlaams-Brabant 1755",
    "addr:housenumber":"304;1755",
    "addr:street":"Edingsesteenweg",
    "iso:country":"BE",
    "sg:address":"Edingsesteenweg 304",
    "sg:city":"Gooik (kester)",
    "sg:orig_category":"Non-Classified Establishments",
    "sg:phone":"+32 54 56 79 71",
    "sg:postcode":"1755",
    "sg:province":"Vlaams-Brabant",
    "wof:name":"All-sales",
    "wof:placetype":"venue"
},
  "geometry": {"coordinates":[4.1230998039,50.7871284485],"type":"Point"}
}