{
  "type": "Feature",
  "properties": {
    "iso:country":"BE",
    "sg:address":"Heerbaan 84",
    "sg:city":"Londerzeel (steenhuffel)",
    "sg:classifiers":[
        {
            "category":"Home & Garden",
            "subcategory":"Kitchen Supply",
            "type":"Retail Goods"
        }
    ],
    "sg:phone":"+32 52 30 03 90",
    "sg:postcode":"1840",
    "sg:province":"Vlaams-Brabant",
    "sg:tags":[
        "installation"
    ],
    "wof:name":"Meskens",
    "wof:placetype":"venue"
},
  "geometry": {"coordinates":[4.2605891228,50.9854049683],"type":"Point"}
}