{
  "type": "Feature",
  "properties": {
    "iso:country":"BE",
    "sg:address":"Place 19",
    "sg:city":"Tournai",
    "sg:classifiers":[
        {
            "category":"Shopping",
            "type":"Retail Goods"
        }
    ],
    "sg:phone":"+32 69 84 11 22",
    "sg:postcode":"7500",
    "sg:province":"Hainaut",
    "sg:tags":[
        "product",
        "cleaning",
        "maintenance"
    ],
    "wof:name":"Bertrand L",
    "wof:placetype":"venue"
},
  "geometry": {"coordinates":[3.3853929043,50.6065940857],"type":"Point"}
}