{
  "type": "Feature",
  "properties": {
    "addr:full":"Dorpsplein 6 Melle Oost-Vlaanderen 9090",
    "addr:housenumber":"6",
    "addr:postcode":"9090",
    "addr:street":"Dorpsplein",
    "iso:country":"BE",
    "sg:address":"Dorpsplein 6",
    "sg:city":"Melle",
    "sg:orig_category":"Equipement photographique. Studios photographiques",
    "sg:phone":"+32 9 252 52 41",
    "sg:postcode":"9090",
    "sg:province":"Oost-Vlaanderen",
    "wof:name":"Studio Klik-klak",
    "wof:placetype":"venue"
},
  "geometry": {"coordinates":[3.8025920391,51.0038452148],"type":"Point"}
}