{
  "type": "Feature",
  "properties": {
    "addr:full":"Kuipstraat 10 Evergem Oost-Vlaanderen 9940",
    "addr:housenumber":"10",
    "addr:postcode":"9940",
    "addr:street":"Kuipstraat;Oost-Vlaanderen",
    "iso:country":"BE",
    "sg:address":"Kuipstraat 10",
    "sg:city":"Evergem",
    "sg:orig_category":"Eleveurs and marchands de porcs",
    "sg:phone":"+32 9 344 54 30",
    "sg:postcode":"9940",
    "sg:province":"Oost-Vlaanderen",
    "wof:name":"Robert De Baets",
    "wof:placetype":"venue"
},
  "geometry": {"coordinates":[3.7425689697,51.1754722595],"type":"Point"}
}