{
  "type": "Feature",
  "properties": {
    "addr:full":"Ringlaan 82 Koekelare West-Vlaanderen 8680",
    "addr:housenumber":"82",
    "addr:postcode":"8680",
    "addr:street":"Ringlaan",
    "iso:country":"BE",
    "sg:address":"Ringlaan 82",
    "sg:city":"Koekelare",
    "sg:orig_category":"Kapsalons",
    "sg:phone":"+32 51 58 27 52",
    "sg:postcode":"8680",
    "sg:province":"West-Vlaanderen",
    "wof:name":"Coiffure Renate",
    "wof:placetype":"venue"
},
  "geometry": {"coordinates":[2.9691240788,51.0906486511],"type":"Point"}
}