{
  "type": "Feature",
  "properties": {
    "addr:full":"Weverijstraat 121 Geraardsbergen Oost-Vlaanderen 9500",
    "addr:housenumber":"121",
    "addr:postcode":"9500",
    "addr:street":"Weverijstraat",
    "iso:country":"BE",
    "sg:address":"Weverijstraat 121",
    "sg:city":"Geraardsbergen",
    "sg:classifiers":[
        {
            "category":"Retail",
            "subcategory":"Auto Repair",
            "type":"Services"
        }
    ],
    "sg:phone":"+32 54 59 69 69",
    "sg:postcode":"9500",
    "sg:province":"Oost-Vlaanderen",
    "sg:tags":[
        "garage"
    ],
    "wof:name":"Delhoux P",
    "wof:placetype":"venue"
},
  "geometry": {"coordinates":[3.8822090626,50.776550293],"type":"Point"}
}