{
  "type": "Feature",
  "properties": {
    "addr:full":"Schippersstraat 14 Roeselare West-Vlaanderen 8800",
    "addr:housenumber":"14",
    "addr:postcode":"8800",
    "addr:street":"Schippersstraat",
    "iso:country":"BE",
    "sg:address":"Schippersstraat 14",
    "sg:city":"Roeselare",
    "sg:classifiers":[
        {
            "category":"Freight",
            "type":"Transportation"
        }
    ],
    "sg:phone":"+32 475 83 32 57",
    "sg:postcode":"8800",
    "sg:province":"West-Vlaanderen",
    "sg:tags":[
        "-",
        "transport"
    ],
    "wof:name":"Van Eeckhoutte Bart Bvba",
    "wof:placetype":"venue"
},
  "geometry": {"coordinates":[3.1445600986,50.9405784607],"type":"Point"}
}