{
  "type": "Feature",
  "properties": {
    "addr:full":"Rue Dupr\u00e9 11 Bruxelles (jette) Bruxelles-Capitale 1090",
    "addr:housenumber":"11",
    "addr:postcode":"1090",
    "addr:street":"Rue Dupre\u0301",
    "iso:country":"BE",
    "sg:address":"Rue Dupr\u00e9 11",
    "sg:city":"Bruxelles (jette)",
    "sg:classifiers":[
        {
            "category":"Real Estate",
            "subcategory":"Architect",
            "type":"Services"
        }
    ],
    "sg:phone":"+32 2 478 05 90",
    "sg:postcode":"1090",
    "sg:province":"Bruxelles-Capitale",
    "wof:name":"Genon Ph",
    "wof:placetype":"venue"
},
  "geometry": {"coordinates":[4.3227601051,50.8808898926],"type":"Point"}
}