{
  "type": "Feature",
  "properties": {
    "iso:country":"BE",
    "sg:address":"Pastoor Verwilghenplein 13",
    "sg:city":"Beveren",
    "sg:orig_category":"Brood, gebak and snoepgoed",
    "sg:phone":"+32 3 775 74 63",
    "sg:postcode":"9120",
    "sg:province":"Oost-Vlaanderen",
    "wof:name":"Baumans",
    "wof:placetype":"venue"
},
  "geometry": {"coordinates":[4.2387619019,51.181602478],"type":"Point"}
}