{
  "type": "Feature",
  "properties": {
    "addr:full":"Lichtelarestraat 49 Lochristi Oost-Vlaanderen 9080",
    "addr:housenumber":"49",
    "addr:postcode":"9080",
    "addr:street":"Lichtelarestraat",
    "iso:country":"BE",
    "sg:address":"Lichtelarestraat 49",
    "sg:city":"Lochristi",
    "sg:orig_category":"Rev\u00eatements pour sols and murs. Construction industrielle and commerciale. Construction de rev\u00eatemen",
    "sg:phone":"+32 9 356 61 05",
    "sg:postcode":"9080",
    "sg:province":"Oost-Vlaanderen",
    "wof:name":"Van Avermaet Frankie",
    "wof:placetype":"venue"
},
  "geometry": {"coordinates":[3.8174920082,51.0859069824],"type":"Point"}
}