{
  "type": "Feature",
  "properties": {
    "addr:full":"Donkerstraat 14 Zulte Oost-Vlaanderen 9870",
    "addr:housenumber":"14",
    "addr:postcode":"9870",
    "addr:street":"Donkerstraat",
    "iso:country":"BE",
    "sg:address":"Donkerstraat 14",
    "sg:city":"Zulte",
    "sg:orig_category":"Sportclubs",
    "sg:phone":"+32 9 386 02 96",
    "sg:postcode":"9870",
    "sg:province":"Oost-Vlaanderen",
    "wof:name":"De Dappere Vlucht",
    "wof:placetype":"venue"
},
  "geometry": {"coordinates":[3.492620945,50.9646224976],"type":"Point"}
}