{
  "type": "Feature",
  "properties": {
    "addr:full":"Rue Van Bortonne 102 Jette Bruxelles-Capitale 1090",
    "addr:housenumber":"102",
    "addr:postcode":"1090",
    "addr:street":"Rue Van Bortonne",
    "iso:country":"BE",
    "sg:address":"Rue Van Bortonne 102",
    "sg:city":"Jette",
    "sg:orig_category":"Assistances juridiques. Conseillers fiscaux",
    "sg:phone":"+32 2 424 29 16",
    "sg:postcode":"1090",
    "sg:province":"Bruxelles-Capitale",
    "wof:name":"Zanzala Ungomba",
    "wof:placetype":"venue"
},
  "geometry": {"coordinates":[4.3267560005,50.8772544861],"type":"Point"}
}