{
  "type": "Feature",
  "properties": {
    "addr:full":"Place Communale 128 Hastiere Namur 5543",
    "addr:postcode":"5543",
    "addr:street":"Place Communale 128 Hastiere",
    "iso:country":"BE",
    "sg:address":"Place Communale 128",
    "sg:city":"Hastiere",
    "sg:orig_category":"Epiceries",
    "sg:phone":"+32 82 64 44 84",
    "sg:postcode":"5543",
    "sg:province":"Namur",
    "wof:name":"Philippe Duplat",
    "wof:placetype":"venue"
},
  "geometry": {"coordinates":[4.8313798904,50.1622581482],"type":"Point"}
}