{
  "type": "Feature",
  "properties": {
    "iso:country":"BE",
    "sg:address":"Statiestraat 117",
    "sg:city":"Zulte",
    "sg:orig_category":"Verplichte sociale verzekeringen",
    "sg:phone":"+32 9 388 87 08",
    "sg:postcode":"9870",
    "sg:province":"Oost-Vlaanderen",
    "wof:name":"Christelijke Mutualiteit",
    "wof:placetype":"venue"
},
  "geometry": {"coordinates":[3.4463620186,50.9157943726],"type":"Point"}
}