{
  "type": "Feature",
  "properties": {
    "iso:country":"BE",
    "sg:address":"Avenue Des Alli\u00c9s 42",
    "sg:city":"Charleroi",
    "sg:orig_category":"Assistances juridiques. Conseillers fiscaux",
    "sg:phone":"+32 71 33 15 35",
    "sg:postcode":"6000",
    "sg:province":"Hainaut",
    "wof:name":"Fiduciaire Cofigest",
    "wof:placetype":"venue"
},
  "geometry": {"coordinates":[4.438243866,50.411365509],"type":"Point"}
}