{
  "type": "Feature",
  "properties": {
    "iso:country":"BE",
    "sg:address":"Stationsstraat 30",
    "sg:city":"Oudenburg",
    "sg:orig_category":"Non-Classified Establishments",
    "sg:postcode":"8460",
    "sg:province":"West-Vlaanderen",
    "wof:name":"Anra",
    "wof:placetype":"venue"
},
  "geometry": {"coordinates":[3.0062589645,51.1969146729],"type":"Point"}
}