{
  "type": "Feature",
  "properties": {
    "iso:country":"BE",
    "sg:address":"Koning Leopold I-straat 8 Box 2",
    "sg:city":"Kortrijk",
    "sg:classifiers":[
        {
            "category":"Professional",
            "subcategory":"Lawyer & Legal Services",
            "type":"Services"
        }
    ],
    "sg:phone":"+32 56 25 90 50",
    "sg:postcode":"8500",
    "sg:province":"West-Vlaanderen",
    "wof:name":"Verschuere Arne",
    "wof:placetype":"venue"
},
  "geometry": {"coordinates":[3.2603271008,50.8273391724],"type":"Point"}
}