{
  "type": "Feature",
  "properties": {
    "addr:full":"Stoomtuigstraat 10 Hooglede (gits) West-Vlaanderen 8830",
    "addr:housenumber":"10",
    "addr:postcode":"8830",
    "addr:street":"Stoomtuigstraat",
    "iso:country":"BE",
    "sg:address":"Stoomtuigstraat 10",
    "sg:city":"Hooglede (gits)",
    "sg:classifiers":[
        {
            "category":"Home & Garden",
            "subcategory":"Kitchen Supply",
            "type":"Retail Goods"
        }
    ],
    "sg:phone":"+32 51 20 35 33",
    "sg:postcode":"8830",
    "sg:province":"West-Vlaanderen",
    "sg:tags":[
        "installation"
    ],
    "wof:name":"Verstraete Interieur Nv",
    "wof:placetype":"venue"
},
  "geometry": {"coordinates":[3.1206130981,50.9834976196],"type":"Point"}
}