{
  "type": "Feature",
  "properties": {
    "addr:full":"Borsbeeksesteenweg 64 Boechout Antwerpen 2530",
    "addr:housenumber":"64",
    "addr:postcode":"2530",
    "addr:street":"Borsbeeksesteenweg",
    "iso:country":"BE",
    "sg:address":"Borsbeeksesteenweg 64",
    "sg:city":"Boechout",
    "sg:orig_category":"Winkelinrichting and handelsuitrusting Gh",
    "sg:phone":"+32 3 455 69 95",
    "sg:postcode":"2530",
    "sg:province":"Antwerpen",
    "wof:name":"Euro-games",
    "wof:placetype":"venue"
},
  "geometry": {"coordinates":[4.4909858704,51.172000885],"type":"Point"}
}