{
  "type": "Feature",
  "properties": {
    "iso:country":"BE",
    "sg:address":"\u00b4s Gravenstraat 214",
    "sg:city":"Nazareth",
    "sg:classifiers":[
        {
            "category":"Insurance",
            "subcategory":"Insurance Agent",
            "type":"Services"
        }
    ],
    "sg:phone":"+32 9 384 27 25",
    "sg:postcode":"9810",
    "sg:province":"Oost-Vlaanderen",
    "sg:tags":[
        "verzekeringsmakelaars",
        "expert"
    ],
    "wof:name":"Le Clercq-verhaeghe",
    "wof:placetype":"venue"
},
  "geometry": {"coordinates":[3.5912890434,50.9466667175],"type":"Point"}
}