{
  "type": "Feature",
  "properties": {
    "iso:country":"BE",
    "sg:address":"Itterbeeksebaan 258",
    "sg:city":"Dilbeek",
    "sg:orig_category":"Kapsalons",
    "sg:phone":"+32 2 569 00 20",
    "sg:postcode":"1701",
    "sg:province":"Vlaams-Brabant",
    "wof:name":"Coiffure Margriet",
    "wof:placetype":"venue"
},
  "geometry": {"coordinates":[4.2444210052,50.8400497437],"type":"Point"}
}