{
  "type": "Feature",
  "properties": {
    "addr:full":"Chauss\u00e9e De Wavre 305 Grez-doiceau Brabant Wallon 1390",
    "addr:housenumber":"305",
    "addr:postcode":"1390",
    "addr:street":"Chausse\u0301E De Wavre",
    "iso:country":"BE",
    "sg:address":"Chauss\u00e9e De Wavre 305",
    "sg:city":"Grez-doiceau",
    "sg:classifiers":[
        {
            "category":"Home & Garden",
            "subcategory":"Garden Supply",
            "type":"Retail Goods"
        }
    ],
    "sg:phone":"+32 10 84 05 53",
    "sg:postcode":"1390",
    "sg:province":"Brabant Wallon",
    "wof:name":"Central Jardin",
    "wof:placetype":"venue"
},
  "geometry": {"coordinates":[4.6621599197,50.7378540039],"type":"Point"}
}