{
  "type": "Feature",
  "properties": {
    "iso:country":"BE",
    "sg:address":"Ilgatlaan 9",
    "sg:city":"Hasselt",
    "sg:classifiers":[
        {
            "category":"Professional",
            "subcategory":"Engineering",
            "type":"Services"
        }
    ],
    "sg:phone":"+32 11 28 88 00",
    "sg:postcode":"3500",
    "sg:province":"Limburg",
    "sg:tags":[
        "-"
    ],
    "wof:name":"Gedas",
    "wof:placetype":"venue"
},
  "geometry": {"coordinates":[5.3541030884,50.9223098755],"type":"Point"}
}