{
  "type": "Feature",
  "properties": {
    "addr:full":"Rue Du Beau Site 17-19 Bruxelles Bruxelles-Capitale 1000",
    "addr:housenumber":"17-19",
    "addr:postcode":"1000",
    "addr:street":"Rue Du Beau Site",
    "iso:country":"BE",
    "sg:address":"Rue Du Beau Site 17-19",
    "sg:city":"Bruxelles",
    "sg:orig_category":"Non-Classified Establishments",
    "sg:phone":"+32 2 512 48 51",
    "sg:postcode":"1000",
    "sg:province":"Bruxelles-Capitale",
    "wof:name":"High Society",
    "wof:placetype":"venue"
},
  "geometry": {"coordinates":[4.3637909889,50.8294944763],"type":"Point"}
}