{
  "type": "Feature",
  "properties": {
    "addr:full":"Boomse Steenweg 346 Antwerpen Antwerpen 2020",
    "addr:housenumber":"346",
    "addr:postcode":"2020",
    "addr:street":"Steenweg",
    "iso:country":"BE",
    "sg:address":"Boomse Steenweg 346",
    "sg:city":"Antwerpen",
    "sg:classifiers":[
        {
            "category":"Health Services",
            "subcategory":"Health Practitioner",
            "type":"Services"
        }
    ],
    "sg:phone":"+32 3 216 30 55",
    "sg:postcode":"2020",
    "sg:province":"Antwerpen",
    "sg:tags":[
        "physiotherapist"
    ],
    "wof:name":"Thielemans Peter",
    "wof:placetype":"venue"
},
  "geometry": {"coordinates":[4.3875007629,51.1876029968],"type":"Point"}
}