{
  "type": "Feature",
  "properties": {
    "iso:country":"BE",
    "sg:address":"Rue De La Moinerie 11",
    "sg:city":"Verviers",
    "sg:orig_category":"Fleurs and plantes",
    "sg:phone":"+32 87 33 24 76",
    "sg:postcode":"4800",
    "sg:province":"Li\u00e8ge",
    "wof:name":"La Fleur Au Coeur",
    "wof:placetype":"venue"
},
  "geometry": {"coordinates":[5.8583259583,50.5889816284],"type":"Point"}
}