{
  "type": "Feature",
  "properties": {
    "iso:country":"BE",
    "sg:address":"Rue De Cond\u00e9 6",
    "sg:city":"Leuze-en-hainaut",
    "sg:classifiers":[
        {
            "category":"Insurance",
            "subcategory":"Insurance Agent",
            "type":"Services"
        }
    ],
    "sg:phone":"+32 69 67 21 70",
    "sg:postcode":"7900",
    "sg:province":"Hainaut",
    "sg:tags":[
        "broker"
    ],
    "wof:name":"Wantrappe-vandeburie & Chenut",
    "wof:placetype":"venue"
},
  "geometry": {"coordinates":[3.6182770729,50.5976867676],"type":"Point"}
}