{
  "type": "Feature",
  "properties": {
    "addr:full":"Lauwershoek 42 Temse Oost-Vlaanderen 9140",
    "addr:housenumber":"42",
    "addr:postcode":"9140",
    "addr:street":"Lauwershoek",
    "iso:country":"BE",
    "sg:address":"Lauwershoek 42",
    "sg:city":"Temse",
    "sg:orig_category":"Dranken Dranken Gh",
    "sg:phone":"+32 3 771 04 65",
    "sg:postcode":"9140",
    "sg:province":"Oost-Vlaanderen",
    "wof:name":"Bierhof",
    "wof:placetype":"venue"
},
  "geometry": {"coordinates":[4.2406730652,51.1417884827],"type":"Point"}
}