{
  "type": "Feature",
  "properties": {
    "iso:country":"BE",
    "sg:address":"Rue Ernest Solvay 29a",
    "sg:city":"Li\u00e8ge 1",
    "sg:classifiers":[
        {
            "category":"Utilities",
            "subcategory":"Telephone",
            "type":"Services"
        }
    ],
    "sg:phone":"+32 4 253 00 59",
    "sg:postcode":"4000",
    "sg:province":"Li\u00e8ge",
    "sg:tags":[
        "-",
        "internet"
    ],
    "wof:name":"Virgo Plus",
    "wof:placetype":"venue"
},
  "geometry": {"coordinates":[5.5716900826,50.6123542786],"type":"Point"}
}