{
  "type": "Feature",
  "properties": {
    "iso:country":"BE",
    "sg:address":"Rue De La Croisette 74",
    "sg:city":"Courcelles",
    "sg:classifiers":[
        {
            "category":"Building & Trades",
            "subcategory":"Landscaping Services",
            "type":"Services"
        }
    ],
    "sg:phone":"+32 71 45 34 42",
    "sg:postcode":"6180",
    "sg:province":"Hainaut",
    "sg:tags":[
        "nurseryman"
    ],
    "wof:name":"Bellini Entreprise",
    "wof:placetype":"venue"
},
  "geometry": {"coordinates":[4.3392882347,50.4563217163],"type":"Point"}
}