{
  "type": "Feature",
  "properties": {
    "iso:country":"BE",
    "sg:address":"Rue L\u00e9on Delhache 9",
    "sg:city":"Ramillies (ramillies-offus)",
    "sg:classifiers":[
        {
            "category":"Communications",
            "subcategory":"Film & Video Production",
            "type":"Services"
        }
    ],
    "sg:phone":"+32 81 87 92 77",
    "sg:postcode":"1367",
    "sg:province":"Brabant Wallon",
    "sg:tags":[
        "multimedia",
        "-",
        "system"
    ],
    "wof:name":"Image'up Sprl",
    "wof:placetype":"venue"
},
  "geometry": {"coordinates":[4.9100079536,50.6520004272],"type":"Point"}
}