{
  "type": "Feature",
  "properties": {
    "addr:full":"Voskenslaan 140 Sint-niklaas Oost-Vlaanderen 9100",
    "addr:housenumber":"140",
    "addr:postcode":"9100",
    "addr:street":"Voskenslaan",
    "iso:country":"BE",
    "sg:address":"Voskenslaan 140",
    "sg:city":"Sint-niklaas",
    "sg:orig_category":"Avocats and conseillers juridiques",
    "sg:phone":"+32 3 766 36 02",
    "sg:postcode":"9100",
    "sg:province":"Oost-Vlaanderen",
    "wof:name":"Herman Bogaerts",
    "wof:placetype":"venue"
},
  "geometry": {"coordinates":[4.1594090462,51.1545372009],"type":"Point"}
}