{
  "type": "Feature",
  "properties": {
    "addr:full":"Rue Du Saiwet 13 Jemeppe-sur-sambre Namur 5190",
    "addr:housenumber":"13",
    "addr:postcode":"5190",
    "addr:street":"Rue Du Saiwet",
    "iso:country":"BE",
    "sg:address":"Rue Du Saiwet 13",
    "sg:city":"Jemeppe-sur-sambre",
    "sg:classifiers":[
        {
            "category":"Health Services",
            "subcategory":"Health Practitioner",
            "type":"Services"
        }
    ],
    "sg:phone":"+32 71 78 61 27",
    "sg:postcode":"5190",
    "sg:province":"Namur",
    "sg:tags":[
        "physiotherapist"
    ],
    "wof:name":"Rouffiange W",
    "wof:placetype":"venue"
},
  "geometry": {"coordinates":[4.6489801407,50.4761810303],"type":"Point"}
}