{
  "type": "Feature",
  "properties": {
    "addr:full":"Place 46 Bi\u00e9v\u00e8ne Vlaams-Brabant 1547",
    "addr:housenumber":"46",
    "addr:postcode":"1547",
    "iso:country":"BE",
    "sg:address":"Place 46",
    "sg:city":"Bi\u00e9v\u00e8ne",
    "sg:classifiers":[
        {
            "category":"Home & Garden",
            "subcategory":"Building Materials",
            "type":"Retail Goods"
        }
    ],
    "sg:phone":"+32 54 58 68 23",
    "sg:postcode":"1547",
    "sg:province":"Vlaams-Brabant",
    "sg:tags":[
        "-",
        "fireplace",
        "open",
        "ornamental"
    ],
    "wof:name":"Connemara Interiors Bvba",
    "wof:placetype":"venue"
},
  "geometry": {"coordinates":[3.9395349026,50.7164573669],"type":"Point"}
}