{
  "type": "Feature",
  "properties": {
    "iso:country":"BE",
    "sg:address":"Rue Des Croisiers 38",
    "sg:city":"Li\u00c8ge",
    "sg:orig_category":"Cr\u00e9dits divers",
    "sg:postcode":"4000",
    "sg:province":"Li\u00e8ge",
    "wof:name":"Bancontact-mister Cash",
    "wof:placetype":"venue"
},
  "geometry": {"coordinates":[5.5740938187,50.6387939453],"type":"Point"}
}