{
  "type": "Feature",
  "properties": {
    "iso:country":"BE",
    "sg:address":"Mechelsesteenweg 16",
    "sg:city":"Heist-op-den-berg",
    "sg:classifiers":[
        {
            "category":"Retail",
            "subcategory":"Car Wash",
            "type":"Services"
        }
    ],
    "sg:phone":"+32 15 24 31 82",
    "sg:postcode":"2220",
    "sg:province":"Antwerpen",
    "sg:tags":[
        "automobile",
        "washing",
        "-",
        "truck"
    ],
    "wof:name":"Eurostar",
    "wof:placetype":"venue"
},
  "geometry": {"coordinates":[4.7051110268,51.0731582642],"type":"Point"}
}