{
  "type": "Feature",
  "properties": {
    "addr:full":"Sint-janstraat 28 Wevelgem West-Vlaanderen 8560",
    "addr:housenumber":"28",
    "addr:postcode":"8560",
    "addr:street":"Sint-Janstraat",
    "iso:country":"BE",
    "sg:address":"Sint-janstraat 28",
    "sg:city":"Wevelgem",
    "sg:orig_category":"Kapsalons",
    "sg:phone":"+32 56 41 89 85",
    "sg:postcode":"8560",
    "sg:province":"West-Vlaanderen",
    "wof:name":"Jean-pierre Baeyens",
    "wof:placetype":"venue"
},
  "geometry": {"coordinates":[3.1644999981,50.8390197754],"type":"Point"}
}