{
  "type": "Feature",
  "properties": {
    "addr:full":"Hendrik I Lei 128 Vilvoorde Vlaams-Brabant 1800",
    "addr:housenumber":"128",
    "addr:postcode":"1800",
    "addr:street":"Hendrik I Lei",
    "iso:country":"BE",
    "sg:address":"Hendrik I Lei 128",
    "sg:city":"Vilvoorde",
    "sg:classifiers":[
        {
            "category":"Building & Trades",
            "subcategory":"Construction",
            "type":"Services"
        }
    ],
    "sg:phone":"+32 2 253 25 75",
    "sg:postcode":"1800",
    "sg:province":"Vlaams-Brabant",
    "sg:tags":[
        "installation",
        "-",
        "central",
        "heating"
    ],
    "wof:name":"E H S Bvba",
    "wof:placetype":"venue"
},
  "geometry": {"coordinates":[4.4311752319,50.9340286255],"type":"Point"}
}