{
  "type": "Feature",
  "properties": {
    "addr:full":"Lammerendries 5 Oudergem/auderghem Bruxelles-Capitale 1160",
    "addr:housenumber":"5",
    "addr:postcode":"1160",
    "addr:street":"Lammerendries;/",
    "iso:country":"BE",
    "sg:address":"Lammerendries 5",
    "sg:city":"Oudergem/auderghem",
    "sg:orig_category":"Slagers",
    "sg:phone":"+32 2 672 03 53",
    "sg:postcode":"1160",
    "sg:province":"Bruxelles-Capitale",
    "wof:name":"Boucherie Sterck",
    "wof:placetype":"venue"
},
  "geometry": {"coordinates":[4.4225711823,50.8111839294],"type":"Point"}
}