{
  "type": "Feature",
  "properties": {
    "addr:full":"Leuvensesteenweg 98 Tervuren Vlaams-Brabant 3080",
    "addr:housenumber":"98",
    "addr:postcode":"3080",
    "addr:street":"Leuvensesteenweg",
    "iso:country":"BE",
    "sg:address":"Leuvensesteenweg 98",
    "sg:city":"Tervuren",
    "sg:classifiers":[
        {
            "category":"Building & Trades",
            "subcategory":"Construction",
            "type":"Services"
        }
    ],
    "sg:phone":"+32 2 767 64 80",
    "sg:postcode":"3080",
    "sg:province":"Vlaams-Brabant",
    "sg:tags":[
        "glazier"
    ],
    "wof:name":"Reniers Glasbedrijf",
    "wof:placetype":"venue"
},
  "geometry": {"coordinates":[4.537498951,50.8366508484],"type":"Point"}
}