{
  "type": "Feature",
  "properties": {
    "iso:country":"BE",
    "sg:address":"De Heuvel 5",
    "sg:city":"Genk",
    "sg:classifiers":[
        {
            "category":"Health Services",
            "subcategory":"Dentist",
            "type":"Services"
        }
    ],
    "sg:phone":"+32 89 35 57 64",
    "sg:postcode":"3600",
    "sg:province":"Limburg",
    "wof:name":"Nijs Nadine",
    "wof:placetype":"venue"
},
  "geometry": {"coordinates":[5.4549460411,50.9733276367],"type":"Point"}
}