{
  "type": "Feature",
  "properties": {
    "addr:full":"Rue Emile Deroover 21 Bruxelles (koekelberg) Bruxelles-Capitale 1081",
    "addr:housenumber":"21",
    "addr:postcode":"1081",
    "addr:street":"Rue Emile Deroover",
    "iso:country":"BE",
    "sg:address":"Rue Emile Deroover 21",
    "sg:city":"Bruxelles (koekelberg)",
    "sg:classifiers":[
        {
            "category":"Professional",
            "subcategory":"Engineering",
            "type":"Services"
        }
    ],
    "sg:phone":"+32 2 414 54 62",
    "sg:postcode":"1081",
    "sg:province":"Bruxelles-Capitale",
    "sg:tags":[
        "-"
    ],
    "wof:name":"Serfoco Sa",
    "wof:placetype":"venue"
},
  "geometry": {"coordinates":[4.3146557808,50.8649368286],"type":"Point"}
}