{
  "type": "Feature",
  "properties": {
    "addr:full":"Rue De Spa 171 Stavelot (francorchamps) Li\u00e8ge 4970",
    "addr:housenumber":"171",
    "addr:postcode":"4970",
    "addr:street":"Rue De Spa",
    "iso:country":"BE",
    "sg:address":"Rue De Spa 171",
    "sg:city":"Stavelot (francorchamps)",
    "sg:classifiers":[
        {
            "category":"Professional",
            "subcategory":"Secretarial Services",
            "type":"Services"
        }
    ],
    "sg:phone":"+32 87 27 51 63",
    "sg:postcode":"4970",
    "sg:province":"Li\u00e8ge",
    "sg:tags":[
        "firm"
    ],
    "wof:name":"Merckaert A-c",
    "wof:placetype":"venue"
},
  "geometry": {"coordinates":[5.952393055,50.4584884644],"type":"Point"}
}