{
  "type": "Feature",
  "properties": {
    "iso:country":"BE",
    "sg:address":"Molenzijde 8",
    "sg:city":"Merksplas",
    "sg:classifiers":[
        {
            "category":"Health Services",
            "subcategory":"Dentist",
            "type":"Services"
        }
    ],
    "sg:phone":"+32 14 63 39 11",
    "sg:postcode":"2330",
    "sg:province":"Antwerpen",
    "wof:name":"Berghmans-schrijvers M",
    "wof:placetype":"venue"
},
  "geometry": {"coordinates":[4.8550820351,51.359664917],"type":"Point"}
}