{
  "type": "Feature",
  "properties": {
    "iso:country":"BE",
    "sg:address":"Rue Du Brochet 73",
    "sg:city":"Bruxelles (ixelles)",
    "sg:classifiers":[
        {
            "category":"Professional",
            "subcategory":"Art Services",
            "type":"Services"
        }
    ],
    "sg:phone":"+32 2 640 19 16",
    "sg:postcode":"1050",
    "sg:province":"Bruxelles-Capitale",
    "sg:tags":[
        "children's",
        "animation"
    ],
    "wof:name":"Magic Stephen",
    "wof:placetype":"venue"
},
  "geometry": {"coordinates":[4.38185215,50.8329124451],"type":"Point"}
}