{
  "type": "Feature",
  "properties": {
    "addr:full":"Hoogstraat 3 Gent Oost-Vlaanderen 9000",
    "addr:housenumber":"3",
    "addr:postcode":"9000",
    "addr:street":"Hoogstraat;Oost-Vlaanderen",
    "iso:country":"BE",
    "sg:address":"Hoogstraat 3",
    "sg:city":"Gent",
    "sg:classifiers":[
        {
            "category":"Restaurant",
            "type":"Food & Drink"
        }
    ],
    "sg:phone":"+32 9 233 76 02",
    "sg:postcode":"9000",
    "sg:province":"Oost-Vlaanderen",
    "wof:name":"Giardino Di Roma",
    "wof:placetype":"venue"
},
  "geometry": {"coordinates":[3.7110540867,51.0558853149],"type":"Point"}
}