{
  "type": "Feature",
  "properties": {
    "iso:country":"BE",
    "sg:address":"Waterstraat 12",
    "sg:city":"Kortenberg",
    "sg:orig_category":"Fabrication and montage de mobilier. Plomberie, chauffage and installations sanitaires. Charpentes a",
    "sg:phone":"+32 16 48 12 25",
    "sg:postcode":"3071",
    "sg:province":"Vlaams-Brabant",
    "wof:name":"Sanital",
    "wof:placetype":"venue"
},
  "geometry": {"coordinates":[4.6078438759,50.9102249146],"type":"Point"}
}