{
  "type": "Feature",
  "properties": {
    "addr:full":"Chauss\u00c9e De Tubize 3 Braine-le-comte Hainaut 7090",
    "addr:housenumber":"3",
    "addr:postcode":"7090",
    "addr:street":"Chausse\u0301E De Tubize",
    "iso:country":"BE",
    "sg:address":"Chauss\u00c9e De Tubize 3",
    "sg:city":"Braine-le-comte",
    "sg:orig_category":"Boekhouders",
    "sg:phone":"+32 67 67 05 06",
    "sg:postcode":"7090",
    "sg:province":"Hainaut",
    "wof:name":"Jacqueline Vandenbriele",
    "wof:placetype":"venue"
},
  "geometry": {"coordinates":[4.1772499084,50.6630401611],"type":"Point"}
}