{
  "type": "Feature",
  "properties": {
    "addr:full":"Rue E. Henrard 15 Oudergem/auderghem Bruxelles-Capitale 1160",
    "addr:housenumber":"15",
    "addr:postcode":"1160",
    "addr:street":"Rue E. Henrard;/",
    "iso:country":"BE",
    "sg:address":"Rue E. Henrard 15",
    "sg:city":"Oudergem/auderghem",
    "sg:orig_category":"Effectenmakelaars and vermogensbeheer",
    "sg:phone":"+32 2 673 15 57",
    "sg:postcode":"1160",
    "sg:province":"Bruxelles-Capitale",
    "wof:name":"Fintec",
    "wof:placetype":"venue"
},
  "geometry": {"coordinates":[4.4074101448,50.8233108521],"type":"Point"}
}