{
  "type": "Feature",
  "properties": {
    "addr:full":"Rue Saint-hubert 74 Waremme Li\u00e8ge 4300",
    "addr:housenumber":"74",
    "addr:postcode":"4300",
    "addr:street":"Rue Saint-Hubert",
    "iso:country":"BE",
    "sg:address":"Rue Saint-hubert 74",
    "sg:city":"Waremme",
    "sg:classifiers":[
        {
            "category":"Banks & Credit Unions",
            "subcategory":"Financial Services",
            "type":"Services"
        }
    ],
    "sg:phone":"+32 19 58 72 93",
    "sg:postcode":"4300",
    "sg:province":"Li\u00e8ge",
    "sg:tags":[
        "debt",
        "recovery"
    ],
    "wof:name":"Mosan",
    "wof:placetype":"venue"
},
  "geometry": {"coordinates":[5.2822270393,50.6689147949],"type":"Point"}
}