{
  "type": "Feature",
  "properties": {
    "iso:country":"BE",
    "sg:address":"Hofstraat 24",
    "sg:city":"Torhout",
    "sg:orig_category":"Artsen and specialisten",
    "sg:phone":"+32 50 21 16 62",
    "sg:postcode":"8820",
    "sg:province":"West-Vlaanderen",
    "wof:name":"Gabri\u00cbl Vandenbussche",
    "wof:placetype":"venue"
},
  "geometry": {"coordinates":[3.1031289101,51.0649147034],"type":"Point"}
}