{
  "type": "Feature",
  "properties": {
    "addr:full":"Kortrijksestraat 12 Kortrijk (heule) West-Vlaanderen 8501",
    "addr:housenumber":"12",
    "addr:postcode":"8501",
    "addr:street":"Kortrijksestraat",
    "iso:country":"BE",
    "sg:address":"Kortrijksestraat 12",
    "sg:city":"Kortrijk (heule)",
    "sg:classifiers":[
        {
            "category":"Professional",
            "subcategory":"Testing Lab",
            "type":"Services"
        }
    ],
    "sg:phone":"+32 56 35 20 92",
    "sg:postcode":"8501",
    "sg:province":"West-Vlaanderen",
    "sg:tags":[
        "chemist"
    ],
    "wof:name":"Vanackere L Bvba",
    "wof:placetype":"venue"
},
  "geometry": {"coordinates":[3.2346460819,50.8421058655],"type":"Point"}
}