{
  "type": "Feature",
  "properties": {
    "iso:country":"BE",
    "sg:address":"Chauss\u00c9e Brunehaut 381",
    "sg:city":"Juprelle",
    "sg:classifiers":[
        {
            "category":"Insurance",
            "subcategory":"Insurance Agent",
            "type":"Services"
        }
    ],
    "sg:phone":"+32 4 278 62 75",
    "sg:postcode":"4453",
    "sg:province":"Li\u00e8ge",
    "sg:tags":[
        "verzekeringsmakelaars",
        "expert"
    ],
    "wof:name":"J. Sauber",
    "wof:placetype":"venue"
},
  "geometry": {"coordinates":[5.5458488464,50.706111908],"type":"Point"}
}