{
  "type": "Feature",
  "properties": {
    "iso:country":"BE",
    "sg:address":"Chauss\u00c9e De Tournai 27",
    "sg:city":"Tournai",
    "sg:orig_category":"Rev\u00eatements de sols and murs. Installation de menuiserie m\u00e9tallique",
    "sg:phone":"+32 69 22 28 51",
    "sg:postcode":"7520",
    "sg:province":"Hainaut",
    "wof:name":"Parent Albert Et Fils",
    "wof:placetype":"venue"
},
  "geometry": {"coordinates":[3.2890689373,50.6433143616],"type":"Point"}
}