{
  "type": "Feature",
  "properties": {
    "addr:full":"Hendrik Consciencestraat 42 Zele Oost-Vlaanderen 9240",
    "addr:housenumber":"42",
    "addr:postcode":"9240",
    "addr:street":"Hendrik Consciencestraat",
    "iso:country":"BE",
    "sg:address":"Hendrik Consciencestraat 42",
    "sg:city":"Zele",
    "sg:classifiers":[
        {
            "category":"Building & Trades",
            "subcategory":"Construction",
            "type":"Services"
        }
    ],
    "sg:phone":"+32 52 44 78 97",
    "sg:postcode":"9240",
    "sg:province":"Oost-Vlaanderen",
    "sg:tags":[
        "carpenter"
    ],
    "wof:name":"Dam Baert Bvba",
    "wof:placetype":"venue"
},
  "geometry": {"coordinates":[4.0324602127,51.0603866577],"type":"Point"}
}