{
  "type": "Feature",
  "properties": {
    "addr:full":"Gentsestraat 2 Harelbeke West-Vlaanderen 8530",
    "addr:housenumber":"2",
    "addr:postcode":"8530",
    "addr:street":"Gentsestraat",
    "iso:country":"BE",
    "sg:address":"Gentsestraat 2",
    "sg:city":"Harelbeke",
    "sg:classifiers":[
        {
            "category":"Restaurant",
            "type":"Food & Drink"
        }
    ],
    "sg:phone":"+32 56 72 36 18",
    "sg:postcode":"8530",
    "sg:province":"West-Vlaanderen",
    "wof:name":"De Mart",
    "wof:placetype":"venue"
},
  "geometry": {"coordinates":[3.3121650219,50.8572006226],"type":"Point"}
}