{
  "type": "Feature",
  "properties": {
    "addr:full":"Rue Saint-jacques 13 Tournai Hainaut 7500",
    "addr:housenumber":"13",
    "addr:postcode":"7500",
    "addr:street":"Rue Saint-Jacques",
    "iso:country":"BE",
    "sg:address":"Rue Saint-jacques 13",
    "sg:city":"Tournai",
    "sg:orig_category":"Antiek",
    "sg:phone":"+32 69 22 70 89",
    "sg:postcode":"7500",
    "sg:province":"Hainaut",
    "wof:name":"Le Camaieu",
    "wof:placetype":"venue"
},
  "geometry": {"coordinates":[3.3840200901,50.6092147827],"type":"Point"}
}