{
  "type": "Feature",
  "properties": {
    "iso:country":"BE",
    "sg:address":"Maurits Sabbestraat 2",
    "sg:city":"Mechelen",
    "sg:classifiers":[
        {
            "category":"Professional",
            "subcategory":"Computer Services",
            "type":"Services"
        }
    ],
    "sg:phone":"+32 15 29 44 88",
    "sg:postcode":"2800",
    "sg:province":"Antwerpen",
    "sg:tags":[
        "-",
        "processing",
        "data",
        "printer"
    ],
    "wof:name":"Odit",
    "wof:placetype":"venue"
},
  "geometry": {"coordinates":[4.4757399559,51.034740448],"type":"Point"}
}