{
  "type": "Feature",
  "properties": {
    "addr:full":"Brugsesteenweg 30 Kuurne West-Vlaanderen 8520",
    "addr:housenumber":"30",
    "addr:postcode":"8520",
    "addr:street":"Brugsesteenweg",
    "iso:country":"BE",
    "sg:address":"Brugsesteenweg 30",
    "sg:city":"Kuurne",
    "sg:orig_category":"Bierproductie and Brouwerijen",
    "sg:phone":"+32 56 35 05 65",
    "sg:postcode":"8520",
    "sg:province":"West-Vlaanderen",
    "wof:name":"Brouwerij Maelfait",
    "wof:placetype":"venue"
},
  "geometry": {"coordinates":[3.2691690922,50.845954895],"type":"Point"}
}