{
  "type": "Feature",
  "properties": {
    "addr:full":"Frans Cretenlaan 89 Schelle Antwerpen 2627",
    "addr:housenumber":"89",
    "addr:postcode":"2627",
    "addr:street":"Frans Cretenlaan",
    "iso:country":"BE",
    "sg:address":"Frans Cretenlaan 89",
    "sg:city":"Schelle",
    "sg:classifiers":[
        {
            "category":"Banks & Credit Unions",
            "subcategory":"Investment Brokerage",
            "type":"Services"
        }
    ],
    "sg:phone":"+32 476 24 65 49",
    "sg:postcode":"2627",
    "sg:province":"Antwerpen",
    "sg:tags":[
        "repair",
        "-",
        "installation",
        "sanitary",
        "article"
    ],
    "wof:name":"Moyaert",
    "wof:placetype":"venue"
},
  "geometry": {"coordinates":[4.3425478935,51.1286392212],"type":"Point"}
}