{
  "type": "Feature",
  "properties": {
    "iso:country":"BE",
    "sg:address":"42 Ch De Wavre",
    "sg:city":"Bruxelles",
    "sg:classifiers":[
        {
            "category":"Home & Garden",
            "subcategory":"Furniture",
            "type":"Retail Goods"
        }
    ],
    "sg:phone":"+32 2 511 26 22",
    "sg:postcode":"1050",
    "sg:province":"Bruxelles-Capitale",
    "sg:tags":[
        "household",
        "wood"
    ],
    "wof:name":"De Rozen",
    "wof:placetype":"venue"
},
  "geometry": {"coordinates":[4.3646697998,50.8369598389],"type":"Point"}
}