{
  "type": "Feature",
  "properties": {
    "addr:full":"Rue Haute-wez 199 Li\u00e8ge 1 (grivegn\u00e9e) Li\u00e8ge 4030",
    "addr:housenumber":"199;1",
    "addr:postcode":"4030",
    "addr:street":"Rue Haute-Wez",
    "iso:country":"BE",
    "sg:address":"Rue Haute-wez 199",
    "sg:city":"Li\u00e8ge 1 (grivegn\u00e9e)",
    "sg:classifiers":[
        {
            "category":"Cafe",
            "type":"Food & Drink"
        }
    ],
    "sg:phone":"+32 4 341 23 19",
    "sg:postcode":"4030",
    "sg:province":"Li\u00e8ge",
    "sg:tags":[
        "snack-bars"
    ],
    "wof:name":"Grignotte (la)",
    "wof:placetype":"venue"
},
  "geometry": {"coordinates":[5.5892820358,50.627571106],"type":"Point"}
}