{
  "type": "Feature",
  "properties": {
    "addr:full":"Rue Emile Vandervelde 141 Fleurus Hainaut 6220",
    "addr:housenumber":"141",
    "addr:postcode":"6220",
    "addr:street":"Rue Emile Vandervelde",
    "iso:country":"BE",
    "sg:address":"Rue Emile Vandervelde 141",
    "sg:city":"Fleurus",
    "sg:classifiers":[
        {
            "category":"Health Services",
            "subcategory":"Dentist",
            "type":"Services"
        }
    ],
    "sg:phone":"+32 71 88 66 20",
    "sg:postcode":"6220",
    "sg:province":"Hainaut",
    "wof:name":"Mignon L",
    "wof:placetype":"venue"
},
  "geometry": {"coordinates":[4.5467481613,50.4798927307],"type":"Point"}
}