{
  "type": "Feature",
  "properties": {
    "addr:full":"Schoolstraat 9b2 Antwerpen Antwerpen 2060",
    "addr:housenumber":"9b2",
    "addr:postcode":"2060",
    "addr:street":"Schoolstraat",
    "iso:country":"BE",
    "sg:address":"Schoolstraat 9b2",
    "sg:city":"Antwerpen",
    "sg:orig_category":"Artsen and specialisten",
    "sg:phone":"+32 3 235 84 34",
    "sg:postcode":"2060",
    "sg:province":"Antwerpen",
    "wof:name":"Denis Duyck",
    "wof:placetype":"venue"
},
  "geometry": {"coordinates":[4.4315280914,51.2249450684],"type":"Point"}
}