{
  "type": "Feature",
  "properties": {
    "addr:full":"Rue De Robermont 147 Li\u00c8ge Li\u00e8ge 4020",
    "addr:housenumber":"147",
    "addr:postcode":"4020",
    "addr:street":"Rue De Robermont",
    "iso:country":"BE",
    "sg:address":"Rue De Robermont 147",
    "sg:city":"Li\u00c8ge",
    "sg:orig_category":"Tabac",
    "sg:phone":"+32 4 341 37 72",
    "sg:postcode":"4020",
    "sg:province":"Li\u00e8ge",
    "wof:name":"Wegria",
    "wof:placetype":"venue"
},
  "geometry": {"coordinates":[5.5967698097,50.6376800537],"type":"Point"}
}