{
  "type": "Feature",
  "properties": {
    "addr:full":"Astridlaan 78 Brugge (assebroek) West-Vlaanderen 8310",
    "addr:housenumber":"78",
    "addr:postcode":"8310",
    "addr:street":"Astridlaan",
    "iso:country":"BE",
    "sg:address":"Astridlaan 78",
    "sg:city":"Brugge (assebroek)",
    "sg:classifiers":[
        {
            "category":"Health Services",
            "subcategory":"Health Practitioner",
            "type":"Services"
        }
    ],
    "sg:phone":"+32 50 35 46 31",
    "sg:postcode":"8310",
    "sg:province":"West-Vlaanderen",
    "sg:tags":[
        "physiotherapist"
    ],
    "wof:name":"Van Cappel F",
    "wof:placetype":"venue"
},
  "geometry": {"coordinates":[3.2493569851,51.1991119385],"type":"Point"}
}