{
  "type": "Feature",
  "properties": {
    "addr:full":"Waalvest 2 Menen West-Vlaanderen 8930",
    "addr:housenumber":"2",
    "addr:postcode":"8930",
    "addr:street":"Waalvest",
    "iso:country":"BE",
    "sg:address":"Waalvest 2",
    "sg:city":"Menen",
    "sg:classifiers":[
        {
            "category":"Banks & Credit Unions",
            "subcategory":"Bank",
            "type":"Services"
        }
    ],
    "sg:phone":"+32 56 51 05 30",
    "sg:postcode":"8930",
    "sg:province":"West-Vlaanderen",
    "sg:tags":[
        "savings-banks"
    ],
    "wof:name":"Axa Bank",
    "wof:placetype":"venue"
},
  "geometry": {"coordinates":[3.1239280701,50.7931137085],"type":"Point"}
}