{
  "type": "Feature",
  "properties": {
    "iso:country":"BE",
    "sg:address":"Rue Jean Jaur\u00e8s 183",
    "sg:city":"Charleroi (dampremy)",
    "sg:classifiers":[
        {
            "category":"Banks & Credit Unions",
            "subcategory":"Bureau De Change",
            "type":"Services"
        }
    ],
    "sg:phone":"+32 71 31 36 52",
    "sg:postcode":"6020",
    "sg:province":"Hainaut",
    "sg:tags":[
        "-",
        "household",
        "gas"
    ],
    "wof:name":"Beghain R",
    "wof:placetype":"venue"
},
  "geometry": {"coordinates":[4.4256000519,50.4203872681],"type":"Point"}
}