{
  "type": "Feature",
  "properties": {
    "iso:country":"BE",
    "sg:address":"Chauss\u00c9e Romaine 180",
    "sg:city":"Waremme",
    "sg:orig_category":"Moteurs, transformateurs and groupes \u00e9lectrog\u00e8nes Fab",
    "sg:phone":"+32 19 33 92 92",
    "sg:postcode":"4300",
    "sg:province":"Li\u00e8ge",
    "wof:name":"Moes Diesel",
    "wof:placetype":"venue"
},
  "geometry": {"coordinates":[5.2709522247,50.6941184998],"type":"Point"}
}