{
  "type": "Feature",
  "properties": {
    "addr:full":"Rue Des Gaulois 4 Ath (meslin - L'ev\u00eaque) Hainaut 7822",
    "addr:housenumber":"4;meslin",
    "addr:postcode":"7822",
    "addr:street":"Rue Des Gaulois;\u0302Que Hainaut",
    "iso:country":"BE",
    "sg:address":"Rue Des Gaulois 4",
    "sg:city":"Ath (meslin - L'ev\u00eaque)",
    "sg:classifiers":[
        {
            "category":"Health Services",
            "subcategory":"Nursing And Care Facility",
            "type":"Services"
        }
    ],
    "sg:phone":"+32 68 44 99 77",
    "sg:postcode":"7822",
    "sg:province":"Hainaut",
    "sg:tags":[
        "access",
        "equipment",
        "hospital",
        "-"
    ],
    "wof:name":"C & I Engineering",
    "wof:placetype":"venue"
},
  "geometry": {"coordinates":[3.8531649113,50.6538887024],"type":"Point"}
}