{
  "type": "Feature",
  "properties": {
    "iso:country":"BE",
    "sg:address":"Woudstraat 6",
    "sg:city":"Genk",
    "sg:classifiers":[
        {
            "category":"Banks & Credit Unions",
            "subcategory":"Investment Brokerage",
            "type":"Services"
        }
    ],
    "sg:phone":"+32 89 84 80 84",
    "sg:postcode":"3600",
    "sg:province":"Limburg",
    "sg:tags":[
        "printing",
        "-"
    ],
    "wof:name":"Illochroma",
    "wof:placetype":"venue"
},
  "geometry": {"coordinates":[5.4827251434,51.006072998],"type":"Point"}
}