{
  "type": "Feature",
  "properties": {
    "iso:country":"BE",
    "sg:address":"Rue Saint-antoine 21",
    "sg:city":"La Louvi\u00e8re (haine-saint-pierre)",
    "sg:classifiers":[
        {
            "category":"Health Services",
            "subcategory":"Health Practitioner",
            "type":"Services"
        }
    ],
    "sg:phone":"+32 64 26 33 88",
    "sg:postcode":"7100",
    "sg:province":"Hainaut",
    "sg:tags":[
        "physiotherapist"
    ],
    "wof:name":"Couillard Anne-jo",
    "wof:placetype":"venue"
},
  "geometry": {"coordinates":[4.1952118874,50.4515838623],"type":"Point"}
}