{
  "type": "Feature",
  "properties": {
    "iso:country":"BE",
    "sg:address":"Vrijheidsstraat 36",
    "sg:city":"Denderleeuw",
    "sg:classifiers":[
        {
            "category":"Cafe",
            "type":"Food & Drink"
        }
    ],
    "sg:phone":"+32 53 66 72 67",
    "sg:postcode":"9470",
    "sg:province":"Oost-Vlaanderen",
    "sg:tags":[
        "caf\u00e9s"
    ],
    "wof:name":"Van Holsbeek & De Muyter",
    "wof:placetype":"venue"
},
  "geometry": {"coordinates":[4.0709791183,50.8762741089],"type":"Point"}
}