{
  "type": "Feature",
  "properties": {
    "iso:country":"BE",
    "sg:address":"Pastorijstraat 40",
    "sg:city":"Sint-niklaas (nieuwkerken-waas)",
    "sg:classifiers":[
        {
            "category":"Real Estate",
            "subcategory":"Surveying",
            "type":"Services"
        }
    ],
    "sg:phone":"+32 3 777 95 39",
    "sg:postcode":"9100",
    "sg:province":"Oost-Vlaanderen",
    "sg:tags":[
        "surveyor",
        "land"
    ],
    "wof:name":"Braem H",
    "wof:placetype":"venue"
},
  "geometry": {"coordinates":[4.1734209061,51.1933555603],"type":"Point"}
}