{
  "type": "Feature",
  "properties": {
    "addr:full":"Boulevard De La Cense 73 Waterloo Brabant Wallon 1410",
    "addr:housenumber":"73",
    "addr:postcode":"1410",
    "addr:street":"Boulevard De La Cense",
    "iso:country":"BE",
    "sg:address":"Boulevard De La Cense 73",
    "sg:city":"Waterloo",
    "sg:classifiers":[
        {
            "category":"Banks & Credit Unions",
            "subcategory":"Financial Services",
            "type":"Services"
        }
    ],
    "sg:phone":"+32 2 351 19 75",
    "sg:postcode":"1410",
    "sg:province":"Brabant Wallon",
    "sg:tags":[
        "loan",
        "mortgage"
    ],
    "wof:name":"Agence Dujardin",
    "wof:placetype":"venue"
},
  "geometry": {"coordinates":[4.3904237747,50.7088432312],"type":"Point"}
}