{
  "type": "Feature",
  "properties": {
    "iso:country":"BE",
    "sg:address":"Hoogstraat 29bb",
    "sg:city":"Lede",
    "sg:orig_category":"Artsen and specialisten",
    "sg:phone":"+32 53 80 04 83",
    "sg:postcode":"9340",
    "sg:province":"Oost-Vlaanderen",
    "wof:name":"Hans Christiaens",
    "wof:placetype":"venue"
},
  "geometry": {"coordinates":[3.9769771099,50.9631652832],"type":"Point"}
}