{
  "type": "Feature",
  "properties": {
    "addr:full":"Bld Albert-elisabeth 88 Mons Hainaut 7000",
    "addr:housenumber":"88",
    "addr:postcode":"7000",
    "addr:street":"Bld Albert-Elisabeth;Hainaut",
    "iso:country":"BE",
    "sg:address":"Bld Albert-elisabeth 88",
    "sg:city":"Mons",
    "sg:orig_category":"Biblioth\u00e8ques and archives publiques",
    "sg:phone":"+32 65 31 17 14",
    "sg:postcode":"7000",
    "sg:province":"Hainaut",
    "wof:name":"Ludoth\u00c8que Petit Cirque",
    "wof:placetype":"venue"
},
  "geometry": {"coordinates":[3.9487299919,50.4462089539],"type":"Point"}
}