{
  "type": "Feature",
  "properties": {
    "iso:country":"BE",
    "sg:address":"Route De La Hesbaye 277",
    "sg:city":"Eghezee",
    "sg:orig_category":"Herstellingen and onderhoud van auto's Voertuigen",
    "sg:phone":"+32 81 81 21 75",
    "sg:postcode":"5310",
    "sg:province":"Namur",
    "wof:name":"Charles Fran\u00c7ois",
    "wof:placetype":"venue"
},
  "geometry": {"coordinates":[4.9339327812,50.6192626953],"type":"Point"}
}