{
  "type": "Feature",
  "properties": {
    "addr:full":"Brusselsepoortstraat 29 Mechelen Antwerpen 2800",
    "addr:housenumber":"29",
    "addr:postcode":"2800",
    "addr:street":"Brusselsepoortstraat",
    "iso:country":"BE",
    "sg:address":"Brusselsepoortstraat 29",
    "sg:city":"Mechelen",
    "sg:orig_category":"Banques and organismes de cr\u00e9dit",
    "sg:phone":"+32 15 45 07 30",
    "sg:postcode":"2800",
    "sg:province":"Antwerpen",
    "wof:name":"Dexia",
    "wof:placetype":"venue"
},
  "geometry": {"coordinates":[4.4725179672,51.0211296082],"type":"Point"}
}