{
  "type": "Feature",
  "properties": {
    "addr:full":"Veldstraat 14 Meerhout Antwerpen 2450",
    "addr:housenumber":"14",
    "addr:postcode":"2450",
    "addr:street":"Veldstraat",
    "iso:country":"BE",
    "sg:address":"Veldstraat 14",
    "sg:city":"Meerhout",
    "sg:classifiers":[
        {
            "category":"Banks & Credit Unions",
            "subcategory":"Bank",
            "type":"Services"
        }
    ],
    "sg:phone":"+32 14 30 46 50",
    "sg:postcode":"2450",
    "sg:province":"Antwerpen",
    "wof:name":"A.c.i. Bvba",
    "wof:placetype":"venue"
},
  "geometry": {"coordinates":[5.0795350075,51.1318092346],"type":"Point"}
}