{
  "type": "Feature",
  "properties": {
    "iso:country":"BE",
    "sg:address":"Tennislaan 29",
    "sg:city":"Genk",
    "sg:classifiers":[
        {
            "category":"Cafe",
            "type":"Food & Drink"
        }
    ],
    "sg:phone":"+32 89 30 31 02",
    "sg:postcode":"3600",
    "sg:province":"Limburg",
    "sg:tags":[
        "caf\u00e9s"
    ],
    "wof:name":"Lorenzo D'addario",
    "wof:placetype":"venue"
},
  "geometry": {"coordinates":[5.4748458862,50.9687194824],"type":"Point"}
}