{
  "type": "Feature",
  "properties": {
    "addr:full":"Hooiveld 22 Ranst Antwerpen 2520",
    "addr:housenumber":"22",
    "addr:postcode":"2520",
    "addr:street":"Hooiveld",
    "iso:country":"BE",
    "sg:address":"Hooiveld 22",
    "sg:city":"Ranst",
    "sg:classifiers":[
        {
            "category":"Arena",
            "subcategory":"Sports Club",
            "type":"Entertainment"
        }
    ],
    "sg:phone":"+32 3 475 00 09",
    "sg:postcode":"2520",
    "sg:province":"Antwerpen",
    "sg:tags":[
        "de"
    ],
    "wof:name":"Woka",
    "wof:placetype":"venue"
},
  "geometry": {"coordinates":[4.56580019,51.1846733093],"type":"Point"}
}