{
  "type": "Feature",
  "properties": {
    "iso:country":"BE",
    "sg:address":"Meulemanslaan 18",
    "sg:city":"Westerlo (tongerlo)",
    "sg:classifiers":[
        {
            "category":"Banks & Credit Unions",
            "subcategory":"Investment Brokerage",
            "type":"Services"
        }
    ],
    "sg:phone":"+32 14 54 40 72",
    "sg:postcode":"2260",
    "sg:province":"Antwerpen",
    "sg:tags":[
        "auditor"
    ],
    "wof:name":"Willemyns H",
    "wof:placetype":"venue"
},
  "geometry": {"coordinates":[4.9142332077,51.1043777466],"type":"Point"}
}