{
  "type": "Feature",
  "properties": {
    "iso:country":"BE",
    "sg:address":"Chauss\u00e9e De Douai 159",
    "sg:city":"Tournai",
    "sg:classifiers":[
        {
            "category":"Autos & Motor Vehicles",
            "subcategory":"Auto Supplies",
            "type":"Retail Goods"
        }
    ],
    "sg:phone":"+32 69 22 69 17",
    "sg:postcode":"7500",
    "sg:province":"Hainaut",
    "sg:tags":[
        "access",
        "automobile",
        "part",
        "-"
    ],
    "wof:name":"Bondroit Jean Sprl",
    "wof:placetype":"venue"
},
  "geometry": {"coordinates":[3.3732140064,50.5984573364],"type":"Point"}
}