{
  "type": "Feature",
  "properties": {
    "iso:country":"BE",
    "sg:address":"Rue Des Soeurs Noires 4a",
    "sg:city":"Mons",
    "sg:orig_category":"Radioproductie and uitzendingen",
    "sg:phone":"+32 65 40 00 40",
    "sg:postcode":"7000",
    "sg:province":"Hainaut",
    "wof:name":"T\u00c9l\u00c9 Mb",
    "wof:placetype":"venue"
},
  "geometry": {"coordinates":[3.9464170933,50.4516677856],"type":"Point"}
}