{
  "type": "Feature",
  "properties": {
    "addr:full":"Hoogboomsteenweg 218 Kapellen (mariaburg) Antwerpen 2950",
    "addr:housenumber":"218",
    "addr:postcode":"2950",
    "addr:street":"Hoogboomsteenweg",
    "iso:country":"BE",
    "sg:address":"Hoogboomsteenweg 218",
    "sg:city":"Kapellen (mariaburg)",
    "sg:classifiers":[
        {
            "category":"Wholesale",
            "subcategory":"Hardware",
            "type":"Manufacturing & Wholesale Goods"
        }
    ],
    "sg:phone":"+32 3 295 39 40",
    "sg:postcode":"2950",
    "sg:province":"Antwerpen",
    "sg:tags":[
        "lubricating",
        "compound"
    ],
    "wof:name":"Atlas Oil Services Bvba",
    "wof:placetype":"venue"
},
  "geometry": {"coordinates":[4.4559278488,51.3138999939],"type":"Point"}
}