{
  "type": "Feature",
  "properties": {
    "addr:full":"Bollestraat 169 Torhout West-Vlaanderen 8820",
    "addr:housenumber":"169",
    "addr:postcode":"8820",
    "addr:street":"Bollestraat",
    "iso:country":"BE",
    "sg:address":"Bollestraat 169",
    "sg:city":"Torhout",
    "sg:orig_category":"Dansscholen",
    "sg:phone":"+32 51 72 39 06",
    "sg:postcode":"8820",
    "sg:province":"West-Vlaanderen",
    "wof:name":"Danscenter Gevada",
    "wof:placetype":"venue"
},
  "geometry": {"coordinates":[3.117180109,51.0413513184],"type":"Point"}
}