{
  "type": "Feature",
  "properties": {
    "addr:full":"Kenislei 76 Brasschaat Antwerpen 2930",
    "addr:housenumber":"76",
    "addr:postcode":"2930",
    "addr:street":"Kenislei",
    "iso:country":"BE",
    "sg:address":"Kenislei 76",
    "sg:city":"Brasschaat",
    "sg:orig_category":"Sportclubs",
    "sg:phone":"+32 3 653 12 89",
    "sg:postcode":"2930",
    "sg:province":"Antwerpen",
    "wof:name":"Skiclub Flanders",
    "wof:placetype":"venue"
},
  "geometry": {"coordinates":[4.4848670959,51.3024787903],"type":"Point"}
}