{
  "type": "Feature",
  "properties": {
    "addr:full":"Rue De Roubaix 16 Tournai Hainaut 7520",
    "addr:housenumber":"16",
    "addr:postcode":"7520",
    "addr:street":"Rue De Roubaix",
    "iso:country":"BE",
    "sg:address":"Rue De Roubaix 16",
    "sg:city":"Tournai",
    "sg:orig_category":"Banques and organismes de cr\u00e9dit",
    "sg:phone":"+32 69 35 23 01",
    "sg:postcode":"7520",
    "sg:province":"Hainaut",
    "wof:name":"Fortis",
    "wof:placetype":"venue"
},
  "geometry": {"coordinates":[3.281234026,50.6446456909],"type":"Point"}
}