{
  "type": "Feature",
  "properties": {
    "addr:full":"Ambachtsstraat 46 Malle (westmalle) Antwerpen 2390",
    "addr:housenumber":"46",
    "addr:postcode":"2390",
    "addr:street":"Ambachtsstraat",
    "iso:country":"BE",
    "sg:address":"Ambachtsstraat 46",
    "sg:city":"Malle (westmalle)",
    "sg:orig_category":"Non-Classified Establishments",
    "sg:phone":"+32 3 311 71 91",
    "sg:postcode":"2390",
    "sg:province":"Antwerpen",
    "wof:name":"Confetec Bvba",
    "wof:placetype":"venue"
},
  "geometry": {"coordinates":[4.7081971169,51.2912902832],"type":"Point"}
}