{
  "type": "Feature",
  "properties": {
    "iso:country":"BE",
    "sg:address":"Nederhasseltstraat 299",
    "sg:city":"Ninove (nederhasselt)",
    "sg:classifiers":[
        {
            "category":"Personal",
            "subcategory":"Barber",
            "type":"Services"
        }
    ],
    "sg:phone":"+32 54 34 21 00",
    "sg:postcode":"9400",
    "sg:province":"Oost-Vlaanderen",
    "sg:tags":[
        "gentleman",
        "salon",
        "-",
        "hairdressing"
    ],
    "wof:name":"Fanny",
    "wof:placetype":"venue"
},
  "geometry": {"coordinates":[3.9688329697,50.84582901],"type":"Point"}
}