{
  "type": "Feature",
  "properties": {
    "addr:full":"Au Werihet 53 Wandre Li\u00e8ge 4020",
    "addr:housenumber":"53",
    "addr:postcode":"4020",
    "iso:country":"BE",
    "sg:address":"Au Werihet 53",
    "sg:city":"Wandre",
    "sg:classifiers":[
        {
            "category":"Utilities",
            "subcategory":"Recycling",
            "type":"Services"
        }
    ],
    "sg:phone":"+32 3 828 29 28",
    "sg:postcode":"4020",
    "sg:province":"Li\u00e8ge",
    "sg:tags":[
        "metal"
    ],
    "wof:name":"Bulmetal B.v.b.a.",
    "wof:placetype":"venue"
},
  "geometry": {"coordinates":[4.3416762352,51.1586990356],"type":"Point"}
}