{
  "type": "Feature",
  "properties": {
    "iso:country":"BE",
    "sg:address":"Rue Mazette 19",
    "sg:city":"Ath (arbre)",
    "sg:classifiers":[
        {
            "category":"Building & Trades",
            "subcategory":"Construction",
            "type":"Services"
        }
    ],
    "sg:phone":"+32 68 28 74 70",
    "sg:postcode":"7811",
    "sg:province":"Hainaut",
    "sg:tags":[
        "installation",
        "-",
        "central",
        "heating"
    ],
    "wof:name":"Ag Chauffage",
    "wof:placetype":"venue"
},
  "geometry": {"coordinates":[3.8159689903,50.6116752625],"type":"Point"}
}