{
  "type": "Feature",
  "properties": {
    "addr:full":"Zwevegemsestraat 17 Kortrijk West-Vlaanderen 8500",
    "addr:housenumber":"17",
    "addr:postcode":"8500",
    "addr:street":"Zwevegemsestraat",
    "iso:country":"BE",
    "sg:address":"Zwevegemsestraat 17",
    "sg:city":"Kortrijk",
    "sg:orig_category":"Imprimeries and copyshops. Reliure and finition",
    "sg:phone":"+32 56 22 82 62",
    "sg:postcode":"8500",
    "sg:province":"West-Vlaanderen",
    "wof:name":"Kopie - Kortrijk",
    "wof:placetype":"venue"
},
  "geometry": {"coordinates":[3.27227211,50.8258132935],"type":"Point"}
}