{
  "type": "Feature",
  "properties": {
    "addr:full":"Chauss\u00e9e De Tongres 283 Juprelle Li\u00e8ge 4450",
    "addr:housenumber":"283",
    "addr:postcode":"4450",
    "addr:street":"Chausse\u0301E De Tongres",
    "iso:country":"BE",
    "sg:address":"Chauss\u00e9e De Tongres 283",
    "sg:city":"Juprelle",
    "sg:classifiers":[
        {
            "category":"Wholesale",
            "subcategory":"Wine & Distilled Alcoholic Beverages",
            "type":"Manufacturing & Wholesale Goods"
        }
    ],
    "sg:phone":"+32 4 278 25 59",
    "sg:postcode":"4450",
    "sg:province":"Li\u00e8ge",
    "sg:tags":[
        "whol",
        "-",
        "spirit",
        "mfg"
    ],
    "wof:name":"Dahan G",
    "wof:placetype":"venue"
},
  "geometry": {"coordinates":[5.5295100212,50.7010650635],"type":"Point"}
}