{
  "type": "Feature",
  "properties": {
    "addr:full":"Avenue Des Villas 97 Vorst/forest Bruxelles-Capitale 1190",
    "addr:housenumber":"97",
    "addr:postcode":"1190",
    "addr:street":"Avenue Des Villas;/ Forest",
    "iso:country":"BE",
    "sg:address":"Avenue Des Villas 97",
    "sg:city":"Vorst/forest",
    "sg:orig_category":"Architectes",
    "sg:phone":"+32 2 534 10 22",
    "sg:postcode":"1190",
    "sg:province":"Bruxelles-Capitale",
    "wof:name":"X. Vanderlinden",
    "wof:placetype":"venue"
},
  "geometry": {"coordinates":[4.3377752304,50.8242797852],"type":"Point"}
}