{
  "type": "Feature",
  "properties": {
    "addr:full":"Rosi\u00c8re-la-grande 61 Vaux-sur-sure Luxembourg 6640",
    "addr:housenumber":"61",
    "addr:postcode":"6640",
    "addr:street":"Rosie\u0300Re-La-Grande",
    "iso:country":"BE",
    "sg:address":"Rosi\u00c8re-la-grande 61",
    "sg:city":"Vaux-sur-sure",
    "sg:orig_category":"Eleveurs de bovins",
    "sg:phone":"+32 61 26 65 48",
    "sg:postcode":"6640",
    "sg:province":"Luxembourg",
    "wof:name":"Rene Cope",
    "wof:placetype":"venue"
},
  "geometry": {"coordinates":[5.5729799271,49.9218444824],"type":"Point"}
}