{
  "type": "Feature",
  "properties": {
    "iso:country":"BE",
    "sg:address":"Rue Des Charbonnages 315",
    "sg:city":"Chatelet",
    "sg:orig_category":"Entretien and r\u00e9parations de voitures",
    "sg:phone":"+32 71 38 41 27",
    "sg:postcode":"6200",
    "sg:province":"Hainaut",
    "wof:name":"Gabriele Giansante",
    "wof:placetype":"venue"
},
  "geometry": {"coordinates":[4.519053936,50.4268989563],"type":"Point"}
}