{
  "type": "Feature",
  "properties": {
    "addr:full":"Place Albert I 31 Herve Li\u00e8ge 4650",
    "addr:housenumber":"31",
    "addr:postcode":"4650",
    "addr:street":"Place Albert I",
    "iso:country":"BE",
    "sg:address":"Place Albert I 31",
    "sg:city":"Herve",
    "sg:classifiers":[
        {
            "category":"Autos & Motor Vehicles",
            "subcategory":"Auto Supplies",
            "type":"Retail Goods"
        }
    ],
    "sg:phone":"+32 87 66 16 76",
    "sg:postcode":"4650",
    "sg:province":"Li\u00e8ge",
    "sg:tags":[
        "access",
        "automobile",
        "part",
        "-"
    ],
    "wof:name":"Automobile (l')",
    "wof:placetype":"venue"
},
  "geometry": {"coordinates":[5.7931160927,50.642742157],"type":"Point"}
}