{
  "type": "Feature",
  "properties": {
    "addr:full":"Meerweg 174 Sint-pieters-leeuw Vlaams-Brabant 1600",
    "addr:housenumber":"174",
    "addr:postcode":"1600",
    "addr:street":"Meerweg",
    "iso:country":"BE",
    "sg:address":"Meerweg 174",
    "sg:city":"Sint-pieters-leeuw",
    "sg:orig_category":"Gespecialiseerde residenti\u00eble bouw",
    "sg:phone":"+32 2 377 81 36",
    "sg:postcode":"1600",
    "sg:province":"Vlaams-Brabant",
    "wof:name":"Vanderkelen",
    "wof:placetype":"venue"
},
  "geometry": {"coordinates":[4.2821102142,50.7826499939],"type":"Point"}
}