{
  "type": "Feature",
  "properties": {
    "addr:full":"Hogeschuurstraat 31 Staden West-Vlaanderen 8840",
    "addr:housenumber":"31",
    "addr:postcode":"8840",
    "addr:street":"Hogeschuurstraat",
    "iso:country":"BE",
    "sg:address":"Hogeschuurstraat 31",
    "sg:city":"Staden",
    "sg:orig_category":"Rundveehouders",
    "sg:phone":"+32 51 70 51 04",
    "sg:postcode":"8840",
    "sg:province":"West-Vlaanderen",
    "wof:name":"Geert Buyse",
    "wof:placetype":"venue"
},
  "geometry": {"coordinates":[3.0007150173,50.9789772034],"type":"Point"}
}