{
  "type": "Feature",
  "properties": {
    "iso:country":"BE",
    "sg:address":"Conservatoriumplein 30",
    "sg:city":"Kortrijk",
    "sg:classifiers":[
        {
            "category":"Cafe",
            "type":"Food & Drink"
        }
    ],
    "sg:phone":"+32 56 22 82 47",
    "sg:postcode":"8500",
    "sg:province":"West-Vlaanderen",
    "sg:tags":[
        "caf\u00e9s"
    ],
    "wof:name":"Roland Godderis",
    "wof:placetype":"venue"
},
  "geometry": {"coordinates":[3.261660099,50.8253707886],"type":"Point"}
}