{
  "type": "Feature",
  "properties": {
    "iso:country":"BE",
    "sg:address":"Guillaume Van Neromlaan 19b25",
    "sg:city":"Oudergem/auderghem",
    "sg:orig_category":"Zuivelproducten",
    "sg:phone":"+32 2 672 25 82",
    "sg:postcode":"1160",
    "sg:province":"Bruxelles-Capitale",
    "wof:name":"Jacques Lytsermeyer",
    "wof:placetype":"venue"
},
  "geometry": {"coordinates":[4.4329099655,50.8062934875],"type":"Point"}
}