{
  "type": "Feature",
  "properties": {
    "iso:country":"BE",
    "sg:address":"Blijde-inkomststraat 5",
    "sg:city":"Leuven",
    "sg:orig_category":"Boekhandels",
    "sg:phone":"+32 16 32 53 45",
    "sg:postcode":"3000",
    "sg:province":"Vlaams-Brabant",
    "wof:name":"Universitaire Pers Leuven",
    "wof:placetype":"venue"
},
  "geometry": {"coordinates":[4.7078948021,50.8774337769],"type":"Point"}
}