{
  "type": "Feature",
  "properties": {
    "addr:full":"Hertsbergsestraat 13 Oostkamp West-Vlaanderen 8020",
    "addr:housenumber":"13",
    "addr:postcode":"8020",
    "addr:street":"Hertsbergsestraat",
    "iso:country":"BE",
    "sg:address":"Hertsbergsestraat 13",
    "sg:city":"Oostkamp",
    "sg:orig_category":"Poissonniers and \u00e9caillers",
    "sg:phone":"+32 50 82 50 27",
    "sg:postcode":"8020",
    "sg:province":"West-Vlaanderen",
    "wof:name":"Filip Degrande",
    "wof:placetype":"venue"
},
  "geometry": {"coordinates":[3.259829998,51.1323699951],"type":"Point"}
}