{
  "type": "Feature",
  "properties": {
    "iso:country":"BE",
    "sg:address":"Roodebeeksteenweg 336",
    "sg:city":"Sint-lambrechts-woluwe/woluwe-saint-lambert",
    "sg:orig_category":"Herstellingen and onderhoud van auto's",
    "sg:phone":"+32 2 771 32 30",
    "sg:postcode":"1200",
    "sg:province":"Bruxelles-Capitale",
    "wof:name":"A.s.l.",
    "wof:placetype":"venue"
},
  "geometry": {"coordinates":[4.4218659401,50.849521637],"type":"Point"}
}