{
  "type": "Feature",
  "properties": {
    "addr:full":"Vredelaan 101 Zemst (weerde) Vlaams-Brabant 1982",
    "addr:housenumber":"101",
    "addr:postcode":"1982",
    "addr:street":"Vredelaan",
    "iso:country":"BE",
    "sg:address":"Vredelaan 101",
    "sg:city":"Zemst (weerde)",
    "sg:orig_category":"Non-Classified Establishments",
    "sg:phone":"+32 15 71 19 73",
    "sg:postcode":"1982",
    "sg:province":"Vlaams-Brabant",
    "wof:name":"Agri-foods Bvba",
    "wof:placetype":"venue"
},
  "geometry": {"coordinates":[4.4765081406,50.9770965576],"type":"Point"}
}