{
  "type": "Feature",
  "properties": {
    "iso:country":"BE",
    "sg:address":"Vleeshouwersstraat 6",
    "sg:city":"Veurne",
    "sg:orig_category":"Drukkerijen and copyshops",
    "sg:phone":"+32 58 31 16 46",
    "sg:postcode":"8630",
    "sg:province":"West-Vlaanderen",
    "wof:name":"Joseph Calcoen",
    "wof:placetype":"venue"
},
  "geometry": {"coordinates":[2.6610050201,51.071762085],"type":"Point"}
}