{
  "type": "Feature",
  "properties": {
    "iso:country":"BE",
    "sg:address":"Albert I -promenade 62",
    "sg:city":"Oostende",
    "sg:classifiers":[
        {
            "category":"Restaurant",
            "type":"Food & Drink"
        }
    ],
    "sg:phone":"+32 59 70 54 44",
    "sg:postcode":"8400",
    "sg:province":"West-Vlaanderen",
    "wof:name":"Restaurant-tearoom Le Basque",
    "wof:placetype":"venue"
},
  "geometry": {"coordinates":[2.9106450081,51.2305030823],"type":"Point"}
}