{
  "type": "Feature",
  "properties": {
    "addr:full":"Leopold Ii Laan 203 Sint-jans-molenbeek/molenbeek-saint-jean Bruxelles-Capitale 1080",
    "addr:housenumber":"203",
    "addr:postcode":"1080",
    "addr:street":"Leopold Ii Laan",
    "iso:country":"BE",
    "sg:address":"Leopold Ii Laan 203",
    "sg:city":"Sint-jans-molenbeek/molenbeek-saint-jean",
    "sg:orig_category":"Artsen and specialisten",
    "sg:phone":"+32 2 424 09 44",
    "sg:postcode":"1080",
    "sg:province":"Bruxelles-Capitale",
    "wof:name":"Polyclinique St.remi",
    "wof:placetype":"venue"
},
  "geometry": {"coordinates":[4.3355817795,50.8620681763],"type":"Point"}
}