{
  "type": "Feature",
  "properties": {
    "iso:country":"BE",
    "sg:address":"Koningin Astridlaan 159",
    "sg:city":"Mechelen",
    "sg:orig_category":"M\u00e9decins and sp\u00e9cialistes",
    "sg:phone":"+32 15 41 13 11",
    "sg:postcode":"2800",
    "sg:province":"Antwerpen",
    "wof:name":"L. De Swert",
    "wof:placetype":"venue"
},
  "geometry": {"coordinates":[4.472055912,51.0236091614],"type":"Point"}
}