{
  "type": "Feature",
  "properties": {
    "addr:full":"Rue Haute 73 Bassenge Li\u00e8ge 4690",
    "addr:housenumber":"73",
    "addr:postcode":"4690",
    "addr:street":"Rue Haute",
    "iso:country":"BE",
    "sg:address":"Rue Haute 73",
    "sg:city":"Bassenge",
    "sg:orig_category":"Pain, p\u00e2tisseries and confiseries",
    "sg:phone":"+32 4 286 15 22",
    "sg:postcode":"4690",
    "sg:province":"Li\u00e8ge",
    "wof:name":"Bertho Blaffart",
    "wof:placetype":"venue"
},
  "geometry": {"coordinates":[5.6637811661,50.7886238098],"type":"Point"}
}