{
  "type": "Feature",
  "properties": {
    "iso:country":"BE",
    "sg:address":"Champs 763a",
    "sg:city":"Bertogne (longchamps)",
    "sg:classifiers":[
        {
            "category":"Retail",
            "subcategory":"Veterinary Services",
            "type":"Services"
        }
    ],
    "sg:phone":"+32 61 21 56 01",
    "sg:postcode":"6688",
    "sg:province":"Luxembourg",
    "sg:tags":[
        "veterinarian"
    ],
    "wof:name":"Martin G",
    "wof:placetype":"venue"
},
  "geometry": {"coordinates":[5.670853138,50.0362243652],"type":"Point"}
}