{
  "type": "Feature",
  "properties": {
    "addr:full":"Place Du Baty 2 Beyne-heusay Li\u00e8ge 4610",
    "addr:housenumber":"2",
    "addr:postcode":"4610",
    "addr:street":"Place Du Baty",
    "iso:country":"BE",
    "sg:address":"Place Du Baty 2",
    "sg:city":"Beyne-heusay",
    "sg:orig_category":"Huisdieren and benodigdheden",
    "sg:phone":"+32 4 358 27 13",
    "sg:postcode":"4610",
    "sg:province":"Li\u00e8ge",
    "wof:name":"Maison Graine D'or",
    "wof:placetype":"venue"
},
  "geometry": {"coordinates":[5.6575598717,50.6195335388],"type":"Point"}
}