{
  "type": "Feature",
  "properties": {
    "iso:country":"BE",
    "sg:address":"All\u00c9e F 20",
    "sg:city":"Charleroi",
    "sg:orig_category":"Huishoudapparaten, televisies and radio's",
    "sg:phone":"+32 71 47 55 93",
    "sg:postcode":"6001",
    "sg:province":"Hainaut",
    "wof:name":"New Age",
    "wof:placetype":"venue"
},
  "geometry": {"coordinates":[4.4448251724,50.3973655701],"type":"Point"}
}