{
  "type": "Feature",
  "properties": {
    "iso:country":"BE",
    "sg:address":"Rue Vlle Voie De Li\u00c8ge 1",
    "sg:city":"Sprimont",
    "sg:orig_category":"Artsen and specialisten",
    "sg:phone":"+32 4 382 15 16",
    "sg:postcode":"4140",
    "sg:province":"Li\u00e8ge",
    "wof:name":"Marianne Lesuisse",
    "wof:placetype":"venue"
},
  "geometry": {"coordinates":[5.6590099335,50.5073661804],"type":"Point"}
}