{
  "type": "Feature",
  "properties": {
    "addr:full":"Den Booien 23 Halle Vlaams-Brabant 1500",
    "addr:housenumber":"23",
    "addr:postcode":"1500",
    "addr:street":"Booien",
    "iso:country":"BE",
    "sg:address":"Den Booien 23",
    "sg:city":"Halle",
    "sg:orig_category":"Belastingconsulenten Diverse juridische dienstverlening",
    "sg:phone":"+32 2 356 44 65",
    "sg:postcode":"1500",
    "sg:province":"Vlaams-Brabant",
    "wof:name":"Tadis",
    "wof:placetype":"venue"
},
  "geometry": {"coordinates":[4.207046032,50.7601089478],"type":"Point"}
}