{
  "type": "Feature",
  "properties": {
    "iso:country":"BE",
    "sg:address":"Zwaanhofweg 8",
    "sg:city":"Ieper",
    "sg:orig_category":"Entretien and r\u00e9parations de voitures. V\u00e9hicules automobiles",
    "sg:phone":"+32 57 21 70 80",
    "sg:postcode":"8900",
    "sg:province":"West-Vlaanderen",
    "wof:name":"Autostar Ieper",
    "wof:placetype":"venue"
},
  "geometry": {"coordinates":[2.8816249371,50.8732376099],"type":"Point"}
}