{
  "type": "Feature",
  "properties": {
    "iso:country":"BE",
    "sg:address":"Route D'havelange 118a",
    "sg:city":"Ohey (evelette)",
    "sg:classifiers":[
        {
            "category":"Wholesale",
            "subcategory":"Plants",
            "type":"Manufacturing & Wholesale Goods"
        }
    ],
    "sg:phone":"+32 85 61 31 39",
    "sg:postcode":"5350",
    "sg:province":"Namur",
    "sg:tags":[
        "whol",
        "flower",
        "-",
        "grower"
    ],
    "wof:name":"Adam Michel-florinter Sa",
    "wof:placetype":"venue"
},
  "geometry": {"coordinates":[5.1785721779,50.405418396],"type":"Point"}
}