{
  "type": "Feature",
  "properties": {
    "addr:full":"Vanderschrickstraat 46 Sint-gillis/saint-gilles Bruxelles-Capitale 1060",
    "addr:housenumber":"46",
    "addr:postcode":"1060",
    "addr:street":"Vanderschrickstraat",
    "iso:country":"BE",
    "sg:address":"Vanderschrickstraat 46",
    "sg:city":"Sint-gillis/saint-gilles",
    "sg:orig_category":"Deurwaarders",
    "sg:phone":"+32 2 534 47 05",
    "sg:postcode":"1060",
    "sg:province":"Bruxelles-Capitale",
    "wof:name":"M. Van Eesbeeck",
    "wof:placetype":"venue"
},
  "geometry": {"coordinates":[4.3419327736,50.830947876],"type":"Point"}
}