{
  "type": "Feature",
  "properties": {
    "iso:country":"BE",
    "sg:address":"Leiestraat 57",
    "sg:city":"Zulte",
    "sg:classifiers":[
        {
            "category":"Building & Trades",
            "subcategory":"Landscaping Services",
            "type":"Services"
        }
    ],
    "sg:phone":"+32 9 388 87 78",
    "sg:postcode":"9870",
    "sg:province":"Oost-Vlaanderen",
    "sg:tags":[
        "slaughterer"
    ],
    "wof:name":"Moerman G",
    "wof:placetype":"venue"
},
  "geometry": {"coordinates":[3.4443449974,50.9266014099],"type":"Point"}
}