{
  "type": "Feature",
  "properties": {
    "addr:full":"Jagersweg 15 Meerhout Antwerpen 2450",
    "addr:housenumber":"15",
    "addr:postcode":"2450",
    "addr:street":"Jagersweg",
    "iso:country":"BE",
    "sg:address":"Jagersweg 15",
    "sg:city":"Meerhout",
    "sg:classifiers":[
        {
            "category":"Manufacturing",
            "subcategory":"Building Materials",
            "type":"Manufacturing & Wholesale Goods"
        }
    ],
    "sg:phone":"+32 14 30 87 38",
    "sg:postcode":"2450",
    "sg:province":"Antwerpen",
    "sg:tags":[
        "fixture",
        "store"
    ],
    "wof:name":"Beko Bvba",
    "wof:placetype":"venue"
},
  "geometry": {"coordinates":[5.070950985,51.1329040527],"type":"Point"}
}