{
  "type": "Feature",
  "properties": {
    "iso:country":"BE",
    "sg:address":"Rue Max Lambert 37 Box 9",
    "sg:city":"Charleroi (marchienne-au-pont)",
    "sg:classifiers":[
        {
            "category":"Wholesale",
            "subcategory":"Wine & Distilled Alcoholic Beverages",
            "type":"Manufacturing & Wholesale Goods"
        }
    ],
    "sg:phone":"+32 71 36 40 03",
    "sg:postcode":"6030",
    "sg:province":"Hainaut",
    "sg:tags":[
        "whol",
        "-",
        "spirit",
        "mfg"
    ],
    "wof:name":"Maison Lempereur Scris",
    "wof:placetype":"venue"
},
  "geometry": {"coordinates":[4.3893480301,50.3980827332],"type":"Point"}
}