{
  "type": "Feature",
  "properties": {
    "iso:country":"BE",
    "sg:address":"Pronkenbergstraat 29e",
    "sg:city":"Kontich",
    "sg:classifiers":[
        {
            "category":"Manufacturing",
            "subcategory":"Signs",
            "type":"Manufacturing & Wholesale Goods"
        }
    ],
    "sg:phone":"+32 3 459 85 49",
    "sg:postcode":"2550",
    "sg:province":"Antwerpen",
    "sg:tags":[
        "-",
        "illuminated"
    ],
    "wof:name":"Image Wizard Nv",
    "wof:placetype":"venue"
},
  "geometry": {"coordinates":[4.4674301147,51.1273384094],"type":"Point"}
}