{
  "type": "Feature",
  "properties": {
    "addr:full":"Noordzandstraat 71 Brugge West-Vlaanderen 8000",
    "addr:housenumber":"71",
    "addr:postcode":"8000",
    "addr:street":"Noordzandstraat",
    "iso:country":"BE",
    "sg:address":"Noordzandstraat 71",
    "sg:city":"Brugge",
    "sg:orig_category":"Herenkledingzaken",
    "sg:phone":"+32 50 33 46 60",
    "sg:postcode":"8000",
    "sg:province":"West-Vlaanderen",
    "wof:name":"Huis Joker",
    "wof:placetype":"venue"
},
  "geometry": {"coordinates":[3.2190070152,51.2064247131],"type":"Point"}
}