{
  "type": "Feature",
  "properties": {
    "addr:full":"Kiezelstraat 98 Hasselt Limburg 3500",
    "addr:housenumber":"98",
    "addr:postcode":"3500",
    "addr:street":"Kiezelstraat",
    "iso:country":"BE",
    "sg:address":"Kiezelstraat 98",
    "sg:city":"Hasselt",
    "sg:orig_category":"Banques and organismes de cr\u00e9dit",
    "sg:phone":"+32 11 22 31 86",
    "sg:postcode":"3500",
    "sg:province":"Limburg",
    "wof:name":"Kbc",
    "wof:placetype":"venue"
},
  "geometry": {"coordinates":[5.373770237,50.9294090271],"type":"Point"}
}