{
  "type": "Feature",
  "properties": {
    "addr:full":"Rue De La Caillouti\u00e8re 67 Brugelette (attre) Hainaut 7941",
    "addr:housenumber":"67",
    "addr:postcode":"7941",
    "addr:street":"Rue De La Cailloutie\u0300Re",
    "iso:country":"BE",
    "sg:address":"Rue De La Caillouti\u00e8re 67",
    "sg:city":"Brugelette (attre)",
    "sg:classifiers":[
        {
            "category":"Communications",
            "type":"Services"
        }
    ],
    "sg:phone":"+32 68 45 54 47",
    "sg:postcode":"7941",
    "sg:province":"Hainaut",
    "sg:tags":[
        "translator"
    ],
    "wof:name":"Prd Research",
    "wof:placetype":"venue"
},
  "geometry": {"coordinates":[3.8368890285,50.6060142517],"type":"Point"}
}