{
  "type": "Feature",
  "properties": {
    "iso:country":"BE",
    "sg:address":"Rijksweg 15ba",
    "sg:city":"Bornem",
    "sg:orig_category":"Boekhouders",
    "sg:phone":"+32 3 890 66 26",
    "sg:postcode":"2880",
    "sg:province":"Antwerpen",
    "wof:name":"Peter Rogiest",
    "wof:placetype":"venue"
},
  "geometry": {"coordinates":[4.2638149261,51.0936470032],"type":"Point"}
}