{
  "type": "Feature",
  "properties": {
    "addr:full":"Kroonstraat 18 Brugge West-Vlaanderen 8000",
    "addr:housenumber":"18",
    "addr:postcode":"8000",
    "addr:street":"Kroonstraat",
    "iso:country":"BE",
    "sg:address":"Kroonstraat 18",
    "sg:city":"Brugge",
    "sg:orig_category":"Advocaten and juridische adviseurs",
    "sg:phone":"+32 50 32 13 10",
    "sg:postcode":"8000",
    "sg:province":"West-Vlaanderen",
    "wof:name":"K. Missiaen",
    "wof:placetype":"venue"
},
  "geometry": {"coordinates":[3.2096400261,51.2172966003],"type":"Point"}
}