{
  "type": "Feature",
  "properties": {
    "addr:full":"Koolkerkse Wegel 6 Brugge (dudzele) West-Vlaanderen 8380",
    "addr:housenumber":"6",
    "addr:postcode":"8380",
    "addr:street":"Koolkerkse Wegel",
    "iso:country":"BE",
    "sg:address":"Koolkerkse Wegel 6",
    "sg:city":"Brugge (dudzele)",
    "sg:classifiers":[
        {
            "category":"Building & Trades",
            "subcategory":"Landscaping Services",
            "type":"Services"
        }
    ],
    "sg:phone":"+32 475 42 87 49",
    "sg:postcode":"8380",
    "sg:province":"West-Vlaanderen",
    "sg:tags":[
        "gardening",
        "garden",
        "maintenance"
    ],
    "wof:name":"Tuinen Dirk",
    "wof:placetype":"venue"
},
  "geometry": {"coordinates":[3.2288448811,51.2742958069],"type":"Point"}
}