{
  "type": "Feature",
  "properties": {
    "addr:full":"Wijnveld 253 Sint-niklaas Oost-Vlaanderen 9112",
    "addr:housenumber":"253",
    "addr:postcode":"9112",
    "addr:street":"Wijnveld",
    "iso:country":"BE",
    "sg:address":"Wijnveld 253",
    "sg:city":"Sint-niklaas",
    "sg:orig_category":"Enseignement maternel and primaire",
    "sg:phone":"+32 3 772 20 93",
    "sg:postcode":"9112",
    "sg:province":"Oost-Vlaanderen",
    "wof:name":"Vrije Kleuterschool",
    "wof:placetype":"venue"
},
  "geometry": {"coordinates":[4.0417251587,51.156879425],"type":"Point"}
}