{
  "type": "Feature",
  "properties": {
    "iso:country":"BE",
    "sg:address":"Rue Du Rossignol 731",
    "sg:city":"Dour",
    "sg:orig_category":"Entretien and r\u00e9parations de voitures. R\u00e9cup\u00e9ration de mati\u00e8res m\u00e9talliques recyclables and d\u00e9moliss",
    "sg:phone":"+32 65 65 33 62",
    "sg:postcode":"7370",
    "sg:province":"Hainaut",
    "wof:name":"Philippe Basecq",
    "wof:placetype":"venue"
},
  "geometry": {"coordinates":[3.7869300842,50.3984985352],"type":"Point"}
}