{
  "type": "Feature",
  "properties": {
    "addr:full":"Latemdreef 77 Zwalm Oost-Vlaanderen 9630",
    "addr:housenumber":"77",
    "addr:postcode":"9630",
    "addr:street":"Latemdreef;Oost-Vlaanderen",
    "iso:country":"BE",
    "sg:address":"Latemdreef 77",
    "sg:city":"Zwalm",
    "sg:orig_category":"Orphelinats. Instituts pour enfants en difficult\u00e9",
    "sg:phone":"+32 55 49 94 08",
    "sg:postcode":"9630",
    "sg:province":"Oost-Vlaanderen",
    "wof:name":"Huize Ten Berg",
    "wof:placetype":"venue"
},
  "geometry": {"coordinates":[3.7057631016,50.8891639709],"type":"Point"}
}