{
  "type": "Feature",
  "properties": {
    "addr:full":"Veldstraat 73 Hasselt Limburg 3500",
    "addr:housenumber":"73",
    "addr:postcode":"3500",
    "addr:street":"Veldstraat",
    "iso:country":"BE",
    "sg:address":"Veldstraat 73",
    "sg:city":"Hasselt",
    "sg:classifiers":[
        {
            "category":"Cafe",
            "type":"Food & Drink"
        }
    ],
    "sg:phone":"+32 11 28 15 10",
    "sg:postcode":"3500",
    "sg:province":"Limburg",
    "sg:tags":[
        "caf\u00e9s"
    ],
    "wof:name":"Jean-pierre Philippaerts",
    "wof:placetype":"venue"
},
  "geometry": {"coordinates":[5.3095211983,50.9300422668],"type":"Point"}
}