{
  "type": "Feature",
  "properties": {
    "addr:full":"Rue H\u00f4tel Des Monnaies 89 St. Gilles Bruxelles-Capitale 1060",
    "addr:housenumber":"89",
    "addr:postcode":"1060",
    "addr:street":"Rue Ho\u0302Tel Des Monnaies",
    "iso:country":"BE",
    "sg:address":"Rue H\u00f4tel Des Monnaies 89",
    "sg:city":"St. Gilles",
    "sg:classifiers":[
        {
            "category":"Banks & Credit Unions",
            "subcategory":"Bank",
            "type":"Services"
        }
    ],
    "sg:phone":"+32 2 538 40 32",
    "sg:postcode":"1060",
    "sg:province":"Bruxelles-Capitale",
    "wof:name":"Aslk-cger Bank",
    "wof:placetype":"venue"
},
  "geometry": {"coordinates":[4.3480110168,50.8306236267],"type":"Point"}
}