{
  "type": "Feature",
  "properties": {
    "addr:full":"Rue D'erez\u00c9e 41b Manhay Luxembourg 6960",
    "addr:housenumber":"41b",
    "addr:postcode":"6960",
    "addr:street":"Rue D'Ereze \u0301E",
    "iso:country":"BE",
    "sg:address":"Rue D'erez\u00c9e 41b",
    "sg:city":"Manhay",
    "sg:classifiers":[
        {
            "category":"Personal",
            "subcategory":"Beauty Salon",
            "type":"Services"
        }
    ],
    "sg:phone":"+32 86 45 55 47",
    "sg:postcode":"6960",
    "sg:province":"Luxembourg",
    "sg:tags":[
        "de",
        "coiffure"
    ],
    "wof:name":"Coiffure Marielle",
    "wof:placetype":"venue"
},
  "geometry": {"coordinates":[5.6574630737,50.2906341553],"type":"Point"}
}