{
  "type": "Feature",
  "properties": {
    "addr:full":"Polderstraat 39 Ravels (weelde) Antwerpen 2381",
    "addr:housenumber":"39",
    "addr:postcode":"2381",
    "addr:street":"Polderstraat",
    "iso:country":"BE",
    "sg:address":"Polderstraat 39",
    "sg:city":"Ravels (weelde)",
    "sg:classifiers":[
        {
            "category":"Farming",
            "subcategory":"Livestock Farm",
            "type":"Manufacturing & Wholesale Goods"
        }
    ],
    "sg:phone":"+32 14 65 68 79",
    "sg:postcode":"2381",
    "sg:province":"Antwerpen",
    "sg:tags":[
        "poultry",
        "rabbit"
    ],
    "wof:name":"Geba Bvba",
    "wof:placetype":"venue"
},
  "geometry": {"coordinates":[5.006374836,51.4099845886],"type":"Point"}
}