{
  "type": "Feature",
  "properties": {
    "addr:full":"Av De L'independance 59 Wandre Li\u00e8ge 4020",
    "addr:housenumber":"59",
    "addr:postcode":"4020",
    "addr:street":"Av De L'Independance",
    "iso:country":"BE",
    "sg:address":"Av De L'independance 59",
    "sg:city":"Wandre",
    "sg:classifiers":[
        {
            "category":"Manufacturing",
            "subcategory":"Chemicals & Compounds",
            "type":"Manufacturing & Wholesale Goods"
        }
    ],
    "sg:phone":"+32 4 362 79 90",
    "sg:postcode":"4020",
    "sg:province":"Li\u00e8ge",
    "sg:tags":[
        "pharmaceutical",
        "energy",
        "chemistry",
        "-",
        "by-product"
    ],
    "wof:name":"Total Fina Elf",
    "wof:placetype":"venue"
},
  "geometry": {"coordinates":[5.6480569839,50.6581420898],"type":"Point"}
}