{
  "type": "Feature",
  "properties": {
    "addr:full":"Lamme Goedzakstraat 17 Gent Oost-Vlaanderen 9050",
    "addr:housenumber":"17",
    "addr:postcode":"9050",
    "addr:street":"Goedzakstraat;Oost-Vlaanderen",
    "iso:country":"BE",
    "sg:address":"Lamme Goedzakstraat 17",
    "sg:city":"Gent",
    "sg:orig_category":"Paramedische behandelingen",
    "sg:phone":"+32 9 231 50 79",
    "sg:postcode":"9050",
    "sg:province":"Oost-Vlaanderen",
    "wof:name":"Marleen Verspeeten",
    "wof:placetype":"venue"
},
  "geometry": {"coordinates":[3.7764079571,51.0344963074],"type":"Point"}
}