{
  "type": "Feature",
  "properties": {
    "iso:country":"BE",
    "sg:address":"Rue Beckers 10",
    "sg:city":"Bruxelles (etterbeek)",
    "sg:classifiers":[
        {
            "category":"Utilities",
            "subcategory":"Telephone",
            "type":"Services"
        }
    ],
    "sg:phone":"+32 2 644 07 54",
    "sg:postcode":"1040",
    "sg:province":"Bruxelles-Capitale",
    "sg:tags":[
        "-",
        "internet"
    ],
    "wof:name":"I.d.informatique",
    "wof:placetype":"venue"
},
  "geometry": {"coordinates":[4.3865680695,50.8279876709],"type":"Point"}
}