{
  "type": "Feature",
  "properties": {
    "addr:full":"Avenue De L'industrie 30 Huy (tihange) Li\u00e8ge 4500",
    "addr:housenumber":"30",
    "addr:postcode":"4500",
    "addr:street":"Avenue De L'Industrie;Tihange",
    "iso:country":"BE",
    "sg:address":"Avenue De L'industrie 30",
    "sg:city":"Huy (tihange)",
    "sg:classifiers":[
        {
            "category":"Retail",
            "subcategory":"Car Wash",
            "type":"Services"
        }
    ],
    "sg:phone":"+32 85 27 11 12",
    "sg:postcode":"4500",
    "sg:province":"Li\u00e8ge",
    "sg:tags":[
        "automobile",
        "washing",
        "-",
        "truck"
    ],
    "wof:name":"Car-wash De Tihange Sa",
    "wof:placetype":"venue"
},
  "geometry": {"coordinates":[5.2638292313,50.5326728821],"type":"Point"}
}