{
  "type": "Feature",
  "properties": {
    "addr:full":"Oostendse Steenweg 146 Brugge West-Vlaanderen 8000",
    "addr:housenumber":"146",
    "addr:postcode":"8000",
    "addr:street":"Oostendse Steenweg",
    "iso:country":"BE",
    "sg:address":"Oostendse Steenweg 146",
    "sg:city":"Brugge",
    "sg:orig_category":"Newspapers, magazines, periodicals - Distribution",
    "sg:phone":"+32 50 31 95 85",
    "sg:postcode":"8000",
    "sg:province":"West-Vlaanderen",
    "wof:name":"V.d.m.",
    "wof:placetype":"venue"
},
  "geometry": {"coordinates":[3.1900799274,51.2292709351],"type":"Point"}
}