{
  "type": "Feature",
  "properties": {
    "addr:full":"Lendedreef 74 Anzegem (vichte) West-Vlaanderen 8570",
    "addr:housenumber":"74",
    "addr:postcode":"8570",
    "addr:street":"Lendedreef",
    "iso:country":"BE",
    "sg:address":"Lendedreef 74",
    "sg:city":"Anzegem (vichte)",
    "sg:classifiers":[
        {
            "category":"Real Estate",
            "subcategory":"Architect",
            "type":"Services"
        }
    ],
    "sg:phone":"+32 56 77 94 23",
    "sg:postcode":"8570",
    "sg:province":"West-Vlaanderen",
    "wof:name":"Bert L",
    "wof:placetype":"venue"
},
  "geometry": {"coordinates":[3.3865039349,50.8385734558],"type":"Point"}
}