{
  "type": "Feature",
  "properties": {
    "iso:country":"BE",
    "sg:address":"Route De Verviers 80",
    "sg:city":"Eupen (grand)",
    "sg:orig_category":"Autokeuringen",
    "sg:phone":"+32 87 55 46 13",
    "sg:postcode":"4700",
    "sg:province":"Li\u00e8ge",
    "wof:name":"Contr\u00d4le Technique Automobile",
    "wof:placetype":"venue"
},
  "geometry": {"coordinates":[6.0190057755,50.6318702698],"type":"Point"}
}