{
  "type": "Feature",
  "properties": {
    "iso:country":"BE",
    "sg:address":"Avenue De La Closeraie 63",
    "sg:city":"Li\u00e8ge 1 (rocourt)",
    "sg:classifiers":[
        {
            "category":"Organizations",
            "subcategory":"Community Association",
            "type":"Services"
        }
    ],
    "sg:phone":"+32 4 225 10 64",
    "sg:postcode":"4000",
    "sg:province":"Li\u00e8ge",
    "sg:tags":[
        "work",
        "assembly"
    ],
    "wof:name":"Houssa & Boucha Industries",
    "wof:placetype":"venue"
},
  "geometry": {"coordinates":[5.5503492355,50.6670722961],"type":"Point"}
}