{
  "type": "Feature",
  "properties": {
    "iso:country":"BE",
    "sg:address":"Watermolenstr 16",
    "sg:city":"Aalst",
    "sg:orig_category":"Metallurgy and Metalworking Plastics Rubber Wood Wood and Furniture",
    "sg:phone":"+32 53 64 76 70",
    "sg:postcode":"9320",
    "sg:province":"Oost-Vlaanderen",
    "wof:name":"Jewe Products Nv",
    "wof:placetype":"venue"
},
  "geometry": {"coordinates":[4.0553851128,50.9209976196],"type":"Point"}
}