{
  "type": "Feature",
  "properties": {
    "addr:full":"Sint-jacobsmarkt 12ba Antwerpen Antwerpen 2000",
    "addr:housenumber":"12ba",
    "addr:postcode":"2000",
    "addr:street":"Sint-Jacobsmarkt",
    "iso:country":"BE",
    "sg:address":"Sint-jacobsmarkt 12ba",
    "sg:city":"Antwerpen",
    "sg:classifiers":[
        {
            "category":"Restaurant",
            "type":"Food & Drink"
        }
    ],
    "sg:phone":"+32 3 226 21 60",
    "sg:postcode":"2000",
    "sg:province":"Antwerpen",
    "wof:name":"Krokant",
    "wof:placetype":"venue"
},
  "geometry": {"coordinates":[4.4103899002,51.2204627991],"type":"Point"}
}