{
  "type": "Feature",
  "properties": {
    "iso:country":"BE",
    "sg:address":"Hortweideweg 46",
    "sg:city":"Zonhoven",
    "sg:orig_category":"Kapsalons",
    "sg:phone":"+32 11 81 64 14",
    "sg:postcode":"3520",
    "sg:province":"Limburg",
    "wof:name":"Coiffure Chris",
    "wof:placetype":"venue"
},
  "geometry": {"coordinates":[5.3572478294,51.0011558533],"type":"Point"}
}