{
  "type": "Feature",
  "properties": {
    "iso:country":"BE",
    "sg:address":"Brusselbaan 78b1",
    "sg:city":"Sint-pieters-leeuw",
    "sg:classifiers":[
        {
            "category":"Food & Beverages",
            "subcategory":"Fruits & Vegetables",
            "type":"Retail Goods"
        }
    ],
    "sg:phone":"+32 2 377 18 91",
    "sg:postcode":"1600",
    "sg:province":"Vlaams-Brabant",
    "sg:tags":[
        "groenten"
    ],
    "wof:name":"Willy Swartenbroeck",
    "wof:placetype":"venue"
},
  "geometry": {"coordinates":[4.2855529785,50.8062553406],"type":"Point"}
}