{
  "type": "Feature",
  "properties": {
    "addr:full":"Gentse Steenweg 137 Zottegem (grotenberge) Oost-Vlaanderen 9620",
    "addr:housenumber":"137",
    "addr:postcode":"9620",
    "addr:street":"Gentse Steenweg",
    "iso:country":"BE",
    "sg:address":"Gentse Steenweg 137",
    "sg:city":"Zottegem (grotenberge)",
    "sg:classifiers":[
        {
            "category":"Bars & Pubs",
            "type":"Food & Drink"
        }
    ],
    "sg:phone":"+32 9 360 89 03",
    "sg:postcode":"9620",
    "sg:province":"Oost-Vlaanderen",
    "wof:name":"Verval ('t)",
    "wof:placetype":"venue"
},
  "geometry": {"coordinates":[3.8366339207,50.8708877563],"type":"Point"}
}