{
  "type": "Feature",
  "properties": {
    "iso:country":"BE",
    "sg:address":"Overslag 46",
    "sg:city":"Wachtebeke",
    "sg:classifiers":[
        {
            "category":"Fast Food",
            "type":"Food & Drink"
        }
    ],
    "sg:phone":"+32 9 342 92 19",
    "sg:postcode":"9185",
    "sg:province":"Oost-Vlaanderen",
    "sg:tags":[
        "meeneem",
        "restaurant"
    ],
    "wof:name":"Frituur De Grenspost",
    "wof:placetype":"venue"
},
  "geometry": {"coordinates":[3.8736629486,51.2067909241],"type":"Point"}
}