{
  "type": "Feature",
  "properties": {
    "addr:full":"Wachtebekestraat 35 Zelzate Oost-Vlaanderen 9060",
    "addr:housenumber":"35",
    "addr:postcode":"9060",
    "addr:street":"Wachtebekestraat",
    "iso:country":"BE",
    "sg:address":"Wachtebekestraat 35",
    "sg:city":"Zelzate",
    "sg:classifiers":[
        {
            "category":"Cafe",
            "type":"Food & Drink"
        }
    ],
    "sg:phone":"+32 9 342 98 67",
    "sg:postcode":"9060",
    "sg:province":"Oost-Vlaanderen",
    "sg:tags":[
        "caf\u00e9s"
    ],
    "wof:name":"Marc Van Loo",
    "wof:placetype":"venue"
},
  "geometry": {"coordinates":[3.8168730736,51.2002716064],"type":"Point"}
}