{
  "type": "Feature",
  "properties": {
    "addr:full":"Hansbekedorp 42 Nevele (hansbeke) Oost-Vlaanderen 9850",
    "addr:housenumber":"42",
    "addr:postcode":"9850",
    "addr:street":"Hansbekedorp",
    "iso:country":"BE",
    "sg:address":"Hansbekedorp 42",
    "sg:city":"Nevele (hansbeke)",
    "sg:classifiers":[
        {
            "category":"Shopping",
            "subcategory":"Clothing, Apparel, & Fashions",
            "type":"Retail Goods"
        }
    ],
    "sg:phone":"+32 9 371 92 53",
    "sg:postcode":"9850",
    "sg:province":"Oost-Vlaanderen",
    "sg:tags":[
        "underwear",
        "lingerie",
        "-"
    ],
    "wof:name":"Carmell",
    "wof:placetype":"venue"
},
  "geometry": {"coordinates":[3.5355920792,51.0759086609],"type":"Point"}
}