{
  "type": "Feature",
  "properties": {
    "addr:full":"Wilderstraat 11ba Galmaarden Vlaams-Brabant 1570",
    "addr:housenumber":"11ba",
    "addr:postcode":"1570",
    "addr:street":"Wilderstraat",
    "iso:country":"BE",
    "sg:address":"Wilderstraat 11ba",
    "sg:city":"Galmaarden",
    "sg:orig_category":"Peinture. Textiles. Rev\u00eatements pour sols and murs. Eclairage et \u00e9quipements du foyer",
    "sg:phone":"+32 54 58 65 28",
    "sg:postcode":"1570",
    "sg:province":"Vlaams-Brabant",
    "wof:name":"Lodewijk Boelaert",
    "wof:placetype":"venue"
},
  "geometry": {"coordinates":[3.9456350803,50.7576675415],"type":"Point"}
}