{
  "type": "Feature",
  "properties": {
    "addr:full":"Halsesteenweg 159 Ninove Oost-Vlaanderen 9402",
    "addr:housenumber":"159",
    "addr:postcode":"9402",
    "addr:street":"Halsesteenweg",
    "iso:country":"BE",
    "sg:address":"Halsesteenweg 159",
    "sg:city":"Ninove",
    "sg:orig_category":"Rundveehouders",
    "sg:phone":"+32 54 33 31 02",
    "sg:postcode":"9402",
    "sg:province":"Oost-Vlaanderen",
    "wof:name":"Jozef Cornelis",
    "wof:placetype":"venue"
},
  "geometry": {"coordinates":[4.0395750999,50.8249015808],"type":"Point"}
}