{
  "type": "Feature",
  "properties": {
    "iso:country":"BE",
    "sg:address":"Kuipersstraat 11",
    "sg:city":"Roeselare",
    "sg:classifiers":[
        {
            "category":"Building & Trades",
            "subcategory":"Pest Control",
            "type":"Services"
        }
    ],
    "sg:phone":"+32 51 22 06 67",
    "sg:postcode":"8800",
    "sg:province":"West-Vlaanderen",
    "sg:tags":[
        "painting",
        "contractor"
    ],
    "wof:name":"Rooryck D",
    "wof:placetype":"venue"
},
  "geometry": {"coordinates":[3.1071100235,50.9534683228],"type":"Point"}
}