{
  "type": "Feature",
  "properties": {
    "addr:full":"Westerlaan 71 Waregem West-Vlaanderen 8790",
    "addr:housenumber":"71",
    "addr:postcode":"8790",
    "addr:street":"Westerlaan",
    "iso:country":"BE",
    "sg:address":"Westerlaan 71",
    "sg:city":"Waregem",
    "sg:orig_category":"Boissons",
    "sg:phone":"+32 56 61 58 41",
    "sg:postcode":"8790",
    "sg:province":"West-Vlaanderen",
    "wof:name":"Vaernewyck Peter",
    "wof:placetype":"venue"
},
  "geometry": {"coordinates":[3.4220790863,50.8888244629],"type":"Point"}
}