{
  "type": "Feature",
  "properties": {
    "addr:full":"Papegaaistraat 80 Gent Oost-Vlaanderen 9000",
    "addr:housenumber":"80",
    "addr:postcode":"9000",
    "addr:street":"Papegaaistraat;Oost-Vlaanderen",
    "iso:country":"BE",
    "sg:address":"Papegaaistraat 80",
    "sg:city":"Gent",
    "sg:classifiers":[
        {
            "category":"Health Services",
            "subcategory":"Doctor",
            "type":"Services"
        }
    ],
    "sg:phone":"+32 9 225 09 20",
    "sg:postcode":"9000",
    "sg:province":"Oost-Vlaanderen",
    "sg:tags":[
        "medicinephysicians",
        "surgeon"
    ],
    "wof:name":"Blindeman E",
    "wof:placetype":"venue"
},
  "geometry": {"coordinates":[3.711990118,51.0507202148],"type":"Point"}
}