{
  "type": "Feature",
  "properties": {
    "addr:full":"Rue Guillaume Stocq 18 Ixelles Bruxelles-Capitale 1050",
    "addr:housenumber":"18",
    "addr:postcode":"1050",
    "addr:street":"Rue Guillaume Stocq",
    "iso:country":"BE",
    "sg:address":"Rue Guillaume Stocq 18",
    "sg:city":"Ixelles",
    "sg:classifiers":[
        {
            "category":"Arena",
            "subcategory":"Sports Club",
            "type":"Entertainment"
        }
    ],
    "sg:phone":"+32 2 644 30 74",
    "sg:postcode":"1050",
    "sg:province":"Bruxelles-Capitale",
    "sg:tags":[
        "de"
    ],
    "wof:name":"E.p.s.m",
    "wof:placetype":"venue"
},
  "geometry": {"coordinates":[4.3754191399,50.8240203857],"type":"Point"}
}