{
  "type": "Feature",
  "properties": {
    "iso:country":"BE",
    "sg:address":"Rue Du Haut-bois 44",
    "sg:city":"Mons",
    "sg:orig_category":"Antiquit\u00e9s",
    "sg:phone":"+32 65 35 55 78",
    "sg:postcode":"7000",
    "sg:province":"Hainaut",
    "wof:name":"Maison My-tho",
    "wof:placetype":"venue"
},
  "geometry": {"coordinates":[3.9552969933,50.4532165527],"type":"Point"}
}