{
  "type": "Feature",
  "properties": {
    "addr:full":"Dijkstraat 40 Heusden-zolder Limburg 3550",
    "addr:housenumber":"40",
    "addr:postcode":"3550",
    "addr:street":"Dijkstraat",
    "iso:country":"BE",
    "sg:address":"Dijkstraat 40",
    "sg:city":"Heusden-zolder",
    "sg:orig_category":"Animations diverses",
    "sg:phone":"+32 11 42 90 60",
    "sg:postcode":"3550",
    "sg:province":"Limburg",
    "wof:name":"D.j. Lubino Weyens",
    "wof:placetype":"venue"
},
  "geometry": {"coordinates":[5.2547659874,51.0342903137],"type":"Point"}
}