{
  "type": "Feature",
  "properties": {
    "iso:country":"BE",
    "sg:address":"Rue Du Ch\u00e2telain 1",
    "sg:city":"Paliseul (maissin)",
    "sg:classifiers":[
        {
            "category":"Banks & Credit Unions",
            "subcategory":"Investment Brokerage",
            "type":"Services"
        }
    ],
    "sg:phone":"+32 61 65 64 41",
    "sg:postcode":"6852",
    "sg:province":"Luxembourg",
    "sg:tags":[
        "repair",
        "-",
        "installation",
        "sanitary",
        "article"
    ],
    "wof:name":"Piquard A",
    "wof:placetype":"venue"
},
  "geometry": {"coordinates":[5.1785240173,49.9646186829],"type":"Point"}
}