{
  "type": "Feature",
  "properties": {
    "iso:country":"BE",
    "sg:address":"Hundelgemsesteenweg 18",
    "sg:city":"Merelbeke",
    "sg:orig_category":"Non-Classified Establishments",
    "sg:phone":"+32 9 230 09 85",
    "sg:postcode":"9820",
    "sg:province":"Oost-Vlaanderen",
    "wof:name":"Aquadis Bvba",
    "wof:placetype":"venue"
},
  "geometry": {"coordinates":[3.7534201145,51.0174484253],"type":"Point"}
}