{
  "type": "Feature",
  "properties": {
    "iso:country":"BE",
    "sg:address":"Route De Mons 90",
    "sg:city":"Erquelinnes",
    "sg:classifiers":[
        {
            "category":"Freight",
            "type":"Transportation"
        }
    ],
    "sg:phone":"+32 71 55 66 85",
    "sg:postcode":"6560",
    "sg:province":"Hainaut",
    "sg:tags":[
        "-",
        "transport"
    ],
    "wof:name":"Lallemand Fourre",
    "wof:placetype":"venue"
},
  "geometry": {"coordinates":[4.1395797729,50.3097991943],"type":"Point"}
}