{
  "type": "Feature",
  "properties": {
    "iso:country":"BE",
    "sg:address":"Chemin \u00e0 Haies 38",
    "sg:city":"Bernissart (blaton)",
    "sg:classifiers":[
        {
            "category":"Home & Garden",
            "subcategory":"Building Materials",
            "type":"Retail Goods"
        }
    ],
    "sg:phone":"+32 69 56 08 66",
    "sg:postcode":"7321",
    "sg:province":"Hainaut",
    "sg:tags":[
        "window"
    ],
    "wof:name":"Plastic Bois Construct Sprl",
    "wof:placetype":"venue"
},
  "geometry": {"coordinates":[3.6481449604,50.5028533936],"type":"Point"}
}