{
  "type": "Feature",
  "properties": {
    "iso:country":"BE",
    "sg:address":"Veurterstraat 37",
    "sg:city":"Neerpelt",
    "sg:classifiers":[
        {
            "category":"Professional",
            "subcategory":"Computer Services",
            "type":"Services"
        }
    ],
    "sg:postcode":"B-3910",
    "wof:name":"Pixelpanic",
    "wof:placetype":"venue"
},
  "geometry": {"coordinates":[5.4856887,51.2200801],"type":"Point"}
}