{
  "type": "Feature",
  "properties": {
    "addr:full":"Avenue Henri Lepage 30 Wavre Brabant Wallon 1300",
    "addr:housenumber":"30;1300",
    "addr:street":"Avenue Henri Lepage",
    "iso:country":"BE",
    "sg:address":"Avenue Henri Lepage 30",
    "sg:city":"Wavre",
    "sg:orig_category":"V\u00e9t\u00e9rinaires",
    "sg:phone":"+32 10 22 80 52",
    "sg:postcode":"1300",
    "sg:province":"Brabant Wallon",
    "wof:name":"Eric Fauvel",
    "wof:placetype":"venue"
},
  "geometry": {"coordinates":[4.6055521965,50.7207145691],"type":"Point"}
}