{
  "type": "Feature",
  "properties": {
    "iso:country":"BE",
    "sg:address":"Rue Jean Pauly 76",
    "sg:city":"Ans",
    "sg:orig_category":"Sportclubs",
    "sg:phone":"+32 4 246 58 02",
    "sg:postcode":"4432",
    "sg:province":"Li\u00e8ge",
    "wof:name":"T.c. Smash 51",
    "wof:placetype":"venue"
},
  "geometry": {"coordinates":[5.5229811668,50.6669006348],"type":"Point"}
}