{
  "type": "Feature",
  "properties": {
    "addr:full":"Schoolstraat 1a Sint-lievens-houtem Oost-Vlaanderen 9520",
    "addr:housenumber":"1a",
    "addr:postcode":"9520",
    "addr:street":"Schoolstraat",
    "iso:country":"BE",
    "sg:address":"Schoolstraat 1a",
    "sg:city":"Sint-lievens-houtem",
    "sg:orig_category":"Fitnesscentra",
    "sg:phone":"+32 53 62 17 31",
    "sg:postcode":"9520",
    "sg:province":"Oost-Vlaanderen",
    "wof:name":"Fitness Centr. Body-style",
    "wof:placetype":"venue"
},
  "geometry": {"coordinates":[3.8548769951,50.9210014343],"type":"Point"}
}