{
  "type": "Feature",
  "properties": {
    "addr:full":"Tongerlodorp 12 Westerlo (tongerlo) Antwerpen 2260",
    "addr:housenumber":"12",
    "addr:postcode":"2260",
    "addr:street":"Tongerlodorp",
    "iso:country":"BE",
    "sg:address":"Tongerlodorp 12",
    "sg:city":"Westerlo (tongerlo)",
    "sg:classifiers":[
        {
            "category":"Cafe",
            "type":"Food & Drink"
        }
    ],
    "sg:phone":"+32 14 54 38 21",
    "sg:postcode":"2260",
    "sg:province":"Antwerpen",
    "sg:tags":[
        "snack-bars"
    ],
    "wof:name":"Mimosa",
    "wof:placetype":"venue"
},
  "geometry": {"coordinates":[4.9155440331,51.1067276001],"type":"Point"}
}