{
  "type": "Feature",
  "properties": {
    "addr:full":"Rue De Stavelot 4 Liege-centre Li\u00e8ge 4020",
    "addr:housenumber":"4",
    "addr:postcode":"4020",
    "addr:street":"Rue De Stavelot",
    "iso:country":"BE",
    "sg:address":"Rue De Stavelot 4",
    "sg:city":"Liege-centre",
    "sg:orig_category":"Huisdieren and benodigdheden Royal Canin",
    "sg:phone":"+32 41410785",
    "sg:postcode":"4020",
    "sg:province":"Li\u00e8ge",
    "wof:name":"Gerard Christine",
    "wof:placetype":"venue"
},
  "geometry": {"coordinates":[2.4079089165,44.1636695862],"type":"Point"}
}