{
  "type": "Feature",
  "properties": {
    "iso:country":"BE",
    "sg:address":"Minderbroedersstraat 39",
    "sg:city":"Sint-niklaas",
    "sg:orig_category":"Non-Classified Establishments",
    "sg:phone":"+32 3 776 37 91",
    "sg:postcode":"9100",
    "sg:province":"Oost-Vlaanderen",
    "wof:name":"Vrancken Hugo Bvba",
    "wof:placetype":"venue"
},
  "geometry": {"coordinates":[4.1522741318,51.1724205017],"type":"Point"}
}