{
  "type": "Feature",
  "properties": {
    "addr:full":"Rue De Dave 436 Namur (jambes) Namur 5100",
    "addr:housenumber":"436",
    "addr:postcode":"5100",
    "addr:street":"Rue De Dave",
    "iso:country":"BE",
    "sg:address":"Rue De Dave 436",
    "sg:city":"Namur (jambes)",
    "sg:classifiers":[
        {
            "category":"Retail",
            "subcategory":"Repair Shop",
            "type":"Services"
        }
    ],
    "sg:phone":"+32 81 31 27 27",
    "sg:postcode":"5100",
    "sg:province":"Namur",
    "sg:tags":[
        "upholsterer"
    ],
    "wof:name":"Atelier Du Siege L'",
    "wof:placetype":"venue"
},
  "geometry": {"coordinates":[4.8713750839,50.4566345215],"type":"Point"}
}