{
  "type": "Feature",
  "properties": {
    "addr:full":"Rue Lamarck 98 Li\u00c8ge Li\u00e8ge 4000",
    "addr:housenumber":"98",
    "addr:postcode":"4000",
    "addr:street":"Rue Lamarck",
    "iso:country":"BE",
    "sg:address":"Rue Lamarck 98",
    "sg:city":"Li\u00c8ge",
    "sg:orig_category":"Peinture. Rev\u00eatements pour sols and murs",
    "sg:phone":"+32 4 227 65 76",
    "sg:postcode":"4000",
    "sg:province":"Li\u00e8ge",
    "wof:name":"Daniel Dirix",
    "wof:placetype":"venue"
},
  "geometry": {"coordinates":[5.5941739082,50.6521377563],"type":"Point"}
}