{
  "type": "Feature",
  "properties": {
    "iso:country":"BE",
    "sg:address":"Rue Bois De L'abbaye 9-11",
    "sg:city":"Seraing",
    "sg:orig_category":"Non-Classified Establishments",
    "sg:phone":"+32 4 338 52 59",
    "sg:postcode":"4100",
    "sg:province":"Li\u00e8ge",
    "wof:name":"Aaz Discount Center",
    "wof:placetype":"venue"
},
  "geometry": {"coordinates":[5.4965839386,50.6062507629],"type":"Point"}
}