{
  "type": "Feature",
  "properties": {
    "addr:full":"Ruelle Au Ris 9 Ouffet Li\u00e8ge 4590",
    "addr:housenumber":"9",
    "addr:postcode":"4590",
    "addr:street":"Ruelle Au Ris",
    "iso:country":"BE",
    "sg:address":"Ruelle Au Ris 9",
    "sg:city":"Ouffet",
    "sg:orig_category":"Rundveehouders",
    "sg:phone":"+32 86 36 64 84",
    "sg:postcode":"4590",
    "sg:province":"Li\u00e8ge",
    "wof:name":"Jose Godefroid",
    "wof:placetype":"venue"
},
  "geometry": {"coordinates":[5.4272298813,50.4481811523],"type":"Point"}
}