{
  "type": "Feature",
  "properties": {
    "iso:country":"BE",
    "sg:address":"Weststraat 79",
    "sg:city":"Blankenberge",
    "sg:classifiers":[
        {
            "category":"Bars & Pubs",
            "type":"Food & Drink"
        }
    ],
    "sg:phone":"+32 50 41 29 26",
    "sg:postcode":"8370",
    "sg:province":"West-Vlaanderen",
    "wof:name":"Sinatra",
    "wof:placetype":"venue"
},
  "geometry": {"coordinates":[3.127464056,51.3137931824],"type":"Point"}
}