{
  "type": "Feature",
  "properties": {
    "addr:full":"Kirchstrasse 72 Raeren/raeren Li\u00e8ge 4730",
    "addr:housenumber":"72",
    "addr:postcode":"4730",
    "addr:street":"Kirchstrasse",
    "iso:country":"BE",
    "sg:address":"Kirchstrasse 72",
    "sg:city":"Raeren/raeren",
    "sg:orig_category":"Installatie van houten of kunststof schrijnwerk",
    "sg:phone":"+32 87 63 07 64",
    "sg:postcode":"4730",
    "sg:province":"Li\u00e8ge",
    "wof:name":"Edgard Lauffs",
    "wof:placetype":"venue"
},
  "geometry": {"coordinates":[6.0901751518,50.7137184143],"type":"Point"}
}