{
  "type": "Feature",
  "properties": {
    "iso:country":"BE",
    "sg:address":"Rue Des Bois 11",
    "sg:city":"Hamois (mohiville)",
    "sg:classifiers":[
        {
            "category":"Freight",
            "type":"Transportation"
        }
    ],
    "sg:phone":"+32 83 61 14 11",
    "sg:postcode":"5361",
    "sg:province":"Namur",
    "sg:tags":[
        "-",
        "transport"
    ],
    "wof:name":"Lotin Sprl",
    "wof:placetype":"venue"
},
  "geometry": {"coordinates":[5.1844630241,50.323135376],"type":"Point"}
}