{
  "type": "Feature",
  "properties": {
    "iso:country":"BE",
    "sg:address":"Koningin Astridstraat 27",
    "sg:city":"Zedelgem (veldegem)",
    "sg:classifiers":[
        {
            "category":"Real Estate",
            "subcategory":"Real Estate Services",
            "type":"Services"
        }
    ],
    "sg:phone":"+32 50 28 02 65",
    "sg:postcode":"8210",
    "sg:province":"West-Vlaanderen",
    "wof:name":"Immo Hiro",
    "wof:placetype":"venue"
},
  "geometry": {"coordinates":[3.1458399296,51.1376457214],"type":"Point"}
}