{
  "type": "Feature",
  "properties": {
    "addr:full":"Brocquevillel 17 Middelkerke (westende) West-Vlaanderen 8434",
    "addr:housenumber":"17",
    "addr:postcode":"8434",
    "addr:street":"Brocquevillel",
    "iso:country":"BE",
    "sg:address":"Brocquevillel 17",
    "sg:city":"Middelkerke (westende)",
    "sg:classifiers":[
        {
            "category":"Travel",
            "subcategory":"Hotels & Motels",
            "type":"Entertainment"
        }
    ],
    "sg:phone":"+32 59 30 08 08",
    "sg:postcode":"8434",
    "sg:province":"West-Vlaanderen",
    "wof:name":"Roi Soleil",
    "wof:placetype":"venue"
},
  "geometry": {"coordinates":[2.7569050789,51.1488685608],"type":"Point"}
}