{
  "type": "Feature",
  "properties": {
    "addr:full":"Sint-margrietestraat 127 Sint-laureins Oost-Vlaanderen 9981",
    "addr:housenumber":"127",
    "addr:postcode":"9981",
    "addr:street":"Sint-Margrietestraat",
    "iso:country":"BE",
    "sg:address":"Sint-margrietestraat 127",
    "sg:city":"Sint-laureins",
    "sg:classifiers":[
        {
            "category":"Food & Beverages",
            "subcategory":"Fruits & Vegetables",
            "type":"Retail Goods"
        }
    ],
    "sg:phone":"+32 9 379 81 45",
    "sg:postcode":"9981",
    "sg:province":"Oost-Vlaanderen",
    "sg:tags":[
        "l\u00e9gumes",
        "gr"
    ],
    "wof:name":"Fa. Buysse H. & R.",
    "wof:placetype":"venue"
},
  "geometry": {"coordinates":[3.5405299664,51.284778595],"type":"Point"}
}