{
  "type": "Feature",
  "properties": {
    "iso:country":"BE",
    "sg:address":"Staatsbaan 5",
    "sg:city":"Maldegem (adegem)",
    "sg:classifiers":[
        {
            "category":"Autos & Motor Vehicles",
            "subcategory":"Fuel & Gas Station",
            "type":"Retail Goods"
        }
    ],
    "sg:phone":"+32 50 71 65 30",
    "sg:postcode":"9991",
    "sg:province":"Oost-Vlaanderen",
    "wof:name":"Ceulenaere Nv",
    "wof:placetype":"venue"
},
  "geometry": {"coordinates":[3.476596117,51.2051582336],"type":"Point"}
}