{
  "type": "Feature",
  "properties": {
    "addr:full":"Torhoutsesteenweg 48 Oostende West-Vlaanderen 8400",
    "addr:housenumber":"48",
    "addr:postcode":"8400",
    "addr:street":"Torhoutsesteenweg",
    "iso:country":"BE",
    "sg:address":"Torhoutsesteenweg 48",
    "sg:city":"Oostende",
    "sg:orig_category":"Royal Canin. Animaux domestiques and accessoires",
    "sg:phone":"+32 59 51 78 96",
    "sg:postcode":"8400",
    "sg:province":"West-Vlaanderen",
    "wof:name":"Bvba Dierenparadijs",
    "wof:placetype":"venue"
},
  "geometry": {"coordinates":[2.9097061157,51.2259597778],"type":"Point"}
}