{
  "type": "Feature",
  "properties": {
    "addr:full":"Avenue Winston Churchill 108 Bruxelles (uccle) Bruxelles-Capitale 1180",
    "addr:housenumber":"108",
    "addr:postcode":"1180",
    "addr:street":"Avenue Winston Churchill",
    "iso:country":"BE",
    "sg:address":"Avenue Winston Churchill 108",
    "sg:city":"Bruxelles (uccle)",
    "sg:orig_category":"Non-Classified Establishments",
    "sg:phone":"+32 2 344 11 98",
    "sg:postcode":"1180",
    "sg:province":"Bruxelles-Capitale",
    "wof:name":"Diffumat Sa",
    "wof:placetype":"venue"
},
  "geometry": {"coordinates":[4.3530869484,50.8122673035],"type":"Point"}
}