{
  "type": "Feature",
  "properties": {
    "addr:full":"Stationsstraat 40 Waregem West-Vlaanderen 8790",
    "addr:housenumber":"40",
    "addr:postcode":"8790",
    "addr:street":"Stationsstraat",
    "iso:country":"BE",
    "sg:address":"Stationsstraat 40",
    "sg:city":"Waregem",
    "sg:orig_category":"Plomberie, chauffage and installations sanitaires. Articles de jardin. Rev\u00eatements de sols and murs.",
    "sg:phone":"+32 56 60 47 96",
    "sg:postcode":"8790",
    "sg:province":"West-Vlaanderen",
    "wof:name":"Brico",
    "wof:placetype":"venue"
},
  "geometry": {"coordinates":[3.4308209419,50.8885002136],"type":"Point"}
}