{
  "type": "Feature",
  "properties": {
    "addr:full":"Avenue Emile De Beco 25 Elsene/ixelles Bruxelles-Capitale 1050",
    "addr:housenumber":"25",
    "addr:postcode":"1050",
    "addr:street":"Avenue Emile De Beco",
    "iso:country":"BE",
    "sg:address":"Avenue Emile De Beco 25",
    "sg:city":"Elsene/ixelles",
    "sg:orig_category":"Banques and organismes de cr\u00e9dit",
    "sg:phone":"+32 2 640 43 87",
    "sg:postcode":"1050",
    "sg:province":"Bruxelles-Capitale",
    "wof:name":"Fortis",
    "wof:placetype":"venue"
},
  "geometry": {"coordinates":[4.3810558319,50.8231048584],"type":"Point"}
}