{
  "type": "Feature",
  "properties": {
    "iso:country":"BE",
    "sg:address":"Hallestraat 26",
    "sg:city":"Vorst/forest",
    "sg:orig_category":"Herstelling and restauratie van meubelen Verlichting and huishoudartikelen",
    "sg:phone":"+32 2 332 30 20",
    "sg:postcode":"1190",
    "sg:province":"Bruxelles-Capitale",
    "wof:name":"Van Biesen",
    "wof:placetype":"venue"
},
  "geometry": {"coordinates":[4.3138241768,50.8087882996],"type":"Point"}
}