{
  "type": "Feature",
  "properties": {
    "addr:full":"Gentsesteenweg 63 Deinze Oost-Vlaanderen 9800",
    "addr:housenumber":"63",
    "addr:postcode":"9800",
    "addr:street":"Gentsesteenweg",
    "iso:country":"BE",
    "sg:address":"Gentsesteenweg 63",
    "sg:city":"Deinze",
    "sg:classifiers":[
        {
            "category":"Retail",
            "subcategory":"Auto Repair",
            "type":"Services"
        }
    ],
    "sg:phone":"+32 9 386 11 73",
    "sg:postcode":"9800",
    "sg:province":"Oost-Vlaanderen",
    "sg:tags":[
        "garage"
    ],
    "wof:name":"De Blauwere P",
    "wof:placetype":"venue"
},
  "geometry": {"coordinates":[3.5418989658,50.9806518555],"type":"Point"}
}