{
  "type": "Feature",
  "properties": {
    "iso:country":"BE",
    "sg:address":"Rue D'arlon 46",
    "sg:city":"Florenville",
    "sg:classifiers":[
        {
            "category":"Food & Beverages",
            "subcategory":"Supermarket",
            "type":"Retail Goods"
        }
    ],
    "sg:phone":"+32 61 31 55 64",
    "sg:postcode":"6820",
    "sg:province":"Luxembourg",
    "sg:tags":[
        "department",
        "store"
    ],
    "wof:name":"Delhaize",
    "wof:placetype":"venue"
},
  "geometry": {"coordinates":[5.3205099106,49.6962432861],"type":"Point"}
}