{
  "type": "Feature",
  "properties": {
    "iso:country":"BE",
    "sg:address":"Kelchterhoef 7",
    "sg:city":"Houthalen-helchteren",
    "sg:classifiers":[
        {
            "category":"Restaurant",
            "type":"Food & Drink"
        }
    ],
    "sg:phone":"+32 89 38 01 69",
    "sg:postcode":"3530",
    "sg:province":"Limburg",
    "wof:name":"Abdijhoeve",
    "wof:placetype":"venue"
},
  "geometry": {"coordinates":[5.4327859879,51.0286903381],"type":"Point"}
}