{
  "type": "Feature",
  "properties": {
    "addr:full":"Rue Des M\u00e9l\u00e8zes 63 Bruxelles (ixelles) Bruxelles-Capitale 1050",
    "addr:housenumber":"63",
    "addr:postcode":"1050",
    "addr:street":"Rue Des Me\u0301Le\u0300Zes",
    "iso:country":"BE",
    "sg:address":"Rue Des M\u00e9l\u00e8zes 63",
    "sg:city":"Bruxelles (ixelles)",
    "sg:classifiers":[
        {
            "category":"Shopping",
            "subcategory":"Clothing, Apparel, & Fashions",
            "type":"Retail Goods"
        }
    ],
    "sg:phone":"+32 2 640 91 81",
    "sg:postcode":"1050",
    "sg:province":"Bruxelles-Capitale",
    "sg:tags":[
        "designer",
        "stylist"
    ],
    "wof:name":"Bertouille M",
    "wof:placetype":"venue"
},
  "geometry": {"coordinates":[4.3632340431,50.8204612732],"type":"Point"}
}