{
  "type": "Feature",
  "properties": {
    "addr:full":"Gentse Steenweg 518a Aalst Oost-Vlaanderen 9300",
    "addr:housenumber":"518a",
    "addr:postcode":"9300",
    "addr:street":"Gentse Steenweg",
    "iso:country":"BE",
    "sg:address":"Gentse Steenweg 518a",
    "sg:city":"Aalst",
    "sg:classifiers":[
        {
            "category":"Juice Bar",
            "subcategory":"None",
            "type":"Food & Drink"
        }
    ],
    "sg:phone":"+32 53 72 96 00",
    "sg:postcode":"9300",
    "sg:province":"Oost-Vlaanderen",
    "sg:tags":[
        "furnishing"
    ],
    "wof:name":"Mts Nv",
    "wof:placetype":"venue"
},
  "geometry": {"coordinates":[3.9980399609,50.9419593811],"type":"Point"}
}