{
  "type": "Feature",
  "properties": {
    "iso:country":"BE",
    "sg:address":"Ekkelgarden 2",
    "sg:city":"Hasselt",
    "sg:classifiers":[
        {
            "category":"Manufacturing",
            "subcategory":"Food",
            "type":"Manufacturing & Wholesale Goods"
        }
    ],
    "sg:phone":"+32 11 28 31 09",
    "sg:postcode":"3500",
    "sg:province":"Limburg",
    "sg:tags":[
        "industry",
        "wrapping",
        "laminated",
        "foil",
        "foils",
        "films"
    ],
    "wof:name":"Gunze Plastics Europe Nv",
    "wof:placetype":"venue"
},
  "geometry": {"coordinates":[5.3546972275,50.9048728943],"type":"Point"}
}