{
  "type": "Feature",
  "properties": {
    "iso:country":"BE",
    "sg:address":"Sint-amandstraat 92",
    "sg:city":"Gent",
    "sg:orig_category":"Enseignement sup\u00e9rieur",
    "sg:phone":"+32 9 225 85 72",
    "sg:postcode":"9000",
    "sg:province":"Oost-Vlaanderen",
    "wof:name":"Klbo-campus Kattenberg",
    "wof:placetype":"venue"
},
  "geometry": {"coordinates":[3.7248160839,51.042098999],"type":"Point"}
}