{
  "type": "Feature",
  "properties": {
    "addr:full":"Av Du Marquis 20 Zi Fleurus Hainaut 6220",
    "addr:housenumber":"20",
    "addr:postcode":"6220",
    "addr:street":"Av Du Marquis",
    "iso:country":"BE",
    "sg:address":"Av Du Marquis 20 Zi",
    "sg:city":"Fleurus",
    "sg:classifiers":[
        {
            "category":"Professional",
            "type":"Services"
        }
    ],
    "sg:phone":"+32 71 81 97 54",
    "sg:postcode":"6220",
    "sg:province":"Hainaut",
    "sg:tags":[
        "transport",
        "road"
    ],
    "wof:name":"T.g.p. Sprl",
    "wof:placetype":"venue"
},
  "geometry": {"coordinates":[4.5496749878,50.4825363159],"type":"Point"}
}