{
  "type": "Feature",
  "properties": {
    "iso:country":"BE",
    "sg:address":"Graaf Van Landaststraat 57",
    "sg:city":"Oudenaarde",
    "sg:classifiers":[
        {
            "category":"Freight",
            "type":"Transportation"
        }
    ],
    "sg:phone":"+32 55 30 96 16",
    "sg:postcode":"9700",
    "sg:province":"Oost-Vlaanderen",
    "sg:tags":[
        "-",
        "transport"
    ],
    "wof:name":"Tranport Martens Bvba",
    "wof:placetype":"venue"
},
  "geometry": {"coordinates":[3.6185390949,50.8742141724],"type":"Point"}
}