{
  "type": "Feature",
  "properties": {
    "addr:full":"Rue De Huy 189 Faimes Li\u00e8ge 4317",
    "addr:housenumber":"189",
    "addr:postcode":"4317",
    "addr:street":"Rue De Huy",
    "iso:country":"BE",
    "sg:address":"Rue De Huy 189",
    "sg:city":"Faimes",
    "sg:orig_category":"Epiceries",
    "sg:phone":"+32 19 32 30 61",
    "sg:postcode":"4317",
    "sg:province":"Li\u00e8ge",
    "wof:name":"Raymonde Lebeau",
    "wof:placetype":"venue"
},
  "geometry": {"coordinates":[5.2666931152,50.6543960571],"type":"Point"}
}