{
  "type": "Feature",
  "properties": {
    "addr:full":"Kerkplein 8 Beerse Antwerpen 2340",
    "addr:housenumber":"8",
    "addr:postcode":"2340",
    "addr:street":"Kerkplein",
    "iso:country":"BE",
    "sg:address":"Kerkplein 8",
    "sg:city":"Beerse",
    "sg:orig_category":"Apotheken",
    "sg:phone":"+32 14 61 12 89",
    "sg:postcode":"2340",
    "sg:province":"Antwerpen",
    "wof:name":"Anne Van Coppenolle",
    "wof:placetype":"venue"
},
  "geometry": {"coordinates":[4.8553972244,51.3195533752],"type":"Point"}
}