{
  "type": "Feature",
  "properties": {
    "addr:full":"Hooilaart 29 Buggenhout Oost-Vlaanderen 9255",
    "addr:housenumber":"29",
    "addr:postcode":"9255",
    "addr:street":"Hooilaart",
    "iso:country":"BE",
    "sg:address":"Hooilaart 29",
    "sg:city":"Buggenhout",
    "sg:classifiers":[
        {
            "category":"Professional",
            "subcategory":"Management & Consulting",
            "type":"Services"
        }
    ],
    "sg:phone":"+32 52 37 58 77",
    "sg:postcode":"9255",
    "sg:province":"Oost-Vlaanderen",
    "sg:tags":[
        "consultant"
    ],
    "wof:name":"Strategy & Scenario Develo",
    "wof:placetype":"venue"
},
  "geometry": {"coordinates":[4.1859397888,51.0211753845],"type":"Point"}
}