{
  "type": "Feature",
  "properties": {
    "addr:full":"Vismarkt 14 Westerlo Antwerpen 2260",
    "addr:housenumber":"14",
    "addr:postcode":"2260",
    "addr:street":"Vismarkt",
    "iso:country":"BE",
    "sg:address":"Vismarkt 14",
    "sg:city":"Westerlo",
    "sg:classifiers":[
        {
            "category":"Shopping",
            "subcategory":"Clothing, Apparel, & Fashions",
            "type":"Retail Goods"
        }
    ],
    "sg:phone":"+32 14 54 72 17",
    "sg:postcode":"2260",
    "sg:province":"Antwerpen",
    "sg:tags":[
        "-",
        "clothing",
        "child"
    ],
    "wof:name":"Happy Kids",
    "wof:placetype":"venue"
},
  "geometry": {"coordinates":[4.9158101082,51.08618927],"type":"Point"}
}