{
  "type": "Feature",
  "properties": {
    "addr:full":"Driehuizen 6 Dendermonde Oost-Vlaanderen 9200",
    "addr:housenumber":"6",
    "addr:postcode":"9200",
    "addr:street":"Driehuizen;Oost-Vlaanderen",
    "iso:country":"BE",
    "sg:address":"Driehuizen 6",
    "sg:city":"Dendermonde",
    "sg:orig_category":"Brood, gebak and snoepgoed",
    "sg:phone":"+32 52 33 25 80",
    "sg:postcode":"9200",
    "sg:province":"Oost-Vlaanderen",
    "wof:name":"E. Jacobs",
    "wof:placetype":"venue"
},
  "geometry": {"coordinates":[4.0983099937,51.0315208435],"type":"Point"}
}