{
  "type": "Feature",
  "properties": {
    "addr:full":"Rue Grande 27 Bievre Namur 5555",
    "addr:housenumber":"27",
    "addr:postcode":"5555",
    "addr:street":"Rue Grande",
    "iso:country":"BE",
    "sg:address":"Rue Grande 27",
    "sg:city":"Bievre",
    "sg:orig_category":"Alimentation sp\u00e9cialis\u00e9e",
    "sg:phone":"+32 61 51 15 06",
    "sg:postcode":"5555",
    "sg:province":"Namur",
    "wof:name":"Traiteur Le Javidin",
    "wof:placetype":"venue"
},
  "geometry": {"coordinates":[5.006690979,49.891746521],"type":"Point"}
}