{
  "type": "Feature",
  "properties": {
    "addr:full":"Lange Leemstraat 187 Antwerpen Antwerpen 2018",
    "addr:housenumber":"187",
    "addr:postcode":"2018",
    "addr:street":"Lange Leemstraat",
    "iso:country":"BE",
    "sg:address":"Lange Leemstraat 187",
    "sg:city":"Antwerpen",
    "sg:orig_category":"Winkelinrichting and handelsuitrusting Gh",
    "sg:phone":"+32 3 239 11 83",
    "sg:postcode":"2018",
    "sg:province":"Antwerpen",
    "wof:name":"Belg. Amusement Sportland",
    "wof:placetype":"venue"
},
  "geometry": {"coordinates":[4.4165492058,51.206489563],"type":"Point"}
}