{
  "type": "Feature",
  "properties": {
    "addr:full":"Kermtstraat 19 Hasselt Limburg 3510",
    "addr:housenumber":"19",
    "addr:postcode":"3510",
    "addr:street":"Kermtstraat",
    "iso:country":"BE",
    "sg:address":"Kermtstraat 19",
    "sg:city":"Hasselt",
    "sg:orig_category":"Producteurs de l\u00e9gumes",
    "sg:phone":"+32 11 25 41 04",
    "sg:postcode":"3510",
    "sg:province":"Limburg",
    "wof:name":"Willy Marechal",
    "wof:placetype":"venue"
},
  "geometry": {"coordinates":[5.2531552315,50.9474906921],"type":"Point"}
}