{
  "type": "Feature",
  "properties": {
    "addr:full":"Meirhoekstraat 51 Laarne Oost-Vlaanderen 9270",
    "addr:housenumber":"51",
    "addr:postcode":"9270",
    "addr:street":"Meirhoekstraat",
    "iso:country":"BE",
    "sg:address":"Meirhoekstraat 51",
    "sg:city":"Laarne",
    "sg:classifiers":[
        {
            "category":"Cafe",
            "type":"Food & Drink"
        }
    ],
    "sg:phone":"+32 9 369 31 54",
    "sg:postcode":"9270",
    "sg:province":"Oost-Vlaanderen",
    "sg:tags":[
        "caf\u00e9s"
    ],
    "wof:name":"Caf\u00c9 De Pony",
    "wof:placetype":"venue"
},
  "geometry": {"coordinates":[3.8676900864,51.0233802795],"type":"Point"}
}