{
  "type": "Feature",
  "properties": {
    "addr:full":"Rue Leopold Ii 7 Les Bons Villers Hainaut 6210",
    "addr:housenumber":"7",
    "addr:postcode":"6210",
    "addr:street":"Rue Leopold Ii",
    "iso:country":"BE",
    "sg:address":"Rue Leopold Ii 7",
    "sg:city":"Les Bons Villers",
    "sg:orig_category":"Jeux de hasard",
    "sg:phone":"+32 71 85 32 98",
    "sg:postcode":"6210",
    "sg:province":"Hainaut",
    "wof:name":"Ladbrokes",
    "wof:placetype":"venue"
},
  "geometry": {"coordinates":[4.4511561394,50.5378227234],"type":"Point"}
}