{
  "type": "Feature",
  "properties": {
    "iso:country":"BE",
    "sg:address":"Rue Sonkeu 4",
    "sg:city":"Soumagne",
    "sg:orig_category":"M\u00e9decins and sp\u00e9cialistes",
    "sg:phone":"+32 87 67 94 46",
    "sg:postcode":"4633",
    "sg:province":"Li\u00e8ge",
    "wof:name":"F. De Zanet",
    "wof:placetype":"venue"
},
  "geometry": {"coordinates":[5.762275219,50.6402854919],"type":"Point"}
}