{
  "type": "Feature",
  "properties": {
    "iso:country":"BE",
    "sg:address":"Van Akenstraat 5",
    "sg:city":"Grimbergen",
    "sg:orig_category":"Boekenuitgeverijen Muziekinstrumenten",
    "sg:phone":"+32 2 270 04 46",
    "sg:postcode":"1850",
    "sg:province":"Vlaams-Brabant",
    "wof:name":"Matmus",
    "wof:placetype":"venue"
},
  "geometry": {"coordinates":[4.3630461693,50.9349899292],"type":"Point"}
}