{
  "type": "Feature",
  "properties": {
    "addr:full":"Ringlaan 231 Kortrijk West-Vlaanderen 8500",
    "addr:housenumber":"231",
    "addr:postcode":"8500",
    "addr:street":"Ringlaan",
    "iso:country":"BE",
    "sg:address":"Ringlaan 231",
    "sg:city":"Kortrijk",
    "sg:orig_category":"Krantenwinkels Rookartikelen",
    "sg:phone":"+32 56 35 42 79",
    "sg:postcode":"8500",
    "sg:province":"West-Vlaanderen",
    "wof:name":"Press Shop",
    "wof:placetype":"venue"
},
  "geometry": {"coordinates":[3.2811141014,50.8409233093],"type":"Point"}
}