{
  "type": "Feature",
  "properties": {
    "addr:full":"Rue Du Pont Neuf 74 Charleroi Hainaut 6000",
    "addr:housenumber":"74",
    "addr:postcode":"6000",
    "addr:street":"Rue Du Pont Neuf;Hainaut",
    "iso:country":"BE",
    "sg:address":"Rue Du Pont Neuf 74",
    "sg:city":"Charleroi",
    "sg:classifiers":[
        {
            "category":"Professional",
            "subcategory":"Detective & Security Services",
            "type":"Services"
        }
    ],
    "sg:phone":"+32 71 30 15 56",
    "sg:postcode":"6000",
    "sg:province":"Hainaut",
    "sg:tags":[
        "-",
        "system",
        "apparatus",
        "surveillance"
    ],
    "wof:name":"All Over Security",
    "wof:placetype":"venue"
},
  "geometry": {"coordinates":[4.4475579262,50.4082183838],"type":"Point"}
}