{
  "type": "Feature",
  "properties": {
    "iso:country":"BE",
    "sg:address":"Rue De Mont Saint-pont 8",
    "sg:city":"Braine-le-chateau",
    "sg:orig_category":"Slagers",
    "sg:phone":"+32 2 366 04 90",
    "sg:postcode":"1440",
    "sg:province":"Brabant Wallon",
    "wof:name":"Francis Demory",
    "wof:placetype":"venue"
},
  "geometry": {"coordinates":[4.2735967636,50.6832351685],"type":"Point"}
}