{
  "type": "Feature",
  "properties": {
    "addr:full":"Lovendonk 6 Evergem Oost-Vlaanderen 9940",
    "addr:housenumber":"6",
    "addr:postcode":"9940",
    "addr:street":"Lovendonk;Oost-Vlaanderen",
    "iso:country":"BE",
    "sg:address":"Lovendonk 6",
    "sg:city":"Evergem",
    "sg:classifiers":[
        {
            "category":"Arena",
            "subcategory":"Sports Club",
            "type":"Entertainment"
        }
    ],
    "sg:phone":"+32 9 357 67 43",
    "sg:postcode":"9940",
    "sg:province":"Oost-Vlaanderen",
    "sg:tags":[
        "de"
    ],
    "wof:name":"Turnkring St. Godelieve",
    "wof:placetype":"venue"
},
  "geometry": {"coordinates":[3.674998045,51.1370506287],"type":"Point"}
}