{
  "type": "Feature",
  "properties": {
    "addr:full":"Rue Gretry 157 Li\u00c8ge Li\u00e8ge 4020",
    "addr:housenumber":"157",
    "addr:postcode":"4020",
    "addr:street":"Rue Gretry",
    "iso:country":"BE",
    "sg:address":"Rue Gretry 157",
    "sg:city":"Li\u00c8ge",
    "sg:orig_category":"Medische and orthopedische apparaten",
    "sg:phone":"+32 4 342 76 94",
    "sg:postcode":"4020",
    "sg:province":"Li\u00e8ge",
    "wof:name":"Param\u00c9dica",
    "wof:placetype":"venue"
},
  "geometry": {"coordinates":[5.5838670731,50.6326446533],"type":"Point"}
}