{
  "type": "Feature",
  "properties": {
    "iso:country":"BE",
    "sg:address":"Avenue Du Luxembourg 3",
    "sg:city":"Li\u00e8ge 1 (li\u00e8ge 2)",
    "sg:classifiers":[
        {
            "category":"Professional",
            "subcategory":"Lawyer & Legal Services",
            "type":"Services"
        }
    ],
    "sg:phone":"+32 4 342 42 21",
    "sg:postcode":"4020",
    "sg:province":"Li\u00e8ge",
    "wof:name":"Bernard Ph",
    "wof:placetype":"venue"
},
  "geometry": {"coordinates":[5.5836539268,50.6226196289],"type":"Point"}
}