{
  "type": "Feature",
  "properties": {
    "iso:country":"BE",
    "sg:address":"Rubensstraat 104 Box 1",
    "sg:city":"Vilvoorde",
    "sg:classifiers":[
        {
            "category":"Food & Beverages",
            "subcategory":"Liquor & Beverages",
            "type":"Retail Goods"
        }
    ],
    "sg:phone":"+32 2 253 65 65",
    "sg:postcode":"1800",
    "sg:province":"Vlaams-Brabant",
    "sg:tags":[
        "-",
        "spirit",
        "wine"
    ],
    "wof:name":"Monseigneur (prestige Du)",
    "wof:placetype":"venue"
},
  "geometry": {"coordinates":[4.4082098007,50.9238204956],"type":"Point"}
}