{
  "type": "Feature",
  "properties": {
    "addr:full":"Banneuxstraat 1 Hasselt Limburg 3500",
    "addr:housenumber":"1",
    "addr:postcode":"3500",
    "addr:street":"Banneuxstraat",
    "iso:country":"BE",
    "sg:address":"Banneuxstraat 1",
    "sg:city":"Hasselt",
    "sg:orig_category":"Banken and kredietinstellingen",
    "sg:phone":"+32 11 22 20 52",
    "sg:postcode":"3500",
    "sg:province":"Limburg",
    "wof:name":"Bacob",
    "wof:placetype":"venue"
},
  "geometry": {"coordinates":[5.3457808495,50.9477272034],"type":"Point"}
}