{
  "type": "Feature",
  "properties": {
    "addr:full":"Cyriel Buyssestraat 6ba Nevele Oost-Vlaanderen 9850",
    "addr:housenumber":"6ba",
    "addr:postcode":"9850",
    "addr:street":"Cyriel Buyssestraat",
    "iso:country":"BE",
    "sg:address":"Cyriel Buyssestraat 6ba",
    "sg:city":"Nevele",
    "sg:orig_category":"Artsen and specialisten",
    "sg:phone":"+32 9 371 51 35",
    "sg:postcode":"9850",
    "sg:province":"Oost-Vlaanderen",
    "wof:name":"Petra Schelstraete",
    "wof:placetype":"venue"
},
  "geometry": {"coordinates":[3.548897028,51.032787323],"type":"Point"}
}