{
  "type": "Feature",
  "properties": {
    "addr:full":"Rue De Maz\u00c9e 1 Viroinval Namur 5670",
    "addr:housenumber":"1",
    "addr:postcode":"5670",
    "addr:street":"Rue De Maze\u0301E",
    "iso:country":"BE",
    "sg:address":"Rue De Maz\u00c9e 1",
    "sg:city":"Viroinval",
    "sg:orig_category":"Eleveurs de bovins",
    "sg:phone":"+32 60 39 90 70",
    "sg:postcode":"5670",
    "sg:province":"Namur",
    "wof:name":"Michel Coulonval",
    "wof:placetype":"venue"
},
  "geometry": {"coordinates":[4.6728038788,50.0937194824],"type":"Point"}
}