{
  "type": "Feature",
  "properties": {
    "addr:full":"Kapucijnenvoer 8 Leuven Vlaams-Brabant 3000",
    "addr:housenumber":"8",
    "addr:postcode":"3000",
    "addr:street":"Kapucijnenvoer",
    "iso:country":"BE",
    "sg:address":"Kapucijnenvoer 8",
    "sg:city":"Leuven",
    "sg:classifiers":[
        {
            "category":"Shopping",
            "subcategory":"Florist",
            "type":"Retail Goods"
        }
    ],
    "sg:phone":"+32 16 22 76 75",
    "sg:postcode":"3000",
    "sg:province":"Vlaams-Brabant",
    "wof:name":"Paeyeneers",
    "wof:placetype":"venue"
},
  "geometry": {"coordinates":[4.7036700249,50.8793869019],"type":"Point"}
}