{
  "type": "Feature",
  "properties": {
    "iso:country":"BE",
    "sg:address":"Bieststraat 47",
    "sg:city":"Laarne",
    "sg:orig_category":"Boekhouders",
    "sg:phone":"+32 9 367 66 06",
    "sg:postcode":"9270",
    "sg:province":"Oost-Vlaanderen",
    "wof:name":"Marc Vanden Boer",
    "wof:placetype":"venue"
},
  "geometry": {"coordinates":[3.9111819267,51.0385246277],"type":"Point"}
}