{
  "type": "Feature",
  "properties": {
    "iso:country":"BE",
    "sg:address":"Groeningekaai",
    "sg:city":"Kortrijk",
    "sg:orig_category":"Services Erotiques et d'Escorte",
    "sg:phone":"+32 486 42 96 55",
    "sg:postcode":"8500",
    "sg:province":"West-Vlaanderen",
    "wof:name":"Disco Boat Gay Club the Boys",
    "wof:placetype":"venue"
},
  "geometry": {"coordinates":[3.2777700424,50.8327560425],"type":"Point"}
}