{
  "type": "Feature",
  "properties": {
    "iso:country":"BE",
    "sg:address":"Rue Du Tennis 1",
    "sg:city":"Thimister-clermont (thimister)",
    "sg:classifiers":[
        {
            "category":"Arena",
            "subcategory":"Sports Club",
            "type":"Entertainment"
        }
    ],
    "sg:phone":"+32 87 44 69 10",
    "sg:postcode":"4890",
    "sg:province":"Li\u00e8ge",
    "wof:name":"Tennis De Thimister",
    "wof:placetype":"venue"
},
  "geometry": {"coordinates":[5.8688769341,50.6552658081],"type":"Point"}
}