{
  "type": "Feature",
  "properties": {
    "iso:country":"BE",
    "sg:address":"Zwijnaardsesteenweg 79",
    "sg:city":"Merelbeke",
    "sg:orig_category":"Fotografen and fotostudio's",
    "sg:phone":"+32 9 231 96 16",
    "sg:postcode":"9820",
    "sg:province":"Oost-Vlaanderen",
    "wof:name":"Fotostudio De Grove",
    "wof:placetype":"venue"
},
  "geometry": {"coordinates":[3.741339922,50.9988746643],"type":"Point"}
}