{
  "type": "Feature",
  "properties": {
    "addr:full":"Oude Baan 62 Maasmechelen Limburg 3630",
    "addr:housenumber":"62",
    "addr:postcode":"3630",
    "addr:street":"Oude Baan",
    "iso:country":"BE",
    "sg:address":"Oude Baan 62",
    "sg:city":"Maasmechelen",
    "sg:orig_category":"Brood, gebak and snoepgoed GROENTEN AND FRUIT",
    "sg:phone":"+32 89 77 17 32",
    "sg:postcode":"3630",
    "sg:province":"Limburg",
    "wof:name":"Huis Icen",
    "wof:placetype":"venue"
},
  "geometry": {"coordinates":[5.6933951378,50.9863739014],"type":"Point"}
}