{
  "type": "Feature",
  "properties": {
    "addr:full":"Rue Gustave Misson 13 Profondeville (lesve) Namur 5170",
    "addr:housenumber":"13",
    "addr:postcode":"5170",
    "addr:street":"Rue Gustave Misson",
    "iso:country":"BE",
    "sg:address":"Rue Gustave Misson 13",
    "sg:city":"Profondeville (lesve)",
    "sg:classifiers":[
        {
            "category":"Health Services",
            "subcategory":"Doctor",
            "type":"Services"
        }
    ],
    "sg:phone":"+32 81 43 34 91",
    "sg:postcode":"5170",
    "sg:province":"Namur",
    "sg:tags":[
        "medicinephysicians",
        "surgeon"
    ],
    "wof:name":"Lienard S",
    "wof:placetype":"venue"
},
  "geometry": {"coordinates":[4.8674049377,50.3786392212],"type":"Point"}
}