{
  "type": "Feature",
  "properties": {
    "addr:full":"Rue Puccini 49 Anderlecht Bruxelles-Capitale 1070",
    "addr:housenumber":"49",
    "addr:postcode":"1070",
    "addr:street":"Rue Puccini",
    "iso:country":"BE",
    "sg:address":"Rue Puccini 49",
    "sg:city":"Anderlecht",
    "sg:orig_category":"Biens d'occasion",
    "sg:phone":"+32 2 524 49 09",
    "sg:postcode":"1070",
    "sg:province":"Bruxelles-Capitale",
    "wof:name":"Maison Jumatho & Cie",
    "wof:placetype":"venue"
},
  "geometry": {"coordinates":[4.3050317764,50.8453178406],"type":"Point"}
}