{
  "type": "Feature",
  "properties": {
    "iso:country":"BE",
    "sg:address":"Rijksweg 163",
    "sg:city":"Dilsen-stokkem",
    "sg:classifiers":[
        {
            "category":"Cafe",
            "type":"Food & Drink"
        }
    ],
    "sg:phone":"+32 89 75 68 08",
    "sg:postcode":"3650",
    "sg:province":"Limburg",
    "sg:tags":[
        "caf\u00e9s"
    ],
    "wof:name":"Helga Dohmen",
    "wof:placetype":"venue"
},
  "geometry": {"coordinates":[5.7266697884,51.0228614807],"type":"Point"}
}