{
  "type": "Feature",
  "properties": {
    "addr:full":"Rue De Chestret 20 Li\u00e8ge 1 Li\u00e8ge 4000",
    "addr:housenumber":"20;1",
    "addr:postcode":"4000",
    "addr:street":"Rue De Chestret",
    "iso:country":"BE",
    "sg:address":"Rue De Chestret 20",
    "sg:city":"Li\u00e8ge 1",
    "sg:classifiers":[
        {
            "category":"Health Services",
            "subcategory":"Doctor",
            "type":"Services"
        }
    ],
    "sg:phone":"+32 4 252 17 83",
    "sg:postcode":"4000",
    "sg:province":"Li\u00e8ge",
    "sg:tags":[
        "medicinephysicians",
        "surgeon"
    ],
    "wof:name":"Goffioul F",
    "wof:placetype":"venue"
},
  "geometry": {"coordinates":[5.5636811256,50.6296806335],"type":"Point"}
}