{
  "type": "Feature",
  "properties": {
    "addr:full":"Rue Saint-christophe 35 Bruxelles Bruxelles-Capitale 1000",
    "addr:housenumber":"35",
    "addr:postcode":"1000",
    "addr:street":"Rue Saint-Christophe",
    "iso:country":"BE",
    "sg:address":"Rue Saint-christophe 35",
    "sg:city":"Bruxelles",
    "sg:classifiers":[
        {
            "category":"Communications",
            "subcategory":"Film & Video Production",
            "type":"Services"
        }
    ],
    "sg:phone":"+32 2 502 22 76",
    "sg:postcode":"1000",
    "sg:province":"Bruxelles-Capitale",
    "sg:tags":[
        "sound",
        "recording",
        "studio"
    ],
    "wof:name":"Schodts F",
    "wof:placetype":"venue"
},
  "geometry": {"coordinates":[4.3456668854,50.8474731445],"type":"Point"}
}