{
  "type": "Feature",
  "properties": {
    "addr:full":"Heirbaan 32 Grobbendonk Antwerpen 2280",
    "addr:housenumber":"32",
    "addr:postcode":"2280",
    "addr:street":"Heirbaan",
    "iso:country":"BE",
    "sg:address":"Heirbaan 32",
    "sg:city":"Grobbendonk",
    "sg:orig_category":"Non-Classified Establishments",
    "sg:phone":"+32 14 50 12 11",
    "sg:postcode":"2280",
    "sg:province":"Antwerpen",
    "wof:name":"Faes",
    "wof:placetype":"venue"
},
  "geometry": {"coordinates":[4.7341341972,51.2023620605],"type":"Point"}
}