{
  "type": "Feature",
  "properties": {
    "addr:full":"Avenue De La Paix 63 Li\u00e8ge 1 (grivegn\u00e9e) Li\u00e8ge 4030",
    "addr:housenumber":"63;1",
    "addr:postcode":"4030",
    "addr:street":"Avenue De La Paix",
    "iso:country":"BE",
    "sg:address":"Avenue De La Paix 63",
    "sg:city":"Li\u00e8ge 1 (grivegn\u00e9e)",
    "sg:classifiers":[
        {
            "category":"Personal",
            "subcategory":"Beauty Salon",
            "type":"Services"
        }
    ],
    "sg:phone":"+32 4 342 72 31",
    "sg:postcode":"4030",
    "sg:province":"Li\u00e8ge",
    "sg:tags":[
        "lady",
        "-",
        "hairdressing"
    ],
    "wof:name":"Espace Coiffure Jp Franco",
    "wof:placetype":"venue"
},
  "geometry": {"coordinates":[5.6076822281,50.6278953552],"type":"Point"}
}