{
  "type": "Feature",
  "properties": {
    "iso:country":"BE",
    "sg:address":"Avenue John-fitzgerald Kennedy 10",
    "sg:city":"Rixensart",
    "sg:classifiers":[
        {
            "category":"Social Services",
            "subcategory":"Child Care",
            "type":"Services"
        }
    ],
    "sg:phone":"+32 2 652 10 88",
    "sg:postcode":"1330",
    "sg:province":"Brabant Wallon",
    "sg:tags":[
        "boy",
        "scout",
        "equipment"
    ],
    "wof:name":"Scoutshop",
    "wof:placetype":"venue"
},
  "geometry": {"coordinates":[4.5214271545,50.709400177],"type":"Point"}
}