{
  "type": "Feature",
  "properties": {
    "iso:country":"BE",
    "sg:address":"Oude Dendermondsebaan 129",
    "sg:city":"Asse",
    "sg:orig_category":"Charpentes and couvertures. Plomberie, chauffage and installations sanitaires",
    "sg:phone":"+32 2 452 58 44",
    "sg:postcode":"1730",
    "sg:province":"Vlaams-Brabant",
    "wof:name":"Van Droogenbroeck",
    "wof:placetype":"venue"
},
  "geometry": {"coordinates":[4.1879291534,50.9207954407],"type":"Point"}
}