{
  "type": "Feature",
  "properties": {
    "addr:full":"Rue De Mons 71 Tubize Brabant Wallon 1480",
    "addr:housenumber":"71",
    "addr:postcode":"1480",
    "addr:street":"Rue De Mons;Wallon",
    "iso:country":"BE",
    "sg:address":"Rue De Mons 71",
    "sg:city":"Tubize",
    "sg:orig_category":"S\u00e9curit\u00e9 sociale",
    "sg:phone":"+32 2 355 69 64",
    "sg:postcode":"1480",
    "sg:province":"Brabant Wallon",
    "wof:name":"Mutualit\u00c9 Socialiste",
    "wof:placetype":"venue"
},
  "geometry": {"coordinates":[4.1943898201,50.6836585999],"type":"Point"}
}