{
  "type": "Feature",
  "properties": {
    "addr:full":"Bellestraat 64 Heuvelland West-Vlaanderen 8954",
    "addr:housenumber":"64",
    "addr:postcode":"8954",
    "addr:street":"Bellestraat",
    "iso:country":"BE",
    "sg:address":"Bellestraat 64",
    "sg:city":"Heuvelland",
    "sg:orig_category":"Brood, gebak and snoepgoed",
    "sg:phone":"+32 57 44 68 25",
    "sg:postcode":"8954",
    "sg:province":"West-Vlaanderen",
    "wof:name":"Lekkerbek",
    "wof:placetype":"venue"
},
  "geometry": {"coordinates":[2.7476201057,50.7867088318],"type":"Point"}
}