{
  "type": "Feature",
  "properties": {
    "addr:full":"Chemin D'arville 17 Gesves (faulx-les-tombes) Namur 5340",
    "addr:housenumber":"17",
    "addr:postcode":"5340",
    "addr:street":"Chemin D'Arville",
    "iso:country":"BE",
    "sg:address":"Chemin D'arville 17",
    "sg:city":"Gesves (faulx-les-tombes)",
    "sg:classifiers":[
        {
            "category":"Personal",
            "subcategory":"Nail Salon",
            "type":"Services"
        }
    ],
    "sg:phone":"+32 81 57 05 52",
    "sg:postcode":"5340",
    "sg:province":"Namur",
    "sg:tags":[
        "pedicure"
    ],
    "wof:name":"Noe Maryline",
    "wof:placetype":"venue"
},
  "geometry": {"coordinates":[4.9996829033,50.4263000488],"type":"Point"}
}