{
  "type": "Feature",
  "properties": {
    "addr:full":"Veldlaan 17 Overijse Vlaams-Brabant 3090",
    "addr:housenumber":"17",
    "addr:postcode":"3090",
    "addr:street":"Veldlaan",
    "iso:country":"BE",
    "sg:address":"Veldlaan 17",
    "sg:city":"Overijse",
    "sg:classifiers":[
        {
            "category":"Professional",
            "subcategory":"Management & Consulting",
            "type":"Services"
        }
    ],
    "sg:phone":"+32 2 688 00 99",
    "sg:postcode":"3090",
    "sg:province":"Vlaams-Brabant",
    "sg:tags":[
        "marketing",
        "-",
        "consultant"
    ],
    "wof:name":"Imc",
    "wof:placetype":"venue"
},
  "geometry": {"coordinates":[4.5645799637,50.7602233887],"type":"Point"}
}