{
  "type": "Feature",
  "properties": {
    "iso:country":"BE",
    "sg:address":"Gemeentestraat 2",
    "sg:city":"Turnhout",
    "sg:orig_category":"Avocats and conseillers juridiques",
    "sg:phone":"+32 14 41 17 22",
    "sg:postcode":"2300",
    "sg:province":"Antwerpen",
    "wof:name":"J. Kersemans",
    "wof:placetype":"venue"
},
  "geometry": {"coordinates":[4.9424061775,51.3232002258],"type":"Point"}
}