{
  "type": "Feature",
  "properties": {
    "addr:full":"Anderlechtsesteenweg 36 Brussel/bruxelles Bruxelles-Capitale 1000",
    "addr:housenumber":"36",
    "addr:postcode":"1000",
    "addr:street":"Anderlechtsesteenweg;/",
    "iso:country":"BE",
    "sg:address":"Anderlechtsesteenweg 36",
    "sg:city":"Brussel/bruxelles",
    "sg:orig_category":"Apotheken",
    "sg:phone":"+32 2 511 46 60",
    "sg:postcode":"1000",
    "sg:province":"Bruxelles-Capitale",
    "wof:name":"Francoise Chailloux",
    "wof:placetype":"venue"
},
  "geometry": {"coordinates":[4.3445158005,50.8453063965],"type":"Point"}
}