{
  "type": "Feature",
  "properties": {
    "iso:country":"BE",
    "sg:address":"Zwartezustersstraat 18",
    "sg:city":"Gent",
    "sg:classifiers":[
        {
            "category":"Social Services",
            "type":"Services"
        }
    ],
    "sg:phone":"+32 52 35 72 00",
    "sg:postcode":"9000",
    "sg:province":"Oost-Vlaanderen",
    "wof:name":"Familiezorg Vlaams Brabant Vzw",
    "wof:placetype":"venue"
},
  "geometry": {"coordinates":[3.7187829018,51.0523414612],"type":"Point"}
}