{
  "type": "Feature",
  "properties": {
    "iso:country":"BE",
    "sg:address":"Volksstraat 22",
    "sg:city":"Willebroek",
    "sg:orig_category":"Epiceries",
    "sg:phone":"+32 3 888 21 17",
    "sg:postcode":"2830",
    "sg:province":"Antwerpen",
    "wof:name":"\u00b4t Winkeltje",
    "wof:placetype":"venue"
},
  "geometry": {"coordinates":[4.3642978668,51.0799827576],"type":"Point"}
}