{
  "type": "Feature",
  "properties": {
    "addr:full":"Place Eug\u00c8ne Derbaix 16 Binche Hainaut 7130",
    "addr:housenumber":"16",
    "addr:postcode":"7130",
    "addr:street":"Place Euge\u0300Ne Derbaix",
    "iso:country":"BE",
    "sg:address":"Place Eug\u00c8ne Derbaix 16",
    "sg:city":"Binche",
    "sg:orig_category":"Traitements param\u00e9dicaux",
    "sg:phone":"+32 64 36 61 81",
    "sg:postcode":"7130",
    "sg:province":"Hainaut",
    "wof:name":"Dispens. H\u00d4pital Jolimont",
    "wof:placetype":"venue"
},
  "geometry": {"coordinates":[4.1716599464,50.4090995789],"type":"Point"}
}