{
  "type": "Feature",
  "properties": {
    "addr:full":"Gulden-vlieslaan 34 Elsene/ixelles Bruxelles-Capitale 1050",
    "addr:housenumber":"34",
    "addr:postcode":"1050",
    "addr:street":"Gulden-Vlieslaan",
    "iso:country":"BE",
    "sg:address":"Gulden-vlieslaan 34",
    "sg:city":"Elsene/ixelles",
    "sg:orig_category":"Herenkledingzaken",
    "sg:phone":"+32 2 514 43 49",
    "sg:postcode":"1050",
    "sg:province":"Bruxelles-Capitale",
    "wof:name":"Marlboro Classics",
    "wof:placetype":"venue"
},
  "geometry": {"coordinates":[4.3575129509,50.836265564],"type":"Point"}
}