{
  "type": "Feature",
  "properties": {
    "addr:full":"Kerkplein 21 Holsbeek Vlaams-Brabant 3220",
    "addr:housenumber":"21",
    "addr:postcode":"3220",
    "addr:street":"Kerkplein",
    "iso:country":"BE",
    "sg:address":"Kerkplein 21",
    "sg:city":"Holsbeek",
    "sg:orig_category":"Installatie van houten of kunststof schrijnwerk",
    "sg:phone":"+32 16 62 06 70",
    "sg:postcode":"3220",
    "sg:province":"Vlaams-Brabant",
    "wof:name":"Achilles Smets",
    "wof:placetype":"venue"
},
  "geometry": {"coordinates":[4.8034667969,50.9268226624],"type":"Point"}
}