{
  "type": "Feature",
  "properties": {
    "addr:full":"Avenue Louise 441 Bruxelles (ixelles) Bruxelles-Capitale 1050",
    "addr:housenumber":"441",
    "addr:postcode":"1050",
    "addr:street":"Avenue Louise",
    "iso:country":"BE",
    "sg:address":"Avenue Louise 441",
    "sg:city":"Bruxelles (ixelles)",
    "sg:classifiers":[
        {
            "category":"Health Services",
            "subcategory":"Hospital",
            "type":"Services"
        }
    ],
    "sg:phone":"+32 2 640 08 81",
    "sg:postcode":"1050",
    "sg:province":"Bruxelles-Capitale",
    "wof:name":"Centre Belge Medecine Du Sport",
    "wof:placetype":"venue"
},
  "geometry": {"coordinates":[4.370909214,50.8183021545],"type":"Point"}
}