{
  "type": "Feature",
  "properties": {
    "addr:full":"Boektsestraat 50 Steenokkerzeel Vlaams-Brabant 1820",
    "addr:housenumber":"50",
    "addr:postcode":"1820",
    "addr:street":"Boektsestraat",
    "iso:country":"BE",
    "sg:address":"Boektsestraat 50",
    "sg:city":"Steenokkerzeel",
    "sg:orig_category":"Advocaten and juridische adviseurs",
    "sg:phone":"+32 15 62 12 83",
    "sg:postcode":"1820",
    "sg:province":"Vlaams-Brabant",
    "wof:name":"P. Mancel",
    "wof:placetype":"venue"
},
  "geometry": {"coordinates":[4.4979400635,50.9555702209],"type":"Point"}
}