{
  "type": "Feature",
  "properties": {
    "addr:full":"Vir\u00e9e-du-renard 21 Vaux-sur-s\u00fbre (sibret) Luxembourg 6640",
    "addr:housenumber":"21",
    "addr:postcode":"6640",
    "addr:street":"Vire\u0301E-Du-Renard",
    "iso:country":"BE",
    "sg:address":"Vir\u00e9e-du-renard 21",
    "sg:city":"Vaux-sur-s\u00fbre (sibret)",
    "sg:classifiers":[
        {
            "category":"Health Services",
            "subcategory":"Health Practitioner",
            "type":"Services"
        }
    ],
    "sg:phone":"+32 61 26 66 37",
    "sg:postcode":"6640",
    "sg:province":"Luxembourg",
    "sg:tags":[
        "physiotherapist"
    ],
    "wof:name":"Demoustier M-p",
    "wof:placetype":"venue"
},
  "geometry": {"coordinates":[5.5671000481,49.91065979],"type":"Point"}
}