{
  "type": "Feature",
  "properties": {
    "addr:full":"Rodter Strasse 1 Sankt Vith/saint-vith Li\u00e8ge 4780",
    "addr:housenumber":"1",
    "addr:postcode":"4780",
    "addr:street":"Rodter Strasse",
    "iso:country":"BE",
    "sg:address":"Rodter Strasse 1",
    "sg:city":"Sankt Vith/saint-vith",
    "sg:orig_category":"Mat\u00e9riaux de construction Gr",
    "sg:phone":"+32 80 28 04 00",
    "sg:postcode":"4780",
    "sg:province":"Li\u00e8ge",
    "wof:name":"Maraite & S\u00d6hne",
    "wof:placetype":"venue"
},
  "geometry": {"coordinates":[6.0429549217,50.3349761963],"type":"Point"}
}