{
  "type": "Feature",
  "properties": {
    "addr:full":"Gulledelle 94 Sint-lambrechts-woluwe/woluwe-saint-lambert Bruxelles-Capitale 1200",
    "addr:housenumber":"94",
    "addr:postcode":"1200",
    "addr:street":"Gulledelle",
    "iso:country":"BE",
    "sg:address":"Gulledelle 94",
    "sg:city":"Sint-lambrechts-woluwe/woluwe-saint-lambert",
    "sg:orig_category":"Mat\u00e9riaux de construction Gr",
    "sg:phone":"+32 2 773 35 11",
    "sg:postcode":"1200",
    "sg:province":"Bruxelles-Capitale",
    "wof:name":"Gralex",
    "wof:placetype":"venue"
},
  "geometry": {"coordinates":[4.4245529175,50.8558616638],"type":"Point"}
}