{
  "type": "Feature",
  "properties": {
    "iso:country":"BE",
    "sg:address":"Dourdanstraat 8",
    "sg:city":"Wervik",
    "sg:orig_category":"Installatie van houten of kunststof schrijnwerk",
    "sg:phone":"+32 56 51 75 74",
    "sg:postcode":"8940",
    "sg:province":"West-Vlaanderen",
    "wof:name":"Marnick Boudry",
    "wof:placetype":"venue"
},
  "geometry": {"coordinates":[3.0671389103,50.8093032837],"type":"Point"}
}