{
  "type": "Feature",
  "properties": {
    "addr:full":"Gullegemsestraat 50 Ledegem West-Vlaanderen 8880",
    "addr:housenumber":"50",
    "addr:postcode":"8880",
    "addr:street":"Gullegemsestraat",
    "iso:country":"BE",
    "sg:address":"Gullegemsestraat 50",
    "sg:city":"Ledegem",
    "sg:orig_category":"Journaux. Tabac",
    "sg:phone":"+32 56 50 99 73",
    "sg:postcode":"8880",
    "sg:province":"West-Vlaanderen",
    "wof:name":"Huis Merlijn",
    "wof:placetype":"venue"
},
  "geometry": {"coordinates":[3.182215929,50.8728942871],"type":"Point"}
}