{
  "type": "Feature",
  "properties": {
    "iso:country":"BE",
    "sg:address":"Rue De Marchienne 3",
    "sg:city":"Charleroi",
    "sg:classifiers":[
        {
            "category":"Shopping",
            "subcategory":"Beauty & Cosmetics",
            "type":"Retail Goods"
        }
    ],
    "sg:phone":"+32 71 31 41 55",
    "sg:postcode":"6000",
    "sg:province":"Hainaut",
    "sg:tags":[
        "-",
        "perfumery"
    ],
    "wof:name":"France Parfums Sa",
    "wof:placetype":"venue"
},
  "geometry": {"coordinates":[4.4407629967,50.407951355],"type":"Point"}
}