{
  "type": "Feature",
  "properties": {
    "iso:country":"BE",
    "sg:address":"Amerstraat 161",
    "sg:city":"Aarschot",
    "sg:classifiers":[
        {
            "category":"Real Estate",
            "subcategory":"Architect",
            "type":"Services"
        }
    ],
    "sg:phone":"+32 16 57 23 71",
    "sg:postcode":"3200",
    "sg:province":"Vlaams-Brabant",
    "wof:name":"Macken & Macken Architecten Bvba",
    "wof:placetype":"venue"
},
  "geometry": {"coordinates":[4.8304400444,50.9865989685],"type":"Point"}
}