{
  "type": "Feature",
  "properties": {
    "iso:country":"BE",
    "sg:address":"Rue Du Mouligneau 39",
    "sg:city":"Soignies (neufvilles)",
    "sg:classifiers":[
        {
            "category":"Manufacturing",
            "subcategory":"Signs",
            "type":"Manufacturing & Wholesale Goods"
        }
    ],
    "sg:phone":"+32 67 33 32 93",
    "sg:postcode":"7063",
    "sg:province":"Hainaut",
    "sg:tags":[
        "-",
        "illuminated"
    ],
    "wof:name":"Kevin & Co",
    "wof:placetype":"venue"
},
  "geometry": {"coordinates":[3.993940115,50.5837898254],"type":"Point"}
}