{
  "type": "Feature",
  "properties": {
    "addr:full":"Kerkstraat 113 Buggenhout Oost-Vlaanderen 9255",
    "addr:housenumber":"113",
    "addr:postcode":"9255",
    "addr:street":"Kerkstraat",
    "iso:country":"BE",
    "sg:address":"Kerkstraat 113",
    "sg:city":"Buggenhout",
    "sg:orig_category":"Kapsalons",
    "sg:phone":"+32 52 34 23 62",
    "sg:postcode":"9255",
    "sg:province":"Oost-Vlaanderen",
    "wof:name":"Kapsalon Liane",
    "wof:placetype":"venue"
},
  "geometry": {"coordinates":[4.2020230293,51.0142936707],"type":"Point"}
}