{
  "type": "Feature",
  "properties": {
    "addr:full":"Grote Steenweg 28 Zoutleeuw (halle-booienhoven) Vlaams-Brabant 3440",
    "addr:housenumber":"28",
    "addr:postcode":"3440",
    "addr:street":"Grote Steenweg",
    "iso:country":"BE",
    "sg:address":"Grote Steenweg 28",
    "sg:city":"Zoutleeuw (halle-booienhoven)",
    "sg:classifiers":[
        {
            "category":"Retail",
            "subcategory":"Auto Repair",
            "type":"Services"
        }
    ],
    "sg:phone":"+32 11 78 24 22",
    "sg:postcode":"3440",
    "sg:province":"Vlaams-Brabant",
    "sg:tags":[
        "breakdown",
        "automobile",
        "-",
        "recovery"
    ],
    "wof:name":"Joris E",
    "wof:placetype":"venue"
},
  "geometry": {"coordinates":[5.0916390419,50.8063430786],"type":"Point"}
}