{
  "type": "Feature",
  "properties": {
    "iso:country":"BE",
    "sg:address":"Guillaume Van Haelenlaan 83",
    "sg:city":"Vorst/forest",
    "sg:orig_category":"Maatschappelijke dienstverlening",
    "sg:phone":"+32 2 343 74 04",
    "sg:postcode":"1190",
    "sg:province":"Bruxelles-Capitale",
    "wof:name":"Centre Planning Fam.",
    "wof:placetype":"venue"
},
  "geometry": {"coordinates":[4.3285169601,50.8211555481],"type":"Point"}
}