{
  "type": "Feature",
  "properties": {
    "iso:country":"BE",
    "sg:address":"Rue De France 12",
    "sg:city":"Philippeville",
    "sg:orig_category":"Bagage and lederwaren",
    "sg:phone":"+32 71 66 96 85",
    "sg:postcode":"5600",
    "sg:province":"Namur",
    "wof:name":"Maison Kabotine",
    "wof:placetype":"venue"
},
  "geometry": {"coordinates":[4.5423212051,50.1959877014],"type":"Point"}
}