{
  "type": "Feature",
  "properties": {
    "iso:country":"BE",
    "sg:address":"Kruisbaan 46",
    "sg:city":"Mechelen",
    "sg:classifiers":[
        {
            "category":"Professional",
            "subcategory":"Computer Services",
            "type":"Services"
        }
    ],
    "sg:phone":"+32 15 41 24 08",
    "sg:postcode":"2800",
    "sg:province":"Antwerpen",
    "sg:tags":[
        "repair",
        "processing",
        "-",
        "maintenance",
        "data"
    ],
    "wof:name":"Comsys",
    "wof:placetype":"venue"
},
  "geometry": {"coordinates":[4.468752861,51.0093154907],"type":"Point"}
}