{
  "type": "Feature",
  "properties": {
    "addr:full":"Groenestraat 43 Houthulst West-Vlaanderen 8650",
    "addr:housenumber":"43",
    "addr:postcode":"8650",
    "addr:street":"Groenestraat",
    "iso:country":"BE",
    "sg:address":"Groenestraat 43",
    "sg:city":"Houthulst",
    "sg:orig_category":"Eleveurs and marchands de porcs. Eleveurs de bovins",
    "sg:phone":"+32 51 54 42 36",
    "sg:postcode":"8650",
    "sg:province":"West-Vlaanderen",
    "wof:name":"Dirk Degryse",
    "wof:placetype":"venue"
},
  "geometry": {"coordinates":[2.8793020248,50.9413452148],"type":"Point"}
}