{
  "type": "Feature",
  "properties": {
    "iso:country":"BE",
    "sg:address":"Rue Des J\u00e9suites 29",
    "sg:city":"Tournai",
    "sg:orig_category":"Non-Classified Establishments",
    "sg:phone":"+32 69 22 03 73",
    "sg:postcode":"7500",
    "sg:province":"Hainaut",
    "wof:name":"Centre Pms Libre Pour L'enseignement Sp\u00e9cial (sp\u00e9cialis\u00e9)",
    "wof:placetype":"venue"
},
  "geometry": {"coordinates":[3.391479969,50.604385376],"type":"Point"}
}