{
  "type": "Feature",
  "properties": {
    "addr:full":"Faubourg Saint-germain 63 Couvin Namur 5660",
    "addr:housenumber":"63",
    "addr:postcode":"5660",
    "addr:street":"Faubourg Saint-Germain",
    "iso:country":"BE",
    "sg:address":"Faubourg Saint-germain 63",
    "sg:city":"Couvin",
    "sg:classifiers":[
        {
            "category":"Shopping",
            "subcategory":"Bicycles & Sporting Goods",
            "type":"Retail Goods"
        }
    ],
    "sg:phone":"+32 60 34 77 60",
    "sg:postcode":"5660",
    "sg:province":"Namur",
    "sg:tags":[
        "sport",
        "-"
    ],
    "wof:name":"Randoraid Sport",
    "wof:placetype":"venue"
},
  "geometry": {"coordinates":[4.493929863,50.0523834229],"type":"Point"}
}