{
  "type": "Feature",
  "properties": {
    "iso:country":"BE",
    "sg:address":"Waaienberg 42",
    "sg:city":"Opwijk",
    "sg:classifiers":[
        {
            "category":"Wholesale",
            "subcategory":"Machinery & Supplies",
            "type":"Manufacturing & Wholesale Goods"
        }
    ],
    "sg:phone":"+32 52 35 67 08",
    "sg:postcode":"1745",
    "sg:province":"Vlaams-Brabant",
    "sg:tags":[
        "agricultural",
        "tractor"
    ],
    "wof:name":"Esselens Michel Bvba",
    "wof:placetype":"venue"
},
  "geometry": {"coordinates":[4.1949357986,50.9471282959],"type":"Point"}
}