{
  "type": "Feature",
  "properties": {
    "iso:country":"BE",
    "sg:address":"Hasseltsebaan 133",
    "sg:city":"Hechtel",
    "sg:classifiers":[
        {
            "category":"Professional",
            "subcategory":"Engineering",
            "type":"Services"
        }
    ],
    "sg:phone":"+32 11 73 40 92",
    "sg:postcode":"3940",
    "sg:province":"Limburg",
    "sg:tags":[
        "machine",
        "-",
        "mechanical"
    ],
    "wof:name":"Gielen Ketelbouw Nv",
    "wof:placetype":"venue"
},
  "geometry": {"coordinates":[5.3712158203,51.1119613647],"type":"Point"}
}