{
  "type": "Feature",
  "properties": {
    "iso:country":"BE",
    "sg:address":"Rue Tienne-des-solins 12",
    "sg:city":"Rochefort",
    "sg:orig_category":"Loodgieterij, verwarming and sanitaire installaties",
    "sg:phone":"+32 84 38 89 78",
    "sg:postcode":"5580",
    "sg:province":"Namur",
    "wof:name":"Moise Pascal",
    "wof:placetype":"venue"
},
  "geometry": {"coordinates":[5.1484241486,50.1107559204],"type":"Point"}
}