{
  "type": "Feature",
  "properties": {
    "addr:full":"Grote Baan 204 Herdersem 9390",
    "addr:housenumber":"204",
    "addr:postcode":"9390",
    "addr:street":"Grote Baan;Herdersem",
    "iso:country":"BE",
    "sg:address":"Grote Baan 204",
    "sg:city":"Herdersem",
    "sg:classifiers":[
        {
            "category":"Banks & Credit Unions",
            "subcategory":"Bank",
            "type":"Services"
        }
    ],
    "sg:phone":"+32 53 21 99 83",
    "sg:postcode":"9390",
    "wof:name":"Banque Bruxelles Lambert Sa",
    "wof:placetype":"venue"
},
  "geometry": {"coordinates":[6.2687401772,49.8712501526],"type":"Point"}
}