{
  "type": "Feature",
  "properties": {
    "addr:full":"Bellestraat 62 Ieper West-Vlaanderen 8908",
    "addr:housenumber":"62",
    "addr:postcode":"8908",
    "addr:street":"Bellestraat",
    "iso:country":"BE",
    "sg:address":"Bellestraat 62",
    "sg:city":"Ieper",
    "sg:orig_category":"R\u00e9cup\u00e9ration de mati\u00e8res m\u00e9talliques recyclables and d\u00e9molisseurs de voitures",
    "sg:phone":"+32 57 20 26 88",
    "sg:postcode":"8908",
    "sg:province":"West-Vlaanderen",
    "wof:name":"Auto Filip",
    "wof:placetype":"venue"
},
  "geometry": {"coordinates":[2.8214490414,50.8520240784],"type":"Point"}
}