{
  "type": "Feature",
  "properties": {
    "addr:full":"Edith Cavellstraat 31 Ukkel/uccle Bruxelles-Capitale 1180",
    "addr:housenumber":"31",
    "addr:postcode":"1180",
    "addr:street":"Edith Cavellstraat;/",
    "iso:country":"BE",
    "sg:address":"Edith Cavellstraat 31",
    "sg:city":"Ukkel/uccle",
    "sg:orig_category":"Artsen and specialisten",
    "sg:phone":"+32 2 344 63 80",
    "sg:postcode":"1180",
    "sg:province":"Bruxelles-Capitale",
    "wof:name":"Philippe De Saint-georges",
    "wof:placetype":"venue"
},
  "geometry": {"coordinates":[4.3568539619,50.8125801086],"type":"Point"}
}