{
  "type": "Feature",
  "properties": {
    "iso:country":"BE",
    "sg:address":"Guinaumont 6",
    "sg:city":"Ellezelles",
    "sg:orig_category":"Plomberie, chauffage and installations sanitaires. Charpentes and couvertures",
    "sg:phone":"+32 68 54 23 71",
    "sg:postcode":"7890",
    "sg:province":"Hainaut",
    "wof:name":"Jean-paul Cambier",
    "wof:placetype":"venue"
},
  "geometry": {"coordinates":[3.6818060875,50.7373390198],"type":"Point"}
}