{
  "type": "Feature",
  "properties": {
    "addr:full":"Rue Fran\u00c7ois Lorge 51 Namur Namur 5020",
    "addr:housenumber":"51",
    "addr:postcode":"5020",
    "addr:street":"Rue Franc\u0327Ois Lorge",
    "iso:country":"BE",
    "sg:address":"Rue Fran\u00c7ois Lorge 51",
    "sg:city":"Namur",
    "sg:orig_category":"Postkantoren Verzekeringsmakelaars and experts",
    "sg:phone":"+32 81 21 25 10",
    "sg:postcode":"5020",
    "sg:province":"Namur",
    "wof:name":"La Poste",
    "wof:placetype":"venue"
},
  "geometry": {"coordinates":[4.8700342178,50.4819221497],"type":"Point"}
}