{
  "type": "Feature",
  "properties": {
    "addr:full":"Zuidstraat 30 Zonnebeke West-Vlaanderen 8980",
    "addr:housenumber":"30",
    "addr:postcode":"8980",
    "addr:street":"Zuidstraat",
    "iso:country":"BE",
    "sg:address":"Zuidstraat 30",
    "sg:city":"Zonnebeke",
    "sg:orig_category":"Rundveehouders Varkenskwekers",
    "sg:phone":"+32 51 77 78 63",
    "sg:postcode":"8980",
    "sg:province":"West-Vlaanderen",
    "wof:name":"Eric Sioen",
    "wof:placetype":"venue"
},
  "geometry": {"coordinates":[3.0271389484,50.8844909668],"type":"Point"}
}