{
  "type": "Feature",
  "properties": {
    "iso:country":"BE",
    "sg:address":"Europalaan 46",
    "sg:city":"Dilsen-stokkem",
    "sg:orig_category":"S\u00e9curit\u00e9 sociale. Traitements param\u00e9dicaux",
    "sg:phone":"+32 89 75 56 79",
    "sg:postcode":"3650",
    "sg:province":"Limburg",
    "wof:name":"Liberale Mutualiteit",
    "wof:placetype":"venue"
},
  "geometry": {"coordinates":[5.7240672112,51.036907196],"type":"Point"}
}