{
  "type": "Feature",
  "properties": {
    "addr:full":"Helen Bosstraat 60 Linter (orsmaal-gussenhoven) Vlaams-Brabant 3350",
    "addr:housenumber":"60",
    "addr:postcode":"3350",
    "addr:street":"Helen Bosstraat",
    "iso:country":"BE",
    "sg:address":"Helen Bosstraat 60",
    "sg:city":"Linter (orsmaal-gussenhoven)",
    "sg:classifiers":[
        {
            "category":"Health Services",
            "subcategory":"Nursing And Care Facility",
            "type":"Services"
        }
    ],
    "sg:phone":"+32 11 48 56 87",
    "sg:postcode":"3350",
    "sg:province":"Vlaams-Brabant",
    "sg:tags":[
        "home",
        "rest"
    ],
    "wof:name":"Residentie Sorgvliet",
    "wof:placetype":"venue"
},
  "geometry": {"coordinates":[5.0640611649,50.8058929443],"type":"Point"}
}