{
  "type": "Feature",
  "properties": {
    "iso:country":"BE",
    "sg:address":"Zi De Jumet - All\u00e9e Centrale",
    "sg:city":"Jumet",
    "sg:classifiers":[
        {
            "category":"Transit Center",
            "subcategory":"Freight",
            "type":"Transportation"
        }
    ],
    "sg:phone":"+32 71 25 82 00",
    "sg:postcode":"6040",
    "sg:province":"Hainaut",
    "sg:tags":[
        "load",
        "cell",
        "dynamometers"
    ],
    "wof:name":"Sensy S.a.",
    "wof:placetype":"venue"
},
  "geometry": {"coordinates":[4.4558048248,50.4553108215],"type":"Point"}
}