{
  "type": "Feature",
  "properties": {
    "iso:country":"BE",
    "sg:address":"Mechelbaan 167",
    "sg:city":"Putte",
    "sg:orig_category":"Editeurs de journaux. Editeurs de revues and p\u00e9riodiques. Imprimeries and copyshops",
    "sg:phone":"+32 15 75 54 72",
    "sg:postcode":"2580",
    "sg:province":"Antwerpen",
    "wof:name":"Drukkerij Peeters",
    "wof:placetype":"venue"
},
  "geometry": {"coordinates":[4.6525201797,51.0606994629],"type":"Point"}
}