{
  "type": "Feature",
  "properties": {
    "iso:country":"BE",
    "sg:address":"Brugsesteenweg 109",
    "sg:city":"Bredene",
    "sg:classifiers":[
        {
            "category":"Shopping",
            "subcategory":"Shoes",
            "type":"Retail Goods"
        }
    ],
    "sg:phone":"+32 59 33 38 29",
    "sg:postcode":"8450",
    "sg:province":"West-Vlaanderen",
    "sg:tags":[
        "slipper",
        "-"
    ],
    "wof:name":"Fontaine & Verburgh Bvba",
    "wof:placetype":"venue"
},
  "geometry": {"coordinates":[2.9852600098,51.2223815918],"type":"Point"}
}