{
  "type": "Feature",
  "properties": {
    "iso:country":"BE",
    "sg:address":"Thier Martin 18",
    "sg:city":"Herve (battice)",
    "sg:classifiers":[
        {
            "category":"Freight",
            "type":"Transportation"
        }
    ],
    "sg:phone":"+32 87 67 58 60",
    "sg:postcode":"4651",
    "sg:province":"Li\u00e8ge",
    "sg:tags":[
        "-",
        "transport"
    ],
    "wof:name":"Vanaubel Sprl",
    "wof:placetype":"venue"
},
  "geometry": {"coordinates":[5.8202219009,50.6246261597],"type":"Point"}
}