{
  "type": "Feature",
  "properties": {
    "addr:full":"Gustaaf Peetersstraat 3 Ranst Antwerpen 2520",
    "addr:housenumber":"3",
    "addr:postcode":"2520",
    "addr:street":"Gustaaf Peetersstraat",
    "iso:country":"BE",
    "sg:address":"Gustaaf Peetersstraat 3",
    "sg:city":"Ranst",
    "sg:orig_category":"Installation de menuiserie en bois and plastique. Fabrication and montage de mobilier",
    "sg:phone":"+32 3 485 68 69",
    "sg:postcode":"2520",
    "sg:province":"Antwerpen",
    "wof:name":"Verdonck Danny",
    "wof:placetype":"venue"
},
  "geometry": {"coordinates":[4.6028342247,51.181137085],"type":"Point"}
}