{
  "type": "Feature",
  "properties": {
    "addr:full":"Maria-christinastraat 154 Brussel/bruxelles Bruxelles-Capitale 1020",
    "addr:housenumber":"154",
    "addr:postcode":"1020",
    "addr:street":"Maria-Christinastraat;/",
    "iso:country":"BE",
    "sg:address":"Maria-christinastraat 154",
    "sg:city":"Brussel/bruxelles",
    "sg:orig_category":"Herstelling horloges and juwelen Juwelen and horloges",
    "sg:phone":"+32 2 426 80 58",
    "sg:postcode":"1020",
    "sg:province":"Bruxelles-Capitale",
    "wof:name":"Maison Claes",
    "wof:placetype":"venue"
},
  "geometry": {"coordinates":[4.3522248268,50.8758239746],"type":"Point"}
}