{
  "type": "Feature",
  "properties": {
    "iso:country":"BE",
    "sg:address":"Cours Du Bia Bouquet 13",
    "sg:city":"Ottignies-louvain-la-neuve (louvain-la-neuve)",
    "sg:classifiers":[
        {
            "category":"Retail",
            "subcategory":"Repair Shop",
            "type":"Services"
        }
    ],
    "sg:phone":"+32 10 45 07 08",
    "sg:postcode":"1348",
    "sg:province":"Brabant Wallon",
    "sg:tags":[
        "upholsterer"
    ],
    "wof:name":"Lannoy C",
    "wof:placetype":"venue"
},
  "geometry": {"coordinates":[4.6151628494,50.6723442078],"type":"Point"}
}