{
  "type": "Feature",
  "properties": {
    "addr:full":"Rue Des Alli\u00c9s 57 Libramont-chevigny Luxembourg 6800",
    "addr:housenumber":"57",
    "addr:postcode":"6800",
    "addr:street":"Rue Des Allie\u0301S",
    "iso:country":"BE",
    "sg:address":"Rue Des Alli\u00c9s 57",
    "sg:city":"Libramont-chevigny",
    "sg:classifiers":[
        {
            "category":"Sports & Exercise",
            "subcategory":"Sports Center",
            "type":"Entertainment"
        }
    ],
    "sg:phone":"+32 61 22 49 81",
    "sg:postcode":"6800",
    "sg:province":"Luxembourg",
    "sg:tags":[
        "de",
        "fitness"
    ],
    "wof:name":"Fitness Medical Center",
    "wof:placetype":"venue"
},
  "geometry": {"coordinates":[5.3761348724,49.9199943542],"type":"Point"}
}