{
  "type": "Feature",
  "properties": {
    "iso:country":"BE",
    "sg:address":"Rue De Maubeuge 38a",
    "sg:city":"Colfontaine (wasmes)",
    "sg:classifiers":[
        {
            "category":"Professional",
            "subcategory":"Lawyer & Legal Services",
            "type":"Services"
        }
    ],
    "sg:phone":"+32 65 67 41 34",
    "sg:postcode":"7340",
    "sg:province":"Hainaut",
    "sg:tags":[
        "notary"
    ],
    "wof:name":"Brouez L",
    "wof:placetype":"venue"
},
  "geometry": {"coordinates":[3.8540189266,50.4133377075],"type":"Point"}
}