{
  "type": "Feature",
  "properties": {
    "iso:country":"BE",
    "sg:address":"Rue De Fleurus 10",
    "sg:city":"Sombreffe (ligny)",
    "sg:classifiers":[
        {
            "category":"Banks & Credit Unions",
            "subcategory":"Bureau De Change",
            "type":"Services"
        }
    ],
    "sg:phone":"+32 71 81 30 88",
    "sg:postcode":"5140",
    "sg:province":"Namur",
    "sg:tags":[
        "-",
        "household",
        "gas"
    ],
    "wof:name":"Combecar Sa",
    "wof:placetype":"venue"
},
  "geometry": {"coordinates":[4.5642399788,50.4953727722],"type":"Point"}
}