{
  "type": "Feature",
  "properties": {
    "addr:full":"Dijkstaplei 10 Duffel Antwerpen 2570",
    "addr:housenumber":"10",
    "addr:postcode":"2570",
    "addr:street":"Dijkstaplei",
    "iso:country":"BE",
    "sg:address":"Dijkstaplei 10",
    "sg:city":"Duffel",
    "sg:classifiers":[
        {
            "category":"Farming",
            "subcategory":"Crops",
            "type":"Manufacturing & Wholesale Goods"
        }
    ],
    "sg:phone":"+32 15 31 56 21",
    "sg:postcode":"2570",
    "sg:province":"Antwerpen",
    "sg:tags":[
        "vegetable",
        "fruit",
        "-",
        "grower"
    ],
    "wof:name":"Van Looy J",
    "wof:placetype":"venue"
},
  "geometry": {"coordinates":[4.4928078651,51.0769119263],"type":"Point"}
}