{
  "type": "Feature",
  "properties": {
    "iso:country":"BE",
    "sg:address":"Kapellei 42",
    "sg:city":"Zoersel",
    "sg:orig_category":"Herstellingen and onderhoud van auto's Voertuigen",
    "sg:phone":"+32 3 383 06 25",
    "sg:postcode":"2980",
    "sg:province":"Antwerpen",
    "wof:name":"Hendrik De Jaegere",
    "wof:placetype":"venue"
},
  "geometry": {"coordinates":[4.631980896,51.2620887756],"type":"Point"}
}