{
  "type": "Feature",
  "properties": {
    "addr:full":"Rue Neuve 19 Charleroi (montignies-sur-sambre) Hainaut 6061",
    "addr:housenumber":"19",
    "addr:postcode":"6061",
    "addr:street":"Rue Neuve",
    "iso:country":"BE",
    "sg:address":"Rue Neuve 19",
    "sg:city":"Charleroi (montignies-sur-sambre)",
    "sg:classifiers":[
        {
            "category":"Professional",
            "subcategory":"Accounting & Tax Preparation",
            "type":"Services"
        }
    ],
    "sg:phone":"+32 71 36 40 55",
    "sg:postcode":"6061",
    "sg:province":"Hainaut",
    "sg:tags":[
        "bookkeeper"
    ],
    "wof:name":"Co-d-gest Sprl",
    "wof:placetype":"venue"
},
  "geometry": {"coordinates":[4.4574270248,50.4107627869],"type":"Point"}
}