{
  "type": "Feature",
  "properties": {
    "iso:country":"BE",
    "sg:address":"Polderdreef 79",
    "sg:city":"De Pinte",
    "sg:classifiers":[
        {
            "category":"Professional",
            "subcategory":"Management & Consulting",
            "type":"Services"
        }
    ],
    "sg:phone":"+32 2 737 05 20",
    "sg:postcode":"9840",
    "sg:province":"Oost-Vlaanderen",
    "sg:tags":[
        "consultant"
    ],
    "wof:name":"Eurostrat\u00e9gies",
    "wof:placetype":"venue"
},
  "geometry": {"coordinates":[3.6681399345,50.9877929688],"type":"Point"}
}