{
  "type": "Feature",
  "properties": {
    "iso:country":"BE",
    "sg:address":"Pontstraat 84",
    "sg:city":"Zwevegem (heestert)",
    "sg:classifiers":[
        {
            "category":"Personal",
            "subcategory":"Nail Salon",
            "type":"Services"
        }
    ],
    "sg:phone":"+32 56 77 89 59",
    "sg:postcode":"8551",
    "sg:province":"West-Vlaanderen",
    "sg:tags":[
        "pedicure"
    ],
    "wof:name":"Bruneel F",
    "wof:placetype":"venue"
},
  "geometry": {"coordinates":[3.4105200768,50.8003005981],"type":"Point"}
}