{
  "type": "Feature",
  "properties": {
    "addr:full":"Rue Du Moh\u00e9ry 44 Hannut (avin) Li\u00e8ge 4280",
    "addr:housenumber":"44",
    "addr:postcode":"4280",
    "addr:street":"Rue Du Mohe\u0301Ry;Avin",
    "iso:country":"BE",
    "sg:address":"Rue Du Moh\u00e9ry 44",
    "sg:city":"Hannut (avin)",
    "sg:classifiers":[
        {
            "category":"Professional",
            "subcategory":"Printing & Photocopies",
            "type":"Services"
        }
    ],
    "sg:phone":"+32 19 69 94 16",
    "sg:postcode":"4280",
    "sg:province":"Li\u00e8ge",
    "sg:tags":[
        "-",
        "offset"
    ],
    "wof:name":"Daxhelet P Sa",
    "wof:placetype":"venue"
},
  "geometry": {"coordinates":[5.0685610771,50.6202735901],"type":"Point"}
}