{
  "type": "Feature",
  "properties": {
    "addr:full":"Rue Des Viaux 1a Namur (naninne) Namur 5100",
    "addr:housenumber":"1a",
    "addr:postcode":"5100",
    "addr:street":"Rue Des Viaux",
    "iso:country":"BE",
    "sg:address":"Rue Des Viaux 1a",
    "sg:city":"Namur (naninne)",
    "sg:classifiers":[
        {
            "category":"Retail",
            "subcategory":"Auto Repair",
            "type":"Services"
        }
    ],
    "sg:phone":"+32 81 40 11 55",
    "sg:postcode":"5100",
    "sg:province":"Namur",
    "sg:tags":[
        "garage"
    ],
    "wof:name":"Comp\u00e8re (garage)",
    "wof:placetype":"venue"
},
  "geometry": {"coordinates":[4.8713750839,50.4566345215],"type":"Point"}
}