{
  "type": "Feature",
  "properties": {
    "iso:country":"BE",
    "sg:address":"Grand Rue 61",
    "sg:city":"Mons",
    "sg:classifiers":[
        {
            "category":"Shopping",
            "subcategory":"Bicycles & Sporting Goods",
            "type":"Retail Goods"
        }
    ],
    "sg:phone":"+32 65 35 57 83",
    "sg:postcode":"7000",
    "sg:province":"Hainaut",
    "sg:tags":[
        "sport",
        "-"
    ],
    "wof:name":"Sports In Sprl",
    "wof:placetype":"venue"
},
  "geometry": {"coordinates":[3.9496340752,50.4505081177],"type":"Point"}
}