{
  "type": "Feature",
  "properties": {
    "addr:full":"Nestor De Theirrestraat 98 Oudenaarde Oost-Vlaanderen 9700",
    "addr:housenumber":"98",
    "addr:postcode":"9700",
    "addr:street":"Nestor De Theirrestraat",
    "iso:country":"BE",
    "sg:address":"Nestor De Theirrestraat 98",
    "sg:city":"Oudenaarde",
    "sg:orig_category":"Woningbouw",
    "sg:phone":"+32 55 30 12 85",
    "sg:postcode":"9700",
    "sg:province":"Oost-Vlaanderen",
    "wof:name":"Nachtergaele Peter",
    "wof:placetype":"venue"
},
  "geometry": {"coordinates":[3.6176741123,50.8667449951],"type":"Point"}
}