{
  "type": "Feature",
  "properties": {
    "iso:country":"BE",
    "sg:address":"Chauss\u00c9e De Vilvoorde 172",
    "sg:city":"Bruxelles",
    "sg:orig_category":"Sportclubs",
    "sg:phone":"+32 2 268 12 37",
    "sg:postcode":"1120",
    "sg:province":"Bruxelles-Capitale",
    "wof:name":"Aviron Club - Union Nautique De Bxl",
    "wof:placetype":"venue"
},
  "geometry": {"coordinates":[4.4035830498,50.9001693726],"type":"Point"}
}