{
  "type": "Feature",
  "properties": {
    "iso:country":"BE",
    "sg:address":"Rue F Dorzee 21",
    "sg:city":"Boussu",
    "sg:classifiers":[
        {
            "category":"Banks & Credit Unions",
            "subcategory":"Bank",
            "type":"Services"
        }
    ],
    "sg:phone":"+32 65 79 52 91",
    "sg:postcode":"7300",
    "sg:province":"Hainaut",
    "wof:name":"G\u00e9n\u00e9rale De Banque Sa",
    "wof:placetype":"venue"
},
  "geometry": {"coordinates":[3.7975180149,50.4338989258],"type":"Point"}
}