{
  "type": "Feature",
  "properties": {
    "iso:country":"BE",
    "sg:address":"Vaddenhoek 41",
    "sg:city":"Oudenaarde (mullem)",
    "sg:classifiers":[
        {
            "category":"Building & Trades",
            "subcategory":"Electrical",
            "type":"Services"
        }
    ],
    "sg:phone":"+32 9 384 05 10",
    "sg:postcode":"9700",
    "sg:province":"Oost-Vlaanderen",
    "sg:tags":[
        "tool",
        "electric"
    ],
    "wof:name":"G.d. Power Tools Bvba",
    "wof:placetype":"venue"
},
  "geometry": {"coordinates":[3.6081459522,50.8890457153],"type":"Point"}
}