{
  "type": "Feature",
  "properties": {
    "addr:full":"Dorpsstraat 44 Bocholt Limburg 3950",
    "addr:housenumber":"44",
    "addr:postcode":"3950",
    "addr:street":"Dorpsstraat",
    "iso:country":"BE",
    "sg:address":"Dorpsstraat 44",
    "sg:city":"Bocholt",
    "sg:orig_category":"Boucheries",
    "sg:phone":"+32 89 46 10 85",
    "sg:postcode":"3950",
    "sg:province":"Limburg",
    "wof:name":"Pieter Crijns",
    "wof:placetype":"venue"
},
  "geometry": {"coordinates":[5.5804748535,51.170955658],"type":"Point"}
}