{
  "type": "Feature",
  "properties": {
    "addr:full":"Place Des Bienfaiteurs 13 Schaerbeek (bruxelles) Bruxelles-Capitale 1030",
    "addr:housenumber":"13",
    "addr:postcode":"1030",
    "addr:street":"Place Des Bienfaiteurs",
    "iso:country":"BE",
    "sg:address":"Place Des Bienfaiteurs 13",
    "sg:city":"Schaerbeek (bruxelles)",
    "sg:classifiers":[
        {
            "category":"Restaurant",
            "type":"Food & Drink"
        }
    ],
    "sg:phone":"+32 2 242 87 80",
    "sg:postcode":"1030",
    "sg:province":"Bruxelles-Capitale",
    "wof:name":"La Strada",
    "wof:placetype":"venue"
},
  "geometry": {"coordinates":[4.3843841553,50.8575210571],"type":"Point"}
}