{
  "type": "Feature",
  "properties": {
    "addr:full":"Rue De Chantilly 1 Watermaal-bosvoorde/watermael-boitsfort Bruxelles-Capitale 1170",
    "addr:housenumber":"1",
    "addr:postcode":"1170",
    "addr:street":"Rue De Chantilly",
    "iso:country":"BE",
    "sg:address":"Rue De Chantilly 1",
    "sg:city":"Watermaal-bosvoorde/watermael-boitsfort",
    "sg:orig_category":"Plomberie, chauffage and installations sanitaires",
    "sg:phone":"+32 2 675 59 73",
    "sg:postcode":"1170",
    "sg:province":"Bruxelles-Capitale",
    "wof:name":"Claude Kavari",
    "wof:placetype":"venue"
},
  "geometry": {"coordinates":[4.39584589,50.8111305237],"type":"Point"}
}