{
  "type": "Feature",
  "properties": {
    "addr:full":"Dr\u00c8ve Pittoresque 93 Ukkel/uccle Bruxelles-Capitale 1180",
    "addr:housenumber":"93",
    "addr:postcode":"1180",
    "addr:street":"Dre\u0300Ve Pittoresque;/",
    "iso:country":"BE",
    "sg:address":"Dr\u00c8ve Pittoresque 93",
    "sg:city":"Ukkel/uccle",
    "sg:orig_category":"M\u00e9decins and sp\u00e9cialistes",
    "sg:phone":"+32 2 358 06 91",
    "sg:postcode":"1180",
    "sg:province":"Bruxelles-Capitale",
    "wof:name":"Carlos Cabolet",
    "wof:placetype":"venue"
},
  "geometry": {"coordinates":[4.3749079704,50.7708282471],"type":"Point"}
}