{
  "type": "Feature",
  "properties": {
    "iso:country":"BE",
    "sg:address":"Rue De La Station 117",
    "sg:city":"Havelange",
    "sg:classifiers":[
        {
            "category":"Retail",
            "subcategory":"Veterinary Services",
            "type":"Services"
        }
    ],
    "sg:phone":"+32 83 63 40 84",
    "sg:postcode":"5370",
    "sg:province":"Namur",
    "sg:tags":[
        "veterinarian"
    ],
    "wof:name":"Cox P",
    "wof:placetype":"venue"
},
  "geometry": {"coordinates":[5.2463750839,50.3850021362],"type":"Point"}
}