{
  "type": "Feature",
  "properties": {
    "iso:country":"BE",
    "sg:address":"Ieperstraat 311",
    "sg:city":"Menen",
    "sg:classifiers":[
        {
            "category":"Shopping",
            "subcategory":"Clothing, Apparel, & Fashions",
            "type":"Retail Goods"
        }
    ],
    "sg:phone":"+32 56 51 19 06",
    "sg:postcode":"8930",
    "sg:province":"West-Vlaanderen",
    "sg:tags":[
        "fur",
        "fake"
    ],
    "wof:name":"Tyber Nv",
    "wof:placetype":"venue"
},
  "geometry": {"coordinates":[3.1039800644,50.8017578125],"type":"Point"}
}