{
  "type": "Feature",
  "properties": {
    "iso:country":"BE",
    "sg:address":"Rue Des Postes 36",
    "sg:city":"Braine-le-comte",
    "sg:classifiers":[
        {
            "category":"Insurance",
            "subcategory":"Insurance Agent",
            "type":"Services"
        }
    ],
    "sg:phone":"+32 67 55 27 40",
    "sg:postcode":"7090",
    "sg:province":"Hainaut",
    "sg:tags":[
        "verzekeringsmakelaars",
        "expert"
    ],
    "wof:name":"Berteau & Fils",
    "wof:placetype":"venue"
},
  "geometry": {"coordinates":[4.1308898926,50.6112709045],"type":"Point"}
}