{
  "type": "Feature",
  "properties": {
    "iso:country":"BE",
    "sg:address":"Rue Des Wallons 18",
    "sg:city":"Li\u00c8ge",
    "sg:orig_category":"Location de voitures",
    "sg:phone":"+32 4 252 04 54",
    "sg:postcode":"4000",
    "sg:province":"Li\u00e8ge",
    "wof:name":"Autoloc",
    "wof:placetype":"venue"
},
  "geometry": {"coordinates":[5.5592780113,50.6313781738],"type":"Point"}
}