{
  "type": "Feature",
  "properties": {
    "addr:full":"Leuvensestraat 38 Tienen Vlaams-Brabant 3300",
    "addr:housenumber":"38",
    "addr:postcode":"3300",
    "addr:street":"Leuvensestraat",
    "iso:country":"BE",
    "sg:address":"Leuvensestraat 38",
    "sg:city":"Tienen",
    "sg:classifiers":[
        {
            "category":"Food & Beverages",
            "subcategory":"Cheese",
            "type":"Retail Goods"
        }
    ],
    "sg:phone":"+32 16 81 62 45",
    "sg:postcode":"3300",
    "sg:province":"Vlaams-Brabant",
    "sg:tags":[
        "-"
    ],
    "wof:name":"Bartholomeus",
    "wof:placetype":"venue"
},
  "geometry": {"coordinates":[4.9344859123,50.8088340759],"type":"Point"}
}