{
  "type": "Feature",
  "properties": {
    "addr:full":". Merksplas Antwerpen 2330",
    "addr:postcode":"2330",
    "iso:country":"BE",
    "sg:address":".",
    "sg:city":"Merksplas",
    "sg:orig_category":"Apotheken",
    "sg:phone":"+32 900 10 500",
    "sg:postcode":"2330",
    "sg:province":"Antwerpen",
    "wof:name":"Apothekers Van Wacht",
    "wof:placetype":"venue"
},
  "geometry": {"coordinates":[4.863421917,51.3595085144],"type":"Point"}
}