{
  "type": "Feature",
  "properties": {
    "iso:country":"BE",
    "sg:address":"Place Communale 14",
    "sg:city":"Rixensart",
    "sg:classifiers":[
        {
            "category":"Fast Food",
            "type":"Food & Drink"
        }
    ],
    "sg:phone":"+32 2 652 10 73",
    "sg:postcode":"1332",
    "sg:province":"Brabant Wallon",
    "sg:tags":[
        "meeneem",
        "restaurant"
    ],
    "wof:name":"Restaurant Le Pain De Sel",
    "wof:placetype":"venue"
},
  "geometry": {"coordinates":[4.4984102249,50.7163887024],"type":"Point"}
}