{
  "type": "Feature",
  "properties": {
    "iso:country":"BE",
    "sg:address":"Zevekotestraat 3",
    "sg:city":"Poperinge (reningelst)",
    "sg:classifiers":[
        {
            "category":"Food & Beverages",
            "subcategory":"Fruits & Vegetables",
            "type":"Retail Goods"
        }
    ],
    "sg:phone":"+32 57 33 90 19",
    "sg:postcode":"8970",
    "sg:province":"West-Vlaanderen",
    "sg:tags":[
        "-"
    ],
    "wof:name":"Gruwier S",
    "wof:placetype":"venue"
},
  "geometry": {"coordinates":[2.764177084,50.8166656494],"type":"Point"}
}