{
  "type": "Feature",
  "properties": {
    "iso:country":"BE",
    "sg:address":"Schonenberg 32",
    "sg:city":"Sint-lievens-esse",
    "sg:orig_category":"Antiek",
    "sg:phone":"+32 54 50 05 96",
    "sg:postcode":"9550",
    "sg:province":"Oost-Vlaanderen",
    "wof:name":"Antiek Deckers",
    "wof:placetype":"venue"
},
  "geometry": {"coordinates":[3.8749599457,50.8595428467],"type":"Point"}
}