{
  "type": "Feature",
  "properties": {
    "iso:country":"BE",
    "sg:address":"Rue Sergent De Bruyne 18",
    "sg:city":"Anderlecht",
    "sg:classifiers":[
        {
            "category":"Organizations",
            "subcategory":"Community Association",
            "type":"Services"
        }
    ],
    "sg:phone":"+32 2 523 42 55",
    "sg:postcode":"1070",
    "sg:province":"Bruxelles-Capitale",
    "sg:tags":[
        "organisation"
    ],
    "wof:name":"T.c.c. Accueil",
    "wof:placetype":"venue"
},
  "geometry": {"coordinates":[4.3313717842,50.8414001465],"type":"Point"}
}