{
  "type": "Feature",
  "properties": {
    "addr:full":"Braambeierhoekstraat 8 Damme West-Vlaanderen 8340",
    "addr:housenumber":"8",
    "addr:postcode":"8340",
    "addr:street":"Braambeierhoekstraat",
    "iso:country":"BE",
    "sg:address":"Braambeierhoekstraat 8",
    "sg:city":"Damme",
    "sg:orig_category":"Instituts de beaut\u00e9",
    "sg:phone":"+32 50 61 08 13",
    "sg:postcode":"8340",
    "sg:province":"West-Vlaanderen",
    "wof:name":"Pedicure Victoria Nails",
    "wof:placetype":"venue"
},
  "geometry": {"coordinates":[3.2815999985,51.2513160706],"type":"Point"}
}