{
  "type": "Feature",
  "properties": {
    "addr:full":"Rue Des Alli\u00c9s 126 Frameries Hainaut 7080",
    "addr:housenumber":"126",
    "addr:postcode":"7080",
    "addr:street":"Rue Des Allie\u0301S",
    "iso:country":"BE",
    "sg:address":"Rue Des Alli\u00c9s 126",
    "sg:city":"Frameries",
    "sg:classifiers":[
        {
            "category":"Recreation",
            "subcategory":"Dog Park",
            "type":"Entertainment"
        }
    ],
    "sg:phone":"+32 65 67 28 58",
    "sg:postcode":"7080",
    "sg:province":"Hainaut",
    "sg:tags":[
        "dame",
        "lingerie",
        "v\u00eatements",
        "pour",
        "sous-v\u00eatements"
    ],
    "wof:name":"Maison Quenon",
    "wof:placetype":"venue"
},
  "geometry": {"coordinates":[3.8934209347,50.4073638916],"type":"Point"}
}