{
  "type": "Feature",
  "properties": {
    "iso:country":"BE",
    "sg:address":"Rue Camille Daper 17",
    "sg:city":"Neupr\u00e9 (neuville-en-condroz)",
    "sg:classifiers":[
        {
            "category":"Building & Trades",
            "subcategory":"Plumbing",
            "type":"Services"
        }
    ],
    "sg:phone":"+32 4 372 03 11",
    "sg:postcode":"4121",
    "sg:province":"Li\u00e8ge",
    "sg:tags":[
        "repair",
        "mainten",
        "-",
        "central",
        "heating"
    ],
    "wof:name":"Moreau P",
    "wof:placetype":"venue"
},
  "geometry": {"coordinates":[5.4535751343,50.5537033081],"type":"Point"}
}