{
  "type": "Feature",
  "properties": {
    "addr:full":"Stasegemsestraat 34b Harelbeke West-Vlaanderen 8530",
    "addr:housenumber":"34b",
    "addr:postcode":"8530",
    "addr:street":"Stasegemsestraat",
    "iso:country":"BE",
    "sg:address":"Stasegemsestraat 34b",
    "sg:city":"Harelbeke",
    "sg:classifiers":[
        {
            "category":"Professional",
            "subcategory":"Computer Services",
            "type":"Services"
        }
    ],
    "sg:phone":"+32 56 32 39 87",
    "sg:postcode":"8530",
    "sg:province":"West-Vlaanderen",
    "sg:tags":[
        "webdesign",
        "-",
        "internet"
    ],
    "wof:name":"Pinker",
    "wof:placetype":"venue"
},
  "geometry": {"coordinates":[3.308727026,50.8496398926],"type":"Point"}
}