{
  "type": "Feature",
  "properties": {
    "iso:country":"BE",
    "sg:address":"Avenue Voltaire 8b6",
    "sg:city":"Schaarbeek/schaerbeek",
    "sg:orig_category":"Plomberie, chauffage and installations sanitaires",
    "sg:phone":"+32 2 215 01 50",
    "sg:postcode":"1030",
    "sg:province":"Bruxelles-Capitale",
    "wof:name":"J. Renier",
    "wof:placetype":"venue"
},
  "geometry": {"coordinates":[4.3757500648,50.8700675964],"type":"Point"}
}