{
  "type": "Feature",
  "properties": {
    "addr:full":"Kleine Dalstraat 36 Sint-joost-ten-node/saint-josse-ten-noode Bruxelles-Capitale 1210",
    "addr:housenumber":"36",
    "addr:postcode":"1210",
    "addr:street":"Kleine Dalstraat",
    "iso:country":"BE",
    "sg:address":"Kleine Dalstraat 36",
    "sg:city":"Sint-joost-ten-node/saint-josse-ten-noode",
    "sg:orig_category":"Werk and personeelsselectie",
    "sg:phone":"+32 2 219 22 53",
    "sg:postcode":"1210",
    "sg:province":"Bruxelles-Capitale",
    "wof:name":"Services For Europe",
    "wof:placetype":"venue"
},
  "geometry": {"coordinates":[4.3719520569,50.8492279053],"type":"Point"}
}