{
  "type": "Feature",
  "properties": {
    "addr:full":"Walstraat 24 Staden West-Vlaanderen 8840",
    "addr:housenumber":"24",
    "addr:postcode":"8840",
    "addr:street":"Walstraat",
    "iso:country":"BE",
    "sg:address":"Walstraat 24",
    "sg:city":"Staden",
    "sg:orig_category":"Groententeelt",
    "sg:phone":"+32 51 70 15 50",
    "sg:postcode":"8840",
    "sg:province":"West-Vlaanderen",
    "wof:name":"Charles Perdu",
    "wof:placetype":"venue"
},
  "geometry": {"coordinates":[2.9939599037,50.9725494385],"type":"Point"}
}