{
  "type": "Feature",
  "properties": {
    "iso:country":"BE",
    "sg:address":"Rue Edouard Pisvin 18a",
    "sg:city":"Gedinne (rienne)",
    "sg:classifiers":[
        {
            "category":"Personal",
            "subcategory":"Beauty Salon",
            "type":"Services"
        }
    ],
    "sg:phone":"+32 61 58 97 78",
    "sg:postcode":"5575",
    "sg:province":"Namur",
    "sg:tags":[
        "lady",
        "-",
        "hairdressing"
    ],
    "wof:name":"L'epi Rebelle",
    "wof:placetype":"venue"
},
  "geometry": {"coordinates":[4.8848071098,49.9934387207],"type":"Point"}
}