{
  "type": "Feature",
  "properties": {
    "iso:country":"BE",
    "sg:address":"Rue Des Plaiteux 38",
    "sg:city":"Fl\u00c9ron",
    "sg:orig_category":"Locations de machines and \u00e9quipement pour la construction. D\u00e9molition d\u00b4immeubles and terrassements",
    "sg:phone":"+32 4 358 50 09",
    "sg:postcode":"4620",
    "sg:province":"Li\u00e8ge",
    "wof:name":"Justo Transports",
    "wof:placetype":"venue"
},
  "geometry": {"coordinates":[5.6846861839,50.6197357178],"type":"Point"}
}