{
  "type": "Feature",
  "properties": {
    "iso:country":"BE",
    "sg:address":"Herentalse Steenweg 108",
    "sg:city":"Grobbendonk",
    "sg:orig_category":"M\u00e9decins and sp\u00e9cialistes",
    "sg:phone":"+32 14 50 08 67",
    "sg:postcode":"2280",
    "sg:province":"Antwerpen",
    "wof:name":"Gabriel Van Damme",
    "wof:placetype":"venue"
},
  "geometry": {"coordinates":[4.776309967,51.1763801575],"type":"Point"}
}