{
  "type": "Feature",
  "properties": {
    "iso:country":"BE",
    "sg:address":"Kleine Roeselarestraat 22",
    "sg:city":"Meulebeke",
    "sg:orig_category":"Gespecialiseerde residenti\u00eble bouw",
    "sg:phone":"+32 51 48 54 47",
    "sg:postcode":"8760",
    "sg:province":"West-Vlaanderen",
    "wof:name":"Jean Descheemaeker",
    "wof:placetype":"venue"
},
  "geometry": {"coordinates":[3.2533700466,50.9458656311],"type":"Point"}
}