{
  "type": "Feature",
  "properties": {
    "iso:country":"BE",
    "sg:address":"Kerkenheide 52",
    "sg:city":"Kasterlee",
    "sg:classifiers":[
        {
            "category":"Home & Garden",
            "subcategory":"Hardware",
            "type":"Retail Goods"
        }
    ],
    "sg:phone":"+32 496 22 08 38",
    "sg:postcode":"2460",
    "sg:province":"Antwerpen",
    "sg:tags":[
        "fixing",
        "material"
    ],
    "wof:name":"Ega Systems Bvba",
    "wof:placetype":"venue"
},
  "geometry": {"coordinates":[4.9591197968,51.2422676086],"type":"Point"}
}