{
  "type": "Feature",
  "properties": {
    "addr:full":"Boulevard De La R\u00c9vision 50 Anderlecht/anderlecht Bruxelles-Capitale 1070",
    "addr:housenumber":"50",
    "addr:postcode":"1070",
    "addr:street":"Boulevard De La Re\u0301Vision",
    "iso:country":"BE",
    "sg:address":"Boulevard De La R\u00c9vision 50",
    "sg:city":"Anderlecht/anderlecht",
    "sg:orig_category":"Avocats and conseillers juridiques",
    "sg:phone":"+32 2 521 81 62",
    "sg:postcode":"1070",
    "sg:province":"Bruxelles-Capitale",
    "wof:name":"St. Moussis",
    "wof:placetype":"venue"
},
  "geometry": {"coordinates":[4.3285980225,50.8356361389],"type":"Point"}
}