{
  "type": "Feature",
  "properties": {
    "iso:country":"BE",
    "sg:address":"Maurice Lemonnierlaan 171",
    "sg:city":"Brussel/bruxelles",
    "sg:orig_category":"Zalen voor culturele evenementen",
    "sg:phone":"+32 2 513 82 14",
    "sg:postcode":"1000",
    "sg:province":"Bruxelles-Capitale",
    "wof:name":"Centre International",
    "wof:placetype":"venue"
},
  "geometry": {"coordinates":[4.3426032066,50.8417167664],"type":"Point"}
}