{
  "type": "Feature",
  "properties": {
    "iso:country":"BE",
    "sg:address":"Atheneumstraat 2",
    "sg:city":"Leopoldsburg",
    "sg:orig_category":"Centres sportifs",
    "sg:phone":"+32 11 34 31 04",
    "sg:postcode":"3970",
    "sg:province":"Limburg",
    "wof:name":"Sportzaal Kon. Atheneum",
    "wof:placetype":"venue"
},
  "geometry": {"coordinates":[5.2536458969,51.1216659546],"type":"Point"}
}