{
  "type": "Feature",
  "properties": {
    "iso:country":"BE",
    "sg:address":"Brusselsesteenweg 427",
    "sg:city":"Gent (gentbrugge)",
    "sg:classifiers":[
        {
            "category":"Manufacturing",
            "subcategory":"Rubber & Plastics",
            "type":"Manufacturing & Wholesale Goods"
        }
    ],
    "sg:phone":"+32 9 230 20 30",
    "sg:postcode":"9050",
    "sg:province":"Oost-Vlaanderen",
    "sg:tags":[
        "hose"
    ],
    "wof:name":"Air Compact Nv",
    "wof:placetype":"venue"
},
  "geometry": {"coordinates":[3.7542519569,51.0352363586],"type":"Point"}
}