{
  "type": "Feature",
  "properties": {
    "iso:country":"BE",
    "sg:address":"Volpestraat 32",
    "sg:city":"Halle",
    "sg:orig_category":"Editeurs de journaux. Editeurs de revues and p\u00e9riodiques",
    "sg:phone":"+32 2 365 04 11",
    "sg:postcode":"1500",
    "sg:province":"Vlaams-Brabant",
    "wof:name":"De Streekkrant",
    "wof:placetype":"venue"
},
  "geometry": {"coordinates":[4.2344679832,50.7358512878],"type":"Point"}
}