{
  "type": "Feature",
  "properties": {
    "iso:country":"BE",
    "sg:address":"Kerkestukstraat 19",
    "sg:city":"Izegem (kachtem)",
    "sg:classifiers":[
        {
            "category":"Health Services",
            "subcategory":"Nursing And Care Facility",
            "type":"Services"
        }
    ],
    "sg:phone":"+32 51 30 85 58",
    "sg:postcode":"8870",
    "sg:province":"West-Vlaanderen",
    "sg:tags":[
        "home"
    ],
    "wof:name":"Verschaeve C",
    "wof:placetype":"venue"
},
  "geometry": {"coordinates":[3.1874411106,50.9347839355],"type":"Point"}
}