{
  "type": "Feature",
  "properties": {
    "iso:country":"BE",
    "sg:address":"Rue De La Chapelle 28",
    "sg:city":"Chiny",
    "sg:orig_category":"RESTAURANTS: MAISONS DE VACANCES",
    "sg:phone":"+32 61 32 92 08",
    "sg:postcode":"6810",
    "sg:province":"Luxembourg",
    "wof:name":"Le Bouillot",
    "wof:placetype":"venue"
},
  "geometry": {"coordinates":[5.4366431236,49.6839447021],"type":"Point"}
}