{
  "type": "Feature",
  "properties": {
    "iso:country":"BE",
    "sg:address":"Eleonorelaan 31",
    "sg:city":"Sint-pieters-woluwe/woluwe-saint-pierre",
    "sg:orig_category":"Artsen and specialisten",
    "sg:phone":"+32 2 736 78 78",
    "sg:postcode":"1150",
    "sg:province":"Bruxelles-Capitale",
    "wof:name":"Michel Hubain",
    "wof:placetype":"venue"
},
  "geometry": {"coordinates":[4.4091091156,50.8275184631],"type":"Point"}
}