{
  "type": "Feature",
  "properties": {
    "iso:country":"BE",
    "sg:address":"Avenue Paul Pastur 40",
    "sg:city":"Charleroi (monceau-sur-sambre)",
    "sg:classifiers":[
        {
            "category":"Arts & Performance",
            "subcategory":"Theater",
            "type":"Entertainment"
        }
    ],
    "sg:phone":"+32 71 30 39 43",
    "sg:postcode":"6031",
    "sg:province":"Hainaut",
    "sg:tags":[
        "theatrical",
        "agency"
    ],
    "wof:name":"Sd'production",
    "wof:placetype":"venue"
},
  "geometry": {"coordinates":[4.3932318687,50.394821167],"type":"Point"}
}