{
  "type": "Feature",
  "properties": {
    "addr:full":"Koninklijke Baan 54 De Panne West-Vlaanderen 8660",
    "addr:housenumber":"54",
    "addr:postcode":"8660",
    "addr:street":"Koninklijke Baan",
    "iso:country":"BE",
    "sg:address":"Koninklijke Baan 54",
    "sg:city":"De Panne",
    "sg:classifiers":[
        {
            "category":"Manufacturing",
            "subcategory":"Paper Products",
            "type":"Manufacturing & Wholesale Goods"
        }
    ],
    "sg:phone":"+32 58 41 17 20",
    "sg:postcode":"8660",
    "sg:province":"West-Vlaanderen",
    "sg:tags":[
        "packing",
        "cardboard",
        "-"
    ],
    "wof:name":"Visage Bvba",
    "wof:placetype":"venue"
},
  "geometry": {"coordinates":[2.5830800533,51.0971183777],"type":"Point"}
}