{
  "type": "Feature",
  "properties": {
    "iso:country":"BE",
    "sg:address":"Chauss\u00e9e De Tirlemont 205",
    "sg:city":"Gembloux-sur-orneau (gembloux)",
    "sg:classifiers":[
        {
            "category":"Building & Trades",
            "subcategory":"Pest Control",
            "type":"Services"
        }
    ],
    "sg:phone":"+32 81 61 09 58",
    "sg:postcode":"5030",
    "sg:province":"Namur",
    "sg:tags":[
        "painting",
        "contractor"
    ],
    "wof:name":"Croes J L",
    "wof:placetype":"venue"
},
  "geometry": {"coordinates":[4.7199997902,50.5900917053],"type":"Point"}
}