{
  "type": "Feature",
  "properties": {
    "iso:country":"BE",
    "sg:address":"Rue Du Moulin 50",
    "sg:city":"Etalle",
    "sg:orig_category":"Brood, gebak and snoepgoed",
    "sg:phone":"+32 63 45 55 12",
    "sg:postcode":"6740",
    "sg:province":"Luxembourg",
    "wof:name":"Boulangerie Gilquin",
    "wof:placetype":"venue"
},
  "geometry": {"coordinates":[5.5978660583,49.6736412048],"type":"Point"}
}