{
  "type": "Feature",
  "properties": {
    "iso:country":"BE",
    "sg:address":"Rue Neuville 9",
    "sg:city":"Braives (ciplet)",
    "sg:classifiers":[
        {
            "category":"Home & Garden",
            "subcategory":"Building Materials",
            "type":"Retail Goods"
        }
    ],
    "sg:phone":"+32 19 69 86 03",
    "sg:postcode":"4260",
    "sg:province":"Li\u00e8ge",
    "sg:tags":[
        "window"
    ],
    "wof:name":"Smisdom Menuiserie",
    "wof:placetype":"venue"
},
  "geometry": {"coordinates":[5.0888381004,50.6214256287],"type":"Point"}
}