{
  "type": "Feature",
  "properties": {
    "addr:full":"Grand-rue 105 Aubange (athus) Luxembourg 6791",
    "addr:housenumber":"105",
    "addr:postcode":"6791",
    "addr:street":"Grand-Rue",
    "iso:country":"BE",
    "sg:address":"Grand-rue 105",
    "sg:city":"Aubange (athus)",
    "sg:classifiers":[
        {
            "category":"Real Estate",
            "subcategory":"Real Estate Services",
            "type":"Services"
        }
    ],
    "sg:phone":"+32 63 38 29 30",
    "sg:postcode":"6791",
    "sg:province":"Luxembourg",
    "wof:name":"Brion Immo Sa",
    "wof:placetype":"venue"
},
  "geometry": {"coordinates":[5.8368301392,49.5627288818],"type":"Point"}
}