{
  "type": "Feature",
  "properties": {
    "iso:country":"BE",
    "sg:address":"Vierhuizen 63",
    "sg:city":"Kortenberg",
    "sg:orig_category":"Imprimeries and copyshops",
    "sg:phone":"+32 2 759 56 30",
    "sg:postcode":"3070",
    "sg:province":"Vlaams-Brabant",
    "wof:name":"Studio Grafiko",
    "wof:placetype":"venue"
},
  "geometry": {"coordinates":[4.5335249901,50.8797798157],"type":"Point"}
}