{
  "type": "Feature",
  "properties": {
    "iso:country":"BE",
    "sg:address":"Dennenlaan 39",
    "sg:city":"Harelbeke",
    "sg:orig_category":"Belastingconsulenten Boekhouders Diverse juridische dienstverlening",
    "sg:phone":"+32 56 71 33 53",
    "sg:postcode":"8530",
    "sg:province":"West-Vlaanderen",
    "wof:name":"Jos Leroy",
    "wof:placetype":"venue"
},
  "geometry": {"coordinates":[3.3065640926,50.8442878723],"type":"Point"}
}