{
  "type": "Feature",
  "properties": {
    "addr:full":"Patrijsstraat 10 Lommel Limburg 3920",
    "addr:housenumber":"10",
    "addr:postcode":"3920",
    "addr:street":"Patrijsstraat",
    "iso:country":"BE",
    "sg:address":"Patrijsstraat 10",
    "sg:city":"Lommel",
    "sg:orig_category":"Industri\u00eble and commerci\u00eble bouw",
    "sg:phone":"+32 11 64 16 64",
    "sg:postcode":"3920",
    "sg:province":"Limburg",
    "wof:name":"Incobe Staalbouw",
    "wof:placetype":"venue"
},
  "geometry": {"coordinates":[5.3783898354,51.2446403503],"type":"Point"}
}