{
  "type": "Feature",
  "properties": {
    "addr:full":"Bellebargie 1 Waarschoot Oost-Vlaanderen 9950",
    "addr:housenumber":"1",
    "addr:postcode":"9950",
    "addr:street":"Bellebargie",
    "iso:country":"BE",
    "sg:address":"Bellebargie 1",
    "sg:city":"Waarschoot",
    "sg:orig_category":"Dranken",
    "sg:phone":"+32 9 377 12 24",
    "sg:postcode":"9950",
    "sg:province":"Oost-Vlaanderen",
    "wof:name":"Albrecht Braeckman",
    "wof:placetype":"venue"
},
  "geometry": {"coordinates":[3.6288089752,51.1628608704],"type":"Point"}
}