{
  "type": "Feature",
  "properties": {
    "addr:full":"Veldkant 35d Kontich Antwerpen 2550",
    "addr:housenumber":"35d",
    "addr:postcode":"2550",
    "addr:street":"Veldkant",
    "iso:country":"BE",
    "sg:address":"Veldkant 35d",
    "sg:city":"Kontich",
    "sg:classifiers":[
        {
            "category":"Professional",
            "subcategory":"Computer Services",
            "type":"Services"
        }
    ],
    "sg:phone":"+32 3 451 23 82",
    "sg:postcode":"2550",
    "sg:province":"Antwerpen",
    "sg:tags":[
        "-",
        "processing",
        "data",
        "software"
    ],
    "wof:name":"Uptime Technologies Nv",
    "wof:placetype":"venue"
},
  "geometry": {"coordinates":[4.4423899651,51.1417045593],"type":"Point"}
}