{
  "type": "Feature",
  "properties": {
    "iso:country":"BE",
    "sg:address":"Kuringersteenweg 332",
    "sg:city":"Hasselt",
    "sg:classifiers":[
        {
            "category":"Arena",
            "subcategory":"Sports Club",
            "type":"Entertainment"
        }
    ],
    "sg:phone":"+32 11 25 45 25",
    "sg:postcode":"3500",
    "sg:province":"Limburg",
    "wof:name":"Play Ball Snooker Center",
    "wof:placetype":"venue"
},
  "geometry": {"coordinates":[5.3112659454,50.9367523193],"type":"Point"}
}