{
  "type": "Feature",
  "properties": {
    "addr:full":"Chauss\u00e9e De Waterloo 35 Rhode-saint-gen\u00e8se Vlaams-Brabant 1640",
    "addr:housenumber":"35",
    "addr:postcode":"1640",
    "addr:street":"Chausse\u0301E De Waterloo",
    "iso:country":"BE",
    "sg:address":"Chauss\u00e9e De Waterloo 35",
    "sg:city":"Rhode-saint-gen\u00e8se",
    "sg:classifiers":[
        {
            "category":"Home & Garden",
            "subcategory":"Home Furnishings",
            "type":"Retail Goods"
        }
    ],
    "sg:phone":"+32 2 358 40 07",
    "sg:postcode":"1640",
    "sg:province":"Vlaams-Brabant",
    "sg:tags":[
        "-",
        "furniture"
    ],
    "wof:name":"Cinna-dominique Rigo",
    "wof:placetype":"venue"
},
  "geometry": {"coordinates":[4.3950901031,50.7466201782],"type":"Point"}
}