{
  "type": "Feature",
  "properties": {
    "addr:full":"Nijvelsesteenweg 447 Halle Vlaams-Brabant 1500",
    "addr:housenumber":"447",
    "addr:postcode":"1500",
    "addr:street":"Nijvelsesteenweg",
    "iso:country":"BE",
    "sg:address":"Nijvelsesteenweg 447",
    "sg:city":"Halle",
    "sg:classifiers":[
        {
            "category":"Bars & Pubs",
            "type":"Food & Drink"
        }
    ],
    "sg:phone":"+32 2 356 53 01",
    "sg:postcode":"1500",
    "sg:province":"Vlaams-Brabant",
    "wof:name":"De Vijver",
    "wof:placetype":"venue"
},
  "geometry": {"coordinates":[4.2502098083,50.7215118408],"type":"Point"}
}