{
  "type": "Feature",
  "properties": {
    "iso:country":"BE",
    "sg:address":"Nevenplein 35",
    "sg:city":"Bocholt (kaulille)",
    "sg:classifiers":[
        {
            "category":"Health Services",
            "subcategory":"Doctor",
            "type":"Services"
        }
    ],
    "sg:phone":"+32 11 44 84 40",
    "sg:postcode":"3950",
    "sg:province":"Limburg",
    "sg:tags":[
        "medicinephysicians",
        "surgeon"
    ],
    "wof:name":"Henkens E",
    "wof:placetype":"venue"
},
  "geometry": {"coordinates":[5.5188770294,51.1891746521],"type":"Point"}
}