{
  "type": "Feature",
  "properties": {
    "iso:country":"BE",
    "sg:address":"Route De Philippeville 290",
    "sg:city":"Charleroi",
    "sg:orig_category":"M\u00e9decins and sp\u00e9cialistes",
    "sg:phone":"+32 71 36 19 62",
    "sg:postcode":"6010",
    "sg:province":"Hainaut",
    "wof:name":"Mich\u00c8le Garot",
    "wof:placetype":"venue"
},
  "geometry": {"coordinates":[4.4633841515,50.3848762512],"type":"Point"}
}