{
  "type": "Feature",
  "properties": {
    "iso:country":"BE",
    "sg:address":"Brabantstraat 2",
    "sg:city":"Oostende",
    "sg:orig_category":"Cr\u00e9dits divers",
    "sg:postcode":"8400",
    "sg:province":"West-Vlaanderen",
    "wof:name":"Bancontact-mister Cash",
    "wof:placetype":"venue"
},
  "geometry": {"coordinates":[2.9180591106,51.2326278687],"type":"Point"}
}