{
  "type": "Feature",
  "properties": {
    "iso:country":"BE",
    "sg:address":"Rue De L\u00b4eglise 2",
    "sg:city":"Courcelles",
    "sg:orig_category":"Mat\u00e9riaux de construction Gr",
    "sg:phone":"+32 71 45 21 32",
    "sg:postcode":"6182",
    "sg:province":"Hainaut",
    "wof:name":"Fe. De Jonghe",
    "wof:placetype":"venue"
},
  "geometry": {"coordinates":[4.3508062363,50.4496955872],"type":"Point"}
}