{
  "type": "Feature",
  "properties": {
    "addr:full":"Tervaetestraat 1ba Diksmuide West-Vlaanderen 8600",
    "addr:housenumber":"1ba",
    "addr:postcode":"8600",
    "addr:street":"Tervaetestraat",
    "iso:country":"BE",
    "sg:address":"Tervaetestraat 1ba",
    "sg:city":"Diksmuide",
    "sg:classifiers":[
        {
            "category":"Cafe",
            "type":"Food & Drink"
        }
    ],
    "sg:phone":"+32 51 50 33 47",
    "sg:postcode":"8600",
    "sg:province":"West-Vlaanderen",
    "sg:tags":[
        "caf\u00e9s"
    ],
    "wof:name":"De Kroeg",
    "wof:placetype":"venue"
},
  "geometry": {"coordinates":[2.880959034,51.0812263489],"type":"Point"}
}