{
  "type": "Feature",
  "properties": {
    "iso:country":"BE",
    "sg:address":"Lindenlei 98",
    "sg:city":"Schoten",
    "sg:classifiers":[
        {
            "category":"Insurance",
            "subcategory":"Life Insurance",
            "type":"Services"
        }
    ],
    "sg:phone":"+32 3 658 32 85",
    "sg:postcode":"2900",
    "sg:province":"Antwerpen",
    "sg:tags":[
        "assurance"
    ],
    "wof:name":"Marynissen Theo",
    "wof:placetype":"venue"
},
  "geometry": {"coordinates":[4.5156707764,51.2491035461],"type":"Point"}
}