{
  "type": "Feature",
  "properties": {
    "iso:country":"BE",
    "sg:address":"Rue Du Moulin Blanc 9",
    "sg:city":"Binche",
    "sg:classifiers":[
        {
            "category":"Health Services",
            "subcategory":"Health Practitioner",
            "type":"Services"
        }
    ],
    "sg:phone":"+32 64 36 63 63",
    "sg:postcode":"7130",
    "sg:province":"Hainaut",
    "sg:tags":[
        "physiotherapist"
    ],
    "wof:name":"Bourgeois Michel",
    "wof:placetype":"venue"
},
  "geometry": {"coordinates":[4.1673769951,50.4164428711],"type":"Point"}
}