{
  "type": "Feature",
  "properties": {
    "addr:full":"Voorstraat 1-3 Kortrijk West-Vlaanderen 8500",
    "addr:housenumber":"1-3",
    "addr:postcode":"8500",
    "addr:street":"Voorstraat",
    "iso:country":"BE",
    "sg:address":"Voorstraat 1-3",
    "sg:city":"Kortrijk",
    "sg:classifiers":[
        {
            "category":"Shopping",
            "subcategory":"Shoes",
            "type":"Retail Goods"
        }
    ],
    "sg:phone":"+32 56 21 70 71",
    "sg:postcode":"8500",
    "sg:province":"West-Vlaanderen",
    "sg:tags":[
        "slipper",
        "-"
    ],
    "wof:name":"Julien",
    "wof:placetype":"venue"
},
  "geometry": {"coordinates":[3.2706298828,50.8275947571],"type":"Point"}
}