{
  "type": "Feature",
  "properties": {
    "addr:full":"Hortensiastraat 24 Antwerpen Antwerpen 2020",
    "addr:housenumber":"24",
    "addr:postcode":"2020",
    "addr:street":"Hortensiastraat",
    "iso:country":"BE",
    "sg:address":"Hortensiastraat 24",
    "sg:city":"Antwerpen",
    "sg:orig_category":"Binnenhuisarchitecten",
    "sg:phone":"+32 3 238 31 82",
    "sg:postcode":"2020",
    "sg:province":"Antwerpen",
    "wof:name":"Ann Kuppens",
    "wof:placetype":"venue"
},
  "geometry": {"coordinates":[4.3927979469,51.1845283508],"type":"Point"}
}