{
  "type": "Feature",
  "properties": {
    "iso:country":"BE",
    "sg:address":"Vooruitgangstraat 49",
    "sg:city":"Sint-joost-ten-node/saint-josse-ten-noode",
    "sg:classifiers":[
        {
            "category":"Restaurant",
            "type":"Food & Drink"
        }
    ],
    "sg:phone":"+32 2 203 60 06",
    "sg:postcode":"1210",
    "sg:province":"Bruxelles-Capitale",
    "sg:tags":[
        "caf\u00e9s"
    ],
    "wof:name":"Taverne Omnibus",
    "wof:placetype":"venue"
},
  "geometry": {"coordinates":[4.3593702316,50.8578948975],"type":"Point"}
}