{
  "type": "Feature",
  "properties": {
    "iso:country":"BE",
    "sg:address":"Tieltsestraat 37",
    "sg:city":"Ardooie",
    "sg:orig_category":"Pluimveekwekers",
    "sg:phone":"+32 51 74 40 03",
    "sg:postcode":"8851",
    "sg:province":"West-Vlaanderen",
    "wof:name":"Fa. Benoot H. & Zn",
    "wof:placetype":"venue"
},
  "geometry": {"coordinates":[3.2179429531,51.0011482239],"type":"Point"}
}