{
  "type": "Feature",
  "properties": {
    "addr:full":"Olmenstraat 6 Izegem West-Vlaanderen 8870",
    "addr:housenumber":"6",
    "addr:postcode":"8870",
    "addr:street":"Olmenstraat",
    "iso:country":"BE",
    "sg:address":"Olmenstraat 6",
    "sg:city":"Izegem",
    "sg:orig_category":"Installation \u00e9lectrique r\u00e9sidentielle",
    "sg:phone":"+32 51 30 90 15",
    "sg:postcode":"8870",
    "sg:province":"West-Vlaanderen",
    "wof:name":"Bart Ceule",
    "wof:placetype":"venue"
},
  "geometry": {"coordinates":[3.1849720478,50.9139213562],"type":"Point"}
}