{
  "type": "Feature",
  "properties": {
    "addr:full":"Rue Saint-martin 24 Tournai Hainaut 7500",
    "addr:housenumber":"24",
    "addr:postcode":"7500",
    "addr:street":"Rue Saint-Martin",
    "iso:country":"BE",
    "sg:address":"Rue Saint-martin 24",
    "sg:city":"Tournai",
    "sg:classifiers":[
        {
            "category":"Health Services",
            "subcategory":"Chiropractor",
            "type":"Services"
        }
    ],
    "sg:phone":"+32 69 22 63 05",
    "sg:postcode":"7500",
    "sg:province":"Hainaut",
    "wof:name":"Claeys J",
    "wof:placetype":"venue"
},
  "geometry": {"coordinates":[3.3874750137,50.604839325],"type":"Point"}
}