{
  "type": "Feature",
  "properties": {
    "iso:country":"BE",
    "sg:address":"Stationsstraat 9",
    "sg:city":"Zottegem",
    "sg:orig_category":"V\u00eatements pour b\u00e9b\u00e9s and enfants",
    "sg:phone":"+32 9 360 20 68",
    "sg:postcode":"9620",
    "sg:province":"Oost-Vlaanderen",
    "wof:name":"Marie-christine Van Oudenhove",
    "wof:placetype":"venue"
},
  "geometry": {"coordinates":[3.8121409416,50.8690872192],"type":"Point"}
}