{
  "type": "Feature",
  "properties": {
    "addr:full":"Stationsstraat 103 Oostrozebeke West-Vlaanderen 8780",
    "addr:housenumber":"103",
    "addr:postcode":"8780",
    "addr:street":"Stationsstraat",
    "iso:country":"BE",
    "sg:address":"Stationsstraat 103",
    "sg:city":"Oostrozebeke",
    "sg:orig_category":"Viessmann",
    "sg:phone":"+32 56 66 77 88",
    "sg:postcode":"8780",
    "sg:province":"West-Vlaanderen",
    "wof:name":"Vandenberghe Guido",
    "wof:placetype":"venue"
},
  "geometry": {"coordinates":[3.3325419426,50.9151802063],"type":"Point"}
}