{
  "type": "Feature",
  "properties": {
    "addr:full":"Rue De La Fusee 100 Bruxelles Bruxelles-Capitale 1130",
    "addr:housenumber":"100",
    "addr:postcode":"1130",
    "addr:street":"Rue De La Fusee",
    "iso:country":"BE",
    "sg:address":"Rue De La Fusee 100",
    "sg:city":"Bruxelles",
    "sg:orig_category":"Miscellaneous Electronic Tubes And Semiconductors",
    "sg:phone":"+32 2 724 22 21",
    "sg:postcode":"1130",
    "sg:province":"Bruxelles-Capitale",
    "wof:name":"Intersil S.a.",
    "wof:placetype":"venue"
},
  "geometry": {"coordinates":[4.4334049225,50.879535675],"type":"Point"}
}