{
  "type": "Feature",
  "properties": {
    "addr:full":"Roeselstraat 7 Hasselt (kuringen) Limburg 3511",
    "addr:housenumber":"7",
    "addr:postcode":"3511",
    "addr:street":"Roeselstraat",
    "iso:country":"BE",
    "sg:address":"Roeselstraat 7",
    "sg:city":"Hasselt (kuringen)",
    "sg:classifiers":[
        {
            "category":"Shopping",
            "subcategory":"Bicycles & Sporting Goods",
            "type":"Retail Goods"
        }
    ],
    "sg:phone":"+32 11 28 49 03",
    "sg:postcode":"3511",
    "sg:province":"Limburg",
    "sg:tags":[
        "sport",
        "-"
    ],
    "wof:name":"Serge Sport Bvba",
    "wof:placetype":"venue"
},
  "geometry": {"coordinates":[5.3037648201,50.933795929],"type":"Point"}
}