{
  "type": "Feature",
  "properties": {
    "iso:country":"BE",
    "sg:address":"Gouverneur Roppesingel 83",
    "sg:city":"Hasselt",
    "sg:orig_category":"Experts-comptables",
    "sg:phone":"+32 11 28 31 00",
    "sg:postcode":"3500",
    "sg:province":"Limburg",
    "wof:name":"Geert Pauwelyn",
    "wof:placetype":"venue"
},
  "geometry": {"coordinates":[5.3537302017,50.9197692871],"type":"Point"}
}