{
  "type": "Feature",
  "properties": {
    "iso:country":"BE",
    "sg:address":"Rue Mathieu Nisen 328a",
    "sg:city":"Stavelot (francorchamps)",
    "sg:classifiers":[
        {
            "category":"Professional",
            "subcategory":"Accounting & Tax Preparation",
            "type":"Services"
        }
    ],
    "sg:phone":"+32 80 67 01 50",
    "sg:postcode":"4970",
    "sg:province":"Li\u00e8ge",
    "sg:tags":[
        "accountant"
    ],
    "wof:name":"Detrembleur V",
    "wof:placetype":"venue"
},
  "geometry": {"coordinates":[5.970826149,50.4601364136],"type":"Point"}
}