{
  "type": "Feature",
  "properties": {
    "iso:country":"BE",
    "sg:address":"Nieuwstraat 7",
    "sg:city":"Bilzen",
    "sg:classifiers":[
        {
            "category":"Professional",
            "subcategory":"Accounting & Tax Preparation",
            "type":"Services"
        }
    ],
    "sg:phone":"+32 89 65 04 53",
    "sg:postcode":"3740",
    "sg:province":"Limburg",
    "sg:tags":[
        "bookkeeper"
    ],
    "wof:name":"Nunez R",
    "wof:placetype":"venue"
},
  "geometry": {"coordinates":[5.508690834,50.8676719666],"type":"Point"}
}