{
  "type": "Feature",
  "properties": {
    "addr:full":"Broekomstraat 56 Borgloon Limburg 3840",
    "addr:housenumber":"56",
    "addr:postcode":"3840",
    "addr:street":"Broekomstraat",
    "iso:country":"BE",
    "sg:address":"Broekomstraat 56",
    "sg:city":"Borgloon",
    "sg:classifiers":[
        {
            "category":"Shopping",
            "subcategory":"Bicycles & Sporting Goods",
            "type":"Retail Goods"
        }
    ],
    "sg:phone":"+32 12 74 14 77",
    "sg:postcode":"3840",
    "sg:province":"Limburg",
    "sg:tags":[
        "article",
        "de",
        "sport",
        "camping"
    ],
    "wof:name":"Raemaekers",
    "wof:placetype":"venue"
},
  "geometry": {"coordinates":[5.3441700935,50.8012466431],"type":"Point"}
}