{
  "type": "Feature",
  "properties": {
    "iso:country":"BE",
    "sg:address":"Chauss\u00e9e De Namur 10",
    "sg:city":"Eghez\u00e9e",
    "sg:classifiers":[
        {
            "category":"Building & Trades",
            "subcategory":"Equipment Rental",
            "type":"Services"
        }
    ],
    "sg:phone":"+32 81 81 21 43",
    "sg:postcode":"5310",
    "sg:province":"Namur",
    "sg:tags":[
        "tableware",
        "-"
    ],
    "wof:name":"La Vague \u00e0 L'ame",
    "wof:placetype":"venue"
},
  "geometry": {"coordinates":[4.9122810364,50.5904121399],"type":"Point"}
}