{
  "type": "Feature",
  "properties": {
    "addr:full":"Beselarestraat 72 Moorslede West-Vlaanderen 8890",
    "addr:housenumber":"72",
    "addr:postcode":"8890",
    "addr:street":"Beselarestraat",
    "iso:country":"BE",
    "sg:address":"Beselarestraat 72",
    "sg:city":"Moorslede",
    "sg:orig_category":"Artsen and specialisten",
    "sg:phone":"+32 475 45 44 80",
    "sg:postcode":"8890",
    "sg:province":"West-Vlaanderen",
    "wof:name":"Hubert Sigiez",
    "wof:placetype":"venue"
},
  "geometry": {"coordinates":[3.0778059959,50.8493881226],"type":"Point"}
}