{
  "type": "Feature",
  "properties": {
    "iso:country":"BE",
    "sg:address":"Route De Philippeville 435",
    "sg:city":"Charleroi",
    "sg:orig_category":"Kapsalons",
    "sg:phone":"+32 71 43 58 26",
    "sg:postcode":"6010",
    "sg:province":"Hainaut",
    "wof:name":"Coiffure Camille Albane",
    "wof:placetype":"venue"
},
  "geometry": {"coordinates":[4.4660949707,50.3792076111],"type":"Point"}
}