{
  "type": "Feature",
  "properties": {
    "addr:full":"Avenue H Schoofs 7 Oudergem/auderghem Bruxelles-Capitale 1160",
    "addr:housenumber":"7",
    "addr:postcode":"1160",
    "addr:street":"Avenue H Schoofs;/",
    "iso:country":"BE",
    "sg:address":"Avenue H Schoofs 7",
    "sg:city":"Oudergem/auderghem",
    "sg:orig_category":"Traitement de donn\u00e9es",
    "sg:phone":"+32 2 646 38 13",
    "sg:postcode":"1160",
    "sg:province":"Bruxelles-Capitale",
    "wof:name":"Tersys",
    "wof:placetype":"venue"
},
  "geometry": {"coordinates":[4.3991141319,50.8245658875],"type":"Point"}
}