{
  "type": "Feature",
  "properties": {
    "addr:full":"Place Des Quatre Grands 13 Seraing Li\u00e8ge 4101",
    "addr:housenumber":"13",
    "addr:postcode":"4101",
    "addr:street":"Place Des Quatre Grands",
    "iso:country":"BE",
    "sg:address":"Place Des Quatre Grands 13",
    "sg:city":"Seraing",
    "sg:orig_category":"Parfumeries",
    "sg:phone":"+32 4 233 42 57",
    "sg:postcode":"4101",
    "sg:province":"Li\u00e8ge",
    "wof:name":"Institut Elle",
    "wof:placetype":"venue"
},
  "geometry": {"coordinates":[5.5039582253,50.615940094],"type":"Point"}
}