{
  "type": "Feature",
  "properties": {
    "iso:country":"BE",
    "sg:address":"Sint-gummarusstraat 13-15",
    "sg:city":"Lier",
    "sg:classifiers":[
        {
            "category":"Health Services",
            "subcategory":"Health Practitioner",
            "type":"Services"
        }
    ],
    "sg:phone":"+32 3 480 41 65",
    "sg:postcode":"2500",
    "sg:province":"Antwerpen",
    "sg:tags":[
        "physiotherapist"
    ],
    "wof:name":"Van Boven Guy",
    "wof:placetype":"venue"
},
  "geometry": {"coordinates":[4.5749688148,51.1308326721],"type":"Point"}
}