{
  "type": "Feature",
  "properties": {
    "addr:full":"Meren 19 Olen Antwerpen 2250",
    "addr:housenumber":"19",
    "addr:postcode":"2250",
    "addr:street":"Meren",
    "iso:country":"BE",
    "sg:address":"Meren 19",
    "sg:city":"Olen",
    "sg:orig_category":"Producteurs de l\u00e9gumes",
    "sg:phone":"+32 14 21 32 28",
    "sg:postcode":"2250",
    "sg:province":"Antwerpen",
    "wof:name":"Aloysius Soontjens",
    "wof:placetype":"venue"
},
  "geometry": {"coordinates":[4.9189691544,51.1571121216],"type":"Point"}
}