{
  "type": "Feature",
  "properties": {
    "iso:country":"BE",
    "sg:address":"Rue De La Laderie 1bd",
    "sg:city":"La Bruyere",
    "sg:orig_category":"Sportclubs Sportterreinen and installaties behalve sportcentra",
    "sg:phone":"+32 81 21 04 08",
    "sg:postcode":"5080",
    "sg:province":"Namur",
    "wof:name":"U.s. Emines",
    "wof:placetype":"venue"
},
  "geometry": {"coordinates":[4.8378281593,50.5207977295],"type":"Point"}
}