{
  "type": "Feature",
  "properties": {
    "iso:country":"BE",
    "sg:address":"Gasthuisstraat 3",
    "sg:city":"Turnhout",
    "sg:orig_category":"V\u00eatements pour Hommes. V\u00eatements pour Dames",
    "sg:phone":"+32 14 43 89 12",
    "sg:postcode":"2300",
    "sg:province":"Antwerpen",
    "wof:name":"Kreymborg",
    "wof:placetype":"venue"
},
  "geometry": {"coordinates":[4.9476900101,51.3222351074],"type":"Point"}
}