{
  "type": "Feature",
  "properties": {
    "addr:full":"Bad Godesberglaan 21 Kortrijk West-Vlaanderen 8500",
    "addr:housenumber":"21",
    "addr:postcode":"8500",
    "addr:street":"Godesberglaan",
    "iso:country":"BE",
    "sg:address":"Bad Godesberglaan 21",
    "sg:city":"Kortrijk",
    "sg:orig_category":"Instituts pour adultes moins valides",
    "sg:phone":"+32 56 21 46 27",
    "sg:postcode":"8500",
    "sg:province":"West-Vlaanderen",
    "wof:name":"K.o.c. De Lange Munte",
    "wof:placetype":"venue"
},
  "geometry": {"coordinates":[3.3032019138,50.8070297241],"type":"Point"}
}