{
  "type": "Feature",
  "properties": {
    "addr:full":"Rue De Bouillon 8-10 Beauraing Namur 5570",
    "addr:housenumber":"8-10",
    "addr:postcode":"5570",
    "addr:street":"Rue De Bouillon",
    "iso:country":"BE",
    "sg:address":"Rue De Bouillon 8-10",
    "sg:city":"Beauraing",
    "sg:classifiers":[
        {
            "category":"Shopping",
            "subcategory":"Hobbies, Toys, & Games",
            "type":"Retail Goods"
        }
    ],
    "sg:phone":"+32 82 71 02 62",
    "sg:postcode":"5570",
    "sg:province":"Namur",
    "sg:tags":[
        "toy",
        "-"
    ],
    "wof:name":"Demars Jouets",
    "wof:placetype":"venue"
},
  "geometry": {"coordinates":[4.9559721947,50.1096992493],"type":"Point"}
}