{
  "type": "Feature",
  "properties": {
    "addr:full":"Handzamestraat 30b Kortemark West-Vlaanderen 8610",
    "addr:housenumber":"30b",
    "addr:postcode":"8610",
    "addr:street":"Handzamestraat",
    "iso:country":"BE",
    "sg:address":"Handzamestraat 30b",
    "sg:city":"Kortemark",
    "sg:classifiers":[
        {
            "category":"Banks & Credit Unions",
            "subcategory":"Bank",
            "type":"Services"
        }
    ],
    "sg:postcode":"8610",
    "sg:province":"West-Vlaanderen",
    "sg:tags":[
        "savings-banks"
    ],
    "wof:name":"Kantoor Tanghe",
    "wof:placetype":"venue"
},
  "geometry": {"coordinates":[3.0354189873,51.0293884277],"type":"Point"}
}