{
  "type": "Feature",
  "properties": {
    "addr:full":"Topmolen 90 Londerzeel Vlaams-Brabant 1840",
    "addr:housenumber":"90",
    "addr:postcode":"1840",
    "addr:street":"Topmolen",
    "iso:country":"BE",
    "sg:address":"Topmolen 90",
    "sg:city":"Londerzeel",
    "sg:orig_category":"Non-Classified Establishments",
    "sg:phone":"+32 52 30 15 34",
    "sg:postcode":"1840",
    "sg:province":"Vlaams-Brabant",
    "wof:name":"Dierickx N",
    "wof:placetype":"venue"
},
  "geometry": {"coordinates":[4.2943301201,51.0254135132],"type":"Point"}
}