{
  "type": "Feature",
  "properties": {
    "iso:country":"BE",
    "sg:address":"Machelenstraat 21",
    "sg:city":"Deinze",
    "sg:orig_category":"Sportclubs",
    "sg:phone":"+32 9 386 69 55",
    "sg:postcode":"9800",
    "sg:province":"Oost-Vlaanderen",
    "wof:name":"Dartsclub De Buckey's",
    "wof:placetype":"venue"
},
  "geometry": {"coordinates":[3.525949955,50.9768486023],"type":"Point"}
}