{
  "type": "Feature",
  "properties": {
    "addr:full":"Rue Du Vigneron 125 Charleroi Hainaut 6043",
    "addr:housenumber":"125",
    "addr:postcode":"6043",
    "addr:street":"Rue Du Vigneron;Hainaut",
    "iso:country":"BE",
    "sg:address":"Rue Du Vigneron 125",
    "sg:city":"Charleroi",
    "sg:classifiers":[
        {
            "category":"Arena",
            "subcategory":"Sports Club",
            "type":"Entertainment"
        }
    ],
    "sg:phone":"+32 71 35 70 48",
    "sg:postcode":"6043",
    "sg:province":"Hainaut",
    "sg:tags":[
        "de"
    ],
    "wof:name":"C.s.v. Ransart",
    "wof:placetype":"venue"
},
  "geometry": {"coordinates":[4.4839549065,50.4479637146],"type":"Point"}
}