{
  "type": "Feature",
  "properties": {
    "addr:full":"Weggevoerdenlaan 14 Kortrijk West-Vlaanderen 8500",
    "addr:housenumber":"14",
    "addr:postcode":"8500",
    "addr:street":"Weggevoerdenlaan",
    "iso:country":"BE",
    "sg:address":"Weggevoerdenlaan 14",
    "sg:city":"Kortrijk",
    "sg:classifiers":[
        {
            "category":"Bars & Pubs",
            "type":"Food & Drink"
        }
    ],
    "sg:phone":"+32 56 21 42 18",
    "sg:postcode":"8500",
    "sg:province":"West-Vlaanderen",
    "wof:name":"Sir\u00e8ne (la)",
    "wof:placetype":"venue"
},
  "geometry": {"coordinates":[3.2491650581,50.8172645569],"type":"Point"}
}