{
  "type": "Feature",
  "properties": {
    "addr:full":"Werviksestraat 32 Ieper West-Vlaanderen 8902",
    "addr:housenumber":"32",
    "addr:postcode":"8902",
    "addr:street":"Werviksestraat",
    "iso:country":"BE",
    "sg:address":"Werviksestraat 32",
    "sg:city":"Ieper",
    "sg:orig_category":"Entretien and r\u00e9parations de voitures",
    "sg:phone":"+32 57 20 04 11",
    "sg:postcode":"8902",
    "sg:province":"West-Vlaanderen",
    "wof:name":"Garage Titeca-warlop",
    "wof:placetype":"venue"
},
  "geometry": {"coordinates":[2.9242188931,50.8336372375],"type":"Point"}
}