{
  "type": "Feature",
  "properties": {
    "addr:full":"Onderwijsstraat 19 Menen West-Vlaanderen 8930",
    "addr:housenumber":"19",
    "addr:postcode":"8930",
    "addr:street":"Onderwijsstraat",
    "iso:country":"BE",
    "sg:address":"Onderwijsstraat 19",
    "sg:city":"Menen",
    "sg:orig_category":"Sportclubs",
    "sg:phone":"+32 56 53 12 75",
    "sg:postcode":"8930",
    "sg:province":"West-Vlaanderen",
    "wof:name":"Aikido Menen",
    "wof:placetype":"venue"
},
  "geometry": {"coordinates":[3.113863945,50.8053245544],"type":"Point"}
}