{
  "type": "Feature",
  "properties": {
    "addr:full":"Rue Emile Muraille 134 Herstal Li\u00e8ge 4040",
    "addr:housenumber":"134",
    "addr:postcode":"4040",
    "addr:street":"Rue Emile Muraille",
    "iso:country":"BE",
    "sg:address":"Rue Emile Muraille 134",
    "sg:city":"Herstal",
    "sg:classifiers":[
        {
            "category":"Arena",
            "subcategory":"Sports Club",
            "type":"Entertainment"
        }
    ],
    "sg:phone":"+32 4 264 10 06",
    "sg:postcode":"4040",
    "sg:province":"Li\u00e8ge",
    "wof:name":"Happy Dance Club Herstal",
    "wof:placetype":"venue"
},
  "geometry": {"coordinates":[5.6166529655,50.6734809875],"type":"Point"}
}