{
  "type": "Feature",
  "properties": {
    "iso:country":"BE",
    "sg:address":"Sluizeken 1",
    "sg:city":"Gent",
    "sg:orig_category":"Verplichte sociale verzekeringen",
    "sg:phone":"+32 9 225 63 23",
    "sg:postcode":"9000",
    "sg:province":"Oost-Vlaanderen",
    "wof:name":"De Behulpzame Broeders",
    "wof:placetype":"venue"
},
  "geometry": {"coordinates":[3.7238070965,51.0597381592],"type":"Point"}
}