{
  "type": "Feature",
  "properties": {
    "addr:full":"Industrieweg 45 Roeselare West-Vlaanderen 8800",
    "addr:housenumber":"45",
    "addr:postcode":"8800",
    "addr:street":"Industrieweg",
    "iso:country":"BE",
    "sg:address":"Industrieweg 45",
    "sg:city":"Roeselare",
    "sg:classifiers":[
        {
            "category":"Manufacturing",
            "subcategory":"Paper Products",
            "type":"Manufacturing & Wholesale Goods"
        }
    ],
    "sg:phone":"+32 51 24 24 65",
    "sg:postcode":"8800",
    "sg:province":"West-Vlaanderen",
    "sg:tags":[
        "bookbinding"
    ],
    "wof:name":"Devolder M Ver Boekbinderijen-relieurs Associ\u00e9s",
    "wof:placetype":"venue"
},
  "geometry": {"coordinates":[3.1282289028,50.9779434204],"type":"Point"}
}