{
  "type": "Feature",
  "properties": {
    "addr:full":"Van Hovestraat 1 Kruibeke Oost-Vlaanderen 9150",
    "addr:housenumber":"1",
    "addr:postcode":"9150",
    "addr:street":"Van Hovestraat",
    "iso:country":"BE",
    "sg:address":"Van Hovestraat 1",
    "sg:city":"Kruibeke",
    "sg:orig_category":"Fournitures de bureau",
    "sg:phone":"+32 3 774 01 18",
    "sg:postcode":"9150",
    "sg:province":"Oost-Vlaanderen",
    "wof:name":"Kantoormachines A Lardon",
    "wof:placetype":"venue"
},
  "geometry": {"coordinates":[4.3087711334,51.1720504761],"type":"Point"}
}