{
  "type": "Feature",
  "properties": {
    "addr:full":"Rue Des Inhauts 9 Namur (boninne - Gelbress\u00e9e) Namur 5021",
    "addr:housenumber":"9",
    "addr:postcode":"5021",
    "addr:street":"Rue Des Inhauts",
    "iso:country":"BE",
    "sg:address":"Rue Des Inhauts 9",
    "sg:city":"Namur (boninne - Gelbress\u00e9e)",
    "sg:classifiers":[
        {
            "category":"Wholesale",
            "subcategory":"Wine & Distilled Alcoholic Beverages",
            "type":"Manufacturing & Wholesale Goods"
        }
    ],
    "sg:phone":"+32 81 21 24 49",
    "sg:postcode":"5021",
    "sg:province":"Namur",
    "sg:tags":[
        "whol",
        "-",
        "spirit",
        "mfg"
    ],
    "wof:name":"Alsavin",
    "wof:placetype":"venue"
},
  "geometry": {"coordinates":[4.9366002083,50.4962081909],"type":"Point"}
}