{
  "type": "Feature",
  "properties": {
    "iso:country":"BE",
    "sg:address":"Bokslaarstraat 96",
    "sg:city":"Lokeren",
    "sg:orig_category":"Eleveurs de bovins",
    "sg:phone":"+32 9 348 85 53",
    "sg:postcode":"9160",
    "sg:province":"Oost-Vlaanderen",
    "wof:name":"Alfons Staessens",
    "wof:placetype":"venue"
},
  "geometry": {"coordinates":[3.9958279133,51.0894584656],"type":"Point"}
}