{
  "type": "Feature",
  "properties": {
    "addr:full":"Hogeweg 2ba Jabbeke West-Vlaanderen 8490",
    "addr:housenumber":"2ba",
    "addr:postcode":"8490",
    "addr:street":"Hogeweg",
    "iso:country":"BE",
    "sg:address":"Hogeweg 2ba",
    "sg:city":"Jabbeke",
    "sg:orig_category":"Groententeelt",
    "sg:phone":"+32 50 39 54 96",
    "sg:postcode":"8490",
    "sg:province":"West-Vlaanderen",
    "wof:name":"Marleen Rabaey",
    "wof:placetype":"venue"
},
  "geometry": {"coordinates":[3.1473140717,51.2043838501],"type":"Point"}
}