{
  "type": "Feature",
  "properties": {
    "addr:full":"Mechelsesteenweg 10b16 Kampenhout Vlaams-Brabant 1910",
    "addr:housenumber":"10b16",
    "addr:postcode":"1910",
    "addr:street":"Mechelsesteenweg",
    "iso:country":"BE",
    "sg:address":"Mechelsesteenweg 10b16",
    "sg:city":"Kampenhout",
    "sg:orig_category":"Verlichting and huishoudartikelen",
    "sg:phone":"+32 16 61 70 83",
    "sg:postcode":"1910",
    "sg:province":"Vlaams-Brabant",
    "wof:name":"Huis Lichtwereld",
    "wof:placetype":"venue"
},
  "geometry": {"coordinates":[4.5910429955,50.9571723938],"type":"Point"}
}