{
  "type": "Feature",
  "properties": {
    "iso:country":"BE",
    "sg:address":"Platte Heegtestraat 29",
    "sg:city":"Bornem",
    "sg:orig_category":"Groententeelt Rundveehouders",
    "sg:phone":"+32 3 899 02 41",
    "sg:postcode":"2880",
    "sg:province":"Antwerpen",
    "wof:name":"Dirk De Wachter",
    "wof:placetype":"venue"
},
  "geometry": {"coordinates":[4.2511148453,51.0832862854],"type":"Point"}
}