{
  "type": "Feature",
  "properties": {
    "iso:country":"BE",
    "sg:address":"Rue De La Franco-belge 28",
    "sg:city":"La Louvi\u00e8re",
    "sg:classifiers":[
        {
            "category":"Bars & Pubs",
            "type":"Food & Drink"
        }
    ],
    "sg:phone":"+32 64 22 94 80",
    "sg:postcode":"7100",
    "sg:province":"Hainaut",
    "wof:name":"Porte Du Prince (la)",
    "wof:placetype":"venue"
},
  "geometry": {"coordinates":[4.206633091,50.4872627258],"type":"Point"}
}