{
  "type": "Feature",
  "properties": {
    "addr:full":"Callestraat 1 Laarne Oost-Vlaanderen 9270",
    "addr:housenumber":"1",
    "addr:postcode":"9270",
    "addr:street":"Callestraat",
    "iso:country":"BE",
    "sg:address":"Callestraat 1",
    "sg:city":"Laarne",
    "sg:classifiers":[
        {
            "category":"Wholesale",
            "subcategory":"Plants",
            "type":"Manufacturing & Wholesale Goods"
        }
    ],
    "sg:phone":"+32 9 369 99 08",
    "sg:postcode":"9270",
    "sg:province":"Oost-Vlaanderen",
    "sg:tags":[
        "whol",
        "flower",
        "-",
        "grower"
    ],
    "wof:name":"Engels R",
    "wof:placetype":"venue"
},
  "geometry": {"coordinates":[3.8848741055,51.0598907471],"type":"Point"}
}