{
  "type": "Feature",
  "properties": {
    "iso:country":"BE",
    "sg:address":"Bareelstraat 15",
    "sg:city":"Geraardsbergen",
    "sg:orig_category":"Assurances. Bureaux de poste",
    "sg:phone":"+32 54 50 02 51",
    "sg:postcode":"9506",
    "sg:province":"Oost-Vlaanderen",
    "wof:name":"De Post",
    "wof:placetype":"venue"
},
  "geometry": {"coordinates":[3.8985300064,50.7987060547],"type":"Point"}
}