{
  "type": "Feature",
  "properties": {
    "iso:country":"BE",
    "sg:address":"Vin\u00e2ve D'ile 3",
    "sg:city":"Li\u00e8ge 1",
    "sg:classifiers":[
        {
            "category":"Shopping",
            "subcategory":"Clothing, Apparel, & Fashions",
            "type":"Retail Goods"
        }
    ],
    "sg:phone":"+32 4 250 06 61",
    "sg:postcode":"4000",
    "sg:province":"Li\u00e8ge",
    "sg:tags":[
        "boutique"
    ],
    "wof:name":"Celio",
    "wof:placetype":"venue"
},
  "geometry": {"coordinates":[5.5710740089,50.6421127319],"type":"Point"}
}