{
  "type": "Feature",
  "properties": {
    "addr:full":"Lierbaan 8 Putte Antwerpen 2580",
    "addr:housenumber":"8",
    "addr:postcode":"2580",
    "addr:street":"Lierbaan",
    "iso:country":"BE",
    "sg:address":"Lierbaan 8",
    "sg:city":"Putte",
    "sg:classifiers":[
        {
            "category":"Fast Food",
            "type":"Food & Drink"
        }
    ],
    "sg:phone":"+32 15 75 42 30",
    "sg:postcode":"2580",
    "sg:province":"Antwerpen",
    "sg:tags":[
        "meeneem",
        "restaurant"
    ],
    "wof:name":"New China",
    "wof:placetype":"venue"
},
  "geometry": {"coordinates":[4.6289777756,51.0552558899],"type":"Point"}
}