{
  "type": "Feature",
  "properties": {
    "addr:full":"Rue De Taillis-pr\u00c9 5 Chatelet Hainaut 6200",
    "addr:housenumber":"5",
    "addr:postcode":"6200",
    "addr:street":"Rue De Taillis-Pre\u0301;Hainaut",
    "iso:country":"BE",
    "sg:address":"Rue De Taillis-pr\u00c9 5",
    "sg:city":"Chatelet",
    "sg:orig_category":"Banques and organismes de cr\u00e9dit",
    "sg:phone":"+32 71 38 62 15",
    "sg:postcode":"6200",
    "sg:province":"Hainaut",
    "wof:name":"Bbl",
    "wof:placetype":"venue"
},
  "geometry": {"coordinates":[4.5056028366,50.4320411682],"type":"Point"}
}