{
  "type": "Feature",
  "properties": {
    "iso:country":"BE",
    "sg:address":"Rue Du Panorama 6bb",
    "sg:city":"Verviers",
    "sg:orig_category":"Sportclubs Sportterreinen and installaties behalve sportcentra",
    "sg:phone":"+32 87 34 09 71",
    "sg:postcode":"4801",
    "sg:province":"Li\u00e8ge",
    "wof:name":"R. Ent. Dison Verviers",
    "wof:placetype":"venue"
},
  "geometry": {"coordinates":[5.8930549622,50.5922393799],"type":"Point"}
}