{
  "type": "Feature",
  "properties": {
    "iso:country":"BE",
    "sg:address":"Rue Des Annettes 53",
    "sg:city":"Ottignies-louvain-la-neuve",
    "sg:orig_category":"Architecten",
    "sg:phone":"+32 10 45 05 12",
    "sg:postcode":"1348",
    "sg:province":"Brabant Wallon",
    "wof:name":"Poels",
    "wof:placetype":"venue"
},
  "geometry": {"coordinates":[4.6067361832,50.6717300415],"type":"Point"}
}