{
  "type": "Feature",
  "properties": {
    "iso:country":"BE",
    "sg:address":"Maasstraat 44",
    "sg:city":"Antwerpen",
    "sg:classifiers":[
        {
            "category":"Banks & Credit Unions",
            "subcategory":"Investment Brokerage",
            "type":"Services"
        }
    ],
    "sg:phone":"+32 3 231 55 44",
    "sg:postcode":"2060",
    "sg:province":"Antwerpen",
    "sg:tags":[
        "flat",
        "grinding",
        "glass"
    ],
    "wof:name":"R. Anseeuw En Zoon B.v.b.a.",
    "wof:placetype":"venue"
},
  "geometry": {"coordinates":[4.4273738861,51.2349815369],"type":"Point"}
}