{
  "type": "Feature",
  "properties": {
    "addr:full":"Uitbreidingstraat 11a Lint Antwerpen 2547",
    "addr:housenumber":"11a",
    "addr:postcode":"2547",
    "addr:street":"Uitbreidingstraat",
    "iso:country":"BE",
    "sg:address":"Uitbreidingstraat 11a",
    "sg:city":"Lint",
    "sg:classifiers":[
        {
            "category":"Professional",
            "type":"Services"
        }
    ],
    "sg:phone":"+32 3 455 95 86",
    "sg:postcode":"2547",
    "sg:province":"Antwerpen",
    "sg:tags":[
        "surveyor",
        "-",
        "valuer"
    ],
    "wof:name":"Fabri J",
    "wof:placetype":"venue"
},
  "geometry": {"coordinates":[4.4890007973,51.1305084229],"type":"Point"}
}