{
  "type": "Feature",
  "properties": {
    "iso:country":"BE",
    "sg:address":"Grand'rue 12",
    "sg:city":"Habay",
    "sg:orig_category":"Apotheken",
    "sg:phone":"+32 63 41 01 11",
    "sg:postcode":"6724",
    "sg:province":"Luxembourg",
    "wof:name":"Pharmacie Ponette",
    "wof:placetype":"venue"
},
  "geometry": {"coordinates":[5.5386037827,49.7265663147],"type":"Point"}
}