{
  "type": "Feature",
  "properties": {
    "iso:country":"BE",
    "sg:address":"Langstraat 102",
    "sg:city":"Westerlo",
    "sg:orig_category":"Boekhouders",
    "sg:phone":"+32 14 54 98 37",
    "sg:postcode":"2260",
    "sg:province":"Antwerpen",
    "wof:name":"Van Der Auwera Jozef",
    "wof:placetype":"venue"
},
  "geometry": {"coordinates":[4.9120759964,51.1147193909],"type":"Point"}
}