{
  "type": "Feature",
  "properties": {
    "iso:country":"BE",
    "sg:address":"Grote Ieperstraat 131",
    "sg:city":"Wevelgem",
    "sg:orig_category":"Woningbouw",
    "sg:phone":"+32 56 41 13 44",
    "sg:postcode":"8560",
    "sg:province":"West-Vlaanderen",
    "wof:name":"Phyfferoen",
    "wof:placetype":"venue"
},
  "geometry": {"coordinates":[3.1995251179,50.8358345032],"type":"Point"}
}