{
  "type": "Feature",
  "properties": {
    "addr:full":"Risquons-toutstraat 8b Kortrijk (aalbeke) West-Vlaanderen 8511",
    "addr:housenumber":"8b",
    "addr:postcode":"8511",
    "addr:street":"Risquons-Toutstraat",
    "iso:country":"BE",
    "sg:address":"Risquons-toutstraat 8b",
    "sg:city":"Kortrijk (aalbeke)",
    "sg:classifiers":[
        {
            "category":"Retail",
            "subcategory":"Auto Repair",
            "type":"Services"
        }
    ],
    "sg:phone":"+32 56 43 53 35",
    "sg:postcode":"8511",
    "sg:province":"West-Vlaanderen",
    "sg:tags":[
        "automobile-body"
    ],
    "wof:name":"Devos Motors Nv",
    "wof:placetype":"venue"
},
  "geometry": {"coordinates":[3.2302849293,50.7784767151],"type":"Point"}
}