{
  "type": "Feature",
  "properties": {
    "iso:country":"BE",
    "sg:address":"Ouwegemsesteenweg 30",
    "sg:city":"Zingem",
    "sg:orig_category":"Installation de menuiserie en bois and plastique. Eclairage et \u00e9quipements du foyer",
    "sg:phone":"+32 9 384 41 20",
    "sg:postcode":"9750",
    "sg:province":"Oost-Vlaanderen",
    "wof:name":"Van Poucke Interieurservice",
    "wof:placetype":"venue"
},
  "geometry": {"coordinates":[3.6115300655,50.9101982117],"type":"Point"}
}