{
  "type": "Feature",
  "properties": {
    "addr:full":"Veemarkt 18-20a Kortrijk West-Vlaanderen 8500",
    "addr:housenumber":"18-20a",
    "addr:postcode":"8500",
    "addr:street":"Veemarkt",
    "iso:country":"BE",
    "sg:address":"Veemarkt 18-20a",
    "sg:city":"Kortrijk",
    "sg:classifiers":[
        {
            "category":"Wholesale",
            "subcategory":"Fruits & Vegetables",
            "type":"Manufacturing & Wholesale Goods"
        }
    ],
    "sg:phone":"+32 56 22 26 70",
    "sg:postcode":"8500",
    "sg:province":"West-Vlaanderen",
    "sg:tags":[
        "whol",
        "-"
    ],
    "wof:name":"Crevits-van Exem W",
    "wof:placetype":"venue"
},
  "geometry": {"coordinates":[3.2728099823,50.8262367249],"type":"Point"}
}