{
  "type": "Feature",
  "properties": {
    "iso:country":"BE",
    "sg:address":"Rue Des Rhieux 1",
    "sg:city":"Seraing",
    "sg:orig_category":"Syst\u00e8mes de t\u00e9l\u00e9communications",
    "sg:phone":"+32 4 234 70 20",
    "sg:postcode":"4101",
    "sg:province":"Li\u00e8ge",
    "wof:name":"Belgacom Telebusiness",
    "wof:placetype":"venue"
},
  "geometry": {"coordinates":[5.5027961731,50.6182594299],"type":"Point"}
}