{
  "type": "Feature",
  "properties": {
    "addr:full":"Avenue De La Grande Boucle 15 Braine L'alleud (braine-l'alleud) Brabant Wallon 1420",
    "addr:housenumber":"15",
    "addr:postcode":"1420",
    "addr:street":"Avenue De La Grande Boucle",
    "iso:country":"BE",
    "sg:address":"Avenue De La Grande Boucle 15",
    "sg:city":"Braine L'alleud (braine-l'alleud)",
    "sg:classifiers":[
        {
            "category":"Communications",
            "subcategory":"Film & Video Production",
            "type":"Services"
        }
    ],
    "sg:phone":"+32 2 354 40 11",
    "sg:postcode":"1420",
    "sg:province":"Brabant Wallon",
    "sg:tags":[
        "producer",
        "realizators"
    ],
    "wof:name":"Productions Du Sablier",
    "wof:placetype":"venue"
},
  "geometry": {"coordinates":[-118.0959396362,45.3295402527],"type":"Point"}
}