{
  "type": "Feature",
  "properties": {
    "iso:country":"BE",
    "sg:address":"Guido Gezellelaan 145",
    "sg:city":"Puurs",
    "sg:classifiers":[
        {
            "category":"Food & Beverages",
            "subcategory":"Supermarket",
            "type":"Retail Goods"
        }
    ],
    "sg:phone":"+32 3 899 63 13",
    "sg:postcode":"2870",
    "sg:province":"Antwerpen",
    "sg:tags":[
        "department",
        "store"
    ],
    "wof:name":"Okay",
    "wof:placetype":"venue"
},
  "geometry": {"coordinates":[4.2905597687,51.0746612549],"type":"Point"}
}