{
  "type": "Feature",
  "properties": {
    "iso:country":"BE",
    "sg:address":"Langeveldstraat 166",
    "sg:city":"Ukkel/uccle",
    "sg:orig_category":"Sportclubs",
    "sg:phone":"+32 2 374 21 82",
    "sg:postcode":"1180",
    "sg:province":"Bruxelles-Capitale",
    "wof:name":"H.c. Langeveld",
    "wof:placetype":"venue"
},
  "geometry": {"coordinates":[4.3667612076,50.8059005737],"type":"Point"}
}