{
  "type": "Feature",
  "properties": {
    "iso:country":"BE",
    "sg:address":"Ooststraat 33",
    "sg:city":"Oostende",
    "sg:orig_category":"Juwelen and horloges Krantenuitgeverijen Tijdschriftenuitgeverijen",
    "sg:phone":"+32 59 51 16 22",
    "sg:postcode":"8400",
    "sg:province":"West-Vlaanderen",
    "wof:name":"Antw. Diam. Gold Discount",
    "wof:placetype":"venue"
},
  "geometry": {"coordinates":[2.9192409515,51.2306556702],"type":"Point"}
}