{
  "type": "Feature",
  "properties": {
    "addr:full":"Volderstraat 17 Dentergem West-Vlaanderen 8720",
    "addr:housenumber":"17",
    "addr:postcode":"8720",
    "addr:street":"Volderstraat",
    "iso:country":"BE",
    "sg:address":"Volderstraat 17",
    "sg:city":"Dentergem",
    "sg:orig_category":"Herstellingen and onderhoud van auto's",
    "sg:phone":"+32 9 388 83 07",
    "sg:postcode":"8720",
    "sg:province":"West-Vlaanderen",
    "wof:name":"Wim Walcarius",
    "wof:placetype":"venue"
},
  "geometry": {"coordinates":[3.4252109528,50.9377822876],"type":"Point"}
}