{
  "type": "Feature",
  "properties": {
    "addr:full":"Kasteelstraat 48 Sint-pieters-leeuw Vlaams-Brabant 1600",
    "addr:housenumber":"48",
    "addr:postcode":"1600",
    "addr:street":"Kasteelstraat",
    "iso:country":"BE",
    "sg:address":"Kasteelstraat 48",
    "sg:city":"Sint-pieters-leeuw",
    "sg:classifiers":[
        {
            "category":"Education",
            "subcategory":"University",
            "type":"Public Place"
        }
    ],
    "sg:phone":"+32 2 334 85 55",
    "sg:postcode":"1600",
    "sg:province":"Vlaams-Brabant",
    "sg:tags":[
        "higher"
    ],
    "wof:name":"Continental Theological Seminary",
    "wof:placetype":"venue"
},
  "geometry": {"coordinates":[4.2570400238,50.8011016846],"type":"Point"}
}