{
  "type": "Feature",
  "properties": {
    "iso:country":"BE",
    "sg:address":"Avenue Des Martyrs 300",
    "sg:city":"Fleron",
    "sg:orig_category":"Catering and organisatie van feesten Slagers Voedingsspeciaalzaken",
    "sg:phone":"+32 4 358 22 32",
    "sg:postcode":"4620",
    "sg:province":"Li\u00e8ge",
    "wof:name":"Traiteur Schumacher Roger",
    "wof:placetype":"venue"
},
  "geometry": {"coordinates":[5.6854968071,50.6145133972],"type":"Point"}
}