{
  "type": "Feature",
  "properties": {
    "addr:full":"Helstraat 25 Kortessem (vliermaalroot) Limburg 3721",
    "addr:housenumber":"25",
    "addr:postcode":"3721",
    "addr:street":"Helstraat",
    "iso:country":"BE",
    "sg:address":"Helstraat 25",
    "sg:city":"Kortessem (vliermaalroot)",
    "sg:classifiers":[
        {
            "category":"Building & Trades",
            "subcategory":"Electrical",
            "type":"Services"
        }
    ],
    "sg:phone":"+32 11 37 61 17",
    "sg:postcode":"3721",
    "sg:province":"Limburg",
    "sg:tags":[
        "electric",
        "-",
        "housewiring",
        "contractor"
    ],
    "wof:name":"Simons Elektro Bvba",
    "wof:placetype":"venue"
},
  "geometry": {"coordinates":[5.42628479,50.8703079224],"type":"Point"}
}