{
  "type": "Feature",
  "properties": {
    "iso:country":"BE",
    "sg:address":"Place De La Lib\u00c9ration 3",
    "sg:city":"Li\u00c8ge",
    "sg:orig_category":"Enseignement maternel and primaire",
    "sg:phone":"+32 4 343 37 63",
    "sg:postcode":"4020",
    "sg:province":"Li\u00e8ge",
    "wof:name":"Ecole Fond. Communale",
    "wof:placetype":"venue"
},
  "geometry": {"coordinates":[5.6045260429,50.6475372314],"type":"Point"}
}