{
  "type": "Feature",
  "properties": {
    "iso:country":"BE",
    "sg:address":"Marais Du Pr\u00c9 5",
    "sg:city":"Mont-de-l'enclus",
    "sg:orig_category":"Eleveurs de bovins",
    "sg:phone":"+32 69 76 81 56",
    "sg:postcode":"7750",
    "sg:province":"Hainaut",
    "wof:name":"Christian Spillers",
    "wof:placetype":"venue"
},
  "geometry": {"coordinates":[5.7178230286,47.0204772949],"type":"Point"}
}