{
  "type": "Feature",
  "properties": {
    "iso:country":"BE",
    "sg:address":"Spoele 48",
    "sg:city":"Lokeren",
    "sg:orig_category":"Rundveehouders",
    "sg:phone":"+32 9 348 16 60",
    "sg:postcode":"9160",
    "sg:province":"Oost-Vlaanderen",
    "wof:name":"Emilienne Staessens",
    "wof:placetype":"venue"
},
  "geometry": {"coordinates":[3.9946649075,51.0910758972],"type":"Point"}
}