{
  "type": "Feature",
  "properties": {
    "addr:full":"Zeelaan 172 Koksijde West-Vlaanderen 8670",
    "addr:housenumber":"172",
    "addr:postcode":"8670",
    "addr:street":"Zeelaan",
    "iso:country":"BE",
    "sg:address":"Zeelaan 172",
    "sg:city":"Koksijde",
    "sg:orig_category":"Avocats and conseillers juridiques",
    "sg:phone":"+32 58 52 12 12",
    "sg:postcode":"8670",
    "sg:province":"West-Vlaanderen",
    "wof:name":"P. Thomas",
    "wof:placetype":"venue"
},
  "geometry": {"coordinates":[2.6371200085,51.1170692444],"type":"Point"}
}