{
  "type": "Feature",
  "properties": {
    "iso:country":"BE",
    "sg:address":"Chauss\u00c9e De Gand 134",
    "sg:city":"Mouscron",
    "sg:orig_category":"Onderdelen and accessoires voor auto's",
    "sg:phone":"+32 56 33 19 55",
    "sg:postcode":"7700",
    "sg:province":"Hainaut",
    "wof:name":"Hollebeke",
    "wof:placetype":"venue"
},
  "geometry": {"coordinates":[3.2042899132,50.7602310181],"type":"Point"}
}