{
  "type": "Feature",
  "properties": {
    "addr:full":"Ternatstraat 35 Ternat (sint-katherina-lombeek) Vlaams-Brabant 1742",
    "addr:housenumber":"35",
    "addr:postcode":"1742",
    "addr:street":"Ternatstraat",
    "iso:country":"BE",
    "sg:address":"Ternatstraat 35",
    "sg:city":"Ternat (sint-katherina-lombeek)",
    "sg:classifiers":[
        {
            "category":"Health Services",
            "subcategory":"Doctor",
            "type":"Services"
        }
    ],
    "sg:phone":"+32 2 582 30 34",
    "sg:postcode":"1742",
    "sg:province":"Vlaams-Brabant",
    "sg:tags":[
        "medicinephysicians",
        "surgeon"
    ],
    "wof:name":"Impens N",
    "wof:placetype":"venue"
},
  "geometry": {"coordinates":[4.1604528427,50.8733444214],"type":"Point"}
}