{
  "type": "Feature",
  "properties": {
    "iso:country":"BE",
    "sg:address":"Brusselsesteenweg 24",
    "sg:city":"Grimbergen",
    "sg:classifiers":[
        {
            "category":"Professional",
            "subcategory":"Computer Services",
            "type":"Services"
        }
    ],
    "sg:phone":"+32 2 251 59 23",
    "sg:postcode":"1850",
    "sg:province":"Vlaams-Brabant",
    "sg:tags":[
        "repair",
        "processing",
        "-",
        "maintenance",
        "data"
    ],
    "wof:name":"First Service Nv",
    "wof:placetype":"venue"
},
  "geometry": {"coordinates":[4.3638219833,50.9340629578],"type":"Point"}
}