{
  "type": "Feature",
  "properties": {
    "iso:country":"BE",
    "sg:address":"Pater Beckersstraat 10",
    "sg:city":"Heusden-zolder (heusden)",
    "sg:classifiers":[
        {
            "category":"Professional",
            "subcategory":"Lawyer & Legal Services",
            "type":"Services"
        }
    ],
    "sg:phone":"+32 11 42 77 33",
    "sg:postcode":"3550",
    "sg:province":"Limburg",
    "wof:name":"Boes Jo",
    "wof:placetype":"venue"
},
  "geometry": {"coordinates":[5.2472882271,51.0336608887],"type":"Point"}
}