{
  "type": "Feature",
  "properties": {
    "iso:country":"BE",
    "sg:address":"Verboekt 94",
    "sg:city":"Laakdal",
    "sg:orig_category":"HUISBRANDOLIE",
    "sg:phone":"+32 13 66 14 13",
    "sg:postcode":"2430",
    "sg:province":"Antwerpen",
    "wof:name":"Fa. Bijloos Ludo",
    "wof:placetype":"venue"
},
  "geometry": {"coordinates":[5.0754990578,51.0896759033],"type":"Point"}
}