{
  "type": "Feature",
  "properties": {
    "addr:full":"Torhoutsesteenweg 501 Oostende West-Vlaanderen 8400",
    "addr:housenumber":"501",
    "addr:postcode":"8400",
    "addr:street":"Torhoutsesteenweg",
    "iso:country":"BE",
    "sg:address":"Torhoutsesteenweg 501",
    "sg:city":"Oostende",
    "sg:orig_category":"D\u00e9taillants en pi\u00e8ces and accessoires de voitures",
    "sg:phone":"+32 59 70 94 28",
    "sg:postcode":"8400",
    "sg:province":"West-Vlaanderen",
    "wof:name":"Aed",
    "wof:placetype":"venue"
},
  "geometry": {"coordinates":[2.9048950672,51.209236145],"type":"Point"}
}