{
  "type": "Feature",
  "properties": {
    "addr:full":"Leopoldstraat 43 Zwevegem West-Vlaanderen 8550",
    "addr:housenumber":"43",
    "addr:postcode":"8550",
    "addr:street":"Leopoldstraat",
    "iso:country":"BE",
    "sg:address":"Leopoldstraat 43",
    "sg:city":"Zwevegem",
    "sg:orig_category":"Non-Classified Establishments",
    "sg:phone":"+32 56 20 49 19",
    "sg:postcode":"8550",
    "sg:province":"West-Vlaanderen",
    "wof:name":"Cher Fashion-crossways",
    "wof:placetype":"venue"
},
  "geometry": {"coordinates":[3.335985899,50.8111152649],"type":"Point"}
}