{
  "type": "Feature",
  "properties": {
    "addr:full":"Rue Haute 77 Bruxelles Bruxelles-Capitale 1000",
    "addr:housenumber":"77",
    "addr:postcode":"1000",
    "addr:street":"Rue Haute",
    "iso:country":"BE",
    "sg:address":"Rue Haute 77",
    "sg:city":"Bruxelles",
    "sg:classifiers":[
        {
            "category":"Professional",
            "subcategory":"Art Services",
            "type":"Services"
        }
    ],
    "sg:phone":"+32 2 511 33 74",
    "sg:postcode":"1000",
    "sg:province":"Bruxelles-Capitale",
    "sg:tags":[
        "-",
        "furniture"
    ],
    "wof:name":"Deschuytere M",
    "wof:placetype":"venue"
},
  "geometry": {"coordinates":[4.35100317,50.8400115967],"type":"Point"}
}