{
  "type": "Feature",
  "properties": {
    "addr:full":"Kaudenaardestraat 71 Dilbeek (groot) Vlaams-Brabant 1700",
    "addr:housenumber":"71",
    "addr:postcode":"1700",
    "addr:street":"Kaudenaardestraat;Groot Vlaams-Brabant",
    "iso:country":"BE",
    "sg:address":"Kaudenaardestraat 71",
    "sg:city":"Dilbeek (groot)",
    "sg:orig_category":"Tissage de la soie",
    "sg:phone":"+32 2 569 39 39",
    "sg:postcode":"1700",
    "sg:province":"Vlaams-Brabant",
    "wof:name":"Vostex",
    "wof:placetype":"venue"
},
  "geometry": {"coordinates":[4.2750501633,50.8424377441],"type":"Point"}
}