{
  "type": "Feature",
  "properties": {
    "iso:country":"BE",
    "sg:address":"Rue Saint-georges 5",
    "sg:city":"Jodoigne",
    "sg:orig_category":"Producteurs de fruits",
    "sg:phone":"+32 10 81 09 22",
    "sg:postcode":"1370",
    "sg:province":"Brabant Wallon",
    "wof:name":"Batinvest",
    "wof:placetype":"venue"
},
  "geometry": {"coordinates":[4.8963260651,50.7393531799],"type":"Point"}
}