{
  "type": "Feature",
  "properties": {
    "addr:full":"Steenstraat 13 Diksmuide West-Vlaanderen 8600",
    "addr:housenumber":"13",
    "addr:postcode":"8600",
    "addr:street":"Steenstraat",
    "iso:country":"BE",
    "sg:address":"Steenstraat 13",
    "sg:city":"Diksmuide",
    "sg:orig_category":"Eleveurs de bovins. Eleveurs and marchands de porcs. Boucheries",
    "sg:phone":"+32 51 50 10 81",
    "sg:postcode":"8600",
    "sg:province":"West-Vlaanderen",
    "wof:name":"Karlo Vandenberghe",
    "wof:placetype":"venue"
},
  "geometry": {"coordinates":[2.9147059917,51.0090751648],"type":"Point"}
}