{
  "type": "Feature",
  "properties": {
    "iso:country":"BE",
    "sg:address":"Quai Fernand Demets 4b8",
    "sg:city":"Anderlecht",
    "sg:orig_category":"Boekhouders",
    "sg:phone":"+32 2 520 04 99",
    "sg:postcode":"1070",
    "sg:province":"Bruxelles-Capitale",
    "wof:name":"Di Giugno Jacques",
    "wof:placetype":"venue"
},
  "geometry": {"coordinates":[4.3168969154,50.837146759],"type":"Point"}
}