{
  "type": "Feature",
  "properties": {
    "addr:full":"Rue Chalet 9 Sint-joost-ten-node/saint-joss Bruxelles-Capitale 1210",
    "addr:housenumber":"9",
    "addr:postcode":"1210",
    "addr:street":"Rue Chalet",
    "iso:country":"BE",
    "sg:address":"Rue Chalet 9",
    "sg:city":"Sint-joost-ten-node/saint-joss",
    "sg:orig_category":"Organisations religieuses and philosophiques",
    "sg:phone":"+32 2 219 66 90",
    "sg:postcode":"1210",
    "sg:province":"Bruxelles-Capitale",
    "wof:name":"Eglise Evang\u00c9lique",
    "wof:placetype":"venue"
},
  "geometry": {"coordinates":[4.3726577759,50.8525161743],"type":"Point"}
}