{
  "type": "Feature",
  "properties": {
    "iso:country":"BE",
    "sg:address":"Eendrachtstraat 115",
    "sg:city":"Gent",
    "sg:orig_category":"Artistes ind\u00e9pendants",
    "sg:phone":"+32 9 223 67 06",
    "sg:postcode":"9000",
    "sg:province":"Oost-Vlaanderen",
    "wof:name":"Engels",
    "wof:placetype":"venue"
},
  "geometry": {"coordinates":[3.7450890541,51.0473098755],"type":"Point"}
}