{
  "type": "Feature",
  "properties": {
    "addr:full":"30 Rue F Robbrechts 1780 Wemmel 30",
    "addr:housenumber":"30;30",
    "addr:postcode":"1780",
    "addr:street":"Rue F Robbrechts;Wemmel",
    "iso:country":"BE",
    "sg:address":"30",
    "sg:city":"Rue F Robbrechts 1780 Wemmel",
    "sg:classifiers":[
        {
            "category":"Wholesale",
            "subcategory":"Machinery & Supplies",
            "type":"Manufacturing & Wholesale Goods"
        }
    ],
    "sg:phone":"+32 2 460 40 65",
    "sg:postcode":"30",
    "sg:tags":[
        "food",
        "processing",
        "-",
        "machine",
        "equipment",
        "engineering",
        "mechanical"
    ],
    "wof:name":"Rovacos",
    "wof:placetype":"venue"
},
  "geometry": {"coordinates":[4.3195648193,50.9174156189],"type":"Point"}
}