{
  "type": "Feature",
  "properties": {
    "addr:full":"Schaffelbergstraat 6 Glabbeek (bunsbeek) Vlaams-Brabant 3380",
    "addr:housenumber":"6",
    "addr:postcode":"3380",
    "addr:street":"Schaffelbergstraat",
    "iso:country":"BE",
    "sg:address":"Schaffelbergstraat 6",
    "sg:city":"Glabbeek (bunsbeek)",
    "sg:classifiers":[
        {
            "category":"Professional",
            "subcategory":"Management & Consulting",
            "type":"Services"
        }
    ],
    "sg:phone":"+32 16 77 03 59",
    "sg:postcode":"3380",
    "sg:province":"Vlaams-Brabant",
    "sg:tags":[
        "-",
        "processing",
        "data",
        "consultant"
    ],
    "wof:name":"Van Herck M",
    "wof:placetype":"venue"
},
  "geometry": {"coordinates":[4.9650301933,50.8476104736],"type":"Point"}
}