{
  "type": "Feature",
  "properties": {
    "iso:country":"BE",
    "sg:address":"Scheldestraat 23",
    "sg:city":"Antwerpen",
    "sg:orig_category":"Huishoudapparaten, televisies and radio's",
    "sg:phone":"+32 3 238 17 50",
    "sg:postcode":"2000",
    "sg:province":"Antwerpen",
    "wof:name":"Luc De Laet",
    "wof:placetype":"venue"
},
  "geometry": {"coordinates":[4.3930640221,51.2126846313],"type":"Point"}
}