{
  "type": "Feature",
  "properties": {
    "addr:full":"Grote Steenweg 35 Zomergem Oost-Vlaanderen 9930",
    "addr:housenumber":"35",
    "addr:postcode":"9930",
    "addr:street":"Grote Steenweg",
    "iso:country":"BE",
    "sg:address":"Grote Steenweg 35",
    "sg:city":"Zomergem",
    "sg:orig_category":"Rev\u00eatements de sols and murs. Constructions r\u00e9sidentielles sp\u00e9cifiques. Rev\u00eatements pour sols and mu",
    "sg:phone":"+32 9 372 95 01",
    "sg:postcode":"9930",
    "sg:province":"Oost-Vlaanderen",
    "wof:name":"Guy Laneuw",
    "wof:placetype":"venue"
},
  "geometry": {"coordinates":[3.5782139301,51.1143875122],"type":"Point"}
}