{
  "type": "Feature",
  "properties": {
    "addr:full":"Avenue De La R\u00e9sistance 253 Soumagne Li\u00e8ge 4630",
    "addr:housenumber":"253",
    "addr:postcode":"4630",
    "addr:street":"Avenue De La Re\u0301Sistance",
    "iso:country":"BE",
    "sg:address":"Avenue De La R\u00e9sistance 253",
    "sg:city":"Soumagne",
    "sg:classifiers":[
        {
            "category":"Building & Trades",
            "subcategory":"Electrical",
            "type":"Services"
        }
    ],
    "sg:phone":"+32 4 377 23 57",
    "sg:postcode":"4630",
    "sg:province":"Li\u00e8ge",
    "sg:tags":[
        "electric",
        "-",
        "housewiring",
        "contractor"
    ],
    "wof:name":"Gomez Basilio",
    "wof:placetype":"venue"
},
  "geometry": {"coordinates":[5.7349281311,50.6308059692],"type":"Point"}
}