{
  "type": "Feature",
  "properties": {
    "iso:country":"BE",
    "sg:address":"Regenbooglaan 11",
    "sg:city":"Zwijndrecht",
    "sg:classifiers":[
        {
            "category":"Shopping",
            "subcategory":"Bicycles & Sporting Goods",
            "type":"Retail Goods"
        }
    ],
    "sg:phone":"+32 3 252 52 92",
    "sg:postcode":"2070",
    "sg:province":"Antwerpen",
    "sg:tags":[
        "sport",
        "-"
    ],
    "wof:name":"Stijn Sport",
    "wof:placetype":"venue"
},
  "geometry": {"coordinates":[4.3290410042,51.2163848877],"type":"Point"}
}