{
  "type": "Feature",
  "properties": {
    "iso:country":"BE",
    "sg:address":"Chauss\u00e9e D'asse 111",
    "sg:city":"Enghien (petit-enghien)",
    "sg:classifiers":[
        {
            "category":"Home & Garden",
            "subcategory":"Building Materials",
            "type":"Retail Goods"
        }
    ],
    "sg:phone":"+32 2 395 53 13",
    "sg:postcode":"7850",
    "sg:province":"Hainaut",
    "sg:tags":[
        "window"
    ],
    "wof:name":"Plastic-hall Devriese",
    "wof:placetype":"venue"
},
  "geometry": {"coordinates":[4.0513978004,50.6981544495],"type":"Point"}
}