{
  "type": "Feature",
  "properties": {
    "addr:full":"Rue Du Nouveau Monde 17a Soignies Hainaut 7060",
    "addr:housenumber":"17a",
    "addr:postcode":"7060",
    "addr:street":"Rue Du Nouveau Monde",
    "iso:country":"BE",
    "sg:address":"Rue Du Nouveau Monde 17a",
    "sg:city":"Soignies",
    "sg:classifiers":[
        {
            "category":"Home & Garden",
            "subcategory":"Home Furnishings",
            "type":"Retail Goods"
        }
    ],
    "sg:phone":"+32 67 33 16 72",
    "sg:postcode":"7060",
    "sg:province":"Hainaut",
    "sg:tags":[
        "interior",
        "decoration"
    ],
    "wof:name":"Atrea",
    "wof:placetype":"venue"
},
  "geometry": {"coordinates":[4.0671272278,50.5752029419],"type":"Point"}
}