{
  "type": "Feature",
  "properties": {
    "iso:country":"BE",
    "sg:address":"Rue Van Ysendyck 20",
    "sg:city":"Schaarbeek/schaerbeek",
    "sg:orig_category":"Imprimeries and copyshops",
    "sg:phone":"+32 2 242 41 43",
    "sg:postcode":"1030",
    "sg:province":"Bruxelles-Capitale",
    "wof:name":"Euroffset",
    "wof:placetype":"venue"
},
  "geometry": {"coordinates":[4.3797669411,50.8685798645],"type":"Point"}
}