{
  "type": "Feature",
  "properties": {
    "addr:full":"Voordelaan 26 Sint-martens-latem Oost-Vlaanderen 9831",
    "addr:housenumber":"26",
    "addr:postcode":"9831",
    "addr:street":"Voordelaan",
    "iso:country":"BE",
    "sg:address":"Voordelaan 26",
    "sg:city":"Sint-martens-latem",
    "sg:orig_category":"Instituts de beaut\u00e9",
    "sg:phone":"+32 9 281 21 12",
    "sg:postcode":"9831",
    "sg:province":"Oost-Vlaanderen",
    "wof:name":"Pascale Andries",
    "wof:placetype":"venue"
},
  "geometry": {"coordinates":[3.599848032,51.0126724243],"type":"Point"}
}