{
  "type": "Feature",
  "properties": {
    "addr:full":"Roereken 18 Baelen Li\u00e8ge 4837",
    "addr:housenumber":"18",
    "addr:postcode":"4837",
    "addr:street":"Roereken",
    "iso:country":"BE",
    "sg:address":"Roereken 18",
    "sg:city":"Baelen",
    "sg:orig_category":"Installation de serres, double vitrage and fen\u00eatres",
    "sg:phone":"+32 87 55 46 07",
    "sg:postcode":"4837",
    "sg:province":"Li\u00e8ge",
    "wof:name":"Evers",
    "wof:placetype":"venue"
},
  "geometry": {"coordinates":[6.0071101189,50.6311378479],"type":"Point"}
}