{
  "type": "Feature",
  "properties": {
    "addr:full":"Meersenstraat 10 Ichtegem West-Vlaanderen 8480",
    "addr:housenumber":"10",
    "addr:postcode":"8480",
    "addr:street":"Meersenstraat",
    "iso:country":"BE",
    "sg:address":"Meersenstraat 10",
    "sg:city":"Ichtegem",
    "sg:orig_category":"Rundveehouders",
    "sg:phone":"+32 59 29 93 35",
    "sg:postcode":"8480",
    "sg:province":"West-Vlaanderen",
    "wof:name":"Michel Vanhollebeke",
    "wof:placetype":"venue"
},
  "geometry": {"coordinates":[3.0161049366,51.1454811096],"type":"Point"}
}