{
  "type": "Feature",
  "properties": {
    "iso:country":"BE",
    "sg:address":"Steendamstraat 1",
    "sg:city":"Alveringem",
    "sg:classifiers":[
        {
            "category":"Building & Trades",
            "subcategory":"Electrical",
            "type":"Services"
        }
    ],
    "sg:phone":"+32 495 69 24 56",
    "sg:postcode":"8690",
    "sg:province":"West-Vlaanderen",
    "sg:tags":[
        "electric",
        "-",
        "housewiring",
        "contractor"
    ],
    "wof:name":"Godd\u00e9lec",
    "wof:placetype":"venue"
},
  "geometry": {"coordinates":[2.7424340248,51.0255813599],"type":"Point"}
}