{
  "type": "Feature",
  "properties": {
    "iso:country":"BE",
    "sg:address":"Pieter Michielsstraat 59",
    "sg:city":"Sint-pieters-leeuw (ruisbroek)",
    "sg:classifiers":[
        {
            "category":"Shopping",
            "subcategory":"Hobbies, Toys, & Games",
            "type":"Retail Goods"
        }
    ],
    "sg:phone":"+32 2 377 14 77",
    "sg:postcode":"1601",
    "sg:province":"Vlaams-Brabant",
    "sg:tags":[
        "toy",
        "-"
    ],
    "wof:name":"A.d.a.l. Bvba",
    "wof:placetype":"venue"
},
  "geometry": {"coordinates":[4.2931280136,50.7851791382],"type":"Point"}
}