{
  "type": "Feature",
  "properties": {
    "iso:country":"BE",
    "sg:address":"Chemin Des Cr\u00c8tes 1",
    "sg:city":"Esneux",
    "sg:orig_category":"Verhuur cateringmateriaal and evenementuitrusting Verhuur diversen Winkelinrichting and handelsuitru",
    "sg:phone":"+32 4 380 23 48",
    "sg:postcode":"4130",
    "sg:province":"Li\u00e8ge",
    "wof:name":"Fe. Mobitentes",
    "wof:placetype":"venue"
},
  "geometry": {"coordinates":[5.5548219681,50.5293197632],"type":"Point"}
}