{
  "type": "Feature",
  "properties": {
    "addr:full":"Klapdorp 67 Sint-gillis-waas (sint-pauwels) Oost-Vlaanderen 9170",
    "addr:housenumber":"67",
    "addr:postcode":"9170",
    "addr:street":"Klapdorp;Sint-Pauwels",
    "iso:country":"BE",
    "sg:address":"Klapdorp 67",
    "sg:city":"Sint-gillis-waas (sint-pauwels)",
    "sg:classifiers":[
        {
            "category":"Arts & Performance",
            "subcategory":"Theater",
            "type":"Entertainment"
        }
    ],
    "sg:phone":"+32 3 765 17 77",
    "sg:postcode":"9170",
    "sg:province":"Oost-Vlaanderen",
    "sg:tags":[
        "group",
        "theatre"
    ],
    "wof:name":"Oekedoeleke",
    "wof:placetype":"venue"
},
  "geometry": {"coordinates":[4.0904998779,51.1898460388],"type":"Point"}
}