{
  "type": "Feature",
  "properties": {
    "iso:country":"BE",
    "sg:address":"Rue Du Roy 46ba",
    "sg:city":"Gouvy",
    "sg:orig_category":"Rundveehouders",
    "sg:phone":"+32 80 51 77 42",
    "sg:postcode":"6670",
    "sg:province":"Luxembourg",
    "wof:name":"Andre Plummer",
    "wof:placetype":"venue"
},
  "geometry": {"coordinates":[5.9258089066,50.1549720764],"type":"Point"}
}