{
  "type": "Feature",
  "properties": {
    "addr:full":"Winterdijkweg 69 Bocholt Limburg 3950",
    "addr:housenumber":"69",
    "addr:postcode":"3950",
    "addr:street":"Winterdijkweg",
    "iso:country":"BE",
    "sg:address":"Winterdijkweg 69",
    "sg:city":"Bocholt",
    "sg:orig_category":"Eleveurs de bovins",
    "sg:phone":"+32 11 62 15 60",
    "sg:postcode":"3950",
    "sg:province":"Limburg",
    "wof:name":"Franciscus Gijbels",
    "wof:placetype":"venue"
},
  "geometry": {"coordinates":[5.5009021759,51.18932724],"type":"Point"}
}