{
  "type": "Feature",
  "properties": {
    "iso:country":"BE",
    "sg:address":"Parklaan 56",
    "sg:city":"Sint-niklaas",
    "sg:orig_category":"Beautyfarms, relaxatie and lichamelijk welzijn Schoonheidssalons",
    "sg:phone":"+32 3 777 71 16",
    "sg:postcode":"9100",
    "sg:province":"Oost-Vlaanderen",
    "wof:name":"Instituut Esthe",
    "wof:placetype":"venue"
},
  "geometry": {"coordinates":[4.15102911,51.1588935852],"type":"Point"}
}