{
  "type": "Feature",
  "properties": {
    "iso:country":"BE",
    "sg:address":"Sint-theresiastraat 10a",
    "sg:city":"Lommel",
    "sg:classifiers":[
        {
            "category":"Home & Garden",
            "subcategory":"Home Furnishings",
            "type":"Retail Goods"
        }
    ],
    "sg:phone":"+32 11 80 27 86",
    "sg:postcode":"3920",
    "sg:province":"Limburg",
    "sg:tags":[
        "interior",
        "decoration"
    ],
    "wof:name":"Boeren F",
    "wof:placetype":"venue"
},
  "geometry": {"coordinates":[5.3724222183,51.2277259827],"type":"Point"}
}