{
  "type": "Feature",
  "properties": {
    "addr:full":"Place De La Gare 6 Marche-en-famenne Luxembourg 6900",
    "addr:housenumber":"6",
    "addr:postcode":"6900",
    "addr:street":"Place De La Gare",
    "iso:country":"BE",
    "sg:address":"Place De La Gare 6",
    "sg:city":"Marche-en-famenne",
    "sg:orig_category":"Pain, p\u00e2tisseries and confiseries",
    "sg:phone":"+32 84 34 50 83",
    "sg:postcode":"6900",
    "sg:province":"Luxembourg",
    "wof:name":"Aux D\u00c9lices De La Gare",
    "wof:placetype":"venue"
},
  "geometry": {"coordinates":[5.3144378662,50.202457428],"type":"Point"}
}