{
  "type": "Feature",
  "properties": {
    "iso:country":"BE",
    "sg:address":"Dendermondsesteenweg 7",
    "sg:city":"Willebroek",
    "sg:classifiers":[
        {
            "category":"Health Services",
            "subcategory":"Health Practitioner",
            "type":"Services"
        }
    ],
    "sg:phone":"+32 3 866 21 40",
    "sg:postcode":"2830",
    "sg:province":"Antwerpen",
    "sg:tags":[
        "physiotherapist"
    ],
    "wof:name":"Decock Tim",
    "wof:placetype":"venue"
},
  "geometry": {"coordinates":[4.3587908745,51.0603561401],"type":"Point"}
}