{
  "type": "Feature",
  "properties": {
    "iso:country":"BE",
    "sg:address":"Astridplein 66",
    "sg:city":"Grobbendonk",
    "sg:classifiers":[
        {
            "category":"Shopping",
            "subcategory":"Shoes",
            "type":"Retail Goods"
        }
    ],
    "sg:phone":"+32 14 51 64 87",
    "sg:postcode":"2280",
    "sg:province":"Antwerpen",
    "sg:tags":[
        "slipper",
        "-"
    ],
    "wof:name":"Avanti Scarpe",
    "wof:placetype":"venue"
},
  "geometry": {"coordinates":[4.7379198074,51.1921691895],"type":"Point"}
}