{
  "type": "Feature",
  "properties": {
    "iso:country":"BE",
    "sg:address":"Grote Baan 136",
    "sg:city":"Hulshout",
    "sg:orig_category":"Banken and kredietinstellingen",
    "sg:phone":"+32 15 22 24 89",
    "sg:postcode":"2235",
    "sg:province":"Antwerpen",
    "wof:name":"Kbc",
    "wof:placetype":"venue"
},
  "geometry": {"coordinates":[4.7921051979,51.0745544434],"type":"Point"}
}