{
  "type": "Feature",
  "properties": {
    "addr:full":"Place De Chablis 17 Ferrieres Li\u00e8ge 4190",
    "addr:housenumber":"17",
    "addr:postcode":"4190",
    "addr:street":"Place De Chablis",
    "iso:country":"BE",
    "sg:address":"Place De Chablis 17",
    "sg:city":"Ferrieres",
    "sg:orig_category":"Journaux. Tabac",
    "sg:phone":"+32 86 40 06 88",
    "sg:postcode":"4190",
    "sg:province":"Li\u00e8ge",
    "wof:name":"Librairie Du Bati",
    "wof:placetype":"venue"
},
  "geometry": {"coordinates":[5.6065988541,50.4000511169],"type":"Point"}
}