{
  "type": "Feature",
  "properties": {
    "addr:full":"Rue Charles Magnette 2 Li\u00e8ge 1 Li\u00e8ge 4000",
    "addr:housenumber":"2;1",
    "addr:postcode":"4000",
    "addr:street":"Rue Charles Magnette",
    "iso:country":"BE",
    "sg:address":"Rue Charles Magnette 2",
    "sg:city":"Li\u00e8ge 1",
    "sg:classifiers":[
        {
            "category":"Shopping",
            "subcategory":"Clothing, Apparel, & Fashions",
            "type":"Retail Goods"
        }
    ],
    "sg:phone":"+32 4 223 14 50",
    "sg:postcode":"4000",
    "sg:province":"Li\u00e8ge",
    "sg:tags":[
        "clothing",
        "-",
        "gentleman"
    ],
    "wof:name":"Bo\u00eete \u00e0 Pulls (la)",
    "wof:placetype":"venue"
},
  "geometry": {"coordinates":[5.5743021965,50.6411514282],"type":"Point"}
}