{
  "type": "Feature",
  "properties": {
    "iso:country":"BE",
    "sg:address":"Rue Broodcorens 9",
    "sg:city":"Terhulpen",
    "sg:classifiers":[
        {
            "category":"Arena",
            "subcategory":"Sports Club",
            "type":"Entertainment"
        }
    ],
    "sg:phone":"+32 2 653 52 16",
    "sg:postcode":"1310",
    "sg:province":"Brabant Wallon",
    "sg:tags":[
        "de"
    ],
    "wof:name":"Mad Foxes",
    "wof:placetype":"venue"
},
  "geometry": {"coordinates":[4.4826169014,50.7294197083],"type":"Point"}
}