{
  "type": "Feature",
  "properties": {
    "addr:full":"Pr\u00c9 M\u00c9tro De Brouck\u00c8re 11-12 Brussel/bruxelles Bruxelles-Capitale 1000",
    "addr:postcode":"11-12;/ bruxelles;1000",
    "addr:street":"Pre\u0301 Me\u0301Tro De Broucke\u0300Re",
    "iso:country":"BE",
    "sg:address":"Pr\u00c9 M\u00c9tro De Brouck\u00c8re 11-12",
    "sg:city":"Brussel/bruxelles",
    "sg:orig_category":"Diverse zakelijke dienstverlening",
    "sg:phone":"+32 2 219 65 48",
    "sg:postcode":"1000",
    "sg:province":"Bruxelles-Capitale",
    "wof:name":"Magic Events",
    "wof:placetype":"venue"
},
  "geometry": {"coordinates":[4.3528680801,50.8510704041],"type":"Point"}
}