{
  "type": "Feature",
  "properties": {
    "iso:country":"BE",
    "sg:address":"Rue Ferrer 78",
    "sg:city":"Charleroi",
    "sg:orig_category":"Kapsalons",
    "sg:phone":"+32 71 35 27 95",
    "sg:postcode":"6041",
    "sg:province":"Hainaut",
    "wof:name":"Alix Lorand",
    "wof:placetype":"venue"
},
  "geometry": {"coordinates":[4.4736509323,50.38829422],"type":"Point"}
}