{
  "type": "Feature",
  "properties": {
    "iso:country":"BE",
    "sg:address":"Rue De La Station 35b",
    "sg:city":"Braine-le-ch\u00e2teau",
    "sg:orig_category":"Canteens For Cutlery",
    "sg:phone":"+32 2 366 05 90",
    "sg:postcode":"1440",
    "sg:province":"Brabant Wallon",
    "wof:name":"Gainerie Brainoise S.p.r.l.",
    "wof:placetype":"venue"
},
  "geometry": {"coordinates":[4.2720808983,50.6816101074],"type":"Point"}
}