{
  "type": "Feature",
  "properties": {
    "iso:country":"BE",
    "sg:address":"Sint-truidersteenweg 407",
    "sg:city":"Hasselt",
    "sg:classifiers":[
        {
            "category":"Home & Garden",
            "subcategory":"Kitchen Supply",
            "type":"Retail Goods"
        }
    ],
    "sg:phone":"+32 11 27 34 91",
    "sg:postcode":"3500",
    "sg:province":"Limburg",
    "sg:tags":[
        "equipment",
        "baker",
        "-"
    ],
    "wof:name":"Broeders Bakkerij Service Nv",
    "wof:placetype":"venue"
},
  "geometry": {"coordinates":[5.327709198,50.9188766479],"type":"Point"}
}