{
  "type": "Feature",
  "properties": {
    "iso:country":"BE",
    "sg:address":"Sint-laureisstraat 29 Box 1",
    "sg:city":"Antwerpen",
    "sg:classifiers":[
        {
            "category":"Building & Trades",
            "subcategory":"Construction",
            "type":"Services"
        }
    ],
    "sg:phone":"+32 3 248 01 24",
    "sg:postcode":"2018",
    "sg:province":"Antwerpen",
    "sg:tags":[
        "carpenter"
    ],
    "wof:name":"Stuer K",
    "wof:placetype":"venue"
},
  "geometry": {"coordinates":[4.3977417946,51.2041664124],"type":"Point"}
}