{
  "type": "Feature",
  "properties": {
    "addr:full":"Hendrik Van Den Eedestr. 18 Dilbeek Vlaams-Brabant 1702",
    "addr:housenumber":"18",
    "addr:postcode":"1702",
    "addr:street":"Hendrik Van Den Eedestr.",
    "iso:country":"BE",
    "sg:address":"Hendrik Van Den Eedestr. 18",
    "sg:city":"Dilbeek",
    "sg:orig_category":"Producteurs de l\u00e9gumes",
    "sg:phone":"+32 2 466 03 42",
    "sg:postcode":"1702",
    "sg:province":"Vlaams-Brabant",
    "wof:name":"Albert Vanden Eede",
    "wof:placetype":"venue"
},
  "geometry": {"coordinates":[4.2684202194,50.8771896362],"type":"Point"}
}