{
  "type": "Feature",
  "properties": {
    "iso:country":"BE",
    "sg:address":"Rn 5",
    "sg:city":"Gosselies",
    "sg:classifiers":[
        {
            "category":"Manufacturing",
            "subcategory":"Building Materials",
            "type":"Manufacturing & Wholesale Goods"
        }
    ],
    "sg:phone":"+32 71 25 65 10",
    "sg:postcode":"6041",
    "sg:province":"Hainaut",
    "sg:tags":[
        "glass",
        "ceramic"
    ],
    "wof:name":"Inter-carrelages S.a.",
    "wof:placetype":"venue"
},
  "geometry": {"coordinates":[4.4314317703,50.4685935974],"type":"Point"}
}