{
  "type": "Feature",
  "properties": {
    "addr:full":"Jasmijnstraat 23 Gent Oost-Vlaanderen 9000",
    "addr:housenumber":"23",
    "addr:postcode":"9000",
    "addr:street":"Jasmijnstraat;Oost-Vlaanderen",
    "iso:country":"BE",
    "sg:address":"Jasmijnstraat 23",
    "sg:city":"Gent",
    "sg:classifiers":[
        {
            "category":"Personal",
            "subcategory":"Beauty Salon",
            "type":"Services"
        }
    ],
    "sg:phone":"+32 9 226 90 91",
    "sg:postcode":"9000",
    "sg:province":"Oost-Vlaanderen",
    "sg:tags":[
        "de",
        "coiffure"
    ],
    "wof:name":"Cindy Van Eesvelde",
    "wof:placetype":"venue"
},
  "geometry": {"coordinates":[3.7068850994,51.072353363],"type":"Point"}
}