{
  "type": "Feature",
  "properties": {
    "iso:country":"BE",
    "sg:address":"Koebrugstraat 58",
    "sg:city":"Aalst (moorsel)",
    "sg:classifiers":[
        {
            "category":"Social Services",
            "subcategory":"Job Training",
            "type":"Services"
        }
    ],
    "sg:phone":"+32 53 70 30 20",
    "sg:postcode":"9310",
    "sg:province":"Oost-Vlaanderen",
    "sg:tags":[
        "coordinator",
        "safety"
    ],
    "wof:name":"Rubbrecht E",
    "wof:placetype":"venue"
},
  "geometry": {"coordinates":[4.0905709267,50.9433784485],"type":"Point"}
}