{
  "type": "Feature",
  "properties": {
    "iso:country":"BE",
    "sg:address":"Iepstraat 18",
    "sg:city":"Houthalen-helchteren",
    "sg:orig_category":"Installation \u00e9lectrique r\u00e9sidentielle",
    "sg:phone":"+32 89 38 28 00",
    "sg:postcode":"3530",
    "sg:province":"Limburg",
    "wof:name":"Willems Techno-trade",
    "wof:placetype":"venue"
},
  "geometry": {"coordinates":[5.477602005,51.0224838257],"type":"Point"}
}