{
  "type": "Feature",
  "properties": {
    "iso:country":"BE",
    "sg:address":"Avenue Neptune 38",
    "sg:city":"Waterloo",
    "sg:classifiers":[
        {
            "category":"Insurance",
            "subcategory":"Life Insurance",
            "type":"Services"
        }
    ],
    "sg:phone":"+32 2 354 47 76",
    "sg:postcode":"1410",
    "sg:province":"Brabant Wallon",
    "sg:tags":[
        "assurance"
    ],
    "wof:name":"B.r.s.",
    "wof:placetype":"venue"
},
  "geometry": {"coordinates":[4.4226369858,50.7069244385],"type":"Point"}
}