{
  "type": "Feature",
  "properties": {
    "iso:country":"BE",
    "sg:address":"Rue Grande 22",
    "sg:city":"Bi\u00e8vre (oizy)",
    "sg:classifiers":[
        {
            "category":"Wholesale",
            "subcategory":"Wine & Distilled Alcoholic Beverages",
            "type":"Manufacturing & Wholesale Goods"
        }
    ],
    "sg:phone":"+32 61 50 01 24",
    "sg:postcode":"5555",
    "sg:province":"Namur",
    "sg:tags":[
        "whol",
        "-",
        "spirit",
        "mfg"
    ],
    "wof:name":"Brume De Semois",
    "wof:placetype":"venue"
},
  "geometry": {"coordinates":[5.00710392,49.8925857544],"type":"Point"}
}