{
  "type": "Feature",
  "properties": {
    "addr:full":"Grote Markt 46 Sint-truiden Limburg 3800",
    "addr:housenumber":"46",
    "addr:postcode":"3800",
    "addr:street":"Grote Markt",
    "iso:country":"BE",
    "sg:address":"Grote Markt 46",
    "sg:city":"Sint-truiden",
    "sg:orig_category":"Banken and kredietinstellingen",
    "sg:phone":"+32 11 68 18 02",
    "sg:postcode":"3800",
    "sg:province":"Limburg",
    "wof:name":"Bank J. Van Breda & Co",
    "wof:placetype":"venue"
},
  "geometry": {"coordinates":[5.1854639053,50.8155326843],"type":"Point"}
}