{
  "type": "Feature",
  "properties": {
    "addr:full":"Aarselestraat 20 Tielt West-Vlaanderen 8700",
    "addr:housenumber":"20",
    "addr:postcode":"8700",
    "addr:street":"Aarselestraat",
    "iso:country":"BE",
    "sg:address":"Aarselestraat 20",
    "sg:city":"Tielt",
    "sg:orig_category":"Peinture",
    "sg:phone":"+32 51 63 34 63",
    "sg:postcode":"8700",
    "sg:province":"West-Vlaanderen",
    "wof:name":"Hoste S",
    "wof:placetype":"venue"
},
  "geometry": {"coordinates":[3.4215340614,50.9943389893],"type":"Point"}
}