{
  "type": "Feature",
  "properties": {
    "addr:full":"Rue Wallay 195 Ohey Namur 5350",
    "addr:housenumber":"195",
    "addr:postcode":"5350",
    "addr:street":"Rue Wallay",
    "iso:country":"BE",
    "sg:address":"Rue Wallay 195",
    "sg:city":"Ohey",
    "sg:classifiers":[
        {
            "category":"Cafe",
            "type":"Food & Drink"
        }
    ],
    "sg:phone":"+32 85 61 24 39",
    "sg:postcode":"5350",
    "sg:province":"Namur",
    "sg:tags":[
        "caf\u00e9s"
    ],
    "wof:name":"Claude Bubbe",
    "wof:placetype":"venue"
},
  "geometry": {"coordinates":[5.11251688,50.4300498962],"type":"Point"}
}