{
  "type": "Feature",
  "properties": {
    "addr:full":"Eikboslaan 67 Herzele Oost-Vlaanderen 9550",
    "addr:housenumber":"67",
    "addr:postcode":"9550",
    "addr:street":"Eikboslaan;Oost-Vlaanderen",
    "iso:country":"BE",
    "sg:address":"Eikboslaan 67",
    "sg:city":"Herzele",
    "sg:classifiers":[
        {
            "category":"Health Services",
            "subcategory":"Health Practitioner",
            "type":"Services"
        }
    ],
    "sg:phone":"+32 53 62 61 86",
    "sg:postcode":"9550",
    "sg:province":"Oost-Vlaanderen",
    "sg:tags":[
        "physiotherapist"
    ],
    "wof:name":"Van Der Bracht Christine",
    "wof:placetype":"venue"
},
  "geometry": {"coordinates":[3.8941628933,50.8885040283],"type":"Point"}
}