{
  "type": "Feature",
  "properties": {
    "iso:country":"BE",
    "sg:address":"Boulevard Emile Bockstael 325",
    "sg:city":"Bruxelles",
    "sg:classifiers":[
        {
            "category":"Insurance",
            "subcategory":"Insurance Agent",
            "type":"Services"
        }
    ],
    "sg:phone":"+32 2 478 65 36",
    "sg:postcode":"1020",
    "sg:province":"Bruxelles-Capitale",
    "sg:tags":[
        "broker"
    ],
    "wof:name":"Rasp\u00e9-gestassur",
    "wof:placetype":"venue"
},
  "geometry": {"coordinates":[4.3465781212,50.8825912476],"type":"Point"}
}