{
  "type": "Feature",
  "properties": {
    "addr:full":"Leopoldstraat 58 Merksplas Antwerpen 2330",
    "addr:housenumber":"58",
    "addr:postcode":"2330",
    "addr:street":"Leopoldstraat",
    "iso:country":"BE",
    "sg:address":"Leopoldstraat 58",
    "sg:city":"Merksplas",
    "sg:orig_category":"D\u00e9molition d\u00b4immeubles and terrassements. Combustibles",
    "sg:phone":"+32 14 63 31 28",
    "sg:postcode":"2330",
    "sg:province":"Antwerpen",
    "wof:name":"Dielis",
    "wof:placetype":"venue"
},
  "geometry": {"coordinates":[4.8644728661,51.3548851013],"type":"Point"}
}