{
  "type": "Feature",
  "properties": {
    "addr:full":"Rue Du Commerce 90 Ciney Namur 5590",
    "addr:housenumber":"90",
    "addr:postcode":"5590",
    "addr:street":"Rue Du Commerce",
    "iso:country":"BE",
    "sg:address":"Rue Du Commerce 90",
    "sg:city":"Ciney",
    "sg:classifiers":[
        {
            "category":"Retail",
            "subcategory":"Laundry & Dry Cleaning",
            "type":"Services"
        }
    ],
    "sg:phone":"+32 82 66 78 22",
    "sg:postcode":"5590",
    "sg:province":"Namur",
    "sg:tags":[
        "self",
        "-"
    ],
    "wof:name":"Lavobor",
    "wof:placetype":"venue"
},
  "geometry": {"coordinates":[5.0962119102,50.2925224304],"type":"Point"}
}