{
  "type": "Feature",
  "properties": {
    "addr:full":"Grand'rue 11 Libramont-chevigny (libramont) Luxembourg 6800",
    "addr:housenumber":"11",
    "addr:postcode":"6800",
    "addr:street":"Grand'Rue",
    "iso:country":"BE",
    "sg:address":"Grand'rue 11",
    "sg:city":"Libramont-chevigny (libramont)",
    "sg:classifiers":[
        {
            "category":"Health Services",
            "subcategory":"Health Practitioner",
            "type":"Services"
        }
    ],
    "sg:phone":"+32 61 22 30 52",
    "sg:postcode":"6800",
    "sg:province":"Luxembourg",
    "sg:tags":[
        "physiotherapist"
    ],
    "wof:name":"Galerin Isabelle",
    "wof:placetype":"venue"
},
  "geometry": {"coordinates":[5.3766279221,49.9193382263],"type":"Point"}
}