{
  "type": "Feature",
  "properties": {
    "addr:full":"Panoramalaan 3 Riemst Limburg 3770",
    "addr:housenumber":"3",
    "addr:postcode":"3770",
    "addr:street":"Panoramalaan",
    "iso:country":"BE",
    "sg:address":"Panoramalaan 3",
    "sg:city":"Riemst",
    "sg:classifiers":[
        {
            "category":"Home & Garden",
            "subcategory":"Carpets & Floor Coverings",
            "type":"Retail Goods"
        }
    ],
    "sg:phone":"+32 12 44 12 85",
    "sg:postcode":"3770",
    "sg:province":"Limburg",
    "sg:tags":[
        "layer",
        "mosaicists"
    ],
    "wof:name":"Willems H",
    "wof:placetype":"venue"
},
  "geometry": {"coordinates":[5.6047067642,50.8084182739],"type":"Point"}
}