{
  "type": "Feature",
  "properties": {
    "iso:country":"BE",
    "sg:address":"Houwstraat 82",
    "sg:city":"Putte",
    "sg:orig_category":"Cosmetica and toiletartikelen Schoonheidssalons",
    "sg:phone":"+32 15 24 43 88",
    "sg:postcode":"2580",
    "sg:province":"Antwerpen",
    "wof:name":"Magda Van Gijsel",
    "wof:placetype":"venue"
},
  "geometry": {"coordinates":[4.6626029015,51.07264328],"type":"Point"}
}