{
  "type": "Feature",
  "properties": {
    "addr:full":"Stationsstraat 17 Nazareth Oost-Vlaanderen 9810",
    "addr:housenumber":"17",
    "addr:postcode":"9810",
    "addr:street":"Stationsstraat",
    "iso:country":"BE",
    "sg:address":"Stationsstraat 17",
    "sg:city":"Nazareth",
    "sg:orig_category":"Electrom\u00e9nager, t\u00e9l\u00e9visions and radios",
    "sg:phone":"+32 9 385 83 97",
    "sg:postcode":"9810",
    "sg:province":"Oost-Vlaanderen",
    "wof:name":"Hans De Clercq",
    "wof:placetype":"venue"
},
  "geometry": {"coordinates":[3.6403589249,50.9572944641],"type":"Point"}
}