{
  "type": "Feature",
  "properties": {
    "addr:full":"Herpelsstraat 85 Harelbeke West-Vlaanderen 8530",
    "addr:housenumber":"85",
    "addr:postcode":"8530",
    "addr:street":"Herpelsstraat",
    "iso:country":"BE",
    "sg:address":"Herpelsstraat 85",
    "sg:city":"Harelbeke",
    "sg:orig_category":"Woningbouw",
    "sg:phone":"+32 56 72 85 12",
    "sg:postcode":"8530",
    "sg:province":"West-Vlaanderen",
    "wof:name":"Bouwwerken Opbrouck Gerry",
    "wof:placetype":"venue"
},
  "geometry": {"coordinates":[3.3285989761,50.8547973633],"type":"Point"}
}