{
  "type": "Feature",
  "properties": {
    "iso:country":"BE",
    "sg:address":"Haven 200 Nieuwelandenweg 4",
    "sg:city":"Antwerpen",
    "sg:classifiers":[
        {
            "category":"Airport",
            "type":"Transportation"
        }
    ],
    "sg:phone":"+32 3 541 92 11",
    "sg:postcode":"2030",
    "sg:province":"Antwerpen",
    "sg:tags":[
        "air-freight",
        "forwarders"
    ],
    "wof:name":"Leschaco Nv",
    "wof:placetype":"venue"
},
  "geometry": {"coordinates":[4.3990387917,51.2743148804],"type":"Point"}
}