{
  "type": "Feature",
  "properties": {
    "iso:country":"BE",
    "sg:address":"Pepersstraat 2",
    "sg:city":"Knokke-heist (knokke)",
    "sg:classifiers":[
        {
            "category":"Professional",
            "subcategory":"Computer Services",
            "type":"Services"
        }
    ],
    "sg:phone":"+32 50 60 85 08",
    "sg:postcode":"8300",
    "sg:province":"West-Vlaanderen",
    "sg:tags":[
        "-",
        "processing",
        "data",
        "software"
    ],
    "wof:name":"Program",
    "wof:placetype":"venue"
},
  "geometry": {"coordinates":[3.2886629105,51.3413314819],"type":"Point"}
}