{
  "type": "Feature",
  "properties": {
    "addr:full":"Hutterprivatweg 22 Eupen/eupen Li\u00e8ge 4700",
    "addr:housenumber":"22",
    "addr:postcode":"4700",
    "addr:street":"Hutterprivatweg",
    "iso:country":"BE",
    "sg:address":"Hutterprivatweg 22",
    "sg:city":"Eupen/eupen",
    "sg:orig_category":"Electrom\u00e9nager, t\u00e9l\u00e9visions and radios",
    "sg:phone":"+32 87 74 29 43",
    "sg:postcode":"4700",
    "sg:province":"Li\u00e8ge",
    "wof:name":"Paul Gensterblum",
    "wof:placetype":"venue"
},
  "geometry": {"coordinates":[6.0458731651,50.6168174744],"type":"Point"}
}