{
  "type": "Feature",
  "properties": {
    "iso:country":"BE",
    "sg:address":"Vaartkant Rechts 1",
    "sg:city":"Brecht",
    "sg:orig_category":"Houtbewerking and -behandeling",
    "sg:phone":"+32 3 313 64 65",
    "sg:postcode":"2960",
    "sg:province":"Antwerpen",
    "wof:name":"Acpa",
    "wof:placetype":"venue"
},
  "geometry": {"coordinates":[4.6325597763,51.3524742126],"type":"Point"}
}