{
  "type": "Feature",
  "properties": {
    "iso:country":"BE",
    "sg:address":"Rue De Huy 79",
    "sg:city":"Trois-ponts - Fosse (basse-bodeux)",
    "sg:classifiers":[
        {
            "category":"Farming",
            "subcategory":"Livestock Farm",
            "type":"Manufacturing & Wholesale Goods"
        }
    ],
    "sg:phone":"+32 80 68 47 87",
    "sg:postcode":"4983",
    "sg:province":"Li\u00e8ge",
    "sg:tags":[
        "buyer"
    ],
    "wof:name":"Mathieu P",
    "wof:placetype":"venue"
},
  "geometry": {"coordinates":[5.8048601151,50.3586807251],"type":"Point"}
}