{
  "type": "Feature",
  "properties": {
    "iso:country":"BE",
    "sg:address":"Budastraat 5",
    "sg:city":"Kortrijk",
    "sg:classifiers":[
        {
            "category":"Shopping",
            "subcategory":"Clothing, Apparel, & Fashions",
            "type":"Retail Goods"
        }
    ],
    "sg:phone":"+32 56 21 71 50",
    "sg:postcode":"8500",
    "sg:province":"West-Vlaanderen",
    "sg:tags":[
        "ondergoed",
        "lingerie"
    ],
    "wof:name":"Huis Edelweiss",
    "wof:placetype":"venue"
},
  "geometry": {"coordinates":[3.2638759613,50.829990387],"type":"Point"}
}