{
  "type": "Feature",
  "properties": {
    "addr:full":"Avenue Am\u00c9lie 5 Rixensart Brabant Wallon 1330",
    "addr:housenumber":"5",
    "addr:postcode":"1330",
    "addr:street":"Avenue Ame\u0301Lie;Wallon",
    "iso:country":"BE",
    "sg:address":"Avenue Am\u00c9lie 5",
    "sg:city":"Rixensart",
    "sg:orig_category":"M\u00e9decins and sp\u00e9cialistes",
    "sg:phone":"+32 2 654 02 77",
    "sg:postcode":"1330",
    "sg:province":"Brabant Wallon",
    "wof:name":"Bernadette Delcourt",
    "wof:placetype":"venue"
},
  "geometry": {"coordinates":[4.5244760513,50.7066497803],"type":"Point"}
}