{
  "type": "Feature",
  "properties": {
    "iso:country":"BE",
    "sg:address":"Lillerbaan 145",
    "sg:city":"Bocholt",
    "sg:orig_category":"Rundveehouders Varkenskwekers",
    "sg:phone":"+32 11 44 11 54",
    "sg:postcode":"3950",
    "sg:province":"Limburg",
    "wof:name":"Ludo Simons",
    "wof:placetype":"venue"
},
  "geometry": {"coordinates":[5.499352932,51.2054138184],"type":"Point"}
}