{
  "type": "Feature",
  "properties": {
    "addr:full":"Avenue De Haveskercke 22 Bruxelles (forest) Bruxelles-Capitale 1190",
    "addr:housenumber":"22",
    "addr:postcode":"1190",
    "addr:street":"Avenue De Haveskercke",
    "iso:country":"BE",
    "sg:address":"Avenue De Haveskercke 22",
    "sg:city":"Bruxelles (forest)",
    "sg:classifiers":[
        {
            "category":"Real Estate",
            "subcategory":"Architect",
            "type":"Services"
        }
    ],
    "sg:phone":"+32 2 376 94 32",
    "sg:postcode":"1190",
    "sg:province":"Bruxelles-Capitale",
    "wof:name":"Dejemeppe D",
    "wof:placetype":"venue"
},
  "geometry": {"coordinates":[4.3236370087,50.8053474426],"type":"Point"}
}