{
  "type": "Feature",
  "properties": {
    "addr:full":"Rue Emile Mazy 6 Namur (flawinne) Namur 5020",
    "addr:housenumber":"6",
    "addr:postcode":"5020",
    "addr:street":"Rue Emile Mazy",
    "iso:country":"BE",
    "sg:address":"Rue Emile Mazy 6",
    "sg:city":"Namur (flawinne)",
    "sg:classifiers":[
        {
            "category":"Professional",
            "subcategory":"Computer Services",
            "type":"Services"
        }
    ],
    "sg:phone":"+32 81 74 10 45",
    "sg:postcode":"5020",
    "sg:province":"Namur",
    "sg:tags":[
        "-",
        "processing",
        "data",
        "software"
    ],
    "wof:name":"Despontin S",
    "wof:placetype":"venue"
},
  "geometry": {"coordinates":[4.7952418327,50.4352035522],"type":"Point"}
}