{
  "type": "Feature",
  "properties": {
    "iso:country":"BE",
    "sg:address":"Theophiel De Biestraat 18 Box 1",
    "sg:city":"Heist-op-den-berg",
    "sg:classifiers":[
        {
            "category":"Shopping",
            "subcategory":"Computers & Home Electronics",
            "type":"Retail Goods"
        }
    ],
    "sg:phone":"+32 15 24 57 41",
    "sg:postcode":"2220",
    "sg:province":"Antwerpen",
    "sg:tags":[
        "personal",
        "-",
        "processing",
        "data"
    ],
    "wof:name":"Shipcom",
    "wof:placetype":"venue"
},
  "geometry": {"coordinates":[4.7236552238,51.0772247314],"type":"Point"}
}