{
  "type": "Feature",
  "properties": {
    "addr:full":"Ledegemsestraat 85 Wevelgem (moorsele) West-Vlaanderen 8560",
    "addr:housenumber":"85",
    "addr:postcode":"8560",
    "addr:street":"Ledegemsestraat",
    "iso:country":"BE",
    "sg:address":"Ledegemsestraat 85",
    "sg:city":"Wevelgem (moorsele)",
    "sg:classifiers":[
        {
            "category":"Retail",
            "subcategory":"Auto Repair",
            "type":"Services"
        }
    ],
    "sg:phone":"+32 56 50 06 80",
    "sg:postcode":"8560",
    "sg:province":"West-Vlaanderen",
    "sg:tags":[
        "automobile-body"
    ],
    "wof:name":"Verstraete G",
    "wof:placetype":"venue"
},
  "geometry": {"coordinates":[3.1546239853,50.8437576294],"type":"Point"}
}