{
  "type": "Feature",
  "properties": {
    "addr:full":"Buksboomstraat 47 Watermaal-bosvoorde/watermael-boitsfort Bruxelles-Capitale 1170",
    "addr:housenumber":"47",
    "addr:postcode":"1170",
    "addr:street":"Buksboomstraat",
    "iso:country":"BE",
    "sg:address":"Buksboomstraat 47",
    "sg:city":"Watermaal-bosvoorde/watermael-boitsfort",
    "sg:orig_category":"Begrafeniswezen",
    "sg:phone":"+32 2 675 56 96",
    "sg:postcode":"1170",
    "sg:province":"Bruxelles-Capitale",
    "wof:name":"Fun\u00c9railles Le Paisible",
    "wof:placetype":"venue"
},
  "geometry": {"coordinates":[4.4230618477,50.7948455811],"type":"Point"}
}