{
  "type": "Feature",
  "properties": {
    "addr:full":"Rue Neuve-chauss\u00c9e 139bb Peruwelz Hainaut 7600",
    "addr:housenumber":"139bb",
    "addr:postcode":"7600",
    "addr:street":"Rue Neuve-Chausse\u0301E;Hainaut",
    "iso:country":"BE",
    "sg:address":"Rue Neuve-chauss\u00c9e 139bb",
    "sg:city":"Peruwelz",
    "sg:orig_category":"Supermarkten",
    "sg:phone":"+32 69 77 39 76",
    "sg:postcode":"7600",
    "sg:province":"Hainaut",
    "wof:name":"Battard",
    "wof:placetype":"venue"
},
  "geometry": {"coordinates":[3.6009941101,50.5252227783],"type":"Point"}
}