{
  "type": "Feature",
  "properties": {
    "iso:country":"BE",
    "sg:address":"Bortierlaan 13",
    "sg:city":"De Panne",
    "sg:orig_category":"Hotels Restaurants Sportterreinen and installaties behalve sportcentra",
    "sg:phone":"+32 58 41 12 22",
    "sg:postcode":"8660",
    "sg:province":"West-Vlaanderen",
    "wof:name":"Hotel Regina Maris",
    "wof:placetype":"venue"
},
  "geometry": {"coordinates":[2.5906550884,51.1009368896],"type":"Point"}
}