{
  "type": "Feature",
  "properties": {
    "iso:country":"BE",
    "sg:address":"Kempenlaan 66",
    "sg:city":"Wommelgem",
    "sg:orig_category":"Non-Classified Establishments",
    "sg:phone":"+32 3 354 08 44",
    "sg:postcode":"2160",
    "sg:province":"Antwerpen",
    "wof:name":"Antonis",
    "wof:placetype":"venue"
},
  "geometry": {"coordinates":[4.5376877785,51.1950759888],"type":"Point"}
}