{
  "type": "Feature",
  "properties": {
    "addr:full":"Mechelbaan 695b1 Putte Antwerpen 2580",
    "addr:housenumber":"695b1",
    "addr:postcode":"2580",
    "addr:street":"Mechelbaan",
    "iso:country":"BE",
    "sg:address":"Mechelbaan 695b1",
    "sg:city":"Putte",
    "sg:orig_category":"Groententeelt",
    "sg:phone":"+32 15 75 65 65",
    "sg:postcode":"2580",
    "sg:province":"Antwerpen",
    "wof:name":"Alfons Van Craen",
    "wof:placetype":"venue"
},
  "geometry": {"coordinates":[4.5973148346,51.0407218933],"type":"Point"}
}