{
  "type": "Feature",
  "properties": {
    "iso:country":"BE",
    "sg:address":"Rue D'ensival 18",
    "sg:city":"Verviers",
    "sg:classifiers":[
        {
            "category":"Bars & Pubs",
            "type":"Food & Drink"
        }
    ],
    "sg:phone":"+32 87 35 14 54",
    "sg:postcode":"4800",
    "sg:province":"Li\u00e8ge",
    "wof:name":"Amis De L\u00e9on (les)",
    "wof:placetype":"venue"
},
  "geometry": {"coordinates":[5.8547258377,50.5886726379],"type":"Point"}
}