{
  "type": "Feature",
  "properties": {
    "iso:country":"BE",
    "sg:address":"Rue De La Xhorr\u00c9e 36",
    "sg:city":"Herstal",
    "sg:orig_category":"Entretien and r\u00e9parations de voitures",
    "sg:phone":"+32 4 264 71 42",
    "sg:postcode":"4040",
    "sg:province":"Li\u00e8ge",
    "wof:name":"Michel Protin",
    "wof:placetype":"venue"
},
  "geometry": {"coordinates":[5.6285009384,50.6768951416],"type":"Point"}
}