{
  "type": "Feature",
  "properties": {
    "addr:full":"Ter Moude 25 Zwevegem 8552",
    "addr:housenumber":"25",
    "addr:postcode":"8552",
    "addr:street":"Zwevegem",
    "iso:country":"BE",
    "sg:address":"Ter Moude 25",
    "sg:city":"Zwevegem",
    "sg:orig_category":"M\u00e9decins and sp\u00e9cialistes",
    "sg:phone":"+32 56 64 43 45",
    "sg:postcode":"8552",
    "wof:name":"Gommaar Crepel",
    "wof:placetype":"venue"
},
  "geometry": {"coordinates":[3.3965609074,50.7679672241],"type":"Point"}
}