{
  "type": "Feature",
  "properties": {
    "addr:full":"Rue Croix F\u00e9au 18 Saint-hubert Luxembourg 6870",
    "addr:housenumber":"18",
    "addr:postcode":"6870",
    "addr:street":"Rue Croix Fe\u0301Au",
    "iso:country":"BE",
    "sg:address":"Rue Croix F\u00e9au 18",
    "sg:city":"Saint-hubert",
    "sg:classifiers":[
        {
            "category":"Health Services",
            "subcategory":"Health Practitioner",
            "type":"Services"
        }
    ],
    "sg:phone":"+32 61 61 10 81",
    "sg:postcode":"6870",
    "sg:province":"Luxembourg",
    "sg:tags":[
        "physiotherapist"
    ],
    "wof:name":"Renouprez Mich\u00e8le",
    "wof:placetype":"venue"
},
  "geometry": {"coordinates":[5.3786439896,50.019203186],"type":"Point"}
}