{
  "type": "Feature",
  "properties": {
    "addr:full":"Zandstappenstraat 20 Schoten Antwerpen 2900",
    "addr:housenumber":"20",
    "addr:postcode":"2900",
    "addr:street":"Zandstappenstraat",
    "iso:country":"BE",
    "sg:address":"Zandstappenstraat 20",
    "sg:city":"Schoten",
    "sg:orig_category":"Activit\u00e9s diverses d'imprimerie",
    "sg:phone":"+32 3 685 20 38",
    "sg:postcode":"2900",
    "sg:province":"Antwerpen",
    "wof:name":"Bureau Phooey!",
    "wof:placetype":"venue"
},
  "geometry": {"coordinates":[4.5046582222,51.255355835],"type":"Point"}
}