{
  "type": "Feature",
  "properties": {
    "addr:full":"Rue Du Marais 16 Silly Hainaut 7830",
    "addr:housenumber":"16",
    "addr:postcode":"7830",
    "addr:street":"Rue Du Marais",
    "iso:country":"BE",
    "sg:address":"Rue Du Marais 16",
    "sg:city":"Silly",
    "sg:orig_category":"Enseignement maternel and primaire",
    "sg:phone":"+32 68 55 17 55",
    "sg:postcode":"7830",
    "sg:province":"Hainaut",
    "wof:name":"Ecole Fondamentale Libre",
    "wof:placetype":"venue"
},
  "geometry": {"coordinates":[3.9253180027,50.6467132568],"type":"Point"}
}