{
  "type": "Feature",
  "properties": {
    "addr:full":"Place De La Vaillance 25 Anderlecht Bruxelles-Capitale 1070",
    "addr:housenumber":"25",
    "addr:postcode":"1070",
    "addr:street":"Place De La Vaillance",
    "iso:country":"BE",
    "sg:address":"Place De La Vaillance 25",
    "sg:city":"Anderlecht",
    "sg:orig_category":"Vedior. Agences d\u00b4interim and personnel temporaire",
    "sg:phone":"+32 2 522 62 37",
    "sg:postcode":"1070",
    "sg:province":"Bruxelles-Capitale",
    "wof:name":"Vedior Interim",
    "wof:placetype":"venue"
},
  "geometry": {"coordinates":[4.3058791161,50.8358306885],"type":"Point"}
}