{
  "type": "Feature",
  "properties": {
    "addr:full":"Stationsplein 6 Geraardsbergen Oost-Vlaanderen 9500",
    "addr:housenumber":"6",
    "addr:postcode":"9500",
    "addr:street":"Stationsplein",
    "iso:country":"BE",
    "sg:address":"Stationsplein 6",
    "sg:city":"Geraardsbergen",
    "sg:orig_category":"Elektrische installaties voor woningen Huishoudapparaten, televisies and radio's",
    "sg:phone":"+32 54 41 22 90",
    "sg:postcode":"9500",
    "sg:province":"Oost-Vlaanderen",
    "wof:name":"De Lil",
    "wof:placetype":"venue"
},
  "geometry": {"coordinates":[3.8743979931,50.7699813843],"type":"Point"}
}