{
  "type": "Feature",
  "properties": {
    "addr:full":"Rue Des Bouleaux 39 Seraing Li\u00e8ge 4100",
    "addr:housenumber":"39",
    "addr:postcode":"4100",
    "addr:street":"Rue Des Bouleaux",
    "iso:country":"BE",
    "sg:address":"Rue Des Bouleaux 39",
    "sg:city":"Seraing",
    "sg:orig_category":"Enseignement maternel and primaire",
    "sg:phone":"+32 4 336 15 31",
    "sg:postcode":"4100",
    "sg:province":"Li\u00e8ge",
    "wof:name":"Ecole Fond. Communale",
    "wof:placetype":"venue"
},
  "geometry": {"coordinates":[5.5263948441,50.5579185486],"type":"Point"}
}