{
  "type": "Feature",
  "properties": {
    "addr:full":"Oostendestraat 17 Nieuwpoort West-Vlaanderen 8620",
    "addr:housenumber":"17",
    "addr:postcode":"8620",
    "addr:street":"Oostendestraat",
    "iso:country":"BE",
    "sg:address":"Oostendestraat 17",
    "sg:city":"Nieuwpoort",
    "sg:classifiers":[
        {
            "category":"Personal",
            "subcategory":"Beauty Salon",
            "type":"Services"
        }
    ],
    "sg:phone":"+32 58 23 34 97",
    "sg:postcode":"8620",
    "sg:province":"West-Vlaanderen",
    "sg:tags":[
        "de",
        "coiffure"
    ],
    "wof:name":"Het Huis Van De Kapper",
    "wof:placetype":"venue"
},
  "geometry": {"coordinates":[2.7519168854,51.1323509216],"type":"Point"}
}