{
  "type": "Feature",
  "properties": {
    "iso:country":"BE",
    "sg:address":"Bosvoordse Steenweg 28",
    "sg:city":"Elsene/ixelles",
    "sg:orig_category":"Zalen voor culturele evenementen",
    "sg:phone":"+32 2 662 27 18",
    "sg:postcode":"1050",
    "sg:province":"Bruxelles-Capitale",
    "wof:name":"Compagnie Les M\u00c9t\u00c9ores",
    "wof:placetype":"venue"
},
  "geometry": {"coordinates":[4.3931818008,50.8072929382],"type":"Point"}
}