{
  "type": "Feature",
  "properties": {
    "iso:country":"BE",
    "sg:address":"9de Liniestraat 28",
    "sg:city":"Izegem (groot)",
    "sg:orig_category":"Metaalbehandeling and -bekleding",
    "sg:phone":"+32 51 30 11 21",
    "sg:postcode":"8870",
    "sg:province":"West-Vlaanderen",
    "wof:name":"Reynaert",
    "wof:placetype":"venue"
},
  "geometry": {"coordinates":[3.1882200241,50.9331130981],"type":"Point"}
}