{
  "type": "Feature",
  "properties": {
    "addr:full":"Rue Des Hautes Hur\u00e9es 26 Nivelles Brabant Wallon 1400",
    "addr:housenumber":"26",
    "addr:postcode":"1400",
    "addr:street":"Rue Des Hautes Hure\u0301Es",
    "iso:country":"BE",
    "sg:address":"Rue Des Hautes Hur\u00e9es 26",
    "sg:city":"Nivelles",
    "sg:classifiers":[
        {
            "category":"Freight",
            "type":"Transportation"
        }
    ],
    "sg:phone":"+32 67 21 91 13",
    "sg:postcode":"1400",
    "sg:province":"Brabant Wallon",
    "sg:tags":[
        "-",
        "transport"
    ],
    "wof:name":"Jonckers F",
    "wof:placetype":"venue"
},
  "geometry": {"coordinates":[4.3105711937,50.5975761414],"type":"Point"}
}