{
  "type": "Feature",
  "properties": {
    "iso:country":"BE",
    "sg:address":"Rue E. Muraille",
    "sg:city":"Herstal",
    "sg:orig_category":"Sportclubs Sportterreinen and installaties behalve sportcentra",
    "sg:phone":"+32 4 240 34 89",
    "sg:postcode":"4040",
    "sg:province":"Li\u00e8ge",
    "wof:name":"Herstal Tennis Club",
    "wof:placetype":"venue"
},
  "geometry": {"coordinates":[5.6228399277,50.6791534424],"type":"Point"}
}