{
  "type": "Feature",
  "properties": {
    "iso:country":"BE",
    "sg:address":"Rue Du Wainage 196",
    "sg:city":"Fleurus",
    "sg:orig_category":"Apotheken",
    "sg:phone":"+32 71 81 19 04",
    "sg:postcode":"6220",
    "sg:province":"Hainaut",
    "wof:name":"G. Pichon",
    "wof:placetype":"venue"
},
  "geometry": {"coordinates":[4.56108284,50.457862854],"type":"Point"}
}