{
  "type": "Feature",
  "properties": {
    "addr:full":"Rue Castor 1 Braine L'alleud (ophain-bois-seigneur-isaac) Brabant Wallon 1421",
    "addr:housenumber":"1",
    "addr:postcode":"1421",
    "addr:street":"Rue Castor",
    "iso:country":"BE",
    "sg:address":"Rue Castor 1",
    "sg:city":"Braine L'alleud (ophain-bois-seigneur-isaac)",
    "sg:classifiers":[
        {
            "category":"Wholesale",
            "subcategory":"Vending Machines",
            "type":"Manufacturing & Wholesale Goods"
        }
    ],
    "sg:phone":"+32 2 384 54 93",
    "sg:postcode":"1421",
    "sg:province":"Brabant Wallon",
    "sg:tags":[
        "sieving",
        "installation"
    ],
    "wof:name":"Cuvelier Philippe Sprl",
    "wof:placetype":"venue"
},
  "geometry": {"coordinates":[-75.60595703120001,37.7877616882],"type":"Point"}
}