{
  "type": "Feature",
  "properties": {
    "addr:full":"Leeuwstraat 70 Gent Oost-Vlaanderen 9000",
    "addr:housenumber":"70",
    "addr:postcode":"9000",
    "addr:street":"Leeuwstraat;Oost-Vlaanderen",
    "iso:country":"BE",
    "sg:address":"Leeuwstraat 70",
    "sg:city":"Gent",
    "sg:classifiers":[
        {
            "category":"Real Estate",
            "subcategory":"Architect",
            "type":"Services"
        }
    ],
    "sg:phone":"+32 9 234 16 90",
    "sg:postcode":"9000",
    "sg:province":"Oost-Vlaanderen",
    "wof:name":"Anthonissen B",
    "wof:placetype":"venue"
},
  "geometry": {"coordinates":[3.7325949669,51.0396347046],"type":"Point"}
}