{
  "type": "Feature",
  "properties": {
    "addr:full":"Rue D\u00e9sir\u00e9 Desmet 14 Bruxelles (schaerbeek) Bruxelles-Capitale 1030",
    "addr:housenumber":"14",
    "addr:postcode":"1030",
    "addr:street":"Rue De\u0301Sire\u0301 Desmet",
    "iso:country":"BE",
    "sg:address":"Rue D\u00e9sir\u00e9 Desmet 14",
    "sg:city":"Bruxelles (schaerbeek)",
    "sg:classifiers":[
        {
            "category":"Communications",
            "subcategory":"Film & Video Production",
            "type":"Services"
        }
    ],
    "sg:phone":"+32 2 245 66 63",
    "sg:postcode":"1030",
    "sg:province":"Bruxelles-Capitale",
    "sg:tags":[
        "producer",
        "realizators"
    ],
    "wof:name":"Max Le Producteur",
    "wof:placetype":"venue"
},
  "geometry": {"coordinates":[4.3940358162,50.8659324646],"type":"Point"}
}