{
  "type": "Feature",
  "properties": {
    "addr:full":"Ijzerenleen 54 Mechelen Antwerpen 2800",
    "addr:housenumber":"54",
    "addr:postcode":"2800",
    "addr:street":"Ijzerenleen",
    "iso:country":"BE",
    "sg:address":"Ijzerenleen 54",
    "sg:city":"Mechelen",
    "sg:orig_category":"Kapsalons",
    "sg:phone":"+32 15 20 38 79",
    "sg:postcode":"2800",
    "sg:province":"Antwerpen",
    "wof:name":"Felix Van Hooff",
    "wof:placetype":"venue"
},
  "geometry": {"coordinates":[4.478000164,51.0264701843],"type":"Point"}
}