{
  "type": "Feature",
  "properties": {
    "iso:country":"BE",
    "sg:address":"Rue Mathieu Desmar\u00c9 16",
    "sg:city":"Brussel/bruxelles",
    "sg:orig_category":"Enseignement secondaire g\u00e9n\u00e9ral",
    "sg:phone":"+32 2 478 03 33",
    "sg:postcode":"1020",
    "sg:province":"Bruxelles-Capitale",
    "wof:name":"Buso Cardijnschool",
    "wof:placetype":"venue"
},
  "geometry": {"coordinates":[4.357129097,50.8796806335],"type":"Point"}
}