{
  "type": "Feature",
  "properties": {
    "iso:country":"BE",
    "sg:address":"Rue Du Bas Commognes 25",
    "sg:city":"Jemeppe-sur-sambre",
    "sg:classifiers":[
        {
            "category":"Retail",
            "subcategory":"Veterinary Services",
            "type":"Services"
        }
    ],
    "sg:phone":"+32 71 78 72 18",
    "sg:postcode":"5190",
    "sg:province":"Namur",
    "sg:tags":[
        "veterinarian"
    ],
    "wof:name":"Lorand G",
    "wof:placetype":"venue"
},
  "geometry": {"coordinates":[4.6556692123,50.4667167664],"type":"Point"}
}