{
  "type": "Feature",
  "properties": {
    "addr:full":"Lodewijk Coiseaukaai 20 Brugge West-Vlaanderen 8000",
    "addr:housenumber":"20",
    "addr:postcode":"8000",
    "addr:street":"Lodewijk Coiseaukaai",
    "iso:country":"BE",
    "sg:address":"Lodewijk Coiseaukaai 20",
    "sg:city":"Brugge",
    "sg:classifiers":[
        {
            "category":"Transit Center",
            "subcategory":"Passenger",
            "type":"Transportation"
        }
    ],
    "sg:phone":"+32 50 33 09 10",
    "sg:postcode":"8000",
    "sg:province":"West-Vlaanderen",
    "sg:tags":[
        "car",
        "trailer"
    ],
    "wof:name":"Jumbo Wheels",
    "wof:placetype":"venue"
},
  "geometry": {"coordinates":[3.2261660099,51.2305412292],"type":"Point"}
}