{
  "type": "Feature",
  "properties": {
    "addr:full":"Rue Du Surtia 14 La Bruy\u00e8re (saint-denis) Namur 5081",
    "addr:housenumber":"14",
    "addr:postcode":"5081",
    "addr:street":"Rue Du Surtia;Bruye\u0300Re Saint-Denis",
    "iso:country":"BE",
    "sg:address":"Rue Du Surtia 14",
    "sg:city":"La Bruy\u00e8re (saint-denis)",
    "sg:classifiers":[
        {
            "category":"Banks & Credit Unions",
            "subcategory":"Investment Brokerage",
            "type":"Services"
        }
    ],
    "sg:phone":"+32 81 56 78 34",
    "sg:postcode":"5081",
    "sg:province":"Namur",
    "sg:tags":[
        "wreath",
        "mourning"
    ],
    "wof:name":"Mathy M",
    "wof:placetype":"venue"
},
  "geometry": {"coordinates":[4.775290966,50.541267395],"type":"Point"}
}