{
  "type": "Feature",
  "properties": {
    "iso:country":"BE",
    "sg:address":"Ertbrandstraat 280",
    "sg:city":"Kapellen",
    "sg:orig_category":"Fournitures de bureau. Tabac. Journaux. Librairies",
    "sg:phone":"+32 3 664 42 68",
    "sg:postcode":"2950",
    "sg:province":"Antwerpen",
    "wof:name":"Edhaco",
    "wof:placetype":"venue"
},
  "geometry": {"coordinates":[4.3995399475,51.3481712341],"type":"Point"}
}