{
  "type": "Feature",
  "properties": {
    "addr:full":"J.f. Debeckerlaan 90 Sint-lambrechts-woluwe/woluwe-saint-lambert Bruxelles-Capitale 1200",
    "addr:housenumber":"90",
    "addr:postcode":"1200",
    "addr:street":"J.F. Debeckerlaan",
    "iso:country":"BE",
    "sg:address":"J.f. Debeckerlaan 90",
    "sg:city":"Sint-lambrechts-woluwe/woluwe-saint-lambert",
    "sg:orig_category":"Artsen and specialisten",
    "sg:phone":"+32 2 770 59 13",
    "sg:postcode":"1200",
    "sg:province":"Bruxelles-Capitale",
    "wof:name":"Jean Hanson",
    "wof:placetype":"venue"
},
  "geometry": {"coordinates":[4.4466781616,50.8451042175],"type":"Point"}
}