{
  "type": "Feature",
  "properties": {
    "addr:full":"Hasseltsesteenweg 220 Tongeren Limburg 3700",
    "addr:housenumber":"220",
    "addr:postcode":"3700",
    "addr:street":"Hasseltsesteenweg",
    "iso:country":"BE",
    "sg:address":"Hasseltsesteenweg 220",
    "sg:city":"Tongeren",
    "sg:classifiers":[
        {
            "category":"Cafe",
            "type":"Food & Drink"
        }
    ],
    "sg:phone":"+32 12 23 15 19",
    "sg:postcode":"3700",
    "sg:province":"Limburg",
    "sg:tags":[
        "caf\u00e9s"
    ],
    "wof:name":"Caf\u00c9 De Pijl",
    "wof:placetype":"venue"
},
  "geometry": {"coordinates":[5.4536547661,50.7872886658],"type":"Point"}
}