{
  "type": "Feature",
  "properties": {
    "iso:country":"BE",
    "sg:address":"Rue Brigade Piron 11",
    "sg:city":"Brunehaut",
    "sg:orig_category":"P\u00e9pini\u00e9ristes",
    "sg:phone":"+32 69 34 47 60",
    "sg:postcode":"7623",
    "sg:province":"Hainaut",
    "wof:name":"Jean-claude Cartigny",
    "wof:placetype":"venue"
},
  "geometry": {"coordinates":[3.3915588856,50.5020446777],"type":"Point"}
}