{
  "type": "Feature",
  "properties": {
    "iso:country":"BE",
    "sg:address":"Rue Houzeau De Lehaie 25",
    "sg:city":"Bruxelles (molenbeek-saint-jean)",
    "sg:classifiers":[
        {
            "category":"Professional",
            "subcategory":"Art Services",
            "type":"Services"
        }
    ],
    "sg:phone":"+32 2 410 48 13",
    "sg:postcode":"1080",
    "sg:province":"Bruxelles-Capitale",
    "sg:tags":[
        "realization",
        "audio-visual"
    ],
    "wof:name":"Blieck H",
    "wof:placetype":"venue"
},
  "geometry": {"coordinates":[4.3372020721,50.8606338501],"type":"Point"}
}