{
  "type": "Feature",
  "properties": {
    "addr:full":"19 Grand Rue 6791 Athus 19",
    "addr:housenumber":"19",
    "addr:postcode":"6791",
    "addr:street":"Grand Rue",
    "iso:country":"BE",
    "sg:address":"19",
    "sg:city":"Grand Rue 6791 Athus",
    "sg:classifiers":[
        {
            "category":"Bakery",
            "type":"Food & Drink"
        }
    ],
    "sg:phone":"+32 63 37 05 13",
    "sg:postcode":"19",
    "sg:tags":[
        "cake",
        "product",
        "related",
        "bread"
    ],
    "wof:name":"Boulangerie Schouweiler Nv",
    "wof:placetype":"venue"
},
  "geometry": {"coordinates":[5.8368301392,49.5627288818],"type":"Point"}
}