{
  "type": "Feature",
  "properties": {
    "addr:full":"Leenstraat 4 Roeselare West-Vlaanderen 8800",
    "addr:housenumber":"4",
    "addr:postcode":"8800",
    "addr:street":"Leenstraat",
    "iso:country":"BE",
    "sg:address":"Leenstraat 4",
    "sg:city":"Roeselare",
    "sg:orig_category":"Technische studies and ingenieursactiviteiten",
    "sg:phone":"+32 51 20 59 41",
    "sg:postcode":"8800",
    "sg:province":"West-Vlaanderen",
    "wof:name":"Demey",
    "wof:placetype":"venue"
},
  "geometry": {"coordinates":[3.1276841164,50.944606781],"type":"Point"}
}