{
  "type": "Feature",
  "properties": {
    "addr:full":"Pijpelstraat 91 Heist-op-den-berg (booischot) Antwerpen 2221",
    "addr:housenumber":"91",
    "addr:postcode":"2221",
    "addr:street":"Pijpelstraat",
    "iso:country":"BE",
    "sg:address":"Pijpelstraat 91",
    "sg:city":"Heist-op-den-berg (booischot)",
    "sg:classifiers":[
        {
            "category":"Airport",
            "subcategory":"International",
            "type":"Transportation"
        }
    ],
    "sg:phone":"+32 15 22 22 26",
    "sg:postcode":"2221",
    "sg:province":"Antwerpen",
    "sg:tags":[
        "-",
        "transport"
    ],
    "wof:name":"G.m.a. Trans",
    "wof:placetype":"venue"
},
  "geometry": {"coordinates":[4.7739758492,51.0512428284],"type":"Point"}
}