{
  "type": "Feature",
  "properties": {
    "addr:full":"Rue De L'eglise 2 Ferri\u00e8res (xhoris) Li\u00e8ge 4190",
    "addr:housenumber":"2",
    "addr:postcode":"4190",
    "addr:street":"Rue De L'Eglise",
    "iso:country":"BE",
    "sg:address":"Rue De L'eglise 2",
    "sg:city":"Ferri\u00e8res (xhoris)",
    "sg:classifiers":[
        {
            "category":"Travel",
            "subcategory":"Resort",
            "type":"Entertainment"
        }
    ],
    "sg:phone":"+32 4 369 27 10",
    "sg:postcode":"4190",
    "sg:province":"Li\u00e8ge",
    "sg:tags":[
        "vacation"
    ],
    "wof:name":"Relaxhoris",
    "wof:placetype":"venue"
},
  "geometry": {"coordinates":[5.6009840965,50.4439086914],"type":"Point"}
}