{
  "type": "Feature",
  "properties": {
    "iso:country":"BE",
    "sg:address":"Maldersesteenweg 24",
    "sg:city":"Londerzeel",
    "sg:orig_category":"Gespecialiseerde residenti\u00eble bouw Tuinen",
    "sg:phone":"+32 52 30 27 02",
    "sg:postcode":"1840",
    "sg:province":"Vlaams-Brabant",
    "wof:name":"Tuinen Jos Meeus",
    "wof:placetype":"venue"
},
  "geometry": {"coordinates":[4.2814421654,51.0306663513],"type":"Point"}
}