{
  "type": "Feature",
  "properties": {
    "iso:country":"BE",
    "sg:address":"Rue Eloi Fouarge 29",
    "sg:city":"Saint-georges-sur-meuse",
    "sg:classifiers":[
        {
            "category":"Bars & Pubs",
            "type":"Food & Drink"
        }
    ],
    "sg:phone":"+32 4 275 20 63",
    "sg:postcode":"4470",
    "sg:province":"Li\u00e8ge",
    "wof:name":"Piscine (caf\u00e9taria De La)",
    "wof:placetype":"venue"
},
  "geometry": {"coordinates":[5.360809803,50.5887184143],"type":"Point"}
}