{
  "type": "Feature",
  "properties": {
    "addr:full":"Zoning Artisanal Chimay Hainaut 6464",
    "addr:postcode":"6464",
    "addr:street":"Zoning;Hainaut",
    "iso:country":"BE",
    "sg:address":"Zoning Artisanal",
    "sg:city":"Chimay",
    "sg:orig_category":"D\u00e9taillants en pi\u00e8ces and accessoires de voitures",
    "sg:phone":"+32 60 21 13 42",
    "sg:postcode":"6464",
    "sg:province":"Hainaut",
    "wof:name":"Sevrain",
    "wof:placetype":"venue"
},
  "geometry": {"coordinates":[4.3209447861,50.0234336853],"type":"Point"}
}