{
  "type": "Feature",
  "properties": {
    "iso:country":"BE",
    "sg:address":"Dendermondsesteenweg 113",
    "sg:city":"Asse",
    "sg:orig_category":"Gespecialiseerde residenti\u00eble bouw",
    "sg:phone":"+32 2 452 57 07",
    "sg:postcode":"1730",
    "sg:province":"Vlaams-Brabant",
    "wof:name":"Louis Raes",
    "wof:placetype":"venue"
},
  "geometry": {"coordinates":[4.1826090813,50.9242515564],"type":"Point"}
}