{
  "type": "Feature",
  "properties": {
    "addr:full":"Camiel Huysmanslaan 13 Sint-niklaas Oost-Vlaanderen 9100",
    "addr:housenumber":"13",
    "addr:postcode":"9100",
    "addr:street":"Camiel Huysmanslaan",
    "iso:country":"BE",
    "sg:address":"Camiel Huysmanslaan 13",
    "sg:city":"Sint-niklaas",
    "sg:classifiers":[
        {
            "category":"Professional",
            "subcategory":"Advertising",
            "type":"Services"
        }
    ],
    "sg:phone":"+32 3 777 48 42",
    "sg:postcode":"9100",
    "sg:province":"Oost-Vlaanderen",
    "sg:tags":[
        "aerial",
        "-"
    ],
    "wof:name":"Balloonteam Dirk Van Avermaet",
    "wof:placetype":"venue"
},
  "geometry": {"coordinates":[4.1407179832,51.1820259094],"type":"Point"}
}