{
  "type": "Feature",
  "properties": {
    "addr:full":"Henri Brounsstraat 34 Machelen Vlaams-Brabant 1830",
    "addr:housenumber":"34",
    "addr:postcode":"1830",
    "addr:street":"Henri Brounsstraat",
    "iso:country":"BE",
    "sg:address":"Henri Brounsstraat 34",
    "sg:city":"Machelen",
    "sg:orig_category":"Verbruikerskredietinstellingen",
    "sg:phone":"+32 2 251 51 97",
    "sg:postcode":"1830",
    "sg:province":"Vlaams-Brabant",
    "wof:name":"Kockaert Willy",
    "wof:placetype":"venue"
},
  "geometry": {"coordinates":[4.4328179359,50.9089279175],"type":"Point"}
}