{
  "type": "Feature",
  "properties": {
    "iso:country":"BE",
    "sg:address":"Bredestraat 46",
    "sg:city":"Gent (oostakker)",
    "sg:classifiers":[
        {
            "category":"Bars & Pubs",
            "type":"Food & Drink"
        }
    ],
    "sg:phone":"+32 9 251 32 45",
    "sg:postcode":"9041",
    "sg:province":"Oost-Vlaanderen",
    "wof:name":"The New Stingray",
    "wof:placetype":"venue"
},
  "geometry": {"coordinates":[3.7673099041,51.1010971069],"type":"Point"}
}