{
  "type": "Feature",
  "properties": {
    "iso:country":"BE",
    "sg:address":"Kruisstraat 42",
    "sg:city":"Tremelo",
    "sg:classifiers":[
        {
            "category":"Cafe",
            "type":"Food & Drink"
        }
    ],
    "sg:phone":"+32 16 53 09 96",
    "sg:postcode":"3120",
    "sg:province":"Vlaams-Brabant",
    "sg:tags":[
        "caf\u00e9s"
    ],
    "wof:name":"Caf\u00c9 De Metteberg",
    "wof:placetype":"venue"
},
  "geometry": {"coordinates":[4.7013292313,50.9941177368],"type":"Point"}
}