{
  "type": "Feature",
  "properties": {
    "iso:country":"BE",
    "sg:address":"Ommeganckstraat 45",
    "sg:city":"Antwerpen",
    "sg:classifiers":[
        {
            "category":"Shopping",
            "subcategory":"Crafts & Fabrics",
            "type":"Retail Goods"
        }
    ],
    "sg:phone":"+32 3 233 31 68",
    "sg:postcode":"2018",
    "sg:province":"Antwerpen",
    "sg:tags":[
        "silk",
        "-"
    ],
    "wof:name":"Schepens G Bvba",
    "wof:placetype":"venue"
},
  "geometry": {"coordinates":[4.4251661301,51.2170944214],"type":"Point"}
}