{
  "type": "Feature",
  "properties": {
    "addr:full":"I.z. Wolfstee Toekomstlaan 14 Herentals Antwerpen 2200",
    "addr:housenumber":"14",
    "addr:postcode":"2200",
    "addr:street":"Toekomstlaan",
    "iso:country":"BE",
    "sg:address":"I.z. Wolfstee Toekomstlaan 14",
    "sg:city":"Herentals",
    "sg:classifiers":[
        {
            "category":"Shopping",
            "subcategory":"Gifts & Souvenirs",
            "type":"Retail Goods"
        }
    ],
    "sg:phone":"+32 14 28 65 00",
    "sg:postcode":"2200",
    "sg:province":"Antwerpen",
    "sg:tags":[
        "box",
        "packing",
        "purpose"
    ],
    "wof:name":"Decapac Nv",
    "wof:placetype":"venue"
},
  "geometry": {"coordinates":[4.8103518486,51.1609764099],"type":"Point"}
}