{
  "type": "Feature",
  "properties": {
    "iso:country":"BE",
    "sg:address":"Marktplein 78",
    "sg:city":"Harelbeke",
    "sg:orig_category":"Technische and wetenschappelijke instrumenten Fab",
    "sg:phone":"+32 56 72 71 11",
    "sg:postcode":"8530",
    "sg:province":"West-Vlaanderen",
    "wof:name":"Alarm Automatic Systems",
    "wof:placetype":"venue"
},
  "geometry": {"coordinates":[3.3086841106,50.8553581238],"type":"Point"}
}