{
  "type": "Feature",
  "properties": {
    "addr:full":"Torhoutbaan 63 Ichtegem West-Vlaanderen 8480",
    "addr:housenumber":"63",
    "addr:postcode":"8480",
    "addr:street":"Torhoutbaan",
    "iso:country":"BE",
    "sg:address":"Torhoutbaan 63",
    "sg:city":"Ichtegem",
    "sg:classifiers":[
        {
            "category":"Banks & Credit Unions",
            "subcategory":"Investment Brokerage",
            "type":"Services"
        }
    ],
    "sg:phone":"+32 51 58 38 50",
    "sg:postcode":"8480",
    "sg:province":"West-Vlaanderen",
    "sg:tags":[
        "fence"
    ],
    "wof:name":"Afsluitingen Koekuyt Bvba",
    "wof:placetype":"venue"
},
  "geometry": {"coordinates":[3.0388948917,51.0972976685],"type":"Point"}
}