{
  "type": "Feature",
  "properties": {
    "iso:country":"BE",
    "sg:address":"Graankaai 4",
    "sg:city":"Roeselare",
    "sg:classifiers":[
        {
            "category":"Transit Center",
            "subcategory":"Passenger",
            "type":"Transportation"
        }
    ],
    "sg:phone":"+32 51 22 79 55",
    "sg:postcode":"8800",
    "sg:province":"West-Vlaanderen",
    "sg:tags":[
        "sand",
        "gravel"
    ],
    "wof:name":"Zandhandel Roeselare Nv",
    "wof:placetype":"venue"
},
  "geometry": {"coordinates":[3.156799078,50.9438858032],"type":"Point"}
}