{
  "type": "Feature",
  "properties": {
    "addr:full":"Camp De Corroy 53 Huy Li\u00e8ge 4500",
    "addr:housenumber":"53",
    "addr:postcode":"4500",
    "addr:street":"Corroy",
    "iso:country":"BE",
    "sg:address":"Camp De Corroy 53",
    "sg:city":"Huy",
    "sg:orig_category":"Boekhouders",
    "sg:phone":"+32 85 21 37 24",
    "sg:postcode":"4500",
    "sg:province":"Li\u00e8ge",
    "wof:name":"Georgette Hercot",
    "wof:placetype":"venue"
},
  "geometry": {"coordinates":[5.2299609184,50.5107536316],"type":"Point"}
}