{
  "type": "Feature",
  "properties": {
    "iso:country":"BE",
    "sg:address":"Vlasendaalstraat 67",
    "sg:city":"Dilbeek",
    "sg:classifiers":[
        {
            "category":"Building & Trades",
            "subcategory":"Landscaping Services",
            "type":"Services"
        }
    ],
    "sg:phone":"+32 2 569 54 25",
    "sg:postcode":"1700",
    "sg:province":"Vlaams-Brabant",
    "sg:tags":[
        "-",
        "lopping",
        "work",
        "tree",
        "felling"
    ],
    "wof:name":"Broekaert G",
    "wof:placetype":"venue"
},
  "geometry": {"coordinates":[4.2544369698,50.8319587708],"type":"Point"}
}