{
  "type": "Feature",
  "properties": {
    "addr:full":"Rue Joseph Wauters 5 Awans Li\u00e8ge 4340",
    "addr:housenumber":"5",
    "addr:postcode":"4340",
    "addr:street":"Rue Joseph Wauters",
    "iso:country":"BE",
    "sg:address":"Rue Joseph Wauters 5",
    "sg:city":"Awans",
    "sg:classifiers":[
        {
            "category":"Bakery",
            "type":"Food & Drink"
        }
    ],
    "sg:phone":"+32 4 263 53 22",
    "sg:postcode":"4340",
    "sg:province":"Li\u00e8ge",
    "sg:tags":[
        "confectioner",
        "baker"
    ],
    "wof:name":"Bellefroid J-n",
    "wof:placetype":"venue"
},
  "geometry": {"coordinates":[5.4686260223,50.6679611206],"type":"Point"}
}