{
  "type": "Feature",
  "properties": {
    "addr:full":"Vaartstraat 47 Laarne Oost-Vlaanderen 9270",
    "addr:housenumber":"47",
    "addr:postcode":"9270",
    "addr:street":"Vaartstraat",
    "iso:country":"BE",
    "sg:address":"Vaartstraat 47",
    "sg:city":"Laarne",
    "sg:orig_category":"Catering and organisatie van feesten Vis and zeevruchten",
    "sg:phone":"+32 9 367 84 74",
    "sg:postcode":"9270",
    "sg:province":"Oost-Vlaanderen",
    "wof:name":"'t Kapiteintje",
    "wof:placetype":"venue"
},
  "geometry": {"coordinates":[3.8489339352,51.0294075012],"type":"Point"}
}