{
  "type": "Feature",
  "properties": {
    "addr:full":"Rue De L'espinette 202 Quaregnon Hainaut 7390",
    "addr:housenumber":"202",
    "addr:postcode":"7390",
    "addr:street":"Rue De L'Espinette",
    "iso:country":"BE",
    "sg:address":"Rue De L'espinette 202",
    "sg:city":"Quaregnon",
    "sg:classifiers":[
        {
            "category":"Shopping",
            "subcategory":"Shoes",
            "type":"Retail Goods"
        }
    ],
    "sg:phone":"+32 65 78 42 13",
    "sg:postcode":"7390",
    "sg:province":"Hainaut",
    "sg:tags":[
        "slipper",
        "-"
    ],
    "wof:name":"Scris Shoe Group Sprl",
    "wof:placetype":"venue"
},
  "geometry": {"coordinates":[3.8572208881,50.4331321716],"type":"Point"}
}