{
  "type": "Feature",
  "properties": {
    "iso:country":"BE",
    "sg:address":"Rue De La Station 17a",
    "sg:city":"Waterloo",
    "sg:classifiers":[
        {
            "category":"Retail",
            "subcategory":"Auto Repair",
            "type":"Services"
        }
    ],
    "sg:phone":"+32 2 354 06 93",
    "sg:postcode":"1410",
    "sg:province":"Brabant Wallon",
    "sg:tags":[
        "garage"
    ],
    "wof:name":"Annez Garage",
    "wof:placetype":"venue"
},
  "geometry": {"coordinates":[4.3938179016,50.7171058655],"type":"Point"}
}