{
  "type": "Feature",
  "properties": {
    "iso:country":"BE",
    "sg:address":"Westerlosesteenweg 26",
    "sg:city":"Heist-op-den-berg",
    "sg:orig_category":"Advocaten and juridische adviseurs",
    "sg:phone":"+32 15 24 17 19",
    "sg:postcode":"2220",
    "sg:province":"Antwerpen",
    "wof:name":"A. Verbist",
    "wof:placetype":"venue"
},
  "geometry": {"coordinates":[4.7348918915,51.0732383728],"type":"Point"}
}