{
  "type": "Feature",
  "properties": {
    "addr:full":"Bremenhulstraat 7 Wichelen (serskamp) Oost-Vlaanderen 9260",
    "addr:housenumber":"7",
    "addr:postcode":"9260",
    "addr:street":"Bremenhulstraat",
    "iso:country":"BE",
    "sg:address":"Bremenhulstraat 7",
    "sg:city":"Wichelen (serskamp)",
    "sg:classifiers":[
        {
            "category":"Professional",
            "subcategory":"Accounting & Tax Preparation",
            "type":"Services"
        }
    ],
    "sg:phone":"+32 9 369 44 94",
    "sg:postcode":"9260",
    "sg:province":"Oost-Vlaanderen",
    "sg:tags":[
        "bookkeeper"
    ],
    "wof:name":"Schuddinck",
    "wof:placetype":"venue"
},
  "geometry": {"coordinates":[3.927628994,50.9931564331],"type":"Point"}
}