{
  "type": "Feature",
  "properties": {
    "addr:full":"Dorperveldstraat 20 Maaseik Limburg 3680",
    "addr:housenumber":"20",
    "addr:postcode":"3680",
    "addr:street":"Dorperveldstraat",
    "iso:country":"BE",
    "sg:address":"Dorperveldstraat 20",
    "sg:city":"Maaseik",
    "sg:orig_category":"Catering and organisation de f\u00eates",
    "sg:phone":"+32 89 86 63 89",
    "sg:postcode":"3680",
    "sg:province":"Limburg",
    "wof:name":"Gilbert Boonen",
    "wof:placetype":"venue"
},
  "geometry": {"coordinates":[5.791285038,51.0954208374],"type":"Point"}
}