{
  "type": "Feature",
  "properties": {
    "iso:country":"BE",
    "sg:address":"155",
    "sg:city":"Quai Des Usines 1000 Bruxelles",
    "sg:classifiers":[
        {
            "category":"Professional",
            "subcategory":"Advertising",
            "type":"Services"
        }
    ],
    "sg:phone":"+32 2 240 81 81",
    "sg:postcode":"155",
    "sg:tags":[
        "communication",
        "medium"
    ],
    "wof:name":"Yes Sir ! Actions That Pay Off Sprl",
    "wof:placetype":"venue"
},
  "geometry": {"coordinates":[4.3636498451,50.8755111694],"type":"Point"}
}