{
  "type": "Feature",
  "properties": {
    "addr:full":"Rode-kruislaan 22 Aarschot Vlaams-Brabant 3200",
    "addr:housenumber":"22",
    "addr:postcode":"3200",
    "addr:street":"Rode-Kruislaan",
    "iso:country":"BE",
    "sg:address":"Rode-kruislaan 22",
    "sg:city":"Aarschot",
    "sg:orig_category":"Secr\u00e9tariats",
    "sg:phone":"+32 16 57 06 58",
    "sg:postcode":"3200",
    "sg:province":"Vlaams-Brabant",
    "wof:name":"Eurosystems",
    "wof:placetype":"venue"
},
  "geometry": {"coordinates":[4.8396611214,50.9946975708],"type":"Point"}
}