{
  "type": "Feature",
  "properties": {
    "addr:full":"Bierbeekstraat 69 Bierbeek (korbeek-lo) Vlaams-Brabant 3360",
    "addr:housenumber":"69",
    "addr:postcode":"3360",
    "addr:street":"Bierbeekstraat",
    "iso:country":"BE",
    "sg:address":"Bierbeekstraat 69",
    "sg:city":"Bierbeek (korbeek-lo)",
    "sg:classifiers":[
        {
            "category":"Professional",
            "subcategory":"Computer Services",
            "type":"Services"
        }
    ],
    "sg:phone":"+32 16 46 35 65",
    "sg:postcode":"3360",
    "sg:province":"Vlaams-Brabant",
    "sg:tags":[
        "-",
        "processing",
        "data",
        "software"
    ],
    "wof:name":"Slimco",
    "wof:placetype":"venue"
},
  "geometry": {"coordinates":[4.7626237869,50.8594856262],"type":"Point"}
}