{
  "type": "Feature",
  "properties": {
    "addr:full":"Zillebeek 98 Beveren Oost-Vlaanderen 9120",
    "addr:housenumber":"98",
    "addr:postcode":"9120",
    "addr:street":"Zillebeek",
    "iso:country":"BE",
    "sg:address":"Zillebeek 98",
    "sg:city":"Beveren",
    "sg:orig_category":"Eleveurs and marchands de porcs",
    "sg:phone":"+32 3 755 01 59",
    "sg:postcode":"9120",
    "sg:province":"Oost-Vlaanderen",
    "wof:name":"Jozef Lenjou",
    "wof:placetype":"venue"
},
  "geometry": {"coordinates":[4.2233262062,51.2227134705],"type":"Point"}
}