{
  "type": "Feature",
  "properties": {
    "addr:full":"Kersbeekdorp 42 Kortenaken Vlaams-Brabant 3472",
    "addr:housenumber":"42",
    "addr:postcode":"3472",
    "addr:street":"Kersbeekdorp",
    "iso:country":"BE",
    "sg:address":"Kersbeekdorp 42",
    "sg:city":"Kortenaken",
    "sg:orig_category":"Eleveurs de bovins. Eleveurs and marchands de porcs. Producteurs de fruits",
    "sg:phone":"+32 16 77 93 77",
    "sg:postcode":"3472",
    "sg:province":"Vlaams-Brabant",
    "wof:name":"Daniel Bilsen",
    "wof:placetype":"venue"
},
  "geometry": {"coordinates":[4.9930720329,50.8910484314],"type":"Point"}
}