{
  "type": "Feature",
  "properties": {
    "iso:country":"BE",
    "sg:address":"Benoit Jansenstraat 6",
    "sg:city":"Balen",
    "sg:orig_category":"Eclairage et \u00e9quipements du foyer. Installation \u00e9lectrique r\u00e9sidentielle. Electrom\u00e9nager, t\u00e9l\u00e9vision",
    "sg:phone":"+32 14 81 30 80",
    "sg:postcode":"2490",
    "sg:province":"Antwerpen",
    "wof:name":"Elektro-bertels",
    "wof:placetype":"venue"
},
  "geometry": {"coordinates":[5.1648130417,51.1635131836],"type":"Point"}
}