{
  "type": "Feature",
  "properties": {
    "iso:country":"BE",
    "sg:address":"Cl\u00c9ment De Cl\u00c9tystraat 11",
    "sg:city":"Anderlecht/anderlecht",
    "sg:orig_category":"Artsen and specialisten",
    "sg:phone":"+32 2 521 35 44",
    "sg:postcode":"1070",
    "sg:province":"Bruxelles-Capitale",
    "wof:name":"Guy Wyndham-thomas",
    "wof:placetype":"venue"
},
  "geometry": {"coordinates":[4.2975959778,50.8239555359],"type":"Point"}
}