{
  "type": "Feature",
  "properties": {
    "iso:country":"BE",
    "sg:address":"Schelfheidestraat 1",
    "sg:city":"Nieuwerkerken",
    "sg:orig_category":"Producteurs de fruits",
    "sg:phone":"+32 11 69 11 44",
    "sg:postcode":"3850",
    "sg:province":"Limburg",
    "wof:name":"Luc Gielen",
    "wof:placetype":"venue"
},
  "geometry": {"coordinates":[5.186164856,50.8746147156],"type":"Point"}
}