{
  "type": "Feature",
  "properties": {
    "addr:full":"Leiselestraat 70 Brugge West-Vlaanderen 8200",
    "addr:housenumber":"70",
    "addr:postcode":"8200",
    "addr:street":"Leiselestraat",
    "iso:country":"BE",
    "sg:address":"Leiselestraat 70",
    "sg:city":"Brugge",
    "sg:orig_category":"Architectes",
    "sg:phone":"+32 50 38 13 99",
    "sg:postcode":"8200",
    "sg:province":"West-Vlaanderen",
    "wof:name":"Lutgardis Christiaens",
    "wof:placetype":"venue"
},
  "geometry": {"coordinates":[3.1904699802,51.1992111206],"type":"Point"}
}