{
  "type": "Feature",
  "properties": {
    "iso:country":"BE",
    "sg:address":"Kerkstraat 15",
    "sg:city":"Herzele",
    "sg:classifiers":[
        {
            "category":"Shopping",
            "subcategory":"Shoes",
            "type":"Retail Goods"
        }
    ],
    "sg:phone":"+32 53 62 62 08",
    "sg:postcode":"9550",
    "sg:province":"Oost-Vlaanderen",
    "sg:tags":[
        "slipper",
        "-"
    ],
    "wof:name":"Ruka Shoe",
    "wof:placetype":"venue"
},
  "geometry": {"coordinates":[3.8918850422,50.8858261108],"type":"Point"}
}