{
  "type": "Feature",
  "properties": {
    "iso:country":"BE",
    "sg:address":"Haringgat 4",
    "sg:city":"Damme (moerkerke)",
    "sg:classifiers":[
        {
            "category":"Building & Trades",
            "subcategory":"Landscaping Services",
            "type":"Services"
        }
    ],
    "sg:phone":"+32 50 50 04 02",
    "sg:postcode":"8340",
    "sg:province":"West-Vlaanderen",
    "sg:tags":[
        "gardening",
        "garden",
        "maintenance"
    ],
    "wof:name":"Martens Theo & Zn Cv",
    "wof:placetype":"venue"
},
  "geometry": {"coordinates":[3.2840259075,51.2510452271],"type":"Point"}
}