{
  "type": "Feature",
  "properties": {
    "iso:country":"BE",
    "sg:address":"Rue Des Marais 213",
    "sg:city":"Attert (thiaumont)",
    "sg:classifiers":[
        {
            "category":"Building & Trades",
            "subcategory":"Landscaping Services",
            "type":"Services"
        }
    ],
    "sg:phone":"+32 63 21 89 67",
    "sg:postcode":"6717",
    "sg:province":"Luxembourg",
    "sg:tags":[
        "forestry"
    ],
    "wof:name":"Sud Bois Sc",
    "wof:placetype":"venue"
},
  "geometry": {"coordinates":[5.756565094,49.719329834],"type":"Point"}
}