{
  "type": "Feature",
  "properties": {
    "iso:country":"BE",
    "sg:address":"Rue Albert I 210",
    "sg:city":"Binche (leval-trahegnies)",
    "sg:classifiers":[
        {
            "category":"Personal",
            "subcategory":"Shoe Repair & Shine",
            "type":"Services"
        }
    ],
    "sg:phone":"+32 477 43 50 91",
    "sg:postcode":"7134",
    "sg:province":"Hainaut",
    "sg:tags":[
        "shoemaker"
    ],
    "wof:name":"Petit Bout De Cuir (au)",
    "wof:placetype":"venue"
},
  "geometry": {"coordinates":[4.2187051773,50.4268684387],"type":"Point"}
}