{
  "type": "Feature",
  "properties": {
    "iso:country":"BE",
    "sg:address":"Beggard 39 B1",
    "sg:city":"Zandhoven",
    "sg:orig_category":"Woningbouw",
    "sg:phone":"+32 3 484 53 88",
    "sg:postcode":"2240",
    "sg:province":"Antwerpen",
    "wof:name":"Bouwwerken Gijsbrechts",
    "wof:placetype":"venue"
},
  "geometry": {"coordinates":[4.6580052376,51.2142944336],"type":"Point"}
}