{
  "type": "Feature",
  "properties": {
    "iso:country":"BE",
    "sg:address":"Blaesstraat 118",
    "sg:city":"Brussel/bruxelles",
    "sg:orig_category":"Antiek Decoratieve kunst and kunstbenodigdheden Diverse zakelijke dienstverlening Zalen voor culture",
    "sg:phone":"+32 2 513 07 22",
    "sg:postcode":"1000",
    "sg:province":"Bruxelles-Capitale",
    "wof:name":"Galerie C. Pfeiffer",
    "wof:placetype":"venue"
},
  "geometry": {"coordinates":[4.3483848572,50.8384666443],"type":"Point"}
}