{
  "type": "Feature",
  "properties": {
    "iso:country":"BE",
    "sg:address":"Brusselbaan 161",
    "sg:city":"Affligem",
    "sg:orig_category":"Artsen and specialisten",
    "sg:phone":"+32 53 66 63 43",
    "sg:postcode":"1790",
    "sg:province":"Vlaams-Brabant",
    "wof:name":"Andy Van Schuerbeeck",
    "wof:placetype":"venue"
},
  "geometry": {"coordinates":[4.1105589867,50.9128303528],"type":"Point"}
}