{
  "type": "Feature",
  "properties": {
    "iso:country":"BE",
    "sg:address":"Parklaan 39",
    "sg:city":"Sint-niklaas",
    "sg:orig_category":"Diverse zakelijke dienstverlening Organisatie van beurzen, congressen and tentoonstellingen Public-r",
    "sg:phone":"+32 3 777 97 17",
    "sg:postcode":"9100",
    "sg:province":"Oost-Vlaanderen",
    "wof:name":"V.p.r. Consult",
    "wof:placetype":"venue"
},
  "geometry": {"coordinates":[4.1451730728,51.1614265442],"type":"Point"}
}