{
  "type": "Feature",
  "properties": {
    "addr:full":"Nieuwstraat 2a Geel Antwerpen 2440",
    "addr:housenumber":"2a",
    "addr:postcode":"2440",
    "addr:street":"Nieuwstraat",
    "iso:country":"BE",
    "sg:address":"Nieuwstraat 2a",
    "sg:city":"Geel",
    "sg:orig_category":"Bloemen and planten",
    "sg:phone":"+32 14 58 09 49",
    "sg:postcode":"2440",
    "sg:province":"Antwerpen",
    "wof:name":"Die Blomme",
    "wof:placetype":"venue"
},
  "geometry": {"coordinates":[4.991133213,51.1627197266],"type":"Point"}
}