{
  "type": "Feature",
  "properties": {
    "addr:full":"Hazebos 13 Zonnebeke West-Vlaanderen 8980",
    "addr:housenumber":"13",
    "addr:postcode":"8980",
    "addr:street":"Hazebos",
    "iso:country":"BE",
    "sg:address":"Hazebos 13",
    "sg:city":"Zonnebeke",
    "sg:classifiers":[
        {
            "category":"Professional",
            "subcategory":"Computer Services",
            "type":"Services"
        }
    ],
    "sg:phone":"+32 57 21 25 71",
    "sg:postcode":"8980",
    "sg:province":"West-Vlaanderen",
    "sg:tags":[
        "-",
        "processing",
        "data",
        "software"
    ],
    "wof:name":"Copy Paste",
    "wof:placetype":"venue"
},
  "geometry": {"coordinates":[2.98864007,50.8584938049],"type":"Point"}
}