{
  "type": "Feature",
  "properties": {
    "addr:full":"Brusselbaan 26 Affligem (hekelgem) Vlaams-Brabant 1790",
    "addr:housenumber":"26",
    "addr:postcode":"1790",
    "addr:street":"Brusselbaan",
    "iso:country":"BE",
    "sg:address":"Brusselbaan 26",
    "sg:city":"Affligem (hekelgem)",
    "sg:orig_category":"Non-Classified Establishments",
    "sg:phone":"+32 53 67 10 31",
    "sg:postcode":"1790",
    "sg:province":"Vlaams-Brabant",
    "wof:name":"Eclipse Decor",
    "wof:placetype":"venue"
},
  "geometry": {"coordinates":[4.0990791321,50.9149169922],"type":"Point"}
}