{
  "type": "Feature",
  "properties": {
    "addr:full":"Rue Julien Marsille 179 Tubize (saintes) Brabant Wallon 1480",
    "addr:housenumber":"179",
    "addr:postcode":"1480",
    "addr:street":"Rue Julien Marsille",
    "iso:country":"BE",
    "sg:address":"Rue Julien Marsille 179",
    "sg:city":"Tubize (saintes)",
    "sg:classifiers":[
        {
            "category":"Banks & Credit Unions",
            "subcategory":"Investment Brokerage",
            "type":"Services"
        }
    ],
    "sg:phone":"+32 2 355 03 88",
    "sg:postcode":"1480",
    "sg:province":"Brabant Wallon",
    "sg:tags":[
        "auditor"
    ],
    "wof:name":"Denayer Y",
    "wof:placetype":"venue"
},
  "geometry": {"coordinates":[4.1612610817,50.7163848877],"type":"Point"}
}