{
  "type": "Feature",
  "properties": {
    "addr:full":"Kukkelbosstraat 91 Diepenbeek Limburg 3590",
    "addr:housenumber":"91",
    "addr:postcode":"3590",
    "addr:street":"Kukkelbosstraat",
    "iso:country":"BE",
    "sg:address":"Kukkelbosstraat 91",
    "sg:city":"Diepenbeek",
    "sg:classifiers":[
        {
            "category":"Building & Trades",
            "subcategory":"Cleaning & Sanitation",
            "type":"Services"
        }
    ],
    "sg:phone":"+32 11 33 19 42",
    "sg:postcode":"3590",
    "sg:province":"Limburg",
    "sg:tags":[
        "fa\u00e7ade",
        "maintenance"
    ],
    "wof:name":"Bosch Bvba",
    "wof:placetype":"venue"
},
  "geometry": {"coordinates":[5.4366297722,50.8870620728],"type":"Point"}
}