{
  "type": "Feature",
  "properties": {
    "addr:full":"Rue Du Hazoir 25 La Bruyere Namur 5080",
    "addr:housenumber":"25",
    "addr:postcode":"5080",
    "addr:street":"Rue Du Hazoir;La Bruyere",
    "iso:country":"BE",
    "sg:address":"Rue Du Hazoir 25",
    "sg:city":"La Bruyere",
    "sg:orig_category":"Paramedische behandelingen",
    "sg:phone":"+32 81 21 30 19",
    "sg:postcode":"5080",
    "sg:province":"Namur",
    "wof:name":"L. Julien",
    "wof:placetype":"venue"
},
  "geometry": {"coordinates":[4.8293709755,50.5170860291],"type":"Point"}
}