{
  "type": "Feature",
  "properties": {
    "addr:full":"Duisburgsesteenweg 120 Overijse Vlaams-Brabant 3090",
    "addr:housenumber":"120",
    "addr:postcode":"3090",
    "addr:street":"Duisburgsesteenweg",
    "iso:country":"BE",
    "sg:address":"Duisburgsesteenweg 120",
    "sg:city":"Overijse",
    "sg:classifiers":[
        {
            "category":"Health Services",
            "subcategory":"Dentist",
            "type":"Services"
        }
    ],
    "sg:phone":"+32 2 687 89 36",
    "sg:postcode":"3090",
    "sg:province":"Vlaams-Brabant",
    "wof:name":"Gorissen Lyda",
    "wof:placetype":"venue"
},
  "geometry": {"coordinates":[4.5490498543,50.7983283997],"type":"Point"}
}