{
  "type": "Feature",
  "properties": {
    "iso:country":"BE",
    "sg:address":"Chemin Notre-dame 3",
    "sg:city":"Villers-la-ville",
    "sg:orig_category":"M\u00e9decins and sp\u00e9cialistes",
    "sg:phone":"+32 71 87 89 39",
    "sg:postcode":"1495",
    "sg:province":"Brabant Wallon",
    "wof:name":"Robert Vanderschueren",
    "wof:placetype":"venue"
},
  "geometry": {"coordinates":[4.5370187759,50.5833930969],"type":"Point"}
}