{
  "type": "Feature",
  "properties": {
    "iso:country":"BE",
    "sg:address":"Moorseelsestraat 97",
    "sg:city":"Kortrijk",
    "sg:orig_category":"Kapsalons",
    "sg:phone":"+32 56 35 54 92",
    "sg:postcode":"8500",
    "sg:province":"West-Vlaanderen",
    "wof:name":"Tanja Geldhof",
    "wof:placetype":"venue"
},
  "geometry": {"coordinates":[3.249119997,50.8317565918],"type":"Point"}
}