{
  "type": "Feature",
  "properties": {
    "addr:full":"Rue De Florival 61 Grez-doiceau Brabant Wallon 1390",
    "addr:housenumber":"61",
    "addr:postcode":"1390",
    "addr:street":"Rue De Florival",
    "iso:country":"BE",
    "sg:address":"Rue De Florival 61",
    "sg:city":"Grez-doiceau",
    "sg:orig_category":"Verplichte sociale verzekeringen",
    "sg:phone":"+32 10 84 52 52",
    "sg:postcode":"1390",
    "sg:province":"Brabant Wallon",
    "wof:name":"Mutualit\u00c9 Socialiste",
    "wof:placetype":"venue"
},
  "geometry": {"coordinates":[4.6638021469,50.7539329529],"type":"Point"}
}