{
  "type": "Feature",
  "properties": {
    "addr:full":"Boomgaardstraat 15 Ieper West-Vlaanderen 8900",
    "addr:housenumber":"15",
    "addr:postcode":"8900",
    "addr:street":"Boomgaardstraat",
    "iso:country":"BE",
    "sg:address":"Boomgaardstraat 15",
    "sg:city":"Ieper",
    "sg:orig_category":"Textiel",
    "sg:phone":"+32 57 20 15 42",
    "sg:postcode":"8900",
    "sg:province":"West-Vlaanderen",
    "wof:name":"Huis De Puydt",
    "wof:placetype":"venue"
},
  "geometry": {"coordinates":[2.8850700855,50.8496170044],"type":"Point"}
}