{
  "type": "Feature",
  "properties": {
    "addr:full":"Frans Vander Elststraat 2 Kraainem Vlaams-Brabant 1950",
    "addr:housenumber":"2",
    "addr:postcode":"1950",
    "addr:street":"Frans Vander Elststraat",
    "iso:country":"BE",
    "sg:address":"Frans Vander Elststraat 2",
    "sg:city":"Kraainem",
    "sg:orig_category":"Textiel Verlichting and huishoudartikelen",
    "sg:phone":"+32 2 784 38 64",
    "sg:postcode":"1950",
    "sg:province":"Vlaams-Brabant",
    "wof:name":"Les Tissus Du Sablon",
    "wof:placetype":"venue"
},
  "geometry": {"coordinates":[4.4668998718,50.8401985168],"type":"Point"}
}