{
  "type": "Feature",
  "properties": {
    "addr:full":"Rue Joseph Wettinck 60 Seraing Li\u00e8ge 4101",
    "addr:housenumber":"60",
    "addr:postcode":"4101",
    "addr:street":"Rue Joseph Wettinck",
    "iso:country":"BE",
    "sg:address":"Rue Joseph Wettinck 60",
    "sg:city":"Seraing",
    "sg:orig_category":"Diverse kredietdiensten",
    "sg:postcode":"4101",
    "sg:province":"Li\u00e8ge",
    "wof:name":"Bancontact-mister Cash",
    "wof:placetype":"venue"
},
  "geometry": {"coordinates":[5.5014438629,50.6151695251],"type":"Point"}
}