{
  "type": "Feature",
  "properties": {
    "iso:country":"BE",
    "sg:address":"Avenue Du Parc 34ba",
    "sg:city":"Herve",
    "sg:orig_category":"Drukkerijen and copyshops",
    "sg:phone":"+32 87 35 14 75",
    "sg:postcode":"4650",
    "sg:province":"Li\u00e8ge",
    "wof:name":"Scurole",
    "wof:placetype":"venue"
},
  "geometry": {"coordinates":[5.8318758011,50.6246185303],"type":"Point"}
}