{
  "type": "Feature",
  "properties": {
    "addr:full":"Koning Albertlaan 79 Gent Oost-Vlaanderen 9000",
    "addr:housenumber":"79",
    "addr:postcode":"9000",
    "addr:street":"Koning Albertlaan;Oost-Vlaanderen",
    "iso:country":"BE",
    "sg:address":"Koning Albertlaan 79",
    "sg:city":"Gent",
    "sg:orig_category":"Werk and personeelsselectie",
    "sg:phone":"+32 9 243 40 80",
    "sg:postcode":"9000",
    "sg:province":"Oost-Vlaanderen",
    "wof:name":"Search & Selection",
    "wof:placetype":"venue"
},
  "geometry": {"coordinates":[3.7101318836,51.0392417908],"type":"Point"}
}