{
  "type": "Feature",
  "properties": {
    "addr:full":"Rue Monstienne 5 Walcourt Namur 5650",
    "addr:housenumber":"5",
    "addr:postcode":"5650",
    "addr:street":"Rue Monstienne",
    "iso:country":"BE",
    "sg:address":"Rue Monstienne 5",
    "sg:city":"Walcourt",
    "sg:orig_category":"Paramedische behandelingen",
    "sg:phone":"+32 71 65 52 63",
    "sg:postcode":"5650",
    "sg:province":"Namur",
    "wof:name":"Ch. Dumont",
    "wof:placetype":"venue"
},
  "geometry": {"coordinates":[4.4313349724,50.2514762878],"type":"Point"}
}