{
  "type": "Feature",
  "properties": {
    "iso:country":"BE",
    "sg:address":"Zomerbloemweg 22",
    "sg:city":"Ieper",
    "sg:orig_category":"Eleveurs de bovins",
    "sg:phone":"+32 57 42 20 30",
    "sg:postcode":"8906",
    "sg:province":"West-Vlaanderen",
    "wof:name":"Robert Lahousse",
    "wof:placetype":"venue"
},
  "geometry": {"coordinates":[2.8110849857,50.894153595],"type":"Point"}
}