{
  "type": "Feature",
  "properties": {
    "iso:country":"BE",
    "sg:address":"Boomsesteenweg 30",
    "sg:city":"Aartselaar",
    "sg:classifiers":[
        {
            "category":"Communications",
            "subcategory":"Film & Video Production",
            "type":"Services"
        }
    ],
    "sg:phone":"+32 3 887 28 08",
    "sg:postcode":"2630",
    "sg:province":"Antwerpen",
    "sg:tags":[
        "sound",
        "recording",
        "studio"
    ],
    "wof:name":"Starline Productions",
    "wof:placetype":"venue"
},
  "geometry": {"coordinates":[4.3754792213,51.130443573],"type":"Point"}
}