{
  "type": "Feature",
  "properties": {
    "addr:full":"Markt 13 Gistel West-Vlaanderen 8470",
    "addr:housenumber":"13",
    "addr:postcode":"8470",
    "addr:street":"Markt",
    "iso:country":"BE",
    "sg:address":"Markt 13",
    "sg:city":"Gistel",
    "sg:orig_category":"Textiles. V\u00eatements",
    "sg:phone":"+32 59 27 92 65",
    "sg:postcode":"8470",
    "sg:province":"West-Vlaanderen",
    "wof:name":"Huis Panesi",
    "wof:placetype":"venue"
},
  "geometry": {"coordinates":[2.9675819874,51.1561508179],"type":"Point"}
}