{
  "type": "Feature",
  "properties": {
    "addr:full":"Place De Brogne 18 Mettet (saint-g\u00e9rard) Namur 5640",
    "addr:housenumber":"18",
    "addr:postcode":"5640",
    "addr:street":"Place De Brogne;Saint-Ge\u0301Rard",
    "iso:country":"BE",
    "sg:address":"Place De Brogne 18",
    "sg:city":"Mettet (saint-g\u00e9rard)",
    "sg:classifiers":[
        {
            "category":"Wholesale",
            "subcategory":"Wine & Distilled Alcoholic Beverages",
            "type":"Manufacturing & Wholesale Goods"
        }
    ],
    "sg:phone":"+32 71 79 90 19",
    "sg:postcode":"5640",
    "sg:province":"Namur",
    "sg:tags":[
        "whol",
        "-",
        "spirit",
        "mfg"
    ],
    "wof:name":"Olivier Vins De Qualit\u00e9 Sprl",
    "wof:placetype":"venue"
},
  "geometry": {"coordinates":[4.7397618294,50.3458976746],"type":"Point"}
}