{
  "type": "Feature",
  "properties": {
    "addr:full":"Rue Du Marechal Foch 23 Fl\u00e9malle Li\u00e8ge 4400",
    "addr:housenumber":"23",
    "addr:postcode":"4400",
    "addr:street":"Rue Du Marechal Foch",
    "iso:country":"BE",
    "sg:address":"Rue Du Marechal Foch 23",
    "sg:city":"Fl\u00e9malle",
    "sg:classifiers":[
        {
            "category":"Real Estate",
            "subcategory":"Developer",
            "type":"Services"
        }
    ],
    "sg:phone":"+32 4 231 35 35",
    "sg:postcode":"4400",
    "sg:province":"Li\u00e8ge",
    "sg:tags":[
        "pipe",
        "lining",
        "coating",
        "plastic"
    ],
    "wof:name":"Tubemeuse Industries 'tmi' S.a.",
    "wof:placetype":"venue"
},
  "geometry": {"coordinates":[5.4724798203,50.5987014771],"type":"Point"}
}