{
  "type": "Feature",
  "properties": {
    "addr:full":"Rue Du Ruisseau 10 Namur (gelbress\u00e9e) Namur 5024",
    "addr:housenumber":"10",
    "addr:postcode":"5024",
    "addr:street":"Rue Du Ruisseau",
    "iso:country":"BE",
    "sg:address":"Rue Du Ruisseau 10",
    "sg:city":"Namur (gelbress\u00e9e)",
    "sg:classifiers":[
        {
            "category":"Banks & Credit Unions",
            "subcategory":"Investment Brokerage",
            "type":"Services"
        }
    ],
    "sg:phone":"+32 81 58 89 24",
    "sg:postcode":"5024",
    "sg:province":"Namur",
    "sg:tags":[
        "repair",
        "-",
        "installation",
        "sanitary",
        "article"
    ],
    "wof:name":"Merckx G",
    "wof:placetype":"venue"
},
  "geometry": {"coordinates":[4.9813652039,50.4942741394],"type":"Point"}
}