{
  "type": "Feature",
  "properties": {
    "iso:country":"BE",
    "sg:address":"4e-liniestraat 11",
    "sg:city":"Houthulst",
    "sg:orig_category":"Openbare veiligheid",
    "sg:phone":"+32 51 70 06 06",
    "sg:postcode":"8650",
    "sg:province":"West-Vlaanderen",
    "wof:name":"Federale Politie",
    "wof:placetype":"venue"
},
  "geometry": {"coordinates":[2.9521479607,50.9789466858],"type":"Point"}
}