{
  "type": "Feature",
  "properties": {
    "addr:full":"Jacob Lacopsstraat 29 Oudenaarde Oost-Vlaanderen 9700",
    "addr:housenumber":"29",
    "addr:postcode":"9700",
    "addr:street":"Lacopsstraat",
    "iso:country":"BE",
    "sg:address":"Jacob Lacopsstraat 29",
    "sg:city":"Oudenaarde",
    "sg:classifiers":[
        {
            "category":"Professional",
            "subcategory":"Art Services",
            "type":"Services"
        }
    ],
    "sg:phone":"+32 55 31 07 49",
    "sg:postcode":"9700",
    "sg:province":"Oost-Vlaanderen",
    "sg:tags":[
        "designer",
        "cr\u00e9ateurs"
    ],
    "wof:name":"Tony Van Achter",
    "wof:placetype":"venue"
},
  "geometry": {"coordinates":[3.6034998894,50.8490943909],"type":"Point"}
}