{
  "type": "Feature",
  "properties": {
    "addr:full":"Rue Hubert Goffin 167 Li\u00e8ge 1 (glain) Li\u00e8ge 4000",
    "addr:housenumber":"167;1",
    "addr:postcode":"4000",
    "addr:street":"Rue Hubert Goffin",
    "iso:country":"BE",
    "sg:address":"Rue Hubert Goffin 167",
    "sg:city":"Li\u00e8ge 1 (glain)",
    "sg:classifiers":[
        {
            "category":"Arena",
            "subcategory":"Sports Club",
            "type":"Entertainment"
        }
    ],
    "sg:phone":"+32 4 263 94 57",
    "sg:postcode":"4000",
    "sg:province":"Li\u00e8ge",
    "wof:name":"Tennis Club Baudouin",
    "wof:placetype":"venue"
},
  "geometry": {"coordinates":[5.5299239159,50.6494598389],"type":"Point"}
}