{
  "type": "Feature",
  "properties": {
    "addr:full":"Avenue Paul Hymans 83-85 Bruxelles (woluwe-saint-lambert) Bruxelles-Capitale 1200",
    "addr:housenumber":"83-85",
    "addr:postcode":"1200",
    "addr:street":"Avenue Paul Hymans",
    "iso:country":"BE",
    "sg:address":"Avenue Paul Hymans 83-85",
    "sg:city":"Bruxelles (woluwe-saint-lambert)",
    "sg:orig_category":"Non-Classified Establishments",
    "sg:phone":"+32 2 253 66 40",
    "sg:postcode":"1200",
    "sg:province":"Bruxelles-Capitale",
    "wof:name":"Delasia Food Impact",
    "wof:placetype":"venue"
},
  "geometry": {"coordinates":[4.4289269447,50.8466835022],"type":"Point"}
}