{
  "type": "Feature",
  "properties": {
    "iso:country":"BE",
    "sg:address":"Smidsestraat 26",
    "sg:city":"Gent",
    "sg:orig_category":"Artsen and specialisten",
    "sg:phone":"+32 9 329 30 86",
    "sg:postcode":"9000",
    "sg:province":"Oost-Vlaanderen",
    "wof:name":"Inge De Gussem",
    "wof:placetype":"venue"
},
  "geometry": {"coordinates":[3.7158529758,51.0400161743],"type":"Point"}
}