{
  "type": "Feature",
  "properties": {
    "addr:full":"Av. Charles Thielemans 93 Sint-pieters-woluwe/woluwe-saint-pierre Bruxelles-Capitale 1150",
    "addr:housenumber":"93",
    "addr:postcode":"1150",
    "addr:street":"Av. Charles Thielemans;/",
    "iso:country":"BE",
    "sg:address":"Av. Charles Thielemans 93",
    "sg:city":"Sint-pieters-woluwe/woluwe-saint-pierre",
    "sg:orig_category":"S\u00e9lection de personnel and placement",
    "sg:phone":"+32 2 773 05 64",
    "sg:postcode":"1150",
    "sg:province":"Bruxelles-Capitale",
    "wof:name":"A.l.e.",
    "wof:placetype":"venue"
},
  "geometry": {"coordinates":[4.4274148941,50.8367805481],"type":"Point"}
}