{
  "type": "Feature",
  "properties": {
    "iso:country":"BE",
    "sg:address":"Hoogdorp 28",
    "sg:city":"Alken",
    "sg:classifiers":[
        {
            "category":"Banks & Credit Unions",
            "subcategory":"Bank",
            "type":"Services"
        }
    ],
    "sg:phone":"+32 11 31 12 34",
    "sg:postcode":"3820",
    "wof:name":"Aslk-cger Bank",
    "wof:placetype":"venue"
},
  "geometry": {"coordinates":[5.3062729836,50.8755302429],"type":"Point"}
}