{
  "type": "Feature",
  "properties": {
    "iso:country":"BE",
    "sg:address":"Kroonstraat 40",
    "sg:city":"Lennik",
    "sg:orig_category":"Enseignement maternel and primaire",
    "sg:phone":"+32 2 532 43 87",
    "sg:postcode":"1750",
    "sg:province":"Vlaams-Brabant",
    "wof:name":"Vrije Basisschool",
    "wof:placetype":"venue"
},
  "geometry": {"coordinates":[4.1521382332,50.8054237366],"type":"Point"}
}