{
  "type": "Feature",
  "properties": {
    "iso:country":"BE",
    "sg:address":"Kasteeldreef 22",
    "sg:city":"Temse",
    "sg:classifiers":[
        {
            "category":"Bars & Pubs",
            "type":"Food & Drink"
        }
    ],
    "sg:phone":"+32 3 771 69 15",
    "sg:postcode":"9140",
    "sg:province":"Oost-Vlaanderen",
    "sg:tags":[
        "tavern"
    ],
    "wof:name":"Gasterie (de)",
    "wof:placetype":"venue"
},
  "geometry": {"coordinates":[4.2241201401,51.1249580383],"type":"Point"}
}