{
  "type": "Feature",
  "properties": {
    "addr:full":"Rue Calus 21 Waterloo Brabant Wallon 1410",
    "addr:housenumber":"21",
    "addr:postcode":"1410",
    "addr:street":"Rue Calus",
    "iso:country":"BE",
    "sg:address":"Rue Calus 21",
    "sg:city":"Waterloo",
    "sg:orig_category":"Passagiersvervoer over de weg Reisbureaus",
    "sg:phone":"+32 2 354 72 75",
    "sg:postcode":"1410",
    "sg:province":"Brabant Wallon",
    "wof:name":"City Liner",
    "wof:placetype":"venue"
},
  "geometry": {"coordinates":[4.4010028839,50.7018165588],"type":"Point"}
}