{
  "type": "Feature",
  "properties": {
    "addr:full":"Grote Baan 71 Ravels Antwerpen 2380",
    "addr:housenumber":"71",
    "addr:postcode":"2380",
    "addr:street":"Grote Baan",
    "iso:country":"BE",
    "sg:address":"Grote Baan 71",
    "sg:city":"Ravels",
    "sg:orig_category":"Diverse opleidingen and onderwijs",
    "sg:phone":"+32 14 65 40 72",
    "sg:postcode":"2380",
    "sg:province":"Antwerpen",
    "wof:name":"A-train",
    "wof:placetype":"venue"
},
  "geometry": {"coordinates":[4.9930529594,51.3673477173],"type":"Point"}
}