{
  "type": "Feature",
  "properties": {
    "iso:country":"BE",
    "sg:address":"Place De L'abbaye 9",
    "sg:city":"Saint-hubert",
    "sg:orig_category":"Rijscholen",
    "sg:phone":"+32 61 23 01 70",
    "sg:postcode":"6870",
    "sg:province":"Luxembourg",
    "wof:name":"Auto-ecole Ardennes",
    "wof:placetype":"venue"
},
  "geometry": {"coordinates":[5.3735971451,50.0261535645],"type":"Point"}
}