{
  "type": "Feature",
  "properties": {
    "addr:full":"Gillebroek 1 Borgloon Limburg 3840",
    "addr:housenumber":"1",
    "addr:postcode":"3840",
    "addr:street":"Gillebroek",
    "iso:country":"BE",
    "sg:address":"Gillebroek 1",
    "sg:city":"Borgloon",
    "sg:classifiers":[
        {
            "category":"Communications",
            "subcategory":"Newspaper",
            "type":"Services"
        }
    ],
    "sg:phone":"+32 12 74 12 62",
    "sg:postcode":"3840",
    "sg:province":"Limburg",
    "sg:tags":[
        "paper",
        "local",
        "free"
    ],
    "wof:name":"Zoeklicht",
    "wof:placetype":"venue"
},
  "geometry": {"coordinates":[5.3481397629,50.8026657104],"type":"Point"}
}