{
  "type": "Feature",
  "properties": {
    "iso:country":"BE",
    "sg:address":"Rue Biomont 26",
    "sg:city":"Herve (battice)",
    "sg:classifiers":[
        {
            "category":"Freight",
            "type":"Transportation"
        }
    ],
    "sg:phone":"+32 87 67 53 69",
    "sg:postcode":"4651",
    "sg:province":"Li\u00e8ge",
    "sg:tags":[
        "-",
        "transport"
    ],
    "wof:name":"Demonceau Transports Sa",
    "wof:placetype":"venue"
},
  "geometry": {"coordinates":[5.7978601456,50.6195793152],"type":"Point"}
}