{
  "type": "Feature",
  "properties": {
    "addr:full":"Velodromstraat 159 Liedekerke Vlaams-Brabant 1770",
    "addr:housenumber":"159",
    "addr:postcode":"1770",
    "addr:street":"Velodromstraat;Vlaams-Brabant",
    "iso:country":"BE",
    "sg:address":"Velodromstraat 159",
    "sg:city":"Liedekerke",
    "sg:orig_category":"Charpentes and couvertures",
    "sg:phone":"+32 53 66 20 10",
    "sg:postcode":"1770",
    "sg:province":"Vlaams-Brabant",
    "wof:name":"De Raes En Zonen",
    "wof:placetype":"venue"
},
  "geometry": {"coordinates":[4.0941381454,50.8668479919],"type":"Point"}
}