{
  "type": "Feature",
  "properties": {
    "addr:full":"Longueville 10 Durbuy Luxembourg 6941",
    "addr:housenumber":"10",
    "addr:postcode":"6941",
    "addr:street":"Longueville",
    "iso:country":"BE",
    "sg:address":"Longueville 10",
    "sg:city":"Durbuy",
    "sg:orig_category":"Eleveurs and marchands de porcs. Eleveurs de bovins",
    "sg:phone":"+32 86 21 10 01",
    "sg:postcode":"6941",
    "sg:province":"Luxembourg",
    "wof:name":"Ringlet & Steensels",
    "wof:placetype":"venue"
},
  "geometry": {"coordinates":[5.4581518173,50.3886985779],"type":"Point"}
}