{
  "type": "Feature",
  "properties": {
    "addr:full":"Hoogstraat 92 Zutendaal Limburg 3690",
    "addr:housenumber":"92",
    "addr:postcode":"3690",
    "addr:street":"Hoogstraat",
    "iso:country":"BE",
    "sg:address":"Hoogstraat 92",
    "sg:city":"Zutendaal",
    "sg:orig_category":"Mat\u00e9riaux de construction Gr",
    "sg:phone":"+32 89 61 12 90",
    "sg:postcode":"3690",
    "sg:province":"Limburg",
    "wof:name":"Kasseien Goyens",
    "wof:placetype":"venue"
},
  "geometry": {"coordinates":[5.5639619827,50.9379692078],"type":"Point"}
}