{
  "type": "Feature",
  "properties": {
    "addr:full":"Nieuwstraat 10 Merchtem Vlaams-Brabant 1785",
    "addr:housenumber":"10",
    "addr:postcode":"1785",
    "addr:street":"Nieuwstraat",
    "iso:country":"BE",
    "sg:address":"Nieuwstraat 10",
    "sg:city":"Merchtem",
    "sg:orig_category":"V\u00eatements pour b\u00e9b\u00e9s and enfants",
    "sg:phone":"+32 52 37 10 56",
    "sg:postcode":"1785",
    "sg:province":"Vlaams-Brabant",
    "wof:name":"Huis Siccard",
    "wof:placetype":"venue"
},
  "geometry": {"coordinates":[4.2276329994,50.981967926],"type":"Point"}
}