{
  "type": "Feature",
  "properties": {
    "addr:full":"Grand'place 9 Huy Li\u00e8ge 4500",
    "addr:housenumber":"9",
    "addr:postcode":"4500",
    "addr:street":"Grand'Place",
    "iso:country":"BE",
    "sg:address":"Grand'place 9",
    "sg:city":"Huy",
    "sg:classifiers":[
        {
            "category":"Shopping",
            "subcategory":"Clothing, Apparel, & Fashions",
            "type":"Retail Goods"
        }
    ],
    "sg:phone":"+32 85 25 31 15",
    "sg:postcode":"4500",
    "sg:province":"Li\u00e8ge",
    "sg:tags":[
        "boutique"
    ],
    "wof:name":"Parisiennes (les)",
    "wof:placetype":"venue"
},
  "geometry": {"coordinates":[5.2410359383,50.5180206299],"type":"Point"}
}