{
  "type": "Feature",
  "properties": {
    "iso:country":"BE",
    "sg:address":"Diestersteenweg 56",
    "sg:city":"Leopoldsburg",
    "sg:classifiers":[
        {
            "category":"Arena",
            "subcategory":"Sports Club",
            "type":"Entertainment"
        }
    ],
    "sg:phone":"+32 11 34 72 91",
    "sg:postcode":"3970",
    "sg:province":"Limburg",
    "sg:tags":[
        "de"
    ],
    "wof:name":"B.c. Leobad",
    "wof:placetype":"venue"
},
  "geometry": {"coordinates":[5.2516908646,51.1151428223],"type":"Point"}
}