{
  "type": "Feature",
  "properties": {
    "addr:full":"Avenue Albert I 64 Mons (hyon) Hainaut 7022",
    "addr:housenumber":"64",
    "addr:postcode":"7022",
    "addr:street":"Avenue Albert I",
    "iso:country":"BE",
    "sg:address":"Avenue Albert I 64",
    "sg:city":"Mons (hyon)",
    "sg:classifiers":[
        {
            "category":"Health Services",
            "subcategory":"Doctor",
            "type":"Services"
        }
    ],
    "sg:phone":"+32 65 84 37 07",
    "sg:postcode":"7022",
    "sg:province":"Hainaut",
    "sg:tags":[
        "medicinephysicians",
        "surgeon"
    ],
    "wof:name":"Cornelis Jean-philippe",
    "wof:placetype":"venue"
},
  "geometry": {"coordinates":[3.9520208836,50.4402503967],"type":"Point"}
}