{
  "type": "Feature",
  "properties": {
    "iso:country":"BE",
    "sg:address":"Rue De Savoie 32b5",
    "sg:city":"Sint-gillis/saint-gilles",
    "sg:orig_category":"Pharmaciens",
    "sg:phone":"+32 2 537 26 09",
    "sg:postcode":"1060",
    "sg:province":"Bruxelles-Capitale",
    "wof:name":"Anne-marie Dubois",
    "wof:placetype":"venue"
},
  "geometry": {"coordinates":[4.3467140198,50.8242263794],"type":"Point"}
}