{
  "type": "Feature",
  "properties": {
    "iso:country":"BE",
    "sg:address":"Antwerpsesteenweg 382",
    "sg:city":"Lier",
    "sg:orig_category":"Mat\u00e9riel de T\u00e9l\u00e9communication. Entretien and r\u00e9parations de voitures. D\u00e9taillants en pi\u00e8ces and acce",
    "sg:phone":"+32 3 480 40 79",
    "sg:postcode":"2500",
    "sg:province":"Antwerpen",
    "wof:name":"Jozef Fierens",
    "wof:placetype":"venue"
},
  "geometry": {"coordinates":[4.5350909233,51.1489372253],"type":"Point"}
}