{
  "type": "Feature",
  "properties": {
    "addr:full":"Sint-maartenplein 33 Hasselt (stevoort) Limburg 3512",
    "addr:housenumber":"33",
    "addr:postcode":"3512",
    "addr:street":"Sint-Maartenplein",
    "iso:country":"BE",
    "sg:address":"Sint-maartenplein 33",
    "sg:city":"Hasselt (stevoort)",
    "sg:classifiers":[
        {
            "category":"Personal",
            "subcategory":"Barber",
            "type":"Services"
        }
    ],
    "sg:phone":"+32 11 31 24 84",
    "sg:postcode":"3512",
    "sg:province":"Limburg",
    "sg:tags":[
        "gentleman",
        "salon",
        "-",
        "hairdressing"
    ],
    "wof:name":"Haarmode Boiten M",
    "wof:placetype":"venue"
},
  "geometry": {"coordinates":[5.2474050522,50.9174156189],"type":"Point"}
}