{
  "type": "Feature",
  "properties": {
    "addr:full":"Brugsken 140 Sint-niklaas Oost-Vlaanderen 9100",
    "addr:housenumber":"140",
    "addr:postcode":"9100",
    "addr:street":"Brugsken",
    "iso:country":"BE",
    "sg:address":"Brugsken 140",
    "sg:city":"Sint-niklaas",
    "sg:orig_category":"Slagers",
    "sg:phone":"+32 3 776 30 56",
    "sg:postcode":"9100",
    "sg:province":"Oost-Vlaanderen",
    "wof:name":"Freddy Van Royen",
    "wof:placetype":"venue"
},
  "geometry": {"coordinates":[4.1591529846,51.1587982178],"type":"Point"}
}