{
  "type": "Feature",
  "properties": {
    "addr:full":"Rue Emile Vandervelde 100 Nivelles Brabant Wallon 1400",
    "addr:housenumber":"100",
    "addr:postcode":"1400",
    "addr:street":"Rue Emile Vandervelde",
    "iso:country":"BE",
    "sg:address":"Rue Emile Vandervelde 100",
    "sg:city":"Nivelles",
    "sg:classifiers":[
        {
            "category":"Professional",
            "subcategory":"Lawyer & Legal Services",
            "type":"Services"
        }
    ],
    "sg:phone":"+32 67 84 14 40",
    "sg:postcode":"1400",
    "sg:province":"Brabant Wallon",
    "wof:name":"Planchat Sylvie",
    "wof:placetype":"venue"
},
  "geometry": {"coordinates":[4.3317952156,50.5943450928],"type":"Point"}
}