{
  "type": "Feature",
  "properties": {
    "addr:full":"Oude Haachtsesteenweg 72 Machelen Vlaams-Brabant 1831",
    "addr:housenumber":"72",
    "addr:postcode":"1831",
    "addr:street":"Oude Haachtsesteenweg",
    "iso:country":"BE",
    "sg:address":"Oude Haachtsesteenweg 72",
    "sg:city":"Machelen",
    "sg:orig_category":"Centres de relaxation and bien-\u00eatre. Instituts de beaut\u00e9",
    "sg:phone":"+32 2 721 46 48",
    "sg:postcode":"1831",
    "sg:province":"Vlaams-Brabant",
    "wof:name":"Schoonheidsinstituut Rosemarijn",
    "wof:placetype":"venue"
},
  "geometry": {"coordinates":[4.4346680641,50.89503479],"type":"Point"}
}