{
  "type": "Feature",
  "properties": {
    "iso:country":"BE",
    "sg:address":"Chemin Du Largepied 25",
    "sg:city":"Soignies (horrues)",
    "sg:classifiers":[
        {
            "category":"Manufacturing",
            "subcategory":"Metals",
            "type":"Manufacturing & Wholesale Goods"
        }
    ],
    "sg:phone":"+32 67 45 88 10",
    "sg:postcode":"7060",
    "sg:province":"Hainaut",
    "sg:tags":[
        "turning"
    ],
    "wof:name":"Noerens M",
    "wof:placetype":"venue"
},
  "geometry": {"coordinates":[4.0724000931,50.5779037476],"type":"Point"}
}