{
  "type": "Feature",
  "properties": {
    "iso:country":"BE",
    "sg:address":"Rue De Hamme-mille 63",
    "sg:city":"Grez-doiceau",
    "sg:orig_category":"Fotografen and fotostudio's",
    "sg:phone":"+32 10 86 10 64",
    "sg:postcode":"1390",
    "sg:province":"Brabant Wallon",
    "wof:name":"Rudi Maes",
    "wof:placetype":"venue"
},
  "geometry": {"coordinates":[4.6812109947,50.7844238281],"type":"Point"}
}