{
  "type": "Feature",
  "properties": {
    "addr:full":"Dorpsstr 51 Meeuwen 3578",
    "addr:housenumber":"51",
    "addr:postcode":"3578",
    "addr:street":"Dorpsstr",
    "iso:country":"BE",
    "sg:address":"Dorpsstr 51",
    "sg:city":"Meeuwen",
    "sg:classifiers":[
        {
            "category":"Banks & Credit Unions",
            "subcategory":"Bank",
            "type":"Services"
        }
    ],
    "sg:phone":"+32 11 43 69 24",
    "sg:postcode":"3578",
    "wof:name":"Gemeentekrediet",
    "wof:placetype":"venue"
},
  "geometry": {"coordinates":[5.0121030807,51.7282371521],"type":"Point"}
}