{
  "type": "Feature",
  "properties": {
    "addr:full":"Porte D'ogy 40 Lessines Hainaut 7860",
    "addr:housenumber":"40",
    "addr:postcode":"7860",
    "addr:street":"Hainaut",
    "iso:country":"BE",
    "sg:address":"Porte D'ogy 40",
    "sg:city":"Lessines",
    "sg:classifiers":[
        {
            "category":"Professional",
            "subcategory":"Engineering",
            "type":"Services"
        }
    ],
    "sg:phone":"+32 68 33 52 26",
    "sg:postcode":"7860",
    "sg:province":"Hainaut",
    "sg:tags":[
        "-"
    ],
    "wof:name":"Bosser & Grigolato Sprl",
    "wof:placetype":"venue"
},
  "geometry": {"coordinates":[3.8267600536,50.7127838135],"type":"Point"}
}