{
  "type": "Feature",
  "properties": {
    "iso:country":"BE",
    "sg:address":"Diestsestraat 18",
    "sg:city":"Aarschot",
    "sg:orig_category":"M\u00e9decins and sp\u00e9cialistes. Chaussures",
    "sg:phone":"+32 16 56 81 85",
    "sg:postcode":"3200",
    "sg:province":"Vlaams-Brabant",
    "wof:name":"Janssens",
    "wof:placetype":"venue"
},
  "geometry": {"coordinates":[4.836643219,50.9833641052],"type":"Point"}
}