{
  "type": "Feature",
  "properties": {
    "iso:country":"BE",
    "sg:address":"Tiensestraat 128",
    "sg:city":"Leuven",
    "sg:orig_category":"Rookartikelen",
    "sg:phone":"+32 16 22 85 62",
    "sg:postcode":"3000",
    "sg:province":"Vlaams-Brabant",
    "wof:name":"Rookartikelen Niclaes (havana House)",
    "wof:placetype":"venue"
},
  "geometry": {"coordinates":[4.7085871696,50.8754806519],"type":"Point"}
}