{
  "type": "Feature",
  "properties": {
    "addr:full":"Zoning Industriel Les Plenesses Andrimont Li\u00e8ge 4821",
    "addr:postcode":"4821",
    "addr:street":"Zoning Industriel",
    "iso:country":"BE",
    "sg:address":"Zoning Industriel Les Plenesses",
    "sg:city":"Andrimont",
    "sg:classifiers":[
        {
            "category":"Utilities",
            "subcategory":"Recycling",
            "type":"Services"
        }
    ],
    "sg:phone":"+32 87 35 03 00",
    "sg:postcode":"4821",
    "sg:province":"Li\u00e8ge",
    "wof:name":"Recygom Sa",
    "wof:placetype":"venue"
},
  "geometry": {"coordinates":[5.881280899,50.6143875122],"type":"Point"}
}