{
  "type": "Feature",
  "properties": {
    "iso:country":"BE",
    "sg:address":"Rue Warlomont 20",
    "sg:city":"Florenville",
    "sg:orig_category":"F\u00eates foraines, parcs d'attractions and de loisirs",
    "sg:phone":"+32 61 31 52 76",
    "sg:postcode":"6824",
    "sg:province":"Luxembourg",
    "wof:name":"Minitrein Caroline",
    "wof:placetype":"venue"
},
  "geometry": {"coordinates":[5.2619099617,49.7068786621],"type":"Point"}
}