{
  "type": "Feature",
  "properties": {
    "iso:country":"BE",
    "sg:address":"Stationsstraat 34",
    "sg:city":"As",
    "sg:orig_category":"Betonnen bouwelementen Fab Bouwmaterialen Gh HUISBRANDOLIE",
    "sg:phone":"+32 89 65 70 83",
    "sg:postcode":"3665",
    "sg:province":"Limburg",
    "wof:name":"Grondelaers",
    "wof:placetype":"venue"
},
  "geometry": {"coordinates":[5.5937070847,51.0061645508],"type":"Point"}
}