{
  "type": "Feature",
  "properties": {
    "addr:full":"Pater R. Vande Wouwerstr 32 Scherpenheuvel-zichem Vlaams-Brabant 3271",
    "addr:housenumber":"32",
    "addr:postcode":"3271",
    "addr:street":"Pater R. Vande Wouwerstr",
    "iso:country":"BE",
    "sg:address":"Pater R. Vande Wouwerstr 32",
    "sg:city":"Scherpenheuvel-zichem",
    "sg:orig_category":"RESTAURANTS: CAF\u00c9S",
    "sg:phone":"+32 13 78 15 35",
    "sg:postcode":"3271",
    "sg:province":"Vlaams-Brabant",
    "wof:name":"Tav. Floere Het Fluwijn",
    "wof:placetype":"venue"
},
  "geometry": {"coordinates":[4.9828920364,51.0005111694],"type":"Point"}
}