{
  "type": "Feature",
  "properties": {
    "addr:full":"Xavier De Cocklaan 66 Box 8 Sint-martens-latem (deurle) Oost-Vlaanderen 9831",
    "addr:housenumber":"66;8",
    "addr:postcode":"9831",
    "addr:street":"Xavier De Cocklaan;Box;Deurle",
    "iso:country":"BE",
    "sg:address":"Xavier De Cocklaan 66 Box 8",
    "sg:city":"Sint-martens-latem (deurle)",
    "sg:classifiers":[
        {
            "category":"Professional",
            "subcategory":"Computer Services",
            "type":"Services"
        }
    ],
    "sg:phone":"+32 9 280 88 11",
    "sg:postcode":"9831",
    "sg:province":"Oost-Vlaanderen",
    "sg:tags":[
        "-",
        "processing",
        "data",
        "software"
    ],
    "wof:name":"Connect It Nv",
    "wof:placetype":"venue"
},
  "geometry": {"coordinates":[3.6009049416,51.0073394775],"type":"Point"}
}