{
  "type": "Feature",
  "properties": {
    "addr:full":"Paternosterstraat 80ba Rotselaar Vlaams-Brabant 3110",
    "addr:housenumber":"80ba",
    "addr:postcode":"3110",
    "addr:street":"Paternosterstraat",
    "iso:country":"BE",
    "sg:address":"Paternosterstraat 80ba",
    "sg:city":"Rotselaar",
    "sg:orig_category":"Binnenhuisarchitecten",
    "sg:phone":"+32 16 58 50 25",
    "sg:postcode":"3110",
    "sg:province":"Vlaams-Brabant",
    "wof:name":"P. Muylle",
    "wof:placetype":"venue"
},
  "geometry": {"coordinates":[4.7558012009,50.9589080811],"type":"Point"}
}