{
  "type": "Feature",
  "properties": {
    "iso:country":"BE",
    "sg:address":"Avenue Du Domaine 181",
    "sg:city":"Bruxelles (forest)",
    "sg:classifiers":[
        {
            "category":"Social Services",
            "subcategory":"Job Training",
            "type":"Services"
        }
    ],
    "sg:phone":"+32 2 345 14 14",
    "sg:postcode":"1190",
    "sg:province":"Bruxelles-Capitale",
    "sg:tags":[
        "interpreter"
    ],
    "wof:name":"Van Hee J P",
    "wof:placetype":"venue"
},
  "geometry": {"coordinates":[4.3299679756,50.8126754761],"type":"Point"}
}