{
  "type": "Feature",
  "properties": {
    "iso:country":"BE",
    "sg:address":"Stee 12",
    "sg:city":"Lommel",
    "sg:orig_category":"Instituts de beaut\u00e9",
    "sg:phone":"+32 11 54 53 92",
    "sg:postcode":"3920",
    "sg:province":"Limburg",
    "wof:name":"Pedicure Rita",
    "wof:placetype":"venue"
},
  "geometry": {"coordinates":[5.300142765,51.2240753174],"type":"Point"}
}