{
  "type": "Feature",
  "properties": {
    "iso:country":"BE",
    "sg:address":"Chauss\u00e9e De Charleroi 421",
    "sg:city":"Gembloux-sur-orneau (corroy-le-ch\u00e2teau)",
    "sg:classifiers":[
        {
            "category":"Autos & Motor Vehicles",
            "subcategory":"Fuel & Gas Station",
            "type":"Retail Goods"
        }
    ],
    "sg:phone":"+32 81 63 42 15",
    "sg:postcode":"5032",
    "sg:province":"Namur",
    "wof:name":"Station De Corroy",
    "wof:placetype":"venue"
},
  "geometry": {"coordinates":[4.6415681839,50.5369224548],"type":"Point"}
}