{
  "type": "Feature",
  "properties": {
    "iso:country":"BE",
    "sg:address":"Ophovenstraat 150",
    "sg:city":"Meeuwen-gruitrode (gruitrode)",
    "sg:classifiers":[
        {
            "category":"Manufacturing",
            "subcategory":"Metals",
            "type":"Manufacturing & Wholesale Goods"
        }
    ],
    "sg:phone":"+32 89 85 54 75",
    "sg:postcode":"3670",
    "sg:province":"Limburg",
    "sg:tags":[
        "working"
    ],
    "wof:name":"Raemen Jos Metaalconstructie Bvba",
    "wof:placetype":"venue"
},
  "geometry": {"coordinates":[5.5348110199,51.0683021545],"type":"Point"}
}