{
  "type": "Feature",
  "properties": {
    "addr:full":"Chauss\u00c9e De Forest 207 Sint-gillis/saint-gilles Bruxelles-Capitale 1060",
    "addr:housenumber":"207",
    "addr:postcode":"1060",
    "addr:street":"Chausse\u0301E De Forest",
    "iso:country":"BE",
    "sg:address":"Chauss\u00c9e De Forest 207",
    "sg:city":"Sint-gillis/saint-gilles",
    "sg:classifiers":[
        {
            "category":"Cafe",
            "type":"Food & Drink"
        }
    ],
    "sg:phone":"+32 2 539 07 96",
    "sg:postcode":"1060",
    "sg:province":"Bruxelles-Capitale",
    "sg:tags":[
        "caf\u00e9s"
    ],
    "wof:name":"Caf\u00c9 Le Barril",
    "wof:placetype":"venue"
},
  "geometry": {"coordinates":[4.338394165,50.8265075684],"type":"Point"}
}