{
  "type": "Feature",
  "properties": {
    "iso:country":"BE",
    "sg:address":"Av.de Sel. De Moranville 50",
    "sg:city":"Sint-agatha-berchem/berchem-sainte-agathe",
    "sg:orig_category":"M\u00e9decins and sp\u00e9cialistes",
    "sg:phone":"+32 2 465 38 27",
    "sg:postcode":"1082",
    "sg:province":"Bruxelles-Capitale",
    "wof:name":"G\u00c9ry Lecuivre",
    "wof:placetype":"venue"
},
  "geometry": {"coordinates":[4.2917141914,50.867729187],"type":"Point"}
}