{
  "type": "Feature",
  "properties": {
    "addr:full":"Dorpsstraat 10 Zulte (machelen) Oost-Vlaanderen 9870",
    "addr:housenumber":"10",
    "addr:postcode":"9870",
    "addr:street":"Dorpsstraat",
    "iso:country":"BE",
    "sg:address":"Dorpsstraat 10",
    "sg:city":"Zulte (machelen)",
    "sg:classifiers":[
        {
            "category":"Health Services",
            "subcategory":"Health Practitioner",
            "type":"Services"
        }
    ],
    "sg:phone":"+32 9 386 96 25",
    "sg:postcode":"9870",
    "sg:province":"Oost-Vlaanderen",
    "sg:tags":[
        "physiotherapist"
    ],
    "wof:name":"Verhegge D",
    "wof:placetype":"venue"
},
  "geometry": {"coordinates":[3.493311882,50.955947876],"type":"Point"}
}