{
  "type": "Feature",
  "properties": {
    "addr:full":"Chauss\u00c9e D'alsemberg 834 Ukkel/uccle Bruxelles-Capitale 1180",
    "addr:housenumber":"834",
    "addr:postcode":"1180",
    "addr:street":"Chausse\u0301E D'Alsemberg;/",
    "iso:country":"BE",
    "sg:address":"Chauss\u00c9e D'alsemberg 834",
    "sg:city":"Ukkel/uccle",
    "sg:orig_category":"Entretien and r\u00e9parations de voitures",
    "sg:phone":"+32 2 376 01 18",
    "sg:postcode":"1180",
    "sg:province":"Bruxelles-Capitale",
    "wof:name":"Carrosserie Francky",
    "wof:placetype":"venue"
},
  "geometry": {"coordinates":[4.3360509872,50.7967262268],"type":"Point"}
}