{
  "type": "Feature",
  "properties": {
    "addr:full":"Burg. Vandenbogaerdelaan 10 Izegem West-Vlaanderen 8870",
    "addr:housenumber":"10",
    "addr:postcode":"8870",
    "addr:street":"Burg. Vandenbogaerdelaan",
    "iso:country":"BE",
    "sg:address":"Burg. Vandenbogaerdelaan 10",
    "sg:city":"Izegem",
    "sg:classifiers":[
        {
            "category":"Cafe",
            "type":"Food & Drink"
        }
    ],
    "sg:phone":"+32 51 31 25 92",
    "sg:postcode":"8870",
    "sg:province":"West-Vlaanderen",
    "sg:tags":[
        "caf\u00e9s"
    ],
    "wof:name":"Roland Deblaere",
    "wof:placetype":"venue"
},
  "geometry": {"coordinates":[3.2116250992,50.9157295227],"type":"Point"}
}