{
  "type": "Feature",
  "properties": {
    "addr:full":". Ingelmunster West-Vlaanderen 8770",
    "addr:postcode":"8770",
    "iso:country":"BE",
    "sg:address":".",
    "sg:city":"Ingelmunster",
    "sg:orig_category":"Apotheken",
    "sg:phone":"+32 900 10 500",
    "sg:postcode":"8770",
    "sg:province":"West-Vlaanderen",
    "wof:name":"Apothekers Van Wacht",
    "wof:placetype":"venue"
},
  "geometry": {"coordinates":[3.2560250759,50.9203109741],"type":"Point"}
}