{
  "type": "Feature",
  "properties": {
    "iso:country":"BE",
    "sg:address":"Chauss\u00c9e De Li\u00c8ge 422",
    "sg:city":"Grace-hollogne",
    "sg:orig_category":"Animaux domestiques and accessoires. Eleveurs d'animaux domestiques. Services pour animaux domestiqu",
    "sg:phone":"+32 4 239 09 55",
    "sg:postcode":"4460",
    "sg:province":"Li\u00e8ge",
    "wof:name":"Domaine Du Pery",
    "wof:placetype":"venue"
},
  "geometry": {"coordinates":[5.4935870171,50.6475563049],"type":"Point"}
}