{
  "type": "Feature",
  "properties": {
    "iso:country":"BE",
    "sg:address":"Markt 51",
    "sg:city":"Geraardsbergen",
    "sg:orig_category":"Banques and organismes de cr\u00e9dit",
    "sg:phone":"+32 54 41 20 43",
    "sg:postcode":"9500",
    "sg:province":"Oost-Vlaanderen",
    "wof:name":"Kbc",
    "wof:placetype":"venue"
},
  "geometry": {"coordinates":[3.8842890263,50.7715911865],"type":"Point"}
}