{
  "type": "Feature",
  "properties": {
    "iso:country":"BE",
    "sg:address":"Potyzestraat 24",
    "sg:city":"Ieper",
    "sg:orig_category":"Maisons de vacances",
    "sg:phone":"+32 57 20 73 38",
    "sg:postcode":"8970",
    "sg:province":"West-Vlaanderen",
    "wof:name":"D.m. Construct",
    "wof:placetype":"venue"
},
  "geometry": {"coordinates":[2.905313015,50.8634338379],"type":"Point"}
}