{
  "type": "Feature",
  "properties": {
    "addr:full":"Dendermondesteenweg 105 Wetteren Oost-Vlaanderen 9230",
    "addr:housenumber":"105",
    "addr:postcode":"9230",
    "addr:street":"Dendermondesteenweg",
    "iso:country":"BE",
    "sg:address":"Dendermondesteenweg 105",
    "sg:city":"Wetteren",
    "sg:orig_category":"Non-Classified Establishments",
    "sg:phone":"+32 9 369 93 23",
    "sg:postcode":"9230",
    "sg:province":"Oost-Vlaanderen",
    "wof:name":"De Coninck Yvan",
    "wof:placetype":"venue"
},
  "geometry": {"coordinates":[3.9181399345,51.011920929],"type":"Point"}
}