{
  "type": "Feature",
  "properties": {
    "iso:country":"BE",
    "sg:address":"Rue Grande 84",
    "sg:city":"Marche-en-famenne",
    "sg:classifiers":[
        {
            "category":"Insurance",
            "subcategory":"Insurance Agent",
            "type":"Services"
        }
    ],
    "sg:phone":"+32 84 31 24 40",
    "sg:postcode":"6900",
    "sg:province":"Luxembourg",
    "sg:tags":[
        "verzekeringsmakelaars",
        "expert"
    ],
    "wof:name":"J.bernard Courtier En Assurances Et Pr\u00cat",
    "wof:placetype":"venue"
},
  "geometry": {"coordinates":[5.3430151939,50.2273483276],"type":"Point"}
}