{
  "type": "Feature",
  "properties": {
    "addr:full":"Dendermondse Steenweg 26 Beervelde Oost-Vlaanderen 9080",
    "addr:housenumber":"26",
    "addr:postcode":"9080",
    "addr:street":"Steenweg;Oost-Vlaanderen",
    "iso:country":"BE",
    "sg:address":"Dendermondse Steenweg 26",
    "sg:city":"Beervelde",
    "sg:classifiers":[
        {
            "category":"Professional",
            "subcategory":"Engineering",
            "type":"Services"
        }
    ],
    "sg:phone":"+32 9 355 80 01",
    "sg:postcode":"9080",
    "sg:province":"Oost-Vlaanderen",
    "sg:tags":[
        "civil"
    ],
    "wof:name":"Abetec Studiebureau B.v.b.a.",
    "wof:placetype":"venue"
},
  "geometry": {"coordinates":[3.8539719582,51.0523757935],"type":"Point"}
}