{
  "type": "Feature",
  "properties": {
    "addr:full":"G. Gezellelaan 111 Puurs Antwerpen 2870",
    "addr:housenumber":"111",
    "addr:postcode":"2870",
    "addr:street":"G. Gezellelaan",
    "iso:country":"BE",
    "sg:address":"G. Gezellelaan 111",
    "sg:city":"Puurs",
    "sg:orig_category":"Benzinestations and brandstoffen",
    "sg:phone":"+32 3 899 14 83",
    "sg:postcode":"2870",
    "sg:province":"Antwerpen",
    "wof:name":"V.d.b. Mazout",
    "wof:placetype":"venue"
},
  "geometry": {"coordinates":[4.2895278931,51.0750465393],"type":"Point"}
}