{
  "type": "Feature",
  "properties": {
    "iso:country":"BE",
    "sg:address":"Rue L\u00c9on Colleaux 5",
    "sg:city":"Virton",
    "sg:orig_category":"Bioscopen",
    "sg:phone":"+32 63 57 14 24",
    "sg:postcode":"6752",
    "wof:name":"Nos Loisirs",
    "wof:placetype":"venue"
},
  "geometry": {"coordinates":[5.5347099304,49.5672607422],"type":"Point"}
}