{
  "type": "Feature",
  "properties": {
    "iso:country":"BE",
    "sg:address":"Nord Avenue V\u00e9sale 30 081408888",
    "sg:city":"Wavre",
    "sg:classifiers":[
        {
            "category":"Shopping",
            "subcategory":"Pharmacy",
            "type":"Retail Goods"
        }
    ],
    "sg:phone":"+32 10 22 83 34",
    "sg:postcode":"1300",
    "sg:province":"Brabant Wallon",
    "sg:tags":[
        "chemical",
        "pharmaceutical",
        "chemistry"
    ],
    "wof:name":"Agrostar",
    "wof:placetype":"venue"
},
  "geometry": {"coordinates":[4.5812587738,50.7359085083],"type":"Point"}
}