{
  "type": "Feature",
  "properties": {
    "iso:country":"BE",
    "sg:address":"Place Jules Galloy 82",
    "sg:city":"Wanze",
    "sg:classifiers":[
        {
            "category":"Insurance",
            "subcategory":"Insurance Agent",
            "type":"Services"
        }
    ],
    "sg:phone":"+32 85 21 33 15",
    "sg:postcode":"4520",
    "sg:province":"Li\u00e8ge",
    "sg:tags":[
        "verzekeringsmakelaars",
        "expert"
    ],
    "wof:name":"J. Delgaudine",
    "wof:placetype":"venue"
},
  "geometry": {"coordinates":[5.1833257675,50.5508766174],"type":"Point"}
}