{
  "type": "Feature",
  "properties": {
    "addr:full":"Rue Newton 1 Bruxelles Bruxelles-Capitale 1000",
    "addr:housenumber":"1",
    "addr:postcode":"1000",
    "addr:street":"Rue Newton",
    "iso:country":"BE",
    "sg:address":"Rue Newton 1",
    "sg:city":"Bruxelles",
    "sg:classifiers":[
        {
            "category":"Organizations",
            "subcategory":"Professional Association",
            "type":"Services"
        }
    ],
    "sg:phone":"+32 2 732 54 07",
    "sg:postcode":"1000",
    "sg:province":"Bruxelles-Capitale",
    "sg:tags":[
        "trade-union",
        "federation"
    ],
    "wof:name":"Comit\u00e9 De Liaison Dentaire",
    "wof:placetype":"venue"
},
  "geometry": {"coordinates":[4.3909888268,50.8468132019],"type":"Point"}
}