{
  "type": "Feature",
  "properties": {
    "addr:full":"Dampoortstraat 39 Gent Oost-Vlaanderen 9000",
    "addr:housenumber":"39",
    "addr:postcode":"9000",
    "addr:street":"Dampoortstraat;Oost-Vlaanderen",
    "iso:country":"BE",
    "sg:address":"Dampoortstraat 39",
    "sg:city":"Gent",
    "sg:classifiers":[
        {
            "category":"Retail",
            "subcategory":"Repair Shop",
            "type":"Services"
        }
    ],
    "sg:phone":"+32 9 225 20 03",
    "sg:postcode":"9000",
    "sg:province":"Oost-Vlaanderen",
    "sg:tags":[
        "-",
        "clothing",
        "alteration"
    ],
    "wof:name":"Vingerhoedje ('t)",
    "wof:placetype":"venue"
},
  "geometry": {"coordinates":[3.7349419594,51.056892395],"type":"Point"}
}