{
  "type": "Feature",
  "properties": {
    "addr:full":"Sentier Du Croquet 8 Boussu Hainaut 7300",
    "addr:housenumber":"8",
    "addr:postcode":"7300",
    "addr:street":"Sentier Du Croquet",
    "iso:country":"BE",
    "sg:address":"Sentier Du Croquet 8",
    "sg:city":"Boussu",
    "sg:classifiers":[
        {
            "category":"Real Estate",
            "subcategory":"Architect",
            "type":"Services"
        }
    ],
    "sg:phone":"+32 65 46 53 22",
    "sg:postcode":"7300",
    "sg:province":"Hainaut",
    "wof:name":"Joly L",
    "wof:placetype":"venue"
},
  "geometry": {"coordinates":[3.778249979,50.4100914001],"type":"Point"}
}