{
  "type": "Feature",
  "properties": {
    "addr:full":"Weversstraat 7 Asse Vlaams-Brabant 1730",
    "addr:housenumber":"7",
    "addr:postcode":"1730",
    "addr:street":"Weversstraat",
    "iso:country":"BE",
    "sg:address":"Weversstraat 7",
    "sg:city":"Asse",
    "sg:orig_category":"Epiceries",
    "sg:phone":"+32 2 452 64 86",
    "sg:postcode":"1730",
    "sg:province":"Vlaams-Brabant",
    "wof:name":"Supermarkt",
    "wof:placetype":"venue"
},
  "geometry": {"coordinates":[4.2024312019,50.9096717834],"type":"Point"}
}