{
  "type": "Feature",
  "properties": {
    "addr:full":"Rue Du Parc De La Tasseni\u00e8re 71 Dinant Namur 5500",
    "addr:housenumber":"71",
    "addr:postcode":"5500",
    "addr:street":"Rue Du Parc De La Tassenie\u0300Re",
    "iso:country":"BE",
    "sg:address":"Rue Du Parc De La Tasseni\u00e8re 71",
    "sg:city":"Dinant",
    "sg:classifiers":[
        {
            "category":"Building & Trades",
            "subcategory":"Plumbing",
            "type":"Services"
        }
    ],
    "sg:phone":"+32 475 45 53 03",
    "sg:postcode":"5500",
    "sg:province":"Namur",
    "sg:tags":[
        "contractor"
    ],
    "wof:name":"Bataille F",
    "wof:placetype":"venue"
},
  "geometry": {"coordinates":[4.8970808983,50.2357711792],"type":"Point"}
}