{
  "type": "Feature",
  "properties": {
    "addr:full":"Rue Bris\u00e9e 258 Mons (obourg) Hainaut 7034",
    "addr:housenumber":"258",
    "addr:postcode":"7034",
    "addr:street":"Rue Brise\u0301E",
    "iso:country":"BE",
    "sg:address":"Rue Bris\u00e9e 258",
    "sg:city":"Mons (obourg)",
    "sg:classifiers":[
        {
            "category":"Insurance",
            "subcategory":"Insurance Agent",
            "type":"Services"
        }
    ],
    "sg:phone":"+32 65 72 33 73",
    "sg:postcode":"7034",
    "sg:province":"Hainaut",
    "sg:tags":[
        "-",
        "representative"
    ],
    "wof:name":"Brichaux J",
    "wof:placetype":"venue"
},
  "geometry": {"coordinates":[4.0086159706,50.4765396118],"type":"Point"}
}