{
  "type": "Feature",
  "properties": {
    "addr:full":"Bogaerdstraat 14 Merchtem Vlaams-Brabant 1785",
    "addr:housenumber":"14",
    "addr:postcode":"1785",
    "addr:street":"Bogaerdstraat",
    "iso:country":"BE",
    "sg:address":"Bogaerdstraat 14",
    "sg:city":"Merchtem",
    "sg:orig_category":"Pain, p\u00e2tisseries and confiseries",
    "sg:phone":"+32 52 37 11 84",
    "sg:postcode":"1785",
    "sg:province":"Vlaams-Brabant",
    "wof:name":"J. De Vos",
    "wof:placetype":"venue"
},
  "geometry": {"coordinates":[4.2320480347,50.9577865601],"type":"Point"}
}