{
  "type": "Feature",
  "properties": {
    "iso:country":"BE",
    "sg:address":"Rue Henry Pastur 6",
    "sg:city":"Jodoigne (lathuy)",
    "sg:classifiers":[
        {
            "category":"Farming",
            "subcategory":"Livestock Farm",
            "type":"Manufacturing & Wholesale Goods"
        }
    ],
    "sg:phone":"+32 10 81 11 66",
    "sg:postcode":"1370",
    "sg:province":"Brabant Wallon",
    "sg:tags":[
        "breeding"
    ],
    "wof:name":"Wilmots L",
    "wof:placetype":"venue"
},
  "geometry": {"coordinates":[4.8254070282,50.7170448303],"type":"Point"}
}