{
  "type": "Feature",
  "properties": {
    "iso:country":"BE",
    "sg:address":"Henri D'hontstraat 29",
    "sg:city":"Tielt",
    "sg:orig_category":"Epiceries",
    "sg:phone":"+32 51 40 08 34",
    "sg:postcode":"8700",
    "sg:province":"West-Vlaanderen",
    "wof:name":"Supermarkt",
    "wof:placetype":"venue"
},
  "geometry": {"coordinates":[3.3384330273,51.0264434814],"type":"Point"}
}