{
  "type": "Feature",
  "properties": {
    "addr:full":"Waversesteenweg 1805 Oudergem/auderghem Bruxelles-Capitale 1160",
    "addr:housenumber":"1805",
    "addr:postcode":"1160",
    "addr:street":"Waversesteenweg;/",
    "iso:country":"BE",
    "sg:address":"Waversesteenweg 1805",
    "sg:city":"Oudergem/auderghem",
    "sg:orig_category":"HERSTELLING ELEKTRISCHE HUISHOUDAPPARATEN Huishoudapparaten, televisies and radio's Meubelzaken, won",
    "sg:phone":"+32 2 675 05 90",
    "sg:postcode":"1160",
    "sg:province":"Bruxelles-Capitale",
    "wof:name":"Mega",
    "wof:placetype":"venue"
},
  "geometry": {"coordinates":[4.4310641289,50.8158340454],"type":"Point"}
}