{
  "type": "Feature",
  "properties": {
    "addr:full":"Voie Sauvages M\u00cal\u00c9es 18 Blegny Li\u00e8ge 4671",
    "addr:housenumber":"18",
    "addr:postcode":"4671",
    "addr:street":"Voie Sauvages Me\u0302Le\u0301Es",
    "iso:country":"BE",
    "sg:address":"Voie Sauvages M\u00cal\u00c9es 18",
    "sg:city":"Blegny",
    "sg:orig_category":"Gespecialiseerde residenti\u00eble bouw Woningbouw",
    "sg:phone":"+32 4 362 28 53",
    "sg:postcode":"4671",
    "sg:province":"Li\u00e8ge",
    "wof:name":"Jacques Hamiot",
    "wof:placetype":"venue"
},
  "geometry": {"coordinates":[5.6746101379,50.6460151672],"type":"Point"}
}