{
  "type": "Feature",
  "properties": {
    "iso:country":"BE",
    "sg:address":"Morkhovenseweg 121",
    "sg:city":"Herentals",
    "sg:classifiers":[
        {
            "category":"Cafe",
            "type":"Food & Drink"
        }
    ],
    "sg:phone":"+32 14 26 37 18",
    "sg:postcode":"2200",
    "sg:province":"Antwerpen",
    "sg:tags":[
        "caf\u00e9s"
    ],
    "wof:name":"Ingrid Derbpven",
    "wof:placetype":"venue"
},
  "geometry": {"coordinates":[4.8269071579,51.1258049011],"type":"Point"}
}