{
  "type": "Feature",
  "properties": {
    "iso:country":"BE",
    "sg:address":"Guido Gezellelaan 52",
    "sg:city":"Roeselare",
    "sg:classifiers":[
        {
            "category":"Health Services",
            "subcategory":"Health Practitioner",
            "type":"Services"
        }
    ],
    "sg:phone":"+32 51 24 06 26",
    "sg:postcode":"8800",
    "sg:province":"West-Vlaanderen",
    "sg:tags":[
        "psychologist"
    ],
    "wof:name":"Keirsschieter B",
    "wof:placetype":"venue"
},
  "geometry": {"coordinates":[3.141644001,50.9399490356],"type":"Point"}
}