{
  "type": "Feature",
  "properties": {
    "iso:country":"BE",
    "sg:address":"Nauwstraat 124",
    "sg:city":"Sint-niklaas",
    "sg:orig_category":"Installatie van houten of kunststof schrijnwerk",
    "sg:phone":"+32 3 777 80 80",
    "sg:postcode":"9111",
    "sg:province":"Oost-Vlaanderen",
    "wof:name":"Dirk Van Lombergen",
    "wof:placetype":"venue"
},
  "geometry": {"coordinates":[4.1083102226,51.1753768921],"type":"Point"}
}