{
  "type": "Feature",
  "properties": {
    "addr:full":"Holleweg 24 Rotselaar Vlaams-Brabant 3110",
    "addr:housenumber":"24",
    "addr:postcode":"3110",
    "addr:street":"Holleweg",
    "iso:country":"BE",
    "sg:address":"Holleweg 24",
    "sg:city":"Rotselaar",
    "sg:classifiers":[
        {
            "category":"Professional",
            "subcategory":"Secretarial Services",
            "type":"Services"
        }
    ],
    "sg:phone":"+32 16 58 14 09",
    "sg:postcode":"3110",
    "sg:province":"Vlaams-Brabant",
    "sg:tags":[
        "firm"
    ],
    "wof:name":"Braet & Co Gcv",
    "wof:placetype":"venue"
},
  "geometry": {"coordinates":[4.7107920647,50.9508590698],"type":"Point"}
}