{
  "type": "Feature",
  "properties": {
    "addr:full":"Rue De La Glaci\u00e8re 31-35 Bruxelles (saint-gilles) Bruxelles-Capitale 1060",
    "addr:housenumber":"31-35",
    "addr:postcode":"1060",
    "addr:street":"Rue De La Glacie\u0300Re",
    "iso:country":"BE",
    "sg:address":"Rue De La Glaci\u00e8re 31-35",
    "sg:city":"Bruxelles (saint-gilles)",
    "sg:classifiers":[
        {
            "category":"Health Services",
            "subcategory":"Nursing And Care Facility",
            "type":"Services"
        }
    ],
    "sg:phone":"+32 2 537 76 66",
    "sg:postcode":"1060",
    "sg:province":"Bruxelles-Capitale",
    "sg:tags":[
        "home",
        "rest"
    ],
    "wof:name":"Heureux S\u00e9jour Asbl",
    "wof:placetype":"venue"
},
  "geometry": {"coordinates":[4.3509068489,50.8224639893],"type":"Point"}
}