{
  "type": "Feature",
  "properties": {
    "addr:full":"Meylandtlaan 105 Heusden-zolder Limburg 3550",
    "addr:housenumber":"105",
    "addr:postcode":"3550",
    "addr:street":"Meylandtlaan",
    "iso:country":"BE",
    "sg:address":"Meylandtlaan 105",
    "sg:city":"Heusden-zolder",
    "sg:classifiers":[
        {
            "category":"Personal",
            "subcategory":"Barber",
            "type":"Services"
        }
    ],
    "sg:phone":"+32 11 82 46 05",
    "sg:postcode":"3550",
    "sg:province":"Limburg",
    "sg:tags":[
        "gentleman",
        "salon",
        "-",
        "hairdressing"
    ],
    "wof:name":"Hairdesign Kathy",
    "wof:placetype":"venue"
},
  "geometry": {"coordinates":[5.2889618874,51.0161361694],"type":"Point"}
}