{
  "type": "Feature",
  "properties": {
    "iso:country":"BE",
    "sg:address":"Rue Grande 17",
    "sg:city":"Grace-hollogne",
    "sg:orig_category":"Dierenartsen",
    "sg:phone":"+32 4 234 38 88",
    "sg:postcode":"4460",
    "sg:province":"Li\u00e8ge",
    "wof:name":"Ann-charlotte Palmgren",
    "wof:placetype":"venue"
},
  "geometry": {"coordinates":[5.4759821892,50.6332893372],"type":"Point"}
}