{
  "type": "Feature",
  "properties": {
    "iso:country":"BE",
    "sg:address":"Vestenstraat 19",
    "sg:city":"Vilvoorde",
    "sg:orig_category":"Newspapers, magazines, periodicals - Distribution",
    "sg:phone":"+32 2 252 66 30",
    "sg:postcode":"1800",
    "sg:province":"Vlaams-Brabant",
    "wof:name":"'t Vestje",
    "wof:placetype":"venue"
},
  "geometry": {"coordinates":[4.4210867882,50.9320907593],"type":"Point"}
}