{
  "type": "Feature",
  "properties": {
    "iso:country":"BE",
    "sg:address":"Rue Joseph-renquin 37",
    "sg:city":"Bastogne",
    "sg:orig_category":"Huishoudapparaten, televisies and radio's",
    "sg:phone":"+32 61 21 14 32",
    "sg:postcode":"6600",
    "sg:province":"Luxembourg",
    "wof:name":"Maison Baguette",
    "wof:placetype":"venue"
},
  "geometry": {"coordinates":[5.7158379555,49.9993934631],"type":"Point"}
}