{
  "type": "Feature",
  "properties": {
    "addr:full":"Gentstraat 73 Oudenaarde Oost-Vlaanderen 9700",
    "addr:housenumber":"73",
    "addr:postcode":"9700",
    "addr:street":"Gentstraat",
    "iso:country":"BE",
    "sg:address":"Gentstraat 73",
    "sg:city":"Oudenaarde",
    "sg:orig_category":"Fitnesscentra",
    "sg:phone":"+32 55 31 93 69",
    "sg:postcode":"9700",
    "sg:province":"Oost-Vlaanderen",
    "wof:name":"Fit Studio",
    "wof:placetype":"venue"
},
  "geometry": {"coordinates":[3.599891901,50.8524742126],"type":"Point"}
}