{
  "type": "Feature",
  "properties": {
    "addr:full":"Kogelstraat 7 Brussel/bruxelles Bruxelles-Capitale 1000",
    "addr:housenumber":"7",
    "addr:postcode":"1000",
    "addr:street":"Kogelstraat;/",
    "iso:country":"BE",
    "sg:address":"Kogelstraat 7",
    "sg:city":"Brussel/bruxelles",
    "sg:orig_category":"Zalen voor culturele evenementen",
    "sg:phone":"+32 2 512 85 42",
    "sg:postcode":"1000",
    "sg:province":"Bruxelles-Capitale",
    "wof:name":"Bullet",
    "wof:placetype":"venue"
},
  "geometry": {"coordinates":[4.3447890282,50.8488044739],"type":"Point"}
}