{
  "type": "Feature",
  "properties": {
    "iso:country":"BE",
    "sg:address":"Lippenslaan 60",
    "sg:city":"Knokke-heist (knokke)",
    "sg:classifiers":[
        {
            "category":"Bakery",
            "type":"Food & Drink"
        }
    ],
    "sg:phone":"+32 50 60 27 56",
    "sg:postcode":"8300",
    "sg:province":"West-Vlaanderen",
    "sg:tags":[
        "confectioner",
        "baker"
    ],
    "wof:name":"Vereecke Bart",
    "wof:placetype":"venue"
},
  "geometry": {"coordinates":[3.2879340649,51.3431053162],"type":"Point"}
}