{
  "type": "Feature",
  "properties": {
    "iso:country":"BE",
    "sg:address":"Rue De Cognel\u00e9e 32",
    "sg:city":"La Bruy\u00e8re (warisoulx)",
    "sg:classifiers":[
        {
            "category":"Health Services",
            "subcategory":"Nursing And Care Facility",
            "type":"Services"
        }
    ],
    "sg:phone":"+32 81 20 00 79",
    "sg:postcode":"5080",
    "sg:province":"Namur",
    "sg:tags":[
        "home"
    ],
    "wof:name":"Lievin L",
    "wof:placetype":"venue"
},
  "geometry": {"coordinates":[4.8657960892,50.5362052917],"type":"Point"}
}