{
  "type": "Feature",
  "properties": {
    "iso:country":"BE",
    "sg:address":"Rue Du Midi 81",
    "sg:city":"Mouscron",
    "sg:classifiers":[
        {
            "category":"Building & Trades",
            "subcategory":"Construction",
            "type":"Services"
        }
    ],
    "sg:phone":"+32 56 34 18 36",
    "sg:postcode":"7700",
    "sg:province":"Hainaut",
    "sg:tags":[
        "carpenter"
    ],
    "wof:name":"Pg Construction",
    "wof:placetype":"venue"
},
  "geometry": {"coordinates":[3.2158069611,50.7388458252],"type":"Point"}
}