{
  "type": "Feature",
  "properties": {
    "addr:full":"Clos Du Bois Du Cheval 7 Mouscron Hainaut 7700",
    "addr:housenumber":"7",
    "addr:postcode":"7700",
    "addr:street":"Clos Du Bois Du Cheval",
    "iso:country":"BE",
    "sg:address":"Clos Du Bois Du Cheval 7",
    "sg:city":"Mouscron",
    "sg:classifiers":[
        {
            "category":"Health Services",
            "subcategory":"Health Practitioner",
            "type":"Services"
        }
    ],
    "sg:phone":"+32 56 33 12 24",
    "sg:postcode":"7700",
    "sg:province":"Hainaut",
    "sg:tags":[
        "osteopath"
    ],
    "wof:name":"Delmotte Jacques",
    "wof:placetype":"venue"
},
  "geometry": {"coordinates":[3.2103559971,50.7600784302],"type":"Point"}
}