{
  "type": "Feature",
  "properties": {
    "iso:country":"BE",
    "sg:address":"Stephensonplein 9",
    "sg:city":"Schaarbeek/schaerbeek",
    "sg:orig_category":"Artsen and specialisten",
    "sg:phone":"+32 2 215 45 06",
    "sg:postcode":"1030",
    "sg:province":"Bruxelles-Capitale",
    "wof:name":"Melanie Ntahorutaba",
    "wof:placetype":"venue"
},
  "geometry": {"coordinates":[4.3699669838,50.8707084656],"type":"Point"}
}