{
  "type": "Feature",
  "properties": {
    "addr:full":"Zeelaan 3 Eeklo Oost-Vlaanderen 9900",
    "addr:housenumber":"3",
    "addr:postcode":"9900",
    "addr:street":"Zeelaan",
    "iso:country":"BE",
    "sg:address":"Zeelaan 3",
    "sg:city":"Eeklo",
    "sg:classifiers":[
        {
            "category":"Home & Garden",
            "subcategory":"Kitchen Supply",
            "type":"Retail Goods"
        }
    ],
    "sg:phone":"+32 9 377 87 22",
    "sg:postcode":"9900",
    "sg:province":"Oost-Vlaanderen",
    "sg:tags":[
        "installation"
    ],
    "wof:name":"Dewi Interieur Bvba",
    "wof:placetype":"venue"
},
  "geometry": {"coordinates":[3.5259480476,51.1996192932],"type":"Point"}
}