{
  "type": "Feature",
  "properties": {
    "addr:full":"Rue De La Magr\u00c9e 60 Anthisnes Li\u00e8ge 4163",
    "addr:housenumber":"60",
    "addr:postcode":"4163",
    "addr:street":"Rue De La Magre\u0301E",
    "iso:country":"BE",
    "sg:address":"Rue De La Magr\u00c9e 60",
    "sg:city":"Anthisnes",
    "sg:orig_category":"M\u00e9decins and sp\u00e9cialistes",
    "sg:phone":"+32 4 383 70 41",
    "sg:postcode":"4163",
    "sg:province":"Li\u00e8ge",
    "wof:name":"N. Ganser",
    "wof:placetype":"venue"
},
  "geometry": {"coordinates":[5.467279911,50.4938583374],"type":"Point"}
}