{
  "type": "Feature",
  "properties": {
    "addr:full":"Chauss\u00e9e De W\u00e9gimont 136 Soumagne (ayeneux) Li\u00e8ge 4630",
    "addr:housenumber":"136",
    "addr:postcode":"4630",
    "addr:street":"Chausse\u0301E De We\u0301Gimont",
    "iso:country":"BE",
    "sg:address":"Chauss\u00e9e De W\u00e9gimont 136",
    "sg:city":"Soumagne (ayeneux)",
    "sg:classifiers":[
        {
            "category":"Manufacturing",
            "subcategory":"Tools & Machinery",
            "type":"Manufacturing & Wholesale Goods"
        }
    ],
    "sg:phone":"+32 4 377 13 65",
    "sg:postcode":"4630",
    "sg:province":"Li\u00e8ge",
    "sg:tags":[
        "builder"
    ],
    "wof:name":"Atelier Mossoux Fr\u00e8res Sprl",
    "wof:placetype":"venue"
},
  "geometry": {"coordinates":[5.7390799522,50.6112098694],"type":"Point"}
}