{
  "type": "Feature",
  "properties": {
    "addr:full":"Draaiboom 102 Oud-turnhout Antwerpen 2360",
    "addr:housenumber":"102",
    "addr:postcode":"2360",
    "addr:street":"Draaiboom",
    "iso:country":"BE",
    "sg:address":"Draaiboom 102",
    "sg:city":"Oud-turnhout",
    "sg:orig_category":"Installatie van houten of kunststof schrijnwerk Plaatsen van vloer- and muurbekleding Woningbouw",
    "sg:phone":"+32 14 45 17 76",
    "sg:postcode":"2360",
    "sg:province":"Antwerpen",
    "wof:name":"Victor Diels",
    "wof:placetype":"venue"
},
  "geometry": {"coordinates":[4.9989161491,51.3212127686],"type":"Point"}
}