{
  "type": "Feature",
  "properties": {
    "addr:full":"Chemin De Walcourt 11 Thuin Hainaut 6530",
    "addr:housenumber":"11",
    "addr:postcode":"6530",
    "addr:street":"Chemin De Walcourt",
    "iso:country":"BE",
    "sg:address":"Chemin De Walcourt 11",
    "sg:city":"Thuin",
    "sg:orig_category":"Tuinen",
    "sg:phone":"+32 71 59 29 37",
    "sg:postcode":"6530",
    "sg:province":"Hainaut",
    "wof:name":"Dusquesne Pierre",
    "wof:placetype":"venue"
},
  "geometry": {"coordinates":[4.2805080414,50.3305854797],"type":"Point"}
}