{
  "type": "Feature",
  "properties": {
    "addr:full":"Avenue Louise 199 Box 114 Bruxelles (ixelles) Bruxelles-Capitale 1050",
    "addr:housenumber":"199",
    "addr:postcode":"1050",
    "addr:street":"Avenue Louise;Box 114",
    "iso:country":"BE",
    "sg:address":"Avenue Louise 199 Box 114",
    "sg:city":"Bruxelles (ixelles)",
    "sg:classifiers":[
        {
            "category":"Professional",
            "subcategory":"Art Services",
            "type":"Services"
        }
    ],
    "sg:phone":"+32 2 646 62 57",
    "sg:postcode":"1050",
    "sg:province":"Bruxelles-Capitale",
    "sg:tags":[
        "photographer"
    ],
    "wof:name":"Cornu W",
    "wof:placetype":"venue"
},
  "geometry": {"coordinates":[4.3637619019,50.8268890381],"type":"Point"}
}