{
  "type": "Feature",
  "properties": {
    "iso:country":"BE",
    "sg:address":"Bergkapelstraat 55",
    "sg:city":"Londerzeel",
    "sg:classifiers":[
        {
            "category":"Bars & Pubs",
            "type":"Food & Drink"
        }
    ],
    "sg:phone":"+32 52 30 13 32",
    "sg:postcode":"1840",
    "sg:province":"Vlaams-Brabant",
    "wof:name":"Bergbos",
    "wof:placetype":"venue"
},
  "geometry": {"coordinates":[4.3225278854,51.0069618225],"type":"Point"}
}