{
  "type": "Feature",
  "properties": {
    "addr:full":"Hagelkruis 2 Wuustwezel Antwerpen 2990",
    "addr:housenumber":"2",
    "addr:postcode":"2990",
    "addr:street":"Hagelkruis",
    "iso:country":"BE",
    "sg:address":"Hagelkruis 2",
    "sg:city":"Wuustwezel",
    "sg:classifiers":[
        {
            "category":"Building & Trades",
            "subcategory":"Construction",
            "type":"Services"
        }
    ],
    "sg:phone":"+32 3 669 85 74",
    "sg:postcode":"2990",
    "sg:province":"Antwerpen",
    "sg:tags":[
        "carpenter"
    ],
    "wof:name":"Jalu Bvba",
    "wof:placetype":"venue"
},
  "geometry": {"coordinates":[4.5920090675,51.3899421692],"type":"Point"}
}