{
  "type": "Feature",
  "properties": {
    "iso:country":"BE",
    "sg:address":"Hoogstraat 43a",
    "sg:city":"Hamme",
    "sg:classifiers":[
        {
            "category":"Wholesale",
            "subcategory":"Plants",
            "type":"Manufacturing & Wholesale Goods"
        }
    ],
    "sg:phone":"+32 52 25 65 90",
    "sg:postcode":"9220",
    "sg:province":"Oost-Vlaanderen",
    "sg:tags":[
        "decoration",
        "flower",
        "-"
    ],
    "wof:name":"Flower Factory",
    "wof:placetype":"venue"
},
  "geometry": {"coordinates":[4.130420208,51.0981483459],"type":"Point"}
}