{
  "type": "Feature",
  "properties": {
    "addr:full":"Kempischveldweg 20 Schilde Antwerpen 2970",
    "addr:housenumber":"20",
    "addr:postcode":"2970",
    "addr:street":"Kempischveldweg",
    "iso:country":"BE",
    "sg:address":"Kempischveldweg 20",
    "sg:city":"Schilde",
    "sg:classifiers":[
        {
            "category":"Professional",
            "subcategory":"Accounting & Tax Preparation",
            "type":"Services"
        }
    ],
    "sg:phone":"+32 3 383 27 17",
    "sg:postcode":"2970",
    "sg:province":"Antwerpen",
    "sg:tags":[
        "bookkeeper"
    ],
    "wof:name":"De Cuyper M",
    "wof:placetype":"venue"
},
  "geometry": {"coordinates":[4.5817480087,51.2293205261],"type":"Point"}
}