{
  "type": "Feature",
  "properties": {
    "addr:full":"Rue Du Motel 7 Eghez\u00e9e (aische-en-refail) Namur 5310",
    "addr:postcode":"5310",
    "addr:street":"Rue Du",
    "iso:country":"BE",
    "sg:address":"Rue Du Motel 7",
    "sg:city":"Eghez\u00e9e (aische-en-refail)",
    "sg:classifiers":[
        {
            "category":"Autos & Motor Vehicles",
            "subcategory":"Fuel & Gas Station",
            "type":"Retail Goods"
        }
    ],
    "sg:phone":"+32 81 64 03 51",
    "sg:postcode":"5310",
    "sg:province":"Namur",
    "wof:name":"Q8 Stations-services",
    "wof:placetype":"venue"
},
  "geometry": {"coordinates":[4.8110890388,50.6029701233],"type":"Point"}
}