{
  "type": "Feature",
  "properties": {
    "iso:country":"BE",
    "sg:address":"Oostdorpstraat 143",
    "sg:city":"Erpe-mere",
    "sg:orig_category":"Eclairage et \u00e9quipements du foyer",
    "sg:phone":"+32 53 83 85 79",
    "sg:postcode":"9420",
    "sg:province":"Oost-Vlaanderen",
    "wof:name":"Lina Lighting",
    "wof:placetype":"venue"
},
  "geometry": {"coordinates":[3.9757111073,50.9097290039],"type":"Point"}
}