{
  "type": "Feature",
  "properties": {
    "addr:full":"Rue De La Poste 50 Eghez\u00e9e (leuze) Namur 5310",
    "addr:housenumber":"50",
    "addr:postcode":"5310",
    "addr:street":"Rue De La Poste",
    "iso:country":"BE",
    "sg:address":"Rue De La Poste 50",
    "sg:city":"Eghez\u00e9e (leuze)",
    "sg:classifiers":[
        {
            "category":"Health Services",
            "subcategory":"Doctor",
            "type":"Services"
        }
    ],
    "sg:phone":"+32 81 51 14 62",
    "sg:postcode":"5310",
    "sg:province":"Namur",
    "sg:tags":[
        "psychotherapist",
        "psychoanalyst"
    ],
    "wof:name":"Genevi\u00e8ve Laloux",
    "wof:placetype":"venue"
},
  "geometry": {"coordinates":[4.9064240456,50.5614204407],"type":"Point"}
}