{
  "type": "Feature",
  "properties": {
    "addr:full":"Quai Andre\u00ef Sakharov 30 Tournai Hainaut 7500",
    "addr:housenumber":"30",
    "addr:postcode":"7500",
    "addr:street":"Quai Andrei\u0308 Sakharov",
    "iso:country":"BE",
    "sg:address":"Quai Andre\u00ef Sakharov 30",
    "sg:city":"Tournai",
    "sg:classifiers":[
        {
            "category":"Health Services",
            "subcategory":"Hospital",
            "type":"Services"
        }
    ],
    "sg:phone":"+32 69 22 73 81",
    "sg:postcode":"7500",
    "sg:province":"Hainaut",
    "wof:name":"Semesotra Asbl",
    "wof:placetype":"venue"
},
  "geometry": {"coordinates":[3.3850409985,50.6128196716],"type":"Point"}
}