{
  "type": "Feature",
  "properties": {
    "addr:full":"Harmoniestraat 36 Turnhout Antwerpen 2300",
    "addr:housenumber":"36",
    "addr:postcode":"2300",
    "addr:street":"Harmoniestraat",
    "iso:country":"BE",
    "sg:address":"Harmoniestraat 36",
    "sg:city":"Turnhout",
    "sg:orig_category":"Avocats and conseillers juridiques",
    "sg:phone":"+32 14 44 80 80",
    "sg:postcode":"2300",
    "sg:province":"Antwerpen",
    "wof:name":"Van Cauwenbergh",
    "wof:placetype":"venue"
},
  "geometry": {"coordinates":[4.9338507652,51.3253669739],"type":"Point"}
}