{
  "type": "Feature",
  "properties": {
    "addr:full":"Bankstraat 60 Kortenberg (everberg) Vlaams-Brabant 3078",
    "addr:housenumber":"60",
    "addr:postcode":"3078",
    "addr:street":"Bankstraat",
    "iso:country":"BE",
    "sg:address":"Bankstraat 60",
    "sg:city":"Kortenberg (everberg)",
    "sg:classifiers":[
        {
            "category":"Banks & Credit Unions",
            "subcategory":"Investment Brokerage",
            "type":"Services"
        }
    ],
    "sg:phone":"+32 2 757 00 04",
    "sg:postcode":"3078",
    "sg:province":"Vlaams-Brabant",
    "sg:tags":[
        "repair",
        "-",
        "installation",
        "sanitary",
        "article"
    ],
    "wof:name":"Instalco",
    "wof:placetype":"venue"
},
  "geometry": {"coordinates":[4.5639600754,50.8801727295],"type":"Point"}
}