{
  "type": "Feature",
  "properties": {
    "addr:full":"Biezenstraat 42ba Erpe-mere Oost-Vlaanderen 9420",
    "addr:housenumber":"42ba",
    "addr:postcode":"9420",
    "addr:street":"Biezenstraat",
    "iso:country":"BE",
    "sg:address":"Biezenstraat 42ba",
    "sg:city":"Erpe-mere",
    "sg:orig_category":"Installation de menuiserie en bois and plastique",
    "sg:phone":"+32 53 63 10 41",
    "sg:postcode":"9420",
    "sg:province":"Oost-Vlaanderen",
    "wof:name":"Karel De Loy Hendrickx",
    "wof:placetype":"venue"
},
  "geometry": {"coordinates":[3.9181399345,50.9087944031],"type":"Point"}
}