{
  "type": "Feature",
  "properties": {
    "addr:full":"Avenue De La Wallonie 0 La Louviere Hainaut 7100",
    "addr:housenumber":"0",
    "addr:postcode":"7100",
    "addr:street":"Avenue De La Wallonie",
    "iso:country":"BE",
    "sg:address":"Avenue De La Wallonie 0",
    "sg:city":"La Louviere",
    "sg:orig_category":"V\u00eatements pour b\u00e9b\u00e9s and enfants. V\u00eatements pour Dames. V\u00eatements pour Hommes",
    "sg:phone":"+32 64 84 98 15",
    "sg:postcode":"7100",
    "sg:province":"Hainaut",
    "wof:name":"Superconfex",
    "wof:placetype":"venue"
},
  "geometry": {"coordinates":[4.2023248672,50.4887733459],"type":"Point"}
}