{
  "type": "Feature",
  "properties": {
    "addr:full":"Rue De Louvranges 60 Chaumont-gistoux Brabant Wallon 1325",
    "addr:housenumber":"60",
    "addr:postcode":"1325",
    "addr:street":"Rue De Louvranges",
    "iso:country":"BE",
    "sg:address":"Rue De Louvranges 60",
    "sg:city":"Chaumont-gistoux",
    "sg:orig_category":"Artsen and specialisten",
    "sg:phone":"+32 10 24 28 00",
    "sg:postcode":"1325",
    "sg:province":"Brabant Wallon",
    "wof:name":"E. Poncelet",
    "wof:placetype":"venue"
},
  "geometry": {"coordinates":[4.6402921677,50.6959037781],"type":"Point"}
}