{
  "type": "Feature",
  "properties": {
    "iso:country":"BE",
    "sg:address":"Rietorchisstraat 8b",
    "sg:city":"Gent",
    "sg:orig_category":"Agences immobili\u00e8res. Assurances",
    "sg:phone":"+32 9 356 94 53",
    "sg:postcode":"9041",
    "sg:province":"Oost-Vlaanderen",
    "wof:name":"Service-& Advieskantoor",
    "wof:placetype":"venue"
},
  "geometry": {"coordinates":[3.7946300507,51.0756721497],"type":"Point"}
}