{
  "type": "Feature",
  "properties": {
    "iso:country":"BE",
    "sg:address":"Rue Fran\u00c7ois Cloes 9",
    "sg:city":"Saint-nicolas",
    "sg:orig_category":"Boucheries",
    "sg:phone":"+32 4 263 95 12",
    "sg:postcode":"4420",
    "sg:province":"Li\u00e8ge",
    "wof:name":"Caprasco",
    "wof:placetype":"venue"
},
  "geometry": {"coordinates":[5.5198140144,50.6380691528],"type":"Point"}
}