{
  "type": "Feature",
  "properties": {
    "addr:full":"Mechelseweg 189 Kapelle-op-den-bos Vlaams-Brabant 1880",
    "addr:housenumber":"189",
    "addr:postcode":"1880",
    "addr:street":"Mechelseweg",
    "iso:country":"BE",
    "sg:address":"Mechelseweg 189",
    "sg:city":"Kapelle-op-den-bos",
    "sg:classifiers":[
        {
            "category":"Real Estate",
            "subcategory":"Architect",
            "type":"Services"
        }
    ],
    "sg:phone":"+32 15 71 44 74",
    "sg:postcode":"1880",
    "sg:province":"Vlaams-Brabant",
    "wof:name":"Palmen B",
    "wof:placetype":"venue"
},
  "geometry": {"coordinates":[4.3578867912,51.0130195618],"type":"Point"}
}