{
  "type": "Feature",
  "properties": {
    "addr:full":"Rue Bonry 136 Plainevaux Li\u00e8ge 4122",
    "addr:housenumber":"136",
    "addr:postcode":"4122",
    "addr:street":"Rue Bonry",
    "iso:country":"BE",
    "sg:address":"Rue Bonry 136",
    "sg:city":"Plainevaux",
    "sg:classifiers":[
        {
            "category":"Professional",
            "subcategory":"Art Services",
            "type":"Services"
        }
    ],
    "sg:phone":"+32 4 372 03 87",
    "sg:postcode":"4122",
    "sg:province":"Li\u00e8ge",
    "sg:tags":[
        "stand",
        "construction",
        "exhibition",
        "fair",
        "trade"
    ],
    "wof:name":"Scott A. Milton S.a.",
    "wof:placetype":"venue"
},
  "geometry": {"coordinates":[5.5223817825,50.5458335876],"type":"Point"}
}