{
  "type": "Feature",
  "properties": {
    "iso:country":"BE",
    "sg:address":"Oude Bruggestraat 55",
    "sg:city":"Wingene",
    "sg:orig_category":"G\u00e9om\u00e8tres. Agences immobili\u00e8res",
    "sg:phone":"+32 51 65 63 61",
    "sg:postcode":"8750",
    "sg:province":"West-Vlaanderen",
    "wof:name":"Bureau Verkest",
    "wof:placetype":"venue"
},
  "geometry": {"coordinates":[3.2741639614,51.0584640503],"type":"Point"}
}