{
  "type": "Feature",
  "properties": {
    "addr:full":"Rue Late 43 Musson Luxembourg 6750",
    "addr:housenumber":"43",
    "addr:postcode":"6750",
    "addr:street":"Rue Late",
    "iso:country":"BE",
    "sg:address":"Rue Late 43",
    "sg:city":"Musson",
    "sg:orig_category":"Decoratieve kunst and kunstbenodigdheden IJzerwaren, bouw- and verfmaterialen Installatie van metale",
    "sg:phone":"+32 63 67 54 96",
    "sg:postcode":"6750",
    "sg:province":"Luxembourg",
    "wof:name":"Victor Staff",
    "wof:placetype":"venue"
},
  "geometry": {"coordinates":[5.6592540741,49.5691680908],"type":"Point"}
}