{
  "type": "Feature",
  "properties": {
    "iso:country":"BE",
    "sg:address":"Putbeekstraat 6",
    "sg:city":"Gooik",
    "sg:orig_category":"Rundveehouders Varkenskwekers",
    "sg:phone":"+32 2 532 48 96",
    "sg:postcode":"1755",
    "sg:province":"Vlaams-Brabant",
    "wof:name":"Adolf Van Bossuyt",
    "wof:placetype":"venue"
},
  "geometry": {"coordinates":[4.1427969933,50.772895813],"type":"Point"}
}