{
  "type": "Feature",
  "properties": {
    "addr:full":"Iddergemstraat 46 Denderleeuw Oost-Vlaanderen 9470",
    "addr:housenumber":"46",
    "addr:postcode":"9470",
    "addr:street":"Iddergemstraat",
    "iso:country":"BE",
    "sg:address":"Iddergemstraat 46",
    "sg:city":"Denderleeuw",
    "sg:orig_category":"Apotheken",
    "sg:phone":"+32 53 66 93 03",
    "sg:postcode":"9470",
    "sg:province":"Oost-Vlaanderen",
    "wof:name":"C Van Den Eynde",
    "wof:placetype":"venue"
},
  "geometry": {"coordinates":[4.0577940941,50.8758811951],"type":"Point"}
}