{
  "type": "Feature",
  "properties": {
    "iso:country":"BE",
    "sg:address":"Rue Du Molinay 95",
    "sg:city":"Seraing",
    "sg:classifiers":[
        {
            "category":"Bars & Pubs",
            "type":"Food & Drink"
        }
    ],
    "sg:phone":"+32 4 337 18 13",
    "sg:postcode":"4100",
    "sg:province":"Li\u00e8ge",
    "wof:name":"Rustique (le)",
    "wof:placetype":"venue"
},
  "geometry": {"coordinates":[5.514354229,50.6068763733],"type":"Point"}
}