{
  "type": "Feature",
  "properties": {
    "iso:country":"BE",
    "sg:address":"Avenue Paul Deschanel 241",
    "sg:city":"Bruxelles (schaerbeek)",
    "sg:classifiers":[
        {
            "category":"Health Services",
            "subcategory":"Health Practitioner",
            "type":"Services"
        }
    ],
    "sg:phone":"+32 2 241 59 86",
    "sg:postcode":"1030",
    "sg:province":"Bruxelles-Capitale",
    "sg:tags":[
        "psychologist"
    ],
    "wof:name":"Groenez I",
    "wof:placetype":"venue"
},
  "geometry": {"coordinates":[4.3774747849,50.8551177979],"type":"Point"}
}