{
  "type": "Feature",
  "properties": {
    "addr:full":"Rue Du Tombois 36 Jodoigne Brabant Wallon 1370",
    "addr:housenumber":"36",
    "addr:postcode":"1370",
    "addr:street":"Rue Du Tombois",
    "iso:country":"BE",
    "sg:address":"Rue Du Tombois 36",
    "sg:city":"Jodoigne",
    "sg:orig_category":"Elektrische installaties voor woningen Loodgieterij, verwarming and sanitaire installaties Woningbou",
    "sg:phone":"+32 10 68 15 56",
    "sg:postcode":"1370",
    "sg:province":"Brabant Wallon",
    "wof:name":"Lb R\u00c9novation",
    "wof:placetype":"venue"
},
  "geometry": {"coordinates":[4.8699908257,50.7229347229],"type":"Point"}
}