{
  "type": "Feature",
  "properties": {
    "iso:country":"BE",
    "sg:address":"Avenue Reine Astrid 23",
    "sg:city":"Waremme",
    "sg:orig_category":"Eclairage et \u00e9quipements du foyer. Jeux and jouets. Souvenirs and objets artisanaux",
    "sg:phone":"+32 19 33 17 84",
    "sg:postcode":"4300",
    "sg:province":"Li\u00e8ge",
    "wof:name":"Blokker",
    "wof:placetype":"venue"
},
  "geometry": {"coordinates":[5.2509088516,50.6949958801],"type":"Point"}
}