{
  "type": "Feature",
  "properties": {
    "addr:full":"Rue G\u00c9n\u00c9raux-cuvelier 11ba Florenville Luxembourg 6820",
    "addr:housenumber":"11ba",
    "addr:postcode":"6820",
    "addr:street":"Rue Ge\u0301Ne\u0301Raux-Cuvelier",
    "iso:country":"BE",
    "sg:address":"Rue G\u00c9n\u00c9raux-cuvelier 11ba",
    "sg:city":"Florenville",
    "sg:orig_category":"Imprimeries and copyshops",
    "sg:phone":"+32 61 31 35 52",
    "sg:postcode":"6820",
    "sg:province":"Luxembourg",
    "wof:name":"Imprimerie Pire",
    "wof:placetype":"venue"
},
  "geometry": {"coordinates":[5.309399128,49.6978912354],"type":"Point"}
}