{
  "type": "Feature",
  "properties": {
    "iso:country":"BE",
    "sg:address":"102",
    "sg:city":"Zuiderring 2400 Mol",
    "sg:classifiers":[
        {
            "category":"Professional",
            "type":"Services"
        }
    ],
    "sg:phone":"+32 14 81 21 21",
    "sg:postcode":"102",
    "sg:tags":[
        "-",
        "related",
        "road",
        "transport"
    ],
    "wof:name":"Belgian Logistic Center Nv",
    "wof:placetype":"venue"
},
  "geometry": {"coordinates":[5.1618552208,51.2062263489],"type":"Point"}
}