{
  "type": "Feature",
  "properties": {
    "addr:full":"Munstersestraat 30 Zutendaal Limburg 3690",
    "addr:housenumber":"30",
    "addr:postcode":"3690",
    "addr:street":"Munstersestraat",
    "iso:country":"BE",
    "sg:address":"Munstersestraat 30",
    "sg:city":"Zutendaal",
    "sg:orig_category":"Location d'articles de sport, de sport nautique and de camping. Articles pour b\u00e9b\u00e9s. Articles de spo",
    "sg:phone":"+32 89 61 23 66",
    "sg:postcode":"3690",
    "sg:province":"Limburg",
    "wof:name":"Lenaerts",
    "wof:placetype":"venue"
},
  "geometry": {"coordinates":[5.5518798828,50.9348297119],"type":"Point"}
}