{
  "type": "Feature",
  "properties": {
    "iso:country":"BE",
    "sg:address":"Apostelstraat 2",
    "sg:city":"Sint-niklaas",
    "sg:classifiers":[
        {
            "category":"Bars & Pubs",
            "type":"Food & Drink"
        }
    ],
    "sg:phone":"+32 3 766 86 55",
    "sg:postcode":"9100",
    "sg:province":"Oost-Vlaanderen",
    "wof:name":"Oud Rethorica",
    "wof:placetype":"venue"
},
  "geometry": {"coordinates":[4.144423008,51.1639823914],"type":"Point"}
}