{
  "type": "Feature",
  "properties": {
    "addr:full":"Handelsstr. 13 Veurne West-Vlaanderen 8630",
    "addr:housenumber":"13",
    "addr:postcode":"8630",
    "addr:street":"Handelsstr.",
    "iso:country":"BE",
    "sg:address":"Handelsstr. 13",
    "sg:city":"Veurne",
    "sg:classifiers":[
        {
            "category":"Food & Beverages",
            "subcategory":"Groceries & Convenience Stores",
            "type":"Retail Goods"
        }
    ],
    "sg:phone":"+32 58 31 03 10",
    "sg:postcode":"8630",
    "sg:province":"West-Vlaanderen",
    "sg:tags":[
        "product",
        "grain",
        "cereal",
        "related"
    ],
    "wof:name":"Meli Nv",
    "wof:placetype":"venue"
},
  "geometry": {"coordinates":[2.6852200031,51.0669136047],"type":"Point"}
}