{
  "type": "Feature",
  "properties": {
    "addr:full":"Place Des Gueux 3 Brussel/bruxelles Bruxelles-Capitale 1000",
    "addr:housenumber":"3",
    "addr:postcode":"1000",
    "addr:street":"Place Des Gueux;/",
    "iso:country":"BE",
    "sg:address":"Place Des Gueux 3",
    "sg:city":"Brussel/bruxelles",
    "sg:orig_category":"Reliure and finition",
    "sg:phone":"+32 2 734 51 69",
    "sg:postcode":"1000",
    "sg:province":"Bruxelles-Capitale",
    "wof:name":"Printing Shop Brussels",
    "wof:placetype":"venue"
},
  "geometry": {"coordinates":[4.3906807899,50.8470458984],"type":"Point"}
}