{
  "type": "Feature",
  "properties": {
    "addr:full":"Antwerpsestraat 272 Mortsel Antwerpen 2640",
    "addr:housenumber":"272",
    "addr:postcode":"2640",
    "addr:street":"Antwerpsestraat",
    "iso:country":"BE",
    "sg:address":"Antwerpsestraat 272",
    "sg:city":"Mortsel",
    "sg:classifiers":[
        {
            "category":"Food & Beverages",
            "subcategory":"Chocolate",
            "type":"Retail Goods"
        }
    ],
    "sg:phone":"+32 3 449 94 89",
    "sg:postcode":"2640",
    "sg:province":"Antwerpen",
    "sg:tags":[
        "confectionery",
        "-"
    ],
    "wof:name":"De Castro J",
    "wof:placetype":"venue"
},
  "geometry": {"coordinates":[4.4378509521,51.1760787964],"type":"Point"}
}