{
  "type": "Feature",
  "properties": {
    "iso:country":"BE",
    "sg:address":"Oude Zoerlebaan 88",
    "sg:city":"Westerlo",
    "sg:classifiers":[
        {
            "category":"Wholesale",
            "subcategory":"Beer",
            "type":"Manufacturing & Wholesale Goods"
        }
    ],
    "sg:phone":"+32 16 69 96 27",
    "sg:postcode":"2260",
    "sg:province":"Antwerpen",
    "sg:tags":[
        "ale",
        "-"
    ],
    "wof:name":"Den Abt - Van Loo Nv",
    "wof:placetype":"venue"
},
  "geometry": {"coordinates":[4.8589100838,51.091632843],"type":"Point"}
}