{
  "type": "Feature",
  "properties": {
    "iso:country":"BE",
    "sg:address":"Rue Du Moulin 70b",
    "sg:city":"Etalle",
    "sg:orig_category":"Banken and kredietinstellingen",
    "sg:phone":"+32 63 45 50 91",
    "sg:postcode":"6740",
    "sg:province":"Luxembourg",
    "wof:name":"Cr\u00c9dit Agricole",
    "wof:placetype":"venue"
},
  "geometry": {"coordinates":[5.5955791473,49.6733818054],"type":"Point"}
}