{
  "type": "Feature",
  "properties": {
    "iso:country":"BE",
    "sg:address":"Sint-rochuslaan 12",
    "sg:city":"Borgloon",
    "sg:orig_category":"Centres sportifs. Clubs de sport. Installations and terrains de sport hors centres sportifs",
    "sg:phone":"+32 12 67 36 45",
    "sg:postcode":"3840",
    "sg:province":"Limburg",
    "wof:name":"Gemeentelijke Sporthal",
    "wof:placetype":"venue"
},
  "geometry": {"coordinates":[5.3514280319,50.8019866943],"type":"Point"}
}