{
  "type": "Feature",
  "properties": {
    "iso:country":"BE",
    "sg:address":"Basilieklaan 329",
    "sg:city":"Koekelberg/koekelberg",
    "sg:orig_category":"Alternatieve geneeskunde",
    "sg:phone":"+32 2 414 53 55",
    "sg:postcode":"1081",
    "sg:province":"Bruxelles-Capitale",
    "wof:name":"D. Lapraille",
    "wof:placetype":"venue"
},
  "geometry": {"coordinates":[4.3078041077,50.8646583557],"type":"Point"}
}