{
  "type": "Feature",
  "properties": {
    "iso:country":"BE",
    "sg:address":"Quai Timmermans 14",
    "sg:city":"Li\u00e8ge 1 (sclessin)",
    "sg:classifiers":[
        {
            "category":"Manufacturing",
            "subcategory":"Rubber & Plastics",
            "type":"Manufacturing & Wholesale Goods"
        }
    ],
    "sg:phone":"+32 4 252 00 50",
    "sg:postcode":"4000",
    "sg:province":"Li\u00e8ge",
    "sg:tags":[
        "industrial",
        "-"
    ],
    "wof:name":"Travhydro Plastics Et Isolants M\u00e9canis\u00e9s",
    "wof:placetype":"venue"
},
  "geometry": {"coordinates":[5.5547118187,50.6078186035],"type":"Point"}
}