{
  "type": "Feature",
  "properties": {
    "addr:full":"Avenue Houba De Strooper 63 Brussel Bruxelles-Capitale 1020",
    "addr:housenumber":"63",
    "addr:postcode":"1020",
    "addr:street":"Avenue Houba De Strooper",
    "iso:country":"BE",
    "sg:address":"Avenue Houba De Strooper 63",
    "sg:city":"Brussel",
    "sg:orig_category":"Instituts de beaut\u00e9. Centres de relaxation and bien-\u00eatre. Parfumeries",
    "sg:phone":"+32 2 478 64 53",
    "sg:postcode":"1020",
    "sg:province":"Bruxelles-Capitale",
    "wof:name":"Parfumerie Cloquet",
    "wof:placetype":"venue"
},
  "geometry": {"coordinates":[4.3400430679,50.8878173828],"type":"Point"}
}