{
  "type": "Feature",
  "properties": {
    "iso:country":"BE",
    "sg:address":"Rue Blaes 111-157",
    "sg:city":"Bruxelles",
    "sg:classifiers":[
        {
            "category":"Education",
            "subcategory":"Music School",
            "type":"Public Place"
        }
    ],
    "sg:phone":"+32 477 44 55 81",
    "sg:postcode":"1000",
    "sg:province":"Bruxelles-Capitale",
    "sg:tags":[
        "-",
        "teacher",
        "private"
    ],
    "wof:name":"Harris N",
    "wof:placetype":"venue"
},
  "geometry": {"coordinates":[4.3479509354,50.8385505676],"type":"Point"}
}