{
  "type": "Feature",
  "properties": {
    "iso:country":"BE",
    "sg:address":"Beukenlaan 4",
    "sg:city":"Harelbeke (hulste)",
    "sg:classifiers":[
        {
            "category":"Personal",
            "subcategory":"Beauty Salon",
            "type":"Services"
        }
    ],
    "sg:phone":"+32 56 71 33 42",
    "sg:postcode":"8531",
    "sg:province":"West-Vlaanderen",
    "wof:name":"Beauty Aromatique",
    "wof:placetype":"venue"
},
  "geometry": {"coordinates":[3.294408083,50.8858566284],"type":"Point"}
}