{
  "type": "Feature",
  "properties": {
    "iso:country":"BE",
    "sg:address":"Grotstraat 33",
    "sg:city":"Arendonk",
    "sg:orig_category":"Gespecialiseerde residenti\u00eble bouw",
    "sg:phone":"+32 14 67 77 94",
    "sg:postcode":"2370",
    "sg:province":"Antwerpen",
    "wof:name":"Michel Eyssen",
    "wof:placetype":"venue"
},
  "geometry": {"coordinates":[5.0780930519,51.3266143799],"type":"Point"}
}