{
  "type": "Feature",
  "properties": {
    "iso:country":"BE",
    "sg:address":"Ieperstraat 12",
    "sg:city":"Tielt",
    "sg:classifiers":[
        {
            "category":"Travel",
            "subcategory":"Travel Agent",
            "type":"Entertainment"
        }
    ],
    "sg:phone":"+32 51 42 40 50",
    "sg:postcode":"8700",
    "sg:province":"West-Vlaanderen",
    "sg:tags":[
        "agency"
    ],
    "wof:name":"Way 2 Canada",
    "wof:placetype":"venue"
},
  "geometry": {"coordinates":[3.3253569603,50.9997749329],"type":"Point"}
}