{
  "type": "Feature",
  "properties": {
    "addr:full":"Vandendriesschestraat 6 Zottegem Oost-Vlaanderen 9620",
    "addr:housenumber":"6",
    "addr:postcode":"9620",
    "addr:street":"Vandendriesschestraat",
    "iso:country":"BE",
    "sg:address":"Vandendriesschestraat 6",
    "sg:city":"Zottegem",
    "sg:orig_category":"Onderdelen and accessoires voertuigen Gh Onderdelen and accessoires voor auto's",
    "sg:phone":"+32 9 361 00 41",
    "sg:postcode":"9620",
    "sg:province":"Oost-Vlaanderen",
    "wof:name":"Autorova",
    "wof:placetype":"venue"
},
  "geometry": {"coordinates":[3.817070961,50.8794174194],"type":"Point"}
}