{
  "type": "Feature",
  "properties": {
    "iso:country":"BE",
    "sg:address":"Rue W\u00c9rihet 7",
    "sg:city":"Engis",
    "sg:orig_category":"Woningbouw",
    "sg:phone":"+32 85 31 74 08",
    "sg:postcode":"4480",
    "sg:province":"Li\u00e8ge",
    "wof:name":"Fossion",
    "wof:placetype":"venue"
},
  "geometry": {"coordinates":[5.4045758247,50.582069397],"type":"Point"}
}