{
  "type": "Feature",
  "properties": {
    "iso:country":"BE",
    "sg:address":"Halvemaanstraat 92",
    "sg:city":"Gent",
    "sg:orig_category":"Biblioth\u00e8ques and archives publiques",
    "sg:phone":"+32 9 229 10 55",
    "sg:postcode":"9040",
    "sg:province":"Oost-Vlaanderen",
    "wof:name":"P.o.b. St-amandus",
    "wof:placetype":"venue"
},
  "geometry": {"coordinates":[3.745331049,51.0614471436],"type":"Point"}
}