{
  "type": "Feature",
  "properties": {
    "iso:country":"BE",
    "sg:address":"Boomstraat 114",
    "sg:city":"Bornem",
    "sg:classifiers":[
        {
            "category":"Travel",
            "subcategory":"Travel Agent",
            "type":"Entertainment"
        }
    ],
    "sg:phone":"+32 3 889 66 32",
    "sg:postcode":"2880",
    "sg:province":"Antwerpen",
    "sg:tags":[
        "accessory",
        "mountaineering"
    ],
    "wof:name":"Klein Amerika",
    "wof:placetype":"venue"
},
  "geometry": {"coordinates":[4.2325592041,51.0961303711],"type":"Point"}
}