{
  "type": "Feature",
  "properties": {
    "iso:country":"BE",
    "sg:address":"Vis\u00e9steenweg 145",
    "sg:city":"Riemst (zichen-zussen-bolder)",
    "sg:classifiers":[
        {
            "category":"Insurance",
            "subcategory":"Insurance Agent",
            "type":"Services"
        }
    ],
    "sg:phone":"+32 12 45 68 73",
    "sg:postcode":"3770",
    "sg:province":"Limburg",
    "sg:tags":[
        "broker"
    ],
    "wof:name":"Laval Bvba",
    "wof:placetype":"venue"
},
  "geometry": {"coordinates":[5.6054201126,50.8047485352],"type":"Point"}
}