{
  "type": "Feature",
  "properties": {
    "addr:full":"Regentlaan 53 Brussels Bruxelles-Capitale 1000",
    "addr:housenumber":"53",
    "addr:postcode":"1000",
    "addr:street":"Regentlaan",
    "iso:country":"BE",
    "sg:address":"Regentlaan 53",
    "sg:city":"Brussels",
    "sg:classifiers":[
        {
            "category":"Banks & Credit Unions",
            "subcategory":"Bank",
            "type":"Services"
        }
    ],
    "sg:postcode":"1000",
    "sg:province":"Bruxelles-Capitale",
    "wof:name":"Abn Amro Bank (belgi\u00eb) Nv",
    "wof:placetype":"venue"
},
  "geometry": {"coordinates":[4.3688230515,50.8479270935],"type":"Point"}
}