{
  "type": "Feature",
  "properties": {
    "iso:country":"BE",
    "sg:address":"Hemelingenstraat 22",
    "sg:city":"Tongeren",
    "sg:classifiers":[
        {
            "category":"Shopping",
            "subcategory":"Optician",
            "type":"Retail Goods"
        }
    ],
    "sg:phone":"+32 12 39 19 53",
    "sg:postcode":"3700",
    "sg:province":"Limburg",
    "sg:tags":[
        "-"
    ],
    "wof:name":"Optiek Fabienne Lesecque",
    "wof:placetype":"venue"
},
  "geometry": {"coordinates":[5.4625692368,50.7813796997],"type":"Point"}
}