{
  "type": "Feature",
  "properties": {
    "iso:country":"BE",
    "sg:address":"Koestraat 28",
    "sg:city":"Overijse",
    "sg:classifiers":[
        {
            "category":"Home & Garden",
            "subcategory":"Furniture",
            "type":"Retail Goods"
        }
    ],
    "sg:phone":"+32 2 687 67 55",
    "sg:postcode":"3090",
    "sg:province":"Vlaams-Brabant",
    "sg:tags":[
        "fab",
        "meubelen",
        "diverse"
    ],
    "wof:name":"Michiels G",
    "wof:placetype":"venue"
},
  "geometry": {"coordinates":[4.5412092209,50.7964782715],"type":"Point"}
}