{
  "type": "Feature",
  "properties": {
    "iso:country":"BE",
    "sg:address":"Oudestraat 61",
    "sg:city":"Hasselt (spalbeek)",
    "sg:classifiers":[
        {
            "category":"Wholesale",
            "subcategory":"Meat",
            "type":"Manufacturing & Wholesale Goods"
        }
    ],
    "sg:phone":"+32 11 25 16 61",
    "sg:postcode":"3510",
    "sg:province":"Limburg",
    "sg:tags":[
        "whol",
        "-"
    ],
    "wof:name":"Baerts Nv",
    "wof:placetype":"venue"
},
  "geometry": {"coordinates":[5.2218952179,50.9435386658],"type":"Point"}
}