{
  "type": "Feature",
  "properties": {
    "iso:country":"BE",
    "sg:address":"Statiesstraat 56",
    "sg:city":"Dentergem",
    "sg:orig_category":"Produits laitiers and huiles comestibles Gr",
    "sg:phone":"+32 51 63 32 46",
    "sg:postcode":"8720",
    "sg:province":"West-Vlaanderen",
    "wof:name":"Ysebaert G",
    "wof:placetype":"venue"
},
  "geometry": {"coordinates":[3.414536953,50.9701728821],"type":"Point"}
}