{
  "type": "Feature",
  "properties": {
    "addr:full":"Nieuwe Baan 80 Belsele Oost-Vlaanderen 9111",
    "addr:housenumber":"80",
    "addr:postcode":"9111",
    "addr:street":"Nieuwe Baan",
    "iso:country":"BE",
    "sg:address":"Nieuwe Baan 80",
    "sg:city":"Belsele",
    "sg:orig_category":"Royal Canin. Producteurs de fruits. Articles de jardin. Fleurs and plantes. Souvenirs and objets art",
    "sg:phone":"+32 3 772 37 91",
    "sg:postcode":"9111",
    "sg:province":"Oost-Vlaanderen",
    "wof:name":"Green Center",
    "wof:placetype":"venue"
},
  "geometry": {"coordinates":[4.0980410576,51.1439666748],"type":"Point"}
}