{
  "type": "Feature",
  "properties": {
    "iso:country":"BE",
    "sg:address":"Dorp-oost 21",
    "sg:city":"Lochristi",
    "sg:orig_category":"Supermarch\u00e9s",
    "sg:phone":"+32 9 355 55 68",
    "sg:postcode":"9080",
    "sg:province":"Oost-Vlaanderen",
    "wof:name":"Unic",
    "wof:placetype":"venue"
},
  "geometry": {"coordinates":[3.8347699642,51.0968322754],"type":"Point"}
}