{
  "type": "Feature",
  "properties": {
    "addr:full":"Zinkstraat 6 Halle Vlaams-Brabant 1500",
    "addr:housenumber":"6",
    "addr:postcode":"1500",
    "addr:street":"Zinkstraat",
    "iso:country":"BE",
    "sg:address":"Zinkstraat 6",
    "sg:city":"Halle",
    "sg:classifiers":[
        {
            "category":"Retail",
            "subcategory":"Auto Repair",
            "type":"Services"
        }
    ],
    "sg:phone":"+32 2 360 34 34",
    "sg:postcode":"1500",
    "sg:province":"Vlaams-Brabant",
    "sg:tags":[
        "wheel",
        "automobile",
        "-",
        "balancing",
        "aligning"
    ],
    "wof:name":"Deproost &",
    "wof:placetype":"venue"
},
  "geometry": {"coordinates":[4.2114629745,50.7272491455],"type":"Point"}
}