{
  "type": "Feature",
  "properties": {
    "addr:full":"Rue Saint-achaire 86 Moeskroen/mouscron Hainaut 7700",
    "addr:housenumber":"86",
    "addr:postcode":"7700",
    "addr:street":"Rue Saint-Achaire",
    "iso:country":"BE",
    "sg:address":"Rue Saint-achaire 86",
    "sg:city":"Moeskroen/mouscron",
    "sg:orig_category":"Avocats and conseillers juridiques",
    "sg:phone":"+32 56 34 99 61",
    "sg:postcode":"7700",
    "sg:province":"Hainaut",
    "wof:name":"H. Van Besien",
    "wof:placetype":"venue"
},
  "geometry": {"coordinates":[3.231926918,50.7478256226],"type":"Point"}
}