{
  "type": "Feature",
  "properties": {
    "addr:full":"Sint-katharinastraat 116 Puurs Antwerpen 2870",
    "addr:housenumber":"116",
    "addr:postcode":"2870",
    "addr:street":"Sint-Katharinastraat",
    "iso:country":"BE",
    "sg:address":"Sint-katharinastraat 116",
    "sg:city":"Puurs",
    "sg:orig_category":"Vitrage",
    "sg:phone":"+32 3 886 52 46",
    "sg:postcode":"2870",
    "sg:province":"Antwerpen",
    "wof:name":"Art Glass Atelier",
    "wof:placetype":"venue"
},
  "geometry": {"coordinates":[4.3336558342,51.0773353577],"type":"Point"}
}