{
  "type": "Feature",
  "properties": {
    "addr:full":"Tremelobaan 206 Keerbergen Vlaams-Brabant 3140",
    "addr:housenumber":"206",
    "addr:postcode":"3140",
    "addr:street":"Tremelobaan",
    "iso:country":"BE",
    "sg:address":"Tremelobaan 206",
    "sg:city":"Keerbergen",
    "sg:classifiers":[
        {
            "category":"Bakery",
            "type":"Food & Drink"
        }
    ],
    "sg:phone":"+32 16 53 33 48",
    "sg:postcode":"3140",
    "sg:province":"Vlaams-Brabant",
    "sg:tags":[
        "confectioner",
        "baker"
    ],
    "wof:name":"Vanderveken-geerts Bakkerij",
    "wof:placetype":"venue"
},
  "geometry": {"coordinates":[4.6856021881,50.994682312],"type":"Point"}
}