{
  "type": "Feature",
  "properties": {
    "addr:full":"Rue De Verviers 32 Welkenraedt Li\u00e8ge 4841",
    "addr:housenumber":"32",
    "addr:postcode":"4841",
    "addr:street":"Rue De Verviers",
    "iso:country":"BE",
    "sg:address":"Rue De Verviers 32",
    "sg:city":"Welkenraedt",
    "sg:classifiers":[
        {
            "category":"Arena",
            "subcategory":"Sports Club",
            "type":"Entertainment"
        }
    ],
    "sg:phone":"+32 87 88 05 67",
    "sg:postcode":"4841",
    "sg:province":"Li\u00e8ge",
    "sg:tags":[
        "de"
    ],
    "wof:name":"T.c. Charlemagne",
    "wof:placetype":"venue"
},
  "geometry": {"coordinates":[5.899228096,50.6402587891],"type":"Point"}
}