{
  "type": "Feature",
  "properties": {
    "iso:country":"BE",
    "sg:address":"Kievitlaan 2",
    "sg:city":"Brecht",
    "sg:classifiers":[
        {
            "category":"Health Services",
            "subcategory":"Health Practitioner",
            "type":"Services"
        }
    ],
    "sg:phone":"+32 3 636 42 57",
    "sg:postcode":"2960",
    "sg:province":"Antwerpen",
    "sg:tags":[
        "physiotherapist"
    ],
    "wof:name":"Denissen Alain",
    "wof:placetype":"venue"
},
  "geometry": {"coordinates":[4.5634732246,51.3072433472],"type":"Point"}
}