{
  "type": "Feature",
  "properties": {
    "addr:full":"Doornstr 51a Temse Oost-Vlaanderen 9140",
    "addr:housenumber":"51a",
    "addr:postcode":"9140",
    "addr:street":"Doornstr",
    "iso:country":"BE",
    "sg:address":"Doornstr 51a",
    "sg:city":"Temse",
    "sg:classifiers":[
        {
            "category":"Food & Beverages",
            "subcategory":"Groceries & Convenience Stores",
            "type":"Retail Goods"
        }
    ],
    "sg:phone":"+32 3 771 31 23",
    "sg:postcode":"9140",
    "sg:province":"Oost-Vlaanderen",
    "sg:tags":[
        "product",
        "related"
    ],
    "wof:name":"Confiserie D.r. Bvba",
    "wof:placetype":"venue"
},
  "geometry": {"coordinates":[4.2093129158,51.1387481689],"type":"Point"}
}