{
  "type": "Feature",
  "properties": {
    "addr:full":"Rue De La Dynastie 4 Erquelinnes Hainaut 6560",
    "addr:housenumber":"4",
    "addr:postcode":"6560",
    "addr:street":"Rue De La Dynastie",
    "iso:country":"BE",
    "sg:address":"Rue De La Dynastie 4",
    "sg:city":"Erquelinnes",
    "sg:orig_category":"Huishoudapparaten, televisies and radio's Rookartikelen",
    "sg:phone":"+32 71 55 56 45",
    "sg:postcode":"6560",
    "sg:province":"Hainaut",
    "wof:name":"Electrom\u00c9nager Monument",
    "wof:placetype":"venue"
},
  "geometry": {"coordinates":[4.1299629211,50.3106918335],"type":"Point"}
}