{
  "type": "Feature",
  "properties": {
    "addr:full":"Chauss\u00c9e De Helmet 169 Schaarbeek/schaerbeek Bruxelles-Capitale 1030",
    "addr:housenumber":"169",
    "addr:postcode":"1030",
    "addr:street":"Chausse\u0301E De Helmet",
    "iso:country":"BE",
    "sg:address":"Chauss\u00c9e De Helmet 169",
    "sg:city":"Schaarbeek/schaerbeek",
    "sg:orig_category":"Blanchisseries and teintureries",
    "sg:phone":"+32 2 242 48 13",
    "sg:postcode":"1030",
    "sg:province":"Bruxelles-Capitale",
    "wof:name":"Ipsomat",
    "wof:placetype":"venue"
},
  "geometry": {"coordinates":[4.3852658272,50.8722724915],"type":"Point"}
}