{
  "type": "Feature",
  "properties": {
    "iso:country":"BE",
    "sg:address":"Kesselsesteenweg 40",
    "sg:city":"Nijlen",
    "sg:orig_category":"Diverse intermediaire producten Gh Juwelen and edelstenen Fab",
    "sg:phone":"+32 3 481 76 27",
    "sg:postcode":"2560",
    "sg:province":"Antwerpen",
    "wof:name":"D.l.s.",
    "wof:placetype":"venue"
},
  "geometry": {"coordinates":[4.6620988846,51.1553459167],"type":"Point"}
}