{
  "type": "Feature",
  "properties": {
    "iso:country":"BE",
    "sg:address":"Putvennestraat 27",
    "sg:city":"Hasselt",
    "sg:orig_category":"Travaux de pl\u00e2trage",
    "sg:phone":"+32 495 32 62 62",
    "sg:postcode":"3500",
    "sg:province":"Limburg",
    "wof:name":"P.g.a.",
    "wof:placetype":"venue"
},
  "geometry": {"coordinates":[5.3614201546,50.9640884399],"type":"Point"}
}