{
  "type": "Feature",
  "properties": {
    "iso:country":"BE",
    "sg:address":"Bois De Thy 974",
    "sg:city":"Genappe",
    "sg:orig_category":"Entretien and r\u00e9parations de voitures",
    "sg:phone":"+32 67 78 02 75",
    "sg:postcode":"1470",
    "sg:province":"Brabant Wallon",
    "wof:name":"Garage Schoonenburg",
    "wof:placetype":"venue"
},
  "geometry": {"coordinates":[4.4865999222,50.6142196655],"type":"Point"}
}