{
  "type": "Feature",
  "properties": {
    "addr:full":"Boulevard Des Alli\u00c9s 240 Moeskroen/mouscron Hainaut 7700",
    "addr:housenumber":"240",
    "addr:postcode":"7700",
    "addr:street":"Boulevard Des Allie\u0301S",
    "iso:country":"BE",
    "sg:address":"Boulevard Des Alli\u00c9s 240",
    "sg:city":"Moeskroen/mouscron",
    "sg:orig_category":"Eleveurs de bovins",
    "sg:phone":"+32 56 33 15 63",
    "sg:postcode":"7700",
    "sg:province":"Hainaut",
    "wof:name":"Jose Pattyn",
    "wof:placetype":"venue"
},
  "geometry": {"coordinates":[3.2323200703,50.7400932312],"type":"Point"}
}