{
  "type": "Feature",
  "properties": {
    "iso:country":"BE",
    "sg:address":"Chauss\u00e9e De L'europe 151",
    "sg:city":"Couvin (cul-des-sarts)",
    "sg:classifiers":[
        {
            "category":"Real Estate",
            "subcategory":"Architect",
            "type":"Services"
        }
    ],
    "sg:phone":"+32 60 37 78 24",
    "sg:postcode":"5660",
    "sg:province":"Namur",
    "wof:name":"Selves E",
    "wof:placetype":"venue"
},
  "geometry": {"coordinates":[4.4537410736,49.9605827332],"type":"Point"}
}