{
  "type": "Feature",
  "properties": {
    "addr:full":"Korte Koepoortstraat 7 Antwerpen Antwerpen 2000",
    "addr:housenumber":"7",
    "addr:postcode":"2000",
    "addr:street":"Korte Koepoortstraat",
    "iso:country":"BE",
    "sg:address":"Korte Koepoortstraat 7",
    "sg:city":"Antwerpen",
    "sg:classifiers":[
        {
            "category":"Food & Beverages",
            "subcategory":"Chocolate",
            "type":"Retail Goods"
        }
    ],
    "sg:phone":"+32 3 231 03 45",
    "sg:postcode":"2000",
    "sg:province":"Antwerpen",
    "sg:tags":[
        "confectionery",
        "-"
    ],
    "wof:name":"'t Peperkoekehuisje",
    "wof:placetype":"venue"
},
  "geometry": {"coordinates":[4.4025578499,51.2213897705],"type":"Point"}
}