{
  "type": "Feature",
  "properties": {
    "addr:full":"Rue Albert I 15-17 Engis Li\u00e8ge 4480",
    "addr:housenumber":"15-17",
    "addr:postcode":"4480",
    "addr:street":"Rue Albert I",
    "iso:country":"BE",
    "sg:address":"Rue Albert I 15-17",
    "sg:city":"Engis",
    "sg:classifiers":[
        {
            "category":"Home & Garden",
            "subcategory":"Building Materials",
            "type":"Retail Goods"
        }
    ],
    "sg:phone":"+32 4 275 11 91",
    "sg:postcode":"4480",
    "sg:province":"Li\u00e8ge",
    "sg:tags":[
        "window"
    ],
    "wof:name":"Halleux Sprl",
    "wof:placetype":"venue"
},
  "geometry": {"coordinates":[5.4059109688,50.5828704834],"type":"Point"}
}