{
  "type": "Feature",
  "properties": {
    "iso:country":"BE",
    "sg:address":"Parc Industriel De Petit-rechain 26",
    "sg:city":"Herve",
    "sg:classifiers":[
        {
            "category":"Retail",
            "subcategory":"Auto Repair",
            "type":"Services"
        }
    ],
    "sg:phone":"+32 87 31 31 60",
    "sg:postcode":"4650",
    "sg:province":"Li\u00e8ge",
    "sg:tags":[
        "garage"
    ],
    "wof:name":"Fagard Garage",
    "wof:placetype":"venue"
},
  "geometry": {"coordinates":[5.8355398178,50.6285514832],"type":"Point"}
}