{
  "type": "Feature",
  "properties": {
    "iso:country":"BE",
    "sg:address":"Rue Des Drapiers 40",
    "sg:city":"Bruxelles (ixelles)",
    "sg:classifiers":[
        {
            "category":"Organizations",
            "subcategory":"Membership Organization",
            "type":"Services"
        }
    ],
    "sg:phone":"+32 2 502 33 02",
    "sg:postcode":"1050",
    "sg:province":"Bruxelles-Capitale",
    "sg:tags":[
        "videoconferencing",
        "system"
    ],
    "wof:name":"Act Teleconferencing Bv",
    "wof:placetype":"venue"
},
  "geometry": {"coordinates":[4.3596601486,50.8351249695],"type":"Point"}
}