{
  "type": "Feature",
  "properties": {
    "addr:full":"Rue Bois Du Bosquet 73 Rixensart Brabant Wallon 1331",
    "addr:housenumber":"73",
    "addr:postcode":"1331",
    "addr:street":"Rue Bois Du Bosquet;Wallon",
    "iso:country":"BE",
    "sg:address":"Rue Bois Du Bosquet 73",
    "sg:city":"Rixensart",
    "sg:orig_category":"Woningbouw",
    "sg:phone":"+32 2 653 60 00",
    "sg:postcode":"1331",
    "sg:province":"Brabant Wallon",
    "wof:name":"Gigot M & Y",
    "wof:placetype":"venue"
},
  "geometry": {"coordinates":[4.5428071022,50.7334327698],"type":"Point"}
}