{
  "type": "Feature",
  "properties": {
    "addr:full":"Blinckaertlaan 10 Knokke-heist West-Vlaanderen 8300",
    "addr:housenumber":"10",
    "addr:postcode":"8300",
    "addr:street":"Blinckaertlaan",
    "iso:country":"BE",
    "sg:address":"Blinckaertlaan 10",
    "sg:city":"Knokke-heist",
    "sg:classifiers":[
        {
            "category":"Fast Food",
            "type":"Food & Drink"
        }
    ],
    "sg:phone":"+32 50 60 39 42",
    "sg:postcode":"8300",
    "sg:province":"West-Vlaanderen",
    "sg:tags":[
        "de",
        "restaurant",
        "organisation",
        "\u00c0",
        "catering",
        "emporter",
        "f\u00cates",
        "restaurants"
    ],
    "wof:name":"Ten Bos",
    "wof:placetype":"venue"
},
  "geometry": {"coordinates":[3.3154559135,51.3486061096],"type":"Point"}
}