{
  "type": "Feature",
  "properties": {
    "iso:country":"BE",
    "sg:address":"Mottestraat 1",
    "sg:city":"Gingelom",
    "sg:orig_category":"Enseignement maternel and primaire",
    "sg:phone":"+32 11 83 21 19",
    "sg:postcode":"3890",
    "sg:province":"Limburg",
    "wof:name":"Gemeentel. Kleuterschool",
    "wof:placetype":"venue"
},
  "geometry": {"coordinates":[5.1401281357,50.7411308289],"type":"Point"}
}