{
  "type": "Feature",
  "properties": {
    "iso:country":"BE",
    "sg:address":"Cuvelierstraat 61",
    "sg:city":"Bilzen",
    "sg:orig_category":"Eleveurs de bovins. Eleveurs and marchands de porcs",
    "sg:phone":"+32 89 41 20 60",
    "sg:postcode":"3740",
    "sg:province":"Limburg",
    "wof:name":"Arnaud Thijs",
    "wof:placetype":"venue"
},
  "geometry": {"coordinates":[5.5133070946,50.8699760437],"type":"Point"}
}