{
  "type": "Feature",
  "properties": {
    "iso:country":"BE",
    "sg:address":"Pont-zuid 25",
    "sg:city":"De Pinte (zevergem)",
    "sg:classifiers":[
        {
            "category":"Wholesale",
            "subcategory":"Plants",
            "type":"Manufacturing & Wholesale Goods"
        }
    ],
    "sg:phone":"+32 9 385 47 50",
    "sg:postcode":"9840",
    "sg:province":"Oost-Vlaanderen",
    "sg:tags":[
        "whol",
        "flower",
        "-",
        "grower"
    ],
    "wof:name":"Begodt H",
    "wof:placetype":"venue"
},
  "geometry": {"coordinates":[3.69094491,50.9762687683],"type":"Point"}
}