{
  "type": "Feature",
  "properties": {
    "addr:full":"Het Pand 246 Waregem West-Vlaanderen 8790",
    "addr:housenumber":"246",
    "addr:postcode":"8790",
    "addr:street":"Het Pand",
    "iso:country":"BE",
    "sg:address":"Het Pand 246",
    "sg:city":"Waregem",
    "sg:orig_category":"Belastingconsulenten Diverse juridische dienstverlening",
    "sg:phone":"+32 56 60 44 51",
    "sg:postcode":"8790",
    "sg:province":"West-Vlaanderen",
    "wof:name":"Fisc. Secret. Wij Helpen",
    "wof:placetype":"venue"
},
  "geometry": {"coordinates":[3.4312300682,50.88621521],"type":"Point"}
}