{
  "type": "Feature",
  "properties": {
    "addr:full":"Kapellekensdreef 34 Mol Antwerpen 2400",
    "addr:housenumber":"34",
    "addr:postcode":"2400",
    "addr:street":"Kapellekensdreef",
    "iso:country":"BE",
    "sg:address":"Kapellekensdreef 34",
    "sg:city":"Mol",
    "sg:classifiers":[
        {
            "category":"Banks & Credit Unions",
            "subcategory":"Investment Brokerage",
            "type":"Services"
        }
    ],
    "sg:phone":"+32 14 31 66 67",
    "sg:postcode":"2400",
    "sg:province":"Antwerpen",
    "sg:tags":[
        "auditor"
    ],
    "wof:name":"Bekkers F",
    "wof:placetype":"venue"
},
  "geometry": {"coordinates":[5.1431050301,51.1883659363],"type":"Point"}
}