{
  "type": "Feature",
  "properties": {
    "addr:full":"Sterrebeekstraat 176 Zaventem Vlaams-Brabant 1930",
    "addr:housenumber":"176",
    "addr:postcode":"1930",
    "addr:street":"Sterrebeekstraat",
    "iso:country":"BE",
    "sg:address":"Sterrebeekstraat 176",
    "sg:city":"Zaventem",
    "sg:classifiers":[
        {
            "category":"Shopping",
            "subcategory":"Bicycles & Sporting Goods",
            "type":"Retail Goods"
        }
    ],
    "sg:phone":"+32 2 720 63 00",
    "sg:postcode":"1930",
    "sg:province":"Vlaams-Brabant",
    "sg:tags":[
        "product",
        "sport",
        "miscellaneous"
    ],
    "wof:name":"Alfa Trading Bvba",
    "wof:placetype":"venue"
},
  "geometry": {"coordinates":[4.4867310524,50.8699989319],"type":"Point"}
}