{
  "type": "Feature",
  "properties": {
    "iso:country":"BE",
    "sg:address":"Hekkergemstraat 117",
    "sg:city":"Wichelen",
    "sg:orig_category":"Fleurs and plantes",
    "sg:phone":"+32 9 366 25 51",
    "sg:postcode":"9260",
    "sg:province":"Oost-Vlaanderen",
    "wof:name":"Bloemen Farell",
    "wof:placetype":"venue"
},
  "geometry": {"coordinates":[3.9330630302,51.0088272095],"type":"Point"}
}