{
  "type": "Feature",
  "properties": {
    "iso:country":"BE",
    "sg:address":"Rue Du Pairay 86",
    "sg:city":"Seraing",
    "sg:classifiers":[
        {
            "category":"Retail",
            "subcategory":"Funeral Services",
            "type":"Services"
        }
    ],
    "sg:phone":"+32 4 336 13 18",
    "sg:postcode":"4100",
    "sg:province":"Li\u00e8ge",
    "sg:tags":[
        "director"
    ],
    "wof:name":"Georis",
    "wof:placetype":"venue"
},
  "geometry": {"coordinates":[5.5104680061,50.5967254639],"type":"Point"}
}