{
  "type": "Feature",
  "properties": {
    "iso:country":"BE",
    "sg:address":"Rue Des Liserons 16",
    "sg:city":"Seraing",
    "sg:orig_category":"Dakwerken Loodgieterij, verwarming and sanitaire installaties",
    "sg:phone":"+32 4 330 91 86",
    "sg:postcode":"4100",
    "sg:province":"Li\u00e8ge",
    "wof:name":"Techni-services",
    "wof:placetype":"venue"
},
  "geometry": {"coordinates":[5.5163559914,50.5851783752],"type":"Point"}
}