{
  "type": "Feature",
  "properties": {
    "addr:full":"V-dagstraat 5 Zwevegem West-Vlaanderen 8551",
    "addr:housenumber":"5",
    "addr:postcode":"8551",
    "addr:street":"V-Dagstraat",
    "iso:country":"BE",
    "sg:address":"V-dagstraat 5",
    "sg:city":"Zwevegem",
    "sg:orig_category":"Installation \u00e9lectrique r\u00e9sidentielle",
    "sg:phone":"+32 56 64 55 01",
    "sg:postcode":"8551",
    "sg:province":"West-Vlaanderen",
    "wof:name":"Vercoutere Jacques",
    "wof:placetype":"venue"
},
  "geometry": {"coordinates":[3.4109840393,50.782283783],"type":"Point"}
}