{
  "type": "Feature",
  "properties": {
    "addr:full":"Wervikstraat 320 Menen West-Vlaanderen 8930",
    "addr:housenumber":"320",
    "addr:postcode":"8930",
    "addr:street":"Wervikstraat",
    "iso:country":"BE",
    "sg:address":"Wervikstraat 320",
    "sg:city":"Menen",
    "sg:orig_category":"Ramassage and traitement des d\u00e9chets m\u00e9nagers",
    "sg:phone":"+32 56 52 13 00",
    "sg:postcode":"8930",
    "sg:province":"West-Vlaanderen",
    "wof:name":"Valorauto Belgium",
    "wof:placetype":"venue"
},
  "geometry": {"coordinates":[3.1054639816,50.7889175415],"type":"Point"}
}