{
  "type": "Feature",
  "properties": {
    "addr:full":"Kapelleriestraat 36 Staden West-Vlaanderen 8840",
    "addr:housenumber":"36",
    "addr:postcode":"8840",
    "addr:street":"Kapelleriestraat",
    "iso:country":"BE",
    "sg:address":"Kapelleriestraat 36",
    "sg:city":"Staden",
    "sg:orig_category":"Aardappelproducten Gh GROENTEN AND FRUIT Groenten and fruit Gh Tuinbenodigdheden",
    "sg:phone":"+32 51 70 16 25",
    "sg:postcode":"8840",
    "sg:province":"West-Vlaanderen",
    "wof:name":"Debeuckelaere",
    "wof:placetype":"venue"
},
  "geometry": {"coordinates":[3.0109078884,50.9734764099],"type":"Point"}
}