{
  "type": "Feature",
  "properties": {
    "addr:full":"Charles De Kerchovelaan 15 Gent Oost-Vlaanderen 9000",
    "addr:housenumber":"15",
    "addr:postcode":"9000",
    "addr:street":"Charles De Kerchovelaan;Oost-Vlaanderen",
    "iso:country":"BE",
    "sg:address":"Charles De Kerchovelaan 15",
    "sg:city":"Gent",
    "sg:orig_category":"Fotografen and fotostudio's",
    "sg:phone":"+32 9 225 29 72",
    "sg:postcode":"9000",
    "sg:province":"Oost-Vlaanderen",
    "wof:name":"Luc Van Acker",
    "wof:placetype":"venue"
},
  "geometry": {"coordinates":[3.7211089134,51.0412063599],"type":"Point"}
}