{
  "type": "Feature",
  "properties": {
    "iso:country":"BE",
    "sg:address":"Nindsebaan 47",
    "sg:city":"Keerbergen",
    "sg:classifiers":[
        {
            "category":"Health Services",
            "subcategory":"Doctor",
            "type":"Services"
        }
    ],
    "sg:phone":"+32 15 73 00 34",
    "sg:postcode":"3140",
    "sg:province":"Vlaams-Brabant",
    "sg:tags":[
        "medicinephysicians",
        "surgeon"
    ],
    "wof:name":"Deferm H",
    "wof:placetype":"venue"
},
  "geometry": {"coordinates":[4.6600937843,50.9959754944],"type":"Point"}
}