{
  "type": "Feature",
  "properties": {
    "addr:full":"Elf-novemberlaan 37 Lochristi Oost-Vlaanderen 9080",
    "addr:housenumber":"37",
    "addr:postcode":"9080",
    "addr:street":"Elf-Novemberlaan",
    "iso:country":"BE",
    "sg:address":"Elf-novemberlaan 37",
    "sg:city":"Lochristi",
    "sg:orig_category":"Schoenen",
    "sg:phone":"+32 9 355 76 86",
    "sg:postcode":"9080",
    "sg:province":"Oost-Vlaanderen",
    "wof:name":"Esther",
    "wof:placetype":"venue"
},
  "geometry": {"coordinates":[3.8306219578,51.1043205261],"type":"Point"}
}