{
  "type": "Feature",
  "properties": {
    "addr:full":"Terlinden 256 Merchtem Vlaams-Brabant 1785",
    "addr:housenumber":"256",
    "addr:postcode":"1785",
    "addr:street":"Terlinden",
    "iso:country":"BE",
    "sg:address":"Terlinden 256",
    "sg:city":"Merchtem",
    "sg:orig_category":"GROENTEN AND FRUIT Varkenskwekers",
    "sg:phone":"+32 52 37 28 45",
    "sg:postcode":"1785",
    "sg:province":"Vlaams-Brabant",
    "wof:name":"Robert Van Den Broeck",
    "wof:placetype":"venue"
},
  "geometry": {"coordinates":[4.2533102036,50.9658813477],"type":"Point"}
}