{
  "type": "Feature",
  "properties": {
    "addr:full":"Schotelven 28 Arendonk Antwerpen 2370",
    "addr:housenumber":"28",
    "addr:postcode":"2370",
    "addr:street":"Schotelven",
    "iso:country":"BE",
    "sg:address":"Schotelven 28",
    "sg:city":"Arendonk",
    "sg:classifiers":[
        {
            "category":"Building & Trades",
            "subcategory":"Construction",
            "type":"Services"
        }
    ],
    "sg:phone":"+32 14 67 83 82",
    "sg:postcode":"2370",
    "sg:province":"Antwerpen",
    "sg:tags":[
        "siemens",
        "fujitsu"
    ],
    "wof:name":"Diamond Computer",
    "wof:placetype":"venue"
},
  "geometry": {"coordinates":[5.0624761581,51.3158874512],"type":"Point"}
}