{
  "type": "Feature",
  "properties": {
    "iso:country":"BE",
    "sg:address":"Avenue De Tervueren 273b1",
    "sg:city":"Sint-pieters-woluwe/woluwe-saint-pierre",
    "sg:classifiers":[
        {
            "category":"Insurance",
            "subcategory":"Life Insurance",
            "type":"Services"
        }
    ],
    "sg:phone":"+32 2 773 08 11",
    "sg:postcode":"1150",
    "sg:province":"Bruxelles-Capitale",
    "sg:tags":[
        "compagnies",
        "habitation",
        "assurance",
        "vie"
    ],
    "wof:name":"Gerling-konzern Belgi\u00cb/gerling-konzern Belgique",
    "wof:placetype":"venue"
},
  "geometry": {"coordinates":[4.4072999954,50.8374786377],"type":"Point"}
}