{
  "type": "Feature",
  "properties": {
    "addr:full":"Rue De Fl\u00e9malle 244 Jemeppe-sur-meuse Li\u00e8ge 4101",
    "addr:housenumber":"244",
    "addr:postcode":"4101",
    "addr:street":"Rue De Fle\u0301Malle",
    "iso:country":"BE",
    "sg:address":"Rue De Fl\u00e9malle 244",
    "sg:city":"Jemeppe-sur-meuse",
    "sg:classifiers":[
        {
            "category":"Manufacturing",
            "subcategory":"Metals",
            "type":"Manufacturing & Wholesale Goods"
        }
    ],
    "sg:phone":"+32 4 233 17 05",
    "sg:postcode":"4101",
    "sg:province":"Li\u00e8ge",
    "sg:tags":[
        "pipe",
        "sheet",
        "-",
        "metalworking",
        "metallic",
        "metallurgy",
        "finished"
    ],
    "wof:name":"Techno Metal Europ Sa",
    "wof:placetype":"venue"
},
  "geometry": {"coordinates":[5.4864401817,50.6061210632],"type":"Point"}
}