{
  "type": "Feature",
  "properties": {
    "iso:country":"BE",
    "sg:address":"Kerkweg 13",
    "sg:city":"Aalst",
    "sg:orig_category":"Caf\u00e9s Sportclubs Sportterreinen and installaties behalve sportcentra",
    "sg:phone":"+32 52 35 58 80",
    "sg:postcode":"9310",
    "sg:province":"Oost-Vlaanderen",
    "wof:name":"Thor Kokerij Meldert",
    "wof:placetype":"venue"
},
  "geometry": {"coordinates":[4.0401887894,50.9379577637],"type":"Point"}
}