{
  "type": "Feature",
  "properties": {
    "addr:full":"Place Alphonse Bosch 11 Wavre Brabant Wallon 1300",
    "addr:housenumber":"11;1300",
    "addr:street":"Place Alphonse Bosch",
    "iso:country":"BE",
    "sg:address":"Place Alphonse Bosch 11",
    "sg:city":"Wavre",
    "sg:classifiers":[
        {
            "category":"Retail",
            "subcategory":"Repair Shop",
            "type":"Services"
        }
    ],
    "sg:phone":"+32 10 22 69 53",
    "sg:postcode":"1300",
    "sg:province":"Brabant Wallon",
    "sg:tags":[
        "-",
        "mainten",
        "watch",
        "clock"
    ],
    "wof:name":"Demaret Sprl",
    "wof:placetype":"venue"
},
  "geometry": {"coordinates":[4.6115369797,50.7141418457],"type":"Point"}
}