{
  "type": "Feature",
  "properties": {
    "addr:full":"Hofstraat 97-99 Gent Oost-Vlaanderen 9000",
    "addr:housenumber":"97-99",
    "addr:postcode":"9000",
    "addr:street":"Hofstraat;Oost-Vlaanderen",
    "iso:country":"BE",
    "sg:address":"Hofstraat 97-99",
    "sg:city":"Gent",
    "sg:classifiers":[
        {
            "category":"Professional",
            "subcategory":"Lawyer & Legal Services",
            "type":"Services"
        }
    ],
    "sg:phone":"+32 9 223 63 10",
    "sg:postcode":"9000",
    "sg:province":"Oost-Vlaanderen",
    "wof:name":"Onbekent Christine",
    "wof:placetype":"venue"
},
  "geometry": {"coordinates":[3.7297420502,51.0465354919],"type":"Point"}
}