{
  "type": "Feature",
  "properties": {
    "iso:country":"BE",
    "sg:address":"Dijkstraat 23",
    "sg:city":"Mol",
    "sg:classifiers":[
        {
            "category":"Building & Trades",
            "subcategory":"Landscaping Services",
            "type":"Services"
        }
    ],
    "sg:phone":"+32 14 31 62 34",
    "sg:postcode":"2400",
    "sg:province":"Antwerpen",
    "sg:tags":[
        "access",
        "pond",
        "laying-out",
        "-"
    ],
    "wof:name":"Nicasi-delien",
    "wof:placetype":"venue"
},
  "geometry": {"coordinates":[5.1556549072,51.2131652832],"type":"Point"}
}