{
  "type": "Feature",
  "properties": {
    "addr:full":"Marionetten 24 Kortrijk West-Vlaanderen 8500",
    "addr:housenumber":"24",
    "addr:postcode":"8500",
    "addr:street":"Marionetten",
    "iso:country":"BE",
    "sg:address":"Marionetten 24",
    "sg:city":"Kortrijk",
    "sg:orig_category":"Diverse bedrijfsbeheeradviesbureaus",
    "sg:phone":"+32 56 21 04 04",
    "sg:postcode":"8500",
    "sg:province":"West-Vlaanderen",
    "wof:name":"Doumanco",
    "wof:placetype":"venue"
},
  "geometry": {"coordinates":[3.2633869648,50.7976837158],"type":"Point"}
}