{
  "type": "Feature",
  "properties": {
    "addr:full":"Chauss\u00e9e De Waterloo 817 Bruxelles (uccle) Bruxelles-Capitale 1180",
    "addr:housenumber":"817",
    "addr:postcode":"1180",
    "addr:street":"Chausse\u0301E De Waterloo",
    "iso:country":"BE",
    "sg:address":"Chauss\u00e9e De Waterloo 817",
    "sg:city":"Bruxelles (uccle)",
    "sg:orig_category":"Non-Classified Establishments",
    "sg:phone":"+32 2 343 68 20",
    "sg:postcode":"1180",
    "sg:province":"Bruxelles-Capitale",
    "wof:name":"Cottages (l'atelier Des)",
    "wof:placetype":"venue"
},
  "geometry": {"coordinates":[4.3686928749,50.8108139038],"type":"Point"}
}