{
  "type": "Feature",
  "properties": {
    "addr:full":"Avenue De La Faisanderie 14 - Brussels Bruxelles-Capitale 1150",
    "addr:housenumber":"14",
    "addr:postcode":"1150",
    "addr:street":"Avenue De La Faisanderie",
    "iso:country":"BE",
    "sg:address":"Avenue De La Faisanderie 14 -",
    "sg:city":"Brussels",
    "sg:classifiers":[
        {
            "category":"Professional",
            "subcategory":"Art Services",
            "type":"Services"
        }
    ],
    "sg:phone":"+32 3 827 13 90",
    "sg:postcode":"1150",
    "sg:province":"Bruxelles-Capitale",
    "sg:tags":[
        "export-import"
    ],
    "wof:name":"Turkey Consulate",
    "wof:placetype":"venue"
},
  "geometry": {"coordinates":[4.4492330551,50.8223304749],"type":"Point"}
}