{
  "type": "Feature",
  "properties": {
    "iso:country":"BE",
    "sg:address":"Mechelsveldstraat 28",
    "sg:city":"Mechelen",
    "sg:orig_category":"D\u00e9taillants en pi\u00e8ces and accessoires de voitures",
    "sg:phone":"+32 15 41 39 20",
    "sg:postcode":"2800",
    "sg:province":"Antwerpen",
    "wof:name":"Lambrecht",
    "wof:placetype":"venue"
},
  "geometry": {"coordinates":[4.4718561172,51.0129852295],"type":"Point"}
}