{
  "type": "Feature",
  "properties": {
    "addr:full":"Rue Entre Les Gh\u00c8tes 19 Jodoigne Brabant Wallon 1370",
    "addr:housenumber":"19",
    "addr:postcode":"1370",
    "addr:street":"Rue Entre Les Ghe\u0300Tes",
    "iso:country":"BE",
    "sg:address":"Rue Entre Les Gh\u00c8tes 19",
    "sg:city":"Jodoigne",
    "sg:orig_category":"Schoonheidssalons",
    "sg:phone":"+32 10 81 03 94",
    "sg:postcode":"1370",
    "sg:province":"Brabant Wallon",
    "wof:name":"P. Dispy",
    "wof:placetype":"venue"
},
  "geometry": {"coordinates":[4.8861289024,50.7609138489],"type":"Point"}
}