{
  "type": "Feature",
  "properties": {
    "addr:full":"Rue Royale 73 Tournai Hainaut 7500",
    "addr:housenumber":"73",
    "addr:postcode":"7500",
    "addr:street":"Rue Royale",
    "iso:country":"BE",
    "sg:address":"Rue Royale 73",
    "sg:city":"Tournai",
    "sg:orig_category":"Ordinateurs and \u00e9quipement informatique. Electrom\u00e9nager, t\u00e9l\u00e9visions and radios",
    "sg:phone":"+32 69 21 00 17",
    "sg:postcode":"7500",
    "sg:province":"Hainaut",
    "wof:name":"Fe. Sapienza",
    "wof:placetype":"venue"
},
  "geometry": {"coordinates":[3.393214941,50.6099090576],"type":"Point"}
}