{
  "type": "Feature",
  "properties": {
    "addr:full":"Pelikaansstraat 69 Antwerpen Antwerpen 2018",
    "addr:housenumber":"69",
    "addr:postcode":"2018",
    "addr:street":"Pelikaansstraat",
    "iso:country":"BE",
    "sg:address":"Pelikaansstraat 69",
    "sg:city":"Antwerpen",
    "sg:orig_category":"Geschenken and souvenirs Juwelen and horloges",
    "sg:phone":"+32 3 226 49 79",
    "sg:postcode":"2018",
    "sg:province":"Antwerpen",
    "wof:name":"Huis Riki",
    "wof:placetype":"venue"
},
  "geometry": {"coordinates":[4.4208731651,51.2142677307],"type":"Point"}
}