{
  "type": "Feature",
  "properties": {
    "addr:full":"Gentsesteenweg 247 Asse Vlaams-Brabant 1730",
    "addr:housenumber":"247",
    "addr:postcode":"1730",
    "addr:street":"Gentsesteenweg",
    "iso:country":"BE",
    "sg:address":"Gentsesteenweg 247",
    "sg:city":"Asse",
    "sg:classifiers":[
        {
            "category":"Building & Trades",
            "subcategory":"Landscaping Services",
            "type":"Services"
        }
    ],
    "sg:phone":"+32 2 453 16 40",
    "sg:postcode":"1730",
    "sg:province":"Vlaams-Brabant",
    "sg:tags":[
        "architect",
        "landscape"
    ],
    "wof:name":"Debekker J",
    "wof:placetype":"venue"
},
  "geometry": {"coordinates":[4.1615581512,50.9204292297],"type":"Point"}
}