{
  "type": "Feature",
  "properties": {
    "addr:full":"Vierwindenlaan 26 Wemmel Vlaams-Brabant 1780",
    "addr:housenumber":"26",
    "addr:postcode":"1780",
    "addr:street":"Vierwindenlaan;Vlaams-Brabant",
    "iso:country":"BE",
    "sg:address":"Vierwindenlaan 26",
    "sg:city":"Wemmel",
    "sg:orig_category":"Artsen and specialisten",
    "sg:phone":"+32 2 460 34 88",
    "sg:postcode":"1780",
    "sg:province":"Vlaams-Brabant",
    "wof:name":"Philip Tavenier",
    "wof:placetype":"venue"
},
  "geometry": {"coordinates":[4.2906589508,50.9143791199],"type":"Point"}
}