{
  "type": "Feature",
  "properties": {
    "addr:full":"Hellegatstraat 11 Berlaar Antwerpen 2590",
    "addr:housenumber":"11",
    "addr:postcode":"2590",
    "addr:street":"Hellegatstraat",
    "iso:country":"BE",
    "sg:address":"Hellegatstraat 11",
    "sg:city":"Berlaar",
    "sg:classifiers":[
        {
            "category":"Retail",
            "subcategory":"Auto Repair",
            "type":"Services"
        }
    ],
    "sg:phone":"+32 3 484 41 14",
    "sg:postcode":"2590",
    "sg:province":"Antwerpen",
    "sg:tags":[
        "garage"
    ],
    "wof:name":"Ford-de Groof Garage",
    "wof:placetype":"venue"
},
  "geometry": {"coordinates":[4.6326432228,51.1077537537],"type":"Point"}
}