{
  "type": "Feature",
  "properties": {
    "addr:full":"Rue De Luttre 145 Courcelles Hainaut 6181",
    "addr:housenumber":"145",
    "addr:postcode":"6181",
    "addr:street":"Rue De Luttre",
    "iso:country":"BE",
    "sg:address":"Rue De Luttre 145",
    "sg:city":"Courcelles",
    "sg:orig_category":"Eleveurs de bovins",
    "sg:phone":"+32 71 84 48 27",
    "sg:postcode":"6181",
    "sg:province":"Hainaut",
    "wof:name":"Daniel Laurent",
    "wof:placetype":"venue"
},
  "geometry": {"coordinates":[4.3392062187,50.4911003113],"type":"Point"}
}