{
  "type": "Feature",
  "properties": {
    "addr:full":"Rue Artan 77 Bruxelles (schaerbeek) Bruxelles-Capitale 1030",
    "addr:housenumber":"77",
    "addr:postcode":"1030",
    "addr:street":"Rue Artan",
    "iso:country":"BE",
    "sg:address":"Rue Artan 77",
    "sg:city":"Bruxelles (schaerbeek)",
    "sg:classifiers":[
        {
            "category":"Health Services",
            "subcategory":"Health Practitioner",
            "type":"Services"
        }
    ],
    "sg:phone":"+32 2 242 98 48",
    "sg:postcode":"1030",
    "sg:province":"Bruxelles-Capitale",
    "sg:tags":[
        "physiotherapist"
    ],
    "wof:name":"Vanden Haezevelde Jean-marc",
    "wof:placetype":"venue"
},
  "geometry": {"coordinates":[4.3833918571,50.8548469543],"type":"Point"}
}