{
  "type": "Feature",
  "properties": {
    "iso:country":"BE",
    "sg:address":"Rue De La Station 75",
    "sg:city":"Fleurus",
    "sg:classifiers":[
        {
            "category":"Retail",
            "subcategory":"Funeral Services",
            "type":"Services"
        }
    ],
    "sg:phone":"+32 71 30 39 00",
    "sg:postcode":"6220",
    "sg:province":"Hainaut",
    "sg:tags":[
        "director"
    ],
    "wof:name":"Scc",
    "wof:placetype":"venue"
},
  "geometry": {"coordinates":[4.5471959114,50.483089447],"type":"Point"}
}