{
  "type": "Feature",
  "properties": {
    "iso:country":"BE",
    "sg:address":"Turnhoutseweg 29",
    "sg:city":"Geel",
    "sg:classifiers":[
        {
            "category":"Retail",
            "subcategory":"Auto Repair",
            "type":"Services"
        }
    ],
    "sg:phone":"+32 14 85 28 55",
    "sg:postcode":"2440",
    "sg:province":"Antwerpen",
    "sg:tags":[
        "breakdown",
        "automobile",
        "-",
        "recovery"
    ],
    "wof:name":"Marinus L & Zoon Bvba",
    "wof:placetype":"venue"
},
  "geometry": {"coordinates":[4.978946209,51.2064476013],"type":"Point"}
}