{
  "type": "Feature",
  "properties": {
    "addr:full":"Nieuwpoortsesteenweg 128 Oostende West-Vlaanderen 8400",
    "addr:housenumber":"128",
    "addr:postcode":"8400",
    "addr:street":"Nieuwpoortsesteenweg",
    "iso:country":"BE",
    "sg:address":"Nieuwpoortsesteenweg 128",
    "sg:city":"Oostende",
    "sg:orig_category":"Banques and organismes de cr\u00e9dit",
    "sg:phone":"+32 59 80 98 83",
    "sg:postcode":"8400",
    "sg:province":"West-Vlaanderen",
    "wof:name":"Dexia",
    "wof:placetype":"venue"
},
  "geometry": {"coordinates":[2.9034729004,51.2219429016],"type":"Point"}
}