{
  "type": "Feature",
  "properties": {
    "addr:full":"Heirweg 29 De Pinte Oost-Vlaanderen 9840",
    "addr:housenumber":"29",
    "addr:postcode":"9840",
    "addr:street":"Heirweg",
    "iso:country":"BE",
    "sg:address":"Heirweg 29",
    "sg:city":"De Pinte",
    "sg:orig_category":"Woningbouw",
    "sg:phone":"+32 9 385 62 86",
    "sg:postcode":"9840",
    "sg:province":"Oost-Vlaanderen",
    "wof:name":"Christiaan Schaubroeck",
    "wof:placetype":"venue"
},
  "geometry": {"coordinates":[3.6571490765,50.979347229],"type":"Point"}
}