{
  "type": "Feature",
  "properties": {
    "addr:full":"Kempenarestraat 53 Box 2 Sint-katelijne-waver Antwerpen 2860",
    "addr:housenumber":"53;2",
    "addr:postcode":"2860",
    "addr:street":"Kempenarestraat;Box",
    "iso:country":"BE",
    "sg:address":"Kempenarestraat 53 Box 2",
    "sg:city":"Sint-katelijne-waver",
    "sg:classifiers":[
        {
            "category":"Professional",
            "type":"Services"
        }
    ],
    "sg:phone":"+32 15 32 28 68",
    "sg:postcode":"2860",
    "sg:province":"Antwerpen",
    "sg:tags":[
        "packing",
        "-"
    ],
    "wof:name":"Euro Pool System Belgi\u00eb Bvba",
    "wof:placetype":"venue"
},
  "geometry": {"coordinates":[4.5195999146,51.0631103516],"type":"Point"}
}