{
  "type": "Feature",
  "properties": {
    "addr:full":"Rue Joseph Wauters 21 Waremme Li\u00e8ge 4300",
    "addr:housenumber":"21",
    "addr:postcode":"4300",
    "addr:street":"Rue Joseph Wauters",
    "iso:country":"BE",
    "sg:address":"Rue Joseph Wauters 21",
    "sg:city":"Waremme",
    "sg:orig_category":"Banken and kredietinstellingen",
    "sg:phone":"+32 19 32 30 02",
    "sg:postcode":"4300",
    "sg:province":"Li\u00e8ge",
    "wof:name":"Bacob",
    "wof:placetype":"venue"
},
  "geometry": {"coordinates":[5.2552990913,50.6973152161],"type":"Point"}
}