{
  "type": "Feature",
  "properties": {
    "addr:full":"Bruggestraat 68 Tielt West-Vlaanderen 8700",
    "addr:housenumber":"68",
    "addr:postcode":"8700",
    "addr:street":"Bruggestraat",
    "iso:country":"BE",
    "sg:address":"Bruggestraat 68",
    "sg:city":"Tielt",
    "sg:orig_category":"Fleurs and plantes",
    "sg:phone":"+32 51 40 01 55",
    "sg:postcode":"8700",
    "sg:province":"West-Vlaanderen",
    "wof:name":"Huis Mayflower",
    "wof:placetype":"venue"
},
  "geometry": {"coordinates":[3.3241550922,51.0026397705],"type":"Point"}
}