{
  "type": "Feature",
  "properties": {
    "addr:full":"Driekastanjelaarsstraat 28 Grimbergen Vlaams-Brabant 1850",
    "addr:housenumber":"28",
    "addr:postcode":"1850",
    "addr:street":"Driekastanjelaarsstraat",
    "iso:country":"BE",
    "sg:address":"Driekastanjelaarsstraat 28",
    "sg:city":"Grimbergen",
    "sg:classifiers":[
        {
            "category":"Building & Trades",
            "subcategory":"Construction",
            "type":"Services"
        }
    ],
    "sg:phone":"+32 2 270 84 77",
    "sg:postcode":"1850",
    "sg:province":"Vlaams-Brabant",
    "sg:tags":[
        "stair"
    ],
    "wof:name":"Franqui R",
    "wof:placetype":"venue"
},
  "geometry": {"coordinates":[4.3791718483,50.9329414368],"type":"Point"}
}