{
  "type": "Feature",
  "properties": {
    "iso:country":"BE",
    "sg:address":"Stationstraat 139",
    "sg:city":"Ardooie",
    "sg:orig_category":"Catering and organisatie van feesten Voedingsspeciaalzaken",
    "sg:phone":"+32 51 74 56 58",
    "sg:postcode":"8850",
    "sg:province":"West-Vlaanderen",
    "wof:name":"Traiteur Vanhecke",
    "wof:placetype":"venue"
},
  "geometry": {"coordinates":[3.2026400566,50.9848670959],"type":"Point"}
}