{
  "type": "Feature",
  "properties": {
    "addr:full":"W. Van Nassaustraat 18 Gent-centrum Oost-Vlaanderen 9000",
    "addr:housenumber":"18",
    "addr:postcode":"9000",
    "addr:street":"W. Van Nassaustraat;Oost-Vlaanderen",
    "iso:country":"BE",
    "sg:address":"W. Van Nassaustraat 18",
    "sg:city":"Gent-centrum",
    "sg:orig_category":"Advocaten and juridische adviseurs Balie van Gent",
    "sg:phone":"+32 9 221 00 44",
    "sg:postcode":"9000",
    "sg:province":"Oost-Vlaanderen",
    "wof:name":"Van Den Noortgaete Patricia",
    "wof:placetype":"venue"
},
  "geometry": {"coordinates":[3.7176680565,51.0396766663],"type":"Point"}
}