{
  "type": "Feature",
  "properties": {
    "iso:country":"BE",
    "sg:address":"Scharebrugstraat 171",
    "sg:city":"Blankenberge",
    "sg:classifiers":[
        {
            "category":"Science Facility",
            "type":"Public Place"
        }
    ],
    "sg:phone":"+32 50 41 92 12",
    "sg:postcode":"8370",
    "sg:province":"West-Vlaanderen",
    "sg:tags":[
        "commerce",
        "installation",
        "gr",
        "equipement",
        "pour",
        "r\u00e9sidentielle",
        "\u00e9lectrique",
        "diver"
    ],
    "wof:name":"Eddy Demeulenaere",
    "wof:placetype":"venue"
},
  "geometry": {"coordinates":[3.1277890205,51.3071594238],"type":"Point"}
}