{
  "type": "Feature",
  "properties": {
    "iso:country":"BE",
    "sg:address":"Sneppenlaan 26",
    "sg:city":"Maasmechelen",
    "sg:classifiers":[
        {
            "category":"Professional",
            "subcategory":"Detective & Security Services",
            "type":"Services"
        }
    ],
    "sg:phone":"+32 89 76 30 88",
    "sg:postcode":"3630",
    "sg:province":"Limburg",
    "sg:tags":[
        "installation",
        "alarm",
        "-",
        "system"
    ],
    "wof:name":"Raeven Elektriciteitswerken",
    "wof:placetype":"venue"
},
  "geometry": {"coordinates":[5.6758470535,50.960773468],"type":"Point"}
}