{
  "type": "Feature",
  "properties": {
    "iso:country":"BE",
    "sg:address":"Molenstraat 31",
    "sg:city":"Harelbeke",
    "sg:classifiers":[
        {
            "category":"Utilities",
            "subcategory":"Fuel Oil & Lpg",
            "type":"Services"
        }
    ],
    "sg:phone":"+32 56 70 48 49",
    "sg:postcode":"8530",
    "sg:province":"West-Vlaanderen",
    "wof:name":"Soetaert P",
    "wof:placetype":"venue"
},
  "geometry": {"coordinates":[3.2997910976,50.8603858948],"type":"Point"}
}