{
  "type": "Feature",
  "properties": {
    "iso:country":"BE",
    "sg:address":"Sint-annarei 19",
    "sg:city":"Brugge",
    "sg:classifiers":[
        {
            "category":"Health Services",
            "subcategory":"Dentist",
            "type":"Services"
        }
    ],
    "sg:phone":"+32 50 33 15 34",
    "sg:postcode":"8000",
    "sg:province":"West-Vlaanderen",
    "wof:name":"Persyn Leentje",
    "wof:placetype":"venue"
},
  "geometry": {"coordinates":[3.2298879623,51.2126159668],"type":"Point"}
}