{
  "type": "Feature",
  "properties": {
    "iso:country":"BE",
    "sg:address":"Bredestraat 71",
    "sg:city":"Kortenaken",
    "sg:orig_category":"Eleveurs and marchands de porcs",
    "sg:phone":"+32 16 77 71 26",
    "sg:postcode":"3471",
    "sg:province":"Vlaams-Brabant",
    "wof:name":"Andre Laermans",
    "wof:placetype":"venue"
},
  "geometry": {"coordinates":[4.9862952232,50.8678398132],"type":"Point"}
}