{
  "type": "Feature",
  "properties": {
    "addr:full":"En Hayeneux 83 Herstal Li\u00e8ge 4040",
    "addr:housenumber":"83",
    "addr:postcode":"4040",
    "iso:country":"BE",
    "sg:address":"En Hayeneux 83",
    "sg:city":"Herstal",
    "sg:classifiers":[
        {
            "category":"Personal",
            "subcategory":"Beauty Salon",
            "type":"Services"
        }
    ],
    "sg:phone":"+32 4 264 50 64",
    "sg:postcode":"4040",
    "sg:province":"Li\u00e8ge",
    "sg:tags":[
        "lady",
        "-",
        "hairdressing"
    ],
    "wof:name":"Coco Janel",
    "wof:placetype":"venue"
},
  "geometry": {"coordinates":[5.6191000938,50.6572799683],"type":"Point"}
}