{
  "type": "Feature",
  "properties": {
    "addr:full":"Kerkplein 3 Westerlo Antwerpen 2260",
    "addr:housenumber":"3",
    "addr:postcode":"2260",
    "addr:street":"Kerkplein",
    "iso:country":"BE",
    "sg:address":"Kerkplein 3",
    "sg:city":"Westerlo",
    "sg:classifiers":[
        {
            "category":"Fast Food",
            "type":"Food & Drink"
        }
    ],
    "sg:phone":"+32 14 54 07 23",
    "sg:postcode":"2260",
    "sg:province":"Antwerpen",
    "sg:tags":[
        "meeneem",
        "restaurant"
    ],
    "wof:name":"China Fong Shou",
    "wof:placetype":"venue"
},
  "geometry": {"coordinates":[4.9112768173,51.0883636475],"type":"Point"}
}