{
  "type": "Feature",
  "properties": {
    "iso:country":"BE",
    "sg:address":"Rue De Flandre 145",
    "sg:city":"Soignies (naast)",
    "sg:classifiers":[
        {
            "category":"Professional",
            "subcategory":"Accounting & Tax Preparation",
            "type":"Services"
        }
    ],
    "sg:phone":"+32 67 33 45 32",
    "sg:postcode":"7062",
    "sg:province":"Hainaut",
    "sg:tags":[
        "bookkeeper"
    ],
    "wof:name":"Gabriel J",
    "wof:placetype":"venue"
},
  "geometry": {"coordinates":[4.0996851921,50.5541000366],"type":"Point"}
}