{
  "type": "Feature",
  "properties": {
    "addr:full":"Vooruitgangstraat 21 Denderleeuw Oost-Vlaanderen 9473",
    "addr:housenumber":"21",
    "addr:postcode":"9473",
    "addr:street":"Vooruitgangstraat",
    "iso:country":"BE",
    "sg:address":"Vooruitgangstraat 21",
    "sg:city":"Denderleeuw",
    "sg:classifiers":[
        {
            "category":"Personal",
            "subcategory":"Beauty Salon",
            "type":"Services"
        }
    ],
    "sg:phone":"+32 53 66 66 25",
    "sg:postcode":"9473",
    "sg:province":"Oost-Vlaanderen",
    "sg:tags":[
        "de",
        "coiffure"
    ],
    "wof:name":"Nicole Van Den Borre",
    "wof:placetype":"venue"
},
  "geometry": {"coordinates":[4.0497322083,50.9014091492],"type":"Point"}
}