{
  "type": "Feature",
  "properties": {
    "addr:full":"Nereth 39a Baelen Li\u00e8ge 4837",
    "addr:housenumber":"39a",
    "addr:postcode":"4837",
    "addr:street":"Nereth",
    "iso:country":"BE",
    "sg:address":"Nereth 39a",
    "sg:city":"Baelen",
    "sg:classifiers":[
        {
            "category":"Building & Trades",
            "subcategory":"Construction",
            "type":"Services"
        }
    ],
    "sg:phone":"+32 87 76 45 39",
    "sg:postcode":"4837",
    "sg:province":"Li\u00e8ge",
    "sg:tags":[
        "carpenter"
    ],
    "wof:name":"Decker-nols",
    "wof:placetype":"venue"
},
  "geometry": {"coordinates":[5.9931650162,50.6438179016],"type":"Point"}
}