{
  "type": "Feature",
  "properties": {
    "iso:country":"BE",
    "sg:address":"Rue De Ninane 37",
    "sg:city":"Chaudfontaine (beaufays)",
    "sg:classifiers":[
        {
            "category":"Home & Garden",
            "subcategory":"Garden Supply",
            "type":"Retail Goods"
        }
    ],
    "sg:phone":"+32 4 368 62 65",
    "sg:postcode":"4052",
    "sg:province":"Li\u00e8ge",
    "sg:tags":[
        "lawn",
        "mower"
    ],
    "wof:name":"Foguenne Beaufays",
    "wof:placetype":"venue"
},
  "geometry": {"coordinates":[5.6392202377,50.5586051941],"type":"Point"}
}