{
  "type": "Feature",
  "properties": {
    "iso:country":"BE",
    "sg:address":"Wampenberg 227",
    "sg:city":"Arendonk",
    "sg:classifiers":[
        {
            "category":"Bakery",
            "type":"Food & Drink"
        }
    ],
    "sg:phone":"+32 14 67 74 46",
    "sg:postcode":"2370",
    "sg:province":"Antwerpen",
    "sg:tags":[
        "confectioner",
        "baker"
    ],
    "wof:name":"Tuytelaers",
    "wof:placetype":"venue"
},
  "geometry": {"coordinates":[5.0959401131,51.3309288025],"type":"Point"}
}