{
  "type": "Feature",
  "properties": {
    "iso:country":"BE",
    "sg:address":"Rue Purgatoire 111",
    "sg:city":"Pepinster",
    "sg:orig_category":"Benzinestations and brandstoffen",
    "sg:phone":"+32 87 31 14 96",
    "sg:postcode":"4860",
    "sg:province":"Li\u00e8ge",
    "wof:name":"Jet",
    "wof:placetype":"venue"
},
  "geometry": {"coordinates":[5.8349781036,50.5766830444],"type":"Point"}
}