{
  "type": "Feature",
  "properties": {
    "iso:country":"BE",
    "sg:address":"Steenweg Op Antwerpen 99",
    "sg:city":"Turnhout",
    "sg:orig_category":"Herstellingen and onderhoud van auto's Onderdelen and accessoires voor auto's",
    "sg:phone":"+32 14 42 35 20",
    "sg:postcode":"2300",
    "sg:province":"Antwerpen",
    "wof:name":"Midas",
    "wof:placetype":"venue"
},
  "geometry": {"coordinates":[4.9191098213,51.3189659119],"type":"Point"}
}