{
  "type": "Feature",
  "properties": {
    "addr:full":"Westvaartdijk 303 Grimbergen Vlaams-Brabant 1851",
    "addr:housenumber":"303",
    "addr:postcode":"1851",
    "addr:street":"Westvaartdijk",
    "iso:country":"BE",
    "sg:address":"Westvaartdijk 303",
    "sg:city":"Grimbergen",
    "sg:orig_category":"Postzegels, munten and trofee\u00ebn",
    "sg:phone":"+32 2 269 32 49",
    "sg:postcode":"1851",
    "sg:province":"Vlaams-Brabant",
    "wof:name":"Tavernier",
    "wof:placetype":"venue"
},
  "geometry": {"coordinates":[4.391315937,50.976146698],"type":"Point"}
}