{
  "type": "Feature",
  "properties": {
    "iso:country":"BE",
    "sg:address":"Rue Gromet 16",
    "sg:city":"Lobbes",
    "sg:classifiers":[
        {
            "category":"Communications",
            "subcategory":"Radio Station",
            "type":"Services"
        }
    ],
    "sg:phone":"+32 71 59 32 42",
    "sg:postcode":"6540",
    "sg:province":"Hainaut",
    "sg:tags":[
        "diffusion",
        "production",
        "de",
        "programme"
    ],
    "wof:name":"Radio Wallonie",
    "wof:placetype":"venue"
},
  "geometry": {"coordinates":[4.237432003,50.3696212769],"type":"Point"}
}