{
  "type": "Feature",
  "properties": {
    "addr:full":"Rue Des Tanneurs 1 Marche-en-famenne Luxembourg 6900",
    "addr:housenumber":"1",
    "addr:postcode":"6900",
    "addr:street":"Rue Des Tanneurs",
    "iso:country":"BE",
    "sg:address":"Rue Des Tanneurs 1",
    "sg:city":"Marche-en-famenne",
    "sg:orig_category":"M\u00e9decins and sp\u00e9cialistes",
    "sg:phone":"+32 84 32 13 14",
    "sg:postcode":"6900",
    "sg:province":"Luxembourg",
    "wof:name":"Martine Dubois",
    "wof:placetype":"venue"
},
  "geometry": {"coordinates":[5.3464431763,50.2271537781],"type":"Point"}
}