{
  "type": "Feature",
  "properties": {
    "addr:full":"Arthur Verhaegenstraat 11 Gent Oost-Vlaanderen 9000",
    "addr:housenumber":"11",
    "addr:postcode":"9000",
    "addr:street":"Arthur Verhaegenstraat;Oost-Vlaanderen",
    "iso:country":"BE",
    "sg:address":"Arthur Verhaegenstraat 11",
    "sg:city":"Gent",
    "sg:classifiers":[
        {
            "category":"Health Services",
            "subcategory":"Doctor",
            "type":"Services"
        }
    ],
    "sg:phone":"+32 9 238 41 36",
    "sg:postcode":"9000",
    "sg:province":"Oost-Vlaanderen",
    "sg:tags":[
        "psychotherapist",
        "psychoanalyst"
    ],
    "wof:name":"Duin M",
    "wof:placetype":"venue"
},
  "geometry": {"coordinates":[3.706635952,51.0267524719],"type":"Point"}
}