{
  "type": "Feature",
  "properties": {
    "iso:country":"BE",
    "sg:address":"Oosterloseweg 41",
    "sg:city":"Geel",
    "sg:classifiers":[
        {
            "category":"Home & Garden",
            "subcategory":"Garden Supply",
            "type":"Retail Goods"
        }
    ],
    "sg:phone":"+32 14 86 81 58",
    "sg:postcode":"2440",
    "sg:province":"Antwerpen",
    "wof:name":"Stijnen F",
    "wof:placetype":"venue"
},
  "geometry": {"coordinates":[4.9788861275,51.1113014221],"type":"Point"}
}