{
  "type": "Feature",
  "properties": {
    "iso:country":"BE",
    "sg:address":"Thonissenlaan 54ba7",
    "sg:city":"Hasselt",
    "sg:orig_category":"Persagentschappen",
    "sg:phone":"+32 11 23 56 54",
    "sg:postcode":"3500",
    "sg:province":"Limburg",
    "wof:name":"Koen Goris",
    "wof:placetype":"venue"
},
  "geometry": {"coordinates":[5.3344478607,50.9329414368],"type":"Point"}
}