{
  "type": "Feature",
  "properties": {
    "iso:country":"BE",
    "sg:address":"Stationsstraat 167",
    "sg:city":"Waasmunster",
    "sg:orig_category":"Hoisiery Goods",
    "sg:phone":"+32 52 46 23 82",
    "sg:postcode":"9250",
    "sg:province":"Oost-Vlaanderen",
    "wof:name":"De Sutter Nv",
    "wof:placetype":"venue"
},
  "geometry": {"coordinates":[4.1034312248,51.1150894165],"type":"Point"}
}