{
  "type": "Feature",
  "properties": {
    "addr:full":"Mechelsesteenweg 60 Rumst Antwerpen 2840",
    "addr:housenumber":"60",
    "addr:postcode":"2840",
    "addr:street":"Mechelsesteenweg",
    "iso:country":"BE",
    "sg:address":"Mechelsesteenweg 60",
    "sg:city":"Rumst",
    "sg:orig_category":"Producteurs de l\u00e9gumes",
    "sg:phone":"+32 15 31 24 00",
    "sg:postcode":"2840",
    "sg:province":"Antwerpen",
    "wof:name":"Pieter Verschueren",
    "wof:placetype":"venue"
},
  "geometry": {"coordinates":[4.4524297714,51.0789375305],"type":"Point"}
}