{
  "type": "Feature",
  "properties": {
    "iso:country":"BE",
    "sg:address":"Rue L\u00c9on Desmottes 19",
    "sg:city":"Frasnes-lez-anvaing",
    "sg:orig_category":"Boucheries",
    "sg:phone":"+32 69 86 65 81",
    "sg:postcode":"7911",
    "sg:province":"Hainaut",
    "wof:name":"Centrale Des Viandes",
    "wof:placetype":"venue"
},
  "geometry": {"coordinates":[3.6175189018,50.6655426025],"type":"Point"}
}