{
  "type": "Feature",
  "properties": {
    "iso:country":"BE",
    "sg:address":"Brusselstraat 5",
    "sg:city":"Dilbeek",
    "sg:orig_category":"Apotheken",
    "sg:phone":"+32 2 466 05 24",
    "sg:postcode":"1702",
    "sg:province":"Vlaams-Brabant",
    "wof:name":"Marc Scheerlinck",
    "wof:placetype":"venue"
},
  "geometry": {"coordinates":[4.2798600197,50.8671684265],"type":"Point"}
}