{
  "type": "Feature",
  "properties": {
    "iso:country":"BE",
    "sg:address":"Lauwbergstraat 51",
    "sg:city":"Menen (lauwe)",
    "sg:classifiers":[
        {
            "category":"Food & Beverages",
            "subcategory":"Liquor & Beverages",
            "type":"Retail Goods"
        }
    ],
    "sg:phone":"+32 56 42 40 01",
    "sg:postcode":"8930",
    "sg:province":"West-Vlaanderen",
    "sg:tags":[
        "-",
        "spirit",
        "wine"
    ],
    "wof:name":"'t Goe Leven",
    "wof:placetype":"venue"
},
  "geometry": {"coordinates":[3.1209149361,50.7961845398],"type":"Point"}
}