{
  "type": "Feature",
  "properties": {
    "addr:full":"Heirebaan 254 Ninove Oost-Vlaanderen 9400",
    "addr:housenumber":"254",
    "addr:postcode":"9400",
    "iso:country":"BE",
    "sg:address":"Heirebaan 254",
    "sg:city":"Ninove",
    "sg:orig_category":"Eleveurs de bovins",
    "sg:phone":"+32 54 33 26 02",
    "sg:postcode":"9400",
    "sg:province":"Oost-Vlaanderen",
    "wof:name":"Anna Goossens",
    "wof:placetype":"venue"
},
  "geometry": {"coordinates":[3.9957840443,50.7950325012],"type":"Point"}
}