{
  "type": "Feature",
  "properties": {
    "addr:full":"Rue Du Chaufour 49 Courcelles (gouy-lez-pi\u00e9ton) Hainaut 6181",
    "addr:housenumber":"49",
    "addr:postcode":"6181",
    "addr:street":"Rue Du Chaufour",
    "iso:country":"BE",
    "sg:address":"Rue Du Chaufour 49",
    "sg:city":"Courcelles (gouy-lez-pi\u00e9ton)",
    "sg:orig_category":"Non-Classified Establishments",
    "sg:phone":"+32 71 84 00 68",
    "sg:postcode":"6181",
    "sg:province":"Hainaut",
    "wof:name":"Chez Laurence & Vincent",
    "wof:placetype":"venue"
},
  "geometry": {"coordinates":[4.3238368034,50.4856185913],"type":"Point"}
}