{
  "type": "Feature",
  "properties": {
    "addr:full":"Eeckhoutdriesstraat 27 Temse Oost-Vlaanderen 9140",
    "addr:housenumber":"27",
    "addr:postcode":"9140",
    "addr:street":"Eeckhoutdriesstraat",
    "iso:country":"BE",
    "sg:address":"Eeckhoutdriesstraat 27",
    "sg:city":"Temse",
    "sg:orig_category":"Kapsalons",
    "sg:phone":"+32 3 771 40 89",
    "sg:postcode":"9140",
    "sg:province":"Oost-Vlaanderen",
    "wof:name":"Coiffure Suzy",
    "wof:placetype":"venue"
},
  "geometry": {"coordinates":[4.2091350555,51.1293563843],"type":"Point"}
}