{
  "type": "Feature",
  "properties": {
    "iso:country":"BE",
    "sg:address":"Dr. Andr\u00c9 Goffaertsstr. 20",
    "sg:city":"Aalst",
    "sg:orig_category":"Pain, p\u00e2tisseries and confiseries",
    "sg:phone":"+32 53 21 34 11",
    "sg:postcode":"9300",
    "sg:province":"Oost-Vlaanderen",
    "wof:name":"G. Wachtelaer",
    "wof:placetype":"venue"
},
  "geometry": {"coordinates":[4.0371260643,50.9298057556],"type":"Point"}
}