{
  "type": "Feature",
  "properties": {
    "iso:country":"BE",
    "sg:address":"Bonestraat 49ba",
    "sg:city":"Meulebeke",
    "sg:orig_category":"Producteurs de l\u00e9gumes",
    "sg:phone":"+32 51 48 50 05",
    "sg:postcode":"8760",
    "sg:province":"West-Vlaanderen",
    "wof:name":"Bernard Noppe",
    "wof:placetype":"venue"
},
  "geometry": {"coordinates":[3.305588007,50.9543266296],"type":"Point"}
}