{
  "type": "Feature",
  "properties": {
    "addr:full":"Bovenstraat 30 Bornem Antwerpen 2880",
    "addr:housenumber":"30",
    "addr:postcode":"2880",
    "addr:street":"Bovenstraat",
    "iso:country":"BE",
    "sg:address":"Bovenstraat 30",
    "sg:city":"Bornem",
    "sg:orig_category":"Banken and kredietinstellingen",
    "sg:phone":"+32 3 889 15 83",
    "sg:postcode":"2880",
    "sg:province":"Antwerpen",
    "wof:name":"Anhyp",
    "wof:placetype":"venue"
},
  "geometry": {"coordinates":[4.1931600571,51.0694007874],"type":"Point"}
}