{
  "type": "Feature",
  "properties": {
    "addr:full":"Hundelgemsesteenweg 359 Gent (ledeberg) Oost-Vlaanderen 9050",
    "addr:housenumber":"359",
    "addr:postcode":"9050",
    "addr:street":"Hundelgemsesteenweg",
    "iso:country":"BE",
    "sg:address":"Hundelgemsesteenweg 359",
    "sg:city":"Gent (ledeberg)",
    "sg:classifiers":[
        {
            "category":"Building & Trades",
            "subcategory":"Cleaning & Sanitation",
            "type":"Services"
        }
    ],
    "sg:phone":"+32 9 225 47 75",
    "sg:postcode":"9050",
    "sg:province":"Oost-Vlaanderen",
    "sg:tags":[
        "sweep",
        "chimney"
    ],
    "wof:name":"Dewaelsche & Zonen",
    "wof:placetype":"venue"
},
  "geometry": {"coordinates":[3.7486228943,51.0257835388],"type":"Point"}
}