{
  "type": "Feature",
  "properties": {
    "addr:full":"Steenweg 41 Asse Vlaams-Brabant 1730",
    "addr:housenumber":"41",
    "addr:postcode":"1730",
    "addr:street":"Steenweg",
    "iso:country":"BE",
    "sg:address":"Steenweg 41",
    "sg:city":"Asse",
    "sg:orig_category":"Tijdelijke werkgelegenheid and uitzendkantoren",
    "sg:phone":"+32 2 453 13 77",
    "sg:postcode":"1730",
    "sg:province":"Vlaams-Brabant",
    "wof:name":"Asb Interim",
    "wof:placetype":"venue"
},
  "geometry": {"coordinates":[4.2224397659,50.9028511047],"type":"Point"}
}