{
  "type": "Feature",
  "properties": {
    "iso:country":"BE",
    "sg:address":"Werfstraat 2",
    "sg:city":"Brussel/bruxelles",
    "sg:orig_category":"Zalen voor culturele evenementen",
    "sg:phone":"+32 2 223 77 03",
    "sg:postcode":"1000",
    "sg:province":"Bruxelles-Capitale",
    "wof:name":"C.c.c.",
    "wof:placetype":"venue"
},
  "geometry": {"coordinates":[4.3491120338,50.8564414978],"type":"Point"}
}