{
  "type": "Feature",
  "properties": {
    "iso:country":"BE",
    "sg:address":"F. Van Arteveldestraat 9",
    "sg:city":"Staden",
    "sg:orig_category":"Producteurs de l\u00e9gumes",
    "sg:phone":"+32 51 78 07 62",
    "sg:postcode":"8840",
    "sg:province":"West-Vlaanderen",
    "wof:name":"Willy Cool",
    "wof:placetype":"venue"
},
  "geometry": {"coordinates":[3.0145280361,50.933013916],"type":"Point"}
}