{
  "type": "Feature",
  "properties": {
    "addr:full":"Pont Aux Lions 15 Verviers Li\u00e8ge 4800",
    "addr:housenumber":"15",
    "addr:postcode":"4800",
    "addr:street":"Pont Aux Lions",
    "iso:country":"BE",
    "sg:address":"Pont Aux Lions 15",
    "sg:city":"Verviers",
    "sg:classifiers":[
        {
            "category":"Shopping",
            "subcategory":"Shoes",
            "type":"Retail Goods"
        }
    ],
    "sg:phone":"+32 87 39 87 15",
    "sg:postcode":"4800",
    "sg:province":"Li\u00e8ge",
    "sg:tags":[
        "slipper",
        "-"
    ],
    "wof:name":"Actuel Chaussures",
    "wof:placetype":"venue"
},
  "geometry": {"coordinates":[5.8618087769,50.5932312012],"type":"Point"}
}