{
  "type": "Feature",
  "properties": {
    "addr:full":"Rue De La Station 87 Soignies Hainaut 7060",
    "addr:housenumber":"87",
    "addr:postcode":"7060",
    "addr:street":"Rue De La Station",
    "iso:country":"BE",
    "sg:address":"Rue De La Station 87",
    "sg:city":"Soignies",
    "sg:classifiers":[
        {
            "category":"Insurance",
            "subcategory":"Insurance Agent",
            "type":"Services"
        }
    ],
    "sg:phone":"+32 67 34 74 11",
    "sg:postcode":"7060",
    "sg:province":"Hainaut",
    "sg:tags":[
        "verzekeringsmakelaars",
        "expert"
    ],
    "wof:name":"P&v",
    "wof:placetype":"venue"
},
  "geometry": {"coordinates":[4.0685539246,50.5743026733],"type":"Point"}
}