{
  "type": "Feature",
  "properties": {
    "addr:full":"Rue Des Robiniers 63 Mons (ciply) Hainaut 7024",
    "addr:housenumber":"63",
    "addr:postcode":"7024",
    "addr:street":"Rue Des Robiniers",
    "iso:country":"BE",
    "sg:address":"Rue Des Robiniers 63",
    "sg:city":"Mons (ciply)",
    "sg:classifiers":[
        {
            "category":"Organizations",
            "subcategory":"Community Association",
            "type":"Services"
        }
    ],
    "sg:phone":"+32 65 84 02 80",
    "sg:postcode":"7024",
    "sg:province":"Hainaut",
    "sg:tags":[
        "environment",
        "organisation",
        "-"
    ],
    "wof:name":"Environnement Et D\u00e9couvertes Asbl",
    "wof:placetype":"venue"
},
  "geometry": {"coordinates":[3.9425880909,50.4187431335],"type":"Point"}
}