{
  "type": "Feature",
  "properties": {
    "addr:full":"Jacob Besagestraat 59 Oostende West-Vlaanderen 8400",
    "addr:housenumber":"59",
    "addr:postcode":"8400",
    "addr:street":"Besagestraat",
    "iso:country":"BE",
    "sg:address":"Jacob Besagestraat 59",
    "sg:city":"Oostende",
    "sg:classifiers":[
        {
            "category":"Personal",
            "subcategory":"Psychics & Astrologers",
            "type":"Services"
        }
    ],
    "sg:phone":"+32 59 32 54 13",
    "sg:postcode":"8400",
    "sg:province":"West-Vlaanderen",
    "sg:tags":[
        "astrology"
    ],
    "wof:name":"Iris",
    "wof:placetype":"venue"
},
  "geometry": {"coordinates":[2.9126999378,51.2312583923],"type":"Point"}
}