{
  "type": "Feature",
  "properties": {
    "iso:country":"BE",
    "sg:address":"Rue Des Combattants 112",
    "sg:city":"La Hulpe",
    "sg:orig_category":"Openbare bibliotheken and archieven",
    "sg:phone":"+32 2 654 12 83",
    "sg:postcode":"1310",
    "sg:province":"Brabant Wallon",
    "wof:name":"Biblioth\u00c8que Publique",
    "wof:placetype":"venue"
},
  "geometry": {"coordinates":[4.4852781296,50.7309112549],"type":"Point"}
}