{
  "type": "Feature",
  "properties": {
    "addr:full":"Th. Van Cauwenberghslei 67 Schoten Antwerpen 2900",
    "addr:housenumber":"67",
    "addr:postcode":"2900",
    "addr:street":"Th. Van Cauwenberghslei",
    "iso:country":"BE",
    "sg:address":"Th. Van Cauwenberghslei 67",
    "sg:city":"Schoten",
    "sg:orig_category":"Tijdelijke werkgelegenheid and uitzendkantoren",
    "sg:phone":"+32 2 552 04 10",
    "sg:postcode":"2900",
    "sg:province":"Antwerpen",
    "wof:name":"Prolink (recruitment Specialists It, Tel",
    "wof:placetype":"venue"
},
  "geometry": {"coordinates":[4.3561310768,50.8471755981],"type":"Point"}
}