{
  "type": "Feature",
  "properties": {
    "addr:full":"Nachtegaalstraat 10 Herk-de-stad Limburg 3540",
    "addr:housenumber":"10",
    "addr:postcode":"3540",
    "addr:street":"Nachtegaalstraat",
    "iso:country":"BE",
    "sg:address":"Nachtegaalstraat 10",
    "sg:city":"Herk-de-stad",
    "sg:orig_category":"Rundveehouders Varkenskwekers",
    "sg:phone":"+32 13 55 29 26",
    "sg:postcode":"3540",
    "sg:province":"Limburg",
    "wof:name":"Cyrillus Surinx",
    "wof:placetype":"venue"
},
  "geometry": {"coordinates":[5.1659698486,50.9407691956],"type":"Point"}
}