{
  "type": "Feature",
  "properties": {
    "addr:full":"Posthoornstraat 59 Beringen (koersel) Limburg 3582",
    "addr:housenumber":"59",
    "addr:postcode":"3582",
    "addr:street":"Posthoornstraat",
    "iso:country":"BE",
    "sg:address":"Posthoornstraat 59",
    "sg:city":"Beringen (koersel)",
    "sg:classifiers":[
        {
            "category":"Shopping",
            "subcategory":"Computers & Home Electronics",
            "type":"Retail Goods"
        }
    ],
    "sg:phone":"+32 11 42 27 34",
    "sg:postcode":"3582",
    "sg:province":"Limburg",
    "sg:tags":[
        "-",
        "television",
        "radio"
    ],
    "wof:name":"Elektro Meeus",
    "wof:placetype":"venue"
},
  "geometry": {"coordinates":[5.2708749771,51.0595359802],"type":"Point"}
}