{
  "type": "Feature",
  "properties": {
    "iso:country":"BE",
    "sg:address":"Avenue Mahatma Gandhi 5",
    "sg:city":"Sint-jans-molenbeek/molenbeek-saint-jean",
    "sg:orig_category":"Centres sportifs. Installations and terrains de sport hors centres sportifs",
    "sg:phone":"+32 2 412 37 93",
    "sg:postcode":"1080",
    "sg:province":"Bruxelles-Capitale",
    "wof:name":"Sporthal Sippelberg",
    "wof:placetype":"venue"
},
  "geometry": {"coordinates":[4.3264579773,50.8597335815],"type":"Point"}
}