{
  "type": "Feature",
  "properties": {
    "addr:full":"Place Du Martyr 49 Verviers Li\u00e8ge 4800",
    "addr:housenumber":"49",
    "addr:postcode":"4800",
    "addr:street":"Place Du Martyr",
    "iso:country":"BE",
    "sg:address":"Place Du Martyr 49",
    "sg:city":"Verviers",
    "sg:classifiers":[
        {
            "category":"Arena",
            "subcategory":"Sports Club",
            "type":"Entertainment"
        }
    ],
    "sg:phone":"+32 87 33 11 95",
    "sg:postcode":"4800",
    "sg:province":"Li\u00e8ge",
    "sg:tags":[
        "de"
    ],
    "wof:name":"Glaucos",
    "wof:placetype":"venue"
},
  "geometry": {"coordinates":[5.8600001335,50.5930976868],"type":"Point"}
}