{
  "type": "Feature",
  "properties": {
    "addr:full":"Puttebroekstraat 41 Leuven Vlaams-Brabant 3012",
    "addr:housenumber":"41",
    "addr:postcode":"3012",
    "addr:street":"Puttebroekstraat",
    "iso:country":"BE",
    "sg:address":"Puttebroekstraat 41",
    "sg:city":"Leuven",
    "sg:orig_category":"Agences de publicit\u00e9",
    "sg:phone":"+32 16 44 98 12",
    "sg:postcode":"3012",
    "sg:province":"Vlaams-Brabant",
    "wof:name":"Adrenaline Advertising",
    "wof:placetype":"venue"
},
  "geometry": {"coordinates":[4.7280302048,50.9222946167],"type":"Point"}
}