{
  "type": "Feature",
  "properties": {
    "iso:country":"BE",
    "sg:address":"Chauss\u00c9e De W\u00c9gimont 93",
    "sg:city":"Soumagne",
    "sg:orig_category":"DIVERSE RECREATIEVE ACTIVITEITEN",
    "sg:phone":"+32 4 377 21 82",
    "sg:postcode":"4630",
    "sg:province":"Li\u00e8ge",
    "wof:name":"Club Philat\u00c9lique",
    "wof:placetype":"venue"
},
  "geometry": {"coordinates":[5.7388620377,50.6098442078],"type":"Point"}
}