{
  "type": "Feature",
  "properties": {
    "iso:country":"BE",
    "sg:address":"Chemin Des Deux Pays 26",
    "sg:city":"Namur (malonne)",
    "sg:classifiers":[
        {
            "category":"Building & Trades",
            "subcategory":"Construction",
            "type":"Services"
        }
    ],
    "sg:phone":"+32 81 44 10 28",
    "sg:postcode":"5020",
    "sg:province":"Namur",
    "sg:tags":[
        "carpenter"
    ],
    "wof:name":"Debouck M",
    "wof:placetype":"venue"
},
  "geometry": {"coordinates":[4.7849459648,50.4168319702],"type":"Point"}
}