{
  "type": "Feature",
  "properties": {
    "addr:full":"Schauwegemstraat 27 Melle Oost-Vlaanderen 9090",
    "addr:housenumber":"27",
    "addr:postcode":"9090",
    "addr:street":"Schauwegemstraat",
    "iso:country":"BE",
    "sg:address":"Schauwegemstraat 27",
    "sg:city":"Melle",
    "sg:classifiers":[
        {
            "category":"Personal",
            "subcategory":"Beauty Salon",
            "type":"Services"
        }
    ],
    "sg:phone":"+32 475 44 77 85",
    "sg:postcode":"9090",
    "sg:province":"Oost-Vlaanderen",
    "sg:tags":[
        "lady",
        "-",
        "hairdressing"
    ],
    "wof:name":"Pascal Thuiskapper",
    "wof:placetype":"venue"
},
  "geometry": {"coordinates":[3.7996358871,51.0007553101],"type":"Point"}
}