{
  "type": "Feature",
  "properties": {
    "addr:full":"Azalealaan 32 Temse Oost-Vlaanderen 9140",
    "addr:housenumber":"32",
    "addr:postcode":"9140",
    "addr:street":"Azalealaan",
    "iso:country":"BE",
    "sg:address":"Azalealaan 32",
    "sg:city":"Temse",
    "sg:orig_category":"Sportclubs Sportterreinen and installaties behalve sportcentra",
    "sg:phone":"+32 3 771 03 63",
    "sg:postcode":"9140",
    "sg:province":"Oost-Vlaanderen",
    "wof:name":"K.s.v. Temse",
    "wof:placetype":"venue"
},
  "geometry": {"coordinates":[4.197119236,51.1262397766],"type":"Point"}
}