{
  "type": "Feature",
  "properties": {
    "iso:country":"BE",
    "sg:address":"Trou De Bra 29",
    "sg:city":"Lierneux",
    "sg:orig_category":"Boucheries",
    "sg:phone":"+32 86 43 32 45",
    "sg:postcode":"4990",
    "sg:province":"Li\u00e8ge",
    "wof:name":"Boucherie Jose Michel",
    "wof:placetype":"venue"
},
  "geometry": {"coordinates":[5.7343831062,50.3231124878],"type":"Point"}
}