{
  "type": "Feature",
  "properties": {
    "addr:full":"Schildesteenweg 14 Ranst Antwerpen 2520",
    "addr:housenumber":"14",
    "addr:postcode":"2520",
    "addr:street":"Schildesteenweg",
    "iso:country":"BE",
    "sg:address":"Schildesteenweg 14",
    "sg:city":"Ranst",
    "sg:orig_category":"Overheidsdiensten",
    "sg:phone":"+32 3 385 38 88",
    "sg:postcode":"2520",
    "sg:province":"Antwerpen",
    "wof:name":"O.c.m.w.",
    "wof:placetype":"venue"
},
  "geometry": {"coordinates":[4.5978078842,51.2139587402],"type":"Point"}
}