{
  "type": "Feature",
  "properties": {
    "addr:full":"Rue Jean Fran\u00e7ois 24 Huy (ben-ahin) Li\u00e8ge 4500",
    "addr:housenumber":"24",
    "addr:postcode":"4500",
    "addr:street":"Rue Jean Franc\u0327Ois",
    "iso:country":"BE",
    "sg:address":"Rue Jean Fran\u00e7ois 24",
    "sg:city":"Huy (ben-ahin)",
    "sg:classifiers":[
        {
            "category":"Building & Trades",
            "subcategory":"Landscaping Services",
            "type":"Services"
        }
    ],
    "sg:phone":"+32 85 25 08 66",
    "sg:postcode":"4500",
    "sg:province":"Li\u00e8ge",
    "sg:tags":[
        "gardening",
        "garden",
        "maintenance"
    ],
    "wof:name":"Pierre B",
    "wof:placetype":"venue"
},
  "geometry": {"coordinates":[5.2262701988,50.5102996826],"type":"Point"}
}