{
  "type": "Feature",
  "properties": {
    "addr:full":"Kortrijkstraat 66 Deinze Oost-Vlaanderen 9800",
    "addr:housenumber":"66",
    "addr:postcode":"9800",
    "addr:street":"Kortrijkstraat",
    "iso:country":"BE",
    "sg:address":"Kortrijkstraat 66",
    "sg:city":"Deinze",
    "sg:classifiers":[
        {
            "category":"Personal",
            "subcategory":"Beauty Salon",
            "type":"Services"
        }
    ],
    "sg:phone":"+32 9 386 37 86",
    "sg:postcode":"9800",
    "sg:province":"Oost-Vlaanderen",
    "sg:tags":[
        "de",
        "coiffure"
    ],
    "wof:name":"Coiffure Shirley",
    "wof:placetype":"venue"
},
  "geometry": {"coordinates":[3.5278549194,50.9771842957],"type":"Point"}
}