{
  "type": "Feature",
  "properties": {
    "iso:country":"BE",
    "sg:address":"Clos Prom\u00e9th\u00e9e 15",
    "sg:city":"Bruxelles (woluwe-saint-lambert)",
    "sg:classifiers":[
        {
            "category":"Professional",
            "subcategory":"Accounting & Tax Preparation",
            "type":"Services"
        }
    ],
    "sg:phone":"+32 2 762 79 88",
    "sg:postcode":"1200",
    "sg:province":"Bruxelles-Capitale",
    "sg:tags":[
        "bookkeeper"
    ],
    "wof:name":"Melotte C",
    "wof:placetype":"venue"
},
  "geometry": {"coordinates":[4.4579110146,50.8462982178],"type":"Point"}
}