{
  "type": "Feature",
  "properties": {
    "iso:country":"BE",
    "sg:address":"Nieuwelaan 42-44",
    "sg:city":"Hamme",
    "sg:orig_category":"Produits c\u00e9r\u00e9aliers Fab",
    "sg:phone":"+32 52 48 01 41",
    "sg:postcode":"9220",
    "sg:province":"Oost-Vlaanderen",
    "wof:name":"Beyer",
    "wof:placetype":"venue"
},
  "geometry": {"coordinates":[4.1260018349,51.0980644226],"type":"Point"}
}