{
  "type": "Feature",
  "properties": {
    "iso:country":"BE",
    "sg:address":"Rue De L'arbre 142",
    "sg:city":"Fourons (fouron-le-comte)",
    "sg:classifiers":[
        {
            "category":"Insurance",
            "subcategory":"Insurance Agent",
            "type":"Services"
        }
    ],
    "sg:phone":"+32 4 381 11 27",
    "sg:postcode":"3798",
    "sg:province":"Limburg",
    "sg:tags":[
        "broker"
    ],
    "wof:name":"Lang N",
    "wof:placetype":"venue"
},
  "geometry": {"coordinates":[5.7607951164,50.7586212158],"type":"Point"}
}