{
  "type": "Feature",
  "properties": {
    "iso:country":"BE",
    "sg:address":"Rue Des Gravelles 85 Box 2",
    "sg:city":"Ch\u00e2telet",
    "sg:classifiers":[
        {
            "category":"Social Services",
            "subcategory":"Job Training",
            "type":"Services"
        }
    ],
    "sg:phone":"+32 497 77 47 47",
    "sg:postcode":"6200",
    "sg:province":"Hainaut",
    "sg:tags":[
        "personnel"
    ],
    "wof:name":"Step Sales & Consulting",
    "wof:placetype":"venue"
},
  "geometry": {"coordinates":[4.5226998329,50.4074897766],"type":"Point"}
}