{
  "type": "Feature",
  "properties": {
    "addr:full":"Trooststraat 103 Schaarbeek/schaerbeek Bruxelles-Capitale 1030",
    "addr:housenumber":"103",
    "addr:postcode":"1030",
    "addr:street":"Trooststraat",
    "iso:country":"BE",
    "sg:address":"Trooststraat 103",
    "sg:city":"Schaarbeek/schaerbeek",
    "sg:orig_category":"Marktonderzoekbureaus",
    "sg:phone":"+32 2 240 96 20",
    "sg:postcode":"1030",
    "sg:province":"Bruxelles-Capitale",
    "wof:name":"Communication Busin. Int.",
    "wof:placetype":"venue"
},
  "geometry": {"coordinates":[4.3800349236,50.8542404175],"type":"Point"}
}