{
  "type": "Feature",
  "properties": {
    "iso:country":"BE",
    "sg:address":"Rue Grande Dr\u00e8ve 40",
    "sg:city":"Chi\u00e8vres (ladeuze)",
    "sg:classifiers":[
        {
            "category":"Shopping",
            "subcategory":"Antiques",
            "type":"Retail Goods"
        }
    ],
    "sg:phone":"+32 68 65 76 78",
    "sg:postcode":"7950",
    "sg:province":"Hainaut",
    "wof:name":"Debuysscher C.",
    "wof:placetype":"venue"
},
  "geometry": {"coordinates":[3.780616045,50.567150116],"type":"Point"}
}