{
  "type": "Feature",
  "properties": {
    "iso:country":"BE",
    "sg:address":"Oudenaardsesteenweg 141",
    "sg:city":"Avelgem",
    "sg:orig_category":"Activit\u00e9s d\u00b4action sociale sans h\u00e9bergement",
    "sg:phone":"+32 56 64 40 91",
    "sg:postcode":"8580",
    "sg:province":"West-Vlaanderen",
    "wof:name":"Rode Kruis Avelgem",
    "wof:placetype":"venue"
},
  "geometry": {"coordinates":[3.460860014,50.7796440125],"type":"Point"}
}