{
  "type": "Feature",
  "properties": {
    "iso:country":"BE",
    "sg:address":"Ieperstraat 106",
    "sg:city":"Menen",
    "sg:orig_category":"Newspapers, magazines, periodicals - Distribution",
    "sg:phone":"+32 56 51 23 78",
    "sg:postcode":"8930",
    "sg:province":"West-Vlaanderen",
    "wof:name":"Pipas Teledac Bvba",
    "wof:placetype":"venue"
},
  "geometry": {"coordinates":[3.1144080162,50.7976531982],"type":"Point"}
}