{
  "type": "Feature",
  "properties": {
    "iso:country":"BE",
    "sg:address":"Avenue Charles Deli\u00c8ge 31",
    "sg:city":"Binche",
    "sg:classifiers":[
        {
            "category":"Cafe",
            "type":"Food & Drink"
        }
    ],
    "sg:phone":"+32 64 33 11 82",
    "sg:postcode":"7130",
    "sg:province":"Hainaut",
    "sg:tags":[
        "caf\u00e9s"
    ],
    "wof:name":"Liliane Boccar",
    "wof:placetype":"venue"
},
  "geometry": {"coordinates":[4.1678118706,50.4157371521],"type":"Point"}
}