{
  "type": "Feature",
  "properties": {
    "iso:country":"BE",
    "sg:address":"Rue Delcampe 84",
    "sg:city":"Binche",
    "sg:orig_category":"Rev\u00eatements pour sols and murs",
    "sg:phone":"+32 64 36 71 46",
    "sg:postcode":"7130",
    "sg:province":"Hainaut",
    "wof:name":"Patrice Draize",
    "wof:placetype":"venue"
},
  "geometry": {"coordinates":[4.1076478958,50.4355316162],"type":"Point"}
}