{
  "type": "Feature",
  "properties": {
    "iso:country":"BE",
    "sg:address":"Beverestraat 74",
    "sg:city":"Oudenaarde",
    "sg:classifiers":[
        {
            "category":"Food & Beverages",
            "subcategory":"Cheese",
            "type":"Retail Goods"
        }
    ],
    "sg:phone":"+32 55 31 88 24",
    "sg:postcode":"9700",
    "sg:province":"Oost-Vlaanderen",
    "sg:tags":[
        "-"
    ],
    "wof:name":"Winkelke ('t)",
    "wof:placetype":"venue"
},
  "geometry": {"coordinates":[3.5981750488,50.8495407104],"type":"Point"}
}