{
  "type": "Feature",
  "properties": {
    "addr:full":"Meensesteenweg 301 Kortrijk (bissegem) West-Vlaanderen 8501",
    "addr:housenumber":"301",
    "addr:postcode":"8501",
    "addr:street":"Meensesteenweg",
    "iso:country":"BE",
    "sg:address":"Meensesteenweg 301",
    "sg:city":"Kortrijk (bissegem)",
    "sg:classifiers":[
        {
            "category":"Personal",
            "subcategory":"Beauty Salon",
            "type":"Services"
        }
    ],
    "sg:phone":"+32 56 35 02 90",
    "sg:postcode":"8501",
    "sg:province":"West-Vlaanderen",
    "sg:tags":[
        "lady",
        "-",
        "hairdressing"
    ],
    "wof:name":"Larielle",
    "wof:placetype":"venue"
},
  "geometry": {"coordinates":[3.2319369316,50.8245735168],"type":"Point"}
}