{
  "type": "Feature",
  "properties": {
    "addr:full":"Ham 31 Gent Oost-Vlaanderen 9000",
    "addr:housenumber":"31",
    "addr:postcode":"9000",
    "addr:street":"Ham;Oost-Vlaanderen",
    "iso:country":"BE",
    "sg:address":"Ham 31",
    "sg:city":"Gent",
    "sg:classifiers":[
        {
            "category":"Food & Beverages",
            "subcategory":"Liquor & Beverages",
            "type":"Retail Goods"
        }
    ],
    "sg:phone":"+32 9 225 34 13",
    "sg:postcode":"9000",
    "sg:province":"Oost-Vlaanderen",
    "sg:tags":[
        "-",
        "spirit",
        "wine"
    ],
    "wof:name":"Mobile Liquor Store",
    "wof:placetype":"venue"
},
  "geometry": {"coordinates":[3.7328560352,51.0577125549],"type":"Point"}
}