{
  "type": "Feature",
  "properties": {
    "addr:full":"Conterdijk 19 Koksijde West-Vlaanderen 8670",
    "addr:housenumber":"19",
    "addr:postcode":"8670",
    "addr:street":"Conterdijk",
    "iso:country":"BE",
    "sg:address":"Conterdijk 19",
    "sg:city":"Koksijde",
    "sg:orig_category":"Travaux de pl\u00e2trage",
    "sg:phone":"+32 58 31 15 49",
    "sg:postcode":"8670",
    "sg:province":"West-Vlaanderen",
    "wof:name":"Maurice Boucquez",
    "wof:placetype":"venue"
},
  "geometry": {"coordinates":[2.6963279247,51.1042098999],"type":"Point"}
}