{
  "type": "Feature",
  "properties": {
    "iso:country":"BE",
    "sg:address":"Avenue Clays 32",
    "sg:city":"Schaarbeek/schaerbeek",
    "sg:orig_category":"Pi\u00e8ces and accessoires de v\u00e9hicules automobiles Gr",
    "sg:phone":"+32 2 242 17 69",
    "sg:postcode":"1030",
    "sg:province":"Bruxelles-Capitale",
    "wof:name":"J P V Diffusion",
    "wof:placetype":"venue"
},
  "geometry": {"coordinates":[4.3819870949,50.8540992737],"type":"Point"}
}