{
  "type": "Feature",
  "properties": {
    "iso:country":"BE",
    "sg:address":"Nieuwstraat 22",
    "sg:city":"Maldegem",
    "sg:orig_category":"M\u00e9decins and sp\u00e9cialistes",
    "sg:phone":"+32 50 71 45 95",
    "sg:postcode":"9990",
    "sg:province":"Oost-Vlaanderen",
    "wof:name":"Veerle Beirnaert",
    "wof:placetype":"venue"
},
  "geometry": {"coordinates":[3.4463469982,51.2078018188],"type":"Point"}
}