{
  "type": "Feature",
  "properties": {
    "addr:full":"Koningin Astridlaan 25 Lier Antwerpen 2500",
    "addr:housenumber":"25",
    "addr:postcode":"2500",
    "addr:street":"Koningin Astridlaan",
    "iso:country":"BE",
    "sg:address":"Koningin Astridlaan 25",
    "sg:city":"Lier",
    "sg:orig_category":"Solariums",
    "sg:phone":"+32 15 27 02 46",
    "sg:postcode":"2500",
    "sg:province":"Antwerpen",
    "wof:name":"Sunbada Zonnecenter",
    "wof:placetype":"venue"
},
  "geometry": {"coordinates":[4.5781822205,51.127407074],"type":"Point"}
}