{
  "type": "Feature",
  "properties": {
    "iso:country":"BE",
    "sg:address":"Avenue Du Diamant 7",
    "sg:city":"Bruxelles",
    "sg:classifiers":[
        {
            "category":"Restaurant",
            "type":"Food & Drink"
        }
    ],
    "sg:phone":"+32 2 736 49 22",
    "sg:postcode":"1030",
    "sg:province":"Bruxelles-Capitale",
    "wof:name":"Athenien",
    "wof:placetype":"venue"
},
  "geometry": {"coordinates":[4.3913807869,50.8531761169],"type":"Point"}
}