{
  "type": "Feature",
  "properties": {
    "iso:country":"BE",
    "sg:address":"Troon 18",
    "sg:city":"Grobbendonk",
    "sg:classifiers":[
        {
            "category":"Sports & Exercise",
            "subcategory":"Sports Center",
            "type":"Entertainment"
        }
    ],
    "sg:phone":"+32 14 50 10 47",
    "sg:postcode":"2280",
    "sg:province":"Antwerpen",
    "sg:tags":[
        "terrain",
        "hors",
        "de",
        "installation",
        "sportifs"
    ],
    "wof:name":"Euro Horse Axel Verlooy",
    "wof:placetype":"venue"
},
  "geometry": {"coordinates":[4.7785401344,51.1858291626],"type":"Point"}
}