{
  "type": "Feature",
  "properties": {
    "addr:full":"Nijverheidslaan 21 Dilsen Limburg 3650",
    "addr:housenumber":"21",
    "addr:postcode":"3650",
    "addr:street":"Nijverheidslaan",
    "iso:country":"BE",
    "sg:address":"Nijverheidslaan 21",
    "sg:city":"Dilsen",
    "sg:orig_category":"HERSTELLING ELEKTRISCHE HUISHOUDAPPARATEN Huishoudapparaten, televisies and radio's Microsoft Teleco",
    "sg:phone":"+32 89 75 58 10",
    "sg:postcode":"3650",
    "sg:province":"Limburg",
    "wof:name":"Leco",
    "wof:placetype":"venue"
},
  "geometry": {"coordinates":[5.7082481384,51.019443512],"type":"Point"}
}