{
  "type": "Feature",
  "properties": {
    "iso:country":"BE",
    "sg:address":"Chauss\u00c9e De Bruxelles 108",
    "sg:city":"Ath",
    "sg:orig_category":"Bloemen and planten",
    "sg:phone":"+32 68 28 22 55",
    "sg:postcode":"7800",
    "sg:province":"Hainaut",
    "wof:name":"Fleuriste Derumier",
    "wof:placetype":"venue"
},
  "geometry": {"coordinates":[3.7887160778,50.6337547302],"type":"Point"}
}