{
  "type": "Feature",
  "properties": {
    "addr:full":"Rue Royale 161-163 Saint-josse-ten-node Bruxelles-Capitale 1210",
    "addr:postcode":"161-163;1210",
    "addr:street":"Rue Royale",
    "iso:country":"BE",
    "sg:address":"Rue Royale 161-163",
    "sg:city":"Saint-josse-ten-node",
    "sg:orig_category":"Instruments de musique",
    "sg:phone":"+32 2 218 38 86",
    "sg:postcode":"1210",
    "sg:province":"Bruxelles-Capitale",
    "wof:name":"Kaufmann Pianos",
    "wof:placetype":"venue"
},
  "geometry": {"coordinates":[6.0982899666,46.2723312378],"type":"Point"}
}