{
  "type": "Feature",
  "properties": {
    "iso:country":"BE",
    "sg:address":"Ganzendries 14",
    "sg:city":"Tienen",
    "sg:orig_category":"Kapsalons",
    "sg:phone":"+32 16 81 73 32",
    "sg:postcode":"3300",
    "sg:province":"Vlaams-Brabant",
    "wof:name":"Coiffure Agnes",
    "wof:placetype":"venue"
},
  "geometry": {"coordinates":[4.9915242195,50.8288421631],"type":"Point"}
}