{
  "type": "Feature",
  "properties": {
    "addr:full":"Mechelbaan 841 Putte Antwerpen 2580",
    "addr:housenumber":"841",
    "addr:postcode":"2580",
    "addr:street":"Mechelbaan",
    "iso:country":"BE",
    "sg:address":"Mechelbaan 841",
    "sg:city":"Putte",
    "sg:classifiers":[
        {
            "category":"Building & Trades",
            "subcategory":"Cleaning & Sanitation",
            "type":"Services"
        }
    ],
    "sg:phone":"+32 477 63 23 59",
    "sg:postcode":"2580",
    "sg:province":"Antwerpen",
    "sg:tags":[
        "fa\u00e7ade",
        "maintenance"
    ],
    "wof:name":"D.k.m.",
    "wof:placetype":"venue"
},
  "geometry": {"coordinates":[4.572988987,51.0378189087],"type":"Point"}
}