{
  "type": "Feature",
  "properties": {
    "addr:full":"Diestersteenweg 308 Maaseik Limburg 3680",
    "addr:housenumber":"308",
    "addr:postcode":"3680",
    "addr:street":"Diestersteenweg",
    "iso:country":"BE",
    "sg:address":"Diestersteenweg 308",
    "sg:city":"Maaseik",
    "sg:classifiers":[
        {
            "category":"Retail",
            "subcategory":"Auto Repair",
            "type":"Services"
        }
    ],
    "sg:phone":"+32 89 56 28 61",
    "sg:postcode":"3680",
    "sg:province":"Limburg",
    "sg:tags":[
        "garage"
    ],
    "wof:name":"May",
    "wof:placetype":"venue"
},
  "geometry": {"coordinates":[5.7483038902,51.1019287109],"type":"Point"}
}