{
  "type": "Feature",
  "properties": {
    "iso:country":"BE",
    "sg:address":"Klaverbladstraat 7-10 Box 726",
    "sg:city":"Lummen",
    "sg:classifiers":[
        {
            "category":"Communications",
            "subcategory":"Film & Video Production",
            "type":"Services"
        }
    ],
    "sg:phone":"+32 476 99 54 34",
    "sg:postcode":"3560",
    "sg:province":"Limburg",
    "sg:tags":[
        "material",
        "audio-visual"
    ],
    "wof:name":"Ml Concept",
    "wof:placetype":"venue"
},
  "geometry": {"coordinates":[5.2274580002,50.9971885681],"type":"Point"}
}