{
  "type": "Feature",
  "properties": {
    "iso:country":"BE",
    "sg:address":"Jan Van Rijswijcklaan 6",
    "sg:city":"Antwerpen",
    "sg:classifiers":[
        {
            "category":"Professional",
            "subcategory":"Lawyer & Legal Services",
            "type":"Services"
        }
    ],
    "sg:phone":"+32 3 238 71 17",
    "sg:postcode":"2018",
    "sg:province":"Antwerpen",
    "wof:name":"De Roeck Kristin",
    "wof:placetype":"venue"
},
  "geometry": {"coordinates":[4.4099650383,51.1981048584],"type":"Point"}
}