{
  "type": "Feature",
  "properties": {
    "iso:country":"BE",
    "sg:address":"Zandoerstraat 17",
    "sg:city":"Genk",
    "sg:orig_category":"Brood, gebak and snoepgoed",
    "sg:phone":"+32 89 35 03 27",
    "sg:postcode":"3600",
    "sg:province":"Limburg",
    "wof:name":"Georges Bruyninx",
    "wof:placetype":"venue"
},
  "geometry": {"coordinates":[5.4526910782,50.9722824097],"type":"Point"}
}