{
  "type": "Feature",
  "properties": {
    "addr:full":"Kapelleommegang 33 Aalst Oost-Vlaanderen 9310",
    "addr:housenumber":"33",
    "addr:postcode":"9310",
    "addr:street":"Kapelleommegang",
    "iso:country":"BE",
    "sg:address":"Kapelleommegang 33",
    "sg:city":"Aalst",
    "sg:orig_category":"G\u00e9om\u00e8tres",
    "sg:phone":"+32 53 78 49 34",
    "sg:postcode":"9310",
    "sg:province":"Oost-Vlaanderen",
    "wof:name":"Herman Vinck",
    "wof:placetype":"venue"
},
  "geometry": {"coordinates":[4.0674929619,50.9644126892],"type":"Point"}
}