{
  "type": "Feature",
  "properties": {
    "iso:country":"BE",
    "sg:address":"Meerlaan 70",
    "sg:city":"Zottegem",
    "sg:classifiers":[
        {
            "category":"Fast Food",
            "type":"Food & Drink"
        }
    ],
    "sg:phone":"+32 9 361 13 46",
    "sg:postcode":"9620",
    "sg:province":"Oost-Vlaanderen",
    "sg:tags":[
        "fried",
        "stand",
        "potato"
    ],
    "wof:name":"Bud's Corner",
    "wof:placetype":"venue"
},
  "geometry": {"coordinates":[3.8109478951,50.8649520874],"type":"Point"}
}