{
  "type": "Feature",
  "properties": {
    "iso:country":"BE",
    "sg:address":"Rue La Coul\u00c9e 54",
    "sg:city":"Modave",
    "sg:orig_category":"M\u00e9decins and sp\u00e9cialistes",
    "sg:phone":"+32 85 41 11 51",
    "sg:postcode":"4577",
    "sg:province":"Li\u00e8ge",
    "wof:name":"L\u00c9on Lhermitte",
    "wof:placetype":"venue"
},
  "geometry": {"coordinates":[5.2915291786,50.4782409668],"type":"Point"}
}