{
  "type": "Feature",
  "properties": {
    "addr:full":"Kalfvaart 11 Ieper West-Vlaanderen 8900",
    "addr:housenumber":"11",
    "addr:postcode":"8900",
    "addr:street":"Kalfvaart",
    "iso:country":"BE",
    "sg:address":"Kalfvaart 11",
    "sg:city":"Ieper",
    "sg:classifiers":[
        {
            "category":"Health Services",
            "subcategory":"Dentist",
            "type":"Services"
        }
    ],
    "sg:phone":"+32 57 21 89 29",
    "sg:postcode":"8900",
    "sg:province":"West-Vlaanderen",
    "wof:name":"Cruyt Jan",
    "wof:placetype":"venue"
},
  "geometry": {"coordinates":[2.8904309273,50.8562240601],"type":"Point"}
}