{
  "type": "Feature",
  "properties": {
    "addr:full":"Rue Pr\u00e9 Des Dames Andenne Namur 5300",
    "addr:postcode":"5300",
    "addr:street":"Rue Pre\u0301 Des Dames",
    "iso:country":"BE",
    "sg:address":"Rue Pr\u00e9 Des Dames",
    "sg:city":"Andenne",
    "sg:classifiers":[
        {
            "category":"Wholesale",
            "subcategory":"Books, Periodicals, & Newspapers",
            "type":"Manufacturing & Wholesale Goods"
        }
    ],
    "sg:phone":"+32 85 84 14 33",
    "sg:postcode":"5300",
    "sg:province":"Namur",
    "sg:tags":[
        "publisher"
    ],
    "wof:name":"Magermans Sa",
    "wof:placetype":"venue"
},
  "geometry": {"coordinates":[5.1077580452,50.4932937622],"type":"Point"}
}