{
  "type": "Feature",
  "properties": {
    "iso:country":"BE",
    "sg:address":"Chauss\u00c9e De Ch\u00c2telet 6a",
    "sg:city":"Charleroi",
    "sg:orig_category":"Fleurs and plantes",
    "sg:phone":"+32 71 30 88 88",
    "sg:postcode":"6042",
    "sg:province":"Hainaut",
    "wof:name":"Vegetal Passion",
    "wof:placetype":"venue"
},
  "geometry": {"coordinates":[4.4490199089,50.4293518066],"type":"Point"}
}