{
  "type": "Feature",
  "properties": {
    "iso:country":"BE",
    "sg:address":"Rue D'ypres 3",
    "sg:city":"Tournai",
    "sg:orig_category":"Sportclubs Sportterreinen and installaties behalve sportcentra",
    "sg:phone":"+32 69 44 21 67",
    "sg:postcode":"7538",
    "sg:province":"Hainaut",
    "wof:name":"J.u.s. Maubray",
    "wof:placetype":"venue"
},
  "geometry": {"coordinates":[3.5087308884,50.5688285828],"type":"Point"}
}