{
  "type": "Feature",
  "properties": {
    "iso:country":"BE",
    "sg:address":"Kontichsesteenweg 86",
    "sg:city":"Aartselaar",
    "sg:classifiers":[
        {
            "category":"Professional",
            "subcategory":"Lawyer & Legal Services",
            "type":"Services"
        }
    ],
    "sg:phone":"+32 3 877 26 00",
    "sg:postcode":"2630",
    "sg:province":"Antwerpen",
    "wof:name":"Advocatenassociatie Van Orshaegen & Thijs Bvba",
    "wof:placetype":"venue"
},
  "geometry": {"coordinates":[4.401444912,51.1441078186],"type":"Point"}
}