{
  "type": "Feature",
  "properties": {
    "iso:country":"BE",
    "sg:address":"Dokter Dekemelelaan 34",
    "sg:city":"Ieper",
    "sg:orig_category":"Elektrische installaties voor woningen",
    "sg:phone":"+32 57 42 24 23",
    "sg:postcode":"8904",
    "sg:province":"West-Vlaanderen",
    "wof:name":"Robert Logie",
    "wof:placetype":"venue"
},
  "geometry": {"coordinates":[2.8608119488,50.8958625793],"type":"Point"}
}