{
  "type": "Feature",
  "properties": {
    "addr:full":"Vlietstraat 13 Zele Oost-Vlaanderen 9240",
    "addr:housenumber":"13",
    "addr:postcode":"9240",
    "addr:street":"Vlietstraat",
    "iso:country":"BE",
    "sg:address":"Vlietstraat 13",
    "sg:city":"Zele",
    "sg:orig_category":"Eleveurs de bovins",
    "sg:phone":"+32 52 44 90 27",
    "sg:postcode":"9240",
    "sg:province":"Oost-Vlaanderen",
    "wof:name":"Karin Heirman",
    "wof:placetype":"venue"
},
  "geometry": {"coordinates":[3.9996099472,51.0692100525],"type":"Point"}
}