{
  "type": "Feature",
  "properties": {
    "addr:full":"Stijn Streuvelsstraat 2 Izegem West-Vlaanderen 8870",
    "addr:housenumber":"2",
    "addr:postcode":"8870",
    "addr:street":"Stijn Streuvelsstraat",
    "iso:country":"BE",
    "sg:address":"Stijn Streuvelsstraat 2",
    "sg:city":"Izegem",
    "sg:classifiers":[
        {
            "category":"Bars & Pubs",
            "type":"Food & Drink"
        }
    ],
    "sg:postcode":"8870",
    "sg:province":"West-Vlaanderen",
    "wof:name":"Sportwereld (de)",
    "wof:placetype":"venue"
},
  "geometry": {"coordinates":[3.2307059765,50.9229316711],"type":"Point"}
}