{
  "type": "Feature",
  "properties": {
    "iso:country":"BE",
    "sg:address":"Chauss\u00e9e De Namur 294",
    "sg:city":"Eghez\u00e9e",
    "sg:classifiers":[
        {
            "category":"Autos & Motor Vehicles",
            "subcategory":"Automobile Sales",
            "type":"Retail Goods"
        }
    ],
    "sg:phone":"+32 81 51 15 98",
    "sg:postcode":"5310",
    "sg:province":"Namur",
    "sg:tags":[
        "car",
        "used",
        "-"
    ],
    "wof:name":"Vangoidsenhoven J",
    "wof:placetype":"venue"
},
  "geometry": {"coordinates":[4.9116740227,50.5860519409],"type":"Point"}
}