{
  "type": "Feature",
  "properties": {
    "iso:country":"BE",
    "sg:address":"Bruggesteenweg 30",
    "sg:city":"Middelkerke",
    "sg:classifiers":[
        {
            "category":"Fast Food",
            "type":"Food & Drink"
        }
    ],
    "sg:phone":"+32 59 27 91 17",
    "sg:postcode":"8433",
    "sg:province":"West-Vlaanderen",
    "sg:tags":[
        "meeneem",
        "restaurant"
    ],
    "wof:name":"\u00b4t Kunstkroegje",
    "wof:placetype":"venue"
},
  "geometry": {"coordinates":[2.8457300663,51.1217842102],"type":"Point"}
}