{
  "type": "Feature",
  "properties": {
    "addr:full":"Broekstraat 5 Dilbeek Vlaams-Brabant 1700",
    "addr:housenumber":"5",
    "addr:postcode":"1700",
    "addr:street":"Broekstraat",
    "iso:country":"BE",
    "sg:address":"Broekstraat 5",
    "sg:city":"Dilbeek",
    "sg:classifiers":[
        {
            "category":"Health Services",
            "subcategory":"Health Practitioner",
            "type":"Services"
        }
    ],
    "sg:phone":"+32 2 569 43 40",
    "sg:postcode":"1700",
    "sg:province":"Vlaams-Brabant",
    "sg:tags":[
        "physiotherapist"
    ],
    "wof:name":"Van Hemelrijck Nadia",
    "wof:placetype":"venue"
},
  "geometry": {"coordinates":[4.2610697746,50.8426437378],"type":"Point"}
}