{
  "type": "Feature",
  "properties": {
    "iso:country":"BE",
    "sg:address":"Rue Des Mineurs 4",
    "sg:city":"Li\u00e8ge 1",
    "sg:classifiers":[
        {
            "category":"Building & Trades",
            "subcategory":"Plumbing",
            "type":"Services"
        }
    ],
    "sg:phone":"+32 4 223 04 33",
    "sg:postcode":"4000",
    "sg:province":"Li\u00e8ge",
    "sg:tags":[
        "relocation"
    ],
    "wof:name":"Li\u00e8ge-link",
    "wof:placetype":"venue"
},
  "geometry": {"coordinates":[5.5769748688,50.6459999084],"type":"Point"}
}