{
  "type": "Feature",
  "properties": {
    "iso:country":"BE",
    "sg:address":"Breestraat 11",
    "sg:city":"Beervelde",
    "sg:orig_category":"Taxis services sp\u00e9ciaux. Taxis. Taxis services sp\u00e9ciaux. Taxis",
    "sg:phone":"+32 9 238 38 32",
    "sg:postcode":"9080",
    "sg:province":"Oost-Vlaanderen",
    "wof:name":"A.c.t. Air Car Trans",
    "wof:placetype":"venue"
},
  "geometry": {"coordinates":[3.8613939285,51.0541915894],"type":"Point"}
}