{
  "type": "Feature",
  "properties": {
    "iso:country":"BE",
    "sg:address":"F\u00c9ronstr\u00c9e 54",
    "sg:city":"Li\u00c8ge",
    "sg:orig_category":"Magasins de r\u00e9parations d'articles personnels et m\u00e9nagers divers",
    "sg:phone":"+32 4 221 27 12",
    "sg:postcode":"4000",
    "sg:province":"Li\u00e8ge",
    "wof:name":"Filfloche",
    "wof:placetype":"venue"
},
  "geometry": {"coordinates":[5.5789651871,50.6462364197],"type":"Point"}
}