{
  "type": "Feature",
  "properties": {
    "addr:full":"Huilaart 18 Wichelen (serskamp) Oost-Vlaanderen 9260",
    "addr:housenumber":"18",
    "addr:postcode":"9260",
    "addr:street":"Huilaart",
    "iso:country":"BE",
    "sg:address":"Huilaart 18",
    "sg:city":"Wichelen (serskamp)",
    "sg:classifiers":[
        {
            "category":"Personal",
            "subcategory":"Beauty Salon",
            "type":"Services"
        }
    ],
    "sg:phone":"+32 9 369 19 33",
    "sg:postcode":"9260",
    "sg:province":"Oost-Vlaanderen",
    "sg:tags":[
        "lady",
        "-",
        "hairdressing"
    ],
    "wof:name":"Hairline",
    "wof:placetype":"venue"
},
  "geometry": {"coordinates":[3.928278923,50.9867324829],"type":"Point"}
}