{
  "type": "Feature",
  "properties": {
    "iso:country":"BE",
    "sg:address":"Rue Des Minimes 30",
    "sg:city":"Brussel/bruxelles",
    "sg:orig_category":"Antiquit\u00e9s",
    "sg:phone":"+32 2 513 32 88",
    "sg:postcode":"1000",
    "sg:province":"Bruxelles-Capitale",
    "wof:name":"Galeries St.louis",
    "wof:placetype":"venue"
},
  "geometry": {"coordinates":[4.353705883,50.8406105042],"type":"Point"}
}