{
  "type": "Feature",
  "properties": {
    "addr:full":"Rue Georges Lef\u00e8vre 52 Musson (mussy-la-ville) Luxembourg 6750",
    "addr:housenumber":"52",
    "addr:postcode":"6750",
    "addr:street":"Rue Georges Lefe\u0300Vre",
    "iso:country":"BE",
    "sg:address":"Rue Georges Lef\u00e8vre 52",
    "sg:city":"Musson (mussy-la-ville)",
    "sg:classifiers":[
        {
            "category":"Building & Trades",
            "subcategory":"Construction",
            "type":"Services"
        }
    ],
    "sg:phone":"+32 63 67 77 49",
    "sg:postcode":"6750",
    "sg:province":"Luxembourg",
    "sg:tags":[
        "carpenter"
    ],
    "wof:name":"Deroisy M",
    "wof:placetype":"venue"
},
  "geometry": {"coordinates":[5.6602602005,49.5724182129],"type":"Point"}
}