{
  "type": "Feature",
  "properties": {
    "addr:full":"Chee De Jolimont 22 Haine St. Paul 7161",
    "addr:housenumber":"22",
    "addr:postcode":"7161",
    "addr:street":"Chee;Haine St.",
    "iso:country":"BE",
    "sg:address":"Chee De Jolimont 22",
    "sg:city":"Haine St. Paul",
    "sg:classifiers":[
        {
            "category":"Banks & Credit Unions",
            "subcategory":"Bank",
            "type":"Services"
        }
    ],
    "sg:phone":"+32 64 21 35 46",
    "sg:postcode":"7161",
    "wof:name":"Caisse Nationale De, Cr\u00e9dit Professionnel",
    "wof:placetype":"venue"
},
  "geometry": {"coordinates":[4.2045412064,50.466468811],"type":"Point"}
}