{
  "type": "Feature",
  "properties": {
    "addr:full":"Oude Ieperseweg 53 Kortrijk West-Vlaanderen 8501",
    "addr:housenumber":"53",
    "addr:postcode":"8501",
    "addr:street":"Oude Ieperseweg",
    "iso:country":"BE",
    "sg:address":"Oude Ieperseweg 53",
    "sg:city":"Kortrijk",
    "sg:orig_category":"Instellingen voor probleemkinderen Kindertehuizen",
    "sg:phone":"+32 56 35 91 99",
    "sg:postcode":"8501",
    "sg:province":"West-Vlaanderen",
    "wof:name":"Oranjehuis",
    "wof:placetype":"venue"
},
  "geometry": {"coordinates":[3.2365870476,50.8367805481],"type":"Point"}
}