{
  "type": "Feature",
  "properties": {
    "iso:country":"BE",
    "sg:address":"Maaltecenter",
    "sg:city":"Gent",
    "sg:orig_category":"Diverse bedrijfsbeheeradviesbureaus",
    "sg:phone":"+32 9 254 02 94",
    "sg:postcode":"9051",
    "sg:province":"Oost-Vlaanderen",
    "wof:name":"Advanced Management Tools",
    "wof:placetype":"venue"
},
  "geometry": {"coordinates":[3.6683819294,51.020690918],"type":"Point"}
}