{
  "type": "Feature",
  "properties": {
    "addr:full":"Waterloosesteenweg 412g Elsene/ixelles Bruxelles-Capitale 1050",
    "addr:housenumber":"412g",
    "addr:postcode":"1050",
    "addr:street":"Waterloosesteenweg",
    "iso:country":"BE",
    "sg:address":"Waterloosesteenweg 412g",
    "sg:city":"Elsene/ixelles",
    "sg:orig_category":"Banken and kredietinstellingen",
    "sg:phone":"+32 2 534 07 96",
    "sg:postcode":"1050",
    "sg:province":"Bruxelles-Capitale",
    "wof:name":"Bbl",
    "wof:placetype":"venue"
},
  "geometry": {"coordinates":[4.3590397835,50.8191795349],"type":"Point"}
}