{
  "type": "Feature",
  "properties": {
    "iso:country":"BE",
    "sg:address":"Avenue Des Pagodes 212",
    "sg:city":"Bruxelles",
    "sg:classifiers":[
        {
            "category":"Social Services",
            "type":"Services"
        }
    ],
    "sg:phone":"+32 2 268 03 71",
    "sg:postcode":"1020",
    "sg:province":"Bruxelles-Capitale",
    "sg:tags":[
        "handicapped",
        "-"
    ],
    "wof:name":"Centre Nos Pilifs Asbl",
    "wof:placetype":"venue"
},
  "geometry": {"coordinates":[4.3682398796,50.8946800232],"type":"Point"}
}