{
  "type": "Feature",
  "properties": {
    "iso:country":"BE",
    "sg:address":"Grimmertringenstr 24",
    "sg:city":"Kortessem",
    "sg:classifiers":[
        {
            "category":"Travel",
            "subcategory":"Hotels & Motels",
            "type":"Entertainment"
        }
    ],
    "sg:phone":"+32 12 23 60 96",
    "sg:postcode":"3724",
    "sg:province":"Limburg",
    "sg:tags":[
        "hotels",
        "business",
        "restaurant"
    ],
    "wof:name":"Clos St Denis Nv",
    "wof:placetype":"venue"
},
  "geometry": {"coordinates":[5.421713829,50.8201942444],"type":"Point"}
}