{
  "type": "Feature",
  "properties": {
    "addr:full":"Avenue De L'esplanade 89 Wezembeek-oppem Vlaams-Brabant 1970",
    "addr:housenumber":"89",
    "addr:postcode":"1970",
    "addr:street":"Avenue De L'Esplanade",
    "iso:country":"BE",
    "sg:address":"Avenue De L'esplanade 89",
    "sg:city":"Wezembeek-oppem",
    "sg:classifiers":[
        {
            "category":"Professional",
            "subcategory":"Art Services",
            "type":"Services"
        }
    ],
    "sg:phone":"+32 2 731 20 92",
    "sg:postcode":"1970",
    "sg:province":"Vlaams-Brabant",
    "sg:tags":[
        "graphic",
        "designer"
    ],
    "wof:name":"Carbon Design",
    "wof:placetype":"venue"
},
  "geometry": {"coordinates":[4.4750409126,50.8389434814],"type":"Point"}
}