{
  "type": "Feature",
  "properties": {
    "iso:country":"BE",
    "sg:address":"Rue De La Gare 180",
    "sg:city":"Neufch\u00e2teau (hamipr\u00e9)",
    "sg:classifiers":[
        {
            "category":"Personal",
            "subcategory":"Beauty Salon",
            "type":"Services"
        }
    ],
    "sg:phone":"+32 61 27 80 01",
    "sg:postcode":"6840",
    "sg:province":"Luxembourg",
    "sg:tags":[
        "lady",
        "-",
        "hairdressing"
    ],
    "wof:name":"Cecile",
    "wof:placetype":"venue"
},
  "geometry": {"coordinates":[5.4506311417,49.8537063599],"type":"Point"}
}