{
  "type": "Feature",
  "properties": {
    "addr:full":"Wagenaarstraat 39 Waregem (beveren-leie) West-Vlaanderen 8791",
    "addr:housenumber":"39",
    "addr:postcode":"8791",
    "addr:street":"Wagenaarstraat",
    "iso:country":"BE",
    "sg:address":"Wagenaarstraat 39",
    "sg:city":"Waregem (beveren-leie)",
    "sg:orig_category":"Non-Classified Establishments",
    "sg:phone":"+32 56 73 14 73",
    "sg:postcode":"8791",
    "sg:province":"West-Vlaanderen",
    "wof:name":"Bulckaert Weverij Nv",
    "wof:placetype":"venue"
},
  "geometry": {"coordinates":[3.3457939625,50.8631057739],"type":"Point"}
}