{
  "type": "Feature",
  "properties": {
    "addr:full":"Fontaine Saint-joseph 2 Viroinval Namur 5670",
    "addr:housenumber":"2",
    "addr:postcode":"5670",
    "iso:country":"BE",
    "sg:address":"Fontaine Saint-joseph 2",
    "sg:city":"Viroinval",
    "sg:orig_category":"Toeristische diensten",
    "sg:phone":"+32 60 39 93 85",
    "sg:postcode":"5670",
    "sg:province":"Namur",
    "wof:name":"Syndicat D\u00b4initiative",
    "wof:placetype":"venue"
},
  "geometry": {"coordinates":[4.6340107918,50.0818099976],"type":"Point"}
}