{
  "type": "Feature",
  "properties": {
    "addr:full":"Steenweg 117a Lierde (sint-maria-lierde) Oost-Vlaanderen 9570",
    "addr:housenumber":"117a",
    "addr:postcode":"9570",
    "addr:street":"Steenweg",
    "iso:country":"BE",
    "sg:address":"Steenweg 117a",
    "sg:city":"Lierde (sint-maria-lierde)",
    "sg:classifiers":[
        {
            "category":"Insurance",
            "subcategory":"Insurance Agent",
            "type":"Services"
        }
    ],
    "sg:phone":"+32 55 42 42 51",
    "sg:postcode":"9570",
    "sg:province":"Oost-Vlaanderen",
    "sg:tags":[
        "-",
        "representative"
    ],
    "wof:name":"Kbc-verlinden Jp",
    "wof:placetype":"venue"
},
  "geometry": {"coordinates":[3.8259561062,50.8151473999],"type":"Point"}
}