{
  "type": "Feature",
  "properties": {
    "iso:country":"BE",
    "sg:address":"Rue Jourdan 108a",
    "sg:city":"Bruxelles (saint-gilles)",
    "sg:classifiers":[
        {
            "category":"Food & Beverages",
            "subcategory":"Groceries & Convenience Stores",
            "type":"Retail Goods"
        }
    ],
    "sg:phone":"+32 2 538 32 08",
    "sg:postcode":"1060",
    "sg:province":"Bruxelles-Capitale",
    "sg:tags":[
        "grocer"
    ],
    "wof:name":"Friendship Store",
    "wof:placetype":"venue"
},
  "geometry": {"coordinates":[4.3504681587,50.8324356079],"type":"Point"}
}