{
  "type": "Feature",
  "properties": {
    "addr:full":"'s Gravenstraat 204 Nazareth Oost-Vlaanderen 9810",
    "addr:housenumber":"204",
    "addr:postcode":"9810",
    "addr:street":"' S Gravenstraat",
    "iso:country":"BE",
    "sg:address":"'s Gravenstraat 204",
    "sg:city":"Nazareth",
    "sg:orig_category":"Plaatsen van vloer- and muurbekleding",
    "sg:phone":"+32 9 385 88 35",
    "sg:postcode":"9810",
    "sg:province":"Oost-Vlaanderen",
    "wof:name":"Marc Moens",
    "wof:placetype":"venue"
},
  "geometry": {"coordinates":[3.5926709175,50.9480400085],"type":"Point"}
}