{
  "type": "Feature",
  "properties": {
    "addr:full":"Avenue Guillaume Herinckx 68 Bruxelles (uccle) Bruxelles-Capitale 1180",
    "addr:housenumber":"68",
    "addr:postcode":"1180",
    "addr:street":"Avenue Guillaume Herinckx",
    "iso:country":"BE",
    "sg:address":"Avenue Guillaume Herinckx 68",
    "sg:city":"Bruxelles (uccle)",
    "sg:classifiers":[
        {
            "category":"Health Services",
            "subcategory":"Health Practitioner",
            "type":"Services"
        }
    ],
    "sg:phone":"+32 2 332 49 82",
    "sg:postcode":"1180",
    "sg:province":"Bruxelles-Capitale",
    "sg:tags":[
        "therapist",
        "speech"
    ],
    "wof:name":"Bachy S",
    "wof:placetype":"venue"
},
  "geometry": {"coordinates":[4.3320841789,50.7954711914],"type":"Point"}
}