{
  "type": "Feature",
  "properties": {
    "addr:full":"Sloesveldstraat 13 Hoeilaart Vlaams-Brabant 1560",
    "addr:housenumber":"13",
    "addr:postcode":"1560",
    "addr:street":"Sloesveldstraat",
    "iso:country":"BE",
    "sg:address":"Sloesveldstraat 13",
    "sg:city":"Hoeilaart",
    "sg:orig_category":"M\u00e9decins and sp\u00e9cialistes",
    "sg:phone":"+32 2 657 29 38",
    "sg:postcode":"1560",
    "sg:province":"Vlaams-Brabant",
    "wof:name":"Jean Lefebvre",
    "wof:placetype":"venue"
},
  "geometry": {"coordinates":[4.4931268692,50.7654953003],"type":"Point"}
}