{
  "type": "Feature",
  "properties": {
    "addr:full":"Industriepark Rostijne 21 Zelzate Oost-Vlaanderen 9060",
    "addr:housenumber":"21",
    "addr:postcode":"9060",
    "addr:street":"Industriepark Rostijne",
    "iso:country":"BE",
    "sg:address":"Industriepark Rostijne 21",
    "sg:city":"Zelzate",
    "sg:classifiers":[
        {
            "category":"Home & Garden",
            "subcategory":"Home Furnishings",
            "type":"Retail Goods"
        }
    ],
    "sg:phone":"+32 9 345 60 71",
    "sg:postcode":"9060",
    "sg:province":"Oost-Vlaanderen",
    "sg:tags":[
        "interior",
        "decoration"
    ],
    "wof:name":"Cleys Interieurinrichting",
    "wof:placetype":"venue"
},
  "geometry": {"coordinates":[3.829668045,51.188709259],"type":"Point"}
}