{
  "type": "Feature",
  "properties": {
    "addr:full":"Koolmijnlaan 230 Beringen (koersel) Limburg 3582",
    "addr:housenumber":"230",
    "addr:postcode":"3582",
    "addr:street":"Koolmijnlaan",
    "iso:country":"BE",
    "sg:address":"Koolmijnlaan 230",
    "sg:city":"Beringen (koersel)",
    "sg:classifiers":[
        {
            "category":"Professional",
            "subcategory":"Testing Lab",
            "type":"Services"
        }
    ],
    "sg:phone":"+32 11 42 26 38",
    "sg:postcode":"3582",
    "sg:province":"Limburg",
    "sg:tags":[
        "chemist"
    ],
    "wof:name":"Van Dyck G",
    "wof:placetype":"venue"
},
  "geometry": {"coordinates":[5.220143795,51.0723152161],"type":"Point"}
}