{
  "type": "Feature",
  "properties": {
    "addr:full":"Houwstraat 40 Maaseik Limburg 3680",
    "addr:housenumber":"40",
    "addr:postcode":"3680",
    "addr:street":"Houwstraat",
    "iso:country":"BE",
    "sg:address":"Houwstraat 40",
    "sg:city":"Maaseik",
    "sg:orig_category":"Eleveurs de bovins",
    "sg:phone":"+32 89 86 64 54",
    "sg:postcode":"3680",
    "sg:province":"Limburg",
    "wof:name":"Willy Schepens",
    "wof:placetype":"venue"
},
  "geometry": {"coordinates":[5.6515798569,51.0573196411],"type":"Point"}
}