{
  "type": "Feature",
  "properties": {
    "addr:full":"Renbaanstraat 14 Nazareth Oost-Vlaanderen 9810",
    "addr:housenumber":"14",
    "addr:postcode":"9810",
    "addr:street":"Renbaanstraat",
    "iso:country":"BE",
    "sg:address":"Renbaanstraat 14",
    "sg:city":"Nazareth",
    "sg:orig_category":"Geluidsopnames",
    "sg:phone":"+32 9 385 64 78",
    "sg:postcode":"9810",
    "sg:province":"Oost-Vlaanderen",
    "wof:name":"Wild Boar Music",
    "wof:placetype":"venue"
},
  "geometry": {"coordinates":[3.5909450054,50.9510536194],"type":"Point"}
}