{
  "type": "Feature",
  "properties": {
    "addr:full":"Louis Tantstraat 10-31 Roeselare West-Vlaanderen 8800",
    "addr:housenumber":"10-31",
    "addr:postcode":"8800",
    "addr:street":"Louis Tantstraat",
    "iso:country":"BE",
    "sg:address":"Louis Tantstraat 10-31",
    "sg:city":"Roeselare",
    "sg:classifiers":[
        {
            "category":"Real Estate",
            "subcategory":"Architect",
            "type":"Services"
        }
    ],
    "sg:phone":"+32 477 57 24 12",
    "sg:postcode":"8800",
    "sg:province":"West-Vlaanderen",
    "wof:name":"Decoopman S",
    "wof:placetype":"venue"
},
  "geometry": {"coordinates":[3.125166893,50.9514770508],"type":"Point"}
}