{
  "type": "Feature",
  "properties": {
    "addr:full":"Rue D'egmont Et De Hornes 24 Seraing Li\u00e8ge 4100",
    "addr:housenumber":"24",
    "addr:postcode":"4100",
    "addr:street":"Rue D'Egmont Et De Hornes",
    "iso:country":"BE",
    "sg:address":"Rue D'egmont Et De Hornes 24",
    "sg:city":"Seraing",
    "sg:classifiers":[
        {
            "category":"Health Services",
            "subcategory":"Health Practitioner",
            "type":"Services"
        }
    ],
    "sg:phone":"+32 4 336 55 62",
    "sg:postcode":"4100",
    "sg:province":"Li\u00e8ge",
    "sg:tags":[
        "physiotherapist"
    ],
    "wof:name":"Zaoui Mohamed",
    "wof:placetype":"venue"
},
  "geometry": {"coordinates":[5.5083899498,50.5838279724],"type":"Point"}
}