{
  "type": "Feature",
  "properties": {
    "addr:full":"Avenue De Mai 266 Sint-lambrechts-woluwe/woluwe-saint-lambert Bruxelles-Capitale 1200",
    "addr:housenumber":"266;/",
    "addr:postcode":"1200",
    "addr:street":"Avenue De Mai;Sint-Lambrechts-Woluwe",
    "iso:country":"BE",
    "sg:address":"Avenue De Mai 266",
    "sg:city":"Sint-lambrechts-woluwe/woluwe-saint-lambert",
    "sg:orig_category":"M\u00e9decins and sp\u00e9cialistes",
    "sg:phone":"+32 2 736 48 51",
    "sg:postcode":"1200",
    "sg:province":"Bruxelles-Capitale",
    "wof:name":"Chantal Mathys",
    "wof:placetype":"venue"
},
  "geometry": {"coordinates":[4.4106321335,50.8482971191],"type":"Point"}
}