{
  "type": "Feature",
  "properties": {
    "addr:full":"Teerlingstraat 35 Haaltert Oost-Vlaanderen 9450",
    "addr:housenumber":"35",
    "addr:postcode":"9450",
    "addr:street":"Teerlingstraat",
    "iso:country":"BE",
    "sg:address":"Teerlingstraat 35",
    "sg:city":"Haaltert",
    "sg:orig_category":"Tuinbenodigdheden",
    "sg:phone":"+32 54 33 11 15",
    "sg:postcode":"9450",
    "sg:province":"Oost-Vlaanderen",
    "wof:name":"Wim De Middeleer",
    "wof:placetype":"venue"
},
  "geometry": {"coordinates":[4.0204401016,50.8717346191],"type":"Point"}
}