{
  "type": "Feature",
  "properties": {
    "iso:country":"BE",
    "sg:address":"Pannestraat 202",
    "sg:city":"Veurne",
    "sg:orig_category":"Eleveurs and marchands de porcs. Eleveurs de bovins",
    "sg:phone":"+32 58 31 15 68",
    "sg:postcode":"8630",
    "sg:province":"West-Vlaanderen",
    "wof:name":"Luc Vandaele",
    "wof:placetype":"venue"
},
  "geometry": {"coordinates":[2.6339600086,51.0839614868],"type":"Point"}
}