{
  "type": "Feature",
  "properties": {
    "iso:country":"BE",
    "sg:address":"Kerkplein 11",
    "sg:city":"Wingene",
    "sg:orig_category":"Drogisterijen Plaatsen van vloer- and muurbekleding Schilders",
    "sg:phone":"+32 51 65 62 10",
    "sg:postcode":"8750",
    "sg:province":"West-Vlaanderen",
    "wof:name":"Geert Creytens",
    "wof:placetype":"venue"
},
  "geometry": {"coordinates":[3.2780599594,51.0580406189],"type":"Point"}
}