{
  "type": "Feature",
  "properties": {
    "addr:full":"Rue Du Centre 18 Li\u00c8ge Li\u00e8ge 4000",
    "addr:housenumber":"18",
    "addr:postcode":"4000",
    "addr:street":"Rue Du Centre",
    "iso:country":"BE",
    "sg:address":"Rue Du Centre 18",
    "sg:city":"Li\u00c8ge",
    "sg:orig_category":"WAPENS AND MUNITIE",
    "sg:phone":"+32 4 253 09 42",
    "sg:postcode":"4000",
    "sg:province":"Li\u00e8ge",
    "wof:name":"A. Piette",
    "wof:placetype":"venue"
},
  "geometry": {"coordinates":[5.5531139374,50.6101837158],"type":"Point"}
}