{
  "type": "Feature",
  "properties": {
    "addr:full":"Fatimastraat 19ba Aalter Oost-Vlaanderen 9880",
    "addr:housenumber":"19ba",
    "addr:postcode":"9880",
    "addr:street":"Fatimastraat",
    "iso:country":"BE",
    "sg:address":"Fatimastraat 19ba",
    "sg:city":"Aalter",
    "sg:orig_category":"Woningbouw",
    "sg:phone":"+32 9 374 78 39",
    "sg:postcode":"9880",
    "sg:province":"Oost-Vlaanderen",
    "wof:name":"Guido Kint",
    "wof:placetype":"venue"
},
  "geometry": {"coordinates":[3.4399929047,51.093624115],"type":"Point"}
}