{
  "type": "Feature",
  "properties": {
    "iso:country":"BE",
    "sg:address":"Rue De Hollogne 211",
    "sg:city":"Seraing",
    "sg:orig_category":"Studios photographiques",
    "sg:phone":"+32 4 234 23 39",
    "sg:postcode":"4101",
    "sg:province":"Li\u00e8ge",
    "wof:name":"G. D\u00b4atria",
    "wof:placetype":"venue"
},
  "geometry": {"coordinates":[5.4892392159,50.6248245239],"type":"Point"}
}