{
  "type": "Feature",
  "properties": {
    "iso:country":"BE",
    "sg:address":"Rue Mar\u00e9chal Foch 30",
    "sg:city":"Virton",
    "sg:classifiers":[
        {
            "category":"Shopping",
            "subcategory":"Florist",
            "type":"Retail Goods"
        }
    ],
    "sg:phone":"+32 63 58 21 81",
    "sg:postcode":"6760",
    "sg:province":"Luxembourg",
    "wof:name":"La Grange Aux Fleurs",
    "wof:placetype":"venue"
},
  "geometry": {"coordinates":[5.529129982,49.5711936951],"type":"Point"}
}