{
  "type": "Feature",
  "properties": {
    "addr:full":"Rue Du Bourrelier 21 Jurbise (masnuy-saint-jean) Hainaut 7050",
    "addr:housenumber":"21",
    "addr:postcode":"7050",
    "addr:street":"Rue Du Bourrelier",
    "iso:country":"BE",
    "sg:address":"Rue Du Bourrelier 21",
    "sg:city":"Jurbise (masnuy-saint-jean)",
    "sg:classifiers":[
        {
            "category":"Organizations",
            "subcategory":"Community Association",
            "type":"Services"
        }
    ],
    "sg:phone":"+32 64 23 59 75",
    "sg:postcode":"7050",
    "sg:province":"Hainaut",
    "sg:tags":[
        "environment",
        "organisation",
        "-"
    ],
    "wof:name":"Protection Des Oiseaux",
    "wof:placetype":"venue"
},
  "geometry": {"coordinates":[3.9256999493,50.5348434448],"type":"Point"}
}