{
  "type": "Feature",
  "properties": {
    "addr:full":"A. De Cockstraat 10 Denderleeuw Oost-Vlaanderen 9470",
    "addr:housenumber":"10",
    "addr:postcode":"9470",
    "addr:street":"A. De Cockstraat",
    "iso:country":"BE",
    "sg:address":"A. De Cockstraat 10",
    "sg:city":"Denderleeuw",
    "sg:orig_category":"Babyspullen Bagage and lederwaren Speelgoed",
    "sg:phone":"+32 53 66 67 42",
    "sg:postcode":"9470",
    "sg:province":"Oost-Vlaanderen",
    "wof:name":"Marc Stevens",
    "wof:placetype":"venue"
},
  "geometry": {"coordinates":[4.0807471275,50.8827667236],"type":"Point"}
}