{
  "type": "Feature",
  "properties": {
    "addr:full":"Rue Du Vigneron 17 Charleroi (jumet) Hainaut 6040",
    "addr:housenumber":"17",
    "addr:postcode":"6040",
    "addr:street":"Rue Du Vigneron",
    "iso:country":"BE",
    "sg:address":"Rue Du Vigneron 17",
    "sg:city":"Charleroi (jumet)",
    "sg:classifiers":[
        {
            "category":"Professional",
            "subcategory":"Engineering",
            "type":"Services"
        }
    ],
    "sg:phone":"+32 71 34 28 64",
    "sg:postcode":"6040",
    "sg:province":"Hainaut",
    "sg:tags":[
        "workshop"
    ],
    "wof:name":"Ateliers Rulens",
    "wof:placetype":"venue"
},
  "geometry": {"coordinates":[4.4216790199,50.4463806152],"type":"Point"}
}