{
  "type": "Feature",
  "properties": {
    "addr:full":"Rue Du Vieux Comt\u00e9 24 Tournai (mourcourt) Hainaut 7543",
    "addr:housenumber":"24",
    "addr:postcode":"7543",
    "addr:street":"Rue Du Vieux Comte\u0301",
    "iso:country":"BE",
    "sg:address":"Rue Du Vieux Comt\u00e9 24",
    "sg:city":"Tournai (mourcourt)",
    "sg:classifiers":[
        {
            "category":"Arts & Performance",
            "subcategory":"Theater",
            "type":"Entertainment"
        }
    ],
    "sg:phone":"+32 69 85 82 82",
    "sg:postcode":"7543",
    "sg:province":"Hainaut",
    "sg:tags":[
        "group",
        "theatre"
    ],
    "wof:name":"Espace Communication Asbl",
    "wof:placetype":"venue"
},
  "geometry": {"coordinates":[3.4436819553,50.6541862488],"type":"Point"}
}