{
  "type": "Feature",
  "properties": {
    "iso:country":"BE",
    "sg:address":"Ardoystraat 54",
    "sg:city":"Hamme",
    "sg:orig_category":"Eleveurs de bovins",
    "sg:phone":"+32 52 47 80 07",
    "sg:postcode":"9220",
    "sg:province":"Oost-Vlaanderen",
    "wof:name":"Hugo Claus",
    "wof:placetype":"venue"
},
  "geometry": {"coordinates":[4.0969171524,51.0934257507],"type":"Point"}
}