{
  "type": "Feature",
  "properties": {
    "iso:country":"BE",
    "sg:address":"Steenweg 281",
    "sg:city":"Alken",
    "sg:orig_category":"Voertuigen",
    "sg:phone":"+32 11 59 36 58",
    "sg:postcode":"3570",
    "sg:province":"Limburg",
    "wof:name":"Roger Gaethofs",
    "wof:placetype":"venue"
},
  "geometry": {"coordinates":[5.2706098557,50.8781585693],"type":"Point"}
}