{
  "type": "Feature",
  "properties": {
    "addr:full":"Rue De La Station 15 Seneffe Hainaut 7181",
    "addr:housenumber":"15",
    "addr:postcode":"7181",
    "addr:street":"Rue De La Station",
    "iso:country":"BE",
    "sg:address":"Rue De La Station 15",
    "sg:city":"Seneffe",
    "sg:orig_category":"Eleveurs de bovins",
    "sg:phone":"+32 64 54 14 74",
    "sg:postcode":"7181",
    "sg:province":"Hainaut",
    "wof:name":"Guy Brichant",
    "wof:placetype":"venue"
},
  "geometry": {"coordinates":[4.2114949226,50.5221939087],"type":"Point"}
}