{
  "type": "Feature",
  "properties": {
    "addr:full":"Lusthofstraat 22 Ravels Antwerpen 2380",
    "addr:housenumber":"22",
    "addr:postcode":"2380",
    "addr:street":"Lusthofstraat",
    "iso:country":"BE",
    "sg:address":"Lusthofstraat 22",
    "sg:city":"Ravels",
    "sg:orig_category":"Travaux de finition and nettoyage de b\u00e2timents. Constructions r\u00e9sidentielles sp\u00e9cifiques",
    "sg:phone":"+32 14 65 59 88",
    "sg:postcode":"2380",
    "sg:province":"Antwerpen",
    "wof:name":"Voegwerken Hertogs Rudy",
    "wof:placetype":"venue"
},
  "geometry": {"coordinates":[4.9881029129,51.3705024719],"type":"Point"}
}