{
  "type": "Feature",
  "properties": {
    "iso:country":"BE",
    "sg:address":"Italianenlaan 7",
    "sg:city":"Izegem",
    "sg:classifiers":[
        {
            "category":"Professional",
            "subcategory":"Art Services",
            "type":"Services"
        }
    ],
    "sg:phone":"+32 51 31 85 19",
    "sg:postcode":"8870",
    "sg:province":"West-Vlaanderen",
    "sg:tags":[
        "model",
        "manufacturer"
    ],
    "wof:name":"R.c.-cars",
    "wof:placetype":"venue"
},
  "geometry": {"coordinates":[3.2297420502,50.918598175],"type":"Point"}
}