{
  "type": "Feature",
  "properties": {
    "addr:full":"Voorhout 44 Stekene Oost-Vlaanderen 9190",
    "addr:housenumber":"44",
    "addr:postcode":"9190",
    "addr:street":"Voorhout",
    "iso:country":"BE",
    "sg:address":"Voorhout 44",
    "sg:city":"Stekene",
    "sg:orig_category":"Rundveehouders",
    "sg:phone":"+32 3 779 50 31",
    "sg:postcode":"9190",
    "sg:province":"Oost-Vlaanderen",
    "wof:name":"Dirk Van Wiele",
    "wof:placetype":"venue"
},
  "geometry": {"coordinates":[4.069712162,51.2155036926],"type":"Point"}
}