{
  "type": "Feature",
  "properties": {
    "iso:country":"BE",
    "sg:address":"Oudenaardsesteenweg 807",
    "sg:city":"Erpe-mere",
    "sg:classifiers":[
        {
            "category":"Restaurant",
            "type":"Food & Drink"
        }
    ],
    "sg:phone":"+32 53 62 85 68",
    "sg:postcode":"9420",
    "sg:province":"Oost-Vlaanderen",
    "wof:name":"Bonaparte",
    "wof:placetype":"venue"
},
  "geometry": {"coordinates":[3.9210801125,50.9136886597],"type":"Point"}
}