{
  "type": "Feature",
  "properties": {
    "iso:country":"BE",
    "sg:address":"Luxemburgstraat 1a",
    "sg:city":"Oostende",
    "sg:classifiers":[
        {
            "category":"Restaurant",
            "type":"Food & Drink"
        }
    ],
    "sg:phone":"+32 59 50 62 11",
    "sg:postcode":"8400",
    "sg:province":"West-Vlaanderen",
    "wof:name":"Jan Van Campenhout",
    "wof:placetype":"venue"
},
  "geometry": {"coordinates":[2.8884549141,51.2205581665],"type":"Point"}
}