{
  "type": "Feature",
  "properties": {
    "addr:full":"Groot Veerle 3 Brecht (sint-lenaarts) Antwerpen 2960",
    "addr:housenumber":"3",
    "addr:postcode":"2960",
    "addr:street":"Groot Veerle",
    "iso:country":"BE",
    "sg:address":"Groot Veerle 3",
    "sg:city":"Brecht (sint-lenaarts)",
    "sg:classifiers":[
        {
            "category":"Wholesale",
            "subcategory":"Seafood",
            "type":"Manufacturing & Wholesale Goods"
        }
    ],
    "sg:phone":"+32 3 313 81 34",
    "sg:postcode":"2960",
    "sg:province":"Antwerpen",
    "sg:tags":[
        "whol",
        "fish",
        "-",
        "shellfish"
    ],
    "wof:name":"Roem Der Kempen Nv",
    "wof:placetype":"venue"
},
  "geometry": {"coordinates":[4.6744217873,51.3312454224],"type":"Point"}
}