{
  "type": "Feature",
  "properties": {
    "addr:full":"Prins Albertlaan 38 Sint-truiden Limburg 3800",
    "addr:housenumber":"38",
    "addr:postcode":"3800",
    "addr:street":"Prins Albertlaan",
    "iso:country":"BE",
    "sg:address":"Prins Albertlaan 38",
    "sg:city":"Sint-truiden",
    "sg:classifiers":[
        {
            "category":"Banks & Credit Unions",
            "subcategory":"Investment Brokerage",
            "type":"Services"
        }
    ],
    "sg:phone":"+32 11 69 27 79",
    "sg:postcode":"3800",
    "sg:province":"Limburg",
    "sg:tags":[
        "auditor"
    ],
    "wof:name":"Fran\u00e7ois J",
    "wof:placetype":"venue"
},
  "geometry": {"coordinates":[5.1799659729,50.8180580139],"type":"Point"}
}