{
  "type": "Feature",
  "properties": {
    "addr:full":"36-38 Kastelsedijk Dessel Antwerpen 2480",
    "addr:housenumber":"36-38",
    "addr:postcode":"2480",
    "addr:street":"Kastelsedijk",
    "iso:country":"BE",
    "sg:address":"36-38 Kastelsedijk",
    "sg:city":"Dessel",
    "sg:orig_category":"Chemicals and Pharmaceuticals Chemistry - by-products Motor-cars Vehicles and Transport Equipment",
    "sg:phone":"+32 14 32 60 01",
    "sg:postcode":"2480",
    "sg:province":"Antwerpen",
    "wof:name":"Pcs Innotec International Nv",
    "wof:placetype":"venue"
},
  "geometry": {"coordinates":[5.0840959549,51.2322769165],"type":"Point"}
}