{
  "type": "Feature",
  "properties": {
    "addr:full":"Route De Gembloux 10 Eghez\u00e9e Namur 5310",
    "addr:housenumber":"10",
    "addr:postcode":"5310",
    "addr:street":"Route De Gembloux;Namur",
    "iso:country":"BE",
    "sg:address":"Route De Gembloux 10",
    "sg:city":"Eghez\u00e9e",
    "sg:classifiers":[
        {
            "category":"Education",
            "subcategory":"School",
            "type":"Public Place"
        }
    ],
    "sg:phone":"+32 81 81 12 18",
    "sg:postcode":"5310",
    "sg:province":"Namur",
    "sg:tags":[
        "primary"
    ],
    "wof:name":"Ecole Fondamentale Autonome Yannick Leroy",
    "wof:placetype":"venue"
},
  "geometry": {"coordinates":[4.9112610817,50.5915756226],"type":"Point"}
}