{
  "type": "Feature",
  "properties": {
    "addr:full":"Rue Vanderkindere 226-230 Bruxelles (uccle) Bruxelles-Capitale 1180",
    "addr:postcode":"226-230;1180",
    "addr:street":"Rue Vanderkindere",
    "iso:country":"BE",
    "sg:address":"Rue Vanderkindere 226-230",
    "sg:city":"Bruxelles (uccle)",
    "sg:classifiers":[
        {
            "category":"Autos & Motor Vehicles",
            "subcategory":"Auto Supplies",
            "type":"Retail Goods"
        }
    ],
    "sg:phone":"+32 2 346 17 17",
    "sg:postcode":"1180",
    "sg:province":"Bruxelles-Capitale",
    "sg:tags":[
        "automobile",
        "alarm",
        "-",
        "system"
    ],
    "wof:name":"Autophone Center No 1",
    "wof:placetype":"venue"
},
  "geometry": {"coordinates":[4.349545002,50.8140716553],"type":"Point"}
}