{
  "type": "Feature",
  "properties": {
    "addr:full":"Grintweg 37 Oostende West-Vlaanderen 8400",
    "addr:housenumber":"37",
    "addr:postcode":"8400",
    "addr:street":"Grintweg",
    "iso:country":"BE",
    "sg:address":"Grintweg 37",
    "sg:city":"Oostende",
    "sg:classifiers":[
        {
            "category":"Cafe",
            "type":"Food & Drink"
        }
    ],
    "sg:phone":"+32 59 26 74 67",
    "sg:postcode":"8400",
    "sg:province":"West-Vlaanderen",
    "sg:tags":[
        "caf\u00e9s"
    ],
    "wof:name":"Z Vanoverschelde",
    "wof:placetype":"venue"
},
  "geometry": {"coordinates":[2.9126999378,51.2312583923],"type":"Point"}
}