{
  "type": "Feature",
  "properties": {
    "iso:country":"BE",
    "sg:address":"Rue Janson Paul 52",
    "sg:city":"Charleroi (jumet)",
    "sg:classifiers":[
        {
            "category":"Personal",
            "subcategory":"Tattoo Parlor",
            "type":"Services"
        }
    ],
    "sg:phone":"+32 71 34 18 75",
    "sg:postcode":"6040",
    "sg:province":"Hainaut",
    "sg:tags":[
        "tattooists"
    ],
    "wof:name":"Maison Du Tatouage Lucky Tattoo (la)",
    "wof:placetype":"venue"
},
  "geometry": {"coordinates":[4.4129190445,50.4475746155],"type":"Point"}
}