{
  "type": "Feature",
  "properties": {
    "iso:country":"BE",
    "sg:address":"Bulestraat 33",
    "sg:city":"Olen",
    "sg:classifiers":[
        {
            "category":"Home & Garden",
            "subcategory":"Home Furnishings",
            "type":"Retail Goods"
        }
    ],
    "sg:phone":"+32 14 26 71 41",
    "sg:postcode":"2250",
    "sg:province":"Antwerpen",
    "sg:tags":[
        "curtain",
        "-",
        "fixture"
    ],
    "wof:name":"Axent",
    "wof:placetype":"venue"
},
  "geometry": {"coordinates":[4.8631849289,51.1444969177],"type":"Point"}
}