{
  "type": "Feature",
  "properties": {
    "addr:full":"Boterlaarbaan 11 Antwerpen Antwerpen 2100",
    "addr:housenumber":"11",
    "addr:postcode":"2100",
    "addr:street":"Boterlaarbaan",
    "iso:country":"BE",
    "sg:address":"Boterlaarbaan 11",
    "sg:city":"Antwerpen",
    "sg:orig_category":"Rusthuizen and serviceflats",
    "sg:phone":"+32 3 366 28 48",
    "sg:postcode":"2100",
    "sg:province":"Antwerpen",
    "wof:name":"Boterlaarhof",
    "wof:placetype":"venue"
},
  "geometry": {"coordinates":[4.4586100578,51.2203941345],"type":"Point"}
}