{
  "type": "Feature",
  "properties": {
    "addr:full":"Avenue Paul Pastur 145 Charleroi (marcinelle) Hainaut 6001",
    "addr:housenumber":"145",
    "addr:postcode":"6001",
    "addr:street":"Avenue Paul Pastur",
    "iso:country":"BE",
    "sg:address":"Avenue Paul Pastur 145",
    "sg:city":"Charleroi (marcinelle)",
    "sg:classifiers":[
        {
            "category":"Professional",
            "subcategory":"Credit Reporting & Collection",
            "type":"Services"
        }
    ],
    "sg:phone":"+32 71 36 94 17",
    "sg:postcode":"6001",
    "sg:province":"Hainaut",
    "sg:tags":[
        "bailiff"
    ],
    "wof:name":"Demine J-f",
    "wof:placetype":"venue"
},
  "geometry": {"coordinates":[4.4275307655,50.4010543823],"type":"Point"}
}