{
  "type": "Feature",
  "properties": {
    "addr:full":"Patronagestraat 51 Zelzate Oost-Vlaanderen 9060",
    "addr:housenumber":"51",
    "addr:postcode":"9060",
    "addr:street":"Patronagestraat",
    "iso:country":"BE",
    "sg:address":"Patronagestraat 51",
    "sg:city":"Zelzate",
    "sg:classifiers":[
        {
            "category":"Education",
            "subcategory":"School",
            "type":"Public Place"
        }
    ],
    "sg:phone":"+32 9 345 73 12",
    "sg:postcode":"9060",
    "sg:province":"Oost-Vlaanderen",
    "sg:tags":[
        "secondary"
    ],
    "wof:name":"Tisl-mm",
    "wof:placetype":"venue"
},
  "geometry": {"coordinates":[3.81427598,51.2022590637],"type":"Point"}
}