{
  "type": "Feature",
  "properties": {
    "addr:full":"Fredericusstraat 89 Mortsel Antwerpen 2640",
    "addr:housenumber":"89",
    "addr:postcode":"2640",
    "addr:street":"Fredericusstraat",
    "iso:country":"BE",
    "sg:address":"Fredericusstraat 89",
    "sg:city":"Mortsel",
    "sg:orig_category":"Maisons de repos and r\u00e9sidences",
    "sg:phone":"+32 3 455 46 96",
    "sg:postcode":"2640",
    "sg:province":"Antwerpen",
    "wof:name":"Mayerhof",
    "wof:placetype":"venue"
},
  "geometry": {"coordinates":[4.469192028,51.1674041748],"type":"Point"}
}