{
  "type": "Feature",
  "properties": {
    "addr:full":"Molenheiken 45 Brecht Antwerpen 2960",
    "addr:housenumber":"45",
    "addr:postcode":"2960",
    "addr:street":"Molenheiken",
    "iso:country":"BE",
    "sg:address":"Molenheiken 45",
    "sg:city":"Brecht",
    "sg:orig_category":"Eleveurs and marchands de porcs",
    "sg:phone":"+32 3 313 64 95",
    "sg:postcode":"2960",
    "sg:province":"Antwerpen",
    "wof:name":"Ronny Rombouts",
    "wof:placetype":"venue"
},
  "geometry": {"coordinates":[4.6549429893,51.3427276611],"type":"Point"}
}