{
  "type": "Feature",
  "properties": {
    "addr:full":"Boulevard Audent 10 Charleroi Hainaut 6000",
    "addr:housenumber":"10",
    "addr:postcode":"6000",
    "addr:street":"Boulevard Audent;Hainaut",
    "iso:country":"BE",
    "sg:address":"Boulevard Audent 10",
    "sg:city":"Charleroi",
    "sg:orig_category":"Hypotheken and hypotheekbanken Verzekeringsmakelaars and experts",
    "sg:phone":"+32 71 32 59 91",
    "sg:postcode":"6000",
    "sg:province":"Hainaut",
    "wof:name":"Roosens Eric Et Cie",
    "wof:placetype":"venue"
},
  "geometry": {"coordinates":[4.4433817863,50.4098243713],"type":"Point"}
}