{
  "type": "Feature",
  "properties": {
    "addr:full":"Rue Maurice Charlent 53 Bruxelles (auderghem) Bruxelles-Capitale 1160",
    "addr:housenumber":"53",
    "addr:postcode":"1160",
    "addr:street":"Rue Maurice Charlent",
    "iso:country":"BE",
    "sg:address":"Rue Maurice Charlent 53",
    "sg:city":"Bruxelles (auderghem)",
    "sg:classifiers":[
        {
            "category":"Airline",
            "type":"Transportation"
        }
    ],
    "sg:phone":"+32 2 751 80 85",
    "sg:postcode":"1160",
    "sg:province":"Bruxelles-Capitale",
    "wof:name":"Korean Air",
    "wof:placetype":"venue"
},
  "geometry": {"coordinates":[4.4327301979,50.9123344421],"type":"Point"}
}