{
  "type": "Feature",
  "properties": {
    "addr:full":"Avenue Des Alli\u00e9s 75 Malmedy Li\u00e8ge 4960",
    "addr:housenumber":"75",
    "addr:postcode":"4960",
    "addr:street":"Avenue Des Allie\u0301S",
    "iso:country":"BE",
    "sg:address":"Avenue Des Alli\u00e9s 75",
    "sg:city":"Malmedy",
    "sg:classifiers":[
        {
            "category":"Communications",
            "subcategory":"Film & Video Production",
            "type":"Services"
        }
    ],
    "sg:phone":"+32 80 57 15 70",
    "sg:postcode":"4960",
    "sg:province":"Li\u00e8ge",
    "sg:tags":[
        "hiring",
        "-"
    ],
    "wof:name":"Image",
    "wof:placetype":"venue"
},
  "geometry": {"coordinates":[6.0166349411,50.4226837158],"type":"Point"}
}