{
  "type": "Feature",
  "properties": {
    "addr:full":"Rue De Taillis Pr\u00e9 330 Ch\u00e2telet (ch\u00e2telineau) Hainaut 6200",
    "addr:housenumber":"330",
    "addr:postcode":"6200",
    "addr:street":"Rue De Taillis Pre\u0301",
    "iso:country":"BE",
    "sg:address":"Rue De Taillis Pr\u00e9 330",
    "sg:city":"Ch\u00e2telet (ch\u00e2telineau)",
    "sg:classifiers":[
        {
            "category":"Health Services",
            "subcategory":"Health Practitioner",
            "type":"Services"
        }
    ],
    "sg:phone":"+32 71 40 14 72",
    "sg:postcode":"6200",
    "sg:province":"Hainaut",
    "sg:tags":[
        "physiotherapist"
    ],
    "wof:name":"Avril P",
    "wof:placetype":"venue"
},
  "geometry": {"coordinates":[4.5157089233,50.442527771],"type":"Point"}
}