{
  "type": "Feature",
  "properties": {
    "addr:full":"Bruggesteenweg 106 Ruiselede West-Vlaanderen 8755",
    "addr:housenumber":"106",
    "addr:postcode":"8755",
    "addr:street":"Bruggesteenweg",
    "iso:country":"BE",
    "sg:address":"Bruggesteenweg 106",
    "sg:city":"Ruiselede",
    "sg:orig_category":"Juwelen and horloges",
    "sg:phone":"+32 51 68 73 32",
    "sg:postcode":"8755",
    "sg:province":"West-Vlaanderen",
    "wof:name":"Best Friend",
    "wof:placetype":"venue"
},
  "geometry": {"coordinates":[3.3533010483,51.0770835876],"type":"Point"}
}