{
  "type": "Feature",
  "properties": {
    "addr:full":"Rue Gr\u00c9try 151 Li\u00c8ge Li\u00e8ge 4020",
    "addr:housenumber":"151",
    "addr:postcode":"4020",
    "addr:street":"Rue Gre\u0301Try",
    "iso:country":"BE",
    "sg:address":"Rue Gr\u00c9try 151",
    "sg:city":"Li\u00c8ge",
    "sg:orig_category":"Tijdelijke werkgelegenheid and uitzendkantoren",
    "sg:phone":"+32 4 342 07 86",
    "sg:postcode":"4020",
    "sg:province":"Li\u00e8ge",
    "wof:name":"Techno Assist",
    "wof:placetype":"venue"
},
  "geometry": {"coordinates":[5.5836038589,50.6328544617],"type":"Point"}
}