{
  "type": "Feature",
  "properties": {
    "iso:country":"BE",
    "sg:address":"Stationsstraat 78",
    "sg:city":"Hechtel-eksel (eksel)",
    "sg:classifiers":[
        {
            "category":"Shopping",
            "subcategory":"Antiques",
            "type":"Retail Goods"
        }
    ],
    "sg:phone":"+32 11 73 19 18",
    "sg:postcode":"3941",
    "sg:province":"Limburg",
    "wof:name":"De Wan Antiek",
    "wof:placetype":"venue"
},
  "geometry": {"coordinates":[5.4158101082,51.1635551453],"type":"Point"}
}