{
  "type": "Feature",
  "properties": {
    "addr:full":"Noordstraat 27 Retie Antwerpen 2470",
    "addr:housenumber":"27",
    "addr:postcode":"2470",
    "addr:street":"Noordstraat",
    "iso:country":"BE",
    "sg:address":"Noordstraat 27",
    "sg:city":"Retie",
    "sg:classifiers":[
        {
            "category":"Building & Trades",
            "subcategory":"Construction",
            "type":"Services"
        }
    ],
    "sg:phone":"+32 14 37 37 81",
    "sg:postcode":"2470",
    "sg:province":"Antwerpen",
    "sg:tags":[
        "carpenter"
    ],
    "wof:name":"Van Gorp Nv",
    "wof:placetype":"venue"
},
  "geometry": {"coordinates":[5.1176600456,51.2780418396],"type":"Point"}
}