{
  "type": "Feature",
  "properties": {
    "addr:full":"Vrijdagmarkt 5 Antwerpen Antwerpen 2000",
    "addr:housenumber":"5",
    "addr:postcode":"2000",
    "addr:street":"Vrijdagmarkt",
    "iso:country":"BE",
    "sg:address":"Vrijdagmarkt 5",
    "sg:city":"Antwerpen",
    "sg:classifiers":[
        {
            "category":"Bars & Pubs",
            "subcategory":"Lounge",
            "type":"Food & Drink"
        }
    ],
    "sg:phone":"+32 3 231 45 99",
    "sg:postcode":"2000",
    "sg:province":"Antwerpen",
    "sg:tags":[
        "caf\u00e9s"
    ],
    "wof:name":"Caf\u00c9 De Fiets",
    "wof:placetype":"venue"
},
  "geometry": {"coordinates":[4.3990588188,51.2185249329],"type":"Point"}
}