{
  "type": "Feature",
  "properties": {
    "addr:full":"Sint-lievensplein 11ba Herzele Oost-Vlaanderen 9550",
    "addr:postcode":"9550",
    "addr:street":"Sint-Lievensplein;Oost-Vlaanderen",
    "iso:country":"BE",
    "sg:address":"Sint-lievensplein 11ba",
    "sg:city":"Herzele",
    "sg:orig_category":"Banques and organismes de cr\u00e9dit",
    "sg:phone":"+32 54 50 26 27",
    "sg:postcode":"9550",
    "sg:province":"Oost-Vlaanderen",
    "wof:name":"Kbc",
    "wof:placetype":"venue"
},
  "geometry": {"coordinates":[3.8804950714,50.8939285278],"type":"Point"}
}