{
  "type": "Feature",
  "properties": {
    "addr:full":"Alfons Pieterslaan 17 Oostende West-Vlaanderen 8400",
    "addr:housenumber":"17",
    "addr:postcode":"8400",
    "addr:street":"Alfons Pieterslaan",
    "iso:country":"BE",
    "sg:address":"Alfons Pieterslaan 17",
    "sg:city":"Oostende",
    "sg:classifiers":[
        {
            "category":"Travel",
            "subcategory":"Travel Agent",
            "type":"Entertainment"
        }
    ],
    "sg:postcode":"8400",
    "sg:province":"West-Vlaanderen",
    "sg:tags":[
        "agency"
    ],
    "wof:name":"Tui Travelcenter-oostende",
    "wof:placetype":"venue"
},
  "geometry": {"coordinates":[2.9147820473,51.2264175415],"type":"Point"}
}