{
  "type": "Feature",
  "properties": {
    "iso:country":"BE",
    "sg:address":"Place De Linde 8",
    "sg:city":"Anderlecht/anderlecht",
    "sg:classifiers":[
        {
            "category":"Cafe",
            "type":"Food & Drink"
        }
    ],
    "sg:phone":"+32 2 524 28 42",
    "sg:postcode":"1070",
    "sg:province":"Bruxelles-Capitale",
    "sg:tags":[
        "caf\u00e9s"
    ],
    "wof:name":"Caf\u00c9 Extra Time",
    "wof:placetype":"venue"
},
  "geometry": {"coordinates":[4.2998828888,50.8359909058],"type":"Point"}
}