{
  "type": "Feature",
  "properties": {
    "iso:country":"BE",
    "sg:address":"Rue Du Haut Courtil 12",
    "sg:city":"Chiny",
    "sg:orig_category":"Rundveehouders",
    "sg:phone":"+32 61 31 41 62",
    "sg:postcode":"6810",
    "sg:province":"Luxembourg",
    "wof:name":"J Monfort",
    "wof:placetype":"venue"
},
  "geometry": {"coordinates":[5.3405580521,49.7382736206],"type":"Point"}
}