{
  "type": "Feature",
  "properties": {
    "addr:full":"Zandstraat 16c Jabbeke (varsenare) West-Vlaanderen 8490",
    "addr:housenumber":"16c",
    "addr:postcode":"8490",
    "addr:street":"Zandstraat",
    "iso:country":"BE",
    "sg:address":"Zandstraat 16c",
    "sg:city":"Jabbeke (varsenare)",
    "sg:classifiers":[
        {
            "category":"Health Services",
            "subcategory":"Nursing And Care Facility",
            "type":"Services"
        }
    ],
    "sg:phone":"+32 50 39 22 07",
    "sg:postcode":"8490",
    "sg:province":"West-Vlaanderen",
    "sg:tags":[
        "humidifiers",
        "dehydrating",
        "apparatus"
    ],
    "wof:name":"Dryco",
    "wof:placetype":"venue"
},
  "geometry": {"coordinates":[3.1472220421,51.1911659241],"type":"Point"}
}