{
  "type": "Feature",
  "properties": {
    "addr:full":"Rue De L'abattoir 160 Chatelet Hainaut 6200",
    "addr:housenumber":"160",
    "addr:postcode":"chatelet;6200",
    "addr:street":"Rue De L'Abattoir",
    "iso:country":"BE",
    "sg:address":"Rue De L'abattoir 160",
    "sg:city":"Chatelet",
    "sg:orig_category":"Gespecialiseerde niet-residenti\u00eble bouw",
    "sg:phone":"+32 71 38 55 12",
    "sg:postcode":"6200",
    "sg:province":"Hainaut",
    "wof:name":"F\u00c9rom\u00c9tal",
    "wof:placetype":"venue"
},
  "geometry": {"coordinates":[4.5262379646,50.4085960388],"type":"Point"}
}