{
  "type": "Feature",
  "properties": {
    "addr:full":"Vis\u00e9steenweg 292a Riemst Limburg 3770",
    "addr:housenumber":"292a",
    "addr:postcode":"3770",
    "addr:street":"Vise\u0301Steenweg",
    "iso:country":"BE",
    "sg:address":"Vis\u00e9steenweg 292a",
    "sg:city":"Riemst",
    "sg:classifiers":[
        {
            "category":"Shopping",
            "subcategory":"Stationery & Office Supplies",
            "type":"Retail Goods"
        }
    ],
    "sg:phone":"+32 12 45 33 31",
    "sg:postcode":"3770",
    "sg:province":"Limburg",
    "sg:tags":[
        "partition"
    ],
    "wof:name":"Megafin Bvba",
    "wof:placetype":"venue"
},
  "geometry": {"coordinates":[5.606347084,50.8036117554],"type":"Point"}
}