{
  "type": "Feature",
  "properties": {
    "addr:full":"Rue Faider 87 Bruxelles (ixelles) Bruxelles-Capitale 1050",
    "addr:housenumber":"87",
    "addr:postcode":"1050",
    "addr:street":"Rue Faider",
    "iso:country":"BE",
    "sg:address":"Rue Faider 87",
    "sg:city":"Bruxelles (ixelles)",
    "sg:classifiers":[
        {
            "category":"Professional",
            "subcategory":"Management & Consulting",
            "type":"Services"
        }
    ],
    "sg:phone":"+32 2 537 26 03",
    "sg:postcode":"1050",
    "sg:province":"Bruxelles-Capitale",
    "sg:tags":[
        "consultant"
    ],
    "wof:name":"Single Market Ventures Sprl",
    "wof:placetype":"venue"
},
  "geometry": {"coordinates":[4.3596191406,50.826839447],"type":"Point"}
}