{
  "type": "Feature",
  "properties": {
    "addr:full":"Rue Du Plagniau 32 Rixensart Brabant Wallon 1330",
    "addr:housenumber":"32",
    "addr:postcode":"1330",
    "addr:street":"Rue Du Plagniau;Wallon",
    "iso:country":"BE",
    "sg:address":"Rue Du Plagniau 32",
    "sg:city":"Rixensart",
    "sg:classifiers":[
        {
            "category":"Building & Trades",
            "subcategory":"Electrical",
            "type":"Services"
        }
    ],
    "sg:phone":"+32 2 654 17 65",
    "sg:postcode":"1330",
    "sg:province":"Brabant Wallon",
    "sg:tags":[
        "-",
        "electric",
        "contractor"
    ],
    "wof:name":"Milan A",
    "wof:placetype":"venue"
},
  "geometry": {"coordinates":[4.5338702202,50.7215499878],"type":"Point"}
}