{
  "type": "Feature",
  "properties": {
    "iso:country":"BE",
    "sg:address":"Route Du Hotchet 7",
    "sg:city":"Bouillon",
    "sg:orig_category":"S\u00e9curit\u00e9 sociale",
    "sg:phone":"+32 61 46 67 95",
    "sg:postcode":"6830",
    "sg:province":"Luxembourg",
    "wof:name":"Mutualit\u00c9 Neutre",
    "wof:placetype":"venue"
},
  "geometry": {"coordinates":[5.0699849129,49.7954597473],"type":"Point"}
}