{
  "type": "Feature",
  "properties": {
    "iso:country":"BE",
    "sg:address":"Theofiel Lybaertstraat 37",
    "sg:city":"Gent",
    "sg:classifiers":[
        {
            "category":"Arena",
            "subcategory":"Sports Club",
            "type":"Entertainment"
        }
    ],
    "sg:phone":"+32 475 46 14 53",
    "sg:postcode":"9040",
    "sg:province":"Oost-Vlaanderen",
    "sg:tags":[
        "de"
    ],
    "wof:name":"W.t.c. Meerakker",
    "wof:placetype":"venue"
},
  "geometry": {"coordinates":[3.7741138935,51.0726737976],"type":"Point"}
}