{
  "type": "Feature",
  "properties": {
    "addr:full":"Pastorijstraat 1 Boortmeerbeek Vlaams-Brabant 3190",
    "addr:housenumber":"1",
    "addr:postcode":"3190",
    "addr:street":"Pastorijstraat",
    "iso:country":"BE",
    "sg:address":"Pastorijstraat 1",
    "sg:city":"Boortmeerbeek",
    "sg:classifiers":[
        {
            "category":"Shopping",
            "subcategory":"Shoes",
            "type":"Retail Goods"
        }
    ],
    "sg:phone":"+32 15 51 63 10",
    "sg:postcode":"3190",
    "sg:province":"Vlaams-Brabant",
    "sg:tags":[
        "slipper",
        "-"
    ],
    "wof:name":"Phil Schoenen",
    "wof:placetype":"venue"
},
  "geometry": {"coordinates":[4.572329998,50.9815406799],"type":"Point"}
}