{
  "type": "Feature",
  "properties": {
    "addr:full":"Zeelaan 152 De Panne West-Vlaanderen 8660",
    "addr:housenumber":"152",
    "addr:postcode":"8660",
    "addr:street":"Zeelaan",
    "iso:country":"BE",
    "sg:address":"Zeelaan 152",
    "sg:city":"De Panne",
    "sg:orig_category":"Banques and organismes de cr\u00e9dit",
    "sg:phone":"+32 58 41 11 31",
    "sg:postcode":"8660",
    "sg:province":"West-Vlaanderen",
    "wof:name":"Bbl",
    "wof:placetype":"venue"
},
  "geometry": {"coordinates":[2.5922191143,51.1014404297],"type":"Point"}
}