{
  "type": "Feature",
  "properties": {
    "addr:full":"Kakelenberg 20 Geraardsbergen Oost-Vlaanderen 9506",
    "addr:housenumber":"20",
    "addr:postcode":"9506",
    "addr:street":"Kakelenberg",
    "iso:country":"BE",
    "sg:address":"Kakelenberg 20",
    "sg:city":"Geraardsbergen",
    "sg:classifiers":[
        {
            "category":"Personal",
            "subcategory":"Beauty Salon",
            "type":"Services"
        }
    ],
    "sg:phone":"+32 54 33 43 26",
    "sg:postcode":"9506",
    "sg:province":"Oost-Vlaanderen",
    "sg:tags":[
        "de",
        "coiffure"
    ],
    "wof:name":"Coiffure Hedwige",
    "wof:placetype":"venue"
},
  "geometry": {"coordinates":[3.9559540749,50.7921676636],"type":"Point"}
}