{
  "type": "Feature",
  "properties": {
    "iso:country":"BE",
    "sg:address":"Peltheide 13",
    "sg:city":"Haacht",
    "sg:classifiers":[
        {
            "category":"Banks & Credit Unions",
            "subcategory":"Investment Brokerage",
            "type":"Services"
        }
    ],
    "sg:phone":"+32 16 60 25 41",
    "sg:postcode":"3150",
    "sg:province":"Vlaams-Brabant",
    "sg:tags":[
        "auditor"
    ],
    "wof:name":"Bellekens A.l",
    "wof:placetype":"venue"
},
  "geometry": {"coordinates":[4.6311187744,50.9769744873],"type":"Point"}
}