{
  "type": "Feature",
  "properties": {
    "addr:full":"Bodenbroekstraat 14 Brussel/bruxelles Bruxelles-Capitale 1000",
    "addr:housenumber":"14",
    "addr:postcode":"1000",
    "addr:street":"Bodenbroekstraat;/",
    "iso:country":"BE",
    "sg:address":"Bodenbroekstraat 14",
    "sg:city":"Brussel/bruxelles",
    "sg:orig_category":"Antiek",
    "sg:phone":"+32 2 511 57 08",
    "sg:postcode":"1000",
    "sg:province":"Bruxelles-Capitale",
    "wof:name":"Maison Extr\u00cames",
    "wof:placetype":"venue"
},
  "geometry": {"coordinates":[4.3564238548,50.8408508301],"type":"Point"}
}