{
  "type": "Feature",
  "properties": {
    "addr:full":"Hofeinde 27 Merksplas Antwerpen 2330",
    "addr:housenumber":"27",
    "addr:postcode":"2330",
    "addr:street":"Hofeinde",
    "iso:country":"BE",
    "sg:address":"Hofeinde 27",
    "sg:city":"Merksplas",
    "sg:orig_category":"Sportclubs",
    "sg:phone":"+32 14 63 58 28",
    "sg:postcode":"2330",
    "sg:province":"Antwerpen",
    "wof:name":"De Witpen",
    "wof:placetype":"venue"
},
  "geometry": {"coordinates":[4.8629479408,51.3646087646],"type":"Point"}
}