{
  "type": "Feature",
  "properties": {
    "iso:country":"BE",
    "sg:address":"Avenue Legrand 8",
    "sg:city":"Brussel/bruxelles",
    "sg:orig_category":"Imprimeries and copyshops. Activit\u00e9s diverses d'imprimerie",
    "sg:phone":"+32 2 640 72 50",
    "sg:postcode":"1000",
    "sg:province":"Bruxelles-Capitale",
    "wof:name":"Eurographics",
    "wof:placetype":"venue"
},
  "geometry": {"coordinates":[4.3715028763,50.8153991699],"type":"Point"}
}