{
  "type": "Feature",
  "properties": {
    "addr:full":"Lange Scholiersstraat 86-88 Antwerpen Antwerpen 2060",
    "addr:postcode":"86-88;2060",
    "addr:street":"Lange Scholiersstraat",
    "iso:country":"BE",
    "sg:address":"Lange Scholiersstraat 86-88",
    "sg:city":"Antwerpen",
    "sg:classifiers":[
        {
            "category":"Bakery",
            "type":"Food & Drink"
        }
    ],
    "sg:phone":"+32 3 272 08 43",
    "sg:postcode":"2060",
    "sg:province":"Antwerpen",
    "sg:tags":[
        "confectioner",
        "baker"
    ],
    "wof:name":"Stuivenberg Bvba",
    "wof:placetype":"venue"
},
  "geometry": {"coordinates":[4.4296550751,51.2247543335],"type":"Point"}
}