{
  "type": "Feature",
  "properties": {
    "iso:country":"BE",
    "sg:address":"Ouren 6",
    "sg:city":"Burg-reuland",
    "sg:classifiers":[
        {
            "category":"Travel",
            "subcategory":"Hotels & Motels",
            "type":"Entertainment"
        }
    ],
    "sg:phone":"+32 80 32 92 64",
    "sg:postcode":"4790",
    "sg:province":"Li\u00e8ge",
    "wof:name":"Hotel Residenz",
    "wof:placetype":"venue"
},
  "geometry": {"coordinates":[6.1385450363,50.1416664124],"type":"Point"}
}