{
  "type": "Feature",
  "properties": {
    "addr:full":"Chauss\u00c9e De Waterloo 788 Ukkel/uccle Bruxelles-Capitale 1180",
    "addr:housenumber":"788",
    "addr:postcode":"1180",
    "addr:street":"Chausse\u0301E De Waterloo;/",
    "iso:country":"BE",
    "sg:address":"Chauss\u00c9e De Waterloo 788",
    "sg:city":"Ukkel/uccle",
    "sg:orig_category":"M\u00e9decins and sp\u00e9cialistes",
    "sg:phone":"+32 2 372 23 51",
    "sg:postcode":"1180",
    "sg:province":"Bruxelles-Capitale",
    "wof:name":"D. Barbieux",
    "wof:placetype":"venue"
},
  "geometry": {"coordinates":[4.3674502373,50.8146095276],"type":"Point"}
}