{
  "type": "Feature",
  "properties": {
    "iso:country":"BE",
    "sg:address":"Bedrijfsstraat 14",
    "sg:city":"Hasselt",
    "sg:orig_category":"Airconditioning and ventilatie Winkelinrichting and handelsuitrusting Gh",
    "sg:phone":"+32 11 26 38 40",
    "sg:postcode":"3500",
    "sg:province":"Limburg",
    "wof:name":"Van Cleven",
    "wof:placetype":"venue"
},
  "geometry": {"coordinates":[5.362596035,50.9554786682],"type":"Point"}
}