{
  "type": "Feature",
  "properties": {
    "addr:full":"Rue Des Puits L'eau 10 Tournai Hainaut 7500",
    "addr:housenumber":"10",
    "addr:postcode":"7500",
    "addr:street":"Rue Des Puits L'Eau",
    "iso:country":"BE",
    "sg:address":"Rue Des Puits L'eau 10",
    "sg:city":"Tournai",
    "sg:classifiers":[
        {
            "category":"Real Estate",
            "subcategory":"Architect",
            "type":"Services"
        }
    ],
    "sg:phone":"+32 69 84 37 25",
    "sg:postcode":"7500",
    "sg:province":"Hainaut",
    "wof:name":"Atelier G Architectes Sprl",
    "wof:placetype":"venue"
},
  "geometry": {"coordinates":[3.392647028,50.6060714722],"type":"Point"}
}