{
  "type": "Feature",
  "properties": {
    "iso:country":"BE",
    "sg:address":"Rue Des Praules 6",
    "sg:city":"Gembloux-sur-orneau (gembloux)",
    "sg:orig_category":"Non-Classified Establishments",
    "sg:phone":"+32 81 61 62 80",
    "sg:postcode":"5030",
    "sg:province":"Namur",
    "wof:name":"Inpaco",
    "wof:placetype":"venue"
},
  "geometry": {"coordinates":[4.6979699135,50.5615348816],"type":"Point"}
}