{
  "type": "Feature",
  "properties": {
    "iso:country":"BE",
    "sg:address":"Rue Chapelle Sainte Anne 24",
    "sg:city":"Walhain (walhain-saint-paul)",
    "sg:classifiers":[
        {
            "category":"Sports & Exercise",
            "subcategory":"Stables",
            "type":"Entertainment"
        }
    ],
    "sg:phone":"+32 10 65 02 77",
    "sg:postcode":"1457",
    "sg:province":"Brabant Wallon",
    "sg:tags":[
        "riding",
        "school"
    ],
    "wof:name":"Cercle Equestre La Balzane Sprl",
    "wof:placetype":"venue"
},
  "geometry": {"coordinates":[4.6986689568,50.617313385],"type":"Point"}
}