{
  "type": "Feature",
  "properties": {
    "iso:country":"BE",
    "sg:address":"Rue Du Relais 1",
    "sg:city":"Somme-leuze (sinsin)",
    "sg:classifiers":[
        {
            "category":"Manufacturing",
            "subcategory":"Chemicals & Compounds",
            "type":"Manufacturing & Wholesale Goods"
        }
    ],
    "sg:phone":"+32 83 68 87 01",
    "sg:postcode":"5377",
    "sg:province":"Namur",
    "sg:tags":[
        "pharmaceutical",
        "product"
    ],
    "wof:name":"Pierson F",
    "wof:placetype":"venue"
},
  "geometry": {"coordinates":[5.245549202,50.2687683105],"type":"Point"}
}