{
  "type": "Feature",
  "properties": {
    "addr:full":"Paepestraat 64a Wichelen Oost-Vlaanderen 9260",
    "addr:housenumber":"64a",
    "addr:postcode":"9260",
    "addr:street":"Paepestraat",
    "iso:country":"BE",
    "sg:address":"Paepestraat 64a",
    "sg:city":"Wichelen",
    "sg:classifiers":[
        {
            "category":"Professional",
            "subcategory":"Testing Lab",
            "type":"Services"
        }
    ],
    "sg:phone":"+32 52 42 46 46",
    "sg:postcode":"9260",
    "sg:province":"Oost-Vlaanderen",
    "sg:tags":[
        "chemist"
    ],
    "wof:name":"Van Schepdael L",
    "wof:placetype":"venue"
},
  "geometry": {"coordinates":[3.9706730843,50.9987983704],"type":"Point"}
}