{
  "type": "Feature",
  "properties": {
    "iso:country":"BE",
    "sg:address":"Ringlaan 20",
    "sg:city":"Kortrijk (heule)",
    "sg:classifiers":[
        {
            "category":"Retail",
            "subcategory":"Car Wash",
            "type":"Services"
        }
    ],
    "sg:phone":"+32 56 35 27 62",
    "sg:postcode":"8501",
    "sg:province":"West-Vlaanderen",
    "sg:tags":[
        "automobile",
        "washing",
        "-",
        "truck"
    ],
    "wof:name":"Van Paemel J-m",
    "wof:placetype":"venue"
},
  "geometry": {"coordinates":[3.2504220009,50.8520927429],"type":"Point"}
}