{
  "type": "Feature",
  "properties": {
    "addr:full":"Ue De Roloux 39d Fexhe-le-haut-clocher Li\u00e8ge 4347",
    "addr:housenumber":"39d",
    "addr:postcode":"4347",
    "iso:country":"BE",
    "sg:address":"Ue De Roloux 39d",
    "sg:city":"Fexhe-le-haut-clocher",
    "sg:orig_category":"Notaires",
    "sg:phone":"+32 4 250 10 56",
    "sg:postcode":"4347",
    "sg:province":"Li\u00e8ge",
    "wof:name":"Philippe Crismer",
    "wof:placetype":"venue"
},
  "geometry": {"coordinates":[5.3988580704,50.6602592468],"type":"Point"}
}