{
  "type": "Feature",
  "properties": {
    "addr:full":"Rue De L'amazone 18 Bruxelles (ixelles) Bruxelles-Capitale 1050",
    "addr:housenumber":"18",
    "addr:postcode":"1050",
    "addr:street":"Rue De L'Amazone",
    "iso:country":"BE",
    "sg:address":"Rue De L'amazone 18",
    "sg:city":"Bruxelles (ixelles)",
    "sg:classifiers":[
        {
            "category":"Shopping",
            "subcategory":"Jewelry",
            "type":"Retail Goods"
        }
    ],
    "sg:phone":"+32 2 539 15 96",
    "sg:postcode":"1050",
    "sg:province":"Bruxelles-Capitale",
    "sg:tags":[
        "-",
        "imitation"
    ],
    "wof:name":"Dedee K",
    "wof:placetype":"venue"
},
  "geometry": {"coordinates":[4.3587040901,50.8247718811],"type":"Point"}
}