{
  "type": "Feature",
  "properties": {
    "addr:full":"Smallerijt 2 Geel Antwerpen 2440",
    "addr:housenumber":"2",
    "addr:postcode":"2440",
    "addr:street":"Smallerijt",
    "iso:country":"BE",
    "sg:address":"Smallerijt 2",
    "sg:city":"Geel",
    "sg:orig_category":"Boissons",
    "sg:phone":"+32 14 54 44 70",
    "sg:postcode":"2440",
    "sg:province":"Antwerpen",
    "wof:name":"Brouwerij Fisser",
    "wof:placetype":"venue"
},
  "geometry": {"coordinates":[4.9906659126,51.1610794067],"type":"Point"}
}