{
  "type": "Feature",
  "properties": {
    "iso:country":"BE",
    "sg:address":"Chemin Du Saiwet 41",
    "sg:city":"Bastogne",
    "sg:classifiers":[
        {
            "category":"Building & Trades",
            "subcategory":"Construction",
            "type":"Services"
        }
    ],
    "sg:phone":"+32 61 21 42 15",
    "sg:postcode":"6600",
    "sg:province":"Luxembourg",
    "sg:tags":[
        "stucco",
        "contractor"
    ],
    "wof:name":"Pondant D",
    "wof:placetype":"venue"
},
  "geometry": {"coordinates":[5.7241158485,49.9825592041],"type":"Point"}
}