{
  "type": "Feature",
  "properties": {
    "addr:full":"Sint-willibrordusplein 3 Heusden-zolder (heusden) Limburg 3550",
    "addr:housenumber":"3",
    "addr:postcode":"3550",
    "addr:street":"Sint-Willibrordusplein",
    "iso:country":"BE",
    "sg:address":"Sint-willibrordusplein 3",
    "sg:city":"Heusden-zolder (heusden)",
    "sg:classifiers":[
        {
            "category":"Shopping",
            "subcategory":"Clothing, Apparel, & Fashions",
            "type":"Retail Goods"
        }
    ],
    "sg:phone":"+32 11 43 31 61",
    "sg:postcode":"3550",
    "sg:province":"Limburg",
    "sg:tags":[
        "clothing",
        "-",
        "motorbike",
        "equipment"
    ],
    "wof:name":"Ducati-zolder",
    "wof:placetype":"venue"
},
  "geometry": {"coordinates":[5.2825469971,51.033493042],"type":"Point"}
}