{
  "type": "Feature",
  "properties": {
    "addr:full":"Rue Du Commerce 18 Marche-en-famenne Luxembourg 6900",
    "addr:housenumber":"18",
    "addr:postcode":"6900",
    "addr:street":"Rue Du Commerce",
    "iso:country":"BE",
    "sg:address":"Rue Du Commerce 18",
    "sg:city":"Marche-en-famenne",
    "sg:classifiers":[
        {
            "category":"Shopping",
            "subcategory":"Luggage & Leather Goods",
            "type":"Retail Goods"
        }
    ],
    "sg:phone":"+32 84 31 15 13",
    "sg:postcode":"6900",
    "sg:province":"Luxembourg",
    "sg:tags":[
        "-"
    ],
    "wof:name":"Claisse R",
    "wof:placetype":"venue"
},
  "geometry": {"coordinates":[5.3441948891,50.227142334],"type":"Point"}
}