{
  "type": "Feature",
  "properties": {
    "addr:full":"Fonteinstraat 67 Turnhout Antwerpen 2300",
    "addr:housenumber":"67",
    "addr:postcode":"2300",
    "addr:street":"Fonteinstraat",
    "iso:country":"BE",
    "sg:address":"Fonteinstraat 67",
    "sg:city":"Turnhout",
    "sg:orig_category":"Entretien and r\u00e9parations de voitures",
    "sg:phone":"+32 14 41 09 02",
    "sg:postcode":"2300",
    "sg:province":"Antwerpen",
    "wof:name":"Andre Wouters",
    "wof:placetype":"venue"
},
  "geometry": {"coordinates":[4.9292531013,51.3307876587],"type":"Point"}
}