{
  "type": "Feature",
  "properties": {
    "iso:country":"BE",
    "sg:address":"Brouckhof Oost 18",
    "sg:city":"Zonnebeke (passendale)",
    "sg:classifiers":[
        {
            "category":"Professional",
            "type":"Services"
        }
    ],
    "sg:phone":"+32 475 34 27 68",
    "sg:postcode":"8980",
    "sg:province":"West-Vlaanderen",
    "sg:tags":[
        "industrial",
        "work",
        "-",
        "maintenance"
    ],
    "wof:name":"Labaere L",
    "wof:placetype":"venue"
},
  "geometry": {"coordinates":[3.028660059,50.9003639221],"type":"Point"}
}