{
  "type": "Feature",
  "properties": {
    "addr:full":"Heldenplein Zaventem Vlaams-Brabant 1930",
    "addr:postcode":"1930",
    "addr:street":"Heldenplein",
    "iso:country":"BE",
    "sg:address":"Heldenplein",
    "sg:city":"Zaventem",
    "sg:orig_category":"Transports ferroviaires",
    "sg:phone":"+32 2 224 83 26",
    "sg:postcode":"1930",
    "sg:province":"Vlaams-Brabant",
    "wof:name":"Station Zaventem",
    "wof:placetype":"venue"
},
  "geometry": {"coordinates":[4.4710521698,50.8846664429],"type":"Point"}
}