{
  "type": "Feature",
  "properties": {
    "addr:full":"Rue De Montm\u00c9dy 14 Virton Luxembourg 6760",
    "addr:housenumber":"14",
    "addr:postcode":"6760",
    "addr:street":"Rue De Montme\u0301Dy",
    "iso:country":"BE",
    "sg:address":"Rue De Montm\u00c9dy 14",
    "sg:city":"Virton",
    "sg:orig_category":"Epiceries",
    "sg:phone":"+32 63 57 73 13",
    "sg:postcode":"6760",
    "sg:province":"Luxembourg",
    "wof:name":"Spar",
    "wof:placetype":"venue"
},
  "geometry": {"coordinates":[5.5182051659,49.5649375916],"type":"Point"}
}