{
  "type": "Feature",
  "properties": {
    "iso:country":"BE",
    "sg:address":"Geluwesesteenweg 67",
    "sg:city":"Wervik",
    "sg:classifiers":[
        {
            "category":"Personal",
            "subcategory":"Beauty Salon",
            "type":"Services"
        }
    ],
    "sg:phone":"+32 56 52 08 14",
    "sg:postcode":"8940",
    "sg:province":"West-Vlaanderen",
    "wof:name":"Beauty And Nails",
    "wof:placetype":"venue"
},
  "geometry": {"coordinates":[3.0505180359,50.7905845642],"type":"Point"}
}