{
  "type": "Feature",
  "properties": {
    "iso:country":"BE",
    "sg:address":"Desir\u00c9 Van Hoomissenstr. 6",
    "sg:city":"Bornem",
    "sg:orig_category":"Voertuigen",
    "sg:phone":"+32 3 889 01 44",
    "sg:postcode":"2880",
    "sg:province":"Antwerpen",
    "wof:name":"Kris Hens",
    "wof:placetype":"venue"
},
  "geometry": {"coordinates":[4.3049759865,51.0917053223],"type":"Point"}
}