{
  "type": "Feature",
  "properties": {
    "addr:full":"Rue De La Madeleine 6 Courcelles (souvret) Hainaut 6182",
    "addr:housenumber":"6",
    "addr:postcode":"6182",
    "addr:street":"Rue De La Madeleine",
    "iso:country":"BE",
    "sg:address":"Rue De La Madeleine 6",
    "sg:city":"Courcelles (souvret)",
    "sg:classifiers":[
        {
            "category":"Professional",
            "subcategory":"Engineering",
            "type":"Services"
        }
    ],
    "sg:phone":"+32 71 46 04 20",
    "sg:postcode":"6182",
    "sg:province":"Hainaut",
    "sg:tags":[
        "technical",
        "equipment",
        "offices-"
    ],
    "wof:name":"Idti",
    "wof:placetype":"venue"
},
  "geometry": {"coordinates":[4.3423352242,50.4470596313],"type":"Point"}
}