{
  "type": "Feature",
  "properties": {
    "iso:country":"BE",
    "sg:address":"Dorpstraat 49",
    "sg:city":"Jabbeke",
    "sg:orig_category":"Bijouteries and horlogeries. R\u00e9parations d'horloges, montres and bijoux",
    "sg:phone":"+32 50 81 20 33",
    "sg:postcode":"8490",
    "sg:province":"West-Vlaanderen",
    "wof:name":"M'onyx's",
    "wof:placetype":"venue"
},
  "geometry": {"coordinates":[3.0897641182,51.1817207336],"type":"Point"}
}