{
  "type": "Feature",
  "properties": {
    "addr:full":"Oorlogsinvalidenlaan 2ba Middelkerke West-Vlaanderen 8434",
    "addr:postcode":"8434",
    "addr:street":"Oorlogsinvalidenlaan",
    "iso:country":"BE",
    "sg:address":"Oorlogsinvalidenlaan 2ba",
    "sg:city":"Middelkerke",
    "sg:orig_category":"Schoonheidssalons",
    "sg:phone":"+32 59 30 10 14",
    "sg:postcode":"8434",
    "sg:province":"West-Vlaanderen",
    "wof:name":"Michael Duprez",
    "wof:placetype":"venue"
},
  "geometry": {"coordinates":[2.7569050789,51.1488685608],"type":"Point"}
}