{
  "type": "Feature",
  "properties": {
    "iso:country":"BE",
    "sg:address":"Winkelcentrum Rijselpoort",
    "sg:city":"Ieper (groot)",
    "sg:orig_category":"Baby- and kinderkleding Dameskledingzaken Herenkledingzaken",
    "sg:phone":"+32 57 42 46 16",
    "sg:postcode":"8900",
    "sg:province":"West-Vlaanderen",
    "wof:name":"E5 Mode",
    "wof:placetype":"venue"
},
  "geometry": {"coordinates":[2.890130043,50.8442382812],"type":"Point"}
}