{
  "type": "Feature",
  "properties": {
    "iso:country":"BE",
    "sg:address":"Pastoor Goossenslaan 39",
    "sg:city":"Maasmechelen",
    "sg:classifiers":[
        {
            "category":"Arena",
            "subcategory":"Sports Club",
            "type":"Entertainment"
        }
    ],
    "sg:phone":"+32 89 71 46 95",
    "sg:postcode":"3631",
    "sg:province":"Limburg",
    "sg:tags":[
        "de"
    ],
    "wof:name":"V.c. Uvoc Uikhoven",
    "wof:placetype":"venue"
},
  "geometry": {"coordinates":[5.7239232063,50.9423713684],"type":"Point"}
}