{
  "type": "Feature",
  "properties": {
    "addr:full":"Chauss\u00c9e De Philippeville 219 Charleroi Hainaut 6010",
    "addr:housenumber":"219",
    "addr:postcode":"6010",
    "addr:street":"Chausse\u0301E De Philippeville;Hainaut",
    "iso:country":"BE",
    "sg:address":"Chauss\u00c9e De Philippeville 219",
    "sg:city":"Charleroi",
    "sg:orig_category":"Supermarkten",
    "sg:phone":"+32 71 43 30 57",
    "sg:postcode":"6010",
    "sg:province":"Hainaut",
    "wof:name":"Match",
    "wof:placetype":"venue"
},
  "geometry": {"coordinates":[4.4621329308,50.3870429993],"type":"Point"}
}