{
  "type": "Feature",
  "properties": {
    "addr:full":"Generaal Deprezstraat 17 Harelbeke West-Vlaanderen 8530",
    "addr:housenumber":"17",
    "addr:postcode":"8530",
    "addr:street":"Generaal Deprezstraat",
    "iso:country":"BE",
    "sg:address":"Generaal Deprezstraat 17",
    "sg:city":"Harelbeke",
    "sg:classifiers":[
        {
            "category":"Fast Food",
            "type":"Food & Drink"
        }
    ],
    "sg:phone":"+32 56 25 33 07",
    "sg:postcode":"8530",
    "sg:province":"West-Vlaanderen",
    "sg:tags":[
        "\u00c0",
        "restaurants",
        "emporter",
        "restaurant"
    ],
    "wof:name":"Frietshop",
    "wof:placetype":"venue"
},
  "geometry": {"coordinates":[3.3127789497,50.8362579346],"type":"Point"}
}