{
  "type": "Feature",
  "properties": {
    "iso:country":"BE",
    "sg:address":"Hoogstraat 141",
    "sg:city":"Lede",
    "sg:orig_category":"V\u00e9t\u00e9rinaires",
    "sg:phone":"+32 53 80 88 54",
    "sg:postcode":"9340",
    "sg:province":"Oost-Vlaanderen",
    "wof:name":"Koen Van Ommeslaeghe",
    "wof:placetype":"venue"
},
  "geometry": {"coordinates":[3.9779689312,50.9562454224],"type":"Point"}
}