{
  "type": "Feature",
  "properties": {
    "addr:full":"Mastellestraat 33 Herent Vlaams-Brabant 3020",
    "addr:housenumber":"33",
    "addr:postcode":"3020",
    "addr:street":"Mastellestraat",
    "iso:country":"BE",
    "sg:address":"Mastellestraat 33",
    "sg:city":"Herent",
    "sg:orig_category":"M\u00e9decins and sp\u00e9cialistes",
    "sg:phone":"+32 16 49 05 15",
    "sg:postcode":"3020",
    "sg:province":"Vlaams-Brabant",
    "wof:name":"Thomas Maselis",
    "wof:placetype":"venue"
},
  "geometry": {"coordinates":[4.6749200821,50.9079055786],"type":"Point"}
}