{
  "type": "Feature",
  "properties": {
    "addr:full":"Rue De Cuesmes 102 Mons (jemappes) Hainaut 7012",
    "addr:housenumber":"102",
    "addr:postcode":"7012",
    "addr:street":"Rue De Cuesmes",
    "iso:country":"BE",
    "sg:address":"Rue De Cuesmes 102",
    "sg:city":"Mons (jemappes)",
    "sg:classifiers":[
        {
            "category":"Health Services",
            "subcategory":"Doctor",
            "type":"Services"
        }
    ],
    "sg:phone":"+32 65 82 48 80",
    "sg:postcode":"7012",
    "sg:province":"Hainaut",
    "sg:tags":[
        "medicinephysicians",
        "surgeon"
    ],
    "wof:name":"Chevalier S",
    "wof:placetype":"venue"
},
  "geometry": {"coordinates":[3.9426341057,50.445438385],"type":"Point"}
}