{
  "type": "Feature",
  "properties": {
    "iso:country":"BE",
    "sg:address":"Rue Des Combattants 123",
    "sg:city":"La Hulpe",
    "sg:orig_category":"Antiek",
    "sg:phone":"+32 2 653 08 37",
    "sg:postcode":"1310",
    "sg:province":"Brabant Wallon",
    "wof:name":"Maison Artwood",
    "wof:placetype":"venue"
},
  "geometry": {"coordinates":[4.4854059219,50.7306556702],"type":"Point"}
}