{
  "type": "Feature",
  "properties": {
    "addr:full":"Sint-jansstraat 78 Staden West-Vlaanderen 8840",
    "addr:housenumber":"78",
    "addr:postcode":"8840",
    "addr:street":"Sint-Jansstraat",
    "iso:country":"BE",
    "sg:address":"Sint-jansstraat 78",
    "sg:city":"Staden",
    "sg:classifiers":[
        {
            "category":"Travel",
            "subcategory":"Travel Agent",
            "type":"Entertainment"
        }
    ],
    "sg:phone":"+32 51 70 56 11",
    "sg:postcode":"8840",
    "sg:province":"West-Vlaanderen",
    "sg:tags":[
        "agency"
    ],
    "wof:name":"Aussie Tours",
    "wof:placetype":"venue"
},
  "geometry": {"coordinates":[3.0156478882,50.9737434387],"type":"Point"}
}