{
  "type": "Feature",
  "properties": {
    "addr:full":"Meensesteenweg 357 Roeselare West-Vlaanderen 8800",
    "addr:housenumber":"357",
    "addr:postcode":"8800",
    "addr:street":"Meensesteenweg",
    "iso:country":"BE",
    "sg:address":"Meensesteenweg 357",
    "sg:city":"Roeselare",
    "sg:classifiers":[
        {
            "category":"Professional",
            "subcategory":"Lawyer & Legal Services",
            "type":"Services"
        }
    ],
    "sg:phone":"+32 51 26 83 00",
    "sg:postcode":"8800",
    "sg:province":"West-Vlaanderen",
    "wof:name":"Plesters Leen",
    "wof:placetype":"venue"
},
  "geometry": {"coordinates":[3.1191599369,50.9288711548],"type":"Point"}
}