{
  "type": "Feature",
  "properties": {
    "addr:full":"Avenue De La Concorde 47 Seraing Li\u00e8ge 4100",
    "addr:housenumber":"47",
    "addr:postcode":"4100",
    "addr:street":"Avenue De La Concorde",
    "iso:country":"BE",
    "sg:address":"Avenue De La Concorde 47",
    "sg:city":"Seraing",
    "sg:orig_category":"Benzinestations and brandstoffen",
    "sg:phone":"+32 4 336 81 27",
    "sg:postcode":"4100",
    "sg:province":"Li\u00e8ge",
    "wof:name":"Bp",
    "wof:placetype":"venue"
},
  "geometry": {"coordinates":[5.4998202324,50.595741272],"type":"Point"}
}