{
  "type": "Feature",
  "properties": {
    "iso:country":"BE",
    "sg:address":"Tulpenlaan 119",
    "sg:city":"Deerlijk",
    "sg:orig_category":"S\u00e9curit\u00e9 sociale",
    "sg:phone":"+32 56 71 57 85",
    "sg:postcode":"8540",
    "sg:province":"West-Vlaanderen",
    "wof:name":"Volksbelangen",
    "wof:placetype":"venue"
},
  "geometry": {"coordinates":[3.3529551029,50.8555183411],"type":"Point"}
}