{
  "type": "Feature",
  "properties": {
    "addr:full":"Oelegemsteenweg 25 Schilde Antwerpen 2970",
    "addr:housenumber":"25",
    "addr:postcode":"2970",
    "addr:street":"Oelegemsteenweg",
    "iso:country":"BE",
    "sg:address":"Oelegemsteenweg 25",
    "sg:city":"Schilde",
    "sg:classifiers":[
        {
            "category":"Real Estate",
            "subcategory":"Architect",
            "type":"Services"
        }
    ],
    "sg:phone":"+32 3 383 05 10",
    "sg:postcode":"2970",
    "sg:province":"Antwerpen",
    "wof:name":"Baeten J",
    "wof:placetype":"venue"
},
  "geometry": {"coordinates":[4.5921587944,51.2300643921],"type":"Point"}
}