{
  "type": "Feature",
  "properties": {
    "iso:country":"BE",
    "sg:address":"Kruisstraat 303",
    "sg:city":"Ronse/renaix",
    "sg:orig_category":"Sportclubs",
    "sg:phone":"+32 55 21 44 08",
    "sg:postcode":"9600",
    "sg:province":"Oost-Vlaanderen",
    "wof:name":"Vl. Ardennen Marcheerders",
    "wof:placetype":"venue"
},
  "geometry": {"coordinates":[3.5890140533,50.7568588257],"type":"Point"}
}