{
  "type": "Feature",
  "properties": {
    "addr:full":"Avenue Jules C\u00e9sar 11 Bruxelles (woluwe-saint-pierre) Bruxelles-Capitale 1150",
    "addr:housenumber":"11",
    "addr:postcode":"1150",
    "addr:street":"Avenue Jules Ce\u0301Sar",
    "iso:country":"BE",
    "sg:address":"Avenue Jules C\u00e9sar 11",
    "sg:city":"Bruxelles (woluwe-saint-pierre)",
    "sg:classifiers":[
        {
            "category":"Health Services",
            "subcategory":"Nursing And Care Facility",
            "type":"Services"
        }
    ],
    "sg:phone":"+32 2 770 34 20",
    "sg:postcode":"1150",
    "sg:province":"Bruxelles-Capitale",
    "sg:tags":[
        "home",
        "rest"
    ],
    "wof:name":"Val Duchesse (le)",
    "wof:placetype":"venue"
},
  "geometry": {"coordinates":[4.4203228951,50.8337860107],"type":"Point"}
}