{
  "type": "Feature",
  "properties": {
    "addr:full":"Leuvensesteenweg 72-4 Diest Vlaams-Brabant 3290",
    "addr:housenumber":"72-4",
    "addr:postcode":"3290",
    "addr:street":"Leuvensesteenweg",
    "iso:country":"BE",
    "sg:address":"Leuvensesteenweg 72-4",
    "sg:city":"Diest",
    "sg:classifiers":[
        {
            "category":"Real Estate",
            "subcategory":"Real Estate Services",
            "type":"Services"
        }
    ],
    "sg:phone":"+32 11 28 57 10",
    "sg:postcode":"3290",
    "sg:province":"Vlaams-Brabant",
    "wof:name":"Laeren Nv",
    "wof:placetype":"venue"
},
  "geometry": {"coordinates":[5.0495457649,50.9816017151],"type":"Point"}
}