{
  "type": "Feature",
  "properties": {
    "addr:full":"Koningsstraat 168 Brussel/bruxelles Bruxelles-Capitale 1000",
    "addr:housenumber":"168",
    "addr:postcode":"1000",
    "addr:street":"Koningsstraat;/",
    "iso:country":"BE",
    "sg:address":"Koningsstraat 168",
    "sg:city":"Brussel/bruxelles",
    "sg:orig_category":"Verbruikerskredietinstellingen",
    "sg:phone":"+32 2 221 04 60",
    "sg:postcode":"1000",
    "sg:province":"Bruxelles-Capitale",
    "wof:name":"Zetel Dhb Bank",
    "wof:placetype":"venue"
},
  "geometry": {"coordinates":[4.3645191193,50.8512954712],"type":"Point"}
}