{
  "type": "Feature",
  "properties": {
    "addr:full":"Fletersdel 2a Genk Limburg 3600",
    "addr:housenumber":"2a",
    "addr:postcode":"3600",
    "addr:street":"Fletersdel",
    "iso:country":"BE",
    "sg:address":"Fletersdel 2a",
    "sg:city":"Genk",
    "sg:classifiers":[
        {
            "category":"Health Services",
            "subcategory":"Health Practitioner",
            "type":"Services"
        }
    ],
    "sg:phone":"+32 89 36 16 45",
    "sg:postcode":"3600",
    "sg:province":"Limburg",
    "sg:tags":[
        "physiotherapist"
    ],
    "wof:name":"Verbruggen Cath\u00e9rine",
    "wof:placetype":"venue"
},
  "geometry": {"coordinates":[5.5164871216,50.9447555542],"type":"Point"}
}