{
  "type": "Feature",
  "properties": {
    "addr:full":"Boulevard Lambermont 169 Bruxelles (schaerbeek) Bruxelles-Capitale 1030",
    "addr:housenumber":"169",
    "addr:postcode":"1030",
    "addr:street":"Boulevard Lambermont",
    "iso:country":"BE",
    "sg:address":"Boulevard Lambermont 169",
    "sg:city":"Bruxelles (schaerbeek)",
    "sg:classifiers":[
        {
            "category":"Home & Garden",
            "subcategory":"Furniture",
            "type":"Retail Goods"
        }
    ],
    "sg:phone":"+32 2 247 95 00",
    "sg:postcode":"1030",
    "sg:province":"Bruxelles-Capitale",
    "sg:tags":[
        "-"
    ],
    "wof:name":"C & M Sa",
    "wof:placetype":"venue"
},
  "geometry": {"coordinates":[4.3821578026,50.8705787659],"type":"Point"}
}