{
  "type": "Feature",
  "properties": {
    "addr:full":"Kerkstraat 282 Blankenberge West-Vlaanderen 8370",
    "addr:housenumber":"282",
    "addr:postcode":"8370",
    "addr:street":"Kerkstraat",
    "iso:country":"BE",
    "sg:address":"Kerkstraat 282",
    "sg:city":"Blankenberge",
    "sg:classifiers":[
        {
            "category":"Professional",
            "subcategory":"Computer Services",
            "type":"Services"
        }
    ],
    "sg:phone":"+32 50 41 65 19",
    "sg:postcode":"8370",
    "sg:province":"West-Vlaanderen",
    "sg:tags":[
        "-",
        "processing",
        "data"
    ],
    "wof:name":"Tevicom",
    "wof:placetype":"venue"
},
  "geometry": {"coordinates":[3.1390879154,51.3071517944],"type":"Point"}
}