{
  "type": "Feature",
  "properties": {
    "addr:full":"Chauss\u00e9e De Haecht 60 Bruxelles (saint-josse-ten-noode) Bruxelles-Capitale 1210",
    "addr:housenumber":"60",
    "addr:postcode":"1210",
    "addr:street":"Chausse\u0301E De Haecht",
    "iso:country":"BE",
    "sg:address":"Chauss\u00e9e De Haecht 60",
    "sg:city":"Bruxelles (saint-josse-ten-noode)",
    "sg:classifiers":[
        {
            "category":"Communications",
            "subcategory":"Film & Video Production",
            "type":"Services"
        }
    ],
    "sg:phone":"+32 2 217 94 41",
    "sg:postcode":"1210",
    "sg:province":"Bruxelles-Capitale",
    "sg:tags":[
        "hiring",
        "distribution"
    ],
    "wof:name":"Coop\u00e9rative Nouveau Cin\u00e9ma",
    "wof:placetype":"venue"
},
  "geometry": {"coordinates":[4.3687582016,50.8559112549],"type":"Point"}
}