{
  "type": "Feature",
  "properties": {
    "addr:full":"Chauss\u00c9e De Mons 45 Brugelette Hainaut 7940",
    "addr:housenumber":"45",
    "addr:postcode":"7940",
    "addr:street":"Chausse\u0301E De Mons;Hainaut",
    "iso:country":"BE",
    "sg:address":"Chauss\u00c9e De Mons 45",
    "sg:city":"Brugelette",
    "sg:classifiers":[
        {
            "category":"Autos & Motor Vehicles",
            "subcategory":"Fuel & Gas Station",
            "type":"Retail Goods"
        }
    ],
    "sg:phone":"+32 68 45 58 25",
    "sg:postcode":"7940",
    "sg:province":"Hainaut",
    "sg:tags":[
        "stations-service",
        "carburants"
    ],
    "wof:name":"Gaetan Cambie",
    "wof:placetype":"venue"
},
  "geometry": {"coordinates":[3.8439459801,50.5879554749],"type":"Point"}
}