{
  "type": "Feature",
  "properties": {
    "iso:country":"BE",
    "sg:address":"Elsense Steenweg 133",
    "sg:city":"Elsene/ixelles",
    "sg:orig_category":"Elektriciteitsproductie and -distributie Overheidsdiensten",
    "sg:phone":"+32 2 549 41 11",
    "sg:postcode":"1050",
    "sg:province":"Bruxelles-Capitale",
    "wof:name":"Interelec",
    "wof:placetype":"venue"
},
  "geometry": {"coordinates":[4.365114212,50.8340873718],"type":"Point"}
}