{
  "type": "Feature",
  "properties": {
    "iso:country":"BE",
    "sg:address":"Rue De Thier 9",
    "sg:city":"Houffalize",
    "sg:orig_category":"Vakantiehuizen",
    "sg:phone":"+32 50 62 44 21",
    "sg:postcode":"6660",
    "sg:province":"Luxembourg",
    "wof:name":"Gyd\u00c9 Marc",
    "wof:placetype":"venue"
},
  "geometry": {"coordinates":[5.6747918129,50.163318634],"type":"Point"}
}