{
  "type": "Feature",
  "properties": {
    "iso:country":"BE",
    "sg:address":"Gammel 90",
    "sg:city":"Rijkevorsel",
    "sg:orig_category":"Producteurs de fruits. Eleveurs de volaille. Producteurs de l\u00e9gumes",
    "sg:phone":"+32 3 314 38 51",
    "sg:postcode":"2310",
    "sg:province":"Antwerpen",
    "wof:name":"Lodewijk Leemans",
    "wof:placetype":"venue"
},
  "geometry": {"coordinates":[4.7567191124,51.3778953552],"type":"Point"}
}