{
  "type": "Feature",
  "properties": {
    "iso:country":"BE",
    "sg:address":"Verhenis 10",
    "sg:city":"Tongeren",
    "sg:orig_category":"M\u00e9decins and sp\u00e9cialistes",
    "sg:phone":"+32 12 39 53 20",
    "sg:postcode":"3700",
    "sg:province":"Limburg",
    "wof:name":"Miriam Henskens",
    "wof:placetype":"venue"
},
  "geometry": {"coordinates":[5.4714608192,50.8053703308],"type":"Point"}
}