{
  "type": "Feature",
  "properties": {
    "addr:full":"Arme Klarenstraat 75 Roeselare West-Vlaanderen 8800",
    "addr:housenumber":"75",
    "addr:postcode":"8800",
    "addr:street":"Arme Klarenstraat",
    "iso:country":"BE",
    "sg:address":"Arme Klarenstraat 75",
    "sg:city":"Roeselare",
    "sg:orig_category":"Openbare bibliotheken and archieven",
    "sg:phone":"+32 51 20 96 42",
    "sg:postcode":"8800",
    "sg:province":"West-Vlaanderen",
    "wof:name":"Openbare Bibliotheek",
    "wof:placetype":"venue"
},
  "geometry": {"coordinates":[3.1191420555,50.9434509277],"type":"Point"}
}