{
  "type": "Feature",
  "properties": {
    "addr:full":"Salvatorstraat 14 Zandhoven Antwerpen 2242",
    "addr:housenumber":"14",
    "addr:postcode":"2242",
    "addr:street":"Salvatorstraat",
    "iso:country":"BE",
    "sg:address":"Salvatorstraat 14",
    "sg:city":"Zandhoven",
    "sg:orig_category":"Dakwerken",
    "sg:phone":"+32 3 464 20 41",
    "sg:postcode":"2242",
    "sg:province":"Antwerpen",
    "wof:name":"A.p.m.",
    "wof:placetype":"venue"
},
  "geometry": {"coordinates":[4.6928639412,51.2167739868],"type":"Point"}
}