{
  "type": "Feature",
  "properties": {
    "iso:country":"BE",
    "sg:address":"Toekomstlaan 5",
    "sg:city":"Neerpelt",
    "sg:orig_category":"Salles de spectacles",
    "sg:phone":"+32 11 64 30 49",
    "sg:postcode":"3910",
    "sg:province":"Limburg",
    "wof:name":"Provincie Limburg Dienst Cultuur",
    "wof:placetype":"venue"
},
  "geometry": {"coordinates":[5.4243040085,51.2308769226],"type":"Point"}
}