{
  "type": "Feature",
  "properties": {
    "addr:full":"Egide Van Ophemstraat 172 Ukkel/uccle Bruxelles-Capitale 1180",
    "addr:housenumber":"172",
    "addr:postcode":"1180",
    "addr:street":"Egide Van Ophemstraat;/",
    "iso:country":"BE",
    "sg:address":"Egide Van Ophemstraat 172",
    "sg:city":"Ukkel/uccle",
    "sg:orig_category":"Apotheken",
    "sg:phone":"+32 2 376 57 36",
    "sg:postcode":"1180",
    "sg:province":"Bruxelles-Capitale",
    "wof:name":"Jean-marc Lebout",
    "wof:placetype":"venue"
},
  "geometry": {"coordinates":[4.3249650002,50.7949485779],"type":"Point"}
}