{
  "type": "Feature",
  "properties": {
    "iso:country":"BE",
    "sg:address":"Bogaardenstraat 29",
    "sg:city":"Leuven",
    "sg:classifiers":[
        {
            "category":"Restaurant",
            "type":"Food & Drink"
        }
    ],
    "sg:phone":"+32 16 29 42 25",
    "sg:postcode":"3000",
    "sg:province":"Vlaams-Brabant",
    "wof:name":"Lido Snack",
    "wof:placetype":"venue"
},
  "geometry": {"coordinates":[4.7092719078,50.8783531189],"type":"Point"}
}