{
  "type": "Feature",
  "properties": {
    "addr:full":"Av. Du Prince D'orange 186 Ukkel/uccle Bruxelles-Capitale 1180",
    "addr:housenumber":"186",
    "addr:postcode":"1180",
    "addr:street":"Av. Du Prince D'Orange;/",
    "iso:country":"BE",
    "sg:address":"Av. Du Prince D'orange 186",
    "sg:city":"Ukkel/uccle",
    "sg:orig_category":"Experts-comptables",
    "sg:phone":"+32 2 374 02 44",
    "sg:postcode":"1180",
    "sg:province":"Bruxelles-Capitale",
    "wof:name":"Eric De Meester",
    "wof:placetype":"venue"
},
  "geometry": {"coordinates":[4.3607649803,50.7821922302],"type":"Point"}
}