{
  "type": "Feature",
  "properties": {
    "addr:full":"Bordeauxstraat 14 Antwerpen Antwerpen 2000",
    "addr:housenumber":"14",
    "addr:postcode":"2000",
    "addr:street":"Bordeauxstraat",
    "iso:country":"BE",
    "sg:address":"Bordeauxstraat 14",
    "sg:city":"Antwerpen",
    "sg:orig_category":"Assistances juridiques. Conseillers fiscaux",
    "sg:phone":"+32 3 231 81 71",
    "sg:postcode":"2000",
    "sg:province":"Antwerpen",
    "wof:name":"Van Deynze",
    "wof:placetype":"venue"
},
  "geometry": {"coordinates":[4.4090747833,51.2301864624],"type":"Point"}
}