{
  "type": "Feature",
  "properties": {
    "iso:country":"BE",
    "sg:address":"Chauss\u00e9e De Marche 585",
    "sg:city":"Namur (erpent)",
    "sg:classifiers":[
        {
            "category":"Professional",
            "subcategory":"Management & Consulting",
            "type":"Services"
        }
    ],
    "sg:phone":"+32 81 33 04 04",
    "sg:postcode":"5101",
    "sg:province":"Namur",
    "sg:tags":[
        "tax-consultants"
    ],
    "wof:name":"Lemercinier G",
    "wof:placetype":"venue"
},
  "geometry": {"coordinates":[4.9065589905,50.4410247803],"type":"Point"}
}