{
  "type": "Feature",
  "properties": {
    "iso:country":"BE",
    "sg:address":"Karel Van Lotaringenstr 4",
    "sg:city":"Leuven",
    "sg:orig_category":"Business advice and other services Communication, advertising and the media Construction and Public ",
    "sg:phone":"+32 16 20 41 98",
    "sg:postcode":"3000",
    "sg:province":"Vlaams-Brabant",
    "wof:name":"Studiebureau Casier Patrick Bvba",
    "wof:placetype":"venue"
},
  "geometry": {"coordinates":[4.6999897957,50.8822975159],"type":"Point"}
}