{
  "type": "Feature",
  "properties": {
    "addr:full":"Dr\u00c8ve Des Renards 6b1 Ukkel/uccle Bruxelles-Capitale 1180",
    "addr:housenumber":"6b1",
    "addr:postcode":"1180",
    "addr:street":"Dre\u0300Ve Des Renards;/",
    "iso:country":"BE",
    "sg:address":"Dr\u00c8ve Des Renards 6b1",
    "sg:city":"Ukkel/uccle",
    "sg:orig_category":"Avocats and conseillers juridiques",
    "sg:phone":"+32 2 374 92 00",
    "sg:postcode":"1180",
    "sg:province":"Bruxelles-Capitale",
    "wof:name":"Maria-garcia Maxia",
    "wof:placetype":"venue"
},
  "geometry": {"coordinates":[4.3748102188,50.7899894714],"type":"Point"}
}