{
  "type": "Feature",
  "properties": {
    "iso:country":"BE",
    "sg:address":"Kreek 54",
    "sg:city":"Beveren",
    "sg:orig_category":"Organisations and associations. Services pour animaux domestiques",
    "sg:phone":"+32 3 773 40 89",
    "sg:postcode":"9130",
    "sg:province":"Oost-Vlaanderen",
    "wof:name":"De Grote Geule",
    "wof:placetype":"venue"
},
  "geometry": {"coordinates":[4.1813378334,51.284324646],"type":"Point"}
}