{
  "type": "Feature",
  "properties": {
    "addr:full":"Ter Kamerenstraat 260 Sint-lambrechts-woluwe/woluwe-saint-lambert Bruxelles-Capitale 1200",
    "addr:housenumber":"260",
    "addr:postcode":"1200",
    "addr:street":"Ter Kamerenstraat",
    "iso:country":"BE",
    "sg:address":"Ter Kamerenstraat 260",
    "sg:city":"Sint-lambrechts-woluwe/woluwe-saint-lambert",
    "sg:orig_category":"Paramedische behandelingen",
    "sg:phone":"+32 2 770 13 76",
    "sg:postcode":"1200",
    "sg:province":"Bruxelles-Capitale",
    "wof:name":"C. Guillain",
    "wof:placetype":"venue"
},
  "geometry": {"coordinates":[4.4151649475,50.8385467529],"type":"Point"}
}