{
  "type": "Feature",
  "properties": {
    "addr:full":"Rue Jean Grosset 31 Walcourt Namur 5650",
    "addr:housenumber":"31",
    "addr:postcode":"5650",
    "addr:street":"Rue Jean Grosset",
    "iso:country":"BE",
    "sg:address":"Rue Jean Grosset 31",
    "sg:city":"Walcourt",
    "sg:orig_category":"HUISBRANDOLIE Houtbewerking and -behandeling Tuinen",
    "sg:phone":"+32 71 65 50 52",
    "sg:postcode":"5650",
    "sg:province":"Namur",
    "wof:name":"C.m. Bois",
    "wof:placetype":"venue"
},
  "geometry": {"coordinates":[4.4893321991,50.2412605286],"type":"Point"}
}