{
  "type": "Feature",
  "properties": {
    "iso:country":"BE",
    "sg:address":"Rue O. Pierard 149",
    "sg:city":"Gembloux",
    "sg:orig_category":"Tuinen",
    "sg:phone":"+32 81 61 06 12",
    "sg:postcode":"5030",
    "sg:province":"Namur",
    "wof:name":"Dufrasne M.",
    "wof:placetype":"venue"
},
  "geometry": {"coordinates":[4.6614761353,50.5917434692],"type":"Point"}
}