{
  "type": "Feature",
  "properties": {
    "iso:country":"BE",
    "sg:address":"Avenue Jean Dubrucq 54",
    "sg:city":"Bruxelles (molenbeek-saint-jean)",
    "sg:classifiers":[
        {
            "category":"Communications",
            "subcategory":"Film & Video Production",
            "type":"Services"
        }
    ],
    "sg:phone":"+32 2 428 40 19",
    "sg:postcode":"1080",
    "sg:province":"Bruxelles-Capitale",
    "sg:tags":[
        "hiring",
        "-"
    ],
    "wof:name":"Cinq-cinq",
    "wof:placetype":"venue"
},
  "geometry": {"coordinates":[4.3342652321,50.8651046753],"type":"Point"}
}