{
  "type": "Feature",
  "properties": {
    "iso:country":"BE",
    "sg:address":"Willekensmolenstraat 34",
    "sg:city":"Hasselt",
    "sg:orig_category":"Epiceries",
    "sg:phone":"+32 11 22 40 08",
    "sg:postcode":"3500",
    "sg:province":"Limburg",
    "wof:name":"'t Winkeltje",
    "wof:placetype":"venue"
},
  "geometry": {"coordinates":[5.3464717865,50.9315032959],"type":"Point"}
}