{
  "type": "Feature",
  "properties": {
    "addr:full":"Ruiterslaan 26 Wijnegem Antwerpen 2110",
    "addr:housenumber":"26",
    "addr:postcode":"2110",
    "addr:street":"Ruiterslaan",
    "iso:country":"BE",
    "sg:address":"Ruiterslaan 26",
    "sg:city":"Wijnegem",
    "sg:classifiers":[
        {
            "category":"Home & Garden",
            "subcategory":"Furniture",
            "type":"Retail Goods"
        }
    ],
    "sg:phone":"+32 3 354 26 51",
    "sg:postcode":"2110",
    "sg:province":"Antwerpen",
    "sg:tags":[
        "fab",
        "meubelen",
        "diverse"
    ],
    "wof:name":"V.a.c.",
    "wof:placetype":"venue"
},
  "geometry": {"coordinates":[4.5494689941,51.2266616821],"type":"Point"}
}