{
  "type": "Feature",
  "properties": {
    "iso:country":"BE",
    "sg:address":"Alice Nahonlei 10",
    "sg:city":"Schoten",
    "sg:orig_category":"Peinture. Rev\u00eatements pour sols and murs",
    "sg:phone":"+32 3 658 98 95",
    "sg:postcode":"2900",
    "sg:province":"Antwerpen",
    "wof:name":"Emmanuel Lombart",
    "wof:placetype":"venue"
},
  "geometry": {"coordinates":[4.5363378525,51.2560081482],"type":"Point"}
}