{
  "type": "Feature",
  "properties": {
    "iso:country":"BE",
    "sg:address":"Sanatoriumstraat 243",
    "sg:city":"Beersel (alsemberg)",
    "sg:classifiers":[
        {
            "category":"Health Services",
            "subcategory":"Doctor",
            "type":"Services"
        }
    ],
    "sg:phone":"+32 2 380 33 74",
    "sg:postcode":"1652",
    "sg:province":"Vlaams-Brabant",
    "sg:tags":[
        "medicinephysicians",
        "surgeon"
    ],
    "wof:name":"Lemmens F",
    "wof:placetype":"venue"
},
  "geometry": {"coordinates":[4.3084759712,50.7566452026],"type":"Point"}
}