{
  "type": "Feature",
  "properties": {
    "addr:full":"Kragendijk 38 Knokke-heist West-Vlaanderen 8300",
    "addr:housenumber":"38",
    "addr:postcode":"8300",
    "addr:street":"Kragendijk",
    "iso:country":"BE",
    "sg:address":"Kragendijk 38",
    "sg:city":"Knokke-heist",
    "sg:orig_category":"Loodgieterij, verwarming and sanitaire installaties Woningbouw",
    "sg:phone":"+32 50 60 93 72",
    "sg:postcode":"8300",
    "sg:province":"West-Vlaanderen",
    "wof:name":"Casteleyn Patrick",
    "wof:placetype":"venue"
},
  "geometry": {"coordinates":[3.287694931,51.3467254639],"type":"Point"}
}