{
  "type": "Feature",
  "properties": {
    "addr:full":"Rue Saint-remy 3bbis Li\u00c8ge Li\u00e8ge 4000",
    "addr:postcode":"3bbis;4000",
    "addr:street":"Rue Saint-Remy",
    "iso:country":"BE",
    "sg:address":"Rue Saint-remy 3bbis",
    "sg:city":"Li\u00c8ge",
    "sg:orig_category":"Salles de spectacles",
    "sg:phone":"+32 4 221 35 25",
    "sg:postcode":"4000",
    "sg:province":"Li\u00e8ge",
    "wof:name":"La Galerie",
    "wof:placetype":"venue"
},
  "geometry": {"coordinates":[5.570456028,50.6390991211],"type":"Point"}
}