{
  "type": "Feature",
  "properties": {
    "addr:full":"Rue Durlet 28 Courcelles Hainaut 6180",
    "addr:housenumber":"28",
    "addr:postcode":"6180",
    "addr:street":"Rue Durlet",
    "iso:country":"BE",
    "sg:address":"Rue Durlet 28",
    "sg:city":"Courcelles",
    "sg:classifiers":[
        {
            "category":"Parking",
            "subcategory":"Bicycle",
            "type":"Transportation"
        }
    ],
    "sg:phone":"+32 71 45 82 90",
    "sg:postcode":"6180",
    "sg:province":"Hainaut",
    "sg:tags":[
        "chiropodist"
    ],
    "wof:name":"Delan V",
    "wof:placetype":"venue"
},
  "geometry": {"coordinates":[4.3947911263,50.4665374756],"type":"Point"}
}