{
  "type": "Feature",
  "properties": {
    "iso:country":"BE",
    "sg:address":"Stationsstraat 118",
    "sg:city":"Sint-genesius-rode/rhode-saint-genese",
    "sg:orig_category":"Drukkerijen and copyshops",
    "sg:phone":"+32 2 380 84 99",
    "sg:postcode":"1640",
    "sg:province":"Vlaams-Brabant",
    "wof:name":"Depessemier Printing",
    "wof:placetype":"venue"
},
  "geometry": {"coordinates":[4.357583046,50.7495613098],"type":"Point"}
}