{
  "type": "Feature",
  "properties": {
    "iso:country":"BE",
    "sg:address":"Smisseweg 9",
    "sg:city":"Ruiselede",
    "sg:classifiers":[
        {
            "category":"Farming",
            "subcategory":"Crops",
            "type":"Manufacturing & Wholesale Goods"
        }
    ],
    "sg:phone":"+32 51 68 96 36",
    "sg:postcode":"8755",
    "sg:province":"West-Vlaanderen",
    "sg:tags":[
        "vegetable",
        "fruit",
        "-",
        "grower"
    ],
    "wof:name":"Goossens R",
    "wof:placetype":"venue"
},
  "geometry": {"coordinates":[3.3604280949,51.0501441956],"type":"Point"}
}