{
  "type": "Feature",
  "properties": {
    "addr:full":"Rue Du Framboisier 14 Bruxelles (uccle) Bruxelles-Capitale 1180",
    "addr:housenumber":"14",
    "addr:postcode":"1180",
    "addr:street":"Rue Du Framboisier",
    "iso:country":"BE",
    "sg:address":"Rue Du Framboisier 14",
    "sg:city":"Bruxelles (uccle)",
    "sg:classifiers":[
        {
            "category":"Manufacturing",
            "subcategory":"Chemicals & Compounds",
            "type":"Manufacturing & Wholesale Goods"
        }
    ],
    "sg:phone":"+32 2 374 90 64",
    "sg:postcode":"1180",
    "sg:province":"Bruxelles-Capitale",
    "sg:tags":[
        "pharmaceutical",
        "product"
    ],
    "wof:name":"Arvet Sa",
    "wof:placetype":"venue"
},
  "geometry": {"coordinates":[4.3692569733,50.8086204529],"type":"Point"}
}