{
  "type": "Feature",
  "properties": {
    "addr:full":"Neutralstrasse 136 Lontzen/lontzen Li\u00e8ge 4710",
    "addr:housenumber":"136",
    "addr:postcode":"4710",
    "addr:street":"Neutralstrasse",
    "iso:country":"BE",
    "sg:address":"Neutralstrasse 136",
    "sg:city":"Lontzen/lontzen",
    "sg:orig_category":"Drogisterijen",
    "sg:phone":"+32 87 89 01 30",
    "sg:postcode":"4710",
    "sg:province":"Li\u00e8ge",
    "wof:name":"Norbert Lejeune",
    "wof:placetype":"venue"
},
  "geometry": {"coordinates":[5.99229002,50.6763191223],"type":"Point"}
}