{
  "type": "Feature",
  "properties": {
    "addr:full":"Avenue Du Gros Ch\u00eane 15 Fl\u00e9malle (ivoz-ramet) Li\u00e8ge 4400",
    "addr:housenumber":"15",
    "addr:postcode":"4400",
    "addr:street":"Avenue Du Gros Che\u0302Ne;Ivoz-Ramet",
    "iso:country":"BE",
    "sg:address":"Avenue Du Gros Ch\u00eane 15",
    "sg:city":"Fl\u00e9malle (ivoz-ramet)",
    "sg:classifiers":[
        {
            "category":"Building & Trades",
            "subcategory":"Landscaping Services",
            "type":"Services"
        }
    ],
    "sg:phone":"+32 4 275 53 06",
    "sg:postcode":"4400",
    "sg:province":"Li\u00e8ge",
    "sg:tags":[
        "gardening",
        "garden",
        "maintenance"
    ],
    "wof:name":"Jardiparc Sprl",
    "wof:placetype":"venue"
},
  "geometry": {"coordinates":[5.4510397911,50.5699539185],"type":"Point"}
}