{
  "type": "Feature",
  "properties": {
    "addr:full":"Avenue Du Bleuet 48 Bruxelles (woluwe-saint-lambert) Bruxelles-Capitale 1200",
    "addr:housenumber":"48",
    "addr:postcode":"1200",
    "addr:street":"Avenue Du Bleuet",
    "iso:country":"BE",
    "sg:address":"Avenue Du Bleuet 48",
    "sg:city":"Bruxelles (woluwe-saint-lambert)",
    "sg:classifiers":[
        {
            "category":"Building & Trades",
            "subcategory":"Construction",
            "type":"Services"
        }
    ],
    "sg:phone":"+32 477 40 59 80",
    "sg:postcode":"1200",
    "sg:province":"Bruxelles-Capitale",
    "sg:tags":[
        "installation",
        "-",
        "central",
        "heating"
    ],
    "wof:name":"Schroeder F",
    "wof:placetype":"venue"
},
  "geometry": {"coordinates":[4.4443712234,50.8398208618],"type":"Point"}
}