{
  "type": "Feature",
  "properties": {
    "iso:country":"BE",
    "sg:address":"Rue De La Vierge Noire 15",
    "sg:city":"Brussel/bruxelles",
    "sg:orig_category":"Antiquit\u00e9s. Biens d'occasion",
    "sg:phone":"+32 2 511 70 64",
    "sg:postcode":"1000",
    "sg:province":"Bruxelles-Capitale",
    "wof:name":"Bouqueinerie Le Meridien",
    "wof:placetype":"venue"
},
  "geometry": {"coordinates":[4.3497657776,50.8500556946],"type":"Point"}
}