{
  "type": "Feature",
  "properties": {
    "addr:full":"Roiseleux 34 Thimister-clermont Li\u00e8ge 4890",
    "addr:housenumber":"34",
    "addr:postcode":"4890",
    "addr:street":"Roiseleux",
    "iso:country":"BE",
    "sg:address":"Roiseleux 34",
    "sg:city":"Thimister-clermont",
    "sg:orig_category":"Entretien and r\u00e9parations de voitures",
    "sg:phone":"+32 87 44 64 65",
    "sg:postcode":"4890",
    "sg:province":"Li\u00e8ge",
    "wof:name":"Garage Derouaux",
    "wof:placetype":"venue"
},
  "geometry": {"coordinates":[5.8446512222,50.6673049927],"type":"Point"}
}