{
  "type": "Feature",
  "properties": {
    "addr:full":"Zandstraat 5 Balen Antwerpen 2490",
    "addr:housenumber":"5",
    "addr:postcode":"2490",
    "addr:street":"Zandstraat",
    "iso:country":"BE",
    "sg:address":"Zandstraat 5",
    "sg:city":"Balen",
    "sg:orig_category":"Kapsalons",
    "sg:phone":"+32 14 81 27 52",
    "sg:postcode":"2490",
    "sg:province":"Antwerpen",
    "wof:name":"Gilberte Vos",
    "wof:placetype":"venue"
},
  "geometry": {"coordinates":[5.1660938263,51.1722679138],"type":"Point"}
}