{
  "type": "Feature",
  "properties": {
    "iso:country":"BE",
    "sg:address":"Vollezelestraat 46",
    "sg:city":"Gooik (oetingen)",
    "sg:classifiers":[
        {
            "category":"Banks & Credit Unions",
            "subcategory":"Investment Brokerage",
            "type":"Services"
        }
    ],
    "sg:phone":"+32 54 56 89 10",
    "sg:postcode":"1755",
    "sg:province":"Vlaams-Brabant",
    "sg:tags":[
        "repair",
        "-",
        "installation",
        "sanitary",
        "article"
    ],
    "wof:name":"Sani-cv Gaillard",
    "wof:placetype":"venue"
},
  "geometry": {"coordinates":[4.0568571091,50.7718772888],"type":"Point"}
}