{
  "type": "Feature",
  "properties": {
    "addr:full":"Rue Du Canal De L'ourthe 8 Angleur Li\u00e8ge Li\u00e8ge 4031",
    "addr:housenumber":"8",
    "addr:postcode":"4031",
    "addr:street":"Rue Du Canal De L'Ourthe",
    "iso:country":"BE",
    "sg:address":"Rue Du Canal De L'ourthe 8 Angleur",
    "sg:city":"Li\u00e8ge",
    "sg:classifiers":[
        {
            "category":"Utilities",
            "type":"Services"
        }
    ],
    "sg:phone":"+32 4 367 84 11",
    "sg:postcode":"4031",
    "sg:province":"Li\u00e8ge",
    "sg:tags":[
        "raw",
        "energy",
        "material"
    ],
    "wof:name":"Compagnie Intercommunale Liegeoise Des Eaux Sc",
    "wof:placetype":"venue"
},
  "geometry": {"coordinates":[5.6025528908,50.6144142151],"type":"Point"}
}