{
  "type": "Feature",
  "properties": {
    "addr:full":"Steenweg 48 Asse Vlaams-Brabant 1730",
    "addr:housenumber":"48",
    "addr:postcode":"1730",
    "addr:street":"Steenweg",
    "iso:country":"BE",
    "sg:address":"Steenweg 48",
    "sg:city":"Asse",
    "sg:orig_category":"Slagers",
    "sg:phone":"+32 2 452 65 89",
    "sg:postcode":"1730",
    "sg:province":"Vlaams-Brabant",
    "wof:name":"Beenhouwerij Kurt",
    "wof:placetype":"venue"
},
  "geometry": {"coordinates":[4.1970391273,50.9117393494],"type":"Point"}
}