{
  "type": "Feature",
  "properties": {
    "iso:country":"BE",
    "sg:address":"Dorpstraat 13",
    "sg:city":"Merchtem (brussegem)",
    "sg:classifiers":[
        {
            "category":"Shopping",
            "subcategory":"Pets & Pet Supplies",
            "type":"Retail Goods"
        }
    ],
    "sg:phone":"+32 2 461 37 53",
    "sg:postcode":"1785",
    "sg:province":"Vlaams-Brabant",
    "sg:tags":[
        "shop",
        "-"
    ],
    "wof:name":"Poultry",
    "wof:placetype":"venue"
},
  "geometry": {"coordinates":[4.2317490578,50.9585723877],"type":"Point"}
}