{
  "type": "Feature",
  "properties": {
    "addr:full":"Hoge Mauw 3ba Arendonk Antwerpen 2370",
    "addr:housenumber":"3ba",
    "addr:postcode":"2370",
    "addr:street":"Hoge Mauw",
    "iso:country":"BE",
    "sg:address":"Hoge Mauw 3ba",
    "sg:city":"Arendonk",
    "sg:orig_category":"Installation de menuiserie en bois and plastique. Construction de maisons",
    "sg:phone":"+32 14 67 74 91",
    "sg:postcode":"2370",
    "sg:province":"Antwerpen",
    "wof:name":"Hooyberghs",
    "wof:placetype":"venue"
},
  "geometry": {"coordinates":[5.1123580933,51.3021621704],"type":"Point"}
}