{
  "type": "Feature",
  "properties": {
    "addr:full":"Genkersteenweg 132 Hasselt Limburg 3500",
    "addr:housenumber":"132",
    "addr:postcode":"3500",
    "addr:street":"Genkersteenweg",
    "iso:country":"BE",
    "sg:address":"Genkersteenweg 132",
    "sg:city":"Hasselt",
    "sg:orig_category":"Bois Gr. Fabrication and montage de mobilier. Quincailleries. D\u00e9corateurs d'int\u00e9rieur",
    "sg:phone":"+32 11 23 18 84",
    "sg:postcode":"3500",
    "sg:province":"Limburg",
    "wof:name":"Go-partners",
    "wof:placetype":"venue"
},
  "geometry": {"coordinates":[5.381734848,50.9450645447],"type":"Point"}
}