{
  "type": "Feature",
  "properties": {
    "addr:full":"Ambachtelaan 30 Leuven Vlaams-Brabant 3001",
    "addr:housenumber":"30",
    "addr:postcode":"3001",
    "addr:street":"Ambachtelaan",
    "iso:country":"BE",
    "sg:address":"Ambachtelaan 30",
    "sg:city":"Leuven",
    "sg:orig_category":"M\u00e9taux and minerais Traitement and rev\u00eatement des m\u00e9taux",
    "sg:phone":"+32 16 40 08 68",
    "sg:postcode":"3001",
    "sg:province":"Vlaams-Brabant",
    "wof:name":"Pirmatech",
    "wof:placetype":"venue"
},
  "geometry": {"coordinates":[4.7160158157,50.8489303589],"type":"Point"}
}