{
  "type": "Feature",
  "properties": {
    "iso:country":"BE",
    "sg:address":"Korte Meer 12",
    "sg:city":"Gent",
    "sg:classifiers":[
        {
            "category":"Education",
            "subcategory":"University",
            "type":"Public Place"
        }
    ],
    "sg:phone":"+32 9 330 40 81",
    "sg:postcode":"9000",
    "sg:province":"Oost-Vlaanderen",
    "sg:tags":[
        "higher"
    ],
    "wof:name":"Orpheus Instituut",
    "wof:placetype":"venue"
},
  "geometry": {"coordinates":[3.722700119,51.0518188477],"type":"Point"}
}