{
  "type": "Feature",
  "properties": {
    "addr:full":"Rodenbachlaan 48 Overpelt Limburg 3900",
    "addr:housenumber":"48",
    "addr:postcode":"3900",
    "addr:street":"Rodenbachlaan",
    "iso:country":"BE",
    "sg:address":"Rodenbachlaan 48",
    "sg:city":"Overpelt",
    "sg:classifiers":[
        {
            "category":"Bars & Pubs",
            "type":"Food & Drink"
        }
    ],
    "sg:phone":"+32 11 64 11 41",
    "sg:postcode":"3900",
    "sg:province":"Limburg",
    "wof:name":"Bij Den Haen",
    "wof:placetype":"venue"
},
  "geometry": {"coordinates":[5.4254198074,51.2112388611],"type":"Point"}
}