{
  "type": "Feature",
  "properties": {
    "addr:full":"Schuttersvest 47b601 Mechelen Antwerpen 2800",
    "addr:housenumber":"47b601",
    "addr:postcode":"2800",
    "addr:street":"Schuttersvest",
    "iso:country":"BE",
    "sg:address":"Schuttersvest 47b601",
    "sg:city":"Mechelen",
    "sg:classifiers":[
        {
            "category":"Sports & Exercise",
            "subcategory":"Sports Center",
            "type":"Entertainment"
        }
    ],
    "sg:phone":"+32 15 43 10 58",
    "sg:postcode":"2800",
    "sg:province":"Antwerpen",
    "sg:tags":[
        "terrain",
        "hors",
        "de",
        "installation",
        "sportifs"
    ],
    "wof:name":"Krit.der Vlaamse Gewesten",
    "wof:placetype":"venue"
},
  "geometry": {"coordinates":[4.4801101685,51.0209083557],"type":"Point"}
}