{
  "type": "Feature",
  "properties": {
    "addr:full":"Dorpsplein 4 Melle Oost-Vlaanderen 9090",
    "addr:housenumber":"4",
    "addr:postcode":"9090",
    "addr:street":"Dorpsplein",
    "iso:country":"BE",
    "sg:address":"Dorpsplein 4",
    "sg:city":"Melle",
    "sg:classifiers":[
        {
            "category":"Cafe",
            "type":"Food & Drink"
        }
    ],
    "sg:phone":"+32 9 252 20 35",
    "sg:postcode":"9090",
    "sg:province":"Oost-Vlaanderen",
    "sg:tags":[
        "caf\u00e9s"
    ],
    "wof:name":"Ronny De Vreese",
    "wof:placetype":"venue"
},
  "geometry": {"coordinates":[3.8021099567,51.0040168762],"type":"Point"}
}