{
  "type": "Feature",
  "properties": {
    "addr:full":"Victoriestraat 10 Turnhout Antwerpen 2300",
    "addr:housenumber":"10",
    "addr:postcode":"2300",
    "addr:street":"Victoriestraat",
    "iso:country":"BE",
    "sg:address":"Victoriestraat 10",
    "sg:city":"Turnhout",
    "sg:orig_category":"Antiquit\u00e9s",
    "sg:phone":"+32 14 41 28 66",
    "sg:postcode":"2300",
    "sg:province":"Antwerpen",
    "wof:name":"Antiek Chris",
    "wof:placetype":"venue"
},
  "geometry": {"coordinates":[4.9430279732,51.3212242126],"type":"Point"}
}