{
  "type": "Feature",
  "properties": {
    "addr:full":"Rue Joseph Dupont 8 Bruxelles Bruxelles-Capitale 1000",
    "addr:housenumber":"8",
    "addr:postcode":"1000",
    "addr:street":"Rue Joseph Dupont",
    "iso:country":"BE",
    "sg:address":"Rue Joseph Dupont 8",
    "sg:city":"Bruxelles",
    "sg:classifiers":[
        {
            "category":"Shopping",
            "subcategory":"Antiques",
            "type":"Retail Goods"
        }
    ],
    "sg:phone":"+32 2 513 30 19",
    "sg:postcode":"1000",
    "sg:province":"Bruxelles-Capitale",
    "wof:name":"Ethnic Art",
    "wof:placetype":"venue"
},
  "geometry": {"coordinates":[4.3553318977,50.838508606],"type":"Point"}
}