{
  "type": "Feature",
  "properties": {
    "iso:country":"BE",
    "sg:address":"Avenue Gustave Latinis 11",
    "sg:city":"Bruxelles (schaerbeek)",
    "sg:classifiers":[
        {
            "category":"Real Estate",
            "subcategory":"Architect",
            "type":"Services"
        }
    ],
    "sg:phone":"+32 2 216 55 95",
    "sg:postcode":"1030",
    "sg:province":"Bruxelles-Capitale",
    "wof:name":"Architectenbureau Maenhout J",
    "wof:placetype":"venue"
},
  "geometry": {"coordinates":[4.3866977692,50.8672218323],"type":"Point"}
}