{
  "type": "Feature",
  "properties": {
    "addr:full":"Sint-jacobsmarkt 77 Antwerpen Antwerpen 2000",
    "addr:housenumber":"77",
    "addr:postcode":"2000",
    "addr:street":"Sint-Jacobsmarkt",
    "iso:country":"BE",
    "sg:address":"Sint-jacobsmarkt 77",
    "sg:city":"Antwerpen",
    "sg:classifiers":[
        {
            "category":"Professional",
            "subcategory":"Employment Agencies",
            "type":"Services"
        }
    ],
    "sg:phone":"+32 3 201 93 00",
    "sg:postcode":"2000",
    "sg:province":"Antwerpen",
    "sg:tags":[
        "temping",
        "-",
        "manual"
    ],
    "wof:name":"Plus Uitzendkrachten",
    "wof:placetype":"venue"
},
  "geometry": {"coordinates":[4.4146370888,51.2201042175],"type":"Point"}
}