{
  "type": "Feature",
  "properties": {
    "iso:country":"BE",
    "sg:address":"Rue De L'h\u00f4tel De Ville 30",
    "sg:city":"Spa",
    "sg:classifiers":[
        {
            "category":"Home & Garden",
            "subcategory":"Kitchen Supply",
            "type":"Retail Goods"
        }
    ],
    "sg:phone":"+32 87 77 03 33",
    "sg:postcode":"4900",
    "sg:province":"Li\u00e8ge",
    "sg:tags":[
        "installation"
    ],
    "wof:name":"Dropsy B",
    "wof:placetype":"venue"
},
  "geometry": {"coordinates":[5.8665862083,50.4929695129],"type":"Point"}
}