{
  "type": "Feature",
  "properties": {
    "addr:full":"11 Campinaweg 2960 Brecht 11",
    "addr:housenumber":"11;11",
    "addr:postcode":"2960",
    "addr:street":"Campinaweg",
    "iso:country":"BE",
    "sg:address":"11",
    "sg:city":"Campinaweg 2960 Brecht",
    "sg:classifiers":[
        {
            "category":"Professional",
            "type":"Services"
        }
    ],
    "sg:phone":"+32 3 272 55 68",
    "sg:postcode":"11",
    "sg:tags":[
        "transport",
        "road"
    ],
    "wof:name":"E.t. Trans",
    "wof:placetype":"venue"
},
  "geometry": {"coordinates":[4.5707149506,51.304599762],"type":"Point"}
}