{
  "type": "Feature",
  "properties": {
    "addr:full":"Kasteellaan 18 Malle Antwerpen 2390",
    "addr:housenumber":"18",
    "addr:postcode":"2390",
    "addr:street":"Kasteellaan",
    "iso:country":"BE",
    "sg:address":"Kasteellaan 18",
    "sg:city":"Malle",
    "sg:orig_category":"Enseignement maternel and primaire",
    "sg:phone":"+32 3 312 98 88",
    "sg:postcode":"2390",
    "sg:province":"Antwerpen",
    "wof:name":"Vrije Basisschool",
    "wof:placetype":"venue"
},
  "geometry": {"coordinates":[4.6939549446,51.2967758179],"type":"Point"}
}