{
  "type": "Feature",
  "properties": {
    "addr:full":"Avenue Eug\u00c8ne Plasky 54 Schaarbeek/schaerbeek Bruxelles-Capitale 1030",
    "addr:housenumber":"54",
    "addr:postcode":"1030",
    "addr:street":"Avenue Euge\u0300Ne Plasky",
    "iso:country":"BE",
    "sg:address":"Avenue Eug\u00c8ne Plasky 54",
    "sg:city":"Schaarbeek/schaerbeek",
    "sg:orig_category":"M\u00e9decins and sp\u00e9cialistes",
    "sg:phone":"+32 2 736 08 30",
    "sg:postcode":"1030",
    "sg:province":"Bruxelles-Capitale",
    "wof:name":"Werner Vanneste",
    "wof:placetype":"venue"
},
  "geometry": {"coordinates":[4.3954501152,50.8495330811],"type":"Point"}
}