{
  "type": "Feature",
  "properties": {
    "addr:full":"Wijngaardlaan 7b3 Wezembeek-oppem/wezembeek-oppem Vlaams-Brabant 1970",
    "addr:housenumber":"7b3",
    "addr:postcode":"1970",
    "addr:street":"Wijngaardlaan",
    "iso:country":"BE",
    "sg:address":"Wijngaardlaan 7b3",
    "sg:city":"Wezembeek-oppem/wezembeek-oppem",
    "sg:orig_category":"Sportclubs",
    "sg:phone":"+32 2 731 83 05",
    "sg:postcode":"1970",
    "sg:province":"Vlaams-Brabant",
    "wof:name":"B.b.c. Wezembeek-oppem",
    "wof:placetype":"venue"
},
  "geometry": {"coordinates":[4.4809398651,50.8454742432],"type":"Point"}
}