{
  "type": "Feature",
  "properties": {
    "addr:full":"Grouwesteenstraat 30 Sint-gillis-waas Oost-Vlaanderen 9170",
    "addr:housenumber":"30",
    "addr:postcode":"9170",
    "addr:street":"Grouwesteenstraat",
    "iso:country":"BE",
    "sg:address":"Grouwesteenstraat 30",
    "sg:city":"Sint-gillis-waas",
    "sg:orig_category":"Afbraak- and draineerwerken Rundveehouders Varkenskwekers",
    "sg:phone":"+32 3 777 71 60",
    "sg:postcode":"9170",
    "sg:province":"Oost-Vlaanderen",
    "wof:name":"Frans Wuytack",
    "wof:placetype":"venue"
},
  "geometry": {"coordinates":[4.0993270874,51.2007789612],"type":"Point"}
}