{
  "type": "Feature",
  "properties": {
    "iso:country":"BE",
    "sg:address":"Perstraat 6",
    "sg:city":"Beveren",
    "sg:orig_category":"Schoonheidssalons",
    "sg:phone":"+32 3 775 98 62",
    "sg:postcode":"9120",
    "sg:province":"Oost-Vlaanderen",
    "wof:name":"K. De Westlinck",
    "wof:placetype":"venue"
},
  "geometry": {"coordinates":[4.239358902,51.1804199219],"type":"Point"}
}