{
  "type": "Feature",
  "properties": {
    "addr:full":"Dr\u00c8ve Angevine 8 Genappe Brabant Wallon 1470",
    "addr:housenumber":"8",
    "addr:postcode":"1470",
    "addr:street":"Dre\u0300Ve Angevine;Wallon",
    "iso:country":"BE",
    "sg:address":"Dr\u00c8ve Angevine 8",
    "sg:city":"Genappe",
    "sg:orig_category":"Opsporingsdiensten and detectivebureaus",
    "sg:phone":"+32 10 61 61 83",
    "sg:postcode":"1470",
    "sg:province":"Brabant Wallon",
    "wof:name":"Roger Allaert",
    "wof:placetype":"venue"
},
  "geometry": {"coordinates":[4.5332689285,50.638633728],"type":"Point"}
}