{
  "type": "Feature",
  "properties": {
    "iso:country":"BE",
    "sg:address":"Akkerstraat 62",
    "sg:city":"Arendonk",
    "sg:orig_category":"Eleveurs de bovins",
    "sg:phone":"+32 14 67 85 93",
    "sg:postcode":"2370",
    "sg:province":"Antwerpen",
    "wof:name":"Luc Van Der Veken",
    "wof:placetype":"venue"
},
  "geometry": {"coordinates":[5.0725269318,51.31042099],"type":"Point"}
}