{
  "type": "Feature",
  "properties": {
    "addr:full":"Pastoor De Swaeflaan 49 Maldegem Oost-Vlaanderen 9990",
    "addr:housenumber":"49",
    "addr:postcode":"9990",
    "addr:street":"Pastoor De Swaeflaan",
    "iso:country":"BE",
    "sg:address":"Pastoor De Swaeflaan 49",
    "sg:city":"Maldegem",
    "sg:orig_category":"G\u00e9om\u00e8tres",
    "sg:phone":"+32 50 71 19 46",
    "sg:postcode":"9990",
    "sg:province":"Oost-Vlaanderen",
    "wof:name":"Robert De Clercq",
    "wof:placetype":"venue"
},
  "geometry": {"coordinates":[3.3837909698,51.207901001],"type":"Point"}
}