{
  "type": "Feature",
  "properties": {
    "iso:country":"BE",
    "sg:address":"Brabantdam 55",
    "sg:city":"Gent",
    "sg:classifiers":[
        {
            "category":"Coffee & Tea",
            "type":"Food & Drink"
        }
    ],
    "sg:phone":"+32 9 225 81 89",
    "sg:postcode":"9000",
    "sg:province":"Oost-Vlaanderen",
    "sg:tags":[
        "retail",
        "-"
    ],
    "wof:name":"Vandekerckhove's Koffiebrander",
    "wof:placetype":"venue"
},
  "geometry": {"coordinates":[3.7293601036,51.0503616333],"type":"Point"}
}