{
  "type": "Feature",
  "properties": {
    "addr:full":"Muilshoek 5 Sint-katelijne-waver Antwerpen 2860",
    "addr:housenumber":"5",
    "addr:postcode":"2860",
    "addr:street":"Muilshoek",
    "iso:country":"BE",
    "sg:address":"Muilshoek 5",
    "sg:city":"Sint-katelijne-waver",
    "sg:orig_category":"Boucheries",
    "sg:phone":"+32 15 31 68 86",
    "sg:postcode":"2860",
    "sg:province":"Antwerpen",
    "wof:name":"Katelijnse Vleesmarkt",
    "wof:placetype":"venue"
},
  "geometry": {"coordinates":[4.54170084,51.0756340027],"type":"Point"}
}