{
  "type": "Feature",
  "properties": {
    "iso:country":"BE",
    "sg:address":"Wegvoeringstraat 57",
    "sg:city":"Wetteren",
    "sg:orig_category":"Maisons de repos and r\u00e9sidences",
    "sg:phone":"+32 9 368 85 00",
    "sg:postcode":"9230",
    "sg:province":"Oost-Vlaanderen",
    "wof:name":"Rusthuis Scheldezicht",
    "wof:placetype":"venue"
},
  "geometry": {"coordinates":[3.8895509243,51.0081710815],"type":"Point"}
}