{
  "type": "Feature",
  "properties": {
    "addr:full":"Lucien Hendrickxlei 20 Borsbeek Antwerpen 2150",
    "addr:housenumber":"20",
    "addr:postcode":"2150",
    "addr:street":"Lucien Hendrickxlei",
    "iso:country":"BE",
    "sg:address":"Lucien Hendrickxlei 20",
    "sg:city":"Borsbeek",
    "sg:classifiers":[
        {
            "category":"Insurance",
            "subcategory":"Insurance Agent",
            "type":"Services"
        }
    ],
    "sg:phone":"+32 3 321 61 98",
    "sg:postcode":"2150",
    "sg:province":"Antwerpen",
    "sg:tags":[
        "verzekeringsmakelaars",
        "expert"
    ],
    "wof:name":"H. Van Rillaer",
    "wof:placetype":"venue"
},
  "geometry": {"coordinates":[4.4871230125,51.1916770935],"type":"Point"}
}