{
  "type": "Feature",
  "properties": {
    "iso:country":"BE",
    "sg:address":"Avenue Des Martyrs 216",
    "sg:city":"Fl\u00e9ron",
    "sg:classifiers":[
        {
            "category":"Recreation",
            "subcategory":"Dance Hall",
            "type":"Entertainment"
        }
    ],
    "sg:phone":"+32 4 358 38 20",
    "sg:postcode":"4620",
    "sg:province":"Li\u00e8ge",
    "sg:tags":[
        "discotheque"
    ],
    "wof:name":"The Groove",
    "wof:placetype":"venue"
},
  "geometry": {"coordinates":[5.6810669899,50.614490509],"type":"Point"}
}