{
  "type": "Feature",
  "properties": {
    "addr:full":"Oude Kuringerbaan 160 Hasselt Limburg 3500",
    "addr:housenumber":"160",
    "addr:postcode":"3500",
    "addr:street":"Oude Kuringerbaan",
    "iso:country":"BE",
    "sg:address":"Oude Kuringerbaan 160",
    "sg:city":"Hasselt",
    "sg:classifiers":[
        {
            "category":"Retail",
            "subcategory":"Car Wash",
            "type":"Services"
        }
    ],
    "sg:phone":"+32 11 25 43 79",
    "sg:postcode":"3500",
    "sg:province":"Limburg",
    "sg:tags":[
        "automobile",
        "washing",
        "-",
        "truck"
    ],
    "wof:name":"Hasselt Car-wash Bvba",
    "wof:placetype":"venue"
},
  "geometry": {"coordinates":[5.3209347725,50.9355278015],"type":"Point"}
}