{
  "type": "Feature",
  "properties": {
    "iso:country":"BE",
    "sg:address":"Hofstraat 70a",
    "sg:city":"Lede (wanzele)",
    "sg:classifiers":[
        {
            "category":"Manufacturing",
            "subcategory":"Metals",
            "type":"Manufacturing & Wholesale Goods"
        }
    ],
    "sg:phone":"+32 53 80 55 69",
    "sg:postcode":"9340",
    "sg:province":"Oost-Vlaanderen",
    "sg:tags":[
        "treatment",
        "surface"
    ],
    "wof:name":"Bagumel Services Bvba",
    "wof:placetype":"venue"
},
  "geometry": {"coordinates":[3.9538929462,50.9728469849],"type":"Point"}
}