{
  "type": "Feature",
  "properties": {
    "addr:full":"Broekstraat 67 Brussel/bruxelles Bruxelles-Capitale 1000",
    "addr:housenumber":"67",
    "addr:postcode":"1000",
    "addr:street":"Broekstraat;/",
    "iso:country":"BE",
    "sg:address":"Broekstraat 67",
    "sg:city":"Brussel/bruxelles",
    "sg:orig_category":"Artsen and specialisten",
    "sg:phone":"+32 2 223 06 79",
    "sg:postcode":"1000",
    "sg:province":"Bruxelles-Capitale",
    "wof:name":"Virginie Chebou Ngantchon",
    "wof:placetype":"venue"
},
  "geometry": {"coordinates":[4.3602061272,50.8525009155],"type":"Point"}
}