{
  "type": "Feature",
  "properties": {
    "iso:country":"BE",
    "sg:address":"Avenue De La Princesse 11",
    "sg:city":"Bernissart",
    "sg:orig_category":"Medische apparatuur, orthopedische artikelen and prothesen Fab",
    "sg:phone":"+32 65 62 23 17",
    "sg:postcode":"7322",
    "sg:province":"Hainaut",
    "wof:name":"Dascotte",
    "wof:placetype":"venue"
},
  "geometry": {"coordinates":[3.7351379395,50.4942893982],"type":"Point"}
}