{
  "type": "Feature",
  "properties": {
    "addr:full":"Rue Elva 260 Fl\u00c9malle Li\u00e8ge 4400",
    "addr:housenumber":"260",
    "addr:postcode":"4400",
    "addr:street":"Rue Elva",
    "iso:country":"BE",
    "sg:address":"Rue Elva 260",
    "sg:city":"Fl\u00c9malle",
    "sg:orig_category":"Openbare veiligheid",
    "sg:phone":"+32 4 231 31 00",
    "sg:postcode":"4400",
    "sg:province":"Li\u00e8ge",
    "wof:name":"Police F\u00c9d\u00c9rale",
    "wof:placetype":"venue"
},
  "geometry": {"coordinates":[5.4804291725,50.6051521301],"type":"Point"}
}