{
  "type": "Feature",
  "properties": {
    "addr:full":"Kunstenstraat 9 Menen West-Vlaanderen 8930",
    "addr:housenumber":"9",
    "addr:postcode":"8930",
    "addr:street":"Kunstenstraat",
    "iso:country":"BE",
    "sg:address":"Kunstenstraat 9",
    "sg:city":"Menen",
    "sg:orig_category":"Non-Classified Establishments",
    "sg:phone":"+32 56 51 21 47",
    "sg:postcode":"8930",
    "sg:province":"West-Vlaanderen",
    "wof:name":"Delaere R Bvba",
    "wof:placetype":"venue"
},
  "geometry": {"coordinates":[3.1160140038,50.7975349426],"type":"Point"}
}