{
  "type": "Feature",
  "properties": {
    "iso:country":"BE",
    "sg:address":"Marli\u00c8restraat 11",
    "sg:city":"Moeskroen/mouscron",
    "sg:classifiers":[
        {
            "category":"Fast Food",
            "type":"Food & Drink"
        }
    ],
    "sg:phone":"+32 56 33 23 08",
    "sg:postcode":"7700",
    "sg:province":"Hainaut",
    "sg:tags":[
        "meeneem",
        "restaurant"
    ],
    "wof:name":"Sibylle Rousseau/le Bristol",
    "wof:placetype":"venue"
},
  "geometry": {"coordinates":[3.2323200703,50.7400932312],"type":"Point"}
}