{
  "type": "Feature",
  "properties": {
    "addr:full":"Rue Belleflamme 349 Li\u00e8ge 1 (grivegn\u00e9e) Li\u00e8ge 4030",
    "addr:housenumber":"349;1",
    "addr:postcode":"4030",
    "addr:street":"Rue Belleflamme",
    "iso:country":"BE",
    "sg:address":"Rue Belleflamme 349",
    "sg:city":"Li\u00e8ge 1 (grivegn\u00e9e)",
    "sg:classifiers":[
        {
            "category":"Personal",
            "subcategory":"Barber",
            "type":"Services"
        }
    ],
    "sg:phone":"+32 4 365 88 30",
    "sg:postcode":"4030",
    "sg:province":"Li\u00e8ge",
    "sg:tags":[
        "gentleman",
        "salon",
        "-",
        "hairdressing"
    ],
    "wof:name":"Albert",
    "wof:placetype":"venue"
},
  "geometry": {"coordinates":[5.6146879196,50.6252441406],"type":"Point"}
}