{
  "type": "Feature",
  "properties": {
    "iso:country":"BE",
    "sg:address":"Elderberg 25",
    "sg:city":"Aalst",
    "sg:orig_category":"Plantes and fleurs Gr",
    "sg:phone":"+32 52 35 77 02",
    "sg:postcode":"9310",
    "sg:province":"Oost-Vlaanderen",
    "wof:name":"Bornauw",
    "wof:placetype":"venue"
},
  "geometry": {"coordinates":[4.1315031052,50.9508895874],"type":"Point"}
}