{
  "type": "Feature",
  "properties": {
    "iso:country":"BE",
    "sg:address":"Rue De Crespin 30",
    "sg:city":"Hensies",
    "sg:classifiers":[
        {
            "category":"Health Services",
            "subcategory":"Doctor",
            "type":"Services"
        }
    ],
    "sg:phone":"+32 65 45 74 97",
    "sg:postcode":"7350",
    "sg:province":"Hainaut",
    "sg:tags":[
        "medicinephysicians",
        "surgeon"
    ],
    "wof:name":"Delaunois A",
    "wof:placetype":"venue"
},
  "geometry": {"coordinates":[3.6836569309,50.4311408997],"type":"Point"}
}