{
  "type": "Feature",
  "properties": {
    "addr:full":"Marktplatz 8 B\u00fctgenbach Li\u00e8ge 4750",
    "addr:housenumber":"8",
    "addr:postcode":"4750",
    "addr:street":"Marktplatz",
    "iso:country":"BE",
    "sg:address":"Marktplatz 8",
    "sg:city":"B\u00fctgenbach",
    "sg:classifiers":[
        {
            "category":"Travel",
            "subcategory":"Hotels & Motels",
            "type":"Entertainment"
        }
    ],
    "sg:phone":"+32 80 44 42 12",
    "sg:postcode":"4750",
    "sg:province":"Li\u00e8ge",
    "wof:name":"Butgenbacher Hof",
    "wof:placetype":"venue"
},
  "geometry": {"coordinates":[6.2058291435,50.426399231],"type":"Point"}
}