{
  "type": "Feature",
  "properties": {
    "addr:full":"Grand'place 8 Braine-le-ch\u00e2teau Brabant Wallon 1440",
    "addr:housenumber":"8",
    "addr:postcode":"1440",
    "addr:street":"Grand'Place",
    "iso:country":"BE",
    "sg:address":"Grand'place 8",
    "sg:city":"Braine-le-ch\u00e2teau",
    "sg:classifiers":[
        {
            "category":"Real Estate",
            "subcategory":"Surveying",
            "type":"Services"
        }
    ],
    "sg:phone":"+32 2 366 90 35",
    "sg:postcode":"1440",
    "sg:province":"Brabant Wallon",
    "sg:tags":[
        "surveyor",
        "land"
    ],
    "wof:name":"De Wals J-l",
    "wof:placetype":"venue"
},
  "geometry": {"coordinates":[4.2669420242,50.6817054749],"type":"Point"}
}