{
  "type": "Feature",
  "properties": {
    "iso:country":"BE",
    "sg:address":"Rue De Lobbes",
    "sg:city":"Thuin",
    "sg:classifiers":[
        {
            "category":"Restaurant",
            "type":"Food & Drink"
        }
    ],
    "sg:postcode":"6530",
    "sg:province":"Hainaut",
    "wof:name":"Ch\u00e2teau Beauregard",
    "wof:placetype":"venue"
},
  "geometry": {"coordinates":[4.271941185,50.3404693604],"type":"Point"}
}