{
  "type": "Feature",
  "properties": {
    "addr:full":"Kalkestraat 126 Opwijk Vlaams-Brabant 1745",
    "addr:housenumber":"126",
    "addr:postcode":"1745",
    "addr:street":"Kalkestraat",
    "iso:country":"BE",
    "sg:address":"Kalkestraat 126",
    "sg:city":"Opwijk",
    "sg:classifiers":[
        {
            "category":"Freight",
            "type":"Transportation"
        }
    ],
    "sg:phone":"+32 52 34 09 45",
    "sg:postcode":"1745",
    "sg:province":"Vlaams-Brabant",
    "sg:tags":[
        "-",
        "transport"
    ],
    "wof:name":"Atim Transport",
    "wof:placetype":"venue"
},
  "geometry": {"coordinates":[4.1688599586,50.9667282104],"type":"Point"}
}