{
  "type": "Feature",
  "properties": {
    "iso:country":"BE",
    "sg:address":"Jevoumont 103",
    "sg:city":"Theux",
    "sg:orig_category":"Elektrische installaties voor woningen",
    "sg:phone":"+32 87 54 24 00",
    "sg:postcode":"4910",
    "sg:province":"Li\u00e8ge",
    "wof:name":"Jean-marc Gilson",
    "wof:placetype":"venue"
},
  "geometry": {"coordinates":[5.8007202148,50.5204582214],"type":"Point"}
}