{
  "type": "Feature",
  "properties": {
    "addr:full":"Iepersestraat 51 Kortrijk West-Vlaanderen 8500",
    "addr:housenumber":"51",
    "addr:postcode":"8500",
    "addr:street":"Iepersestraat",
    "iso:country":"BE",
    "sg:address":"Iepersestraat 51",
    "sg:city":"Kortrijk",
    "sg:classifiers":[
        {
            "category":"Health Services",
            "subcategory":"Health Practitioner",
            "type":"Services"
        }
    ],
    "sg:phone":"+32 56 35 16 76",
    "sg:postcode":"8500",
    "sg:province":"West-Vlaanderen",
    "sg:tags":[
        "therapist",
        "speech"
    ],
    "wof:name":"Maes S",
    "wof:placetype":"venue"
},
  "geometry": {"coordinates":[3.2609601021,50.8429336548],"type":"Point"}
}