{
  "type": "Feature",
  "properties": {
    "iso:country":"BE",
    "sg:address":"Rue Des Trois Cerisiers 2",
    "sg:city":"Walhain (nil-saint-vincent-saint-martin)",
    "sg:classifiers":[
        {
            "category":"Health Services",
            "subcategory":"Health Practitioner",
            "type":"Services"
        }
    ],
    "sg:phone":"+32 10 65 91 87",
    "sg:postcode":"1457",
    "sg:province":"Brabant Wallon",
    "sg:tags":[
        "therapist",
        "speech"
    ],
    "wof:name":"Bouttiau J",
    "wof:placetype":"venue"
},
  "geometry": {"coordinates":[4.6753129959,50.6366462708],"type":"Point"}
}