{
  "type": "Feature",
  "properties": {
    "addr:full":"Ninoofse Steenweg 207 Gooik Vlaams-Brabant 1755",
    "addr:housenumber":"207",
    "addr:postcode":"1755",
    "addr:street":"Ninoofse Steenweg",
    "iso:country":"BE",
    "sg:address":"Ninoofse Steenweg 207",
    "sg:city":"Gooik",
    "sg:classifiers":[
        {
            "category":"Insurance",
            "subcategory":"Insurance Agent",
            "type":"Services"
        }
    ],
    "sg:phone":"+32 2 532 43 78",
    "sg:postcode":"1755",
    "sg:province":"Vlaams-Brabant",
    "sg:tags":[
        "verzekeringsmakelaars",
        "expert"
    ],
    "wof:name":"Vannijvel Service-buro",
    "wof:placetype":"venue"
},
  "geometry": {"coordinates":[4.0883002281,50.7812805176],"type":"Point"}
}