{
  "type": "Feature",
  "properties": {
    "addr:full":"Basiliekstraat 16 Halle Vlaams-Brabant 1500",
    "addr:housenumber":"16",
    "addr:postcode":"1500",
    "addr:street":"Basiliekstraat",
    "iso:country":"BE",
    "sg:address":"Basiliekstraat 16",
    "sg:city":"Halle",
    "sg:orig_category":"Sous-v\u00eatements and lingerie. Parfumeries",
    "sg:phone":"+32 2 356 50 13",
    "sg:postcode":"1500",
    "sg:province":"Vlaams-Brabant",
    "wof:name":"In 't Boerinneke",
    "wof:placetype":"venue"
},
  "geometry": {"coordinates":[4.2370419502,50.7356071472],"type":"Point"}
}