{
  "type": "Feature",
  "properties": {
    "addr:full":"Schoenberg 170 Sankt Vith/saint-vith Li\u00e8ge 4782",
    "addr:housenumber":"170",
    "addr:postcode":"4782",
    "addr:street":"Schoenberg",
    "iso:country":"BE",
    "sg:address":"Schoenberg 170",
    "sg:city":"Sankt Vith/saint-vith",
    "sg:orig_category":"Dakwerken Woningbouw",
    "sg:phone":"+32 80 54 00 10",
    "sg:postcode":"4782",
    "sg:province":"Li\u00e8ge",
    "wof:name":"J.- M. Leufgen/leufgen Jm",
    "wof:placetype":"venue"
},
  "geometry": {"coordinates":[6.2570099831,50.2879943848],"type":"Point"}
}