{
  "type": "Feature",
  "properties": {
    "iso:country":"BE",
    "sg:address":"Avenue Des Martyrs 185bb",
    "sg:city":"Fleron",
    "sg:orig_category":"S\u00e9curit\u00e9 sociale",
    "sg:phone":"+32 4 358 90 10",
    "sg:postcode":"4620",
    "sg:province":"Li\u00e8ge",
    "wof:name":"Mutualit\u00c9 Chr\u00c9tienne",
    "wof:placetype":"venue"
},
  "geometry": {"coordinates":[5.6799368858,50.6147651672],"type":"Point"}
}