{
  "type": "Feature",
  "properties": {
    "iso:country":"BE",
    "sg:address":"Rue Henri Massange 3",
    "sg:city":"Stavelot",
    "sg:orig_category":"Antiquit\u00e9s",
    "sg:phone":"+32 80 86 31 02",
    "sg:postcode":"4970",
    "sg:province":"Li\u00e8ge",
    "wof:name":"Raymonde Blaise",
    "wof:placetype":"venue"
},
  "geometry": {"coordinates":[5.933163166,50.3915863037],"type":"Point"}
}