{
  "type": "Feature",
  "properties": {
    "iso:country":"BE",
    "sg:address":"Goudenkruispunt 57",
    "sg:city":"Tielt-winge",
    "sg:orig_category":"Biens d'occasion. Traitement de donn\u00e9es",
    "sg:phone":"+32 16 47 44 23",
    "sg:postcode":"3390",
    "sg:province":"Vlaams-Brabant",
    "wof:name":"Cash'land",
    "wof:placetype":"venue"
},
  "geometry": {"coordinates":[4.8715348244,50.906124115],"type":"Point"}
}