{
  "type": "Feature",
  "properties": {
    "iso:country":"BE",
    "sg:address":"Chee De Lodelinsart 72",
    "sg:city":"Gilly",
    "sg:classifiers":[
        {
            "category":"Banks & Credit Unions",
            "subcategory":"Bank",
            "type":"Services"
        }
    ],
    "sg:phone":"+32 83 41 09 58",
    "sg:postcode":"6060",
    "sg:province":"Hainaut",
    "wof:name":"Cr\u00e9dit Communal",
    "wof:placetype":"venue"
},
  "geometry": {"coordinates":[4.4781742096,50.4247055054],"type":"Point"}
}