{
  "type": "Feature",
  "properties": {
    "addr:full":". Zele Oost-Vlaanderen 9240",
    "addr:postcode":"9240",
    "iso:country":"BE",
    "sg:address":".",
    "sg:city":"Zele",
    "sg:orig_category":"Apotheken",
    "sg:phone":"+32 900 10 500",
    "sg:postcode":"9240",
    "sg:province":"Oost-Vlaanderen",
    "wof:name":"Apothekers Van Wacht",
    "wof:placetype":"venue"
},
  "geometry": {"coordinates":[4.037899971,51.0681152344],"type":"Point"}
}