{
  "type": "Feature",
  "properties": {
    "iso:country":"BE",
    "sg:address":"Marktplein 7 Box 1",
    "sg:city":"Neerpelt",
    "sg:classifiers":[
        {
            "category":"Personal",
            "subcategory":"Beauty Salon",
            "type":"Services"
        }
    ],
    "sg:phone":"+32 11 39 29 00",
    "sg:postcode":"3910",
    "sg:province":"Limburg",
    "sg:tags":[
        "slimming"
    ],
    "wof:name":"Cara Vita",
    "wof:placetype":"venue"
},
  "geometry": {"coordinates":[5.4308919907,51.2294998169],"type":"Point"}
}