{
  "type": "Feature",
  "properties": {
    "iso:country":"BE",
    "sg:address":"De Stappe 2",
    "sg:city":"Mortsel",
    "sg:orig_category":"Boissons Boissons",
    "sg:phone":"+32 3 455 97 21",
    "sg:postcode":"2640",
    "sg:province":"Antwerpen",
    "wof:name":"Fa. Hutsebaut",
    "wof:placetype":"venue"
},
  "geometry": {"coordinates":[4.4694981575,51.1645278931],"type":"Point"}
}