{
  "type": "Feature",
  "properties": {
    "addr:full":"Chauss\u00c9e De Namur 47 Eghezee Namur 5310",
    "addr:housenumber":"47",
    "addr:postcode":"5310",
    "addr:street":"Chausse\u0301E De Namur;Namur",
    "iso:country":"BE",
    "sg:address":"Chauss\u00c9e De Namur 47",
    "sg:city":"Eghezee",
    "sg:orig_category":"GROENTEN AND FRUIT Voedingsspeciaalzaken",
    "sg:phone":"+32 81 81 23 67",
    "sg:postcode":"5310",
    "sg:province":"Namur",
    "wof:name":"Au Panier Mosan",
    "wof:placetype":"venue"
},
  "geometry": {"coordinates":[4.9123549461,50.5878753662],"type":"Point"}
}