{
  "type": "Feature",
  "properties": {
    "addr:full":"39 Stoppelweg 8970 Poperinge 39",
    "addr:housenumber":"39;39",
    "addr:postcode":"8970",
    "addr:street":"Stoppelweg",
    "iso:country":"BE",
    "sg:address":"39",
    "sg:city":"Stoppelweg 8970 Poperinge",
    "sg:classifiers":[
        {
            "category":"Travel",
            "subcategory":"Hotels & Motels",
            "type":"Entertainment"
        }
    ],
    "sg:phone":"+32 57 33 41 39",
    "sg:postcode":"39",
    "sg:tags":[
        "hotels",
        "business",
        "restaurant"
    ],
    "wof:name":"Lebbe Filip M.",
    "wof:placetype":"venue"
},
  "geometry": {"coordinates":[2.6690819263,50.8319091797],"type":"Point"}
}