{
  "type": "Feature",
  "properties": {
    "iso:country":"BE",
    "sg:address":"Nieuwstraat 46",
    "sg:city":"Knesselare",
    "sg:classifiers":[
        {
            "category":"Real Estate",
            "subcategory":"Architect",
            "type":"Services"
        }
    ],
    "sg:phone":"+32 9 374 50 40",
    "sg:postcode":"9910",
    "sg:province":"Oost-Vlaanderen",
    "wof:name":"Van Den Brande G",
    "wof:placetype":"venue"
},
  "geometry": {"coordinates":[3.4192860126,51.1450881958],"type":"Point"}
}