{
  "type": "Feature",
  "properties": {
    "addr:full":"Rue Du Coll\u00c8ge 2 Dinant Namur 5500",
    "addr:housenumber":"2",
    "addr:postcode":"5500",
    "addr:street":"Rue Du Colle\u0300Ge",
    "iso:country":"BE",
    "sg:address":"Rue Du Coll\u00c8ge 2",
    "sg:city":"Dinant",
    "sg:orig_category":"Rusthuizen and serviceflats",
    "sg:phone":"+32 82 22 68 44",
    "sg:postcode":"5500",
    "sg:province":"Namur",
    "wof:name":"Home Churchill",
    "wof:placetype":"venue"
},
  "geometry": {"coordinates":[4.9134430885,50.2582778931],"type":"Point"}
}