{
  "type": "Feature",
  "properties": {
    "addr:full":"Avenue Du Progr\u00c8s 10 Ans Li\u00e8ge 4432",
    "addr:housenumber":"10",
    "addr:postcode":"4432",
    "addr:street":"Avenue Du Progre\u0300S",
    "iso:country":"BE",
    "sg:address":"Avenue Du Progr\u00c8s 10",
    "sg:city":"Ans",
    "sg:orig_category":"Procesbesturingssystemen Fab",
    "sg:phone":"+32 4 247 36 37",
    "sg:postcode":"4432",
    "sg:province":"Li\u00e8ge",
    "wof:name":"Procim Industrie",
    "wof:placetype":"venue"
},
  "geometry": {"coordinates":[5.5253558159,50.6730155945],"type":"Point"}
}