{
  "type": "Feature",
  "properties": {
    "addr:full":"Houtsaegerlaan 12 Koksijde West-Vlaanderen 8670",
    "addr:housenumber":"12",
    "addr:postcode":"8670",
    "addr:street":"Houtsaegerlaan",
    "iso:country":"BE",
    "sg:address":"Houtsaegerlaan 12",
    "sg:city":"Koksijde",
    "sg:classifiers":[
        {
            "category":"Autos & Motor Vehicles",
            "subcategory":"Automobile Sales",
            "type":"Retail Goods"
        }
    ],
    "sg:phone":"+32 58 52 06 40",
    "sg:postcode":"8670",
    "sg:province":"West-Vlaanderen",
    "sg:tags":[
        "car",
        "used",
        "-"
    ],
    "wof:name":"Autohandel Topcars Bvba",
    "wof:placetype":"venue"
},
  "geometry": {"coordinates":[2.6512598991,51.1057243347],"type":"Point"}
}