{
  "type": "Feature",
  "properties": {
    "iso:country":"BE",
    "sg:address":"Noordzandstraat 24",
    "sg:city":"Brugge",
    "sg:classifiers":[
        {
            "category":"Real Estate",
            "subcategory":"Real Estate Services",
            "type":"Services"
        }
    ],
    "sg:phone":"+32 50 33 39 76",
    "sg:postcode":"8000",
    "sg:province":"West-Vlaanderen",
    "wof:name":"Agence Van Den Abeele Bvba",
    "wof:placetype":"venue"
},
  "geometry": {"coordinates":[3.2206120491,51.2078514099],"type":"Point"}
}