{
  "type": "Feature",
  "properties": {
    "addr:full":"Kasterstr 86 Wetteren Oost-Vlaanderen 9230",
    "addr:housenumber":"86",
    "addr:postcode":"9230",
    "addr:street":"Kasterstr",
    "iso:country":"BE",
    "sg:address":"Kasterstr 86",
    "sg:city":"Wetteren",
    "sg:classifiers":[
        {
            "category":"Farming",
            "subcategory":"Farm",
            "type":"Manufacturing & Wholesale Goods"
        }
    ],
    "sg:phone":"+32 9 369 39 22",
    "sg:postcode":"9230",
    "sg:province":"Oost-Vlaanderen",
    "sg:tags":[
        "horticulture",
        "agriculture",
        "livestock"
    ],
    "wof:name":"Abog Nv",
    "wof:placetype":"venue"
},
  "geometry": {"coordinates":[3.8876450062,51.012096405],"type":"Point"}
}