{
  "type": "Feature",
  "properties": {
    "addr:full":"Grezstraat 11 Oud-heverlee Vlaams-Brabant 3054",
    "addr:housenumber":"11",
    "addr:postcode":"3054",
    "addr:street":"Grezstraat",
    "iso:country":"BE",
    "sg:address":"Grezstraat 11",
    "sg:city":"Oud-heverlee",
    "sg:classifiers":[
        {
            "category":"Government",
            "subcategory":"Police Station",
            "type":"Public Place"
        }
    ],
    "sg:phone":"+32 16 40 12 13",
    "sg:postcode":"3054",
    "sg:province":"Vlaams-Brabant",
    "sg:tags":[
        "gendarmerie"
    ],
    "wof:name":"Federale Politie",
    "wof:placetype":"venue"
},
  "geometry": {"coordinates":[4.6893939972,50.8263511658],"type":"Point"}
}