{
  "type": "Feature",
  "properties": {
    "addr:full":"Jozef Wautersstraat 77 Leuven Vlaams-Brabant 3010",
    "addr:housenumber":"77",
    "addr:postcode":"3010",
    "addr:street":"Jozef Wautersstraat",
    "iso:country":"BE",
    "sg:address":"Jozef Wautersstraat 77",
    "sg:city":"Leuven",
    "sg:orig_category":"M\u00e9decins and sp\u00e9cialistes",
    "sg:phone":"+32 16 25 44 00",
    "sg:postcode":"3010",
    "sg:province":"Vlaams-Brabant",
    "wof:name":"Ann-katrien Minne",
    "wof:placetype":"venue"
},
  "geometry": {"coordinates":[4.7304501534,50.889755249],"type":"Point"}
}