{
  "type": "Feature",
  "properties": {
    "addr:full":"August Van Landeghemstr. 97 Willebroek Antwerpen 2830",
    "addr:housenumber":"97",
    "addr:postcode":"2830",
    "addr:street":"August;Landeghemstr.",
    "iso:country":"BE",
    "sg:address":"August Van Landeghemstr. 97",
    "sg:city":"Willebroek",
    "sg:orig_category":"Offices du tourisme",
    "sg:phone":"+32 3 886 22 66",
    "sg:postcode":"2830",
    "sg:province":"Antwerpen",
    "wof:name":"V.v.v. Vaartland",
    "wof:placetype":"venue"
},
  "geometry": {"coordinates":[4.3617768288,51.0634651184],"type":"Point"}
}