{
  "type": "Feature",
  "properties": {
    "iso:country":"BE",
    "sg:address":"Meeuwerweg 16",
    "sg:city":"Houthalen-helchteren (houthalen)",
    "sg:classifiers":[
        {
            "category":"Communications",
            "subcategory":"Television Station",
            "type":"Services"
        }
    ],
    "sg:phone":"+32 11 52 64 52",
    "sg:postcode":"3530",
    "sg:province":"Limburg",
    "sg:tags":[
        "report",
        "video"
    ],
    "wof:name":"Johan Videoprodukties",
    "wof:placetype":"venue"
},
  "geometry": {"coordinates":[5.3997192383,51.0358161926],"type":"Point"}
}