{
  "type": "Feature",
  "properties": {
    "addr:full":"Olmenlei 46 Zoersel Antwerpen 2980",
    "addr:housenumber":"46",
    "addr:postcode":"2980",
    "addr:street":"Olmenlei",
    "iso:country":"BE",
    "sg:address":"Olmenlei 46",
    "sg:city":"Zoersel",
    "sg:orig_category":"Installatie van houten of kunststof schrijnwerk Installatie van metalen schrijnwerk Verlichting and ",
    "sg:phone":"+32 3 309 96 07",
    "sg:postcode":"2980",
    "sg:province":"Antwerpen",
    "wof:name":"I.s.p.",
    "wof:placetype":"venue"
},
  "geometry": {"coordinates":[4.6589951515,51.2741584778],"type":"Point"}
}