{
  "type": "Feature",
  "properties": {
    "iso:country":"BE",
    "sg:address":"Tiensesteenweg 80",
    "sg:city":"Sint-truiden",
    "sg:classifiers":[
        {
            "category":"Health Services",
            "subcategory":"Nursing And Care Facility",
            "type":"Services"
        }
    ],
    "sg:phone":"+32 11 69 36 60",
    "sg:postcode":"3800",
    "sg:province":"Limburg",
    "sg:tags":[
        "access",
        "equipment",
        "hospital",
        "-"
    ],
    "wof:name":"Entermed Belgium Bvba",
    "wof:placetype":"venue"
},
  "geometry": {"coordinates":[5.1832799911,50.8136482239],"type":"Point"}
}