{
  "type": "Feature",
  "properties": {
    "iso:country":"BE",
    "sg:address":"Rue Des P\u00e2querettes 8",
    "sg:city":"Estaimpuis (estaimbourg)",
    "sg:classifiers":[
        {
            "category":"Personal",
            "subcategory":"Nail Salon",
            "type":"Services"
        }
    ],
    "sg:phone":"+32 69 55 69 20",
    "sg:postcode":"7730",
    "sg:province":"Hainaut",
    "sg:tags":[
        "pedicure"
    ],
    "wof:name":"Willocq N",
    "wof:placetype":"venue"
},
  "geometry": {"coordinates":[3.3133280277,50.6830558777],"type":"Point"}
}