{
  "type": "Feature",
  "properties": {
    "addr:full":"Prinses Clementinalaan 45 Gent Oost-Vlaanderen 9000",
    "addr:housenumber":"45",
    "addr:postcode":"9000",
    "addr:street":"Prinses Clementinalaan;Oost-Vlaanderen",
    "iso:country":"BE",
    "sg:address":"Prinses Clementinalaan 45",
    "sg:city":"Gent",
    "sg:orig_category":"Cr\u00e9meries",
    "sg:phone":"+32 9 222 21 30",
    "sg:postcode":"9000",
    "sg:province":"Oost-Vlaanderen",
    "wof:name":"Huis Lekkerbek",
    "wof:placetype":"venue"
},
  "geometry": {"coordinates":[3.7153170109,51.0348014832],"type":"Point"}
}