{
  "type": "Feature",
  "properties": {
    "addr:full":"Marktplein 82 Harelbeke West-Vlaanderen 8530",
    "addr:housenumber":"82",
    "addr:postcode":"8530",
    "addr:street":"Marktplein",
    "iso:country":"BE",
    "sg:address":"Marktplein 82",
    "sg:city":"Harelbeke",
    "sg:classifiers":[
        {
            "category":"Retail",
            "subcategory":"Laundry & Dry Cleaning",
            "type":"Services"
        }
    ],
    "sg:phone":"+32 56 71 18 81",
    "sg:postcode":"8530",
    "sg:province":"West-Vlaanderen",
    "sg:tags":[
        "dyer",
        "cleaner"
    ],
    "wof:name":"Wasserij Perfecta Bvba",
    "wof:placetype":"venue"
},
  "geometry": {"coordinates":[3.3085339069,50.8552398682],"type":"Point"}
}