{
  "type": "Feature",
  "properties": {
    "iso:country":"BE",
    "sg:address":"Louis Melsensstraat 9",
    "sg:city":"Leuven",
    "sg:classifiers":[
        {
            "category":"Personal",
            "subcategory":"Beauty Salon",
            "type":"Services"
        }
    ],
    "sg:phone":"+32 16 22 93 87",
    "sg:postcode":"3000",
    "sg:province":"Vlaams-Brabant",
    "sg:tags":[
        "lady",
        "-",
        "hairdressing"
    ],
    "wof:name":"Jones Hair",
    "wof:placetype":"venue"
},
  "geometry": {"coordinates":[4.7091507912,50.880821228],"type":"Point"}
}