{
  "type": "Feature",
  "properties": {
    "addr:full":"Kouterstraat 63 Houthulst West-Vlaanderen 8650",
    "addr:housenumber":"63",
    "addr:postcode":"8650",
    "addr:street":"Kouterstraat",
    "iso:country":"BE",
    "sg:address":"Kouterstraat 63",
    "sg:city":"Houthulst",
    "sg:orig_category":"Herstellingen and onderhoud van auto's",
    "sg:phone":"+32 51 54 59 92",
    "sg:postcode":"8650",
    "sg:province":"West-Vlaanderen",
    "wof:name":"Dirk Boussemaere",
    "wof:placetype":"venue"
},
  "geometry": {"coordinates":[2.8557620049,50.9510345459],"type":"Point"}
}