{
  "type": "Feature",
  "properties": {
    "addr:full":"Rue Du Warch\u00c9 35 La Hulpe Brabant Wallon 1310",
    "addr:housenumber":"35",
    "addr:postcode":"1310",
    "addr:street":"Rue Du Warche\u0301",
    "iso:country":"BE",
    "sg:address":"Rue Du Warch\u00c9 35",
    "sg:city":"La Hulpe",
    "sg:classifiers":[
        {
            "category":"Fast Food",
            "type":"Food & Drink"
        }
    ],
    "sg:phone":"+32 2 652 00 23",
    "sg:postcode":"1310",
    "sg:province":"Brabant Wallon",
    "sg:tags":[
        "de",
        "co",
        "organisation",
        "\u00c0",
        "catering",
        "emporter",
        "salles",
        "f\u00cates",
        "restaurants"
    ],
    "wof:name":"Resto Gaillemarde",
    "wof:placetype":"venue"
},
  "geometry": {"coordinates":[4.4517669678,50.72498703],"type":"Point"}
}