{
  "type": "Feature",
  "properties": {
    "iso:country":"BE",
    "sg:address":"Fazantenlaan 8",
    "sg:city":"Antwerpen (wilrijk)",
    "sg:classifiers":[
        {
            "category":"Arts & Performance",
            "subcategory":"Theater",
            "type":"Entertainment"
        }
    ],
    "sg:phone":"+32 3 440 26 44",
    "sg:postcode":"2610",
    "sg:province":"Antwerpen",
    "sg:tags":[
        "group",
        "theatre"
    ],
    "wof:name":"Vlaams Radio-toneel",
    "wof:placetype":"venue"
},
  "geometry": {"coordinates":[4.3946051598,51.1691131592],"type":"Point"}
}