{
  "type": "Feature",
  "properties": {
    "iso:country":"BE",
    "sg:address":"Rue De La Blanche T\u00eate 14",
    "sg:city":"Estaimpuis",
    "sg:classifiers":[
        {
            "category":"Building & Trades",
            "subcategory":"Plumbing",
            "type":"Services"
        }
    ],
    "sg:phone":"+32 56 48 69 29",
    "sg:postcode":"7730",
    "sg:province":"Hainaut",
    "sg:tags":[
        "contractor"
    ],
    "wof:name":"Dewaele D",
    "wof:placetype":"venue"
},
  "geometry": {"coordinates":[3.2643830776,50.7037811279],"type":"Point"}
}