{
  "type": "Feature",
  "properties": {
    "addr:full":"Rue Pont Saint-pierre 46 Bassenge (glons) Li\u00e8ge 4690",
    "addr:housenumber":"46",
    "addr:postcode":"4690",
    "addr:street":"Rue Pont Saint-Pierre;Glons",
    "iso:country":"BE",
    "sg:address":"Rue Pont Saint-pierre 46",
    "sg:city":"Bassenge (glons)",
    "sg:classifiers":[
        {
            "category":"Real Estate",
            "subcategory":"Real Estate Services",
            "type":"Services"
        }
    ],
    "sg:phone":"+32 4 286 18 87",
    "sg:postcode":"4690",
    "sg:province":"Li\u00e8ge",
    "wof:name":"Cloes J",
    "wof:placetype":"venue"
},
  "geometry": {"coordinates":[5.5454077721,50.7539634705],"type":"Point"}
}