{
  "type": "Feature",
  "properties": {
    "iso:country":"BE",
    "sg:address":"Marktplein 13",
    "sg:city":"Brakel",
    "sg:orig_category":"Caf\u00e9s Varkenskwekers",
    "sg:phone":"+32 55 42 41 07",
    "sg:postcode":"9660",
    "sg:province":"Oost-Vlaanderen",
    "wof:name":"Victor Everaet",
    "wof:placetype":"venue"
},
  "geometry": {"coordinates":[3.7652659416,50.8038978577],"type":"Point"}
}