{
  "type": "Feature",
  "properties": {
    "addr:full":"Vogelsancklaan 265 Zonhoven Limburg 3520",
    "addr:housenumber":"265",
    "addr:postcode":"3520",
    "addr:street":"Vogelsancklaan",
    "iso:country":"BE",
    "sg:address":"Vogelsancklaan 265",
    "sg:city":"Zonhoven",
    "sg:classifiers":[
        {
            "category":"Professional",
            "subcategory":"Management & Consulting",
            "type":"Services"
        }
    ],
    "sg:phone":"+32 475 94 34 80",
    "sg:postcode":"3520",
    "sg:province":"Limburg",
    "sg:tags":[
        "marketing",
        "-",
        "consultant"
    ],
    "wof:name":"Accel Nv",
    "wof:placetype":"venue"
},
  "geometry": {"coordinates":[5.3303670883,50.9995918274],"type":"Point"}
}