{
  "type": "Feature",
  "properties": {
    "addr:full":"Rue Barth\u00e9lemy Molet 28 Sambreville (tamines) Namur 5060",
    "addr:housenumber":"28",
    "addr:postcode":"5060",
    "addr:street":"Rue Barthe\u0301Lemy Molet",
    "iso:country":"BE",
    "sg:address":"Rue Barth\u00e9lemy Molet 28",
    "sg:city":"Sambreville (tamines)",
    "sg:classifiers":[
        {
            "category":"Health Services",
            "subcategory":"Health Practitioner",
            "type":"Services"
        }
    ],
    "sg:phone":"+32 71 77 72 58",
    "sg:postcode":"5060",
    "sg:province":"Namur",
    "sg:tags":[
        "physiotherapist"
    ],
    "wof:name":"Levrie Christian",
    "wof:placetype":"venue"
},
  "geometry": {"coordinates":[4.5897297859,50.4382591248],"type":"Point"}
}