{
  "type": "Feature",
  "properties": {
    "addr:full":"Zavelstraat 9 Stekene Oost-Vlaanderen 9190",
    "addr:housenumber":"9",
    "addr:postcode":"9190",
    "addr:street":"Zavelstraat",
    "iso:country":"BE",
    "sg:address":"Zavelstraat 9",
    "sg:city":"Stekene",
    "sg:orig_category":"Carpets, Hand-Tufted",
    "sg:phone":"+32 3 779 80 97",
    "sg:postcode":"9190",
    "sg:province":"Oost-Vlaanderen",
    "wof:name":"Jean-marie Desseaux B.v.b.a.",
    "wof:placetype":"venue"
},
  "geometry": {"coordinates":[4.0519762039,51.2083473206],"type":"Point"}
}