{
  "type": "Feature",
  "properties": {
    "addr:full":"Rue Des Dominicains 38 Liege-centre Li\u00e8ge 4000",
    "addr:housenumber":"38",
    "addr:postcode":"4000",
    "addr:street":"Rue Des Dominicains",
    "iso:country":"BE",
    "sg:address":"Rue Des Dominicains 38",
    "sg:city":"Liege-centre",
    "sg:classifiers":[
        {
            "category":"Utilities",
            "subcategory":"Telephone",
            "type":"Services"
        }
    ],
    "sg:phone":"+32 4 220 50 00",
    "sg:postcode":"4000",
    "sg:province":"Li\u00e8ge",
    "sg:tags":[
        "phone",
        "telecommunicatiesystemen",
        "house"
    ],
    "wof:name":"The Phone House",
    "wof:placetype":"venue"
},
  "geometry": {"coordinates":[6.2250900269,44.0888595581],"type":"Point"}
}