{
  "type": "Feature",
  "properties": {
    "addr:full":"Frederik Burvenichstraat 171 Gent (gentbrugge) Oost-Vlaanderen 9050",
    "addr:housenumber":"171",
    "addr:postcode":"9050",
    "addr:street":"Frederik Burvenichstraat",
    "iso:country":"BE",
    "sg:address":"Frederik Burvenichstraat 171",
    "sg:city":"Gent (gentbrugge)",
    "sg:classifiers":[
        {
            "category":"Sports & Exercise",
            "subcategory":"Gym",
            "type":"Entertainment"
        }
    ],
    "sg:phone":"+32 9 232 32 58",
    "sg:postcode":"9050",
    "sg:province":"Oost-Vlaanderen",
    "sg:tags":[
        "fitness"
    ],
    "wof:name":"Body Shape",
    "wof:placetype":"venue"
},
  "geometry": {"coordinates":[3.7480499744,51.0391197205],"type":"Point"}
}