{
  "type": "Feature",
  "properties": {
    "addr:full":"Nieuwewandeling 52 Gent Oost-Vlaanderen 9000",
    "addr:housenumber":"52",
    "addr:postcode":"9000",
    "addr:street":"Nieuwewandeling;Oost-Vlaanderen",
    "iso:country":"BE",
    "sg:address":"Nieuwewandeling 52",
    "sg:city":"Gent",
    "sg:orig_category":"Electrom\u00e9nager, t\u00e9l\u00e9visions and radios",
    "sg:phone":"+32 9 223 01 52",
    "sg:postcode":"9000",
    "sg:province":"Oost-Vlaanderen",
    "wof:name":"Fa. Deweerd",
    "wof:placetype":"venue"
},
  "geometry": {"coordinates":[3.7067248821,51.0552330017],"type":"Point"}
}