{
  "type": "Feature",
  "properties": {
    "iso:country":"BE",
    "sg:address":"Dorpstraat 17",
    "sg:city":"Huldenberg (neerijse)",
    "sg:classifiers":[
        {
            "category":"Communications",
            "type":"Services"
        }
    ],
    "sg:phone":"+32 16 89 96 06",
    "sg:postcode":"3040",
    "sg:province":"Vlaams-Brabant",
    "sg:tags":[
        "translator"
    ],
    "wof:name":"Quartier Dieter Translations",
    "wof:placetype":"venue"
},
  "geometry": {"coordinates":[4.6265978813,50.8175048828],"type":"Point"}
}