{
  "type": "Feature",
  "properties": {
    "iso:country":"BE",
    "sg:address":"Rue De Neuville 2",
    "sg:city":"Philippeville",
    "sg:orig_category":"Koerierbedrijven",
    "sg:phone":"+32 71 66 83 20",
    "sg:postcode":"5600",
    "sg:province":"Namur",
    "wof:name":"Taxipost-e.m.s.",
    "wof:placetype":"venue"
},
  "geometry": {"coordinates":[4.5362081528,50.1952056885],"type":"Point"}
}