{
  "type": "Feature",
  "properties": {
    "addr:full":"Oostmeetstraat 2 Koekelare West-Vlaanderen 8680",
    "addr:housenumber":"2",
    "addr:postcode":"8680",
    "addr:street":"Oostmeetstraat",
    "iso:country":"BE",
    "sg:address":"Oostmeetstraat 2",
    "sg:city":"Koekelare",
    "sg:classifiers":[
        {
            "category":"Bars & Pubs",
            "type":"Food & Drink"
        }
    ],
    "sg:phone":"+32 51 58 18 24",
    "sg:postcode":"8680",
    "sg:province":"West-Vlaanderen",
    "wof:name":"Valentino Club",
    "wof:placetype":"venue"
},
  "geometry": {"coordinates":[2.9734818935,51.0892372131],"type":"Point"}
}