{
  "type": "Feature",
  "properties": {
    "iso:country":"BE",
    "sg:address":"Kruisabeel 31",
    "sg:city":"Lebbeke (wieze)",
    "sg:classifiers":[
        {
            "category":"Professional",
            "subcategory":"Engineering",
            "type":"Services"
        }
    ],
    "sg:phone":"+32 53 75 00 15",
    "sg:postcode":"9280",
    "sg:province":"Oost-Vlaanderen",
    "sg:tags":[
        "workshop"
    ],
    "wof:name":"Van Den Broeck Construct Bvba",
    "wof:placetype":"venue"
},
  "geometry": {"coordinates":[4.0822439194,50.9722938538],"type":"Point"}
}