{
  "type": "Feature",
  "properties": {
    "addr:full":"Avenue Du Centenaire 0 Nivelles Brabant Wallon 1400",
    "addr:housenumber":"0",
    "addr:postcode":"1400",
    "addr:street":"Avenue Du Centenaire",
    "iso:country":"BE",
    "sg:address":"Avenue Du Centenaire 0",
    "sg:city":"Nivelles",
    "sg:orig_category":"Schoenen",
    "sg:phone":"+32 67 21 84 84",
    "sg:postcode":"1400",
    "sg:province":"Brabant Wallon",
    "wof:name":"Shoe Discount",
    "wof:placetype":"venue"
},
  "geometry": {"coordinates":[4.346804142,50.5981941223],"type":"Point"}
}