{
  "type": "Feature",
  "properties": {
    "addr:full":"Sint-lenaartseweg 55b Hoogstraten Antwerpen 2320",
    "addr:housenumber":"55b",
    "addr:postcode":"2320",
    "addr:street":"Sint-Lenaartseweg",
    "iso:country":"BE",
    "sg:address":"Sint-lenaartseweg 55b",
    "sg:city":"Hoogstraten",
    "sg:classifiers":[
        {
            "category":"Structure",
            "subcategory":"Office Building",
            "type":"Public Place"
        }
    ],
    "sg:phone":"+32 3 314 89 17",
    "sg:postcode":"2320",
    "sg:province":"Antwerpen",
    "sg:tags":[
        "-",
        "type",
        "door",
        "sliding",
        "overhead"
    ],
    "wof:name":"Goris Bvba",
    "wof:placetype":"venue"
},
  "geometry": {"coordinates":[4.7395238876,51.38722229],"type":"Point"}
}