{
  "type": "Feature",
  "properties": {
    "iso:country":"BE",
    "sg:address":"Major-long-strasse 7",
    "sg:city":"Sankt Vith",
    "sg:classifiers":[
        {
            "category":"Health Services",
            "subcategory":"Dentist",
            "type":"Services"
        }
    ],
    "sg:phone":"+32 80 22 79 50",
    "sg:postcode":"4780",
    "sg:province":"Li\u00e8ge",
    "wof:name":"Huppertz A",
    "wof:placetype":"venue"
},
  "geometry": {"coordinates":[6.127204895,50.280128479],"type":"Point"}
}