{
  "type": "Feature",
  "properties": {
    "addr:full":"Av De Cortenbergh 52 Bruxelles Bruxelles-Capitale 1000",
    "addr:housenumber":"52",
    "addr:postcode":"1000",
    "addr:street":"Av De Cortenbergh",
    "iso:country":"BE",
    "sg:address":"Av De Cortenbergh 52",
    "sg:city":"Bruxelles",
    "sg:classifiers":[
        {
            "category":"Banks & Credit Unions",
            "subcategory":"Financial Services",
            "type":"Services"
        }
    ],
    "sg:phone":"+32 2 740 27 50",
    "sg:postcode":"1000",
    "sg:province":"Bruxelles-Capitale",
    "sg:tags":[
        "banking",
        "finance",
        "insurance"
    ],
    "wof:name":"Cigna Life Insurancy Cy Sa",
    "wof:placetype":"venue"
},
  "geometry": {"coordinates":[4.3866710663,50.8437385559],"type":"Point"}
}