{
  "type": "Feature",
  "properties": {
    "iso:country":"BE",
    "sg:address":"Hoog Keizel 33b11",
    "sg:city":"Diepenbeek",
    "sg:orig_category":"Eleveurs de bovins. Eleveurs and marchands de porcs",
    "sg:phone":"+32 11 23 48 77",
    "sg:postcode":"3590",
    "sg:province":"Limburg",
    "wof:name":"Luc Cornelissen",
    "wof:placetype":"venue"
},
  "geometry": {"coordinates":[5.3934440613,50.9132156372],"type":"Point"}
}