{
  "type": "Feature",
  "properties": {
    "addr:full":"Aarschotsebaan 95 Berlaar Antwerpen 2590",
    "addr:housenumber":"95",
    "addr:postcode":"2590",
    "addr:street":"Aarschotsebaan",
    "iso:country":"BE",
    "sg:address":"Aarschotsebaan 95",
    "sg:city":"Berlaar",
    "sg:classifiers":[
        {
            "category":"Cafe",
            "type":"Food & Drink"
        }
    ],
    "sg:phone":"+32 15 24 14 44",
    "sg:postcode":"2590",
    "sg:province":"Antwerpen",
    "sg:tags":[
        "caf\u00e9s"
    ],
    "wof:name":"Jan Gui",
    "wof:placetype":"venue"
},
  "geometry": {"coordinates":[4.6533699036,51.085018158],"type":"Point"}
}