{
  "type": "Feature",
  "properties": {
    "addr:full":"Liefjeslaan 2 Koksijde West-Vlaanderen 8670",
    "addr:housenumber":"2",
    "addr:postcode":"8670",
    "addr:street":"Liefjeslaan",
    "iso:country":"BE",
    "sg:address":"Liefjeslaan 2",
    "sg:city":"Koksijde",
    "sg:orig_category":"Boekhouders",
    "sg:phone":"+32 58 51 89 51",
    "sg:postcode":"8670",
    "sg:province":"West-Vlaanderen",
    "wof:name":"Bureau Bruneel Danny",
    "wof:placetype":"venue"
},
  "geometry": {"coordinates":[2.6408970356,51.1142425537],"type":"Point"}
}