{
  "type": "Feature",
  "properties": {
    "iso:country":"BE",
    "sg:address":"Boulevard Adolphe Max 48-50",
    "sg:city":"Bruxelles",
    "sg:classifiers":[
        {
            "category":"Professional",
            "subcategory":"Computer Services",
            "type":"Services"
        }
    ],
    "sg:phone":"+32 2 219 60 47",
    "sg:postcode":"1000",
    "sg:province":"Bruxelles-Capitale",
    "sg:tags":[
        "-",
        "processing",
        "data"
    ],
    "wof:name":"Pc One Sprl",
    "wof:placetype":"venue"
},
  "geometry": {"coordinates":[4.3545851707,50.8529624939],"type":"Point"}
}