{
  "type": "Feature",
  "properties": {
    "addr:full":"Berlaars 2a Maldegem Oost-Vlaanderen 9991",
    "addr:housenumber":"2a",
    "addr:postcode":"9991",
    "addr:street":"Berlaars",
    "iso:country":"BE",
    "sg:address":"Berlaars 2a",
    "sg:city":"Maldegem",
    "sg:classifiers":[
        {
            "category":"Restaurant",
            "type":"Food & Drink"
        }
    ],
    "sg:phone":"+32 9 377 07 42",
    "sg:postcode":"9991",
    "sg:province":"Oost-Vlaanderen",
    "wof:name":"De Koetshoeve",
    "wof:placetype":"venue"
},
  "geometry": {"coordinates":[3.5249860287,51.1828651428],"type":"Point"}
}