{
  "type": "Feature",
  "properties": {
    "addr:full":"Edingensesteenweg 634 Halle Vlaams-Brabant 1502",
    "addr:housenumber":"634;1502",
    "addr:street":"Edingensesteenweg",
    "iso:country":"BE",
    "sg:address":"Edingensesteenweg 634",
    "sg:city":"Halle",
    "sg:orig_category":"Enseignement maternel and primaire",
    "sg:phone":"+32 2 356 97 19",
    "sg:postcode":"1502",
    "sg:province":"Vlaams-Brabant",
    "wof:name":"Vrije Kleuterschool",
    "wof:placetype":"venue"
},
  "geometry": {"coordinates":[4.1994338036,50.720954895],"type":"Point"}
}