{
  "type": "Feature",
  "properties": {
    "iso:country":"BE",
    "sg:address":"Maalderijstraat 1",
    "sg:city":"Diksmuide",
    "sg:orig_category":"Rundveehouders Varkenskwekers",
    "sg:phone":"+32 51 50 11 03",
    "sg:postcode":"8600",
    "sg:province":"West-Vlaanderen",
    "wof:name":"Wim Vanneste",
    "wof:placetype":"venue"
},
  "geometry": {"coordinates":[2.9181001186,51.019569397],"type":"Point"}
}