{
  "type": "Feature",
  "properties": {
    "iso:country":"BE",
    "sg:address":"Avenue G\u00e9n\u00e9ral Cambronne 4",
    "sg:city":"Lasne (plancenoit)",
    "sg:classifiers":[
        {
            "category":"Professional",
            "subcategory":"Accounting & Tax Preparation",
            "type":"Services"
        }
    ],
    "sg:phone":"+32 2 384 36 56",
    "sg:postcode":"1380",
    "sg:province":"Brabant Wallon",
    "sg:tags":[
        "bookkeeper"
    ],
    "wof:name":"Pieyns V",
    "wof:placetype":"venue"
},
  "geometry": {"coordinates":[4.483235836,50.6850166321],"type":"Point"}
}