{
  "type": "Feature",
  "properties": {
    "addr:full":"Holt 10 Bilzen Limburg 3740",
    "addr:housenumber":"10",
    "addr:postcode":"3740",
    "addr:street":"Holt",
    "iso:country":"BE",
    "sg:address":"Holt 10",
    "sg:city":"Bilzen",
    "sg:classifiers":[
        {
            "category":"Shopping",
            "subcategory":"Party Supplies",
            "type":"Retail Goods"
        }
    ],
    "sg:phone":"+32 89 41 11 39",
    "sg:postcode":"3740",
    "sg:province":"Limburg",
    "sg:tags":[
        "hunting"
    ],
    "wof:name":"Appermont Nv",
    "wof:placetype":"venue"
},
  "geometry": {"coordinates":[5.4850311279,50.8844451904],"type":"Point"}
}