{
  "type": "Feature",
  "properties": {
    "iso:country":"BE",
    "sg:address":"Cesar Van Kerckhovenstraat 110",
    "sg:city":"Bornem",
    "sg:classifiers":[
        {
            "category":"Professional",
            "subcategory":"Computer Services",
            "type":"Services"
        }
    ],
    "sg:phone":"+32 3 890 47 30",
    "sg:postcode":"2880",
    "sg:province":"Antwerpen",
    "sg:tags":[
        "-",
        "processing",
        "data",
        "software"
    ],
    "wof:name":"Mobile Innovations",
    "wof:placetype":"venue"
},
  "geometry": {"coordinates":[4.2675909996,51.0953025818],"type":"Point"}
}