{
  "type": "Feature",
  "properties": {
    "iso:country":"BE",
    "sg:address":"Kriktestraat 13",
    "sg:city":"Lokeren",
    "sg:classifiers":[
        {
            "category":"Military Area",
            "subcategory":"Air Force Base",
            "type":"Public Place"
        }
    ],
    "sg:phone":"+32 9 348 54 13",
    "sg:postcode":"9160",
    "sg:province":"Oost-Vlaanderen",
    "sg:tags":[
        "fire",
        "protection"
    ],
    "wof:name":"Fremur Consultancy Bvba",
    "wof:placetype":"venue"
},
  "geometry": {"coordinates":[3.9981799126,51.1256713867],"type":"Point"}
}