{
  "type": "Feature",
  "properties": {
    "addr:full":"Gentsesteenweg 143 Kortrijk West-Vlaanderen 8500",
    "addr:housenumber":"143",
    "addr:postcode":"8500",
    "addr:street":"Gentsesteenweg",
    "iso:country":"BE",
    "sg:address":"Gentsesteenweg 143",
    "sg:city":"Kortrijk",
    "sg:orig_category":"Transports routiers de marchandises",
    "sg:phone":"+32 56 25 99 99",
    "sg:postcode":"8500",
    "sg:province":"West-Vlaanderen",
    "wof:name":"Vatrabel",
    "wof:placetype":"venue"
},
  "geometry": {"coordinates":[3.2842988968,50.8380661011],"type":"Point"}
}