{
  "type": "Feature",
  "properties": {
    "iso:country":"BE",
    "sg:address":"Chauss\u00c9e Des Ballons 118",
    "sg:city":"Moeskroen/mouscron",
    "sg:classifiers":[
        {
            "category":"Insurance",
            "subcategory":"Life Insurance",
            "type":"Services"
        }
    ],
    "sg:phone":"+32 56 33 46 25",
    "sg:postcode":"7700",
    "sg:province":"Hainaut",
    "sg:tags":[
        "assurance"
    ],
    "wof:name":"Rondaert-verfaille",
    "wof:placetype":"venue"
},
  "geometry": {"coordinates":[3.2226970196,50.7203941345],"type":"Point"}
}