{
  "type": "Feature",
  "properties": {
    "addr:full":"Generaal Guffensstraat 62 Tienen Vlaams-Brabant 3300",
    "addr:housenumber":"62",
    "addr:postcode":"3300",
    "addr:street":"Generaal Guffensstraat",
    "iso:country":"BE",
    "sg:address":"Generaal Guffensstraat 62",
    "sg:city":"Tienen",
    "sg:classifiers":[
        {
            "category":"Real Estate",
            "subcategory":"Architect",
            "type":"Services"
        }
    ],
    "sg:phone":"+32 16 81 25 44",
    "sg:postcode":"3300",
    "sg:province":"Vlaams-Brabant",
    "wof:name":"Brik\u00e9 M",
    "wof:placetype":"venue"
},
  "geometry": {"coordinates":[4.9469561577,50.8087692261],"type":"Point"}
}