{
  "type": "Feature",
  "properties": {
    "addr:full":"Burgstrasse 19bc Raeren Li\u00e8ge 4730",
    "addr:housenumber":"19bc",
    "addr:postcode":"4730",
    "addr:street":"Burgstrasse",
    "iso:country":"BE",
    "sg:address":"Burgstrasse 19bc",
    "sg:city":"Raeren",
    "sg:orig_category":"Serres and speciale beglazing",
    "sg:phone":"+32 87 85 15 19",
    "sg:postcode":"4730",
    "sg:province":"Li\u00e8ge",
    "wof:name":"Leo Vonhoff",
    "wof:placetype":"venue"
},
  "geometry": {"coordinates":[6.1117100716,50.6780395508],"type":"Point"}
}