{
  "type": "Feature",
  "properties": {
    "iso:country":"BE",
    "sg:address":"Rue Royale 290",
    "sg:city":"Sint-joost-ten-node/saint-josse-ten-noode",
    "sg:orig_category":"Production de films, t\u00e9l\u00e9films and vid\u00e9os",
    "sg:phone":"+32 2 223 20 20",
    "sg:postcode":"1210",
    "sg:province":"Bruxelles-Capitale",
    "wof:name":"Petits D\u00c9jeuners Cin\u00c9ma",
    "wof:placetype":"venue"
},
  "geometry": {"coordinates":[4.3672370911,50.8565940857],"type":"Point"}
}