{
  "type": "Feature",
  "properties": {
    "addr:full":"Vrouwestraat 7 Eeklo Oost-Vlaanderen 9900",
    "addr:housenumber":"7",
    "addr:postcode":"9900",
    "addr:street":"Vrouwestraat",
    "iso:country":"BE",
    "sg:address":"Vrouwestraat 7",
    "sg:city":"Eeklo",
    "sg:orig_category":"Rundveehouders Varkenskwekers",
    "sg:phone":"+32 9 377 36 72",
    "sg:postcode":"9900",
    "sg:province":"Oost-Vlaanderen",
    "wof:name":"Gaston Bommele",
    "wof:placetype":"venue"
},
  "geometry": {"coordinates":[3.5384199619,51.2032928467],"type":"Point"}
}