{
  "type": "Feature",
  "properties": {
    "addr:full":"Rue Charles Dubois 63 Ottignies-louvain-la-neuve (limelette) Brabant Wallon 1342",
    "addr:housenumber":"63",
    "addr:postcode":"1342",
    "addr:street":"Rue Charles Dubois",
    "iso:country":"BE",
    "sg:address":"Rue Charles Dubois 63",
    "sg:city":"Ottignies-louvain-la-neuve (limelette)",
    "sg:classifiers":[
        {
            "category":"Professional",
            "subcategory":"Engineering",
            "type":"Services"
        }
    ],
    "sg:phone":"+32 10 41 42 94",
    "sg:postcode":"1342",
    "sg:province":"Brabant Wallon",
    "sg:tags":[
        "civil",
        "offices-"
    ],
    "wof:name":"Buxico Sprl",
    "wof:placetype":"venue"
},
  "geometry": {"coordinates":[4.5841121674,50.684753418],"type":"Point"}
}