{
  "type": "Feature",
  "properties": {
    "iso:country":"BE",
    "sg:address":"Akker 2",
    "sg:city":"Zaventem (nossegem)",
    "sg:classifiers":[
        {
            "category":"Health Services",
            "subcategory":"Health Practitioner",
            "type":"Services"
        }
    ],
    "sg:phone":"+32 2 757 91 91",
    "sg:postcode":"1930",
    "sg:province":"Vlaams-Brabant",
    "sg:tags":[
        "physiotherapist"
    ],
    "wof:name":"Breucq A",
    "wof:placetype":"venue"
},
  "geometry": {"coordinates":[4.510556221,50.8807754517],"type":"Point"}
}