{
  "type": "Feature",
  "properties": {
    "iso:country":"BE",
    "sg:address":"Chauss\u00e9e De Bruxelles 417a",
    "sg:city":"Charleroi (jumet)",
    "sg:classifiers":[
        {
            "category":"Retail",
            "subcategory":"Auto Repair",
            "type":"Services"
        }
    ],
    "sg:phone":"+32 71 35 75 70",
    "sg:postcode":"6040",
    "sg:province":"Hainaut",
    "sg:tags":[
        "garage"
    ],
    "wof:name":"Lagaune Sprl",
    "wof:placetype":"venue"
},
  "geometry": {"coordinates":[4.4333381653,50.4512214661],"type":"Point"}
}