{
  "type": "Feature",
  "properties": {
    "addr:full":"Pieter Breughelstraat 25 Kortrijk West-Vlaanderen 8510",
    "addr:housenumber":"25",
    "addr:postcode":"8510",
    "addr:street":"Pieter Breughelstraat",
    "iso:country":"BE",
    "sg:address":"Pieter Breughelstraat 25",
    "sg:city":"Kortrijk",
    "sg:orig_category":"Avocats and conseillers juridiques",
    "sg:phone":"+32 56 25 60 60",
    "sg:postcode":"8510",
    "sg:province":"West-Vlaanderen",
    "wof:name":"S. Tetaert",
    "wof:placetype":"venue"
},
  "geometry": {"coordinates":[3.2333650589,50.8071060181],"type":"Point"}
}