{
  "type": "Feature",
  "properties": {
    "addr:full":"Hoogstraat 60 Kasterlee Antwerpen 2460",
    "addr:housenumber":"60",
    "addr:postcode":"2460",
    "addr:street":"Hoogstraat",
    "iso:country":"BE",
    "sg:address":"Hoogstraat 60",
    "sg:city":"Kasterlee",
    "sg:orig_category":"Kapsalons",
    "sg:phone":"+32 14 55 45 65",
    "sg:postcode":"2460",
    "sg:province":"Antwerpen",
    "wof:name":"Coiffure Els",
    "wof:placetype":"venue"
},
  "geometry": {"coordinates":[4.9671049118,51.2406616211],"type":"Point"}
}