{
  "type": "Feature",
  "properties": {
    "addr:full":"Torenstraat 25 Meeuwen-gruitrode (meeuwen) Limburg 3670",
    "addr:housenumber":"25",
    "addr:postcode":"3670",
    "addr:street":"Torenstraat",
    "iso:country":"BE",
    "sg:address":"Torenstraat 25",
    "sg:city":"Meeuwen-gruitrode (meeuwen)",
    "sg:classifiers":[
        {
            "category":"Building & Trades",
            "subcategory":"Landscaping Services",
            "type":"Services"
        }
    ],
    "sg:phone":"+32 11 79 25 35",
    "sg:postcode":"3670",
    "sg:province":"Limburg",
    "sg:tags":[
        "architect",
        "landscape"
    ],
    "wof:name":"Bonhomme M",
    "wof:placetype":"venue"
},
  "geometry": {"coordinates":[5.5235090256,51.0982818604],"type":"Point"}
}