{
  "type": "Feature",
  "properties": {
    "addr:full":"Sint-anna 69 Kortrijk West-Vlaanderen 8510",
    "addr:housenumber":"69",
    "addr:postcode":"8510",
    "addr:street":"Sint-Anna",
    "iso:country":"BE",
    "sg:address":"Sint-anna 69",
    "sg:city":"Kortrijk",
    "sg:orig_category":"Parfumeries",
    "sg:phone":"+32 56 20 47 06",
    "sg:postcode":"8510",
    "sg:province":"West-Vlaanderen",
    "wof:name":"Catherine Malfait",
    "wof:placetype":"venue"
},
  "geometry": {"coordinates":[3.2485098839,50.7860603333],"type":"Point"}
}