{
  "type": "Feature",
  "properties": {
    "iso:country":"BE",
    "sg:address":"Hoogkamerstraat 22",
    "sg:city":"Sint-niklaas",
    "sg:orig_category":"Produits laitiers and huiles comestibles Gr",
    "sg:phone":"+32 3 766 17 99",
    "sg:postcode":"9100",
    "sg:province":"Oost-Vlaanderen",
    "wof:name":"De Wilde Eieren",
    "wof:placetype":"venue"
},
  "geometry": {"coordinates":[4.1820487976,51.1446762085],"type":"Point"}
}