{
  "type": "Feature",
  "properties": {
    "addr:full":"Antwerpseweg 18 Geel Antwerpen 2440",
    "addr:housenumber":"18",
    "addr:postcode":"2440",
    "addr:street":"Antwerpseweg",
    "iso:country":"BE",
    "sg:address":"Antwerpseweg 18",
    "sg:city":"Geel",
    "sg:orig_category":"Bloemen and planten",
    "sg:phone":"+32 14 58 41 24",
    "sg:postcode":"2440",
    "sg:province":"Antwerpen",
    "wof:name":"\u00b4t Roosje",
    "wof:placetype":"venue"
},
  "geometry": {"coordinates":[4.9719290733,51.1513900757],"type":"Point"}
}