{
  "type": "Feature",
  "properties": {
    "addr:full":"Rue Xhav\u00e9e 9 Verviers Li\u00e8ge 4800",
    "addr:housenumber":"9",
    "addr:postcode":"4800",
    "addr:street":"Rue Xhave\u0301E",
    "iso:country":"BE",
    "sg:address":"Rue Xhav\u00e9e 9",
    "sg:city":"Verviers",
    "sg:classifiers":[
        {
            "category":"Shopping",
            "subcategory":"Clothing, Apparel, & Fashions",
            "type":"Retail Goods"
        }
    ],
    "sg:phone":"+32 87 33 92 19",
    "sg:postcode":"4800",
    "sg:province":"Li\u00e8ge",
    "sg:tags":[
        "purchase",
        "clothing",
        "-",
        "sale",
        "second-hand"
    ],
    "wof:name":"Parall\u00e8les",
    "wof:placetype":"venue"
},
  "geometry": {"coordinates":[5.8599262238,50.5918045044],"type":"Point"}
}