{
  "type": "Feature",
  "properties": {
    "addr:full":"Boogstraat 6 Retie Antwerpen 2470",
    "addr:housenumber":"6",
    "addr:postcode":"2470",
    "addr:street":"Boogstraat",
    "iso:country":"BE",
    "sg:address":"Boogstraat 6",
    "sg:city":"Retie",
    "sg:orig_category":"Installation de menuiserie en bois and plastique",
    "sg:phone":"+32 14 37 86 15",
    "sg:postcode":"2470",
    "sg:province":"Antwerpen",
    "wof:name":"Gustaaf Daems",
    "wof:placetype":"venue"
},
  "geometry": {"coordinates":[5.0605978966,51.2717895508],"type":"Point"}
}