{
  "type": "Feature",
  "properties": {
    "addr:full":"Rue Du Sacr\u00c9 Coeur 3 Welkenraedt/welkenraedt Li\u00e8ge 4841",
    "addr:housenumber":"3",
    "addr:postcode":"4841",
    "addr:street":"Rue Du Sacre\u0301 Coeur",
    "iso:country":"BE",
    "sg:address":"Rue Du Sacr\u00c9 Coeur 3",
    "sg:city":"Welkenraedt/welkenraedt",
    "sg:orig_category":"Fabrication and montage de mobilier",
    "sg:phone":"+32 87 44 84 57",
    "sg:postcode":"4841",
    "sg:province":"Li\u00e8ge",
    "wof:name":"Tracomi Construction",
    "wof:placetype":"venue"
},
  "geometry": {"coordinates":[5.896625042,50.6417160034],"type":"Point"}
}