{
  "type": "Feature",
  "properties": {
    "iso:country":"BE",
    "sg:address":"Verbroederingstraat 9",
    "sg:city":"Gent (gentbrugge)",
    "sg:classifiers":[
        {
            "category":"Autos & Motor Vehicles",
            "subcategory":"Automobile Sales",
            "type":"Retail Goods"
        }
    ],
    "sg:phone":"+32 9 230 58 37",
    "sg:postcode":"9050",
    "sg:province":"Oost-Vlaanderen",
    "sg:tags":[
        "distributor",
        "independent",
        "-"
    ],
    "wof:name":"De Wilde W Bvba",
    "wof:placetype":"venue"
},
  "geometry": {"coordinates":[3.752603054,51.0424613953],"type":"Point"}
}