{
  "type": "Feature",
  "properties": {
    "addr:full":"Bergensesteenweg 199 Sint-pieters-leeuw Vlaams-Brabant 1600",
    "addr:housenumber":"199",
    "addr:postcode":"1600",
    "addr:street":"Bergensesteenweg",
    "iso:country":"BE",
    "sg:address":"Bergensesteenweg 199",
    "sg:city":"Sint-pieters-leeuw",
    "sg:orig_category":"Sportcentra Sportclubs",
    "sg:phone":"+32 2 331 29 99",
    "sg:postcode":"1600",
    "sg:province":"Vlaams-Brabant",
    "wof:name":"Acad\u00c9mie Belge Arts Martiaux",
    "wof:placetype":"venue"
},
  "geometry": {"coordinates":[4.286441803,50.7971687317],"type":"Point"}
}