{
  "type": "Feature",
  "properties": {
    "iso:country":"BE",
    "sg:address":"P. De Smet De Naeyerpln 9",
    "sg:city":"Gent",
    "sg:orig_category":"Artsen and specialisten",
    "sg:phone":"+32 9 221 12 05",
    "sg:postcode":"9000",
    "sg:province":"Oost-Vlaanderen",
    "wof:name":"Guy Heyndrickx",
    "wof:placetype":"venue"
},
  "geometry": {"coordinates":[3.7176089287,51.0323791504],"type":"Point"}
}