{
  "type": "Feature",
  "properties": {
    "addr:full":"Kraenepoelpad 28 Aalter Oost-Vlaanderen 9880",
    "addr:housenumber":"28",
    "addr:postcode":"9880",
    "addr:street":"Kraenepoelpad",
    "iso:country":"BE",
    "sg:address":"Kraenepoelpad 28",
    "sg:city":"Aalter",
    "sg:classifiers":[
        {
            "category":"Professional",
            "subcategory":"Engineering",
            "type":"Services"
        }
    ],
    "sg:phone":"+32 9 375 19 40",
    "sg:postcode":"9880",
    "sg:province":"Oost-Vlaanderen",
    "sg:tags":[
        "industrial",
        "-",
        "automation"
    ],
    "wof:name":"Technocon Bvba",
    "wof:placetype":"venue"
},
  "geometry": {"coordinates":[3.473170042,51.075050354],"type":"Point"}
}