{
  "type": "Feature",
  "properties": {
    "iso:country":"BE",
    "sg:address":"Rue Des Battis 34",
    "sg:city":"Chimay",
    "sg:orig_category":"Caf\u00e9s Sportcentra Sportclubs Sportterreinen and installaties behalve sportcentra Zalen voor culturel",
    "sg:phone":"+32 60 21 22 10",
    "sg:postcode":"6464",
    "sg:province":"Hainaut",
    "wof:name":"Centre Culturel & Sportif",
    "wof:placetype":"venue"
},
  "geometry": {"coordinates":[4.3713622093,50.0306396484],"type":"Point"}
}