{
  "type": "Feature",
  "properties": {
    "iso:country":"BE",
    "sg:address":"Halleweg 381",
    "sg:city":"Halle",
    "sg:classifiers":[
        {
            "category":"Home & Garden",
            "subcategory":"Garden Supply",
            "type":"Retail Goods"
        }
    ],
    "sg:phone":"+32 2 356 76 28",
    "sg:postcode":"1500",
    "sg:province":"Vlaams-Brabant",
    "wof:name":"Vanstalle Rene",
    "wof:placetype":"venue"
},
  "geometry": {"coordinates":[4.254049778,50.7235794067],"type":"Point"}
}