{
  "type": "Feature",
  "properties": {
    "addr:full":"Vuurkruisenlaan 23 Zaventem Vlaams-Brabant 1930",
    "addr:housenumber":"23",
    "addr:postcode":"1930",
    "addr:street":"Vuurkruisenlaan",
    "iso:country":"BE",
    "sg:address":"Vuurkruisenlaan 23",
    "sg:city":"Zaventem",
    "sg:orig_category":"Installation \u00e9lectrique industrielle",
    "sg:phone":"+32 2 720 09 83",
    "sg:postcode":"1930",
    "sg:province":"Vlaams-Brabant",
    "wof:name":"Mosbeux Jacques Electricite",
    "wof:placetype":"venue"
},
  "geometry": {"coordinates":[4.478746891,50.8739624023],"type":"Point"}
}