{
  "type": "Feature",
  "properties": {
    "iso:country":"BE",
    "sg:address":"Ramskapellestraat 40",
    "sg:city":"Knokke-heist (ramskapelle)",
    "sg:classifiers":[
        {
            "category":"Home & Garden",
            "subcategory":"Household Appliances",
            "type":"Retail Goods"
        }
    ],
    "sg:phone":"+32 50 51 35 95",
    "sg:postcode":"8301",
    "sg:province":"West-Vlaanderen",
    "sg:tags":[
        "repair",
        "mainten",
        "-",
        "electric"
    ],
    "wof:name":"Demeyer J",
    "wof:placetype":"venue"
},
  "geometry": {"coordinates":[3.2497329712,51.3150138855],"type":"Point"}
}