{
  "type": "Feature",
  "properties": {
    "iso:country":"BE",
    "sg:address":"Oude Vijvers 1",
    "sg:city":"Boutersem",
    "sg:classifiers":[
        {
            "category":"Military Area",
            "subcategory":"Air Force Base",
            "type":"Public Place"
        }
    ],
    "sg:phone":"+32 16 73 55 72",
    "sg:postcode":"3370",
    "sg:province":"Vlaams-Brabant",
    "sg:tags":[
        "water",
        "treatment"
    ],
    "wof:name":"Imlab Bvba",
    "wof:placetype":"venue"
},
  "geometry": {"coordinates":[4.8442339897,50.8449897766],"type":"Point"}
}