{
  "type": "Feature",
  "properties": {
    "iso:country":"BE",
    "sg:address":"Lindenboomstraat 19",
    "sg:city":"Borsbeek",
    "sg:orig_category":"Herstelling and restauratie van meubelen",
    "sg:phone":"+32 3 322 41 86",
    "sg:postcode":"2150",
    "sg:province":"Antwerpen",
    "wof:name":"Jan Engels Restauraties",
    "wof:placetype":"venue"
},
  "geometry": {"coordinates":[4.4821610451,51.1955413818],"type":"Point"}
}