{
  "type": "Feature",
  "properties": {
    "addr:full":"Bieststraat 5 Aalst Oost-Vlaanderen 9308",
    "addr:housenumber":"5",
    "addr:postcode":"9308",
    "addr:street":"Bieststraat",
    "iso:country":"BE",
    "sg:address":"Bieststraat 5",
    "sg:city":"Aalst",
    "sg:orig_category":"Air conditionn\u00e9 and ventilation. Electrom\u00e9nager, t\u00e9l\u00e9visions and radios Equipement divers pour comme",
    "sg:phone":"+32 53 70 19 59",
    "sg:postcode":"9308",
    "sg:province":"Oost-Vlaanderen",
    "wof:name":"Philippe Sonck",
    "wof:placetype":"venue"
},
  "geometry": {"coordinates":[4.0347590446,50.9603500366],"type":"Point"}
}