{
  "type": "Feature",
  "properties": {
    "addr:full":"Route De Fouron 6 Dalhem Li\u00e8ge 4607",
    "addr:housenumber":"6",
    "addr:postcode":"4607",
    "addr:street":"Route De Fouron",
    "iso:country":"BE",
    "sg:address":"Route De Fouron 6",
    "sg:city":"Dalhem",
    "sg:orig_category":"Houtbewerking and -behandeling",
    "sg:phone":"+32 4 379 16 86",
    "sg:postcode":"4607",
    "sg:province":"Li\u00e8ge",
    "wof:name":"Francois Bebelmans",
    "wof:placetype":"venue"
},
  "geometry": {"coordinates":[5.7329411507,50.7430725098],"type":"Point"}
}