{
  "type": "Feature",
  "properties": {
    "iso:country":"BE",
    "sg:address":"Goede Herderstraat 54",
    "sg:city":"Sint-jans-molenbeek/molenbeek-",
    "sg:orig_category":"Zuivelproducten and spijsolie Gh",
    "sg:phone":"+32 2 465 26 03",
    "sg:postcode":"1080",
    "sg:province":"Bruxelles-Capitale",
    "wof:name":"Decaestecker A",
    "wof:placetype":"venue"
},
  "geometry": {"coordinates":[4.298623085,50.8562545776],"type":"Point"}
}