{
  "type": "Feature",
  "properties": {
    "addr:full":"Groenstraat 2 Gooik Vlaams-Brabant 1755",
    "addr:housenumber":"2",
    "addr:postcode":"1755",
    "addr:street":"Groenstraat",
    "iso:country":"BE",
    "sg:address":"Groenstraat 2",
    "sg:city":"Gooik",
    "sg:orig_category":"Sportclubs",
    "sg:phone":"+32 54 56 69 00",
    "sg:postcode":"1755",
    "sg:province":"Vlaams-Brabant",
    "wof:name":"De Warande",
    "wof:placetype":"venue"
},
  "geometry": {"coordinates":[4.0801739693,50.7918014526],"type":"Point"}
}