{
  "type": "Feature",
  "properties": {
    "iso:country":"BE",
    "sg:address":"De Burburestraat 11",
    "sg:city":"Antwerpen",
    "sg:classifiers":[
        {
            "category":"Real Estate",
            "subcategory":"Surveying",
            "type":"Services"
        }
    ],
    "sg:phone":"+32 3 238 44 40",
    "sg:postcode":"2000",
    "sg:province":"Antwerpen",
    "sg:tags":[
        "lettering",
        "letter"
    ],
    "wof:name":"Beerts Lettershop",
    "wof:placetype":"venue"
},
  "geometry": {"coordinates":[4.3920669556,51.2091407776],"type":"Point"}
}