{
  "type": "Feature",
  "properties": {
    "iso:country":"BE",
    "sg:address":"Poederllesteenweg 114",
    "sg:city":"Kasterlee",
    "sg:orig_category":"Imprimeries and copyshops. Articles textiles and tissus de d\u00e9coration Fab. Textiles divers Fab. Arti",
    "sg:phone":"+32 14 55 69 22",
    "sg:postcode":"2460",
    "sg:province":"Antwerpen",
    "wof:name":"Herva",
    "wof:placetype":"venue"
},
  "geometry": {"coordinates":[4.9671049118,51.2406616211],"type":"Point"}
}