{
  "type": "Feature",
  "properties": {
    "iso:country":"BE",
    "sg:address":"Jozef Vervaenestraat 147",
    "sg:city":"Gent (ledeberg)",
    "sg:classifiers":[
        {
            "category":"Health Services",
            "subcategory":"Health Practitioner",
            "type":"Services"
        }
    ],
    "sg:phone":"+32 9 329 83 32",
    "sg:postcode":"9050",
    "sg:province":"Oost-Vlaanderen",
    "sg:tags":[
        "alternative",
        "therapy",
        "treatment"
    ],
    "wof:name":"Pyramids Of Truth (the)",
    "wof:placetype":"venue"
},
  "geometry": {"coordinates":[3.750125885,51.0303344727],"type":"Point"}
}