{
  "type": "Feature",
  "properties": {
    "addr:full":"Rue Du Coriat 43 Floreffe Namur 5150",
    "addr:housenumber":"43",
    "addr:postcode":"5150",
    "addr:street":"Rue Du Coriat",
    "iso:country":"BE",
    "sg:address":"Rue Du Coriat 43",
    "sg:city":"Floreffe",
    "sg:orig_category":"Boekhouders",
    "sg:phone":"+32 81 74 28 64",
    "sg:postcode":"5150",
    "sg:province":"Namur",
    "wof:name":"Liliane L\u00c9on",
    "wof:placetype":"venue"
},
  "geometry": {"coordinates":[4.7633361816,50.4349517822],"type":"Point"}
}