{
  "type": "Feature",
  "properties": {
    "addr:full":"Moortselestraat 23 Oosterzele Oost-Vlaanderen 9860",
    "addr:housenumber":"23",
    "addr:postcode":"9860",
    "addr:street":"Moortselestraat;Oost-Vlaanderen",
    "iso:country":"BE",
    "sg:address":"Moortselestraat 23",
    "sg:city":"Oosterzele",
    "sg:orig_category":"Woningbouw",
    "sg:phone":"+32 9 362 69 63",
    "sg:postcode":"9860",
    "sg:province":"Oost-Vlaanderen",
    "wof:name":"Marc De Geyter",
    "wof:placetype":"venue"
},
  "geometry": {"coordinates":[3.7796120644,50.9552764893],"type":"Point"}
}