{
  "type": "Feature",
  "properties": {
    "addr:full":"Avenue J. Swartenbrouck 3 Jette/jette Bruxelles-Capitale 1090",
    "addr:housenumber":"3",
    "addr:postcode":"1090",
    "addr:street":"Avenue J. Swartenbrouck",
    "iso:country":"BE",
    "sg:address":"Avenue J. Swartenbrouck 3",
    "sg:city":"Jette/jette",
    "sg:classifiers":[
        {
            "category":"Shopping Center",
            "type":"Public Place"
        }
    ],
    "sg:phone":"+32 2 479 92 75",
    "sg:postcode":"1090",
    "sg:province":"Bruxelles-Capitale",
    "sg:tags":[
        "enseignement",
        "formation"
    ],
    "wof:name":"Humania",
    "wof:placetype":"venue"
},
  "geometry": {"coordinates":[4.3189268112,50.889957428],"type":"Point"}
}