{
  "type": "Feature",
  "properties": {
    "addr:full":"Rue Du Plan Inclin\u00c9 87 Li\u00c8ge Li\u00e8ge 4000",
    "addr:housenumber":"87",
    "addr:postcode":"4000",
    "addr:street":"Rue Du Plan Incline\u0301",
    "iso:country":"BE",
    "sg:address":"Rue Du Plan Inclin\u00c9 87",
    "sg:city":"Li\u00c8ge",
    "sg:orig_category":"Zalen voor culturele evenementen",
    "sg:phone":"+32 4 254 05 54",
    "sg:postcode":"4000",
    "sg:province":"Li\u00e8ge",
    "wof:name":"Th\u00c9\u00c2tre Comiq'art",
    "wof:placetype":"venue"
},
  "geometry": {"coordinates":[5.5648598671,50.6278343201],"type":"Point"}
}