{
  "type": "Feature",
  "properties": {
    "iso:country":"BE",
    "sg:address":"Esenweg",
    "sg:city":"Diksmuide",
    "sg:classifiers":[
        {
            "category":"Fast Food",
            "type":"Food & Drink"
        }
    ],
    "sg:phone":"+32 51 50 34 32",
    "sg:postcode":"8600",
    "sg:province":"West-Vlaanderen",
    "sg:tags":[
        "fried",
        "stand",
        "potato"
    ],
    "wof:name":"Tyrol-imant",
    "wof:placetype":"venue"
},
  "geometry": {"coordinates":[2.882324934,51.0306167603],"type":"Point"}
}