{
  "type": "Feature",
  "properties": {
    "addr:full":"Duinkerkelaan 60 Box 1 De Panne West-Vlaanderen 8660",
    "addr:housenumber":"60",
    "addr:postcode":"8660",
    "addr:street":"Duinkerkelaan;Box 1",
    "iso:country":"BE",
    "sg:address":"Duinkerkelaan 60 Box 1",
    "sg:city":"De Panne",
    "sg:classifiers":[
        {
            "category":"Shopping",
            "subcategory":"Jewelry",
            "type":"Retail Goods"
        }
    ],
    "sg:phone":"+32 58 42 13 33",
    "sg:postcode":"8660",
    "sg:province":"West-Vlaanderen",
    "sg:tags":[
        "jeweller",
        "-"
    ],
    "wof:name":"Bonj\u00e9 G",
    "wof:placetype":"venue"
},
  "geometry": {"coordinates":[2.5871989727,51.1015739441],"type":"Point"}
}