{
  "type": "Feature",
  "properties": {
    "iso:country":"BE",
    "sg:address":"Rue Des Archers 4",
    "sg:city":"Mons",
    "sg:classifiers":[
        {
            "category":"Insurance",
            "subcategory":"Life Insurance",
            "type":"Services"
        }
    ],
    "sg:phone":"+32 65 31 73 38",
    "sg:postcode":"7000",
    "sg:province":"Hainaut",
    "sg:tags":[
        "assurance"
    ],
    "wof:name":"Grimard Et Compagnie",
    "wof:placetype":"venue"
},
  "geometry": {"coordinates":[3.9577760696,50.4524497986],"type":"Point"}
}