{
  "type": "Feature",
  "properties": {
    "addr:full":"Rekkemstraat 139 Menen West-Vlaanderen 8930",
    "addr:housenumber":"139",
    "addr:postcode":"8930",
    "addr:street":"Rekkemstraat",
    "iso:country":"BE",
    "sg:address":"Rekkemstraat 139",
    "sg:city":"Menen",
    "sg:classifiers":[
        {
            "category":"Food & Beverages",
            "subcategory":"Fruits & Vegetables",
            "type":"Retail Goods"
        }
    ],
    "sg:phone":"+32 56 40 31 52",
    "sg:postcode":"8930",
    "sg:province":"West-Vlaanderen",
    "sg:tags":[
        "l\u00e9gumes"
    ],
    "wof:name":"Annie Deplae",
    "wof:placetype":"venue"
},
  "geometry": {"coordinates":[3.1209149361,50.7961845398],"type":"Point"}
}