{
  "type": "Feature",
  "properties": {
    "addr:full":"Avenue Des Celtes 22 Etterbeek/etterbeek Bruxelles-Capitale 1040",
    "addr:housenumber":"22",
    "addr:postcode":"1040",
    "addr:street":"Avenue Des Celtes",
    "iso:country":"BE",
    "sg:address":"Avenue Des Celtes 22",
    "sg:city":"Etterbeek/etterbeek",
    "sg:orig_category":"Antiquit\u00e9s",
    "sg:phone":"+32 2 732 48 65",
    "sg:postcode":"1040",
    "sg:province":"Bruxelles-Capitale",
    "wof:name":"Libermann Antiques",
    "wof:placetype":"venue"
},
  "geometry": {"coordinates":[4.3980579376,50.8384742737],"type":"Point"}
}