{
  "type": "Feature",
  "properties": {
    "addr:full":"Chauss\u00c9e De Heusy 60 Verviers Li\u00e8ge 4800",
    "addr:housenumber":"60",
    "addr:postcode":"4800",
    "addr:street":"Chausse\u0301E De Heusy",
    "iso:country":"BE",
    "sg:address":"Chauss\u00c9e De Heusy 60",
    "sg:city":"Verviers",
    "sg:orig_category":"Enseignement maternel and primaire",
    "sg:phone":"+32 87 22 67 92",
    "sg:postcode":"4800",
    "sg:province":"Li\u00e8ge",
    "wof:name":"E.f.l. St.joseph",
    "wof:placetype":"venue"
},
  "geometry": {"coordinates":[5.8660812378,50.5900688171],"type":"Point"}
}