{
  "type": "Feature",
  "properties": {
    "addr:full":"Nieuwstraat 21 Wellen Limburg 3832",
    "addr:housenumber":"21",
    "addr:postcode":"3832",
    "addr:street":"Nieuwstraat",
    "iso:country":"BE",
    "sg:address":"Nieuwstraat 21",
    "sg:city":"Wellen",
    "sg:orig_category":"Production de films, t\u00e9l\u00e9films and vid\u00e9os",
    "sg:phone":"+32 12 74 39 13",
    "sg:postcode":"3832",
    "sg:province":"Limburg",
    "wof:name":"Free Lance Camera",
    "wof:placetype":"venue"
},
  "geometry": {"coordinates":[5.2887091637,50.8399391174],"type":"Point"}
}