{
  "type": "Feature",
  "properties": {
    "addr:full":"Rue Du Bois Mastrade 13 Lasne (couture-saint-germain) Brabant Wallon 1380",
    "addr:housenumber":"13",
    "addr:postcode":"1380",
    "addr:street":"Rue Du Bois Mastrade;Wallon",
    "iso:country":"BE",
    "sg:address":"Rue Du Bois Mastrade 13",
    "sg:city":"Lasne (couture-saint-germain)",
    "sg:classifiers":[
        {
            "category":"Health Services",
            "subcategory":"Doctor",
            "type":"Services"
        }
    ],
    "sg:phone":"+32 2 633 48 15",
    "sg:postcode":"1380",
    "sg:province":"Brabant Wallon",
    "sg:tags":[
        "medicinephysicians",
        "surgeon"
    ],
    "wof:name":"Di Paolantonio G",
    "wof:placetype":"venue"
},
  "geometry": {"coordinates":[4.4900488853,50.6572875977],"type":"Point"}
}