{
  "type": "Feature",
  "properties": {
    "addr:full":"Jozef Cardijnstraat 7 Pittem West-Vlaanderen 8740",
    "addr:housenumber":"7",
    "addr:postcode":"8740",
    "addr:street":"Jozef Cardijnstraat",
    "iso:country":"BE",
    "sg:address":"Jozef Cardijnstraat 7",
    "sg:city":"Pittem",
    "sg:orig_category":"Peinture. Rev\u00eatements pour sols and murs",
    "sg:phone":"+32 51 46 56 13",
    "sg:postcode":"8740",
    "sg:province":"West-Vlaanderen",
    "wof:name":"Guy Brusseel",
    "wof:placetype":"venue"
},
  "geometry": {"coordinates":[3.2564361095,50.995300293],"type":"Point"}
}