{
  "type": "Feature",
  "properties": {
    "addr:full":"Route De Wallonie 1 Ghlin Hainaut 7011",
    "addr:housenumber":"1",
    "addr:postcode":"7011",
    "addr:street":"Route De Wallonie",
    "iso:country":"BE",
    "sg:address":"Route De Wallonie 1",
    "sg:city":"Ghlin",
    "sg:classifiers":[
        {
            "category":"Professional",
            "subcategory":"Employment Agencies",
            "type":"Services"
        }
    ],
    "sg:phone":"+32 65 37 72 11",
    "sg:postcode":"7011",
    "sg:province":"Hainaut",
    "sg:tags":[
        "profile",
        "vehicular",
        "use",
        "aluminium"
    ],
    "wof:name":"Rc Aleurope S.a.",
    "wof:placetype":"venue"
},
  "geometry": {"coordinates":[3.8753650188,50.4779243469],"type":"Point"}
}