{
  "type": "Feature",
  "properties": {
    "iso:country":"BE",
    "sg:address":"Tongersesteenweg 124b",
    "sg:city":"Borgloon",
    "sg:orig_category":"Motorfietsen Voertuigen",
    "sg:phone":"+32 12 74 14 17",
    "sg:postcode":"3840",
    "sg:province":"Limburg",
    "wof:name":"Gerard Vrijdaghs",
    "wof:placetype":"venue"
},
  "geometry": {"coordinates":[5.3611898422,50.798210144],"type":"Point"}
}