{
  "type": "Feature",
  "properties": {
    "iso:country":"BE",
    "sg:address":"Graaf Witgerstraat 20",
    "sg:city":"Mortsel",
    "sg:classifiers":[
        {
            "category":"Professional",
            "subcategory":"Accounting & Tax Preparation",
            "type":"Services"
        }
    ],
    "sg:phone":"+32 3 449 04 92",
    "sg:postcode":"2640",
    "sg:province":"Antwerpen",
    "sg:tags":[
        "bookkeeper"
    ],
    "wof:name":"Ykx Cvba",
    "wof:placetype":"venue"
},
  "geometry": {"coordinates":[4.4545488358,51.1790008545],"type":"Point"}
}