{
  "type": "Feature",
  "properties": {
    "addr:full":"Courte Rue Des Fontaines 66 Wavre Brabant Wallon 1300",
    "addr:housenumber":"66;1300",
    "addr:street":"Rue Des Fontaines",
    "iso:country":"BE",
    "sg:address":"Courte Rue Des Fontaines 66",
    "sg:city":"Wavre",
    "sg:classifiers":[
        {
            "category":"Arts & Performance",
            "subcategory":"Dance",
            "type":"Entertainment"
        }
    ],
    "sg:phone":"+32 10 22 35 92",
    "sg:postcode":"1300",
    "sg:province":"Brabant Wallon",
    "sg:tags":[
        "supply"
    ],
    "wof:name":"Olympe",
    "wof:placetype":"venue"
},
  "geometry": {"coordinates":[4.6098737717,50.7150878906],"type":"Point"}
}