{
  "type": "Feature",
  "properties": {
    "iso:country":"BE",
    "sg:address":"Rue D\u00b4acoz 2b",
    "sg:city":"Nalinnes",
    "sg:orig_category":"Bloemen and planten Fleurop Interflora",
    "sg:phone":"+32 71 21 73 91",
    "sg:postcode":"6120",
    "sg:province":"Hainaut",
    "wof:name":"Le Petit Coquelicot",
    "wof:placetype":"venue"
},
  "geometry": {"coordinates":[4.4724979401,50.3430404663],"type":"Point"}
}