{
  "type": "Feature",
  "properties": {
    "iso:country":"BE",
    "sg:address":"Boulevard G\u00c9n\u00c9ral Jacques 231",
    "sg:city":"Elsene/ixelles",
    "sg:orig_category":"Agences immobili\u00e8res",
    "sg:phone":"+32 2 644 68 01",
    "sg:postcode":"1050",
    "sg:province":"Bruxelles-Capitale",
    "wof:name":"D. De Duve",
    "wof:placetype":"venue"
},
  "geometry": {"coordinates":[4.3877701759,50.8213806152],"type":"Point"}
}