{
  "type": "Feature",
  "properties": {
    "addr:full":"Groeneweg 151 Leuven Vlaams-Brabant 3001",
    "addr:housenumber":"151",
    "addr:postcode":"3001",
    "addr:street":"Groeneweg",
    "iso:country":"BE",
    "sg:address":"Groeneweg 151",
    "sg:city":"Leuven",
    "sg:orig_category":"Hoger onderwijs Volwassenenonderwijs",
    "sg:phone":"+32 16 23 45 41",
    "sg:postcode":"3001",
    "sg:province":"Vlaams-Brabant",
    "wof:name":"K.h.l.-dep.sociale School",
    "wof:placetype":"venue"
},
  "geometry": {"coordinates":[4.6622610092,50.8771781921],"type":"Point"}
}