{
  "type": "Feature",
  "properties": {
    "iso:country":"BE",
    "sg:address":"Brechtsebaan 459b",
    "sg:city":"Schoten",
    "sg:orig_category":"Location de v\u00e9hicules sauf voitures. Stations-service and carburants. V\u00e9hicules automobiles. Entreti",
    "sg:phone":"+32 3 651 78 41",
    "sg:postcode":"2900",
    "sg:province":"Antwerpen",
    "wof:name":"Carrosserie Vanderheyden",
    "wof:placetype":"venue"
},
  "geometry": {"coordinates":[4.5279550552,51.2804412842],"type":"Point"}
}