{
  "type": "Feature",
  "properties": {
    "iso:country":"BE",
    "sg:address":"Avenue De L'emeraude 34bc",
    "sg:city":"Sint-genesius-rode/rhode-saint-genese",
    "sg:orig_category":"Entreprises de travail adapt\u00e9",
    "sg:phone":"+32 2 380 82 77",
    "sg:postcode":"1640",
    "sg:province":"Vlaams-Brabant",
    "wof:name":"Rodea",
    "wof:placetype":"venue"
},
  "geometry": {"coordinates":[4.3324561119,50.737159729],"type":"Point"}
}