{
  "type": "Feature",
  "properties": {
    "addr:full":"Aarschotsesteenweg 517 Leuven Vlaams-Brabant 3012",
    "addr:housenumber":"517",
    "addr:postcode":"3012",
    "addr:street":"Aarschotsesteenweg",
    "iso:country":"BE",
    "sg:address":"Aarschotsesteenweg 517",
    "sg:city":"Leuven",
    "sg:orig_category":"Vitrage. Installation de menuiserie en bois and plastique. Installation de serres, double vitrage an",
    "sg:phone":"+32 16 44 55 75",
    "sg:postcode":"3012",
    "sg:province":"Vlaams-Brabant",
    "wof:name":"Maenen J. & K.",
    "wof:placetype":"venue"
},
  "geometry": {"coordinates":[4.7230768204,50.9280395508],"type":"Point"}
}