{
  "type": "Feature",
  "properties": {
    "iso:country":"BE",
    "sg:address":"Avenue Henri Lepage 49",
    "sg:city":"Wavre",
    "sg:classifiers":[
        {
            "category":"Home & Garden",
            "subcategory":"Building Materials",
            "type":"Retail Goods"
        }
    ],
    "sg:phone":"+32 477 20 53 07",
    "sg:postcode":"1300",
    "sg:province":"Brabant Wallon",
    "sg:tags":[
        "window"
    ],
    "wof:name":"Espace Chassis",
    "wof:placetype":"venue"
},
  "geometry": {"coordinates":[4.6036949158,50.7200660706],"type":"Point"}
}