{
  "type": "Feature",
  "properties": {
    "iso:country":"BE",
    "sg:address":"Grand Place 7",
    "sg:city":"Mons",
    "sg:classifiers":[
        {
            "category":"Bars & Pubs",
            "type":"Food & Drink"
        }
    ],
    "sg:phone":"+32 65 35 49 03",
    "sg:postcode":"7000",
    "sg:province":"Hainaut",
    "wof:name":"Royal (le)",
    "wof:placetype":"venue"
},
  "geometry": {"coordinates":[3.9522330761,50.4544715881],"type":"Point"}
}