{
  "type": "Feature",
  "properties": {
    "addr:full":"Kleine Pintstraat 1 Hoogstraten Antwerpen 2320",
    "addr:housenumber":"1",
    "addr:postcode":"2320",
    "addr:street":"Kleine Pintstraat",
    "iso:country":"BE",
    "sg:address":"Kleine Pintstraat 1",
    "sg:city":"Hoogstraten",
    "sg:orig_category":"Fruitteelt Varkenskwekers",
    "sg:phone":"+32 3 314 54 33",
    "sg:postcode":"2320",
    "sg:province":"Antwerpen",
    "wof:name":"Augustinus Verheyen",
    "wof:placetype":"venue"
},
  "geometry": {"coordinates":[4.7424740791,51.410358429],"type":"Point"}
}