{
  "type": "Feature",
  "properties": {
    "iso:country":"BE",
    "sg:address":"Ouden Dendermondse Stwg 77",
    "sg:city":"Aalst",
    "sg:orig_category":"Parfumeries",
    "sg:phone":"+32 53 71 16 66",
    "sg:postcode":"9300",
    "sg:province":"Oost-Vlaanderen",
    "wof:name":"Parfumerie Givani",
    "wof:placetype":"venue"
},
  "geometry": {"coordinates":[4.0465888977,50.9506263733],"type":"Point"}
}