{
  "type": "Feature",
  "properties": {
    "addr:full":"Rue Pepin 41 Namur Namur 5000",
    "addr:housenumber":"41",
    "addr:postcode":"5000",
    "addr:street":"Rue Pepin",
    "iso:country":"BE",
    "sg:address":"Rue Pepin 41",
    "sg:city":"Namur",
    "sg:classifiers":[
        {
            "category":"Banks & Credit Unions",
            "subcategory":"Investment Brokerage",
            "type":"Services"
        }
    ],
    "sg:phone":"+32 81 25 05 50",
    "sg:postcode":"5000",
    "sg:province":"Namur",
    "sg:tags":[
        "printing",
        "-"
    ],
    "wof:name":"Adrenaline Sprl",
    "wof:placetype":"venue"
},
  "geometry": {"coordinates":[4.8700709343,50.4666442871],"type":"Point"}
}