{
  "type": "Feature",
  "properties": {
    "iso:country":"BE",
    "sg:address":"Avenue Jules Henin 8",
    "sg:city":"Charleroi",
    "sg:orig_category":"Dameskledingzaken",
    "sg:phone":"+32 71 31 43 86",
    "sg:postcode":"6000",
    "sg:province":"Hainaut",
    "wof:name":"Tout Pour Elle",
    "wof:placetype":"venue"
},
  "geometry": {"coordinates":[4.4492912292,50.4163284302],"type":"Point"}
}