{
  "type": "Feature",
  "properties": {
    "addr:full":"Rue De Cureghem 34 Bruxelles Bruxelles-Capitale 1000",
    "addr:housenumber":"34",
    "addr:postcode":"1000",
    "addr:street":"Rue De Cureghem",
    "iso:country":"BE",
    "sg:address":"Rue De Cureghem 34",
    "sg:city":"Bruxelles",
    "sg:classifiers":[
        {
            "category":"Professional",
            "subcategory":"Advertising",
            "type":"Services"
        }
    ],
    "sg:phone":"+32 2 512 31 04",
    "sg:postcode":"1000",
    "sg:province":"Bruxelles-Capitale",
    "sg:tags":[
        "photography"
    ],
    "wof:name":"Maeseele J",
    "wof:placetype":"venue"
},
  "geometry": {"coordinates":[4.3416900635,50.8448829651],"type":"Point"}
}