{
  "type": "Feature",
  "properties": {
    "addr:full":"Chauss\u00e9e De La Grande Espinette 20 Rhode-saint-gen\u00e8se Vlaams-Brabant 1640",
    "addr:housenumber":"20",
    "addr:postcode":"1640",
    "addr:street":"Chausse\u0301E De La Grande Espinette",
    "iso:country":"BE",
    "sg:address":"Chauss\u00e9e De La Grande Espinette 20",
    "sg:city":"Rhode-saint-gen\u00e8se",
    "sg:classifiers":[
        {
            "category":"Utilities",
            "subcategory":"Cable",
            "type":"Services"
        }
    ],
    "sg:phone":"+32 2 255 87 60",
    "sg:postcode":"1640",
    "sg:province":"Vlaams-Brabant",
    "sg:tags":[
        "galvanizing",
        "hot-dip"
    ],
    "wof:name":"Cs-galva",
    "wof:placetype":"venue"
},
  "geometry": {"coordinates":[4.4250388145,50.9034881592],"type":"Point"}
}