{
  "type": "Feature",
  "properties": {
    "addr:full":"Vlasbloemstraat 10 Ingelmunster West-Vlaanderen 8770",
    "addr:housenumber":"10",
    "addr:postcode":"8770",
    "addr:street":"Vlasbloemstraat",
    "iso:country":"BE",
    "sg:address":"Vlasbloemstraat 10",
    "sg:city":"Ingelmunster",
    "sg:orig_category":"Entretien and r\u00e9parations de voitures",
    "sg:phone":"+32 51 30 86 39",
    "sg:postcode":"8770",
    "sg:province":"West-Vlaanderen",
    "wof:name":"J. Soenens",
    "wof:placetype":"venue"
},
  "geometry": {"coordinates":[3.2736539841,50.9122200012],"type":"Point"}
}