{
  "type": "Feature",
  "properties": {
    "addr:full":"Rue Des Ch\u00e2taigniers 64 La Louvi\u00e8re (saint-vaast) Hainaut 7100",
    "addr:housenumber":"64",
    "addr:postcode":"7100",
    "addr:street":"Rue Des Cha\u0302Taigniers",
    "iso:country":"BE",
    "sg:address":"Rue Des Ch\u00e2taigniers 64",
    "sg:city":"La Louvi\u00e8re (saint-vaast)",
    "sg:classifiers":[
        {
            "category":"Shopping",
            "subcategory":"Discount & Variety Stores",
            "type":"Retail Goods"
        }
    ],
    "sg:phone":"+32 64 26 03 79",
    "sg:postcode":"7100",
    "sg:province":"Hainaut",
    "sg:tags":[
        "shop",
        "clearers",
        "curiosity",
        "furniture"
    ],
    "wof:name":"Ergot Bongiovanni P",
    "wof:placetype":"venue"
},
  "geometry": {"coordinates":[4.1714911461,50.4657020569],"type":"Point"}
}