{
  "type": "Feature",
  "properties": {
    "addr:full":"Retische Weg Z/n Geel Antwerpen 2440",
    "addr:housenumber":"z / n",
    "addr:postcode":"2440",
    "addr:street":"Retische Weg",
    "iso:country":"BE",
    "sg:address":"Retische Weg Z/n",
    "sg:city":"Geel",
    "sg:classifiers":[
        {
            "category":"Manufacturing",
            "subcategory":"Chemicals & Compounds",
            "type":"Manufacturing & Wholesale Goods"
        }
    ],
    "sg:phone":"+32 14 57 13 36",
    "sg:postcode":"2440",
    "sg:province":"Antwerpen",
    "sg:tags":[
        "analysis"
    ],
    "wof:name":"Irmm",
    "wof:placetype":"venue"
},
  "geometry": {"coordinates":[4.9906659126,51.1610794067],"type":"Point"}
}