{
  "type": "Feature",
  "properties": {
    "addr:full":"Steenweg 147 Lanaken Limburg 3620",
    "addr:housenumber":"147",
    "addr:postcode":"3620",
    "addr:street":"Steenweg",
    "iso:country":"BE",
    "sg:address":"Steenweg 147",
    "sg:city":"Lanaken",
    "sg:orig_category":"Beheer onroerend goed Projectontwikkelaars",
    "sg:phone":"+32 89 71 31 02",
    "sg:postcode":"3620",
    "sg:province":"Limburg",
    "wof:name":"Provestim",
    "wof:placetype":"venue"
},
  "geometry": {"coordinates":[5.6821899414,50.9127311707],"type":"Point"}
}