{
  "type": "Feature",
  "properties": {
    "iso:country":"BE",
    "sg:address":"Meensesteenweg 320k",
    "sg:city":"Roeselare",
    "sg:classifiers":[
        {
            "category":"Shopping",
            "subcategory":"Antiques",
            "type":"Retail Goods"
        }
    ],
    "sg:phone":"+32 51 20 61 03",
    "sg:postcode":"8800",
    "sg:province":"West-Vlaanderen",
    "wof:name":"Antiek Rodenbach Bvba",
    "wof:placetype":"venue"
},
  "geometry": {"coordinates":[3.1192240715,50.9300422668],"type":"Point"}
}