{
  "type": "Feature",
  "properties": {
    "iso:country":"BE",
    "sg:address":"Rue Du Nord 84",
    "sg:city":"Charleroi",
    "sg:orig_category":"Epiceries",
    "sg:phone":"+32 71 41 01 78",
    "sg:postcode":"6060",
    "sg:province":"Hainaut",
    "wof:name":"Claudine Decoster",
    "wof:placetype":"venue"
},
  "geometry": {"coordinates":[4.4880981445,50.4251937866],"type":"Point"}
}