{
  "type": "Feature",
  "properties": {
    "iso:country":"BE",
    "sg:address":"Wagenmakerstraat 24",
    "sg:city":"Zwevegem (otegem)",
    "sg:classifiers":[
        {
            "category":"Shopping",
            "subcategory":"Jewelry",
            "type":"Retail Goods"
        }
    ],
    "sg:phone":"+32 56 77 81 85",
    "sg:postcode":"8553",
    "sg:province":"West-Vlaanderen",
    "sg:tags":[
        "jeweller",
        "-"
    ],
    "wof:name":"Moerman E",
    "wof:placetype":"venue"
},
  "geometry": {"coordinates":[3.395690918,50.8120956421],"type":"Point"}
}