{
  "type": "Feature",
  "properties": {
    "iso:country":"BE",
    "sg:address":"Brusselstraat 95",
    "sg:city":"Dilbeek",
    "sg:orig_category":"Services de Nettoyage and de D\u00e9sinfection. Installation \u00e9lectrique r\u00e9sidentielle",
    "sg:phone":"+32 2 453 91 08",
    "sg:postcode":"1700",
    "sg:province":"Vlaams-Brabant",
    "wof:name":"Futur'elec",
    "wof:placetype":"venue"
},
  "geometry": {"coordinates":[4.2083501816,50.8759994507],"type":"Point"}
}