{
  "type": "Feature",
  "properties": {
    "iso:country":"BE",
    "sg:address":"Lijsterlaan 6",
    "sg:city":"Bornem",
    "sg:classifiers":[
        {
            "category":"Insurance",
            "subcategory":"Insurance Agent",
            "type":"Services"
        }
    ],
    "sg:phone":"+32 3 889 45 69",
    "sg:postcode":"2880",
    "sg:province":"Antwerpen",
    "sg:tags":[
        "verzekeringsmakelaars",
        "expert"
    ],
    "wof:name":"Smet-windey",
    "wof:placetype":"venue"
},
  "geometry": {"coordinates":[4.2042479515,51.0743179321],"type":"Point"}
}