{
  "type": "Feature",
  "properties": {
    "addr:full":"Rue Des Machines 8 Amay Li\u00e8ge 4540",
    "addr:housenumber":"8",
    "addr:postcode":"4540",
    "addr:street":"Rue Des Machines",
    "iso:country":"BE",
    "sg:address":"Rue Des Machines 8",
    "sg:city":"Amay",
    "sg:classifiers":[
        {
            "category":"Utilities",
            "subcategory":"Telephone",
            "type":"Services"
        }
    ],
    "sg:phone":"+32 85 31 43 91",
    "sg:postcode":"4540",
    "sg:province":"Li\u00e8ge",
    "sg:tags":[
        "karting",
        "accessory"
    ],
    "wof:name":"Amay Cobra Karting",
    "wof:placetype":"venue"
},
  "geometry": {"coordinates":[5.3180990219,50.5478668213],"type":"Point"}
}