{
  "type": "Feature",
  "properties": {
    "addr:full":"Rue Nan\u00e8che 45 Charleroi (gilly) Hainaut 6060",
    "addr:housenumber":"45",
    "addr:postcode":"6060",
    "addr:street":"Rue Nane\u0300Che",
    "iso:country":"BE",
    "sg:address":"Rue Nan\u00e8che 45",
    "sg:city":"Charleroi (gilly)",
    "sg:classifiers":[
        {
            "category":"Shopping",
            "subcategory":"Books",
            "type":"Retail Goods"
        }
    ],
    "sg:phone":"+32 71 41 00 76",
    "sg:postcode":"6060",
    "sg:province":"Hainaut",
    "sg:tags":[
        "bookseller"
    ],
    "wof:name":"Rond Point (librairie Du)",
    "wof:placetype":"venue"
},
  "geometry": {"coordinates":[4.4880981445,50.4251937866],"type":"Point"}
}