{
  "type": "Feature",
  "properties": {
    "addr:full":"Boulevard De France 0 Braine-l`alleud Brabant Wallon 1420",
    "addr:housenumber":"0",
    "addr:postcode":"1420",
    "addr:street":"Boulevard De France;Brabant Wallon",
    "iso:country":"BE",
    "sg:address":"Boulevard De France 0",
    "sg:city":"Braine-l`alleud",
    "sg:orig_category":"Bioscopen",
    "sg:phone":"+32 2 389 17 17",
    "sg:postcode":"1420",
    "sg:province":"Brabant Wallon",
    "wof:name":"Imagibraine",
    "wof:placetype":"venue"
},
  "geometry": {"coordinates":[5.8036999702,45.9799995422],"type":"Point"}
}