{
  "type": "Feature",
  "properties": {
    "addr:full":"Leeuwerikenstraat 170 Oostende West-Vlaanderen 8400",
    "addr:housenumber":"170",
    "addr:postcode":"8400",
    "addr:street":"Leeuwerikenstraat",
    "iso:country":"BE",
    "sg:address":"Leeuwerikenstraat 170",
    "sg:city":"Oostende",
    "sg:classifiers":[
        {
            "category":"Building & Trades",
            "subcategory":"Construction",
            "type":"Services"
        }
    ],
    "sg:phone":"+32 59 80 65 99",
    "sg:postcode":"8400",
    "sg:province":"West-Vlaanderen",
    "sg:tags":[
        "stucco",
        "contractor"
    ],
    "wof:name":"Schmidt A",
    "wof:placetype":"venue"
},
  "geometry": {"coordinates":[2.9126999378,51.2312583923],"type":"Point"}
}