{
  "type": "Feature",
  "properties": {
    "addr:full":"Doorniksewijk 132 Kortrijk West-Vlaanderen 8500",
    "addr:housenumber":"132",
    "addr:postcode":"8500",
    "iso:country":"BE",
    "sg:address":"Doorniksewijk 132",
    "sg:city":"Kortrijk",
    "sg:orig_category":"Cr\u00e9meries",
    "sg:phone":"+32 56 21 84 58",
    "sg:postcode":"8500",
    "sg:province":"West-Vlaanderen",
    "wof:name":"St.rochus",
    "wof:placetype":"venue"
},
  "geometry": {"coordinates":[3.2691249847,50.8193740845],"type":"Point"}
}