{
  "type": "Feature",
  "properties": {
    "iso:country":"BE",
    "sg:address":"Rue Du Centre 41ba",
    "sg:city":"Braives",
    "sg:orig_category":"Artsen and specialisten",
    "sg:phone":"+32 19 69 77 50",
    "sg:postcode":"4260",
    "sg:province":"Li\u00e8ge",
    "wof:name":"Patrick Cvjetic",
    "wof:placetype":"venue"
},
  "geometry": {"coordinates":[5.1512508392,50.6246337891],"type":"Point"}
}