{
  "type": "Feature",
  "properties": {
    "addr:full":"Jules Pauwelsstraat 50-52 Antwerpen (hoboken) Antwerpen 2660",
    "addr:postcode":"50-52;2660",
    "addr:street":"Jules Pauwelsstraat",
    "iso:country":"BE",
    "sg:address":"Jules Pauwelsstraat 50-52",
    "sg:city":"Antwerpen (hoboken)",
    "sg:classifiers":[
        {
            "category":"Building & Trades",
            "subcategory":"Landscaping Services",
            "type":"Services"
        }
    ],
    "sg:phone":"+32 3 830 44 90",
    "sg:postcode":"2660",
    "sg:province":"Antwerpen",
    "sg:tags":[
        "gardening",
        "garden",
        "maintenance"
    ],
    "wof:name":"Huylebroeck Jan Tuinaanleg",
    "wof:placetype":"venue"
},
  "geometry": {"coordinates":[4.3397898674,51.1732788086],"type":"Point"}
}