{
  "type": "Feature",
  "properties": {
    "addr:full":"Oorlogskruisenlaan 137 Brussel/bruxelles Bruxelles-Capitale 1120",
    "addr:housenumber":"137",
    "addr:postcode":"1120",
    "addr:street":"Oorlogskruisenlaan;/",
    "iso:country":"BE",
    "sg:address":"Oorlogskruisenlaan 137",
    "sg:city":"Brussel/bruxelles",
    "sg:orig_category":"Telecommunicatieapparaten Telecommunicatiesystemen",
    "sg:phone":"+32 2 245 07 47",
    "sg:postcode":"1120",
    "sg:province":"Bruxelles-Capitale",
    "wof:name":"Beam Electronics",
    "wof:placetype":"venue"
},
  "geometry": {"coordinates":[4.3826751709,50.890460968],"type":"Point"}
}