{
  "type": "Feature",
  "properties": {
    "iso:country":"BE",
    "sg:address":"Ottergemdorp 69ba",
    "sg:city":"Erpe-mere",
    "sg:orig_category":"Boekhandels",
    "sg:phone":"+32 53 80 86 31",
    "sg:postcode":"9420",
    "sg:province":"Oost-Vlaanderen",
    "wof:name":"Martiss",
    "wof:placetype":"venue"
},
  "geometry": {"coordinates":[3.9500620365,50.9346351624],"type":"Point"}
}