{
  "type": "Feature",
  "properties": {
    "iso:country":"BE",
    "sg:address":"Oude Leuvensebaan 47",
    "sg:city":"Bekkevoort",
    "sg:orig_category":"Goederenvervoer over de weg",
    "sg:phone":"+32 13 32 21 07",
    "sg:postcode":"3460",
    "sg:province":"Vlaams-Brabant",
    "wof:name":"Vlaeyen",
    "wof:placetype":"venue"
},
  "geometry": {"coordinates":[4.9705381393,50.9458999634],"type":"Point"}
}