{
  "type": "Feature",
  "properties": {
    "addr:full":"Nieuwstraat 16 Wingene West-Vlaanderen 8750",
    "addr:housenumber":"16",
    "addr:postcode":"8750",
    "addr:street":"Nieuwstraat",
    "iso:country":"BE",
    "sg:address":"Nieuwstraat 16",
    "sg:city":"Wingene",
    "sg:orig_category":"Enseignement maternel and primaire",
    "sg:phone":"+32 51 65 68 52",
    "sg:postcode":"8750",
    "sg:province":"West-Vlaanderen",
    "wof:name":"Vrije Kleuterschool",
    "wof:placetype":"venue"
},
  "geometry": {"coordinates":[3.2788949013,51.0612754822],"type":"Point"}
}