{
  "type": "Feature",
  "properties": {
    "iso:country":"BE",
    "sg:address":"Hof Van Loostraat 6",
    "sg:city":"Kasterlee",
    "sg:classifiers":[
        {
            "category":"Autos & Motor Vehicles",
            "subcategory":"Fuel & Gas Station",
            "type":"Retail Goods"
        }
    ],
    "sg:phone":"+32 14 85 14 13",
    "sg:postcode":"2460",
    "sg:province":"Antwerpen",
    "sg:tags":[
        "stations-service",
        "carburants"
    ],
    "wof:name":"Diels",
    "wof:placetype":"venue"
},
  "geometry": {"coordinates":[4.9909582138,51.2419586182],"type":"Point"}
}