{
  "type": "Feature",
  "properties": {
    "iso:country":"BE",
    "sg:address":"Lededries 7",
    "sg:city":"Gent",
    "sg:orig_category":"Etalage- and showroomontwerpers",
    "sg:phone":"+32 9 230 41 20",
    "sg:postcode":"9050",
    "sg:province":"Oost-Vlaanderen",
    "wof:name":"Emmanuel Demuynck",
    "wof:placetype":"venue"
},
  "geometry": {"coordinates":[3.7456400394,51.0385398865],"type":"Point"}
}