{
  "type": "Feature",
  "properties": {
    "addr:full":"Rue De Malmedy 4 Sankt Vith Li\u00e8ge 4780",
    "addr:housenumber":"4",
    "addr:postcode":"4780",
    "addr:street":"Rue De Malmedy",
    "iso:country":"BE",
    "sg:address":"Rue De Malmedy 4",
    "sg:city":"Sankt Vith",
    "sg:orig_category":"Cr\u00e9dits divers",
    "sg:postcode":"4780",
    "sg:province":"Li\u00e8ge",
    "wof:name":"Postomat Saint-vith",
    "wof:placetype":"venue"
},
  "geometry": {"coordinates":[6.1242489815,50.2828598022],"type":"Point"}
}