{
  "type": "Feature",
  "properties": {
    "iso:country":"BE",
    "sg:address":"Industriepark Klein Frankrijk 62",
    "sg:city":"Ronse",
    "sg:classifiers":[
        {
            "category":"Manufacturing",
            "subcategory":"Textiles",
            "type":"Manufacturing & Wholesale Goods"
        }
    ],
    "sg:phone":"+32 55 23 00 10",
    "sg:postcode":"9600",
    "sg:province":"Oost-Vlaanderen",
    "sg:tags":[
        "linen",
        "clothing",
        "fabric"
    ],
    "wof:name":"Printed Carpets Ve.de.be. Nv",
    "wof:placetype":"venue"
},
  "geometry": {"coordinates":[3.6462850571,50.7514572144],"type":"Point"}
}