{
  "type": "Feature",
  "properties": {
    "addr:full":"Kasteeldreef 81 Beveren (beveren-waas) Oost-Vlaanderen 9120",
    "addr:housenumber":"81",
    "addr:postcode":"9120",
    "addr:street":"Kasteeldreef;Oost-Vlaanderen",
    "iso:country":"BE",
    "sg:address":"Kasteeldreef 81",
    "sg:city":"Beveren (beveren-waas)",
    "sg:classifiers":[
        {
            "category":"Health Services",
            "subcategory":"Dentist",
            "type":"Services"
        }
    ],
    "sg:phone":"+32 3 775 59 80",
    "sg:postcode":"9120",
    "sg:province":"Oost-Vlaanderen",
    "wof:name":"Van Goethem R",
    "wof:placetype":"venue"
},
  "geometry": {"coordinates":[4.2554678917,51.2173347473],"type":"Point"}
}