{
  "type": "Feature",
  "properties": {
    "iso:country":"BE",
    "sg:address":"Hoogstraat 3",
    "sg:city":"Aalst (meldert)",
    "sg:classifiers":[
        {
            "category":"Professional",
            "subcategory":"Art Services",
            "type":"Services"
        }
    ],
    "sg:phone":"+32 52 35 44 43",
    "sg:postcode":"9310",
    "sg:province":"Oost-Vlaanderen",
    "sg:tags":[
        "designer",
        "display"
    ],
    "wof:name":"Schepens G",
    "wof:placetype":"venue"
},
  "geometry": {"coordinates":[4.0615320206,50.9491729736],"type":"Point"}
}