{
  "type": "Feature",
  "properties": {
    "addr:full":"Chauss\u00e9e De Bruxelles 9 Mons Hainaut 7000",
    "addr:housenumber":"9",
    "addr:postcode":"7000",
    "addr:street":"Chausse\u0301E De Bruxelles;Hainaut",
    "iso:country":"BE",
    "sg:address":"Chauss\u00e9e De Bruxelles 9",
    "sg:city":"Mons",
    "sg:classifiers":[
        {
            "category":"Building & Trades",
            "subcategory":"Plumbing",
            "type":"Services"
        }
    ],
    "sg:phone":"+32 65 84 74 05",
    "sg:postcode":"7000",
    "sg:province":"Hainaut",
    "sg:tags":[
        "relocation"
    ],
    "wof:name":"Cabinet Solutions",
    "wof:placetype":"venue"
},
  "geometry": {"coordinates":[3.9575889111,50.4660644531],"type":"Point"}
}