{
  "type": "Feature",
  "properties": {
    "iso:country":"BE",
    "sg:address":"Donkvijverstraat 11b12",
    "sg:city":"Beveren",
    "sg:orig_category":"Journaux. Tabac",
    "sg:phone":"+32 3 775 35 54",
    "sg:postcode":"9120",
    "sg:province":"Oost-Vlaanderen",
    "wof:name":"Margaretha De Boeck",
    "wof:placetype":"venue"
},
  "geometry": {"coordinates":[4.2524189949,51.2147674561],"type":"Point"}
}