{
  "type": "Feature",
  "properties": {
    "iso:country":"BE",
    "sg:address":"Peerderbaan 64",
    "sg:city":"Meeuwen-gruitrode (meeuwen)",
    "sg:classifiers":[
        {
            "category":"Farming",
            "subcategory":"Fish & Marine Products",
            "type":"Manufacturing & Wholesale Goods"
        }
    ],
    "sg:phone":"+32 11 79 16 54",
    "sg:postcode":"3670",
    "sg:province":"Limburg",
    "sg:tags":[
        "equipment",
        "fishery"
    ],
    "wof:name":"Elisabethbronnen",
    "wof:placetype":"venue"
},
  "geometry": {"coordinates":[5.5068421364,51.1088218689],"type":"Point"}
}