{
  "type": "Feature",
  "properties": {
    "addr:full":"Europark 1060 Houthalen Limburg 3530",
    "addr:housenumber":"1060",
    "addr:postcode":"3530",
    "addr:street":"Europark",
    "iso:country":"BE",
    "sg:address":"Europark 1060",
    "sg:city":"Houthalen",
    "sg:classifiers":[
        {
            "category":"Manufacturing",
            "subcategory":"Rubber & Plastics",
            "type":"Manufacturing & Wholesale Goods"
        }
    ],
    "sg:phone":"+32 11 60 91 30",
    "sg:postcode":"3530",
    "sg:province":"Limburg",
    "wof:name":"Alpagro Plastics Nv",
    "wof:placetype":"venue"
},
  "geometry": {"coordinates":[5.4055519104,51.0423774719],"type":"Point"}
}