{
  "type": "Feature",
  "properties": {
    "iso:country":"BE",
    "sg:address":"Neerstraat 40",
    "sg:city":"Brakel",
    "sg:classifiers":[
        {
            "category":"Insurance",
            "subcategory":"Life Insurance",
            "type":"Services"
        }
    ],
    "sg:phone":"+32 55 42 26 61",
    "sg:postcode":"9660",
    "sg:province":"Oost-Vlaanderen",
    "sg:tags":[
        "assurance"
    ],
    "wof:name":"N.m.k.n.",
    "wof:placetype":"venue"
},
  "geometry": {"coordinates":[3.7663469315,50.8041000366],"type":"Point"}
}