{
  "type": "Feature",
  "properties": {
    "iso:country":"BE",
    "sg:address":"Rue Reper Vreven 32",
    "sg:city":"Bruxelles",
    "sg:classifiers":[
        {
            "category":"Insurance",
            "subcategory":"Insurance Agent",
            "type":"Services"
        }
    ],
    "sg:phone":"+32 2 478 33 95",
    "sg:postcode":"1020",
    "sg:province":"Bruxelles-Capitale",
    "sg:tags":[
        "broker"
    ],
    "wof:name":"Leonard Yvan Sprl",
    "wof:placetype":"venue"
},
  "geometry": {"coordinates":[4.3409647942,50.890499115],"type":"Point"}
}