{
  "type": "Feature",
  "properties": {
    "iso:country":"BE",
    "sg:address":"Armentierestraat 153bf",
    "sg:city":"Komen-waasten/comines-warneton",
    "sg:orig_category":"Apotheken",
    "sg:phone":"+32 56 58 82 83",
    "sg:postcode":"7782",
    "sg:province":"Hainaut",
    "wof:name":"Katelijn Goddeeris/k. Goddeeris",
    "wof:placetype":"venue"
},
  "geometry": {"coordinates":[2.8795371056,50.7278747559],"type":"Point"}
}