{
  "type": "Feature",
  "properties": {
    "addr:full":"Av.l'exposit.universelle 97 Ganshoren Bruxelles-Capitale 1083",
    "addr:housenumber":"97",
    "addr:postcode":"1083",
    "addr:street":"Av.L'Exposit.Universelle",
    "iso:country":"BE",
    "sg:address":"Av.l'exposit.universelle 97",
    "sg:city":"Ganshoren",
    "sg:orig_category":"Location de logements sociaux",
    "sg:phone":"+32 2 424 20 78",
    "sg:postcode":"1083",
    "sg:province":"Bruxelles-Capitale",
    "wof:name":"Le Home",
    "wof:placetype":"venue"
},
  "geometry": {"coordinates":[4.3088898659,50.873588562],"type":"Point"}
}