{
  "type": "Feature",
  "properties": {
    "iso:country":"BE",
    "sg:address":"Waterstraat 33",
    "sg:city":"Menen",
    "sg:orig_category":"Elektrische installaties voor woningen",
    "sg:phone":"+32 56 40 12 46",
    "sg:postcode":"8930",
    "sg:province":"West-Vlaanderen",
    "wof:name":"Jean-pierre Dejonghe",
    "wof:placetype":"venue"
},
  "geometry": {"coordinates":[3.1412780285,50.7909202576],"type":"Point"}
}