{
  "type": "Feature",
  "properties": {
    "iso:country":"BE",
    "sg:address":"Jos Hostelaan 9",
    "sg:city":"Temse",
    "sg:orig_category":"Reclamebureaus Sportactiviteiten en -evenementen",
    "sg:phone":"+32 3 711 24 44",
    "sg:postcode":"9140",
    "sg:province":"Oost-Vlaanderen",
    "wof:name":"Flying Comics",
    "wof:placetype":"venue"
},
  "geometry": {"coordinates":[4.2080001831,51.132976532],"type":"Point"}
}