{
  "type": "Feature",
  "properties": {
    "iso:country":"BE",
    "sg:address":"Rue De La D\u00e9portation 129",
    "sg:city":"Tubize",
    "sg:classifiers":[
        {
            "category":"Insurance",
            "subcategory":"Insurance Agent",
            "type":"Services"
        }
    ],
    "sg:phone":"+32 2 355 25 61",
    "sg:postcode":"1480",
    "sg:province":"Brabant Wallon",
    "sg:tags":[
        "broker"
    ],
    "wof:name":"Dcm Conseils",
    "wof:placetype":"venue"
},
  "geometry": {"coordinates":[4.2102217674,50.6912689209],"type":"Point"}
}