{
  "type": "Feature",
  "properties": {
    "iso:country":"BE",
    "sg:address":"Industrielaan 12",
    "sg:city":"Maldegem",
    "sg:orig_category":"Boekenuitgeverijen",
    "sg:phone":"+32 50 72 06 54",
    "sg:postcode":"9990",
    "sg:province":"Oost-Vlaanderen",
    "wof:name":"Pro",
    "wof:placetype":"venue"
},
  "geometry": {"coordinates":[3.4663250446,51.1989479065],"type":"Point"}
}