{
  "type": "Feature",
  "properties": {
    "addr:full":"Schotelven 98 Arendonk Antwerpen 2370",
    "addr:housenumber":"98",
    "addr:postcode":"2370",
    "addr:street":"Schotelven",
    "iso:country":"BE",
    "sg:address":"Schotelven 98",
    "sg:city":"Arendonk",
    "sg:orig_category":"Meubelzaken, woning- and keukeninrichting",
    "sg:phone":"+32 14 67 25 94",
    "sg:postcode":"2370",
    "sg:province":"Antwerpen",
    "wof:name":"H. & B. Trading",
    "wof:placetype":"venue"
},
  "geometry": {"coordinates":[5.051861763,51.3133621216],"type":"Point"}
}