{
  "type": "Feature",
  "properties": {
    "iso:country":"BE",
    "sg:address":"Markt 34",
    "sg:city":"Brugge",
    "sg:classifiers":[
        {
            "category":"Restaurant",
            "type":"Food & Drink"
        }
    ],
    "sg:phone":"+32 50 33 41 37",
    "sg:postcode":"8000",
    "sg:province":"West-Vlaanderen",
    "wof:name":"Beiaardier",
    "wof:placetype":"venue"
},
  "geometry": {"coordinates":[3.2244439125,51.2092247009],"type":"Point"}
}