{
  "type": "Feature",
  "properties": {
    "iso:country":"BE",
    "sg:address":"Middelburgstraat 28",
    "sg:city":"Watermaal-bosvoorde/watermael-",
    "sg:classifiers":[
        {
            "category":"Restaurant",
            "type":"Food & Drink"
        }
    ],
    "sg:phone":"+32 2 673 53 93",
    "sg:postcode":"1170",
    "sg:province":"Bruxelles-Capitale",
    "wof:name":"Nouveau Chez Nous",
    "wof:placetype":"venue"
},
  "geometry": {"coordinates":[4.4178848267,50.7968902588],"type":"Point"}
}