{
  "type": "Feature",
  "properties": {
    "addr:full":"Grote Markt 34 Ieper West-Vlaanderen 8900",
    "addr:housenumber":"34",
    "addr:postcode":"8900",
    "addr:street":"Grote Markt",
    "iso:country":"BE",
    "sg:address":"Grote Markt 34",
    "sg:city":"Ieper",
    "sg:orig_category":"Overheidsdiensten",
    "sg:phone":"+32 57 22 85 55",
    "sg:postcode":"8900",
    "sg:province":"West-Vlaanderen",
    "wof:name":"Stadsbestuur",
    "wof:placetype":"venue"
},
  "geometry": {"coordinates":[2.8872299194,50.8515586853],"type":"Point"}
}