{
  "type": "Feature",
  "properties": {
    "iso:country":"BE",
    "sg:address":"Square Vergote 51",
    "sg:city":"Bruxelles (schaerbeek)",
    "sg:classifiers":[
        {
            "category":"Health Services",
            "subcategory":"Doctor",
            "type":"Services"
        }
    ],
    "sg:phone":"+32 2 735 27 21",
    "sg:postcode":"1030",
    "sg:province":"Bruxelles-Capitale",
    "sg:tags":[
        "psychotherapist",
        "psychoanalyst"
    ],
    "wof:name":"Stevens A",
    "wof:placetype":"venue"
},
  "geometry": {"coordinates":[4.4031949043,50.8466033936],"type":"Point"}
}