{
  "type": "Feature",
  "properties": {
    "addr:full":"Rue Du Cimeti\u00e8re 2 P\u00e9ruwelz (bon-secours) Hainaut 7603",
    "addr:housenumber":"2",
    "addr:postcode":"7603",
    "addr:street":"Rue Du Cimetie\u0300Re",
    "iso:country":"BE",
    "sg:address":"Rue Du Cimeti\u00e8re 2",
    "sg:city":"P\u00e9ruwelz (bon-secours)",
    "sg:classifiers":[
        {
            "category":"Shopping",
            "subcategory":"Antiques",
            "type":"Retail Goods"
        }
    ],
    "sg:phone":"+32 69 77 10 54",
    "sg:postcode":"7603",
    "sg:province":"Hainaut",
    "wof:name":"Vieux Grenier (le)",
    "wof:placetype":"venue"
},
  "geometry": {"coordinates":[3.6071500778,50.497051239],"type":"Point"}
}