{
  "type": "Feature",
  "properties": {
    "addr:full":"Koningstraat 1 Gent Oost-Vlaanderen 9000",
    "addr:housenumber":"1",
    "addr:postcode":"9000",
    "addr:street":"Koningstraat;Oost-Vlaanderen",
    "iso:country":"BE",
    "sg:address":"Koningstraat 1",
    "sg:city":"Gent",
    "sg:classifiers":[
        {
            "category":"Real Estate",
            "subcategory":"Real Estate Services",
            "type":"Services"
        }
    ],
    "sg:phone":"+32 9 269 02 20",
    "sg:postcode":"9000",
    "sg:province":"Oost-Vlaanderen",
    "wof:name":"Dionite Nv",
    "wof:placetype":"venue"
},
  "geometry": {"coordinates":[3.7272319794,51.0551109314],"type":"Point"}
}