{
  "type": "Feature",
  "properties": {
    "addr:full":"Rue De B\u00e9tissart 45 Ath (ormeignies) Hainaut 7802",
    "addr:housenumber":"45",
    "addr:postcode":"7802",
    "addr:street":"Rue De Be\u0301Tissart",
    "iso:country":"BE",
    "sg:address":"Rue De B\u00e9tissart 45",
    "sg:city":"Ath (ormeignies)",
    "sg:classifiers":[
        {
            "category":"Retail",
            "subcategory":"Veterinary Services",
            "type":"Services"
        }
    ],
    "sg:phone":"+32 68 28 18 17",
    "sg:postcode":"7802",
    "sg:province":"Hainaut",
    "sg:tags":[
        "veterinarian"
    ],
    "wof:name":"Dejonckheere P",
    "wof:placetype":"venue"
},
  "geometry": {"coordinates":[3.7527279854,50.5938110352],"type":"Point"}
}