{
  "type": "Feature",
  "properties": {
    "iso:country":"BE",
    "sg:address":"Jan Michiel Huybrechtsstraat 6",
    "sg:city":"Heusden-zolder (heusden)",
    "sg:classifiers":[
        {
            "category":"Autos & Motor Vehicles",
            "subcategory":"Recreational Vehicle Sales",
            "type":"Retail Goods"
        }
    ],
    "sg:phone":"+32 11 42 93 25",
    "sg:postcode":"3550",
    "sg:province":"Limburg",
    "sg:tags":[
        "saw"
    ],
    "wof:name":"Claes Hendrik",
    "wof:placetype":"venue"
},
  "geometry": {"coordinates":[5.2877578735,51.0346221924],"type":"Point"}
}