{
  "type": "Feature",
  "properties": {
    "iso:country":"BE",
    "sg:address":"Van Praetlei 137",
    "sg:city":"Antwerpen",
    "sg:orig_category":"Caf\u00e9s. Salles de conf\u00e9rences and de r\u00e9ceptions",
    "sg:phone":"+32 3 645 50 41",
    "sg:postcode":"2170",
    "sg:province":"Antwerpen",
    "wof:name":"Paroch. Centrum St-jozef",
    "wof:placetype":"venue"
},
  "geometry": {"coordinates":[4.460545063,51.2519378662],"type":"Point"}
}