{
  "type": "Feature",
  "properties": {
    "addr:full":"Rue Du Cortil 48 Fleurus Hainaut 6224",
    "addr:housenumber":"48",
    "addr:postcode":"6224",
    "addr:street":"Rue Du Cortil",
    "iso:country":"BE",
    "sg:address":"Rue Du Cortil 48",
    "sg:city":"Fleurus",
    "sg:classifiers":[
        {
            "category":"Arena",
            "subcategory":"Sports Club",
            "type":"Entertainment"
        }
    ],
    "sg:phone":"+32 71 81 58 40",
    "sg:postcode":"6224",
    "sg:province":"Hainaut",
    "sg:tags":[
        "de"
    ],
    "wof:name":"T.c. Central Baulet",
    "wof:placetype":"venue"
},
  "geometry": {"coordinates":[4.581679821,50.4616775513],"type":"Point"}
}