{
  "type": "Feature",
  "properties": {
    "addr:full":"Bouwelsesteenweg 100 Nijlen Antwerpen 2560",
    "addr:housenumber":"100",
    "addr:postcode":"2560",
    "addr:street":"Bouwelsesteenweg",
    "iso:country":"BE",
    "sg:address":"Bouwelsesteenweg 100",
    "sg:city":"Nijlen",
    "sg:orig_category":"Instituts de beaut\u00e9",
    "sg:phone":"+32 3 411 07 45",
    "sg:postcode":"2560",
    "sg:province":"Antwerpen",
    "wof:name":"Instituut Epiphanie",
    "wof:placetype":"venue"
},
  "geometry": {"coordinates":[4.6819119453,51.1651763916],"type":"Point"}
}