{
  "type": "Feature",
  "properties": {
    "addr:full":"Rue Gr\u00c9try 44bh Li\u00c8ge Li\u00e8ge 4020",
    "addr:housenumber":"44bh",
    "addr:postcode":"4020",
    "addr:street":"Rue Gre\u0301Try",
    "iso:country":"BE",
    "sg:address":"Rue Gr\u00c9try 44bh",
    "sg:city":"Li\u00c8ge",
    "sg:classifiers":[
        {
            "category":"Cafe",
            "type":"Food & Drink"
        }
    ],
    "sg:phone":"+32 4 343 90 37",
    "sg:postcode":"4020",
    "sg:province":"Li\u00e8ge",
    "sg:tags":[
        "caf\u00e9s"
    ],
    "wof:name":"Caf\u00c9 Sur Le Pouce",
    "wof:placetype":"venue"
},
  "geometry": {"coordinates":[5.5803761482,50.6354141235],"type":"Point"}
}