{
  "type": "Feature",
  "properties": {
    "addr:full":"Josaphatstraat 79 Schaarbeek/schaerbeek Bruxelles-Capitale 1030",
    "addr:housenumber":"79",
    "addr:postcode":"1030",
    "addr:street":"Josaphatstraat",
    "iso:country":"BE",
    "sg:address":"Josaphatstraat 79",
    "sg:city":"Schaarbeek/schaerbeek",
    "sg:orig_category":"Artsen and specialisten",
    "sg:phone":"+32 2 242 50 81",
    "sg:postcode":"1030",
    "sg:province":"Bruxelles-Capitale",
    "wof:name":"Abdulkadir Kara",
    "wof:placetype":"venue"
},
  "geometry": {"coordinates":[4.3737077713,50.8582305908],"type":"Point"}
}