{
  "type": "Feature",
  "properties": {
    "iso:country":"BE",
    "sg:address":"Leopold De Waelstraat 10",
    "sg:city":"Antwerpen",
    "sg:orig_category":"D\u00e9corateurs d'int\u00e9rieur",
    "sg:phone":"+32 3 248 53 91",
    "sg:postcode":"2000",
    "sg:province":"Antwerpen",
    "wof:name":"Marc Merckx",
    "wof:placetype":"venue"
},
  "geometry": {"coordinates":[4.3920578957,51.2081069946],"type":"Point"}
}