{
  "type": "Feature",
  "properties": {
    "addr:full":"Mont-saint-martin 29 Li\u00e8ge 1 Li\u00e8ge 4000",
    "addr:housenumber":"29;1",
    "addr:postcode":"4000",
    "addr:street":"Mont-Saint-Martin",
    "iso:country":"BE",
    "sg:address":"Mont-saint-martin 29",
    "sg:city":"Li\u00e8ge 1",
    "sg:classifiers":[
        {
            "category":"Banks & Credit Unions",
            "subcategory":"Investment Brokerage",
            "type":"Services"
        }
    ],
    "sg:phone":"+32 4 223 73 85",
    "sg:postcode":"4000",
    "sg:province":"Li\u00e8ge",
    "sg:tags":[
        "auditor"
    ],
    "wof:name":"Pauwen E",
    "wof:placetype":"venue"
},
  "geometry": {"coordinates":[5.5660471916,50.6445159912],"type":"Point"}
}