{
  "type": "Feature",
  "properties": {
    "addr:full":"Leinstraat 130 Brakel Oost-Vlaanderen 9660",
    "addr:housenumber":"130",
    "addr:postcode":"9660",
    "addr:street":"Leinstraat",
    "iso:country":"BE",
    "sg:address":"Leinstraat 130",
    "sg:city":"Brakel",
    "sg:orig_category":"Epiceries",
    "sg:phone":"+32 55 42 29 38",
    "sg:postcode":"9660",
    "sg:province":"Oost-Vlaanderen",
    "wof:name":"G Vander Maelen",
    "wof:placetype":"venue"
},
  "geometry": {"coordinates":[3.7329909801,50.7766799927],"type":"Point"}
}