{
  "type": "Feature",
  "properties": {
    "addr:full":"Van Diepenbeeckstraat 66 Antwerpen Antwerpen 2018",
    "addr:housenumber":"66",
    "addr:postcode":"2018",
    "addr:street":"Van Diepenbeeckstraat",
    "iso:country":"BE",
    "sg:address":"Van Diepenbeeckstraat 66",
    "sg:city":"Antwerpen",
    "sg:orig_category":"Juwelen and edelstenen Fab",
    "sg:phone":"+32 3 239 02 83",
    "sg:postcode":"2018",
    "sg:province":"Antwerpen",
    "wof:name":"C. Kennis",
    "wof:placetype":"venue"
},
  "geometry": {"coordinates":[4.4235248566,51.2047462463],"type":"Point"}
}