{
  "type": "Feature",
  "properties": {
    "iso:country":"BE",
    "sg:address":"Elisabethlaan 103ba",
    "sg:city":"Aarschot",
    "sg:orig_category":"Apotheken Ziekenhuizen and zorginstellingen",
    "sg:phone":"+32 16 56 38 88",
    "sg:postcode":"3200",
    "sg:province":"Vlaams-Brabant",
    "wof:name":"O.c.m.w.-ziekenhuis",
    "wof:placetype":"venue"
},
  "geometry": {"coordinates":[4.8388900757,50.9884719849],"type":"Point"}
}