{
  "type": "Feature",
  "properties": {
    "addr:full":"Terdeltplein 2 Schaarbeek/schaerbeek Bruxelles-Capitale 1030",
    "addr:housenumber":"2",
    "addr:postcode":"1030",
    "addr:street":"Terdeltplein",
    "iso:country":"BE",
    "sg:address":"Terdeltplein 2",
    "sg:city":"Schaarbeek/schaerbeek",
    "sg:orig_category":"Artsen and specialisten",
    "sg:phone":"+32 2 241 53 37",
    "sg:postcode":"1030",
    "sg:province":"Bruxelles-Capitale",
    "wof:name":"Nathalie Denis",
    "wof:placetype":"venue"
},
  "geometry": {"coordinates":[4.3896551132,50.8680648804],"type":"Point"}
}