{
  "type": "Feature",
  "properties": {
    "addr:full":"Pastoor De Katerstraat 5 Baarle-hertog 2338",
    "addr:housenumber":"5",
    "addr:postcode":"2338",
    "addr:street":"Pastoor De Katerstraat;Baarle-Hertog",
    "iso:country":"BE",
    "sg:address":"Pastoor De Katerstraat 5",
    "sg:city":"Baarle-hertog",
    "sg:orig_category":"Kunstonderwijs",
    "sg:phone":"+32 14 69 95 39",
    "sg:postcode":"2338",
    "wof:name":"Muziekacademie De Noorderkempen",
    "wof:placetype":"venue"
},
  "geometry": {"coordinates":[4.9258198738,51.4415779114],"type":"Point"}
}