{
  "type": "Feature",
  "properties": {
    "addr:full":"Rue De Wand 107 Brussel/bruxelles Bruxelles-Capitale 1020",
    "addr:housenumber":"107",
    "addr:postcode":"1020",
    "addr:street":"Rue De Wand;/",
    "iso:country":"BE",
    "sg:address":"Rue De Wand 107",
    "sg:city":"Brussel/bruxelles",
    "sg:orig_category":"Pain, p\u00e2tisseries and confiseries",
    "sg:phone":"+32 2 268 09 60",
    "sg:postcode":"1020",
    "sg:province":"Bruxelles-Capitale",
    "wof:name":"Mosin",
    "wof:placetype":"venue"
},
  "geometry": {"coordinates":[4.3595547676,50.8982925415],"type":"Point"}
}