{
  "type": "Feature",
  "properties": {
    "addr:full":"Sint-elooisdreef 22 Kortrijk West-Vlaanderen 8500",
    "addr:housenumber":"22",
    "addr:postcode":"8500",
    "addr:street":"Sint-Elooisdreef",
    "iso:country":"BE",
    "sg:address":"Sint-elooisdreef 22",
    "sg:city":"Kortrijk",
    "sg:orig_category":"Avocats and conseillers juridiques",
    "sg:phone":"+32 56 35 06 48",
    "sg:postcode":"8500",
    "sg:province":"West-Vlaanderen",
    "wof:name":"P. Delafontaine",
    "wof:placetype":"venue"
},
  "geometry": {"coordinates":[3.2700150013,50.8395881653],"type":"Point"}
}