{
  "type": "Feature",
  "properties": {
    "addr:full":"Grote Hemmenweg 50 Zonhoven Limburg 3520",
    "addr:housenumber":"50",
    "addr:postcode":"3520",
    "addr:street":"Grote Hemmenweg",
    "iso:country":"BE",
    "sg:address":"Grote Hemmenweg 50",
    "sg:city":"Zonhoven",
    "sg:orig_category":"Installation \u00e9lectrique r\u00e9sidentielle",
    "sg:phone":"+32 11 81 86 23",
    "sg:postcode":"3520",
    "sg:province":"Limburg",
    "wof:name":"Elektro Thuwis",
    "wof:placetype":"venue"
},
  "geometry": {"coordinates":[5.3757767677,50.9941673279],"type":"Point"}
}