{
  "type": "Feature",
  "properties": {
    "addr:full":"Rue D'armenti\u00c8res 403 Bizet Hainaut 7783",
    "addr:housenumber":"403",
    "addr:postcode":"7783",
    "addr:street":"Rue D'Armentie \u0300Res;Bizet Hainaut",
    "iso:country":"BE",
    "sg:address":"Rue D'armenti\u00c8res 403",
    "sg:city":"Bizet",
    "sg:orig_category":"Reisbureaus",
    "sg:phone":"+32 56 58 74 41",
    "sg:postcode":"7783",
    "sg:province":"Hainaut",
    "wof:name":"Lys Travel",
    "wof:placetype":"venue"
},
  "geometry": {"coordinates":[2.8834369183,50.7067222595],"type":"Point"}
}