{
  "type": "Feature",
  "properties": {
    "iso:country":"BE",
    "sg:address":"Schurhoven 36",
    "sg:city":"Sint-truiden",
    "sg:classifiers":[
        {
            "category":"Restaurant",
            "type":"Food & Drink"
        }
    ],
    "sg:phone":"+32 11 68 64 11",
    "sg:postcode":"3800",
    "sg:province":"Limburg",
    "sg:tags":[
        "caf\u00e9s"
    ],
    "wof:name":"Taverne Casteleyn",
    "wof:placetype":"venue"
},
  "geometry": {"coordinates":[5.1930818558,50.8194274902],"type":"Point"}
}