{
  "type": "Feature",
  "properties": {
    "addr:full":"Congresstraat 5-7 Brussel/bruxelles Bruxelles-Capitale 1000",
    "addr:housenumber":"5-7",
    "addr:postcode":"1000",
    "addr:street":"Congresstraat;/",
    "iso:country":"BE",
    "sg:address":"Congresstraat 5-7",
    "sg:city":"Brussel/bruxelles",
    "sg:orig_category":"Sociale secretariaten",
    "sg:phone":"+32 2 223 24 68",
    "sg:postcode":"1000",
    "sg:province":"Bruxelles-Capitale",
    "wof:name":"Kinderbijslagfonds Kbl",
    "wof:placetype":"venue"
},
  "geometry": {"coordinates":[4.364440918,50.8497428894],"type":"Point"}
}