{
  "type": "Feature",
  "properties": {
    "addr:full":"Isidoor Crokaertstraat 290 Asse Vlaams-Brabant 1731",
    "addr:housenumber":"290",
    "addr:postcode":"1731",
    "addr:street":"Isidoor Crokaertstraat",
    "iso:country":"BE",
    "sg:address":"Isidoor Crokaertstraat 290",
    "sg:city":"Asse",
    "sg:orig_category":"Plaatsen van vloer- and muurbekleding Schilders",
    "sg:phone":"+32 2 463 27 85",
    "sg:postcode":"1731",
    "sg:province":"Vlaams-Brabant",
    "wof:name":"Marc De Vleeschauwer",
    "wof:placetype":"venue"
},
  "geometry": {"coordinates":[4.2580099106,50.8963890076],"type":"Point"}
}