{
  "type": "Feature",
  "properties": {
    "iso:country":"BE",
    "sg:address":"Rue Collebrine 7",
    "sg:city":"Chaumont-gistoux",
    "sg:orig_category":"Non-Classified Establishments",
    "sg:phone":"+32 10 24 71 61",
    "sg:postcode":"1325",
    "sg:province":"Brabant Wallon",
    "wof:name":"Pro-vera Sprl",
    "wof:placetype":"venue"
},
  "geometry": {"coordinates":[4.6954197884,50.687953949],"type":"Point"}
}