{
  "type": "Feature",
  "properties": {
    "addr:full":"Dorpsplein 25 Kortenberg Vlaams-Brabant 3071",
    "addr:housenumber":"25",
    "addr:postcode":"3071",
    "addr:street":"Dorpsplein;Vlaams-Brabant",
    "iso:country":"BE",
    "sg:address":"Dorpsplein 25",
    "sg:city":"Kortenberg",
    "sg:orig_category":"Banques and organismes de cr\u00e9dit",
    "sg:phone":"+32 2 759 91 05",
    "sg:postcode":"3071",
    "sg:province":"Vlaams-Brabant",
    "wof:name":"Fortis",
    "wof:placetype":"venue"
},
  "geometry": {"coordinates":[4.5583171844,50.904209137],"type":"Point"}
}