{
  "type": "Feature",
  "properties": {
    "iso:country":"BE",
    "sg:address":"Rue De La Cure 15",
    "sg:city":"Viroinval (oignies-en-thi\u00e9rache)",
    "sg:classifiers":[
        {
            "category":"Bakery",
            "type":"Food & Drink"
        }
    ],
    "sg:phone":"+32 60 39 97 19",
    "sg:postcode":"5670",
    "sg:province":"Namur",
    "sg:tags":[
        "confectioner",
        "baker"
    ],
    "wof:name":"Chez Caro",
    "wof:placetype":"venue"
},
  "geometry": {"coordinates":[4.6394000053,50.0235099792],"type":"Point"}
}