{
  "type": "Feature",
  "properties": {
    "iso:country":"BE",
    "sg:address":"Gierlebaan 48",
    "sg:city":"Lille",
    "sg:classifiers":[
        {
            "category":"Food & Beverages",
            "subcategory":"Meat & Fish",
            "type":"Retail Goods"
        }
    ],
    "sg:phone":"+32 14 26 19 74",
    "sg:postcode":"2275",
    "sg:province":"Antwerpen",
    "sg:tags":[
        "poultry",
        "whol",
        "game",
        "-"
    ],
    "wof:name":"Mannaerts J",
    "wof:placetype":"venue"
},
  "geometry": {"coordinates":[4.8288111687,51.2447128296],"type":"Point"}
}