{
  "type": "Feature",
  "properties": {
    "iso:country":"BE",
    "sg:address":"Rijksweg 180",
    "sg:city":"Dilsen-stokkem (dilsen)",
    "sg:classifiers":[
        {
            "category":"Building & Trades",
            "subcategory":"Plumbing",
            "type":"Services"
        }
    ],
    "sg:phone":"+32 89 75 62 25",
    "sg:postcode":"3650",
    "sg:province":"Limburg",
    "sg:tags":[
        "repair",
        "mainten",
        "-",
        "central",
        "heating"
    ],
    "wof:name":"Kvs Dilsen Nv",
    "wof:placetype":"venue"
},
  "geometry": {"coordinates":[5.7434449196,51.0565567017],"type":"Point"}
}