{
  "type": "Feature",
  "properties": {
    "iso:country":"BE",
    "sg:address":"Eernegemsestraat 113",
    "sg:city":"Zedelgem",
    "sg:orig_category":"Loodgieterij, verwarming and sanitaire installaties",
    "sg:phone":"+32 50 20 81 19",
    "sg:postcode":"8211",
    "sg:province":"West-Vlaanderen",
    "wof:name":"Vanheste Roger",
    "wof:placetype":"venue"
},
  "geometry": {"coordinates":[3.0889649391,51.1200408936],"type":"Point"}
}