{
  "type": "Feature",
  "properties": {
    "addr:full":"Rue \u00c0 Paniers 85 Colfontaine Hainaut 7340",
    "addr:housenumber":"85",
    "addr:postcode":"7340",
    "addr:street":"Rue A\u0300 Paniers",
    "iso:country":"BE",
    "sg:address":"Rue \u00c0 Paniers 85",
    "sg:city":"Colfontaine",
    "sg:orig_category":"Salles de spectacles",
    "sg:phone":"+32 65 67 15 44",
    "sg:postcode":"7340",
    "sg:province":"Hainaut",
    "wof:name":"Atis Th\u00c9\u00c2tre",
    "wof:placetype":"venue"
},
  "geometry": {"coordinates":[3.8395700455,50.4096755981],"type":"Point"}
}