{
  "type": "Feature",
  "properties": {
    "iso:country":"BE",
    "sg:address":"Rue Edith Cavell 40",
    "sg:city":"Ukkel/uccle",
    "sg:orig_category":"M\u00e9decins and sp\u00e9cialistes",
    "sg:phone":"+32 2 346 99 39",
    "sg:postcode":"1180",
    "sg:province":"Bruxelles-Capitale",
    "wof:name":"Ivan Vermeulen",
    "wof:placetype":"venue"
},
  "geometry": {"coordinates":[4.3571858406,50.8127975464],"type":"Point"}
}