{
  "type": "Feature",
  "properties": {
    "iso:country":"BE",
    "sg:address":"Langestraat 21-23",
    "sg:city":"Lebbeke",
    "sg:classifiers":[
        {
            "category":"Retail",
            "subcategory":"Repair Shop",
            "type":"Services"
        }
    ],
    "sg:phone":"+32 52 41 06 27",
    "sg:postcode":"9280",
    "sg:province":"Oost-Vlaanderen",
    "sg:tags":[
        "denture"
    ],
    "wof:name":"Tandlabo Jacops",
    "wof:placetype":"venue"
},
  "geometry": {"coordinates":[4.1463241577,50.9992980957],"type":"Point"}
}