{
  "type": "Feature",
  "properties": {
    "iso:country":"BE",
    "sg:address":"Chauss\u00e9e De Charleroi 93",
    "sg:city":"Beaumont (str\u00e9e)",
    "sg:classifiers":[
        {
            "category":"Home & Garden",
            "subcategory":"Garden Supply",
            "type":"Retail Goods"
        }
    ],
    "sg:phone":"+32 71 53 44 84",
    "sg:postcode":"6511",
    "sg:province":"Hainaut",
    "sg:tags":[
        "lawn",
        "mower"
    ],
    "wof:name":"Gillard Christian",
    "wof:placetype":"venue"
},
  "geometry": {"coordinates":[4.2807421684,50.2678451538],"type":"Point"}
}