{
  "type": "Feature",
  "properties": {
    "iso:country":"BE",
    "sg:address":"Poederleese Weg 43",
    "sg:city":"Lille",
    "sg:classifiers":[
        {
            "category":"Bars & Pubs",
            "type":"Food & Drink"
        }
    ],
    "sg:phone":"+32 14 88 01 39",
    "sg:postcode":"2275",
    "sg:province":"Antwerpen",
    "wof:name":"De Sporthal",
    "wof:placetype":"venue"
},
  "geometry": {"coordinates":[4.8266282082,51.2362785339],"type":"Point"}
}