{
  "type": "Feature",
  "properties": {
    "iso:country":"BE",
    "sg:address":"Avenue Adolphe Buyl 110",
    "sg:city":"Elsene/ixelles",
    "sg:orig_category":"S\u00e9curit\u00e9 sociale",
    "sg:phone":"+32 2 647 64 28",
    "sg:postcode":"1050",
    "sg:province":"Bruxelles-Capitale",
    "wof:name":"Mutualit\u00c9 Chr\u00c9tienne Saint-michel",
    "wof:placetype":"venue"
},
  "geometry": {"coordinates":[4.383482933,50.8158531189],"type":"Point"}
}