{
  "type": "Feature",
  "properties": {
    "iso:country":"BE",
    "sg:address":"Rue Visart De Bocarm\u00c9 66",
    "sg:city":"Namur",
    "sg:orig_category":"Elektrische installaties voor woningen Verlichting and huishoudartikelen",
    "sg:phone":"+32 81 56 65 20",
    "sg:postcode":"5020",
    "sg:province":"Namur",
    "wof:name":"Philippe Bertrand",
    "wof:placetype":"venue"
},
  "geometry": {"coordinates":[4.7952418327,50.4352035522],"type":"Point"}
}