{
  "type": "Feature",
  "properties": {
    "iso:country":"BE",
    "sg:address":"Stuiverstraat 354",
    "sg:city":"Oostende",
    "sg:classifiers":[
        {
            "category":"Health Services",
            "subcategory":"Health Practitioner",
            "type":"Services"
        }
    ],
    "sg:phone":"+32 59 70 70 19",
    "sg:postcode":"8400",
    "sg:province":"West-Vlaanderen",
    "sg:tags":[
        "physiotherapist"
    ],
    "wof:name":"Lingier Rik",
    "wof:placetype":"venue"
},
  "geometry": {"coordinates":[2.9086999893,51.2146186829],"type":"Point"}
}