{
  "type": "Feature",
  "properties": {
    "iso:country":"BE",
    "sg:address":"Mirakelstraat 120",
    "sg:city":"Waregem",
    "sg:orig_category":"M\u00e9decins and sp\u00e9cialistes",
    "sg:phone":"+32 56 60 85 35",
    "sg:postcode":"8790",
    "sg:province":"West-Vlaanderen",
    "wof:name":"Martine Bourgeois",
    "wof:placetype":"venue"
},
  "geometry": {"coordinates":[3.3983280659,50.8708152771],"type":"Point"}
}