{
  "type": "Feature",
  "properties": {
    "iso:country":"BE",
    "sg:address":"Gelei 4",
    "sg:city":"Lochristi",
    "sg:orig_category":"Rundveehouders Varkenskwekers",
    "sg:phone":"+32 9 355 81 12",
    "sg:postcode":"9080",
    "sg:province":"Oost-Vlaanderen",
    "wof:name":"Hilaire Polfliet",
    "wof:placetype":"venue"
},
  "geometry": {"coordinates":[3.8345279694,51.1027755737],"type":"Point"}
}