{
  "type": "Feature",
  "properties": {
    "addr:full":"Barbierstraat 9 Kruibeke Oost-Vlaanderen 9150",
    "addr:housenumber":"9",
    "addr:postcode":"9150",
    "addr:street":"Barbierstraat",
    "iso:country":"BE",
    "sg:address":"Barbierstraat 9",
    "sg:city":"Kruibeke",
    "sg:orig_category":"Herstellingen and onderhoud aan huis voor voertuigen Herstellingen and onderhoud van auto's Voertuig",
    "sg:phone":"+32 3 774 27 22",
    "sg:postcode":"9150",
    "sg:province":"Oost-Vlaanderen",
    "wof:name":"Garage Carrosserie Maes",
    "wof:placetype":"venue"
},
  "geometry": {"coordinates":[4.2989010811,51.1548805237],"type":"Point"}
}