{
  "type": "Feature",
  "properties": {
    "addr:full":"Rue Chants-d'oiseaux 40 Gembloux Namur 5030",
    "addr:housenumber":"40",
    "addr:postcode":"5030",
    "addr:street":"Rue Chants-D'Oiseaux;Namur",
    "iso:country":"BE",
    "sg:address":"Rue Chants-d'oiseaux 40",
    "sg:city":"Gembloux",
    "sg:classifiers":[
        {
            "category":"Utilities",
            "subcategory":"Cable",
            "type":"Services"
        }
    ],
    "sg:phone":"+32 81 61 48 77",
    "sg:postcode":"5030",
    "sg:province":"Namur",
    "sg:tags":[
        "steel",
        "wire"
    ],
    "wof:name":"Omnifil Sprl",
    "wof:placetype":"venue"
},
  "geometry": {"coordinates":[4.7109851837,50.5542678833],"type":"Point"}
}