{
  "type": "Feature",
  "properties": {
    "iso:country":"BE",
    "sg:address":"Martelaarslaan 194",
    "sg:city":"Gent",
    "sg:orig_category":"Newspapers, magazines, periodicals - Distribution",
    "sg:phone":"+32 9 225 17 52",
    "sg:postcode":"9000",
    "sg:province":"Oost-Vlaanderen",
    "wof:name":"Winkeltje ('t)",
    "wof:placetype":"venue"
},
  "geometry": {"coordinates":[3.7120919228,51.0467567444],"type":"Point"}
}