{
  "type": "Feature",
  "properties": {
    "iso:country":"BE",
    "sg:address":"Rue Du Ruisseau 2",
    "sg:city":"Dinant",
    "sg:classifiers":[
        {
            "category":"Insurance",
            "subcategory":"Life Insurance",
            "type":"Services"
        }
    ],
    "sg:phone":"+32 82 22 79 88",
    "sg:postcode":"5500",
    "sg:province":"Namur",
    "sg:tags":[
        "assurance"
    ],
    "wof:name":"G. Fr\u00c8re",
    "wof:placetype":"venue"
},
  "geometry": {"coordinates":[4.9103970528,50.2598686218],"type":"Point"}
}