{
  "type": "Feature",
  "properties": {
    "iso:country":"BE",
    "sg:address":"Wijerstraat 86",
    "sg:city":"Hasselt",
    "sg:orig_category":"Jardinage. Installation de menuiserie en bois and plastique",
    "sg:phone":"+32 11 59 34 43",
    "sg:postcode":"3510",
    "sg:province":"Limburg",
    "wof:name":"Marcel Leurs",
    "wof:placetype":"venue"
},
  "geometry": {"coordinates":[5.2270021439,50.938583374],"type":"Point"}
}