{
  "type": "Feature",
  "properties": {
    "addr:full":"Rue Du Tram 6 Fleurus Hainaut 6224",
    "addr:housenumber":"6",
    "addr:postcode":"6224",
    "addr:street":"Rue Du Tram",
    "iso:country":"BE",
    "sg:address":"Rue Du Tram 6",
    "sg:city":"Fleurus",
    "sg:orig_category":"Banques and organismes de cr\u00e9dit",
    "sg:phone":"+32 71 81 19 46",
    "sg:postcode":"6224",
    "sg:province":"Hainaut",
    "wof:name":"Bbl",
    "wof:placetype":"venue"
},
  "geometry": {"coordinates":[4.586286068,50.4710006714],"type":"Point"}
}