{
  "type": "Feature",
  "properties": {
    "addr:full":"Dorpplaats 6 Lo-reninge (reninge) West-Vlaanderen 8647",
    "addr:housenumber":"6",
    "addr:postcode":"8647",
    "addr:street":"Dorpplaats",
    "iso:country":"BE",
    "sg:address":"Dorpplaats 6",
    "sg:city":"Lo-reninge (reninge)",
    "sg:classifiers":[
        {
            "category":"Bars & Pubs",
            "type":"Food & Drink"
        }
    ],
    "sg:phone":"+32 57 40 11 88",
    "sg:postcode":"8647",
    "sg:province":"West-Vlaanderen",
    "wof:name":"Hemel (de)",
    "wof:placetype":"venue"
},
  "geometry": {"coordinates":[2.788932085,50.9478530884],"type":"Point"}
}