{
  "type": "Feature",
  "properties": {
    "iso:country":"BE",
    "sg:address":"Rue Haute 5",
    "sg:city":"Merbes-le-ch\u00c2teau",
    "sg:orig_category":"Biblioth\u00e8ques and archives publiques",
    "sg:phone":"+32 71 52 69 46",
    "sg:postcode":"6567",
    "sg:province":"Hainaut",
    "wof:name":"Biblioth\u00c8que Publique",
    "wof:placetype":"venue"
},
  "geometry": {"coordinates":[4.1639451981,50.3247146606],"type":"Point"}
}