{
  "type": "Feature",
  "properties": {
    "iso:country":"BE",
    "sg:address":"Rue De La R\u00c9gence 33",
    "sg:city":"Brussel/bruxelles",
    "sg:orig_category":"Traducteurs and interpr\u00e8tes",
    "sg:phone":"+32 2 502 19 61",
    "sg:postcode":"1000",
    "sg:province":"Bruxelles-Capitale",
    "wof:name":"Deceunynck P. Cbtip/bkvtf",
    "wof:placetype":"venue"
},
  "geometry": {"coordinates":[4.3546910286,50.8390769958],"type":"Point"}
}