{
  "type": "Feature",
  "properties": {
    "addr:full":"Baron Vander Bruggenlaan 18 Wingene West-Vlaanderen 8750",
    "addr:housenumber":"18",
    "addr:postcode":"8750",
    "addr:street":"Baron Vander Bruggenlaan",
    "iso:country":"BE",
    "sg:address":"Baron Vander Bruggenlaan 18",
    "sg:city":"Wingene",
    "sg:orig_category":"Non-Classified Establishments",
    "sg:phone":"+32 51 65 89 63",
    "sg:postcode":"8750",
    "sg:province":"West-Vlaanderen",
    "wof:name":"Vleeshandel Puype",
    "wof:placetype":"venue"
},
  "geometry": {"coordinates":[3.304254055,51.0815696716],"type":"Point"}
}