{
  "type": "Feature",
  "properties": {
    "addr:full":"Hendrik Van Veldekestr. 55 Lommel Limburg 3920",
    "addr:housenumber":"55",
    "addr:postcode":"3920",
    "addr:street":"Hendrik Van Veldekestr.",
    "iso:country":"BE",
    "sg:address":"Hendrik Van Veldekestr. 55",
    "sg:city":"Lommel",
    "sg:orig_category":"Enseignement maternel and primaire",
    "sg:phone":"+32 11 54 44 48",
    "sg:postcode":"3920",
    "sg:province":"Limburg",
    "wof:name":"B.s.g.o. Heeserbergen",
    "wof:placetype":"venue"
},
  "geometry": {"coordinates":[5.2909450531,51.2297363281],"type":"Point"}
}