{
  "type": "Feature",
  "properties": {
    "addr:full":"Mechelsesteenweg 476 Edegem Antwerpen 2650",
    "addr:housenumber":"476",
    "addr:postcode":"2650",
    "addr:street":"Mechelsesteenweg",
    "iso:country":"BE",
    "sg:address":"Mechelsesteenweg 476",
    "sg:city":"Edegem",
    "sg:orig_category":"Installation de menuiserie m\u00e9tallique",
    "sg:phone":"+32 3 230 19 55",
    "sg:postcode":"2650",
    "sg:province":"Antwerpen",
    "wof:name":"Boonen",
    "wof:placetype":"venue"
},
  "geometry": {"coordinates":[4.4554481506,51.1636428833],"type":"Point"}
}