{
  "type": "Feature",
  "properties": {
    "iso:country":"BE",
    "sg:address":"Rue Du Routeu 27",
    "sg:city":"Libramont-chevigny",
    "sg:orig_category":"Dierenartsen",
    "sg:phone":"+32 61 68 86 66",
    "sg:postcode":"6800",
    "sg:province":"Luxembourg",
    "wof:name":"Marc Coenen",
    "wof:placetype":"venue"
},
  "geometry": {"coordinates":[5.3761348724,49.9199943542],"type":"Point"}
}