{
  "type": "Feature",
  "properties": {
    "addr:full":"Rue Du Tilleul 269 Bruxelles (evere) Bruxelles-Capitale 1140",
    "addr:housenumber":"269",
    "addr:postcode":"1140",
    "addr:street":"Rue Du Tilleul",
    "iso:country":"BE",
    "sg:address":"Rue Du Tilleul 269",
    "sg:city":"Bruxelles (evere)",
    "sg:classifiers":[
        {
            "category":"Autos & Motor Vehicles",
            "subcategory":"Fuel & Gas Station",
            "type":"Retail Goods"
        }
    ],
    "sg:phone":"+32 2 245 26 51",
    "sg:postcode":"1140",
    "sg:province":"Bruxelles-Capitale",
    "wof:name":"Seca",
    "wof:placetype":"venue"
},
  "geometry": {"coordinates":[4.3952989578,50.870639801],"type":"Point"}
}