{
  "type": "Feature",
  "properties": {
    "iso:country":"BE",
    "sg:address":"Leiestraat 75",
    "sg:city":"Lauwe",
    "sg:classifiers":[
        {
            "category":"Manufacturing",
            "subcategory":"Furniture",
            "type":"Manufacturing & Wholesale Goods"
        }
    ],
    "sg:phone":"+32 56 41 35 28",
    "sg:postcode":"8930",
    "sg:province":"West-Vlaanderen",
    "sg:tags":[
        "fabric"
    ],
    "wof:name":"Adeka Textiles Nv",
    "wof:placetype":"venue"
},
  "geometry": {"coordinates":[3.186371088,50.799118042],"type":"Point"}
}