{
  "type": "Feature",
  "properties": {
    "iso:country":"BE",
    "sg:address":"Spedamstraat 16",
    "sg:city":"Buggenhout",
    "sg:orig_category":"Paramedische behandelingen",
    "sg:phone":"+32 52 33 69 78",
    "sg:postcode":"9255",
    "sg:province":"Oost-Vlaanderen",
    "wof:name":"Team Verpleegkundigen",
    "wof:placetype":"venue"
},
  "geometry": {"coordinates":[4.2364897728,51.0289802551],"type":"Point"}
}