{
  "type": "Feature",
  "properties": {
    "iso:country":"BE",
    "sg:address":"Coupure Rechts 158",
    "sg:city":"Gent",
    "sg:orig_category":"Deurwaarders",
    "sg:phone":"+32 9 225 04 55",
    "sg:postcode":"9000",
    "sg:province":"Oost-Vlaanderen",
    "wof:name":"Yvan Delie",
    "wof:placetype":"venue"
},
  "geometry": {"coordinates":[3.714261055,51.0481567383],"type":"Point"}
}