{
  "type": "Feature",
  "properties": {
    "addr:full":"Place Des Bienfaiteurs 4 Schaarbeek/schaerbeek Bruxelles-Capitale 1030",
    "addr:housenumber":"4",
    "addr:postcode":"1030",
    "addr:street":"Place Des Bienfaiteurs",
    "iso:country":"BE",
    "sg:address":"Place Des Bienfaiteurs 4",
    "sg:city":"Schaarbeek/schaerbeek",
    "sg:orig_category":"Messageries",
    "sg:phone":"+32 2 242 09 28",
    "sg:postcode":"1030",
    "sg:province":"Bruxelles-Capitale",
    "wof:name":"Extenso Service",
    "wof:placetype":"venue"
},
  "geometry": {"coordinates":[4.3835158348,50.8578681946],"type":"Point"}
}