{
  "type": "Feature",
  "properties": {
    "addr:full":"Rue Des Bois 42 Trazegnies Hainaut 6183",
    "addr:housenumber":"42",
    "addr:postcode":"6183",
    "addr:street":"Rue Des Bois",
    "iso:country":"BE",
    "sg:address":"Rue Des Bois 42",
    "sg:city":"Trazegnies",
    "sg:orig_category":"Etablissements Erotiques",
    "sg:phone":"+32 71 45 43 10",
    "sg:postcode":"6183",
    "sg:province":"Hainaut",
    "wof:name":"Secret D'alc\u00d4ve",
    "wof:placetype":"venue"
},
  "geometry": {"coordinates":[4.3287639618,50.4705162048],"type":"Point"}
}