{
  "type": "Feature",
  "properties": {
    "iso:country":"BE",
    "sg:address":"Sterrestraat 177",
    "sg:city":"Lokeren",
    "sg:orig_category":"Cr\u00e9meries",
    "sg:phone":"+32 9 348 12 38",
    "sg:postcode":"9160",
    "sg:province":"Oost-Vlaanderen",
    "wof:name":"R. De Waele",
    "wof:placetype":"venue"
},
  "geometry": {"coordinates":[3.9854240417,51.095867157],"type":"Point"}
}