{
  "type": "Feature",
  "properties": {
    "addr:full":"Rue D'eynatten 10 Raeren/raeren Li\u00e8ge 4730",
    "addr:housenumber":"10",
    "addr:postcode":"4730",
    "addr:street":"Rue D'Eynatten",
    "iso:country":"BE",
    "sg:address":"Rue D'eynatten 10",
    "sg:city":"Raeren/raeren",
    "sg:orig_category":"Installation de menuiserie en bois and plastique",
    "sg:phone":"+32 87 85 24 39",
    "sg:postcode":"4730",
    "sg:province":"Li\u00e8ge",
    "wof:name":"Bernd Toerkel",
    "wof:placetype":"venue"
},
  "geometry": {"coordinates":[6.1032571793,50.6801300049],"type":"Point"}
}