{
  "type": "Feature",
  "properties": {
    "iso:country":"BE",
    "sg:address":"Kasteeldreef 43",
    "sg:city":"Laarne",
    "sg:orig_category":"Boekhouders Immobili\u00ebnkantoren",
    "sg:phone":"+32 9 230 37 22",
    "sg:postcode":"9270",
    "sg:province":"Oost-Vlaanderen",
    "wof:name":"Immo-bel",
    "wof:placetype":"venue"
},
  "geometry": {"coordinates":[3.8462810516,51.0288314819],"type":"Point"}
}