{
  "type": "Feature",
  "properties": {
    "iso:country":"BE",
    "sg:address":"Battelsesteenweg 458",
    "sg:city":"Mechelen",
    "sg:orig_category":"Taxi's Taxi's speciale diensten",
    "sg:phone":"+32 15 27 04 00",
    "sg:postcode":"2800",
    "sg:province":"Antwerpen",
    "wof:name":"Ax6",
    "wof:placetype":"venue"
},
  "geometry": {"coordinates":[4.4517087936,51.0374031067],"type":"Point"}
}