{
  "type": "Feature",
  "properties": {
    "addr:full":"Six-planes 25 Bievre Namur 5555",
    "addr:housenumber":"25",
    "addr:postcode":"5555",
    "addr:street":"Six-Planes",
    "iso:country":"BE",
    "sg:address":"Six-planes 25",
    "sg:city":"Bievre",
    "sg:classifiers":[
        {
            "category":"Cafe",
            "type":"Food & Drink"
        }
    ],
    "sg:phone":"+32 61 50 16 60",
    "sg:postcode":"5555",
    "sg:province":"Namur",
    "sg:tags":[
        "caf\u00e9s"
    ],
    "wof:name":"Laurent Tomasi",
    "wof:placetype":"venue"
},
  "geometry": {"coordinates":[4.9714770317,49.8804512024],"type":"Point"}
}