{
  "type": "Feature",
  "properties": {
    "iso:country":"BE",
    "sg:address":"Rue Arthur-patiny 14",
    "sg:city":"Floreffe",
    "sg:orig_category":"Entretien and r\u00e9parations de voitures",
    "sg:phone":"+32 81 45 02 38",
    "sg:postcode":"5150",
    "sg:province":"Namur",
    "wof:name":"Benoit Patout",
    "wof:placetype":"venue"
},
  "geometry": {"coordinates":[4.7614769936,50.4128341675],"type":"Point"}
}