{
  "type": "Feature",
  "properties": {
    "addr:full":"Rue Edouard Colson Loncin Li\u00e8ge 4431",
    "addr:postcode":"4431",
    "addr:street":"Rue Edouard Colson",
    "iso:country":"BE",
    "sg:address":"Rue Edouard Colson",
    "sg:city":"Loncin",
    "sg:orig_category":"Diensten voor huisdieren Huisdieren and benodigdheden Royal Canin",
    "sg:phone":"+32 4 247 47 46",
    "sg:postcode":"4431",
    "sg:province":"Li\u00e8ge",
    "wof:name":"Ets Animal Confort",
    "wof:placetype":"venue"
},
  "geometry": {"coordinates":[5.5013899803,50.6678009033],"type":"Point"}
}