{
  "type": "Feature",
  "properties": {
    "addr:full":"P.vanhoudtstraat 84 Beringen Limburg 3582",
    "addr:housenumber":"84",
    "addr:postcode":"3582",
    "addr:street":"P.Vanhoudtstraat",
    "iso:country":"BE",
    "sg:address":"P.vanhoudtstraat 84",
    "sg:city":"Beringen",
    "sg:orig_category":"Supermarch\u00e9s",
    "sg:postcode":"3582",
    "sg:province":"Limburg",
    "wof:name":"Aldi",
    "wof:placetype":"venue"
},
  "geometry": {"coordinates":[5.2708749771,51.0595359802],"type":"Point"}
}