{
  "type": "Feature",
  "properties": {
    "iso:country":"BE",
    "sg:address":"Rue De La Procession 12",
    "sg:city":"Ath",
    "sg:orig_category":"Installatie van houten of kunststof schrijnwerk",
    "sg:phone":"+32 68 57 20 34",
    "sg:postcode":"7822",
    "sg:province":"Hainaut",
    "wof:name":"Wagnies Et Fils",
    "wof:placetype":"venue"
},
  "geometry": {"coordinates":[3.8452620506,50.6482391357],"type":"Point"}
}