{
  "type": "Feature",
  "properties": {
    "addr:full":"Leenmolenstraat 92 Wingene West-Vlaanderen 8750",
    "addr:housenumber":"92",
    "addr:postcode":"8750",
    "addr:street":"Leenmolenstraat",
    "iso:country":"BE",
    "sg:address":"Leenmolenstraat 92",
    "sg:city":"Wingene",
    "sg:orig_category":"Gespecialiseerde residenti\u00eble bouw Woningbouw",
    "sg:phone":"+32 51 65 72 83",
    "sg:postcode":"8750",
    "sg:province":"West-Vlaanderen",
    "wof:name":"Dirk Vlaeminck",
    "wof:placetype":"venue"
},
  "geometry": {"coordinates":[3.2673380375,51.0729446411],"type":"Point"}
}