{
  "type": "Feature",
  "properties": {
    "addr:full":"Centrumlaan 38 Genk Limburg 3600",
    "addr:housenumber":"38",
    "addr:postcode":"3600",
    "addr:street":"Centrumlaan",
    "iso:country":"BE",
    "sg:address":"Centrumlaan 38",
    "sg:city":"Genk",
    "sg:classifiers":[
        {
            "category":"Restaurant",
            "type":"Food & Drink"
        }
    ],
    "sg:phone":"+32 89 36 28 92",
    "sg:postcode":"3600",
    "sg:province":"Limburg",
    "wof:name":"'t Pleintje",
    "wof:placetype":"venue"
},
  "geometry": {"coordinates":[5.4972419739,50.9648971558],"type":"Point"}
}