{
  "type": "Feature",
  "properties": {
    "addr:full":"Rue Max Buset 94 Flemalle Li\u00e8ge 4400",
    "addr:housenumber":"94",
    "addr:postcode":"4400",
    "addr:street":"Rue Max Buset",
    "iso:country":"BE",
    "sg:address":"Rue Max Buset 94",
    "sg:city":"Flemalle",
    "sg:orig_category":"Installation \u00e9lectrique r\u00e9sidentielle. Electrom\u00e9nager, t\u00e9l\u00e9visions and radios",
    "sg:phone":"+32 4 275 49 66",
    "sg:postcode":"4400",
    "sg:province":"Li\u00e8ge",
    "wof:name":"E.p.i.",
    "wof:placetype":"venue"
},
  "geometry": {"coordinates":[5.4201369286,50.5806121826],"type":"Point"}
}