{
  "type": "Feature",
  "properties": {
    "iso:country":"BE",
    "sg:address":"Moerkerkse Steenweg 185",
    "sg:city":"Brugge",
    "sg:orig_category":"Catering and organisatie van feesten Voedingsspeciaalzaken",
    "sg:phone":"+32 50 35 05 59",
    "sg:postcode":"8310",
    "sg:province":"West-Vlaanderen",
    "wof:name":"Traiteur De Terrine",
    "wof:placetype":"venue"
},
  "geometry": {"coordinates":[3.2503359318,51.2137145996],"type":"Point"}
}