{
  "type": "Feature",
  "properties": {
    "addr:full":"Rue Haute 84 Bassenge (eben-emael) Li\u00e8ge 4690",
    "addr:housenumber":"84",
    "addr:postcode":"4690",
    "addr:street":"Rue Haute;Eben-Emael",
    "iso:country":"BE",
    "sg:address":"Rue Haute 84",
    "sg:city":"Bassenge (eben-emael)",
    "sg:classifiers":[
        {
            "category":"Freight",
            "type":"Transportation"
        }
    ],
    "sg:phone":"+32 4 286 16 09",
    "sg:postcode":"4690",
    "sg:province":"Li\u00e8ge",
    "sg:tags":[
        "-",
        "transport"
    ],
    "wof:name":"Transnet Sprl",
    "wof:placetype":"venue"
},
  "geometry": {"coordinates":[5.6637029648,50.7898406982],"type":"Point"}
}