{
  "type": "Feature",
  "properties": {
    "addr:full":"Asterstraat 48 Knokke-heist (knokke) West-Vlaanderen 8300",
    "addr:housenumber":"48",
    "addr:postcode":"8300",
    "addr:street":"Asterstraat",
    "iso:country":"BE",
    "sg:address":"Asterstraat 48",
    "sg:city":"Knokke-heist (knokke)",
    "sg:classifiers":[
        {
            "category":"Building & Trades",
            "subcategory":"Construction",
            "type":"Services"
        }
    ],
    "sg:phone":"+32 50 51 07 42",
    "sg:postcode":"8300",
    "sg:province":"West-Vlaanderen",
    "sg:tags":[
        "carpenter"
    ],
    "wof:name":"Demunter W",
    "wof:placetype":"venue"
},
  "geometry": {"coordinates":[3.274725914,51.341632843],"type":"Point"}
}