{
  "type": "Feature",
  "properties": {
    "addr:full":"Rue Du Centre 80 Sprimont Li\u00e8ge 4140",
    "addr:housenumber":"80",
    "addr:postcode":"4140",
    "addr:street":"Rue Du Centre",
    "iso:country":"BE",
    "sg:address":"Rue Du Centre 80",
    "sg:city":"Sprimont",
    "sg:orig_category":"Pain, p\u00e2tisseries and confiseries",
    "sg:phone":"+32 4 382 12 14",
    "sg:postcode":"4140",
    "sg:province":"Li\u00e8ge",
    "wof:name":"Patrick Dachouffe",
    "wof:placetype":"venue"
},
  "geometry": {"coordinates":[5.6641879082,50.5014801025],"type":"Point"}
}