{
  "type": "Feature",
  "properties": {
    "addr:full":"Kerklei 18 Brecht Antwerpen 2960",
    "addr:housenumber":"18",
    "addr:postcode":"2960",
    "addr:street":"Kerklei",
    "iso:country":"BE",
    "sg:address":"Kerklei 18",
    "sg:city":"Brecht",
    "sg:orig_category":"Artsen and specialisten",
    "sg:phone":"+32 3 636 24 96",
    "sg:postcode":"2960",
    "sg:province":"Antwerpen",
    "wof:name":"Consultatiebur.jonge Kind",
    "wof:placetype":"venue"
},
  "geometry": {"coordinates":[4.5743432045,51.2922744751],"type":"Point"}
}