{
  "type": "Feature",
  "properties": {
    "addr:full":"Avenue D'auderghem 60b1 Etterbeek Bruxelles-Capitale 1040",
    "addr:housenumber":"60b1",
    "addr:postcode":"1040",
    "addr:street":"Avenue D'Auderghem",
    "iso:country":"BE",
    "sg:address":"Avenue D'auderghem 60b1",
    "sg:city":"Etterbeek",
    "sg:orig_category":"Elektrische installaties voor woningen Industri\u00eble elektrische installaties Installatie van metalen ",
    "sg:phone":"+32 2 736 10 51",
    "sg:postcode":"1040",
    "sg:province":"Bruxelles-Capitale",
    "wof:name":"A.c. Consortium",
    "wof:placetype":"venue"
},
  "geometry": {"coordinates":[4.3847961426,50.8403816223],"type":"Point"}
}