{
  "type": "Feature",
  "properties": {
    "addr:full":"Chauss\u00c9e De Dinant 710 Namur Namur 5100",
    "addr:housenumber":"710",
    "addr:postcode":"5100",
    "addr:street":"Chausse\u0301E De Dinant",
    "iso:country":"BE",
    "sg:address":"Chauss\u00c9e De Dinant 710",
    "sg:city":"Namur",
    "sg:orig_category":"Rusthuizen and serviceflats",
    "sg:phone":"+32 81 46 18 61",
    "sg:postcode":"5100",
    "sg:province":"Namur",
    "wof:name":"Le Petit Bois",
    "wof:placetype":"venue"
},
  "geometry": {"coordinates":[4.864967823,50.430431366],"type":"Point"}
}