{
  "type": "Feature",
  "properties": {
    "iso:country":"BE",
    "sg:address":"Av. De La Porte De Hal 69",
    "sg:city":"Sint-gillis/saint-gilles",
    "sg:classifiers":[
        {
            "category":"Autos & Motor Vehicles",
            "subcategory":"Fuel & Gas Station",
            "type":"Retail Goods"
        }
    ],
    "sg:phone":"+32 2 537 52 55",
    "sg:postcode":"1060",
    "sg:province":"Bruxelles-Capitale",
    "sg:tags":[
        "stations-service",
        "carburants"
    ],
    "wof:name":"Fina",
    "wof:placetype":"venue"
},
  "geometry": {"coordinates":[4.3421602249,50.8302116394],"type":"Point"}
}