{
  "type": "Feature",
  "properties": {
    "iso:country":"BE",
    "sg:address":"Veldenstraat 14",
    "sg:city":"Retie",
    "sg:orig_category":"Pi\u00e8ces and accessoires de v\u00e9hicules automobiles Gr",
    "sg:phone":"+32 14 37 83 06",
    "sg:postcode":"2470",
    "sg:province":"Antwerpen",
    "wof:name":"Spooren Zetelovertrekken",
    "wof:placetype":"venue"
},
  "geometry": {"coordinates":[5.0784740448,51.2732887268],"type":"Point"}
}