{
  "type": "Feature",
  "properties": {
    "addr:full":"Peperstraat 2 Riemst Limburg 3770",
    "addr:housenumber":"2",
    "addr:postcode":"3770",
    "addr:street":"Peperstraat",
    "iso:country":"BE",
    "sg:address":"Peperstraat 2",
    "sg:city":"Riemst",
    "sg:classifiers":[
        {
            "category":"Cafe",
            "type":"Food & Drink"
        }
    ],
    "sg:phone":"+32 12 23 32 11",
    "sg:postcode":"3770",
    "sg:province":"Limburg",
    "sg:tags":[
        "caf\u00e9s"
    ],
    "wof:name":"Giselene Martens",
    "wof:placetype":"venue"
},
  "geometry": {"coordinates":[5.5621500015,50.7892684937],"type":"Point"}
}