{
  "type": "Feature",
  "properties": {
    "iso:country":"BE",
    "sg:address":"Rue De La Barri\u00e8re 40",
    "sg:city":"Seraing",
    "sg:classifiers":[
        {
            "category":"Banks & Credit Unions",
            "subcategory":"Investment Brokerage",
            "type":"Services"
        }
    ],
    "sg:phone":"+32 4 338 81 10",
    "sg:postcode":"4100",
    "sg:province":"Li\u00e8ge",
    "sg:tags":[
        "cast",
        "roller",
        "iron"
    ],
    "wof:name":"Akers Group, Sales & Marketing Europe",
    "wof:placetype":"venue"
},
  "geometry": {"coordinates":[5.4957838058,50.6054534912],"type":"Point"}
}