{
  "type": "Feature",
  "properties": {
    "addr:full":"Noorderlaan Asse Vlaams-Brabant 1730",
    "addr:postcode":"1730",
    "addr:street":"Noorderlaan",
    "iso:country":"BE",
    "sg:address":"Noorderlaan",
    "sg:city":"Asse",
    "sg:classifiers":[
        {
            "category":"Arena",
            "subcategory":"Sports Club",
            "type":"Entertainment"
        }
    ],
    "sg:phone":"+32 2 466 68 14",
    "sg:postcode":"1730",
    "sg:province":"Vlaams-Brabant",
    "sg:tags":[
        "terrain",
        "hors",
        "de",
        "installation",
        "sportifs"
    ],
    "wof:name":"Zellik Sport Fc",
    "wof:placetype":"venue"
},
  "geometry": {"coordinates":[4.1986222267,50.9108505249],"type":"Point"}
}