{
  "type": "Feature",
  "properties": {
    "addr:full":"Ernest Duezstraat 23 Halle Vlaams-Brabant 1500",
    "addr:housenumber":"23",
    "addr:postcode":"1500",
    "addr:street":"Duezstraat",
    "iso:country":"BE",
    "sg:address":"Ernest Duezstraat 23",
    "sg:city":"Halle",
    "sg:classifiers":[
        {
            "category":"Health Services",
            "subcategory":"Health Practitioner",
            "type":"Services"
        }
    ],
    "sg:phone":"+32 2 305 06 23",
    "sg:postcode":"1500",
    "sg:province":"Vlaams-Brabant",
    "sg:tags":[
        "physiotherapist"
    ],
    "wof:name":"Musch Peter",
    "wof:placetype":"venue"
},
  "geometry": {"coordinates":[4.2475218773,50.7220535278],"type":"Point"}
}