{
  "type": "Feature",
  "properties": {
    "iso:country":"BE",
    "sg:address":"Rue De Praetere 25b1",
    "sg:city":"Elsene/ixelles",
    "sg:orig_category":"Avocats and conseillers juridiques",
    "sg:phone":"+32 2 647 06 30",
    "sg:postcode":"1050",
    "sg:province":"Bruxelles-Capitale",
    "wof:name":"Evelyne Dammans",
    "wof:placetype":"venue"
},
  "geometry": {"coordinates":[4.3687229156,50.8165969849],"type":"Point"}
}