{
  "type": "Feature",
  "properties": {
    "addr:full":"Rue De Stinval 25 Sprimont (louveign\u00e9) Li\u00e8ge 4141",
    "addr:housenumber":"25",
    "addr:postcode":"4141",
    "addr:street":"Rue De Stinval",
    "iso:country":"BE",
    "sg:address":"Rue De Stinval 25",
    "sg:city":"Sprimont (louveign\u00e9)",
    "sg:classifiers":[
        {
            "category":"Health Services",
            "subcategory":"Doctor",
            "type":"Services"
        }
    ],
    "sg:phone":"+32 4 360 85 45",
    "sg:postcode":"4141",
    "sg:province":"Li\u00e8ge",
    "sg:tags":[
        "medicinephysicians",
        "surgeon"
    ],
    "wof:name":"De Leval J",
    "wof:placetype":"venue"
},
  "geometry": {"coordinates":[5.7102560997,50.5312538147],"type":"Point"}
}