{
  "type": "Feature",
  "properties": {
    "addr:full":"Torhoutse Steenweg 201 Brugge (sint-andries) West-Vlaanderen 8200",
    "addr:housenumber":"201",
    "addr:postcode":"8200",
    "addr:street":"Torhoutse Steenweg",
    "iso:country":"BE",
    "sg:address":"Torhoutse Steenweg 201",
    "sg:city":"Brugge (sint-andries)",
    "sg:classifiers":[
        {
            "category":"Building & Trades",
            "subcategory":"Construction",
            "type":"Services"
        }
    ],
    "sg:phone":"+32 50 39 26 06",
    "sg:postcode":"8200",
    "sg:province":"West-Vlaanderen",
    "sg:tags":[
        "insulation",
        "thermical",
        "work",
        "acoustical"
    ],
    "wof:name":"Isobert Bvba",
    "wof:placetype":"venue"
},
  "geometry": {"coordinates":[3.2011520863,51.1968765259],"type":"Point"}
}