{
  "type": "Feature",
  "properties": {
    "iso:country":"BE",
    "sg:address":"Kapelstraat 89",
    "sg:city":"Hoboken",
    "sg:orig_category":"Royal Canin. Animaux domestiques and accessoires",
    "sg:phone":"+32 3 828 32 55",
    "sg:postcode":"2660",
    "sg:province":"Antwerpen",
    "wof:name":"De Backer-groener Wonen Pvba",
    "wof:placetype":"venue"
},
  "geometry": {"coordinates":[4.3467869759,51.1746673584],"type":"Point"}
}