{
  "type": "Feature",
  "properties": {
    "addr:full":"Overleiestraat 108d Harelbeke West-Vlaanderen 8530",
    "addr:housenumber":"108d",
    "addr:postcode":"8530",
    "addr:street":"Overleiestraat",
    "iso:country":"BE",
    "sg:address":"Overleiestraat 108d",
    "sg:city":"Harelbeke",
    "sg:classifiers":[
        {
            "category":"Manufacturing",
            "subcategory":"Building Materials",
            "type":"Manufacturing & Wholesale Goods"
        }
    ],
    "sg:phone":"+32 56 70 56 84",
    "sg:postcode":"8530",
    "sg:province":"West-Vlaanderen",
    "sg:tags":[
        "fixture",
        "store"
    ],
    "wof:name":"Real Design Bvba",
    "wof:placetype":"venue"
},
  "geometry": {"coordinates":[3.3049030304,50.8607177734],"type":"Point"}
}