{
  "type": "Feature",
  "properties": {
    "iso:country":"BE",
    "sg:address":"Meerskant 8",
    "sg:city":"Lebbeke (denderbelle)",
    "sg:classifiers":[
        {
            "category":"Shopping",
            "subcategory":"Used Merchandise",
            "type":"Retail Goods"
        }
    ],
    "sg:phone":"+32 52 22 66 87",
    "sg:postcode":"9280",
    "sg:province":"Oost-Vlaanderen",
    "sg:tags":[
        "salvage",
        "surplus"
    ],
    "wof:name":"Dayyeh Company Bvba",
    "wof:placetype":"venue"
},
  "geometry": {"coordinates":[4.0877962112,50.9989891052],"type":"Point"}
}