{
  "type": "Feature",
  "properties": {
    "addr:full":"Mechelsesteenweg 66 Antwerpen Antwerpen 2018",
    "addr:housenumber":"66",
    "addr:postcode":"2018",
    "addr:street":"Mechelsesteenweg",
    "iso:country":"BE",
    "sg:address":"Mechelsesteenweg 66",
    "sg:city":"Antwerpen",
    "sg:orig_category":"Hypotheken and hypotheekbanken Levensverzekeringsmaatschappijen Verbruikerskredietinstellingen Verze",
    "sg:phone":"+32 3 247 35 11",
    "sg:postcode":"2018",
    "sg:province":"Antwerpen",
    "wof:name":"Naviga",
    "wof:placetype":"venue"
},
  "geometry": {"coordinates":[4.4089751244,51.208480835],"type":"Point"}
}