{
  "type": "Feature",
  "properties": {
    "addr:full":"Begoniastraat 7 Nazareth (eke) Oost-Vlaanderen 9810",
    "addr:housenumber":"7",
    "addr:postcode":"9810",
    "addr:street":"Begoniastraat",
    "iso:country":"BE",
    "sg:address":"Begoniastraat 7",
    "sg:city":"Nazareth (eke)",
    "sg:classifiers":[
        {
            "category":"Landmark",
            "subcategory":"City Walls",
            "type":"Public Place"
        }
    ],
    "sg:phone":"+32 9 385 57 11",
    "sg:postcode":"9810",
    "sg:province":"Oost-Vlaanderen",
    "sg:tags":[
        "covering"
    ],
    "wof:name":"Vandeweege Verfdistributie",
    "wof:placetype":"venue"
},
  "geometry": {"coordinates":[3.6587190628,50.9741439819],"type":"Point"}
}