{
  "type": "Feature",
  "properties": {
    "iso:country":"BE",
    "sg:address":"Rue Du Marais 155",
    "sg:city":"Qui\u00e9vrain",
    "sg:classifiers":[
        {
            "category":"Wholesale",
            "subcategory":"Beer",
            "type":"Manufacturing & Wholesale Goods"
        }
    ],
    "sg:phone":"+32 65 43 13 30",
    "sg:postcode":"7380",
    "sg:province":"Hainaut",
    "sg:tags":[
        "ale",
        "-"
    ],
    "wof:name":"Chr\u00e9tien R",
    "wof:placetype":"venue"
},
  "geometry": {"coordinates":[3.6847040653,50.4177894592],"type":"Point"}
}