{
  "type": "Feature",
  "properties": {
    "iso:country":"BE",
    "sg:address":"Dalstraat 22",
    "sg:city":"Elsene/ixelles",
    "sg:orig_category":"Diverse grafische activiteiten",
    "sg:phone":"+32 2 648 56 66",
    "sg:postcode":"1050",
    "sg:province":"Bruxelles-Capitale",
    "wof:name":"Manfred Hurrig Com. Vis.",
    "wof:placetype":"venue"
},
  "geometry": {"coordinates":[4.3713650703,50.8242492676],"type":"Point"}
}