{
  "type": "Feature",
  "properties": {
    "iso:country":"BE",
    "sg:address":"Eikvarenweg 26",
    "sg:city":"Gent",
    "sg:orig_category":"Traducteurs and interpr\u00e8tes. Agences de publicit\u00e9",
    "sg:phone":"+32 9 236 22 33",
    "sg:postcode":"9031",
    "sg:province":"Oost-Vlaanderen",
    "wof:name":"Brantra Vertaalbureau",
    "wof:placetype":"venue"
},
  "geometry": {"coordinates":[3.6384179592,51.0464859009],"type":"Point"}
}