{
  "type": "Feature",
  "properties": {
    "addr:full":"Bruggestraat 95 Ingelmunster West-Vlaanderen 8770",
    "addr:housenumber":"95",
    "addr:postcode":"8770",
    "addr:street":"Bruggestraat",
    "iso:country":"BE",
    "sg:address":"Bruggestraat 95",
    "sg:city":"Ingelmunster",
    "sg:orig_category":"Gespecialiseerde niet-residenti\u00eble bouw Metaalbehandeling and -bekleding",
    "sg:phone":"+32 51 30 34 85",
    "sg:postcode":"8770",
    "sg:province":"West-Vlaanderen",
    "wof:name":"Clarebout",
    "wof:placetype":"venue"
},
  "geometry": {"coordinates":[3.2535610199,50.9252204895],"type":"Point"}
}