{
  "type": "Feature",
  "properties": {
    "addr:full":"Kerkstraat 60 Sint-lievens-houtem (letterhoutem) Oost-Vlaanderen 9521",
    "addr:housenumber":"60",
    "addr:postcode":"9521",
    "addr:street":"Kerkstraat;Letterhoutem",
    "iso:country":"BE",
    "sg:address":"Kerkstraat 60",
    "sg:city":"Sint-lievens-houtem (letterhoutem)",
    "sg:classifiers":[
        {
            "category":"Professional",
            "subcategory":"Art Services",
            "type":"Services"
        }
    ],
    "sg:phone":"+32 53 63 11 92",
    "sg:postcode":"9521",
    "sg:province":"Oost-Vlaanderen",
    "sg:tags":[
        "children's",
        "animation"
    ],
    "wof:name":"Jeuk Animatiegroep Vzw",
    "wof:placetype":"venue"
},
  "geometry": {"coordinates":[3.8805570602,50.9297981262],"type":"Point"}
}