{
  "type": "Feature",
  "properties": {
    "iso:country":"BE",
    "sg:address":"Rue Du Vieux Mayeur 13",
    "sg:city":"Tubize (clabecq)",
    "sg:classifiers":[
        {
            "category":"Food & Beverages",
            "subcategory":"Groceries & Convenience Stores",
            "type":"Retail Goods"
        }
    ],
    "sg:phone":"+32 2 355 66 53",
    "sg:postcode":"1480",
    "sg:province":"Brabant Wallon",
    "sg:tags":[
        "grocer"
    ],
    "wof:name":"Calamera",
    "wof:placetype":"venue"
},
  "geometry": {"coordinates":[4.2251229286,50.683216095],"type":"Point"}
}