{
  "type": "Feature",
  "properties": {
    "addr:full":"Buizerdlei 13 Kapellen Antwerpen 2950",
    "addr:housenumber":"13",
    "addr:postcode":"2950",
    "addr:street":"Buizerdlei",
    "iso:country":"BE",
    "sg:address":"Buizerdlei 13",
    "sg:city":"Kapellen",
    "sg:classifiers":[
        {
            "category":"Taxi",
            "type":"Transportation"
        }
    ],
    "sg:phone":"+32 3 665 24 36",
    "sg:postcode":"2950",
    "sg:province":"Antwerpen",
    "wof:name":"Michel Lijssens",
    "wof:placetype":"venue"
},
  "geometry": {"coordinates":[4.4723777771,51.3378829956],"type":"Point"}
}