{
  "type": "Feature",
  "properties": {
    "iso:country":"BE",
    "sg:address":"Spelverstraat 26a",
    "sg:city":"Bilzen",
    "sg:classifiers":[
        {
            "category":"Ice Cream",
            "type":"Food & Drink"
        }
    ],
    "sg:phone":"+32 89 49 29 91",
    "sg:postcode":"3740",
    "sg:province":"Limburg",
    "sg:tags":[
        "lollipop"
    ],
    "wof:name":"De Palm Confiserie Nv",
    "wof:placetype":"venue"
},
  "geometry": {"coordinates":[5.5279688835,50.8722381592],"type":"Point"}
}