{
  "type": "Feature",
  "properties": {
    "addr:full":"Langerbrugsestraat 241 Evergem Oost-Vlaanderen 9940",
    "addr:housenumber":"241",
    "addr:postcode":"9940",
    "addr:street":"Langerbrugsestraat;Oost-Vlaanderen",
    "iso:country":"BE",
    "sg:address":"Langerbrugsestraat 241",
    "sg:city":"Evergem",
    "sg:orig_category":"P\u00e9pini\u00e9ristes",
    "sg:phone":"+32 9 253 92 28",
    "sg:postcode":"9940",
    "sg:province":"Oost-Vlaanderen",
    "wof:name":"Herman Verstraete",
    "wof:placetype":"venue"
},
  "geometry": {"coordinates":[3.7326719761,51.1119995117],"type":"Point"}
}