{
  "type": "Feature",
  "properties": {
    "iso:country":"BE",
    "sg:address":"Rue Van Peteghen 2a",
    "sg:city":"Charleroi",
    "sg:orig_category":"Kapsalons",
    "sg:phone":"+32 71 52 97 25",
    "sg:postcode":"6030",
    "sg:province":"Hainaut",
    "wof:name":"Basso Valentina N",
    "wof:placetype":"venue"
},
  "geometry": {"coordinates":[4.3949289322,50.4065132141],"type":"Point"}
}