{
  "type": "Feature",
  "properties": {
    "addr:full":"Rue De Gouy 3 Chapelle-lez-herlaimont Hainaut 7160",
    "addr:housenumber":"3",
    "addr:postcode":"7160",
    "addr:street":"Rue De Gouy",
    "iso:country":"BE",
    "sg:address":"Rue De Gouy 3",
    "sg:city":"Chapelle-lez-herlaimont",
    "sg:orig_category":"V\u00eatements pour b\u00e9b\u00e9s and enfants",
    "sg:phone":"+32 64 44 70 88",
    "sg:postcode":"7160",
    "sg:province":"Hainaut",
    "wof:name":"Boutique Ninie",
    "wof:placetype":"venue"
},
  "geometry": {"coordinates":[4.2834820747,50.470916748],"type":"Point"}
}