{
  "type": "Feature",
  "properties": {
    "iso:country":"BE",
    "sg:address":"Jozef Duthoystraat 40",
    "sg:city":"Waregem",
    "sg:classifiers":[
        {
            "category":"Professional",
            "subcategory":"Computer Services",
            "type":"Services"
        }
    ],
    "sg:phone":"+32 56 60 93 61",
    "sg:postcode":"8790",
    "sg:province":"West-Vlaanderen",
    "sg:tags":[
        "-",
        "processing",
        "data"
    ],
    "wof:name":"Sdp",
    "wof:placetype":"venue"
},
  "geometry": {"coordinates":[3.4227619171,50.8831100464],"type":"Point"}
}