{
  "type": "Feature",
  "properties": {
    "addr:full":"Avenue Rogier 23 Li\u00c8ge Li\u00e8ge 4000",
    "addr:housenumber":"23",
    "addr:postcode":"4000",
    "addr:street":"Avenue Rogier",
    "iso:country":"BE",
    "sg:address":"Avenue Rogier 23",
    "sg:city":"Li\u00c8ge",
    "sg:orig_category":"M\u00e9decins and sp\u00e9cialistes",
    "sg:phone":"+32 4 252 84 62",
    "sg:postcode":"4000",
    "sg:province":"Li\u00e8ge",
    "wof:name":"Christine Manette",
    "wof:placetype":"venue"
},
  "geometry": {"coordinates":[5.5695681572,50.6315803528],"type":"Point"}
}