{
  "type": "Feature",
  "properties": {
    "addr:full":"Langstraat 41 Riemst Limburg 3770",
    "addr:housenumber":"41",
    "addr:postcode":"3770",
    "addr:street":"Langstraat",
    "iso:country":"BE",
    "sg:address":"Langstraat 41",
    "sg:city":"Riemst",
    "sg:orig_category":"Boekhouders",
    "sg:phone":"+32 12 39 11 39",
    "sg:postcode":"3770",
    "sg:province":"Limburg",
    "wof:name":"Armand L'hoest",
    "wof:placetype":"venue"
},
  "geometry": {"coordinates":[5.5662112236,50.7856674194],"type":"Point"}
}