{
  "type": "Feature",
  "properties": {
    "addr:full":"Rue De St.amand 93 Peruwelz Hainaut 7600",
    "addr:housenumber":"93",
    "addr:postcode":"7600",
    "addr:street":"Rue De St.Amand;Hainaut",
    "iso:country":"BE",
    "sg:address":"Rue De St.amand 93",
    "sg:city":"Peruwelz",
    "sg:orig_category":"Huisdieren and benodigdheden",
    "sg:phone":"+32 69 77 49 07",
    "sg:postcode":"7600",
    "sg:province":"Hainaut",
    "wof:name":"Chatterie De La Loquette",
    "wof:placetype":"venue"
},
  "geometry": {"coordinates":[3.6010420322,50.4948196411],"type":"Point"}
}