{
  "type": "Feature",
  "properties": {
    "iso:country":"BE",
    "sg:address":"Grote Baan 349",
    "sg:city":"Houthalen-helchteren (helchteren)",
    "sg:classifiers":[
        {
            "category":"Health Services",
            "subcategory":"Dentist",
            "type":"Services"
        }
    ],
    "sg:phone":"+32 11 52 14 31",
    "sg:postcode":"3530",
    "sg:province":"Limburg",
    "wof:name":"Moens R",
    "wof:placetype":"venue"
},
  "geometry": {"coordinates":[5.3800802231,51.0446815491],"type":"Point"}
}