{
  "type": "Feature",
  "properties": {
    "addr:full":"Rue De Bomer\u00e9e 126 Charleroi (mont-sur-marchienne) Hainaut 6032",
    "addr:housenumber":"126",
    "addr:postcode":"6032",
    "addr:street":"Rue De Bomere\u0301E",
    "iso:country":"BE",
    "sg:address":"Rue De Bomer\u00e9e 126",
    "sg:city":"Charleroi (mont-sur-marchienne)",
    "sg:classifiers":[
        {
            "category":"Real Estate",
            "subcategory":"Architect",
            "type":"Services"
        }
    ],
    "sg:phone":"+32 71 43 54 27",
    "sg:postcode":"6032",
    "sg:province":"Hainaut",
    "wof:name":"Herveau C",
    "wof:placetype":"venue"
},
  "geometry": {"coordinates":[4.3990368843,50.3738212585],"type":"Point"}
}