{
  "type": "Feature",
  "properties": {
    "iso:country":"BE",
    "sg:address":"Heikant 44",
    "sg:city":"Meerhout",
    "sg:classifiers":[
        {
            "category":"Utilities",
            "subcategory":"Refuse",
            "type":"Services"
        }
    ],
    "sg:phone":"+32 14 30 70 10",
    "sg:postcode":"2450",
    "sg:province":"Antwerpen",
    "sg:tags":[
        "management",
        "waste"
    ],
    "wof:name":"Rencare Nv",
    "wof:placetype":"venue"
},
  "geometry": {"coordinates":[5.058880806,51.1397361755],"type":"Point"}
}