{
  "type": "Feature",
  "properties": {
    "iso:country":"BE",
    "sg:address":"Chauss\u00c9e De Waterloo 1316-1318",
    "sg:city":"Ukkel/uccle",
    "sg:classifiers":[
        {
            "category":"Banks & Credit Unions",
            "subcategory":"Bureau De Change",
            "type":"Services"
        }
    ],
    "sg:phone":"+32 2 558 03 90",
    "sg:postcode":"1180",
    "sg:province":"Bruxelles-Capitale",
    "sg:tags":[
        "voyage",
        "maroquinerie",
        "v\u00eatements",
        "pour",
        "article",
        "dame"
    ],
    "wof:name":"Archie Pell",
    "wof:placetype":"venue"
},
  "geometry": {"coordinates":[4.3747901917,50.7909164429],"type":"Point"}
}