{
  "type": "Feature",
  "properties": {
    "addr:full":"Dampoortstraat 86-88 Gent Oost-Vlaanderen 9000",
    "addr:housenumber":"86-88",
    "addr:postcode":"9000",
    "addr:street":"Dampoortstraat;Oost-Vlaanderen",
    "iso:country":"BE",
    "sg:address":"Dampoortstraat 86-88",
    "sg:city":"Gent",
    "sg:orig_category":"Fleurs and plantes",
    "sg:phone":"+32 9 224 40 98",
    "sg:postcode":"9000",
    "sg:province":"Oost-Vlaanderen",
    "wof:name":"Arioso",
    "wof:placetype":"venue"
},
  "geometry": {"coordinates":[3.7377269268,51.0568161011],"type":"Point"}
}