{
  "type": "Feature",
  "properties": {
    "addr:full":"Waterstraat 30 Sint-katelijne-waver Antwerpen 2860",
    "addr:housenumber":"30",
    "addr:postcode":"2860",
    "addr:street":"Waterstraat",
    "iso:country":"BE",
    "sg:address":"Waterstraat 30",
    "sg:city":"Sint-katelijne-waver",
    "sg:classifiers":[
        {
            "category":"Farming",
            "subcategory":"Crops",
            "type":"Manufacturing & Wholesale Goods"
        }
    ],
    "sg:phone":"+32 15 31 41 93",
    "sg:postcode":"2860",
    "sg:province":"Antwerpen",
    "sg:tags":[
        "vegetable",
        "fruit",
        "-",
        "grower"
    ],
    "wof:name":"Agre-top Product",
    "wof:placetype":"venue"
},
  "geometry": {"coordinates":[4.5477237701,51.0796585083],"type":"Point"}
}