{
  "type": "Feature",
  "properties": {
    "addr:full":"Hundelgemsesteenweg 635 Merelbeke Oost-Vlaanderen 9820",
    "addr:housenumber":"635",
    "addr:postcode":"9820",
    "addr:street":"Hundelgemsesteenweg",
    "iso:country":"BE",
    "sg:address":"Hundelgemsesteenweg 635",
    "sg:city":"Merelbeke",
    "sg:orig_category":"D\u00e9corateurs d'int\u00e9rieur",
    "sg:phone":"+32 9 231 15 52",
    "sg:postcode":"9820",
    "sg:province":"Oost-Vlaanderen",
    "wof:name":"A. De Neve",
    "wof:placetype":"venue"
},
  "geometry": {"coordinates":[3.7446289062,50.9807548523],"type":"Point"}
}