{
  "type": "Feature",
  "properties": {
    "iso:country":"BE",
    "sg:address":"Breedstraat 3",
    "sg:city":"Sint-niklaas",
    "sg:classifiers":[
        {
            "category":"Wholesale",
            "subcategory":"Vending Machines",
            "type":"Manufacturing & Wholesale Goods"
        }
    ],
    "sg:phone":"+32 3 780 12 11",
    "sg:postcode":"9100",
    "sg:province":"Oost-Vlaanderen",
    "sg:tags":[
        "sterilization",
        "installation",
        "-"
    ],
    "wof:name":"Fmc Europe Nv",
    "wof:placetype":"venue"
},
  "geometry": {"coordinates":[4.158536911,51.1694221497],"type":"Point"}
}