{
  "type": "Feature",
  "properties": {
    "iso:country":"BE",
    "sg:address":"Haven 503 Scheldelaan 410",
    "sg:city":"Antwerpen",
    "sg:classifiers":[
        {
            "category":"Banks & Credit Unions",
            "subcategory":"Investment Brokerage",
            "type":"Services"
        }
    ],
    "sg:phone":"+32 3 546 03 00",
    "sg:postcode":"2040",
    "sg:province":"Antwerpen",
    "sg:tags":[
        "-",
        "transport",
        "related"
    ],
    "wof:name":"Vopak Terminal Acs Nv",
    "wof:placetype":"venue"
},
  "geometry": {"coordinates":[4.2969307899,51.304725647],"type":"Point"}
}