{
  "type": "Feature",
  "properties": {
    "addr:full":"Rue D'ordin 21 Jemeppe-sur-sambre Namur 5190",
    "addr:housenumber":"21",
    "addr:postcode":"5190",
    "addr:street":"Rue D'Ordin",
    "iso:country":"BE",
    "sg:address":"Rue D'ordin 21",
    "sg:city":"Jemeppe-sur-sambre",
    "sg:orig_category":"V\u00e9hicules automobiles. Entretien and r\u00e9parations de voitures. Imprimeries and copyshops",
    "sg:phone":"+32 71 78 41 82",
    "sg:postcode":"5190",
    "sg:province":"Namur",
    "wof:name":"Prestige Cars",
    "wof:placetype":"venue"
},
  "geometry": {"coordinates":[4.7007040977,50.4673309326],"type":"Point"}
}