{
  "type": "Feature",
  "properties": {
    "addr:full":"Route D'ath 187 Mons (nimy) Hainaut 7020",
    "addr:housenumber":"187",
    "addr:postcode":"7020",
    "addr:street":"Route D'Ath",
    "iso:country":"BE",
    "sg:address":"Route D'ath 187",
    "sg:city":"Mons (nimy)",
    "sg:classifiers":[
        {
            "category":"Building & Trades",
            "subcategory":"Electrical",
            "type":"Services"
        }
    ],
    "sg:phone":"+32 65 32 85 10",
    "sg:postcode":"7020",
    "sg:province":"Hainaut",
    "sg:tags":[
        "tool",
        "electric"
    ],
    "wof:name":"Tout Fix Sa",
    "wof:placetype":"venue"
},
  "geometry": {"coordinates":[3.9435119629,50.4883422852],"type":"Point"}
}