{
  "type": "Feature",
  "properties": {
    "iso:country":"BE",
    "sg:address":"Senenne 10",
    "sg:city":"Anhee",
    "sg:orig_category":"Producteurs de fruits. Eleveurs de bovins",
    "sg:phone":"+32 82 61 18 69",
    "sg:postcode":"5537",
    "sg:province":"Namur",
    "wof:name":"Emmanuel De Wouters De Bouchout",
    "wof:placetype":"venue"
},
  "geometry": {"coordinates":[4.8772888184,50.299030304],"type":"Point"}
}