{
  "type": "Feature",
  "properties": {
    "addr:full":"Rue De L' Industrie 11 Braine-le-comte Hainaut 7090",
    "addr:housenumber":"11",
    "addr:postcode":"7090",
    "addr:street":"Rue De L ' Industrie",
    "iso:country":"BE",
    "sg:address":"Rue De L' Industrie 11",
    "sg:city":"Braine-le-comte",
    "sg:orig_category":"Locations de machines and \u00e9quipement pour la construction. Installation de menuiserie en bois and pl",
    "sg:phone":"+32 67 55 65 39",
    "sg:postcode":"7090",
    "sg:province":"Hainaut",
    "wof:name":"A.b.c Echaf",
    "wof:placetype":"venue"
},
  "geometry": {"coordinates":[4.1386079788,50.6025085449],"type":"Point"}
}