{
  "type": "Feature",
  "properties": {
    "addr:full":"Rue De La Place 26 Villers-la-ville Brabant Wallon 1495",
    "addr:housenumber":"26",
    "addr:postcode":"1495",
    "addr:street":"Rue De La Place",
    "iso:country":"BE",
    "sg:address":"Rue De La Place 26",
    "sg:city":"Villers-la-ville",
    "sg:orig_category":"Boekhouders",
    "sg:phone":"+32 71 87 83 15",
    "sg:postcode":"1495",
    "sg:province":"Brabant Wallon",
    "wof:name":"Jean-yves Dupuis",
    "wof:placetype":"venue"
},
  "geometry": {"coordinates":[4.530477047,50.5786132812],"type":"Point"}
}