{
  "type": "Feature",
  "properties": {
    "addr:full":"Lindeboomstraat 18 Gavere Oost-Vlaanderen 9890",
    "addr:housenumber":"18",
    "addr:postcode":"9890",
    "addr:street":"Lindeboomstraat",
    "iso:country":"BE",
    "sg:address":"Lindeboomstraat 18",
    "sg:city":"Gavere",
    "sg:orig_category":"Baby- and kinderkleding",
    "sg:phone":"+32 9 384 14 68",
    "sg:postcode":"9890",
    "sg:province":"Oost-Vlaanderen",
    "wof:name":"Huis Goody Woody",
    "wof:placetype":"venue"
},
  "geometry": {"coordinates":[3.6754031181,50.9373054504],"type":"Point"}
}