{
  "type": "Feature",
  "properties": {
    "iso:country":"BE",
    "sg:address":"Berlarij 77",
    "sg:city":"Lier",
    "sg:classifiers":[
        {
            "category":"Personal",
            "subcategory":"Beauty Salon",
            "type":"Services"
        }
    ],
    "sg:phone":"+32 3 480 41 58",
    "sg:postcode":"2500",
    "sg:province":"Antwerpen",
    "sg:tags":[
        "de",
        "coiffure"
    ],
    "wof:name":"Coiffure Hilda",
    "wof:placetype":"venue"
},
  "geometry": {"coordinates":[4.5805978775,51.1285552979],"type":"Point"}
}