{
  "type": "Feature",
  "properties": {
    "iso:country":"BE",
    "sg:address":"Gemeentehuisstraat 26",
    "sg:city":"Grimbergen",
    "sg:orig_category":"Advocaten and juridische adviseurs",
    "sg:phone":"+32 2 269 36 66",
    "sg:postcode":"1852",
    "sg:province":"Vlaams-Brabant",
    "wof:name":"P. Mensalt",
    "wof:placetype":"venue"
},
  "geometry": {"coordinates":[4.3613147736,50.9563789368],"type":"Point"}
}