{
  "type": "Feature",
  "properties": {
    "iso:country":"BE",
    "sg:address":"Rue Grande 54",
    "sg:city":"Dour",
    "sg:orig_category":"Slagers",
    "sg:phone":"+32 65 65 28 21",
    "sg:postcode":"7370",
    "sg:province":"Hainaut",
    "wof:name":"Boucherie Pochet",
    "wof:placetype":"venue"
},
  "geometry": {"coordinates":[3.779802084,50.398601532],"type":"Point"}
}