{
  "type": "Feature",
  "properties": {
    "addr:full":"Lage Kaart 1 Brasschaat Antwerpen 2930",
    "addr:housenumber":"1",
    "addr:postcode":"2930",
    "addr:street":"Lage Kaart",
    "iso:country":"BE",
    "sg:address":"Lage Kaart 1",
    "sg:city":"Brasschaat",
    "sg:classifiers":[
        {
            "category":"Professional",
            "subcategory":"Detective & Security Services",
            "type":"Services"
        }
    ],
    "sg:phone":"+32 475 53 68 05",
    "sg:postcode":"2930",
    "sg:province":"Antwerpen",
    "sg:tags":[
        "agency"
    ],
    "wof:name":"Abyss Investigations",
    "wof:placetype":"venue"
},
  "geometry": {"coordinates":[4.4887948036,51.2958488464],"type":"Point"}
}