{
  "type": "Feature",
  "properties": {
    "addr:full":"Rue Grande 30 Farciennes Hainaut 6240",
    "addr:housenumber":"30",
    "addr:postcode":"6240",
    "addr:street":"Rue Grande",
    "iso:country":"BE",
    "sg:address":"Rue Grande 30",
    "sg:city":"Farciennes",
    "sg:orig_category":"Advocaten and juridische adviseurs",
    "sg:phone":"+32 71 38 14 75",
    "sg:postcode":"6240",
    "sg:province":"Hainaut",
    "wof:name":"A. De Hennault",
    "wof:placetype":"venue"
},
  "geometry": {"coordinates":[4.5516600609,50.426700592],"type":"Point"}
}