{
  "type": "Feature",
  "properties": {
    "iso:country":"BE",
    "sg:address":"Rue Brun 14",
    "sg:city":"Andenne",
    "sg:orig_category":"Biljart- and snookerzalen Restaurants",
    "sg:phone":"+32 85 84 32 68",
    "sg:postcode":"5300",
    "sg:province":"Namur",
    "wof:name":"Le Barcelone",
    "wof:placetype":"venue"
},
  "geometry": {"coordinates":[5.0974597931,50.4882888794],"type":"Point"}
}