{
  "type": "Feature",
  "properties": {
    "addr:full":"Schoebroekstraat 46 Beringen (paal) Limburg 3583",
    "addr:housenumber":"46",
    "addr:postcode":"3583",
    "addr:street":"Schoebroekstraat",
    "iso:country":"BE",
    "sg:address":"Schoebroekstraat 46",
    "sg:city":"Beringen (paal)",
    "sg:classifiers":[
        {
            "category":"Military Area",
            "subcategory":"Air Force Base",
            "type":"Public Place"
        }
    ],
    "sg:phone":"+32 11 43 39 46",
    "sg:postcode":"3583",
    "sg:province":"Limburg",
    "sg:tags":[
        "corrosion",
        "prevention",
        "rust"
    ],
    "wof:name":"P.i. Of Europe Nv",
    "wof:placetype":"venue"
},
  "geometry": {"coordinates":[5.1706700325,51.0389442444],"type":"Point"}
}