{
  "type": "Feature",
  "properties": {
    "iso:country":"BE",
    "sg:address":"Droeshoutstraat 144",
    "sg:city":"Opwijk",
    "sg:orig_category":"Belastingconsulenten Diverse juridische dienstverlening",
    "sg:phone":"+32 52 35 40 98",
    "sg:postcode":"1745",
    "sg:province":"Vlaams-Brabant",
    "wof:name":"Alain Van Der Kuylen",
    "wof:placetype":"venue"
},
  "geometry": {"coordinates":[4.1765480042,50.9569549561],"type":"Point"}
}