{
  "type": "Feature",
  "properties": {
    "iso:country":"BE",
    "sg:address":"Chemin Du Meunier 9",
    "sg:city":"Rixensart",
    "sg:orig_category":"M\u00e9decins and sp\u00e9cialistes",
    "sg:phone":"+32 2 652 03 25",
    "sg:postcode":"1330",
    "sg:province":"Brabant Wallon",
    "wof:name":"Eric Fran\u00c7ois",
    "wof:placetype":"venue"
},
  "geometry": {"coordinates":[4.5352511406,50.7057495117],"type":"Point"}
}