{
  "type": "Feature",
  "properties": {
    "iso:country":"BE",
    "sg:address":"Verlorenbroodstraat 120 Box 1",
    "sg:city":"Merelbeke",
    "sg:classifiers":[
        {
            "category":"Banks & Credit Unions",
            "subcategory":"Financial Services",
            "type":"Services"
        }
    ],
    "sg:phone":"+32 9 244 70 00",
    "sg:postcode":"9820",
    "sg:province":"Oost-Vlaanderen",
    "sg:tags":[
        "group"
    ],
    "wof:name":"Dvs Nv",
    "wof:placetype":"venue"
},
  "geometry": {"coordinates":[3.7497489452,51.0094909668],"type":"Point"}
}