{
  "type": "Feature",
  "properties": {
    "addr:full":"Avenue De L'universit\u00c9 6 Elsene/ixelles Bruxelles-Capitale 1050",
    "addr:housenumber":"6",
    "addr:postcode":"1050",
    "addr:street":"Avenue De L'Universite \u0301",
    "iso:country":"BE",
    "sg:address":"Avenue De L'universit\u00c9 6",
    "sg:city":"Elsene/ixelles",
    "sg:orig_category":"Cr\u00e9dits divers",
    "sg:postcode":"1050",
    "sg:province":"Bruxelles-Capitale",
    "wof:name":"Bancontact-mister Cash",
    "wof:placetype":"venue"
},
  "geometry": {"coordinates":[4.3894062042,50.8153610229],"type":"Point"}
}