{
  "type": "Feature",
  "properties": {
    "addr:full":"Avenue De La Jonction 2 Bruxelles (saint-gilles) Bruxelles-Capitale 1060",
    "addr:housenumber":"2",
    "addr:postcode":"1060",
    "addr:street":"Avenue De La Jonction",
    "iso:country":"BE",
    "sg:address":"Avenue De La Jonction 2",
    "sg:city":"Bruxelles (saint-gilles)",
    "sg:classifiers":[
        {
            "category":"Exhibition Hall",
            "type":"Public Place"
        }
    ],
    "sg:phone":"+32 2 345 36 93",
    "sg:postcode":"1060",
    "sg:province":"Bruxelles-Capitale",
    "sg:tags":[
        "stand"
    ],
    "wof:name":"Dams L",
    "wof:placetype":"venue"
},
  "geometry": {"coordinates":[4.3518958092,50.8207092285],"type":"Point"}
}