{
  "type": "Feature",
  "properties": {
    "addr:full":"Sint-hubertusstraat 2 Beernem West-Vlaanderen 8730",
    "addr:housenumber":"2",
    "addr:postcode":"8730",
    "addr:street":"Sint-Hubertusstraat",
    "iso:country":"BE",
    "sg:address":"Sint-hubertusstraat 2",
    "sg:city":"Beernem",
    "sg:orig_category":"Kapsalons",
    "sg:phone":"+32 50 78 98 96",
    "sg:postcode":"8730",
    "sg:province":"West-Vlaanderen",
    "wof:name":"Coiffure Erica",
    "wof:placetype":"venue"
},
  "geometry": {"coordinates":[3.3260290623,51.1282081604],"type":"Point"}
}