{
  "type": "Feature",
  "properties": {
    "addr:full":"Rue Albert-elisabeth 38 Binche Hainaut 7134",
    "addr:housenumber":"38",
    "addr:postcode":"7134",
    "addr:street":"Rue Albert-Elisabeth",
    "iso:country":"BE",
    "sg:address":"Rue Albert-elisabeth 38",
    "sg:city":"Binche",
    "sg:orig_category":"Kapsalons",
    "sg:phone":"+32 64 33 35 78",
    "sg:postcode":"7134",
    "sg:province":"Hainaut",
    "wof:name":"Coiffure Nicole",
    "wof:placetype":"venue"
},
  "geometry": {"coordinates":[4.1812000275,50.4355392456],"type":"Point"}
}