{
  "type": "Feature",
  "properties": {
    "iso:country":"BE",
    "sg:address":"Kouterdreef 45",
    "sg:city":"Mechelen",
    "sg:orig_category":"Mat\u00e9riel pour plomberie and chauffage Mat\u00e9riaux de construction Machines-outils Gr",
    "sg:phone":"+32 15 21 28 75",
    "sg:postcode":"2800",
    "sg:province":"Antwerpen",
    "wof:name":"Oventrop",
    "wof:placetype":"venue"
},
  "geometry": {"coordinates":[4.4638948441,51.0496063232],"type":"Point"}
}