{
  "type": "Feature",
  "properties": {
    "addr:full":"Ch De Luxembourg 7 Assesse Namur 5336",
    "addr:housenumber":"7",
    "addr:postcode":"5336",
    "addr:street":"Ch De Luxembourg",
    "iso:country":"BE",
    "sg:address":"Ch De Luxembourg 7",
    "sg:city":"Assesse",
    "sg:classifiers":[
        {
            "category":"Bakery",
            "type":"Food & Drink"
        }
    ],
    "sg:phone":"+32 83 65 53 01",
    "sg:postcode":"5336",
    "sg:province":"Namur",
    "sg:tags":[
        "cake",
        "product",
        "related",
        "bread"
    ],
    "wof:name":"Pierson Luc Robert M.",
    "wof:placetype":"venue"
},
  "geometry": {"coordinates":[4.9839367867,50.3917312622],"type":"Point"}
}