{
  "type": "Feature",
  "properties": {
    "iso:country":"BE",
    "sg:address":"Zwarteleenstraat 28",
    "sg:city":"Ieper",
    "sg:orig_category":"Epiceries",
    "sg:phone":"+32 57 21 86 28",
    "sg:postcode":"8902",
    "sg:province":"West-Vlaanderen",
    "wof:name":"Superette Dehaize",
    "wof:placetype":"venue"
},
  "geometry": {"coordinates":[2.9301331043,50.8248748779],"type":"Point"}
}