{
  "type": "Feature",
  "properties": {
    "addr:full":"Philipslaan 9 Leuven Vlaams-Brabant 3000",
    "addr:housenumber":"9",
    "addr:postcode":"3000",
    "addr:street":"Philipslaan",
    "iso:country":"BE",
    "sg:address":"Philipslaan 9",
    "sg:city":"Leuven",
    "sg:orig_category":"M\u00e9decins and sp\u00e9cialistes",
    "sg:phone":"+32 16 25 00 50",
    "sg:postcode":"3000",
    "sg:province":"Vlaams-Brabant",
    "wof:name":"Michel Decq",
    "wof:placetype":"venue"
},
  "geometry": {"coordinates":[4.7317700386,50.8672714233],"type":"Point"}
}