{
  "type": "Feature",
  "properties": {
    "addr:full":"Elsterweg 46 Riemst (millen) Limburg 3770",
    "addr:housenumber":"46",
    "addr:postcode":"3770",
    "addr:street":"Elsterweg",
    "iso:country":"BE",
    "sg:address":"Elsterweg 46",
    "sg:city":"Riemst (millen)",
    "sg:classifiers":[
        {
            "category":"Retail",
            "subcategory":"Car Wash",
            "type":"Services"
        }
    ],
    "sg:postcode":"3770",
    "sg:province":"Limburg",
    "sg:tags":[
        "automobile",
        "washing",
        "-",
        "truck"
    ],
    "wof:name":"Xl-wash",
    "wof:placetype":"venue"
},
  "geometry": {"coordinates":[5.5574531555,50.7679176331],"type":"Point"}
}