{
  "type": "Feature",
  "properties": {
    "addr:full":"Avenue De L'ange 30 Waterloo Brabant Wallon 1410",
    "addr:housenumber":"30",
    "addr:postcode":"1410",
    "addr:street":"Avenue De L'Ange",
    "iso:country":"BE",
    "sg:address":"Avenue De L'ange 30",
    "sg:city":"Waterloo",
    "sg:orig_category":"M\u00e9decins and sp\u00e9cialistes",
    "sg:phone":"+32 2 354 91 76",
    "sg:postcode":"1410",
    "sg:province":"Brabant Wallon",
    "wof:name":"Marianne Odeyn",
    "wof:placetype":"venue"
},
  "geometry": {"coordinates":[4.4015030861,50.7159080505],"type":"Point"}
}