{
  "type": "Feature",
  "properties": {
    "iso:country":"BE",
    "sg:address":"Grote Roeselarestraat 21",
    "sg:city":"Zonnebeke",
    "sg:orig_category":"Eleveurs de bovins",
    "sg:phone":"+32 51 77 87 97",
    "sg:postcode":"8980",
    "sg:province":"West-Vlaanderen",
    "wof:name":"Willy Tyvaert",
    "wof:placetype":"venue"
},
  "geometry": {"coordinates":[2.9889750481,50.8733978271],"type":"Point"}
}