{
  "type": "Feature",
  "properties": {
    "iso:country":"BE",
    "sg:address":"Marktstraat 28",
    "sg:city":"Oudenburg",
    "sg:orig_category":"Banken and kredietinstellingen",
    "sg:phone":"+32 59 26 70 24",
    "sg:postcode":"8460",
    "sg:province":"West-Vlaanderen",
    "wof:name":"Fortis",
    "wof:placetype":"venue"
},
  "geometry": {"coordinates":[3.0062630177,51.1847343445],"type":"Point"}
}