{
  "type": "Feature",
  "properties": {
    "iso:country":"BE",
    "sg:address":"Einde 215",
    "sg:city":"Lommel",
    "sg:classifiers":[
        {
            "category":"Bars & Pubs",
            "type":"Food & Drink"
        }
    ],
    "sg:phone":"+32 11 54 44 89",
    "sg:postcode":"3920",
    "sg:province":"Limburg",
    "wof:name":"De Mulder",
    "wof:placetype":"venue"
},
  "geometry": {"coordinates":[5.3143701553,51.2127799988],"type":"Point"}
}