{
  "type": "Feature",
  "properties": {
    "iso:country":"BE",
    "sg:address":"Sentier Du Br\u00dble 14",
    "sg:city":"Quaregnon",
    "sg:orig_category":"Begrafeniswezen",
    "sg:phone":"+32 65 78 64 77",
    "sg:postcode":"7390",
    "sg:province":"Hainaut",
    "wof:name":"Pompes Fun\u00c8bres Coton - Hanot",
    "wof:placetype":"venue"
},
  "geometry": {"coordinates":[3.864538908,50.4465026855],"type":"Point"}
}