{
  "type": "Feature",
  "properties": {
    "addr:full":"Appelmansstraat 28 Antwerpen Antwerpen 2018",
    "addr:housenumber":"28",
    "addr:postcode":"2018",
    "addr:street":"Appelmansstraat",
    "iso:country":"BE",
    "sg:address":"Appelmansstraat 28",
    "sg:city":"Antwerpen",
    "sg:classifiers":[
        {
            "category":"Restaurant",
            "type":"Food & Drink"
        }
    ],
    "sg:phone":"+32 3 213 22 00",
    "sg:postcode":"2018",
    "sg:province":"Antwerpen",
    "wof:name":"Lamalo",
    "wof:placetype":"venue"
},
  "geometry": {"coordinates":[4.4171037674,51.2165565491],"type":"Point"}
}