{
  "type": "Feature",
  "properties": {
    "addr:full":"Vrouwenboomstraat 14 Tielt West-Vlaanderen 8700",
    "addr:housenumber":"14",
    "addr:postcode":"8700",
    "addr:street":"Vrouwenboomstraat",
    "iso:country":"BE",
    "sg:address":"Vrouwenboomstraat 14",
    "sg:city":"Tielt",
    "sg:orig_category":"Epiceries",
    "sg:phone":"+32 51 40 79 46",
    "sg:postcode":"8700",
    "sg:province":"West-Vlaanderen",
    "wof:name":"Frans Van Coppenolle",
    "wof:placetype":"venue"
},
  "geometry": {"coordinates":[3.3157539368,51.0173492432],"type":"Point"}
}