{
  "type": "Feature",
  "properties": {
    "addr:full":"Rue P\u00c9trias 26 Ham-sur-heure-nalinnes Hainaut 6120",
    "addr:housenumber":"26",
    "addr:postcode":"6120",
    "addr:street":"Rue Pe\u0301Trias;Hainaut",
    "iso:country":"BE",
    "sg:address":"Rue P\u00c9trias 26",
    "sg:city":"Ham-sur-heure-nalinnes",
    "sg:orig_category":"Woningbouw",
    "sg:phone":"+32 71 21 79 28",
    "sg:postcode":"6120",
    "sg:province":"Hainaut",
    "wof:name":"V.d.g. Constructions",
    "wof:placetype":"venue"
},
  "geometry": {"coordinates":[4.4294638634,50.3383178711],"type":"Point"}
}