{
  "type": "Feature",
  "properties": {
    "addr:full":"Oudenaardsesteenweg 334 Erpe-mere Oost-Vlaanderen 9420",
    "addr:housenumber":"334",
    "addr:postcode":"9420",
    "addr:street":"Oudenaardsesteenweg",
    "iso:country":"BE",
    "sg:address":"Oudenaardsesteenweg 334",
    "sg:city":"Erpe-mere",
    "sg:orig_category":"Supermarch\u00e9s",
    "sg:postcode":"9420",
    "sg:province":"Oost-Vlaanderen",
    "wof:name":"Aldi",
    "wof:placetype":"venue"
},
  "geometry": {"coordinates":[3.9683699608,50.9321403503],"type":"Point"}
}