{
  "type": "Feature",
  "properties": {
    "addr:full":"Route De Sortiau 167b Thuin Hainaut 6530",
    "addr:housenumber":"167b",
    "addr:postcode":"6530",
    "addr:street":"Route De Sortiau",
    "iso:country":"BE",
    "sg:address":"Route De Sortiau 167b",
    "sg:city":"Thuin",
    "sg:orig_category":"Afvalwaterverwerking and ontstoppingsdiensten",
    "sg:phone":"+32 71 59 53 58",
    "sg:postcode":"6530",
    "sg:province":"Hainaut",
    "wof:name":"Vidange Rousseau",
    "wof:placetype":"venue"
},
  "geometry": {"coordinates":[4.2859711647,50.3395843506],"type":"Point"}
}