{
  "type": "Feature",
  "properties": {
    "addr:full":"Rue De Le Haye 80 Frameries (sars-la-bruy\u00e8re) Hainaut 7080",
    "addr:housenumber":"80",
    "addr:postcode":"7080",
    "addr:street":"Rue De Le Haye",
    "iso:country":"BE",
    "sg:address":"Rue De Le Haye 80",
    "sg:city":"Frameries (sars-la-bruy\u00e8re)",
    "sg:classifiers":[
        {
            "category":"Shopping",
            "subcategory":"Bicycles & Sporting Goods",
            "type":"Retail Goods"
        }
    ],
    "sg:phone":"+32 65 67 24 38",
    "sg:postcode":"7080",
    "sg:province":"Hainaut",
    "sg:tags":[
        "-"
    ],
    "wof:name":"Cycle Veltri",
    "wof:placetype":"venue"
},
  "geometry": {"coordinates":[3.8801081181,50.3757514954],"type":"Point"}
}