{
  "type": "Feature",
  "properties": {
    "iso:country":"BE",
    "sg:address":"Rue Linette 50",
    "sg:city":"Neupr\u00e9 (plainevaux)",
    "sg:classifiers":[
        {
            "category":"Real Estate",
            "subcategory":"Architect",
            "type":"Services"
        }
    ],
    "sg:phone":"+32 4 371 33 12",
    "sg:postcode":"4122",
    "sg:province":"Li\u00e8ge",
    "wof:name":"Gregoire A",
    "wof:placetype":"venue"
},
  "geometry": {"coordinates":[5.5076727867,50.5419692993],"type":"Point"}
}