{
  "type": "Feature",
  "properties": {
    "addr:full":"Rue Zaine 16 Chaumont-gistoux Brabant Wallon 1325",
    "addr:housenumber":"16",
    "addr:postcode":"1325",
    "addr:street":"Rue Zaine",
    "iso:country":"BE",
    "sg:address":"Rue Zaine 16",
    "sg:city":"Chaumont-gistoux",
    "sg:orig_category":"Charpentes and couvertures",
    "sg:phone":"+32 10 68 89 57",
    "sg:postcode":"1325",
    "sg:province":"Brabant Wallon",
    "wof:name":"Saintenoy Leopold",
    "wof:placetype":"venue"
},
  "geometry": {"coordinates":[4.6971111298,50.682510376],"type":"Point"}
}