{
  "type": "Feature",
  "properties": {
    "iso:country":"BE",
    "sg:address":"Rue Frinoise 12",
    "sg:city":"Tournai",
    "sg:orig_category":"Enseignement sup\u00e9rieur",
    "sg:phone":"+32 69 89 05 60",
    "sg:postcode":"7500",
    "sg:province":"Hainaut",
    "wof:name":"Haute Ecole Libre",
    "wof:placetype":"venue"
},
  "geometry": {"coordinates":[3.3796579838,50.6107826233],"type":"Point"}
}