{
  "type": "Feature",
  "properties": {
    "addr:full":"Zegeplein 4 Brasschaat Antwerpen 2930",
    "addr:housenumber":"4",
    "addr:postcode":"2930",
    "addr:street":"Zegeplein",
    "iso:country":"BE",
    "sg:address":"Zegeplein 4",
    "sg:city":"Brasschaat",
    "sg:classifiers":[
        {
            "category":"Insurance",
            "subcategory":"Life Insurance",
            "type":"Services"
        }
    ],
    "sg:phone":"+32 3 633 07 30",
    "sg:postcode":"2930",
    "sg:province":"Antwerpen",
    "sg:tags":[
        "assurance"
    ],
    "wof:name":"Axa",
    "wof:placetype":"venue"
},
  "geometry": {"coordinates":[4.519944191,51.3236656189],"type":"Point"}
}