{
  "type": "Feature",
  "properties": {
    "iso:country":"BE",
    "sg:address":"Grand'place 36",
    "sg:city":"Le Roeulx",
    "sg:orig_category":"Epiceries",
    "sg:phone":"+32 64 65 01 33",
    "sg:postcode":"7070",
    "sg:province":"Hainaut",
    "wof:name":"Louis Delhaize",
    "wof:placetype":"venue"
},
  "geometry": {"coordinates":[4.1089048386,50.5016059875],"type":"Point"}
}