{
  "type": "Feature",
  "properties": {
    "addr:full":"Stadsheide 27 Hasselt Limburg 3500",
    "addr:housenumber":"27",
    "addr:postcode":"3500",
    "addr:street":"Stadsheide",
    "iso:country":"BE",
    "sg:address":"Stadsheide 27",
    "sg:city":"Hasselt",
    "sg:orig_category":"Elektrische huishoudapparaten, radio and televisie Gh",
    "sg:phone":"+32 11 30 13 90",
    "sg:postcode":"3500",
    "sg:province":"Limburg",
    "wof:name":"Alpha Industries",
    "wof:placetype":"venue"
},
  "geometry": {"coordinates":[5.3684120178,50.9522514343],"type":"Point"}
}