{
  "type": "Feature",
  "properties": {
    "addr:full":"Statiestraat 10 Antwerpen Antwerpen 2600",
    "addr:housenumber":"10",
    "addr:postcode":"2600",
    "addr:street":"Statiestraat",
    "iso:country":"BE",
    "sg:address":"Statiestraat 10",
    "sg:city":"Antwerpen",
    "sg:orig_category":"Ordinateurs and \u00e9quipement informatique",
    "sg:phone":"+32 3 218 69 21",
    "sg:postcode":"2600",
    "sg:province":"Antwerpen",
    "wof:name":"Photo Hall",
    "wof:placetype":"venue"
},
  "geometry": {"coordinates":[4.4185051918,51.2181816101],"type":"Point"}
}