{
  "type": "Feature",
  "properties": {
    "addr:full":"Moerbeeklaan 22 Malle Antwerpen 2390",
    "addr:housenumber":"22",
    "addr:postcode":"2390",
    "addr:street":"Moerbeeklaan",
    "iso:country":"BE",
    "sg:address":"Moerbeeklaan 22",
    "sg:city":"Malle",
    "sg:orig_category":"Travaux de pl\u00e2trage",
    "sg:phone":"+32 3 464 00 76",
    "sg:postcode":"2390",
    "sg:province":"Antwerpen",
    "wof:name":"Stuk-all",
    "wof:placetype":"venue"
},
  "geometry": {"coordinates":[4.667787075,51.2809104919],"type":"Point"}
}