{
  "type": "Feature",
  "properties": {
    "addr:full":"Moorselbaan 164 Aalst Oost-Vlaanderen 9300",
    "addr:housenumber":"164",
    "addr:postcode":"9300",
    "addr:street":"Moorselbaan",
    "iso:country":"BE",
    "sg:address":"Moorselbaan 164",
    "sg:city":"Aalst",
    "sg:classifiers":[
        {
            "category":"Community Center",
            "type":"Public Place"
        }
    ],
    "sg:phone":"+32 53 72 42 65",
    "sg:postcode":"9300",
    "sg:province":"Oost-Vlaanderen",
    "sg:tags":[
        "medical"
    ],
    "wof:name":"Revalidatiecentrum (lokomotorisch & Neurologische Aandoeningen)",
    "wof:placetype":"venue"
},
  "geometry": {"coordinates":[4.0541710854,50.9427604675],"type":"Point"}
}