{
  "type": "Feature",
  "properties": {
    "iso:country":"BE",
    "sg:address":"Oude Baan 4",
    "sg:city":"Mechelen",
    "sg:orig_category":"Installation de menuiserie en bois and plastique",
    "sg:phone":"+32 15 20 66 20",
    "sg:postcode":"2800",
    "sg:province":"Antwerpen",
    "wof:name":"Maglo",
    "wof:placetype":"venue"
},
  "geometry": {"coordinates":[4.4593811035,51.0514335632],"type":"Point"}
}