{
  "type": "Feature",
  "properties": {
    "iso:country":"BE",
    "sg:address":"Avenue Emile Herman 1a",
    "sg:city":"Manage (fayt-lez-manage)",
    "sg:classifiers":[
        {
            "category":"Health Services",
            "subcategory":"Health Practitioner",
            "type":"Services"
        }
    ],
    "sg:phone":"+32 64 55 44 94",
    "sg:postcode":"7170",
    "sg:province":"Hainaut",
    "sg:tags":[
        "physiotherapist"
    ],
    "wof:name":"Van Der Aspoilden Doris",
    "wof:placetype":"venue"
},
  "geometry": {"coordinates":[4.2269849777,50.4885101318],"type":"Point"}
}