{
  "type": "Feature",
  "properties": {
    "iso:country":"BE",
    "sg:address":"Brusselsesteenweg 188a",
    "sg:city":"Melle",
    "sg:classifiers":[
        {
            "category":"Building & Trades",
            "subcategory":"Construction",
            "type":"Services"
        }
    ],
    "sg:phone":"+32 9 252 13 40",
    "sg:postcode":"9090",
    "sg:province":"Oost-Vlaanderen",
    "sg:tags":[
        "roofing",
        "material",
        "-"
    ],
    "wof:name":"Herreman-lippens Bvba",
    "wof:placetype":"venue"
},
  "geometry": {"coordinates":[3.7972350121,51.0052070618],"type":"Point"}
}