{
  "type": "Feature",
  "properties": {
    "addr:full":"Bevrijdingslei 17 Kapellen Antwerpen 2950",
    "addr:housenumber":"17",
    "addr:postcode":"2950",
    "addr:street":"Bevrijdingslei",
    "iso:country":"BE",
    "sg:address":"Bevrijdingslei 17",
    "sg:city":"Kapellen",
    "sg:classifiers":[
        {
            "category":"Banks & Credit Unions",
            "subcategory":"Investment Brokerage",
            "type":"Services"
        }
    ],
    "sg:phone":"+32 3 605 21 03",
    "sg:postcode":"2950",
    "sg:province":"Antwerpen",
    "sg:tags":[
        "fence"
    ],
    "wof:name":"Janssens Afsluitingen Bvba",
    "wof:placetype":"venue"
},
  "geometry": {"coordinates":[4.42791605,51.3126068115],"type":"Point"}
}