{
  "type": "Feature",
  "properties": {
    "iso:country":"BE",
    "sg:address":"Rue Grande 58",
    "sg:city":"Dinant",
    "sg:classifiers":[
        {
            "category":"Home & Garden",
            "subcategory":"Home Furnishings",
            "type":"Retail Goods"
        }
    ],
    "sg:phone":"+32 82 22 69 12",
    "sg:postcode":"5500",
    "sg:province":"Namur",
    "sg:tags":[
        "linen",
        "household",
        "-"
    ],
    "wof:name":"Galons De Brume (les)",
    "wof:placetype":"venue"
},
  "geometry": {"coordinates":[4.9144120216,50.2577323914],"type":"Point"}
}