{
  "type": "Feature",
  "properties": {
    "addr:full":"Sentier Du Br\u00dbl\u00c9 30 Quaregnon Hainaut 7390",
    "addr:housenumber":"30",
    "addr:postcode":"7390",
    "addr:street":"Sentier Du Bru\u0302Le\u0301",
    "iso:country":"BE",
    "sg:address":"Sentier Du Br\u00dbl\u00c9 30",
    "sg:city":"Quaregnon",
    "sg:orig_category":"Peinture. Rev\u00eatements pour sols and murs",
    "sg:phone":"+32 65 78 09 10",
    "sg:postcode":"7390",
    "sg:province":"Hainaut",
    "wof:name":"Solepeint",
    "wof:placetype":"venue"
},
  "geometry": {"coordinates":[3.8631060123,50.4500732422],"type":"Point"}
}