{
  "type": "Feature",
  "properties": {
    "addr:full":"Rue Royale Sainte-marie 103 Bruxelles (schaerbeek) Bruxelles-Capitale 1030",
    "addr:housenumber":"103",
    "addr:postcode":"1030",
    "addr:street":"Rue Royale Sainte-Marie",
    "iso:country":"BE",
    "sg:address":"Rue Royale Sainte-marie 103",
    "sg:city":"Bruxelles (schaerbeek)",
    "sg:classifiers":[
        {
            "category":"Communications",
            "subcategory":"Film & Video Production",
            "type":"Services"
        }
    ],
    "sg:phone":"+32 2 215 12 74",
    "sg:postcode":"1030",
    "sg:province":"Bruxelles-Capitale",
    "sg:tags":[
        "realisation",
        "-"
    ],
    "wof:name":"Rouffaer Bvba",
    "wof:placetype":"venue"
},
  "geometry": {"coordinates":[4.37038517,50.862323761],"type":"Point"}
}