{
  "type": "Feature",
  "properties": {
    "iso:country":"BE",
    "sg:address":"Rue D'aywaille 61",
    "sg:city":"Comblain-au-pont",
    "sg:classifiers":[
        {
            "category":"Retail",
            "subcategory":"Auto Repair",
            "type":"Services"
        }
    ],
    "sg:phone":"+32 4 369 17 68",
    "sg:postcode":"4170",
    "sg:province":"Li\u00e8ge",
    "sg:tags":[
        "automobile-body"
    ],
    "wof:name":"Philippin Michel",
    "wof:placetype":"venue"
},
  "geometry": {"coordinates":[5.5959692001,50.4806289673],"type":"Point"}
}