{
  "type": "Feature",
  "properties": {
    "addr:full":"Koning Boudewijnlaan 11 Olen Antwerpen 2250",
    "addr:housenumber":"11",
    "addr:postcode":"2250",
    "addr:street":"Koning Boudewijnlaan",
    "iso:country":"BE",
    "sg:address":"Koning Boudewijnlaan 11",
    "sg:city":"Olen",
    "sg:orig_category":"Non-Classified Establishments",
    "sg:phone":"+32 14 26 77 05",
    "sg:postcode":"2250",
    "sg:province":"Antwerpen",
    "wof:name":"De Wachter Kaarsen",
    "wof:placetype":"venue"
},
  "geometry": {"coordinates":[4.8582677841,51.1472930908],"type":"Point"}
}