{
  "type": "Feature",
  "properties": {
    "addr:full":"Oosteneindlaan 16 Wuustwezel (loenhout) Antwerpen 2990",
    "addr:housenumber":"16",
    "addr:postcode":"2990",
    "addr:street":"Oosteneindlaan",
    "iso:country":"BE",
    "sg:address":"Oosteneindlaan 16",
    "sg:city":"Wuustwezel (loenhout)",
    "sg:classifiers":[
        {
            "category":"Transit Center",
            "subcategory":"Freight",
            "type":"Transportation"
        }
    ],
    "sg:phone":"+32 3 669 55 53",
    "sg:postcode":"2990",
    "sg:province":"Antwerpen",
    "sg:tags":[
        "import",
        "export",
        "-"
    ],
    "wof:name":"Lec",
    "wof:placetype":"venue"
},
  "geometry": {"coordinates":[4.6495990753,51.4016685486],"type":"Point"}
}