{
  "type": "Feature",
  "properties": {
    "iso:country":"BE",
    "sg:address":"Overrepenstraat 54",
    "sg:city":"Tongeren (overrepen)",
    "sg:classifiers":[
        {
            "category":"Food & Beverages",
            "subcategory":"Groceries & Convenience Stores",
            "type":"Retail Goods"
        }
    ],
    "sg:phone":"+32 12 23 31 02",
    "sg:postcode":"3700",
    "sg:province":"Limburg",
    "sg:tags":[
        "grocer"
    ],
    "wof:name":"Wijnants J",
    "wof:placetype":"venue"
},
  "geometry": {"coordinates":[5.4636240005,50.7807197571],"type":"Point"}
}