{
  "type": "Feature",
  "properties": {
    "addr:full":"Herengracht 14 As Limburg 3665",
    "addr:housenumber":"14",
    "addr:postcode":"3665",
    "addr:street":"Herengracht",
    "iso:country":"BE",
    "sg:address":"Herengracht 14",
    "sg:city":"As",
    "sg:classifiers":[
        {
            "category":"Home & Garden",
            "subcategory":"Building Materials",
            "type":"Retail Goods"
        }
    ],
    "sg:phone":"+32 89 65 65 75",
    "sg:postcode":"3665",
    "sg:province":"Limburg",
    "sg:tags":[
        "veranda"
    ],
    "wof:name":"Kubomat Bvba",
    "wof:placetype":"venue"
},
  "geometry": {"coordinates":[5.5683498383,51.0009651184],"type":"Point"}
}