{
  "type": "Feature",
  "properties": {
    "iso:country":"BE",
    "sg:address":"Ten Akkerdreef 93",
    "sg:city":"Kortrijk",
    "sg:classifiers":[
        {
            "category":"Recreation",
            "type":"Entertainment"
        }
    ],
    "sg:phone":"+32 56 25 74 62",
    "sg:postcode":"8500",
    "sg:province":"West-Vlaanderen",
    "sg:tags":[
        "diver",
        "amusement"
    ],
    "wof:name":"Dos Santos Nascimento Manoel",
    "wof:placetype":"venue"
},
  "geometry": {"coordinates":[3.2772769928,50.8208389282],"type":"Point"}
}