{
  "type": "Feature",
  "properties": {
    "addr:full":"Rue Jardins-d\u00b4annevoie 33 Anh\u00c9e Namur 5537",
    "addr:housenumber":"33",
    "addr:postcode":"5537",
    "addr:street":"Rue Jardins-D\u00b4Annevoie",
    "iso:country":"BE",
    "sg:address":"Rue Jardins-d\u00b4annevoie 33",
    "sg:city":"Anh\u00c9e",
    "sg:orig_category":"Restaurants Ruimtes voor conferenties, recepties and feesten",
    "sg:phone":"+32 82 61 28 33",
    "sg:postcode":"5537",
    "sg:province":"Namur",
    "wof:name":"Le Moulin D\u00b4henryette",
    "wof:placetype":"venue"
},
  "geometry": {"coordinates":[4.8392977715,50.343208313],"type":"Point"}
}