{
  "type": "Feature",
  "properties": {
    "addr:full":"Ieperstraat 377 Menen West-Vlaanderen 8930",
    "addr:housenumber":"377",
    "addr:postcode":"8930",
    "addr:street":"Ieperstraat",
    "iso:country":"BE",
    "sg:address":"Ieperstraat 377",
    "sg:city":"Menen",
    "sg:orig_category":"Herstellingen and onderhoud van auto's",
    "sg:phone":"+32 56 51 11 98",
    "sg:postcode":"8930",
    "sg:province":"West-Vlaanderen",
    "wof:name":"Stefaan Berten",
    "wof:placetype":"venue"
},
  "geometry": {"coordinates":[3.101195097,50.8026390076],"type":"Point"}
}