{
  "type": "Feature",
  "properties": {
    "addr:full":"Paddeschootdreef 4 Sint-niklaas Oost-Vlaanderen 9100",
    "addr:housenumber":"4",
    "addr:postcode":"9100",
    "addr:street":"Paddeschootdreef",
    "iso:country":"BE",
    "sg:address":"Paddeschootdreef 4",
    "sg:city":"Sint-niklaas",
    "sg:classifiers":[
        {
            "category":"Health Services",
            "subcategory":"Dentist",
            "type":"Services"
        }
    ],
    "sg:phone":"+32 3 776 31 49",
    "sg:postcode":"9100",
    "sg:province":"Oost-Vlaanderen",
    "wof:name":"Rycek M",
    "wof:placetype":"venue"
},
  "geometry": {"coordinates":[4.1285881996,51.1681251526],"type":"Point"}
}