{
  "type": "Feature",
  "properties": {
    "iso:country":"BE",
    "sg:address":"Rue Madame 13",
    "sg:city":"Beaumont",
    "sg:classifiers":[
        {
            "category":"Shopping",
            "subcategory":"Bicycles & Sporting Goods",
            "type":"Retail Goods"
        }
    ],
    "sg:phone":"+32 71 58 85 88",
    "sg:postcode":"6500",
    "sg:province":"Hainaut",
    "sg:tags":[
        "-"
    ],
    "wof:name":"Beaumont Cyclo Sport",
    "wof:placetype":"venue"
},
  "geometry": {"coordinates":[4.2372989655,50.2369041443],"type":"Point"}
}