{
  "type": "Feature",
  "properties": {
    "addr:full":"Av Hermann-debroux 46 Bruxelles Bruxelles-Capitale 1160",
    "addr:housenumber":"46",
    "addr:postcode":"1160",
    "addr:street":"Av Hermann-Debroux",
    "iso:country":"BE",
    "sg:address":"Av Hermann-debroux 46",
    "sg:city":"Bruxelles",
    "sg:classifiers":[
        {
            "category":"Banks & Credit Unions",
            "subcategory":"Financial Services",
            "type":"Services"
        }
    ],
    "sg:phone":"+32 2 679 45 11",
    "sg:postcode":"1160",
    "sg:province":"Bruxelles-Capitale",
    "sg:tags":[
        "banking",
        "insurance",
        "institution",
        "finance"
    ],
    "wof:name":"Puilaetco Sa",
    "wof:placetype":"venue"
},
  "geometry": {"coordinates":[4.4328289032,50.8134765625],"type":"Point"}
}