{
  "type": "Feature",
  "properties": {
    "iso:country":"BE",
    "sg:address":"Keistraat 11",
    "sg:city":"Kortenberg (meerbeek)",
    "sg:classifiers":[
        {
            "category":"Social Services",
            "subcategory":"Child Care",
            "type":"Services"
        }
    ],
    "sg:phone":"+32 16 48 11 91",
    "sg:postcode":"3078",
    "sg:province":"Vlaams-Brabant",
    "sg:tags":[
        "baby",
        "food",
        "children's"
    ],
    "wof:name":"Borstvoeding Vzw",
    "wof:placetype":"venue"
},
  "geometry": {"coordinates":[4.6072669029,50.8700332642],"type":"Point"}
}