{
  "type": "Feature",
  "properties": {
    "addr:full":"Rue Du Thier 56 Marche-en-famenne (waha) Luxembourg 6900",
    "addr:housenumber":"56",
    "addr:postcode":"6900",
    "addr:street":"Rue Du Thier",
    "iso:country":"BE",
    "sg:address":"Rue Du Thier 56",
    "sg:city":"Marche-en-famenne (waha)",
    "sg:classifiers":[
        {
            "category":"Building & Trades",
            "subcategory":"Construction",
            "type":"Services"
        }
    ],
    "sg:phone":"+32 84 32 22 06",
    "sg:postcode":"6900",
    "sg:province":"Luxembourg",
    "sg:tags":[
        "stone",
        "cutter"
    ],
    "wof:name":"Parmentier A",
    "wof:placetype":"venue"
},
  "geometry": {"coordinates":[5.3430151939,50.2273483276],"type":"Point"}
}