{
  "type": "Feature",
  "properties": {
    "addr:full":"Rue Froide 49 Walcourt (berz\u00e9e) Namur 5651",
    "addr:housenumber":"49",
    "addr:postcode":"5651",
    "addr:street":"Rue Froide",
    "iso:country":"BE",
    "sg:address":"Rue Froide 49",
    "sg:city":"Walcourt (berz\u00e9e)",
    "sg:classifiers":[
        {
            "category":"Professional",
            "subcategory":"Computer Services",
            "type":"Services"
        }
    ],
    "sg:phone":"+32 71 61 36 29",
    "sg:postcode":"5651",
    "sg:province":"Namur",
    "sg:tags":[
        "webdesign",
        "-",
        "internet"
    ],
    "wof:name":"Inforlab",
    "wof:placetype":"venue"
},
  "geometry": {"coordinates":[4.39539814,50.2930297852],"type":"Point"}
}