{
  "type": "Feature",
  "properties": {
    "addr:full":"Rue Maigret 3 Saint-ghislain Hainaut 7330",
    "addr:housenumber":"3",
    "addr:postcode":"7330",
    "addr:street":"Rue Maigret;Hainaut",
    "iso:country":"BE",
    "sg:address":"Rue Maigret 3",
    "sg:city":"Saint-ghislain",
    "sg:classifiers":[
        {
            "category":"Insurance",
            "subcategory":"Insurance Agent",
            "type":"Services"
        }
    ],
    "sg:phone":"+32 65 78 60 46",
    "sg:postcode":"7330",
    "sg:province":"Hainaut",
    "sg:tags":[
        "verzekeringsmakelaars",
        "expert"
    ],
    "wof:name":"Giovanni Cannizzaro",
    "wof:placetype":"venue"
},
  "geometry": {"coordinates":[3.8208999634,50.4487266541],"type":"Point"}
}