{
  "type": "Feature",
  "properties": {
    "iso:country":"BE",
    "sg:address":"Rue Du Travail 3",
    "sg:city":"Gr\u00e2ce-hollogne",
    "sg:classifiers":[
        {
            "category":"Juice Bar",
            "subcategory":"None",
            "type":"Food & Drink"
        }
    ],
    "sg:phone":"+32 4 246 46 26",
    "sg:postcode":"4460",
    "sg:province":"Li\u00e8ge",
    "sg:tags":[
        "furnishing"
    ],
    "wof:name":"Pmd S.a.",
    "wof:placetype":"venue"
},
  "geometry": {"coordinates":[5.4963970184,50.6553115845],"type":"Point"}
}