{
  "type": "Feature",
  "properties": {
    "addr:full":"F Couteauxstraat 8 Jette Bruxelles-Capitale 1090",
    "addr:housenumber":"8",
    "addr:postcode":"1090",
    "addr:street":"Couteauxstraat",
    "iso:country":"BE",
    "sg:address":"F Couteauxstraat 8",
    "sg:city":"Jette",
    "sg:orig_category":"Technische and wetenschappelijke instrumenten Fab",
    "sg:phone":"+32 2 426 46 76",
    "sg:postcode":"1090",
    "sg:province":"Bruxelles-Capitale",
    "wof:name":"Laborimpex",
    "wof:placetype":"venue"
},
  "geometry": {"coordinates":[4.329805851,50.8784179688],"type":"Point"}
}