{
  "type": "Feature",
  "properties": {
    "addr:full":"Rue De La Brasserie 95 Elsene/ixelles Bruxelles-Capitale 1050",
    "addr:housenumber":"95",
    "addr:postcode":"1050",
    "addr:street":"Rue De La Brasserie",
    "iso:country":"BE",
    "sg:address":"Rue De La Brasserie 95",
    "sg:city":"Elsene/ixelles",
    "sg:orig_category":"Pharmaciens",
    "sg:phone":"+32 2 649 56 26",
    "sg:postcode":"1050",
    "sg:province":"Bruxelles-Capitale",
    "wof:name":"C.d. Pharma",
    "wof:placetype":"venue"
},
  "geometry": {"coordinates":[4.3749542236,50.8280792236],"type":"Point"}
}