{
  "type": "Feature",
  "properties": {
    "addr:full":"Rue Lebeau 17 Brussel/bruxelles Bruxelles-Capitale 1000",
    "addr:housenumber":"17",
    "addr:postcode":"1000",
    "addr:street":"Rue Lebeau;/",
    "iso:country":"BE",
    "sg:address":"Rue Lebeau 17",
    "sg:city":"Brussel/bruxelles",
    "sg:orig_category":"R\u00e9paration and restauration de meubles. Antiquit\u00e9s",
    "sg:phone":"+32 2 511 46 13",
    "sg:postcode":"1000",
    "sg:province":"Bruxelles-Capitale",
    "wof:name":"Collectors Gallery",
    "wof:placetype":"venue"
},
  "geometry": {"coordinates":[4.3542571068,50.8428077698],"type":"Point"}
}