{
  "type": "Feature",
  "properties": {
    "iso:country":"BE",
    "sg:address":"Fostierlaan 21",
    "sg:city":"Ronse/renaix",
    "sg:classifiers":[
        {
            "category":"Professional",
            "subcategory":"Accounting & Tax Preparation",
            "type":"Services"
        }
    ],
    "sg:phone":"+32 55 21 72 04",
    "sg:postcode":"9600",
    "sg:province":"Oost-Vlaanderen",
    "sg:tags":[
        "accountant"
    ],
    "wof:name":"Patrick Himpe",
    "wof:placetype":"venue"
},
  "geometry": {"coordinates":[3.5977709293,50.7450561523],"type":"Point"}
}