{
  "type": "Feature",
  "properties": {
    "iso:country":"BE",
    "sg:address":"Dampoortstraat 40",
    "sg:city":"Gent",
    "sg:orig_category":"Dierenartsen",
    "sg:phone":"+32 9 225 16 49",
    "sg:postcode":"9000",
    "sg:province":"Oost-Vlaanderen",
    "wof:name":"R.a. Vandevelde",
    "wof:placetype":"venue"
},
  "geometry": {"coordinates":[3.7356760502,51.0566864014],"type":"Point"}
}