{
  "type": "Feature",
  "properties": {
    "addr:full":"Essenhoutstraat 10 Kapellen Antwerpen 2950",
    "addr:housenumber":"10",
    "addr:postcode":"2950",
    "addr:street":"Essenhoutstraat",
    "iso:country":"BE",
    "sg:address":"Essenhoutstraat 10",
    "sg:city":"Kapellen",
    "sg:orig_category":"Verplichte sociale verzekeringen",
    "sg:phone":"+32 3 664 28 05",
    "sg:postcode":"2950",
    "sg:province":"Antwerpen",
    "wof:name":"Onafhankelijk Ziekenfonds",
    "wof:placetype":"venue"
},
  "geometry": {"coordinates":[4.426803112,51.3136024475],"type":"Point"}
}