{
  "type": "Feature",
  "properties": {
    "iso:country":"BE",
    "sg:address":"Schransken 4",
    "sg:city":"Ranst (oelegem)",
    "sg:classifiers":[
        {
            "category":"Building & Trades",
            "subcategory":"Pest Control",
            "type":"Services"
        }
    ],
    "sg:phone":"+32 3 383 17 25",
    "sg:postcode":"2520",
    "sg:province":"Antwerpen",
    "sg:tags":[
        "painting",
        "contractor"
    ],
    "wof:name":"De Bie H",
    "wof:placetype":"venue"
},
  "geometry": {"coordinates":[4.5981302261,51.2118682861],"type":"Point"}
}