{
  "type": "Feature",
  "properties": {
    "addr:full":"Natendries 31 Oudenaarde Oost-Vlaanderen 9700",
    "addr:housenumber":"31",
    "addr:postcode":"9700",
    "addr:street":"Natendries",
    "iso:country":"BE",
    "sg:address":"Natendries 31",
    "sg:city":"Oudenaarde",
    "sg:classifiers":[
        {
            "category":"Cafe",
            "type":"Food & Drink"
        }
    ],
    "sg:phone":"+32 55 31 23 60",
    "sg:postcode":"9700",
    "sg:province":"Oost-Vlaanderen",
    "sg:tags":[
        "caf\u00e9s"
    ],
    "wof:name":"Amata De Temmerman",
    "wof:placetype":"venue"
},
  "geometry": {"coordinates":[3.6428489685,50.8470573425],"type":"Point"}
}