{
  "type": "Feature",
  "properties": {
    "addr:full":"Chauss\u00c9e De Louvain 43b2 Wavre Brabant Wallon 1300",
    "addr:housenumber":"43b2;1300",
    "addr:street":"Chausse\u0301E De Louvain",
    "iso:country":"BE",
    "sg:address":"Chauss\u00c9e De Louvain 43b2",
    "sg:city":"Wavre",
    "sg:orig_category":"Avocats and conseillers juridiques",
    "sg:phone":"+32 10 22 96 66",
    "sg:postcode":"1300",
    "sg:province":"Brabant Wallon",
    "wof:name":"J.y. Leroux",
    "wof:placetype":"venue"
},
  "geometry": {"coordinates":[4.6140141487,50.7140464783],"type":"Point"}
}