{
  "type": "Feature",
  "properties": {
    "addr:full":"Place Jean Vander Elst 24 Ukkel/uccle Bruxelles-Capitale 1180",
    "addr:housenumber":"24",
    "addr:postcode":"1180",
    "addr:street":"Place Jean Vander Elst;/",
    "iso:country":"BE",
    "sg:address":"Place Jean Vander Elst 24",
    "sg:city":"Ukkel/uccle",
    "sg:orig_category":"M\u00e9decins and sp\u00e9cialistes",
    "sg:phone":"+32 2 376 54 08",
    "sg:postcode":"1180",
    "sg:province":"Bruxelles-Capitale",
    "wof:name":"Philippe Delsupehe",
    "wof:placetype":"venue"
},
  "geometry": {"coordinates":[4.3331918716,50.8031959534],"type":"Point"}
}