{
  "type": "Feature",
  "properties": {
    "addr:full":"Koolstraat 4 Evergem Oost-Vlaanderen 9940",
    "addr:housenumber":"4",
    "addr:postcode":"9940",
    "addr:street":"Koolstraat;Oost-Vlaanderen",
    "iso:country":"BE",
    "sg:address":"Koolstraat 4",
    "sg:city":"Evergem",
    "sg:classifiers":[
        {
            "category":"Building & Trades",
            "subcategory":"Cleaning & Sanitation",
            "type":"Services"
        }
    ],
    "sg:phone":"+32 9 258 03 44",
    "sg:postcode":"9940",
    "sg:province":"Oost-Vlaanderen",
    "sg:tags":[
        "fa\u00e7ade",
        "maintenance"
    ],
    "wof:name":"Destorme J",
    "wof:placetype":"venue"
},
  "geometry": {"coordinates":[3.6792778969,51.105506897],"type":"Point"}
}