{
  "type": "Feature",
  "properties": {
    "addr:full":"Liersesteenweg 471 Mechelen Antwerpen 2800",
    "addr:housenumber":"471",
    "addr:postcode":"2800",
    "addr:street":"Liersesteenweg",
    "iso:country":"BE",
    "sg:address":"Liersesteenweg 471",
    "sg:city":"Mechelen",
    "sg:classifiers":[
        {
            "category":"Retail",
            "subcategory":"Auto Repair",
            "type":"Services"
        }
    ],
    "sg:phone":"+32 15 27 82 04",
    "sg:postcode":"2800",
    "sg:province":"Antwerpen",
    "sg:tags":[
        "automobile-body"
    ],
    "wof:name":"L & D Service Bvba",
    "wof:placetype":"venue"
},
  "geometry": {"coordinates":[4.4802331924,51.0516853333],"type":"Point"}
}