{
  "type": "Feature",
  "properties": {
    "addr:full":"Iepersestraat 175 Kortrijk West-Vlaanderen 8500",
    "addr:housenumber":"175",
    "addr:postcode":"8500",
    "addr:street":"Iepersestraat",
    "iso:country":"BE",
    "sg:address":"Iepersestraat 175",
    "sg:city":"Kortrijk",
    "sg:classifiers":[
        {
            "category":"Building & Trades",
            "subcategory":"Construction",
            "type":"Services"
        }
    ],
    "sg:phone":"+32 56 37 19 62",
    "sg:postcode":"8500",
    "sg:province":"West-Vlaanderen",
    "sg:tags":[
        "carpenter"
    ],
    "wof:name":"Devriese D",
    "wof:placetype":"venue"
},
  "geometry": {"coordinates":[3.2698569298,50.8428878784],"type":"Point"}
}