{
  "type": "Feature",
  "properties": {
    "addr:full":"Kerkstraat 1 Deerlijk West-Vlaanderen 8540",
    "addr:housenumber":"1",
    "addr:postcode":"8540",
    "addr:street":"Kerkstraat",
    "iso:country":"BE",
    "sg:address":"Kerkstraat 1",
    "sg:city":"Deerlijk",
    "sg:classifiers":[
        {
            "category":"Bars & Pubs",
            "type":"Food & Drink"
        }
    ],
    "sg:phone":"+32 56 77 40 43",
    "sg:postcode":"8540",
    "sg:province":"West-Vlaanderen",
    "wof:name":"St-benedictus",
    "wof:placetype":"venue"
},
  "geometry": {"coordinates":[3.3769218922,50.82188797],"type":"Point"}
}