{
  "type": "Feature",
  "properties": {
    "addr:full":"Tiensesteenweg 284 Leuven Vlaams-Brabant 3000",
    "addr:housenumber":"284",
    "addr:postcode":"3000",
    "addr:street":"Tiensesteenweg",
    "iso:country":"BE",
    "sg:address":"Tiensesteenweg 284",
    "sg:city":"Leuven",
    "sg:orig_category":"Meubles D\u00e9taillants, Am\u00e9nagement de B\u00e2timents et de Cuisines",
    "sg:phone":"+32 16 25 00 17",
    "sg:postcode":"3000",
    "sg:province":"Vlaams-Brabant",
    "wof:name":"Matrassenstock",
    "wof:placetype":"venue"
},
  "geometry": {"coordinates":[4.7134261131,50.8735809326],"type":"Point"}
}