{
  "type": "Feature",
  "properties": {
    "addr:full":"Edith Cavellstraat 193ba Ukkel/uccle Bruxelles-Capitale 1180",
    "addr:postcode":"1180",
    "addr:street":"Edith Cavellstraat 193Ba",
    "iso:country":"BE",
    "sg:address":"Edith Cavellstraat 193ba",
    "sg:city":"Ukkel/uccle",
    "sg:orig_category":"Boekhouders",
    "sg:phone":"+32 2 372 06 48",
    "sg:postcode":"1180",
    "sg:province":"Bruxelles-Capitale",
    "wof:name":"Bruno Honnay",
    "wof:placetype":"venue"
},
  "geometry": {"coordinates":[4.3582000732,50.804561615],"type":"Point"}
}