{
  "type": "Feature",
  "properties": {
    "iso:country":"BE",
    "sg:address":"Rue De La Marzelle 32",
    "sg:city":"Sivry-rance",
    "sg:orig_category":"Charpentes and couvertures",
    "sg:phone":"+32 60 45 60 37",
    "sg:postcode":"6470",
    "sg:province":"Hainaut",
    "wof:name":"Philippe Dermonne",
    "wof:placetype":"venue"
},
  "geometry": {"coordinates":[4.1690659523,50.1656761169],"type":"Point"}
}