{
  "type": "Feature",
  "properties": {
    "addr:full":"Leopoldlaan 78 Middelkerke West-Vlaanderen 8430",
    "addr:housenumber":"78",
    "addr:postcode":"8430",
    "addr:street":"Leopoldlaan",
    "iso:country":"BE",
    "sg:address":"Leopoldlaan 78",
    "sg:city":"Middelkerke",
    "sg:orig_category":"Cr\u00e9meries. Boucheries. Alimentation sp\u00e9cialis\u00e9e",
    "sg:phone":"+32 59 30 04 27",
    "sg:postcode":"8430",
    "sg:province":"West-Vlaanderen",
    "wof:name":"Van Acker",
    "wof:placetype":"venue"
},
  "geometry": {"coordinates":[2.8137030602,51.1872367859],"type":"Point"}
}