{
  "type": "Feature",
  "properties": {
    "addr:full":"Zuidstraat 30 Ronse/renaix Oost-Vlaanderen 9600",
    "addr:housenumber":"30",
    "addr:postcode":"9600",
    "addr:street":"Zuidstraat",
    "iso:country":"BE",
    "sg:address":"Zuidstraat 30",
    "sg:city":"Ronse/renaix",
    "sg:orig_category":"Sportclubs",
    "sg:phone":"+32 55 21 64 02",
    "sg:postcode":"9600",
    "sg:province":"Oost-Vlaanderen",
    "wof:name":"R.h.c. Renaix",
    "wof:placetype":"venue"
},
  "geometry": {"coordinates":[3.6042990685,50.7452812195],"type":"Point"}
}