{
  "type": "Feature",
  "properties": {
    "addr:full":"Gentsestraat 40 Aalst Oost-Vlaanderen 9300",
    "addr:housenumber":"40",
    "addr:postcode":"9300",
    "addr:street":"Gentsestraat",
    "iso:country":"BE",
    "sg:address":"Gentsestraat 40",
    "sg:city":"Aalst",
    "sg:orig_category":"Antiek",
    "sg:phone":"+32 53 77 97 73",
    "sg:postcode":"9300",
    "sg:province":"Oost-Vlaanderen",
    "wof:name":"Clock-house",
    "wof:placetype":"venue"
},
  "geometry": {"coordinates":[4.0309581757,50.9376182556],"type":"Point"}
}