{
  "type": "Feature",
  "properties": {
    "iso:country":"BE",
    "sg:address":"Avenue Adolphe Buyl 104",
    "sg:city":"Elsene/ixelles",
    "sg:classifiers":[
        {
            "category":"Restaurant",
            "type":"Food & Drink"
        }
    ],
    "sg:phone":"+32 2 647 80 99",
    "sg:postcode":"1050",
    "sg:province":"Bruxelles-Capitale",
    "wof:name":"Bistro Marilou",
    "wof:placetype":"venue"
},
  "geometry": {"coordinates":[4.3832669258,50.8160057068],"type":"Point"}
}