{
  "type": "Feature",
  "properties": {
    "iso:country":"BE",
    "sg:address":"Domien Ingelsstraat 15",
    "sg:city":"Gent (drongen)",
    "sg:classifiers":[
        {
            "category":"Retail",
            "subcategory":"Event Space",
            "type":"Services"
        }
    ],
    "sg:phone":"+32 9 226 20 08",
    "sg:postcode":"9031",
    "sg:province":"Oost-Vlaanderen",
    "sg:tags":[
        "rental",
        "-",
        "hall"
    ],
    "wof:name":"Boerenhof",
    "wof:placetype":"venue"
},
  "geometry": {"coordinates":[3.6635661125,51.0507316589],"type":"Point"}
}