{
  "type": "Feature",
  "properties": {
    "iso:country":"BE",
    "sg:address":"Rozeveldstraat 2",
    "sg:city":"Torhout",
    "sg:orig_category":"Caf\u00e9s Ruimtes voor conferenties, recepties and feesten",
    "sg:phone":"+32 50 21 43 37",
    "sg:postcode":"8820",
    "sg:province":"West-Vlaanderen",
    "wof:name":"Rozeveld",
    "wof:placetype":"venue"
},
  "geometry": {"coordinates":[3.1269700527,51.0832977295],"type":"Point"}
}