{
  "type": "Feature",
  "properties": {
    "addr:full":"Place Saint-g\u00e9ry 29-32 Bruxelles Bruxelles-Capitale 1000",
    "addr:housenumber":"29-32",
    "addr:postcode":"1000",
    "addr:street":"Place Saint-Ge\u0301Ry",
    "iso:country":"BE",
    "sg:address":"Place Saint-g\u00e9ry 29-32",
    "sg:city":"Bruxelles",
    "sg:classifiers":[
        {
            "category":"Travel",
            "subcategory":"Hotels & Motels",
            "type":"Entertainment"
        }
    ],
    "sg:phone":"+32 2 511 01 25",
    "sg:postcode":"1000",
    "sg:province":"Bruxelles-Capitale",
    "wof:name":"Potini\u00e8re (la)",
    "wof:placetype":"venue"
},
  "geometry": {"coordinates":[4.3477730751,50.8479995728],"type":"Point"}
}