{
  "type": "Feature",
  "properties": {
    "iso:country":"BE",
    "sg:address":"Chauss\u00c9e De Bruxelles 165b40",
    "sg:city":"Waterloo",
    "sg:classifiers":[
        {
            "category":"Restaurant",
            "type":"Food & Drink"
        }
    ],
    "sg:phone":"+32 2 354 86 06",
    "sg:postcode":"1410",
    "sg:province":"Brabant Wallon",
    "wof:name":"Le Coeur D'artichaut",
    "wof:placetype":"venue"
},
  "geometry": {"coordinates":[4.3982839584,50.7172241211],"type":"Point"}
}