{
  "type": "Feature",
  "properties": {
    "addr:full":"Rue Henri Rapez 1 Mons Hainaut 7031",
    "addr:housenumber":"1",
    "addr:postcode":"7031",
    "addr:street":"Rue Henri Rapez;Hainaut",
    "iso:country":"BE",
    "sg:address":"Rue Henri Rapez 1",
    "sg:city":"Mons",
    "sg:orig_category":"Boekhouders",
    "sg:phone":"+32 65 87 37 44",
    "sg:postcode":"7031",
    "sg:province":"Hainaut",
    "wof:name":"Vincent Secretin",
    "wof:placetype":"venue"
},
  "geometry": {"coordinates":[4.0398697853,50.4295654297],"type":"Point"}
}