{
  "type": "Feature",
  "properties": {
    "addr:full":"Waterloose Steenweg 1155 Ukkel/uccle Bruxelles-Capitale 1180",
    "addr:postcode":"1155;1180",
    "addr:street":"Waterloose Steenweg",
    "iso:country":"BE",
    "sg:address":"Waterloose Steenweg 1155",
    "sg:city":"Ukkel/uccle",
    "sg:orig_category":"Artsen and specialisten",
    "sg:phone":"+32 2 375 33 99",
    "sg:postcode":"1180",
    "sg:province":"Bruxelles-Capitale",
    "wof:name":"Michel Ouchinsky",
    "wof:placetype":"venue"
},
  "geometry": {"coordinates":[4.375166893,50.797668457],"type":"Point"}
}