{
  "type": "Feature",
  "properties": {
    "addr:full":"Avenue Daniel Boon 52 Oudergem/auderghem Bruxelles-Capitale 1160",
    "addr:housenumber":"52",
    "addr:postcode":"1160",
    "addr:street":"Avenue Daniel Boon;/",
    "iso:country":"BE",
    "sg:address":"Avenue Daniel Boon 52",
    "sg:city":"Oudergem/auderghem",
    "sg:orig_category":"M\u00e9decins and sp\u00e9cialistes",
    "sg:phone":"+32 2 660 39 03",
    "sg:postcode":"1160",
    "sg:province":"Bruxelles-Capitale",
    "wof:name":"Fran\u00c7ois Crabb\u00c9",
    "wof:placetype":"venue"
},
  "geometry": {"coordinates":[4.431622982,50.8099021912],"type":"Point"}
}