{
  "type": "Feature",
  "properties": {
    "iso:country":"BE",
    "sg:address":"Noord-brabantlaan 3",
    "sg:city":"Turnhout",
    "sg:classifiers":[
        {
            "category":"Real Estate",
            "subcategory":"Real Estate Services",
            "type":"Services"
        }
    ],
    "sg:phone":"+32 14 41 12 27",
    "sg:postcode":"2300",
    "sg:province":"Antwerpen",
    "wof:name":"Vastgoedadvies Lauwers Bvba",
    "wof:placetype":"venue"
},
  "geometry": {"coordinates":[4.9671502113,51.3216133118],"type":"Point"}
}