{
  "type": "Feature",
  "properties": {
    "iso:country":"BE",
    "sg:address":"Boulevard Fulgence Masson 28",
    "sg:city":"Mons",
    "sg:classifiers":[
        {
            "category":"Social Services",
            "subcategory":"Job Training",
            "type":"Services"
        }
    ],
    "sg:phone":"+32 65 31 86 72",
    "sg:postcode":"7000",
    "sg:province":"Hainaut",
    "sg:tags":[
        "personnel"
    ],
    "wof:name":"Cefop",
    "wof:placetype":"venue"
},
  "geometry": {"coordinates":[3.9612300396,50.455368042],"type":"Point"}
}