{
  "type": "Feature",
  "properties": {
    "iso:country":"BE",
    "sg:address":"Rue Commandant Lemaire 171",
    "sg:city":"Mons",
    "sg:orig_category":"Slagers",
    "sg:phone":"+32 65 33 58 90",
    "sg:postcode":"7033",
    "sg:province":"Hainaut",
    "wof:name":"Christian Hannotte",
    "wof:placetype":"venue"
},
  "geometry": {"coordinates":[3.9253261089,50.4366378784],"type":"Point"}
}