{
  "type": "Feature",
  "properties": {
    "iso:country":"BE",
    "sg:address":"Rue De Borlon 12",
    "sg:city":"Somme-leuze",
    "sg:orig_category":"Animations diverses",
    "sg:phone":"+32 86 34 41 63",
    "sg:postcode":"5377",
    "sg:province":"Namur",
    "wof:name":"Fr\u00c9d\u00c9ric Vincent",
    "wof:placetype":"venue"
},
  "geometry": {"coordinates":[5.3698949814,50.3404350281],"type":"Point"}
}