{
  "type": "Feature",
  "properties": {
    "addr:full":"Chemin Du Rossignol 74b76 Braine-l'alleud Brabant Wallon 1420",
    "addr:housenumber":"74b76",
    "addr:postcode":"1420",
    "addr:street":"Chemin Du Rossignol",
    "iso:country":"BE",
    "sg:address":"Chemin Du Rossignol 74b76",
    "sg:city":"Braine-l'alleud",
    "sg:orig_category":"Maisons de repos and r\u00e9sidences",
    "sg:phone":"+32 2 385 03 94",
    "sg:postcode":"1420",
    "sg:province":"Brabant Wallon",
    "wof:name":"Home Du Rossignol",
    "wof:placetype":"venue"
},
  "geometry": {"coordinates":[-0.7004899979,47.369140625],"type":"Point"}
}