{
  "type": "Feature",
  "properties": {
    "addr:full":"Bondgenotenlaan 107 Leuven Vlaams-Brabant 3000",
    "addr:housenumber":"107",
    "addr:postcode":"3000",
    "addr:street":"Bondgenotenlaan",
    "iso:country":"BE",
    "sg:address":"Bondgenotenlaan 107",
    "sg:city":"Leuven",
    "sg:orig_category":"Tijdelijke werkgelegenheid and uitzendkantoren",
    "sg:phone":"+32 16 20 81 60",
    "sg:postcode":"3000",
    "sg:province":"Vlaams-Brabant",
    "wof:name":"Randstad",
    "wof:placetype":"venue"
},
  "geometry": {"coordinates":[4.7097630501,50.8804931641],"type":"Point"}
}