{
  "type": "Feature",
  "properties": {
    "addr:full":"Clos Des Grenadiers 4 Boussu Hainaut 7300",
    "addr:housenumber":"4",
    "addr:postcode":"7300",
    "addr:street":"Clos Des Grenadiers",
    "iso:country":"BE",
    "sg:address":"Clos Des Grenadiers 4",
    "sg:city":"Boussu",
    "sg:classifiers":[
        {
            "category":"Home & Garden",
            "subcategory":"Home Furnishings",
            "type":"Retail Goods"
        }
    ],
    "sg:phone":"+32 65 77 06 68",
    "sg:postcode":"7300",
    "sg:province":"Hainaut",
    "sg:tags":[
        "interior",
        "decoration"
    ],
    "wof:name":"Roy B & Fils",
    "wof:placetype":"venue"
},
  "geometry": {"coordinates":[3.7900021076,50.4280052185],"type":"Point"}
}