{
  "type": "Feature",
  "properties": {
    "iso:country":"BE",
    "sg:address":"Jacques Eggermontstraat 57",
    "sg:city":"Gent (ledeberg)",
    "sg:classifiers":[
        {
            "category":"Wholesale",
            "subcategory":"Machinery & Supplies",
            "type":"Manufacturing & Wholesale Goods"
        }
    ],
    "sg:phone":"+32 9 232 11 06",
    "sg:postcode":"9050",
    "sg:province":"Oost-Vlaanderen",
    "sg:tags":[
        "retail",
        "-",
        "electric"
    ],
    "wof:name":"Iljana Bvba",
    "wof:placetype":"venue"
},
  "geometry": {"coordinates":[3.740240097,51.0369796753],"type":"Point"}
}