{
  "type": "Feature",
  "properties": {
    "iso:country":"BE",
    "sg:address":"Aux Houx 9b12",
    "sg:city":"Engis",
    "sg:orig_category":"Diverse meubelen Fab Huishoudapparaten, televisies and radio's MEUBELONTWERP AND -INSTALLATIE",
    "sg:phone":"+32 4 275 15 99",
    "sg:postcode":"4480",
    "sg:province":"Li\u00e8ge",
    "wof:name":"Entreprises Remans Fr\u00c8res",
    "wof:placetype":"venue"
},
  "geometry": {"coordinates":[5.3989901543,50.5485916138],"type":"Point"}
}