{
  "type": "Feature",
  "properties": {
    "iso:country":"BE",
    "sg:address":"De Damhouderestraat 7",
    "sg:city":"Antwerpen",
    "sg:classifiers":[
        {
            "category":"Real Estate",
            "subcategory":"Architect",
            "type":"Services"
        }
    ],
    "sg:phone":"+32 3 288 49 05",
    "sg:postcode":"2018",
    "sg:province":"Antwerpen",
    "wof:name":"Decuypere H",
    "wof:placetype":"venue"
},
  "geometry": {"coordinates":[4.404613018,51.2082023621],"type":"Point"}
}