{
  "type": "Feature",
  "properties": {
    "addr:full":"Rue Marcel-moreau 12 Couvin Namur 5660",
    "addr:housenumber":"12",
    "addr:postcode":"5660",
    "addr:street":"Rue Marcel-Moreau",
    "iso:country":"BE",
    "sg:address":"Rue Marcel-moreau 12",
    "sg:city":"Couvin",
    "sg:orig_category":"Catering and organisation de f\u00eates",
    "sg:phone":"+32 60 34 47 96",
    "sg:postcode":"5660",
    "sg:province":"Namur",
    "wof:name":"Traiteur Libert-delvaux",
    "wof:placetype":"venue"
},
  "geometry": {"coordinates":[4.4820637703,50.0536766052],"type":"Point"}
}