{
  "type": "Feature",
  "properties": {
    "addr:full":"Antwerpsesteenweg 207 Zwijndrecht Antwerpen 2070",
    "addr:housenumber":"207",
    "addr:postcode":"2070",
    "addr:street":"Antwerpsesteenweg",
    "iso:country":"BE",
    "sg:address":"Antwerpsesteenweg 207",
    "sg:city":"Zwijndrecht",
    "sg:classifiers":[
        {
            "category":"Professional",
            "subcategory":"Detective & Security Services",
            "type":"Services"
        }
    ],
    "sg:phone":"+32 475 20 40 59",
    "sg:postcode":"2070",
    "sg:province":"Antwerpen",
    "sg:tags":[
        "-",
        "system",
        "apparatus",
        "surveillance"
    ],
    "wof:name":"Robello",
    "wof:placetype":"venue"
},
  "geometry": {"coordinates":[4.3408999443,51.2136383057],"type":"Point"}
}