{
  "type": "Feature",
  "properties": {
    "iso:country":"BE",
    "sg:address":"115",
    "sg:city":"Dagmoedstraat 9500 Geraardsbergen",
    "sg:classifiers":[
        {
            "category":"Food & Beverages",
            "subcategory":"Dairy",
            "type":"Retail Goods"
        }
    ],
    "sg:phone":"+32 54 41 21 33",
    "sg:postcode":"115",
    "sg:tags":[
        "product",
        "related"
    ],
    "wof:name":"Kaasimport Temmerman Willy & Desiree Nv",
    "wof:placetype":"venue"
},
  "geometry": {"coordinates":[3.8843801022,50.7716445923],"type":"Point"}
}