{
  "type": "Feature",
  "properties": {
    "addr:full":"Rue Ferdinand Lenoir 66 Bruxelles (jette) Bruxelles-Capitale 1090",
    "addr:housenumber":"66",
    "addr:postcode":"1090",
    "addr:street":"Rue Ferdinand Lenoir",
    "iso:country":"BE",
    "sg:address":"Rue Ferdinand Lenoir 66",
    "sg:city":"Bruxelles (jette)",
    "sg:classifiers":[
        {
            "category":"Retail",
            "subcategory":"Event Space",
            "type":"Services"
        }
    ],
    "sg:phone":"+32 2 420 98 82",
    "sg:postcode":"1090",
    "sg:province":"Bruxelles-Capitale",
    "sg:tags":[
        "organisation"
    ],
    "wof:name":"Event-full",
    "wof:placetype":"venue"
},
  "geometry": {"coordinates":[4.3309559822,50.8755950928],"type":"Point"}
}