{
  "type": "Feature",
  "properties": {
    "addr:full":"Thier Des Trixhes 50-52 Fl\u00e9malle Li\u00e8ge 4400",
    "addr:housenumber":"50-52",
    "addr:postcode":"4400",
    "addr:street":"Thier Des Trixhes",
    "iso:country":"BE",
    "sg:address":"Thier Des Trixhes 50-52",
    "sg:city":"Fl\u00e9malle",
    "sg:classifiers":[
        {
            "category":"Building & Trades",
            "subcategory":"Pest Control",
            "type":"Services"
        }
    ],
    "sg:phone":"+32 4 231 24 75",
    "sg:postcode":"4400",
    "sg:province":"Li\u00e8ge",
    "sg:tags":[
        "painting",
        "contractor"
    ],
    "wof:name":"Harmonia Decor Sprl",
    "wof:placetype":"venue"
},
  "geometry": {"coordinates":[5.4579200745,50.5987701416],"type":"Point"}
}