{
  "type": "Feature",
  "properties": {
    "iso:country":"BE",
    "sg:address":"Twee Dreven 8",
    "sg:city":"De Pinte",
    "sg:classifiers":[
        {
            "category":"Building & Trades",
            "subcategory":"Plumbing",
            "type":"Services"
        }
    ],
    "sg:phone":"+32 9 282 23 32",
    "sg:postcode":"9840",
    "sg:province":"Oost-Vlaanderen",
    "sg:tags":[
        "repair",
        "mainten",
        "-",
        "central",
        "heating"
    ],
    "wof:name":"Lefever J",
    "wof:placetype":"venue"
},
  "geometry": {"coordinates":[3.6398808956,50.9954605103],"type":"Point"}
}