{
  "type": "Feature",
  "properties": {
    "addr:full":"Rue Vin\u00e2ve 12a Amay (ampsin) Li\u00e8ge 4540",
    "addr:housenumber":"12a",
    "addr:postcode":"4540",
    "addr:street":"Rue Vina\u0302Ve;Ampsin",
    "iso:country":"BE",
    "sg:address":"Rue Vin\u00e2ve 12a",
    "sg:city":"Amay (ampsin)",
    "sg:classifiers":[
        {
            "category":"Health Services",
            "subcategory":"Doctor",
            "type":"Services"
        }
    ],
    "sg:phone":"+32 85 31 18 96",
    "sg:postcode":"4540",
    "sg:province":"Li\u00e8ge",
    "sg:tags":[
        "medicinephysicians",
        "surgeon"
    ],
    "wof:name":"Detry M",
    "wof:placetype":"venue"
},
  "geometry": {"coordinates":[5.3180990219,50.5478668213],"type":"Point"}
}