{
  "type": "Feature",
  "properties": {
    "iso:country":"BE",
    "sg:address":"Route De Luxembourg 16",
    "sg:city":"Malmedy",
    "sg:classifiers":[
        {
            "category":"Wholesale",
            "subcategory":"Metals & Minerals",
            "type":"Manufacturing & Wholesale Goods"
        }
    ],
    "sg:phone":"+32 53 83 42 15",
    "sg:postcode":"4960",
    "sg:province":"Li\u00e8ge",
    "sg:tags":[
        "conduit",
        "made",
        "cable"
    ],
    "wof:name":"H\u00e4wa Nv",
    "wof:placetype":"venue"
},
  "geometry": {"coordinates":[4.0263381004,50.9086227417],"type":"Point"}
}