{
  "type": "Feature",
  "properties": {
    "addr:full":"Avenue Des Platanes 98 Herve Li\u00e8ge 4650",
    "addr:housenumber":"98",
    "addr:postcode":"4650",
    "addr:street":"Avenue Des Platanes",
    "iso:country":"BE",
    "sg:address":"Avenue Des Platanes 98",
    "sg:city":"Herve",
    "sg:classifiers":[
        {
            "category":"Personal",
            "subcategory":"Beauty Salon",
            "type":"Services"
        }
    ],
    "sg:phone":"+32 87 31 41 64",
    "sg:postcode":"4650",
    "sg:province":"Li\u00e8ge",
    "sg:tags":[
        "de",
        "coiffure"
    ],
    "wof:name":"Coiffure L'atelier",
    "wof:placetype":"venue"
},
  "geometry": {"coordinates":[5.814453125,50.6090812683],"type":"Point"}
}