{
  "type": "Feature",
  "properties": {
    "addr:full":"Ambachtstraat 7 Tessenderlo Limburg 3980",
    "addr:housenumber":"7",
    "addr:postcode":"3980",
    "addr:street":"Ambachtstraat",
    "iso:country":"BE",
    "sg:address":"Ambachtstraat 7",
    "sg:city":"Tessenderlo",
    "sg:orig_category":"Produits pharmaceutiques Gr",
    "sg:phone":"+32 13 67 48 88",
    "sg:postcode":"3980",
    "sg:province":"Limburg",
    "wof:name":"Sissel Belgium",
    "wof:placetype":"venue"
},
  "geometry": {"coordinates":[5.1516270638,51.0760993958],"type":"Point"}
}