{
  "type": "Feature",
  "properties": {
    "iso:country":"BE",
    "sg:address":"Eppegemsesteenweg 20/2",
    "sg:city":"Grimbergen",
    "sg:orig_category":"Plomberie, chauffage and installations sanitaires",
    "sg:phone":"+32 2 251 44 79",
    "sg:postcode":"1850",
    "sg:province":"Vlaams-Brabant",
    "wof:name":"Gielens En Zoon Bvba",
    "wof:placetype":"venue"
},
  "geometry": {"coordinates":[4.4155650139,50.9484443665],"type":"Point"}
}