{
  "type": "Feature",
  "properties": {
    "addr:full":"Rijkbos 13 Zottegem (elene - Oombergen) Oost-Vlaanderen 9620",
    "addr:housenumber":"13",
    "addr:postcode":"9620",
    "addr:street":"Rijkbos;Oost-Vlaanderen",
    "iso:country":"BE",
    "sg:address":"Rijkbos 13",
    "sg:city":"Zottegem (elene - Oombergen)",
    "sg:classifiers":[
        {
            "category":"Wholesale",
            "subcategory":"Meat",
            "type":"Manufacturing & Wholesale Goods"
        }
    ],
    "sg:phone":"+32 9 360 74 16",
    "sg:postcode":"9620",
    "sg:province":"Oost-Vlaanderen",
    "sg:tags":[
        "whol",
        "-"
    ],
    "wof:name":"Van Audenhove L",
    "wof:placetype":"venue"
},
  "geometry": {"coordinates":[3.8218100071,50.8829841614],"type":"Point"}
}