{
  "type": "Feature",
  "properties": {
    "addr:full":"Rue Du Lombard 41b Bruxelles Bruxelles-Capitale 1000",
    "addr:housenumber":"41b",
    "addr:postcode":"1000",
    "addr:street":"Rue Du Lombard",
    "iso:country":"BE",
    "sg:address":"Rue Du Lombard 41b",
    "sg:city":"Bruxelles",
    "sg:classifiers":[
        {
            "category":"Building & Trades",
            "subcategory":"Construction",
            "type":"Services"
        }
    ],
    "sg:phone":"+32 2 513 50 15",
    "sg:postcode":"1000",
    "sg:province":"Bruxelles-Capitale",
    "sg:tags":[
        "tapestry"
    ],
    "wof:name":"Textilux Center",
    "wof:placetype":"venue"
},
  "geometry": {"coordinates":[4.3507881165,50.845451355],"type":"Point"}
}