{
  "type": "Feature",
  "properties": {
    "addr:full":"Baron Ruzettelaan 131 Brugge West-Vlaanderen 8310",
    "addr:housenumber":"131",
    "addr:postcode":"8310",
    "addr:street":"Baron Ruzettelaan",
    "iso:country":"BE",
    "sg:address":"Baron Ruzettelaan 131",
    "sg:city":"Brugge",
    "sg:orig_category":"Dranken",
    "sg:phone":"+32 50 35 65 01",
    "sg:postcode":"8310",
    "sg:province":"West-Vlaanderen",
    "wof:name":"Olivier Boutelegier",
    "wof:placetype":"venue"
},
  "geometry": {"coordinates":[3.2321031094,51.1946411133],"type":"Point"}
}