{
  "type": "Feature",
  "properties": {
    "addr:full":"Ichtegemstraat 130 Koekelare West-Vlaanderen 8680",
    "addr:housenumber":"130",
    "addr:postcode":"8680",
    "addr:street":"Ichtegemstraat",
    "iso:country":"BE",
    "sg:address":"Ichtegemstraat 130",
    "sg:city":"Koekelare",
    "sg:orig_category":"Schoonheidssalons",
    "sg:phone":"+32 51 58 28 75",
    "sg:postcode":"8680",
    "sg:province":"West-Vlaanderen",
    "wof:name":"Hilde Coucke",
    "wof:placetype":"venue"
},
  "geometry": {"coordinates":[2.9934670925,51.0907516479],"type":"Point"}
}