{
  "type": "Feature",
  "properties": {
    "addr:full":"Vaartstraat 65 Oudenburg West-Vlaanderen 8460",
    "addr:housenumber":"65",
    "addr:postcode":"8460",
    "addr:street":"Vaartstraat",
    "iso:country":"BE",
    "sg:address":"Vaartstraat 65",
    "sg:city":"Oudenburg",
    "sg:classifiers":[
        {
            "category":"Personal",
            "subcategory":"Sauna",
            "type":"Services"
        }
    ],
    "sg:phone":"+32 59 26 64 34",
    "sg:postcode":"8460",
    "sg:province":"West-Vlaanderen",
    "wof:name":"Fit Line Sauna-center",
    "wof:placetype":"venue"
},
  "geometry": {"coordinates":[2.996409893,51.1877326965],"type":"Point"}
}