{
  "type": "Feature",
  "properties": {
    "addr:full":"Leopoldstraat 66 Zemst Vlaams-Brabant 1980",
    "addr:housenumber":"66",
    "addr:postcode":"1980",
    "addr:street":"Leopoldstraat;Vlaams-Brabant",
    "iso:country":"BE",
    "sg:address":"Leopoldstraat 66",
    "sg:city":"Zemst",
    "sg:classifiers":[
        {
            "category":"Taxi",
            "type":"Transportation"
        }
    ],
    "sg:phone":"+32 15 61 36 60",
    "sg:postcode":"1980",
    "sg:province":"Vlaams-Brabant",
    "sg:tags":[
        "taxi's"
    ],
    "wof:name":"Juliens Taxi",
    "wof:placetype":"venue"
},
  "geometry": {"coordinates":[4.460624218,50.9831237793],"type":"Point"}
}