{
  "type": "Feature",
  "properties": {
    "iso:country":"BE",
    "sg:address":"Camille Huysmanslaan 94",
    "sg:city":"Antwerpen",
    "sg:orig_category":"M\u00e9decins and sp\u00e9cialistes",
    "sg:phone":"+32 3 238 68 80",
    "sg:postcode":"2020",
    "sg:province":"Antwerpen",
    "wof:name":"W. Neyes",
    "wof:placetype":"venue"
},
  "geometry": {"coordinates":[4.3908581734,51.1910057068],"type":"Point"}
}