{
  "type": "Feature",
  "properties": {
    "iso:country":"BE",
    "sg:address":"Jan Vandersteenstraat 8",
    "sg:city":"Sint-pieters-leeuw",
    "sg:orig_category":"Loodgieterij, verwarming and sanitaire installaties",
    "sg:phone":"+32 2 532 12 19",
    "sg:postcode":"1600",
    "sg:province":"Vlaams-Brabant",
    "wof:name":"Guido Walravens",
    "wof:placetype":"venue"
},
  "geometry": {"coordinates":[4.1982798576,50.7788505554],"type":"Point"}
}