{
  "type": "Feature",
  "properties": {
    "addr:full":"Rue Leopold Aubry 70 La Louvi\u00e8re (str\u00e9py-bracquegnies) Hainaut 7110",
    "addr:housenumber":"70",
    "addr:postcode":"7110",
    "addr:street":"Rue Leopold Aubry",
    "iso:country":"BE",
    "sg:address":"Rue Leopold Aubry 70",
    "sg:city":"La Louvi\u00e8re (str\u00e9py-bracquegnies)",
    "sg:classifiers":[
        {
            "category":"Building & Trades",
            "subcategory":"Electrical",
            "type":"Services"
        }
    ],
    "sg:phone":"+32 64 67 36 82",
    "sg:postcode":"7110",
    "sg:province":"Hainaut",
    "sg:tags":[
        "electric",
        "-",
        "housewiring",
        "contractor"
    ],
    "wof:name":"Proietti W Ets",
    "wof:placetype":"venue"
},
  "geometry": {"coordinates":[4.1505050659,50.4826698303],"type":"Point"}
}