{
  "type": "Feature",
  "properties": {
    "addr:full":"Grote Markt 20 Poperinge West-Vlaanderen 8970",
    "addr:housenumber":"20",
    "addr:postcode":"8970",
    "addr:street":"Grote Markt",
    "iso:country":"BE",
    "sg:address":"Grote Markt 20",
    "sg:city":"Poperinge",
    "sg:classifiers":[
        {
            "category":"Bars & Pubs",
            "type":"Food & Drink"
        }
    ],
    "sg:phone":"+32 57 33 95 78",
    "sg:postcode":"8970",
    "sg:province":"West-Vlaanderen",
    "wof:name":"Caf\u00e9 De La Paix",
    "wof:placetype":"venue"
},
  "geometry": {"coordinates":[2.725620985,50.8558540344],"type":"Point"}
}