{
  "type": "Feature",
  "properties": {
    "addr:full":"Avenue Louise 245 Brussel/bruxelles Bruxelles-Capitale 1050",
    "addr:housenumber":"245",
    "addr:postcode":"1050",
    "addr:street":"Avenue Louise;/",
    "iso:country":"BE",
    "sg:address":"Avenue Louise 245",
    "sg:city":"Brussel/bruxelles",
    "sg:classifiers":[
        {
            "category":"Health Services",
            "subcategory":"Nursing And Care Facility",
            "type":"Services"
        }
    ],
    "sg:phone":"+32 2 641 06 50",
    "sg:postcode":"1050",
    "sg:province":"Bruxelles-Capitale",
    "sg:tags":[
        "public"
    ],
    "wof:name":"Admin. Contrib. Directes",
    "wof:placetype":"venue"
},
  "geometry": {"coordinates":[4.355919838,50.8357810974],"type":"Point"}
}