{
  "type": "Feature",
  "properties": {
    "iso:country":"BE",
    "sg:address":"Alsembergsesteenweg 167",
    "sg:city":"Halle (buizingen)",
    "sg:classifiers":[
        {
            "category":"Health Services",
            "subcategory":"Health Practitioner",
            "type":"Services"
        }
    ],
    "sg:phone":"+32 2 356 41 75",
    "sg:postcode":"1501",
    "sg:province":"Vlaams-Brabant",
    "sg:tags":[
        "physiotherapist"
    ],
    "wof:name":"Janssens Lut",
    "wof:placetype":"venue"
},
  "geometry": {"coordinates":[4.2496151924,50.7407913208],"type":"Point"}
}