{
  "type": "Feature",
  "properties": {
    "iso:country":"BE",
    "sg:address":"Hopveldweg 6",
    "sg:city":"Buggenhout",
    "sg:classifiers":[
        {
            "category":"Building & Trades",
            "subcategory":"Pest Control",
            "type":"Services"
        }
    ],
    "sg:phone":"+32 475 56 49 89",
    "sg:postcode":"9255",
    "sg:province":"Oost-Vlaanderen",
    "sg:tags":[
        "painting",
        "contractor"
    ],
    "wof:name":"Peeleman B",
    "wof:placetype":"venue"
},
  "geometry": {"coordinates":[4.1581420898,51.021396637],"type":"Point"}
}