{
  "type": "Feature",
  "properties": {
    "addr:full":"Avenue Albert Ier 75 Huy Li\u00e8ge 4500",
    "addr:housenumber":"75",
    "addr:postcode":"4500",
    "addr:street":"Avenue Albert Ier",
    "iso:country":"BE",
    "sg:address":"Avenue Albert Ier 75",
    "sg:city":"Huy",
    "sg:orig_category":"Architecten",
    "sg:phone":"+32 85 41 22 25",
    "sg:postcode":"4500",
    "sg:province":"Li\u00e8ge",
    "wof:name":"S\u00c9bastien Deckmyn",
    "wof:placetype":"venue"
},
  "geometry": {"coordinates":[5.2331228256,50.5259552002],"type":"Point"}
}