{
  "type": "Feature",
  "properties": {
    "addr:full":"Rue De France 11 Sivry-rance Hainaut 6470",
    "addr:housenumber":"11",
    "addr:postcode":"6470",
    "addr:street":"Rue De France",
    "iso:country":"BE",
    "sg:address":"Rue De France 11",
    "sg:city":"Sivry-rance",
    "sg:orig_category":"Rundveehouders",
    "sg:phone":"+32 60 45 51 47",
    "sg:postcode":"6470",
    "sg:province":"Hainaut",
    "wof:name":"Andre Charlotteaux",
    "wof:placetype":"venue"
},
  "geometry": {"coordinates":[4.225730896,50.1628303528],"type":"Point"}
}