{
  "type": "Feature",
  "properties": {
    "addr:full":"Avenue De La Toison D'or 12 Bruxelles (ixelles) Bruxelles-Capitale 1050",
    "addr:housenumber":"12",
    "addr:postcode":"1050",
    "addr:street":"Avenue De La Toison D'Or",
    "iso:country":"BE",
    "sg:address":"Avenue De La Toison D'or 12",
    "sg:city":"Bruxelles (ixelles)",
    "sg:classifiers":[
        {
            "category":"Personal",
            "subcategory":"Barber",
            "type":"Services"
        }
    ],
    "sg:phone":"+32 2 515 11 11",
    "sg:postcode":"1050",
    "sg:province":"Bruxelles-Capitale",
    "sg:tags":[
        "gentleman",
        "salon",
        "-",
        "hairdressing"
    ],
    "wof:name":"Toni & Guy",
    "wof:placetype":"venue"
},
  "geometry": {"coordinates":[4.3798799515,50.8206710815],"type":"Point"}
}