{
  "type": "Feature",
  "properties": {
    "addr:full":"Boulevard De La Cambre 33 Bruxelles Bruxelles-Capitale 1000",
    "addr:housenumber":"33",
    "addr:postcode":"1000",
    "addr:street":"Boulevard De La Cambre",
    "iso:country":"BE",
    "sg:address":"Boulevard De La Cambre 33",
    "sg:city":"Bruxelles",
    "sg:classifiers":[
        {
            "category":"Communications",
            "subcategory":"Film & Video Production",
            "type":"Services"
        }
    ],
    "sg:phone":"+32 2 649 78 32",
    "sg:postcode":"1000",
    "sg:province":"Bruxelles-Capitale",
    "sg:tags":[
        "multimedia",
        "-",
        "system"
    ],
    "wof:name":"Mediadreams Sa",
    "wof:placetype":"venue"
},
  "geometry": {"coordinates":[4.374420166,50.8161697388],"type":"Point"}
}