{
  "type": "Feature",
  "properties": {
    "iso:country":"BE",
    "sg:address":"De S\u00c9vign\u00c9straat 12",
    "sg:city":"Anderlecht/anderlecht",
    "sg:orig_category":"Apotheken",
    "sg:phone":"+32 2 522 09 51",
    "sg:postcode":"1070",
    "sg:province":"Bruxelles-Capitale",
    "wof:name":"Multipharma",
    "wof:placetype":"venue"
},
  "geometry": {"coordinates":[4.2905259132,50.8446998596],"type":"Point"}
}