{
  "type": "Feature",
  "properties": {
    "addr:full":"Rue Haute 250 Brussel/bruxelles Bruxelles-Capitale 1000",
    "addr:housenumber":"250",
    "addr:postcode":"1000",
    "addr:street":"Rue Haute;/",
    "iso:country":"BE",
    "sg:address":"Rue Haute 250",
    "sg:city":"Brussel/bruxelles",
    "sg:orig_category":"Pharmaciens",
    "sg:phone":"+32 2 511 99 62",
    "sg:postcode":"1000",
    "sg:province":"Bruxelles-Capitale",
    "wof:name":"G. Degelin",
    "wof:placetype":"venue"
},
  "geometry": {"coordinates":[4.3483910561,50.8366088867],"type":"Point"}
}