{
  "type": "Feature",
  "properties": {
    "iso:country":"BE",
    "sg:address":"Tervuursesteenweg 295",
    "sg:city":"Bertem",
    "sg:orig_category":"Openbare veiligheid",
    "sg:phone":"+32 16 49 92 30",
    "sg:postcode":"3060",
    "sg:province":"Vlaams-Brabant",
    "wof:name":"Federale Politie",
    "wof:placetype":"venue"
},
  "geometry": {"coordinates":[4.6064600945,50.8594017029],"type":"Point"}
}