{
  "type": "Feature",
  "properties": {
    "iso:country":"BE",
    "sg:address":"Konrad Adenauerlaan 3",
    "sg:city":"Sint-lambrechts-woluwe/woluwe-saint-lambert",
    "sg:orig_category":"Volwassenenonderwijs",
    "sg:phone":"+32 2 772 10 90",
    "sg:postcode":"1200",
    "sg:province":"Bruxelles-Capitale",
    "wof:name":"E.p.h.e.c.",
    "wof:placetype":"venue"
},
  "geometry": {"coordinates":[4.4492521286,50.8499298096],"type":"Point"}
}