{
  "type": "Feature",
  "properties": {
    "iso:country":"BE",
    "sg:address":"Rue Saint-roch 20",
    "sg:city":"Gerpinnes",
    "sg:orig_category":"Eleveurs de bovins",
    "sg:phone":"+32 71 50 11 67",
    "sg:postcode":"6280",
    "sg:province":"Hainaut",
    "wof:name":"Jacques Collet",
    "wof:placetype":"venue"
},
  "geometry": {"coordinates":[4.5220909119,50.3401069641],"type":"Point"}
}