{
  "type": "Feature",
  "properties": {
    "addr:full":"F\u00e9ronstr\u00e9e 43 Li\u00e8ge 1 Li\u00e8ge 4000",
    "addr:housenumber":"43;1",
    "addr:postcode":"4000",
    "addr:street":"Fe\u0301Ronstre\u0301E",
    "iso:country":"BE",
    "sg:address":"F\u00e9ronstr\u00e9e 43",
    "sg:city":"Li\u00e8ge 1",
    "sg:classifiers":[
        {
            "category":"Personal",
            "subcategory":"Beauty Salon",
            "type":"Services"
        }
    ],
    "sg:phone":"+32 4 221 10 31",
    "sg:postcode":"4000",
    "sg:province":"Li\u00e8ge",
    "sg:tags":[
        "lady",
        "-",
        "hairdressing"
    ],
    "wof:name":"Cafresta",
    "wof:placetype":"venue"
},
  "geometry": {"coordinates":[5.5784859657,50.6463928223],"type":"Point"}
}