{
  "type": "Feature",
  "properties": {
    "iso:country":"BE",
    "sg:address":"Krokussenlaan 7",
    "sg:city":"Herent",
    "sg:orig_category":"Ecoles de pilotage de bateaux and d\u00b4avions. Clubs de sport",
    "sg:phone":"+32 16 48 80 35",
    "sg:postcode":"3020",
    "sg:province":"Vlaams-Brabant",
    "wof:name":"Kempische Aero Club",
    "wof:placetype":"venue"
},
  "geometry": {"coordinates":[4.6749200821,50.9079055786],"type":"Point"}
}