{
  "type": "Feature",
  "properties": {
    "iso:country":"BE",
    "sg:address":"Rue Des Plantes 98",
    "sg:city":"Bruxelles",
    "sg:classifiers":[
        {
            "category":"Professional",
            "subcategory":"Advertising",
            "type":"Services"
        }
    ],
    "sg:phone":"+32 2 217 35 23",
    "sg:postcode":"1210",
    "sg:province":"Bruxelles-Capitale",
    "sg:tags":[
        "information",
        "medium",
        "communication"
    ],
    "wof:name":"Laboratoire Titra Sa",
    "wof:placetype":"venue"
},
  "geometry": {"coordinates":[4.3634419441,50.8591117859],"type":"Point"}
}