{
  "type": "Feature",
  "properties": {
    "addr:full":"Avenue De La Floride 127 Ukkel/uccle Bruxelles-Capitale 1180",
    "addr:housenumber":"127",
    "addr:postcode":"1180",
    "addr:street":"Avenue De La Floride;/",
    "iso:country":"BE",
    "sg:address":"Avenue De La Floride 127",
    "sg:city":"Ukkel/uccle",
    "sg:orig_category":"M\u00e9decins and sp\u00e9cialistes",
    "sg:phone":"+32 2 640 04 32",
    "sg:postcode":"1180",
    "sg:province":"Bruxelles-Capitale",
    "wof:name":"R\u00c9gis De Muylder",
    "wof:placetype":"venue"
},
  "geometry": {"coordinates":[4.3625478745,50.8041954041],"type":"Point"}
}