{
  "type": "Feature",
  "properties": {
    "iso:country":"BE",
    "sg:address":"Rue Maurice Dumont 9",
    "sg:city":"Saint-ghislain (neufmaison)",
    "sg:classifiers":[
        {
            "category":"Arts & Performance",
            "subcategory":"Music",
            "type":"Entertainment"
        }
    ],
    "sg:phone":"+32 65 62 12 45",
    "sg:postcode":"7332",
    "sg:province":"Hainaut",
    "sg:tags":[
        "freelance",
        "musician"
    ],
    "wof:name":"Piano Solo",
    "wof:placetype":"venue"
},
  "geometry": {"coordinates":[3.786839962,50.5054969788],"type":"Point"}
}