{
  "type": "Feature",
  "properties": {
    "addr:full":"Lindedorp 12 Peer Limburg 3990",
    "addr:housenumber":"12",
    "addr:postcode":"3990",
    "addr:street":"Lindedorp",
    "iso:country":"BE",
    "sg:address":"Lindedorp 12",
    "sg:city":"Peer",
    "sg:orig_category":"Enseignement maternel and primaire",
    "sg:phone":"+32 11 79 13 92",
    "sg:postcode":"3990",
    "sg:province":"Limburg",
    "wof:name":"Vrije Kleuterschool",
    "wof:placetype":"venue"
},
  "geometry": {"coordinates":[5.4443697929,51.0933189392],"type":"Point"}
}