{
  "type": "Feature",
  "properties": {
    "addr:full":"St Elooiswinkelstraat 8 Ledegem West-Vlaanderen 8880",
    "addr:housenumber":"8",
    "addr:postcode":"8880",
    "addr:street":"Elooiswinkelstraat",
    "iso:country":"BE",
    "sg:address":"St Elooiswinkelstraat 8",
    "sg:city":"Ledegem",
    "sg:orig_category":"Dierenartsen Drogisterijen Royal Canin",
    "sg:phone":"+32 56 50 22 34",
    "sg:postcode":"8880",
    "sg:province":"West-Vlaanderen",
    "wof:name":"D'hulster Bart",
    "wof:placetype":"venue"
},
  "geometry": {"coordinates":[3.1239609718,50.8588180542],"type":"Point"}
}