{
  "type": "Feature",
  "properties": {
    "iso:country":"BE",
    "sg:address":"Speurtstraat 1",
    "sg:city":"Lede (oordegem)",
    "sg:classifiers":[
        {
            "category":"Shopping",
            "subcategory":"Clothing, Apparel, & Fashions",
            "type":"Retail Goods"
        }
    ],
    "sg:phone":"+32 9 369 08 53",
    "sg:postcode":"9340",
    "sg:province":"Oost-Vlaanderen",
    "sg:tags":[
        "clothing",
        "-",
        "gentleman"
    ],
    "wof:name":"Ediers Wed",
    "wof:placetype":"venue"
},
  "geometry": {"coordinates":[3.9010140896,50.9583053589],"type":"Point"}
}