{
  "type": "Feature",
  "properties": {
    "addr:full":"Krommewege 78 Maldegem Oost-Vlaanderen 9990",
    "addr:housenumber":"78",
    "addr:postcode":"9990",
    "addr:street":"Krommewege",
    "iso:country":"BE",
    "sg:address":"Krommewege 78",
    "sg:city":"Maldegem",
    "sg:orig_category":"SMEEDWERK, METAALBEWERKING AND POEDERMETALLURGIE",
    "sg:phone":"+32 50 71 57 66",
    "sg:postcode":"9990",
    "sg:province":"Oost-Vlaanderen",
    "wof:name":"De Roo W.",
    "wof:placetype":"venue"
},
  "geometry": {"coordinates":[3.4703900814,51.1936912537],"type":"Point"}
}