{
  "type": "Feature",
  "properties": {
    "addr:full":"Rue De La Station 7 Houyet Namur 5560",
    "addr:housenumber":"7",
    "addr:postcode":"5560",
    "addr:street":"Rue De La Station",
    "iso:country":"BE",
    "sg:address":"Rue De La Station 7",
    "sg:city":"Houyet",
    "sg:orig_category":"Brood, gebak and snoepgoed",
    "sg:phone":"+32 82 66 66 24",
    "sg:postcode":"5560",
    "sg:province":"Namur",
    "wof:name":"G. Haquenne",
    "wof:placetype":"venue"
},
  "geometry": {"coordinates":[5.0054941177,50.1886138916],"type":"Point"}
}