{
  "type": "Feature",
  "properties": {
    "addr:full":"Kere 17 Waarschoot Oost-Vlaanderen 9950",
    "addr:housenumber":"17",
    "addr:postcode":"9950",
    "addr:street":"Kere",
    "iso:country":"BE",
    "sg:address":"Kere 17",
    "sg:city":"Waarschoot",
    "sg:orig_category":"Boucheries",
    "sg:phone":"+32 9 377 15 01",
    "sg:postcode":"9950",
    "sg:province":"Oost-Vlaanderen",
    "wof:name":"Beenhouwerij Luc",
    "wof:placetype":"venue"
},
  "geometry": {"coordinates":[3.5963189602,51.1543502808],"type":"Point"}
}