{
  "type": "Feature",
  "properties": {
    "addr:full":"Kerkhofstraat 80 Londerzeel Vlaams-Brabant 1840",
    "addr:housenumber":"80",
    "addr:postcode":"1840",
    "addr:street":"Kerkhofstraat",
    "iso:country":"BE",
    "sg:address":"Kerkhofstraat 80",
    "sg:city":"Londerzeel",
    "sg:orig_category":"Agences d'exp\u00e9dition",
    "sg:phone":"+32 52 30 57 11",
    "sg:postcode":"1840",
    "sg:province":"Vlaams-Brabant",
    "wof:name":"Belimpex",
    "wof:placetype":"venue"
},
  "geometry": {"coordinates":[4.3077440262,51.0021362305],"type":"Point"}
}