{
  "type": "Feature",
  "properties": {
    "iso:country":"BE",
    "sg:address":"Eugeen Van De Vellaan 70",
    "sg:city":"Schilde",
    "sg:classifiers":[
        {
            "category":"Professional",
            "subcategory":"Management & Consulting",
            "type":"Services"
        }
    ],
    "sg:phone":"+32 3 384 22 06",
    "sg:postcode":"2970",
    "sg:province":"Antwerpen",
    "sg:tags":[
        "consultant"
    ],
    "wof:name":"Assist-consult Bvba",
    "wof:placetype":"venue"
},
  "geometry": {"coordinates":[4.5734829903,51.2425003052],"type":"Point"}
}