{
  "type": "Feature",
  "properties": {
    "addr:full":"Rue Du Travail 83 Sambreville (auvelais) Namur 5060",
    "addr:housenumber":"83",
    "addr:postcode":"5060",
    "addr:street":"Rue Du Travail",
    "iso:country":"BE",
    "sg:address":"Rue Du Travail 83",
    "sg:city":"Sambreville (auvelais)",
    "sg:classifiers":[
        {
            "category":"Manufacturing",
            "subcategory":"Tools & Machinery",
            "type":"Manufacturing & Wholesale Goods"
        }
    ],
    "sg:phone":"+32 71 77 25 11",
    "sg:postcode":"5060",
    "sg:province":"Namur",
    "sg:tags":[
        "builder"
    ],
    "wof:name":"Delmeca",
    "wof:placetype":"venue"
},
  "geometry": {"coordinates":[4.6285200119,50.4448738098],"type":"Point"}
}