{
  "type": "Feature",
  "properties": {
    "addr:full":"Avenue Edouard Lacombl\u00e9 17 Bruxelles (etterbeek) Bruxelles-Capitale 1040",
    "addr:housenumber":"17",
    "addr:postcode":"1040",
    "addr:street":"Avenue Edouard Lacomble\u0301",
    "iso:country":"BE",
    "sg:address":"Avenue Edouard Lacombl\u00e9 17",
    "sg:city":"Bruxelles (etterbeek)",
    "sg:classifiers":[
        {
            "category":"Social Services",
            "subcategory":"Job Training",
            "type":"Services"
        }
    ],
    "sg:phone":"+32 2 732 29 20",
    "sg:postcode":"1040",
    "sg:province":"Bruxelles-Capitale",
    "sg:tags":[
        "personnel",
        "-selection",
        "recruitment"
    ],
    "wof:name":"Prospective Management Overseas",
    "wof:placetype":"venue"
},
  "geometry": {"coordinates":[4.4092960358,50.8325843811],"type":"Point"}
}