{
  "type": "Feature",
  "properties": {
    "iso:country":"BE",
    "sg:address":"Avenue Du Ch\u00cane Saint-jean 31",
    "sg:city":"Charleroi",
    "sg:orig_category":"Installation de menuiserie en bois and plastique. Fabrication and montage de mobilier",
    "sg:phone":"+32 71 37 18 44",
    "sg:postcode":"6041",
    "sg:province":"Hainaut",
    "wof:name":"Bruynzeel Cuisines",
    "wof:placetype":"venue"
},
  "geometry": {"coordinates":[4.4314317703,50.4685935974],"type":"Point"}
}