{
  "type": "Feature",
  "properties": {
    "iso:country":"BE",
    "sg:address":"Dorpsstraat 87",
    "sg:city":"Tielt-winge",
    "sg:orig_category":"Installation \u00e9lectrique r\u00e9sidentielle",
    "sg:phone":"+32 16 50 12 24",
    "sg:postcode":"3390",
    "sg:province":"Vlaams-Brabant",
    "wof:name":"Joseph Van Aerschot",
    "wof:placetype":"venue"
},
  "geometry": {"coordinates":[4.916258812,50.9453926086],"type":"Point"}
}