{
  "type": "Feature",
  "properties": {
    "addr:full":"Rue Saint-roch 12 Profondeville Namur 5170",
    "addr:housenumber":"12",
    "addr:postcode":"5170",
    "addr:street":"Rue Saint-Roch",
    "iso:country":"BE",
    "sg:address":"Rue Saint-roch 12",
    "sg:city":"Profondeville",
    "sg:orig_category":"Slagers",
    "sg:phone":"+32 81 41 26 94",
    "sg:postcode":"5170",
    "sg:province":"Namur",
    "wof:name":"Christian Dochain",
    "wof:placetype":"venue"
},
  "geometry": {"coordinates":[4.9034948349,50.3800773621],"type":"Point"}
}