{
  "type": "Feature",
  "properties": {
    "iso:country":"BE",
    "sg:address":"Toekomstlaan 27",
    "sg:city":"Herentals",
    "sg:orig_category":"Bouwmaterialen Gh Loodgieterij, verwarming and sanitaire installaties",
    "sg:phone":"+32 14 21 87 03",
    "sg:postcode":"2200",
    "sg:province":"Antwerpen",
    "wof:name":"Henco Industries",
    "wof:placetype":"venue"
},
  "geometry": {"coordinates":[4.8015589714,51.1632881165],"type":"Point"}
}