{
  "type": "Feature",
  "properties": {
    "addr:full":"Route De L'etat 5 Box 2 Lasne (lasne-chapelle-saint-lambert) Brabant Wallon 1380",
    "addr:housenumber":"5;2",
    "addr:postcode":"1380",
    "addr:street":"Route De L'Etat;Box;Wallon",
    "iso:country":"BE",
    "sg:address":"Route De L'etat 5 Box 2",
    "sg:city":"Lasne (lasne-chapelle-saint-lambert)",
    "sg:classifiers":[
        {
            "category":"Professional",
            "subcategory":"Accounting & Tax Preparation",
            "type":"Services"
        }
    ],
    "sg:phone":"+32 2 633 69 34",
    "sg:postcode":"1380",
    "sg:province":"Brabant Wallon",
    "sg:tags":[
        "bookkeeper"
    ],
    "wof:name":"Lasco Scris",
    "wof:placetype":"venue"
},
  "geometry": {"coordinates":[4.4813570976,50.6839637756],"type":"Point"}
}