{
  "type": "Feature",
  "properties": {
    "iso:country":"BE",
    "sg:address":"Spechtendreef 24",
    "sg:city":"Zoersel (halle)",
    "sg:classifiers":[
        {
            "category":"Professional",
            "subcategory":"Management & Consulting",
            "type":"Services"
        }
    ],
    "sg:phone":"+32 3 384 30 04",
    "sg:postcode":"2980",
    "sg:province":"Antwerpen",
    "sg:tags":[
        "consultant"
    ],
    "wof:name":"Retema Nv",
    "wof:placetype":"venue"
},
  "geometry": {"coordinates":[4.713435173,51.269985199],"type":"Point"}
}