{
  "type": "Feature",
  "properties": {
    "addr:full":"Antwerpsestraat 59b4 Boom Antwerpen 2850",
    "addr:housenumber":"59b4",
    "addr:postcode":"2850",
    "addr:street":"Antwerpsestraat",
    "iso:country":"BE",
    "sg:address":"Antwerpsestraat 59b4",
    "sg:city":"Boom",
    "sg:orig_category":"Artsen and specialisten",
    "sg:phone":"+32 3 844 75 35",
    "sg:postcode":"2850",
    "sg:province":"Antwerpen",
    "wof:name":"M. Nelis",
    "wof:placetype":"venue"
},
  "geometry": {"coordinates":[4.3649740219,51.0891914368],"type":"Point"}
}