{
  "type": "Feature",
  "properties": {
    "addr:full":"R Du Dobbelenberg 115 Bruxelles Bruxelles-Capitale 1130",
    "addr:housenumber":"115",
    "addr:postcode":"1130",
    "addr:street":"R Du Dobbelenberg",
    "iso:country":"BE",
    "sg:address":"R Du Dobbelenberg 115",
    "sg:city":"Bruxelles",
    "sg:classifiers":[
        {
            "category":"Food & Beverages",
            "subcategory":"Groceries & Convenience Stores",
            "type":"Retail Goods"
        }
    ],
    "sg:phone":"+32 2 240 75 75",
    "sg:postcode":"1130",
    "sg:province":"Bruxelles-Capitale",
    "sg:tags":[
        "product",
        "related"
    ],
    "wof:name":"Ferrarese (la) Sa",
    "wof:placetype":"venue"
},
  "geometry": {"coordinates":[4.4171171188,50.9047355652],"type":"Point"}
}