{
  "type": "Feature",
  "properties": {
    "iso:country":"BE",
    "sg:address":"Nijvelsesteenweg 272",
    "sg:city":"Halle",
    "sg:classifiers":[
        {
            "category":"Health Services",
            "subcategory":"Dentist",
            "type":"Services"
        }
    ],
    "sg:phone":"+32 2 361 63 21",
    "sg:postcode":"1500",
    "sg:province":"Vlaams-Brabant",
    "wof:name":"Muylle Dieter",
    "wof:placetype":"venue"
},
  "geometry": {"coordinates":[4.248524189,50.7226104736],"type":"Point"}
}