{
  "type": "Feature",
  "properties": {
    "addr:full":"Veerstraat 35 Wellen Limburg 3830",
    "addr:housenumber":"35",
    "addr:postcode":"3830",
    "addr:street":"Veerstraat",
    "iso:country":"BE",
    "sg:address":"Veerstraat 35",
    "sg:city":"Wellen",
    "sg:orig_category":"Schoonheidssalons",
    "sg:phone":"+32 12 74 14 08",
    "sg:postcode":"3830",
    "sg:province":"Limburg",
    "wof:name":"Alice Bulen",
    "wof:placetype":"venue"
},
  "geometry": {"coordinates":[5.3221130371,50.8443908691],"type":"Point"}
}