{
  "type": "Feature",
  "properties": {
    "addr:full":"Rue D'elvaux 28 Herve Li\u00e8ge 4650",
    "addr:housenumber":"28",
    "addr:postcode":"4650",
    "addr:street":"Rue D'Elvaux",
    "iso:country":"BE",
    "sg:address":"Rue D'elvaux 28",
    "sg:city":"Herve",
    "sg:classifiers":[
        {
            "category":"Education",
            "subcategory":"School",
            "type":"Public Place"
        }
    ],
    "sg:phone":"+32 87 67 45 44",
    "sg:postcode":"4650",
    "sg:province":"Li\u00e8ge",
    "sg:tags":[
        "primary"
    ],
    "wof:name":"Ecole Fondamentale Libre Subventionn\u00e9e",
    "wof:placetype":"venue"
},
  "geometry": {"coordinates":[5.7948169708,50.6384620667],"type":"Point"}
}