{
  "type": "Feature",
  "properties": {
    "addr:full":"Rue Du Roi Albert 46 Oupeye Li\u00e8ge 4680",
    "addr:housenumber":"46",
    "addr:postcode":"4680",
    "addr:street":"Rue Du Roi Albert",
    "iso:country":"BE",
    "sg:address":"Rue Du Roi Albert 46",
    "sg:city":"Oupeye",
    "sg:classifiers":[
        {
            "category":"Retail",
            "subcategory":"Auto Repair",
            "type":"Services"
        }
    ],
    "sg:phone":"+32 4 248 22 19",
    "sg:postcode":"4680",
    "sg:province":"Li\u00e8ge",
    "sg:tags":[
        "automobile-body"
    ],
    "wof:name":"Passuello J",
    "wof:placetype":"venue"
},
  "geometry": {"coordinates":[5.6497340202,50.7051811218],"type":"Point"}
}