{
  "type": "Feature",
  "properties": {
    "addr:full":"Avenue Des H\u00c9ros Leuzois 71 Leuze-en-hainaut Hainaut 7900",
    "addr:housenumber":"71",
    "addr:postcode":"7900",
    "addr:street":"Avenue Des He\u0301Ros Leuzois",
    "iso:country":"BE",
    "sg:address":"Avenue Des H\u00c9ros Leuzois 71",
    "sg:city":"Leuze-en-hainaut",
    "sg:orig_category":"Jeux de hasard",
    "sg:phone":"+32 69 66 61 37",
    "sg:postcode":"7900",
    "sg:province":"Hainaut",
    "wof:name":"Tierc\u00c9 Vincennes",
    "wof:placetype":"venue"
},
  "geometry": {"coordinates":[3.6310040951,50.5998764038],"type":"Point"}
}