{
  "type": "Feature",
  "properties": {
    "addr:full":"Rue Gallait 26 Tournai Hainaut 7500",
    "addr:housenumber":"26",
    "addr:postcode":"7500",
    "addr:street":"Rue Gallait",
    "iso:country":"BE",
    "sg:address":"Rue Gallait 26",
    "sg:city":"Tournai",
    "sg:classifiers":[
        {
            "category":"Retail",
            "subcategory":"Repair Shop",
            "type":"Services"
        }
    ],
    "sg:phone":"+32 69 84 04 40",
    "sg:postcode":"7500",
    "sg:province":"Hainaut",
    "sg:tags":[
        "-",
        "clothing",
        "alteration"
    ],
    "wof:name":"De Fil En Aiguille",
    "wof:placetype":"venue"
},
  "geometry": {"coordinates":[3.3910939693,50.6060752869],"type":"Point"}
}