{
  "type": "Feature",
  "properties": {
    "addr:full":"Chauss\u00e9e De Boondael 518 Bruxelles (ixelles) Bruxelles-Capitale 1050",
    "addr:housenumber":"518",
    "addr:postcode":"1050",
    "addr:street":"Chausse\u0301E De Boondael",
    "iso:country":"BE",
    "sg:address":"Chauss\u00e9e De Boondael 518",
    "sg:city":"Bruxelles (ixelles)",
    "sg:classifiers":[
        {
            "category":"Bars & Pubs",
            "type":"Food & Drink"
        }
    ],
    "sg:phone":"+32 2 644 32 90",
    "sg:postcode":"1050",
    "sg:province":"Bruxelles-Capitale",
    "wof:name":"Guet-a-pinte",
    "wof:placetype":"venue"
},
  "geometry": {"coordinates":[4.3913240433,50.8124198914],"type":"Point"}
}