{
  "type": "Feature",
  "properties": {
    "iso:country":"BE",
    "sg:address":"Rue Charles Dupuis 118",
    "sg:city":"Quaregnon",
    "sg:orig_category":"Cliniques and h\u00f4pitaux",
    "sg:phone":"+32 65 78 66 59",
    "sg:postcode":"7390",
    "sg:province":"Hainaut",
    "wof:name":"Clinique Dr.haquin",
    "wof:placetype":"venue"
},
  "geometry": {"coordinates":[3.8688099384,50.4423103333],"type":"Point"}
}