{
  "type": "Feature",
  "properties": {
    "iso:country":"BE",
    "sg:address":"Brugsesteenweg 148",
    "sg:city":"Gent",
    "sg:orig_category":"Beautyfarms, relaxatie and lichamelijk welzijn Kapsalons",
    "sg:phone":"+32 9 226 91 41",
    "sg:postcode":"9000",
    "sg:province":"Oost-Vlaanderen",
    "wof:name":"Valentino",
    "wof:placetype":"venue"
},
  "geometry": {"coordinates":[3.6939589977,51.0642127991],"type":"Point"}
}