{
  "type": "Feature",
  "properties": {
    "addr:full":"Rue De Wallonie 16 Ans Li\u00e8ge 4432",
    "addr:housenumber":"16",
    "addr:postcode":"4432",
    "addr:street":"Rue De Wallonie",
    "iso:country":"BE",
    "sg:address":"Rue De Wallonie 16",
    "sg:city":"Ans",
    "sg:orig_category":"Mat\u00e9riel pour plomberie and chauffage Mat\u00e9riaux de construction Quincailleries",
    "sg:phone":"+32 4 239 76 20",
    "sg:postcode":"4432",
    "sg:province":"Li\u00e8ge",
    "wof:name":"Facq",
    "wof:placetype":"venue"
},
  "geometry": {"coordinates":[5.5275559425,50.6705093384],"type":"Point"}
}