{
  "type": "Feature",
  "properties": {
    "addr:full":"Kard. J. Cardijnstraat 1 Sint-gillis-waas Oost-Vlaanderen 9170",
    "addr:housenumber":"1",
    "addr:postcode":"9170",
    "addr:street":"Cardijnstraat",
    "iso:country":"BE",
    "sg:address":"Kard. J. Cardijnstraat 1",
    "sg:city":"Sint-gillis-waas",
    "sg:orig_category":"Cr\u00e8ches and garderies d'enfants",
    "sg:phone":"+32 3 770 84 84",
    "sg:postcode":"9170",
    "sg:province":"Oost-Vlaanderen",
    "wof:name":"Kinderopvangd. B.g.j.g.",
    "wof:placetype":"venue"
},
  "geometry": {"coordinates":[4.1255750656,51.2189941406],"type":"Point"}
}