{
  "type": "Feature",
  "properties": {
    "iso:country":"BE",
    "sg:address":"Patersstraat 32 Box 1",
    "sg:city":"Turnhout",
    "sg:classifiers":[
        {
            "category":"Retail",
            "subcategory":"Repair Shop",
            "type":"Services"
        }
    ],
    "sg:phone":"+32 14 41 22 94",
    "sg:postcode":"2300",
    "sg:province":"Antwerpen",
    "sg:tags":[
        "machine",
        "sewing",
        "-"
    ],
    "wof:name":"Singer Naaicenter",
    "wof:placetype":"venue"
},
  "geometry": {"coordinates":[4.9499111176,51.3250656128],"type":"Point"}
}