{
  "type": "Feature",
  "properties": {
    "addr:full":"Oude Baan 51 Dendermonde (oudegem) Oost-Vlaanderen 9200",
    "addr:housenumber":"51",
    "addr:postcode":"9200",
    "addr:street":"Oude Baan",
    "iso:country":"BE",
    "sg:address":"Oude Baan 51",
    "sg:city":"Dendermonde (oudegem)",
    "sg:classifiers":[
        {
            "category":"Health Services",
            "subcategory":"Dentist",
            "type":"Services"
        }
    ],
    "sg:phone":"+32 52 21 28 17",
    "sg:postcode":"9200",
    "sg:province":"Oost-Vlaanderen",
    "wof:name":"Verhaegen Liesbeth",
    "wof:placetype":"venue"
},
  "geometry": {"coordinates":[4.1009860039,51.0290298462],"type":"Point"}
}