{
  "type": "Feature",
  "properties": {
    "addr:full":"Wollestraat 46 Oostkamp West-Vlaanderen 8020",
    "addr:housenumber":"46",
    "addr:postcode":"8020",
    "addr:street":"Wollestraat",
    "iso:country":"BE",
    "sg:address":"Wollestraat 46",
    "sg:city":"Oostkamp",
    "sg:orig_category":"Belastingconsulenten Diverse juridische dienstverlening",
    "sg:phone":"+32 50 82 46 24",
    "sg:postcode":"8020",
    "sg:province":"West-Vlaanderen",
    "wof:name":"M. Van Canneyt",
    "wof:placetype":"venue"
},
  "geometry": {"coordinates":[3.2575008869,51.1388206482],"type":"Point"}
}