{
  "type": "Feature",
  "properties": {
    "iso:country":"BE",
    "sg:address":"Van Cromphoutstraat 25",
    "sg:city":"Wetteren",
    "sg:classifiers":[
        {
            "category":"Professional",
            "subcategory":"Business Services",
            "type":"Services"
        }
    ],
    "sg:phone":"+32 9 366 21 95",
    "sg:postcode":"9230",
    "sg:province":"Oost-Vlaanderen",
    "sg:tags":[
        "machine",
        "mailing",
        "supply"
    ],
    "wof:name":"E.s.t. Bvba-sprl",
    "wof:placetype":"venue"
},
  "geometry": {"coordinates":[3.8833549023,51.0069732666],"type":"Point"}
}