{
  "type": "Feature",
  "properties": {
    "addr:full":"Werchtersesteenweg 168 Haacht Vlaams-Brabant 3150",
    "addr:housenumber":"168",
    "addr:postcode":"3150",
    "addr:street":"Werchtersesteenweg",
    "iso:country":"BE",
    "sg:address":"Werchtersesteenweg 168",
    "sg:city":"Haacht",
    "sg:orig_category":"Dakwerken",
    "sg:phone":"+32 16 60 02 70",
    "sg:postcode":"3150",
    "sg:province":"Vlaams-Brabant",
    "wof:name":"Haachtse Dakwerken",
    "wof:placetype":"venue"
},
  "geometry": {"coordinates":[4.6657800674,50.9718322754],"type":"Point"}
}