{
  "type": "Feature",
  "properties": {
    "addr:full":"Katharinenweg 15a Eupen (kettenis) Li\u00e8ge 4701",
    "addr:housenumber":"15a",
    "addr:postcode":"4701",
    "addr:street":"Katharinenweg",
    "iso:country":"BE",
    "sg:address":"Katharinenweg 15a",
    "sg:city":"Eupen (kettenis)",
    "sg:orig_category":"Non-Classified Establishments",
    "sg:phone":"+32 87 55 83 48",
    "sg:postcode":"4701",
    "sg:province":"Li\u00e8ge",
    "wof:name":"Helge I",
    "wof:placetype":"venue"
},
  "geometry": {"coordinates":[6.0484991074,50.634349823],"type":"Point"}
}