{
  "type": "Feature",
  "properties": {
    "iso:country":"BE",
    "sg:address":"Rue De Li\u00e8ge 5",
    "sg:city":"Lincent",
    "sg:classifiers":[
        {
            "category":"Wholesale",
            "subcategory":"Books, Periodicals, & Newspapers",
            "type":"Manufacturing & Wholesale Goods"
        }
    ],
    "sg:phone":"+32 19 65 69 27",
    "sg:postcode":"4287",
    "sg:province":"Li\u00e8ge",
    "sg:tags":[
        "publisher"
    ],
    "wof:name":"Phenix (editions)",
    "wof:placetype":"venue"
},
  "geometry": {"coordinates":[5.0402741432,50.7126197815],"type":"Point"}
}