{
  "type": "Feature",
  "properties": {
    "iso:country":"BE",
    "sg:address":"Route D'ath 177",
    "sg:city":"Jurbise",
    "sg:orig_category":"Supermarkten",
    "sg:phone":"+32 65 22 77 00",
    "sg:postcode":"7050",
    "sg:province":"Hainaut",
    "wof:name":"Intermarch\u00c9",
    "wof:placetype":"venue"
},
  "geometry": {"coordinates":[3.9220070839,50.5153388977],"type":"Point"}
}