{
  "type": "Feature",
  "properties": {
    "addr:full":"Mechelseweg 408 Kapelle-op-den-bos Vlaams-Brabant 1880",
    "addr:housenumber":"408",
    "addr:postcode":"1880",
    "addr:street":"Mechelseweg",
    "iso:country":"BE",
    "sg:address":"Mechelseweg 408",
    "sg:city":"Kapelle-op-den-bos",
    "sg:classifiers":[
        {
            "category":"Personal",
            "subcategory":"Beauty Salon",
            "type":"Services"
        }
    ],
    "sg:phone":"+32 15 71 34 70",
    "sg:postcode":"1880",
    "sg:province":"Vlaams-Brabant",
    "sg:tags":[
        "de",
        "coiffure"
    ],
    "wof:name":"Coiffure Yvette",
    "wof:placetype":"venue"
},
  "geometry": {"coordinates":[4.3693699837,51.0120887756],"type":"Point"}
}