{
  "type": "Feature",
  "properties": {
    "addr:full":"Rue De Matignol 5 Doische (matagne-la-petite) Namur 5680",
    "addr:housenumber":"5",
    "addr:postcode":"5680",
    "addr:street":"Rue De Matignol",
    "iso:country":"BE",
    "sg:address":"Rue De Matignol 5",
    "sg:city":"Doische (matagne-la-petite)",
    "sg:classifiers":[
        {
            "category":"Retail",
            "subcategory":"Auto Repair",
            "type":"Services"
        }
    ],
    "sg:phone":"+32 60 39 06 45",
    "sg:postcode":"5680",
    "sg:province":"Namur",
    "sg:tags":[
        "garage"
    ],
    "wof:name":"Hayot Jj Scrl Scrl",
    "wof:placetype":"venue"
},
  "geometry": {"coordinates":[4.6492199898,50.1127662659],"type":"Point"}
}