{
  "type": "Feature",
  "properties": {
    "addr:full":"Avenue Du Centenaire 305a Charleroi Hainaut 6061",
    "addr:housenumber":"305a",
    "addr:postcode":"6061",
    "addr:street":"Avenue Du Centenaire;Hainaut",
    "iso:country":"BE",
    "sg:address":"Avenue Du Centenaire 305a",
    "sg:city":"Charleroi",
    "sg:orig_category":"Bouwmaterialen Gh Installatie van houten of kunststof schrijnwerk",
    "sg:phone":"+32 71 41 57 19",
    "sg:postcode":"6061",
    "sg:province":"Hainaut",
    "wof:name":"Plastica",
    "wof:placetype":"venue"
},
  "geometry": {"coordinates":[4.4772028923,50.4124412537],"type":"Point"}
}