{
  "type": "Feature",
  "properties": {
    "iso:country":"BE",
    "sg:address":"Grote Steenweg 7",
    "sg:city":"Zoutleeuw",
    "sg:orig_category":"Voertuigen",
    "sg:phone":"+32 11 78 13 50",
    "sg:postcode":"3440",
    "sg:province":"Vlaams-Brabant",
    "wof:name":"Vd Cars",
    "wof:placetype":"venue"
},
  "geometry": {"coordinates":[5.1030359268,50.8328094482],"type":"Point"}
}