{
  "type": "Feature",
  "properties": {
    "iso:country":"BE",
    "sg:address":"Rue Joseph Triffaux 8",
    "sg:city":"Hannut (grand-hallet)",
    "sg:classifiers":[
        {
            "category":"Professional",
            "subcategory":"Advertising",
            "type":"Services"
        }
    ],
    "sg:phone":"+32 19 63 58 08",
    "sg:postcode":"4280",
    "sg:province":"Li\u00e8ge",
    "sg:tags":[
        "item",
        "-",
        "business",
        "gift",
        "promotional"
    ],
    "wof:name":"Publi Renta",
    "wof:placetype":"venue"
},
  "geometry": {"coordinates":[5.0148849487,50.6900444031],"type":"Point"}
}