{
  "type": "Feature",
  "properties": {
    "addr:full":"Priesteragiestraat 10 Wielsbeke West-Vlaanderen 8710",
    "addr:housenumber":"10",
    "addr:postcode":"8710",
    "addr:street":"Priesteragiestraat;West-Vlaanderen",
    "iso:country":"BE",
    "sg:address":"Priesteragiestraat 10",
    "sg:city":"Wielsbeke",
    "sg:orig_category":"Rev\u00eatements de sols and murs",
    "sg:phone":"+32 56 61 11 46",
    "sg:postcode":"8710",
    "sg:province":"West-Vlaanderen",
    "wof:name":"Kurt Ornelis",
    "wof:placetype":"venue"
},
  "geometry": {"coordinates":[3.3867089748,50.9161224365],"type":"Point"}
}