{
  "type": "Feature",
  "properties": {
    "addr:full":"Sint-jansbergsteenweg 38ba Huldenberg Vlaams-Brabant 3040",
    "addr:housenumber":"38ba",
    "addr:postcode":"3040",
    "addr:street":"Sint-Jansbergsteenweg",
    "iso:country":"BE",
    "sg:address":"Sint-jansbergsteenweg 38ba",
    "sg:city":"Huldenberg",
    "sg:orig_category":"Banques and organismes de cr\u00e9dit. Assurances",
    "sg:phone":"+32 16 47 26 74",
    "sg:postcode":"3040",
    "sg:province":"Vlaams-Brabant",
    "wof:name":"Centea",
    "wof:placetype":"venue"
},
  "geometry": {"coordinates":[4.5990819931,50.7986869812],"type":"Point"}
}