{
  "type": "Feature",
  "properties": {
    "addr:full":"Rue Adolphe-sax 38 Dinant Namur 5500",
    "addr:housenumber":"38",
    "addr:postcode":"5500",
    "addr:street":"Rue Adolphe-Sax",
    "iso:country":"BE",
    "sg:address":"Rue Adolphe-sax 38",
    "sg:city":"Dinant",
    "sg:orig_category":"Schoonheidssalons",
    "sg:phone":"+32 82 22 36 61",
    "sg:postcode":"5500",
    "sg:province":"Namur",
    "wof:name":"P\u00c9dicure Lottin J.",
    "wof:placetype":"venue"
},
  "geometry": {"coordinates":[4.9109401703,50.2616004944],"type":"Point"}
}