{
  "type": "Feature",
  "properties": {
    "addr:full":"Grote Markt 27 Diest Vlaams-Brabant 3290",
    "addr:housenumber":"27",
    "addr:postcode":"3290",
    "addr:street":"Grote Markt",
    "iso:country":"BE",
    "sg:address":"Grote Markt 27",
    "sg:city":"Diest",
    "sg:orig_category":"Ruimtes voor conferenties, recepties and feesten",
    "sg:phone":"+32 13 32 25 10",
    "sg:postcode":"3290",
    "sg:province":"Vlaams-Brabant",
    "wof:name":"Casino",
    "wof:placetype":"venue"
},
  "geometry": {"coordinates":[5.0505099297,50.9844055176],"type":"Point"}
}