{
  "type": "Feature",
  "properties": {
    "iso:country":"BE",
    "sg:address":"Steenweg Op Vilvoorde 338",
    "sg:city":"Opwijk",
    "sg:orig_category":"Herstellingen and onderhoud van auto's",
    "sg:phone":"+32 52 35 54 72",
    "sg:postcode":"1745",
    "sg:province":"Vlaams-Brabant",
    "wof:name":"De Ghendt",
    "wof:placetype":"venue"
},
  "geometry": {"coordinates":[4.1859798431,50.9557113647],"type":"Point"}
}