{
  "type": "Feature",
  "properties": {
    "addr:full":"Rue Fourneau 2a Marchin Li\u00e8ge 4570",
    "addr:housenumber":"2a",
    "addr:postcode":"4570",
    "addr:street":"Rue Fourneau",
    "iso:country":"BE",
    "sg:address":"Rue Fourneau 2a",
    "sg:city":"Marchin",
    "sg:orig_category":"Installation \u00e9lectrique r\u00e9sidentielle",
    "sg:phone":"+32 85 25 13 68",
    "sg:postcode":"4570",
    "sg:province":"Li\u00e8ge",
    "wof:name":"Michel Lamproye",
    "wof:placetype":"venue"
},
  "geometry": {"coordinates":[5.2445001602,50.4803466797],"type":"Point"}
}