{
  "type": "Feature",
  "properties": {
    "iso:country":"BE",
    "sg:address":"Rue Jean Vercheval 37",
    "sg:city":"Herstal",
    "sg:classifiers":[
        {
            "category":"Wholesale",
            "subcategory":"Construction Materials",
            "type":"Manufacturing & Wholesale Goods"
        }
    ],
    "sg:phone":"+32 4 264 76 06",
    "sg:postcode":"4040",
    "sg:province":"Li\u00e8ge",
    "sg:tags":[
        "tubing",
        "industrial"
    ],
    "wof:name":"E.r.i.c. Sprl",
    "wof:placetype":"venue"
},
  "geometry": {"coordinates":[5.6386218071,50.6686134338],"type":"Point"}
}