{
  "type": "Feature",
  "properties": {
    "addr:full":"Diepenbeek 4 Zomergem Oost-Vlaanderen 9931",
    "addr:housenumber":"4",
    "addr:postcode":"9931",
    "addr:street":"Diepenbeek",
    "iso:country":"BE",
    "sg:address":"Diepenbeek 4",
    "sg:city":"Zomergem",
    "sg:orig_category":"Eleveurs de bovins",
    "sg:phone":"+32 9 372 84 68",
    "sg:postcode":"9931",
    "sg:province":"Oost-Vlaanderen",
    "wof:name":"Antoon Blomme",
    "wof:placetype":"venue"
},
  "geometry": {"coordinates":[3.5290091038,51.1375236511],"type":"Point"}
}