{
  "type": "Feature",
  "properties": {
    "addr:full":"Gurincksstraat 40 Machelen (groot) Vlaams-Brabant 1831",
    "addr:housenumber":"40",
    "addr:postcode":"1831",
    "addr:street":"Gurincksstraat;Groot Vlaams-Brabant",
    "iso:country":"BE",
    "sg:address":"Gurincksstraat 40",
    "sg:city":"Machelen (groot)",
    "sg:orig_category":"Beautyfarms, relaxatie and lichamelijk welzijn",
    "sg:phone":"+32 486 45 24 75",
    "sg:postcode":"1831",
    "sg:province":"Vlaams-Brabant",
    "wof:name":"Zonnecenter Corner Inn",
    "wof:placetype":"venue"
},
  "geometry": {"coordinates":[4.4359431267,50.8944854736],"type":"Point"}
}