{
  "type": "Feature",
  "properties": {
    "addr:full":"Rue Reine Astrid 113 Saint-georges-sur-meuse Li\u00e8ge 4470",
    "addr:housenumber":"113",
    "addr:postcode":"4470",
    "addr:street":"Rue Reine Astrid",
    "iso:country":"BE",
    "sg:address":"Rue Reine Astrid 113",
    "sg:city":"Saint-georges-sur-meuse",
    "sg:orig_category":"Jeux de hasard",
    "sg:phone":"+32 4 275 33 48",
    "sg:postcode":"4470",
    "sg:province":"Li\u00e8ge",
    "wof:name":"Tierc\u00c9 Franco Belge",
    "wof:placetype":"venue"
},
  "geometry": {"coordinates":[5.3590202332,50.5849304199],"type":"Point"}
}