{
  "type": "Feature",
  "properties": {
    "addr:full":"Rue Des Remparts 52a Bastogne Luxembourg 6600",
    "addr:housenumber":"52a",
    "addr:postcode":"6600",
    "addr:street":"Rue Des Remparts",
    "iso:country":"BE",
    "sg:address":"Rue Des Remparts 52a",
    "sg:city":"Bastogne",
    "sg:classifiers":[
        {
            "category":"Retail",
            "subcategory":"Repair Shop",
            "type":"Services"
        }
    ],
    "sg:phone":"+32 61 21 31 73",
    "sg:postcode":"6600",
    "sg:province":"Luxembourg",
    "sg:tags":[
        "denture"
    ],
    "wof:name":"Grandjenette F",
    "wof:placetype":"venue"
},
  "geometry": {"coordinates":[5.7177901268,50.0041694641],"type":"Point"}
}