{
  "type": "Feature",
  "properties": {
    "addr:full":"Rue Britannique 17 Braine-le-comte Hainaut 7090",
    "addr:housenumber":"17",
    "addr:postcode":"7090",
    "addr:street":"Rue Britannique",
    "iso:country":"BE",
    "sg:address":"Rue Britannique 17",
    "sg:city":"Braine-le-comte",
    "sg:classifiers":[
        {
            "category":"Education",
            "subcategory":"School",
            "type":"Public Place"
        }
    ],
    "sg:phone":"+32 67 55 22 87",
    "sg:postcode":"7090",
    "sg:province":"Hainaut",
    "sg:tags":[
        "secondary"
    ],
    "wof:name":"Acad\u00e9mie De Musique",
    "wof:placetype":"venue"
},
  "geometry": {"coordinates":[4.1338448524,50.6067199707],"type":"Point"}
}