{
  "type": "Feature",
  "properties": {
    "iso:country":"BE",
    "sg:address":"Rue De La Banque 12",
    "sg:city":"Seraing",
    "sg:orig_category":"Cr\u00e9dits divers",
    "sg:postcode":"4100",
    "sg:province":"Li\u00e8ge",
    "wof:name":"Bancontact-mister Cash",
    "wof:placetype":"venue"
},
  "geometry": {"coordinates":[5.5128569603,50.6093330383],"type":"Point"}
}