{
  "type": "Feature",
  "properties": {
    "iso:country":"BE",
    "sg:address":"Brugstraat 8",
    "sg:city":"Boutersem",
    "sg:classifiers":[
        {
            "category":"Professional",
            "subcategory":"Business Services",
            "type":"Services"
        }
    ],
    "sg:phone":"+32 16 72 10 05",
    "sg:postcode":"3370",
    "sg:province":"Vlaams-Brabant",
    "sg:tags":[
        "bookkeeping"
    ],
    "wof:name":"Bollion Finance",
    "wof:placetype":"venue"
},
  "geometry": {"coordinates":[4.8316512108,50.8391952515],"type":"Point"}
}