{
  "type": "Feature",
  "properties": {
    "addr:full":"Hovenierstraat 95 Lokeren Oost-Vlaanderen 9160",
    "addr:housenumber":"95",
    "addr:postcode":"9160",
    "addr:street":"Hovenierstraat",
    "iso:country":"BE",
    "sg:address":"Hovenierstraat 95",
    "sg:city":"Lokeren",
    "sg:orig_category":"Pleisterwerk",
    "sg:phone":"+32 9 348 02 90",
    "sg:postcode":"9160",
    "sg:province":"Oost-Vlaanderen",
    "wof:name":"Omer Haeck",
    "wof:placetype":"venue"
},
  "geometry": {"coordinates":[3.9909310341,51.0964012146],"type":"Point"}
}