{
  "type": "Feature",
  "properties": {
    "addr:full":"Bergen 36 Herenthout Antwerpen 2270",
    "addr:housenumber":"36",
    "addr:postcode":"2270",
    "addr:street":"Bergen",
    "iso:country":"BE",
    "sg:address":"Bergen 36",
    "sg:city":"Herenthout",
    "sg:classifiers":[
        {
            "category":"Building & Trades",
            "subcategory":"Landscaping Services",
            "type":"Services"
        }
    ],
    "sg:phone":"+32 14 50 29 58",
    "sg:postcode":"2270",
    "sg:province":"Antwerpen",
    "sg:tags":[
        "architect",
        "landscape"
    ],
    "wof:name":"Marien E",
    "wof:placetype":"venue"
},
  "geometry": {"coordinates":[4.7824702263,51.1542282104],"type":"Point"}
}