{
  "type": "Feature",
  "properties": {
    "iso:country":"BE",
    "sg:address":"Bergendriesstraat 116",
    "sg:city":"Lokeren",
    "sg:classifiers":[
        {
            "category":"Autos & Motor Vehicles",
            "subcategory":"Fuel & Gas Station",
            "type":"Retail Goods"
        }
    ],
    "sg:phone":"+32 9 349 31 28",
    "sg:postcode":"9160",
    "sg:province":"Oost-Vlaanderen",
    "sg:tags":[
        "stations-service",
        "carburants"
    ],
    "wof:name":"De Fre",
    "wof:placetype":"venue"
},
  "geometry": {"coordinates":[3.987719059,51.1127929688],"type":"Point"}
}