{
  "type": "Feature",
  "properties": {
    "iso:country":"BE",
    "sg:address":"Clos Du Li\u00c8vre 5",
    "sg:city":"Court-saint-etienne",
    "sg:orig_category":"M\u00e9decins and sp\u00e9cialistes",
    "sg:phone":"+32 10 61 17 43",
    "sg:postcode":"1490",
    "sg:province":"Brabant Wallon",
    "wof:name":"L\u00c9on Fiasse",
    "wof:placetype":"venue"
},
  "geometry": {"coordinates":[4.5374269485,50.6214447021],"type":"Point"}
}