{
  "type": "Feature",
  "properties": {
    "iso:country":"BE",
    "sg:address":"Moorsledestraat 4",
    "sg:city":"Staden",
    "sg:orig_category":"Varkenskwekers",
    "sg:phone":"+32 51 77 23 43",
    "sg:postcode":"8840",
    "sg:province":"West-Vlaanderen",
    "wof:name":"Frans Vandewiele",
    "wof:placetype":"venue"
},
  "geometry": {"coordinates":[3.0537829399,50.9249000549],"type":"Point"}
}