{
  "type": "Feature",
  "properties": {
    "addr:full":"Avenue Adolphe Lacombl\u00c9 52 Brussel/bruxelles Bruxelles-Capitale 1030",
    "addr:housenumber":"52",
    "addr:postcode":"1030",
    "addr:street":"Avenue Adolphe Lacomble\u0301;/",
    "iso:country":"BE",
    "sg:address":"Avenue Adolphe Lacombl\u00c9 52",
    "sg:city":"Brussel/bruxelles",
    "sg:orig_category":"Grossistes divers",
    "sg:phone":"+32 2 736 76 01",
    "sg:postcode":"1030",
    "sg:province":"Bruxelles-Capitale",
    "wof:name":"Quo Vadis Benelux",
    "wof:placetype":"venue"
},
  "geometry": {"coordinates":[4.399160862,50.8490905762],"type":"Point"}
}