{
  "type": "Feature",
  "properties": {
    "addr:full":"Chauss\u00c9e De Haecht 1255 Brussel/bruxelles Bruxelles-Capitale 1130",
    "addr:postcode":"1255;/ bruxelles;1130",
    "addr:street":"Chausse\u0301E De Haecht",
    "iso:country":"BE",
    "sg:address":"Chauss\u00c9e De Haecht 1255",
    "sg:city":"Brussel/bruxelles",
    "sg:orig_category":"Herstellingen and onderhoud van auto's",
    "sg:phone":"+32 2 216 96 35",
    "sg:postcode":"1130",
    "sg:province":"Bruxelles-Capitale",
    "wof:name":"Car Wash Kennedy Ii",
    "wof:placetype":"venue"
},
  "geometry": {"coordinates":[4.4142651558,50.8804473877],"type":"Point"}
}