{
  "type": "Feature",
  "properties": {
    "iso:country":"BE",
    "sg:address":"Baaigemstraat 383",
    "sg:city":"Gavere",
    "sg:classifiers":[
        {
            "category":"Professional",
            "subcategory":"Lawyer & Legal Services",
            "type":"Services"
        }
    ],
    "sg:phone":"+32 9 362 86 56",
    "sg:postcode":"9890",
    "sg:province":"Oost-Vlaanderen",
    "wof:name":"De Brabandere Andr\u00e9",
    "wof:placetype":"venue"
},
  "geometry": {"coordinates":[3.7020909786,50.932723999],"type":"Point"}
}