{
  "type": "Feature",
  "properties": {
    "iso:country":"BE",
    "sg:address":"Lange Munteplein 2",
    "sg:city":"Kortrijk",
    "sg:classifiers":[
        {
            "category":"Bakery",
            "type":"Food & Drink"
        }
    ],
    "sg:postcode":"8500",
    "sg:province":"West-Vlaanderen",
    "sg:tags":[
        "confectioner",
        "baker"
    ],
    "wof:name":"Deltour Vincent",
    "wof:placetype":"venue"
},
  "geometry": {"coordinates":[3.2672870159,50.8260421753],"type":"Point"}
}