{
  "type": "Feature",
  "properties": {
    "iso:country":"BE",
    "sg:address":"Place Reine Astrid 2",
    "sg:city":"Jette",
    "sg:orig_category":"Agences de voyages",
    "sg:phone":"+32 2 424 25 50",
    "sg:postcode":"1090",
    "sg:province":"Bruxelles-Capitale",
    "wof:name":"Jetexpress",
    "wof:placetype":"venue"
},
  "geometry": {"coordinates":[4.3255558014,50.8727645874],"type":"Point"}
}