{
  "type": "Feature",
  "properties": {
    "addr:full":"Rijselstr 60 Heuvelland West-Vlaanderen 8953",
    "addr:housenumber":"60",
    "addr:postcode":"8953",
    "addr:street":"Rijselstr",
    "iso:country":"BE",
    "sg:address":"Rijselstr 60",
    "sg:city":"Heuvelland",
    "sg:classifiers":[
        {
            "category":"Professional",
            "type":"Services"
        }
    ],
    "sg:phone":"+32 57 44 50 01",
    "sg:postcode":"8953",
    "sg:province":"West-Vlaanderen",
    "sg:tags":[
        "transport",
        "road"
    ],
    "wof:name":"Plantefeve Bvba",
    "wof:placetype":"venue"
},
  "geometry": {"coordinates":[2.9231569767,50.7779045105],"type":"Point"}
}