{
  "type": "Feature",
  "properties": {
    "iso:country":"BE",
    "sg:address":"Rue Du Chant Des Oiseaux 7",
    "sg:city":"Mettet (furnaux)",
    "sg:classifiers":[
        {
            "category":"Real Estate",
            "subcategory":"Architect",
            "type":"Services"
        }
    ],
    "sg:phone":"+32 71 72 86 69",
    "sg:postcode":"5641",
    "sg:province":"Namur",
    "wof:name":"Denis A-s",
    "wof:placetype":"venue"
},
  "geometry": {"coordinates":[4.7102999687,50.3089103699],"type":"Point"}
}