{
  "type": "Feature",
  "properties": {
    "iso:country":"BE",
    "sg:address":"Rue Du Ch\u00c2teau 176",
    "sg:city":"Ohey",
    "sg:orig_category":"Rundveehouders",
    "sg:phone":"+32 85 61 11 21",
    "sg:postcode":"5350",
    "sg:province":"Namur",
    "wof:name":"Beguin Etienne & Pierre",
    "wof:placetype":"venue"
},
  "geometry": {"coordinates":[5.1270170212,50.429473877],"type":"Point"}
}