{
  "type": "Feature",
  "properties": {
    "addr:full":"Rue De La Concorde 5 Verviers Li\u00e8ge 4800",
    "addr:housenumber":"5",
    "addr:postcode":"4800",
    "addr:street":"Rue De La Concorde",
    "iso:country":"BE",
    "sg:address":"Rue De La Concorde 5",
    "sg:city":"Verviers",
    "sg:classifiers":[
        {
            "category":"Personal",
            "subcategory":"Beauty Salon",
            "type":"Services"
        }
    ],
    "sg:phone":"+32 87 31 58 38",
    "sg:postcode":"4800",
    "sg:province":"Li\u00e8ge",
    "sg:tags":[
        "lady",
        "-",
        "hairdressing"
    ],
    "wof:name":"Danson's Style",
    "wof:placetype":"venue"
},
  "geometry": {"coordinates":[5.8560681343,50.591545105],"type":"Point"}
}