{
  "type": "Feature",
  "properties": {
    "iso:country":"BE",
    "sg:address":"Visserijstraat 96",
    "sg:city":"Ukkel/uccle",
    "sg:orig_category":"Etalage- and showroomontwerpers",
    "sg:phone":"+32 2 375 71 65",
    "sg:postcode":"1180",
    "sg:province":"Bruxelles-Capitale",
    "wof:name":"Sophie De Ridder",
    "wof:placetype":"venue"
},
  "geometry": {"coordinates":[4.3583979607,50.7933158875],"type":"Point"}
}