{
  "type": "Feature",
  "properties": {
    "addr:full":"Rue Saxe-cobourg 4a Bruxelles (saint-josse-ten-noode) Bruxelles-Capitale 1210",
    "addr:housenumber":"4a",
    "addr:postcode":"1210",
    "addr:street":"Rue Saxe-Cobourg",
    "iso:country":"BE",
    "sg:address":"Rue Saxe-cobourg 4a",
    "sg:city":"Bruxelles (saint-josse-ten-noode)",
    "sg:classifiers":[
        {
            "category":"Personal",
            "subcategory":"Psychics & Astrologers",
            "type":"Services"
        }
    ],
    "sg:phone":"+32 2 223 06 03",
    "sg:postcode":"1210",
    "sg:province":"Bruxelles-Capitale",
    "sg:tags":[
        "astrology"
    ],
    "wof:name":"Lina Asbl",
    "wof:placetype":"venue"
},
  "geometry": {"coordinates":[4.3726911545,50.8501968384],"type":"Point"}
}