{
  "type": "Feature",
  "properties": {
    "addr:full":"Rue De Dison 134 Verviers Li\u00e8ge 4800",
    "addr:housenumber":"134",
    "addr:postcode":"4800",
    "addr:street":"Rue De Dison",
    "iso:country":"BE",
    "sg:address":"Rue De Dison 134",
    "sg:city":"Verviers",
    "sg:orig_category":"Overheidsdiensten",
    "sg:phone":"+32 87 39 35 96",
    "sg:postcode":"4800",
    "sg:province":"Li\u00e8ge",
    "wof:name":"Admin. Contrib. Directes",
    "wof:placetype":"venue"
},
  "geometry": {"coordinates":[5.8594508171,50.5917663574],"type":"Point"}
}