{
  "type": "Feature",
  "properties": {
    "iso:country":"BE",
    "sg:address":"Rue Neuve 7",
    "sg:city":"Stavelot",
    "sg:orig_category":"Fleurs and plantes",
    "sg:phone":"+32 80 86 33 62",
    "sg:postcode":"4970",
    "sg:province":"Li\u00e8ge",
    "wof:name":"Maison Fleur\u00c9al",
    "wof:placetype":"venue"
},
  "geometry": {"coordinates":[5.9255290031,50.3918228149],"type":"Point"}
}