{
  "type": "Feature",
  "properties": {
    "addr:full":"Rue Des Rabots 30 Fleurus Hainaut 6220",
    "addr:housenumber":"30",
    "addr:postcode":"6220",
    "addr:street":"Rue Des Rabots",
    "iso:country":"BE",
    "sg:address":"Rue Des Rabots 30",
    "sg:city":"Fleurus",
    "sg:orig_category":"R\u00e9parations de chaussures and articles en cuir",
    "sg:phone":"+32 71 81 53 52",
    "sg:postcode":"6220",
    "sg:province":"Hainaut",
    "wof:name":"Raffa\u00cble Gigliotti",
    "wof:placetype":"venue"
},
  "geometry": {"coordinates":[4.5466589928,50.4823532104],"type":"Point"}
}