{
  "type": "Feature",
  "properties": {
    "addr:full":"Bavikhoofsestraat 71 Harelbeke West-Vlaanderen 8531",
    "addr:housenumber":"71",
    "addr:postcode":"8531",
    "addr:street":"Bavikhoofsestraat",
    "iso:country":"BE",
    "sg:address":"Bavikhoofsestraat 71",
    "sg:city":"Harelbeke",
    "sg:orig_category":"Kapsalons",
    "sg:phone":"+32 56 71 72 64",
    "sg:postcode":"8531",
    "sg:province":"West-Vlaanderen",
    "wof:name":"Coiffure Martine",
    "wof:placetype":"venue"
},
  "geometry": {"coordinates":[3.3094480038,50.8736991882],"type":"Point"}
}