{
  "type": "Feature",
  "properties": {
    "iso:country":"BE",
    "sg:address":"Hoekheide 32",
    "sg:city":"Herselt",
    "sg:orig_category":"Tuinen",
    "sg:phone":"+32 16 69 70 81",
    "sg:postcode":"2230",
    "sg:province":"Antwerpen",
    "wof:name":"Jozef Eulaerts",
    "wof:placetype":"venue"
},
  "geometry": {"coordinates":[4.8070931435,51.0288887024],"type":"Point"}
}