{
  "type": "Feature",
  "properties": {
    "iso:country":"BE",
    "sg:address":"Les Pindants 20",
    "sg:city":"Sambreville",
    "sg:orig_category":"Elektrische installaties voor woningen",
    "sg:phone":"+32 71 77 16 74",
    "sg:postcode":"5060",
    "sg:province":"Namur",
    "wof:name":"Philippe Pietequin",
    "wof:placetype":"venue"
},
  "geometry": {"coordinates":[4.6285200119,50.4448738098],"type":"Point"}
}