{
  "type": "Feature",
  "properties": {
    "iso:country":"BE",
    "sg:address":"Drie Sleutelstraat 74",
    "sg:city":"Aalst",
    "sg:classifiers":[
        {
            "category":"Building & Trades",
            "subcategory":"Construction",
            "type":"Services"
        }
    ],
    "sg:phone":"+32 53 41 70 13",
    "sg:postcode":"9300",
    "sg:province":"Oost-Vlaanderen",
    "sg:tags":[
        "work",
        "waterproofing"
    ],
    "wof:name":"Osmotec Bvba",
    "wof:placetype":"venue"
},
  "geometry": {"coordinates":[4.0418729782,50.9469261169],"type":"Point"}
}