{
  "type": "Feature",
  "properties": {
    "iso:country":"BE",
    "sg:address":"Rue De Pervyse 38",
    "sg:city":"Bruxelles (etterbeek)",
    "sg:classifiers":[
        {
            "category":"Professional",
            "subcategory":"Art Services",
            "type":"Services"
        }
    ],
    "sg:phone":"+32 2 502 35 98",
    "sg:postcode":"1040",
    "sg:province":"Bruxelles-Capitale",
    "sg:tags":[
        "photographer",
        "-",
        "portrait"
    ],
    "wof:name":"Van Der Straten S",
    "wof:placetype":"venue"
},
  "geometry": {"coordinates":[4.4007258415,50.8313751221],"type":"Point"}
}