{
  "type": "Feature",
  "properties": {
    "addr:full":"Kasteelstraat 19 Hoeselt Limburg 3730",
    "addr:housenumber":"19",
    "addr:postcode":"3730",
    "addr:street":"Kasteelstraat",
    "iso:country":"BE",
    "sg:address":"Kasteelstraat 19",
    "sg:city":"Hoeselt",
    "sg:classifiers":[
        {
            "category":"Social Services",
            "subcategory":"Job Training",
            "type":"Services"
        }
    ],
    "sg:phone":"+32 89 51 11 84",
    "sg:postcode":"3730",
    "sg:province":"Limburg",
    "sg:tags":[
        "personnel"
    ],
    "wof:name":"Adoma Cv",
    "wof:placetype":"venue"
},
  "geometry": {"coordinates":[5.4760689735,50.8513870239],"type":"Point"}
}