{
  "type": "Feature",
  "properties": {
    "addr:full":"Avenue De Vis\u00e9 11 Bruxelles (watermael-boitsfort) Bruxelles-Capitale 1170",
    "addr:housenumber":"11",
    "addr:postcode":"1170",
    "addr:street":"Avenue De Vise\u0301",
    "iso:country":"BE",
    "sg:address":"Avenue De Vis\u00e9 11",
    "sg:city":"Bruxelles (watermael-boitsfort)",
    "sg:classifiers":[
        {
            "category":"Wholesale",
            "subcategory":"Books, Periodicals, & Newspapers",
            "type":"Manufacturing & Wholesale Goods"
        }
    ],
    "sg:phone":"+32 2 672 23 18",
    "sg:postcode":"1170",
    "sg:province":"Bruxelles-Capitale",
    "sg:tags":[
        "publisher"
    ],
    "wof:name":"Joker Editions",
    "wof:placetype":"venue"
},
  "geometry": {"coordinates":[4.3976950645,50.8101425171],"type":"Point"}
}