{
  "type": "Feature",
  "properties": {
    "iso:country":"BE",
    "sg:address":"Miksebaan 346",
    "sg:city":"Brasschaat",
    "sg:classifiers":[
        {
            "category":"Health Services",
            "subcategory":"Doctor",
            "type":"Services"
        }
    ],
    "sg:phone":"+32 3 663 27 72",
    "sg:postcode":"2930",
    "sg:province":"Antwerpen",
    "sg:tags":[
        "medicinephysicians",
        "surgeon"
    ],
    "wof:name":"Dierckxsens J",
    "wof:placetype":"venue"
},
  "geometry": {"coordinates":[4.5472898483,51.3149986267],"type":"Point"}
}