{
  "type": "Feature",
  "properties": {
    "iso:country":"BE",
    "sg:address":"Elverdingseweg 23",
    "sg:city":"Poperinge",
    "sg:orig_category":"Rundveehouders Varkenskwekers",
    "sg:phone":"+32 57 42 23 56",
    "sg:postcode":"8970",
    "sg:province":"West-Vlaanderen",
    "wof:name":"Gilbert Sticker",
    "wof:placetype":"venue"
},
  "geometry": {"coordinates":[2.7678859234,50.8745651245],"type":"Point"}
}