{
  "type": "Feature",
  "properties": {
    "addr:full":"Nieuwpoortsesteenweg 495 Oostende West-Vlaanderen 8400",
    "addr:housenumber":"495",
    "addr:postcode":"8400",
    "addr:street":"Nieuwpoortsesteenweg",
    "iso:country":"BE",
    "sg:address":"Nieuwpoortsesteenweg 495",
    "sg:city":"Oostende",
    "sg:classifiers":[
        {
            "category":"Fast Food",
            "type":"Food & Drink"
        }
    ],
    "sg:phone":"+32 59 50 95 14",
    "sg:postcode":"8400",
    "sg:province":"West-Vlaanderen",
    "sg:tags":[
        "\u00c0",
        "restaurants",
        "emporter",
        "restaurant"
    ],
    "wof:name":"Restaurant Ocean City",
    "wof:placetype":"venue"
},
  "geometry": {"coordinates":[2.8889119625,51.215423584],"type":"Point"}
}