{
  "type": "Feature",
  "properties": {
    "iso:country":"BE",
    "sg:address":"Chauss\u00e9e De Waterloo 1338",
    "sg:city":"Bruxelles (uccle)",
    "sg:classifiers":[
        {
            "category":"Personal",
            "subcategory":"Beauty Salon",
            "type":"Services"
        }
    ],
    "sg:phone":"+32 2 262 27 25",
    "sg:postcode":"1180",
    "sg:province":"Bruxelles-Capitale",
    "sg:tags":[
        "lady",
        "-",
        "hairdressing"
    ],
    "wof:name":"Coiffure R\u00e9cr\u00e9 (la)",
    "wof:placetype":"venue"
},
  "geometry": {"coordinates":[4.3749480247,50.7899093628],"type":"Point"}
}