{
  "type": "Feature",
  "properties": {
    "addr:full":"Chauss\u00c9e De Tongres 269 Li\u00c8ge Li\u00e8ge 4000",
    "addr:housenumber":"269",
    "addr:postcode":"4000",
    "addr:street":"Chausse\u0301E De Tongres",
    "iso:country":"BE",
    "sg:address":"Chauss\u00c9e De Tongres 269",
    "sg:city":"Li\u00c8ge",
    "sg:orig_category":"Diverse kredietdiensten",
    "sg:postcode":"4000",
    "sg:province":"Li\u00e8ge",
    "wof:name":"Bancontact-mister Cash",
    "wof:placetype":"venue"
},
  "geometry": {"coordinates":[5.5499567986,50.6700172424],"type":"Point"}
}