{
  "type": "Feature",
  "properties": {
    "addr:full":"Rue De La Station 48 Havelange Namur 5370",
    "addr:housenumber":"48",
    "addr:postcode":"5370",
    "addr:street":"Rue De La Station",
    "iso:country":"BE",
    "sg:address":"Rue De La Station 48",
    "sg:city":"Havelange",
    "sg:classifiers":[
        {
            "category":"Retail",
            "subcategory":"Repair Shop",
            "type":"Services"
        }
    ],
    "sg:phone":"+32 83 63 38 32",
    "sg:postcode":"5370",
    "sg:province":"Namur",
    "sg:tags":[
        "-",
        "mainten",
        "watch",
        "clock"
    ],
    "wof:name":"Degreve B",
    "wof:placetype":"venue"
},
  "geometry": {"coordinates":[5.2427568436,50.3876075745],"type":"Point"}
}