{
  "type": "Feature",
  "properties": {
    "iso:country":"BE",
    "sg:address":"Achtelsestraat 72",
    "sg:city":"Hoogstraten",
    "sg:orig_category":"Sportcentra Sportclubs Sportterreinen and installaties behalve sportcentra",
    "sg:phone":"+32 3 314 37 76",
    "sg:postcode":"2320",
    "sg:province":"Antwerpen",
    "wof:name":"De Vrijheid",
    "wof:placetype":"venue"
},
  "geometry": {"coordinates":[4.7631268501,51.3938179016],"type":"Point"}
}