{
  "type": "Feature",
  "properties": {
    "iso:country":"BE",
    "sg:address":"Chauss\u00c9e De Mons 155",
    "sg:city":"La Louviere",
    "sg:orig_category":"Assurances. Pr\u00eats hypoth\u00e9caires and cr\u00e9dits immobiliers",
    "sg:phone":"+32 64 22 27 66",
    "sg:postcode":"7100",
    "sg:province":"Hainaut",
    "wof:name":"Assurances Services & Cr\u00c9dits",
    "wof:placetype":"venue"
},
  "geometry": {"coordinates":[4.1995410919,50.4645805359],"type":"Point"}
}