{
  "type": "Feature",
  "properties": {
    "iso:country":"BE",
    "sg:address":"Catstraat 66",
    "sg:city":"Koekelare",
    "sg:orig_category":"Boekhouders",
    "sg:phone":"+32 51 58 81 36",
    "sg:postcode":"8680",
    "sg:province":"West-Vlaanderen",
    "wof:name":"Godelieve Beuselinck",
    "wof:placetype":"venue"
},
  "geometry": {"coordinates":[2.9495379925,51.0883293152],"type":"Point"}
}