{
  "type": "Feature",
  "properties": {
    "iso:country":"BE",
    "sg:address":"Rue Paul Pastur 42",
    "sg:city":"Quaregnon",
    "sg:classifiers":[
        {
            "category":"Real Estate",
            "subcategory":"Architect",
            "type":"Services"
        }
    ],
    "sg:phone":"+32 65 78 22 90",
    "sg:postcode":"7390",
    "sg:province":"Hainaut",
    "wof:name":"Duez Th",
    "wof:placetype":"venue"
},
  "geometry": {"coordinates":[3.8635499477,50.4452438354],"type":"Point"}
}