{
  "type": "Feature",
  "properties": {
    "iso:country":"BE",
    "sg:address":"Noordervaart 28",
    "sg:city":"Herentals",
    "sg:orig_category":"Mat\u00e9riaux de construction Gr",
    "sg:phone":"+32 14 21 30 74",
    "sg:postcode":"2200",
    "sg:province":"Antwerpen",
    "wof:name":"Bouwmaterialen J.van Peer",
    "wof:placetype":"venue"
},
  "geometry": {"coordinates":[4.8523640633,51.1745948792],"type":"Point"}
}