{
  "type": "Feature",
  "properties": {
    "addr:full":"Chauss\u00e9e Romaine 39 Oreye Li\u00e8ge 4360",
    "addr:housenumber":"39",
    "addr:postcode":"4360",
    "addr:street":"Chausse\u0301E Romaine",
    "iso:country":"BE",
    "sg:address":"Chauss\u00e9e Romaine 39",
    "sg:city":"Oreye",
    "sg:classifiers":[
        {
            "category":"Building & Trades",
            "subcategory":"Construction",
            "type":"Services"
        }
    ],
    "sg:phone":"+32 19 67 82 70",
    "sg:postcode":"4360",
    "sg:province":"Li\u00e8ge",
    "sg:tags":[
        "installation",
        "-",
        "central",
        "heating"
    ],
    "wof:name":"Remy G",
    "wof:placetype":"venue"
},
  "geometry": {"coordinates":[5.3494801521,50.733581543],"type":"Point"}
}