{
  "type": "Feature",
  "properties": {
    "iso:country":"BE",
    "sg:address":"Square Des Nations-unies 2",
    "sg:city":"Nivelles",
    "sg:orig_category":"Diverse kredietdiensten",
    "sg:postcode":"1400",
    "sg:province":"Brabant Wallon",
    "wof:name":"Bancontact-mister Cash",
    "wof:placetype":"venue"
},
  "geometry": {"coordinates":[4.344771862,50.6015281677],"type":"Point"}
}