{
  "type": "Feature",
  "properties": {
    "iso:country":"BE",
    "sg:address":"Urselseweg 154",
    "sg:city":"Knesselare",
    "sg:classifiers":[
        {
            "category":"Communications",
            "subcategory":"News Services",
            "type":"Services"
        }
    ],
    "sg:phone":"+32 9 374 57 61",
    "sg:postcode":"9910",
    "sg:province":"Oost-Vlaanderen",
    "sg:tags":[
        "illustrator"
    ],
    "wof:name":"Leo Cartoons",
    "wof:placetype":"venue"
},
  "geometry": {"coordinates":[3.4643468857,51.1306686401],"type":"Point"}
}