{
  "type": "Feature",
  "properties": {
    "addr:full":"Zoning Industrielle Aubange Luxembourg 6790",
    "addr:postcode":"6790",
    "addr:street":"Zoning Industrielle",
    "iso:country":"BE",
    "sg:address":"Zoning Industrielle",
    "sg:city":"Aubange",
    "sg:classifiers":[
        {
            "category":"Organizations",
            "subcategory":"Community Association",
            "type":"Services"
        }
    ],
    "sg:phone":"+32 63 38 18 00",
    "sg:postcode":"6790",
    "sg:province":"Luxembourg",
    "sg:tags":[
        "box",
        "cardboard"
    ],
    "wof:name":"Michelman Int And Co",
    "wof:placetype":"venue"
},
  "geometry": {"coordinates":[5.8051338196,49.5689849854],"type":"Point"}
}