{
  "type": "Feature",
  "properties": {
    "iso:country":"BE",
    "sg:address":"Grijspeerdstraat 103",
    "sg:city":"Gits",
    "sg:classifiers":[
        {
            "category":"Professional",
            "type":"Services"
        }
    ],
    "sg:phone":"+32 51 72 39 02",
    "sg:postcode":"8830",
    "sg:province":"West-Vlaanderen",
    "sg:tags":[
        "transport"
    ],
    "wof:name":"Maes Vervoer Nv",
    "wof:placetype":"venue"
},
  "geometry": {"coordinates":[3.0801548958,51.011505127],"type":"Point"}
}