{
  "type": "Feature",
  "properties": {
    "addr:full":"Hoge Weg 129 Stabroek Antwerpen 2940",
    "addr:housenumber":"129",
    "addr:postcode":"2940",
    "addr:street":"Hoge Weg",
    "iso:country":"BE",
    "sg:address":"Hoge Weg 129",
    "sg:city":"Stabroek",
    "sg:orig_category":"Mat\u00e9riel scientifique and technique Fab",
    "sg:phone":"+32 3 660 13 45",
    "sg:postcode":"2940",
    "sg:province":"Antwerpen",
    "wof:name":"Miravox",
    "wof:placetype":"venue"
},
  "geometry": {"coordinates":[4.395720005,51.314201355],"type":"Point"}
}