{
  "type": "Feature",
  "properties": {
    "addr:full":"Grand-route 105 Mons Hainaut 7000",
    "addr:housenumber":"105",
    "addr:postcode":"7000",
    "addr:street":"Grand-Route;Hainaut",
    "iso:country":"BE",
    "sg:address":"Grand-route 105",
    "sg:city":"Mons",
    "sg:orig_category":"Formation permanente",
    "sg:phone":"+32 65 33 55 46",
    "sg:postcode":"7000",
    "sg:province":"Hainaut",
    "wof:name":"Cours Des M\u00c9tiers D'art",
    "wof:placetype":"venue"
},
  "geometry": {"coordinates":[3.9303979874,50.4526138306],"type":"Point"}
}