{
  "type": "Feature",
  "properties": {
    "addr:full":"J.-g. Eggerickxstraat 7 Sint-pieters-woluwe/woluwe-saint-pierre Bruxelles-Capitale 1150",
    "addr:housenumber":"7",
    "addr:postcode":"1150",
    "addr:street":"Eggerickxstraat;/",
    "iso:country":"BE",
    "sg:address":"J.-g. Eggerickxstraat 7",
    "sg:city":"Sint-pieters-woluwe/woluwe-saint-pierre",
    "sg:orig_category":"Dansscholen",
    "sg:phone":"+32 2 346 10 12",
    "sg:postcode":"1150",
    "sg:province":"Bruxelles-Capitale",
    "wof:name":"La Woluwe Danse",
    "wof:placetype":"venue"
},
  "geometry": {"coordinates":[4.4183940887,50.837310791],"type":"Point"}
}