{
  "type": "Feature",
  "properties": {
    "addr:full":"Bergensesteenweg 137 Sint-pieters-leeuw Vlaams-Brabant 1600",
    "addr:housenumber":"137",
    "addr:postcode":"1600",
    "addr:street":"Bergensesteenweg",
    "iso:country":"BE",
    "sg:address":"Bergensesteenweg 137",
    "sg:city":"Sint-pieters-leeuw",
    "sg:classifiers":[
        {
            "category":"Restaurant",
            "type":"Food & Drink"
        }
    ],
    "sg:phone":"+32 2 331 11 61",
    "sg:postcode":"1600",
    "sg:province":"Vlaams-Brabant",
    "wof:name":"Greco Palace",
    "wof:placetype":"venue"
},
  "geometry": {"coordinates":[4.2882099152,50.799659729],"type":"Point"}
}