{
  "type": "Feature",
  "properties": {
    "addr:full":"Statiestraat 118 Lichtervelde West-Vlaanderen 8810",
    "addr:housenumber":"118",
    "addr:postcode":"8810",
    "addr:street":"Statiestraat",
    "iso:country":"BE",
    "sg:address":"Statiestraat 118",
    "sg:city":"Lichtervelde",
    "sg:classifiers":[
        {
            "category":"Wholesale",
            "subcategory":"Machinery & Supplies",
            "type":"Manufacturing & Wholesale Goods"
        }
    ],
    "sg:phone":"+32 51 72 67 05",
    "sg:postcode":"8810",
    "sg:province":"West-Vlaanderen",
    "sg:tags":[
        "water",
        "pump",
        "-"
    ],
    "wof:name":"Ricover Nv",
    "wof:placetype":"venue"
},
  "geometry": {"coordinates":[3.1307349205,51.0250320435],"type":"Point"}
}