{
  "type": "Feature",
  "properties": {
    "iso:country":"BE",
    "sg:address":"Vrouwstraat 13",
    "sg:city":"Kaprijke",
    "sg:orig_category":"Rundveehouders Varkenskwekers",
    "sg:phone":"+32 9 373 65 54",
    "sg:postcode":"9970",
    "sg:province":"Oost-Vlaanderen",
    "wof:name":"Marc Blondeel",
    "wof:placetype":"venue"
},
  "geometry": {"coordinates":[3.6229810715,51.2197990417],"type":"Point"}
}