{
  "type": "Feature",
  "properties": {
    "addr:full":"Biezestraat 10 Hamme Oost-Vlaanderen 9220",
    "addr:housenumber":"10",
    "addr:postcode":"9220",
    "addr:street":"Biezestraat",
    "iso:country":"BE",
    "sg:address":"Biezestraat 10",
    "sg:city":"Hamme",
    "sg:classifiers":[
        {
            "category":"Professional",
            "subcategory":"Engineering",
            "type":"Services"
        }
    ],
    "sg:phone":"+32 52 47 28 43",
    "sg:postcode":"9220",
    "sg:province":"Oost-Vlaanderen",
    "sg:tags":[
        "industrial",
        "-",
        "automation"
    ],
    "wof:name":"I T M",
    "wof:placetype":"venue"
},
  "geometry": {"coordinates":[4.143764019,51.1007575989],"type":"Point"}
}