{
  "type": "Feature",
  "properties": {
    "iso:country":"BE",
    "sg:address":"Overheulestraat 88",
    "sg:city":"Wevelgem",
    "sg:orig_category":"Transports routiers de marchandises",
    "sg:phone":"+32 56 41 11 02",
    "sg:postcode":"8560",
    "sg:province":"West-Vlaanderen",
    "wof:name":"Samyn",
    "wof:placetype":"venue"
},
  "geometry": {"coordinates":[3.1647539139,50.8438262939],"type":"Point"}
}