{
  "type": "Feature",
  "properties": {
    "iso:country":"BE",
    "sg:address":"Meulebeeksestraat 38a",
    "sg:city":"Ardooie",
    "sg:classifiers":[
        {
            "category":"Wholesale",
            "subcategory":"Fruits & Vegetables",
            "type":"Manufacturing & Wholesale Goods"
        }
    ],
    "sg:phone":"+32 477 33 04 47",
    "sg:postcode":"8850",
    "sg:province":"West-Vlaanderen",
    "sg:tags":[
        "whol",
        "-"
    ],
    "wof:name":"Tomabel Vzw",
    "wof:placetype":"venue"
},
  "geometry": {"coordinates":[3.2410640717,50.9654922485],"type":"Point"}
}