{
  "type": "Feature",
  "properties": {
    "addr:full":"Rue Charles Magnette 11 Li\u00e8ge 1 Li\u00e8ge 4000",
    "addr:housenumber":"11;1",
    "addr:postcode":"4000",
    "addr:street":"Rue Charles Magnette",
    "iso:country":"BE",
    "sg:address":"Rue Charles Magnette 11",
    "sg:city":"Li\u00e8ge 1",
    "sg:classifiers":[
        {
            "category":"Shopping",
            "subcategory":"Crafts & Fabrics",
            "type":"Retail Goods"
        }
    ],
    "sg:phone":"+32 4 223 23 13",
    "sg:postcode":"4000",
    "sg:province":"Li\u00e8ge",
    "sg:tags":[
        "-",
        "wool",
        "knitting",
        "yarn"
    ],
    "wof:name":"Anny Blatt",
    "wof:placetype":"venue"
},
  "geometry": {"coordinates":[5.5734658241,50.6407356262],"type":"Point"}
}