{
  "type": "Feature",
  "properties": {
    "iso:country":"BE",
    "sg:address":"Oude Bruggeweg 13",
    "sg:city":"Jabbeke",
    "sg:orig_category":"Rundveehouders Varkenskwekers",
    "sg:phone":"+32 50 81 18 83",
    "sg:postcode":"8490",
    "sg:province":"West-Vlaanderen",
    "wof:name":"Freddy Vandaele",
    "wof:placetype":"venue"
},
  "geometry": {"coordinates":[3.0984399319,51.1680908203],"type":"Point"}
}