{
  "type": "Feature",
  "properties": {
    "iso:country":"BE",
    "sg:address":"Brugseweg 28",
    "sg:city":"Langemark-poelkapelle",
    "sg:classifiers":[
        {
            "category":"Manufacturing",
            "subcategory":"Textiles",
            "type":"Manufacturing & Wholesale Goods"
        }
    ],
    "sg:phone":"+32 57 48 93 07",
    "sg:postcode":"8920",
    "sg:province":"West-Vlaanderen",
    "wof:name":"Naaishop Marleen",
    "wof:placetype":"venue"
},
  "geometry": {"coordinates":[2.9355399609,50.8884620667],"type":"Point"}
}