{
  "type": "Feature",
  "properties": {
    "addr:full":"Place G\u00e9neral Mac Auliffe Bastogne Luxembourg 6600",
    "addr:postcode":"6600",
    "addr:street":"Place Ge\u0301Neral",
    "iso:country":"BE",
    "sg:address":"Place G\u00e9neral Mac Auliffe",
    "sg:city":"Bastogne",
    "sg:classifiers":[
        {
            "category":"Government",
            "subcategory":"Office",
            "type":"Public Place"
        }
    ],
    "sg:phone":"+32 61 21 27 11",
    "sg:postcode":"6600",
    "sg:province":"Luxembourg",
    "sg:tags":[
        "-",
        "tourism",
        "federation"
    ],
    "wof:name":"Syndicat D'initiative",
    "wof:placetype":"venue"
},
  "geometry": {"coordinates":[5.7155098915,50.0006561279],"type":"Point"}
}