{
  "type": "Feature",
  "properties": {
    "addr:full":"Place L\u00e9on D'andrimont 22 Limbourg Li\u00e8ge 4830",
    "addr:housenumber":"22",
    "addr:postcode":"4830",
    "addr:street":"Place Le\u0301On D'Andrimont",
    "iso:country":"BE",
    "sg:address":"Place L\u00e9on D'andrimont 22",
    "sg:city":"Limbourg",
    "sg:classifiers":[
        {
            "category":"Bars & Pubs",
            "type":"Food & Drink"
        }
    ],
    "sg:phone":"+32 87 76 28 40",
    "sg:postcode":"4830",
    "sg:province":"Li\u00e8ge",
    "wof:name":"American Bar Road-house",
    "wof:placetype":"venue"
},
  "geometry": {"coordinates":[5.9412178993,50.62059021],"type":"Point"}
}