{
  "type": "Feature",
  "properties": {
    "addr:full":"Verbindingslaan 72 Genk Limburg 3600",
    "addr:housenumber":"72",
    "addr:postcode":"3600",
    "addr:street":"Verbindingslaan",
    "iso:country":"BE",
    "sg:address":"Verbindingslaan 72",
    "sg:city":"Genk",
    "sg:orig_category":"Kapsalons",
    "sg:phone":"+32 89 38 10 41",
    "sg:postcode":"3600",
    "sg:province":"Limburg",
    "wof:name":"Coiffure Lella",
    "wof:placetype":"venue"
},
  "geometry": {"coordinates":[5.514485836,50.9933662415],"type":"Point"}
}