{
  "type": "Feature",
  "properties": {
    "iso:country":"BE",
    "sg:address":"Place Monseu 1",
    "sg:city":"Ciney",
    "sg:orig_category":"Slagers",
    "sg:phone":"+32 83 21 21 57",
    "sg:postcode":"5590",
    "sg:province":"Namur",
    "wof:name":"Michel Questiaux",
    "wof:placetype":"venue"
},
  "geometry": {"coordinates":[5.0990071297,50.2964019775],"type":"Point"}
}