{
  "type": "Feature",
  "properties": {
    "iso:country":"BE",
    "sg:address":"Visesteenweg 146",
    "sg:city":"Riemst",
    "sg:orig_category":"Groententeelt",
    "sg:phone":"+32 12 45 69 63",
    "sg:postcode":"3770",
    "sg:province":"Limburg",
    "wof:name":"Stefan Schoubs",
    "wof:placetype":"venue"
},
  "geometry": {"coordinates":[5.606347084,50.8036117554],"type":"Point"}
}