{
  "type": "Feature",
  "properties": {
    "addr:full":"Generaal De Krahestraat 26 Leopoldsburg (groot) Limburg 3970",
    "addr:housenumber":"26",
    "addr:postcode":"3970",
    "addr:street":"Generaal De Krahestraat;Groot Limburg",
    "iso:country":"BE",
    "sg:address":"Generaal De Krahestraat 26",
    "sg:city":"Leopoldsburg (groot)",
    "sg:orig_category":"Herstellingen and onderhoud aan huis voor voertuigen Metaalafval, schrootrecyclage and sloperijen",
    "sg:phone":"+32 11 34 12 40",
    "sg:postcode":"3970",
    "sg:province":"Limburg",
    "wof:name":"Pairoux",
    "wof:placetype":"venue"
},
  "geometry": {"coordinates":[5.2624220848,51.1210517883],"type":"Point"}
}