{
  "type": "Feature",
  "properties": {
    "iso:country":"BE",
    "sg:address":"C\u00f4te De Hagelstein 9",
    "sg:city":"Aubel",
    "sg:classifiers":[
        {
            "category":"Building & Trades",
            "subcategory":"Electrical",
            "type":"Services"
        }
    ],
    "sg:phone":"+32 87 68 67 45",
    "sg:postcode":"4880",
    "sg:province":"Li\u00e8ge",
    "sg:tags":[
        "electric",
        "-",
        "housewiring",
        "contractor"
    ],
    "wof:name":"Lahaye G Sprl",
    "wof:placetype":"venue"
},
  "geometry": {"coordinates":[5.8582000732,50.7129211426],"type":"Point"}
}