{
  "type": "Feature",
  "properties": {
    "iso:country":"BE",
    "sg:address":"Beverenstraat 72",
    "sg:city":"Ardooie",
    "sg:orig_category":"Huisdieren and benodigdheden Royal Canin",
    "sg:phone":"+32 51 74 60 34",
    "sg:postcode":"8850",
    "sg:province":"West-Vlaanderen",
    "wof:name":"Verkindere Filip",
    "wof:placetype":"venue"
},
  "geometry": {"coordinates":[3.1745829582,50.9753265381],"type":"Point"}
}