{
  "type": "Feature",
  "properties": {
    "iso:country":"BE",
    "sg:address":"Beekstraat 15",
    "sg:city":"Zwevegem",
    "sg:orig_category":"Bouwmaterialen Gh Installatie van houten of kunststof schrijnwerk Installatie van metalen schrijnwer",
    "sg:phone":"+32 56 75 78 33",
    "sg:postcode":"8550",
    "sg:province":"West-Vlaanderen",
    "wof:name":"Kurt Vermeulen",
    "wof:placetype":"venue"
},
  "geometry": {"coordinates":[3.311522007,50.8009605408],"type":"Point"}
}