{
  "type": "Feature",
  "properties": {
    "iso:country":"BE",
    "sg:address":"Rue De La Limite 116",
    "sg:city":"Sint-joost-ten-node/saint-josse-ten-noode",
    "sg:orig_category":"Instituts pour adultes moins valides",
    "sg:phone":"+32 2 218 44 98",
    "sg:postcode":"1210",
    "sg:province":"Bruxelles-Capitale",
    "wof:name":"C.e.r.d.a.",
    "wof:placetype":"venue"
},
  "geometry": {"coordinates":[4.3723759651,50.8560295105],"type":"Point"}
}