{
  "type": "Feature",
  "properties": {
    "addr:full":"Rue De La Verrerie 185b44 Seraing Li\u00e8ge 4100",
    "addr:housenumber":"185b44",
    "addr:postcode":"4100",
    "addr:street":"Rue De La Verrerie",
    "iso:country":"BE",
    "sg:address":"Rue De La Verrerie 185b44",
    "sg:city":"Seraing",
    "sg:orig_category":"Apotheken",
    "sg:phone":"+32 4 337 16 69",
    "sg:postcode":"4100",
    "sg:province":"Li\u00e8ge",
    "wof:name":"Jean Carra",
    "wof:placetype":"venue"
},
  "geometry": {"coordinates":[5.5009551048,50.5786399841],"type":"Point"}
}