{
  "type": "Feature",
  "properties": {
    "iso:country":"BE",
    "sg:address":"Cours De Valduc 13",
    "sg:city":"Ottignies-louvain-la-neuve",
    "sg:orig_category":"M\u00e9decins and sp\u00e9cialistes",
    "sg:phone":"+32 10 45 05 96",
    "sg:postcode":"1348",
    "sg:province":"Brabant Wallon",
    "wof:name":"Catherine De Villers Grand Champs",
    "wof:placetype":"venue"
},
  "geometry": {"coordinates":[4.6132831573,50.6745414734],"type":"Point"}
}