{
  "type": "Feature",
  "properties": {
    "addr:full":"Sterrestraat 79 Koekelare West-Vlaanderen 8680",
    "addr:housenumber":"79",
    "addr:postcode":"8680",
    "addr:street":"Sterrestraat",
    "iso:country":"BE",
    "sg:address":"Sterrestraat 79",
    "sg:city":"Koekelare",
    "sg:orig_category":"Varkenskwekers",
    "sg:phone":"+32 51 58 80 77",
    "sg:postcode":"8680",
    "sg:province":"West-Vlaanderen",
    "wof:name":"Louis Montaigne",
    "wof:placetype":"venue"
},
  "geometry": {"coordinates":[2.9676721096,51.0870666504],"type":"Point"}
}