{
  "type": "Feature",
  "properties": {
    "addr:full":"Hoogveldweg 93 Lier Antwerpen 2500",
    "addr:housenumber":"93",
    "addr:postcode":"2500",
    "addr:street":"Hoogveldweg",
    "iso:country":"BE",
    "sg:address":"Hoogveldweg 93",
    "sg:city":"Lier",
    "sg:classifiers":[
        {
            "category":"Home & Garden",
            "subcategory":"Household Appliances",
            "type":"Retail Goods"
        }
    ],
    "sg:phone":"+32 3 488 02 51",
    "sg:postcode":"2500",
    "sg:province":"Antwerpen",
    "sg:tags":[
        "repair",
        "mainten",
        "-",
        "electric"
    ],
    "wof:name":"De Cuyper Nv",
    "wof:placetype":"venue"
},
  "geometry": {"coordinates":[4.5781269073,51.1242294312],"type":"Point"}
}