{
  "type": "Feature",
  "properties": {
    "addr:full":"Rue Haygraben 26 La Calamine Li\u00e8ge 4720",
    "addr:housenumber":"26",
    "addr:postcode":"4720",
    "addr:street":"Rue Haygraben",
    "iso:country":"BE",
    "sg:address":"Rue Haygraben 26",
    "sg:city":"La Calamine",
    "sg:orig_category":"Diverse bedrijfsbeheeradviesbureaus",
    "sg:phone":"+32 87 65 26 54",
    "sg:postcode":"4720",
    "sg:province":"Li\u00e8ge",
    "wof:name":"E.f.s.",
    "wof:placetype":"venue"
},
  "geometry": {"coordinates":[6.0148301125,50.7149848938],"type":"Point"}
}