{
  "type": "Feature",
  "properties": {
    "addr:full":"Rue Du March\u00e9 Aux Poulets 32 Bruxelles Bruxelles-Capitale 1000",
    "addr:housenumber":"32",
    "addr:postcode":"1000",
    "addr:street":"Rue Du Marche\u0301 Aux Poulets",
    "iso:country":"BE",
    "sg:address":"Rue Du March\u00e9 Aux Poulets 32",
    "sg:city":"Bruxelles",
    "sg:classifiers":[
        {
            "category":"Arena",
            "subcategory":"Sports Club",
            "type":"Entertainment"
        }
    ],
    "sg:phone":"+32 2 219 49 01",
    "sg:postcode":"1000",
    "sg:province":"Bruxelles-Capitale",
    "wof:name":"Sharkeys Snooker Cafe",
    "wof:placetype":"venue"
},
  "geometry": {"coordinates":[4.3508181572,50.848941803],"type":"Point"}
}