{
  "type": "Feature",
  "properties": {
    "iso:country":"BE",
    "sg:address":"Rueelstraat 2",
    "sg:city":"Maaseik",
    "sg:classifiers":[
        {
            "category":"Shopping",
            "subcategory":"Clothing, Apparel, & Fashions",
            "type":"Retail Goods"
        }
    ],
    "sg:phone":"+32 89 65 03 57",
    "sg:postcode":"3680",
    "sg:province":"Limburg",
    "sg:tags":[
        "lady",
        "clothing",
        "-"
    ],
    "wof:name":"Girls Company",
    "wof:placetype":"venue"
},
  "geometry": {"coordinates":[5.7882709503,51.0954093933],"type":"Point"}
}