{
  "type": "Feature",
  "properties": {
    "iso:country":"BE",
    "sg:address":"Abergstraat 2",
    "sg:city":"Retie",
    "sg:orig_category":"Installation de menuiserie en bois and plastique. Installation de menuiserie m\u00e9tallique",
    "sg:phone":"+32 14 37 37 75",
    "sg:postcode":"2470",
    "sg:province":"Antwerpen",
    "wof:name":"Herman Ooms",
    "wof:placetype":"venue"
},
  "geometry": {"coordinates":[5.110681057,51.2595901489],"type":"Point"}
}