{
  "type": "Feature",
  "properties": {
    "iso:country":"BE",
    "sg:address":"Perzikenlaan 11",
    "sg:city":"Beveren",
    "sg:orig_category":"Entretien and r\u00e9parations de voitures",
    "sg:phone":"+32 3 775 55 25",
    "sg:postcode":"9120",
    "sg:province":"Oost-Vlaanderen",
    "wof:name":"Andre Cap",
    "wof:placetype":"venue"
},
  "geometry": {"coordinates":[4.2932481766,51.2163238525],"type":"Point"}
}