{
  "type": "Feature",
  "properties": {
    "iso:country":"BE",
    "sg:address":"Rue Saint-sebastien 96",
    "sg:city":"Braine-l\u00b4alleud",
    "sg:classifiers":[
        {
            "category":"Fast Food",
            "type":"Food & Drink"
        }
    ],
    "sg:phone":"+32 2 384 22 05",
    "sg:postcode":"1420",
    "sg:province":"Brabant Wallon",
    "sg:tags":[
        "huis",
        "aan",
        "levering",
        "meeneem",
        "restaurant"
    ],
    "wof:name":"Le Nord",
    "wof:placetype":"venue"
},
  "geometry": {"coordinates":[4.379650116,50.6781806946],"type":"Point"}
}