{
  "type": "Feature",
  "properties": {
    "addr:full":"Zandbergerstraat 10 Maaseik (neeroeteren) Limburg 3680",
    "addr:housenumber":"10",
    "addr:postcode":"3680",
    "addr:street":"Zandbergerstraat",
    "iso:country":"BE",
    "sg:address":"Zandbergerstraat 10",
    "sg:city":"Maaseik (neeroeteren)",
    "sg:classifiers":[
        {
            "category":"Arts & Performance",
            "subcategory":"Art Gallery",
            "type":"Entertainment"
        }
    ],
    "sg:phone":"+32 89 86 45 58",
    "sg:postcode":"3680",
    "sg:province":"Limburg",
    "wof:name":"Exelmans Kunstgalerie/beeldentuin",
    "wof:placetype":"venue"
},
  "geometry": {"coordinates":[5.791285038,51.0954208374],"type":"Point"}
}