{
  "type": "Feature",
  "properties": {
    "iso:country":"BE",
    "sg:address":"Heilig-hartstraat 37b3",
    "sg:city":"Roeselare",
    "sg:orig_category":"Beheer onroerend goed",
    "sg:phone":"+32 51 20 28 24",
    "sg:postcode":"8800",
    "sg:province":"West-Vlaanderen",
    "wof:name":"Roland Brouckaert",
    "wof:placetype":"venue"
},
  "geometry": {"coordinates":[3.1227169037,50.9358787537],"type":"Point"}
}