{
  "type": "Feature",
  "properties": {
    "addr:full":"Visbeekstraat 9 Turnhout Antwerpen 2300",
    "addr:housenumber":"9",
    "addr:postcode":"2300",
    "addr:street":"Visbeekstraat",
    "iso:country":"BE",
    "sg:address":"Visbeekstraat 9",
    "sg:city":"Turnhout",
    "sg:classifiers":[
        {
            "category":"Banks & Credit Unions",
            "subcategory":"Investment Brokerage",
            "type":"Services"
        }
    ],
    "sg:phone":"+32 14 42 76 71",
    "sg:postcode":"2300",
    "sg:province":"Antwerpen",
    "sg:tags":[
        "printing",
        "ink"
    ],
    "wof:name":"O + R Inktchemie Nv",
    "wof:placetype":"venue"
},
  "geometry": {"coordinates":[4.9150319099,51.3076248169],"type":"Point"}
}