{
  "type": "Feature",
  "properties": {
    "addr:full":"Naamsestraat 115 Leuven Vlaams-Brabant 3000",
    "addr:housenumber":"115",
    "addr:postcode":"3000",
    "addr:street":"Naamsestraat",
    "iso:country":"BE",
    "sg:address":"Naamsestraat 115",
    "sg:city":"Leuven",
    "sg:orig_category":"Imprimeries and copyshops",
    "sg:phone":"+32 16 23 70 03",
    "sg:postcode":"3000",
    "sg:province":"Vlaams-Brabant",
    "wof:name":"Eco-copy",
    "wof:placetype":"venue"
},
  "geometry": {"coordinates":[4.699821949,50.8719520569],"type":"Point"}
}