{
  "type": "Feature",
  "properties": {
    "iso:country":"BE",
    "sg:address":"Bois Nd 1",
    "sg:city":"Marche-en-famenne",
    "sg:classifiers":[
        {
            "category":"Professional",
            "type":"Services"
        }
    ],
    "sg:phone":"+32 84 31 17 90",
    "sg:postcode":"6900",
    "sg:province":"Luxembourg",
    "sg:tags":[
        "transport",
        "road"
    ],
    "wof:name":"Magermans Guy Ets",
    "wof:placetype":"venue"
},
  "geometry": {"coordinates":[5.3324599266,50.2278404236],"type":"Point"}
}