{
  "type": "Feature",
  "properties": {
    "iso:country":"BE",
    "sg:address":"Avenue De L'europe 3",
    "sg:city":"Huy",
    "sg:orig_category":"Artsen and specialisten",
    "sg:phone":"+32 85 21 41 70",
    "sg:postcode":"4500",
    "sg:province":"Li\u00e8ge",
    "wof:name":"Jacques Hyeulle",
    "wof:placetype":"venue"
},
  "geometry": {"coordinates":[5.2530069351,50.5207824707],"type":"Point"}
}