{
  "type": "Feature",
  "properties": {
    "addr:full":"Rue Pepin 5a Profondeville (lustin) Namur 5170",
    "addr:housenumber":"5a",
    "addr:postcode":"5170",
    "addr:street":"Rue Pepin",
    "iso:country":"BE",
    "sg:address":"Rue Pepin 5a",
    "sg:city":"Profondeville (lustin)",
    "sg:classifiers":[
        {
            "category":"Insurance",
            "subcategory":"Insurance Agent",
            "type":"Services"
        }
    ],
    "sg:phone":"+32 81 41 28 93",
    "sg:postcode":"5170",
    "sg:province":"Namur",
    "sg:tags":[
        "broker"
    ],
    "wof:name":"Bureau Assurances P Hens",
    "wof:placetype":"venue"
},
  "geometry": {"coordinates":[4.8662858009,50.3785209656],"type":"Point"}
}