{
  "type": "Feature",
  "properties": {
    "iso:country":"BE",
    "sg:address":"Avenue De La Gare 156",
    "sg:city":"Hotton",
    "sg:orig_category":"Produits \u00e0 base de pommes de terre Fruits and l\u00e9gumes Gr",
    "sg:phone":"+32 84 46 60 55",
    "sg:postcode":"6990",
    "sg:province":"Luxembourg",
    "wof:name":"Laffineuse",
    "wof:placetype":"venue"
},
  "geometry": {"coordinates":[5.439209938,50.2756614685],"type":"Point"}
}