{
  "type": "Feature",
  "properties": {
    "iso:country":"BE",
    "sg:address":"Rue Jean Paquot 55",
    "sg:city":"Bruxelles (ixelles)",
    "sg:classifiers":[
        {
            "category":"Retail",
            "subcategory":"Funeral Services",
            "type":"Services"
        }
    ],
    "sg:phone":"+32 2 647 26 10",
    "sg:postcode":"1050",
    "sg:province":"Bruxelles-Capitale",
    "sg:tags":[
        "director"
    ],
    "wof:name":"Rogge-celerier",
    "wof:placetype":"venue"
},
  "geometry": {"coordinates":[4.3787579536,50.8259849548],"type":"Point"}
}