{
  "type": "Feature",
  "properties": {
    "iso:country":"BE",
    "sg:address":"Kruisstraat 35",
    "sg:city":"Berlare",
    "sg:orig_category":"Pain, p\u00e2tisseries and confiseries",
    "sg:phone":"+32 9 367 50 41",
    "sg:postcode":"9290",
    "sg:province":"Oost-Vlaanderen",
    "wof:name":"Bakkerij D'hooge",
    "wof:placetype":"venue"
},
  "geometry": {"coordinates":[3.9577019215,51.0471572876],"type":"Point"}
}