{
  "type": "Feature",
  "properties": {
    "iso:country":"BE",
    "sg:address":"Hoortverten 35",
    "sg:city":"Vosselaar",
    "sg:classifiers":[
        {
            "category":"Social Services",
            "subcategory":"Job Training",
            "type":"Services"
        }
    ],
    "sg:phone":"+32 14 61 67 22",
    "sg:postcode":"2350",
    "sg:province":"Antwerpen",
    "sg:tags":[
        "interpreter"
    ],
    "wof:name":"Sauvillers L",
    "wof:placetype":"venue"
},
  "geometry": {"coordinates":[4.8845829964,51.3008003235],"type":"Point"}
}