{
  "type": "Feature",
  "properties": {
    "iso:country":"BE",
    "sg:address":"Laarstraat 15",
    "sg:city":"Zwijndrecht",
    "sg:orig_category":"Openbare bibliotheken and archieven",
    "sg:phone":"+32 3 252 64 99",
    "sg:postcode":"2070",
    "sg:province":"Antwerpen",
    "wof:name":"Openbare Bibliotheek",
    "wof:placetype":"venue"
},
  "geometry": {"coordinates":[4.3325228691,51.2144355774],"type":"Point"}
}