{
  "type": "Feature",
  "properties": {
    "addr:full":"Rue Du Val-beno\u00cet 76 Li\u00c8ge Li\u00e8ge 4031",
    "addr:housenumber":"76",
    "addr:postcode":"4031",
    "addr:street":"Rue Du Val-Benoi\u0302T",
    "iso:country":"BE",
    "sg:address":"Rue Du Val-beno\u00cet 76",
    "sg:city":"Li\u00c8ge",
    "sg:orig_category":"Architectes",
    "sg:phone":"+32 4 365 03 96",
    "sg:postcode":"4031",
    "sg:province":"Li\u00e8ge",
    "wof:name":"Mauro Baccarini",
    "wof:placetype":"venue"
},
  "geometry": {"coordinates":[5.5937709808,50.613735199],"type":"Point"}
}