{
  "type": "Feature",
  "properties": {
    "iso:country":"BE",
    "sg:address":"Rue De L'ornia 9",
    "sg:city":"Hamois (mohiville)",
    "sg:classifiers":[
        {
            "category":"Farming",
            "subcategory":"Livestock Farm",
            "type":"Manufacturing & Wholesale Goods"
        }
    ],
    "sg:phone":"+32 83 68 81 37",
    "sg:postcode":"5361",
    "sg:province":"Namur",
    "sg:tags":[
        "buyer"
    ],
    "wof:name":"Colinet P",
    "wof:placetype":"venue"
},
  "geometry": {"coordinates":[5.1804847717,50.3201904297],"type":"Point"}
}