{
  "type": "Feature",
  "properties": {
    "iso:country":"BE",
    "sg:address":"Avenue Eug\u00c8ne Mascaux 37",
    "sg:city":"Charleroi",
    "sg:orig_category":"Banques and organismes de cr\u00e9dit",
    "sg:phone":"+32 71 43 04 24",
    "sg:postcode":"6001",
    "sg:province":"Hainaut",
    "wof:name":"Bacob",
    "wof:placetype":"venue"
},
  "geometry": {"coordinates":[4.4466981888,50.3988342285],"type":"Point"}
}