{
  "type": "Feature",
  "properties": {
    "iso:country":"BE",
    "sg:address":"Avenue G\u00e9n\u00e9ral Michel 1a",
    "sg:city":"Charleroi",
    "sg:classifiers":[
        {
            "category":"Professional",
            "subcategory":"Accounting & Tax Preparation",
            "type":"Services"
        }
    ],
    "sg:phone":"+32 71 32 11 60",
    "sg:postcode":"6000",
    "sg:province":"Hainaut",
    "sg:tags":[
        "bookkeeper"
    ],
    "wof:name":"Auxiliary Sc",
    "wof:placetype":"venue"
},
  "geometry": {"coordinates":[4.4504227638,50.4104766846],"type":"Point"}
}