{
  "type": "Feature",
  "properties": {
    "addr:full":"Rue Saint-jacques 4-6 Namur Namur 5000",
    "addr:housenumber":"4-6",
    "addr:postcode":"5000",
    "addr:street":"Rue Saint-Jacques",
    "iso:country":"BE",
    "sg:address":"Rue Saint-jacques 4-6",
    "sg:city":"Namur",
    "sg:classifiers":[
        {
            "category":"Shopping",
            "subcategory":"Luggage & Leather Goods",
            "type":"Retail Goods"
        }
    ],
    "sg:phone":"+32 81 23 01 82",
    "sg:postcode":"5000",
    "sg:province":"Namur",
    "sg:tags":[
        "-"
    ],
    "wof:name":"Caract\u00e8re Chaussures",
    "wof:placetype":"venue"
},
  "geometry": {"coordinates":[4.8648080826,50.4650764465],"type":"Point"}
}