{
  "type": "Feature",
  "properties": {
    "addr:full":"Opaaigem 1 Erpe-mere (aaigem) Oost-Vlaanderen 9420",
    "addr:housenumber":"1",
    "addr:postcode":"9420",
    "addr:street":"Opaaigem",
    "iso:country":"BE",
    "sg:address":"Opaaigem 1",
    "sg:city":"Erpe-mere (aaigem)",
    "sg:classifiers":[
        {
            "category":"Building & Trades",
            "subcategory":"Construction",
            "type":"Services"
        }
    ],
    "sg:phone":"+32 497 04 70 57",
    "sg:postcode":"9420",
    "sg:province":"Oost-Vlaanderen",
    "sg:tags":[
        "installation",
        "-",
        "central",
        "heating"
    ],
    "wof:name":"Eliano",
    "wof:placetype":"venue"
},
  "geometry": {"coordinates":[3.9387021065,50.8909988403],"type":"Point"}
}