{
  "type": "Feature",
  "properties": {
    "iso:country":"BE",
    "sg:address":"Chemin De Couture 1b1",
    "sg:city":"Genappe",
    "sg:orig_category":"Kapsalons",
    "sg:phone":"+32 10 61 22 81",
    "sg:postcode":"1470",
    "sg:province":"Brabant Wallon",
    "wof:name":"Coup'in",
    "wof:placetype":"venue"
},
  "geometry": {"coordinates":[4.5125827789,50.6351928711],"type":"Point"}
}