{
  "type": "Feature",
  "properties": {
    "addr:full":"Rue Du Sondage 23 Gerpinnes Hainaut 6280",
    "addr:housenumber":"23",
    "addr:postcode":"6280",
    "addr:street":"Rue Du Sondage;Hainaut",
    "iso:country":"BE",
    "sg:address":"Rue Du Sondage 23",
    "sg:city":"Gerpinnes",
    "sg:classifiers":[
        {
            "category":"Restaurant",
            "type":"Food & Drink"
        }
    ],
    "sg:phone":"+32 71 50 57 64",
    "sg:postcode":"6280",
    "sg:province":"Hainaut",
    "wof:name":"Les Jardins Fleuris",
    "wof:placetype":"venue"
},
  "geometry": {"coordinates":[4.5014801025,50.339302063],"type":"Point"}
}