{
  "type": "Feature",
  "properties": {
    "addr:full":"Surm. De Volsbergestr. 48 Ieper West-Vlaanderen 8900",
    "addr:housenumber":"48",
    "addr:postcode":"8900",
    "iso:country":"BE",
    "sg:address":"Surm. De Volsbergestr. 48",
    "sg:city":"Ieper",
    "sg:orig_category":"Verplichte sociale verzekeringen",
    "sg:phone":"+32 57 20 06 62",
    "sg:postcode":"8900",
    "sg:province":"West-Vlaanderen",
    "wof:name":"Westvl. Liberaal Ziekenf.",
    "wof:placetype":"venue"
},
  "geometry": {"coordinates":[2.8839979172,50.85338974],"type":"Point"}
}