{
  "type": "Feature",
  "properties": {
    "iso:country":"BE",
    "sg:address":"Leenhaagstraat 34",
    "sg:city":"Zoutleeuw",
    "sg:classifiers":[
        {
            "category":"Cafe",
            "type":"Food & Drink"
        }
    ],
    "sg:phone":"+32 11 58 80 24",
    "sg:postcode":"3440",
    "sg:province":"Vlaams-Brabant",
    "sg:tags":[
        "caf\u00e9s"
    ],
    "wof:name":"Anna Rubens",
    "wof:placetype":"venue"
},
  "geometry": {"coordinates":[5.0636110306,50.8706970215],"type":"Point"}
}