{
  "type": "Feature",
  "properties": {
    "iso:country":"BE",
    "sg:address":"Jonkerweg 17",
    "sg:city":"Wuustwezel",
    "sg:orig_category":"Ramassage and traitement des d\u00e9chets m\u00e9nagers. D\u00e9molition d\u00b4immeubles and terrassements",
    "sg:phone":"+32 3 669 75 78",
    "sg:postcode":"2990",
    "sg:province":"Antwerpen",
    "wof:name":"Swa Aernouts",
    "wof:placetype":"venue"
},
  "geometry": {"coordinates":[4.6682357788,51.4095153809],"type":"Point"}
}