{
  "type": "Feature",
  "properties": {
    "iso:country":"BE",
    "sg:address":"Rue Neuve 33",
    "sg:city":"Huy",
    "sg:orig_category":"Apotheken",
    "sg:phone":"+32 85 21 14 85",
    "sg:postcode":"4500",
    "sg:province":"Li\u00e8ge",
    "wof:name":"Julienne Fassotte",
    "wof:placetype":"venue"
},
  "geometry": {"coordinates":[5.2351880074,50.5208625793],"type":"Point"}
}