{
  "type": "Feature",
  "properties": {
    "iso:country":"BE",
    "sg:address":"Kortrijkstraat 246",
    "sg:city":"Wevelgem",
    "sg:classifiers":[
        {
            "category":"Structure",
            "subcategory":"Building",
            "type":"Public Place"
        }
    ],
    "sg:phone":"+32 56 42 62 07",
    "sg:postcode":"8560",
    "sg:province":"West-Vlaanderen",
    "sg:tags":[
        "door"
    ],
    "wof:name":"Trappen Verschaeve",
    "wof:placetype":"venue"
},
  "geometry": {"coordinates":[3.1970579624,50.8126525879],"type":"Point"}
}