{
  "type": "Feature",
  "properties": {
    "addr:full":"Rue Thomas Edison 57 Grace-hollogne Li\u00e8ge 4460",
    "addr:housenumber":"57",
    "addr:postcode":"4460",
    "addr:street":"Rue Thomas Edison",
    "iso:country":"BE",
    "sg:address":"Rue Thomas Edison 57",
    "sg:city":"Grace-hollogne",
    "sg:classifiers":[
        {
            "category":"Arena",
            "subcategory":"Sports Club",
            "type":"Entertainment"
        }
    ],
    "sg:phone":"+32 4 233 13 03",
    "sg:postcode":"4460",
    "sg:province":"Li\u00e8ge",
    "sg:tags":[
        "de"
    ],
    "wof:name":"La Tourelle T.c.",
    "wof:placetype":"venue"
},
  "geometry": {"coordinates":[5.4981350899,50.6343994141],"type":"Point"}
}