{
  "type": "Feature",
  "properties": {
    "addr:full":"Kokstraat 45 Nieuwpoort West-Vlaanderen 8620",
    "addr:housenumber":"45",
    "addr:postcode":"8620",
    "addr:street":"Kokstraat",
    "iso:country":"BE",
    "sg:address":"Kokstraat 45",
    "sg:city":"Nieuwpoort",
    "sg:orig_category":"Notarissen",
    "sg:phone":"+32 58 23 31 19",
    "sg:postcode":"8620",
    "sg:province":"West-Vlaanderen",
    "wof:name":"M. Swennen",
    "wof:placetype":"venue"
},
  "geometry": {"coordinates":[2.7484240532,51.1308822632],"type":"Point"}
}