{
  "type": "Feature",
  "properties": {
    "addr:full":"Bas-v\u00c2 43 Manhay Luxembourg 6960",
    "addr:housenumber":"43",
    "addr:postcode":"6960",
    "addr:street":"Bas-Va\u0302",
    "iso:country":"BE",
    "sg:address":"Bas-v\u00c2 43",
    "sg:city":"Manhay",
    "sg:orig_category":"Rundveehouders",
    "sg:phone":"+32 86 45 54 48",
    "sg:postcode":"6960",
    "sg:province":"Luxembourg",
    "wof:name":"Claude Bernier",
    "wof:placetype":"venue"
},
  "geometry": {"coordinates":[5.6710062027,50.2944068909],"type":"Point"}
}