{
  "type": "Feature",
  "properties": {
    "addr:full":"Rue D'havr\u00c9 73 Mons Hainaut 7000",
    "addr:housenumber":"73",
    "addr:postcode":"7000",
    "addr:street":"Rue D'Havre \u0301;Hainaut",
    "iso:country":"BE",
    "sg:address":"Rue D'havr\u00c9 73",
    "sg:city":"Mons",
    "sg:classifiers":[
        {
            "category":"Fast Food",
            "type":"Food & Drink"
        }
    ],
    "sg:phone":"+32 65 34 82 60",
    "sg:postcode":"7000",
    "sg:province":"Hainaut",
    "sg:tags":[
        "\u00c0",
        "restaurants",
        "emporter",
        "restaurant"
    ],
    "wof:name":"Liang's Jardins",
    "wof:placetype":"venue"
},
  "geometry": {"coordinates":[3.9554240704,50.4538459778],"type":"Point"}
}