{
  "type": "Feature",
  "properties": {
    "iso:country":"BE",
    "sg:address":"Rue L\u00c9on Navez 1",
    "sg:city":"Mons",
    "sg:orig_category":"Schoonheidssalons",
    "sg:phone":"+32 65 31 59 39",
    "sg:postcode":"7000",
    "sg:province":"Hainaut",
    "wof:name":"Liliane Baleine",
    "wof:placetype":"venue"
},
  "geometry": {"coordinates":[3.9523251057,50.4624671936],"type":"Point"}
}