{
  "type": "Feature",
  "properties": {
    "addr:full":"Klei 85 Opwijk Vlaams-Brabant 1745",
    "addr:housenumber":"85",
    "addr:postcode":"1745",
    "addr:street":"Klei",
    "iso:country":"BE",
    "sg:address":"Klei 85",
    "sg:city":"Opwijk",
    "sg:classifiers":[
        {
            "category":"Restaurant",
            "type":"Food & Drink"
        }
    ],
    "sg:phone":"+32 52 37 52 38",
    "sg:postcode":"1745",
    "sg:province":"Vlaams-Brabant",
    "wof:name":"De Kleihoeve",
    "wof:placetype":"venue"
},
  "geometry": {"coordinates":[4.2072658539,50.962020874],"type":"Point"}
}