{
  "type": "Feature",
  "properties": {
    "iso:country":"BE",
    "sg:address":"Nieuwstraat 21",
    "sg:city":"Asse",
    "sg:classifiers":[
        {
            "category":"Bars & Pubs",
            "type":"Food & Drink"
        }
    ],
    "sg:phone":"+32 2 453 23 52",
    "sg:postcode":"1730",
    "sg:province":"Vlaams-Brabant",
    "wof:name":"Den Hoek",
    "wof:placetype":"venue"
},
  "geometry": {"coordinates":[4.1955118179,50.911239624],"type":"Point"}
}