{
  "type": "Feature",
  "properties": {
    "addr:full":"Kiezelweg 93 Herk-de-stad Limburg 3540",
    "addr:housenumber":"93",
    "addr:postcode":"3540",
    "addr:street":"Kiezelweg",
    "iso:country":"BE",
    "sg:address":"Kiezelweg 93",
    "sg:city":"Herk-de-stad",
    "sg:orig_category":"Epiceries",
    "sg:phone":"+32 13 55 46 80",
    "sg:postcode":"3540",
    "sg:province":"Limburg",
    "wof:name":"Mady Brams",
    "wof:placetype":"venue"
},
  "geometry": {"coordinates":[5.1778497696,50.9556999207],"type":"Point"}
}