{
  "type": "Feature",
  "properties": {
    "iso:country":"BE",
    "sg:address":"Rue Des Fusill\u00c9s 5",
    "sg:city":"Ottignies-louvain-la-neuve",
    "sg:orig_category":"Apotheken",
    "sg:phone":"+32 10 41 53 38",
    "sg:postcode":"1340",
    "sg:province":"Brabant Wallon",
    "wof:name":"Pharmacie Wuiame",
    "wof:placetype":"venue"
},
  "geometry": {"coordinates":[4.5732250214,50.6697769165],"type":"Point"}
}