{
  "type": "Feature",
  "properties": {
    "iso:country":"BE",
    "sg:address":"Kammenstraat 84",
    "sg:city":"Antwerpen",
    "sg:orig_category":"Babyspullen Dameskledingzaken",
    "sg:phone":"+32 3 226 21 94",
    "sg:postcode":"2000",
    "sg:province":"Antwerpen",
    "wof:name":"Fragile",
    "wof:placetype":"venue"
},
  "geometry": {"coordinates":[4.4019150734,51.2157211304],"type":"Point"}
}