{
  "type": "Feature",
  "properties": {
    "addr:full":"J. B. Charlierlaan 53 Hoeilaart Vlaams-Brabant 1560",
    "addr:housenumber":"53",
    "addr:postcode":"1560",
    "addr:street":"J.;Charlierlaan",
    "iso:country":"BE",
    "sg:address":"J. B. Charlierlaan 53",
    "sg:city":"Hoeilaart",
    "sg:orig_category":"Herstellingen and onderhoud van auto's Onderdelen and accessoires voor auto's Verhuur voertuigen beh",
    "sg:phone":"+32 2 657 92 22",
    "sg:postcode":"1560",
    "sg:province":"Vlaams-Brabant",
    "wof:name":"De Rudder",
    "wof:placetype":"venue"
},
  "geometry": {"coordinates":[4.465637207,50.7664070129],"type":"Point"}
}