{
  "type": "Feature",
  "properties": {
    "addr:full":"Gruuthusestraat 44 Tielt West-Vlaanderen 8700",
    "addr:housenumber":"44",
    "addr:postcode":"8700",
    "addr:street":"Gruuthusestraat",
    "iso:country":"BE",
    "sg:address":"Gruuthusestraat 44",
    "sg:city":"Tielt",
    "sg:orig_category":"Verhuur textielartikelen and schoenen",
    "sg:phone":"+32 51 40 06 78",
    "sg:postcode":"8700",
    "sg:province":"West-Vlaanderen",
    "wof:name":"Huis Maes",
    "wof:placetype":"venue"
},
  "geometry": {"coordinates":[3.3334710598,50.9897956848],"type":"Point"}
}