{
  "type": "Feature",
  "properties": {
    "addr:full":"Kortrijkseweg 78 Waregem (beveren-leie) West-Vlaanderen 8791",
    "addr:housenumber":"78",
    "addr:postcode":"8791",
    "addr:street":"Kortrijkseweg",
    "iso:country":"BE",
    "sg:address":"Kortrijkseweg 78",
    "sg:city":"Waregem (beveren-leie)",
    "sg:orig_category":"Non-Classified Establishments",
    "sg:phone":"+32 56 73 11 00",
    "sg:postcode":"8791",
    "sg:province":"West-Vlaanderen",
    "wof:name":"Byttebier A & Zn Nv",
    "wof:placetype":"venue"
},
  "geometry": {"coordinates":[3.3362491131,50.868850708],"type":"Point"}
}