{
  "type": "Feature",
  "properties": {
    "addr:full":"Rue De Beauval 31 Mons Hainaut 7034",
    "addr:housenumber":"31",
    "addr:postcode":"7034",
    "addr:street":"Rue De Beauval;Hainaut",
    "iso:country":"BE",
    "sg:address":"Rue De Beauval 31",
    "sg:city":"Mons",
    "sg:orig_category":"Cr\u00e8ches and garderies d'enfants",
    "sg:phone":"+32 65 33 98 64",
    "sg:postcode":"7034",
    "sg:province":"Hainaut",
    "wof:name":"L'ile Aux Enfants",
    "wof:placetype":"venue"
},
  "geometry": {"coordinates":[4.0086159706,50.4765396118],"type":"Point"}
}