{
  "type": "Feature",
  "properties": {
    "addr:full":"Shondstraat 23 Sint-gillis-waas Oost-Vlaanderen 9170",
    "addr:housenumber":"23",
    "addr:postcode":"9170",
    "addr:street":"Shondstraat",
    "iso:country":"BE",
    "sg:address":"Shondstraat 23",
    "sg:city":"Sint-gillis-waas",
    "sg:orig_category":"Rundveehouders Varkenskwekers",
    "sg:phone":"+32 3 766 25 53",
    "sg:postcode":"9170",
    "sg:province":"Oost-Vlaanderen",
    "wof:name":"Andre De Witte",
    "wof:placetype":"venue"
},
  "geometry": {"coordinates":[4.1115069389,51.1996421814],"type":"Point"}
}