{
  "type": "Feature",
  "properties": {
    "iso:country":"BE",
    "sg:address":"Liersebaan 156",
    "sg:city":"Lier (koningshooikt)",
    "sg:classifiers":[
        {
            "category":"Bars & Pubs",
            "type":"Food & Drink"
        }
    ],
    "sg:phone":"+32 3 482 11 12",
    "sg:postcode":"2500",
    "sg:province":"Antwerpen",
    "wof:name":"Lammeke ('t)",
    "wof:placetype":"venue"
},
  "geometry": {"coordinates":[4.5964031219,51.108921051],"type":"Point"}
}