{
  "type": "Feature",
  "properties": {
    "addr:full":"Lessensestraat 20 Geraardsbergen Oost-Vlaanderen 9500",
    "addr:housenumber":"20",
    "addr:postcode":"9500",
    "addr:street":"Lessensestraat",
    "iso:country":"BE",
    "sg:address":"Lessensestraat 20",
    "sg:city":"Geraardsbergen",
    "sg:classifiers":[
        {
            "category":"Shopping",
            "subcategory":"Clothing, Apparel, & Fashions",
            "type":"Retail Goods"
        }
    ],
    "sg:phone":"+32 54 41 06 15",
    "sg:postcode":"9500",
    "sg:province":"Oost-Vlaanderen",
    "sg:tags":[
        "lingerie",
        "sous-v\u00eatements"
    ],
    "wof:name":"Huis Bodily",
    "wof:placetype":"venue"
},
  "geometry": {"coordinates":[3.8759870529,50.7711372375],"type":"Point"}
}