{
  "type": "Feature",
  "properties": {
    "addr:full":"Hondsbergstraat 11 Herne Vlaams-Brabant 1540",
    "addr:housenumber":"11",
    "addr:postcode":"1540",
    "addr:street":"Hondsbergstraat",
    "iso:country":"BE",
    "sg:address":"Hondsbergstraat 11",
    "sg:city":"Herne",
    "sg:orig_category":"Rundveehouders Varkenskwekers",
    "sg:phone":"+32 54 56 60 43",
    "sg:postcode":"1540",
    "sg:province":"Vlaams-Brabant",
    "wof:name":"Wayteck Theophiel & Eddy",
    "wof:placetype":"venue"
},
  "geometry": {"coordinates":[4.0905342102,50.7473297119],"type":"Point"}
}