{
  "type": "Feature",
  "properties": {
    "addr:full":"Avenue Des Anciens Combattants 52 Bruxelles (evere) Bruxelles-Capitale 1140",
    "addr:housenumber":"52",
    "addr:postcode":"1140",
    "addr:street":"Avenue Des Anciens Combattants",
    "iso:country":"BE",
    "sg:address":"Avenue Des Anciens Combattants 52",
    "sg:city":"Bruxelles (evere)",
    "sg:classifiers":[
        {
            "category":"Personal",
            "subcategory":"Beauty Salon",
            "type":"Services"
        }
    ],
    "sg:phone":"+32 2 726 75 99",
    "sg:postcode":"1140",
    "sg:province":"Bruxelles-Capitale",
    "sg:tags":[
        "lady",
        "-",
        "hairdressing"
    ],
    "wof:name":"Coiffure Nanou",
    "wof:placetype":"venue"
},
  "geometry": {"coordinates":[4.4129748344,50.8609848022],"type":"Point"}
}