{
  "type": "Feature",
  "properties": {
    "iso:country":"BE",
    "sg:address":"Place Du Marais 4",
    "sg:city":"Pont-a-celles",
    "sg:orig_category":"M\u00e9decins and sp\u00e9cialistes",
    "sg:phone":"+32 71 84 62 73",
    "sg:postcode":"6230",
    "sg:province":"Hainaut",
    "wof:name":"P. Francart",
    "wof:placetype":"venue"
},
  "geometry": {"coordinates":[4.3613238335,50.5115394592],"type":"Point"}
}