{
  "type": "Feature",
  "properties": {
    "iso:country":"BE",
    "sg:address":"Zwarte-zustersstraat 16b6",
    "sg:city":"Leuven",
    "sg:orig_category":"Alimentation sp\u00e9cialis\u00e9e",
    "sg:phone":"+32 16 20 69 50",
    "sg:postcode":"3000",
    "sg:province":"Vlaams-Brabant",
    "wof:name":"Huis Biotoop",
    "wof:placetype":"venue"
},
  "geometry": {"coordinates":[4.6967968941,50.8730239868],"type":"Point"}
}