{
  "type": "Feature",
  "properties": {
    "addr:full":"Kapel Ter Bede 86 Kortrijk West-Vlaanderen 8500",
    "addr:housenumber":"86",
    "addr:postcode":"8500",
    "addr:street":"Bede",
    "iso:country":"BE",
    "sg:address":"Kapel Ter Bede 86",
    "sg:city":"Kortrijk",
    "sg:classifiers":[
        {
            "category":"Shopping",
            "subcategory":"Stationery & Office Supplies",
            "type":"Retail Goods"
        }
    ],
    "sg:postcode":"8500",
    "sg:province":"West-Vlaanderen",
    "sg:tags":[
        "partition"
    ],
    "wof:name":"Afkor Nv (dhr Van Thuyne)",
    "wof:placetype":"venue"
},
  "geometry": {"coordinates":[3.2991828918,50.823764801],"type":"Point"}
}