{
  "type": "Feature",
  "properties": {
    "addr:full":"Filips De Goedelaan 21-22 Brugge West-Vlaanderen 8000",
    "addr:postcode":"21-22;8000",
    "addr:street":"Filips De Goedelaan",
    "iso:country":"BE",
    "sg:address":"Filips De Goedelaan 21-22",
    "sg:city":"Brugge",
    "sg:classifiers":[
        {
            "category":"Professional",
            "subcategory":"Lawyer & Legal Services",
            "type":"Services"
        }
    ],
    "sg:phone":"+32 50 31 83 23",
    "sg:postcode":"8000",
    "sg:province":"West-Vlaanderen",
    "wof:name":"Huys P",
    "wof:placetype":"venue"
},
  "geometry": {"coordinates":[3.2146000862,51.215057373],"type":"Point"}
}