{
  "type": "Feature",
  "properties": {
    "addr:full":"Rue De Bruxelles 60 Enghien Hainaut 7850",
    "addr:housenumber":"60",
    "addr:postcode":"7850",
    "addr:street":"Rue De Bruxelles",
    "iso:country":"BE",
    "sg:address":"Rue De Bruxelles 60",
    "sg:city":"Enghien",
    "sg:classifiers":[
        {
            "category":"Shopping",
            "subcategory":"Jewelry",
            "type":"Retail Goods"
        }
    ],
    "sg:phone":"+32 2 395 89 49",
    "sg:postcode":"7850",
    "sg:province":"Hainaut",
    "sg:tags":[
        "jeweller",
        "-"
    ],
    "wof:name":"Floval Sprl",
    "wof:placetype":"venue"
},
  "geometry": {"coordinates":[4.0417790413,50.6947860718],"type":"Point"}
}