{
  "type": "Feature",
  "properties": {
    "addr:full":"Avenue Des Mespeliers 26 Ottignies-louvain-la-neuve Brabant Wallon 1348",
    "addr:housenumber":"26",
    "addr:postcode":"1348",
    "addr:street":"Avenue Des Mespeliers",
    "iso:country":"BE",
    "sg:address":"Avenue Des Mespeliers 26",
    "sg:city":"Ottignies-louvain-la-neuve",
    "sg:orig_category":"M\u00e9decins and sp\u00e9cialistes",
    "sg:phone":"+32 10 45 46 42",
    "sg:postcode":"1348",
    "sg:province":"Brabant Wallon",
    "wof:name":"J. Blockmans",
    "wof:placetype":"venue"
},
  "geometry": {"coordinates":[4.6166901588,50.67445755],"type":"Point"}
}