{
  "type": "Feature",
  "properties": {
    "iso:country":"BE",
    "sg:address":"Nerenweg 67",
    "sg:city":"Laarne (kalken)",
    "sg:classifiers":[
        {
            "category":"Shopping",
            "subcategory":"Clothing, Apparel, & Fashions",
            "type":"Retail Goods"
        }
    ],
    "sg:phone":"+32 9 367 53 16",
    "sg:postcode":"9270",
    "sg:province":"Oost-Vlaanderen",
    "sg:tags":[
        "lady",
        "clothing",
        "-"
    ],
    "wof:name":"Van Rijsselberghe-van Uytvanck",
    "wof:placetype":"venue"
},
  "geometry": {"coordinates":[3.8489339352,51.0294075012],"type":"Point"}
}