{
  "type": "Feature",
  "properties": {
    "addr:full":"Rue L. Couvreur 30 Saint-ghislain Hainaut 7333",
    "addr:housenumber":"30",
    "addr:postcode":"7333",
    "addr:street":"Rue L. Couvreur;Hainaut",
    "iso:country":"BE",
    "sg:address":"Rue L. Couvreur 30",
    "sg:city":"Saint-ghislain",
    "sg:orig_category":"Architectes",
    "sg:phone":"+32 65 62 02 50",
    "sg:postcode":"7333",
    "sg:province":"Hainaut",
    "wof:name":"Benoit Nis",
    "wof:placetype":"venue"
},
  "geometry": {"coordinates":[3.7818520069,50.4570960999],"type":"Point"}
}