{
  "type": "Feature",
  "properties": {
    "iso:country":"BE",
    "sg:address":"Square Du Val De La Cambre 9",
    "sg:city":"Bruxelles (ixelles)",
    "sg:classifiers":[
        {
            "category":"Health Services",
            "subcategory":"Doctor",
            "type":"Services"
        }
    ],
    "sg:phone":"+32 2 649 86 21",
    "sg:postcode":"1050",
    "sg:province":"Bruxelles-Capitale",
    "sg:tags":[
        "medicinephysicians",
        "surgeon"
    ],
    "wof:name":"Drossos A",
    "wof:placetype":"venue"
},
  "geometry": {"coordinates":[4.37748909,50.818069458],"type":"Point"}
}