{
  "type": "Feature",
  "properties": {
    "addr:full":"Kruiswegstraat 13 Heusden-zolder (heusden) Limburg 3550",
    "addr:housenumber":"13",
    "addr:postcode":"3550",
    "addr:street":"Kruiswegstraat",
    "iso:country":"BE",
    "sg:address":"Kruiswegstraat 13",
    "sg:city":"Heusden-zolder (heusden)",
    "sg:classifiers":[
        {
            "category":"Professional",
            "subcategory":"Accounting & Tax Preparation",
            "type":"Services"
        }
    ],
    "sg:phone":"+32 11 42 37 20",
    "sg:postcode":"3550",
    "sg:province":"Limburg",
    "sg:tags":[
        "accountant"
    ],
    "wof:name":"Wijnen Jan",
    "wof:placetype":"venue"
},
  "geometry": {"coordinates":[5.2894091606,51.0351257324],"type":"Point"}
}