{
  "type": "Feature",
  "properties": {
    "addr:full":"Brusselsesteenweg 98 Lebbeke Oost-Vlaanderen 9280",
    "addr:housenumber":"98",
    "addr:postcode":"9280",
    "addr:street":"Brusselsesteenweg",
    "iso:country":"BE",
    "sg:address":"Brusselsesteenweg 98",
    "sg:city":"Lebbeke",
    "sg:orig_category":"Slagers",
    "sg:phone":"+32 52 41 15 66",
    "sg:postcode":"9280",
    "sg:province":"Oost-Vlaanderen",
    "wof:name":"Batselier P & Collaert P",
    "wof:placetype":"venue"
},
  "geometry": {"coordinates":[4.1281199455,51.0000915527],"type":"Point"}
}