{
  "type": "Feature",
  "properties": {
    "addr:full":"Argentini\u00eblaan 50 Antwerpen Antwerpen 2030",
    "addr:housenumber":"50",
    "addr:postcode":"2030",
    "addr:street":"Argentinie\u0308Laan",
    "iso:country":"BE",
    "sg:address":"Argentini\u00eblaan 50",
    "sg:city":"Antwerpen",
    "sg:classifiers":[
        {
            "category":"Military Area",
            "subcategory":"Air Force Base",
            "type":"Public Place"
        }
    ],
    "sg:phone":"+32 3 218 96 00",
    "sg:postcode":"2030",
    "sg:province":"Antwerpen",
    "sg:tags":[
        "balustrade"
    ],
    "wof:name":"Arcos Bvba",
    "wof:placetype":"venue"
},
  "geometry": {"coordinates":[4.4257268906,51.2574119568],"type":"Point"}
}