{
  "type": "Feature",
  "properties": {
    "addr:full":"Rue De La Pr\u00c9voyance 56 Brussel/bruxelles Bruxelles-Capitale 1000",
    "addr:housenumber":"56",
    "addr:postcode":"1000",
    "addr:street":"Rue De La Pre\u0301Voyance;/",
    "iso:country":"BE",
    "sg:address":"Rue De La Pr\u00c9voyance 56",
    "sg:city":"Brussel/bruxelles",
    "sg:orig_category":"Organisations and associations. Activit\u00e9s d\u00b4action sociale sans h\u00e9bergement",
    "sg:phone":"+32 2 512 73 60",
    "sg:postcode":"1000",
    "sg:province":"Bruxelles-Capitale",
    "wof:name":"Foyer Montserrat",
    "wof:placetype":"venue"
},
  "geometry": {"coordinates":[4.3510198593,50.8347206116],"type":"Point"}
}