{
  "type": "Feature",
  "properties": {
    "addr:full":"Rue Du Fond Collart 10 Wavre (bierges) Brabant Wallon 1301",
    "addr:housenumber":"10;1301",
    "addr:street":"Rue Du Fond Collart",
    "iso:country":"BE",
    "sg:address":"Rue Du Fond Collart 10",
    "sg:city":"Wavre (bierges)",
    "sg:classifiers":[
        {
            "category":"Retail",
            "subcategory":"Event Space",
            "type":"Services"
        }
    ],
    "sg:phone":"+32 2 652 01 90",
    "sg:postcode":"1301",
    "sg:province":"Brabant Wallon",
    "sg:tags":[
        "rental",
        "-",
        "hall"
    ],
    "wof:name":"Matinag Sa",
    "wof:placetype":"venue"
},
  "geometry": {"coordinates":[4.5584287643,50.7304763794],"type":"Point"}
}