{
  "type": "Feature",
  "properties": {
    "addr:full":"Rue Bara 54b Charleroi (jumet) Hainaut 6040",
    "addr:housenumber":"54b",
    "addr:postcode":"6040",
    "addr:street":"Rue Bara",
    "iso:country":"BE",
    "sg:address":"Rue Bara 54b",
    "sg:city":"Charleroi (jumet)",
    "sg:orig_category":"Woodenware",
    "sg:phone":"+32 71 35 80 35",
    "sg:postcode":"6040",
    "sg:province":"Hainaut",
    "wof:name":"Oxygene+forestry",
    "wof:placetype":"venue"
},
  "geometry": {"coordinates":[4.4352269173,50.4381484985],"type":"Point"}
}