{
  "type": "Feature",
  "properties": {
    "addr:full":"Den Duine 2 Beernem West-Vlaanderen 8730",
    "addr:housenumber":"2",
    "addr:postcode":"8730",
    "addr:street":"Den Duine",
    "iso:country":"BE",
    "sg:address":"Den Duine 2",
    "sg:city":"Beernem",
    "sg:classifiers":[
        {
            "category":"Personal",
            "subcategory":"Beauty Salon",
            "type":"Services"
        }
    ],
    "sg:phone":"+32 50 78 93 62",
    "sg:postcode":"8730",
    "sg:province":"West-Vlaanderen",
    "sg:tags":[
        "de",
        "coiffure"
    ],
    "wof:name":"Coiffure Top Style",
    "wof:placetype":"venue"
},
  "geometry": {"coordinates":[3.3190159798,51.1293716431],"type":"Point"}
}