{
  "type": "Feature",
  "properties": {
    "addr:full":"De Smet De Naeyerlaan 7 Blankenberge West-Vlaanderen 8370",
    "addr:housenumber":"7",
    "addr:postcode":"8370",
    "addr:street":"De Smet De Naeyerlaan",
    "iso:country":"BE",
    "sg:address":"De Smet De Naeyerlaan 7",
    "sg:city":"Blankenberge",
    "sg:classifiers":[
        {
            "category":"Banks & Credit Unions",
            "subcategory":"Investment Brokerage",
            "type":"Services"
        }
    ],
    "sg:phone":"+32 50 42 32 20",
    "sg:postcode":"8370",
    "sg:province":"West-Vlaanderen",
    "sg:tags":[
        "-",
        "sale",
        "yachts",
        "accessory",
        "pleasure",
        "boat"
    ],
    "wof:name":"Boat Shop Spinnaker",
    "wof:placetype":"venue"
},
  "geometry": {"coordinates":[3.1216540337,51.3124160767],"type":"Point"}
}