{
  "type": "Feature",
  "properties": {
    "iso:country":"BE",
    "sg:address":"Gouden-boomstraat 28",
    "sg:city":"Brugge",
    "sg:orig_category":"Artsen and specialisten",
    "sg:phone":"+32 50 31 66 89",
    "sg:postcode":"8000",
    "sg:province":"West-Vlaanderen",
    "wof:name":"Godelieve Claus",
    "wof:placetype":"venue"
},
  "geometry": {"coordinates":[3.21220994,51.2148361206],"type":"Point"}
}