{
  "type": "Feature",
  "properties": {
    "iso:country":"BE",
    "sg:address":"Rue Germaine Dewandre 1ba",
    "sg:city":"Charleroi",
    "sg:orig_category":"Geschenken and souvenirs Verlichting and huishoudartikelen",
    "sg:phone":"+32 71 51 79 56",
    "sg:postcode":"6032",
    "sg:province":"Hainaut",
    "wof:name":"Couleur Saison",
    "wof:placetype":"venue"
},
  "geometry": {"coordinates":[4.3981909752,50.3704109192],"type":"Point"}
}