{
  "type": "Feature",
  "properties": {
    "addr:full":"Fonteinstraat 20 Hasselt Limburg 3500",
    "addr:housenumber":"20",
    "addr:postcode":"3500",
    "addr:street":"Fonteinstraat",
    "iso:country":"BE",
    "sg:address":"Fonteinstraat 20",
    "sg:city":"Hasselt",
    "sg:classifiers":[
        {
            "category":"Arena",
            "subcategory":"Sports Club",
            "type":"Entertainment"
        }
    ],
    "sg:phone":"+32 11 72 80 26",
    "sg:postcode":"3500",
    "sg:province":"Limburg",
    "sg:tags":[
        "de"
    ],
    "wof:name":"Ijshockeyclub Haskey",
    "wof:placetype":"venue"
},
  "geometry": {"coordinates":[5.3332481384,50.9254798889],"type":"Point"}
}