{
  "type": "Feature",
  "properties": {
    "iso:country":"BE",
    "sg:address":"Oudeheerweg Heide 94",
    "sg:city":"Waasmunster",
    "sg:classifiers":[
        {
            "category":"Bars & Pubs",
            "type":"Food & Drink"
        }
    ],
    "sg:phone":"+32 52 46 38 77",
    "sg:postcode":"9250",
    "sg:province":"Oost-Vlaanderen",
    "sg:tags":[
        "tavern"
    ],
    "wof:name":"Drie Linden (de)",
    "wof:placetype":"venue"
},
  "geometry": {"coordinates":[4.1071000099,51.1260108948],"type":"Point"}
}