{
  "type": "Feature",
  "properties": {
    "addr:full":"Brugstraat 2 Bilzen Limburg 3740",
    "addr:housenumber":"2",
    "addr:postcode":"3740",
    "addr:street":"Brugstraat",
    "iso:country":"BE",
    "sg:address":"Brugstraat 2",
    "sg:city":"Bilzen",
    "sg:orig_category":"Tribunaux",
    "sg:phone":"+32 89 41 14 41",
    "sg:postcode":"3740",
    "sg:province":"Limburg",
    "wof:name":"Vredegerecht",
    "wof:placetype":"venue"
},
  "geometry": {"coordinates":[5.5178380013,50.8695373535],"type":"Point"}
}