{
  "type": "Feature",
  "properties": {
    "addr:full":"Rue De La Croix 11 Paliseul (framont) Luxembourg 6853",
    "addr:housenumber":"11",
    "addr:postcode":"6853",
    "addr:street":"Rue De La Croix",
    "iso:country":"BE",
    "sg:address":"Rue De La Croix 11",
    "sg:city":"Paliseul (framont)",
    "sg:classifiers":[
        {
            "category":"Wholesale",
            "subcategory":"Machinery & Supplies",
            "type":"Manufacturing & Wholesale Goods"
        }
    ],
    "sg:phone":"+32 61 53 30 75",
    "sg:postcode":"6853",
    "sg:province":"Luxembourg",
    "sg:tags":[
        "agricultural",
        "tractor"
    ],
    "wof:name":"Arnould Agri Sprl",
    "wof:placetype":"venue"
},
  "geometry": {"coordinates":[5.1605811119,49.9196281433],"type":"Point"}
}