{
  "type": "Feature",
  "properties": {
    "addr:full":"Sint-gabrielstraat 127 Liedekerke Vlaams-Brabant 1770",
    "addr:housenumber":"127",
    "addr:postcode":"1770",
    "addr:street":"Vlaams-Brabant",
    "iso:country":"BE",
    "sg:address":"Sint-gabrielstraat 127",
    "sg:city":"Liedekerke",
    "sg:orig_category":"Rev\u00eatements de sols and murs. Rev\u00eatements pour sols and murs",
    "sg:phone":"+32 53 68 34 31",
    "sg:postcode":"1770",
    "sg:province":"Vlaams-Brabant",
    "wof:name":"Miguel Van Valckenborgh",
    "wof:placetype":"venue"
},
  "geometry": {"coordinates":[4.0878992081,50.8651657104],"type":"Point"}
}