{
  "type": "Feature",
  "properties": {
    "iso:country":"BE",
    "sg:address":"Schloss Strasse 43",
    "sg:city":"Lontzen/lontzen",
    "sg:orig_category":"Rundveehouders",
    "sg:phone":"+32 87 65 96 71",
    "sg:postcode":"4710",
    "sg:province":"Li\u00e8ge",
    "wof:name":"Lucien Hagelstein",
    "wof:placetype":"venue"
},
  "geometry": {"coordinates":[6.0110960007,50.6802711487],"type":"Point"}
}