{
  "type": "Feature",
  "properties": {
    "iso:country":"BE",
    "sg:address":"Sint-annaweg 8",
    "sg:city":"Waregem (beveren-leie)",
    "sg:classifiers":[
        {
            "category":"Parking",
            "subcategory":"Garage",
            "type":"Transportation"
        }
    ],
    "sg:phone":"+32 56 71 53 75",
    "sg:postcode":"8791",
    "sg:province":"West-Vlaanderen",
    "sg:tags":[
        "truck",
        "-",
        "dump",
        "transport"
    ],
    "wof:name":"Deleersnijder P Intervervoer Bvba",
    "wof:placetype":"venue"
},
  "geometry": {"coordinates":[3.3476150036,50.8772544861],"type":"Point"}
}