{
  "type": "Feature",
  "properties": {
    "addr:full":"De Valk 27 Mortsel Antwerpen 2640",
    "addr:housenumber":"27",
    "addr:postcode":"2640",
    "addr:street":"De Valk",
    "iso:country":"BE",
    "sg:address":"De Valk 27",
    "sg:city":"Mortsel",
    "sg:classifiers":[
        {
            "category":"Food & Beverages",
            "subcategory":"Liquor & Beverages",
            "type":"Retail Goods"
        }
    ],
    "sg:phone":"+32 3 297 84 97",
    "sg:postcode":"2640",
    "sg:province":"Antwerpen",
    "sg:tags":[
        "-",
        "spirit",
        "wine"
    ],
    "wof:name":"Terravino",
    "wof:placetype":"venue"
},
  "geometry": {"coordinates":[4.4748811722,51.1652107239],"type":"Point"}
}