{
  "type": "Feature",
  "properties": {
    "iso:country":"BE",
    "sg:address":"Phoenixstraat 81",
    "sg:city":"Gent",
    "sg:classifiers":[
        {
            "category":"Personal",
            "subcategory":"Beauty Salon",
            "type":"Services"
        }
    ],
    "sg:phone":"+32 9 226 42 45",
    "sg:postcode":"9000",
    "sg:province":"Oost-Vlaanderen",
    "sg:tags":[
        "lady",
        "-",
        "hairdressing"
    ],
    "wof:name":"Free Style",
    "wof:placetype":"venue"
},
  "geometry": {"coordinates":[3.7050790787,51.0583610535],"type":"Point"}
}