{
  "type": "Feature",
  "properties": {
    "addr:full":"Industriezone 6c Kruishoutem Oost-Vlaanderen 9770",
    "addr:housenumber":"6c",
    "addr:postcode":"9770",
    "addr:street":"Industriezone",
    "iso:country":"BE",
    "sg:address":"Industriezone 6c",
    "sg:city":"Kruishoutem",
    "sg:classifiers":[
        {
            "category":"Freight",
            "type":"Transportation"
        }
    ],
    "sg:phone":"+32 9 338 54 54",
    "sg:postcode":"9770",
    "sg:province":"Oost-Vlaanderen",
    "sg:tags":[
        "-",
        "transport"
    ],
    "wof:name":"Belspeed Nv",
    "wof:placetype":"venue"
},
  "geometry": {"coordinates":[3.4817891121,50.9088134766],"type":"Point"}
}