{
  "type": "Feature",
  "properties": {
    "addr:full":"Bld Fr\u00c8re Orban 35ba101 Li\u00c8ge Li\u00e8ge 4000",
    "addr:postcode":"4000",
    "addr:street":"Bld Fre\u0300Re Orban 35Ba101",
    "iso:country":"BE",
    "sg:address":"Bld Fr\u00c8re Orban 35ba101",
    "sg:city":"Li\u00c8ge",
    "sg:orig_category":"Beheer onroerend goed",
    "sg:phone":"+32 4 253 48 42",
    "sg:postcode":"4000",
    "sg:province":"Li\u00e8ge",
    "wof:name":"Lambermont",
    "wof:placetype":"venue"
},
  "geometry": {"coordinates":[5.5705461502,50.6304473877],"type":"Point"}
}