{
  "type": "Feature",
  "properties": {
    "addr:full":"Rue Grande 148 Grace-hollogne Li\u00e8ge 4460",
    "addr:housenumber":"148",
    "addr:postcode":"4460",
    "addr:street":"Rue Grande",
    "iso:country":"BE",
    "sg:address":"Rue Grande 148",
    "sg:city":"Grace-hollogne",
    "sg:orig_category":"Bloemen and planten",
    "sg:phone":"+32 4 234 00 78",
    "sg:postcode":"4460",
    "sg:province":"Li\u00e8ge",
    "wof:name":"Amaryllis",
    "wof:placetype":"venue"
},
  "geometry": {"coordinates":[5.4747262001,50.6382598877],"type":"Point"}
}