{
  "type": "Feature",
  "properties": {
    "addr:full":"Rue Chavez 9 Etalle Luxembourg 6741",
    "addr:housenumber":"9",
    "addr:postcode":"6741",
    "addr:street":"Rue Chavez",
    "iso:country":"BE",
    "sg:address":"Rue Chavez 9",
    "sg:city":"Etalle",
    "sg:orig_category":"Installation \u00e9lectrique r\u00e9sidentielle",
    "sg:phone":"+32 63 45 56 81",
    "sg:postcode":"6741",
    "sg:province":"Luxembourg",
    "wof:name":"G\u00c9rard Halkin",
    "wof:placetype":"venue"
},
  "geometry": {"coordinates":[5.6673212051,49.6705703735],"type":"Point"}
}