{
  "type": "Feature",
  "properties": {
    "iso:country":"BE",
    "sg:address":"Rue Marie De Bourgogne 52",
    "sg:city":"Brussel/bruxelles",
    "sg:orig_category":"S\u00e9lection de personnel and placement",
    "sg:phone":"+32 2 234 62 11",
    "sg:postcode":"1000",
    "sg:province":"Bruxelles-Capitale",
    "wof:name":"Bureau Adelphi Consulting",
    "wof:placetype":"venue"
},
  "geometry": {"coordinates":[4.3717370033,50.8413581848],"type":"Point"}
}