{
  "type": "Feature",
  "properties": {
    "addr:full":"Rue J.b. Brabant 33 Namur Namur 5000",
    "addr:housenumber":"33",
    "addr:postcode":"5000",
    "addr:street":"Rue J.B. Brabant",
    "iso:country":"BE",
    "sg:address":"Rue J.b. Brabant 33",
    "sg:city":"Namur",
    "sg:classifiers":[
        {
            "category":"Personal",
            "subcategory":"Beauty Salon",
            "type":"Services"
        }
    ],
    "sg:phone":"+32 81 22 23 35",
    "sg:postcode":"5000",
    "sg:province":"Namur",
    "sg:tags":[
        "lady",
        "-",
        "hairdressing"
    ],
    "wof:name":"Martine",
    "wof:placetype":"venue"
},
  "geometry": {"coordinates":[4.8729138374,50.4649238586],"type":"Point"}
}