{
  "type": "Feature",
  "properties": {
    "addr:full":"Place Paul Pastur 41 Anderlues Hainaut 6150",
    "addr:housenumber":"41",
    "addr:postcode":"6150",
    "addr:street":"Place Paul Pastur",
    "iso:country":"BE",
    "sg:address":"Place Paul Pastur 41",
    "sg:city":"Anderlues",
    "sg:classifiers":[
        {
            "category":"Restaurant",
            "type":"Food & Drink"
        }
    ],
    "sg:phone":"+32 71 54 50 59",
    "sg:postcode":"6150",
    "sg:province":"Hainaut",
    "sg:tags":[
        "caf\u00e9s"
    ],
    "wof:name":"Taverne La Houblonni\u00c8re",
    "wof:placetype":"venue"
},
  "geometry": {"coordinates":[4.2702422142,50.4072990417],"type":"Point"}
}