{
  "type": "Feature",
  "properties": {
    "iso:country":"BE",
    "sg:address":"Kapellestraat 25",
    "sg:city":"Meulebeke",
    "sg:orig_category":"Brood, gebak and snoepgoed",
    "sg:phone":"+32 51 48 82 48",
    "sg:postcode":"8760",
    "sg:province":"West-Vlaanderen",
    "wof:name":"Hector Van Daele",
    "wof:placetype":"venue"
},
  "geometry": {"coordinates":[3.2874701023,50.9476966858],"type":"Point"}
}