{
  "type": "Feature",
  "properties": {
    "addr:full":"Klaverbeekstraat 16 Waasmunster Oost-Vlaanderen 9250",
    "addr:housenumber":"16",
    "addr:postcode":"9250",
    "addr:street":"Klaverbeekstraat",
    "iso:country":"BE",
    "sg:address":"Klaverbeekstraat 16",
    "sg:city":"Waasmunster",
    "sg:orig_category":"Diverse bedrijfsbeheeradviesbureaus",
    "sg:phone":"+32 9 348 96 83",
    "sg:postcode":"9250",
    "sg:province":"Oost-Vlaanderen",
    "wof:name":"Fimac/g-mac Management Consultants",
    "wof:placetype":"venue"
},
  "geometry": {"coordinates":[4.0333762169,51.1260910034],"type":"Point"}
}