{
  "type": "Feature",
  "properties": {
    "iso:country":"BE",
    "sg:address":"Rue Hubert Halet",
    "sg:city":"Pepinster",
    "sg:classifiers":[
        {
            "category":"Shopping",
            "subcategory":"Antiques",
            "type":"Retail Goods"
        }
    ],
    "sg:phone":"+32 87 46 90 90",
    "sg:postcode":"4860",
    "sg:province":"Li\u00e8ge",
    "wof:name":"Keutiens",
    "wof:placetype":"venue"
},
  "geometry": {"coordinates":[5.8068499565,50.5698509216],"type":"Point"}
}