{
  "type": "Feature",
  "properties": {
    "addr:full":"Rue Saumont 31 Marche-en-famenne (aye) Luxembourg 6900",
    "addr:housenumber":"31",
    "addr:postcode":"6900",
    "addr:street":"Rue Saumont",
    "iso:country":"BE",
    "sg:address":"Rue Saumont 31",
    "sg:city":"Marche-en-famenne (aye)",
    "sg:classifiers":[
        {
            "category":"Building & Trades",
            "subcategory":"Construction",
            "type":"Services"
        }
    ],
    "sg:phone":"+32 84 31 39 23",
    "sg:postcode":"6900",
    "sg:province":"Luxembourg",
    "sg:tags":[
        "carpenter"
    ],
    "wof:name":"Maillen M",
    "wof:placetype":"venue"
},
  "geometry": {"coordinates":[5.3004498482,50.2316818237],"type":"Point"}
}