{
  "type": "Feature",
  "properties": {
    "addr:full":"Stoofstraat 27 Brussel/bruxelles Bruxelles-Capitale 1000",
    "addr:housenumber":"27",
    "addr:postcode":"1000",
    "addr:street":"Stoofstraat;/",
    "iso:country":"BE",
    "sg:address":"Stoofstraat 27",
    "sg:city":"Brussel/bruxelles",
    "sg:classifiers":[
        {
            "category":"Shopping",
            "subcategory":"Gifts & Souvenirs",
            "type":"Retail Goods"
        }
    ],
    "sg:phone":"+32 2 511 98 49",
    "sg:postcode":"1000",
    "sg:province":"Bruxelles-Capitale",
    "sg:tags":[
        "geschenken"
    ],
    "wof:name":"The Brussels Corner",
    "wof:placetype":"venue"
},
  "geometry": {"coordinates":[4.3505558968,50.8455543518],"type":"Point"}
}