{
  "type": "Feature",
  "properties": {
    "iso:country":"BE",
    "sg:address":"Rue Des Hirondelles 12",
    "sg:city":"Thuin",
    "sg:classifiers":[
        {
            "category":"Insurance",
            "subcategory":"Life Insurance",
            "type":"Services"
        }
    ],
    "sg:phone":"+32 71 51 08 74",
    "sg:postcode":"6534",
    "sg:province":"Hainaut",
    "sg:tags":[
        "assurance"
    ],
    "wof:name":"Pay Consult",
    "wof:placetype":"venue"
},
  "geometry": {"coordinates":[4.3721327782,50.3556861877],"type":"Point"}
}