{
  "type": "Feature",
  "properties": {
    "iso:country":"BE",
    "sg:address":"Rue De Soleilmont 67",
    "sg:city":"Charleroi (ransart)",
    "sg:classifiers":[
        {
            "category":"Wholesale",
            "subcategory":"Construction Materials",
            "type":"Manufacturing & Wholesale Goods"
        }
    ],
    "sg:phone":"+32 71 39 59 12",
    "sg:postcode":"6043",
    "sg:province":"Hainaut",
    "sg:tags":[
        "tubing",
        "industrial"
    ],
    "wof:name":"B.e.c.m. Sprl",
    "wof:placetype":"venue"
},
  "geometry": {"coordinates":[4.4839549065,50.4479637146],"type":"Point"}
}