{
  "type": "Feature",
  "properties": {
    "iso:country":"BE",
    "sg:address":"Vismijn-pakhuis 44",
    "sg:city":"Oostende",
    "sg:classifiers":[
        {
            "category":"Shopping Center",
            "type":"Public Place"
        }
    ],
    "sg:phone":"+32 59 33 02 75",
    "sg:postcode":"8400",
    "sg:province":"West-Vlaanderen",
    "sg:tags":[
        "enseignement",
        "formation"
    ],
    "wof:name":"Vdab Training En Opleiding",
    "wof:placetype":"venue"
},
  "geometry": {"coordinates":[2.9126999378,51.2312583923],"type":"Point"}
}