{
  "type": "Feature",
  "properties": {
    "iso:country":"BE",
    "sg:address":"Rue Au Bois 24",
    "sg:city":"Drogenbos",
    "sg:classifiers":[
        {
            "category":"Utilities",
            "subcategory":"Water",
            "type":"Services"
        }
    ],
    "sg:phone":"+32 2 331 26 18",
    "sg:postcode":"1620",
    "sg:province":"Vlaams-Brabant",
    "sg:tags":[
        "softener"
    ],
    "wof:name":"Aqua-clean",
    "wof:placetype":"venue"
},
  "geometry": {"coordinates":[4.3208851814,50.7821960449],"type":"Point"}
}