{
  "type": "Feature",
  "properties": {
    "iso:country":"BE",
    "sg:address":"Eikestraat 18",
    "sg:city":"Herent (winksele)",
    "sg:classifiers":[
        {
            "category":"Food & Beverages",
            "subcategory":"Specialty",
            "type":"Retail Goods"
        }
    ],
    "sg:phone":"+32 16 60 25 77",
    "sg:postcode":"3020",
    "sg:province":"Vlaams-Brabant",
    "sg:tags":[
        "health",
        "dietary",
        "-",
        "biological"
    ],
    "wof:name":"Vandereet I",
    "wof:placetype":"venue"
},
  "geometry": {"coordinates":[4.6749200821,50.9079055786],"type":"Point"}
}