{
  "type": "Feature",
  "properties": {
    "addr:full":"Lijsterstraat 25 Kortrijk West-Vlaanderen 8511",
    "addr:housenumber":"25",
    "addr:postcode":"8511",
    "addr:street":"Lijsterstraat",
    "iso:country":"BE",
    "sg:address":"Lijsterstraat 25",
    "sg:city":"Kortrijk",
    "sg:classifiers":[
        {
            "category":"Personal",
            "subcategory":"Beauty Salon",
            "type":"Services"
        }
    ],
    "sg:phone":"+32 56 41 43 18",
    "sg:postcode":"8511",
    "sg:province":"West-Vlaanderen",
    "sg:tags":[
        "de",
        "coiffure"
    ],
    "wof:name":"C Verstichel",
    "wof:placetype":"venue"
},
  "geometry": {"coordinates":[3.2310700417,50.7805900574],"type":"Point"}
}