{
  "type": "Feature",
  "properties": {
    "iso:country":"BE",
    "sg:address":"Dieupart 41",
    "sg:city":"Aywaille (sougn\u00e9-remouchamps)",
    "sg:classifiers":[
        {
            "category":"Autos & Motor Vehicles",
            "subcategory":"Recreational Vehicle Sales",
            "type":"Retail Goods"
        }
    ],
    "sg:phone":"+32 4 384 41 41",
    "sg:postcode":"4920",
    "sg:province":"Li\u00e8ge",
    "sg:tags":[
        "saw"
    ],
    "wof:name":"Husqvarna Leloup Aywaille",
    "wof:placetype":"venue"
},
  "geometry": {"coordinates":[5.6915960312,50.4767913818],"type":"Point"}
}