{
  "type": "Feature",
  "properties": {
    "addr:full":"Roeveld 30 Denderleeuw (welle) Oost-Vlaanderen 9473",
    "addr:housenumber":"30",
    "addr:postcode":"9473",
    "addr:street":"Roeveld",
    "iso:country":"BE",
    "sg:address":"Roeveld 30",
    "sg:city":"Denderleeuw (welle)",
    "sg:classifiers":[
        {
            "category":"Freight",
            "type":"Transportation"
        }
    ],
    "sg:phone":"+32 53 68 17 12",
    "sg:postcode":"9473",
    "sg:province":"Oost-Vlaanderen",
    "sg:tags":[
        "-",
        "transport"
    ],
    "wof:name":"Rubbrecht M",
    "wof:placetype":"venue"
},
  "geometry": {"coordinates":[4.0544710159,50.9011611938],"type":"Point"}
}