{
  "type": "Feature",
  "properties": {
    "iso:country":"BE",
    "sg:address":"Rue Emile Masset 72",
    "sg:city":"Perwez",
    "sg:orig_category":"Experts-comptables",
    "sg:phone":"+32 10 88 92 81",
    "sg:postcode":"1360",
    "sg:province":"Brabant Wallon",
    "wof:name":"Andr\u00c9 Gourdin",
    "wof:placetype":"venue"
},
  "geometry": {"coordinates":[4.828663826,50.6668701172],"type":"Point"}
}