{
  "type": "Feature",
  "properties": {
    "addr:full":"Woubrechtstraat 18 Herzele Oost-Vlaanderen 9550",
    "addr:housenumber":"18",
    "addr:postcode":"9550",
    "addr:street":"Woubrechtstraat;Oost-Vlaanderen",
    "iso:country":"BE",
    "sg:address":"Woubrechtstraat 18",
    "sg:city":"Herzele",
    "sg:orig_category":"Charpentes and couvertures. Installation de menuiserie en bois and plastique",
    "sg:phone":"+32 53 62 32 98",
    "sg:postcode":"9550",
    "sg:province":"Oost-Vlaanderen",
    "wof:name":"De Pauw",
    "wof:placetype":"venue"
},
  "geometry": {"coordinates":[3.917124033,50.8717460632],"type":"Point"}
}