{
  "type": "Feature",
  "properties": {
    "addr:full":"Constant Permekelaan 4 Jabbeke West-Vlaanderen 8490",
    "addr:housenumber":"4",
    "addr:postcode":"8490",
    "addr:street":"Constant Permekelaan",
    "iso:country":"BE",
    "sg:address":"Constant Permekelaan 4",
    "sg:city":"Jabbeke",
    "sg:orig_category":"Openbare veiligheid",
    "sg:phone":"+32 50 81 35 07",
    "sg:postcode":"8490",
    "sg:province":"West-Vlaanderen",
    "wof:name":"Federale Politie/police F\u00c9d\u00c9rale",
    "wof:placetype":"venue"
},
  "geometry": {"coordinates":[3.0954360962,51.1827468872],"type":"Point"}
}