{
  "type": "Feature",
  "properties": {
    "addr:full":"Bredabaan 478 Wuustwezel Antwerpen 2990",
    "addr:housenumber":"478",
    "addr:postcode":"2990",
    "addr:street":"Bredabaan",
    "iso:country":"BE",
    "sg:address":"Bredabaan 478",
    "sg:city":"Wuustwezel",
    "sg:classifiers":[
        {
            "category":"Fast Food",
            "type":"Food & Drink"
        }
    ],
    "sg:phone":"+32 3 669 74 72",
    "sg:postcode":"2990",
    "sg:province":"Antwerpen",
    "sg:tags":[
        "\u00c0",
        "emporter",
        "restaurants"
    ],
    "wof:name":"Frituur Jos\u00c9",
    "wof:placetype":"venue"
},
  "geometry": {"coordinates":[4.5910291672,51.389793396],"type":"Point"}
}