{
  "type": "Feature",
  "properties": {
    "addr:full":"Place Du Chapitre 12 Fosses-la-ville Namur 5070",
    "addr:housenumber":"12",
    "addr:postcode":"5070",
    "addr:street":"Place Du Chapitre",
    "iso:country":"BE",
    "sg:address":"Place Du Chapitre 12",
    "sg:city":"Fosses-la-ville",
    "sg:classifiers":[
        {
            "category":"Insurance",
            "subcategory":"Insurance Agent",
            "type":"Services"
        }
    ],
    "sg:phone":"+32 71 71 21 19",
    "sg:postcode":"5070",
    "sg:province":"Namur",
    "sg:tags":[
        "broker"
    ],
    "wof:name":"Assurances & Services Sc",
    "wof:placetype":"venue"
},
  "geometry": {"coordinates":[4.6976008415,50.3962631226],"type":"Point"}
}