{
  "type": "Feature",
  "properties": {
    "iso:country":"BE",
    "sg:address":"Rue Natalis 54-56",
    "sg:city":"Li\u00e8ge 1 (li\u00e8ge 2)",
    "sg:classifiers":[
        {
            "category":"Manufacturing",
            "subcategory":"Motor Vehicles & Parts",
            "type":"Manufacturing & Wholesale Goods"
        }
    ],
    "sg:phone":"+32 4 342 43 40",
    "sg:postcode":"4020",
    "sg:province":"Li\u00e8ge",
    "sg:tags":[
        "engine",
        "gasoline",
        "-"
    ],
    "wof:name":"Nadin Moteurs Sc",
    "wof:placetype":"venue"
},
  "geometry": {"coordinates":[5.5818600655,50.630027771],"type":"Point"}
}