{
  "type": "Feature",
  "properties": {
    "addr:full":"Rue G\u00e9n\u00e9ral Fiv\u00e9 9b Bruxelles (etterbeek) Bruxelles-Capitale 1040",
    "addr:housenumber":"9b",
    "addr:postcode":"1040",
    "addr:street":"Rue Ge\u0301Ne\u0301Ral Five\u0301",
    "iso:country":"BE",
    "sg:address":"Rue G\u00e9n\u00e9ral Fiv\u00e9 9b",
    "sg:city":"Bruxelles (etterbeek)",
    "sg:classifiers":[
        {
            "category":"Shopping",
            "subcategory":"Pets & Pet Supplies",
            "type":"Retail Goods"
        }
    ],
    "sg:phone":"+32 2 649 30 10",
    "sg:postcode":"1040",
    "sg:province":"Bruxelles-Capitale",
    "sg:tags":[
        "equipment",
        "plumber",
        "-"
    ],
    "wof:name":"Orzechowski",
    "wof:placetype":"venue"
},
  "geometry": {"coordinates":[4.3938651085,50.8287200928],"type":"Point"}
}