{
  "type": "Feature",
  "properties": {
    "addr:full":"Pontstraat 30 Box 7 Aalst Oost-Vlaanderen 9300",
    "addr:housenumber":"30;7",
    "addr:postcode":"9300",
    "addr:street":"Pontstraat;Box",
    "iso:country":"BE",
    "sg:address":"Pontstraat 30 Box 7",
    "sg:city":"Aalst",
    "sg:classifiers":[
        {
            "category":"Health Services",
            "subcategory":"Dentist",
            "type":"Services"
        }
    ],
    "sg:phone":"+32 53 21 60 43",
    "sg:postcode":"9300",
    "sg:province":"Oost-Vlaanderen",
    "wof:name":"Soete R",
    "wof:placetype":"venue"
},
  "geometry": {"coordinates":[4.0426502228,50.9364395142],"type":"Point"}
}