{
  "type": "Feature",
  "properties": {
    "addr:full":"Boulevard Lambermont Brussel/bruxelles Bruxelles-Capitale 1030",
    "addr:postcode":"1030",
    "addr:street":"Boulevard Lambermont",
    "iso:country":"BE",
    "sg:address":"Boulevard Lambermont",
    "sg:city":"Brussel/bruxelles",
    "sg:orig_category":"Dierenartsen",
    "sg:phone":"+32 2 216 40 09",
    "sg:postcode":"1030",
    "sg:province":"Bruxelles-Capitale",
    "wof:name":"Thierry Coulon",
    "wof:placetype":"venue"
},
  "geometry": {"coordinates":[4.3816390038,50.8708763123],"type":"Point"}
}