{
  "type": "Feature",
  "properties": {
    "addr:full":"Stationstraat 14 A Meise Vlaams-Brabant 1861",
    "addr:housenumber":"14 a",
    "addr:postcode":"1861",
    "addr:street":"Stationstraat",
    "iso:country":"BE",
    "sg:address":"Stationstraat 14 A",
    "sg:city":"Meise",
    "sg:orig_category":"Sportterreinen and installaties behalve sportcentra",
    "sg:phone":"+32 2 270 13 01",
    "sg:postcode":"1861",
    "sg:province":"Vlaams-Brabant",
    "wof:name":"Sport Point Bowling",
    "wof:placetype":"venue"
},
  "geometry": {"coordinates":[4.3104391098,50.949760437],"type":"Point"}
}