{
  "type": "Feature",
  "properties": {
    "addr:full":"Rue Du Village 48 Lontzen/lontzen Li\u00e8ge 4711",
    "addr:housenumber":"48",
    "addr:postcode":"4711",
    "addr:street":"Rue Du Village",
    "iso:country":"BE",
    "sg:address":"Rue Du Village 48",
    "sg:city":"Lontzen/lontzen",
    "sg:orig_category":"Eleveurs de bovins",
    "sg:phone":"+32 87 65 77 46",
    "sg:postcode":"4711",
    "sg:province":"Li\u00e8ge",
    "wof:name":"Elisabeth Jonas",
    "wof:placetype":"venue"
},
  "geometry": {"coordinates":[6.047369957,50.6752853394],"type":"Point"}
}