{
  "type": "Feature",
  "properties": {
    "iso:country":"BE",
    "sg:address":"Pottershoek 6",
    "sg:city":"Wachtebeke",
    "sg:classifiers":[
        {
            "category":"Health Services",
            "subcategory":"Health Practitioner",
            "type":"Services"
        }
    ],
    "sg:phone":"+32 9 342 95 60",
    "sg:postcode":"9185",
    "sg:province":"Oost-Vlaanderen",
    "sg:tags":[
        "physiotherapist"
    ],
    "wof:name":"Buysse Cynthia",
    "wof:placetype":"venue"
},
  "geometry": {"coordinates":[3.8517019749,51.1647224426],"type":"Point"}
}