{
  "type": "Feature",
  "properties": {
    "iso:country":"BE",
    "sg:address":"Zavelstraat 27",
    "sg:city":"Boutersem",
    "sg:orig_category":"G\u00e9om\u00e8tres",
    "sg:phone":"+32 16 73 54 28",
    "sg:postcode":"3370",
    "sg:province":"Vlaams-Brabant",
    "wof:name":"Giovanni Cauwenberghs",
    "wof:placetype":"venue"
},
  "geometry": {"coordinates":[4.8667759895,50.830745697],"type":"Point"}
}