{
  "type": "Feature",
  "properties": {
    "iso:country":"BE",
    "sg:address":"Eversestraat 56",
    "sg:city":"Zaventem",
    "sg:orig_category":"Artsen and specialisten",
    "sg:phone":"+32 2 720 04 94",
    "sg:postcode":"1932",
    "sg:province":"Vlaams-Brabant",
    "wof:name":"Michel De Volder",
    "wof:placetype":"venue"
},
  "geometry": {"coordinates":[4.4420228004,50.8671226501],"type":"Point"}
}