{
  "type": "Feature",
  "properties": {
    "addr:full":"Statiestraat 118bb Zulte Oost-Vlaanderen 9870",
    "addr:housenumber":"118bb",
    "addr:postcode":"9870",
    "addr:street":"Statiestraat",
    "iso:country":"BE",
    "sg:address":"Statiestraat 118bb",
    "sg:city":"Zulte",
    "sg:orig_category":"Fabrication and montage de mobilier",
    "sg:phone":"+32 9 388 97 84",
    "sg:postcode":"9870",
    "sg:province":"Oost-Vlaanderen",
    "wof:name":"Classanic",
    "wof:placetype":"venue"
},
  "geometry": {"coordinates":[3.4471449852,50.9150733948],"type":"Point"}
}