{
  "type": "Feature",
  "properties": {
    "iso:country":"BE",
    "sg:address":"Ambachtsweg 6",
    "sg:city":"Merelbeke",
    "sg:orig_category":"Plomberie, chauffage and installations sanitaires",
    "sg:phone":"+32 9 252 63 85",
    "sg:postcode":"9820",
    "sg:province":"Oost-Vlaanderen",
    "wof:name":"De Boevere Marcel & Zoon",
    "wof:placetype":"venue"
},
  "geometry": {"coordinates":[3.7652170658,50.9937934875],"type":"Point"}
}