{
  "type": "Feature",
  "properties": {
    "iso:country":"BE",
    "sg:address":"Avenue Du Diamant 103b19",
    "sg:city":"Schaarbeek/schaerbeek",
    "sg:orig_category":"M\u00e9decins and sp\u00e9cialistes",
    "sg:phone":"+32 2 736 12 39",
    "sg:postcode":"1030",
    "sg:province":"Bruxelles-Capitale",
    "wof:name":"G\u00c9rard Stibbe",
    "wof:placetype":"venue"
},
  "geometry": {"coordinates":[4.39564991,50.8510665894],"type":"Point"}
}