{
  "type": "Feature",
  "properties": {
    "addr:full":"Avenue De Charmes 8 Bertrix Luxembourg 6880",
    "addr:housenumber":"8",
    "addr:postcode":"6880",
    "addr:street":"Avenue De Charmes",
    "iso:country":"BE",
    "sg:address":"Avenue De Charmes 8",
    "sg:city":"Bertrix",
    "sg:orig_category":"Artsen and specialisten",
    "sg:phone":"+32 61 41 18 11",
    "sg:postcode":"6880",
    "sg:province":"Luxembourg",
    "wof:name":"Armand Colson",
    "wof:placetype":"venue"
},
  "geometry": {"coordinates":[5.2529239655,49.859172821],"type":"Point"}
}