{
  "type": "Feature",
  "properties": {
    "addr:full":"Rue Du Redeau 70 Yvoir Namur 5530",
    "addr:housenumber":"70",
    "addr:postcode":"5530",
    "addr:street":"Rue Du Redeau",
    "iso:country":"BE",
    "sg:address":"Rue Du Redeau 70",
    "sg:city":"Yvoir",
    "sg:orig_category":"Instituts pour enfants en difficult\u00e9. Action sociale avec h\u00e9bergement. Orphelinats",
    "sg:phone":"+32 82 61 12 29",
    "sg:postcode":"5530",
    "sg:province":"Namur",
    "wof:name":"I.n.d.l.",
    "wof:placetype":"venue"
},
  "geometry": {"coordinates":[4.9051508904,50.3371086121],"type":"Point"}
}