{
  "type": "Feature",
  "properties": {
    "iso:country":"BE",
    "sg:address":"Chauss\u00c9e De Louvain 31",
    "sg:city":"Eghezee",
    "sg:classifiers":[
        {
            "category":"Recreation",
            "subcategory":"Theme Park",
            "type":"Entertainment"
        }
    ],
    "sg:phone":"+32 81 81 32 81",
    "sg:postcode":"5310",
    "sg:province":"Namur",
    "sg:tags":[
        "paris",
        "disneyland"
    ],
    "wof:name":"Flash Travel",
    "wof:placetype":"venue"
},
  "geometry": {"coordinates":[4.9095129967,50.5941505432],"type":"Point"}
}