{
  "type": "Feature",
  "properties": {
    "iso:country":"BE",
    "sg:address":"Chauss\u00e9e De Louvain 183",
    "sg:city":"Waterloo",
    "sg:classifiers":[
        {
            "category":"Real Estate",
            "subcategory":"Real Estate Services",
            "type":"Services"
        }
    ],
    "sg:phone":"+32 2 385 20 75",
    "sg:postcode":"1410",
    "sg:province":"Brabant Wallon",
    "sg:tags":[
        "-",
        "abroad"
    ],
    "wof:name":"Best For You (the) Sprl",
    "wof:placetype":"venue"
},
  "geometry": {"coordinates":[4.4192972183,50.6957893372],"type":"Point"}
}