{
  "type": "Feature",
  "properties": {
    "iso:country":"BE",
    "sg:address":"Zwarteweg 7",
    "sg:city":"Gistel",
    "sg:orig_category":"Eleveurs de bovins",
    "sg:phone":"+32 59 27 99 21",
    "sg:postcode":"8470",
    "sg:province":"West-Vlaanderen",
    "wof:name":"Eddy Passchyn",
    "wof:placetype":"venue"
},
  "geometry": {"coordinates":[2.9299299717,51.1582870483],"type":"Point"}
}