{
  "type": "Feature",
  "properties": {
    "iso:country":"BE",
    "sg:address":"Torhoutsestraat 190",
    "sg:city":"Oostkamp (ruddervoorde)",
    "sg:orig_category":"Non-Classified Establishments",
    "sg:phone":"+32 50 27 63 44",
    "sg:postcode":"8020",
    "sg:province":"West-Vlaanderen",
    "wof:name":"Rumix Voeders Bvba",
    "wof:placetype":"venue"
},
  "geometry": {"coordinates":[3.1920759678,51.0849266052],"type":"Point"}
}