{
  "type": "Feature",
  "properties": {
    "addr:full":"Rue De Herve 220 Li\u00e8ge 1 (grivegn\u00e9e) Li\u00e8ge 4030",
    "addr:housenumber":"220;1",
    "addr:postcode":"4030",
    "addr:street":"Rue De Herve",
    "iso:country":"BE",
    "sg:address":"Rue De Herve 220",
    "sg:city":"Li\u00e8ge 1 (grivegn\u00e9e)",
    "sg:classifiers":[
        {
            "category":"Shopping",
            "subcategory":"Bicycles & Sporting Goods",
            "type":"Retail Goods"
        }
    ],
    "sg:phone":"+32 4 367 08 47",
    "sg:postcode":"4030",
    "sg:province":"Li\u00e8ge",
    "sg:tags":[
        "tyre"
    ],
    "wof:name":"Massin Pneus",
    "wof:placetype":"venue"
},
  "geometry": {"coordinates":[5.6210517883,50.6290893555],"type":"Point"}
}