{
  "type": "Feature",
  "properties": {
    "addr:full":"Iepersestraat 52 Moorslede West-Vlaanderen 8890",
    "addr:housenumber":"52",
    "addr:postcode":"8890",
    "addr:street":"Iepersestraat",
    "iso:country":"BE",
    "sg:address":"Iepersestraat 52",
    "sg:city":"Moorslede",
    "sg:orig_category":"Voertuigen",
    "sg:phone":"+32 51 77 01 97",
    "sg:postcode":"8890",
    "sg:province":"West-Vlaanderen",
    "wof:name":"Marc Decorte",
    "wof:placetype":"venue"
},
  "geometry": {"coordinates":[3.0503599644,50.8855323792],"type":"Point"}
}