{
  "type": "Feature",
  "properties": {
    "addr:full":"Paddevijverstraat 69 Ieper West-Vlaanderen 8900",
    "addr:housenumber":"69",
    "addr:postcode":"8900",
    "addr:street":"Paddevijverstraat",
    "iso:country":"BE",
    "sg:address":"Paddevijverstraat 69",
    "sg:city":"Ieper",
    "sg:classifiers":[
        {
            "category":"Building & Trades",
            "subcategory":"Pest Control",
            "type":"Services"
        }
    ],
    "sg:phone":"+32 57 21 82 50",
    "sg:postcode":"8900",
    "sg:province":"West-Vlaanderen",
    "sg:tags":[
        "painting",
        "contractor"
    ],
    "wof:name":"Cherchye Bvba",
    "wof:placetype":"venue"
},
  "geometry": {"coordinates":[2.8849298954,50.8655891418],"type":"Point"}
}