{
  "type": "Feature",
  "properties": {
    "addr:full":"Rootenstraat 8 Genk Limburg 3600",
    "addr:housenumber":"8",
    "addr:postcode":"3600",
    "addr:street":"Rootenstraat",
    "iso:country":"BE",
    "sg:address":"Rootenstraat 8",
    "sg:city":"Genk",
    "sg:orig_category":"V\u00eatements pour b\u00e9b\u00e9s and enfants. V\u00eatements pour Hommes",
    "sg:phone":"+32 89 35 68 84",
    "sg:postcode":"3600",
    "sg:province":"Limburg",
    "wof:name":"We Men",
    "wof:placetype":"venue"
},
  "geometry": {"coordinates":[5.5032610893,50.9652328491],"type":"Point"}
}