{
  "type": "Feature",
  "properties": {
    "addr:full":"Herentalsebaan 170-172 Wommelgem Antwerpen 2160",
    "addr:housenumber":"170-172",
    "addr:postcode":"2160",
    "addr:street":"Herentalsebaan",
    "iso:country":"BE",
    "sg:address":"Herentalsebaan 170-172",
    "sg:city":"Wommelgem",
    "sg:classifiers":[
        {
            "category":"Home & Garden",
            "subcategory":"Household Appliances",
            "type":"Retail Goods"
        }
    ],
    "sg:phone":"+32 3 366 16 62",
    "sg:postcode":"2160",
    "sg:province":"Antwerpen",
    "sg:tags":[
        "repair",
        "mainten",
        "-",
        "electric"
    ],
    "wof:name":"Handyshop-de Geyter",
    "wof:placetype":"venue"
},
  "geometry": {"coordinates":[4.5027999878,51.1958312988],"type":"Point"}
}