{
  "type": "Feature",
  "properties": {
    "addr:full":"Brussegemkerkstr 18 Merchtem (groot) Vlaams-Brabant 1785",
    "addr:housenumber":"18",
    "addr:postcode":"1785",
    "addr:street":"Brussegemkerkstr;Groot Vlaams-Brabant",
    "iso:country":"BE",
    "sg:address":"Brussegemkerkstr 18",
    "sg:city":"Merchtem (groot)",
    "sg:classifiers":[
        {
            "category":"Personal",
            "subcategory":"Beauty Salon",
            "type":"Services"
        }
    ],
    "sg:phone":"+32 2 460 11 92",
    "sg:postcode":"1785",
    "sg:province":"Vlaams-Brabant",
    "sg:tags":[
        "de",
        "coiffure"
    ],
    "wof:name":"Simon",
    "wof:placetype":"venue"
},
  "geometry": {"coordinates":[4.2317490578,50.9585723877],"type":"Point"}
}