{
  "type": "Feature",
  "properties": {
    "addr:full":"Augustijnenstraat 25 Oud-turnhout Antwerpen 2360",
    "addr:housenumber":"25",
    "addr:postcode":"2360",
    "addr:street":"Augustijnenstraat",
    "iso:country":"BE",
    "sg:address":"Augustijnenstraat 25",
    "sg:city":"Oud-turnhout",
    "sg:classifiers":[
        {
            "category":"Professional",
            "subcategory":"Art Services",
            "type":"Services"
        }
    ],
    "sg:phone":"+32 14 45 30 18",
    "sg:postcode":"2360",
    "sg:province":"Antwerpen",
    "sg:tags":[
        "-",
        "painter",
        "artist"
    ],
    "wof:name":"Waterschoot A",
    "wof:placetype":"venue"
},
  "geometry": {"coordinates":[4.9933729172,51.3104743958],"type":"Point"}
}