{
  "type": "Feature",
  "properties": {
    "addr:full":"Rue Des Pr\u00c9s-fleuris 22 Couvin Namur 5660",
    "addr:housenumber":"22",
    "addr:postcode":"5660",
    "addr:street":"Rue Des Pre\u0301S-Fleuris",
    "iso:country":"BE",
    "sg:address":"Rue Des Pr\u00c9s-fleuris 22",
    "sg:city":"Couvin",
    "sg:orig_category":"Meubelzaken, woning- and keukeninrichting",
    "sg:phone":"+32 60 34 57 53",
    "sg:postcode":"5660",
    "sg:province":"Namur",
    "wof:name":"Jacqueline Belleflamme",
    "wof:placetype":"venue"
},
  "geometry": {"coordinates":[4.4800310135,50.0547904968],"type":"Point"}
}