{
  "type": "Feature",
  "properties": {
    "addr:full":"Chauss\u00e9e D'arlon 64 Bastogne Luxembourg 6600",
    "addr:housenumber":"64",
    "addr:postcode":"6600",
    "addr:street":"Chausse\u0301E D'Arlon",
    "iso:country":"BE",
    "sg:address":"Chauss\u00e9e D'arlon 64",
    "sg:city":"Bastogne",
    "sg:classifiers":[
        {
            "category":"Shopping",
            "subcategory":"Crafts & Fabrics",
            "type":"Retail Goods"
        }
    ],
    "sg:postcode":"6600",
    "sg:province":"Luxembourg",
    "sg:tags":[
        "hi-fi",
        "equipment",
        "stereophonic",
        "-"
    ],
    "wof:name":"Avs",
    "wof:placetype":"venue"
},
  "geometry": {"coordinates":[5.7213559151,49.9917755127],"type":"Point"}
}