{
  "type": "Feature",
  "properties": {
    "iso:country":"BE",
    "sg:address":"Brugsesteenweg 179",
    "sg:city":"Kuurne",
    "sg:classifiers":[
        {
            "category":"Cafe",
            "type":"Food & Drink"
        }
    ],
    "sg:phone":"+32 56 37 33 93",
    "sg:postcode":"8520",
    "sg:province":"West-Vlaanderen",
    "sg:tags":[
        "caf\u00e9s"
    ],
    "wof:name":"Nicole Eggermont",
    "wof:placetype":"venue"
},
  "geometry": {"coordinates":[3.2700529099,50.8562507629],"type":"Point"}
}