{
  "type": "Feature",
  "properties": {
    "iso:country":"BE",
    "sg:address":"Boulevard Poincar\u00c9 32b33",
    "sg:city":"Anderlecht/anderlecht",
    "sg:orig_category":"Entretien and r\u00e9parations de voitures. V\u00e9hicules automobiles",
    "sg:phone":"+32 2 522 04 01",
    "sg:postcode":"1070",
    "sg:province":"Bruxelles-Capitale",
    "wof:name":"Garage Otto & Fils",
    "wof:placetype":"venue"
},
  "geometry": {"coordinates":[4.3386969566,50.8440933228],"type":"Point"}
}