{
  "type": "Feature",
  "properties": {
    "iso:country":"BE",
    "sg:address":"Casselstraat 55",
    "sg:city":"Poperinge",
    "sg:classifiers":[
        {
            "category":"Retail",
            "subcategory":"Event Space",
            "type":"Services"
        }
    ],
    "sg:phone":"+32 57 33 30 76",
    "sg:postcode":"8970",
    "sg:province":"West-Vlaanderen",
    "sg:tags":[
        "rental",
        "-",
        "hall"
    ],
    "wof:name":"Hof Van Commerce",
    "wof:placetype":"venue"
},
  "geometry": {"coordinates":[2.7210509777,50.8524398804],"type":"Point"}
}