{
  "type": "Feature",
  "properties": {
    "iso:country":"BE",
    "sg:address":"Kievitstraat 57",
    "sg:city":"Neerpelt",
    "sg:classifiers":[
        {
            "category":"Building & Trades",
            "subcategory":"Construction",
            "type":"Services"
        }
    ],
    "sg:phone":"+32 11 64 15 09",
    "sg:postcode":"3910",
    "sg:province":"Limburg",
    "sg:tags":[
        "carpenter"
    ],
    "wof:name":"Boonen M",
    "wof:placetype":"venue"
},
  "geometry": {"coordinates":[5.4464879036,51.2271652222],"type":"Point"}
}