{
  "type": "Feature",
  "properties": {
    "iso:country":"BE",
    "sg:address":"Kapucijnenvoer 133",
    "sg:city":"Leuven",
    "sg:classifiers":[
        {
            "category":"Food & Beverages",
            "subcategory":"Meat & Fish",
            "type":"Retail Goods"
        }
    ],
    "sg:phone":"+32 16 22 29 02",
    "sg:postcode":"3000",
    "sg:province":"Vlaams-Brabant",
    "sg:tags":[
        "poultry",
        "whol",
        "game",
        "-"
    ],
    "wof:name":"Long Bvba",
    "wof:placetype":"venue"
},
  "geometry": {"coordinates":[4.6908659935,50.8757591248],"type":"Point"}
}