{
  "type": "Feature",
  "properties": {
    "iso:country":"BE",
    "sg:address":"Osystraat 17",
    "sg:city":"Antwerpen",
    "sg:orig_category":"M\u00e9decins and sp\u00e9cialistes",
    "sg:phone":"+32 3 232 67 32",
    "sg:postcode":"2060",
    "sg:province":"Antwerpen",
    "wof:name":"R. Van Audenrode",
    "wof:placetype":"venue"
},
  "geometry": {"coordinates":[4.4183478355,51.2224502563],"type":"Point"}
}