{
  "type": "Feature",
  "properties": {
    "addr:full":"Sneppendreef 12 Brugge (sint-michiels) West-Vlaanderen 8200",
    "addr:housenumber":"12",
    "addr:postcode":"8200",
    "addr:street":"Sneppendreef",
    "iso:country":"BE",
    "sg:address":"Sneppendreef 12",
    "sg:city":"Brugge (sint-michiels)",
    "sg:classifiers":[
        {
            "category":"Health Services",
            "subcategory":"Doctor",
            "type":"Services"
        }
    ],
    "sg:phone":"+32 50 38 31 45",
    "sg:postcode":"8200",
    "sg:province":"West-Vlaanderen",
    "sg:tags":[
        "medicinephysicians",
        "surgeon"
    ],
    "wof:name":"Declerck A",
    "wof:placetype":"venue"
},
  "geometry": {"coordinates":[3.1924209595,51.1668663025],"type":"Point"}
}