{
  "type": "Feature",
  "properties": {
    "iso:country":"BE",
    "sg:address":"Ottergemsesteenweg 5",
    "sg:city":"Gent",
    "sg:classifiers":[
        {
            "category":"Banks & Credit Unions",
            "subcategory":"Investment Brokerage",
            "type":"Services"
        }
    ],
    "sg:phone":"+32 9 245 01 68",
    "sg:postcode":"9000",
    "sg:province":"Oost-Vlaanderen",
    "sg:tags":[
        "exchange",
        "stock"
    ],
    "wof:name":"Speybrouck Bvba",
    "wof:placetype":"venue"
},
  "geometry": {"coordinates":[3.726993084,51.037322998],"type":"Point"}
}