{
  "type": "Feature",
  "properties": {
    "iso:country":"BE",
    "sg:address":"Kortrijksesteenweg 401",
    "sg:city":"Harelbeke",
    "sg:orig_category":"V\u00e9hicules automobiles. Entretien and r\u00e9parations de voitures",
    "sg:phone":"+32 56 22 92 55",
    "sg:postcode":"8530",
    "sg:province":"West-Vlaanderen",
    "wof:name":"Garage Novoto",
    "wof:placetype":"venue"
},
  "geometry": {"coordinates":[3.2871038914,50.8395805359],"type":"Point"}
}