{
  "type": "Feature",
  "properties": {
    "addr:full":"Arthur De Greefstraat 5 Leuven Vlaams-Brabant 3000",
    "addr:housenumber":"5",
    "addr:postcode":"3000",
    "addr:street":"Greefstraat",
    "iso:country":"BE",
    "sg:address":"Arthur De Greefstraat 5",
    "sg:city":"Leuven",
    "sg:classifiers":[
        {
            "category":"Real Estate",
            "subcategory":"Architect",
            "type":"Services"
        }
    ],
    "sg:phone":"+32 16 22 10 44",
    "sg:postcode":"3000",
    "sg:province":"Vlaams-Brabant",
    "wof:name":"Mellaerts E",
    "wof:placetype":"venue"
},
  "geometry": {"coordinates":[4.6900448799,50.8747901917],"type":"Point"}
}