{
  "type": "Feature",
  "properties": {
    "iso:country":"BE",
    "sg:address":"Ezelstraat 143",
    "sg:city":"Brugge",
    "sg:classifiers":[
        {
            "category":"Real Estate",
            "subcategory":"Real Estate Services",
            "type":"Services"
        }
    ],
    "sg:phone":"+32 50 34 44 66",
    "sg:postcode":"8000",
    "sg:province":"West-Vlaanderen",
    "wof:name":"Immo Merco Bvba",
    "wof:placetype":"venue"
},
  "geometry": {"coordinates":[3.216397047,51.2146644592],"type":"Point"}
}