{
  "type": "Feature",
  "properties": {
    "iso:country":"BE",
    "sg:address":"Hondschottestraat 104",
    "sg:city":"Wevelgem",
    "sg:orig_category":"IJzerwaren, bouw- and verfmaterialen Speciaalzaken Verlichting and huishoudartikelen Vloer- and muur",
    "sg:phone":"+32 78 71 89 96",
    "sg:postcode":"8560",
    "sg:province":"West-Vlaanderen",
    "wof:name":"Abc Interieur",
    "wof:placetype":"venue"
},
  "geometry": {"coordinates":[3.1905589104,50.844493866],"type":"Point"}
}