{
  "type": "Feature",
  "properties": {
    "iso:country":"BE",
    "sg:address":"Rue De La Kelle 1",
    "sg:city":"Lasne (lasne-chapelle-saint-lambert)",
    "sg:classifiers":[
        {
            "category":"Health Services",
            "subcategory":"Health Practitioner",
            "type":"Services"
        }
    ],
    "sg:phone":"+32 2 633 34 03",
    "sg:postcode":"1380",
    "sg:province":"Brabant Wallon",
    "sg:tags":[
        "osteopath"
    ],
    "wof:name":"Jacquet E (d.o.)",
    "wof:placetype":"venue"
},
  "geometry": {"coordinates":[4.4921221733,50.681804657],"type":"Point"}
}