{
  "type": "Feature",
  "properties": {
    "iso:country":"BE",
    "sg:address":"Moorstraat 71b2",
    "sg:city":"Puurs",
    "sg:orig_category":"Boekhouders",
    "sg:phone":"+32 3 886 34 32",
    "sg:postcode":"2870",
    "sg:province":"Antwerpen",
    "wof:name":"Anja Van Der Straeten",
    "wof:placetype":"venue"
},
  "geometry": {"coordinates":[4.3219799995,51.0454292297],"type":"Point"}
}