{
  "type": "Feature",
  "properties": {
    "addr:full":"Rue Sainte-anne 11 Les Bons Villers (r\u00eaves) Hainaut 6210",
    "addr:housenumber":"11",
    "addr:postcode":"6210",
    "addr:street":"Rue Sainte-Anne",
    "iso:country":"BE",
    "sg:address":"Rue Sainte-anne 11",
    "sg:city":"Les Bons Villers (r\u00eaves)",
    "sg:classifiers":[
        {
            "category":"Home & Garden",
            "subcategory":"Garden Supply",
            "type":"Retail Goods"
        }
    ],
    "sg:phone":"+32 71 84 47 52",
    "sg:postcode":"6210",
    "sg:province":"Hainaut",
    "sg:tags":[
        "machine",
        "agricultural",
        "-"
    ],
    "wof:name":"Gevagri Sa",
    "wof:placetype":"venue"
},
  "geometry": {"coordinates":[4.4511561394,50.5378227234],"type":"Point"}
}