{
  "type": "Feature",
  "properties": {
    "iso:country":"BE",
    "sg:address":"Edm. Van Hoorebekestraat 58",
    "sg:city":"Gent",
    "sg:orig_category":"Artsen and specialisten",
    "sg:phone":"+32 9 230 22 35",
    "sg:postcode":"9050",
    "sg:province":"Oost-Vlaanderen",
    "wof:name":"L. Van Loo",
    "wof:placetype":"venue"
},
  "geometry": {"coordinates":[3.7470440865,51.0367584229],"type":"Point"}
}