{
  "type": "Feature",
  "properties": {
    "addr:full":"Chauss\u00e9e Du Roeulx 129 Soignies Hainaut 7060",
    "addr:housenumber":"129",
    "addr:postcode":"7060",
    "addr:street":"Chausse\u0301E Du Roeulx",
    "iso:country":"BE",
    "sg:address":"Chauss\u00e9e Du Roeulx 129",
    "sg:city":"Soignies",
    "sg:classifiers":[
        {
            "category":"Banks & Credit Unions",
            "subcategory":"Investment Brokerage",
            "type":"Services"
        }
    ],
    "sg:phone":"+32 67 33 23 73",
    "sg:postcode":"7060",
    "sg:province":"Hainaut",
    "sg:tags":[
        "fence"
    ],
    "wof:name":"Lebrun Ets",
    "wof:placetype":"venue"
},
  "geometry": {"coordinates":[4.0749759674,50.5637359619],"type":"Point"}
}