{
  "type": "Feature",
  "properties": {
    "iso:country":"BE",
    "sg:address":"Avenue De La D\u00c9portation 36",
    "sg:city":"Ecaussinnes",
    "sg:orig_category":"Winkelinrichting and handelsuitrusting Gh",
    "sg:phone":"+32 67 44 31 91",
    "sg:postcode":"7190",
    "sg:province":"Hainaut",
    "wof:name":"Savig",
    "wof:placetype":"venue"
},
  "geometry": {"coordinates":[4.1591567993,50.5628242493],"type":"Point"}
}