{
  "type": "Feature",
  "properties": {
    "addr:full":"Place Franklin-delano Roosevelt 35 Courcelles Hainaut 6180",
    "addr:housenumber":"35",
    "addr:postcode":"6180",
    "addr:street":"Place Franklin-Delano Roosevelt",
    "iso:country":"BE",
    "sg:address":"Place Franklin-delano Roosevelt 35",
    "sg:city":"Courcelles",
    "sg:classifiers":[
        {
            "category":"Shopping",
            "subcategory":"Music",
            "type":"Retail Goods"
        }
    ],
    "sg:phone":"+32 71 45 84 43",
    "sg:postcode":"6180",
    "sg:province":"Hainaut",
    "sg:tags":[
        "-",
        "cd's",
        "recorded",
        "cassette"
    ],
    "wof:name":"Music-house",
    "wof:placetype":"venue"
},
  "geometry": {"coordinates":[4.3743700981,50.4565086365],"type":"Point"}
}