{
  "type": "Feature",
  "properties": {
    "addr:full":"Druartstraat 17 Kortrijk West-Vlaanderen 8510",
    "addr:housenumber":"17",
    "addr:postcode":"8510",
    "addr:street":"Druartstraat",
    "iso:country":"BE",
    "sg:address":"Druartstraat 17",
    "sg:city":"Kortrijk",
    "sg:orig_category":"Woningbouw",
    "sg:phone":"+32 56 22 98 22",
    "sg:postcode":"8510",
    "sg:province":"West-Vlaanderen",
    "wof:name":"Vanderbeke L.",
    "wof:placetype":"venue"
},
  "geometry": {"coordinates":[3.2407360077,50.810836792],"type":"Point"}
}