{
  "type": "Feature",
  "properties": {
    "addr:full":"Gevangenisstraat 0 Brugge West-Vlaanderen 8000",
    "addr:housenumber":"0",
    "addr:postcode":"8000",
    "addr:street":"Gevangenisstraat",
    "iso:country":"BE",
    "sg:address":"Gevangenisstraat 0",
    "sg:city":"Brugge",
    "sg:orig_category":"Services annexes des transports terrestres",
    "sg:phone":"+32 50 34 89 51",
    "sg:postcode":"8000",
    "sg:province":"West-Vlaanderen",
    "wof:name":"Interparking",
    "wof:placetype":"venue"
},
  "geometry": {"coordinates":[3.2292048931,51.2065887451],"type":"Point"}
}