{
  "type": "Feature",
  "properties": {
    "iso:country":"BE",
    "sg:address":"Holt 96ba12",
    "sg:city":"Bilzen",
    "sg:orig_category":"Modellenbureaus",
    "sg:phone":"+32 89 51 54 03",
    "sg:postcode":"3740",
    "sg:province":"Limburg",
    "wof:name":"Marly Schoenmaekers",
    "wof:placetype":"venue"
},
  "geometry": {"coordinates":[5.4787402153,50.8886528015],"type":"Point"}
}