{
  "type": "Feature",
  "properties": {
    "addr:full":"Bergenstraat 5 Hoogstraten Antwerpen 2322",
    "addr:housenumber":"5",
    "addr:postcode":"2322",
    "addr:street":"Bergenstraat",
    "iso:country":"BE",
    "sg:address":"Bergenstraat 5",
    "sg:city":"Hoogstraten",
    "sg:orig_category":"Fruits and l\u00e9gumes. Producteurs de fruits",
    "sg:phone":"+32 3 315 73 37",
    "sg:postcode":"2322",
    "sg:province":"Antwerpen",
    "wof:name":"Wim Stoffels",
    "wof:placetype":"venue"
},
  "geometry": {"coordinates":[4.763384819,51.4160041809],"type":"Point"}
}