{
  "type": "Feature",
  "properties": {
    "addr:full":"Molenstraat 86 Berlare Oost-Vlaanderen 9290",
    "addr:housenumber":"86",
    "addr:postcode":"9290",
    "addr:street":"Molenstraat",
    "iso:country":"BE",
    "sg:address":"Molenstraat 86",
    "sg:city":"Berlare",
    "sg:orig_category":"Eleveurs d'animaux domestiques",
    "sg:phone":"+32 9 367 78 21",
    "sg:postcode":"9290",
    "sg:province":"Oost-Vlaanderen",
    "wof:name":"Rashondenkwekerij Huylebroek",
    "wof:placetype":"venue"
},
  "geometry": {"coordinates":[4.0041799545,51.0150184631],"type":"Point"}
}