{
  "type": "Feature",
  "properties": {
    "iso:country":"BE",
    "sg:address":"Rue L\u00e9opold 40",
    "sg:city":"Mouscron",
    "sg:classifiers":[
        {
            "category":"Education",
            "subcategory":"School",
            "type":"Public Place"
        }
    ],
    "sg:phone":"+32 56 33 23 20",
    "sg:postcode":"7700",
    "sg:province":"Hainaut",
    "sg:tags":[
        "primary"
    ],
    "wof:name":"Centre Educatif Europ\u00e9en",
    "wof:placetype":"venue"
},
  "geometry": {"coordinates":[3.221200943,50.7442016602],"type":"Point"}
}