{
  "type": "Feature",
  "properties": {
    "addr:full":"Stalenstraat 64 Genk Limburg 3600",
    "addr:housenumber":"64",
    "addr:postcode":"3600",
    "addr:street":"Stalenstraat",
    "iso:country":"BE",
    "sg:address":"Stalenstraat 64",
    "sg:city":"Genk",
    "sg:classifiers":[
        {
            "category":"Food & Beverages",
            "subcategory":"Fruits & Vegetables",
            "type":"Retail Goods"
        }
    ],
    "sg:phone":"+32 89 84 21 78",
    "sg:postcode":"3600",
    "sg:province":"Limburg",
    "sg:tags":[
        "l\u00e9gumes"
    ],
    "wof:name":"Huis Tekin-kardesler",
    "wof:placetype":"venue"
},
  "geometry": {"coordinates":[5.5187759399,50.9939193726],"type":"Point"}
}