{
  "type": "Feature",
  "properties": {
    "iso:country":"BE",
    "sg:address":"Albert I Laan 268",
    "sg:city":"Nieuwpoort",
    "sg:classifiers":[
        {
            "category":"Bars & Pubs",
            "type":"Food & Drink"
        }
    ],
    "sg:phone":"+32 58 24 13 94",
    "sg:postcode":"8620",
    "sg:province":"West-Vlaanderen",
    "wof:name":"Leopold's Caf\u00e9",
    "wof:placetype":"venue"
},
  "geometry": {"coordinates":[2.7109210491,51.1463012695],"type":"Point"}
}