{
  "type": "Feature",
  "properties": {
    "iso:country":"BE",
    "sg:address":"Rue Fran\u00e7ois Dorz\u00e9e 20",
    "sg:city":"Boussu",
    "sg:classifiers":[
        {
            "category":"Shopping",
            "subcategory":"Pets & Pet Supplies",
            "type":"Retail Goods"
        }
    ],
    "sg:postcode":"7300",
    "sg:province":"Hainaut",
    "sg:tags":[
        "shop",
        "-"
    ],
    "wof:name":"Au Mackintosh",
    "wof:placetype":"venue"
},
  "geometry": {"coordinates":[3.7978749275,50.4336280823],"type":"Point"}
}