{
  "type": "Feature",
  "properties": {
    "addr:full":"Dijlekant 7 Rotselaar Vlaams-Brabant 3118",
    "addr:housenumber":"7",
    "addr:postcode":"3118",
    "addr:street":"Dijlekant",
    "iso:country":"BE",
    "sg:address":"Dijlekant 7",
    "sg:city":"Rotselaar",
    "sg:orig_category":"Producteurs de l\u00e9gumes",
    "sg:phone":"+32 16 60 49 68",
    "sg:postcode":"3118",
    "sg:province":"Vlaams-Brabant",
    "wof:name":"Elza Van Hoof",
    "wof:placetype":"venue"
},
  "geometry": {"coordinates":[4.6925702095,50.964931488],"type":"Point"}
}