{
  "type": "Feature",
  "properties": {
    "iso:country":"BE",
    "sg:address":"Rue Arnold Trillet 75ba",
    "sg:city":"Soumagne",
    "sg:orig_category":"Diverse opleidingen and onderwijs",
    "sg:phone":"+32 4 377 64 31",
    "sg:postcode":"4630",
    "sg:province":"Li\u00e8ge",
    "wof:name":"K.y. Communication",
    "wof:placetype":"venue"
},
  "geometry": {"coordinates":[5.7262601852,50.6223602295],"type":"Point"}
}