{
  "type": "Feature",
  "properties": {
    "addr:full":"Ernest Gossartstraat 27b6 Ukkel/uccle Bruxelles-Capitale 1180",
    "addr:housenumber":"27b6",
    "addr:postcode":"1180",
    "addr:street":"Ernest Gossartstraat;/",
    "iso:country":"BE",
    "sg:address":"Ernest Gossartstraat 27b6",
    "sg:city":"Ukkel/uccle",
    "sg:orig_category":"Herstelling leer and schoeisel",
    "sg:phone":"+32 2 345 60 68",
    "sg:postcode":"1180",
    "sg:province":"Bruxelles-Capitale",
    "wof:name":"Domenico Mussari",
    "wof:placetype":"venue"
},
  "geometry": {"coordinates":[4.3630161285,50.8104324341],"type":"Point"}
}