{
  "type": "Feature",
  "properties": {
    "addr:full":"Ave Louise 287 Box 1 Bruxelles Bruxelles-Capitale 1050",
    "addr:housenumber":"287;1",
    "addr:postcode":"1050",
    "addr:street":"Ave Louise;Box",
    "iso:country":"BE",
    "sg:address":"Ave Louise 287 Box 1",
    "sg:city":"Bruxelles",
    "sg:classifiers":[
        {
            "category":"Banks & Credit Unions",
            "subcategory":"Bank",
            "type":"Services"
        }
    ],
    "sg:phone":"+32 2 648 82 85",
    "sg:postcode":"1050",
    "sg:province":"Bruxelles-Capitale",
    "wof:name":"Bank Of Yokohama Sa",
    "wof:placetype":"venue"
},
  "geometry": {"coordinates":[4.3671460152,50.8236999512],"type":"Point"}
}