{
  "type": "Feature",
  "properties": {
    "addr:full":"Nieuwlandstraat 34 Oostende West-Vlaanderen 8400",
    "addr:housenumber":"34",
    "addr:postcode":"8400",
    "addr:street":"Nieuwlandstraat",
    "iso:country":"BE",
    "sg:address":"Nieuwlandstraat 34",
    "sg:city":"Oostende",
    "sg:orig_category":"Alternatieve geneeskunde Artsen and specialisten Boekhouders",
    "sg:phone":"+32 59 70 38 38",
    "sg:postcode":"8400",
    "sg:province":"West-Vlaanderen",
    "wof:name":"Christiaan Wille",
    "wof:placetype":"venue"
},
  "geometry": {"coordinates":[2.9088420868,51.2170372009],"type":"Point"}
}