{
  "type": "Feature",
  "properties": {
    "addr:full":"Oude Steenweg 79 Antwerpen Antwerpen 2060",
    "addr:housenumber":"79",
    "addr:postcode":"2060",
    "addr:street":"Oude Steenweg",
    "iso:country":"BE",
    "sg:address":"Oude Steenweg 79",
    "sg:city":"Antwerpen",
    "sg:classifiers":[
        {
            "category":"Insurance",
            "subcategory":"Insurance Agent",
            "type":"Services"
        }
    ],
    "sg:phone":"+32 3 225 20 72",
    "sg:postcode":"2060",
    "sg:province":"Antwerpen",
    "sg:tags":[
        "broker"
    ],
    "wof:name":"Janssens & Co Nv",
    "wof:placetype":"venue"
},
  "geometry": {"coordinates":[4.4209218025,51.2266654968],"type":"Point"}
}