{
  "type": "Feature",
  "properties": {
    "iso:country":"BE",
    "sg:address":"Pater Beckersstraat 26",
    "sg:city":"Heusden-zolder (heusden)",
    "sg:classifiers":[
        {
            "category":"Personal",
            "subcategory":"Beauty Salon",
            "type":"Services"
        }
    ],
    "sg:phone":"+32 11 43 72 05",
    "sg:postcode":"3550",
    "sg:province":"Limburg",
    "sg:tags":[
        "lady",
        "-",
        "hairdressing"
    ],
    "wof:name":"Joris A",
    "wof:placetype":"venue"
},
  "geometry": {"coordinates":[5.2454180717,51.0327377319],"type":"Point"}
}