{
  "type": "Feature",
  "properties": {
    "addr:full":"Rue Fran\u00c7ois Lapierre 79 Fleron Li\u00e8ge 4620",
    "addr:housenumber":"79",
    "addr:postcode":"4620",
    "addr:street":"Rue Franc\u0327Ois Lapierre",
    "iso:country":"BE",
    "sg:address":"Rue Fran\u00c7ois Lapierre 79",
    "sg:city":"Fleron",
    "sg:orig_category":"Enseignement maternel and primaire",
    "sg:phone":"+32 4 355 91 27",
    "sg:postcode":"4620",
    "sg:province":"Li\u00e8ge",
    "wof:name":"Ecole Fond. Communale",
    "wof:placetype":"venue"
},
  "geometry": {"coordinates":[5.682199955,50.6196594238],"type":"Point"}
}