{
  "type": "Feature",
  "properties": {
    "iso:country":"BE",
    "sg:address":"Kapitein A.tobbackstraat 12",
    "sg:city":"Boortmeerbeek",
    "sg:classifiers":[
        {
            "category":"Building & Trades",
            "subcategory":"Electrical",
            "type":"Services"
        }
    ],
    "sg:phone":"+32 15 52 73 75",
    "sg:postcode":"3190",
    "sg:province":"Vlaams-Brabant",
    "sg:tags":[
        "electric",
        "-",
        "housewiring",
        "contractor"
    ],
    "wof:name":"Deboudt H Bvba",
    "wof:placetype":"venue"
},
  "geometry": {"coordinates":[4.569756031,50.983341217],"type":"Point"}
}