{
  "type": "Feature",
  "properties": {
    "iso:country":"BE",
    "sg:address":"Kerkstraat 45",
    "sg:city":"Kaprijke",
    "sg:orig_category":"Woningbouw",
    "sg:phone":"+32 9 378 31 64",
    "sg:postcode":"9971",
    "sg:province":"Oost-Vlaanderen",
    "wof:name":"Philippe Spiessens",
    "wof:placetype":"venue"
},
  "geometry": {"coordinates":[3.6414339542,51.2014961243],"type":"Point"}
}