{
  "type": "Feature",
  "properties": {
    "iso:country":"BE",
    "sg:address":"Ruiseleedsesteenweg 37",
    "sg:city":"Tielt",
    "sg:classifiers":[
        {
            "category":"Organizations",
            "subcategory":"Labor Organization",
            "type":"Services"
        }
    ],
    "sg:phone":"+32 51 40 88 45",
    "sg:postcode":"8700",
    "sg:province":"West-Vlaanderen",
    "sg:tags":[
        "harness",
        "maker",
        "saddler"
    ],
    "wof:name":"Delaere",
    "wof:placetype":"venue"
},
  "geometry": {"coordinates":[3.3527309895,51.0083618164],"type":"Point"}
}