{
  "type": "Feature",
  "properties": {
    "addr:full":"Rudolfstraat 47 Antwerpen Antwerpen 2018",
    "addr:housenumber":"47",
    "addr:postcode":"2018",
    "addr:street":"Rudolfstraat",
    "iso:country":"BE",
    "sg:address":"Rudolfstraat 47",
    "sg:city":"Antwerpen",
    "sg:classifiers":[
        {
            "category":"Health Services",
            "subcategory":"Doctor",
            "type":"Services"
        }
    ],
    "sg:phone":"+32 3 216 26 76",
    "sg:postcode":"2018",
    "sg:province":"Antwerpen",
    "sg:tags":[
        "medicinephysicians",
        "surgeon"
    ],
    "wof:name":"Mareels J",
    "wof:placetype":"venue"
},
  "geometry": {"coordinates":[4.4015078545,51.2048072815],"type":"Point"}
}