{
  "type": "Feature",
  "properties": {
    "addr:full":"Dorp 46 Zoersel Antwerpen 2980",
    "addr:housenumber":"46",
    "addr:postcode":"2980",
    "addr:street":"Dorp",
    "iso:country":"BE",
    "sg:address":"Dorp 46",
    "sg:city":"Zoersel",
    "sg:orig_category":"Postkantoren Verzekeringsmakelaars and experts",
    "sg:phone":"+32 3 312 20 03",
    "sg:postcode":"2980",
    "sg:province":"Antwerpen",
    "wof:name":"De Post",
    "wof:placetype":"venue"
},
  "geometry": {"coordinates":[4.7130432129,51.2691650391],"type":"Point"}
}