{
  "type": "Feature",
  "properties": {
    "iso:country":"BE",
    "sg:address":"Rue Barbe D'or 37",
    "sg:city":"Celles (aineffe)",
    "sg:classifiers":[
        {
            "category":"Professional",
            "subcategory":"Accounting & Tax Preparation",
            "type":"Services"
        }
    ],
    "sg:phone":"+32 19 56 77 70",
    "sg:postcode":"4317",
    "sg:province":"Li\u00e8ge",
    "sg:tags":[
        "accountant"
    ],
    "wof:name":"Cornet A",
    "wof:placetype":"venue"
},
  "geometry": {"coordinates":[3.4295620918,43.6282691956],"type":"Point"}
}