{
  "type": "Feature",
  "properties": {
    "addr:full":"Hillarestraat 318 Lokeren Oost-Vlaanderen 9160",
    "addr:housenumber":"318",
    "addr:postcode":"9160",
    "addr:street":"Hillarestraat",
    "iso:country":"BE",
    "sg:address":"Hillarestraat 318",
    "sg:city":"Lokeren",
    "sg:classifiers":[
        {
            "category":"Retail",
            "subcategory":"Repair Shop",
            "type":"Services"
        }
    ],
    "sg:phone":"+32 9 348 59 89",
    "sg:postcode":"9160",
    "sg:province":"Oost-Vlaanderen",
    "sg:tags":[
        "jobbing",
        "tailoring",
        "-"
    ],
    "wof:name":"Van Den Bosch A",
    "wof:placetype":"venue"
},
  "geometry": {"coordinates":[3.9654300213,51.0918998718],"type":"Point"}
}