{
  "type": "Feature",
  "properties": {
    "iso:country":"BE",
    "sg:address":"Brusselstraat 90-92",
    "sg:city":"Ninove",
    "sg:classifiers":[
        {
            "category":"Professional",
            "subcategory":"Art Services",
            "type":"Services"
        }
    ],
    "sg:phone":"+32 54 33 89 04",
    "sg:postcode":"9400",
    "sg:province":"Oost-Vlaanderen",
    "sg:tags":[
        "photographer"
    ],
    "wof:name":"Studio Jos",
    "wof:placetype":"venue"
},
  "geometry": {"coordinates":[4.0251588821,50.8284034729],"type":"Point"}
}