{
  "type": "Feature",
  "properties": {
    "addr:full":"Leemskuilenstraat 22 Bocholt Limburg 3950",
    "addr:housenumber":"22",
    "addr:postcode":"3950",
    "addr:street":"Leemskuilenstraat",
    "iso:country":"BE",
    "sg:address":"Leemskuilenstraat 22",
    "sg:city":"Bocholt",
    "sg:classifiers":[
        {
            "category":"Building & Trades",
            "subcategory":"Construction",
            "type":"Services"
        }
    ],
    "sg:phone":"+32 11 44 19 73",
    "sg:postcode":"3950",
    "sg:province":"Limburg",
    "sg:tags":[
        "stucco",
        "contractor"
    ],
    "wof:name":"Ragostuc",
    "wof:placetype":"venue"
},
  "geometry": {"coordinates":[5.5658612251,51.2041625977],"type":"Point"}
}