{
  "type": "Feature",
  "properties": {
    "iso:country":"BE",
    "sg:address":"Rue Emile Royer 193-204",
    "sg:city":"Seraing",
    "sg:orig_category":"Entretien and r\u00e9parations de voitures. V\u00e9hicules automobiles",
    "sg:phone":"+32 4 233 32 39",
    "sg:postcode":"4101",
    "sg:province":"Li\u00e8ge",
    "wof:name":"Garage Humblet",
    "wof:placetype":"venue"
},
  "geometry": {"coordinates":[5.4888958931,50.609703064],"type":"Point"}
}