{
  "type": "Feature",
  "properties": {
    "iso:country":"BE",
    "sg:address":"Parklaan 30",
    "sg:city":"Nieuwpoort",
    "sg:orig_category":"Luchtvaart zonder dienstregeling Vlieg- and vaarscholen",
    "sg:phone":"+32 58 23 51 93",
    "sg:postcode":"8620",
    "sg:province":"West-Vlaanderen",
    "wof:name":"Eurobelgium Helicopters",
    "wof:placetype":"venue"
},
  "geometry": {"coordinates":[2.746753931,51.1304130554],"type":"Point"}
}