{
  "type": "Feature",
  "properties": {
    "iso:country":"BE",
    "sg:address":"Noordabeelstraat 6",
    "sg:city":"Hooglede",
    "sg:orig_category":"Eleveurs de bovins. Eleveurs and marchands de porcs",
    "sg:phone":"+32 51 72 35 32",
    "sg:postcode":"8830",
    "sg:province":"West-Vlaanderen",
    "wof:name":"Noel Muyssen",
    "wof:placetype":"venue"
},
  "geometry": {"coordinates":[3.0772809982,51.0084609985],"type":"Point"}
}