{
  "type": "Feature",
  "properties": {
    "addr:full":"Aduatukersstraat 53 Etterbeek/etterbeek Bruxelles-Capitale 1040",
    "addr:housenumber":"53",
    "addr:postcode":"1040",
    "addr:street":"Aduatukersstraat",
    "iso:country":"BE",
    "sg:address":"Aduatukersstraat 53",
    "sg:city":"Etterbeek/etterbeek",
    "sg:orig_category":"Artsen and specialisten",
    "sg:phone":"+32 2 736 66 90",
    "sg:postcode":"1040",
    "sg:province":"Bruxelles-Capitale",
    "wof:name":"Louis Dubois",
    "wof:placetype":"venue"
},
  "geometry": {"coordinates":[4.4024548531,50.837184906],"type":"Point"}
}