{
  "type": "Feature",
  "properties": {
    "addr:full":"Sint-jansplein 49 Box 6 Antwerpen Antwerpen 2060",
    "addr:housenumber":"49;6",
    "addr:postcode":"2060",
    "addr:street":"Sint-Jansplein;Box",
    "iso:country":"BE",
    "sg:address":"Sint-jansplein 49 Box 6",
    "sg:city":"Antwerpen",
    "sg:classifiers":[
        {
            "category":"Professional",
            "subcategory":"Lawyer & Legal Services",
            "type":"Services"
        }
    ],
    "sg:phone":"+32 3 233 87 48",
    "sg:postcode":"2060",
    "sg:province":"Antwerpen",
    "wof:name":"Pepermans Lieve",
    "wof:placetype":"venue"
},
  "geometry": {"coordinates":[4.4168019295,51.2249488831],"type":"Point"}
}