{
  "type": "Feature",
  "properties": {
    "addr:full":"Oordegemsesteenweg 257 Wetteren Oost-Vlaanderen 9230",
    "addr:housenumber":"257",
    "addr:postcode":"9230",
    "addr:street":"Oordegemsesteenweg",
    "iso:country":"BE",
    "sg:address":"Oordegemsesteenweg 257",
    "sg:city":"Wetteren",
    "sg:orig_category":"Installation de menuiserie en bois and plastique",
    "sg:phone":"+32 9 366 42 51",
    "sg:postcode":"9230",
    "sg:province":"Oost-Vlaanderen",
    "wof:name":"Vdas-design",
    "wof:placetype":"venue"
},
  "geometry": {"coordinates":[3.8870398998,50.9932403564],"type":"Point"}
}