{
  "type": "Feature",
  "properties": {
    "addr:full":"Lange Wegel 118 Wetteren Oost-Vlaanderen 9230",
    "addr:housenumber":"118",
    "addr:postcode":"9230",
    "addr:street":"Lange Wegel",
    "iso:country":"BE",
    "sg:address":"Lange Wegel 118",
    "sg:city":"Wetteren",
    "sg:classifiers":[
        {
            "category":"Retail",
            "subcategory":"Veterinary Services",
            "type":"Services"
        }
    ],
    "sg:phone":"+32 9 369 53 39",
    "sg:postcode":"9230",
    "sg:province":"Oost-Vlaanderen",
    "sg:tags":[
        "veterinarian"
    ],
    "wof:name":"Marius M",
    "wof:placetype":"venue"
},
  "geometry": {"coordinates":[3.9063870907,51.0086288452],"type":"Point"}
}