{
  "type": "Feature",
  "properties": {
    "addr:full":"Heikant 18 Herenthout Antwerpen 2270",
    "addr:housenumber":"18",
    "addr:postcode":"2270",
    "addr:street":"Heikant",
    "iso:country":"BE",
    "sg:address":"Heikant 18",
    "sg:city":"Herenthout",
    "sg:classifiers":[
        {
            "category":"Insurance",
            "subcategory":"Life Insurance",
            "type":"Services"
        }
    ],
    "sg:phone":"+32 14 51 55 73",
    "sg:postcode":"2270",
    "sg:province":"Antwerpen",
    "sg:tags":[
        "assurance"
    ],
    "wof:name":"J. Van Den Broeck",
    "wof:placetype":"venue"
},
  "geometry": {"coordinates":[4.7715520859,51.1321487427],"type":"Point"}
}