{
  "type": "Feature",
  "properties": {
    "addr:full":"Kortemarkstraat 70 Torhout West-Vlaanderen 8820",
    "addr:housenumber":"70",
    "addr:postcode":"8820",
    "addr:street":"Kortemarkstraat",
    "iso:country":"BE",
    "sg:address":"Kortemarkstraat 70",
    "sg:city":"Torhout",
    "sg:classifiers":[
        {
            "category":"Banks & Credit Unions",
            "subcategory":"Bank",
            "type":"Services"
        }
    ],
    "sg:phone":"+32 50 22 14 51",
    "sg:postcode":"8820",
    "sg:province":"West-Vlaanderen",
    "sg:tags":[
        "savings-banks"
    ],
    "wof:name":"Agf Belgium Bank-maeckelbergh-heyndrickx-ag D\u00e9l",
    "wof:placetype":"venue"
},
  "geometry": {"coordinates":[3.096955061,51.0605545044],"type":"Point"}
}