{
  "type": "Feature",
  "properties": {
    "iso:country":"BE",
    "sg:address":"Nekke 35",
    "sg:city":"Zomergem",
    "sg:orig_category":"Quincailleries",
    "sg:phone":"+32 9 372 71 59",
    "sg:postcode":"9930",
    "sg:province":"Oost-Vlaanderen",
    "wof:name":"Yvonne Baute",
    "wof:placetype":"venue"
},
  "geometry": {"coordinates":[3.538310051,51.1146011353],"type":"Point"}
}