{
  "type": "Feature",
  "properties": {
    "iso:country":"BE",
    "sg:address":"Kerkstraat 33",
    "sg:city":"Schilde ('s Gravenwezel)",
    "sg:classifiers":[
        {
            "category":"Bars & Pubs",
            "type":"Food & Drink"
        }
    ],
    "sg:phone":"+32 3 658 23 33",
    "sg:postcode":"2970",
    "sg:province":"Antwerpen",
    "wof:name":"Keysershof",
    "wof:placetype":"venue"
},
  "geometry": {"coordinates":[4.5833687782,51.239200592],"type":"Point"}
}