{
  "type": "Feature",
  "properties": {
    "addr:full":"Hingenesteenweg 71 Bornem Antwerpen 2880",
    "addr:housenumber":"71",
    "addr:postcode":"2880",
    "addr:street":"Hingenesteenweg",
    "iso:country":"BE",
    "sg:address":"Hingenesteenweg 71",
    "sg:city":"Bornem",
    "sg:classifiers":[
        {
            "category":"Building & Trades",
            "subcategory":"Cleaning & Sanitation",
            "type":"Services"
        }
    ],
    "sg:phone":"+32 3 899 18 49",
    "sg:postcode":"2880",
    "sg:province":"Antwerpen",
    "sg:tags":[
        "fa\u00e7ade",
        "maintenance"
    ],
    "wof:name":"Ceulemans Bjorn Bvba",
    "wof:placetype":"venue"
},
  "geometry": {"coordinates":[4.249985218,51.1010856628],"type":"Point"}
}