{
  "type": "Feature",
  "properties": {
    "iso:country":"BE",
    "sg:address":"Overstraat 37",
    "sg:city":"Diest",
    "sg:orig_category":"Enseignement maternel and primaire",
    "sg:phone":"+32 13 31 14 42",
    "sg:postcode":"3290",
    "sg:province":"Vlaams-Brabant",
    "wof:name":"Basisschool",
    "wof:placetype":"venue"
},
  "geometry": {"coordinates":[5.055188179,50.9863586426],"type":"Point"}
}