{
  "type": "Feature",
  "properties": {
    "addr:full":"Chauss\u00c9e De Bruxelles 64 Charleroi Hainaut 6020",
    "addr:housenumber":"64",
    "addr:postcode":"6020",
    "addr:street":"Chausse\u0301E De Bruxelles;Hainaut",
    "iso:country":"BE",
    "sg:address":"Chauss\u00c9e De Bruxelles 64",
    "sg:city":"Charleroi",
    "sg:orig_category":"Installatie van metalen schrijnwerk Technische and wetenschappelijke instrumenten Fab",
    "sg:phone":"+32 81 74 08 49",
    "sg:postcode":"6020",
    "sg:province":"Hainaut",
    "wof:name":"Security Door",
    "wof:placetype":"venue"
},
  "geometry": {"coordinates":[4.4378871918,50.4149703979],"type":"Point"}
}