{
  "type": "Feature",
  "properties": {
    "addr:full":"Kerkborre 3 Geraardsbergen (schendelbeke) Oost-Vlaanderen 9506",
    "addr:housenumber":"3",
    "addr:postcode":"9506",
    "addr:street":"Kerkborre",
    "iso:country":"BE",
    "sg:address":"Kerkborre 3",
    "sg:city":"Geraardsbergen (schendelbeke)",
    "sg:classifiers":[
        {
            "category":"Professional",
            "subcategory":"Testing Lab",
            "type":"Services"
        }
    ],
    "sg:phone":"+32 54 41 74 74",
    "sg:postcode":"9506",
    "sg:province":"Oost-Vlaanderen",
    "sg:tags":[
        "chemist"
    ],
    "wof:name":"Rebry R-g",
    "wof:placetype":"venue"
},
  "geometry": {"coordinates":[3.8985300064,50.7987060547],"type":"Point"}
}