{
  "type": "Feature",
  "properties": {
    "iso:country":"BE",
    "sg:address":"Ieperstraat 81",
    "sg:city":"Hooglede",
    "sg:orig_category":"Voertuigen",
    "sg:phone":"+32 51 20 35 94",
    "sg:postcode":"8830",
    "sg:province":"West-Vlaanderen",
    "wof:name":"Garage Coghe",
    "wof:placetype":"venue"
},
  "geometry": {"coordinates":[3.0743429661,50.9729270935],"type":"Point"}
}