{
  "type": "Feature",
  "properties": {
    "addr:full":"Orteliuskaai 2 Antwerpen Antwerpen 2000",
    "addr:housenumber":"2",
    "addr:postcode":"2000",
    "addr:street":"Orteliuskaai",
    "iso:country":"BE",
    "sg:address":"Orteliuskaai 2",
    "sg:city":"Antwerpen",
    "sg:classifiers":[
        {
            "category":"Professional",
            "subcategory":"Computer Services",
            "type":"Services"
        }
    ],
    "sg:phone":"+32 3 658 56 50",
    "sg:postcode":"2000",
    "sg:province":"Antwerpen",
    "sg:tags":[
        "-",
        "processing",
        "data",
        "software"
    ],
    "wof:name":"Imagine-e Nv",
    "wof:placetype":"venue"
},
  "geometry": {"coordinates":[4.4000592232,51.2254562378],"type":"Point"}
}