{
  "type": "Feature",
  "properties": {
    "iso:country":"BE",
    "sg:address":"Fabiolapad 5",
    "sg:city":"Deerlijk",
    "sg:classifiers":[
        {
            "category":"Cafe",
            "type":"Food & Drink"
        }
    ],
    "sg:phone":"+32 56 71 64 22",
    "sg:postcode":"8540",
    "sg:province":"West-Vlaanderen",
    "sg:tags":[
        "caf\u00e9s"
    ],
    "wof:name":"Palmer Deleersnyder",
    "wof:placetype":"venue"
},
  "geometry": {"coordinates":[3.3545029163,50.8609809875],"type":"Point"}
}