{
  "type": "Feature",
  "properties": {
    "addr:full":"Rue Carl Jost 38 Fleron Li\u00e8ge 4621",
    "addr:housenumber":"38",
    "addr:postcode":"4621",
    "addr:street":"Rue Carl Jost",
    "iso:country":"BE",
    "sg:address":"Rue Carl Jost 38",
    "sg:city":"Fleron",
    "sg:classifiers":[
        {
            "category":"Cafe",
            "type":"Food & Drink"
        }
    ],
    "sg:phone":"+32 4 358 85 76",
    "sg:postcode":"4621",
    "sg:province":"Li\u00e8ge",
    "sg:tags":[
        "caf\u00e9s"
    ],
    "wof:name":"Caf\u00c9 Le Ritz",
    "wof:placetype":"venue"
},
  "geometry": {"coordinates":[5.7072181702,50.6249427795],"type":"Point"}
}