{
  "type": "Feature",
  "properties": {
    "addr:full":"Meesberg 2 Holsbeek Vlaams-Brabant 3220",
    "addr:housenumber":"2",
    "addr:postcode":"3220",
    "addr:street":"Meesberg",
    "iso:country":"BE",
    "sg:address":"Meesberg 2",
    "sg:city":"Holsbeek",
    "sg:orig_category":"Boucheries",
    "sg:phone":"+32 16 44 52 54",
    "sg:postcode":"3220",
    "sg:province":"Vlaams-Brabant",
    "wof:name":"Beenhouwerij Eug\u00c8ne",
    "wof:placetype":"venue"
},
  "geometry": {"coordinates":[4.7563490868,50.9183959961],"type":"Point"}
}