{
  "type": "Feature",
  "properties": {
    "addr:full":"Monseigneur Heylenstraat 20 Kasterlee Antwerpen 2460",
    "addr:housenumber":"20",
    "addr:postcode":"2460",
    "addr:street":"Monseigneur Heylenstraat",
    "iso:country":"BE",
    "sg:address":"Monseigneur Heylenstraat 20",
    "sg:city":"Kasterlee",
    "sg:classifiers":[
        {
            "category":"Health Services",
            "subcategory":"Nursing And Care Facility",
            "type":"Services"
        }
    ],
    "sg:phone":"+32 14 85 20 52",
    "sg:postcode":"2460",
    "sg:province":"Antwerpen",
    "sg:tags":[
        "home"
    ],
    "wof:name":"De Ceuster C",
    "wof:placetype":"venue"
},
  "geometry": {"coordinates":[4.9651098251,51.2388000488],"type":"Point"}
}