{
  "type": "Feature",
  "properties": {
    "addr:full":"Dendermondse Steenweg 75 Aalst Oost-Vlaanderen 9300",
    "addr:housenumber":"75",
    "addr:postcode":"9300",
    "addr:street":"Steenweg",
    "iso:country":"BE",
    "sg:address":"Dendermondse Steenweg 75",
    "sg:city":"Aalst",
    "sg:orig_category":"Installation de menuiserie en bois and plastique",
    "sg:phone":"+32 53 78 68 69",
    "sg:postcode":"9300",
    "sg:province":"Oost-Vlaanderen",
    "wof:name":"Frank Geldhof",
    "wof:placetype":"venue"
},
  "geometry": {"coordinates":[4.0465779305,50.9505729675],"type":"Point"}
}