{
  "type": "Feature",
  "properties": {
    "addr:full":"Doornzeelsestraat 92 Evergem Oost-Vlaanderen 9940",
    "addr:housenumber":"92",
    "addr:postcode":"9940",
    "addr:street":"Doornzeelsestraat;Oost-Vlaanderen",
    "iso:country":"BE",
    "sg:address":"Doornzeelsestraat 92",
    "sg:city":"Evergem",
    "sg:orig_category":"Installation \u00e9lectrique r\u00e9sidentielle",
    "sg:phone":"+32 9 258 04 78",
    "sg:postcode":"9940",
    "sg:province":"Oost-Vlaanderen",
    "wof:name":"Dirk Buysse",
    "wof:placetype":"venue"
},
  "geometry": {"coordinates":[3.7516069412,51.1354484558],"type":"Point"}
}