{
  "type": "Feature",
  "properties": {
    "addr:full":"Chauss\u00c9e De Mons 36 Soignies Hainaut 7060",
    "addr:housenumber":"36",
    "addr:postcode":"7060",
    "addr:street":"Chausse\u0301E De Mons",
    "iso:country":"BE",
    "sg:address":"Chauss\u00c9e De Mons 36",
    "sg:city":"Soignies",
    "sg:orig_category":"Dierenartsen",
    "sg:phone":"+32 67 34 13 48",
    "sg:postcode":"7060",
    "sg:province":"Hainaut",
    "wof:name":"Eric Valissant",
    "wof:placetype":"venue"
},
  "geometry": {"coordinates":[4.0659217834,50.5705108643],"type":"Point"}
}