{
  "type": "Feature",
  "properties": {
    "addr:full":"Beverlosesteenweg 289 Beringen (paal) Limburg 3583",
    "addr:housenumber":"289",
    "addr:postcode":"3583",
    "addr:street":"Beverlosesteenweg",
    "iso:country":"BE",
    "sg:address":"Beverlosesteenweg 289",
    "sg:city":"Beringen (paal)",
    "sg:classifiers":[
        {
            "category":"Home & Garden",
            "subcategory":"Kitchen Supply",
            "type":"Retail Goods"
        }
    ],
    "sg:phone":"+32 11 45 27 30",
    "sg:postcode":"3583",
    "sg:province":"Limburg",
    "sg:tags":[
        "equipment",
        "baker",
        "-"
    ],
    "wof:name":"Bamach Bvba",
    "wof:placetype":"venue"
},
  "geometry": {"coordinates":[5.2034950256,51.0651473999],"type":"Point"}
}