{
  "type": "Feature",
  "properties": {
    "iso:country":"BE",
    "sg:address":"Avenue De L'equerre 33-1",
    "sg:city":"Ottignies-louvain-la-neuve (louvain-la-neuve)",
    "sg:classifiers":[
        {
            "category":"Retail",
            "subcategory":"Veterinary Services",
            "type":"Services"
        }
    ],
    "sg:phone":"+32 475 70 02 06",
    "sg:postcode":"1348",
    "sg:province":"Brabant Wallon",
    "sg:tags":[
        "veterinarian"
    ],
    "wof:name":"Vanherreweghe V",
    "wof:placetype":"venue"
},
  "geometry": {"coordinates":[4.6097569466,50.6640892029],"type":"Point"}
}