{
  "type": "Feature",
  "properties": {
    "iso:country":"BE",
    "sg:address":"Avenue De La Couronne 412",
    "sg:city":"Elsene/ixelles",
    "sg:orig_category":"Journaux. Librairies. Tabac",
    "sg:phone":"+32 2 647 14 84",
    "sg:postcode":"1050",
    "sg:province":"Bruxelles-Capitale",
    "wof:name":"Librairie De La Couronne",
    "wof:placetype":"venue"
},
  "geometry": {"coordinates":[4.3889951706,50.8219032288],"type":"Point"}
}