{
  "type": "Feature",
  "properties": {
    "iso:country":"BE",
    "sg:address":"Chauss\u00c9e De L'ourthe 153",
    "sg:city":"Marche-en-famenne",
    "sg:orig_category":"Woningbouw",
    "sg:phone":"+32 84 32 22 95",
    "sg:postcode":"6900",
    "sg:province":"Luxembourg",
    "wof:name":"Rasquin Construction",
    "wof:placetype":"venue"
},
  "geometry": {"coordinates":[5.3637051582,50.2365684509],"type":"Point"}
}