{
  "type": "Feature",
  "properties": {
    "iso:country":"BE",
    "sg:address":"Vaartlaan 34",
    "sg:city":"Aalter",
    "sg:orig_category":"Installation de menuiserie m\u00e9tallique",
    "sg:phone":"+32 9 374 29 30",
    "sg:postcode":"9880",
    "sg:province":"Oost-Vlaanderen",
    "wof:name":"Guido De Boever",
    "wof:placetype":"venue"
},
  "geometry": {"coordinates":[3.396723032,51.1118202209],"type":"Point"}
}