{
  "type": "Feature",
  "properties": {
    "iso:country":"BE",
    "sg:address":"Chauss\u00c9e De Louvain 496",
    "sg:city":"Wavre",
    "sg:orig_category":"Chemicali\u00ebn Gh",
    "sg:phone":"+32 10 24 25 22",
    "sg:postcode":"1300",
    "sg:province":"Brabant Wallon",
    "wof:name":"Bevil",
    "wof:placetype":"venue"
},
  "geometry": {"coordinates":[4.629406929,50.7232780457],"type":"Point"}
}