{
  "type": "Feature",
  "properties": {
    "addr:full":"Grand Rue 74 Malmedy/malmedy Li\u00e8ge 4960",
    "addr:housenumber":"74",
    "addr:postcode":"4960",
    "addr:street":"Grand Rue",
    "iso:country":"BE",
    "sg:address":"Grand Rue 74",
    "sg:city":"Malmedy/malmedy",
    "sg:classifiers":[
        {
            "category":"Cafe",
            "type":"Food & Drink"
        }
    ],
    "sg:phone":"+32 80 57 01 93",
    "sg:postcode":"4960",
    "sg:province":"Li\u00e8ge",
    "sg:tags":[
        "caf\u00e9s"
    ],
    "wof:name":"Elisabeth Gabriel",
    "wof:placetype":"venue"
},
  "geometry": {"coordinates":[6.0532631874,50.3620567322],"type":"Point"}
}