{
  "type": "Feature",
  "properties": {
    "addr:full":"Chrysantenstraat 59b Merelbeke Oost-Vlaanderen 9820",
    "addr:housenumber":"59b",
    "addr:postcode":"9820",
    "addr:street":"Chrysantenstraat",
    "iso:country":"BE",
    "sg:address":"Chrysantenstraat 59b",
    "sg:city":"Merelbeke",
    "sg:orig_category":"Airconditioning and ventilatie",
    "sg:phone":"+32 9 231 01 31",
    "sg:postcode":"9820",
    "sg:province":"Oost-Vlaanderen",
    "wof:name":"Ventomatic",
    "wof:placetype":"venue"
},
  "geometry": {"coordinates":[3.7556579113,51.0016860962],"type":"Point"}
}