{
  "type": "Feature",
  "properties": {
    "iso:country":"BE",
    "sg:address":"Walstraat 25",
    "sg:city":"Oostkamp",
    "sg:classifiers":[
        {
            "category":"Shopping",
            "subcategory":"Discount & Variety Stores",
            "type":"Retail Goods"
        }
    ],
    "sg:phone":"+32 50 39 00 84",
    "sg:postcode":"8020",
    "sg:province":"West-Vlaanderen",
    "sg:tags":[
        "shop",
        "clearers",
        "curiosity",
        "furniture"
    ],
    "wof:name":"Desmet Pol",
    "wof:placetype":"venue"
},
  "geometry": {"coordinates":[3.2335479259,51.1530075073],"type":"Point"}
}