{
  "type": "Feature",
  "properties": {
    "iso:country":"BE",
    "sg:address":"Cornellekestraat 15",
    "sg:city":"Steenokkerzeel",
    "sg:orig_category":"Eclairage et \u00e9quipements du foyer",
    "sg:phone":"+32 2 759 51 57",
    "sg:postcode":"1820",
    "sg:province":"Vlaams-Brabant",
    "wof:name":"Studio R.l.",
    "wof:placetype":"venue"
},
  "geometry": {"coordinates":[4.5162777901,50.9234848022],"type":"Point"}
}