{
  "type": "Feature",
  "properties": {
    "addr:full":"Aarschotsesteenweg 132 Rotselaar Vlaams-Brabant 3111",
    "addr:housenumber":"132",
    "addr:postcode":"3111",
    "addr:street":"Aarschotsesteenweg",
    "iso:country":"BE",
    "sg:address":"Aarschotsesteenweg 132",
    "sg:city":"Rotselaar",
    "sg:orig_category":"M\u00e9decins and sp\u00e9cialistes",
    "sg:phone":"+32 16 58 90 59",
    "sg:postcode":"3111",
    "sg:province":"Vlaams-Brabant",
    "wof:name":"Sofie Nackaerts",
    "wof:placetype":"venue"
},
  "geometry": {"coordinates":[4.7498679161,50.9464607239],"type":"Point"}
}