{
  "type": "Feature",
  "properties": {
    "addr:full":"Molenstraat 172 Eeklo Oost-Vlaanderen 9900",
    "addr:housenumber":"172",
    "addr:postcode":"9900",
    "addr:street":"Molenstraat",
    "iso:country":"BE",
    "sg:address":"Molenstraat 172",
    "sg:city":"Eeklo",
    "sg:classifiers":[
        {
            "category":"Building & Trades",
            "subcategory":"Pest Control",
            "type":"Services"
        }
    ],
    "sg:phone":"+32 9 327 01 81",
    "sg:postcode":"9900",
    "sg:province":"Oost-Vlaanderen",
    "sg:tags":[
        "painting",
        "contractor"
    ],
    "wof:name":"Decor-paint J & B",
    "wof:placetype":"venue"
},
  "geometry": {"coordinates":[3.5580070019,51.1891326904],"type":"Point"}
}