{
  "type": "Feature",
  "properties": {
    "addr:full":"Chauss\u00e9e De Redemont 153 La Louvi\u00e8re (haine-saint-pierre) Hainaut 7100",
    "addr:housenumber":"153",
    "addr:postcode":"7100",
    "addr:street":"Chausse\u0301E De Redemont",
    "iso:country":"BE",
    "sg:address":"Chauss\u00e9e De Redemont 153",
    "sg:city":"La Louvi\u00e8re (haine-saint-pierre)",
    "sg:classifiers":[
        {
            "category":"Professional",
            "subcategory":"Lawyer & Legal Services",
            "type":"Services"
        }
    ],
    "sg:phone":"+32 64 21 34 40",
    "sg:postcode":"7100",
    "sg:province":"Hainaut",
    "wof:name":"Doclot A",
    "wof:placetype":"venue"
},
  "geometry": {"coordinates":[4.2071900368,50.4667510986],"type":"Point"}
}