{
  "type": "Feature",
  "properties": {
    "iso:country":"BE",
    "sg:address":"Drinkteilstraat 29bb",
    "sg:city":"Geetbets",
    "sg:orig_category":"Boekhouders",
    "sg:phone":"+32 11 58 87 54",
    "sg:postcode":"3450",
    "sg:province":"Vlaams-Brabant",
    "wof:name":"L. Trekels",
    "wof:placetype":"venue"
},
  "geometry": {"coordinates":[5.1084327698,50.8948936462],"type":"Point"}
}