{
  "type": "Feature",
  "properties": {
    "addr:full":"Rue Des Six-bras 33 Profondeville Namur 5170",
    "addr:housenumber":"33",
    "addr:postcode":"5170",
    "addr:street":"Rue Des Six-Bras",
    "iso:country":"BE",
    "sg:address":"Rue Des Six-bras 33",
    "sg:city":"Profondeville",
    "sg:orig_category":"Charpentes and couvertures. Plomberie, chauffage and installations sanitaires",
    "sg:phone":"+32 81 43 44 16",
    "sg:postcode":"5170",
    "sg:province":"Namur",
    "wof:name":"Jean-philippe Diz Villanueva",
    "wof:placetype":"venue"
},
  "geometry": {"coordinates":[4.8030409813,50.387714386],"type":"Point"}
}