{
  "type": "Feature",
  "properties": {
    "iso:country":"BE",
    "sg:address":"Rue Du Bourdon 71ba",
    "sg:city":"Ukkel/uccle",
    "sg:orig_category":"D\u00e9taillants en pi\u00e8ces and accessoires de voitures. R\u00e9cup\u00e9ration de mati\u00e8res m\u00e9talliques recyclables ",
    "sg:phone":"+32 2 376 01 69",
    "sg:postcode":"1180",
    "sg:province":"Bruxelles-Capitale",
    "wof:name":"Yellow Submarine",
    "wof:placetype":"venue"
},
  "geometry": {"coordinates":[4.3316659927,50.7853889465],"type":"Point"}
}