{
  "type": "Feature",
  "properties": {
    "iso:country":"BE",
    "sg:address":"Mudakkers 17",
    "sg:city":"Lommel",
    "sg:orig_category":"Verlichting and huishoudartikelen",
    "sg:phone":"+32 11 55 18 54",
    "sg:postcode":"3920",
    "sg:province":"Limburg",
    "wof:name":"Cartofolie",
    "wof:placetype":"venue"
},
  "geometry": {"coordinates":[5.3108038902,51.2308311462],"type":"Point"}
}