{
  "type": "Feature",
  "properties": {
    "addr:full":"Rue Des Cren\u00c9es 34 Burdinne Li\u00e8ge 4210",
    "addr:housenumber":"34",
    "addr:postcode":"4210",
    "addr:street":"Rue Des Crene\u0301Es",
    "iso:country":"BE",
    "sg:address":"Rue Des Cren\u00c9es 34",
    "sg:city":"Burdinne",
    "sg:orig_category":"Agences immobili\u00e8res",
    "sg:phone":"+32 85 71 27 77",
    "sg:postcode":"4210",
    "sg:province":"Li\u00e8ge",
    "wof:name":"Antoinette Loumaye",
    "wof:placetype":"venue"
},
  "geometry": {"coordinates":[5.1293702126,50.5687446594],"type":"Point"}
}