{
  "type": "Feature",
  "properties": {
    "addr:full":"Rue Jean Fran\u00c7ois 24 Huy Li\u00e8ge 4500",
    "addr:housenumber":"24",
    "addr:postcode":"4500",
    "addr:street":"Rue Jean Franc\u0327Ois",
    "iso:country":"BE",
    "sg:address":"Rue Jean Fran\u00c7ois 24",
    "sg:city":"Huy",
    "sg:orig_category":"Jardinage",
    "sg:phone":"+32 85 25 08 66",
    "sg:postcode":"4500",
    "sg:province":"Li\u00e8ge",
    "wof:name":"Bernard Pierre",
    "wof:placetype":"venue"
},
  "geometry": {"coordinates":[5.2262701988,50.5102996826],"type":"Point"}
}