{
  "type": "Feature",
  "properties": {
    "iso:country":"BE",
    "sg:address":"Zeedijk-het Zoute 488",
    "sg:city":"Knokke-heist (knokke)",
    "sg:orig_category":"Non-Classified Establishments",
    "sg:phone":"+32 50 62 38 00",
    "sg:postcode":"8300",
    "sg:province":"West-Vlaanderen",
    "wof:name":"C & T",
    "wof:placetype":"venue"
},
  "geometry": {"coordinates":[3.3267199993,51.3504714966],"type":"Point"}
}