{
  "type": "Feature",
  "properties": {
    "addr:full":"Zwarte Zusterslaan 43 Maldegem Oost-Vlaanderen 9990",
    "addr:housenumber":"43",
    "addr:postcode":"9990",
    "addr:street":"Zusterslaan",
    "iso:country":"BE",
    "sg:address":"Zwarte Zusterslaan 43",
    "sg:city":"Maldegem",
    "sg:classifiers":[
        {
            "category":"Professional",
            "subcategory":"Management & Consulting",
            "type":"Services"
        }
    ],
    "sg:phone":"+32 50 71 80 34",
    "sg:postcode":"9990",
    "sg:province":"Oost-Vlaanderen",
    "sg:tags":[
        "-",
        "processing",
        "data",
        "consultant"
    ],
    "wof:name":"Claeys Consult",
    "wof:placetype":"venue"
},
  "geometry": {"coordinates":[3.4523251057,51.206401825],"type":"Point"}
}