{
  "type": "Feature",
  "properties": {
    "addr:full":"Alfons Dessenislaan 5 Sint-martens-latem Oost-Vlaanderen 9830",
    "addr:housenumber":"5",
    "addr:postcode":"9830",
    "addr:street":"Dessenislaan",
    "iso:country":"BE",
    "sg:address":"Alfons Dessenislaan 5",
    "sg:city":"Sint-martens-latem",
    "sg:classifiers":[
        {
            "category":"Professional",
            "subcategory":"Art Services",
            "type":"Services"
        }
    ],
    "sg:phone":"+32 475 54 41 10",
    "sg:postcode":"9830",
    "sg:province":"Oost-Vlaanderen",
    "sg:tags":[
        "designer",
        "display"
    ],
    "wof:name":"Derby Schelstraete",
    "wof:placetype":"venue"
},
  "geometry": {"coordinates":[3.629776001,50.9990921021],"type":"Point"}
}