{
  "type": "Feature",
  "properties": {
    "iso:country":"BE",
    "sg:address":"Stationsstraat 18",
    "sg:city":"Ramsel",
    "sg:orig_category":"Geschenken and souvenirs Textiel",
    "sg:phone":"+32 16 69 73 44",
    "sg:postcode":"2230",
    "sg:province":"Antwerpen",
    "wof:name":"\u00b4t Kreatiefje",
    "wof:placetype":"venue"
},
  "geometry": {"coordinates":[4.831867218,51.0320739746],"type":"Point"}
}