{
  "type": "Feature",
  "properties": {
    "addr:full":"Geldenaaksebaan 326 Leuven Vlaams-Brabant 3001",
    "addr:housenumber":"326",
    "addr:postcode":"3001",
    "addr:street":"Geldenaaksebaan",
    "iso:country":"BE",
    "sg:address":"Geldenaaksebaan 326",
    "sg:city":"Leuven",
    "sg:orig_category":"Public-relationsbureaus",
    "sg:phone":"+32 16 40 69 89",
    "sg:postcode":"3001",
    "sg:province":"Vlaams-Brabant",
    "wof:name":"Bureau Cats Consult",
    "wof:placetype":"venue"
},
  "geometry": {"coordinates":[4.7159671783,50.859577179],"type":"Point"}
}