{
  "type": "Feature",
  "properties": {
    "iso:country":"BE",
    "sg:address":"Nisramont 33",
    "sg:city":"La Roche-en-ardenne",
    "sg:orig_category":"Eleveurs de bovins",
    "sg:phone":"+32 84 43 31 38",
    "sg:postcode":"6983",
    "sg:province":"Luxembourg",
    "wof:name":"Maboge Michel Et Gilles",
    "wof:placetype":"venue"
},
  "geometry": {"coordinates":[5.6033000946,50.1450004578],"type":"Point"}
}