{
  "type": "Feature",
  "properties": {
    "iso:country":"BE",
    "sg:address":"Rue De Marvis 20b2",
    "sg:city":"Tournai",
    "sg:orig_category":"Mat\u00e9riel pour plomberie and chauffage Plomberie, chauffage and installations sanitaires. Mat\u00e9riaux d",
    "sg:phone":"+32 69 22 64 42",
    "sg:postcode":"7500",
    "sg:province":"Hainaut",
    "wof:name":"Ets. Leclercq M.",
    "wof:placetype":"venue"
},
  "geometry": {"coordinates":[3.3995149136,50.6073913574],"type":"Point"}
}