{
  "type": "Feature",
  "properties": {
    "addr:full":"Heufkensstraat 113 Zwalm Oost-Vlaanderen 9630",
    "addr:housenumber":"113",
    "addr:postcode":"9630",
    "addr:street":"Heufkensstraat;Oost-Vlaanderen",
    "iso:country":"BE",
    "sg:address":"Heufkensstraat 113",
    "sg:city":"Zwalm",
    "sg:orig_category":"Boekhouders",
    "sg:phone":"+32 55 49 82 59",
    "sg:postcode":"9630",
    "sg:province":"Oost-Vlaanderen",
    "wof:name":"M.l. Michiels",
    "wof:placetype":"venue"
},
  "geometry": {"coordinates":[3.70282197,50.8735351562],"type":"Point"}
}