{
  "type": "Feature",
  "properties": {
    "addr:full":"Stationstraat 37 Dilbeek Vlaams-Brabant 1702",
    "addr:housenumber":"37",
    "addr:postcode":"1702",
    "addr:street":"Stationstraat",
    "iso:country":"BE",
    "sg:address":"Stationstraat 37",
    "sg:city":"Dilbeek",
    "sg:orig_category":"Informaticaconsulenten",
    "sg:phone":"+32 2 463 52 78",
    "sg:postcode":"1702",
    "sg:province":"Vlaams-Brabant",
    "wof:name":"Distrimax",
    "wof:placetype":"venue"
},
  "geometry": {"coordinates":[4.2765498161,50.8710403442],"type":"Point"}
}