{
  "type": "Feature",
  "properties": {
    "iso:country":"BE",
    "sg:address":"Rooberg 15",
    "sg:city":"Oosterzele (landskouter)",
    "sg:classifiers":[
        {
            "category":"Real Estate",
            "subcategory":"Architect",
            "type":"Services"
        }
    ],
    "sg:phone":"+32 9 362 50 94",
    "sg:postcode":"9860",
    "sg:province":"Oost-Vlaanderen",
    "wof:name":"Van Den Driessche J",
    "wof:placetype":"venue"
},
  "geometry": {"coordinates":[3.8017148972,50.9646720886],"type":"Point"}
}