{
  "type": "Feature",
  "properties": {
    "iso:country":"BE",
    "sg:address":"Route De Philippeville 124",
    "sg:city":"Gerpinnes",
    "sg:orig_category":"Maisons de repos and r\u00e9sidences",
    "sg:phone":"+32 71 36 08 50",
    "sg:postcode":"6280",
    "sg:province":"Hainaut",
    "wof:name":"Les Amarantes Ii",
    "wof:placetype":"venue"
},
  "geometry": {"coordinates":[4.4724001884,50.3461799622],"type":"Point"}
}