{
  "type": "Feature",
  "properties": {
    "iso:country":"BE",
    "sg:address":"Leistraat 52a",
    "sg:city":"Kasterlee (lichtaart)",
    "sg:classifiers":[
        {
            "category":"Insurance",
            "subcategory":"Insurance Agent",
            "type":"Services"
        }
    ],
    "sg:phone":"+32 14 55 61 70",
    "sg:postcode":"2460",
    "sg:province":"Antwerpen",
    "sg:tags":[
        "broker"
    ],
    "wof:name":"Spruyt Nv",
    "wof:placetype":"venue"
},
  "geometry": {"coordinates":[4.9192042351,51.2246627808],"type":"Point"}
}