{
  "type": "Feature",
  "properties": {
    "addr:full":"Rue D'en-bas 7 Yvoir Namur 5530",
    "addr:housenumber":"7",
    "addr:postcode":"5530",
    "addr:street":"Rue D'En-Bas",
    "iso:country":"BE",
    "sg:address":"Rue D'en-bas 7",
    "sg:city":"Yvoir",
    "sg:orig_category":"M\u00e9decins and sp\u00e9cialistes",
    "sg:phone":"+32 83 69 99 30",
    "sg:postcode":"5530",
    "sg:province":"Namur",
    "wof:name":"Thierry Botilde",
    "wof:placetype":"venue"
},
  "geometry": {"coordinates":[4.9083228111,50.352558136],"type":"Point"}
}