{
  "type": "Feature",
  "properties": {
    "addr:full":"Kerkstraat 1 De Panne West-Vlaanderen 8660",
    "addr:housenumber":"1",
    "addr:postcode":"8660",
    "addr:street":"Kerkstraat",
    "iso:country":"BE",
    "sg:address":"Kerkstraat 1",
    "sg:city":"De Panne",
    "sg:orig_category":"V\u00eatements pour Dames. V\u00eatements de mariage and c\u00e9r\u00e9monies",
    "sg:phone":"+32 58 41 58 00",
    "sg:postcode":"8660",
    "sg:province":"West-Vlaanderen",
    "wof:name":"Huis Santolina",
    "wof:placetype":"venue"
},
  "geometry": {"coordinates":[2.5889110565,51.0952758789],"type":"Point"}
}