{
  "type": "Feature",
  "properties": {
    "addr:full":"Rue De L'eglise 23 Ouffet (warz\u00e9e) Li\u00e8ge 4590",
    "addr:housenumber":"23",
    "addr:postcode":"4590",
    "addr:street":"Rue De L'Eglise;Warze\u0301E",
    "iso:country":"BE",
    "sg:address":"Rue De L'eglise 23",
    "sg:city":"Ouffet (warz\u00e9e)",
    "sg:classifiers":[
        {
            "category":"Health Services",
            "subcategory":"Health Practitioner",
            "type":"Services"
        }
    ],
    "sg:phone":"+32 495 21 87 02",
    "sg:postcode":"4590",
    "sg:province":"Li\u00e8ge",
    "sg:tags":[
        "physiotherapist"
    ],
    "wof:name":"Rossion Pascal",
    "wof:placetype":"venue"
},
  "geometry": {"coordinates":[5.4318380356,50.4513282776],"type":"Point"}
}