{
  "type": "Feature",
  "properties": {
    "addr:full":"Kruishuisstraat 66 Turnhout Antwerpen 2300",
    "addr:housenumber":"66",
    "addr:postcode":"2300",
    "addr:street":"Kruishuisstraat",
    "iso:country":"BE",
    "sg:address":"Kruishuisstraat 66",
    "sg:city":"Turnhout",
    "sg:orig_category":"Articles pour b\u00e9b\u00e9s. V\u00eatements pour b\u00e9b\u00e9s and enfants",
    "sg:phone":"+32 14 41 91 53",
    "sg:postcode":"2300",
    "sg:province":"Antwerpen",
    "wof:name":"Babywereld",
    "wof:placetype":"venue"
},
  "geometry": {"coordinates":[4.9406399727,51.3197860718],"type":"Point"}
}