{
  "type": "Feature",
  "properties": {
    "iso:country":"BE",
    "sg:address":"Avenue Louise 140 Box 7",
    "sg:city":"Bruxelles (ixelles)",
    "sg:classifiers":[
        {
            "category":"Insurance",
            "subcategory":"Insurance Agent",
            "type":"Services"
        }
    ],
    "sg:phone":"+32 2 643 63 63",
    "sg:postcode":"1050",
    "sg:province":"Bruxelles-Capitale",
    "sg:tags":[
        "factoring"
    ],
    "wof:name":"Eurofactor Sa",
    "wof:placetype":"venue"
},
  "geometry": {"coordinates":[4.3572201729,50.8337287903],"type":"Point"}
}