{
  "type": "Feature",
  "properties": {
    "addr:full":"Attenhovenstraat 184 Landen (attenhoven) Vlaams-Brabant 3404",
    "addr:housenumber":"184",
    "addr:postcode":"3404",
    "addr:street":"Attenhovenstraat",
    "iso:country":"BE",
    "sg:address":"Attenhovenstraat 184",
    "sg:city":"Landen (attenhoven)",
    "sg:classifiers":[
        {
            "category":"Personal",
            "subcategory":"Beauty Salon",
            "type":"Services"
        }
    ],
    "sg:phone":"+32 11 88 43 25",
    "sg:postcode":"3404",
    "sg:province":"Vlaams-Brabant",
    "sg:tags":[
        "lady",
        "-",
        "hairdressing"
    ],
    "wof:name":"Marleen",
    "wof:placetype":"venue"
},
  "geometry": {"coordinates":[5.0929851532,50.7672653198],"type":"Point"}
}