{
  "type": "Feature",
  "properties": {
    "addr:full":"Rue Gospert 51 Eupen/eupen Li\u00e8ge 4700",
    "addr:housenumber":"51",
    "addr:postcode":"4700",
    "addr:street":"Rue Gospert",
    "iso:country":"BE",
    "sg:address":"Rue Gospert 51",
    "sg:city":"Eupen/eupen",
    "sg:orig_category":"Alimentation sp\u00e9cialis\u00e9e. Boucheries",
    "sg:phone":"+32 87 74 03 29",
    "sg:postcode":"4700",
    "sg:province":"Li\u00e8ge",
    "wof:name":"Johann Peissen",
    "wof:placetype":"venue"
},
  "geometry": {"coordinates":[6.034992218,50.6317672729],"type":"Point"}
}