{
  "type": "Feature",
  "properties": {
    "iso:country":"BE",
    "sg:address":"Rue De La Roue 21",
    "sg:city":"Brussel/bruxelles",
    "sg:orig_category":"Maatschappelijke dienstverlening",
    "sg:phone":"+32 2 511 29 90",
    "sg:postcode":"1000",
    "sg:province":"Bruxelles-Capitale",
    "wof:name":"Planning Marolles",
    "wof:placetype":"venue"
},
  "geometry": {"coordinates":[4.3457760811,50.8417243958],"type":"Point"}
}