{
  "type": "Feature",
  "properties": {
    "addr:full":"Weg Naar Zwartberg 172 Opglabbeek Limburg 3660",
    "addr:housenumber":"172",
    "addr:postcode":"3660",
    "addr:street":"Weg Naar Zwartberg",
    "iso:country":"BE",
    "sg:address":"Weg Naar Zwartberg 172",
    "sg:city":"Opglabbeek",
    "sg:orig_category":"Herstellingen and onderhoud van auto's",
    "sg:phone":"+32 89 85 32 94",
    "sg:postcode":"3660",
    "sg:province":"Limburg",
    "wof:name":"Carmine Lampariello",
    "wof:placetype":"venue"
},
  "geometry": {"coordinates":[5.5675649643,51.0396957397],"type":"Point"}
}