{
  "type": "Feature",
  "properties": {
    "iso:country":"BE",
    "sg:address":"Rue De L\u00b4auflette 4",
    "sg:city":"Mons",
    "sg:orig_category":"Verbruikerskredietinstellingen",
    "sg:phone":"+32 65 34 62 37",
    "sg:postcode":"7033",
    "sg:province":"Hainaut",
    "wof:name":"D. Dartevelle",
    "wof:placetype":"venue"
},
  "geometry": {"coordinates":[3.9253261089,50.4366378784],"type":"Point"}
}