{
  "type": "Feature",
  "properties": {
    "addr:full":"Sint-bernardsesteenweg 876 Antwerpen Antwerpen 2660",
    "addr:housenumber":"876",
    "addr:postcode":"2660",
    "addr:street":"Sint-Bernardsesteenweg",
    "iso:country":"BE",
    "sg:address":"Sint-bernardsesteenweg 876",
    "sg:city":"Antwerpen",
    "sg:orig_category":"Rev\u00eatements de sols and murs",
    "sg:phone":"+32 3 827 66 96",
    "sg:postcode":"2660",
    "sg:province":"Antwerpen",
    "wof:name":"Arba",
    "wof:placetype":"venue"
},
  "geometry": {"coordinates":[4.3397898674,51.1732788086],"type":"Point"}
}