{
  "type": "Feature",
  "properties": {
    "addr:full":"Opzichterstraat 116 Bruxelles-molenbeek-saint-jean Bruxelles-Capitale 1080",
    "addr:housenumber":"116",
    "addr:postcode":"1080",
    "addr:street":"Opzichterstraat",
    "iso:country":"BE",
    "sg:address":"Opzichterstraat 116",
    "sg:city":"Bruxelles-molenbeek-saint-jean",
    "sg:orig_category":"Artsen and specialisten Medische and orthopedische apparaten Paramedische behandelingen",
    "sg:phone":"+32 2 427 68 58",
    "sg:postcode":"1080",
    "sg:province":"Bruxelles-Capitale",
    "wof:name":"Guillaume Orthoprotec",
    "wof:placetype":"venue"
},
  "geometry": {"coordinates":[4.3408999443,50.861328125],"type":"Point"}
}