{
  "type": "Feature",
  "properties": {
    "addr:full":"Centrum Zuid 1527 Houthalen-helchteren Limburg 3530",
    "addr:housenumber":"1527",
    "addr:postcode":"3530",
    "addr:street":"Centrum Zuid",
    "iso:country":"BE",
    "sg:address":"Centrum Zuid 1527",
    "sg:city":"Houthalen-helchteren",
    "sg:orig_category":"R\u00e9alisation de programmes and logiciels",
    "sg:phone":"+32 11 52 67 36",
    "sg:postcode":"3530",
    "sg:province":"Limburg",
    "wof:name":"A.s.q.",
    "wof:placetype":"venue"
},
  "geometry": {"coordinates":[5.3624520302,51.0265808105],"type":"Point"}
}