{
  "type": "Feature",
  "properties": {
    "addr:full":"Oudebaan 244b1 Leuven Vlaams-Brabant 3000",
    "addr:housenumber":"244b1",
    "addr:postcode":"3000",
    "addr:street":"Oudebaan",
    "iso:country":"BE",
    "sg:address":"Oudebaan 244b1",
    "sg:city":"Leuven",
    "sg:orig_category":"Animations diverses",
    "sg:phone":"+32 16 35 67 00",
    "sg:postcode":"3000",
    "sg:province":"Vlaams-Brabant",
    "wof:name":"S. Miermans",
    "wof:placetype":"venue"
},
  "geometry": {"coordinates":[4.7411899567,50.8644142151],"type":"Point"}
}