{
  "type": "Feature",
  "properties": {
    "iso:country":"BE",
    "sg:address":"Lindekensbaan 47",
    "sg:city":"Nijlen",
    "sg:orig_category":"Juwelen and edelstenen Fab",
    "sg:phone":"+32 3 480 47 42",
    "sg:postcode":"2560",
    "sg:province":"Antwerpen",
    "wof:name":"Jozef Vervoort",
    "wof:placetype":"venue"
},
  "geometry": {"coordinates":[4.6209478378,51.1530342102],"type":"Point"}
}