{
  "type": "Feature",
  "properties": {
    "iso:country":"BE",
    "sg:address":"Lampestraat 59",
    "sg:city":"Kortrijk",
    "sg:orig_category":"Fruitteelt",
    "sg:phone":"+32 56 41 36 07",
    "sg:postcode":"8510",
    "sg:province":"West-Vlaanderen",
    "wof:name":"Chiers Gilbert & Marc",
    "wof:placetype":"venue"
},
  "geometry": {"coordinates":[3.2457211018,50.7767715454],"type":"Point"}
}