{
  "type": "Feature",
  "properties": {
    "iso:country":"BE",
    "sg:address":"Avenue T\u00e9l\u00e9maque 33",
    "sg:city":"Bruxelles (forest)",
    "sg:classifiers":[
        {
            "category":"Communications",
            "subcategory":"Radio Station",
            "type":"Services"
        }
    ],
    "sg:phone":"+32 2 344 18 10",
    "sg:postcode":"1190",
    "sg:province":"Bruxelles-Capitale",
    "sg:tags":[
        "local"
    ],
    "wof:name":"Fun Radio (fm Developpement)",
    "wof:placetype":"venue"
},
  "geometry": {"coordinates":[4.3312330246,50.8125762939],"type":"Point"}
}