{
  "type": "Feature",
  "properties": {
    "addr:full":"Avenue Reine Astrid 159 Spa Li\u00e8ge 4900",
    "addr:housenumber":"159",
    "addr:postcode":"4900",
    "addr:street":"Avenue Reine Astrid",
    "iso:country":"BE",
    "sg:address":"Avenue Reine Astrid 159",
    "sg:city":"Spa",
    "sg:classifiers":[
        {
            "category":"Autos & Motor Vehicles",
            "subcategory":"Fuel & Gas Station",
            "type":"Retail Goods"
        }
    ],
    "sg:phone":"+32 87 77 50 80",
    "sg:postcode":"4900",
    "sg:province":"Li\u00e8ge",
    "sg:tags":[
        "stations-service",
        "carburants"
    ],
    "wof:name":"Shell",
    "wof:placetype":"venue"
},
  "geometry": {"coordinates":[5.8465719223,50.4902153015],"type":"Point"}
}