{
  "type": "Feature",
  "properties": {
    "addr:full":"Bredabaan 93bc Wuustwezel Antwerpen 2990",
    "addr:housenumber":"93bc",
    "addr:postcode":"2990",
    "addr:street":"Bredabaan",
    "iso:country":"BE",
    "sg:address":"Bredabaan 93bc",
    "sg:city":"Wuustwezel",
    "sg:orig_category":"Herstellingen and onderhoud van auto's",
    "sg:phone":"+32 3 669 82 33",
    "sg:postcode":"2990",
    "sg:province":"Antwerpen",
    "wof:name":"Jan Bevers",
    "wof:placetype":"venue"
},
  "geometry": {"coordinates":[4.6180868149,51.4175949097],"type":"Point"}
}