{
  "type": "Feature",
  "properties": {
    "addr:full":"Schaffensestraat 5 Diest Vlaams-Brabant 3290",
    "addr:housenumber":"5",
    "addr:postcode":"3290",
    "addr:street":"Schaffensestraat",
    "iso:country":"BE",
    "sg:address":"Schaffensestraat 5",
    "sg:city":"Diest",
    "sg:classifiers":[
        {
            "category":"Shopping",
            "subcategory":"Computers & Home Electronics",
            "type":"Retail Goods"
        }
    ],
    "sg:phone":"+32 13 31 15 86",
    "sg:postcode":"3290",
    "sg:province":"Vlaams-Brabant",
    "sg:tags":[
        "-",
        "television",
        "radio"
    ],
    "wof:name":"Vandepoel",
    "wof:placetype":"venue"
},
  "geometry": {"coordinates":[5.0564031601,50.9877433777],"type":"Point"}
}