{
  "type": "Feature",
  "properties": {
    "iso:country":"BE",
    "sg:address":"Place Albert-ier 8",
    "sg:city":"Dinant",
    "sg:classifiers":[
        {
            "category":"Restaurant",
            "type":"Food & Drink"
        }
    ],
    "sg:phone":"+32 82 22 24 31",
    "sg:postcode":"5500",
    "sg:province":"Namur",
    "sg:tags":[
        "caf\u00e9s"
    ],
    "wof:name":"Taverne W\u00c9pion",
    "wof:placetype":"venue"
},
  "geometry": {"coordinates":[4.9138069153,50.2567214966],"type":"Point"}
}