{
  "type": "Feature",
  "properties": {
    "iso:country":"BE",
    "sg:address":"Monthouet 23",
    "sg:city":"Stoumont",
    "sg:orig_category":"Boekhouders",
    "sg:phone":"+32 80 78 62 39",
    "sg:postcode":"4987",
    "sg:province":"Li\u00e8ge",
    "wof:name":"Stephan Brandt",
    "wof:placetype":"venue"
},
  "geometry": {"coordinates":[5.8138952255,50.4203224182],"type":"Point"}
}