{
  "type": "Feature",
  "properties": {
    "iso:country":"BE",
    "sg:address":"Balgerhoekstraat 4",
    "sg:city":"Wingene",
    "sg:classifiers":[
        {
            "category":"Recreation",
            "subcategory":"Amusement Park",
            "type":"Entertainment"
        }
    ],
    "sg:phone":"+32 51 46 44 86",
    "sg:postcode":"8750",
    "sg:province":"West-Vlaanderen",
    "sg:tags":[
        "attraction",
        "-",
        "sale",
        "fair",
        "hiring"
    ],
    "wof:name":"Andy's Kids-fun",
    "wof:placetype":"venue"
},
  "geometry": {"coordinates":[3.3209450245,51.066204071],"type":"Point"}
}