{
  "type": "Feature",
  "properties": {
    "addr:full":"Rue Maurice Van Rolleghem 32 Bruxelles (jette) Bruxelles-Capitale 1090",
    "addr:housenumber":"32",
    "addr:postcode":"1090",
    "addr:street":"Rue Maurice Van Rolleghem",
    "iso:country":"BE",
    "sg:address":"Rue Maurice Van Rolleghem 32",
    "sg:city":"Bruxelles (jette)",
    "sg:classifiers":[
        {
            "category":"Building & Trades",
            "subcategory":"Plumbing",
            "type":"Services"
        }
    ],
    "sg:phone":"+32 2 479 48 40",
    "sg:postcode":"1090",
    "sg:province":"Bruxelles-Capitale",
    "sg:tags":[
        "contractor"
    ],
    "wof:name":"Lucas M",
    "wof:placetype":"venue"
},
  "geometry": {"coordinates":[4.3221311569,50.8906402588],"type":"Point"}
}