{
  "type": "Feature",
  "properties": {
    "iso:country":"BE",
    "sg:address":"Grotstraat 14",
    "sg:city":"Bilzen",
    "sg:orig_category":"Antiek Vloer- and muurbekleding",
    "sg:phone":"+32 89 41 46 29",
    "sg:postcode":"3740",
    "sg:province":"Limburg",
    "wof:name":"Delarue",
    "wof:placetype":"venue"
},
  "geometry": {"coordinates":[5.4838609695,50.9040145874],"type":"Point"}
}