{
  "type": "Feature",
  "properties": {
    "iso:country":"BE",
    "sg:address":"Route De Hamoir 40",
    "sg:city":"Ferri\u00e8res (xhoris)",
    "sg:classifiers":[
        {
            "category":"Personal",
            "subcategory":"Beauty Salon",
            "type":"Services"
        }
    ],
    "sg:phone":"+32 4 369 14 85",
    "sg:postcode":"4190",
    "sg:province":"Li\u00e8ge",
    "sg:tags":[
        "lady",
        "-",
        "hairdressing"
    ],
    "wof:name":"Colette",
    "wof:placetype":"venue"
},
  "geometry": {"coordinates":[5.6015930176,50.4445152283],"type":"Point"}
}