{
  "type": "Feature",
  "properties": {
    "iso:country":"BE",
    "sg:address":"Avenue Du Chant D'oiseau 42",
    "sg:city":"Sint-pieters-woluwe/woluwe-saint-pierre",
    "sg:orig_category":"Action sociale avec h\u00e9bergement",
    "sg:phone":"+32 2 660 58 70",
    "sg:postcode":"1150",
    "sg:province":"Bruxelles-Capitale",
    "wof:name":"Mais.matern.chant Oiseau",
    "wof:placetype":"venue"
},
  "geometry": {"coordinates":[4.4166150093,50.8255844116],"type":"Point"}
}