{
  "type": "Feature",
  "properties": {
    "addr:full":"Goor 101 Kasterlee Antwerpen 2460",
    "addr:housenumber":"101",
    "addr:postcode":"2460",
    "addr:street":"Goor",
    "iso:country":"BE",
    "sg:address":"Goor 101",
    "sg:city":"Kasterlee",
    "sg:orig_category":"Rundveehouders",
    "sg:phone":"+32 14 85 24 69",
    "sg:postcode":"2460",
    "sg:province":"Antwerpen",
    "wof:name":"Herman Wens",
    "wof:placetype":"venue"
},
  "geometry": {"coordinates":[4.9482059479,51.2210540771],"type":"Point"}
}