{
  "type": "Feature",
  "properties": {
    "addr:full":"Markt 10 Balen Antwerpen 2490",
    "addr:housenumber":"10",
    "addr:postcode":"2490",
    "addr:street":"Markt",
    "iso:country":"BE",
    "sg:address":"Markt 10",
    "sg:city":"Balen",
    "sg:orig_category":"Banques and organismes de cr\u00e9dit",
    "sg:phone":"+32 14 81 19 37",
    "sg:postcode":"2490",
    "sg:province":"Antwerpen",
    "wof:name":"Fortis",
    "wof:placetype":"venue"
},
  "geometry": {"coordinates":[5.1678180695,51.1709976196],"type":"Point"}
}