{
  "type": "Feature",
  "properties": {
    "iso:country":"BE",
    "sg:address":"Rue Du Piroy 17",
    "sg:city":"Jodoigne",
    "sg:classifiers":[
        {
            "category":"Personal",
            "subcategory":"Beauty Salon",
            "type":"Services"
        }
    ],
    "sg:phone":"+32 10 81 07 48",
    "sg:postcode":"1370",
    "sg:province":"Brabant Wallon",
    "sg:tags":[
        "de",
        "coiffure"
    ],
    "wof:name":"Coiffure Francis",
    "wof:placetype":"venue"
},
  "geometry": {"coordinates":[4.8646759987,50.7219085693],"type":"Point"}
}