{
  "type": "Feature",
  "properties": {
    "addr:full":"Westerse Clyttestraat 6 Poperinge West-Vlaanderen 8970",
    "addr:housenumber":"6",
    "addr:postcode":"8970",
    "addr:street":"Westerse Clyttestraat",
    "iso:country":"BE",
    "sg:address":"Westerse Clyttestraat 6",
    "sg:city":"Poperinge",
    "sg:orig_category":"Entretien and r\u00e9parations de voitures. D\u00e9taillants en pi\u00e8ces and accessoires de voitures. Pi\u00e8ces and",
    "sg:phone":"+32 57 21 74 01",
    "sg:postcode":"8970",
    "sg:province":"West-Vlaanderen",
    "wof:name":"J.p.c. Belgium",
    "wof:placetype":"venue"
},
  "geometry": {"coordinates":[2.7736849785,50.8121757507],"type":"Point"}
}