{
  "type": "Feature",
  "properties": {
    "addr:full":"Kortrijkstraat 121 Zwevegem West-Vlaanderen 8550",
    "addr:housenumber":"121",
    "addr:postcode":"8550",
    "addr:street":"Kortrijkstraat",
    "iso:country":"BE",
    "sg:address":"Kortrijkstraat 121",
    "sg:city":"Zwevegem",
    "sg:classifiers":[
        {
            "category":"Retail",
            "subcategory":"Auto Repair",
            "type":"Services"
        }
    ],
    "sg:phone":"+32 56 75 61 31",
    "sg:postcode":"8550",
    "sg:province":"West-Vlaanderen",
    "sg:tags":[
        "garage",
        "mainten",
        "-",
        "truck"
    ],
    "wof:name":"Vantieghem Bus & Coach",
    "wof:placetype":"venue"
},
  "geometry": {"coordinates":[3.3189170361,50.8146476746],"type":"Point"}
}