{
  "type": "Feature",
  "properties": {
    "iso:country":"BE",
    "sg:address":"Vaartstraat 59",
    "sg:city":"Beerse",
    "sg:orig_category":"D\u00e9chets and d\u00e9bris Gr",
    "sg:phone":"+32 14 60 95 11",
    "sg:postcode":"2340",
    "sg:province":"Antwerpen",
    "wof:name":"Metallo Chimique Intern.",
    "wof:placetype":"venue"
},
  "geometry": {"coordinates":[4.8235940933,51.323513031],"type":"Point"}
}