{
  "type": "Feature",
  "properties": {
    "addr:full":"Lindestraat 9 Gavere Oost-Vlaanderen 9890",
    "addr:housenumber":"9",
    "addr:postcode":"9890",
    "addr:street":"Lindestraat",
    "iso:country":"BE",
    "sg:address":"Lindestraat 9",
    "sg:city":"Gavere",
    "sg:orig_category":"Installatie van houten of kunststof schrijnwerk Woningbouw",
    "sg:phone":"+32 9 362 58 52",
    "sg:postcode":"9890",
    "sg:province":"Oost-Vlaanderen",
    "wof:name":"Dirk De Graeve",
    "wof:placetype":"venue"
},
  "geometry": {"coordinates":[3.6588599682,50.9283752441],"type":"Point"}
}