{
  "type": "Feature",
  "properties": {
    "addr:full":"Torhoutsesteenweg 222 Zedelgem West-Vlaanderen 8210",
    "addr:housenumber":"222",
    "addr:postcode":"8210",
    "addr:street":"Torhoutsesteenweg",
    "iso:country":"BE",
    "sg:address":"Torhoutsesteenweg 222",
    "sg:city":"Zedelgem",
    "sg:classifiers":[
        {
            "category":"Home & Garden",
            "subcategory":"Garden Supply",
            "type":"Retail Goods"
        }
    ],
    "sg:phone":"+32 50 25 01 02",
    "sg:postcode":"8210",
    "sg:province":"West-Vlaanderen",
    "sg:tags":[
        "lawn",
        "mower"
    ],
    "wof:name":"Stiga Benelux",
    "wof:placetype":"venue"
},
  "geometry": {"coordinates":[3.1576468945,51.1365127563],"type":"Point"}
}