{
  "type": "Feature",
  "properties": {
    "addr:full":"Plaats 6 Menen (rekkem) West-Vlaanderen 8930",
    "addr:housenumber":"6",
    "addr:postcode":"8930",
    "addr:street":"Plaats",
    "iso:country":"BE",
    "sg:address":"Plaats 6",
    "sg:city":"Menen (rekkem)",
    "sg:classifiers":[
        {
            "category":"Education",
            "subcategory":"School",
            "type":"Public Place"
        }
    ],
    "sg:phone":"+32 56 41 57 40",
    "sg:postcode":"8930",
    "sg:province":"West-Vlaanderen",
    "sg:tags":[
        "supply"
    ],
    "wof:name":"V H",
    "wof:placetype":"venue"
},
  "geometry": {"coordinates":[3.1634559631,50.7834243774],"type":"Point"}
}