{
  "type": "Feature",
  "properties": {
    "iso:country":"BE",
    "sg:address":"Rue Des P\u00e9lissiers 14",
    "sg:city":"Binche",
    "sg:classifiers":[
        {
            "category":"Health Services",
            "subcategory":"Dentist",
            "type":"Services"
        }
    ],
    "sg:phone":"+32 64 33 38 39",
    "sg:postcode":"7130",
    "sg:province":"Hainaut",
    "wof:name":"Dumont Marcelle",
    "wof:placetype":"venue"
},
  "geometry": {"coordinates":[4.1747770309,50.4155845642],"type":"Point"}
}