{
  "type": "Feature",
  "properties": {
    "iso:country":"BE",
    "sg:address":"Stationsstraat 7",
    "sg:city":"Kortrijk",
    "sg:classifiers":[
        {
            "category":"Shopping",
            "subcategory":"Jewelry",
            "type":"Retail Goods"
        }
    ],
    "sg:phone":"+32 56 22 81 91",
    "sg:postcode":"8500",
    "sg:province":"West-Vlaanderen",
    "sg:tags":[
        "diamond",
        "-"
    ],
    "wof:name":"Fabrigold Juwelen Bvba",
    "wof:placetype":"venue"
},
  "geometry": {"coordinates":[3.2644910812,50.8257789612],"type":"Point"}
}