{
  "type": "Feature",
  "properties": {
    "iso:country":"BE",
    "sg:address":"Klein Terbankstraat Z/n",
    "sg:city":"Tildonk",
    "sg:classifiers":[
        {
            "category":"Utilities",
            "subcategory":"Cable",
            "type":"Services"
        }
    ],
    "sg:phone":"+32 16 61 81 81",
    "sg:postcode":"3150",
    "sg:province":"Vlaams-Brabant",
    "sg:tags":[
        "steel",
        "spring",
        "wire"
    ],
    "wof:name":"Trebos Duferco Ll Nv",
    "wof:placetype":"venue"
},
  "geometry": {"coordinates":[4.6619920731,50.9430656433],"type":"Point"}
}