{
  "type": "Feature",
  "properties": {
    "addr:full":"Rue Dreve-rouge 68 Lontzen Li\u00e8ge 4710",
    "addr:housenumber":"68",
    "addr:postcode":"4710",
    "addr:street":"Rue Dreve-Rouge",
    "iso:country":"BE",
    "sg:address":"Rue Dreve-rouge 68",
    "sg:city":"Lontzen",
    "sg:classifiers":[
        {
            "category":"Arena",
            "subcategory":"Sports Club",
            "type":"Entertainment"
        }
    ],
    "sg:phone":"+32 87 88 30 68",
    "sg:postcode":"4710",
    "sg:province":"Li\u00e8ge",
    "sg:tags":[
        "de"
    ],
    "wof:name":"Vbc St.joseph Welkenraedt",
    "wof:placetype":"venue"
},
  "geometry": {"coordinates":[5.9884829521,50.6685256958],"type":"Point"}
}