{
  "type": "Feature",
  "properties": {
    "iso:country":"BE",
    "sg:address":"Ten Beukenboom 27",
    "sg:city":"Ninove (appelterre-eichem)",
    "sg:classifiers":[
        {
            "category":"Professional",
            "type":"Services"
        }
    ],
    "sg:phone":"+32 54 31 73 17",
    "sg:postcode":"9400",
    "sg:province":"Oost-Vlaanderen",
    "sg:tags":[
        "industrial",
        "automation"
    ],
    "wof:name":"De Jonge Luc Bvba",
    "wof:placetype":"venue"
},
  "geometry": {"coordinates":[4.0232000351,50.8349113464],"type":"Point"}
}