{
  "type": "Feature",
  "properties": {
    "addr:full":"Parvis De La Trinit\u00c9 8 Ixelles Bruxelles-Capitale 1050",
    "addr:housenumber":"8",
    "addr:postcode":"1050",
    "addr:street":"Parvis De La Trinite\u0301",
    "iso:country":"BE",
    "sg:address":"Parvis De La Trinit\u00c9 8",
    "sg:city":"Ixelles",
    "sg:orig_category":"Agences de voyages",
    "sg:phone":"+32 2 537 11 00",
    "sg:postcode":"1050",
    "sg:province":"Bruxelles-Capitale",
    "wof:name":"Travex",
    "wof:placetype":"venue"
},
  "geometry": {"coordinates":[4.3586740494,50.8254318237],"type":"Point"}
}