{
  "type": "Feature",
  "properties": {
    "addr:full":"Lokerenbaan 220b1 Zele Oost-Vlaanderen 9240",
    "addr:housenumber":"220b1",
    "addr:postcode":"9240",
    "addr:street":"Lokerenbaan",
    "iso:country":"BE",
    "sg:address":"Lokerenbaan 220b1",
    "sg:city":"Zele",
    "sg:orig_category":"Peinture. Rev\u00eatements pour sols and murs",
    "sg:phone":"+32 52 44 51 39",
    "sg:postcode":"9240",
    "sg:province":"Oost-Vlaanderen",
    "wof:name":"Antoine Gysens",
    "wof:placetype":"venue"
},
  "geometry": {"coordinates":[4.0369830132,51.0815048218],"type":"Point"}
}