{
  "type": "Feature",
  "properties": {
    "addr:full":"Kortrijksestr 33 Ardooie West-Vlaanderen 8850",
    "addr:housenumber":"33",
    "addr:postcode":"8850",
    "addr:street":"Kortrijksestr",
    "iso:country":"BE",
    "sg:address":"Kortrijksestr 33",
    "sg:city":"Ardooie",
    "sg:classifiers":[
        {
            "category":"Banks & Credit Unions",
            "subcategory":"Bank",
            "type":"Services"
        }
    ],
    "sg:phone":"+32 51 74 40 49",
    "sg:postcode":"8850",
    "sg:province":"West-Vlaanderen",
    "wof:name":"Bank Van Roeselare",
    "wof:placetype":"venue"
},
  "geometry": {"coordinates":[3.1982040405,50.9760856628],"type":"Point"}
}