{
  "type": "Feature",
  "properties": {
    "iso:country":"BE",
    "sg:address":"Chauss\u00c9e De Helmet 372",
    "sg:city":"Schaarbeek/schaerbeek",
    "sg:orig_category":"Installation \u00e9lectrique r\u00e9sidentielle",
    "sg:phone":"+32 2 215 32 14",
    "sg:postcode":"1030",
    "sg:province":"Bruxelles-Capitale",
    "wof:name":"F. De Puydt",
    "wof:placetype":"venue"
},
  "geometry": {"coordinates":[4.3918981552,50.8755912781],"type":"Point"}
}