{
  "type": "Feature",
  "properties": {
    "addr:full":"Teutelbergstraat 65 Dilsen-stokkem (lanklaar) Limburg 3650",
    "addr:housenumber":"65",
    "addr:postcode":"3650",
    "addr:street":"Teutelbergstraat",
    "iso:country":"BE",
    "sg:address":"Teutelbergstraat 65",
    "sg:city":"Dilsen-stokkem (lanklaar)",
    "sg:classifiers":[
        {
            "category":"Wholesale",
            "subcategory":"Scrap",
            "type":"Manufacturing & Wholesale Goods"
        }
    ],
    "sg:phone":"+32 89 75 27 76",
    "sg:postcode":"3650",
    "sg:province":"Limburg",
    "sg:tags":[
        "metal"
    ],
    "wof:name":"Van Hoef W",
    "wof:placetype":"venue"
},
  "geometry": {"coordinates":[5.727396965,51.0364189148],"type":"Point"}
}