{
  "type": "Feature",
  "properties": {
    "addr:full":"Cathilleweg 55 Jabbeke (stalhille) West-Vlaanderen 8490",
    "addr:housenumber":"55",
    "addr:postcode":"8490",
    "addr:street":"Cathilleweg",
    "iso:country":"BE",
    "sg:address":"Cathilleweg 55",
    "sg:city":"Jabbeke (stalhille)",
    "sg:classifiers":[
        {
            "category":"Health Services",
            "subcategory":"Nursing And Care Facility",
            "type":"Services"
        }
    ],
    "sg:phone":"+32 50 41 75 47",
    "sg:postcode":"8490",
    "sg:province":"West-Vlaanderen",
    "sg:tags":[
        "home"
    ],
    "wof:name":"De Clercq Ingrid",
    "wof:placetype":"venue"
},
  "geometry": {"coordinates":[3.0738060474,51.2120475769],"type":"Point"}
}