{
  "type": "Feature",
  "properties": {
    "addr:full":"Kirchstrasse 1 Sankt Vith Li\u00e8ge 4780",
    "addr:housenumber":"1",
    "addr:postcode":"4780",
    "addr:street":"Kirchstrasse",
    "iso:country":"BE",
    "sg:address":"Kirchstrasse 1",
    "sg:city":"Sankt Vith",
    "sg:orig_category":"Mutualities",
    "sg:phone":"+32 80 22 63 62",
    "sg:postcode":"4780",
    "sg:province":"Li\u00e8ge",
    "wof:name":"Krankenkasse Caami Asbl",
    "wof:placetype":"venue"
},
  "geometry": {"coordinates":[6.1260437965,50.2815246582],"type":"Point"}
}