{
  "type": "Feature",
  "properties": {
    "addr:full":"Dorpsstraat 27 Overpelt Limburg 3900",
    "addr:housenumber":"27",
    "addr:postcode":"3900",
    "addr:street":"Dorpsstraat",
    "iso:country":"BE",
    "sg:address":"Dorpsstraat 27",
    "sg:city":"Overpelt",
    "sg:orig_category":"Newspapers, magazines, periodicals - Distribution",
    "sg:phone":"+32 11 64 42 30",
    "sg:postcode":"3900",
    "sg:province":"Limburg",
    "wof:name":"Pelterkrantenkiosk",
    "wof:placetype":"venue"
},
  "geometry": {"coordinates":[5.4253048897,51.2141456604],"type":"Point"}
}