{
  "type": "Feature",
  "properties": {
    "addr:full":"Flog 77 Raeren Li\u00e8ge 4730",
    "addr:housenumber":"77",
    "addr:postcode":"4730",
    "addr:street":"Flog",
    "iso:country":"BE",
    "sg:address":"Flog 77",
    "sg:city":"Raeren",
    "sg:orig_category":"Medische apparatuur, orthopedische artikelen and prothesen Fab",
    "sg:phone":"+32 87 65 89 25",
    "sg:postcode":"4730",
    "sg:province":"Li\u00e8ge",
    "wof:name":"Dieter Grassmann",
    "wof:placetype":"venue"
},
  "geometry": {"coordinates":[6.0759840012,50.7169380188],"type":"Point"}
}