{
  "type": "Feature",
  "properties": {
    "addr:full":"Oude Molenstraat 75bd Sint-gillis-waas Oost-Vlaanderen 9170",
    "addr:housenumber":"75bd",
    "addr:postcode":"9170",
    "addr:street":"Oude Molenstraat",
    "iso:country":"BE",
    "sg:address":"Oude Molenstraat 75bd",
    "sg:city":"Sint-gillis-waas",
    "sg:orig_category":"Installation \u00e9lectrique r\u00e9sidentielle",
    "sg:phone":"+32 3 707 14 57",
    "sg:postcode":"9170",
    "sg:province":"Oost-Vlaanderen",
    "wof:name":"Patrick Vermeire",
    "wof:placetype":"venue"
},
  "geometry": {"coordinates":[4.1109480858,51.2596817017],"type":"Point"}
}