{
  "type": "Feature",
  "properties": {
    "iso:country":"BE",
    "sg:address":"Rue De Quevaucamps 79",
    "sg:city":"Beloeil (bas\u00e8cles)",
    "sg:classifiers":[
        {
            "category":"Health Services",
            "subcategory":"Health Practitioner",
            "type":"Services"
        }
    ],
    "sg:phone":"+32 69 57 86 17",
    "sg:postcode":"7971",
    "sg:province":"Hainaut",
    "sg:tags":[
        "physiotherapist"
    ],
    "wof:name":"Flamme Jean-pierre",
    "wof:placetype":"venue"
},
  "geometry": {"coordinates":[3.6649129391,50.5212402344],"type":"Point"}
}