{
  "type": "Feature",
  "properties": {
    "addr:full":"Deerlijkseweg 17 Waregem West-Vlaanderen 8790",
    "addr:housenumber":"17",
    "addr:postcode":"8790",
    "addr:street":"Deerlijkseweg",
    "iso:country":"BE",
    "sg:address":"Deerlijkseweg 17",
    "sg:city":"Waregem",
    "sg:orig_category":"Woningbouw",
    "sg:phone":"+32 56 61 05 25",
    "sg:postcode":"8790",
    "sg:province":"West-Vlaanderen",
    "wof:name":"Bouwwerken Claeys",
    "wof:placetype":"venue"
},
  "geometry": {"coordinates":[3.4192669392,50.8743133545],"type":"Point"}
}