{
  "type": "Feature",
  "properties": {
    "iso:country":"BE",
    "sg:address":"Brusselsesteenweg 40",
    "sg:city":"Halle",
    "sg:classifiers":[
        {
            "category":"Restaurant",
            "type":"Food & Drink"
        }
    ],
    "sg:phone":"+32 2 360 28 06",
    "sg:postcode":"1500",
    "sg:province":"Vlaams-Brabant",
    "wof:name":"\u00b4t Wit Paard",
    "wof:placetype":"venue"
},
  "geometry": {"coordinates":[4.2380928993,50.7382736206],"type":"Point"}
}