{
  "type": "Feature",
  "properties": {
    "iso:country":"BE",
    "sg:address":"Dendermondsesteenweg 89",
    "sg:city":"Wetteren",
    "sg:orig_category":"Loodgieterij, verwarming and sanitaire installaties",
    "sg:phone":"+32 9 369 57 74",
    "sg:postcode":"9230",
    "sg:province":"Oost-Vlaanderen",
    "wof:name":"Schepens Denis",
    "wof:placetype":"venue"
},
  "geometry": {"coordinates":[3.9149389267,51.0115318298],"type":"Point"}
}