{
  "type": "Feature",
  "properties": {
    "addr:full":"Diesterstw 213 Kermt Limburg 3510",
    "addr:housenumber":"213",
    "addr:postcode":"3510",
    "iso:country":"BE",
    "sg:address":"Diesterstw 213",
    "sg:city":"Kermt",
    "sg:classifiers":[
        {
            "category":"Banks & Credit Unions",
            "subcategory":"Bank",
            "type":"Services"
        }
    ],
    "sg:phone":"+32 11 25 33 79",
    "sg:postcode":"3510",
    "sg:province":"Limburg",
    "wof:name":"Aslk-cger Bank",
    "wof:placetype":"venue"
},
  "geometry": {"coordinates":[5.2520089149,50.9474906921],"type":"Point"}
}