{
  "type": "Feature",
  "properties": {
    "addr:full":"Rue Saint-jean 17 Chievres Hainaut 7950",
    "addr:housenumber":"17",
    "addr:postcode":"7950",
    "addr:street":"Rue Saint-Jean;Hainaut",
    "iso:country":"BE",
    "sg:address":"Rue Saint-jean 17",
    "sg:city":"Chievres",
    "sg:orig_category":"Supermarkten",
    "sg:phone":"+32 68 65 82 01",
    "sg:postcode":"7950",
    "sg:province":"Hainaut",
    "wof:name":"Battard",
    "wof:placetype":"venue"
},
  "geometry": {"coordinates":[3.8073029518,50.5867729187],"type":"Point"}
}