{
  "type": "Feature",
  "properties": {
    "addr:full":"Speiestraat 21 Wervik West-Vlaanderen 8940",
    "addr:housenumber":"21",
    "addr:postcode":"8940",
    "addr:street":"Speiestraat",
    "iso:country":"BE",
    "sg:address":"Speiestraat 21",
    "sg:city":"Wervik",
    "sg:orig_category":"Dierenartsen",
    "sg:phone":"+32 56 31 25 85",
    "sg:postcode":"8940",
    "sg:province":"West-Vlaanderen",
    "wof:name":"Kristian Samyn",
    "wof:placetype":"venue"
},
  "geometry": {"coordinates":[3.0456249714,50.7788276672],"type":"Point"}
}