{
  "type": "Feature",
  "properties": {
    "iso:country":"BE",
    "sg:address":"Rue Marianne 9",
    "sg:city":"Bruxelles (uccle)",
    "sg:classifiers":[
        {
            "category":"Professional",
            "subcategory":"Testing Lab",
            "type":"Services"
        }
    ],
    "sg:phone":"+32 2 347 13 27",
    "sg:postcode":"1180",
    "sg:province":"Bruxelles-Capitale",
    "sg:tags":[
        "laboratory",
        "medical"
    ],
    "wof:name":"Laboratoire D'analyses Morphologiques L A M Sprl",
    "wof:placetype":"venue"
},
  "geometry": {"coordinates":[4.3515839577,50.8136672974],"type":"Point"}
}