{
  "type": "Feature",
  "properties": {
    "iso:country":"BE",
    "sg:address":"Route De Luxembourg 12",
    "sg:city":"Malmedy (beverc\u00e9)",
    "sg:classifiers":[
        {
            "category":"Home & Garden",
            "subcategory":"Home Furnishings",
            "type":"Retail Goods"
        }
    ],
    "sg:phone":"+32 80 33 82 65",
    "sg:postcode":"4960",
    "sg:province":"Li\u00e8ge",
    "sg:tags":[
        "interior",
        "decoration"
    ],
    "wof:name":"Intemporel",
    "wof:placetype":"venue"
},
  "geometry": {"coordinates":[6.0666079521,50.401725769],"type":"Point"}
}