{
  "type": "Feature",
  "properties": {
    "addr:full":"Philadelphiastraat 25 Antwerpen Antwerpen 2030",
    "addr:housenumber":"25",
    "addr:postcode":"2030",
    "addr:street":"Philadelphiastraat",
    "iso:country":"BE",
    "sg:address":"Philadelphiastraat 25",
    "sg:city":"Antwerpen",
    "sg:orig_category":"Plomberie, chauffage and installations sanitaires",
    "sg:phone":"+32 3 542 01 59",
    "sg:postcode":"2030",
    "sg:province":"Antwerpen",
    "wof:name":"Dave Sels",
    "wof:placetype":"venue"
},
  "geometry": {"coordinates":[4.4247989655,51.2598571777],"type":"Point"}
}