{
  "type": "Feature",
  "properties": {
    "iso:country":"BE",
    "sg:address":"Rue De Trazegnies 77ba",
    "sg:city":"Pont-a-celles",
    "sg:orig_category":"Textiel",
    "sg:phone":"+32 71 84 27 08",
    "sg:postcode":"6230",
    "sg:province":"Hainaut",
    "wof:name":"Gerard Molle",
    "wof:placetype":"venue"
},
  "geometry": {"coordinates":[4.3635468483,50.5010223389],"type":"Point"}
}