{
  "type": "Feature",
  "properties": {
    "addr:full":"Koestraat 181b3 Roeselare West-Vlaanderen 8800",
    "addr:housenumber":"181b3",
    "addr:postcode":"8800",
    "addr:street":"Koestraat",
    "iso:country":"BE",
    "sg:address":"Koestraat 181b3",
    "sg:city":"Roeselare",
    "sg:orig_category":"Electrom\u00e9nager, t\u00e9l\u00e9visions and radios",
    "sg:phone":"+32 51 69 61 96",
    "sg:postcode":"8800",
    "sg:province":"West-Vlaanderen",
    "wof:name":"Huis De Rammelaere",
    "wof:placetype":"venue"
},
  "geometry": {"coordinates":[3.148761034,50.9221801758],"type":"Point"}
}