{
  "type": "Feature",
  "properties": {
    "addr:full":"Lindenlei 84 Schoten Antwerpen 2900",
    "addr:housenumber":"84",
    "addr:postcode":"2900",
    "addr:street":"Lindenlei",
    "iso:country":"BE",
    "sg:address":"Lindenlei 84",
    "sg:city":"Schoten",
    "sg:orig_category":"Installatie van houten of kunststof schrijnwerk",
    "sg:phone":"+32 3 658 09 16",
    "sg:postcode":"2900",
    "sg:province":"Antwerpen",
    "wof:name":"Francis De Ruyck",
    "wof:placetype":"venue"
},
  "geometry": {"coordinates":[4.5155830383,51.2495651245],"type":"Point"}
}