{
  "type": "Feature",
  "properties": {
    "iso:country":"BE",
    "sg:address":"Koekoekslaan 1",
    "sg:city":"Wingene",
    "sg:orig_category":"Woningbouw",
    "sg:phone":"+32 51 65 72 09",
    "sg:postcode":"8750",
    "sg:province":"West-Vlaanderen",
    "wof:name":"Chris Frodure Bouwt",
    "wof:placetype":"venue"
},
  "geometry": {"coordinates":[3.2680499554,51.0528717041],"type":"Point"}
}