{
  "type": "Feature",
  "properties": {
    "iso:country":"BE",
    "sg:address":"Rue De La Cornette 1",
    "sg:city":"Fexhe-le-haut-clocher",
    "sg:classifiers":[
        {
            "category":"Sports & Exercise",
            "subcategory":"Gym",
            "type":"Entertainment"
        }
    ],
    "sg:phone":"+32 4 273 73 39",
    "sg:postcode":"4347",
    "sg:province":"Li\u00e8ge",
    "sg:tags":[
        "fitness"
    ],
    "wof:name":"Japan Karate Association",
    "wof:placetype":"venue"
},
  "geometry": {"coordinates":[5.4299631119,50.6521644592],"type":"Point"}
}