{
  "type": "Feature",
  "properties": {
    "iso:country":"BE",
    "sg:address":"Grand Chemin 17",
    "sg:city":"Lasne (lasne-chapelle-saint-lambert)",
    "sg:classifiers":[
        {
            "category":"Professional",
            "subcategory":"Computer Services",
            "type":"Services"
        }
    ],
    "sg:phone":"+32 2 633 34 44",
    "sg:postcode":"1380",
    "sg:province":"Brabant Wallon",
    "sg:tags":[
        "network"
    ],
    "wof:name":"Ooops Sprl",
    "wof:placetype":"venue"
},
  "geometry": {"coordinates":[4.4986658096,50.6669273376],"type":"Point"}
}