{
  "type": "Feature",
  "properties": {
    "addr:full":"Grote Markt 0 Zelzate Oost-Vlaanderen 9060",
    "addr:housenumber":"0",
    "addr:postcode":"9060",
    "addr:street":"Grote Markt",
    "iso:country":"BE",
    "sg:address":"Grote Markt 0",
    "sg:city":"Zelzate",
    "sg:classifiers":[
        {
            "category":"Fast Food",
            "type":"Food & Drink"
        }
    ],
    "sg:phone":"+32 9 342 83 82",
    "sg:postcode":"9060",
    "sg:province":"Oost-Vlaanderen",
    "sg:tags":[
        "meeneem",
        "restaurant"
    ],
    "wof:name":"Tina\u00b4s Frituur",
    "wof:placetype":"venue"
},
  "geometry": {"coordinates":[3.8098940849,51.2022972107],"type":"Point"}
}