{
  "type": "Feature",
  "properties": {
    "iso:country":"BE",
    "sg:address":"Wijnendale 81",
    "sg:city":"Audenarde",
    "sg:orig_category":"Meubles D\u00e9taillants, Am\u00e9nagement de B\u00e2timents et de Cuisines",
    "sg:phone":"+32 55 30 22 41",
    "sg:postcode":"9700",
    "sg:province":"Oost-Vlaanderen",
    "wof:name":"Tency",
    "wof:placetype":"venue"
},
  "geometry": {"coordinates":[3.618899107,50.8442497253],"type":"Point"}
}