{
  "type": "Feature",
  "properties": {
    "iso:country":"BE",
    "sg:address":"Hooistraat 8",
    "sg:city":"Torhout",
    "sg:orig_category":"Sportclubs",
    "sg:phone":"+32 50 21 49 68",
    "sg:postcode":"8820",
    "sg:province":"West-Vlaanderen",
    "wof:name":"Wielerclub Wijnendaele Sportief",
    "wof:placetype":"venue"
},
  "geometry": {"coordinates":[3.0977809429,51.0871772766],"type":"Point"}
}