{
  "type": "Feature",
  "properties": {
    "iso:country":"BE",
    "sg:address":"Maenhoutstraat 70",
    "sg:city":"Sint-martens-latem",
    "sg:orig_category":"Banken and kredietinstellingen Verzekeringsmakelaars and experts",
    "sg:phone":"+32 9 282 87 22",
    "sg:postcode":"9830",
    "sg:province":"Oost-Vlaanderen",
    "wof:name":"Eural",
    "wof:placetype":"venue"
},
  "geometry": {"coordinates":[3.6447598934,51.0140037537],"type":"Point"}
}