{
  "type": "Feature",
  "properties": {
    "addr:full":"Chauss\u00e9e De Mons 791 Bruxelles (anderlecht) Bruxelles-Capitale 1070",
    "addr:housenumber":"791",
    "addr:postcode":"1070",
    "addr:street":"Chausse\u0301E De Mons",
    "iso:country":"BE",
    "sg:address":"Chauss\u00e9e De Mons 791",
    "sg:city":"Bruxelles (anderlecht)",
    "sg:classifiers":[
        {
            "category":"Home & Garden",
            "subcategory":"Home Furnishings",
            "type":"Retail Goods"
        }
    ],
    "sg:phone":"+32 2 527 56 55",
    "sg:postcode":"1070",
    "sg:province":"Bruxelles-Capitale",
    "sg:tags":[
        "-",
        "furniture"
    ],
    "wof:name":"G\u00e9ant Du Matelas",
    "wof:placetype":"venue"
},
  "geometry": {"coordinates":[4.3060259819,50.8295516968],"type":"Point"}
}