{
  "type": "Feature",
  "properties": {
    "addr:full":"Rue Beeckman 44 Bruxelles (uccle) Bruxelles-Capitale 1180",
    "addr:housenumber":"44",
    "addr:postcode":"1180",
    "addr:street":"Rue Beeckman",
    "iso:country":"BE",
    "sg:address":"Rue Beeckman 44",
    "sg:city":"Bruxelles (uccle)",
    "sg:classifiers":[
        {
            "category":"Education",
            "subcategory":"School",
            "type":"Public Place"
        }
    ],
    "sg:phone":"+32 2 420 32 50",
    "sg:postcode":"1180",
    "sg:province":"Bruxelles-Capitale",
    "sg:tags":[
        "-",
        "private"
    ],
    "wof:name":"Atelier Gilman V",
    "wof:placetype":"venue"
},
  "geometry": {"coordinates":[4.3349928856,50.8053512573],"type":"Point"}
}