{
  "type": "Feature",
  "properties": {
    "addr:full":"Anton Catriestraat 8 Gent Oost-Vlaanderen 9031",
    "addr:housenumber":"8",
    "addr:postcode":"9031",
    "addr:street":"Catriestraat;Oost-Vlaanderen",
    "iso:country":"BE",
    "sg:address":"Anton Catriestraat 8",
    "sg:city":"Gent",
    "sg:orig_category":"Dameskledingzaken Herenkledingzaken",
    "sg:phone":"+32 9 227 08 88",
    "sg:postcode":"9031",
    "sg:province":"Oost-Vlaanderen",
    "wof:name":"Galleria Laurenzo",
    "wof:placetype":"venue"
},
  "geometry": {"coordinates":[3.6575069427,51.0500068665],"type":"Point"}
}