{
  "type": "Feature",
  "properties": {
    "iso:country":"BE",
    "sg:address":"496-498 Alsembergsesteenweg",
    "sg:city":"Beersel",
    "sg:classifiers":[
        {
            "category":"Autos & Motor Vehicles",
            "subcategory":"Automobile Sales",
            "type":"Retail Goods"
        }
    ],
    "sg:phone":"+32 2 380 10 08",
    "sg:postcode":"1653",
    "sg:province":"Vlaams-Brabant",
    "sg:tags":[
        "equipment",
        "motor-cars",
        "transport"
    ],
    "wof:name":"Garage Surkeyn Bvba",
    "wof:placetype":"venue"
},
  "geometry": {"coordinates":[4.325466156,50.7795410156],"type":"Point"}
}