{
  "type": "Feature",
  "properties": {
    "addr:full":"Rue Des Villas 157 Seraing Li\u00e8ge 4100",
    "addr:housenumber":"157",
    "addr:postcode":"4100",
    "addr:street":"Rue Des Villas",
    "iso:country":"BE",
    "sg:address":"Rue Des Villas 157",
    "sg:city":"Seraing",
    "sg:classifiers":[
        {
            "category":"Government",
            "subcategory":"Fire Station",
            "type":"Public Place"
        }
    ],
    "sg:phone":"+32 4 337 10 92",
    "sg:postcode":"4100",
    "sg:province":"Li\u00e8ge",
    "sg:tags":[
        "commerce",
        "conditionn\u00e9",
        "equipement",
        "pour",
        "air",
        "ventilation",
        "diver"
    ],
    "wof:name":"Jean Berenguier",
    "wof:placetype":"venue"
},
  "geometry": {"coordinates":[5.5095930099,50.5807189941],"type":"Point"}
}