{
  "type": "Feature",
  "properties": {
    "iso:country":"BE",
    "sg:address":"Vanden Tymplestraat 59 Bus 2",
    "sg:city":"Leuven",
    "sg:orig_category":"Fournitures de bureau. Ordinateurs and \u00e9quipement informatique",
    "sg:phone":"+32 485 46 89 10",
    "sg:postcode":"3000",
    "sg:province":"Vlaams-Brabant",
    "wof:name":"T & C.c. Bvba-sprl",
    "wof:placetype":"venue"
},
  "geometry": {"coordinates":[4.7101612091,50.8835639954],"type":"Point"}
}