{
  "type": "Feature",
  "properties": {
    "iso:country":"BE",
    "sg:address":"Rue Dachet 23",
    "sg:city":"Namur (w\u00e9pion)",
    "sg:classifiers":[
        {
            "category":"Manufacturing",
            "subcategory":"Rubber & Plastics",
            "type":"Manufacturing & Wholesale Goods"
        }
    ],
    "sg:phone":"+32 81 46 02 07",
    "sg:postcode":"5100",
    "sg:province":"Namur",
    "sg:tags":[
        "working"
    ],
    "wof:name":"Design Cutting",
    "wof:placetype":"venue"
},
  "geometry": {"coordinates":[4.8720121384,50.422000885],"type":"Point"}
}