{
  "type": "Feature",
  "properties": {
    "addr:full":"Rue Des Coloniaux 8 Virton Luxembourg 6760",
    "addr:housenumber":"8",
    "addr:postcode":"6760",
    "addr:street":"Rue Des Coloniaux",
    "iso:country":"BE",
    "sg:address":"Rue Des Coloniaux 8",
    "sg:city":"Virton",
    "sg:orig_category":"Sportclubs",
    "sg:phone":"+32 63 57 10 37",
    "sg:postcode":"6760",
    "sg:province":"Luxembourg",
    "wof:name":"Volley Club Virton",
    "wof:placetype":"venue"
},
  "geometry": {"coordinates":[5.5213689804,49.5656356812],"type":"Point"}
}