{
  "type": "Feature",
  "properties": {
    "iso:country":"BE",
    "sg:address":"Moerlaanstraat 21",
    "sg:city":"Overijse",
    "sg:orig_category":"Activit\u00e9s r\u00e9cr\u00e9atives diverses",
    "sg:phone":"+32 2 687 50 86",
    "sg:postcode":"3090",
    "sg:province":"Vlaams-Brabant",
    "wof:name":"Cercle Philat\u00c9l. Woluw\u00c9",
    "wof:placetype":"venue"
},
  "geometry": {"coordinates":[4.565513134,50.7527656555],"type":"Point"}
}