{
  "type": "Feature",
  "properties": {
    "addr:full":"Chauss\u00c9e De Tirlemont 37 Wanze Li\u00e8ge 4520",
    "addr:housenumber":"37",
    "addr:postcode":"4520",
    "addr:street":"Chausse\u0301E De Tirlemont",
    "iso:country":"BE",
    "sg:address":"Chauss\u00c9e De Tirlemont 37",
    "sg:city":"Wanze",
    "sg:orig_category":"Jeux de hasard",
    "sg:phone":"+32 85 21 25 16",
    "sg:postcode":"4520",
    "sg:province":"Li\u00e8ge",
    "wof:name":"Tierc\u00c9 Franco Belge",
    "wof:placetype":"venue"
},
  "geometry": {"coordinates":[5.2195658684,50.5348358154],"type":"Point"}
}