{
  "type": "Feature",
  "properties": {
    "addr:full":"Chauss\u00e9e De Louvain 652 Namur (champion - Cognel\u00e9e) Namur 5020",
    "addr:housenumber":"652",
    "addr:postcode":"cognele\u0301e;5020",
    "addr:street":"Chausse\u0301E De Louvain",
    "iso:country":"BE",
    "sg:address":"Chauss\u00e9e De Louvain 652",
    "sg:city":"Namur (champion - Cognel\u00e9e)",
    "sg:classifiers":[
        {
            "category":"Professional",
            "subcategory":"Testing Lab",
            "type":"Services"
        }
    ],
    "sg:phone":"+32 81 21 51 09",
    "sg:postcode":"5020",
    "sg:province":"Namur",
    "sg:tags":[
        "chemist"
    ],
    "wof:name":"Pharmacie Angely Sa",
    "wof:placetype":"venue"
},
  "geometry": {"coordinates":[4.7952418327,50.4352035522],"type":"Point"}
}