{
  "type": "Feature",
  "properties": {
    "iso:country":"BE",
    "sg:address":"Bruggestraat 134ba",
    "sg:city":"Beernem",
    "sg:orig_category":"Elektrische installaties voor woningen",
    "sg:phone":"+32 50 79 10 37",
    "sg:postcode":"8730",
    "sg:province":"West-Vlaanderen",
    "wof:name":"Janne & Co",
    "wof:placetype":"venue"
},
  "geometry": {"coordinates":[3.3171100616,51.1749572754],"type":"Point"}
}