{
  "type": "Feature",
  "properties": {
    "addr:full":"Place De La Reine 51-53 Bruxelles (schaerbeek) Bruxelles-Capitale 1030",
    "addr:postcode":"51-53;1030",
    "addr:street":"Place De La Reine",
    "iso:country":"BE",
    "sg:address":"Place De La Reine 51-53",
    "sg:city":"Bruxelles (schaerbeek)",
    "sg:orig_category":"Mutualities",
    "sg:phone":"+32 2 209 48 11",
    "sg:postcode":"1030",
    "sg:province":"Bruxelles-Capitale",
    "wof:name":"Liberale Mutualiteit Van Brabant",
    "wof:placetype":"venue"
},
  "geometry": {"coordinates":[4.368388176,50.8584442139],"type":"Point"}
}