{
  "type": "Feature",
  "properties": {
    "addr:full":"Nijverheidsln 3 Wervik West-Vlaanderen 8940",
    "addr:housenumber":"3",
    "addr:postcode":"8940",
    "addr:street":"Nijverheidsln",
    "iso:country":"BE",
    "sg:address":"Nijverheidsln 3",
    "sg:city":"Wervik",
    "sg:classifiers":[
        {
            "category":"Shopping",
            "subcategory":"Computers & Home Electronics",
            "type":"Retail Goods"
        }
    ],
    "sg:phone":"+32 56 51 80 00",
    "sg:postcode":"8940",
    "sg:province":"West-Vlaanderen",
    "sg:tags":[
        "equipment",
        "household",
        "electrical",
        "appliance",
        "electronic"
    ],
    "wof:name":"Calis Koeltechniek Nv",
    "wof:placetype":"venue"
},
  "geometry": {"coordinates":[3.069879055,50.8130950928],"type":"Point"}
}