{
  "type": "Feature",
  "properties": {
    "addr:full":"Rue De Rochefort 66-68 Beauraing Namur 5570",
    "addr:housenumber":"66-68",
    "addr:postcode":"5570",
    "addr:street":"Rue De Rochefort",
    "iso:country":"BE",
    "sg:address":"Rue De Rochefort 66-68",
    "sg:city":"Beauraing",
    "sg:classifiers":[
        {
            "category":"Cafe",
            "type":"Food & Drink"
        }
    ],
    "sg:phone":"+32 82 71 43 43",
    "sg:postcode":"5570",
    "sg:province":"Namur",
    "sg:tags":[
        "snack-bars"
    ],
    "wof:name":"Vigne\u00e9 (le)",
    "wof:placetype":"venue"
},
  "geometry": {"coordinates":[4.9608330727,50.1103897095],"type":"Point"}
}