{
  "type": "Feature",
  "properties": {
    "addr:full":"Loksbergenstraat 78 Halen Limburg 3545",
    "addr:housenumber":"78",
    "addr:postcode":"3545",
    "addr:street":"Loksbergenstraat",
    "iso:country":"BE",
    "sg:address":"Loksbergenstraat 78",
    "sg:city":"Halen",
    "sg:orig_category":"Fruitteelt",
    "sg:phone":"+32 13 44 14 75",
    "sg:postcode":"3545",
    "sg:province":"Limburg",
    "wof:name":"Paul Devos",
    "wof:placetype":"venue"
},
  "geometry": {"coordinates":[5.0669088364,50.9325523376],"type":"Point"}
}