{
  "type": "Feature",
  "properties": {
    "addr:full":"Rue Notre-dame Des Champs 50 Namur (champion - Cognel\u00e9e) Namur 5020",
    "addr:housenumber":"50",
    "addr:postcode":"cognele\u0301e;5020",
    "addr:street":"Rue Notre-Dame Des Champs",
    "iso:country":"BE",
    "sg:address":"Rue Notre-dame Des Champs 50",
    "sg:city":"Namur (champion - Cognel\u00e9e)",
    "sg:classifiers":[
        {
            "category":"Health Services",
            "subcategory":"Doctor",
            "type":"Services"
        }
    ],
    "sg:phone":"+32 81 21 17 92",
    "sg:postcode":"5020",
    "sg:province":"Namur",
    "sg:tags":[
        "medicinephysicians",
        "surgeon"
    ],
    "wof:name":"Devogelaer Jean-pierre",
    "wof:placetype":"venue"
},
  "geometry": {"coordinates":[4.7952418327,50.4352035522],"type":"Point"}
}