{
  "type": "Feature",
  "properties": {
    "iso:country":"BE",
    "sg:address":"Zeelsebaan 27",
    "sg:city":"Dendermonde",
    "sg:orig_category":"Sportterreinen and installaties behalve sportcentra",
    "sg:phone":"+32 52 22 21 31",
    "sg:postcode":"9200",
    "sg:province":"Oost-Vlaanderen",
    "wof:name":"Watersportver. Del Mare",
    "wof:placetype":"venue"
},
  "geometry": {"coordinates":[4.0941581726,51.0446510315],"type":"Point"}
}