{
  "type": "Feature",
  "properties": {
    "addr:full":"Chauss\u00e9e De Li\u00e8ge 157 Gr\u00e2ce-hollogne (gr\u00e2ce-berleur) Li\u00e8ge 4460",
    "addr:housenumber":"157",
    "addr:postcode":"4460",
    "addr:street":"Chausse\u0301E De Lie\u0300Ge;Gra\u0302Ce-Berleur",
    "iso:country":"BE",
    "sg:address":"Chauss\u00e9e De Li\u00e8ge 157",
    "sg:city":"Gr\u00e2ce-hollogne (gr\u00e2ce-berleur)",
    "sg:classifiers":[
        {
            "category":"Wholesale",
            "subcategory":"Metals & Minerals",
            "type":"Manufacturing & Wholesale Goods"
        }
    ],
    "sg:phone":"+32 4 234 18 18",
    "sg:postcode":"4460",
    "sg:province":"Li\u00e8ge",
    "sg:tags":[
        "sheet"
    ],
    "wof:name":"Mafer Sprl",
    "wof:placetype":"venue"
},
  "geometry": {"coordinates":[5.4802589417,50.6485443115],"type":"Point"}
}