{
  "type": "Feature",
  "properties": {
    "addr:full":"Sint-hubertstraat 290 Deinze Oost-Vlaanderen 9800",
    "addr:housenumber":"290",
    "addr:postcode":"9800",
    "iso:country":"BE",
    "sg:address":"Sint-hubertstraat 290",
    "sg:city":"Deinze",
    "sg:orig_category":"Ramassage and traitement des d\u00e9chets m\u00e9nagers. Collecte and \u00e9puration des eaux us\u00e9es",
    "sg:phone":"+32 9 386 15 63",
    "sg:postcode":"9800",
    "sg:province":"Oost-Vlaanderen",
    "wof:name":"E. Van Hove",
    "wof:placetype":"venue"
},
  "geometry": {"coordinates":[3.5132958889,50.9620361328],"type":"Point"}
}