{
  "type": "Feature",
  "properties": {
    "addr:full":"Bredepleinstraat 20 Boortmeerbeek Vlaams-Brabant 3190",
    "addr:housenumber":"20",
    "addr:postcode":"3190",
    "addr:street":"Bredepleinstraat",
    "iso:country":"BE",
    "sg:address":"Bredepleinstraat 20",
    "sg:city":"Boortmeerbeek",
    "sg:classifiers":[
        {
            "category":"Health Services",
            "subcategory":"Health Practitioner",
            "type":"Services"
        }
    ],
    "sg:phone":"+32 15 51 73 83",
    "sg:postcode":"3190",
    "sg:province":"Vlaams-Brabant",
    "sg:tags":[
        "physiotherapist"
    ],
    "wof:name":"De Hont Ilse",
    "wof:placetype":"venue"
},
  "geometry": {"coordinates":[4.5695419312,50.9767913818],"type":"Point"}
}