{
  "type": "Feature",
  "properties": {
    "iso:country":"BE",
    "sg:address":"Place Du Congr\u00c8s 4",
    "sg:city":"Li\u00c8ge",
    "sg:orig_category":"M\u00e9decins and sp\u00e9cialistes",
    "sg:phone":"+32 4 344 33 93",
    "sg:postcode":"4020",
    "sg:province":"Li\u00e8ge",
    "wof:name":"N. Warin",
    "wof:placetype":"venue"
},
  "geometry": {"coordinates":[5.5880098343,50.6424598694],"type":"Point"}
}