{
  "type": "Feature",
  "properties": {
    "addr:full":"Avenue De Wisterz\u00c9e 46 Court-saint-etienne Brabant Wallon 1490",
    "addr:housenumber":"46;1490",
    "addr:street":"Avenue De Wisterze\u0301E",
    "iso:country":"BE",
    "sg:address":"Avenue De Wisterz\u00c9e 46",
    "sg:city":"Court-saint-etienne",
    "sg:classifiers":[
        {
            "category":"Personal",
            "subcategory":"Beauty Salon",
            "type":"Services"
        }
    ],
    "sg:phone":"+32 10 61 75 46",
    "sg:postcode":"1490",
    "sg:province":"Brabant Wallon",
    "sg:tags":[
        "de",
        "coiffure"
    ],
    "wof:name":"Coiffure John",
    "wof:placetype":"venue"
},
  "geometry": {"coordinates":[4.5642991066,50.6479530334],"type":"Point"}
}