{
  "type": "Feature",
  "properties": {
    "addr:full":"Vieux Chemin De Hal 41 Braine-le-chateau Brabant Wallon 1440",
    "addr:housenumber":"41",
    "addr:postcode":"1440",
    "addr:street":"Vieux Chemin De Hal;Brabant Wallon",
    "iso:country":"BE",
    "sg:address":"Vieux Chemin De Hal 41",
    "sg:city":"Braine-le-chateau",
    "sg:orig_category":"Woningbouw",
    "sg:phone":"+32 2 366 12 32",
    "sg:postcode":"1440",
    "sg:province":"Brabant Wallon",
    "wof:name":"Joseph Vanderheyden",
    "wof:placetype":"venue"
},
  "geometry": {"coordinates":[4.2692070007,50.6917533875],"type":"Point"}
}