{
  "type": "Feature",
  "properties": {
    "addr:full":"Route De Val-dieu 75 Aubel Li\u00e8ge 4880",
    "addr:housenumber":"75",
    "addr:postcode":"4880",
    "addr:street":"Route De Val-Dieu",
    "iso:country":"BE",
    "sg:address":"Route De Val-dieu 75",
    "sg:city":"Aubel",
    "sg:orig_category":"Bloemen and planten Boomkwekerijen Tuinen",
    "sg:phone":"+32 87 68 77 45",
    "sg:postcode":"4880",
    "sg:province":"Li\u00e8ge",
    "wof:name":"P\u00c9pini\u00c8res Meurens",
    "wof:placetype":"venue"
},
  "geometry": {"coordinates":[5.8471608162,50.7092475891],"type":"Point"}
}