{
  "type": "Feature",
  "properties": {
    "iso:country":"BE",
    "sg:address":"Tuinwijkstraat 42",
    "sg:city":"Zaventem",
    "sg:classifiers":[
        {
            "category":"Arena",
            "subcategory":"Sports Club",
            "type":"Entertainment"
        }
    ],
    "sg:phone":"+32 2 720 46 17",
    "sg:postcode":"1930",
    "sg:province":"Vlaams-Brabant",
    "sg:tags":[
        "terrain",
        "hors",
        "de",
        "installation",
        "sportifs"
    ],
    "wof:name":"S.k. Hoek Zaventem",
    "wof:placetype":"venue"
},
  "geometry": {"coordinates":[4.4650759697,50.8903999329],"type":"Point"}
}