{
  "type": "Feature",
  "properties": {
    "addr:full":"Rue De La Fonderie 1 La Louvi\u00e8re Hainaut 7100",
    "addr:housenumber":"1",
    "addr:postcode":"7100",
    "addr:street":"Rue De La Fonderie",
    "iso:country":"BE",
    "sg:address":"Rue De La Fonderie 1",
    "sg:city":"La Louvi\u00e8re",
    "sg:classifiers":[
        {
            "category":"Real Estate",
            "subcategory":"Architect",
            "type":"Services"
        }
    ],
    "sg:phone":"+32 64 21 23 69",
    "sg:postcode":"7100",
    "sg:province":"Hainaut",
    "wof:name":"Dal Cin R",
    "wof:placetype":"venue"
},
  "geometry": {"coordinates":[4.1831002235,50.4717216492],"type":"Point"}
}