{
  "type": "Feature",
  "properties": {
    "iso:country":"BE",
    "sg:address":"Avenue Mar\u00c9chal Joffre 125",
    "sg:city":"Vorst/forest",
    "sg:orig_category":"M\u00e9decins and sp\u00e9cialistes",
    "sg:phone":"+32 2 347 27 25",
    "sg:postcode":"1190",
    "sg:province":"Bruxelles-Capitale",
    "wof:name":"Thierry Hubert",
    "wof:placetype":"venue"
},
  "geometry": {"coordinates":[4.3368339539,50.8143844604],"type":"Point"}
}