{
  "type": "Feature",
  "properties": {
    "iso:country":"BE",
    "sg:address":"Genkersteenweg 465",
    "sg:city":"Hasselt",
    "sg:classifiers":[
        {
            "category":"Banks & Credit Unions",
            "subcategory":"Financial Services",
            "type":"Services"
        }
    ],
    "sg:phone":"+32 11 21 01 62",
    "sg:postcode":"3500",
    "sg:province":"Limburg",
    "sg:tags":[
        "banking",
        "finance",
        "insurance"
    ],
    "wof:name":"Eurorent Verhuurbedrijf Nv",
    "wof:placetype":"venue"
},
  "geometry": {"coordinates":[5.3834700584,50.9453887939],"type":"Point"}
}