{
  "type": "Feature",
  "properties": {
    "iso:country":"BE",
    "sg:address":"Rodestraat 100",
    "sg:city":"Zottegem",
    "sg:orig_category":"Rundveehouders",
    "sg:phone":"+32 9 360 29 48",
    "sg:postcode":"9620",
    "sg:province":"Oost-Vlaanderen",
    "wof:name":"Gilbert Van Damme",
    "wof:placetype":"venue"
},
  "geometry": {"coordinates":[3.8382050991,50.8560600281],"type":"Point"}
}