{
  "type": "Feature",
  "properties": {
    "addr:full":"Molenstraat 27 Harelbeke West-Vlaanderen 8530",
    "addr:housenumber":"27",
    "addr:postcode":"8530",
    "addr:street":"Molenstraat",
    "iso:country":"BE",
    "sg:address":"Molenstraat 27",
    "sg:city":"Harelbeke",
    "sg:classifiers":[
        {
            "category":"Building & Trades",
            "subcategory":"Electrical",
            "type":"Services"
        }
    ],
    "sg:phone":"+32 56 71 95 74",
    "sg:postcode":"8530",
    "sg:province":"West-Vlaanderen",
    "sg:tags":[
        "electric",
        "-",
        "housewiring",
        "contractor"
    ],
    "wof:name":"Blondeel F",
    "wof:placetype":"venue"
},
  "geometry": {"coordinates":[3.3004250526,50.8606643677],"type":"Point"}
}