{
  "type": "Feature",
  "properties": {
    "addr:full":"Rue Van Artevelde 48 Brussel/bruxelles Bruxelles-Capitale 1000",
    "addr:housenumber":"48",
    "addr:postcode":"1000",
    "addr:street":"Rue Van Artevelde;/",
    "iso:country":"BE",
    "sg:address":"Rue Van Artevelde 48",
    "sg:city":"Brussel/bruxelles",
    "sg:classifiers":[
        {
            "category":"Personal",
            "subcategory":"Beauty Salon",
            "type":"Services"
        }
    ],
    "sg:phone":"+32 2 513 61 03",
    "sg:postcode":"1000",
    "sg:province":"Bruxelles-Capitale",
    "sg:tags":[
        "de",
        "coiffure"
    ],
    "wof:name":"Coiffure Haar",
    "wof:placetype":"venue"
},
  "geometry": {"coordinates":[4.3462738991,50.8479232788],"type":"Point"}
}