{
  "type": "Feature",
  "properties": {
    "iso:country":"BE",
    "sg:address":"Rue Henri Lema\u00eetre 41",
    "sg:city":"Namur",
    "sg:classifiers":[
        {
            "category":"Health Services",
            "subcategory":"Doctor",
            "type":"Services"
        }
    ],
    "sg:phone":"+32 81 74 30 68",
    "sg:postcode":"5000",
    "sg:province":"Namur",
    "sg:tags":[
        "medicinephysicians",
        "surgeon"
    ],
    "wof:name":"D'hulst-verghote Martine",
    "wof:placetype":"venue"
},
  "geometry": {"coordinates":[4.8543767929,50.464931488],"type":"Point"}
}