{
  "type": "Feature",
  "properties": {
    "addr:full":"Alex Vermaelenstraat 55 Oud-heverlee (blanden) Vlaams-Brabant 3052",
    "addr:housenumber":"55",
    "addr:postcode":"3052",
    "addr:street":"Vermaelenstraat",
    "iso:country":"BE",
    "sg:address":"Alex Vermaelenstraat 55",
    "sg:city":"Oud-heverlee (blanden)",
    "sg:classifiers":[
        {
            "category":"Communications",
            "type":"Services"
        }
    ],
    "sg:phone":"+32 16 40 23 24",
    "sg:postcode":"3052",
    "sg:province":"Vlaams-Brabant",
    "sg:tags":[
        "translator"
    ],
    "wof:name":"Rutten M C",
    "wof:placetype":"venue"
},
  "geometry": {"coordinates":[4.7140197754,50.8110809326],"type":"Point"}
}