{
  "type": "Feature",
  "properties": {
    "addr:full":"Andr\u00c9 Dumontlaan 146 Genk Limburg 3600",
    "addr:housenumber":"146",
    "addr:postcode":"3600",
    "addr:street":"Dumontlaan",
    "iso:country":"BE",
    "sg:address":"Andr\u00c9 Dumontlaan 146",
    "sg:city":"Genk",
    "sg:orig_category":"V\u00e9hicules automobiles",
    "sg:phone":"+32 89 38 20 88",
    "sg:postcode":"3600",
    "sg:province":"Limburg",
    "wof:name":"Garage Willems",
    "wof:placetype":"venue"
},
  "geometry": {"coordinates":[5.5357809067,50.9919242859],"type":"Point"}
}