{
  "type": "Feature",
  "properties": {
    "iso:country":"BE",
    "sg:address":"Torhoutse Steenweg 480",
    "sg:city":"Brugge",
    "sg:orig_category":"Artistes ind\u00e9pendants",
    "sg:phone":"+32 50 38 29 38",
    "sg:postcode":"8200",
    "sg:province":"West-Vlaanderen",
    "wof:name":"Johan Nyssen",
    "wof:placetype":"venue"
},
  "geometry": {"coordinates":[3.1747438908,51.1693115234],"type":"Point"}
}