{
  "type": "Feature",
  "properties": {
    "iso:country":"BE",
    "sg:address":"Rue Jean Vinois 25",
    "sg:city":"Ellezelles",
    "sg:orig_category":"Huisdieren and benodigdheden Royal Canin",
    "sg:phone":"+32 68 54 29 99",
    "sg:postcode":"7890",
    "sg:province":"Hainaut",
    "wof:name":"Equival Sprl",
    "wof:placetype":"venue"
},
  "geometry": {"coordinates":[3.6812660694,50.732635498],"type":"Point"}
}