{
  "type": "Feature",
  "properties": {
    "iso:country":"BE",
    "sg:address":"Vaatjesstraat 38",
    "sg:city":"Putte",
    "sg:orig_category":"Producteurs de l\u00e9gumes",
    "sg:phone":"+32 15 75 67 86",
    "sg:postcode":"2580",
    "sg:province":"Antwerpen",
    "wof:name":"Louis Lettani",
    "wof:placetype":"venue"
},
  "geometry": {"coordinates":[4.6137318611,51.0414085388],"type":"Point"}
}