{
  "type": "Feature",
  "properties": {
    "iso:country":"BE",
    "sg:address":"Gistelsteenweg 35",
    "sg:city":"Jabbeke",
    "sg:classifiers":[
        {
            "category":"Autos & Motor Vehicles",
            "subcategory":"Automobile Sales",
            "type":"Retail Goods"
        }
    ],
    "sg:phone":"+32 50 38 80 66",
    "sg:postcode":"8490",
    "sg:province":"West-Vlaanderen",
    "sg:tags":[
        "car",
        "used",
        "-"
    ],
    "wof:name":"Phlips & Zonen Bvba",
    "wof:placetype":"venue"
},
  "geometry": {"coordinates":[3.1111450195,51.1791343689],"type":"Point"}
}