{
  "type": "Feature",
  "properties": {
    "addr:full":"Brakelstraat 3 Zottegem (sint-maria-oudenhove) Oost-Vlaanderen 9620",
    "addr:housenumber":"3",
    "addr:postcode":"9620",
    "addr:street":"Brakelstraat",
    "iso:country":"BE",
    "sg:address":"Brakelstraat 3",
    "sg:city":"Zottegem (sint-maria-oudenhove)",
    "sg:orig_category":"Non-Classified Establishments",
    "sg:phone":"+32 9 360 82 64",
    "sg:postcode":"9620",
    "sg:province":"Oost-Vlaanderen",
    "wof:name":"Claes S/cifa",
    "wof:placetype":"venue"
},
  "geometry": {"coordinates":[3.8112111092,50.871181488],"type":"Point"}
}