{
  "type": "Feature",
  "properties": {
    "addr:full":"Roeselaarsestraat 542 Izegem West-Vlaanderen 8870",
    "addr:housenumber":"542",
    "addr:postcode":"8870",
    "addr:street":"Roeselaarsestraat",
    "iso:country":"BE",
    "sg:address":"Roeselaarsestraat 542",
    "sg:city":"Izegem",
    "sg:classifiers":[
        {
            "category":"Professional",
            "subcategory":"Computer Services",
            "type":"Services"
        }
    ],
    "sg:phone":"+32 51 30 23 85",
    "sg:postcode":"8870",
    "sg:province":"West-Vlaanderen",
    "sg:tags":[
        "-",
        "processing",
        "data",
        "software"
    ],
    "wof:name":"Personal Soft",
    "wof:placetype":"venue"
},
  "geometry": {"coordinates":[3.1888999939,50.9245681763],"type":"Point"}
}