{
  "type": "Feature",
  "properties": {
    "addr:full":"Avenue De La Niv\u00e9ole 49 Bruxelles Bruxelles-Capitale 1020",
    "addr:housenumber":"49",
    "addr:postcode":"1020",
    "addr:street":"Avenue De La Nive\u0301Ole",
    "iso:country":"BE",
    "sg:address":"Avenue De La Niv\u00e9ole 49",
    "sg:city":"Bruxelles",
    "sg:classifiers":[
        {
            "category":"Building & Trades",
            "subcategory":"Construction",
            "type":"Services"
        }
    ],
    "sg:phone":"+32 476 44 16 30",
    "sg:postcode":"1020",
    "sg:province":"Bruxelles-Capitale",
    "sg:tags":[
        "glazier"
    ],
    "wof:name":"Van Mileghem Walter",
    "wof:placetype":"venue"
},
  "geometry": {"coordinates":[4.3673400879,50.8979988098],"type":"Point"}
}