{
  "type": "Feature",
  "properties": {
    "iso:country":"BE",
    "sg:address":"Edward Claessenslaan 94",
    "sg:city":"Niel",
    "sg:orig_category":"Brood, gebak and snoepgoed",
    "sg:phone":"+32 3 888 08 42",
    "sg:postcode":"2845",
    "sg:province":"Antwerpen",
    "wof:name":"Bakk. Baeyaert-van Praet",
    "wof:placetype":"venue"
},
  "geometry": {"coordinates":[4.328950882,51.113155365],"type":"Point"}
}