{
  "type": "Feature",
  "properties": {
    "iso:country":"BE",
    "sg:address":"Henry Fordlaan 47",
    "sg:city":"Genk",
    "sg:orig_category":"Ordinateurs and \u00e9quipement informatique. R\u00e9alisation de programmes and logiciels",
    "sg:phone":"+32 89 35 39 46",
    "sg:postcode":"3600",
    "sg:province":"Limburg",
    "wof:name":"S.a.p.",
    "wof:placetype":"venue"
},
  "geometry": {"coordinates":[5.486205101,50.9196586609],"type":"Point"}
}