{
  "type": "Feature",
  "properties": {
    "addr:full":"Charles Coppensstraat 48 Hoeilaart Vlaams-Brabant 1560",
    "addr:housenumber":"48",
    "addr:postcode":"1560",
    "addr:street":"Charles Coppensstraat",
    "iso:country":"BE",
    "sg:address":"Charles Coppensstraat 48",
    "sg:city":"Hoeilaart",
    "sg:orig_category":"Installation \u00e9lectrique r\u00e9sidentielle. Artistes ind\u00e9pendants",
    "sg:phone":"+32 2 657 05 38",
    "sg:postcode":"1560",
    "sg:province":"Vlaams-Brabant",
    "wof:name":"M. Rowies",
    "wof:placetype":"venue"
},
  "geometry": {"coordinates":[4.4714560509,50.7616233826],"type":"Point"}
}