{
  "type": "Feature",
  "properties": {
    "addr:full":"Rue De La Croix 7-9 Namur Namur 5000",
    "addr:housenumber":"7-9",
    "addr:postcode":"5000",
    "addr:street":"Rue De La Croix",
    "iso:country":"BE",
    "sg:address":"Rue De La Croix 7-9",
    "sg:city":"Namur",
    "sg:orig_category":"Meubelzaken, woning- and keukeninrichting Verlichting and huishoudartikelen",
    "sg:phone":"+32 81 22 03 03",
    "sg:postcode":"5000",
    "sg:province":"Namur",
    "wof:name":"Maison Vande Ryse",
    "wof:placetype":"venue"
},
  "geometry": {"coordinates":[4.8649439812,50.463508606],"type":"Point"}
}