{
  "type": "Feature",
  "properties": {
    "iso:country":"BE",
    "sg:address":"Rue De Gembloux 134",
    "sg:city":"Namur (saint-servais)",
    "sg:classifiers":[
        {
            "category":"Farming",
            "subcategory":"Fish & Marine Products",
            "type":"Manufacturing & Wholesale Goods"
        }
    ],
    "sg:phone":"+32 81 73 00 32",
    "sg:postcode":"5002",
    "sg:province":"Namur",
    "sg:tags":[
        "retail",
        "-",
        "shellfish"
    ],
    "wof:name":"Banquise (la)",
    "wof:placetype":"venue"
},
  "geometry": {"coordinates":[4.8462319374,50.4782791138],"type":"Point"}
}