{
  "type": "Feature",
  "properties": {
    "addr:full":"Rue De La Burlanderie 2 Florenville Luxembourg 6820",
    "addr:housenumber":"2",
    "addr:postcode":"6820",
    "addr:street":"Rue De La Burlanderie",
    "iso:country":"BE",
    "sg:address":"Rue De La Burlanderie 2",
    "sg:city":"Florenville",
    "sg:classifiers":[
        {
            "category":"Health Services",
            "subcategory":"Health Practitioner",
            "type":"Services"
        }
    ],
    "sg:phone":"+32 61 31 30 27",
    "sg:postcode":"6820",
    "sg:province":"Luxembourg",
    "sg:tags":[
        "physiotherapist"
    ],
    "wof:name":"Moreau A",
    "wof:placetype":"venue"
},
  "geometry": {"coordinates":[5.3072948456,49.6983718872],"type":"Point"}
}