{
  "type": "Feature",
  "properties": {
    "addr:full":"Langestraat 26 Aalst Oost-Vlaanderen 9300",
    "addr:housenumber":"26",
    "addr:postcode":"9300",
    "addr:street":"Langestraat",
    "iso:country":"BE",
    "sg:address":"Langestraat 26",
    "sg:city":"Aalst",
    "sg:classifiers":[
        {
            "category":"Health Services",
            "subcategory":"Health Practitioner",
            "type":"Services"
        }
    ],
    "sg:phone":"+32 53 78 50 62",
    "sg:postcode":"9300",
    "sg:province":"Oost-Vlaanderen",
    "sg:tags":[
        "physiotherapist"
    ],
    "wof:name":"De Cock Marleen",
    "wof:placetype":"venue"
},
  "geometry": {"coordinates":[4.0621209145,50.9413833618],"type":"Point"}
}