{
  "type": "Feature",
  "properties": {
    "iso:country":"BE",
    "sg:address":"Nobeekstraat 55",
    "sg:city":"Kruibeke",
    "sg:orig_category":"Ordinateurs and \u00e9quipement informatique. Entretien and r\u00e9parations de machines de bureau and ordinat",
    "sg:phone":"+32 3 774 28 23",
    "sg:postcode":"9150",
    "sg:province":"Oost-Vlaanderen",
    "wof:name":"Kryotech",
    "wof:placetype":"venue"
},
  "geometry": {"coordinates":[4.2905302048,51.1386108398],"type":"Point"}
}