{
  "type": "Feature",
  "properties": {
    "addr:full":"Rue De La Terre \u00e0 Briques 13 Tournai (blandain - Hertain) Hainaut 7522",
    "addr:housenumber":"13",
    "addr:postcode":"7522",
    "addr:street":"Rue De La Terre A\u0300 Briques;Hainaut",
    "iso:country":"BE",
    "sg:address":"Rue De La Terre \u00e0 Briques 13",
    "sg:city":"Tournai (blandain - Hertain)",
    "sg:classifiers":[
        {
            "category":"Professional",
            "subcategory":"Business Services",
            "type":"Services"
        }
    ],
    "sg:phone":"+32 69 84 63 63",
    "sg:postcode":"7522",
    "sg:province":"Hainaut",
    "sg:tags":[
        "firm"
    ],
    "wof:name":"Futur Orcq-bedrijfscentrum",
    "wof:placetype":"venue"
},
  "geometry": {"coordinates":[3.3337929249,50.6103935242],"type":"Point"}
}