{
  "type": "Feature",
  "properties": {
    "addr:full":"Bredestr 179 Putte Antwerpen 2580",
    "addr:housenumber":"179",
    "addr:postcode":"2580",
    "iso:country":"BE",
    "sg:address":"Bredestr 179",
    "sg:city":"Putte",
    "sg:classifiers":[
        {
            "category":"Personal",
            "subcategory":"Beauty Salon",
            "type":"Services"
        }
    ],
    "sg:phone":"+32 15 75 32 15",
    "sg:postcode":"2580",
    "sg:province":"Antwerpen",
    "sg:tags":[
        "de",
        "coiffure"
    ],
    "wof:name":"Knipsz",
    "wof:placetype":"venue"
},
  "geometry": {"coordinates":[4.6319699287,51.0603408813],"type":"Point"}
}