{
  "type": "Feature",
  "properties": {
    "addr:full":"Violetstraat 33 Westerlo (oevel) Antwerpen 2260",
    "addr:housenumber":"33",
    "addr:postcode":"2260",
    "addr:street":"Violetstraat",
    "iso:country":"BE",
    "sg:address":"Violetstraat 33",
    "sg:city":"Westerlo (oevel)",
    "sg:classifiers":[
        {
            "category":"Arts & Performance",
            "subcategory":"Music",
            "type":"Entertainment"
        }
    ],
    "sg:phone":"+32 14 23 52 10",
    "sg:postcode":"2260",
    "sg:province":"Antwerpen",
    "sg:tags":[
        "disc-jockeys"
    ],
    "wof:name":"Starlight",
    "wof:placetype":"venue"
},
  "geometry": {"coordinates":[4.9098567963,51.1364440918],"type":"Point"}
}