{
  "type": "Feature",
  "properties": {
    "iso:country":"BE",
    "sg:address":"Route De Saussin 36",
    "sg:city":"Jemeppe-sur-sambre (spy)",
    "sg:classifiers":[
        {
            "category":"Retail",
            "subcategory":"Auto Repair",
            "type":"Services"
        }
    ],
    "sg:phone":"+32 71 78 72 19",
    "sg:postcode":"5190",
    "sg:province":"Namur",
    "sg:tags":[
        "automobile-body"
    ],
    "wof:name":"Englebert Willy",
    "wof:placetype":"venue"
},
  "geometry": {"coordinates":[4.7194371223,50.4915733337],"type":"Point"}
}