{
  "type": "Feature",
  "properties": {
    "addr:full":"Pantheonlaan 69 Koekelberg Bruxelles-Capitale 1081",
    "addr:housenumber":"69",
    "addr:postcode":"1081",
    "addr:street":"Pantheonlaan",
    "iso:country":"BE",
    "sg:address":"Pantheonlaan 69",
    "sg:city":"Koekelberg",
    "sg:orig_category":"Kapsalons",
    "sg:phone":"+32 2 411 14 53",
    "sg:postcode":"1081",
    "sg:province":"Bruxelles-Capitale",
    "wof:name":"Tif For You",
    "wof:placetype":"venue"
},
  "geometry": {"coordinates":[4.3202428818,50.8648872375],"type":"Point"}
}