{
  "type": "Feature",
  "properties": {
    "addr:full":"Hasseltsesteenweg 384 Sint-truiden Limburg 3800",
    "addr:housenumber":"384",
    "addr:postcode":"sint-truiden;3800",
    "addr:street":"Hasseltsesteenweg",
    "iso:country":"BE",
    "sg:address":"Hasseltsesteenweg 384",
    "sg:city":"Sint-truiden",
    "sg:orig_category":"Artsen and specialisten",
    "sg:phone":"+32 11 68 24 35",
    "sg:postcode":"3800",
    "sg:province":"Limburg",
    "wof:name":"H. Lemmens",
    "wof:placetype":"venue"
},
  "geometry": {"coordinates":[5.2024002075,50.8291053772],"type":"Point"}
}