{
  "type": "Feature",
  "properties": {
    "iso:country":"BE",
    "sg:address":"Grote Baan 373",
    "sg:city":"Geraardsbergen",
    "sg:orig_category":"Supermarch\u00e9s",
    "sg:phone":"+32 54 41 29 76",
    "sg:postcode":"9500",
    "sg:province":"Oost-Vlaanderen",
    "wof:name":"Colruyt",
    "wof:placetype":"venue"
},
  "geometry": {"coordinates":[3.8763101101,50.7717781067],"type":"Point"}
}