{
  "type": "Feature",
  "properties": {
    "iso:country":"BE",
    "sg:address":"Postweg 4",
    "sg:city":"Sint-pieters-leeuw (vlezenbeek)",
    "sg:classifiers":[
        {
            "category":"Banks & Credit Unions",
            "subcategory":"Investment Brokerage",
            "type":"Services"
        }
    ],
    "sg:phone":"+32 2 569 31 70",
    "sg:postcode":"1602",
    "sg:province":"Vlaams-Brabant",
    "sg:tags":[
        "-",
        "plastic"
    ],
    "wof:name":"Atelier V.o.p. Plastics",
    "wof:placetype":"venue"
},
  "geometry": {"coordinates":[4.2582139969,50.8136711121],"type":"Point"}
}