{
  "type": "Feature",
  "properties": {
    "addr:full":"Rue Jean - Baptiste Vannypen 49 Bruxelles (auderghem) Bruxelles-Capitale 1160",
    "addr:housenumber":"49",
    "addr:postcode":"1160",
    "addr:street":"Rue Jean Baptiste Vannypen",
    "iso:country":"BE",
    "sg:address":"Rue Jean - Baptiste Vannypen 49",
    "sg:city":"Bruxelles (auderghem)",
    "sg:classifiers":[
        {
            "category":"Professional",
            "subcategory":"Art Services",
            "type":"Services"
        }
    ],
    "sg:phone":"+32 2 675 41 94",
    "sg:postcode":"1160",
    "sg:province":"Bruxelles-Capitale",
    "sg:tags":[
        "photographer"
    ],
    "wof:name":"Acken & Co",
    "wof:placetype":"venue"
},
  "geometry": {"coordinates":[4.438533783,50.8092536926],"type":"Point"}
}