{
  "type": "Feature",
  "properties": {
    "iso:country":"BE",
    "sg:address":"Rue D'oth\u00e9e 105",
    "sg:city":"Ans",
    "sg:classifiers":[
        {
            "category":"Home & Garden",
            "subcategory":"Hardware",
            "type":"Retail Goods"
        }
    ],
    "sg:phone":"+32 4 247 96 11",
    "sg:postcode":"4430",
    "sg:province":"Li\u00e8ge",
    "sg:tags":[
        "nut",
        "bolt"
    ],
    "wof:name":"Marc G\u00e9rard",
    "wof:placetype":"venue"
},
  "geometry": {"coordinates":[5.530892849,50.6652603149],"type":"Point"}
}