{
  "type": "Feature",
  "properties": {
    "addr:full":"Oude Markt 3 Leuven Vlaams-Brabant 3000",
    "addr:housenumber":"3",
    "addr:postcode":"3000",
    "addr:street":"Oude Markt",
    "iso:country":"BE",
    "sg:address":"Oude Markt 3",
    "sg:city":"Leuven",
    "sg:classifiers":[
        {
            "category":"Bars & Pubs",
            "type":"Food & Drink"
        }
    ],
    "sg:phone":"+32 16 22 26 64",
    "sg:postcode":"3000",
    "sg:province":"Vlaams-Brabant",
    "wof:name":"Ambiorix",
    "wof:placetype":"venue"
},
  "geometry": {"coordinates":[4.6999411583,50.8786582947],"type":"Point"}
}