{
  "type": "Feature",
  "properties": {
    "iso:country":"BE",
    "sg:address":"Kortrijksesteenweg 546",
    "sg:city":"Gent",
    "sg:classifiers":[
        {
            "category":"Personal",
            "subcategory":"Beauty Salon",
            "type":"Services"
        }
    ],
    "sg:phone":"+32 9 222 54 00",
    "sg:postcode":"9000",
    "sg:province":"Oost-Vlaanderen",
    "sg:tags":[
        "slimming"
    ],
    "wof:name":"Bodystiling",
    "wof:placetype":"venue"
},
  "geometry": {"coordinates":[3.7140700817,51.0324287415],"type":"Point"}
}