{
  "type": "Feature",
  "properties": {
    "addr:full":"Verlorenstraat 19 Meeuwen-gruitrode Limburg 3670",
    "addr:housenumber":"19",
    "addr:postcode":"3670",
    "addr:street":"Verlorenstraat",
    "iso:country":"BE",
    "sg:address":"Verlorenstraat 19",
    "sg:city":"Meeuwen-gruitrode",
    "sg:orig_category":"Film-, tv- and videoproductie Geluidsopnames",
    "sg:phone":"+32 89 85 89 90",
    "sg:postcode":"3670",
    "sg:province":"Limburg",
    "wof:name":"Johan Vanoosterhout",
    "wof:placetype":"venue"
},
  "geometry": {"coordinates":[5.5205497742,51.0963516235],"type":"Point"}
}