{
  "type": "Feature",
  "properties": {
    "iso:country":"BE",
    "sg:address":"Bosakker 34",
    "sg:city":"Geel",
    "sg:classifiers":[
        {
            "category":"Professional",
            "subcategory":"Engineering",
            "type":"Services"
        }
    ],
    "sg:phone":"+32 14 56 04 28",
    "sg:postcode":"2440",
    "sg:province":"Antwerpen",
    "sg:tags":[
        "-"
    ],
    "wof:name":"Veiligheidsadvies Thielemans",
    "wof:placetype":"venue"
},
  "geometry": {"coordinates":[4.9914188385,51.1728172302],"type":"Point"}
}