{
  "type": "Feature",
  "properties": {
    "addr:full":"Avenue Eug\u00c8ne Mascaux 327 Charleroi Hainaut 6001",
    "addr:housenumber":"327",
    "addr:postcode":"6001",
    "addr:street":"Avenue Euge\u0300Ne Mascaux;Hainaut",
    "iso:country":"BE",
    "sg:address":"Avenue Eug\u00c8ne Mascaux 327",
    "sg:city":"Charleroi",
    "sg:orig_category":"Librairies. Journaux. Fournitures de bureau. Tabac. Imprimeries and copyshops",
    "sg:phone":"+32 71 43 75 56",
    "sg:postcode":"6001",
    "sg:province":"Hainaut",
    "wof:name":"Librairie Christine",
    "wof:placetype":"venue"
},
  "geometry": {"coordinates":[4.4396028519,50.3924598694],"type":"Point"}
}