{
  "type": "Feature",
  "properties": {
    "addr:full":"Hoevenzavellaan 5 Genk Limburg 3600",
    "addr:housenumber":"5",
    "addr:postcode":"3600",
    "addr:street":"Hoevenzavellaan",
    "iso:country":"BE",
    "sg:address":"Hoevenzavellaan 5",
    "sg:city":"Genk",
    "sg:classifiers":[
        {
            "category":"Cafe",
            "type":"Food & Drink"
        }
    ],
    "sg:phone":"+32 89 38 28 80",
    "sg:postcode":"3600",
    "sg:province":"Limburg",
    "sg:tags":[
        "caf\u00e9s"
    ],
    "wof:name":"Caf\u00c9 Oberbayen",
    "wof:placetype":"venue"
},
  "geometry": {"coordinates":[5.5059809685,50.9989395142],"type":"Point"}
}