{
  "type": "Feature",
  "properties": {
    "iso:country":"BE",
    "sg:address":"Halle-dorp 119",
    "sg:city":"Zoersel (halle)",
    "sg:classifiers":[
        {
            "category":"Bars & Pubs",
            "type":"Food & Drink"
        }
    ],
    "sg:phone":"+32 3 294 80 50",
    "sg:postcode":"2980",
    "sg:province":"Antwerpen",
    "wof:name":"Pierenhof",
    "wof:placetype":"venue"
},
  "geometry": {"coordinates":[4.7131400108,51.2696685791],"type":"Point"}
}