{
  "type": "Feature",
  "properties": {
    "iso:country":"BE",
    "sg:address":"Vrijetijdslaan 3",
    "sg:city":"Evere/evere",
    "sg:orig_category":"Diverse kredietdiensten",
    "sg:postcode":"1140",
    "sg:province":"Bruxelles-Capitale",
    "wof:name":"Bancontact-mister Cash",
    "wof:placetype":"venue"
},
  "geometry": {"coordinates":[4.4047298431,50.8670425415],"type":"Point"}
}