{
  "type": "Feature",
  "properties": {
    "addr:full":"Kerkstraat 4 Rotselaar Vlaams-Brabant 3111",
    "addr:housenumber":"4",
    "addr:postcode":"3111",
    "addr:street":"Kerkstraat",
    "iso:country":"BE",
    "sg:address":"Kerkstraat 4",
    "sg:city":"Rotselaar",
    "sg:orig_category":"Banken and kredietinstellingen",
    "sg:phone":"+32 16 58 15 89",
    "sg:postcode":"3111",
    "sg:province":"Vlaams-Brabant",
    "wof:name":"Fortis",
    "wof:placetype":"venue"
},
  "geometry": {"coordinates":[4.7555217743,50.9477272034],"type":"Point"}
}