{
  "type": "Feature",
  "properties": {
    "addr:full":"Bizetplein 29 Anderlecht Bruxelles-Capitale 1070",
    "addr:housenumber":"29",
    "addr:postcode":"1070",
    "addr:street":"Bizetplein",
    "iso:country":"BE",
    "sg:address":"Bizetplein 29",
    "sg:city":"Anderlecht",
    "sg:orig_category":"Etalage- and showroomontwerpers",
    "sg:phone":"+32 2 521 62 41",
    "sg:postcode":"1070",
    "sg:province":"Bruxelles-Capitale",
    "wof:name":"Etalages Mafort",
    "wof:placetype":"venue"
},
  "geometry": {"coordinates":[4.2983651161,50.8249511719],"type":"Point"}
}