{
  "type": "Feature",
  "properties": {
    "iso:country":"BE",
    "sg:address":"Parvis Sainte-alix 9",
    "sg:city":"Sint-pieters-woluwe/woluwe-saint-pierre",
    "sg:orig_category":"Blanchisseries and teintureries",
    "sg:phone":"+32 2 772 43 03",
    "sg:postcode":"1150",
    "sg:province":"Bruxelles-Capitale",
    "wof:name":"La Com\u00c8te",
    "wof:placetype":"venue"
},
  "geometry": {"coordinates":[4.4615387917,50.8274421692],"type":"Point"}
}