{
  "type": "Feature",
  "properties": {
    "addr:full":"Centrumstraat 24 Zulte Oost-Vlaanderen 9870",
    "addr:housenumber":"24",
    "addr:postcode":"9870",
    "addr:street":"Centrumstraat",
    "iso:country":"BE",
    "sg:address":"Centrumstraat 24",
    "sg:city":"Zulte",
    "sg:orig_category":"Architectes",
    "sg:phone":"+32 9 388 95 29",
    "sg:postcode":"9870",
    "sg:province":"Oost-Vlaanderen",
    "wof:name":"An Van De Wiele",
    "wof:placetype":"venue"
},
  "geometry": {"coordinates":[3.4668879509,50.9348335266],"type":"Point"}
}