{
  "type": "Feature",
  "properties": {
    "iso:country":"BE",
    "sg:address":"Heldenlaan 42",
    "sg:city":"Zottegem",
    "sg:classifiers":[
        {
            "category":"Personal",
            "subcategory":"Beauty Salon",
            "type":"Services"
        }
    ],
    "sg:phone":"+32 9 360 44 90",
    "sg:postcode":"9620",
    "sg:province":"Oost-Vlaanderen",
    "sg:tags":[
        "de",
        "coiffure"
    ],
    "wof:name":"Hairclub Dirk De Witte",
    "wof:placetype":"venue"
},
  "geometry": {"coordinates":[3.8095939159,50.8709259033],"type":"Point"}
}