{
  "type": "Feature",
  "properties": {
    "iso:country":"BE",
    "sg:address":"Rue De La Clawenne 15",
    "sg:city":"Herstal",
    "sg:orig_category":"Beveiligingsdiensten and bewakingsbedrijven",
    "sg:phone":"+32 4 240 25 25",
    "sg:postcode":"4040",
    "sg:province":"Li\u00e8ge",
    "wof:name":"Patrem Security",
    "wof:placetype":"venue"
},
  "geometry": {"coordinates":[5.639067173,50.6739768982],"type":"Point"}
}