{
  "type": "Feature",
  "properties": {
    "addr:full":"Groenestraat 22 Kortrijk (heule) West-Vlaanderen 8501",
    "addr:housenumber":"22",
    "addr:postcode":"8501",
    "addr:street":"Groenestraat",
    "iso:country":"BE",
    "sg:address":"Groenestraat 22",
    "sg:city":"Kortrijk (heule)",
    "sg:classifiers":[
        {
            "category":"Autos & Motor Vehicles",
            "subcategory":"Automobile Sales",
            "type":"Retail Goods"
        }
    ],
    "sg:phone":"+32 56 35 91 03",
    "sg:postcode":"8501",
    "sg:province":"West-Vlaanderen",
    "sg:tags":[
        "delivery",
        "-",
        "used",
        "van",
        "truck"
    ],
    "wof:name":"Vanhaesebrouck Johan",
    "wof:placetype":"venue"
},
  "geometry": {"coordinates":[3.2438800335,50.8608703613],"type":"Point"}
}