{
  "type": "Feature",
  "properties": {
    "addr:full":"Kerkgate 36 Oudenaarde Oost-Vlaanderen 9700",
    "addr:housenumber":"36",
    "addr:postcode":"9700",
    "addr:street":"Kerkgate",
    "iso:country":"BE",
    "sg:address":"Kerkgate 36",
    "sg:city":"Oudenaarde",
    "sg:orig_category":"Banken and kredietinstellingen",
    "sg:phone":"+32 55 45 63 17",
    "sg:postcode":"9700",
    "sg:province":"Oost-Vlaanderen",
    "wof:name":"Kbc",
    "wof:placetype":"venue"
},
  "geometry": {"coordinates":[3.6659419537,50.8455619812],"type":"Point"}
}