{
  "type": "Feature",
  "properties": {
    "addr:full":"Ninoofsesteenweg 638 Halle Vlaams-Brabant 1500",
    "addr:housenumber":"638",
    "addr:postcode":"1500",
    "addr:street":"Ninoofsesteenweg",
    "iso:country":"BE",
    "sg:address":"Ninoofsesteenweg 638",
    "sg:city":"Halle",
    "sg:classifiers":[
        {
            "category":"Building & Trades",
            "subcategory":"Electrical",
            "type":"Services"
        }
    ],
    "sg:phone":"+32 473 71 64 96",
    "sg:postcode":"1500",
    "sg:province":"Vlaams-Brabant",
    "sg:tags":[
        "electric",
        "-",
        "housewiring",
        "contractor"
    ],
    "wof:name":"Vanderoost M",
    "wof:placetype":"venue"
},
  "geometry": {"coordinates":[4.2040472031,50.7438545227],"type":"Point"}
}