{
  "type": "Feature",
  "properties": {
    "addr:full":"Stationsstraat 169 Geel Antwerpen 2440",
    "addr:housenumber":"169",
    "addr:postcode":"2440",
    "addr:street":"Stationsstraat",
    "iso:country":"BE",
    "sg:address":"Stationsstraat 169",
    "sg:city":"Geel",
    "sg:orig_category":"Binnenhuisarchitecten Installatie van houten of kunststof schrijnwerk Meubelzaken, woning- and keuke",
    "sg:phone":"+32 14 58 65 69",
    "sg:postcode":"2440",
    "sg:province":"Antwerpen",
    "wof:name":"Meubelen Alinea",
    "wof:placetype":"venue"
},
  "geometry": {"coordinates":[4.9884901047,51.1679611206],"type":"Point"}
}