{
  "type": "Feature",
  "properties": {
    "iso:country":"BE",
    "sg:address":"Rue D\u00ceme 7",
    "sg:city":"Frasnes-lez-anvaing",
    "sg:orig_category":"Afbraak- and draineerwerken",
    "sg:phone":"+32 69 86 79 09",
    "sg:postcode":"7911",
    "sg:province":"Hainaut",
    "wof:name":"Clement",
    "wof:placetype":"venue"
},
  "geometry": {"coordinates":[3.5649609566,50.6571922302],"type":"Point"}
}