{
  "type": "Feature",
  "properties": {
    "iso:country":"BE",
    "sg:address":"Tieblokkenlaan 1",
    "sg:city":"Turnhout",
    "sg:classifiers":[
        {
            "category":"Wholesale",
            "subcategory":"Construction Materials",
            "type":"Manufacturing & Wholesale Goods"
        }
    ],
    "sg:phone":"+32 14 40 48 11",
    "sg:postcode":"2300",
    "sg:province":"Antwerpen",
    "sg:tags":[
        "adhesive"
    ],
    "wof:name":"Avery Dennison Belgi\u00eb",
    "wof:placetype":"venue"
},
  "geometry": {"coordinates":[4.9290561676,51.3011703491],"type":"Point"}
}