{
  "type": "Feature",
  "properties": {
    "addr:full":"Avenue De L'h\u00f4pital 3 Box 32 Mons Hainaut 7000",
    "addr:housenumber":"3 box 32",
    "addr:postcode":"7000",
    "addr:street":"Avenue De L'Ho \u0302Pital;Hainaut",
    "iso:country":"BE",
    "sg:address":"Avenue De L'h\u00f4pital 3 Box 32",
    "sg:city":"Mons",
    "sg:classifiers":[
        {
            "category":"Professional",
            "subcategory":"Lawyer & Legal Services",
            "type":"Services"
        }
    ],
    "sg:phone":"+32 65 84 53 20",
    "sg:postcode":"7000",
    "sg:province":"Hainaut",
    "wof:name":"Kesteman Pascal",
    "wof:placetype":"venue"
},
  "geometry": {"coordinates":[3.9622149467,50.4559860229],"type":"Point"}
}