{
  "type": "Feature",
  "properties": {
    "addr:full":"Pater Lambertusstraat 7 Bree Limburg 3960",
    "addr:housenumber":"7",
    "addr:postcode":"3960",
    "addr:street":"Pater Lambertusstraat",
    "iso:country":"BE",
    "sg:address":"Pater Lambertusstraat 7",
    "sg:city":"Bree",
    "sg:orig_category":"Artiesten and kunstenaars",
    "sg:phone":"+32 89 46 15 49",
    "sg:postcode":"3960",
    "sg:province":"Limburg",
    "wof:name":"Stefan Bongaerts",
    "wof:placetype":"venue"
},
  "geometry": {"coordinates":[5.5964941978,51.1386833191],"type":"Point"}
}