{
  "type": "Feature",
  "properties": {
    "addr:full":"Izegemseaardeweg 160 Roeselare West-Vlaanderen 8800",
    "addr:housenumber":"160",
    "addr:postcode":"8800",
    "addr:street":"Izegemseaardeweg",
    "iso:country":"BE",
    "sg:address":"Izegemseaardeweg 160",
    "sg:city":"Roeselare",
    "sg:classifiers":[
        {
            "category":"Personal",
            "subcategory":"Beauty Salon",
            "type":"Services"
        }
    ],
    "sg:phone":"+32 51 20 27 29",
    "sg:postcode":"8800",
    "sg:province":"West-Vlaanderen",
    "sg:tags":[
        "lady",
        "-",
        "hairdressing"
    ],
    "wof:name":"Lucrece",
    "wof:placetype":"venue"
},
  "geometry": {"coordinates":[3.1564600468,50.9580459595],"type":"Point"}
}