{
  "type": "Feature",
  "properties": {
    "addr:full":"Rue Pierre Biddaer 30 Bruxelles (anderlecht) Bruxelles-Capitale 1070",
    "addr:housenumber":"30",
    "addr:postcode":"1070",
    "addr:street":"Rue Pierre Biddaer",
    "iso:country":"BE",
    "sg:address":"Rue Pierre Biddaer 30",
    "sg:city":"Bruxelles (anderlecht)",
    "sg:classifiers":[
        {
            "category":"Home & Garden",
            "subcategory":"Kitchen Supply",
            "type":"Retail Goods"
        }
    ],
    "sg:phone":"+32 2 523 62 08",
    "sg:postcode":"1070",
    "sg:province":"Bruxelles-Capitale",
    "sg:tags":[
        "-",
        "industrial",
        "installation",
        "equipment"
    ],
    "wof:name":"Kvr Distribution Sa",
    "wof:placetype":"venue"
},
  "geometry": {"coordinates":[4.3086748123,50.8315582275],"type":"Point"}
}