{
  "type": "Feature",
  "properties": {
    "addr:full":"Laan Op Heusden 52 Beringen (koersel) Limburg 3582",
    "addr:housenumber":"52",
    "addr:postcode":"3582",
    "addr:street":"Laan Op Heusden",
    "iso:country":"BE",
    "sg:address":"Laan Op Heusden 52",
    "sg:city":"Beringen (koersel)",
    "sg:classifiers":[
        {
            "category":"Shopping",
            "subcategory":"Beauty & Cosmetics",
            "type":"Retail Goods"
        }
    ],
    "sg:phone":"+32 11 45 11 83",
    "sg:postcode":"3582",
    "sg:province":"Limburg",
    "sg:tags":[
        "-",
        "perfumery"
    ],
    "wof:name":"Atrium",
    "wof:placetype":"venue"
},
  "geometry": {"coordinates":[5.2708749771,51.0595359802],"type":"Point"}
}