{
  "type": "Feature",
  "properties": {
    "iso:country":"BE",
    "sg:address":"Noordzandstraat 84",
    "sg:city":"Brugge",
    "sg:orig_category":"Huishoudapparaten, televisies and radio's Verlichting and huishoudartikelen",
    "sg:phone":"+32 50 33 32 69",
    "sg:postcode":"8000",
    "sg:province":"West-Vlaanderen",
    "wof:name":"Cathenis Verlichting",
    "wof:placetype":"venue"
},
  "geometry": {"coordinates":[3.2183289528,51.2064628601],"type":"Point"}
}