{
  "type": "Feature",
  "properties": {
    "addr:full":"Rue De La Haie 65 Ecaussinnes Hainaut 7190",
    "addr:housenumber":"65",
    "addr:postcode":"7190",
    "addr:street":"Rue De La Haie;Hainaut",
    "iso:country":"BE",
    "sg:address":"Rue De La Haie 65",
    "sg:city":"Ecaussinnes",
    "sg:orig_category":"V\u00e9t\u00e9rinaires",
    "sg:phone":"+32 67 44 27 52",
    "sg:postcode":"7190",
    "sg:province":"Hainaut",
    "wof:name":"Dominique Desanthoine",
    "wof:placetype":"venue"
},
  "geometry": {"coordinates":[4.1682991982,50.5675735474],"type":"Point"}
}