{
  "type": "Feature",
  "properties": {
    "iso:country":"BE",
    "sg:address":"Kerkplein 7",
    "sg:city":"Herentals",
    "sg:orig_category":"Boekenuitgeverijen Muziekinstrumenten",
    "sg:phone":"+32 14 22 04 39",
    "sg:postcode":"2200",
    "sg:province":"Antwerpen",
    "wof:name":"Huis Limit",
    "wof:placetype":"venue"
},
  "geometry": {"coordinates":[4.8347988129,51.1743621826],"type":"Point"}
}