{
  "type": "Feature",
  "properties": {
    "iso:country":"BE",
    "sg:address":"Edmond Blockstraat 7b11",
    "sg:city":"Gent",
    "sg:orig_category":"Electrom\u00e9nager, t\u00e9l\u00e9visions and radios",
    "sg:phone":"+32 9 230 44 03",
    "sg:postcode":"9050",
    "sg:province":"Oost-Vlaanderen",
    "wof:name":"Emiel De Smet En Zonen",
    "wof:placetype":"venue"
},
  "geometry": {"coordinates":[3.7554209232,51.0452651978],"type":"Point"}
}