{
  "type": "Feature",
  "properties": {
    "iso:country":"BE",
    "sg:address":"Zwevezelestraat 77",
    "sg:city":"Lichtervelde",
    "sg:orig_category":"Benzinestations and brandstoffen Onderdelen and accessoires voor auto's",
    "sg:phone":"+32 51 72 44 59",
    "sg:postcode":"8810",
    "sg:province":"West-Vlaanderen",
    "wof:name":"Texaco",
    "wof:placetype":"venue"
},
  "geometry": {"coordinates":[3.1495120525,51.030921936],"type":"Point"}
}