{
  "type": "Feature",
  "properties": {
    "iso:country":"BE",
    "sg:address":"Rue De Ros\u00c9e 2",
    "sg:city":"Florennes",
    "sg:orig_category":"Epiceries",
    "sg:phone":"+32 82 68 88 11",
    "sg:postcode":"5620",
    "sg:province":"Namur",
    "wof:name":"Uma",
    "wof:placetype":"venue"
},
  "geometry": {"coordinates":[4.6772499084,50.2522087097],"type":"Point"}
}