{
  "type": "Feature",
  "properties": {
    "addr:full":"Pamelse Klei 27 Roosdaal Vlaams-Brabant 1760",
    "addr:housenumber":"27",
    "addr:postcode":"1760",
    "addr:street":"Klei",
    "iso:country":"BE",
    "sg:address":"Pamelse Klei 27",
    "sg:city":"Roosdaal",
    "sg:classifiers":[
        {
            "category":"Health Services",
            "subcategory":"Health Practitioner",
            "type":"Services"
        }
    ],
    "sg:phone":"+32 54 32 71 85",
    "sg:postcode":"1760",
    "sg:province":"Vlaams-Brabant",
    "sg:tags":[
        "physiotherapist"
    ],
    "wof:name":"De Vriendt Geert",
    "wof:placetype":"venue"
},
  "geometry": {"coordinates":[4.0744271278,50.8435707092],"type":"Point"}
}