{
  "type": "Feature",
  "properties": {
    "addr:full":"Lariksdreef 6 Oostkamp West-Vlaanderen 8020",
    "addr:housenumber":"6",
    "addr:postcode":"8020",
    "addr:street":"Lariksdreef",
    "iso:country":"BE",
    "sg:address":"Lariksdreef 6",
    "sg:city":"Oostkamp",
    "sg:orig_category":"Plaatsen van vloer- and muurbekleding Woningbouw",
    "sg:phone":"+32 50 27 70 45",
    "sg:postcode":"8020",
    "sg:province":"West-Vlaanderen",
    "wof:name":"Gebroeders Schoonbaert",
    "wof:placetype":"venue"
},
  "geometry": {"coordinates":[3.2175478935,51.1212844849],"type":"Point"}
}