{
  "type": "Feature",
  "properties": {
    "addr:full":"Gistelsteenweg 300 Jabbeke West-Vlaanderen 8490",
    "addr:housenumber":"300",
    "addr:postcode":"8490",
    "addr:street":"Gistelsteenweg",
    "iso:country":"BE",
    "sg:address":"Gistelsteenweg 300",
    "sg:city":"Jabbeke",
    "sg:classifiers":[
        {
            "category":"Insurance",
            "subcategory":"Insurance Agent",
            "type":"Services"
        }
    ],
    "sg:phone":"+32 50 81 68 00",
    "sg:postcode":"8490",
    "sg:province":"West-Vlaanderen",
    "sg:tags":[
        "broker"
    ],
    "wof:name":"Derca Bvba",
    "wof:placetype":"venue"
},
  "geometry": {"coordinates":[3.0935089588,51.1803703308],"type":"Point"}
}