{
  "type": "Feature",
  "properties": {
    "iso:country":"BE",
    "sg:address":"Erasmuslaan 9",
    "sg:city":"Boortmeerbeek",
    "sg:orig_category":"Experts-comptables",
    "sg:phone":"+32 15 61 58 17",
    "sg:postcode":"3191",
    "sg:province":"Vlaams-Brabant",
    "wof:name":"Freddy Caluwaerts",
    "wof:placetype":"venue"
},
  "geometry": {"coordinates":[4.554901123,50.9925537109],"type":"Point"}
}