{
  "type": "Feature",
  "properties": {
    "iso:country":"BE",
    "sg:address":"Onderstraat 106",
    "sg:city":"Gavere",
    "sg:classifiers":[
        {
            "category":"Insurance",
            "subcategory":"Insurance Agent",
            "type":"Services"
        }
    ],
    "sg:phone":"+32 9 384 78 36",
    "sg:postcode":"9890",
    "sg:province":"Oost-Vlaanderen",
    "sg:tags":[
        "broker"
    ],
    "wof:name":"Argenta/goetgebuer P",
    "wof:placetype":"venue"
},
  "geometry": {"coordinates":[3.661000967,50.9305763245],"type":"Point"}
}