{
  "type": "Feature",
  "properties": {
    "addr:full":"Rue Des Grand Carmes 6 Brussel/bruxelles Bruxelles-Capitale 1000",
    "addr:housenumber":"6",
    "addr:postcode":"1000",
    "addr:street":"Rue Des Grand Carmes;/",
    "iso:country":"BE",
    "sg:address":"Rue Des Grand Carmes 6",
    "sg:city":"Brussel/bruxelles",
    "sg:classifiers":[
        {
            "category":"Restaurant",
            "type":"Food & Drink"
        }
    ],
    "sg:phone":"+32 2 502 65 40",
    "sg:postcode":"1000",
    "sg:province":"Bruxelles-Capitale",
    "wof:name":"La Cantina Cubana",
    "wof:placetype":"venue"
},
  "geometry": {"coordinates":[4.3483738899,50.8455810547],"type":"Point"}
}