{
  "type": "Feature",
  "properties": {
    "addr:full":"Rue Bois 54b Welkenraedt Li\u00e8ge 4840",
    "addr:housenumber":"54b",
    "addr:postcode":"4840",
    "addr:street":"Rue Bois",
    "iso:country":"BE",
    "sg:address":"Rue Bois 54b",
    "sg:city":"Welkenraedt",
    "sg:orig_category":"Woningbouw",
    "sg:phone":"+32 475 66 46 43",
    "sg:postcode":"4840",
    "sg:province":"Li\u00e8ge",
    "wof:name":"Alvan",
    "wof:placetype":"venue"
},
  "geometry": {"coordinates":[5.9461150169,50.6553230286],"type":"Point"}
}