{
  "type": "Feature",
  "properties": {
    "iso:country":"BE",
    "sg:address":"Maastrichtersteenweg 30",
    "sg:city":"Hasselt",
    "sg:classifiers":[
        {
            "category":"Bars & Pubs",
            "type":"Food & Drink"
        }
    ],
    "sg:phone":"+32 11 21 01 10",
    "sg:postcode":"3500",
    "sg:province":"Limburg",
    "wof:name":"Prof 2000 (de)",
    "wof:placetype":"venue"
},
  "geometry": {"coordinates":[5.3539710045,50.9286270142],"type":"Point"}
}