{
  "type": "Feature",
  "properties": {
    "iso:country":"BE",
    "sg:address":"Rue Haut Baty 23",
    "sg:city":"Fosses-la-ville (aisemont)",
    "sg:classifiers":[
        {
            "category":"Health Services",
            "subcategory":"Doctor",
            "type":"Services"
        }
    ],
    "sg:phone":"+32 71 77 54 10",
    "sg:postcode":"5070",
    "sg:province":"Namur",
    "sg:tags":[
        "medicinephysicians",
        "surgeon"
    ],
    "wof:name":"Geerinck I",
    "wof:placetype":"venue"
},
  "geometry": {"coordinates":[4.6493330002,50.4229812622],"type":"Point"}
}