{
  "type": "Feature",
  "properties": {
    "iso:country":"BE",
    "sg:address":"Camille Huysmanslaan 5 Box 19",
    "sg:city":"Antwerpen",
    "sg:classifiers":[
        {
            "category":"Health Services",
            "subcategory":"Nursing And Care Facility",
            "type":"Services"
        }
    ],
    "sg:phone":"+32 3 216 26 42",
    "sg:postcode":"2020",
    "sg:province":"Antwerpen",
    "sg:tags":[
        "home"
    ],
    "wof:name":"Van De Voorde B",
    "wof:placetype":"venue"
},
  "geometry": {"coordinates":[4.3971290588,51.1914978027],"type":"Point"}
}