{
  "type": "Feature",
  "properties": {
    "iso:country":"BE",
    "sg:address":"Route De Gosselies 392",
    "sg:city":"Fleurus",
    "sg:orig_category":"Artiesten and kunstenaars",
    "sg:phone":"+32 71 81 27 79",
    "sg:postcode":"6220",
    "sg:province":"Hainaut",
    "wof:name":"Jean-luc Draye",
    "wof:placetype":"venue"
},
  "geometry": {"coordinates":[4.5218100548,50.4741401672],"type":"Point"}
}