{
  "type": "Feature",
  "properties": {
    "iso:country":"BE",
    "sg:address":"Kerkstraat 26a",
    "sg:city":"Lochristi",
    "sg:orig_category":"Verlichting and huishoudartikelen",
    "sg:phone":"+32 9 356 80 36",
    "sg:postcode":"9080",
    "sg:province":"Oost-Vlaanderen",
    "wof:name":"Kaifi",
    "wof:placetype":"venue"
},
  "geometry": {"coordinates":[3.864937067,51.127494812],"type":"Point"}
}