{
  "type": "Feature",
  "properties": {
    "iso:country":"BE",
    "sg:address":"Chemin De Perwez 5",
    "sg:city":"Huy",
    "sg:orig_category":"Herstellingen and onderhoud van auto's",
    "sg:phone":"+32 85 21 33 13",
    "sg:postcode":"4500",
    "sg:province":"Li\u00e8ge",
    "wof:name":"Garage Libois",
    "wof:placetype":"venue"
},
  "geometry": {"coordinates":[5.1760139465,50.4831237793],"type":"Point"}
}