{
  "type": "Feature",
  "properties": {
    "addr:full":"Nieuwpoortlaan 21 De Panne West-Vlaanderen 8660",
    "addr:housenumber":"21",
    "addr:postcode":"8660",
    "addr:street":"Nieuwpoortlaan",
    "iso:country":"BE",
    "sg:address":"Nieuwpoortlaan 21",
    "sg:city":"De Panne",
    "sg:classifiers":[
        {
            "category":"Restaurant",
            "type":"Food & Drink"
        }
    ],
    "sg:phone":"+32 58 41 22 64",
    "sg:postcode":"8660",
    "sg:province":"West-Vlaanderen",
    "wof:name":"Bristol",
    "wof:placetype":"venue"
},
  "geometry": {"coordinates":[2.5912790298,51.1032714844],"type":"Point"}
}