{
  "type": "Feature",
  "properties": {
    "addr:full":"Rue De L'obus 199 Anderlecht Bruxelles-Capitale 1070",
    "addr:housenumber":"199",
    "addr:postcode":"1070",
    "addr:street":"Rue De L'Obus",
    "iso:country":"BE",
    "sg:address":"Rue De L'obus 199",
    "sg:city":"Anderlecht",
    "sg:orig_category":"Studios photographiques",
    "sg:phone":"+32 2 520 95 54",
    "sg:postcode":"1070",
    "sg:province":"Bruxelles-Capitale",
    "wof:name":"Thierry Rog\u00c9",
    "wof:placetype":"venue"
},
  "geometry": {"coordinates":[4.306388855,50.8409576416],"type":"Point"}
}