{
  "type": "Feature",
  "properties": {
    "addr:full":"Brasschaatselei 10ba Kapellen Antwerpen 2950",
    "addr:housenumber":"10ba",
    "addr:postcode":"2950",
    "addr:street":"Brasschaatselei",
    "iso:country":"BE",
    "sg:address":"Brasschaatselei 10ba",
    "sg:city":"Kapellen",
    "sg:orig_category":"Voertuigen",
    "sg:phone":"+32 3 666 66 44",
    "sg:postcode":"2950",
    "sg:province":"Antwerpen",
    "wof:name":"Jasperse O.n.o",
    "wof:placetype":"venue"
},
  "geometry": {"coordinates":[4.4713969231,51.3473815918],"type":"Point"}
}