{
  "type": "Feature",
  "properties": {
    "addr:full":"Blekerijstraat 81 Roeselare West-Vlaanderen 8800",
    "addr:housenumber":"81",
    "addr:postcode":"8800",
    "addr:street":"Blekerijstraat",
    "iso:country":"BE",
    "sg:address":"Blekerijstraat 81",
    "sg:city":"Roeselare",
    "sg:classifiers":[
        {
            "category":"Cafe",
            "type":"Food & Drink"
        }
    ],
    "sg:phone":"+32 51 20 35 81",
    "sg:postcode":"8800",
    "sg:province":"West-Vlaanderen",
    "sg:tags":[
        "caf\u00e9s"
    ],
    "wof:name":"Caf\u00c9 't Vlaams Front",
    "wof:placetype":"venue"
},
  "geometry": {"coordinates":[3.1195321083,50.9426307678],"type":"Point"}
}