{
  "type": "Feature",
  "properties": {
    "addr:full":"Bormtestraat 116 Stekene Oost-Vlaanderen 9190",
    "addr:housenumber":"116",
    "addr:postcode":"9190",
    "addr:street":"Bormtestraat",
    "iso:country":"BE",
    "sg:address":"Bormtestraat 116",
    "sg:city":"Stekene",
    "sg:classifiers":[
        {
            "category":"Insurance",
            "subcategory":"Insurance Agent",
            "type":"Services"
        }
    ],
    "sg:phone":"+32 3 789 98 20",
    "sg:postcode":"9190",
    "sg:province":"Oost-Vlaanderen",
    "sg:tags":[
        "broker"
    ],
    "wof:name":"Uab-verzekeringen",
    "wof:placetype":"venue"
},
  "geometry": {"coordinates":[4.0445141792,51.1999320984],"type":"Point"}
}