{
  "type": "Feature",
  "properties": {
    "iso:country":"BE",
    "sg:address":"Dorp 1bb",
    "sg:city":"Alveringem",
    "sg:orig_category":"Overheidsdiensten",
    "sg:phone":"+32 58 28 08 20",
    "sg:postcode":"8690",
    "sg:province":"West-Vlaanderen",
    "wof:name":"O.c.m.w.",
    "wof:placetype":"venue"
},
  "geometry": {"coordinates":[2.7107961178,51.0116844177],"type":"Point"}
}