{
  "type": "Feature",
  "properties": {
    "addr:full":"Mechelsesteenweg 15 Leuven Vlaams-Brabant 3012",
    "addr:housenumber":"15",
    "addr:postcode":"3012",
    "addr:street":"Mechelsesteenweg",
    "iso:country":"BE",
    "sg:address":"Mechelsesteenweg 15",
    "sg:city":"Leuven",
    "sg:classifiers":[
        {
            "category":"Personal",
            "subcategory":"Beauty Salon",
            "type":"Services"
        }
    ],
    "sg:phone":"+32 16 22 69 90",
    "sg:postcode":"3012",
    "sg:province":"Vlaams-Brabant",
    "sg:tags":[
        "de",
        "coiffure"
    ],
    "wof:name":"Wax Incorporate",
    "wof:placetype":"venue"
},
  "geometry": {"coordinates":[4.6947407722,50.8903617859],"type":"Point"}
}