{
  "type": "Feature",
  "properties": {
    "addr:full":"Lantaarnstraatje 8 Aalter Oost-Vlaanderen 9880",
    "addr:housenumber":"8",
    "addr:postcode":"9880",
    "addr:street":"Lantaarnstraatje",
    "iso:country":"BE",
    "sg:address":"Lantaarnstraatje 8",
    "sg:city":"Aalter",
    "sg:orig_category":"Rev\u00eatements pour sols and murs",
    "sg:phone":"+32 9 374 56 29",
    "sg:postcode":"9880",
    "sg:province":"Oost-Vlaanderen",
    "wof:name":"Eddy Van Damme",
    "wof:placetype":"venue"
},
  "geometry": {"coordinates":[3.3706159592,51.092048645],"type":"Point"}
}