{
  "type": "Feature",
  "properties": {
    "iso:country":"BE",
    "sg:address":"Rue Saint-lambert 3",
    "sg:city":"Walcourt",
    "sg:orig_category":"Location de v\u00eatements, chaussures and textiles",
    "sg:phone":"+32 71 65 05 07",
    "sg:postcode":"5650",
    "sg:province":"Namur",
    "wof:name":"Roger Sauvage (children)",
    "wof:placetype":"venue"
},
  "geometry": {"coordinates":[4.5072960854,50.2368125916],"type":"Point"}
}