{
  "type": "Feature",
  "properties": {
    "addr:full":"17 Kapelstraat 3590 Diepenbeek 17",
    "addr:housenumber":"17",
    "addr:postcode":"3590",
    "addr:street":"Kapelstraat",
    "iso:country":"BE",
    "sg:address":"17",
    "sg:city":"Kapelstraat 3590 Diepenbeek",
    "sg:classifiers":[
        {
            "category":"Professional",
            "subcategory":"Engineering",
            "type":"Services"
        }
    ],
    "sg:phone":"+32 11 28 70 70",
    "sg:postcode":"17",
    "sg:tags":[
        "machine",
        "-",
        "environment",
        "equipment",
        "machinery",
        "mechanical"
    ],
    "wof:name":"Remo Milieubeheer Nv",
    "wof:placetype":"venue"
},
  "geometry": {"coordinates":[5.4158849716,50.9101448059],"type":"Point"}
}