{
  "type": "Feature",
  "properties": {
    "addr:full":"Noordlaan 22 Kuurne West-Vlaanderen 8520",
    "addr:housenumber":"22",
    "addr:postcode":"8520",
    "addr:street":"Noordlaan",
    "iso:country":"BE",
    "sg:address":"Noordlaan 22",
    "sg:city":"Kuurne",
    "sg:orig_category":"V\u00e9hicules automobiles",
    "sg:phone":"+32 56 35 65 57",
    "sg:postcode":"8520",
    "sg:province":"West-Vlaanderen",
    "wof:name":"Fibotrans",
    "wof:placetype":"venue"
},
  "geometry": {"coordinates":[3.262182951,50.8610343933],"type":"Point"}
}