{
  "type": "Feature",
  "properties": {
    "addr:full":"Flanders Fieldweg 37 Waregem West-Vlaanderen 8790",
    "addr:housenumber":"37",
    "addr:postcode":"8790",
    "addr:street":"Fieldweg",
    "iso:country":"BE",
    "sg:address":"Flanders Fieldweg 37",
    "sg:city":"Waregem",
    "sg:orig_category":"Formation permanente. Enseignement secondaire technique and professionnel",
    "sg:phone":"+32 56 62 73 73",
    "sg:postcode":"8790",
    "sg:province":"West-Vlaanderen",
    "wof:name":"Concordia Textiles",
    "wof:placetype":"venue"
},
  "geometry": {"coordinates":[3.4485189915,50.8702316284],"type":"Point"}
}