{
  "type": "Feature",
  "properties": {
    "addr:full":"Ruddervoordestraat 80 Torhout West-Vlaanderen 8820",
    "addr:housenumber":"80",
    "addr:postcode":"8820",
    "addr:street":"Ruddervoordestraat",
    "iso:country":"BE",
    "sg:address":"Ruddervoordestraat 80",
    "sg:city":"Torhout",
    "sg:classifiers":[
        {
            "category":"Shopping",
            "subcategory":"Crafts & Fabrics",
            "type":"Retail Goods"
        }
    ],
    "sg:phone":"+32 50 21 63 17",
    "sg:postcode":"8820",
    "sg:province":"West-Vlaanderen",
    "sg:tags":[
        "pleating",
        "embroidery"
    ],
    "wof:name":"Couture Marie-rose",
    "wof:placetype":"venue"
},
  "geometry": {"coordinates":[3.1146829128,51.0635871887],"type":"Point"}
}