{
  "type": "Feature",
  "properties": {
    "addr:full":"Hofdreef 94 Wuustwezel Antwerpen 2990",
    "addr:housenumber":"94",
    "addr:postcode":"2990",
    "addr:street":"Hofdreef",
    "iso:country":"BE",
    "sg:address":"Hofdreef 94",
    "sg:city":"Wuustwezel",
    "sg:orig_category":"Experts-comptables",
    "sg:phone":"+32 3 669 50 24",
    "sg:postcode":"2990",
    "sg:province":"Antwerpen",
    "wof:name":"Marc Aertsen",
    "wof:placetype":"venue"
},
  "geometry": {"coordinates":[4.6322259903,51.4015083313],"type":"Point"}
}