{
  "type": "Feature",
  "properties": {
    "iso:country":"BE",
    "sg:address":"Palinghuizen 65",
    "sg:city":"Gent",
    "sg:orig_category":"Textiel",
    "sg:phone":"+32 9 227 95 25",
    "sg:postcode":"9000",
    "sg:province":"Oost-Vlaanderen",
    "wof:name":"Denise De Vos",
    "wof:placetype":"venue"
},
  "geometry": {"coordinates":[3.7004909515,51.0657844543],"type":"Point"}
}