{
  "type": "Feature",
  "properties": {
    "iso:country":"BE",
    "sg:address":"Dokter De Drijverestraat 63",
    "sg:city":"Brakel (nederbrakel)",
    "sg:classifiers":[
        {
            "category":"Health Services",
            "subcategory":"Doctor",
            "type":"Services"
        }
    ],
    "sg:phone":"+32 55 42 89 35",
    "sg:postcode":"9660",
    "sg:province":"Oost-Vlaanderen",
    "sg:tags":[
        "medicinephysicians",
        "surgeon"
    ],
    "wof:name":"Jacobs Veronique",
    "wof:placetype":"venue"
},
  "geometry": {"coordinates":[3.7693560123,50.8014678955],"type":"Point"}
}