{
  "type": "Feature",
  "properties": {
    "addr:full":"Spinele 6 Brakel (everbeek) Oost-Vlaanderen 9660",
    "addr:housenumber":"6",
    "addr:postcode":"9660",
    "addr:street":"Spinele",
    "iso:country":"BE",
    "sg:address":"Spinele 6",
    "sg:city":"Brakel (everbeek)",
    "sg:classifiers":[
        {
            "category":"Health Services",
            "subcategory":"Health Practitioner",
            "type":"Services"
        }
    ],
    "sg:phone":"+32 55 42 43 96",
    "sg:postcode":"9660",
    "sg:province":"Oost-Vlaanderen",
    "sg:tags":[
        "therapist",
        "speech"
    ],
    "wof:name":"Faut K",
    "wof:placetype":"venue"
},
  "geometry": {"coordinates":[3.7642250061,50.8031082153],"type":"Point"}
}