{
  "type": "Feature",
  "properties": {
    "addr:full":"Staatsbaan 59 Bekkevoort Vlaams-Brabant 3460",
    "addr:housenumber":"59",
    "addr:postcode":"3460",
    "addr:street":"Staatsbaan",
    "iso:country":"BE",
    "sg:address":"Staatsbaan 59",
    "sg:city":"Bekkevoort",
    "sg:orig_category":"Electrom\u00e9nager, t\u00e9l\u00e9visions and radios",
    "sg:phone":"+32 13 31 27 43",
    "sg:postcode":"3460",
    "sg:province":"Vlaams-Brabant",
    "wof:name":"Maurice Das",
    "wof:placetype":"venue"
},
  "geometry": {"coordinates":[4.9852399826,50.9479370117],"type":"Point"}
}