{
  "type": "Feature",
  "properties": {
    "addr:full":"Avenue Eug\u00c8ne Mascaux 193 Charleroi Hainaut 6001",
    "addr:housenumber":"193",
    "addr:postcode":"6001",
    "addr:street":"Avenue Euge\u0300Ne Mascaux;Hainaut",
    "iso:country":"BE",
    "sg:address":"Avenue Eug\u00c8ne Mascaux 193",
    "sg:city":"Charleroi",
    "sg:orig_category":"Tabac",
    "sg:phone":"+32 71 36 26 02",
    "sg:postcode":"6001",
    "sg:province":"Hainaut",
    "wof:name":"Jacques Hublet",
    "wof:placetype":"venue"
},
  "geometry": {"coordinates":[4.4431362152,50.3956336975],"type":"Point"}
}