{
  "type": "Feature",
  "properties": {
    "addr:full":"Rue De La Broucheterre 19 Charleroi Hainaut 6000",
    "addr:housenumber":"19",
    "addr:postcode":"6000",
    "addr:street":"Rue De La Broucheterre;Hainaut",
    "iso:country":"BE",
    "sg:address":"Rue De La Broucheterre 19",
    "sg:city":"Charleroi",
    "sg:orig_category":"Openbare bibliotheken and archieven",
    "sg:phone":"+32 71 53 12 11",
    "sg:postcode":"6000",
    "sg:province":"Hainaut",
    "wof:name":"Ludo Univ. Du Travail",
    "wof:placetype":"venue"
},
  "geometry": {"coordinates":[4.4455499649,50.4187889099],"type":"Point"}
}