{
  "type": "Feature",
  "properties": {
    "iso:country":"BE",
    "sg:address":"Muntstraat 10",
    "sg:city":"Leuven",
    "sg:orig_category":"Antiek",
    "sg:phone":"+32 16 23 39 19",
    "sg:postcode":"3000",
    "sg:province":"Vlaams-Brabant",
    "wof:name":"Cornelius Engelen",
    "wof:placetype":"venue"
},
  "geometry": {"coordinates":[4.7017140388,50.8784332275],"type":"Point"}
}