{
  "type": "Feature",
  "properties": {
    "iso:country":"BE",
    "sg:address":"Doornstraat 115",
    "sg:city":"Temse",
    "sg:orig_category":"Agences de presse",
    "sg:phone":"+32 3 771 03 98",
    "sg:postcode":"9140",
    "sg:province":"Oost-Vlaanderen",
    "wof:name":"Caroline Tyck",
    "wof:placetype":"venue"
},
  "geometry": {"coordinates":[4.2063717842,51.1456871033],"type":"Point"}
}