{
  "type": "Feature",
  "properties": {
    "addr:full":"Eernegemweg 29 Jabbeke (snellegem) West-Vlaanderen 8490",
    "addr:housenumber":"29",
    "addr:postcode":"8490",
    "addr:street":"Eernegemweg",
    "iso:country":"BE",
    "sg:address":"Eernegemweg 29",
    "sg:city":"Jabbeke (snellegem)",
    "sg:classifiers":[
        {
            "category":"Retail",
            "subcategory":"Veterinary Services",
            "type":"Services"
        }
    ],
    "sg:phone":"+32 50 54 84 05",
    "sg:postcode":"8490",
    "sg:province":"West-Vlaanderen",
    "sg:tags":[
        "veterinarian"
    ],
    "wof:name":"Van Acker S",
    "wof:placetype":"venue"
},
  "geometry": {"coordinates":[3.1199979782,51.1678543091],"type":"Point"}
}