{
  "type": "Feature",
  "properties": {
    "addr:full":"Rue Eloy 46 Anderlecht Bruxelles-Capitale 1070",
    "addr:housenumber":"46",
    "addr:postcode":"1070",
    "addr:street":"Rue Eloy",
    "iso:country":"BE",
    "sg:address":"Rue Eloy 46",
    "sg:city":"Anderlecht",
    "sg:classifiers":[
        {
            "category":"Cafe",
            "type":"Food & Drink"
        }
    ],
    "sg:phone":"+32 2 523 66 18",
    "sg:postcode":"1070",
    "sg:province":"Bruxelles-Capitale",
    "sg:tags":[
        "caf\u00e9s"
    ],
    "wof:name":"Caf\u00c9 Le Platane",
    "wof:placetype":"venue"
},
  "geometry": {"coordinates":[4.3284521103,50.8363571167],"type":"Point"}
}