{
  "type": "Feature",
  "properties": {
    "addr:full":"Boulevard Ernest Solvay 254 Li\u00c8ge Li\u00e8ge 4000",
    "addr:housenumber":"254",
    "addr:postcode":"4000",
    "addr:street":"Boulevard Ernest Solvay",
    "iso:country":"BE",
    "sg:address":"Boulevard Ernest Solvay 254",
    "sg:city":"Li\u00c8ge",
    "sg:orig_category":"M\u00e9decins and sp\u00e9cialistes",
    "sg:phone":"+32 4 227 45 33",
    "sg:postcode":"4000",
    "sg:province":"Li\u00e8ge",
    "wof:name":"Antonio Lombardo",
    "wof:placetype":"venue"
},
  "geometry": {"coordinates":[5.5969147682,50.6607666016],"type":"Point"}
}