{
  "type": "Feature",
  "properties": {
    "addr:full":"Meensesteenweg 401 Kortrijk West-Vlaanderen 8501",
    "addr:housenumber":"401",
    "addr:postcode":"8501",
    "addr:street":"Meensesteenweg",
    "iso:country":"BE",
    "sg:address":"Meensesteenweg 401",
    "sg:city":"Kortrijk",
    "sg:orig_category":"Banques and organismes de cr\u00e9dit",
    "sg:phone":"+32 56 35 10 17",
    "sg:postcode":"8501",
    "sg:province":"West-Vlaanderen",
    "wof:name":"Kbc",
    "wof:placetype":"venue"
},
  "geometry": {"coordinates":[3.2263569832,50.822971344],"type":"Point"}
}