{
  "type": "Feature",
  "properties": {
    "addr:full":"Huidevettersstraat 58 Antwerpen Antwerpen 2000",
    "addr:housenumber":"58",
    "addr:postcode":"2000",
    "addr:street":"Huidevettersstraat",
    "iso:country":"BE",
    "sg:address":"Huidevettersstraat 58",
    "sg:city":"Antwerpen",
    "sg:classifiers":[
        {
            "category":"Restaurant",
            "type":"Food & Drink"
        }
    ],
    "sg:phone":"+32 3 231 18 52",
    "sg:postcode":"2000",
    "sg:province":"Antwerpen",
    "wof:name":"Matterhorn",
    "wof:placetype":"venue"
},
  "geometry": {"coordinates":[4.4048190117,51.2163047791],"type":"Point"}
}