{
  "type": "Feature",
  "properties": {
    "addr:full":"Strainchamps 8 Fauvillers Luxembourg 6637",
    "addr:housenumber":"8",
    "addr:postcode":"6637",
    "addr:street":"Strainchamps",
    "iso:country":"BE",
    "sg:address":"Strainchamps 8",
    "sg:city":"Fauvillers",
    "sg:classifiers":[
        {
            "category":"Parking",
            "subcategory":"Lot",
            "type":"Transportation"
        }
    ],
    "sg:phone":"+32 63 60 08 18",
    "sg:postcode":"6637",
    "sg:province":"Luxembourg",
    "sg:tags":[
        "parking-places",
        "laying-out"
    ],
    "wof:name":"Noiset A",
    "wof:placetype":"venue"
},
  "geometry": {"coordinates":[5.6638197899,49.8519592285],"type":"Point"}
}