{
  "type": "Feature",
  "properties": {
    "addr:full":"Gentsestraat 50 Sint-lievens-houtem Oost-Vlaanderen 9520",
    "addr:housenumber":"50",
    "addr:postcode":"9520",
    "addr:street":"Gentsestraat;Oost-Vlaanderen",
    "iso:country":"BE",
    "sg:address":"Gentsestraat 50",
    "sg:city":"Sint-lievens-houtem",
    "sg:orig_category":"Cr\u00e8ches and garderies d'enfants",
    "sg:phone":"+32 53 62 19 82",
    "sg:postcode":"9520",
    "sg:province":"Oost-Vlaanderen",
    "wof:name":"Kribbe Pipo",
    "wof:placetype":"venue"
},
  "geometry": {"coordinates":[3.9077188969,50.9272727966],"type":"Point"}
}