{
  "type": "Feature",
  "properties": {
    "iso:country":"BE",
    "sg:address":"Walbosstraat 14",
    "sg:city":"Destelbergen",
    "sg:orig_category":"Pleisterwerk",
    "sg:phone":"+32 9 228 15 15",
    "sg:postcode":"9070",
    "sg:province":"Oost-Vlaanderen",
    "wof:name":"Hebbelinck Bezetwerken",
    "wof:placetype":"venue"
},
  "geometry": {"coordinates":[3.7902960777,51.0551528931],"type":"Point"}
}