{
  "type": "Feature",
  "properties": {
    "iso:country":"BE",
    "sg:address":"Rue Fontaine D'amour 14",
    "sg:city":"Schaarbeek/schaerbeek",
    "sg:orig_category":"Charpentes and couvertures",
    "sg:phone":"+32 2 241 20 80",
    "sg:postcode":"1030",
    "sg:province":"Bruxelles-Capitale",
    "wof:name":"Jean-marie Godart",
    "wof:placetype":"venue"
},
  "geometry": {"coordinates":[4.3825330734,50.8605728149],"type":"Point"}
}