{
  "type": "Feature",
  "properties": {
    "addr:full":"Rue De L'ypr\u00c9au 16 Ronse/renaix Oost-Vlaanderen 9600",
    "addr:housenumber":"16",
    "addr:postcode":"9600",
    "addr:street":"Rue De L'Ypre \u0301Au",
    "iso:country":"BE",
    "sg:address":"Rue De L'ypr\u00c9au 16",
    "sg:city":"Ronse/renaix",
    "sg:orig_category":"Alimentation sp\u00e9cialis\u00e9e",
    "sg:phone":"+32 55 20 73 77",
    "sg:postcode":"9600",
    "sg:province":"Oost-Vlaanderen",
    "wof:name":"Huis Natuur & Dieet",
    "wof:placetype":"venue"
},
  "geometry": {"coordinates":[3.5999140739,50.7458534241],"type":"Point"}
}