{
  "type": "Feature",
  "properties": {
    "iso:country":"BE",
    "sg:address":"Rue Neuve 51",
    "sg:city":"Charleroi",
    "sg:classifiers":[
        {
            "category":"Restaurant",
            "type":"Food & Drink"
        }
    ],
    "sg:phone":"+32 71 70 17 03",
    "sg:postcode":"6000",
    "sg:province":"Hainaut",
    "wof:name":"Snack-bar L'ideal",
    "wof:placetype":"venue"
},
  "geometry": {"coordinates":[4.4458031654,50.4134292603],"type":"Point"}
}