{
  "type": "Feature",
  "properties": {
    "addr:full":"St Rochusstr 97 Halle Vlaams-Brabant 1500",
    "addr:housenumber":"97",
    "addr:postcode":"1500",
    "iso:country":"BE",
    "sg:address":"St Rochusstr 97",
    "sg:city":"Halle",
    "sg:classifiers":[
        {
            "category":"Banks & Credit Unions",
            "subcategory":"Bank",
            "type":"Services"
        }
    ],
    "sg:phone":"+32 2 361 28 51",
    "sg:postcode":"1500",
    "sg:province":"Vlaams-Brabant",
    "wof:name":"Kredietbank Nv",
    "wof:placetype":"venue"
},
  "geometry": {"coordinates":[4.2332601547,50.737953186],"type":"Point"}
}