{
  "type": "Feature",
  "properties": {
    "addr:full":"Leuvensestraat 9 Aarschot (groot) Vlaams-Brabant 3200",
    "addr:housenumber":"9",
    "addr:postcode":"3200",
    "addr:street":"Leuvensestraat;Groot Vlaams-Brabant",
    "iso:country":"BE",
    "sg:address":"Leuvensestraat 9",
    "sg:city":"Aarschot (groot)",
    "sg:orig_category":"Textiel",
    "sg:phone":"+32 16 56 86 18",
    "sg:postcode":"3200",
    "sg:province":"Vlaams-Brabant",
    "wof:name":"Huis Analca",
    "wof:placetype":"venue"
},
  "geometry": {"coordinates":[4.8310399055,50.9835510254],"type":"Point"}
}