{
  "type": "Feature",
  "properties": {
    "iso:country":"BE",
    "sg:address":"Rue Des Pieds D'alouette 7",
    "sg:city":"Namur (naninne)",
    "sg:classifiers":[
        {
            "category":"Professional",
            "type":"Services"
        }
    ],
    "sg:phone":"+32 81 40 04 28",
    "sg:postcode":"5100",
    "sg:province":"Namur",
    "sg:tags":[
        "industrial",
        "work",
        "-",
        "maintenance"
    ],
    "wof:name":"Mrt",
    "wof:placetype":"venue"
},
  "geometry": {"coordinates":[4.9310631752,50.4230422974],"type":"Point"}
}