{
  "type": "Feature",
  "properties": {
    "addr:full":"Bisschopslaan 32 Beerse Antwerpen 2340",
    "addr:housenumber":"32",
    "addr:postcode":"2340",
    "addr:street":"Bisschopslaan",
    "iso:country":"BE",
    "sg:address":"Bisschopslaan 32",
    "sg:city":"Beerse",
    "sg:orig_category":"S\u00e9curit\u00e9 sociale",
    "sg:phone":"+32 14 61 14 92",
    "sg:postcode":"2340",
    "sg:province":"Antwerpen",
    "wof:name":"Socialist. Mutualiteit",
    "wof:placetype":"venue"
},
  "geometry": {"coordinates":[4.8557500839,51.3168029785],"type":"Point"}
}