{
  "type": "Feature",
  "properties": {
    "iso:country":"BE",
    "sg:address":"Vlaamse Kaai 40",
    "sg:city":"Antwerpen",
    "sg:orig_category":"Brood, gebak and snoepgoed Restaurants",
    "sg:phone":"+32 3 238 37 76",
    "sg:postcode":"2000",
    "sg:province":"Antwerpen",
    "wof:name":"Farine's Food & Future",
    "wof:placetype":"venue"
},
  "geometry": {"coordinates":[4.3909311295,51.2097244263],"type":"Point"}
}