{
  "type": "Feature",
  "properties": {
    "addr:full":"Lambermontlaan 34ba Schaarbeek/schaerbeek Bruxelles-Capitale 1030",
    "addr:housenumber":"34ba",
    "addr:postcode":"1030",
    "addr:street":"Lambermontlaan",
    "iso:country":"BE",
    "sg:address":"Lambermontlaan 34ba",
    "sg:city":"Schaarbeek/schaerbeek",
    "sg:orig_category":"Artiesten and kunstenaars",
    "sg:phone":"+32 2 215 57 51",
    "sg:postcode":"1030",
    "sg:province":"Bruxelles-Capitale",
    "wof:name":"Cao Bei-an",
    "wof:placetype":"venue"
},
  "geometry": {"coordinates":[4.3756308556,50.8745346069],"type":"Point"}
}