{
  "type": "Feature",
  "properties": {
    "addr:full":"Rue De La Chapelle 44 Kelmis/la Calamine Li\u00e8ge 4720",
    "addr:housenumber":"44",
    "addr:postcode":"4720",
    "addr:street":"Rue De La Chapelle",
    "iso:country":"BE",
    "sg:address":"Rue De La Chapelle 44",
    "sg:city":"Kelmis/la Calamine",
    "sg:orig_category":"Armes and munitions. Parfumeries",
    "sg:phone":"+32 87 65 90 91",
    "sg:postcode":"4720",
    "sg:province":"Li\u00e8ge",
    "wof:name":"Maison De Rycke",
    "wof:placetype":"venue"
},
  "geometry": {"coordinates":[6.0121397972,50.7155456543],"type":"Point"}
}