{
  "type": "Feature",
  "properties": {
    "addr:full":"Rue Pair\u00c9e 38 Libin Luxembourg 6890",
    "addr:housenumber":"38",
    "addr:postcode":"6890",
    "addr:street":"Rue Paire\u0301E",
    "iso:country":"BE",
    "sg:address":"Rue Pair\u00c9e 38",
    "sg:city":"Libin",
    "sg:orig_category":"V\u00e9los",
    "sg:phone":"+32 61 65 57 87",
    "sg:postcode":"6890",
    "sg:province":"Luxembourg",
    "wof:name":"Jean Breuskin",
    "wof:placetype":"venue"
},
  "geometry": {"coordinates":[5.2584071159,49.9781227112],"type":"Point"}
}