{
  "type": "Feature",
  "properties": {
    "iso:country":"BE",
    "sg:address":"Chauss\u00c9e De Lille 124",
    "sg:city":"Komen-waasten/comines-warneton",
    "sg:orig_category":"Poissonniers and \u00e9caillers",
    "sg:phone":"+32 56 58 98 13",
    "sg:postcode":"7784",
    "sg:province":"Hainaut",
    "wof:name":"Peggy Mesure",
    "wof:placetype":"venue"
},
  "geometry": {"coordinates":[2.9404909611,50.7490615845],"type":"Point"}
}