{
  "type": "Feature",
  "properties": {
    "addr:full":"Van Schoonbekestraat 186 Antwerpen Antwerpen 2018",
    "addr:housenumber":"186",
    "addr:postcode":"2018",
    "addr:street":"Van Schoonbekestraat",
    "iso:country":"BE",
    "sg:address":"Van Schoonbekestraat 186",
    "sg:city":"Antwerpen",
    "sg:classifiers":[
        {
            "category":"Restaurant",
            "type":"Food & Drink"
        }
    ],
    "sg:phone":"+32 3 248 11 41",
    "sg:postcode":"2018",
    "sg:province":"Antwerpen",
    "wof:name":"Taverne De Grave",
    "wof:placetype":"venue"
},
  "geometry": {"coordinates":[4.4024658203,51.1987380981],"type":"Point"}
}