{
  "type": "Feature",
  "properties": {
    "addr:full":"Avenue Du Roi Albert 168 Box 1 Bruxelles (berchem-sainte-agathe) Bruxelles-Capitale 1082",
    "addr:housenumber":"168;1",
    "addr:postcode":"1082",
    "addr:street":"Avenue Du Roi Albert;Box",
    "iso:country":"BE",
    "sg:address":"Avenue Du Roi Albert 168 Box 1",
    "sg:city":"Bruxelles (berchem-sainte-agathe)",
    "sg:classifiers":[
        {
            "category":"Retail",
            "subcategory":"Veterinary Services",
            "type":"Services"
        }
    ],
    "sg:phone":"+32 2 468 11 30",
    "sg:postcode":"1082",
    "sg:province":"Bruxelles-Capitale",
    "sg:tags":[
        "veterinarian"
    ],
    "wof:name":"Van Crombrugge B",
    "wof:placetype":"venue"
},
  "geometry": {"coordinates":[4.2872929573,50.8666038513],"type":"Point"}
}