{
  "type": "Feature",
  "properties": {
    "iso:country":"BE",
    "sg:address":"Rue Saint-donat 56",
    "sg:city":"Namur",
    "sg:orig_category":"Biblioth\u00e8ques and archives publiques",
    "sg:phone":"+32 81 73 02 22",
    "sg:postcode":"5002",
    "sg:province":"Namur",
    "wof:name":"Biblioth\u00c8que Publique",
    "wof:placetype":"venue"
},
  "geometry": {"coordinates":[4.8519911766,50.473526001],"type":"Point"}
}