{
  "type": "Feature",
  "properties": {
    "addr:full":"Brusselbaan 505 Sint-pieters-leeuw Vlaams-Brabant 1600",
    "addr:housenumber":"505",
    "addr:postcode":"1600",
    "addr:street":"Brusselbaan",
    "iso:country":"BE",
    "sg:address":"Brusselbaan 505",
    "sg:city":"Sint-pieters-leeuw",
    "sg:classifiers":[
        {
            "category":"Health Services",
            "subcategory":"Doctor",
            "type":"Services"
        }
    ],
    "sg:phone":"+32 2 378 14 01",
    "sg:postcode":"1600",
    "sg:province":"Vlaams-Brabant",
    "sg:tags":[
        "medicinephysicians",
        "surgeon"
    ],
    "wof:name":"Bove Th",
    "wof:placetype":"venue"
},
  "geometry": {"coordinates":[4.2463288307,50.7821617126],"type":"Point"}
}