{
  "type": "Feature",
  "properties": {
    "iso:country":"BE",
    "sg:address":"Zeedijk-duinbergen 306",
    "sg:city":"Knokke-heist (heist-aan-zee)",
    "sg:classifiers":[
        {
            "category":"Shopping",
            "subcategory":"Hobbies, Toys, & Games",
            "type":"Retail Goods"
        }
    ],
    "sg:phone":"+32 50 51 00 25",
    "sg:postcode":"8301",
    "sg:province":"West-Vlaanderen",
    "sg:tags":[
        "toy",
        "-"
    ],
    "wof:name":"Bolo",
    "wof:placetype":"venue"
},
  "geometry": {"coordinates":[3.2558279037,51.3437347412],"type":"Point"}
}