{
  "type": "Feature",
  "properties": {
    "addr:full":"Avenue Eug\u00e8ne Philippe 9 Genappe (glabais) Brabant Wallon 1473",
    "addr:housenumber":"9",
    "addr:postcode":"1473",
    "addr:street":"Avenue Euge\u0300Ne Philippe;Wallon",
    "iso:country":"BE",
    "sg:address":"Avenue Eug\u00e8ne Philippe 9",
    "sg:city":"Genappe (glabais)",
    "sg:classifiers":[
        {
            "category":"Professional",
            "subcategory":"Accounting & Tax Preparation",
            "type":"Services"
        }
    ],
    "sg:phone":"+32 67 79 06 95",
    "sg:postcode":"1473",
    "sg:province":"Brabant Wallon",
    "sg:tags":[
        "bookkeeper"
    ],
    "wof:name":"De Ville De Goyet P",
    "wof:placetype":"venue"
},
  "geometry": {"coordinates":[4.4617519379,50.6324462891],"type":"Point"}
}