{
  "type": "Feature",
  "properties": {
    "addr:full":"Rue Croix De Bourgogne 12 Mettet Namur 5640",
    "addr:housenumber":"12",
    "addr:postcode":"5640",
    "addr:street":"Rue Croix De Bourgogne",
    "iso:country":"BE",
    "sg:address":"Rue Croix De Bourgogne 12",
    "sg:city":"Mettet",
    "sg:orig_category":"Enseignement maternel and primaire",
    "sg:phone":"+32 71 72 78 83",
    "sg:postcode":"5640",
    "sg:province":"Namur",
    "wof:name":"Ecole Fondamentale",
    "wof:placetype":"venue"
},
  "geometry": {"coordinates":[4.6605358124,50.3222846985],"type":"Point"}
}