{
  "type": "Feature",
  "properties": {
    "addr:full":"Zabekestraat 21a Zedelgem (aartrijke) West-Vlaanderen 8211",
    "addr:housenumber":"21a",
    "addr:postcode":"8211",
    "addr:street":"Zabekestraat",
    "iso:country":"BE",
    "sg:address":"Zabekestraat 21a",
    "sg:city":"Zedelgem (aartrijke)",
    "sg:classifiers":[
        {
            "category":"Farming",
            "subcategory":"Livestock Farm",
            "type":"Manufacturing & Wholesale Goods"
        }
    ],
    "sg:phone":"+32 50 20 80 96",
    "sg:postcode":"8211",
    "sg:province":"West-Vlaanderen",
    "sg:tags":[
        "poultry",
        "rabbit"
    ],
    "wof:name":"Vloethem-gryp",
    "wof:placetype":"venue"
},
  "geometry": {"coordinates":[3.0889649391,51.1200408936],"type":"Point"}
}