{
  "type": "Feature",
  "properties": {
    "iso:country":"BE",
    "sg:address":"Dokter Persoonslaan 24",
    "sg:city":"Willebroek",
    "sg:classifiers":[
        {
            "category":"Shopping",
            "subcategory":"Crafts & Fabrics",
            "type":"Retail Goods"
        }
    ],
    "sg:phone":"+32 3 886 83 17",
    "sg:postcode":"2830",
    "sg:province":"Antwerpen",
    "sg:tags":[
        "-",
        "wool",
        "knitting",
        "yarn"
    ],
    "wof:name":"Trifil",
    "wof:placetype":"venue"
},
  "geometry": {"coordinates":[4.361987114,51.0600128174],"type":"Point"}
}