{
  "type": "Feature",
  "properties": {
    "iso:country":"BE",
    "sg:address":"Chemin De Hameau 259",
    "sg:city":"Ham-sur-heure-nalinnes",
    "sg:orig_category":"Eleveurs de bovins",
    "sg:phone":"+32 71 21 31 43",
    "sg:postcode":"6120",
    "sg:province":"Hainaut",
    "wof:name":"Jean-louis Jopart",
    "wof:placetype":"venue"
},
  "geometry": {"coordinates":[4.433327198,50.3207817078],"type":"Point"}
}