{
  "type": "Feature",
  "properties": {
    "iso:country":"BE",
    "sg:address":"Potterijstraat 173",
    "sg:city":"Tienen",
    "sg:orig_category":"Herstelling and restauratie van meubelen",
    "sg:phone":"+32 16 82 43 23",
    "sg:postcode":"3300",
    "sg:province":"Vlaams-Brabant",
    "wof:name":"Roche",
    "wof:placetype":"venue"
},
  "geometry": {"coordinates":[4.9391498566,50.800868988],"type":"Point"}
}