{
  "type": "Feature",
  "properties": {
    "addr:full":"Driesstraat 6 Laarne Oost-Vlaanderen 9270",
    "addr:housenumber":"6",
    "addr:postcode":"9270",
    "addr:street":"Driesstraat",
    "iso:country":"BE",
    "sg:address":"Driesstraat 6",
    "sg:city":"Laarne",
    "sg:orig_category":"Installatie van houten of kunststof schrijnwerk Installatie van metalen schrijnwerk",
    "sg:phone":"+32 9 231 45 04",
    "sg:postcode":"9270",
    "sg:province":"Oost-Vlaanderen",
    "wof:name":"De Bruyne",
    "wof:placetype":"venue"
},
  "geometry": {"coordinates":[3.8325929642,51.0336647034],"type":"Point"}
}