{
  "type": "Feature",
  "properties": {
    "addr:full":"Rue Gergel 103 Wezembeek-oppem Vlaams-Brabant 1970",
    "addr:housenumber":"103",
    "addr:postcode":"1970",
    "addr:street":"Rue Gergel",
    "iso:country":"BE",
    "sg:address":"Rue Gergel 103",
    "sg:city":"Wezembeek-oppem",
    "sg:classifiers":[
        {
            "category":"Personal",
            "subcategory":"Beauty Salon",
            "type":"Services"
        }
    ],
    "sg:phone":"+32 2 731 21 65",
    "sg:postcode":"1970",
    "sg:province":"Vlaams-Brabant",
    "sg:tags":[
        "lady",
        "-",
        "hairdressing"
    ],
    "wof:name":"Hairstyle Paul",
    "wof:placetype":"venue"
},
  "geometry": {"coordinates":[4.4853739738,50.8489837646],"type":"Point"}
}