{
  "type": "Feature",
  "properties": {
    "addr:full":"Azalealaan 14 Beveren Oost-Vlaanderen 9120",
    "addr:housenumber":"14",
    "addr:postcode":"9120",
    "addr:street":"Azalealaan",
    "iso:country":"BE",
    "sg:address":"Azalealaan 14",
    "sg:city":"Beveren",
    "sg:orig_category":"Elektrische installaties voor woningen",
    "sg:phone":"+32 3 775 67 96",
    "sg:postcode":"9120",
    "sg:province":"Oost-Vlaanderen",
    "wof:name":"Rudy Baert",
    "wof:placetype":"venue"
},
  "geometry": {"coordinates":[4.2593860626,51.2236557007],"type":"Point"}
}