{
  "type": "Feature",
  "properties": {
    "addr:full":"Terbeeksestraat 32 Hoogstraten (meer) Antwerpen 2321",
    "addr:housenumber":"32",
    "addr:postcode":"2321",
    "addr:street":"Terbeeksestraat;Meer",
    "iso:country":"BE",
    "sg:address":"Terbeeksestraat 32",
    "sg:city":"Hoogstraten (meer)",
    "sg:classifiers":[
        {
            "category":"Retail",
            "subcategory":"Auto Repair",
            "type":"Services"
        }
    ],
    "sg:phone":"+32 3 315 08 61",
    "sg:postcode":"2321",
    "sg:province":"Antwerpen",
    "sg:tags":[
        "garage"
    ],
    "wof:name":"Verschueren E",
    "wof:placetype":"venue"
},
  "geometry": {"coordinates":[4.7366099358,51.442325592],"type":"Point"}
}