{
  "type": "Feature",
  "properties": {
    "iso:country":"BE",
    "sg:address":"Groenstraat 87",
    "sg:city":"Boechout",
    "sg:classifiers":[
        {
            "category":"Farming",
            "subcategory":"Crops",
            "type":"Manufacturing & Wholesale Goods"
        }
    ],
    "sg:phone":"+32 3 455 28 21",
    "sg:postcode":"2530",
    "sg:province":"Antwerpen",
    "sg:tags":[
        "vegetable",
        "fruit",
        "-",
        "grower"
    ],
    "wof:name":"Janssens L",
    "wof:placetype":"venue"
},
  "geometry": {"coordinates":[4.5067849159,51.1737251282],"type":"Point"}
}