{
  "type": "Feature",
  "properties": {
    "addr:full":"Stationsplein 9 Lede Oost-Vlaanderen 9340",
    "addr:housenumber":"9",
    "addr:postcode":"9340",
    "addr:street":"Stationsplein",
    "iso:country":"BE",
    "sg:address":"Stationsplein 9",
    "sg:city":"Lede",
    "sg:orig_category":"Treinen and spoorwegen",
    "sg:phone":"+32 53 21 41 31",
    "sg:postcode":"9340",
    "sg:province":"Oost-Vlaanderen",
    "wof:name":"Station Lede",
    "wof:placetype":"venue"
},
  "geometry": {"coordinates":[3.9853079319,50.9707336426],"type":"Point"}
}