{
  "type": "Feature",
  "properties": {
    "iso:country":"BE",
    "sg:address":"Mierenberg 65",
    "sg:city":"Halle",
    "sg:orig_category":"Eleveurs de bovins",
    "sg:phone":"+32 2 356 57 83",
    "sg:postcode":"1500",
    "sg:province":"Vlaams-Brabant",
    "wof:name":"Debelder",
    "wof:placetype":"venue"
},
  "geometry": {"coordinates":[4.2088651657,50.738571167],"type":"Point"}
}