{
  "type": "Feature",
  "properties": {
    "addr:full":"Driesstraat 167 Sint-lambrechts-woluwe/woluwe-saint-lambert Bruxelles-Capitale 1200",
    "addr:housenumber":"167;/",
    "addr:postcode":"1200",
    "addr:street":"Driesstraat;Sint-Lambrechts-Woluwe",
    "iso:country":"BE",
    "sg:address":"Driesstraat 167",
    "sg:city":"Sint-lambrechts-woluwe/woluwe-saint-lambert",
    "sg:orig_category":"Onderhoud van kantoor- and computeruitrusting",
    "sg:phone":"+32 2 770 02 29",
    "sg:postcode":"1200",
    "sg:province":"Bruxelles-Capitale",
    "wof:name":"Full Power",
    "wof:placetype":"venue"
},
  "geometry": {"coordinates":[4.4236998558,50.8453178406],"type":"Point"}
}