{
  "type": "Feature",
  "properties": {
    "addr:full":"Maria Doolaeghestraat 11 Diksmuide West-Vlaanderen 8600",
    "addr:housenumber":"11",
    "addr:postcode":"8600",
    "addr:street":"Doolaeghestraat",
    "iso:country":"BE",
    "sg:address":"Maria Doolaeghestraat 11",
    "sg:city":"Diksmuide",
    "sg:orig_category":"Non-Classified Establishments",
    "sg:phone":"+32 51 50 47 09",
    "sg:postcode":"8600",
    "sg:province":"West-Vlaanderen",
    "wof:name":"Timigrie Bvba",
    "wof:placetype":"venue"
},
  "geometry": {"coordinates":[2.8646769524,51.0319366455],"type":"Point"}
}