{
  "type": "Feature",
  "properties": {
    "addr:full":"Rue Du Pr\u00e9 Au Loup 61 Namur (naninne) Namur 5100",
    "addr:housenumber":"61",
    "addr:postcode":"5100",
    "addr:street":"Rue Du Pre\u0301 Au Loup",
    "iso:country":"BE",
    "sg:address":"Rue Du Pr\u00e9 Au Loup 61",
    "sg:city":"Namur (naninne)",
    "sg:classifiers":[
        {
            "category":"Insurance",
            "subcategory":"Insurance Agent",
            "type":"Services"
        }
    ],
    "sg:phone":"+32 81 40 22 50",
    "sg:postcode":"5100",
    "sg:province":"Namur",
    "sg:tags":[
        "-",
        "representative"
    ],
    "wof:name":"Bragard O",
    "wof:placetype":"venue"
},
  "geometry": {"coordinates":[4.8713750839,50.4566345215],"type":"Point"}
}