{
  "type": "Feature",
  "properties": {
    "iso:country":"BE",
    "sg:address":"Rue De La Station 22",
    "sg:city":"Walcourt",
    "sg:classifiers":[
        {
            "category":"Personal",
            "subcategory":"Beauty Salon",
            "type":"Services"
        }
    ],
    "sg:phone":"+32 71 61 12 36",
    "sg:postcode":"5650",
    "sg:province":"Namur",
    "sg:tags":[
        "lady",
        "-",
        "hairdressing"
    ],
    "wof:name":"Hair-ligne",
    "wof:placetype":"venue"
},
  "geometry": {"coordinates":[4.4360508919,50.2553062439],"type":"Point"}
}