{
  "type": "Feature",
  "properties": {
    "addr:full":"Rue Prince Baudouin 46 Bruxelles (jette) Bruxelles-Capitale 1090",
    "addr:housenumber":"46",
    "addr:postcode":"1090",
    "addr:street":"Rue Prince Baudouin",
    "iso:country":"BE",
    "sg:address":"Rue Prince Baudouin 46",
    "sg:city":"Bruxelles (jette)",
    "sg:classifiers":[
        {
            "category":"Professional",
            "subcategory":"Accounting & Tax Preparation",
            "type":"Services"
        }
    ],
    "sg:phone":"+32 2 420 48 98",
    "sg:postcode":"1090",
    "sg:province":"Bruxelles-Capitale",
    "sg:tags":[
        "bookkeeper"
    ],
    "wof:name":"Moghimi P",
    "wof:placetype":"venue"
},
  "geometry": {"coordinates":[4.3228487968,50.8724479675],"type":"Point"}
}