{
  "type": "Feature",
  "properties": {
    "addr:full":"Belgi\u00cblei 181 Antwerpen Antwerpen 2018",
    "addr:housenumber":"181",
    "addr:postcode":"2018",
    "addr:street":"Belgie\u0308Lei",
    "iso:country":"BE",
    "sg:address":"Belgi\u00cblei 181",
    "sg:city":"Antwerpen",
    "sg:orig_category":"Fabrication and montage de mobilier. Meubles D\u00e9taillants, Am\u00e9nagement de B\u00e2timents et de Cuisines. E",
    "sg:phone":"+32 3 230 21 34",
    "sg:postcode":"2018",
    "sg:province":"Antwerpen",
    "wof:name":"Aform",
    "wof:placetype":"venue"
},
  "geometry": {"coordinates":[4.4140920639,51.2026329041],"type":"Point"}
}