{
  "type": "Feature",
  "properties": {
    "iso:country":"BE",
    "sg:address":"Rue Des Comognes 20",
    "sg:city":"Gesves",
    "sg:orig_category":"Artsen and specialisten",
    "sg:phone":"+32 81 58 22 44",
    "sg:postcode":"5340",
    "sg:province":"Namur",
    "wof:name":"C. Boursois",
    "wof:placetype":"venue"
},
  "geometry": {"coordinates":[4.9855389595,50.4461898804],"type":"Point"}
}