{
  "type": "Feature",
  "properties": {
    "iso:country":"BE",
    "sg:address":"Testeltsesteenweg 184",
    "sg:city":"Aarschot",
    "sg:orig_category":"Landmeters",
    "sg:phone":"+32 16 56 54 01",
    "sg:postcode":"3201",
    "sg:province":"Vlaams-Brabant",
    "wof:name":"Joseph Theys",
    "wof:placetype":"venue"
},
  "geometry": {"coordinates":[4.9074258804,51.0055122375],"type":"Point"}
}