{
  "type": "Feature",
  "properties": {
    "addr:full":"Sint-martinusstraat 76 Retie Antwerpen 2470",
    "addr:housenumber":"76",
    "addr:postcode":"2470",
    "addr:street":"Sint-Martinusstraat",
    "iso:country":"BE",
    "sg:address":"Sint-martinusstraat 76",
    "sg:city":"Retie",
    "sg:orig_category":"V\u00e9los",
    "sg:phone":"+32 14 37 71 40",
    "sg:postcode":"2470",
    "sg:province":"Antwerpen",
    "wof:name":"Bart Van Der Veken",
    "wof:placetype":"venue"
},
  "geometry": {"coordinates":[5.0875711441,51.2632598877],"type":"Point"}
}