{
  "type": "Feature",
  "properties": {
    "addr:full":"Rue D'en-dessous 45 Les Bons Villers Hainaut 6211",
    "addr:housenumber":"45",
    "addr:postcode":"6211",
    "addr:street":"Rue D'En-Dessous",
    "iso:country":"BE",
    "sg:address":"Rue D'en-dessous 45",
    "sg:city":"Les Bons Villers",
    "sg:orig_category":"Plomberie, chauffage and installations sanitaires",
    "sg:phone":"+32 71 85 28 97",
    "sg:postcode":"6211",
    "sg:province":"Hainaut",
    "wof:name":"Andre Deschamps",
    "wof:placetype":"venue"
},
  "geometry": {"coordinates":[4.464840889,50.4993171692],"type":"Point"}
}