{
  "type": "Feature",
  "properties": {
    "iso:country":"BE",
    "sg:address":"Rue De Berlaimont - Zi De Martinrou",
    "sg:city":"Fleurus",
    "sg:classifiers":[
        {
            "category":"Wholesale",
            "subcategory":"Construction Materials",
            "type":"Manufacturing & Wholesale Goods"
        }
    ],
    "sg:phone":"+32 71 81 51 21",
    "sg:postcode":"6220",
    "sg:province":"Hainaut",
    "sg:tags":[
        "concrete",
        "additive"
    ],
    "wof:name":"Pimpurniaux Fr\u00e8res S.a.",
    "wof:placetype":"venue"
},
  "geometry": {"coordinates":[4.5463747978,50.456199646],"type":"Point"}
}