{
  "type": "Feature",
  "properties": {
    "iso:country":"BE",
    "sg:address":"Vinkenstraat 24",
    "sg:city":"Grimbergen",
    "sg:classifiers":[
        {
            "category":"Health Services",
            "subcategory":"Dentist",
            "type":"Services"
        }
    ],
    "sg:phone":"+32 2 252 19 15",
    "sg:postcode":"1850",
    "sg:province":"Vlaams-Brabant",
    "wof:name":"Guillaume D",
    "wof:placetype":"venue"
},
  "geometry": {"coordinates":[4.3995962143,50.9299507141],"type":"Point"}
}