{
  "type": "Feature",
  "properties": {
    "addr:full":"Chauss\u00c9e De Waterloo 655 Ukkel/uccle Bruxelles-Capitale 1180",
    "addr:housenumber":"655",
    "addr:postcode":"1180",
    "addr:street":"Chausse\u0301E De Waterloo;/",
    "iso:country":"BE",
    "sg:address":"Chauss\u00c9e De Waterloo 655",
    "sg:city":"Ukkel/uccle",
    "sg:orig_category":"Blanchisseries and teintureries",
    "sg:phone":"+32 2 345 31 03",
    "sg:postcode":"1180",
    "sg:province":"Bruxelles-Capitale",
    "wof:name":"La Com\u00c8te",
    "wof:placetype":"venue"
},
  "geometry": {"coordinates":[4.3666601181,50.8170394897],"type":"Point"}
}