{
  "type": "Feature",
  "properties": {
    "iso:country":"BE",
    "sg:address":"Grendelbaan 109",
    "sg:city":"Diepenbeek",
    "sg:classifiers":[
        {
            "category":"Manufacturing",
            "subcategory":"Lumber",
            "type":"Manufacturing & Wholesale Goods"
        }
    ],
    "sg:phone":"+32 11 32 33 18",
    "sg:postcode":"3590",
    "sg:province":"Limburg",
    "sg:tags":[
        "timber"
    ],
    "wof:name":"Modest (bois & Brico)",
    "wof:placetype":"venue"
},
  "geometry": {"coordinates":[5.4433379173,50.900592804],"type":"Point"}
}