{
  "type": "Feature",
  "properties": {
    "iso:country":"BE",
    "sg:address":"Rue Des Bouleaux 9",
    "sg:city":"Ham-sur-heure-nalinnes (nalinnes)",
    "sg:classifiers":[
        {
            "category":"Health Services",
            "subcategory":"Doctor",
            "type":"Services"
        }
    ],
    "sg:phone":"+32 71 21 40 71",
    "sg:postcode":"6120",
    "sg:province":"Hainaut",
    "sg:tags":[
        "medicinephysicians",
        "surgeon"
    ],
    "wof:name":"Chapaux Pierre",
    "wof:placetype":"venue"
},
  "geometry": {"coordinates":[4.4643330574,50.319278717],"type":"Point"}
}