{
  "type": "Feature",
  "properties": {
    "addr:full":"Rue Longue 72 Tournai Hainaut 7502",
    "addr:housenumber":"72",
    "addr:postcode":"7502",
    "addr:street":"Rue Longue",
    "iso:country":"BE",
    "sg:address":"Rue Longue 72",
    "sg:city":"Tournai",
    "sg:orig_category":"Kapsalons",
    "sg:phone":"+32 69 64 86 12",
    "sg:postcode":"7502",
    "sg:province":"Hainaut",
    "wof:name":"Coiffure Bernadette",
    "wof:placetype":"venue"
},
  "geometry": {"coordinates":[3.2952570915,50.57371521],"type":"Point"}
}