{
  "type": "Feature",
  "properties": {
    "iso:country":"BE",
    "sg:address":"Rue Du Palais-de-justice 24",
    "sg:city":"Dinant",
    "sg:classifiers":[
        {
            "category":"Real Estate",
            "subcategory":"Architect",
            "type":"Services"
        }
    ],
    "sg:phone":"+32 82 22 56 00",
    "sg:postcode":"5500",
    "sg:province":"Namur",
    "wof:name":"Clarenne G",
    "wof:placetype":"venue"
},
  "geometry": {"coordinates":[4.9142489433,50.2589225769],"type":"Point"}
}