{
  "type": "Feature",
  "properties": {
    "iso:country":"BE",
    "sg:address":"Kerkstraat 173",
    "sg:city":"Grimbergen",
    "sg:orig_category":"Agences de voyages",
    "sg:phone":"+32 2 270 22 44",
    "sg:postcode":"1851",
    "sg:province":"Vlaams-Brabant",
    "wof:name":"Bias Travel",
    "wof:placetype":"venue"
},
  "geometry": {"coordinates":[4.3867721558,50.9745979309],"type":"Point"}
}