{
  "type": "Feature",
  "properties": {
    "addr:full":"Avenue Du Duc Jean 52 Bruxelles (ganshoren) Bruxelles-Capitale 1083",
    "addr:housenumber":"52",
    "addr:postcode":"1083",
    "addr:street":"Avenue Du Duc Jean",
    "iso:country":"BE",
    "sg:address":"Avenue Du Duc Jean 52",
    "sg:city":"Bruxelles (ganshoren)",
    "sg:classifiers":[
        {
            "category":"Health Services",
            "subcategory":"Doctor",
            "type":"Services"
        }
    ],
    "sg:phone":"+32 2 425 95 18",
    "sg:postcode":"1083",
    "sg:province":"Bruxelles-Capitale",
    "sg:tags":[
        "medicinephysicians",
        "surgeon"
    ],
    "wof:name":"Bocquet Jean-pierre",
    "wof:placetype":"venue"
},
  "geometry": {"coordinates":[4.3193478584,50.8693237305],"type":"Point"}
}