{
  "type": "Feature",
  "properties": {
    "iso:country":"BE",
    "sg:address":"Noordhoutstraat 123",
    "sg:city":"Gent (drongen)",
    "sg:classifiers":[
        {
            "category":"Home & Garden",
            "subcategory":"Furniture",
            "type":"Retail Goods"
        }
    ],
    "sg:phone":"+32 9 282 53 79",
    "sg:postcode":"9031",
    "sg:province":"Oost-Vlaanderen",
    "sg:tags":[
        "-"
    ],
    "wof:name":"Seder",
    "wof:placetype":"venue"
},
  "geometry": {"coordinates":[3.5927560329,51.0297164917],"type":"Point"}
}