{
  "type": "Feature",
  "properties": {
    "addr:full":"Eduard Robeynslaan 56 Diest Vlaams-Brabant 3290",
    "addr:housenumber":"56",
    "addr:postcode":"3290",
    "addr:street":"Robeynslaan",
    "iso:country":"BE",
    "sg:address":"Eduard Robeynslaan 56",
    "sg:city":"Diest",
    "sg:orig_category":"Architectes",
    "sg:phone":"+32 13 31 12 66",
    "sg:postcode":"3290",
    "sg:province":"Vlaams-Brabant",
    "wof:name":"Architectenbureel Micheels - Vanuytrecht",
    "wof:placetype":"venue"
},
  "geometry": {"coordinates":[5.0593380928,50.9777870178],"type":"Point"}
}