{
  "type": "Feature",
  "properties": {
    "iso:country":"BE",
    "sg:address":"Avenue Georges Henri 500",
    "sg:city":"Sint-lambrechts-woluwe/woluwe-saint-lambert",
    "sg:orig_category":"Epiceries",
    "sg:phone":"+32 2 732 30 14",
    "sg:postcode":"1200",
    "sg:province":"Bruxelles-Capitale",
    "wof:name":"Michel Van Damme",
    "wof:placetype":"venue"
},
  "geometry": {"coordinates":[4.4024400711,50.8415184021],"type":"Point"}
}