{
  "type": "Feature",
  "properties": {
    "addr:full":"Gentse Steenweg 146 Lede Oost-Vlaanderen 9340",
    "addr:housenumber":"146",
    "addr:postcode":"9340",
    "addr:street":"Gentse Steenweg",
    "iso:country":"BE",
    "sg:address":"Gentse Steenweg 146",
    "sg:city":"Lede",
    "sg:classifiers":[
        {
            "category":"Shopping",
            "subcategory":"Clothing, Apparel, & Fashions",
            "type":"Retail Goods"
        }
    ],
    "sg:phone":"+32 9 369 29 18",
    "sg:postcode":"9340",
    "sg:province":"Oost-Vlaanderen",
    "sg:tags":[
        "lingerie",
        "sous-v\u00eatements"
    ],
    "wof:name":"Huis Kriko",
    "wof:placetype":"venue"
},
  "geometry": {"coordinates":[4.0095219612,50.9626045227],"type":"Point"}
}