{
  "type": "Feature",
  "properties": {
    "iso:country":"BE",
    "sg:address":"Rue Pierre-thomas 4a",
    "sg:city":"Bastogne",
    "sg:classifiers":[
        {
            "category":"Social Services",
            "type":"Services"
        }
    ],
    "sg:phone":"+32 61 21 36 12",
    "sg:postcode":"6600",
    "sg:province":"Luxembourg",
    "wof:name":"Centre De Planning & De Consultation Familiale Et Conjugale",
    "wof:placetype":"venue"
},
  "geometry": {"coordinates":[5.7212371826,50.007144928],"type":"Point"}
}