{
  "type": "Feature",
  "properties": {
    "iso:country":"BE",
    "sg:address":"Steenweg Buda 2d",
    "sg:city":"Machelen",
    "sg:classifiers":[
        {
            "category":"Wholesale",
            "subcategory":"Scrap",
            "type":"Manufacturing & Wholesale Goods"
        }
    ],
    "sg:phone":"+32 2 252 13 16",
    "sg:postcode":"1830",
    "sg:province":"Vlaams-Brabant",
    "sg:tags":[
        "metal"
    ],
    "wof:name":"C.m.r. Nv",
    "wof:placetype":"venue"
},
  "geometry": {"coordinates":[4.4173679352,50.9062995911],"type":"Point"}
}