{
  "type": "Feature",
  "properties": {
    "iso:country":"BE",
    "sg:address":"Mechelsesteenweg 25",
    "sg:city":"Leuven (wilsele)",
    "sg:classifiers":[
        {
            "category":"Fast Food",
            "type":"Food & Drink"
        }
    ],
    "sg:phone":"+32 16 29 26 97",
    "sg:postcode":"3012",
    "sg:province":"Vlaams-Brabant",
    "sg:tags":[
        "fried",
        "stand",
        "potato"
    ],
    "wof:name":"Mechelsepoort",
    "wof:placetype":"venue"
},
  "geometry": {"coordinates":[4.6942977905,50.8907928467],"type":"Point"}
}