{
  "type": "Feature",
  "properties": {
    "addr:full":"Paardenmarkt 3 Zoersel Antwerpen 2980",
    "addr:housenumber":"3",
    "addr:postcode":"2980",
    "addr:street":"Paardenmarkt",
    "iso:country":"BE",
    "sg:address":"Paardenmarkt 3",
    "sg:city":"Zoersel",
    "sg:orig_category":"Artsen and specialisten",
    "sg:phone":"+32 3 383 69 25",
    "sg:postcode":"2980",
    "sg:province":"Antwerpen",
    "wof:name":"Sandrina Simons",
    "wof:placetype":"venue"
},
  "geometry": {"coordinates":[4.643556118,51.2374153137],"type":"Point"}
}