{
  "type": "Feature",
  "properties": {
    "iso:country":"BE",
    "sg:address":"Hollestraat 22",
    "sg:city":"Heist-op-den-berg",
    "sg:classifiers":[
        {
            "category":"Building & Trades",
            "subcategory":"Pest Control",
            "type":"Services"
        }
    ],
    "sg:phone":"+32 15 24 48 21",
    "sg:postcode":"2220",
    "sg:province":"Antwerpen",
    "sg:tags":[
        "painting",
        "contractor"
    ],
    "wof:name":"Mertens Bvba",
    "wof:placetype":"venue"
},
  "geometry": {"coordinates":[4.7349720001,51.0809249878],"type":"Point"}
}