{
  "type": "Feature",
  "properties": {
    "iso:country":"BE",
    "sg:address":"Diestersteenweg 172b2",
    "sg:city":"Hasselt",
    "sg:orig_category":"Pharmaciens",
    "sg:phone":"+32 11 25 24 52",
    "sg:postcode":"3510",
    "sg:province":"Limburg",
    "wof:name":"Hilda Vangeneugden",
    "wof:placetype":"venue"
},
  "geometry": {"coordinates":[5.2359399796,50.947719574],"type":"Point"}
}