{
  "type": "Feature",
  "properties": {
    "iso:country":"BE",
    "sg:address":"Kiliaanstraat 14-16",
    "sg:city":"Duffel",
    "sg:classifiers":[
        {
            "category":"Professional",
            "subcategory":"Lawyer & Legal Services",
            "type":"Services"
        }
    ],
    "sg:phone":"+32 15 31 31 75",
    "sg:postcode":"2570",
    "sg:province":"Antwerpen",
    "sg:tags":[
        "notary"
    ],
    "wof:name":"De Coster J",
    "wof:placetype":"venue"
},
  "geometry": {"coordinates":[4.5055952072,51.0956115723],"type":"Point"}
}