{
  "type": "Feature",
  "properties": {
    "iso:country":"BE",
    "sg:address":"Avenue George Bergmann 50",
    "sg:city":"Bruxelles (ixelles)",
    "sg:classifiers":[
        {
            "category":"Health Services",
            "subcategory":"Doctor",
            "type":"Services"
        }
    ],
    "sg:phone":"+32 2 673 74 99",
    "sg:postcode":"1050",
    "sg:province":"Bruxelles-Capitale",
    "sg:tags":[
        "medicinephysicians",
        "surgeon"
    ],
    "wof:name":"Goolaerts J-p",
    "wof:placetype":"venue"
},
  "geometry": {"coordinates":[4.3919010162,50.8091201782],"type":"Point"}
}