{
  "type": "Feature",
  "properties": {
    "addr:full":"Boulevard Joseph Tirou 213 Charleroi Hainaut 6000",
    "addr:housenumber":"213",
    "addr:postcode":"6000",
    "addr:street":"Boulevard Joseph Tirou;Hainaut",
    "iso:country":"BE",
    "sg:address":"Boulevard Joseph Tirou 213",
    "sg:city":"Charleroi",
    "sg:classifiers":[
        {
            "category":"Health Services",
            "subcategory":"Doctor",
            "type":"Services"
        }
    ],
    "sg:phone":"+32 71 31 20 83",
    "sg:postcode":"6000",
    "sg:province":"Hainaut",
    "sg:tags":[
        "medicinephysicians",
        "surgeon"
    ],
    "wof:name":"Detournay Michel",
    "wof:placetype":"venue"
},
  "geometry": {"coordinates":[4.4466657639,50.4064674377],"type":"Point"}
}