{
  "type": "Feature",
  "properties": {
    "iso:country":"BE",
    "sg:address":"Kapellei 190",
    "sg:city":"Zoersel",
    "sg:orig_category":"RESTAURANTS: SALLES DE CONF\u00c9RENCES AND DE R\u00c9CEPTIONS. RESTAURANTS FAST FOOD AND \u00c0 EMPORTER",
    "sg:phone":"+32 3 385 03 86",
    "sg:postcode":"2980",
    "sg:province":"Antwerpen",
    "wof:name":"Abacus Ling's Hof",
    "wof:placetype":"venue"
},
  "geometry": {"coordinates":[4.6191058159,51.2555656433],"type":"Point"}
}