{
  "type": "Feature",
  "properties": {
    "addr:full":"Square Roi Baudouin 6 Oupeye Li\u00e8ge 4684",
    "addr:housenumber":"6",
    "addr:postcode":"4684",
    "addr:street":"Square Roi Baudouin",
    "iso:country":"BE",
    "sg:address":"Square Roi Baudouin 6",
    "sg:city":"Oupeye",
    "sg:orig_category":"Artsen and specialisten",
    "sg:phone":"+32 4 374 15 62",
    "sg:postcode":"4684",
    "sg:province":"Li\u00e8ge",
    "wof:name":"Anabelle Piron",
    "wof:placetype":"venue"
},
  "geometry": {"coordinates":[5.6711401939,50.7362632751],"type":"Point"}
}