{
  "type": "Feature",
  "properties": {
    "addr:full":"Bisschopslaan 68 Beerse Antwerpen 2340",
    "addr:housenumber":"68",
    "addr:postcode":"2340",
    "addr:street":"Bisschopslaan",
    "iso:country":"BE",
    "sg:address":"Bisschopslaan 68",
    "sg:city":"Beerse",
    "sg:classifiers":[
        {
            "category":"Retail",
            "subcategory":"Veterinary Services",
            "type":"Services"
        }
    ],
    "sg:phone":"+32 14 62 20 20",
    "sg:postcode":"2340",
    "sg:province":"Antwerpen",
    "sg:tags":[
        "veterinarian"
    ],
    "wof:name":"Michiels B het Binnenhof",
    "wof:placetype":"venue"
},
  "geometry": {"coordinates":[4.8559861183,51.3132095337],"type":"Point"}
}