{
  "type": "Feature",
  "properties": {
    "iso:country":"BE",
    "sg:address":"Avenue Minerve 37",
    "sg:city":"Vorst/forest",
    "sg:orig_category":"Artistes ind\u00e9pendants",
    "sg:phone":"+32 2 343 75 05",
    "sg:postcode":"1190",
    "sg:province":"Bruxelles-Capitale",
    "wof:name":"Yvonne Garden",
    "wof:placetype":"venue"
},
  "geometry": {"coordinates":[4.3315219879,50.810382843],"type":"Point"}
}