{
  "type": "Feature",
  "properties": {
    "addr:full":"Geraardsbergsesteenweg 199 Melle Oost-Vlaanderen 9090",
    "addr:housenumber":"199",
    "addr:postcode":"9090",
    "addr:street":"Geraardsbergsesteenweg",
    "iso:country":"BE",
    "sg:address":"Geraardsbergsesteenweg 199",
    "sg:city":"Melle",
    "sg:orig_category":"Peinture. Rev\u00eatements pour sols and murs",
    "sg:phone":"+32 9 252 58 96",
    "sg:postcode":"9090",
    "sg:province":"Oost-Vlaanderen",
    "wof:name":"Demo Decor",
    "wof:placetype":"venue"
},
  "geometry": {"coordinates":[3.7989499569,50.9907608032],"type":"Point"}
}