{
  "type": "Feature",
  "properties": {
    "iso:country":"BE",
    "sg:address":"Rue Roblet 14",
    "sg:city":"Nivelles",
    "sg:classifiers":[
        {
            "category":"Manufacturing",
            "subcategory":"Tools & Machinery",
            "type":"Manufacturing & Wholesale Goods"
        }
    ],
    "sg:phone":"+32 67 21 21 91",
    "sg:postcode":"1400",
    "sg:province":"Brabant Wallon",
    "sg:tags":[
        "builder"
    ],
    "wof:name":"Ateliers De M\u00e9canique G\u00e9n\u00e9rale",
    "wof:placetype":"venue"
},
  "geometry": {"coordinates":[4.3301501274,50.5981941223],"type":"Point"}
}