{
  "type": "Feature",
  "properties": {
    "iso:country":"BE",
    "sg:address":"Waversebaan 244",
    "sg:city":"Oud-heverlee",
    "sg:orig_category":"M\u00e9decins and sp\u00e9cialistes",
    "sg:phone":"+32 16 47 70 50",
    "sg:postcode":"3050",
    "sg:province":"Vlaams-Brabant",
    "wof:name":"Ellen De Ceunynck",
    "wof:placetype":"venue"
},
  "geometry": {"coordinates":[4.6535758972,50.8255767822],"type":"Point"}
}