{
  "type": "Feature",
  "properties": {
    "addr:full":"Putsesteenweg 197 Bonheiden Antwerpen 2820",
    "addr:housenumber":"197",
    "addr:postcode":"2820",
    "addr:street":"Putsesteenweg",
    "iso:country":"BE",
    "sg:address":"Putsesteenweg 197",
    "sg:city":"Bonheiden",
    "sg:classifiers":[
        {
            "category":"Personal",
            "subcategory":"Beauty Salon",
            "type":"Services"
        }
    ],
    "sg:phone":"+32 15 34 03 91",
    "sg:postcode":"2820",
    "sg:province":"Antwerpen",
    "sg:tags":[
        "de",
        "coiffure"
    ],
    "wof:name":"Veronique Verhoeven",
    "wof:placetype":"venue"
},
  "geometry": {"coordinates":[4.5326628685,51.0359153748],"type":"Point"}
}