{
  "type": "Feature",
  "properties": {
    "addr:full":"Rue Claessens 13 Brussel/bruxelles Bruxelles-Capitale 1020",
    "addr:housenumber":"13",
    "addr:postcode":"1020",
    "addr:street":"Rue Claessens;/",
    "iso:country":"BE",
    "sg:address":"Rue Claessens 13",
    "sg:city":"Brussel/bruxelles",
    "sg:orig_category":"Ramassage and traitement des d\u00e9chets m\u00e9nagers",
    "sg:phone":"+32 2 427 65 75",
    "sg:postcode":"1020",
    "sg:province":"Bruxelles-Capitale",
    "wof:name":"Aramis Containers",
    "wof:placetype":"venue"
},
  "geometry": {"coordinates":[4.3581390381,50.8730201721],"type":"Point"}
}