{
  "type": "Feature",
  "properties": {
    "addr:full":"Weiveldlaan 29 Zaventem Vlaams-Brabant 1930",
    "addr:housenumber":"29",
    "addr:postcode":"1930",
    "addr:street":"Weiveldlaan",
    "iso:country":"BE",
    "sg:address":"Weiveldlaan 29",
    "sg:city":"Zaventem",
    "sg:classifiers":[
        {
            "category":"Home & Garden",
            "subcategory":"Home Furnishings",
            "type":"Retail Goods"
        }
    ],
    "sg:phone":"+32 2 719 22 11",
    "sg:postcode":"1930",
    "sg:province":"Vlaams-Brabant",
    "sg:tags":[
        "interior",
        "decoration"
    ],
    "wof:name":"Ikea Belgium Nv",
    "wof:placetype":"venue"
},
  "geometry": {"coordinates":[4.4947600365,50.8697090149],"type":"Point"}
}