{
  "type": "Feature",
  "properties": {
    "iso:country":"BE",
    "sg:address":"Rue Gressi\u00e8re 30",
    "sg:city":"Chimay (baileux)",
    "sg:classifiers":[
        {
            "category":"Health Services",
            "subcategory":"Health Practitioner",
            "type":"Services"
        }
    ],
    "sg:phone":"+32 60 21 24 84",
    "sg:postcode":"6464",
    "sg:province":"Hainaut",
    "sg:tags":[
        "physiotherapist"
    ],
    "wof:name":"Monaux Nicolas",
    "wof:placetype":"venue"
},
  "geometry": {"coordinates":[4.3846259117,50.0255203247],"type":"Point"}
}