{
  "type": "Feature",
  "properties": {
    "iso:country":"BE",
    "sg:address":"Houtmarkt 3",
    "sg:city":"Sint-truiden",
    "sg:classifiers":[
        {
            "category":"Professional",
            "subcategory":"Lawyer & Legal Services",
            "type":"Services"
        }
    ],
    "sg:phone":"+32 11 68 22 30",
    "sg:postcode":"3800",
    "sg:province":"Limburg",
    "sg:tags":[
        "notary"
    ],
    "wof:name":"Odeurs Ph",
    "wof:placetype":"venue"
},
  "geometry": {"coordinates":[5.1892671585,50.8171958923],"type":"Point"}
}