{
  "type": "Feature",
  "properties": {
    "iso:country":"BE",
    "sg:address":"Pont Des Bayards 137",
    "sg:city":"Li\u00e8ge 1",
    "sg:classifiers":[
        {
            "category":"Building & Trades",
            "subcategory":"Cleaning & Sanitation",
            "type":"Services"
        }
    ],
    "sg:phone":"+32 4 228 08 79",
    "sg:postcode":"4000",
    "sg:province":"Li\u00e8ge",
    "sg:tags":[
        "cleaner",
        "window"
    ],
    "wof:name":"Bosquillon M-l",
    "wof:placetype":"venue"
},
  "geometry": {"coordinates":[5.5977940559,50.6557998657],"type":"Point"}
}