{
  "type": "Feature",
  "properties": {
    "iso:country":"BE",
    "sg:address":"Dorp 10",
    "sg:city":"Denderleeuw",
    "sg:classifiers":[
        {
            "category":"Building & Trades",
            "subcategory":"Electrical",
            "type":"Services"
        }
    ],
    "sg:phone":"+32 53 67 23 49",
    "sg:postcode":"9470",
    "sg:province":"Oost-Vlaanderen",
    "sg:tags":[
        "electric",
        "-",
        "housewiring",
        "contractor"
    ],
    "wof:name":"D'hoe Electro",
    "wof:placetype":"venue"
},
  "geometry": {"coordinates":[4.0822501183,50.8833007812],"type":"Point"}
}