{
  "type": "Feature",
  "properties": {
    "iso:country":"BE",
    "sg:address":"Mierdsedijk 86bb",
    "sg:city":"Ravels",
    "sg:orig_category":"Eleveurs de bovins",
    "sg:phone":"+32 14 65 51 08",
    "sg:postcode":"2382",
    "sg:province":"Antwerpen",
    "wof:name":"Blockx Emiel Bols Jozef",
    "wof:placetype":"venue"
},
  "geometry": {"coordinates":[5.041768074,51.4469108582],"type":"Point"}
}