{
  "type": "Feature",
  "properties": {
    "addr:full":"Place De La Louve 3 La Louvi\u00c8re Hainaut 7100",
    "addr:housenumber":"3",
    "addr:postcode":"7100",
    "addr:street":"Place De La Louve",
    "iso:country":"BE",
    "sg:address":"Place De La Louve 3",
    "sg:city":"La Louvi\u00c8re",
    "sg:classifiers":[
        {
            "category":"Restaurant",
            "type":"Food & Drink"
        }
    ],
    "sg:phone":"+32 64 26 14 85",
    "sg:postcode":"7100",
    "sg:province":"Hainaut",
    "wof:name":"A L\u00b4epi De Bl\u00c9",
    "wof:placetype":"venue"
},
  "geometry": {"coordinates":[4.1866579056,50.4774246216],"type":"Point"}
}