{
  "type": "Feature",
  "properties": {
    "addr:full":"3070 Kortenberg (grand) Vlaams-Brabant 3070",
    "addr:postcode":"3070;3070",
    "addr:street":"Kortenberg Grand Vlaams-Brabant",
    "iso:country":"BE",
    "sg:address":"3070",
    "sg:city":"Kortenberg (grand)",
    "sg:orig_category":"Pharmaciens",
    "sg:phone":"+32 900 10 500",
    "sg:postcode":"3070",
    "sg:province":"Vlaams-Brabant",
    "wof:name":"Pharmacies De Garde",
    "wof:placetype":"venue"
},
  "geometry": {"coordinates":[4.5394101143,50.8836708069],"type":"Point"}
}