{
  "type": "Feature",
  "properties": {
    "addr:full":"Avenue Georges Henri 348 Bruxelles (woluwe-saint-lambert) Bruxelles-Capitale 1200",
    "addr:housenumber":"348",
    "addr:postcode":"1200",
    "addr:street":"Avenue Georges Henri",
    "iso:country":"BE",
    "sg:address":"Avenue Georges Henri 348",
    "sg:city":"Bruxelles (woluwe-saint-lambert)",
    "sg:classifiers":[
        {
            "category":"Shopping",
            "subcategory":"Clothing, Apparel, & Fashions",
            "type":"Retail Goods"
        }
    ],
    "sg:phone":"+32 2 733 39 26",
    "sg:postcode":"1200",
    "sg:province":"Bruxelles-Capitale",
    "sg:tags":[
        "boutique"
    ],
    "wof:name":"Coraline Couture Sa",
    "wof:placetype":"venue"
},
  "geometry": {"coordinates":[4.4088850021,50.8430366516],"type":"Point"}
}