{
  "type": "Feature",
  "properties": {
    "addr:full":"Steenlandermeers 2 Kortrijk West-Vlaanderen 8510",
    "addr:housenumber":"2",
    "addr:postcode":"8510",
    "addr:street":"Steenlandermeers",
    "iso:country":"BE",
    "sg:address":"Steenlandermeers 2",
    "sg:city":"Kortrijk",
    "sg:orig_category":"Tuinen",
    "sg:phone":"+32 56 22 48 85",
    "sg:postcode":"8510",
    "sg:province":"West-Vlaanderen",
    "wof:name":"Beyls Frank",
    "wof:placetype":"venue"
},
  "geometry": {"coordinates":[3.2904570103,50.7696456909],"type":"Point"}
}