{
  "type": "Feature",
  "properties": {
    "iso:country":"BE",
    "sg:address":"Markt 47",
    "sg:city":"Peer",
    "sg:orig_category":"Begrafeniswezen",
    "sg:phone":"+32 11 63 16 94",
    "sg:postcode":"3990",
    "sg:province":"Limburg",
    "wof:name":"Jaeken Danny",
    "wof:placetype":"venue"
},
  "geometry": {"coordinates":[5.4559488297,51.1313247681],"type":"Point"}
}