{
  "type": "Feature",
  "properties": {
    "addr:full":"Avenue Wielemans Ceuppens 36a Bruxelles (forest) Bruxelles-Capitale 1190",
    "addr:housenumber":"36a",
    "addr:postcode":"1190",
    "addr:street":"Avenue Wielemans Ceuppens",
    "iso:country":"BE",
    "sg:address":"Avenue Wielemans Ceuppens 36a",
    "sg:city":"Bruxelles (forest)",
    "sg:classifiers":[
        {
            "category":"Bakery",
            "type":"Food & Drink"
        }
    ],
    "sg:phone":"+32 2 534 56 63",
    "sg:postcode":"1190",
    "sg:province":"Bruxelles-Capitale",
    "sg:tags":[
        "confectioner",
        "baker"
    ],
    "wof:name":"Croissant D'orient (au)",
    "wof:placetype":"venue"
},
  "geometry": {"coordinates":[4.3279671669,50.8244171143],"type":"Point"}
}