{
  "type": "Feature",
  "properties": {
    "iso:country":"BE",
    "sg:address":"Avenue Des Nerviens 117",
    "sg:city":"Etterbeek (bruxelles)",
    "sg:classifiers":[
        {
            "category":"Shopping",
            "subcategory":"Clothing, Apparel, & Fashions",
            "type":"Retail Goods"
        }
    ],
    "sg:postcode":"1040",
    "sg:province":"Bruxelles-Capitale",
    "sg:tags":[
        "ondergoed",
        "lingerie"
    ],
    "wof:name":"Jasmin Massage",
    "wof:placetype":"venue"
},
  "geometry": {"coordinates":[4.3917198181,50.8381080627],"type":"Point"}
}