{
  "type": "Feature",
  "properties": {
    "addr:full":"Rue Petit Baimont 15 Nandrin Li\u00e8ge 4550",
    "addr:housenumber":"15",
    "addr:postcode":"4550",
    "addr:street":"Rue Petit Baimont",
    "iso:country":"BE",
    "sg:address":"Rue Petit Baimont 15",
    "sg:city":"Nandrin",
    "sg:classifiers":[
        {
            "category":"Health Services",
            "subcategory":"Nursing And Care Facility",
            "type":"Services"
        }
    ],
    "sg:phone":"+32 85 51 24 67",
    "sg:postcode":"4550",
    "sg:province":"Li\u00e8ge",
    "sg:tags":[
        "home",
        "rest"
    ],
    "wof:name":"Chatelaine (la)",
    "wof:placetype":"venue"
},
  "geometry": {"coordinates":[5.408249855,50.5077857971],"type":"Point"}
}