{
  "type": "Feature",
  "properties": {
    "addr:full":"Rue Deru-dehayes 17 Verviers Li\u00e8ge 4802",
    "addr:housenumber":"17",
    "addr:postcode":"4802",
    "addr:street":"Rue Deru-Dehayes",
    "iso:country":"BE",
    "sg:address":"Rue Deru-dehayes 17",
    "sg:city":"Verviers",
    "sg:orig_category":"Instituts de beaut\u00e9",
    "sg:phone":"+32 87 22 05 61",
    "sg:postcode":"4802",
    "sg:province":"Li\u00e8ge",
    "wof:name":"Institut Daveloose",
    "wof:placetype":"venue"
},
  "geometry": {"coordinates":[5.864484787,50.5772895813],"type":"Point"}
}