{
  "type": "Feature",
  "properties": {
    "addr:full":"Volksberg 45 Kortrijk (bellegem) West-Vlaanderen 8510",
    "addr:housenumber":"45",
    "addr:postcode":"8510",
    "addr:street":"Volksberg",
    "iso:country":"BE",
    "sg:address":"Volksberg 45",
    "sg:city":"Kortrijk (bellegem)",
    "sg:classifiers":[
        {
            "category":"Shopping",
            "subcategory":"Computers & Home Electronics",
            "type":"Retail Goods"
        }
    ],
    "sg:phone":"+32 56 21 25 96",
    "sg:postcode":"8510",
    "sg:province":"West-Vlaanderen",
    "sg:tags":[
        "-",
        "processing",
        "data",
        "cleaning"
    ],
    "wof:name":"C D C Cleaning",
    "wof:placetype":"venue"
},
  "geometry": {"coordinates":[3.2897200584,50.7752799988],"type":"Point"}
}