{
  "type": "Feature",
  "properties": {
    "addr:full":"Rue Ernest Montelier 18 Fernelmont (noville-les-bois) Namur 5380",
    "addr:housenumber":"18",
    "addr:postcode":"5380",
    "addr:street":"Rue Ernest Montelier",
    "iso:country":"BE",
    "sg:address":"Rue Ernest Montelier 18",
    "sg:city":"Fernelmont (noville-les-bois)",
    "sg:classifiers":[
        {
            "category":"Building & Trades",
            "subcategory":"Construction",
            "type":"Services"
        }
    ],
    "sg:phone":"+32 81 83 53 33",
    "sg:postcode":"5380",
    "sg:province":"Namur",
    "sg:tags":[
        "carpenter"
    ],
    "wof:name":"Levecq M",
    "wof:placetype":"venue"
},
  "geometry": {"coordinates":[4.9772920609,50.534236908],"type":"Point"}
}