{
  "type": "Feature",
  "properties": {
    "addr:full":"Nieuwstraat 45 Tienen Vlaams-Brabant 3300",
    "addr:housenumber":"45",
    "addr:postcode":"3300",
    "addr:street":"Nieuwstraat",
    "iso:country":"BE",
    "sg:address":"Nieuwstraat 45",
    "sg:city":"Tienen",
    "sg:orig_category":"Banken and kredietinstellingen",
    "sg:phone":"+32 16 81 41 48",
    "sg:postcode":"3300",
    "sg:province":"Vlaams-Brabant",
    "wof:name":"Anhyp",
    "wof:placetype":"venue"
},
  "geometry": {"coordinates":[4.93983078,50.8065948486],"type":"Point"}
}