{
  "type": "Feature",
  "properties": {
    "iso:country":"BE",
    "sg:address":"Rue Des Quatre Arbres 14",
    "sg:city":"Florenville",
    "sg:orig_category":"Maisons de vacances",
    "sg:phone":"+32 61 31 22 39",
    "sg:postcode":"6820",
    "sg:province":"Luxembourg",
    "wof:name":"Le Chalet",
    "wof:placetype":"venue"
},
  "geometry": {"coordinates":[5.2283329964,49.7104873657],"type":"Point"}
}