{
  "type": "Feature",
  "properties": {
    "iso:country":"BE",
    "sg:address":"Daalderdijk 47",
    "sg:city":"Dilsen-stokkem (stokkem)",
    "sg:classifiers":[
        {
            "category":"Farming",
            "subcategory":"Livestock Farm",
            "type":"Manufacturing & Wholesale Goods"
        }
    ],
    "sg:phone":"+32 89 75 62 89",
    "sg:postcode":"3650",
    "sg:province":"Limburg",
    "sg:tags":[
        "buyer"
    ],
    "wof:name":"Wittebols J - Reggers I",
    "wof:placetype":"venue"
},
  "geometry": {"coordinates":[5.727396965,51.0364189148],"type":"Point"}
}