{
  "type": "Feature",
  "properties": {
    "iso:country":"BE",
    "sg:address":"Avenue Jacques Gr\u00e9goire 5",
    "sg:city":"Huy",
    "sg:classifiers":[
        {
            "category":"Professional",
            "subcategory":"Art Services",
            "type":"Services"
        }
    ],
    "sg:phone":"+32 85 23 58 59",
    "sg:postcode":"4500",
    "sg:province":"Li\u00e8ge",
    "sg:tags":[
        "photography",
        "reporting",
        "-"
    ],
    "wof:name":"Photo P Randaxhe",
    "wof:placetype":"venue"
},
  "geometry": {"coordinates":[5.2503829002,50.519733429],"type":"Point"}
}