{
  "type": "Feature",
  "properties": {
    "iso:country":"BE",
    "sg:address":"Herenstraat 201",
    "sg:city":"Genk",
    "sg:classifiers":[
        {
            "category":"Health Services",
            "subcategory":"Dentist",
            "type":"Services"
        }
    ],
    "sg:phone":"+32 89 30 88 40",
    "sg:postcode":"3600",
    "sg:province":"Limburg",
    "wof:name":"Metalidis Spyridon",
    "wof:placetype":"venue"
},
  "geometry": {"coordinates":[5.5168938637,50.9844589233],"type":"Point"}
}