{
  "type": "Feature",
  "properties": {
    "iso:country":"BE",
    "sg:address":"Latemstraat 113",
    "sg:city":"Sint-martens-latem",
    "sg:classifiers":[
        {
            "category":"Health Services",
            "subcategory":"Dentist",
            "type":"Services"
        }
    ],
    "sg:phone":"+32 9 281 29 12",
    "sg:postcode":"9830",
    "sg:province":"Oost-Vlaanderen",
    "wof:name":"Michiels Greet",
    "wof:placetype":"venue"
},
  "geometry": {"coordinates":[3.6313550472,51.0158882141],"type":"Point"}
}