{
  "type": "Feature",
  "properties": {
    "addr:full":"Duinenstraat 296 Bredene West-Vlaanderen 8450",
    "addr:housenumber":"296",
    "addr:postcode":"8450",
    "addr:street":"Duinenstraat",
    "iso:country":"BE",
    "sg:address":"Duinenstraat 296",
    "sg:city":"Bredene",
    "sg:classifiers":[
        {
            "category":"Retail",
            "subcategory":"Auto Repair",
            "type":"Services"
        }
    ],
    "sg:phone":"+32 59 32 18 87",
    "sg:postcode":"8450",
    "sg:province":"West-Vlaanderen",
    "sg:tags":[
        "automobile",
        "-",
        "wrecking"
    ],
    "wof:name":"Van Heuverzwijn-heerman",
    "wof:placetype":"venue"
},
  "geometry": {"coordinates":[2.9630448818,51.2456321716],"type":"Point"}
}