{
  "type": "Feature",
  "properties": {
    "iso:country":"BE",
    "sg:address":"Avenue Ch\u00c2teau De Walzin 11b26",
    "sg:city":"Ukkel/uccle",
    "sg:orig_category":"Agences immobili\u00e8res",
    "sg:phone":"+32 2 345 90 80",
    "sg:postcode":"1180",
    "sg:province":"Bruxelles-Capitale",
    "wof:name":"Bureau Logeurop",
    "wof:placetype":"venue"
},
  "geometry": {"coordinates":[4.3475570679,50.8095092773],"type":"Point"}
}