{
  "type": "Feature",
  "properties": {
    "iso:country":"BE",
    "sg:address":"Poorterijstraat 34ba",
    "sg:city":"Zedelgem",
    "sg:orig_category":"Slagers",
    "sg:phone":"+32 50 21 67 90",
    "sg:postcode":"8211",
    "sg:province":"West-Vlaanderen",
    "wof:name":"Marc Vermeulen",
    "wof:placetype":"venue"
},
  "geometry": {"coordinates":[3.0889649391,51.1200408936],"type":"Point"}
}