{
  "type": "Feature",
  "properties": {
    "iso:country":"BE",
    "sg:address":"Talstrasse 28 B",
    "sg:city":"Kettenis",
    "sg:orig_category":"Industri\u00eble elektrische installaties",
    "sg:phone":"+32 87 55 23 37",
    "sg:postcode":"4701",
    "sg:province":"Li\u00e8ge",
    "wof:name":"Elektro-seel",
    "wof:placetype":"venue"
},
  "geometry": {"coordinates":[6.0516381264,50.6449623108],"type":"Point"}
}