{
  "type": "Feature",
  "properties": {
    "addr:full":"Vichtesteenweg 70 Deerlijk West-Vlaanderen 8540",
    "addr:housenumber":"70",
    "addr:postcode":"8540",
    "addr:street":"Vichtesteenweg",
    "iso:country":"BE",
    "sg:address":"Vichtesteenweg 70",
    "sg:city":"Deerlijk",
    "sg:orig_category":"Herstellingen and onderhoud van auto's",
    "sg:phone":"+32 56 77 30 46",
    "sg:postcode":"8540",
    "sg:province":"West-Vlaanderen",
    "wof:name":"Garage Casteele",
    "wof:placetype":"venue"
},
  "geometry": {"coordinates":[3.3649230003,50.8510246277],"type":"Point"}
}