{
  "type": "Feature",
  "properties": {
    "addr:full":"C\u00c9sar Snoecklaan 1 Ronse/renaix Oost-Vlaanderen 9600",
    "addr:housenumber":"1",
    "addr:postcode":"9600",
    "addr:street":"Ce\u0301Sar Snoecklaan",
    "iso:country":"BE",
    "sg:address":"C\u00c9sar Snoecklaan 1",
    "sg:city":"Ronse/renaix",
    "sg:orig_category":"Schoenen",
    "sg:phone":"+32 55 20 92 29",
    "sg:postcode":"9600",
    "sg:province":"Oost-Vlaanderen",
    "wof:name":"Brantano",
    "wof:placetype":"venue"
},
  "geometry": {"coordinates":[3.5992999077,50.7470397949],"type":"Point"}
}