{
  "type": "Feature",
  "properties": {
    "addr:full":"Rue Du Doyenn\u00e9 75 Bruxelles (uccle) Bruxelles-Capitale 1180",
    "addr:housenumber":"75",
    "addr:postcode":"1180",
    "addr:street":"Rue Du Doyenne\u0301",
    "iso:country":"BE",
    "sg:address":"Rue Du Doyenn\u00e9 75",
    "sg:city":"Bruxelles (uccle)",
    "sg:classifiers":[
        {
            "category":"Home & Garden",
            "subcategory":"Home Furnishings",
            "type":"Retail Goods"
        }
    ],
    "sg:phone":"+32 2 346 53 27",
    "sg:postcode":"1180",
    "sg:province":"Bruxelles-Capitale",
    "sg:tags":[
        "interior",
        "decoration"
    ],
    "wof:name":"Interd\u00e9cor",
    "wof:placetype":"venue"
},
  "geometry": {"coordinates":[4.3403530121,50.8031349182],"type":"Point"}
}