{
  "type": "Feature",
  "properties": {
    "iso:country":"BE",
    "sg:address":"Lange Herentalsestraat 16 A",
    "sg:city":"Antwerpen",
    "sg:orig_category":"Etablissements Erotiques",
    "sg:phone":"+32 3 231 73 64",
    "sg:postcode":"2018",
    "sg:province":"Antwerpen",
    "wof:name":"Condessa",
    "wof:placetype":"venue"
},
  "geometry": {"coordinates":[4.417142868,51.215877533],"type":"Point"}
}