{
  "type": "Feature",
  "properties": {
    "addr:full":"Nekkerplas 20 Wevelgem West-Vlaanderen 8560",
    "addr:housenumber":"20",
    "addr:postcode":"8560",
    "addr:street":"Nekkerplas",
    "iso:country":"BE",
    "sg:address":"Nekkerplas 20",
    "sg:city":"Wevelgem",
    "sg:orig_category":"Artsen and specialisten",
    "sg:phone":"+32 56 41 47 85",
    "sg:postcode":"8560",
    "sg:province":"West-Vlaanderen",
    "wof:name":"Tomas Herman",
    "wof:placetype":"venue"
},
  "geometry": {"coordinates":[3.2059679031,50.8464202881],"type":"Point"}
}