{
  "type": "Feature",
  "properties": {
    "addr:full":"Sleihagestraat 3 Staden West-Vlaanderen 8840",
    "addr:housenumber":"3",
    "addr:postcode":"8840",
    "addr:street":"Sleihagestraat",
    "iso:country":"BE",
    "sg:address":"Sleihagestraat 3",
    "sg:city":"Staden",
    "sg:orig_category":"V\u00eatements pour Dames. V\u00eatements pour Hommes",
    "sg:phone":"+32 51 20 31 40",
    "sg:postcode":"8840",
    "sg:province":"West-Vlaanderen",
    "wof:name":"Huis Vaco",
    "wof:placetype":"venue"
},
  "geometry": {"coordinates":[3.0591781139,50.9409637451],"type":"Point"}
}