{
  "type": "Feature",
  "properties": {
    "iso:country":"BE",
    "sg:address":"Oscar Colbrandtstraat 91",
    "sg:city":"Gent",
    "sg:orig_category":"Artistes ind\u00e9pendants",
    "sg:phone":"+32 9 228 52 93",
    "sg:postcode":"9040",
    "sg:province":"Oost-Vlaanderen",
    "wof:name":"Desmedt",
    "wof:placetype":"venue"
},
  "geometry": {"coordinates":[3.7554299831,51.0556411743],"type":"Point"}
}