{
  "type": "Feature",
  "properties": {
    "iso:country":"BE",
    "sg:address":"Hoogstraat 123",
    "sg:city":"As",
    "sg:orig_category":"Apotheken",
    "sg:phone":"+32 89 65 75 80",
    "sg:postcode":"3668",
    "sg:province":"Limburg",
    "wof:name":"M. Craeghs",
    "wof:placetype":"venue"
},
  "geometry": {"coordinates":[5.6019868851,51.0160980225],"type":"Point"}
}