{
  "type": "Feature",
  "properties": {
    "addr:full":"Hameau De Kin 54 Aywaille Li\u00e8ge 4920",
    "addr:housenumber":"54",
    "addr:postcode":"4920",
    "addr:street":"Hameau De Kin",
    "iso:country":"BE",
    "sg:address":"Hameau De Kin 54",
    "sg:city":"Aywaille",
    "sg:orig_category":"Enseignement maternel and primaire",
    "sg:phone":"+32 4 384 58 66",
    "sg:postcode":"4920",
    "sg:province":"Li\u00e8ge",
    "wof:name":"Ecole Fond. Communale",
    "wof:placetype":"venue"
},
  "geometry": {"coordinates":[5.692029953,50.4668998718],"type":"Point"}
}