{
  "type": "Feature",
  "properties": {
    "addr:full":"Krekelenbergweg 8 Sint-katelijne-waver Antwerpen 2860",
    "addr:housenumber":"8",
    "addr:postcode":"2860",
    "addr:street":"Krekelenbergweg",
    "iso:country":"BE",
    "sg:address":"Krekelenbergweg 8",
    "sg:city":"Sint-katelijne-waver",
    "sg:orig_category":"Groententeelt",
    "sg:phone":"+32 15 31 31 13",
    "sg:postcode":"2860",
    "sg:province":"Antwerpen",
    "wof:name":"Asselberghs Jules-karina",
    "wof:placetype":"venue"
},
  "geometry": {"coordinates":[4.5245041847,51.0837936401],"type":"Point"}
}