{
  "type": "Feature",
  "properties": {
    "iso:country":"BE",
    "sg:address":"Kortrijksestraat 204",
    "sg:city":"Izegem",
    "sg:classifiers":[
        {
            "category":"Food & Beverages",
            "subcategory":"Cheese",
            "type":"Retail Goods"
        }
    ],
    "sg:phone":"+32 51 30 60 53",
    "sg:postcode":"8870",
    "sg:province":"West-Vlaanderen",
    "sg:tags":[
        "-"
    ],
    "wof:name":"Hoeveke ('t)",
    "wof:placetype":"venue"
},
  "geometry": {"coordinates":[3.2183830738,50.909072876],"type":"Point"}
}