{
  "type": "Feature",
  "properties": {
    "addr:full":"Place Jourdan 47 Bruxelles (etterbeek) Bruxelles-Capitale 1040",
    "addr:housenumber":"47",
    "addr:postcode":"1040",
    "addr:street":"Place Jourdan",
    "iso:country":"BE",
    "sg:address":"Place Jourdan 47",
    "sg:city":"Bruxelles (etterbeek)",
    "sg:classifiers":[
        {
            "category":"Bars & Pubs",
            "type":"Food & Drink"
        }
    ],
    "sg:phone":"+32 2 230 85 92",
    "sg:postcode":"1040",
    "sg:province":"Bruxelles-Capitale",
    "wof:name":"Esp\u00e9rence",
    "wof:placetype":"venue"
},
  "geometry": {"coordinates":[4.3811349869,50.8368186951],"type":"Point"}
}