{
  "type": "Feature",
  "properties": {
    "iso:country":"BE",
    "sg:address":"Chauss\u00c9e De Waterloo 255",
    "sg:city":"Sint-gillis",
    "sg:orig_category":"Agences d'exp\u00e9dition",
    "sg:phone":"+32 2 534 60 20",
    "sg:postcode":"1060",
    "sg:province":"Bruxelles-Capitale",
    "wof:name":"Sogetrade",
    "wof:placetype":"venue"
},
  "geometry": {"coordinates":[4.3489189148,50.8248100281],"type":"Point"}
}