{
  "type": "Feature",
  "properties": {
    "addr:full":"Liersesteenweg 52 Lint Antwerpen 2547",
    "addr:housenumber":"52",
    "addr:postcode":"2547",
    "addr:street":"Liersesteenweg",
    "iso:country":"BE",
    "sg:address":"Liersesteenweg 52",
    "sg:city":"Lint",
    "sg:orig_category":"S\u00e9lection de personnel and placement",
    "sg:phone":"+32 3 454 35 66",
    "sg:postcode":"2547",
    "sg:province":"Antwerpen",
    "wof:name":"Pwa Lint",
    "wof:placetype":"venue"
},
  "geometry": {"coordinates":[4.5004611015,51.1268806458],"type":"Point"}
}