{
  "type": "Feature",
  "properties": {
    "iso:country":"BE",
    "sg:address":"Route De Mons 34",
    "sg:city":"Binche",
    "sg:classifiers":[
        {
            "category":"Shopping",
            "subcategory":"Florist",
            "type":"Retail Goods"
        }
    ],
    "sg:phone":"+32 64 33 88 68",
    "sg:postcode":"7130",
    "sg:province":"Hainaut",
    "wof:name":"Malory (fleurs)",
    "wof:placetype":"venue"
},
  "geometry": {"coordinates":[4.1646361351,50.4131126404],"type":"Point"}
}