{
  "type": "Feature",
  "properties": {
    "iso:country":"BE",
    "sg:address":"Grand'place 7",
    "sg:city":"Nivelles",
    "sg:classifiers":[
        {
            "category":"Fast Food",
            "type":"Food & Drink"
        }
    ],
    "sg:phone":"+32 67 21 12 41",
    "sg:postcode":"1400",
    "sg:province":"Brabant Wallon",
    "sg:tags":[
        "\u00c0",
        "restaurants",
        "emporter",
        "restaurant"
    ],
    "wof:name":"H\u00d4tel Du Commerce",
    "wof:placetype":"venue"
},
  "geometry": {"coordinates":[4.3232650757,50.596786499],"type":"Point"}
}