{
  "type": "Feature",
  "properties": {
    "addr:full":"Roekendreef 5 Vosselaar Antwerpen 2350",
    "addr:housenumber":"5",
    "addr:postcode":"2350",
    "addr:street":"Roekendreef",
    "iso:country":"BE",
    "sg:address":"Roekendreef 5",
    "sg:city":"Vosselaar",
    "sg:orig_category":"Artsen and specialisten",
    "sg:phone":"+32 14 43 95 70",
    "sg:postcode":"2350",
    "sg:province":"Antwerpen",
    "wof:name":"Hildegarde Creus",
    "wof:placetype":"venue"
},
  "geometry": {"coordinates":[4.896859169,51.3194885254],"type":"Point"}
}