{
  "type": "Feature",
  "properties": {
    "addr:full":"Boulevard Albert Elisabeth 91 Mons Hainaut 7000",
    "addr:housenumber":"91",
    "addr:postcode":"7000",
    "addr:street":"Boulevard Albert Elisabeth;Hainaut",
    "iso:country":"BE",
    "sg:address":"Boulevard Albert Elisabeth 91",
    "sg:city":"Mons",
    "sg:classifiers":[
        {
            "category":"Health Services",
            "subcategory":"Health Practitioner",
            "type":"Services"
        }
    ],
    "sg:phone":"+32 65 36 37 16",
    "sg:postcode":"7000",
    "sg:province":"Hainaut",
    "sg:tags":[
        "osteopath"
    ],
    "wof:name":"Pamelard P",
    "wof:placetype":"venue"
},
  "geometry": {"coordinates":[3.9508569241,50.4457931519],"type":"Point"}
}