{
  "type": "Feature",
  "properties": {
    "iso:country":"BE",
    "sg:address":"Rue Du G\u00e9n\u00e9ral De Gaulle 192",
    "sg:city":"Courcelles",
    "sg:classifiers":[
        {
            "category":"Shopping",
            "subcategory":"Jewelry",
            "type":"Retail Goods"
        }
    ],
    "sg:postcode":"6180",
    "sg:province":"Hainaut",
    "sg:tags":[
        "jeweller",
        "-"
    ],
    "wof:name":"Horlotec Scrl",
    "wof:placetype":"venue"
},
  "geometry": {"coordinates":[4.3816738129,50.4541702271],"type":"Point"}
}