{
  "type": "Feature",
  "properties": {
    "addr:full":"Heusdendorp 4 Destelbergen Oost-Vlaanderen 9070",
    "addr:housenumber":"4",
    "addr:postcode":"9070",
    "addr:street":"Heusdendorp",
    "iso:country":"BE",
    "sg:address":"Heusdendorp 4",
    "sg:city":"Destelbergen",
    "sg:classifiers":[
        {
            "category":"Shopping",
            "subcategory":"Clothing, Apparel, & Fashions",
            "type":"Retail Goods"
        }
    ],
    "sg:phone":"+32 9 230 20 65",
    "sg:postcode":"9070",
    "sg:province":"Oost-Vlaanderen",
    "sg:tags":[
        "ondergoed",
        "lingerie"
    ],
    "wof:name":"Elsina",
    "wof:placetype":"venue"
},
  "geometry": {"coordinates":[3.8000409603,51.0289344788],"type":"Point"}
}