{
  "type": "Feature",
  "properties": {
    "addr:full":"Mercatorstraat 2 Kruibeke Oost-Vlaanderen 9150",
    "addr:housenumber":"2",
    "addr:postcode":"9150",
    "addr:street":"Mercatorstraat",
    "iso:country":"BE",
    "sg:address":"Mercatorstraat 2",
    "sg:city":"Kruibeke",
    "sg:orig_category":"Kapsalons",
    "sg:phone":"+32 3 774 34 49",
    "sg:postcode":"9150",
    "sg:province":"Oost-Vlaanderen",
    "wof:name":"Picass Hair",
    "wof:placetype":"venue"
},
  "geometry": {"coordinates":[4.3118748665,51.166267395],"type":"Point"}
}