{
  "type": "Feature",
  "properties": {
    "iso:country":"BE",
    "sg:address":"Rue Des Lapins 32",
    "sg:city":"Anderlecht",
    "sg:classifiers":[
        {
            "category":"Arena",
            "subcategory":"Sports Club",
            "type":"Entertainment"
        }
    ],
    "sg:phone":"+32 2 523 69 39",
    "sg:postcode":"1070",
    "sg:province":"Bruxelles-Capitale",
    "sg:tags":[
        "terrain",
        "hors",
        "de",
        "installation",
        "sportifs"
    ],
    "wof:name":"Salle New-mayfair",
    "wof:placetype":"venue"
},
  "geometry": {"coordinates":[4.2750811577,50.8253288269],"type":"Point"}
}