{
  "type": "Feature",
  "properties": {
    "iso:country":"BE",
    "sg:address":"Avenue George Bergmann 43",
    "sg:city":"Bruxelles (ixelles)",
    "sg:classifiers":[
        {
            "category":"Health Services",
            "subcategory":"Health Practitioner",
            "type":"Services"
        }
    ],
    "sg:phone":"+32 2 672 30 87",
    "sg:postcode":"1050",
    "sg:province":"Bruxelles-Capitale",
    "sg:tags":[
        "physiotherapist"
    ],
    "wof:name":"Hebrant M",
    "wof:placetype":"venue"
},
  "geometry": {"coordinates":[4.3919091225,50.8094367981],"type":"Point"}
}