{
  "type": "Feature",
  "properties": {
    "iso:country":"BE",
    "sg:address":"Rue De Namur 34",
    "sg:city":"Genappe (houtain-le-val)",
    "sg:classifiers":[
        {
            "category":"Home & Garden",
            "subcategory":"Building Materials",
            "type":"Retail Goods"
        }
    ],
    "sg:phone":"+32 67 77 18 18",
    "sg:postcode":"1476",
    "sg:province":"Brabant Wallon",
    "sg:tags":[
        "window"
    ],
    "wof:name":"De Vijlder M",
    "wof:placetype":"venue"
},
  "geometry": {"coordinates":[4.4224982262,50.5797271729],"type":"Point"}
}