{
  "type": "Feature",
  "properties": {
    "iso:country":"BE",
    "sg:address":"Langemarkstraat 132",
    "sg:city":"Zonnebeke",
    "sg:orig_category":"Eleveurs and marchands de porcs",
    "sg:phone":"+32 51 77 70 37",
    "sg:postcode":"8980",
    "sg:province":"West-Vlaanderen",
    "wof:name":"Paul Vulsteke",
    "wof:placetype":"venue"
},
  "geometry": {"coordinates":[2.9751970768,50.8805656433],"type":"Point"}
}