{
  "type": "Feature",
  "properties": {
    "addr:full":"Zwaanhofweg 1 Ieper West-Vlaanderen 8900",
    "addr:housenumber":"1",
    "addr:postcode":"8900",
    "addr:street":"Zwaanhofweg",
    "iso:country":"BE",
    "sg:address":"Zwaanhofweg 1",
    "sg:city":"Ieper",
    "sg:classifiers":[
        {
            "category":"Manufacturing",
            "subcategory":"Food",
            "type":"Manufacturing & Wholesale Goods"
        }
    ],
    "sg:phone":"+32 57 22 84 21",
    "sg:postcode":"8900",
    "sg:province":"West-Vlaanderen",
    "sg:tags":[
        "industry",
        "-",
        "ingredient"
    ],
    "wof:name":"Dupont Protein Technologies Nv",
    "wof:placetype":"venue"
},
  "geometry": {"coordinates":[2.8758130074,50.8726921082],"type":"Point"}
}