{
  "type": "Feature",
  "properties": {
    "iso:country":"BE",
    "sg:address":"Rue Du Bosquet 7",
    "sg:city":"Louvain-la-neuve",
    "sg:classifiers":[
        {
            "category":"Manufacturing",
            "subcategory":"Chemicals & Compounds",
            "type":"Manufacturing & Wholesale Goods"
        }
    ],
    "sg:phone":"+32 2 652 12 27",
    "sg:postcode":"1348",
    "sg:province":"Brabant Wallon",
    "sg:tags":[
        "industrial"
    ],
    "wof:name":"Collard Et Collette S.a.",
    "wof:placetype":"venue"
},
  "geometry": {"coordinates":[4.4948849678,50.732006073],"type":"Point"}
}