{
  "type": "Feature",
  "properties": {
    "addr:full":"Statiestraat 61 Langemark-poelkapelle (langemark) West-Vlaanderen 8920",
    "addr:housenumber":"61",
    "addr:postcode":"8920",
    "addr:street":"Statiestraat",
    "iso:country":"BE",
    "sg:address":"Statiestraat 61",
    "sg:city":"Langemark-poelkapelle (langemark)",
    "sg:orig_category":"Newspapers, magazines, periodicals - Distribution",
    "sg:phone":"+32 57 48 52 40",
    "sg:postcode":"8920",
    "sg:province":"West-Vlaanderen",
    "wof:name":"Het Statieplein",
    "wof:placetype":"venue"
},
  "geometry": {"coordinates":[2.919770956,50.9132423401],"type":"Point"}
}