{
  "type": "Feature",
  "properties": {
    "iso:country":"BE",
    "sg:address":"Golflaan 2",
    "sg:city":"Sint-martens-latem",
    "sg:classifiers":[
        {
            "category":"Restaurant",
            "type":"Food & Drink"
        }
    ],
    "sg:phone":"+32 9 282 65 62",
    "sg:postcode":"9830",
    "sg:province":"Oost-Vlaanderen",
    "sg:tags":[
        "caf\u00e9s"
    ],
    "wof:name":"'t Misverstand",
    "wof:placetype":"venue"
},
  "geometry": {"coordinates":[3.6290419102,51.0134048462],"type":"Point"}
}