{
  "type": "Feature",
  "properties": {
    "iso:country":"BE",
    "sg:address":"Van Orleystraat 4",
    "sg:city":"Brussel/bruxelles",
    "sg:orig_category":"Diverse organisaties and verenigingen Vakantiedorpen",
    "sg:phone":"+32 2 209 03 00",
    "sg:postcode":"1000",
    "sg:province":"Bruxelles-Capitale",
    "wof:name":"C.b.t.j.",
    "wof:placetype":"venue"
},
  "geometry": {"coordinates":[4.3671789169,50.8518295288],"type":"Point"}
}