{
  "type": "Feature",
  "properties": {
    "addr:full":"Visesteenweg 209 Riemst Limburg 3770",
    "addr:housenumber":"209",
    "addr:postcode":"3770",
    "addr:street":"Visesteenweg",
    "iso:country":"BE",
    "sg:address":"Visesteenweg 209",
    "sg:city":"Riemst",
    "sg:orig_category":"Banken and kredietinstellingen",
    "sg:phone":"+32 12 45 19 79",
    "sg:postcode":"3770",
    "sg:province":"Limburg",
    "wof:name":"Kbc",
    "wof:placetype":"venue"
},
  "geometry": {"coordinates":[5.6054201126,50.8047485352],"type":"Point"}
}