{
  "type": "Feature",
  "properties": {
    "iso:country":"BE",
    "sg:address":"Grote Kring 10",
    "sg:city":"Kortrijk",
    "sg:classifiers":[
        {
            "category":"Shopping",
            "subcategory":"Antiques",
            "type":"Retail Goods"
        }
    ],
    "sg:phone":"+32 56 20 30 07",
    "sg:postcode":"8500",
    "sg:province":"West-Vlaanderen",
    "wof:name":"Aquarelle",
    "wof:placetype":"venue"
},
  "geometry": {"coordinates":[3.2700688839,50.8280296326],"type":"Point"}
}