{
  "type": "Feature",
  "properties": {
    "addr:full":"Fortsteenweg 3 Kapellen Antwerpen 2950",
    "addr:housenumber":"3",
    "addr:postcode":"2950",
    "addr:street":"Fortsteenweg",
    "iso:country":"BE",
    "sg:address":"Fortsteenweg 3",
    "sg:city":"Kapellen",
    "sg:classifiers":[
        {
            "category":"Banks & Credit Unions",
            "subcategory":"Investment Brokerage",
            "type":"Services"
        }
    ],
    "sg:phone":"+32 3 664 69 81",
    "sg:postcode":"2950",
    "sg:province":"Antwerpen",
    "sg:tags":[
        "auditor"
    ],
    "wof:name":"Meyers R",
    "wof:placetype":"venue"
},
  "geometry": {"coordinates":[4.4378418922,51.3202972412],"type":"Point"}
}