{
  "type": "Feature",
  "properties": {
    "iso:country":"BE",
    "sg:address":"Jodestraat 5",
    "sg:city":"Herk-de-stad",
    "sg:classifiers":[
        {
            "category":"Retail",
            "subcategory":"Animal Services",
            "type":"Services"
        }
    ],
    "sg:phone":"+32 13 55 44 57",
    "sg:postcode":"3540",
    "sg:province":"Limburg",
    "sg:tags":[
        "breeding",
        "selling",
        "-",
        "dog"
    ],
    "wof:name":"Bex P",
    "wof:placetype":"venue"
},
  "geometry": {"coordinates":[5.1764469147,50.9214630127],"type":"Point"}
}