{
  "type": "Feature",
  "properties": {
    "iso:country":"BE",
    "sg:address":"Kerkstraat 61bw5",
    "sg:city":"Lommel",
    "sg:orig_category":"V\u00eatements pour Dames. V\u00eatements pour Hommes",
    "sg:phone":"+32 11 54 63 35",
    "sg:postcode":"3920",
    "sg:province":"Limburg",
    "wof:name":"Fa. Gerelli",
    "wof:placetype":"venue"
},
  "geometry": {"coordinates":[5.313120842,51.2291259766],"type":"Point"}
}