{
  "type": "Feature",
  "properties": {
    "iso:country":"BE",
    "sg:address":"Gerststraat 4",
    "sg:city":"Jabbeke",
    "sg:orig_category":"Software ontwikkeling and ontwerp",
    "sg:phone":"+32 50 81 42 75",
    "sg:postcode":"8490",
    "sg:province":"West-Vlaanderen",
    "wof:name":"Vermaut Digital Media",
    "wof:placetype":"venue"
},
  "geometry": {"coordinates":[3.0845839977,51.1745223999],"type":"Point"}
}