{
  "type": "Feature",
  "properties": {
    "addr:full":"Avenue Jottrand 29 Sint-joost-ten-node/saint-joss Bruxelles-Capitale 1210",
    "addr:housenumber":"29",
    "addr:postcode":"1210",
    "addr:street":"Avenue Jottrand",
    "iso:country":"BE",
    "sg:address":"Avenue Jottrand 29",
    "sg:city":"Sint-joost-ten-node/saint-joss",
    "sg:orig_category":"Sociale secretariaten",
    "sg:phone":"+32 2 223 06 80",
    "sg:postcode":"1210",
    "sg:province":"Bruxelles-Capitale",
    "wof:name":"Groupe Gestion Sociale",
    "wof:placetype":"venue"
},
  "geometry": {"coordinates":[4.3776159286,50.8519859314],"type":"Point"}
}