{
  "type": "Feature",
  "properties": {
    "addr:full":"Rue De La Caserne 27 Arlon Luxembourg 6700",
    "addr:housenumber":"27",
    "addr:postcode":"6700",
    "addr:street":"Rue De La Caserne",
    "iso:country":"BE",
    "sg:address":"Rue De La Caserne 27",
    "sg:city":"Arlon",
    "sg:orig_category":"Muziekinstrumenten",
    "sg:phone":"+32 63 22 22 53",
    "sg:postcode":"6700",
    "sg:province":"Luxembourg",
    "wof:name":"B.a.t.e.s. Europe",
    "wof:placetype":"venue"
},
  "geometry": {"coordinates":[5.8160052299,49.685585022],"type":"Point"}
}