{
  "type": "Feature",
  "properties": {
    "addr:full":"Diksmuidekaai 1-21 Kortrijk West-Vlaanderen 8500",
    "addr:housenumber":"1-21",
    "addr:postcode":"8500",
    "iso:country":"BE",
    "sg:address":"Diksmuidekaai 1-21",
    "sg:city":"Kortrijk",
    "sg:orig_category":"Juwelen and horloges",
    "sg:phone":"+32 56 20 52 85",
    "sg:postcode":"8500",
    "sg:province":"West-Vlaanderen",
    "wof:name":"Ducastille",
    "wof:placetype":"venue"
},
  "geometry": {"coordinates":[3.2594380379,50.8274879456],"type":"Point"}
}