{
  "type": "Feature",
  "properties": {
    "addr:full":"Herenthoutseweg 13 Heist-op-den-berg Antwerpen 2222",
    "addr:housenumber":"13",
    "addr:postcode":"2222",
    "addr:street":"Herenthoutseweg",
    "iso:country":"BE",
    "sg:address":"Herenthoutseweg 13",
    "sg:city":"Heist-op-den-berg",
    "sg:orig_category":"Banken and kredietinstellingen Verzekeringsmakelaars and experts",
    "sg:phone":"+32 14 26 03 59",
    "sg:postcode":"2222",
    "sg:province":"Antwerpen",
    "wof:name":"Landbouwkrediet",
    "wof:placetype":"venue"
},
  "geometry": {"coordinates":[4.7292399406,51.1032218933],"type":"Point"}
}