{
  "type": "Feature",
  "properties": {
    "iso:country":"BE",
    "sg:address":"Kloosterstraat 13",
    "sg:city":"Brecht",
    "sg:orig_category":"Rundveehouders",
    "sg:phone":"+32 3 313 63 61",
    "sg:postcode":"2960",
    "sg:province":"Antwerpen",
    "wof:name":"Vanriel Frans En Jan",
    "wof:placetype":"venue"
},
  "geometry": {"coordinates":[4.5578680038,51.3014183044],"type":"Point"}
}