{
  "type": "Feature",
  "properties": {
    "addr:full":"Avenue De La Reine 367 Bruxelles Bruxelles-Capitale 1020",
    "addr:housenumber":"367",
    "addr:postcode":"1020",
    "addr:street":"Avenue De La Reine",
    "iso:country":"BE",
    "sg:address":"Avenue De La Reine 367",
    "sg:city":"Bruxelles",
    "sg:classifiers":[
        {
            "category":"Wholesale",
            "subcategory":"Plants",
            "type":"Manufacturing & Wholesale Goods"
        }
    ],
    "sg:phone":"+32 2 478 02 10",
    "sg:postcode":"1020",
    "sg:province":"Bruxelles-Capitale",
    "sg:tags":[
        "decoration",
        "flower",
        "-"
    ],
    "wof:name":"Florever",
    "wof:placetype":"venue"
},
  "geometry": {"coordinates":[4.3566308022,50.8778991699],"type":"Point"}
}