{
  "type": "Feature",
  "properties": {
    "iso:country":"BE",
    "sg:address":"Rue Des Mineurs 9-11",
    "sg:city":"Li\u00e8ge 1",
    "sg:classifiers":[
        {
            "category":"Organizations",
            "subcategory":"Community Association",
            "type":"Services"
        }
    ],
    "sg:phone":"+32 4 222 12 46",
    "sg:postcode":"4000",
    "sg:province":"Li\u00e8ge",
    "sg:tags":[
        "cultural"
    ],
    "wof:name":"D'une Certaine Gaite",
    "wof:placetype":"venue"
},
  "geometry": {"coordinates":[5.5763630867,50.6460914612],"type":"Point"}
}