{
  "type": "Feature",
  "properties": {
    "iso:country":"BE",
    "sg:address":"Rue Ferdinand Kinnen 73",
    "sg:city":"Kraainem",
    "sg:classifiers":[
        {
            "category":"Health Services",
            "subcategory":"Health Practitioner",
            "type":"Services"
        }
    ],
    "sg:phone":"+32 2 731 04 44",
    "sg:postcode":"1950",
    "sg:province":"Vlaams-Brabant",
    "sg:tags":[
        "physiotherapist"
    ],
    "wof:name":"Istas Viviane",
    "wof:placetype":"venue"
},
  "geometry": {"coordinates":[4.4704999924,50.8445205688],"type":"Point"}
}