{
  "type": "Feature",
  "properties": {
    "iso:country":"BE",
    "sg:address":"Avenue Georges Benoidt 22",
    "sg:city":"Watermaal-bosvoorde/watermael-boitsfort",
    "sg:orig_category":"Location de logements sociaux",
    "sg:phone":"+32 2 672 33 59",
    "sg:postcode":"1170",
    "sg:province":"Bruxelles-Capitale",
    "wof:name":"Le Logis",
    "wof:placetype":"venue"
},
  "geometry": {"coordinates":[4.4140658379,50.8002891541],"type":"Point"}
}