{
  "type": "Feature",
  "properties": {
    "addr:full":"Waterloose Steenweg 1377 Ukkel/uccle Bruxelles-Capitale 1180",
    "addr:housenumber":"1377",
    "addr:postcode":"1180",
    "addr:street":"Waterloose Steenweg;/",
    "iso:country":"BE",
    "sg:address":"Waterloose Steenweg 1377",
    "sg:city":"Ukkel/uccle",
    "sg:orig_category":"Verlichting and huishoudartikelen",
    "sg:phone":"+32 2 375 51 07",
    "sg:postcode":"1180",
    "sg:province":"Bruxelles-Capitale",
    "wof:name":"Atelier Reflets Abat-jour",
    "wof:placetype":"venue"
},
  "geometry": {"coordinates":[4.3754858971,50.7877426147],"type":"Point"}
}