{
  "type": "Feature",
  "properties": {
    "addr:full":"Henri Maubelstraat 95 Vorst/forest Bruxelles-Capitale 1190",
    "addr:housenumber":"95",
    "addr:postcode":"1190",
    "addr:street":"Henri Maubelstraat;/ Forest",
    "iso:country":"BE",
    "sg:address":"Henri Maubelstraat 95",
    "sg:city":"Vorst/forest",
    "sg:orig_category":"Herstelling and restauratie van meubelen",
    "sg:phone":"+32 2 343 19 43",
    "sg:postcode":"1190",
    "sg:province":"Bruxelles-Capitale",
    "wof:name":"Daniel Lampo",
    "wof:placetype":"venue"
},
  "geometry": {"coordinates":[4.3352499008,50.8112754822],"type":"Point"}
}