{
  "type": "Feature",
  "properties": {
    "iso:country":"BE",
    "sg:address":"Stroomstraat 10",
    "sg:city":"Assenede",
    "sg:orig_category":"Tweedehandsgoederen Verlichting and huishoudartikelen",
    "sg:phone":"+32 9 373 67 14",
    "sg:postcode":"9968",
    "sg:province":"Oost-Vlaanderen",
    "wof:name":"Oxfam Wereldwinkel",
    "wof:placetype":"venue"
},
  "geometry": {"coordinates":[3.6890199184,51.1932144165],"type":"Point"}
}