{
  "type": "Feature",
  "properties": {
    "addr:full":"Vroonstraat 9 Waregem West-Vlaanderen 8792",
    "addr:housenumber":"9",
    "addr:postcode":"8792",
    "addr:street":"Vroonstraat",
    "iso:country":"BE",
    "sg:address":"Vroonstraat 9",
    "sg:city":"Waregem",
    "sg:orig_category":"Software ontwikkeling and ontwerp",
    "sg:phone":"+32 56 70 40 10",
    "sg:postcode":"8792",
    "sg:province":"West-Vlaanderen",
    "wof:name":"Jan Decloedt",
    "wof:placetype":"venue"
},
  "geometry": {"coordinates":[3.3600430489,50.8882980347],"type":"Point"}
}