{
  "type": "Feature",
  "properties": {
    "iso:country":"BE",
    "sg:address":"Chauss\u00e9e De Bruxelles 47",
    "sg:city":"Tournai",
    "sg:classifiers":[
        {
            "category":"Autos & Motor Vehicles",
            "subcategory":"Fuel & Gas Station",
            "type":"Retail Goods"
        }
    ],
    "sg:phone":"+32 69 45 45 99",
    "sg:postcode":"7500",
    "sg:province":"Hainaut",
    "wof:name":"Station Shell",
    "wof:placetype":"venue"
},
  "geometry": {"coordinates":[3.4087851048,50.6050262451],"type":"Point"}
}