{
  "type": "Feature",
  "properties": {
    "addr:full":"Place Nicola\u00ef 54 Ans Li\u00e8ge 4430",
    "addr:housenumber":"54",
    "addr:postcode":"4430",
    "addr:street":"Place Nicolai\u0308",
    "iso:country":"BE",
    "sg:address":"Place Nicola\u00ef 54",
    "sg:city":"Ans",
    "sg:orig_category":"Ice-cream parlours",
    "sg:phone":"+32 4 226 12 31",
    "sg:postcode":"4430",
    "sg:province":"Li\u00e8ge",
    "wof:name":"Jean & Fils Ets",
    "wof:placetype":"venue"
},
  "geometry": {"coordinates":[5.5401058197,50.6529769897],"type":"Point"}
}