{
  "type": "Feature",
  "properties": {
    "addr:full":"Pemenhoek 26 Nieuwpoort West-Vlaanderen 8620",
    "addr:housenumber":"26",
    "addr:postcode":"8620",
    "addr:street":"Pemenhoek",
    "iso:country":"BE",
    "sg:address":"Pemenhoek 26",
    "sg:city":"Nieuwpoort",
    "sg:classifiers":[
        {
            "category":"Banks & Credit Unions",
            "subcategory":"Investment Brokerage",
            "type":"Services"
        }
    ],
    "sg:phone":"+32 58 23 91 25",
    "sg:postcode":"8620",
    "sg:province":"West-Vlaanderen",
    "sg:tags":[
        "rental",
        "-",
        "yacht",
        "boat",
        "pleasure"
    ],
    "wof:name":"Adventure Sailing Tian",
    "wof:placetype":"venue"
},
  "geometry": {"coordinates":[2.7364389896,51.136844635],"type":"Point"}
}