{
  "type": "Feature",
  "properties": {
    "addr:full":"Witvenstraat 71 Stabroek (hoevenen) Antwerpen 2940",
    "addr:housenumber":"71",
    "addr:postcode":"2940",
    "addr:street":"Witvenstraat",
    "iso:country":"BE",
    "sg:address":"Witvenstraat 71",
    "sg:city":"Stabroek (hoevenen)",
    "sg:classifiers":[
        {
            "category":"Home & Garden",
            "subcategory":"Kitchen Supply",
            "type":"Retail Goods"
        }
    ],
    "sg:phone":"+32 3 605 78 80",
    "sg:postcode":"2940",
    "sg:province":"Antwerpen",
    "sg:tags":[
        "-",
        "industrial",
        "installation",
        "equipment"
    ],
    "wof:name":"Professional Technics Nv",
    "wof:placetype":"venue"
},
  "geometry": {"coordinates":[4.3649148941,51.331943512],"type":"Point"}
}