{
  "type": "Feature",
  "properties": {
    "addr:full":"Kortrijksestraat 293 Izegem West-Vlaanderen 8870",
    "addr:housenumber":"293",
    "addr:postcode":"8870",
    "addr:street":"Kortrijksestraat",
    "iso:country":"BE",
    "sg:address":"Kortrijksestraat 293",
    "sg:city":"Izegem",
    "sg:classifiers":[
        {
            "category":"Cafe",
            "type":"Food & Drink"
        }
    ],
    "sg:phone":"+32 51 31 19 85",
    "sg:postcode":"8870",
    "sg:province":"West-Vlaanderen",
    "sg:tags":[
        "caf\u00e9s"
    ],
    "wof:name":"Dario Vanderwee",
    "wof:placetype":"venue"
},
  "geometry": {"coordinates":[3.2204170227,50.9074211121],"type":"Point"}
}