{
  "type": "Feature",
  "properties": {
    "addr:full":"Rue Du Vieux Ti\u00e8ge 6 Herve (grand-rechain) Li\u00e8ge 4650",
    "addr:housenumber":"6",
    "addr:postcode":"4650",
    "addr:street":"Rue Du Vieux Tie\u0300Ge;Grand-Rechain",
    "iso:country":"BE",
    "sg:address":"Rue Du Vieux Ti\u00e8ge 6",
    "sg:city":"Herve (grand-rechain)",
    "sg:classifiers":[
        {
            "category":"Home & Garden",
            "subcategory":"Building Materials",
            "type":"Retail Goods"
        }
    ],
    "sg:phone":"+32 87 33 17 06",
    "sg:postcode":"4650",
    "sg:province":"Li\u00e8ge",
    "sg:tags":[
        "window"
    ],
    "wof:name":"Bozard R",
    "wof:placetype":"venue"
},
  "geometry": {"coordinates":[5.8174548149,50.6114387512],"type":"Point"}
}