{
  "type": "Feature",
  "properties": {
    "addr:full":"Heiendestraat 18 Lokeren Oost-Vlaanderen 9160",
    "addr:housenumber":"18",
    "addr:postcode":"9160",
    "addr:street":"Heiendestraat",
    "iso:country":"BE",
    "sg:address":"Heiendestraat 18",
    "sg:city":"Lokeren",
    "sg:classifiers":[
        {
            "category":"Personal",
            "subcategory":"Beauty Salon",
            "type":"Services"
        }
    ],
    "sg:phone":"+32 9 348 24 30",
    "sg:postcode":"9160",
    "sg:province":"Oost-Vlaanderen",
    "sg:tags":[
        "lady",
        "-",
        "hairdressing"
    ],
    "wof:name":"Gianni's Le Salon",
    "wof:placetype":"venue"
},
  "geometry": {"coordinates":[3.9577410221,51.0856628418],"type":"Point"}
}