{
  "type": "Feature",
  "properties": {
    "addr:full":"Veemarkt 33 Box 1 Mechelen Antwerpen 2800",
    "addr:housenumber":"33;1",
    "addr:postcode":"2800",
    "addr:street":"Veemarkt;Box",
    "iso:country":"BE",
    "sg:address":"Veemarkt 33 Box 1",
    "sg:city":"Mechelen",
    "sg:classifiers":[
        {
            "category":"Banks & Credit Unions",
            "subcategory":"Financial Services",
            "type":"Services"
        }
    ],
    "sg:phone":"+32 15 33 03 50",
    "sg:postcode":"2800",
    "sg:province":"Antwerpen",
    "sg:tags":[
        "loan",
        "mortgage"
    ],
    "wof:name":"Cox H",
    "wof:placetype":"venue"
},
  "geometry": {"coordinates":[4.4838328362,51.0290908813],"type":"Point"}
}