{
  "type": "Feature",
  "properties": {
    "addr:full":"Tombroekstraat 10 Harelbeke West-Vlaanderen 8531",
    "addr:housenumber":"10",
    "addr:postcode":"8531",
    "addr:street":"Tombroekstraat",
    "iso:country":"BE",
    "sg:address":"Tombroekstraat 10",
    "sg:city":"Harelbeke",
    "sg:orig_category":"Producteurs de l\u00e9gumes",
    "sg:phone":"+32 56 66 65 59",
    "sg:postcode":"8531",
    "sg:province":"West-Vlaanderen",
    "wof:name":"Ivan Vannoote",
    "wof:placetype":"venue"
},
  "geometry": {"coordinates":[3.3000929356,50.8977546692],"type":"Point"}
}