{
  "type": "Feature",
  "properties": {
    "addr:full":"Alsembergse Steenweg 993 Ukkel/uccle Bruxelles-Capitale 1180",
    "addr:housenumber":"993",
    "addr:postcode":"1180",
    "addr:street":"Alsembergse Steenweg;/",
    "iso:country":"BE",
    "sg:address":"Alsembergse Steenweg 993",
    "sg:city":"Ukkel/uccle",
    "sg:orig_category":"Kantoormateriaal",
    "sg:phone":"+32 2 332 15 11",
    "sg:postcode":"1180",
    "sg:province":"Bruxelles-Capitale",
    "wof:name":"Forma",
    "wof:placetype":"venue"
},
  "geometry": {"coordinates":[4.3351988792,50.7959938049],"type":"Point"}
}