{
  "type": "Feature",
  "properties": {
    "addr:full":"Daalakker 18 Herentals Antwerpen 2200",
    "addr:housenumber":"18",
    "addr:postcode":"2200",
    "addr:street":"Daalakker",
    "iso:country":"BE",
    "sg:address":"Daalakker 18",
    "sg:city":"Herentals",
    "sg:classifiers":[
        {
            "category":"Building & Trades",
            "subcategory":"Electrical",
            "type":"Services"
        }
    ],
    "sg:phone":"+32 14 22 11 66",
    "sg:postcode":"2200",
    "sg:province":"Antwerpen",
    "sg:tags":[
        "electric",
        "-",
        "housewiring",
        "contractor"
    ],
    "wof:name":"Dlp Studiebureel",
    "wof:placetype":"venue"
},
  "geometry": {"coordinates":[4.8175849915,51.1626472473],"type":"Point"}
}