{
  "type": "Feature",
  "properties": {
    "iso:country":"BE",
    "sg:address":"Turnhoutsebaan 288",
    "sg:city":"Schilde",
    "sg:classifiers":[
        {
            "category":"Building & Trades",
            "subcategory":"Cleaning & Sanitation",
            "type":"Services"
        }
    ],
    "sg:phone":"+32 3 383 35 05",
    "sg:postcode":"2970",
    "sg:province":"Antwerpen",
    "sg:tags":[
        "janitor"
    ],
    "wof:name":"Joma Cleaning",
    "wof:placetype":"venue"
},
  "geometry": {"coordinates":[4.5823168755,51.2402992249],"type":"Point"}
}