{
  "type": "Feature",
  "properties": {
    "addr:full":"Boulevard Des G\u00e9rardchamps 32 Verviers Li\u00e8ge 4800",
    "addr:housenumber":"32",
    "addr:postcode":"4800",
    "addr:street":"Boulevard Des Ge\u0301Rardchamps",
    "iso:country":"BE",
    "sg:address":"Boulevard Des G\u00e9rardchamps 32",
    "sg:city":"Verviers",
    "sg:classifiers":[
        {
            "category":"Building & Trades",
            "subcategory":"Construction",
            "type":"Services"
        }
    ],
    "sg:phone":"+32 87 26 73 54",
    "sg:postcode":"4800",
    "sg:province":"Li\u00e8ge",
    "sg:tags":[
        "glazier"
    ],
    "wof:name":"Vitrerie Couard Sa",
    "wof:placetype":"venue"
},
  "geometry": {"coordinates":[5.8469438553,50.5933456421],"type":"Point"}
}