{
  "type": "Feature",
  "properties": {
    "addr:full":"Rue Saint-m\u00c9dard 13 Jodoigne Brabant Wallon 1370",
    "addr:housenumber":"13",
    "addr:postcode":"1370",
    "addr:street":"Rue Saint-Me\u0301Dard",
    "iso:country":"BE",
    "sg:address":"Rue Saint-m\u00c9dard 13",
    "sg:city":"Jodoigne",
    "sg:orig_category":"Herstelling leer and schoeisel",
    "sg:phone":"+32 10 81 23 18",
    "sg:postcode":"1370",
    "sg:province":"Brabant Wallon",
    "wof:name":"Rombaut Sports",
    "wof:placetype":"venue"
},
  "geometry": {"coordinates":[4.8685889244,50.7228126526],"type":"Point"}
}