{
  "type": "Feature",
  "properties": {
    "addr:full":"Rue D'adzeux 12 Sprimont Li\u00e8ge 4141",
    "addr:housenumber":"12",
    "addr:postcode":"4141",
    "addr:street":"Rue D'Adzeux",
    "iso:country":"BE",
    "sg:address":"Rue D'adzeux 12",
    "sg:city":"Sprimont",
    "sg:classifiers":[
        {
            "category":"Cafe",
            "type":"Food & Drink"
        }
    ],
    "sg:phone":"+32 4 360 98 02",
    "sg:postcode":"4141",
    "sg:province":"Li\u00e8ge",
    "sg:tags":[
        "caf\u00e9s"
    ],
    "wof:name":"Isabelle Etienne",
    "wof:placetype":"venue"
},
  "geometry": {"coordinates":[5.7287378311,50.5203857422],"type":"Point"}
}