{
  "type": "Feature",
  "properties": {
    "addr:full":"C Marechalstraat 3 Beernem West-Vlaanderen 8730",
    "addr:housenumber":"3",
    "addr:postcode":"8730",
    "addr:street":"C Marechalstraat",
    "iso:country":"BE",
    "sg:address":"C Marechalstraat 3",
    "sg:city":"Beernem",
    "sg:classifiers":[
        {
            "category":"Sports & Exercise",
            "subcategory":"Sports Center",
            "type":"Entertainment"
        }
    ],
    "sg:phone":"+32 50 78 92 72",
    "sg:postcode":"8730",
    "sg:province":"West-Vlaanderen",
    "sg:tags":[
        "terrain",
        "hors",
        "de",
        "installation",
        "sportifs"
    ],
    "wof:name":"Gemeentelijk Zwembad",
    "wof:placetype":"venue"
},
  "geometry": {"coordinates":[3.3336141109,51.1397743225],"type":"Point"}
}