{
  "type": "Feature",
  "properties": {
    "addr:full":"Bleukenstraat 4 Nieuwerkerken Limburg 3850",
    "addr:housenumber":"4",
    "addr:postcode":"3850",
    "addr:street":"Bleukenstraat",
    "iso:country":"BE",
    "sg:address":"Bleukenstraat 4",
    "sg:city":"Nieuwerkerken",
    "sg:orig_category":"Sportclubs",
    "sg:phone":"+32 11 58 86 09",
    "sg:postcode":"3850",
    "sg:province":"Limburg",
    "wof:name":"Het Vrije Spel",
    "wof:placetype":"venue"
},
  "geometry": {"coordinates":[5.2019600868,50.8878440857],"type":"Point"}
}