{
  "type": "Feature",
  "properties": {
    "iso:country":"BE",
    "sg:address":"Gr. Van Vlaanderenplein 40",
    "sg:city":"Gent",
    "sg:orig_category":"Biblioth\u00e8ques and archives publiques",
    "sg:phone":"+32 9 266 70 00",
    "sg:postcode":"9000",
    "sg:province":"Oost-Vlaanderen",
    "wof:name":"Openbare Bibliotheek",
    "wof:placetype":"venue"
},
  "geometry": {"coordinates":[3.7311680317,51.0477333069],"type":"Point"}
}