{
  "type": "Feature",
  "properties": {
    "iso:country":"BE",
    "sg:address":"Avenue Du Parc 32",
    "sg:city":"Herve (chaineux)",
    "sg:classifiers":[
        {
            "category":"Professional",
            "type":"Services"
        }
    ],
    "sg:phone":"+32 87 31 38 00",
    "sg:postcode":"4650",
    "sg:province":"Li\u00e8ge",
    "sg:tags":[
        "forwarding",
        "agency"
    ],
    "wof:name":"Atramef",
    "wof:placetype":"venue"
},
  "geometry": {"coordinates":[5.8391771317,50.6252250671],"type":"Point"}
}