{
  "type": "Feature",
  "properties": {
    "addr:full":"Antwerpsestraat 107 Lier Antwerpen 2500",
    "addr:housenumber":"107",
    "addr:postcode":"2500",
    "addr:street":"Antwerpsestraat",
    "iso:country":"BE",
    "sg:address":"Antwerpsestraat 107",
    "sg:city":"Lier",
    "sg:classifiers":[
        {
            "category":"Shopping",
            "subcategory":"Computers & Home Electronics",
            "type":"Retail Goods"
        }
    ],
    "sg:phone":"+32 3 488 37 23",
    "sg:postcode":"2500",
    "sg:province":"Antwerpen",
    "sg:tags":[
        "nec",
        "computerapparatuur",
        "packard",
        "bell"
    ],
    "wof:name":"Eurosys Lier",
    "wof:placetype":"venue"
},
  "geometry": {"coordinates":[4.5660839081,51.134147644],"type":"Point"}
}