{
  "type": "Feature",
  "properties": {
    "addr:full":"Vierhuizen 18 Evergem Oost-Vlaanderen 9940",
    "addr:housenumber":"18",
    "addr:postcode":"9940",
    "addr:street":"Vierhuizen;Oost-Vlaanderen",
    "iso:country":"BE",
    "sg:address":"Vierhuizen 18",
    "sg:city":"Evergem",
    "sg:orig_category":"Rundveehouders",
    "sg:phone":"+32 9 357 36 46",
    "sg:postcode":"9940",
    "sg:province":"Oost-Vlaanderen",
    "wof:name":"Marc Engels",
    "wof:placetype":"venue"
},
  "geometry": {"coordinates":[3.6489388943,51.1666564941],"type":"Point"}
}