{
  "type": "Feature",
  "properties": {
    "addr:full":"Rue D'ocquier 9 Somme-leuze Namur 5377",
    "addr:housenumber":"9",
    "addr:postcode":"5377",
    "addr:street":"Rue D'Ocquier",
    "iso:country":"BE",
    "sg:address":"Rue D'ocquier 9",
    "sg:city":"Somme-leuze",
    "sg:orig_category":"Slagers",
    "sg:phone":"+32 86 34 40 43",
    "sg:postcode":"5377",
    "sg:province":"Namur",
    "wof:name":"Paul Dodet",
    "wof:placetype":"venue"
},
  "geometry": {"coordinates":[5.3755960464,50.3734817505],"type":"Point"}
}