{
  "type": "Feature",
  "properties": {
    "iso:country":"BE",
    "sg:address":"Boechoutsesteenweg 42",
    "sg:city":"Borsbeek",
    "sg:classifiers":[
        {
            "category":"Personal",
            "subcategory":"Beauty Salon",
            "type":"Services"
        }
    ],
    "sg:phone":"+32 3 454 44 95",
    "sg:postcode":"2150",
    "sg:province":"Antwerpen",
    "wof:name":"C.n.c. Belgium",
    "wof:placetype":"venue"
},
  "geometry": {"coordinates":[4.4867620468,51.1826667786],"type":"Point"}
}