{
  "type": "Feature",
  "properties": {
    "iso:country":"BE",
    "sg:address":"Rue De Florence 32",
    "sg:city":"Elsene/ixelles",
    "sg:orig_category":"Diverse voedingsmiddelen Gh",
    "sg:phone":"+32 2 538 23 31",
    "sg:postcode":"1050",
    "sg:province":"Bruxelles-Capitale",
    "wof:name":"Ecomail-bioflor",
    "wof:placetype":"venue"
},
  "geometry": {"coordinates":[4.3591032028,50.8290405273],"type":"Point"}
}