{
  "type": "Feature",
  "properties": {
    "iso:country":"BE",
    "sg:address":"Brugstraat 41",
    "sg:city":"Ardooie",
    "sg:orig_category":"Imprimeries and copyshops",
    "sg:phone":"+32 51 74 50 76",
    "sg:postcode":"8850",
    "sg:province":"West-Vlaanderen",
    "wof:name":"Pmu",
    "wof:placetype":"venue"
},
  "geometry": {"coordinates":[3.2017960548,50.9767570496],"type":"Point"}
}