{
  "type": "Feature",
  "properties": {
    "addr:full":"Brugmannlaan 202 Elsene/ixelles Bruxelles-Capitale 1050",
    "addr:housenumber":"202",
    "addr:postcode":"1050",
    "addr:street":"Brugmannlaan",
    "iso:country":"BE",
    "sg:address":"Brugmannlaan 202",
    "sg:city":"Elsene/ixelles",
    "sg:orig_category":"Antiek",
    "sg:phone":"+32 2 343 50 19",
    "sg:postcode":"1050",
    "sg:province":"Bruxelles-Capitale",
    "wof:name":"Maison Bermann B.",
    "wof:placetype":"venue"
},
  "geometry": {"coordinates":[4.3489818573,50.8149909973],"type":"Point"}
}