{
  "type": "Feature",
  "properties": {
    "iso:country":"BE",
    "sg:address":"Rot 65",
    "sg:city":"Holsbeek (nieuwrode)",
    "sg:classifiers":[
        {
            "category":"Arts & Performance",
            "subcategory":"Music",
            "type":"Entertainment"
        }
    ],
    "sg:phone":"+32 475 40 64 98",
    "sg:postcode":"3221",
    "sg:province":"Vlaams-Brabant",
    "sg:tags":[
        "disc-jockeys"
    ],
    "wof:name":"High Voltage Discobar",
    "wof:placetype":"venue"
},
  "geometry": {"coordinates":[4.8165621758,50.9567947388],"type":"Point"}
}