{
  "type": "Feature",
  "properties": {
    "iso:country":"BE",
    "sg:address":"Onze-lieve-vrouwestraat 143",
    "sg:city":"Mechelen",
    "sg:classifiers":[
        {
            "category":"Shopping",
            "subcategory":"Clothing, Apparel, & Fashions",
            "type":"Retail Goods"
        }
    ],
    "sg:phone":"+32 15 43 02 42",
    "sg:postcode":"2800",
    "sg:province":"Antwerpen",
    "sg:tags":[
        "ondergoed",
        "lingerie"
    ],
    "wof:name":"Huis Profiterolles",
    "wof:placetype":"venue"
},
  "geometry": {"coordinates":[4.4820652008,51.0225410461],"type":"Point"}
}