{
  "type": "Feature",
  "properties": {
    "addr:full":"Frans Geldersstraat 12 Vilvoorde Vlaams-Brabant 1800",
    "addr:housenumber":"12",
    "addr:postcode":"1800",
    "addr:street":"Frans Geldersstraat",
    "iso:country":"BE",
    "sg:address":"Frans Geldersstraat 12",
    "sg:city":"Vilvoorde",
    "sg:orig_category":"Activit\u00e9s d\u00b4action sociale sans h\u00e9bergement. Biens d'occasion",
    "sg:phone":"+32 15 62 39 70",
    "sg:postcode":"1800",
    "sg:province":"Vlaams-Brabant",
    "wof:name":"'t Winkelke",
    "wof:placetype":"venue"
},
  "geometry": {"coordinates":[4.4234838486,50.9296684265],"type":"Point"}
}