{
  "type": "Feature",
  "properties": {
    "addr:full":"Edingseweg 535 Geraardsbergen Oost-Vlaanderen 9500",
    "addr:housenumber":"535",
    "addr:postcode":"9500",
    "addr:street":"Edingseweg",
    "iso:country":"BE",
    "sg:address":"Edingseweg 535",
    "sg:city":"Geraardsbergen",
    "sg:classifiers":[
        {
            "category":"Cafe",
            "type":"Food & Drink"
        }
    ],
    "sg:phone":"+32 54 58 95 35",
    "sg:postcode":"9500",
    "sg:province":"Oost-Vlaanderen",
    "sg:tags":[
        "caf\u00e9s"
    ],
    "wof:name":"Caf\u00c9 Het Schepershof",
    "wof:placetype":"venue"
},
  "geometry": {"coordinates":[3.8944499493,50.7723007202],"type":"Point"}
}