{
  "type": "Feature",
  "properties": {
    "addr:full":"Rue Victor Hugo 72 Bruxelles (schaerbeek) Bruxelles-Capitale 1030",
    "addr:housenumber":"72",
    "addr:postcode":"1030",
    "addr:street":"Rue Victor Hugo",
    "iso:country":"BE",
    "sg:address":"Rue Victor Hugo 72",
    "sg:city":"Bruxelles (schaerbeek)",
    "sg:classifiers":[
        {
            "category":"Cafe",
            "type":"Food & Drink"
        }
    ],
    "sg:phone":"+32 2 742 01 28",
    "sg:postcode":"1030",
    "sg:province":"Bruxelles-Capitale",
    "sg:tags":[
        "snack-bars"
    ],
    "wof:name":"Babylone (le)",
    "wof:placetype":"venue"
},
  "geometry": {"coordinates":[4.3927922249,50.8515663147],"type":"Point"}
}