{
  "type": "Feature",
  "properties": {
    "iso:country":"BE",
    "sg:address":"Rue De La Station 195",
    "sg:city":"Jemeppe-sur-sambre",
    "sg:orig_category":"Jeux de hasard",
    "sg:phone":"+32 71 78 84 26",
    "sg:postcode":"5190",
    "sg:province":"Namur",
    "wof:name":"Ladbroke",
    "wof:placetype":"venue"
},
  "geometry": {"coordinates":[4.6952700615,50.4536094666],"type":"Point"}
}