{
  "type": "Feature",
  "properties": {
    "iso:country":"BE",
    "sg:address":"Patershoek 6",
    "sg:city":"Sint-niklaas",
    "sg:classifiers":[
        {
            "category":"Restaurant",
            "type":"Food & Drink"
        }
    ],
    "sg:phone":"+32 3 777 31 38",
    "sg:postcode":"9111",
    "sg:province":"Oost-Vlaanderen",
    "wof:name":"Rozenhofke",
    "wof:placetype":"venue"
},
  "geometry": {"coordinates":[4.1116681099,51.1758117676],"type":"Point"}
}