{
  "type": "Feature",
  "properties": {
    "addr:full":"Rue Jean Jaur\u00c8s 281 Charleroi Hainaut 6020",
    "addr:housenumber":"281",
    "addr:postcode":"6020",
    "addr:street":"Rue Jean Jaure\u0300S;Hainaut",
    "iso:country":"BE",
    "sg:address":"Rue Jean Jaur\u00c8s 281",
    "sg:city":"Charleroi",
    "sg:orig_category":"Dierenartsen",
    "sg:phone":"+32 71 30 42 76",
    "sg:postcode":"6020",
    "sg:province":"Hainaut",
    "wof:name":"Philippe Gruselle",
    "wof:placetype":"venue"
},
  "geometry": {"coordinates":[4.4256868362,50.422164917],"type":"Point"}
}