{
  "type": "Feature",
  "properties": {
    "iso:country":"BE",
    "sg:address":"Kawaterstraat 12",
    "sg:city":"Liedekerke",
    "sg:classifiers":[
        {
            "category":"Arena",
            "subcategory":"Sports Club",
            "type":"Entertainment"
        }
    ],
    "sg:phone":"+32 53 68 23 19",
    "sg:postcode":"1770",
    "sg:province":"Vlaams-Brabant",
    "sg:tags":[
        "de"
    ],
    "wof:name":"V.c. Daatmet Liedekerke",
    "wof:placetype":"venue"
},
  "geometry": {"coordinates":[4.0915908813,50.8777923584],"type":"Point"}
}