{
  "type": "Feature",
  "properties": {
    "addr:full":"Veerstraat 18 Rumst Antwerpen 2840",
    "addr:housenumber":"18",
    "addr:postcode":"2840",
    "addr:street":"Veerstraat",
    "iso:country":"BE",
    "sg:address":"Veerstraat 18",
    "sg:city":"Rumst",
    "sg:classifiers":[
        {
            "category":"Personal",
            "subcategory":"Nail Salon",
            "type":"Services"
        }
    ],
    "sg:phone":"+32 3 844 37 12",
    "sg:postcode":"2840",
    "sg:province":"Antwerpen",
    "sg:tags":[
        "pedicure"
    ],
    "wof:name":"Vandenbroeck K",
    "wof:placetype":"venue"
},
  "geometry": {"coordinates":[4.4232311249,51.0770263672],"type":"Point"}
}