{
  "type": "Feature",
  "properties": {
    "addr:full":"Miksebaan 77 Brasschaat Antwerpen 2930",
    "addr:housenumber":"77",
    "addr:postcode":"2930",
    "addr:street":"Miksebaan",
    "iso:country":"BE",
    "sg:address":"Miksebaan 77",
    "sg:city":"Brasschaat",
    "sg:classifiers":[
        {
            "category":"Bars & Pubs",
            "type":"Food & Drink"
        }
    ],
    "sg:phone":"+32 3 653 00 01",
    "sg:postcode":"2930",
    "sg:province":"Antwerpen",
    "wof:name":"Hovenierke ('t)",
    "wof:placetype":"venue"
},
  "geometry": {"coordinates":[4.4985442162,51.2901496887],"type":"Point"}
}