{
  "type": "Feature",
  "properties": {
    "addr:full":"Waregemstraat 6 Deerlijk West-Vlaanderen 8540",
    "addr:housenumber":"6",
    "addr:postcode":"8540",
    "addr:street":"Waregemstraat",
    "iso:country":"BE",
    "sg:address":"Waregemstraat 6",
    "sg:city":"Deerlijk",
    "sg:classifiers":[
        {
            "category":"Personal",
            "subcategory":"Beauty Salon",
            "type":"Services"
        }
    ],
    "sg:phone":"+32 56 70 38 42",
    "sg:postcode":"8540",
    "sg:province":"West-Vlaanderen",
    "sg:tags":[
        "de",
        "coiffure"
    ],
    "wof:name":"Coiffure Kristien",
    "wof:placetype":"venue"
},
  "geometry": {"coordinates":[3.3609380722,50.8545761108],"type":"Point"}
}