{
  "type": "Feature",
  "properties": {
    "iso:country":"BE",
    "sg:address":"Rue Fran\u00c7ois-hittelet 156b2",
    "sg:city":"Jemeppe-sur-sambre",
    "sg:orig_category":"Afval and schroot Gh",
    "sg:phone":"+32 71 75 00 80",
    "sg:postcode":"5190",
    "sg:province":"Namur",
    "wof:name":"Sobeca International",
    "wof:placetype":"venue"
},
  "geometry": {"coordinates":[4.6641540527,50.4609260559],"type":"Point"}
}