{
  "type": "Feature",
  "properties": {
    "addr:full":"Rue F\u00e9tis 18 Bruxelles (etterbeek) Bruxelles-Capitale 1040",
    "addr:housenumber":"18",
    "addr:postcode":"1040",
    "addr:street":"Rue Fe\u0301Tis",
    "iso:country":"BE",
    "sg:address":"Rue F\u00e9tis 18",
    "sg:city":"Bruxelles (etterbeek)",
    "sg:classifiers":[
        {
            "category":"Health Services",
            "subcategory":"Health Practitioner",
            "type":"Services"
        }
    ],
    "sg:phone":"+32 2 649 64 65",
    "sg:postcode":"1040",
    "sg:province":"Bruxelles-Capitale",
    "sg:tags":[
        "physiotherapist"
    ],
    "wof:name":"Cardon F",
    "wof:placetype":"venue"
},
  "geometry": {"coordinates":[4.3864331245,50.8335952759],"type":"Point"}
}