{
  "type": "Feature",
  "properties": {
    "iso:country":"BE",
    "sg:address":"Noordweststraat 6",
    "sg:city":"Lo-reninge",
    "sg:orig_category":"Eleveurs de bovins",
    "sg:phone":"+32 51 54 59 57",
    "sg:postcode":"8647",
    "sg:province":"West-Vlaanderen",
    "wof:name":"Geert Van Kerschaver",
    "wof:placetype":"venue"
},
  "geometry": {"coordinates":[2.8077459335,50.9488258362],"type":"Point"}
}