{
  "type": "Feature",
  "properties": {
    "iso:country":"BE",
    "sg:address":"Rue De Neufchateau 88",
    "sg:city":"Arlon",
    "sg:orig_category":"Kapsalons",
    "sg:phone":"+32 63 22 18 28",
    "sg:postcode":"6700",
    "sg:province":"Luxembourg",
    "wof:name":"Coiffure Eden",
    "wof:placetype":"venue"
},
  "geometry": {"coordinates":[5.8041391373,49.6854171753],"type":"Point"}
}