{
  "type": "Feature",
  "properties": {
    "addr:full":"Rue De L'aube 15 Qu\u00e9vy (blaregnies) Hainaut 7040",
    "addr:housenumber":"15",
    "addr:postcode":"7040",
    "addr:street":"Rue De L'Aube;Blaregnies Hainaut",
    "iso:country":"BE",
    "sg:address":"Rue De L'aube 15",
    "sg:city":"Qu\u00e9vy (blaregnies)",
    "sg:classifiers":[
        {
            "category":"Real Estate",
            "subcategory":"Architect",
            "type":"Services"
        }
    ],
    "sg:phone":"+32 65 31 40 37",
    "sg:postcode":"7040",
    "sg:province":"Hainaut",
    "wof:name":"Giovannelli V",
    "wof:placetype":"venue"
},
  "geometry": {"coordinates":[3.9075319767,50.3581542969],"type":"Point"}
}