{
  "type": "Feature",
  "properties": {
    "addr:full":"Altenberger Strasse 42 Kelmis/la Calamine Li\u00e8ge 4728",
    "addr:housenumber":"42",
    "addr:postcode":"4728",
    "addr:street":"Altenberger Strasse",
    "iso:country":"BE",
    "sg:address":"Altenberger Strasse 42",
    "sg:city":"Kelmis/la Calamine",
    "sg:orig_category":"Boekhouders",
    "sg:phone":"+32 87 65 96 27",
    "sg:postcode":"4728",
    "sg:province":"Li\u00e8ge",
    "wof:name":"J. Meessen",
    "wof:placetype":"venue"
},
  "geometry": {"coordinates":[6.021876812,50.7108001709],"type":"Point"}
}