{
  "type": "Feature",
  "properties": {
    "iso:country":"BE",
    "sg:address":"Rue Taravis\u00c9e 2",
    "sg:city":"Gembloux",
    "sg:orig_category":"Editeurs de journaux. Editeurs de revues and p\u00e9riodiques",
    "sg:phone":"+32 81 64 03 11",
    "sg:postcode":"5031",
    "sg:province":"Namur",
    "wof:name":"Edit.travailler Le Social",
    "wof:placetype":"venue"
},
  "geometry": {"coordinates":[4.7688560486,50.5917434692],"type":"Point"}
}