{
  "type": "Feature",
  "properties": {
    "iso:country":"BE",
    "sg:address":"Avenue De La Couronne 41b18",
    "sg:city":"Elsene/ixelles",
    "sg:orig_category":"M\u00e9decins and sp\u00e9cialistes",
    "sg:phone":"+32 2 649 13 48",
    "sg:postcode":"1050",
    "sg:province":"Bruxelles-Capitale",
    "wof:name":"Philippe Cauwel",
    "wof:placetype":"venue"
},
  "geometry": {"coordinates":[4.3775548935,50.8306655884],"type":"Point"}
}