{
  "type": "Feature",
  "properties": {
    "iso:country":"BE",
    "sg:address":"Eburonenstraat 10",
    "sg:city":"Tongeren",
    "sg:classifiers":[
        {
            "category":"Personal",
            "subcategory":"Beauty Salon",
            "type":"Services"
        }
    ],
    "sg:phone":"+32 12 23 31 87",
    "sg:postcode":"3700",
    "sg:province":"Limburg",
    "sg:tags":[
        "de",
        "coiffure"
    ],
    "wof:name":"Coiffure Paula",
    "wof:placetype":"venue"
},
  "geometry": {"coordinates":[5.4711718559,50.7864646912],"type":"Point"}
}