{
  "type": "Feature",
  "properties": {
    "addr:full":"Rue De L'etang Derbaix 185 Mons Hainaut 7033",
    "addr:housenumber":"185",
    "addr:postcode":"7033",
    "addr:street":"Rue De L'Etang Derbaix;Hainaut",
    "iso:country":"BE",
    "sg:address":"Rue De L'etang Derbaix 185",
    "sg:city":"Mons",
    "sg:orig_category":"Ordinateurs and \u00e9quipement informatique",
    "sg:phone":"+32 65 33 53 52",
    "sg:postcode":"7033",
    "sg:province":"Hainaut",
    "wof:name":"Italdata",
    "wof:placetype":"venue"
},
  "geometry": {"coordinates":[3.9178259373,50.4403762817],"type":"Point"}
}