{
  "type": "Feature",
  "properties": {
    "addr:full":"Astridlaan 103 Nieuwpoort West-Vlaanderen 8620",
    "addr:housenumber":"103",
    "addr:postcode":"8620",
    "addr:street":"Astridlaan",
    "iso:country":"BE",
    "sg:address":"Astridlaan 103",
    "sg:city":"Nieuwpoort",
    "sg:orig_category":"Rusthuizen and serviceflats",
    "sg:phone":"+32 58 22 38 10",
    "sg:postcode":"8620",
    "sg:province":"West-Vlaanderen",
    "wof:name":"Rusthuis De Zathe",
    "wof:placetype":"venue"
},
  "geometry": {"coordinates":[2.7478311062,51.1281433105],"type":"Point"}
}