{
  "type": "Feature",
  "properties": {
    "addr:full":"Schotensteenweg 23 Brecht Antwerpen 2960",
    "addr:housenumber":"23",
    "addr:postcode":"2960",
    "addr:street":"Schotensteenweg",
    "iso:country":"BE",
    "sg:address":"Schotensteenweg 23",
    "sg:city":"Brecht",
    "sg:orig_category":"Rundveehouders",
    "sg:phone":"+32 3 313 89 13",
    "sg:postcode":"2960",
    "sg:province":"Antwerpen",
    "wof:name":"Bart Floren",
    "wof:placetype":"venue"
},
  "geometry": {"coordinates":[4.6155500412,51.3359107971],"type":"Point"}
}