{
  "type": "Feature",
  "properties": {
    "addr:full":"Rue De La Bruy\u00c8re 11 Jodoigne Brabant Wallon 1370",
    "addr:housenumber":"11",
    "addr:postcode":"1370",
    "addr:street":"Rue De La Bruye\u0300Re",
    "iso:country":"BE",
    "sg:address":"Rue De La Bruy\u00c8re 11",
    "sg:city":"Jodoigne",
    "sg:orig_category":"Banken and kredietinstellingen",
    "sg:phone":"+32 10 81 35 16",
    "sg:postcode":"1370",
    "sg:province":"Brabant Wallon",
    "wof:name":"Fortis",
    "wof:placetype":"venue"
},
  "geometry": {"coordinates":[4.8688511848,50.7245483398],"type":"Point"}
}