{
  "type": "Feature",
  "properties": {
    "addr:full":"Hoeksken 9 Evergem Oost-Vlaanderen 9940",
    "addr:housenumber":"9",
    "addr:postcode":"9940",
    "addr:street":"Hoeksken;Oost-Vlaanderen",
    "iso:country":"BE",
    "sg:address":"Hoeksken 9",
    "sg:city":"Evergem",
    "sg:orig_category":"Diverse kredietdiensten",
    "sg:postcode":"9940",
    "sg:province":"Oost-Vlaanderen",
    "wof:name":"Bancontact-mister Cash",
    "wof:placetype":"venue"
},
  "geometry": {"coordinates":[3.7067298889,51.110080719],"type":"Point"}
}