{
  "type": "Feature",
  "properties": {
    "iso:country":"BE",
    "sg:address":"Kattestraat 67",
    "sg:city":"Aalst",
    "sg:classifiers":[
        {
            "category":"Bakery",
            "type":"Food & Drink"
        }
    ],
    "sg:phone":"+32 53 21 50 90",
    "sg:postcode":"9300",
    "sg:province":"Oost-Vlaanderen",
    "sg:tags":[
        "cake",
        "product",
        "related",
        "bread"
    ],
    "wof:name":"Malpertuus Bvba",
    "wof:placetype":"venue"
},
  "geometry": {"coordinates":[4.036550045,50.9404602051],"type":"Point"}
}