{
  "type": "Feature",
  "properties": {
    "addr:full":"Rue Du Plavitout 135 Mouscron Hainaut 7700",
    "addr:housenumber":"135",
    "addr:postcode":"7700",
    "addr:street":"Rue Du Plavitout",
    "iso:country":"BE",
    "sg:address":"Rue Du Plavitout 135",
    "sg:city":"Mouscron",
    "sg:classifiers":[
        {
            "category":"Professional",
            "type":"Services"
        }
    ],
    "sg:phone":"+32 4 340 55 82",
    "sg:postcode":"7700",
    "sg:province":"Hainaut",
    "sg:tags":[
        "transport"
    ],
    "wof:name":"Transports Mosans S.p.r.l.",
    "wof:placetype":"venue"
},
  "geometry": {"coordinates":[5.6046648026,50.6188240051],"type":"Point"}
}