{
  "type": "Feature",
  "properties": {
    "addr:full":"Stationsstraat 148 Lommel Limburg 3920",
    "addr:housenumber":"148",
    "addr:postcode":"3920",
    "addr:street":"Stationsstraat",
    "iso:country":"BE",
    "sg:address":"Stationsstraat 148",
    "sg:city":"Lommel",
    "sg:classifiers":[
        {
            "category":"Utilities",
            "subcategory":"Fuel Oil & Lpg",
            "type":"Services"
        }
    ],
    "sg:phone":"+32 11 54 40 75",
    "sg:postcode":"3920",
    "sg:province":"Limburg",
    "wof:name":"Brandstoffen Van Duffel",
    "wof:placetype":"venue"
},
  "geometry": {"coordinates":[5.3135180473,51.2204742432],"type":"Point"}
}