{
  "type": "Feature",
  "properties": {
    "addr:full":"Rue P.fluche 59/27 Verviers Li\u00e8ge 4800",
    "addr:housenumber":"59 / 27",
    "addr:postcode":"4800",
    "addr:street":"Rue P.Fluche",
    "iso:country":"BE",
    "sg:address":"Rue P.fluche 59/27",
    "sg:city":"Verviers",
    "sg:classifiers":[
        {
            "category":"Arena",
            "subcategory":"Sports Club",
            "type":"Entertainment"
        }
    ],
    "sg:phone":"+32 87 22 65 25",
    "sg:postcode":"4800",
    "sg:province":"Li\u00e8ge",
    "sg:tags":[
        "de"
    ],
    "wof:name":"V\u00c9lo Club Ardennes",
    "wof:placetype":"venue"
},
  "geometry": {"coordinates":[5.8688287735,50.5876693726],"type":"Point"}
}