{
  "type": "Feature",
  "properties": {
    "iso:country":"BE",
    "sg:address":"L\u00c9on Theodorstraat 6",
    "sg:city":"Jette",
    "sg:orig_category":"Brood, gebak and snoepgoed Dranken Plaatsen van vloer- and muurbekleding Schilders Verlichting and h",
    "sg:phone":"+32 2 427 46 35",
    "sg:postcode":"1090",
    "sg:province":"Bruxelles-Capitale",
    "wof:name":"Multi Need",
    "wof:placetype":"venue"
},
  "geometry": {"coordinates":[4.325630188,50.873500824],"type":"Point"}
}