{
  "type": "Feature",
  "properties": {
    "addr:full":"Velpenstraat 39 Halen Limburg 3545",
    "addr:housenumber":"39",
    "addr:postcode":"3545",
    "addr:street":"Velpenstraat",
    "iso:country":"BE",
    "sg:address":"Velpenstraat 39",
    "sg:city":"Halen",
    "sg:classifiers":[
        {
            "category":"Retail",
            "subcategory":"Auto Rental",
            "type":"Services"
        }
    ],
    "sg:phone":"+32 13 46 11 26",
    "sg:postcode":"3545",
    "sg:province":"Limburg",
    "sg:tags":[
        "-",
        "motorbike"
    ],
    "wof:name":"Trike Center Belgium",
    "wof:placetype":"venue"
},
  "geometry": {"coordinates":[5.1016850471,50.929851532],"type":"Point"}
}