{
  "type": "Feature",
  "properties": {
    "addr:full":"De Waerde 1032 Zonhoven Limburg 3520",
    "addr:postcode":"1032 zonhoven;3520",
    "iso:country":"BE",
    "sg:address":"De Waerde 1032",
    "sg:city":"Zonhoven",
    "sg:orig_category":"Travaux d\u00b4installation divers. Lampes and appareils \u00e9lectriques Fab. Installation \u00e9lectrique industr",
    "sg:phone":"+32 11 81 92 92",
    "sg:postcode":"3520",
    "sg:province":"Limburg",
    "wof:name":"E.l. Systems",
    "wof:placetype":"venue"
},
  "geometry": {"coordinates":[5.3844108582,50.9980201721],"type":"Point"}
}