{
  "type": "Feature",
  "properties": {
    "addr:full":"Grand Rue 12 Mouscron Hainaut 7700",
    "addr:housenumber":"12",
    "addr:postcode":"7700",
    "addr:street":"Grand Rue",
    "iso:country":"BE",
    "sg:address":"Grand Rue 12",
    "sg:city":"Mouscron",
    "sg:classifiers":[
        {
            "category":"Shopping",
            "subcategory":"Jewelry",
            "type":"Retail Goods"
        }
    ],
    "sg:phone":"+32 56 33 23 97",
    "sg:postcode":"7700",
    "sg:province":"Hainaut",
    "sg:tags":[
        "jeweller",
        "-"
    ],
    "wof:name":"Mullebrouck B",
    "wof:placetype":"venue"
},
  "geometry": {"coordinates":[3.1970870495,50.7284965515],"type":"Point"}
}