{
  "type": "Feature",
  "properties": {
    "addr:full":"Rue Marie Joyle 2 Bergen Hainaut 7021",
    "addr:housenumber":"2",
    "addr:postcode":"7021",
    "addr:street":"Rue Marie Joyle",
    "iso:country":"BE",
    "sg:address":"Rue Marie Joyle 2",
    "sg:city":"Bergen",
    "sg:orig_category":"Herstellingen and onderhoud aan huis voor voertuigen Herstellingen and onderhoud van auto's Metaalaf",
    "sg:phone":"+32 65 87 20 40",
    "sg:postcode":"7021",
    "sg:province":"Hainaut",
    "wof:name":"Autovel Garage",
    "wof:placetype":"venue"
},
  "geometry": {"coordinates":[4.0456829071,50.4640655518],"type":"Point"}
}