{
  "type": "Feature",
  "properties": {
    "addr:full":"Meulebekestraat 107 Pittem West-Vlaanderen 8740",
    "addr:housenumber":"107",
    "addr:postcode":"8740",
    "addr:street":"Meulebekestraat",
    "iso:country":"BE",
    "sg:address":"Meulebekestraat 107",
    "sg:city":"Pittem",
    "sg:orig_category":"Antiek",
    "sg:phone":"+32 51 46 74 13",
    "sg:postcode":"8740",
    "sg:province":"West-Vlaanderen",
    "wof:name":"Fa. De Krieke",
    "wof:placetype":"venue"
},
  "geometry": {"coordinates":[3.2719130516,50.9755325317],"type":"Point"}
}