{
  "type": "Feature",
  "properties": {
    "addr:full":"Dijk 54 Zele Oost-Vlaanderen 9240",
    "addr:housenumber":"54",
    "addr:postcode":"9240",
    "addr:street":"Dijk",
    "iso:country":"BE",
    "sg:address":"Dijk 54",
    "sg:city":"Zele",
    "sg:classifiers":[
        {
            "category":"Bars & Pubs",
            "type":"Food & Drink"
        }
    ],
    "sg:phone":"+32 52 44 69 19",
    "sg:postcode":"9240",
    "sg:province":"Oost-Vlaanderen",
    "sg:tags":[
        "tavern"
    ],
    "wof:name":"Den Anker Nv",
    "wof:placetype":"venue"
},
  "geometry": {"coordinates":[4.0625948906,51.0501022339],"type":"Point"}
}