{
  "type": "Feature",
  "properties": {
    "addr:full":"Rue Du Christ 8 Moeskroen/mouscron Hainaut 7700",
    "addr:housenumber":"8",
    "addr:postcode":"7700",
    "addr:street":"Rue Du Christ",
    "iso:country":"BE",
    "sg:address":"Rue Du Christ 8",
    "sg:city":"Moeskroen/mouscron",
    "sg:orig_category":"Agences de voyages",
    "sg:phone":"+32 56 33 70 71",
    "sg:postcode":"7700",
    "sg:province":"Hainaut",
    "wof:name":"C.a.d. Voyages",
    "wof:placetype":"venue"
},
  "geometry": {"coordinates":[3.2323200703,50.7400932312],"type":"Point"}
}