{
  "type": "Feature",
  "properties": {
    "iso:country":"BE",
    "sg:address":"Dorenstraat 10",
    "sg:city":"Aarschot",
    "sg:orig_category":"Installation de menuiserie m\u00e9tallique. Installation de menuiserie en bois and plastique",
    "sg:phone":"+32 16 56 00 19",
    "sg:postcode":"3200",
    "sg:province":"Vlaams-Brabant",
    "wof:name":"Intermon",
    "wof:placetype":"venue"
},
  "geometry": {"coordinates":[4.8506240845,50.9904518127],"type":"Point"}
}