{
  "type": "Feature",
  "properties": {
    "addr:full":"Generaal Jacqueslaan 59 Elsene/ixelles Bruxelles-Capitale 1050",
    "addr:housenumber":"59",
    "addr:postcode":"1050",
    "addr:street":"Generaal Jacqueslaan",
    "iso:country":"BE",
    "sg:address":"Generaal Jacqueslaan 59",
    "sg:city":"Elsene/ixelles",
    "sg:orig_category":"Boekhouders",
    "sg:phone":"+32 2 647 86 20",
    "sg:postcode":"1050",
    "sg:province":"Bruxelles-Capitale",
    "wof:name":"Vincent Dupont",
    "wof:placetype":"venue"
},
  "geometry": {"coordinates":[4.3804221153,50.8188323975],"type":"Point"}
}