{
  "type": "Feature",
  "properties": {
    "iso:country":"BE",
    "sg:address":"Rue De La Cour 21",
    "sg:city":"Thuin",
    "sg:orig_category":"Eleveurs de bovins",
    "sg:phone":"+32 71 53 42 67",
    "sg:postcode":"6536",
    "sg:province":"Hainaut",
    "wof:name":"Julien Van Nieuwenhuyse",
    "wof:placetype":"venue"
},
  "geometry": {"coordinates":[4.3253350258,50.2954521179],"type":"Point"}
}