{
  "type": "Feature",
  "properties": {
    "iso:country":"BE",
    "sg:address":"Rue Stanislas Legrelle 42",
    "sg:city":"Bruxelles (jette)",
    "sg:orig_category":"Solar protection - Inside",
    "sg:phone":"+32 2 426 49 00",
    "sg:postcode":"1090",
    "sg:province":"Bruxelles-Capitale",
    "wof:name":"Entreprise Rolling Store Sprl",
    "wof:placetype":"venue"
},
  "geometry": {"coordinates":[4.3224048615,50.8762931824],"type":"Point"}
}