{
  "type": "Feature",
  "properties": {
    "addr:full":"Avenue Des Feux-follets 79 Mouscron Hainaut 7700",
    "addr:housenumber":"79",
    "addr:postcode":"7700",
    "addr:street":"Avenue Des Feux-Follets",
    "iso:country":"BE",
    "sg:address":"Avenue Des Feux-follets 79",
    "sg:city":"Mouscron",
    "sg:orig_category":"Transports terrestres de voyageurs. Auto-\u00e9coles",
    "sg:phone":"+32 56 33 25 07",
    "sg:postcode":"7700",
    "sg:province":"Hainaut",
    "wof:name":"Autocars Belpeer",
    "wof:placetype":"venue"
},
  "geometry": {"coordinates":[3.2019619942,50.7508544922],"type":"Point"}
}