{
  "type": "Feature",
  "properties": {
    "addr:full":"Lokerenbaan 98a Zele Oost-Vlaanderen 9240",
    "addr:housenumber":"98a",
    "addr:postcode":"9240",
    "addr:street":"Lokerenbaan",
    "iso:country":"BE",
    "sg:address":"Lokerenbaan 98a",
    "sg:city":"Zele",
    "sg:classifiers":[
        {
            "category":"Utilities",
            "subcategory":"Mobile Phone",
            "type":"Services"
        }
    ],
    "sg:postcode":"9240",
    "sg:province":"Oost-Vlaanderen",
    "sg:tags":[
        "answering",
        "telephone"
    ],
    "wof:name":"Adutel Bvba",
    "wof:placetype":"venue"
},
  "geometry": {"coordinates":[4.0407562256,51.0750617981],"type":"Point"}
}