{
  "type": "Feature",
  "properties": {
    "addr:full":"Rue Gustave Taillard 2 Herve Li\u00e8ge 4650",
    "addr:housenumber":"2",
    "addr:postcode":"4650",
    "addr:street":"Rue Gustave Taillard",
    "iso:country":"BE",
    "sg:address":"Rue Gustave Taillard 2",
    "sg:city":"Herve",
    "sg:classifiers":[
        {
            "category":"Fast Food",
            "type":"Food & Drink"
        }
    ],
    "sg:phone":"+32 87 66 23 13",
    "sg:postcode":"4650",
    "sg:province":"Li\u00e8ge",
    "sg:tags":[
        "\u00c0",
        "emporter",
        "restaurants"
    ],
    "wof:name":"Friterie Boule Et Frites",
    "wof:placetype":"venue"
},
  "geometry": {"coordinates":[5.7940688133,50.6412811279],"type":"Point"}
}