{
  "type": "Feature",
  "properties": {
    "iso:country":"BE",
    "sg:address":"Gravenstraat 26",
    "sg:city":"Holsbeek (kortrijk-dutsel)",
    "sg:classifiers":[
        {
            "category":"Utilities",
            "subcategory":"Fuel Oil & Lpg",
            "type":"Services"
        }
    ],
    "sg:phone":"+32 16 62 11 19",
    "sg:postcode":"3220",
    "sg:province":"Vlaams-Brabant",
    "wof:name":"Smets Arthur & Zoon Nv",
    "wof:placetype":"venue"
},
  "geometry": {"coordinates":[4.8166399002,50.9314002991],"type":"Point"}
}