{
  "type": "Feature",
  "properties": {
    "iso:country":"BE",
    "sg:address":"Belgi\u00eblei 7",
    "sg:city":"Antwerpen",
    "sg:classifiers":[
        {
            "category":"Real Estate",
            "subcategory":"Real Estate Services",
            "type":"Services"
        }
    ],
    "sg:phone":"+32 3 218 97 00",
    "sg:postcode":"2018",
    "sg:province":"Antwerpen",
    "wof:name":"City Center Invest Bvba",
    "wof:placetype":"venue"
},
  "geometry": {"coordinates":[4.4226169586,51.2086372375],"type":"Point"}
}