{
  "type": "Feature",
  "properties": {
    "iso:country":"BE",
    "sg:address":"Rue Du Coq 2be",
    "sg:city":"Lasne",
    "sg:orig_category":"Meubelzaken, woning- and keukeninrichting",
    "sg:phone":"+32 2 351 00 13",
    "sg:postcode":"1380",
    "sg:province":"Brabant Wallon",
    "wof:name":"Le Grenier Du Coq",
    "wof:placetype":"venue"
},
  "geometry": {"coordinates":[4.483235836,50.6850166321],"type":"Point"}
}