{
  "type": "Feature",
  "properties": {
    "addr:full":"'s Herenbaan 116 Rumst Antwerpen 2840",
    "addr:housenumber":"116",
    "addr:postcode":"2840",
    "addr:street":"' S Herenbaan",
    "iso:country":"BE",
    "sg:address":"'s Herenbaan 116",
    "sg:city":"Rumst",
    "sg:orig_category":"V\u00e9t\u00e9rinaires",
    "sg:phone":"+32 3 844 44 51",
    "sg:postcode":"2840",
    "sg:province":"Antwerpen",
    "wof:name":"Jan Marijnissen",
    "wof:placetype":"venue"
},
  "geometry": {"coordinates":[4.3806381226,51.1038780212],"type":"Point"}
}