{
  "type": "Feature",
  "properties": {
    "addr:full":"Schouwburgplein 8b51 Kortrijk West-Vlaanderen 8500",
    "addr:housenumber":"8b51",
    "addr:postcode":"8500",
    "addr:street":"Schouwburgplein",
    "iso:country":"BE",
    "sg:address":"Schouwburgplein 8b51",
    "sg:city":"Kortrijk",
    "sg:orig_category":"Produits interm\u00e9diaires Gr",
    "sg:phone":"+32 56 21 46 57",
    "sg:postcode":"8500",
    "sg:province":"West-Vlaanderen",
    "wof:name":"Fa. Claus International",
    "wof:placetype":"venue"
},
  "geometry": {"coordinates":[3.265599966,50.8255310059],"type":"Point"}
}