{
  "type": "Feature",
  "properties": {
    "addr:full":"Rue Hautmont 21 Braine-l`alleud Brabant Wallon 1421",
    "addr:housenumber":"21;1421",
    "addr:street":"Rue Hautmont;Brabant Wallon",
    "iso:country":"BE",
    "sg:address":"Rue Hautmont 21",
    "sg:city":"Braine-l`alleud",
    "sg:orig_category":"Boekhouders",
    "sg:phone":"+32 2 384 03 76",
    "sg:postcode":"1421",
    "sg:province":"Brabant Wallon",
    "wof:name":"Beke Bernard",
    "wof:placetype":"venue"
},
  "geometry": {"coordinates":[1.2029399872,47.4052200317],"type":"Point"}
}