{
  "type": "Feature",
  "properties": {
    "addr:full":"Vaartstraat 5 Veurne West-Vlaanderen 8630",
    "addr:housenumber":"5",
    "addr:postcode":"8630",
    "addr:street":"Vaartstraat",
    "iso:country":"BE",
    "sg:address":"Vaartstraat 5",
    "sg:city":"Veurne",
    "sg:classifiers":[
        {
            "category":"Bars & Pubs",
            "type":"Food & Drink"
        }
    ],
    "sg:phone":"+32 58 31 58 60",
    "sg:postcode":"8630",
    "sg:province":"West-Vlaanderen",
    "wof:name":"Beurte Van Antwerpen (de)",
    "wof:placetype":"venue"
},
  "geometry": {"coordinates":[2.6690499783,51.0720176697],"type":"Point"}
}