{
  "type": "Feature",
  "properties": {
    "addr:full":"Schaarbeeklei 14 Vilvoorde Vlaams-Brabant 1800",
    "addr:housenumber":"14",
    "addr:postcode":"1800",
    "addr:street":"Schaarbeeklei",
    "iso:country":"BE",
    "sg:address":"Schaarbeeklei 14",
    "sg:city":"Vilvoorde",
    "sg:orig_category":"Boekhandels Disneyland Parijs Reisbureaus",
    "sg:phone":"+32 2 251 17 15",
    "sg:postcode":"1800",
    "sg:province":"Vlaams-Brabant",
    "wof:name":"Vtb Vilvoorde",
    "wof:placetype":"venue"
},
  "geometry": {"coordinates":[4.4261288643,50.9259033203],"type":"Point"}
}