{
  "type": "Feature",
  "properties": {
    "addr:full":"Beukenlaan 9 Beveren (kieldrecht) Oost-Vlaanderen 9130",
    "addr:housenumber":"9",
    "addr:postcode":"9130",
    "addr:street":"Beukenlaan",
    "iso:country":"BE",
    "sg:address":"Beukenlaan 9",
    "sg:city":"Beveren (kieldrecht)",
    "sg:classifiers":[
        {
            "category":"Education",
            "subcategory":"School",
            "type":"Public Place"
        }
    ],
    "sg:phone":"+32 3 773 47 90",
    "sg:postcode":"9130",
    "sg:province":"Oost-Vlaanderen",
    "sg:tags":[
        "primary"
    ],
    "wof:name":"Leefschool De Zonnewijzer",
    "wof:placetype":"venue"
},
  "geometry": {"coordinates":[4.1767268181,51.2905578613],"type":"Point"}
}