{
  "type": "Feature",
  "properties": {
    "addr:full":"Boeretangstraat 24 Westerlo Antwerpen 2260",
    "addr:housenumber":"24",
    "addr:postcode":"2260",
    "addr:street":"Boeretangstraat",
    "iso:country":"BE",
    "sg:address":"Boeretangstraat 24",
    "sg:city":"Westerlo",
    "sg:orig_category":"Slagers",
    "sg:phone":"+32 14 54 56 53",
    "sg:postcode":"2260",
    "sg:province":"Antwerpen",
    "wof:name":"Raoul Van Den Meerssche",
    "wof:placetype":"venue"
},
  "geometry": {"coordinates":[4.9129629135,51.106754303],"type":"Point"}
}