{
  "type": "Feature",
  "properties": {
    "iso:country":"BE",
    "sg:address":"Wijgmaalsesteenweg 36",
    "sg:city":"Leuven (wilsele)",
    "sg:classifiers":[
        {
            "category":"Professional",
            "subcategory":"Management & Consulting",
            "type":"Services"
        }
    ],
    "sg:phone":"+32 16 89 44 04",
    "sg:postcode":"3012",
    "sg:province":"Vlaams-Brabant",
    "sg:tags":[
        "-",
        "processing",
        "data",
        "consultant"
    ],
    "wof:name":"Ebusiness Consulting Bvba",
    "wof:placetype":"venue"
},
  "geometry": {"coordinates":[4.707408905,50.9069366455],"type":"Point"}
}