{
  "type": "Feature",
  "properties": {
    "iso:country":"BE",
    "sg:address":"Kiekenhaag 35",
    "sg:city":"Stekene",
    "sg:orig_category":"Rundveehouders",
    "sg:phone":"+32 3 779 77 40",
    "sg:postcode":"9190",
    "sg:province":"Oost-Vlaanderen",
    "wof:name":"Eugeen Van Goethem",
    "wof:placetype":"venue"
},
  "geometry": {"coordinates":[4.0412678719,51.2196273804],"type":"Point"}
}