{
  "type": "Feature",
  "properties": {
    "addr:full":"Spekmolenstraat 1 Box 1 Herentals Antwerpen 2200",
    "addr:housenumber":"1;1",
    "addr:postcode":"2200",
    "addr:street":"Spekmolenstraat;Box",
    "iso:country":"BE",
    "sg:address":"Spekmolenstraat 1 Box 1",
    "sg:city":"Herentals",
    "sg:classifiers":[
        {
            "category":"Building & Trades",
            "subcategory":"Construction",
            "type":"Services"
        }
    ],
    "sg:phone":"+32 14 21 34 35",
    "sg:postcode":"2200",
    "sg:province":"Antwerpen",
    "sg:tags":[
        "installation",
        "-",
        "central",
        "heating"
    ],
    "wof:name":"Van Wolputte A",
    "wof:placetype":"venue"
},
  "geometry": {"coordinates":[4.8381800652,51.1724205017],"type":"Point"}
}