{
  "type": "Feature",
  "properties": {
    "addr:full":"Van Goethemstraat 17 A Merelbeke Oost-Vlaanderen 9820",
    "addr:housenumber":"17 a",
    "addr:postcode":"9820",
    "addr:street":"Van Goethemstraat",
    "iso:country":"BE",
    "sg:address":"Van Goethemstraat 17 A",
    "sg:city":"Merelbeke",
    "sg:classifiers":[
        {
            "category":"Shopping",
            "subcategory":"Clothing, Apparel, & Fashions",
            "type":"Retail Goods"
        }
    ],
    "sg:phone":"+32 9 230 84 49",
    "sg:postcode":"9820",
    "sg:province":"Oost-Vlaanderen",
    "sg:tags":[
        "textile",
        "clothing",
        "clothes"
    ],
    "wof:name":"Faket Nv",
    "wof:placetype":"venue"
},
  "geometry": {"coordinates":[3.7608249187,51.0184173584],"type":"Point"}
}