{
  "type": "Feature",
  "properties": {
    "iso:country":"BE",
    "sg:address":"Cour Cession 4",
    "sg:city":"Luik",
    "sg:orig_category":"Installation de menuiserie m\u00e9tallique",
    "sg:phone":"+32 4 342 05 14",
    "sg:postcode":"4020",
    "sg:province":"Li\u00e8ge",
    "wof:name":"Wallendorff",
    "wof:placetype":"venue"
},
  "geometry": {"coordinates":[5.5899529457,50.6386871338],"type":"Point"}
}