{
  "type": "Feature",
  "properties": {
    "addr:full":"Nedergemlaan 3 Zemst (eppegem) Vlaams-Brabant 1980",
    "addr:housenumber":"3",
    "addr:postcode":"1980",
    "addr:street":"Nedergemlaan",
    "iso:country":"BE",
    "sg:address":"Nedergemlaan 3",
    "sg:city":"Zemst (eppegem)",
    "sg:classifiers":[
        {
            "category":"Building & Trades",
            "subcategory":"Construction",
            "type":"Services"
        }
    ],
    "sg:phone":"+32 15 61 71 85",
    "sg:postcode":"1980",
    "sg:province":"Vlaams-Brabant",
    "sg:tags":[
        "carpenter"
    ],
    "wof:name":"P & M Bvba",
    "wof:placetype":"venue"
},
  "geometry": {"coordinates":[4.4566669464,50.9647445679],"type":"Point"}
}