{
  "type": "Feature",
  "properties": {
    "addr:full":"Monnikenhofstraat 95 Antwerpen Antwerpen 2040",
    "addr:housenumber":"95",
    "addr:postcode":"2040",
    "addr:street":"Monnikenhofstraat",
    "iso:country":"BE",
    "sg:address":"Monnikenhofstraat 95",
    "sg:city":"Antwerpen",
    "sg:orig_category":"Banques and organismes de cr\u00e9dit",
    "sg:phone":"+32 3 558 33 70",
    "sg:postcode":"2040",
    "sg:province":"Antwerpen",
    "wof:name":"Dexia",
    "wof:placetype":"venue"
},
  "geometry": {"coordinates":[4.3280501366,51.3489608765],"type":"Point"}
}