{
  "type": "Feature",
  "properties": {
    "addr:full":"Rijselstraat 25a Menen West-Vlaanderen 8930",
    "addr:housenumber":"25a",
    "addr:postcode":"8930",
    "addr:street":"Rijselstraat",
    "iso:country":"BE",
    "sg:address":"Rijselstraat 25a",
    "sg:city":"Menen",
    "sg:classifiers":[
        {
            "category":"Shopping",
            "subcategory":"Clothing, Apparel, & Fashions",
            "type":"Retail Goods"
        }
    ],
    "sg:phone":"+32 56 51 05 21",
    "sg:postcode":"8930",
    "sg:province":"West-Vlaanderen",
    "sg:tags":[
        "underwear",
        "lingerie",
        "-"
    ],
    "wof:name":"Fidel",
    "wof:placetype":"venue"
},
  "geometry": {"coordinates":[3.1218819618,50.7951011658],"type":"Point"}
}