{
  "type": "Feature",
  "properties": {
    "addr:full":"Meienbroek 38 Lovendegem Oost-Vlaanderen 9920",
    "addr:housenumber":"38",
    "addr:postcode":"9920",
    "addr:street":"Meienbroek",
    "iso:country":"BE",
    "sg:address":"Meienbroek 38",
    "sg:city":"Lovendegem",
    "sg:orig_category":"Plantes and fleurs Gr",
    "sg:phone":"+32 9 372 52 73",
    "sg:postcode":"9920",
    "sg:province":"Oost-Vlaanderen",
    "wof:name":"De Roose Philip",
    "wof:placetype":"venue"
},
  "geometry": {"coordinates":[3.6172280312,51.1163711548],"type":"Point"}
}