{
  "type": "Feature",
  "properties": {
    "addr:full":"Nokerseweg 109 Waregem West-Vlaanderen 8790",
    "addr:housenumber":"109",
    "addr:postcode":"8790",
    "iso:country":"BE",
    "sg:address":"Nokerseweg 109",
    "sg:city":"Waregem",
    "sg:classifiers":[
        {
            "category":"Sports & Exercise",
            "subcategory":"Stables",
            "type":"Entertainment"
        }
    ],
    "sg:phone":"+32 473 70 36 70",
    "sg:postcode":"8790",
    "sg:province":"West-Vlaanderen",
    "sg:tags":[
        "riding",
        "school"
    ],
    "wof:name":"Paardenpension Franky Meheus",
    "wof:placetype":"venue"
},
  "geometry": {"coordinates":[3.45855093,50.8876533508],"type":"Point"}
}