{
  "type": "Feature",
  "properties": {
    "iso:country":"BE",
    "sg:address":"Nieuwstraat 13b15",
    "sg:city":"Sint-katelijne-waver",
    "sg:orig_category":"Produits surgel\u00e9s Fruits and l\u00e9gumes Gr",
    "sg:phone":"+32 15 75 52 77",
    "sg:postcode":"2861",
    "sg:province":"Antwerpen",
    "wof:name":"Fe. Heylen & Zonen",
    "wof:placetype":"venue"
},
  "geometry": {"coordinates":[4.5819549561,51.0602645874],"type":"Point"}
}