{
  "type": "Feature",
  "properties": {
    "addr:full":"Rue Poucet 7 Chimay (bourlers) Hainaut 6464",
    "addr:housenumber":"7",
    "addr:postcode":"6464",
    "addr:street":"Rue Poucet",
    "iso:country":"BE",
    "sg:address":"Rue Poucet 7",
    "sg:city":"Chimay (bourlers)",
    "sg:classifiers":[
        {
            "category":"Shopping",
            "subcategory":"Bicycles & Sporting Goods",
            "type":"Retail Goods"
        }
    ],
    "sg:phone":"+32 60 21 13 42",
    "sg:postcode":"6464",
    "sg:province":"Hainaut",
    "sg:tags":[
        "tyre"
    ],
    "wof:name":"Sevrain Pneus Sa",
    "wof:placetype":"venue"
},
  "geometry": {"coordinates":[4.3415060043,50.0240592957],"type":"Point"}
}