{
  "type": "Feature",
  "properties": {
    "addr:full":"Kerkplein 28 Waregem West-Vlaanderen 8791",
    "addr:housenumber":"28",
    "addr:postcode":"8791",
    "addr:street":"Kerkplein",
    "iso:country":"BE",
    "sg:address":"Kerkplein 28",
    "sg:city":"Waregem",
    "sg:classifiers":[
        {
            "category":"Food & Beverages",
            "subcategory":"Fruits & Vegetables",
            "type":"Retail Goods"
        }
    ],
    "sg:phone":"+32 56 72 93 21",
    "sg:postcode":"8791",
    "sg:province":"West-Vlaanderen",
    "sg:tags":[
        "groenten"
    ],
    "wof:name":"De Fruitcentrale",
    "wof:placetype":"venue"
},
  "geometry": {"coordinates":[3.3463599682,50.8759231567],"type":"Point"}
}