{
  "type": "Feature",
  "properties": {
    "addr:full":"Kerkstraat 35 Sint-lievens-houtem Oost-Vlaanderen 9521",
    "addr:housenumber":"35",
    "addr:postcode":"9521",
    "addr:street":"Kerkstraat",
    "iso:country":"BE",
    "sg:address":"Kerkstraat 35",
    "sg:city":"Sint-lievens-houtem",
    "sg:orig_category":"Woningbouw",
    "sg:phone":"+32 53 62 40 26",
    "sg:postcode":"9521",
    "sg:province":"Oost-Vlaanderen",
    "wof:name":"De Moor F",
    "wof:placetype":"venue"
},
  "geometry": {"coordinates":[3.8806929588,50.9285202026],"type":"Point"}
}