{
  "type": "Feature",
  "properties": {
    "iso:country":"BE",
    "sg:address":"Place De La Madeleine 4",
    "sg:city":"Chatelet",
    "sg:classifiers":[
        {
            "category":"Cafe",
            "type":"Food & Drink"
        }
    ],
    "sg:phone":"+32 71 39 58 84",
    "sg:postcode":"6200",
    "sg:province":"Hainaut",
    "sg:tags":[
        "caf\u00e9s"
    ],
    "wof:name":"Caf\u00c9 Des Combattants",
    "wof:placetype":"venue"
},
  "geometry": {"coordinates":[4.5236740112,50.4041366577],"type":"Point"}
}