{
  "type": "Feature",
  "properties": {
    "iso:country":"BE",
    "sg:address":"Magere Schorre 49",
    "sg:city":"Knokke-heist (knokke)",
    "sg:classifiers":[
        {
            "category":"Real Estate",
            "subcategory":"Architect",
            "type":"Services"
        }
    ],
    "sg:phone":"+32 50 60 53 57",
    "sg:postcode":"8300",
    "sg:province":"West-Vlaanderen",
    "wof:name":"Wymeersch W",
    "wof:placetype":"venue"
},
  "geometry": {"coordinates":[3.3023641109,51.3406600952],"type":"Point"}
}