{
  "type": "Feature",
  "properties": {
    "addr:full":"Hasseltsebaan 134 Hechtel-eksel (hechtel) Limburg 3940",
    "addr:housenumber":"134",
    "addr:postcode":"3940",
    "addr:street":"Hasseltsebaan",
    "iso:country":"BE",
    "sg:address":"Hasseltsebaan 134",
    "sg:city":"Hechtel-eksel (hechtel)",
    "sg:classifiers":[
        {
            "category":"Autos & Motor Vehicles",
            "subcategory":"Automobile Sales",
            "type":"Retail Goods"
        }
    ],
    "sg:phone":"+32 11 73 34 67",
    "sg:postcode":"3940",
    "sg:province":"Limburg",
    "sg:tags":[
        "car",
        "used",
        "-"
    ],
    "wof:name":"Auto's P&h Bvba",
    "wof:placetype":"venue"
},
  "geometry": {"coordinates":[5.3746128082,51.0967674255],"type":"Point"}
}