{
  "type": "Feature",
  "properties": {
    "addr:full":"Lindestraat 37a Denderleeuw Oost-Vlaanderen 9470",
    "addr:housenumber":"37a",
    "addr:postcode":"9470",
    "addr:street":"Lindestraat",
    "iso:country":"BE",
    "sg:address":"Lindestraat 37a",
    "sg:city":"Denderleeuw",
    "sg:classifiers":[
        {
            "category":"Shopping",
            "subcategory":"Optician",
            "type":"Retail Goods"
        }
    ],
    "sg:phone":"+32 53 66 14 39",
    "sg:postcode":"9470",
    "sg:province":"Oost-Vlaanderen",
    "sg:tags":[
        "-"
    ],
    "wof:name":"Keymeulen Optiek Bvba",
    "wof:placetype":"venue"
},
  "geometry": {"coordinates":[4.0738339424,50.8828773499],"type":"Point"}
}