{
  "type": "Feature",
  "properties": {
    "iso:country":"BE",
    "sg:address":"Rue De Val-meer 12",
    "sg:city":"Bassenge",
    "sg:orig_category":"Varkenskwekers",
    "sg:phone":"+32 4 286 36 44",
    "sg:postcode":"4690",
    "sg:province":"Li\u00e8ge",
    "wof:name":"Debrus A. & D'archis Ph.",
    "wof:placetype":"venue"
},
  "geometry": {"coordinates":[5.5991539955,50.7641944885],"type":"Point"}
}