{
  "type": "Feature",
  "properties": {
    "addr:full":"Desselgemse Steenweg 39 Deerlijk West-Vlaanderen 8540",
    "addr:housenumber":"39",
    "addr:postcode":"8540",
    "addr:street":"Steenweg",
    "iso:country":"BE",
    "sg:address":"Desselgemse Steenweg 39",
    "sg:city":"Deerlijk",
    "sg:classifiers":[
        {
            "category":"Manufacturing",
            "subcategory":"Paper Products",
            "type":"Manufacturing & Wholesale Goods"
        }
    ],
    "sg:phone":"+32 56 71 09 23",
    "sg:postcode":"8540",
    "sg:province":"West-Vlaanderen",
    "sg:tags":[
        "bag"
    ],
    "wof:name":"Lannoo J & Zonen Bvba",
    "wof:placetype":"venue"
},
  "geometry": {"coordinates":[3.3766129017,50.8612709045],"type":"Point"}
}