{
  "type": "Feature",
  "properties": {
    "iso:country":"BE",
    "sg:address":"Rue De Loyers 11",
    "sg:city":"Gesves",
    "sg:orig_category":"Woningbouw",
    "sg:phone":"+32 81 58 02 34",
    "sg:postcode":"5340",
    "sg:province":"Namur",
    "wof:name":"B.guala",
    "wof:placetype":"venue"
},
  "geometry": {"coordinates":[4.9858360291,50.4428977966],"type":"Point"}
}