{
  "type": "Feature",
  "properties": {
    "iso:country":"BE",
    "sg:address":"Leopoldlaan 59",
    "sg:city":"Middelkerke",
    "sg:classifiers":[
        {
            "category":"Fast Food",
            "type":"Food & Drink"
        }
    ],
    "sg:phone":"+32 59 31 03 82",
    "sg:postcode":"8430",
    "sg:province":"West-Vlaanderen",
    "sg:tags":[
        "\u00c0",
        "restaurants",
        "emporter",
        "restaurant"
    ],
    "wof:name":"Aydis",
    "wof:placetype":"venue"
},
  "geometry": {"coordinates":[2.815666914,51.1877250671],"type":"Point"}
}