{
  "type": "Feature",
  "properties": {
    "addr:full":"Vogelsberg 50 Genk Limburg 3600",
    "addr:housenumber":"50",
    "addr:postcode":"3600",
    "addr:street":"Vogelsberg",
    "iso:country":"BE",
    "sg:address":"Vogelsberg 50",
    "sg:city":"Genk",
    "sg:classifiers":[
        {
            "category":"Health Services",
            "subcategory":"Health Practitioner",
            "type":"Services"
        }
    ],
    "sg:phone":"+32 89 30 38 54",
    "sg:postcode":"3600",
    "sg:province":"Limburg",
    "sg:tags":[
        "physiotherapist"
    ],
    "wof:name":"Kums Hilde",
    "wof:placetype":"venue"
},
  "geometry": {"coordinates":[5.4894571304,50.9920387268],"type":"Point"}
}