{
  "type": "Feature",
  "properties": {
    "iso:country":"BE",
    "sg:address":"Mellestraat 21",
    "sg:city":"Laarne",
    "sg:orig_category":"Boomkwekerijen",
    "sg:phone":"+32 9 230 69 47",
    "sg:postcode":"9270",
    "sg:province":"Oost-Vlaanderen",
    "wof:name":"Bjorn Rombaut",
    "wof:placetype":"venue"
},
  "geometry": {"coordinates":[3.8378200531,51.0238113403],"type":"Point"}
}