{
  "type": "Feature",
  "properties": {
    "iso:country":"BE",
    "sg:address":"Avenue De Bouillon 1",
    "sg:city":"Libramont-chevigny",
    "sg:orig_category":"S\u00e9curit\u00e9 sociale. Secr\u00e9tariats sociaux",
    "sg:phone":"+32 61 22 90 20",
    "sg:postcode":"6800",
    "sg:province":"Luxembourg",
    "wof:name":"Partena",
    "wof:placetype":"venue"
},
  "geometry": {"coordinates":[5.3764801025,49.9201660156],"type":"Point"}
}