{
  "type": "Feature",
  "properties": {
    "addr:full":"Morinnegoed 51 Kortrijk West-Vlaanderen 8500",
    "addr:housenumber":"51",
    "addr:postcode":"8500",
    "addr:street":"Morinnegoed",
    "iso:country":"BE",
    "sg:address":"Morinnegoed 51",
    "sg:city":"Kortrijk",
    "sg:orig_category":"Slagers",
    "sg:phone":"+32 56 22 89 46",
    "sg:postcode":"8500",
    "sg:province":"West-Vlaanderen",
    "wof:name":"Angelo Verschelde",
    "wof:placetype":"venue"
},
  "geometry": {"coordinates":[3.3039391041,50.8096885681],"type":"Point"}
}