{
  "type": "Feature",
  "properties": {
    "iso:country":"BE",
    "sg:address":"Rue De Belle-vue 125",
    "sg:city":"La Louviere",
    "sg:orig_category":"Deurwaarders",
    "sg:phone":"+32 64 22 17 29",
    "sg:postcode":"7100",
    "sg:province":"Hainaut",
    "wof:name":"Thierry Deroubaix",
    "wof:placetype":"venue"
},
  "geometry": {"coordinates":[4.1896948814,50.4717674255],"type":"Point"}
}