{
  "type": "Feature",
  "properties": {
    "iso:country":"BE",
    "sg:address":"Oostmolenstraat 226",
    "sg:city":"Aalter",
    "sg:classifiers":[
        {
            "category":"Shopping",
            "subcategory":"Pets & Pet Supplies",
            "type":"Retail Goods"
        }
    ],
    "sg:phone":"+32 9 375 07 84",
    "sg:postcode":"9880",
    "sg:province":"Oost-Vlaanderen",
    "sg:tags":[
        "shop",
        "-"
    ],
    "wof:name":"Baele Dier- & Tuincenter",
    "wof:placetype":"venue"
},
  "geometry": {"coordinates":[3.471832037,51.0983963013],"type":"Point"}
}