{
  "type": "Feature",
  "properties": {
    "addr:full":"Thier De La Rivi\u00e8re 1 Wanze (huccorgne) Li\u00e8ge 4520",
    "addr:housenumber":"1",
    "addr:postcode":"4520",
    "addr:street":"Thier De La Rivie\u0300Re",
    "iso:country":"BE",
    "sg:address":"Thier De La Rivi\u00e8re 1",
    "sg:city":"Wanze (huccorgne)",
    "sg:classifiers":[
        {
            "category":"Real Estate",
            "subcategory":"Real Estate Services",
            "type":"Services"
        }
    ],
    "sg:phone":"+32 85 71 12 84",
    "sg:postcode":"4520",
    "sg:province":"Li\u00e8ge",
    "wof:name":"Ager-geo Sprl",
    "wof:placetype":"venue"
},
  "geometry": {"coordinates":[5.1497869492,50.5425376892],"type":"Point"}
}