{
  "type": "Feature",
  "properties": {
    "iso:country":"BE",
    "sg:address":"Tunnelstraat 163",
    "sg:city":"Leopoldsburg (heppen)",
    "sg:classifiers":[
        {
            "category":"Shopping",
            "subcategory":"Crafts & Fabrics",
            "type":"Retail Goods"
        }
    ],
    "sg:phone":"+32 11 34 89 36",
    "sg:postcode":"3971",
    "sg:province":"Limburg",
    "sg:tags":[
        "pleating",
        "embroidery"
    ],
    "wof:name":"A.l. Borduurwerken",
    "wof:placetype":"venue"
},
  "geometry": {"coordinates":[5.2284450531,51.1292724609],"type":"Point"}
}