{
  "type": "Feature",
  "properties": {
    "addr:full":"Esenstraat 18ba Kortemark West-Vlaanderen 8610",
    "addr:postcode":"8610",
    "addr:street":"Esenstraat",
    "iso:country":"BE",
    "sg:address":"Esenstraat 18ba",
    "sg:city":"Kortemark",
    "sg:orig_category":"Banques and organismes de cr\u00e9dit",
    "sg:phone":"+32 51 57 09 90",
    "sg:postcode":"8610",
    "sg:province":"West-Vlaanderen",
    "wof:name":"Kbc",
    "wof:placetype":"venue"
},
  "geometry": {"coordinates":[2.9569599628,51.0182762146],"type":"Point"}
}