{
  "type": "Feature",
  "properties": {
    "iso:country":"BE",
    "sg:address":"Euphrosina Beernaertstraat 13",
    "sg:city":"Oostende",
    "sg:classifiers":[
        {
            "category":"Real Estate",
            "subcategory":"Real Estate Services",
            "type":"Services"
        }
    ],
    "sg:phone":"+32 59 80 34 38",
    "sg:postcode":"8400",
    "sg:province":"West-Vlaanderen",
    "wof:name":"Immo Dot Bvba",
    "wof:placetype":"venue"
},
  "geometry": {"coordinates":[2.9185349941,51.2282562256],"type":"Point"}
}