{
  "type": "Feature",
  "properties": {
    "iso:country":"BE",
    "sg:address":"Groendreef 32 Box 1",
    "sg:city":"Lokeren",
    "sg:classifiers":[
        {
            "category":"Personal",
            "subcategory":"Beauty Salon",
            "type":"Services"
        }
    ],
    "sg:phone":"+32 9 349 32 91",
    "sg:postcode":"9160",
    "sg:province":"Oost-Vlaanderen",
    "wof:name":"Karo",
    "wof:placetype":"venue"
},
  "geometry": {"coordinates":[3.9833810329,51.1106376648],"type":"Point"}
}