{
  "type": "Feature",
  "properties": {
    "iso:country":"BE",
    "sg:address":"Fran\u00c7ois Gaystraat 118",
    "sg:city":"Sint-pieters-woluwe/woluwe-saint-pierre",
    "sg:orig_category":"Herstellingen and onderhoud van auto's",
    "sg:phone":"+32 2 771 07 00",
    "sg:postcode":"1150",
    "sg:province":"Bruxelles-Capitale",
    "wof:name":"Garage Timmermans",
    "wof:placetype":"venue"
},
  "geometry": {"coordinates":[4.4262318611,50.8376731873],"type":"Point"}
}