{
  "type": "Feature",
  "properties": {
    "addr:full":"Guido Gezellelaan 100b3 Deinze Oost-Vlaanderen 9800",
    "addr:housenumber":"100b3",
    "addr:postcode":"9800",
    "addr:street":"Guido Gezellelaan",
    "iso:country":"BE",
    "sg:address":"Guido Gezellelaan 100b3",
    "sg:city":"Deinze",
    "sg:orig_category":"Alternatieve geneeskunde",
    "sg:phone":"+32 9 282 84 04",
    "sg:postcode":"9800",
    "sg:province":"Oost-Vlaanderen",
    "wof:name":"Osteopaat Blanchaert Ph.",
    "wof:placetype":"venue"
},
  "geometry": {"coordinates":[3.5338730812,50.9816017151],"type":"Point"}
}