{
  "type": "Feature",
  "properties": {
    "iso:country":"BE",
    "sg:address":"Albert Vanlaethemstraat 20",
    "sg:city":"Hoeilaart",
    "sg:classifiers":[
        {
            "category":"Freight",
            "type":"Transportation"
        }
    ],
    "sg:phone":"+32 2 657 17 91",
    "sg:postcode":"1560",
    "sg:province":"Vlaams-Brabant",
    "sg:tags":[
        "-",
        "transport"
    ],
    "wof:name":"Transport Poot & Zn Bvba",
    "wof:placetype":"venue"
},
  "geometry": {"coordinates":[4.4673080444,50.758605957],"type":"Point"}
}