{
  "type": "Feature",
  "properties": {
    "iso:country":"BE",
    "sg:address":"Antwerpsesteenweg 11",
    "sg:city":"Antwerpen",
    "sg:orig_category":"Kansspelen",
    "sg:phone":"+32 3 828 70 06",
    "sg:postcode":"2660",
    "sg:province":"Antwerpen",
    "wof:name":"Tierc\u00c9 Franco-belge",
    "wof:placetype":"venue"
},
  "geometry": {"coordinates":[4.3397898674,51.1732788086],"type":"Point"}
}