{
  "type": "Feature",
  "properties": {
    "addr:full":"Mortelstraat 5 Brecht Antwerpen 2960",
    "addr:housenumber":"5",
    "addr:postcode":"2960",
    "addr:street":"Mortelstraat",
    "iso:country":"BE",
    "sg:address":"Mortelstraat 5",
    "sg:city":"Brecht",
    "sg:classifiers":[
        {
            "category":"Retail",
            "subcategory":"Auto Repair",
            "type":"Services"
        }
    ],
    "sg:phone":"+32 3 313 96 32",
    "sg:postcode":"2960",
    "sg:province":"Antwerpen",
    "sg:tags":[
        "garage"
    ],
    "wof:name":"Kustermans",
    "wof:placetype":"venue"
},
  "geometry": {"coordinates":[4.6078910828,51.3445930481],"type":"Point"}
}