{
  "type": "Feature",
  "properties": {
    "addr:full":"Rue De La Salette Philippeville Namur 5600",
    "addr:postcode":"5600",
    "addr:street":"Rue De La Salette",
    "iso:country":"BE",
    "sg:address":"Rue De La Salette",
    "sg:city":"Philippeville",
    "sg:orig_category":"Installatie van houten of kunststof schrijnwerk",
    "sg:phone":"+32 71 66 79 70",
    "sg:postcode":"5600",
    "sg:province":"Namur",
    "wof:name":"Mathot C & Fils",
    "wof:placetype":"venue"
},
  "geometry": {"coordinates":[4.5273041725,50.1764640808],"type":"Point"}
}