{
  "type": "Feature",
  "properties": {
    "addr:full":"Pater Kenislaan 30 Box 2 Schilde Antwerpen 2970",
    "addr:housenumber":"30;2",
    "addr:postcode":"2970",
    "addr:street":"Pater Kenislaan;Box",
    "iso:country":"BE",
    "sg:address":"Pater Kenislaan 30 Box 2",
    "sg:city":"Schilde",
    "sg:classifiers":[
        {
            "category":"Professional",
            "subcategory":"Lawyer & Legal Services",
            "type":"Services"
        }
    ],
    "sg:phone":"+32 3 385 96 58",
    "sg:postcode":"2970",
    "sg:province":"Antwerpen",
    "wof:name":"Verheyen Luc",
    "wof:placetype":"venue"
},
  "geometry": {"coordinates":[4.5750951767,51.2470626831],"type":"Point"}
}