{
  "type": "Feature",
  "properties": {
    "iso:country":"BE",
    "sg:address":"Rue De Rixensart 18b71",
    "sg:city":"Rixensart",
    "sg:orig_category":"Woningbouw",
    "sg:phone":"+32 2 652 52 04",
    "sg:postcode":"1332",
    "sg:province":"Brabant Wallon",
    "wof:name":"Renomac",
    "wof:placetype":"venue"
},
  "geometry": {"coordinates":[4.5144748688,50.7222442627],"type":"Point"}
}