{
  "type": "Feature",
  "properties": {
    "addr:full":"Blaesstraat 107b1 Brussel/bruxelles Bruxelles-Capitale 1000",
    "addr:housenumber":"107b1",
    "addr:postcode":"1000",
    "addr:street":"Blaesstraat;/",
    "iso:country":"BE",
    "sg:address":"Blaesstraat 107b1",
    "sg:city":"Brussel/bruxelles",
    "sg:classifiers":[
        {
            "category":"Professional",
            "subcategory":"Accounting & Tax Preparation",
            "type":"Services"
        }
    ],
    "sg:phone":"+32 2 223 12 40",
    "sg:postcode":"1000",
    "sg:province":"Bruxelles-Capitale",
    "sg:tags":[
        "accountant"
    ],
    "wof:name":"Antonio Ruiz Galan",
    "wof:placetype":"venue"
},
  "geometry": {"coordinates":[4.3480238914,50.8386116028],"type":"Point"}
}