{
  "type": "Feature",
  "properties": {
    "iso:country":"BE",
    "sg:address":"Klein Ravels 66",
    "sg:city":"Ravels",
    "sg:orig_category":"Woningbouw",
    "sg:phone":"+32 14 65 24 62",
    "sg:postcode":"2380",
    "sg:province":"Antwerpen",
    "wof:name":"Gecuver",
    "wof:placetype":"venue"
},
  "geometry": {"coordinates":[4.9917430878,51.3765220642],"type":"Point"}
}