{
  "type": "Feature",
  "properties": {
    "addr:full":"Rue De Soudromont 20 Seneffe Hainaut 7180",
    "addr:housenumber":"20",
    "addr:postcode":"7180",
    "addr:street":"Rue De Soudromont",
    "iso:country":"BE",
    "sg:address":"Rue De Soudromont 20",
    "sg:city":"Seneffe",
    "sg:classifiers":[
        {
            "category":"Food & Beverages",
            "subcategory":"Specialty",
            "type":"Retail Goods"
        }
    ],
    "sg:phone":"+32 64 54 81 76",
    "sg:postcode":"7180",
    "sg:province":"Hainaut",
    "sg:tags":[
        "health",
        "dietary",
        "-",
        "biological"
    ],
    "wof:name":"Ferme Thunus",
    "wof:placetype":"venue"
},
  "geometry": {"coordinates":[4.2616209984,50.5178527832],"type":"Point"}
}