{
  "type": "Feature",
  "properties": {
    "addr:full":"Dentergemstraat 44 Deinze Oost-Vlaanderen 9800",
    "addr:housenumber":"44",
    "addr:postcode":"9800",
    "addr:street":"Dentergemstraat",
    "iso:country":"BE",
    "sg:address":"Dentergemstraat 44",
    "sg:city":"Deinze",
    "sg:orig_category":"Enseignement maternel and primaire",
    "sg:phone":"+32 51 63 47 80",
    "sg:postcode":"9800",
    "sg:province":"Oost-Vlaanderen",
    "wof:name":"Vrije Kleuterschool",
    "wof:placetype":"venue"
},
  "geometry": {"coordinates":[3.4446079731,50.9796257019],"type":"Point"}
}