{
  "type": "Feature",
  "properties": {
    "iso:country":"BE",
    "sg:address":"Legeweg 2b",
    "sg:city":"Jabbeke",
    "sg:classifiers":[
        {
            "category":"Communications",
            "subcategory":"Television Station",
            "type":"Services"
        }
    ],
    "sg:phone":"+32 50 81 48 14",
    "sg:postcode":"8490",
    "sg:province":"West-Vlaanderen",
    "sg:tags":[
        "audio",
        "video",
        "cable"
    ],
    "wof:name":"Eye-d Nv",
    "wof:placetype":"venue"
},
  "geometry": {"coordinates":[3.096405983,51.1884727478],"type":"Point"}
}