{
  "type": "Feature",
  "properties": {
    "addr:full":"Stationsstraat 49ba Ichtegem West-Vlaanderen 8480",
    "addr:housenumber":"49ba",
    "addr:postcode":"8480",
    "addr:street":"Stationsstraat",
    "iso:country":"BE",
    "sg:address":"Stationsstraat 49ba",
    "sg:city":"Ichtegem",
    "sg:orig_category":"Banques and organismes de cr\u00e9dit",
    "sg:phone":"+32 59 29 96 58",
    "sg:postcode":"8480",
    "sg:province":"West-Vlaanderen",
    "wof:name":"Ippa",
    "wof:placetype":"venue"
},
  "geometry": {"coordinates":[3.0226531029,51.1296615601],"type":"Point"}
}