{
  "type": "Feature",
  "properties": {
    "addr:full":"Hoveniersstraat 70 Gent (ledeberg) Oost-Vlaanderen 9050",
    "addr:housenumber":"70",
    "addr:postcode":"9050",
    "addr:street":"Hoveniersstraat",
    "iso:country":"BE",
    "sg:address":"Hoveniersstraat 70",
    "sg:city":"Gent (ledeberg)",
    "sg:classifiers":[
        {
            "category":"Personal",
            "subcategory":"Beauty Salon",
            "type":"Services"
        }
    ],
    "sg:phone":"+32 9 230 57 94",
    "sg:postcode":"9050",
    "sg:province":"Oost-Vlaanderen",
    "sg:tags":[
        "lady",
        "-",
        "hairdressing"
    ],
    "wof:name":"Salon Eliane",
    "wof:placetype":"venue"
},
  "geometry": {"coordinates":[3.7466480732,51.0376091003],"type":"Point"}
}