{
  "type": "Feature",
  "properties": {
    "iso:country":"BE",
    "sg:address":"Rue De L\u00b4abattoir 12",
    "sg:city":"Spa",
    "sg:orig_category":"Blanchisseries and teintureries",
    "sg:phone":"+32 87 77 26 62",
    "sg:postcode":"4900",
    "sg:province":"Li\u00e8ge",
    "wof:name":"Lavoir De Barisart",
    "wof:placetype":"venue"
},
  "geometry": {"coordinates":[5.8622288704,50.4890708923],"type":"Point"}
}