{
  "type": "Feature",
  "properties": {
    "iso:country":"BE",
    "sg:address":"Berkenstraat 9",
    "sg:city":"Herk-de-stad (donk)",
    "sg:classifiers":[
        {
            "category":"Autos & Motor Vehicles",
            "subcategory":"Recreational Vehicle Sales",
            "type":"Retail Goods"
        }
    ],
    "sg:phone":"+32 13 44 22 46",
    "sg:postcode":"3540",
    "sg:province":"Limburg",
    "sg:tags":[
        "caravan",
        "accessory"
    ],
    "wof:name":"Boussu Bvba Depannage",
    "wof:placetype":"venue"
},
  "geometry": {"coordinates":[5.135822773,50.9383506775],"type":"Point"}
}