{
  "type": "Feature",
  "properties": {
    "addr:full":"Pater Damiaanstraat 65 Evere/evere Bruxelles-Capitale 1140",
    "addr:housenumber":"65",
    "addr:postcode":"1140",
    "addr:street":"Pater Damiaanstraat",
    "iso:country":"BE",
    "sg:address":"Pater Damiaanstraat 65",
    "sg:city":"Evere/evere",
    "sg:orig_category":"Elektrische installaties voor woningen",
    "sg:phone":"+32 2 216 33 48",
    "sg:postcode":"1140",
    "sg:province":"Bruxelles-Capitale",
    "wof:name":"Ackermans & Co",
    "wof:placetype":"venue"
},
  "geometry": {"coordinates":[4.4010419846,50.8694610596],"type":"Point"}
}