{
  "type": "Feature",
  "properties": {
    "iso:country":"BE",
    "sg:address":"Rue De Givet 56",
    "sg:city":"Durbuy",
    "sg:orig_category":"Brood, gebak and snoepgoed HUISBRANDOLIE",
    "sg:phone":"+32 86 21 25 42",
    "sg:postcode":"6940",
    "sg:province":"Luxembourg",
    "wof:name":"Thierry Destine",
    "wof:placetype":"venue"
},
  "geometry": {"coordinates":[5.4364848137,50.333442688],"type":"Point"}
}