{
  "type": "Feature",
  "properties": {
    "iso:country":"BE",
    "sg:address":"Vurtense Schansstraat 21",
    "sg:city":"Beringen (koersel)",
    "sg:classifiers":[
        {
            "category":"Building & Trades",
            "subcategory":"Construction",
            "type":"Services"
        }
    ],
    "sg:phone":"+32 11 45 32 41",
    "sg:postcode":"3582",
    "sg:province":"Limburg",
    "sg:tags":[
        "carpenter"
    ],
    "wof:name":"Peko",
    "wof:placetype":"venue"
},
  "geometry": {"coordinates":[5.2708749771,51.0595359802],"type":"Point"}
}