{
  "type": "Feature",
  "properties": {
    "addr:full":"Leopoldstraat 98 Mechelen Antwerpen 2800",
    "addr:housenumber":"98",
    "addr:postcode":"2800",
    "addr:street":"Leopoldstraat",
    "iso:country":"BE",
    "sg:address":"Leopoldstraat 98",
    "sg:city":"Mechelen",
    "sg:classifiers":[
        {
            "category":"Education",
            "subcategory":"Dance Studio",
            "type":"Public Place"
        }
    ],
    "sg:phone":"+32 15 42 28 49",
    "sg:postcode":"2800",
    "sg:province":"Antwerpen",
    "sg:tags":[
        "ballet",
        "school"
    ],
    "wof:name":"Dansacademie Pro Arte Vzw",
    "wof:placetype":"venue"
},
  "geometry": {"coordinates":[4.4816379547,51.0179862976],"type":"Point"}
}