{
  "type": "Feature",
  "properties": {
    "addr:full":"Tiensevest 170 Leuven Vlaams-Brabant 3000",
    "addr:housenumber":"170",
    "addr:postcode":"3000",
    "addr:street":"Tiensevest",
    "iso:country":"BE",
    "sg:address":"Tiensevest 170",
    "sg:city":"Leuven",
    "sg:orig_category":"Fairs, shows, exhibitions",
    "sg:phone":"+32 16 22 93 50",
    "sg:postcode":"3000",
    "sg:province":"Vlaams-Brabant",
    "wof:name":"Handelaarsverbond - Leuven",
    "wof:placetype":"venue"
},
  "geometry": {"coordinates":[4.714413166,50.8744850159],"type":"Point"}
}