{
  "type": "Feature",
  "properties": {
    "addr:full":"Stationsstraat 31 Waregem West-Vlaanderen 8790",
    "addr:housenumber":"31",
    "addr:postcode":"8790",
    "addr:street":"Stationsstraat",
    "iso:country":"BE",
    "sg:address":"Stationsstraat 31",
    "sg:city":"Waregem",
    "sg:orig_category":"Bruids- and ceremoniekledij Herenkledingzaken Maatkleding Fab Verhuur textielartikelen and schoenen",
    "sg:phone":"+32 56 60 16 31",
    "sg:postcode":"8790",
    "sg:province":"West-Vlaanderen",
    "wof:name":"Huis St.jacques",
    "wof:placetype":"venue"
},
  "geometry": {"coordinates":[3.4311220646,50.8876876831],"type":"Point"}
}