{
  "type": "Feature",
  "properties": {
    "iso:country":"BE",
    "sg:address":"Rue Fran\u00e7ois Lapierre 22",
    "sg:city":"Fl\u00e9ron",
    "sg:classifiers":[
        {
            "category":"Manufacturing",
            "subcategory":"Musical Instruments",
            "type":"Manufacturing & Wholesale Goods"
        }
    ],
    "sg:phone":"+32 4 358 30 85",
    "sg:postcode":"4620",
    "sg:province":"Li\u00e8ge",
    "sg:tags":[
        "piano"
    ],
    "wof:name":"Bovy Pianos",
    "wof:placetype":"venue"
},
  "geometry": {"coordinates":[5.6827111244,50.617477417],"type":"Point"}
}