{
  "type": "Feature",
  "properties": {
    "iso:country":"BE",
    "sg:address":"Rue Docteur Henri Schaltin 45",
    "sg:city":"Spa",
    "sg:classifiers":[
        {
            "category":"Health Services",
            "subcategory":"Health Practitioner",
            "type":"Services"
        }
    ],
    "sg:phone":"+32 87 22 61 77",
    "sg:postcode":"4900",
    "sg:province":"Li\u00e8ge",
    "sg:tags":[
        "alternative",
        "therapy",
        "treatment"
    ],
    "wof:name":"Ateliers De La Rose (les)-feltes Rita",
    "wof:placetype":"venue"
},
  "geometry": {"coordinates":[5.8662471771,50.4910736084],"type":"Point"}
}