{
  "type": "Feature",
  "properties": {
    "iso:country":"BE",
    "sg:address":"Rue Chaudfontaine 19",
    "sg:city":"Liege",
    "sg:orig_category":"Experts-comptables",
    "sg:phone":"+32 4 342 78 58",
    "sg:postcode":"4020",
    "sg:province":"Li\u00e8ge",
    "wof:name":"Jean F. Nelis",
    "wof:placetype":"venue"
},
  "geometry": {"coordinates":[5.5851831436,50.621925354],"type":"Point"}
}