{
  "type": "Feature",
  "properties": {
    "addr:full":"Rue Du Wayaux 24 Ramillies Brabant Wallon 1367",
    "addr:housenumber":"24",
    "addr:postcode":"1367",
    "addr:street":"Rue Du Wayaux",
    "iso:country":"BE",
    "sg:address":"Rue Du Wayaux 24",
    "sg:city":"Ramillies",
    "sg:orig_category":"Catering and organisatie van feesten Kruideniers",
    "sg:phone":"+32 81 87 73 34",
    "sg:postcode":"1367",
    "sg:province":"Brabant Wallon",
    "wof:name":"Le Tour De Main",
    "wof:placetype":"venue"
},
  "geometry": {"coordinates":[4.932349205,50.64453125],"type":"Point"}
}