{
  "type": "Feature",
  "properties": {
    "iso:country":"BE",
    "sg:address":"Alfons De Cockplein 9",
    "sg:city":"Machelen (diegem)",
    "sg:classifiers":[
        {
            "category":"Professional",
            "subcategory":"Lawyer & Legal Services",
            "type":"Services"
        }
    ],
    "sg:phone":"+32 2 720 08 13",
    "sg:postcode":"1831",
    "sg:province":"Vlaams-Brabant",
    "wof:name":"Milde Peter",
    "wof:placetype":"venue"
},
  "geometry": {"coordinates":[4.4358401299,50.8946228027],"type":"Point"}
}