{
  "type": "Feature",
  "properties": {
    "addr:full":"Tuindijk 48 Schriek Antwerpen 2223",
    "addr:housenumber":"48",
    "addr:postcode":"2223",
    "addr:street":"Tuindijk",
    "iso:country":"BE",
    "sg:address":"Tuindijk 48",
    "sg:city":"Schriek",
    "sg:classifiers":[
        {
            "category":"Building & Trades",
            "subcategory":"Construction",
            "type":"Services"
        }
    ],
    "sg:phone":"+32 15 23 35 68",
    "sg:postcode":"2223",
    "sg:province":"Antwerpen",
    "sg:tags":[
        "roofing"
    ],
    "wof:name":"Dakwerken Dieltjens B.v.b.a.",
    "wof:placetype":"venue"
},
  "geometry": {"coordinates":[4.6977248192,51.0226478577],"type":"Point"}
}