{
  "type": "Feature",
  "properties": {
    "addr:full":"Bollestraat 14 Overijse Vlaams-Brabant 3090",
    "addr:housenumber":"14",
    "addr:postcode":"3090",
    "addr:street":"Bollestraat",
    "iso:country":"BE",
    "sg:address":"Bollestraat 14",
    "sg:city":"Overijse",
    "sg:orig_category":"M\u00e9decins and sp\u00e9cialistes",
    "sg:phone":"+32 16 47 24 65",
    "sg:postcode":"3090",
    "sg:province":"Vlaams-Brabant",
    "wof:name":"Jean Bronckaers",
    "wof:placetype":"venue"
},
  "geometry": {"coordinates":[4.5914998055,50.7695808411],"type":"Point"}
}