{
  "type": "Feature",
  "properties": {
    "iso:country":"BE",
    "sg:address":"Dries 2a",
    "sg:city":"Kontich",
    "sg:classifiers":[
        {
            "category":"Social Services",
            "type":"Services"
        }
    ],
    "sg:phone":"+32 3 458 42 50",
    "sg:postcode":"2550",
    "sg:province":"Antwerpen",
    "wof:name":"Begeleid Wonen Rupelstreek & Zuidelijk Antwerpen",
    "wof:placetype":"venue"
},
  "geometry": {"coordinates":[4.4707140923,51.1355361938],"type":"Point"}
}