{
  "type": "Feature",
  "properties": {
    "iso:country":"BE",
    "sg:address":"Rue Large Voie 23",
    "sg:city":"Bassenge (wonck)",
    "sg:classifiers":[
        {
            "category":"Health Services",
            "subcategory":"Dentist",
            "type":"Services"
        }
    ],
    "sg:phone":"+32 4 286 21 34",
    "sg:postcode":"4690",
    "sg:province":"Li\u00e8ge",
    "wof:name":"Vandenbeylaardt G",
    "wof:placetype":"venue"
},
  "geometry": {"coordinates":[5.6301012039,50.7635345459],"type":"Point"}
}