{
  "type": "Feature",
  "properties": {
    "addr:full":"Rue Du Bon Voisin 26 Tubize Brabant Wallon 1480",
    "addr:housenumber":"26",
    "addr:postcode":"1480",
    "addr:street":"Rue Du Bon Voisin;Wallon",
    "iso:country":"BE",
    "sg:address":"Rue Du Bon Voisin 26",
    "sg:city":"Tubize",
    "sg:classifiers":[
        {
            "category":"Professional",
            "subcategory":"Accounting & Tax Preparation",
            "type":"Services"
        }
    ],
    "sg:phone":"+32 67 64 70 55",
    "sg:postcode":"1480",
    "sg:province":"Brabant Wallon",
    "sg:tags":[
        "accountant"
    ],
    "wof:name":"Michel Goldberg",
    "wof:placetype":"venue"
},
  "geometry": {"coordinates":[4.2244000435,50.6604881287],"type":"Point"}
}