{
  "type": "Feature",
  "properties": {
    "iso:country":"BE",
    "sg:address":"Oeverstr 3",
    "sg:city":"Lokeren",
    "sg:classifiers":[
        {
            "category":"Government",
            "subcategory":"Department Of Motor Vehicles",
            "type":"Public Place"
        }
    ],
    "sg:phone":"+32 9 340 41 41",
    "sg:postcode":"9160",
    "sg:province":"Oost-Vlaanderen",
    "sg:tags":[
        "equipment",
        "industrial",
        "transport",
        "motor-cars"
    ],
    "wof:name":"Garage Van Winkel Marcel Nv",
    "wof:placetype":"venue"
},
  "geometry": {"coordinates":[4.0196027756,51.0910606384],"type":"Point"}
}