{
  "type": "Feature",
  "properties": {
    "iso:country":"BE",
    "sg:address":"Groenstraat 28",
    "sg:city":"Holsbeek",
    "sg:orig_category":"Fruitteelt Groententeelt",
    "sg:phone":"+32 16 56 59 21",
    "sg:postcode":"3221",
    "sg:province":"Vlaams-Brabant",
    "wof:name":"Roger Crabbe",
    "wof:placetype":"venue"
},
  "geometry": {"coordinates":[4.8366518021,50.942741394],"type":"Point"}
}