{
  "type": "Feature",
  "properties": {
    "addr:full":"Rue Du Breucq 64 Ath Hainaut 7822",
    "addr:housenumber":"64",
    "addr:postcode":"7822",
    "addr:street":"Rue Du Breucq",
    "iso:country":"BE",
    "sg:address":"Rue Du Breucq 64",
    "sg:city":"Ath",
    "sg:orig_category":"Pluimveekwekers Rundveehouders",
    "sg:phone":"+32 68 55 10 38",
    "sg:postcode":"7822",
    "sg:province":"Hainaut",
    "wof:name":"Joseph Holvoet",
    "wof:placetype":"venue"
},
  "geometry": {"coordinates":[3.8452620506,50.6482391357],"type":"Point"}
}