{
  "type": "Feature",
  "properties": {
    "iso:country":"BE",
    "sg:address":"Koningsstraat 266",
    "sg:city":"Sint-joost-ten-node/saint-josse-ten-noode",
    "sg:orig_category":"Informaticaconsulenten Onderhoud van kantoor- and computeruitrusting Software ontwikkeling and ontwe",
    "sg:phone":"+32 2 217 20 07",
    "sg:postcode":"1210",
    "sg:province":"Bruxelles-Capitale",
    "wof:name":"Incisive",
    "wof:placetype":"venue"
},
  "geometry": {"coordinates":[4.3669271469,50.8556213379],"type":"Point"}
}