{
  "type": "Feature",
  "properties": {
    "addr:full":"Rue De La Maladrerie 74 Jodoigne Brabant Wallon 1370",
    "addr:housenumber":"74",
    "addr:postcode":"1370",
    "addr:street":"Rue De La Maladrerie",
    "iso:country":"BE",
    "sg:address":"Rue De La Maladrerie 74",
    "sg:city":"Jodoigne",
    "sg:orig_category":"Architectes",
    "sg:phone":"+32 10 81 55 27",
    "sg:postcode":"1370",
    "sg:province":"Brabant Wallon",
    "wof:name":"Leonello Scossiroli",
    "wof:placetype":"venue"
},
  "geometry": {"coordinates":[4.8592939377,50.7196731567],"type":"Point"}
}