{
  "type": "Feature",
  "properties": {
    "addr:full":"Kleemstraat 23 Box 21 Halle Vlaams-Brabant 1500",
    "addr:housenumber":"23 box 21",
    "addr:postcode":"1500",
    "addr:street":"Kleemstraat",
    "iso:country":"BE",
    "sg:address":"Kleemstraat 23 Box 21",
    "sg:city":"Halle",
    "sg:classifiers":[
        {
            "category":"Transit Center",
            "subcategory":"Freight",
            "type":"Transportation"
        }
    ],
    "sg:phone":"+32 2 361 37 38",
    "sg:postcode":"1500",
    "sg:province":"Vlaams-Brabant",
    "sg:tags":[
        "import",
        "export",
        "-"
    ],
    "wof:name":"Exporama-indorama",
    "wof:placetype":"venue"
},
  "geometry": {"coordinates":[4.2581467628,50.7198066711],"type":"Point"}
}