{
  "type": "Feature",
  "properties": {
    "addr:full":"Rue De Campine 332 Li\u00c8ge Li\u00e8ge 4000",
    "addr:housenumber":"332",
    "addr:postcode":"4000",
    "addr:street":"Rue De Campine",
    "iso:country":"BE",
    "sg:address":"Rue De Campine 332",
    "sg:city":"Li\u00c8ge",
    "sg:orig_category":"Traitements param\u00e9dicaux",
    "sg:phone":"+32 4 226 77 23",
    "sg:postcode":"4000",
    "sg:province":"Li\u00e8ge",
    "wof:name":"Chantal Melotte",
    "wof:placetype":"venue"
},
  "geometry": {"coordinates":[5.5663099289,50.655620575],"type":"Point"}
}