{
  "type": "Feature",
  "properties": {
    "addr:full":"Waterschransweg 6 Lier Antwerpen 2500",
    "addr:housenumber":"6",
    "addr:postcode":"2500",
    "addr:street":"Waterschransweg",
    "iso:country":"BE",
    "sg:address":"Waterschransweg 6",
    "sg:city":"Lier",
    "sg:classifiers":[
        {
            "category":"Health Services",
            "subcategory":"Health Practitioner",
            "type":"Services"
        }
    ],
    "sg:phone":"+32 3 488 09 73",
    "sg:postcode":"2500",
    "sg:province":"Antwerpen",
    "sg:tags":[
        "therapist",
        "speech"
    ],
    "wof:name":"Keteleer H",
    "wof:placetype":"venue"
},
  "geometry": {"coordinates":[4.5479588509,51.1226425171],"type":"Point"}
}