{
  "type": "Feature",
  "properties": {
    "addr:full":"De Hulsten 161 Zoersel Antwerpen 2980",
    "addr:housenumber":"161",
    "addr:postcode":"2980",
    "iso:country":"BE",
    "sg:address":"De Hulsten 161",
    "sg:city":"Zoersel",
    "sg:classifiers":[
        {
            "category":"Building & Trades",
            "subcategory":"Electrical",
            "type":"Services"
        }
    ],
    "sg:phone":"+32 3 324 66 38",
    "sg:postcode":"2980",
    "sg:province":"Antwerpen",
    "sg:tags":[
        "electric",
        "-",
        "housewiring",
        "contractor"
    ],
    "wof:name":"Decaluwe Marc Bvba",
    "wof:placetype":"venue"
},
  "geometry": {"coordinates":[4.6896729469,51.2690391541],"type":"Point"}
}