{
  "type": "Feature",
  "properties": {
    "addr:full":"Chauss\u00c9e D'ath 242 Enghien Hainaut 7850",
    "addr:housenumber":"242",
    "addr:postcode":"7850",
    "addr:street":"Chausse\u0301E D'Ath",
    "iso:country":"BE",
    "sg:address":"Chauss\u00c9e D'ath 242",
    "sg:city":"Enghien",
    "sg:orig_category":"Informaticaconsulenten",
    "sg:phone":"+32 2 397 02 33",
    "sg:postcode":"7850",
    "sg:province":"Hainaut",
    "wof:name":"A.d.j. Consultancy",
    "wof:placetype":"venue"
},
  "geometry": {"coordinates":[3.9902288914,50.6814041138],"type":"Point"}
}