{
  "type": "Feature",
  "properties": {
    "iso:country":"BE",
    "sg:address":"Sint-anna 64",
    "sg:city":"Hamme",
    "sg:classifiers":[
        {
            "category":"Retail",
            "subcategory":"Animal Services",
            "type":"Services"
        }
    ],
    "sg:phone":"+32 52 47 19 84",
    "sg:postcode":"9220",
    "sg:province":"Oost-Vlaanderen",
    "sg:tags":[
        "breeding",
        "selling",
        "-",
        "dog"
    ],
    "wof:name":"Quality Dogs",
    "wof:placetype":"venue"
},
  "geometry": {"coordinates":[4.0762400627,51.0947227478],"type":"Point"}
}