{
  "type": "Feature",
  "properties": {
    "iso:country":"BE",
    "sg:address":"Voie De L\u00b4ardenne 51",
    "sg:city":"Chaudfontaine",
    "sg:classifiers":[
        {
            "category":"Food & Beverages",
            "subcategory":"Fruits & Vegetables",
            "type":"Retail Goods"
        }
    ],
    "sg:phone":"+32 4 365 28 04",
    "sg:postcode":"4053",
    "sg:province":"Li\u00e8ge",
    "sg:tags":[
        "l\u00e9gumes"
    ],
    "wof:name":"Chez Philippe",
    "wof:placetype":"venue"
},
  "geometry": {"coordinates":[5.6074872017,50.5953826904],"type":"Point"}
}