{
  "type": "Feature",
  "properties": {
    "addr:full":"Val Braban\u00e7on 10 Wemmel Vlaams-Brabant 1780",
    "addr:housenumber":"10",
    "addr:postcode":"1780",
    "addr:street":"Val Brabanc\u0327On;Vlaams-Brabant",
    "iso:country":"BE",
    "sg:address":"Val Braban\u00e7on 10",
    "sg:city":"Wemmel",
    "sg:classifiers":[
        {
            "category":"Manufacturing",
            "subcategory":"Tools & Machinery",
            "type":"Manufacturing & Wholesale Goods"
        }
    ],
    "sg:phone":"+32 2 478 64 52",
    "sg:postcode":"1780",
    "sg:province":"Vlaams-Brabant",
    "sg:tags":[
        "-"
    ],
    "wof:name":"Belgian Automotive Tools",
    "wof:placetype":"venue"
},
  "geometry": {"coordinates":[4.3102002144,50.904083252],"type":"Point"}
}