{
  "type": "Feature",
  "properties": {
    "addr:full":"Rue Saint-l\u00e9onard 361 Li\u00e8ge 1 Li\u00e8ge 4000",
    "addr:housenumber":"361;1",
    "addr:postcode":"4000",
    "addr:street":"Rue Saint-Le\u0301Onard",
    "iso:country":"BE",
    "sg:address":"Rue Saint-l\u00e9onard 361",
    "sg:city":"Li\u00e8ge 1",
    "sg:classifiers":[
        {
            "category":"Personal",
            "subcategory":"Barber",
            "type":"Services"
        }
    ],
    "sg:phone":"+32 4 227 21 79",
    "sg:postcode":"4000",
    "sg:province":"Li\u00e8ge",
    "sg:tags":[
        "gentleman",
        "salon",
        "-",
        "hairdressing"
    ],
    "wof:name":"Claudio Coiffure",
    "wof:placetype":"venue"
},
  "geometry": {"coordinates":[5.5990018845,50.6521492004],"type":"Point"}
}