{
  "type": "Feature",
  "properties": {
    "iso:country":"BE",
    "sg:address":"Broekzijstraat 123ba",
    "sg:city":"Lille",
    "sg:orig_category":"Jardinage",
    "sg:phone":"+32 14 88 30 12",
    "sg:postcode":"2275",
    "sg:province":"Antwerpen",
    "wof:name":"Werner Verreth",
    "wof:placetype":"venue"
},
  "geometry": {"coordinates":[4.8075728416,51.2462806702],"type":"Point"}
}