{
  "type": "Feature",
  "properties": {
    "addr:full":"Vakebuurtstraat 230 Maldegem Oost-Vlaanderen 9990",
    "addr:housenumber":"230",
    "addr:postcode":"9990",
    "addr:street":"Vakebuurtstraat",
    "iso:country":"BE",
    "sg:address":"Vakebuurtstraat 230",
    "sg:city":"Maldegem",
    "sg:orig_category":"Medische apparatuur, orthopedische artikelen and prothesen Fab",
    "sg:phone":"+32 50 71 91 79",
    "sg:postcode":"9990",
    "sg:province":"Oost-Vlaanderen",
    "wof:name":"Labo Delaca",
    "wof:placetype":"venue"
},
  "geometry": {"coordinates":[3.4308319092,51.2179107666],"type":"Point"}
}