{
  "type": "Feature",
  "properties": {
    "addr:full":"Chauss\u00c9e De Dinant 128 Anhee Namur 5537",
    "addr:housenumber":"128",
    "addr:postcode":"5537",
    "addr:street":"Chausse\u0301E De Dinant;Namur",
    "iso:country":"BE",
    "sg:address":"Chauss\u00c9e De Dinant 128",
    "sg:city":"Anhee",
    "sg:orig_category":"Natuursteenbewerking Speciaalzaken",
    "sg:phone":"+32 82 61 45 23",
    "sg:postcode":"5537",
    "sg:province":"Namur",
    "wof:name":"Balthazart",
    "wof:placetype":"venue"
},
  "geometry": {"coordinates":[4.8933978081,50.2971305847],"type":"Point"}
}