{
  "type": "Feature",
  "properties": {
    "iso:country":"BE",
    "sg:address":"Rue Du Onze Novembre 24",
    "sg:city":"Mons",
    "sg:classifiers":[
        {
            "category":"Arena",
            "subcategory":"Sports Club",
            "type":"Entertainment"
        }
    ],
    "sg:phone":"+32 65 33 55 56",
    "sg:postcode":"7000",
    "sg:province":"Hainaut",
    "wof:name":"Chantal Lancelot",
    "wof:placetype":"venue"
},
  "geometry": {"coordinates":[3.9520089626,50.4567184448],"type":"Point"}
}