{
  "type": "Feature",
  "properties": {
    "iso:country":"BE",
    "sg:address":"Daverlostraat 81",
    "sg:city":"Brugge (assebroek)",
    "sg:classifiers":[
        {
            "category":"Farming",
            "subcategory":"Fish & Marine Products",
            "type":"Manufacturing & Wholesale Goods"
        }
    ],
    "sg:phone":"+32 50 35 62 67",
    "sg:postcode":"8310",
    "sg:province":"West-Vlaanderen",
    "sg:tags":[
        "retail",
        "-",
        "shellfish"
    ],
    "wof:name":"Vishandel Traiteur Vistje",
    "wof:placetype":"venue"
},
  "geometry": {"coordinates":[3.2383730412,51.2003974915],"type":"Point"}
}