{
  "type": "Feature",
  "properties": {
    "addr:full":"Hasseltsebaan 194 Hechtel-eksel (hechtel) Limburg 3940",
    "addr:housenumber":"194",
    "addr:postcode":"3940",
    "addr:street":"Hasseltsebaan",
    "iso:country":"BE",
    "sg:address":"Hasseltsebaan 194",
    "sg:city":"Hechtel-eksel (hechtel)",
    "sg:classifiers":[
        {
            "category":"Home & Garden",
            "subcategory":"Building Materials",
            "type":"Retail Goods"
        }
    ],
    "sg:phone":"+32 11 73 23 24",
    "sg:postcode":"3940",
    "sg:province":"Limburg",
    "sg:tags":[
        "window"
    ],
    "wof:name":"Kempische Metaalwerken Nv",
    "wof:placetype":"venue"
},
  "geometry": {"coordinates":[5.3758201599,51.0928688049],"type":"Point"}
}