{
  "type": "Feature",
  "properties": {
    "addr:full":"Rue Louis Bonte 6 Mouscron (herseaux) Hainaut 7712",
    "addr:housenumber":"6",
    "addr:postcode":"7712",
    "addr:street":"Rue Louis Bonte",
    "iso:country":"BE",
    "sg:address":"Rue Louis Bonte 6",
    "sg:city":"Mouscron (herseaux)",
    "sg:classifiers":[
        {
            "category":"Building & Trades",
            "subcategory":"Cleaning & Sanitation",
            "type":"Services"
        }
    ],
    "sg:phone":"+32 56 48 62 84",
    "sg:postcode":"7712",
    "sg:province":"Hainaut",
    "sg:tags":[
        "cleaner",
        "window"
    ],
    "wof:name":"Clean Carreaux",
    "wof:placetype":"venue"
},
  "geometry": {"coordinates":[3.231169939,50.7229003906],"type":"Point"}
}