{
  "type": "Feature",
  "properties": {
    "addr:full":"Tramstraat 31 Tielt West-Vlaanderen 8700",
    "addr:housenumber":"31",
    "addr:postcode":"8700",
    "addr:street":"Tramstraat",
    "iso:country":"BE",
    "sg:address":"Tramstraat 31",
    "sg:city":"Tielt",
    "sg:classifiers":[
        {
            "category":"Home & Garden",
            "subcategory":"Home Furnishings",
            "type":"Retail Goods"
        }
    ],
    "sg:phone":"+32 51 40 00 11",
    "sg:postcode":"8700",
    "sg:province":"West-Vlaanderen",
    "sg:tags":[
        "interior",
        "decoration"
    ],
    "wof:name":"Home Design",
    "wof:placetype":"venue"
},
  "geometry": {"coordinates":[3.329818964,51.0019645691],"type":"Point"}
}