{
  "type": "Feature",
  "properties": {
    "iso:country":"BE",
    "sg:address":"Place De Chablis 3",
    "sg:city":"Ferri\u00e8res",
    "sg:classifiers":[
        {
            "category":"Food & Beverages",
            "subcategory":"Supermarket",
            "type":"Retail Goods"
        }
    ],
    "sg:phone":"+32 86 40 02 27",
    "sg:postcode":"4190",
    "sg:province":"Li\u00e8ge",
    "sg:tags":[
        "department",
        "store"
    ],
    "wof:name":"Counasse & Cie",
    "wof:placetype":"venue"
},
  "geometry": {"coordinates":[5.6060638428,50.3999710083],"type":"Point"}
}