{
  "type": "Feature",
  "properties": {
    "iso:country":"BE",
    "sg:address":"Rue Joseph Weicker 3ba",
    "sg:city":"Etalle",
    "sg:orig_category":"Location de v\u00e9hicules sauf voitures. Eleveurs de bovins",
    "sg:phone":"+32 63 41 13 41",
    "sg:postcode":"6740",
    "sg:province":"Luxembourg",
    "wof:name":"Jean Rossignon",
    "wof:placetype":"venue"
},
  "geometry": {"coordinates":[5.5552310944,49.6996459961],"type":"Point"}
}