{
  "type": "Feature",
  "properties": {
    "iso:country":"BE",
    "sg:address":"Place Du March\u00c9 20",
    "sg:city":"Verviers",
    "sg:orig_category":"Transports terrestres de voyageurs. Agences de voyages",
    "sg:phone":"+32 87 34 00 41",
    "sg:postcode":"4800",
    "sg:province":"Li\u00e8ge",
    "wof:name":"Amicar",
    "wof:placetype":"venue"
},
  "geometry": {"coordinates":[5.8674988747,50.5931663513],"type":"Point"}
}