{
  "type": "Feature",
  "properties": {
    "iso:country":"BE",
    "sg:address":"Rue De La Fontaine 16",
    "sg:city":"Couvin (frasnes)",
    "sg:classifiers":[
        {
            "category":"Travel",
            "subcategory":"Hotels & Motels",
            "type":"Entertainment"
        }
    ],
    "sg:phone":"+32 60 31 14 31",
    "sg:postcode":"5660",
    "sg:province":"Namur",
    "sg:tags":[
        "supply",
        "hotels",
        "catering"
    ],
    "wof:name":"Maurenne",
    "wof:placetype":"venue"
},
  "geometry": {"coordinates":[4.5100121498,50.0792121887],"type":"Point"}
}