{
  "type": "Feature",
  "properties": {
    "addr:full":"Stokerijstraat 9 Zaventem Vlaams-Brabant 1930",
    "addr:housenumber":"9",
    "addr:postcode":"1930",
    "addr:street":"Stokerijstraat",
    "iso:country":"BE",
    "sg:address":"Stokerijstraat 9",
    "sg:city":"Zaventem",
    "sg:orig_category":"Gespecialiseerde residenti\u00eble bouw Woningbouw",
    "sg:phone":"+32 2 759 98 08",
    "sg:postcode":"1930",
    "sg:province":"Vlaams-Brabant",
    "wof:name":"Pierre Ogier",
    "wof:placetype":"venue"
},
  "geometry": {"coordinates":[4.5020198822,50.880607605],"type":"Point"}
}