{
  "type": "Feature",
  "properties": {
    "iso:country":"BE",
    "sg:address":"Conservatoriumplein 11",
    "sg:city":"Kortrijk",
    "sg:classifiers":[
        {
            "category":"Insurance",
            "subcategory":"Life Insurance",
            "type":"Services"
        }
    ],
    "sg:phone":"+32 56 21 10 58",
    "sg:postcode":"8500",
    "sg:province":"West-Vlaanderen",
    "sg:tags":[
        "assurance"
    ],
    "wof:name":"Bureau D'helf",
    "wof:placetype":"venue"
},
  "geometry": {"coordinates":[3.2600400448,50.8255805969],"type":"Point"}
}