{
  "type": "Feature",
  "properties": {
    "addr:full":"Zwaaikomstraat 4 Roeselare West-Vlaanderen 8800",
    "addr:housenumber":"4",
    "addr:postcode":"8800",
    "addr:street":"Zwaaikomstraat",
    "iso:country":"BE",
    "sg:address":"Zwaaikomstraat 4",
    "sg:city":"Roeselare",
    "sg:classifiers":[
        {
            "category":"Building & Trades",
            "subcategory":"Construction",
            "type":"Services"
        }
    ],
    "sg:phone":"+32 51 20 23 12",
    "sg:postcode":"8800",
    "sg:province":"West-Vlaanderen",
    "sg:tags":[
        "carpenter"
    ],
    "wof:name":"Vanacker Nv",
    "wof:placetype":"venue"
},
  "geometry": {"coordinates":[3.153126955,50.9496612549],"type":"Point"}
}