{
  "type": "Feature",
  "properties": {
    "addr:full":"Avenue Du Derby 61 Box 9 Bruxelles (ixelles) Bruxelles-Capitale 1050",
    "addr:housenumber":"61;9",
    "addr:postcode":"1050",
    "addr:street":"Avenue Du Derby;Box",
    "iso:country":"BE",
    "sg:address":"Avenue Du Derby 61 Box 9",
    "sg:city":"Bruxelles (ixelles)",
    "sg:classifiers":[
        {
            "category":"Professional",
            "subcategory":"Management & Consulting",
            "type":"Services"
        }
    ],
    "sg:phone":"+32 2 672 47 04",
    "sg:postcode":"1050",
    "sg:province":"Bruxelles-Capitale",
    "sg:tags":[
        "consultant",
        "agency",
        "advertising"
    ],
    "wof:name":"Victoria Communication",
    "wof:placetype":"venue"
},
  "geometry": {"coordinates":[4.390871048,50.8022842407],"type":"Point"}
}