{
  "type": "Feature",
  "properties": {
    "iso:country":"BE",
    "sg:address":"Kozenstraat 45",
    "sg:city":"Hasselt (stevoort)",
    "sg:classifiers":[
        {
            "category":"Retail",
            "subcategory":"Animal Services",
            "type":"Services"
        }
    ],
    "sg:phone":"+32 11 31 45 02",
    "sg:postcode":"3512",
    "sg:province":"Limburg",
    "sg:tags":[
        "grooming",
        "-",
        "dog"
    ],
    "wof:name":"Dog-style",
    "wof:placetype":"venue"
},
  "geometry": {"coordinates":[5.2462787628,50.9068832397],"type":"Point"}
}