{
  "type": "Feature",
  "properties": {
    "addr:full":"Elfenstraat 21 Mechelen Antwerpen 2800",
    "addr:housenumber":"21",
    "addr:postcode":"2800",
    "addr:street":"Elfenstraat",
    "iso:country":"BE",
    "sg:address":"Elfenstraat 21",
    "sg:city":"Mechelen",
    "sg:orig_category":"Werk and personeelsselectie",
    "sg:phone":"+32 15 34 32 05",
    "sg:postcode":"2800",
    "sg:province":"Antwerpen",
    "wof:name":"Din Consulting",
    "wof:placetype":"venue"
},
  "geometry": {"coordinates":[4.4826550484,51.0459938049],"type":"Point"}
}