{
  "type": "Feature",
  "properties": {
    "iso:country":"BE",
    "sg:address":"Bovenboekakker 6",
    "sg:city":"Wetteren",
    "sg:orig_category":"Biljart- and snookerzalen Sportterreinen and installaties behalve sportcentra",
    "sg:phone":"+32 9 369 92 27",
    "sg:postcode":"9230",
    "sg:province":"Oost-Vlaanderen",
    "wof:name":"Xanadu Bowling & Snooker",
    "wof:placetype":"venue"
},
  "geometry": {"coordinates":[3.8645200729,50.9988136292],"type":"Point"}
}