{
  "type": "Feature",
  "properties": {
    "addr:full":"Stadsheide 35 Hasselt Limburg 3500",
    "addr:housenumber":"35",
    "addr:postcode":"3500",
    "addr:street":"Stadsheide",
    "iso:country":"BE",
    "sg:address":"Stadsheide 35",
    "sg:city":"Hasselt",
    "sg:classifiers":[
        {
            "category":"Wholesale",
            "subcategory":"Wine & Distilled Alcoholic Beverages",
            "type":"Manufacturing & Wholesale Goods"
        }
    ],
    "sg:phone":"+32 11 29 99 02",
    "sg:postcode":"3500",
    "sg:province":"Limburg",
    "sg:tags":[
        "whol",
        "-",
        "spirit",
        "mfg"
    ],
    "wof:name":"Vandenplas Nv",
    "wof:placetype":"venue"
},
  "geometry": {"coordinates":[5.3703308105,50.9531707764],"type":"Point"}
}