{
  "type": "Feature",
  "properties": {
    "iso:country":"BE",
    "sg:address":"Rue Fons Vande Maele 15",
    "sg:city":"Bruxelles (evere)",
    "sg:classifiers":[
        {
            "category":"Parking",
            "subcategory":"Bicycle",
            "type":"Transportation"
        }
    ],
    "sg:phone":"+32 2 215 79 77",
    "sg:postcode":"1140",
    "sg:province":"Bruxelles-Capitale",
    "sg:tags":[
        "chiropodist"
    ],
    "wof:name":"Van Hecke",
    "wof:placetype":"venue"
},
  "geometry": {"coordinates":[4.3999872208,50.872467041],"type":"Point"}
}