{
  "type": "Feature",
  "properties": {
    "iso:country":"BE",
    "sg:address":"Rue De L'eglise 3",
    "sg:city":"Lontzen/lontzen",
    "sg:orig_category":"Ordinateurs and \u00e9quipement informatique",
    "sg:phone":"+32 87 88 25 06",
    "sg:postcode":"4710",
    "sg:province":"Li\u00e8ge",
    "wof:name":"Systemes Informatiques",
    "wof:placetype":"venue"
},
  "geometry": {"coordinates":[5.9820318222,50.6601104736],"type":"Point"}
}