{
  "type": "Feature",
  "properties": {
    "iso:country":"BE",
    "sg:address":"Essestraat 86",
    "sg:city":"Lede",
    "sg:orig_category":"Rundveehouders Varkenskwekers",
    "sg:phone":"+32 53 80 58 87",
    "sg:postcode":"9340",
    "sg:province":"Oost-Vlaanderen",
    "wof:name":"Dirk De Prez",
    "wof:placetype":"venue"
},
  "geometry": {"coordinates":[3.9331400394,50.9537086487],"type":"Point"}
}