{
  "type": "Feature",
  "properties": {
    "addr:full":"Avenue De La Wallonie 17 Leuze-en-hainaut Hainaut 7900",
    "addr:housenumber":"17",
    "addr:postcode":"7900",
    "addr:street":"Avenue De La Wallonie",
    "iso:country":"BE",
    "sg:address":"Avenue De La Wallonie 17",
    "sg:city":"Leuze-en-hainaut",
    "sg:classifiers":[
        {
            "category":"Bakery",
            "type":"Food & Drink"
        }
    ],
    "sg:phone":"+32 69 66 33 71",
    "sg:postcode":"7900",
    "sg:province":"Hainaut",
    "sg:tags":[
        "confectioner",
        "baker"
    ],
    "wof:name":"Eglantine",
    "wof:placetype":"venue"
},
  "geometry": {"coordinates":[3.6254899502,50.5958099365],"type":"Point"}
}