{
  "type": "Feature",
  "properties": {
    "addr:full":"Misstr 101 Lier Antwerpen 2500",
    "addr:housenumber":"101",
    "addr:postcode":"2500",
    "iso:country":"BE",
    "sg:address":"Misstr 101",
    "sg:city":"Lier",
    "sg:classifiers":[
        {
            "category":"Autos & Motor Vehicles",
            "subcategory":"Automobile Sales",
            "type":"Retail Goods"
        }
    ],
    "sg:phone":"+32 3 420 00 20",
    "sg:postcode":"2500",
    "sg:province":"Antwerpen",
    "sg:tags":[
        "equipment",
        "motor-cars",
        "transport"
    ],
    "wof:name":"Carrosserie Jan Engels Nv",
    "wof:placetype":"venue"
},
  "geometry": {"coordinates":[4.6151838303,51.1002044678],"type":"Point"}
}