{
  "type": "Feature",
  "properties": {
    "addr:full":"Avenue Plasky 144 Bruxelles Bruxelles-Capitale 1030",
    "addr:housenumber":"144",
    "addr:postcode":"1030",
    "addr:street":"Avenue Plasky",
    "iso:country":"BE",
    "sg:address":"Avenue Plasky 144",
    "sg:city":"Bruxelles",
    "sg:orig_category":"Produits chimiques Gr",
    "sg:phone":"+32 2 735 40 72",
    "sg:postcode":"1030",
    "sg:province":"Bruxelles-Capitale",
    "wof:name":"Keyser & Mackay",
    "wof:placetype":"venue"
},
  "geometry": {"coordinates":[4.396417141,50.8515892029],"type":"Point"}
}