{
  "type": "Feature",
  "properties": {
    "iso:country":"BE",
    "sg:address":"Sint-elisabethstraat 46",
    "sg:city":"Antwerpen",
    "sg:orig_category":"Verplichte sociale verzekeringen",
    "sg:phone":"+32 3 236 53 00",
    "sg:postcode":"2060",
    "sg:province":"Antwerpen",
    "wof:name":"Socialist. Mutualiteit",
    "wof:placetype":"venue"
},
  "geometry": {"coordinates":[4.4248871803,51.222820282],"type":"Point"}
}