{
  "type": "Feature",
  "properties": {
    "iso:country":"BE",
    "sg:address":"Georges Wittouckstraat 215",
    "sg:city":"Sint-pieters-leeuw",
    "sg:orig_category":"Slagers",
    "sg:phone":"+32 2 377 57 96",
    "sg:postcode":"1600",
    "sg:province":"Vlaams-Brabant",
    "wof:name":"B. Herremans",
    "wof:placetype":"venue"
},
  "geometry": {"coordinates":[4.2718482018,50.7874641418],"type":"Point"}
}