{
  "type": "Feature",
  "properties": {
    "iso:country":"BE",
    "sg:address":"Avenue Albert 208",
    "sg:city":"Vorst",
    "sg:orig_category":"Agences d'exp\u00e9dition",
    "sg:phone":"+32 2 346 00 73",
    "sg:postcode":"1190",
    "sg:province":"Bruxelles-Capitale",
    "wof:name":"Proter",
    "wof:placetype":"venue"
},
  "geometry": {"coordinates":[4.3471179008,50.8161888123],"type":"Point"}
}