{
  "type": "Feature",
  "properties": {
    "addr:full":"Kuringersteenweg 103 Hasselt Limburg 3500",
    "addr:housenumber":"103",
    "addr:postcode":"3500",
    "addr:street":"Kuringersteenweg",
    "iso:country":"BE",
    "sg:address":"Kuringersteenweg 103",
    "sg:city":"Hasselt",
    "sg:classifiers":[
        {
            "category":"Personal",
            "subcategory":"Beauty Salon",
            "type":"Services"
        }
    ],
    "sg:phone":"+32 11 25 34 79",
    "sg:postcode":"3500",
    "sg:province":"Limburg",
    "sg:tags":[
        "de",
        "coiffure"
    ],
    "wof:name":"Coiffure Georges",
    "wof:placetype":"venue"
},
  "geometry": {"coordinates":[5.3240551949,50.9341163635],"type":"Point"}
}