{
  "type": "Feature",
  "properties": {
    "iso:country":"BE",
    "sg:address":"Dorpstraat 52",
    "sg:city":"Ichtegem",
    "sg:orig_category":"Elektrische installaties voor woningen Huishoudapparaten, televisies and radio's",
    "sg:phone":"+32 50 81 11 72",
    "sg:postcode":"8480",
    "sg:province":"West-Vlaanderen",
    "wof:name":"Johnny Vanhee",
    "wof:placetype":"venue"
},
  "geometry": {"coordinates":[3.0506010056,51.1585159302],"type":"Point"}
}