{
  "type": "Feature",
  "properties": {
    "addr:full":"Testeltsesteenweg 33 Scherpenheuvel-zichem Vlaams-Brabant 3271",
    "addr:housenumber":"33",
    "addr:postcode":"3271",
    "addr:street":"Testeltsesteenweg",
    "iso:country":"BE",
    "sg:address":"Testeltsesteenweg 33",
    "sg:city":"Scherpenheuvel-zichem",
    "sg:orig_category":"Artsen and specialisten",
    "sg:phone":"+32 13 77 35 90",
    "sg:postcode":"3271",
    "sg:province":"Vlaams-Brabant",
    "wof:name":"P. Peeters",
    "wof:placetype":"venue"
},
  "geometry": {"coordinates":[4.9686698914,51.0227088928],"type":"Point"}
}