{
  "type": "Feature",
  "properties": {
    "iso:country":"BE",
    "sg:address":"Avenue Arthur Dezangr\u00e9 3",
    "sg:city":"Kraainem",
    "sg:classifiers":[
        {
            "category":"Home & Garden",
            "subcategory":"Building Materials",
            "type":"Retail Goods"
        }
    ],
    "sg:phone":"+32 2 725 64 60",
    "sg:postcode":"1950",
    "sg:province":"Vlaams-Brabant",
    "sg:tags":[
        "window"
    ],
    "wof:name":"Weldimo Group Sa",
    "wof:placetype":"venue"
},
  "geometry": {"coordinates":[4.4671401978,50.8616905212],"type":"Point"}
}