{
  "type": "Feature",
  "properties": {
    "addr:full":"Lozenberg 18 Zaventem (sint-stevens-woluwe) Vlaams-Brabant 1932",
    "addr:housenumber":"18",
    "addr:postcode":"1932",
    "addr:street":"Lozenberg",
    "iso:country":"BE",
    "sg:address":"Lozenberg 18",
    "sg:city":"Zaventem (sint-stevens-woluwe)",
    "sg:classifiers":[
        {
            "category":"Professional",
            "subcategory":"Management & Consulting",
            "type":"Services"
        }
    ],
    "sg:phone":"+32 2 721 51 28",
    "sg:postcode":"1932",
    "sg:province":"Vlaams-Brabant",
    "sg:tags":[
        "consultant"
    ],
    "wof:name":"D.c.e. Consultants Nv",
    "wof:placetype":"venue"
},
  "geometry": {"coordinates":[4.4598970413,50.8684883118],"type":"Point"}
}