{
  "type": "Feature",
  "properties": {
    "addr:full":"Rue Saint-l\u00e9onard 23 Li\u00e8ge 1 Li\u00e8ge 4000",
    "addr:housenumber":"23;1",
    "addr:postcode":"4000",
    "addr:street":"Rue Saint-Le\u0301Onard",
    "iso:country":"BE",
    "sg:address":"Rue Saint-l\u00e9onard 23",
    "sg:city":"Li\u00e8ge 1",
    "sg:classifiers":[
        {
            "category":"Social Services",
            "subcategory":"Child Care",
            "type":"Services"
        }
    ],
    "sg:phone":"+32 4 227 81 01",
    "sg:postcode":"4000",
    "sg:province":"Li\u00e8ge",
    "sg:tags":[
        "baby",
        "nursery",
        "day",
        "sitting"
    ],
    "wof:name":"Maison Marrante (la)",
    "wof:placetype":"venue"
},
  "geometry": {"coordinates":[5.5870018005,50.648399353],"type":"Point"}
}