{
  "type": "Feature",
  "properties": {
    "iso:country":"BE",
    "sg:address":"Oostrozebeekstraat",
    "sg:city":"Meulebeke",
    "sg:orig_category":"Non-Classified Establishments",
    "sg:phone":"+32 51 48 90 45",
    "sg:postcode":"8760",
    "sg:province":"West-Vlaanderen",
    "wof:name":"Sagaert Leon N.v.",
    "wof:placetype":"venue"
},
  "geometry": {"coordinates":[3.2939369678,50.9431991577],"type":"Point"}
}