{
  "type": "Feature",
  "properties": {
    "addr:full":"Groene Hofstraat 10 Boom Antwerpen 2850",
    "addr:housenumber":"10",
    "addr:postcode":"2850",
    "addr:street":"Groene Hofstraat",
    "iso:country":"BE",
    "sg:address":"Groene Hofstraat 10",
    "sg:city":"Boom",
    "sg:classifiers":[
        {
            "category":"Cafe",
            "type":"Food & Drink"
        }
    ],
    "sg:phone":"+32 3 888 68 68",
    "sg:postcode":"2850",
    "sg:province":"Antwerpen",
    "sg:tags":[
        "caf\u00e9s"
    ],
    "wof:name":"Parochiecentrum O.l.vrouw",
    "wof:placetype":"venue"
},
  "geometry": {"coordinates":[4.3652391434,51.085193634],"type":"Point"}
}