{
  "type": "Feature",
  "properties": {
    "iso:country":"BE",
    "sg:address":"18",
    "sg:city":"Rue Van Bergen 1081 Bruxelles",
    "sg:classifiers":[
        {
            "category":"Bakery",
            "type":"Food & Drink"
        }
    ],
    "sg:phone":"+32 2 414 27 45",
    "sg:postcode":"18",
    "sg:tags":[
        "cake",
        "product",
        "related",
        "bread"
    ],
    "wof:name":"Mannedor Sa",
    "wof:placetype":"venue"
},
  "geometry": {"coordinates":[4.3313798904,50.8615341187],"type":"Point"}
}