{
  "type": "Feature",
  "properties": {
    "addr:full":"Terheidedreef 47 Schoten Antwerpen 2900",
    "addr:housenumber":"47",
    "addr:postcode":"2900",
    "addr:street":"Terheidedreef",
    "iso:country":"BE",
    "sg:address":"Terheidedreef 47",
    "sg:city":"Schoten",
    "sg:classifiers":[
        {
            "category":"Professional",
            "subcategory":"Accounting & Tax Preparation",
            "type":"Services"
        }
    ],
    "sg:phone":"+32 3 663 20 22",
    "sg:postcode":"2900",
    "sg:province":"Antwerpen",
    "sg:tags":[
        "accountant"
    ],
    "wof:name":"Berckmoes G",
    "wof:placetype":"venue"
},
  "geometry": {"coordinates":[4.5428957939,51.3012504578],"type":"Point"}
}