{
  "type": "Feature",
  "properties": {
    "addr:full":"Pelgrimsplein 35 Arendonk Antwerpen 2370",
    "addr:housenumber":"35",
    "addr:postcode":"2370",
    "addr:street":"Pelgrimsplein",
    "iso:country":"BE",
    "sg:address":"Pelgrimsplein 35",
    "sg:city":"Arendonk",
    "sg:orig_category":"Enseignement maternel and primaire",
    "sg:phone":"+32 14 67 82 73",
    "sg:postcode":"2370",
    "sg:province":"Antwerpen",
    "wof:name":"B.s.g.o. De Wamp",
    "wof:placetype":"venue"
},
  "geometry": {"coordinates":[5.0986890793,51.3348808289],"type":"Point"}
}