{
  "type": "Feature",
  "properties": {
    "addr:full":"Quai De Meuse 44-5 Namur (jambes) Namur 5100",
    "addr:housenumber":"44-5",
    "addr:postcode":"5100",
    "addr:street":"Quai De Meuse",
    "iso:country":"BE",
    "sg:address":"Quai De Meuse 44-5",
    "sg:city":"Namur (jambes)",
    "sg:classifiers":[
        {
            "category":"Health Services",
            "subcategory":"Doctor",
            "type":"Services"
        }
    ],
    "sg:phone":"+32 81 31 27 86",
    "sg:postcode":"5100",
    "sg:province":"Namur",
    "sg:tags":[
        "medicinephysicians",
        "surgeon"
    ],
    "wof:name":"Blouard P",
    "wof:placetype":"venue"
},
  "geometry": {"coordinates":[4.8713750839,50.4566345215],"type":"Point"}
}