{
  "type": "Feature",
  "properties": {
    "iso:country":"BE",
    "sg:address":"Avenue Du Centenaire 56c",
    "sg:city":"Charleroi (montignies-sur-sambre)",
    "sg:classifiers":[
        {
            "category":"Personal",
            "subcategory":"Beauty Salon",
            "type":"Services"
        }
    ],
    "sg:phone":"+32 71 31 54 07",
    "sg:postcode":"6061",
    "sg:province":"Hainaut",
    "sg:tags":[
        "lady",
        "-",
        "hairdressing"
    ],
    "wof:name":"New Style (galerie Mestdagh)",
    "wof:placetype":"venue"
},
  "geometry": {"coordinates":[4.4790301323,50.4029769897],"type":"Point"}
}