{
  "type": "Feature",
  "properties": {
    "iso:country":"BE",
    "sg:address":"Leopold Ii Laan 41",
    "sg:city":"Dendermonde",
    "sg:orig_category":"Tijdelijke werkgelegenheid and uitzendkantoren",
    "sg:phone":"+32 52 22 15 75",
    "sg:postcode":"9200",
    "sg:province":"Oost-Vlaanderen",
    "wof:name":"Creyf\u00b4s Interim",
    "wof:placetype":"venue"
},
  "geometry": {"coordinates":[4.1039319038,51.0272026062],"type":"Point"}
}