{
  "type": "Feature",
  "properties": {
    "addr:full":"Rue De Wytschaete 18 Komen-waasten/comines-warneton Hainaut 7781",
    "addr:housenumber":"18;7781",
    "addr:street":"Rue De Wytschaete",
    "iso:country":"BE",
    "sg:address":"Rue De Wytschaete 18",
    "sg:city":"Komen-waasten/comines-warneton",
    "sg:orig_category":"Boissons",
    "sg:phone":"+32 56 55 56 19",
    "sg:postcode":"7781",
    "sg:province":"Hainaut",
    "wof:name":"Luc Duthois",
    "wof:placetype":"venue"
},
  "geometry": {"coordinates":[2.9591751099,50.7852554321],"type":"Point"}
}