{
  "type": "Feature",
  "properties": {
    "addr:full":"Consciencestraat 45 Blankenberge West-Vlaanderen 8370",
    "addr:housenumber":"45",
    "addr:postcode":"8370",
    "addr:street":"Consciencestraat",
    "iso:country":"BE",
    "sg:address":"Consciencestraat 45",
    "sg:city":"Blankenberge",
    "sg:classifiers":[
        {
            "category":"Travel",
            "subcategory":"Hotels & Motels",
            "type":"Entertainment"
        }
    ],
    "sg:phone":"+32 50 41 13 49",
    "sg:postcode":"8370",
    "sg:province":"West-Vlaanderen",
    "wof:name":"Albatros",
    "wof:placetype":"venue"
},
  "geometry": {"coordinates":[3.1253619194,51.3141441345],"type":"Point"}
}