{
  "type": "Feature",
  "properties": {
    "addr:full":"Vanderaeylaan 70 Ukkel/uccle Bruxelles-Capitale 1180",
    "addr:housenumber":"70",
    "addr:postcode":"1180",
    "addr:street":"Vanderaeylaan;/",
    "iso:country":"BE",
    "sg:address":"Vanderaeylaan 70",
    "sg:city":"Ukkel/uccle",
    "sg:orig_category":"Advocaten and juridische adviseurs",
    "sg:phone":"+32 2 356 57 68",
    "sg:postcode":"1180",
    "sg:province":"Bruxelles-Capitale",
    "wof:name":"Gr. Van Witzenburg",
    "wof:placetype":"venue"
},
  "geometry": {"coordinates":[4.3388190269,50.7962112427],"type":"Point"}
}