{
  "type": "Feature",
  "properties": {
    "iso:country":"BE",
    "sg:address":"Persijzerstraat 10",
    "sg:city":"Lochristi (zaffelare)",
    "sg:classifiers":[
        {
            "category":"Manufacturing",
            "subcategory":"Textiles",
            "type":"Manufacturing & Wholesale Goods"
        }
    ],
    "sg:phone":"+32 9 355 59 64",
    "sg:postcode":"9080",
    "sg:province":"Oost-Vlaanderen",
    "sg:tags":[
        "retail",
        "-"
    ],
    "wof:name":"Verniers M",
    "wof:placetype":"venue"
},
  "geometry": {"coordinates":[3.8830471039,51.1261062622],"type":"Point"}
}