{
  "type": "Feature",
  "properties": {
    "addr:full":"Bergensesteenweg 518 Halle Vlaams-Brabant 1502",
    "addr:housenumber":"518;1502",
    "addr:street":"Bergensesteenweg",
    "iso:country":"BE",
    "sg:address":"Bergensesteenweg 518",
    "sg:city":"Halle",
    "sg:orig_category":"Traitement and rev\u00eatement des m\u00e9taux",
    "sg:phone":"+32 2 360 10 65",
    "sg:postcode":"1502",
    "sg:province":"Vlaams-Brabant",
    "wof:name":"Ferrodur",
    "wof:placetype":"venue"
},
  "geometry": {"coordinates":[4.223470211,50.719291687],"type":"Point"}
}