{
  "type": "Feature",
  "properties": {
    "addr:full":"Poperingseweg 137 Ieper West-Vlaanderen 8900",
    "addr:housenumber":"137",
    "addr:postcode":"8900",
    "addr:street":"Poperingseweg",
    "iso:country":"BE",
    "sg:address":"Poperingseweg 137",
    "sg:city":"Ieper",
    "sg:classifiers":[
        {
            "category":"Home & Garden",
            "subcategory":"Home Furnishings",
            "type":"Retail Goods"
        }
    ],
    "sg:phone":"+32 57 20 21 29",
    "sg:postcode":"8900",
    "sg:province":"West-Vlaanderen",
    "sg:tags":[
        "-",
        "furniture"
    ],
    "wof:name":"Fleurbaey M",
    "wof:placetype":"venue"
},
  "geometry": {"coordinates":[2.8611829281,50.8495407104],"type":"Point"}
}