{
  "type": "Feature",
  "properties": {
    "addr:full":"Kerkeweg 34 Jabbeke (snellegem) West-Vlaanderen 8490",
    "addr:housenumber":"34",
    "addr:postcode":"8490",
    "addr:street":"Kerkeweg",
    "iso:country":"BE",
    "sg:address":"Kerkeweg 34",
    "sg:city":"Jabbeke (snellegem)",
    "sg:classifiers":[
        {
            "category":"Personal",
            "subcategory":"Beauty Salon",
            "type":"Services"
        }
    ],
    "sg:phone":"+32 50 81 31 80",
    "sg:postcode":"8490",
    "sg:province":"West-Vlaanderen",
    "sg:tags":[
        "lady",
        "-",
        "hairdressing"
    ],
    "wof:name":"Alysee",
    "wof:placetype":"venue"
},
  "geometry": {"coordinates":[3.1236360073,51.1721839905],"type":"Point"}
}