{
  "type": "Feature",
  "properties": {
    "addr:full":"Liebroekstraat 57 Halen Limburg 3545",
    "addr:housenumber":"57",
    "addr:postcode":"3545",
    "addr:street":"Liebroekstraat",
    "iso:country":"BE",
    "sg:address":"Liebroekstraat 57",
    "sg:city":"Halen",
    "sg:orig_category":"Fietsen Motorfietsen",
    "sg:phone":"+32 13 44 13 78",
    "sg:postcode":"3545",
    "sg:province":"Limburg",
    "wof:name":"Jacobs Guido",
    "wof:placetype":"venue"
},
  "geometry": {"coordinates":[5.0907502174,50.9548301697],"type":"Point"}
}