{
  "type": "Feature",
  "properties": {
    "addr:full":"Hoogstraatsesteenweg 51 Rijkevorsel Antwerpen 2310",
    "addr:housenumber":"51",
    "addr:postcode":"2310",
    "addr:street":"Hoogstraatsesteenweg",
    "iso:country":"BE",
    "sg:address":"Hoogstraatsesteenweg 51",
    "sg:city":"Rijkevorsel",
    "sg:classifiers":[
        {
            "category":"Retail",
            "subcategory":"Repair Shop",
            "type":"Services"
        }
    ],
    "sg:phone":"+32 3 314 43 85",
    "sg:postcode":"2310",
    "sg:province":"Antwerpen",
    "wof:name":"Willebrords P",
    "wof:placetype":"venue"
},
  "geometry": {"coordinates":[4.7596302032,51.3536949158],"type":"Point"}
}