{
  "type": "Feature",
  "properties": {
    "iso:country":"BE",
    "sg:address":"Poelkapellestraat 50",
    "sg:city":"Langemark-poelkapelle",
    "sg:orig_category":"Banques and organismes de cr\u00e9dit",
    "sg:phone":"+32 57 48 88 85",
    "sg:postcode":"8920",
    "sg:province":"West-Vlaanderen",
    "wof:name":"Centea",
    "wof:placetype":"venue"
},
  "geometry": {"coordinates":[2.919770956,50.9132423401],"type":"Point"}
}