{
  "type": "Feature",
  "properties": {
    "iso:country":"BE",
    "sg:address":"Veldstraat 6",
    "sg:city":"Etterbeek",
    "sg:orig_category":"Voedingsspeciaalzaken",
    "sg:phone":"+32 2 648 17 37",
    "sg:postcode":"1040",
    "sg:province":"Bruxelles-Capitale",
    "wof:name":"Restolux",
    "wof:placetype":"venue"
},
  "geometry": {"coordinates":[4.3905081749,50.8303947449],"type":"Point"}
}