{
  "type": "Feature",
  "properties": {
    "iso:country":"BE",
    "sg:address":"Generaal Dempseylaan 23",
    "sg:city":"Hamont-achel",
    "sg:classifiers":[
        {
            "category":"Fast Food",
            "type":"Food & Drink"
        }
    ],
    "sg:phone":"+32 11 80 18 61",
    "sg:postcode":"3930",
    "sg:province":"Limburg",
    "sg:tags":[
        "\u00c0",
        "emporter",
        "restaurants"
    ],
    "wof:name":"Restaurant Mec Harrie",
    "wof:placetype":"venue"
},
  "geometry": {"coordinates":[5.4780278206,51.257598877],"type":"Point"}
}