{
  "type": "Feature",
  "properties": {
    "addr:full":"Waterloose Steenweg 172 Sint-gillis/saint-gilles Bruxelles-Capitale 1060",
    "addr:housenumber":"172",
    "addr:postcode":"1060",
    "addr:street":"Waterloose Steenweg",
    "iso:country":"BE",
    "sg:address":"Waterloose Steenweg 172",
    "sg:city":"Sint-gillis/saint-gilles",
    "sg:orig_category":"Schoonheidssalons",
    "sg:phone":"+32 2 538 42 69",
    "sg:postcode":"1060",
    "sg:province":"Bruxelles-Capitale",
    "wof:name":"Institut De Beaut\u00c9 D.s.",
    "wof:placetype":"venue"
},
  "geometry": {"coordinates":[4.3445701599,50.8277702332],"type":"Point"}
}