{
  "type": "Feature",
  "properties": {
    "iso:country":"BE",
    "sg:address":"Chemin Du Rosoir 8",
    "sg:city":"Braine-le-chateau",
    "sg:orig_category":"Rev\u00eatements de sols and murs. Installation de menuiserie en bois and plastique",
    "sg:phone":"+32 2 366 98 07",
    "sg:postcode":"1440",
    "sg:province":"Brabant Wallon",
    "wof:name":"Selen Luc",
    "wof:placetype":"venue"
},
  "geometry": {"coordinates":[4.3178668022,50.6809425354],"type":"Point"}
}