{
  "type": "Feature",
  "properties": {
    "iso:country":"BE",
    "sg:address":"Aachenerstrasse 218",
    "sg:city":"Raeren",
    "sg:orig_category":"Decoratiestoffen and buitenhuistextiel Fab",
    "sg:phone":"+32 87 65 63 66",
    "sg:postcode":"4730",
    "sg:province":"Li\u00e8ge",
    "wof:name":"Carpro",
    "wof:placetype":"venue"
},
  "geometry": {"coordinates":[6.0676717758,50.667427063],"type":"Point"}
}