{
  "type": "Feature",
  "properties": {
    "addr:full":"Rue D'anderlues 178 Thuin Hainaut 6530",
    "addr:housenumber":"178",
    "addr:postcode":"6530",
    "addr:street":"Rue D'Anderlues",
    "iso:country":"BE",
    "sg:address":"Rue D'anderlues 178",
    "sg:city":"Thuin",
    "sg:orig_category":"Tankcleaning",
    "sg:phone":"+32 71 59 34 64",
    "sg:postcode":"6530",
    "sg:province":"Hainaut",
    "wof:name":"Huaux B",
    "wof:placetype":"venue"
},
  "geometry": {"coordinates":[4.2812008858,50.3556175232],"type":"Point"}
}