{
  "type": "Feature",
  "properties": {
    "iso:country":"BE",
    "sg:address":"Fernand Van Baelstraat 3",
    "sg:city":"Leopoldsburg",
    "sg:classifiers":[
        {
            "category":"Professional",
            "subcategory":"Lawyer & Legal Services",
            "type":"Services"
        }
    ],
    "sg:phone":"+32 11 34 27 34",
    "sg:postcode":"3970",
    "sg:province":"Limburg",
    "wof:name":"Vandewalle B\u00e9n\u00e9dicte",
    "wof:placetype":"venue"
},
  "geometry": {"coordinates":[5.2535638809,51.1149177551],"type":"Point"}
}