{
  "type": "Feature",
  "properties": {
    "iso:country":"BE",
    "sg:address":"Rue Montjoie 41",
    "sg:city":"Eupen",
    "sg:orig_category":"Installation de menuiserie m\u00e9tallique. Constructions r\u00e9sidentielles sp\u00e9cifiques",
    "sg:phone":"+32 87 56 09 50",
    "sg:postcode":"4700",
    "sg:province":"Li\u00e8ge",
    "wof:name":"Euro-fencing",
    "wof:placetype":"venue"
},
  "geometry": {"coordinates":[6.0332789421,50.6290283203],"type":"Point"}
}