{
  "type": "Feature",
  "properties": {
    "iso:country":"BE",
    "sg:address":"Belseledorp 142",
    "sg:city":"Sint-niklaas",
    "sg:orig_category":"Banken and kredietinstellingen",
    "sg:phone":"+32 3 772 30 98",
    "sg:postcode":"9111",
    "sg:province":"Oost-Vlaanderen",
    "wof:name":"Centea",
    "wof:placetype":"venue"
},
  "geometry": {"coordinates":[4.0812849998,51.1438179016],"type":"Point"}
}