{
  "type": "Feature",
  "properties": {
    "iso:country":"BE",
    "sg:address":"Van Hoorebekeplaats 16",
    "sg:city":"Eeklo",
    "sg:orig_category":"Kapsalons",
    "sg:phone":"+32 9 377 65 05",
    "sg:postcode":"9900",
    "sg:province":"Oost-Vlaanderen",
    "wof:name":"Coiffure Art & Style",
    "wof:placetype":"venue"
},
  "geometry": {"coordinates":[3.564344883,51.1861801147],"type":"Point"}
}