{
  "type": "Feature",
  "properties": {
    "iso:country":"BE",
    "sg:address":"Koekhoven 44",
    "sg:city":"Merksplas",
    "sg:orig_category":"Fruitteelt Rundveehouders Varkenskwekers",
    "sg:phone":"+32 14 63 31 34",
    "sg:postcode":"2330",
    "sg:province":"Antwerpen",
    "wof:name":"Karel Quirynen",
    "wof:placetype":"venue"
},
  "geometry": {"coordinates":[4.899450779,51.3722381592],"type":"Point"}
}