{
  "type": "Feature",
  "properties": {
    "addr:full":"Rue C\u00c9sar De Paepe 128 Charleroi Hainaut 6040",
    "addr:housenumber":"128",
    "addr:postcode":"6040",
    "addr:street":"Rue Ce\u0301Sar De Paepe;Hainaut",
    "iso:country":"BE",
    "sg:address":"Rue C\u00c9sar De Paepe 128",
    "sg:city":"Charleroi",
    "sg:classifiers":[
        {
            "category":"Fast Food",
            "type":"Food & Drink"
        }
    ],
    "sg:phone":"+32 71 37 40 78",
    "sg:postcode":"6040",
    "sg:province":"Hainaut",
    "sg:tags":[
        "meeneem",
        "restaurant"
    ],
    "wof:name":"Le Garby",
    "wof:placetype":"venue"
},
  "geometry": {"coordinates":[4.4134068489,50.4354820251],"type":"Point"}
}