{
  "type": "Feature",
  "properties": {
    "addr:full":"Dorp 39 Ravels Antwerpen 2382",
    "addr:housenumber":"39",
    "addr:postcode":"2382",
    "addr:street":"Dorp",
    "iso:country":"BE",
    "sg:address":"Dorp 39",
    "sg:city":"Ravels",
    "sg:orig_category":"Banques and organismes de cr\u00e9dit",
    "sg:phone":"+32 14 65 01 01",
    "sg:postcode":"2382",
    "sg:province":"Antwerpen",
    "wof:name":"Kbc",
    "wof:placetype":"venue"
},
  "geometry": {"coordinates":[5.041768074,51.4469108582],"type":"Point"}
}