{
  "type": "Feature",
  "properties": {
    "addr:full":"Rue De Wibrin 7 Houffalize Luxembourg 6660",
    "addr:housenumber":"7",
    "addr:postcode":"6660",
    "addr:street":"Rue De Wibrin",
    "iso:country":"BE",
    "sg:address":"Rue De Wibrin 7",
    "sg:city":"Houffalize",
    "sg:orig_category":"Rundveehouders",
    "sg:phone":"+32 61 28 86 01",
    "sg:postcode":"6660",
    "sg:province":"Luxembourg",
    "wof:name":"La Grange",
    "wof:placetype":"venue"
},
  "geometry": {"coordinates":[5.7902050018,50.1322784424],"type":"Point"}
}