{
  "type": "Feature",
  "properties": {
    "iso:country":"BE",
    "sg:address":"Jacob Smitslaan 69",
    "sg:city":"Aartselaar",
    "sg:classifiers":[
        {
            "category":"Cafe",
            "type":"Food & Drink"
        }
    ],
    "sg:phone":"+32 3 887 05 55",
    "sg:postcode":"2630",
    "sg:province":"Antwerpen",
    "sg:tags":[
        "caf\u00e9s"
    ],
    "wof:name":"Joannes Hendrickx",
    "wof:placetype":"venue"
},
  "geometry": {"coordinates":[4.3807621002,51.1396636963],"type":"Point"}
}