{
  "type": "Feature",
  "properties": {
    "addr:full":"Rue Des Vennes 36 Li\u00c8ge Li\u00e8ge 4020",
    "addr:housenumber":"36",
    "addr:postcode":"4020",
    "addr:street":"Rue Des Vennes",
    "iso:country":"BE",
    "sg:address":"Rue Des Vennes 36",
    "sg:city":"Li\u00c8ge",
    "sg:orig_category":"Blanchisseries and teintureries",
    "sg:phone":"+32 4 342 32 60",
    "sg:postcode":"4020",
    "sg:province":"Li\u00e8ge",
    "wof:name":"La Grande Laverie Vennes",
    "wof:placetype":"venue"
},
  "geometry": {"coordinates":[5.5810427666,50.6280517578],"type":"Point"}
}