{
  "type": "Feature",
  "properties": {
    "iso:country":"BE",
    "sg:address":"Volkstraat 36",
    "sg:city":"Antwerpen",
    "sg:classifiers":[
        {
            "category":"Shopping",
            "subcategory":"Hobbies, Toys, & Games",
            "type":"Retail Goods"
        }
    ],
    "sg:phone":"+32 3 216 96 26",
    "sg:postcode":"2000",
    "sg:province":"Antwerpen",
    "sg:tags":[
        "toy",
        "-"
    ],
    "wof:name":"Jojo",
    "wof:placetype":"venue"
},
  "geometry": {"coordinates":[4.3956580162,51.2110176086],"type":"Point"}
}