{
  "type": "Feature",
  "properties": {
    "addr:full":"Onledemolenstraat 57 Roeselare West-Vlaanderen 8800",
    "addr:housenumber":"57",
    "addr:postcode":"8800",
    "addr:street":"Onledemolenstraat",
    "iso:country":"BE",
    "sg:address":"Onledemolenstraat 57",
    "sg:city":"Roeselare",
    "sg:classifiers":[
        {
            "category":"Cafe",
            "type":"Food & Drink"
        }
    ],
    "sg:phone":"+32 51 20 48 54",
    "sg:postcode":"8800",
    "sg:province":"West-Vlaanderen",
    "sg:tags":[
        "caf\u00e9s"
    ],
    "wof:name":"Rosa Declercq",
    "wof:placetype":"venue"
},
  "geometry": {"coordinates":[3.1422600746,50.9804191589],"type":"Point"}
}