{
  "type": "Feature",
  "properties": {
    "iso:country":"BE",
    "sg:address":"Rue Raoul Warocqu\u00c9 32",
    "sg:city":"Morlanwelz",
    "sg:orig_category":"Elektrische installaties voor woningen",
    "sg:phone":"+32 64 44 62 09",
    "sg:postcode":"7140",
    "sg:province":"Hainaut",
    "wof:name":"Industrielle Electricit\u00c9",
    "wof:placetype":"venue"
},
  "geometry": {"coordinates":[4.2437529564,50.4566421509],"type":"Point"}
}