{
  "type": "Feature",
  "properties": {
    "iso:country":"BE",
    "sg:address":"Witte Hoeve 14",
    "sg:city":"Laakdal (veerle)",
    "sg:classifiers":[
        {
            "category":"Communications",
            "type":"Services"
        }
    ],
    "sg:phone":"+32 14 30 23 53",
    "sg:postcode":"2431",
    "sg:province":"Antwerpen",
    "sg:tags":[
        "translator"
    ],
    "wof:name":"Vertaalbureau Elly Slegers",
    "wof:placetype":"venue"
},
  "geometry": {"coordinates":[4.9811577797,51.0540657043],"type":"Point"}
}