{
  "type": "Feature",
  "properties": {
    "iso:country":"BE",
    "sg:address":"Alice Nahonstraat 4",
    "sg:city":"Putte",
    "sg:orig_category":"Werk and personeelsselectie",
    "sg:phone":"+32 15 76 78 96",
    "sg:postcode":"2580",
    "sg:province":"Antwerpen",
    "wof:name":"Pwa Putte",
    "wof:placetype":"venue"
},
  "geometry": {"coordinates":[4.6302552223,51.0567779541],"type":"Point"}
}