{
  "type": "Feature",
  "properties": {
    "addr:full":"Lutselusplein 10 Box 2 Diepenbeek Limburg 3590",
    "addr:housenumber":"10;2",
    "addr:postcode":"3590",
    "addr:street":"Lutselusplein;Box",
    "iso:country":"BE",
    "sg:address":"Lutselusplein 10 Box 2",
    "sg:city":"Diepenbeek",
    "sg:classifiers":[
        {
            "category":"Banks & Credit Unions",
            "subcategory":"Investment Brokerage",
            "type":"Services"
        }
    ],
    "sg:phone":"+32 11 33 27 92",
    "sg:postcode":"3590",
    "sg:province":"Limburg",
    "sg:tags":[
        "auditor"
    ],
    "wof:name":"Claes G",
    "wof:placetype":"venue"
},
  "geometry": {"coordinates":[5.4385452271,50.9090995789],"type":"Point"}
}