{
  "type": "Feature",
  "properties": {
    "iso:country":"BE",
    "sg:address":"Wasstraat 4",
    "sg:city":"Gent",
    "sg:orig_category":"Activit\u00e9s diverses d'imprimerie",
    "sg:phone":"+32 9 238 21 77",
    "sg:postcode":"9000",
    "sg:province":"Oost-Vlaanderen",
    "wof:name":"E.v.h.",
    "wof:placetype":"venue"
},
  "geometry": {"coordinates":[3.7439548969,51.0566902161],"type":"Point"}
}