{
  "type": "Feature",
  "properties": {
    "iso:country":"BE",
    "sg:address":"R. De L' Institut 87a",
    "sg:city":"Rixensart",
    "sg:classifiers":[
        {
            "category":"Health Services",
            "subcategory":"Medical Lab",
            "type":"Services"
        }
    ],
    "sg:phone":"+32 2 655 07 11",
    "sg:postcode":"1330",
    "sg:province":"Brabant Wallon",
    "sg:tags":[
        "chemical",
        "pharmaceutical",
        "pharmacy"
    ],
    "wof:name":"Phibro Animal Health Sprl",
    "wof:placetype":"venue"
},
  "geometry": {"coordinates":[4.52810812,50.7233428955],"type":"Point"}
}