{
  "type": "Feature",
  "properties": {
    "iso:country":"BE",
    "sg:address":"Rue Stordoir 1",
    "sg:city":"Gembloux",
    "sg:orig_category":"Beheer van afvalopslag- and stortplaatsen",
    "sg:phone":"+32 81 61 61 15",
    "sg:postcode":"5030",
    "sg:province":"Namur",
    "wof:name":"Parcs A Conteneurs Gembloux",
    "wof:placetype":"venue"
},
  "geometry": {"coordinates":[4.7222151756,50.5805244446],"type":"Point"}
}