{
  "type": "Feature",
  "properties": {
    "addr:full":"Stationsplein 1 Tielt West-Vlaanderen 8700",
    "addr:housenumber":"1",
    "addr:postcode":"8700",
    "addr:street":"Stationsplein",
    "iso:country":"BE",
    "sg:address":"Stationsplein 1",
    "sg:city":"Tielt",
    "sg:classifiers":[
        {
            "category":"Banks & Credit Unions",
            "subcategory":"Investment Brokerage",
            "type":"Services"
        }
    ],
    "sg:phone":"+32 51 40 45 21",
    "sg:postcode":"8700",
    "sg:province":"West-Vlaanderen",
    "sg:tags":[
        "printing",
        "-"
    ],
    "wof:name":"Schrijverke ('t)",
    "wof:placetype":"venue"
},
  "geometry": {"coordinates":[3.3257000446,50.9941902161],"type":"Point"}
}