{
  "type": "Feature",
  "properties": {
    "iso:country":"BE",
    "sg:address":"Oude Leestsebaan 124a",
    "sg:city":"Mechelen",
    "sg:orig_category":"Editeurs de revues and p\u00e9riodiques. Editeurs de journaux",
    "sg:phone":"+32 15 27 32 82",
    "sg:postcode":"2800",
    "sg:province":"Antwerpen",
    "wof:name":"Agora- Press",
    "wof:placetype":"venue"
},
  "geometry": {"coordinates":[4.4348192215,51.0363731384],"type":"Point"}
}