{
  "type": "Feature",
  "properties": {
    "addr:full":"Sacramentsstraat 1 Hasselt Limburg 3511",
    "addr:housenumber":"1",
    "addr:postcode":"3511",
    "addr:street":"Sacramentsstraat",
    "iso:country":"BE",
    "sg:address":"Sacramentsstraat 1",
    "sg:city":"Hasselt",
    "sg:orig_category":"Grands magasins",
    "sg:phone":"+32 11 25 61 71",
    "sg:postcode":"3511",
    "sg:province":"Limburg",
    "wof:name":"Athina Michelakis",
    "wof:placetype":"venue"
},
  "geometry": {"coordinates":[5.2787351608,50.9537773132],"type":"Point"}
}