{
  "type": "Feature",
  "properties": {
    "addr:full":"Cabergstraat 4 Bilzen Limburg 3740",
    "addr:housenumber":"4",
    "addr:postcode":"3740",
    "addr:street":"Cabergstraat",
    "iso:country":"BE",
    "sg:address":"Cabergstraat 4",
    "sg:city":"Bilzen",
    "sg:orig_category":"Producteurs de fruits",
    "sg:phone":"+32 89 41 18 31",
    "sg:postcode":"3740",
    "sg:province":"Limburg",
    "wof:name":"Mariette Beckers",
    "wof:placetype":"venue"
},
  "geometry": {"coordinates":[5.5730600357,50.8645477295],"type":"Point"}
}