{
  "type": "Feature",
  "properties": {
    "addr:full":"Hoogstraat 39 Duffel Antwerpen 2570",
    "addr:housenumber":"39",
    "addr:postcode":"2570",
    "addr:street":"Hoogstraat",
    "iso:country":"BE",
    "sg:address":"Hoogstraat 39",
    "sg:city":"Duffel",
    "sg:orig_category":"Plomberie, chauffage and installations sanitaires. Construction de maisons",
    "sg:phone":"+32 475 69 06 95",
    "sg:postcode":"2570",
    "sg:province":"Antwerpen",
    "wof:name":"Chm",
    "wof:placetype":"venue"
},
  "geometry": {"coordinates":[4.5156641006,51.0942344666],"type":"Point"}
}