{
  "type": "Feature",
  "properties": {
    "addr:full":"Rue Menil 88 Libramont-chevigny Luxembourg 6800",
    "addr:housenumber":"88",
    "addr:postcode":"6800",
    "addr:street":"Rue Menil",
    "iso:country":"BE",
    "sg:address":"Rue Menil 88",
    "sg:city":"Libramont-chevigny",
    "sg:orig_category":"Installation de menuiserie en bois and plastique. Meubles D\u00e9taillants, Am\u00e9nagement de B\u00e2timents et d",
    "sg:phone":"+32 61 22 48 89",
    "sg:postcode":"6800",
    "sg:province":"Luxembourg",
    "wof:name":"Houba Fr\u00c8res",
    "wof:placetype":"venue"
},
  "geometry": {"coordinates":[5.3761348724,49.9199943542],"type":"Point"}
}