{
  "type": "Feature",
  "properties": {
    "iso:country":"BE",
    "sg:address":"Duinenstraat 325",
    "sg:city":"Bredene",
    "sg:orig_category":"RESTAURANTS: LIVRAISON \u00c0 DOMICILE. RESTAURANTS",
    "sg:phone":"+32 59 32 02 28",
    "sg:postcode":"8450",
    "sg:province":"West-Vlaanderen",
    "wof:name":"Mosselhuis",
    "wof:placetype":"venue"
},
  "geometry": {"coordinates":[2.9623498917,51.246295929],"type":"Point"}
}