{
  "type": "Feature",
  "properties": {
    "addr:full":"Rue Arthur Warocqu\u00c9 24 La Louvi\u00c8re Hainaut 7100",
    "addr:housenumber":"24",
    "addr:postcode":"7100",
    "addr:street":"Rue Arthur Warocque\u0301",
    "iso:country":"BE",
    "sg:address":"Rue Arthur Warocqu\u00c9 24",
    "sg:city":"La Louvi\u00c8re",
    "sg:orig_category":"Mat\u00e9riel m\u00e9dical and orthop\u00e9dique and proth\u00e8ses Fab",
    "sg:phone":"+32 64 22 18 88",
    "sg:postcode":"7100",
    "sg:province":"Hainaut",
    "wof:name":"Roger Massin",
    "wof:placetype":"venue"
},
  "geometry": {"coordinates":[4.1909408569,50.4774169922],"type":"Point"}
}