{
  "type": "Feature",
  "properties": {
    "addr:full":"Georges Brugmannplein 35 Elsene/ixelles Bruxelles-Capitale 1050",
    "addr:housenumber":"35",
    "addr:postcode":"1050",
    "iso:country":"BE",
    "sg:address":"Georges Brugmannplein 35",
    "sg:city":"Elsene/ixelles",
    "sg:classifiers":[
        {
            "category":"Restaurant",
            "type":"Food & Drink"
        }
    ],
    "sg:phone":"+32 2 344 32 10",
    "sg:postcode":"1050",
    "sg:province":"Bruxelles-Capitale",
    "wof:name":"Baroqu's Caf\u00c9",
    "wof:placetype":"venue"
},
  "geometry": {"coordinates":[4.3553757668,50.8174552917],"type":"Point"}
}