{
  "type": "Feature",
  "properties": {
    "iso:country":"BE",
    "sg:address":"Atheneumstraat 3",
    "sg:city":"Elsene/ixelles",
    "sg:orig_category":"Boekhandels",
    "sg:phone":"+32 2 513 50 88",
    "sg:postcode":"1050",
    "sg:province":"Bruxelles-Capitale",
    "wof:name":"Maison Durango",
    "wof:placetype":"venue"
},
  "geometry": {"coordinates":[4.3646640778,50.8348617554],"type":"Point"}
}