{
  "type": "Feature",
  "properties": {
    "addr:full":"Rue Jennart 19 Bruxelles (molenbeek-saint-jean) Bruxelles-Capitale 1080",
    "addr:housenumber":"19",
    "addr:postcode":"1080",
    "addr:street":"Rue Jennart",
    "iso:country":"BE",
    "sg:address":"Rue Jennart 19",
    "sg:city":"Bruxelles (molenbeek-saint-jean)",
    "sg:classifiers":[
        {
            "category":"Retail",
            "subcategory":"Auto Repair",
            "type":"Services"
        }
    ],
    "sg:phone":"+32 2 414 23 98",
    "sg:postcode":"1080",
    "sg:province":"Bruxelles-Capitale",
    "sg:tags":[
        "garage"
    ],
    "wof:name":"Mgd Cars Sprl",
    "wof:placetype":"venue"
},
  "geometry": {"coordinates":[4.3385930061,50.8602027893],"type":"Point"}
}