{
  "type": "Feature",
  "properties": {
    "addr:full":"Peter Benoitstraat 7-9 Oostende West-Vlaanderen 8400",
    "addr:housenumber":"7-9",
    "addr:postcode":"8400",
    "addr:street":"Peter Benoitstraat",
    "iso:country":"BE",
    "sg:address":"Peter Benoitstraat 7-9",
    "sg:city":"Oostende",
    "sg:classifiers":[
        {
            "category":"Building & Trades",
            "subcategory":"Construction",
            "type":"Services"
        }
    ],
    "sg:postcode":"8400",
    "sg:province":"West-Vlaanderen",
    "sg:tags":[
        "truss-makers"
    ],
    "wof:name":"Bond Moyson Medishop",
    "wof:placetype":"venue"
},
  "geometry": {"coordinates":[2.9106149673,51.2247047424],"type":"Point"}
}