{
  "type": "Feature",
  "properties": {
    "iso:country":"BE",
    "sg:address":"Chauss\u00e9e De Forest 72a",
    "sg:city":"Bruxelles (saint-gilles)",
    "sg:classifiers":[
        {
            "category":"Utilities",
            "subcategory":"Telephone",
            "type":"Services"
        }
    ],
    "sg:phone":"+32 2 538 83 13",
    "sg:postcode":"1060",
    "sg:province":"Bruxelles-Capitale",
    "sg:tags":[
        "installation"
    ],
    "wof:name":"Med Communication",
    "wof:placetype":"venue"
},
  "geometry": {"coordinates":[4.3401660919,50.8314437866],"type":"Point"}
}