{
  "type": "Feature",
  "properties": {
    "iso:country":"BE",
    "sg:address":"Avenue De Broqueville 302",
    "sg:city":"Brussel/bruxelles",
    "sg:orig_category":"Diverse zakelijke dienstverlening",
    "sg:phone":"+32 2 779 47 51",
    "sg:postcode":"1200",
    "sg:province":"Bruxelles-Capitale",
    "wof:name":"Lambert & Cie",
    "wof:placetype":"venue"
},
  "geometry": {"coordinates":[4.423789978,50.8426322937],"type":"Point"}
}