{
  "type": "Feature",
  "properties": {
    "addr:full":"Rue Chapelle Saint-ghislain 4 Honnelles (erquennes) Hainaut 7387",
    "addr:housenumber":"4",
    "addr:postcode":"7387",
    "addr:street":"Rue Chapelle Saint-Ghislain;Erquennes Hainaut",
    "iso:country":"BE",
    "sg:address":"Rue Chapelle Saint-ghislain 4",
    "sg:city":"Honnelles (erquennes)",
    "sg:classifiers":[
        {
            "category":"Retail",
            "subcategory":"Auto Repair",
            "type":"Services"
        }
    ],
    "sg:phone":"+32 65 65 34 21",
    "sg:postcode":"7387",
    "sg:province":"Hainaut",
    "sg:tags":[
        "garage"
    ],
    "wof:name":"Winkowski Ets",
    "wof:placetype":"venue"
},
  "geometry": {"coordinates":[3.8055479527,50.3568534851],"type":"Point"}
}