{
  "type": "Feature",
  "properties": {
    "iso:country":"BE",
    "sg:address":"Bredabaan 279",
    "sg:city":"Brasschaat",
    "sg:orig_category":"Magasins de r\u00e9parations d'articles personnels et m\u00e9nagers divers. R\u00e9parations de chaussures and arti",
    "sg:phone":"+32 3 651 49 97",
    "sg:postcode":"2930",
    "sg:province":"Antwerpen",
    "wof:name":"Schoenmakerij Alerco",
    "wof:placetype":"venue"
},
  "geometry": {"coordinates":[4.4879570007,51.288192749],"type":"Point"}
}