{
  "type": "Feature",
  "properties": {
    "addr:full":"Brechtsebaan 10 Brecht (sint-job-in-'t Goor) Antwerpen 2960",
    "addr:housenumber":"10",
    "addr:postcode":"2960",
    "addr:street":"Brechtsebaan;' T Goor",
    "iso:country":"BE",
    "sg:address":"Brechtsebaan 10",
    "sg:city":"Brecht (sint-job-in-'t Goor)",
    "sg:classifiers":[
        {
            "category":"Manufacturing",
            "subcategory":"Metals",
            "type":"Manufacturing & Wholesale Goods"
        }
    ],
    "sg:phone":"+32 3 636 43 53",
    "sg:postcode":"2960",
    "sg:province":"Antwerpen",
    "sg:tags":[
        "ornamental",
        "work",
        "-"
    ],
    "wof:name":"Creators",
    "wof:placetype":"venue"
},
  "geometry": {"coordinates":[4.5689129829,51.3044281006],"type":"Point"}
}