{
  "type": "Feature",
  "properties": {
    "addr:full":"Bouwerijstraat 50 Hemiksem Antwerpen 2620",
    "addr:housenumber":"50",
    "addr:postcode":"2620",
    "addr:street":"Bouwerijstraat",
    "iso:country":"BE",
    "sg:address":"Bouwerijstraat 50",
    "sg:city":"Hemiksem",
    "sg:classifiers":[
        {
            "category":"Health Services",
            "subcategory":"Nursing And Care Facility",
            "type":"Services"
        }
    ],
    "sg:phone":"+32 3 887 38 40",
    "sg:postcode":"2620",
    "sg:province":"Antwerpen",
    "sg:tags":[
        "public"
    ],
    "wof:name":"O.c.m.w.",
    "wof:placetype":"venue"
},
  "geometry": {"coordinates":[4.3413801193,51.1364898682],"type":"Point"}
}