{
  "type": "Feature",
  "properties": {
    "addr:full":"Route De Durbuy 36 Durbuy (barvaux-sur-ourthe) Luxembourg 6940",
    "addr:housenumber":"36",
    "addr:postcode":"6940",
    "addr:street":"Route De Durbuy",
    "iso:country":"BE",
    "sg:address":"Route De Durbuy 36",
    "sg:city":"Durbuy (barvaux-sur-ourthe)",
    "sg:classifiers":[
        {
            "category":"Personal",
            "subcategory":"Beauty Salon",
            "type":"Services"
        }
    ],
    "sg:phone":"+32 86 21 31 41",
    "sg:postcode":"6940",
    "sg:province":"Luxembourg",
    "sg:tags":[
        "lady",
        "-",
        "hairdressing"
    ],
    "wof:name":"Chariot B",
    "wof:placetype":"venue"
},
  "geometry": {"coordinates":[5.4543361664,50.3515777588],"type":"Point"}
}