{
  "type": "Feature",
  "properties": {
    "iso:country":"BE",
    "sg:address":"Jan Mahieustraat 24",
    "sg:city":"Roeselare",
    "sg:classifiers":[
        {
            "category":"Shopping",
            "subcategory":"Clothing, Apparel, & Fashions",
            "type":"Retail Goods"
        }
    ],
    "sg:phone":"+32 51 25 31 44",
    "sg:postcode":"8800",
    "sg:province":"West-Vlaanderen",
    "sg:tags":[
        "purchase",
        "clothing",
        "-",
        "sale",
        "second-hand"
    ],
    "wof:name":"Nounours",
    "wof:placetype":"venue"
},
  "geometry": {"coordinates":[3.1269910336,50.9476089478],"type":"Point"}
}