{
  "type": "Feature",
  "properties": {
    "addr:full":"Waterkasteelstraat 1-2 Blankenberge West-Vlaanderen 8370",
    "addr:housenumber":"1-2",
    "addr:postcode":"8370",
    "addr:street":"Waterkasteelstraat",
    "iso:country":"BE",
    "sg:address":"Waterkasteelstraat 1-2",
    "sg:city":"Blankenberge",
    "sg:classifiers":[
        {
            "category":"Professional",
            "subcategory":"Lawyer & Legal Services",
            "type":"Services"
        }
    ],
    "sg:phone":"+32 50 41 06 00",
    "sg:postcode":"8370",
    "sg:province":"West-Vlaanderen",
    "wof:name":"Vandamme Dirk",
    "wof:placetype":"venue"
},
  "geometry": {"coordinates":[3.1215810776,51.3117904663],"type":"Point"}
}