{
  "type": "Feature",
  "properties": {
    "iso:country":"BE",
    "sg:address":"Chauss\u00e9e De Louvain 25",
    "sg:city":"Wavre",
    "sg:classifiers":[
        {
            "category":"Community Center",
            "type":"Public Place"
        }
    ],
    "sg:phone":"+32 10 22 63 88",
    "sg:postcode":"1300",
    "sg:province":"Brabant Wallon",
    "sg:tags":[
        "medical"
    ],
    "wof:name":"Centre De Radiologie Dechamps",
    "wof:placetype":"venue"
},
  "geometry": {"coordinates":[4.6133890152,50.7138328552],"type":"Point"}
}