{
  "type": "Feature",
  "properties": {
    "iso:country":"BE",
    "sg:address":"Chemin Des Dames - Avelines 25",
    "sg:city":"Villers-la-ville (sart-dames-avelines)",
    "sg:classifiers":[
        {
            "category":"Building & Trades",
            "subcategory":"Cleaning & Sanitation",
            "type":"Services"
        }
    ],
    "sg:phone":"+32 67 77 20 23",
    "sg:postcode":"1495",
    "sg:province":"Brabant Wallon",
    "sg:tags":[
        "fa\u00e7ade",
        "maintenance"
    ],
    "wof:name":"Maach H",
    "wof:placetype":"venue"
},
  "geometry": {"coordinates":[4.4634261131,50.5718727112],"type":"Point"}
}