{
  "type": "Feature",
  "properties": {
    "iso:country":"BE",
    "sg:address":"Gelaagstraat 19",
    "sg:city":"Kruibeke",
    "sg:orig_category":"Sportclubs",
    "sg:phone":"+32 3 774 28 22",
    "sg:postcode":"9150",
    "sg:province":"Oost-Vlaanderen",
    "wof:name":"T.c. S.o.k.s. Rupelmonde",
    "wof:placetype":"venue"
},
  "geometry": {"coordinates":[4.2882490158,51.1255264282],"type":"Point"}
}