{
  "type": "Feature",
  "properties": {
    "addr:full":"Eekhoutstraat 1 Ardooie West-Vlaanderen 8850",
    "addr:housenumber":"1",
    "addr:postcode":"8850",
    "addr:street":"Eekhoutstraat",
    "iso:country":"BE",
    "sg:address":"Eekhoutstraat 1",
    "sg:city":"Ardooie",
    "sg:classifiers":[
        {
            "category":"Real Estate",
            "subcategory":"Architect",
            "type":"Services"
        }
    ],
    "sg:phone":"+32 51 74 50 47",
    "sg:postcode":"8850",
    "sg:province":"West-Vlaanderen",
    "wof:name":"Cauwe J",
    "wof:placetype":"venue"
},
  "geometry": {"coordinates":[3.2007079124,50.9813766479],"type":"Point"}
}