{
  "type": "Feature",
  "properties": {
    "addr:full":"Boomsesteenweg 342 Antwerpen Antwerpen 2020",
    "addr:housenumber":"342",
    "addr:postcode":"2020",
    "addr:street":"Boomsesteenweg",
    "iso:country":"BE",
    "sg:address":"Boomsesteenweg 342",
    "sg:city":"Antwerpen",
    "sg:orig_category":"V\u00eatements, chaussures and accessoires Gr",
    "sg:phone":"+32 3 237 68 17",
    "sg:postcode":"2020",
    "sg:province":"Antwerpen",
    "wof:name":"Havi De Braekeleer",
    "wof:placetype":"venue"
},
  "geometry": {"coordinates":[4.3874669075,51.1876831055],"type":"Point"}
}