{
  "type": "Feature",
  "properties": {
    "addr:full":"Slinkerstraat 58 Lommel Limburg 3920",
    "addr:housenumber":"58",
    "addr:postcode":"3920",
    "addr:street":"Slinkerstraat",
    "iso:country":"BE",
    "sg:address":"Slinkerstraat 58",
    "sg:city":"Lommel",
    "sg:classifiers":[
        {
            "category":"Cafe",
            "type":"Food & Drink"
        }
    ],
    "sg:phone":"+32 11 54 06 90",
    "sg:postcode":"3920",
    "sg:province":"Limburg",
    "sg:tags":[
        "caf\u00e9s"
    ],
    "wof:name":"Caf\u00c9 Heuvelhof",
    "wof:placetype":"venue"
},
  "geometry": {"coordinates":[5.3357329369,51.2450561523],"type":"Point"}
}