{
  "type": "Feature",
  "properties": {
    "iso:country":"BE",
    "sg:address":"Rue Cit\u00c9 De L\u00b4enfance 45",
    "sg:city":"Charleroi",
    "sg:orig_category":"Rusthuizen and serviceflats",
    "sg:phone":"+32 71 43 75 75",
    "sg:postcode":"6001",
    "sg:province":"Hainaut",
    "wof:name":"Home La Tramontane",
    "wof:placetype":"venue"
},
  "geometry": {"coordinates":[4.4251680374,50.3841209412],"type":"Point"}
}