{
  "type": "Feature",
  "properties": {
    "iso:country":"BE",
    "sg:address":"Bronweg 7",
    "sg:city":"Houthalen-helchteren",
    "sg:orig_category":"RESTAURANTS: H\u00d4TELS",
    "sg:phone":"+32 11 60 64 09",
    "sg:postcode":"3530",
    "sg:province":"Limburg",
    "wof:name":"Bonaparte",
    "wof:placetype":"venue"
},
  "geometry": {"coordinates":[5.3798241615,51.0313224792],"type":"Point"}
}