{
  "type": "Feature",
  "properties": {
    "addr:full":"Avenue Du Grand Jardin 14 Courcelles Hainaut 6183",
    "addr:housenumber":"14",
    "addr:postcode":"6183",
    "addr:street":"Avenue Du Grand Jardin",
    "iso:country":"BE",
    "sg:address":"Avenue Du Grand Jardin 14",
    "sg:city":"Courcelles",
    "sg:orig_category":"Installation de menuiserie en bois and plastique",
    "sg:phone":"+32 71 45 36 92",
    "sg:postcode":"6183",
    "sg:province":"Hainaut",
    "wof:name":"Roberto Vivian",
    "wof:placetype":"venue"
},
  "geometry": {"coordinates":[4.3325839043,50.4599380493],"type":"Point"}
}