{
  "type": "Feature",
  "properties": {
    "iso:country":"BE",
    "sg:address":"Atembekestraat 10",
    "sg:city":"Geraardsbergen",
    "sg:orig_category":"Woningbouw",
    "sg:phone":"+32 54 41 50 10",
    "sg:postcode":"9500",
    "sg:province":"Oost-Vlaanderen",
    "wof:name":"Van Liefferinge",
    "wof:placetype":"venue"
},
  "geometry": {"coordinates":[3.9135899544,50.756526947],"type":"Point"}
}