{
  "type": "Feature",
  "properties": {
    "addr:full":"Vanderkinderestraat 171 Ukkel/uccle Bruxelles-Capitale 1180",
    "addr:housenumber":"171",
    "addr:postcode":"1180",
    "addr:street":"Vanderkinderestraat;/",
    "iso:country":"BE",
    "sg:address":"Vanderkinderestraat 171",
    "sg:city":"Ukkel/uccle",
    "sg:orig_category":"Drukkerijen and copyshops",
    "sg:phone":"+32 2 345 91 51",
    "sg:postcode":"1180",
    "sg:province":"Bruxelles-Capitale",
    "wof:name":"Select-copy",
    "wof:placetype":"venue"
},
  "geometry": {"coordinates":[4.3493170738,50.8137931824],"type":"Point"}
}