{
  "type": "Feature",
  "properties": {
    "iso:country":"BE",
    "sg:address":"Nieuwesteenweg 10",
    "sg:city":"Nieuwerkerken",
    "sg:orig_category":"Banken and kredietinstellingen",
    "sg:phone":"+32 11 68 73 61",
    "sg:postcode":"3850",
    "sg:province":"Limburg",
    "wof:name":"Kbc",
    "wof:placetype":"venue"
},
  "geometry": {"coordinates":[5.1923799515,50.8648452759],"type":"Point"}
}