{
  "type": "Feature",
  "properties": {
    "iso:country":"BE",
    "sg:address":"Rue De Virelles 20ba",
    "sg:city":"Chimay",
    "sg:orig_category":"Banques and organismes de cr\u00e9dit",
    "sg:phone":"+32 60 21 51 25",
    "sg:postcode":"6460",
    "sg:province":"Hainaut",
    "wof:name":"Axa",
    "wof:placetype":"venue"
},
  "geometry": {"coordinates":[4.3278870583,50.1165390015],"type":"Point"}
}