{
  "type": "Feature",
  "properties": {
    "addr:full":"Oudebareellei 114 Antwerpen Antwerpen 2170",
    "addr:housenumber":"114",
    "addr:postcode":"2170",
    "addr:street":"Oudebareellei",
    "iso:country":"BE",
    "sg:address":"Oudebareellei 114",
    "sg:city":"Antwerpen",
    "sg:orig_category":"Schoenen",
    "sg:phone":"+32 3 646 31 40",
    "sg:postcode":"2170",
    "sg:province":"Antwerpen",
    "wof:name":"Huis Van Assche J.",
    "wof:placetype":"venue"
},
  "geometry": {"coordinates":[4.4505147934,51.246723175],"type":"Point"}
}