{
  "type": "Feature",
  "properties": {
    "addr:full":"Rue Du Roi-chevalier 53 Fleurus Hainaut 6220",
    "addr:housenumber":"53",
    "addr:postcode":"6220",
    "addr:street":"Rue Du Roi-Chevalier",
    "iso:country":"BE",
    "sg:address":"Rue Du Roi-chevalier 53",
    "sg:city":"Fleurus",
    "sg:orig_category":"Epiceries",
    "sg:phone":"+32 71 81 26 04",
    "sg:postcode":"6220",
    "sg:province":"Hainaut",
    "wof:name":"Maison Decamp",
    "wof:placetype":"venue"
},
  "geometry": {"coordinates":[4.5496749878,50.4825363159],"type":"Point"}
}