{
  "type": "Feature",
  "properties": {
    "iso:country":"BE",
    "sg:address":"Ceintuurlaan 146",
    "sg:city":"Genk",
    "sg:orig_category":"Epiceries",
    "sg:phone":"+32 89 84 34 09",
    "sg:postcode":"3600",
    "sg:province":"Limburg",
    "wof:name":"Gokuzum",
    "wof:placetype":"venue"
},
  "geometry": {"coordinates":[5.5159659386,51.0034141541],"type":"Point"}
}