{
  "type": "Feature",
  "properties": {
    "iso:country":"BE",
    "sg:address":"Poedermagazijnstraat 107",
    "sg:city":"Menen",
    "sg:orig_category":"Epiceries",
    "sg:phone":"+32 56 51 02 30",
    "sg:postcode":"8930",
    "sg:province":"West-Vlaanderen",
    "wof:name":"Kathleen Vandewiele",
    "wof:placetype":"venue"
},
  "geometry": {"coordinates":[3.11916399,50.800403595],"type":"Point"}
}