{
  "type": "Feature",
  "properties": {
    "addr:full":"Rue Chapelle Ste Anne 24 Walhain Brabant Wallon 1457",
    "addr:housenumber":"24;1457",
    "addr:street":"Rue Chapelle Ste",
    "iso:country":"BE",
    "sg:address":"Rue Chapelle Ste Anne 24",
    "sg:city":"Walhain",
    "sg:orig_category":"Jardinage",
    "sg:phone":"+32 10 65 03 96",
    "sg:postcode":"1457",
    "sg:province":"Brabant Wallon",
    "wof:name":"Green Farms",
    "wof:placetype":"venue"
},
  "geometry": {"coordinates":[4.6986689568,50.617313385],"type":"Point"}
}