{
  "type": "Feature",
  "properties": {
    "addr:full":"Petite Rue Des Bouchers 28 Brussel/bruxelles Bruxelles-Capitale 1000",
    "addr:housenumber":"28",
    "addr:postcode":"1000",
    "addr:street":"Petite Rue Des Bouchers;/",
    "iso:country":"BE",
    "sg:address":"Petite Rue Des Bouchers 28",
    "sg:city":"Brussel/bruxelles",
    "sg:classifiers":[
        {
            "category":"Restaurant",
            "type":"Food & Drink"
        }
    ],
    "sg:phone":"+32 2 512 51 11",
    "sg:postcode":"1000",
    "sg:province":"Bruxelles-Capitale",
    "sg:tags":[
        "de",
        "organisation",
        "\u00e0",
        "fast",
        "catering",
        "emporter",
        "f\u00eates",
        "restaurants"
    ],
    "wof:name":"Restaurant La Belg'epoque",
    "wof:placetype":"venue"
},
  "geometry": {"coordinates":[4.3537211418,50.847946167],"type":"Point"}
}