{
  "type": "Feature",
  "properties": {
    "addr:full":"Holmlei 64 Mechelen Antwerpen 2800",
    "addr:housenumber":"64",
    "addr:postcode":"2800",
    "addr:street":"Holmlei",
    "iso:country":"BE",
    "sg:address":"Holmlei 64",
    "sg:city":"Mechelen",
    "sg:classifiers":[
        {
            "category":"Arena",
            "subcategory":"Sports Club",
            "type":"Entertainment"
        }
    ],
    "sg:phone":"+32 15 21 62 44",
    "sg:postcode":"2800",
    "sg:province":"Antwerpen",
    "wof:name":"Albatros V.k. Vzw",
    "wof:placetype":"venue"
},
  "geometry": {"coordinates":[4.4613361359,51.0409469604],"type":"Point"}
}