{
  "type": "Feature",
  "properties": {
    "addr:full":"Bercheux 68 Vaux-sur-s\u00fbre (juseret) Luxembourg 6642",
    "addr:housenumber":"68",
    "addr:postcode":"6642",
    "addr:street":"Bercheux",
    "iso:country":"BE",
    "sg:address":"Bercheux 68",
    "sg:city":"Vaux-sur-s\u00fbre (juseret)",
    "sg:classifiers":[
        {
            "category":"Building & Trades",
            "subcategory":"Plumbing",
            "type":"Services"
        }
    ],
    "sg:phone":"+32 61 25 60 43",
    "sg:postcode":"6642",
    "sg:province":"Luxembourg",
    "sg:tags":[
        "repair",
        "mainten",
        "-",
        "central",
        "heating"
    ],
    "wof:name":"Leonard M",
    "wof:placetype":"venue"
},
  "geometry": {"coordinates":[5.5497012138,49.8756828308],"type":"Point"}
}