{
  "type": "Feature",
  "properties": {
    "addr:full":"Brusselsesteenweg 630 Overijse Vlaams-Brabant 3090",
    "addr:housenumber":"630",
    "addr:postcode":"3090",
    "addr:street":"Brusselsesteenweg",
    "iso:country":"BE",
    "sg:address":"Brusselsesteenweg 630",
    "sg:city":"Overijse",
    "sg:classifiers":[
        {
            "category":"Personal",
            "subcategory":"Beauty Salon",
            "type":"Services"
        }
    ],
    "sg:phone":"+32 2 657 69 89",
    "sg:postcode":"3090",
    "sg:province":"Vlaams-Brabant",
    "sg:tags":[
        "lady",
        "-",
        "hairdressing"
    ],
    "wof:name":"Salon D'carlo",
    "wof:placetype":"venue"
},
  "geometry": {"coordinates":[4.5077381134,50.7832832336],"type":"Point"}
}