{
  "type": "Feature",
  "properties": {
    "iso:country":"BE",
    "sg:address":"Avenue De La Toison D\u00b4or 18",
    "sg:city":"Marche-en-famenne",
    "sg:classifiers":[
        {
            "category":"Insurance",
            "subcategory":"Life Insurance",
            "type":"Services"
        }
    ],
    "sg:phone":"+32 84 31 23 76",
    "sg:postcode":"6900",
    "sg:province":"Luxembourg",
    "sg:tags":[
        "assurance"
    ],
    "wof:name":"Kbc Assurances",
    "wof:placetype":"venue"
},
  "geometry": {"coordinates":[5.3454971313,50.2251205444],"type":"Point"}
}