{
  "type": "Feature",
  "properties": {
    "addr:full":"Av.de L'eglise St.julien 18 Oudergem/auderghem Bruxelles-Capitale 1160",
    "addr:housenumber":"18",
    "addr:postcode":"1160",
    "addr:street":"Av.De;St.Julien;/",
    "iso:country":"BE",
    "sg:address":"Av.de L'eglise St.julien 18",
    "sg:city":"Oudergem/auderghem",
    "sg:orig_category":"Enseignement maternel and primaire",
    "sg:phone":"+32 2 673 86 34",
    "sg:postcode":"1160",
    "sg:province":"Bruxelles-Capitale",
    "wof:name":"Ecole Fondamentale Libre",
    "wof:placetype":"venue"
},
  "geometry": {"coordinates":[4.4251499176,50.8167381287],"type":"Point"}
}