{
  "type": "Feature",
  "properties": {
    "addr:full":"Distellaan 2 Middelkerke West-Vlaanderen 8434",
    "addr:housenumber":"2",
    "addr:postcode":"8434",
    "addr:street":"Distellaan",
    "iso:country":"BE",
    "sg:address":"Distellaan 2",
    "sg:city":"Middelkerke",
    "sg:orig_category":"Banken and kredietinstellingen",
    "sg:phone":"+32 59 30 10 78",
    "sg:postcode":"8434",
    "sg:province":"West-Vlaanderen",
    "wof:name":"Fortis",
    "wof:placetype":"venue"
},
  "geometry": {"coordinates":[2.7569050789,51.1488685608],"type":"Point"}
}