{
  "type": "Feature",
  "properties": {
    "addr:full":"Clos Des Epilobes 11 Namur (w\u00e9pion) Namur 5100",
    "addr:housenumber":"11",
    "addr:postcode":"5100",
    "addr:street":"Clos Des Epilobes",
    "iso:country":"BE",
    "sg:address":"Clos Des Epilobes 11",
    "sg:city":"Namur (w\u00e9pion)",
    "sg:classifiers":[
        {
            "category":"Health Services",
            "subcategory":"Health Practitioner",
            "type":"Services"
        }
    ],
    "sg:phone":"+32 81 46 15 28",
    "sg:postcode":"5100",
    "sg:province":"Namur",
    "sg:tags":[
        "physiotherapist"
    ],
    "wof:name":"Li\u00e9geois Albert",
    "wof:placetype":"venue"
},
  "geometry": {"coordinates":[4.8684000969,50.4217033386],"type":"Point"}
}