{
  "type": "Feature",
  "properties": {
    "iso:country":"BE",
    "sg:address":"Avenue Van Volxem 322a",
    "sg:city":"Bruxelles",
    "sg:classifiers":[
        {
            "category":"Home & Garden",
            "subcategory":"Building Materials",
            "type":"Retail Goods"
        }
    ],
    "sg:phone":"+32 2 346 20 60",
    "sg:postcode":"1190",
    "sg:province":"Bruxelles-Capitale",
    "sg:tags":[
        "garage",
        "door"
    ],
    "wof:name":"A Cube S.p.r.l.",
    "wof:placetype":"venue"
},
  "geometry": {"coordinates":[4.3257322311,50.8231582642],"type":"Point"}
}