{
  "type": "Feature",
  "properties": {
    "addr:full":"Rue Basse 59 Wellin Luxembourg 6920",
    "addr:housenumber":"59",
    "addr:postcode":"6920",
    "addr:street":"Rue Basse",
    "iso:country":"BE",
    "sg:address":"Rue Basse 59",
    "sg:city":"Wellin",
    "sg:orig_category":"Eleveurs de bovins",
    "sg:phone":"+32 84 38 88 84",
    "sg:postcode":"6920",
    "sg:province":"Luxembourg",
    "wof:name":"Gis\u00c8le Thiry",
    "wof:placetype":"venue"
},
  "geometry": {"coordinates":[5.0770401955,50.0679092407],"type":"Point"}
}