{
  "type": "Feature",
  "properties": {
    "addr:full":"Maarschalk Frenchlaan 45 Ieper West-Vlaanderen 8900",
    "addr:housenumber":"45",
    "addr:postcode":"8900",
    "addr:street":"Maarschalk Frenchlaan",
    "iso:country":"BE",
    "sg:address":"Maarschalk Frenchlaan 45",
    "sg:city":"Ieper",
    "sg:classifiers":[
        {
            "category":"Banks & Credit Unions",
            "subcategory":"Investment Brokerage",
            "type":"Services"
        }
    ],
    "sg:phone":"+32 57 20 24 67",
    "sg:postcode":"8900",
    "sg:province":"West-Vlaanderen",
    "sg:tags":[
        "jean",
        "casual",
        "wear"
    ],
    "wof:name":"Black Pepper",
    "wof:placetype":"venue"
},
  "geometry": {"coordinates":[2.8940219879,50.8531799316],"type":"Point"}
}