{
  "type": "Feature",
  "properties": {
    "addr:full":"Albert I Promenade 79 Oostende West-Vlaanderen 8400",
    "addr:housenumber":"79",
    "addr:postcode":"8400",
    "addr:street":"Albert I Promenade",
    "iso:country":"BE",
    "sg:address":"Albert I Promenade 79",
    "sg:city":"Oostende",
    "sg:orig_category":"Immobili\u00ebnkantoren Landmeters and schatters Vakantiehuizen",
    "sg:phone":"+32 59 70 51 05",
    "sg:postcode":"8400",
    "sg:province":"West-Vlaanderen",
    "wof:name":"Agence Lecomte",
    "wof:placetype":"venue"
},
  "geometry": {"coordinates":[2.9080440998,51.229221344],"type":"Point"}
}