{
  "type": "Feature",
  "properties": {
    "addr:full":"Av. Hospitaliers St.jean 21 Waterloo Brabant Wallon 1410",
    "addr:housenumber":"21",
    "addr:postcode":"1410",
    "addr:street":"Av. Hospitaliers St.Jean",
    "iso:country":"BE",
    "sg:address":"Av. Hospitaliers St.jean 21",
    "sg:city":"Waterloo",
    "sg:orig_category":"Boekhouders",
    "sg:phone":"+32 2 384 48 87",
    "sg:postcode":"1410",
    "sg:province":"Brabant Wallon",
    "wof:name":"Francis Daix",
    "wof:placetype":"venue"
},
  "geometry": {"coordinates":[4.3947749138,50.6969108582],"type":"Point"}
}