{
  "type": "Feature",
  "properties": {
    "addr:full":"Route De Frasnes 237 Ath (mainvault) Hainaut 7812",
    "addr:housenumber":"237",
    "addr:postcode":"7812",
    "addr:street":"Route De Frasnes",
    "iso:country":"BE",
    "sg:address":"Route De Frasnes 237",
    "sg:city":"Ath (mainvault)",
    "sg:classifiers":[
        {
            "category":"Building & Trades",
            "subcategory":"Equipment Rental",
            "type":"Services"
        }
    ],
    "sg:phone":"+32 68 64 66 56",
    "sg:postcode":"7812",
    "sg:province":"Hainaut",
    "sg:tags":[
        "use",
        "apparatus",
        "tool",
        "-",
        "professional",
        "machines"
    ],
    "wof:name":"Cobel Sc",
    "wof:placetype":"venue"
},
  "geometry": {"coordinates":[3.6734309196,50.6524047852],"type":"Point"}
}