{
  "type": "Feature",
  "properties": {
    "iso:country":"BE",
    "sg:address":"Rue De L' Eglise 245",
    "sg:city":"Wanze (groot)",
    "sg:orig_category":"Entretien and r\u00e9parations de voitures. Entretien et r\u00e9parations de v\u00e9hicules \u00e0 domicile",
    "sg:phone":"+32 85 23 17 94",
    "sg:postcode":"4520",
    "sg:province":"Li\u00e8ge",
    "wof:name":"Boesmans Baudoin Garage",
    "wof:placetype":"venue"
},
  "geometry": {"coordinates":[5.1859469414,50.5436439514],"type":"Point"}
}