{
  "type": "Feature",
  "properties": {
    "addr:full":"Singelstraat 18 Borgloon Limburg 3840",
    "addr:housenumber":"18",
    "addr:postcode":"3840",
    "addr:street":"Singelstraat",
    "iso:country":"BE",
    "sg:address":"Singelstraat 18",
    "sg:city":"Borgloon",
    "sg:orig_category":"Eleveurs and marchands de porcs",
    "sg:phone":"+32 12 74 21 89",
    "sg:postcode":"3840",
    "sg:province":"Limburg",
    "wof:name":"Yvan Paque",
    "wof:placetype":"venue"
},
  "geometry": {"coordinates":[5.3441700935,50.8012466431],"type":"Point"}
}