{
  "type": "Feature",
  "properties": {
    "iso:country":"BE",
    "sg:address":"Rue Pottiez 3",
    "sg:city":"P\u00e9ruwelz (braffe)",
    "sg:classifiers":[
        {
            "category":"Wholesale",
            "subcategory":"Beer",
            "type":"Manufacturing & Wholesale Goods"
        }
    ],
    "sg:phone":"+32 69 66 52 95",
    "sg:postcode":"7604",
    "sg:province":"Hainaut",
    "sg:tags":[
        "ale",
        "-"
    ],
    "wof:name":"Drink Delhaye Philippe",
    "wof:placetype":"venue"
},
  "geometry": {"coordinates":[3.5455200672,50.5414009094],"type":"Point"}
}