{
  "type": "Feature",
  "properties": {
    "addr:full":"Kempenarestraat 60 Sint-katelijne-waver Antwerpen 2860",
    "addr:housenumber":"60",
    "addr:postcode":"2860",
    "addr:street":"Kempenarestraat",
    "iso:country":"BE",
    "sg:address":"Kempenarestraat 60",
    "sg:city":"Sint-katelijne-waver",
    "sg:orig_category":"Kantoormateriaal Procesbesturingssystemen Fab Software ontwikkeling and ontwerp",
    "sg:phone":"+32 15 55 68 84",
    "sg:postcode":"2860",
    "sg:province":"Antwerpen",
    "wof:name":"A.a.c.d.",
    "wof:placetype":"venue"
},
  "geometry": {"coordinates":[4.5237851143,51.0598907471],"type":"Point"}
}