{
  "type": "Feature",
  "properties": {
    "addr:full":"Hovestraat 48 Edegem Antwerpen 2650",
    "addr:housenumber":"48",
    "addr:postcode":"2650",
    "addr:street":"Hovestraat",
    "iso:country":"BE",
    "sg:address":"Hovestraat 48",
    "sg:city":"Edegem",
    "sg:orig_category":"Hypermarch\u00e9s",
    "sg:phone":"+32 3 451 38 40",
    "sg:postcode":"2650",
    "sg:province":"Antwerpen",
    "wof:name":"Match",
    "wof:placetype":"venue"
},
  "geometry": {"coordinates":[4.448433876,51.1558570862],"type":"Point"}
}