{
  "type": "Feature",
  "properties": {
    "addr:full":"Vossensteert 14 Brugge (assebroek) West-Vlaanderen 8310",
    "addr:housenumber":"14",
    "addr:postcode":"8310",
    "addr:street":"Vossensteert",
    "iso:country":"BE",
    "sg:address":"Vossensteert 14",
    "sg:city":"Brugge (assebroek)",
    "sg:classifiers":[
        {
            "category":"Manufacturing",
            "subcategory":"Glass & Minerals",
            "type":"Manufacturing & Wholesale Goods"
        }
    ],
    "sg:phone":"+32 50 35 36 58",
    "sg:postcode":"8310",
    "sg:province":"West-Vlaanderen",
    "sg:tags":[
        "stained",
        "glazier",
        "-"
    ],
    "wof:name":"Cloetens",
    "wof:placetype":"venue"
},
  "geometry": {"coordinates":[3.2560579777,51.202091217],"type":"Point"}
}