{
  "type": "Feature",
  "properties": {
    "addr:full":"Philipstockstraat 3 Brugge West-Vlaanderen 8000",
    "addr:housenumber":"3",
    "addr:postcode":"8000",
    "addr:street":"Philipstockstraat",
    "iso:country":"BE",
    "sg:address":"Philipstockstraat 3",
    "sg:city":"Brugge",
    "sg:classifiers":[
        {
            "category":"Manufacturing",
            "subcategory":"Textiles",
            "type":"Manufacturing & Wholesale Goods"
        }
    ],
    "sg:phone":"+32 50 33 74 73",
    "sg:postcode":"8000",
    "sg:province":"West-Vlaanderen",
    "wof:name":"Huis Duchesse",
    "wof:placetype":"venue"
},
  "geometry": {"coordinates":[3.2249441147,51.2095298767],"type":"Point"}
}