{
  "type": "Feature",
  "properties": {
    "iso:country":"BE",
    "sg:address":"Wellingstraat 76",
    "sg:city":"Destelbergen",
    "sg:orig_category":"Woningbouw",
    "sg:phone":"+32 9 252 26 13",
    "sg:postcode":"9070",
    "sg:province":"Oost-Vlaanderen",
    "wof:name":"Saegerman Gebroeders",
    "wof:placetype":"venue"
},
  "geometry": {"coordinates":[3.8051478863,51.0146980286],"type":"Point"}
}