{
  "type": "Feature",
  "properties": {
    "addr:full":"Avenue L\u00c9o Errera 22 Ukkel/uccle Bruxelles-Capitale 1180",
    "addr:housenumber":"22",
    "addr:postcode":"1180",
    "addr:street":"Avenue Le\u0301O Errera;/",
    "iso:country":"BE",
    "sg:address":"Avenue L\u00c9o Errera 22",
    "sg:city":"Ukkel/uccle",
    "sg:orig_category":"Maisons de repos and r\u00e9sidences",
    "sg:phone":"+32 2 343 79 76",
    "sg:postcode":"1180",
    "sg:province":"Bruxelles-Capitale",
    "wof:name":"R\u00c9sidence Errera",
    "wof:placetype":"venue"
},
  "geometry": {"coordinates":[4.3542108536,50.8108711243],"type":"Point"}
}