{
  "type": "Feature",
  "properties": {
    "addr:full":"Rue De Dinant 116 Beauraing Namur 5570",
    "addr:housenumber":"116",
    "addr:postcode":"5570",
    "addr:street":"Rue De Dinant",
    "iso:country":"BE",
    "sg:address":"Rue De Dinant 116",
    "sg:city":"Beauraing",
    "sg:classifiers":[
        {
            "category":"Bars & Pubs",
            "type":"Food & Drink"
        }
    ],
    "sg:phone":"+32 82 71 38 49",
    "sg:postcode":"5570",
    "sg:province":"Namur",
    "wof:name":"Must (le)",
    "wof:placetype":"venue"
},
  "geometry": {"coordinates":[4.9554519653,50.1171722412],"type":"Point"}
}