{
  "type": "Feature",
  "properties": {
    "addr:full":"Av. Pr\u00c9sident Roosevelt 57 Sambreville Namur 5060",
    "addr:housenumber":"57",
    "addr:postcode":"5060",
    "addr:street":"Av. Pre\u0301Sident Roosevelt",
    "iso:country":"BE",
    "sg:address":"Av. Pr\u00c9sident Roosevelt 57",
    "sg:city":"Sambreville",
    "sg:orig_category":"Algemeen secundair onderwijs Technisch and beroeps secundair onderwijs",
    "sg:phone":"+32 71 77 23 88",
    "sg:postcode":"5060",
    "sg:province":"Namur",
    "wof:name":"Ath\u00c9n\u00c9e Royal",
    "wof:placetype":"venue"
},
  "geometry": {"coordinates":[4.6285200119,50.4448738098],"type":"Point"}
}