{
  "type": "Feature",
  "properties": {
    "addr:full":"Rijkenhoekstraat 3 Hever Vlaams-Brabant 3191",
    "addr:housenumber":"3",
    "addr:postcode":"3191",
    "addr:street":"Rijkenhoekstraat",
    "iso:country":"BE",
    "sg:address":"Rijkenhoekstraat 3",
    "sg:city":"Hever",
    "sg:classifiers":[
        {
            "category":"Building & Trades",
            "subcategory":"Landscaping Services",
            "type":"Services"
        }
    ],
    "sg:phone":"+32 15 61 75 41",
    "sg:postcode":"3191",
    "sg:province":"Vlaams-Brabant",
    "sg:tags":[
        "gardening",
        "garden",
        "maintenance"
    ],
    "wof:name":"Swinnen",
    "wof:placetype":"venue"
},
  "geometry": {"coordinates":[4.5450577736,50.9809608459],"type":"Point"}
}