{
  "type": "Feature",
  "properties": {
    "addr:full":"Neutralstrasse 404 Lontzen Li\u00e8ge 4710",
    "addr:housenumber":"404",
    "addr:postcode":"4710",
    "addr:street":"Neutralstrasse",
    "iso:country":"BE",
    "sg:address":"Neutralstrasse 404",
    "sg:city":"Lontzen",
    "sg:classifiers":[
        {
            "category":"Retail",
            "subcategory":"Auto Repair",
            "type":"Services"
        }
    ],
    "sg:phone":"+32 87 88 39 13",
    "sg:postcode":"4710",
    "sg:province":"Li\u00e8ge",
    "sg:tags":[
        "garage"
    ],
    "wof:name":"Ernens J",
    "wof:placetype":"venue"
},
  "geometry": {"coordinates":[5.9626188278,50.6792488098],"type":"Point"}
}