{
  "type": "Feature",
  "properties": {
    "iso:country":"BE",
    "sg:address":"Rue Du Planois 72",
    "sg:city":"Mettet",
    "sg:orig_category":"V\u00e9t\u00e9rinaires",
    "sg:phone":"+32 71 72 78 33",
    "sg:postcode":"5640",
    "sg:province":"Namur",
    "wof:name":"Fabrice Van Lierde",
    "wof:placetype":"venue"
},
  "geometry": {"coordinates":[4.6578397751,50.3198051453],"type":"Point"}
}