{
  "type": "Feature",
  "properties": {
    "addr:full":"Chauss\u00c9e Fernand Deli\u00c8ge 66 Beaumont Hainaut 6500",
    "addr:housenumber":"66",
    "addr:postcode":"6500",
    "addr:street":"Chausse\u0301E Fernand Delie\u0300Ge;Hainaut",
    "iso:country":"BE",
    "sg:address":"Chauss\u00c9e Fernand Deli\u00c8ge 66",
    "sg:city":"Beaumont",
    "sg:orig_category":"Plomberie, chauffage and installations sanitaires",
    "sg:phone":"+32 71 58 95 11",
    "sg:postcode":"6500",
    "sg:province":"Hainaut",
    "wof:name":"Fe. Dossin",
    "wof:placetype":"venue"
},
  "geometry": {"coordinates":[4.2497239113,50.2376022339],"type":"Point"}
}