{
  "type": "Feature",
  "properties": {
    "iso:country":"BE",
    "sg:address":"Bree\u00cbrweg 25",
    "sg:city":"Bocholt",
    "sg:orig_category":"D\u00e9molition d\u00b4immeubles and terrassements",
    "sg:phone":"+32 89 47 36 27",
    "sg:postcode":"3950",
    "sg:province":"Limburg",
    "wof:name":"Fa. Swinters-nijssen",
    "wof:placetype":"venue"
},
  "geometry": {"coordinates":[5.5841269493,51.1683921814],"type":"Point"}
}