{
  "type": "Feature",
  "properties": {
    "iso:country":"BE",
    "sg:address":"Dendermondsesteenweg 51",
    "sg:city":"Lebbeke",
    "sg:orig_category":"Pain, p\u00e2tisseries and confiseries",
    "sg:phone":"+32 52 41 42 68",
    "sg:postcode":"9280",
    "sg:province":"Oost-Vlaanderen",
    "wof:name":"Johan Lanckbeen",
    "wof:placetype":"venue"
},
  "geometry": {"coordinates":[4.1263289452,51.0024757385],"type":"Point"}
}