{
  "type": "Feature",
  "properties": {
    "iso:country":"BE",
    "sg:address":"Herentalsebaan 150",
    "sg:city":"Wommelgem",
    "sg:orig_category":"Supermarch\u00e9s",
    "sg:postcode":"2160",
    "sg:province":"Antwerpen",
    "wof:name":"Aldi",
    "wof:placetype":"venue"
},
  "geometry": {"coordinates":[4.5027999878,51.1958312988],"type":"Point"}
}