{
  "type": "Feature",
  "properties": {
    "addr:full":"Waalse Kaai 2 Antwerpen Antwerpen 2000",
    "addr:housenumber":"2",
    "addr:postcode":"2000",
    "addr:street":"Kaai",
    "iso:country":"BE",
    "sg:address":"Waalse Kaai 2",
    "sg:city":"Antwerpen",
    "sg:orig_category":"Newspapers, magazines, periodicals - Distribution",
    "sg:phone":"+32 3 257 18 09",
    "sg:postcode":"2000",
    "sg:province":"Antwerpen",
    "wof:name":"Papyrus",
    "wof:placetype":"venue"
},
  "geometry": {"coordinates":[4.3922700882,51.2125892639],"type":"Point"}
}