{
  "type": "Feature",
  "properties": {
    "addr:full":"Alexander Franckstraat 55 Boechout Antwerpen 2530",
    "addr:housenumber":"55",
    "addr:postcode":"2530",
    "addr:street":"Alexander Franckstraat",
    "iso:country":"BE",
    "sg:address":"Alexander Franckstraat 55",
    "sg:city":"Boechout",
    "sg:classifiers":[
        {
            "category":"Home & Garden",
            "subcategory":"Furniture",
            "type":"Retail Goods"
        }
    ],
    "sg:phone":"+32 3 454 41 77",
    "sg:postcode":"2530",
    "sg:province":"Antwerpen",
    "sg:tags":[
        "-"
    ],
    "wof:name":"Diap International",
    "wof:placetype":"venue"
},
  "geometry": {"coordinates":[4.5042901039,51.1581916809],"type":"Point"}
}