{
  "type": "Feature",
  "properties": {
    "addr:full":"Warandestraat 7 Wevelgem West-Vlaanderen 8560",
    "addr:housenumber":"7",
    "addr:postcode":"8560",
    "addr:street":"Warandestraat",
    "iso:country":"BE",
    "sg:address":"Warandestraat 7",
    "sg:city":"Wevelgem",
    "sg:orig_category":"Slagers",
    "sg:phone":"+32 56 40 13 50",
    "sg:postcode":"8560",
    "sg:province":"West-Vlaanderen",
    "wof:name":"Beenhouwerij 't Hoekske",
    "wof:placetype":"venue"
},
  "geometry": {"coordinates":[3.1653800011,50.8383140564],"type":"Point"}
}