{
  "type": "Feature",
  "properties": {
    "iso:country":"BE",
    "sg:address":"Berkenlaan 35",
    "sg:city":"Balen",
    "sg:orig_category":"V\u00e9hicules automobiles",
    "sg:phone":"+32 14 30 25 27",
    "sg:postcode":"2491",
    "sg:province":"Antwerpen",
    "wof:name":"Patrick Vleminx",
    "wof:placetype":"venue"
},
  "geometry": {"coordinates":[5.1542630196,51.139919281],"type":"Point"}
}