{
  "type": "Feature",
  "properties": {
    "addr:full":"Hopmarkt 3 Aalst Oost-Vlaanderen 9300",
    "addr:housenumber":"3",
    "addr:postcode":"9300",
    "addr:street":"Hopmarkt",
    "iso:country":"BE",
    "sg:address":"Hopmarkt 3",
    "sg:city":"Aalst",
    "sg:classifiers":[
        {
            "category":"Banks & Credit Unions",
            "subcategory":"Bank",
            "type":"Services"
        }
    ],
    "sg:phone":"+32 53 77 87 88",
    "sg:postcode":"9300",
    "sg:province":"Oost-Vlaanderen",
    "wof:name":"Europabank",
    "wof:placetype":"venue"
},
  "geometry": {"coordinates":[4.0376348495,50.938079834],"type":"Point"}
}