{
  "type": "Feature",
  "properties": {
    "iso:country":"BE",
    "sg:address":"Nieuwstraat 4",
    "sg:city":"Lebbeke",
    "sg:orig_category":"Kapsalons",
    "sg:phone":"+32 53 21 65 02",
    "sg:postcode":"9280",
    "sg:province":"Oost-Vlaanderen",
    "wof:name":"Coiffure Denise",
    "wof:placetype":"venue"
},
  "geometry": {"coordinates":[4.0830960274,50.9808921814],"type":"Point"}
}