{
  "type": "Feature",
  "properties": {
    "addr:full":"De Beughemlaan 30a Kapelle-op-den-bos (ramsdonk) Vlaams-Brabant 1880",
    "addr:housenumber":"30a",
    "addr:postcode":"1880",
    "addr:street":"De Beughemlaan",
    "iso:country":"BE",
    "sg:address":"De Beughemlaan 30a",
    "sg:city":"Kapelle-op-den-bos (ramsdonk)",
    "sg:classifiers":[
        {
            "category":"Professional",
            "subcategory":"Accounting & Tax Preparation",
            "type":"Services"
        }
    ],
    "sg:phone":"+32 15 71 00 15",
    "sg:postcode":"1880",
    "sg:province":"Vlaams-Brabant",
    "sg:tags":[
        "bookkeeper"
    ],
    "wof:name":"Fiscaal Kantoor Pauwels",
    "wof:placetype":"venue"
},
  "geometry": {"coordinates":[4.3314981461,51.0123786926],"type":"Point"}
}