{
  "type": "Feature",
  "properties": {
    "iso:country":"BE",
    "sg:address":"Rue Am\u00e9ricaine 88",
    "sg:city":"Bruxelles (ixelles)",
    "sg:classifiers":[
        {
            "category":"Bars & Pubs",
            "type":"Food & Drink"
        }
    ],
    "sg:phone":"+32 2 534 41 85",
    "sg:postcode":"1050",
    "sg:province":"Bruxelles-Capitale",
    "wof:name":"Bar (le)",
    "wof:placetype":"venue"
},
  "geometry": {"coordinates":[4.3590211868,50.8233718872],"type":"Point"}
}