{
  "type": "Feature",
  "properties": {
    "iso:country":"BE",
    "sg:address":"Vianderdal 10",
    "sg:city":"Tienen",
    "sg:orig_category":"M\u00e9decins and sp\u00e9cialistes",
    "sg:phone":"+32 16 82 46 79",
    "sg:postcode":"3300",
    "sg:province":"Vlaams-Brabant",
    "wof:name":"Thierry Van Den Bosch",
    "wof:placetype":"venue"
},
  "geometry": {"coordinates":[4.9492588043,50.8175086975],"type":"Point"}
}