{
  "type": "Feature",
  "properties": {
    "addr:full":"Katelijnestraat 65c Brugge West-Vlaanderen 8000",
    "addr:housenumber":"65c",
    "addr:postcode":"8000",
    "addr:street":"Katelijnestraat",
    "iso:country":"BE",
    "sg:address":"Katelijnestraat 65c",
    "sg:city":"Brugge",
    "sg:classifiers":[
        {
            "category":"Social Services",
            "type":"Services"
        }
    ],
    "sg:phone":"+32 50 34 88 08",
    "sg:postcode":"8000",
    "sg:province":"West-Vlaanderen",
    "wof:name":"Yambo Regionaal Onthaalbueau",
    "wof:placetype":"venue"
},
  "geometry": {"coordinates":[3.2266418934,51.2023048401],"type":"Point"}
}