{
  "type": "Feature",
  "properties": {
    "addr:full":"Rue De La Longue Haie 3 Namen Namur 5001",
    "addr:housenumber":"3",
    "addr:postcode":"5001",
    "addr:street":"Rue De La Longue Haie",
    "iso:country":"BE",
    "sg:address":"Rue De La Longue Haie 3",
    "sg:city":"Namen",
    "sg:orig_category":"Diverse bedrijfsbeheeradviesbureaus",
    "sg:phone":"+32 81 73 33 30",
    "sg:postcode":"5001",
    "sg:province":"Namur",
    "wof:name":"E. H. Management",
    "wof:placetype":"venue"
},
  "geometry": {"coordinates":[4.8257050514,50.4722557068],"type":"Point"}
}