{
  "type": "Feature",
  "properties": {
    "addr:full":"Gaversesteenweg 293 Merelbeke Oost-Vlaanderen 9820",
    "addr:housenumber":"293",
    "addr:postcode":"9820",
    "addr:street":"Gaversesteenweg",
    "iso:country":"BE",
    "sg:address":"Gaversesteenweg 293",
    "sg:city":"Merelbeke",
    "sg:classifiers":[
        {
            "category":"Arts & Performance",
            "subcategory":"Symphony",
            "type":"Entertainment"
        }
    ],
    "sg:phone":"+32 9 230 64 54",
    "sg:postcode":"9820",
    "sg:province":"Oost-Vlaanderen",
    "sg:tags":[
        "orchestra"
    ],
    "wof:name":"Freddy Saget - All-stars",
    "wof:placetype":"venue"
},
  "geometry": {"coordinates":[3.7362680435,50.994178772],"type":"Point"}
}