{
  "type": "Feature",
  "properties": {
    "iso:country":"BE",
    "sg:address":"Kleine Kouterstraat 2 A",
    "sg:city":"Beveren",
    "sg:orig_category":"Elektrische installaties voor woningen Gespecialiseerde residenti\u00eble bouw Installatie van houten of ",
    "sg:phone":"+32 3 755 32 77",
    "sg:postcode":"9120",
    "sg:province":"Oost-Vlaanderen",
    "wof:name":"Meersman Electro",
    "wof:placetype":"venue"
},
  "geometry": {"coordinates":[4.1721520424,51.218044281],"type":"Point"}
}