{
  "type": "Feature",
  "properties": {
    "addr:full":"Jagersdreef 1 Grobbendonk Antwerpen 2280",
    "addr:housenumber":"1",
    "addr:postcode":"2280",
    "addr:street":"Jagersdreef",
    "iso:country":"BE",
    "sg:address":"Jagersdreef 1",
    "sg:city":"Grobbendonk",
    "sg:orig_category":"Beautyfarms, relaxatie and lichamelijk welzijn Hotels Organisatie van beurzen, congressen and tentoo",
    "sg:phone":"+32 14 50 10 01",
    "sg:postcode":"2280",
    "sg:province":"Antwerpen",
    "wof:name":"Rigoletto (aldhem Hotel)",
    "wof:placetype":"venue"
},
  "geometry": {"coordinates":[4.7620692253,51.1763839722],"type":"Point"}
}