{
  "type": "Feature",
  "properties": {
    "iso:country":"BE",
    "sg:address":"Rue Marcel Moreau 11",
    "sg:city":"Couvin",
    "sg:classifiers":[
        {
            "category":"Health Services",
            "subcategory":"Doctor",
            "type":"Services"
        }
    ],
    "sg:phone":"+32 60 34 61 14",
    "sg:postcode":"5660",
    "sg:province":"Namur",
    "sg:tags":[
        "medicinephysicians",
        "surgeon"
    ],
    "wof:name":"Ballat P",
    "wof:placetype":"venue"
},
  "geometry": {"coordinates":[4.4820637703,50.0536766052],"type":"Point"}
}