{
  "type": "Feature",
  "properties": {
    "iso:country":"BE",
    "sg:address":"Rue De Montpellier 47",
    "sg:city":"Charleroi",
    "sg:orig_category":"Artsen and specialisten",
    "sg:phone":"+32 71 51 59 33",
    "sg:postcode":"6030",
    "sg:province":"Hainaut",
    "wof:name":"Jean-pol Navez",
    "wof:placetype":"venue"
},
  "geometry": {"coordinates":[4.393558979,50.4018707275],"type":"Point"}
}