{
  "type": "Feature",
  "properties": {
    "addr:full":"Dorpsstraat 82 Brecht Antwerpen 2960",
    "addr:housenumber":"82",
    "addr:postcode":"2960",
    "addr:street":"Dorpsstraat",
    "iso:country":"BE",
    "sg:address":"Dorpsstraat 82",
    "sg:city":"Brecht",
    "sg:orig_category":"M\u00e9decins and sp\u00e9cialistes",
    "sg:phone":"+32 3 313 82 03",
    "sg:postcode":"2960",
    "sg:province":"Antwerpen",
    "wof:name":"F. Bonne",
    "wof:placetype":"venue"
},
  "geometry": {"coordinates":[4.6415200233,51.3512115479],"type":"Point"}
}