{
  "type": "Feature",
  "properties": {
    "iso:country":"BE",
    "sg:address":"Slingerstraat 37",
    "sg:city":"Torhout",
    "sg:orig_category":"Forge, Moulage and Profilage des M\u00e9taux",
    "sg:phone":"+32 51 72 59 37",
    "sg:postcode":"8820",
    "sg:province":"West-Vlaanderen",
    "wof:name":"Deruelle W.",
    "wof:placetype":"venue"
},
  "geometry": {"coordinates":[3.0956349373,51.0350723267],"type":"Point"}
}