{
  "type": "Feature",
  "properties": {
    "iso:country":"BE",
    "sg:address":"Witte Nonnenstr 28",
    "sg:city":"Hasselt",
    "sg:classifiers":[
        {
            "category":"Travel",
            "subcategory":"Hotels & Motels",
            "type":"Entertainment"
        }
    ],
    "sg:phone":"+32 11 24 32 28",
    "sg:postcode":"3500",
    "sg:province":"Limburg",
    "sg:tags":[
        "hotels",
        "business",
        "restaurant"
    ],
    "wof:name":"Borrelhuis Nv",
    "wof:placetype":"venue"
},
  "geometry": {"coordinates":[5.3408608437,50.9328117371],"type":"Point"}
}