{
  "type": "Feature",
  "properties": {
    "addr:full":"Rue Des Boers 72 Bruxelles (etterbeek) Bruxelles-Capitale 1040",
    "addr:housenumber":"72",
    "addr:postcode":"1040",
    "addr:street":"Rue Des Boers",
    "iso:country":"BE",
    "sg:address":"Rue Des Boers 72",
    "sg:city":"Bruxelles (etterbeek)",
    "sg:classifiers":[
        {
            "category":"Bakery",
            "type":"Food & Drink"
        }
    ],
    "sg:phone":"+32 2 733 12 96",
    "sg:postcode":"1040",
    "sg:province":"Bruxelles-Capitale",
    "sg:tags":[
        "confectioner",
        "baker"
    ],
    "wof:name":"Bo\u00eete \u00e0 Pain (la)",
    "wof:placetype":"venue"
},
  "geometry": {"coordinates":[4.3942418098,50.834941864],"type":"Point"}
}