{
  "type": "Feature",
  "properties": {
    "addr:full":"Eernegemstraat 92 Koekelare West-Vlaanderen 8680",
    "addr:housenumber":"92",
    "addr:postcode":"8680",
    "addr:street":"Eernegemstraat",
    "iso:country":"BE",
    "sg:address":"Eernegemstraat 92",
    "sg:city":"Koekelare",
    "sg:orig_category":"Rundveehouders Varkenskwekers",
    "sg:phone":"+32 51 58 93 41",
    "sg:postcode":"8680",
    "sg:province":"West-Vlaanderen",
    "wof:name":"Georges Vandenbussche",
    "wof:placetype":"venue"
},
  "geometry": {"coordinates":[2.988902092,51.1074943542],"type":"Point"}
}