{
  "type": "Feature",
  "properties": {
    "addr:full":"Avenue Louise 349 Box 1 Bruxelles (ixelles) Bruxelles-Capitale 1050",
    "addr:housenumber":"349;1",
    "addr:postcode":"1050",
    "addr:street":"Avenue Louise;Box",
    "iso:country":"BE",
    "sg:address":"Avenue Louise 349 Box 1",
    "sg:city":"Bruxelles (ixelles)",
    "sg:classifiers":[
        {
            "category":"Professional",
            "subcategory":"Accounting & Tax Preparation",
            "type":"Services"
        }
    ],
    "sg:phone":"+32 2 626 12 00",
    "sg:postcode":"1050",
    "sg:province":"Bruxelles-Capitale",
    "sg:tags":[
        "bookkeeper"
    ],
    "wof:name":"Vander Elst A",
    "wof:placetype":"venue"
},
  "geometry": {"coordinates":[4.3692178726,50.8217430115],"type":"Point"}
}