{
  "type": "Feature",
  "properties": {
    "addr:full":"Molenstraat 110 Rumst (reet) Antwerpen 2840",
    "addr:housenumber":"110",
    "addr:postcode":"2840",
    "addr:street":"Molenstraat",
    "iso:country":"BE",
    "sg:address":"Molenstraat 110",
    "sg:city":"Rumst (reet)",
    "sg:classifiers":[
        {
            "category":"Professional",
            "subcategory":"Accounting & Tax Preparation",
            "type":"Services"
        }
    ],
    "sg:phone":"+32 3 843 23 94",
    "sg:postcode":"2840",
    "sg:province":"Antwerpen",
    "sg:tags":[
        "bookkeeper"
    ],
    "wof:name":"De Boeck H",
    "wof:placetype":"venue"
},
  "geometry": {"coordinates":[4.3992958069,51.1005477905],"type":"Point"}
}