{
  "type": "Feature",
  "properties": {
    "addr:full":"Rue Simone Patiny 13 Profondeville (bois-de-villers) Namur 5170",
    "addr:housenumber":"13",
    "addr:postcode":"5170",
    "addr:street":"Rue Simone Patiny",
    "iso:country":"BE",
    "sg:address":"Rue Simone Patiny 13",
    "sg:city":"Profondeville (bois-de-villers)",
    "sg:classifiers":[
        {
            "category":"Health Services",
            "subcategory":"Health Practitioner",
            "type":"Services"
        }
    ],
    "sg:phone":"+32 81 43 33 27",
    "sg:postcode":"5170",
    "sg:province":"Namur",
    "sg:tags":[
        "physiotherapist"
    ],
    "wof:name":"Cayer J",
    "wof:placetype":"venue"
},
  "geometry": {"coordinates":[4.8105502129,50.397151947],"type":"Point"}
}