{
  "type": "Feature",
  "properties": {
    "iso:country":"BE",
    "sg:address":"Vrijheid 62",
    "sg:city":"Hoogstraten",
    "sg:orig_category":"Boucheries",
    "sg:phone":"+32 3 314 50 93",
    "sg:postcode":"2320",
    "sg:province":"Antwerpen",
    "wof:name":"Slagerij Bastiaensen",
    "wof:placetype":"venue"
},
  "geometry": {"coordinates":[4.7627720833,51.4053993225],"type":"Point"}
}