{
  "type": "Feature",
  "properties": {
    "iso:country":"BE",
    "sg:address":"Kattestraat 9",
    "sg:city":"Geel",
    "sg:classifiers":[
        {
            "category":"Building & Trades",
            "subcategory":"Landscaping Services",
            "type":"Services"
        }
    ],
    "sg:phone":"+32 14 59 01 26",
    "sg:postcode":"2440",
    "sg:province":"Antwerpen",
    "sg:tags":[
        "gardening",
        "garden",
        "maintenance"
    ],
    "wof:name":"Benjo Tuinaanleg",
    "wof:placetype":"venue"
},
  "geometry": {"coordinates":[4.9437789917,51.1623497009],"type":"Point"}
}