{
  "type": "Feature",
  "properties": {
    "iso:country":"BE",
    "sg:address":"Roodebeeksteenweg 99",
    "sg:city":"Sint-lambrechts-woluwe/woluwe-saint-lambert",
    "sg:orig_category":"Meubelzaken, woning- and keukeninrichting",
    "sg:phone":"+32 2 771 51 26",
    "sg:postcode":"1200",
    "sg:province":"Bruxelles-Capitale",
    "wof:name":"Maison Confort",
    "wof:placetype":"venue"
},
  "geometry": {"coordinates":[4.432559967,50.8488044739],"type":"Point"}
}