{
  "type": "Feature",
  "properties": {
    "addr:full":"Molenlei 88 Berlaar Antwerpen 2590",
    "addr:housenumber":"88",
    "addr:postcode":"2590",
    "addr:street":"Molenlei",
    "iso:country":"BE",
    "sg:address":"Molenlei 88",
    "sg:city":"Berlaar",
    "sg:classifiers":[
        {
            "category":"Building & Trades",
            "subcategory":"Pest Control",
            "type":"Services"
        }
    ],
    "sg:phone":"+32 3 385 55 01",
    "sg:postcode":"2590",
    "sg:province":"Antwerpen",
    "sg:tags":[
        "painting",
        "contractor"
    ],
    "wof:name":"Bouwen R",
    "wof:placetype":"venue"
},
  "geometry": {"coordinates":[4.6392540932,51.1185874939],"type":"Point"}
}