{
  "type": "Feature",
  "properties": {
    "addr:full":"Heilig Hartlaan 22 Aalst Oost-Vlaanderen 9300",
    "addr:housenumber":"22",
    "addr:postcode":"9300",
    "addr:street":"Hartlaan",
    "iso:country":"BE",
    "sg:address":"Heilig Hartlaan 22",
    "sg:city":"Aalst",
    "sg:classifiers":[
        {
            "category":"Cafe",
            "type":"Food & Drink"
        }
    ],
    "sg:phone":"+32 53 21 13 36",
    "sg:postcode":"9300",
    "sg:province":"Oost-Vlaanderen",
    "sg:tags":[
        "caf\u00e9s"
    ],
    "wof:name":"Paroch. Werken H.hart",
    "wof:placetype":"venue"
},
  "geometry": {"coordinates":[4.0428981781,50.9491271973],"type":"Point"}
}