{
  "type": "Feature",
  "properties": {
    "addr:full":"Nieuwstraat 4 Geel Antwerpen 2440",
    "addr:housenumber":"4",
    "addr:postcode":"2440",
    "addr:street":"Nieuwstraat",
    "iso:country":"BE",
    "sg:address":"Nieuwstraat 4",
    "sg:city":"Geel",
    "sg:classifiers":[
        {
            "category":"Professional",
            "subcategory":"Management & Consulting",
            "type":"Services"
        }
    ],
    "sg:phone":"+32 14 72 47 88",
    "sg:postcode":"2440",
    "sg:province":"Antwerpen",
    "sg:tags":[
        "-",
        "processing",
        "data",
        "consultant"
    ],
    "wof:name":"Bulck System Support",
    "wof:placetype":"venue"
},
  "geometry": {"coordinates":[4.9911999702,51.1627349854],"type":"Point"}
}