{
  "type": "Feature",
  "properties": {
    "iso:country":"BE",
    "sg:address":"Kasteelstraat 26",
    "sg:city":"Kruibeke (rupelmonde)",
    "sg:classifiers":[
        {
            "category":"Health Services",
            "subcategory":"Health Practitioner",
            "type":"Services"
        }
    ],
    "sg:phone":"+32 3 774 36 17",
    "sg:postcode":"9150",
    "sg:province":"Oost-Vlaanderen",
    "sg:tags":[
        "physiotherapist"
    ],
    "wof:name":"Martens G",
    "wof:placetype":"venue"
},
  "geometry": {"coordinates":[4.2921462059,51.1265716553],"type":"Point"}
}