{
  "type": "Feature",
  "properties": {
    "iso:country":"BE",
    "sg:address":"Rue Henri Stacquet 41",
    "sg:city":"Brussel/bruxelles",
    "sg:orig_category":"Editeurs de livres. Animations diverses. Services divers aux entreprises",
    "sg:phone":"+32 2 248 13 83",
    "sg:postcode":"1030",
    "sg:province":"Bruxelles-Capitale",
    "wof:name":"Bureau Contre-jour",
    "wof:placetype":"venue"
},
  "geometry": {"coordinates":[4.3892002106,50.8583068848],"type":"Point"}
}