{
  "type": "Feature",
  "properties": {
    "iso:country":"BE",
    "sg:address":"Appelmansstraat 17",
    "sg:city":"Antwerpen",
    "sg:classifiers":[
        {
            "category":"Restaurant",
            "type":"Food & Drink"
        }
    ],
    "sg:phone":"+32 3 225 23 24",
    "sg:postcode":"2018",
    "sg:province":"Antwerpen",
    "wof:name":"La Cigale D\u00b4argent",
    "wof:placetype":"venue"
},
  "geometry": {"coordinates":[4.4176440239,51.2168083191],"type":"Point"}
}