{
  "type": "Feature",
  "properties": {
    "iso:country":"BE",
    "sg:address":"Rue De La C\u00d4te 71",
    "sg:city":"Charleroi",
    "sg:orig_category":"Industri\u00eble and commerci\u00eble bouw",
    "sg:phone":"+32 475 24 74 10",
    "sg:postcode":"6010",
    "sg:province":"Hainaut",
    "wof:name":"Les Hauts Droits",
    "wof:placetype":"venue"
},
  "geometry": {"coordinates":[4.4733719826,50.3877296448],"type":"Point"}
}