{
  "type": "Feature",
  "properties": {
    "iso:country":"BE",
    "sg:address":"Rue D\u00b4aix La Chapelle 392",
    "sg:city":"Eupen",
    "sg:classifiers":[
        {
            "category":"Cafe",
            "type":"Food & Drink"
        }
    ],
    "sg:phone":"+32 87 85 30 86",
    "sg:postcode":"4701",
    "sg:province":"Li\u00e8ge",
    "sg:tags":[
        "caf\u00e9s"
    ],
    "wof:name":"Caf\u00c9 La Lanterne",
    "wof:placetype":"venue"
},
  "geometry": {"coordinates":[6.0412201881,50.6376190186],"type":"Point"}
}