{
  "type": "Feature",
  "properties": {
    "iso:country":"BE",
    "sg:address":"Rue Saint-jean 7",
    "sg:city":"Namur",
    "sg:classifiers":[
        {
            "category":"Professional",
            "subcategory":"Computer Services",
            "type":"Services"
        }
    ],
    "sg:phone":"+32 81 24 92 49",
    "sg:postcode":"5000",
    "sg:province":"Namur",
    "sg:tags":[
        "-",
        "processing",
        "data"
    ],
    "wof:name":"Bureautique Sa",
    "wof:placetype":"venue"
},
  "geometry": {"coordinates":[4.8648910522,50.4630126953],"type":"Point"}
}