{
  "type": "Feature",
  "properties": {
    "addr:full":"Dorpstraat 17 Mechelen (leest) Antwerpen 2811",
    "addr:housenumber":"17",
    "addr:postcode":"2811",
    "addr:street":"Dorpstraat",
    "iso:country":"BE",
    "sg:address":"Dorpstraat 17",
    "sg:city":"Mechelen (leest)",
    "sg:classifiers":[
        {
            "category":"Banks & Credit Unions",
            "subcategory":"Financial Services",
            "type":"Services"
        }
    ],
    "sg:phone":"+32 15 27 74 60",
    "sg:postcode":"2811",
    "sg:province":"Antwerpen",
    "sg:tags":[
        "loan",
        "mortgage"
    ],
    "wof:name":"Dons Tony Bvba",
    "wof:placetype":"venue"
},
  "geometry": {"coordinates":[4.4443998337,51.014541626],"type":"Point"}
}