{
  "type": "Feature",
  "properties": {
    "addr:full":"Chauss\u00c9e De Haecht 121 Schaarbeek/schaerbeek Bruxelles-Capitale 1030",
    "addr:housenumber":"121",
    "addr:postcode":"1030",
    "addr:street":"Chausse\u0301E De Haecht",
    "iso:country":"BE",
    "sg:address":"Chauss\u00c9e De Haecht 121",
    "sg:city":"Schaarbeek/schaerbeek",
    "sg:classifiers":[
        {
            "category":"Restaurant",
            "type":"Food & Drink"
        }
    ],
    "sg:phone":"+32 2 219 08 80",
    "sg:postcode":"1030",
    "sg:province":"Bruxelles-Capitale",
    "wof:name":"Bergama",
    "wof:placetype":"venue"
},
  "geometry": {"coordinates":[4.3699841499,50.8584022522],"type":"Point"}
}