{
  "type": "Feature",
  "properties": {
    "iso:country":"BE",
    "sg:address":"Rue Warechaix 16",
    "sg:city":"Dour",
    "sg:classifiers":[
        {
            "category":"Wholesale",
            "subcategory":"Farm Supplies",
            "type":"Manufacturing & Wholesale Goods"
        }
    ],
    "sg:phone":"+32 65 65 04 02",
    "sg:postcode":"7370",
    "sg:province":"Hainaut",
    "sg:tags":[
        "machine",
        "agricoles",
        "mat\u00e9riel",
        "gr"
    ],
    "wof:name":"Hubert Godart",
    "wof:placetype":"venue"
},
  "geometry": {"coordinates":[3.8242750168,50.3696632385],"type":"Point"}
}