{
  "type": "Feature",
  "properties": {
    "iso:country":"BE",
    "sg:address":"Rue Ct Achille G\u00c9h\u00c9not 1",
    "sg:city":"Beauraing",
    "sg:orig_category":"Eclairage et \u00e9quipements du foyer",
    "sg:phone":"+32 82 71 13 47",
    "sg:postcode":"5570",
    "sg:province":"Namur",
    "wof:name":"Nicole Gernay",
    "wof:placetype":"venue"
},
  "geometry": {"coordinates":[4.9586668015,50.1085662842],"type":"Point"}
}