{
  "type": "Feature",
  "properties": {
    "addr:full":"Pieter Breugheldreef 1 Ieper West-Vlaanderen 8900",
    "addr:housenumber":"1",
    "addr:postcode":"8900",
    "addr:street":"Pieter Breugheldreef",
    "iso:country":"BE",
    "sg:address":"Pieter Breugheldreef 1",
    "sg:city":"Ieper",
    "sg:orig_category":"Afval and schroot Gh",
    "sg:phone":"+32 57 20 99 63",
    "sg:postcode":"8900",
    "sg:province":"West-Vlaanderen",
    "wof:name":"Paul Waeles",
    "wof:placetype":"venue"
},
  "geometry": {"coordinates":[2.8708670139,50.8615760803],"type":"Point"}
}