{
  "type": "Feature",
  "properties": {
    "addr:full":"Rue G\u00e9n\u00e9ral Michel 39 Namur Namur 5000",
    "addr:housenumber":"39",
    "addr:postcode":"5000",
    "addr:street":"Rue Ge\u0301Ne\u0301Ral Michel",
    "iso:country":"BE",
    "sg:address":"Rue G\u00e9n\u00e9ral Michel 39",
    "sg:city":"Namur",
    "sg:classifiers":[
        {
            "category":"Wholesale",
            "subcategory":"Meat",
            "type":"Manufacturing & Wholesale Goods"
        }
    ],
    "sg:phone":"+32 81 22 79 88",
    "sg:postcode":"5000",
    "sg:province":"Namur",
    "sg:tags":[
        "whol",
        "-"
    ],
    "wof:name":"Reveillon A Sprl",
    "wof:placetype":"venue"
},
  "geometry": {"coordinates":[4.8724040985,50.4680366516],"type":"Point"}
}