{
  "type": "Feature",
  "properties": {
    "iso:country":"BE",
    "sg:address":"Rue De Rebecq 4",
    "sg:city":"Rebecq",
    "sg:orig_category":"Sportclubs",
    "sg:phone":"+32 67 63 61 57",
    "sg:postcode":"1430",
    "sg:province":"Brabant Wallon",
    "wof:name":"Quanaka",
    "wof:placetype":"venue"
},
  "geometry": {"coordinates":[4.1453609467,50.664276123],"type":"Point"}
}