{
  "type": "Feature",
  "properties": {
    "addr:full":"Avenue Des Saisons 84 Elsene Bruxelles-Capitale 1050",
    "addr:housenumber":"84",
    "addr:postcode":"1050",
    "addr:street":"Avenue Des Saisons",
    "iso:country":"BE",
    "sg:address":"Avenue Des Saisons 84",
    "sg:city":"Elsene",
    "sg:orig_category":"Agences d'exp\u00e9dition",
    "sg:phone":"+32 2 648 66 05",
    "sg:postcode":"1050",
    "sg:province":"Bruxelles-Capitale",
    "wof:name":"Saja",
    "wof:placetype":"venue"
},
  "geometry": {"coordinates":[4.3878650665,50.8184814453],"type":"Point"}
}