{
  "type": "Feature",
  "properties": {
    "iso:country":"BE",
    "sg:address":"Grand'rue 45",
    "sg:city":"Walhain",
    "sg:orig_category":"Enseignement maternel and primaire",
    "sg:phone":"+32 10 65 53 56",
    "sg:postcode":"1457",
    "sg:province":"Brabant Wallon",
    "wof:name":"Ecole Fond. Communale",
    "wof:placetype":"venue"
},
  "geometry": {"coordinates":[4.6581568718,50.6102600098],"type":"Point"}
}