{
  "type": "Feature",
  "properties": {
    "iso:country":"BE",
    "sg:address":"Rue De Douvrain 0",
    "sg:city":"Saint-ghislain",
    "sg:orig_category":"Vitrage. Peinture. Rev\u00eatements pour sols and murs. Blanchisserie, Nettoyage \u00e0 Sec and Salons-Lavoirs",
    "sg:phone":"+32 65 31 40 43",
    "sg:postcode":"7331",
    "sg:province":"Hainaut",
    "wof:name":"D\u00c9coration Jean Raes",
    "wof:placetype":"venue"
},
  "geometry": {"coordinates":[3.832367897,50.4841804504],"type":"Point"}
}