{
  "type": "Feature",
  "properties": {
    "addr:full":"Fosselstraat 19a Affligem Vlaams-Brabant 1790",
    "addr:housenumber":"19a",
    "addr:postcode":"1790",
    "addr:street":"Fosselstraat",
    "iso:country":"BE",
    "sg:address":"Fosselstraat 19a",
    "sg:city":"Affligem",
    "sg:classifiers":[
        {
            "category":"Insurance",
            "subcategory":"Insurance Agent",
            "type":"Services"
        }
    ],
    "sg:phone":"+32 53 68 42 90",
    "sg:postcode":"1790",
    "sg:province":"Vlaams-Brabant",
    "sg:tags":[
        "verzekeringsmakelaars",
        "expert"
    ],
    "wof:name":"Zakenkantoor Nevens",
    "wof:placetype":"venue"
},
  "geometry": {"coordinates":[4.1134848595,50.9186325073],"type":"Point"}
}