{
  "type": "Feature",
  "properties": {
    "addr:full":"Rue Du Haut-cortil 13 Jemeppe-sur-sambre Namur 5190",
    "addr:housenumber":"13",
    "addr:postcode":"5190",
    "addr:street":"Rue Du Haut-Cortil",
    "iso:country":"BE",
    "sg:address":"Rue Du Haut-cortil 13",
    "sg:city":"Jemeppe-sur-sambre",
    "sg:orig_category":"Artsen and specialisten",
    "sg:phone":"+32 71 78 56 83",
    "sg:postcode":"5190",
    "sg:province":"Namur",
    "wof:name":"M. Ligny",
    "wof:placetype":"venue"
},
  "geometry": {"coordinates":[4.6690001488,50.4641914368],"type":"Point"}
}