{
  "type": "Feature",
  "properties": {
    "iso:country":"BE",
    "sg:address":"Neerbroek 120",
    "sg:city":"Zwijndrecht",
    "sg:orig_category":"Peinture. Rev\u00eatements pour sols and murs",
    "sg:phone":"+32 3 252 54 94",
    "sg:postcode":"2070",
    "sg:province":"Antwerpen",
    "wof:name":"Ronald Steppe",
    "wof:placetype":"venue"
},
  "geometry": {"coordinates":[4.3385810852,51.2213973999],"type":"Point"}
}