{
  "type": "Feature",
  "properties": {
    "addr:full":"Rue De Lambais 48 Grez-doiceau Brabant Wallon 1390",
    "addr:housenumber":"48",
    "addr:postcode":"1390",
    "addr:street":"Rue De Lambais",
    "iso:country":"BE",
    "sg:address":"Rue De Lambais 48",
    "sg:city":"Grez-doiceau",
    "sg:orig_category":"Fleurop Interflora. Fleurs and plantes",
    "sg:phone":"+32 10 84 42 78",
    "sg:postcode":"1390",
    "sg:province":"Brabant Wallon",
    "wof:name":"Les Fleurs De Marie",
    "wof:placetype":"venue"
},
  "geometry": {"coordinates":[4.6958799362,50.7423591614],"type":"Point"}
}