{
  "type": "Feature",
  "properties": {
    "addr:full":"Rue Emile L\u00e9t\u00e9 33 Saint-ghislain (sirault) Hainaut 7332",
    "addr:housenumber":"33",
    "addr:postcode":"7332",
    "addr:street":"Rue Emile Le\u0301Te\u0301",
    "iso:country":"BE",
    "sg:address":"Rue Emile L\u00e9t\u00e9 33",
    "sg:city":"Saint-ghislain (sirault)",
    "sg:classifiers":[
        {
            "category":"Fast Food",
            "type":"Food & Drink"
        }
    ],
    "sg:phone":"+32 65 62 06 65",
    "sg:postcode":"7332",
    "sg:province":"Hainaut",
    "sg:tags":[
        "fried",
        "stand",
        "potato"
    ],
    "wof:name":"Bon Accueil (le)",
    "wof:placetype":"venue"
},
  "geometry": {"coordinates":[3.786839962,50.5054969788],"type":"Point"}
}