{
  "type": "Feature",
  "properties": {
    "iso:country":"BE",
    "sg:address":"Rue Des Coteaux 4",
    "sg:city":"Verviers",
    "sg:orig_category":"Diverse opleidingen and onderwijs",
    "sg:phone":"+32 87 22 14 17",
    "sg:postcode":"4800",
    "sg:province":"Li\u00e8ge",
    "wof:name":"Michel Regnier",
    "wof:placetype":"venue"
},
  "geometry": {"coordinates":[5.8678498268,50.5886611938],"type":"Point"}
}