{
  "type": "Feature",
  "properties": {
    "addr:full":"Hessenplein 11-20 Antwerpen 2008",
    "addr:postcode":"11-20;2008",
    "iso:country":"BE",
    "sg:address":"Hessenplein 11-20",
    "sg:city":"Antwerpen",
    "sg:classifiers":[
        {
            "category":"Marine",
            "type":"Transportation"
        }
    ],
    "sg:phone":"+32 3 231 89 50",
    "sg:postcode":"2008",
    "sg:tags":[
        "transport",
        "sea"
    ],
    "wof:name":"Steved & Trading Cy Brabo Nv",
    "wof:placetype":"venue"
},
  "geometry": {"coordinates":[4.4097700119,51.2265815735],"type":"Point"}
}