{
  "type": "Feature",
  "properties": {
    "addr:full":"Av De Lothier 30 Bruxelles Bruxelles-Capitale 1150",
    "addr:housenumber":"30",
    "addr:postcode":"1150",
    "addr:street":"Av De Lothier",
    "iso:country":"BE",
    "sg:address":"Av De Lothier 30",
    "sg:city":"Bruxelles",
    "sg:classifiers":[
        {
            "category":"Manufacturing",
            "subcategory":"Rubber & Plastics",
            "type":"Manufacturing & Wholesale Goods"
        }
    ],
    "sg:phone":"+32 2 771 80 91",
    "sg:postcode":"1150",
    "sg:province":"Bruxelles-Capitale",
    "sg:tags":[
        "packaging",
        "material",
        "-",
        "paper",
        "cardboard"
    ],
    "wof:name":"Euro Pak 2000 Sa",
    "wof:placetype":"venue"
},
  "geometry": {"coordinates":[4.4380397797,50.8223838806],"type":"Point"}
}