{
  "type": "Feature",
  "properties": {
    "addr:full":"Chauss\u00c9e De Tongres 307 Juprelle Li\u00e8ge 4450",
    "addr:housenumber":"307",
    "addr:postcode":"4450",
    "addr:street":"Chausse\u0301E De Tongres",
    "iso:country":"BE",
    "sg:address":"Chauss\u00c9e De Tongres 307",
    "sg:city":"Juprelle",
    "sg:orig_category":"Belastingconsulenten Diverse juridische dienstverlening",
    "sg:phone":"+32 4 278 64 74",
    "sg:postcode":"4450",
    "sg:province":"Li\u00e8ge",
    "wof:name":"Ch. Grimmomprez Et Cie",
    "wof:placetype":"venue"
},
  "geometry": {"coordinates":[5.5282230377,50.7030601501],"type":"Point"}
}