{
  "type": "Feature",
  "properties": {
    "addr:full":"Hoevensebaan 44 Kapellen Antwerpen 2950",
    "addr:housenumber":"44",
    "addr:postcode":"2950",
    "addr:street":"Hoevensebaan",
    "iso:country":"BE",
    "sg:address":"Hoevensebaan 44",
    "sg:city":"Kapellen",
    "sg:orig_category":"Caf\u00e9s Sportclubs",
    "sg:phone":"+32 3 665 14 58",
    "sg:postcode":"2950",
    "sg:province":"Antwerpen",
    "wof:name":"Rubens",
    "wof:placetype":"venue"
},
  "geometry": {"coordinates":[4.4266500473,51.3141288757],"type":"Point"}
}