{
  "type": "Feature",
  "properties": {
    "iso:country":"BE",
    "sg:address":"Magdalenastraat 124",
    "sg:city":"Wervik",
    "sg:classifiers":[
        {
            "category":"Shopping",
            "subcategory":"Jewelry",
            "type":"Retail Goods"
        }
    ],
    "sg:phone":"+32 56 31 19 60",
    "sg:postcode":"8940",
    "sg:province":"West-Vlaanderen",
    "sg:tags":[
        "jeweller",
        "-"
    ],
    "wof:name":"Hugo J",
    "wof:placetype":"venue"
},
  "geometry": {"coordinates":[3.0393600464,50.7791290283],"type":"Point"}
}