{
  "type": "Feature",
  "properties": {
    "addr:full":"Blauwstraat 9 Boom Antwerpen 2850",
    "addr:housenumber":"9",
    "addr:postcode":"2850",
    "addr:street":"Blauwstraat",
    "iso:country":"BE",
    "sg:address":"Blauwstraat 9",
    "sg:city":"Boom",
    "sg:classifiers":[
        {
            "category":"Bakery",
            "type":"Food & Drink"
        }
    ],
    "sg:phone":"+32 3 888 83 22",
    "sg:postcode":"2850",
    "sg:province":"Antwerpen",
    "sg:tags":[
        "confectioner",
        "baker"
    ],
    "wof:name":"Croissanterietje ('t)",
    "wof:placetype":"venue"
},
  "geometry": {"coordinates":[4.3668541908,51.086353302],"type":"Point"}
}