{
  "type": "Feature",
  "properties": {
    "addr:full":"Chemin Des Maro\u00cblles 10 Thuin Hainaut 6530",
    "addr:housenumber":"10",
    "addr:postcode":"6530",
    "addr:street":"Chemin Des Maroe\u0308Lles",
    "iso:country":"BE",
    "sg:address":"Chemin Des Maro\u00cblles 10",
    "sg:city":"Thuin",
    "sg:orig_category":"Artsen and specialisten",
    "sg:phone":"+32 71 59 36 46",
    "sg:postcode":"6530",
    "sg:province":"Hainaut",
    "wof:name":"F. Dussart",
    "wof:placetype":"venue"
},
  "geometry": {"coordinates":[4.2752990723,50.3327636719],"type":"Point"}
}