{
  "type": "Feature",
  "properties": {
    "iso:country":"BE",
    "sg:address":"Rue Jacques Ray\u00e9 28",
    "sg:city":"Bruxelles (schaerbeek)",
    "sg:classifiers":[
        {
            "category":"Retail",
            "subcategory":"Auto Repair",
            "type":"Services"
        }
    ],
    "sg:phone":"+32 2 216 04 94",
    "sg:postcode":"1030",
    "sg:province":"Bruxelles-Capitale",
    "sg:tags":[
        "automobile",
        "-",
        "wrecking"
    ],
    "wof:name":"New Vp Motor",
    "wof:placetype":"venue"
},
  "geometry": {"coordinates":[4.3826937675,50.8692474365],"type":"Point"}
}