{
  "type": "Feature",
  "properties": {
    "iso:country":"BE",
    "sg:address":"Veerlepad 24",
    "sg:city":"Herselt",
    "sg:orig_category":"Loodgieterij, verwarming and sanitaire installaties",
    "sg:phone":"+32 14 54 57 43",
    "sg:postcode":"2230",
    "sg:province":"Antwerpen",
    "wof:name":"Amara",
    "wof:placetype":"venue"
},
  "geometry": {"coordinates":[4.8895940781,51.054599762],"type":"Point"}
}