{
  "type": "Feature",
  "properties": {
    "addr:full":"Place Cri Du Perron 2 Saint-nicolas (montegn\u00e9e) Li\u00e8ge 4420",
    "addr:housenumber":"2",
    "addr:postcode":"4420",
    "addr:street":"Place Cri Du Perron;Montegne\u0301E",
    "iso:country":"BE",
    "sg:address":"Place Cri Du Perron 2",
    "sg:city":"Saint-nicolas (montegn\u00e9e)",
    "sg:classifiers":[
        {
            "category":"Professional",
            "subcategory":"Testing Lab",
            "type":"Services"
        }
    ],
    "sg:phone":"+32 4 263 44 78",
    "sg:postcode":"4420",
    "sg:province":"Li\u00e8ge",
    "sg:tags":[
        "chemist"
    ],
    "wof:name":"Henry A",
    "wof:placetype":"venue"
},
  "geometry": {"coordinates":[5.5146551132,50.6404075623],"type":"Point"}
}