{
  "type": "Feature",
  "properties": {
    "addr:full":"Rue Emile Vandervelde 380 Fontaine-l'ev\u00eaque (forchies-la-marche) Hainaut 6141",
    "addr:housenumber":"380",
    "addr:postcode":"6141",
    "addr:street":"Rue Emile Vandervelde;Hainaut",
    "iso:country":"BE",
    "sg:address":"Rue Emile Vandervelde 380",
    "sg:city":"Fontaine-l'ev\u00eaque (forchies-la-marche)",
    "sg:classifiers":[
        {
            "category":"Building & Trades",
            "subcategory":"Pest Control",
            "type":"Services"
        }
    ],
    "sg:phone":"+32 71 54 37 70",
    "sg:postcode":"6141",
    "sg:province":"Hainaut",
    "sg:tags":[
        "painting",
        "contractor"
    ],
    "wof:name":"Reno-propre",
    "wof:placetype":"venue"
},
  "geometry": {"coordinates":[-111.9644622803,46.2507972717],"type":"Point"}
}