{
  "type": "Feature",
  "properties": {
    "addr:full":"Rue Coquer\u00c9e 49 Ottignies-louvain-la-neuve Brabant Wallon 1341",
    "addr:housenumber":"49",
    "addr:postcode":"1341",
    "addr:street":"Rue Coquere\u0301E",
    "iso:country":"BE",
    "sg:address":"Rue Coquer\u00c9e 49",
    "sg:city":"Ottignies-louvain-la-neuve",
    "sg:classifiers":[
        {
            "category":"Arena",
            "subcategory":"Sports Club",
            "type":"Entertainment"
        }
    ],
    "sg:phone":"+32 10 61 46 95",
    "sg:postcode":"1341",
    "sg:province":"Brabant Wallon",
    "sg:tags":[
        "de"
    ],
    "wof:name":"Les Compagnons De La Dyle Romane",
    "wof:placetype":"venue"
},
  "geometry": {"coordinates":[4.5627598763,50.6583099365],"type":"Point"}
}