{
  "type": "Feature",
  "properties": {
    "iso:country":"BE",
    "sg:address":"Chauss\u00e9e De Verviers 112",
    "sg:city":"Theux",
    "sg:classifiers":[
        {
            "category":"Health Services",
            "subcategory":"Health Practitioner",
            "type":"Services"
        }
    ],
    "sg:phone":"+32 87 54 28 07",
    "sg:postcode":"4910",
    "sg:province":"Li\u00e8ge",
    "sg:tags":[
        "physiotherapist"
    ],
    "wof:name":"Cormanne Fabienne",
    "wof:placetype":"venue"
},
  "geometry": {"coordinates":[5.8310518265,50.5438270569],"type":"Point"}
}