{
  "type": "Feature",
  "properties": {
    "iso:country":"BE",
    "sg:address":"Rue De Bouffioulx 20",
    "sg:city":"Chatelet",
    "sg:orig_category":"Brood, gebak and snoepgoed",
    "sg:phone":"+32 71 38 06 80",
    "sg:postcode":"6200",
    "sg:province":"Hainaut",
    "wof:name":"Goossens",
    "wof:placetype":"venue"
},
  "geometry": {"coordinates":[4.5210199356,50.4036903381],"type":"Point"}
}