{
  "type": "Feature",
  "properties": {
    "addr:full":"Kerstenmannekensstraat 1 Brussel/bruxelles Bruxelles-Capitale 1000",
    "addr:housenumber":"1",
    "addr:postcode":"1000",
    "addr:street":"Kerstenmannekensstraat;/",
    "iso:country":"BE",
    "sg:address":"Kerstenmannekensstraat 1",
    "sg:city":"Brussel/bruxelles",
    "sg:orig_category":"Zalen voor culturele evenementen",
    "sg:phone":"+32 2 511 65 78",
    "sg:postcode":"1000",
    "sg:province":"Bruxelles-Capitale",
    "wof:name":"Polaris",
    "wof:placetype":"venue"
},
  "geometry": {"coordinates":[4.3534770012,50.8453025818],"type":"Point"}
}