{
  "type": "Feature",
  "properties": {
    "iso:country":"BE",
    "sg:address":"Avenue Des Saisons 29",
    "sg:city":"Elsene/ixelles",
    "sg:orig_category":"Verbruikerskredietinstellingen",
    "sg:phone":"+32 2 644 33 58",
    "sg:postcode":"1050",
    "sg:province":"Bruxelles-Capitale",
    "wof:name":"Wauthier Y.",
    "wof:placetype":"venue"
},
  "geometry": {"coordinates":[4.3861169815,50.8196525574],"type":"Point"}
}