{
  "type": "Feature",
  "properties": {
    "iso:country":"BE",
    "sg:address":"Wouwersdreef 39",
    "sg:city":"Schoten",
    "sg:classifiers":[
        {
            "category":"Building & Trades",
            "subcategory":"Plumbing",
            "type":"Services"
        }
    ],
    "sg:phone":"+32 3 658 18 99",
    "sg:postcode":"2900",
    "sg:province":"Antwerpen",
    "sg:tags":[
        "contractor"
    ],
    "wof:name":"L Vervoort Loodgieterij Bvba",
    "wof:placetype":"venue"
},
  "geometry": {"coordinates":[4.5424809456,51.2710914612],"type":"Point"}
}