{
  "type": "Feature",
  "properties": {
    "addr:full":"Rue La Ferme D\u00b4en Haut 48 Profondeville Namur 5170",
    "addr:housenumber":"48",
    "addr:postcode":"5170",
    "addr:street":"Rue La Ferme D\u00b4En Haut",
    "iso:country":"BE",
    "sg:address":"Rue La Ferme D\u00b4en Haut 48",
    "sg:city":"Profondeville",
    "sg:classifiers":[
        {
            "category":"Arena",
            "subcategory":"Sports Club",
            "type":"Entertainment"
        }
    ],
    "sg:phone":"+32 81 41 32 71",
    "sg:postcode":"5170",
    "sg:province":"Namur",
    "sg:tags":[
        "terrain",
        "hors",
        "de",
        "installation",
        "sportifs"
    ],
    "wof:name":"R.c.s. Profondeville",
    "wof:placetype":"venue"
},
  "geometry": {"coordinates":[4.8646740913,50.3724365234],"type":"Point"}
}