{
  "type": "Feature",
  "properties": {
    "iso:country":"BE",
    "sg:address":"Clos Des Hauts Aimonts 3",
    "sg:city":"Jurbise",
    "sg:orig_category":"Artsen and specialisten",
    "sg:phone":"+32 65 22 61 56",
    "sg:postcode":"7050",
    "sg:province":"Hainaut",
    "wof:name":"Daniel Vercruysse",
    "wof:placetype":"venue"
},
  "geometry": {"coordinates":[3.8845689297,50.5049514771],"type":"Point"}
}