{
  "type": "Feature",
  "properties": {
    "addr:full":"Frans Beirenslaan 299 Borsbeek Antwerpen 2150",
    "addr:housenumber":"299",
    "addr:postcode":"2150",
    "addr:street":"Frans Beirenslaan",
    "iso:country":"BE",
    "sg:address":"Frans Beirenslaan 299",
    "sg:city":"Borsbeek",
    "sg:classifiers":[
        {
            "category":"Home & Garden",
            "subcategory":"Carpets & Floor Coverings",
            "type":"Retail Goods"
        }
    ],
    "sg:phone":"+32 3 322 45 31",
    "sg:postcode":"2150",
    "sg:province":"Antwerpen",
    "sg:tags":[
        "layer",
        "mosaicists"
    ],
    "wof:name":"Rottiers W",
    "wof:placetype":"venue"
},
  "geometry": {"coordinates":[4.4844331741,51.2014541626],"type":"Point"}
}