{
  "type": "Feature",
  "properties": {
    "addr:full":"Polenlaan 47 Stekene Oost-Vlaanderen 9190",
    "addr:housenumber":"47",
    "addr:postcode":"9190",
    "addr:street":"Polenlaan",
    "iso:country":"BE",
    "sg:address":"Polenlaan 47",
    "sg:city":"Stekene",
    "sg:classifiers":[
        {
            "category":"Insurance",
            "subcategory":"Life Insurance",
            "type":"Services"
        }
    ],
    "sg:phone":"+32 3 779 99 84",
    "sg:postcode":"9190",
    "sg:province":"Oost-Vlaanderen",
    "sg:tags":[
        "assurance"
    ],
    "wof:name":"Van Duyse Verzekeringen",
    "wof:placetype":"venue"
},
  "geometry": {"coordinates":[4.0429182053,51.2082519531],"type":"Point"}
}