{
  "type": "Feature",
  "properties": {
    "iso:country":"BE",
    "sg:address":"Schoterweg 205",
    "sg:city":"Tessenderlo",
    "sg:classifiers":[
        {
            "category":"Communications",
            "type":"Services"
        }
    ],
    "sg:phone":"+32 13 66 19 75",
    "sg:postcode":"3980",
    "sg:province":"Limburg",
    "sg:tags":[
        "translator"
    ],
    "wof:name":"Japan Consulting Service",
    "wof:placetype":"venue"
},
  "geometry": {"coordinates":[5.0284900665,51.0672798157],"type":"Point"}
}