{
  "type": "Feature",
  "properties": {
    "addr:full":"Avenue De Merode 33 Rixensart Brabant Wallon 1330",
    "addr:housenumber":"33",
    "addr:postcode":"1330",
    "addr:street":"Avenue De Merode;Wallon",
    "iso:country":"BE",
    "sg:address":"Avenue De Merode 33",
    "sg:city":"Rixensart",
    "sg:classifiers":[
        {
            "category":"Organizations",
            "subcategory":"Community Association",
            "type":"Services"
        }
    ],
    "sg:phone":"+32 2 653 56 67",
    "sg:postcode":"1330",
    "sg:province":"Brabant Wallon",
    "sg:tags":[
        "organisation"
    ],
    "wof:name":"Maison Des Jeunes",
    "wof:placetype":"venue"
},
  "geometry": {"coordinates":[4.5276050568,50.7123565674],"type":"Point"}
}