{
  "type": "Feature",
  "properties": {
    "iso:country":"BE",
    "sg:address":"Avenue Notre-dame 121",
    "sg:city":"Evere/evere",
    "sg:orig_category":"M\u00e9decins and sp\u00e9cialistes",
    "sg:phone":"+32 2 241 02 01",
    "sg:postcode":"1140",
    "sg:province":"Bruxelles-Capitale",
    "wof:name":"Eric Koelman",
    "wof:placetype":"venue"
},
  "geometry": {"coordinates":[4.4011220932,50.8715133667],"type":"Point"}
}