{
  "type": "Feature",
  "properties": {
    "iso:country":"BE",
    "sg:address":"Aandorenstraat 31",
    "sg:city":"Tienen",
    "sg:classifiers":[
        {
            "category":"Autos & Motor Vehicles",
            "subcategory":"Automobile Sales",
            "type":"Retail Goods"
        }
    ],
    "sg:phone":"+32 475 62 31 48",
    "sg:postcode":"3300",
    "sg:province":"Vlaams-Brabant",
    "sg:tags":[
        "ceremony",
        "car"
    ],
    "wof:name":"Govaerts-vangilbergen",
    "wof:placetype":"venue"
},
  "geometry": {"coordinates":[4.9507060051,50.8017692566],"type":"Point"}
}