{
  "type": "Feature",
  "properties": {
    "addr:full":"Haagstraat 1 Puurs Antwerpen 2870",
    "addr:housenumber":"1",
    "addr:postcode":"2870",
    "addr:street":"Haagstraat",
    "iso:country":"BE",
    "sg:address":"Haagstraat 1",
    "sg:city":"Puurs",
    "sg:orig_category":"Producteurs de l\u00e9gumes",
    "sg:phone":"+32 3 889 03 76",
    "sg:postcode":"2870",
    "sg:province":"Antwerpen",
    "wof:name":"August Van Oostenryk",
    "wof:placetype":"venue"
},
  "geometry": {"coordinates":[4.3139882088,51.0562133789],"type":"Point"}
}