{
  "type": "Feature",
  "properties": {
    "iso:country":"BE",
    "sg:address":"Rue Charles Maniate 1",
    "sg:city":"Li\u00c8ge",
    "sg:orig_category":"Journaux. Tabac",
    "sg:phone":"+32 4 223 56 58",
    "sg:postcode":"4000",
    "sg:province":"Li\u00e8ge",
    "wof:name":"Librairie Chuller",
    "wof:placetype":"venue"
},
  "geometry": {"coordinates":[5.5744819641,50.6409721375],"type":"Point"}
}