{
  "type": "Feature",
  "properties": {
    "iso:country":"BE",
    "sg:address":"Kerkhofstraat 37",
    "sg:city":"Diksmuide (woumen)",
    "sg:classifiers":[
        {
            "category":"Personal",
            "subcategory":"Beauty Salon",
            "type":"Services"
        }
    ],
    "sg:phone":"+32 51 50 13 85",
    "sg:postcode":"8600",
    "sg:province":"West-Vlaanderen",
    "sg:tags":[
        "lady",
        "-",
        "hairdressing"
    ],
    "wof:name":"Ghysselen M",
    "wof:placetype":"venue"
},
  "geometry": {"coordinates":[2.8709750175,51.0027198792],"type":"Point"}
}