{
  "type": "Feature",
  "properties": {
    "iso:country":"BE",
    "sg:address":"Markt 31",
    "sg:city":"Sint-katelijne-waver",
    "sg:orig_category":"Pain, p\u00e2tisseries and confiseries",
    "sg:phone":"+32 15 31 33 52",
    "sg:postcode":"2860",
    "sg:province":"Antwerpen",
    "wof:name":"Brabants Confiserie",
    "wof:placetype":"venue"
},
  "geometry": {"coordinates":[4.5325779915,51.0704040527],"type":"Point"}
}