{
  "type": "Feature",
  "properties": {
    "iso:country":"BE",
    "sg:address":"Rue Des Chanterelles 36",
    "sg:city":"Charleroi (goutroux)",
    "sg:orig_category":"Ice-cream parlours",
    "sg:phone":"+32 497 81 45 31",
    "sg:postcode":"6030",
    "sg:province":"Hainaut",
    "wof:name":"Frimapower",
    "wof:placetype":"venue"
},
  "geometry": {"coordinates":[4.36714077,50.4205322266],"type":"Point"}
}