{
  "type": "Feature",
  "properties": {
    "iso:country":"BE",
    "sg:address":"Wezenstraat 8",
    "sg:city":"Melle",
    "sg:orig_category":"Enseignement maternel and primaire",
    "sg:phone":"+32 9 252 27 87",
    "sg:postcode":"9090",
    "sg:province":"Oost-Vlaanderen",
    "wof:name":"Vrije Basisschool",
    "wof:placetype":"venue"
},
  "geometry": {"coordinates":[3.8002409935,51.0047569275],"type":"Point"}
}