{
  "type": "Feature",
  "properties": {
    "addr:full":"Woeringenstraat 16 Nijlen Antwerpen 2560",
    "addr:housenumber":"16",
    "addr:postcode":"2560",
    "addr:street":"Woeringenstraat",
    "iso:country":"BE",
    "sg:address":"Woeringenstraat 16",
    "sg:city":"Nijlen",
    "sg:classifiers":[
        {
            "category":"Home & Garden",
            "subcategory":"Building Materials",
            "type":"Retail Goods"
        }
    ],
    "sg:phone":"+32 3 481 86 96",
    "sg:postcode":"2560",
    "sg:province":"Antwerpen",
    "sg:tags":[
        "article",
        "-",
        "do-it-yourself"
    ],
    "wof:name":"Bernaerts D",
    "wof:placetype":"venue"
},
  "geometry": {"coordinates":[4.6735801697,51.1609954834],"type":"Point"}
}