{
  "type": "Feature",
  "properties": {
    "iso:country":"BE",
    "sg:address":"Molenweg 46",
    "sg:city":"Gistel (groot)",
    "sg:orig_category":"Traitements param\u00e9dicaux",
    "sg:phone":"+32 59 30 69 67",
    "sg:postcode":"8470",
    "sg:province":"West-Vlaanderen",
    "wof:name":"Baert Ruben",
    "wof:placetype":"venue"
},
  "geometry": {"coordinates":[2.9556500912,51.1484603882],"type":"Point"}
}