{
  "type": "Feature",
  "properties": {
    "addr:full":"Rue Vandervelde 107 Forchies La March\u00e9 Hainaut 6150",
    "addr:housenumber":"107",
    "addr:postcode":"6150",
    "addr:street":"Rue Vandervelde;La;Hainaut",
    "iso:country":"BE",
    "sg:address":"Rue Vandervelde 107",
    "sg:city":"Forchies La March\u00e9",
    "sg:classifiers":[
        {
            "category":"Banks & Credit Unions",
            "subcategory":"Bank",
            "type":"Services"
        }
    ],
    "sg:phone":"+32 81 52 50 32",
    "sg:postcode":"6150",
    "sg:province":"Hainaut",
    "wof:name":"G\u00e9n\u00e9rale De Banque Sa",
    "wof:placetype":"venue"
},
  "geometry": {"coordinates":[4.269701004,50.4036712646],"type":"Point"}
}