{
  "type": "Feature",
  "properties": {
    "addr:full":"Chauss\u00e9e D'alsemberg 1051 Bruxelles (uccle) Bruxelles-Capitale 1180",
    "addr:postcode":"1051;1180",
    "addr:street":"Chausse\u0301E D'Alsemberg",
    "iso:country":"BE",
    "sg:address":"Chauss\u00e9e D'alsemberg 1051",
    "sg:city":"Bruxelles (uccle)",
    "sg:classifiers":[
        {
            "category":"Home & Garden",
            "subcategory":"Carpets & Floor Coverings",
            "type":"Retail Goods"
        }
    ],
    "sg:phone":"+32 2 376 63 52",
    "sg:postcode":"1180",
    "sg:province":"Bruxelles-Capitale",
    "sg:tags":[
        "layer",
        "mosaicists"
    ],
    "wof:name":"Campisi P",
    "wof:placetype":"venue"
},
  "geometry": {"coordinates":[4.3328361511,50.7922706604],"type":"Point"}
}