{
  "type": "Feature",
  "properties": {
    "addr:full":"Brugstraat 4 Laarne Oost-Vlaanderen 9270",
    "addr:housenumber":"4",
    "addr:postcode":"9270",
    "addr:street":"Brugstraat",
    "iso:country":"BE",
    "sg:address":"Brugstraat 4",
    "sg:city":"Laarne",
    "sg:orig_category":"Schoonmaakbedrijven and ongediertebestrijding",
    "sg:phone":"+32 9 367 75 63",
    "sg:postcode":"9270",
    "sg:province":"Oost-Vlaanderen",
    "wof:name":"Petrus Bracke",
    "wof:placetype":"venue"
},
  "geometry": {"coordinates":[3.8911919594,51.0450363159],"type":"Point"}
}