{
  "type": "Feature",
  "properties": {
    "addr:full":"Bergensesteenweg 70 Halle Vlaams-Brabant 1500",
    "addr:housenumber":"70",
    "addr:postcode":"1500",
    "addr:street":"Bergensesteenweg",
    "iso:country":"BE",
    "sg:address":"Bergensesteenweg 70",
    "sg:city":"Halle",
    "sg:orig_category":"Babyspullen",
    "sg:phone":"+32 2 361 26 60",
    "sg:postcode":"1500",
    "sg:province":"Vlaams-Brabant",
    "wof:name":"J & J",
    "wof:placetype":"venue"
},
  "geometry": {"coordinates":[4.2316617966,50.7324028015],"type":"Point"}
}