{
  "type": "Feature",
  "properties": {
    "addr:full":"Rue De Jeneffe 80 Fexhe-le-haut-clocher Li\u00e8ge 4347",
    "addr:housenumber":"80",
    "addr:postcode":"4347",
    "addr:street":"Rue De Jeneffe",
    "iso:country":"BE",
    "sg:address":"Rue De Jeneffe 80",
    "sg:city":"Fexhe-le-haut-clocher",
    "sg:orig_category":"V\u00e9hicules automobiles",
    "sg:phone":"+32 4 250 27 59",
    "sg:postcode":"4347",
    "sg:province":"Li\u00e8ge",
    "wof:name":"Garage Lelubre",
    "wof:placetype":"venue"
},
  "geometry": {"coordinates":[5.396062851,50.6519546509],"type":"Point"}
}