{
  "type": "Feature",
  "properties": {
    "addr:full":"Rue Du Cortil 91ba Fleurus Hainaut 6224",
    "addr:housenumber":"91ba",
    "addr:postcode":"6224",
    "addr:street":"Rue Du Cortil",
    "iso:country":"BE",
    "sg:address":"Rue Du Cortil 91ba",
    "sg:city":"Fleurus",
    "sg:classifiers":[
        {
            "category":"Cafe",
            "type":"Food & Drink"
        }
    ],
    "sg:phone":"+32 71 81 06 09",
    "sg:postcode":"6224",
    "sg:province":"Hainaut",
    "sg:tags":[
        "caf\u00e9s"
    ],
    "wof:name":"Caf\u00c9 Le Rouet",
    "wof:placetype":"venue"
},
  "geometry": {"coordinates":[4.5820741653,50.461517334],"type":"Point"}
}