{
  "type": "Feature",
  "properties": {
    "addr:full":"Groenewandeling 46 Gent Oost-Vlaanderen 9031",
    "addr:housenumber":"46",
    "addr:postcode":"9031",
    "addr:street":"Groenewandeling;Oost-Vlaanderen",
    "iso:country":"BE",
    "sg:address":"Groenewandeling 46",
    "sg:city":"Gent",
    "sg:orig_category":"Artistes ind\u00e9pendants",
    "sg:phone":"+32 9 227 65 88",
    "sg:postcode":"9031",
    "sg:province":"Oost-Vlaanderen",
    "wof:name":"Dirk Blanchaert",
    "wof:placetype":"venue"
},
  "geometry": {"coordinates":[3.657449007,51.0553321838],"type":"Point"}
}