{
  "type": "Feature",
  "properties": {
    "iso:country":"BE",
    "sg:address":"Steenbrugsestraat 30",
    "sg:city":"Zedelgem (loppem)",
    "sg:classifiers":[
        {
            "category":"Shopping",
            "subcategory":"Party Supplies",
            "type":"Retail Goods"
        }
    ],
    "sg:phone":"+32 50 82 27 81",
    "sg:postcode":"8210",
    "sg:province":"West-Vlaanderen",
    "sg:tags":[
        "rental",
        "-"
    ],
    "wof:name":"'t Evershof Voorheen St-elooi",
    "wof:placetype":"venue"
},
  "geometry": {"coordinates":[3.1458399296,51.1376457214],"type":"Point"}
}