{
  "type": "Feature",
  "properties": {
    "iso:country":"BE",
    "sg:address":"Rue De L'etat 2a",
    "sg:city":"Yvoir",
    "sg:orig_category":"Kantoormateriaal Gh",
    "sg:phone":"+32 83 69 97 59",
    "sg:postcode":"5530",
    "sg:province":"Namur",
    "wof:name":"Debemat",
    "wof:placetype":"venue"
},
  "geometry": {"coordinates":[4.9761128426,50.315158844],"type":"Point"}
}