{
  "type": "Feature",
  "properties": {
    "addr:full":"Chauss\u00c9e Paul Houtart 339 La Louvi\u00c8re Hainaut 7110",
    "addr:housenumber":"339",
    "addr:postcode":"7110",
    "addr:street":"Chausse\u0301E Paul Houtart",
    "iso:country":"BE",
    "sg:address":"Chauss\u00c9e Paul Houtart 339",
    "sg:city":"La Louvi\u00c8re",
    "sg:orig_category":"Kinderopvang",
    "sg:phone":"+32 64 28 38 33",
    "sg:postcode":"7110",
    "sg:province":"Hainaut",
    "wof:name":"Cr\u00c8che Communale",
    "wof:placetype":"venue"
},
  "geometry": {"coordinates":[4.1543450356,50.488067627],"type":"Point"}
}