{
  "type": "Feature",
  "properties": {
    "iso:country":"BE",
    "sg:address":"Houtstraat 37",
    "sg:city":"Destelbergen",
    "sg:orig_category":"Services pour animaux domestiques",
    "sg:phone":"+32 9 228 00 19",
    "sg:postcode":"9070",
    "sg:province":"Oost-Vlaanderen",
    "wof:name":"Dikie's",
    "wof:placetype":"venue"
},
  "geometry": {"coordinates":[3.809525013,51.0681304932],"type":"Point"}
}