{
  "type": "Feature",
  "properties": {
    "addr:full":"Kanaaldijk 4d Ravels Antwerpen 2380",
    "addr:housenumber":"4d",
    "addr:postcode":"2380",
    "addr:street":"Kanaaldijk",
    "iso:country":"BE",
    "sg:address":"Kanaaldijk 4d",
    "sg:city":"Ravels",
    "sg:classifiers":[
        {
            "category":"Manufacturing",
            "subcategory":"Tools & Machinery",
            "type":"Manufacturing & Wholesale Goods"
        }
    ],
    "sg:phone":"+32 14 65 05 50",
    "sg:postcode":"2380",
    "sg:province":"Antwerpen",
    "sg:tags":[
        "scale"
    ],
    "wof:name":"Pm Benelux",
    "wof:placetype":"venue"
},
  "geometry": {"coordinates":[4.9858789444,51.3611488342],"type":"Point"}
}