{
  "type": "Feature",
  "properties": {
    "iso:country":"BE",
    "sg:address":"Bornstraat 54",
    "sg:city":"Kortessem (vliermaalroot)",
    "sg:classifiers":[
        {
            "category":"Health Services",
            "subcategory":"Health Practitioner",
            "type":"Services"
        }
    ],
    "sg:phone":"+32 476 89 59 72",
    "sg:postcode":"3721",
    "sg:province":"Limburg",
    "sg:tags":[
        "physiotherapist"
    ],
    "wof:name":"Cartenstadt Cindy",
    "wof:placetype":"venue"
},
  "geometry": {"coordinates":[5.4354357719,50.8692359924],"type":"Point"}
}