{
  "type": "Feature",
  "properties": {
    "addr:full":"Dreefstraat 14 Herzele Oost-Vlaanderen 9552",
    "addr:housenumber":"14",
    "addr:postcode":"9552",
    "addr:street":"Dreefstraat;Oost-Vlaanderen",
    "iso:country":"BE",
    "sg:address":"Dreefstraat 14",
    "sg:city":"Herzele",
    "sg:orig_category":"Installatie van houten of kunststof schrijnwerk",
    "sg:phone":"+32 53 62 56 99",
    "sg:postcode":"9552",
    "sg:province":"Oost-Vlaanderen",
    "wof:name":"Gilbert De Cooman",
    "wof:placetype":"venue"
},
  "geometry": {"coordinates":[3.8856599331,50.9053115845],"type":"Point"}
}