{
  "type": "Feature",
  "properties": {
    "addr:full":"Chemin Pr\u00c9 De Beauterre 1 Leuze-en-hainaut Hainaut 7901",
    "addr:housenumber":"1",
    "addr:postcode":"7901",
    "addr:street":"Chemin Pre\u0301 De Beauterre",
    "iso:country":"BE",
    "sg:address":"Chemin Pr\u00c9 De Beauterre 1",
    "sg:city":"Leuze-en-hainaut",
    "sg:orig_category":"Rundveehouders",
    "sg:phone":"+32 69 66 24 37",
    "sg:postcode":"7901",
    "sg:province":"Hainaut",
    "wof:name":"Gaston Marichal",
    "wof:placetype":"venue"
},
  "geometry": {"coordinates":[3.6130108833,50.6235542297],"type":"Point"}
}