{
  "type": "Feature",
  "properties": {
    "iso:country":"BE",
    "sg:address":"Kapelanielaan 9a",
    "sg:city":"Temse",
    "sg:orig_category":"V\u00e9hicules automobiles",
    "sg:phone":"+32 3 771 47 53",
    "sg:postcode":"9140",
    "sg:province":"Oost-Vlaanderen",
    "wof:name":"Waasland Motor",
    "wof:placetype":"venue"
},
  "geometry": {"coordinates":[4.1830821037,51.1364631653],"type":"Point"}
}