{
  "type": "Feature",
  "properties": {
    "iso:country":"BE",
    "sg:address":"Chauss\u00c9e De Marche 464",
    "sg:city":"Erpent",
    "sg:orig_category":"Fietsen",
    "sg:phone":"+32 81 31 21 81",
    "sg:postcode":"5101",
    "sg:province":"Namur",
    "wof:name":"Helios Namur",
    "wof:placetype":"venue"
},
  "geometry": {"coordinates":[4.8977937698,50.4464569092],"type":"Point"}
}