{
  "type": "Feature",
  "properties": {
    "addr:full":"Avenue Des Princes Braban\u00e7ons 55-57 Bruxelles (watermael-boitsfort) Bruxelles-Capitale 1170",
    "addr:housenumber":"55-57",
    "addr:postcode":"1170",
    "addr:street":"Avenue Des Princes Brabanc\u0327Ons",
    "iso:country":"BE",
    "sg:address":"Avenue Des Princes Braban\u00e7ons 55-57",
    "sg:city":"Bruxelles (watermael-boitsfort)",
    "sg:orig_category":"Oldtimers",
    "sg:phone":"+32 2 660 40 65",
    "sg:postcode":"1170",
    "sg:province":"Bruxelles-Capitale",
    "wof:name":"Roland G",
    "wof:placetype":"venue"
},
  "geometry": {"coordinates":[4.4153409004,50.8100891113],"type":"Point"}
}