{
  "type": "Feature",
  "properties": {
    "addr:full":"Avenue Jean Derave 8 Binche Hainaut 7130",
    "addr:housenumber":"8",
    "addr:postcode":"7130",
    "addr:street":"Avenue Jean Derave",
    "iso:country":"BE",
    "sg:address":"Avenue Jean Derave 8",
    "sg:city":"Binche",
    "sg:orig_category":"Maatschappelijke dienstverlening",
    "sg:phone":"+32 64 33 28 55",
    "sg:postcode":"7130",
    "sg:province":"Hainaut",
    "wof:name":"Centre P.m.s.",
    "wof:placetype":"venue"
},
  "geometry": {"coordinates":[4.1728510857,50.4099464417],"type":"Point"}
}