{
  "type": "Feature",
  "properties": {
    "addr:full":"Pladijsstraat 21 Deerlijk West-Vlaanderen 8540",
    "addr:housenumber":"21",
    "addr:postcode":"8540",
    "addr:street":"Pladijsstraat",
    "iso:country":"BE",
    "sg:address":"Pladijsstraat 21",
    "sg:city":"Deerlijk",
    "sg:orig_category":"V\u00e9hicules automobiles",
    "sg:phone":"+32 56 77 78 45",
    "sg:postcode":"8540",
    "sg:province":"West-Vlaanderen",
    "wof:name":"Garage Schwind",
    "wof:placetype":"venue"
},
  "geometry": {"coordinates":[3.3545639515,50.8337974548],"type":"Point"}
}