{
  "type": "Feature",
  "properties": {
    "addr:full":"Grotehondstraat 5 Antwerpen Antwerpen 2018",
    "addr:housenumber":"5",
    "addr:postcode":"2018",
    "addr:street":"Grotehondstraat",
    "iso:country":"BE",
    "sg:address":"Grotehondstraat 5",
    "sg:city":"Antwerpen",
    "sg:orig_category":"Maatschappelijke dienstverlening",
    "sg:phone":"+32 3 230 26 87",
    "sg:postcode":"2018",
    "sg:province":"Antwerpen",
    "wof:name":"Kinderzorg",
    "wof:placetype":"venue"
},
  "geometry": {"coordinates":[4.4269881248,51.2062225342],"type":"Point"}
}