{
  "type": "Feature",
  "properties": {
    "addr:full":"Oosterveldlaan 273 Mortsel Antwerpen 2640",
    "addr:housenumber":"273",
    "addr:postcode":"2640",
    "addr:street":"Oosterveldlaan",
    "iso:country":"BE",
    "sg:address":"Oosterveldlaan 273",
    "sg:city":"Mortsel",
    "sg:orig_category":"Proef- and grondboringen",
    "sg:phone":"+32 3 448 08 63",
    "sg:postcode":"2640",
    "sg:province":"Antwerpen",
    "wof:name":"Terraconsult",
    "wof:placetype":"venue"
},
  "geometry": {"coordinates":[4.4359197617,51.1767883301],"type":"Point"}
}