{
  "type": "Feature",
  "properties": {
    "addr:full":"Rue De L'echauffour\u00e9e 13 Mouscron Hainaut 7700",
    "addr:housenumber":"13",
    "addr:postcode":"7700",
    "addr:street":"Rue De L'Echauffoure \u0301E",
    "iso:country":"BE",
    "sg:address":"Rue De L'echauffour\u00e9e 13",
    "sg:city":"Mouscron",
    "sg:classifiers":[
        {
            "category":"Food & Beverages",
            "subcategory":"Liquor & Beverages",
            "type":"Retail Goods"
        }
    ],
    "sg:phone":"+32 56 85 52 00",
    "sg:postcode":"7700",
    "sg:province":"Hainaut",
    "sg:tags":[
        "-",
        "spirit",
        "wine"
    ],
    "wof:name":"Royale Cave Sprl",
    "wof:placetype":"venue"
},
  "geometry": {"coordinates":[3.1822490692,50.7528762817],"type":"Point"}
}