{
  "type": "Feature",
  "properties": {
    "iso:country":"BE",
    "sg:address":"148",
    "sg:city":"Hannuitsesteenweg 3401 Landen Walshoutem",
    "sg:classifiers":[
        {
            "category":"Travel",
            "subcategory":"Hotels & Motels",
            "type":"Entertainment"
        }
    ],
    "sg:phone":"+32 11 88 29 94",
    "sg:postcode":"148",
    "sg:tags":[
        "hotels",
        "business",
        "restaurant"
    ],
    "wof:name":"Traiteur Marcel Nv",
    "wof:placetype":"venue"
},
  "geometry": {"coordinates":[5.0810899734,50.7410583496],"type":"Point"}
}