{
  "type": "Feature",
  "properties": {
    "iso:country":"BE",
    "sg:address":"Markt 41",
    "sg:city":"Gavere",
    "sg:classifiers":[
        {
            "category":"Banks & Credit Unions",
            "subcategory":"Bank",
            "type":"Services"
        }
    ],
    "sg:phone":"+32 54 84 17 10",
    "sg:postcode":"9740",
    "wof:name":"G\u00e9n\u00e9rale De Banque Sa",
    "wof:placetype":"venue"
},
  "geometry": {"coordinates":[3.6598849297,50.9299964905],"type":"Point"}
}