{
  "type": "Feature",
  "properties": {
    "iso:country":"BE",
    "sg:address":"Meeuwerweg 33",
    "sg:city":"Houthalen-helchteren (houthalen)",
    "sg:classifiers":[
        {
            "category":"Shopping",
            "subcategory":"Antiques",
            "type":"Retail Goods"
        }
    ],
    "sg:phone":"+32 11 52 43 70",
    "sg:postcode":"3530",
    "sg:province":"Limburg",
    "sg:tags":[
        "restoration"
    ],
    "wof:name":"Vaes W",
    "wof:placetype":"venue"
},
  "geometry": {"coordinates":[5.398747921,51.035697937],"type":"Point"}
}