{
  "type": "Feature",
  "properties": {
    "addr:full":"Koningin Astridlaan 78 Brugge (sint-michiels) West-Vlaanderen 8200",
    "addr:housenumber":"78",
    "addr:postcode":"8200",
    "addr:street":"Koningin Astridlaan",
    "iso:country":"BE",
    "sg:address":"Koningin Astridlaan 78",
    "sg:city":"Brugge (sint-michiels)",
    "sg:classifiers":[
        {
            "category":"Banks & Credit Unions",
            "subcategory":"Investment Brokerage",
            "type":"Services"
        }
    ],
    "sg:phone":"+32 50 38 32 92",
    "sg:postcode":"8200",
    "sg:province":"West-Vlaanderen",
    "sg:tags":[
        "repair",
        "-",
        "installation",
        "sanitary",
        "article"
    ],
    "wof:name":"Temalec",
    "wof:placetype":"venue"
},
  "geometry": {"coordinates":[3.2493569851,51.1991119385],"type":"Point"}
}