{
  "type": "Feature",
  "properties": {
    "addr:full":"Stationsstraat 131 Landen Vlaams-Brabant 3400",
    "addr:housenumber":"131",
    "addr:postcode":"3400",
    "addr:street":"Stationsstraat",
    "iso:country":"BE",
    "sg:address":"Stationsstraat 131",
    "sg:city":"Landen",
    "sg:orig_category":"Pain, p\u00e2tisseries and confiseries",
    "sg:phone":"+32 11 88 26 98",
    "sg:postcode":"3400",
    "sg:province":"Vlaams-Brabant",
    "wof:name":"\u00b4t Croissanterietje",
    "wof:placetype":"venue"
},
  "geometry": {"coordinates":[5.0810008049,50.7485580444],"type":"Point"}
}