{
  "type": "Feature",
  "properties": {
    "addr:full":"Rue Haute 269 Eupen/eupen Li\u00e8ge 4701",
    "addr:housenumber":"269",
    "addr:postcode":"4701",
    "addr:street":"Rue Haute",
    "iso:country":"BE",
    "sg:address":"Rue Haute 269",
    "sg:city":"Eupen/eupen",
    "sg:orig_category":"Quincailleries",
    "sg:phone":"+32 87 55 41 29",
    "sg:postcode":"4701",
    "sg:province":"Li\u00e8ge",
    "wof:name":"Fabienne Nyssen",
    "wof:placetype":"venue"
},
  "geometry": {"coordinates":[6.0461649895,50.6460838318],"type":"Point"}
}