{
  "type": "Feature",
  "properties": {
    "addr:full":"Avenue Des Bouleaux 28 Watermaal-bosvoorde/watermael-boitsfort Bruxelles-Capitale 1170",
    "addr:housenumber":"28",
    "addr:postcode":"1170",
    "addr:street":"Avenue Des Bouleaux",
    "iso:country":"BE",
    "sg:address":"Avenue Des Bouleaux 28",
    "sg:city":"Watermaal-bosvoorde/watermael-boitsfort",
    "sg:orig_category":"M\u00e9decins and sp\u00e9cialistes",
    "sg:phone":"+32 2 673 90 72",
    "sg:postcode":"1170",
    "sg:province":"Bruxelles-Capitale",
    "wof:name":"Christine De Raikem",
    "wof:placetype":"venue"
},
  "geometry": {"coordinates":[4.4075169563,50.8042602539],"type":"Point"}
}