{
  "type": "Feature",
  "properties": {
    "addr:full":"Kiezelweg 172 Mol Antwerpen 2400",
    "addr:housenumber":"172",
    "addr:postcode":"2400",
    "addr:street":"Kiezelweg",
    "iso:country":"BE",
    "sg:address":"Kiezelweg 172",
    "sg:city":"Mol",
    "sg:classifiers":[
        {
            "category":"Bars & Pubs",
            "type":"Food & Drink"
        }
    ],
    "sg:phone":"+32 14 81 19 23",
    "sg:postcode":"2400",
    "sg:province":"Antwerpen",
    "wof:name":"Gambrinus",
    "wof:placetype":"venue"
},
  "geometry": {"coordinates":[5.1930098534,51.2158508301],"type":"Point"}
}