{
  "type": "Feature",
  "properties": {
    "iso:country":"BE",
    "sg:address":"Rue De La R\u00e9volution 63",
    "sg:city":"Charleroi (jumet)",
    "sg:classifiers":[
        {
            "category":"Health Services",
            "subcategory":"Nursing And Care Facility",
            "type":"Services"
        }
    ],
    "sg:phone":"+32 71 35 18 25",
    "sg:postcode":"6040",
    "sg:province":"Hainaut",
    "sg:tags":[
        "home"
    ],
    "wof:name":"Debetancourt-trefois M",
    "wof:placetype":"venue"
},
  "geometry": {"coordinates":[4.4592471123,50.4437904358],"type":"Point"}
}