{
  "type": "Feature",
  "properties": {
    "iso:country":"BE",
    "sg:address":"Naamsesteenweg 235",
    "sg:city":"Leuven",
    "sg:orig_category":"R\u00e9parations d'horloges, montres and bijoux. Bijouteries and horlogeries",
    "sg:phone":"+32 16 40 62 54",
    "sg:postcode":"3001",
    "sg:province":"Vlaams-Brabant",
    "wof:name":"Desire Allaert",
    "wof:placetype":"venue"
},
  "geometry": {"coordinates":[4.6959300041,50.8615264893],"type":"Point"}
}