{
  "type": "Feature",
  "properties": {
    "iso:country":"BE",
    "sg:address":"Bokkerijdersweg 28",
    "sg:city":"Maaseik",
    "sg:classifiers":[
        {
            "category":"Personal",
            "subcategory":"Beauty Salon",
            "type":"Services"
        }
    ],
    "sg:phone":"+32 89 56 60 70",
    "sg:postcode":"3680",
    "sg:province":"Limburg",
    "sg:tags":[
        "lady",
        "-",
        "hairdressing"
    ],
    "wof:name":"Haarmode Berty",
    "wof:placetype":"venue"
},
  "geometry": {"coordinates":[5.7609891891,51.0857276917],"type":"Point"}
}