{
  "type": "Feature",
  "properties": {
    "iso:country":"BE",
    "sg:address":"Heldergemstraat 124",
    "sg:city":"Haaltert",
    "sg:orig_category":"Artsen and specialisten",
    "sg:phone":"+32 53 63 28 63",
    "sg:postcode":"9450",
    "sg:province":"Oost-Vlaanderen",
    "wof:name":"Marijke De Rijck",
    "wof:placetype":"venue"
},
  "geometry": {"coordinates":[3.9561440945,50.8791046143],"type":"Point"}
}