{
  "type": "Feature",
  "properties": {
    "iso:country":"BE",
    "sg:address":"Rue De Monin 44",
    "sg:city":"Hamois",
    "sg:orig_category":"Slagers",
    "sg:phone":"+32 83 61 28 37",
    "sg:postcode":"5362",
    "sg:province":"Namur",
    "wof:name":"Jacqueline Quoidbach",
    "wof:placetype":"venue"
},
  "geometry": {"coordinates":[5.1514501572,50.3216629028],"type":"Point"}
}