{
  "type": "Feature",
  "properties": {
    "iso:country":"BE",
    "sg:address":"Bredabaan 777",
    "sg:city":"Brasschaat",
    "sg:classifiers":[
        {
            "category":"Bars & Pubs",
            "type":"Food & Drink"
        }
    ],
    "sg:phone":"+32 3 633 21 43",
    "sg:postcode":"2930",
    "sg:province":"Antwerpen",
    "wof:name":"Barcode",
    "wof:placetype":"venue"
},
  "geometry": {"coordinates":[4.5078449249,51.30809021],"type":"Point"}
}