{
  "type": "Feature",
  "properties": {
    "iso:country":"BE",
    "sg:address":"Postweg 35",
    "sg:city":"Sint-pieters-leeuw",
    "sg:orig_category":"Eleveurs de bovins. Producteurs de fruits",
    "sg:phone":"+32 2 569 33 77",
    "sg:postcode":"1602",
    "sg:province":"Vlaams-Brabant",
    "wof:name":"Maurits Segers",
    "wof:placetype":"venue"
},
  "geometry": {"coordinates":[4.2513728142,50.8123779297],"type":"Point"}
}