{
  "type": "Feature",
  "properties": {
    "iso:country":"BE",
    "sg:address":"Rue Paul Spaak 15",
    "sg:city":"Brussel",
    "sg:classifiers":[
        {
            "category":"Restaurant",
            "type":"Food & Drink"
        }
    ],
    "sg:phone":"+32 2 645 68 88",
    "sg:postcode":"1000",
    "sg:province":"Bruxelles-Capitale",
    "wof:name":"La Vacherie",
    "wof:placetype":"venue"
},
  "geometry": {"coordinates":[4.3652777672,50.8284873962],"type":"Point"}
}