{
  "type": "Feature",
  "properties": {
    "iso:country":"BE",
    "sg:address":"Europalaan 121",
    "sg:city":"Halle",
    "sg:orig_category":"Elektrische installaties voor woningen",
    "sg:phone":"+32 2 356 22 87",
    "sg:postcode":"1500",
    "sg:province":"Vlaams-Brabant",
    "wof:name":"Luc Behets",
    "wof:placetype":"venue"
},
  "geometry": {"coordinates":[4.2223410606,50.7205200195],"type":"Point"}
}