{
  "type": "Feature",
  "properties": {
    "addr:full":"Noordomstraat 41 Koekelare West-Vlaanderen 8680",
    "addr:housenumber":"41",
    "addr:postcode":"8680",
    "addr:street":"Noordomstraat",
    "iso:country":"BE",
    "sg:address":"Noordomstraat 41",
    "sg:city":"Koekelare",
    "sg:classifiers":[
        {
            "category":"Shopping",
            "subcategory":"Clothing, Apparel, & Fashions",
            "type":"Retail Goods"
        }
    ],
    "sg:phone":"+32 51 58 25 20",
    "sg:postcode":"8680",
    "sg:province":"West-Vlaanderen",
    "sg:tags":[
        "lady",
        "clothing",
        "-"
    ],
    "wof:name":"Papegaai",
    "wof:placetype":"venue"
},
  "geometry": {"coordinates":[2.9736599922,51.0896224976],"type":"Point"}
}