{
  "type": "Feature",
  "properties": {
    "addr:full":"Nieuwland 8 Aarschot Vlaams-Brabant 3200",
    "addr:housenumber":"8",
    "addr:postcode":"3200",
    "addr:street":"Nieuwland",
    "iso:country":"BE",
    "sg:address":"Nieuwland 8",
    "sg:city":"Aarschot",
    "sg:orig_category":"Boomkwekerijen",
    "sg:phone":"+32 16 56 46 94",
    "sg:postcode":"3200",
    "sg:province":"Vlaams-Brabant",
    "wof:name":"Boomkwekerij Vencken",
    "wof:placetype":"venue"
},
  "geometry": {"coordinates":[4.806084156,50.9782562256],"type":"Point"}
}