{
  "type": "Feature",
  "properties": {
    "addr:full":"Chauss\u00c9e De Haecht 999 Evere/evere Bruxelles-Capitale 1140",
    "addr:housenumber":"999",
    "addr:postcode":"1140",
    "addr:street":"Chausse\u0301E De Haecht",
    "iso:country":"BE",
    "sg:address":"Chauss\u00c9e De Haecht 999",
    "sg:city":"Evere/evere",
    "sg:orig_category":"Pharmaciens",
    "sg:phone":"+32 2 216 68 53",
    "sg:postcode":"1140",
    "sg:province":"Bruxelles-Capitale",
    "wof:name":"Jacques Beeckman",
    "wof:placetype":"venue"
},
  "geometry": {"coordinates":[4.4022169113,50.8745346069],"type":"Point"}
}