{
  "type": "Feature",
  "properties": {
    "addr:full":"Willebringsestraat 42 Boutersem (honsem) Vlaams-Brabant 3370",
    "addr:housenumber":"42",
    "addr:postcode":"3370",
    "addr:street":"Willebringsestraat",
    "iso:country":"BE",
    "sg:address":"Willebringsestraat 42",
    "sg:city":"Boutersem (honsem)",
    "sg:classifiers":[
        {
            "category":"Personal",
            "subcategory":"Beauty Salon",
            "type":"Services"
        }
    ],
    "sg:phone":"+32 16 73 31 52",
    "sg:postcode":"3370",
    "sg:province":"Vlaams-Brabant",
    "sg:tags":[
        "lady",
        "-",
        "hairdressing"
    ],
    "wof:name":"Agnes",
    "wof:placetype":"venue"
},
  "geometry": {"coordinates":[4.8391928673,50.8111457825],"type":"Point"}
}