{
  "type": "Feature",
  "properties": {
    "iso:country":"BE",
    "sg:address":"Rue De N\u00c9chin 47",
    "sg:city":"Tournai",
    "sg:classifiers":[
        {
            "category":"Arena",
            "subcategory":"Sports Club",
            "type":"Entertainment"
        }
    ],
    "sg:phone":"+32 69 35 30 79",
    "sg:postcode":"7520",
    "sg:province":"Hainaut",
    "sg:tags":[
        "terrain",
        "hors",
        "de",
        "installation",
        "sportifs"
    ],
    "wof:name":"R.s.c. Templeuvois",
    "wof:placetype":"venue"
},
  "geometry": {"coordinates":[3.2787020206,50.6464653015],"type":"Point"}
}