{
  "type": "Feature",
  "properties": {
    "addr:full":"Heiligestraat 8 Riemst (herderen) Limburg 3770",
    "addr:housenumber":"8",
    "addr:postcode":"3770",
    "addr:street":"Heiligestraat",
    "iso:country":"BE",
    "sg:address":"Heiligestraat 8",
    "sg:city":"Riemst (herderen)",
    "sg:classifiers":[
        {
            "category":"Shopping",
            "subcategory":"Clothing, Apparel, & Fashions",
            "type":"Retail Goods"
        }
    ],
    "sg:phone":"+32 12 45 10 39",
    "sg:postcode":"3770",
    "sg:province":"Limburg",
    "sg:tags":[
        "milliner"
    ],
    "wof:name":"Reynders R",
    "wof:placetype":"venue"
},
  "geometry": {"coordinates":[5.5729660988,50.8098678589],"type":"Point"}
}