{
  "type": "Feature",
  "properties": {
    "iso:country":"BE",
    "sg:address":"Rue De L'ind\u00e9pendance 113",
    "sg:city":"Bruxelles (molenbeek-saint-jean)",
    "sg:classifiers":[
        {
            "category":"Professional",
            "subcategory":"Advertising",
            "type":"Services"
        }
    ],
    "sg:phone":"+32 2 410 25 71",
    "sg:postcode":"1080",
    "sg:province":"Bruxelles-Capitale",
    "sg:tags":[
        "clothes"
    ],
    "wof:name":"Enelle Sa",
    "wof:placetype":"venue"
},
  "geometry": {"coordinates":[4.3280119896,50.8534164429],"type":"Point"}
}