{
  "type": "Feature",
  "properties": {
    "iso:country":"BE",
    "sg:address":"Rue \u00e0 Canadas 31",
    "sg:city":"Ham-sur-heure-nalinnes (nalinnes)",
    "sg:classifiers":[
        {
            "category":"Bars & Pubs",
            "type":"Food & Drink"
        }
    ],
    "sg:phone":"+32 71 21 85 58",
    "sg:postcode":"6120",
    "sg:province":"Hainaut",
    "wof:name":"Marloyats (aux)",
    "wof:placetype":"venue"
},
  "geometry": {"coordinates":[4.4466052055,50.324432373],"type":"Point"}
}