{
  "type": "Feature",
  "properties": {
    "iso:country":"BE",
    "sg:address":"Rue Francs Arquebusiers 1",
    "sg:city":"Vise",
    "sg:orig_category":"Jeux de hasard",
    "sg:phone":"+32 4 379 21 54",
    "sg:postcode":"4600",
    "sg:province":"Li\u00e8ge",
    "wof:name":"Tierc\u00c9 Franco Belge",
    "wof:placetype":"venue"
},
  "geometry": {"coordinates":[5.6936421394,50.7377624512],"type":"Point"}
}