{
  "type": "Feature",
  "properties": {
    "iso:country":"BE",
    "sg:address":"Kerkplein 1",
    "sg:city":"Zonhoven",
    "sg:orig_category":"Biblioth\u00e8ques and archives publiques",
    "sg:phone":"+32 11 81 05 81",
    "sg:postcode":"3520",
    "sg:province":"Limburg",
    "wof:name":"Openbare Bibliotheek",
    "wof:placetype":"venue"
},
  "geometry": {"coordinates":[5.3665938377,50.9916877747],"type":"Point"}
}