{
  "type": "Feature",
  "properties": {
    "addr:full":"Petite Rue 44 Mouscron Hainaut 7700",
    "addr:housenumber":"44",
    "addr:postcode":"7700",
    "addr:street":"Petite Rue",
    "iso:country":"BE",
    "sg:address":"Petite Rue 44",
    "sg:city":"Mouscron",
    "sg:classifiers":[
        {
            "category":"Shopping",
            "subcategory":"Shoes",
            "type":"Retail Goods"
        }
    ],
    "sg:phone":"+32 56 84 64 84",
    "sg:postcode":"7700",
    "sg:province":"Hainaut",
    "sg:tags":[
        "slipper",
        "-"
    ],
    "wof:name":"Allure Chaussures",
    "wof:placetype":"venue"
},
  "geometry": {"coordinates":[3.2123889923,50.7444915771],"type":"Point"}
}