{
  "type": "Feature",
  "properties": {
    "addr:full":"Stationsstraat 30 Maldegem Oost-Vlaanderen 9990",
    "addr:housenumber":"30",
    "addr:postcode":"9990",
    "addr:street":"Stationsstraat",
    "iso:country":"BE",
    "sg:address":"Stationsstraat 30",
    "sg:city":"Maldegem",
    "sg:orig_category":"Plaatsen van vloer- and muurbekleding Schilders Textiel Verlichting and huishoudartikelen",
    "sg:phone":"+32 50 71 25 89",
    "sg:postcode":"9990",
    "sg:province":"Oost-Vlaanderen",
    "wof:name":"Huis Van Hoecke",
    "wof:placetype":"venue"
},
  "geometry": {"coordinates":[3.4481399059,51.2080192566],"type":"Point"}
}