{
  "type": "Feature",
  "properties": {
    "addr:full":"Rue De La Blanche Borne 2 Gerpinnes Hainaut 6280",
    "addr:housenumber":"2",
    "addr:postcode":"6280",
    "addr:street":"Rue De La Blanche Borne;Hainaut",
    "iso:country":"BE",
    "sg:address":"Rue De La Blanche Borne 2",
    "sg:city":"Gerpinnes",
    "sg:orig_category":"Woningbouw",
    "sg:phone":"+32 71 47 18 63",
    "sg:postcode":"6280",
    "sg:province":"Hainaut",
    "wof:name":"Gerard Robert",
    "wof:placetype":"venue"
},
  "geometry": {"coordinates":[4.4708981514,50.3618278503],"type":"Point"}
}