{
  "type": "Feature",
  "properties": {
    "iso:country":"BE",
    "sg:address":"Stationsstraat 8",
    "sg:city":"Avelgem",
    "sg:classifiers":[
        {
            "category":"Bars & Pubs",
            "type":"Food & Drink"
        }
    ],
    "sg:phone":"+32 56 64 58 28",
    "sg:postcode":"8580",
    "sg:province":"West-Vlaanderen",
    "wof:name":"Bergenhof",
    "wof:placetype":"venue"
},
  "geometry": {"coordinates":[3.4432299137,50.7714233398],"type":"Point"}
}