{
  "type": "Feature",
  "properties": {
    "addr:full":"Place D\u00b4ostiches 1 Ath Hainaut 7804",
    "addr:housenumber":"1",
    "addr:postcode":"7804",
    "addr:street":"Place D\u00b4Ostiches",
    "iso:country":"BE",
    "sg:address":"Place D\u00b4ostiches 1",
    "sg:city":"Ath",
    "sg:classifiers":[
        {
            "category":"Organizations",
            "subcategory":"Community Association",
            "type":"Services"
        }
    ],
    "sg:phone":"+32 68 64 50 69",
    "sg:postcode":"7804",
    "sg:province":"Hainaut",
    "sg:tags":[
        "organisation"
    ],
    "wof:name":"Le Ch\u00cane",
    "wof:placetype":"venue"
},
  "geometry": {"coordinates":[3.7832849026,50.6607551575],"type":"Point"}
}