{
  "type": "Feature",
  "properties": {
    "iso:country":"BE",
    "sg:address":"Belseledorp 112",
    "sg:city":"Sint-niklaas",
    "sg:orig_category":"M\u00e9decins and sp\u00e9cialistes",
    "sg:phone":"+32 3 772 37 61",
    "sg:postcode":"9111",
    "sg:province":"Oost-Vlaanderen",
    "wof:name":"G. De Vijlder",
    "wof:placetype":"venue"
},
  "geometry": {"coordinates":[4.08562994,51.1460456848],"type":"Point"}
}