{
  "type": "Feature",
  "properties": {
    "addr:full":"Rue De L'industrie 13 Charleroi (jumet) Hainaut 6040",
    "addr:housenumber":"13",
    "addr:postcode":"6040",
    "addr:street":"Rue De L'Industrie",
    "iso:country":"BE",
    "sg:address":"Rue De L'industrie 13",
    "sg:city":"Charleroi (jumet)",
    "sg:classifiers":[
        {
            "category":"Building & Trades",
            "subcategory":"Construction",
            "type":"Services"
        }
    ],
    "sg:phone":"+32 71 37 28 78",
    "sg:postcode":"6040",
    "sg:province":"Hainaut",
    "sg:tags":[
        "duct",
        "underground",
        "ducting"
    ],
    "wof:name":"Etwal Sa",
    "wof:placetype":"venue"
},
  "geometry": {"coordinates":[4.4688310623,50.4434585571],"type":"Point"}
}