{
  "type": "Feature",
  "properties": {
    "addr:full":"Geiboomstraat 4b4 Maaseik Limburg 3680",
    "addr:housenumber":"4b4",
    "addr:postcode":"3680",
    "addr:street":"Geiboomstraat",
    "iso:country":"BE",
    "sg:address":"Geiboomstraat 4b4",
    "sg:city":"Maaseik",
    "sg:classifiers":[
        {
            "category":"Shopping",
            "subcategory":"Clothing, Apparel, & Fashions",
            "type":"Retail Goods"
        }
    ],
    "sg:phone":"+32 89 56 19 22",
    "sg:postcode":"3680",
    "sg:province":"Limburg",
    "sg:tags":[
        "v\u00eatements",
        "pour",
        "dame"
    ],
    "wof:name":"Hekers J. & Juressen H.",
    "wof:placetype":"venue"
},
  "geometry": {"coordinates":[5.781375885,51.0990219116],"type":"Point"}
}