{
  "type": "Feature",
  "properties": {
    "addr:full":"Plaatsstraat 14 Galmaarden Vlaams-Brabant 1570",
    "addr:housenumber":"14",
    "addr:postcode":"1570",
    "addr:street":"Plaatsstraat",
    "iso:country":"BE",
    "sg:address":"Plaatsstraat 14",
    "sg:city":"Galmaarden",
    "sg:orig_category":"Banques and organismes de cr\u00e9dit",
    "sg:phone":"+32 54 58 79 44",
    "sg:postcode":"1570",
    "sg:province":"Vlaams-Brabant",
    "wof:name":"Groep Argenta",
    "wof:placetype":"venue"
},
  "geometry": {"coordinates":[4.0055718422,50.7414283752],"type":"Point"}
}