{
  "type": "Feature",
  "properties": {
    "addr:full":"Hoge Hul 4-8 Brugge West-Vlaanderen 8000",
    "addr:housenumber":"4-8",
    "addr:postcode":"8000",
    "addr:street":"Hoge Hul",
    "iso:country":"BE",
    "sg:address":"Hoge Hul 4-8",
    "sg:city":"Brugge",
    "sg:classifiers":[
        {
            "category":"Wholesale",
            "subcategory":"Machinery & Supplies",
            "type":"Manufacturing & Wholesale Goods"
        }
    ],
    "sg:phone":"+32 50 45 04 80",
    "sg:postcode":"8000",
    "sg:province":"West-Vlaanderen",
    "sg:tags":[
        "packing"
    ],
    "wof:name":"Pattyn Bvba",
    "wof:placetype":"venue"
},
  "geometry": {"coordinates":[3.2023770809,51.2476005554],"type":"Point"}
}