{
  "type": "Feature",
  "properties": {
    "addr:full":"Rue Louvrex 1 Li\u00e8ge 1 Li\u00e8ge 4000",
    "addr:housenumber":"1;1",
    "addr:postcode":"4000",
    "addr:street":"Rue Louvrex",
    "iso:country":"BE",
    "sg:address":"Rue Louvrex 1",
    "sg:city":"Li\u00e8ge 1",
    "sg:classifiers":[
        {
            "category":"Bars & Pubs",
            "type":"Food & Drink"
        }
    ],
    "sg:phone":"+32 4 221 31 50",
    "sg:postcode":"4000",
    "sg:province":"Li\u00e8ge",
    "sg:tags":[
        "tavern"
    ],
    "wof:name":"Shamroch (le)",
    "wof:placetype":"venue"
},
  "geometry": {"coordinates":[5.5631017685,50.6375465393],"type":"Point"}
}