{
  "type": "Feature",
  "properties": {
    "addr:full":"Torhoutse Steenweg 16 Brugge (sint-andries) West-Vlaanderen 8200",
    "addr:housenumber":"16",
    "addr:postcode":"8200",
    "addr:street":"Torhoutse Steenweg",
    "iso:country":"BE",
    "sg:address":"Torhoutse Steenweg 16",
    "sg:city":"Brugge (sint-andries)",
    "sg:classifiers":[
        {
            "category":"Professional",
            "subcategory":"Art Services",
            "type":"Services"
        }
    ],
    "sg:phone":"+32 50 39 51 25",
    "sg:postcode":"8200",
    "sg:province":"West-Vlaanderen",
    "sg:tags":[
        "interior",
        "designer"
    ],
    "wof:name":"Dentant Greet",
    "wof:placetype":"venue"
},
  "geometry": {"coordinates":[3.2081398964,51.2034912109],"type":"Point"}
}