{
  "type": "Feature",
  "properties": {
    "iso:country":"BE",
    "sg:address":"Kleine Konijnenboslaan 2",
    "sg:city":"Gistel",
    "sg:orig_category":"Groenten and fruit Gh",
    "sg:phone":"+32 59 27 41 69",
    "sg:postcode":"8470",
    "sg:province":"West-Vlaanderen",
    "wof:name":"Duva Fruit",
    "wof:placetype":"venue"
},
  "geometry": {"coordinates":[2.9514410496,51.1480293274],"type":"Point"}
}