{
  "type": "Feature",
  "properties": {
    "addr:full":"Edgar Tinelstraat 9 Brugge (sint-andries) West-Vlaanderen 8200",
    "addr:housenumber":"9",
    "addr:postcode":"8200",
    "addr:street":"Edgar Tinelstraat",
    "iso:country":"BE",
    "sg:address":"Edgar Tinelstraat 9",
    "sg:city":"Brugge (sint-andries)",
    "sg:classifiers":[
        {
            "category":"Building & Trades",
            "subcategory":"Cleaning & Sanitation",
            "type":"Services"
        }
    ],
    "sg:phone":"+32 50 31 07 89",
    "sg:postcode":"8200",
    "sg:province":"West-Vlaanderen",
    "sg:tags":[
        "janitor"
    ],
    "wof:name":"Duflou M",
    "wof:placetype":"venue"
},
  "geometry": {"coordinates":[3.2018859386,51.2078132629],"type":"Point"}
}