{
  "type": "Feature",
  "properties": {
    "iso:country":"BE",
    "sg:address":"Rue Voie Des G\u00e9rons 249",
    "sg:city":"Ohey (haillot)",
    "sg:classifiers":[
        {
            "category":"Health Services",
            "subcategory":"Doctor",
            "type":"Services"
        }
    ],
    "sg:phone":"+32 85 61 16 95",
    "sg:postcode":"5351",
    "sg:province":"Namur",
    "sg:tags":[
        "psychotherapist",
        "psychoanalyst"
    ],
    "wof:name":"Meunier H",
    "wof:placetype":"venue"
},
  "geometry": {"coordinates":[5.1459288597,50.4588508606],"type":"Point"}
}