{
  "type": "Feature",
  "properties": {
    "addr:full":"Chauss\u00e9e De Ch\u00e2telineau 266 Charleroi (montignies-sur-sambre) Hainaut 6061",
    "addr:housenumber":"266",
    "addr:postcode":"6061",
    "addr:street":"Chausse\u0301E De Cha\u0302Telineau",
    "iso:country":"BE",
    "sg:address":"Chauss\u00e9e De Ch\u00e2telineau 266",
    "sg:city":"Charleroi (montignies-sur-sambre)",
    "sg:classifiers":[
        {
            "category":"Retail",
            "subcategory":"Auto Repair",
            "type":"Services"
        }
    ],
    "sg:phone":"+32 71 31 21 68",
    "sg:postcode":"6061",
    "sg:province":"Hainaut",
    "sg:tags":[
        "garage"
    ],
    "wof:name":"Hyundai-pacini",
    "wof:placetype":"venue"
},
  "geometry": {"coordinates":[4.4948849678,50.4045982361],"type":"Point"}
}