{
  "type": "Feature",
  "properties": {
    "addr:full":"Chauss\u00e9e De Fleurus 1 Charleroi (gilly) Hainaut 6060",
    "addr:housenumber":"1",
    "addr:postcode":"6060",
    "addr:street":"Chausse\u0301E De Fleurus",
    "iso:country":"BE",
    "sg:address":"Chauss\u00e9e De Fleurus 1",
    "sg:city":"Charleroi (gilly)",
    "sg:classifiers":[
        {
            "category":"Shopping",
            "subcategory":"Used Merchandise",
            "type":"Retail Goods"
        }
    ],
    "sg:phone":"+32 71 42 33 30",
    "sg:postcode":"6060",
    "sg:province":"Hainaut",
    "sg:tags":[
        "salvage",
        "surplus"
    ],
    "wof:name":"Solderie Banzai",
    "wof:placetype":"venue"
},
  "geometry": {"coordinates":[4.4725561142,50.4454345703],"type":"Point"}
}