{
  "type": "Feature",
  "properties": {
    "iso:country":"BE",
    "sg:address":"Heibloem 22",
    "sg:city":"Olen",
    "sg:classifiers":[
        {
            "category":"Recreation",
            "subcategory":"Fishing",
            "type":"Entertainment"
        }
    ],
    "sg:phone":"+32 14 22 11 91",
    "sg:postcode":"2250",
    "sg:province":"Antwerpen",
    "sg:tags":[
        "tackle"
    ],
    "wof:name":"Snoekske (het)",
    "wof:placetype":"venue"
},
  "geometry": {"coordinates":[4.8936018944,51.1909103394],"type":"Point"}
}