{
  "type": "Feature",
  "properties": {
    "iso:country":"BE",
    "sg:address":"Chauss\u00c9e De Louvain 511",
    "sg:city":"Schaarbeek/schaerbeek",
    "sg:classifiers":[
        {
            "category":"Cafe",
            "type":"Food & Drink"
        }
    ],
    "sg:phone":"+32 2 734 55 13",
    "sg:postcode":"1030",
    "sg:province":"Bruxelles-Capitale",
    "sg:tags":[
        "caf\u00e9s"
    ],
    "wof:name":"Nathalie Van Langendonck",
    "wof:placetype":"venue"
},
  "geometry": {"coordinates":[4.3977298737,50.8548583984],"type":"Point"}
}