{
  "type": "Feature",
  "properties": {
    "iso:country":"BE",
    "sg:address":"Rue Reine Astrid 72",
    "sg:city":"Saint-georges-sur-meuse",
    "sg:orig_category":"Instituts de beaut\u00e9. Parfumeries",
    "sg:phone":"+32 4 275 38 33",
    "sg:postcode":"4470",
    "sg:province":"Li\u00e8ge",
    "wof:name":"Institut Votre Beaut\u00c9",
    "wof:placetype":"venue"
},
  "geometry": {"coordinates":[5.3590202332,50.5849304199],"type":"Point"}
}