{
  "type": "Feature",
  "properties": {
    "iso:country":"BE",
    "sg:address":"Kerkstraat 30b2",
    "sg:city":"Kasterlee",
    "sg:orig_category":"M\u00e9decins and sp\u00e9cialistes",
    "sg:phone":"+32 14 55 28 05",
    "sg:postcode":"2460",
    "sg:province":"Antwerpen",
    "wof:name":"Ph. Cuypers",
    "wof:placetype":"venue"
},
  "geometry": {"coordinates":[4.8998498917,51.2426681519],"type":"Point"}
}