{
  "type": "Feature",
  "properties": {
    "addr:full":"Stationsstraat 57 Liedekerke Vlaams-Brabant 1770",
    "addr:housenumber":"57",
    "addr:postcode":"1770",
    "addr:street":"Stationsstraat;Vlaams-Brabant",
    "iso:country":"BE",
    "sg:address":"Stationsstraat 57",
    "sg:city":"Liedekerke",
    "sg:classifiers":[
        {
            "category":"Real Estate",
            "subcategory":"Architect",
            "type":"Services"
        }
    ],
    "sg:phone":"+32 53 66 69 06",
    "sg:postcode":"1770",
    "sg:province":"Vlaams-Brabant",
    "wof:name":"Demaegd Architectenbureau",
    "wof:placetype":"venue"
},
  "geometry": {"coordinates":[4.0847840309,50.8726387024],"type":"Point"}
}