{
  "type": "Feature",
  "properties": {
    "iso:country":"BE",
    "sg:address":"Achiel Cleynhenslaan 36",
    "sg:city":"Keerbergen",
    "sg:orig_category":"Non-Classified Establishments",
    "sg:phone":"+32 15 51 73 91",
    "sg:postcode":"3140",
    "sg:province":"Vlaams-Brabant",
    "wof:name":"Lens Frans & Zn Bvba",
    "wof:placetype":"venue"
},
  "geometry": {"coordinates":[4.6508851051,51.0061378479],"type":"Point"}
}