{
  "type": "Feature",
  "properties": {
    "addr:full":"Heidekapelstraat 30 Waasmunster Oost-Vlaanderen 9250",
    "addr:housenumber":"30",
    "addr:postcode":"9250",
    "addr:street":"Heidekapelstraat",
    "iso:country":"BE",
    "sg:address":"Heidekapelstraat 30",
    "sg:city":"Waasmunster",
    "sg:classifiers":[
        {
            "category":"Travel",
            "subcategory":"Hotels & Motels",
            "type":"Entertainment"
        }
    ],
    "sg:phone":"+32 52 46 99 99",
    "sg:postcode":"9250",
    "sg:province":"Oost-Vlaanderen",
    "sg:tags":[
        "hotels",
        "business",
        "restaurant"
    ],
    "wof:name":"De Gulden Schaduw Bvba",
    "wof:placetype":"venue"
},
  "geometry": {"coordinates":[4.0985012054,51.1226501465],"type":"Point"}
}