{
  "type": "Feature",
  "properties": {
    "iso:country":"BE",
    "sg:address":"Hondekerkhofstraat 22",
    "sg:city":"Meulebeke",
    "sg:classifiers":[
        {
            "category":"Arena",
            "subcategory":"Sports Club",
            "type":"Entertainment"
        }
    ],
    "sg:phone":"+32 51 48 65 77",
    "sg:postcode":"8760",
    "sg:province":"West-Vlaanderen",
    "sg:tags":[
        "de"
    ],
    "wof:name":"Deeko's Duikclub",
    "wof:placetype":"venue"
},
  "geometry": {"coordinates":[3.3145899773,50.944316864],"type":"Point"}
}