{
  "type": "Feature",
  "properties": {
    "iso:country":"BE",
    "sg:address":"Lenniksesteenweg 534",
    "sg:city":"Halle",
    "sg:classifiers":[
        {
            "category":"Shopping",
            "subcategory":"Gifts & Souvenirs",
            "type":"Retail Goods"
        }
    ],
    "sg:phone":"+32 2 361 57 96",
    "sg:postcode":"1500",
    "sg:province":"Vlaams-Brabant",
    "sg:tags":[
        "-"
    ],
    "wof:name":"Maretak (de)",
    "wof:placetype":"venue"
},
  "geometry": {"coordinates":[4.1957950592,50.76612854],"type":"Point"}
}