{
  "type": "Feature",
  "properties": {
    "addr:full":"En Laixheau 25 Herstal Li\u00e8ge 4040",
    "addr:housenumber":"25",
    "addr:postcode":"4040",
    "iso:country":"BE",
    "sg:address":"En Laixheau 25",
    "sg:city":"Herstal",
    "sg:classifiers":[
        {
            "category":"Bars & Pubs",
            "type":"Food & Drink"
        }
    ],
    "sg:phone":"+32 4 248 18 44",
    "sg:postcode":"4040",
    "sg:province":"Li\u00e8ge",
    "wof:name":"Union",
    "wof:placetype":"venue"
},
  "geometry": {"coordinates":[5.6287927628,50.6666145325],"type":"Point"}
}