{
  "type": "Feature",
  "properties": {
    "iso:country":"BE",
    "sg:address":"Rue Des Aiselies 18",
    "sg:city":"Charleroi (jumet)",
    "sg:classifiers":[
        {
            "category":"Health Services",
            "subcategory":"Health Practitioner",
            "type":"Services"
        }
    ],
    "sg:phone":"+32 71 35 76 88",
    "sg:postcode":"6040",
    "sg:province":"Hainaut",
    "sg:tags":[
        "physiotherapist"
    ],
    "wof:name":"Tournay M",
    "wof:placetype":"venue"
},
  "geometry": {"coordinates":[4.4120960236,50.4397315979],"type":"Point"}
}