{
  "type": "Feature",
  "properties": {
    "iso:country":"BE",
    "sg:address":"Leernsesteenweg 68a",
    "sg:city":"Deinze (bachte-maria-leerne)",
    "sg:classifiers":[
        {
            "category":"Building & Trades",
            "subcategory":"Landscaping Services",
            "type":"Services"
        }
    ],
    "sg:phone":"+32 9 386 73 76",
    "sg:postcode":"9800",
    "sg:province":"Oost-Vlaanderen",
    "sg:tags":[
        "gardening",
        "garden",
        "maintenance"
    ],
    "wof:name":"Eggermont S",
    "wof:placetype":"venue"
},
  "geometry": {"coordinates":[3.542730093,50.9896011353],"type":"Point"}
}