{
  "type": "Feature",
  "properties": {
    "addr:full":"Geerdegemvaart 145 Mechelen Antwerpen 2800",
    "addr:housenumber":"145",
    "addr:postcode":"2800",
    "addr:street":"Geerdegemvaart",
    "iso:country":"BE",
    "sg:address":"Geerdegemvaart 145",
    "sg:city":"Mechelen",
    "sg:orig_category":"Produits laitiers and huiles comestibles Gr",
    "sg:phone":"+32 15 43 41 21",
    "sg:postcode":"2800",
    "sg:province":"Antwerpen",
    "wof:name":"Faes - Van Roey",
    "wof:placetype":"venue"
},
  "geometry": {"coordinates":[4.4869132042,51.0117492676],"type":"Point"}
}