{
  "type": "Feature",
  "properties": {
    "iso:country":"BE",
    "sg:address":"Barri\u00e8re De Fer 51",
    "sg:city":"Espierres-helchin (espierres)",
    "sg:classifiers":[
        {
            "category":"Shopping",
            "subcategory":"Used Merchandise",
            "type":"Retail Goods"
        }
    ],
    "sg:phone":"+32 56 45 77 21",
    "sg:postcode":"8587",
    "sg:province":"West-Vlaanderen",
    "sg:tags":[
        "salvage",
        "surplus"
    ],
    "wof:name":"Bingo",
    "wof:placetype":"venue"
},
  "geometry": {"coordinates":[3.3305530548,50.7264633179],"type":"Point"}
}