{
  "type": "Feature",
  "properties": {
    "iso:country":"BE",
    "sg:address":"Brugsesteenweg 382",
    "sg:city":"Kuurne",
    "sg:orig_category":"Pain, p\u00e2tisseries and confiseries",
    "sg:phone":"+32 56 71 15 17",
    "sg:postcode":"8520",
    "sg:province":"West-Vlaanderen",
    "wof:name":"Pimpernel",
    "wof:placetype":"venue"
},
  "geometry": {"coordinates":[3.2715699673,50.8694610596],"type":"Point"}
}