{
  "type": "Feature",
  "properties": {
    "iso:country":"BE",
    "sg:address":"Rue Edmond Laffineur 2",
    "sg:city":"Wavre (limal)",
    "sg:classifiers":[
        {
            "category":"Personal",
            "subcategory":"Beauty Salon",
            "type":"Services"
        }
    ],
    "sg:phone":"+32 10 40 22 50",
    "sg:postcode":"1300",
    "sg:province":"Brabant Wallon",
    "wof:name":"Morelle N",
    "wof:placetype":"venue"
},
  "geometry": {"coordinates":[4.6116552353,50.7134132385],"type":"Point"}
}