{
  "type": "Feature",
  "properties": {
    "iso:country":"BE",
    "sg:address":"Rue De La Petite Guirlande 1",
    "sg:city":"Mons",
    "sg:classifiers":[
        {
            "category":"Personal",
            "subcategory":"Beauty Salon",
            "type":"Services"
        }
    ],
    "sg:phone":"+32 65 36 15 90",
    "sg:postcode":"7000",
    "sg:province":"Hainaut",
    "wof:name":"Maqui-art",
    "wof:placetype":"venue"
},
  "geometry": {"coordinates":[3.9462909698,50.4511108398],"type":"Point"}
}