{
  "type": "Feature",
  "properties": {
    "iso:country":"BE",
    "sg:address":"Chauss\u00e9e De Bruxelles 129",
    "sg:city":"Waterloo",
    "sg:classifiers":[
        {
            "category":"Shopping",
            "subcategory":"Books",
            "type":"Retail Goods"
        }
    ],
    "sg:phone":"+32 2 354 57 96",
    "sg:postcode":"1410",
    "sg:province":"Brabant Wallon",
    "sg:tags":[
        "bookseller"
    ],
    "wof:name":"Graffiti (librairie)",
    "wof:placetype":"venue"
},
  "geometry": {"coordinates":[4.3979759216,50.7186546326],"type":"Point"}
}