{
  "type": "Feature",
  "properties": {
    "iso:country":"BE",
    "sg:address":"Bergekouter 98",
    "sg:city":"Aalst",
    "sg:orig_category":"Plaatsen van vloer- and muurbekleding",
    "sg:phone":"+32 53 41 03 83",
    "sg:postcode":"9300",
    "sg:province":"Oost-Vlaanderen",
    "wof:name":"Fosco",
    "wof:placetype":"venue"
},
  "geometry": {"coordinates":[4.0626511574,50.9373703003],"type":"Point"}
}