{
  "type": "Feature",
  "properties": {
    "iso:country":"BE",
    "sg:address":"Steenweg Op Alsemberg 1408",
    "sg:city":"Drogenbos/drogenbos",
    "sg:classifiers":[
        {
            "category":"Cafe",
            "type":"Food & Drink"
        }
    ],
    "sg:phone":"+32 2 331 02 81",
    "sg:postcode":"1620",
    "sg:province":"Vlaams-Brabant",
    "sg:tags":[
        "caf\u00e9s"
    ],
    "wof:name":"Caf\u00c9 La Limite",
    "wof:placetype":"venue"
},
  "geometry": {"coordinates":[4.3073601723,50.7963600159],"type":"Point"}
}