{
  "type": "Feature",
  "properties": {
    "addr:full":"Nijverheidsstr 18 Mol Antwerpen 2400",
    "addr:housenumber":"18",
    "addr:postcode":"2400",
    "addr:street":"Nijverheidsstr",
    "iso:country":"BE",
    "sg:address":"Nijverheidsstr 18",
    "sg:city":"Mol",
    "sg:classifiers":[
        {
            "category":"Autos & Motor Vehicles",
            "subcategory":"Automobile Sales",
            "type":"Retail Goods"
        }
    ],
    "sg:phone":"+32 14 31 24 62",
    "sg:postcode":"2400",
    "sg:province":"Antwerpen",
    "sg:tags":[
        "equipment",
        "motor-cars",
        "transport"
    ],
    "wof:name":"Etablissementen Guido Verkoeyen Nv",
    "wof:placetype":"venue"
},
  "geometry": {"coordinates":[5.0961141586,51.1876373291],"type":"Point"}
}