{
  "type": "Feature",
  "properties": {
    "iso:country":"BE",
    "sg:address":"2 Rue De Tournai",
    "sg:city":"Callenelle",
    "sg:classifiers":[
        {
            "category":"Shopping",
            "type":"Retail Goods"
        }
    ],
    "sg:phone":"+32 69 77 82 11",
    "sg:postcode":"7604",
    "sg:province":"Hainaut",
    "sg:tags":[
        "metallurgy",
        "finished",
        "-",
        "metalworking",
        "metallic"
    ],
    "wof:name":"Saluc Sa",
    "wof:placetype":"venue"
},
  "geometry": {"coordinates":[3.5133900642,50.5373306274],"type":"Point"}
}