{
  "type": "Feature",
  "properties": {
    "iso:country":"BE",
    "sg:address":"Kerkstraat 15",
    "sg:city":"Londerzeel",
    "sg:classifiers":[
        {
            "category":"Bars & Pubs",
            "type":"Food & Drink"
        }
    ],
    "sg:phone":"+32 52 30 01 73",
    "sg:postcode":"1840",
    "sg:province":"Vlaams-Brabant",
    "sg:tags":[
        "tavern"
    ],
    "wof:name":"Grooten Hert (den)",
    "wof:placetype":"venue"
},
  "geometry": {"coordinates":[4.3024320602,51.0024528503],"type":"Point"}
}