{
  "type": "Feature",
  "properties": {
    "iso:country":"BE",
    "sg:address":"Kasteeldreef 2",
    "sg:city":"Herzele",
    "sg:orig_category":"Ruimtes voor conferenties, recepties and feesten",
    "sg:phone":"+32 53 62 20 17",
    "sg:postcode":"9550",
    "sg:province":"Oost-Vlaanderen",
    "wof:name":"Kasteel Van Herzele",
    "wof:placetype":"venue"
},
  "geometry": {"coordinates":[3.9126040936,50.8727836609],"type":"Point"}
}