{
  "type": "Feature",
  "properties": {
    "iso:country":"BE",
    "sg:address":"Route De Hayen 7",
    "sg:city":"Sprimont",
    "sg:orig_category":"Artsen and specialisten",
    "sg:phone":"+32 4 368 49 30",
    "sg:postcode":"4140",
    "sg:province":"Li\u00e8ge",
    "wof:name":"Richard Mar\u00c9chal",
    "wof:placetype":"venue"
},
  "geometry": {"coordinates":[5.6295628548,50.5427818298],"type":"Point"}
}