{
  "type": "Feature",
  "properties": {
    "addr:full":"Montagne Sainte-walburge 104 Li\u00c8ge Li\u00e8ge 4000",
    "addr:housenumber":"104",
    "addr:postcode":"4000",
    "addr:street":"Montagne Sainte-Walburge",
    "iso:country":"BE",
    "sg:address":"Montagne Sainte-walburge 104",
    "sg:city":"Li\u00c8ge",
    "sg:orig_category":"Dakwerken Loodgieterij, verwarming and sanitaire installaties",
    "sg:phone":"+32 4 226 00 72",
    "sg:postcode":"4000",
    "sg:province":"Li\u00e8ge",
    "wof:name":"Fe. De Mey L. & Fils",
    "wof:placetype":"venue"
},
  "geometry": {"coordinates":[5.5706038475,50.6512451172],"type":"Point"}
}