{
  "type": "Feature",
  "properties": {
    "addr:full":"Avenue Des M\u00e9nestrels 121 Bruxelles (molenbeek-saint-jean) Bruxelles-Capitale 1080",
    "addr:housenumber":"121",
    "addr:postcode":"1080",
    "addr:street":"Avenue Des Me\u0301Nestrels",
    "iso:country":"BE",
    "sg:address":"Avenue Des M\u00e9nestrels 121",
    "sg:city":"Bruxelles (molenbeek-saint-jean)",
    "sg:classifiers":[
        {
            "category":"Health Services",
            "subcategory":"Health Practitioner",
            "type":"Services"
        }
    ],
    "sg:phone":"+32 2 410 80 42",
    "sg:postcode":"1080",
    "sg:province":"Bruxelles-Capitale",
    "sg:tags":[
        "physiotherapist"
    ],
    "wof:name":"Pastur Th",
    "wof:placetype":"venue"
},
  "geometry": {"coordinates":[4.309431076,50.8505783081],"type":"Point"}
}