{
  "type": "Feature",
  "properties": {
    "iso:country":"BE",
    "sg:address":"Rue Gustave Taillard 10",
    "sg:city":"Herve",
    "sg:orig_category":"Magasins de r\u00e9parations d'articles personnels et m\u00e9nagers divers. R\u00e9parations \u00e0 domicile d'articles ",
    "sg:phone":"+32 87 66 15 25",
    "sg:postcode":"4650",
    "sg:province":"Li\u00e8ge",
    "wof:name":"Beno\u00cet Carlier",
    "wof:placetype":"venue"
},
  "geometry": {"coordinates":[5.7934961319,50.6416511536],"type":"Point"}
}