{
  "type": "Feature",
  "properties": {
    "addr:full":"Lamorinierestraat 83 Antwerpen Antwerpen 2018",
    "addr:housenumber":"83",
    "addr:postcode":"2018",
    "addr:street":"Lamorinierestraat",
    "iso:country":"BE",
    "sg:address":"Lamorinierestraat 83",
    "sg:city":"Antwerpen",
    "sg:orig_category":"Traitements param\u00e9dicaux",
    "sg:phone":"+32 3 286 98 98",
    "sg:postcode":"2018",
    "sg:province":"Antwerpen",
    "wof:name":"Wit-gele Kruis",
    "wof:placetype":"venue"
},
  "geometry": {"coordinates":[4.4221749306,51.2052574158],"type":"Point"}
}