{
  "type": "Feature",
  "properties": {
    "iso:country":"BE",
    "sg:address":"Cyriel Buysselaan 32",
    "sg:city":"De Pinte",
    "sg:classifiers":[
        {
            "category":"Parking",
            "subcategory":"Bicycle",
            "type":"Transportation"
        }
    ],
    "sg:phone":"+32 9 282 85 26",
    "sg:postcode":"9840",
    "sg:province":"Oost-Vlaanderen",
    "sg:tags":[
        "chiropodist"
    ],
    "wof:name":"Schelstraete C",
    "wof:placetype":"venue"
},
  "geometry": {"coordinates":[3.6593420506,50.9918556213],"type":"Point"}
}