{
  "type": "Feature",
  "properties": {
    "iso:country":"BE",
    "sg:address":"Nieuwland 2b",
    "sg:city":"Beveren",
    "sg:classifiers":[
        {
            "category":"Coffee & Tea",
            "type":"Food & Drink"
        }
    ],
    "sg:phone":"+32 3 252 71 95",
    "sg:postcode":"9150",
    "sg:province":"Oost-Vlaanderen",
    "sg:tags":[
        "cooky",
        "spekulatius",
        "spice"
    ],
    "wof:name":"Delistar B.v.b.a.",
    "wof:placetype":"venue"
},
  "geometry": {"coordinates":[5.0139198303,51.9019088745],"type":"Point"}
}