{
  "type": "Feature",
  "properties": {
    "addr:full":"Lysbrugstraat 31 Ingelmunster West-Vlaanderen 8770",
    "addr:housenumber":"31",
    "addr:postcode":"8770",
    "addr:street":"Lysbrugstraat",
    "iso:country":"BE",
    "sg:address":"Lysbrugstraat 31",
    "sg:city":"Ingelmunster",
    "sg:orig_category":"Non-Classified Establishments",
    "sg:phone":"+32 51 30 95 01",
    "sg:postcode":"8770",
    "sg:province":"West-Vlaanderen",
    "wof:name":"Depaepe N",
    "wof:placetype":"venue"
},
  "geometry": {"coordinates":[3.2655649185,50.9142684937],"type":"Point"}
}