{
  "type": "Feature",
  "properties": {
    "addr:full":"Zandstraat 221 Sint-gillis-waas Oost-Vlaanderen 9170",
    "addr:housenumber":"221",
    "addr:postcode":"9170",
    "addr:street":"Zandstraat",
    "iso:country":"BE",
    "sg:address":"Zandstraat 221",
    "sg:city":"Sint-gillis-waas",
    "sg:classifiers":[
        {
            "category":"Restaurant",
            "type":"Food & Drink"
        }
    ],
    "sg:phone":"+32 3 779 55 48",
    "sg:postcode":"9170",
    "sg:province":"Oost-Vlaanderen",
    "wof:name":"De Rietgaard",
    "wof:placetype":"venue"
},
  "geometry": {"coordinates":[4.0783529282,51.2029151917],"type":"Point"}
}