{
  "type": "Feature",
  "properties": {
    "addr:full":"Peerderbaan 29 Meeuwen-gruitrode (meeuwen) Limburg 3670",
    "addr:housenumber":"29",
    "addr:postcode":"3670",
    "addr:street":"Peerderbaan",
    "iso:country":"BE",
    "sg:address":"Peerderbaan 29",
    "sg:city":"Meeuwen-gruitrode (meeuwen)",
    "sg:classifiers":[
        {
            "category":"Building & Trades",
            "subcategory":"Construction",
            "type":"Services"
        }
    ],
    "sg:phone":"+32 11 79 16 37",
    "sg:postcode":"3670",
    "sg:province":"Limburg",
    "sg:tags":[
        "stucco",
        "contractor"
    ],
    "wof:name":"Schrooten Bvba",
    "wof:placetype":"venue"
},
  "geometry": {"coordinates":[5.5089211464,51.1059494019],"type":"Point"}
}