{
  "type": "Feature",
  "properties": {
    "iso:country":"BE",
    "sg:address":"Niemandshoek 12",
    "sg:city":"Herenthout",
    "sg:classifiers":[
        {
            "category":"Cafe",
            "type":"Food & Drink"
        }
    ],
    "sg:phone":"+32 14 50 01 74",
    "sg:postcode":"2270",
    "sg:province":"Antwerpen",
    "sg:tags":[
        "caf\u00e9s"
    ],
    "wof:name":"Caf\u00c9 't Schipke",
    "wof:placetype":"venue"
},
  "geometry": {"coordinates":[4.7219400406,51.1282310486],"type":"Point"}
}