{
  "type": "Feature",
  "properties": {
    "iso:country":"BE",
    "sg:address":"Avenue Jean Derave 8",
    "sg:city":"Binche",
    "sg:orig_category":"Non-Classified Establishments",
    "sg:phone":"+32 64 33 28 55",
    "sg:postcode":"7130",
    "sg:province":"Hainaut",
    "wof:name":"Centres Pms Provincial",
    "wof:placetype":"venue"
},
  "geometry": {"coordinates":[4.1728510857,50.4099464417],"type":"Point"}
}