{
  "type": "Feature",
  "properties": {
    "addr:full":"R. Borremansstraat 4 Huldenberg (groot) Vlaams-Brabant 3040",
    "addr:housenumber":"4",
    "addr:postcode":"3040",
    "addr:street":"R. Borremansstraat;Groot Vlaams-Brabant",
    "iso:country":"BE",
    "sg:address":"R. Borremansstraat 4",
    "sg:city":"Huldenberg (groot)",
    "sg:orig_category":"Banques and organismes de cr\u00e9dit",
    "sg:phone":"+32 2 686 10 10",
    "sg:postcode":"3040",
    "sg:province":"Vlaams-Brabant",
    "wof:name":"Dexia",
    "wof:placetype":"venue"
},
  "geometry": {"coordinates":[4.5846772194,50.7893066406],"type":"Point"}
}