{
  "type": "Feature",
  "properties": {
    "addr:full":"Van De Wiellei 198 Brasschaat Antwerpen 2930",
    "addr:housenumber":"198",
    "addr:postcode":"2930",
    "addr:street":"Van",
    "iso:country":"BE",
    "sg:address":"Van De Wiellei 198",
    "sg:city":"Brasschaat",
    "sg:orig_category":"Banken and kredietinstellingen",
    "sg:phone":"+32 3 651 36 47",
    "sg:postcode":"2930",
    "sg:province":"Antwerpen",
    "wof:name":"Groep Argenta",
    "wof:placetype":"venue"
},
  "geometry": {"coordinates":[4.4798789024,51.298614502],"type":"Point"}
}