{
  "type": "Feature",
  "properties": {
    "iso:country":"BE",
    "sg:address":"Coppendries 2",
    "sg:city":"Grimbergen (beigem)",
    "sg:classifiers":[
        {
            "category":"Professional",
            "type":"Services"
        }
    ],
    "sg:phone":"+32 2 270 15 05",
    "sg:postcode":"1852",
    "sg:province":"Vlaams-Brabant",
    "sg:tags":[
        "entertainer"
    ],
    "wof:name":"De Wit L",
    "wof:placetype":"venue"
},
  "geometry": {"coordinates":[4.3623070717,50.9601211548],"type":"Point"}
}