{
  "type": "Feature",
  "properties": {
    "iso:country":"BE",
    "sg:address":"Prevent 351bb",
    "sg:city":"Aubel",
    "sg:orig_category":"Installation de menuiserie en bois and plastique. Timbres, monnaies and troph\u00e9es",
    "sg:phone":"+32 87 68 62 94",
    "sg:postcode":"4880",
    "sg:province":"Li\u00e8ge",
    "wof:name":"Jose Collins",
    "wof:placetype":"venue"
},
  "geometry": {"coordinates":[5.8508858681,50.7043609619],"type":"Point"}
}