{
  "type": "Feature",
  "properties": {
    "iso:country":"BE",
    "sg:address":"Maalsesteenweg 37",
    "sg:city":"Sint-kruis",
    "sg:orig_category":"Articles de f\u00eate, farces and attrapes",
    "sg:phone":"+32 50 35 72 49",
    "sg:postcode":"8310",
    "sg:province":"West-Vlaanderen",
    "wof:name":"\u00b4t Ballonneke",
    "wof:placetype":"venue"
},
  "geometry": {"coordinates":[3.2438819408,51.2106056213],"type":"Point"}
}