{
  "type": "Feature",
  "properties": {
    "iso:country":"BE",
    "sg:address":"Armand Segerslei 118",
    "sg:city":"Mortsel",
    "sg:classifiers":[
        {
            "category":"Insurance",
            "subcategory":"Insurance Agent",
            "type":"Services"
        }
    ],
    "sg:phone":"+32 3 440 00 99",
    "sg:postcode":"2640",
    "sg:province":"Antwerpen",
    "sg:tags":[
        "verzekeringsmakelaars",
        "expert"
    ],
    "wof:name":"Makelaarskant. Appelboom",
    "wof:placetype":"venue"
},
  "geometry": {"coordinates":[4.4438900948,51.1684799194],"type":"Point"}
}