{
  "type": "Feature",
  "properties": {
    "iso:country":"BE",
    "sg:address":"Diesterestraat 56",
    "sg:city":"Diest",
    "sg:orig_category":"Gespecialiseerde residenti\u00eble bouw",
    "sg:phone":"+32 13 32 16 93",
    "sg:postcode":"3294",
    "sg:province":"Vlaams-Brabant",
    "wof:name":"Robert Gressens",
    "wof:placetype":"venue"
},
  "geometry": {"coordinates":[5.0392479897,51.0024719238],"type":"Point"}
}