{
  "type": "Feature",
  "properties": {
    "addr:full":"Rue De La L\u00e9gende 32 D Sprimont Li\u00e8ge 4141",
    "addr:housenumber":"32 d",
    "addr:postcode":"4141",
    "addr:street":"Rue De La Le\u0301Gende",
    "iso:country":"BE",
    "sg:address":"Rue De La L\u00e9gende 32 D",
    "sg:city":"Sprimont",
    "sg:orig_category":"Aircraft Parts, Components, Modules, And Construction Supplies",
    "sg:phone":"+32 4 360 02 70",
    "sg:postcode":"4141",
    "sg:province":"Li\u00e8ge",
    "wof:name":"Meister Benelux S.a.",
    "wof:placetype":"venue"
},
  "geometry": {"coordinates":[5.7102560997,50.5312538147],"type":"Point"}
}