{
  "type": "Feature",
  "properties": {
    "addr:full":"Rue Des H\u00catres 22 Rendeux 6787",
    "addr:housenumber":"22",
    "addr:postcode":"6787",
    "addr:street":"Rue Des He\u0302Tres",
    "iso:country":"BE",
    "sg:address":"Rue Des H\u00catres 22",
    "sg:city":"Rendeux",
    "sg:orig_category":"Rev\u00eatements pour sols and murs. Peinture",
    "sg:phone":"+32 84 47 79 16",
    "sg:postcode":"6787",
    "wof:name":"Entreprise G\u00c9n. De Peinture Rentmeister",
    "wof:placetype":"venue"
},
  "geometry": {"coordinates":[5.4902911186,50.2446784973],"type":"Point"}
}