{
  "type": "Feature",
  "properties": {
    "iso:country":"BE",
    "sg:address":"Houtemstraat 449",
    "sg:city":"Tienen",
    "sg:classifiers":[
        {
            "category":"Health Services",
            "subcategory":"Doctor",
            "type":"Services"
        }
    ],
    "sg:phone":"+32 16 81 46 45",
    "sg:postcode":"3300",
    "sg:province":"Vlaams-Brabant",
    "sg:tags":[
        "medicinephysicians",
        "surgeon"
    ],
    "wof:name":"Geernaert K",
    "wof:placetype":"venue"
},
  "geometry": {"coordinates":[4.9456100464,50.8188896179],"type":"Point"}
}