{
  "type": "Feature",
  "properties": {
    "iso:country":"BE",
    "sg:address":"Jean B\u00e9thunestraat 9",
    "sg:city":"Gent (sint-amandsberg)",
    "sg:classifiers":[
        {
            "category":"Sports & Exercise",
            "subcategory":"Skate Park",
            "type":"Entertainment"
        }
    ],
    "sg:phone":"+32 9 228 70 90",
    "sg:postcode":"9040",
    "sg:province":"Oost-Vlaanderen",
    "sg:tags":[
        "mushroom"
    ],
    "wof:name":"Mycelia Broedlaboratorium Bvba",
    "wof:placetype":"venue"
},
  "geometry": {"coordinates":[3.7471139431,51.054397583],"type":"Point"}
}