{
  "type": "Feature",
  "properties": {
    "iso:country":"BE",
    "sg:address":"Vieux Chemin De Mons 37",
    "sg:city":"Tournai (vaulx)",
    "sg:classifiers":[
        {
            "category":"Freight",
            "type":"Transportation"
        }
    ],
    "sg:phone":"+32 69 89 14 00",
    "sg:postcode":"7536",
    "sg:province":"Hainaut",
    "sg:tags":[
        "-",
        "transport"
    ],
    "wof:name":"Staroute",
    "wof:placetype":"venue"
},
  "geometry": {"coordinates":[3.4367499352,50.5936088562],"type":"Point"}
}