{
  "type": "Feature",
  "properties": {
    "iso:country":"BE",
    "sg:address":"Thomas Van Loostraat 39",
    "sg:city":"Oostende",
    "sg:orig_category":"Artsen and specialisten",
    "sg:phone":"+32 59 33 09 92",
    "sg:postcode":"8400",
    "sg:province":"West-Vlaanderen",
    "wof:name":"J. Osstyn",
    "wof:placetype":"venue"
},
  "geometry": {"coordinates":[2.9434599876,51.2304229736],"type":"Point"}
}