{
  "type": "Feature",
  "properties": {
    "addr:full":"Bulestraat 2a Olen Antwerpen 2250",
    "addr:housenumber":"2a",
    "addr:postcode":"2250",
    "addr:street":"Bulestraat",
    "iso:country":"BE",
    "sg:address":"Bulestraat 2a",
    "sg:city":"Olen",
    "sg:classifiers":[
        {
            "category":"Personal",
            "subcategory":"Barber",
            "type":"Services"
        }
    ],
    "sg:phone":"+32 14 26 70 70",
    "sg:postcode":"2250",
    "sg:province":"Antwerpen",
    "sg:tags":[
        "gentleman",
        "salon",
        "-",
        "hairdressing"
    ],
    "wof:name":"Creatieve Kappers (de)",
    "wof:placetype":"venue"
},
  "geometry": {"coordinates":[4.8603839874,51.1443138123],"type":"Point"}
}