{
  "type": "Feature",
  "properties": {
    "addr:full":"Kortrijkstraat 1 Ingelmunster West-Vlaanderen 8770",
    "addr:housenumber":"1",
    "addr:postcode":"8770",
    "addr:street":"Kortrijkstraat",
    "iso:country":"BE",
    "sg:address":"Kortrijkstraat 1",
    "sg:city":"Ingelmunster",
    "sg:orig_category":"Astrologen, grafologen and mediums",
    "sg:phone":"+32 475 66 10 54",
    "sg:postcode":"8770",
    "sg:province":"West-Vlaanderen",
    "wof:name":"Anima Art",
    "wof:placetype":"venue"
},
  "geometry": {"coordinates":[3.2572479248,50.9126472473],"type":"Point"}
}