{
  "type": "Feature",
  "properties": {
    "addr:full":"Vlieger Thieffrystraat 24 Etterbeek/etterbeek Bruxelles-Capitale 1040",
    "addr:housenumber":"24",
    "addr:postcode":"1040",
    "addr:street":"Vlieger Thieffrystraat",
    "iso:country":"BE",
    "sg:address":"Vlieger Thieffrystraat 24",
    "sg:city":"Etterbeek/etterbeek",
    "sg:orig_category":"Diverse grafische activiteiten",
    "sg:phone":"+32 2 736 02 09",
    "sg:postcode":"1040",
    "sg:province":"Bruxelles-Capitale",
    "wof:name":"E-magic",
    "wof:placetype":"venue"
},
  "geometry": {"coordinates":[4.4014940262,50.8314170837],"type":"Point"}
}