{
  "type": "Feature",
  "properties": {
    "iso:country":"BE",
    "sg:address":"Kwinten 47",
    "sg:city":"Voeren",
    "sg:orig_category":"Maisons de vacances",
    "sg:phone":"+32 4 381 13 31",
    "sg:postcode":"3790",
    "sg:province":"Limburg",
    "wof:name":"Berg En Dal",
    "wof:placetype":"venue"
},
  "geometry": {"coordinates":[5.8218269348,50.7533378601],"type":"Point"}
}