{
  "type": "Feature",
  "properties": {
    "iso:country":"BE",
    "sg:address":"Leopoldstraat 22",
    "sg:city":"Merksplas",
    "sg:classifiers":[
        {
            "category":"Fast Food",
            "type":"Food & Drink"
        }
    ],
    "sg:phone":"+32 14 63 36 41",
    "sg:postcode":"2330",
    "sg:province":"Antwerpen",
    "sg:tags":[
        "meeneem",
        "restaurant"
    ],
    "wof:name":"Fritshop",
    "wof:placetype":"venue"
},
  "geometry": {"coordinates":[4.8641009331,51.3569793701],"type":"Point"}
}