{
  "type": "Feature",
  "properties": {
    "addr:full":"Oudendoel-kleinstraatje 1 Beveren Oost-Vlaanderen 9130",
    "addr:housenumber":"1",
    "addr:postcode":"9130",
    "addr:street":"Oudendoel-Kleinstraatje",
    "iso:country":"BE",
    "sg:address":"Oudendoel-kleinstraatje 1",
    "sg:city":"Beveren",
    "sg:orig_category":"Transports fluviaux",
    "sg:phone":"+32 3 773 27 96",
    "sg:postcode":"9130",
    "sg:province":"Oost-Vlaanderen",
    "wof:name":"Natuurvr.prosperpold.wsv",
    "wof:placetype":"venue"
},
  "geometry": {"coordinates":[4.2362551689,51.3342857361],"type":"Point"}
}