{
  "type": "Feature",
  "properties": {
    "iso:country":"BE",
    "sg:address":"Rue Fernand Lorent 12",
    "sg:city":"Aiseau-presles",
    "sg:orig_category":"Kapsalons",
    "sg:phone":"+32 71 74 00 12",
    "sg:postcode":"6250",
    "sg:province":"Hainaut",
    "wof:name":"Isabella Capirchio",
    "wof:placetype":"venue"
},
  "geometry": {"coordinates":[4.5756387711,50.4235267639],"type":"Point"}
}