{
  "type": "Feature",
  "properties": {
    "iso:country":"BE",
    "sg:address":"Place Favresse 51",
    "sg:city":"La Hulpe",
    "sg:classifiers":[
        {
            "category":"Restaurant",
            "type":"Food & Drink"
        }
    ],
    "sg:phone":"+32 479 31 76 22",
    "sg:postcode":"1310",
    "sg:province":"Brabant Wallon",
    "wof:name":"L'intemporel",
    "wof:placetype":"venue"
},
  "geometry": {"coordinates":[4.4954071045,50.7376098633],"type":"Point"}
}