{
  "type": "Feature",
  "properties": {
    "iso:country":"BE",
    "sg:address":"Rue De La Converserie 89",
    "sg:city":"Saint-hubert",
    "sg:classifiers":[
        {
            "category":"Insurance",
            "subcategory":"Insurance Agent",
            "type":"Services"
        }
    ],
    "sg:phone":"+32 61 26 62 96",
    "sg:postcode":"6870",
    "sg:province":"Luxembourg",
    "sg:tags":[
        "broker"
    ],
    "wof:name":"Collin O",
    "wof:placetype":"venue"
},
  "geometry": {"coordinates":[5.3837299347,50.0321388245],"type":"Point"}
}