{
  "type": "Feature",
  "properties": {
    "addr:full":"Rue De L\u00c0-haut 35 Dour Hainaut 7370",
    "addr:housenumber":"35",
    "addr:postcode":"7370",
    "addr:street":"Rue De La\u0300-Haut;Hainaut",
    "iso:country":"BE",
    "sg:address":"Rue De L\u00c0-haut 35",
    "sg:city":"Dour",
    "sg:orig_category":"S\u00e9curit\u00e9 sociale",
    "sg:phone":"+32 65 63 15 77",
    "sg:postcode":"7370",
    "sg:province":"Hainaut",
    "wof:name":"Mutualit\u00c9 Libre",
    "wof:placetype":"venue"
},
  "geometry": {"coordinates":[3.7527968884,50.3963661194],"type":"Point"}
}