{
  "type": "Feature",
  "properties": {
    "addr:full":"Brugse Steenweg 30 Zuienkerke West-Vlaanderen 8377",
    "addr:housenumber":"30",
    "addr:postcode":"8377",
    "addr:street":"Brugse Steenweg",
    "iso:country":"BE",
    "sg:address":"Brugse Steenweg 30",
    "sg:city":"Zuienkerke",
    "sg:orig_category":"Rundveehouders",
    "sg:phone":"+32 50 41 20 82",
    "sg:postcode":"8377",
    "sg:province":"West-Vlaanderen",
    "wof:name":"Willy Derycker",
    "wof:placetype":"venue"
},
  "geometry": {"coordinates":[3.1104590893,51.2581253052],"type":"Point"}
}