{
  "type": "Feature",
  "properties": {
    "addr:full":"Drogenbroodstraat 57 Pittem West-Vlaanderen 8740",
    "addr:housenumber":"57",
    "addr:postcode":"8740",
    "addr:street":"Drogenbroodstraat",
    "iso:country":"BE",
    "sg:address":"Drogenbroodstraat 57",
    "sg:city":"Pittem",
    "sg:orig_category":"Eleveurs and marchands de porcs",
    "sg:phone":"+32 51 46 64 95",
    "sg:postcode":"8740",
    "sg:province":"West-Vlaanderen",
    "wof:name":"Lafaut-vandenbulcke",
    "wof:placetype":"venue"
},
  "geometry": {"coordinates":[3.2443819046,51.0202865601],"type":"Point"}
}