{
  "type": "Feature",
  "properties": {
    "iso:country":"BE",
    "sg:address":"Ville No 2",
    "sg:city":"Charleroi",
    "sg:classifiers":[
        {
            "category":"Bakery",
            "type":"Food & Drink"
        }
    ],
    "sg:phone":"+32 71 42 34 14",
    "sg:postcode":"6000",
    "sg:province":"Hainaut",
    "sg:tags":[
        "confectioner",
        "baker"
    ],
    "wof:name":"Tr\u00e9sors De M\u00e9lanie",
    "wof:placetype":"venue"
},
  "geometry": {"coordinates":[4.4434351921,50.41015625],"type":"Point"}
}