{
  "type": "Feature",
  "properties": {
    "iso:country":"BE",
    "sg:address":"Rue De Bruxelles 126",
    "sg:city":"Les Bons Villers (r\u00eaves)",
    "sg:classifiers":[
        {
            "category":"Communications",
            "subcategory":"Film & Video Production",
            "type":"Services"
        }
    ],
    "sg:phone":"+32 71 84 23 22",
    "sg:postcode":"6210",
    "sg:province":"Hainaut",
    "sg:tags":[
        "realisation",
        "-"
    ],
    "wof:name":"Denis Dupont Studio",
    "wof:placetype":"venue"
},
  "geometry": {"coordinates":[4.3998260498,50.5466690063],"type":"Point"}
}