{
  "type": "Feature",
  "properties": {
    "addr:full":"Rue Edouard Anseele 4 Quaregnon Hainaut 7390",
    "addr:housenumber":"4",
    "addr:postcode":"7390",
    "addr:street":"Rue Edouard Anseele",
    "iso:country":"BE",
    "sg:address":"Rue Edouard Anseele 4",
    "sg:city":"Quaregnon",
    "sg:classifiers":[
        {
            "category":"Personal",
            "subcategory":"Barber",
            "type":"Services"
        }
    ],
    "sg:phone":"+32 65 79 51 49",
    "sg:postcode":"7390",
    "sg:province":"Hainaut",
    "sg:tags":[
        "gentleman",
        "salon",
        "-",
        "hairdressing"
    ],
    "wof:name":"Coiffure Rella",
    "wof:placetype":"venue"
},
  "geometry": {"coordinates":[3.8664391041,50.4410400391],"type":"Point"}
}