{
  "type": "Feature",
  "properties": {
    "addr:full":"Dekenijstraat 118 Ukkel/uccle Bruxelles-Capitale 1180",
    "addr:housenumber":"118",
    "addr:postcode":"1180",
    "addr:street":"Dekenijstraat;/",
    "iso:country":"BE",
    "sg:address":"Dekenijstraat 118",
    "sg:city":"Ukkel/uccle",
    "sg:orig_category":"Rijscholen",
    "sg:phone":"+32 2 344 46 73",
    "sg:postcode":"1180",
    "sg:province":"Bruxelles-Capitale",
    "wof:name":"Auto-ecole Europ\u00c9enne",
    "wof:placetype":"venue"
},
  "geometry": {"coordinates":[4.3407440186,50.8032493591],"type":"Point"}
}