{
  "type": "Feature",
  "properties": {
    "addr:full":"Luithagen Haven 16 Antwerpen Antwerpen 2030",
    "addr:housenumber":"16",
    "addr:postcode":"2030",
    "addr:street":"Luithagen Haven",
    "iso:country":"BE",
    "sg:address":"Luithagen Haven 16",
    "sg:city":"Antwerpen",
    "sg:classifiers":[
        {
            "category":"Autos & Motor Vehicles",
            "subcategory":"Automobile Sales",
            "type":"Retail Goods"
        }
    ],
    "sg:phone":"+32 3 541 25 09",
    "sg:postcode":"2030",
    "sg:province":"Antwerpen",
    "sg:tags":[
        "equipment",
        "motor-cars",
        "transport"
    ],
    "wof:name":"Tip Trailer Rental Bvba",
    "wof:placetype":"venue"
},
  "geometry": {"coordinates":[4.4010038376,51.2717895508],"type":"Point"}
}