{
  "type": "Feature",
  "properties": {
    "addr:full":"Rue Vergote 13 Schaarbeek/schaerbeek Bruxelles-Capitale 1030",
    "addr:housenumber":"13",
    "addr:postcode":"1030",
    "addr:street":"Rue Vergote",
    "iso:country":"BE",
    "sg:address":"Rue Vergote 13",
    "sg:city":"Schaarbeek/schaerbeek",
    "sg:orig_category":"Administration d'immeubles",
    "sg:phone":"+32 2 735 86 82",
    "sg:postcode":"1030",
    "sg:province":"Bruxelles-Capitale",
    "wof:name":"Gruuthuyse Castellum",
    "wof:placetype":"venue"
},
  "geometry": {"coordinates":[4.4011330605,50.8443603516],"type":"Point"}
}