{
  "type": "Feature",
  "properties": {
    "iso:country":"BE",
    "sg:address":"Rue Dufrane Friart 11",
    "sg:city":"Frameries",
    "sg:classifiers":[
        {
            "category":"Health Services",
            "subcategory":"Nursing And Care Facility",
            "type":"Services"
        }
    ],
    "sg:phone":"+32 65 61 18 50",
    "sg:postcode":"7080",
    "sg:province":"Hainaut",
    "sg:tags":[
        "home",
        "rest"
    ],
    "wof:name":"Home Les Bosquets",
    "wof:placetype":"venue"
},
  "geometry": {"coordinates":[3.8973629475,50.414390564],"type":"Point"}
}