{
  "type": "Feature",
  "properties": {
    "addr:full":"Rue Grand Vin\u00e2ve 38 Seraing (jemeppe-sur-meuse) Li\u00e8ge 4101",
    "addr:housenumber":"38",
    "addr:postcode":"4101",
    "addr:street":"Rue Grand Vina\u0302Ve;Jemeppe-Sur-Meuse",
    "iso:country":"BE",
    "sg:address":"Rue Grand Vin\u00e2ve 38",
    "sg:city":"Seraing (jemeppe-sur-meuse)",
    "sg:classifiers":[
        {
            "category":"Shopping",
            "subcategory":"Clothing, Apparel, & Fashions",
            "type":"Retail Goods"
        }
    ],
    "sg:phone":"+32 4 233 38 98",
    "sg:postcode":"4101",
    "sg:province":"Li\u00e8ge",
    "sg:tags":[
        "underwear",
        "lingerie",
        "-"
    ],
    "wof:name":"Manon Lingerie",
    "wof:placetype":"venue"
},
  "geometry": {"coordinates":[5.5064082146,50.6166343689],"type":"Point"}
}