{
  "type": "Feature",
  "properties": {
    "iso:country":"BE",
    "sg:address":"Jetselaan 3",
    "sg:city":"Koekelberg",
    "sg:orig_category":"Glaszetten and glaswerk Herstelling and restauratie van meubelen",
    "sg:phone":"+32 2 426 71 64",
    "sg:postcode":"1081",
    "sg:province":"Bruxelles-Capitale",
    "wof:name":"Gdalewitch",
    "wof:placetype":"venue"
},
  "geometry": {"coordinates":[4.3278422356,50.8655128479],"type":"Point"}
}