{
  "type": "Feature",
  "properties": {
    "addr:full":"Kerkelei 81 Brecht Antwerpen 2960",
    "addr:housenumber":"81",
    "addr:postcode":"2960",
    "addr:street":"Kerkelei",
    "iso:country":"BE",
    "sg:address":"Kerkelei 81",
    "sg:city":"Brecht",
    "sg:orig_category":"Agences d'exp\u00e9dition",
    "sg:phone":"+32 3 636 27 68",
    "sg:postcode":"2960",
    "sg:province":"Antwerpen",
    "wof:name":"Cheung Kwong",
    "wof:placetype":"venue"
},
  "geometry": {"coordinates":[4.5854668617,51.2931480408],"type":"Point"}
}