{
  "type": "Feature",
  "properties": {
    "iso:country":"BE",
    "sg:address":"Pastoor Pypestraat 31",
    "sg:city":"Wervik",
    "sg:orig_category":"Activit\u00e9s d\u00b4action sociale sans h\u00e9bergement",
    "sg:phone":"+32 56 51 05 18",
    "sg:postcode":"8940",
    "sg:province":"West-Vlaanderen",
    "wof:name":"Rode Kruis Wervik",
    "wof:placetype":"venue"
},
  "geometry": {"coordinates":[3.0834829807,50.8152503967],"type":"Point"}
}