{
  "type": "Feature",
  "properties": {
    "iso:country":"BE",
    "sg:address":"Antwerpsestraat 87-89",
    "sg:city":"Niel",
    "sg:classifiers":[
        {
            "category":"Shopping",
            "subcategory":"Gifts & Souvenirs",
            "type":"Retail Goods"
        }
    ],
    "sg:phone":"+32 3 844 12 52",
    "sg:postcode":"2845",
    "sg:province":"Antwerpen",
    "sg:tags":[
        "-"
    ],
    "wof:name":"Contact",
    "wof:placetype":"venue"
},
  "geometry": {"coordinates":[4.3308029175,51.1095314026],"type":"Point"}
}