{
  "type": "Feature",
  "properties": {
    "iso:country":"BE",
    "sg:address":"Rue Du Marquis 1",
    "sg:city":"Thuin (leers-et-fosteau)",
    "sg:classifiers":[
        {
            "category":"Home & Garden",
            "subcategory":"Home Furnishings",
            "type":"Retail Goods"
        }
    ],
    "sg:phone":"+32 71 59 23 44",
    "sg:postcode":"6530",
    "sg:province":"Hainaut",
    "sg:tags":[
        "interior",
        "decoration"
    ],
    "wof:name":"Ch\u00e2teau Du Fosteau",
    "wof:placetype":"venue"
},
  "geometry": {"coordinates":[4.2511181831,50.3078460693],"type":"Point"}
}