{
  "type": "Feature",
  "properties": {
    "addr:full":"Rue D'ecosse 17 Ath Hainaut 7800",
    "addr:housenumber":"17",
    "addr:postcode":"7800",
    "addr:street":"Rue D'Ecosse",
    "iso:country":"BE",
    "sg:address":"Rue D'ecosse 17",
    "sg:city":"Ath",
    "sg:classifiers":[
        {
            "category":"Building & Trades",
            "subcategory":"Cleaning & Sanitation",
            "type":"Services"
        }
    ],
    "sg:phone":"+32 68 84 04 75",
    "sg:postcode":"7800",
    "sg:province":"Hainaut",
    "sg:tags":[
        "janitor"
    ],
    "wof:name":"Jumbo Clean Sprl",
    "wof:placetype":"venue"
},
  "geometry": {"coordinates":[3.771420002,50.6245155334],"type":"Point"}
}