{
  "type": "Feature",
  "properties": {
    "iso:country":"BE",
    "sg:address":"Boeschepestraat 14",
    "sg:city":"Poperinge",
    "sg:orig_category":"Enseignement secondaire technique and professionnel",
    "sg:phone":"+32 57 33 46 45",
    "sg:postcode":"8970",
    "sg:province":"West-Vlaanderen",
    "wof:name":"Instituut Heilig Hart",
    "wof:placetype":"venue"
},
  "geometry": {"coordinates":[2.7238330841,50.8525466919],"type":"Point"}
}