{
  "type": "Feature",
  "properties": {
    "addr:full":"Rue Hambursin 94 Gembloux-sur-orneau (gembloux) Namur 5030",
    "addr:housenumber":"94",
    "addr:postcode":"5030",
    "addr:street":"Rue Hambursin;Namur",
    "iso:country":"BE",
    "sg:address":"Rue Hambursin 94",
    "sg:city":"Gembloux-sur-orneau (gembloux)",
    "sg:classifiers":[
        {
            "category":"Building & Trades",
            "subcategory":"Construction",
            "type":"Services"
        }
    ],
    "sg:phone":"+32 81 61 23 99",
    "sg:postcode":"5030",
    "sg:province":"Namur",
    "sg:tags":[
        "carpenter"
    ],
    "wof:name":"Charloteaux S",
    "wof:placetype":"venue"
},
  "geometry": {"coordinates":[4.692109108,50.565612793],"type":"Point"}
}