{
  "type": "Feature",
  "properties": {
    "iso:country":"BE",
    "sg:address":"Stationsstraat 29",
    "sg:city":"Aalst",
    "sg:orig_category":"M\u00e9decins and sp\u00e9cialistes",
    "sg:phone":"+32 2 532 23 66",
    "sg:postcode":"9300",
    "sg:province":"Oost-Vlaanderen",
    "wof:name":"Moonen",
    "wof:placetype":"venue"
},
  "geometry": {"coordinates":[4.0382118225,50.9419288635],"type":"Point"}
}