{
  "type": "Feature",
  "properties": {
    "iso:country":"BE",
    "sg:address":"Joseph Smeetslaan 34",
    "sg:city":"Maasmechelen",
    "sg:orig_category":"Groenten and fruit Gh",
    "sg:phone":"+32 89 76 15 45",
    "sg:postcode":"3630",
    "sg:province":"Limburg",
    "wof:name":"'t Vitamientje",
    "wof:placetype":"venue"
},
  "geometry": {"coordinates":[5.6934070587,50.9649505615],"type":"Point"}
}