{
  "type": "Feature",
  "properties": {
    "iso:country":"BE",
    "sg:address":"Poddegemstraat 25",
    "sg:city":"Grimbergen",
    "sg:orig_category":"Agences de voyages",
    "sg:phone":"+32 2 270 87 78",
    "sg:postcode":"1850",
    "sg:province":"Vlaams-Brabant",
    "wof:name":"Touring",
    "wof:placetype":"venue"
},
  "geometry": {"coordinates":[4.3836550713,50.9378395081],"type":"Point"}
}