{
  "type": "Feature",
  "properties": {
    "addr:full":"Kerkstraat 33 De Haan West-Vlaanderen 8420",
    "addr:housenumber":"33",
    "addr:postcode":"8420",
    "addr:street":"Kerkstraat",
    "iso:country":"BE",
    "sg:address":"Kerkstraat 33",
    "sg:city":"De Haan",
    "sg:classifiers":[
        {
            "category":"Travel",
            "subcategory":"Hotels & Motels",
            "type":"Entertainment"
        }
    ],
    "sg:phone":"+32 50 41 14 17",
    "sg:postcode":"8420",
    "sg:province":"West-Vlaanderen",
    "wof:name":"Cosmopolite",
    "wof:placetype":"venue"
},
  "geometry": {"coordinates":[3.0802690983,51.3000144958],"type":"Point"}
}