{
  "type": "Feature",
  "properties": {
    "addr:full":"Place Du Centre 8 Ham-sur-heure-nalinnes Hainaut 6120",
    "addr:housenumber":"8",
    "addr:postcode":"6120",
    "addr:street":"Place Du Centre;Hainaut",
    "iso:country":"BE",
    "sg:address":"Place Du Centre 8",
    "sg:city":"Ham-sur-heure-nalinnes",
    "sg:classifiers":[
        {
            "category":"Restaurant",
            "type":"Food & Drink"
        }
    ],
    "sg:phone":"+32 71 21 68 81",
    "sg:postcode":"6120",
    "sg:province":"Hainaut",
    "wof:name":"Le Bouchon",
    "wof:placetype":"venue"
},
  "geometry": {"coordinates":[4.4450311661,50.3241424561],"type":"Point"}
}