{
  "type": "Feature",
  "properties": {
    "iso:country":"BE",
    "sg:address":"Rue De La Corderie 47",
    "sg:city":"La Louvi\u00e8re (houdeng-goegnies)",
    "sg:classifiers":[
        {
            "category":"Home & Garden",
            "subcategory":"Home Furnishings",
            "type":"Retail Goods"
        }
    ],
    "sg:phone":"+32 64 84 29 10",
    "sg:postcode":"7110",
    "sg:province":"Hainaut",
    "sg:tags":[
        "interior",
        "decoration"
    ],
    "wof:name":"Harmonie Deco",
    "wof:placetype":"venue"
},
  "geometry": {"coordinates":[4.1505050659,50.4826698303],"type":"Point"}
}