{
  "type": "Feature",
  "properties": {
    "iso:country":"BE",
    "sg:address":"Mulk 155",
    "sg:city":"Hamont-achel (hamont)",
    "sg:classifiers":[
        {
            "category":"Building & Trades",
            "subcategory":"Electrical",
            "type":"Services"
        }
    ],
    "sg:phone":"+32 11 61 25 38",
    "sg:postcode":"3930",
    "sg:province":"Limburg",
    "sg:tags":[
        "industrial",
        "-",
        "electric",
        "contractor"
    ],
    "wof:name":"Atb Electrotechniek",
    "wof:placetype":"venue"
},
  "geometry": {"coordinates":[5.5450549126,51.2511863708],"type":"Point"}
}