{
  "type": "Feature",
  "properties": {
    "iso:country":"BE",
    "sg:address":"Rue Des Isra\u00eblites 10",
    "sg:city":"Frameries (la Bouverie)",
    "sg:classifiers":[
        {
            "category":"Health Services",
            "subcategory":"Doctor",
            "type":"Services"
        }
    ],
    "sg:phone":"+32 65 67 17 32",
    "sg:postcode":"7080",
    "sg:province":"Hainaut",
    "sg:tags":[
        "medicinephysicians",
        "surgeon"
    ],
    "wof:name":"Mairesse C",
    "wof:placetype":"venue"
},
  "geometry": {"coordinates":[3.8732230663,50.3992576599],"type":"Point"}
}