{
  "type": "Feature",
  "properties": {
    "iso:country":"BE",
    "sg:address":"Place Aux Foires 5",
    "sg:city":"Durbuy",
    "sg:classifiers":[
        {
            "category":"Restaurant",
            "type":"Food & Drink"
        }
    ],
    "sg:phone":"+32 86 21 27 62",
    "sg:postcode":"6940",
    "sg:province":"Luxembourg",
    "wof:name":"Restaurant L'hacienda",
    "wof:placetype":"venue"
},
  "geometry": {"coordinates":[5.4562830925,50.3511352539],"type":"Point"}
}