{
  "type": "Feature",
  "properties": {
    "iso:country":"BE",
    "sg:address":"Rue Hocheporte 3",
    "sg:city":"Liege 1",
    "sg:classifiers":[
        {
            "category":"Arts & Performance",
            "subcategory":"Theater",
            "type":"Entertainment"
        }
    ],
    "sg:phone":"+32 4 223 05 76",
    "sg:postcode":"4000",
    "sg:province":"Li\u00e8ge",
    "sg:tags":[
        "group",
        "theatre"
    ],
    "wof:name":"Al Botroule",
    "wof:placetype":"venue"
},
  "geometry": {"coordinates":[5.5656061172,50.6458587646],"type":"Point"}
}