{
  "type": "Feature",
  "properties": {
    "addr:full":"Boulevard Charles-vanp\u00c9e 8 Nivelles Brabant Wallon 1400",
    "addr:housenumber":"8",
    "addr:postcode":"1400",
    "addr:street":"Boulevard Charles-Vanpe\u0301E",
    "iso:country":"BE",
    "sg:address":"Boulevard Charles-vanp\u00c9e 8",
    "sg:city":"Nivelles",
    "sg:orig_category":"D\u00e9corateurs d'int\u00e9rieur",
    "sg:phone":"+32 67 84 25 73",
    "sg:postcode":"1400",
    "sg:province":"Brabant Wallon",
    "wof:name":"Caroline Vanderborght",
    "wof:placetype":"venue"
},
  "geometry": {"coordinates":[4.3284430504,50.5967712402],"type":"Point"}
}