{
  "type": "Feature",
  "properties": {
    "addr:full":"Rue App\u00e2a 16 Colfontaine (wasmes) Hainaut 7340",
    "addr:housenumber":"16",
    "addr:postcode":"7340",
    "addr:street":"Rue Appa\u0302A",
    "iso:country":"BE",
    "sg:address":"Rue App\u00e2a 16",
    "sg:city":"Colfontaine (wasmes)",
    "sg:classifiers":[
        {
            "category":"Health Services",
            "subcategory":"Doctor",
            "type":"Services"
        }
    ],
    "sg:phone":"+32 65 66 76 05",
    "sg:postcode":"7340",
    "sg:province":"Hainaut",
    "sg:tags":[
        "medicinephysicians",
        "surgeon"
    ],
    "wof:name":"Henaut J",
    "wof:placetype":"venue"
},
  "geometry": {"coordinates":[3.8470649719,50.4166488647],"type":"Point"}
}