{
  "type": "Feature",
  "properties": {
    "addr:full":"Rue D'aix La Chapelle 207 Eupen Li\u00e8ge 4701",
    "addr:housenumber":"207",
    "addr:postcode":"4701",
    "addr:street":"Rue D'Aix La Chapelle",
    "iso:country":"BE",
    "sg:address":"Rue D'aix La Chapelle 207",
    "sg:city":"Eupen",
    "sg:orig_category":"Charpentes and couvertures",
    "sg:phone":"+32 87 55 30 35",
    "sg:postcode":"4701",
    "sg:province":"Li\u00e8ge",
    "wof:name":"Jansen J.p. Bedachungen",
    "wof:placetype":"venue"
},
  "geometry": {"coordinates":[6.0404901505,50.6520996094],"type":"Point"}
}