{
  "type": "Feature",
  "properties": {
    "iso:country":"BE",
    "sg:address":"Brugsesteenweg 529",
    "sg:city":"Kuurne",
    "sg:orig_category":"Herstellingen and onderhoud van auto's",
    "sg:phone":"+32 56 72 59 27",
    "sg:postcode":"8520",
    "sg:province":"West-Vlaanderen",
    "wof:name":"Exclusief Cars Carol",
    "wof:placetype":"venue"
},
  "geometry": {"coordinates":[3.2715420723,50.8739967346],"type":"Point"}
}