{
  "type": "Feature",
  "properties": {
    "iso:country":"BE",
    "sg:address":"Lange Lobroekstraat 77",
    "sg:city":"Antwerpen",
    "sg:classifiers":[
        {
            "category":"Bars & Pubs",
            "type":"Food & Drink"
        }
    ],
    "sg:phone":"+32 3 271 08 46",
    "sg:postcode":"2060",
    "sg:province":"Antwerpen",
    "wof:name":"Commericial",
    "wof:placetype":"venue"
},
  "geometry": {"coordinates":[4.4317240715,51.2295036316],"type":"Point"}
}