{
  "type": "Feature",
  "properties": {
    "addr:full":"Prins Albertstraat 2 Sint-niklaas Oost-Vlaanderen 9100",
    "addr:housenumber":"2",
    "addr:postcode":"9100",
    "addr:street":"Prins Albertstraat",
    "iso:country":"BE",
    "sg:address":"Prins Albertstraat 2",
    "sg:city":"Sint-niklaas",
    "sg:classifiers":[
        {
            "category":"Home & Garden",
            "subcategory":"Home Furnishings",
            "type":"Retail Goods"
        }
    ],
    "sg:phone":"+32 3 766 41 83",
    "sg:postcode":"9100",
    "sg:province":"Oost-Vlaanderen",
    "sg:tags":[
        "interior",
        "decoration"
    ],
    "wof:name":"Home",
    "wof:placetype":"venue"
},
  "geometry": {"coordinates":[4.1433620453,51.1703338623],"type":"Point"}
}