{
  "type": "Feature",
  "properties": {
    "iso:country":"BE",
    "sg:address":"Dam 73",
    "sg:city":"Lochristi (zaffelare)",
    "sg:classifiers":[
        {
            "category":"Real Estate",
            "subcategory":"Architect",
            "type":"Services"
        }
    ],
    "sg:phone":"+32 9 355 94 65",
    "sg:postcode":"9080",
    "sg:province":"Oost-Vlaanderen",
    "wof:name":"De Cleene W",
    "wof:placetype":"venue"
},
  "geometry": {"coordinates":[3.865021944,51.1474571228],"type":"Point"}
}