{
  "type": "Feature",
  "properties": {
    "iso:country":"BE",
    "sg:address":"Hoogstraat 220",
    "sg:city":"Zemst",
    "sg:orig_category":"Jardinage",
    "sg:phone":"+32 15 61 53 37",
    "sg:postcode":"1980",
    "sg:province":"Vlaams-Brabant",
    "wof:name":"Van Vlasselaer",
    "wof:placetype":"venue"
},
  "geometry": {"coordinates":[4.4493298531,50.9951400757],"type":"Point"}
}