{
  "type": "Feature",
  "properties": {
    "iso:country":"BE",
    "sg:address":"Kloosterstraat 7",
    "sg:city":"Zele",
    "sg:orig_category":"Artsen and specialisten",
    "sg:phone":"+32 52 45 19 09",
    "sg:postcode":"9240",
    "sg:province":"Oost-Vlaanderen",
    "wof:name":"H\u00c9l\u00c8ne De Keyser",
    "wof:placetype":"venue"
},
  "geometry": {"coordinates":[4.040116787,51.068561554],"type":"Point"}
}