{
  "type": "Feature",
  "properties": {
    "addr:full":"Rue Paul Leduc 14 La Louviere Hainaut 7100",
    "addr:housenumber":"14",
    "addr:postcode":"7100",
    "addr:street":"Rue Paul Leduc",
    "iso:country":"BE",
    "sg:address":"Rue Paul Leduc 14",
    "sg:city":"La Louviere",
    "sg:orig_category":"Chaussures",
    "sg:phone":"+32 64 22 15 71",
    "sg:postcode":"7100",
    "sg:province":"Hainaut",
    "wof:name":"Maison Luyckx",
    "wof:placetype":"venue"
},
  "geometry": {"coordinates":[4.1855678558,50.4764175415],"type":"Point"}
}