{
  "type": "Feature",
  "properties": {
    "iso:country":"BE",
    "sg:address":"Place Henri Hallet 4",
    "sg:city":"Hannut",
    "sg:classifiers":[
        {
            "category":"Shopping",
            "subcategory":"Clothing, Apparel, & Fashions",
            "type":"Retail Goods"
        }
    ],
    "sg:phone":"+32 19 51 44 50",
    "sg:postcode":"4280",
    "sg:province":"Li\u00e8ge",
    "sg:tags":[
        "v\u00eatements",
        "pour",
        "dame"
    ],
    "wof:name":"Maison Clin D'oeil",
    "wof:placetype":"venue"
},
  "geometry": {"coordinates":[5.0790610313,50.6716194153],"type":"Point"}
}