{
  "type": "Feature",
  "properties": {
    "addr:full":"Heistraat 121 Sint-niklaas Oost-Vlaanderen 9100",
    "addr:housenumber":"121",
    "addr:postcode":"9100",
    "addr:street":"Heistraat",
    "iso:country":"BE",
    "sg:address":"Heistraat 121",
    "sg:city":"Sint-niklaas",
    "sg:classifiers":[
        {
            "category":"Retail",
            "subcategory":"Auto Repair",
            "type":"Services"
        }
    ],
    "sg:phone":"+32 3 776 48 70",
    "sg:postcode":"9100",
    "sg:province":"Oost-Vlaanderen",
    "sg:tags":[
        "automobile-body"
    ],
    "wof:name":"Rooselaer R",
    "wof:placetype":"venue"
},
  "geometry": {"coordinates":[4.1318368912,51.1746253967],"type":"Point"}
}