{
  "type": "Feature",
  "properties": {
    "addr:full":"Dr\u00e8ve De Lansrode 11 Rhode-saint-gen\u00e8se Vlaams-Brabant 1640",
    "addr:housenumber":"11",
    "addr:postcode":"1640",
    "addr:street":"Dre\u0300Ve De Lansrode",
    "iso:country":"BE",
    "sg:address":"Dr\u00e8ve De Lansrode 11",
    "sg:city":"Rhode-saint-gen\u00e8se",
    "sg:classifiers":[
        {
            "category":"Shopping",
            "subcategory":"Crafts & Fabrics",
            "type":"Retail Goods"
        }
    ],
    "sg:phone":"+32 2 358 32 68",
    "sg:postcode":"1640",
    "sg:province":"Vlaams-Brabant",
    "sg:tags":[
        "plant",
        "flower",
        "artificial"
    ],
    "wof:name":"S\u00e9rie Verte-natalie Reiche",
    "wof:placetype":"venue"
},
  "geometry": {"coordinates":[4.38813591,50.7520828247],"type":"Point"}
}