{
  "type": "Feature",
  "properties": {
    "addr:full":"Hazelaarstraat 6 Eeklo Oost-Vlaanderen 9900",
    "addr:housenumber":"6",
    "addr:postcode":"9900",
    "addr:street":"Hazelaarstraat",
    "iso:country":"BE",
    "sg:address":"Hazelaarstraat 6",
    "sg:city":"Eeklo",
    "sg:orig_category":"Elektrische installaties voor woningen",
    "sg:phone":"+32 9 378 14 16",
    "sg:postcode":"9900",
    "sg:province":"Oost-Vlaanderen",
    "wof:name":"Patrick Neerinck",
    "wof:placetype":"venue"
},
  "geometry": {"coordinates":[3.5632269382,51.1888389587],"type":"Point"}
}