{
  "type": "Feature",
  "properties": {
    "addr:full":"Eikse Amer 16 Puurs Antwerpen 2870",
    "addr:housenumber":"16",
    "addr:postcode":"2870",
    "addr:street":"Amer",
    "iso:country":"BE",
    "sg:address":"Eikse Amer 16",
    "sg:city":"Puurs",
    "sg:classifiers":[
        {
            "category":"Food & Beverages",
            "subcategory":"Fruits & Vegetables",
            "type":"Retail Goods"
        }
    ],
    "sg:phone":"+32 3 889 02 47",
    "sg:postcode":"2870",
    "sg:province":"Antwerpen",
    "sg:tags":[
        "-"
    ],
    "wof:name":"De Boelpaep Bvba",
    "wof:placetype":"venue"
},
  "geometry": {"coordinates":[4.3115167618,51.0894775391],"type":"Point"}
}