{
  "type": "Feature",
  "properties": {
    "iso:country":"BE",
    "sg:address":"Rue Cloquet 2",
    "sg:city":"Braine L'alleud (braine-l'alleud)",
    "sg:classifiers":[
        {
            "category":"Home & Garden",
            "subcategory":"Garden Supply",
            "type":"Retail Goods"
        }
    ],
    "sg:phone":"+32 2 384 38 98",
    "sg:postcode":"1420",
    "sg:province":"Brabant Wallon",
    "wof:name":"Graineterie-jardinerie De La Poste",
    "wof:placetype":"venue"
},
  "geometry": {"coordinates":[-92.4810409546,46.7143096924],"type":"Point"}
}