{
  "type": "Feature",
  "properties": {
    "addr:full":"Route Du Fraineux 7 Theux (la Reid) Li\u00e8ge 4910",
    "addr:housenumber":"7",
    "addr:postcode":"4910",
    "addr:street":"Route Du Fraineux;La Reid",
    "iso:country":"BE",
    "sg:address":"Route Du Fraineux 7",
    "sg:city":"Theux (la Reid)",
    "sg:classifiers":[
        {
            "category":"Health Services",
            "subcategory":"Doctor",
            "type":"Services"
        }
    ],
    "sg:phone":"+32 87 37 66 00",
    "sg:postcode":"4910",
    "sg:province":"Li\u00e8ge",
    "sg:tags":[
        "medicinephysicians",
        "surgeon"
    ],
    "wof:name":"Legrand V",
    "wof:placetype":"venue"
},
  "geometry": {"coordinates":[5.7905697823,50.4877166748],"type":"Point"}
}