{
  "type": "Feature",
  "properties": {
    "addr:full":"Blektestraat 22 Aalst (hofstade) Oost-Vlaanderen 9308",
    "addr:housenumber":"22",
    "addr:postcode":"9308",
    "addr:street":"Blektestraat",
    "iso:country":"BE",
    "sg:address":"Blektestraat 22",
    "sg:city":"Aalst (hofstade)",
    "sg:classifiers":[
        {
            "category":"Parking",
            "subcategory":"Lot",
            "type":"Transportation"
        }
    ],
    "sg:phone":"+32 495 21 33 31",
    "sg:postcode":"9308",
    "sg:province":"Oost-Vlaanderen",
    "sg:tags":[
        "parking-places",
        "laying-out"
    ],
    "wof:name":"Marckx W",
    "wof:placetype":"venue"
},
  "geometry": {"coordinates":[4.0347590446,50.9603500366],"type":"Point"}
}