{
  "type": "Feature",
  "properties": {
    "iso:country":"BE",
    "sg:address":"Jagerslaan 17",
    "sg:city":"Maasmechelen",
    "sg:classifiers":[
        {
            "category":"Professional",
            "subcategory":"Accounting & Tax Preparation",
            "type":"Services"
        }
    ],
    "sg:phone":"+32 89 76 36 42",
    "sg:postcode":"3630",
    "sg:province":"Limburg",
    "sg:tags":[
        "accountant"
    ],
    "wof:name":"Accountancy En Fiscaliteit Jm Somers Bvba",
    "wof:placetype":"venue"
},
  "geometry": {"coordinates":[5.6758217812,50.9569473267],"type":"Point"}
}