{
  "type": "Feature",
  "properties": {
    "addr:full":"Rue Albert Ier 54 Estaimpuis Hainaut 7730",
    "addr:housenumber":"54",
    "addr:postcode":"7730",
    "addr:street":"Rue Albert Ier;Hainaut",
    "iso:country":"BE",
    "sg:address":"Rue Albert Ier 54",
    "sg:city":"Estaimpuis",
    "sg:classifiers":[
        {
            "category":"Cafe",
            "type":"Food & Drink"
        }
    ],
    "sg:phone":"+32 69 35 20 62",
    "sg:postcode":"7730",
    "sg:province":"Hainaut",
    "sg:tags":[
        "caf\u00e9s"
    ],
    "wof:name":"Caf\u00c9 Du Club",
    "wof:placetype":"venue"
},
  "geometry": {"coordinates":[3.2735199928,50.6673164368],"type":"Point"}
}