{
  "type": "Feature",
  "properties": {
    "addr:full":"Rue Baron Lambert 57 Bruxelles (etterbeek) Bruxelles-Capitale 1040",
    "addr:housenumber":"57",
    "addr:postcode":"1040",
    "addr:street":"Rue Baron Lambert",
    "iso:country":"BE",
    "sg:address":"Rue Baron Lambert 57",
    "sg:city":"Bruxelles (etterbeek)",
    "sg:classifiers":[
        {
            "category":"Building & Trades",
            "subcategory":"Pest Control",
            "type":"Services"
        }
    ],
    "sg:phone":"+32 2 251 46 77",
    "sg:postcode":"1040",
    "sg:province":"Bruxelles-Capitale",
    "sg:tags":[
        "painting",
        "contractor"
    ],
    "wof:name":"Heyvaert & Fils",
    "wof:placetype":"venue"
},
  "geometry": {"coordinates":[4.3890929222,50.8345680237],"type":"Point"}
}