{
  "type": "Feature",
  "properties": {
    "addr:full":"Esenweg 60 Diksmuide West-Vlaanderen 8600",
    "addr:housenumber":"60",
    "addr:postcode":"8600",
    "addr:street":"Esenweg",
    "iso:country":"BE",
    "sg:address":"Esenweg 60",
    "sg:city":"Diksmuide",
    "sg:classifiers":[
        {
            "category":"Arena",
            "subcategory":"Sports Club",
            "type":"Entertainment"
        }
    ],
    "sg:phone":"+32 51 50 31 13",
    "sg:postcode":"8600",
    "sg:province":"West-Vlaanderen",
    "sg:tags":[
        "de"
    ],
    "wof:name":"Zwemverenig. Bruinvissen",
    "wof:placetype":"venue"
},
  "geometry": {"coordinates":[2.8749558926,51.0322227478],"type":"Point"}
}