{
  "type": "Feature",
  "properties": {
    "addr:full":"Rue De Stoupr\u00e9 10 Thuin Hainaut 6530",
    "addr:housenumber":"10",
    "addr:postcode":"6530",
    "addr:street":"Rue De Stoupre\u0301",
    "iso:country":"BE",
    "sg:address":"Rue De Stoupr\u00e9 10",
    "sg:city":"Thuin",
    "sg:classifiers":[
        {
            "category":"Health Services",
            "subcategory":"Doctor",
            "type":"Services"
        }
    ],
    "sg:phone":"+32 71 59 21 82",
    "sg:postcode":"6530",
    "sg:province":"Hainaut",
    "sg:tags":[
        "medicinephysicians",
        "surgeon"
    ],
    "wof:name":"Cuisenaire Jean-pierre",
    "wof:placetype":"venue"
},
  "geometry": {"coordinates":[4.2963018417,50.3370094299],"type":"Point"}
}