{
  "type": "Feature",
  "properties": {
    "addr:full":"Rue Des Bruy\u00e8res 141 Li\u00e8ge 1 Li\u00e8ge 4000",
    "addr:housenumber":"141;1",
    "addr:postcode":"4000",
    "addr:street":"Rue Des Bruye\u0300Res",
    "iso:country":"BE",
    "sg:address":"Rue Des Bruy\u00e8res 141",
    "sg:city":"Li\u00e8ge 1",
    "sg:classifiers":[
        {
            "category":"Health Services",
            "subcategory":"Doctor",
            "type":"Services"
        }
    ],
    "sg:phone":"+32 4 254 11 84",
    "sg:postcode":"4000",
    "sg:province":"Li\u00e8ge",
    "sg:tags":[
        "medicinephysicians",
        "surgeon"
    ],
    "wof:name":"De Lunardo C",
    "wof:placetype":"venue"
},
  "geometry": {"coordinates":[5.5516490936,50.61951828],"type":"Point"}
}