{
  "type": "Feature",
  "properties": {
    "iso:country":"BE",
    "sg:address":"Groendalstraat 15a",
    "sg:city":"Antwerpen",
    "sg:classifiers":[
        {
            "category":"Shopping",
            "subcategory":"Shoes",
            "type":"Retail Goods"
        }
    ],
    "sg:phone":"+32 3 213 05 75",
    "sg:postcode":"2000",
    "sg:province":"Antwerpen",
    "sg:tags":[
        "slipper",
        "-"
    ],
    "wof:name":"Allez Y",
    "wof:placetype":"venue"
},
  "geometry": {"coordinates":[4.4049739838,51.2176704407],"type":"Point"}
}