{
  "type": "Feature",
  "properties": {
    "addr:full":"Heimolenhoek 5 Sint-niklaas Oost-Vlaanderen 9100",
    "addr:housenumber":"5",
    "addr:postcode":"9100",
    "addr:street":"Heimolenhoek",
    "iso:country":"BE",
    "sg:address":"Heimolenhoek 5",
    "sg:city":"Sint-niklaas",
    "sg:classifiers":[
        {
            "category":"Farming",
            "subcategory":"Poultry Farm",
            "type":"Manufacturing & Wholesale Goods"
        }
    ],
    "sg:phone":"+32 3 776 27 98",
    "sg:postcode":"9100",
    "sg:province":"Oost-Vlaanderen",
    "sg:tags":[
        "rabbit",
        "slaughterhouse"
    ],
    "wof:name":"Van Gucht P",
    "wof:placetype":"venue"
},
  "geometry": {"coordinates":[4.131401062,51.1345367432],"type":"Point"}
}