{
  "type": "Feature",
  "properties": {
    "addr:full":"Jezusstraat 28 Antwerpen Antwerpen 2000",
    "addr:housenumber":"28",
    "addr:postcode":"2000",
    "addr:street":"Jezusstraat",
    "iso:country":"BE",
    "sg:address":"Jezusstraat 28",
    "sg:city":"Antwerpen",
    "sg:orig_category":"Diverse opleidingen and onderwijs Krantenuitgeverijen Tijdschriftenuitgeverijen",
    "sg:phone":"+32 3 203 42 00",
    "sg:postcode":"2000",
    "sg:province":"Antwerpen",
    "wof:name":"Provinciaal Veiligheidsinstituut",
    "wof:placetype":"venue"
},
  "geometry": {"coordinates":[4.4141349792,51.2191238403],"type":"Point"}
}