{
  "type": "Feature",
  "properties": {
    "addr:full":"9090 Melle (groot) Oost-Vlaanderen 9090",
    "addr:housenumber":"9090",
    "addr:postcode":"9090",
    "addr:street":"Melle Groot Oost-Vlaanderen",
    "iso:country":"BE",
    "sg:address":"9090",
    "sg:city":"Melle (groot)",
    "sg:orig_category":"Pharmaciens",
    "sg:phone":"+32 900 10 500",
    "sg:postcode":"9090",
    "sg:province":"Oost-Vlaanderen",
    "wof:name":"Pharmacies De Garde",
    "wof:placetype":"venue"
},
  "geometry": {"coordinates":[3.8026149273,51.0023956299],"type":"Point"}
}