{
  "type": "Feature",
  "properties": {
    "addr:full":"Europalaan 37 Overpelt Limburg 3900",
    "addr:housenumber":"37",
    "addr:postcode":"3900",
    "addr:street":"Europalaan",
    "iso:country":"BE",
    "sg:address":"Europalaan 37",
    "sg:city":"Overpelt",
    "sg:orig_category":"Chemicali\u00ebn Gh",
    "sg:phone":"+32 11 66 13 75",
    "sg:postcode":"3900",
    "sg:province":"Limburg",
    "wof:name":"Tigro Chemie",
    "wof:placetype":"venue"
},
  "geometry": {"coordinates":[5.4010329247,51.2234535217],"type":"Point"}
}