{
  "type": "Feature",
  "properties": {
    "iso:country":"BE",
    "sg:address":"Hasseltweg 284",
    "sg:city":"Genk",
    "sg:orig_category":"Bouwwerktuigen Gh Verhuur bouwmachines",
    "sg:phone":"+32 89 35 39 44",
    "sg:postcode":"3600",
    "sg:province":"Limburg",
    "wof:name":"Swinnen G.",
    "wof:placetype":"venue"
},
  "geometry": {"coordinates":[5.4438672066,50.9591064453],"type":"Point"}
}