{
  "type": "Feature",
  "properties": {
    "addr:full":"Rue De Saint-hubert 49 Libramont-chevigny Luxembourg 6800",
    "addr:housenumber":"49",
    "addr:postcode":"6800",
    "addr:street":"Rue De Saint-Hubert",
    "iso:country":"BE",
    "sg:address":"Rue De Saint-hubert 49",
    "sg:city":"Libramont-chevigny",
    "sg:orig_category":"Voedingsspeciaalzaken",
    "sg:phone":"+32 61 22 31 22",
    "sg:postcode":"6800",
    "sg:province":"Luxembourg",
    "wof:name":"Christophe Deom",
    "wof:placetype":"venue"
},
  "geometry": {"coordinates":[5.4735198021,50.0093307495],"type":"Point"}
}