{
  "type": "Feature",
  "properties": {
    "addr:full":"Ter Perre 145 Harelbeke West-Vlaanderen 8530",
    "addr:housenumber":"145",
    "addr:postcode":"8530",
    "iso:country":"BE",
    "sg:address":"Ter Perre 145",
    "sg:city":"Harelbeke",
    "sg:orig_category":"Dansscholen",
    "sg:phone":"+32 56 71 06 16",
    "sg:postcode":"8530",
    "sg:province":"West-Vlaanderen",
    "wof:name":"Dance Generation Kay B.",
    "wof:placetype":"venue"
},
  "geometry": {"coordinates":[3.3012769222,50.8597488403],"type":"Point"}
}