{
  "type": "Feature",
  "properties": {
    "addr:full":"Stationsstraat 6 Erpe-mere Oost-Vlaanderen 9420",
    "addr:housenumber":"6",
    "addr:postcode":"9420",
    "addr:street":"Stationsstraat",
    "iso:country":"BE",
    "sg:address":"Stationsstraat 6",
    "sg:city":"Erpe-mere",
    "sg:orig_category":"Banken and kredietinstellingen",
    "sg:phone":"+32 53 62 32 91",
    "sg:postcode":"9420",
    "sg:province":"Oost-Vlaanderen",
    "wof:name":"Citibank",
    "wof:placetype":"venue"
},
  "geometry": {"coordinates":[3.9221389294,50.9063529968],"type":"Point"}
}