{
  "type": "Feature",
  "properties": {
    "iso:country":"BE",
    "sg:address":"Zandberg 81w",
    "sg:city":"Zele",
    "sg:classifiers":[
        {
            "category":"Bars & Pubs",
            "type":"Food & Drink"
        }
    ],
    "sg:phone":"+32 52 45 16 17",
    "sg:postcode":"9240",
    "sg:province":"Oost-Vlaanderen",
    "sg:tags":[
        "tavern"
    ],
    "wof:name":"Swingcafe Herb's",
    "wof:placetype":"venue"
},
  "geometry": {"coordinates":[4.045129776,51.0691108704],"type":"Point"}
}