{
  "type": "Feature",
  "properties": {
    "iso:country":"BE",
    "sg:address":"Hooiestraat 7",
    "sg:city":"Knesselare",
    "sg:orig_category":"Herstellingen and onderhoud van auto's",
    "sg:phone":"+32 9 374 66 86",
    "sg:postcode":"9910",
    "sg:province":"Oost-Vlaanderen",
    "wof:name":"Garage Deprest",
    "wof:placetype":"venue"
},
  "geometry": {"coordinates":[3.4199519157,51.1351699829],"type":"Point"}
}