{
  "type": "Feature",
  "properties": {
    "addr:full":"Dennenlaan 50 Antwerpen Antwerpen 2610",
    "addr:housenumber":"50",
    "addr:postcode":"2610",
    "addr:street":"Dennenlaan",
    "iso:country":"BE",
    "sg:address":"Dennenlaan 50",
    "sg:city":"Antwerpen",
    "sg:orig_category":"Geluidsopnames Informaticaconsulenten Verhuur televisie- and audiovisuele apparatuur",
    "sg:phone":"+32 3 825 08 91",
    "sg:postcode":"2610",
    "sg:province":"Antwerpen",
    "wof:name":"S.c.s.",
    "wof:placetype":"venue"
},
  "geometry": {"coordinates":[4.4070429802,51.176197052],"type":"Point"}
}