{
  "type": "Feature",
  "properties": {
    "iso:country":"BE",
    "sg:address":"Rue Du Berger 27",
    "sg:city":"Mouscron (dottignies)",
    "sg:classifiers":[
        {
            "category":"Personal",
            "subcategory":"Nail Salon",
            "type":"Services"
        }
    ],
    "sg:phone":"+32 56 48 76 15",
    "sg:postcode":"7711",
    "sg:province":"Hainaut",
    "sg:tags":[
        "pedicure"
    ],
    "wof:name":"P\u00e9dichris",
    "wof:placetype":"venue"
},
  "geometry": {"coordinates":[3.3008790016,50.7357330322],"type":"Point"}
}