{
  "type": "Feature",
  "properties": {
    "addr:full":"Sint-pietersnoordstraat 9 Brugge West-Vlaanderen 8000",
    "addr:housenumber":"9",
    "addr:postcode":"8000",
    "addr:street":"Sint-Pietersnoordstraat",
    "iso:country":"BE",
    "sg:address":"Sint-pietersnoordstraat 9",
    "sg:city":"Brugge",
    "sg:classifiers":[
        {
            "category":"Building & Trades",
            "subcategory":"Construction",
            "type":"Services"
        }
    ],
    "sg:phone":"+32 50 67 02 58",
    "sg:postcode":"8000",
    "sg:province":"West-Vlaanderen",
    "sg:tags":[
        "installation",
        "-",
        "central",
        "heating"
    ],
    "wof:name":"Daerden Nv",
    "wof:placetype":"venue"
},
  "geometry": {"coordinates":[3.2024469376,51.2332878113],"type":"Point"}
}