{
  "type": "Feature",
  "properties": {
    "addr:full":"De Lei 25 Balen Antwerpen 2491",
    "addr:housenumber":"25",
    "addr:postcode":"2491",
    "addr:street":"De Lei",
    "iso:country":"BE",
    "sg:address":"De Lei 25",
    "sg:city":"Balen",
    "sg:classifiers":[
        {
            "category":"Cafe",
            "type":"Food & Drink"
        }
    ],
    "sg:phone":"+32 14 30 18 62",
    "sg:postcode":"2491",
    "sg:province":"Antwerpen",
    "sg:tags":[
        "caf\u00e9s"
    ],
    "wof:name":"Hans Bloemmen",
    "wof:placetype":"venue"
},
  "geometry": {"coordinates":[5.1497840881,51.1437683105],"type":"Point"}
}