{
  "type": "Feature",
  "properties": {
    "addr:full":"Grote Markt 31 Sint Truiden Limburg 3800",
    "addr:housenumber":"31",
    "addr:postcode":"3800",
    "addr:street":"Grote Markt",
    "iso:country":"BE",
    "sg:address":"Grote Markt 31",
    "sg:city":"Sint Truiden",
    "sg:orig_category":"Agences d\u00b4interim and personnel temporaire",
    "sg:phone":"+32 11 68 79 00",
    "sg:postcode":"3800",
    "sg:province":"Limburg",
    "wof:name":"Vedior Interim",
    "wof:placetype":"venue"
},
  "geometry": {"coordinates":[5.1845397949,50.8150062561],"type":"Point"}
}