{
  "type": "Feature",
  "properties": {
    "addr:full":"Antwerpsebaan 220 Antwerpen Antwerpen 2040",
    "addr:housenumber":"220",
    "addr:postcode":"2040",
    "addr:street":"Antwerpsebaan",
    "iso:country":"BE",
    "sg:address":"Antwerpsebaan 220",
    "sg:city":"Antwerpen",
    "sg:classifiers":[
        {
            "category":"Professional",
            "subcategory":"Engineering",
            "type":"Services"
        }
    ],
    "sg:phone":"+32 3 568 65 97",
    "sg:postcode":"2040",
    "sg:province":"Antwerpen",
    "sg:tags":[
        "road",
        "surfacing",
        "asphalt",
        "highway"
    ],
    "wof:name":"Gebroeders Simons Wegenbouw Nv",
    "wof:placetype":"venue"
},
  "geometry": {"coordinates":[4.3201899529,51.3488044739],"type":"Point"}
}