{
  "type": "Feature",
  "properties": {
    "iso:country":"BE",
    "sg:address":"9170",
    "sg:city":"Sint-gillis-waas",
    "sg:classifiers":[
        {
            "category":"Utilities",
            "subcategory":"Cable",
            "type":"Services"
        }
    ],
    "sg:phone":"+32 3 727 11 27",
    "sg:postcode":"9170",
    "sg:province":"Oost-Vlaanderen",
    "sg:tags":[
        "laying"
    ],
    "wof:name":"Pima Nv",
    "wof:placetype":"venue"
},
  "geometry": {"coordinates":[4.1255750656,51.2189941406],"type":"Point"}
}