{
  "type": "Feature",
  "properties": {
    "addr:full":"Sterrenstraat 58-1 Lier Antwerpen 2500",
    "addr:housenumber":"58-1",
    "addr:postcode":"2500",
    "addr:street":"Sterrenstraat",
    "iso:country":"BE",
    "sg:address":"Sterrenstraat 58-1",
    "sg:city":"Lier",
    "sg:classifiers":[
        {
            "category":"Banks & Credit Unions",
            "subcategory":"Investment Brokerage",
            "type":"Services"
        }
    ],
    "sg:phone":"+32 3 491 91 50",
    "sg:postcode":"2500",
    "sg:province":"Antwerpen",
    "sg:tags":[
        "detection",
        "gas"
    ],
    "wof:name":"Msa Belgium Nv",
    "wof:placetype":"venue"
},
  "geometry": {"coordinates":[4.5659441948,51.139251709],"type":"Point"}
}