{
  "type": "Feature",
  "properties": {
    "iso:country":"BE",
    "sg:address":"Rue De Courtrai 16",
    "sg:city":"Mouscron",
    "sg:orig_category":"Reisbureaus",
    "sg:phone":"+32 56 33 01 17",
    "sg:postcode":"7700",
    "sg:province":"Hainaut",
    "wof:name":"Promo Travel",
    "wof:placetype":"venue"
},
  "geometry": {"coordinates":[3.2166700363,50.7447624207],"type":"Point"}
}