{
  "type": "Feature",
  "properties": {
    "iso:country":"BE",
    "sg:address":"Th. Van Cauwenberghslei 62a",
    "sg:city":"Schoten",
    "sg:orig_category":"Kapsalons",
    "sg:phone":"+32 3 658 24 49",
    "sg:postcode":"2900",
    "sg:province":"Antwerpen",
    "wof:name":"Coiffure Miranda",
    "wof:placetype":"venue"
},
  "geometry": {"coordinates":[4.5045361519,51.2524414062],"type":"Point"}
}