{
  "type": "Feature",
  "properties": {
    "addr:full":"Avenue D'argenteuil 102 Waterloo Brabant Wallon 1410",
    "addr:housenumber":"102",
    "addr:postcode":"1410",
    "addr:street":"Avenue D'Argenteuil",
    "iso:country":"BE",
    "sg:address":"Avenue D'argenteuil 102",
    "sg:city":"Waterloo",
    "sg:classifiers":[
        {
            "category":"Building & Trades",
            "subcategory":"Landscaping Services",
            "type":"Services"
        }
    ],
    "sg:phone":"+32 10 22 34 22",
    "sg:postcode":"1410",
    "sg:province":"Brabant Wallon",
    "sg:tags":[
        "gardening",
        "garden",
        "maintenance"
    ],
    "wof:name":"Arrosage",
    "wof:placetype":"venue"
},
  "geometry": {"coordinates":[4.4111027718,50.7027816772],"type":"Point"}
}