{
  "type": "Feature",
  "properties": {
    "addr:full":"Koning Albertstraat 9 Diest Vlaams-Brabant 3290",
    "addr:housenumber":"9",
    "addr:postcode":"3290",
    "addr:street":"Koning Albertstraat",
    "iso:country":"BE",
    "sg:address":"Koning Albertstraat 9",
    "sg:city":"Diest",
    "sg:orig_category":"Rainwear",
    "sg:phone":"+32 13 33 71 73",
    "sg:postcode":"3290",
    "sg:province":"Vlaams-Brabant",
    "wof:name":"Borgias",
    "wof:placetype":"venue"
},
  "geometry": {"coordinates":[5.0523791313,50.9853935242],"type":"Point"}
}