{
  "type": "Feature",
  "properties": {
    "addr:full":"Pr\u00c9 Messire 8bb Stavelot Li\u00e8ge 4970",
    "addr:housenumber":"8bb",
    "addr:postcode":"4970",
    "addr:street":"Pre\u0301 Messire",
    "iso:country":"BE",
    "sg:address":"Pr\u00c9 Messire 8bb",
    "sg:city":"Stavelot",
    "sg:orig_category":"Belastingconsulenten Diverse juridische dienstverlening",
    "sg:phone":"+32 80 86 34 03",
    "sg:postcode":"4970",
    "sg:province":"Li\u00e8ge",
    "wof:name":"Fiduciaire Andr\u00c9 Thunus",
    "wof:placetype":"venue"
},
  "geometry": {"coordinates":[5.9385647774,50.3959503174],"type":"Point"}
}