{
  "type": "Feature",
  "properties": {
    "addr:full":"Rue Louis Germeaux 19 Awans (hognoul) Li\u00e8ge 4342",
    "addr:housenumber":"19",
    "addr:postcode":"4342",
    "addr:street":"Rue Louis Germeaux",
    "iso:country":"BE",
    "sg:address":"Rue Louis Germeaux 19",
    "sg:city":"Awans (hognoul)",
    "sg:classifiers":[
        {
            "category":"Personal",
            "subcategory":"Beauty Salon",
            "type":"Services"
        }
    ],
    "sg:phone":"+32 4 257 47 64",
    "sg:postcode":"4342",
    "sg:province":"Li\u00e8ge",
    "sg:tags":[
        "lady",
        "-",
        "hairdressing"
    ],
    "wof:name":"Maris-bouquet",
    "wof:placetype":"venue"
},
  "geometry": {"coordinates":[5.4536581039,50.6813278198],"type":"Point"}
}