{
  "type": "Feature",
  "properties": {
    "iso:country":"BE",
    "sg:address":"Rue Saint-bernard 106",
    "sg:city":"Bruxelles (saint-gilles)",
    "sg:classifiers":[
        {
            "category":"Retail",
            "subcategory":"Repair Shop",
            "type":"Services"
        }
    ],
    "sg:phone":"+32 2 538 89 30",
    "sg:postcode":"1060",
    "sg:province":"Bruxelles-Capitale",
    "sg:tags":[
        "-",
        "mainten",
        "watch",
        "clock"
    ],
    "wof:name":"Ceulemans L",
    "wof:placetype":"venue"
},
  "geometry": {"coordinates":[4.3521227837,50.8271751404],"type":"Point"}
}