{
  "type": "Feature",
  "properties": {
    "addr:full":"Avenue Victor David 133 Limbourg Li\u00e8ge 4830",
    "addr:housenumber":"133",
    "addr:postcode":"4830",
    "addr:street":"Avenue Victor David",
    "iso:country":"BE",
    "sg:address":"Avenue Victor David 133",
    "sg:city":"Limbourg",
    "sg:orig_category":"Boissons",
    "sg:phone":"+32 87 76 35 26",
    "sg:postcode":"4830",
    "sg:province":"Li\u00e8ge",
    "wof:name":"Aux Accords Gourmands",
    "wof:placetype":"venue"
},
  "geometry": {"coordinates":[5.9407401085,50.6112518311],"type":"Point"}
}