{
  "type": "Feature",
  "properties": {
    "addr:full":"Clos Du Rouge Clo\u00eetre 5 La Hulpe Brabant Wallon 1310",
    "addr:housenumber":"5",
    "addr:postcode":"1310",
    "addr:street":"Clos Du Rouge Cloi\u0302Tre",
    "iso:country":"BE",
    "sg:address":"Clos Du Rouge Clo\u00eetre 5",
    "sg:city":"La Hulpe",
    "sg:classifiers":[
        {
            "category":"Home & Garden",
            "subcategory":"Home Furnishings",
            "type":"Retail Goods"
        }
    ],
    "sg:phone":"+32 2 653 26 26",
    "sg:postcode":"1310",
    "sg:province":"Brabant Wallon",
    "sg:tags":[
        "interior",
        "decoration"
    ],
    "wof:name":"De Capitani Invest Sprl",
    "wof:placetype":"venue"
},
  "geometry": {"coordinates":[4.4899721146,50.7492523193],"type":"Point"}
}