{
  "type": "Feature",
  "properties": {
    "addr:full":"Rue De Bois Seigneur Isaac 71 Braine L'alleud (ophain-bois-seigneur-isaac) Brabant Wallon 1421",
    "addr:housenumber":"71",
    "addr:postcode":"1421",
    "addr:street":"Rue De Bois Seigneur Isaac",
    "iso:country":"BE",
    "sg:address":"Rue De Bois Seigneur Isaac 71",
    "sg:city":"Braine L'alleud (ophain-bois-seigneur-isaac)",
    "sg:classifiers":[
        {
            "category":"Health Services",
            "subcategory":"Health Practitioner",
            "type":"Services"
        }
    ],
    "sg:phone":"+32 2 385 09 04",
    "sg:postcode":"1421",
    "sg:province":"Brabant Wallon",
    "sg:tags":[
        "physiotherapist"
    ],
    "wof:name":"Bousson M",
    "wof:placetype":"venue"
},
  "geometry": {"coordinates":[4.3260340691,50.6664619446],"type":"Point"}
}