{
  "type": "Feature",
  "properties": {
    "iso:country":"BE",
    "sg:address":"Madouplein 1b34",
    "sg:city":"Sint-joost-ten-node/saint-josse-ten-noode",
    "sg:orig_category":"Advocaten and juridische adviseurs",
    "sg:phone":"+32 2 219 16 20",
    "sg:postcode":"1210",
    "sg:province":"Bruxelles-Capitale",
    "wof:name":"Sofie Dejonghe",
    "wof:placetype":"venue"
},
  "geometry": {"coordinates":[4.369576931,50.8494567871],"type":"Point"}
}