{
  "type": "Feature",
  "properties": {
    "addr:full":"Avenue Marie-jos\u00e9 61 Binche (ressaix) Hainaut 7134",
    "addr:housenumber":"61",
    "addr:postcode":"7134",
    "addr:street":"Avenue Marie-Jose\u0301",
    "iso:country":"BE",
    "sg:address":"Avenue Marie-jos\u00e9 61",
    "sg:city":"Binche (ressaix)",
    "sg:classifiers":[
        {
            "category":"Building & Trades",
            "subcategory":"Plumbing",
            "type":"Services"
        }
    ],
    "sg:phone":"+32 64 33 58 68",
    "sg:postcode":"7134",
    "sg:province":"Hainaut",
    "sg:tags":[
        "contractor"
    ],
    "wof:name":"Demory E",
    "wof:placetype":"venue"
},
  "geometry": {"coordinates":[4.1806979179,50.4138259888],"type":"Point"}
}