{
  "type": "Feature",
  "properties": {
    "iso:country":"BE",
    "sg:address":"Marktplein 15",
    "sg:city":"Diepenbeek",
    "sg:classifiers":[
        {
            "category":"Insurance",
            "subcategory":"Life Insurance",
            "type":"Services"
        }
    ],
    "sg:phone":"+32 11 33 28 11",
    "sg:postcode":"3590",
    "sg:province":"Limburg",
    "sg:tags":[
        "assurance"
    ],
    "wof:name":"Thys Andr\u00c9",
    "wof:placetype":"venue"
},
  "geometry": {"coordinates":[5.4186367989,50.9073982239],"type":"Point"}
}