{
  "type": "Feature",
  "properties": {
    "iso:country":"BE",
    "sg:address":"Rue Arthur Baudhuin 58",
    "sg:city":"Fleurus",
    "sg:orig_category":"Kapsalons",
    "sg:phone":"+32 71 81 54 69",
    "sg:postcode":"6220",
    "sg:province":"Hainaut",
    "wof:name":"Curzi Oria",
    "wof:placetype":"venue"
},
  "geometry": {"coordinates":[4.5549092293,50.4568328857],"type":"Point"}
}