{
  "type": "Feature",
  "properties": {
    "addr:full":"Molenberg 3 Dilbeek Vlaams-Brabant 1702",
    "addr:housenumber":"3",
    "addr:postcode":"1702",
    "addr:street":"Molenberg",
    "iso:country":"BE",
    "sg:address":"Molenberg 3",
    "sg:city":"Dilbeek",
    "sg:orig_category":"Plomberie, chauffage and installations sanitaires. Installation de menuiserie en bois and plastique.",
    "sg:phone":"+32 2 466 23 28",
    "sg:postcode":"1702",
    "sg:province":"Vlaams-Brabant",
    "wof:name":"Leunens",
    "wof:placetype":"venue"
},
  "geometry": {"coordinates":[4.2452511787,50.8729400635],"type":"Point"}
}