{
  "type": "Feature",
  "properties": {
    "iso:country":"BE",
    "sg:address":"Rue Grande 155",
    "sg:city":"Dinant",
    "sg:orig_category":"Geschenken and souvenirs Meubelzaken, woning- and keukeninrichting Verlichting and huishoudartikelen",
    "sg:phone":"+32 82 22 73 69",
    "sg:postcode":"5500",
    "sg:province":"Namur",
    "wof:name":"Casa",
    "wof:placetype":"venue"
},
  "geometry": {"coordinates":[4.9130120277,50.2604408264],"type":"Point"}
}