{
  "type": "Feature",
  "properties": {
    "addr:full":"Rue Balthazar-florence 27 Namur Namur 5000",
    "addr:housenumber":"27",
    "addr:postcode":"5000",
    "addr:street":"Rue Balthazar-Florence",
    "iso:country":"BE",
    "sg:address":"Rue Balthazar-florence 27",
    "sg:city":"Namur",
    "sg:orig_category":"Entretien and r\u00e9parations de voitures",
    "sg:phone":"+32 81 73 65 10",
    "sg:postcode":"5000",
    "sg:province":"Namur",
    "wof:name":"Jacques Demonte",
    "wof:placetype":"venue"
},
  "geometry": {"coordinates":[4.8446288109,50.4660339355],"type":"Point"}
}