{
  "type": "Feature",
  "properties": {
    "addr:full":"Chemin Du Fort Des Voiles 70 Chaumont-gistoux (bonlez) Brabant Wallon 1325",
    "addr:housenumber":"70",
    "addr:postcode":"1325",
    "addr:street":"Chemin Du Fort Des Voiles",
    "iso:country":"BE",
    "sg:address":"Chemin Du Fort Des Voiles 70",
    "sg:city":"Chaumont-gistoux (bonlez)",
    "sg:classifiers":[
        {
            "category":"Banks & Credit Unions",
            "subcategory":"Investment Brokerage",
            "type":"Services"
        }
    ],
    "sg:phone":"+32 10 68 95 28",
    "sg:postcode":"1325",
    "sg:province":"Brabant Wallon",
    "sg:tags":[
        "repair",
        "-",
        "installation",
        "sanitary",
        "article"
    ],
    "wof:name":"Smeyers (les) Entreprises",
    "wof:placetype":"venue"
},
  "geometry": {"coordinates":[4.7223548889,50.6729545593],"type":"Point"}
}