{
  "type": "Feature",
  "properties": {
    "iso:country":"BE",
    "sg:address":"Rue Saint-jacques 2",
    "sg:city":"Charleroi (mont-sur-marchienne)",
    "sg:classifiers":[
        {
            "category":"Professional",
            "subcategory":"Computer Services",
            "type":"Services"
        }
    ],
    "sg:phone":"+32 71 43 73 54",
    "sg:postcode":"6032",
    "sg:province":"Hainaut",
    "sg:tags":[
        "-",
        "processing",
        "data"
    ],
    "wof:name":"B C I",
    "wof:placetype":"venue"
},
  "geometry": {"coordinates":[4.4098391533,50.3925514221],"type":"Point"}
}