{
  "type": "Feature",
  "properties": {
    "iso:country":"BE",
    "sg:address":"Pullaarsteenweg 107",
    "sg:city":"Puurs",
    "sg:orig_category":"Woningbouw",
    "sg:phone":"+32 3 866 11 24",
    "sg:postcode":"2870",
    "sg:province":"Antwerpen",
    "wof:name":"Haubo",
    "wof:placetype":"venue"
},
  "geometry": {"coordinates":[4.3238382339,51.0721206665],"type":"Point"}
}