{
  "type": "Feature",
  "properties": {
    "addr:full":"Noordzandstraat 60 Brugge West-Vlaanderen 8000",
    "addr:housenumber":"60",
    "addr:postcode":"8000",
    "addr:street":"Noordzandstraat",
    "iso:country":"BE",
    "sg:address":"Noordzandstraat 60",
    "sg:city":"Brugge",
    "sg:orig_category":"Art and fournitures artistiques. Souvenirs and objets artisanaux",
    "sg:phone":"+32 50 33 11 51",
    "sg:postcode":"8000",
    "sg:province":"West-Vlaanderen",
    "wof:name":"Expo",
    "wof:placetype":"venue"
},
  "geometry": {"coordinates":[3.2194271088,51.2068977356],"type":"Point"}
}