{
  "type": "Feature",
  "properties": {
    "iso:country":"BE",
    "sg:address":"Everdijkruis 22",
    "sg:city":"Wuustwezel",
    "sg:orig_category":"Non-Classified Establishments",
    "sg:phone":"+32 3 633 30 15",
    "sg:postcode":"2990",
    "sg:province":"Antwerpen",
    "wof:name":"D&m Motorsport",
    "wof:placetype":"venue"
},
  "geometry": {"coordinates":[4.5402750969,51.3398132324],"type":"Point"}
}