{
  "type": "Feature",
  "properties": {
    "addr:full":". Meise (groot) Vlaams-Brabant 1860",
    "addr:postcode":"1860",
    "addr:street":"Groot Vlaams-Brabant",
    "iso:country":"BE",
    "sg:address":".",
    "sg:city":"Meise (groot)",
    "sg:orig_category":"Apotheken",
    "sg:phone":"+32 900 10 500",
    "sg:postcode":"1860",
    "sg:province":"Vlaams-Brabant",
    "wof:name":"Apothekers Van Wacht",
    "wof:placetype":"venue"
},
  "geometry": {"coordinates":[4.3299398422,50.9351844788],"type":"Point"}
}