{
  "type": "Feature",
  "properties": {
    "addr:full":"Ijzerkaai 28 Kortrijk West-Vlaanderen 8500",
    "addr:housenumber":"28",
    "addr:postcode":"8500",
    "addr:street":"Ijzerkaai",
    "iso:country":"BE",
    "sg:address":"Ijzerkaai 28",
    "sg:city":"Kortrijk",
    "sg:classifiers":[
        {
            "category":"Home & Garden",
            "subcategory":"Home Furnishings",
            "type":"Retail Goods"
        }
    ],
    "sg:phone":"+32 56 21 46 66",
    "sg:postcode":"8500",
    "sg:province":"West-Vlaanderen",
    "sg:tags":[
        "interior",
        "decoration"
    ],
    "wof:name":"Burggraeve Jan Bvba",
    "wof:placetype":"venue"
},
  "geometry": {"coordinates":[3.2657880783,50.8325119019],"type":"Point"}
}