{
  "type": "Feature",
  "properties": {
    "addr:full":"Kleine Snijderstraat 32 Lebbeke Oost-Vlaanderen 9280",
    "addr:housenumber":"32",
    "addr:postcode":"9280",
    "addr:street":"Kleine Snijderstraat",
    "iso:country":"BE",
    "sg:address":"Kleine Snijderstraat 32",
    "sg:city":"Lebbeke",
    "sg:orig_category":"Sportclubs",
    "sg:phone":"+32 52 41 11 03",
    "sg:postcode":"9280",
    "sg:province":"Oost-Vlaanderen",
    "wof:name":"V.c. V.d.b.modern Lebbeke",
    "wof:placetype":"venue"
},
  "geometry": {"coordinates":[4.1491370201,51.0064926147],"type":"Point"}
}