{
  "type": "Feature",
  "properties": {
    "iso:country":"BE",
    "sg:address":"Grote Potterijstraat 8",
    "sg:city":"Moorslede",
    "sg:orig_category":"Eleveurs and marchands de porcs",
    "sg:phone":"+32 51 77 72 99",
    "sg:postcode":"8890",
    "sg:province":"West-Vlaanderen",
    "wof:name":"Willy Ledoux",
    "wof:placetype":"venue"
},
  "geometry": {"coordinates":[3.0664560795,50.8683815002],"type":"Point"}
}