{
  "type": "Feature",
  "properties": {
    "addr:full":"Koning Albertstraat 87 Eeklo Oost-Vlaanderen 9900",
    "addr:housenumber":"87",
    "addr:postcode":"9900",
    "addr:street":"Koning Albertstraat",
    "iso:country":"BE",
    "sg:address":"Koning Albertstraat 87",
    "sg:city":"Eeklo",
    "sg:classifiers":[
        {
            "category":"Personal",
            "subcategory":"Beauty Salon",
            "type":"Services"
        }
    ],
    "sg:phone":"+32 9 377 34 68",
    "sg:postcode":"9900",
    "sg:province":"Oost-Vlaanderen",
    "sg:tags":[
        "lady",
        "-",
        "hairdressing"
    ],
    "wof:name":"Ginneberge",
    "wof:placetype":"venue"
},
  "geometry": {"coordinates":[3.5596649647,51.185508728],"type":"Point"}
}