{
  "type": "Feature",
  "properties": {
    "iso:country":"BE",
    "sg:address":"Oude Vest 45",
    "sg:city":"Dendermonde",
    "sg:orig_category":"Eclairage et \u00e9quipements du foyer",
    "sg:phone":"+32 52 21 10 58",
    "sg:postcode":"9200",
    "sg:province":"Oost-Vlaanderen",
    "wof:name":"Blokker",
    "wof:placetype":"venue"
},
  "geometry": {"coordinates":[4.1008329391,51.0289421082],"type":"Point"}
}