{
  "type": "Feature",
  "properties": {
    "addr:full":"Ieperlaan 14 Brussel/bruxelles Bruxelles-Capitale 1000",
    "addr:housenumber":"14",
    "addr:postcode":"1000",
    "addr:street":"Ieperlaan;/",
    "iso:country":"BE",
    "sg:address":"Ieperlaan 14",
    "sg:city":"Brussel/bruxelles",
    "sg:orig_category":"GROENTEN AND FRUIT Kruideniers",
    "sg:phone":"+32 2 217 56 46",
    "sg:postcode":"1000",
    "sg:province":"Bruxelles-Capitale",
    "wof:name":"Amin",
    "wof:placetype":"venue"
},
  "geometry": {"coordinates":[4.3466119766,50.8559570312],"type":"Point"}
}