{
  "type": "Feature",
  "properties": {
    "addr:full":"Rue Pairois 38 Dour Hainaut 7370",
    "addr:housenumber":"38",
    "addr:postcode":"7370",
    "addr:street":"Rue Pairois;Hainaut",
    "iso:country":"BE",
    "sg:address":"Rue Pairois 38",
    "sg:city":"Dour",
    "sg:orig_category":"Diverse voedingsmiddelen Gh Vis and zeevruchten",
    "sg:phone":"+32 65 65 22 15",
    "sg:postcode":"7370",
    "sg:province":"Hainaut",
    "wof:name":"Maison Labye",
    "wof:placetype":"venue"
},
  "geometry": {"coordinates":[3.7813870907,50.397895813],"type":"Point"}
}