{
  "type": "Feature",
  "properties": {
    "addr:full":"Avenue Jean Xxiii 4 Rixensart Brabant Wallon 1330",
    "addr:housenumber":"4",
    "addr:postcode":"1330",
    "addr:street":"Avenue Jean Xxiii;Wallon",
    "iso:country":"BE",
    "sg:address":"Avenue Jean Xxiii 4",
    "sg:city":"Rixensart",
    "sg:classifiers":[
        {
            "category":"Health Services",
            "subcategory":"Health Practitioner",
            "type":"Services"
        }
    ],
    "sg:phone":"+32 2 653 67 94",
    "sg:postcode":"1330",
    "sg:province":"Brabant Wallon",
    "sg:tags":[
        "physiotherapist"
    ],
    "wof:name":"Kindermans E Mme",
    "wof:placetype":"venue"
},
  "geometry": {"coordinates":[4.5208940506,50.7068901062],"type":"Point"}
}