{
  "type": "Feature",
  "properties": {
    "iso:country":"BE",
    "sg:address":"Nieuwe Steenweg 98",
    "sg:city":"Tongeren",
    "sg:classifiers":[
        {
            "category":"Banks & Credit Unions",
            "subcategory":"Bank",
            "type":"Services"
        }
    ],
    "sg:phone":"+32 12 23 35 49",
    "sg:postcode":"3700",
    "sg:province":"Limburg",
    "sg:tags":[
        "savings-banks"
    ],
    "wof:name":"Bellis C",
    "wof:placetype":"venue"
},
  "geometry": {"coordinates":[5.4504909515,50.7980728149],"type":"Point"}
}