{
  "type": "Feature",
  "properties": {
    "addr:full":"Brasschaatbaan 25 Brecht Antwerpen 2960",
    "addr:housenumber":"25",
    "addr:postcode":"2960",
    "addr:street":"Brasschaatbaan",
    "iso:country":"BE",
    "sg:address":"Brasschaatbaan 25",
    "sg:city":"Brecht",
    "sg:classifiers":[
        {
            "category":"Government",
            "subcategory":"Post Office",
            "type":"Public Place"
        }
    ],
    "sg:phone":"+32 3 663 49 03",
    "sg:postcode":"2960",
    "sg:province":"Antwerpen",
    "sg:tags":[
        "picture",
        "restoring"
    ],
    "wof:name":"Buyens I",
    "wof:placetype":"venue"
},
  "geometry": {"coordinates":[4.5802259445,51.3405036926],"type":"Point"}
}