{
  "type": "Feature",
  "properties": {
    "addr:full":"Chauss\u00c9e De March\u00c9 27 Assesse Namur 5330",
    "addr:housenumber":"27",
    "addr:postcode":"5330",
    "addr:street":"Chausse\u0301E De Marche\u0301",
    "iso:country":"BE",
    "sg:address":"Chauss\u00c9e De March\u00c9 27",
    "sg:city":"Assesse",
    "sg:orig_category":"V\u00e9t\u00e9rinaires",
    "sg:phone":"+32 83 65 55 00",
    "sg:postcode":"5330",
    "sg:province":"Namur",
    "wof:name":"Luc Bouveroux",
    "wof:placetype":"venue"
},
  "geometry": {"coordinates":[5.0211567879,50.3733482361],"type":"Point"}
}