{
  "type": "Feature",
  "properties": {
    "iso:country":"BE",
    "sg:address":"Baron Ruzettelaan 113",
    "sg:city":"Brugge",
    "sg:orig_category":"Epiceries",
    "sg:phone":"+32 50 35 88 54",
    "sg:postcode":"8310",
    "sg:province":"West-Vlaanderen",
    "wof:name":"Battard",
    "wof:placetype":"venue"
},
  "geometry": {"coordinates":[3.2319970131,51.195098877],"type":"Point"}
}