{
  "type": "Feature",
  "properties": {
    "iso:country":"BE",
    "sg:address":"Sint-waldetrudisstraat 65",
    "sg:city":"Herentals",
    "sg:orig_category":"V\u00e9t\u00e9rinaires",
    "sg:phone":"+32 14 21 63 46",
    "sg:postcode":"2200",
    "sg:province":"Antwerpen",
    "wof:name":"Frans Van Tendeloo",
    "wof:placetype":"venue"
},
  "geometry": {"coordinates":[4.8370819092,51.1716651917],"type":"Point"}
}