{
  "type": "Feature",
  "properties": {
    "iso:country":"BE",
    "sg:address":"Rozenstraat 12",
    "sg:city":"Niel",
    "sg:orig_category":"MEUBELONTWERP AND -INSTALLATIE",
    "sg:phone":"+32 3 888 81 52",
    "sg:postcode":"2845",
    "sg:province":"Antwerpen",
    "wof:name":"Dirk Rypens",
    "wof:placetype":"venue"
},
  "geometry": {"coordinates":[4.3375101089,51.1149215698],"type":"Point"}
}