{
  "type": "Feature",
  "properties": {
    "addr:full":"Rue De La Machine \u00e0 Feu 10 Dour Hainaut 7370",
    "addr:housenumber":"10",
    "addr:postcode":"7370",
    "addr:street":"Rue De La;Hainaut",
    "iso:country":"BE",
    "sg:address":"Rue De La Machine \u00e0 Feu 10",
    "sg:city":"Dour",
    "sg:classifiers":[
        {
            "category":"Bakery",
            "type":"Food & Drink"
        }
    ],
    "sg:phone":"+32 65 69 00 39",
    "sg:postcode":"7370",
    "sg:province":"Hainaut",
    "sg:tags":[
        "confectioner",
        "baker"
    ],
    "wof:name":"J N Gaufre",
    "wof:placetype":"venue"
},
  "geometry": {"coordinates":[3.7785201073,50.39635849],"type":"Point"}
}