{
  "type": "Feature",
  "properties": {
    "addr:full":"Rue De Bouttignies 34 Erquelinnes Hainaut 6560",
    "addr:housenumber":"34",
    "addr:postcode":"6560",
    "addr:street":"Rue De Bouttignies",
    "iso:country":"BE",
    "sg:address":"Rue De Bouttignies 34",
    "sg:city":"Erquelinnes",
    "sg:classifiers":[
        {
            "category":"Food & Beverages",
            "subcategory":"Fruits & Vegetables",
            "type":"Retail Goods"
        }
    ],
    "sg:phone":"+32 64 77 25 52",
    "sg:postcode":"6560",
    "sg:province":"Hainaut",
    "sg:tags":[
        "l\u00e9gumes"
    ],
    "wof:name":"Pascal Flore",
    "wof:placetype":"venue"
},
  "geometry": {"coordinates":[4.0812530518,50.3334846497],"type":"Point"}
}