{
  "type": "Feature",
  "properties": {
    "addr:full":"Rue Du G\u00c9n\u00c9ral Bertrand 43 Li\u00c8ge Li\u00e8ge 4000",
    "addr:housenumber":"43",
    "addr:postcode":"4000",
    "addr:street":"Rue Du Ge\u0301Ne\u0301Ral Bertrand",
    "iso:country":"BE",
    "sg:address":"Rue Du G\u00c9n\u00c9ral Bertrand 43",
    "sg:city":"Li\u00c8ge",
    "sg:orig_category":"Mobiele kappers",
    "sg:phone":"+32 4 226 64 71",
    "sg:postcode":"4000",
    "sg:province":"Li\u00e8ge",
    "wof:name":"Madeleine Hayard",
    "wof:placetype":"venue"
},
  "geometry": {"coordinates":[5.557267189,50.6446876526],"type":"Point"}
}