{
  "type": "Feature",
  "properties": {
    "addr:full":"Galgebergstraat 42 Hasselt (kuringen) Limburg 3511",
    "addr:housenumber":"42",
    "addr:postcode":"3511",
    "addr:street":"Galgebergstraat",
    "iso:country":"BE",
    "sg:address":"Galgebergstraat 42",
    "sg:city":"Hasselt (kuringen)",
    "sg:classifiers":[
        {
            "category":"Banks & Credit Unions",
            "subcategory":"Investment Brokerage",
            "type":"Services"
        }
    ],
    "sg:phone":"+32 11 23 35 85",
    "sg:postcode":"3511",
    "sg:province":"Limburg",
    "sg:tags":[
        "auditor"
    ],
    "wof:name":"Vos R",
    "wof:placetype":"venue"
},
  "geometry": {"coordinates":[5.3034238815,50.9432487488],"type":"Point"}
}