{
  "type": "Feature",
  "properties": {
    "iso:country":"BE",
    "sg:address":"Rue Du Culot 9",
    "sg:city":"Bouillon",
    "sg:classifiers":[
        {
            "category":"Autos & Motor Vehicles",
            "subcategory":"Fuel & Gas Station",
            "type":"Retail Goods"
        }
    ],
    "sg:phone":"+32 61 46 67 07",
    "sg:postcode":"6831",
    "sg:province":"Luxembourg",
    "sg:tags":[
        "stations-service",
        "carburants"
    ],
    "wof:name":"Godart Guy",
    "wof:placetype":"venue"
},
  "geometry": {"coordinates":[5.0937948227,49.8202438354],"type":"Point"}
}