{
  "type": "Feature",
  "properties": {
    "addr:full":"Ontmijnersstraat 46 Blankenberge West-Vlaanderen 8370",
    "addr:housenumber":"46",
    "addr:postcode":"8370",
    "addr:street":"Ontmijnersstraat",
    "iso:country":"BE",
    "sg:address":"Ontmijnersstraat 46",
    "sg:city":"Blankenberge",
    "sg:orig_category":"G\u00e2teaux, p\u00e2tisserie and biscuits Fab",
    "sg:phone":"+32 50 41 86 00",
    "sg:postcode":"8370",
    "sg:province":"West-Vlaanderen",
    "wof:name":"V.t.en V.t.",
    "wof:placetype":"venue"
},
  "geometry": {"coordinates":[3.1328039169,51.308303833],"type":"Point"}
}