{
  "type": "Feature",
  "properties": {
    "iso:country":"BE",
    "sg:address":"Rue Octave Battaille 3",
    "sg:city":"Beloeil",
    "sg:classifiers":[
        {
            "category":"Personal",
            "subcategory":"Beauty Salon",
            "type":"Services"
        }
    ],
    "sg:phone":"+32 69 57 57 10",
    "sg:postcode":"7971",
    "sg:province":"Hainaut",
    "sg:tags":[
        "de",
        "coiffure"
    ],
    "wof:name":"Coiffure Mo'tif",
    "wof:placetype":"venue"
},
  "geometry": {"coordinates":[3.6455869675,50.5262794495],"type":"Point"}
}