{
  "type": "Feature",
  "properties": {
    "iso:country":"BE",
    "sg:address":"Broeckstraat 47",
    "sg:city":"Gavere",
    "sg:orig_category":"Immobili\u00ebnkantoren",
    "sg:phone":"+32 9 384 70 43",
    "sg:postcode":"9890",
    "sg:province":"Oost-Vlaanderen",
    "wof:name":"Verloove",
    "wof:placetype":"venue"
},
  "geometry": {"coordinates":[3.658010006,50.9319343567],"type":"Point"}
}