{
  "type": "Feature",
  "properties": {
    "addr:full":"Rue Du Pavillon 60 Bruxelles (schaerbeek) Bruxelles-Capitale 1030",
    "addr:housenumber":"60",
    "addr:postcode":"1030",
    "addr:street":"Rue Du Pavillon",
    "iso:country":"BE",
    "sg:address":"Rue Du Pavillon 60",
    "sg:city":"Bruxelles (schaerbeek)",
    "sg:classifiers":[
        {
            "category":"Shopping",
            "subcategory":"Antiques",
            "type":"Retail Goods"
        }
    ],
    "sg:phone":"+32 2 241 59 15",
    "sg:postcode":"1030",
    "sg:province":"Bruxelles-Capitale",
    "wof:name":"Galerie Du Pavillon",
    "wof:placetype":"venue"
},
  "geometry": {"coordinates":[4.3695421219,50.8698348999],"type":"Point"}
}