{
  "type": "Feature",
  "properties": {
    "addr:full":"Rue D\u00b4en Haut 22 Beaumont Hainaut 6500",
    "addr:housenumber":"22",
    "addr:postcode":"6500",
    "addr:street":"Rue D\u00b4En Haut;Hainaut",
    "iso:country":"BE",
    "sg:address":"Rue D\u00b4en Haut 22",
    "sg:city":"Beaumont",
    "sg:orig_category":"Bloemen and planten",
    "sg:phone":"+32 71 33 46 62",
    "sg:postcode":"6500",
    "sg:province":"Hainaut",
    "wof:name":"L\u00b4en Vie De Fleurs",
    "wof:placetype":"venue"
},
  "geometry": {"coordinates":[4.2378540039,50.2354545593],"type":"Point"}
}