{
  "type": "Feature",
  "properties": {
    "iso:country":"BE",
    "sg:address":"Rue De Fleurie 26",
    "sg:city":"Durbuy (bomal-sur-ourthe)",
    "sg:classifiers":[
        {
            "category":"Bars & Pubs",
            "type":"Food & Drink"
        }
    ],
    "sg:phone":"+32 86 21 13 93",
    "sg:postcode":"6941",
    "sg:province":"Luxembourg",
    "sg:tags":[
        "tavern"
    ],
    "wof:name":"Big-ben (le)",
    "wof:placetype":"venue"
},
  "geometry": {"coordinates":[5.524184227,50.3770332336],"type":"Point"}
}