{
  "type": "Feature",
  "properties": {
    "addr:full":"Antwerpsesteenweg 92 Mechelen Antwerpen 2800",
    "addr:housenumber":"92",
    "addr:postcode":"2800",
    "addr:street":"Antwerpsesteenweg",
    "iso:country":"BE",
    "sg:address":"Antwerpsesteenweg 92",
    "sg:city":"Mechelen",
    "sg:orig_category":"Salles de conf\u00e9rences and de r\u00e9ceptions. Alimentation sp\u00e9cialis\u00e9e. Restaurants",
    "sg:phone":"+32 15 20 95 82",
    "sg:postcode":"2800",
    "sg:province":"Antwerpen",
    "wof:name":"Tivoli Kasteel",
    "wof:placetype":"venue"
},
  "geometry": {"coordinates":[4.4688458443,51.0460853577],"type":"Point"}
}