{
  "type": "Feature",
  "properties": {
    "iso:country":"BE",
    "sg:address":"Ferdinand Verbieststraat 4",
    "sg:city":"Antwerpen",
    "sg:classifiers":[
        {
            "category":"Fast Food",
            "type":"Food & Drink"
        }
    ],
    "sg:phone":"+32 3 542 26 33",
    "sg:postcode":"2030",
    "sg:province":"Antwerpen",
    "sg:tags":[
        "\u00c0",
        "restaurants",
        "emporter",
        "restaurant"
    ],
    "wof:name":"Wong",
    "wof:placetype":"venue"
},
  "geometry": {"coordinates":[4.4162697792,51.2725105286],"type":"Point"}
}