{
  "type": "Feature",
  "properties": {
    "iso:country":"BE",
    "sg:address":"Politieke-gevangenenstraat 32",
    "sg:city":"Harelbeke",
    "sg:orig_category":"Charpentes and couvertures. Mat\u00e9riaux de construction Gr",
    "sg:phone":"+32 56 22 23 48",
    "sg:postcode":"8530",
    "sg:province":"West-Vlaanderen",
    "wof:name":"Luc Callens",
    "wof:placetype":"venue"
},
  "geometry": {"coordinates":[3.3078279495,50.8334236145],"type":"Point"}
}