{
  "type": "Feature",
  "properties": {
    "addr:full":"Groendreef 23 Waasmunster Oost-Vlaanderen 9250",
    "addr:housenumber":"23",
    "addr:postcode":"9250",
    "addr:street":"Groendreef",
    "iso:country":"BE",
    "sg:address":"Groendreef 23",
    "sg:city":"Waasmunster",
    "sg:orig_category":"Plaatsen van vloer- and muurbekleding",
    "sg:phone":"+32 3 772 41 84",
    "sg:postcode":"9250",
    "sg:province":"Oost-Vlaanderen",
    "wof:name":"Johan De Cock",
    "wof:placetype":"venue"
},
  "geometry": {"coordinates":[4.1054258347,51.1287078857],"type":"Point"}
}