{
  "type": "Feature",
  "properties": {
    "addr:full":"Place De Linde 6 Bruxelles (anderlecht) Bruxelles-Capitale 1070",
    "addr:housenumber":"6",
    "addr:postcode":"1070",
    "addr:street":"Place De Linde",
    "iso:country":"BE",
    "sg:address":"Place De Linde 6",
    "sg:city":"Bruxelles (anderlecht)",
    "sg:classifiers":[
        {
            "category":"Personal",
            "subcategory":"Beauty Salon",
            "type":"Services"
        }
    ],
    "sg:phone":"+32 2 523 58 02",
    "sg:postcode":"1070",
    "sg:province":"Bruxelles-Capitale",
    "sg:tags":[
        "lady",
        "-",
        "hairdressing"
    ],
    "wof:name":"Paola",
    "wof:placetype":"venue"
},
  "geometry": {"coordinates":[4.2997617722,50.8359947205],"type":"Point"}
}