{
  "type": "Feature",
  "properties": {
    "addr:full":"Stationsstraat 127 Oostkamp West-Vlaanderen 8020",
    "addr:housenumber":"127",
    "addr:postcode":"8020",
    "addr:street":"Stationsstraat",
    "iso:country":"BE",
    "sg:address":"Stationsstraat 127",
    "sg:city":"Oostkamp",
    "sg:orig_category":"Herstelling leer and schoeisel",
    "sg:phone":"+32 50 84 01 19",
    "sg:postcode":"8020",
    "sg:province":"West-Vlaanderen",
    "wof:name":"Andre Taveirne",
    "wof:placetype":"venue"
},
  "geometry": {"coordinates":[3.2445559502,51.1535873413],"type":"Point"}
}