{
  "type": "Feature",
  "properties": {
    "addr:full":"Molenstraat 158 Rumst Antwerpen 2840",
    "addr:housenumber":"158",
    "addr:postcode":"2840",
    "addr:street":"Molenstraat",
    "iso:country":"BE",
    "sg:address":"Molenstraat 158",
    "sg:city":"Rumst",
    "sg:orig_category":"Installatie van houten of kunststof schrijnwerk Installatie van metalen schrijnwerk",
    "sg:phone":"+32 3 888 92 67",
    "sg:postcode":"2840",
    "sg:province":"Antwerpen",
    "wof:name":"Jozef Sas En Zoon",
    "wof:placetype":"venue"
},
  "geometry": {"coordinates":[4.3949408531,51.101852417],"type":"Point"}
}