{
  "type": "Feature",
  "properties": {
    "iso:country":"BE",
    "sg:address":"J.p. Minckelersstraat 94",
    "sg:city":"Leuven",
    "sg:classifiers":[
        {
            "category":"Parking",
            "subcategory":"Garage",
            "type":"Transportation"
        }
    ],
    "sg:phone":"+32 16 20 28 77",
    "sg:postcode":"3000",
    "sg:province":"Vlaams-Brabant",
    "wof:name":"Pmb Bvba",
    "wof:placetype":"venue"
},
  "geometry": {"coordinates":[4.7057490349,50.8836669922],"type":"Point"}
}