{
  "type": "Feature",
  "properties": {
    "iso:country":"BE",
    "sg:address":"Koolmijnlaan 77",
    "sg:city":"Beringen",
    "sg:orig_category":"Boucheries",
    "sg:phone":"+32 11 43 17 59",
    "sg:postcode":"3580",
    "sg:province":"Limburg",
    "wof:name":"Budgetslager",
    "wof:placetype":"venue"
},
  "geometry": {"coordinates":[5.2231497765,51.0546646118],"type":"Point"}
}