{
  "type": "Feature",
  "properties": {
    "addr:full":"Rue Chauss\u00c9e 141 Awans Li\u00e8ge 4342",
    "addr:housenumber":"141",
    "addr:postcode":"4342",
    "addr:street":"Rue Chausse\u0301E",
    "iso:country":"BE",
    "sg:address":"Rue Chauss\u00c9e 141",
    "sg:city":"Awans",
    "sg:orig_category":"V\u00e9hicules automobiles",
    "sg:phone":"+32 4 257 68 68",
    "sg:postcode":"4342",
    "sg:province":"Li\u00e8ge",
    "wof:name":"Euro-cars",
    "wof:placetype":"venue"
},
  "geometry": {"coordinates":[5.4523801804,50.6873283386],"type":"Point"}
}