{
  "type": "Feature",
  "properties": {
    "addr:full":"Grote Ieperstraat 98 Wevelgem West-Vlaanderen 8560",
    "addr:housenumber":"98",
    "addr:postcode":"8560",
    "addr:street":"Grote Ieperstraat",
    "iso:country":"BE",
    "sg:address":"Grote Ieperstraat 98",
    "sg:city":"Wevelgem",
    "sg:orig_category":"Ordinateurs and \u00e9quipement informatique",
    "sg:phone":"+32 495 37 00 03",
    "sg:postcode":"8560",
    "sg:province":"West-Vlaanderen",
    "wof:name":"Kmo-software",
    "wof:placetype":"venue"
},
  "geometry": {"coordinates":[3.2022719383,50.8358039856],"type":"Point"}
}