{
  "type": "Feature",
  "properties": {
    "iso:country":"BE",
    "sg:address":"Rue De La Station 74",
    "sg:city":"Paliseul",
    "sg:orig_category":"D\u00e9taillants en pi\u00e8ces and accessoires de voitures",
    "sg:phone":"+32 61 53 41 68",
    "sg:postcode":"6850",
    "sg:province":"Luxembourg",
    "wof:name":"Devillers Autodistribution",
    "wof:placetype":"venue"
},
  "geometry": {"coordinates":[5.122341156,49.8977050781],"type":"Point"}
}