{
  "type": "Feature",
  "properties": {
    "addr:full":"Doorniksesteenweg 81ab1 Kortrijk West-Vlaanderen 8500",
    "addr:postcode":"8500",
    "addr:street":"Doorniksesteenweg",
    "iso:country":"BE",
    "sg:address":"Doorniksesteenweg 81ab1",
    "sg:city":"Kortrijk",
    "sg:orig_category":"Secr\u00e9tariats sociaux",
    "sg:phone":"+32 56 26 61 60",
    "sg:postcode":"8500",
    "sg:province":"West-Vlaanderen",
    "wof:name":"Seco",
    "wof:placetype":"venue"
},
  "geometry": {"coordinates":[3.2784368992,50.8091964722],"type":"Point"}
}