{
  "type": "Feature",
  "properties": {
    "addr:full":"Meuleken 1 Assenede (boekhoute) Oost-Vlaanderen 9961",
    "addr:housenumber":"1",
    "addr:postcode":"9961",
    "addr:street":"Meuleken",
    "iso:country":"BE",
    "sg:address":"Meuleken 1",
    "sg:city":"Assenede (boekhoute)",
    "sg:orig_category":"Non-Classified Establishments",
    "sg:phone":"+32 9 373 71 18",
    "sg:postcode":"9961",
    "sg:province":"Oost-Vlaanderen",
    "wof:name":"Valo",
    "wof:placetype":"venue"
},
  "geometry": {"coordinates":[3.7533829212,51.2274360657],"type":"Point"}
}