{
  "type": "Feature",
  "properties": {
    "addr:full":"Chauss\u00c9e De Bruxelles 441 Edingen/enghien Hainaut 7850",
    "addr:housenumber":"441",
    "addr:postcode":"7850",
    "addr:street":"Chausse\u0301E De Bruxelles",
    "iso:country":"BE",
    "sg:address":"Chauss\u00c9e De Bruxelles 441",
    "sg:city":"Edingen/enghien",
    "sg:classifiers":[
        {
            "category":"Professional",
            "subcategory":"Business Services",
            "type":"Services"
        }
    ],
    "sg:phone":"+32 2 397 00 97",
    "sg:postcode":"7850",
    "sg:province":"Hainaut",
    "sg:tags":[
        "aux",
        "diver",
        "entreprises"
    ],
    "wof:name":"Bureau Faits D'hiver",
    "wof:placetype":"venue"
},
  "geometry": {"coordinates":[4.0494527817,50.6934928894],"type":"Point"}
}