{
  "type": "Feature",
  "properties": {
    "addr:full":"Kazernenln 7 Etterbeek Bruxelles-Capitale 1040",
    "addr:housenumber":"7",
    "addr:postcode":"1040",
    "addr:street":"Kazernenln",
    "iso:country":"BE",
    "sg:address":"Kazernenln 7",
    "sg:city":"Etterbeek",
    "sg:classifiers":[
        {
            "category":"Banks & Credit Unions",
            "subcategory":"Bank",
            "type":"Services"
        }
    ],
    "sg:phone":"+32 2 648 47 44",
    "sg:postcode":"1040",
    "sg:province":"Bruxelles-Capitale",
    "wof:name":"Banque Bruxelles Lambert Sa",
    "wof:placetype":"venue"
},
  "geometry": {"coordinates":[4.3899698257,50.8299942017],"type":"Point"}
}