{
  "type": "Feature",
  "properties": {
    "iso:country":"BE",
    "sg:address":"Brusselsesteenweg 810",
    "sg:city":"Asse",
    "sg:orig_category":"Catering and organisatie van feesten Diverse zakelijke dienstverlening Voedingsspeciaalzaken Winkeli",
    "sg:phone":"+32 477 82 28 24",
    "sg:postcode":"1731",
    "sg:province":"Vlaams-Brabant",
    "wof:name":"Partyline",
    "wof:placetype":"venue"
},
  "geometry": {"coordinates":[4.2834329605,50.8768196106],"type":"Point"}
}