{
  "type": "Feature",
  "properties": {
    "iso:country":"BE",
    "sg:address":"Josse Biesmansstraat 57",
    "sg:city":"Hoeilaart",
    "sg:classifiers":[
        {
            "category":"Food & Beverages",
            "subcategory":"Bakery",
            "type":"Retail Goods"
        }
    ],
    "sg:phone":"+32 10 23 01 50",
    "sg:postcode":"1560",
    "sg:province":"Vlaams-Brabant",
    "sg:tags":[
        "biscuit"
    ],
    "wof:name":"Etablissement J.l. Lambert S.a.",
    "wof:placetype":"venue"
},
  "geometry": {"coordinates":[4.4667158127,50.7705459595],"type":"Point"}
}