{
  "type": "Feature",
  "properties": {
    "addr:full":"Statielei 51 Mortsel Antwerpen 2640",
    "addr:housenumber":"51",
    "addr:postcode":"2640",
    "addr:street":"Statielei",
    "iso:country":"BE",
    "sg:address":"Statielei 51",
    "sg:city":"Mortsel",
    "sg:orig_category":"Parfumeries. Drogueries",
    "sg:phone":"+32 3 448 02 11",
    "sg:postcode":"2640",
    "sg:province":"Antwerpen",
    "wof:name":"Kruidvat",
    "wof:placetype":"venue"
},
  "geometry": {"coordinates":[4.451775074,51.1707305908],"type":"Point"}
}