{
  "type": "Feature",
  "properties": {
    "addr:full":"Rue Saint-joseph 2 Mouscron Hainaut 7700",
    "addr:housenumber":"2",
    "addr:postcode":"7700",
    "addr:street":"Rue Saint-Joseph",
    "iso:country":"BE",
    "sg:address":"Rue Saint-joseph 2",
    "sg:city":"Mouscron",
    "sg:orig_category":"Pr\u00eats hypoth\u00e9caires and cr\u00e9dits immobiliers",
    "sg:phone":"+32 56 33 22 61",
    "sg:postcode":"7700",
    "sg:province":"Hainaut",
    "wof:name":"Foyer De La Fronti\u00c8re",
    "wof:placetype":"venue"
},
  "geometry": {"coordinates":[3.1943259239,50.7268981934],"type":"Point"}
}