{
  "type": "Feature",
  "properties": {
    "addr:full":"Koning Albert I-laan 131 Brugge West-Vlaanderen 8200",
    "addr:housenumber":"131",
    "addr:postcode":"8200",
    "addr:street":"Koning Albert I-Laan",
    "iso:country":"BE",
    "sg:address":"Koning Albert I-laan 131",
    "sg:city":"Brugge",
    "sg:orig_category":"Verbruikerskredietinstellingen Verzekeringsmakelaars and experts",
    "sg:phone":"+32 50 40 28 60",
    "sg:postcode":"8200",
    "sg:province":"West-Vlaanderen",
    "wof:name":"Discontokant. Brugge-kust",
    "wof:placetype":"venue"
},
  "geometry": {"coordinates":[3.1942210197,51.1648864746],"type":"Point"}
}