{
  "type": "Feature",
  "properties": {
    "iso:country":"BE",
    "sg:address":"Baaigemstraat 123",
    "sg:city":"Gavere",
    "sg:orig_category":"Pharmaciens",
    "sg:phone":"+32 9 384 54 32",
    "sg:postcode":"9890",
    "sg:province":"Oost-Vlaanderen",
    "wof:name":"Francoise Van Der Heggen",
    "wof:placetype":"venue"
},
  "geometry": {"coordinates":[3.6737511158,50.9312019348],"type":"Point"}
}