{
  "type": "Feature",
  "properties": {
    "addr:full":"Sint-denijslaan 201 Gent Oost-Vlaanderen 9000",
    "addr:housenumber":"201",
    "addr:postcode":"9000",
    "addr:street":"Oost-Vlaanderen",
    "iso:country":"BE",
    "sg:address":"Sint-denijslaan 201",
    "sg:city":"Gent",
    "sg:classifiers":[
        {
            "category":"Professional",
            "subcategory":"Lawyer & Legal Services",
            "type":"Services"
        }
    ],
    "sg:phone":"+32 9 222 89 19",
    "sg:postcode":"9000",
    "sg:province":"Oost-Vlaanderen",
    "wof:name":"Van Der Gucht Willy",
    "wof:placetype":"venue"
},
  "geometry": {"coordinates":[3.7080259323,51.0351715088],"type":"Point"}
}