{
  "type": "Feature",
  "properties": {
    "iso:country":"BE",
    "sg:address":"Sint-truidensesteenweg 26",
    "sg:city":"Tienen",
    "sg:classifiers":[
        {
            "category":"Social Services",
            "subcategory":"Job Training",
            "type":"Services"
        }
    ],
    "sg:phone":"+32 16 80 58 30",
    "sg:postcode":"3300",
    "sg:province":"Vlaams-Brabant",
    "sg:tags":[
        "personnel"
    ],
    "wof:name":"Fundament",
    "wof:placetype":"venue"
},
  "geometry": {"coordinates":[4.9552521706,50.80103302],"type":"Point"}
}