{
  "type": "Feature",
  "properties": {
    "iso:country":"BE",
    "sg:address":"J.p. Minckelersstraat 64",
    "sg:city":"Leuven",
    "sg:orig_category":"Slagers",
    "sg:phone":"+32 16 23 81 44",
    "sg:postcode":"3000",
    "sg:province":"Vlaams-Brabant",
    "wof:name":"Renmans",
    "wof:placetype":"venue"
},
  "geometry": {"coordinates":[4.7064938545,50.8831863403],"type":"Point"}
}