{
  "type": "Feature",
  "properties": {
    "addr:full":"Sint-jorislaan 133 Herk-de-stad Limburg 3540",
    "addr:housenumber":"133",
    "addr:postcode":"3540",
    "addr:street":"Sint-Jorislaan",
    "iso:country":"BE",
    "sg:address":"Sint-jorislaan 133",
    "sg:city":"Herk-de-stad",
    "sg:orig_category":"Instituts de beaut\u00e9",
    "sg:phone":"+32 13 55 34 44",
    "sg:postcode":"3540",
    "sg:province":"Limburg",
    "wof:name":"Instituut Rita",
    "wof:placetype":"venue"
},
  "geometry": {"coordinates":[5.1942958832,50.9538154602],"type":"Point"}
}