{
  "type": "Feature",
  "properties": {
    "iso:country":"BE",
    "sg:address":"Kapelstraat 39",
    "sg:city":"Harelbeke",
    "sg:orig_category":"Rev\u00eatements pour sols and murs. Construction de maisons",
    "sg:phone":"+32 56 70 60 12",
    "sg:postcode":"8531",
    "sg:province":"West-Vlaanderen",
    "wof:name":"Adams",
    "wof:placetype":"venue"
},
  "geometry": {"coordinates":[3.2922339439,50.88098526],"type":"Point"}
}