{
  "type": "Feature",
  "properties": {
    "addr:full":"Tuinwijkstraat 16 Middelkerke West-Vlaanderen 8434",
    "addr:housenumber":"16",
    "addr:postcode":"8434",
    "addr:street":"Tuinwijkstraat",
    "iso:country":"BE",
    "sg:address":"Tuinwijkstraat 16",
    "sg:city":"Middelkerke",
    "sg:classifiers":[
        {
            "category":"Arena",
            "subcategory":"Sports Club",
            "type":"Entertainment"
        }
    ],
    "sg:phone":"+32 58 23 62 13",
    "sg:postcode":"8434",
    "sg:province":"West-Vlaanderen",
    "sg:tags":[
        "de"
    ],
    "wof:name":"W.c. De Lombarden",
    "wof:placetype":"venue"
},
  "geometry": {"coordinates":[2.7611548901,51.1487159729],"type":"Point"}
}