{
  "type": "Feature",
  "properties": {
    "addr:full":"Processieweg 28 Steenokkerzeel Vlaams-Brabant 1820",
    "addr:housenumber":"28",
    "addr:postcode":"1820",
    "addr:street":"Processieweg",
    "iso:country":"BE",
    "sg:address":"Processieweg 28",
    "sg:city":"Steenokkerzeel",
    "sg:classifiers":[
        {
            "category":"Home & Garden",
            "subcategory":"Carpets & Floor Coverings",
            "type":"Retail Goods"
        }
    ],
    "sg:phone":"+32 2 757 63 73",
    "sg:postcode":"1820",
    "sg:province":"Vlaams-Brabant",
    "sg:tags":[
        "layer",
        "mosaicists"
    ],
    "wof:name":"Milani B",
    "wof:placetype":"venue"
},
  "geometry": {"coordinates":[4.5209598541,50.9025230408],"type":"Point"}
}