{
  "type": "Feature",
  "properties": {
    "addr:full":"Leuvensestraat 126 Tienen Vlaams-Brabant 3300",
    "addr:housenumber":"126",
    "addr:postcode":"3300",
    "addr:street":"Leuvensestraat",
    "iso:country":"BE",
    "sg:address":"Leuvensestraat 126",
    "sg:city":"Tienen",
    "sg:classifiers":[
        {
            "category":"Bakery",
            "type":"Food & Drink"
        }
    ],
    "sg:phone":"+32 16 81 02 98",
    "sg:postcode":"3300",
    "sg:province":"Vlaams-Brabant",
    "sg:tags":[
        "confectioner",
        "baker"
    ],
    "wof:name":"Bob",
    "wof:placetype":"venue"
},
  "geometry": {"coordinates":[4.9307451248,50.8095474243],"type":"Point"}
}