{
  "type": "Feature",
  "properties": {
    "addr:full":"Herentalsstraat 18 Turnhout Antwerpen 2300",
    "addr:housenumber":"18",
    "addr:postcode":"2300",
    "addr:street":"Herentalsstraat",
    "iso:country":"BE",
    "sg:address":"Herentalsstraat 18",
    "sg:city":"Turnhout",
    "sg:classifiers":[
        {
            "category":"Restaurant",
            "type":"Food & Drink"
        }
    ],
    "sg:phone":"+32 14 41 87 57",
    "sg:postcode":"2300",
    "sg:province":"Antwerpen",
    "wof:name":"Restaurant Ter Driezen",
    "wof:placetype":"venue"
},
  "geometry": {"coordinates":[4.9491801262,51.3215332031],"type":"Point"}
}