{
  "type": "Feature",
  "properties": {
    "iso:country":"BE",
    "sg:address":"K. Albertlaan 134",
    "sg:city":"Gent",
    "sg:orig_category":"R\u00e9parations d'appareils \u00e9lectrom\u00e9nagers. Electrom\u00e9nager, t\u00e9l\u00e9visions and radios. Mat\u00e9riel de T\u00e9l\u00e9com",
    "sg:phone":"+32 9 245 29 31",
    "sg:postcode":"9000",
    "sg:province":"Oost-Vlaanderen",
    "wof:name":"A S T",
    "wof:placetype":"venue"
},
  "geometry": {"coordinates":[3.7285690308,51.0556335449],"type":"Point"}
}