{
  "type": "Feature",
  "properties": {
    "addr:full":"Quai De La Boverie 28 Li\u00c8ge Li\u00e8ge 4020",
    "addr:housenumber":"28",
    "addr:postcode":"4020",
    "addr:street":"Quai De La Boverie",
    "iso:country":"BE",
    "sg:address":"Quai De La Boverie 28",
    "sg:city":"Li\u00c8ge",
    "sg:orig_category":"Sportclubs Sportterreinen and installaties behalve sportcentra",
    "sg:phone":"+32 4 343 83 37",
    "sg:postcode":"4020",
    "sg:province":"Li\u00e8ge",
    "wof:name":"R.f.c. Li\u00c8geois",
    "wof:placetype":"venue"
},
  "geometry": {"coordinates":[5.5770688057,50.6354942322],"type":"Point"}
}