{
  "type": "Feature",
  "properties": {
    "addr:full":"Langemunt 29 Gent Oost-Vlaanderen 9000",
    "addr:housenumber":"29",
    "addr:postcode":"9000",
    "addr:street":"Langemunt;Oost-Vlaanderen",
    "iso:country":"BE",
    "sg:address":"Langemunt 29",
    "sg:city":"Gent",
    "sg:classifiers":[
        {
            "category":"Personal",
            "subcategory":"Beauty Salon",
            "type":"Services"
        }
    ],
    "sg:phone":"+32 9 223 07 66",
    "sg:postcode":"9000",
    "sg:province":"Oost-Vlaanderen",
    "wof:name":"Yves Rocher",
    "wof:placetype":"venue"
},
  "geometry": {"coordinates":[3.7232899666,51.0565223694],"type":"Point"}
}