{
  "type": "Feature",
  "properties": {
    "iso:country":"BE",
    "sg:address":"Albert Giraudlaan 116",
    "sg:city":"Brussel/bruxelles",
    "sg:orig_category":"Aanleg van opritten and terreinen bij woningen Dakwerken Loodgieterij, verwarming and sanitaire inst",
    "sg:phone":"+32 2 759 89 85",
    "sg:postcode":"1030",
    "sg:province":"Bruxelles-Capitale",
    "wof:name":"Francis Entreprise",
    "wof:placetype":"venue"
},
  "geometry": {"coordinates":[4.3818731308,50.8757667542],"type":"Point"}
}