{
  "type": "Feature",
  "properties": {
    "addr:full":"Rue Des Alli\u00e9s 92-94 Bruxelles Bruxelles-Capitale 1190",
    "addr:postcode":"92-94;1190",
    "addr:street":"Rue Des Allie\u0301S",
    "iso:country":"BE",
    "sg:address":"Rue Des Alli\u00e9s 92-94",
    "sg:city":"Bruxelles",
    "sg:orig_category":"Miscellaneous Products",
    "sg:phone":"+32 2 344 44 91",
    "sg:postcode":"1190",
    "sg:province":"Bruxelles-Capitale",
    "wof:name":"Pyrindus Sa",
    "wof:placetype":"venue"
},
  "geometry": {"coordinates":[4.3265538216,50.8170509338],"type":"Point"}
}