{
  "type": "Feature",
  "properties": {
    "addr:full":"Luikersteenweg 159 Hasselt Limburg 3500",
    "addr:housenumber":"159",
    "addr:postcode":"3500",
    "addr:street":"Luikersteenweg",
    "iso:country":"BE",
    "sg:address":"Luikersteenweg 159",
    "sg:city":"Hasselt",
    "sg:orig_category":"Kantoormateriaal Gh",
    "sg:phone":"+32 11 28 14 24",
    "sg:postcode":"3500",
    "sg:province":"Limburg",
    "wof:name":"Algemeen Kasregisterbedrijf",
    "wof:placetype":"venue"
},
  "geometry": {"coordinates":[5.3435587883,50.9196586609],"type":"Point"}
}