{
  "type": "Feature",
  "properties": {
    "iso:country":"BE",
    "sg:address":"Chauss\u00c9e De Wavre 54",
    "sg:city":"Gembloux",
    "sg:orig_category":"Chemicali\u00ebn Gh Schoonmaakbedrijven and ongediertebestrijding",
    "sg:phone":"+32 81 60 07 16",
    "sg:postcode":"5030",
    "sg:province":"Namur",
    "wof:name":"Baxith Dcs",
    "wof:placetype":"venue"
},
  "geometry": {"coordinates":[4.6876511574,50.577796936],"type":"Point"}
}