{
  "type": "Feature",
  "properties": {
    "iso:country":"BE",
    "sg:address":"Rue De La Mande-brat 17",
    "sg:city":"Leglise",
    "sg:orig_category":"Kampeerterreinen",
    "sg:phone":"+32 63 43 32 26",
    "sg:postcode":"6860",
    "sg:province":"Luxembourg",
    "wof:name":"Camping \u00c0 La Ferme",
    "wof:placetype":"venue"
},
  "geometry": {"coordinates":[5.5519971848,49.7822341919],"type":"Point"}
}