{
  "type": "Feature",
  "properties": {
    "iso:country":"BE",
    "sg:address":"Rue De Libin 93",
    "sg:city":"Wellin",
    "sg:orig_category":"H\u00f4tels. Restaurants",
    "sg:phone":"+32 84 38 81 33",
    "sg:postcode":"6922",
    "sg:province":"Luxembourg",
    "wof:name":"H\u00d4tel Le Ry Des Glands",
    "wof:placetype":"venue"
},
  "geometry": {"coordinates":[5.1350479126,50.0764503479],"type":"Point"}
}