{
  "type": "Feature",
  "properties": {
    "iso:country":"BE",
    "sg:address":"Tielendorp 16",
    "sg:city":"Kasterlee (tielen)",
    "sg:classifiers":[
        {
            "category":"Fast Food",
            "type":"Food & Drink"
        }
    ],
    "sg:phone":"+32 14 55 60 95",
    "sg:postcode":"2460",
    "sg:province":"Antwerpen",
    "sg:tags":[
        "fried",
        "stand",
        "potato"
    ],
    "wof:name":"Tielenhof",
    "wof:placetype":"venue"
},
  "geometry": {"coordinates":[4.9671049118,51.2406616211],"type":"Point"}
}