{
  "type": "Feature",
  "properties": {
    "addr:full":"Dijkstraat 6b1 Brecht Antwerpen 2960",
    "addr:housenumber":"6b1",
    "addr:postcode":"2960",
    "addr:street":"Dijkstraat",
    "iso:country":"BE",
    "sg:address":"Dijkstraat 6b1",
    "sg:city":"Brecht",
    "sg:orig_category":"Plaatsen van vloer- and muurbekleding",
    "sg:phone":"+32 3 313 98 13",
    "sg:postcode":"2960",
    "sg:province":"Antwerpen",
    "wof:name":"Tigla",
    "wof:placetype":"venue"
},
  "geometry": {"coordinates":[4.6415200233,51.3512115479],"type":"Point"}
}