{
  "type": "Feature",
  "properties": {
    "addr:full":"Mechelsebaan 240 Duffel Antwerpen 2570",
    "addr:housenumber":"240",
    "addr:postcode":"2570",
    "addr:street":"Mechelsebaan",
    "iso:country":"BE",
    "sg:address":"Mechelsebaan 240",
    "sg:city":"Duffel",
    "sg:orig_category":"Benzinestations and brandstoffen Voertuigen",
    "sg:phone":"+32 15 31 06 73",
    "sg:postcode":"2570",
    "sg:province":"Antwerpen",
    "wof:name":"Q 8",
    "wof:placetype":"venue"
},
  "geometry": {"coordinates":[4.4906182289,51.076877594],"type":"Point"}
}