{
  "type": "Feature",
  "properties": {
    "addr:full":"Tervuursesteenweg 223-225 Leuven Vlaams-Brabant 3001",
    "addr:housenumber":"223-225",
    "addr:postcode":"3001",
    "addr:street":"Tervuursesteenweg",
    "iso:country":"BE",
    "sg:address":"Tervuursesteenweg 223-225",
    "sg:city":"Leuven",
    "sg:orig_category":"Benzinestations and brandstoffen Herstellingen and onderhoud van auto's Onderdelen and accessoires v",
    "sg:phone":"+32 16 20 23 48",
    "sg:postcode":"3001",
    "sg:province":"Vlaams-Brabant",
    "wof:name":"Etn. Pauwels",
    "wof:placetype":"venue"
},
  "geometry": {"coordinates":[4.6744298935,50.8747177124],"type":"Point"}
}