{
  "type": "Feature",
  "properties": {
    "iso:country":"BE",
    "sg:address":"Rue Des Alli\u00e9s 135",
    "sg:city":"Nassogne (forri\u00e8res)",
    "sg:classifiers":[
        {
            "category":"Health Services",
            "subcategory":"Health Practitioner",
            "type":"Services"
        }
    ],
    "sg:phone":"+32 84 21 28 17",
    "sg:postcode":"6953",
    "sg:province":"Luxembourg",
    "sg:tags":[
        "physiotherapist"
    ],
    "wof:name":"Rondeaux Anne-marie",
    "wof:placetype":"venue"
},
  "geometry": {"coordinates":[5.2943620682,50.1362762451],"type":"Point"}
}