{
  "type": "Feature",
  "properties": {
    "addr:full":"Avenue De La Salm 3 Vielsalm Luxembourg 6690",
    "addr:housenumber":"3",
    "addr:postcode":"6690",
    "addr:street":"Avenue De La Salm",
    "iso:country":"BE",
    "sg:address":"Avenue De La Salm 3",
    "sg:city":"Vielsalm",
    "sg:classifiers":[
        {
            "category":"Restaurant",
            "type":"Food & Drink"
        }
    ],
    "sg:phone":"+32 80 21 78 28",
    "sg:postcode":"6690",
    "sg:province":"Luxembourg",
    "wof:name":"Snack-bar La Fringale",
    "wof:placetype":"venue"
},
  "geometry": {"coordinates":[5.91410923,50.2829818726],"type":"Point"}
}