{
  "type": "Feature",
  "properties": {
    "iso:country":"BE",
    "sg:address":"Diksmuidesteenweg 27",
    "sg:city":"Hooglede",
    "sg:classifiers":[
        {
            "category":"Utilities",
            "subcategory":"Natural Gas",
            "type":"Services"
        }
    ],
    "sg:phone":"+32 51 22 12 42",
    "sg:postcode":"8830",
    "sg:province":"West-Vlaanderen",
    "sg:tags":[
        "apiculture",
        "accessory"
    ],
    "wof:name":"Bene-bombus",
    "wof:placetype":"venue"
},
  "geometry": {"coordinates":[3.0706169605,50.9598045349],"type":"Point"}
}