{
  "type": "Feature",
  "properties": {
    "addr:full":"Steentjestraat 103 Laarne Oost-Vlaanderen 9270",
    "addr:housenumber":"103",
    "addr:postcode":"9270",
    "addr:street":"Steentjestraat",
    "iso:country":"BE",
    "sg:address":"Steentjestraat 103",
    "sg:city":"Laarne",
    "sg:classifiers":[
        {
            "category":"Manufacturing",
            "subcategory":"Textiles",
            "type":"Manufacturing & Wholesale Goods"
        }
    ],
    "sg:phone":"+32 9 366 11 79",
    "sg:postcode":"9270",
    "sg:province":"Oost-Vlaanderen",
    "sg:tags":[
        "polyester"
    ],
    "wof:name":"Rooseparck P",
    "wof:placetype":"venue"
},
  "geometry": {"coordinates":[3.8808600903,51.0410614014],"type":"Point"}
}