{
  "type": "Feature",
  "properties": {
    "addr:full":"Rue Bois Renard 589 Theux (la Reid) Li\u00e8ge 4910",
    "addr:housenumber":"589",
    "addr:postcode":"4910",
    "addr:street":"Rue Bois Renard;La Reid",
    "iso:country":"BE",
    "sg:address":"Rue Bois Renard 589",
    "sg:city":"Theux (la Reid)",
    "sg:classifiers":[
        {
            "category":"Social Services",
            "type":"Services"
        }
    ],
    "sg:phone":"+32 87 37 62 96",
    "sg:postcode":"4910",
    "sg:province":"Li\u00e8ge",
    "wof:name":"Cent Voies Asbl",
    "wof:placetype":"venue"
},
  "geometry": {"coordinates":[5.7703499794,50.5011901855],"type":"Point"}
}