{
  "type": "Feature",
  "properties": {
    "addr:full":"Rue Du Parc 4 Modave Li\u00e8ge 4577",
    "addr:housenumber":"4",
    "addr:postcode":"4577",
    "addr:street":"Rue Du Parc",
    "iso:country":"BE",
    "sg:address":"Rue Du Parc 4",
    "sg:city":"Modave",
    "sg:orig_category":"Salles de conf\u00e9rences and de r\u00e9ceptions. Mus\u00e9es and patrimoine culturel",
    "sg:phone":"+32 85 41 13 69",
    "sg:postcode":"4577",
    "sg:province":"Li\u00e8ge",
    "wof:name":"Ch\u00c2teau Des Comtes De Marchin",
    "wof:placetype":"venue"
},
  "geometry": {"coordinates":[5.2886590958,50.4414215088],"type":"Point"}
}