{
  "type": "Feature",
  "properties": {
    "iso:country":"BE",
    "sg:address":"Beemdenstraat 3",
    "sg:city":"Lille",
    "sg:orig_category":"Rundveehouders",
    "sg:phone":"+32 14 55 48 55",
    "sg:postcode":"2275",
    "sg:province":"Antwerpen",
    "wof:name":"Van Dijck & Van Bedts",
    "wof:placetype":"venue"
},
  "geometry": {"coordinates":[4.9036631584,51.2826766968],"type":"Point"}
}