{
  "type": "Feature",
  "properties": {
    "iso:country":"BE",
    "sg:address":"Brasschaatsesteenweg 142",
    "sg:city":"Kalmthout",
    "sg:orig_category":"Herstellingen and onderhoud van auto's",
    "sg:phone":"+32 3 666 29 31",
    "sg:postcode":"2920",
    "sg:province":"Antwerpen",
    "wof:name":"Petrovert",
    "wof:placetype":"venue"
},
  "geometry": {"coordinates":[4.5044131279,51.3810882568],"type":"Point"}
}