{
  "type": "Feature",
  "properties": {
    "addr:full":"Avenue L\u00e9o Errera 41 Bruxelles (uccle) Bruxelles-Capitale 1180",
    "addr:housenumber":"41",
    "addr:postcode":"1180",
    "addr:street":"Avenue Le\u0301O Errera",
    "iso:country":"BE",
    "sg:address":"Avenue L\u00e9o Errera 41",
    "sg:city":"Bruxelles (uccle)",
    "sg:classifiers":[
        {
            "category":"Museum",
            "type":"Entertainment"
        }
    ],
    "sg:phone":"+32 2 343 48 51",
    "sg:postcode":"1180",
    "sg:province":"Bruxelles-Capitale",
    "wof:name":"Mus\u00e9e David & Alice Van Buuren",
    "wof:placetype":"venue"
},
  "geometry": {"coordinates":[4.3539528847,50.8101158142],"type":"Point"}
}