{
  "type": "Feature",
  "properties": {
    "iso:country":"BE",
    "sg:address":"Hoogpoort 8",
    "sg:city":"Gent",
    "sg:classifiers":[
        {
            "category":"Shopping",
            "subcategory":"Crafts & Fabrics",
            "type":"Retail Goods"
        }
    ],
    "sg:phone":"+32 9 233 37 48",
    "sg:postcode":"9000",
    "sg:province":"Oost-Vlaanderen",
    "sg:tags":[
        "silk",
        "-"
    ],
    "wof:name":"Stoffenidee",
    "wof:placetype":"venue"
},
  "geometry": {"coordinates":[3.722645998,51.0555648804],"type":"Point"}
}