{
  "type": "Feature",
  "properties": {
    "addr:full":"Rue Philippe Monnoyer 67 Courcelles Hainaut 6180",
    "addr:housenumber":"67",
    "addr:postcode":"6180",
    "addr:street":"Rue Philippe Monnoyer",
    "iso:country":"BE",
    "sg:address":"Rue Philippe Monnoyer 67",
    "sg:city":"Courcelles",
    "sg:classifiers":[
        {
            "category":"Health Services",
            "subcategory":"Doctor",
            "type":"Services"
        }
    ],
    "sg:phone":"+32 71 45 08 75",
    "sg:postcode":"6180",
    "sg:province":"Hainaut",
    "sg:tags":[
        "medicinephysicians",
        "surgeon"
    ],
    "wof:name":"Marcelle Louis",
    "wof:placetype":"venue"
},
  "geometry": {"coordinates":[4.3757820129,50.4628257751],"type":"Point"}
}