{
  "type": "Feature",
  "properties": {
    "iso:country":"BE",
    "sg:address":"Square Goldschmidt 5",
    "sg:city":"Elsene/ixelles",
    "sg:orig_category":"Avocats and conseillers juridiques",
    "sg:phone":"+32 2 640 42 34",
    "sg:postcode":"1050",
    "sg:province":"Bruxelles-Capitale",
    "wof:name":"Culler D.",
    "wof:placetype":"venue"
},
  "geometry": {"coordinates":[4.3869690895,50.8144378662],"type":"Point"}
}