{
  "type": "Feature",
  "properties": {
    "addr:full":"Rue D'houdeng 27c Le Roeulx Hainaut 7070",
    "addr:housenumber":"27c",
    "addr:postcode":"7070",
    "addr:street":"Rue D'Houdeng",
    "iso:country":"BE",
    "sg:address":"Rue D'houdeng 27c",
    "sg:city":"Le Roeulx",
    "sg:classifiers":[
        {
            "category":"Organizations",
            "subcategory":"Community Association",
            "type":"Services"
        }
    ],
    "sg:phone":"+32 64 66 52 39",
    "sg:postcode":"7070",
    "sg:province":"Hainaut",
    "sg:tags":[
        "cultural"
    ],
    "wof:name":"Faucom J",
    "wof:placetype":"venue"
},
  "geometry": {"coordinates":[4.1120738983,50.5019073486],"type":"Point"}
}