{
  "type": "Feature",
  "properties": {
    "addr:full":"Hoekstraat 26 Anzegem West-Vlaanderen 8570",
    "addr:housenumber":"26",
    "addr:postcode":"8570",
    "addr:street":"Hoekstraat",
    "iso:country":"BE",
    "sg:address":"Hoekstraat 26",
    "sg:city":"Anzegem",
    "sg:orig_category":"Equipement photographique. Studios photographiques",
    "sg:phone":"+32 56 77 79 88",
    "sg:postcode":"8570",
    "sg:province":"West-Vlaanderen",
    "wof:name":"Studio Renaat",
    "wof:placetype":"venue"
},
  "geometry": {"coordinates":[3.4089410305,50.8367347717],"type":"Point"}
}