{
  "type": "Feature",
  "properties": {
    "iso:country":"BE",
    "sg:address":"Frans De Beckstraat 18",
    "sg:city":"Zottegem",
    "sg:orig_category":"Glaszetten and glaswerk Installatie van houten of kunststof schrijnwerk Installatie van metalen schr",
    "sg:phone":"+32 9 360 07 21",
    "sg:postcode":"9620",
    "sg:province":"Oost-Vlaanderen",
    "wof:name":"Soleme Gebrs",
    "wof:placetype":"venue"
},
  "geometry": {"coordinates":[3.8125760555,50.8662490845],"type":"Point"}
}