{
  "type": "Feature",
  "properties": {
    "addr:full":"Rue De Marcinelle 215 Charleroi Hainaut 6032",
    "addr:housenumber":"215",
    "addr:postcode":"6032",
    "addr:street":"Rue De Marcinelle;Hainaut",
    "iso:country":"BE",
    "sg:address":"Rue De Marcinelle 215",
    "sg:city":"Charleroi",
    "sg:orig_category":"M\u00e9decins and sp\u00e9cialistes",
    "sg:phone":"+32 71 36 15 65",
    "sg:postcode":"6032",
    "sg:province":"Hainaut",
    "wof:name":"R. Lejeune",
    "wof:placetype":"venue"
},
  "geometry": {"coordinates":[4.4075870514,50.3705596924],"type":"Point"}
}