{
  "type": "Feature",
  "properties": {
    "iso:country":"BE",
    "sg:address":"Hauwaart 48",
    "sg:city":"Oudenaarde (mater)",
    "sg:classifiers":[
        {
            "category":"Professional",
            "subcategory":"Management & Consulting",
            "type":"Services"
        }
    ],
    "sg:phone":"+32 55 45 54 14",
    "sg:postcode":"9700",
    "sg:province":"Oost-Vlaanderen",
    "sg:tags":[
        "consultant"
    ],
    "wof:name":"Temtec Bvba",
    "wof:placetype":"venue"
},
  "geometry": {"coordinates":[3.6672968864,50.8311691284],"type":"Point"}
}