{
  "type": "Feature",
  "properties": {
    "addr:full":"Hoevelei 27 Aartselaar Antwerpen 2630",
    "addr:housenumber":"27",
    "addr:postcode":"2630",
    "addr:street":"Hoevelei",
    "iso:country":"BE",
    "sg:address":"Hoevelei 27",
    "sg:city":"Aartselaar",
    "sg:classifiers":[
        {
            "category":"Autos & Motor Vehicles",
            "subcategory":"Automobile Sales",
            "type":"Retail Goods"
        }
    ],
    "sg:phone":"+32 3 887 43 12",
    "sg:postcode":"2630",
    "sg:province":"Antwerpen",
    "sg:tags":[
        "car",
        "used",
        "-"
    ],
    "wof:name":"Van De Cruys",
    "wof:placetype":"venue"
},
  "geometry": {"coordinates":[4.3868708611,51.1353416443],"type":"Point"}
}