{
  "type": "Feature",
  "properties": {
    "addr:full":"Rue D'oignies 224 Aiseau-presles Hainaut 6250",
    "addr:housenumber":"224",
    "addr:postcode":"6250",
    "addr:street":"Rue D'Oignies;Hainaut",
    "iso:country":"BE",
    "sg:address":"Rue D'oignies 224",
    "sg:city":"Aiseau-presles",
    "sg:orig_category":"Quincailleries",
    "sg:phone":"+32 71 77 14 03",
    "sg:postcode":"6250",
    "sg:province":"Hainaut",
    "wof:name":"Maison Vandelois",
    "wof:placetype":"venue"
},
  "geometry": {"coordinates":[4.6131420135,50.4296455383],"type":"Point"}
}