{
  "type": "Feature",
  "properties": {
    "addr:full":"Verbindingsstraat 6 Alken Limburg 3570",
    "addr:housenumber":"6",
    "addr:postcode":"3570",
    "addr:street":"Verbindingsstraat",
    "iso:country":"BE",
    "sg:address":"Verbindingsstraat 6",
    "sg:city":"Alken",
    "sg:classifiers":[
        {
            "category":"Building & Trades",
            "subcategory":"Pest Control",
            "type":"Services"
        }
    ],
    "sg:phone":"+32 496 86 96 88",
    "sg:postcode":"3570",
    "sg:province":"Limburg",
    "sg:tags":[
        "painting",
        "contractor"
    ],
    "wof:name":"Vt",
    "wof:placetype":"venue"
},
  "geometry": {"coordinates":[5.2763290405,50.8721160889],"type":"Point"}
}