{
  "type": "Feature",
  "properties": {
    "addr:full":"Guillaume De Greeflaan 9b9 Jette Bruxelles-Capitale 1090",
    "addr:housenumber":"9b9",
    "addr:postcode":"1090",
    "addr:street":"Guillaume De Greeflaan",
    "iso:country":"BE",
    "sg:address":"Guillaume De Greeflaan 9b9",
    "sg:city":"Jette",
    "sg:orig_category":"Artsen and specialisten",
    "sg:phone":"+32 495 50 59 25",
    "sg:postcode":"1090",
    "sg:province":"Bruxelles-Capitale",
    "wof:name":"M. Hoffmans",
    "wof:placetype":"venue"
},
  "geometry": {"coordinates":[4.3355998993,50.8832321167],"type":"Point"}
}