{
  "type": "Feature",
  "properties": {
    "iso:country":"BE",
    "sg:address":"All\u00c9e D'espagne 16",
    "sg:city":"Vise",
    "sg:orig_category":"Herstelling leer and schoeisel",
    "sg:phone":"+32 4 379 78 17",
    "sg:postcode":"4600",
    "sg:province":"Li\u00e8ge",
    "wof:name":"Vaessen Et Cie",
    "wof:placetype":"venue"
},
  "geometry": {"coordinates":[5.7050209045,50.7404632568],"type":"Point"}
}