{
  "type": "Feature",
  "properties": {
    "iso:country":"BE",
    "sg:address":"Rue Victor Libert 48",
    "sg:city":"Marche-en-famenne",
    "sg:orig_category":"Sportclubs",
    "sg:phone":"+32 84 32 00 91",
    "sg:postcode":"6900",
    "sg:province":"Luxembourg",
    "wof:name":"C.comm.nat.marche-en-fam.",
    "wof:placetype":"venue"
},
  "geometry": {"coordinates":[5.3334369659,50.2290687561],"type":"Point"}
}