{
  "type": "Feature",
  "properties": {
    "iso:country":"BE",
    "sg:address":"Place Xhov\u00c9mont 20",
    "sg:city":"Verviers",
    "sg:orig_category":"Woningbouw",
    "sg:phone":"+32 87 31 73 79",
    "sg:postcode":"4800",
    "sg:province":"Li\u00e8ge",
    "wof:name":"Vincent Nanson",
    "wof:placetype":"venue"
},
  "geometry": {"coordinates":[5.8594508171,50.5917663574],"type":"Point"}
}