{
  "type": "Feature",
  "properties": {
    "iso:country":"BE",
    "sg:address":"Staatsbaan",
    "sg:city":"Zulte",
    "sg:classifiers":[
        {
            "category":"Bakery",
            "type":"Food & Drink"
        }
    ],
    "sg:phone":"+32 9 388 79 04",
    "sg:postcode":"9870",
    "sg:province":"Oost-Vlaanderen",
    "sg:tags":[
        "confectioner",
        "baker"
    ],
    "wof:name":"De Strohalm",
    "wof:placetype":"venue"
},
  "geometry": {"coordinates":[3.4455199242,50.9228057861],"type":"Point"}
}