{
  "type": "Feature",
  "properties": {
    "iso:country":"BE",
    "sg:address":"Brugstraat 20b3",
    "sg:city":"Geraardsbergen",
    "sg:orig_category":"Avocats and conseillers juridiques",
    "sg:phone":"+32 54 41 48 32",
    "sg:postcode":"9500",
    "sg:province":"Oost-Vlaanderen",
    "wof:name":"A. Van Den Bossche",
    "wof:placetype":"venue"
},
  "geometry": {"coordinates":[3.8812770844,50.7713241577],"type":"Point"}
}