{
  "type": "Feature",
  "properties": {
    "iso:country":"BE",
    "sg:address":"Rue Du Commerce 20",
    "sg:city":"Bruxelles",
    "sg:classifiers":[
        {
            "category":"Professional",
            "subcategory":"Employment Agencies",
            "type":"Services"
        }
    ],
    "sg:phone":"+32 2 512 38 23",
    "sg:postcode":"1000",
    "sg:province":"Bruxelles-Capitale",
    "sg:tags":[
        "temping",
        "clerical",
        "-"
    ],
    "wof:name":"Manpower Office People",
    "wof:placetype":"venue"
},
  "geometry": {"coordinates":[4.3672199249,50.8400840759],"type":"Point"}
}