{
  "type": "Feature",
  "properties": {
    "iso:country":"BE",
    "sg:address":"Stationsstraat 5",
    "sg:city":"Bornem",
    "sg:orig_category":"Medische and orthopedische apparaten Opticiens",
    "sg:phone":"+32 3 889 00 82",
    "sg:postcode":"2880",
    "sg:province":"Antwerpen",
    "wof:name":"Europtica",
    "wof:placetype":"venue"
},
  "geometry": {"coordinates":[4.2403259277,51.0996894836],"type":"Point"}
}