{
  "type": "Feature",
  "properties": {
    "iso:country":"BE",
    "sg:address":"Rue Victor Horta 55",
    "sg:city":"Ottignies-louvain-la-neuve",
    "sg:orig_category":"Architectes",
    "sg:phone":"+32 10 45 38 66",
    "sg:postcode":"1348",
    "sg:province":"Brabant Wallon",
    "wof:name":"Patrick Monteyne",
    "wof:placetype":"venue"
},
  "geometry": {"coordinates":[4.6068887711,50.6637687683],"type":"Point"}
}