{
  "type": "Feature",
  "properties": {
    "iso:country":"BE",
    "sg:address":"Oostvaartdijk 77",
    "sg:city":"Grimbergen",
    "sg:classifiers":[
        {
            "category":"Freight",
            "type":"Transportation"
        }
    ],
    "sg:phone":"+32 2 252 09 50",
    "sg:postcode":"1850",
    "sg:province":"Vlaams-Brabant",
    "sg:tags":[
        "-",
        "transport"
    ],
    "wof:name":"A D Etn Bvba",
    "wof:placetype":"venue"
},
  "geometry": {"coordinates":[4.4078497887,50.9575881958],"type":"Point"}
}