{
  "type": "Feature",
  "properties": {
    "addr:full":"Rue De Tournai 1 Pecq Hainaut 7740",
    "addr:housenumber":"1",
    "addr:postcode":"7740",
    "addr:street":"Rue De Tournai",
    "iso:country":"BE",
    "sg:address":"Rue De Tournai 1",
    "sg:city":"Pecq",
    "sg:classifiers":[
        {
            "category":"Cafe",
            "type":"Food & Drink"
        }
    ],
    "sg:phone":"+32 69 55 77 85",
    "sg:postcode":"7740",
    "sg:province":"Hainaut",
    "sg:tags":[
        "caf\u00e9s"
    ],
    "wof:name":"Caf\u00c9 Jean Mich'",
    "wof:placetype":"venue"
},
  "geometry": {"coordinates":[3.3386390209,50.6854286194],"type":"Point"}
}