{
  "type": "Feature",
  "properties": {
    "iso:country":"BE",
    "sg:address":"Bloemstraat 40",
    "sg:city":"Gent",
    "sg:classifiers":[
        {
            "category":"Personal",
            "subcategory":"Beauty Salon",
            "type":"Services"
        }
    ],
    "sg:phone":"+32 9 232 09 32",
    "sg:postcode":"9050",
    "sg:province":"Oost-Vlaanderen",
    "sg:tags":[
        "de",
        "coiffure"
    ],
    "wof:name":"Hair Fashion Kathy",
    "wof:placetype":"venue"
},
  "geometry": {"coordinates":[3.7628440857,51.019077301],"type":"Point"}
}