{
  "type": "Feature",
  "properties": {
    "addr:full":"Avenue De La Chasse 159 Etterbeek Bruxelles-Capitale 1040",
    "addr:housenumber":"159",
    "addr:postcode":"1040",
    "addr:street":"Avenue De La Chasse",
    "iso:country":"BE",
    "sg:address":"Avenue De La Chasse 159",
    "sg:city":"Etterbeek",
    "sg:orig_category":"Electrom\u00e9nager, t\u00e9l\u00e9visions and radios",
    "sg:phone":"+32 2 733 55 01",
    "sg:postcode":"1040",
    "sg:province":"Bruxelles-Capitale",
    "wof:name":"Audio 2000",
    "wof:placetype":"venue"
},
  "geometry": {"coordinates":[4.3936309814,50.8345718384],"type":"Point"}
}