{
  "type": "Feature",
  "properties": {
    "iso:country":"BE",
    "sg:address":"Kruisveldstraat 29",
    "sg:city":"Mechelen",
    "sg:orig_category":"Dakwerken Loodgieterij, verwarming and sanitaire installaties",
    "sg:phone":"+32 15 42 03 10",
    "sg:postcode":"2800",
    "sg:province":"Antwerpen",
    "wof:name":"Rudeco",
    "wof:placetype":"venue"
},
  "geometry": {"coordinates":[4.4848737717,51.0125007629],"type":"Point"}
}