{
  "type": "Feature",
  "properties": {
    "iso:country":"BE",
    "sg:address":"Blasiusstraat 24bb",
    "sg:city":"Poperinge",
    "sg:orig_category":"Instituts de beaut\u00e9",
    "sg:phone":"+32 57 40 00 11",
    "sg:postcode":"8972",
    "sg:province":"West-Vlaanderen",
    "wof:name":"Patrick Deschrevel",
    "wof:placetype":"venue"
},
  "geometry": {"coordinates":[2.6847200394,50.9132614136],"type":"Point"}
}