{
  "type": "Feature",
  "properties": {
    "addr:full":"Avenue Houba De Strooper 748 Bruxelles Bruxelles-Capitale 1020",
    "addr:housenumber":"748",
    "addr:postcode":"1020",
    "addr:street":"Avenue Houba De Strooper",
    "iso:country":"BE",
    "sg:address":"Avenue Houba De Strooper 748",
    "sg:city":"Bruxelles",
    "sg:classifiers":[
        {
            "category":"Real Estate",
            "subcategory":"Real Estate Services",
            "type":"Services"
        }
    ],
    "sg:phone":"+32 2 478 77 07",
    "sg:postcode":"1020",
    "sg:province":"Bruxelles-Capitale",
    "wof:name":"Fastigon Bvba-sprl",
    "wof:placetype":"venue"
},
  "geometry": {"coordinates":[4.3269300461,50.897567749],"type":"Point"}
}