{
  "type": "Feature",
  "properties": {
    "addr:full":"Rue St-donat 8 Nassogne Luxembourg 6950",
    "addr:housenumber":"8",
    "addr:postcode":"6950",
    "addr:street":"Rue St-Donat",
    "iso:country":"BE",
    "sg:address":"Rue St-donat 8",
    "sg:city":"Nassogne",
    "sg:orig_category":"Installation de menuiserie en bois and plastique",
    "sg:phone":"+32 84 34 44 47",
    "sg:postcode":"6950",
    "sg:province":"Luxembourg",
    "wof:name":"Labbe M",
    "wof:placetype":"venue"
},
  "geometry": {"coordinates":[5.3412861824,50.1745529175],"type":"Point"}
}