{
  "type": "Feature",
  "properties": {
    "addr:full":"Zonnestraat 2d Ronse Oost-Vlaanderen 9600",
    "addr:housenumber":"2d",
    "addr:postcode":"9600",
    "addr:street":"Zonnestraat",
    "iso:country":"BE",
    "sg:address":"Zonnestraat 2d",
    "sg:city":"Ronse",
    "sg:orig_category":"Huisdieren and benodigdheden Royal Canin",
    "sg:phone":"+32 55 20 79 62",
    "sg:postcode":"9600",
    "sg:province":"Oost-Vlaanderen",
    "wof:name":"Tom & Co",
    "wof:placetype":"venue"
},
  "geometry": {"coordinates":[3.5963509083,50.7501106262],"type":"Point"}
}