{
  "type": "Feature",
  "properties": {
    "addr:full":"Zeelaan 120 De Panne West-Vlaanderen 8660",
    "addr:housenumber":"120",
    "addr:postcode":"8660",
    "addr:street":"Zeelaan",
    "iso:country":"BE",
    "sg:address":"Zeelaan 120",
    "sg:city":"De Panne",
    "sg:classifiers":[
        {
            "category":"Shopping",
            "subcategory":"Jewelry",
            "type":"Retail Goods"
        }
    ],
    "sg:phone":"+32 58 41 32 04",
    "sg:postcode":"8660",
    "sg:province":"West-Vlaanderen",
    "sg:tags":[
        "jeweller",
        "-"
    ],
    "wof:name":"Playa De Oro",
    "wof:placetype":"venue"
},
  "geometry": {"coordinates":[2.5924921036,51.1001663208],"type":"Point"}
}