{
  "type": "Feature",
  "properties": {
    "addr:full":"Zamanstraat 49 Sint-niklaas Oost-Vlaanderen 9100",
    "addr:housenumber":"49",
    "addr:postcode":"9100",
    "addr:street":"Zamanstraat",
    "iso:country":"BE",
    "sg:address":"Zamanstraat 49",
    "sg:city":"Sint-niklaas",
    "sg:orig_category":"Mus\u00e9es and patrimoine culturel",
    "sg:phone":"+32 3 777 29 42",
    "sg:postcode":"9100",
    "sg:province":"Oost-Vlaanderen",
    "wof:name":"Mercatormuseum",
    "wof:placetype":"venue"
},
  "geometry": {"coordinates":[4.1448040009,51.1674194336],"type":"Point"}
}