{
  "type": "Feature",
  "properties": {
    "iso:country":"BE",
    "sg:address":"Rue De Neufch\u00c2teau 132",
    "sg:city":"Arlon",
    "sg:orig_category":"Openbare veiligheid",
    "sg:phone":"+32 63 21 43 98",
    "sg:postcode":"6700",
    "sg:province":"Luxembourg",
    "wof:name":"Police F\u00c9d\u00c9rale/federale Politie",
    "wof:placetype":"venue"
},
  "geometry": {"coordinates":[5.8025097847,49.6856803894],"type":"Point"}
}