{
  "type": "Feature",
  "properties": {
    "addr:full":"Oude Heirweg 3 Lichtervelde West-Vlaanderen 8810",
    "addr:housenumber":"3",
    "addr:postcode":"8810",
    "addr:street":"Oude Heirweg",
    "iso:country":"BE",
    "sg:address":"Oude Heirweg 3",
    "sg:city":"Lichtervelde",
    "sg:classifiers":[
        {
            "category":"Farming",
            "subcategory":"Farm & Veterinary Services",
            "type":"Manufacturing & Wholesale Goods"
        }
    ],
    "sg:phone":"+32 51 61 23 36",
    "sg:postcode":"8810",
    "sg:province":"West-Vlaanderen",
    "sg:tags":[
        "agricultural",
        "contractor"
    ],
    "wof:name":"Duva Nv",
    "wof:placetype":"venue"
},
  "geometry": {"coordinates":[3.1775569916,51.0080566406],"type":"Point"}
}