{
  "type": "Feature",
  "properties": {
    "iso:country":"BE",
    "sg:address":"Herentalseweg 54",
    "sg:city":"Geel",
    "sg:classifiers":[
        {
            "category":"Shopping",
            "subcategory":"Bicycles & Sporting Goods",
            "type":"Retail Goods"
        }
    ],
    "sg:phone":"+32 14 58 21 45",
    "sg:postcode":"2440",
    "sg:province":"Antwerpen",
    "sg:tags":[
        "sport",
        "-"
    ],
    "wof:name":"Lornoy Sport",
    "wof:placetype":"venue"
},
  "geometry": {"coordinates":[4.9272990227,51.1812934875],"type":"Point"}
}