{
  "type": "Feature",
  "properties": {
    "iso:country":"BE",
    "sg:address":"Place Au Foire 26",
    "sg:city":"Durbuy",
    "sg:orig_category":"H\u00f4tels. Restaurants",
    "sg:phone":"+32 86 21 28 08",
    "sg:postcode":"6940",
    "sg:province":"Luxembourg",
    "wof:name":"H\u00d4tel Du Vieux Pont",
    "wof:placetype":"venue"
},
  "geometry": {"coordinates":[5.4560241699,50.3518676758],"type":"Point"}
}