{
  "type": "Feature",
  "properties": {
    "addr:full":"Hufengasse 53 Eupen/eupen Li\u00e8ge 4700",
    "addr:housenumber":"53",
    "addr:postcode":"4700",
    "addr:street":"Hufengasse",
    "iso:country":"BE",
    "sg:address":"Hufengasse 53",
    "sg:city":"Eupen/eupen",
    "sg:orig_category":"Services fun\u00e9raires",
    "sg:phone":"+32 87 55 35 67",
    "sg:postcode":"4700",
    "sg:province":"Li\u00e8ge",
    "wof:name":"Danielle Karls",
    "wof:placetype":"venue"
},
  "geometry": {"coordinates":[6.0287032127,50.6289901733],"type":"Point"}
}