{
  "type": "Feature",
  "properties": {
    "addr:full":"Vredestraat 3 Niel Antwerpen 2845",
    "addr:housenumber":"3",
    "addr:postcode":"2845",
    "addr:street":"Vredestraat",
    "iso:country":"BE",
    "sg:address":"Vredestraat 3",
    "sg:city":"Niel",
    "sg:orig_category":"Peinture. Rev\u00eatements pour sols and murs",
    "sg:phone":"+32 3 888 65 57",
    "sg:postcode":"2845",
    "sg:province":"Antwerpen",
    "wof:name":"Paul Van Der Velde",
    "wof:placetype":"venue"
},
  "geometry": {"coordinates":[4.3278250694,51.112159729],"type":"Point"}
}