{
  "type": "Feature",
  "properties": {
    "addr:full":"4250 Geer (groot) Li\u00e8ge 4250",
    "addr:housenumber":"4250",
    "addr:postcode":"4250",
    "addr:street":"Geer Groot Lie\u0300Ge",
    "iso:country":"BE",
    "sg:address":"4250",
    "sg:city":"Geer (groot)",
    "sg:orig_category":"Pharmaciens",
    "sg:phone":"+32 900 10 500",
    "sg:postcode":"4250",
    "sg:province":"Li\u00e8ge",
    "wof:name":"Pharmacies De Garde",
    "wof:placetype":"venue"
},
  "geometry": {"coordinates":[5.1836800575,50.6721000671],"type":"Point"}
}