{
  "type": "Feature",
  "properties": {
    "addr:full":"Rue Du Village 2a Beauvechain Brabant Wallon 1320",
    "addr:housenumber":"2a",
    "addr:postcode":"1320",
    "addr:street":"Rue Du Village",
    "iso:country":"BE",
    "sg:address":"Rue Du Village 2a",
    "sg:city":"Beauvechain",
    "sg:orig_category":"Fournitures de bureau. Librairies. Tabac. Journaux",
    "sg:phone":"+32 10 86 16 88",
    "sg:postcode":"1320",
    "sg:province":"Brabant Wallon",
    "wof:name":"Librairie Le Point Virgule",
    "wof:placetype":"venue"
},
  "geometry": {"coordinates":[4.7761731148,50.7820358276],"type":"Point"}
}