{
  "type": "Feature",
  "properties": {
    "iso:country":"BE",
    "sg:address":"Antwerpsesteenweg 386",
    "sg:city":"Gent",
    "sg:orig_category":"Industri\u00eble wasserijen and droogkuis",
    "sg:phone":"+32 9 228 90 54",
    "sg:postcode":"9040",
    "sg:province":"Oost-Vlaanderen",
    "wof:name":"Pressing 2000",
    "wof:placetype":"venue"
},
  "geometry": {"coordinates":[3.7495861053,51.0618667603],"type":"Point"}
}