{
  "type": "Feature",
  "properties": {
    "addr:full":"Amersveldestraat 199a Kortemark West-Vlaanderen 8610",
    "addr:housenumber":"199a",
    "addr:postcode":"8610",
    "addr:street":"Amersveldestraat",
    "iso:country":"BE",
    "sg:address":"Amersveldestraat 199a",
    "sg:city":"Kortemark",
    "sg:classifiers":[
        {
            "category":"Education",
            "subcategory":"Dance Studio",
            "type":"Public Place"
        }
    ],
    "sg:phone":"+32 51 56 93 44",
    "sg:postcode":"8610",
    "sg:province":"West-Vlaanderen",
    "sg:tags":[
        "pallet"
    ],
    "wof:name":"Wihopal",
    "wof:placetype":"venue"
},
  "geometry": {"coordinates":[3.0157899857,51.0112915039],"type":"Point"}
}