{
  "type": "Feature",
  "properties": {
    "addr:full":"Weeldestraat 83 Ravels Antwerpen 2381",
    "addr:housenumber":"83",
    "addr:postcode":"2381",
    "addr:street":"Weeldestraat",
    "iso:country":"BE",
    "sg:address":"Weeldestraat 83",
    "sg:city":"Ravels",
    "sg:orig_category":"Schoenen",
    "sg:phone":"+32 14 65 56 46",
    "sg:postcode":"2381",
    "sg:province":"Antwerpen",
    "wof:name":"Ramo",
    "wof:placetype":"venue"
},
  "geometry": {"coordinates":[5.006374836,51.4099845886],"type":"Point"}
}