{
  "type": "Feature",
  "properties": {
    "addr:full":"Paleisstraat 39 Antwerpen Antwerpen 2018",
    "addr:housenumber":"39",
    "addr:postcode":"2018",
    "addr:street":"Paleisstraat",
    "iso:country":"BE",
    "sg:address":"Paleisstraat 39",
    "sg:city":"Antwerpen",
    "sg:classifiers":[
        {
            "category":"Social Services",
            "type":"Services"
        }
    ],
    "sg:phone":"+32 3 238 16 93",
    "sg:postcode":"2018",
    "sg:province":"Antwerpen",
    "wof:name":"Y.w.c.a.",
    "wof:placetype":"venue"
},
  "geometry": {"coordinates":[4.400988102,51.2070884705],"type":"Point"}
}