{
  "type": "Feature",
  "properties": {
    "iso:country":"BE",
    "sg:address":"Engelstraat 98",
    "sg:city":"Ichtegem",
    "sg:classifiers":[
        {
            "category":"Personal",
            "subcategory":"Beauty Salon",
            "type":"Services"
        }
    ],
    "sg:phone":"+32 51 58 11 64",
    "sg:postcode":"8480",
    "sg:province":"West-Vlaanderen",
    "sg:tags":[
        "lady",
        "-",
        "hairdressing"
    ],
    "wof:name":"Luc",
    "wof:placetype":"venue"
},
  "geometry": {"coordinates":[3.0205130577,51.0954360962],"type":"Point"}
}