{
  "type": "Feature",
  "properties": {
    "addr:full":"Westvleterendorp 58 Vleteren West-Vlaanderen 8640",
    "addr:housenumber":"58",
    "addr:postcode":"8640",
    "addr:street":"Westvleterendorp",
    "iso:country":"BE",
    "sg:address":"Westvleterendorp 58",
    "sg:city":"Vleteren",
    "sg:orig_category":"G\u00e9om\u00e8tres",
    "sg:phone":"+32 57 40 08 15",
    "sg:postcode":"8640",
    "sg:province":"West-Vlaanderen",
    "wof:name":"Martin Ryckebosch",
    "wof:placetype":"venue"
},
  "geometry": {"coordinates":[2.720635891,50.9235038757],"type":"Point"}
}