{
  "type": "Feature",
  "properties": {
    "iso:country":"BE",
    "sg:address":"Rue L\u00c9opold 5b1",
    "sg:city":"Welkenraedt",
    "sg:orig_category":"Dakwerken Loodgieterij, verwarming and sanitaire installaties",
    "sg:phone":"+32 87 88 39 70",
    "sg:postcode":"4840",
    "sg:province":"Li\u00e8ge",
    "wof:name":"Mahin Fr\u00c8res",
    "wof:placetype":"venue"
},
  "geometry": {"coordinates":[5.9749760628,50.6618766785],"type":"Point"}
}