{
  "type": "Feature",
  "properties": {
    "addr:full":"Treurnietstraat 8 Harelbeke West-Vlaanderen 8531",
    "addr:housenumber":"8",
    "addr:postcode":"8531",
    "addr:street":"Treurnietstraat",
    "iso:country":"BE",
    "sg:address":"Treurnietstraat 8",
    "sg:city":"Harelbeke",
    "sg:orig_category":"Peinture. Rev\u00eatements pour sols and murs",
    "sg:phone":"+32 56 71 97 44",
    "sg:postcode":"8531",
    "sg:province":"West-Vlaanderen",
    "wof:name":"Schilderwerken Maes",
    "wof:placetype":"venue"
},
  "geometry": {"coordinates":[3.3151769638,50.8835601807],"type":"Point"}
}