{
  "type": "Feature",
  "properties": {
    "addr:full":"Avenue Du Beau Site 31 Braine-l\u00b4alleud Brabant Wallon 1420",
    "addr:housenumber":"31",
    "addr:postcode":"1420",
    "addr:street":"Avenue Du Beau Site;Brabant Wallon",
    "iso:country":"BE",
    "sg:address":"Avenue Du Beau Site 31",
    "sg:city":"Braine-l\u00b4alleud",
    "sg:orig_category":"Public-relationsbureaus",
    "sg:phone":"+32 2 354 57 51",
    "sg:postcode":"1420",
    "sg:province":"Brabant Wallon",
    "wof:name":"Go Mi Ka Conception",
    "wof:placetype":"venue"
},
  "geometry": {"coordinates":[4.334376812,50.7323684692],"type":"Point"}
}