{
  "type": "Feature",
  "properties": {
    "addr:full":"Vis\u00c9laan 28 Watermael-boitsfort Bruxelles-Capitale 1170",
    "addr:housenumber":"28",
    "addr:postcode":"1170",
    "addr:street":"Vise\u0301Laan",
    "iso:country":"BE",
    "sg:address":"Vis\u00c9laan 28",
    "sg:city":"Watermael-boitsfort",
    "sg:classifiers":[
        {
            "category":"Restaurant",
            "type":"Food & Drink"
        }
    ],
    "sg:phone":"+32 2 672 76 45",
    "sg:postcode":"1170",
    "sg:province":"Bruxelles-Capitale",
    "wof:name":"Il Nabucco",
    "wof:placetype":"venue"
},
  "geometry": {"coordinates":[4.3973560333,50.810092926],"type":"Point"}
}