{
  "type": "Feature",
  "properties": {
    "iso:country":"BE",
    "sg:address":"Reyndersstraat 33",
    "sg:city":"Antwerpen",
    "sg:classifiers":[
        {
            "category":"Bars & Pubs",
            "type":"Food & Drink"
        }
    ],
    "sg:phone":"+32 3 232 21 57",
    "sg:postcode":"2000",
    "sg:province":"Antwerpen",
    "wof:name":"Herk (de)",
    "wof:placetype":"venue"
},
  "geometry": {"coordinates":[4.3994021416,51.2191162109],"type":"Point"}
}