{
  "type": "Feature",
  "properties": {
    "iso:country":"BE",
    "sg:address":"Weiveldlaan 41b 34",
    "sg:city":"Zaventem",
    "sg:classifiers":[
        {
            "category":"Professional",
            "subcategory":"Computer Services",
            "type":"Services"
        }
    ],
    "sg:phone":"+32 2 716 81 68",
    "sg:postcode":"1930",
    "sg:province":"Vlaams-Brabant",
    "sg:tags":[
        "informatics",
        "consulting"
    ],
    "wof:name":"T-services Nv",
    "wof:placetype":"venue"
},
  "geometry": {"coordinates":[4.4947600365,50.8697090149],"type":"Point"}
}