{
  "type": "Feature",
  "properties": {
    "iso:country":"BE",
    "sg:address":"Drapstraat 81",
    "sg:city":"Hamme",
    "sg:orig_category":"Schoenen Verzekeringsmakelaars and experts",
    "sg:phone":"+32 52 47 10 37",
    "sg:postcode":"9220",
    "sg:province":"Oost-Vlaanderen",
    "wof:name":"Schoonvliet Zakenkantoor",
    "wof:placetype":"venue"
},
  "geometry": {"coordinates":[4.1431469917,51.1000213623],"type":"Point"}
}