{
  "type": "Feature",
  "properties": {
    "iso:country":"BE",
    "sg:address":"Rue De Farciennes 2",
    "sg:city":"Aiseau-presles (roselies)",
    "sg:classifiers":[
        {
            "category":"Shopping",
            "subcategory":"Books",
            "type":"Retail Goods"
        }
    ],
    "sg:phone":"+32 71 76 11 31",
    "sg:postcode":"6250",
    "sg:province":"Hainaut",
    "sg:tags":[
        "bookseller"
    ],
    "wof:name":"Au Coin D'angels",
    "wof:placetype":"venue"
},
  "geometry": {"coordinates":[4.5711078644,50.4262466431],"type":"Point"}
}