{
  "type": "Feature",
  "properties": {
    "iso:country":"BE",
    "sg:address":"Alfred Nichelsstraat 10-12",
    "sg:city":"Aalst",
    "sg:classifiers":[
        {
            "category":"Shopping",
            "subcategory":"Computers & Home Electronics",
            "type":"Retail Goods"
        }
    ],
    "sg:phone":"+32 53 70 15 86",
    "sg:postcode":"9300",
    "sg:province":"Oost-Vlaanderen",
    "sg:tags":[
        "-",
        "television",
        "radio"
    ],
    "wof:name":"Bang & Olufsen-altronik",
    "wof:placetype":"venue"
},
  "geometry": {"coordinates":[4.0451221466,50.9350128174],"type":"Point"}
}