{
  "type": "Feature",
  "properties": {
    "iso:country":"BE",
    "sg:address":"Antwerpsesteenweg 184",
    "sg:city":"Gent",
    "sg:orig_category":"Location d'articles de sport, de sport nautique and de camping. V\u00e9los",
    "sg:phone":"+32 9 238 22 51",
    "sg:postcode":"9040",
    "sg:province":"Oost-Vlaanderen",
    "wof:name":"Moving Store",
    "wof:placetype":"venue"
},
  "geometry": {"coordinates":[3.7459750175,51.0593490601],"type":"Point"}
}