{
  "type": "Feature",
  "properties": {
    "addr:full":"Chauss\u00e9e D'enghien 52 Soignies Hainaut 7060",
    "addr:housenumber":"52",
    "addr:postcode":"7060",
    "addr:street":"Chausse\u0301E D'Enghien",
    "iso:country":"BE",
    "sg:address":"Chauss\u00e9e D'enghien 52",
    "sg:city":"Soignies",
    "sg:classifiers":[
        {
            "category":"Health Services",
            "subcategory":"Dentist",
            "type":"Services"
        }
    ],
    "sg:phone":"+32 67 33 63 14",
    "sg:postcode":"7060",
    "sg:province":"Hainaut",
    "wof:name":"Cock P",
    "wof:placetype":"venue"
},
  "geometry": {"coordinates":[4.0663437843,50.583278656],"type":"Point"}
}