{
  "type": "Feature",
  "properties": {
    "iso:country":"BE",
    "sg:address":"Rue Baillet Latour 52",
    "sg:city":"Virton",
    "sg:classifiers":[
        {
            "category":"Arena",
            "subcategory":"Sports Club",
            "type":"Entertainment"
        }
    ],
    "sg:phone":"+32 63 57 01 15",
    "sg:postcode":"6761",
    "sg:province":"Luxembourg",
    "sg:tags":[
        "de"
    ],
    "wof:name":"La Boule F\u00c9odale",
    "wof:placetype":"venue"
},
  "geometry": {"coordinates":[5.5809650421,49.5557098389],"type":"Point"}
}