{
  "type": "Feature",
  "properties": {
    "addr:full":"Leliestraat 49 Hove Antwerpen 2540",
    "addr:housenumber":"49",
    "addr:postcode":"2540",
    "addr:street":"Leliestraat",
    "iso:country":"BE",
    "sg:address":"Leliestraat 49",
    "sg:city":"Hove",
    "sg:classifiers":[
        {
            "category":"Health Services",
            "subcategory":"Dentist",
            "type":"Services"
        }
    ],
    "sg:phone":"+32 3 455 48 22",
    "sg:postcode":"2540",
    "sg:province":"Antwerpen",
    "wof:name":"Heeren L",
    "wof:placetype":"venue"
},
  "geometry": {"coordinates":[4.4652490616,51.1570549011],"type":"Point"}
}