{
  "type": "Feature",
  "properties": {
    "addr:full":"Rue Lambot 142 Aiseau-presles Hainaut 6250",
    "addr:housenumber":"142",
    "addr:postcode":"6250",
    "addr:street":"Rue Lambot;Hainaut",
    "iso:country":"BE",
    "sg:address":"Rue Lambot 142",
    "sg:city":"Aiseau-presles",
    "sg:orig_category":"Artsen and specialisten",
    "sg:phone":"+32 71 77 01 92",
    "sg:postcode":"6250",
    "sg:province":"Hainaut",
    "wof:name":"Haftane Aslan",
    "wof:placetype":"venue"
},
  "geometry": {"coordinates":[4.5906238556,50.4264373779],"type":"Point"}
}