{
  "type": "Feature",
  "properties": {
    "addr:full":"Zedelgemsesteenweg 210 Ichtegem West-Vlaanderen 8480",
    "addr:housenumber":"210",
    "addr:postcode":"8480",
    "addr:street":"Zedelgemsesteenweg",
    "iso:country":"BE",
    "sg:address":"Zedelgemsesteenweg 210",
    "sg:city":"Ichtegem",
    "sg:orig_category":"Travaux de finition and nettoyage de b\u00e2timents. Construction de maisons",
    "sg:phone":"+32 59 29 83 92",
    "sg:postcode":"8480",
    "sg:province":"West-Vlaanderen",
    "wof:name":"Brinckman Eric & Stefaan",
    "wof:placetype":"venue"
},
  "geometry": {"coordinates":[3.0563249588,51.1230125427],"type":"Point"}
}