{
  "type": "Feature",
  "properties": {
    "addr:full":"Place De Ros\u00c9e 42 Florennes Namur 5620",
    "addr:housenumber":"42",
    "addr:postcode":"5620",
    "addr:street":"Place De Rose\u0301E",
    "iso:country":"BE",
    "sg:address":"Place De Ros\u00c9e 42",
    "sg:city":"Florennes",
    "sg:orig_category":"Boucheries",
    "sg:phone":"+32 82 68 86 82",
    "sg:postcode":"5620",
    "sg:province":"Namur",
    "wof:name":"Jean-marc Stevens",
    "wof:placetype":"venue"
},
  "geometry": {"coordinates":[4.6876020432,50.233669281],"type":"Point"}
}