{
  "type": "Feature",
  "properties": {
    "addr:full":"Zittaardstraat 1 Halen Limburg 3545",
    "addr:housenumber":"1",
    "addr:postcode":"3545",
    "addr:street":"Zittaardstraat",
    "iso:country":"BE",
    "sg:address":"Zittaardstraat 1",
    "sg:city":"Halen",
    "sg:orig_category":"Banques and organismes de cr\u00e9dit",
    "sg:phone":"+32 13 46 15 24",
    "sg:postcode":"3545",
    "sg:province":"Limburg",
    "wof:name":"Groep Argenta",
    "wof:placetype":"venue"
},
  "geometry": {"coordinates":[5.1072258949,50.9465484619],"type":"Point"}
}