{
  "type": "Feature",
  "properties": {
    "addr:full":"Brusselsesteenweg 170 Melle Oost-Vlaanderen 9090",
    "addr:housenumber":"170",
    "addr:postcode":"9090",
    "addr:street":"Brusselsesteenweg",
    "iso:country":"BE",
    "sg:address":"Brusselsesteenweg 170",
    "sg:city":"Melle",
    "sg:classifiers":[
        {
            "category":"Building & Trades",
            "subcategory":"Construction",
            "type":"Services"
        }
    ],
    "sg:phone":"+32 9 230 49 65",
    "sg:postcode":"9090",
    "sg:province":"Oost-Vlaanderen",
    "sg:tags":[
        "carpenter's",
        "work",
        "supraregional"
    ],
    "wof:name":"Defeyco B.v.b.a.",
    "wof:placetype":"venue"
},
  "geometry": {"coordinates":[3.7946279049,51.0072174072],"type":"Point"}
}