{
  "type": "Feature",
  "properties": {
    "iso:country":"BE",
    "sg:address":"Spelonckvaart 112",
    "sg:city":"Moerbeke",
    "sg:orig_category":"Afbraak- and draineerwerken",
    "sg:phone":"+32 9 346 72 65",
    "sg:postcode":"9180",
    "sg:province":"Oost-Vlaanderen",
    "wof:name":"Antheunis B",
    "wof:placetype":"venue"
},
  "geometry": {"coordinates":[3.9715650082,51.1855354309],"type":"Point"}
}