{
  "type": "Feature",
  "properties": {
    "addr:full":"Markt 59 Eeklo Oost-Vlaanderen 9900",
    "addr:housenumber":"59",
    "addr:postcode":"9900",
    "addr:street":"Markt",
    "iso:country":"BE",
    "sg:address":"Markt 59",
    "sg:city":"Eeklo",
    "sg:classifiers":[
        {
            "category":"Professional",
            "subcategory":"Testing Lab",
            "type":"Services"
        }
    ],
    "sg:phone":"+32 9 377 10 92",
    "sg:postcode":"9900",
    "sg:province":"Oost-Vlaanderen",
    "sg:tags":[
        "chemist"
    ],
    "wof:name":"Vandewynckele G",
    "wof:placetype":"venue"
},
  "geometry": {"coordinates":[3.5655798912,51.1845283508],"type":"Point"}
}