{
  "type": "Feature",
  "properties": {
    "iso:country":"BE",
    "sg:address":"Plantin En Moretuslei 23",
    "sg:city":"Antwerpen",
    "sg:orig_category":"Antiquit\u00e9s",
    "sg:phone":"+32 475 73 25 28",
    "sg:postcode":"2018",
    "sg:province":"Antwerpen",
    "wof:name":"Antiek Eug\u00c9nie",
    "wof:placetype":"venue"
},
  "geometry": {"coordinates":[4.4198760986,51.2105674744],"type":"Point"}
}