{
  "type": "Feature",
  "properties": {
    "iso:country":"BE",
    "sg:address":"Diederik Van Den Elzaslaan 8",
    "sg:city":"Torhout",
    "sg:classifiers":[
        {
            "category":"Health Services",
            "subcategory":"Doctor",
            "type":"Services"
        }
    ],
    "sg:phone":"+32 50 21 19 15",
    "sg:postcode":"8820",
    "sg:province":"West-Vlaanderen",
    "sg:tags":[
        "medicinephysicians",
        "surgeon"
    ],
    "wof:name":"Leuridan P",
    "wof:placetype":"venue"
},
  "geometry": {"coordinates":[3.0957500935,51.0768470764],"type":"Point"}
}