{
  "type": "Feature",
  "properties": {
    "addr:full":"Groenstraat 68 Geel Antwerpen 2440",
    "addr:housenumber":"68",
    "addr:postcode":"2440",
    "addr:street":"Groenstraat",
    "iso:country":"BE",
    "sg:address":"Groenstraat 68",
    "sg:city":"Geel",
    "sg:orig_category":"Kapsalons",
    "sg:phone":"+32 14 58 04 22",
    "sg:postcode":"2440",
    "sg:province":"Antwerpen",
    "wof:name":"Coiffure Maria",
    "wof:placetype":"venue"
},
  "geometry": {"coordinates":[4.9754810333,51.1708984375],"type":"Point"}
}