{
  "type": "Feature",
  "properties": {
    "addr:full":"Grootrees 13 Kasterlee Antwerpen 2460",
    "addr:housenumber":"13",
    "addr:postcode":"2460",
    "addr:street":"Grootrees",
    "iso:country":"BE",
    "sg:address":"Grootrees 13",
    "sg:city":"Kasterlee",
    "sg:classifiers":[
        {
            "category":"Retail",
            "subcategory":"Animal Services",
            "type":"Services"
        }
    ],
    "sg:phone":"+32 14 85 22 31",
    "sg:postcode":"2460",
    "sg:province":"Antwerpen",
    "sg:tags":[
        "grooming",
        "-",
        "dog"
    ],
    "wof:name":"Poedelshop",
    "wof:placetype":"venue"
},
  "geometry": {"coordinates":[4.966878891,51.2526130676],"type":"Point"}
}