{
  "type": "Feature",
  "properties": {
    "addr:full":"Hasseltsesteenweg 149 Kortessem Limburg 3720",
    "addr:housenumber":"149",
    "addr:postcode":"3720",
    "addr:street":"Hasseltsesteenweg;Limburg",
    "iso:country":"BE",
    "sg:address":"Hasseltsesteenweg 149",
    "sg:city":"Kortessem",
    "sg:orig_category":"Installation de menuiserie m\u00e9tallique",
    "sg:phone":"+32 11 37 81 70",
    "sg:postcode":"3720",
    "sg:province":"Limburg",
    "wof:name":"Dekens Georges",
    "wof:placetype":"venue"
},
  "geometry": {"coordinates":[5.3684301376,50.8719367981],"type":"Point"}
}