{
  "type": "Feature",
  "properties": {
    "addr:full":"Rue Saint-pierre 21 Huy Li\u00e8ge 4500",
    "addr:housenumber":"21",
    "addr:postcode":"4500",
    "addr:street":"Rue Saint-Pierre",
    "iso:country":"BE",
    "sg:address":"Rue Saint-pierre 21",
    "sg:city":"Huy",
    "sg:orig_category":"Kansspelen",
    "sg:phone":"+32 85 21 52 90",
    "sg:postcode":"4500",
    "sg:province":"Li\u00e8ge",
    "wof:name":"Ladbrokes",
    "wof:placetype":"venue"
},
  "geometry": {"coordinates":[5.2348589897,50.521938324],"type":"Point"}
}