{
  "type": "Feature",
  "properties": {
    "iso:country":"BE",
    "sg:address":"Kulvestraat 41",
    "sg:city":"Geraardsbergen",
    "sg:orig_category":"Boomkwekerijen",
    "sg:phone":"+32 54 50 06 68",
    "sg:postcode":"9506",
    "sg:province":"Oost-Vlaanderen",
    "wof:name":"Roger De Sterck",
    "wof:placetype":"venue"
},
  "geometry": {"coordinates":[3.8985300064,50.7987060547],"type":"Point"}
}