{
  "type": "Feature",
  "properties": {
    "iso:country":"BE",
    "sg:address":"Heerweg 29",
    "sg:city":"Beersel",
    "sg:classifiers":[
        {
            "category":"Personal",
            "subcategory":"Beauty Salon",
            "type":"Services"
        }
    ],
    "sg:phone":"+32 2 377 93 07",
    "sg:postcode":"1650",
    "sg:province":"Vlaams-Brabant",
    "sg:tags":[
        "lady",
        "-",
        "hairdressing"
    ],
    "wof:name":"Van De Voorde S",
    "wof:placetype":"venue"
},
  "geometry": {"coordinates":[4.3168048859,50.7631111145],"type":"Point"}
}