{
  "type": "Feature",
  "properties": {
    "iso:country":"BE",
    "sg:address":"Rue Des Artisans 20",
    "sg:city":"Anhee",
    "sg:classifiers":[
        {
            "category":"Restaurant",
            "type":"Food & Drink"
        }
    ],
    "sg:phone":"+32 82 69 91 32",
    "sg:postcode":"5537",
    "sg:province":"Namur",
    "wof:name":"Chez Leon",
    "wof:placetype":"venue"
},
  "geometry": {"coordinates":[4.7519569397,50.2997093201],"type":"Point"}
}