{
  "type": "Feature",
  "properties": {
    "addr:full":"Rijksweg 165 Box 2 Maasmechelen Limburg 3630",
    "addr:housenumber":"165;2",
    "addr:postcode":"3630",
    "addr:street":"Rijksweg;Box",
    "iso:country":"BE",
    "sg:address":"Rijksweg 165 Box 2",
    "sg:city":"Maasmechelen",
    "sg:classifiers":[
        {
            "category":"Insurance",
            "subcategory":"Insurance Agent",
            "type":"Services"
        }
    ],
    "sg:phone":"+32 89 76 44 85",
    "sg:postcode":"3630",
    "sg:province":"Limburg",
    "sg:tags":[
        "broker"
    ],
    "wof:name":"Maaslands Zakenkantoor Bekkers Nv",
    "wof:placetype":"venue"
},
  "geometry": {"coordinates":[5.7010397911,50.9787216187],"type":"Point"}
}