{
  "type": "Feature",
  "properties": {
    "iso:country":"BE",
    "sg:address":"Winkelstraat 19",
    "sg:city":"Kortessem",
    "sg:classifiers":[
        {
            "category":"Home & Garden",
            "subcategory":"Home Furnishings",
            "type":"Retail Goods"
        }
    ],
    "sg:phone":"+32 11 37 68 15",
    "sg:postcode":"3720",
    "sg:province":"Limburg",
    "sg:tags":[
        "-",
        "furniture"
    ],
    "wof:name":"Claesen Gebr Bvba",
    "wof:placetype":"venue"
},
  "geometry": {"coordinates":[5.3735980988,50.8715438843],"type":"Point"}
}