{
  "type": "Feature",
  "properties": {
    "addr:full":"Stationsstraat 2 Tessenderlo Limburg 3980",
    "addr:housenumber":"2",
    "addr:postcode":"3980",
    "addr:street":"Stationsstraat",
    "iso:country":"BE",
    "sg:address":"Stationsstraat 2",
    "sg:city":"Tessenderlo",
    "sg:orig_category":"Herenkledingzaken Maatkleding Fab",
    "sg:phone":"+32 13 66 11 88",
    "sg:postcode":"3980",
    "sg:province":"Limburg",
    "wof:name":"In De Scheer",
    "wof:placetype":"venue"
},
  "geometry": {"coordinates":[5.0921378136,51.0673675537],"type":"Point"}
}