{
  "type": "Feature",
  "properties": {
    "iso:country":"BE",
    "sg:address":"Albert I Laan 177b",
    "sg:city":"Nieuwpoort",
    "sg:classifiers":[
        {
            "category":"Shopping",
            "subcategory":"Clothing, Apparel, & Fashions",
            "type":"Retail Goods"
        }
    ],
    "sg:phone":"+32 58 24 14 35",
    "sg:postcode":"8620",
    "sg:province":"West-Vlaanderen",
    "sg:tags":[
        "lady",
        "clothing",
        "-"
    ],
    "wof:name":"Sarah Pacini",
    "wof:placetype":"venue"
},
  "geometry": {"coordinates":[2.7182519436,51.1491699219],"type":"Point"}
}