{
  "type": "Feature",
  "properties": {
    "addr:full":"Vierhekkenstraat 5ba Gent Oost-Vlaanderen 9031",
    "addr:housenumber":"5ba",
    "addr:postcode":"9031",
    "addr:street":"Vierhekkenstraat;Oost-Vlaanderen",
    "iso:country":"BE",
    "sg:address":"Vierhekkenstraat 5ba",
    "sg:city":"Gent",
    "sg:classifiers":[
        {
            "category":"Insurance",
            "subcategory":"Insurance Agent",
            "type":"Services"
        }
    ],
    "sg:phone":"+32 9 236 24 33",
    "sg:postcode":"9031",
    "sg:province":"Oost-Vlaanderen",
    "sg:tags":[
        "verzekeringsmakelaars",
        "expert"
    ],
    "wof:name":"H. Cocquyt",
    "wof:placetype":"venue"
},
  "geometry": {"coordinates":[3.662966013,51.0507011414],"type":"Point"}
}