{
  "type": "Feature",
  "properties": {
    "iso:country":"BE",
    "sg:address":"Frankrijklei 31d",
    "sg:city":"Antwerpen",
    "sg:classifiers":[
        {
            "category":"Shopping",
            "subcategory":"Clothing, Apparel, & Fashions",
            "type":"Retail Goods"
        }
    ],
    "sg:phone":"+32 3 234 17 78",
    "sg:postcode":"2000",
    "sg:province":"Antwerpen",
    "sg:tags":[
        "lady",
        "clothing",
        "-"
    ],
    "wof:name":"Missoni By Moda E Modi",
    "wof:placetype":"venue"
},
  "geometry": {"coordinates":[4.4152870178,51.2170944214],"type":"Point"}
}