{
  "type": "Feature",
  "properties": {
    "addr:full":"Ratelingestraat 38 Wingene West-Vlaanderen 8750",
    "addr:housenumber":"38",
    "addr:postcode":"8750",
    "addr:street":"Ratelingestraat",
    "iso:country":"BE",
    "sg:address":"Ratelingestraat 38",
    "sg:city":"Wingene",
    "sg:classifiers":[
        {
            "category":"Parking",
            "subcategory":"Lot",
            "type":"Transportation"
        }
    ],
    "sg:phone":"+32 51 65 59 31",
    "sg:postcode":"8750",
    "sg:province":"West-Vlaanderen",
    "sg:tags":[
        "-",
        "livestock",
        "transport"
    ],
    "wof:name":"Dekeyzer B Bvba",
    "wof:placetype":"venue"
},
  "geometry": {"coordinates":[3.2699890137,51.0365943909],"type":"Point"}
}