{
  "type": "Feature",
  "properties": {
    "addr:full":"Sint-augustinuslaan 23 Vorst/forest Bruxelles-Capitale 1190",
    "addr:housenumber":"23",
    "addr:postcode":"1190",
    "addr:street":"Sint-Augustinuslaan;/ Forest",
    "iso:country":"BE",
    "sg:address":"Sint-augustinuslaan 23",
    "sg:city":"Vorst/forest",
    "sg:orig_category":"Artsen and specialisten",
    "sg:phone":"+32 2 343 96 47",
    "sg:postcode":"1190",
    "sg:province":"Bruxelles-Capitale",
    "wof:name":"Genevi\u00c8ve Naome",
    "wof:placetype":"venue"
},
  "geometry": {"coordinates":[4.3385529518,50.8164978027],"type":"Point"}
}