{
  "type": "Feature",
  "properties": {
    "iso:country":"BE",
    "sg:address":"Nieuwstraat 7",
    "sg:city":"Tielt",
    "sg:orig_category":"Artsen and specialisten",
    "sg:phone":"+32 51 40 05 02",
    "sg:postcode":"8700",
    "sg:province":"West-Vlaanderen",
    "wof:name":"Jozef-hektor Speybrouck",
    "wof:placetype":"venue"
},
  "geometry": {"coordinates":[3.3274669647,50.9996604919],"type":"Point"}
}