{
  "type": "Feature",
  "properties": {
    "iso:country":"BE",
    "sg:address":"Rue Des Foss\u00c9s 21",
    "sg:city":"Braine-l\u00b4alleud",
    "sg:classifiers":[
        {
            "category":"Restaurant",
            "type":"Food & Drink"
        }
    ],
    "sg:phone":"+32 2 385 29 60",
    "sg:postcode":"1420",
    "sg:province":"Brabant Wallon",
    "wof:name":"Snack-bar Le Dagobar",
    "wof:placetype":"venue"
},
  "geometry": {"coordinates":[4.3710021973,50.6836357117],"type":"Point"}
}