{
  "type": "Feature",
  "properties": {
    "addr:full":"Dreef 1 Zomergem Oost-Vlaanderen 9930",
    "addr:housenumber":"1",
    "addr:postcode":"9930",
    "addr:street":"Dreef",
    "iso:country":"BE",
    "sg:address":"Dreef 1",
    "sg:city":"Zomergem",
    "sg:classifiers":[
        {
            "category":"Banks & Credit Unions",
            "subcategory":"Bank",
            "type":"Services"
        }
    ],
    "sg:phone":"+32 52 72 81 63",
    "sg:postcode":"9930",
    "sg:province":"Oost-Vlaanderen",
    "wof:name":"Banque Bruxelles Lambert Sa",
    "wof:placetype":"venue"
},
  "geometry": {"coordinates":[3.5612859726,51.1186637878],"type":"Point"}
}