{
  "type": "Feature",
  "properties": {
    "iso:country":"BE",
    "sg:address":"Speibeekweg 2",
    "sg:city":"Wingene",
    "sg:orig_category":"Eleveurs and marchands de porcs. Eleveurs de bovins",
    "sg:phone":"+32 51 65 58 42",
    "sg:postcode":"8750",
    "sg:province":"West-Vlaanderen",
    "wof:name":"Frans Danneels",
    "wof:placetype":"venue"
},
  "geometry": {"coordinates":[3.2571399212,51.0566711426],"type":"Point"}
}