{
  "type": "Feature",
  "properties": {
    "iso:country":"BE",
    "sg:address":"Graaf Boudewijn I-straat 20",
    "sg:city":"Harelbeke",
    "sg:orig_category":"Herstellingen and onderhoud van auto's",
    "sg:phone":"+32 56 72 68 77",
    "sg:postcode":"8530",
    "sg:province":"West-Vlaanderen",
    "wof:name":"Peter Verhaeghe",
    "wof:placetype":"venue"
},
  "geometry": {"coordinates":[3.3150110245,50.8594284058],"type":"Point"}
}