{
  "type": "Feature",
  "properties": {
    "iso:country":"BE",
    "sg:address":"Krekelberg 19",
    "sg:city":"Oosterzele",
    "sg:orig_category":"Baby- and kinderkleding",
    "sg:phone":"+32 9 362 50 74",
    "sg:postcode":"9860",
    "sg:province":"Oost-Vlaanderen",
    "wof:name":"Delhim",
    "wof:placetype":"venue"
},
  "geometry": {"coordinates":[3.7920749187,50.9267654419],"type":"Point"}
}