{
  "type": "Feature",
  "properties": {
    "addr:full":"Dorpsstraat 27 Jabbeke West-Vlaanderen 8490",
    "addr:housenumber":"27",
    "addr:postcode":"8490",
    "addr:street":"Dorpsstraat",
    "iso:country":"BE",
    "sg:address":"Dorpsstraat 27",
    "sg:city":"Jabbeke",
    "sg:classifiers":[
        {
            "category":"Shopping",
            "subcategory":"Clothing, Apparel, & Fashions",
            "type":"Retail Goods"
        }
    ],
    "sg:phone":"+32 50 81 55 73",
    "sg:postcode":"8490",
    "sg:province":"West-Vlaanderen",
    "sg:tags":[
        "-",
        "clothing",
        "child"
    ],
    "wof:name":"Fidel",
    "wof:placetype":"venue"
},
  "geometry": {"coordinates":[3.0913629532,51.1820487976],"type":"Point"}
}