{
  "type": "Feature",
  "properties": {
    "addr:full":"Chauss\u00e9e De Boondael 415 Bruxelles (ixelles) Bruxelles-Capitale 1050",
    "addr:housenumber":"415",
    "addr:postcode":"1050",
    "addr:street":"Chausse\u0301E De Boondael",
    "iso:country":"BE",
    "sg:address":"Chauss\u00e9e De Boondael 415",
    "sg:city":"Bruxelles (ixelles)",
    "sg:classifiers":[
        {
            "category":"Home & Garden",
            "subcategory":"Carpets & Floor Coverings",
            "type":"Retail Goods"
        }
    ],
    "sg:phone":"+32 2 771 68 13",
    "sg:postcode":"1050",
    "sg:province":"Bruxelles-Capitale",
    "sg:tags":[
        "-",
        "rug"
    ],
    "wof:name":"D\u00e9co Lines Sprl",
    "wof:placetype":"venue"
},
  "geometry": {"coordinates":[4.3883361816,50.8174057007],"type":"Point"}
}