{
  "type": "Feature",
  "properties": {
    "addr:full":"Norbert Neeckxlaan 156 Lommel Limburg 3920",
    "addr:housenumber":"156",
    "addr:postcode":"3920",
    "addr:street":"Neeckxlaan",
    "iso:country":"BE",
    "sg:address":"Norbert Neeckxlaan 156",
    "sg:city":"Lommel",
    "sg:orig_category":"Voertuigen",
    "sg:phone":"+32 11 54 43 00",
    "sg:postcode":"3920",
    "sg:province":"Limburg",
    "wof:name":"Garage Brouwers",
    "wof:placetype":"venue"
},
  "geometry": {"coordinates":[5.3430271149,51.2222709656],"type":"Point"}
}