{
  "type": "Feature",
  "properties": {
    "addr:full":"Avenue D'esneux 69 Esneux (tilff) Li\u00e8ge 4130",
    "addr:housenumber":"69",
    "addr:postcode":"4130",
    "addr:street":"Avenue D'Esneux",
    "iso:country":"BE",
    "sg:address":"Avenue D'esneux 69",
    "sg:city":"Esneux (tilff)",
    "sg:classifiers":[
        {
            "category":"Recreation",
            "subcategory":"Fishing",
            "type":"Entertainment"
        }
    ],
    "sg:phone":"+32 4 388 22 06",
    "sg:postcode":"4130",
    "sg:province":"Li\u00e8ge",
    "sg:tags":[
        "tackle"
    ],
    "wof:name":"Epuisette (l')",
    "wof:placetype":"venue"
},
  "geometry": {"coordinates":[5.5908060074,50.5476646423],"type":"Point"}
}