{
  "type": "Feature",
  "properties": {
    "addr:full":"Rue Des Alli\u00e9s 21 Nassogne (forri\u00e8res) Luxembourg 6953",
    "addr:housenumber":"21",
    "addr:postcode":"6953",
    "addr:street":"Rue Des Allie\u0301S",
    "iso:country":"BE",
    "sg:address":"Rue Des Alli\u00e9s 21",
    "sg:city":"Nassogne (forri\u00e8res)",
    "sg:classifiers":[
        {
            "category":"Shopping",
            "subcategory":"Books",
            "type":"Retail Goods"
        }
    ],
    "sg:phone":"+32 84 21 16 85",
    "sg:postcode":"6953",
    "sg:province":"Luxembourg",
    "sg:tags":[
        "bookseller"
    ],
    "wof:name":"Librairie Abc Sprl",
    "wof:placetype":"venue"
},
  "geometry": {"coordinates":[5.2784819603,50.1333312988],"type":"Point"}
}