{
  "type": "Feature",
  "properties": {
    "addr:full":"Hunselberg 4 Roosdaal Vlaams-Brabant 1760",
    "addr:housenumber":"4",
    "addr:postcode":"1760",
    "addr:street":"Hunselberg",
    "iso:country":"BE",
    "sg:address":"Hunselberg 4",
    "sg:city":"Roosdaal",
    "sg:classifiers":[
        {
            "category":"Banks & Credit Unions",
            "subcategory":"Investment Brokerage",
            "type":"Services"
        }
    ],
    "sg:phone":"+32 54 33 13 82",
    "sg:postcode":"1760",
    "sg:province":"Vlaams-Brabant",
    "sg:tags":[
        "agricoles",
        "gr",
        "de",
        "machine",
        "mat\u00e9riel",
        "article",
        "jardin"
    ],
    "wof:name":"M Rooseleer & Co",
    "wof:placetype":"venue"
},
  "geometry": {"coordinates":[4.0744271278,50.8435707092],"type":"Point"}
}