{
  "type": "Feature",
  "properties": {
    "addr:full":"Rue Du Bas-comognes Jemeppe-sur-sambre Namur 5190",
    "addr:postcode":"5190",
    "addr:street":"Rue Du Bas-Comognes",
    "iso:country":"BE",
    "sg:address":"Rue Du Bas-comognes",
    "sg:city":"Jemeppe-sur-sambre",
    "sg:orig_category":"Animaux domestiques and accessoires",
    "sg:phone":"+32 71 78 51 23",
    "sg:postcode":"5190",
    "sg:province":"Namur",
    "wof:name":"Graineterie Marcipont",
    "wof:placetype":"venue"
},
  "geometry": {"coordinates":[4.6570367813,50.4668273926],"type":"Point"}
}