{
  "type": "Feature",
  "properties": {
    "iso:country":"BE",
    "sg:address":"Lenniksestraat 46",
    "sg:city":"Gooik",
    "sg:orig_category":"Mat\u00e9riaux de construction Gr",
    "sg:phone":"+32 54 56 60 07",
    "sg:postcode":"1755",
    "sg:province":"Vlaams-Brabant",
    "wof:name":"Bouwst. W. Dehandschutter",
    "wof:placetype":"venue"
},
  "geometry": {"coordinates":[4.0746021271,50.776309967],"type":"Point"}
}