{
  "type": "Feature",
  "properties": {
    "iso:country":"BE",
    "sg:address":"Zijlaan 3",
    "sg:city":"Ukkel/uccle",
    "sg:orig_category":"Immobili\u00ebnkantoren",
    "sg:phone":"+32 2 375 33 02",
    "sg:postcode":"1180",
    "sg:province":"Bruxelles-Capitale",
    "wof:name":"Immo Trust",
    "wof:placetype":"venue"
},
  "geometry": {"coordinates":[4.3731760979,50.7965240479],"type":"Point"}
}