{
  "type": "Feature",
  "properties": {
    "addr:full":"Chauss\u00c9e De Boondael 88 Elsene/ixelles Bruxelles-Capitale 1050",
    "addr:housenumber":"88",
    "addr:postcode":"1050",
    "addr:street":"Chausse\u0301E De Boondael",
    "iso:country":"BE",
    "sg:address":"Chauss\u00c9e De Boondael 88",
    "sg:city":"Elsene/ixelles",
    "sg:orig_category":"Meubles D\u00e9taillants, Am\u00e9nagement de B\u00e2timents et de Cuisines",
    "sg:phone":"+32 2 647 47 27",
    "sg:postcode":"1050",
    "sg:province":"Bruxelles-Capitale",
    "wof:name":"Locomoson",
    "wof:placetype":"venue"
},
  "geometry": {"coordinates":[4.3767061234,50.8252906799],"type":"Point"}
}