{
  "type": "Feature",
  "properties": {
    "addr:full":"Noorderlaan 87 Antwerpen Antwerpen 2030",
    "addr:housenumber":"87",
    "addr:postcode":"2030",
    "addr:street":"Noorderlaan",
    "iso:country":"BE",
    "sg:address":"Noorderlaan 87",
    "sg:city":"Antwerpen",
    "sg:classifiers":[
        {
            "category":"Social Services",
            "subcategory":"Job Training",
            "type":"Services"
        }
    ],
    "sg:phone":"+32 3 541 71 30",
    "sg:postcode":"2030",
    "sg:province":"Antwerpen",
    "sg:tags":[
        "personnel"
    ],
    "wof:name":"Sgs Training Institute Vzw",
    "wof:placetype":"venue"
},
  "geometry": {"coordinates":[4.4198851585,51.2562942505],"type":"Point"}
}