{
  "type": "Feature",
  "properties": {
    "addr:full":"Pleinstraat 6 Heist-op-den-berg (booischot) Antwerpen 2221",
    "addr:housenumber":"6",
    "addr:postcode":"2221",
    "addr:street":"Pleinstraat",
    "iso:country":"BE",
    "sg:address":"Pleinstraat 6",
    "sg:city":"Heist-op-den-berg (booischot)",
    "sg:classifiers":[
        {
            "category":"Bakery",
            "type":"Food & Drink"
        }
    ],
    "sg:phone":"+32 15 22 14 49",
    "sg:postcode":"2221",
    "sg:province":"Antwerpen",
    "sg:tags":[
        "confectioner",
        "baker"
    ],
    "wof:name":"Dageraad",
    "wof:placetype":"venue"
},
  "geometry": {"coordinates":[4.7739758492,51.0512428284],"type":"Point"}
}