{
  "type": "Feature",
  "properties": {
    "addr:full":"Stationsstraat 32 Genk Limburg 3600",
    "addr:housenumber":"32",
    "addr:postcode":"3600",
    "addr:street":"Stationsstraat",
    "iso:country":"BE",
    "sg:address":"Stationsstraat 32",
    "sg:city":"Genk",
    "sg:classifiers":[
        {
            "category":"Bakery",
            "type":"Food & Drink"
        }
    ],
    "sg:phone":"+32 89 35 30 72",
    "sg:postcode":"3600",
    "sg:province":"Limburg",
    "sg:tags":[
        "confectioner",
        "baker"
    ],
    "wof:name":"Geebelen J",
    "wof:placetype":"venue"
},
  "geometry": {"coordinates":[5.5006327629,50.9650306702],"type":"Point"}
}