{
  "type": "Feature",
  "properties": {
    "addr:full":"Wielewaallaan 71 Grimbergen Vlaams-Brabant 1850",
    "addr:housenumber":"71",
    "addr:postcode":"1850",
    "addr:street":"Wielewaallaan",
    "iso:country":"BE",
    "sg:address":"Wielewaallaan 71",
    "sg:city":"Grimbergen",
    "sg:orig_category":"Rev\u00eatements pour sols and murs. Peinture",
    "sg:phone":"+32 2 253 26 67",
    "sg:postcode":"1850",
    "sg:province":"Vlaams-Brabant",
    "wof:name":"Dmr Interieur",
    "wof:placetype":"venue"
},
  "geometry": {"coordinates":[4.4027299881,50.9328384399],"type":"Point"}
}