{
  "type": "Feature",
  "properties": {
    "iso:country":"BE",
    "sg:address":"Rue De Taillis-pr\u00c9 39",
    "sg:city":"Chatelet",
    "sg:classifiers":[
        {
            "category":"Food & Beverages",
            "subcategory":"Fruits & Vegetables",
            "type":"Retail Goods"
        }
    ],
    "sg:phone":"+32 71 40 40 71",
    "sg:postcode":"6200",
    "sg:province":"Hainaut",
    "sg:tags":[
        "l\u00e9gumes"
    ],
    "wof:name":"Maison Printannier",
    "wof:placetype":"venue"
},
  "geometry": {"coordinates":[4.5064558983,50.4330215454],"type":"Point"}
}