{
  "type": "Feature",
  "properties": {
    "addr:full":"Puyveldestraat 18 Sint-gillis-waas Oost-Vlaanderen 9170",
    "addr:housenumber":"18",
    "addr:postcode":"9170",
    "addr:street":"Puyveldestraat",
    "iso:country":"BE",
    "sg:address":"Puyveldestraat 18",
    "sg:city":"Sint-gillis-waas",
    "sg:orig_category":"Benzinestations and brandstoffen",
    "sg:phone":"+32 3 779 93 42",
    "sg:postcode":"9170",
    "sg:province":"Oost-Vlaanderen",
    "wof:name":"Andre Vereecken",
    "wof:placetype":"venue"
},
  "geometry": {"coordinates":[4.0664892197,51.1828117371],"type":"Point"}
}