{
  "type": "Feature",
  "properties": {
    "addr:full":"Diestsesteenweg 305 Aarschot (rillaar) Vlaams-Brabant 3202",
    "addr:housenumber":"305",
    "addr:postcode":"3202",
    "addr:street":"Diestsesteenweg",
    "iso:country":"BE",
    "sg:address":"Diestsesteenweg 305",
    "sg:city":"Aarschot (rillaar)",
    "sg:classifiers":[
        {
            "category":"Personal",
            "subcategory":"Beauty Salon",
            "type":"Services"
        }
    ],
    "sg:phone":"+32 16 50 06 63",
    "sg:postcode":"3202",
    "sg:province":"Vlaams-Brabant",
    "sg:tags":[
        "lady",
        "-",
        "hairdressing"
    ],
    "wof:name":"Gaby",
    "wof:placetype":"venue"
},
  "geometry": {"coordinates":[4.8923540115,50.97473526],"type":"Point"}
}