{
  "type": "Feature",
  "properties": {
    "addr:full":"Rozestraat 97 Knesselare Oost-Vlaanderen 9910",
    "addr:housenumber":"97",
    "addr:postcode":"9910",
    "addr:street":"Rozestraat;Oost-Vlaanderen",
    "iso:country":"BE",
    "sg:address":"Rozestraat 97",
    "sg:city":"Knesselare",
    "sg:orig_category":"Eleveurs de bovins",
    "sg:phone":"+32 9 374 34 51",
    "sg:postcode":"9910",
    "sg:province":"Oost-Vlaanderen",
    "wof:name":"Gabriel Wille",
    "wof:placetype":"venue"
},
  "geometry": {"coordinates":[3.494560957,51.1265182495],"type":"Point"}
}