{
  "type": "Feature",
  "properties": {
    "iso:country":"BE",
    "sg:address":"Schoolstraat 13",
    "sg:city":"Dendermonde",
    "sg:orig_category":"Boissons",
    "sg:phone":"+32 52 21 31 28",
    "sg:postcode":"9200",
    "sg:province":"Oost-Vlaanderen",
    "wof:name":"Etienne Bogaert",
    "wof:placetype":"venue"
},
  "geometry": {"coordinates":[4.0725860596,51.0333938599],"type":"Point"}
}