{
  "type": "Feature",
  "properties": {
    "addr:full":"Chauss\u00e9e De Namur 64 Eghez\u00e9e Namur 5310",
    "addr:housenumber":"64",
    "addr:postcode":"5310",
    "addr:street":"Chausse\u0301E De Namur",
    "iso:country":"BE",
    "sg:address":"Chauss\u00e9e De Namur 64",
    "sg:city":"Eghez\u00e9e",
    "sg:classifiers":[
        {
            "category":"Home & Garden",
            "subcategory":"Garden Supply",
            "type":"Retail Goods"
        }
    ],
    "sg:phone":"+32 81 81 25 01",
    "sg:postcode":"5310",
    "sg:province":"Namur",
    "sg:tags":[
        "lawn",
        "mower"
    ],
    "wof:name":"Honda Eghezee",
    "wof:placetype":"venue"
},
  "geometry": {"coordinates":[4.9117450714,50.5865592957],"type":"Point"}
}