{
  "type": "Feature",
  "properties": {
    "addr:full":"Noordabeelstraat 28 Hooglede West-Vlaanderen 8830",
    "addr:housenumber":"28",
    "addr:postcode":"8830",
    "addr:street":"Noordabeelstraat",
    "iso:country":"BE",
    "sg:address":"Noordabeelstraat 28",
    "sg:city":"Hooglede",
    "sg:orig_category":"Mat\u00e9riaux de construction Construction de maisons. Travaux de finition and nettoyage de b\u00e2timents. R",
    "sg:phone":"+32 51 72 57 28",
    "sg:postcode":"8830",
    "sg:province":"West-Vlaanderen",
    "wof:name":"Allaert",
    "wof:placetype":"venue"
},
  "geometry": {"coordinates":[3.0825901031,50.9787139893],"type":"Point"}
}