{
  "type": "Feature",
  "properties": {
    "iso:country":"BE",
    "sg:address":"Stationsbaan 14ba",
    "sg:city":"Linter",
    "sg:orig_category":"Producteurs de fruits",
    "sg:phone":"+32 11 78 47 73",
    "sg:postcode":"3350",
    "sg:province":"Vlaams-Brabant",
    "wof:name":"Kris Jorissen",
    "wof:placetype":"venue"
},
  "geometry": {"coordinates":[5.05412817,50.8462905884],"type":"Point"}
}