{
  "type": "Feature",
  "properties": {
    "addr:full":"Avenue Reine Elisabeth 1 Rixensart Brabant Wallon 1330",
    "addr:housenumber":"1",
    "addr:postcode":"1330",
    "addr:street":"Avenue Reine Elisabeth;Wallon",
    "iso:country":"BE",
    "sg:address":"Avenue Reine Elisabeth 1",
    "sg:city":"Rixensart",
    "sg:orig_category":"M\u00e9decins and sp\u00e9cialistes",
    "sg:phone":"+32 2 653 79 68",
    "sg:postcode":"1330",
    "sg:province":"Brabant Wallon",
    "wof:name":"Michel Hoton",
    "wof:placetype":"venue"
},
  "geometry": {"coordinates":[4.537127018,50.7110290527],"type":"Point"}
}