{
  "type": "Feature",
  "properties": {
    "iso:country":"BE",
    "sg:address":"Staartmolenslaan 15b3",
    "sg:city":"Sint-lambrechts-woluwe/woluwe-saint-lambert",
    "sg:orig_category":"Artsen and specialisten",
    "sg:phone":"+32 2 772 58 23",
    "sg:postcode":"1200",
    "sg:province":"Bruxelles-Capitale",
    "wof:name":"Pierre De Backer",
    "wof:placetype":"venue"
},
  "geometry": {"coordinates":[4.441177845,50.8541870117],"type":"Point"}
}