{
  "type": "Feature",
  "properties": {
    "addr:full":"Russelt 44 Wellen Limburg 3830",
    "addr:housenumber":"44",
    "addr:postcode":"3830",
    "addr:street":"Russelt",
    "iso:country":"BE",
    "sg:address":"Russelt 44",
    "sg:city":"Wellen",
    "sg:classifiers":[
        {
            "category":"Utilities",
            "subcategory":"Electric",
            "type":"Services"
        }
    ],
    "sg:phone":"+32 11 31 47 05",
    "sg:postcode":"3830",
    "sg:province":"Limburg",
    "sg:tags":[
        "energy",
        "renewable"
    ],
    "wof:name":"Alrasol Energy",
    "wof:placetype":"venue"
},
  "geometry": {"coordinates":[5.3134918213,50.8508338928],"type":"Point"}
}