{
  "type": "Feature",
  "properties": {
    "addr:full":"Hortstraat 7 Zonhoven Limburg 3520",
    "addr:housenumber":"7",
    "addr:postcode":"3520",
    "addr:street":"Hortstraat",
    "iso:country":"BE",
    "sg:address":"Hortstraat 7",
    "sg:city":"Zonhoven",
    "sg:classifiers":[
        {
            "category":"Real Estate",
            "subcategory":"Architect",
            "type":"Services"
        }
    ],
    "sg:phone":"+32 11 82 15 53",
    "sg:postcode":"3520",
    "sg:province":"Limburg",
    "wof:name":"Vanhoudt J",
    "wof:placetype":"venue"
},
  "geometry": {"coordinates":[5.346765995,50.9990081787],"type":"Point"}
}