{
  "type": "Feature",
  "properties": {
    "iso:country":"BE",
    "sg:address":"Gruisweg 8",
    "sg:city":"Dilsen-stokkem",
    "sg:orig_category":"Installatie van houten of kunststof schrijnwerk",
    "sg:phone":"+32 89 75 43 60",
    "sg:postcode":"3650",
    "sg:province":"Limburg",
    "wof:name":"Christiaan Jacobs",
    "wof:placetype":"venue"
},
  "geometry": {"coordinates":[5.7369251251,51.0347099304],"type":"Point"}
}