{
  "type": "Feature",
  "properties": {
    "addr:full":"Rue De L'armistice 56 Li\u00e8ge 1 (li\u00e8ge 2) Li\u00e8ge 4020",
    "addr:housenumber":"56;1;2",
    "addr:postcode":"4020",
    "addr:street":"Rue De L'Armistice",
    "iso:country":"BE",
    "sg:address":"Rue De L'armistice 56",
    "sg:city":"Li\u00e8ge 1 (li\u00e8ge 2)",
    "sg:classifiers":[
        {
            "category":"Health Services",
            "subcategory":"Health Practitioner",
            "type":"Services"
        }
    ],
    "sg:phone":"+32 4 226 77 23",
    "sg:postcode":"4020",
    "sg:province":"Li\u00e8ge",
    "sg:tags":[
        "therapist",
        "speech"
    ],
    "wof:name":"Melotte C",
    "wof:placetype":"venue"
},
  "geometry": {"coordinates":[5.5942530632,50.6391563416],"type":"Point"}
}