{
  "type": "Feature",
  "properties": {
    "addr:full":"Tuinwijkstraat 59 Halen (zelem) Limburg 3545",
    "addr:housenumber":"59",
    "addr:postcode":"3545",
    "addr:street":"Tuinwijkstraat",
    "iso:country":"BE",
    "sg:address":"Tuinwijkstraat 59",
    "sg:city":"Halen (zelem)",
    "sg:classifiers":[
        {
            "category":"Building & Trades",
            "subcategory":"Construction",
            "type":"Services"
        }
    ],
    "sg:phone":"+32 13 46 13 86",
    "sg:postcode":"3545",
    "sg:province":"Limburg",
    "sg:tags":[
        "stucco",
        "contractor"
    ],
    "wof:name":"Interstuc Bvba",
    "wof:placetype":"venue"
},
  "geometry": {"coordinates":[5.1254301071,50.9838294983],"type":"Point"}
}