{
  "type": "Feature",
  "properties": {
    "iso:country":"BE",
    "sg:address":"Rue Des Gaux 13ba",
    "sg:city":"Ham-sur-heure-nalinnes",
    "sg:orig_category":"Secretariaatsdiensten",
    "sg:phone":"+32 71 21 35 18",
    "sg:postcode":"6120",
    "sg:province":"Hainaut",
    "wof:name":"Jean-marc Tamigniaux",
    "wof:placetype":"venue"
},
  "geometry": {"coordinates":[4.4506239891,50.3257751465],"type":"Point"}
}