{
  "type": "Feature",
  "properties": {
    "iso:country":"BE",
    "sg:address":"Kortwagenstraat 11",
    "sg:city":"Ledegem",
    "sg:orig_category":"M\u00e9decins and sp\u00e9cialistes",
    "sg:phone":"+32 56 50 39 63",
    "sg:postcode":"8880",
    "sg:province":"West-Vlaanderen",
    "wof:name":"L. Clarysse",
    "wof:placetype":"venue"
},
  "geometry": {"coordinates":[3.1263380051,50.859539032],"type":"Point"}
}