{
  "type": "Feature",
  "properties": {
    "addr:full":"Carnotstraat 112-114 Antwerpen Antwerpen 2060",
    "addr:housenumber":"112-114",
    "addr:postcode":"2060",
    "addr:street":"Carnotstraat",
    "iso:country":"BE",
    "sg:address":"Carnotstraat 112-114",
    "sg:city":"Antwerpen",
    "sg:orig_category":"HERSTELLING ELEKTRISCHE HUISHOUDAPPARATEN Huishoudapparaten, televisies and radio's Telecommunicatie",
    "sg:phone":"+32 3 233 86 28",
    "sg:postcode":"2060",
    "sg:province":"Antwerpen",
    "wof:name":"Eldi",
    "wof:placetype":"venue"
},
  "geometry": {"coordinates":[4.426733017,51.2177391052],"type":"Point"}
}