{
  "type": "Feature",
  "properties": {
    "addr:full":"Rue Joseph Weicker 40 Etalle Luxembourg 6740",
    "addr:housenumber":"40",
    "addr:postcode":"6740",
    "addr:street":"Rue Joseph Weicker",
    "iso:country":"BE",
    "sg:address":"Rue Joseph Weicker 40",
    "sg:city":"Etalle",
    "sg:orig_category":"Enseignement maternel and primaire",
    "sg:phone":"+32 63 41 22 26",
    "sg:postcode":"6740",
    "sg:province":"Luxembourg",
    "wof:name":"Ecole Fond. Communale",
    "wof:placetype":"venue"
},
  "geometry": {"coordinates":[5.5618019104,49.697807312],"type":"Point"}
}