{
  "type": "Feature",
  "properties": {
    "addr:full":"Moestoemaat 34 Westerlo Antwerpen 2260",
    "addr:housenumber":"34",
    "addr:postcode":"2260",
    "addr:street":"Moestoemaat",
    "iso:country":"BE",
    "sg:address":"Moestoemaat 34",
    "sg:city":"Westerlo",
    "sg:orig_category":"Eleveurs de bovins",
    "sg:phone":"+32 14 54 47 30",
    "sg:postcode":"2260",
    "sg:province":"Antwerpen",
    "wof:name":"Jozef Van Den Eynde",
    "wof:placetype":"venue"
},
  "geometry": {"coordinates":[4.928524971,51.11876297],"type":"Point"}
}