{
  "type": "Feature",
  "properties": {
    "addr:full":"Grondwetlaan 59 Gent (sint-amandsberg) Oost-Vlaanderen 9040",
    "addr:housenumber":"59",
    "addr:postcode":"9040",
    "addr:street":"Grondwetlaan",
    "iso:country":"BE",
    "sg:address":"Grondwetlaan 59",
    "sg:city":"Gent (sint-amandsberg)",
    "sg:classifiers":[
        {
            "category":"Community Center",
            "subcategory":"Youth",
            "type":"Public Place"
        }
    ],
    "sg:phone":"+32 9 259 29 36",
    "sg:postcode":"9040",
    "sg:province":"Oost-Vlaanderen",
    "sg:tags":[
        "club"
    ],
    "wof:name":"Fontein (de)",
    "wof:placetype":"venue"
},
  "geometry": {"coordinates":[3.7511100769,51.0671043396],"type":"Point"}
}