{
  "type": "Feature",
  "properties": {
    "addr:full":"Chauss\u00c9e De Maubeuge 449 Mons Hainaut 7022",
    "addr:housenumber":"449",
    "addr:postcode":"7022",
    "addr:street":"Chausse\u0301E De Maubeuge;Hainaut",
    "iso:country":"BE",
    "sg:address":"Chauss\u00c9e De Maubeuge 449",
    "sg:city":"Mons",
    "sg:classifiers":[
        {
            "category":"Restaurant",
            "type":"Food & Drink"
        }
    ],
    "sg:phone":"+32 65 35 25 35",
    "sg:postcode":"7022",
    "sg:province":"Hainaut",
    "sg:tags":[
        "dancing",
        "nachtclubs"
    ],
    "wof:name":"Restaurant Discobar",
    "wof:placetype":"venue"
},
  "geometry": {"coordinates":[3.9516630173,50.4191589355],"type":"Point"}
}