{
  "type": "Feature",
  "properties": {
    "addr:full":"Nijverheidslaan 2 Strombeek-bever Vlaams-Brabant 1853",
    "addr:housenumber":"2;1853",
    "addr:street":"Nijverheidslaan;Vlaams-Brabant",
    "iso:country":"BE",
    "sg:address":"Nijverheidslaan 2",
    "sg:city":"Strombeek-bever",
    "sg:classifiers":[
        {
            "category":"Shopping",
            "subcategory":"Clothing, Apparel, & Fashions",
            "type":"Retail Goods"
        }
    ],
    "sg:phone":"+32 2 263 01 70",
    "sg:postcode":"1853",
    "sg:province":"Vlaams-Brabant",
    "sg:tags":[
        "children's",
        "clothing"
    ],
    "wof:name":"Schiesser International Nv",
    "wof:placetype":"venue"
},
  "geometry": {"coordinates":[4.3619771004,50.9115829468],"type":"Point"}
}