{
  "type": "Feature",
  "properties": {
    "addr:full":"Kloosterstraat 11 Malle Antwerpen 2390",
    "addr:housenumber":"11",
    "addr:postcode":"2390",
    "addr:street":"Kloosterstraat",
    "iso:country":"BE",
    "sg:address":"Kloosterstraat 11",
    "sg:city":"Malle",
    "sg:orig_category":"Peinture. Rev\u00eatements pour sols and murs",
    "sg:phone":"+32 3 312 26 48",
    "sg:postcode":"2390",
    "sg:province":"Antwerpen",
    "wof:name":"Eddy Brabants",
    "wof:placetype":"venue"
},
  "geometry": {"coordinates":[4.7322821617,51.3003845215],"type":"Point"}
}