{
  "type": "Feature",
  "properties": {
    "iso:country":"BE",
    "sg:address":"Statielei 129",
    "sg:city":"Mortsel",
    "sg:orig_category":"Agences de voyages",
    "sg:phone":"+32 3 448 36 32",
    "sg:postcode":"2640",
    "sg:province":"Antwerpen",
    "wof:name":"Reizen Elite",
    "wof:placetype":"venue"
},
  "geometry": {"coordinates":[4.4551930428,51.1703948975],"type":"Point"}
}