{
  "type": "Feature",
  "properties": {
    "iso:country":"BE",
    "sg:address":"Place De La Station 5",
    "sg:city":"Charleroi (gosselies)",
    "sg:classifiers":[
        {
            "category":"Professional",
            "subcategory":"Accounting & Tax Preparation",
            "type":"Services"
        }
    ],
    "sg:phone":"+32 71 35 35 70",
    "sg:postcode":"6041",
    "sg:province":"Hainaut",
    "sg:tags":[
        "accountant"
    ],
    "wof:name":"Infanti E",
    "wof:placetype":"venue"
},
  "geometry": {"coordinates":[4.4375047684,50.4689216614],"type":"Point"}
}