{
  "type": "Feature",
  "properties": {
    "iso:country":"BE",
    "sg:address":"Rostockweg 14",
    "sg:city":"Antwerpen",
    "sg:classifiers":[
        {
            "category":"Farming",
            "subcategory":"Fish & Marine Products",
            "type":"Manufacturing & Wholesale Goods"
        }
    ],
    "sg:phone":"+32 3 542 22 03",
    "sg:postcode":"2030",
    "sg:province":"Antwerpen",
    "sg:tags":[
        "surveyor",
        "-"
    ],
    "wof:name":"De Meyer Expertisebureau Bvba",
    "wof:placetype":"venue"
},
  "geometry": {"coordinates":[4.3611431122,51.2668495178],"type":"Point"}
}