{
  "type": "Feature",
  "properties": {
    "addr:full":"Rue De Mettet 7 Florennes Namur 5620",
    "addr:housenumber":"7",
    "addr:postcode":"5620",
    "addr:street":"Rue De Mettet",
    "iso:country":"BE",
    "sg:address":"Rue De Mettet 7",
    "sg:city":"Florennes",
    "sg:orig_category":"Kapsalons",
    "sg:phone":"+32 71 68 86 38",
    "sg:postcode":"5620",
    "sg:province":"Namur",
    "wof:name":"Coiffure Albert",
    "wof:placetype":"venue"
},
  "geometry": {"coordinates":[4.6048150063,50.2509765625],"type":"Point"}
}