{
  "type": "Feature",
  "properties": {
    "addr:full":"Paardenstraat 40 Bornem Antwerpen 2880",
    "addr:housenumber":"40",
    "addr:postcode":"2880",
    "addr:street":"Paardenstraat",
    "iso:country":"BE",
    "sg:address":"Paardenstraat 40",
    "sg:city":"Bornem",
    "sg:orig_category":"Poissonniers and \u00e9caillers",
    "sg:phone":"+32 52 33 23 68",
    "sg:postcode":"2880",
    "sg:province":"Antwerpen",
    "wof:name":"Borremans",
    "wof:placetype":"venue"
},
  "geometry": {"coordinates":[4.192305088,51.0648269653],"type":"Point"}
}