{
  "type": "Feature",
  "properties": {
    "addr:full":"Rue Cockerill 176 Seraing Li\u00e8ge 4100",
    "addr:housenumber":"176",
    "addr:postcode":"4100",
    "addr:street":"Rue Cockerill",
    "iso:country":"BE",
    "sg:address":"Rue Cockerill 176",
    "sg:city":"Seraing",
    "sg:classifiers":[
        {
            "category":"Home & Garden",
            "subcategory":"Home Furnishings",
            "type":"Retail Goods"
        }
    ],
    "sg:phone":"+32 4 337 34 93",
    "sg:postcode":"4100",
    "sg:province":"Li\u00e8ge",
    "sg:tags":[
        "curtain",
        "-",
        "fixture"
    ],
    "wof:name":"Centrale Textile Decor Sa",
    "wof:placetype":"venue"
},
  "geometry": {"coordinates":[5.5125031471,50.6099472046],"type":"Point"}
}