{
  "type": "Feature",
  "properties": {
    "addr:full":"Rue Grande 25 Chiny (suxy) Luxembourg 6812",
    "addr:housenumber":"25",
    "addr:postcode":"6812",
    "addr:street":"Rue Grande",
    "iso:country":"BE",
    "sg:address":"Rue Grande 25",
    "sg:city":"Chiny (suxy)",
    "sg:classifiers":[
        {
            "category":"Government",
            "subcategory":"Department Of Motor Vehicles",
            "type":"Public Place"
        }
    ],
    "sg:phone":"+32 61 31 15 94",
    "sg:postcode":"6812",
    "sg:province":"Luxembourg",
    "sg:tags":[
        "planing",
        "wood",
        "sawing"
    ],
    "wof:name":"Pierrard S",
    "wof:placetype":"venue"
},
  "geometry": {"coordinates":[5.4004077911,49.7640266418],"type":"Point"}
}