{
  "type": "Feature",
  "properties": {
    "addr:full":"Chauss\u00e9e De Gand 1140 Box 37 Bruxelles (berchem-sainte-agathe) Bruxelles-Capitale 1082",
    "addr:housenumber":"1140 box 37",
    "addr:postcode":"1082",
    "addr:street":"Chausse\u0301E De Gand",
    "iso:country":"BE",
    "sg:address":"Chauss\u00e9e De Gand 1140 Box 37",
    "sg:city":"Bruxelles (berchem-sainte-agathe)",
    "sg:classifiers":[
        {
            "category":"Bus Station",
            "type":"Transportation"
        }
    ],
    "sg:phone":"+32 2 469 19 99",
    "sg:postcode":"1082",
    "sg:province":"Bruxelles-Capitale",
    "sg:tags":[
        "commercial",
        "industrial",
        "-",
        "investigator"
    ],
    "wof:name":"Agreco Services Sa",
    "wof:placetype":"venue"
},
  "geometry": {"coordinates":[4.2982621193,50.8636779785],"type":"Point"}
}