{
  "type": "Feature",
  "properties": {
    "iso:country":"BE",
    "sg:address":"Chaus\u00c9e De Namur",
    "sg:city":"Wavre",
    "sg:orig_category":"Paardenfokkers",
    "sg:phone":"+32 10 45 27 61",
    "sg:postcode":"1300",
    "sg:province":"Brabant Wallon",
    "wof:name":"Haras De Lauzelle",
    "wof:placetype":"venue"
},
  "geometry": {"coordinates":[4.6154098511,50.6981506348],"type":"Point"}
}