{
  "type": "Feature",
  "properties": {
    "iso:country":"BE",
    "sg:address":"Avenue Du Panth\u00c9on 60",
    "sg:city":"Koekelberg/koekelberg",
    "sg:classifiers":[
        {
            "category":"Arena",
            "subcategory":"Sports Club",
            "type":"Entertainment"
        }
    ],
    "sg:phone":"+32 2 411 77 30",
    "sg:postcode":"1081",
    "sg:province":"Bruxelles-Capitale",
    "sg:tags":[
        "terrain",
        "hors",
        "de",
        "installation",
        "sportifs"
    ],
    "wof:name":"L'oc\u00c9an Marin",
    "wof:placetype":"venue"
},
  "geometry": {"coordinates":[4.3208599091,50.8647460938],"type":"Point"}
}