{
  "type": "Feature",
  "properties": {
    "iso:country":"BE",
    "sg:address":"Landmolenstraat 99",
    "sg:city":"Temse",
    "sg:orig_category":"Eleveurs de bovins",
    "sg:phone":"+32 3 771 19 42",
    "sg:postcode":"9140",
    "sg:province":"Oost-Vlaanderen",
    "wof:name":"Jozef Smet",
    "wof:placetype":"venue"
},
  "geometry": {"coordinates":[4.2340650558,51.1577110291],"type":"Point"}
}