{
  "type": "Feature",
  "properties": {
    "iso:country":"BE",
    "sg:address":"Borluutlaan 18",
    "sg:city":"De Pinte",
    "sg:classifiers":[
        {
            "category":"Building & Trades",
            "subcategory":"Electrical",
            "type":"Services"
        }
    ],
    "sg:phone":"+32 9 282 82 23",
    "sg:postcode":"9840",
    "sg:province":"Oost-Vlaanderen",
    "sg:tags":[
        "electric",
        "-",
        "housewiring",
        "contractor"
    ],
    "wof:name":"Vlerick N",
    "wof:placetype":"venue"
},
  "geometry": {"coordinates":[3.6586999893,50.9960212708],"type":"Point"}
}