{
  "type": "Feature",
  "properties": {
    "addr:full":"Gistelse Steenweg 229 Brugge West-Vlaanderen 8200",
    "addr:housenumber":"229",
    "addr:postcode":"8200",
    "addr:street":"Gistelse Steenweg",
    "iso:country":"BE",
    "sg:address":"Gistelse Steenweg 229",
    "sg:city":"Brugge",
    "sg:classifiers":[
        {
            "category":"Arena",
            "subcategory":"Sports Club",
            "type":"Entertainment"
        }
    ],
    "sg:phone":"+32 50 38 92 32",
    "sg:postcode":"8200",
    "sg:province":"West-Vlaanderen",
    "sg:tags":[
        "terrain",
        "hors",
        "de",
        "installation",
        "sportifs"
    ],
    "wof:name":"Cl.van De Generale Brugge",
    "wof:placetype":"venue"
},
  "geometry": {"coordinates":[3.1961660385,51.2002716064],"type":"Point"}
}