{
  "type": "Feature",
  "properties": {
    "iso:country":"BE",
    "sg:address":"Kiewitstraat 196",
    "sg:city":"Hasselt",
    "sg:orig_category":"Messageries",
    "sg:phone":"+32 11 24 12 62",
    "sg:postcode":"3500",
    "sg:province":"Limburg",
    "wof:name":"Leurs Express",
    "wof:placetype":"venue"
},
  "geometry": {"coordinates":[5.389070034,50.9657783508],"type":"Point"}
}