{
  "type": "Feature",
  "properties": {
    "iso:country":"BE",
    "sg:address":"Rue De La Station 19ba",
    "sg:city":"Gembloux",
    "sg:orig_category":"Epiceries",
    "sg:phone":"+32 81 56 69 59",
    "sg:postcode":"5030",
    "sg:province":"Namur",
    "wof:name":"Courtheoux",
    "wof:placetype":"venue"
},
  "geometry": {"coordinates":[4.743678093,50.5333938599],"type":"Point"}
}