{
  "type": "Feature",
  "properties": {
    "iso:country":"BE",
    "sg:address":"Doornzeelsestraat 60",
    "sg:city":"Evergem",
    "sg:classifiers":[
        {
            "category":"Wholesale",
            "subcategory":"Meat",
            "type":"Manufacturing & Wholesale Goods"
        }
    ],
    "sg:phone":"+32 9 253 79 10",
    "sg:postcode":"9940",
    "sg:province":"Oost-Vlaanderen",
    "sg:tags":[
        "whol",
        "-"
    ],
    "wof:name":"Duprez A",
    "wof:placetype":"venue"
},
  "geometry": {"coordinates":[3.7485260963,51.1317596436],"type":"Point"}
}