{
  "type": "Feature",
  "properties": {
    "addr:full":"Bosstraat 32 Lummen Limburg 3560",
    "addr:housenumber":"32",
    "addr:postcode":"3560",
    "addr:street":"Bosstraat",
    "iso:country":"BE",
    "sg:address":"Bosstraat 32",
    "sg:city":"Lummen",
    "sg:orig_category":"Installatie van houten of kunststof schrijnwerk MEUBELONTWERP AND -INSTALLATIE",
    "sg:phone":"+32 13 52 33 65",
    "sg:postcode":"3560",
    "sg:province":"Limburg",
    "wof:name":"Romain Postelmans",
    "wof:placetype":"venue"
},
  "geometry": {"coordinates":[5.2080922127,50.9964332581],"type":"Point"}
}