{
  "type": "Feature",
  "properties": {
    "addr:full":"Rue De Viville 32 Arlon Luxembourg 6700",
    "addr:housenumber":"32",
    "addr:postcode":"6700",
    "addr:street":"Rue De Viville",
    "iso:country":"BE",
    "sg:address":"Rue De Viville 32",
    "sg:city":"Arlon",
    "sg:classifiers":[
        {
            "category":"Banks & Credit Unions",
            "subcategory":"Financial Services",
            "type":"Services"
        }
    ],
    "sg:phone":"+32 63 23 04 70",
    "sg:postcode":"6700",
    "sg:province":"Luxembourg",
    "sg:tags":[
        "loan",
        "mortgage"
    ],
    "wof:name":"Belgolux Finances",
    "wof:placetype":"venue"
},
  "geometry": {"coordinates":[5.8048810959,49.6902732849],"type":"Point"}
}