{
  "type": "Feature",
  "properties": {
    "iso:country":"BE",
    "sg:address":"Rue De Leernes 168",
    "sg:city":"Charleroi",
    "sg:classifiers":[
        {
            "category":"Personal",
            "subcategory":"Beauty Salon",
            "type":"Services"
        }
    ],
    "sg:phone":"+32 71 52 73 29",
    "sg:postcode":"6030",
    "sg:province":"Hainaut",
    "sg:tags":[
        "de",
        "coiffure"
    ],
    "wof:name":"A.b. Coiffure",
    "wof:placetype":"venue"
},
  "geometry": {"coordinates":[4.355407238,50.4139785767],"type":"Point"}
}