{
  "type": "Feature",
  "properties": {
    "addr:full":"Ruiterstraat 8-1 Bornem Antwerpen 2880",
    "addr:housenumber":"8-1",
    "addr:postcode":"2880",
    "addr:street":"Ruiterstraat",
    "iso:country":"BE",
    "sg:address":"Ruiterstraat 8-1",
    "sg:city":"Bornem",
    "sg:classifiers":[
        {
            "category":"Shopping",
            "subcategory":"Computers & Home Electronics",
            "type":"Retail Goods"
        }
    ],
    "sg:phone":"+32 3 899 17 69",
    "sg:postcode":"2880",
    "sg:province":"Antwerpen",
    "sg:tags":[
        "plate",
        "name"
    ],
    "wof:name":"Pro Signs",
    "wof:placetype":"venue"
},
  "geometry": {"coordinates":[4.2332420349,51.0985717773],"type":"Point"}
}