{
  "type": "Feature",
  "properties": {
    "iso:country":"BE",
    "sg:address":"Rue Britannique 3",
    "sg:city":"Braine-le-comte",
    "sg:orig_category":"Avocats and conseillers juridiques",
    "sg:phone":"+32 67 56 07 76",
    "sg:postcode":"7090",
    "sg:province":"Hainaut",
    "wof:name":"Christian Bouton",
    "wof:placetype":"venue"
},
  "geometry": {"coordinates":[4.1357488632,50.6084632874],"type":"Point"}
}