{
  "type": "Feature",
  "properties": {
    "addr:full":"Place Du Perron 44 Theux Li\u00e8ge 4910",
    "addr:housenumber":"44",
    "addr:postcode":"4910",
    "addr:street":"Place Du Perron",
    "iso:country":"BE",
    "sg:address":"Place Du Perron 44",
    "sg:city":"Theux",
    "sg:orig_category":"Banques and organismes de cr\u00e9dit",
    "sg:phone":"+32 87 54 14 16",
    "sg:postcode":"4910",
    "sg:province":"Li\u00e8ge",
    "wof:name":"Nagelmackers",
    "wof:placetype":"venue"
},
  "geometry": {"coordinates":[5.8130698204,50.5348701477],"type":"Point"}
}