{
  "type": "Feature",
  "properties": {
    "iso:country":"BE",
    "sg:address":"Rue De Lonz\u00e9e 57",
    "sg:city":"Gembloux-sur-orneau (gembloux)",
    "sg:classifiers":[
        {
            "category":"Professional",
            "subcategory":"Management & Consulting",
            "type":"Services"
        }
    ],
    "sg:phone":"+32 81 61 42 12",
    "sg:postcode":"5030",
    "sg:province":"Namur",
    "sg:tags":[
        "-",
        "processing",
        "data",
        "consultant"
    ],
    "wof:name":"Devillers P",
    "wof:placetype":"venue"
},
  "geometry": {"coordinates":[4.7302470207,50.554599762],"type":"Point"}
}