{
  "type": "Feature",
  "properties": {
    "addr:full":"Rue Sainte-ivette 58 Huy Li\u00e8ge 4500",
    "addr:housenumber":"58",
    "addr:postcode":"4500",
    "addr:street":"Rue Sainte-Ivette",
    "iso:country":"BE",
    "sg:address":"Rue Sainte-ivette 58",
    "sg:city":"Huy",
    "sg:classifiers":[
        {
            "category":"Real Estate",
            "subcategory":"Surveying",
            "type":"Services"
        }
    ],
    "sg:phone":"+32 85 21 42 90",
    "sg:postcode":"4500",
    "sg:province":"Li\u00e8ge",
    "sg:tags":[
        "surveyor",
        "land"
    ],
    "wof:name":"Vignisse R",
    "wof:placetype":"venue"
},
  "geometry": {"coordinates":[5.2367601395,50.5288734436],"type":"Point"}
}