{
  "type": "Feature",
  "properties": {
    "iso:country":"BE",
    "sg:address":"Pav\u00e9 D'ath 50",
    "sg:city":"Silly",
    "sg:classifiers":[
        {
            "category":"Retail",
            "subcategory":"Auto Repair",
            "type":"Services"
        }
    ],
    "sg:phone":"+32 68 55 12 57",
    "sg:postcode":"7830",
    "sg:province":"Hainaut",
    "sg:tags":[
        "garage"
    ],
    "wof:name":"Richard",
    "wof:placetype":"venue"
},
  "geometry": {"coordinates":[3.9463160038,50.6707801819],"type":"Point"}
}