{
  "type": "Feature",
  "properties": {
    "addr:full":"Tervurenlaan 197 Sint-pieters-woluwe/woluwe-saint-pierre Bruxelles-Capitale 1150",
    "addr:housenumber":"197",
    "addr:postcode":"1150",
    "addr:street":"Tervurenlaan;/",
    "iso:country":"BE",
    "sg:address":"Tervurenlaan 197",
    "sg:city":"Sint-pieters-woluwe/woluwe-saint-pierre",
    "sg:orig_category":"Secretariaatsdiensten",
    "sg:phone":"+32 2 736 03 07",
    "sg:postcode":"1150",
    "sg:province":"Bruxelles-Capitale",
    "wof:name":"Littera Graphics",
    "wof:placetype":"venue"
},
  "geometry": {"coordinates":[4.4092907906,50.8367004395],"type":"Point"}
}