{
  "type": "Feature",
  "properties": {
    "addr:full":"Burg. L. Pussemierstraat 192 Eeklo Oost-Vlaanderen 9900",
    "addr:housenumber":"192",
    "addr:postcode":"9900",
    "addr:street":"Burg.;Pussemierstraat",
    "iso:country":"BE",
    "sg:address":"Burg. L. Pussemierstraat 192",
    "sg:city":"Eeklo",
    "sg:orig_category":"Sportclubs",
    "sg:phone":"+32 9 377 61 39",
    "sg:postcode":"9900",
    "sg:province":"Oost-Vlaanderen",
    "wof:name":"Wielercomit\u00c9 Eeklo",
    "wof:placetype":"venue"
},
  "geometry": {"coordinates":[3.5771679878,51.1820220947],"type":"Point"}
}