{
  "type": "Feature",
  "properties": {
    "addr:full":"Rue Saint-roch 28 Neufch\u00c2teau Luxembourg 6840",
    "addr:housenumber":"28",
    "addr:postcode":"6840",
    "addr:street":"Rue Saint-Roch",
    "iso:country":"BE",
    "sg:address":"Rue Saint-roch 28",
    "sg:city":"Neufch\u00c2teau",
    "sg:orig_category":"Librairies. Journaux. Ordinateurs and \u00e9quipement informatique",
    "sg:phone":"+32 61 27 15 12",
    "sg:postcode":"6840",
    "sg:province":"Luxembourg",
    "wof:name":"Maison Oxyg\u00c8ne",
    "wof:placetype":"venue"
},
  "geometry": {"coordinates":[5.4343671799,49.8431167603],"type":"Point"}
}