{
  "type": "Feature",
  "properties": {
    "addr:full":"Rue De Herve 17 Herve (battice) Li\u00e8ge 4651",
    "addr:housenumber":"17",
    "addr:postcode":"4651",
    "addr:street":"Rue De Herve",
    "iso:country":"BE",
    "sg:address":"Rue De Herve 17",
    "sg:city":"Herve (battice)",
    "sg:classifiers":[
        {
            "category":"Social Services",
            "type":"Services"
        }
    ],
    "sg:phone":"+32 87 68 16 62",
    "sg:postcode":"4651",
    "sg:province":"Li\u00e8ge",
    "wof:name":"Hall (le) Asbl",
    "wof:placetype":"venue"
},
  "geometry": {"coordinates":[5.8133201599,50.6472396851],"type":"Point"}
}