{
  "type": "Feature",
  "properties": {
    "iso:country":"BE",
    "sg:address":"Grote Kruisstraat 60-66",
    "sg:city":"Menen (lauwe)",
    "sg:classifiers":[
        {
            "category":"Real Estate",
            "subcategory":"Developer",
            "type":"Services"
        }
    ],
    "sg:phone":"+32 56 41 90 59",
    "sg:postcode":"8930",
    "sg:province":"West-Vlaanderen",
    "sg:tags":[
        "project"
    ],
    "wof:name":"Polyvalent Bvba",
    "wof:placetype":"venue"
},
  "geometry": {"coordinates":[3.1209149361,50.7961845398],"type":"Point"}
}