{
  "type": "Feature",
  "properties": {
    "addr:full":"Grand'place 25b1 Binche Hainaut 7130",
    "addr:housenumber":"25b1",
    "addr:postcode":"7130",
    "addr:street":"Grand'Place",
    "iso:country":"BE",
    "sg:address":"Grand'place 25b1",
    "sg:city":"Binche",
    "sg:orig_category":"Textiel",
    "sg:phone":"+32 64 36 63 76",
    "sg:postcode":"7130",
    "sg:province":"Hainaut",
    "wof:name":"Centre De La Dentelle",
    "wof:placetype":"venue"
},
  "geometry": {"coordinates":[4.1649107933,50.4107818604],"type":"Point"}
}