{
  "type": "Feature",
  "properties": {
    "addr:full":"Oscar Van Goidtsnovenln 29 Ukkel/uccle Bruxelles-Capitale 1180",
    "addr:housenumber":"29",
    "addr:postcode":"1180",
    "addr:street":"Oscar Van Goidtsnovenln;/",
    "iso:country":"BE",
    "sg:address":"Oscar Van Goidtsnovenln 29",
    "sg:city":"Ukkel/uccle",
    "sg:orig_category":"Installatie van houten of kunststof schrijnwerk",
    "sg:phone":"+32 2 344 25 66",
    "sg:postcode":"1180",
    "sg:province":"Bruxelles-Capitale",
    "wof:name":"Fe. Thoen & Fils",
    "wof:placetype":"venue"
},
  "geometry": {"coordinates":[4.3381791115,50.8145523071],"type":"Point"}
}