{
  "type": "Feature",
  "properties": {
    "iso:country":"BE",
    "sg:address":"Rue Des Belneux",
    "sg:city":"Mons",
    "sg:classifiers":[
        {
            "category":"Community Center",
            "type":"Public Place"
        }
    ],
    "sg:phone":"+32 69 34 88 01",
    "sg:postcode":"7000",
    "sg:province":"Hainaut",
    "sg:tags":[
        "medical"
    ],
    "wof:name":"Car D'or (le)",
    "wof:placetype":"venue"
},
  "geometry": {"coordinates":[3.9552609921,50.4544029236],"type":"Point"}
}