{
  "type": "Feature",
  "properties": {
    "iso:country":"BE",
    "sg:address":"Haachtsesteenweg 409",
    "sg:city":"Kampenhout",
    "sg:orig_category":"Installatie van houten of kunststof schrijnwerk",
    "sg:phone":"+32 16 65 72 03",
    "sg:postcode":"1910",
    "sg:province":"Vlaams-Brabant",
    "wof:name":"Merantiplast",
    "wof:placetype":"venue"
},
  "geometry": {"coordinates":[4.5674290657,50.9446411133],"type":"Point"}
}