{
  "type": "Feature",
  "properties": {
    "addr:full":"Rue Des Villas 129 Seraing Li\u00e8ge 4100",
    "addr:housenumber":"129",
    "addr:postcode":"4100",
    "addr:street":"Rue Des Villas",
    "iso:country":"BE",
    "sg:address":"Rue Des Villas 129",
    "sg:city":"Seraing",
    "sg:classifiers":[
        {
            "category":"Health Services",
            "subcategory":"Doctor",
            "type":"Services"
        }
    ],
    "sg:phone":"+32 497 19 34 21",
    "sg:postcode":"4100",
    "sg:province":"Li\u00e8ge",
    "sg:tags":[
        "psychotherapist",
        "psychoanalyst"
    ],
    "wof:name":"Geuns J",
    "wof:placetype":"venue"
},
  "geometry": {"coordinates":[5.5093560219,50.5815238953],"type":"Point"}
}