{
  "type": "Feature",
  "properties": {
    "addr:full":"Industriezone Berkenhoek Sint-katelijne-waver Antwerpen 2861",
    "addr:postcode":"2861",
    "addr:street":"Industriezone Berkenhoek",
    "iso:country":"BE",
    "sg:address":"Industriezone Berkenhoek",
    "sg:city":"Sint-katelijne-waver",
    "sg:orig_category":"Herstellingen and onderhoud van auto's Verhuur voertuigen behalve auto's Voertuigen",
    "sg:phone":"+32 15 76 13 00",
    "sg:postcode":"2861",
    "sg:province":"Antwerpen",
    "wof:name":"Flitecar-fleurette",
    "wof:placetype":"venue"
},
  "geometry": {"coordinates":[4.5803399086,51.0623168945],"type":"Point"}
}