{
  "type": "Feature",
  "properties": {
    "iso:country":"BE",
    "sg:address":"Place Georges Brugmann 12b1",
    "sg:city":"Elsene/ixelles",
    "sg:orig_category":"Avocats and conseillers juridiques",
    "sg:phone":"+32 2 345 19 92",
    "sg:postcode":"1050",
    "sg:province":"Bruxelles-Capitale",
    "wof:name":"Th. De Moor",
    "wof:placetype":"venue"
},
  "geometry": {"coordinates":[4.3539099693,50.8173904419],"type":"Point"}
}