{
  "type": "Feature",
  "properties": {
    "addr:full":"Rue De Gilly 81 Chatelet Hainaut 6200",
    "addr:housenumber":"81",
    "addr:postcode":"6200",
    "addr:street":"Rue De Gilly;Hainaut",
    "iso:country":"BE",
    "sg:address":"Rue De Gilly 81",
    "sg:city":"Chatelet",
    "sg:classifiers":[
        {
            "category":"Personal",
            "subcategory":"Beauty Salon",
            "type":"Services"
        }
    ],
    "sg:phone":"+32 71 38 64 35",
    "sg:postcode":"6200",
    "sg:province":"Hainaut",
    "sg:tags":[
        "de",
        "coiffure"
    ],
    "wof:name":"Coiffure M.b.",
    "wof:placetype":"venue"
},
  "geometry": {"coordinates":[4.5236740112,50.4041366577],"type":"Point"}
}