{
  "type": "Feature",
  "properties": {
    "iso:country":"BE",
    "sg:address":"Place Verte 11",
    "sg:city":"Verviers",
    "sg:orig_category":"Cosmetica and toiletartikelen Drogisterijen",
    "sg:phone":"+32 87 33 79 76",
    "sg:postcode":"4800",
    "sg:province":"Li\u00e8ge",
    "wof:name":"Di",
    "wof:placetype":"venue"
},
  "geometry": {"coordinates":[5.8611760139,50.5922012329],"type":"Point"}
}