{
  "type": "Feature",
  "properties": {
    "addr:full":"Champs 783 Bertogne (groot) Luxembourg 6688",
    "addr:housenumber":"783",
    "addr:postcode":"6688",
    "addr:street":"Bertogne Groot Luxembourg",
    "iso:country":"BE",
    "sg:address":"Champs 783",
    "sg:city":"Bertogne (groot)",
    "sg:orig_category":"Kapsalons",
    "sg:phone":"+32 61 21 69 20",
    "sg:postcode":"6688",
    "sg:province":"Luxembourg",
    "wof:name":"Bleret A",
    "wof:placetype":"venue"
},
  "geometry": {"coordinates":[5.6690778732,50.0387840271],"type":"Point"}
}