{
  "type": "Feature",
  "properties": {
    "addr:full":"Markt 3 Assenede Oost-Vlaanderen 9960",
    "addr:housenumber":"3",
    "addr:postcode":"9960",
    "addr:street":"Markt",
    "iso:country":"BE",
    "sg:address":"Markt 3",
    "sg:city":"Assenede",
    "sg:classifiers":[
        {
            "category":"Bars & Pubs",
            "type":"Food & Drink"
        }
    ],
    "sg:phone":"+32 9 344 48 39",
    "sg:postcode":"9960",
    "sg:province":"Oost-Vlaanderen",
    "wof:name":"St-sebastiaan",
    "wof:placetype":"venue"
},
  "geometry": {"coordinates":[3.7535719872,51.2273521423],"type":"Point"}
}