{
  "type": "Feature",
  "properties": {
    "addr:full":"Rue De Burhaimont 69 Bertrix Luxembourg 6880",
    "addr:housenumber":"69",
    "addr:postcode":"6880",
    "addr:street":"Rue De Burhaimont",
    "iso:country":"BE",
    "sg:address":"Rue De Burhaimont 69",
    "sg:city":"Bertrix",
    "sg:classifiers":[
        {
            "category":"Restaurant",
            "type":"Food & Drink"
        }
    ],
    "sg:phone":"+32 61 41 47 17",
    "sg:postcode":"6880",
    "sg:province":"Luxembourg",
    "sg:tags":[
        "organisation",
        "de",
        "f\u00eates",
        "catering"
    ],
    "wof:name":"Le P\u00c9ch\u00c9 Mignon",
    "wof:placetype":"venue"
},
  "geometry": {"coordinates":[5.2528119087,49.8621673584],"type":"Point"}
}