{
  "type": "Feature",
  "properties": {
    "addr:full":"Dorpsstraat 62 Beveren Oost-Vlaanderen 9130",
    "addr:housenumber":"62",
    "addr:postcode":"9130",
    "addr:street":"Dorpsstraat",
    "iso:country":"BE",
    "sg:address":"Dorpsstraat 62",
    "sg:city":"Beveren",
    "sg:orig_category":"Kapsalons",
    "sg:phone":"+32 3 773 49 51",
    "sg:postcode":"9130",
    "sg:province":"Oost-Vlaanderen",
    "wof:name":"Christine",
    "wof:placetype":"venue"
},
  "geometry": {"coordinates":[4.1741428375,51.2915763855],"type":"Point"}
}