{
  "type": "Feature",
  "properties": {
    "addr:full":"Rue Franklin Roosevelt 6 Neufch\u00e2teau Luxembourg 6840",
    "addr:housenumber":"6",
    "addr:postcode":"6840",
    "addr:street":"Rue Franklin Roosevelt",
    "iso:country":"BE",
    "sg:address":"Rue Franklin Roosevelt 6",
    "sg:city":"Neufch\u00e2teau",
    "sg:classifiers":[
        {
            "category":"Bakery",
            "type":"Food & Drink"
        }
    ],
    "sg:phone":"+32 61 27 72 17",
    "sg:postcode":"6840",
    "sg:province":"Luxembourg",
    "sg:tags":[
        "confectioner",
        "baker"
    ],
    "wof:name":"Delices Chestrolais (aux)",
    "wof:placetype":"venue"
},
  "geometry": {"coordinates":[5.4351201057,49.8406677246],"type":"Point"}
}