{
  "type": "Feature",
  "properties": {
    "iso:country":"BE",
    "sg:address":"Scheldekant 12",
    "sg:city":"Destelbergen",
    "sg:orig_category":"Architectes",
    "sg:phone":"+32 9 238 38 95",
    "sg:postcode":"9070",
    "sg:province":"Oost-Vlaanderen",
    "wof:name":"Paul De Pue",
    "wof:placetype":"venue"
},
  "geometry": {"coordinates":[3.7933959961,51.0492286682],"type":"Point"}
}