{
  "type": "Feature",
  "properties": {
    "iso:country":"BE",
    "sg:address":"Mierdsedijk 51",
    "sg:city":"Ravels",
    "sg:orig_category":"Eleveurs and marchands de porcs. Eleveurs de bovins",
    "sg:phone":"+32 14 65 72 24",
    "sg:postcode":"2382",
    "sg:province":"Antwerpen",
    "wof:name":"Leo Haagen",
    "wof:placetype":"venue"
},
  "geometry": {"coordinates":[5.041768074,51.4469108582],"type":"Point"}
}