{
  "type": "Feature",
  "properties": {
    "addr:full":"Rue Du Wainage 3 Farciennes Hainaut 6240",
    "addr:housenumber":"3",
    "addr:postcode":"6240",
    "addr:street":"Rue Du Wainage",
    "iso:country":"BE",
    "sg:address":"Rue Du Wainage 3",
    "sg:city":"Farciennes",
    "sg:orig_category":"Entretien and r\u00e9parations de voitures",
    "sg:phone":"+32 71 39 71 26",
    "sg:postcode":"6240",
    "sg:province":"Hainaut",
    "wof:name":"Garage Claudy Verkamer",
    "wof:placetype":"venue"
},
  "geometry": {"coordinates":[4.5302262306,50.4410514832],"type":"Point"}
}