{
  "type": "Feature",
  "properties": {
    "iso:country":"BE",
    "sg:address":"Molenweg 18",
    "sg:city":"Halen",
    "sg:orig_category":"Eleveurs and marchands de porcs",
    "sg:phone":"+32 13 44 16 86",
    "sg:postcode":"3545",
    "sg:province":"Limburg",
    "wof:name":"G Sempels",
    "wof:placetype":"venue"
},
  "geometry": {"coordinates":[5.0788388252,50.9523735046],"type":"Point"}
}