{
  "type": "Feature",
  "properties": {
    "addr:full":"De Keyserlei 50 Antwerpen Antwerpen 2018",
    "addr:housenumber":"50",
    "addr:postcode":"2018",
    "addr:street":"De Keyserlei",
    "iso:country":"BE",
    "sg:address":"De Keyserlei 50",
    "sg:city":"Antwerpen",
    "sg:orig_category":"Dameskledingzaken",
    "sg:phone":"+32 3 234 10 56",
    "sg:postcode":"2018",
    "sg:province":"Antwerpen",
    "wof:name":"Huis Differente",
    "wof:placetype":"venue"
},
  "geometry": {"coordinates":[4.4186530113,51.217376709],"type":"Point"}
}