{
  "type": "Feature",
  "properties": {
    "addr:full":"Dorp-oost 1 Lochristi Oost-Vlaanderen 9080",
    "addr:housenumber":"1",
    "addr:postcode":"9080",
    "addr:street":"Dorp-Oost",
    "iso:country":"BE",
    "sg:address":"Dorp-oost 1",
    "sg:city":"Lochristi",
    "sg:orig_category":"Eclairage et \u00e9quipements du foyer. Biens d'occasion",
    "sg:phone":"+32 9 355 68 84",
    "sg:postcode":"9080",
    "sg:province":"Oost-Vlaanderen",
    "wof:name":"Oxfam Wereldwinkel",
    "wof:placetype":"venue"
},
  "geometry": {"coordinates":[3.8331549168,51.0963516235],"type":"Point"}
}