{
  "type": "Feature",
  "properties": {
    "addr:full":"Borstekouterstraat 81 Zwalm (roborst) Oost-Vlaanderen 9630",
    "addr:housenumber":"81",
    "addr:postcode":"9630",
    "addr:street":"Borstekouterstraat;Roborst Oost-Vlaanderen",
    "iso:country":"BE",
    "sg:address":"Borstekouterstraat 81",
    "sg:city":"Zwalm (roborst)",
    "sg:classifiers":[
        {
            "category":"Personal",
            "subcategory":"Beauty Salon",
            "type":"Services"
        }
    ],
    "sg:phone":"+32 55 49 96 02",
    "sg:postcode":"9630",
    "sg:province":"Oost-Vlaanderen",
    "sg:tags":[
        "lady",
        "-",
        "hairdressing"
    ],
    "wof:name":"Bradt M-j",
    "wof:placetype":"venue"
},
  "geometry": {"coordinates":[3.7535889149,50.8685951233],"type":"Point"}
}