{
  "type": "Feature",
  "properties": {
    "addr:full":"Smisstraat 44 Tervuren Vlaams-Brabant 3080",
    "addr:housenumber":"44",
    "addr:postcode":"3080",
    "addr:street":"Smisstraat",
    "iso:country":"BE",
    "sg:address":"Smisstraat 44",
    "sg:city":"Tervuren",
    "sg:classifiers":[
        {
            "category":"Professional",
            "subcategory":"Advertising",
            "type":"Services"
        }
    ],
    "sg:phone":"+32 2 768 15 07",
    "sg:postcode":"3080",
    "sg:province":"Vlaams-Brabant",
    "sg:tags":[
        "studio"
    ],
    "wof:name":"A-one Consult Bvba",
    "wof:placetype":"venue"
},
  "geometry": {"coordinates":[4.5533518791,50.8338737488],"type":"Point"}
}