{
  "type": "Feature",
  "properties": {
    "addr:full":"Hendrik Baelskaai 40 Oostende West-Vlaanderen 8400",
    "addr:housenumber":"40",
    "addr:postcode":"8400",
    "iso:country":"BE",
    "sg:address":"Hendrik Baelskaai 40",
    "sg:city":"Oostende",
    "sg:orig_category":"Diepvriesproducten Gh",
    "sg:phone":"+32 59 32 00 07",
    "sg:postcode":"8400",
    "sg:province":"West-Vlaanderen",
    "wof:name":"Everest",
    "wof:placetype":"venue"
},
  "geometry": {"coordinates":[2.9372389317,51.2315444946],"type":"Point"}
}