{
  "type": "Feature",
  "properties": {
    "iso:country":"BE",
    "sg:address":"Chauss\u00e9e De Renaix 39bis",
    "sg:city":"Tournai",
    "sg:classifiers":[
        {
            "category":"Building & Trades",
            "subcategory":"Equipment Rental",
            "type":"Services"
        }
    ],
    "sg:phone":"+32 69 84 34 15",
    "sg:postcode":"7500",
    "sg:province":"Hainaut",
    "sg:tags":[
        "sound",
        "-",
        "system"
    ],
    "wof:name":"Jafo Multi-services",
    "wof:placetype":"venue"
},
  "geometry": {"coordinates":[3.4044480324,50.6129341125],"type":"Point"}
}