{
  "type": "Feature",
  "properties": {
    "addr:full":"Rue Des Rentiers 176 La Louvi\u00e8re Hainaut 7100",
    "addr:housenumber":"176",
    "addr:postcode":"7100",
    "addr:street":"Rue Des Rentiers",
    "iso:country":"BE",
    "sg:address":"Rue Des Rentiers 176",
    "sg:city":"La Louvi\u00e8re",
    "sg:classifiers":[
        {
            "category":"Utilities",
            "subcategory":"Recycling",
            "type":"Services"
        }
    ],
    "sg:phone":"+32 64 23 60 40",
    "sg:postcode":"7100",
    "sg:province":"Hainaut",
    "sg:tags":[
        "rubbish",
        "removal"
    ],
    "wof:name":"Decover",
    "wof:placetype":"venue"
},
  "geometry": {"coordinates":[4.2036399841,50.4747886658],"type":"Point"}
}