{
  "type": "Feature",
  "properties": {
    "addr:full":"Les Taillisses 9 Fl\u00e9malle Li\u00e8ge 4400",
    "addr:housenumber":"9",
    "addr:postcode":"4400",
    "iso:country":"BE",
    "sg:address":"Les Taillisses 9",
    "sg:city":"Fl\u00e9malle",
    "sg:classifiers":[
        {
            "category":"Autos & Motor Vehicles",
            "subcategory":"Auto Supplies",
            "type":"Retail Goods"
        }
    ],
    "sg:phone":"+32 4 273 01 88",
    "sg:postcode":"4400",
    "sg:province":"Li\u00e8ge",
    "sg:tags":[
        "hydraulics"
    ],
    "wof:name":"Vanderweeghde Ets",
    "wof:placetype":"venue"
},
  "geometry": {"coordinates":[5.4450440407,50.597076416],"type":"Point"}
}