{
  "type": "Feature",
  "properties": {
    "addr:full":"Nattehofstraat 31 Mechelen Antwerpen 2800",
    "addr:housenumber":"31",
    "addr:postcode":"2800",
    "addr:street":"Nattehofstraat",
    "iso:country":"BE",
    "sg:address":"Nattehofstraat 31",
    "sg:city":"Mechelen",
    "sg:classifiers":[
        {
            "category":"Health Services",
            "subcategory":"Health Practitioner",
            "type":"Services"
        }
    ],
    "sg:phone":"+32 15 33 60 33",
    "sg:postcode":"2800",
    "sg:province":"Antwerpen",
    "sg:tags":[
        "physiotherapist"
    ],
    "wof:name":"Piscaer Riet",
    "wof:placetype":"venue"
},
  "geometry": {"coordinates":[4.4649782181,51.0274925232],"type":"Point"}
}