{
  "type": "Feature",
  "properties": {
    "iso:country":"BE",
    "sg:address":"Rue Du Parc Industriel 28",
    "sg:city":"Marche-en-famenne",
    "sg:orig_category":"Installation de menuiserie en bois and plastique",
    "sg:phone":"+32 84 31 39 04",
    "sg:postcode":"6900",
    "sg:province":"Luxembourg",
    "wof:name":"Lobet Dominique",
    "wof:placetype":"venue"
},
  "geometry": {"coordinates":[5.3259921074,50.2206802368],"type":"Point"}
}