{
  "type": "Feature",
  "properties": {
    "addr:full":"Edgard Tinelstraat 24 Sint-lievens-houtem Oost-Vlaanderen 9520",
    "addr:housenumber":"24",
    "addr:postcode":"9520",
    "addr:street":"Edgard Tinelstraat;Oost-Vlaanderen",
    "iso:country":"BE",
    "sg:address":"Edgard Tinelstraat 24",
    "sg:city":"Sint-lievens-houtem",
    "sg:classifiers":[
        {
            "category":"Shopping",
            "subcategory":"Baby Store",
            "type":"Retail Goods"
        }
    ],
    "sg:phone":"+32 53 62 90 28",
    "sg:postcode":"9520",
    "sg:province":"Oost-Vlaanderen",
    "sg:tags":[
        "-",
        "accessory"
    ],
    "wof:name":"Duimelotte",
    "wof:placetype":"venue"
},
  "geometry": {"coordinates":[3.860145092,50.9199485779],"type":"Point"}
}