{
  "type": "Feature",
  "properties": {
    "addr:full":"Rue De Mons 80 Charleroi Hainaut 6000",
    "addr:housenumber":"80",
    "addr:postcode":"6000",
    "addr:street":"Rue De Mons;Hainaut",
    "iso:country":"BE",
    "sg:address":"Rue De Mons 80",
    "sg:city":"Charleroi",
    "sg:classifiers":[
        {
            "category":"Retail",
            "subcategory":"Auto Repair",
            "type":"Services"
        }
    ],
    "sg:phone":"+32 71 20 22 60",
    "sg:postcode":"6000",
    "sg:province":"Hainaut",
    "sg:tags":[
        "automobile-body"
    ],
    "wof:name":"Louyet Sa",
    "wof:placetype":"venue"
},
  "geometry": {"coordinates":[4.4330420494,50.4121742249],"type":"Point"}
}