{
  "type": "Feature",
  "properties": {
    "addr:full":"Rue Des Enfers 1 Brugelette (attre) Hainaut 7941",
    "addr:housenumber":"1",
    "addr:postcode":"7941",
    "addr:street":"Rue Des Enfers",
    "iso:country":"BE",
    "sg:address":"Rue Des Enfers 1",
    "sg:city":"Brugelette (attre)",
    "sg:classifiers":[
        {
            "category":"Retail",
            "subcategory":"Auto Repair",
            "type":"Services"
        }
    ],
    "sg:phone":"+32 68 45 63 69",
    "sg:postcode":"7941",
    "sg:province":"Hainaut",
    "sg:tags":[
        "breakdown",
        "automobile",
        "-",
        "recovery"
    ],
    "wof:name":"Willain E",
    "wof:placetype":"venue"
},
  "geometry": {"coordinates":[3.8322930336,50.6004524231],"type":"Point"}
}