{
  "type": "Feature",
  "properties": {
    "iso:country":"BE",
    "sg:address":"Olmenstraat 12",
    "sg:city":"Sint-niklaas",
    "sg:orig_category":"Traitements param\u00e9dicaux",
    "sg:phone":"+32 3 777 94 17",
    "sg:postcode":"9100",
    "sg:province":"Oost-Vlaanderen",
    "wof:name":"A. Van Puymbroeck",
    "wof:placetype":"venue"
},
  "geometry": {"coordinates":[4.1524209976,51.1848640442],"type":"Point"}
}