{
  "type": "Feature",
  "properties": {
    "iso:country":"BE",
    "sg:address":"Rue Henri Neuman 1",
    "sg:city":"Braine-le-comte",
    "sg:classifiers":[
        {
            "category":"Cafe",
            "type":"Food & Drink"
        }
    ],
    "sg:phone":"+32 67 55 71 23",
    "sg:postcode":"7090",
    "sg:province":"Hainaut",
    "sg:tags":[
        "snack-bars"
    ],
    "wof:name":"Pick Quick",
    "wof:placetype":"venue"
},
  "geometry": {"coordinates":[4.1372799873,50.6087913513],"type":"Point"}
}