{
  "type": "Feature",
  "properties": {
    "addr:full":"Rue Les Longchamps 5 Bouillon (noirefontaine) Luxembourg 6831",
    "addr:housenumber":"5",
    "addr:postcode":"6831",
    "addr:street":"Rue Les Longchamps",
    "iso:country":"BE",
    "sg:address":"Rue Les Longchamps 5",
    "sg:city":"Bouillon (noirefontaine)",
    "sg:classifiers":[
        {
            "category":"Building & Trades",
            "subcategory":"Pest Control",
            "type":"Services"
        }
    ],
    "sg:phone":"+32 61 46 76 00",
    "sg:postcode":"6831",
    "sg:province":"Luxembourg",
    "sg:tags":[
        "painting",
        "contractor"
    ],
    "wof:name":"Billiaux R",
    "wof:placetype":"venue"
},
  "geometry": {"coordinates":[5.0937948227,49.8202438354],"type":"Point"}
}