{
  "type": "Feature",
  "properties": {
    "addr:full":"Boelare 59 Eeklo Oost-Vlaanderen 9900",
    "addr:housenumber":"59",
    "addr:postcode":"9900",
    "addr:street":"Boelare",
    "iso:country":"BE",
    "sg:address":"Boelare 59",
    "sg:city":"Eeklo",
    "sg:classifiers":[
        {
            "category":"Shopping",
            "subcategory":"Beauty & Cosmetics",
            "type":"Retail Goods"
        }
    ],
    "sg:phone":"+32 9 377 34 54",
    "sg:postcode":"9900",
    "sg:province":"Oost-Vlaanderen",
    "sg:tags":[
        "-",
        "perfumery"
    ],
    "wof:name":"Carin Parfumerie",
    "wof:placetype":"venue"
},
  "geometry": {"coordinates":[3.5657699108,51.1870193481],"type":"Point"}
}