{
  "type": "Feature",
  "properties": {
    "addr:full":"Gravin M. D'alcantaraln 120 Kaprijke (groot) Oost-Vlaanderen 9971",
    "addr:housenumber":"120",
    "addr:postcode":"9971",
    "addr:street":"Gravin M. D'Alcantaraln;Groot Oost-Vlaanderen",
    "iso:country":"BE",
    "sg:address":"Gravin M. D'alcantaraln 120",
    "sg:city":"Kaprijke (groot)",
    "sg:orig_category":"Fleurs and plantes",
    "sg:phone":"+32 9 378 08 78",
    "sg:postcode":"9971",
    "sg:province":"Oost-Vlaanderen",
    "wof:name":"Cleome",
    "wof:placetype":"venue"
},
  "geometry": {"coordinates":[3.6304900646,51.1943702698],"type":"Point"}
}