{
  "type": "Feature",
  "properties": {
    "iso:country":"BE",
    "sg:address":"Gaston Gheldolflaan 18",
    "sg:city":"Gent",
    "sg:orig_category":"Rusthuizen and serviceflats",
    "sg:phone":"+32 9 226 92 92",
    "sg:postcode":"9030",
    "sg:province":"Oost-Vlaanderen",
    "wof:name":"Pension Zurich",
    "wof:placetype":"venue"
},
  "geometry": {"coordinates":[3.6904439926,51.0726203918],"type":"Point"}
}