{
  "type": "Feature",
  "properties": {
    "iso:country":"BE",
    "sg:address":"Steenovenstraat 9",
    "sg:city":"Malle",
    "sg:orig_category":"Etalage- and showroomontwerpers",
    "sg:phone":"+32 3 312 25 91",
    "sg:postcode":"2390",
    "sg:province":"Antwerpen",
    "wof:name":"Kathelijne Huypens",
    "wof:placetype":"venue"
},
  "geometry": {"coordinates":[4.708275795,51.3065490723],"type":"Point"}
}