{
  "type": "Feature",
  "properties": {
    "iso:country":"BE",
    "sg:address":"Persijzerstraat 29",
    "sg:city":"Lochristi (zaffelare)",
    "sg:classifiers":[
        {
            "category":"Communications",
            "type":"Services"
        }
    ],
    "sg:phone":"+32 9 326 06 01",
    "sg:postcode":"9080",
    "sg:province":"Oost-Vlaanderen",
    "sg:tags":[
        "translator"
    ],
    "wof:name":"Foket N",
    "wof:placetype":"venue"
},
  "geometry": {"coordinates":[3.8859570026,51.1271858215],"type":"Point"}
}