{
  "type": "Feature",
  "properties": {
    "addr:full":"Antwerpsesteenweg 22 Gent Oost-Vlaanderen 9000",
    "addr:housenumber":"22",
    "addr:postcode":"9000",
    "addr:street":"Antwerpsesteenweg;Oost-Vlaanderen",
    "iso:country":"BE",
    "sg:address":"Antwerpsesteenweg 22",
    "sg:city":"Gent",
    "sg:orig_category":"Benzinestations and brandstoffen",
    "sg:phone":"+32 9 228 17 25",
    "sg:postcode":"9000",
    "sg:province":"Oost-Vlaanderen",
    "wof:name":"William Thaler",
    "wof:placetype":"venue"
},
  "geometry": {"coordinates":[3.7419650555,51.0576972961],"type":"Point"}
}