{
  "type": "Feature",
  "properties": {
    "iso:country":"BE",
    "sg:address":"Tulpenstraat 30",
    "sg:city":"Meeuwen-gruitrode",
    "sg:orig_category":"Woningbouw",
    "sg:phone":"+32 11 79 21 82",
    "sg:postcode":"3670",
    "sg:province":"Limburg",
    "wof:name":"Bouwonderneming Haex",
    "wof:placetype":"venue"
},
  "geometry": {"coordinates":[5.5243902206,51.0884094238],"type":"Point"}
}