{
  "type": "Feature",
  "properties": {
    "addr:full":"Leischoot 4 Zomergem Oost-Vlaanderen 9931",
    "addr:housenumber":"4",
    "addr:postcode":"9931",
    "addr:street":"Leischoot",
    "iso:country":"BE",
    "sg:address":"Leischoot 4",
    "sg:city":"Zomergem",
    "sg:orig_category":"Rundveehouders Varkenskwekers",
    "sg:phone":"+32 9 377 16 27",
    "sg:postcode":"9931",
    "sg:province":"Oost-Vlaanderen",
    "wof:name":"Silvain Geirnaert",
    "wof:placetype":"venue"
},
  "geometry": {"coordinates":[3.5321359634,51.1467704773],"type":"Point"}
}