{
  "type": "Feature",
  "properties": {
    "iso:country":"BE",
    "sg:address":"K.m.-hendrikalaan 111",
    "sg:city":"Vorst/forest",
    "sg:orig_category":"Binnenhuisarchitecten",
    "sg:phone":"+32 2 344 73 94",
    "sg:postcode":"1190",
    "sg:province":"Bruxelles-Capitale",
    "wof:name":"Sonia Cantillon",
    "wof:placetype":"venue"
},
  "geometry": {"coordinates":[4.3360519409,50.821434021],"type":"Point"}
}