{
  "type": "Feature",
  "properties": {
    "iso:country":"BE",
    "sg:address":"Chauss\u00c9e De Haecht 1281",
    "sg:city":"Brussel/bruxelles",
    "sg:orig_category":"Entretien et r\u00e9parations de v\u00e9hicules \u00e0 domicile. R\u00e9cup\u00e9ration de mati\u00e8res m\u00e9talliques recyclables a",
    "sg:phone":"+32 2 216 57 18",
    "sg:postcode":"1130",
    "sg:province":"Bruxelles-Capitale",
    "wof:name":"Garage De Cooman",
    "wof:placetype":"venue"
},
  "geometry": {"coordinates":[4.4149141312,50.8808021545],"type":"Point"}
}