{
  "type": "Feature",
  "properties": {
    "iso:country":"BE",
    "sg:address":"Hofstraat 121",
    "sg:city":"Dendermonde (oudegem)",
    "sg:classifiers":[
        {
            "category":"Building & Trades",
            "subcategory":"Electrical",
            "type":"Services"
        }
    ],
    "sg:phone":"+32 52 21 55 48",
    "sg:postcode":"9200",
    "sg:province":"Oost-Vlaanderen",
    "sg:tags":[
        "-",
        "electric",
        "contractor"
    ],
    "wof:name":"Elektrotechniek Van Den Berghe",
    "wof:placetype":"venue"
},
  "geometry": {"coordinates":[4.050924778,51.022644043],"type":"Point"}
}