{
  "type": "Feature",
  "properties": {
    "addr:full":"Place De Saint-sauveur 1b2 Frasnes-lez-anvaing Hainaut 7912",
    "addr:housenumber":"1b2",
    "addr:postcode":"7912",
    "addr:street":"Place De Saint-Sauveur",
    "iso:country":"BE",
    "sg:address":"Place De Saint-sauveur 1b2",
    "sg:city":"Frasnes-lez-anvaing",
    "sg:orig_category":"Artsen and specialisten",
    "sg:phone":"+32 69 76 92 82",
    "sg:postcode":"7912",
    "sg:province":"Hainaut",
    "wof:name":"Alain Brassart",
    "wof:placetype":"venue"
},
  "geometry": {"coordinates":[3.5987689495,50.7061424255],"type":"Point"}
}