{
  "type": "Feature",
  "properties": {
    "addr:full":"Kolderbosstraat 6 Genk Limburg 3600",
    "addr:housenumber":"6",
    "addr:postcode":"3600",
    "addr:street":"Kolderbosstraat",
    "iso:country":"BE",
    "sg:address":"Kolderbosstraat 6",
    "sg:city":"Genk",
    "sg:orig_category":"Sportclubs",
    "sg:phone":"+32 89 35 89 23",
    "sg:postcode":"3600",
    "sg:province":"Limburg",
    "wof:name":"Sei Bu Kan",
    "wof:placetype":"venue"
},
  "geometry": {"coordinates":[5.5186500549,50.9511909485],"type":"Point"}
}