{
  "type": "Feature",
  "properties": {
    "iso:country":"BE",
    "sg:address":"Boulevard Du Midi 81-82",
    "sg:city":"Bruxelles",
    "sg:classifiers":[
        {
            "category":"Bars & Pubs",
            "type":"Food & Drink"
        }
    ],
    "sg:phone":"+32 2 512 26 67",
    "sg:postcode":"1000",
    "sg:province":"Bruxelles-Capitale",
    "wof:name":"Aux Deux Amis Sprl",
    "wof:placetype":"venue"
},
  "geometry": {"coordinates":[4.3417081833,50.8383789062],"type":"Point"}
}