{
  "type": "Feature",
  "properties": {
    "addr:full":"Heygraben 12 Kelmis/la Calamine Li\u00e8ge 4720",
    "addr:housenumber":"12",
    "addr:postcode":"4720",
    "addr:street":"Heygraben",
    "iso:country":"BE",
    "sg:address":"Heygraben 12",
    "sg:city":"Kelmis/la Calamine",
    "sg:orig_category":"Belastingconsulenten Diverse juridische dienstverlening",
    "sg:phone":"+32 87 65 76 18",
    "sg:postcode":"4720",
    "sg:province":"Li\u00e8ge",
    "wof:name":"R.w. Consult",
    "wof:placetype":"venue"
},
  "geometry": {"coordinates":[6.0171527863,50.7187995911],"type":"Point"}
}