{
  "type": "Feature",
  "properties": {
    "addr:full":"Rue Du Camp 14 Bruxelles Bruxelles-Capitale 1130",
    "addr:housenumber":"14",
    "addr:postcode":"1130",
    "addr:street":"Rue Du Camp",
    "iso:country":"BE",
    "sg:address":"Rue Du Camp 14",
    "sg:city":"Bruxelles",
    "sg:classifiers":[
        {
            "category":"Professional",
            "subcategory":"Management & Consulting",
            "type":"Services"
        }
    ],
    "sg:phone":"+32 2 215 09 60",
    "sg:postcode":"1130",
    "sg:province":"Bruxelles-Capitale",
    "sg:tags":[
        "consultant"
    ],
    "wof:name":"Goin Sprl",
    "wof:placetype":"venue"
},
  "geometry": {"coordinates":[4.4144248962,50.8915290833],"type":"Point"}
}