{
  "type": "Feature",
  "properties": {
    "iso:country":"BE",
    "sg:address":"Rue D'en Haut 8",
    "sg:city":"Momignies",
    "sg:orig_category":"Kapsalons",
    "sg:phone":"+32 60 51 18 88",
    "sg:postcode":"6590",
    "sg:province":"Hainaut",
    "wof:name":"Daniel Bajomee",
    "wof:placetype":"venue"
},
  "geometry": {"coordinates":[4.2241849899,50.0360145569],"type":"Point"}
}