{
  "type": "Feature",
  "properties": {
    "iso:country":"BE",
    "sg:address":"Rue De Berneau 93",
    "sg:city":"Vis\u00c9",
    "sg:orig_category":"V\u00e9t\u00e9rinaires",
    "sg:phone":"+32 4 374 83 00",
    "sg:postcode":"4600",
    "sg:province":"Li\u00e8ge",
    "wof:name":"Clinique V\u00c9t\u00c9rinaire",
    "wof:placetype":"venue"
},
  "geometry": {"coordinates":[5.7143769264,50.7393569946],"type":"Point"}
}