{
  "type": "Feature",
  "properties": {
    "addr:full":"Kouter 109-111 Deinze Oost-Vlaanderen 9800",
    "addr:housenumber":"109-111",
    "addr:postcode":"9800",
    "addr:street":"Kouter",
    "iso:country":"BE",
    "sg:address":"Kouter 109-111",
    "sg:city":"Deinze",
    "sg:classifiers":[
        {
            "category":"Home & Garden",
            "subcategory":"Hardware",
            "type":"Retail Goods"
        }
    ],
    "sg:phone":"+32 9 386 71 99",
    "sg:postcode":"9800",
    "sg:province":"Oost-Vlaanderen",
    "sg:tags":[
        "machine",
        "horticultural"
    ],
    "wof:name":"De Volder M",
    "wof:placetype":"venue"
},
  "geometry": {"coordinates":[3.506814003,50.9902572632],"type":"Point"}
}