{
  "type": "Feature",
  "properties": {
    "iso:country":"BE",
    "sg:address":"Rue Bonne-fortune 3-5",
    "sg:city":"Li\u00e8ge 1",
    "sg:classifiers":[
        {
            "category":"Shopping",
            "subcategory":"Books",
            "type":"Retail Goods"
        }
    ],
    "sg:phone":"+32 4 222 38 17",
    "sg:postcode":"4000",
    "sg:province":"Li\u00e8ge",
    "sg:tags":[
        "antiquarian",
        "trade"
    ],
    "wof:name":"Cadre D'art (le)",
    "wof:placetype":"venue"
},
  "geometry": {"coordinates":[5.5725641251,50.6399002075],"type":"Point"}
}