{
  "type": "Feature",
  "properties": {
    "iso:country":"BE",
    "sg:address":"Henry Fordlaan 7",
    "sg:city":"Genk",
    "sg:orig_category":"Non-Classified Establishments",
    "sg:phone":"+32 89 62 02 60",
    "sg:postcode":"3600",
    "sg:province":"Limburg",
    "wof:name":"Belplas Industries Nv",
    "wof:placetype":"venue"
},
  "geometry": {"coordinates":[5.5116472244,50.9216384888],"type":"Point"}
}