{
  "type": "Feature",
  "properties": {
    "addr:full":"Kwadeweg 4 Evergem Oost-Vlaanderen 9940",
    "addr:housenumber":"4",
    "addr:postcode":"9940",
    "addr:street":"Kwadeweg;Oost-Vlaanderen",
    "iso:country":"BE",
    "sg:address":"Kwadeweg 4",
    "sg:city":"Evergem",
    "sg:orig_category":"Diensten voor huisdieren Huisdieren and benodigdheden Royal Canin",
    "sg:phone":"+32 9 253 62 00",
    "sg:postcode":"9940",
    "sg:province":"Oost-Vlaanderen",
    "wof:name":"De Zaadwinkel",
    "wof:placetype":"venue"
},
  "geometry": {"coordinates":[3.6990959644,51.1110191345],"type":"Point"}
}