{
  "type": "Feature",
  "properties": {
    "iso:country":"BE",
    "sg:address":"Rue Du Tissage 4",
    "sg:city":"Mouscron",
    "sg:classifiers":[
        {
            "category":"Government",
            "subcategory":"Fire Station",
            "type":"Public Place"
        }
    ],
    "sg:phone":"+32 56 85 63 56",
    "sg:postcode":"7700",
    "sg:province":"Hainaut",
    "sg:tags":[
        "extraction",
        "gas",
        "system",
        "smoke"
    ],
    "wof:name":"Bic Group",
    "wof:placetype":"venue"
},
  "geometry": {"coordinates":[3.2480919361,50.7536735535],"type":"Point"}
}