{
  "type": "Feature",
  "properties": {
    "iso:country":"BE",
    "sg:address":"Ballewijerweg 24bb",
    "sg:city":"Zonhoven",
    "sg:orig_category":"Charpentes and couvertures",
    "sg:phone":"+32 11 81 63 44",
    "sg:postcode":"3520",
    "sg:province":"Limburg",
    "wof:name":"Kelbo",
    "wof:placetype":"venue"
},
  "geometry": {"coordinates":[5.3972101212,50.9893684387],"type":"Point"}
}