{
  "type": "Feature",
  "properties": {
    "addr:full":"Sinjorendreef 9 Zoersel Antwerpen 2980",
    "addr:housenumber":"9",
    "addr:postcode":"2980",
    "addr:street":"Sinjorendreef",
    "iso:country":"BE",
    "sg:address":"Sinjorendreef 9",
    "sg:city":"Zoersel",
    "sg:classifiers":[
        {
            "category":"Home & Garden",
            "subcategory":"Kitchen Supply",
            "type":"Retail Goods"
        }
    ],
    "sg:phone":"+32 3 385 39 44",
    "sg:postcode":"2980",
    "sg:province":"Antwerpen",
    "sg:tags":[
        "installation"
    ],
    "wof:name":"Kokkeurel",
    "wof:placetype":"venue"
},
  "geometry": {"coordinates":[4.6642951965,51.2631874084],"type":"Point"}
}