{
  "type": "Feature",
  "properties": {
    "addr:full":"Zavelstraat 27 Lubbeek (pellenberg) Vlaams-Brabant 3212",
    "addr:housenumber":"27",
    "addr:postcode":"3212",
    "addr:street":"Zavelstraat",
    "iso:country":"BE",
    "sg:address":"Zavelstraat 27",
    "sg:city":"Lubbeek (pellenberg)",
    "sg:classifiers":[
        {
            "category":"Wholesale",
            "subcategory":"Plants",
            "type":"Manufacturing & Wholesale Goods"
        }
    ],
    "sg:phone":"+32 16 48 01 11",
    "sg:postcode":"3212",
    "sg:province":"Vlaams-Brabant",
    "sg:tags":[
        "whol",
        "flower",
        "-",
        "grower"
    ],
    "wof:name":"Hostas & Zo",
    "wof:placetype":"venue"
},
  "geometry": {"coordinates":[4.7727589607,50.8850479126],"type":"Point"}
}