{
  "type": "Feature",
  "properties": {
    "addr:full":"Rue Grande 10 Messancy Luxembourg 6780",
    "addr:housenumber":"10",
    "addr:postcode":"6780",
    "addr:street":"Rue Grande",
    "iso:country":"BE",
    "sg:address":"Rue Grande 10",
    "sg:city":"Messancy",
    "sg:orig_category":"Fleurs and plantes",
    "sg:phone":"+32 63 38 44 68",
    "sg:postcode":"6780",
    "sg:province":"Luxembourg",
    "wof:name":"Sandflore",
    "wof:placetype":"venue"
},
  "geometry": {"coordinates":[5.8173279762,49.5903968811],"type":"Point"}
}