{
  "type": "Feature",
  "properties": {
    "addr:full":"Diestsebaan 99 Diest (schaffen) Vlaams-Brabant 3290",
    "addr:housenumber":"99",
    "addr:postcode":"3290",
    "addr:street":"Diestsebaan",
    "iso:country":"BE",
    "sg:address":"Diestsebaan 99",
    "sg:city":"Diest (schaffen)",
    "sg:classifiers":[
        {
            "category":"Taxi",
            "type":"Transportation"
        }
    ],
    "sg:phone":"+32 13 31 10 39",
    "sg:postcode":"3290",
    "sg:province":"Vlaams-Brabant",
    "sg:tags":[
        "taxicab"
    ],
    "wof:name":"Boxberger",
    "wof:placetype":"venue"
},
  "geometry": {"coordinates":[5.075674057,50.9973373413],"type":"Point"}
}