{
  "type": "Feature",
  "properties": {
    "addr:full":"Kempenlaan 63 Wommelgem Antwerpen 2160",
    "addr:housenumber":"63",
    "addr:postcode":"2160",
    "addr:street":"Kempenlaan",
    "iso:country":"BE",
    "sg:address":"Kempenlaan 63",
    "sg:city":"Wommelgem",
    "sg:orig_category":"Plaatsen van vloer- and muurbekleding Schilders",
    "sg:phone":"+32 3 353 69 40",
    "sg:postcode":"2160",
    "sg:province":"Antwerpen",
    "wof:name":"Rene Gommers",
    "wof:placetype":"venue"
},
  "geometry": {"coordinates":[4.5352711678,51.1963882446],"type":"Point"}
}