{
  "type": "Feature",
  "properties": {
    "iso:country":"BE",
    "sg:address":"Arthur Goemaerelei 1",
    "sg:city":"Antwerpen",
    "sg:orig_category":"Catering and organisatie van feesten Restaurants Voedingsspeciaalzaken",
    "sg:phone":"+32 3 216 12 28",
    "sg:postcode":"2018",
    "sg:province":"Antwerpen",
    "wof:name":"La Petite Diligence",
    "wof:placetype":"venue"
},
  "geometry": {"coordinates":[4.4035668373,51.1977424622],"type":"Point"}
}