{
  "type": "Feature",
  "properties": {
    "addr:full":"Route Du Condroz 136ba Neupr\u00c9 Li\u00e8ge 4121",
    "addr:postcode":"4121",
    "addr:street":"Route Du Condroz 136Ba",
    "iso:country":"BE",
    "sg:address":"Route Du Condroz 136ba",
    "sg:city":"Neupr\u00c9",
    "sg:orig_category":"Studios photographiques. Equipement photographique",
    "sg:phone":"+32 4 372 12 23",
    "sg:postcode":"4121",
    "sg:province":"Li\u00e8ge",
    "wof:name":"Le Petit Oiseau Va Sortir",
    "wof:placetype":"venue"
},
  "geometry": {"coordinates":[5.4677038193,50.5415077209],"type":"Point"}
}