{
  "type": "Feature",
  "properties": {
    "iso:country":"BE",
    "sg:address":"Daalstraat 118",
    "sg:city":"Grimbergen",
    "sg:orig_category":"Bijouteries and horlogeries",
    "sg:phone":"+32 2 269 54 23",
    "sg:postcode":"1852",
    "sg:province":"Vlaams-Brabant",
    "wof:name":"Hugo Depaepe",
    "wof:placetype":"venue"
},
  "geometry": {"coordinates":[4.3781070709,50.9543762207],"type":"Point"}
}