{
  "type": "Feature",
  "properties": {
    "addr:full":"Avenue Acker 17 Beveren Oost-Vlaanderen 9130",
    "addr:housenumber":"17",
    "addr:postcode":"9130",
    "addr:street":"Avenue Acker",
    "iso:country":"BE",
    "sg:address":"Avenue Acker 17",
    "sg:city":"Beveren",
    "sg:orig_category":"Travaux de finition and nettoyage de b\u00e2timents",
    "sg:phone":"+32 3 773 27 03",
    "sg:postcode":"9130",
    "sg:province":"Oost-Vlaanderen",
    "wof:name":"Franssens W",
    "wof:placetype":"venue"
},
  "geometry": {"coordinates":[4.1916561127,51.2499694824],"type":"Point"}
}