{
  "type": "Feature",
  "properties": {
    "iso:country":"BE",
    "sg:address":"Rue De La Cense Au Bois 30",
    "sg:city":"Ath",
    "sg:orig_category":"M\u00e9decins and sp\u00e9cialistes",
    "sg:phone":"+32 68 28 48 26",
    "sg:postcode":"7800",
    "sg:province":"Hainaut",
    "wof:name":"Pierre Delvoye",
    "wof:placetype":"venue"
},
  "geometry": {"coordinates":[3.7913711071,50.6315536499],"type":"Point"}
}