{
  "type": "Feature",
  "properties": {
    "addr:full":"Jan Stobbaertslaan 99 Schaarbeek/schaerbeek Bruxelles-Capitale 1030",
    "addr:housenumber":"99",
    "addr:postcode":"1030",
    "addr:street":"Jan Stobbaertslaan",
    "iso:country":"BE",
    "sg:address":"Jan Stobbaertslaan 99",
    "sg:city":"Schaarbeek/schaerbeek",
    "sg:orig_category":"Film-, tv- and videoproductie",
    "sg:phone":"+32 2 215 40 66",
    "sg:postcode":"1030",
    "sg:province":"Bruxelles-Capitale",
    "wof:name":"Yellow Brick Road",
    "wof:placetype":"venue"
},
  "geometry": {"coordinates":[4.3891382217,50.8587837219],"type":"Point"}
}