{
  "type": "Feature",
  "properties": {
    "addr:full":"Chauss\u00c9e D'ixelles 29-31 Elsene/ixelles Bruxelles-Capitale 1050",
    "addr:housenumber":"29-31",
    "addr:postcode":"1050",
    "addr:street":"Chausse\u0301E D'Ixelles",
    "iso:country":"BE",
    "sg:address":"Chauss\u00c9e D'ixelles 29-31",
    "sg:city":"Elsene/ixelles",
    "sg:orig_category":"Grossistes divers. Horloges, m\u00e9taux pr\u00e9cieux and bijoux Gr",
    "sg:phone":"+32 2 512 18 87",
    "sg:postcode":"1050",
    "sg:province":"Bruxelles-Capitale",
    "wof:name":"Belitex Import Export",
    "wof:placetype":"venue"
},
  "geometry": {"coordinates":[4.3622069359,50.8370094299],"type":"Point"}
}