{
  "type": "Feature",
  "properties": {
    "addr:full":"Deuzeldlaan 85 Schoten Antwerpen 2900",
    "addr:housenumber":"85",
    "addr:postcode":"2900",
    "addr:street":"Deuzeldlaan",
    "iso:country":"BE",
    "sg:address":"Deuzeldlaan 85",
    "sg:city":"Schoten",
    "sg:orig_category":"M\u00e9decins and sp\u00e9cialistes",
    "sg:phone":"+32 3 646 75 70",
    "sg:postcode":"2900",
    "sg:province":"Antwerpen",
    "wof:name":"R. Raeymaeckers",
    "wof:placetype":"venue"
},
  "geometry": {"coordinates":[4.4652647972,51.2448272705],"type":"Point"}
}