{
  "type": "Feature",
  "properties": {
    "addr:full":"Huidevettersstraat 38bw12- Antwerpen Antwerpen 2000",
    "addr:housenumber":"38bw12",
    "addr:postcode":"2000",
    "addr:street":"Huidevettersstraat",
    "iso:country":"BE",
    "sg:address":"Huidevettersstraat 38bw12-",
    "sg:city":"Antwerpen",
    "sg:orig_category":"V\u00eatements pour Hommes",
    "sg:phone":"+32 3 231 39 43",
    "sg:postcode":"2000",
    "sg:province":"Antwerpen",
    "wof:name":"Boetiek Mano",
    "wof:placetype":"venue"
},
  "geometry": {"coordinates":[4.4053850174,51.2170143127],"type":"Point"}
}