{
  "type": "Feature",
  "properties": {
    "addr:full":"Avenue Des Croix Du Feu 265 Bruxelles Bruxelles-Capitale 1020",
    "addr:housenumber":"265",
    "addr:postcode":"1020",
    "addr:street":"Avenue Des Croix Du Feu",
    "iso:country":"BE",
    "sg:address":"Avenue Des Croix Du Feu 265",
    "sg:city":"Bruxelles",
    "sg:classifiers":[
        {
            "category":"Utilities",
            "subcategory":"Telephone",
            "type":"Services"
        }
    ],
    "sg:phone":"+32 2 270 42 82",
    "sg:postcode":"1020",
    "sg:province":"Bruxelles-Capitale",
    "sg:tags":[
        "-",
        "internet"
    ],
    "wof:name":"Digital3d",
    "wof:placetype":"venue"
},
  "geometry": {"coordinates":[4.3614149094,50.8947486877],"type":"Point"}
}