{
  "type": "Feature",
  "properties": {
    "addr:full":"Avenue De Marlagne 21 Namur Namur 5000",
    "addr:housenumber":"21",
    "addr:postcode":"5000",
    "addr:street":"Avenue De Marlagne",
    "iso:country":"BE",
    "sg:address":"Avenue De Marlagne 21",
    "sg:city":"Namur",
    "sg:classifiers":[
        {
            "category":"Personal",
            "subcategory":"Beauty Salon",
            "type":"Services"
        }
    ],
    "sg:phone":"+32 81 74 55 39",
    "sg:postcode":"5000",
    "sg:province":"Namur",
    "sg:tags":[
        "lady",
        "-",
        "hairdressing"
    ],
    "wof:name":"Rossi M",
    "wof:placetype":"venue"
},
  "geometry": {"coordinates":[4.8426799774,50.459438324],"type":"Point"}
}