{
  "type": "Feature",
  "properties": {
    "iso:country":"BE",
    "sg:address":"Rue De La Halle 1",
    "sg:city":"Namur",
    "sg:orig_category":"Antiquit\u00e9s",
    "sg:phone":"+32 475 29 12 58",
    "sg:postcode":"5000",
    "sg:province":"Namur",
    "wof:name":"Maison Ann\u00c9es Folles",
    "wof:placetype":"venue"
},
  "geometry": {"coordinates":[4.865503788,50.462978363],"type":"Point"}
}