{
  "type": "Feature",
  "properties": {
    "addr:full":"Zeven Bunderlaan 310 Vorst/forest Bruxelles-Capitale 1190",
    "addr:housenumber":"310",
    "addr:postcode":"1190",
    "addr:street":"Zeven Bunderlaan;/ Forest",
    "iso:country":"BE",
    "sg:address":"Zeven Bunderlaan 310",
    "sg:city":"Vorst/forest",
    "sg:orig_category":"Artsen and specialisten",
    "sg:phone":"+32 2 343 78 62",
    "sg:postcode":"1190",
    "sg:province":"Bruxelles-Capitale",
    "wof:name":"J. Tsachor",
    "wof:placetype":"venue"
},
  "geometry": {"coordinates":[4.3310518265,50.8074684143],"type":"Point"}
}