{
  "type": "Feature",
  "properties": {
    "iso:country":"BE",
    "sg:address":"Rue Des Chrysanth\u00c8mes 7",
    "sg:city":"Brussel/bruxelles",
    "sg:orig_category":"Activit\u00e9s diverses d'imprimerie. Artistes ind\u00e9pendants",
    "sg:phone":"+32 2 478 15 19",
    "sg:postcode":"1020",
    "sg:province":"Bruxelles-Capitale",
    "wof:name":"Victor Sanchez Pando",
    "wof:placetype":"venue"
},
  "geometry": {"coordinates":[4.3496208191,50.879611969],"type":"Point"}
}