{
  "type": "Feature",
  "properties": {
    "addr:full":"Kiezel Kleine Brogel 25 Peer Limburg 3990",
    "addr:housenumber":"25",
    "addr:postcode":"3990",
    "addr:street":"Kiezel Kleine Brogel",
    "iso:country":"BE",
    "sg:address":"Kiezel Kleine Brogel 25",
    "sg:city":"Peer",
    "sg:classifiers":[
        {
            "category":"Real Estate",
            "subcategory":"Architect",
            "type":"Services"
        }
    ],
    "sg:phone":"+32 11 63 11 49",
    "sg:postcode":"3990",
    "sg:province":"Limburg",
    "wof:name":"Van Hoef L",
    "wof:placetype":"venue"
},
  "geometry": {"coordinates":[5.4533557892,51.1371803284],"type":"Point"}
}