{
  "type": "Feature",
  "properties": {
    "addr:full":"Chemin Du Croiseau 26 Soignies Hainaut 7060",
    "addr:housenumber":"26",
    "addr:postcode":"7060",
    "addr:street":"Chemin Du Croiseau",
    "iso:country":"BE",
    "sg:address":"Chemin Du Croiseau 26",
    "sg:city":"Soignies",
    "sg:orig_category":"Evaluation and estimation de biens immobiliers",
    "sg:phone":"+32 67 33 20 38",
    "sg:postcode":"7060",
    "sg:province":"Hainaut",
    "wof:name":"Paul Van Driessche",
    "wof:placetype":"venue"
},
  "geometry": {"coordinates":[4.0724000931,50.5779037476],"type":"Point"}
}