{
  "type": "Feature",
  "properties": {
    "iso:country":"BE",
    "sg:address":"Koekuitstraat 14",
    "sg:city":"Vleteren (westvleteren)",
    "sg:classifiers":[
        {
            "category":"Retail",
            "subcategory":"Animal Services",
            "type":"Services"
        }
    ],
    "sg:phone":"+32 57 33 58 88",
    "sg:postcode":"8640",
    "sg:province":"West-Vlaanderen",
    "sg:tags":[
        "breeding",
        "selling",
        "-",
        "dog"
    ],
    "wof:name":"Kennel Van De Paterhoek",
    "wof:placetype":"venue"
},
  "geometry": {"coordinates":[2.7274930477,50.890838623],"type":"Point"}
}