{
  "type": "Feature",
  "properties": {
    "addr:full":"James Ensorgalerij 40c Oostende West-Vlaanderen 8400",
    "addr:housenumber":"40c",
    "addr:postcode":"8400",
    "iso:country":"BE",
    "sg:address":"James Ensorgalerij 40c",
    "sg:city":"Oostende",
    "sg:classifiers":[
        {
            "category":"Shopping",
            "subcategory":"Jewelry",
            "type":"Retail Goods"
        }
    ],
    "sg:phone":"+32 59 50 13 52",
    "sg:postcode":"8400",
    "sg:province":"West-Vlaanderen",
    "sg:tags":[
        "-",
        "imitation"
    ],
    "wof:name":"Plus",
    "wof:placetype":"venue"
},
  "geometry": {"coordinates":[2.916312933,51.2321014404],"type":"Point"}
}