{
  "type": "Feature",
  "properties": {
    "addr:full":"Lascheid 42 Burg-reuland Li\u00e8ge 4790",
    "addr:housenumber":"42",
    "addr:postcode":"4790",
    "addr:street":"Lascheid",
    "iso:country":"BE",
    "sg:address":"Lascheid 42",
    "sg:city":"Burg-reuland",
    "sg:orig_category":"Maisons de vacances",
    "sg:phone":"+32 80 32 94 27",
    "sg:postcode":"4790",
    "sg:province":"Li\u00e8ge",
    "wof:name":"J. Kneip",
    "wof:placetype":"venue"
},
  "geometry": {"coordinates":[6.1315770149,50.1943702698],"type":"Point"}
}