{
  "type": "Feature",
  "properties": {
    "addr:full":"Langemunt 65 Nevele Oost-Vlaanderen 9850",
    "addr:housenumber":"65",
    "addr:postcode":"9850",
    "addr:street":"Langemunt",
    "iso:country":"BE",
    "sg:address":"Langemunt 65",
    "sg:city":"Nevele",
    "sg:orig_category":"Boucheries",
    "sg:phone":"+32 9 371 59 71",
    "sg:postcode":"9850",
    "sg:province":"Oost-Vlaanderen",
    "wof:name":"Guido D'aubioul",
    "wof:placetype":"venue"
},
  "geometry": {"coordinates":[3.5543398857,51.0308990479],"type":"Point"}
}