{
  "type": "Feature",
  "properties": {
    "addr:full":"Rue L\u00c9opold I 331 Jette/jette Bruxelles-Capitale 1090",
    "addr:housenumber":"331",
    "addr:postcode":"1090",
    "addr:street":"Rue Le\u0301Opold I",
    "iso:country":"BE",
    "sg:address":"Rue L\u00c9opold I 331",
    "sg:city":"Jette/jette",
    "sg:orig_category":"Banques and organismes de cr\u00e9dit",
    "sg:phone":"+32 2 428 81 88",
    "sg:postcode":"1090",
    "sg:province":"Bruxelles-Capitale",
    "wof:name":"Dexia",
    "wof:placetype":"venue"
},
  "geometry": {"coordinates":[4.3369197845,50.8760910034],"type":"Point"}
}