{
  "type": "Feature",
  "properties": {
    "addr:full":"Nieuwstraat 1 Box 1 Haaltert (denderhoutem) Oost-Vlaanderen 9450",
    "addr:housenumber":"1;1",
    "addr:postcode":"9450",
    "addr:street":"Nieuwstraat;Box",
    "iso:country":"BE",
    "sg:address":"Nieuwstraat 1 Box 1",
    "sg:city":"Haaltert (denderhoutem)",
    "sg:classifiers":[
        {
            "category":"Professional",
            "subcategory":"Accounting & Tax Preparation",
            "type":"Services"
        }
    ],
    "sg:phone":"+32 54 31 70 70",
    "sg:postcode":"9450",
    "sg:province":"Oost-Vlaanderen",
    "sg:tags":[
        "bookkeeper"
    ],
    "wof:name":"De Blander R",
    "wof:placetype":"venue"
},
  "geometry": {"coordinates":[4.0171928406,50.8703651428],"type":"Point"}
}