{
  "type": "Feature",
  "properties": {
    "addr:full":"Troonstraat 179 Elsene/ixelles Bruxelles-Capitale 1050",
    "addr:housenumber":"179",
    "addr:postcode":"1050",
    "addr:street":"Troonstraat",
    "iso:country":"BE",
    "sg:address":"Troonstraat 179",
    "sg:city":"Elsene/ixelles",
    "sg:orig_category":"Binnenhuisarchitecten",
    "sg:phone":"+32 2 466 79 24",
    "sg:postcode":"1050",
    "sg:province":"Bruxelles-Capitale",
    "wof:name":"Archi D\u00c9cor",
    "wof:placetype":"venue"
},
  "geometry": {"coordinates":[4.3722519875,50.8349456787],"type":"Point"}
}