{
  "type": "Feature",
  "properties": {
    "addr:full":"Frissehoeken 40 Mol Antwerpen 2400",
    "addr:housenumber":"40",
    "addr:postcode":"2400",
    "addr:street":"Frissehoeken",
    "iso:country":"BE",
    "sg:address":"Frissehoeken 40",
    "sg:city":"Mol",
    "sg:classifiers":[
        {
            "category":"Real Estate",
            "subcategory":"Surveying",
            "type":"Services"
        }
    ],
    "sg:phone":"+32 14 31 79 06",
    "sg:postcode":"2400",
    "sg:province":"Antwerpen",
    "sg:tags":[
        "surveyor",
        "land"
    ],
    "wof:name":"Van Hoof C",
    "wof:placetype":"venue"
},
  "geometry": {"coordinates":[5.1121082306,51.208530426],"type":"Point"}
}