{
  "type": "Feature",
  "properties": {
    "iso:country":"BE",
    "sg:address":"Kerkstraat 1",
    "sg:city":"Lanaken (gellik)",
    "sg:classifiers":[
        {
            "category":"Bars & Pubs",
            "type":"Food & Drink"
        }
    ],
    "sg:phone":"+32 89 71 59 83",
    "sg:postcode":"3620",
    "sg:province":"Limburg",
    "wof:name":"Oude Hoeve (in De)",
    "wof:placetype":"venue"
},
  "geometry": {"coordinates":[5.6338968277,50.863986969],"type":"Point"}
}