{
  "type": "Feature",
  "properties": {
    "addr:full":"Schelselei 15f Aartselaar Antwerpen 2630",
    "addr:housenumber":"15f",
    "addr:postcode":"2630",
    "iso:country":"BE",
    "sg:address":"Schelselei 15f",
    "sg:city":"Aartselaar",
    "sg:orig_category":"Zuivelproducten and spijsolie Gh",
    "sg:phone":"+32 3 877 61 71",
    "sg:postcode":"2630",
    "sg:province":"Antwerpen",
    "wof:name":"De Kaasman",
    "wof:placetype":"venue"
},
  "geometry": {"coordinates":[4.3725199699,51.1309890747],"type":"Point"}
}