{
  "type": "Feature",
  "properties": {
    "addr:full":"Rue De Moustier 48 Jemeppe-sur-sambre Namur 5190",
    "addr:housenumber":"48",
    "addr:postcode":"5190",
    "addr:street":"Rue De Moustier",
    "iso:country":"BE",
    "sg:address":"Rue De Moustier 48",
    "sg:city":"Jemeppe-sur-sambre",
    "sg:orig_category":"Journaux. Tabac",
    "sg:phone":"+32 71 78 47 46",
    "sg:postcode":"5190",
    "sg:province":"Namur",
    "wof:name":"Maison Blondiaux",
    "wof:placetype":"venue"
},
  "geometry": {"coordinates":[4.7003598213,50.4759178162],"type":"Point"}
}