{
  "type": "Feature",
  "properties": {
    "addr:full":"Avenue Georges Henri 256 Bruxelles (woluwe-saint-lambert) Bruxelles-Capitale 1200",
    "addr:housenumber":"256",
    "addr:postcode":"1200",
    "addr:street":"Avenue Georges Henri",
    "iso:country":"BE",
    "sg:address":"Avenue Georges Henri 256",
    "sg:city":"Bruxelles (woluwe-saint-lambert)",
    "sg:classifiers":[
        {
            "category":"Personal",
            "subcategory":"Barber",
            "type":"Services"
        }
    ],
    "sg:phone":"+32 2 736 58 54",
    "sg:postcode":"1200",
    "sg:province":"Bruxelles-Capitale",
    "sg:tags":[
        "gentleman",
        "salon",
        "-",
        "hairdressing"
    ],
    "wof:name":"Gentlemen",
    "wof:placetype":"venue"
},
  "geometry": {"coordinates":[4.4127659798,50.8439903259],"type":"Point"}
}