{
  "type": "Feature",
  "properties": {
    "iso:country":"BE",
    "sg:address":"Tongersesteenweg 104",
    "sg:city":"Kortessem",
    "sg:classifiers":[
        {
            "category":"Sports & Exercise",
            "subcategory":"Swimming Pool",
            "type":"Entertainment"
        }
    ],
    "sg:phone":"+32 11 37 61 53",
    "sg:postcode":"3720",
    "sg:province":"Limburg",
    "sg:tags":[
        "tank",
        "septic"
    ],
    "wof:name":"De Clercq G",
    "wof:placetype":"venue"
},
  "geometry": {"coordinates":[5.3889398575,50.8546981812],"type":"Point"}
}