{
  "type": "Feature",
  "properties": {
    "addr:full":"2 Oost-gistelhof Brugge West-Vlaanderen 8000",
    "addr:housenumber":"2",
    "addr:postcode":"8000",
    "addr:street":"Oost-Gistelhof",
    "iso:country":"BE",
    "sg:address":"2 Oost-gistelhof",
    "sg:city":"Brugge",
    "sg:classifiers":[
        {
            "category":"Travel",
            "subcategory":"Hotels & Motels",
            "type":"Entertainment"
        }
    ],
    "sg:phone":"+32 50 34 03 24",
    "sg:postcode":"8000",
    "sg:province":"West-Vlaanderen",
    "sg:tags":[
        "hotels",
        "business",
        "restaurant"
    ],
    "wof:name":"Ter Brughe Nv",
    "wof:placetype":"venue"
},
  "geometry": {"coordinates":[3.2254300117,51.2139472961],"type":"Point"}
}