{
  "type": "Feature",
  "properties": {
    "addr:full":"Avenue Jean Vanhaelen 13 Oudergem/auderghem Bruxelles-Capitale 1160",
    "addr:housenumber":"13",
    "addr:postcode":"1160",
    "addr:street":"Avenue Jean Vanhaelen;/",
    "iso:country":"BE",
    "sg:address":"Avenue Jean Vanhaelen 13",
    "sg:city":"Oudergem/auderghem",
    "sg:orig_category":"Mat\u00e9riel m\u00e9dical and orthop\u00e9dique and proth\u00e8ses Fab",
    "sg:phone":"+32 2 675 71 42",
    "sg:postcode":"1160",
    "sg:province":"Bruxelles-Capitale",
    "wof:name":"Eric Godeaux",
    "wof:placetype":"venue"
},
  "geometry": {"coordinates":[4.4255809784,50.8120384216],"type":"Point"}
}