{
  "type": "Feature",
  "properties": {
    "iso:country":"BE",
    "sg:address":"Heikant 25",
    "sg:city":"Arendonk",
    "sg:classifiers":[
        {
            "category":"Retail",
            "subcategory":"Animal Services",
            "type":"Services"
        }
    ],
    "sg:phone":"+32 496 27 01 41",
    "sg:postcode":"2370",
    "sg:province":"Antwerpen",
    "sg:tags":[
        "breeding",
        "selling",
        "-",
        "dog"
    ],
    "wof:name":"Everaert",
    "wof:placetype":"venue"
},
  "geometry": {"coordinates":[5.0785169601,51.3301239014],"type":"Point"}
}