{
  "type": "Feature",
  "properties": {
    "iso:country":"BE",
    "sg:address":"Rue Ariste Caussin 75",
    "sg:city":"Dinant",
    "sg:classifiers":[
        {
            "category":"Insurance",
            "subcategory":"Insurance Agent",
            "type":"Services"
        }
    ],
    "sg:phone":"+32 82 22 29 34",
    "sg:postcode":"5500",
    "sg:province":"Namur",
    "sg:tags":[
        "broker"
    ],
    "wof:name":"Mahy M & R Sprl",
    "wof:placetype":"venue"
},
  "geometry": {"coordinates":[4.9158158302,50.2390975952],"type":"Point"}
}