{
  "type": "Feature",
  "properties": {
    "addr:full":"Rommersheide G 1 Brecht Antwerpen 2960",
    "addr:housenumber":"1",
    "addr:postcode":"2960",
    "addr:street":"Rommersheide G",
    "iso:country":"BE",
    "sg:address":"Rommersheide G 1",
    "sg:city":"Brecht",
    "sg:orig_category":"Schoonmaakbedrijven and ongediertebestrijding",
    "sg:phone":"+32 477 79 18 11",
    "sg:postcode":"2960",
    "sg:province":"Antwerpen",
    "wof:name":"Fa. Correct",
    "wof:placetype":"venue"
},
  "geometry": {"coordinates":[4.5649738312,51.3201828003],"type":"Point"}
}