{
  "type": "Feature",
  "properties": {
    "addr:full":"Kardinaal Mercierplein 6 Jette Bruxelles-Capitale 1090",
    "addr:housenumber":"6",
    "addr:postcode":"1090",
    "addr:street":"Kardinaal Mercierplein",
    "iso:country":"BE",
    "sg:address":"Kardinaal Mercierplein 6",
    "sg:city":"Jette",
    "sg:orig_category":"Biblioth\u00e8ques and archives publiques",
    "sg:phone":"+32 2 427 76 07",
    "sg:postcode":"1090",
    "sg:province":"Bruxelles-Capitale",
    "wof:name":"Bibliotheek",
    "wof:placetype":"venue"
},
  "geometry": {"coordinates":[4.3281350136,50.8802947998],"type":"Point"}
}