{
  "type": "Feature",
  "properties": {
    "addr:full":"Geinsteindestraat 1 Sint-gillis-waas (sint-pauwels) Oost-Vlaanderen 9170",
    "addr:housenumber":"1",
    "addr:postcode":"9170",
    "addr:street":"Geinsteindestraat;Sint-Pauwels",
    "iso:country":"BE",
    "sg:address":"Geinsteindestraat 1",
    "sg:city":"Sint-gillis-waas (sint-pauwels)",
    "sg:classifiers":[
        {
            "category":"Farming",
            "subcategory":"Farm & Veterinary Services",
            "type":"Manufacturing & Wholesale Goods"
        }
    ],
    "sg:phone":"+32 3 776 65 29",
    "sg:postcode":"9170",
    "sg:province":"Oost-Vlaanderen",
    "sg:tags":[
        "agricultural",
        "contractor"
    ],
    "wof:name":"Buys Loonbedrijf Nv",
    "wof:placetype":"venue"
},
  "geometry": {"coordinates":[4.1209897995,51.1979827881],"type":"Point"}
}