{
  "type": "Feature",
  "properties": {
    "iso:country":"BE",
    "sg:address":"Rue De La Gare 93",
    "sg:city":"Bertrix",
    "sg:orig_category":"Brood, gebak and snoepgoed",
    "sg:phone":"+32 61 41 34 13",
    "sg:postcode":"6880",
    "sg:province":"Luxembourg",
    "wof:name":"Boulangerie Toussaint",
    "wof:placetype":"venue"
},
  "geometry": {"coordinates":[5.2614722252,49.8547401428],"type":"Point"}
}