{
  "type": "Feature",
  "properties": {
    "addr:full":"Jozef Cuyversstr 21 Wilrijk Antwerpen 2610",
    "addr:housenumber":"21",
    "addr:postcode":"2610",
    "addr:street":"Jozef Cuyversstr;Antwerpen",
    "iso:country":"BE",
    "sg:address":"Jozef Cuyversstr 21",
    "sg:city":"Wilrijk",
    "sg:classifiers":[
        {
            "category":"Manufacturing",
            "subcategory":"Jewelry",
            "type":"Manufacturing & Wholesale Goods"
        }
    ],
    "sg:phone":"+32 3 830 27 88",
    "sg:postcode":"2610",
    "sg:province":"Antwerpen",
    "sg:tags":[
        "product",
        "miscellaneous",
        "jewellery"
    ],
    "wof:name":"Marek Nv",
    "wof:placetype":"venue"
},
  "geometry": {"coordinates":[4.3906149864,51.1675033569],"type":"Point"}
}