{
  "type": "Feature",
  "properties": {
    "iso:country":"BE",
    "sg:address":"Bosheide 2",
    "sg:city":"Geel",
    "sg:orig_category":"Varkenskwekers",
    "sg:phone":"+32 14 85 12 42",
    "sg:postcode":"2440",
    "sg:province":"Antwerpen",
    "wof:name":"Simonne Stessens",
    "wof:placetype":"venue"
},
  "geometry": {"coordinates":[5.0189380646,51.2384643555],"type":"Point"}
}