{
  "type": "Feature",
  "properties": {
    "iso:country":"BE",
    "sg:address":"Rue Des Meuniers 46",
    "sg:city":"Beloeil (stambruges)",
    "sg:classifiers":[
        {
            "category":"Food & Beverages",
            "subcategory":"Cheese",
            "type":"Retail Goods"
        }
    ],
    "sg:phone":"+32 69 57 97 69",
    "sg:postcode":"7973",
    "sg:province":"Hainaut",
    "sg:tags":[
        "-"
    ],
    "wof:name":"Cange J",
    "wof:placetype":"venue"
},
  "geometry": {"coordinates":[3.7123930454,50.5118942261],"type":"Point"}
}