{
  "type": "Feature",
  "properties": {
    "iso:country":"BE",
    "sg:address":"Charneux 80",
    "sg:city":"Jalhay",
    "sg:orig_category":"Rundveehouders",
    "sg:phone":"+32 87 64 71 85",
    "sg:postcode":"4845",
    "sg:province":"Li\u00e8ge",
    "wof:name":"Ferdinand Carpentier",
    "wof:placetype":"venue"
},
  "geometry": {"coordinates":[5.9664101601,50.5517997742],"type":"Point"}
}