{
  "type": "Feature",
  "properties": {
    "addr:full":"Avenue Huart Hamoir 32 Schaarbeek/schaerbeek Bruxelles-Capitale 1030",
    "addr:housenumber":"32",
    "addr:postcode":"1030",
    "addr:street":"Avenue Huart Hamoir",
    "iso:country":"BE",
    "sg:address":"Avenue Huart Hamoir 32",
    "sg:city":"Schaarbeek/schaerbeek",
    "sg:classifiers":[
        {
            "category":"Retail",
            "subcategory":"Auto Rental",
            "type":"Services"
        }
    ],
    "sg:phone":"+32 2 241 28 45",
    "sg:postcode":"1030",
    "sg:province":"Bruxelles-Capitale",
    "sg:tags":[
        "machine",
        "fab",
        "de",
        "bureau"
    ],
    "wof:name":"Van Campenhoudt",
    "wof:placetype":"venue"
},
  "geometry": {"coordinates":[4.3817830086,50.8771972656],"type":"Point"}
}