{
  "type": "Feature",
  "properties": {
    "addr:full":"Grote Baan 3 Bocholt Limburg 3950",
    "addr:housenumber":"3",
    "addr:postcode":"3950",
    "addr:street":"Grote Baan",
    "iso:country":"BE",
    "sg:address":"Grote Baan 3",
    "sg:city":"Bocholt",
    "sg:orig_category":"Eleveurs and marchands de porcs",
    "sg:phone":"+32 89 46 16 61",
    "sg:postcode":"3950",
    "sg:province":"Limburg",
    "wof:name":"Tijskens & Bullen",
    "wof:placetype":"venue"
},
  "geometry": {"coordinates":[5.5544838905,51.1382369995],"type":"Point"}
}