{
  "type": "Feature",
  "properties": {
    "addr:full":"Monseigneur Van Waeyenberghlaan 1 Box 7 Leuven Vlaams-Brabant 3000",
    "addr:housenumber":"1;7",
    "addr:postcode":"3000",
    "addr:street":"Monseigneur Van Waeyenberghlaan;Box",
    "iso:country":"BE",
    "sg:address":"Monseigneur Van Waeyenberghlaan 1 Box 7",
    "sg:city":"Leuven",
    "sg:classifiers":[
        {
            "category":"Social Services",
            "type":"Services"
        }
    ],
    "sg:phone":"+32 16 20 29 81",
    "sg:postcode":"3000",
    "sg:province":"Vlaams-Brabant",
    "wof:name":"Centrum Voor Levensvragen, Relaties En Seksualiteit (cawleuven)",
    "wof:placetype":"venue"
},
  "geometry": {"coordinates":[4.6889262199,50.8795013428],"type":"Point"}
}