{
  "type": "Feature",
  "properties": {
    "iso:country":"BE",
    "sg:address":"Rue Sauveni\u00c8re 58",
    "sg:city":"Ouffet",
    "sg:orig_category":"R\u00e9parations de chaussures and articles en cuir",
    "sg:phone":"+32 86 36 68 78",
    "sg:postcode":"4590",
    "sg:province":"Li\u00e8ge",
    "wof:name":"Alain Marecaux",
    "wof:placetype":"venue"
},
  "geometry": {"coordinates":[5.4630260468,50.4407348633],"type":"Point"}
}