{
  "type": "Feature",
  "properties": {
    "addr:full":"Rendestede 11 Ninove Oost-Vlaanderen 9400",
    "addr:housenumber":"11",
    "addr:postcode":"9400",
    "addr:street":"Rendestede",
    "iso:country":"BE",
    "sg:address":"Rendestede 11",
    "sg:city":"Ninove",
    "sg:orig_category":"Rundveehouders",
    "sg:phone":"+32 54 33 17 79",
    "sg:postcode":"9400",
    "sg:province":"Oost-Vlaanderen",
    "wof:name":"Jan Bruyland",
    "wof:placetype":"venue"
},
  "geometry": {"coordinates":[4.0232000351,50.8349113464],"type":"Point"}
}