{
  "type": "Feature",
  "properties": {
    "addr:full":"Schuttersvest 23 Box 3 Mechelen Antwerpen 2800",
    "addr:housenumber":"23;3",
    "addr:postcode":"2800",
    "addr:street":"Schuttersvest;Box",
    "iso:country":"BE",
    "sg:address":"Schuttersvest 23 Box 3",
    "sg:city":"Mechelen",
    "sg:classifiers":[
        {
            "category":"Professional",
            "subcategory":"Lawyer & Legal Services",
            "type":"Services"
        }
    ],
    "sg:phone":"+32 15 41 33 91",
    "sg:postcode":"2800",
    "sg:province":"Antwerpen",
    "wof:name":"Verhaegen Johan",
    "wof:placetype":"venue"
},
  "geometry": {"coordinates":[4.4785108566,51.0210456848],"type":"Point"}
}