{
  "type": "Feature",
  "properties": {
    "iso:country":"BE",
    "sg:address":"Beemdstraat 21",
    "sg:city":"Tongeren",
    "sg:classifiers":[
        {
            "category":"Personal",
            "subcategory":"Beauty Salon",
            "type":"Services"
        }
    ],
    "sg:phone":"+32 12 23 07 98",
    "sg:postcode":"3700",
    "sg:province":"Limburg",
    "sg:tags":[
        "de",
        "coiffure"
    ],
    "wof:name":"Coiffure Adelin",
    "wof:placetype":"venue"
},
  "geometry": {"coordinates":[5.4759631157,50.7820701599],"type":"Point"}
}