{
  "type": "Feature",
  "properties": {
    "addr:full":". Rotselaar (groot) Vlaams-Brabant 3110",
    "addr:postcode":"3110",
    "addr:street":"Groot Vlaams-Brabant",
    "iso:country":"BE",
    "sg:address":".",
    "sg:city":"Rotselaar (groot)",
    "sg:orig_category":"Apotheken",
    "sg:phone":"+32 900 10 500",
    "sg:postcode":"3110",
    "sg:province":"Vlaams-Brabant",
    "wof:name":"Apothekers Van Wacht",
    "wof:placetype":"venue"
},
  "geometry": {"coordinates":[4.7107920647,50.9508590698],"type":"Point"}
}