{
  "type": "Feature",
  "properties": {
    "iso:country":"BE",
    "sg:address":"Maria-hendrikalaan 20",
    "sg:city":"De Haan",
    "sg:orig_category":"H\u00f4tels",
    "sg:phone":"+32 59 23 33 01",
    "sg:postcode":"8420",
    "sg:province":"West-Vlaanderen",
    "wof:name":"Atlanta",
    "wof:placetype":"venue"
},
  "geometry": {"coordinates":[3.0305221081,51.2769584656],"type":"Point"}
}