{
  "type": "Feature",
  "properties": {
    "iso:country":"BE",
    "sg:address":"J. B. Charlierlaan 86",
    "sg:city":"Hoeilaart",
    "sg:classifiers":[
        {
            "category":"Retail",
            "subcategory":"Auto Repair",
            "type":"Services"
        }
    ],
    "sg:phone":"+32 2 657 36 14",
    "sg:postcode":"1560",
    "sg:province":"Vlaams-Brabant",
    "sg:tags":[
        "garage"
    ],
    "wof:name":"Demaerschalk Ren\u00e9 Nv",
    "wof:placetype":"venue"
},
  "geometry": {"coordinates":[4.4629611969,50.7666740417],"type":"Point"}
}