{
  "type": "Feature",
  "properties": {
    "addr:full":"Turnhoutsebaan 388 Wijnegem Antwerpen 2110",
    "addr:housenumber":"388",
    "addr:postcode":"2110",
    "addr:street":"Turnhoutsebaan",
    "iso:country":"BE",
    "sg:address":"Turnhoutsebaan 388",
    "sg:city":"Wijnegem",
    "sg:orig_category":"Banques and organismes de cr\u00e9dit",
    "sg:phone":"+32 3 353 92 48",
    "sg:postcode":"2110",
    "sg:province":"Antwerpen",
    "wof:name":"Kbc",
    "wof:placetype":"venue"
},
  "geometry": {"coordinates":[4.5205769539,51.2273292542],"type":"Point"}
}