{
  "type": "Feature",
  "properties": {
    "addr:full":"Kruisbooglaan 14 Watermaal-bosvoorde/watermael-boitsfort Bruxelles-Capitale 1170",
    "addr:housenumber":"14",
    "addr:postcode":"1170",
    "addr:street":"Kruisbooglaan",
    "iso:country":"BE",
    "sg:address":"Kruisbooglaan 14",
    "sg:city":"Watermaal-bosvoorde/watermael-boitsfort",
    "sg:orig_category":"Artiesten and kunstenaars",
    "sg:phone":"+32 2 672 09 98",
    "sg:postcode":"1170",
    "sg:province":"Bruxelles-Capitale",
    "wof:name":"Bouhisse",
    "wof:placetype":"venue"
},
  "geometry": {"coordinates":[4.4120249748,50.8021850586],"type":"Point"}
}