{
  "type": "Feature",
  "properties": {
    "iso:country":"BE",
    "sg:address":"Zuidstraat 103",
    "sg:city":"Ichtegem",
    "sg:orig_category":"V\u00eatements. Grossistes divers",
    "sg:phone":"+32 51 58 92 95",
    "sg:postcode":"8480",
    "sg:province":"West-Vlaanderen",
    "wof:name":"Mia's Collection",
    "wof:placetype":"venue"
},
  "geometry": {"coordinates":[3.0373001099,51.1067771912],"type":"Point"}
}