{
  "type": "Feature",
  "properties": {
    "addr:full":"Avenue De L'aulne 13 Box 3 Bruxelles (uccle) Bruxelles-Capitale 1180",
    "addr:housenumber":"13;3",
    "addr:postcode":"1180",
    "addr:street":"Avenue De L'Aulne;Box",
    "iso:country":"BE",
    "sg:address":"Avenue De L'aulne 13 Box 3",
    "sg:city":"Bruxelles (uccle)",
    "sg:classifiers":[
        {
            "category":"Professional",
            "subcategory":"Lawyer & Legal Services",
            "type":"Services"
        }
    ],
    "sg:phone":"+32 2 356 57 68",
    "sg:postcode":"1180",
    "sg:province":"Bruxelles-Capitale",
    "wof:name":"Van Witzenburg Gr\u00e9gory",
    "wof:placetype":"venue"
},
  "geometry": {"coordinates":[4.3308119774,50.8059196472],"type":"Point"}
}