{
  "type": "Feature",
  "properties": {
    "addr:full":"Albertusplein 12 Scherpenheuvel-zichem (scherpenheuvel) Vlaams-Brabant 3270",
    "addr:housenumber":"12",
    "addr:postcode":"3270",
    "addr:street":"Albertusplein",
    "iso:country":"BE",
    "sg:address":"Albertusplein 12",
    "sg:city":"Scherpenheuvel-zichem (scherpenheuvel)",
    "sg:classifiers":[
        {
            "category":"Travel",
            "subcategory":"Hotels & Motels",
            "type":"Entertainment"
        }
    ],
    "sg:phone":"+32 13 77 13 69",
    "sg:postcode":"3270",
    "sg:province":"Vlaams-Brabant",
    "wof:name":"De Zwaan",
    "wof:placetype":"venue"
},
  "geometry": {"coordinates":[4.9775061607,50.9795265198],"type":"Point"}
}