{
  "type": "Feature",
  "properties": {
    "addr:full":"All\u00e9e Des Peupliers 17 Bernissart Hainaut 7320",
    "addr:housenumber":"17",
    "addr:postcode":"7320",
    "addr:street":"Alle\u0301E Des Peupliers",
    "iso:country":"BE",
    "sg:address":"All\u00e9e Des Peupliers 17",
    "sg:city":"Bernissart",
    "sg:classifiers":[
        {
            "category":"Professional",
            "subcategory":"Accounting & Tax Preparation",
            "type":"Services"
        }
    ],
    "sg:phone":"+32 69 57 56 16",
    "sg:postcode":"7320",
    "sg:province":"Hainaut",
    "sg:tags":[
        "bookkeeper"
    ],
    "wof:name":"Vancauwenberghe L",
    "wof:placetype":"venue"
},
  "geometry": {"coordinates":[3.6649050713,50.4776153564],"type":"Point"}
}