{
  "type": "Feature",
  "properties": {
    "addr:full":"Zwaanstraat 5 Box 11 Zele Oost-Vlaanderen 9240",
    "addr:housenumber":"5 box 11",
    "addr:postcode":"9240",
    "addr:street":"Zwaanstraat",
    "iso:country":"BE",
    "sg:address":"Zwaanstraat 5 Box 11",
    "sg:city":"Zele",
    "sg:classifiers":[
        {
            "category":"Manufacturing",
            "subcategory":"Musical Instruments",
            "type":"Manufacturing & Wholesale Goods"
        }
    ],
    "sg:phone":"+32 52 45 17 61",
    "sg:postcode":"9240",
    "sg:province":"Oost-Vlaanderen",
    "sg:tags":[
        "rental",
        "-"
    ],
    "wof:name":"Rental Percussion",
    "wof:placetype":"venue"
},
  "geometry": {"coordinates":[4.0379681587,51.0668754578],"type":"Point"}
}