{
  "type": "Feature",
  "properties": {
    "addr:full":"Rue La Roue 2 Donceel Li\u00e8ge 4357",
    "addr:housenumber":"2",
    "addr:postcode":"4357",
    "addr:street":"Rue La Roue",
    "iso:country":"BE",
    "sg:address":"Rue La Roue 2",
    "sg:city":"Donceel",
    "sg:orig_category":"Eleveurs de bovins",
    "sg:phone":"+32 4 250 10 36",
    "sg:postcode":"4357",
    "sg:province":"Li\u00e8ge",
    "wof:name":"Felix Halleux",
    "wof:placetype":"venue"
},
  "geometry": {"coordinates":[5.3516302109,50.6567115784],"type":"Point"}
}