{
  "type": "Feature",
  "properties": {
    "iso:country":"BE",
    "sg:address":"Rue Vaux 65",
    "sg:city":"Soumagne",
    "sg:orig_category":"Installation de menuiserie en bois and plastique",
    "sg:phone":"+32 4 377 20 01",
    "sg:postcode":"4632",
    "sg:province":"Li\u00e8ge",
    "wof:name":"Tony Henssen",
    "wof:placetype":"venue"
},
  "geometry": {"coordinates":[5.7423458099,50.6548614502],"type":"Point"}
}