{
  "type": "Feature",
  "properties": {
    "iso:country":"BE",
    "sg:address":"Wijngaardstraat 34",
    "sg:city":"Aalst",
    "sg:orig_category":"Elektrische installaties voor woningen",
    "sg:phone":"+32 53 78 35 66",
    "sg:postcode":"9300",
    "sg:province":"Oost-Vlaanderen",
    "wof:name":"Ronny Jacob",
    "wof:placetype":"venue"
},
  "geometry": {"coordinates":[4.0623879433,50.9402236938],"type":"Point"}
}