{
  "type": "Feature",
  "properties": {
    "addr:full":"Rue Du Grand-marais 1 Hannut Li\u00e8ge 4280",
    "addr:housenumber":"1",
    "addr:postcode":"4280",
    "addr:street":"Rue Du Grand-Marais",
    "iso:country":"BE",
    "sg:address":"Rue Du Grand-marais 1",
    "sg:city":"Hannut",
    "sg:orig_category":"Rundveehouders",
    "sg:phone":"+32 19 51 06 77",
    "sg:postcode":"4280",
    "sg:province":"Li\u00e8ge",
    "wof:name":"Jacques Maquet",
    "wof:placetype":"venue"
},
  "geometry": {"coordinates":[5.126581192,50.6581382751],"type":"Point"}
}