{
  "type": "Feature",
  "properties": {
    "addr:full":"Rue Des Flamands 9 Jette/jette Bruxelles-Capitale 1090",
    "addr:housenumber":"9",
    "addr:postcode":"1090",
    "addr:street":"Rue Des Flamands",
    "iso:country":"BE",
    "sg:address":"Rue Des Flamands 9",
    "sg:city":"Jette/jette",
    "sg:orig_category":"Peinture. Rev\u00eatements pour sols and murs",
    "sg:phone":"+32 2 420 29 07",
    "sg:postcode":"1090",
    "sg:province":"Bruxelles-Capitale",
    "wof:name":"Martens",
    "wof:placetype":"venue"
},
  "geometry": {"coordinates":[4.3243460655,50.8754386902],"type":"Point"}
}