{
  "type": "Feature",
  "properties": {
    "iso:country":"BE",
    "sg:address":"Burgemeester Maenhautstraat 100-102",
    "sg:city":"Merelbeke",
    "sg:classifiers":[
        {
            "category":"Professional",
            "subcategory":"Accounting & Tax Preparation",
            "type":"Services"
        }
    ],
    "sg:phone":"+32 9 210 11 80",
    "sg:postcode":"9820",
    "sg:province":"Oost-Vlaanderen",
    "sg:tags":[
        "accountant"
    ],
    "wof:name":"Accountantskantoor Verbeurgt A & Zoon Bvba",
    "wof:placetype":"venue"
},
  "geometry": {"coordinates":[3.7643110752,50.9891471863],"type":"Point"}
}