{
  "type": "Feature",
  "properties": {
    "addr:full":"Postbus 10 Kapellen1 Antwerpen 2950",
    "addr:housenumber":"10 kapellen1",
    "addr:postcode":"2950",
    "addr:street":"Postbus",
    "iso:country":"BE",
    "sg:address":"Postbus 10",
    "sg:city":"Kapellen1",
    "sg:classifiers":[
        {
            "category":"Personal",
            "subcategory":"Psychics & Astrologers",
            "type":"Services"
        }
    ],
    "sg:phone":"+32 3 544 95 42",
    "sg:postcode":"2950",
    "sg:province":"Antwerpen",
    "sg:tags":[
        "astrology"
    ],
    "wof:name":"Wanrooy R",
    "wof:placetype":"venue"
},
  "geometry": {"coordinates":[4.4289097786,51.3147697449],"type":"Point"}
}