{
  "type": "Feature",
  "properties": {
    "iso:country":"BE",
    "sg:address":"Rue Du Four 10",
    "sg:city":"Braine-l'alleud",
    "sg:orig_category":"Aanleg van opritten and terreinen bij woningen Afbraak- and draineerwerken",
    "sg:phone":"+32 2 385 00 46",
    "sg:postcode":"1420",
    "sg:province":"Brabant Wallon",
    "wof:name":"Jardinor-herdies",
    "wof:placetype":"venue"
},
  "geometry": {"coordinates":[4.3579320908,50.696559906],"type":"Point"}
}