{
  "type": "Feature",
  "properties": {
    "addr:full":"Baan Naar Bree 31 Peer Limburg 3990",
    "addr:housenumber":"31",
    "addr:postcode":"3990",
    "addr:street":"Baan Naar Bree",
    "iso:country":"BE",
    "sg:address":"Baan Naar Bree 31",
    "sg:city":"Peer",
    "sg:classifiers":[
        {
            "category":"Shopping",
            "subcategory":"Baby Store",
            "type":"Retail Goods"
        }
    ],
    "sg:phone":"+32 11 63 16 80",
    "sg:postcode":"3990",
    "sg:province":"Limburg",
    "sg:tags":[
        "article",
        "b\u00e9b\u00e9s",
        "pour"
    ],
    "wof:name":"Baby Lux",
    "wof:placetype":"venue"
},
  "geometry": {"coordinates":[5.4629688263,51.1319389343],"type":"Point"}
}