{
  "type": "Feature",
  "properties": {
    "iso:country":"BE",
    "sg:address":"Netelzeepstraat 23",
    "sg:city":"Bekkevoort",
    "sg:orig_category":"Jardinage",
    "sg:phone":"+32 16 77 19 64",
    "sg:postcode":"3460",
    "sg:province":"Vlaams-Brabant",
    "wof:name":"Meurrens",
    "wof:placetype":"venue"
},
  "geometry": {"coordinates":[4.9603757858,50.9136238098],"type":"Point"}
}