{
  "type": "Feature",
  "properties": {
    "iso:country":"BE",
    "sg:address":"Boulevard De La Sauveni\u00c8re 145",
    "sg:city":"Wavre",
    "sg:orig_category":"Autoverhuur",
    "sg:phone":"+32 10 41 24 44",
    "sg:postcode":"1301",
    "sg:province":"Brabant Wallon",
    "wof:name":"Keddy",
    "wof:placetype":"venue"
},
  "geometry": {"coordinates":[4.5812849998,50.7129745483],"type":"Point"}
}