{
  "type": "Feature",
  "properties": {
    "iso:country":"BE",
    "sg:address":"Tongersesteenweg 12ba",
    "sg:city":"Hoeselt",
    "sg:orig_category":"Meubelzaken, woning- and keukeninrichting",
    "sg:phone":"+32 89 79 15 79",
    "sg:postcode":"3730",
    "sg:province":"Limburg",
    "wof:name":"Meubelen Corneline",
    "wof:placetype":"venue"
},
  "geometry": {"coordinates":[5.4901819229,50.8491325378],"type":"Point"}
}