{
  "type": "Feature",
  "properties": {
    "iso:country":"BE",
    "sg:address":"Risstraat 3",
    "sg:city":"Genk (waterschei)",
    "sg:classifiers":[
        {
            "category":"Organizations",
            "subcategory":"Professional Association",
            "type":"Services"
        }
    ],
    "sg:phone":"+32 89 38 33 85",
    "sg:postcode":"3600",
    "sg:province":"Limburg",
    "sg:tags":[
        "trade-union",
        "federation"
    ],
    "wof:name":"Centro Cattolico Italiano",
    "wof:placetype":"venue"
},
  "geometry": {"coordinates":[5.5101041794,51.0027961731],"type":"Point"}
}