{
  "type": "Feature",
  "properties": {
    "addr:full":"Schrieksebaan 26 Tremelo Vlaams-Brabant 3120",
    "addr:housenumber":"26",
    "addr:postcode":"3120",
    "addr:street":"Schrieksebaan",
    "iso:country":"BE",
    "sg:address":"Schrieksebaan 26",
    "sg:city":"Tremelo",
    "sg:orig_category":"Centres de relaxation and bien-\u00eatre. Instituts de beaut\u00e9",
    "sg:phone":"+32 16 52 04 41",
    "sg:postcode":"3120",
    "sg:province":"Vlaams-Brabant",
    "wof:name":"Parfumerie Blush",
    "wof:placetype":"venue"
},
  "geometry": {"coordinates":[4.7062039375,50.9924964905],"type":"Point"}
}