{
  "type": "Feature",
  "properties": {
    "iso:country":"BE",
    "sg:address":"Medendorf 9",
    "sg:city":"B\u00fcllingen (medendorf)",
    "sg:classifiers":[
        {
            "category":"Health Services",
            "subcategory":"Doctor",
            "type":"Services"
        }
    ],
    "sg:phone":"+32 80 54 81 54",
    "sg:postcode":"4760",
    "sg:province":"Li\u00e8ge",
    "sg:tags":[
        "medicinephysicians",
        "surgeon"
    ],
    "wof:name":"Baumann A",
    "wof:placetype":"venue"
},
  "geometry": {"coordinates":[6.2860221863,50.3341178894],"type":"Point"}
}