{
  "type": "Feature",
  "properties": {
    "iso:country":"BE",
    "sg:address":"Henri Lebbestraat 25",
    "sg:city":"Waregem",
    "sg:orig_category":"Eclairage et \u00e9quipements du foyer. Installation de menuiserie en bois and plastique. Meubles D\u00e9taill",
    "sg:phone":"+32 56 60 23 80",
    "sg:postcode":"8790",
    "sg:province":"West-Vlaanderen",
    "wof:name":"Galerie Vynckier W. & G.",
    "wof:placetype":"venue"
},
  "geometry": {"coordinates":[3.4250130653,50.8823852539],"type":"Point"}
}