{
  "type": "Feature",
  "properties": {
    "iso:country":"BE",
    "sg:address":"Rue De France 54",
    "sg:city":"Rochefort",
    "sg:orig_category":"Dierenartsen",
    "sg:phone":"+32 84 22 14 87",
    "sg:postcode":"5580",
    "sg:province":"Namur",
    "wof:name":"Claude Saegerman",
    "wof:placetype":"venue"
},
  "geometry": {"coordinates":[5.2191820145,50.1563491821],"type":"Point"}
}