{
  "type": "Feature",
  "properties": {
    "iso:country":"BE",
    "sg:address":"Rue De Nivelles 33",
    "sg:city":"Wavre",
    "sg:orig_category":"Eclairage et \u00e9quipements du foyer",
    "sg:phone":"+32 10 22 45 46",
    "sg:postcode":"1300",
    "sg:province":"Brabant Wallon",
    "wof:name":"Gifts & Design",
    "wof:placetype":"venue"
},
  "geometry": {"coordinates":[4.6076898575,50.7151451111],"type":"Point"}
}