{
  "type": "Feature",
  "properties": {
    "addr:full":"Fortlaan 82 Gent Oost-Vlaanderen 9000",
    "addr:housenumber":"82",
    "addr:postcode":"9000",
    "addr:street":"Fortlaan;Oost-Vlaanderen",
    "iso:country":"BE",
    "sg:address":"Fortlaan 82",
    "sg:city":"Gent",
    "sg:orig_category":"Artsen and specialisten",
    "sg:phone":"+32 9 221 16 22",
    "sg:postcode":"9000",
    "sg:province":"Oost-Vlaanderen",
    "wof:name":"Rudy Vanden Borre",
    "wof:placetype":"venue"
},
  "geometry": {"coordinates":[3.7183830738,51.0353851318],"type":"Point"}
}