{
  "type": "Feature",
  "properties": {
    "addr:full":"Rue De France 1 Momignies (forge-philippe) Hainaut 6596",
    "addr:housenumber":"1",
    "addr:postcode":"6596",
    "addr:street":"Rue De France",
    "iso:country":"BE",
    "sg:address":"Rue De France 1",
    "sg:city":"Momignies (forge-philippe)",
    "sg:classifiers":[
        {
            "category":"Animal Shelter",
            "type":"Public Place"
        }
    ],
    "sg:phone":"+32 479 44 94 93",
    "sg:postcode":"6596",
    "sg:province":"Hainaut",
    "wof:name":"Auberge De La Rivi\u00e8re",
    "wof:placetype":"venue"
},
  "geometry": {"coordinates":[4.2721171379,49.9658622742],"type":"Point"}
}