{
  "type": "Feature",
  "properties": {
    "iso:country":"BE",
    "sg:address":"Leuvensesteenweg 613",
    "sg:city":"Zaventem",
    "sg:classifiers":[
        {
            "category":"Banks & Credit Unions",
            "subcategory":"Bureau De Change",
            "type":"Services"
        }
    ],
    "sg:phone":"+32 2 757 91 26",
    "sg:postcode":"1930",
    "sg:province":"Vlaams-Brabant",
    "sg:tags":[
        "regulating",
        "system"
    ],
    "wof:name":"Belparts",
    "wof:placetype":"venue"
},
  "geometry": {"coordinates":[4.4972071648,50.8761253357],"type":"Point"}
}