{
  "type": "Feature",
  "properties": {
    "addr:full":"Waverstraat 16 Aalst (moorsel) Oost-Vlaanderen 9310",
    "addr:housenumber":"16",
    "addr:postcode":"9310",
    "addr:street":"Waverstraat;Moorsel Oost-Vlaanderen",
    "iso:country":"BE",
    "sg:address":"Waverstraat 16",
    "sg:city":"Aalst (moorsel)",
    "sg:classifiers":[
        {
            "category":"Home & Garden",
            "subcategory":"Furniture",
            "type":"Retail Goods"
        }
    ],
    "sg:phone":"+32 53 70 27 61",
    "sg:postcode":"9310",
    "sg:province":"Oost-Vlaanderen",
    "sg:tags":[
        "-"
    ],
    "wof:name":"Van Praet Spraakmakend In Interieur En Kantoor",
    "wof:placetype":"venue"
},
  "geometry": {"coordinates":[4.0977458954,50.9436264038],"type":"Point"}
}