{
  "type": "Feature",
  "properties": {
    "iso:country":"BE",
    "sg:address":"Tomberglaan 22",
    "sg:city":"Zaventem",
    "sg:classifiers":[
        {
            "category":"Building & Trades",
            "subcategory":"Plumbing",
            "type":"Services"
        }
    ],
    "sg:phone":"+32 2 720 86 98",
    "sg:postcode":"1930",
    "sg:province":"Vlaams-Brabant",
    "sg:tags":[
        "pipe",
        "drain",
        "unblocking"
    ],
    "wof:name":"Maxi Cleaning Bvba",
    "wof:placetype":"venue"
},
  "geometry": {"coordinates":[4.4830021858,50.8758087158],"type":"Point"}
}