{
  "type": "Feature",
  "properties": {
    "addr:full":"Rijselstraat 132 Menen West-Vlaanderen 8930",
    "addr:housenumber":"132",
    "addr:postcode":"8930",
    "addr:street":"Rijselstraat",
    "iso:country":"BE",
    "sg:address":"Rijselstraat 132",
    "sg:city":"Menen",
    "sg:classifiers":[
        {
            "category":"Restaurant",
            "type":"Food & Drink"
        }
    ],
    "sg:phone":"+32 56 53 09 39",
    "sg:postcode":"8930",
    "sg:province":"West-Vlaanderen",
    "sg:tags":[
        "caf\u00e9s"
    ],
    "wof:name":"Chez Jean",
    "wof:placetype":"venue"
},
  "geometry": {"coordinates":[3.1249101162,50.7909393311],"type":"Point"}
}