{
  "type": "Feature",
  "properties": {
    "addr:full":"Rue Du Parc-saint-roch 7 Couvin Namur 5660",
    "addr:housenumber":"7",
    "addr:postcode":"5660",
    "addr:street":"Rue Du Parc-Saint-Roch",
    "iso:country":"BE",
    "sg:address":"Rue Du Parc-saint-roch 7",
    "sg:city":"Couvin",
    "sg:orig_category":"Schoonheidssalons",
    "sg:phone":"+32 60 34 68 57",
    "sg:postcode":"5660",
    "sg:province":"Namur",
    "wof:name":"Carine Crowet",
    "wof:placetype":"venue"
},
  "geometry": {"coordinates":[4.4968800545,50.0538597107],"type":"Point"}
}