{
  "type": "Feature",
  "properties": {
    "addr:full":"Naamsevest 18 Box 3 Leuven Vlaams-Brabant 3000",
    "addr:housenumber":"18;3",
    "addr:postcode":"3000",
    "addr:street":"Naamsevest;Box",
    "iso:country":"BE",
    "sg:address":"Naamsevest 18 Box 3",
    "sg:city":"Leuven",
    "sg:classifiers":[
        {
            "category":"Professional",
            "subcategory":"Art Services",
            "type":"Services"
        }
    ],
    "sg:phone":"+32 16 22 24 43",
    "sg:postcode":"3000",
    "sg:province":"Vlaams-Brabant",
    "sg:tags":[
        "technical",
        "photographer",
        "industrial",
        "-"
    ],
    "wof:name":"Hoogsteyns J",
    "wof:placetype":"venue"
},
  "geometry": {"coordinates":[4.6994671822,50.8685836792],"type":"Point"}
}