{
  "type": "Feature",
  "properties": {
    "addr:full":"Einde 5 Lommel Limburg 3920",
    "addr:housenumber":"5",
    "addr:postcode":"3920",
    "addr:street":"Einde",
    "iso:country":"BE",
    "sg:address":"Einde 5",
    "sg:city":"Lommel",
    "sg:orig_category":"Enseignement maternel and primaire",
    "sg:phone":"+32 11 54 46 74",
    "sg:postcode":"3920",
    "sg:province":"Limburg",
    "wof:name":"Vrije Basisschool",
    "wof:placetype":"venue"
},
  "geometry": {"coordinates":[5.3099060059,51.230342865],"type":"Point"}
}