{
  "type": "Feature",
  "properties": {
    "addr:full":"Steenstraat 84 Brugge West-Vlaanderen 8000",
    "addr:housenumber":"84",
    "addr:postcode":"8000",
    "addr:street":"Steenstraat",
    "iso:country":"BE",
    "sg:address":"Steenstraat 84",
    "sg:city":"Brugge",
    "sg:orig_category":"Chaussures",
    "sg:phone":"+32 50 33 47 14",
    "sg:postcode":"8000",
    "sg:province":"West-Vlaanderen",
    "wof:name":"Giraldo",
    "wof:placetype":"venue"
},
  "geometry": {"coordinates":[3.2213439941,51.2062454224],"type":"Point"}
}