{
  "type": "Feature",
  "properties": {
    "addr:full":"Olympialaan 43 Ledegem West-Vlaanderen 8880",
    "addr:housenumber":"43",
    "addr:postcode":"8880",
    "addr:street":"Olympialaan",
    "iso:country":"BE",
    "sg:address":"Olympialaan 43",
    "sg:city":"Ledegem",
    "sg:orig_category":"Studios photographiques",
    "sg:phone":"+32 56 50 50 18",
    "sg:postcode":"8880",
    "sg:province":"West-Vlaanderen",
    "wof:name":"Video Dirk",
    "wof:placetype":"venue"
},
  "geometry": {"coordinates":[3.1821379662,50.8700027466],"type":"Point"}
}