{
  "type": "Feature",
  "properties": {
    "addr:full":"Nieuwstr 51 Aalst Oost-Vlaanderen 9300",
    "addr:housenumber":"51",
    "addr:postcode":"9300",
    "addr:street":"Nieuwstr",
    "iso:country":"BE",
    "sg:address":"Nieuwstr 51",
    "sg:city":"Aalst",
    "sg:classifiers":[
        {
            "category":"Banks & Credit Unions",
            "subcategory":"Bank",
            "type":"Services"
        }
    ],
    "sg:phone":"+32 3 286 91 40",
    "sg:postcode":"9300",
    "sg:province":"Oost-Vlaanderen",
    "wof:name":"Parnib Belgi\u00eb Nv",
    "wof:placetype":"venue"
},
  "geometry": {"coordinates":[4.4174151421,51.1974411011],"type":"Point"}
}