{
  "type": "Feature",
  "properties": {
    "iso:country":"BE",
    "sg:address":"Odilon Vanderlindenstraat 2",
    "sg:city":"Gent",
    "sg:orig_category":"Boucheries",
    "sg:phone":"+32 9 230 11 48",
    "sg:postcode":"9050",
    "sg:province":"Oost-Vlaanderen",
    "wof:name":"Slagerij Laurent De Waele",
    "wof:placetype":"venue"
},
  "geometry": {"coordinates":[3.7555799484,51.0448074341],"type":"Point"}
}