{
  "type": "Feature",
  "properties": {
    "addr:full":"Rue Joseph Sneessens 33 Wavre Brabant Wallon 1300",
    "addr:housenumber":"33;1300",
    "addr:street":"Rue Joseph Sneessens",
    "iso:country":"BE",
    "sg:address":"Rue Joseph Sneessens 33",
    "sg:city":"Wavre",
    "sg:orig_category":"Groenten and fruit Gh",
    "sg:phone":"+32 10 41 47 26",
    "sg:postcode":"1300",
    "sg:province":"Brabant Wallon",
    "wof:name":"Pivaropack",
    "wof:placetype":"venue"
},
  "geometry": {"coordinates":[4.6116552353,50.7134132385],"type":"Point"}
}