{
  "type": "Feature",
  "properties": {
    "addr:full":"Plezantstraat 50 Sint-niklaas Oost-Vlaanderen 9100",
    "addr:housenumber":"50",
    "addr:postcode":"9100",
    "addr:street":"Plezantstraat",
    "iso:country":"BE",
    "sg:address":"Plezantstraat 50",
    "sg:city":"Sint-niklaas",
    "sg:orig_category":"Telecommunicatiesystemen",
    "sg:phone":"+32 3 780 91 20",
    "sg:postcode":"9100",
    "sg:province":"Oost-Vlaanderen",
    "wof:name":"Belgacom Telebusiness",
    "wof:placetype":"venue"
},
  "geometry": {"coordinates":[4.1341571808,51.1666488647],"type":"Point"}
}