{
  "type": "Feature",
  "properties": {
    "iso:country":"BE",
    "sg:address":"Avenue Professeur Henrijean 17",
    "sg:city":"Spa",
    "sg:classifiers":[
        {
            "category":"Real Estate",
            "subcategory":"Surveying",
            "type":"Services"
        }
    ],
    "sg:phone":"+32 87 77 13 59",
    "sg:postcode":"4900",
    "sg:province":"Li\u00e8ge",
    "sg:tags":[
        "surveyor",
        "land"
    ],
    "wof:name":"Pecher F",
    "wof:placetype":"venue"
},
  "geometry": {"coordinates":[5.8583140373,50.4868545532],"type":"Point"}
}