{
  "type": "Feature",
  "properties": {
    "iso:country":"BE",
    "sg:address":"Bld Emile De Laveleye 65bb",
    "sg:city":"Li\u00c8ge",
    "sg:orig_category":"M\u00e9decins and sp\u00e9cialistes",
    "sg:phone":"+32 4 343 45 52",
    "sg:postcode":"4020",
    "sg:province":"Li\u00e8ge",
    "wof:name":"Marie-louise Colucci",
    "wof:placetype":"venue"
},
  "geometry": {"coordinates":[5.5842971802,50.6243057251],"type":"Point"}
}