{
  "type": "Feature",
  "properties": {
    "iso:country":"BE",
    "sg:address":"Terwestvaart 40",
    "sg:city":"Moerbeke",
    "sg:orig_category":"Eleveurs de bovins",
    "sg:phone":"+32 9 346 89 53",
    "sg:postcode":"9180",
    "sg:province":"Oost-Vlaanderen",
    "wof:name":"Maurice Baetens",
    "wof:placetype":"venue"
},
  "geometry": {"coordinates":[3.9240720272,51.1769332886],"type":"Point"}
}