{
  "type": "Feature",
  "properties": {
    "iso:country":"BE",
    "sg:address":"Industrieweg 70",
    "sg:city":"Gent (wondelgem)",
    "sg:classifiers":[
        {
            "category":"Transit Center",
            "subcategory":"Freight",
            "type":"Transportation"
        }
    ],
    "sg:phone":"+32 9 253 55 00",
    "sg:postcode":"9032",
    "sg:province":"Oost-Vlaanderen",
    "sg:tags":[
        "plant",
        "-",
        "transport"
    ],
    "wof:name":"De Decker G Transport Nv",
    "wof:placetype":"venue"
},
  "geometry": {"coordinates":[3.6899850368,51.0904388428],"type":"Point"}
}