{
  "type": "Feature",
  "properties": {
    "addr:full":"Gidsenlaan 6 Maldegem Oost-Vlaanderen 9990",
    "addr:housenumber":"6",
    "addr:postcode":"9990",
    "addr:street":"Gidsenlaan",
    "iso:country":"BE",
    "sg:address":"Gidsenlaan 6",
    "sg:city":"Maldegem",
    "sg:classifiers":[
        {
            "category":"Personal",
            "subcategory":"Beauty Salon",
            "type":"Services"
        }
    ],
    "sg:phone":"+32 50 71 27 65",
    "sg:postcode":"9990",
    "sg:province":"Oost-Vlaanderen",
    "sg:tags":[
        "de",
        "coiffure"
    ],
    "wof:name":"Coiffure Rubin",
    "wof:placetype":"venue"
},
  "geometry": {"coordinates":[3.4416480064,51.2109069824],"type":"Point"}
}