{
  "type": "Feature",
  "properties": {
    "addr:full":"Rue Jacques Jordaens 32 Bruxelles Bruxelles-Capitale 1000",
    "addr:housenumber":"32",
    "addr:postcode":"1000",
    "addr:street":"Rue Jacques Jordaens",
    "iso:country":"BE",
    "sg:address":"Rue Jacques Jordaens 32",
    "sg:city":"Bruxelles",
    "sg:classifiers":[
        {
            "category":"Shopping",
            "subcategory":"Antiques",
            "type":"Retail Goods"
        }
    ],
    "sg:phone":"+32 2 648 00 80",
    "sg:postcode":"1000",
    "sg:province":"Bruxelles-Capitale",
    "wof:name":"Sotheby's Sa",
    "wof:placetype":"venue"
},
  "geometry": {"coordinates":[4.3685340881,50.8210220337],"type":"Point"}
}