{
  "type": "Feature",
  "properties": {
    "addr:full":"Polderdijkweg 447haven Antwerpen Antwerpen 2030",
    "addr:postcode":"2030",
    "addr:street":"447Haven",
    "iso:country":"BE",
    "sg:address":"Polderdijkweg 447haven",
    "sg:city":"Antwerpen",
    "sg:classifiers":[
        {
            "category":"Utilities",
            "subcategory":"Fuel Oil & Lpg",
            "type":"Services"
        }
    ],
    "sg:phone":"+32 3 543 31 11",
    "sg:postcode":"2030",
    "sg:province":"Antwerpen",
    "sg:tags":[
        "refinery"
    ],
    "wof:name":"Esso Belgium, Divisie Van Exxonmobil Petroleum & Chemical",
    "wof:placetype":"venue"
},
  "geometry": {"coordinates":[4.3439741135,51.2626876831],"type":"Point"}
}