{
  "type": "Feature",
  "properties": {
    "iso:country":"BE",
    "sg:address":"Rue Henin 33",
    "sg:city":"Farciennes",
    "sg:orig_category":"Brood, gebak and snoepgoed",
    "sg:phone":"+32 71 38 18 74",
    "sg:postcode":"6240",
    "sg:province":"Hainaut",
    "wof:name":"Robert Trefois",
    "wof:placetype":"venue"
},
  "geometry": {"coordinates":[4.5469360352,50.4271354675],"type":"Point"}
}