{
  "type": "Feature",
  "properties": {
    "addr:full":"Rue De Jemeppe 57 Ans Li\u00e8ge 4431",
    "addr:housenumber":"57",
    "addr:postcode":"4431",
    "addr:street":"Rue De Jemeppe",
    "iso:country":"BE",
    "sg:address":"Rue De Jemeppe 57",
    "sg:city":"Ans",
    "sg:orig_category":"Pain, p\u00e2tisseries and confiseries",
    "sg:phone":"+32 4 263 58 12",
    "sg:postcode":"4431",
    "sg:province":"Li\u00e8ge",
    "wof:name":"Lhoest Serge",
    "wof:placetype":"venue"
},
  "geometry": {"coordinates":[5.5024929047,50.6646614075],"type":"Point"}
}