{
  "type": "Feature",
  "properties": {
    "addr:full":"Rue Hanesse 1 Andenne Namur 5300",
    "addr:housenumber":"1",
    "addr:postcode":"5300",
    "addr:street":"Rue Hanesse",
    "iso:country":"BE",
    "sg:address":"Rue Hanesse 1",
    "sg:city":"Andenne",
    "sg:classifiers":[
        {
            "category":"Professional",
            "subcategory":"Art Services",
            "type":"Services"
        }
    ],
    "sg:phone":"+32 485 72 77 27",
    "sg:postcode":"5300",
    "sg:province":"Namur",
    "sg:tags":[
        "-",
        "painter",
        "artist"
    ],
    "wof:name":"Art Wall Image",
    "wof:placetype":"venue"
},
  "geometry": {"coordinates":[5.0981669426,50.4861221313],"type":"Point"}
}