{
  "type": "Feature",
  "properties": {
    "addr:full":"Krekelgrachtstraat 14a Riemst Limburg 3770",
    "addr:housenumber":"14a",
    "addr:postcode":"3770",
    "addr:street":"Krekelgrachtstraat",
    "iso:country":"BE",
    "sg:address":"Krekelgrachtstraat 14a",
    "sg:city":"Riemst",
    "sg:orig_category":"Sportclubs",
    "sg:phone":"+32 12 45 46 78",
    "sg:postcode":"3770",
    "sg:province":"Limburg",
    "wof:name":"Eddy Merckx Boys - Meise",
    "wof:placetype":"venue"
},
  "geometry": {"coordinates":[5.6084961891,50.806350708],"type":"Point"}
}