{
  "type": "Feature",
  "properties": {
    "iso:country":"BE",
    "sg:address":"Aarschotsebaan 294",
    "sg:city":"Berlaar",
    "sg:classifiers":[
        {
            "category":"Banks & Credit Unions",
            "subcategory":"Bureau De Change",
            "type":"Services"
        }
    ],
    "sg:phone":"+32 3 482 25 66",
    "sg:postcode":"2590",
    "sg:province":"Antwerpen",
    "sg:tags":[
        "-",
        "household",
        "gas"
    ],
    "wof:name":"Verlinden Jozef & Lena Berlaarse Gashandel",
    "wof:placetype":"venue"
},
  "geometry": {"coordinates":[4.6402330399,51.0874938965],"type":"Point"}
}