{
  "type": "Feature",
  "properties": {
    "addr:full":"Place De L'h\u00d4tel De Ville 11 Eupen/eupen Li\u00e8ge 4700",
    "addr:housenumber":"11",
    "addr:postcode":"4700",
    "addr:street":"Place De L'Ho \u0302Tel De Ville",
    "iso:country":"BE",
    "sg:address":"Place De L'h\u00d4tel De Ville 11",
    "sg:city":"Eupen/eupen",
    "sg:orig_category":"Banques and organismes de cr\u00e9dit",
    "sg:phone":"+32 87 74 38 09",
    "sg:postcode":"4700",
    "sg:province":"Li\u00e8ge",
    "wof:name":"Dexia",
    "wof:placetype":"venue"
},
  "geometry": {"coordinates":[6.1348800659,50.5989990234],"type":"Point"}
}