{
  "type": "Feature",
  "properties": {
    "addr:full":"Avenue De La Pairelle 83 Namur Namur 5000",
    "addr:housenumber":"83",
    "addr:postcode":"5000",
    "addr:street":"Avenue De La Pairelle",
    "iso:country":"BE",
    "sg:address":"Avenue De La Pairelle 83",
    "sg:city":"Namur",
    "sg:classifiers":[
        {
            "category":"Real Estate",
            "subcategory":"Architect",
            "type":"Services"
        }
    ],
    "sg:phone":"+32 81 23 18 11",
    "sg:postcode":"5000",
    "sg:province":"Namur",
    "wof:name":"Nelis-tellier Sprl",
    "wof:placetype":"venue"
},
  "geometry": {"coordinates":[4.8618597984,50.4373283386],"type":"Point"}
}