{
  "type": "Feature",
  "properties": {
    "iso:country":"BE",
    "sg:address":"Rue De La Senne 21b1",
    "sg:city":"Soignies",
    "sg:classifiers":[
        {
            "category":"Cafe",
            "type":"Food & Drink"
        }
    ],
    "sg:phone":"+32 67 33 17 30",
    "sg:postcode":"7060",
    "sg:province":"Hainaut",
    "sg:tags":[
        "caf\u00e9s"
    ],
    "wof:name":"Andrew Michael",
    "wof:placetype":"venue"
},
  "geometry": {"coordinates":[4.0684509277,50.5827865601],"type":"Point"}
}