{
  "type": "Feature",
  "properties": {
    "addr:full":"Grand-rue 58 Clavier Li\u00e8ge 4560",
    "addr:housenumber":"58",
    "addr:postcode":"4560",
    "addr:street":"Grand-Rue",
    "iso:country":"BE",
    "sg:address":"Grand-rue 58",
    "sg:city":"Clavier",
    "sg:orig_category":"Electrom\u00e9nager, t\u00e9l\u00e9visions and radios. R\u00e9parations d'appareils \u00e9lectrom\u00e9nagers",
    "sg:phone":"+32 86 34 42 27",
    "sg:postcode":"4560",
    "sg:province":"Li\u00e8ge",
    "wof:name":"Marcel Septon",
    "wof:placetype":"venue"
},
  "geometry": {"coordinates":[5.3226718903,50.4294242859],"type":"Point"}
}