{
  "type": "Feature",
  "properties": {
    "iso:country":"BE",
    "sg:address":"Avenue De Bouillon 71",
    "sg:city":"Libramont-chevigny (libramont)",
    "sg:classifiers":[
        {
            "category":"Travel",
            "subcategory":"Hotels & Motels",
            "type":"Entertainment"
        }
    ],
    "sg:phone":"+32 61 22 25 61",
    "sg:postcode":"6800",
    "sg:province":"Luxembourg",
    "wof:name":"Bon Vieux Temps (le)",
    "wof:placetype":"venue"
},
  "geometry": {"coordinates":[5.36774683,49.9166412354],"type":"Point"}
}