{
  "type": "Feature",
  "properties": {
    "addr:full":"Prinses Paolalaan 14 Menen West-Vlaanderen 8930",
    "addr:housenumber":"14",
    "addr:postcode":"8930",
    "addr:street":"Prinses Paolalaan",
    "iso:country":"BE",
    "sg:address":"Prinses Paolalaan 14",
    "sg:city":"Menen",
    "sg:classifiers":[
        {
            "category":"Arena",
            "subcategory":"Sports Club",
            "type":"Entertainment"
        }
    ],
    "sg:phone":"+32 56 51 80 46",
    "sg:postcode":"8930",
    "sg:province":"West-Vlaanderen",
    "sg:tags":[
        "de"
    ],
    "wof:name":"Turnclub Steeds Hoger",
    "wof:placetype":"venue"
},
  "geometry": {"coordinates":[3.1342198849,50.791015625],"type":"Point"}
}