{
  "type": "Feature",
  "properties": {
    "addr:full":"Rue De La Clef 6 Fl\u00e9ron Li\u00e8ge 4620",
    "addr:housenumber":"6",
    "addr:postcode":"4620",
    "addr:street":"Rue De La Clef",
    "iso:country":"BE",
    "sg:address":"Rue De La Clef 6",
    "sg:city":"Fl\u00e9ron",
    "sg:classifiers":[
        {
            "category":"Cafe",
            "type":"Food & Drink"
        }
    ],
    "sg:phone":"+32 4 388 44 08",
    "sg:postcode":"4620",
    "sg:province":"Li\u00e8ge",
    "sg:tags":[
        "snack-bars"
    ],
    "wof:name":"Cherche Midi (le)",
    "wof:placetype":"venue"
},
  "geometry": {"coordinates":[5.6890239716,50.6147766113],"type":"Point"}
}