{
  "type": "Feature",
  "properties": {
    "iso:country":"BE",
    "sg:address":"Grote Markt 30",
    "sg:city":"Dendermonde",
    "sg:classifiers":[
        {
            "category":"Bars & Pubs",
            "type":"Food & Drink"
        }
    ],
    "sg:phone":"+32 52 21 06 39",
    "sg:postcode":"9200",
    "sg:province":"Oost-Vlaanderen",
    "wof:name":"Ahura Eetkafee",
    "wof:placetype":"venue"
},
  "geometry": {"coordinates":[4.0977511406,51.0311355591],"type":"Point"}
}