{
  "type": "Feature",
  "properties": {
    "iso:country":"BE",
    "sg:address":"Sint-katelijnevest 53",
    "sg:city":"Antwerpen",
    "sg:classifiers":[
        {
            "category":"Building & Trades",
            "subcategory":"Equipment Rental",
            "type":"Services"
        }
    ],
    "sg:phone":"+32 3 234 12 82",
    "sg:postcode":"2000",
    "sg:province":"Antwerpen",
    "sg:tags":[
        "lighting",
        "-",
        "fixture"
    ],
    "wof:name":"Hi-fi Centrum Decreus",
    "wof:placetype":"venue"
},
  "geometry": {"coordinates":[4.4054532051,51.2196083069],"type":"Point"}
}