{
  "type": "Feature",
  "properties": {
    "addr:full":"Petit Vin\u00c2ve 9 Malmedy Li\u00e8ge 4960",
    "addr:housenumber":"9",
    "addr:postcode":"4960",
    "addr:street":"Petit Vina\u0302Ve",
    "iso:country":"BE",
    "sg:address":"Petit Vin\u00c2ve 9",
    "sg:city":"Malmedy",
    "sg:classifiers":[
        {
            "category":"Insurance",
            "subcategory":"Life Insurance",
            "type":"Services"
        }
    ],
    "sg:phone":"+32 80 33 75 99",
    "sg:postcode":"4960",
    "sg:province":"Li\u00e8ge",
    "sg:tags":[
        "assurance"
    ],
    "wof:name":"J.p.g. Gestion",
    "wof:placetype":"venue"
},
  "geometry": {"coordinates":[6.0298700333,50.425743103],"type":"Point"}
}