{
  "type": "Feature",
  "properties": {
    "iso:country":"BE",
    "sg:address":"Ave Des Combattants 66",
    "sg:city":"Court St. Etienne",
    "sg:classifiers":[
        {
            "category":"Banks & Credit Unions",
            "subcategory":"Bank",
            "type":"Services"
        }
    ],
    "sg:phone":"+32 10 61 46 55",
    "sg:postcode":"1490",
    "sg:province":"Brabant Wallon",
    "wof:name":"G\u00e9n\u00e9rale De Banque Sa",
    "wof:placetype":"venue"
},
  "geometry": {"coordinates":[4.5626811981,50.6478347778],"type":"Point"}
}