{
  "type": "Feature",
  "properties": {
    "iso:country":"BE",
    "sg:address":"Urselseweg 255",
    "sg:city":"Knesselare",
    "sg:classifiers":[
        {
            "category":"Bakery",
            "type":"Food & Drink"
        }
    ],
    "sg:phone":"+32 9 374 12 96",
    "sg:postcode":"9910",
    "sg:province":"Oost-Vlaanderen",
    "sg:tags":[
        "confectioner",
        "baker"
    ],
    "wof:name":"Trenson G",
    "wof:placetype":"venue"
},
  "geometry": {"coordinates":[3.4427700043,51.1326789856],"type":"Point"}
}