{
  "type": "Feature",
  "properties": {
    "iso:country":"BE",
    "sg:address":"Edmond Vandervaerenstraat 64",
    "sg:city":"Hoeilaart",
    "sg:classifiers":[
        {
            "category":"Shopping",
            "subcategory":"Clothing, Apparel, & Fashions",
            "type":"Retail Goods"
        }
    ],
    "sg:phone":"+32 2 657 52 46",
    "sg:postcode":"1560",
    "sg:province":"Vlaams-Brabant",
    "sg:tags":[
        "leather",
        "-",
        "buckskin",
        "clothing"
    ],
    "wof:name":"Katerina Furs",
    "wof:placetype":"venue"
},
  "geometry": {"coordinates":[4.4654622078,50.7732925415],"type":"Point"}
}