{
  "type": "Feature",
  "properties": {
    "addr:full":"Antwerpsestaat 150 Lier Antwerpen 2500",
    "addr:housenumber":"150",
    "addr:postcode":"2500",
    "iso:country":"BE",
    "sg:address":"Antwerpsestaat 150",
    "sg:city":"Lier",
    "sg:orig_category":"Randstad",
    "sg:phone":"+32 3 491 99 90",
    "sg:postcode":"2500",
    "sg:province":"Antwerpen",
    "wof:name":"Randstad",
    "wof:placetype":"venue"
},
  "geometry": {"coordinates":[4.5547590256,51.1400375366],"type":"Point"}
}