{
  "type": "Feature",
  "properties": {
    "addr:full":"Beekstraat 5 Turnhout Antwerpen 2300",
    "addr:housenumber":"5",
    "addr:postcode":"2300",
    "addr:street":"Beekstraat",
    "iso:country":"BE",
    "sg:address":"Beekstraat 5",
    "sg:city":"Turnhout",
    "sg:orig_category":"Enseignement maternel and primaire",
    "sg:phone":"+32 14 41 89 11",
    "sg:postcode":"2300",
    "sg:province":"Antwerpen",
    "wof:name":"Vrije Kleuterschool",
    "wof:placetype":"venue"
},
  "geometry": {"coordinates":[4.9519920349,51.3217887878],"type":"Point"}
}