{
  "type": "Feature",
  "properties": {
    "iso:country":"BE",
    "sg:address":"Avenue Montjoie 81",
    "sg:city":"Ukkel/uccle",
    "sg:orig_category":"Traitements param\u00e9dicaux",
    "sg:phone":"+32 2 345 76 56",
    "sg:postcode":"1180",
    "sg:province":"Bruxelles-Capitale",
    "wof:name":"R. Honhon",
    "wof:placetype":"venue"
},
  "geometry": {"coordinates":[4.3657708168,50.8103065491],"type":"Point"}
}