{
  "type": "Feature",
  "properties": {
    "addr:full":"Chauss\u00e9e De Charleroi 15 Charleroi (montignies-sur-sambre) Hainaut 6061",
    "addr:housenumber":"15",
    "addr:postcode":"6061",
    "addr:street":"Chausse\u0301E De Charleroi",
    "iso:country":"BE",
    "sg:address":"Chauss\u00e9e De Charleroi 15",
    "sg:city":"Charleroi (montignies-sur-sambre)",
    "sg:classifiers":[
        {
            "category":"Retail",
            "subcategory":"Laundry & Dry Cleaning",
            "type":"Services"
        }
    ],
    "sg:phone":"+32 71 31 72 69",
    "sg:postcode":"6061",
    "sg:province":"Hainaut",
    "sg:tags":[
        "dyer",
        "cleaner"
    ],
    "wof:name":"Marie Claude",
    "wof:placetype":"venue"
},
  "geometry": {"coordinates":[4.4783911705,50.4010353088],"type":"Point"}
}