{
  "type": "Feature",
  "properties": {
    "iso:country":"BE",
    "sg:address":"Ontvoeringsplein 12",
    "sg:city":"Mechelen",
    "sg:orig_category":"Pre-press",
    "sg:phone":"+32 15 29 38 00",
    "sg:postcode":"2800",
    "sg:province":"Antwerpen",
    "wof:name":"Lu's Paragraph Nv",
    "wof:placetype":"venue"
},
  "geometry": {"coordinates":[4.4893498421,51.0303115845],"type":"Point"}
}