{
  "type": "Feature",
  "properties": {
    "addr:full":"Guillaume Herinckxlaan 68 Ukkel/uccle Bruxelles-Capitale 1180",
    "addr:housenumber":"68",
    "addr:postcode":"1180",
    "addr:street":"Guillaume Herinckxlaan;/",
    "iso:country":"BE",
    "sg:address":"Guillaume Herinckxlaan 68",
    "sg:city":"Ukkel/uccle",
    "sg:orig_category":"Paramedische behandelingen",
    "sg:phone":"+32 2 332 49 82",
    "sg:postcode":"1180",
    "sg:province":"Bruxelles-Capitale",
    "wof:name":"S. Bachy",
    "wof:placetype":"venue"
},
  "geometry": {"coordinates":[4.3320841789,50.7954711914],"type":"Point"}
}