{
  "type": "Feature",
  "properties": {
    "iso:country":"BE",
    "sg:address":"Hof Van Obbergenstraat 4",
    "sg:city":"Grimbergen (beigem)",
    "sg:classifiers":[
        {
            "category":"Professional",
            "type":"Services"
        }
    ],
    "sg:phone":"+32 2 270 18 70",
    "sg:postcode":"1852",
    "sg:province":"Vlaams-Brabant",
    "sg:tags":[
        "entertainer"
    ],
    "wof:name":"Habils H",
    "wof:placetype":"venue"
},
  "geometry": {"coordinates":[4.3638281822,50.952293396],"type":"Point"}
}