{
  "type": "Feature",
  "properties": {
    "iso:country":"BE",
    "sg:address":"Frans Lyceumlaan 6",
    "sg:city":"Ukkel/uccle",
    "sg:orig_category":"Rusthuizen and serviceflats",
    "sg:phone":"+32 2 375 37 44",
    "sg:postcode":"1180",
    "sg:province":"Bruxelles-Capitale",
    "wof:name":"Les R\u00c9sidences Services",
    "wof:placetype":"venue"
},
  "geometry": {"coordinates":[4.344563961,50.7899780273],"type":"Point"}
}