{
  "type": "Feature",
  "properties": {
    "addr:full":"Quai De Coronmeuse 24 Li\u00e8ge 1 Li\u00e8ge 4000",
    "addr:housenumber":"24;1",
    "addr:postcode":"4000",
    "addr:street":"Quai De Coronmeuse",
    "iso:country":"BE",
    "sg:address":"Quai De Coronmeuse 24",
    "sg:city":"Li\u00e8ge 1",
    "sg:classifiers":[
        {
            "category":"Farming",
            "subcategory":"Fish & Marine Products",
            "type":"Manufacturing & Wholesale Goods"
        }
    ],
    "sg:phone":"+32 4 227 17 10",
    "sg:postcode":"4000",
    "sg:province":"Li\u00e8ge",
    "sg:tags":[
        "surveyor",
        "-"
    ],
    "wof:name":"Meyers J",
    "wof:placetype":"venue"
},
  "geometry": {"coordinates":[5.6023449898,50.6515655518],"type":"Point"}
}