{
  "type": "Feature",
  "properties": {
    "addr:full":"Pontweg 141 Aalst (herdersem) Oost-Vlaanderen 9310",
    "addr:housenumber":"141",
    "addr:postcode":"9310",
    "addr:street":"Pontweg",
    "iso:country":"BE",
    "sg:address":"Pontweg 141",
    "sg:city":"Aalst (herdersem)",
    "sg:classifiers":[
        {
            "category":"Retail",
            "subcategory":"Auto Repair",
            "type":"Services"
        }
    ],
    "sg:phone":"+32 53 70 38 56",
    "sg:postcode":"9310",
    "sg:province":"Oost-Vlaanderen",
    "sg:tags":[
        "garage"
    ],
    "wof:name":"Dierickx J",
    "wof:placetype":"venue"
},
  "geometry": {"coordinates":[4.0774598122,50.961391449],"type":"Point"}
}