{
  "type": "Feature",
  "properties": {
    "addr:full":"Rue Des Banni\u00e8res 28 Bruxelles (woluwe-saint-pierre) Bruxelles-Capitale 1150",
    "addr:housenumber":"28",
    "addr:postcode":"1150",
    "addr:street":"Rue Des Bannie\u0300Res",
    "iso:country":"BE",
    "sg:address":"Rue Des Banni\u00e8res 28",
    "sg:city":"Bruxelles (woluwe-saint-pierre)",
    "sg:classifiers":[
        {
            "category":"Professional",
            "subcategory":"Credit Reporting & Collection",
            "type":"Services"
        }
    ],
    "sg:phone":"+32 2 771 72 60",
    "sg:postcode":"1150",
    "sg:province":"Bruxelles-Capitale",
    "sg:tags":[
        "bailiff"
    ],
    "wof:name":"De Haes M C",
    "wof:placetype":"venue"
},
  "geometry": {"coordinates":[4.4328231812,50.8399085999],"type":"Point"}
}