{
  "type": "Feature",
  "properties": {
    "iso:country":"BE",
    "sg:address":"Tiensestraat 73",
    "sg:city":"Scherpenheuvel-zichem",
    "sg:classifiers":[
        {
            "category":"Travel",
            "subcategory":"Bed & Breakfast",
            "type":"Entertainment"
        }
    ],
    "sg:phone":"+32 13 77 15 90",
    "sg:postcode":"3271",
    "sg:province":"Vlaams-Brabant",
    "sg:tags":[
        "voyage",
        "de",
        "agences",
        "flash",
        "holidays",
        "plus"
    ],
    "wof:name":"Pego",
    "wof:placetype":"venue"
},
  "geometry": {"coordinates":[4.9571690559,50.9844055176],"type":"Point"}
}