{
  "type": "Feature",
  "properties": {
    "addr:full":"Limberg 37 Herselt Antwerpen 2230",
    "addr:housenumber":"37",
    "addr:postcode":"2230",
    "addr:street":"Limberg",
    "iso:country":"BE",
    "sg:address":"Limberg 37",
    "sg:city":"Herselt",
    "sg:classifiers":[
        {
            "category":"Retail",
            "subcategory":"Repair Shop",
            "type":"Services"
        }
    ],
    "sg:phone":"+32 14 54 15 24",
    "sg:postcode":"2230",
    "sg:province":"Antwerpen",
    "wof:name":"D S T Karweidienst",
    "wof:placetype":"venue"
},
  "geometry": {"coordinates":[4.87271595,51.0576667786],"type":"Point"}
}