{
  "type": "Feature",
  "properties": {
    "addr:full":"Rue J. Vander Veken 27 Wemmel Vlaams-Brabant 1780",
    "addr:housenumber":"27",
    "addr:postcode":"1780",
    "addr:street":"Rue J. Vander Veken;Vlaams-Brabant",
    "iso:country":"BE",
    "sg:address":"Rue J. Vander Veken 27",
    "sg:city":"Wemmel",
    "sg:classifiers":[
        {
            "category":"Building & Trades",
            "subcategory":"Plumbing",
            "type":"Services"
        }
    ],
    "sg:phone":"+32 2 461 05 13",
    "sg:postcode":"1780",
    "sg:province":"Vlaams-Brabant",
    "sg:tags":[
        "repair",
        "mainten",
        "-",
        "central",
        "heating"
    ],
    "wof:name":"A.a.a.m / Vanderelst",
    "wof:placetype":"venue"
},
  "geometry": {"coordinates":[4.3152189255,50.9086036682],"type":"Point"}
}