{
  "type": "Feature",
  "properties": {
    "iso:country":"BE",
    "sg:address":"H. Caronstraat 16",
    "sg:city":"Hoeilaart",
    "sg:orig_category":"Foto-uitrusting Fotografen and fotostudio's Telecommunicatieapparaten",
    "sg:phone":"+32 2 657 99 03",
    "sg:postcode":"1560",
    "sg:province":"Vlaams-Brabant",
    "wof:name":"Top Camera Camera Obscura",
    "wof:placetype":"venue"
},
  "geometry": {"coordinates":[4.4755988121,50.7670516968],"type":"Point"}
}