{
  "type": "Feature",
  "properties": {
    "addr:full":"Antoon Van Dyckstraat 23 Antwerpen Antwerpen 2018",
    "addr:housenumber":"23",
    "addr:postcode":"2018",
    "addr:street":"Antoon Van Dyckstraat",
    "iso:country":"BE",
    "sg:address":"Antoon Van Dyckstraat 23",
    "sg:city":"Antwerpen",
    "sg:classifiers":[
        {
            "category":"Professional",
            "subcategory":"Art Services",
            "type":"Services"
        }
    ],
    "sg:phone":"+32 3 281 46 35",
    "sg:postcode":"2018",
    "sg:province":"Antwerpen",
    "sg:tags":[
        "interior",
        "designer"
    ],
    "wof:name":"Van Humbeeck A",
    "wof:placetype":"venue"
},
  "geometry": {"coordinates":[4.4159507751,51.2092285156],"type":"Point"}
}