{
  "type": "Feature",
  "properties": {
    "iso:country":"BE",
    "sg:address":"Vuurkruisenlaan 36",
    "sg:city":"Wijnegem",
    "sg:classifiers":[
        {
            "category":"Professional",
            "subcategory":"Accounting & Tax Preparation",
            "type":"Services"
        }
    ],
    "sg:phone":"+32 3 354 33 12",
    "sg:postcode":"2110",
    "sg:province":"Antwerpen",
    "sg:tags":[
        "bookkeeper"
    ],
    "wof:name":"De Bruyn R",
    "wof:placetype":"venue"
},
  "geometry": {"coordinates":[4.5113739967,51.2281837463],"type":"Point"}
}