{
  "type": "Feature",
  "properties": {
    "iso:country":"BE",
    "sg:address":"Rue Vieille Voie 51",
    "sg:city":"Vis\u00e9 (cheratte)",
    "sg:classifiers":[
        {
            "category":"Building & Trades",
            "subcategory":"Landscaping Services",
            "type":"Services"
        }
    ],
    "sg:phone":"+32 4 370 65 23",
    "sg:postcode":"4602",
    "sg:province":"Li\u00e8ge",
    "sg:tags":[
        "gardening",
        "garden",
        "maintenance"
    ],
    "wof:name":"Jardin D\u00e9coratif",
    "wof:placetype":"venue"
},
  "geometry": {"coordinates":[5.6751770973,50.6841201782],"type":"Point"}
}