{
  "type": "Feature",
  "properties": {
    "iso:country":"BE",
    "sg:address":"Rue De La Station 139",
    "sg:city":"Estaimpuis",
    "sg:orig_category":"Woningbouw",
    "sg:phone":"+32 69 35 39 19",
    "sg:postcode":"7730",
    "sg:province":"Hainaut",
    "wof:name":"David Fabbrizio",
    "wof:placetype":"venue"
},
  "geometry": {"coordinates":[3.2935009003,50.6700248718],"type":"Point"}
}