{
  "type": "Feature",
  "properties": {
    "iso:country":"BE",
    "sg:address":"Overwinningsstraat 15b2m",
    "sg:city":"Niel",
    "sg:orig_category":"Maatschappelijke dienstverlening",
    "sg:phone":"+32 3 290 37 63",
    "sg:postcode":"2845",
    "sg:province":"Antwerpen",
    "wof:name":"Rode Kruis Niel-schelle",
    "wof:placetype":"venue"
},
  "geometry": {"coordinates":[4.3290538788,51.1113319397],"type":"Point"}
}