{
  "type": "Feature",
  "properties": {
    "addr:full":"Izegemsestraat 412a Kortrijk (heule) West-Vlaanderen 8501",
    "addr:housenumber":"412a",
    "addr:postcode":"8501",
    "addr:street":"Izegemsestraat",
    "iso:country":"BE",
    "sg:address":"Izegemsestraat 412a",
    "sg:city":"Kortrijk (heule)",
    "sg:classifiers":[
        {
            "category":"Food & Beverages",
            "subcategory":"Supermarket",
            "type":"Retail Goods"
        }
    ],
    "sg:phone":"+32 56 37 03 82",
    "sg:postcode":"8501",
    "sg:province":"West-Vlaanderen",
    "sg:tags":[
        "frozen",
        "-"
    ],
    "wof:name":"Frozen Foods Commercial Bvba",
    "wof:placetype":"venue"
},
  "geometry": {"coordinates":[3.2514240742,50.8543510437],"type":"Point"}
}