{
  "type": "Feature",
  "properties": {
    "iso:country":"BE",
    "sg:address":"Rue De La Maison Blanche 10",
    "sg:city":"Estaimpuis (evregnies)",
    "sg:classifiers":[
        {
            "category":"Building & Trades",
            "subcategory":"Electrical",
            "type":"Services"
        }
    ],
    "sg:phone":"+32 56 48 90 66",
    "sg:postcode":"7730",
    "sg:province":"Hainaut",
    "sg:tags":[
        "electric",
        "-",
        "housewiring",
        "contractor"
    ],
    "wof:name":"Balcaen J.m.",
    "wof:placetype":"venue"
},
  "geometry": {"coordinates":[3.288369894,50.7145805359],"type":"Point"}
}