{
  "type": "Feature",
  "properties": {
    "iso:country":"BE",
    "sg:address":"Molenstraat 20",
    "sg:city":"Zonnebeke (passendale)",
    "sg:classifiers":[
        {
            "category":"Farming",
            "subcategory":"Fish & Marine Products",
            "type":"Manufacturing & Wholesale Goods"
        }
    ],
    "sg:phone":"+32 51 77 09 33",
    "sg:postcode":"8980",
    "sg:province":"West-Vlaanderen",
    "sg:tags":[
        "retail",
        "-",
        "shellfish"
    ],
    "wof:name":"Viswienkeltje ('t)",
    "wof:placetype":"venue"
},
  "geometry": {"coordinates":[3.0215249062,50.9017524719],"type":"Point"}
}