{
  "type": "Feature",
  "properties": {
    "iso:country":"BE",
    "sg:address":"Stationsstraat 114",
    "sg:city":"Sint-niklaas",
    "sg:classifiers":[
        {
            "category":"Shopping",
            "subcategory":"Jewelry",
            "type":"Retail Goods"
        }
    ],
    "sg:phone":"+32 3 777 92 71",
    "sg:postcode":"9100",
    "sg:province":"Oost-Vlaanderen",
    "sg:tags":[
        "-",
        "imitation"
    ],
    "wof:name":"De Stijl",
    "wof:placetype":"venue"
},
  "geometry": {"coordinates":[4.1422247887,51.1696662903],"type":"Point"}
}