{
  "type": "Feature",
  "properties": {
    "addr:full":"Avenue Roi Albert 7 Le Roeulx Hainaut 7070",
    "addr:housenumber":"7",
    "addr:postcode":"7070",
    "addr:street":"Avenue Roi Albert",
    "iso:country":"BE",
    "sg:address":"Avenue Roi Albert 7",
    "sg:city":"Le Roeulx",
    "sg:orig_category":"Bloemen and planten",
    "sg:phone":"+32 64 65 06 17",
    "sg:postcode":"7070",
    "sg:province":"Hainaut",
    "wof:name":"Van Hove-gava",
    "wof:placetype":"venue"
},
  "geometry": {"coordinates":[4.1113100052,50.5051422119],"type":"Point"}
}