{
  "type": "Feature",
  "properties": {
    "iso:country":"BE",
    "sg:address":"Rue Ardichamps 10a",
    "sg:city":"Braine-le-chateau",
    "sg:orig_category":"Diverse opleidingen and onderwijs Informaticaconsulenten Software ontwikkeling and ontwerp Technisch",
    "sg:phone":"+32 2 366 96 70",
    "sg:postcode":"1440",
    "sg:province":"Brabant Wallon",
    "wof:name":"Dip",
    "wof:placetype":"venue"
},
  "geometry": {"coordinates":[4.3061008453,50.6907653809],"type":"Point"}
}