{
  "type": "Feature",
  "properties": {
    "iso:country":"BE",
    "sg:address":"Houterveld 5",
    "sg:city":"Geel",
    "sg:orig_category":"Artiesten and kunstenaars",
    "sg:phone":"+32 14 58 63 80",
    "sg:postcode":"2440",
    "sg:province":"Antwerpen",
    "wof:name":"Achilles Cools",
    "wof:placetype":"venue"
},
  "geometry": {"coordinates":[4.9185519218,51.1798286438],"type":"Point"}
}