{
  "type": "Feature",
  "properties": {
    "addr:full":"Stuivenbergstraat 130 Oostkamp West-Vlaanderen 8020",
    "addr:housenumber":"130",
    "addr:postcode":"8020",
    "addr:street":"Stuivenbergstraat",
    "iso:country":"BE",
    "sg:address":"Stuivenbergstraat 130",
    "sg:city":"Oostkamp",
    "sg:orig_category":"Eleveurs and marchands de porcs. Eleveurs de bovins",
    "sg:phone":"+32 50 82 26 37",
    "sg:postcode":"8020",
    "sg:province":"West-Vlaanderen",
    "wof:name":"Dirk Teetaert",
    "wof:placetype":"venue"
},
  "geometry": {"coordinates":[3.2740280628,51.1381187439],"type":"Point"}
}