{
  "type": "Feature",
  "properties": {
    "iso:country":"BE",
    "sg:address":"Sint-bavostraat 2",
    "sg:city":"Wielsbeke",
    "sg:orig_category":"Epiceries",
    "sg:phone":"+32 56 60 21 57",
    "sg:postcode":"8710",
    "sg:province":"West-Vlaanderen",
    "wof:name":"Adrienne Taelman",
    "wof:placetype":"venue"
},
  "geometry": {"coordinates":[3.3908069134,50.9097633362],"type":"Point"}
}