{
  "type": "Feature",
  "properties": {
    "iso:country":"BE",
    "sg:address":"Weg Naar Zwartberg 26",
    "sg:city":"Opglabbeek",
    "sg:classifiers":[
        {
            "category":"Home & Garden",
            "subcategory":"Home Furnishings",
            "type":"Retail Goods"
        }
    ],
    "sg:phone":"+32 89 85 40 12",
    "sg:postcode":"3660",
    "sg:province":"Limburg",
    "sg:tags":[
        "curtain",
        "-",
        "fixture"
    ],
    "wof:name":"Paredis (huis)",
    "wof:placetype":"venue"
},
  "geometry": {"coordinates":[5.5804510117,51.0419235229],"type":"Point"}
}