{
  "type": "Feature",
  "properties": {
    "addr:full":"Boulevard E De Laveleye 153 Luik Li\u00e8ge 4020",
    "addr:housenumber":"153",
    "addr:postcode":"4020",
    "addr:street":"Boulevard E De Laveleye;Luik Lie\u0300Ge",
    "iso:country":"BE",
    "sg:address":"Boulevard E De Laveleye 153",
    "sg:city":"Luik",
    "sg:orig_category":"Winkelinrichting and handelsuitrusting Gh",
    "sg:phone":"+32 4 342 16 03",
    "sg:postcode":"4020",
    "sg:province":"Li\u00e8ge",
    "wof:name":"C T R",
    "wof:placetype":"venue"
},
  "geometry": {"coordinates":[5.5910868645,50.6212501526],"type":"Point"}
}