{
  "type": "Feature",
  "properties": {
    "addr:full":"Gistelse Steenweg 186 Brugge (sint-andries) West-Vlaanderen 8200",
    "addr:housenumber":"186",
    "addr:postcode":"8200",
    "addr:street":"Gistelse Steenweg",
    "iso:country":"BE",
    "sg:address":"Gistelse Steenweg 186",
    "sg:city":"Brugge (sint-andries)",
    "sg:classifiers":[
        {
            "category":"Personal",
            "subcategory":"Shoe Repair & Shine",
            "type":"Services"
        }
    ],
    "sg:phone":"+32 50 38 59 37",
    "sg:postcode":"8200",
    "sg:province":"West-Vlaanderen",
    "sg:tags":[
        "shoemaker"
    ],
    "wof:name":"Peter",
    "wof:placetype":"venue"
},
  "geometry": {"coordinates":[3.1992609501,51.2012329102],"type":"Point"}
}