{
  "type": "Feature",
  "properties": {
    "iso:country":"BE",
    "sg:address":"Feldweg 24",
    "sg:city":"Eupen/eupen",
    "sg:orig_category":"R\u00e9cup\u00e9ration de mati\u00e8res m\u00e9talliques recyclables and d\u00e9molisseurs de voitures. Taxis. Entretien et r",
    "sg:phone":"+32 87 55 44 39",
    "sg:postcode":"4701",
    "sg:province":"Li\u00e8ge",
    "wof:name":"Heinen",
    "wof:placetype":"venue"
},
  "geometry": {"coordinates":[6.0461649895,50.6460838318],"type":"Point"}
}