{
  "type": "Feature",
  "properties": {
    "addr:full":"Velodroomstraat 206 Boom Antwerpen 2850",
    "addr:housenumber":"206",
    "addr:postcode":"2850",
    "addr:street":"Velodroomstraat",
    "iso:country":"BE",
    "sg:address":"Velodroomstraat 206",
    "sg:city":"Boom",
    "sg:classifiers":[
        {
            "category":"Building & Trades",
            "subcategory":"Construction",
            "type":"Services"
        }
    ],
    "sg:phone":"+32 3 844 86 50",
    "sg:postcode":"2850",
    "sg:province":"Antwerpen",
    "sg:tags":[
        "la",
        "de",
        "\u00e9quipement",
        "pour",
        "machine",
        "location",
        "equipements"
    ],
    "wof:name":"Atlet Multicar",
    "wof:placetype":"venue"
},
  "geometry": {"coordinates":[4.3733730316,51.093006134],"type":"Point"}
}