{
  "type": "Feature",
  "properties": {
    "addr:full":"Chauss\u00e9e De Ghlin 146-148 Mons Hainaut 7000",
    "addr:postcode":"146-148;7000",
    "addr:street":"Chausse\u0301E De Ghlin;Hainaut",
    "iso:country":"BE",
    "sg:address":"Chauss\u00e9e De Ghlin 146-148",
    "sg:city":"Mons",
    "sg:classifiers":[
        {
            "category":"Health Services",
            "subcategory":"Hospital",
            "type":"Services"
        }
    ],
    "sg:phone":"+32 65 35 11 11",
    "sg:postcode":"7000",
    "sg:province":"Hainaut",
    "sg:tags":[
        "ambulance"
    ],
    "wof:name":"Ambulances Lepoint Sprl",
    "wof:placetype":"venue"
},
  "geometry": {"coordinates":[3.9336700439,50.4646606445],"type":"Point"}
}