{
  "type": "Feature",
  "properties": {
    "iso:country":"BE",
    "sg:address":"Marcottedreef 7",
    "sg:city":"Kapellen",
    "sg:orig_category":"Avocats and conseillers juridiques",
    "sg:phone":"+32 3 666 65 31",
    "sg:postcode":"2950",
    "sg:province":"Antwerpen",
    "wof:name":"D. Weyns",
    "wof:placetype":"venue"
},
  "geometry": {"coordinates":[4.4447770119,51.3448982239],"type":"Point"}
}