{
  "type": "Feature",
  "properties": {
    "iso:country":"BE",
    "sg:address":"Rue T'kint 30",
    "sg:city":"Bruxelles",
    "sg:classifiers":[
        {
            "category":"Personal",
            "subcategory":"Psychics & Astrologers",
            "type":"Services"
        }
    ],
    "sg:phone":"+32 475 47 96 65",
    "sg:postcode":"1000",
    "sg:province":"Bruxelles-Capitale",
    "sg:tags":[
        "astrology"
    ],
    "wof:name":"Astroconsult",
    "wof:placetype":"venue"
},
  "geometry": {"coordinates":[4.3425350189,50.8475875854],"type":"Point"}
}