{
  "type": "Feature",
  "properties": {
    "addr:full":"Meester Paul Gilsonlaan 445 Drogenbos/drogenbos Vlaams-Brabant 1620",
    "addr:housenumber":"445",
    "addr:postcode":"1620",
    "addr:street":"Meester Paul Gilsonlaan",
    "iso:country":"BE",
    "sg:address":"Meester Paul Gilsonlaan 445",
    "sg:city":"Drogenbos/drogenbos",
    "sg:classifiers":[
        {
            "category":"Fast Food",
            "type":"Food & Drink"
        }
    ],
    "sg:phone":"+32 2 377 39 64",
    "sg:postcode":"1620",
    "sg:province":"Vlaams-Brabant",
    "sg:tags":[
        "meeneem",
        "restaurant"
    ],
    "wof:name":"Quick",
    "wof:placetype":"venue"
},
  "geometry": {"coordinates":[4.3100500107,50.7969703674],"type":"Point"}
}