{
  "type": "Feature",
  "properties": {
    "addr:full":"Heilig Hartlaan 53 Lokeren Oost-Vlaanderen 9160",
    "addr:housenumber":"53",
    "addr:postcode":"9160",
    "addr:street":"Hartlaan",
    "iso:country":"BE",
    "sg:address":"Heilig Hartlaan 53",
    "sg:city":"Lokeren",
    "sg:classifiers":[
        {
            "category":"Building & Trades",
            "subcategory":"Plumbing",
            "type":"Services"
        }
    ],
    "sg:phone":"+32 9 348 39 73",
    "sg:postcode":"9160",
    "sg:province":"Oost-Vlaanderen",
    "sg:tags":[
        "contractor"
    ],
    "wof:name":"Quintelier R",
    "wof:placetype":"venue"
},
  "geometry": {"coordinates":[3.9889969826,51.0960922241],"type":"Point"}
}