{
  "type": "Feature",
  "properties": {
    "addr:full":"Square Larousse 26 Bruxelles (forest) Bruxelles-Capitale 1190",
    "addr:housenumber":"26",
    "addr:postcode":"1190",
    "addr:street":"Square Larousse",
    "iso:country":"BE",
    "sg:address":"Square Larousse 26",
    "sg:city":"Bruxelles (forest)",
    "sg:classifiers":[
        {
            "category":"Building & Trades",
            "subcategory":"Pest Control",
            "type":"Services"
        }
    ],
    "sg:phone":"+32 2 343 73 52",
    "sg:postcode":"1190",
    "sg:province":"Bruxelles-Capitale",
    "sg:tags":[
        "painting",
        "contractor"
    ],
    "wof:name":"Aronde",
    "wof:placetype":"venue"
},
  "geometry": {"coordinates":[4.3506817818,50.8199882507],"type":"Point"}
}