{
  "type": "Feature",
  "properties": {
    "addr:full":"Bruyelstraat 8 Harelbeke West-Vlaanderen 8531",
    "addr:housenumber":"8",
    "addr:postcode":"8531",
    "addr:street":"Bruyelstraat",
    "iso:country":"BE",
    "sg:address":"Bruyelstraat 8",
    "sg:city":"Harelbeke",
    "sg:orig_category":"Enseignement maternel and primaire",
    "sg:phone":"+32 56 71 09 98",
    "sg:postcode":"8531",
    "sg:province":"West-Vlaanderen",
    "wof:name":"Vrije Basisschool",
    "wof:placetype":"venue"
},
  "geometry": {"coordinates":[3.3129870892,50.8758049011],"type":"Point"}
}