{
  "type": "Feature",
  "properties": {
    "addr:full":"Ieperstraat 135 Heuvelland West-Vlaanderen 8953",
    "addr:housenumber":"135",
    "addr:postcode":"8953",
    "addr:street":"Ieperstraat",
    "iso:country":"BE",
    "sg:address":"Ieperstraat 135",
    "sg:city":"Heuvelland",
    "sg:orig_category":"RESTAURANTS: CAF\u00c9S",
    "sg:phone":"+32 57 44 72 36",
    "sg:postcode":"8953",
    "sg:province":"West-Vlaanderen",
    "wof:name":"Taverne Tramstatie",
    "wof:placetype":"venue"
},
  "geometry": {"coordinates":[2.8876919746,50.7825660706],"type":"Point"}
}