{
  "type": "Feature",
  "properties": {
    "addr:full":"Rue Albert 1er Liers Li\u00e8ge 4042",
    "addr:postcode":"4042",
    "addr:street":"Rue Albert 1Er Liers",
    "iso:country":"BE",
    "sg:address":"Rue Albert 1er",
    "sg:city":"Liers",
    "sg:orig_category":"Huisdieren and benodigdheden",
    "sg:phone":"+32 4 278 52 62",
    "sg:postcode":"4042",
    "sg:province":"Li\u00e8ge",
    "wof:name":"Seronvalle",
    "wof:placetype":"venue"
},
  "geometry": {"coordinates":[5.5688199997,50.6977272034],"type":"Point"}
}