{
  "type": "Feature",
  "properties": {
    "addr:full":"Frederik Lintsstraat 61 Leuven Vlaams-Brabant 3000",
    "addr:housenumber":"61",
    "addr:postcode":"3000",
    "addr:street":"Frederik Lintsstraat",
    "iso:country":"BE",
    "sg:address":"Frederik Lintsstraat 61",
    "sg:city":"Leuven",
    "sg:classifiers":[
        {
            "category":"Education",
            "subcategory":"School",
            "type":"Public Place"
        }
    ],
    "sg:phone":"+32 16 22 55 41",
    "sg:postcode":"3000",
    "sg:province":"Vlaams-Brabant",
    "sg:tags":[
        "-",
        "private"
    ],
    "wof:name":"Repetitiecentrum Massaer",
    "wof:placetype":"venue"
},
  "geometry": {"coordinates":[4.7064881325,50.872089386],"type":"Point"}
}