{
  "type": "Feature",
  "properties": {
    "addr:full":"Failon 49 Havelange Namur 5370",
    "addr:housenumber":"49",
    "addr:postcode":"5370",
    "addr:street":"Failon",
    "iso:country":"BE",
    "sg:address":"Failon 49",
    "sg:city":"Havelange",
    "sg:orig_category":"Installatie van houten of kunststof schrijnwerk",
    "sg:phone":"+32 83 63 33 34",
    "sg:postcode":"5370",
    "sg:province":"Namur",
    "wof:name":"Roland Meirlaen",
    "wof:placetype":"venue"
},
  "geometry": {"coordinates":[5.2412161827,50.387878418],"type":"Point"}
}