{
  "type": "Feature",
  "properties": {
    "iso:country":"BE",
    "sg:address":"Moershoofde 43",
    "sg:city":"Sint-laureins",
    "sg:orig_category":"G\u00e9om\u00e8tres",
    "sg:phone":"+32 9 379 98 09",
    "sg:postcode":"9980",
    "sg:province":"Oost-Vlaanderen",
    "wof:name":"Pierre Van Hyfte Erme",
    "wof:placetype":"venue"
},
  "geometry": {"coordinates":[3.513792038,51.2445983887],"type":"Point"}
}