{
  "type": "Feature",
  "properties": {
    "iso:country":"BE",
    "sg:address":"Processiestraat 10",
    "sg:city":"Hooglede",
    "sg:classifiers":[
        {
            "category":"Arena",
            "subcategory":"Sports Club",
            "type":"Entertainment"
        }
    ],
    "sg:phone":"+32 51 70 27 14",
    "sg:postcode":"8830",
    "sg:province":"West-Vlaanderen",
    "sg:tags":[
        "de"
    ],
    "wof:name":"Jenos Kwai Hooglede",
    "wof:placetype":"venue"
},
  "geometry": {"coordinates":[3.0413939953,50.9673309326],"type":"Point"}
}