{
  "type": "Feature",
  "properties": {
    "addr:full":"Hoogweg 78 Wervik West-Vlaanderen 8940",
    "addr:housenumber":"78",
    "addr:postcode":"8940",
    "addr:street":"Hoogweg",
    "iso:country":"BE",
    "sg:address":"Hoogweg 78",
    "sg:city":"Wervik",
    "sg:classifiers":[
        {
            "category":"Real Estate",
            "subcategory":"Developer",
            "type":"Services"
        }
    ],
    "sg:phone":"+32 56 22 77 25",
    "sg:postcode":"8940",
    "sg:province":"West-Vlaanderen",
    "sg:tags":[
        "project"
    ],
    "wof:name":"Bathos",
    "wof:placetype":"venue"
},
  "geometry": {"coordinates":[3.0828769207,50.7935752869],"type":"Point"}
}