{
  "type": "Feature",
  "properties": {
    "iso:country":"BE",
    "sg:address":"Van Luppenstraat 18",
    "sg:city":"Antwerpen",
    "sg:classifiers":[
        {
            "category":"Professional",
            "subcategory":"Computer Services",
            "type":"Services"
        }
    ],
    "sg:phone":"+32 3 281 19 48",
    "sg:postcode":"2018",
    "sg:province":"Antwerpen",
    "sg:tags":[
        "-",
        "processing",
        "data",
        "used"
    ],
    "wof:name":"Pro Used Computers Bvba",
    "wof:placetype":"venue"
},
  "geometry": {"coordinates":[4.4274392128,51.202671051],"type":"Point"}
}