{
  "type": "Feature",
  "properties": {
    "addr:full":"Fr. Verbeekstraat 102 Overijse Vlaams-Brabant 3090",
    "addr:housenumber":"102",
    "addr:postcode":"3090",
    "addr:street":"Fr. Verbeekstraat",
    "iso:country":"BE",
    "sg:address":"Fr. Verbeekstraat 102",
    "sg:city":"Overijse",
    "sg:classifiers":[
        {
            "category":"Professional",
            "subcategory":"Management & Consulting",
            "type":"Services"
        }
    ],
    "sg:phone":"+32 2 688 36 40",
    "sg:postcode":"3090",
    "sg:province":"Vlaams-Brabant",
    "sg:tags":[
        "consultant"
    ],
    "wof:name":"Bmc Bvba",
    "wof:placetype":"venue"
},
  "geometry": {"coordinates":[4.5141382217,50.7699890137],"type":"Point"}
}