{
  "type": "Feature",
  "properties": {
    "iso:country":"BE",
    "sg:address":"Frans Smeyersstraat 41",
    "sg:city":"Scherpenheuvel-zichem",
    "sg:orig_category":"Producteurs de fruits",
    "sg:phone":"+32 13 77 34 74",
    "sg:postcode":"3270",
    "sg:province":"Vlaams-Brabant",
    "wof:name":"Andre Weckx",
    "wof:placetype":"venue"
},
  "geometry": {"coordinates":[4.9848079681,50.970741272],"type":"Point"}
}