{
  "type": "Feature",
  "properties": {
    "iso:country":"BE",
    "sg:address":"Galgeveld 37",
    "sg:city":"Beernem",
    "sg:classifiers":[
        {
            "category":"Arena",
            "subcategory":"Sports Club",
            "type":"Entertainment"
        }
    ],
    "sg:phone":"+32 50 79 01 79",
    "sg:postcode":"8730",
    "sg:province":"West-Vlaanderen",
    "sg:tags":[
        "de"
    ],
    "wof:name":"Nu Of Nooit",
    "wof:placetype":"venue"
},
  "geometry": {"coordinates":[3.3641779423,51.1246109009],"type":"Point"}
}