{
  "type": "Feature",
  "properties": {
    "iso:country":"BE",
    "sg:address":"Axelwalle 12",
    "sg:city":"Oudenaarde",
    "sg:orig_category":"Eleveurs de bovins",
    "sg:phone":"+32 9 384 12 71",
    "sg:postcode":"9700",
    "sg:province":"Oost-Vlaanderen",
    "wof:name":"Lieven De Ruyck",
    "wof:placetype":"venue"
},
  "geometry": {"coordinates":[3.6313719749,50.8950576782],"type":"Point"}
}