{
  "type": "Feature",
  "properties": {
    "iso:country":"BE",
    "sg:address":"De Zwaantjes 23",
    "sg:city":"Malle",
    "sg:orig_category":"Experts-comptables. Comptables",
    "sg:phone":"+32 3 311 76 25",
    "sg:postcode":"2390",
    "sg:province":"Antwerpen",
    "wof:name":"Luc Daems",
    "wof:placetype":"venue"
},
  "geometry": {"coordinates":[4.738656044,51.3052062988],"type":"Point"}
}