{
  "type": "Feature",
  "properties": {
    "iso:country":"BE",
    "sg:address":"Koning Albertlaan 31",
    "sg:city":"Sint-agatha-berchem/berchem-sainte-agathe",
    "sg:orig_category":"Herstelling aan huis van huishoudartikelen Herstellingswinkels voor diverse persoonlijke and huishou",
    "sg:phone":"+32 2 465 51 71",
    "sg:postcode":"1082",
    "sg:province":"Bruxelles-Capitale",
    "wof:name":"Verschelde & Zonen",
    "wof:placetype":"venue"
},
  "geometry": {"coordinates":[4.2949390411,50.8648033142],"type":"Point"}
}