{
  "type": "Feature",
  "properties": {
    "iso:country":"BE",
    "sg:address":"Turnhoutsebaan 112",
    "sg:city":"Malle",
    "sg:orig_category":"Transports routiers de marchandises",
    "sg:phone":"+32 3 311 63 39",
    "sg:postcode":"2390",
    "sg:province":"Antwerpen",
    "wof:name":"Fa. Vermeiren & Zoon",
    "wof:placetype":"venue"
},
  "geometry": {"coordinates":[4.7458062172,51.30128479],"type":"Point"}
}