{
  "type": "Feature",
  "properties": {
    "addr:full":"Aartrijkestraat 87 Torhout West-Vlaanderen 8820",
    "addr:housenumber":"87",
    "addr:postcode":"8820",
    "addr:street":"Aartrijkestraat",
    "iso:country":"BE",
    "sg:address":"Aartrijkestraat 87",
    "sg:city":"Torhout",
    "sg:orig_category":"Boekhouders",
    "sg:phone":"+32 50 22 10 58",
    "sg:postcode":"8820",
    "sg:province":"West-Vlaanderen",
    "wof:name":"Jan Schuyesmans",
    "wof:placetype":"venue"
},
  "geometry": {"coordinates":[3.0990839005,51.0746917725],"type":"Point"}
}