{
  "type": "Feature",
  "properties": {
    "addr:full":"Rue Des Bonniers 4 Courcelles (trazegnies) Hainaut 6183",
    "addr:housenumber":"4",
    "addr:postcode":"6183",
    "addr:street":"Rue Des Bonniers",
    "iso:country":"BE",
    "sg:address":"Rue Des Bonniers 4",
    "sg:city":"Courcelles (trazegnies)",
    "sg:classifiers":[
        {
            "category":"Professional",
            "subcategory":"Computer Services",
            "type":"Services"
        }
    ],
    "sg:phone":"+32 71 45 71 78",
    "sg:postcode":"6183",
    "sg:province":"Hainaut",
    "sg:tags":[
        "network"
    ],
    "wof:name":"Net & Sys",
    "wof:placetype":"venue"
},
  "geometry": {"coordinates":[4.3369760513,50.4674911499],"type":"Point"}
}