{
  "type": "Feature",
  "properties": {
    "addr:full":"Rue De La Croix De Fer 70 Brussel/bruxelles Bruxelles-Capitale 1000",
    "addr:housenumber":"70",
    "addr:postcode":"1000",
    "addr:street":"Rue De La Croix De Fer;/",
    "iso:country":"BE",
    "sg:address":"Rue De La Croix De Fer 70",
    "sg:city":"Brussel/bruxelles",
    "sg:classifiers":[
        {
            "category":"Restaurant",
            "type":"Food & Drink"
        }
    ],
    "sg:phone":"+32 2 223 09 33",
    "sg:postcode":"1000",
    "sg:province":"Bruxelles-Capitale",
    "wof:name":"Le Bambou Vert",
    "wof:placetype":"venue"
},
  "geometry": {"coordinates":[4.3663191795,50.8485298157],"type":"Point"}
}