{
  "type": "Feature",
  "properties": {
    "iso:country":"BE",
    "sg:address":"Chemin Pic L'esquinterie 17",
    "sg:city":"Ath",
    "sg:orig_category":"Fotografen and fotostudio's",
    "sg:phone":"+32 68 55 30 81",
    "sg:postcode":"7822",
    "sg:province":"Hainaut",
    "wof:name":"Patrick Remy",
    "wof:placetype":"venue"
},
  "geometry": {"coordinates":[3.8480899334,50.6549186707],"type":"Point"}
}