{
  "type": "Feature",
  "properties": {
    "addr:full":"Route De Wallonie 4b Mons (ghlin) Hainaut 7011",
    "addr:housenumber":"4b",
    "addr:postcode":"7011",
    "addr:street":"Route De Wallonie",
    "iso:country":"BE",
    "sg:address":"Route De Wallonie 4b",
    "sg:city":"Mons (ghlin)",
    "sg:classifiers":[
        {
            "category":"Building & Trades",
            "subcategory":"Cleaning & Sanitation",
            "type":"Services"
        }
    ],
    "sg:phone":"+32 65 35 62 10",
    "sg:postcode":"7011",
    "sg:province":"Hainaut",
    "sg:tags":[
        "asbestos",
        "removal"
    ],
    "wof:name":"S.b.m.i. Sa",
    "wof:placetype":"venue"
},
  "geometry": {"coordinates":[3.8731050491,50.477394104],"type":"Point"}
}