{
  "type": "Feature",
  "properties": {
    "iso:country":"BE",
    "sg:address":"Rue Des Pr\u00c9s 4",
    "sg:city":"Marche-en-famenne",
    "sg:orig_category":"Kapsalons",
    "sg:phone":"+32 84 31 17 02",
    "sg:postcode":"6900",
    "sg:province":"Luxembourg",
    "wof:name":"Danielle Tordeur",
    "wof:placetype":"venue"
},
  "geometry": {"coordinates":[5.3151159286,50.2025947571],"type":"Point"}
}