{
  "type": "Feature",
  "properties": {
    "iso:country":"BE",
    "sg:address":"Sint-pietersplein 15",
    "sg:city":"Ukkel/uccle",
    "sg:orig_category":"Decoratieve kunst and kunstbenodigdheden Foto-uitrusting Telecommunicatieapparaten",
    "sg:phone":"+32 2 343 26 34",
    "sg:postcode":"1180",
    "sg:province":"Bruxelles-Capitale",
    "wof:name":"Espace Photo",
    "wof:placetype":"venue"
},
  "geometry": {"coordinates":[4.34025383,50.8032608032],"type":"Point"}
}