{
  "type": "Feature",
  "properties": {
    "addr:full":"Witte Burg 53 Koksijde (oostduinkerke) West-Vlaanderen 8670",
    "addr:housenumber":"53",
    "addr:postcode":"8670",
    "addr:street":"Witte Burg",
    "iso:country":"BE",
    "sg:address":"Witte Burg 53",
    "sg:city":"Koksijde (oostduinkerke)",
    "sg:classifiers":[
        {
            "category":"Banks & Credit Unions",
            "subcategory":"Investment Brokerage",
            "type":"Services"
        }
    ],
    "sg:phone":"+32 58 51 77 69",
    "sg:postcode":"8670",
    "sg:province":"West-Vlaanderen",
    "wof:name":"Beleggingsgroep",
    "wof:placetype":"venue"
},
  "geometry": {"coordinates":[2.6755900383,51.1218299866],"type":"Point"}
}