{
  "type": "Feature",
  "properties": {
    "addr:full":"Voort 47 Hoogstraten Antwerpen 2328",
    "addr:housenumber":"47",
    "addr:postcode":"2328",
    "addr:street":"Voort",
    "iso:country":"BE",
    "sg:address":"Voort 47",
    "sg:city":"Hoogstraten",
    "sg:orig_category":"Eleveurs d'\u00e9quid\u00e9s",
    "sg:phone":"+32 3 315 44 06",
    "sg:postcode":"2328",
    "sg:province":"Antwerpen",
    "wof:name":"Ipenrooy",
    "wof:placetype":"venue"
},
  "geometry": {"coordinates":[4.7940797806,51.4644012451],"type":"Point"}
}