{
  "type": "Feature",
  "properties": {
    "addr:full":"Rue De La Cordialit\u00e9 23 Bruxelles (anderlecht) Bruxelles-Capitale 1070",
    "addr:housenumber":"23",
    "addr:postcode":"1070",
    "addr:street":"Rue De La Cordialite\u0301",
    "iso:country":"BE",
    "sg:address":"Rue De La Cordialit\u00e9 23",
    "sg:city":"Bruxelles (anderlecht)",
    "sg:classifiers":[
        {
            "category":"Health Services",
            "subcategory":"Doctor",
            "type":"Services"
        }
    ],
    "sg:phone":"+32 2 411 01 73",
    "sg:postcode":"1070",
    "sg:province":"Bruxelles-Capitale",
    "sg:tags":[
        "medicinephysicians",
        "surgeon"
    ],
    "wof:name":"Dupont Alain",
    "wof:placetype":"venue"
},
  "geometry": {"coordinates":[4.3102869987,50.8483009338],"type":"Point"}
}