{
  "type": "Feature",
  "properties": {
    "addr:full":"Rue Des Comtes De Salm 27 Vielsalm Luxembourg 6690",
    "addr:housenumber":"27",
    "addr:postcode":"6690",
    "addr:street":"Rue Des Comtes De Salm",
    "iso:country":"BE",
    "sg:address":"Rue Des Comtes De Salm 27",
    "sg:city":"Vielsalm",
    "sg:orig_category":"R\u00e9parations d'appareils \u00e9lectrom\u00e9nagers. Electrom\u00e9nager, t\u00e9l\u00e9visions and radios",
    "sg:phone":"+32 80 21 64 65",
    "sg:postcode":"6690",
    "sg:province":"Luxembourg",
    "wof:name":"Syndicat D'initiative",
    "wof:placetype":"venue"
},
  "geometry": {"coordinates":[5.8893389702,50.2683677673],"type":"Point"}
}