{
  "type": "Feature",
  "properties": {
    "addr:full":"362 Gentsesteenweg 9420 Erpe-mere 362",
    "addr:housenumber":"362;9420;362",
    "addr:street":"Gentsesteenweg;Erpe-Mere",
    "iso:country":"BE",
    "sg:address":"362",
    "sg:city":"Gentsesteenweg 9420 Erpe-mere",
    "sg:classifiers":[
        {
            "category":"Shopping",
            "subcategory":"Clothing, Apparel, & Fashions",
            "type":"Retail Goods"
        }
    ],
    "sg:phone":"+32 53 80 28 35",
    "sg:postcode":"362",
    "sg:tags":[
        "textile",
        "clothing",
        "clothes"
    ],
    "wof:name":"Lietex Nv",
    "wof:placetype":"venue"
},
  "geometry": {"coordinates":[3.9416899681,50.949131012],"type":"Point"}
}