{
  "type": "Feature",
  "properties": {
    "addr:full":"Serskampsteenweg 286 Wetteren Oost-Vlaanderen 9230",
    "addr:housenumber":"286",
    "addr:postcode":"9230",
    "addr:street":"Serskampsteenweg",
    "iso:country":"BE",
    "sg:address":"Serskampsteenweg 286",
    "sg:city":"Wetteren",
    "sg:orig_category":"Boomkwekerijen Groenten and fruit Gh",
    "sg:phone":"+32 9 369 19 46",
    "sg:postcode":"9230",
    "sg:province":"Oost-Vlaanderen",
    "wof:name":"Calle Plant",
    "wof:placetype":"venue"
},
  "geometry": {"coordinates":[3.9093699455,50.9974327087],"type":"Point"}
}