{
  "type": "Feature",
  "properties": {
    "addr:full":"32 Rittwegerlaan Machelen Vlaams-Brabant 1830",
    "addr:housenumber":"32",
    "addr:postcode":"1830",
    "addr:street":"Rittwegerlaan",
    "iso:country":"BE",
    "sg:address":"32 Rittwegerlaan",
    "sg:city":"Machelen",
    "sg:classifiers":[
        {
            "category":"Transit Center",
            "subcategory":"Freight",
            "type":"Transportation"
        }
    ],
    "sg:phone":"+32 2 255 95 00",
    "sg:postcode":"1830",
    "sg:province":"Vlaams-Brabant",
    "sg:tags":[
        "metallurgy",
        "pipe",
        "metalworking",
        "sheet"
    ],
    "wof:name":"Disteel Sa",
    "wof:placetype":"venue"
},
  "geometry": {"coordinates":[4.4221410751,50.9094848633],"type":"Point"}
}