{
  "type": "Feature",
  "properties": {
    "addr:full":"Klapdorp 90 Antwerpen Antwerpen 2000",
    "addr:housenumber":"90",
    "addr:postcode":"2000",
    "addr:street":"Klapdorp",
    "iso:country":"BE",
    "sg:address":"Klapdorp 90",
    "sg:city":"Antwerpen",
    "sg:classifiers":[
        {
            "category":"Food & Beverages",
            "subcategory":"Fruits & Vegetables",
            "type":"Retail Goods"
        }
    ],
    "sg:phone":"+32 3 231 02 68",
    "sg:postcode":"2000",
    "sg:province":"Antwerpen",
    "sg:tags":[
        "-",
        "shirt"
    ],
    "wof:name":"Letty",
    "wof:placetype":"venue"
},
  "geometry": {"coordinates":[4.4070210457,51.224899292],"type":"Point"}
}