{
  "type": "Feature",
  "properties": {
    "addr:full":"Drie Eikenstraat 106 Edegem Antwerpen 2650",
    "addr:housenumber":"106",
    "addr:postcode":"2650",
    "addr:street":"Drie Eikenstraat",
    "iso:country":"BE",
    "sg:address":"Drie Eikenstraat 106",
    "sg:city":"Edegem",
    "sg:classifiers":[
        {
            "category":"Professional",
            "subcategory":"Management & Consulting",
            "type":"Services"
        }
    ],
    "sg:phone":"+32 3 458 30 82",
    "sg:postcode":"2650",
    "sg:province":"Antwerpen",
    "sg:tags":[
        "consultant"
    ],
    "wof:name":"Avesco",
    "wof:placetype":"venue"
},
  "geometry": {"coordinates":[4.438231945,51.1558685303],"type":"Point"}
}