{
  "type": "Feature",
  "properties": {
    "iso:country":"BE",
    "sg:address":"Elsleukenstraat 19bb",
    "sg:city":"Aarschot",
    "sg:orig_category":"Plomberie, chauffage and installations sanitaires",
    "sg:phone":"+32 16 56 39 51",
    "sg:postcode":"3201",
    "sg:province":"Vlaams-Brabant",
    "wof:name":"Victor Baus",
    "wof:placetype":"venue"
},
  "geometry": {"coordinates":[4.9041361809,51.0181732178],"type":"Point"}
}