{
  "type": "Feature",
  "properties": {
    "iso:country":"BE",
    "sg:address":"Rue Neuve 111",
    "sg:city":"Brussel/bruxelles",
    "sg:orig_category":"Geschenken and souvenirs Herstelling horloges and juwelen Juwelen and edelstenen Fab Juwelen and hor",
    "sg:phone":"+32 2 219 92 87",
    "sg:postcode":"1000",
    "sg:province":"Bruxelles-Capitale",
    "wof:name":"Venizi",
    "wof:placetype":"venue"
},
  "geometry": {"coordinates":[4.3571557999,50.8536758423],"type":"Point"}
}