{
  "type": "Feature",
  "properties": {
    "addr:full":"Handelstraat 2 Veurne West-Vlaanderen 8630",
    "addr:housenumber":"2",
    "addr:postcode":"8630",
    "addr:street":"Handelstraat",
    "iso:country":"BE",
    "sg:address":"Handelstraat 2",
    "sg:city":"Veurne",
    "sg:classifiers":[
        {
            "category":"Shopping",
            "type":"Retail Goods"
        }
    ],
    "sg:phone":"+32 58 31 59 59",
    "sg:postcode":"8630",
    "sg:province":"West-Vlaanderen",
    "sg:tags":[
        "metallurgy",
        "finished",
        "-",
        "metalworking",
        "metallic"
    ],
    "wof:name":"Noordermetaal Nv",
    "wof:placetype":"venue"
},
  "geometry": {"coordinates":[2.6852200031,51.0669136047],"type":"Point"}
}