{
  "type": "Feature",
  "properties": {
    "addr:full":"Raverschootstraat 293 Eeklo Oost-Vlaanderen 9900",
    "addr:housenumber":"293",
    "addr:postcode":"9900",
    "addr:street":"Raverschootstraat",
    "iso:country":"BE",
    "sg:address":"Raverschootstraat 293",
    "sg:city":"Eeklo",
    "sg:classifiers":[
        {
            "category":"Professional",
            "subcategory":"Computer Services",
            "type":"Services"
        }
    ],
    "sg:phone":"+32 9 377 14 01",
    "sg:postcode":"9900",
    "sg:province":"Oost-Vlaanderen",
    "sg:tags":[
        "-",
        "processing",
        "data"
    ],
    "wof:name":"Boca Nv",
    "wof:placetype":"venue"
},
  "geometry": {"coordinates":[3.5356960297,51.1883354187],"type":"Point"}
}