{
  "type": "Feature",
  "properties": {
    "addr:full":"Oudebaan 420 Leuven Vlaams-Brabant 3000",
    "addr:housenumber":"420",
    "addr:postcode":"3000",
    "addr:street":"Oudebaan",
    "iso:country":"BE",
    "sg:address":"Oudebaan 420",
    "sg:city":"Leuven",
    "sg:classifiers":[
        {
            "category":"Building & Trades",
            "subcategory":"Construction",
            "type":"Services"
        }
    ],
    "sg:phone":"+32 16 26 18 18",
    "sg:postcode":"3000",
    "sg:province":"Vlaams-Brabant",
    "sg:tags":[
        "installation",
        "-",
        "central",
        "heating"
    ],
    "wof:name":"Janssens E",
    "wof:placetype":"venue"
},
  "geometry": {"coordinates":[4.7317700386,50.8672714233],"type":"Point"}
}