{
  "type": "Feature",
  "properties": {
    "addr:full":"Bonzellaan 14 De Panne West-Vlaanderen 8660",
    "addr:housenumber":"14",
    "addr:postcode":"8660",
    "addr:street":"Bonzellaan",
    "iso:country":"BE",
    "sg:address":"Bonzellaan 14",
    "sg:city":"De Panne",
    "sg:orig_category":"Postkantoren Verzekeringsmakelaars and experts",
    "sg:phone":"+32 58 41 18 89",
    "sg:postcode":"8660",
    "sg:province":"West-Vlaanderen",
    "wof:name":"De Post",
    "wof:placetype":"venue"
},
  "geometry": {"coordinates":[2.5903480053,51.1020469666],"type":"Point"}
}