{
  "type": "Feature",
  "properties": {
    "addr:full":"Dendermondesteenweg 459 Destelbergen Oost-Vlaanderen 9070",
    "addr:housenumber":"459",
    "addr:postcode":"9070",
    "addr:street":"Dendermondesteenweg",
    "iso:country":"BE",
    "sg:address":"Dendermondesteenweg 459",
    "sg:city":"Destelbergen",
    "sg:orig_category":"Boekhandels Krantenwinkels Rookartikelen",
    "sg:phone":"+32 9 228 88 33",
    "sg:postcode":"9070",
    "sg:province":"Oost-Vlaanderen",
    "wof:name":"De Winkel",
    "wof:placetype":"venue"
},
  "geometry": {"coordinates":[3.7976140976,51.0561218262],"type":"Point"}
}