{
  "type": "Feature",
  "properties": {
    "iso:country":"BE",
    "sg:address":"Rue Fran\u00c7ois Vandamme 39",
    "sg:city":"Ham-sur-heure-nalinnes",
    "sg:classifiers":[
        {
            "category":"Arena",
            "subcategory":"Sports Club",
            "type":"Entertainment"
        }
    ],
    "sg:phone":"+32 71 21 78 18",
    "sg:postcode":"6120",
    "sg:province":"Hainaut",
    "sg:tags":[
        "terrain",
        "hors",
        "de",
        "installation",
        "sportifs"
    ],
    "wof:name":"Jeun. Sport. Jamioulx",
    "wof:placetype":"venue"
},
  "geometry": {"coordinates":[4.4167909622,50.35389328],"type":"Point"}
}