{
  "type": "Feature",
  "properties": {
    "iso:country":"BE",
    "sg:address":"Leopoldstraat 4",
    "sg:city":"Duffel",
    "sg:classifiers":[
        {
            "category":"Shopping",
            "subcategory":"Clothing, Apparel, & Fashions",
            "type":"Retail Goods"
        }
    ],
    "sg:phone":"+32 15 31 00 69",
    "sg:postcode":"2570",
    "sg:province":"Antwerpen",
    "sg:tags":[
        "underwear",
        "lingerie",
        "-"
    ],
    "wof:name":"Nefertite",
    "wof:placetype":"venue"
},
  "geometry": {"coordinates":[4.5017089844,51.095375061],"type":"Point"}
}