{
  "type": "Feature",
  "properties": {
    "addr:full":"Blauwhuisstraat 7 Izegem West-Vlaanderen 8870",
    "addr:housenumber":"7",
    "addr:postcode":"8870",
    "addr:street":"Blauwhuisstraat",
    "iso:country":"BE",
    "sg:address":"Blauwhuisstraat 7",
    "sg:city":"Izegem",
    "sg:orig_category":"Fleurs and plantes",
    "sg:phone":"+32 51 30 18 09",
    "sg:postcode":"8870",
    "sg:province":"West-Vlaanderen",
    "wof:name":"Rita Vandenberghe",
    "wof:placetype":"venue"
},
  "geometry": {"coordinates":[3.2244689465,50.9152297974],"type":"Point"}
}