{
  "type": "Feature",
  "properties": {
    "iso:country":"BE",
    "sg:address":"R Ulens 49",
    "sg:city":"Bruxelles",
    "sg:classifiers":[
        {
            "category":"Professional",
            "subcategory":"Engineering",
            "type":"Services"
        }
    ],
    "sg:phone":"+32 80 57 03 67",
    "sg:postcode":"1080",
    "sg:province":"Bruxelles-Capitale",
    "sg:tags":[
        "machine",
        "-",
        "mechanical"
    ],
    "wof:name":"Hugo Karl Ag",
    "wof:placetype":"venue"
},
  "geometry": {"coordinates":[6.0709547997,50.3497962952],"type":"Point"}
}