{
  "type": "Feature",
  "properties": {
    "addr:full":"Gasthuisbosdreef 18 Tongeren Limburg 3700",
    "addr:housenumber":"18",
    "addr:postcode":"3700",
    "addr:street":"Gasthuisbosdreef",
    "iso:country":"BE",
    "sg:address":"Gasthuisbosdreef 18",
    "sg:city":"Tongeren",
    "sg:classifiers":[
        {
            "category":"Retail",
            "subcategory":"Animal Services",
            "type":"Services"
        }
    ],
    "sg:phone":"+32 12 26 37 97",
    "sg:postcode":"3700",
    "sg:province":"Limburg",
    "sg:tags":[
        "grooming",
        "-",
        "dog"
    ],
    "wof:name":"Jolli",
    "wof:placetype":"venue"
},
  "geometry": {"coordinates":[5.4527668953,50.7920417786],"type":"Point"}
}