{
  "type": "Feature",
  "properties": {
    "addr:full":"Britse Lei 1c Antwerpen Antwerpen 2000",
    "addr:housenumber":"1c",
    "addr:postcode":"2000",
    "addr:street":"Lei",
    "iso:country":"BE",
    "sg:address":"Britse Lei 1c",
    "sg:city":"Antwerpen",
    "sg:classifiers":[
        {
            "category":"Personal",
            "subcategory":"Beauty Salon",
            "type":"Services"
        }
    ],
    "sg:phone":"+32 3 238 08 23",
    "sg:postcode":"2000",
    "sg:province":"Antwerpen",
    "sg:tags":[
        "child",
        "-",
        "hairdressing"
    ],
    "wof:name":"Albert",
    "wof:placetype":"venue"
},
  "geometry": {"coordinates":[4.407761097,51.2107810974],"type":"Point"}
}