{
  "type": "Feature",
  "properties": {
    "addr:full":"Avenue Eug\u00e8ne Mascaux 107 Charleroi (marcinelle) Hainaut 6001",
    "addr:housenumber":"107",
    "addr:postcode":"6001",
    "addr:street":"Avenue Euge\u0300Ne Mascaux",
    "iso:country":"BE",
    "sg:address":"Avenue Eug\u00e8ne Mascaux 107",
    "sg:city":"Charleroi (marcinelle)",
    "sg:classifiers":[
        {
            "category":"Shopping",
            "subcategory":"Clothing, Apparel, & Fashions",
            "type":"Retail Goods"
        }
    ],
    "sg:phone":"+32 71 36 07 66",
    "sg:postcode":"6001",
    "sg:province":"Hainaut",
    "sg:tags":[
        "boutique"
    ],
    "wof:name":"Anne Couture",
    "wof:placetype":"venue"
},
  "geometry": {"coordinates":[4.4449629784,50.3973579407],"type":"Point"}
}