{
  "type": "Feature",
  "properties": {
    "addr:full":"Kortrijkseweg 367a Waregem (beveren-leie) West-Vlaanderen 8791",
    "addr:housenumber":"367a",
    "addr:postcode":"8791",
    "iso:country":"BE",
    "sg:address":"Kortrijkseweg 367a",
    "sg:city":"Waregem (beveren-leie)",
    "sg:classifiers":[
        {
            "category":"Food & Beverages",
            "subcategory":"Groceries & Convenience Stores",
            "type":"Retail Goods"
        }
    ],
    "sg:phone":"+32 56 70 63 92",
    "sg:postcode":"8791",
    "sg:province":"West-Vlaanderen",
    "sg:tags":[
        "grocer"
    ],
    "wof:name":"Figaro",
    "wof:placetype":"venue"
},
  "geometry": {"coordinates":[3.3570189476,50.8790512085],"type":"Point"}
}