{
  "type": "Feature",
  "properties": {
    "addr:full":"R.emmanuel Van Driessche 23 Elsene/ixelles Bruxelles-Capitale 1050",
    "addr:housenumber":"23",
    "addr:postcode":"1050",
    "addr:street":"Van Driessche",
    "iso:country":"BE",
    "sg:address":"R.emmanuel Van Driessche 23",
    "sg:city":"Elsene/ixelles",
    "sg:orig_category":"Salles de spectacles",
    "sg:phone":"+32 2 343 38 69",
    "sg:postcode":"1050",
    "sg:province":"Bruxelles-Capitale",
    "wof:name":"E.t.c.",
    "wof:placetype":"venue"
},
  "geometry": {"coordinates":[4.3550481796,50.8196601868],"type":"Point"}
}