{
  "type": "Feature",
  "properties": {
    "addr:full":"Rue Des Trieux 24 Binche Hainaut 7134",
    "addr:housenumber":"24",
    "addr:postcode":"7134",
    "addr:street":"Rue Des Trieux",
    "iso:country":"BE",
    "sg:address":"Rue Des Trieux 24",
    "sg:city":"Binche",
    "sg:orig_category":"Plomberie, chauffage and installations sanitaires",
    "sg:phone":"+32 64 36 86 77",
    "sg:postcode":"7134",
    "sg:province":"Hainaut",
    "wof:name":"Philippe Leroy",
    "wof:placetype":"venue"
},
  "geometry": {"coordinates":[4.2267398834,50.4200553894],"type":"Point"}
}