{
  "type": "Feature",
  "properties": {
    "addr:full":"Pereboomhof 6 Wevelgem (gullegem) West-Vlaanderen 8560",
    "addr:housenumber":"6",
    "addr:postcode":"8560",
    "addr:street":"Pereboomhof",
    "iso:country":"BE",
    "sg:address":"Pereboomhof 6",
    "sg:city":"Wevelgem (gullegem)",
    "sg:classifiers":[
        {
            "category":"Personal",
            "subcategory":"Nail Salon",
            "type":"Services"
        }
    ],
    "sg:phone":"+32 56 37 25 80",
    "sg:postcode":"8560",
    "sg:province":"West-Vlaanderen",
    "sg:tags":[
        "pedicure"
    ],
    "wof:name":"De Nolf V",
    "wof:placetype":"venue"
},
  "geometry": {"coordinates":[3.2046809196,50.8322372437],"type":"Point"}
}