{
  "type": "Feature",
  "properties": {
    "iso:country":"BE",
    "sg:address":"Avenue Du Globe 57",
    "sg:city":"Bruxelles (forest)",
    "sg:classifiers":[
        {
            "category":"Transit Center",
            "subcategory":"Freight",
            "type":"Transportation"
        }
    ],
    "sg:phone":"+32 2 345 35 62",
    "sg:postcode":"1190",
    "sg:province":"Bruxelles-Capitale",
    "sg:tags":[
        "import",
        "export",
        "-"
    ],
    "wof:name":"Gesaco",
    "wof:placetype":"venue"
},
  "geometry": {"coordinates":[4.3260822296,50.8073272705],"type":"Point"}
}