{
  "type": "Feature",
  "properties": {
    "addr:full":"Markt 3 Bree Limburg 3960",
    "addr:housenumber":"3",
    "addr:postcode":"3960",
    "addr:street":"Markt",
    "iso:country":"BE",
    "sg:address":"Markt 3",
    "sg:city":"Bree",
    "sg:orig_category":"Babyspullen",
    "sg:phone":"+32 89 48 12 87",
    "sg:postcode":"3960",
    "sg:province":"Limburg",
    "wof:name":"Huis Ojensien",
    "wof:placetype":"venue"
},
  "geometry": {"coordinates":[5.5972099304,51.14087677],"type":"Point"}
}