{
  "type": "Feature",
  "properties": {
    "iso:country":"BE",
    "sg:address":"Beveldorp 96ba",
    "sg:city":"Nijlen",
    "sg:classifiers":[
        {
            "category":"Food & Beverages",
            "subcategory":"Fruits & Vegetables",
            "type":"Retail Goods"
        }
    ],
    "sg:phone":"+32 3 411 23 61",
    "sg:postcode":"2560",
    "sg:province":"Antwerpen",
    "sg:tags":[
        "l\u00e9gumes"
    ],
    "wof:name":"Het Tuintje",
    "wof:placetype":"venue"
},
  "geometry": {"coordinates":[4.6823067665,51.1368408203],"type":"Point"}
}