{
  "type": "Feature",
  "properties": {
    "addr:full":"Groenstraat 54a Hoeselt Limburg 3730",
    "addr:housenumber":"54a",
    "addr:postcode":"3730",
    "addr:street":"Groenstraat",
    "iso:country":"BE",
    "sg:address":"Groenstraat 54a",
    "sg:city":"Hoeselt",
    "sg:orig_category":"Non-Classified Establishments",
    "sg:phone":"+32 89 50 30 99",
    "sg:postcode":"3730",
    "sg:province":"Limburg",
    "wof:name":"Quality Heating",
    "wof:placetype":"venue"
},
  "geometry": {"coordinates":[5.4790878296,50.8645935059],"type":"Point"}
}