{
  "type": "Feature",
  "properties": {
    "addr:full":"Lispersteenweg 153 Lier Antwerpen 2500",
    "addr:housenumber":"153",
    "addr:postcode":"2500",
    "addr:street":"Lispersteenweg",
    "iso:country":"BE",
    "sg:address":"Lispersteenweg 153",
    "sg:city":"Lier",
    "sg:classifiers":[
        {
            "category":"Cafe",
            "type":"Food & Drink"
        }
    ],
    "sg:phone":"+32 3 489 34 65",
    "sg:postcode":"2500",
    "sg:province":"Antwerpen",
    "sg:tags":[
        "caf\u00e9s"
    ],
    "wof:name":"Rudolf Verbueken",
    "wof:placetype":"venue"
},
  "geometry": {"coordinates":[4.5745530128,51.1416397095],"type":"Point"}
}