{
  "type": "Feature",
  "properties": {
    "addr:full":"Duinenstraat 147 Oostende West-Vlaanderen 8400",
    "addr:housenumber":"147",
    "addr:postcode":"8400",
    "addr:street":"Duinenstraat",
    "iso:country":"BE",
    "sg:address":"Duinenstraat 147",
    "sg:city":"Oostende",
    "sg:orig_category":"Restaurants Ruimtes voor conferenties, recepties and feesten",
    "sg:phone":"+32 59 30 62 44",
    "sg:postcode":"8400",
    "sg:province":"West-Vlaanderen",
    "wof:name":"Walrave",
    "wof:placetype":"venue"
},
  "geometry": {"coordinates":[2.8485069275,51.2012825012],"type":"Point"}
}