{
  "type": "Feature",
  "properties": {
    "addr:full":"Landbouwstraat 9 Mechelen Antwerpen 2800",
    "addr:housenumber":"9",
    "addr:postcode":"2800",
    "addr:street":"Landbouwstraat",
    "iso:country":"BE",
    "sg:address":"Landbouwstraat 9",
    "sg:city":"Mechelen",
    "sg:classifiers":[
        {
            "category":"Social Services",
            "subcategory":"Job Training",
            "type":"Services"
        }
    ],
    "sg:phone":"+32 15 43 36 69",
    "sg:postcode":"2800",
    "sg:province":"Antwerpen",
    "sg:tags":[
        "interpreter"
    ],
    "wof:name":"B En D",
    "wof:placetype":"venue"
},
  "geometry": {"coordinates":[4.465157032,51.0222053528],"type":"Point"}
}