{
  "type": "Feature",
  "properties": {
    "iso:country":"BE",
    "sg:address":"Dendermondsestw 455",
    "sg:city":"Gent",
    "sg:orig_category":"Kapsalons",
    "sg:phone":"+32 9 228 36 88",
    "sg:postcode":"9040",
    "sg:province":"Oost-Vlaanderen",
    "wof:name":"New Kreatief",
    "wof:placetype":"venue"
},
  "geometry": {"coordinates":[3.7548890114,51.0520935059],"type":"Point"}
}