{
  "type": "Feature",
  "properties": {
    "addr:full":"Derbystraat 365 Gent (sint-denijs-westrem - Afsnee) Oost-Vlaanderen 9051",
    "addr:housenumber":"365",
    "addr:postcode":"9051",
    "addr:street":"Derbystraat;Oost-Vlaanderen",
    "iso:country":"BE",
    "sg:address":"Derbystraat 365",
    "sg:city":"Gent (sint-denijs-westrem - Afsnee)",
    "sg:classifiers":[
        {
            "category":"Banks & Credit Unions",
            "subcategory":"Investment Brokerage",
            "type":"Services"
        }
    ],
    "sg:phone":"+32 9 245 48 31",
    "sg:postcode":"9051",
    "sg:province":"Oost-Vlaanderen",
    "sg:tags":[
        "printing",
        "-"
    ],
    "wof:name":"Ycomm Europe",
    "wof:placetype":"venue"
},
  "geometry": {"coordinates":[3.6965939999,51.023475647],"type":"Point"}
}