{
  "type": "Feature",
  "properties": {
    "iso:country":"BE",
    "sg:address":"Grand'rue 53",
    "sg:city":"Walcourt",
    "sg:orig_category":"Slagers",
    "sg:phone":"+32 71 21 46 28",
    "sg:postcode":"5651",
    "sg:province":"Namur",
    "wof:name":"Maurice Pirmez",
    "wof:placetype":"venue"
},
  "geometry": {"coordinates":[4.4332799911,50.2857818604],"type":"Point"}
}