{
  "type": "Feature",
  "properties": {
    "iso:country":"BE",
    "sg:address":"Moerestraat 30",
    "sg:city":"Diksmuide",
    "sg:orig_category":"Pluimveekwekers",
    "sg:phone":"+32 51 50 11 37",
    "sg:postcode":"8600",
    "sg:province":"West-Vlaanderen",
    "wof:name":"Pol Steen",
    "wof:placetype":"venue"
},
  "geometry": {"coordinates":[2.9020400047,51.0896148682],"type":"Point"}
}