{
  "type": "Feature",
  "properties": {
    "addr:full":"Rue Renory 20 Liege Li\u00e8ge 4020",
    "addr:housenumber":"20",
    "addr:postcode":"4020",
    "addr:street":"Rue Renory",
    "iso:country":"BE",
    "sg:address":"Rue Renory 20",
    "sg:city":"Liege",
    "sg:orig_category":"Sportclubs",
    "sg:phone":"+32 4 343 42 69",
    "sg:postcode":"4020",
    "sg:province":"Li\u00e8ge",
    "wof:name":"R.c.a.e Plonge",
    "wof:placetype":"venue"
},
  "geometry": {"coordinates":[5.5796051025,50.6146354675],"type":"Point"}
}