{
  "type": "Feature",
  "properties": {
    "iso:country":"BE",
    "sg:address":"7750",
    "sg:city":"Mont-de-l'enclus",
    "sg:orig_category":"Pharmaciens",
    "sg:phone":"+32 900 10 500",
    "sg:postcode":"7750",
    "sg:province":"Hainaut",
    "wof:name":"Pharmacies De Garde",
    "wof:placetype":"venue"
},
  "geometry": {"coordinates":[2.6025109291,46.3370933533],"type":"Point"}
}