{
  "type": "Feature",
  "properties": {
    "addr:full":"Rue De L'institut 30 Blegny Li\u00e8ge 4670",
    "addr:housenumber":"30",
    "addr:postcode":"4670",
    "addr:street":"Rue De L'Institut",
    "iso:country":"BE",
    "sg:address":"Rue De L'institut 30",
    "sg:city":"Blegny",
    "sg:orig_category":"Enseignement maternel and primaire",
    "sg:phone":"+32 4 387 41 73",
    "sg:postcode":"4670",
    "sg:province":"Li\u00e8ge",
    "wof:name":"Ecole Fondamentale Libre",
    "wof:placetype":"venue"
},
  "geometry": {"coordinates":[5.7219290733,50.6734580994],"type":"Point"}
}