{
  "type": "Feature",
  "properties": {
    "addr:full":"Hazelstraat 36 Hooglede (gits) West-Vlaanderen 8830",
    "addr:housenumber":"36",
    "addr:postcode":"8830",
    "addr:street":"Hazelstraat",
    "iso:country":"BE",
    "sg:address":"Hazelstraat 36",
    "sg:city":"Hooglede (gits)",
    "sg:classifiers":[
        {
            "category":"Utilities",
            "subcategory":"Fuel Oil & Lpg",
            "type":"Services"
        }
    ],
    "sg:phone":"+32 51 72 21 23",
    "sg:postcode":"8830",
    "sg:province":"West-Vlaanderen",
    "wof:name":"Vandepitte P",
    "wof:placetype":"venue"
},
  "geometry": {"coordinates":[3.1095569134,51.0063018799],"type":"Point"}
}