{
  "type": "Feature",
  "properties": {
    "iso:country":"BE",
    "sg:address":"Eikelstraat 30",
    "sg:city":"Eeklo",
    "sg:classifiers":[
        {
            "category":"Professional",
            "subcategory":"Lawyer & Legal Services",
            "type":"Services"
        }
    ],
    "sg:phone":"+32 9 377 67 54",
    "sg:postcode":"9900",
    "sg:province":"Oost-Vlaanderen",
    "wof:name":"Vervaet Geert",
    "wof:placetype":"venue"
},
  "geometry": {"coordinates":[3.5613698959,51.1884155273],"type":"Point"}
}