{
  "type": "Feature",
  "properties": {
    "iso:country":"BE",
    "sg:address":"Rue Fran\u00c7ois-dache 1",
    "sg:city":"Floreffe",
    "sg:orig_category":"Woningbouw",
    "sg:phone":"+32 81 44 13 81",
    "sg:postcode":"5150",
    "sg:province":"Namur",
    "wof:name":"Alex George",
    "wof:placetype":"venue"
},
  "geometry": {"coordinates":[4.764934063,50.4543800354],"type":"Point"}
}