{
  "type": "Feature",
  "properties": {
    "addr:full":"Rekkemstr. 58 Lauwe West-Vlaanderen 8930",
    "addr:housenumber":"58",
    "addr:postcode":"8930",
    "addr:street":"Rekkemstr.",
    "iso:country":"BE",
    "sg:address":"Rekkemstr. 58",
    "sg:city":"Lauwe",
    "sg:classifiers":[
        {
            "category":"Food & Beverages",
            "subcategory":"Groceries & Convenience Stores",
            "type":"Retail Goods"
        }
    ],
    "sg:phone":"+32 56 50 97 40",
    "sg:postcode":"8930",
    "sg:province":"West-Vlaanderen",
    "sg:tags":[
        "product",
        "related"
    ],
    "wof:name":"Jet Import",
    "wof:placetype":"venue"
},
  "geometry": {"coordinates":[3.1771390438,50.7933120728],"type":"Point"}
}