{
  "type": "Feature",
  "properties": {
    "iso:country":"BE",
    "sg:address":"Rue Joseph Wauters 174",
    "sg:city":"Charleroi",
    "sg:orig_category":"Services de Nettoyage and de D\u00e9sinfection",
    "sg:phone":"+32 71 33 33 97",
    "sg:postcode":"6020",
    "sg:province":"Hainaut",
    "wof:name":"Fr\u00c9d\u00c9ric Eyckerman",
    "wof:placetype":"venue"
},
  "geometry": {"coordinates":[4.4298958778,50.4206924438],"type":"Point"}
}