{
  "type": "Feature",
  "properties": {
    "addr:full":"Andries Pevernagestraat 10 Harelbeke West-Vlaanderen 8530",
    "addr:housenumber":"10",
    "addr:postcode":"8530",
    "addr:street":"Andries Pevernagestraat",
    "iso:country":"BE",
    "sg:address":"Andries Pevernagestraat 10",
    "sg:city":"Harelbeke",
    "sg:classifiers":[
        {
            "category":"Personal",
            "subcategory":"Beauty Salon",
            "type":"Services"
        }
    ],
    "sg:phone":"+32 56 71 26 92",
    "sg:postcode":"8530",
    "sg:province":"West-Vlaanderen",
    "sg:tags":[
        "lady",
        "-",
        "hairdressing"
    ],
    "wof:name":"Nicole",
    "wof:placetype":"venue"
},
  "geometry": {"coordinates":[3.3079149723,50.853351593],"type":"Point"}
}