{
  "type": "Feature",
  "properties": {
    "addr:full":"Lange Lozanastraat 23 Antwerpen-centrum Antwerpen 2018",
    "addr:housenumber":"23",
    "addr:postcode":"2018",
    "addr:street":"Lange Lozanastraat",
    "iso:country":"BE",
    "sg:address":"Lange Lozanastraat 23",
    "sg:city":"Antwerpen-centrum",
    "sg:orig_category":"Magasins de r\u00e9parations d'articles personnels et m\u00e9nagers divers. R\u00e9parations \u00e0 domicile d'articles ",
    "sg:phone":"+32 3 248 69 16",
    "sg:postcode":"2018",
    "sg:province":"Antwerpen",
    "wof:name":"Schoenmakerij Rob",
    "wof:placetype":"venue"
},
  "geometry": {"coordinates":[4.4025669098,51.2062950134],"type":"Point"}
}