{
  "type": "Feature",
  "properties": {
    "addr:full":"Chauss\u00c9e De Hannut 54 Jodoigne Brabant Wallon 1370",
    "addr:housenumber":"54",
    "addr:postcode":"1370",
    "addr:street":"Chausse\u0301E De Hannut",
    "iso:country":"BE",
    "sg:address":"Chauss\u00c9e De Hannut 54",
    "sg:city":"Jodoigne",
    "sg:orig_category":"Herstellingen and onderhoud van auto's Voertuigen",
    "sg:phone":"+32 10 81 25 76",
    "sg:postcode":"1370",
    "sg:province":"Brabant Wallon",
    "wof:name":"Fraipont",
    "wof:placetype":"venue"
},
  "geometry": {"coordinates":[4.8814020157,50.7194404602],"type":"Point"}
}