{
  "type": "Feature",
  "properties": {
    "addr:full":"Fond De Ville 14 Pepinster Li\u00e8ge 4860",
    "addr:housenumber":"14",
    "addr:postcode":"4860",
    "addr:street":"De",
    "iso:country":"BE",
    "sg:address":"Fond De Ville 14",
    "sg:city":"Pepinster",
    "sg:orig_category":"Rundveehouders",
    "sg:phone":"+32 87 46 04 25",
    "sg:postcode":"4860",
    "sg:province":"Li\u00e8ge",
    "wof:name":"Tony Leveque-remy",
    "wof:placetype":"venue"
},
  "geometry": {"coordinates":[5.7917098999,50.5781745911],"type":"Point"}
}