{
  "type": "Feature",
  "properties": {
    "iso:country":"BE",
    "sg:address":"Smetlededorp 19",
    "sg:city":"Lede",
    "sg:classifiers":[
        {
            "category":"Cafe",
            "type":"Food & Drink"
        }
    ],
    "sg:phone":"+32 9 369 84 65",
    "sg:postcode":"9340",
    "sg:province":"Oost-Vlaanderen",
    "sg:tags":[
        "caf\u00e9s"
    ],
    "wof:name":"De Oude Smidse",
    "wof:placetype":"venue"
},
  "geometry": {"coordinates":[3.9294381142,50.9663391113],"type":"Point"}
}