{
  "type": "Feature",
  "properties": {
    "addr:full":"Rue C\u00e9sar De Paepe 44 Oupeye (vivegnis) Li\u00e8ge 4683",
    "addr:housenumber":"44",
    "addr:postcode":"4683",
    "addr:street":"Rue Ce\u0301Sar De Paepe;Vivegnis",
    "iso:country":"BE",
    "sg:address":"Rue C\u00e9sar De Paepe 44",
    "sg:city":"Oupeye (vivegnis)",
    "sg:classifiers":[
        {
            "category":"Shopping",
            "subcategory":"Pharmacy",
            "type":"Retail Goods"
        }
    ],
    "sg:phone":"+32 4 264 06 44",
    "sg:postcode":"4683",
    "sg:province":"Li\u00e8ge",
    "sg:tags":[
        "store",
        "drug"
    ],
    "wof:name":"Thecheur",
    "wof:placetype":"venue"
},
  "geometry": {"coordinates":[5.6495499611,50.6958198547],"type":"Point"}
}