{
  "type": "Feature",
  "properties": {
    "addr:full":"Passage Linthout 11 Bruxelles (woluwe-saint-lambert) Bruxelles-Capitale 1200",
    "addr:housenumber":"11",
    "addr:postcode":"1200",
    "addr:street":"Passage Linthout",
    "iso:country":"BE",
    "sg:address":"Passage Linthout 11",
    "sg:city":"Bruxelles (woluwe-saint-lambert)",
    "sg:classifiers":[
        {
            "category":"Retail",
            "subcategory":"Event Space",
            "type":"Services"
        }
    ],
    "sg:phone":"+32 2 733 36 72",
    "sg:postcode":"1200",
    "sg:province":"Bruxelles-Capitale",
    "sg:tags":[
        "organisation"
    ],
    "wof:name":"Outdoor & Scooting",
    "wof:placetype":"venue"
},
  "geometry": {"coordinates":[4.4026899338,50.8409805298],"type":"Point"}
}