{
  "type": "Feature",
  "properties": {
    "addr:full":"Albert I Laan 79 Koksijde West-Vlaanderen 8670",
    "addr:housenumber":"79",
    "addr:postcode":"8670",
    "addr:street":"Albert I Laan",
    "iso:country":"BE",
    "sg:address":"Albert I Laan 79",
    "sg:city":"Koksijde",
    "sg:orig_category":"Slagers",
    "sg:phone":"+32 58 51 11 57",
    "sg:postcode":"8670",
    "sg:province":"West-Vlaanderen",
    "wof:name":"Johan Ghyllebert",
    "wof:placetype":"venue"
},
  "geometry": {"coordinates":[2.6978850365,51.1396827698],"type":"Point"}
}