{
  "type": "Feature",
  "properties": {
    "addr:full":"Leopoldstraat 127a Ninove (okegem) Oost-Vlaanderen 9400",
    "addr:housenumber":"127a",
    "addr:postcode":"9400",
    "addr:street":"Leopoldstraat",
    "iso:country":"BE",
    "sg:address":"Leopoldstraat 127a",
    "sg:city":"Ninove (okegem)",
    "sg:classifiers":[
        {
            "category":"Travel",
            "subcategory":"Hotels & Motels",
            "type":"Entertainment"
        }
    ],
    "sg:phone":"+32 54 34 23 30",
    "sg:postcode":"9400",
    "sg:province":"Oost-Vlaanderen",
    "sg:tags":[
        "supply",
        "hotels",
        "catering"
    ],
    "wof:name":"Van Vaerenbergh B",
    "wof:placetype":"venue"
},
  "geometry": {"coordinates":[4.0175762177,50.8263282776],"type":"Point"}
}