{
  "type": "Feature",
  "properties": {
    "addr:full":"Chemin De Neerstalle 17 Bruxelles (forest) Bruxelles-Capitale 1190",
    "addr:housenumber":"17",
    "addr:postcode":"1190",
    "addr:street":"Chemin De Neerstalle",
    "iso:country":"BE",
    "sg:address":"Chemin De Neerstalle 17",
    "sg:city":"Bruxelles (forest)",
    "sg:classifiers":[
        {
            "category":"Personal",
            "subcategory":"Nail Salon",
            "type":"Services"
        }
    ],
    "sg:phone":"+32 2 376 39 44",
    "sg:postcode":"1190",
    "sg:province":"Bruxelles-Capitale",
    "sg:tags":[
        "pedicure"
    ],
    "wof:name":"Pedicentre",
    "wof:placetype":"venue"
},
  "geometry": {"coordinates":[4.3172831535,50.8094940186],"type":"Point"}
}