{
  "type": "Feature",
  "properties": {
    "addr:full":"Rijckeveldestraat 7 Damme West-Vlaanderen 8340",
    "addr:housenumber":"7",
    "addr:postcode":"8340",
    "addr:street":"Rijckeveldestraat",
    "iso:country":"BE",
    "sg:address":"Rijckeveldestraat 7",
    "sg:city":"Damme",
    "sg:orig_category":"Eleveurs de bovins",
    "sg:phone":"+32 50 36 21 26",
    "sg:postcode":"8340",
    "sg:province":"West-Vlaanderen",
    "wof:name":"Eric Vincke",
    "wof:placetype":"venue"
},
  "geometry": {"coordinates":[3.293241024,51.2017707825],"type":"Point"}
}