{
  "type": "Feature",
  "properties": {
    "addr:full":"Rue De L'informatique 5 Grace-hollogne Li\u00e8ge 4460",
    "addr:housenumber":"5",
    "addr:postcode":"4460",
    "addr:street":"Rue De L'Informatique",
    "iso:country":"BE",
    "sg:address":"Rue De L'informatique 5",
    "sg:city":"Grace-hollogne",
    "sg:classifiers":[
        {
            "category":"Professional",
            "subcategory":"Testing Lab",
            "type":"Services"
        }
    ],
    "sg:phone":"+32 4 365 03 97",
    "sg:postcode":"4460",
    "sg:province":"Li\u00e8ge",
    "sg:tags":[
        "laboratory",
        "-",
        "machines",
        "apparatus",
        "supply"
    ],
    "wof:name":"Veramic Sa",
    "wof:placetype":"venue"
},
  "geometry": {"coordinates":[5.4990739822,50.654384613],"type":"Point"}
}