{
  "type": "Feature",
  "properties": {
    "iso:country":"BE",
    "sg:address":"Av. G. Henri 401",
    "sg:city":"Bruxelles",
    "sg:classifiers":[
        {
            "category":"Personal",
            "subcategory":"Beauty Salon",
            "type":"Services"
        }
    ],
    "sg:phone":"+32 2 734 27 44",
    "sg:postcode":"1200",
    "sg:province":"Bruxelles-Capitale",
    "sg:tags":[
        "de",
        "coiffure"
    ],
    "wof:name":"Perfect Face",
    "wof:placetype":"venue"
},
  "geometry": {"coordinates":[4.4071297646,50.8413696289],"type":"Point"}
}