{
  "type": "Feature",
  "properties": {
    "iso:country":"BE",
    "sg:address":"Doelstraat 3",
    "sg:city":"Pittem",
    "sg:classifiers":[
        {
            "category":"Retail",
            "subcategory":"Veterinary Services",
            "type":"Services"
        }
    ],
    "sg:phone":"+32 51 46 56 49",
    "sg:postcode":"8740",
    "sg:province":"West-Vlaanderen",
    "sg:tags":[
        "veterinarian"
    ],
    "wof:name":"Vandeputte L",
    "wof:placetype":"venue"
},
  "geometry": {"coordinates":[3.2660489082,50.9951896667],"type":"Point"}
}