{
  "type": "Feature",
  "properties": {
    "iso:country":"BE",
    "sg:address":"Eric Sasselaan 33 Box 22",
    "sg:city":"Antwerpen",
    "sg:classifiers":[
        {
            "category":"Building & Trades",
            "subcategory":"Construction",
            "type":"Services"
        }
    ],
    "sg:phone":"+32 3 248 41 00",
    "sg:postcode":"2020",
    "sg:province":"Antwerpen",
    "sg:tags":[
        "surveyor",
        "-"
    ],
    "wof:name":"Arex Nv",
    "wof:placetype":"venue"
},
  "geometry": {"coordinates":[4.3934879303,51.1922798157],"type":"Point"}
}