{
  "type": "Feature",
  "properties": {
    "iso:country":"BE",
    "sg:address":"Rue Karel Vande Woestijne 24",
    "sg:city":"Bruxelles (anderlecht)",
    "sg:classifiers":[
        {
            "category":"Professional",
            "subcategory":"Art Services",
            "type":"Services"
        }
    ],
    "sg:phone":"+32 2 527 38 38",
    "sg:postcode":"1070",
    "sg:province":"Bruxelles-Capitale",
    "sg:tags":[
        "graphic",
        "designer"
    ],
    "wof:name":"El'd Graphic Design",
    "wof:placetype":"venue"
},
  "geometry": {"coordinates":[4.2943220139,50.8360404968],"type":"Point"}
}