{
  "type": "Feature",
  "properties": {
    "addr:full":"Bredabaan 222 Wuustwezel Antwerpen 2990",
    "addr:housenumber":"222",
    "addr:postcode":"2990",
    "addr:street":"Bredabaan",
    "iso:country":"BE",
    "sg:address":"Bredabaan 222",
    "sg:city":"Wuustwezel",
    "sg:orig_category":"Electrom\u00e9nager, t\u00e9l\u00e9visions and radios",
    "sg:phone":"+32 3 669 61 12",
    "sg:postcode":"2990",
    "sg:province":"Antwerpen",
    "wof:name":"Alfons Kennis",
    "wof:placetype":"venue"
},
  "geometry": {"coordinates":[4.6038799286,51.4000701904],"type":"Point"}
}