{
  "type": "Feature",
  "properties": {
    "iso:country":"BE",
    "sg:address":"Volkslaan 60",
    "sg:city":"Menen",
    "sg:orig_category":"Ordinateurs and \u00e9quipement informatique",
    "sg:phone":"+32 56 53 11 07",
    "sg:postcode":"8930",
    "sg:province":"West-Vlaanderen",
    "wof:name":"G.e.t. Computers",
    "wof:placetype":"venue"
},
  "geometry": {"coordinates":[3.1140050888,50.8063201904],"type":"Point"}
}