{
  "type": "Feature",
  "properties": {
    "iso:country":"BE",
    "sg:address":"Rue De Gougnies 31",
    "sg:city":"Mettet (biesme)",
    "sg:classifiers":[
        {
            "category":"Retail",
            "subcategory":"Veterinary Services",
            "type":"Services"
        }
    ],
    "sg:phone":"+32 71 72 90 12",
    "sg:postcode":"5640",
    "sg:province":"Namur",
    "sg:tags":[
        "veterinarian"
    ],
    "wof:name":"Van Lierde F",
    "wof:placetype":"venue"
},
  "geometry": {"coordinates":[4.6578397751,50.3198051453],"type":"Point"}
}