{
  "type": "Feature",
  "properties": {
    "addr:full":"Nieuwesteenweg 207 De Haan West-Vlaanderen 8420",
    "addr:housenumber":"207",
    "addr:postcode":"8420",
    "addr:street":"Nieuwesteenweg",
    "iso:country":"BE",
    "sg:address":"Nieuwesteenweg 207",
    "sg:city":"De Haan",
    "sg:orig_category":"Computers and computerapparatuur Onderhoud van kantoor- and computeruitrusting Software ontwikkeling",
    "sg:phone":"+32 475 28 54 73",
    "sg:postcode":"8420",
    "sg:province":"West-Vlaanderen",
    "wof:name":"Cuypers Consulting",
    "wof:placetype":"venue"
},
  "geometry": {"coordinates":[3.032253027,51.2651100159],"type":"Point"}
}