{
  "type": "Feature",
  "properties": {
    "iso:country":"BE",
    "sg:address":"Edestraat 127",
    "sg:city":"Haaltert",
    "sg:orig_category":"Entretien and r\u00e9parations de voitures. V\u00e9hicules automobiles",
    "sg:phone":"+32 53 83 57 03",
    "sg:postcode":"9450",
    "sg:province":"Oost-Vlaanderen",
    "wof:name":"Addec",
    "wof:placetype":"venue"
},
  "geometry": {"coordinates":[3.9935400486,50.9095916748],"type":"Point"}
}