{
  "type": "Feature",
  "properties": {
    "addr:full":"Oud Gooreind 37 Wuustwezel Antwerpen 2990",
    "addr:housenumber":"37",
    "addr:postcode":"2990",
    "addr:street":"Oud Gooreind",
    "iso:country":"BE",
    "sg:address":"Oud Gooreind 37",
    "sg:city":"Wuustwezel",
    "sg:orig_category":"Varkenskwekers",
    "sg:phone":"+32 3 663 22 13",
    "sg:postcode":"2990",
    "sg:province":"Antwerpen",
    "wof:name":"Vorsselmans C. & K.",
    "wof:placetype":"venue"
},
  "geometry": {"coordinates":[4.5449738503,51.3645706177],"type":"Point"}
}