{
  "type": "Feature",
  "properties": {
    "iso:country":"BE",
    "sg:address":"Picardstraat 74",
    "sg:city":"Sint-jans-molenbeek/molenbeek-saint-jean",
    "sg:classifiers":[
        {
            "category":"Cafe",
            "type":"Food & Drink"
        }
    ],
    "sg:phone":"+32 2 420 72 72",
    "sg:postcode":"1080",
    "sg:province":"Bruxelles-Capitale",
    "sg:tags":[
        "caf\u00e9s"
    ],
    "wof:name":"Caf\u00c9 Welcom",
    "wof:placetype":"venue"
},
  "geometry": {"coordinates":[4.3450160027,50.8636054993],"type":"Point"}
}