{
  "type": "Feature",
  "properties": {
    "iso:country":"BE",
    "sg:address":"Eeuwfeestlaan 27",
    "sg:city":"Lier",
    "sg:classifiers":[
        {
            "category":"Professional",
            "subcategory":"Lawyer & Legal Services",
            "type":"Services"
        }
    ],
    "sg:phone":"+32 3 489 01 29",
    "sg:postcode":"2500",
    "sg:province":"Antwerpen",
    "wof:name":"Jansens M",
    "wof:placetype":"venue"
},
  "geometry": {"coordinates":[4.5594730377,51.1390686035],"type":"Point"}
}