{
  "type": "Feature",
  "properties": {
    "addr:full":"Nederkouter 112 Gent Oost-Vlaanderen 9000",
    "addr:housenumber":"112",
    "addr:postcode":"9000",
    "addr:street":"Nederkouter;Oost-Vlaanderen",
    "iso:country":"BE",
    "sg:address":"Nederkouter 112",
    "sg:city":"Gent",
    "sg:orig_category":"Enseignement maternel and primaire",
    "sg:phone":"+32 9 265 70 60",
    "sg:postcode":"9000",
    "sg:province":"Oost-Vlaanderen",
    "wof:name":"Vrije Basisschool",
    "wof:placetype":"venue"
},
  "geometry": {"coordinates":[3.7218370438,51.0466880798],"type":"Point"}
}