{
  "type": "Feature",
  "properties": {
    "iso:country":"BE",
    "sg:address":"Konijnestraat 172",
    "sg:city":"Sint-pieters-leeuw",
    "sg:orig_category":"Jardins botaniques, zoologiques, observatoires and r\u00e9serves naturelles",
    "sg:phone":"+32 2 532 24 10",
    "sg:postcode":"1602",
    "sg:province":"Vlaams-Brabant",
    "wof:name":"Kasteelpark Groennenberg",
    "wof:placetype":"venue"
},
  "geometry": {"coordinates":[4.2128500938,50.8046684265],"type":"Point"}
}