{
  "type": "Feature",
  "properties": {
    "iso:country":"BE",
    "sg:address":"Steenweg Op Weelde 13",
    "sg:city":"Merksplas",
    "sg:classifiers":[
        {
            "category":"Retail",
            "subcategory":"Veterinary Services",
            "type":"Services"
        }
    ],
    "sg:phone":"+32 14 63 50 63",
    "sg:postcode":"2330",
    "sg:province":"Antwerpen",
    "sg:tags":[
        "veterinarian"
    ],
    "wof:name":"Van Gelder G",
    "wof:placetype":"venue"
},
  "geometry": {"coordinates":[4.8771247864,51.3780975342],"type":"Point"}
}