{
  "type": "Feature",
  "properties": {
    "addr:full":"Stationsstraat 76 Sint-niklaas Oost-Vlaanderen 9100",
    "addr:housenumber":"76",
    "addr:postcode":"9100",
    "addr:street":"Stationsstraat",
    "iso:country":"BE",
    "sg:address":"Stationsstraat 76",
    "sg:city":"Sint-niklaas",
    "sg:orig_category":"Baby- and kinderkleding",
    "sg:phone":"+32 3 766 60 87",
    "sg:postcode":"9100",
    "sg:province":"Oost-Vlaanderen",
    "wof:name":"Mexx",
    "wof:placetype":"venue"
},
  "geometry": {"coordinates":[4.1417589188,51.1677589417],"type":"Point"}
}