{
  "type": "Feature",
  "properties": {
    "addr:full":"Dorpsdam 46 Beveren (vrasene) Oost-Vlaanderen 9120",
    "addr:housenumber":"46",
    "addr:postcode":"9120",
    "addr:street":"Dorpsdam",
    "iso:country":"BE",
    "sg:address":"Dorpsdam 46",
    "sg:city":"Beveren (vrasene)",
    "sg:classifiers":[
        {
            "category":"Health Services",
            "subcategory":"Health Practitioner",
            "type":"Services"
        }
    ],
    "sg:phone":"+32 3 775 27 97",
    "sg:postcode":"9120",
    "sg:province":"Oost-Vlaanderen",
    "sg:tags":[
        "physiotherapist"
    ],
    "wof:name":"Smet J",
    "wof:placetype":"venue"
},
  "geometry": {"coordinates":[4.1924519539,51.2215690613],"type":"Point"}
}