{
  "type": "Feature",
  "properties": {
    "addr:full":"Kromme Elleboogstraat 11 Lede Oost-Vlaanderen 9340",
    "addr:housenumber":"11",
    "addr:postcode":"9340",
    "addr:street":"Kromme Elleboogstraat",
    "iso:country":"BE",
    "sg:address":"Kromme Elleboogstraat 11",
    "sg:city":"Lede",
    "sg:orig_category":"M\u00e9decins and sp\u00e9cialistes",
    "sg:phone":"+32 53 80 12 81",
    "sg:postcode":"9340",
    "sg:province":"Oost-Vlaanderen",
    "wof:name":"Marianne Van Landuyt",
    "wof:placetype":"venue"
},
  "geometry": {"coordinates":[3.9986960888,50.9749450684],"type":"Point"}
}