{
  "type": "Feature",
  "properties": {
    "iso:country":"BE",
    "sg:address":"Lamorinierestraat 187",
    "sg:city":"Antwerpen",
    "sg:orig_category":"Apotheken",
    "sg:phone":"+32 3 239 09 56",
    "sg:postcode":"2018",
    "sg:province":"Antwerpen",
    "wof:name":"Isabelle Rotti",
    "wof:placetype":"venue"
},
  "geometry": {"coordinates":[4.4198899269,51.2023353577],"type":"Point"}
}