{
  "type": "Feature",
  "properties": {
    "iso:country":"BE",
    "sg:address":"J. Smeetslaan 3",
    "sg:city":"Maasmechelen",
    "sg:orig_category":"Natuursteenbewerking",
    "sg:phone":"+32 89 77 18 89",
    "sg:postcode":"3630",
    "sg:province":"Limburg",
    "wof:name":"Westhovens R.",
    "wof:placetype":"venue"
},
  "geometry": {"coordinates":[5.6950411797,50.964515686],"type":"Point"}
}