{
  "type": "Feature",
  "properties": {
    "iso:country":"BE",
    "sg:address":"Bijlokestraat 20",
    "sg:city":"Dendermonde",
    "sg:classifiers":[
        {
            "category":"Cafe",
            "type":"Food & Drink"
        }
    ],
    "sg:phone":"+32 52 21 78 85",
    "sg:postcode":"9200",
    "sg:province":"Oost-Vlaanderen",
    "sg:tags":[
        "caf\u00e9s"
    ],
    "wof:name":"Micheline Mertens",
    "wof:placetype":"venue"
},
  "geometry": {"coordinates":[4.0826859474,51.0366477966],"type":"Point"}
}