{
  "type": "Feature",
  "properties": {
    "addr:full":"G. Gezellelaan 16 Wuustwezel Antwerpen 2990",
    "addr:housenumber":"16",
    "addr:postcode":"2990",
    "addr:street":"G. Gezellelaan",
    "iso:country":"BE",
    "sg:address":"G. Gezellelaan 16",
    "sg:city":"Wuustwezel",
    "sg:orig_category":"Fleurs and plantes",
    "sg:phone":"+32 3 669 71 58",
    "sg:postcode":"2990",
    "sg:province":"Antwerpen",
    "wof:name":"'t Meiklokje",
    "wof:placetype":"venue"
},
  "geometry": {"coordinates":[4.5977640152,51.3936767578],"type":"Point"}
}