{
  "type": "Feature",
  "properties": {
    "iso:country":"BE",
    "sg:address":"Bosstraat 71",
    "sg:city":"Bertem",
    "sg:classifiers":[
        {
            "category":"Health Services",
            "subcategory":"Doctor",
            "type":"Services"
        }
    ],
    "sg:phone":"+32 16 47 49 74",
    "sg:postcode":"3060",
    "sg:province":"Vlaams-Brabant",
    "sg:tags":[
        "medicinephysicians",
        "surgeon"
    ],
    "wof:name":"Goedseels Goele",
    "wof:placetype":"venue"
},
  "geometry": {"coordinates":[4.64523983,50.8648414612],"type":"Point"}
}