{
  "type": "Feature",
  "properties": {
    "iso:country":"BE",
    "sg:address":"Bruggestraat 28",
    "sg:city":"Hoeselt",
    "sg:orig_category":"Sportclubs",
    "sg:phone":"+32 89 51 40 20",
    "sg:postcode":"3730",
    "sg:province":"Limburg",
    "wof:name":"De Rommelaar",
    "wof:placetype":"venue"
},
  "geometry": {"coordinates":[5.4550728798,50.8519897461],"type":"Point"}
}