{
  "type": "Feature",
  "properties": {
    "addr:full":"Belgi\u00eblei 21 Antwerpen Antwerpen 2018",
    "addr:housenumber":"21",
    "addr:postcode":"2018",
    "addr:street":"Belgie\u0308Lei",
    "iso:country":"BE",
    "sg:address":"Belgi\u00eblei 21",
    "sg:city":"Antwerpen",
    "sg:classifiers":[
        {
            "category":"Shopping",
            "subcategory":"Jewelry",
            "type":"Retail Goods"
        }
    ],
    "sg:phone":"+32 3 230 05 50",
    "sg:postcode":"2018",
    "sg:province":"Antwerpen",
    "sg:tags":[
        "diamond",
        "-"
    ],
    "wof:name":"Alta-gi Intermediary Services",
    "wof:placetype":"venue"
},
  "geometry": {"coordinates":[4.4221110344,51.2082862854],"type":"Point"}
}