{
  "type": "Feature",
  "properties": {
    "addr:full":"Leiestraat 101 Waregem West-Vlaanderen 8792",
    "addr:housenumber":"101",
    "addr:postcode":"8792",
    "addr:street":"Leiestraat",
    "iso:country":"BE",
    "sg:address":"Leiestraat 101",
    "sg:city":"Waregem",
    "sg:orig_category":"Groententeelt",
    "sg:phone":"+32 56 71 39 61",
    "sg:postcode":"8792",
    "sg:province":"West-Vlaanderen",
    "wof:name":"Fa. Biebuyck Jacques",
    "wof:placetype":"venue"
},
  "geometry": {"coordinates":[3.3608651161,50.8929901123],"type":"Point"}
}