{
  "type": "Feature",
  "properties": {
    "iso:country":"BE",
    "sg:address":"Mandelln 533",
    "sg:city":"Roeselare",
    "sg:classifiers":[
        {
            "category":"Manufacturing",
            "subcategory":"Printing",
            "type":"Manufacturing & Wholesale Goods"
        }
    ],
    "sg:phone":"+32 51 24 38 00",
    "sg:postcode":"8800",
    "sg:province":"West-Vlaanderen",
    "sg:tags":[
        "publishing"
    ],
    "wof:name":"Concordia Bvba",
    "wof:placetype":"venue"
},
  "geometry": {"coordinates":[3.1549549103,50.9368476868],"type":"Point"}
}