{
  "type": "Feature",
  "properties": {
    "iso:country":"BE",
    "sg:address":"Lippeloseweg 44",
    "sg:city":"Sint-amands",
    "sg:classifiers":[
        {
            "category":"Cafe",
            "type":"Food & Drink"
        }
    ],
    "sg:phone":"+32 3 889 03 60",
    "sg:postcode":"2890",
    "sg:province":"Antwerpen",
    "sg:tags":[
        "caf\u00e9s"
    ],
    "wof:name":"Patrick Stevens",
    "wof:placetype":"venue"
},
  "geometry": {"coordinates":[4.2452840805,51.0629959106],"type":"Point"}
}