{
  "type": "Feature",
  "properties": {
    "iso:country":"BE",
    "sg:address":"Kouterbaan 30",
    "sg:city":"Londerzeel",
    "sg:orig_category":"Dakwerken",
    "sg:phone":"+32 52 33 75 93",
    "sg:postcode":"1840",
    "sg:province":"Vlaams-Brabant",
    "wof:name":"Dakwerken Sollie",
    "wof:placetype":"venue"
},
  "geometry": {"coordinates":[4.2488369942,51.0200843811],"type":"Point"}
}