{
  "type": "Feature",
  "properties": {
    "iso:country":"BE",
    "sg:address":"Rue L\u00e9on-castilhon 11",
    "sg:city":"Arlon",
    "sg:classifiers":[
        {
            "category":"Professional",
            "subcategory":"Lawyer & Legal Services",
            "type":"Services"
        }
    ],
    "sg:phone":"+32 63 21 61 13",
    "sg:postcode":"6700",
    "sg:province":"Luxembourg",
    "wof:name":"Mortier Thierry",
    "wof:placetype":"venue"
},
  "geometry": {"coordinates":[5.8089270592,49.6844520569],"type":"Point"}
}