{
  "type": "Feature",
  "properties": {
    "iso:country":"BE",
    "sg:address":"Geuzenplein 10",
    "sg:city":"Brussel/bruxelles",
    "sg:orig_category":"Banken and kredietinstellingen",
    "sg:phone":"+32 2 735 02 66",
    "sg:postcode":"1000",
    "sg:province":"Bruxelles-Capitale",
    "wof:name":"Dexia",
    "wof:placetype":"venue"
},
  "geometry": {"coordinates":[4.3911547661,50.8473358154],"type":"Point"}
}