{
  "type": "Feature",
  "properties": {
    "addr:full":"Gravin Elisabethlaan 1 Hoogstraten Antwerpen 2320",
    "addr:housenumber":"1",
    "addr:postcode":"2320",
    "addr:street":"Gravin Elisabethlaan",
    "iso:country":"BE",
    "sg:address":"Gravin Elisabethlaan 1",
    "sg:city":"Hoogstraten",
    "sg:orig_category":"Parfumeries",
    "sg:phone":"+32 3 314 14 40",
    "sg:postcode":"2320",
    "sg:province":"Antwerpen",
    "wof:name":"I.f.f.",
    "wof:placetype":"venue"
},
  "geometry": {"coordinates":[4.760488987,51.4005012512],"type":"Point"}
}