{
  "type": "Feature",
  "properties": {
    "addr:full":"Herent 50 Neerpelt Limburg 3910",
    "addr:housenumber":"50",
    "addr:postcode":"3910",
    "addr:street":"Herent",
    "iso:country":"BE",
    "sg:address":"Herent 50",
    "sg:city":"Neerpelt",
    "sg:orig_category":"Rundveehouders",
    "sg:phone":"+32 11 80 27 11",
    "sg:postcode":"3910",
    "sg:province":"Limburg",
    "wof:name":"Lemmens Geert & Henricus",
    "wof:placetype":"venue"
},
  "geometry": {"coordinates":[5.4431872368,51.2077217102],"type":"Point"}
}