{
  "type": "Feature",
  "properties": {
    "iso:country":"BE",
    "sg:address":"Pietingbaan 29",
    "sg:city":"Boechout",
    "sg:orig_category":"Groententeelt",
    "sg:phone":"+32 3 455 80 27",
    "sg:postcode":"2531",
    "sg:province":"Antwerpen",
    "wof:name":"Marcel Van Ostaeyen",
    "wof:placetype":"venue"
},
  "geometry": {"coordinates":[4.5179710388,51.1865081787],"type":"Point"}
}