{
  "type": "Feature",
  "properties": {
    "iso:country":"BE",
    "sg:address":"Beselarestraat 33",
    "sg:city":"Wervik",
    "sg:orig_category":"Enseignement maternel and primaire",
    "sg:phone":"+32 56 51 24 92",
    "sg:postcode":"8940",
    "sg:province":"West-Vlaanderen",
    "wof:name":"Vrije Lagere School",
    "wof:placetype":"venue"
},
  "geometry": {"coordinates":[3.0441479683,50.7851867676],"type":"Point"}
}