{
  "type": "Feature",
  "properties": {
    "iso:country":"BE",
    "sg:address":"Grotesteenweg 11",
    "sg:city":"Geel",
    "sg:orig_category":"Elektrische installaties voor woningen",
    "sg:phone":"+32 14 59 11 31",
    "sg:postcode":"2440",
    "sg:province":"Antwerpen",
    "wof:name":"Narviflex",
    "wof:placetype":"venue"
},
  "geometry": {"coordinates":[4.9426350594,51.1224632263],"type":"Point"}
}