{
  "type": "Feature",
  "properties": {
    "addr:full":"Rue Des Rhieux 47 Saint-nicolas Li\u00e8ge 4420",
    "addr:housenumber":"47",
    "addr:postcode":"4420",
    "addr:street":"Rue Des Rhieux",
    "iso:country":"BE",
    "sg:address":"Rue Des Rhieux 47",
    "sg:city":"Saint-nicolas",
    "sg:orig_category":"Instituts de beaut\u00e9",
    "sg:phone":"+32 4 247 39 54",
    "sg:postcode":"4420",
    "sg:province":"Li\u00e8ge",
    "wof:name":"P\u00c9dicure Damico",
    "wof:placetype":"venue"
},
  "geometry": {"coordinates":[5.5170049667,50.640586853],"type":"Point"}
}