{
  "type": "Feature",
  "properties": {
    "addr:full":"Rue Gustave Fi\u00e9vet 47 Sombreffe Namur 5140",
    "addr:housenumber":"47",
    "addr:postcode":"5140",
    "addr:street":"Rue Gustave Fie\u0301Vet",
    "iso:country":"BE",
    "sg:address":"Rue Gustave Fi\u00e9vet 47",
    "sg:city":"Sombreffe",
    "sg:classifiers":[
        {
            "category":"Personal",
            "subcategory":"Beauty Salon",
            "type":"Services"
        }
    ],
    "sg:phone":"+32 71 88 79 03",
    "sg:postcode":"5140",
    "sg:province":"Namur",
    "sg:tags":[
        "lady",
        "-",
        "hairdressing"
    ],
    "wof:name":"Coif'actuelle",
    "wof:placetype":"venue"
},
  "geometry": {"coordinates":[4.6031842232,50.5222320557],"type":"Point"}
}