{
  "type": "Feature",
  "properties": {
    "addr:full":"Koolstraat 16 Mechelen Antwerpen 2800",
    "addr:housenumber":"16",
    "addr:postcode":"2800",
    "addr:street":"Koolstraat",
    "iso:country":"BE",
    "sg:address":"Koolstraat 16",
    "sg:city":"Mechelen",
    "sg:classifiers":[
        {
            "category":"Manufacturing",
            "subcategory":"Metals",
            "type":"Manufacturing & Wholesale Goods"
        }
    ],
    "sg:phone":"+32 15 26 01 42",
    "sg:postcode":"2800",
    "sg:province":"Antwerpen",
    "sg:tags":[
        "working"
    ],
    "wof:name":"Vekemans-de Vos Nv",
    "wof:placetype":"venue"
},
  "geometry": {"coordinates":[4.4643602371,51.0281105042],"type":"Point"}
}