{
  "type": "Feature",
  "properties": {
    "addr:full":"'s Gravenhagestraat 17 Heist-op-den-berg Antwerpen 2220",
    "addr:housenumber":"17",
    "addr:postcode":"2220",
    "addr:street":"' S Gravenhagestraat",
    "iso:country":"BE",
    "sg:address":"'s Gravenhagestraat 17",
    "sg:city":"Heist-op-den-berg",
    "sg:classifiers":[
        {
            "category":"Personal",
            "subcategory":"Beauty Salon",
            "type":"Services"
        }
    ],
    "sg:phone":"+32 15 24 61 57",
    "sg:postcode":"2220",
    "sg:province":"Antwerpen",
    "sg:tags":[
        "de",
        "coiffure"
    ],
    "wof:name":"Coiffure Sonja",
    "wof:placetype":"venue"
},
  "geometry": {"coordinates":[4.7088541985,51.0478210449],"type":"Point"}
}