{
  "type": "Feature",
  "properties": {
    "iso:country":"BE",
    "sg:address":"Jaak Blockxstraat 82",
    "sg:city":"Mortsel",
    "sg:classifiers":[
        {
            "category":"Food & Beverages",
            "subcategory":"Groceries & Convenience Stores",
            "type":"Retail Goods"
        }
    ],
    "sg:phone":"+32 3 440 49 05",
    "sg:postcode":"2640",
    "sg:province":"Antwerpen",
    "sg:tags":[
        "grocer"
    ],
    "wof:name":"Bij De Wies",
    "wof:placetype":"venue"
},
  "geometry": {"coordinates":[4.4480481148,51.1754302979],"type":"Point"}
}