{
  "type": "Feature",
  "properties": {
    "iso:country":"BE",
    "sg:address":"Groendreef 131",
    "sg:city":"Gent",
    "sg:classifiers":[
        {
            "category":"Personal",
            "subcategory":"Beauty Salon",
            "type":"Services"
        }
    ],
    "sg:phone":"+32 9 226 12 33",
    "sg:postcode":"9000",
    "sg:province":"Oost-Vlaanderen",
    "sg:tags":[
        "de",
        "coiffure"
    ],
    "wof:name":"Coiffure D'art",
    "wof:placetype":"venue"
},
  "geometry": {"coordinates":[3.699477911,51.0652656555],"type":"Point"}
}