{
  "type": "Feature",
  "properties": {
    "addr:full":"Rue Macdonald 38 Mons (jemappes) Hainaut 7012",
    "addr:housenumber":"38",
    "addr:postcode":"7012",
    "addr:street":"Rue Macdonald",
    "iso:country":"BE",
    "sg:address":"Rue Macdonald 38",
    "sg:city":"Mons (jemappes)",
    "sg:classifiers":[
        {
            "category":"Communications",
            "type":"Services"
        }
    ],
    "sg:phone":"+32 65 36 14 18",
    "sg:postcode":"7012",
    "sg:province":"Hainaut",
    "sg:tags":[
        "translator"
    ],
    "wof:name":"@nnnet",
    "wof:placetype":"venue"
},
  "geometry": {"coordinates":[3.8894600868,50.4481964111],"type":"Point"}
}