{
  "type": "Feature",
  "properties": {
    "iso:country":"BE",
    "sg:address":"Ch Romaine 177 Zi",
    "sg:city":"Waremme",
    "sg:classifiers":[
        {
            "category":"Transit Center",
            "subcategory":"Freight",
            "type":"Transportation"
        }
    ],
    "sg:phone":"+32 19 32 86 06",
    "sg:postcode":"4300",
    "sg:province":"Li\u00e8ge",
    "sg:tags":[
        "metallurgy",
        "pipe",
        "metalworking",
        "sheet"
    ],
    "wof:name":"Robert Sa",
    "wof:placetype":"venue"
},
  "geometry": {"coordinates":[5.2565498352,50.6982498169],"type":"Point"}
}