{
  "type": "Feature",
  "properties": {
    "iso:country":"BE",
    "sg:address":"Chemin Du Sabotier 4",
    "sg:city":"Seneffe",
    "sg:classifiers":[
        {
            "category":"Arts & Performance",
            "subcategory":"Music",
            "type":"Entertainment"
        }
    ],
    "sg:phone":"+32 64 54 89 75",
    "sg:postcode":"7180",
    "sg:province":"Hainaut",
    "sg:tags":[
        "disc-jockeys"
    ],
    "wof:name":"Killing Night Sonorisation",
    "wof:placetype":"venue"
},
  "geometry": {"coordinates":[4.2534079552,50.5265541077],"type":"Point"}
}