{
  "type": "Feature",
  "properties": {
    "addr:full":"Spieveldstraat 7 Lokeren Oost-Vlaanderen 9160",
    "addr:housenumber":"7",
    "addr:postcode":"9160",
    "addr:street":"Spieveldstraat",
    "iso:country":"BE",
    "sg:address":"Spieveldstraat 7",
    "sg:city":"Lokeren",
    "sg:classifiers":[
        {
            "category":"Government",
            "subcategory":"Fire Station",
            "type":"Public Place"
        }
    ],
    "sg:phone":"+32 9 348 66 86",
    "sg:postcode":"9160",
    "sg:province":"Oost-Vlaanderen",
    "sg:tags":[
        "supraregional",
        "plant",
        "installation",
        "heating"
    ],
    "wof:name":"Ongena B.v.b.a.",
    "wof:placetype":"venue"
},
  "geometry": {"coordinates":[4.0038809776,51.0873603821],"type":"Point"}
}