{
  "type": "Feature",
  "properties": {
    "addr:full":"Koekamerstraat 59 Maarkedal Oost-Vlaanderen 9688",
    "addr:housenumber":"59",
    "addr:postcode":"9688",
    "addr:street":"Koekamerstraat",
    "iso:country":"BE",
    "sg:address":"Koekamerstraat 59",
    "sg:city":"Maarkedal",
    "sg:orig_category":"Elektrische installaties voor woningen",
    "sg:phone":"+32 55 21 79 39",
    "sg:postcode":"9688",
    "sg:province":"Oost-Vlaanderen",
    "wof:name":"Martin Van Quickelberghe",
    "wof:placetype":"venue"
},
  "geometry": {"coordinates":[3.6700649261,50.7720375061],"type":"Point"}
}