{
  "type": "Feature",
  "properties": {
    "addr:full":"Philippe Spethstraat 64 Kapellen Antwerpen 2950",
    "addr:housenumber":"64",
    "addr:postcode":"2950",
    "addr:street":"Philippe Spethstraat",
    "iso:country":"BE",
    "sg:address":"Philippe Spethstraat 64",
    "sg:city":"Kapellen",
    "sg:orig_category":"Kapsalons",
    "sg:phone":"+32 3 664 85 12",
    "sg:postcode":"2950",
    "sg:province":"Antwerpen",
    "wof:name":"De Bodt",
    "wof:placetype":"venue"
},
  "geometry": {"coordinates":[4.4276151657,51.3208236694],"type":"Point"}
}