{
  "type": "Feature",
  "properties": {
    "addr:full":"Kerkstraat 64 Ninove Oost-Vlaanderen 9406",
    "addr:housenumber":"64",
    "addr:postcode":"9406",
    "addr:street":"Kerkstraat",
    "iso:country":"BE",
    "sg:address":"Kerkstraat 64",
    "sg:city":"Ninove",
    "sg:orig_category":"Enseignement maternel and primaire",
    "sg:phone":"+32 54 33 44 35",
    "sg:postcode":"9406",
    "sg:province":"Oost-Vlaanderen",
    "wof:name":"Vrije Basisschool",
    "wof:placetype":"venue"
},
  "geometry": {"coordinates":[3.996860981,50.8439674377],"type":"Point"}
}