{
  "type": "Feature",
  "properties": {
    "addr:full":"Molenstraat 19ba Moorslede West-Vlaanderen 8890",
    "addr:housenumber":"19ba",
    "addr:postcode":"8890",
    "addr:street":"Molenstraat",
    "iso:country":"BE",
    "sg:address":"Molenstraat 19ba",
    "sg:city":"Moorslede",
    "sg:orig_category":"Pluimveekwekers Rundveehouders",
    "sg:phone":"+32 51 77 92 80",
    "sg:postcode":"8890",
    "sg:province":"West-Vlaanderen",
    "wof:name":"Rik Demuynck",
    "wof:placetype":"venue"
},
  "geometry": {"coordinates":[3.0317349434,50.8849945068],"type":"Point"}
}