{
  "type": "Feature",
  "properties": {
    "addr:full":"Rue Des Coteaux 63 Brussel Bruxelles-Capitale 1030",
    "addr:housenumber":"63",
    "addr:postcode":"1030",
    "addr:street":"Rue Des Coteaux",
    "iso:country":"BE",
    "sg:address":"Rue Des Coteaux 63",
    "sg:city":"Brussel",
    "sg:orig_category":"Sportcentra",
    "sg:phone":"+32 2 218 52 64",
    "sg:postcode":"1030",
    "sg:province":"Bruxelles-Capitale",
    "wof:name":"Graciosa Hatha-yoga",
    "wof:placetype":"venue"
},
  "geometry": {"coordinates":[4.3746829033,50.8561248779],"type":"Point"}
}