{
  "type": "Feature",
  "properties": {
    "iso:country":"BE",
    "sg:address":"Fabriekstraat 16",
    "sg:city":"Geel",
    "sg:orig_category":"Rev\u00eatements de sols and murs",
    "sg:phone":"+32 14 58 92 62",
    "sg:postcode":"2440",
    "sg:province":"Antwerpen",
    "wof:name":"Ga-vra",
    "wof:placetype":"venue"
},
  "geometry": {"coordinates":[4.9910240173,51.16796875],"type":"Point"}
}