{
  "type": "Feature",
  "properties": {
    "addr:full":"Rue Pierreuse 46 Li\u00c8ge Li\u00e8ge 4000",
    "addr:housenumber":"46",
    "addr:postcode":"4000",
    "addr:street":"Rue Pierreuse",
    "iso:country":"BE",
    "sg:address":"Rue Pierreuse 46",
    "sg:city":"Li\u00c8ge",
    "sg:orig_category":"Kapsalons",
    "sg:phone":"+32 4 222 42 83",
    "sg:postcode":"4000",
    "sg:province":"Li\u00e8ge",
    "wof:name":"Coiffure Chez Joseph",
    "wof:placetype":"venue"
},
  "geometry": {"coordinates":[5.5727229118,50.6472129822],"type":"Point"}
}