{
  "type": "Feature",
  "properties": {
    "iso:country":"BE",
    "sg:address":"97",
    "sg:city":"Avenue Buysdelle 1180 Uccle",
    "sg:classifiers":[
        {
            "category":"Travel",
            "subcategory":"Hotels & Motels",
            "type":"Entertainment"
        }
    ],
    "sg:phone":"+32 2 380 68 60",
    "sg:postcode":"97",
    "sg:tags":[
        "hotels",
        "business",
        "restaurant"
    ],
    "wof:name":"Noicha Sprl",
    "wof:placetype":"venue"
},
  "geometry": {"coordinates":[4.3542451859,50.7742538452],"type":"Point"}
}