{
  "type": "Feature",
  "properties": {
    "iso:country":"BE",
    "sg:address":"Handelslei 85",
    "sg:city":"Zoersel",
    "sg:orig_category":"Diverse bouwinstallaties Reclamebureaus Verlichtingsapparaten and elektrische lampen Fab",
    "sg:phone":"+32 3 384 17 94",
    "sg:postcode":"2980",
    "sg:province":"Antwerpen",
    "wof:name":"Neonlight",
    "wof:placetype":"venue"
},
  "geometry": {"coordinates":[4.645430088,51.2712097168],"type":"Point"}
}