{
  "type": "Feature",
  "properties": {
    "addr:full":"Heidestraat 41 Kasterlee Antwerpen 2460",
    "addr:housenumber":"41",
    "addr:postcode":"2460",
    "addr:street":"Heidestraat",
    "iso:country":"BE",
    "sg:address":"Heidestraat 41",
    "sg:city":"Kasterlee",
    "sg:orig_category":"V\u00e9t\u00e9rinaires",
    "sg:phone":"+32 14 55 10 70",
    "sg:postcode":"2460",
    "sg:province":"Antwerpen",
    "wof:name":"Vera Wellens",
    "wof:placetype":"venue"
},
  "geometry": {"coordinates":[4.9098849297,51.2095680237],"type":"Point"}
}