{
  "type": "Feature",
  "properties": {
    "iso:country":"BE",
    "sg:address":"Bruggesteenweg 110",
    "sg:city":"Hooglede",
    "sg:orig_category":"Royal Canin. Animaux domestiques and accessoires",
    "sg:phone":"+32 51 22 08 34",
    "sg:postcode":"8830",
    "sg:province":"West-Vlaanderen",
    "wof:name":"Spanhove",
    "wof:placetype":"venue"
},
  "geometry": {"coordinates":[3.0932149887,50.9820137024],"type":"Point"}
}