{
  "type": "Feature",
  "properties": {
    "iso:country":"BE",
    "sg:address":"Beverestraat 52",
    "sg:city":"Oudenaarde",
    "sg:classifiers":[
        {
            "category":"Shopping",
            "subcategory":"Clothing, Apparel, & Fashions",
            "type":"Retail Goods"
        }
    ],
    "sg:phone":"+32 55 31 33 41",
    "sg:postcode":"9700",
    "sg:province":"Oost-Vlaanderen",
    "sg:tags":[
        "v\u00eatements",
        "pour",
        "dame"
    ],
    "wof:name":"Jacqueline Vereecken",
    "wof:placetype":"venue"
},
  "geometry": {"coordinates":[3.5989639759,50.8489952087],"type":"Point"}
}