{
  "type": "Feature",
  "properties": {
    "iso:country":"BE",
    "sg:address":"Populierestraat 3",
    "sg:city":"Herzele (sint-lievens-esse)",
    "sg:classifiers":[
        {
            "category":"Professional",
            "subcategory":"Lawyer & Legal Services",
            "type":"Services"
        }
    ],
    "sg:phone":"+32 54 50 04 51",
    "sg:postcode":"9550",
    "sg:province":"Oost-Vlaanderen",
    "sg:tags":[
        "notary"
    ],
    "wof:name":"Laloo V",
    "wof:placetype":"venue"
},
  "geometry": {"coordinates":[3.8842589855,50.8542251587],"type":"Point"}
}