{
  "type": "Feature",
  "properties": {
    "iso:country":"BE",
    "sg:address":"Avenue Albert I 123",
    "sg:city":"Li\u00e8ge 1 (grivegn\u00e9e)",
    "sg:orig_category":"Non-Classified Establishments",
    "sg:phone":"+32 4 342 77 53",
    "sg:postcode":"4030",
    "sg:province":"Li\u00e8ge",
    "wof:name":"Quincaillerie Centrale-hody",
    "wof:placetype":"venue"
},
  "geometry": {"coordinates":[5.5945649147,50.6235275269],"type":"Point"}
}