{
  "type": "Feature",
  "properties": {
    "iso:country":"BE",
    "sg:address":"Avenue Marius Meur\u00e9e 24",
    "sg:city":"Charleroi (marcinelle)",
    "sg:orig_category":"Non-Classified Establishments",
    "sg:phone":"+32 71 43 32 83",
    "sg:postcode":"6001",
    "sg:province":"Hainaut",
    "wof:name":"Centre P M S Sp\u00e9cialis\u00e9 Provincial",
    "wof:placetype":"venue"
},
  "geometry": {"coordinates":[4.4477009773,50.4008178711],"type":"Point"}
}