{
  "type": "Feature",
  "properties": {
    "addr:full":"Stationsstraat 33 Bierbeek (lovenjoel) Vlaams-Brabant 3360",
    "addr:housenumber":"33",
    "addr:postcode":"3360",
    "addr:street":"Stationsstraat",
    "iso:country":"BE",
    "sg:address":"Stationsstraat 33",
    "sg:city":"Bierbeek (lovenjoel)",
    "sg:classifiers":[
        {
            "category":"Fast Food",
            "type":"Food & Drink"
        }
    ],
    "sg:phone":"+32 16 46 15 05",
    "sg:postcode":"3360",
    "sg:province":"Vlaams-Brabant",
    "sg:tags":[
        "fried",
        "stand",
        "potato"
    ],
    "wof:name":"D.l.",
    "wof:placetype":"venue"
},
  "geometry": {"coordinates":[4.7825431824,50.8534240723],"type":"Point"}
}