{
  "type": "Feature",
  "properties": {
    "addr:full":"Willem Van Doornyckstr. 40 Beveren Oost-Vlaanderen 9120",
    "addr:housenumber":"40",
    "addr:postcode":"9120",
    "addr:street":"Willem Van Doornyckstr.",
    "iso:country":"BE",
    "sg:address":"Willem Van Doornyckstr. 40",
    "sg:city":"Beveren",
    "sg:orig_category":"Boucheries",
    "sg:phone":"+32 3 775 71 27",
    "sg:postcode":"9120",
    "sg:province":"Oost-Vlaanderen",
    "wof:name":"Willi Pauwels",
    "wof:placetype":"venue"
},
  "geometry": {"coordinates":[4.2352671623,51.1802062988],"type":"Point"}
}