{
  "type": "Feature",
  "properties": {
    "addr:full":"Vlasgaard 31 Zoersel Antwerpen 2980",
    "addr:housenumber":"31",
    "addr:postcode":"2980",
    "addr:street":"Vlasgaard",
    "iso:country":"BE",
    "sg:address":"Vlasgaard 31",
    "sg:city":"Zoersel",
    "sg:orig_category":"Woningbouw",
    "sg:phone":"+32 3 383 52 43",
    "sg:postcode":"2980",
    "sg:province":"Antwerpen",
    "wof:name":"David Huybrechts",
    "wof:placetype":"venue"
},
  "geometry": {"coordinates":[4.6417531967,51.2389411926],"type":"Point"}
}