{
  "type": "Feature",
  "properties": {
    "iso:country":"BE",
    "sg:address":"Leuvensesteenweg 25-27",
    "sg:city":"Aarschot (gelrode)",
    "sg:classifiers":[
        {
            "category":"Cemetery",
            "type":"Public Place"
        }
    ],
    "sg:phone":"+32 16 56 66 26",
    "sg:postcode":"3200",
    "sg:province":"Vlaams-Brabant",
    "sg:tags":[
        "crematory"
    ],
    "wof:name":"Goovaerts & Andries",
    "wof:placetype":"venue"
},
  "geometry": {"coordinates":[4.8230700493,50.9806289673],"type":"Point"}
}