{
  "type": "Feature",
  "properties": {
    "addr:full":"Ferdinand Maesstraat 62 Kontich (waarloos) Antwerpen 2550",
    "addr:housenumber":"62",
    "addr:postcode":"2550",
    "addr:street":"Ferdinand Maesstraat",
    "iso:country":"BE",
    "sg:address":"Ferdinand Maesstraat 62",
    "sg:city":"Kontich (waarloos)",
    "sg:classifiers":[
        {
            "category":"Bakery",
            "type":"Food & Drink"
        }
    ],
    "sg:phone":"+32 15 31 51 12",
    "sg:postcode":"2550",
    "sg:province":"Antwerpen",
    "sg:tags":[
        "confectioner",
        "baker"
    ],
    "wof:name":"Dom Bvba",
    "wof:placetype":"venue"
},
  "geometry": {"coordinates":[4.4540729523,51.1055259705],"type":"Point"}
}