{
  "type": "Feature",
  "properties": {
    "iso:country":"BE",
    "sg:address":"Ballonssteenweg 70",
    "sg:city":"Moeskroen/mouscron",
    "sg:orig_category":"Loodgieterij, verwarming and sanitaire installaties Rundveehouders",
    "sg:phone":"+32 56 33 10 56",
    "sg:postcode":"7700",
    "sg:province":"Hainaut",
    "wof:name":"Etienne Rogge",
    "wof:placetype":"venue"
},
  "geometry": {"coordinates":[3.2236790657,50.7215881348],"type":"Point"}
}