{
  "type": "Feature",
  "properties": {
    "iso:country":"BE",
    "sg:address":"Stalingradlaan 74",
    "sg:city":"Brussel/bruxelles",
    "sg:orig_category":"Musea and historische gebouwen",
    "sg:phone":"+32 2 512 39 64",
    "sg:postcode":"1000",
    "sg:province":"Bruxelles-Capitale",
    "wof:name":"Joods Museum Van Belgi\u00cb/musee Juif De Belgique",
    "wof:placetype":"venue"
},
  "geometry": {"coordinates":[4.3434448242,50.8406486511],"type":"Point"}
}