{
  "type": "Feature",
  "properties": {
    "addr:full":"Rekkemsestraat 133 Kortrijk West-Vlaanderen 8510",
    "addr:housenumber":"133",
    "addr:postcode":"8510",
    "addr:street":"Rekkemsestraat",
    "iso:country":"BE",
    "sg:address":"Rekkemsestraat 133",
    "sg:city":"Kortrijk",
    "sg:orig_category":"Slagers Supermarkten",
    "sg:phone":"+32 56 22 24 14",
    "sg:postcode":"8510",
    "sg:province":"West-Vlaanderen",
    "wof:name":"Goma",
    "wof:placetype":"venue"
},
  "geometry": {"coordinates":[3.2280659676,50.8078956604],"type":"Point"}
}