{
  "type": "Feature",
  "properties": {
    "iso:country":"BE",
    "sg:address":"Museumstraat 45",
    "sg:city":"Antwerpen",
    "sg:classifiers":[
        {
            "category":"Bars & Pubs",
            "type":"Food & Drink"
        }
    ],
    "sg:phone":"+32 3 238 09 95",
    "sg:postcode":"2000",
    "sg:province":"Antwerpen",
    "wof:name":"Artist (den)",
    "wof:placetype":"venue"
},
  "geometry": {"coordinates":[4.3934397697,51.209148407],"type":"Point"}
}