{
  "type": "Feature",
  "properties": {
    "iso:country":"BE",
    "sg:address":"Micheletstraat 15",
    "sg:city":"Antwerpen",
    "sg:orig_category":"Foto-uitrusting",
    "sg:phone":"+32 3 219 55 81",
    "sg:postcode":"2050",
    "sg:province":"Antwerpen",
    "wof:name":"Advertising Photography",
    "wof:placetype":"venue"
},
  "geometry": {"coordinates":[4.3887162209,51.2285499573],"type":"Point"}
}