{
  "type": "Feature",
  "properties": {
    "iso:country":"BE",
    "sg:address":"Rue Du Rivage 31",
    "sg:city":"Thuin",
    "sg:classifiers":[
        {
            "category":"Cafe",
            "type":"Food & Drink"
        }
    ],
    "sg:phone":"+32 71 59 62 00",
    "sg:postcode":"6530",
    "sg:province":"Hainaut",
    "sg:tags":[
        "caf\u00e9s"
    ],
    "wof:name":"Freddy Jovet",
    "wof:placetype":"venue"
},
  "geometry": {"coordinates":[4.289126873,50.3411712646],"type":"Point"}
}