{
  "type": "Feature",
  "properties": {
    "addr:full":"Grand'rue 113 Morlanwelz Hainaut 7140",
    "addr:housenumber":"113",
    "addr:postcode":"7140",
    "addr:street":"Grand'Rue",
    "iso:country":"BE",
    "sg:address":"Grand'rue 113",
    "sg:city":"Morlanwelz",
    "sg:orig_category":"Speelgoed",
    "sg:phone":"+32 64 44 82 47",
    "sg:postcode":"7140",
    "sg:province":"Hainaut",
    "wof:name":"Delsinne J",
    "wof:placetype":"venue"
},
  "geometry": {"coordinates":[4.2428760529,50.45520401],"type":"Point"}
}