{
  "type": "Feature",
  "properties": {
    "iso:country":"BE",
    "sg:address":"Ieperstraat 56",
    "sg:city":"Kortemark",
    "sg:orig_category":"Eleveurs de bovins",
    "sg:phone":"+32 51 56 79 14",
    "sg:postcode":"8610",
    "sg:province":"West-Vlaanderen",
    "wof:name":"Demedts Rafael En Jules",
    "wof:placetype":"venue"
},
  "geometry": {"coordinates":[3.0554189682,51.0184936523],"type":"Point"}
}