{
  "type": "Feature",
  "properties": {
    "addr:full":"Chauss\u00e9e De Namur 414 Gembloux-sur-orneau (beuzet) Namur 5030",
    "addr:housenumber":"414",
    "addr:postcode":"5030",
    "addr:street":"Chausse\u0301E De Namur;Namur",
    "iso:country":"BE",
    "sg:address":"Chauss\u00e9e De Namur 414",
    "sg:city":"Gembloux-sur-orneau (beuzet)",
    "sg:classifiers":[
        {
            "category":"Wholesale",
            "subcategory":"Wine & Distilled Alcoholic Beverages",
            "type":"Manufacturing & Wholesale Goods"
        }
    ],
    "sg:phone":"+32 81 56 78 14",
    "sg:postcode":"5030",
    "sg:province":"Namur",
    "sg:tags":[
        "whol",
        "-",
        "spirit",
        "mfg"
    ],
    "wof:name":"Groupvin",
    "wof:placetype":"venue"
},
  "geometry": {"coordinates":[4.7464299202,50.5299911499],"type":"Point"}
}