{
  "type": "Feature",
  "properties": {
    "addr:full":"Holenbroek 6 Brakel Oost-Vlaanderen 9660",
    "addr:housenumber":"6",
    "addr:postcode":"9660",
    "addr:street":"Holenbroek",
    "iso:country":"BE",
    "sg:address":"Holenbroek 6",
    "sg:city":"Brakel",
    "sg:orig_category":"Installation \u00e9lectrique r\u00e9sidentielle. Plomberie, chauffage and installations sanitaires",
    "sg:phone":"+32 55 42 62 96",
    "sg:postcode":"9660",
    "sg:province":"Oost-Vlaanderen",
    "wof:name":"Helmut Van Onacker",
    "wof:placetype":"venue"
},
  "geometry": {"coordinates":[3.7462790012,50.789516449],"type":"Point"}
}