{
  "type": "Feature",
  "properties": {
    "iso:country":"BE",
    "sg:address":"Levieplein 2",
    "sg:city":"Sint-lambrechts-woluwe/woluwe-saint-lambert",
    "sg:orig_category":"Kapsalons",
    "sg:phone":"+32 2 735 36 44",
    "sg:postcode":"1200",
    "sg:province":"Bruxelles-Capitale",
    "wof:name":"Coiffure Autre Chose",
    "wof:placetype":"venue"
},
  "geometry": {"coordinates":[4.4090590477,50.8480453491],"type":"Point"}
}