{
  "type": "Feature",
  "properties": {
    "iso:country":"BE",
    "sg:address":"Donkerstraat 61",
    "sg:city":"Zulte",
    "sg:classifiers":[
        {
            "category":"Arena",
            "subcategory":"Sports Club",
            "type":"Entertainment"
        }
    ],
    "sg:phone":"+32 9 386 60 26",
    "sg:postcode":"9870",
    "sg:province":"Oost-Vlaanderen",
    "sg:tags":[
        "terrain",
        "hors",
        "de",
        "installation",
        "sportifs"
    ],
    "wof:name":"K. Eendr. Machelen-a-leie",
    "wof:placetype":"venue"
},
  "geometry": {"coordinates":[3.4953100681,50.9597167969],"type":"Point"}
}