{
  "type": "Feature",
  "properties": {
    "iso:country":"BE",
    "sg:address":"Merestraat 10",
    "sg:city":"Erpe-mere (erpe)",
    "sg:classifiers":[
        {
            "category":"Health Services",
            "subcategory":"Health Practitioner",
            "type":"Services"
        }
    ],
    "sg:phone":"+32 53 83 20 54",
    "sg:postcode":"9420",
    "sg:province":"Oost-Vlaanderen",
    "sg:tags":[
        "physiotherapist"
    ],
    "wof:name":"Vermassen Mieke",
    "wof:placetype":"venue"
},
  "geometry": {"coordinates":[3.9837799072,50.9264144897],"type":"Point"}
}