{
  "type": "Feature",
  "properties": {
    "addr:full":"Nijvendries 24 Sint-amands (oppuurs) Antwerpen 2890",
    "addr:housenumber":"24",
    "addr:postcode":"2890",
    "addr:street":"Nijvendries",
    "iso:country":"BE",
    "sg:address":"Nijvendries 24",
    "sg:city":"Sint-amands (oppuurs)",
    "sg:classifiers":[
        {
            "category":"Health Services",
            "subcategory":"Health Practitioner",
            "type":"Services"
        }
    ],
    "sg:phone":"+32 3 889 14 28",
    "sg:postcode":"2890",
    "sg:province":"Antwerpen",
    "sg:tags":[
        "dietitian"
    ],
    "wof:name":"Dewitte E",
    "wof:placetype":"venue"
},
  "geometry": {"coordinates":[4.2380108833,51.0595664978],"type":"Point"}
}