{
  "type": "Feature",
  "properties": {
    "addr:full":"Vondelstraat 1 Harelbeke West-Vlaanderen 8531",
    "addr:housenumber":"1",
    "addr:postcode":"8531",
    "addr:street":"Vondelstraat",
    "iso:country":"BE",
    "sg:address":"Vondelstraat 1",
    "sg:city":"Harelbeke",
    "sg:orig_category":"Installation \u00e9lectrique r\u00e9sidentielle",
    "sg:phone":"+32 56 71 02 31",
    "sg:postcode":"8531",
    "sg:province":"West-Vlaanderen",
    "wof:name":"Dirk Vermaut",
    "wof:placetype":"venue"
},
  "geometry": {"coordinates":[3.3015680313,50.870464325],"type":"Point"}
}