{
  "type": "Feature",
  "properties": {
    "iso:country":"BE",
    "sg:address":"Sint-jansstraat 138",
    "sg:city":"Essen",
    "sg:classifiers":[
        {
            "category":"Utilities",
            "subcategory":"Fuel Oil & Lpg",
            "type":"Services"
        }
    ],
    "sg:phone":"+32 3 677 23 40",
    "sg:postcode":"2910",
    "sg:province":"Antwerpen",
    "wof:name":"Koninckx Gebr Bvba",
    "wof:placetype":"venue"
},
  "geometry": {"coordinates":[4.4797201157,51.4242210388],"type":"Point"}
}