{
  "type": "Feature",
  "properties": {
    "iso:country":"BE",
    "sg:address":"Prinses Patriciastraat 1",
    "sg:city":"Zonnebeke",
    "sg:orig_category":"Agences de presse",
    "sg:phone":"+32 57 46 75 05",
    "sg:postcode":"8980",
    "sg:province":"West-Vlaanderen",
    "wof:name":"Marc Dejonckheere",
    "wof:placetype":"venue"
},
  "geometry": {"coordinates":[2.9571669102,50.8559417725],"type":"Point"}
}