{
  "type": "Feature",
  "properties": {
    "iso:country":"BE",
    "sg:address":"Rue Trou Barbeau 84",
    "sg:city":"Charleroi",
    "sg:orig_category":"Woningbouw",
    "sg:phone":"+32 71 30 75 82",
    "sg:postcode":"6031",
    "sg:province":"Hainaut",
    "wof:name":"Michel Franceschino",
    "wof:placetype":"venue"
},
  "geometry": {"coordinates":[4.38022995,50.4121742249],"type":"Point"}
}