{
  "type": "Feature",
  "properties": {
    "addr:full":"Voie De L'ardenne 75 Chaudfontaine (embourg) Li\u00e8ge 4053",
    "addr:housenumber":"75",
    "addr:postcode":"4053",
    "addr:street":"Voie De L'Ardenne",
    "iso:country":"BE",
    "sg:address":"Voie De L'ardenne 75",
    "sg:city":"Chaudfontaine (embourg)",
    "sg:classifiers":[
        {
            "category":"Health Services",
            "subcategory":"Doctor",
            "type":"Services"
        }
    ],
    "sg:phone":"+32 4 366 01 06",
    "sg:postcode":"4053",
    "sg:province":"Li\u00e8ge",
    "sg:tags":[
        "medicinephysicians",
        "surgeon"
    ],
    "wof:name":"Henrijean A",
    "wof:placetype":"venue"
},
  "geometry": {"coordinates":[5.6064329147,50.5915145874],"type":"Point"}
}