{
  "type": "Feature",
  "properties": {
    "addr:full":"Rue Verte Herbe 8 Antoing Hainaut 7640",
    "addr:housenumber":"8",
    "addr:postcode":"7640",
    "addr:street":"Rue Verte Herbe",
    "iso:country":"BE",
    "sg:address":"Rue Verte Herbe 8",
    "sg:city":"Antoing",
    "sg:classifiers":[
        {
            "category":"Home & Garden",
            "subcategory":"Furniture",
            "type":"Retail Goods"
        }
    ],
    "sg:phone":"+32 69 44 30 50",
    "sg:postcode":"7640",
    "sg:province":"Hainaut",
    "sg:tags":[
        "wood"
    ],
    "wof:name":"De Terck Bois Sa",
    "wof:placetype":"venue"
},
  "geometry": {"coordinates":[3.4500029087,50.5638885498],"type":"Point"}
}