{
  "type": "Feature",
  "properties": {
    "addr:full":"Avenue De L'et\u00e9 78 Waterloo Brabant Wallon 1410",
    "addr:housenumber":"78",
    "addr:postcode":"1410",
    "addr:street":"Avenue De L'Ete \u0301",
    "iso:country":"BE",
    "sg:address":"Avenue De L'et\u00e9 78",
    "sg:city":"Waterloo",
    "sg:classifiers":[
        {
            "category":"Home & Garden",
            "subcategory":"Furniture",
            "type":"Retail Goods"
        }
    ],
    "sg:phone":"+32 2 351 09 00",
    "sg:postcode":"1410",
    "sg:province":"Brabant Wallon",
    "sg:tags":[
        "-"
    ],
    "wof:name":"Cegeco Bvba",
    "wof:placetype":"venue"
},
  "geometry": {"coordinates":[4.3906188011,50.707572937],"type":"Point"}
}