{
  "type": "Feature",
  "properties": {
    "addr:full":"Chauss\u00c9e De Gand 1108 Sint-agatha-berchem/berchem-sainte-agathe Bruxelles-Capitale 1082",
    "addr:housenumber":"1108",
    "addr:postcode":"1082",
    "addr:street":"Chausse\u0301E De Gand;/",
    "iso:country":"BE",
    "sg:address":"Chauss\u00c9e De Gand 1108",
    "sg:city":"Sint-agatha-berchem/berchem-sainte-agathe",
    "sg:orig_category":"Salles de spectacles",
    "sg:phone":"+32 2 465 31 08",
    "sg:postcode":"1082",
    "sg:province":"Bruxelles-Capitale",
    "wof:name":"Galerij Amaryllis",
    "wof:placetype":"venue"
},
  "geometry": {"coordinates":[4.3007650375,50.8621025085],"type":"Point"}
}