{
  "type": "Feature",
  "properties": {
    "addr:full":"Rue Brigade Piron 12 Charleroi Hainaut 6061",
    "addr:housenumber":"12",
    "addr:postcode":"6061",
    "addr:street":"Rue Brigade Piron;Hainaut",
    "iso:country":"BE",
    "sg:address":"Rue Brigade Piron 12",
    "sg:city":"Charleroi",
    "sg:orig_category":"Dierenartsen",
    "sg:phone":"+32 71 31 94 35",
    "sg:postcode":"6061",
    "sg:province":"Hainaut",
    "wof:name":"Jean-claude Depape",
    "wof:placetype":"venue"
},
  "geometry": {"coordinates":[4.4660429955,50.4038543701],"type":"Point"}
}