{
  "type": "Feature",
  "properties": {
    "addr:full":"Meiboomstraat 16 Blankenberge (uitkerke) West-Vlaanderen 8370",
    "addr:housenumber":"16",
    "addr:postcode":"8370",
    "addr:street":"Meiboomstraat",
    "iso:country":"BE",
    "sg:address":"Meiboomstraat 16",
    "sg:city":"Blankenberge (uitkerke)",
    "sg:classifiers":[
        {
            "category":"Communications",
            "subcategory":"Film & Video Production",
            "type":"Services"
        }
    ],
    "sg:phone":"+32 50 41 07 70",
    "sg:postcode":"8370",
    "sg:province":"West-Vlaanderen",
    "sg:tags":[
        "realisation",
        "-"
    ],
    "wof:name":"E & A Video Productions",
    "wof:placetype":"venue"
},
  "geometry": {"coordinates":[3.1501700878,51.3007354736],"type":"Point"}
}