{
  "type": "Feature",
  "properties": {
    "iso:country":"BE",
    "sg:address":"Rue De Quevaucamps 31",
    "sg:city":"Beloeil (bas\u00e8cles)",
    "sg:orig_category":"Fiduciairies",
    "sg:phone":"+32 69 59 03 20",
    "sg:postcode":"7971",
    "sg:province":"Hainaut",
    "wof:name":"I C S",
    "wof:placetype":"venue"
},
  "geometry": {"coordinates":[3.663230896,50.5217895508],"type":"Point"}
}