{
  "type": "Feature",
  "properties": {
    "addr:full":"Hollestraat 54 Erpe-mere Oost-Vlaanderen 9420",
    "addr:housenumber":"54",
    "addr:postcode":"9420",
    "addr:street":"Hollestraat",
    "iso:country":"BE",
    "sg:address":"Hollestraat 54",
    "sg:city":"Erpe-mere",
    "sg:orig_category":"Eclairage et \u00e9quipements du foyer. Souvenirs and objets artisanaux",
    "sg:phone":"+32 53 62 43 05",
    "sg:postcode":"9420",
    "sg:province":"Oost-Vlaanderen",
    "wof:name":"Uno De Cock",
    "wof:placetype":"venue"
},
  "geometry": {"coordinates":[3.9462680817,50.8881797791],"type":"Point"}
}