{
  "type": "Feature",
  "properties": {
    "addr:full":"Tiensestraat 69 Leuven Vlaams-Brabant 3000",
    "addr:housenumber":"69",
    "addr:postcode":"3000",
    "addr:street":"Tiensestraat",
    "iso:country":"BE",
    "sg:address":"Tiensestraat 69",
    "sg:city":"Leuven",
    "sg:classifiers":[
        {
            "category":"Restaurant",
            "type":"Food & Drink"
        }
    ],
    "sg:phone":"+32 16 22 44 44",
    "sg:postcode":"3000",
    "sg:province":"Vlaams-Brabant",
    "wof:name":"Panach\u00c9",
    "wof:placetype":"venue"
},
  "geometry": {"coordinates":[4.7053608894,50.8769760132],"type":"Point"}
}