{
  "type": "Feature",
  "properties": {
    "addr:full":"Scharynckweg 1 Koekelare West-Vlaanderen 8680",
    "addr:housenumber":"1",
    "addr:postcode":"8680",
    "addr:street":"Scharynckweg",
    "iso:country":"BE",
    "sg:address":"Scharynckweg 1",
    "sg:city":"Koekelare",
    "sg:orig_category":"Rundveehouders Varkenskwekers",
    "sg:phone":"+32 59 27 86 29",
    "sg:postcode":"8680",
    "sg:province":"West-Vlaanderen",
    "wof:name":"Amede Vandecasteele",
    "wof:placetype":"venue"
},
  "geometry": {"coordinates":[2.943666935,51.1108627319],"type":"Point"}
}