{
  "type": "Feature",
  "properties": {
    "addr:full":"Rozelaarstraat 10 Hasselt (sint-lambrechts-herk) Limburg 3500",
    "addr:housenumber":"10",
    "addr:postcode":"3500",
    "addr:street":"Rozelaarstraat",
    "iso:country":"BE",
    "sg:address":"Rozelaarstraat 10",
    "sg:city":"Hasselt (sint-lambrechts-herk)",
    "sg:classifiers":[
        {
            "category":"Health Services",
            "subcategory":"Health Practitioner",
            "type":"Services"
        }
    ],
    "sg:phone":"+32 11 72 63 10",
    "sg:postcode":"3500",
    "sg:province":"Limburg",
    "sg:tags":[
        "physiotherapist"
    ],
    "wof:name":"Van De Perre Hilde",
    "wof:placetype":"venue"
},
  "geometry": {"coordinates":[5.3066802025,50.9071922302],"type":"Point"}
}