{
  "type": "Feature",
  "properties": {
    "iso:country":"BE",
    "sg:address":"Avenue Alphonse Valkeners 5-1",
    "sg:city":"Bruxelles (auderghem)",
    "sg:classifiers":[
        {
            "category":"Professional",
            "subcategory":"Employment Agencies",
            "type":"Services"
        }
    ],
    "sg:phone":"+32 2 663 65 55",
    "sg:postcode":"1160",
    "sg:province":"Bruxelles-Capitale",
    "sg:tags":[
        "market",
        "research"
    ],
    "wof:name":"Eole Belgium Sprl",
    "wof:placetype":"venue"
},
  "geometry": {"coordinates":[4.4100089073,50.8225097656],"type":"Point"}
}