{
  "type": "Feature",
  "properties": {
    "iso:country":"BE",
    "sg:address":"Rue Georges Truffaut 31",
    "sg:city":"Ans",
    "sg:orig_category":"Dansscholen",
    "sg:phone":"+32 4 263 62 14",
    "sg:postcode":"4432",
    "sg:province":"Li\u00e8ge",
    "wof:name":"Salons Le Carr\u00c9",
    "wof:placetype":"venue"
},
  "geometry": {"coordinates":[5.5141468048,50.6749458313],"type":"Point"}
}