{
  "type": "Feature",
  "properties": {
    "addr:full":"Rue De Fl\u00e9nu 37 Quaregnon Hainaut 7390",
    "addr:housenumber":"37",
    "addr:postcode":"7390",
    "addr:street":"Rue De Fle\u0301Nu",
    "iso:country":"BE",
    "sg:address":"Rue De Fl\u00e9nu 37",
    "sg:city":"Quaregnon",
    "sg:classifiers":[
        {
            "category":"Professional",
            "subcategory":"Accounting & Tax Preparation",
            "type":"Services"
        }
    ],
    "sg:phone":"+32 65 78 31 23",
    "sg:postcode":"7390",
    "sg:province":"Hainaut",
    "sg:tags":[
        "bookkeeper"
    ],
    "wof:name":"Meersseman J",
    "wof:placetype":"venue"
},
  "geometry": {"coordinates":[3.8746459484,50.4410705566],"type":"Point"}
}