{
  "type": "Feature",
  "properties": {
    "addr:full":"Kerkenbos 10 Mechelen Antwerpen 2812",
    "addr:housenumber":"10",
    "addr:postcode":"2812",
    "addr:street":"Kerkenbos",
    "iso:country":"BE",
    "sg:address":"Kerkenbos 10",
    "sg:city":"Mechelen",
    "sg:orig_category":"Installation \u00e9lectrique r\u00e9sidentielle",
    "sg:phone":"+32 15 41 92 54",
    "sg:postcode":"2812",
    "sg:province":"Antwerpen",
    "wof:name":"Jan Cooreman",
    "wof:placetype":"venue"
},
  "geometry": {"coordinates":[4.5207519531,51.0089569092],"type":"Point"}
}