{
  "type": "Feature",
  "properties": {
    "addr:full":"Heerbaan 35 Opwijk (mazenzele) Vlaams-Brabant 1745",
    "addr:housenumber":"35",
    "addr:postcode":"1745",
    "addr:street":"Heerbaan",
    "iso:country":"BE",
    "sg:address":"Heerbaan 35",
    "sg:city":"Opwijk (mazenzele)",
    "sg:classifiers":[
        {
            "category":"Building & Trades",
            "subcategory":"Construction",
            "type":"Services"
        }
    ],
    "sg:phone":"+32 52 35 50 85",
    "sg:postcode":"1745",
    "sg:province":"Vlaams-Brabant",
    "sg:tags":[
        "carpenter"
    ],
    "wof:name":"Van De Velde E & Zn",
    "wof:placetype":"venue"
},
  "geometry": {"coordinates":[4.1687898636,50.9405632019],"type":"Point"}
}