{
  "type": "Feature",
  "properties": {
    "iso:country":"BE",
    "sg:address":"Meerseniersstraat 14",
    "sg:city":"Gent",
    "sg:classifiers":[
        {
            "category":"Bars & Pubs",
            "type":"Food & Drink"
        }
    ],
    "sg:phone":"+32 9 233 67 34",
    "sg:postcode":"9000",
    "sg:province":"Oost-Vlaanderen",
    "sg:tags":[
        "tavern"
    ],
    "wof:name":"Stropke ('t)",
    "wof:placetype":"venue"
},
  "geometry": {"coordinates":[3.7243850231,51.057559967],"type":"Point"}
}