{
  "type": "Feature",
  "properties": {
    "addr:full":"Amb. Zone De Waerde 2063 Zonhoven Limburg 3520",
    "addr:postcode":"2063 zonhoven;3520",
    "iso:country":"BE",
    "sg:address":"Amb. Zone De Waerde 2063",
    "sg:city":"Zonhoven",
    "sg:orig_category":"Traitement and rev\u00eatement des m\u00e9taux",
    "sg:phone":"+32 11 81 52 78",
    "sg:postcode":"3520",
    "sg:province":"Limburg",
    "wof:name":"Metaaldecor",
    "wof:placetype":"venue"
},
  "geometry": {"coordinates":[5.3856692314,51.0018310547],"type":"Point"}
}