{
  "type": "Feature",
  "properties": {
    "iso:country":"BE",
    "sg:address":"Populierenstraat 11",
    "sg:city":"Overpelt",
    "sg:orig_category":"Installation \u00e9lectrique r\u00e9sidentielle",
    "sg:phone":"+32 11 64 74 24",
    "sg:postcode":"3900",
    "sg:province":"Limburg",
    "wof:name":"Josse Boonen",
    "wof:placetype":"venue"
},
  "geometry": {"coordinates":[5.4125781059,51.2224769592],"type":"Point"}
}