{
  "type": "Feature",
  "properties": {
    "addr:full":"Boulevard Joseph Tirou 35 Charleroi Hainaut 6000",
    "addr:housenumber":"35",
    "addr:postcode":"6000",
    "addr:street":"Boulevard Joseph Tirou;Hainaut",
    "iso:country":"BE",
    "sg:address":"Boulevard Joseph Tirou 35",
    "sg:city":"Charleroi",
    "sg:classifiers":[
        {
            "category":"Insurance",
            "subcategory":"Life Insurance",
            "type":"Services"
        }
    ],
    "sg:phone":"+32 71 20 05 00",
    "sg:postcode":"6000",
    "sg:province":"Hainaut",
    "sg:tags":[
        "assurance"
    ],
    "wof:name":"Assurances Generali Belg.",
    "wof:placetype":"venue"
},
  "geometry": {"coordinates":[4.4390249252,50.4089775085],"type":"Point"}
}