{
  "type": "Feature",
  "properties": {
    "iso:country":"BE",
    "sg:address":"Urselweg 17",
    "sg:city":"Aalter",
    "sg:classifiers":[
        {
            "category":"Professional",
            "subcategory":"Management & Consulting",
            "type":"Services"
        }
    ],
    "sg:phone":"+32 9 374 32 70",
    "sg:postcode":"9880",
    "sg:province":"Oost-Vlaanderen",
    "sg:tags":[
        "consultant"
    ],
    "wof:name":"Hoste & Partners Gcv",
    "wof:placetype":"venue"
},
  "geometry": {"coordinates":[3.4432361126,51.1145057678],"type":"Point"}
}