{
  "type": "Feature",
  "properties": {
    "addr:full":"Frederik Peltzerstraat 34 Lier Antwerpen 2500",
    "addr:housenumber":"34",
    "addr:postcode":"2500",
    "addr:street":"Frederik Peltzerstraat",
    "iso:country":"BE",
    "sg:address":"Frederik Peltzerstraat 34",
    "sg:city":"Lier",
    "sg:orig_category":"M\u00e9decins and sp\u00e9cialistes",
    "sg:phone":"+32 3 480 75 26",
    "sg:postcode":"2500",
    "sg:province":"Antwerpen",
    "wof:name":"J. Van Der Wee",
    "wof:placetype":"venue"
},
  "geometry": {"coordinates":[4.5718870163,51.1358947754],"type":"Point"}
}