{
  "type": "Feature",
  "properties": {
    "addr:full":"Redingenhof 4 Leuven Vlaams-Brabant 3000",
    "addr:housenumber":"4",
    "addr:postcode":"3000",
    "addr:street":"Redingenhof",
    "iso:country":"BE",
    "sg:address":"Redingenhof 4",
    "sg:city":"Leuven",
    "sg:classifiers":[
        {
            "category":"Food & Beverages",
            "subcategory":"Cheese",
            "type":"Retail Goods"
        }
    ],
    "sg:phone":"+32 16 22 22 72",
    "sg:postcode":"3000",
    "sg:province":"Vlaams-Brabant",
    "sg:tags":[
        "-"
    ],
    "wof:name":"Coosemans A",
    "wof:placetype":"venue"
},
  "geometry": {"coordinates":[4.6957368851,50.8748893738],"type":"Point"}
}