{
  "type": "Feature",
  "properties": {
    "addr:full":"Kortrijkstraat 6 Lichtervelde West-Vlaanderen 8810",
    "addr:housenumber":"6",
    "addr:postcode":"8810",
    "addr:street":"Kortrijkstraat",
    "iso:country":"BE",
    "sg:address":"Kortrijkstraat 6",
    "sg:city":"Lichtervelde",
    "sg:orig_category":"Non-Classified Establishments",
    "sg:phone":"+32 51 72 26 04",
    "sg:postcode":"8810",
    "sg:province":"West-Vlaanderen",
    "wof:name":"Thevelein D",
    "wof:placetype":"venue"
},
  "geometry": {"coordinates":[3.156596899,51.0132865906],"type":"Point"}
}