{
  "type": "Feature",
  "properties": {
    "iso:country":"BE",
    "sg:address":"Rue Des Panottes 2",
    "sg:city":"Silly",
    "sg:orig_category":"Artiesten and kunstenaars",
    "sg:phone":"+32 67 45 89 87",
    "sg:postcode":"7830",
    "sg:province":"Hainaut",
    "wof:name":"Desmette",
    "wof:placetype":"venue"
},
  "geometry": {"coordinates":[3.94810009,50.6096000671],"type":"Point"}
}