{
  "type": "Feature",
  "properties": {
    "addr:full":"Nieuwe Bevelsesteenweg 45 Nijlen Antwerpen 2560",
    "addr:housenumber":"45",
    "addr:postcode":"2560",
    "addr:street":"Nieuwe Bevelsesteenweg",
    "iso:country":"BE",
    "sg:address":"Nieuwe Bevelsesteenweg 45",
    "sg:city":"Nijlen",
    "sg:orig_category":"Eleveurs de bovins",
    "sg:phone":"+32 3 480 49 47",
    "sg:postcode":"2560",
    "sg:province":"Antwerpen",
    "wof:name":"Ludovicus Van Den Bergh",
    "wof:placetype":"venue"
},
  "geometry": {"coordinates":[4.6713829041,51.1590843201],"type":"Point"}
}