{
  "type": "Feature",
  "properties": {
    "addr:full":"Rue L\u00c9opold I 293 Brussel/bruxelles Bruxelles-Capitale 1020",
    "addr:housenumber":"293",
    "addr:postcode":"1020",
    "addr:street":"Rue Le\u0301Opold I;/",
    "iso:country":"BE",
    "sg:address":"Rue L\u00c9opold I 293",
    "sg:city":"Brussel/bruxelles",
    "sg:orig_category":"Artistes ind\u00e9pendants",
    "sg:phone":"+32 2 427 01 12",
    "sg:postcode":"1020",
    "sg:province":"Bruxelles-Capitale",
    "wof:name":"Georges Liegeois",
    "wof:placetype":"venue"
},
  "geometry": {"coordinates":[4.3405051231,50.8769226074],"type":"Point"}
}