{
  "type": "Feature",
  "properties": {
    "iso:country":"BE",
    "sg:address":"Ind. Park Brechtsebaan 18b",
    "sg:city":"Schoten",
    "sg:orig_category":"Bouwmaterialen Gh Chemicali\u00ebn Gh Loodgieterij, verwarming and sanitaire installaties Zwembadinstalla",
    "sg:phone":"+32 3 658 57 07",
    "sg:postcode":"2900",
    "sg:province":"Antwerpen",
    "wof:name":"Frencken",
    "wof:placetype":"venue"
},
  "geometry": {"coordinates":[4.5107097626,51.2652397156],"type":"Point"}
}