{
  "type": "Feature",
  "properties": {
    "addr:full":"Rue Du Commerce 22 Wavre Brabant Wallon 1300",
    "addr:housenumber":"22;1300",
    "addr:street":"Rue Du Commerce",
    "iso:country":"BE",
    "sg:address":"Rue Du Commerce 22",
    "sg:city":"Wavre",
    "sg:orig_category":"Chaussures",
    "sg:phone":"+32 10 22 85 66",
    "sg:postcode":"1300",
    "sg:province":"Brabant Wallon",
    "wof:name":"Maison Collard Germaine",
    "wof:placetype":"venue"
},
  "geometry": {"coordinates":[4.6102638245,50.7163543701],"type":"Point"}
}