{
  "type": "Feature",
  "properties": {
    "addr:full":"Provincialebaan 24 Buggenhout Oost-Vlaanderen 9255",
    "addr:housenumber":"24",
    "addr:postcode":"9255",
    "addr:street":"Provincialebaan",
    "iso:country":"BE",
    "sg:address":"Provincialebaan 24",
    "sg:city":"Buggenhout",
    "sg:classifiers":[
        {
            "category":"Cafe",
            "type":"Food & Drink"
        }
    ],
    "sg:phone":"+32 52 34 02 86",
    "sg:postcode":"9255",
    "sg:province":"Oost-Vlaanderen",
    "sg:tags":[
        "caf\u00e9s"
    ],
    "wof:name":"Daisy Wauters",
    "wof:placetype":"venue"
},
  "geometry": {"coordinates":[4.182600975,51.0290298462],"type":"Point"}
}