{
  "type": "Feature",
  "properties": {
    "iso:country":"BE",
    "sg:address":"Heilig-kruisplein 25",
    "sg:city":"Gent",
    "sg:orig_category":"ACCOUNTANTS Boekhouders",
    "sg:phone":"+32 9 238 30 69",
    "sg:postcode":"9040",
    "sg:province":"Oost-Vlaanderen",
    "wof:name":"Patrick Staelraeve",
    "wof:placetype":"venue"
},
  "geometry": {"coordinates":[3.770359993,51.0647506714],"type":"Point"}
}