{
  "type": "Feature",
  "properties": {
    "iso:country":"BE",
    "sg:address":"Begijnenstraat 40b6",
    "sg:city":"Turnhout",
    "sg:classifiers":[
        {
            "category":"Building & Trades",
            "subcategory":"Landscaping Services",
            "type":"Services"
        }
    ],
    "sg:phone":"+32 14 41 58 76",
    "sg:postcode":"2300",
    "sg:province":"Antwerpen",
    "sg:tags":[
        "etude",
        "technique",
        "ing\u00e9nierie"
    ],
    "wof:name":"Baeten Studie & Adviesbureau",
    "wof:placetype":"venue"
},
  "geometry": {"coordinates":[4.942855835,51.3279953003],"type":"Point"}
}