{
  "type": "Feature",
  "properties": {
    "iso:country":"BE",
    "sg:address":"Rue Des Basjaunes 23a",
    "sg:city":"Court-saint-etienne",
    "sg:classifiers":[
        {
            "category":"Personal",
            "subcategory":"Beauty Salon",
            "type":"Services"
        }
    ],
    "sg:phone":"+32 10 61 56 40",
    "sg:postcode":"1490",
    "sg:province":"Brabant Wallon",
    "sg:tags":[
        "lady",
        "-",
        "hairdressing"
    ],
    "wof:name":"Myriam",
    "wof:placetype":"venue"
},
  "geometry": {"coordinates":[4.5630288124,50.6230278015],"type":"Point"}
}