{
  "type": "Feature",
  "properties": {
    "iso:country":"BE",
    "sg:address":"Rue Du Moulin 53",
    "sg:city":"Montigny-le-tilleul",
    "sg:orig_category":"Paramedische behandelingen",
    "sg:phone":"+32 71 51 01 91",
    "sg:postcode":"6110",
    "sg:province":"Hainaut",
    "wof:name":"D. Van Roosbroeck",
    "wof:placetype":"venue"
},
  "geometry": {"coordinates":[4.3884968758,50.3756141663],"type":"Point"}
}