{
  "type": "Feature",
  "properties": {
    "addr:full":"Avenue Du Roi Albert 11 Sint-agatha-berchem/berchem-sainte-agathe Bruxelles-Capitale 1082",
    "addr:housenumber":"11",
    "addr:postcode":"1082",
    "addr:street":"Avenue Du Roi Albert",
    "iso:country":"BE",
    "sg:address":"Avenue Du Roi Albert 11",
    "sg:city":"Sint-agatha-berchem/berchem-sainte-agathe",
    "sg:orig_category":"Cr\u00e9dits divers",
    "sg:postcode":"1082",
    "sg:province":"Bruxelles-Capitale",
    "wof:name":"Bancontact-mister Cash",
    "wof:placetype":"venue"
},
  "geometry": {"coordinates":[4.2957677841,50.864566803],"type":"Point"}
}