{
  "type": "Feature",
  "properties": {
    "iso:country":"BE",
    "sg:address":"Parc Du Bois De Mons 48",
    "sg:city":"Mons",
    "sg:orig_category":"Architectes",
    "sg:phone":"+32 65 35 58 83",
    "sg:postcode":"7000",
    "sg:province":"Hainaut",
    "wof:name":"Dimitri Pillon",
    "wof:placetype":"venue"
},
  "geometry": {"coordinates":[3.9866950512,50.447303772],"type":"Point"}
}