{
  "type": "Feature",
  "properties": {
    "iso:country":"BE",
    "sg:address":"Route De Liers 4-6",
    "sg:city":"Herstal (milmort)",
    "sg:classifiers":[
        {
            "category":"Home & Garden",
            "subcategory":"Building Materials",
            "type":"Retail Goods"
        }
    ],
    "sg:phone":"+32 4 278 73 25",
    "sg:postcode":"4041",
    "sg:province":"Li\u00e8ge",
    "sg:tags":[
        "granite",
        "stone",
        "natural",
        "marble"
    ],
    "wof:name":"Van Dijck Sa",
    "wof:placetype":"venue"
},
  "geometry": {"coordinates":[5.5866789818,50.6886177063],"type":"Point"}
}