{
  "type": "Feature",
  "properties": {
    "addr:full":"Grote Baan 62 Houthalen-helchteren Limburg 3530",
    "addr:housenumber":"62",
    "addr:postcode":"3530",
    "addr:street":"Grote Baan",
    "iso:country":"BE",
    "sg:address":"Grote Baan 62",
    "sg:city":"Houthalen-helchteren",
    "sg:orig_category":"MEUBELONTWERP AND -INSTALLATIE",
    "sg:phone":"+32 11 60 16 64",
    "sg:postcode":"3530",
    "sg:province":"Limburg",
    "wof:name":"Keukens Dea Plus",
    "wof:placetype":"venue"
},
  "geometry": {"coordinates":[5.3755588531,51.0263938904],"type":"Point"}
}