{
  "type": "Feature",
  "properties": {
    "addr:full":"Rue Du Labyrinthe 234 Moeskroen/mouscron Hainaut 7700",
    "addr:housenumber":"234",
    "addr:postcode":"7700",
    "addr:street":"Rue Du Labyrinthe",
    "iso:country":"BE",
    "sg:address":"Rue Du Labyrinthe 234",
    "sg:city":"Moeskroen/mouscron",
    "sg:orig_category":"Rev\u00eatements pour sols and murs",
    "sg:phone":"+32 56 84 44 53",
    "sg:postcode":"7700",
    "sg:province":"Hainaut",
    "wof:name":"Daniel Debue",
    "wof:placetype":"venue"
},
  "geometry": {"coordinates":[3.2323200703,50.7400932312],"type":"Point"}
}