{
  "type": "Feature",
  "properties": {
    "iso:country":"BE",
    "sg:address":"Quai Des Usines 2211g",
    "sg:city":"Bruxelles",
    "sg:classifiers":[
        {
            "category":"Freight",
            "type":"Transportation"
        }
    ],
    "sg:phone":"+32 2 241 39 37",
    "sg:postcode":"1000",
    "sg:province":"Bruxelles-Capitale",
    "sg:tags":[
        "-",
        "refrigerated",
        "transport"
    ],
    "wof:name":"Bms",
    "wof:placetype":"venue"
},
  "geometry": {"coordinates":[4.362830162,50.8747291565],"type":"Point"}
}