{
  "type": "Feature",
  "properties": {
    "addr:full":"Vlamingstraat 13 Oostkamp West-Vlaanderen 8020",
    "addr:housenumber":"13",
    "addr:postcode":"8020",
    "addr:street":"Vlamingstraat",
    "iso:country":"BE",
    "sg:address":"Vlamingstraat 13",
    "sg:city":"Oostkamp",
    "sg:orig_category":"Installation de menuiserie en bois and plastique",
    "sg:phone":"+32 50 27 56 18",
    "sg:postcode":"8020",
    "sg:province":"West-Vlaanderen",
    "wof:name":"Riemaeker",
    "wof:placetype":"venue"
},
  "geometry": {"coordinates":[3.207928896,51.0955238342],"type":"Point"}
}