{
  "type": "Feature",
  "properties": {
    "iso:country":"BE",
    "sg:address":"Avenue De Jette 226",
    "sg:city":"Bruxelles (jette)",
    "sg:classifiers":[
        {
            "category":"Personal",
            "subcategory":"Barber",
            "type":"Services"
        }
    ],
    "sg:phone":"+32 2 420 44 49",
    "sg:postcode":"1090",
    "sg:province":"Bruxelles-Capitale",
    "sg:tags":[
        "gentleman",
        "salon",
        "-",
        "hairdressing"
    ],
    "wof:name":"Cr\u00e9ation Haute Coiffure",
    "wof:placetype":"venue"
},
  "geometry": {"coordinates":[4.3251729012,50.8705711365],"type":"Point"}
}