{
  "type": "Feature",
  "properties": {
    "iso:country":"BE",
    "sg:address":"Wildstraat 8",
    "sg:city":"Mol",
    "sg:classifiers":[
        {
            "category":"Arena",
            "subcategory":"Sports Club",
            "type":"Entertainment"
        }
    ],
    "sg:phone":"+32 14 31 26 57",
    "sg:postcode":"2400",
    "sg:province":"Antwerpen",
    "sg:tags":[
        "terrain",
        "hors",
        "de",
        "installation",
        "sportifs"
    ],
    "wof:name":"G.s.k '70",
    "wof:placetype":"venue"
},
  "geometry": {"coordinates":[5.1502890587,51.1904411316],"type":"Point"}
}