{
  "type": "Feature",
  "properties": {
    "addr:full":"Rue Des Pens\u00c9es 1-5 Brussel/bruxelles Bruxelles-Capitale 1030",
    "addr:housenumber":"1-5",
    "addr:postcode":"1030",
    "addr:street":"Rue Des Pense\u0301Es;/",
    "iso:country":"BE",
    "sg:address":"Rue Des Pens\u00c9es 1-5",
    "sg:city":"Brussel/bruxelles",
    "sg:orig_category":"Cliniques and h\u00f4pitaux",
    "sg:phone":"+32 2 240 60 60",
    "sg:postcode":"1030",
    "sg:province":"Bruxelles-Capitale",
    "wof:name":"Centre M\u00c9dical Europe-lambermont",
    "wof:placetype":"venue"
},
  "geometry": {"coordinates":[4.390253067,50.8617706299],"type":"Point"}
}