{
  "type": "Feature",
  "properties": {
    "iso:country":"BE",
    "sg:address":"Maraillestraat 50",
    "sg:city":"Avelgem (outrijve)",
    "sg:classifiers":[
        {
            "category":"Professional",
            "subcategory":"Art Services",
            "type":"Services"
        }
    ],
    "sg:phone":"+32 56 64 96 49",
    "sg:postcode":"8582",
    "sg:province":"West-Vlaanderen",
    "sg:tags":[
        "-",
        "painter",
        "artist"
    ],
    "wof:name":"Adelbert",
    "wof:placetype":"venue"
},
  "geometry": {"coordinates":[3.4170451164,50.7592430115],"type":"Point"}
}