{
  "type": "Feature",
  "properties": {
    "iso:country":"BE",
    "sg:address":"Grotenbergestraat 19",
    "sg:city":"Zottegem",
    "sg:classifiers":[
        {
            "category":"Professional",
            "subcategory":"Lawyer & Legal Services",
            "type":"Services"
        }
    ],
    "sg:phone":"+32 9 361 26 34",
    "sg:postcode":"9620",
    "sg:province":"Oost-Vlaanderen",
    "wof:name":"Vander Kimpen Marc",
    "wof:placetype":"venue"
},
  "geometry": {"coordinates":[3.8165550232,50.8719139099],"type":"Point"}
}