{
  "type": "Feature",
  "properties": {
    "addr:full":"Rue De Tohogne 4c Durbuy (bomal-sur-ourthe) Luxembourg 6941",
    "addr:housenumber":"4c",
    "addr:postcode":"6941",
    "addr:street":"Rue De Tohogne",
    "iso:country":"BE",
    "sg:address":"Rue De Tohogne 4c",
    "sg:city":"Durbuy (bomal-sur-ourthe)",
    "sg:classifiers":[
        {
            "category":"Health Services",
            "subcategory":"Health Practitioner",
            "type":"Services"
        }
    ],
    "sg:phone":"+32 86 21 81 92",
    "sg:postcode":"6941",
    "sg:province":"Luxembourg",
    "sg:tags":[
        "physiotherapist"
    ],
    "wof:name":"Bonjean St\u00e9phane",
    "wof:placetype":"venue"
},
  "geometry": {"coordinates":[5.524184227,50.3770332336],"type":"Point"}
}