{
  "type": "Feature",
  "properties": {
    "iso:country":"BE",
    "sg:address":"Rue Walth\u00c8re Jamar 79",
    "sg:city":"Ans",
    "sg:orig_category":"Advocaten and juridische adviseurs",
    "sg:phone":"+32 4 224 00 30",
    "sg:postcode":"4430",
    "sg:province":"Li\u00e8ge",
    "wof:name":"Abdennacer Talha",
    "wof:placetype":"venue"
},
  "geometry": {"coordinates":[5.543035984,50.6514205933],"type":"Point"}
}