{
  "type": "Feature",
  "properties": {
    "addr:full":"Torhoutse Steenweg 16ba Brugge West-Vlaanderen 8200",
    "addr:housenumber":"16ba",
    "addr:postcode":"8200",
    "addr:street":"Torhoutse Steenweg",
    "iso:country":"BE",
    "sg:address":"Torhoutse Steenweg 16ba",
    "sg:city":"Brugge",
    "sg:orig_category":"Verplichte sociale verzekeringen",
    "sg:phone":"+32 50 38 98 45",
    "sg:postcode":"8200",
    "sg:province":"West-Vlaanderen",
    "wof:name":"Onafhankelijk Ziekenfonds",
    "wof:placetype":"venue"
},
  "geometry": {"coordinates":[3.2081398964,51.2034912109],"type":"Point"}
}