{
  "type": "Feature",
  "properties": {
    "iso:country":"BE",
    "sg:address":"Handelsstraat 72",
    "sg:city":"Londerzeel",
    "sg:classifiers":[
        {
            "category":"Personal",
            "subcategory":"Beauty Salon",
            "type":"Services"
        }
    ],
    "sg:phone":"+32 52 33 45 04",
    "sg:postcode":"1840",
    "sg:province":"Vlaams-Brabant",
    "sg:tags":[
        "de",
        "coiffure"
    ],
    "wof:name":"Myriam Cnapelinckx",
    "wof:placetype":"venue"
},
  "geometry": {"coordinates":[4.2342228889,51.0151901245],"type":"Point"}
}