{
  "type": "Feature",
  "properties": {
    "addr:full":"Rue Des Martyrs 42 Jurbise Hainaut 7050",
    "addr:housenumber":"42",
    "addr:postcode":"7050",
    "addr:street":"Rue Des Martyrs",
    "iso:country":"BE",
    "sg:address":"Rue Des Martyrs 42",
    "sg:city":"Jurbise",
    "sg:classifiers":[
        {
            "category":"Farming",
            "subcategory":"Fish & Marine Products",
            "type":"Manufacturing & Wholesale Goods"
        }
    ],
    "sg:phone":"+32 65 22 93 18",
    "sg:postcode":"7050",
    "sg:province":"Hainaut",
    "sg:tags":[
        "equipment",
        "fishery"
    ],
    "wof:name":"Etangs Dessilly",
    "wof:placetype":"venue"
},
  "geometry": {"coordinates":[3.9160919189,50.5327835083],"type":"Point"}
}