{
  "type": "Feature",
  "properties": {
    "addr:full":"Vrijdagmarkt 16 Brugge West-Vlaanderen 8000",
    "addr:housenumber":"16",
    "addr:postcode":"8000",
    "addr:street":"Vrijdagmarkt",
    "iso:country":"BE",
    "sg:address":"Vrijdagmarkt 16",
    "sg:city":"Brugge",
    "sg:classifiers":[
        {
            "category":"Restaurant",
            "type":"Food & Drink"
        }
    ],
    "sg:phone":"+32 50 33 59 60",
    "sg:postcode":"8000",
    "sg:province":"West-Vlaanderen",
    "sg:tags":[
        "caf\u00e9s"
    ],
    "wof:name":"Caf\u00c9 Paradoks",
    "wof:placetype":"venue"
},
  "geometry": {"coordinates":[3.216643095,51.2055091858],"type":"Point"}
}