{
  "type": "Feature",
  "properties": {
    "iso:country":"BE",
    "sg:address":"Canadalaan 35",
    "sg:city":"Stabroek",
    "sg:classifiers":[
        {
            "category":"Arena",
            "subcategory":"Sports Club",
            "type":"Entertainment"
        }
    ],
    "sg:phone":"+32 3 664 89 72",
    "sg:postcode":"2940",
    "sg:province":"Antwerpen",
    "sg:tags":[
        "de"
    ],
    "wof:name":"A.c. Kapellen",
    "wof:placetype":"venue"
},
  "geometry": {"coordinates":[4.3904819489,51.3552246094],"type":"Point"}
}