{
  "type": "Feature",
  "properties": {
    "addr:full":"Bondgenotenlaan 60 Leuven Vlaams-Brabant 3000",
    "addr:housenumber":"60",
    "addr:postcode":"3000",
    "addr:street":"Bondgenotenlaan",
    "iso:country":"BE",
    "sg:address":"Bondgenotenlaan 60",
    "sg:city":"Leuven",
    "sg:classifiers":[
        {
            "category":"Bars & Pubs",
            "type":"Food & Drink"
        }
    ],
    "sg:phone":"+32 16 22 58 47",
    "sg:postcode":"3000",
    "sg:province":"Vlaams-Brabant",
    "wof:name":"De Ton",
    "wof:placetype":"venue"
},
  "geometry": {"coordinates":[4.7076392174,50.8798866272],"type":"Point"}
}