{
  "type": "Feature",
  "properties": {
    "iso:country":"BE",
    "sg:address":"9",
    "sg:city":"Kapellekensweg 3391 Tielt-winge",
    "sg:classifiers":[
        {
            "category":"Manufacturing",
            "subcategory":"Chemicals & Compounds",
            "type":"Manufacturing & Wholesale Goods"
        }
    ],
    "sg:phone":"+32 16 63 99 00",
    "sg:postcode":"9",
    "sg:tags":[
        "pharmaceutical",
        "chemistry",
        "-",
        "by-product"
    ],
    "wof:name":"Cappelle Nv",
    "wof:placetype":"venue"
},
  "geometry": {"coordinates":[4.9184150696,50.8969993591],"type":"Point"}
}