{
  "type": "Feature",
  "properties": {
    "iso:country":"BE",
    "sg:address":"Rue Du G\u00e9n\u00e9ral De Gaulle 122",
    "sg:city":"Courcelles",
    "sg:classifiers":[
        {
            "category":"Shopping",
            "subcategory":"Pets & Pet Supplies",
            "type":"Retail Goods"
        }
    ],
    "sg:phone":"+32 71 46 42 12",
    "sg:postcode":"6180",
    "sg:province":"Hainaut",
    "sg:tags":[
        "aquarium",
        "accessory"
    ],
    "wof:name":"Aqua'nimals Sprl",
    "wof:placetype":"venue"
},
  "geometry": {"coordinates":[4.380833149,50.4565353394],"type":"Point"}
}