{
  "type": "Feature",
  "properties": {
    "addr:full":"Oude Geldenaaksebaan 6 Bierbeek Vlaams-Brabant 3360",
    "addr:housenumber":"6",
    "addr:postcode":"3360",
    "addr:street":"Oude Geldenaaksebaan",
    "iso:country":"BE",
    "sg:address":"Oude Geldenaaksebaan 6",
    "sg:city":"Bierbeek",
    "sg:classifiers":[
        {
            "category":"Retail",
            "subcategory":"Auto Repair",
            "type":"Services"
        }
    ],
    "sg:phone":"+32 16 46 03 46",
    "sg:postcode":"3360",
    "sg:province":"Vlaams-Brabant",
    "sg:tags":[
        "garage"
    ],
    "wof:name":"Tollet W",
    "wof:placetype":"venue"
},
  "geometry": {"coordinates":[4.7444791794,50.8288917542],"type":"Point"}
}