{
  "type": "Feature",
  "properties": {
    "iso:country":"BE",
    "sg:address":"Tussen Tweebroek 60",
    "sg:city":"Tongeren",
    "sg:orig_category":"Varkenskwekers",
    "sg:phone":"+32 12 23 89 99",
    "sg:postcode":"3700",
    "sg:province":"Limburg",
    "wof:name":"Jean-paul Mouha",
    "wof:placetype":"venue"
},
  "geometry": {"coordinates":[5.4803748131,50.7614212036],"type":"Point"}
}