{
  "type": "Feature",
  "properties": {
    "iso:country":"BE",
    "sg:address":"Bellevue 4",
    "sg:city":"Gent",
    "sg:orig_category":"Marketingbureaus Marktonderzoekbureaus",
    "sg:phone":"+32 9 210 53 53",
    "sg:postcode":"9050",
    "sg:province":"Oost-Vlaanderen",
    "wof:name":"Bureau Colombus",
    "wof:placetype":"venue"
},
  "geometry": {"coordinates":[3.7358438969,51.0349769592],"type":"Point"}
}