{
  "type": "Feature",
  "properties": {
    "addr:full":"Avenue Des Vignes 6 Namur (belgrade) Namur 5001",
    "addr:housenumber":"6",
    "addr:postcode":"5001",
    "addr:street":"Avenue Des Vignes",
    "iso:country":"BE",
    "sg:address":"Avenue Des Vignes 6",
    "sg:city":"Namur (belgrade)",
    "sg:classifiers":[
        {
            "category":"Professional",
            "subcategory":"Accounting & Tax Preparation",
            "type":"Services"
        }
    ],
    "sg:phone":"+32 81 58 39 84",
    "sg:postcode":"5001",
    "sg:province":"Namur",
    "sg:tags":[
        "accountant"
    ],
    "wof:name":"Stampetta D",
    "wof:placetype":"venue"
},
  "geometry": {"coordinates":[4.8257050514,50.4722557068],"type":"Point"}
}