{
  "type": "Feature",
  "properties": {
    "addr:full":"Mechelsesteenweg 225 Zaventem (sterrebeek) Vlaams-Brabant 1933",
    "addr:housenumber":"225",
    "addr:postcode":"1933",
    "addr:street":"Mechelsesteenweg",
    "iso:country":"BE",
    "sg:address":"Mechelsesteenweg 225",
    "sg:city":"Zaventem (sterrebeek)",
    "sg:classifiers":[
        {
            "category":"Professional",
            "subcategory":"Testing Lab",
            "type":"Services"
        }
    ],
    "sg:phone":"+32 2 731 23 66",
    "sg:postcode":"1933",
    "sg:province":"Vlaams-Brabant",
    "sg:tags":[
        "chemist"
    ],
    "wof:name":"De Coster A",
    "wof:placetype":"venue"
},
  "geometry": {"coordinates":[4.5152769089,50.8622779846],"type":"Point"}
}