{
  "type": "Feature",
  "properties": {
    "addr:full":"Veeweidestraat 19 Tervuren (duisburg) Vlaams-Brabant 3080",
    "addr:housenumber":"19",
    "addr:postcode":"3080",
    "addr:street":"Veeweidestraat",
    "iso:country":"BE",
    "sg:address":"Veeweidestraat 19",
    "sg:city":"Tervuren (duisburg)",
    "sg:classifiers":[
        {
            "category":"Building & Trades",
            "subcategory":"Landscaping Services",
            "type":"Services"
        }
    ],
    "sg:phone":"+32 2 767 87 30",
    "sg:postcode":"3080",
    "sg:province":"Vlaams-Brabant",
    "sg:tags":[
        "gardening",
        "garden",
        "maintenance"
    ],
    "wof:name":"Lecart Garden Architecture",
    "wof:placetype":"venue"
},
  "geometry": {"coordinates":[4.5618739128,50.8178901672],"type":"Point"}
}