{
  "type": "Feature",
  "properties": {
    "addr:full":"Kasteellaan 92 Moeskroen/mouscron Hainaut 7700",
    "addr:housenumber":"92",
    "addr:postcode":"7700",
    "addr:street":"Kasteellaan",
    "iso:country":"BE",
    "sg:address":"Kasteellaan 92",
    "sg:city":"Moeskroen/mouscron",
    "sg:orig_category":"Aanleg van wegen, sportterreinen and vliegvelden Loodgieterij, verwarming and sanitaire installaties",
    "sg:phone":"+32 56 33 25 70",
    "sg:postcode":"7700",
    "sg:province":"Hainaut",
    "wof:name":"T.p.m.",
    "wof:placetype":"venue"
},
  "geometry": {"coordinates":[3.2323200703,50.7400932312],"type":"Point"}
}