{
  "type": "Feature",
  "properties": {
    "iso:country":"BE",
    "sg:address":"Retiesebaan 1",
    "sg:city":"Kasterlee",
    "sg:classifiers":[
        {
            "category":"Travel",
            "subcategory":"Travel Agent",
            "type":"Entertainment"
        }
    ],
    "sg:phone":"+32 14 85 07 42",
    "sg:postcode":"2460",
    "sg:province":"Antwerpen",
    "sg:tags":[
        "voyage",
        "de",
        "agences",
        "flash",
        "holidays",
        "plus"
    ],
    "wof:name":"Boschmans Reizen",
    "wof:placetype":"venue"
},
  "geometry": {"coordinates":[4.9695401192,51.2410087585],"type":"Point"}
}