{
  "type": "Feature",
  "properties": {
    "iso:country":"BE",
    "sg:address":"Essenhoutstraat 168",
    "sg:city":"Kapellen",
    "sg:orig_category":"Diverse bouwafwerking and reiniging Plaatsen van vloer- and muurbekleding Schilders",
    "sg:phone":"+32 3 605 37 63",
    "sg:postcode":"2950",
    "sg:province":"Antwerpen",
    "wof:name":"Van Den Berghe",
    "wof:placetype":"venue"
},
  "geometry": {"coordinates":[4.421090126,51.3105506897],"type":"Point"}
}