{
  "type": "Feature",
  "properties": {
    "iso:country":"BE",
    "sg:address":"Vredestraat 105",
    "sg:city":"Hasselt",
    "sg:orig_category":"Artsen and specialisten",
    "sg:phone":"+32 11 27 59 36",
    "sg:postcode":"3500",
    "sg:province":"Limburg",
    "wof:name":"Luc Vanderbruggen",
    "wof:placetype":"venue"
},
  "geometry": {"coordinates":[5.3217358589,50.9255905151],"type":"Point"}
}