{
  "type": "Feature",
  "properties": {
    "addr:full":"Rue De La Gare 33 Seraing (ougr\u00e9e) Li\u00e8ge 4102",
    "addr:housenumber":"33",
    "addr:postcode":"4102",
    "addr:street":"Rue De La Gare",
    "iso:country":"BE",
    "sg:address":"Rue De La Gare 33",
    "sg:city":"Seraing (ougr\u00e9e)",
    "sg:classifiers":[
        {
            "category":"Banks & Credit Unions",
            "subcategory":"Bank",
            "type":"Services"
        }
    ],
    "sg:phone":"+32 4 337 06 08",
    "sg:postcode":"4102",
    "sg:province":"Li\u00e8ge",
    "sg:tags":[
        "savings-banks"
    ],
    "wof:name":"Banque Alimentaire Vzw",
    "wof:placetype":"venue"
},
  "geometry": {"coordinates":[5.5359277725,50.6070632935],"type":"Point"}
}