{
  "type": "Feature",
  "properties": {
    "addr:full":"Boulevard Adolphe Max 64 Bruxelles Bruxelles-Capitale 1000",
    "addr:housenumber":"64",
    "addr:postcode":"1000",
    "addr:street":"Boulevard Adolphe Max",
    "iso:country":"BE",
    "sg:address":"Boulevard Adolphe Max 64",
    "sg:city":"Bruxelles",
    "sg:classifiers":[
        {
            "category":"Shopping",
            "subcategory":"Discount & Variety Stores",
            "type":"Retail Goods"
        }
    ],
    "sg:phone":"+32 2 217 67 43",
    "sg:postcode":"1000",
    "sg:province":"Bruxelles-Capitale",
    "sg:tags":[
        "shop",
        "night"
    ],
    "wof:name":"City Shop",
    "wof:placetype":"venue"
},
  "geometry": {"coordinates":[4.3549661636,50.8533058167],"type":"Point"}
}