{
  "type": "Feature",
  "properties": {
    "addr:full":"Rue De L'enclos Saint-martin Tournai Hainaut 7500",
    "addr:postcode":"7500",
    "addr:street":"Rue De L'Enclos",
    "iso:country":"BE",
    "sg:address":"Rue De L'enclos Saint-martin",
    "sg:city":"Tournai",
    "sg:classifiers":[
        {
            "category":"Museum",
            "type":"Entertainment"
        }
    ],
    "sg:phone":"+32 69 22 20 43",
    "sg:postcode":"7500",
    "sg:province":"Hainaut",
    "wof:name":"Mus\u00e9e Des Beaux-arts De Tournai",
    "wof:placetype":"venue"
},
  "geometry": {"coordinates":[3.3855559826,50.602973938],"type":"Point"}
}