{
  "type": "Feature",
  "properties": {
    "addr:full":"Industrieweg 3 Aartselaar Antwerpen 2630",
    "addr:housenumber":"3",
    "addr:postcode":"2630",
    "addr:street":"Industrieweg",
    "iso:country":"BE",
    "sg:address":"Industrieweg 3",
    "sg:city":"Aartselaar",
    "sg:classifiers":[
        {
            "category":"Food & Beverages",
            "subcategory":"Groceries & Convenience Stores",
            "type":"Retail Goods"
        }
    ],
    "sg:phone":"+32 3 870 70 10",
    "sg:postcode":"2630",
    "sg:province":"Antwerpen",
    "sg:tags":[
        "machine",
        "industry",
        "blade",
        "knife"
    ],
    "wof:name":"Stumabo International Nv",
    "wof:placetype":"venue"
},
  "geometry": {"coordinates":[4.3705129623,51.1318016052],"type":"Point"}
}