{
  "type": "Feature",
  "properties": {
    "iso:country":"BE",
    "sg:address":"Chemin De L'hermitage 7",
    "sg:city":"Pepinster",
    "sg:classifiers":[
        {
            "category":"Health Services",
            "subcategory":"Health Practitioner",
            "type":"Services"
        }
    ],
    "sg:phone":"+32 87 46 07 12",
    "sg:postcode":"4860",
    "sg:province":"Li\u00e8ge",
    "sg:tags":[
        "physiotherapist"
    ],
    "wof:name":"Lekeu Isabelle",
    "wof:placetype":"venue"
},
  "geometry": {"coordinates":[5.8041992188,50.5545158386],"type":"Point"}
}