{
  "type": "Feature",
  "properties": {
    "iso:country":"BE",
    "sg:address":"Stationsstraat 106",
    "sg:city":"Rhode-saint-gen\u00e8se",
    "sg:classifiers":[
        {
            "category":"Building & Trades",
            "subcategory":"Pest Control",
            "type":"Services"
        }
    ],
    "sg:phone":"+32 2 380 60 50",
    "sg:postcode":"1640",
    "sg:province":"Vlaams-Brabant",
    "sg:tags":[
        "inventory",
        "invoicing",
        "system"
    ],
    "wof:name":"Ets. E. Absalon S.a.",
    "wof:placetype":"venue"
},
  "geometry": {"coordinates":[4.3568878174,50.7494277954],"type":"Point"}
}