{
  "type": "Feature",
  "properties": {
    "iso:country":"BE",
    "sg:address":"Waterloosesteenweg",
    "sg:city":"Bruxelles",
    "sg:classifiers":[
        {
            "category":"Bars & Pubs",
            "type":"Food & Drink"
        }
    ],
    "sg:phone":"+32 475 46 71 16",
    "sg:postcode":"1060",
    "sg:province":"Bruxelles-Capitale",
    "sg:tags":[
        "restaurant"
    ],
    "wof:name":"Moda-moda",
    "wof:placetype":"venue"
},
  "geometry": {"coordinates":[4.3445949554,50.8307991028],"type":"Point"}
}