{
  "type": "Feature",
  "properties": {
    "addr:full":"Gravenstraat 4a Assenede (bassevelde) Oost-Vlaanderen 9968",
    "addr:housenumber":"4a",
    "addr:postcode":"9968",
    "addr:street":"Gravenstraat",
    "iso:country":"BE",
    "sg:address":"Gravenstraat 4a",
    "sg:city":"Assenede (bassevelde)",
    "sg:classifiers":[
        {
            "category":"Animal Shelter",
            "type":"Public Place"
        }
    ],
    "sg:phone":"+32 9 373 51 71",
    "sg:postcode":"9968",
    "sg:province":"Oost-Vlaanderen",
    "sg:tags":[
        "construction",
        "installation",
        "stable"
    ],
    "wof:name":"Depaco Bouwbedrijf",
    "wof:placetype":"venue"
},
  "geometry": {"coordinates":[3.640196085,51.2517852783],"type":"Point"}
}