{
  "type": "Feature",
  "properties": {
    "addr:full":"Rue Saint-l\u00c9onard 95 Li\u00c8ge Li\u00e8ge 4000",
    "addr:housenumber":"95",
    "addr:postcode":"4000",
    "addr:street":"Rue Saint-Le\u0301Onard",
    "iso:country":"BE",
    "sg:address":"Rue Saint-l\u00c9onard 95",
    "sg:city":"Li\u00c8ge",
    "sg:classifiers":[
        {
            "category":"Restaurant",
            "type":"Food & Drink"
        }
    ],
    "sg:phone":"+32 4 227 41 18",
    "sg:postcode":"4000",
    "sg:province":"Li\u00e8ge",
    "wof:name":"Restaurant Le Finist\u00c8re",
    "wof:placetype":"venue"
},
  "geometry": {"coordinates":[5.5897707939,50.6490516663],"type":"Point"}
}