{
  "type": "Feature",
  "properties": {
    "iso:country":"BE",
    "sg:address":"Gentse Steenweg 115bb",
    "sg:city":"Lokeren",
    "sg:orig_category":"Assistances juridiques",
    "sg:phone":"+32 9 348 99 48",
    "sg:postcode":"9160",
    "sg:province":"Oost-Vlaanderen",
    "wof:name":"De Veiling",
    "wof:placetype":"venue"
},
  "geometry": {"coordinates":[3.9510440826,51.114780426],"type":"Point"}
}