{
  "type": "Feature",
  "properties": {
    "iso:country":"BE",
    "sg:address":"Rue De La Care 46",
    "sg:city":"Meix-devant-virton",
    "sg:orig_category":"Installatie van houten of kunststof schrijnwerk",
    "sg:phone":"+32 63 57 87 28",
    "sg:postcode":"6769",
    "sg:province":"Luxembourg",
    "wof:name":"Somebat",
    "wof:placetype":"venue"
},
  "geometry": {"coordinates":[5.4800958633,49.6040344238],"type":"Point"}
}