{
  "type": "Feature",
  "properties": {
    "iso:country":"BE",
    "sg:address":"R De Herbesthal",
    "sg:city":"Eupen",
    "sg:orig_category":"Eclairage et \u00e9quipements du foyer",
    "sg:phone":"+32 87 56 03 39",
    "sg:postcode":"4700",
    "sg:province":"Li\u00e8ge",
    "wof:name":"Home Market",
    "wof:placetype":"venue"
},
  "geometry": {"coordinates":[6.0205597878,50.6365661621],"type":"Point"}
}