{
  "type": "Feature",
  "properties": {
    "iso:country":"BE",
    "sg:address":"Kastanjelaan 22",
    "sg:city":"Harelbeke",
    "sg:classifiers":[
        {
            "category":"Arena",
            "subcategory":"Sports Club",
            "type":"Entertainment"
        }
    ],
    "sg:phone":"+32 56 71 58 20",
    "sg:postcode":"8530",
    "sg:province":"West-Vlaanderen",
    "sg:tags":[
        "terrain",
        "hors",
        "de",
        "installation",
        "sportifs"
    ],
    "wof:name":"V.c.o.g. Stasegem",
    "wof:placetype":"venue"
},
  "geometry": {"coordinates":[3.3029079437,50.8412704468],"type":"Point"}
}