{
  "type": "Feature",
  "properties": {
    "iso:country":"BE",
    "sg:address":"Rathausplatz 2",
    "sg:city":"Eupen/eupen",
    "sg:orig_category":"Herstellingswinkels voor diverse persoonlijke and huishoudartikelen",
    "sg:phone":"+32 87 74 49 78",
    "sg:postcode":"4700",
    "sg:province":"Li\u00e8ge",
    "wof:name":"Alternative G.o.e.",
    "wof:placetype":"venue"
},
  "geometry": {"coordinates":[6.0291371346,50.6317214966],"type":"Point"}
}