{
  "type": "Feature",
  "properties": {
    "iso:country":"BE",
    "sg:address":"Rijksweg 249b3",
    "sg:city":"Maasmechelen",
    "sg:orig_category":"Agents artistiques",
    "sg:phone":"+32 89 77 29 54",
    "sg:postcode":"3630",
    "sg:province":"Limburg",
    "wof:name":"Big-o Promotions En Ijdeltuit",
    "wof:placetype":"venue"
},
  "geometry": {"coordinates":[5.6988921165,50.9733581543],"type":"Point"}
}