{
  "type": "Feature",
  "properties": {
    "addr:full":"Kapucinessenstraat 9 Antwerpen Antwerpen 2000",
    "addr:housenumber":"9",
    "addr:postcode":"2000",
    "addr:street":"Kapucinessenstraat",
    "iso:country":"BE",
    "sg:address":"Kapucinessenstraat 9",
    "sg:city":"Antwerpen",
    "sg:classifiers":[
        {
            "category":"Wholesale",
            "subcategory":"Wine & Distilled Alcoholic Beverages",
            "type":"Manufacturing & Wholesale Goods"
        }
    ],
    "sg:phone":"+32 3 231 10 98",
    "sg:postcode":"2000",
    "sg:province":"Antwerpen",
    "sg:tags":[
        "whol",
        "-",
        "spirit",
        "mfg"
    ],
    "wof:name":"Vinoherck Nv",
    "wof:placetype":"venue"
},
  "geometry": {"coordinates":[4.4040632248,51.2116546631],"type":"Point"}
}