{
  "type": "Feature",
  "properties": {
    "iso:country":"BE",
    "sg:address":"Brasschaatsteenweg 318",
    "sg:city":"Kalmthout",
    "sg:classifiers":[
        {
            "category":"Food & Beverages",
            "subcategory":"Groceries & Convenience Stores",
            "type":"Retail Goods"
        }
    ],
    "sg:phone":"+32 3 666 74 36",
    "sg:postcode":"2920",
    "sg:province":"Antwerpen",
    "sg:tags":[
        "product",
        "related"
    ],
    "wof:name":"Wycams Produkten Nv",
    "wof:placetype":"venue"
},
  "geometry": {"coordinates":[4.5072698593,51.3579711914],"type":"Point"}
}