{
  "type": "Feature",
  "properties": {
    "iso:country":"BE",
    "sg:address":"Place Croix Du Sud 4b5",
    "sg:city":"Ottignies-louvain-la-neuve",
    "sg:orig_category":"Enseignement sup\u00e9rieur",
    "sg:phone":"+32 10 47 34 89",
    "sg:postcode":"1348",
    "sg:province":"Brabant Wallon",
    "wof:name":"U.c.l.-d\u00c9partement Biol",
    "wof:placetype":"venue"
},
  "geometry": {"coordinates":[4.6223249435,50.6668205261],"type":"Point"}
}