{
  "type": "Feature",
  "properties": {
    "iso:country":"BE",
    "sg:address":"Rue De Grand Bry 19",
    "sg:city":"Montigny-le-tilleul",
    "sg:classifiers":[
        {
            "category":"Home & Garden",
            "subcategory":"Building Materials",
            "type":"Retail Goods"
        }
    ],
    "sg:phone":"+32 71 51 94 65",
    "sg:postcode":"6110",
    "sg:province":"Hainaut",
    "sg:tags":[
        "veranda"
    ],
    "wof:name":"Lebailly R",
    "wof:placetype":"venue"
},
  "geometry": {"coordinates":[4.3641610146,50.3649101257],"type":"Point"}
}