{
  "type": "Feature",
  "properties": {
    "addr:full":"Koning Albertstraat 154 Ravels Antwerpen 2381",
    "addr:housenumber":"154",
    "addr:postcode":"2381",
    "addr:street":"Koning Albertstraat",
    "iso:country":"BE",
    "sg:address":"Koning Albertstraat 154",
    "sg:city":"Ravels",
    "sg:classifiers":[
        {
            "category":"Cafe",
            "type":"Food & Drink"
        }
    ],
    "sg:phone":"+32 14 65 88 52",
    "sg:postcode":"2381",
    "sg:province":"Antwerpen",
    "sg:tags":[
        "caf\u00e9s"
    ],
    "wof:name":"De Kroeg",
    "wof:placetype":"venue"
},
  "geometry": {"coordinates":[5.006374836,51.4099845886],"type":"Point"}
}