{
  "type": "Feature",
  "properties": {
    "addr:full":"Kleine Zavel 13 Brussel/bruxelles Bruxelles-Capitale 1000",
    "addr:housenumber":"13",
    "addr:postcode":"1000",
    "addr:street":"Kleine Zavel;/",
    "iso:country":"BE",
    "sg:address":"Kleine Zavel 13",
    "sg:city":"Brussel/bruxelles",
    "sg:orig_category":"Advocaten and juridische adviseurs",
    "sg:phone":"+32 2 512 55 31",
    "sg:postcode":"1000",
    "sg:province":"Bruxelles-Capitale",
    "wof:name":"Marc Poumay/m. Poumay",
    "wof:placetype":"venue"
},
  "geometry": {"coordinates":[4.3562021255,50.8392677307],"type":"Point"}
}