{
  "type": "Feature",
  "properties": {
    "addr:full":"Deurnestraat 166b15 Mortsel Antwerpen 2640",
    "addr:housenumber":"166b15",
    "addr:postcode":"2640",
    "addr:street":"Deurnestraat",
    "iso:country":"BE",
    "sg:address":"Deurnestraat 166b15",
    "sg:city":"Mortsel",
    "sg:orig_category":"Electrom\u00e9nager, t\u00e9l\u00e9visions and radios",
    "sg:phone":"+32 3 230 77 03",
    "sg:postcode":"2640",
    "sg:province":"Antwerpen",
    "wof:name":"Delimex",
    "wof:placetype":"venue"
},
  "geometry": {"coordinates":[4.4463291168,51.179069519],"type":"Point"}
}