{
  "type": "Feature",
  "properties": {
    "addr:full":"Place Reine Astrid 10 Vise Li\u00e8ge 4600",
    "addr:housenumber":"10",
    "addr:postcode":"4600",
    "addr:street":"Place Reine Astrid",
    "iso:country":"BE",
    "sg:address":"Place Reine Astrid 10",
    "sg:city":"Vise",
    "sg:orig_category":"Artsen and specialisten",
    "sg:phone":"+32 4 379 25 17",
    "sg:postcode":"4600",
    "sg:province":"Li\u00e8ge",
    "wof:name":"Genevi\u00c8ve Bruwier",
    "wof:placetype":"venue"
},
  "geometry": {"coordinates":[5.6954259872,50.738079071],"type":"Point"}
}