{
  "type": "Feature",
  "properties": {
    "addr:full":"Grand'place 14 Jodoigne Brabant Wallon 1370",
    "addr:housenumber":"14",
    "addr:postcode":"1370",
    "addr:street":"Grand'Place",
    "iso:country":"BE",
    "sg:address":"Grand'place 14",
    "sg:city":"Jodoigne",
    "sg:classifiers":[
        {
            "category":"Food & Beverages",
            "subcategory":"Fruits & Vegetables",
            "type":"Retail Goods"
        }
    ],
    "sg:phone":"+32 10 81 54 66",
    "sg:postcode":"1370",
    "sg:province":"Brabant Wallon",
    "sg:tags":[
        "-"
    ],
    "wof:name":"Gadale (la)",
    "wof:placetype":"venue"
},
  "geometry": {"coordinates":[4.8666749001,50.7255744934],"type":"Point"}
}