{
  "type": "Feature",
  "properties": {
    "iso:country":"BE",
    "sg:address":"Meir 72",
    "sg:city":"Ravels",
    "sg:orig_category":"Goederenvervoer over de weg Huisvuilophaling and -verwerking",
    "sg:phone":"+32 14 65 86 44",
    "sg:postcode":"2381",
    "sg:province":"Antwerpen",
    "wof:name":"Segers",
    "wof:placetype":"venue"
},
  "geometry": {"coordinates":[4.9962759018,51.4222373962],"type":"Point"}
}