{
  "type": "Feature",
  "properties": {
    "iso:country":"BE",
    "sg:address":"Platanenlaan 34",
    "sg:city":"Essen",
    "sg:orig_category":"Kapsalons",
    "sg:phone":"+32 3 677 02 65",
    "sg:postcode":"2910",
    "sg:province":"Antwerpen",
    "wof:name":"Bertha Bonte",
    "wof:placetype":"venue"
},
  "geometry": {"coordinates":[4.4477300644,51.4311294556],"type":"Point"}
}