{
  "type": "Feature",
  "properties": {
    "addr:full":"Peter Benoitlaan 18 Kontich Antwerpen 2550",
    "addr:housenumber":"18",
    "addr:postcode":"2550",
    "addr:street":"Peter Benoitlaan",
    "iso:country":"BE",
    "sg:address":"Peter Benoitlaan 18",
    "sg:city":"Kontich",
    "sg:classifiers":[
        {
            "category":"Cafe",
            "type":"Food & Drink"
        }
    ],
    "sg:phone":"+32 3 458 44 86",
    "sg:postcode":"2550",
    "sg:province":"Antwerpen",
    "sg:tags":[
        "caf\u00e9s"
    ],
    "wof:name":"Ronny Piessens",
    "wof:placetype":"venue"
},
  "geometry": {"coordinates":[4.4444150925,51.1381034851],"type":"Point"}
}