{
  "type": "Feature",
  "properties": {
    "addr:full":"Rue Aim\u00e9 Smekens 98 Bruxelles (schaerbeek) Bruxelles-Capitale 1030",
    "addr:housenumber":"98",
    "addr:postcode":"1030",
    "addr:street":"Rue Aime\u0301 Smekens",
    "iso:country":"BE",
    "sg:address":"Rue Aim\u00e9 Smekens 98",
    "sg:city":"Bruxelles (schaerbeek)",
    "sg:classifiers":[
        {
            "category":"Professional",
            "subcategory":"Accounting & Tax Preparation",
            "type":"Services"
        }
    ],
    "sg:phone":"+32 2 771 02 36",
    "sg:postcode":"1030",
    "sg:province":"Bruxelles-Capitale",
    "sg:tags":[
        "bookkeeper"
    ],
    "wof:name":"Geulette J P",
    "wof:placetype":"venue"
},
  "geometry": {"coordinates":[4.409265995,50.8496322632],"type":"Point"}
}