{
  "type": "Feature",
  "properties": {
    "iso:country":"BE",
    "sg:address":"Assenedestraat 18",
    "sg:city":"Assenede (bassevelde)",
    "sg:classifiers":[
        {
            "category":"Health Services",
            "subcategory":"Nursing And Care Facility",
            "type":"Services"
        }
    ],
    "sg:phone":"+32 9 323 92 20",
    "sg:postcode":"9968",
    "sg:province":"Oost-Vlaanderen",
    "sg:tags":[
        "home",
        "rest"
    ],
    "wof:name":"St-bernardus Wzc",
    "wof:placetype":"venue"
},
  "geometry": {"coordinates":[3.6887938976,51.1923027039],"type":"Point"}
}