{
  "type": "Feature",
  "properties": {
    "iso:country":"BE",
    "sg:address":"Dorpsstraat 56",
    "sg:city":"Geetbets",
    "sg:classifiers":[
        {
            "category":"Manufacturing",
            "subcategory":"Textiles",
            "type":"Manufacturing & Wholesale Goods"
        }
    ],
    "sg:phone":"+32 11 58 71 63",
    "sg:postcode":"3450",
    "sg:province":"Vlaams-Brabant",
    "sg:tags":[
        "retail",
        "-"
    ],
    "wof:name":"Jong Mode Uten",
    "wof:placetype":"venue"
},
  "geometry": {"coordinates":[5.1155481339,50.8896713257],"type":"Point"}
}