{
  "type": "Feature",
  "properties": {
    "addr:full":"Eekstraat 293 Lokeren Oost-Vlaanderen 9160",
    "addr:housenumber":"293",
    "addr:postcode":"9160",
    "addr:street":"Eekstraat",
    "iso:country":"BE",
    "sg:address":"Eekstraat 293",
    "sg:city":"Lokeren",
    "sg:classifiers":[
        {
            "category":"Communications",
            "subcategory":"News Services",
            "type":"Services"
        }
    ],
    "sg:phone":"+32 9 328 70 44",
    "sg:postcode":"9160",
    "sg:province":"Oost-Vlaanderen",
    "sg:tags":[
        "illustrator"
    ],
    "wof:name":"Artoya",
    "wof:placetype":"venue"
},
  "geometry": {"coordinates":[3.9637310505,51.1008453369],"type":"Point"}
}