{
  "type": "Feature",
  "properties": {
    "addr:full":"Rue Tour Malherbe 252 Nandrin (villers-le-temple) Li\u00e8ge 4550",
    "addr:housenumber":"252",
    "addr:postcode":"4550",
    "addr:street":"Rue Tour Malherbe;Villers-Le-Temple",
    "iso:country":"BE",
    "sg:address":"Rue Tour Malherbe 252",
    "sg:city":"Nandrin (villers-le-temple)",
    "sg:classifiers":[
        {
            "category":"Health Services",
            "subcategory":"Medical Lab",
            "type":"Services"
        }
    ],
    "sg:phone":"+32 85 31 63 40",
    "sg:postcode":"4550",
    "sg:province":"Li\u00e8ge",
    "sg:tags":[
        "laboratory",
        "dental"
    ],
    "wof:name":"Labo Ceram",
    "wof:placetype":"venue"
},
  "geometry": {"coordinates":[5.3495898247,50.536441803],"type":"Point"}
}