{
  "type": "Feature",
  "properties": {
    "iso:country":"BE",
    "sg:address":"Warandestraat 2bb",
    "sg:city":"Ravels",
    "sg:orig_category":"Transports routiers de marchandises",
    "sg:phone":"+32 14 65 50 62",
    "sg:postcode":"2380",
    "sg:province":"Antwerpen",
    "wof:name":"Vervoer Thielemans",
    "wof:placetype":"venue"
},
  "geometry": {"coordinates":[5.0118598938,51.3731575012],"type":"Point"}
}