{
  "type": "Feature",
  "properties": {
    "iso:country":"BE",
    "sg:address":"Koningin Elisabethlaan 114",
    "sg:city":"Gent",
    "sg:orig_category":"Dameskledingzaken",
    "sg:phone":"+32 9 222 15 58",
    "sg:postcode":"9000",
    "sg:province":"Oost-Vlaanderen",
    "wof:name":"Huis Leonardo",
    "wof:placetype":"venue"
},
  "geometry": {"coordinates":[3.7130661011,51.0370750427],"type":"Point"}
}