{
  "type": "Feature",
  "properties": {
    "iso:country":"BE",
    "sg:address":"Clos De La Maloue 4",
    "sg:city":"Waterloo",
    "sg:classifiers":[
        {
            "category":"Personal",
            "subcategory":"Beauty Salon",
            "type":"Services"
        }
    ],
    "sg:phone":"+32 2 385 21 32",
    "sg:postcode":"1410",
    "sg:province":"Brabant Wallon",
    "sg:tags":[
        "de",
        "coiffure"
    ],
    "wof:name":"Cristina Ingenito",
    "wof:placetype":"venue"
},
  "geometry": {"coordinates":[4.3952040672,50.6939506531],"type":"Point"}
}