{
  "type": "Feature",
  "properties": {
    "iso:country":"BE",
    "sg:address":"Boulevard Du Roi Albert 76",
    "sg:city":"Tournai",
    "sg:orig_category":"Mat\u00e9riel m\u00e9dical and orthop\u00e9dique and proth\u00e8ses Fab",
    "sg:phone":"+32 69 22 63 68",
    "sg:postcode":"7500",
    "sg:province":"Hainaut",
    "wof:name":"Henri Prouvost",
    "wof:placetype":"venue"
},
  "geometry": {"coordinates":[3.3950350285,50.6007537842],"type":"Point"}
}