{
  "type": "Feature",
  "properties": {
    "addr:full":"Oudstrijderslaan 30 Harelbeke (bavikhove) West-Vlaanderen 8531",
    "addr:housenumber":"30",
    "addr:postcode":"8531",
    "addr:street":"Oudstrijderslaan",
    "iso:country":"BE",
    "sg:address":"Oudstrijderslaan 30",
    "sg:city":"Harelbeke (bavikhove)",
    "sg:classifiers":[
        {
            "category":"Professional",
            "subcategory":"Computer Services",
            "type":"Services"
        }
    ],
    "sg:phone":"+32 56 72 90 78",
    "sg:postcode":"8531",
    "sg:province":"West-Vlaanderen",
    "sg:tags":[
        "-",
        "processing",
        "data",
        "software"
    ],
    "wof:name":"H.c.c.s. Bvba",
    "wof:placetype":"venue"
},
  "geometry": {"coordinates":[3.3075730801,50.8740196228],"type":"Point"}
}