{
  "type": "Feature",
  "properties": {
    "iso:country":"BE",
    "sg:address":"Chauss\u00e9e De Waterloo 1487",
    "sg:city":"Bruxelles (uccle)",
    "sg:classifiers":[
        {
            "category":"Social Services",
            "subcategory":"Retirement Home",
            "type":"Services"
        }
    ],
    "sg:phone":"+32 2 374 93 33",
    "sg:postcode":"1180",
    "sg:province":"Bruxelles-Capitale",
    "sg:tags":[
        "printing",
        "-",
        "relief"
    ],
    "wof:name":"Handley Sprl",
    "wof:placetype":"venue"
},
  "geometry": {"coordinates":[4.3792247772,50.7830314636],"type":"Point"}
}