{
  "type": "Feature",
  "properties": {
    "iso:country":"BE",
    "sg:address":"Gebroeders Van De Woestyneplein 12a",
    "sg:city":"Eeklo",
    "sg:classifiers":[
        {
            "category":"Home & Garden",
            "subcategory":"Kitchen Supply",
            "type":"Retail Goods"
        }
    ],
    "sg:phone":"+32 9 378 58 25",
    "sg:postcode":"9900",
    "sg:province":"Oost-Vlaanderen",
    "sg:tags":[
        "installation"
    ],
    "wof:name":"Antheunis J",
    "wof:placetype":"venue"
},
  "geometry": {"coordinates":[3.5691580772,51.1801757812],"type":"Point"}
}