{
  "type": "Feature",
  "properties": {
    "addr:full":"Av. Du G\u00c9n\u00c9ral De Gaulle 18 Elsene/ixelles Bruxelles-Capitale 1050",
    "addr:housenumber":"18",
    "addr:postcode":"1050",
    "addr:street":"Av. Du Ge\u0301Ne\u0301Ral De Gaulle",
    "iso:country":"BE",
    "sg:address":"Av. Du G\u00c9n\u00c9ral De Gaulle 18",
    "sg:city":"Elsene/ixelles",
    "sg:orig_category":"Activit\u00e9s diverses d'imprimerie",
    "sg:phone":"+32 2 648 86 70",
    "sg:postcode":"1050",
    "sg:province":"Bruxelles-Capitale",
    "wof:name":"Bureau Marsily J.p.",
    "wof:placetype":"venue"
},
  "geometry": {"coordinates":[4.3708200455,50.8261184692],"type":"Point"}
}