{
  "type": "Feature",
  "properties": {
    "iso:country":"BE",
    "sg:address":"Dokter Persoonslaan 15be",
    "sg:city":"Willebroek",
    "sg:orig_category":"Verplichte sociale verzekeringen",
    "sg:phone":"+32 3 886 61 08",
    "sg:postcode":"2830",
    "sg:province":"Antwerpen",
    "wof:name":"Socialist. Mutualiteit",
    "wof:placetype":"venue"
},
  "geometry": {"coordinates":[4.3621959686,51.0597419739],"type":"Point"}
}