{
  "type": "Feature",
  "properties": {
    "iso:country":"BE",
    "sg:address":"Dorp 4",
    "sg:city":"Scherpenheuvel-zichem (testelt)",
    "sg:classifiers":[
        {
            "category":"Personal",
            "subcategory":"Beauty Salon",
            "type":"Services"
        }
    ],
    "sg:phone":"+32 13 77 74 65",
    "sg:postcode":"3272",
    "sg:province":"Vlaams-Brabant",
    "sg:tags":[
        "lady",
        "-",
        "hairdressing"
    ],
    "wof:name":"Mardulier H",
    "wof:placetype":"venue"
},
  "geometry": {"coordinates":[4.9546971321,51.0088844299],"type":"Point"}
}