{
  "type": "Feature",
  "properties": {
    "addr:full":"Boulevard Albert-elisabeth 81 Mons Hainaut 7000",
    "addr:housenumber":"81",
    "addr:postcode":"7000",
    "addr:street":"Boulevard Albert-Elisabeth;Hainaut",
    "iso:country":"BE",
    "sg:address":"Boulevard Albert-elisabeth 81",
    "sg:city":"Mons",
    "sg:orig_category":"Installation de menuiserie m\u00e9tallique. Installation de menuiserie en bois and plastique",
    "sg:phone":"+32 65 36 09 89",
    "sg:postcode":"7000",
    "sg:province":"Hainaut",
    "wof:name":"De Spirlet",
    "wof:placetype":"venue"
},
  "geometry": {"coordinates":[3.9513289928,50.4458885193],"type":"Point"}
}