{
  "type": "Feature",
  "properties": {
    "addr:full":"Rue Des Fran\u00e7ais 45 Ans Li\u00e8ge 4430",
    "addr:housenumber":"45",
    "addr:postcode":"4430",
    "addr:street":"Rue Des Franc\u0327Ais",
    "iso:country":"BE",
    "sg:address":"Rue Des Fran\u00e7ais 45",
    "sg:city":"Ans",
    "sg:classifiers":[
        {
            "category":"Retail",
            "subcategory":"Repair Shop",
            "type":"Services"
        }
    ],
    "sg:phone":"+32 4 247 40 70",
    "sg:postcode":"4430",
    "sg:province":"Li\u00e8ge",
    "sg:tags":[
        "denture"
    ],
    "wof:name":"Ans Dental",
    "wof:placetype":"venue"
},
  "geometry": {"coordinates":[5.5310869217,50.6572532654],"type":"Point"}
}