{
  "type": "Feature",
  "properties": {
    "addr:full":"Rue Des R\u00d4tisseurs 12 Huy Li\u00e8ge 4500",
    "addr:housenumber":"12",
    "addr:postcode":"4500",
    "addr:street":"Rue Des Ro\u0302Tisseurs",
    "iso:country":"BE",
    "sg:address":"Rue Des R\u00d4tisseurs 12",
    "sg:city":"Huy",
    "sg:orig_category":"Salles de spectacles",
    "sg:phone":"+32 85 25 10 13",
    "sg:postcode":"4500",
    "sg:province":"Li\u00e8ge",
    "wof:name":"Dus\u00b4art Gallery",
    "wof:placetype":"venue"
},
  "geometry": {"coordinates":[5.2402591705,50.5189170837],"type":"Point"}
}