{
  "type": "Feature",
  "properties": {
    "iso:country":"BE",
    "sg:address":"Rue De Verviers 76",
    "sg:city":"Welkenraedt",
    "sg:orig_category":"Charpentes and couvertures",
    "sg:phone":"+32 87 44 67 13",
    "sg:postcode":"4841",
    "sg:province":"Li\u00e8ge",
    "wof:name":"Halleux Baudouin",
    "wof:placetype":"venue"
},
  "geometry": {"coordinates":[5.9200701714,50.6682510376],"type":"Point"}
}