{
  "type": "Feature",
  "properties": {
    "addr:full":"Rue Albert I 22 Hannut Li\u00e8ge 4280",
    "addr:housenumber":"22",
    "addr:postcode":"4280",
    "addr:street":"Rue Albert I",
    "iso:country":"BE",
    "sg:address":"Rue Albert I 22",
    "sg:city":"Hannut",
    "sg:classifiers":[
        {
            "category":"Shopping",
            "subcategory":"Shoes",
            "type":"Retail Goods"
        }
    ],
    "sg:phone":"+32 19 51 30 90",
    "sg:postcode":"4280",
    "sg:province":"Li\u00e8ge",
    "sg:tags":[
        "slipper",
        "-"
    ],
    "wof:name":"Chat Bottine",
    "wof:placetype":"venue"
},
  "geometry": {"coordinates":[5.0804719925,50.6708602905],"type":"Point"}
}