{
  "type": "Feature",
  "properties": {
    "iso:country":"BE",
    "sg:address":"Bergstrasse 48",
    "sg:city":"Eupen",
    "sg:orig_category":"Slagers",
    "sg:phone":"+32 87 55 40 30",
    "sg:postcode":"4700",
    "sg:province":"Li\u00e8ge",
    "wof:name":"Peter Koonen",
    "wof:placetype":"venue"
},
  "geometry": {"coordinates":[6.0335698128,50.6285018921],"type":"Point"}
}