{
  "type": "Feature",
  "properties": {
    "iso:country":"BE",
    "sg:address":"Van Dijcklaan 10",
    "sg:city":"Hasselt",
    "sg:orig_category":"Chaussures",
    "sg:phone":"+32 11 87 16 88",
    "sg:postcode":"3500",
    "sg:province":"Limburg",
    "wof:name":"Vanstraelen",
    "wof:placetype":"venue"
},
  "geometry": {"coordinates":[5.3306918144,50.9390296936],"type":"Point"}
}