{
  "type": "Feature",
  "properties": {
    "addr:full":"Weststraat 24 Aalter Oost-Vlaanderen 9880",
    "addr:housenumber":"24",
    "addr:postcode":"9880",
    "addr:street":"Weststraat",
    "iso:country":"BE",
    "sg:address":"Weststraat 24",
    "sg:city":"Aalter",
    "sg:orig_category":"Eleveurs de bovins",
    "sg:phone":"+32 9 374 55 27",
    "sg:postcode":"9880",
    "sg:province":"Oost-Vlaanderen",
    "wof:name":"Johan Cornelis",
    "wof:placetype":"venue"
},
  "geometry": {"coordinates":[3.4222249985,51.1078643799],"type":"Point"}
}