{
  "type": "Feature",
  "properties": {
    "iso:country":"BE",
    "sg:address":"Chaussee De Bruxelles Bovesse 4",
    "sg:city":"Bovesse",
    "sg:classifiers":[
        {
            "category":"Retail",
            "subcategory":"Auto Repair",
            "type":"Services"
        }
    ],
    "sg:phone":"+32 81 56 70 57",
    "sg:postcode":"5081",
    "sg:province":"Namur",
    "sg:tags":[
        "engine",
        "industrial",
        "diesel",
        "maintenance"
    ],
    "wof:name":"Universal Trucks Namur S.a.",
    "wof:placetype":"venue"
},
  "geometry": {"coordinates":[4.7882180214,50.5460700989],"type":"Point"}
}