{
  "type": "Feature",
  "properties": {
    "addr:full":"Justitieplein 9 Box 9 Dendermonde Oost-Vlaanderen 9200",
    "addr:housenumber":"9;9",
    "addr:postcode":"9200",
    "addr:street":"Justitieplein;Box;Oost-Vlaanderen",
    "iso:country":"BE",
    "sg:address":"Justitieplein 9 Box 9",
    "sg:city":"Dendermonde",
    "sg:classifiers":[
        {
            "category":"Real Estate",
            "subcategory":"Developer",
            "type":"Services"
        }
    ],
    "sg:phone":"+32 52 22 54 23",
    "sg:postcode":"9200",
    "sg:province":"Oost-Vlaanderen",
    "sg:tags":[
        "project"
    ],
    "wof:name":"J & D Projects Nv",
    "wof:placetype":"venue"
},
  "geometry": {"coordinates":[4.09851408,51.0308647156],"type":"Point"}
}