{
  "type": "Feature",
  "properties": {
    "iso:country":"BE",
    "sg:address":"De Villegaslaan 14",
    "sg:city":"Ganshoren",
    "sg:orig_category":"Dranken",
    "sg:phone":"+32 2 428 61 36",
    "sg:postcode":"1083",
    "sg:province":"Bruxelles-Capitale",
    "wof:name":"A La Vigne",
    "wof:placetype":"venue"
},
  "geometry": {"coordinates":[4.3091549873,50.8699531555],"type":"Point"}
}