{
  "type": "Feature",
  "properties": {
    "addr:full":"Klipperstraat 15b4 Antwerpen Antwerpen 2030",
    "addr:housenumber":"15b4",
    "addr:postcode":"2030",
    "addr:street":"Klipperstraat",
    "iso:country":"BE",
    "sg:address":"Klipperstraat 15b4",
    "sg:city":"Antwerpen",
    "sg:classifiers":[
        {
            "category":"Airport",
            "type":"Transportation"
        }
    ],
    "sg:phone":"+32 3 545 35 11",
    "sg:postcode":"2030",
    "sg:province":"Antwerpen",
    "sg:tags":[
        "air-freight",
        "forwarders"
    ],
    "wof:name":"Abumex-hudsons Nv",
    "wof:placetype":"venue"
},
  "geometry": {"coordinates":[4.4244451523,51.2439994812],"type":"Point"}
}