{
  "type": "Feature",
  "properties": {
    "addr:full":"Volksv. De Jaegerelaan 4 Kortrijk West-Vlaanderen 8500",
    "addr:housenumber":"4",
    "addr:postcode":"8500",
    "addr:street":"Jaegerelaan",
    "iso:country":"BE",
    "sg:address":"Volksv. De Jaegerelaan 4",
    "sg:city":"Kortrijk",
    "sg:orig_category":"Boissons",
    "sg:phone":"+32 56 22 47 59",
    "sg:postcode":"8500",
    "sg:province":"West-Vlaanderen",
    "wof:name":"Enedita Hernandez-ramos",
    "wof:placetype":"venue"
},
  "geometry": {"coordinates":[3.2825629711,50.8236236572],"type":"Point"}
}