{
  "type": "Feature",
  "properties": {
    "addr:full":"Eindhoutsebaan 93 Meerhout Antwerpen 2450",
    "addr:housenumber":"93",
    "addr:postcode":"2450",
    "addr:street":"Eindhoutsebaan",
    "iso:country":"BE",
    "sg:address":"Eindhoutsebaan 93",
    "sg:city":"Meerhout",
    "sg:classifiers":[
        {
            "category":"Shopping Center",
            "type":"Public Place"
        }
    ],
    "sg:phone":"+32 14 21 93 99",
    "sg:postcode":"2450",
    "sg:province":"Antwerpen",
    "sg:tags":[
        "enseignement",
        "formation"
    ],
    "wof:name":"B.i. Opleidingscentrum",
    "wof:placetype":"venue"
},
  "geometry": {"coordinates":[5.0303111076,51.1176834106],"type":"Point"}
}