{
  "type": "Feature",
  "properties": {
    "iso:country":"BE",
    "sg:address":"Rue Du Tour 12",
    "sg:city":"Boussu (hornu)",
    "sg:classifiers":[
        {
            "category":"Health Services",
            "subcategory":"Health Practitioner",
            "type":"Services"
        }
    ],
    "sg:phone":"+32 65 63 39 31",
    "sg:postcode":"7301",
    "sg:province":"Hainaut",
    "sg:tags":[
        "physiotherapist"
    ],
    "wof:name":"Gallegos C",
    "wof:placetype":"venue"
},
  "geometry": {"coordinates":[3.8140490055,50.3999977112],"type":"Point"}
}