{
  "type": "Feature",
  "properties": {
    "addr:full":"Capucienenlaan 31 Aalst Oost-Vlaanderen 9300",
    "addr:housenumber":"31",
    "addr:postcode":"9300",
    "addr:street":"Capucienenlaan",
    "iso:country":"BE",
    "sg:address":"Capucienenlaan 31",
    "sg:city":"Aalst",
    "sg:classifiers":[
        {
            "category":"Retail",
            "subcategory":"Repair Shop",
            "type":"Services"
        }
    ],
    "sg:phone":"+32 53 77 54 31",
    "sg:postcode":"9300",
    "sg:province":"Oost-Vlaanderen",
    "sg:tags":[
        "denture"
    ],
    "wof:name":"Van Den Eynde Tandlabo",
    "wof:placetype":"venue"
},
  "geometry": {"coordinates":[4.0279898643,50.9362297058],"type":"Point"}
}