{
  "type": "Feature",
  "properties": {
    "addr:full":"Rue Winston Churchill 40 Courcelles Hainaut 6180",
    "addr:housenumber":"40",
    "addr:postcode":"6180",
    "addr:street":"Rue Winston Churchill",
    "iso:country":"BE",
    "sg:address":"Rue Winston Churchill 40",
    "sg:city":"Courcelles",
    "sg:classifiers":[
        {
            "category":"Communications",
            "subcategory":"Television Station",
            "type":"Services"
        }
    ],
    "sg:phone":"+32 71 46 32 78",
    "sg:postcode":"6180",
    "sg:province":"Hainaut",
    "sg:tags":[
        "video",
        "audio",
        "verhuur"
    ],
    "wof:name":"Cin\u00c9 Musique",
    "wof:placetype":"venue"
},
  "geometry": {"coordinates":[4.3918800354,50.462890625],"type":"Point"}
}