{
  "type": "Feature",
  "properties": {
    "addr:full":"Turnhoutsebaan 214 Wijnegem Antwerpen 2110",
    "addr:housenumber":"214",
    "addr:postcode":"2110",
    "addr:street":"Turnhoutsebaan",
    "iso:country":"BE",
    "sg:address":"Turnhoutsebaan 214",
    "sg:city":"Wijnegem",
    "sg:orig_category":"Avocats and conseillers juridiques",
    "sg:phone":"+32 3 353 62 96",
    "sg:postcode":"2110",
    "sg:province":"Antwerpen",
    "wof:name":"A.m. De Baudringhien",
    "wof:placetype":"venue"
},
  "geometry": {"coordinates":[4.5124621391,51.2260704041],"type":"Point"}
}