{
  "type": "Feature",
  "properties": {
    "addr:full":"Rue Du Bois Des Dammes 11 Court-saint-etienne Brabant Wallon 1490",
    "addr:housenumber":"11;1490",
    "addr:street":"Rue Du Bois Des Dammes",
    "iso:country":"BE",
    "sg:address":"Rue Du Bois Des Dammes 11",
    "sg:city":"Court-saint-etienne",
    "sg:orig_category":"Auto-\u00e9coles",
    "sg:phone":"+32 10 61 69 83",
    "sg:postcode":"1490",
    "sg:province":"Brabant Wallon",
    "wof:name":"Gentleman Driver School",
    "wof:placetype":"venue"
},
  "geometry": {"coordinates":[4.5441322327,50.6202812195],"type":"Point"}
}