{
  "type": "Feature",
  "properties": {
    "addr:full":"Chauss\u00c9e De Bruxelles 279 Wemmel/wemmel Vlaams-Brabant 1780",
    "addr:housenumber":"279",
    "addr:postcode":"1780",
    "addr:street":"Chausse\u0301E De Bruxelles",
    "iso:country":"BE",
    "sg:address":"Chauss\u00c9e De Bruxelles 279",
    "sg:city":"Wemmel/wemmel",
    "sg:orig_category":"Rev\u00eatements pour sols and murs. Peinture",
    "sg:phone":"+32 2 460 51 77",
    "sg:postcode":"1780",
    "sg:province":"Vlaams-Brabant",
    "wof:name":"Florent Verhasselt",
    "wof:placetype":"venue"
},
  "geometry": {"coordinates":[4.3102350235,50.8989105225],"type":"Point"}
}