{
  "type": "Feature",
  "properties": {
    "addr:full":"Rue Emile Nils 22 Ittre Brabant Wallon 1460",
    "addr:housenumber":"22;1460",
    "addr:street":"Rue Emile Nils",
    "iso:country":"BE",
    "sg:address":"Rue Emile Nils 22",
    "sg:city":"Ittre",
    "sg:orig_category":"Activit\u00e9s diverses d'imprimerie",
    "sg:phone":"+32 67 64 84 12",
    "sg:postcode":"1460",
    "sg:province":"Brabant Wallon",
    "wof:name":"Thierry Vandeputte",
    "wof:placetype":"venue"
},
  "geometry": {"coordinates":[4.2073831558,50.6362419128],"type":"Point"}
}