{
  "type": "Feature",
  "properties": {
    "addr:full":"Rue Du Vert Bois 178 Montigny-le-tilleul Hainaut 6110",
    "addr:housenumber":"178",
    "addr:postcode":"6110",
    "addr:street":"Rue Du Vert Bois",
    "iso:country":"BE",
    "sg:address":"Rue Du Vert Bois 178",
    "sg:city":"Montigny-le-tilleul",
    "sg:classifiers":[
        {
            "category":"Manufacturing",
            "subcategory":"Tools & Machinery",
            "type":"Manufacturing & Wholesale Goods"
        }
    ],
    "sg:phone":"+32 71 56 08 33",
    "sg:postcode":"6110",
    "sg:province":"Hainaut",
    "sg:tags":[
        "-"
    ],
    "wof:name":"The Boss & Co Sc",
    "wof:placetype":"venue"
},
  "geometry": {"coordinates":[4.3975090981,50.3584480286],"type":"Point"}
}