{
  "type": "Feature",
  "properties": {
    "addr:full":"Rue Du Sart 51 Ittre Brabant Wallon 1460",
    "addr:housenumber":"51;1460",
    "addr:street":"Rue Du Sart",
    "iso:country":"BE",
    "sg:address":"Rue Du Sart 51",
    "sg:city":"Ittre",
    "sg:orig_category":"RESTAURANTS: CAF\u00c9S",
    "sg:phone":"+32 67 64 63 98",
    "sg:postcode":"1460",
    "sg:province":"Brabant Wallon",
    "wof:name":"Taverne Les Flocons",
    "wof:placetype":"venue"
},
  "geometry": {"coordinates":[4.2329068184,50.6541938782],"type":"Point"}
}