{
  "type": "Feature",
  "properties": {
    "iso:country":"BE",
    "sg:address":"Kleine Veldstraat 72",
    "sg:city":"Staden",
    "sg:classifiers":[
        {
            "category":"Building & Trades",
            "subcategory":"Construction",
            "type":"Services"
        }
    ],
    "sg:phone":"+32 51 70 15 16",
    "sg:postcode":"8840",
    "sg:province":"West-Vlaanderen",
    "sg:tags":[
        "asphalt",
        "contractor"
    ],
    "wof:name":"Steelandt",
    "wof:placetype":"venue"
},
  "geometry": {"coordinates":[3.0158159733,50.9467468262],"type":"Point"}
}