{
  "type": "Feature",
  "properties": {
    "iso:country":"BE",
    "sg:address":"Gouvernementstraat 20",
    "sg:city":"Gent",
    "sg:orig_category":"Advocaten and juridische adviseurs",
    "sg:phone":"+32 9 225 80 46",
    "sg:postcode":"9000",
    "sg:province":"Oost-Vlaanderen",
    "wof:name":"De Wildeman Hendrik",
    "wof:placetype":"venue"
},
  "geometry": {"coordinates":[3.7266891003,51.0517845154],"type":"Point"}
}