{
  "type": "Feature",
  "properties": {
    "addr:full":"Kromstraat 6 Glabbeek (glabbeek-zuurbemde) Vlaams-Brabant 3380",
    "addr:housenumber":"6",
    "addr:postcode":"3380",
    "addr:street":"Kromstraat",
    "iso:country":"BE",
    "sg:address":"Kromstraat 6",
    "sg:city":"Glabbeek (glabbeek-zuurbemde)",
    "sg:classifiers":[
        {
            "category":"Building & Trades",
            "subcategory":"Landscaping Services",
            "type":"Services"
        }
    ],
    "sg:phone":"+32 16 77 00 93",
    "sg:postcode":"3380",
    "sg:province":"Vlaams-Brabant",
    "sg:tags":[
        "equipment",
        "swimming",
        "-",
        "pool",
        "contractor"
    ],
    "wof:name":"Van Nerum A",
    "wof:placetype":"venue"
},
  "geometry": {"coordinates":[4.9426088333,50.8812255859],"type":"Point"}
}