{
  "type": "Feature",
  "properties": {
    "iso:country":"BE",
    "sg:address":"Kasteelstraat 16",
    "sg:city":"Ruiselede",
    "sg:orig_category":"Artsen and specialisten",
    "sg:phone":"+32 51 68 80 61",
    "sg:postcode":"8755",
    "sg:province":"West-Vlaanderen",
    "wof:name":"Ignace Bergez",
    "wof:placetype":"venue"
},
  "geometry": {"coordinates":[3.3959779739,51.0407981873],"type":"Point"}
}