{
  "type": "Feature",
  "properties": {
    "addr:full":"Avenue Platon 6 Bruxelles (evere) Bruxelles-Capitale 1140",
    "addr:housenumber":"6",
    "addr:postcode":"1140",
    "addr:street":"Avenue Platon",
    "iso:country":"BE",
    "sg:address":"Avenue Platon 6",
    "sg:city":"Bruxelles (evere)",
    "sg:classifiers":[
        {
            "category":"Retail",
            "subcategory":"Animal Services",
            "type":"Services"
        }
    ],
    "sg:phone":"+32 2 726 62 82",
    "sg:postcode":"1140",
    "sg:province":"Bruxelles-Capitale",
    "sg:tags":[
        "grooming",
        "-",
        "dog"
    ],
    "wof:name":"Nom D'un Chien",
    "wof:placetype":"venue"
},
  "geometry": {"coordinates":[4.4212388992,50.8617782593],"type":"Point"}
}