{
  "type": "Feature",
  "properties": {
    "addr:full":"Sint-truidersteenweg 390 Tongeren Limburg 3700",
    "addr:housenumber":"390",
    "addr:postcode":"3700",
    "addr:street":"Sint-Truidersteenweg",
    "iso:country":"BE",
    "sg:address":"Sint-truidersteenweg 390",
    "sg:city":"Tongeren",
    "sg:orig_category":"Pain, p\u00e2tisseries and confiseries",
    "sg:phone":"+32 12 39 21 72",
    "sg:postcode":"3700",
    "sg:province":"Limburg",
    "wof:name":"Emile Nijs",
    "wof:placetype":"venue"
},
  "geometry": {"coordinates":[5.4229159355,50.7801208496],"type":"Point"}
}