{
  "type": "Feature",
  "properties": {
    "addr:full":"Rue Pierre Michaux 74 Oupeye Li\u00e8ge 4683",
    "addr:housenumber":"74",
    "addr:postcode":"4683",
    "addr:street":"Rue Pierre Michaux",
    "iso:country":"BE",
    "sg:address":"Rue Pierre Michaux 74",
    "sg:city":"Oupeye",
    "sg:orig_category":"Articles de camping and de sport. V\u00e9hicules automobiles. Caravanes and remorques. V\u00e9hicules automobi",
    "sg:phone":"+32 4 240 14 10",
    "sg:postcode":"4683",
    "sg:province":"Li\u00e8ge",
    "wof:name":"Siesta Caravanes",
    "wof:placetype":"venue"
},
  "geometry": {"coordinates":[5.647465229,50.6922645569],"type":"Point"}
}