{
  "type": "Feature",
  "properties": {
    "iso:country":"BE",
    "sg:address":"Fortenstraat 1",
    "sg:city":"Waasmunster",
    "sg:orig_category":"Erotische Etablissementen",
    "sg:phone":"+32 52 46 11 97",
    "sg:postcode":"9250",
    "sg:province":"Oost-Vlaanderen",
    "wof:name":"The Professionals",
    "wof:placetype":"venue"
},
  "geometry": {"coordinates":[4.1148381233,51.1239204407],"type":"Point"}
}