{
  "type": "Feature",
  "properties": {
    "addr:full":"Rue Pont De Soleil 5b Wanze (vinalmont) Li\u00e8ge 4520",
    "addr:housenumber":"5b",
    "addr:postcode":"4520",
    "addr:street":"Rue Pont De Soleil",
    "iso:country":"BE",
    "sg:address":"Rue Pont De Soleil 5b",
    "sg:city":"Wanze (vinalmont)",
    "sg:classifiers":[
        {
            "category":"Building & Trades",
            "subcategory":"Construction",
            "type":"Services"
        }
    ],
    "sg:phone":"+32 85 23 35 02",
    "sg:postcode":"4520",
    "sg:province":"Li\u00e8ge",
    "sg:tags":[
        "installation",
        "-",
        "central",
        "heating"
    ],
    "wof:name":"Bertoncello",
    "wof:placetype":"venue"
},
  "geometry": {"coordinates":[5.2216601372,50.5645523071],"type":"Point"}
}