{
  "type": "Feature",
  "properties": {
    "iso:country":"BE",
    "sg:address":"Rue Willy Ernst 29",
    "sg:city":"Charleroi",
    "sg:orig_category":"Advocaten and juridische adviseurs",
    "sg:phone":"+32 71 70 14 99",
    "sg:postcode":"6000",
    "sg:province":"Hainaut",
    "wof:name":"Micha\u00cbl Donatangelo",
    "wof:placetype":"venue"
},
  "geometry": {"coordinates":[4.4492897987,50.4094276428],"type":"Point"}
}