{
  "type": "Feature",
  "properties": {
    "addr:full":"Waterstraat 36 Sint-katelijne-waver Antwerpen 2860",
    "addr:housenumber":"36",
    "addr:postcode":"2860",
    "addr:street":"Waterstraat",
    "iso:country":"BE",
    "sg:address":"Waterstraat 36",
    "sg:city":"Sint-katelijne-waver",
    "sg:orig_category":"Groententeelt",
    "sg:phone":"+32 15 31 23 45",
    "sg:postcode":"2860",
    "sg:province":"Antwerpen",
    "wof:name":"Theophiel Loffens",
    "wof:placetype":"venue"
},
  "geometry": {"coordinates":[4.5484480858,51.0803756714],"type":"Point"}
}