{
  "type": "Feature",
  "properties": {
    "addr:full":"Rue Des Viaducs 207 Mons Hainaut 7020",
    "addr:housenumber":"207",
    "addr:postcode":"7020",
    "addr:street":"Rue Des Viaducs;Hainaut",
    "iso:country":"BE",
    "sg:address":"Rue Des Viaducs 207",
    "sg:city":"Mons",
    "sg:orig_category":"Banken and kredietinstellingen",
    "sg:phone":"+32 65 35 44 36",
    "sg:postcode":"7020",
    "sg:province":"Hainaut",
    "wof:name":"Fortis",
    "wof:placetype":"venue"
},
  "geometry": {"coordinates":[3.9553449154,50.4761772156],"type":"Point"}
}