{
  "type": "Feature",
  "properties": {
    "iso:country":"BE",
    "sg:address":"Raoul Merckstraat 3",
    "sg:city":"Gooik",
    "sg:orig_category":"Architectes",
    "sg:phone":"+32 54 56 93 88",
    "sg:postcode":"1755",
    "sg:province":"Vlaams-Brabant",
    "wof:name":"Musch Pascal",
    "wof:placetype":"venue"
},
  "geometry": {"coordinates":[4.1193699837,50.7632713318],"type":"Point"}
}