{
  "type": "Feature",
  "properties": {
    "addr:full":"Zwaluwenstraat 23 Geel Antwerpen 2440",
    "addr:housenumber":"23",
    "addr:postcode":"2440",
    "addr:street":"Zwaluwenstraat",
    "iso:country":"BE",
    "sg:address":"Zwaluwenstraat 23",
    "sg:city":"Geel",
    "sg:orig_category":"Boucheries",
    "sg:phone":"+32 14 58 30 03",
    "sg:postcode":"2440",
    "sg:province":"Antwerpen",
    "wof:name":"Danny Vanhoof",
    "wof:placetype":"venue"
},
  "geometry": {"coordinates":[4.9728112221,51.1731262207],"type":"Point"}
}