{
  "type": "Feature",
  "properties": {
    "iso:country":"BE",
    "sg:address":"Luikersteenweg 393 Box 2",
    "sg:city":"Hasselt",
    "sg:classifiers":[
        {
            "category":"Shopping",
            "subcategory":"Discount & Variety Stores",
            "type":"Retail Goods"
        }
    ],
    "sg:phone":"+32 478 32 46 99",
    "sg:postcode":"3500",
    "sg:province":"Limburg",
    "sg:tags":[
        "shop",
        "clearers",
        "curiosity",
        "furniture"
    ],
    "wof:name":"Lauwers R Bvba",
    "wof:placetype":"venue"
},
  "geometry": {"coordinates":[5.3548398018,50.909450531],"type":"Point"}
}