{
  "type": "Feature",
  "properties": {
    "iso:country":"BE",
    "sg:address":"Doelstraat 35",
    "sg:city":"Berlaar",
    "sg:classifiers":[
        {
            "category":"Professional",
            "subcategory":"Accounting & Tax Preparation",
            "type":"Services"
        }
    ],
    "sg:phone":"+32 475 75 32 16",
    "sg:postcode":"2590",
    "sg:province":"Antwerpen",
    "sg:tags":[
        "bookkeeper"
    ],
    "wof:name":"Marien P",
    "wof:placetype":"venue"
},
  "geometry": {"coordinates":[4.6488218307,51.1129226685],"type":"Point"}
}