{
  "type": "Feature",
  "properties": {
    "addr:full":"Avenue Henry Dunant 25 Box 1 Bruxelles (evere) Bruxelles-Capitale 1140",
    "addr:housenumber":"25;1",
    "addr:postcode":"1140",
    "addr:street":"Avenue Henry Dunant;Box",
    "iso:country":"BE",
    "sg:address":"Avenue Henry Dunant 25 Box 1",
    "sg:city":"Bruxelles (evere)",
    "sg:classifiers":[
        {
            "category":"Professional",
            "subcategory":"Computer Services",
            "type":"Services"
        }
    ],
    "sg:phone":"+32 2 729 54 70",
    "sg:postcode":"1140",
    "sg:province":"Bruxelles-Capitale",
    "sg:tags":[
        "-",
        "processing",
        "data",
        "software"
    ],
    "wof:name":"Top Itservices Belgium Sa",
    "wof:placetype":"venue"
},
  "geometry": {"coordinates":[4.4137420654,50.8640060425],"type":"Point"}
}