{
  "type": "Feature",
  "properties": {
    "addr:full":"Rue De Bruxelles 7 Fleurus Hainaut 6220",
    "addr:housenumber":"7",
    "addr:postcode":"6220",
    "addr:street":"Rue De Bruxelles",
    "iso:country":"BE",
    "sg:address":"Rue De Bruxelles 7",
    "sg:city":"Fleurus",
    "sg:orig_category":"Kapsalons",
    "sg:phone":"+32 71 81 13 89",
    "sg:postcode":"6220",
    "sg:province":"Hainaut",
    "wof:name":"Jocelyne Noel",
    "wof:placetype":"venue"
},
  "geometry": {"coordinates":[4.5511741638,50.4833984375],"type":"Point"}
}