{
  "type": "Feature",
  "properties": {
    "iso:country":"BE",
    "sg:address":"Anjerweg 1",
    "sg:city":"Staden",
    "sg:orig_category":"Elektrische installaties voor woningen",
    "sg:phone":"+32 51 70 06 41",
    "sg:postcode":"8840",
    "sg:province":"West-Vlaanderen",
    "wof:name":"Vandewalle Elektro",
    "wof:placetype":"venue"
},
  "geometry": {"coordinates":[3.0077800751,50.9742584229],"type":"Point"}
}