{
  "type": "Feature",
  "properties": {
    "iso:country":"BE",
    "sg:address":"Nijverheidstraat 17",
    "sg:city":"Londerzeel",
    "sg:classifiers":[
        {
            "category":"Restaurant",
            "type":"Food & Drink"
        }
    ],
    "sg:phone":"+32 52 30 77 19",
    "sg:postcode":"1840",
    "sg:province":"Vlaams-Brabant",
    "wof:name":"V T S Restaurant",
    "wof:placetype":"venue"
},
  "geometry": {"coordinates":[4.3245778084,51.0114822388],"type":"Point"}
}