{
  "type": "Feature",
  "properties": {
    "iso:country":"BE",
    "sg:address":"Varestraat 19",
    "sg:city":"Sint-katelijne-waver",
    "sg:orig_category":"Groententeelt",
    "sg:phone":"+32 15 31 56 26",
    "sg:postcode":"2860",
    "sg:province":"Antwerpen",
    "wof:name":"Leopold De Wit",
    "wof:placetype":"venue"
},
  "geometry": {"coordinates":[4.5069627762,51.0794296265],"type":"Point"}
}