{
  "type": "Feature",
  "properties": {
    "iso:country":"BE",
    "sg:address":"Izegemsestraat 379",
    "sg:city":"Kortrijk",
    "sg:orig_category":"Herstellingen and onderhoud van auto's Voertuigen",
    "sg:phone":"+32 56 35 91 03",
    "sg:postcode":"8501",
    "sg:province":"West-Vlaanderen",
    "wof:name":"Garage Van Haesebrouck",
    "wof:placetype":"venue"
},
  "geometry": {"coordinates":[3.2471818924,50.8600540161],"type":"Point"}
}