{
  "type": "Feature",
  "properties": {
    "addr:full":"Bouxhmont 662 Herve Li\u00e8ge 4654",
    "addr:housenumber":"662",
    "addr:postcode":"4654",
    "addr:street":"Bouxhmont",
    "iso:country":"BE",
    "sg:address":"Bouxhmont 662",
    "sg:city":"Herve",
    "sg:orig_category":"Rundveehouders Varkenskwekers",
    "sg:phone":"+32 87 67 47 76",
    "sg:postcode":"4654",
    "sg:province":"Li\u00e8ge",
    "wof:name":"Jean Deckers",
    "wof:placetype":"venue"
},
  "geometry": {"coordinates":[5.8190112114,50.6578445435],"type":"Point"}
}