{
  "type": "Feature",
  "properties": {
    "addr:full":"Gentsestraat 49 Geraardsbergen Oost-Vlaanderen 9500",
    "addr:housenumber":"49",
    "addr:postcode":"9500",
    "addr:street":"Gentsestraat",
    "iso:country":"BE",
    "sg:address":"Gentsestraat 49",
    "sg:city":"Geraardsbergen",
    "sg:classifiers":[
        {
            "category":"Shopping",
            "subcategory":"Clothing, Apparel, & Fashions",
            "type":"Retail Goods"
        }
    ],
    "sg:phone":"+32 54 41 28 18",
    "sg:postcode":"9500",
    "sg:province":"Oost-Vlaanderen",
    "sg:tags":[
        "v\u00eatements",
        "pour",
        "dame"
    ],
    "wof:name":"Huis Angele",
    "wof:placetype":"venue"
},
  "geometry": {"coordinates":[3.8748428822,50.7745323181],"type":"Point"}
}