{
  "type": "Feature",
  "properties": {
    "addr:full":"Rue Albert I 44 P\u00e9ruwelz Hainaut 7600",
    "addr:housenumber":"44",
    "addr:postcode":"7600",
    "addr:street":"Rue Albert I",
    "iso:country":"BE",
    "sg:address":"Rue Albert I 44",
    "sg:city":"P\u00e9ruwelz",
    "sg:classifiers":[
        {
            "category":"Shopping",
            "subcategory":"Clothing, Apparel, & Fashions",
            "type":"Retail Goods"
        }
    ],
    "sg:phone":"+32 69 77 50 70",
    "sg:postcode":"7600",
    "sg:province":"Hainaut",
    "sg:tags":[
        "lady",
        "clothing",
        "-"
    ],
    "wof:name":"Picvert Sc",
    "wof:placetype":"venue"
},
  "geometry": {"coordinates":[3.5909259319,50.5084838867],"type":"Point"}
}