{
  "type": "Feature",
  "properties": {
    "addr:full":"Koning Albertlaan 13 Maaseik Limburg 3680",
    "addr:housenumber":"13",
    "addr:postcode":"3680",
    "addr:street":"Koning Albertlaan",
    "iso:country":"BE",
    "sg:address":"Koning Albertlaan 13",
    "sg:city":"Maaseik",
    "sg:orig_category":"V\u00e9t\u00e9rinaires",
    "sg:phone":"+32 89 56 45 00",
    "sg:postcode":"3680",
    "sg:province":"Limburg",
    "wof:name":"Jozef Molenaers",
    "wof:placetype":"venue"
},
  "geometry": {"coordinates":[5.7845649719,51.0964393616],"type":"Point"}
}