{
  "type": "Feature",
  "properties": {
    "addr:full":"Rue De La T\u00cate D\u00b4or 5 Brussel/bruxelles Bruxelles-Capitale 1000",
    "addr:housenumber":"5",
    "addr:postcode":"1000",
    "addr:street":"Rue De La Te\u0302Te D\u00b4Or;/",
    "iso:country":"BE",
    "sg:address":"Rue De La T\u00cate D\u00b4or 5",
    "sg:city":"Brussel/bruxelles",
    "sg:orig_category":"Salles de spectacles",
    "sg:phone":"+32 2 502 97 50",
    "sg:postcode":"1000",
    "sg:province":"Bruxelles-Capitale",
    "wof:name":"Galerie S.scohy-talent 21",
    "wof:placetype":"venue"
},
  "geometry": {"coordinates":[4.351418972,50.8469238281],"type":"Point"}
}