{
  "type": "Feature",
  "properties": {
    "iso:country":"BE",
    "sg:address":"Mechelbaan 402",
    "sg:city":"Putte",
    "sg:classifiers":[
        {
            "category":"Professional",
            "subcategory":"Testing Lab",
            "type":"Services"
        }
    ],
    "sg:phone":"+32 15 75 51 06",
    "sg:postcode":"2580",
    "sg:province":"Antwerpen",
    "sg:tags":[
        "chemist"
    ],
    "wof:name":"Gysemans H",
    "wof:placetype":"venue"
},
  "geometry": {"coordinates":[4.6310281754,51.0560073853],"type":"Point"}
}