{
  "type": "Feature",
  "properties": {
    "addr:full":"Avenue Winston Churchill 224b12 Ukkel/uccle Bruxelles-Capitale 1180",
    "addr:housenumber":"224b12",
    "addr:postcode":"1180",
    "addr:street":"Avenue Winston Churchill;/",
    "iso:country":"BE",
    "sg:address":"Avenue Winston Churchill 224b12",
    "sg:city":"Ukkel/uccle",
    "sg:orig_category":"Artistes ind\u00e9pendants",
    "sg:phone":"+32 2 343 70 21",
    "sg:postcode":"1180",
    "sg:province":"Bruxelles-Capitale",
    "wof:name":"B\u00c9atrice Bencsik",
    "wof:placetype":"venue"
},
  "geometry": {"coordinates":[4.3651041985,50.8118743896],"type":"Point"}
}