{
  "type": "Feature",
  "properties": {
    "iso:country":"BE",
    "sg:address":"Heist Goorstraat 29",
    "sg:city":"Heist-op-den-berg",
    "sg:classifiers":[
        {
            "category":"Professional",
            "subcategory":"Testing Lab",
            "type":"Services"
        }
    ],
    "sg:phone":"+32 15 25 19 78",
    "sg:postcode":"2220",
    "sg:province":"Antwerpen",
    "sg:tags":[
        "chemist"
    ],
    "wof:name":"Heist-farma",
    "wof:placetype":"venue"
},
  "geometry": {"coordinates":[4.7276301384,51.0509300232],"type":"Point"}
}