{
  "type": "Feature",
  "properties": {
    "addr:full":"Stationsstraat 262 Liedekerke Vlaams-Brabant 1770",
    "addr:housenumber":"262",
    "addr:postcode":"1770",
    "addr:street":"Stationsstraat;Vlaams-Brabant",
    "iso:country":"BE",
    "sg:address":"Stationsstraat 262",
    "sg:city":"Liedekerke",
    "sg:orig_category":"Catering and organisation de f\u00eates",
    "sg:phone":"+32 53 68 00 78",
    "sg:postcode":"1770",
    "sg:province":"Vlaams-Brabant",
    "wof:name":"Traiteur Ronny",
    "wof:placetype":"venue"
},
  "geometry": {"coordinates":[4.0924482346,50.8780212402],"type":"Point"}
}