{
  "type": "Feature",
  "properties": {
    "iso:country":"BE",
    "sg:address":"Roggestraat 1",
    "sg:city":"Wielsbeke",
    "sg:orig_category":"Gestion de media publicitaires",
    "sg:phone":"+32 56 66 47 11",
    "sg:postcode":"8710",
    "sg:province":"West-Vlaanderen",
    "wof:name":"Real Publicity Service",
    "wof:placetype":"venue"
},
  "geometry": {"coordinates":[3.3807830811,50.9105682373],"type":"Point"}
}