{
  "type": "Feature",
  "properties": {
    "iso:country":"BE",
    "sg:address":"Wenenstraat 9",
    "sg:city":"Meer",
    "sg:orig_category":"Boissons",
    "sg:phone":"+32 3 315 05 11",
    "sg:postcode":"2321",
    "sg:province":"Antwerpen",
    "wof:name":"Het Bierparadijs",
    "wof:placetype":"venue"
},
  "geometry": {"coordinates":[4.726544857,51.4725532532],"type":"Point"}
}