{
  "type": "Feature",
  "properties": {
    "iso:country":"BE",
    "sg:address":"Route De Philippeville",
    "sg:city":"Charleroi (couillet)",
    "sg:classifiers":[
        {
            "category":"Education",
            "subcategory":"Special Training",
            "type":"Public Place"
        }
    ],
    "sg:phone":"+32 71 47 02 61",
    "sg:postcode":"6010",
    "sg:province":"Hainaut",
    "sg:tags":[
        "-",
        "processing",
        "data"
    ],
    "wof:name":"Gil Informatique Sprl",
    "wof:placetype":"venue"
},
  "geometry": {"coordinates":[4.4660949707,50.378993988],"type":"Point"}
}