{
  "type": "Feature",
  "properties": {
    "addr:full":"Beemdstraat 12 Puurs Antwerpen 2870",
    "addr:housenumber":"12",
    "addr:postcode":"2870",
    "addr:street":"Beemdstraat",
    "iso:country":"BE",
    "sg:address":"Beemdstraat 12",
    "sg:city":"Puurs",
    "sg:orig_category":"Domotics",
    "sg:phone":"+32 3 886 79 85",
    "sg:postcode":"2870",
    "sg:province":"Antwerpen",
    "wof:name":"Kempisec",
    "wof:placetype":"venue"
},
  "geometry": {"coordinates":[4.3230528831,51.0834960938],"type":"Point"}
}