{
  "type": "Feature",
  "properties": {
    "iso:country":"BE",
    "sg:address":"Vorsenzang 13",
    "sg:city":"Aarschot",
    "sg:orig_category":"Installatie van houten of kunststof schrijnwerk Meubelzaken, woning- and keukeninrichting",
    "sg:phone":"+32 16 56 62 52",
    "sg:postcode":"3200",
    "sg:province":"Vlaams-Brabant",
    "wof:name":"De Wijngaert",
    "wof:placetype":"venue"
},
  "geometry": {"coordinates":[4.8315200806,50.9838638306],"type":"Point"}
}