{
  "type": "Feature",
  "properties": {
    "addr:full":"Sur Les Vignes 41 Herve (battice) Li\u00e8ge 4651",
    "addr:housenumber":"41",
    "addr:postcode":"4651",
    "addr:street":"Sur Les Vignes",
    "iso:country":"BE",
    "sg:address":"Sur Les Vignes 41",
    "sg:city":"Herve (battice)",
    "sg:classifiers":[
        {
            "category":"Retail",
            "subcategory":"Auto Repair",
            "type":"Services"
        }
    ],
    "sg:phone":"+32 87 67 50 23",
    "sg:postcode":"4651",
    "sg:province":"Li\u00e8ge",
    "sg:tags":[
        "garage"
    ],
    "wof:name":"Bovens",
    "wof:placetype":"venue"
},
  "geometry": {"coordinates":[5.7797598839,50.6372489929],"type":"Point"}
}