{
  "type": "Feature",
  "properties": {
    "addr:full":"Sint-jozeflaan 5 Halle Vlaams-Brabant 1501",
    "addr:housenumber":"5",
    "addr:postcode":"1501",
    "addr:street":"Sint-Jozeflaan",
    "iso:country":"BE",
    "sg:address":"Sint-jozeflaan 5",
    "sg:city":"Halle",
    "sg:orig_category":"Antiek",
    "sg:phone":"+32 2 356 09 94",
    "sg:postcode":"1501",
    "sg:province":"Vlaams-Brabant",
    "wof:name":"Antiek Karsten",
    "wof:placetype":"venue"
},
  "geometry": {"coordinates":[4.2514300346,50.7381820679],"type":"Point"}
}