{
  "type": "Feature",
  "properties": {
    "iso:country":"BE",
    "sg:address":"Bruul 101",
    "sg:city":"Mechelen",
    "sg:classifiers":[
        {
            "category":"Shopping",
            "subcategory":"Clothing, Apparel, & Fashions",
            "type":"Retail Goods"
        }
    ],
    "sg:phone":"+32 15 27 60 80",
    "sg:postcode":"2800",
    "sg:province":"Antwerpen",
    "sg:tags":[
        "-",
        "clothing",
        "child"
    ],
    "wof:name":"Luna",
    "wof:placetype":"venue"
},
  "geometry": {"coordinates":[4.4821147919,51.024105072],"type":"Point"}
}