{
  "type": "Feature",
  "properties": {
    "addr:full":"Elisabeth Willemslaan 57 Haacht Vlaams-Brabant 3150",
    "addr:housenumber":"57",
    "addr:postcode":"3150",
    "addr:street":"Elisabeth Willemslaan",
    "iso:country":"BE",
    "sg:address":"Elisabeth Willemslaan 57",
    "sg:city":"Haacht",
    "sg:orig_category":"Entretien and r\u00e9parations de voitures. V\u00e9hicules automobiles. Stations-service and carburants",
    "sg:phone":"+32 16 60 13 55",
    "sg:postcode":"3150",
    "sg:province":"Vlaams-Brabant",
    "wof:name":"Garage De Clerck",
    "wof:placetype":"venue"
},
  "geometry": {"coordinates":[4.6389708519,50.9561347961],"type":"Point"}
}