{
  "type": "Feature",
  "properties": {
    "iso:country":"BE",
    "sg:address":"Coupl'voie 39",
    "sg:city":"Ronse/renaix",
    "sg:orig_category":"Traitements param\u00e9dicaux",
    "sg:phone":"+32 55 21 15 46",
    "sg:postcode":"9600",
    "sg:province":"Oost-Vlaanderen",
    "wof:name":"Vanliefde A",
    "wof:placetype":"venue"
},
  "geometry": {"coordinates":[3.5946750641,50.7438087463],"type":"Point"}
}