{
  "type": "Feature",
  "properties": {
    "addr:full":"Heidestraat 5 Berlaar Antwerpen 2590",
    "addr:housenumber":"5",
    "addr:postcode":"2590",
    "addr:street":"Heidestraat",
    "iso:country":"BE",
    "sg:address":"Heidestraat 5",
    "sg:city":"Berlaar",
    "sg:orig_category":"Artsen and specialisten",
    "sg:phone":"+32 15 24 97 12",
    "sg:postcode":"2590",
    "sg:province":"Antwerpen",
    "wof:name":"Michel Coenen",
    "wof:placetype":"venue"
},
  "geometry": {"coordinates":[4.6691718102,51.0900497437],"type":"Point"}
}