{
  "type": "Feature",
  "properties": {
    "iso:country":"BE",
    "sg:address":"Nestor De Ti\u00c8restraat 199",
    "sg:city":"Oudenaarde",
    "sg:orig_category":"Alimentation sp\u00e9cialis\u00e9e",
    "sg:phone":"+32 55 30 27 34",
    "sg:postcode":"9700",
    "sg:province":"Oost-Vlaanderen",
    "wof:name":"Den Bascuul",
    "wof:placetype":"venue"
},
  "geometry": {"coordinates":[3.6213009357,50.8693351746],"type":"Point"}
}