{
  "type": "Feature",
  "properties": {
    "iso:country":"BE",
    "sg:address":"Stratem 15",
    "sg:city":"Aalter",
    "sg:classifiers":[
        {
            "category":"Insurance",
            "subcategory":"Life Insurance",
            "type":"Services"
        }
    ],
    "sg:phone":"+32 9 374 60 67",
    "sg:postcode":"9880",
    "sg:province":"Oost-Vlaanderen",
    "sg:tags":[
        "assurance"
    ],
    "wof:name":"Zakenkantoor Houtman",
    "wof:placetype":"venue"
},
  "geometry": {"coordinates":[3.4482300282,51.0872917175],"type":"Point"}
}