{
  "type": "Feature",
  "properties": {
    "addr:full":"Brugsestw 15a Harelbeke West-Vlaanderen 8531",
    "addr:housenumber":"15a",
    "addr:postcode":"8531",
    "addr:street":"Brugsestw",
    "iso:country":"BE",
    "sg:address":"Brugsestw 15a",
    "sg:city":"Harelbeke",
    "sg:classifiers":[
        {
            "category":"Travel",
            "subcategory":"Hotels & Motels",
            "type":"Entertainment"
        }
    ],
    "sg:phone":"+32 56 71 15 36",
    "sg:postcode":"8531",
    "sg:province":"West-Vlaanderen",
    "sg:tags":[
        "hotels",
        "business",
        "restaurant"
    ],
    "wof:name":"Restaurant 't Popelierenhof",
    "wof:placetype":"venue"
},
  "geometry": {"coordinates":[3.3104400635,50.8748130798],"type":"Point"}
}