{
  "type": "Feature",
  "properties": {
    "addr:full":"Chauss\u00e9e De Mons 22 Nivelles Brabant Wallon 1400",
    "addr:housenumber":"22",
    "addr:postcode":"1400",
    "addr:street":"Chausse\u0301E De Mons",
    "iso:country":"BE",
    "sg:address":"Chauss\u00e9e De Mons 22",
    "sg:city":"Nivelles",
    "sg:classifiers":[
        {
            "category":"Home & Garden",
            "subcategory":"Home Furnishings",
            "type":"Retail Goods"
        }
    ],
    "sg:phone":"+32 67 63 96 90",
    "sg:postcode":"1400",
    "sg:province":"Brabant Wallon",
    "sg:tags":[
        "-",
        "furniture"
    ],
    "wof:name":"Bakker L",
    "wof:placetype":"venue"
},
  "geometry": {"coordinates":[4.3078727722,50.5880661011],"type":"Point"}
}