{
  "type": "Feature",
  "properties": {
    "iso:country":"BE",
    "sg:address":"Chemin Coparty 3",
    "sg:city":"Nivelles",
    "sg:orig_category":"Slagers",
    "sg:phone":"+32 67 84 10 82",
    "sg:postcode":"1400",
    "sg:province":"Brabant Wallon",
    "wof:name":"Mic-discount",
    "wof:placetype":"venue"
},
  "geometry": {"coordinates":[4.3354029655,50.5990028381],"type":"Point"}
}