{
  "type": "Feature",
  "properties": {
    "addr:full":"Etikhovestraat 28 Maarkedal Oost-Vlaanderen 9680",
    "addr:housenumber":"28",
    "addr:postcode":"9680",
    "addr:street":"Etikhovestraat",
    "iso:country":"BE",
    "sg:address":"Etikhovestraat 28",
    "sg:city":"Maarkedal",
    "sg:orig_category":"Banken and kredietinstellingen",
    "sg:phone":"+32 55 31 59 20",
    "sg:postcode":"9680",
    "sg:province":"Oost-Vlaanderen",
    "wof:name":"Kbc",
    "wof:placetype":"venue"
},
  "geometry": {"coordinates":[3.6251978874,50.8114929199],"type":"Point"}
}