{
  "type": "Feature",
  "properties": {
    "addr:full":"Koningin Astridlaan 43 Kapellen Antwerpen 2950",
    "addr:housenumber":"43",
    "addr:postcode":"2950",
    "addr:street":"Koningin Astridlaan",
    "iso:country":"BE",
    "sg:address":"Koningin Astridlaan 43",
    "sg:city":"Kapellen",
    "sg:orig_category":"Papierwaren and schoolbenodigdheden Gh",
    "sg:phone":"+32 3 605 63 49",
    "sg:postcode":"2950",
    "sg:province":"Antwerpen",
    "wof:name":"Reduma",
    "wof:placetype":"venue"
},
  "geometry": {"coordinates":[4.4416670799,51.3124275208],"type":"Point"}
}