{
  "type": "Feature",
  "properties": {
    "iso:country":"BE",
    "sg:address":"Oudaenstraat 8",
    "sg:city":"Brecht",
    "sg:orig_category":"Eleveurs and marchands de porcs. Eleveurs de bovins",
    "sg:phone":"+32 3 313 08 00",
    "sg:postcode":"2960",
    "sg:province":"Antwerpen",
    "wof:name":"Joannes Van Dyck",
    "wof:placetype":"venue"
},
  "geometry": {"coordinates":[4.6361508369,51.3607215881],"type":"Point"}
}