{
  "type": "Feature",
  "properties": {
    "iso:country":"BE",
    "sg:address":"Vennestraat 191",
    "sg:city":"Winterslag",
    "sg:orig_category":"Equipement photographique",
    "sg:phone":"+32 89 35 36 06",
    "sg:postcode":"3600",
    "sg:province":"Limburg",
    "wof:name":"Digifot",
    "wof:placetype":"venue"
},
  "geometry": {"coordinates":[5.4907488823,50.9784736633],"type":"Point"}
}