{
  "type": "Feature",
  "properties": {
    "iso:country":"BE",
    "sg:address":"Industrielaan 31",
    "sg:city":"Ieper",
    "sg:orig_category":"Electrom\u00e9nager, t\u00e9l\u00e9visions and radios. Plomberie, chauffage and installations sanitaires. Mat\u00e9riel ",
    "sg:phone":"+32 2 331 03 66",
    "sg:postcode":"8900",
    "sg:province":"West-Vlaanderen",
    "wof:name":"Aldes",
    "wof:placetype":"venue"
},
  "geometry": {"coordinates":[2.8878269196,50.8513641357],"type":"Point"}
}