{
  "type": "Feature",
  "properties": {
    "iso:country":"BE",
    "sg:address":"Rue Du Vigneron 127",
    "sg:city":"Charleroi",
    "sg:orig_category":"Fabrication and montage de mobilier",
    "sg:phone":"+32 71 35 35 67",
    "sg:postcode":"6043",
    "sg:province":"Hainaut",
    "wof:name":"Cuisines Electro-services",
    "wof:placetype":"venue"
},
  "geometry": {"coordinates":[4.4839549065,50.4479637146],"type":"Point"}
}