{
  "type": "Feature",
  "properties": {
    "addr:full":"Chauss\u00c9e De Warterloo 1127 Ukkel/uccle Bruxelles-Capitale 1180",
    "addr:housenumber":"1127",
    "addr:postcode":"1180",
    "addr:street":"Chausse\u0301E De Warterloo;/",
    "iso:country":"BE",
    "sg:address":"Chauss\u00c9e De Warterloo 1127",
    "sg:city":"Ukkel/uccle",
    "sg:classifiers":[
        {
            "category":"Restaurant",
            "type":"Food & Drink"
        }
    ],
    "sg:phone":"+32 2 375 33 17",
    "sg:postcode":"1180",
    "sg:province":"Bruxelles-Capitale",
    "wof:name":"La Table Ronde De Mona",
    "wof:placetype":"venue"
},
  "geometry": {"coordinates":[4.3627800941,50.7902793884],"type":"Point"}
}