{
  "type": "Feature",
  "properties": {
    "iso:country":"BE",
    "sg:address":"Naamsestraat 74",
    "sg:city":"Brussel/bruxelles",
    "sg:orig_category":"Diverse kredietdiensten",
    "sg:postcode":"1000",
    "sg:province":"Bruxelles-Capitale",
    "wof:name":"Bancontact-mister Cash",
    "wof:placetype":"venue"
},
  "geometry": {"coordinates":[4.3611359596,50.8394355774],"type":"Point"}
}