{
  "type": "Feature",
  "properties": {
    "iso:country":"BE",
    "sg:address":"Rue Nalamont 54",
    "sg:city":"Andenne",
    "sg:orig_category":"Travail and traitement du bois",
    "sg:phone":"+32 85 61 11 72",
    "sg:postcode":"5300",
    "sg:province":"Namur",
    "wof:name":"Scierie Havelange",
    "wof:placetype":"venue"
},
  "geometry": {"coordinates":[5.105820179,50.4533081055],"type":"Point"}
}