{
  "type": "Feature",
  "properties": {
    "addr:full":"Avenue Ch. Et L. Godin 2-1 Huy Li\u00e8ge 4500",
    "addr:housenumber":"2-1",
    "addr:postcode":"4500",
    "addr:street":"Avenue Ch. Et L. Godin",
    "iso:country":"BE",
    "sg:address":"Avenue Ch. Et L. Godin 2-1",
    "sg:city":"Huy",
    "sg:classifiers":[
        {
            "category":"Health Services",
            "subcategory":"Dentist",
            "type":"Services"
        }
    ],
    "sg:phone":"+32 85 21 19 46",
    "sg:postcode":"4500",
    "sg:province":"Li\u00e8ge",
    "wof:name":"Delmoiti\u00e9 L",
    "wof:placetype":"venue"
},
  "geometry": {"coordinates":[5.2433071136,50.5226173401],"type":"Point"}
}