{
  "type": "Feature",
  "properties": {
    "iso:country":"BE",
    "sg:address":"Driehoekstraat 69",
    "sg:city":"Haaltert",
    "sg:orig_category":"Sportclubs",
    "sg:phone":"+32 53 83 69 72",
    "sg:postcode":"9451",
    "sg:province":"Oost-Vlaanderen",
    "wof:name":"Synchro Club Aalst",
    "wof:placetype":"venue"
},
  "geometry": {"coordinates":[3.9824500084,50.8868293762],"type":"Point"}
}