{
  "type": "Feature",
  "properties": {
    "addr:full":"Chemin De La Halle 9 Herve Li\u00e8ge 4651",
    "addr:housenumber":"9",
    "addr:postcode":"4651",
    "addr:street":"Chemin De La Halle",
    "iso:country":"BE",
    "sg:address":"Chemin De La Halle 9",
    "sg:city":"Herve",
    "sg:orig_category":"Articles de jardin. P\u00e9pini\u00e9ristes",
    "sg:phone":"+32 87 66 01 42",
    "sg:postcode":"4651",
    "sg:province":"Li\u00e8ge",
    "wof:name":"P\u00c9pini\u00c8re Plateau Herve",
    "wof:placetype":"venue"
},
  "geometry": {"coordinates":[5.7701301575,50.6300735474],"type":"Point"}
}