{
  "type": "Feature",
  "properties": {
    "iso:country":"BE",
    "sg:address":"Louis Schmidtlaan 119",
    "sg:city":"Etterbeek",
    "sg:orig_category":"Banken and kredietinstellingen",
    "sg:phone":"+32 2 736 06 00",
    "sg:postcode":"1040",
    "sg:province":"Bruxelles-Capitale",
    "wof:name":"Fortis",
    "wof:placetype":"venue"
},
  "geometry": {"coordinates":[4.404856205,50.831237793],"type":"Point"}
}