{
  "type": "Feature",
  "properties": {
    "addr:full":"Elegastlaan 2 Schoten Antwerpen 2900",
    "addr:housenumber":"2",
    "addr:postcode":"2900",
    "addr:street":"Elegastlaan",
    "iso:country":"BE",
    "sg:address":"Elegastlaan 2",
    "sg:city":"Schoten",
    "sg:orig_category":"Fotogravure and zetwerk Secretariaatsdiensten",
    "sg:phone":"+32 3 658 33 29",
    "sg:postcode":"2900",
    "sg:province":"Antwerpen",
    "wof:name":"Artwork",
    "wof:placetype":"venue"
},
  "geometry": {"coordinates":[4.5179572105,51.2607765198],"type":"Point"}
}