{
  "type": "Feature",
  "properties": {
    "addr:full":"Bredestraat 26 Gent (oostakker) Oost-Vlaanderen 9041",
    "addr:housenumber":"26",
    "addr:postcode":"9041",
    "addr:street":"Bredestraat",
    "iso:country":"BE",
    "sg:address":"Bredestraat 26",
    "sg:city":"Gent (oostakker)",
    "sg:classifiers":[
        {
            "category":"Bars & Pubs",
            "type":"Food & Drink"
        }
    ],
    "sg:phone":"+32 9 251 45 60",
    "sg:postcode":"9041",
    "sg:province":"Oost-Vlaanderen",
    "wof:name":"Leopold Ii",
    "wof:placetype":"venue"
},
  "geometry": {"coordinates":[3.7663669586,51.1006469727],"type":"Point"}
}