{
  "type": "Feature",
  "properties": {
    "addr:full":"Heirstraat 61 Dendermonde Oost-Vlaanderen 9200",
    "addr:housenumber":"61",
    "addr:postcode":"9200",
    "addr:street":"Heirstraat;Oost-Vlaanderen",
    "iso:country":"BE",
    "sg:address":"Heirstraat 61",
    "sg:city":"Dendermonde",
    "sg:orig_category":"Enseignement maternel and primaire",
    "sg:phone":"+32 52 21 75 27",
    "sg:postcode":"9200",
    "sg:province":"Oost-Vlaanderen",
    "wof:name":"Gemeentel. Lagere School",
    "wof:placetype":"venue"
},
  "geometry": {"coordinates":[4.0616998672,51.0296592712],"type":"Point"}
}