{
  "type": "Feature",
  "properties": {
    "iso:country":"BE",
    "sg:address":"Groeningestraat 36",
    "sg:city":"Kortrijk",
    "sg:orig_category":"Werk and personeelsselectie",
    "sg:phone":"+32 56 25 62 60",
    "sg:postcode":"8500",
    "sg:province":"West-Vlaanderen",
    "wof:name":"Pwa Kortrijk",
    "wof:placetype":"venue"
},
  "geometry": {"coordinates":[3.2700579166,50.8298110962],"type":"Point"}
}