{
  "type": "Feature",
  "properties": {
    "iso:country":"BE",
    "sg:address":"Rue Pirauchamps 9",
    "sg:city":"Assesse",
    "sg:classifiers":[
        {
            "category":"Communications",
            "subcategory":"Film & Video Production",
            "type":"Services"
        }
    ],
    "sg:phone":"+32 83 65 64 03",
    "sg:postcode":"5332",
    "sg:province":"Namur",
    "sg:tags":[
        "platen",
        "cassette",
        "cd's"
    ],
    "wof:name":"Guy Scaillet",
    "wof:placetype":"venue"
},
  "geometry": {"coordinates":[4.9603500366,50.3483772278],"type":"Point"}
}