{
  "type": "Feature",
  "properties": {
    "iso:country":"BE",
    "sg:address":"Rue Joseph Renquin 40",
    "sg:city":"Bastogne",
    "sg:classifiers":[
        {
            "category":"Health Services",
            "subcategory":"Doctor",
            "type":"Services"
        }
    ],
    "sg:phone":"+32 61 21 93 40",
    "sg:postcode":"6600",
    "sg:province":"Luxembourg",
    "sg:tags":[
        "medicinephysicians",
        "surgeon"
    ],
    "wof:name":"Kareh Patrick",
    "wof:placetype":"venue"
},
  "geometry": {"coordinates":[5.7164421082,49.9989776611],"type":"Point"}
}