{
  "type": "Feature",
  "properties": {
    "addr:full":"Kerkhofstraat 173 Boom Antwerpen 2850",
    "addr:housenumber":"173",
    "addr:postcode":"2850",
    "addr:street":"Kerkhofstraat",
    "iso:country":"BE",
    "sg:address":"Kerkhofstraat 173",
    "sg:city":"Boom",
    "sg:classifiers":[
        {
            "category":"Bakery",
            "type":"Food & Drink"
        }
    ],
    "sg:phone":"+32 3 888 06 07",
    "sg:postcode":"2850",
    "sg:province":"Antwerpen",
    "sg:tags":[
        "confectioner",
        "baker"
    ],
    "wof:name":"Cooreman A",
    "wof:placetype":"venue"
},
  "geometry": {"coordinates":[4.3749790192,51.0912322998],"type":"Point"}
}