{
  "type": "Feature",
  "properties": {
    "iso:country":"BE",
    "sg:address":"Diestsebaan 16",
    "sg:city":"Diest (schaffen)",
    "sg:classifiers":[
        {
            "category":"Health Services",
            "subcategory":"Dentist",
            "type":"Services"
        }
    ],
    "sg:phone":"+32 13 33 75 27",
    "sg:postcode":"3290",
    "sg:province":"Vlaams-Brabant",
    "wof:name":"Doucet Mirielle",
    "wof:placetype":"venue"
},
  "geometry": {"coordinates":[5.0825462341,50.9989929199],"type":"Point"}
}