{
  "type": "Feature",
  "properties": {
    "iso:country":"BE",
    "sg:address":"Groenestraat 112",
    "sg:city":"Zedelgem",
    "sg:classifiers":[
        {
            "category":"Professional",
            "subcategory":"Advertising",
            "type":"Services"
        }
    ],
    "sg:phone":"+32 50 24 14 46",
    "sg:postcode":"8210",
    "sg:province":"West-Vlaanderen",
    "sg:tags":[
        "photography"
    ],
    "wof:name":"Zoom Zone!",
    "wof:placetype":"venue"
},
  "geometry": {"coordinates":[3.149285078,51.1318588257],"type":"Point"}
}