{
  "type": "Feature",
  "properties": {
    "addr:full":"Kruishofstraat 257 Box 2 Antwerpen (wilrijk) Antwerpen 2610",
    "addr:housenumber":"257;2",
    "addr:postcode":"2610",
    "addr:street":"Kruishofstraat;Box;Antwerpen",
    "iso:country":"BE",
    "sg:address":"Kruishofstraat 257 Box 2",
    "sg:city":"Antwerpen (wilrijk)",
    "sg:classifiers":[
        {
            "category":"Building & Trades",
            "subcategory":"Cleaning & Sanitation",
            "type":"Services"
        }
    ],
    "sg:phone":"+32 3 297 22 56",
    "sg:postcode":"2610",
    "sg:province":"Antwerpen",
    "sg:tags":[
        "fa\u00e7ade",
        "maintenance"
    ],
    "wof:name":"Jeurissen (bouwonderneming) Bvba",
    "wof:placetype":"venue"
},
  "geometry": {"coordinates":[4.3946051598,51.1691131592],"type":"Point"}
}