{
  "type": "Feature",
  "properties": {
    "iso:country":"BE",
    "sg:address":"Fr\u00e8re-orbanstraat 109",
    "sg:city":"Oostende",
    "sg:classifiers":[
        {
            "category":"Professional",
            "subcategory":"Computer Services",
            "type":"Services"
        }
    ],
    "sg:phone":"+32 59 43 43 01",
    "sg:postcode":"8400",
    "sg:province":"West-Vlaanderen",
    "sg:tags":[
        "-",
        "processing",
        "data",
        "software"
    ],
    "wof:name":"Digital Systems",
    "wof:placetype":"venue"
},
  "geometry": {"coordinates":[2.9132249355,51.2188224792],"type":"Point"}
}