{
  "type": "Feature",
  "properties": {
    "iso:country":"BE",
    "sg:address":"Boulevard Auguste Reyers 109",
    "sg:city":"Schaarbeek/schaerbeek",
    "sg:orig_category":"Mat\u00e9riel scientifique and technique Fab",
    "sg:phone":"+32 2 733 98 11",
    "sg:postcode":"1030",
    "sg:province":"Bruxelles-Capitale",
    "wof:name":"Ista",
    "wof:placetype":"venue"
},
  "geometry": {"coordinates":[4.400867939,50.8507270813],"type":"Point"}
}