{
  "type": "Feature",
  "properties": {
    "addr:full":"Galgestraat 10 Mechelen Antwerpen 2800",
    "addr:housenumber":"10",
    "addr:postcode":"2800",
    "addr:street":"Galgestraat",
    "iso:country":"BE",
    "sg:address":"Galgestraat 10",
    "sg:city":"Mechelen",
    "sg:orig_category":"Instellingen voor mindervalide volwassenen",
    "sg:phone":"+32 15 29 03 60",
    "sg:postcode":"2800",
    "sg:province":"Antwerpen",
    "wof:name":"Logeerhuis Willekom",
    "wof:placetype":"venue"
},
  "geometry": {"coordinates":[4.4685077667,51.0450897217],"type":"Point"}
}