{
  "type": "Feature",
  "properties": {
    "addr:full":"Corbiestraat 39 Mol Antwerpen 2400",
    "addr:housenumber":"39",
    "addr:postcode":"2400",
    "addr:street":"Corbiestraat",
    "iso:country":"BE",
    "sg:address":"Corbiestraat 39",
    "sg:city":"Mol",
    "sg:classifiers":[
        {
            "category":"Cafe",
            "type":"Food & Drink"
        }
    ],
    "sg:phone":"+32 14 31 87 70",
    "sg:postcode":"2400",
    "sg:province":"Antwerpen",
    "sg:tags":[
        "snack-bars"
    ],
    "wof:name":"Nefertete",
    "wof:placetype":"venue"
},
  "geometry": {"coordinates":[5.1167612076,51.1883964539],"type":"Point"}
}