{
  "type": "Feature",
  "properties": {
    "iso:country":"BE",
    "sg:address":"Grand-rue 21",
    "sg:city":"Chatelet",
    "sg:classifiers":[
        {
            "category":"Personal",
            "subcategory":"Beauty Salon",
            "type":"Services"
        }
    ],
    "sg:phone":"+32 71 38 34 36",
    "sg:postcode":"6200",
    "sg:province":"Hainaut",
    "sg:tags":[
        "de",
        "coiffure"
    ],
    "wof:name":"Maria",
    "wof:placetype":"venue"
},
  "geometry": {"coordinates":[4.5273227692,50.4030036926],"type":"Point"}
}