{
  "type": "Feature",
  "properties": {
    "addr:full":"Pont Du Christ 56 Wavre Brabant Wallon 1300",
    "addr:housenumber":"56;1300",
    "addr:street":"Pont Du Christ",
    "iso:country":"BE",
    "sg:address":"Pont Du Christ 56",
    "sg:city":"Wavre",
    "sg:classifiers":[
        {
            "category":"Shopping",
            "subcategory":"Shoes",
            "type":"Retail Goods"
        }
    ],
    "sg:phone":"+32 10 22 70 41",
    "sg:postcode":"1300",
    "sg:province":"Brabant Wallon",
    "sg:tags":[
        "slipper",
        "-"
    ],
    "wof:name":"Libouton Colette Et Martine Sa",
    "wof:placetype":"venue"
},
  "geometry": {"coordinates":[4.608935833,50.716053009],"type":"Point"}
}