{
  "type": "Feature",
  "properties": {
    "iso:country":"BE",
    "sg:address":"Jacquetbosstraat 70bb",
    "sg:city":"Spiere-helkijn/espierres-helchin",
    "sg:orig_category":"Herstellingen and onderhoud van auto's",
    "sg:phone":"+32 56 45 61 14",
    "sg:postcode":"8587",
    "sg:province":"West-Vlaanderen",
    "wof:name":"Garage Delfosse",
    "wof:placetype":"venue"
},
  "geometry": {"coordinates":[3.3426630497,50.728263855],"type":"Point"}
}