{
  "type": "Feature",
  "properties": {
    "iso:country":"BE",
    "sg:address":"Klein Antwerpenstraat 62",
    "sg:city":"Lebbeke",
    "sg:orig_category":"Activit\u00e9s r\u00e9cr\u00e9atives diverses",
    "sg:phone":"+32 52 35 02 28",
    "sg:postcode":"9280",
    "sg:province":"Oost-Vlaanderen",
    "wof:name":"The Moonrakers",
    "wof:placetype":"venue"
},
  "geometry": {"coordinates":[4.1562399864,50.9898986816],"type":"Point"}
}