{
  "type": "Feature",
  "properties": {
    "addr:full":"Nieuwpoortsesteenweg 256 Oostende West-Vlaanderen 8400",
    "addr:housenumber":"256",
    "addr:postcode":"8400",
    "addr:street":"Nieuwpoortsesteenweg",
    "iso:country":"BE",
    "sg:address":"Nieuwpoortsesteenweg 256",
    "sg:city":"Oostende",
    "sg:orig_category":"Alimentation sp\u00e9cialis\u00e9e. Cr\u00e9meries",
    "sg:phone":"+32 59 70 00 94",
    "sg:postcode":"8400",
    "sg:province":"West-Vlaanderen",
    "wof:name":"Toespieze",
    "wof:placetype":"venue"
},
  "geometry": {"coordinates":[2.891315937,51.2168045044],"type":"Point"}
}