{
  "type": "Feature",
  "properties": {
    "addr:full":"Rue De La Station 1 Linkebeek Vlaams-Brabant 1630",
    "addr:housenumber":"1",
    "addr:postcode":"1630",
    "addr:street":"Rue De La Station",
    "iso:country":"BE",
    "sg:address":"Rue De La Station 1",
    "sg:city":"Linkebeek",
    "sg:classifiers":[
        {
            "category":"Home & Garden",
            "subcategory":"Garden Supply",
            "type":"Retail Goods"
        }
    ],
    "sg:phone":"+32 2 380 77 89",
    "sg:postcode":"1630",
    "sg:province":"Vlaams-Brabant",
    "wof:name":"Indemans Christian Sprl",
    "wof:placetype":"venue"
},
  "geometry": {"coordinates":[4.3383078575,50.7738304138],"type":"Point"}
}