{
  "type": "Feature",
  "properties": {
    "addr:full":"Tomberg 2 Zaventem Vlaams-Brabant 1930",
    "addr:housenumber":"2",
    "addr:postcode":"1930",
    "addr:street":"Tomberg",
    "iso:country":"BE",
    "sg:address":"Tomberg 2",
    "sg:city":"Zaventem",
    "sg:orig_category":"Cr\u00e9meries",
    "sg:phone":"+32 2 725 19 63",
    "sg:postcode":"1930",
    "sg:province":"Vlaams-Brabant",
    "wof:name":"Marie Janssens",
    "wof:placetype":"venue"
},
  "geometry": {"coordinates":[4.4822640419,50.8784141541],"type":"Point"}
}