{
  "type": "Feature",
  "properties": {
    "iso:country":"BE",
    "sg:address":"Zuidmoerstraat 21",
    "sg:city":"Eeklo",
    "sg:classifiers":[
        {
            "category":"Food & Beverages",
            "subcategory":"Fruits & Vegetables",
            "type":"Retail Goods"
        }
    ],
    "sg:phone":"+32 9 377 52 72",
    "sg:postcode":"9900",
    "sg:province":"Oost-Vlaanderen",
    "sg:tags":[
        "-"
    ],
    "wof:name":"Eggermont G",
    "wof:placetype":"venue"
},
  "geometry": {"coordinates":[3.5726530552,51.1800003052],"type":"Point"}
}