{
  "type": "Feature",
  "properties": {
    "iso:country":"BE",
    "sg:address":"Stadsomvaart 11",
    "sg:city":"Hasselt",
    "sg:classifiers":[
        {
            "category":"Health Services",
            "subcategory":"Doctor",
            "type":"Services"
        }
    ],
    "sg:phone":"+32 11 30 90 46",
    "sg:postcode":"3500",
    "sg:province":"Limburg",
    "sg:tags":[
        "medicinephysicians",
        "surgeon"
    ],
    "wof:name":"Dewandre J",
    "wof:placetype":"venue"
},
  "geometry": {"coordinates":[5.3415780067,50.9264144897],"type":"Point"}
}