{
  "type": "Feature",
  "properties": {
    "addr:full":"Kleine Kraaiwijk 14 Antwerpen Antwerpen 2000",
    "addr:housenumber":"14",
    "addr:postcode":"2000",
    "addr:street":"Kleine Kraaiwijk",
    "iso:country":"BE",
    "sg:address":"Kleine Kraaiwijk 14",
    "sg:city":"Antwerpen",
    "sg:classifiers":[
        {
            "category":"Personal",
            "subcategory":"Tattoo Parlor",
            "type":"Services"
        }
    ],
    "sg:phone":"+32 3 231 38 14",
    "sg:postcode":"2000",
    "sg:province":"Antwerpen",
    "sg:tags":[
        "tattooists"
    ],
    "wof:name":"Tattoo Alberto Vzw",
    "wof:placetype":"venue"
},
  "geometry": {"coordinates":[4.4007601738,51.2244415283],"type":"Point"}
}