{
  "type": "Feature",
  "properties": {
    "iso:country":"BE",
    "sg:address":"Rue Jean Mintens 7",
    "sg:city":"Genappe",
    "sg:classifiers":[
        {
            "category":"Professional",
            "subcategory":"Business Services",
            "type":"Services"
        }
    ],
    "sg:phone":"+32 67 78 07 08",
    "sg:postcode":"1470",
    "sg:province":"Brabant Wallon",
    "sg:tags":[
        "aux",
        "diver",
        "entreprises"
    ],
    "wof:name":"Bureau Monautopole",
    "wof:placetype":"venue"
},
  "geometry": {"coordinates":[4.4515790939,50.6101455688],"type":"Point"}
}