{
  "type": "Feature",
  "properties": {
    "addr:full":"Hofstraat 37ba Dendermonde Oost-Vlaanderen 9200",
    "addr:housenumber":"37ba",
    "addr:postcode":"9200",
    "addr:street":"Hofstraat;Oost-Vlaanderen",
    "iso:country":"BE",
    "sg:address":"Hofstraat 37ba",
    "sg:city":"Dendermonde",
    "sg:orig_category":"Enseignement maternel and primaire",
    "sg:phone":"+32 52 21 04 58",
    "sg:postcode":"9200",
    "sg:province":"Oost-Vlaanderen",
    "wof:name":"Vrije Kleuterschool",
    "wof:placetype":"venue"
},
  "geometry": {"coordinates":[4.050924778,51.022644043],"type":"Point"}
}