{
  "type": "Feature",
  "properties": {
    "addr:full":"Rembert Dodoensstraat 1 Mechelen Antwerpen 2800",
    "addr:housenumber":"1",
    "addr:postcode":"2800",
    "addr:street":"Rembert Dodoensstraat",
    "iso:country":"BE",
    "sg:address":"Rembert Dodoensstraat 1",
    "sg:city":"Mechelen",
    "sg:classifiers":[
        {
            "category":"Cafe",
            "type":"Food & Drink"
        }
    ],
    "sg:phone":"+32 15 41 95 35",
    "sg:postcode":"2800",
    "sg:province":"Antwerpen",
    "sg:tags":[
        "caf\u00e9s"
    ],
    "wof:name":"Adelheid Biesen",
    "wof:placetype":"venue"
},
  "geometry": {"coordinates":[4.4709410667,51.0199508667],"type":"Point"}
}