{
  "type": "Feature",
  "properties": {
    "addr:full":"Dr\u00c8ve Du S\u00c9n\u00c9chal 20 Ukkel/uccle Bruxelles-Capitale 1180",
    "addr:housenumber":"20",
    "addr:postcode":"1180",
    "addr:street":"Dre\u0300Ve Du Se\u0301Ne\u0301Chal;/",
    "iso:country":"BE",
    "sg:address":"Dr\u00c8ve Du S\u00c9n\u00c9chal 20",
    "sg:city":"Ukkel/uccle",
    "sg:orig_category":"D\u00e9corateurs d'int\u00e9rieur",
    "sg:phone":"+32 2 375 69 76",
    "sg:postcode":"1180",
    "sg:province":"Bruxelles-Capitale",
    "wof:name":"M. Rommelaere",
    "wof:placetype":"venue"
},
  "geometry": {"coordinates":[4.3744959831,50.7953071594],"type":"Point"}
}