{
  "type": "Feature",
  "properties": {
    "addr:full":"Leeuweriksstraat 18 Haacht Vlaams-Brabant 3150",
    "addr:housenumber":"18",
    "addr:postcode":"3150",
    "addr:street":"Leeuweriksstraat",
    "iso:country":"BE",
    "sg:address":"Leeuweriksstraat 18",
    "sg:city":"Haacht",
    "sg:classifiers":[
        {
            "category":"Arena",
            "subcategory":"Sports Club",
            "type":"Entertainment"
        }
    ],
    "sg:phone":"+32 16 60 89 10",
    "sg:postcode":"3150",
    "sg:province":"Vlaams-Brabant",
    "sg:tags":[
        "de"
    ],
    "wof:name":"V.c. Olympia Haacht",
    "wof:placetype":"venue"
},
  "geometry": {"coordinates":[4.6440248489,50.9712753296],"type":"Point"}
}