{
  "type": "Feature",
  "properties": {
    "addr:full":"Rue Du Progr\u00e8s 225 Bruxelles (schaerbeek) Bruxelles-Capitale 1030",
    "addr:housenumber":"225",
    "addr:postcode":"1030",
    "addr:street":"Rue Du Progre\u0300S",
    "iso:country":"BE",
    "sg:address":"Rue Du Progr\u00e8s 225",
    "sg:city":"Bruxelles (schaerbeek)",
    "sg:classifiers":[
        {
            "category":"Organizations",
            "subcategory":"Community Association",
            "type":"Services"
        }
    ],
    "sg:phone":"+32 2 201 15 10",
    "sg:postcode":"1030",
    "sg:province":"Bruxelles-Capitale",
    "sg:tags":[
        "cultural"
    ],
    "wof:name":"Ksj-ksa-vksj-landelijk Verbond Vzw",
    "wof:placetype":"venue"
},
  "geometry": {"coordinates":[4.3616709709,50.8633804321],"type":"Point"}
}