{
  "type": "Feature",
  "properties": {
    "addr:full":"Boulevard G. Van Haelen 94 Bruxelles (forest) Bruxelles-Capitale 1190",
    "addr:housenumber":"94",
    "addr:postcode":"1190",
    "addr:street":"Boulevard G. Van Haelen",
    "iso:country":"BE",
    "sg:address":"Boulevard G. Van Haelen 94",
    "sg:city":"Bruxelles (forest)",
    "sg:classifiers":[
        {
            "category":"Professional",
            "subcategory":"Accounting & Tax Preparation",
            "type":"Services"
        }
    ],
    "sg:phone":"+32 2 343 21 34",
    "sg:postcode":"1190",
    "sg:province":"Bruxelles-Capitale",
    "sg:tags":[
        "accountant"
    ],
    "wof:name":"Malrain E",
    "wof:placetype":"venue"
},
  "geometry": {"coordinates":[4.3298220634,50.822052002],"type":"Point"}
}