{
  "type": "Feature",
  "properties": {
    "iso:country":"BE",
    "sg:address":"Eugeen Verbiststraat 31",
    "sg:city":"Schoten",
    "sg:orig_category":"Boekhouders",
    "sg:phone":"+32 3 647 02 35",
    "sg:postcode":"2900",
    "sg:province":"Antwerpen",
    "wof:name":"Ronald Laureys",
    "wof:placetype":"venue"
},
  "geometry": {"coordinates":[4.4660458565,51.2523994446],"type":"Point"}
}