{
  "type": "Feature",
  "properties": {
    "iso:country":"BE",
    "sg:address":"Rue Des Petits-sarts 34",
    "sg:city":"Seraing",
    "sg:classifiers":[
        {
            "category":"Food & Beverages",
            "subcategory":"Fruits & Vegetables",
            "type":"Retail Goods"
        }
    ],
    "sg:phone":"+32 4 338 46 15",
    "sg:postcode":"4100",
    "sg:province":"Li\u00e8ge",
    "sg:tags":[
        "l\u00e9gumes"
    ],
    "wof:name":"Proto M+jacquemotte M",
    "wof:placetype":"venue"
},
  "geometry": {"coordinates":[5.497918129,50.5851516724],"type":"Point"}
}