{
  "type": "Feature",
  "properties": {
    "iso:country":"BE",
    "sg:address":"Bastelare 114",
    "sg:city":"Lochristi",
    "sg:orig_category":"Projectontwikkelaars",
    "sg:phone":"+32 9 355 30 99",
    "sg:postcode":"9080",
    "sg:province":"Oost-Vlaanderen",
    "wof:name":"Greneda",
    "wof:placetype":"venue"
},
  "geometry": {"coordinates":[3.8854379654,51.0957946777],"type":"Point"}
}