{
  "type": "Feature",
  "properties": {
    "addr:full":"Pastoor Claeysstraat 10 Dendermonde (sint-gillis-bij-dendermonde) Oost-Vlaanderen 9200",
    "addr:housenumber":"10",
    "addr:postcode":"9200",
    "addr:street":"Pastoor Claeysstraat",
    "iso:country":"BE",
    "sg:address":"Pastoor Claeysstraat 10",
    "sg:city":"Dendermonde (sint-gillis-bij-dendermonde)",
    "sg:classifiers":[
        {
            "category":"Utilities",
            "subcategory":"Telephone",
            "type":"Services"
        }
    ],
    "sg:phone":"+32 52 34 55 04",
    "sg:postcode":"9200",
    "sg:province":"Oost-Vlaanderen",
    "sg:tags":[
        "-",
        "internet"
    ],
    "wof:name":"Itbizz Networks Bvba",
    "wof:placetype":"venue"
},
  "geometry": {"coordinates":[4.1147651672,51.0215644836],"type":"Point"}
}