{
  "type": "Feature",
  "properties": {
    "iso:country":"BE",
    "sg:address":"Koningin Fabiolastraat 41",
    "sg:city":"Wevelgem",
    "sg:orig_category":"RESTAURANTS: SALLES DE CONF\u00c9RENCES AND DE R\u00c9CEPTIONS. CATERING AND ORGANISATION DE F\u00caTES",
    "sg:phone":"+32 56 40 04 76",
    "sg:postcode":"8560",
    "sg:province":"West-Vlaanderen",
    "wof:name":"De Gouden Kroon",
    "wof:placetype":"venue"
},
  "geometry": {"coordinates":[3.2022910118,50.8404197693],"type":"Point"}
}