{
  "type": "Feature",
  "properties": {
    "addr:full":"Duinkerkelaan 60b1 De Panne West-Vlaanderen 8660",
    "addr:housenumber":"60b1",
    "addr:postcode":"8660",
    "addr:street":"Duinkerkelaan",
    "iso:country":"BE",
    "sg:address":"Duinkerkelaan 60b1",
    "sg:city":"De Panne",
    "sg:orig_category":"Herstelling horloges and juwelen Juwelen and horloges",
    "sg:phone":"+32 58 42 13 33",
    "sg:postcode":"8660",
    "sg:province":"West-Vlaanderen",
    "wof:name":"Geert Bonj\u00c9",
    "wof:placetype":"venue"
},
  "geometry": {"coordinates":[2.5871989727,51.1015739441],"type":"Point"}
}