{
  "type": "Feature",
  "properties": {
    "addr:full":"Rue Saint-bernard 74 Sint-gillis/saint-gilles Bruxelles-Capitale 1060",
    "addr:housenumber":"74",
    "addr:postcode":"1060",
    "addr:street":"Rue Saint-Bernard",
    "iso:country":"BE",
    "sg:address":"Rue Saint-bernard 74",
    "sg:city":"Sint-gillis/saint-gilles",
    "sg:orig_category":"Artistes ind\u00e9pendants. Architectes",
    "sg:phone":"+32 2 537 82 91",
    "sg:postcode":"1060",
    "sg:province":"Bruxelles-Capitale",
    "wof:name":"Pierre-paul Bogaert",
    "wof:placetype":"venue"
},
  "geometry": {"coordinates":[4.3533678055,50.8280487061],"type":"Point"}
}