{
  "type": "Feature",
  "properties": {
    "iso:country":"BE",
    "sg:address":"Rue Du Rossignol 7",
    "sg:city":"Seneffe",
    "sg:orig_category":"Afbraak- and draineerwerken Rundveehouders",
    "sg:phone":"+32 64 54 15 33",
    "sg:postcode":"7180",
    "sg:province":"Hainaut",
    "wof:name":"Chapelle",
    "wof:placetype":"venue"
},
  "geometry": {"coordinates":[4.2748570442,50.5157203674],"type":"Point"}
}