{
  "type": "Feature",
  "properties": {
    "iso:country":"BE",
    "sg:address":"Rue De La Libert\u00c9 21",
    "sg:city":"Li\u00c8ge",
    "sg:orig_category":"Artsen and specialisten",
    "sg:phone":"+32 4 342 45 70",
    "sg:postcode":"4020",
    "sg:province":"Li\u00e8ge",
    "wof:name":"Martine Heinz",
    "wof:placetype":"venue"
},
  "geometry": {"coordinates":[5.5864219666,50.6399230957],"type":"Point"}
}