{
  "type": "Feature",
  "properties": {
    "addr:full":"Rue De Huy 2 Waremme Li\u00e8ge 4300",
    "addr:housenumber":"2",
    "addr:postcode":"4300",
    "addr:street":"Rue De Huy",
    "iso:country":"BE",
    "sg:address":"Rue De Huy 2",
    "sg:city":"Waremme",
    "sg:classifiers":[
        {
            "category":"Food & Beverages",
            "subcategory":"Chocolate",
            "type":"Retail Goods"
        }
    ],
    "sg:phone":"+32 19 32 57 47",
    "sg:postcode":"4300",
    "sg:province":"Li\u00e8ge",
    "sg:tags":[
        "confectionery",
        "-"
    ],
    "wof:name":"Leonidas",
    "wof:placetype":"venue"
},
  "geometry": {"coordinates":[5.2525658607,50.6952056885],"type":"Point"}
}