{
  "type": "Feature",
  "properties": {
    "addr:full":"Rue Du Dahlia 30 Schaarbeek/schaerbeek Bruxelles-Capitale 1030",
    "addr:housenumber":"30",
    "addr:postcode":"1030",
    "addr:street":"Rue Du Dahlia",
    "iso:country":"BE",
    "sg:address":"Rue Du Dahlia 30",
    "sg:city":"Schaarbeek/schaerbeek",
    "sg:orig_category":"Parfumeries",
    "sg:phone":"+32 2 241 27 97",
    "sg:postcode":"1030",
    "sg:province":"Bruxelles-Capitale",
    "wof:name":"Claude Verbeeck",
    "wof:placetype":"venue"
},
  "geometry": {"coordinates":[4.3839149475,50.8727760315],"type":"Point"}
}