{
  "type": "Feature",
  "properties": {
    "iso:country":"BE",
    "sg:address":"Shopping Center 9",
    "sg:city":"Renaix",
    "sg:classifiers":[
        {
            "category":"Shopping",
            "subcategory":"Optician",
            "type":"Retail Goods"
        }
    ],
    "sg:phone":"+32 55 21 91 06",
    "sg:postcode":"9600",
    "sg:province":"Oost-Vlaanderen",
    "sg:tags":[
        "-"
    ],
    "wof:name":"Dhondt K",
    "wof:placetype":"venue"
},
  "geometry": {"coordinates":[3.5993049145,50.7470397949],"type":"Point"}
}