{
  "type": "Feature",
  "properties": {
    "addr:full":"Rue Des Fran\u00e7ais 1a Les Bons Villers (frasnes-lez-gosselies) Hainaut 6210",
    "addr:housenumber":"1a",
    "addr:postcode":"6210",
    "addr:street":"Rue Des Franc\u0327Ais",
    "iso:country":"BE",
    "sg:address":"Rue Des Fran\u00e7ais 1a",
    "sg:city":"Les Bons Villers (frasnes-lez-gosselies)",
    "sg:classifiers":[
        {
            "category":"Real Estate",
            "subcategory":"Architect",
            "type":"Services"
        }
    ],
    "sg:phone":"+32 71 85 15 68",
    "sg:postcode":"6210",
    "sg:province":"Hainaut",
    "wof:name":"Vassart M",
    "wof:placetype":"venue"
},
  "geometry": {"coordinates":[4.4511561394,50.5378227234],"type":"Point"}
}