{
  "type": "Feature",
  "properties": {
    "addr:full":"Dorpsplein 0 Anzegem West-Vlaanderen 8570",
    "addr:housenumber":"0",
    "addr:postcode":"8570",
    "addr:street":"Dorpsplein",
    "iso:country":"BE",
    "sg:address":"Dorpsplein 0",
    "sg:city":"Anzegem",
    "sg:classifiers":[
        {
            "category":"Health Services",
            "subcategory":"Nursing And Care Facility",
            "type":"Services"
        }
    ],
    "sg:phone":"+32 56 69 44 40",
    "sg:postcode":"8570",
    "sg:province":"West-Vlaanderen",
    "sg:tags":[
        "public"
    ],
    "wof:name":"Gemeentebestuur",
    "wof:placetype":"venue"
},
  "geometry": {"coordinates":[3.4805450439,50.8329315186],"type":"Point"}
}