{
  "type": "Feature",
  "properties": {
    "iso:country":"BE",
    "sg:address":"'t Walletje 1",
    "sg:city":"Knokke-heist (westkapelle)",
    "sg:classifiers":[
        {
            "category":"Retail",
            "subcategory":"Auto Repair",
            "type":"Services"
        }
    ],
    "sg:phone":"+32 50 61 33 41",
    "sg:postcode":"8300",
    "sg:province":"West-Vlaanderen",
    "sg:tags":[
        "garage"
    ],
    "wof:name":"Buyck Ludo",
    "wof:placetype":"venue"
},
  "geometry": {"coordinates":[3.2903749943,51.3231391907],"type":"Point"}
}