{
  "type": "Feature",
  "properties": {
    "iso:country":"BE",
    "sg:address":"Brusselsesteenweg 624",
    "sg:city":"Meerbeke",
    "sg:classifiers":[
        {
            "category":"Farming",
            "subcategory":"Farm",
            "type":"Manufacturing & Wholesale Goods"
        }
    ],
    "sg:phone":"+32 69 21 00 85",
    "sg:postcode":"9402",
    "sg:province":"Oost-Vlaanderen",
    "sg:tags":[
        "horticulture",
        "agriculture",
        "livestock"
    ],
    "wof:name":"Escaut Silos Sa",
    "wof:placetype":"venue"
},
  "geometry": {"coordinates":[3.4192149639,50.6428985596],"type":"Point"}
}