{
  "type": "Feature",
  "properties": {
    "addr:full":"Wolfsdonksesteenweg 6 Herselt Antwerpen 2230",
    "addr:housenumber":"6",
    "addr:postcode":"2230",
    "addr:street":"Wolfsdonksesteenweg",
    "iso:country":"BE",
    "sg:address":"Wolfsdonksesteenweg 6",
    "sg:city":"Herselt",
    "sg:orig_category":"Caf\u00e9s Sportterreinen and installaties behalve sportcentra",
    "sg:phone":"+32 14 54 44 87",
    "sg:postcode":"2230",
    "sg:province":"Antwerpen",
    "wof:name":"Delen's Bowling",
    "wof:placetype":"venue"
},
  "geometry": {"coordinates":[4.8814191818,51.0518341064],"type":"Point"}
}