{
  "type": "Feature",
  "properties": {
    "iso:country":"BE",
    "sg:address":"Oostkade 64",
    "sg:city":"Zelzate",
    "sg:classifiers":[
        {
            "category":"Personal",
            "subcategory":"Beauty Salon",
            "type":"Services"
        }
    ],
    "sg:phone":"+32 9 345 52 99",
    "sg:postcode":"9060",
    "sg:province":"Oost-Vlaanderen",
    "sg:tags":[
        "lady",
        "-",
        "hairdressing"
    ],
    "wof:name":"Danschutter M",
    "wof:placetype":"venue"
},
  "geometry": {"coordinates":[3.8100678921,51.1961936951],"type":"Point"}
}