{
  "type": "Feature",
  "properties": {
    "iso:country":"BE",
    "sg:address":"K. Boudewijnstraat 11",
    "sg:city":"Ingelmunster",
    "sg:classifiers":[
        {
            "category":"Personal",
            "subcategory":"Beauty Salon",
            "type":"Services"
        }
    ],
    "sg:phone":"+32 51 30 86 03",
    "sg:postcode":"8770",
    "sg:province":"West-Vlaanderen",
    "sg:tags":[
        "lady",
        "-",
        "hairdressing"
    ],
    "wof:name":"Coiffure Marlou",
    "wof:placetype":"venue"
},
  "geometry": {"coordinates":[3.249268055,50.9220695496],"type":"Point"}
}