{
  "type": "Feature",
  "properties": {
    "iso:country":"BE",
    "sg:address":"Basseveldestraat 13",
    "sg:city":"Assenede",
    "sg:orig_category":"Installation de menuiserie en bois and plastique",
    "sg:phone":"+32 9 373 89 50",
    "sg:postcode":"9961",
    "sg:province":"Oost-Vlaanderen",
    "wof:name":"Mario Malot",
    "wof:placetype":"venue"
},
  "geometry": {"coordinates":[3.7327470779,51.2353019714],"type":"Point"}
}