{
  "type": "Feature",
  "properties": {
    "iso:country":"BE",
    "sg:address":"Rue Jules Tonneau 7",
    "sg:city":"Namur",
    "sg:orig_category":"Rev\u00eatements pour sols and murs",
    "sg:phone":"+32 81 73 73 03",
    "sg:postcode":"5001",
    "sg:province":"Namur",
    "wof:name":"Francis Robin",
    "wof:placetype":"venue"
},
  "geometry": {"coordinates":[4.8257050514,50.4722557068],"type":"Point"}
}