{
  "type": "Feature",
  "properties": {
    "iso:country":"BE",
    "sg:address":"Daelemveld 1002",
    "sg:city":"Herk-de-stad",
    "sg:orig_category":"Diverse voedingsmiddelen Gh",
    "sg:phone":"+32 13 55 31 18",
    "sg:postcode":"3540",
    "sg:province":"Limburg",
    "wof:name":"Kesteloot",
    "wof:placetype":"venue"
},
  "geometry": {"coordinates":[5.1723809242,50.9441719055],"type":"Point"}
}