{
  "type": "Feature",
  "properties": {
    "iso:country":"BE",
    "sg:address":"Parkstraat 62",
    "sg:city":"Boom",
    "sg:classifiers":[
        {
            "category":"Cafe",
            "type":"Food & Drink"
        }
    ],
    "sg:phone":"+32 3 844 59 45",
    "sg:postcode":"2850",
    "sg:province":"Antwerpen",
    "sg:tags":[
        "snack-bars"
    ],
    "wof:name":"Snackske (het)",
    "wof:placetype":"venue"
},
  "geometry": {"coordinates":[4.3701100349,51.0975494385],"type":"Point"}
}