{
  "type": "Feature",
  "properties": {
    "iso:country":"BE",
    "sg:address":"Kaprijkstraat 14",
    "sg:city":"Kaprijke (lembeke)",
    "sg:classifiers":[
        {
            "category":"Building & Trades",
            "subcategory":"Electrical",
            "type":"Services"
        }
    ],
    "sg:phone":"+32 9 378 02 58",
    "sg:postcode":"9971",
    "sg:province":"Oost-Vlaanderen",
    "sg:tags":[
        "electric",
        "-",
        "housewiring",
        "contractor"
    ],
    "wof:name":"Debruyne J",
    "wof:placetype":"venue"
},
  "geometry": {"coordinates":[3.6469669342,51.2003440857],"type":"Point"}
}