{
  "type": "Feature",
  "properties": {
    "addr:full":"Oudstrijdersstraat 23 Wevelgem West-Vlaanderen 8560",
    "addr:housenumber":"23",
    "addr:postcode":"8560",
    "addr:street":"Oudstrijdersstraat",
    "iso:country":"BE",
    "sg:address":"Oudstrijdersstraat 23",
    "sg:city":"Wevelgem",
    "sg:orig_category":"Elektrische installaties voor woningen",
    "sg:phone":"+32 56 40 37 10",
    "sg:postcode":"8560",
    "sg:province":"West-Vlaanderen",
    "wof:name":"E.v.s.",
    "wof:placetype":"venue"
},
  "geometry": {"coordinates":[3.1702339649,50.8215332031],"type":"Point"}
}