{
  "type": "Feature",
  "properties": {
    "addr:full":"Chemin Des Serres 3ba Ath Hainaut 7802",
    "addr:housenumber":"3ba",
    "addr:postcode":"7802",
    "addr:street":"Chemin Des Serres",
    "iso:country":"BE",
    "sg:address":"Chemin Des Serres 3ba",
    "sg:city":"Ath",
    "sg:orig_category":"Enseignement maternel and primaire",
    "sg:phone":"+32 68 28 10 43",
    "sg:postcode":"7802",
    "sg:province":"Hainaut",
    "wof:name":"Ecole Fond. Communale",
    "wof:placetype":"venue"
},
  "geometry": {"coordinates":[3.7527279854,50.5938110352],"type":"Point"}
}