{
  "type": "Feature",
  "properties": {
    "iso:country":"BE",
    "sg:address":"Rue Simonis 17",
    "sg:city":"Bruxelles (saint-gilles)",
    "sg:classifiers":[
        {
            "category":"Professional",
            "subcategory":"Management & Consulting",
            "type":"Services"
        }
    ],
    "sg:phone":"+32 2 533 94 00",
    "sg:postcode":"1060",
    "sg:province":"Bruxelles-Capitale",
    "sg:tags":[
        "consultant",
        "agency",
        "advertising"
    ],
    "wof:name":"Pharma Sales Sa",
    "wof:placetype":"venue"
},
  "geometry": {"coordinates":[4.3575658798,50.8268699646],"type":"Point"}
}