{
  "type": "Feature",
  "properties": {
    "addr:full":"Rue De La Praie 44 Ham-sur-heure-nalinnes Hainaut 6120",
    "addr:housenumber":"44",
    "addr:postcode":"6120",
    "addr:street":"Rue De La Praie;Hainaut",
    "iso:country":"BE",
    "sg:address":"Rue De La Praie 44",
    "sg:city":"Ham-sur-heure-nalinnes",
    "sg:orig_category":"Plomberie, chauffage and installations sanitaires",
    "sg:phone":"+32 71 21 37 27",
    "sg:postcode":"6120",
    "sg:province":"Hainaut",
    "wof:name":"Dominique Gagliardini",
    "wof:placetype":"venue"
},
  "geometry": {"coordinates":[4.3872900009,50.3219146729],"type":"Point"}
}