{
  "type": "Feature",
  "properties": {
    "iso:country":"BE",
    "sg:address":"Alpenroosstraat 44",
    "sg:city":"Berlaar",
    "sg:classifiers":[
        {
            "category":"Autos & Motor Vehicles",
            "subcategory":"Fuel & Gas Station",
            "type":"Retail Goods"
        }
    ],
    "sg:phone":"+32 3 482 26 25",
    "sg:postcode":"2590",
    "sg:province":"Antwerpen",
    "sg:tags":[
        "stations-service",
        "carburants"
    ],
    "wof:name":"Joan Van Strydonck",
    "wof:placetype":"venue"
},
  "geometry": {"coordinates":[4.6533908844,51.1202468872],"type":"Point"}
}