{
  "type": "Feature",
  "properties": {
    "iso:country":"BE",
    "sg:address":"Burg-reuland 56",
    "sg:city":"Burg-reuland",
    "sg:orig_category":"Gespecialiseerde niet-residenti\u00eble bouw",
    "sg:phone":"+32 80 32 95 98",
    "sg:postcode":"4790",
    "sg:province":"Li\u00e8ge",
    "wof:name":"Heindrichs",
    "wof:placetype":"venue"
},
  "geometry": {"coordinates":[6.1315770149,50.1943702698],"type":"Point"}
}