{
  "type": "Feature",
  "properties": {
    "addr:full":"Poperingseweg 226 Ieper West-Vlaanderen 8908",
    "addr:housenumber":"226",
    "addr:postcode":"8908",
    "addr:street":"Poperingseweg",
    "iso:country":"BE",
    "sg:address":"Poperingseweg 226",
    "sg:city":"Ieper",
    "sg:orig_category":"Decoratiestoffen and buitenhuistextiel Fab",
    "sg:phone":"+32 57 20 01 14",
    "sg:postcode":"8908",
    "sg:province":"West-Vlaanderen",
    "wof:name":"Kestelyn",
    "wof:placetype":"venue"
},
  "geometry": {"coordinates":[2.8233549595,50.8541069031],"type":"Point"}
}