{
  "type": "Feature",
  "properties": {
    "iso:country":"BE",
    "sg:address":"Avenue Henry Dunant 11b12",
    "sg:city":"Evere/evere",
    "sg:orig_category":"Installation \u00e9lectrique r\u00e9sidentielle",
    "sg:phone":"+32 2 726 19 74",
    "sg:postcode":"1140",
    "sg:province":"Bruxelles-Capitale",
    "wof:name":"Jmg Concept",
    "wof:placetype":"venue"
},
  "geometry": {"coordinates":[4.4113202095,50.8628883362],"type":"Point"}
}