{
  "type": "Feature",
  "properties": {
    "addr:full":"Terwilgenstraat 12 Deinze Oost-Vlaanderen 9800",
    "addr:housenumber":"12",
    "addr:postcode":"9800",
    "addr:street":"Terwilgenstraat",
    "iso:country":"BE",
    "sg:address":"Terwilgenstraat 12",
    "sg:city":"Deinze",
    "sg:orig_category":"Kapsalons",
    "sg:phone":"+32 9 386 83 02",
    "sg:postcode":"9800",
    "sg:province":"Oost-Vlaanderen",
    "wof:name":"Gerty Lavent",
    "wof:placetype":"venue"
},
  "geometry": {"coordinates":[3.530174017,50.9863166809],"type":"Point"}
}