{
  "type": "Feature",
  "properties": {
    "iso:country":"BE",
    "sg:address":"Boulevard Du Ch\u00c2teau 11",
    "sg:city":"Ath",
    "sg:classifiers":[
        {
            "category":"Insurance",
            "subcategory":"Life Insurance",
            "type":"Services"
        }
    ],
    "sg:phone":"+32 68 28 34 25",
    "sg:postcode":"7800",
    "sg:province":"Hainaut",
    "sg:tags":[
        "assurance"
    ],
    "wof:name":"Bureau Vandenbulcke",
    "wof:placetype":"venue"
},
  "geometry": {"coordinates":[3.7743010521,50.6318321228],"type":"Point"}
}