{
  "type": "Feature",
  "properties": {
    "iso:country":"BE",
    "sg:address":"Industrieweg 11-12",
    "sg:city":"Dendermonde",
    "sg:orig_category":"Transports routiers de marchandises",
    "sg:phone":"+32 52 22 25 60",
    "sg:postcode":"9200",
    "sg:province":"Oost-Vlaanderen",
    "wof:name":"Transport Maes",
    "wof:placetype":"venue"
},
  "geometry": {"coordinates":[4.1409649849,51.0312385559],"type":"Point"}
}