{
  "type": "Feature",
  "properties": {
    "iso:country":"BE",
    "sg:address":"Rue Jef. Thumas 17",
    "sg:city":"Kraainem",
    "sg:classifiers":[
        {
            "category":"Arena",
            "subcategory":"Sports Club",
            "type":"Entertainment"
        }
    ],
    "sg:phone":"+32 2 305 79 70",
    "sg:postcode":"1950",
    "sg:province":"Vlaams-Brabant",
    "sg:tags":[
        "de"
    ],
    "wof:name":"Hc A.s.e.k. 72",
    "wof:placetype":"venue"
},
  "geometry": {"coordinates":[4.4545650482,50.8646888733],"type":"Point"}
}