{
  "type": "Feature",
  "properties": {
    "iso:country":"BE",
    "sg:address":"Vismarkt 7",
    "sg:city":"Leuven",
    "sg:classifiers":[
        {
            "category":"Professional",
            "type":"Services"
        }
    ],
    "sg:phone":"+32 16 23 54 90",
    "sg:postcode":"3000",
    "sg:province":"Vlaams-Brabant",
    "sg:tags":[
        "auction",
        "room"
    ],
    "wof:name":"Lovansia",
    "wof:placetype":"venue"
},
  "geometry": {"coordinates":[4.7002778053,50.8813781738],"type":"Point"}
}