{
  "type": "Feature",
  "properties": {
    "addr:full":"Stationsstraat 26 Kortemark West-Vlaanderen 8610",
    "addr:housenumber":"26",
    "addr:postcode":"8610",
    "addr:street":"Stationsstraat",
    "iso:country":"BE",
    "sg:address":"Stationsstraat 26",
    "sg:city":"Kortemark",
    "sg:orig_category":"Banques and organismes de cr\u00e9dit",
    "sg:phone":"+32 51 56 97 38",
    "sg:postcode":"8610",
    "sg:province":"West-Vlaanderen",
    "wof:name":"Dexia",
    "wof:placetype":"venue"
},
  "geometry": {"coordinates":[3.0420498848,51.0253181458],"type":"Point"}
}