{
  "type": "Feature",
  "properties": {
    "addr:full":"3 Industrielaan Menen West-Vlaanderen 8930",
    "addr:housenumber":"3",
    "addr:postcode":"8930",
    "addr:street":"Industrielaan",
    "iso:country":"BE",
    "sg:address":"3 Industrielaan",
    "sg:city":"Menen",
    "sg:classifiers":[
        {
            "category":"Professional",
            "subcategory":"Engineering",
            "type":"Services"
        }
    ],
    "sg:phone":"+32 56 52 80 60",
    "sg:postcode":"8930",
    "sg:province":"West-Vlaanderen",
    "sg:tags":[
        "machine",
        "-",
        "mechanical"
    ],
    "wof:name":"Nvs Nv",
    "wof:placetype":"venue"
},
  "geometry": {"coordinates":[3.1003348827,50.789226532],"type":"Point"}
}