{
  "type": "Feature",
  "properties": {
    "iso:country":"BE",
    "sg:address":"Place Emile De Lalieux 9-11",
    "sg:city":"Nivelles",
    "sg:classifiers":[
        {
            "category":"Shopping",
            "subcategory":"Computers & Home Electronics",
            "type":"Retail Goods"
        }
    ],
    "sg:phone":"+32 67 21 71 00",
    "sg:postcode":"1400",
    "sg:province":"Brabant Wallon",
    "sg:tags":[
        "-",
        "television",
        "radio"
    ],
    "wof:name":"Hi-fi Vid\u00e9o Nivelles",
    "wof:placetype":"venue"
},
  "geometry": {"coordinates":[4.3285012245,50.5984573364],"type":"Point"}
}