{
  "type": "Feature",
  "properties": {
    "iso:country":"BE",
    "sg:address":"Rue Du Coll\u00c8ge 1",
    "sg:city":"Eghez\u00c9e",
    "sg:orig_category":"Dameskledingzaken Herenkledingzaken",
    "sg:phone":"+32 81 81 15 52",
    "sg:postcode":"5310",
    "sg:province":"Namur",
    "wof:name":"Fran\u00c7oise Bertrand",
    "wof:placetype":"venue"
},
  "geometry": {"coordinates":[4.9096999168,50.5939216614],"type":"Point"}
}