{
  "type": "Feature",
  "properties": {
    "iso:country":"BE",
    "sg:address":"Guido Gezellestraat 60",
    "sg:city":"Gent",
    "sg:orig_category":"Diverse opleidingen and onderwijs Software ontwikkeling and ontwerp",
    "sg:phone":"+32 9 231 00 35",
    "sg:postcode":"9050",
    "sg:province":"Oost-Vlaanderen",
    "wof:name":"Back Up",
    "wof:placetype":"venue"
},
  "geometry": {"coordinates":[3.7453598976,51.0354537964],"type":"Point"}
}