{
  "type": "Feature",
  "properties": {
    "addr:full":"Chauss\u00c9e De Tervuren 42 Waterloo Brabant Wallon 1410",
    "addr:housenumber":"42",
    "addr:postcode":"1410",
    "addr:street":"Chausse\u0301E De Tervuren",
    "iso:country":"BE",
    "sg:address":"Chauss\u00c9e De Tervuren 42",
    "sg:city":"Waterloo",
    "sg:orig_category":"Auto-\u00e9coles",
    "sg:phone":"+32 2 354 55 42",
    "sg:postcode":"1410",
    "sg:province":"Brabant Wallon",
    "wof:name":"Auto-ecole G. Herode",
    "wof:placetype":"venue"
},
  "geometry": {"coordinates":[4.4028792381,50.7023200989],"type":"Point"}
}