{
  "type": "Feature",
  "properties": {
    "iso:country":"BE",
    "sg:address":"Waregemseweg 146",
    "sg:city":"Wortegem-petegem",
    "sg:classifiers":[
        {
            "category":"Professional",
            "subcategory":"Detective & Security Services",
            "type":"Services"
        }
    ],
    "sg:phone":"+32 56 69 42 13",
    "sg:postcode":"9790",
    "sg:province":"Oost-Vlaanderen",
    "sg:tags":[
        "consulting",
        "engineering"
    ],
    "wof:name":"Bureau Voor Commerciele Verwerking Nv",
    "wof:placetype":"venue"
},
  "geometry": {"coordinates":[3.4789509773,50.8639297485],"type":"Point"}
}