{
  "type": "Feature",
  "properties": {
    "iso:country":"BE",
    "sg:address":"Rue Des Fauvettes 8",
    "sg:city":"Beyne-heusay",
    "sg:orig_category":"Diverse bedrijfsbeheeradviesbureaus",
    "sg:phone":"+32 4 358 63 17",
    "sg:postcode":"4610",
    "sg:province":"Li\u00e8ge",
    "wof:name":"Logistique Op\u00c9rationelle",
    "wof:placetype":"venue"
},
  "geometry": {"coordinates":[5.669069767,50.6260681152],"type":"Point"}
}