{
  "type": "Feature",
  "properties": {
    "addr:full":"Bruggesteenweg 4d Ardooie West-Vlaanderen 8850",
    "addr:housenumber":"4d",
    "addr:postcode":"8850",
    "addr:street":"Bruggesteenweg",
    "iso:country":"BE",
    "sg:address":"Bruggesteenweg 4d",
    "sg:city":"Ardooie",
    "sg:orig_category":"HERSTELLING ELEKTRISCHE HUISHOUDAPPARATEN Huishoudapparaten, televisies and radio's",
    "sg:phone":"+32 51 46 79 80",
    "sg:postcode":"8850",
    "sg:province":"West-Vlaanderen",
    "wof:name":"E. Fraeye",
    "wof:placetype":"venue"
},
  "geometry": {"coordinates":[3.2410509586,50.9781913757],"type":"Point"}
}