{
  "type": "Feature",
  "properties": {
    "addr:full":"Waterloose Steenweg 507 Elsene/ixelles Bruxelles-Capitale 1050",
    "addr:housenumber":"507",
    "addr:postcode":"1050",
    "addr:street":"Waterloose Steenweg",
    "iso:country":"BE",
    "sg:address":"Waterloose Steenweg 507",
    "sg:city":"Elsene/ixelles",
    "sg:orig_category":"Apotheken",
    "sg:phone":"+32 2 344 59 05",
    "sg:postcode":"1050",
    "sg:province":"Bruxelles-Capitale",
    "wof:name":"Jacques Pirot",
    "wof:placetype":"venue"
},
  "geometry": {"coordinates":[4.3590669632,50.8201446533],"type":"Point"}
}