{
  "type": "Feature",
  "properties": {
    "addr:full":"Rue De L'int\u00e9rieur 122 Perwez (thorembais-saint-trond) Brabant Wallon 1360",
    "addr:housenumber":"122",
    "addr:postcode":"1360",
    "addr:street":"Rue De L'Inte \u0301Rieur;Wallon",
    "iso:country":"BE",
    "sg:address":"Rue De L'int\u00e9rieur 122",
    "sg:city":"Perwez (thorembais-saint-trond)",
    "sg:classifiers":[
        {
            "category":"Home & Garden",
            "subcategory":"Building Materials",
            "type":"Retail Goods"
        }
    ],
    "sg:phone":"+32 81 65 50 55",
    "sg:postcode":"1360",
    "sg:province":"Brabant Wallon",
    "sg:tags":[
        "-",
        "fireplace",
        "open",
        "ornamental"
    ],
    "wof:name":"Cheminee Gabriel",
    "wof:placetype":"venue"
},
  "geometry": {"coordinates":[4.7757248878,50.6271820068],"type":"Point"}
}