{
  "type": "Feature",
  "properties": {
    "iso:country":"BE",
    "sg:address":"Velveken 68",
    "sg:city":"Geel",
    "sg:orig_category":"Rundveehouders",
    "sg:phone":"+32 14 58 93 29",
    "sg:postcode":"2440",
    "sg:province":"Antwerpen",
    "wof:name":"Joannes Bakelants",
    "wof:placetype":"venue"
},
  "geometry": {"coordinates":[4.9370379448,51.1547050476],"type":"Point"}
}