{
  "type": "Feature",
  "properties": {
    "addr:full":"Stationsstraat 41 Lochristi Oost-Vlaanderen 9080",
    "addr:housenumber":"41",
    "addr:postcode":"9080",
    "addr:street":"Stationsstraat",
    "iso:country":"BE",
    "sg:address":"Stationsstraat 41",
    "sg:city":"Lochristi",
    "sg:classifiers":[
        {
            "category":"Personal",
            "subcategory":"Barber",
            "type":"Services"
        }
    ],
    "sg:phone":"+32 9 355 87 16",
    "sg:postcode":"9080",
    "sg:province":"Oost-Vlaanderen",
    "sg:tags":[
        "gentleman",
        "salon",
        "-",
        "hairdressing"
    ],
    "wof:name":"Rudy's Hairclub",
    "wof:placetype":"venue"
},
  "geometry": {"coordinates":[3.8268380165,51.0922317505],"type":"Point"}
}