{
  "type": "Feature",
  "properties": {
    "addr:full":"Zottegemstraat 24 Maarkedal (schorisse) Oost-Vlaanderen 9688",
    "addr:housenumber":"24",
    "addr:postcode":"9688",
    "addr:street":"Zottegemstraat",
    "iso:country":"BE",
    "sg:address":"Zottegemstraat 24",
    "sg:city":"Maarkedal (schorisse)",
    "sg:classifiers":[
        {
            "category":"Professional",
            "subcategory":"Testing Lab",
            "type":"Services"
        }
    ],
    "sg:phone":"+32 55 45 56 81",
    "sg:postcode":"9688",
    "sg:province":"Oost-Vlaanderen",
    "sg:tags":[
        "chemist"
    ],
    "wof:name":"Dupuis H",
    "wof:placetype":"venue"
},
  "geometry": {"coordinates":[3.6804740429,50.8125305176],"type":"Point"}
}