{
  "type": "Feature",
  "properties": {
    "addr:full":"Avenue Peltzer 48 Verviers Li\u00e8ge 4800",
    "addr:housenumber":"48",
    "addr:postcode":"4800",
    "addr:street":"Avenue Peltzer",
    "iso:country":"BE",
    "sg:address":"Avenue Peltzer 48",
    "sg:city":"Verviers",
    "sg:classifiers":[
        {
            "category":"Health Services",
            "subcategory":"Doctor",
            "type":"Services"
        }
    ],
    "sg:phone":"+32 87 22 65 65",
    "sg:postcode":"4800",
    "sg:province":"Li\u00e8ge",
    "sg:tags":[
        "medicinephysicians",
        "surgeon"
    ],
    "wof:name":"Deville J-l",
    "wof:placetype":"venue"
},
  "geometry": {"coordinates":[5.8532447815,50.5825004578],"type":"Point"}
}