{
  "type": "Feature",
  "properties": {
    "iso:country":"BE",
    "sg:address":"Lodewijk De Raetlaan 25",
    "sg:city":"Izegem",
    "sg:orig_category":"Non-Classified Establishments",
    "sg:phone":"+32 51 31 13 71",
    "sg:postcode":"8870",
    "sg:province":"West-Vlaanderen",
    "wof:name":"Kesteloot Gebr Nv",
    "wof:placetype":"venue"
},
  "geometry": {"coordinates":[3.202600956,50.9288024902],"type":"Point"}
}