{
  "type": "Feature",
  "properties": {
    "addr:full":"Schautenstraat 258 Maldegem Oost-Vlaanderen 9990",
    "addr:housenumber":"258",
    "addr:postcode":"9990",
    "addr:street":"Schautenstraat",
    "iso:country":"BE",
    "sg:address":"Schautenstraat 258",
    "sg:city":"Maldegem",
    "sg:orig_category":"Enseignement maternel and primaire",
    "sg:phone":"+32 50 71 68 26",
    "sg:postcode":"9990",
    "sg:province":"Oost-Vlaanderen",
    "wof:name":"Vrije Basisschool",
    "wof:placetype":"venue"
},
  "geometry": {"coordinates":[3.4184710979,51.1941947937],"type":"Point"}
}