{
  "type": "Feature",
  "properties": {
    "iso:country":"BE",
    "sg:address":"Rue Marcq 13",
    "sg:city":"Brussel",
    "sg:classifiers":[
        {
            "category":"Manufacturing",
            "subcategory":"Signs",
            "type":"Manufacturing & Wholesale Goods"
        }
    ],
    "sg:phone":"+32 2 521 94 08",
    "sg:postcode":"1000",
    "sg:province":"Bruxelles-Capitale",
    "sg:tags":[
        "display"
    ],
    "wof:name":"Kreisman Gabor",
    "wof:placetype":"venue"
},
  "geometry": {"coordinates":[4.3487210274,50.8541107178],"type":"Point"}
}