{
  "type": "Feature",
  "properties": {
    "iso:country":"BE",
    "sg:address":"Route De L'etat 118",
    "sg:city":"Lasne (maransart)",
    "sg:classifiers":[
        {
            "category":"Professional",
            "subcategory":"Accounting & Tax Preparation",
            "type":"Services"
        }
    ],
    "sg:phone":"+32 2 633 32 78",
    "sg:postcode":"1380",
    "sg:province":"Brabant Wallon",
    "sg:tags":[
        "bookkeeper"
    ],
    "wof:name":"Management And Consulting Services",
    "wof:placetype":"venue"
},
  "geometry": {"coordinates":[4.4718770981,50.6747436523],"type":"Point"}
}