{
  "type": "Feature",
  "properties": {
    "iso:country":"BE",
    "sg:address":"Stichelberg 33",
    "sg:city":"Dilbeek",
    "sg:classifiers":[
        {
            "category":"Arena",
            "subcategory":"Sports Club",
            "type":"Entertainment"
        }
    ],
    "sg:phone":"+32 2 466 09 04",
    "sg:postcode":"1702",
    "sg:province":"Vlaams-Brabant",
    "sg:tags":[
        "de"
    ],
    "wof:name":"V.y.c.",
    "wof:placetype":"venue"
},
  "geometry": {"coordinates":[4.2639508247,50.8644065857],"type":"Point"}
}