{
  "type": "Feature",
  "properties": {
    "addr:full":"Rysseveldstraat 1a Nevele (vosselare) Oost-Vlaanderen 9850",
    "addr:housenumber":"1a",
    "addr:postcode":"9850",
    "addr:street":"Rysseveldstraat",
    "iso:country":"BE",
    "sg:address":"Rysseveldstraat 1a",
    "sg:city":"Nevele (vosselare)",
    "sg:classifiers":[
        {
            "category":"Farming",
            "subcategory":"Crops",
            "type":"Manufacturing & Wholesale Goods"
        }
    ],
    "sg:phone":"+32 9 371 77 64",
    "sg:postcode":"9850",
    "sg:province":"Oost-Vlaanderen",
    "sg:tags":[
        "vegetable",
        "fruit",
        "-",
        "grower"
    ],
    "wof:name":"De Gheest P",
    "wof:placetype":"venue"
},
  "geometry": {"coordinates":[3.5666899681,51.0256767273],"type":"Point"}
}