{
  "type": "Feature",
  "properties": {
    "iso:country":"BE",
    "sg:address":"Beverestraat 40",
    "sg:city":"Oudenaarde",
    "sg:orig_category":"Animaux domestiques and accessoires",
    "sg:phone":"+32 55 31 40 19",
    "sg:postcode":"9700",
    "sg:province":"Oost-Vlaanderen",
    "wof:name":"Orni Dierenweelde",
    "wof:placetype":"venue"
},
  "geometry": {"coordinates":[3.599230051,50.8487472534],"type":"Point"}
}