{
  "type": "Feature",
  "properties": {
    "addr:full":"Rue De Genval 14 La Hulpe Brabant Wallon 1310",
    "addr:housenumber":"14",
    "addr:postcode":"1310",
    "addr:street":"Rue De Genval",
    "iso:country":"BE",
    "sg:address":"Rue De Genval 14",
    "sg:city":"La Hulpe",
    "sg:classifiers":[
        {
            "category":"Cafe",
            "type":"Food & Drink"
        }
    ],
    "sg:phone":"+32 2 653 01 13",
    "sg:postcode":"1310",
    "sg:province":"Brabant Wallon",
    "sg:tags":[
        "snack-bars"
    ],
    "wof:name":"C\u00f4t\u00e9 Jardin",
    "wof:placetype":"venue"
},
  "geometry": {"coordinates":[4.4857821465,50.7299385071],"type":"Point"}
}