{
  "type": "Feature",
  "properties": {
    "iso:country":"BE",
    "sg:address":"Brabantstraat 117",
    "sg:city":"Waregem",
    "sg:classifiers":[
        {
            "category":"Home & Garden",
            "subcategory":"Home Furnishings",
            "type":"Retail Goods"
        }
    ],
    "sg:phone":"+32 3 366 17 70",
    "sg:postcode":"8790",
    "sg:province":"West-Vlaanderen",
    "sg:tags":[
        "bathroom",
        "wc",
        "fitting"
    ],
    "wof:name":"Sanal Nv",
    "wof:placetype":"venue"
},
  "geometry": {"coordinates":[4.4764537811,51.1916923523],"type":"Point"}
}