{
  "type": "Feature",
  "properties": {
    "iso:country":"BE",
    "sg:address":"Rue Foss\u00c9 Des Vaux 10bb",
    "sg:city":"Court-saint-etienne",
    "sg:orig_category":"Boekhouders",
    "sg:phone":"+32 10 61 76 50",
    "sg:postcode":"1490",
    "sg:province":"Brabant Wallon",
    "wof:name":"Patrick Moreels",
    "wof:placetype":"venue"
},
  "geometry": {"coordinates":[4.6037688255,50.6478347778],"type":"Point"}
}