{
  "type": "Feature",
  "properties": {
    "iso:country":"BE",
    "sg:address":"Av Du Ch\u00e2teau 92",
    "sg:city":"Mouscron",
    "sg:classifiers":[
        {
            "category":"Building & Trades",
            "subcategory":"Construction",
            "type":"Services"
        }
    ],
    "sg:phone":"+32 56 33 25 70",
    "sg:postcode":"7700",
    "sg:province":"Hainaut",
    "sg:tags":[
        "work",
        "public"
    ],
    "wof:name":"Travaux Publics Mouscron Sa",
    "wof:placetype":"venue"
},
  "geometry": {"coordinates":[3.2272689342,50.7453041077],"type":"Point"}
}