{
  "type": "Feature",
  "properties": {
    "iso:country":"BE",
    "sg:address":"Rue Du Ry-d'ao\u00dbt 5",
    "sg:city":"Yvoir",
    "sg:orig_category":"Kapsalons",
    "sg:phone":"+32 83 69 01 76",
    "sg:postcode":"5530",
    "sg:province":"Namur",
    "wof:name":"Laura Lyne",
    "wof:placetype":"venue"
},
  "geometry": {"coordinates":[4.9861707687,50.3179244995],"type":"Point"}
}