{
  "type": "Feature",
  "properties": {
    "addr:full":"Rue Du Bluet 15-16 Charleroi Hainaut 6040",
    "addr:postcode":"15-16;6040",
    "addr:street":"Rue Du Bluet;Hainaut",
    "iso:country":"BE",
    "sg:address":"Rue Du Bluet 15-16",
    "sg:city":"Charleroi",
    "sg:orig_category":"Salles de spectacles. Art and fournitures artistiques",
    "sg:phone":"+32 71 35 99 49",
    "sg:postcode":"6040",
    "sg:province":"Hainaut",
    "wof:name":"Van Impe Daniel Perim\u00c8tre",
    "wof:placetype":"venue"
},
  "geometry": {"coordinates":[4.4225358963,50.4381980896],"type":"Point"}
}