{
  "type": "Feature",
  "properties": {
    "addr:full":"Wittemolenstraat 86 Wevelgem West-Vlaanderen 8560",
    "addr:housenumber":"86",
    "addr:postcode":"8560",
    "addr:street":"Wittemolenstraat",
    "iso:country":"BE",
    "sg:address":"Wittemolenstraat 86",
    "sg:city":"Wevelgem",
    "sg:orig_category":"Woningbouw",
    "sg:phone":"+32 56 41 28 82",
    "sg:postcode":"8560",
    "sg:province":"West-Vlaanderen",
    "wof:name":"Vermeersch Luc",
    "wof:placetype":"venue"
},
  "geometry": {"coordinates":[3.1576209068,50.8361778259],"type":"Point"}
}