{
  "type": "Feature",
  "properties": {
    "addr:full":"Rue Porte De Souvr\u00c9 35 Vise Li\u00e8ge 4600",
    "addr:housenumber":"35",
    "addr:postcode":"4600",
    "addr:street":"Rue Porte De Souvre\u0301",
    "iso:country":"BE",
    "sg:address":"Rue Porte De Souvr\u00c9 35",
    "sg:city":"Vise",
    "sg:orig_category":"Caf\u00e9s Ruimtes voor conferenties, recepties and feesten",
    "sg:phone":"+32 4 379 33 41",
    "sg:postcode":"4600",
    "sg:province":"Li\u00e8ge",
    "wof:name":"Salons Au Vieux Vis\u00c9",
    "wof:placetype":"venue"
},
  "geometry": {"coordinates":[5.6951971054,50.7315483093],"type":"Point"}
}