{
  "type": "Feature",
  "properties": {
    "iso:country":"BE",
    "sg:address":"Broekzijstraat 24",
    "sg:city":"Lille",
    "sg:orig_category":"Rundveehouders",
    "sg:phone":"+32 14 88 16 32",
    "sg:postcode":"2275",
    "sg:province":"Antwerpen",
    "wof:name":"Josephus Goossens",
    "wof:placetype":"venue"
},
  "geometry": {"coordinates":[4.8061490059,51.2363700867],"type":"Point"}
}