{
  "type": "Feature",
  "properties": {
    "iso:country":"BE",
    "sg:address":"Rue De L'h\u00f4tel Communal 141",
    "sg:city":"Gr\u00e2ce-hollogne (hollogne-aux-pierres)",
    "sg:classifiers":[
        {
            "category":"Communications",
            "subcategory":"Film & Video Production",
            "type":"Services"
        }
    ],
    "sg:phone":"+32 4 233 88 02",
    "sg:postcode":"4460",
    "sg:province":"Li\u00e8ge",
    "sg:tags":[
        "hiring",
        "-"
    ],
    "wof:name":"Videoscopie",
    "wof:placetype":"venue"
},
  "geometry": {"coordinates":[5.4855289459,50.628528595],"type":"Point"}
}