{
  "type": "Feature",
  "properties": {
    "iso:country":"BE",
    "sg:address":"Voisinage De La Tour 3",
    "sg:city":"Boncelles",
    "sg:classifiers":[
        {
            "category":"Communications",
            "subcategory":"Film & Video Production",
            "type":"Services"
        }
    ],
    "sg:phone":"+32 4 337 50 95",
    "sg:postcode":"4100",
    "sg:province":"Li\u00e8ge",
    "sg:tags":[
        "equipment",
        "presentation"
    ],
    "wof:name":"City Communication",
    "wof:placetype":"venue"
},
  "geometry": {"coordinates":[5.5272722244,50.5793838501],"type":"Point"}
}