{
  "type": "Feature",
  "properties": {
    "iso:country":"BE",
    "sg:address":"Nieuwstraat 228",
    "sg:city":"Diepenbeek",
    "sg:classifiers":[
        {
            "category":"Cafe",
            "type":"Food & Drink"
        }
    ],
    "sg:phone":"+32 11 33 25 91",
    "sg:postcode":"3590",
    "sg:province":"Limburg",
    "sg:tags":[
        "caf\u00e9s"
    ],
    "wof:name":"Roza Goossens",
    "wof:placetype":"venue"
},
  "geometry": {"coordinates":[5.4639029503,50.9300231934],"type":"Point"}
}