{
  "type": "Feature",
  "properties": {
    "addr:full":"Meerskant 52 Zele Oost-Vlaanderen 9240",
    "addr:housenumber":"52",
    "addr:postcode":"9240",
    "addr:street":"Meerskant",
    "iso:country":"BE",
    "sg:address":"Meerskant 52",
    "sg:city":"Zele",
    "sg:classifiers":[
        {
            "category":"Health Services",
            "subcategory":"Doctor",
            "type":"Services"
        }
    ],
    "sg:phone":"+32 52 44 71 54",
    "sg:postcode":"9240",
    "sg:province":"Oost-Vlaanderen",
    "sg:tags":[
        "medicinephysicians",
        "surgeon"
    ],
    "wof:name":"De Decker Theo",
    "wof:placetype":"venue"
},
  "geometry": {"coordinates":[4.0305361748,51.050239563],"type":"Point"}
}