{
  "type": "Feature",
  "properties": {
    "iso:country":"BE",
    "sg:address":"Herentalsebaan 388-400",
    "sg:city":"Wommelgem",
    "sg:classifiers":[
        {
            "category":"Structure",
            "subcategory":"Office Building",
            "type":"Public Place"
        }
    ],
    "sg:phone":"+32 3 366 18 66",
    "sg:postcode":"2160",
    "sg:province":"Antwerpen",
    "sg:tags":[
        "-",
        "type",
        "door",
        "sliding",
        "overhead"
    ],
    "wof:name":"All-jobs",
    "wof:placetype":"venue"
},
  "geometry": {"coordinates":[4.5032410622,51.1959953308],"type":"Point"}
}