{
  "type": "Feature",
  "properties": {
    "addr:full":"Rue Du Prince 14 Verviers Li\u00e8ge 4800",
    "addr:housenumber":"14",
    "addr:postcode":"4800",
    "addr:street":"Rue Du Prince",
    "iso:country":"BE",
    "sg:address":"Rue Du Prince 14",
    "sg:city":"Verviers",
    "sg:orig_category":"Openbare bibliotheken and archieven",
    "sg:phone":"+32 87 33 58 76",
    "sg:postcode":"4800",
    "sg:province":"Li\u00e8ge",
    "wof:name":"Centre Information Th\u00c9atrale",
    "wof:placetype":"venue"
},
  "geometry": {"coordinates":[5.8750219345,50.5973434448],"type":"Point"}
}