{
  "type": "Feature",
  "properties": {
    "iso:country":"BE",
    "sg:address":"Grote Nieuwedijkstraat 129",
    "sg:city":"Mechelen",
    "sg:orig_category":"Slagers",
    "sg:phone":"+32 15 55 80 00",
    "sg:postcode":"2800",
    "sg:province":"Antwerpen",
    "wof:name":"De Vleeshoeve",
    "wof:placetype":"venue"
},
  "geometry": {"coordinates":[4.4942231178,51.0341529846],"type":"Point"}
}