{
  "type": "Feature",
  "properties": {
    "iso:country":"BE",
    "sg:address":"Rue St-nicolas 396",
    "sg:city":"Saint-nicolas",
    "sg:classifiers":[
        {
            "category":"Retail",
            "subcategory":"Event Space",
            "type":"Services"
        }
    ],
    "sg:phone":"+32 4 250 59 39",
    "sg:postcode":"4420",
    "sg:province":"Li\u00e8ge",
    "sg:tags":[
        "rental",
        "-",
        "hall"
    ],
    "wof:name":"Sapore Del Sol",
    "wof:placetype":"venue"
},
  "geometry": {"coordinates":[5.5360078812,50.6397476196],"type":"Point"}
}