{
  "type": "Feature",
  "properties": {
    "iso:country":"BE",
    "sg:address":"Rue Bollinckx 241",
    "sg:city":"Vorst/forest",
    "sg:orig_category":"Non-foodwinkels",
    "sg:phone":"+32 2 376 91 82",
    "sg:postcode":"1190",
    "sg:province":"Bruxelles-Capitale",
    "wof:name":"Imatex",
    "wof:placetype":"venue"
},
  "geometry": {"coordinates":[4.3066902161,50.8119697571],"type":"Point"}
}