{
  "type": "Feature",
  "properties": {
    "addr:full":"Groenlaan 54 Tervuren Vlaams-Brabant 3080",
    "addr:housenumber":"54",
    "addr:postcode":"3080",
    "addr:street":"Groenlaan",
    "iso:country":"BE",
    "sg:address":"Groenlaan 54",
    "sg:city":"Tervuren",
    "sg:classifiers":[
        {
            "category":"Professional",
            "subcategory":"Management & Consulting",
            "type":"Services"
        }
    ],
    "sg:phone":"+32 2 768 24 70",
    "sg:postcode":"3080",
    "sg:province":"Vlaams-Brabant",
    "sg:tags":[
        "-",
        "processing",
        "data",
        "consultant"
    ],
    "wof:name":"Aaw Trading En Consultancy",
    "wof:placetype":"venue"
},
  "geometry": {"coordinates":[4.5454788208,50.8544998169],"type":"Point"}
}