{
  "type": "Feature",
  "properties": {
    "addr:full":"Albert I Laan 97 Koksijde (oostduinkerke) West-Vlaanderen 8670",
    "addr:housenumber":"97",
    "addr:postcode":"8670",
    "addr:street":"Albert I Laan",
    "iso:country":"BE",
    "sg:address":"Albert I Laan 97",
    "sg:city":"Koksijde (oostduinkerke)",
    "sg:classifiers":[
        {
            "category":"Shopping",
            "subcategory":"Gifts & Souvenirs",
            "type":"Retail Goods"
        }
    ],
    "sg:phone":"+32 58 51 16 16",
    "sg:postcode":"8670",
    "sg:province":"West-Vlaanderen",
    "sg:tags":[
        "-"
    ],
    "wof:name":"Tania",
    "wof:placetype":"venue"
},
  "geometry": {"coordinates":[2.6982328892,51.1397666931],"type":"Point"}
}