{
  "type": "Feature",
  "properties": {
    "iso:country":"BE",
    "sg:address":"Rue De Gand 20",
    "sg:city":"Ath",
    "sg:orig_category":"HERSTELLING ELEKTRISCHE HUISHOUDAPPARATEN Huishoudapparaten, televisies and radio's",
    "sg:phone":"+32 68 28 50 51",
    "sg:postcode":"7800",
    "sg:province":"Hainaut",
    "wof:name":"Duquesne",
    "wof:placetype":"venue"
},
  "geometry": {"coordinates":[3.7763679028,50.6278343201],"type":"Point"}
}