{
  "type": "Feature",
  "properties": {
    "addr:full":"Dendermondsesteenweg 38 Lebbeke Oost-Vlaanderen 9280",
    "addr:housenumber":"38",
    "addr:postcode":"9280",
    "addr:street":"Dendermondsesteenweg",
    "iso:country":"BE",
    "sg:address":"Dendermondsesteenweg 38",
    "sg:city":"Lebbeke",
    "sg:orig_category":"MEUBELONTWERP AND -INSTALLATIE",
    "sg:phone":"+32 52 41 08 85",
    "sg:postcode":"9280",
    "sg:province":"Oost-Vlaanderen",
    "wof:name":"Roelandt Keukens",
    "wof:placetype":"venue"
},
  "geometry": {"coordinates":[4.1267170906,51.0020980835],"type":"Point"}
}