{
  "type": "Feature",
  "properties": {
    "iso:country":"BE",
    "sg:address":"Rue Ernest Milcamps 3",
    "sg:city":"La Louviere",
    "sg:orig_category":"Formation permanente",
    "sg:phone":"+32 64 22 37 20",
    "sg:postcode":"7100",
    "sg:province":"Hainaut",
    "wof:name":"I.n.f.o.p.",
    "wof:placetype":"venue"
},
  "geometry": {"coordinates":[4.1909298897,50.478931427],"type":"Point"}
}