{
  "type": "Feature",
  "properties": {
    "addr:full":"Autoweg E17 Noord Laarne Oost-Vlaanderen 9270",
    "addr:postcode":"9270",
    "addr:street":"Oost-Vlaanderen",
    "iso:country":"BE",
    "sg:address":"Autoweg E17 Noord",
    "sg:city":"Laarne",
    "sg:orig_category":"Journaux. Stations-service and carburants",
    "sg:phone":"+32 9 367 63 71",
    "sg:postcode":"9270",
    "sg:province":"Oost-Vlaanderen",
    "wof:name":"Fina",
    "wof:placetype":"venue"
},
  "geometry": {"coordinates":[3.8337709904,51.0527801514],"type":"Point"}
}