{
  "type": "Feature",
  "properties": {
    "addr:full":"Oppitterkiezel 18 Bree Limburg 3960",
    "addr:housenumber":"18",
    "addr:postcode":"3960",
    "addr:street":"Oppitterkiezel",
    "iso:country":"BE",
    "sg:address":"Oppitterkiezel 18",
    "sg:city":"Bree",
    "sg:orig_category":"Industri\u00eble and commerci\u00eble bouw",
    "sg:phone":"+32 89 46 07 00",
    "sg:postcode":"3960",
    "sg:province":"Limburg",
    "wof:name":"Das",
    "wof:placetype":"venue"
},
  "geometry": {"coordinates":[5.6085591316,51.1364555359],"type":"Point"}
}