{
  "type": "Feature",
  "properties": {
    "addr:full":"Passage Du Centre 18 Mons Hainaut 7000",
    "addr:housenumber":"18",
    "addr:postcode":"7000",
    "addr:street":"Passage Du Centre;Hainaut",
    "iso:country":"BE",
    "sg:address":"Passage Du Centre 18",
    "sg:city":"Mons",
    "sg:classifiers":[
        {
            "category":"Personal",
            "subcategory":"Beauty Salon",
            "type":"Services"
        }
    ],
    "sg:phone":"+32 65 34 63 87",
    "sg:postcode":"7000",
    "sg:province":"Hainaut",
    "wof:name":"Professionails",
    "wof:placetype":"venue"
},
  "geometry": {"coordinates":[3.9487791061,50.451133728],"type":"Point"}
}