{
  "type": "Feature",
  "properties": {
    "iso:country":"BE",
    "sg:address":"Parc Industriel De Keumiee",
    "sg:city":"Sombreffe",
    "sg:classifiers":[
        {
            "category":"Shopping",
            "subcategory":"Pets & Pet Supplies",
            "type":"Retail Goods"
        }
    ],
    "sg:phone":"+32 71 81 36 50",
    "sg:postcode":"5140",
    "sg:province":"Namur",
    "sg:tags":[
        "crematory",
        "cemetery"
    ],
    "wof:name":"Animal Repos Sprl",
    "wof:placetype":"venue"
},
  "geometry": {"coordinates":[4.6057400703,50.5255966187],"type":"Point"}
}