{
  "type": "Feature",
  "properties": {
    "addr:full":"Caetsbeekstraat 3 Bilzen Limburg 3740",
    "addr:housenumber":"3",
    "addr:postcode":"3740",
    "addr:street":"Caetsbeekstraat",
    "iso:country":"BE",
    "sg:address":"Caetsbeekstraat 3",
    "sg:city":"Bilzen",
    "sg:orig_category":"Non-Classified Establishments",
    "sg:phone":"+32 89 30 48 00",
    "sg:postcode":"3740",
    "sg:province":"Limburg",
    "wof:name":"Kromoxi Prof Nv",
    "wof:placetype":"venue"
},
  "geometry": {"coordinates":[5.5057888031,50.9120407104],"type":"Point"}
}