{
  "type": "Feature",
  "properties": {
    "addr:full":"Marie-jos\u00e9plein 3 Oostende West-Vlaanderen 8400",
    "addr:housenumber":"3",
    "addr:postcode":"8400",
    "addr:street":"Marie-Jose\u0301Plein",
    "iso:country":"BE",
    "sg:address":"Marie-jos\u00e9plein 3",
    "sg:city":"Oostende",
    "sg:classifiers":[
        {
            "category":"Bars & Pubs",
            "type":"Food & Drink"
        }
    ],
    "sg:phone":"+32 59 51 13 05",
    "sg:postcode":"8400",
    "sg:province":"West-Vlaanderen",
    "sg:tags":[
        "tavern"
    ],
    "wof:name":"Du Parc Brasserie Bvba",
    "wof:placetype":"venue"
},
  "geometry": {"coordinates":[2.9135279655,51.2307853699],"type":"Point"}
}