{
  "type": "Feature",
  "properties": {
    "addr:full":"Chauss\u00c9e Colonel Joset 63 Soumagne Li\u00e8ge 4630",
    "addr:housenumber":"63",
    "addr:postcode":"4630",
    "addr:street":"Chausse\u0301E Colonel Joset",
    "iso:country":"BE",
    "sg:address":"Chauss\u00c9e Colonel Joset 63",
    "sg:city":"Soumagne",
    "sg:orig_category":"Voedingsspeciaalzaken",
    "sg:phone":"+32 4 377 50 08",
    "sg:postcode":"4630",
    "sg:province":"Li\u00e8ge",
    "wof:name":"Marc Biname",
    "wof:placetype":"venue"
},
  "geometry": {"coordinates":[5.7621541023,50.6164207458],"type":"Point"}
}