{
  "type": "Feature",
  "properties": {
    "iso:country":"BE",
    "sg:address":"Tweebruggenstraat 6",
    "sg:city":"Lokeren",
    "sg:orig_category":"Quincailleries",
    "sg:phone":"+32 9 349 39 39",
    "sg:postcode":"9160",
    "sg:province":"Oost-Vlaanderen",
    "wof:name":"Brico",
    "wof:placetype":"venue"
},
  "geometry": {"coordinates":[3.9697060585,51.1095848083],"type":"Point"}
}