{
  "type": "Feature",
  "properties": {
    "addr:full":"Nieuwstraat 36 Meulebeke West-Vlaanderen 8760",
    "addr:housenumber":"36",
    "addr:postcode":"8760",
    "addr:street":"Nieuwstraat",
    "iso:country":"BE",
    "sg:address":"Nieuwstraat 36",
    "sg:city":"Meulebeke",
    "sg:orig_category":"Artsen and specialisten",
    "sg:phone":"+32 51 48 91 69",
    "sg:postcode":"8760",
    "sg:province":"West-Vlaanderen",
    "wof:name":"Jos\u00c9 Vermaete",
    "wof:placetype":"venue"
},
  "geometry": {"coordinates":[3.2839300632,50.950969696],"type":"Point"}
}