{
  "type": "Feature",
  "properties": {
    "addr:full":"Chauss\u00c9e De Charleroi 59 Anderlues Hainaut 6150",
    "addr:housenumber":"59",
    "addr:postcode":"6150",
    "addr:street":"Chausse\u0301E De Charleroi",
    "iso:country":"BE",
    "sg:address":"Chauss\u00c9e De Charleroi 59",
    "sg:city":"Anderlues",
    "sg:orig_category":"Maisons de repos and r\u00e9sidences",
    "sg:phone":"+32 71 52 07 93",
    "sg:postcode":"6150",
    "sg:province":"Hainaut",
    "wof:name":"R\u00c9sidence Mallory",
    "wof:placetype":"venue"
},
  "geometry": {"coordinates":[4.2651338577,50.4055557251],"type":"Point"}
}