{
  "type": "Feature",
  "properties": {
    "iso:country":"BE",
    "sg:address":"Brusselsesteenweg 305",
    "sg:city":"Mechelen",
    "sg:orig_category":"Astrologen, grafologen and mediums",
    "sg:phone":"+32 15 43 10 43",
    "sg:postcode":"2800",
    "sg:province":"Antwerpen",
    "wof:name":"Wils Fons",
    "wof:placetype":"venue"
},
  "geometry": {"coordinates":[4.4746699333,51.0077896118],"type":"Point"}
}