{
  "type": "Feature",
  "properties": {
    "addr:full":"Rue De Behogne 5 Rochefort Namur 5580",
    "addr:housenumber":"5",
    "addr:postcode":"5580",
    "addr:street":"Rue De Behogne",
    "iso:country":"BE",
    "sg:address":"Rue De Behogne 5",
    "sg:city":"Rochefort",
    "sg:orig_category":"Zalen voor culturele evenementen",
    "sg:phone":"+32 84 22 13 76",
    "sg:postcode":"5580",
    "sg:province":"Namur",
    "wof:name":"Ctre Culturel Des Roches",
    "wof:placetype":"venue"
},
  "geometry": {"coordinates":[5.2236628532,50.1601448059],"type":"Point"}
}