{
  "type": "Feature",
  "properties": {
    "addr:full":"Schoolstraat 2 Wachtebeke Oost-Vlaanderen 9185",
    "addr:housenumber":"2",
    "addr:postcode":"9185",
    "addr:street":"Schoolstraat",
    "iso:country":"BE",
    "sg:address":"Schoolstraat 2",
    "sg:city":"Wachtebeke",
    "sg:orig_category":"Rundveehouders",
    "sg:phone":"+32 9 345 03 07",
    "sg:postcode":"9185",
    "sg:province":"Oost-Vlaanderen",
    "wof:name":"Roger Alliet",
    "wof:placetype":"venue"
},
  "geometry": {"coordinates":[3.8929400444,51.199836731],"type":"Point"}
}