{
  "type": "Feature",
  "properties": {
    "iso:country":"BE",
    "sg:address":"Kampelaarstraat 33",
    "sg:city":"Kampenhout",
    "sg:classifiers":[
        {
            "category":"Building & Trades",
            "subcategory":"Locksmith",
            "type":"Services"
        }
    ],
    "sg:phone":"+32 16 65 04 19",
    "sg:postcode":"1910",
    "sg:province":"Vlaams-Brabant",
    "sg:tags":[
        "material",
        "road"
    ],
    "wof:name":"Artois K",
    "wof:placetype":"venue"
},
  "geometry": {"coordinates":[4.5454788208,50.9507522583],"type":"Point"}
}