{
  "type": "Feature",
  "properties": {
    "addr:full":"Adm.ronarchstraat 17 Diksmuide 8160",
    "addr:housenumber":"17",
    "addr:postcode":"8160",
    "addr:street":"Adm.Ronarchstraat",
    "iso:country":"BE",
    "sg:address":"Adm.ronarchstraat 17",
    "sg:city":"Diksmuide",
    "sg:classifiers":[
        {
            "category":"Banks & Credit Unions",
            "subcategory":"Bank",
            "type":"Services"
        }
    ],
    "sg:phone":"+32 51 50 01 90",
    "sg:postcode":"8160",
    "wof:name":"Bank Van Roeselare",
    "wof:placetype":"venue"
},
  "geometry": {"coordinates":[2.8657801151,51.0334587097],"type":"Point"}
}