{
  "type": "Feature",
  "properties": {
    "addr:full":"Rue De Landen 166 Hannut Li\u00e8ge 4280",
    "addr:housenumber":"166",
    "addr:postcode":"4280",
    "addr:street":"Rue De Landen",
    "iso:country":"BE",
    "sg:address":"Rue De Landen 166",
    "sg:city":"Hannut",
    "sg:classifiers":[
        {
            "category":"Retail",
            "subcategory":"Auto Repair",
            "type":"Services"
        }
    ],
    "sg:phone":"+32 19 51 24 40",
    "sg:postcode":"4280",
    "sg:province":"Li\u00e8ge",
    "sg:tags":[
        "garage"
    ],
    "wof:name":"Delbrassinne Motors Sa",
    "wof:placetype":"venue"
},
  "geometry": {"coordinates":[5.0821199417,50.683139801],"type":"Point"}
}