{
  "type": "Feature",
  "properties": {
    "addr:full":"Chauss\u00e9e De Bruxelles 372b Waterloo Brabant Wallon 1410",
    "addr:housenumber":"372b",
    "addr:postcode":"1410",
    "addr:street":"Chausse\u0301E De Bruxelles",
    "iso:country":"BE",
    "sg:address":"Chauss\u00e9e De Bruxelles 372b",
    "sg:city":"Waterloo",
    "sg:classifiers":[
        {
            "category":"Shopping",
            "subcategory":"Antiques",
            "type":"Retail Goods"
        }
    ],
    "sg:phone":"+32 2 354 51 72",
    "sg:postcode":"1410",
    "sg:province":"Brabant Wallon",
    "sg:tags":[
        "restoration"
    ],
    "wof:name":"Atelier D'eb\u00e9nisterie D'art",
    "wof:placetype":"venue"
},
  "geometry": {"coordinates":[4.4008059502,50.7102737427],"type":"Point"}
}