{
  "type": "Feature",
  "properties": {
    "addr:full":"Rue De Monsville 302 Quaregnon Hainaut 7390",
    "addr:housenumber":"302",
    "addr:postcode":"7390",
    "addr:street":"Rue De Monsville",
    "iso:country":"BE",
    "sg:address":"Rue De Monsville 302",
    "sg:city":"Quaregnon",
    "sg:orig_category":"Tabac. Journaux. Librairies",
    "sg:phone":"+32 65 78 10 51",
    "sg:postcode":"7390",
    "sg:province":"Hainaut",
    "wof:name":"Librairie De Monville",
    "wof:placetype":"venue"
},
  "geometry": {"coordinates":[3.8633050919,50.4344749451],"type":"Point"}
}