{
  "type": "Feature",
  "properties": {
    "addr:full":"Langestraat 122 Denderleeuw Oost-Vlaanderen 9473",
    "addr:housenumber":"122",
    "addr:postcode":"9473",
    "addr:street":"Langestraat",
    "iso:country":"BE",
    "sg:address":"Langestraat 122",
    "sg:city":"Denderleeuw",
    "sg:orig_category":"Banques and organismes de cr\u00e9dit",
    "sg:phone":"+32 53 67 13 73",
    "sg:postcode":"9473",
    "sg:province":"Oost-Vlaanderen",
    "wof:name":"Centea",
    "wof:placetype":"venue"
},
  "geometry": {"coordinates":[4.0529379845,50.89793396],"type":"Point"}
}