{
  "type": "Feature",
  "properties": {
    "addr:full":"Rue Des Horticulteurs 115 Brussel/bruxelles Bruxelles-Capitale 1020",
    "addr:housenumber":"115",
    "addr:postcode":"1020",
    "addr:street":"Rue Des Horticulteurs;/",
    "iso:country":"BE",
    "sg:address":"Rue Des Horticulteurs 115",
    "sg:city":"Brussel/bruxelles",
    "sg:orig_category":"Technische and wetenschappelijke instrumenten Fab",
    "sg:phone":"+32 2 476 01 72",
    "sg:postcode":"1020",
    "sg:province":"Bruxelles-Capitale",
    "wof:name":"Jibe",
    "wof:placetype":"venue"
},
  "geometry": {"coordinates":[4.3495488167,50.8822860718],"type":"Point"}
}