{
  "type": "Feature",
  "properties": {
    "addr:full":"Avenue Des Ormes 12 Mons Hainaut 7020",
    "addr:housenumber":"12",
    "addr:postcode":"7020",
    "addr:street":"Avenue Des Ormes;Hainaut",
    "iso:country":"BE",
    "sg:address":"Avenue Des Ormes 12",
    "sg:city":"Mons",
    "sg:orig_category":"Vertalers and tolken",
    "sg:phone":"+32 65 84 53 25",
    "sg:postcode":"7020",
    "sg:province":"Hainaut",
    "wof:name":"Eggermont F. Cbtip/bkvtf",
    "wof:placetype":"venue"
},
  "geometry": {"coordinates":[3.9553449154,50.4761772156],"type":"Point"}
}