{
  "type": "Feature",
  "properties": {
    "addr:full":"Rue Nestor Dehon 1 Mons Hainaut 7030",
    "addr:housenumber":"1",
    "addr:postcode":"7030",
    "addr:street":"Rue Nestor Dehon;Hainaut",
    "iso:country":"BE",
    "sg:address":"Rue Nestor Dehon 1",
    "sg:city":"Mons",
    "sg:orig_category":"Entretien and r\u00e9parations de voitures",
    "sg:phone":"+32 65 35 46 40",
    "sg:postcode":"7030",
    "sg:province":"Hainaut",
    "wof:name":"Garage Antoine",
    "wof:placetype":"venue"
},
  "geometry": {"coordinates":[4.0108299255,50.4393882751],"type":"Point"}
}