{
  "type": "Feature",
  "properties": {
    "iso:country":"BE",
    "sg:address":"Drie-eikenstraat 22",
    "sg:city":"Herentals",
    "sg:orig_category":"Gespecialiseerde residenti\u00eble bouw",
    "sg:phone":"+32 14 26 26 36",
    "sg:postcode":"2200",
    "sg:province":"Antwerpen",
    "wof:name":"Jozef Verwimp",
    "wof:placetype":"venue"
},
  "geometry": {"coordinates":[4.8238220215,51.1609306335],"type":"Point"}
}