{
  "type": "Feature",
  "properties": {
    "iso:country":"BE",
    "sg:address":"Roeselaarsestraat 411",
    "sg:city":"Izegem",
    "sg:orig_category":"Herstellingen and onderhoud van auto's",
    "sg:phone":"+32 51 30 01 34",
    "sg:postcode":"8870",
    "sg:province":"West-Vlaanderen",
    "wof:name":"Carrosserie Vleirick",
    "wof:placetype":"venue"
},
  "geometry": {"coordinates":[3.1878569126,50.9249305725],"type":"Point"}
}