{
  "type": "Feature",
  "properties": {
    "addr:full":"Rijselstraat 1 Heuvelland West-Vlaanderen 8953",
    "addr:housenumber":"1",
    "addr:postcode":"8953",
    "addr:street":"Rijselstraat",
    "iso:country":"BE",
    "sg:address":"Rijselstraat 1",
    "sg:city":"Heuvelland",
    "sg:orig_category":"Eleveurs de bovins",
    "sg:phone":"+32 57 20 19 85",
    "sg:postcode":"8953",
    "sg:province":"West-Vlaanderen",
    "wof:name":"Joel Vandeweghe",
    "wof:placetype":"venue"
},
  "geometry": {"coordinates":[2.8978629112,50.8022422791],"type":"Point"}
}