{
  "type": "Feature",
  "properties": {
    "addr:full":"Avenue Victor Jacobs 4 Bruxelles Bruxelles-Capitale 1040",
    "addr:housenumber":"4",
    "addr:postcode":"1040",
    "addr:street":"Avenue Victor Jacobs",
    "iso:country":"BE",
    "sg:address":"Avenue Victor Jacobs 4",
    "sg:city":"Bruxelles",
    "sg:orig_category":"Internet-Design, Web-Design",
    "sg:phone":"+32 2 709 09 45",
    "sg:postcode":"1040",
    "sg:province":"Bruxelles-Capitale",
    "wof:name":"Around Communications",
    "wof:placetype":"venue"
},
  "geometry": {"coordinates":[4.3857550621,50.8297233582],"type":"Point"}
}