{
  "type": "Feature",
  "properties": {
    "addr:full":"Rue De La Vall\u00c9e 20 Chatelet Hainaut 6200",
    "addr:housenumber":"20",
    "addr:postcode":"6200",
    "addr:street":"Rue De La Valle\u0301E;Hainaut",
    "iso:country":"BE",
    "sg:address":"Rue De La Vall\u00c9e 20",
    "sg:city":"Chatelet",
    "sg:orig_category":"Benzinestations and brandstoffen",
    "sg:phone":"+32 71 38 10 56",
    "sg:postcode":"6200",
    "sg:province":"Hainaut",
    "wof:name":"Bp",
    "wof:placetype":"venue"
},
  "geometry": {"coordinates":[4.5184111595,50.4130477905],"type":"Point"}
}