{
  "type": "Feature",
  "properties": {
    "iso:country":"BE",
    "sg:address":"Avenue Du Progr\u00c8s 5",
    "sg:city":"Ans",
    "sg:orig_category":"Meubles D\u00e9taillants, Am\u00e9nagement de B\u00e2timents et de Cuisines",
    "sg:phone":"+32 4 263 18 24",
    "sg:postcode":"4432",
    "sg:province":"Li\u00e8ge",
    "wof:name":"Matelat Waremme",
    "wof:placetype":"venue"
},
  "geometry": {"coordinates":[5.5269970894,50.6727790833],"type":"Point"}
}