{
  "type": "Feature",
  "properties": {
    "iso:country":"BE",
    "sg:address":"Luitenant Jacopsstraat 38",
    "sg:city":"Lennik",
    "sg:orig_category":"Avocats and conseillers juridiques",
    "sg:phone":"+32 2 582 40 52",
    "sg:postcode":"1750",
    "sg:province":"Vlaams-Brabant",
    "wof:name":"Geert Dumon",
    "wof:placetype":"venue"
},
  "geometry": {"coordinates":[4.136841774,50.8316917419],"type":"Point"}
}