{
  "type": "Feature",
  "properties": {
    "iso:country":"BE",
    "sg:address":"Neerstraat 20",
    "sg:city":"Tessenderlo",
    "sg:orig_category":"Dameskledingzaken",
    "sg:phone":"+32 13 66 10 28",
    "sg:postcode":"3980",
    "sg:province":"Limburg",
    "wof:name":"Boetiek Regis",
    "wof:placetype":"venue"
},
  "geometry": {"coordinates":[5.0880451202,51.0684242249],"type":"Point"}
}