{
  "type": "Feature",
  "properties": {
    "iso:country":"BE",
    "sg:address":"Rue De La Cayauderie 61",
    "sg:city":"Charleroi",
    "sg:classifiers":[
        {
            "category":"Health Services",
            "subcategory":"Doctor",
            "type":"Services"
        }
    ],
    "sg:phone":"+32 71 42 22 14",
    "sg:postcode":"6000",
    "sg:province":"Hainaut",
    "sg:tags":[
        "medicinephysicians",
        "surgeon"
    ],
    "wof:name":"Lagneaux V",
    "wof:placetype":"venue"
},
  "geometry": {"coordinates":[4.4592871666,50.4230461121],"type":"Point"}
}