{
  "type": "Feature",
  "properties": {
    "addr:full":"Rue Parmentier 22 La Louvi\u00e8re Hainaut 7100",
    "addr:housenumber":"22",
    "addr:postcode":"7100",
    "addr:street":"Rue Parmentier",
    "iso:country":"BE",
    "sg:address":"Rue Parmentier 22",
    "sg:city":"La Louvi\u00e8re",
    "sg:classifiers":[
        {
            "category":"Health Services",
            "subcategory":"Health Practitioner",
            "type":"Services"
        }
    ],
    "sg:phone":"+32 64 22 87 73",
    "sg:postcode":"7100",
    "sg:province":"Hainaut",
    "sg:tags":[
        "physiotherapist"
    ],
    "wof:name":"Gerard D",
    "wof:placetype":"venue"
},
  "geometry": {"coordinates":[4.2041130066,50.4888648987],"type":"Point"}
}