{
  "type": "Feature",
  "properties": {
    "iso:country":"BE",
    "sg:address":"Rue Du Bois Paillet 2",
    "sg:city":"Incourt",
    "sg:orig_category":"Artsen and specialisten",
    "sg:phone":"+32 10 88 88 85",
    "sg:postcode":"1315",
    "sg:province":"Brabant Wallon",
    "wof:name":"J. Goossens",
    "wof:placetype":"venue"
},
  "geometry": {"coordinates":[4.7868309021,50.7123947144],"type":"Point"}
}