{
  "type": "Feature",
  "properties": {
    "addr:full":"Beverlaai 32 Kortrijk West-Vlaanderen 8500",
    "addr:housenumber":"32",
    "addr:postcode":"8500",
    "addr:street":"Beverlaai",
    "iso:country":"BE",
    "sg:address":"Beverlaai 32",
    "sg:city":"Kortrijk",
    "sg:orig_category":"Artsen and specialisten",
    "sg:phone":"+32 56 21 33 88",
    "sg:postcode":"8500",
    "sg:province":"West-Vlaanderen",
    "wof:name":"Eric Bockaert",
    "wof:placetype":"venue"
},
  "geometry": {"coordinates":[3.2619349957,50.8201637268],"type":"Point"}
}