{
  "type": "Feature",
  "properties": {
    "addr:full":"Rue De Tourcoing 45 Moeskroen/mouscron Hainaut 7700",
    "addr:housenumber":"45",
    "addr:postcode":"7700",
    "addr:street":"Rue De Tourcoing",
    "iso:country":"BE",
    "sg:address":"Rue De Tourcoing 45",
    "sg:city":"Moeskroen/mouscron",
    "sg:orig_category":"Tabac",
    "sg:phone":"+32 56 33 02 11",
    "sg:postcode":"7700",
    "sg:province":"Hainaut",
    "wof:name":"Maison Rousselle",
    "wof:placetype":"venue"
},
  "geometry": {"coordinates":[3.2323200703,50.7400932312],"type":"Point"}
}