{
  "type": "Feature",
  "properties": {
    "addr:full":"Frankrijklei 81-83 Antwerpen Antwerpen 2018",
    "addr:postcode":"81-83;2018",
    "addr:street":"Frankrijklei",
    "iso:country":"BE",
    "sg:address":"Frankrijklei 81-83",
    "sg:city":"Antwerpen",
    "sg:classifiers":[
        {
            "category":"Banks & Credit Unions",
            "subcategory":"Bank",
            "type":"Services"
        }
    ],
    "sg:phone":"+32 3 223 17 11",
    "sg:postcode":"2018",
    "sg:province":"Antwerpen",
    "wof:name":"Nationale Maatschappij, Voor Krediet Aan De Nijverheid",
    "wof:placetype":"venue"
},
  "geometry": {"coordinates":[4.4131650925,51.214630127],"type":"Point"}
}