{
  "type": "Feature",
  "properties": {
    "addr:full":"Rue De La Primev\u00c8re 5 Ukkel/uccle Bruxelles-Capitale 1180",
    "addr:housenumber":"5",
    "addr:postcode":"1180",
    "addr:street":"Rue De La Primeve\u0300Re;/",
    "iso:country":"BE",
    "sg:address":"Rue De La Primev\u00c8re 5",
    "sg:city":"Ukkel/uccle",
    "sg:orig_category":"Cr\u00e8ches and garderies d'enfants",
    "sg:phone":"+32 2 347 69 60",
    "sg:postcode":"1180",
    "sg:province":"Bruxelles-Capitale",
    "wof:name":"Cr\u00c8che La Primev\u00c8re",
    "wof:placetype":"venue"
},
  "geometry": {"coordinates":[4.3606410027,50.8151893616],"type":"Point"}
}