{
  "type": "Feature",
  "properties": {
    "iso:country":"BE",
    "sg:address":"Avenue Minerve 33",
    "sg:city":"Bruxelles (forest)",
    "sg:classifiers":[
        {
            "category":"Organizations",
            "subcategory":"Professional Association",
            "type":"Services"
        }
    ],
    "sg:phone":"+32 2 219 15 87",
    "sg:postcode":"1190",
    "sg:province":"Bruxelles-Capitale",
    "sg:tags":[
        "trade-union",
        "federation"
    ],
    "wof:name":"F\u00e9d\u00e9ration Belge De Scrabble",
    "wof:placetype":"venue"
},
  "geometry": {"coordinates":[4.3313140869,50.8103218079],"type":"Point"}
}