{
  "type": "Feature",
  "properties": {
    "addr:full":"Rue De Herve 72 Li\u00e8ge 1 (grivegn\u00e9e) Li\u00e8ge 4030",
    "addr:housenumber":"72;1",
    "addr:postcode":"4030",
    "addr:street":"Rue De Herve",
    "iso:country":"BE",
    "sg:address":"Rue De Herve 72",
    "sg:city":"Li\u00e8ge 1 (grivegn\u00e9e)",
    "sg:classifiers":[
        {
            "category":"Insurance",
            "subcategory":"Insurance Agent",
            "type":"Services"
        }
    ],
    "sg:phone":"+32 4 361 16 61",
    "sg:postcode":"4030",
    "sg:province":"Li\u00e8ge",
    "sg:tags":[
        "broker"
    ],
    "wof:name":"Collignon B",
    "wof:placetype":"venue"
},
  "geometry": {"coordinates":[5.6124219894,50.6303482056],"type":"Point"}
}