{
  "type": "Feature",
  "properties": {
    "iso:country":"BE",
    "sg:address":"Rue De Bastogne 46",
    "sg:city":"Arlon",
    "sg:classifiers":[
        {
            "category":"Social Services",
            "type":"Services"
        }
    ],
    "sg:phone":"+32 63 41 30 26",
    "sg:postcode":"6700",
    "sg:province":"Luxembourg",
    "wof:name":"Oasis Famille",
    "wof:placetype":"venue"
},
  "geometry": {"coordinates":[5.8099541664,49.6879386902],"type":"Point"}
}