{
  "type": "Feature",
  "properties": {
    "iso:country":"BE",
    "sg:address":"Kennedylaan 7",
    "sg:city":"Kortrijk",
    "sg:orig_category":"Diverse bedrijfsbeheeradviesbureaus Werk and personeelsselectie",
    "sg:phone":"+32 56 25 81 00",
    "sg:postcode":"8500",
    "sg:province":"West-Vlaanderen",
    "wof:name":"Meeremans & Bloemen",
    "wof:placetype":"venue"
},
  "geometry": {"coordinates":[3.274559021,50.8030395508],"type":"Point"}
}