{
  "type": "Feature",
  "properties": {
    "addr:full":"Ubbelstraat 16 Heusden-zolder Limburg 3550",
    "addr:housenumber":"16",
    "addr:postcode":"3550",
    "addr:street":"Ubbelstraat",
    "iso:country":"BE",
    "sg:address":"Ubbelstraat 16",
    "sg:city":"Heusden-zolder",
    "sg:orig_category":"Sportclubs",
    "sg:phone":"+32 11 53 63 85",
    "sg:postcode":"3550",
    "sg:province":"Limburg",
    "wof:name":"T.c. Boekt",
    "wof:placetype":"venue"
},
  "geometry": {"coordinates":[5.2908649445,51.0138397217],"type":"Point"}
}