{
  "type": "Feature",
  "properties": {
    "iso:country":"BE",
    "sg:address":"Baalse Baan 53b",
    "sg:city":"Tremelo",
    "sg:orig_category":"Agences d'exp\u00e9dition",
    "sg:phone":"+32 16 53 77 11",
    "sg:postcode":"3120",
    "sg:province":"Vlaams-Brabant",
    "wof:name":"Kimex",
    "wof:placetype":"venue"
},
  "geometry": {"coordinates":[4.7107548714,50.9946136475],"type":"Point"}
}