{
  "type": "Feature",
  "properties": {
    "iso:country":"BE",
    "sg:address":"Pottebezemstraat 35",
    "sg:city":"Koekelare",
    "sg:classifiers":[
        {
            "category":"Insurance",
            "subcategory":"Life Insurance",
            "type":"Services"
        }
    ],
    "sg:phone":"+32 51 58 99 02",
    "sg:postcode":"8680",
    "sg:province":"West-Vlaanderen",
    "sg:tags":[
        "assurance"
    ],
    "wof:name":"U. Vanbavinckhove",
    "wof:placetype":"venue"
},
  "geometry": {"coordinates":[2.94602108,51.0833320618],"type":"Point"}
}