{
  "type": "Feature",
  "properties": {
    "addr:full":"Rue D'armenti\u00c8res 333 Komen-waasten/comines-warneton Hainaut 7783",
    "addr:housenumber":"333;7783",
    "addr:street":"Rue D'Armentie \u0300Res",
    "iso:country":"BE",
    "sg:address":"Rue D'armenti\u00c8res 333",
    "sg:city":"Komen-waasten/comines-warneton",
    "sg:orig_category":"S\u00e9curit\u00e9 sociale",
    "sg:phone":"+32 56 58 71 44",
    "sg:postcode":"7783",
    "sg:province":"Hainaut",
    "wof:name":"Mutualite Liberale",
    "wof:placetype":"venue"
},
  "geometry": {"coordinates":[2.8827819824,50.7086372375],"type":"Point"}
}