{
  "type": "Feature",
  "properties": {
    "iso:country":"BE",
    "sg:address":"Bargiestraat 14",
    "sg:city":"Ieper",
    "sg:classifiers":[
        {
            "category":"Communications",
            "subcategory":"Television Station",
            "type":"Services"
        }
    ],
    "sg:phone":"+32 57 22 10 90",
    "sg:postcode":"8900",
    "sg:province":"West-Vlaanderen",
    "sg:tags":[
        "electricity",
        "cabling",
        "wiring",
        "-"
    ],
    "wof:name":"Ypes Nv",
    "wof:placetype":"venue"
},
  "geometry": {"coordinates":[2.8733839989,50.8905639648],"type":"Point"}
}