{
  "type": "Feature",
  "properties": {
    "iso:country":"BE",
    "sg:address":"Grand'place 5",
    "sg:city":"Huy",
    "sg:classifiers":[
        {
            "category":"Real Estate",
            "subcategory":"Architect",
            "type":"Services"
        }
    ],
    "sg:phone":"+32 85 25 49 72",
    "sg:postcode":"4500",
    "sg:province":"Li\u00e8ge",
    "wof:name":"Flament Y",
    "wof:placetype":"venue"
},
  "geometry": {"coordinates":[5.2410359383,50.5180206299],"type":"Point"}
}