{
  "type": "Feature",
  "properties": {
    "addr:full":"Smoutebos 18 Essen Antwerpen 2910",
    "addr:housenumber":"18",
    "addr:postcode":"2910",
    "addr:street":"Smoutebos",
    "iso:country":"BE",
    "sg:address":"Smoutebos 18",
    "sg:city":"Essen",
    "sg:classifiers":[
        {
            "category":"Professional",
            "subcategory":"Business Services",
            "type":"Services"
        }
    ],
    "sg:phone":"+32 3 667 37 24",
    "sg:postcode":"2910",
    "sg:province":"Antwerpen",
    "sg:tags":[
        "bookkeeping"
    ],
    "wof:name":"Van Mol L",
    "wof:placetype":"venue"
},
  "geometry": {"coordinates":[4.4490571022,51.4565429688],"type":"Point"}
}