{
  "type": "Feature",
  "properties": {
    "iso:country":"BE",
    "sg:address":"Grote Markt 41",
    "sg:city":"Herentals",
    "sg:orig_category":"Diverse organisaties and verenigingen",
    "sg:phone":"+32 14 22 05 42",
    "sg:postcode":"2200",
    "sg:province":"Antwerpen",
    "wof:name":"Jeugdhuis 10r20",
    "wof:placetype":"venue"
},
  "geometry": {"coordinates":[4.8355660439,51.1777496338],"type":"Point"}
}