{
  "type": "Feature",
  "properties": {
    "addr:full":"Stationstraat 1 Olen Antwerpen 2250",
    "addr:housenumber":"1",
    "addr:postcode":"2250",
    "addr:street":"Stationstraat",
    "iso:country":"BE",
    "sg:address":"Stationstraat 1",
    "sg:city":"Olen",
    "sg:orig_category":"Enseignement maternel and primaire",
    "sg:phone":"+32 14 22 03 90",
    "sg:postcode":"2250",
    "sg:province":"Antwerpen",
    "wof:name":"Vrije Basisschool",
    "wof:placetype":"venue"
},
  "geometry": {"coordinates":[4.9007720947,51.1679840088],"type":"Point"}
}