{
  "type": "Feature",
  "properties": {
    "iso:country":"BE",
    "sg:address":"Liebroekstraat 111",
    "sg:city":"Halen",
    "sg:classifiers":[
        {
            "category":"Professional",
            "type":"Services"
        }
    ],
    "sg:phone":"+32 13 44 28 88",
    "sg:postcode":"3545",
    "sg:province":"Limburg",
    "sg:tags":[
        "transport"
    ],
    "wof:name":"Euro Volume B.v.b.a.",
    "wof:placetype":"venue"
},
  "geometry": {"coordinates":[5.0907502174,50.9548301697],"type":"Point"}
}