{
  "type": "Feature",
  "properties": {
    "iso:country":"BE",
    "sg:address":"Savy 10",
    "sg:city":"Bastogne",
    "sg:orig_category":"Eleveurs de bovins",
    "sg:phone":"+32 61 21 65 05",
    "sg:postcode":"6600",
    "sg:province":"Luxembourg",
    "wof:name":"Andre Clesse",
    "wof:placetype":"venue"
},
  "geometry": {"coordinates":[5.7042379379,50.0206604004],"type":"Point"}
}