{
  "type": "Feature",
  "properties": {
    "iso:country":"BE",
    "sg:address":"Grote Markt 8",
    "sg:city":"Westerlo",
    "sg:orig_category":"R\u00e9parations d'horloges, montres and bijoux",
    "sg:phone":"+32 14 54 41 72",
    "sg:postcode":"2260",
    "sg:province":"Antwerpen",
    "wof:name":"Jan Thys",
    "wof:placetype":"venue"
},
  "geometry": {"coordinates":[4.916574955,51.0862960815],"type":"Point"}
}