{
  "type": "Feature",
  "properties": {
    "addr:full":"Chemin Des Halles 19 Herve (battice) Li\u00e8ge 4651",
    "addr:housenumber":"19",
    "addr:postcode":"4651",
    "addr:street":"Chemin Des Halles",
    "iso:country":"BE",
    "sg:address":"Chemin Des Halles 19",
    "sg:city":"Herve (battice)",
    "sg:classifiers":[
        {
            "category":"Home & Garden",
            "subcategory":"Garden Supply",
            "type":"Retail Goods"
        }
    ],
    "sg:phone":"+32 87 67 80 34",
    "sg:postcode":"4651",
    "sg:province":"Li\u00e8ge",
    "wof:name":"Pepiniere Du Plateau",
    "wof:placetype":"venue"
},
  "geometry": {"coordinates":[5.7694048882,50.6306343079],"type":"Point"}
}