{
  "type": "Feature",
  "properties": {
    "iso:country":"BE",
    "sg:address":"Generaal Mac Arthurstr. 32",
    "sg:city":"Ukkel/uccle",
    "sg:orig_category":"Artsen and specialisten",
    "sg:phone":"+32 2 344 95 12",
    "sg:postcode":"1180",
    "sg:province":"Bruxelles-Capitale",
    "wof:name":"Cohn Rene",
    "wof:placetype":"venue"
},
  "geometry": {"coordinates":[4.3544278145,50.8129081726],"type":"Point"}
}