{
  "type": "Feature",
  "properties": {
    "addr:full":"Rue Des Juifs 3 Saint-ghislain Hainaut 7331",
    "addr:housenumber":"3",
    "addr:postcode":"7331",
    "addr:street":"Rue Des Juifs;Hainaut",
    "iso:country":"BE",
    "sg:address":"Rue Des Juifs 3",
    "sg:city":"Saint-ghislain",
    "sg:orig_category":"Herstellingen and onderhoud van auto's",
    "sg:phone":"+32 65 64 16 73",
    "sg:postcode":"7331",
    "sg:province":"Hainaut",
    "wof:name":"G. Lemaire",
    "wof:placetype":"venue"
},
  "geometry": {"coordinates":[3.832367897,50.4841804504],"type":"Point"}
}