{
  "type": "Feature",
  "properties": {
    "addr:full":"Parklaan 30 Temse Oost-Vlaanderen 9140",
    "addr:housenumber":"30",
    "addr:postcode":"9140",
    "addr:street":"Parklaan",
    "iso:country":"BE",
    "sg:address":"Parklaan 30",
    "sg:city":"Temse",
    "sg:classifiers":[
        {
            "category":"Structure",
            "subcategory":"Office Building",
            "type":"Public Place"
        }
    ],
    "sg:phone":"+32 3 771 42 32",
    "sg:postcode":"9140",
    "sg:province":"Oost-Vlaanderen",
    "sg:tags":[
        "-",
        "type",
        "door",
        "sliding",
        "overhead"
    ],
    "wof:name":"F Waltens",
    "wof:placetype":"venue"
},
  "geometry": {"coordinates":[4.2238898277,51.1257705688],"type":"Point"}
}