{
  "type": "Feature",
  "properties": {
    "iso:country":"BE",
    "sg:address":"Kleemstraat 68",
    "sg:city":"Sint-niklaas",
    "sg:orig_category":"Rundveehouders Varkenskwekers",
    "sg:phone":"+32 3 772 40 23",
    "sg:postcode":"9111",
    "sg:province":"Oost-Vlaanderen",
    "wof:name":"Kris De Belie Paulen",
    "wof:placetype":"venue"
},
  "geometry": {"coordinates":[4.083837986,51.1519088745],"type":"Point"}
}