{
  "type": "Feature",
  "properties": {
    "addr:full":"Werkenstraat 81 Kortemark (handzame) West-Vlaanderen 8610",
    "addr:housenumber":"81",
    "addr:postcode":"8610",
    "addr:street":"Werkenstraat",
    "iso:country":"BE",
    "sg:address":"Werkenstraat 81",
    "sg:city":"Kortemark (handzame)",
    "sg:classifiers":[
        {
            "category":"Building & Trades",
            "subcategory":"Construction",
            "type":"Services"
        }
    ],
    "sg:phone":"+32 51 56 67 34",
    "sg:postcode":"8610",
    "sg:province":"West-Vlaanderen",
    "sg:tags":[
        "carpenter"
    ],
    "wof:name":"Dewilde En Zn Bvba",
    "wof:placetype":"venue"
},
  "geometry": {"coordinates":[2.9843139648,51.0263061523],"type":"Point"}
}