{
  "type": "Feature",
  "properties": {
    "iso:country":"BE",
    "sg:address":"Okkevoordestraat 39",
    "sg:city":"Sint-gillis-waas",
    "sg:classifiers":[
        {
            "category":"Structure",
            "subcategory":"Office Building",
            "type":"Public Place"
        }
    ],
    "sg:phone":"+32 3 707 00 24",
    "sg:postcode":"9170",
    "sg:province":"Oost-Vlaanderen",
    "sg:tags":[
        "-",
        "type",
        "door",
        "sliding",
        "overhead"
    ],
    "wof:name":"Laureys M",
    "wof:placetype":"venue"
},
  "geometry": {"coordinates":[4.1422300339,51.2234992981],"type":"Point"}
}