{
  "type": "Feature",
  "properties": {
    "addr:full":"Houthulststraat 9 Brugge West-Vlaanderen 8000",
    "addr:housenumber":"9",
    "addr:postcode":"8000",
    "addr:street":"Houthulststraat",
    "iso:country":"BE",
    "sg:address":"Houthulststraat 9",
    "sg:city":"Brugge",
    "sg:classifiers":[
        {
            "category":"Professional",
            "subcategory":"Lawyer & Legal Services",
            "type":"Services"
        }
    ],
    "sg:phone":"+32 50 67 55 75",
    "sg:postcode":"8000",
    "sg:province":"West-Vlaanderen",
    "wof:name":"De Busscher Jan & Vandeputte Riet Advokatenkantoor",
    "wof:placetype":"venue"
},
  "geometry": {"coordinates":[3.2137029171,51.2174072266],"type":"Point"}
}