{
  "type": "Feature",
  "properties": {
    "addr:full":"Markt 35 Mol Antwerpen 2400",
    "addr:housenumber":"35",
    "addr:postcode":"2400",
    "addr:street":"Markt",
    "iso:country":"BE",
    "sg:address":"Markt 35",
    "sg:city":"Mol",
    "sg:orig_category":"Banken and kredietinstellingen",
    "sg:phone":"+32 14 31 44 47",
    "sg:postcode":"2400",
    "sg:province":"Antwerpen",
    "wof:name":"Beroepskrediet",
    "wof:placetype":"venue"
},
  "geometry": {"coordinates":[5.116517067,51.1846046448],"type":"Point"}
}