{
  "type": "Feature",
  "properties": {
    "addr:full":"Rue Bruy\u00c8re-saint-jean 137 Waterloo Brabant Wallon 1410",
    "addr:housenumber":"137",
    "addr:postcode":"1410",
    "addr:street":"Rue Bruye\u0300Re-Saint-Jean",
    "iso:country":"BE",
    "sg:address":"Rue Bruy\u00c8re-saint-jean 137",
    "sg:city":"Waterloo",
    "sg:orig_category":"Secr\u00e9tariats",
    "sg:phone":"+32 2 354 10 99",
    "sg:postcode":"1410",
    "sg:province":"Brabant Wallon",
    "wof:name":"Mouse Power",
    "wof:placetype":"venue"
},
  "geometry": {"coordinates":[4.3741822243,50.7147254944],"type":"Point"}
}