{
  "type": "Feature",
  "properties": {
    "addr:full":"Ch De Bruxelles 200g Waterloo Brabant Wallon 1410",
    "addr:housenumber":"200g",
    "addr:postcode":"1410",
    "addr:street":"Ch De Bruxelles",
    "iso:country":"BE",
    "sg:address":"Ch De Bruxelles 200g",
    "sg:city":"Waterloo",
    "sg:classifiers":[
        {
            "category":"Travel",
            "subcategory":"Hotels & Motels",
            "type":"Entertainment"
        }
    ],
    "sg:phone":"+32 2 354 01 05",
    "sg:postcode":"1410",
    "sg:province":"Brabant Wallon",
    "sg:tags":[
        "hotels",
        "business",
        "restaurant"
    ],
    "wof:name":"Hotel Le Cote Vert Sa",
    "wof:placetype":"venue"
},
  "geometry": {"coordinates":[4.3975458145,50.7197608948],"type":"Point"}
}