{
  "type": "Feature",
  "properties": {
    "iso:country":"BE",
    "sg:address":"Galgstraat 50",
    "sg:city":"Sint-pieters-leeuw",
    "sg:orig_category":"Cr\u00e9meries",
    "sg:phone":"+32 2 378 28 55",
    "sg:postcode":"1600",
    "sg:province":"Vlaams-Brabant",
    "wof:name":"Moons W & Zoon",
    "wof:placetype":"venue"
},
  "geometry": {"coordinates":[4.2662172318,50.786491394],"type":"Point"}
}