{
  "type": "Feature",
  "properties": {
    "iso:country":"BE",
    "sg:address":"Nieuwstraat 8",
    "sg:city":"Wingene",
    "sg:orig_category":"Landbouwmachines Gh Tuinbenodigdheden",
    "sg:phone":"+32 51 65 50 80",
    "sg:postcode":"8750",
    "sg:province":"West-Vlaanderen",
    "wof:name":"Deroo",
    "wof:placetype":"venue"
},
  "geometry": {"coordinates":[3.2786550522,51.0610542297],"type":"Point"}
}