{
  "type": "Feature",
  "properties": {
    "addr:full":"Voskenslaan 147 Gent Oost-Vlaanderen 9000",
    "addr:housenumber":"147",
    "addr:postcode":"9000",
    "addr:street":"Voskenslaan;Oost-Vlaanderen",
    "iso:country":"BE",
    "sg:address":"Voskenslaan 147",
    "sg:city":"Gent",
    "sg:orig_category":"Schoonmaakbedrijven and ongediertebestrijding",
    "sg:phone":"+32 9 243 83 00",
    "sg:postcode":"9000",
    "sg:province":"Oost-Vlaanderen",
    "wof:name":"Euroclean",
    "wof:placetype":"venue"
},
  "geometry": {"coordinates":[3.7067899704,51.0311851501],"type":"Point"}
}