{
  "type": "Feature",
  "properties": {
    "iso:country":"BE",
    "sg:address":"Industrielaan 20",
    "sg:city":"Overpelt",
    "sg:classifiers":[
        {
            "category":"Home & Garden",
            "subcategory":"Furniture",
            "type":"Retail Goods"
        }
    ],
    "sg:phone":"+32 11 80 07 00",
    "sg:postcode":"3900",
    "sg:province":"Limburg",
    "sg:tags":[
        "professional",
        "household",
        "wood"
    ],
    "wof:name":"Pami Nv",
    "wof:placetype":"venue"
},
  "geometry": {"coordinates":[5.3659601212,51.2179603577],"type":"Point"}
}