{
  "type": "Feature",
  "properties": {
    "iso:country":"BE",
    "sg:address":"Omgangstraat 11",
    "sg:city":"Bornem",
    "sg:orig_category":"Salles de conf\u00e9rences and de r\u00e9ceptions",
    "sg:phone":"+32 52 33 54 27",
    "sg:postcode":"2880",
    "sg:province":"Antwerpen",
    "wof:name":"Sinte-marie",
    "wof:placetype":"venue"
},
  "geometry": {"coordinates":[4.1899461746,51.0608901978],"type":"Point"}
}