{
  "type": "Feature",
  "properties": {
    "iso:country":"BE",
    "sg:address":"Rue Du Horloz 5",
    "sg:city":"Saint-nicolas",
    "sg:classifiers":[
        {
            "category":"Professional",
            "subcategory":"Testing Lab",
            "type":"Services"
        }
    ],
    "sg:phone":"+32 4 233 88 40",
    "sg:postcode":"4420",
    "sg:province":"Li\u00e8ge",
    "sg:tags":[
        "chemist"
    ],
    "wof:name":"Mathot",
    "wof:placetype":"venue"
},
  "geometry": {"coordinates":[5.5316591263,50.6292610168],"type":"Point"}
}