{
  "type": "Feature",
  "properties": {
    "iso:country":"BE",
    "sg:address":"Borzestraat 1",
    "sg:city":"Mechelen",
    "sg:classifiers":[
        {
            "category":"Shopping",
            "subcategory":"Pets & Pet Supplies",
            "type":"Retail Goods"
        }
    ],
    "sg:phone":"+32 475 80 50 29",
    "sg:postcode":"2800",
    "sg:province":"Antwerpen",
    "sg:tags":[
        "shop",
        "-"
    ],
    "wof:name":"Elsenberghen Bvba",
    "wof:placetype":"venue"
},
  "geometry": {"coordinates":[4.4792537689,51.0268745422],"type":"Point"}
}