{
  "type": "Feature",
  "properties": {
    "addr:full":"Rue De L\u00b4arsenal 25 Namur Namur 5000",
    "addr:housenumber":"25",
    "addr:postcode":"5000",
    "addr:street":"Rue De L\u00b4Arsenal",
    "iso:country":"BE",
    "sg:address":"Rue De L\u00b4arsenal 25",
    "sg:city":"Namur",
    "sg:orig_category":"RESTAURANTS: PAIN, P\u00c2TISSERIES AND CONFISERIES",
    "sg:phone":"+32 81 22 25 51",
    "sg:postcode":"5000",
    "sg:province":"Namur",
    "wof:name":"Dechamps Alain",
    "wof:placetype":"venue"
},
  "geometry": {"coordinates":[4.8579387665,50.4646148682],"type":"Point"}
}