{
  "type": "Feature",
  "properties": {
    "addr:full":"Rue De Bray 84 La Louviere Hainaut 7110",
    "addr:housenumber":"84",
    "addr:postcode":"7110",
    "addr:street":"Rue De Bray",
    "iso:country":"BE",
    "sg:address":"Rue De Bray 84",
    "sg:city":"La Louviere",
    "sg:orig_category":"R\u00e9parations d'appareils \u00e9lectrom\u00e9nagers",
    "sg:phone":"+32 64 66 57 21",
    "sg:postcode":"7110",
    "sg:province":"Hainaut",
    "wof:name":"Fr\u00c9d\u00c9ric Querriaux",
    "wof:placetype":"venue"
},
  "geometry": {"coordinates":[4.099293232,50.4499931335],"type":"Point"}
}