{
  "type": "Feature",
  "properties": {
    "iso:country":"BE",
    "sg:address":"Mechelsesteenweg 118",
    "sg:city":"Willebroek",
    "sg:orig_category":"Instellingen voor mindervalide volwassenen",
    "sg:phone":"+32 3 866 22 33",
    "sg:postcode":"2830",
    "sg:province":"Antwerpen",
    "wof:name":"De Meerpaal",
    "wof:placetype":"venue"
},
  "geometry": {"coordinates":[4.3713641167,51.0562095642],"type":"Point"}
}