{
  "type": "Feature",
  "properties": {
    "addr:full":"Rue Nicolay 9 Brussel/bruxelles Bruxelles-Capitale 1000",
    "addr:housenumber":"9",
    "addr:postcode":"1000",
    "addr:street":"Rue Nicolay;/",
    "iso:country":"BE",
    "sg:address":"Rue Nicolay 9",
    "sg:city":"Brussel/bruxelles",
    "sg:orig_category":"Enseignement maternel and primaire",
    "sg:phone":"+32 2 203 36 27",
    "sg:postcode":"1000",
    "sg:province":"Bruxelles-Capitale",
    "wof:name":"Ecole Fond. Communale",
    "wof:placetype":"venue"
},
  "geometry": {"coordinates":[4.3535051346,50.8598442078],"type":"Point"}
}