{
  "type": "Feature",
  "properties": {
    "iso:country":"BE",
    "sg:address":"Nieuwstraat 70",
    "sg:city":"Haacht",
    "sg:orig_category":"Sportclubs",
    "sg:phone":"+32 16 60 62 58",
    "sg:postcode":"3150",
    "sg:province":"Vlaams-Brabant",
    "wof:name":"V.c. De Mitters Wespelaar",
    "wof:placetype":"venue"
},
  "geometry": {"coordinates":[4.6447892189,50.959072113],"type":"Point"}
}