{
  "type": "Feature",
  "properties": {
    "iso:country":"BE",
    "sg:address":"Achttiende - Oogstwal 9",
    "sg:city":"Tongeren",
    "sg:orig_category":"Belastingconsulenten Diverse juridische dienstverlening",
    "sg:phone":"+32 12 23 63 43",
    "sg:postcode":"3700",
    "sg:province":"Limburg",
    "wof:name":"S.b.b.",
    "wof:placetype":"venue"
},
  "geometry": {"coordinates":[5.470459938,50.783706665],"type":"Point"}
}