{
  "type": "Feature",
  "properties": {
    "addr:full":"Burrelstraat 34 Sint-niklaas Oost-Vlaanderen 9100",
    "addr:housenumber":"34",
    "addr:postcode":"9100",
    "addr:street":"Burrelstraat",
    "iso:country":"BE",
    "sg:address":"Burrelstraat 34",
    "sg:city":"Sint-niklaas",
    "sg:orig_category":"Artsen and specialisten",
    "sg:phone":"+32 3 766 15 34",
    "sg:postcode":"9100",
    "sg:province":"Oost-Vlaanderen",
    "wof:name":"Sabina Liekens",
    "wof:placetype":"venue"
},
  "geometry": {"coordinates":[4.1435317993,51.1448326111],"type":"Point"}
}