{
  "type": "Feature",
  "properties": {
    "iso:country":"BE",
    "sg:address":"Chauss\u00e9e De Bruxelles 46",
    "sg:city":"La Hulpe",
    "sg:classifiers":[
        {
            "category":"Retail",
            "subcategory":"Auto Repair",
            "type":"Services"
        }
    ],
    "sg:phone":"+32 2 654 00 20",
    "sg:postcode":"1310",
    "sg:province":"Brabant Wallon",
    "sg:tags":[
        "garage"
    ],
    "wof:name":"Dellis D",
    "wof:placetype":"venue"
},
  "geometry": {"coordinates":[4.4800930023,50.7326622009],"type":"Point"}
}