{
  "type": "Feature",
  "properties": {
    "addr:full":"Lage Kaart 34 Brasschaat Antwerpen 2930",
    "addr:housenumber":"34",
    "addr:postcode":"2930",
    "addr:street":"Lage Kaart",
    "iso:country":"BE",
    "sg:address":"Lage Kaart 34",
    "sg:city":"Brasschaat",
    "sg:classifiers":[
        {
            "category":"Real Estate",
            "subcategory":"Architect",
            "type":"Services"
        }
    ],
    "sg:phone":"+32 3 231 62 97",
    "sg:postcode":"2930",
    "sg:province":"Antwerpen",
    "wof:name":"Frimout M",
    "wof:placetype":"venue"
},
  "geometry": {"coordinates":[4.453856945,51.2933998108],"type":"Point"}
}