{
  "type": "Feature",
  "properties": {
    "iso:country":"BE",
    "sg:address":"De Krab 8",
    "sg:city":"Knokke-heist",
    "sg:orig_category":"Landmeters and schatters",
    "sg:phone":"+32 50 51 76 42",
    "sg:postcode":"8301",
    "sg:province":"West-Vlaanderen",
    "wof:name":"Vyvey M.",
    "wof:placetype":"venue"
},
  "geometry": {"coordinates":[3.2639000416,51.3396911621],"type":"Point"}
}