{
  "type": "Feature",
  "properties": {
    "addr:full":"Biezenstraat 24 Tienen Vlaams-Brabant 3300",
    "addr:housenumber":"24",
    "addr:postcode":"3300",
    "addr:street":"Biezenstraat",
    "iso:country":"BE",
    "sg:address":"Biezenstraat 24",
    "sg:city":"Tienen",
    "sg:orig_category":"Kapsalons",
    "sg:phone":"+32 16 81 52 55",
    "sg:postcode":"3300",
    "sg:province":"Vlaams-Brabant",
    "wof:name":"Jacqueline Vos",
    "wof:placetype":"venue"
},
  "geometry": {"coordinates":[4.9255671501,50.8021774292],"type":"Point"}
}