{
  "type": "Feature",
  "properties": {
    "addr:full":"Chemin Des P\u00c9lerins 5 Tournai Hainaut 7542",
    "addr:housenumber":"5",
    "addr:postcode":"7542",
    "addr:street":"Chemin Des Pe\u0301Lerins",
    "iso:country":"BE",
    "sg:address":"Chemin Des P\u00c9lerins 5",
    "sg:city":"Tournai",
    "sg:orig_category":"M\u00e9decins and sp\u00e9cialistes",
    "sg:phone":"+32 69 22 76 46",
    "sg:postcode":"7542",
    "sg:province":"Hainaut",
    "wof:name":"Marie-christine Deviviers",
    "wof:placetype":"venue"
},
  "geometry": {"coordinates":[3.4003000259,50.6479492188],"type":"Point"}
}