{
  "type": "Feature",
  "properties": {
    "iso:country":"BE",
    "sg:address":"Rue Rome 1",
    "sg:city":"Durbuy",
    "sg:classifiers":[
        {
            "category":"Travel",
            "subcategory":"Resort",
            "type":"Entertainment"
        }
    ],
    "sg:phone":"+32 86 36 76 96",
    "sg:postcode":"6940",
    "sg:province":"Luxembourg",
    "sg:tags":[
        "farm",
        "house",
        "holiday",
        "guest"
    ],
    "wof:name":"Rome Detente Sprl",
    "wof:placetype":"venue"
},
  "geometry": {"coordinates":[5.4547491074,50.3407783508],"type":"Point"}
}