{
  "type": "Feature",
  "properties": {
    "iso:country":"BE",
    "sg:address":"Wenduinesteenweg 125",
    "sg:city":"De Haan",
    "sg:orig_category":"Kampeerterreinen",
    "sg:phone":"+32 59 23 42 18",
    "sg:postcode":"8421",
    "sg:province":"West-Vlaanderen",
    "wof:name":"Strooiendorp",
    "wof:placetype":"venue"
},
  "geometry": {"coordinates":[3.042429924,51.2756004333],"type":"Point"}
}