{
  "type": "Feature",
  "properties": {
    "addr:full":"Fourquepire 9 Ellezelles Hainaut 7890",
    "addr:housenumber":"9",
    "addr:postcode":"7890",
    "addr:street":"Fourquepire",
    "iso:country":"BE",
    "sg:address":"Fourquepire 9",
    "sg:city":"Ellezelles",
    "sg:classifiers":[
        {
            "category":"Social Services",
            "subcategory":"Job Training",
            "type":"Services"
        }
    ],
    "sg:phone":"+32 68 54 26 13",
    "sg:postcode":"7890",
    "sg:province":"Hainaut",
    "sg:tags":[
        "agricoles",
        "plantes",
        "gr",
        "fleurs",
        "machine",
        "mat\u00e9riel"
    ],
    "wof:name":"La Grange Aux Fleurs",
    "wof:placetype":"venue"
},
  "geometry": {"coordinates":[3.6846311092,50.7268676758],"type":"Point"}
}