{
  "type": "Feature",
  "properties": {
    "addr:full":"Rue Ainseveau 6 Viroinval Namur 5670",
    "addr:housenumber":"6",
    "addr:postcode":"5670",
    "addr:street":"Rue Ainseveau",
    "iso:country":"BE",
    "sg:address":"Rue Ainseveau 6",
    "sg:city":"Viroinval",
    "sg:orig_category":"M\u00e9decins and sp\u00e9cialistes",
    "sg:phone":"+32 60 31 20 00",
    "sg:postcode":"5670",
    "sg:province":"Namur",
    "wof:name":"M C Sim\u00c9on",
    "wof:placetype":"venue"
},
  "geometry": {"coordinates":[4.5464258194,50.0753211975],"type":"Point"}
}