{
  "type": "Feature",
  "properties": {
    "addr:full":"Braambessenstraat 27 Dilbeek Vlaams-Brabant 1700",
    "addr:housenumber":"27",
    "addr:postcode":"1700",
    "addr:street":"Braambessenstraat",
    "iso:country":"BE",
    "sg:address":"Braambessenstraat 27",
    "sg:city":"Dilbeek",
    "sg:classifiers":[
        {
            "category":"Professional",
            "subcategory":"Art Services",
            "type":"Services"
        }
    ],
    "sg:phone":"+32 2 466 78 13",
    "sg:postcode":"1700",
    "sg:province":"Vlaams-Brabant",
    "sg:tags":[
        "graphic",
        "designer"
    ],
    "wof:name":"Van Wambeke T",
    "wof:placetype":"venue"
},
  "geometry": {"coordinates":[4.2443809509,50.8606147766],"type":"Point"}
}