{
  "type": "Feature",
  "properties": {
    "iso:country":"BE",
    "sg:address":"Rue De Harz\u00e9 22",
    "sg:city":"La Roche-en-ardenne",
    "sg:classifiers":[
        {
            "category":"Fast Food",
            "type":"Food & Drink"
        }
    ],
    "sg:phone":"+32 84 36 79 67",
    "sg:postcode":"6980",
    "sg:province":"Luxembourg",
    "sg:tags":[
        "fried",
        "stand",
        "potato"
    ],
    "wof:name":"Grillon (le) Restaurant",
    "wof:placetype":"venue"
},
  "geometry": {"coordinates":[5.5740408897,50.1908950806],"type":"Point"}
}