{
  "type": "Feature",
  "properties": {
    "iso:country":"BE",
    "sg:address":"Onderheide 40",
    "sg:city":"Brasschaat",
    "sg:classifiers":[
        {
            "category":"Professional",
            "subcategory":"Management & Consulting",
            "type":"Services"
        }
    ],
    "sg:phone":"+32 3 653 09 29",
    "sg:postcode":"2930",
    "sg:province":"Antwerpen",
    "sg:tags":[
        "consultant",
        "agency",
        "advertising"
    ],
    "wof:name":"Tailor Made Consult",
    "wof:placetype":"venue"
},
  "geometry": {"coordinates":[4.4996218681,51.310382843],"type":"Point"}
}