{
  "type": "Feature",
  "properties": {
    "addr:full":"Galgstraat 166 Sint-pieters-leeuw Vlaams-Brabant 1600",
    "addr:housenumber":"166",
    "addr:postcode":"1600",
    "addr:street":"Galgstraat",
    "iso:country":"BE",
    "sg:address":"Galgstraat 166",
    "sg:city":"Sint-pieters-leeuw",
    "sg:classifiers":[
        {
            "category":"Health Services",
            "subcategory":"Health Practitioner",
            "type":"Services"
        }
    ],
    "sg:phone":"+32 2 377 91 06",
    "sg:postcode":"1600",
    "sg:province":"Vlaams-Brabant",
    "sg:tags":[
        "physiotherapist"
    ],
    "wof:name":"Vander Borght Val\u00e9rie",
    "wof:placetype":"venue"
},
  "geometry": {"coordinates":[4.254696846,50.7814483643],"type":"Point"}
}