{
  "type": "Feature",
  "properties": {
    "addr:full":"Rue De La Perche 38 Colfontaine Hainaut 7340",
    "addr:housenumber":"38",
    "addr:postcode":"7340",
    "addr:street":"Rue De La Perche",
    "iso:country":"BE",
    "sg:address":"Rue De La Perche 38",
    "sg:city":"Colfontaine",
    "sg:orig_category":"Supermarkten",
    "sg:phone":"+32 65 67 34 89",
    "sg:postcode":"7340",
    "sg:province":"Hainaut",
    "wof:name":"Gb Contact",
    "wof:placetype":"venue"
},
  "geometry": {"coordinates":[3.8592269421,50.4087142944],"type":"Point"}
}