{
  "type": "Feature",
  "properties": {
    "iso:country":"BE",
    "sg:address":"Rue Du Bola 14",
    "sg:city":"Herve",
    "sg:orig_category":"M\u00e9decins and sp\u00e9cialistes",
    "sg:phone":"+32 87 34 03 51",
    "sg:postcode":"4650",
    "sg:province":"Li\u00e8ge",
    "wof:name":"Jean-pierre Christophe",
    "wof:placetype":"venue"
},
  "geometry": {"coordinates":[5.8066301346,50.6064872742],"type":"Point"}
}