{
  "type": "Feature",
  "properties": {
    "addr:full":"Statiestraat 91 Anzegem West-Vlaanderen 8570",
    "addr:housenumber":"91",
    "addr:postcode":"8570",
    "addr:street":"Statiestraat",
    "iso:country":"BE",
    "sg:address":"Statiestraat 91",
    "sg:city":"Anzegem",
    "sg:classifiers":[
        {
            "category":"Personal",
            "subcategory":"Beauty Salon",
            "type":"Services"
        }
    ],
    "sg:phone":"+32 56 68 96 41",
    "sg:postcode":"8570",
    "sg:province":"West-Vlaanderen",
    "sg:tags":[
        "lady",
        "-",
        "hairdressing"
    ],
    "wof:name":"Forccina Haarstudio",
    "wof:placetype":"venue"
},
  "geometry": {"coordinates":[3.4921519756,50.827507019],"type":"Point"}
}