{
  "type": "Feature",
  "properties": {
    "addr:full":"Zoning Des Cahottes 43 Fl\u00c9malle Li\u00e8ge 4400",
    "addr:housenumber":"43",
    "addr:postcode":"4400",
    "addr:street":"Zoning",
    "iso:country":"BE",
    "sg:address":"Zoning Des Cahottes 43",
    "sg:city":"Fl\u00c9malle",
    "sg:orig_category":"Meubelzaken, woning- and keukeninrichting",
    "sg:phone":"+32 473 93 15 17",
    "sg:postcode":"4400",
    "sg:province":"Li\u00e8ge",
    "wof:name":"Sit Down",
    "wof:placetype":"venue"
},
  "geometry": {"coordinates":[5.4325499535,50.6207771301],"type":"Point"}
}