{
  "type": "Feature",
  "properties": {
    "addr:full":"Quai Aux Hu\u00cetres 22 Wavre Brabant Wallon 1300",
    "addr:housenumber":"22;1300",
    "addr:street":"Quai Aux Hui\u0302Tres",
    "iso:country":"BE",
    "sg:address":"Quai Aux Hu\u00cetres 22",
    "sg:city":"Wavre",
    "sg:orig_category":"R\u00e9parations \u00e0 domicile d'appareils \u00e9lectriques",
    "sg:phone":"+32 475 69 32 56",
    "sg:postcode":"1300",
    "sg:province":"Brabant Wallon",
    "wof:name":"Collart Marc",
    "wof:placetype":"venue"
},
  "geometry": {"coordinates":[4.6116380692,50.7152099609],"type":"Point"}
}