{
  "type": "Feature",
  "properties": {
    "addr:full":"Route De Biesme 50 Thuin (biesme-sous-thuin) Hainaut 6531",
    "addr:housenumber":"50",
    "addr:postcode":"6531",
    "addr:street":"Route De Biesme",
    "iso:country":"BE",
    "sg:address":"Route De Biesme 50",
    "sg:city":"Thuin (biesme-sous-thuin)",
    "sg:orig_category":"Non-Classified Establishments",
    "sg:phone":"+32 71 59 59 82",
    "sg:postcode":"6531",
    "sg:province":"Hainaut",
    "wof:name":"P S I",
    "wof:placetype":"venue"
},
  "geometry": {"coordinates":[4.3064169884,50.3253211975],"type":"Point"}
}