{
  "type": "Feature",
  "properties": {
    "addr:full":"Avenue De La D\u00e9portation 41 Ecaussinnes (ecaussinnes-d'enghien) Hainaut 7190",
    "addr:housenumber":"41",
    "addr:postcode":"7190",
    "addr:street":"Avenue De La De\u0301Portation;Ecaussinnes-D'Enghien Hainaut",
    "iso:country":"BE",
    "sg:address":"Avenue De La D\u00e9portation 41",
    "sg:city":"Ecaussinnes (ecaussinnes-d'enghien)",
    "sg:classifiers":[
        {
            "category":"Home & Garden",
            "subcategory":"Household Appliances",
            "type":"Retail Goods"
        }
    ],
    "sg:phone":"+32 67 49 05 17",
    "sg:postcode":"7190",
    "sg:province":"Hainaut",
    "sg:tags":[
        "repair",
        "mainten",
        "-",
        "electric"
    ],
    "wof:name":"Electro D\u00e9pannage",
    "wof:placetype":"venue"
},
  "geometry": {"coordinates":[4.1592750549,50.5625076294],"type":"Point"}
}