{
  "type": "Feature",
  "properties": {
    "iso:country":"BE",
    "sg:address":"Rue Potaerdegat 18a",
    "sg:city":"Bruxelles (molenbeek-saint-jean)",
    "sg:classifiers":[
        {
            "category":"Communications",
            "subcategory":"Film & Video Production",
            "type":"Services"
        }
    ],
    "sg:phone":"+32 2 469 17 00",
    "sg:postcode":"1080",
    "sg:province":"Bruxelles-Capitale",
    "sg:tags":[
        "producer",
        "realizators"
    ],
    "wof:name":"Prime-time Bvba",
    "wof:placetype":"venue"
},
  "geometry": {"coordinates":[4.3058581352,50.8596115112],"type":"Point"}
}