{
  "type": "Feature",
  "properties": {
    "addr:full":"Kloosterstraat 82 Antwerpen (ekeren) Antwerpen 2180",
    "addr:housenumber":"82",
    "addr:postcode":"2180",
    "addr:street":"Kloosterstraat",
    "iso:country":"BE",
    "sg:address":"Kloosterstraat 82",
    "sg:city":"Antwerpen (ekeren)",
    "sg:classifiers":[
        {
            "category":"Education",
            "subcategory":"School",
            "type":"Public Place"
        }
    ],
    "sg:phone":"+32 3 541 01 36",
    "sg:postcode":"2180",
    "sg:province":"Antwerpen",
    "sg:tags":[
        "secondary"
    ],
    "wof:name":"O L Vrouw Van Lourdes Instituut",
    "wof:placetype":"venue"
},
  "geometry": {"coordinates":[4.3941059113,51.2149009705],"type":"Point"}
}