{
  "type": "Feature",
  "properties": {
    "iso:country":"BE",
    "sg:address":"Eindeken 40",
    "sg:city":"Evergem",
    "sg:orig_category":"Artistes ind\u00e9pendants",
    "sg:phone":"+32 9 253 26 04",
    "sg:postcode":"9940",
    "sg:province":"Oost-Vlaanderen",
    "wof:name":"Brigitte Pauwels",
    "wof:placetype":"venue"
},
  "geometry": {"coordinates":[3.7091898918,51.106716156],"type":"Point"}
}