{
  "type": "Feature",
  "properties": {
    "iso:country":"BE",
    "sg:address":"Wakkensteenweg 70",
    "sg:city":"Wielsbeke",
    "sg:orig_category":"Loodgieterij, verwarming and sanitaire installaties",
    "sg:phone":"+32 56 60 22 20",
    "sg:postcode":"8710",
    "sg:province":"West-Vlaanderen",
    "wof:name":"Maurice Vandekerckhove",
    "wof:placetype":"venue"
},
  "geometry": {"coordinates":[3.3940560818,50.9220046997],"type":"Point"}
}