{
  "type": "Feature",
  "properties": {
    "addr:full":"Hoogeind 64 Hoogstraten Antwerpen 2321",
    "addr:housenumber":"64",
    "addr:postcode":"2321",
    "addr:street":"Hoogeind",
    "iso:country":"BE",
    "sg:address":"Hoogeind 64",
    "sg:city":"Hoogstraten",
    "sg:orig_category":"Groententeelt",
    "sg:phone":"+32 3 315 75 92",
    "sg:postcode":"2321",
    "sg:province":"Antwerpen",
    "wof:name":"Corneel Vermeiren",
    "wof:placetype":"venue"
},
  "geometry": {"coordinates":[4.7351031303,51.46484375],"type":"Point"}
}