{
  "type": "Feature",
  "properties": {
    "iso:country":"BE",
    "sg:address":"Rue Haute 45",
    "sg:city":"Hensies",
    "sg:classifiers":[
        {
            "category":"Health Services",
            "subcategory":"Doctor",
            "type":"Services"
        }
    ],
    "sg:phone":"+32 65 46 52 12",
    "sg:postcode":"7350",
    "sg:province":"Hainaut",
    "sg:tags":[
        "medicinephysicians",
        "surgeon"
    ],
    "wof:name":"Berchiche R",
    "wof:placetype":"venue"
},
  "geometry": {"coordinates":[3.6836268902,50.4343109131],"type":"Point"}
}