{
  "type": "Feature",
  "properties": {
    "addr:full":"Beilen 10 Olen Antwerpen 2250",
    "addr:housenumber":"10",
    "addr:postcode":"2250",
    "addr:street":"Beilen",
    "iso:country":"BE",
    "sg:address":"Beilen 10",
    "sg:city":"Olen",
    "sg:classifiers":[
        {
            "category":"Manufacturing",
            "subcategory":"Tools & Machinery",
            "type":"Manufacturing & Wholesale Goods"
        }
    ],
    "sg:phone":"+32 14 21 16 29",
    "sg:postcode":"2250",
    "sg:province":"Antwerpen",
    "sg:tags":[
        "-"
    ],
    "wof:name":"Verbinnen-dieltjens J",
    "wof:placetype":"venue"
},
  "geometry": {"coordinates":[4.8974618912,51.1668167114],"type":"Point"}
}