{
  "type": "Feature",
  "properties": {
    "iso:country":"BE",
    "sg:address":"Stuivenbergvaart 105",
    "sg:city":"Mechelen",
    "sg:classifiers":[
        {
            "category":"Health Services",
            "subcategory":"Health Practitioner",
            "type":"Services"
        }
    ],
    "sg:phone":"+32 15 41 97 52",
    "sg:postcode":"2800",
    "sg:province":"Antwerpen",
    "sg:tags":[
        "physiotherapist"
    ],
    "wof:name":"Crab C",
    "wof:placetype":"venue"
},
  "geometry": {"coordinates":[4.4629487991,51.0265541077],"type":"Point"}
}