{
  "type": "Feature",
  "properties": {
    "addr:full":"Rue D'ascotte 70 Braine-le-comte (hennuy\u00e8res) Hainaut 7090",
    "addr:housenumber":"70",
    "addr:postcode":"7090",
    "addr:street":"Rue D'Ascotte;Hennuye\u0300Res Hainaut",
    "iso:country":"BE",
    "sg:address":"Rue D'ascotte 70",
    "sg:city":"Braine-le-comte (hennuy\u00e8res)",
    "sg:classifiers":[
        {
            "category":"Health Services",
            "subcategory":"Health Practitioner",
            "type":"Services"
        }
    ],
    "sg:phone":"+32 67 55 65 88",
    "sg:postcode":"7090",
    "sg:province":"Hainaut",
    "sg:tags":[
        "therapist",
        "speech"
    ],
    "wof:name":"Singele C",
    "wof:placetype":"venue"
},
  "geometry": {"coordinates":[4.1355600357,50.610748291],"type":"Point"}
}