{
  "type": "Feature",
  "properties": {
    "addr:full":"Smetledestraat 2b Wichelen (serskamp) Oost-Vlaanderen 9260",
    "addr:housenumber":"2b",
    "addr:postcode":"9260",
    "addr:street":"Smetledestraat",
    "iso:country":"BE",
    "sg:address":"Smetledestraat 2b",
    "sg:city":"Wichelen (serskamp)",
    "sg:classifiers":[
        {
            "category":"Real Estate",
            "subcategory":"Surveying",
            "type":"Services"
        }
    ],
    "sg:phone":"+32 9 369 46 33",
    "sg:postcode":"9260",
    "sg:province":"Oost-Vlaanderen",
    "sg:tags":[
        "surveyor",
        "land"
    ],
    "wof:name":"Vereecken M",
    "wof:placetype":"venue"
},
  "geometry": {"coordinates":[3.9370360374,50.9775924683],"type":"Point"}
}