{
  "type": "Feature",
  "properties": {
    "addr:full":"Diestsesteenweg 3 Lubbeek Vlaams-Brabant 3210",
    "addr:housenumber":"3",
    "addr:postcode":"3210",
    "addr:street":"Diestsesteenweg",
    "iso:country":"BE",
    "sg:address":"Diestsesteenweg 3",
    "sg:city":"Lubbeek",
    "sg:orig_category":"Afbraak- and draineerwerken",
    "sg:phone":"+32 16 25 33 72",
    "sg:postcode":"3210",
    "sg:province":"Vlaams-Brabant",
    "wof:name":"Vaillemans",
    "wof:placetype":"venue"
},
  "geometry": {"coordinates":[4.8020000458,50.8922615051],"type":"Point"}
}