{
  "type": "Feature",
  "properties": {
    "iso:country":"BE",
    "sg:address":"Meir 17",
    "sg:city":"Antwerpen",
    "sg:classifiers":[
        {
            "category":"Shopping",
            "subcategory":"Clothing, Apparel, & Fashions",
            "type":"Retail Goods"
        }
    ],
    "sg:phone":"+32 3 231 80 00",
    "sg:postcode":"2000",
    "sg:province":"Antwerpen",
    "sg:tags":[
        "lingerie",
        "sous-v\u00eatements"
    ],
    "wof:name":"Hunkem\u00d6ller",
    "wof:placetype":"venue"
},
  "geometry": {"coordinates":[4.4062991142,51.2183837891],"type":"Point"}
}