{
  "type": "Feature",
  "properties": {
    "addr:full":"Gravenstraat 40 Holsbeek (sint-pieters-rode) Vlaams-Brabant 3220",
    "addr:housenumber":"40",
    "addr:postcode":"3220",
    "addr:street":"Gravenstraat",
    "iso:country":"BE",
    "sg:address":"Gravenstraat 40",
    "sg:city":"Holsbeek (sint-pieters-rode)",
    "sg:classifiers":[
        {
            "category":"Building & Trades",
            "subcategory":"Construction",
            "type":"Services"
        }
    ],
    "sg:phone":"+32 16 62 27 26",
    "sg:postcode":"3220",
    "sg:province":"Vlaams-Brabant",
    "sg:tags":[
        "builder",
        "chimney"
    ],
    "wof:name":"De Hertoghe-sauer W",
    "wof:placetype":"venue"
},
  "geometry": {"coordinates":[4.8161168098,50.9314308167],"type":"Point"}
}