{
  "type": "Feature",
  "properties": {
    "iso:country":"BE",
    "sg:address":"Tervuursesteenweg 206",
    "sg:city":"Bertem",
    "sg:classifiers":[
        {
            "category":"Real Estate",
            "subcategory":"Architect",
            "type":"Services"
        }
    ],
    "sg:phone":"+32 16 49 04 11",
    "sg:postcode":"3060",
    "sg:province":"Vlaams-Brabant",
    "wof:name":"G.v.e. Studiebureau Van Eycken",
    "wof:placetype":"venue"
},
  "geometry": {"coordinates":[4.6269388199,50.8651885986],"type":"Point"}
}