{
  "type": "Feature",
  "properties": {
    "addr:full":"Rijkenhoekstraat 18 Grimbergen Vlaams-Brabant 1850",
    "addr:housenumber":"18",
    "addr:postcode":"1850",
    "addr:street":"Rijkenhoekstraat",
    "iso:country":"BE",
    "sg:address":"Rijkenhoekstraat 18",
    "sg:city":"Grimbergen",
    "sg:orig_category":"M\u00e9decins and sp\u00e9cialistes",
    "sg:phone":"+32 2 270 20 92",
    "sg:postcode":"1850",
    "sg:province":"Vlaams-Brabant",
    "wof:name":"Consultatiebur.jonge Kind",
    "wof:placetype":"venue"
},
  "geometry": {"coordinates":[4.3734898567,50.9356536865],"type":"Point"}
}