{
  "type": "Feature",
  "properties": {
    "addr:full":"Industrieweg 4 Beerse Antwerpen 2340",
    "addr:housenumber":"4",
    "addr:postcode":"2340",
    "addr:street":"Industrieweg",
    "iso:country":"BE",
    "sg:address":"Industrieweg 4",
    "sg:city":"Beerse",
    "sg:classifiers":[
        {
            "category":"Autos & Motor Vehicles",
            "subcategory":"Automobile Sales",
            "type":"Retail Goods"
        }
    ],
    "sg:phone":"+32 14 61 41 64",
    "sg:postcode":"2340",
    "sg:province":"Antwerpen",
    "sg:tags":[
        "equipment",
        "industrial",
        "transport"
    ],
    "wof:name":"Renders Nv",
    "wof:placetype":"venue"
},
  "geometry": {"coordinates":[4.8367419243,51.2994308472],"type":"Point"}
}