{
  "type": "Feature",
  "properties": {
    "addr:full":"Geraardsbergse Steenweg 101 Oosterzele Oost-Vlaanderen 9860",
    "addr:housenumber":"101",
    "addr:postcode":"9860",
    "addr:street":"Steenweg;Oost-Vlaanderen",
    "iso:country":"BE",
    "sg:address":"Geraardsbergse Steenweg 101",
    "sg:city":"Oosterzele",
    "sg:classifiers":[
        {
            "category":"Building & Trades",
            "subcategory":"Electrical",
            "type":"Services"
        }
    ],
    "sg:phone":"+32 9 363 04 13",
    "sg:postcode":"9860",
    "sg:province":"Oost-Vlaanderen",
    "sg:tags":[
        "electric",
        "-",
        "housewiring",
        "contractor"
    ],
    "wof:name":"De Clercq D",
    "wof:placetype":"venue"
},
  "geometry": {"coordinates":[3.8142371178,50.9477157593],"type":"Point"}
}