{
  "type": "Feature",
  "properties": {
    "addr:full":"Nielsestraat 104 Boom Antwerpen 2850",
    "addr:housenumber":"104",
    "addr:postcode":"2850",
    "addr:street":"Nielsestraat",
    "iso:country":"BE",
    "sg:address":"Nielsestraat 104",
    "sg:city":"Boom",
    "sg:orig_category":"V\u00e9hicules automobiles",
    "sg:phone":"+32 3 888 05 47",
    "sg:postcode":"2850",
    "sg:province":"Antwerpen",
    "wof:name":"Garage Van Dyck",
    "wof:placetype":"venue"
},
  "geometry": {"coordinates":[4.3567128181,51.0908355713],"type":"Point"}
}