{
  "type": "Feature",
  "properties": {
    "addr:full":"Turnhoutsebaan 20a Lille Antwerpen 2275",
    "addr:housenumber":"20a",
    "addr:postcode":"2275",
    "addr:street":"Turnhoutsebaan",
    "iso:country":"BE",
    "sg:address":"Turnhoutsebaan 20a",
    "sg:city":"Lille",
    "sg:orig_category":"Epiceries",
    "sg:phone":"+32 14 55 70 10",
    "sg:postcode":"2275",
    "sg:province":"Antwerpen",
    "wof:name":"Spar",
    "wof:placetype":"venue"
},
  "geometry": {"coordinates":[4.878993988,51.2723388672],"type":"Point"}
}