{
  "type": "Feature",
  "properties": {
    "iso:country":"BE",
    "sg:address":"Sint-pankraasstraat 2",
    "sg:city":"Tongeren",
    "sg:orig_category":"Sportclubs",
    "sg:phone":"+32 12 23 62 00",
    "sg:postcode":"3700",
    "sg:province":"Limburg",
    "wof:name":"De Veldkets",
    "wof:placetype":"venue"
},
  "geometry": {"coordinates":[5.4635000229,50.7787666321],"type":"Point"}
}