{
  "type": "Feature",
  "properties": {
    "addr:full":"Avenue Des D\u00c9mineurs 13 Jette Bruxelles-Capitale 1090",
    "addr:housenumber":"13",
    "addr:postcode":"1090",
    "addr:street":"Avenue Des De\u0301Mineurs",
    "iso:country":"BE",
    "sg:address":"Avenue Des D\u00c9mineurs 13",
    "sg:city":"Jette",
    "sg:orig_category":"Architectes",
    "sg:phone":"+32 2 425 80 36",
    "sg:postcode":"1090",
    "sg:province":"Bruxelles-Capitale",
    "wof:name":"Raymond Boulogne",
    "wof:placetype":"venue"
},
  "geometry": {"coordinates":[4.3322877884,50.8790359497],"type":"Point"}
}