{
  "type": "Feature",
  "properties": {
    "addr:full":"Brusselbaan 102c Sint-pieters-leeuw Vlaams-Brabant 1600",
    "addr:housenumber":"102c",
    "addr:postcode":"1600",
    "addr:street":"Brusselbaan",
    "iso:country":"BE",
    "sg:address":"Brusselbaan 102c",
    "sg:city":"Sint-pieters-leeuw",
    "sg:classifiers":[
        {
            "category":"Shopping",
            "subcategory":"Florist",
            "type":"Retail Goods"
        }
    ],
    "sg:phone":"+32 2 377 59 46",
    "sg:postcode":"1600",
    "sg:province":"Vlaams-Brabant",
    "wof:name":"Florbel",
    "wof:placetype":"venue"
},
  "geometry": {"coordinates":[4.2845630646,50.8058547974],"type":"Point"}
}