{
  "type": "Feature",
  "properties": {
    "iso:country":"BE",
    "sg:address":"Scheldelaan 444",
    "sg:city":"Antwerpen",
    "sg:classifiers":[
        {
            "category":"Organizations",
            "subcategory":"Community Association",
            "type":"Services"
        }
    ],
    "sg:phone":"+32 3 569 90 12",
    "sg:postcode":"2040",
    "sg:province":"Antwerpen",
    "sg:tags":[
        "cultural"
    ],
    "wof:name":"Havencentrum Lillo Vzw",
    "wof:placetype":"venue"
},
  "geometry": {"coordinates":[4.2969307899,51.304725647],"type":"Point"}
}