{
  "type": "Feature",
  "properties": {
    "addr:full":"Rue D'houdeng 135 Le Roeulx Hainaut 7070",
    "addr:housenumber":"135",
    "addr:postcode":"7070",
    "addr:street":"Rue D'Houdeng",
    "iso:country":"BE",
    "sg:address":"Rue D'houdeng 135",
    "sg:city":"Le Roeulx",
    "sg:classifiers":[
        {
            "category":"Home & Garden",
            "subcategory":"Home Furnishings",
            "type":"Retail Goods"
        }
    ],
    "sg:phone":"+32 64 31 21 40",
    "sg:postcode":"7070",
    "sg:province":"Hainaut",
    "sg:tags":[
        "-",
        "bed",
        "mattress"
    ],
    "wof:name":"Bemo Sa",
    "wof:placetype":"venue"
},
  "geometry": {"coordinates":[4.1194009781,50.5002784729],"type":"Point"}
}