{
  "type": "Feature",
  "properties": {
    "addr:full":"Heiken 29 Sint-katelijne-waver (onze-lieve-vrouw-waver) Antwerpen 2861",
    "addr:housenumber":"29",
    "addr:postcode":"2861",
    "addr:street":"Heiken",
    "iso:country":"BE",
    "sg:address":"Heiken 29",
    "sg:city":"Sint-katelijne-waver (onze-lieve-vrouw-waver)",
    "sg:classifiers":[
        {
            "category":"Farming",
            "subcategory":"Crops",
            "type":"Manufacturing & Wholesale Goods"
        }
    ],
    "sg:phone":"+32 15 55 19 10",
    "sg:postcode":"2861",
    "sg:province":"Antwerpen",
    "sg:tags":[
        "vegetable",
        "fruit",
        "-",
        "grower"
    ],
    "wof:name":"Frans E",
    "wof:placetype":"venue"
},
  "geometry": {"coordinates":[4.5463848114,51.047908783],"type":"Point"}
}