{
  "type": "Feature",
  "properties": {
    "addr:full":"Kortrijkstraat 151a Zwevegem West-Vlaanderen 8550",
    "addr:housenumber":"151a",
    "addr:postcode":"8550",
    "addr:street":"Kortrijkstraat",
    "iso:country":"BE",
    "sg:address":"Kortrijkstraat 151a",
    "sg:city":"Zwevegem",
    "sg:classifiers":[
        {
            "category":"Banks & Credit Unions",
            "subcategory":"Investment Brokerage",
            "type":"Services"
        }
    ],
    "sg:phone":"+32 56 75 93 09",
    "sg:postcode":"8550",
    "sg:province":"West-Vlaanderen",
    "sg:tags":[
        "auditor"
    ],
    "wof:name":"Teerlynck J",
    "wof:placetype":"venue"
},
  "geometry": {"coordinates":[3.3154959679,50.814704895],"type":"Point"}
}