{
  "type": "Feature",
  "properties": {
    "iso:country":"BE",
    "sg:address":"Avenue Besme 107-109",
    "sg:city":"Bruxelles",
    "sg:classifiers":[
        {
            "category":"Professional",
            "subcategory":"Computer Services",
            "type":"Services"
        }
    ],
    "sg:phone":"+32 2 340 84 00",
    "sg:postcode":"1190",
    "sg:province":"Bruxelles-Capitale",
    "sg:tags":[
        "spreadsheet",
        "software"
    ],
    "wof:name":"Acordata S.a.",
    "wof:placetype":"venue"
},
  "geometry": {"coordinates":[4.340649128,50.8212928772],"type":"Point"}
}