{
  "type": "Feature",
  "properties": {
    "addr:full":"Rue Bodson 14 Courcelles Hainaut 6180",
    "addr:housenumber":"14",
    "addr:postcode":"6180",
    "addr:street":"Rue Bodson",
    "iso:country":"BE",
    "sg:address":"Rue Bodson 14",
    "sg:city":"Courcelles",
    "sg:orig_category":"Installatie van houten of kunststof schrijnwerk Installatie van metalen schrijnwerk SMEEDWERK, METAA",
    "sg:phone":"+32 71 45 67 29",
    "sg:postcode":"6180",
    "sg:province":"Hainaut",
    "wof:name":"Di Giaco",
    "wof:placetype":"venue"
},
  "geometry": {"coordinates":[4.3874697685,50.4677009583],"type":"Point"}
}