{
  "type": "Feature",
  "properties": {
    "addr:full":"Ovenstraat 6 Roeselare West-Vlaanderen 8800",
    "addr:housenumber":"6",
    "addr:postcode":"8800",
    "addr:street":"Ovenstraat",
    "iso:country":"BE",
    "sg:address":"Ovenstraat 6",
    "sg:city":"Roeselare",
    "sg:classifiers":[
        {
            "category":"Home & Garden",
            "subcategory":"Kitchen Supply",
            "type":"Retail Goods"
        }
    ],
    "sg:phone":"+32 51 22 31 31",
    "sg:postcode":"8800",
    "sg:province":"West-Vlaanderen",
    "sg:tags":[
        "-",
        "industrial",
        "installation",
        "equipment"
    ],
    "wof:name":"Cd Constructs Bvba",
    "wof:placetype":"venue"
},
  "geometry": {"coordinates":[3.0981938839,50.9483337402],"type":"Point"}
}