{
  "type": "Feature",
  "properties": {
    "addr:full":"Avenue Pr\u00c9 Aily 1 Liege Li\u00e8ge 4031",
    "addr:housenumber":"1",
    "addr:postcode":"4031",
    "addr:street":"Avenue Pre\u0301 Aily",
    "iso:country":"BE",
    "sg:address":"Avenue Pr\u00c9 Aily 1",
    "sg:city":"Liege",
    "sg:orig_category":"Diverse bedrijfsbeheeradviesbureaus",
    "sg:phone":"+32 4 367 83 23",
    "sg:postcode":"4031",
    "sg:province":"Li\u00e8ge",
    "wof:name":"Innobip",
    "wof:placetype":"venue"
},
  "geometry": {"coordinates":[5.5648798943,50.5961799622],"type":"Point"}
}