{
  "type": "Feature",
  "properties": {
    "addr:full":"Canadastraat 48 Hasselt Limburg 3500",
    "addr:housenumber":"48",
    "addr:postcode":"3500",
    "addr:street":"Canadastraat",
    "iso:country":"BE",
    "sg:address":"Canadastraat 48",
    "sg:city":"Hasselt",
    "sg:classifiers":[
        {
            "category":"Metro Station",
            "type":"Transportation"
        }
    ],
    "sg:phone":"+32 11 21 02 38",
    "sg:postcode":"3500",
    "sg:province":"Limburg",
    "sg:tags":[
        "repair",
        "ship",
        "mainten",
        "-"
    ],
    "wof:name":"Van Der Werf T",
    "wof:placetype":"venue"
},
  "geometry": {"coordinates":[5.3466081619,50.9423866272],"type":"Point"}
}