{
  "type": "Feature",
  "properties": {
    "addr:full":"Hoge Buizemont 174 Geraardsbergen Oost-Vlaanderen 9500",
    "addr:housenumber":"174",
    "addr:postcode":"9500",
    "addr:street":"Hoge Buizemont",
    "iso:country":"BE",
    "sg:address":"Hoge Buizemont 174",
    "sg:city":"Geraardsbergen",
    "sg:classifiers":[
        {
            "category":"Cafe",
            "type":"Food & Drink"
        }
    ],
    "sg:phone":"+32 54 41 33 57",
    "sg:postcode":"9500",
    "sg:province":"Oost-Vlaanderen",
    "sg:tags":[
        "caf\u00e9s"
    ],
    "wof:name":"Caf\u00c9 Retour Des Wallons",
    "wof:placetype":"venue"
},
  "geometry": {"coordinates":[3.8826038837,50.759677887],"type":"Point"}
}