{
  "type": "Feature",
  "properties": {
    "addr:full":"Glazenleeuwstraat 45-47 Beveren (beveren-waas) Oost-Vlaanderen 9120",
    "addr:postcode":"45-47;9120",
    "addr:street":"Glazenleeuwstraat",
    "iso:country":"BE",
    "sg:address":"Glazenleeuwstraat 45-47",
    "sg:city":"Beveren (beveren-waas)",
    "sg:classifiers":[
        {
            "category":"Banks & Credit Unions",
            "subcategory":"Investment Brokerage",
            "type":"Services"
        }
    ],
    "sg:phone":"+32 3 775 05 92",
    "sg:postcode":"9120",
    "sg:province":"Oost-Vlaanderen",
    "sg:tags":[
        "repair",
        "-",
        "installation",
        "sanitary",
        "article"
    ],
    "wof:name":"Algemene Loodgieterij Roelandt",
    "wof:placetype":"venue"
},
  "geometry": {"coordinates":[4.2481021881,51.2181663513],"type":"Point"}
}