{
  "type": "Feature",
  "properties": {
    "iso:country":"BE",
    "sg:address":"Steegstraat 68",
    "sg:city":"Balen",
    "sg:classifiers":[
        {
            "category":"Shopping",
            "subcategory":"Florist",
            "type":"Retail Goods"
        }
    ],
    "sg:phone":"+32 14 81 72 30",
    "sg:postcode":"2490",
    "sg:province":"Antwerpen",
    "wof:name":"Groenhuis (het)",
    "wof:placetype":"venue"
},
  "geometry": {"coordinates":[5.1740322113,51.1671066284],"type":"Point"}
}