{
  "type": "Feature",
  "properties": {
    "addr:full":"Rue De La Gare 35 Malmedy Li\u00e8ge 4750",
    "addr:housenumber":"35",
    "addr:postcode":"4750",
    "addr:street":"Rue De La Gare",
    "iso:country":"BE",
    "sg:address":"Rue De La Gare 35",
    "sg:city":"Malmedy",
    "sg:orig_category":"Quincailleries. Installation de menuiserie m\u00e9tallique. Mat\u00e9riaux de construction Bois Gr",
    "sg:phone":"+32 80 44 62 19",
    "sg:postcode":"4750",
    "sg:province":"Li\u00e8ge",
    "wof:name":"Niwaco",
    "wof:placetype":"venue"
},
  "geometry": {"coordinates":[6.2043948174,50.4263038635],"type":"Point"}
}