{
  "type": "Feature",
  "properties": {
    "iso:country":"BE",
    "sg:address":"Knokkestraat 671",
    "sg:city":"Knokke-heist (knokke)",
    "sg:classifiers":[
        {
            "category":"Retail",
            "subcategory":"Repair Shop",
            "type":"Services"
        }
    ],
    "sg:phone":"+32 50 60 73 23",
    "sg:postcode":"8300",
    "sg:province":"West-Vlaanderen",
    "sg:tags":[
        "radio",
        "television",
        "-",
        "maintenance"
    ],
    "wof:name":"Tv Dokter",
    "wof:placetype":"venue"
},
  "geometry": {"coordinates":[3.2836790085,51.3410072327],"type":"Point"}
}