{
  "type": "Feature",
  "properties": {
    "iso:country":"BE",
    "sg:address":"Hoogkamerstraat 108bc",
    "sg:city":"Temse",
    "sg:orig_category":"Herstellingen and onderhoud van auto's",
    "sg:phone":"+32 3 771 57 57",
    "sg:postcode":"9140",
    "sg:province":"Oost-Vlaanderen",
    "wof:name":"Heirbaut Temse",
    "wof:placetype":"venue"
},
  "geometry": {"coordinates":[4.1975049973,51.1279220581],"type":"Point"}
}