{
  "type": "Feature",
  "properties": {
    "addr:full":"Rue Aux Fleurs 220b Beloeil (grand) Hainaut 7973",
    "addr:housenumber":"220b",
    "addr:postcode":"7973",
    "addr:street":"Rue Aux Fleurs",
    "iso:country":"BE",
    "sg:address":"Rue Aux Fleurs 220b",
    "sg:city":"Beloeil (grand)",
    "sg:classifiers":[
        {
            "category":"Personal",
            "subcategory":"Beauty Salon",
            "type":"Services"
        }
    ],
    "sg:phone":"+32 69 56 25 31",
    "sg:postcode":"7973",
    "sg:province":"Hainaut",
    "sg:tags":[
        "de",
        "coiffure"
    ],
    "wof:name":"Coiffure Dimitri",
    "wof:placetype":"venue"
},
  "geometry": {"coordinates":[3.7007200718,50.4970283508],"type":"Point"}
}