{
  "type": "Feature",
  "properties": {
    "iso:country":"BE",
    "sg:address":"Nachtegalenlaan 27b",
    "sg:city":"Kapelle-op-den-bos",
    "sg:classifiers":[
        {
            "category":"Parking",
            "subcategory":"Lot",
            "type":"Transportation"
        }
    ],
    "sg:phone":"+32 15 71 22 83",
    "sg:postcode":"1880",
    "sg:province":"Vlaams-Brabant",
    "sg:tags":[
        "parking-places",
        "laying-out"
    ],
    "wof:name":"Van Haesendonck W",
    "wof:placetype":"venue"
},
  "geometry": {"coordinates":[4.3590660095,51.0001678467],"type":"Point"}
}