{
  "type": "Feature",
  "properties": {
    "iso:country":"BE",
    "sg:address":"Nieuwstraat 71",
    "sg:city":"Lede",
    "sg:classifiers":[
        {
            "category":"Cafe",
            "type":"Food & Drink"
        }
    ],
    "sg:phone":"+32 53 80 75 39",
    "sg:postcode":"9340",
    "sg:province":"Oost-Vlaanderen",
    "sg:tags":[
        "caf\u00e9s"
    ],
    "wof:name":"Peter Van Hauwermeiren",
    "wof:placetype":"venue"
},
  "geometry": {"coordinates":[3.9827470779,50.9654312134],"type":"Point"}
}