{
  "type": "Feature",
  "properties": {
    "addr:full":"Hoogstraat 2 Nieuwpoort West-Vlaanderen 8620",
    "addr:housenumber":"2",
    "addr:postcode":"8620",
    "addr:street":"Hoogstraat",
    "iso:country":"BE",
    "sg:address":"Hoogstraat 2",
    "sg:city":"Nieuwpoort",
    "sg:orig_category":"Biblioth\u00e8ques and archives publiques",
    "sg:phone":"+32 58 22 30 40",
    "sg:postcode":"8620",
    "sg:province":"West-Vlaanderen",
    "wof:name":"Openbare Bibliotheek",
    "wof:placetype":"venue"
},
  "geometry": {"coordinates":[2.7500989437,51.1320037842],"type":"Point"}
}