{
  "type": "Feature",
  "properties": {
    "addr:full":"Waverse Steenweg 1586 Oudergem/auderghem Bruxelles-Capitale 1160",
    "addr:housenumber":"1586",
    "addr:postcode":"1160",
    "addr:street":"Waverse Steenweg;/",
    "iso:country":"BE",
    "sg:address":"Waverse Steenweg 1586",
    "sg:city":"Oudergem/auderghem",
    "sg:orig_category":"Fotogravure and zetwerk",
    "sg:phone":"+32 2 673 58 57",
    "sg:postcode":"1160",
    "sg:province":"Bruxelles-Capitale",
    "wof:name":"Graveur Rapida",
    "wof:placetype":"venue"
},
  "geometry": {"coordinates":[4.4234771729,50.8171691895],"type":"Point"}
}