{
  "type": "Feature",
  "properties": {
    "iso:country":"BE",
    "sg:address":"Bredabaan 661",
    "sg:city":"Brasschaat",
    "sg:orig_category":"MEUBELONTWERP AND -INSTALLATIE",
    "sg:phone":"+32 3 653 06 14",
    "sg:postcode":"2930",
    "sg:province":"Antwerpen",
    "wof:name":"Vastgoed Rombouts Frank",
    "wof:placetype":"venue"
},
  "geometry": {"coordinates":[4.5024299622,51.3017463684],"type":"Point"}
}