{
  "type": "Feature",
  "properties": {
    "iso:country":"BE",
    "sg:address":"Rue Darchis 19",
    "sg:city":"Li\u00e8ge 1",
    "sg:classifiers":[
        {
            "category":"Social Services",
            "type":"Services"
        }
    ],
    "sg:phone":"+32 4 223 01 00",
    "sg:postcode":"4000",
    "sg:province":"Li\u00e8ge",
    "sg:tags":[
        "handicapped",
        "-"
    ],
    "wof:name":"A.v.j. Li\u00e8ge",
    "wof:placetype":"venue"
},
  "geometry": {"coordinates":[5.5661458969,50.6370277405],"type":"Point"}
}