{
  "type": "Feature",
  "properties": {
    "iso:country":"BE",
    "sg:address":"Avenue Des Fr\u00c8res Haeghe 8",
    "sg:city":"Tournai",
    "sg:orig_category":"E-activit\u00e9s. Ordinateurs Fab. Entretien and r\u00e9parations de machines de bureau and ordinateurs. Ordin",
    "sg:phone":"+32 69 84 34 71",
    "sg:postcode":"7500",
    "sg:province":"Hainaut",
    "wof:name":"Orditronics",
    "wof:placetype":"venue"
},
  "geometry": {"coordinates":[3.3969759941,50.6107292175],"type":"Point"}
}