{
  "type": "Feature",
  "properties": {
    "iso:country":"BE",
    "sg:address":"Kardinaal Cardijnlaan 36",
    "sg:city":"Mortsel",
    "sg:orig_category":"Diverse bedrijfsbeheeradviesbureaus",
    "sg:phone":"+32 3 455 77 18",
    "sg:postcode":"2640",
    "sg:province":"Antwerpen",
    "wof:name":"J.w. Management Corporation",
    "wof:placetype":"venue"
},
  "geometry": {"coordinates":[4.4764199257,51.1727485657],"type":"Point"}
}