{
  "type": "Feature",
  "properties": {
    "addr:full":"Rue Cockerill 156 Seraing Li\u00e8ge 4100",
    "addr:housenumber":"156",
    "addr:postcode":"4100",
    "addr:street":"Rue Cockerill",
    "iso:country":"BE",
    "sg:address":"Rue Cockerill 156",
    "sg:city":"Seraing",
    "sg:orig_category":"Agences de voyages",
    "sg:phone":"+32 4 336 79 33",
    "sg:postcode":"4100",
    "sg:province":"Li\u00e8ge",
    "wof:name":"C.i.t. Belgique",
    "wof:placetype":"venue"
},
  "geometry": {"coordinates":[5.512319088,50.6103935242],"type":"Point"}
}