{
  "type": "Feature",
  "properties": {
    "addr:full":"Avenue Valentin Tondeur 26 Waterloo Brabant Wallon 1410",
    "addr:housenumber":"26",
    "addr:postcode":"1410",
    "addr:street":"Avenue Valentin Tondeur",
    "iso:country":"BE",
    "sg:address":"Avenue Valentin Tondeur 26",
    "sg:city":"Waterloo",
    "sg:classifiers":[
        {
            "category":"Health Services",
            "subcategory":"Doctor",
            "type":"Services"
        }
    ],
    "sg:phone":"+32 2 387 11 88",
    "sg:postcode":"1410",
    "sg:province":"Brabant Wallon",
    "sg:tags":[
        "medicinephysicians",
        "surgeon"
    ],
    "wof:name":"Jacoby H",
    "wof:placetype":"venue"
},
  "geometry": {"coordinates":[4.4052820206,50.6960258484],"type":"Point"}
}