{
  "type": "Feature",
  "properties": {
    "iso:country":"BE",
    "sg:address":"Hongerije 47",
    "sg:city":"Oudenaarde",
    "sg:orig_category":"Sportclubs",
    "sg:phone":"+32 55 31 81 44",
    "sg:postcode":"9700",
    "sg:province":"Oost-Vlaanderen",
    "wof:name":"Recrean Fv",
    "wof:placetype":"venue"
},
  "geometry": {"coordinates":[3.6316409111,50.850112915],"type":"Point"}
}