{
  "type": "Feature",
  "properties": {
    "iso:country":"BE",
    "sg:address":"Akrenbos 99",
    "sg:city":"Bever",
    "sg:orig_category":"Installation \u00e9lectrique industrielle",
    "sg:phone":"+32 54 58 81 39",
    "sg:postcode":"1547",
    "sg:province":"Vlaams-Brabant",
    "wof:name":"Avez Indus Elektro",
    "wof:placetype":"venue"
},
  "geometry": {"coordinates":[3.913351059,50.7317962646],"type":"Point"}
}