{
  "type": "Feature",
  "properties": {
    "addr:full":"Lucasstraat 41 Staden West-Vlaanderen 8840",
    "addr:housenumber":"41",
    "addr:postcode":"8840",
    "addr:street":"Lucasstraat",
    "iso:country":"BE",
    "sg:address":"Lucasstraat 41",
    "sg:city":"Staden",
    "sg:orig_category":"Eleveurs and marchands de porcs",
    "sg:phone":"+32 51 70 25 78",
    "sg:postcode":"8840",
    "sg:province":"West-Vlaanderen",
    "wof:name":"Roger Lesage",
    "wof:placetype":"venue"
},
  "geometry": {"coordinates":[3.0155808926,50.9862365723],"type":"Point"}
}