{
  "type": "Feature",
  "properties": {
    "iso:country":"BE",
    "sg:address":"Kapelanielaan 31",
    "sg:city":"Temse",
    "sg:classifiers":[
        {
            "category":"Building & Trades",
            "subcategory":"Equipment Rental",
            "type":"Services"
        }
    ],
    "sg:phone":"+32 3 711 05 05",
    "sg:postcode":"9140",
    "sg:province":"Oost-Vlaanderen",
    "sg:tags":[
        "use",
        "apparatus",
        "tool",
        "-",
        "professional",
        "machines"
    ],
    "wof:name":"Welding Services Nv",
    "wof:placetype":"venue"
},
  "geometry": {"coordinates":[4.1811161041,51.1385803223],"type":"Point"}
}