{
  "type": "Feature",
  "properties": {
    "iso:country":"BE",
    "sg:address":"Astridlaan 171",
    "sg:city":"Geraardsbergen",
    "sg:classifiers":[
        {
            "category":"Freight",
            "type":"Transportation"
        }
    ],
    "sg:phone":"+32 54 41 90 41",
    "sg:postcode":"9500",
    "sg:province":"Oost-Vlaanderen",
    "sg:tags":[
        "-",
        "transport"
    ],
    "wof:name":"Bauwens M",
    "wof:placetype":"venue"
},
  "geometry": {"coordinates":[3.8745100498,50.78125],"type":"Point"}
}