{
  "type": "Feature",
  "properties": {
    "iso:country":"BE",
    "sg:address":"Hoogstraat 25",
    "sg:city":"Lede",
    "sg:orig_category":"Instituts de beaut\u00e9. Eclairage et \u00e9quipements du foyer",
    "sg:phone":"+32 53 80 12 22",
    "sg:postcode":"9340",
    "sg:province":"Oost-Vlaanderen",
    "wof:name":"Jo De Ras",
    "wof:placetype":"venue"
},
  "geometry": {"coordinates":[3.976970911,50.963344574],"type":"Point"}
}