{
  "type": "Feature",
  "properties": {
    "addr:full":"Keizershoek 287 Kontich Antwerpen 2550",
    "addr:housenumber":"287",
    "addr:postcode":"2550",
    "addr:street":"Keizershoek",
    "iso:country":"BE",
    "sg:address":"Keizershoek 287",
    "sg:city":"Kontich",
    "sg:orig_category":"Office, Building, Fa\u00e7ade, Industry, Hospital Cleaning Services",
    "sg:phone":"+32 3 457 88 82",
    "sg:postcode":"2550",
    "sg:province":"Antwerpen",
    "wof:name":"Alpin Cleaning Enterprise B.v.b.a.",
    "wof:placetype":"venue"
},
  "geometry": {"coordinates":[4.4119839668,51.1221313477],"type":"Point"}
}