{
  "type": "Feature",
  "properties": {
    "addr:full":"Rue Edison 18 Bruxelles (forest) Bruxelles-Capitale 1190",
    "addr:housenumber":"18",
    "addr:postcode":"1190",
    "addr:street":"Rue Edison",
    "iso:country":"BE",
    "sg:address":"Rue Edison 18",
    "sg:city":"Bruxelles (forest)",
    "sg:classifiers":[
        {
            "category":"Professional",
            "subcategory":"Accounting & Tax Preparation",
            "type":"Services"
        }
    ],
    "sg:phone":"+32 2 539 14 95",
    "sg:postcode":"1190",
    "sg:province":"Bruxelles-Capitale",
    "sg:tags":[
        "bookkeeper"
    ],
    "wof:name":"Gharbaoui H",
    "wof:placetype":"venue"
},
  "geometry": {"coordinates":[4.3296332359,50.8257598877],"type":"Point"}
}