{
  "type": "Feature",
  "properties": {
    "addr:full":"Les-respes 30 Anhee Namur 5537",
    "addr:housenumber":"30",
    "addr:postcode":"5537",
    "addr:street":"Les-Respes;Namur",
    "iso:country":"BE",
    "sg:address":"Les-respes 30",
    "sg:city":"Anhee",
    "sg:orig_category":"Groententeelt",
    "sg:phone":"+32 71 79 84 52",
    "sg:postcode":"5537",
    "sg:province":"Namur",
    "wof:name":"Eric Cabosart",
    "wof:placetype":"venue"
},
  "geometry": {"coordinates":[4.7617549896,50.3166313171],"type":"Point"}
}