{
  "type": "Feature",
  "properties": {
    "addr:full":"Rommelsweg 12 Sint-laureins Oost-Vlaanderen 9980",
    "addr:housenumber":"12",
    "addr:postcode":"9980",
    "addr:street":"Rommelsweg",
    "iso:country":"BE",
    "sg:address":"Rommelsweg 12",
    "sg:city":"Sint-laureins",
    "sg:orig_category":"Overheidsdiensten",
    "sg:phone":"+32 9 379 04 05",
    "sg:postcode":"9980",
    "sg:province":"Oost-Vlaanderen",
    "wof:name":"O.c.m.w.",
    "wof:placetype":"venue"
},
  "geometry": {"coordinates":[3.5202879906,51.2396354675],"type":"Point"}
}