{
  "type": "Feature",
  "properties": {
    "addr:full":"Boekhoutstraat 40 Gingelom Limburg 3890",
    "addr:housenumber":"40",
    "addr:postcode":"3890",
    "addr:street":"Boekhoutstraat",
    "iso:country":"BE",
    "sg:address":"Boekhoutstraat 40",
    "sg:city":"Gingelom",
    "sg:orig_category":"Fruitteelt",
    "sg:phone":"+32 11 48 21 39",
    "sg:postcode":"3890",
    "sg:province":"Limburg",
    "wof:name":"Herman Vanmarsenille",
    "wof:placetype":"venue"
},
  "geometry": {"coordinates":[5.2329740524,50.7454109192],"type":"Point"}
}