{
  "type": "Feature",
  "properties": {
    "iso:country":"BE",
    "sg:address":"Kleine Potelstwegel 4",
    "sg:city":"Koekelare",
    "sg:classifiers":[
        {
            "category":"Building & Trades",
            "subcategory":"Landscaping Services",
            "type":"Services"
        }
    ],
    "sg:phone":"+32 51 58 27 89",
    "sg:postcode":"8680",
    "sg:province":"West-Vlaanderen",
    "sg:tags":[
        "gardening",
        "garden",
        "maintenance"
    ],
    "wof:name":"Hemeryck M",
    "wof:placetype":"venue"
},
  "geometry": {"coordinates":[2.9609930515,51.1022033691],"type":"Point"}
}