{
  "type": "Feature",
  "properties": {
    "addr:full":"Houtkaai 10 Vilvoorde Vlaams-Brabant 1800",
    "addr:housenumber":"10",
    "addr:postcode":"1800",
    "addr:street":"Houtkaai",
    "iso:country":"BE",
    "sg:address":"Houtkaai 10",
    "sg:city":"Vilvoorde",
    "sg:classifiers":[
        {
            "category":"Wholesale",
            "subcategory":"Tobacco Products",
            "type":"Manufacturing & Wholesale Goods"
        }
    ],
    "sg:phone":"+32 2 216 02 76",
    "sg:postcode":"1800",
    "sg:province":"Vlaams-Brabant",
    "sg:tags":[
        "import",
        "wood",
        "-"
    ],
    "wof:name":"Parmentier C Nv",
    "wof:placetype":"venue"
},
  "geometry": {"coordinates":[4.4146080017,50.9285430908],"type":"Point"}
}