{
  "type": "Feature",
  "properties": {
    "addr:full":"Kruisberg 36 Dessel Antwerpen 2480",
    "addr:housenumber":"36",
    "addr:postcode":"2480",
    "addr:street":"Kruisberg",
    "iso:country":"BE",
    "sg:address":"Kruisberg 36",
    "sg:city":"Dessel",
    "sg:orig_category":"Caravans, aanhangwagens and opleggers",
    "sg:phone":"+32 14 37 86 11",
    "sg:postcode":"2480",
    "sg:province":"Antwerpen",
    "wof:name":"Emmelcamper",
    "wof:placetype":"venue"
},
  "geometry": {"coordinates":[5.1239700317,51.2514533997],"type":"Point"}
}