{
  "type": "Feature",
  "properties": {
    "addr:full":"Chemin D'enghien 29 Lessines Hainaut 7860",
    "addr:housenumber":"29",
    "addr:postcode":"7860",
    "addr:street":"Chemin D'Enghien;Hainaut",
    "iso:country":"BE",
    "sg:address":"Chemin D'enghien 29",
    "sg:city":"Lessines",
    "sg:orig_category":"Winkelinrichting and handelsuitrusting Gh",
    "sg:phone":"+32 68 33 48 47",
    "sg:postcode":"7860",
    "sg:province":"Hainaut",
    "wof:name":"Andre Sculier",
    "wof:placetype":"venue"
},
  "geometry": {"coordinates":[3.8475110531,50.7065849304],"type":"Point"}
}