{
  "type": "Feature",
  "properties": {
    "addr:full":"Place Du Man\u00c8ge 12 Charleroi Hainaut 6000",
    "addr:housenumber":"12",
    "addr:postcode":"6000",
    "addr:street":"Place Du Mane\u0300Ge;Hainaut",
    "iso:country":"BE",
    "sg:address":"Place Du Man\u00c8ge 12",
    "sg:city":"Charleroi",
    "sg:orig_category":"Disneyland Paris. Agences de voyages",
    "sg:phone":"+32 71 31 61 70",
    "sg:postcode":"6000",
    "sg:province":"Hainaut",
    "wof:name":"Intertour Voyages Sa",
    "wof:placetype":"venue"
},
  "geometry": {"coordinates":[4.4441452026,50.4129562378],"type":"Point"}
}