{
  "type": "Feature",
  "properties": {
    "iso:country":"BE",
    "sg:address":"Rue Du Sablon 123",
    "sg:city":"Bastogne",
    "sg:orig_category":"Biens d'occasion",
    "sg:phone":"+32 61 21 83 01",
    "sg:postcode":"6600",
    "sg:province":"Luxembourg",
    "wof:name":"La Bouquinerie Du Sablon",
    "wof:placetype":"venue"
},
  "geometry": {"coordinates":[5.7184691429,50.0032234192],"type":"Point"}
}