{
  "type": "Feature",
  "properties": {
    "iso:country":"BE",
    "sg:address":"Rue De La Cure 39",
    "sg:city":"Tubize (saintes)",
    "sg:classifiers":[
        {
            "category":"Education",
            "subcategory":"School",
            "type":"Public Place"
        }
    ],
    "sg:phone":"+32 2 355 39 95",
    "sg:postcode":"1480",
    "sg:province":"Brabant Wallon",
    "sg:tags":[
        "primary"
    ],
    "wof:name":"Ecole Des Sacr\u00e9s Coeurs",
    "wof:placetype":"venue"
},
  "geometry": {"coordinates":[4.1608729362,50.7055587769],"type":"Point"}
}