{
  "type": "Feature",
  "properties": {
    "iso:country":"BE",
    "sg:address":"Proostdijstraat 8",
    "sg:city":"Maasmechelen",
    "sg:classifiers":[
        {
            "category":"Building & Trades",
            "subcategory":"Construction",
            "type":"Services"
        }
    ],
    "sg:phone":"+32 89 77 18 15",
    "sg:postcode":"3630",
    "sg:province":"Limburg",
    "sg:tags":[
        "ventilation",
        "conditionn\u00e9",
        "air"
    ],
    "wof:name":"Fa. Eurocool",
    "wof:placetype":"venue"
},
  "geometry": {"coordinates":[5.6994137764,50.9649620056],"type":"Point"}
}