{
  "type": "Feature",
  "properties": {
    "iso:country":"BE",
    "sg:address":"Place 10",
    "sg:city":"Ellezelles",
    "sg:classifiers":[
        {
            "category":"Insurance",
            "subcategory":"Insurance Agent",
            "type":"Services"
        }
    ],
    "sg:phone":"+32 68 54 31 41",
    "sg:postcode":"7890",
    "sg:province":"Hainaut",
    "sg:tags":[
        "broker"
    ],
    "wof:name":"Livemont J C",
    "wof:placetype":"venue"
},
  "geometry": {"coordinates":[3.6814301014,50.7337265015],"type":"Point"}
}