{
  "type": "Feature",
  "properties": {
    "addr:full":"Industrieweg 2019 Zonhoven Limburg 3520",
    "addr:postcode":"2019 zonhoven;3520",
    "addr:street":"Industrieweg",
    "iso:country":"BE",
    "sg:address":"Industrieweg 2019",
    "sg:city":"Zonhoven",
    "sg:classifiers":[
        {
            "category":"Professional",
            "subcategory":"Engineering",
            "type":"Services"
        }
    ],
    "sg:phone":"+32 11 81 30 25",
    "sg:postcode":"3520",
    "sg:province":"Limburg",
    "sg:tags":[
        "machine",
        "-",
        "mechanical"
    ],
    "wof:name":"Melotte Nv",
    "wof:placetype":"venue"
},
  "geometry": {"coordinates":[5.3905029297,51.001865387],"type":"Point"}
}