{
  "type": "Feature",
  "properties": {
    "addr:full":"Rue De J\u00e9honville 40z Libin (ochamps) Luxembourg 6890",
    "addr:housenumber":"40z",
    "addr:postcode":"6890",
    "addr:street":"Rue De Je\u0301Honville",
    "iso:country":"BE",
    "sg:address":"Rue De J\u00e9honville 40z",
    "sg:city":"Libin (ochamps)",
    "sg:classifiers":[
        {
            "category":"Farming",
            "subcategory":"Livestock Farm",
            "type":"Manufacturing & Wholesale Goods"
        }
    ],
    "sg:phone":"+32 61 22 51 99",
    "sg:postcode":"6890",
    "sg:province":"Luxembourg",
    "sg:tags":[
        "breeding"
    ],
    "wof:name":"Plennevaux D",
    "wof:placetype":"venue"
},
  "geometry": {"coordinates":[5.2673711777,49.9219589233],"type":"Point"}
}