{
  "type": "Feature",
  "properties": {
    "addr:full":"Oostendestraat 36 Gent Oost-Vlaanderen 9000",
    "addr:housenumber":"36",
    "addr:postcode":"9000",
    "addr:street":"Oostendestraat;Oost-Vlaanderen",
    "iso:country":"BE",
    "sg:address":"Oostendestraat 36",
    "sg:city":"Gent",
    "sg:classifiers":[
        {
            "category":"Health Services",
            "subcategory":"Doctor",
            "type":"Services"
        }
    ],
    "sg:phone":"+32 9 221 94 48",
    "sg:postcode":"9000",
    "sg:province":"Oost-Vlaanderen",
    "sg:tags":[
        "psychotherapist",
        "psychoanalyst"
    ],
    "wof:name":"De Coninck A",
    "wof:placetype":"venue"
},
  "geometry": {"coordinates":[3.7147901058,51.0354804993],"type":"Point"}
}