{
  "type": "Feature",
  "properties": {
    "addr:full":"Avenue Tereycken 10 Kraainem Vlaams-Brabant 1950",
    "addr:housenumber":"10",
    "addr:postcode":"1950",
    "addr:street":"Avenue Tereycken",
    "iso:country":"BE",
    "sg:address":"Avenue Tereycken 10",
    "sg:city":"Kraainem",
    "sg:classifiers":[
        {
            "category":"Professional",
            "subcategory":"Accounting & Tax Preparation",
            "type":"Services"
        }
    ],
    "sg:phone":"+32 2 725 33 86",
    "sg:postcode":"1950",
    "sg:province":"Vlaams-Brabant",
    "sg:tags":[
        "bookkeeper"
    ],
    "wof:name":"Calleeuw M",
    "wof:placetype":"venue"
},
  "geometry": {"coordinates":[4.4600200653,50.8531227112],"type":"Point"}
}