{
  "type": "Feature",
  "properties": {
    "addr:full":"Heilig-hartplein 7 Herzele Oost-Vlaanderen 9550",
    "addr:housenumber":"7",
    "addr:postcode":"9550",
    "addr:street":"Heilig-Hartplein;Oost-Vlaanderen",
    "iso:country":"BE",
    "sg:address":"Heilig-hartplein 7",
    "sg:city":"Herzele",
    "sg:classifiers":[
        {
            "category":"Cafe",
            "type":"Food & Drink"
        }
    ],
    "sg:phone":"+32 53 62 79 53",
    "sg:postcode":"9550",
    "sg:province":"Oost-Vlaanderen",
    "sg:tags":[
        "caf\u00e9s"
    ],
    "wof:name":"Goossens",
    "wof:placetype":"venue"
},
  "geometry": {"coordinates":[3.915241003,50.87317276],"type":"Point"}
}