{
  "type": "Feature",
  "properties": {
    "iso:country":"BE",
    "sg:address":"Avenue De La R\u00c9sistance 271",
    "sg:city":"Soumagne",
    "sg:classifiers":[
        {
            "category":"Restaurant",
            "type":"Food & Drink"
        }
    ],
    "sg:phone":"+32 4 377 50 04",
    "sg:postcode":"4630",
    "sg:province":"Li\u00e8ge",
    "wof:name":"Chez Franck",
    "wof:placetype":"venue"
},
  "geometry": {"coordinates":[5.7352080345,50.631023407],"type":"Point"}
}