{
  "type": "Feature",
  "properties": {
    "iso:country":"BE",
    "sg:address":"Rue De Charleroi 2",
    "sg:city":"Nivelles",
    "sg:classifiers":[
        {
            "category":"Professional",
            "subcategory":"Lawyer & Legal Services",
            "type":"Services"
        }
    ],
    "sg:phone":"+32 67 21 79 91",
    "sg:postcode":"1400",
    "sg:province":"Brabant Wallon",
    "wof:name":"Vanhouche D",
    "wof:placetype":"venue"
},
  "geometry": {"coordinates":[4.331430912,50.5886230469],"type":"Point"}
}