{
  "type": "Feature",
  "properties": {
    "addr:full":"Napoleonsdijk 4 Bocholt Limburg 3950",
    "addr:housenumber":"4",
    "addr:postcode":"3950",
    "addr:street":"Napoleonsdijk",
    "iso:country":"BE",
    "sg:address":"Napoleonsdijk 4",
    "sg:city":"Bocholt",
    "sg:orig_category":"Eleveurs and marchands de porcs",
    "sg:phone":"+32 89 46 28 72",
    "sg:postcode":"3950",
    "sg:province":"Limburg",
    "wof:name":"Alfons Langens",
    "wof:placetype":"venue"
},
  "geometry": {"coordinates":[5.6373381615,51.1894302368],"type":"Point"}
}