{
  "type": "Feature",
  "properties": {
    "addr:full":"Vaartstraat 60 Leuven Vlaams-Brabant 3000",
    "addr:housenumber":"60",
    "addr:postcode":"3000",
    "addr:street":"Vaartstraat",
    "iso:country":"BE",
    "sg:address":"Vaartstraat 60",
    "sg:city":"Leuven",
    "sg:orig_category":"Advocaten and juridische adviseurs",
    "sg:phone":"+32 16 31 01 31",
    "sg:postcode":"3000",
    "sg:province":"Vlaams-Brabant",
    "wof:name":"V. Coigniez",
    "wof:placetype":"venue"
},
  "geometry": {"coordinates":[4.7011699677,50.8837738037],"type":"Point"}
}