{
  "type": "Feature",
  "properties": {
    "addr:full":"Zoomstraat 48 Lokeren Oost-Vlaanderen 9160",
    "addr:housenumber":"48",
    "addr:postcode":"9160",
    "addr:street":"Zoomstraat",
    "iso:country":"BE",
    "sg:address":"Zoomstraat 48",
    "sg:city":"Lokeren",
    "sg:classifiers":[
        {
            "category":"Home & Garden",
            "subcategory":"Home Furnishings",
            "type":"Retail Goods"
        }
    ],
    "sg:phone":"+32 9 348 05 51",
    "sg:postcode":"9160",
    "sg:province":"Oost-Vlaanderen",
    "sg:tags":[
        "fitting"
    ],
    "wof:name":"Ars",
    "wof:placetype":"venue"
},
  "geometry": {"coordinates":[4.0269298553,51.0930786133],"type":"Point"}
}