{
  "type": "Feature",
  "properties": {
    "addr:full":"Heidestraat 17 Tessenderlo Limburg 3980",
    "addr:housenumber":"17",
    "addr:postcode":"3980",
    "addr:street":"Heidestraat",
    "iso:country":"BE",
    "sg:address":"Heidestraat 17",
    "sg:city":"Tessenderlo",
    "sg:orig_category":"Jardinage",
    "sg:phone":"+32 13 32 26 03",
    "sg:postcode":"3980",
    "sg:province":"Limburg",
    "wof:name":"Tuinen Sannen",
    "wof:placetype":"venue"
},
  "geometry": {"coordinates":[5.0322780609,51.0227622986],"type":"Point"}
}