{
  "type": "Feature",
  "properties": {
    "addr:full":"Mgr. De Haernelaan 6 Kortrijk West-Vlaanderen 8500",
    "addr:housenumber":"6",
    "addr:postcode":"8500",
    "addr:street":"Mgr.;Haernelaan",
    "iso:country":"BE",
    "sg:address":"Mgr. De Haernelaan 6",
    "sg:city":"Kortrijk",
    "sg:orig_category":"Immobili\u00ebnkantoren Verzekeringsmakelaars and experts",
    "sg:phone":"+32 56 25 71 75",
    "sg:postcode":"8500",
    "sg:province":"West-Vlaanderen",
    "wof:name":"Verzekeringskantoor Pylyser",
    "wof:placetype":"venue"
},
  "geometry": {"coordinates":[3.2571389675,50.8222732544],"type":"Point"}
}