{
  "type": "Feature",
  "properties": {
    "addr:full":"Rue De Rouillon 93 Anhee Namur 5537",
    "addr:housenumber":"93",
    "addr:postcode":"5537",
    "addr:street":"Rue De Rouillon",
    "iso:country":"BE",
    "sg:address":"Rue De Rouillon 93",
    "sg:city":"Anhee",
    "sg:orig_category":"Benzinestations and brandstoffen Herstellingen and onderhoud van auto's Voertuigen",
    "sg:phone":"+32 71 79 91 28",
    "sg:postcode":"5537",
    "sg:province":"Namur",
    "wof:name":"Colpe Roger & Fils",
    "wof:placetype":"venue"
},
  "geometry": {"coordinates":[4.8169221878,50.3388977051],"type":"Point"}
}