{
  "type": "Feature",
  "properties": {
    "addr:full":"Rue D'ardevoor 74 H\u00e9l\u00e9cine (neerheylissem) Brabant Wallon 1357",
    "addr:housenumber":"74",
    "addr:postcode":"1357",
    "addr:street":"Rue D'Ardevoor;Wallon",
    "iso:country":"BE",
    "sg:address":"Rue D'ardevoor 74",
    "sg:city":"H\u00e9l\u00e9cine (neerheylissem)",
    "sg:classifiers":[
        {
            "category":"Health Services",
            "subcategory":"Health Practitioner",
            "type":"Services"
        }
    ],
    "sg:phone":"+32 19 65 69 21",
    "sg:postcode":"1357",
    "sg:province":"Brabant Wallon",
    "sg:tags":[
        "physiotherapist"
    ],
    "wof:name":"Dezone Sandra",
    "wof:placetype":"venue"
},
  "geometry": {"coordinates":[4.9993729591,50.7633628845],"type":"Point"}
}