{
  "type": "Feature",
  "properties": {
    "iso:country":"BE",
    "sg:address":"Chauss\u00c9e De Dinant 931",
    "sg:city":"Namur",
    "sg:orig_category":"Woningbouw",
    "sg:phone":"+32 81 46 18 04",
    "sg:postcode":"5100",
    "sg:province":"Namur",
    "wof:name":"Tradihouse",
    "wof:placetype":"venue"
},
  "geometry": {"coordinates":[4.8745150566,50.4232597351],"type":"Point"}
}