{
  "type": "Feature",
  "properties": {
    "iso:country":"BE",
    "sg:address":"Gentstraat 220",
    "sg:city":"Ingelmunster",
    "sg:orig_category":"Etalage- and showroomontwerpers",
    "sg:phone":"+32 56 66 80 76",
    "sg:postcode":"8770",
    "sg:province":"West-Vlaanderen",
    "wof:name":"Tillo Vandenbroucke",
    "wof:placetype":"venue"
},
  "geometry": {"coordinates":[3.2804260254,50.911315918],"type":"Point"}
}