{
  "type": "Feature",
  "properties": {
    "iso:country":"BE",
    "sg:address":"Crapaurue 101",
    "sg:city":"Verviers",
    "sg:orig_category":"Cr\u00e9meries",
    "sg:phone":"+32 87 33 67 78",
    "sg:postcode":"4800",
    "sg:province":"Li\u00e8ge",
    "wof:name":"Cr\u00c8merie Colette",
    "wof:placetype":"venue"
},
  "geometry": {"coordinates":[5.864151001,50.5927200317],"type":"Point"}
}