{
  "type": "Feature",
  "properties": {
    "addr:full":"Boulevard Joseph Tirou 33 Charleroi Hainaut 6000",
    "addr:housenumber":"33",
    "addr:postcode":"6000",
    "addr:street":"Boulevard Joseph Tirou;Hainaut",
    "iso:country":"BE",
    "sg:address":"Boulevard Joseph Tirou 33",
    "sg:city":"Charleroi",
    "sg:classifiers":[
        {
            "category":"Arts & Performance",
            "subcategory":"Symphony",
            "type":"Entertainment"
        }
    ],
    "sg:phone":"+32 71 31 41 34",
    "sg:postcode":"6000",
    "sg:province":"Hainaut",
    "sg:tags":[
        "orchestra"
    ],
    "wof:name":"Sean Jones",
    "wof:placetype":"venue"
},
  "geometry": {"coordinates":[4.4388790131,50.408946991],"type":"Point"}
}