{
  "type": "Feature",
  "properties": {
    "iso:country":"BE",
    "sg:address":"Rue Du Bijard 17",
    "sg:city":"Fosses-la-ville (sart-saint-laurent)",
    "sg:classifiers":[
        {
            "category":"Farming",
            "subcategory":"Farm & Veterinary Services",
            "type":"Manufacturing & Wholesale Goods"
        }
    ],
    "sg:phone":"+32 71 71 37 03",
    "sg:postcode":"5070",
    "sg:province":"Namur",
    "sg:tags":[
        "agricultural",
        "contractor"
    ],
    "wof:name":"Michaux P",
    "wof:placetype":"venue"
},
  "geometry": {"coordinates":[4.7199487686,50.4109230042],"type":"Point"}
}