{
  "type": "Feature",
  "properties": {
    "iso:country":"BE",
    "sg:address":"Boulevard Des G\u00c9rardchamps 6",
    "sg:city":"Verviers",
    "sg:orig_category":"Boekhandels Speelgoed",
    "sg:phone":"+32 87 31 11 85",
    "sg:postcode":"4800",
    "sg:province":"Li\u00e8ge",
    "wof:name":"Librairie L'ille Ouverte",
    "wof:placetype":"venue"
},
  "geometry": {"coordinates":[5.8471598625,50.5935783386],"type":"Point"}
}