{
  "type": "Feature",
  "properties": {
    "iso:country":"BE",
    "sg:address":"Zandstraat 31a",
    "sg:city":"Heist-op-den-berg (schriek)",
    "sg:classifiers":[
        {
            "category":"Professional",
            "subcategory":"Computer Services",
            "type":"Services"
        }
    ],
    "sg:phone":"+32 15 51 37 63",
    "sg:postcode":"2223",
    "sg:province":"Antwerpen",
    "sg:tags":[
        "repair",
        "processing",
        "-",
        "maintenance",
        "data"
    ],
    "wof:name":"Bruwier G",
    "wof:placetype":"venue"
},
  "geometry": {"coordinates":[4.7163939476,51.0167045593],"type":"Point"}
}