{
  "type": "Feature",
  "properties": {
    "addr:full":"Chauss\u00c9e De Bruxelles Waterloo Brabant Wallon 1410",
    "addr:postcode":"1410",
    "addr:street":"Chausse\u0301E De Bruxelles",
    "iso:country":"BE",
    "sg:address":"Chauss\u00c9e De Bruxelles",
    "sg:city":"Waterloo",
    "sg:classifiers":[
        {
            "category":"Restaurant",
            "type":"Food & Drink"
        }
    ],
    "sg:phone":"+32 2 351 57 27",
    "sg:postcode":"1410",
    "sg:province":"Brabant Wallon",
    "wof:name":"La Baraka",
    "wof:placetype":"venue"
},
  "geometry": {"coordinates":[4.4002289772,50.7122306824],"type":"Point"}
}