{
  "type": "Feature",
  "properties": {
    "addr:full":"Boekweitstraat 3 Jabbeke West-Vlaanderen 8490",
    "addr:housenumber":"3",
    "addr:postcode":"8490",
    "addr:street":"Boekweitstraat",
    "iso:country":"BE",
    "sg:address":"Boekweitstraat 3",
    "sg:city":"Jabbeke",
    "sg:classifiers":[
        {
            "category":"Wholesale",
            "subcategory":"Wine & Distilled Alcoholic Beverages",
            "type":"Manufacturing & Wholesale Goods"
        }
    ],
    "sg:phone":"+32 50 81 39 36",
    "sg:postcode":"8490",
    "sg:province":"West-Vlaanderen",
    "sg:tags":[
        "whol",
        "-",
        "spirit",
        "mfg"
    ],
    "wof:name":"El Pozo",
    "wof:placetype":"venue"
},
  "geometry": {"coordinates":[3.0842421055,51.1754608154],"type":"Point"}
}