{
  "type": "Feature",
  "properties": {
    "addr:full":"Aarschotsesteenweg 394 Leuven Vlaams-Brabant 3012",
    "addr:housenumber":"394",
    "addr:postcode":"3012",
    "addr:street":"Aarschotsesteenweg",
    "iso:country":"BE",
    "sg:address":"Aarschotsesteenweg 394",
    "sg:city":"Leuven",
    "sg:orig_category":"Pharmaciens",
    "sg:phone":"+32 16 44 53 15",
    "sg:postcode":"3012",
    "sg:province":"Vlaams-Brabant",
    "wof:name":"Agnes Laevers",
    "wof:placetype":"venue"
},
  "geometry": {"coordinates":[4.7156820297,50.913898468],"type":"Point"}
}