{
  "type": "Feature",
  "properties": {
    "addr:full":"Place Chanoine J Pierlot 7 Bertrix Luxembourg 6880",
    "addr:housenumber":"7",
    "addr:postcode":"6880",
    "addr:street":"Place Chanoine J Pierlot",
    "iso:country":"BE",
    "sg:address":"Place Chanoine J Pierlot 7",
    "sg:city":"Bertrix",
    "sg:classifiers":[
        {
            "category":"Travel",
            "subcategory":"Hotels & Motels",
            "type":"Entertainment"
        }
    ],
    "sg:phone":"+32 61 41 21 62",
    "sg:postcode":"6880",
    "sg:province":"Luxembourg",
    "wof:name":"Hotel Des Roches",
    "wof:placetype":"venue"
},
  "geometry": {"coordinates":[5.2535948753,49.8544845581],"type":"Point"}
}