{
  "type": "Feature",
  "properties": {
    "iso:country":"BE",
    "sg:address":"Robynsstraat 1",
    "sg:city":"Ham (kwaadmechelen)",
    "sg:classifiers":[
        {
            "category":"Utilities",
            "subcategory":"Recycling",
            "type":"Services"
        }
    ],
    "sg:phone":"+32 13 66 53 73",
    "sg:postcode":"3945",
    "sg:province":"Limburg",
    "sg:tags":[
        "rubbish",
        "removal"
    ],
    "wof:name":"Van Bael E",
    "wof:placetype":"venue"
},
  "geometry": {"coordinates":[5.1776199341,51.1046104431],"type":"Point"}
}