{
  "type": "Feature",
  "properties": {
    "addr:full":"Chauss\u00c9e De Binche 92b1 Mons Hainaut 7000",
    "addr:housenumber":"92b1",
    "addr:postcode":"7000",
    "addr:street":"Chausse\u0301E De Binche;Hainaut",
    "iso:country":"BE",
    "sg:address":"Chauss\u00c9e De Binche 92b1",
    "sg:city":"Mons",
    "sg:orig_category":"Dierenartsen",
    "sg:phone":"+32 65 34 74 90",
    "sg:postcode":"7000",
    "sg:province":"Hainaut",
    "wof:name":"Veronique De Haan",
    "wof:placetype":"venue"
},
  "geometry": {"coordinates":[3.9894969463,50.4490470886],"type":"Point"}
}