{
  "type": "Feature",
  "properties": {
    "iso:country":"BE",
    "sg:address":"Vlaamsesteenweg 169",
    "sg:city":"Brussel/bruxelles",
    "sg:orig_category":"Drukkerijen and copyshops",
    "sg:phone":"+32 2 218 68 00",
    "sg:postcode":"1000",
    "sg:province":"Bruxelles-Capitale",
    "wof:name":"Imprim. & Public. Marais",
    "wof:placetype":"venue"
},
  "geometry": {"coordinates":[4.3430562019,50.8531150818],"type":"Point"}
}