{
  "type": "Feature",
  "properties": {
    "iso:country":"BE",
    "sg:address":"Zeedijk 182",
    "sg:city":"Blankenberge",
    "sg:classifiers":[
        {
            "category":"Building & Trades",
            "subcategory":"Electrical",
            "type":"Services"
        }
    ],
    "sg:phone":"+32 475 94 92 60",
    "sg:postcode":"8370",
    "sg:province":"West-Vlaanderen",
    "sg:tags":[
        "electric",
        "-",
        "housewiring",
        "contractor"
    ],
    "wof:name":"Geoffrey Light Decor Bvba",
    "wof:placetype":"venue"
},
  "geometry": {"coordinates":[3.1348159313,51.3176078796],"type":"Point"}
}