{
  "type": "Feature",
  "properties": {
    "addr:full":"Savoiestraat 25 Sint-gillis/saint-gilles Bruxelles-Capitale 1060",
    "addr:housenumber":"25",
    "addr:postcode":"1060",
    "addr:street":"Savoiestraat",
    "iso:country":"BE",
    "sg:address":"Savoiestraat 25",
    "sg:city":"Sint-gillis/saint-gilles",
    "sg:orig_category":"Zalen voor culturele evenementen",
    "sg:phone":"+32 2 534 20 98",
    "sg:postcode":"1060",
    "sg:province":"Bruxelles-Capitale",
    "wof:name":"Macadam",
    "wof:placetype":"venue"
},
  "geometry": {"coordinates":[4.3473601341,50.8246459961],"type":"Point"}
}