{
  "type": "Feature",
  "properties": {
    "addr:full":"Avenue De La Houssi\u00c8re 100 Braine-le-comte Hainaut 7090",
    "addr:housenumber":"100",
    "addr:postcode":"7090",
    "addr:street":"Avenue De La Houssie\u0300Re",
    "iso:country":"BE",
    "sg:address":"Avenue De La Houssi\u00c8re 100",
    "sg:city":"Braine-le-comte",
    "sg:orig_category":"Enseignement maternel and primaire. Enseignement secondaire g\u00e9n\u00e9ral",
    "sg:phone":"+32 67 55 31 21",
    "sg:postcode":"7090",
    "sg:province":"Hainaut",
    "wof:name":"E.p.e.s.c.f.",
    "wof:placetype":"venue"
},
  "geometry": {"coordinates":[4.1530618668,50.6103553772],"type":"Point"}
}