{
  "type": "Feature",
  "properties": {
    "addr:full":"Rue Debast 2 Qui\u00e9vrain Hainaut 7380",
    "addr:housenumber":"2",
    "addr:postcode":"7380",
    "addr:street":"Rue Debast",
    "iso:country":"BE",
    "sg:address":"Rue Debast 2",
    "sg:city":"Qui\u00e9vrain",
    "sg:classifiers":[
        {
            "category":"Bars & Pubs",
            "type":"Food & Drink"
        }
    ],
    "sg:phone":"+32 65 45 71 32",
    "sg:postcode":"7380",
    "sg:province":"Hainaut",
    "wof:name":"Taverne (de La)",
    "wof:placetype":"venue"
},
  "geometry": {"coordinates":[3.6831018925,50.4075202942],"type":"Point"}
}