{
  "type": "Feature",
  "properties": {
    "addr:full":"Rue Franklin-roosevelt 5 Neufchateau Luxembourg 6840",
    "addr:housenumber":"5",
    "addr:postcode":"6840",
    "addr:street":"Rue Franklin-Roosevelt",
    "iso:country":"BE",
    "sg:address":"Rue Franklin-roosevelt 5",
    "sg:city":"Neufchateau",
    "sg:orig_category":"Schoonheidssalons",
    "sg:phone":"+32 61 27 88 84",
    "sg:postcode":"6840",
    "sg:province":"Luxembourg",
    "wof:name":"P\u00c9dicure Alicia",
    "wof:placetype":"venue"
},
  "geometry": {"coordinates":[5.4347410202,49.8405456543],"type":"Point"}
}