{
  "type": "Feature",
  "properties": {
    "iso:country":"BE",
    "sg:address":"Rue De L'industrie 24",
    "sg:city":"Saint-nicolas",
    "sg:orig_category":"Gespecialiseerde niet-residenti\u00eble bouw Metalen constructies Fab",
    "sg:phone":"+32 4 231 22 89",
    "sg:postcode":"4420",
    "sg:province":"Li\u00e8ge",
    "wof:name":"Tardec",
    "wof:placetype":"venue"
},
  "geometry": {"coordinates":[5.5231590271,50.6202545166],"type":"Point"}
}