{
  "type": "Feature",
  "properties": {
    "iso:country":"BE",
    "sg:address":"Appelmansstraat 16",
    "sg:city":"Antwerpen",
    "sg:classifiers":[
        {
            "category":"Shopping",
            "subcategory":"Party Supplies",
            "type":"Retail Goods"
        }
    ],
    "sg:phone":"+32 3 232 32 97",
    "sg:postcode":"2018",
    "sg:province":"Antwerpen",
    "sg:tags":[
        "hunting"
    ],
    "wof:name":"Pire J & Co Bvba",
    "wof:placetype":"venue"
},
  "geometry": {"coordinates":[4.4172148705,51.2168464661],"type":"Point"}
}