{
  "type": "Feature",
  "properties": {
    "addr:full":"Hoogstraat 10 Riemst Limburg 3770",
    "addr:housenumber":"10",
    "addr:postcode":"3770",
    "addr:street":"Hoogstraat",
    "iso:country":"BE",
    "sg:address":"Hoogstraat 10",
    "sg:city":"Riemst",
    "sg:classifiers":[
        {
            "category":"Manufacturing",
            "subcategory":"Wood Products",
            "type":"Manufacturing & Wholesale Goods"
        }
    ],
    "sg:phone":"+32 12 45 39 19",
    "sg:postcode":"3770",
    "sg:province":"Limburg",
    "sg:tags":[
        "gate",
        "made",
        "door"
    ],
    "wof:name":"Skantrae B.v.b.a.",
    "wof:placetype":"venue"
},
  "geometry": {"coordinates":[5.5929632187,50.7907333374],"type":"Point"}
}