{
  "type": "Feature",
  "properties": {
    "iso:country":"BE",
    "sg:address":"Blankenbergse Steenweg 50",
    "sg:city":"Brugge",
    "sg:classifiers":[
        {
            "category":"Retail",
            "subcategory":"Veterinary Services",
            "type":"Services"
        }
    ],
    "sg:phone":"+32 50 31 84 27",
    "sg:postcode":"8000",
    "sg:province":"West-Vlaanderen",
    "sg:tags":[
        "veterinarian"
    ],
    "wof:name":"Laleman J",
    "wof:placetype":"venue"
},
  "geometry": {"coordinates":[3.2225248814,51.2070388794],"type":"Point"}
}