{
  "type": "Feature",
  "properties": {
    "iso:country":"BE",
    "sg:address":"Bld Maurice Lemonnier 26",
    "sg:city":"Brussel/bruxelles",
    "sg:orig_category":"Agences de presse",
    "sg:phone":"+32 2 511 32 85",
    "sg:postcode":"1000",
    "sg:province":"Bruxelles-Capitale",
    "wof:name":"Anne-fran\u00c7oise Moyson",
    "wof:placetype":"venue"
},
  "geometry": {"coordinates":[4.3457841873,50.8443870544],"type":"Point"}
}