{
  "type": "Feature",
  "properties": {
    "iso:country":"BE",
    "sg:address":"Kanonstraat 25",
    "sg:city":"Kortrijk",
    "sg:orig_category":"Artsen and specialisten",
    "sg:phone":"+32 56 22 38 26",
    "sg:postcode":"8500",
    "sg:province":"West-Vlaanderen",
    "wof:name":"Norbert Naert",
    "wof:placetype":"venue"
},
  "geometry": {"coordinates":[3.2711930275,50.8225364685],"type":"Point"}
}