{
  "type": "Feature",
  "properties": {
    "addr:full":"Ieperstraat 67-69 Poperinge West-Vlaanderen 8970",
    "addr:housenumber":"67-69",
    "addr:postcode":"8970",
    "addr:street":"Ieperstraat",
    "iso:country":"BE",
    "sg:address":"Ieperstraat 67-69",
    "sg:city":"Poperinge",
    "sg:classifiers":[
        {
            "category":"Shopping",
            "subcategory":"Luggage & Leather Goods",
            "type":"Retail Goods"
        }
    ],
    "sg:phone":"+32 57 33 77 88",
    "sg:postcode":"8970",
    "sg:province":"West-Vlaanderen",
    "sg:tags":[
        "-"
    ],
    "wof:name":"Decuyper Lederwaren",
    "wof:placetype":"venue"
},
  "geometry": {"coordinates":[2.7304499149,50.8541755676],"type":"Point"}
}