{
  "type": "Feature",
  "properties": {
    "addr:full":"Hasseltsesteenweg 469 Sint-truiden Limburg 3800",
    "addr:housenumber":"469",
    "addr:postcode":"3800",
    "addr:street":"Hasseltsesteenweg",
    "iso:country":"BE",
    "sg:address":"Hasseltsesteenweg 469",
    "sg:city":"Sint-truiden",
    "sg:classifiers":[
        {
            "category":"Personal",
            "subcategory":"Beauty Salon",
            "type":"Services"
        }
    ],
    "sg:phone":"+32 11 59 23 59",
    "sg:postcode":"3800",
    "sg:province":"Limburg",
    "wof:name":"Orchis Bvba",
    "wof:placetype":"venue"
},
  "geometry": {"coordinates":[5.2025399208,50.8290252686],"type":"Point"}
}