{
  "type": "Feature",
  "properties": {
    "iso:country":"BE",
    "sg:address":"D\u00c9sir\u00c9 Vandervaerenstr. 1ba",
    "sg:city":"Hoeilaart",
    "sg:orig_category":"Enseignement maternel and primaire",
    "sg:phone":"+32 2 657 51 95",
    "sg:postcode":"1560",
    "sg:province":"Vlaams-Brabant",
    "wof:name":"Vrije Kleuterschool",
    "wof:placetype":"venue"
},
  "geometry": {"coordinates":[4.4757871628,50.7664527893],"type":"Point"}
}