{
  "type": "Feature",
  "properties": {
    "addr:full":"Meren 4a Olen Antwerpen 2250",
    "addr:housenumber":"4a",
    "addr:postcode":"2250",
    "addr:street":"Meren",
    "iso:country":"BE",
    "sg:address":"Meren 4a",
    "sg:city":"Olen",
    "sg:orig_category":"Agences de voyages",
    "sg:phone":"+32 14 22 39 33",
    "sg:postcode":"2250",
    "sg:province":"Antwerpen",
    "wof:name":"Hummel Ski Sport",
    "wof:placetype":"venue"
},
  "geometry": {"coordinates":[4.9182338715,51.1640129089],"type":"Point"}
}