{
  "type": "Feature",
  "properties": {
    "addr:full":"Gentsesteenweg 552 Aalst Oost-Vlaanderen 9300",
    "addr:housenumber":"552",
    "addr:postcode":"9300",
    "addr:street":"Gentsesteenweg",
    "iso:country":"BE",
    "sg:address":"Gentsesteenweg 552",
    "sg:city":"Aalst",
    "sg:orig_category":"Meubles D\u00e9taillants, Am\u00e9nagement de B\u00e2timents et de Cuisines. Meubles D\u00e9taillants, Am\u00e9nagement de B\u00e2",
    "sg:phone":"+32 53 70 90 77",
    "sg:postcode":"9300",
    "sg:province":"Oost-Vlaanderen",
    "wof:name":"Ch\u00c2teau D'ax",
    "wof:placetype":"venue"
},
  "geometry": {"coordinates":[3.9962251186,50.9420280457],"type":"Point"}
}