{
  "type": "Feature",
  "properties": {
    "iso:country":"BE",
    "sg:address":"Th. De Cleynlaan 12",
    "sg:city":"Denderleeuw",
    "sg:orig_category":"Caf\u00e9s Sportclubs",
    "sg:phone":"+32 53 66 63 04",
    "sg:postcode":"9470",
    "sg:province":"Oost-Vlaanderen",
    "wof:name":"Denderleeuw G T C",
    "wof:placetype":"venue"
},
  "geometry": {"coordinates":[4.0745410919,50.8881607056],"type":"Point"}
}