{
  "type": "Feature",
  "properties": {
    "iso:country":"BE",
    "sg:address":".",
    "sg:city":"Tinlot",
    "sg:orig_category":"Sportterreinen and installaties behalve sportcentra",
    "sg:phone":"+32 80 41 84 60",
    "sg:postcode":"4557",
    "sg:province":"Li\u00e8ge",
    "wof:name":"Piste outdoor Ski Relais",
    "wof:placetype":"venue"
},
  "geometry": {"coordinates":[5.3753452301,50.47864151],"type":"Point"}
}