{
  "type": "Feature",
  "properties": {
    "iso:country":"BE",
    "sg:address":"Oostrozebekestraat 85-87",
    "sg:city":"Meulebeke",
    "sg:classifiers":[
        {
            "category":"Home & Garden",
            "subcategory":"Household Appliances",
            "type":"Retail Goods"
        }
    ],
    "sg:phone":"+32 51 48 88 46",
    "sg:postcode":"8760",
    "sg:province":"West-Vlaanderen",
    "sg:tags":[
        "repair",
        "mainten",
        "-",
        "electric"
    ],
    "wof:name":"Elektro Van Severen Bvba",
    "wof:placetype":"venue"
},
  "geometry": {"coordinates":[3.2921760082,50.9462165833],"type":"Point"}
}