{
  "type": "Feature",
  "properties": {
    "iso:country":"BE",
    "sg:address":"Grand'rue 67",
    "sg:city":"Tintigny",
    "sg:classifiers":[
        {
            "category":"Professional",
            "subcategory":"Accounting & Tax Preparation",
            "type":"Services"
        }
    ],
    "sg:phone":"+32 63 44 00 55",
    "sg:postcode":"6730",
    "sg:province":"Luxembourg",
    "sg:tags":[
        "bookkeeper"
    ],
    "wof:name":"Bureau Comptable Denis & Genin Snc",
    "wof:placetype":"venue"
},
  "geometry": {"coordinates":[5.519217968,49.6826286316],"type":"Point"}
}