{
  "type": "Feature",
  "properties": {
    "iso:country":"BE",
    "sg:address":"Rue Des Monts 57",
    "sg:city":"Beauraing (pondr\u00f4me)",
    "sg:classifiers":[
        {
            "category":"Building & Trades",
            "subcategory":"Construction",
            "type":"Services"
        }
    ],
    "sg:phone":"+32 82 71 10 62",
    "sg:postcode":"5574",
    "sg:province":"Namur",
    "sg:tags":[
        "carpenter"
    ],
    "wof:name":"Damilot Leonet Sprl",
    "wof:placetype":"venue"
},
  "geometry": {"coordinates":[5.0153150558,50.1016960144],"type":"Point"}
}