{
  "type": "Feature",
  "properties": {
    "addr:full":"Roeselaarsestraat 191 Moorslede West-Vlaanderen 8890",
    "addr:housenumber":"191",
    "addr:postcode":"8890",
    "addr:street":"Roeselaarsestraat",
    "iso:country":"BE",
    "sg:address":"Roeselaarsestraat 191",
    "sg:city":"Moorslede",
    "sg:classifiers":[
        {
            "category":"Farming",
            "subcategory":"Farm & Veterinary Services",
            "type":"Manufacturing & Wholesale Goods"
        }
    ],
    "sg:phone":"+32 51 77 10 56",
    "sg:postcode":"8890",
    "sg:province":"West-Vlaanderen",
    "sg:tags":[
        "material",
        "cattle-breeding"
    ],
    "wof:name":"Degro's Trofeeshop",
    "wof:placetype":"venue"
},
  "geometry": {"coordinates":[3.0722539425,50.9045143127],"type":"Point"}
}