{
  "type": "Feature",
  "properties": {
    "iso:country":"BE",
    "sg:address":"Kloosterstraat 6",
    "sg:city":"Gavere",
    "sg:orig_category":"Maisons de repos and r\u00e9sidences",
    "sg:phone":"+32 9 384 47 14",
    "sg:postcode":"9890",
    "sg:province":"Oost-Vlaanderen",
    "wof:name":"Rustoord Mariahuis",
    "wof:placetype":"venue"
},
  "geometry": {"coordinates":[3.662938118,50.9291038513],"type":"Point"}
}