{
  "type": "Feature",
  "properties": {
    "iso:country":"BE",
    "sg:address":"Edgar Tinellaan 57",
    "sg:city":"Kortrijk",
    "sg:classifiers":[
        {
            "category":"Professional",
            "subcategory":"Lawyer & Legal Services",
            "type":"Services"
        }
    ],
    "sg:phone":"+32 56 35 91 94",
    "sg:postcode":"8500",
    "sg:province":"West-Vlaanderen",
    "wof:name":"Deprez Kristel",
    "wof:placetype":"venue"
},
  "geometry": {"coordinates":[3.2666471004,50.8395118713],"type":"Point"}
}