{
  "type": "Feature",
  "properties": {
    "iso:country":"BE",
    "sg:address":"Rue Du Moulin \u00e0 Eau 1",
    "sg:city":"Braine L'alleud (ophain-bois-seigneur-isaac)",
    "sg:classifiers":[
        {
            "category":"Building & Trades",
            "subcategory":"Landscaping Services",
            "type":"Services"
        }
    ],
    "sg:phone":"+32 2 387 34 13",
    "sg:postcode":"1421",
    "sg:province":"Brabant Wallon",
    "sg:tags":[
        "gardening",
        "garden",
        "maintenance"
    ],
    "wof:name":"Scheerlinckx C",
    "wof:placetype":"venue"
},
  "geometry": {"coordinates":[-0.708509028,47.4608650208],"type":"Point"}
}