{
  "type": "Feature",
  "properties": {
    "addr:full":"Solterweg 13 Maaseik (neeroeteren) Limburg 3680",
    "addr:housenumber":"13",
    "addr:postcode":"3680",
    "addr:street":"Solterweg",
    "iso:country":"BE",
    "sg:address":"Solterweg 13",
    "sg:city":"Maaseik (neeroeteren)",
    "sg:classifiers":[
        {
            "category":"Utilities",
            "subcategory":"Fuel Oil & Lpg",
            "type":"Services"
        }
    ],
    "sg:phone":"+32 89 86 40 60",
    "sg:postcode":"3680",
    "sg:province":"Limburg",
    "wof:name":"Segers J Brandstoffen",
    "wof:placetype":"venue"
},
  "geometry": {"coordinates":[5.6861419678,51.1113166809],"type":"Point"}
}