{
  "type": "Feature",
  "properties": {
    "addr:full":"Rue De Goz\u00c9e 217 Montigny-le-tilleul Hainaut 6110",
    "addr:housenumber":"217",
    "addr:postcode":"6110",
    "addr:street":"Rue De Goze\u0301E",
    "iso:country":"BE",
    "sg:address":"Rue De Goz\u00c9e 217",
    "sg:city":"Montigny-le-tilleul",
    "sg:orig_category":"Landmeters",
    "sg:phone":"+32 71 51 80 41",
    "sg:postcode":"6110",
    "sg:province":"Hainaut",
    "wof:name":"Jean Mercier",
    "wof:placetype":"venue"
},
  "geometry": {"coordinates":[4.3798661232,50.3855743408],"type":"Point"}
}