{
  "type": "Feature",
  "properties": {
    "addr:full":"Rue L\u00e9opold Crasset 127 Profondeville (bois-de-villers) Namur 5170",
    "addr:housenumber":"127",
    "addr:postcode":"5170",
    "addr:street":"Rue Le\u0301Opold Crasset",
    "iso:country":"BE",
    "sg:address":"Rue L\u00e9opold Crasset 127",
    "sg:city":"Profondeville (bois-de-villers)",
    "sg:classifiers":[
        {
            "category":"Home & Garden",
            "subcategory":"Hardware",
            "type":"Retail Goods"
        }
    ],
    "sg:phone":"+32 81 43 40 05",
    "sg:postcode":"5170",
    "sg:province":"Namur",
    "sg:tags":[
        "machine",
        "horticultural"
    ],
    "wof:name":"Botton Z",
    "wof:placetype":"venue"
},
  "geometry": {"coordinates":[4.8264980316,50.3732337952],"type":"Point"}
}