{
  "type": "Feature",
  "properties": {
    "addr:full":"Rue Lotard 87 Bernissart Hainaut 7320",
    "addr:housenumber":"87",
    "addr:postcode":"7320",
    "addr:street":"Rue Lotard",
    "iso:country":"BE",
    "sg:address":"Rue Lotard 87",
    "sg:city":"Bernissart",
    "sg:orig_category":"Boissons",
    "sg:phone":"+32 69 57 57 58",
    "sg:postcode":"7320",
    "sg:province":"Hainaut",
    "wof:name":"Fe. Ronfaut & Fils",
    "wof:placetype":"venue"
},
  "geometry": {"coordinates":[3.6449980736,50.4775695801],"type":"Point"}
}