{
  "type": "Feature",
  "properties": {
    "addr:full":"Avenue De L'aquilon 15b1 Sint-lambrechts-woluwe/woluwe-saint-lambert Bruxelles-Capitale 1200",
    "addr:housenumber":"15b1",
    "addr:postcode":"1200",
    "addr:street":"Avenue De L'Aquilon",
    "iso:country":"BE",
    "sg:address":"Avenue De L'aquilon 15b1",
    "sg:city":"Sint-lambrechts-woluwe/woluwe-saint-lambert",
    "sg:classifiers":[
        {
            "category":"Personal",
            "subcategory":"Beauty Salon",
            "type":"Services"
        }
    ],
    "sg:phone":"+32 2 771 86 10",
    "sg:postcode":"1200",
    "sg:province":"Bruxelles-Capitale",
    "sg:tags":[
        "de",
        "coiffure"
    ],
    "wof:name":"Diminu Tif",
    "wof:placetype":"venue"
},
  "geometry": {"coordinates":[4.4389410019,50.8510780334],"type":"Point"}
}