{
  "type": "Feature",
  "properties": {
    "iso:country":"BE",
    "sg:address":"Verbondstraat 31",
    "sg:city":"Antwerpen",
    "sg:classifiers":[
        {
            "category":"School Buses",
            "type":"Transportation"
        }
    ],
    "sg:phone":"+32 486 25 38 98",
    "sg:postcode":"2000",
    "sg:province":"Antwerpen",
    "sg:tags":[
        "homeopathy"
    ],
    "wof:name":"Bergmans G",
    "wof:placetype":"venue"
},
  "geometry": {"coordinates":[4.4006171227,51.2103042603],"type":"Point"}
}