{
  "type": "Feature",
  "properties": {
    "addr:full":"Dorpstraat 7 Dilsen-stokkem Limburg 3650",
    "addr:housenumber":"7",
    "addr:postcode":"3650",
    "addr:street":"Dorpstraat",
    "iso:country":"BE",
    "sg:address":"Dorpstraat 7",
    "sg:city":"Dilsen-stokkem",
    "sg:orig_category":"V\u00eatements. V\u00eatements pour Hommes. V\u00eatements pour Dames. V\u00eatements pour b\u00e9b\u00e9s and enfants",
    "sg:phone":"+32 89 75 47 77",
    "sg:postcode":"3650",
    "sg:province":"Limburg",
    "wof:name":"Strike",
    "wof:placetype":"venue"
},
  "geometry": {"coordinates":[5.726170063,51.0189208984],"type":"Point"}
}