{
  "type": "Feature",
  "properties": {
    "iso:country":"BE",
    "sg:address":"Bruggestraat 127",
    "sg:city":"Torhout",
    "sg:classifiers":[
        {
            "category":"Building & Trades",
            "subcategory":"Pest Control",
            "type":"Services"
        }
    ],
    "sg:phone":"+32 50 21 25 82",
    "sg:postcode":"8820",
    "sg:province":"West-Vlaanderen",
    "sg:tags":[
        "painting",
        "contractor"
    ],
    "wof:name":"Vande Caveye K",
    "wof:placetype":"venue"
},
  "geometry": {"coordinates":[3.1125628948,51.0780487061],"type":"Point"}
}