{
  "type": "Feature",
  "properties": {
    "iso:country":"BE",
    "sg:address":"Lambroekstraat 5a",
    "sg:city":"Machelen (diegem)",
    "sg:orig_category":"Non-Classified Establishments",
    "sg:phone":"+32 2 719 03 39",
    "sg:postcode":"1831",
    "sg:province":"Vlaams-Brabant",
    "wof:name":"Erico Benelux Bvba",
    "wof:placetype":"venue"
},
  "geometry": {"coordinates":[4.4486842155,50.880191803],"type":"Point"}
}