{
  "type": "Feature",
  "properties": {
    "iso:country":"BE",
    "sg:address":"Place Roi Albert I 2",
    "sg:city":"Rochefort",
    "sg:classifiers":[
        {
            "category":"Travel",
            "subcategory":"Hotels & Motels",
            "type":"Entertainment"
        }
    ],
    "sg:phone":"+32 84 21 31 68",
    "sg:postcode":"5580",
    "sg:province":"Namur",
    "wof:name":"Luxembourg (le)",
    "wof:placetype":"venue"
},
  "geometry": {"coordinates":[5.223470211,50.1585006714],"type":"Point"}
}