{
  "type": "Feature",
  "properties": {
    "addr:full":"Rue Hansez 85 Olne Li\u00e8ge 4877",
    "addr:housenumber":"85",
    "addr:postcode":"4877",
    "addr:street":"Rue Hansez",
    "iso:country":"BE",
    "sg:address":"Rue Hansez 85",
    "sg:city":"Olne",
    "sg:classifiers":[
        {
            "category":"Communications",
            "type":"Services"
        }
    ],
    "sg:phone":"+32 4 351 82 51",
    "sg:postcode":"4877",
    "sg:province":"Li\u00e8ge",
    "sg:tags":[
        "translator"
    ],
    "wof:name":"Chantrain G",
    "wof:placetype":"venue"
},
  "geometry": {"coordinates":[5.7174677849,50.5719146729],"type":"Point"}
}