{
  "type": "Feature",
  "properties": {
    "iso:country":"BE",
    "sg:address":"Rue Haigne 54",
    "sg:city":"Tournai",
    "sg:classifiers":[
        {
            "category":"Real Estate",
            "subcategory":"Architect",
            "type":"Services"
        }
    ],
    "sg:phone":"+32 69 22 65 74",
    "sg:postcode":"7500",
    "sg:province":"Hainaut",
    "wof:name":"Patte Ch",
    "wof:placetype":"venue"
},
  "geometry": {"coordinates":[3.3966200352,50.6069831848],"type":"Point"}
}