{
  "type": "Feature",
  "properties": {
    "iso:country":"BE",
    "sg:address":"Jules Vermandelestraat 6",
    "sg:city":"Ingelmunster",
    "sg:orig_category":"Kapsalons",
    "sg:phone":"+32 51 31 89 19",
    "sg:postcode":"8770",
    "sg:province":"West-Vlaanderen",
    "wof:name":"Coiffure Isabel Windels",
    "wof:placetype":"venue"
},
  "geometry": {"coordinates":[3.2430429459,50.9279556274],"type":"Point"}
}