{
  "type": "Feature",
  "properties": {
    "iso:country":"BE",
    "sg:address":"Rue Rochers De Fr\u00e8ne 2",
    "sg:city":"Profondeville (lustin)",
    "sg:classifiers":[
        {
            "category":"Utilities",
            "subcategory":"Telephone",
            "type":"Services"
        }
    ],
    "sg:phone":"+32 81 41 25 54",
    "sg:postcode":"5170",
    "sg:province":"Namur",
    "sg:tags":[
        "-",
        "internet"
    ],
    "wof:name":"Pmi Consulting",
    "wof:placetype":"venue"
},
  "geometry": {"coordinates":[4.8674049377,50.3786392212],"type":"Point"}
}