{
  "type": "Feature",
  "properties": {
    "addr:full":"Bessenlaan 83 Rotselaar Vlaams-Brabant 3110",
    "addr:housenumber":"83",
    "addr:postcode":"3110",
    "addr:street":"Bessenlaan",
    "iso:country":"BE",
    "sg:address":"Bessenlaan 83",
    "sg:city":"Rotselaar",
    "sg:orig_category":"Studios photographiques",
    "sg:phone":"+32 16 58 06 99",
    "sg:postcode":"3110",
    "sg:province":"Vlaams-Brabant",
    "wof:name":"P.l. Photography",
    "wof:placetype":"venue"
},
  "geometry": {"coordinates":[4.7107920647,50.9508590698],"type":"Point"}
}