{
  "type": "Feature",
  "properties": {
    "iso:country":"BE",
    "sg:address":"Rue Du Gravier 15",
    "sg:city":"Li\u00e8ge 1 (ch\u00ean\u00e9e)",
    "sg:classifiers":[
        {
            "category":"Shopping",
            "subcategory":"Clothing, Apparel, & Fashions",
            "type":"Retail Goods"
        }
    ],
    "sg:phone":"+32 4 365 66 87",
    "sg:postcode":"4032",
    "sg:province":"Li\u00e8ge",
    "sg:tags":[
        "boutique"
    ],
    "wof:name":"Clermont A Boutique",
    "wof:placetype":"venue"
},
  "geometry": {"coordinates":[5.6156249046,50.6108322144],"type":"Point"}
}