{
  "type": "Feature",
  "properties": {
    "addr:full":"Gentsesteenweg 252 Wetteren Oost-Vlaanderen 9230",
    "addr:housenumber":"252",
    "addr:postcode":"9230",
    "addr:street":"Gentsesteenweg",
    "iso:country":"BE",
    "sg:address":"Gentsesteenweg 252",
    "sg:city":"Wetteren",
    "sg:orig_category":"M\u00e9decins and sp\u00e9cialistes",
    "sg:phone":"+32 9 369 12 25",
    "sg:postcode":"9230",
    "sg:province":"Oost-Vlaanderen",
    "wof:name":"Andr\u00c9 Sandra",
    "wof:placetype":"venue"
},
  "geometry": {"coordinates":[3.864759922,50.9994621277],"type":"Point"}
}