{
  "type": "Feature",
  "properties": {
    "addr:full":"Gobbelsrode 30 Holsbeek Vlaams-Brabant 3220",
    "addr:housenumber":"30",
    "addr:postcode":"3220",
    "addr:street":"Gobbelsrode",
    "iso:country":"BE",
    "sg:address":"Gobbelsrode 30",
    "sg:city":"Holsbeek",
    "sg:orig_category":"M\u00e9decins and sp\u00e9cialistes",
    "sg:phone":"+32 16 62 23 12",
    "sg:postcode":"3220",
    "sg:province":"Vlaams-Brabant",
    "wof:name":"Hilde Lagae",
    "wof:placetype":"venue"
},
  "geometry": {"coordinates":[4.7575721741,50.9207267761],"type":"Point"}
}