{
  "type": "Feature",
  "properties": {
    "addr:full":"Handboogstraat 41 Wevelgem West-Vlaanderen 8560",
    "addr:housenumber":"41",
    "addr:postcode":"8560",
    "addr:street":"Handboogstraat",
    "iso:country":"BE",
    "sg:address":"Handboogstraat 41",
    "sg:city":"Wevelgem",
    "sg:classifiers":[
        {
            "category":"Professional",
            "subcategory":"Detective & Security Services",
            "type":"Services"
        }
    ],
    "sg:phone":"+32 56 42 08 83",
    "sg:postcode":"8560",
    "sg:province":"West-Vlaanderen",
    "sg:tags":[
        "installation",
        "alarm",
        "-",
        "system"
    ],
    "wof:name":"Aveco Bvba",
    "wof:placetype":"venue"
},
  "geometry": {"coordinates":[3.1875779629,50.8113861084],"type":"Point"}
}