{
  "type": "Feature",
  "properties": {
    "iso:country":"BE",
    "sg:address":"Rue Victor Delporte 114",
    "sg:city":"Dour",
    "sg:orig_category":"Groenten and fruit Gh Kruideniers",
    "sg:phone":"+32 65 65 39 85",
    "sg:postcode":"7370",
    "sg:province":"Hainaut",
    "wof:name":"Marie-rose De Leye",
    "wof:placetype":"venue"
},
  "geometry": {"coordinates":[3.7876229286,50.3921699524],"type":"Point"}
}