{
  "type": "Feature",
  "properties": {
    "iso:country":"BE",
    "sg:address":"Strombeek Beverselaan 132",
    "sg:city":"Meise",
    "sg:classifiers":[
        {
            "category":"Professional",
            "subcategory":"Management & Consulting",
            "type":"Services"
        }
    ],
    "sg:phone":"+32 477 80 36 20",
    "sg:postcode":"1860",
    "sg:province":"Vlaams-Brabant",
    "sg:tags":[
        "-",
        "processing",
        "data",
        "consultant"
    ],
    "wof:name":"Dlw Consulting",
    "wof:placetype":"venue"
},
  "geometry": {"coordinates":[4.339700222,50.9226074219],"type":"Point"}
}