{
  "type": "Feature",
  "properties": {
    "addr:full":"Wolfstee 7-1 Herentals Antwerpen 2200",
    "addr:housenumber":"7-1",
    "addr:postcode":"2200",
    "addr:street":"Wolfstee",
    "iso:country":"BE",
    "sg:address":"Wolfstee 7-1",
    "sg:city":"Herentals",
    "sg:classifiers":[
        {
            "category":"Home & Garden",
            "subcategory":"Building Materials",
            "type":"Retail Goods"
        }
    ],
    "sg:phone":"+32 14 22 27 10",
    "sg:postcode":"2200",
    "sg:province":"Antwerpen",
    "sg:tags":[
        "article",
        "-",
        "do-it-yourself"
    ],
    "wof:name":"Verwimp Doe Het Zelf Nv",
    "wof:placetype":"venue"
},
  "geometry": {"coordinates":[4.7984261513,51.1682167053],"type":"Point"}
}