{
  "type": "Feature",
  "properties": {
    "iso:country":"BE",
    "sg:address":"Kuitenbergstraat 2",
    "sg:city":"Evergem",
    "sg:orig_category":"Pain, p\u00e2tisseries and confiseries",
    "sg:phone":"+32 9 253 05 03",
    "sg:postcode":"9940",
    "sg:province":"Oost-Vlaanderen",
    "wof:name":"Danny Bernaerdt",
    "wof:placetype":"venue"
},
  "geometry": {"coordinates":[3.6616580486,51.102191925],"type":"Point"}
}