{
  "type": "Feature",
  "properties": {
    "iso:country":"BE",
    "sg:address":"Passage De L'universit\u00c9 41f",
    "sg:city":"Liege",
    "sg:orig_category":"Aanleg van wegen, sportterreinen and vliegvelden Afbraak- and draineerwerken Industri\u00eble and commerc",
    "sg:phone":"+32 4 368 80 04",
    "sg:postcode":"4000",
    "sg:province":"Li\u00e8ge",
    "wof:name":"Vanmos Winck",
    "wof:placetype":"venue"
},
  "geometry": {"coordinates":[5.5744590759,50.6414642334],"type":"Point"}
}