{
  "type": "Feature",
  "properties": {
    "iso:country":"BE",
    "sg:address":"Wijngaard 1",
    "sg:city":"Rotselaar",
    "sg:orig_category":"Productie van shows and podiumkunsten",
    "sg:phone":"+32 16 44 57 80",
    "sg:postcode":"3110",
    "sg:province":"Vlaams-Brabant",
    "wof:name":"Kon. Fanfare Rotselaers Ware Vrienden",
    "wof:placetype":"venue"
},
  "geometry": {"coordinates":[4.7112708092,50.9492721558],"type":"Point"}
}