{
  "type": "Feature",
  "properties": {
    "iso:country":"BE",
    "sg:address":"Place De La Vaillance 4",
    "sg:city":"Anderlecht",
    "sg:classifiers":[
        {
            "category":"Personal",
            "subcategory":"Beauty Salon",
            "type":"Services"
        }
    ],
    "sg:phone":"+32 2 520 78 40",
    "sg:postcode":"1070",
    "sg:province":"Bruxelles-Capitale",
    "sg:tags":[
        "de",
        "coiffure"
    ],
    "wof:name":"Jean - Claude Biguine",
    "wof:placetype":"venue"
},
  "geometry": {"coordinates":[4.3071651459,50.8354949951],"type":"Point"}
}