{
  "type": "Feature",
  "properties": {
    "addr:full":"Kapellensteenweg 381 Kalmthout Antwerpen 2920",
    "addr:housenumber":"381",
    "addr:postcode":"2920",
    "addr:street":"Kapellensteenweg",
    "iso:country":"BE",
    "sg:address":"Kapellensteenweg 381",
    "sg:city":"Kalmthout",
    "sg:classifiers":[
        {
            "category":"Health Services",
            "subcategory":"Health Practitioner",
            "type":"Services"
        }
    ],
    "sg:phone":"+32 3 666 88 32",
    "sg:postcode":"2920",
    "sg:province":"Antwerpen",
    "sg:tags":[
        "physiotherapist"
    ],
    "wof:name":"Adriaenssens Guy",
    "wof:placetype":"venue"
},
  "geometry": {"coordinates":[4.472140789,51.3739318848],"type":"Point"}
}