{
  "type": "Feature",
  "properties": {
    "iso:country":"BE",
    "sg:address":"Kromstraat 93",
    "sg:city":"Dessel",
    "sg:classifiers":[
        {
            "category":"Shopping",
            "type":"Retail Goods"
        }
    ],
    "sg:phone":"+32 14 37 40 71",
    "sg:postcode":"2480",
    "sg:province":"Antwerpen",
    "sg:tags":[
        "product",
        "cleaning",
        "maintenance"
    ],
    "wof:name":"Green Cleaning Products Bvba",
    "wof:placetype":"venue"
},
  "geometry": {"coordinates":[5.1418762207,51.2371482849],"type":"Point"}
}