{
  "type": "Feature",
  "properties": {
    "addr:full":"Romeinsesteenweg 452 Grimbergen (strombeek-bever) Vlaams-Brabant 1853",
    "addr:housenumber":"452",
    "addr:postcode":"1853",
    "addr:street":"Romeinsesteenweg",
    "iso:country":"BE",
    "sg:address":"Romeinsesteenweg 452",
    "sg:city":"Grimbergen (strombeek-bever)",
    "sg:classifiers":[
        {
            "category":"Professional",
            "subcategory":"Computer Services",
            "type":"Services"
        }
    ],
    "sg:phone":"+32 2 306 00 03",
    "sg:postcode":"1853",
    "sg:province":"Vlaams-Brabant",
    "sg:tags":[
        "webdesign",
        "-",
        "internet"
    ],
    "wof:name":"Uniweb Bvba",
    "wof:placetype":"venue"
},
  "geometry": {"coordinates":[4.3538870811,50.9014434814],"type":"Point"}
}