{
  "type": "Feature",
  "properties": {
    "addr:full":"Rue Sax 2 Dinant Namur 5500",
    "addr:housenumber":"2",
    "addr:postcode":"5500",
    "addr:street":"Rue Sax",
    "iso:country":"BE",
    "sg:address":"Rue Sax 2",
    "sg:city":"Dinant",
    "sg:classifiers":[
        {
            "category":"Restaurant",
            "type":"Food & Drink"
        }
    ],
    "sg:phone":"+32 82 22 23 72",
    "sg:postcode":"5500",
    "sg:province":"Namur",
    "sg:tags":[
        "de",
        "organisation",
        "\u00e0",
        "fast",
        "catering",
        "emporter",
        "f\u00eates",
        "restaurants"
    ],
    "wof:name":"Caf\u00c9 Leffe",
    "wof:placetype":"venue"
},
  "geometry": {"coordinates":[4.9119329453,50.2604866028],"type":"Point"}
}