{
  "type": "Feature",
  "properties": {
    "addr:full":"Schoolstraat 102 Mol Antwerpen 2400",
    "addr:housenumber":"102",
    "addr:postcode":"2400",
    "addr:street":"Schoolstraat",
    "iso:country":"BE",
    "sg:address":"Schoolstraat 102",
    "sg:city":"Mol",
    "sg:classifiers":[
        {
            "category":"Arena",
            "subcategory":"Sports Club",
            "type":"Entertainment"
        }
    ],
    "sg:phone":"+32 14 31 86 23",
    "sg:postcode":"2400",
    "sg:province":"Antwerpen",
    "sg:tags":[
        "terrain",
        "hors",
        "de",
        "installation",
        "sportifs"
    ],
    "wof:name":"Millegem Sport",
    "wof:placetype":"venue"
},
  "geometry": {"coordinates":[5.2066721916,51.2083892822],"type":"Point"}
}