{
  "type": "Feature",
  "properties": {
    "addr:full":"Neringstraat 2 Blankenberge (uitkerke) West-Vlaanderen 8370",
    "addr:housenumber":"2",
    "addr:postcode":"8370",
    "addr:street":"Neringstraat",
    "iso:country":"BE",
    "sg:address":"Neringstraat 2",
    "sg:city":"Blankenberge (uitkerke)",
    "sg:orig_category":"Non-Classified Establishments",
    "sg:phone":"+32 50 42 72 40",
    "sg:postcode":"8370",
    "sg:province":"West-Vlaanderen",
    "wof:name":"S.s.a. Sportings Goods",
    "wof:placetype":"venue"
},
  "geometry": {"coordinates":[3.1544480324,51.2963447571],"type":"Point"}
}