{
  "type": "Feature",
  "properties": {
    "iso:country":"BE",
    "sg:address":"Rue De Verviers 109bb",
    "sg:city":"Eupen/eupen",
    "sg:orig_category":"Artistes ind\u00e9pendants",
    "sg:phone":"+32 87 55 46 56",
    "sg:postcode":"4700",
    "sg:province":"Li\u00e8ge",
    "wof:name":"Joseph Christmann",
    "wof:placetype":"venue"
},
  "geometry": {"coordinates":[6.0155520439,50.6323051453],"type":"Point"}
}