{
  "type": "Feature",
  "properties": {
    "iso:country":"BE",
    "sg:address":"Dorpsstraat 13",
    "sg:city":"Kapellen",
    "sg:orig_category":"Equipement photographique. Studios photographiques",
    "sg:phone":"+32 3 665 18 44",
    "sg:postcode":"2950",
    "sg:province":"Antwerpen",
    "wof:name":"Studio Karin",
    "wof:placetype":"venue"
},
  "geometry": {"coordinates":[4.4287657738,51.3154792786],"type":"Point"}
}