{
  "type": "Feature",
  "properties": {
    "addr:full":"Topmolen 22 Londerzeel Vlaams-Brabant 1840",
    "addr:housenumber":"22",
    "addr:postcode":"1840",
    "addr:street":"Topmolen",
    "iso:country":"BE",
    "sg:address":"Topmolen 22",
    "sg:city":"Londerzeel",
    "sg:classifiers":[
        {
            "category":"Building & Trades",
            "subcategory":"Locksmith",
            "type":"Services"
        }
    ],
    "sg:phone":"+32 52 30 62 69",
    "sg:postcode":"1840",
    "sg:province":"Vlaams-Brabant",
    "sg:tags":[
        "lock",
        "key"
    ],
    "wof:name":"Pepa Beveiliging",
    "wof:placetype":"venue"
},
  "geometry": {"coordinates":[4.294093132,51.0227432251],"type":"Point"}
}