{
  "type": "Feature",
  "properties": {
    "iso:country":"BE",
    "sg:address":"Achterstraat 26",
    "sg:city":"Evergem",
    "sg:orig_category":"Salles de billard and snooker",
    "sg:phone":"+32 9 344 70 39",
    "sg:postcode":"9940",
    "sg:province":"Oost-Vlaanderen",
    "wof:name":"Pallieter",
    "wof:placetype":"venue"
},
  "geometry": {"coordinates":[3.7452750206,51.1806564331],"type":"Point"}
}