{
  "type": "Feature",
  "properties": {
    "iso:country":"BE",
    "sg:address":"Van Monstraat 22",
    "sg:city":"Blankenberge",
    "sg:orig_category":"V\u00e9los. Articles de camping and de sport. Location d'articles de sport, de sport nautique and de camp",
    "sg:phone":"+32 50 41 39 33",
    "sg:postcode":"8370",
    "sg:province":"West-Vlaanderen",
    "wof:name":"Alain Croes",
    "wof:placetype":"venue"
},
  "geometry": {"coordinates":[3.1329228878,51.3162345886],"type":"Point"}
}