{
  "type": "Feature",
  "properties": {
    "iso:country":"BE",
    "sg:address":"Rue D'andenne 13",
    "sg:city":"Havelange",
    "sg:classifiers":[
        {
            "category":"Retail",
            "subcategory":"Funeral Services",
            "type":"Services"
        }
    ],
    "sg:phone":"+32 83 63 30 52",
    "sg:postcode":"5370",
    "sg:province":"Namur",
    "sg:tags":[
        "director"
    ],
    "wof:name":"Hebette-daxhelet",
    "wof:placetype":"venue"
},
  "geometry": {"coordinates":[5.2361311913,50.3903961182],"type":"Point"}
}