{
  "type": "Feature",
  "properties": {
    "addr:full":"Chauss\u00e9e De Louvain 867 Bruxelles (evere) Bruxelles-Capitale 1140",
    "addr:housenumber":"867",
    "addr:postcode":"1140",
    "addr:street":"Chausse\u0301E De Louvain",
    "iso:country":"BE",
    "sg:address":"Chauss\u00e9e De Louvain 867",
    "sg:city":"Bruxelles (evere)",
    "sg:classifiers":[
        {
            "category":"Retail",
            "subcategory":"Driving School",
            "type":"Services"
        }
    ],
    "sg:phone":"+32 2 726 65 64",
    "sg:postcode":"1140",
    "sg:province":"Bruxelles-Capitale",
    "sg:tags":[
        "automobile",
        "officially",
        "-",
        "recognized"
    ],
    "wof:name":"Auto Ecoles Contact Sprl",
    "wof:placetype":"venue"
},
  "geometry": {"coordinates":[4.4168448448,50.8598136902],"type":"Point"}
}