{
  "type": "Feature",
  "properties": {
    "iso:country":"BE",
    "sg:address":"Route De Durbuy 14",
    "sg:city":"Havelange (maffe)",
    "sg:classifiers":[
        {
            "category":"Food & Beverages",
            "subcategory":"Cheese",
            "type":"Retail Goods"
        }
    ],
    "sg:phone":"+32 86 32 23 43",
    "sg:postcode":"5374",
    "sg:province":"Namur",
    "sg:tags":[
        "-"
    ],
    "wof:name":"La Fermi\u00e8re De Mean Scrl",
    "wof:placetype":"venue"
},
  "geometry": {"coordinates":[5.3241510391,50.3534507751],"type":"Point"}
}