{
  "type": "Feature",
  "properties": {
    "iso:country":"BE",
    "sg:address":"Handelstraat 31",
    "sg:city":"Ingelmunster",
    "sg:classifiers":[
        {
            "category":"Building & Trades",
            "subcategory":"Construction",
            "type":"Services"
        }
    ],
    "sg:phone":"+32 51 30 31 28",
    "sg:postcode":"8770",
    "sg:province":"West-Vlaanderen",
    "sg:tags":[
        "carpenter"
    ],
    "wof:name":"Verstraete M",
    "wof:placetype":"venue"
},
  "geometry": {"coordinates":[3.2581980228,50.9135704041],"type":"Point"}
}