{
  "type": "Feature",
  "properties": {
    "addr:full":"Rue Larmoulin 95 Pont-a-celles Hainaut 6230",
    "addr:housenumber":"95",
    "addr:postcode":"6230",
    "addr:street":"Rue Larmoulin",
    "iso:country":"BE",
    "sg:address":"Rue Larmoulin 95",
    "sg:city":"Pont-a-celles",
    "sg:orig_category":"Plaatsen van vloer- and muurbekleding Schilders",
    "sg:phone":"+32 71 37 37 61",
    "sg:postcode":"6230",
    "sg:province":"Hainaut",
    "wof:name":"Peintures Schollaert",
    "wof:placetype":"venue"
},
  "geometry": {"coordinates":[4.3908920288,50.4976539612],"type":"Point"}
}