{
  "type": "Feature",
  "properties": {
    "addr:full":"Izegemsestraat 35 Ledegem West-Vlaanderen 8880",
    "addr:housenumber":"35",
    "addr:postcode":"8880",
    "addr:street":"Izegemsestraat",
    "iso:country":"BE",
    "sg:address":"Izegemsestraat 35",
    "sg:city":"Ledegem",
    "sg:orig_category":"M\u00e9decins and sp\u00e9cialistes",
    "sg:phone":"+32 56 50 00 88",
    "sg:postcode":"8880",
    "sg:province":"West-Vlaanderen",
    "wof:name":"Brigitte Delmotte",
    "wof:placetype":"venue"
},
  "geometry": {"coordinates":[3.1810200214,50.880531311],"type":"Point"}
}