{
  "type": "Feature",
  "properties": {
    "iso:country":"BE",
    "sg:address":"Rue Du Faubourg 1",
    "sg:city":"Beloeil (bas\u00e8cles)",
    "sg:orig_category":"Non-Classified Establishments",
    "sg:phone":"+32 69 57 65 74",
    "sg:postcode":"7971",
    "sg:province":"Hainaut",
    "wof:name":"Gosselin G",
    "wof:placetype":"venue"
},
  "geometry": {"coordinates":[3.6358969212,50.5285644531],"type":"Point"}
}