{
  "type": "Feature",
  "properties": {
    "addr:full":"Rue Des Combattants 58 Wavre Brabant Wallon 1301",
    "addr:housenumber":"58;1301",
    "addr:street":"Rue Des Combattants",
    "iso:country":"BE",
    "sg:address":"Rue Des Combattants 58",
    "sg:city":"Wavre",
    "sg:orig_category":"Woningbouw",
    "sg:phone":"+32 10 41 49 15",
    "sg:postcode":"1301",
    "sg:province":"Brabant Wallon",
    "wof:name":"Entreprises Damoiseau",
    "wof:placetype":"venue"
},
  "geometry": {"coordinates":[4.5811271667,50.712852478],"type":"Point"}
}