{
  "type": "Feature",
  "properties": {
    "addr:full":"Rue Du Moulin 53 Montigny-le-tilleul Hainaut 6110",
    "addr:housenumber":"53",
    "addr:postcode":"6110",
    "addr:street":"Rue Du Moulin",
    "iso:country":"BE",
    "sg:address":"Rue Du Moulin 53",
    "sg:city":"Montigny-le-tilleul",
    "sg:classifiers":[
        {
            "category":"Health Services",
            "subcategory":"Nursing And Care Facility",
            "type":"Services"
        }
    ],
    "sg:phone":"+32 71 51 01 91",
    "sg:postcode":"6110",
    "sg:province":"Hainaut",
    "sg:tags":[
        "home"
    ],
    "wof:name":"Paternoster B",
    "wof:placetype":"venue"
},
  "geometry": {"coordinates":[4.3884968758,50.3756141663],"type":"Point"}
}