{
  "type": "Feature",
  "properties": {
    "iso:country":"BE",
    "sg:address":"Lascheid 43",
    "sg:city":"Burg-reuland",
    "sg:classifiers":[
        {
            "category":"Travel",
            "subcategory":"Hotels & Motels",
            "type":"Entertainment"
        }
    ],
    "sg:phone":"+32 80 32 96 24",
    "sg:postcode":"4790",
    "sg:province":"Li\u00e8ge",
    "wof:name":"Paquet",
    "wof:placetype":"venue"
},
  "geometry": {"coordinates":[6.1315770149,50.1943702698],"type":"Point"}
}