{
  "type": "Feature",
  "properties": {
    "iso:country":"BE",
    "sg:address":"Kruisenstraat 61",
    "sg:city":"Laarne",
    "sg:orig_category":"Artsen and specialisten",
    "sg:phone":"+32 9 367 64 30",
    "sg:postcode":"9270",
    "sg:province":"Oost-Vlaanderen",
    "wof:name":"Alex De Smet",
    "wof:placetype":"venue"
},
  "geometry": {"coordinates":[3.8489339352,51.0294075012],"type":"Point"}
}