{
  "type": "Feature",
  "properties": {
    "addr:full":"Rozendaalstraat 60 Ieper West-Vlaanderen 8900",
    "addr:housenumber":"60",
    "addr:postcode":"8900",
    "addr:street":"Rozendaalstraat",
    "iso:country":"BE",
    "sg:address":"Rozendaalstraat 60",
    "sg:city":"Ieper",
    "sg:orig_category":"Ramassage and traitement des d\u00e9chets m\u00e9nagers",
    "sg:phone":"+32 57 21 69 16",
    "sg:postcode":"8900",
    "sg:province":"West-Vlaanderen",
    "wof:name":"Westcompost Ieper",
    "wof:placetype":"venue"
},
  "geometry": {"coordinates":[2.8878269196,50.8513641357],"type":"Point"}
}