{
  "type": "Feature",
  "properties": {
    "iso:country":"BE",
    "sg:address":"Roeselaarsestraat 114",
    "sg:city":"Moorslede",
    "sg:orig_category":"Boucheries",
    "sg:phone":"+32 51 77 82 39",
    "sg:postcode":"8890",
    "sg:province":"West-Vlaanderen",
    "wof:name":"Frederik Vandevelde",
    "wof:placetype":"venue"
},
  "geometry": {"coordinates":[3.0661129951,50.8952903748],"type":"Point"}
}