{
  "type": "Feature",
  "properties": {
    "iso:country":"BE",
    "sg:address":"Tijl Uilenspiegelstraat 14",
    "sg:city":"Gent",
    "sg:classifiers":[
        {
            "category":"Insurance",
            "subcategory":"Insurance Agent",
            "type":"Services"
        }
    ],
    "sg:phone":"+32 9 230 19 12",
    "sg:postcode":"9050",
    "sg:province":"Oost-Vlaanderen",
    "sg:tags":[
        "verzekeringsmakelaars",
        "expert"
    ],
    "wof:name":"V.s. Consulting Verzekeringen",
    "wof:placetype":"venue"
},
  "geometry": {"coordinates":[3.7754518986,51.0336303711],"type":"Point"}
}