{
  "type": "Feature",
  "properties": {
    "addr:full":"Nieuwstraat 59 Leuven Vlaams-Brabant 3018",
    "addr:housenumber":"59",
    "addr:postcode":"3018",
    "addr:street":"Nieuwstraat",
    "iso:country":"BE",
    "sg:address":"Nieuwstraat 59",
    "sg:city":"Leuven",
    "sg:orig_category":"Kapsalons",
    "sg:phone":"+32 16 44 54 71",
    "sg:postcode":"3018",
    "sg:province":"Vlaams-Brabant",
    "wof:name":"Coiffure Brigitte",
    "wof:placetype":"venue"
},
  "geometry": {"coordinates":[4.6969590187,50.9251403809],"type":"Point"}
}