{
  "type": "Feature",
  "properties": {
    "addr:full":"Oud Kapellekelaan 5b48 Evere Bruxelles-Capitale 1140",
    "addr:housenumber":"5b48",
    "addr:postcode":"1140",
    "addr:street":"Oud Kapellekelaan",
    "iso:country":"BE",
    "sg:address":"Oud Kapellekelaan 5b48",
    "sg:city":"Evere",
    "sg:orig_category":"Marketingbureaus",
    "sg:phone":"+32 2 245 47 24",
    "sg:postcode":"1140",
    "sg:province":"Bruxelles-Capitale",
    "wof:name":"Caelen",
    "wof:placetype":"venue"
},
  "geometry": {"coordinates":[4.4037761688,50.8741836548],"type":"Point"}
}