{
  "type": "Feature",
  "properties": {
    "addr:full":"Rue Grande 92 Mons Hainaut 7020",
    "addr:housenumber":"92",
    "addr:postcode":"7020",
    "addr:street":"Rue Grande;Hainaut",
    "iso:country":"BE",
    "sg:address":"Rue Grande 92",
    "sg:city":"Mons",
    "sg:classifiers":[
        {
            "category":"Food & Beverages",
            "subcategory":"Fruits & Vegetables",
            "type":"Retail Goods"
        }
    ],
    "sg:phone":"+32 65 31 34 50",
    "sg:postcode":"7020",
    "sg:province":"Hainaut",
    "sg:tags":[
        "l\u00e9gumes",
        "gr"
    ],
    "wof:name":"Jean-marie Hachez",
    "wof:placetype":"venue"
},
  "geometry": {"coordinates":[3.9553449154,50.4761772156],"type":"Point"}
}