{
  "type": "Feature",
  "properties": {
    "addr:full":"Rue Haute 29 Aubange Luxembourg 6791",
    "addr:housenumber":"29",
    "addr:postcode":"6791",
    "addr:street":"Rue Haute",
    "iso:country":"BE",
    "sg:address":"Rue Haute 29",
    "sg:city":"Aubange",
    "sg:orig_category":"Postkantoren Verzekeringsmakelaars and experts",
    "sg:phone":"+32 63 38 81 92",
    "sg:postcode":"6791",
    "sg:province":"Luxembourg",
    "wof:name":"La Poste",
    "wof:placetype":"venue"
},
  "geometry": {"coordinates":[5.8290491104,49.5621757507],"type":"Point"}
}