{
  "type": "Feature",
  "properties": {
    "addr:full":"Koning Boudewijnlaan 1 Hasselt Limburg 3500",
    "addr:housenumber":"1",
    "addr:postcode":"3500",
    "addr:street":"Koning Boudewijnlaan",
    "iso:country":"BE",
    "sg:address":"Koning Boudewijnlaan 1",
    "sg:city":"Hasselt",
    "sg:orig_category":"Sportclubs Sportterreinen and installaties behalve sportcentra",
    "sg:phone":"+32 11 22 44 36",
    "sg:postcode":"3500",
    "sg:province":"Limburg",
    "wof:name":"Hasselt V.v.",
    "wof:placetype":"venue"
},
  "geometry": {"coordinates":[5.3245539665,50.915435791],"type":"Point"}
}