{
  "type": "Feature",
  "properties": {
    "addr:full":"Rue Vanderkindere 440 Bruxelles (uccle) Bruxelles-Capitale 1180",
    "addr:housenumber":"440",
    "addr:postcode":"1180",
    "addr:street":"Rue Vanderkindere",
    "iso:country":"BE",
    "sg:address":"Rue Vanderkindere 440",
    "sg:city":"Bruxelles (uccle)",
    "sg:classifiers":[
        {
            "category":"Home & Garden",
            "subcategory":"Building Materials",
            "type":"Retail Goods"
        }
    ],
    "sg:phone":"+32 2 372 24 35",
    "sg:postcode":"1180",
    "sg:province":"Bruxelles-Capitale",
    "sg:tags":[
        "article",
        "-",
        "do-it-yourself"
    ],
    "wof:name":"Nova Brico",
    "wof:placetype":"venue"
},
  "geometry": {"coordinates":[4.3601861,50.8144798279],"type":"Point"}
}