{
  "type": "Feature",
  "properties": {
    "addr:full":"Burgemeesterstraat 12 Sint-martens-latem Oost-Vlaanderen 9830",
    "addr:housenumber":"12",
    "addr:postcode":"9830",
    "addr:street":"Burgemeesterstraat",
    "iso:country":"BE",
    "sg:address":"Burgemeesterstraat 12",
    "sg:city":"Sint-martens-latem",
    "sg:orig_category":"Diverse bedrijfsbeheeradviesbureaus",
    "sg:phone":"+32 9 281 00 82",
    "sg:postcode":"9830",
    "sg:province":"Oost-Vlaanderen",
    "wof:name":"P.m.c.",
    "wof:placetype":"venue"
},
  "geometry": {"coordinates":[3.6303219795,51.0164642334],"type":"Point"}
}