{
  "type": "Feature",
  "properties": {
    "iso:country":"BE",
    "sg:address":"Martelarenstraat 46",
    "sg:city":"Leopoldsburg",
    "sg:classifiers":[
        {
            "category":"Manufacturing",
            "subcategory":"Lumber",
            "type":"Manufacturing & Wholesale Goods"
        }
    ],
    "sg:phone":"+32 11 40 11 06",
    "sg:postcode":"3970",
    "sg:province":"Limburg",
    "sg:tags":[
        "timber"
    ],
    "wof:name":"Verellen Houthandel Nv",
    "wof:placetype":"venue"
},
  "geometry": {"coordinates":[5.2533950806,51.1238861084],"type":"Point"}
}