{
  "type": "Feature",
  "properties": {
    "iso:country":"BE",
    "sg:address":"Sint-amandsplein 11",
    "sg:city":"Kortrijk",
    "sg:orig_category":"Blanchisseries and teintureries",
    "sg:phone":"+32 56 35 47 72",
    "sg:postcode":"8500",
    "sg:province":"West-Vlaanderen",
    "wof:name":"Wassalon Soenen G.",
    "wof:placetype":"venue"
},
  "geometry": {"coordinates":[3.260997057,50.8328437805],"type":"Point"}
}