{
  "type": "Feature",
  "properties": {
    "addr:full":"Brandstraat 18 Beveren Oost-Vlaanderen 9120",
    "addr:housenumber":"18",
    "addr:postcode":"9120",
    "addr:street":"Brandstraat",
    "iso:country":"BE",
    "sg:address":"Brandstraat 18",
    "sg:city":"Beveren",
    "sg:orig_category":"Installation de menuiserie m\u00e9tallique. Installation de menuiserie en bois and plastique",
    "sg:phone":"+32 3 775 54 72",
    "sg:postcode":"9120",
    "sg:province":"Oost-Vlaanderen",
    "wof:name":"De Clerck & Zoon",
    "wof:placetype":"venue"
},
  "geometry": {"coordinates":[4.2109489441,51.2198486328],"type":"Point"}
}