{
  "type": "Feature",
  "properties": {
    "addr:full":"Avenue Des Bouleaux 15 Eigenbrakel Brabant Wallon 1420",
    "addr:housenumber":"15",
    "addr:postcode":"1420",
    "addr:street":"Avenue Des Bouleaux;Brabant Wallon",
    "iso:country":"BE",
    "sg:address":"Avenue Des Bouleaux 15",
    "sg:city":"Eigenbrakel",
    "sg:orig_category":"Diverse bedrijfsbeheeradviesbureaus",
    "sg:phone":"+32 2 353 12 57",
    "sg:postcode":"1420",
    "sg:province":"Brabant Wallon",
    "wof:name":"Albevco",
    "wof:placetype":"venue"
},
  "geometry": {"coordinates":[4.3375840187,50.7268486023],"type":"Point"}
}