{
  "type": "Feature",
  "properties": {
    "addr:full":"Route De Durbuy 78 Durbuy (barvaux-sur-ourthe) Luxembourg 6940",
    "addr:housenumber":"78",
    "addr:postcode":"6940",
    "addr:street":"Route De Durbuy",
    "iso:country":"BE",
    "sg:address":"Route De Durbuy 78",
    "sg:city":"Durbuy (barvaux-sur-ourthe)",
    "sg:classifiers":[
        {
            "category":"Real Estate",
            "subcategory":"Architect",
            "type":"Services"
        }
    ],
    "sg:phone":"+32 86 21 31 59",
    "sg:postcode":"6940",
    "sg:province":"Luxembourg",
    "wof:name":"Th\u00e9ate Joseph",
    "wof:placetype":"venue"
},
  "geometry": {"coordinates":[5.4543361664,50.3515777588],"type":"Point"}
}