{
  "type": "Feature",
  "properties": {
    "addr:full":"Vennelaan 7bc Sint-martens-latem Oost-Vlaanderen 9830",
    "addr:housenumber":"7bc",
    "addr:postcode":"9830",
    "addr:street":"Vennelaan",
    "iso:country":"BE",
    "sg:address":"Vennelaan 7bc",
    "sg:city":"Sint-martens-latem",
    "sg:orig_category":"Marketingbureaus Marktonderzoekbureaus",
    "sg:phone":"+32 9 282 28 39",
    "sg:postcode":"9830",
    "sg:province":"Oost-Vlaanderen",
    "wof:name":"Bureau Lexxus",
    "wof:placetype":"venue"
},
  "geometry": {"coordinates":[3.6336450577,51.0186538696],"type":"Point"}
}