{
  "type": "Feature",
  "properties": {
    "addr:full":"Meir 73 Antwerpen Antwerpen 2000",
    "addr:housenumber":"73",
    "addr:postcode":"2000",
    "addr:street":"Meir",
    "iso:country":"BE",
    "sg:address":"Meir 73",
    "sg:city":"Antwerpen",
    "sg:classifiers":[
        {
            "category":"Shopping",
            "subcategory":"Clothing, Apparel, & Fashions",
            "type":"Retail Goods"
        }
    ],
    "sg:phone":"+32 3 213 06 13",
    "sg:postcode":"2000",
    "sg:province":"Antwerpen",
    "sg:tags":[
        "lady",
        "clothing",
        "-"
    ],
    "wof:name":"Mango",
    "wof:placetype":"venue"
},
  "geometry": {"coordinates":[4.4097619057,51.2181930542],"type":"Point"}
}