{
  "type": "Feature",
  "properties": {
    "addr:full":"Winterslagstraat 79 Genk Limburg 3600",
    "addr:housenumber":"79",
    "addr:postcode":"3600",
    "addr:street":"Winterslagstraat",
    "iso:country":"BE",
    "sg:address":"Winterslagstraat 79",
    "sg:city":"Genk",
    "sg:orig_category":"Solariums",
    "sg:phone":"+32 89 35 97 92",
    "sg:postcode":"3600",
    "sg:province":"Limburg",
    "wof:name":"Bruincenter Cuypers",
    "wof:placetype":"venue"
},
  "geometry": {"coordinates":[5.4992399216,50.9671440125],"type":"Point"}
}