{
  "type": "Feature",
  "properties": {
    "addr:full":"Chemin Notre Dame 4 Ath (isi\u00e8res) Hainaut 7822",
    "addr:housenumber":"4",
    "addr:postcode":"7822",
    "addr:street":"Chemin Notre Dame",
    "iso:country":"BE",
    "sg:address":"Chemin Notre Dame 4",
    "sg:city":"Ath (isi\u00e8res)",
    "sg:classifiers":[
        {
            "category":"Health Services",
            "subcategory":"Doctor",
            "type":"Services"
        }
    ],
    "sg:phone":"+32 68 28 72 11",
    "sg:postcode":"7822",
    "sg:province":"Hainaut",
    "sg:tags":[
        "medicinephysicians",
        "surgeon"
    ],
    "wof:name":"Francq Nathalie",
    "wof:placetype":"venue"
},
  "geometry": {"coordinates":[3.8452620506,50.6482391357],"type":"Point"}
}