{
  "type": "Feature",
  "properties": {
    "addr:full":"Rue Du Lombard 29-31 Bruxelles Bruxelles-Capitale 1000",
    "addr:postcode":"29-31;1000",
    "addr:street":"Rue Du Lombard",
    "iso:country":"BE",
    "sg:address":"Rue Du Lombard 29-31",
    "sg:city":"Bruxelles",
    "sg:classifiers":[
        {
            "category":"Home & Garden",
            "subcategory":"Carpets & Floor Coverings",
            "type":"Retail Goods"
        }
    ],
    "sg:postcode":"1000",
    "sg:province":"Bruxelles-Capitale",
    "sg:tags":[
        "repair",
        "restoration",
        "-",
        "rug"
    ],
    "wof:name":"G.h. Sauvage Nv-sa",
    "wof:placetype":"venue"
},
  "geometry": {"coordinates":[4.3500361443,50.8457183838],"type":"Point"}
}