{
  "type": "Feature",
  "properties": {
    "iso:country":"BE",
    "sg:address":"Kruisbooglaan 18",
    "sg:city":"Brecht (sint-job-in-'t Goor)",
    "sg:classifiers":[
        {
            "category":"Building & Trades",
            "subcategory":"Cleaning & Sanitation",
            "type":"Services"
        }
    ],
    "sg:phone":"+32 3 636 25 74",
    "sg:postcode":"2960",
    "sg:province":"Antwerpen",
    "sg:tags":[
        "industrial",
        "-"
    ],
    "wof:name":"Aroo Bedrijfshygiene",
    "wof:placetype":"venue"
},
  "geometry": {"coordinates":[4.5609321594,51.2968788147],"type":"Point"}
}