{
  "type": "Feature",
  "properties": {
    "iso:country":"BE",
    "sg:address":"Rue Du Tilleul 13",
    "sg:city":"Genval",
    "sg:classifiers":[
        {
            "category":"Wholesale",
            "subcategory":"Drugs",
            "type":"Manufacturing & Wholesale Goods"
        }
    ],
    "sg:phone":"+32 2 656 21 11",
    "sg:postcode":"1332",
    "sg:province":"Brabant Wallon",
    "sg:tags":[
        "antibiotic"
    ],
    "wof:name":"Sb Pharma S.a.",
    "wof:placetype":"venue"
},
  "geometry": {"coordinates":[4.4994292259,50.7217292786],"type":"Point"}
}