{
  "type": "Feature",
  "properties": {
    "addr:full":"Boekentstraat 71 Haaltert Oost-Vlaanderen 9451",
    "addr:housenumber":"71",
    "addr:postcode":"9451",
    "addr:street":"Boekentstraat",
    "iso:country":"BE",
    "sg:address":"Boekentstraat 71",
    "sg:city":"Haaltert",
    "sg:orig_category":"Eleveurs de bovins",
    "sg:phone":"+32 53 83 59 03",
    "sg:postcode":"9451",
    "sg:province":"Oost-Vlaanderen",
    "wof:name":"Gustaaf Van Melckebeke",
    "wof:placetype":"venue"
},
  "geometry": {"coordinates":[3.974957943,50.8869285583],"type":"Point"}
}