{
  "type": "Feature",
  "properties": {
    "addr:full":"Kromstraat 33 Ranst Antwerpen 2520",
    "addr:housenumber":"33",
    "addr:postcode":"2520",
    "addr:street":"Kromstraat",
    "iso:country":"BE",
    "sg:address":"Kromstraat 33",
    "sg:city":"Ranst",
    "sg:classifiers":[
        {
            "category":"Health Services",
            "subcategory":"Health Practitioner",
            "type":"Services"
        }
    ],
    "sg:phone":"+32 3 233 66 26",
    "sg:postcode":"2520",
    "sg:province":"Antwerpen",
    "sg:tags":[
        "dietitian"
    ],
    "wof:name":"Thys Ellen",
    "wof:placetype":"venue"
},
  "geometry": {"coordinates":[4.5532178879,51.1923751831],"type":"Point"}
}