{
  "type": "Feature",
  "properties": {
    "addr:full":"Oudstationstraat 1 Oostende West-Vlaanderen 8400",
    "addr:housenumber":"1",
    "addr:postcode":"8400",
    "addr:street":"Oudstationstraat",
    "iso:country":"BE",
    "sg:address":"Oudstationstraat 1",
    "sg:city":"Oostende",
    "sg:classifiers":[
        {
            "category":"Government",
            "subcategory":"Police Station",
            "type":"Public Place"
        }
    ],
    "sg:phone":"+32 59 70 71 36",
    "sg:postcode":"8400",
    "sg:province":"West-Vlaanderen",
    "sg:tags":[
        "gendarmerie"
    ],
    "wof:name":"Federale Politie",
    "wof:placetype":"venue"
},
  "geometry": {"coordinates":[2.9126999378,51.2312583923],"type":"Point"}
}