{
  "type": "Feature",
  "properties": {
    "addr:full":"Boseind 28 Neerpelt Limburg 3910",
    "addr:housenumber":"28",
    "addr:postcode":"3910",
    "addr:street":"Boseind",
    "iso:country":"BE",
    "sg:address":"Boseind 28",
    "sg:city":"Neerpelt",
    "sg:orig_category":"Pain, p\u00e2tisseries and confiseries",
    "sg:phone":"+32 11 64 99 40",
    "sg:postcode":"3910",
    "sg:province":"Limburg",
    "wof:name":"Bakkerij Sylvie",
    "wof:placetype":"venue"
},
  "geometry": {"coordinates":[5.4401979446,51.2221641541],"type":"Point"}
}