{
  "type": "Feature",
  "properties": {
    "addr:full":"Rue Du Caurus 5 Nivelles Brabant Wallon 1400",
    "addr:housenumber":"5",
    "addr:postcode":"1400",
    "addr:street":"Rue Du Caurus",
    "iso:country":"BE",
    "sg:address":"Rue Du Caurus 5",
    "sg:city":"Nivelles",
    "sg:orig_category":"Kapsalons",
    "sg:phone":"+32 67 21 44 61",
    "sg:postcode":"1400",
    "sg:province":"Brabant Wallon",
    "wof:name":"Coiffure Mirage",
    "wof:placetype":"venue"
},
  "geometry": {"coordinates":[4.3327717781,50.5893325806],"type":"Point"}
}