{
  "type": "Feature",
  "properties": {
    "addr:full":"Rue G\u00c9n\u00c9ral Lotz 70 Ukkel/uccle Bruxelles-Capitale 1180",
    "addr:housenumber":"70",
    "addr:postcode":"1180",
    "addr:street":"Rue Ge\u0301Ne\u0301Ral Lotz;/",
    "iso:country":"BE",
    "sg:address":"Rue G\u00c9n\u00c9ral Lotz 70",
    "sg:city":"Ukkel/uccle",
    "sg:orig_category":"Cr\u00e8ches and garderies d'enfants",
    "sg:phone":"+32 2 343 76 31",
    "sg:postcode":"1180",
    "sg:province":"Bruxelles-Capitale",
    "wof:name":"Het Tinnen Soldaatje",
    "wof:placetype":"venue"
},
  "geometry": {"coordinates":[4.358771801,50.8128128052],"type":"Point"}
}