{
  "type": "Feature",
  "properties": {
    "addr:full":"Hanswijkvaart 77 Mechelen Antwerpen 2800",
    "addr:housenumber":"77",
    "addr:postcode":"2800",
    "addr:street":"Hanswijkvaart",
    "iso:country":"BE",
    "sg:address":"Hanswijkvaart 77",
    "sg:city":"Mechelen",
    "sg:orig_category":"Herstellingen and onderhoud van auto's",
    "sg:phone":"+32 15 45 05 60",
    "sg:postcode":"2800",
    "sg:province":"Antwerpen",
    "wof:name":"Belport Belgium",
    "wof:placetype":"venue"
},
  "geometry": {"coordinates":[4.4903979301,51.0105171204],"type":"Point"}
}