{
  "type": "Feature",
  "properties": {
    "iso:country":"BE",
    "sg:address":"Rue Crimont 11",
    "sg:city":"Ellezelles",
    "sg:classifiers":[
        {
            "category":"Health Services",
            "subcategory":"Doctor",
            "type":"Services"
        }
    ],
    "sg:phone":"+32 68 54 26 58",
    "sg:postcode":"7890",
    "sg:province":"Hainaut",
    "sg:tags":[
        "medicinephysicians",
        "surgeon"
    ],
    "wof:name":"Buidin E",
    "wof:placetype":"venue"
},
  "geometry": {"coordinates":[3.6650989056,50.7342453003],"type":"Point"}
}