{
  "type": "Feature",
  "properties": {
    "addr:full":"Koolkerkse Steenweg 77 Brugge West-Vlaanderen 8000",
    "addr:housenumber":"77",
    "addr:postcode":"8000",
    "addr:street":"Koolkerkse Steenweg",
    "iso:country":"BE",
    "sg:address":"Koolkerkse Steenweg 77",
    "sg:city":"Brugge",
    "sg:classifiers":[
        {
            "category":"Personal",
            "subcategory":"Beauty Salon",
            "type":"Services"
        }
    ],
    "sg:phone":"+32 50 33 65 95",
    "sg:postcode":"8000",
    "sg:province":"West-Vlaanderen",
    "wof:name":"Caroline",
    "wof:placetype":"venue"
},
  "geometry": {"coordinates":[3.2354710102,51.2251052856],"type":"Point"}
}