{
  "type": "Feature",
  "properties": {
    "iso:country":"BE",
    "sg:address":"Tervuursesteenweg 462",
    "sg:city":"Bertem (leefdaal)",
    "sg:classifiers":[
        {
            "category":"Professional",
            "subcategory":"Lawyer & Legal Services",
            "type":"Services"
        }
    ],
    "sg:phone":"+32 2 767 87 67",
    "sg:postcode":"3061",
    "sg:province":"Vlaams-Brabant",
    "sg:tags":[
        "notary"
    ],
    "wof:name":"Vangoetsenhoven E",
    "wof:placetype":"venue"
},
  "geometry": {"coordinates":[4.6010370255,50.8580284119],"type":"Point"}
}