{
  "type": "Feature",
  "properties": {
    "iso:country":"BE",
    "sg:address":"Rue Sous-le-ch\u00e2teau 80",
    "sg:city":"Huy",
    "sg:classifiers":[
        {
            "category":"Shopping",
            "subcategory":"Florist",
            "type":"Retail Goods"
        }
    ],
    "sg:phone":"+32 85 21 27 44",
    "sg:postcode":"4500",
    "sg:province":"Li\u00e8ge",
    "wof:name":"Javaux (maison)",
    "wof:placetype":"venue"
},
  "geometry": {"coordinates":[5.2378978729,50.5160827637],"type":"Point"}
}