{
  "type": "Feature",
  "properties": {
    "iso:country":"BE",
    "sg:address":"Rue Neuve 34",
    "sg:city":"Kelmis/la Calamine",
    "sg:orig_category":"Services pour animaux domestiques",
    "sg:phone":"+32 87 63 00 49",
    "sg:postcode":"4720",
    "sg:province":"Li\u00e8ge",
    "wof:name":"Dog Saloon",
    "wof:placetype":"venue"
},
  "geometry": {"coordinates":[6.0060319901,50.7137413025],"type":"Point"}
}