{
  "type": "Feature",
  "properties": {
    "iso:country":"BE",
    "sg:address":"Smissestraat 15bb",
    "sg:city":"Avelgem",
    "sg:classifiers":[
        {
            "category":"Professional",
            "type":"Services"
        }
    ],
    "sg:phone":"+32 56 64 83 43",
    "sg:postcode":"8582",
    "sg:province":"West-Vlaanderen",
    "sg:tags":[
        "aux",
        "diver",
        "personnes"
    ],
    "wof:name":"Geert Vandendriessche",
    "wof:placetype":"venue"
},
  "geometry": {"coordinates":[3.4248259068,50.7568893433],"type":"Point"}
}