{
  "type": "Feature",
  "properties": {
    "addr:full":"Bosstraat 12 Hasselt Limburg 3500",
    "addr:housenumber":"12",
    "addr:postcode":"3500",
    "addr:street":"Bosstraat",
    "iso:country":"BE",
    "sg:address":"Bosstraat 12",
    "sg:city":"Hasselt",
    "sg:classifiers":[
        {
            "category":"Real Estate",
            "subcategory":"Architect",
            "type":"Services"
        }
    ],
    "sg:phone":"+32 11 26 15 68",
    "sg:postcode":"3500",
    "sg:province":"Limburg",
    "wof:name":"Kaye K",
    "wof:placetype":"venue"
},
  "geometry": {"coordinates":[5.3511629105,50.9298019409],"type":"Point"}
}