{
  "type": "Feature",
  "properties": {
    "addr:full":"Avenue Du Couronnement 9 Bruxelles (woluwe-saint-lambert) Bruxelles-Capitale 1200",
    "addr:housenumber":"9",
    "addr:postcode":"1200",
    "addr:street":"Avenue Du Couronnement",
    "iso:country":"BE",
    "sg:address":"Avenue Du Couronnement 9",
    "sg:city":"Bruxelles (woluwe-saint-lambert)",
    "sg:classifiers":[
        {
            "category":"Professional",
            "subcategory":"Accounting & Tax Preparation",
            "type":"Services"
        }
    ],
    "sg:phone":"+32 2 772 52 79",
    "sg:postcode":"1200",
    "sg:province":"Bruxelles-Capitale",
    "sg:tags":[
        "bookkeeper"
    ],
    "wof:name":"Binon M",
    "wof:placetype":"venue"
},
  "geometry": {"coordinates":[4.4172830582,50.84324646],"type":"Point"}
}