{
  "type": "Feature",
  "properties": {
    "iso:country":"BE",
    "sg:address":"Meersblomme 23",
    "sg:city":"Waregem",
    "sg:orig_category":"Kapsalons",
    "sg:phone":"+32 56 60 32 56",
    "sg:postcode":"8790",
    "sg:province":"West-Vlaanderen",
    "wof:name":"Mon-r\u00cave",
    "wof:placetype":"venue"
},
  "geometry": {"coordinates":[3.4463329315,50.8874855042],"type":"Point"}
}