{
  "type": "Feature",
  "properties": {
    "addr:full":"Rue Marie-th\u00e9r\u00e8se 87 Bruxelles (saint-josse-ten-noode) Bruxelles-Capitale 1210",
    "addr:housenumber":"87",
    "addr:postcode":"1210",
    "addr:street":"Rue Marie-The\u0301Re\u0300Se",
    "iso:country":"BE",
    "sg:address":"Rue Marie-th\u00e9r\u00e8se 87",
    "sg:city":"Bruxelles (saint-josse-ten-noode)",
    "sg:classifiers":[
        {
            "category":"Organizations",
            "subcategory":"Community Association",
            "type":"Services"
        }
    ],
    "sg:phone":"+32 2 280 64 23",
    "sg:postcode":"1210",
    "sg:province":"Bruxelles-Capitale",
    "sg:tags":[
        "cultural"
    ],
    "wof:name":"Aves Asbl",
    "wof:placetype":"venue"
},
  "geometry": {"coordinates":[4.3730978966,50.84923172],"type":"Point"}
}