{
  "type": "Feature",
  "properties": {
    "addr:full":"Mechelsesteenweg 40 Mortsel Antwerpen 2640",
    "addr:housenumber":"40",
    "addr:postcode":"2640",
    "addr:street":"Mechelsesteenweg",
    "iso:country":"BE",
    "sg:address":"Mechelsesteenweg 40",
    "sg:city":"Mortsel",
    "sg:orig_category":"Advocaten and juridische adviseurs",
    "sg:phone":"+32 3 440 24 92",
    "sg:postcode":"2640",
    "sg:province":"Antwerpen",
    "wof:name":"Marie-jos\u00c9e Van Nueten",
    "wof:placetype":"venue"
},
  "geometry": {"coordinates":[4.4508018494,51.1688575745],"type":"Point"}
}