{
  "type": "Feature",
  "properties": {
    "addr:full":"Kolonel Dusartplein 31 Hasselt Limburg 3500",
    "addr:housenumber":"31",
    "addr:postcode":"3500",
    "addr:street":"Kolonel Dusartplein",
    "iso:country":"BE",
    "sg:address":"Kolonel Dusartplein 31",
    "sg:city":"Hasselt",
    "sg:classifiers":[
        {
            "category":"Professional",
            "subcategory":"Art Services",
            "type":"Services"
        }
    ],
    "sg:phone":"+32 11 24 27 17",
    "sg:postcode":"3500",
    "sg:province":"Limburg",
    "sg:tags":[
        "interior",
        "designer"
    ],
    "wof:name":"Valeska Interieurarchitecte",
    "wof:placetype":"venue"
},
  "geometry": {"coordinates":[5.3448438644,50.931728363],"type":"Point"}
}