{
  "type": "Feature",
  "properties": {
    "iso:country":"BE",
    "sg:address":"Rue De Rouillon 34",
    "sg:city":"Anhee",
    "sg:orig_category":"Postkantoren Verzekeringsmakelaars and experts",
    "sg:phone":"+32 71 79 93 16",
    "sg:postcode":"5537",
    "sg:province":"Namur",
    "wof:name":"La Poste",
    "wof:placetype":"venue"
},
  "geometry": {"coordinates":[4.8065109253,50.3351173401],"type":"Point"}
}