{
  "type": "Feature",
  "properties": {
    "iso:country":"BE",
    "sg:address":"Chauss\u00c9e De Vleurgat 181",
    "sg:city":"Elsene/ixelles",
    "sg:orig_category":"Organisations religieuses and philosophiques",
    "sg:phone":"+32 2 649 02 19",
    "sg:postcode":"1050",
    "sg:province":"Bruxelles-Capitale",
    "wof:name":"St. Andrews Presbyterian Church Of Schotland",
    "wof:placetype":"venue"
},
  "geometry": {"coordinates":[4.3667302132,50.8220481873],"type":"Point"}
}