{
  "type": "Feature",
  "properties": {
    "addr:full":"Dorpsstraat 51 Opglabbeek Limburg 3660",
    "addr:housenumber":"51",
    "addr:postcode":"3660",
    "addr:street":"Dorpsstraat",
    "iso:country":"BE",
    "sg:address":"Dorpsstraat 51",
    "sg:city":"Opglabbeek",
    "sg:classifiers":[
        {
            "category":"Bars & Pubs",
            "type":"Food & Drink"
        }
    ],
    "sg:phone":"+32 89 85 33 49",
    "sg:postcode":"3660",
    "sg:province":"Limburg",
    "wof:name":"Gildenhuis",
    "wof:placetype":"venue"
},
  "geometry": {"coordinates":[5.5848908424,51.0459976196],"type":"Point"}
}