{
  "type": "Feature",
  "properties": {
    "addr:full":"Valleistraat 33 Ninove (meerbeke) Oost-Vlaanderen 9402",
    "addr:housenumber":"33",
    "addr:postcode":"9402",
    "addr:street":"Valleistraat",
    "iso:country":"BE",
    "sg:address":"Valleistraat 33",
    "sg:city":"Ninove (meerbeke)",
    "sg:classifiers":[
        {
            "category":"Home & Garden",
            "subcategory":"Carpets & Floor Coverings",
            "type":"Retail Goods"
        }
    ],
    "sg:phone":"+32 54 33 59 30",
    "sg:postcode":"9402",
    "sg:province":"Oost-Vlaanderen",
    "sg:tags":[
        "layer",
        "mosaicists"
    ],
    "wof:name":"Villers G",
    "wof:placetype":"venue"
},
  "geometry": {"coordinates":[4.0437631607,50.8167533875],"type":"Point"}
}