{
  "type": "Feature",
  "properties": {
    "addr:full":"Rue De Baume 1 Box 2 La Louvi\u00e8re (haine-saint-pierre) Hainaut 7100",
    "addr:housenumber":"1;2",
    "addr:postcode":"7100",
    "addr:street":"Rue De Baume;Box",
    "iso:country":"BE",
    "sg:address":"Rue De Baume 1 Box 2",
    "sg:city":"La Louvi\u00e8re (haine-saint-pierre)",
    "sg:classifiers":[
        {
            "category":"Home & Garden",
            "subcategory":"Building Materials",
            "type":"Retail Goods"
        }
    ],
    "sg:phone":"+32 64 55 55 70",
    "sg:postcode":"7100",
    "sg:province":"Hainaut",
    "sg:tags":[
        "aluminium",
        "construction",
        "-"
    ],
    "wof:name":"T.t.f. Sprl",
    "wof:placetype":"venue"
},
  "geometry": {"coordinates":[4.1994800568,50.4748916626],"type":"Point"}
}