{
  "type": "Feature",
  "properties": {
    "addr:full":"Rue De L\u00b4orme 44 Bruxelles Bruxelles-Capitale 1030",
    "addr:housenumber":"44",
    "addr:postcode":"1030",
    "addr:street":"Rue De L\u00b4Orme",
    "iso:country":"BE",
    "sg:address":"Rue De L\u00b4orme 44",
    "sg:city":"Bruxelles",
    "sg:orig_category":"Dranken",
    "sg:phone":"+32 2 736 13 06",
    "sg:postcode":"1030",
    "sg:province":"Bruxelles-Capitale",
    "wof:name":"Ser-vin",
    "wof:placetype":"venue"
},
  "geometry": {"coordinates":[4.3975138664,50.8442268372],"type":"Point"}
}