{
  "type": "Feature",
  "properties": {
    "addr:full":"Fok 48 Sint-amands Antwerpen 2890",
    "addr:housenumber":"48",
    "addr:postcode":"2890",
    "addr:street":"Fok",
    "iso:country":"BE",
    "sg:address":"Fok 48",
    "sg:city":"Sint-amands",
    "sg:orig_category":"Fabrication and montage de mobilier. Meubles D\u00e9taillants, Am\u00e9nagement de B\u00e2timents et de Cuisines",
    "sg:phone":"+32 52 33 33 17",
    "sg:postcode":"2890",
    "sg:province":"Antwerpen",
    "wof:name":"Keukens Segers",
    "wof:placetype":"venue"
},
  "geometry": {"coordinates":[4.2127828598,51.0394439697],"type":"Point"}
}