{
  "type": "Feature",
  "properties": {
    "iso:country":"BE",
    "sg:address":"Zangstraat 4",
    "sg:city":"Wellen",
    "sg:orig_category":"Kapsalons",
    "sg:phone":"+32 12 74 73 74",
    "sg:postcode":"3830",
    "sg:province":"Limburg",
    "wof:name":"Coiffure A",
    "wof:placetype":"venue"
},
  "geometry": {"coordinates":[5.3522372246,50.8343048096],"type":"Point"}
}