{
  "type": "Feature",
  "properties": {
    "addr:full":"Rue Saint-nicolas 35 Bruxelles Bruxelles-Capitale 1120",
    "addr:housenumber":"35",
    "addr:postcode":"1120",
    "addr:street":"Rue Saint-Nicolas",
    "iso:country":"BE",
    "sg:address":"Rue Saint-nicolas 35",
    "sg:city":"Bruxelles",
    "sg:classifiers":[
        {
            "category":"Professional",
            "subcategory":"Accounting & Tax Preparation",
            "type":"Services"
        }
    ],
    "sg:phone":"+32 2 268 06 47",
    "sg:postcode":"1120",
    "sg:province":"Bruxelles-Capitale",
    "sg:tags":[
        "bookkeeper"
    ],
    "wof:name":"Hauwaert M",
    "wof:placetype":"venue"
},
  "geometry": {"coordinates":[4.3842282295,50.8930549622],"type":"Point"}
}