{
  "type": "Feature",
  "properties": {
    "addr:full":"Boulevard Charles Van Pee 2 Nijvel Brabant Wallon 1400",
    "addr:housenumber":"2",
    "addr:postcode":"1400",
    "addr:street":"Boulevard Charles Van Pee;Brabant Wallon",
    "iso:country":"BE",
    "sg:address":"Boulevard Charles Van Pee 2",
    "sg:city":"Nijvel",
    "sg:orig_category":"Autoverhuur",
    "sg:phone":"+32 67 84 26 39",
    "sg:postcode":"1400",
    "sg:province":"Brabant Wallon",
    "wof:name":"Hertz",
    "wof:placetype":"venue"
},
  "geometry": {"coordinates":[4.3283939362,50.5974464417],"type":"Point"}
}