{
  "type": "Feature",
  "properties": {
    "iso:country":"BE",
    "sg:address":"Hoveniersstraat 96",
    "sg:city":"Gent",
    "sg:classifiers":[
        {
            "category":"Fast Food",
            "type":"Food & Drink"
        }
    ],
    "sg:phone":"+32 9 231 67 77",
    "sg:postcode":"9050",
    "sg:province":"Oost-Vlaanderen",
    "sg:tags":[
        "\u00c0",
        "restaurants",
        "emporter",
        "restaurant"
    ],
    "wof:name":"De Gelaarsde Kat",
    "wof:placetype":"venue"
},
  "geometry": {"coordinates":[3.7480700016,51.0377578735],"type":"Point"}
}