{
  "type": "Feature",
  "properties": {
    "addr:full":"Chauss\u00c9e De Boondael 6 Elsene/ixelles Bruxelles-Capitale 1050",
    "addr:housenumber":"6",
    "addr:postcode":"1050",
    "addr:street":"Chausse\u0301E De Boondael",
    "iso:country":"BE",
    "sg:address":"Chauss\u00c9e De Boondael 6",
    "sg:city":"Elsene/ixelles",
    "sg:orig_category":"Secr\u00e9tariats",
    "sg:phone":"+32 2 649 91 61",
    "sg:postcode":"1050",
    "sg:province":"Bruxelles-Capitale",
    "wof:name":"A3-a4",
    "wof:placetype":"venue"
},
  "geometry": {"coordinates":[4.37414217,50.8274841309],"type":"Point"}
}