{
  "type": "Feature",
  "properties": {
    "addr:full":"Bruggesteenweg 86 Middelkerke West-Vlaanderen 8433",
    "addr:housenumber":"86",
    "addr:postcode":"8433",
    "addr:street":"Bruggesteenweg",
    "iso:country":"BE",
    "sg:address":"Bruggesteenweg 86",
    "sg:city":"Middelkerke",
    "sg:orig_category":"Rundveehouders",
    "sg:phone":"+32 58 23 43 12",
    "sg:postcode":"8433",
    "sg:province":"West-Vlaanderen",
    "wof:name":"Antoon D'hoore",
    "wof:placetype":"venue"
},
  "geometry": {"coordinates":[2.8457300663,51.1217842102],"type":"Point"}
}