{
  "type": "Feature",
  "properties": {
    "iso:country":"BE",
    "sg:address":"Rue Pont D'amour 4",
    "sg:city":"Dinant",
    "sg:orig_category":"Non-Classified Establishments",
    "sg:phone":"+32 82 22 48 92",
    "sg:postcode":"5500",
    "sg:province":"Namur",
    "wof:name":"Salaisons Du Pont D'amour",
    "wof:placetype":"venue"
},
  "geometry": {"coordinates":[4.9233469963,50.2660217285],"type":"Point"}
}