{
  "type": "Feature",
  "properties": {
    "iso:country":"BE",
    "sg:address":"Beuntstraat 21",
    "sg:city":"Duffel",
    "sg:classifiers":[
        {
            "category":"Cafe",
            "type":"Food & Drink"
        }
    ],
    "sg:phone":"+32 15 31 53 47",
    "sg:postcode":"2570",
    "sg:province":"Antwerpen",
    "sg:tags":[
        "caf\u00e9s"
    ],
    "wof:name":"Alfred Stevens",
    "wof:placetype":"venue"
},
  "geometry": {"coordinates":[4.5069069862,51.1026115417],"type":"Point"}
}