{
  "type": "Feature",
  "properties": {
    "addr:full":"Rue Du Mouton-blanc 7 Li\u00e8ge 1 Li\u00e8ge 4000",
    "addr:housenumber":"7;1",
    "addr:postcode":"4000",
    "addr:street":"Rue Du Mouton-Blanc",
    "iso:country":"BE",
    "sg:address":"Rue Du Mouton-blanc 7",
    "sg:city":"Li\u00e8ge 1",
    "sg:classifiers":[
        {
            "category":"Professional",
            "subcategory":"Testing Lab",
            "type":"Services"
        }
    ],
    "sg:phone":"+32 4 223 00 97",
    "sg:postcode":"4000",
    "sg:province":"Li\u00e8ge",
    "sg:tags":[
        "chemist"
    ],
    "wof:name":"Nysten J",
    "wof:placetype":"venue"
},
  "geometry": {"coordinates":[5.5703420639,50.6415596008],"type":"Point"}
}