{
  "type": "Feature",
  "properties": {
    "iso:country":"BE",
    "sg:address":"Av De La M\u00e9trologie",
    "sg:city":"Bruxelles",
    "sg:classifiers":[
        {
            "category":"Food Court",
            "type":"Food & Drink"
        }
    ],
    "sg:phone":"+32 2 240 01 00",
    "sg:postcode":"1130",
    "sg:province":"Bruxelles-Capitale",
    "sg:tags":[
        "product",
        "related"
    ],
    "wof:name":"Marques De Champagne Et De Spiritueux Scrl (mcs)",
    "wof:placetype":"venue"
},
  "geometry": {"coordinates":[4.4281778336,50.8940391541],"type":"Point"}
}