{
  "type": "Feature",
  "properties": {
    "addr:full":"Herkkantstraat 47 Herk-de-stad Limburg 3540",
    "addr:housenumber":"47",
    "addr:postcode":"3540",
    "addr:street":"Herkkantstraat",
    "iso:country":"BE",
    "sg:address":"Herkkantstraat 47",
    "sg:city":"Herk-de-stad",
    "sg:orig_category":"Groententeelt",
    "sg:phone":"+32 13 55 16 84",
    "sg:postcode":"3540",
    "sg:province":"Limburg",
    "wof:name":"Antonius Lavrijsen",
    "wof:placetype":"venue"
},
  "geometry": {"coordinates":[5.1659698486,50.9407691956],"type":"Point"}
}