{
  "type": "Feature",
  "properties": {
    "iso:country":"BE",
    "sg:address":"Henri Debrabanderestraat 13",
    "sg:city":"Wevelgem",
    "sg:orig_category":"Schoonheidssalons",
    "sg:phone":"+32 56 51 06 60",
    "sg:postcode":"8560",
    "sg:province":"West-Vlaanderen",
    "wof:name":"Instituut Christel",
    "wof:placetype":"venue"
},
  "geometry": {"coordinates":[3.1490209103,50.8024711609],"type":"Point"}
}