{
  "type": "Feature",
  "properties": {
    "iso:country":"BE",
    "sg:address":"Rue Des D\u00b4joyeux Wallons 38",
    "sg:city":"Seraing",
    "sg:orig_category":"Architectes",
    "sg:phone":"+32 4 338 25 61",
    "sg:postcode":"4100",
    "sg:province":"Li\u00e8ge",
    "wof:name":"Caroline Ovaere",
    "wof:placetype":"venue"
},
  "geometry": {"coordinates":[5.5504250526,50.5624084473],"type":"Point"}
}