{
  "type": "Feature",
  "properties": {
    "iso:country":"BE",
    "sg:address":"Bilzerweg 15",
    "sg:city":"Genk",
    "sg:classifiers":[
        {
            "category":"Utilities",
            "subcategory":"Fuel Oil & Lpg",
            "type":"Services"
        }
    ],
    "sg:phone":"+32 89 61 30 31",
    "sg:postcode":"3600",
    "sg:province":"Limburg",
    "wof:name":"Intercoal Nv",
    "wof:placetype":"venue"
},
  "geometry": {"coordinates":[5.5275950432,50.9221191406],"type":"Point"}
}