{
  "type": "Feature",
  "properties": {
    "iso:country":"BE",
    "sg:address":"Quellinstraat 25",
    "sg:city":"Antwerpen",
    "sg:classifiers":[
        {
            "category":"Personal",
            "subcategory":"Beauty Salon",
            "type":"Services"
        }
    ],
    "sg:phone":"+32 3 233 80 02",
    "sg:postcode":"2018",
    "sg:province":"Antwerpen",
    "sg:tags":[
        "de",
        "coiffure"
    ],
    "wof:name":"Hairdesign",
    "wof:placetype":"venue"
},
  "geometry": {"coordinates":[4.4164209366,51.2163276672],"type":"Point"}
}