{
  "type": "Feature",
  "properties": {
    "iso:country":"BE",
    "sg:address":"Rue Fril\u00c9e 22",
    "sg:city":"Binche",
    "sg:orig_category":"Verlichting and huishoudartikelen",
    "sg:phone":"+32 64 36 69 67",
    "sg:postcode":"7131",
    "sg:province":"Hainaut",
    "wof:name":"Mortier",
    "wof:placetype":"venue"
},
  "geometry": {"coordinates":[4.1615400314,50.403881073],"type":"Point"}
}