{
  "type": "Feature",
  "properties": {
    "iso:country":"BE",
    "sg:address":"Wielewaallaan 18",
    "sg:city":"Sint-pieters-woluwe/woluwe-saint-pierre",
    "sg:orig_category":"Medische apparatuur, orthopedische artikelen and prothesen Fab",
    "sg:phone":"+32 2 672 45 91",
    "sg:postcode":"1150",
    "sg:province":"Bruxelles-Capitale",
    "wof:name":"Robert Nils",
    "wof:placetype":"venue"
},
  "geometry": {"coordinates":[4.4179959297,50.8220939636],"type":"Point"}
}