{
  "type": "Feature",
  "properties": {
    "addr:full":"Londerzeelseweg 30 Kapelle-op-den-bos (ramsdonk) Vlaams-Brabant 1880",
    "addr:housenumber":"30",
    "addr:postcode":"1880",
    "addr:street":"Londerzeelseweg",
    "iso:country":"BE",
    "sg:address":"Londerzeelseweg 30",
    "sg:city":"Kapelle-op-den-bos (ramsdonk)",
    "sg:classifiers":[
        {
            "category":"Food & Beverages",
            "subcategory":"Groceries & Convenience Stores",
            "type":"Retail Goods"
        }
    ],
    "sg:phone":"+32 15 27 61 33",
    "sg:postcode":"1880",
    "sg:province":"Vlaams-Brabant",
    "sg:tags":[
        "grocer"
    ],
    "wof:name":"Okay-ramsdonk",
    "wof:placetype":"venue"
},
  "geometry": {"coordinates":[4.3478899002,51.0139808655],"type":"Point"}
}