{
  "type": "Feature",
  "properties": {
    "iso:country":"BE",
    "sg:address":"Groot Burkelkalseide 1",
    "sg:city":"Maldegem",
    "sg:orig_category":"Fleurs and plantes. Articles de jardin",
    "sg:phone":"+32 50 71 11 89",
    "sg:postcode":"9990",
    "sg:province":"Oost-Vlaanderen",
    "wof:name":"De Andere Tuin",
    "wof:placetype":"venue"
},
  "geometry": {"coordinates":[3.4135930538,51.1686973572],"type":"Point"}
}