{
  "type": "Feature",
  "properties": {
    "addr:full":"Honvelez 1 Gouvy Luxembourg 6671",
    "addr:housenumber":"1",
    "addr:postcode":"6671",
    "addr:street":"Honvelez",
    "iso:country":"BE",
    "sg:address":"Honvelez 1",
    "sg:city":"Gouvy",
    "sg:classifiers":[
        {
            "category":"Autos & Motor Vehicles",
            "subcategory":"Fuel & Gas Station",
            "type":"Retail Goods"
        }
    ],
    "sg:phone":"+32 80 21 44 66",
    "sg:postcode":"6671",
    "sg:province":"Luxembourg",
    "sg:tags":[
        "stations-service",
        "carburants"
    ],
    "wof:name":"Lommers Francis",
    "wof:placetype":"venue"
},
  "geometry": {"coordinates":[5.9206929207,50.2257118225],"type":"Point"}
}