{
  "type": "Feature",
  "properties": {
    "addr:full":"Rue Lintermans 20 Seneffe Hainaut 7180",
    "addr:housenumber":"20",
    "addr:postcode":"7180",
    "addr:street":"Rue Lintermans",
    "iso:country":"BE",
    "sg:address":"Rue Lintermans 20",
    "sg:city":"Seneffe",
    "sg:orig_category":"RESTAURANTS: CAF\u00c9S. SALLES DE CONF\u00c9RENCES AND DE R\u00c9CEPTIONS",
    "sg:phone":"+32 64 54 13 87",
    "sg:postcode":"7180",
    "sg:province":"Hainaut",
    "wof:name":"La Fontaine",
    "wof:placetype":"venue"
},
  "geometry": {"coordinates":[4.2571120262,50.5298576355],"type":"Point"}
}