{
  "type": "Feature",
  "properties": {
    "iso:country":"BE",
    "sg:address":"Rue Des Communes 39",
    "sg:city":"Courcelles",
    "sg:orig_category":"Epiceries",
    "sg:phone":"+32 64 55 63 50",
    "sg:postcode":"6181",
    "sg:province":"Hainaut",
    "wof:name":"Francine Bernard",
    "wof:placetype":"venue"
},
  "geometry": {"coordinates":[4.2989292145,50.5036430359],"type":"Point"}
}