{
  "type": "Feature",
  "properties": {
    "iso:country":"BE",
    "sg:address":"Rue De Wiltz 17",
    "sg:city":"Bastogne",
    "sg:orig_category":"Transports terrestres de voyageurs",
    "sg:phone":"+32 61 21 65 22",
    "sg:postcode":"6600",
    "sg:province":"Luxembourg",
    "wof:name":"Transports Lambin",
    "wof:placetype":"venue"
},
  "geometry": {"coordinates":[5.7327871323,49.9936637878],"type":"Point"}
}