{
  "type": "Feature",
  "properties": {
    "addr:full":"Wenenstraat 6 Meer Antwerpen 2321",
    "addr:housenumber":"6",
    "addr:postcode":"2321",
    "addr:street":"Wenenstraat",
    "iso:country":"BE",
    "sg:address":"Wenenstraat 6",
    "sg:city":"Meer",
    "sg:classifiers":[
        {
            "category":"Farming",
            "subcategory":"Crops",
            "type":"Manufacturing & Wholesale Goods"
        }
    ],
    "sg:phone":"+32 3 315 07 73",
    "sg:postcode":"2321",
    "sg:province":"Antwerpen",
    "sg:tags":[
        "vegetable",
        "fruit",
        "agriculture",
        "livestock"
    ],
    "wof:name":"Special Fruit Nv",
    "wof:placetype":"venue"
},
  "geometry": {"coordinates":[4.726544857,51.4725532532],"type":"Point"}
}