{
  "type": "Feature",
  "properties": {
    "addr:full":"Rue Des Aises 1 Charleroi Hainaut 6060",
    "addr:housenumber":"1",
    "addr:postcode":"6060",
    "addr:street":"Rue Des Aises;Hainaut",
    "iso:country":"BE",
    "sg:address":"Rue Des Aises 1",
    "sg:city":"Charleroi",
    "sg:orig_category":"Epiceries",
    "sg:phone":"+32 71 41 95 81",
    "sg:postcode":"6060",
    "sg:province":"Hainaut",
    "wof:name":"Delhaize",
    "wof:placetype":"venue"
},
  "geometry": {"coordinates":[4.4880981445,50.4251937866],"type":"Point"}
}