{
  "type": "Feature",
  "properties": {
    "iso:country":"BE",
    "sg:address":"Cornelis De Herdtstraat 10",
    "sg:city":"Mortsel",
    "sg:orig_category":"Paramedische behandelingen",
    "sg:phone":"+32 3 449 28 23",
    "sg:postcode":"2640",
    "sg:province":"Antwerpen",
    "wof:name":"A. Schaubroeck",
    "wof:placetype":"venue"
},
  "geometry": {"coordinates":[4.4465742111,51.1650695801],"type":"Point"}
}