{
  "type": "Feature",
  "properties": {
    "addr:full":"Drieselstraat 49 Gent Oost-Vlaanderen 9041",
    "addr:housenumber":"49",
    "addr:postcode":"9041",
    "addr:street":"Drieselstraat;Oost-Vlaanderen",
    "iso:country":"BE",
    "sg:address":"Drieselstraat 49",
    "sg:city":"Gent",
    "sg:orig_category":"Woningbouw",
    "sg:phone":"+32 9 226 09 02",
    "sg:postcode":"9041",
    "sg:province":"Oost-Vlaanderen",
    "wof:name":"Verstraeten Julien",
    "wof:placetype":"venue"
},
  "geometry": {"coordinates":[3.7703149319,51.1020812988],"type":"Point"}
}