{
  "type": "Feature",
  "properties": {
    "addr:full":"Brusselsesteenweg 741 Gent (gentbrugge) Oost-Vlaanderen 9050",
    "addr:housenumber":"741",
    "addr:postcode":"9050",
    "addr:street":"Brusselsesteenweg",
    "iso:country":"BE",
    "sg:address":"Brusselsesteenweg 741",
    "sg:city":"Gent (gentbrugge)",
    "sg:classifiers":[
        {
            "category":"Building & Trades",
            "subcategory":"Electrical",
            "type":"Services"
        }
    ],
    "sg:phone":"+32 9 210 89 89",
    "sg:postcode":"9050",
    "sg:province":"Oost-Vlaanderen",
    "sg:tags":[
        "-",
        "electric",
        "contractor"
    ],
    "wof:name":"Bracke-monin Nv Nv",
    "wof:placetype":"venue"
},
  "geometry": {"coordinates":[3.7681889534,51.028339386],"type":"Point"}
}