{
  "type": "Feature",
  "properties": {
    "iso:country":"BE",
    "sg:address":"Chauss\u00c9e De Bruxelles 21",
    "sg:city":"Sombreffe",
    "sg:orig_category":"Bloemen and planten",
    "sg:phone":"+32 71 88 77 08",
    "sg:postcode":"5140",
    "sg:province":"Namur",
    "wof:name":"Millefleurs",
    "wof:placetype":"venue"
},
  "geometry": {"coordinates":[4.6159057617,50.5244483948],"type":"Point"}
}