{
  "type": "Feature",
  "properties": {
    "iso:country":"BE",
    "sg:address":"Rue Saint-urbain 122bc",
    "sg:city":"Tellin",
    "sg:classifiers":[
        {
            "category":"Arena",
            "subcategory":"Sports Club",
            "type":"Entertainment"
        }
    ],
    "sg:phone":"+32 84 36 68 07",
    "sg:postcode":"6927",
    "sg:province":"Luxembourg",
    "sg:tags":[
        "terrain",
        "hors",
        "de",
        "installation",
        "sportifs"
    ],
    "wof:name":"R.u.s. Tellinoise",
    "wof:placetype":"venue"
},
  "geometry": {"coordinates":[5.2146711349,50.0820884705],"type":"Point"}
}