{
  "type": "Feature",
  "properties": {
    "addr:full":"Fonteinstraat 21 Assenede Oost-Vlaanderen 9960",
    "addr:housenumber":"21",
    "addr:postcode":"9960",
    "addr:street":"Fonteinstraat",
    "iso:country":"BE",
    "sg:address":"Fonteinstraat 21",
    "sg:city":"Assenede",
    "sg:orig_category":"HUISBRANDOLIE",
    "sg:phone":"+32 9 344 55 97",
    "sg:postcode":"9960",
    "sg:province":"Oost-Vlaanderen",
    "wof:name":"Staelens",
    "wof:placetype":"venue"
},
  "geometry": {"coordinates":[3.7451090813,51.2090263367],"type":"Point"}
}