{
  "type": "Feature",
  "properties": {
    "addr:full":"Weg Naar As 159 Genk Limburg 3600",
    "addr:housenumber":"159",
    "addr:postcode":"3600",
    "addr:street":"Weg Naar As",
    "iso:country":"BE",
    "sg:address":"Weg Naar As 159",
    "sg:city":"Genk",
    "sg:orig_category":"Bouwwerktuigen Gh Kleding Metalen and ertsen Gh Motoren, transformatoren and generatoren Fab Onderde",
    "sg:phone":"+32 89 35 35 35",
    "sg:postcode":"3600",
    "sg:province":"Limburg",
    "wof:name":"Autostuc",
    "wof:placetype":"venue"
},
  "geometry": {"coordinates":[5.5156521797,50.9723243713],"type":"Point"}
}