{
  "type": "Feature",
  "properties": {
    "addr:full":"Rue De La Campagnette 19 Walhain Brabant Wallon 1457",
    "addr:housenumber":"19;1457",
    "addr:street":"Rue De La Campagnette",
    "iso:country":"BE",
    "sg:address":"Rue De La Campagnette 19",
    "sg:city":"Walhain",
    "sg:orig_category":"Elektrische installaties voor woningen",
    "sg:phone":"+32 10 65 78 83",
    "sg:postcode":"1457",
    "sg:province":"Brabant Wallon",
    "wof:name":"Andre Misson",
    "wof:placetype":"venue"
},
  "geometry": {"coordinates":[4.6914968491,50.615562439],"type":"Point"}
}