{
  "type": "Feature",
  "properties": {
    "iso:country":"BE",
    "sg:address":"Place Verte 47",
    "sg:city":"Verviers",
    "sg:orig_category":"Agences d\u00b4interim and personnel temporaire",
    "sg:phone":"+32 87 33 03 33",
    "sg:postcode":"4800",
    "sg:province":"Li\u00e8ge",
    "wof:name":"Id\u00c9al Int\u00c9rim",
    "wof:placetype":"venue"
},
  "geometry": {"coordinates":[5.8620710373,50.5924034119],"type":"Point"}
}