{
  "type": "Feature",
  "properties": {
    "addr:full":"Marktplein 8 Wijnegem Antwerpen 2110",
    "addr:housenumber":"8",
    "addr:postcode":"2110",
    "addr:street":"Marktplein",
    "iso:country":"BE",
    "sg:address":"Marktplein 8",
    "sg:city":"Wijnegem",
    "sg:classifiers":[
        {
            "category":"Arena",
            "subcategory":"Sports Club",
            "type":"Entertainment"
        }
    ],
    "sg:phone":"+32 3 353 89 26",
    "sg:postcode":"2110",
    "sg:province":"Antwerpen",
    "sg:tags":[
        "de"
    ],
    "wof:name":"B.c. Fontes",
    "wof:placetype":"venue"
},
  "geometry": {"coordinates":[4.52312994,51.2271614075],"type":"Point"}
}