{
  "type": "Feature",
  "properties": {
    "addr:full":"Poperingseweg 18 Ieper West-Vlaanderen 8900",
    "addr:housenumber":"18",
    "addr:postcode":"8900",
    "addr:street":"Poperingseweg",
    "iso:country":"BE",
    "sg:address":"Poperingseweg 18",
    "sg:city":"Ieper",
    "sg:orig_category":"Architectes",
    "sg:phone":"+32 57 21 69 68",
    "sg:postcode":"8900",
    "sg:province":"West-Vlaanderen",
    "wof:name":"Albert Coigne",
    "wof:placetype":"venue"
},
  "geometry": {"coordinates":[2.8655838966,50.8491210938],"type":"Point"}
}