{
  "type": "Feature",
  "properties": {
    "iso:country":"BE",
    "sg:address":"Rue Du Croiseau 153",
    "sg:city":"Ittre",
    "sg:orig_category":"Epiceries",
    "sg:phone":"+32 67 64 71 09",
    "sg:postcode":"1460",
    "sg:province":"Brabant Wallon",
    "wof:name":"Christian Delestienne",
    "wof:placetype":"venue"
},
  "geometry": {"coordinates":[4.2536392212,50.6352005005],"type":"Point"}
}