{
  "type": "Feature",
  "properties": {
    "iso:country":"BE",
    "sg:address":"Ingberthoeveweg 3g",
    "sg:city":"Aartselaar",
    "sg:classifiers":[
        {
            "category":"Military Area",
            "subcategory":"Air Force Base",
            "type":"Public Place"
        }
    ],
    "sg:phone":"+32 3 829 00 99",
    "sg:postcode":"2630",
    "sg:province":"Antwerpen",
    "sg:tags":[
        "fire",
        "protection"
    ],
    "wof:name":"Ajax Fire Protection Systems Bv",
    "wof:placetype":"venue"
},
  "geometry": {"coordinates":[4.3969092369,51.1482505798],"type":"Point"}
}