{
  "type": "Feature",
  "properties": {
    "iso:country":"BE",
    "sg:address":"Rue Mogn\u00c9e 21",
    "sg:city":"Ouffet",
    "sg:orig_category":"Algemeen secundair onderwijs Technisch and beroeps secundair onderwijs",
    "sg:phone":"+32 86 36 62 77",
    "sg:postcode":"4590",
    "sg:province":"Li\u00e8ge",
    "wof:name":"Ath\u00c9n\u00c9e Royal",
    "wof:placetype":"venue"
},
  "geometry": {"coordinates":[5.4665150642,50.4413528442],"type":"Point"}
}