{
  "type": "Feature",
  "properties": {
    "addr:full":"Avenue Lat\u00c9rale 21 Uccle Bruxelles-Capitale 1180",
    "addr:housenumber":"21",
    "addr:postcode":"1180",
    "addr:street":"Avenue Late\u0301Rale",
    "iso:country":"BE",
    "sg:address":"Avenue Lat\u00c9rale 21",
    "sg:city":"Uccle",
    "sg:orig_category":"Verlichting and huishoudartikelen",
    "sg:phone":"+32 2 374 89 47",
    "sg:postcode":"1180",
    "sg:province":"Bruxelles-Capitale",
    "wof:name":"Weemaels",
    "wof:placetype":"venue"
},
  "geometry": {"coordinates":[4.3723378181,50.7964897156],"type":"Point"}
}