{
  "type": "Feature",
  "properties": {
    "addr:full":"Rue Heideken 5 Bruxelles (ganshoren) Bruxelles-Capitale 1083",
    "addr:housenumber":"5",
    "addr:postcode":"1083",
    "addr:street":"Rue Heideken",
    "iso:country":"BE",
    "sg:address":"Rue Heideken 5",
    "sg:city":"Bruxelles (ganshoren)",
    "sg:classifiers":[
        {
            "category":"Professional",
            "subcategory":"Management & Consulting",
            "type":"Services"
        }
    ],
    "sg:phone":"+32 2 426 45 55",
    "sg:postcode":"1083",
    "sg:province":"Bruxelles-Capitale",
    "sg:tags":[
        "consultant"
    ],
    "wof:name":"R\u00e9sorce Sprl",
    "wof:placetype":"venue"
},
  "geometry": {"coordinates":[4.320748806,50.8745613098],"type":"Point"}
}