{
  "type": "Feature",
  "properties": {
    "addr:full":"Rue Raymond 6 Verviers Li\u00e8ge 4800",
    "addr:housenumber":"6",
    "addr:postcode":"4800",
    "addr:street":"Rue Raymond",
    "iso:country":"BE",
    "sg:address":"Rue Raymond 6",
    "sg:city":"Verviers",
    "sg:orig_category":"Dakwerken",
    "sg:phone":"+32 87 33 78 22",
    "sg:postcode":"4800",
    "sg:province":"Li\u00e8ge",
    "wof:name":"Ga\u00cbtano Mazza",
    "wof:placetype":"venue"
},
  "geometry": {"coordinates":[5.8720707893,50.5971794128],"type":"Point"}
}