{
  "type": "Feature",
  "properties": {
    "addr:full":"Industrieterrein Schurhovenveld 4 2326 Sint-truiden Limburg 3800",
    "addr:housenumber":"4",
    "addr:postcode":"2326 sint-truiden;3800",
    "addr:street":"Industrieterrein Schurhovenveld",
    "iso:country":"BE",
    "sg:address":"Industrieterrein Schurhovenveld 4 2326",
    "sg:city":"Sint-truiden",
    "sg:classifiers":[
        {
            "category":"Retail",
            "subcategory":"Auto Repair",
            "type":"Services"
        }
    ],
    "sg:phone":"+32 11 68 27 36",
    "sg:postcode":"3800",
    "sg:province":"Limburg",
    "sg:tags":[
        "automobile-body"
    ],
    "wof:name":"Dirix Nv",
    "wof:placetype":"venue"
},
  "geometry": {"coordinates":[5.2026247978,50.8207054138],"type":"Point"}
}