{
  "type": "Feature",
  "properties": {
    "addr:full":"Tongerlodorp 26a Westerlo (tongerlo) Antwerpen 2260",
    "addr:housenumber":"26a",
    "addr:postcode":"2260",
    "addr:street":"Tongerlodorp",
    "iso:country":"BE",
    "sg:address":"Tongerlodorp 26a",
    "sg:city":"Westerlo (tongerlo)",
    "sg:classifiers":[
        {
            "category":"Health Services",
            "subcategory":"Nursing And Care Facility",
            "type":"Services"
        }
    ],
    "sg:phone":"+32 3 312 87 87",
    "sg:postcode":"2260",
    "sg:province":"Antwerpen",
    "sg:tags":[
        "home"
    ],
    "wof:name":"Landelijke Thuiszorg",
    "wof:placetype":"venue"
},
  "geometry": {"coordinates":[4.9152059555,51.1071624756],"type":"Point"}
}