{
  "type": "Feature",
  "properties": {
    "iso:country":"BE",
    "sg:address":"Europastraat 58",
    "sg:city":"Boom",
    "sg:classifiers":[
        {
            "category":"Shopping Center",
            "type":"Public Place"
        }
    ],
    "sg:phone":"+32 3 289 09 37",
    "sg:postcode":"2850",
    "sg:province":"Antwerpen",
    "sg:tags":[
        "enseignement",
        "formation"
    ],
    "wof:name":"Leonard Van Deyck",
    "wof:placetype":"venue"
},
  "geometry": {"coordinates":[4.3816361427,51.1004867554],"type":"Point"}
}