{
  "type": "Feature",
  "properties": {
    "iso:country":"BE",
    "sg:address":"Vestingstraat 16",
    "sg:city":"Antwerpen",
    "sg:classifiers":[
        {
            "category":"Shopping",
            "subcategory":"Antiques",
            "type":"Retail Goods"
        }
    ],
    "sg:phone":"+32 3 233 50 92",
    "sg:postcode":"2018",
    "sg:province":"Antwerpen",
    "wof:name":"Adin Nv",
    "wof:placetype":"venue"
},
  "geometry": {"coordinates":[4.4180459976,51.2168464661],"type":"Point"}
}