{
  "type": "Feature",
  "properties": {
    "iso:country":"BE",
    "sg:address":"Leegstraat 211a",
    "sg:city":"Zelzate",
    "sg:classifiers":[
        {
            "category":"Real Estate",
            "subcategory":"Architect",
            "type":"Services"
        }
    ],
    "sg:phone":"+32 9 342 87 15",
    "sg:postcode":"9060",
    "sg:province":"Oost-Vlaanderen",
    "wof:name":"Van Hoofstadt T",
    "wof:placetype":"venue"
},
  "geometry": {"coordinates":[3.8336040974,51.2043838501],"type":"Point"}
}