{
  "type": "Feature",
  "properties": {
    "iso:country":"BE",
    "sg:address":"Rue Du Man\u00c8ge",
    "sg:city":"Bierges",
    "sg:orig_category":"Royal Canin. Animaux domestiques and accessoires",
    "sg:phone":"+32 10 41 37 80",
    "sg:postcode":"1301",
    "sg:province":"Brabant Wallon",
    "wof:name":"Vromman",
    "wof:placetype":"venue"
},
  "geometry": {"coordinates":[4.6002669334,50.707572937],"type":"Point"}
}