{
  "type": "Feature",
  "properties": {
    "addr:full":"Rue Du Viveroux 1 Philippeville Namur 5600",
    "addr:housenumber":"1",
    "addr:postcode":"5600",
    "addr:street":"Rue Du Viveroux",
    "iso:country":"BE",
    "sg:address":"Rue Du Viveroux 1",
    "sg:city":"Philippeville",
    "sg:orig_category":"Eleveurs de bovins",
    "sg:phone":"+32 71 66 74 21",
    "sg:postcode":"5600",
    "sg:province":"Namur",
    "wof:name":"Raymond Martinet",
    "wof:placetype":"venue"
},
  "geometry": {"coordinates":[4.6242198944,50.1718673706],"type":"Point"}
}