{
  "type": "Feature",
  "properties": {
    "addr:full":"Avenue De Broqueville 283 Bruxelles (woluwe-saint-lambert) Bruxelles-Capitale 1200",
    "addr:housenumber":"283",
    "addr:postcode":"1200",
    "addr:street":"Avenue De Broqueville",
    "iso:country":"BE",
    "sg:address":"Avenue De Broqueville 283",
    "sg:city":"Bruxelles (woluwe-saint-lambert)",
    "sg:classifiers":[
        {
            "category":"Health Services",
            "subcategory":"Health Practitioner",
            "type":"Services"
        }
    ],
    "sg:phone":"+32 2 771 48 40",
    "sg:postcode":"1200",
    "sg:province":"Bruxelles-Capitale",
    "sg:tags":[
        "physiotherapist"
    ],
    "wof:name":"Maquet Philippe",
    "wof:placetype":"venue"
},
  "geometry": {"coordinates":[4.4228100777,50.8430671692],"type":"Point"}
}