{
  "type": "Feature",
  "properties": {
    "iso:country":"BE",
    "sg:address":"Vandernootstraat 22b4",
    "sg:city":"Sint-jans-molenbeek/molenbeek-saint-jean",
    "sg:orig_category":"Boekhouders",
    "sg:phone":"+32 2 420 06 97",
    "sg:postcode":"1080",
    "sg:province":"Bruxelles-Capitale",
    "wof:name":"Mohamed Ben-omar-bridi",
    "wof:placetype":"venue"
},
  "geometry": {"coordinates":[4.334939003,50.8629493713],"type":"Point"}
}