{
  "type": "Feature",
  "properties": {
    "addr:full":"Varent 4 Oudenaarde Oost-Vlaanderen 9700",
    "addr:housenumber":"4",
    "addr:postcode":"9700",
    "addr:street":"Varent",
    "iso:country":"BE",
    "sg:address":"Varent 4",
    "sg:city":"Oudenaarde",
    "sg:orig_category":"Rundveehouders",
    "sg:phone":"+32 55 45 55 64",
    "sg:postcode":"9700",
    "sg:province":"Oost-Vlaanderen",
    "wof:name":"Rene Beghin",
    "wof:placetype":"venue"
},
  "geometry": {"coordinates":[3.6728389263,50.8290901184],"type":"Point"}
}