{
  "type": "Feature",
  "properties": {
    "addr:full":"Rue D'arlon 22-24 Bruxelles (ixelles) Bruxelles-Capitale 1050",
    "addr:postcode":"22-24;1050",
    "addr:street":"Rue D'Arlon",
    "iso:country":"BE",
    "sg:address":"Rue D'arlon 22-24",
    "sg:city":"Bruxelles (ixelles)",
    "sg:classifiers":[
        {
            "category":"Organizations",
            "subcategory":"Professional Association",
            "type":"Services"
        }
    ],
    "sg:phone":"+32 2 511 74 77",
    "sg:postcode":"1050",
    "sg:province":"Bruxelles-Capitale",
    "sg:tags":[
        "trade-union",
        "federation"
    ],
    "wof:name":"Conseil Communes & Regions Eur",
    "wof:placetype":"venue"
},
  "geometry": {"coordinates":[4.3717970848,50.8390388489],"type":"Point"}
}