{
  "type": "Feature",
  "properties": {
    "addr:full":"Diestersesteenweg 176 Beringen (paal) Limburg 3583",
    "addr:housenumber":"176",
    "addr:postcode":"3583",
    "addr:street":"Diestersesteenweg",
    "iso:country":"BE",
    "sg:address":"Diestersesteenweg 176",
    "sg:city":"Beringen (paal)",
    "sg:classifiers":[
        {
            "category":"Shopping",
            "subcategory":"Event Tickets",
            "type":"Retail Goods"
        }
    ],
    "sg:phone":"+32 11 42 22 77",
    "sg:postcode":"3583",
    "sg:province":"Limburg",
    "wof:name":"Spel 21 Karmijn",
    "wof:placetype":"venue"
},
  "geometry": {"coordinates":[5.1706700325,51.0389442444],"type":"Point"}
}