{
  "type": "Feature",
  "properties": {
    "addr:full":"Rue Hubert Krains 36 Waremme Li\u00e8ge 4300",
    "addr:housenumber":"36",
    "addr:postcode":"4300",
    "addr:street":"Rue Hubert Krains",
    "iso:country":"BE",
    "sg:address":"Rue Hubert Krains 36",
    "sg:city":"Waremme",
    "sg:orig_category":"Artistes ind\u00e9pendants. Agences de publicit\u00e9",
    "sg:phone":"+32 19 33 09 61",
    "sg:postcode":"4300",
    "sg:province":"Li\u00e8ge",
    "wof:name":"Patrick Haugen",
    "wof:placetype":"venue"
},
  "geometry": {"coordinates":[5.2436380386,50.6934013367],"type":"Point"}
}