{
  "type": "Feature",
  "properties": {
    "iso:country":"BE",
    "sg:address":"Rue Vieille Porte 4",
    "sg:city":"La Roche-en-ardenne",
    "sg:classifiers":[
        {
            "category":"Professional",
            "type":"Services"
        }
    ],
    "sg:phone":"+32 84 41 17 05",
    "sg:postcode":"6980",
    "sg:province":"Luxembourg",
    "sg:tags":[
        "surveyor",
        "-",
        "valuer"
    ],
    "wof:name":"La Roche Immobili\u00e8re",
    "wof:placetype":"venue"
},
  "geometry": {"coordinates":[5.5750021935,50.1811180115],"type":"Point"}
}