{
  "type": "Feature",
  "properties": {
    "addr:full":"Paleisstraat 76 Antwerpen Antwerpen 2018",
    "addr:housenumber":"76",
    "addr:postcode":"2018",
    "addr:street":"Paleisstraat",
    "iso:country":"BE",
    "sg:address":"Paleisstraat 76",
    "sg:city":"Antwerpen",
    "sg:orig_category":"M\u00e9decins and sp\u00e9cialistes",
    "sg:phone":"+32 3 237 42 15",
    "sg:postcode":"2018",
    "sg:province":"Antwerpen",
    "wof:name":"Paul L.m.f. Ickx",
    "wof:placetype":"venue"
},
  "geometry": {"coordinates":[4.3992781639,51.2067718506],"type":"Point"}
}