{
  "type": "Feature",
  "properties": {
    "addr:full":"Leeuweriklaan 8 Ravels Antwerpen 2382",
    "addr:housenumber":"8",
    "addr:postcode":"2382",
    "addr:street":"Leeuweriklaan",
    "iso:country":"BE",
    "sg:address":"Leeuweriklaan 8",
    "sg:city":"Ravels",
    "sg:classifiers":[
        {
            "category":"Banks & Credit Unions",
            "subcategory":"Investment Brokerage",
            "type":"Services"
        }
    ],
    "sg:phone":"+32 14 65 86 08",
    "sg:postcode":"2382",
    "sg:province":"Antwerpen",
    "sg:tags":[
        "machine",
        "mat\u00e9riel",
        "de",
        "bureau",
        "gr"
    ],
    "wof:name":"Act Belgium",
    "wof:placetype":"venue"
},
  "geometry": {"coordinates":[5.041768074,51.4469108582],"type":"Point"}
}