{
  "type": "Feature",
  "properties": {
    "addr:full":"Groot Begijnhof 10 Gent (sint-amandsberg) Oost-Vlaanderen 9040",
    "addr:housenumber":"10",
    "addr:postcode":"9040",
    "addr:street":"Groot Begijnhof",
    "iso:country":"BE",
    "sg:address":"Groot Begijnhof 10",
    "sg:city":"Gent (sint-amandsberg)",
    "sg:classifiers":[
        {
            "category":"Social Services",
            "type":"Services"
        }
    ],
    "sg:phone":"+32 9 238 25 72",
    "sg:postcode":"9040",
    "sg:province":"Oost-Vlaanderen",
    "sg:tags":[
        "handicapped",
        "-"
    ],
    "wof:name":"V.m.g.",
    "wof:placetype":"venue"
},
  "geometry": {"coordinates":[3.7497830391,51.0575942993],"type":"Point"}
}