{
  "type": "Feature",
  "properties": {
    "addr:full":"Jagershoek 21 Vichte West-Vlaanderen 8570",
    "addr:housenumber":"21",
    "addr:postcode":"8570",
    "addr:street":"Jagershoek;West-Vlaanderen",
    "iso:country":"BE",
    "sg:address":"Jagershoek 21",
    "sg:city":"Vichte",
    "sg:classifiers":[
        {
            "category":"Government",
            "subcategory":"Fire Station",
            "type":"Public Place"
        }
    ],
    "sg:phone":"+32 71 35 33 84",
    "sg:postcode":"8570",
    "sg:province":"West-Vlaanderen",
    "sg:tags":[
        "brass",
        "aluminium",
        "washer"
    ],
    "wof:name":"Fabriro S.a.",
    "wof:placetype":"venue"
},
  "geometry": {"coordinates":[4.435945034,50.4440040588],"type":"Point"}
}