{
  "type": "Feature",
  "properties": {
    "iso:country":"BE",
    "sg:address":"Muizelstraat 4",
    "sg:city":"Wevelgem (moorsele)",
    "sg:classifiers":[
        {
            "category":"Manufacturing",
            "subcategory":"Textiles",
            "type":"Manufacturing & Wholesale Goods"
        }
    ],
    "sg:phone":"+32 56 42 48 55",
    "sg:postcode":"8560",
    "sg:province":"West-Vlaanderen",
    "sg:tags":[
        "polyester"
    ],
    "wof:name":"Acl",
    "wof:placetype":"venue"
},
  "geometry": {"coordinates":[3.1761128902,50.8449783325],"type":"Point"}
}