{
  "type": "Feature",
  "properties": {
    "addr:full":"Rue De Longtain 168 La Louvi\u00e8re Hainaut 7100",
    "addr:housenumber":"168",
    "addr:postcode":"7100",
    "addr:street":"Rue De Longtain",
    "iso:country":"BE",
    "sg:address":"Rue De Longtain 168",
    "sg:city":"La Louvi\u00e8re",
    "sg:classifiers":[
        {
            "category":"Autos & Motor Vehicles",
            "subcategory":"Automobile Sales",
            "type":"Retail Goods"
        }
    ],
    "sg:phone":"+32 64 22 47 34",
    "sg:postcode":"7100",
    "sg:province":"Hainaut",
    "sg:tags":[
        "car",
        "used",
        "-"
    ],
    "wof:name":"Mol C",
    "wof:placetype":"venue"
},
  "geometry": {"coordinates":[4.2082118988,50.4793777466],"type":"Point"}
}