{
  "type": "Feature",
  "properties": {
    "addr:full":"Knokstraat 3 Zwalm Oost-Vlaanderen 9630",
    "addr:housenumber":"3",
    "addr:postcode":"9630",
    "addr:street":"Knokstraat;Oost-Vlaanderen",
    "iso:country":"BE",
    "sg:address":"Knokstraat 3",
    "sg:city":"Zwalm",
    "sg:orig_category":"Charpentes and couvertures. Installation de menuiserie en bois and plastique",
    "sg:phone":"+32 55 49 55 18",
    "sg:postcode":"9630",
    "sg:province":"Oost-Vlaanderen",
    "wof:name":"Inter-immo",
    "wof:placetype":"venue"
},
  "geometry": {"coordinates":[3.6993350983,50.8728065491],"type":"Point"}
}