{
  "type": "Feature",
  "properties": {
    "iso:country":"BE",
    "sg:address":"Hoogkamerstraat 294",
    "sg:city":"Temse",
    "sg:orig_category":"Drukkerijen and copyshops",
    "sg:phone":"+32 3 710 07 70",
    "sg:postcode":"9140",
    "sg:province":"Oost-Vlaanderen",
    "wof:name":"Full-printing",
    "wof:placetype":"venue"
},
  "geometry": {"coordinates":[4.1860089302,51.1373405457],"type":"Point"}
}