{
  "type": "Feature",
  "properties": {
    "iso:country":"BE",
    "sg:address":"Drogenbroodstraat 50",
    "sg:city":"Pittem",
    "sg:orig_category":"Rundveehouders",
    "sg:phone":"+32 51 46 71 82",
    "sg:postcode":"8740",
    "sg:province":"West-Vlaanderen",
    "wof:name":"Marc Neirynck",
    "wof:placetype":"venue"
},
  "geometry": {"coordinates":[3.2563800812,51.0192108154],"type":"Point"}
}