{
  "type": "Feature",
  "properties": {
    "iso:country":"BE",
    "sg:address":"Nachtegaalstraat 20",
    "sg:city":"Peer",
    "sg:orig_category":"Schoonheidssalons",
    "sg:phone":"+32 11 63 27 92",
    "sg:postcode":"3990",
    "sg:province":"Limburg",
    "wof:name":"Odette Flipkens",
    "wof:placetype":"venue"
},
  "geometry": {"coordinates":[5.4577698708,51.1371955872],"type":"Point"}
}