{
  "type": "Feature",
  "properties": {
    "addr:full":"Emile Verhaerenlaan 20-22 Knokke-heist (knokke) West-Vlaanderen 8300",
    "addr:postcode":"20-22;8300",
    "addr:street":"Emile Verhaerenlaan",
    "iso:country":"BE",
    "sg:address":"Emile Verhaerenlaan 20-22",
    "sg:city":"Knokke-heist (knokke)",
    "sg:classifiers":[
        {
            "category":"Food & Beverages",
            "subcategory":"Fruits & Vegetables",
            "type":"Retail Goods"
        }
    ],
    "sg:phone":"+32 50 63 17 17",
    "sg:postcode":"8300",
    "sg:province":"West-Vlaanderen",
    "sg:tags":[
        "-"
    ],
    "wof:name":"Grappe De Raisins",
    "wof:placetype":"venue"
},
  "geometry": {"coordinates":[3.287694931,51.3467254639],"type":"Point"}
}