{
  "type": "Feature",
  "properties": {
    "addr:full":"Rue Du Solitaire 37 Leuze-en-hainaut Hainaut 7900",
    "addr:housenumber":"37",
    "addr:postcode":"7900",
    "addr:street":"Rue Du Solitaire",
    "iso:country":"BE",
    "sg:address":"Rue Du Solitaire 37",
    "sg:city":"Leuze-en-hainaut",
    "sg:classifiers":[
        {
            "category":"Arts & Performance",
            "subcategory":"Music",
            "type":"Entertainment"
        }
    ],
    "sg:phone":"+32 69 66 40 43",
    "sg:postcode":"7900",
    "sg:province":"Hainaut",
    "sg:tags":[
        "freelance",
        "musician"
    ],
    "wof:name":"Lurkin L",
    "wof:placetype":"venue"
},
  "geometry": {"coordinates":[3.6124389172,50.5966033936],"type":"Point"}
}