{
  "type": "Feature",
  "properties": {
    "addr:full":"Sint-jacobsmarkt 39 Antwerpen Antwerpen 2000",
    "addr:housenumber":"39",
    "addr:postcode":"2000",
    "addr:street":"Sint-Jacobsmarkt",
    "iso:country":"BE",
    "sg:address":"Sint-jacobsmarkt 39",
    "sg:city":"Antwerpen",
    "sg:classifiers":[
        {
            "category":"Organizations",
            "subcategory":"Community Association",
            "type":"Services"
        }
    ],
    "sg:phone":"+32 3 232 32 83",
    "sg:postcode":"2000",
    "sg:province":"Antwerpen",
    "sg:tags":[
        "cultural"
    ],
    "wof:name":"Bond Zonder Naam Vzw",
    "wof:placetype":"venue"
},
  "geometry": {"coordinates":[4.4124522209,51.2204055786],"type":"Point"}
}