{
  "type": "Feature",
  "properties": {
    "addr:full":"Henry Fordlaan 39 Genk Limburg 3600",
    "addr:housenumber":"39",
    "addr:postcode":"3600",
    "addr:street":"Henry Fordlaan",
    "iso:country":"BE",
    "sg:address":"Henry Fordlaan 39",
    "sg:city":"Genk",
    "sg:orig_category":"Verhuur cateringmateriaal and evenementuitrusting Winkelinrichting and handelsuitrusting Gh",
    "sg:phone":"+32 89 62 01 30",
    "sg:postcode":"3600",
    "sg:province":"Limburg",
    "wof:name":"Beneserv",
    "wof:placetype":"venue"
},
  "geometry": {"coordinates":[5.4888272285,50.9173049927],"type":"Point"}
}