{
  "type": "Feature",
  "properties": {
    "iso:country":"BE",
    "sg:address":"Heirbaan 181",
    "sg:city":"Hamme",
    "sg:orig_category":"Non-Classified Establishments",
    "sg:phone":"+32 52 47 77 05",
    "sg:postcode":"9220",
    "sg:province":"Oost-Vlaanderen",
    "wof:name":"Audenaert M",
    "wof:placetype":"venue"
},
  "geometry": {"coordinates":[4.0907459259,51.0805091858],"type":"Point"}
}