{
  "type": "Feature",
  "properties": {
    "addr:full":"Apostelhuizen 26 Gent Oost-Vlaanderen 9000",
    "addr:housenumber":"26",
    "addr:postcode":"9000",
    "addr:street":"Apostelhuizen;Oost-Vlaanderen",
    "iso:country":"BE",
    "sg:address":"Apostelhuizen 26",
    "sg:city":"Gent",
    "sg:classifiers":[
        {
            "category":"Shopping",
            "subcategory":"Stationery & Office Supplies",
            "type":"Retail Goods"
        }
    ],
    "sg:phone":"+32 9 220 80 73",
    "sg:postcode":"9000",
    "sg:province":"Oost-Vlaanderen",
    "sg:tags":[
        "fixture"
    ],
    "wof:name":"Arredo Cvba",
    "wof:placetype":"venue"
},
  "geometry": {"coordinates":[3.733987093,51.0512962341],"type":"Point"}
}