{
  "type": "Feature",
  "properties": {
    "addr:full":"Graaf Jansdijk 189 Knokke-heist West-Vlaanderen 8300",
    "addr:housenumber":"189",
    "addr:postcode":"8300",
    "addr:street":"Graaf Jansdijk",
    "iso:country":"BE",
    "sg:address":"Graaf Jansdijk 189",
    "sg:city":"Knokke-heist",
    "sg:orig_category":"Banques and organismes de cr\u00e9dit",
    "sg:phone":"+32 50 60 97 15",
    "sg:postcode":"8300",
    "sg:province":"West-Vlaanderen",
    "wof:name":"Sofibank",
    "wof:placetype":"venue"
},
  "geometry": {"coordinates":[3.3052420616,51.3387451172],"type":"Point"}
}