{
  "type": "Feature",
  "properties": {
    "iso:country":"BE",
    "sg:address":"Ieperstraat 160",
    "sg:city":"Poperinge",
    "sg:classifiers":[
        {
            "category":"Food & Beverages",
            "subcategory":"Fruits & Vegetables",
            "type":"Retail Goods"
        }
    ],
    "sg:phone":"+32 57 33 79 35",
    "sg:postcode":"8970",
    "sg:province":"West-Vlaanderen",
    "sg:tags":[
        "-"
    ],
    "wof:name":"Fruitkorve (de)",
    "wof:placetype":"venue"
},
  "geometry": {"coordinates":[2.7363409996,50.8550186157],"type":"Point"}
}