{
  "type": "Feature",
  "properties": {
    "iso:country":"BE",
    "sg:address":"Konijnenberg 26",
    "sg:city":"Sint-lambrechts-woluwe/woluwe-saint-lambert",
    "sg:orig_category":"Sportclubs",
    "sg:phone":"+32 2 770 63 85",
    "sg:postcode":"1200",
    "sg:province":"Bruxelles-Capitale",
    "wof:name":"Entente Basket Woluwe",
    "wof:placetype":"venue"
},
  "geometry": {"coordinates":[4.4388442039,50.8388595581],"type":"Point"}
}