{
  "type": "Feature",
  "properties": {
    "addr:full":"Gramayestraat 4 Antwerpen Antwerpen 2000",
    "addr:housenumber":"4",
    "addr:postcode":"2000",
    "addr:street":"Gramayestraat",
    "iso:country":"BE",
    "sg:address":"Gramayestraat 4",
    "sg:city":"Antwerpen",
    "sg:orig_category":"Agences d'exp\u00e9dition",
    "sg:phone":"+32 3 205 63 33",
    "sg:postcode":"2000",
    "sg:province":"Antwerpen",
    "wof:name":"Hamburg S\u00dcd Belgium",
    "wof:placetype":"venue"
},
  "geometry": {"coordinates":[4.4069199562,51.2189674377],"type":"Point"}
}