{
  "type": "Feature",
  "properties": {
    "iso:country":"BE",
    "sg:address":"Ninovesteenweg 182",
    "sg:city":"Aalst",
    "sg:orig_category":"Equipement photographique",
    "sg:phone":"+32 53 21 68 05",
    "sg:postcode":"9320",
    "sg:province":"Oost-Vlaanderen",
    "wof:name":"Fa. De Crem P.& F.",
    "wof:placetype":"venue"
},
  "geometry": {"coordinates":[4.0553851128,50.9209976196],"type":"Point"}
}