{
  "type": "Feature",
  "properties": {
    "iso:country":"BE",
    "sg:address":"Kloosterstraat 33",
    "sg:city":"Denderleeuw",
    "sg:orig_category":"Artsen and specialisten",
    "sg:phone":"+32 53 66 39 59",
    "sg:postcode":"9472",
    "sg:province":"Oost-Vlaanderen",
    "wof:name":"Walter Van Den Borre",
    "wof:placetype":"venue"
},
  "geometry": {"coordinates":[4.0474457741,50.8776359558],"type":"Point"}
}