{
  "type": "Feature",
  "properties": {
    "addr:full":"Lange Kroonstraat 18 Boechout Antwerpen 2530",
    "addr:housenumber":"18",
    "addr:postcode":"2530",
    "addr:street":"Lange Kroonstraat",
    "iso:country":"BE",
    "sg:address":"Lange Kroonstraat 18",
    "sg:city":"Boechout",
    "sg:classifiers":[
        {
            "category":"Communications",
            "type":"Services"
        }
    ],
    "sg:phone":"+32 3 454 13 50",
    "sg:postcode":"2530",
    "sg:province":"Antwerpen",
    "sg:tags":[
        "translator"
    ],
    "wof:name":"Reyniers Bvba",
    "wof:placetype":"venue"
},
  "geometry": {"coordinates":[4.4900307655,51.1614227295],"type":"Point"}
}