{
  "type": "Feature",
  "properties": {
    "iso:country":"BE",
    "sg:address":"Reepstraat 163",
    "sg:city":"Sint-gillis-waas",
    "sg:classifiers":[
        {
            "category":"Professional",
            "subcategory":"Management & Consulting",
            "type":"Services"
        }
    ],
    "sg:phone":"+32 475 41 84 32",
    "sg:postcode":"9170",
    "sg:province":"Oost-Vlaanderen",
    "sg:tags":[
        "consultant"
    ],
    "wof:name":"Icm",
    "wof:placetype":"venue"
},
  "geometry": {"coordinates":[4.0855231285,51.2262306213],"type":"Point"}
}