{
  "type": "Feature",
  "properties": {
    "addr:full":"Rue Pierre-joseph Wincqz 19 Soignies Hainaut 7060",
    "addr:housenumber":"19",
    "addr:postcode":"7060",
    "addr:street":"Rue Pierre-Joseph Wincqz",
    "iso:country":"BE",
    "sg:address":"Rue Pierre-joseph Wincqz 19",
    "sg:city":"Soignies",
    "sg:orig_category":"M\u00e9decins and sp\u00e9cialistes",
    "sg:phone":"+32 67 33 49 30",
    "sg:postcode":"7060",
    "sg:province":"Hainaut",
    "wof:name":"Jean Maquet",
    "wof:placetype":"venue"
},
  "geometry": {"coordinates":[4.0716638565,50.5753936768],"type":"Point"}
}