{
  "type": "Feature",
  "properties": {
    "iso:country":"BE",
    "sg:address":"Golfbrekerslaan 36",
    "sg:city":"Middelkerke",
    "sg:classifiers":[
        {
            "category":"Insurance",
            "subcategory":"Insurance Agent",
            "type":"Services"
        }
    ],
    "sg:phone":"+32 59 30 23 98",
    "sg:postcode":"8430",
    "sg:province":"West-Vlaanderen",
    "sg:tags":[
        "verzekeringsmakelaars",
        "expert"
    ],
    "wof:name":"Bernaert-laleman",
    "wof:placetype":"venue"
},
  "geometry": {"coordinates":[2.7972700596,51.177066803],"type":"Point"}
}