{
  "type": "Feature",
  "properties": {
    "addr:full":"Wapenaarteinde 5 Sint-niklaas (sinaai) Oost-Vlaanderen 9112",
    "addr:housenumber":"5",
    "addr:postcode":"9112",
    "addr:street":"Wapenaarteinde;Oost-Vlaanderen",
    "iso:country":"BE",
    "sg:address":"Wapenaarteinde 5",
    "sg:city":"Sint-niklaas (sinaai)",
    "sg:classifiers":[
        {
            "category":"Retail",
            "subcategory":"Event Space",
            "type":"Services"
        }
    ],
    "sg:phone":"+32 9 349 37 47",
    "sg:postcode":"9112",
    "sg:province":"Oost-Vlaanderen",
    "sg:tags":[
        "rental",
        "-",
        "hall"
    ],
    "wof:name":"Klein Londen",
    "wof:placetype":"venue"
},
  "geometry": {"coordinates":[3.9949679375,51.1497497559],"type":"Point"}
}