{
  "type": "Feature",
  "properties": {
    "iso:country":"BE",
    "sg:address":"Drogenbroodstraat 13",
    "sg:city":"Pittem",
    "sg:orig_category":"Kapsalons",
    "sg:phone":"+32 51 46 78 08",
    "sg:postcode":"8740",
    "sg:province":"West-Vlaanderen",
    "wof:name":"Coiffure Christine",
    "wof:placetype":"venue"
},
  "geometry": {"coordinates":[3.2586069107,51.0159416199],"type":"Point"}
}