{
  "type": "Feature",
  "properties": {
    "addr:full":"Avenue De La Chapelle 179 Kraainem Vlaams-Brabant 1950",
    "addr:housenumber":"179",
    "addr:postcode":"1950",
    "addr:street":"Avenue De La Chapelle",
    "iso:country":"BE",
    "sg:address":"Avenue De La Chapelle 179",
    "sg:city":"Kraainem",
    "sg:classifiers":[
        {
            "category":"Insurance",
            "subcategory":"Insurance Agent",
            "type":"Services"
        }
    ],
    "sg:phone":"+32 2 720 51 55",
    "sg:postcode":"1950",
    "sg:province":"Vlaams-Brabant",
    "sg:tags":[
        "verzekeringsmakelaars",
        "expert"
    ],
    "wof:name":"Pierre-yves Destree",
    "wof:placetype":"venue"
},
  "geometry": {"coordinates":[4.4571962357,50.8570137024],"type":"Point"}
}