{
  "type": "Feature",
  "properties": {
    "iso:country":"BE",
    "sg:address":"Kiewitdreef 0",
    "sg:city":"Hasselt",
    "sg:classifiers":[
        {
            "category":"Restaurant",
            "type":"Food & Drink"
        }
    ],
    "sg:phone":"+32 11 21 02 60",
    "sg:postcode":"3500",
    "sg:province":"Limburg",
    "wof:name":"Tearoom Koetshuis",
    "wof:placetype":"venue"
},
  "geometry": {"coordinates":[5.3670539856,50.9664268494],"type":"Point"}
}