{
  "type": "Feature",
  "properties": {
    "addr:full":"Keuzelingsstraat 12 Kluisbergen Oost-Vlaanderen 9690",
    "addr:housenumber":"12",
    "addr:postcode":"9690",
    "addr:street":"Keuzelingsstraat",
    "iso:country":"BE",
    "sg:address":"Keuzelingsstraat 12",
    "sg:city":"Kluisbergen",
    "sg:orig_category":"Rundveehouders",
    "sg:phone":"+32 55 38 88 53",
    "sg:postcode":"9690",
    "sg:province":"Oost-Vlaanderen",
    "wof:name":"Jozef Lambrecht",
    "wof:placetype":"venue"
},
  "geometry": {"coordinates":[3.5245571136,50.7763328552],"type":"Point"}
}