{
  "type": "Feature",
  "properties": {
    "addr:full":"Hildeghemweg 5 Jabbeke West-Vlaanderen 8490",
    "addr:housenumber":"5",
    "addr:postcode":"8490",
    "addr:street":"Hildeghemweg",
    "iso:country":"BE",
    "sg:address":"Hildeghemweg 5",
    "sg:city":"Jabbeke",
    "sg:orig_category":"Eleveurs and marchands de porcs. Eleveurs de bovins",
    "sg:phone":"+32 50 81 39 74",
    "sg:postcode":"8490",
    "sg:province":"West-Vlaanderen",
    "wof:name":"Roger Verfaille",
    "wof:placetype":"venue"
},
  "geometry": {"coordinates":[3.1021900177,51.1597824097],"type":"Point"}
}