{
  "type": "Feature",
  "properties": {
    "addr:full":"Seulestraat 106 Heuvelland West-Vlaanderen 8950",
    "addr:housenumber":"106",
    "addr:postcode":"8950",
    "addr:street":"Seulestraat",
    "iso:country":"BE",
    "sg:address":"Seulestraat 106",
    "sg:city":"Heuvelland",
    "sg:orig_category":"Eleveurs and marchands de porcs. Eleveurs de bovins",
    "sg:phone":"+32 57 44 45 94",
    "sg:postcode":"8950",
    "sg:province":"West-Vlaanderen",
    "wof:name":"Marc Bossaert",
    "wof:placetype":"venue"
},
  "geometry": {"coordinates":[2.8249499798,50.7459411621],"type":"Point"}
}