{
  "type": "Feature",
  "properties": {
    "addr:full":"Rue Jourdan 181 Bruxelles (saint-gilles) Bruxelles-Capitale 1060",
    "addr:housenumber":"181",
    "addr:postcode":"1060",
    "addr:street":"Rue Jourdan",
    "iso:country":"BE",
    "sg:address":"Rue Jourdan 181",
    "sg:city":"Bruxelles (saint-gilles)",
    "sg:classifiers":[
        {
            "category":"Food & Beverages",
            "subcategory":"Meat & Fish",
            "type":"Retail Goods"
        }
    ],
    "sg:phone":"+32 2 537 78 65",
    "sg:postcode":"1060",
    "sg:province":"Bruxelles-Capitale",
    "sg:tags":[
        "poultry",
        "whol",
        "game",
        "-"
    ],
    "wof:name":"Segers G",
    "wof:placetype":"venue"
},
  "geometry": {"coordinates":[4.3469901085,50.8312263489],"type":"Point"}
}