{
  "type": "Feature",
  "properties": {
    "addr:full":"Vissersstraat 5 Destelbergen Oost-Vlaanderen 9070",
    "addr:housenumber":"5",
    "addr:postcode":"9070",
    "addr:street":"Vissersstraat",
    "iso:country":"BE",
    "sg:address":"Vissersstraat 5",
    "sg:city":"Destelbergen",
    "sg:classifiers":[
        {
            "category":"Wholesale",
            "subcategory":"Plants",
            "type":"Manufacturing & Wholesale Goods"
        }
    ],
    "sg:phone":"+32 9 228 61 97",
    "sg:postcode":"9070",
    "sg:province":"Oost-Vlaanderen",
    "sg:tags":[
        "whol",
        "flower",
        "-",
        "grower"
    ],
    "wof:name":"Paelinck M",
    "wof:placetype":"venue"
},
  "geometry": {"coordinates":[3.8123660088,51.0650062561],"type":"Point"}
}