{
  "type": "Feature",
  "properties": {
    "iso:country":"BE",
    "sg:address":"Rue Des Canadiens 36",
    "sg:city":"Dour (groot)",
    "sg:classifiers":[
        {
            "category":"Personal",
            "subcategory":"Beauty Salon",
            "type":"Services"
        }
    ],
    "sg:phone":"+32 65 63 02 28",
    "sg:postcode":"7370",
    "sg:province":"Hainaut",
    "sg:tags":[
        "de",
        "coiffure"
    ],
    "wof:name":"Coiffure Nathalie",
    "wof:placetype":"venue"
},
  "geometry": {"coordinates":[3.7740869522,50.3998641968],"type":"Point"}
}