{
  "type": "Feature",
  "properties": {
    "iso:country":"BE",
    "sg:address":"Grand-m\u00c8re Hilson 32",
    "sg:city":"Walcourt",
    "sg:orig_category":"Charpentes and couvertures",
    "sg:phone":"+32 495 16 94 66",
    "sg:postcode":"5650",
    "sg:province":"Namur",
    "wof:name":"Euro-toiture",
    "wof:placetype":"venue"
},
  "geometry": {"coordinates":[4.4313349724,50.2514762878],"type":"Point"}
}