{
  "type": "Feature",
  "properties": {
    "iso:country":"BE",
    "sg:address":"Cocquytstraat 49",
    "sg:city":"Eeklo",
    "sg:classifiers":[
        {
            "category":"Insurance",
            "subcategory":"Insurance Agent",
            "type":"Services"
        }
    ],
    "sg:phone":"+32 9 377 65 98",
    "sg:postcode":"9900",
    "sg:province":"Oost-Vlaanderen",
    "sg:tags":[
        "broker"
    ],
    "wof:name":"Francois P",
    "wof:placetype":"venue"
},
  "geometry": {"coordinates":[3.5622370243,51.1834716797],"type":"Point"}
}