{
  "type": "Feature",
  "properties": {
    "addr:full":"Kleine Kruisstraat 19 Herk-de-stad Limburg 3540",
    "addr:housenumber":"19",
    "addr:postcode":"3540",
    "addr:street":"Kleine Kruisstraat",
    "iso:country":"BE",
    "sg:address":"Kleine Kruisstraat 19",
    "sg:city":"Herk-de-stad",
    "sg:orig_category":"Fruitteelt Rundveehouders",
    "sg:phone":"+32 13 55 16 93",
    "sg:postcode":"3540",
    "sg:province":"Limburg",
    "wof:name":"Andre Maris",
    "wof:placetype":"venue"
},
  "geometry": {"coordinates":[5.1747469902,50.9276885986],"type":"Point"}
}