{
  "type": "Feature",
  "properties": {
    "addr:full":"Boulevard De La Constitution 25 Li\u00e8ge 1 (li\u00e8ge 2) Li\u00e8ge 4020",
    "addr:housenumber":"25;1;2",
    "addr:postcode":"4020",
    "addr:street":"Boulevard De La Constitution",
    "iso:country":"BE",
    "sg:address":"Boulevard De La Constitution 25",
    "sg:city":"Li\u00e8ge 1 (li\u00e8ge 2)",
    "sg:classifiers":[
        {
            "category":"Retail",
            "subcategory":"Funeral Services",
            "type":"Services"
        }
    ],
    "sg:postcode":"4020",
    "sg:province":"Li\u00e8ge",
    "sg:tags":[
        "director"
    ],
    "wof:name":"Largefeuille (pompes Funebres)",
    "wof:placetype":"venue"
},
  "geometry": {"coordinates":[5.5844459534,50.6434822083],"type":"Point"}
}