{
  "type": "Feature",
  "properties": {
    "iso:country":"BE",
    "sg:address":"Rue Du Thier 26",
    "sg:city":"Soumagne",
    "sg:orig_category":"Services pour animaux domestiques",
    "sg:phone":"+32 4 377 35 39",
    "sg:postcode":"4631",
    "sg:province":"Li\u00e8ge",
    "wof:name":"Dressage Pays Perdu",
    "wof:placetype":"venue"
},
  "geometry": {"coordinates":[5.7083230019,50.6447639465],"type":"Point"}
}