{
  "type": "Feature",
  "properties": {
    "iso:country":"BE",
    "sg:address":"Godveerdegemstraat 15 Box 11",
    "sg:city":"Zottegem",
    "sg:classifiers":[
        {
            "category":"Building & Trades",
            "subcategory":"Construction",
            "type":"Services"
        }
    ],
    "sg:phone":"+32 9 360 49 49",
    "sg:postcode":"9620",
    "sg:province":"Oost-Vlaanderen",
    "sg:tags":[
        "surveyor",
        "-"
    ],
    "wof:name":"De Roose M",
    "wof:placetype":"venue"
},
  "geometry": {"coordinates":[3.8183269501,50.8647956848],"type":"Point"}
}