{
  "type": "Feature",
  "properties": {
    "iso:country":"BE",
    "sg:address":"Niskensstraat 7",
    "sg:city":"Bree",
    "sg:orig_category":"Woningbouw",
    "sg:phone":"+32 89 46 37 42",
    "sg:postcode":"3960",
    "sg:province":"Limburg",
    "wof:name":"Lambert Brulez",
    "wof:placetype":"venue"
},
  "geometry": {"coordinates":[5.5944190025,51.1405677795],"type":"Point"}
}