{
  "type": "Feature",
  "properties": {
    "iso:country":"BE",
    "sg:address":"Noorderwijseweg 1b",
    "sg:city":"Olen",
    "sg:orig_category":"Architecten",
    "sg:phone":"+32 14 26 64 23",
    "sg:postcode":"2250",
    "sg:province":"Antwerpen",
    "wof:name":"Adriaensens",
    "wof:placetype":"venue"
},
  "geometry": {"coordinates":[4.8547282219,51.1431236267],"type":"Point"}
}