{
  "type": "Feature",
  "properties": {
    "addr:full":"Place Albert Ier 24 Charleroi Hainaut 6000",
    "addr:housenumber":"24",
    "addr:postcode":"6000",
    "addr:street":"Place Albert Ier;Hainaut",
    "iso:country":"BE",
    "sg:address":"Place Albert Ier 24",
    "sg:city":"Charleroi",
    "sg:orig_category":"Banken and kredietinstellingen",
    "sg:phone":"+32 71 32 94 84",
    "sg:postcode":"6000",
    "sg:province":"Hainaut",
    "wof:name":"Gesbanque",
    "wof:placetype":"venue"
},
  "geometry": {"coordinates":[4.4409389496,50.4081344604],"type":"Point"}
}