{
  "type": "Feature",
  "properties": {
    "addr:full":"Galgestr 4 Ouwegem 9761",
    "addr:housenumber":"4",
    "addr:postcode":"9761",
    "addr:street":"Galgestr",
    "iso:country":"BE",
    "sg:address":"Galgestr 4",
    "sg:city":"Ouwegem",
    "sg:classifiers":[
        {
            "category":"Banks & Credit Unions",
            "subcategory":"Bank",
            "type":"Services"
        }
    ],
    "sg:phone":"+32 53 84 16 90",
    "sg:postcode":"9761",
    "wof:name":"Famibank",
    "wof:placetype":"venue"
},
  "geometry": {"coordinates":[6.578619957,53.1300315857],"type":"Point"}
}