{
  "type": "Feature",
  "properties": {
    "iso:country":"BE",
    "sg:address":"Verbindingslaan 44",
    "sg:city":"Leuven",
    "sg:orig_category":"M\u00e9decins and sp\u00e9cialistes",
    "sg:phone":"+32 16 40 48 71",
    "sg:postcode":"3001",
    "sg:province":"Vlaams-Brabant",
    "wof:name":"Robberecht Dieu",
    "wof:placetype":"venue"
},
  "geometry": {"coordinates":[4.7015709877,50.8602142334],"type":"Point"}
}