{
  "type": "Feature",
  "properties": {
    "addr:full":"Stadionstraat 16 Stekene Oost-Vlaanderen 9190",
    "addr:housenumber":"16",
    "addr:postcode":"9190",
    "addr:street":"Stadionstraat",
    "iso:country":"BE",
    "sg:address":"Stadionstraat 16",
    "sg:city":"Stekene",
    "sg:classifiers":[
        {
            "category":"Shopping",
            "subcategory":"Jewelry",
            "type":"Retail Goods"
        }
    ],
    "sg:phone":"+32 3 779 45 81",
    "sg:postcode":"9190",
    "sg:province":"Oost-Vlaanderen",
    "sg:tags":[
        "jeweller",
        "-"
    ],
    "wof:name":"Devina Juwelen",
    "wof:placetype":"venue"
},
  "geometry": {"coordinates":[4.0419020653,51.2056503296],"type":"Point"}
}