{
  "type": "Feature",
  "properties": {
    "addr:full":"Zomerweg 10 Veurne West-Vlaanderen 8630",
    "addr:housenumber":"10",
    "addr:postcode":"8630",
    "addr:street":"Zomerweg",
    "iso:country":"BE",
    "sg:address":"Zomerweg 10",
    "sg:city":"Veurne",
    "sg:orig_category":"Animations diverses",
    "sg:phone":"+32 477 66 64 92",
    "sg:postcode":"8630",
    "sg:province":"West-Vlaanderen",
    "wof:name":"Studio Vermant",
    "wof:placetype":"venue"
},
  "geometry": {"coordinates":[2.6633110046,51.0159568787],"type":"Point"}
}