{
  "type": "Feature",
  "properties": {
    "iso:country":"BE",
    "sg:address":"Rue Du Centre 39",
    "sg:city":"Geer (hollogne-sur-geer)",
    "sg:classifiers":[
        {
            "category":"Home & Garden",
            "subcategory":"Furniture",
            "type":"Retail Goods"
        }
    ],
    "sg:phone":"+32 19 58 72 52",
    "sg:postcode":"4250",
    "sg:province":"Li\u00e8ge",
    "sg:tags":[
        "-"
    ],
    "wof:name":"Roha",
    "wof:placetype":"venue"
},
  "geometry": {"coordinates":[5.2090668678,50.6763420105],"type":"Point"}
}