{
  "type": "Feature",
  "properties": {
    "iso:country":"BE",
    "sg:address":"Steenbrugstr 114",
    "sg:city":"Harelbeke",
    "sg:classifiers":[
        {
            "category":"Autos & Motor Vehicles",
            "subcategory":"Automobile Sales",
            "type":"Retail Goods"
        }
    ],
    "sg:phone":"+32 56 22 51 44",
    "sg:postcode":"8530",
    "sg:province":"West-Vlaanderen",
    "sg:tags":[
        "equipment",
        "motor-cars",
        "transport"
    ],
    "wof:name":"Maesss Motorhomes Nv",
    "wof:placetype":"venue"
},
  "geometry": {"coordinates":[3.3261470795,50.8343353271],"type":"Point"}
}