{
  "type": "Feature",
  "properties": {
    "addr:full":"Rue Grand-vin\u00c2ve 78 Seraing Li\u00e8ge 4101",
    "addr:housenumber":"78",
    "addr:postcode":"4101",
    "addr:street":"Rue Grand-Vina\u0302Ve",
    "iso:country":"BE",
    "sg:address":"Rue Grand-vin\u00c2ve 78",
    "sg:city":"Seraing",
    "sg:orig_category":"Beautyfarms, relaxatie and lichamelijk welzijn Cosmetica and toiletartikelen Schoonheidssalons",
    "sg:phone":"+32 4 231 08 52",
    "sg:postcode":"4101",
    "sg:province":"Li\u00e8ge",
    "wof:name":"Yves Rocher",
    "wof:placetype":"venue"
},
  "geometry": {"coordinates":[5.5071787834,50.6170120239],"type":"Point"}
}