{
  "type": "Feature",
  "properties": {
    "iso:country":"BE",
    "sg:address":"Heirstraat 467b1",
    "sg:city":"Maasmechelen",
    "sg:classifiers":[
        {
            "category":"Cafe",
            "type":"Food & Drink"
        }
    ],
    "sg:phone":"+32 89 77 52 43",
    "sg:postcode":"3630",
    "sg:province":"Limburg",
    "sg:tags":[
        "caf\u00e9s"
    ],
    "wof:name":"Caf\u00c9 Yellow Cab",
    "wof:placetype":"venue"
},
  "geometry": {"coordinates":[5.6846699715,50.9509391785],"type":"Point"}
}