{
  "type": "Feature",
  "properties": {
    "iso:country":"BE",
    "sg:address":"Otegemse Steenweg 72",
    "sg:city":"Deerlijk",
    "sg:classifiers":[
        {
            "category":"Retail",
            "subcategory":"Auto Repair",
            "type":"Services"
        }
    ],
    "sg:phone":"+32 56 77 70 94",
    "sg:postcode":"8540",
    "sg:province":"West-Vlaanderen",
    "sg:tags":[
        "garage"
    ],
    "wof:name":"Deconinck",
    "wof:placetype":"venue"
},
  "geometry": {"coordinates":[3.3779129982,50.8154525757],"type":"Point"}
}