{
  "type": "Feature",
  "properties": {
    "iso:country":"BE",
    "sg:address":"Rue De Valenciennes",
    "sg:city":"Quievrain",
    "sg:orig_category":"Huisdieren and benodigdheden Royal Canin Sport- and kampeermateriaal",
    "sg:phone":"+32 65 45 80 03",
    "sg:postcode":"7380",
    "sg:province":"Hainaut",
    "wof:name":"Ets Douliez",
    "wof:placetype":"venue"
},
  "geometry": {"coordinates":[3.6782341003,50.4041023254],"type":"Point"}
}