{
  "type": "Feature",
  "properties": {
    "addr:full":"Nijverheidsstraat 90ba Rumst Antwerpen 2840",
    "addr:housenumber":"90ba",
    "addr:postcode":"2840",
    "addr:street":"Nijverheidsstraat",
    "iso:country":"BE",
    "sg:address":"Nijverheidsstraat 90ba",
    "sg:city":"Rumst",
    "sg:orig_category":"Voertuigen",
    "sg:phone":"+32 3 844 74 71",
    "sg:postcode":"2840",
    "sg:province":"Antwerpen",
    "wof:name":"Garage Van Den Brande",
    "wof:placetype":"venue"
},
  "geometry": {"coordinates":[4.4202709198,51.0792274475],"type":"Point"}
}