{
  "type": "Feature",
  "properties": {
    "addr:full":"P.i. Taymansstraat 47 Overijse Vlaams-Brabant 3090",
    "addr:housenumber":"47",
    "addr:postcode":"3090",
    "addr:street":"P.I. Taymansstraat",
    "iso:country":"BE",
    "sg:address":"P.i. Taymansstraat 47",
    "sg:city":"Overijse",
    "sg:classifiers":[
        {
            "category":"Insurance",
            "subcategory":"Insurance Agent",
            "type":"Services"
        }
    ],
    "sg:phone":"+32 2 687 75 63",
    "sg:postcode":"3090",
    "sg:province":"Vlaams-Brabant",
    "sg:tags":[
        "verzekeringsmakelaars",
        "expert"
    ],
    "wof:name":"Christian Janssens",
    "wof:placetype":"venue"
},
  "geometry": {"coordinates":[4.5364160538,50.7764511108],"type":"Point"}
}