{
  "type": "Feature",
  "properties": {
    "iso:country":"BE",
    "sg:address":"Albert Peeterslei 8",
    "sg:city":"Kalmthout",
    "sg:orig_category":"Elektrische installaties voor woningen",
    "sg:phone":"+32 3 666 16 68",
    "sg:postcode":"2920",
    "sg:province":"Antwerpen",
    "wof:name":"Mous",
    "wof:placetype":"venue"
},
  "geometry": {"coordinates":[4.4682297707,51.393535614],"type":"Point"}
}