{
  "type": "Feature",
  "properties": {
    "addr:full":"Roeselarestraat 122 Ledegem West-Vlaanderen 8880",
    "addr:housenumber":"122",
    "addr:postcode":"8880",
    "addr:street":"Roeselarestraat",
    "iso:country":"BE",
    "sg:address":"Roeselarestraat 122",
    "sg:city":"Ledegem",
    "sg:orig_category":"Tuinen",
    "sg:phone":"+32 56 50 27 09",
    "sg:postcode":"8880",
    "sg:province":"West-Vlaanderen",
    "wof:name":"Malfait P",
    "wof:placetype":"venue"
},
  "geometry": {"coordinates":[3.1506230831,50.8768043518],"type":"Point"}
}