{
  "type": "Feature",
  "properties": {
    "addr:full":"Henri Lebbestraat 131 Bp 164 Waregem West-Vlaanderen 8790",
    "addr:housenumber":"131 bp 164",
    "addr:postcode":"8790",
    "addr:street":"Henri Lebbestraat",
    "iso:country":"BE",
    "sg:address":"Henri Lebbestraat 131 Bp 164",
    "sg:city":"Waregem",
    "sg:classifiers":[
        {
            "category":"Shopping",
            "subcategory":"Computers & Home Electronics",
            "type":"Retail Goods"
        }
    ],
    "sg:phone":"+32 56 60 17 44",
    "sg:postcode":"8790",
    "sg:province":"West-Vlaanderen",
    "sg:tags":[
        "electric",
        "electricity",
        "component",
        "equipment",
        "electrical",
        "electronic"
    ],
    "wof:name":"Albert Castelein Bvba",
    "wof:placetype":"venue"
},
  "geometry": {"coordinates":[3.4235460758,50.8776397705],"type":"Point"}
}