{
  "type": "Feature",
  "properties": {
    "iso:country":"BE",
    "sg:address":"Selsaetenstraat 25",
    "sg:city":"Wommelgem",
    "sg:orig_category":"Bloemen and planten Gh",
    "sg:phone":"+32 3 353 12 60",
    "sg:postcode":"2160",
    "sg:province":"Antwerpen",
    "wof:name":"Albrecht F",
    "wof:placetype":"venue"
},
  "geometry": {"coordinates":[4.5377140045,51.2074012756],"type":"Point"}
}