{
  "type": "Feature",
  "properties": {
    "addr:full":"Rijselstraat 274 Menen West-Vlaanderen 8930",
    "addr:housenumber":"274",
    "addr:postcode":"8930",
    "addr:street":"Rijselstraat",
    "iso:country":"BE",
    "sg:address":"Rijselstraat 274",
    "sg:city":"Menen",
    "sg:classifiers":[
        {
            "category":"Bars & Pubs",
            "type":"Food & Drink"
        }
    ],
    "sg:phone":"+32 56 53 06 63",
    "sg:postcode":"8930",
    "sg:province":"West-Vlaanderen",
    "wof:name":"Caf\u00e9 Du Centre",
    "wof:placetype":"venue"
},
  "geometry": {"coordinates":[3.127259016,50.7875022888],"type":"Point"}
}