{
  "type": "Feature",
  "properties": {
    "addr:full":"Gemeentestraat 122 Lubbeek Vlaams-Brabant 3210",
    "addr:housenumber":"122",
    "addr:postcode":"3210",
    "addr:street":"Gemeentestraat",
    "iso:country":"BE",
    "sg:address":"Gemeentestraat 122",
    "sg:city":"Lubbeek",
    "sg:orig_category":"Kapsalons",
    "sg:phone":"+32 16 62 03 52",
    "sg:postcode":"3210",
    "sg:province":"Vlaams-Brabant",
    "wof:name":"Kapsalon Bart",
    "wof:placetype":"venue"
},
  "geometry": {"coordinates":[4.7774949074,50.8912658691],"type":"Point"}
}