{
  "type": "Feature",
  "properties": {
    "addr:full":"Place Louis Pasteur 3 Ottignies-louvain-la-neuve Brabant Wallon 1348",
    "addr:housenumber":"3",
    "addr:postcode":"1348",
    "addr:street":"Place Louis Pasteur",
    "iso:country":"BE",
    "sg:address":"Place Louis Pasteur 3",
    "sg:city":"Ottignies-louvain-la-neuve",
    "sg:orig_category":"Hoger onderwijs",
    "sg:phone":"+32 10 47 28 94",
    "sg:postcode":"1348",
    "sg:province":"Brabant Wallon",
    "wof:name":"U.c.l.-d\u00c9partement Geo",
    "wof:placetype":"venue"
},
  "geometry": {"coordinates":[4.6193060875,50.6692695618],"type":"Point"}
}