{
  "type": "Feature",
  "properties": {
    "iso:country":"BE",
    "sg:address":"Het Prieel 29",
    "sg:city":"Mortsel",
    "sg:classifiers":[
        {
            "category":"Professional",
            "subcategory":"Accounting & Tax Preparation",
            "type":"Services"
        }
    ],
    "sg:phone":"+32 3 449 87 86",
    "sg:postcode":"2640",
    "sg:province":"Antwerpen",
    "sg:tags":[
        "accountant"
    ],
    "wof:name":"Guido Boonen",
    "wof:placetype":"venue"
},
  "geometry": {"coordinates":[4.4467902184,51.1889915466],"type":"Point"}
}