{
  "type": "Feature",
  "properties": {
    "iso:country":"BE",
    "sg:address":"Roggestraat 10",
    "sg:city":"Wielsbeke",
    "sg:classifiers":[
        {
            "category":"Home & Garden",
            "subcategory":"Carpets & Floor Coverings",
            "type":"Retail Goods"
        }
    ],
    "sg:phone":"+32 56 66 39 79",
    "sg:postcode":"8710",
    "sg:province":"West-Vlaanderen",
    "sg:tags":[
        "layer",
        "mosaicists"
    ],
    "wof:name":"Bouwonderneming Lattre Ivan Bvba",
    "wof:placetype":"venue"
},
  "geometry": {"coordinates":[3.3804190159,50.9110984802],"type":"Point"}
}