{
  "type": "Feature",
  "properties": {
    "addr:full":"Bierweg 6 Aalter Oost-Vlaanderen 9880",
    "addr:housenumber":"6",
    "addr:postcode":"9880",
    "addr:street":"Bierweg",
    "iso:country":"BE",
    "sg:address":"Bierweg 6",
    "sg:city":"Aalter",
    "sg:classifiers":[
        {
            "category":"Health Services",
            "subcategory":"Health Practitioner",
            "type":"Services"
        }
    ],
    "sg:phone":"+32 9 375 04 58",
    "sg:postcode":"9880",
    "sg:province":"Oost-Vlaanderen",
    "sg:tags":[
        "physiotherapist"
    ],
    "wof:name":"De Borle Katrien",
    "wof:placetype":"venue"
},
  "geometry": {"coordinates":[3.4423019886,51.0842666626],"type":"Point"}
}