{
  "type": "Feature",
  "properties": {
    "addr:full":"Edingseweg 212 Geraardsbergen Oost-Vlaanderen 9500",
    "addr:housenumber":"212",
    "addr:postcode":"9500",
    "addr:street":"Edingseweg",
    "iso:country":"BE",
    "sg:address":"Edingseweg 212",
    "sg:city":"Geraardsbergen",
    "sg:classifiers":[
        {
            "category":"Cafe",
            "type":"Food & Drink"
        }
    ],
    "sg:phone":"+32 54 41 15 74",
    "sg:postcode":"9500",
    "sg:province":"Oost-Vlaanderen",
    "sg:tags":[
        "caf\u00e9s"
    ],
    "wof:name":"Caf\u00c9 Het Witte Paard",
    "wof:placetype":"venue"
},
  "geometry": {"coordinates":[3.8971400261,50.7698707581],"type":"Point"}
}