{
  "type": "Feature",
  "properties": {
    "iso:country":"BE",
    "sg:address":"Chemin De Roy 1",
    "sg:city":"Marche-en-famenne (waha)",
    "sg:classifiers":[
        {
            "category":"Communications",
            "subcategory":"Film & Video Production",
            "type":"Services"
        }
    ],
    "sg:phone":"+32 84 32 36 32",
    "sg:postcode":"6900",
    "sg:province":"Luxembourg",
    "sg:tags":[
        "realisation",
        "-"
    ],
    "wof:name":"Image",
    "wof:placetype":"venue"
},
  "geometry": {"coordinates":[5.3736019135,50.2183456421],"type":"Point"}
}