{
  "type": "Feature",
  "properties": {
    "addr:full":"Chauss\u00c9e De Waterloo 879 Ukkel/uccle Bruxelles-Capitale 1180",
    "addr:housenumber":"879",
    "addr:postcode":"1180",
    "addr:street":"Chausse\u0301E De Waterloo;/",
    "iso:country":"BE",
    "sg:address":"Chauss\u00c9e De Waterloo 879",
    "sg:city":"Ukkel/uccle",
    "sg:orig_category":"Boucheries",
    "sg:phone":"+32 2 374 53 25",
    "sg:postcode":"1180",
    "sg:province":"Bruxelles-Capitale",
    "wof:name":"Boucherie Langhendries",
    "wof:placetype":"venue"
},
  "geometry": {"coordinates":[4.3698167801,50.8088302612],"type":"Point"}
}