{
  "type": "Feature",
  "properties": {
    "addr:full":"Benedictijnenstraat 15 Brugge (assebroek) West-Vlaanderen 8310",
    "addr:housenumber":"15",
    "addr:postcode":"8310",
    "addr:street":"Benedictijnenstraat",
    "iso:country":"BE",
    "sg:address":"Benedictijnenstraat 15",
    "sg:city":"Brugge (assebroek)",
    "sg:classifiers":[
        {
            "category":"Real Estate",
            "subcategory":"Architect",
            "type":"Services"
        }
    ],
    "sg:phone":"+32 50 36 06 01",
    "sg:postcode":"8310",
    "sg:province":"West-Vlaanderen",
    "wof:name":"Blanckaert R",
    "wof:placetype":"venue"
},
  "geometry": {"coordinates":[3.2361059189,51.1851158142],"type":"Point"}
}