{
  "type": "Feature",
  "properties": {
    "addr:full":"Thonissenlaan 90 Hasselt Limburg 3500",
    "addr:housenumber":"90",
    "addr:postcode":"3500",
    "addr:street":"Thonissenlaan",
    "iso:country":"BE",
    "sg:address":"Thonissenlaan 90",
    "sg:city":"Hasselt",
    "sg:orig_category":"Maatschappelijke dienstverlening",
    "sg:phone":"+32 11 26 40 50",
    "sg:postcode":"3500",
    "sg:province":"Limburg",
    "wof:name":"Comite Voor Bijzondere Jeugdbijstand",
    "wof:placetype":"venue"
},
  "geometry": {"coordinates":[5.3367447853,50.9341621399],"type":"Point"}
}