{
  "type": "Feature",
  "properties": {
    "addr:full":"Rue Haute-wez 1 Li\u00e8ge 1 (grivegn\u00e9e) Li\u00e8ge 4030",
    "addr:housenumber":"1;1",
    "addr:postcode":"4030",
    "addr:street":"Rue Haute-Wez",
    "iso:country":"BE",
    "sg:address":"Rue Haute-wez 1",
    "sg:city":"Li\u00e8ge 1 (grivegn\u00e9e)",
    "sg:classifiers":[
        {
            "category":"Retail",
            "subcategory":"Auto Repair",
            "type":"Services"
        }
    ],
    "sg:phone":"+32 4 343 27 01",
    "sg:postcode":"4030",
    "sg:province":"Li\u00e8ge",
    "sg:tags":[
        "garage"
    ],
    "wof:name":"Garage De L'euro-mobile",
    "wof:placetype":"venue"
},
  "geometry": {"coordinates":[5.5947370529,50.6244049072],"type":"Point"}
}