{
  "type": "Feature",
  "properties": {
    "iso:country":"BE",
    "sg:address":"Rue Des Charmes 82ba",
    "sg:city":"Andenne",
    "sg:orig_category":"Dakwerken Hout and afgeleiden Gh",
    "sg:phone":"+32 85 61 20 13",
    "sg:postcode":"5300",
    "sg:province":"Namur",
    "wof:name":"Dethier Toitures",
    "wof:placetype":"venue"
},
  "geometry": {"coordinates":[5.1147289276,50.4609870911],"type":"Point"}
}