{
  "type": "Feature",
  "properties": {
    "iso:country":"BE",
    "sg:address":"Industrieterrein Kanaal-noord 1449",
    "sg:city":"Bree",
    "sg:classifiers":[
        {
            "category":"Communications",
            "subcategory":"Film & Video Production",
            "type":"Services"
        }
    ],
    "sg:phone":"+32 89 46 73 31",
    "sg:postcode":"3960",
    "sg:province":"Limburg",
    "sg:tags":[
        "warehouse",
        "storage",
        "cold",
        "-"
    ],
    "wof:name":"Flanders Meat Traders Nv",
    "wof:placetype":"venue"
},
  "geometry": {"coordinates":[5.6272478104,51.1498527527],"type":"Point"}
}