{
  "type": "Feature",
  "properties": {
    "iso:country":"BE",
    "sg:address":"Bruul 123",
    "sg:city":"Mechelen",
    "sg:classifiers":[
        {
            "category":"Shopping",
            "subcategory":"Clothing, Apparel, & Fashions",
            "type":"Retail Goods"
        }
    ],
    "sg:phone":"+32 15 34 83 79",
    "sg:postcode":"2800",
    "sg:province":"Antwerpen",
    "sg:tags":[
        "boutique"
    ],
    "wof:name":"Dejiez Fashion",
    "wof:placetype":"venue"
},
  "geometry": {"coordinates":[4.4821891785,51.0236206055],"type":"Point"}
}