{
  "type": "Feature",
  "properties": {
    "addr:full":"Loonbeekstraat 21 Huldenberg (neerijse) Vlaams-Brabant 3040",
    "addr:housenumber":"21",
    "addr:postcode":"3040",
    "addr:street":"Loonbeekstraat",
    "iso:country":"BE",
    "sg:address":"Loonbeekstraat 21",
    "sg:city":"Huldenberg (neerijse)",
    "sg:classifiers":[
        {
            "category":"Insurance",
            "subcategory":"Insurance Agent",
            "type":"Services"
        }
    ],
    "sg:phone":"+32 16 47 74 62",
    "sg:postcode":"3040",
    "sg:province":"Vlaams-Brabant",
    "sg:tags":[
        "broker"
    ],
    "wof:name":"Michiels E & B Bvba",
    "wof:placetype":"venue"
},
  "geometry": {"coordinates":[4.617538929,50.8135986328],"type":"Point"}
}