{
  "type": "Feature",
  "properties": {
    "addr:full":"Godveerdegemstraat 149-190 Zottegem Oost-Vlaanderen 9620",
    "addr:housenumber":"149-190",
    "addr:postcode":"9620",
    "addr:street":"Godveerdegemstraat",
    "iso:country":"BE",
    "sg:address":"Godveerdegemstraat 149-190",
    "sg:city":"Zottegem",
    "sg:orig_category":"Fiduciairies",
    "sg:phone":"+32 9 360 22 95",
    "sg:postcode":"9620",
    "sg:province":"Oost-Vlaanderen",
    "wof:name":"Hovandafisc Bvba",
    "wof:placetype":"venue"
},
  "geometry": {"coordinates":[3.8230850697,50.8641242981],"type":"Point"}
}