{
  "type": "Feature",
  "properties": {
    "iso:country":"BE",
    "sg:address":"Lampestraat 89",
    "sg:city":"Kortrijk (rollegem)",
    "sg:classifiers":[
        {
            "category":"Farming",
            "subcategory":"Fish & Marine Products",
            "type":"Manufacturing & Wholesale Goods"
        }
    ],
    "sg:phone":"+32 56 41 84 19",
    "sg:postcode":"8510",
    "sg:province":"West-Vlaanderen",
    "sg:tags":[
        "retail",
        "-",
        "shellfish"
    ],
    "wof:name":"Dubrul H",
    "wof:placetype":"venue"
},
  "geometry": {"coordinates":[3.2429149151,50.772731781],"type":"Point"}
}