{
  "type": "Feature",
  "properties": {
    "iso:country":"BE",
    "sg:address":"Raymond Lauwersstraat 17bb",
    "sg:city":"Hoeilaart",
    "sg:orig_category":"Dansscholen",
    "sg:phone":"+32 2 657 94 60",
    "sg:postcode":"1560",
    "sg:province":"Vlaams-Brabant",
    "wof:name":"Dansclub Favoriet",
    "wof:placetype":"venue"
},
  "geometry": {"coordinates":[4.4811720848,50.767906189],"type":"Point"}
}