{
  "type": "Feature",
  "properties": {
    "iso:country":"BE",
    "sg:address":"Rue Du Gravier 25",
    "sg:city":"Li\u00e8ge 1 (ch\u00ean\u00e9e)",
    "sg:classifiers":[
        {
            "category":"Personal",
            "subcategory":"Shoe Repair & Shine",
            "type":"Services"
        }
    ],
    "sg:phone":"+32 4 367 74 53",
    "sg:postcode":"4032",
    "sg:province":"Li\u00e8ge",
    "sg:tags":[
        "shoemaker"
    ],
    "wof:name":"Artisans Cordonniers (les)",
    "wof:placetype":"venue"
},
  "geometry": {"coordinates":[5.615696907,50.6105728149],"type":"Point"}
}