{
  "type": "Feature",
  "properties": {
    "addr:full":"Avenue De Cortenbergh 75 Bruxelles Bruxelles-Capitale 1000",
    "addr:housenumber":"75",
    "addr:postcode":"1000",
    "addr:street":"Avenue De Cortenbergh",
    "iso:country":"BE",
    "sg:address":"Avenue De Cortenbergh 75",
    "sg:city":"Bruxelles",
    "sg:classifiers":[
        {
            "category":"Organizations",
            "subcategory":"Professional Association",
            "type":"Services"
        }
    ],
    "sg:phone":"+32 2 740 27 10",
    "sg:postcode":"1000",
    "sg:province":"Bruxelles-Capitale",
    "sg:tags":[
        "trade-union",
        "federation"
    ],
    "wof:name":"West Midlands In Europe",
    "wof:placetype":"venue"
},
  "geometry": {"coordinates":[4.3894968033,50.8446846008],"type":"Point"}
}