{
  "type": "Feature",
  "properties": {
    "addr:full":"Rue De La Gare 69 Bernissart Hainaut 7322",
    "addr:housenumber":"69",
    "addr:postcode":"7322",
    "addr:street":"Rue De La Gare",
    "iso:country":"BE",
    "sg:address":"Rue De La Gare 69",
    "sg:city":"Bernissart",
    "sg:orig_category":"Artistes ind\u00e9pendants. Bijouteries and horlogeries",
    "sg:phone":"+32 65 62 08 06",
    "sg:postcode":"7322",
    "sg:province":"Hainaut",
    "wof:name":"Cr\u00c9ations Christiguey",
    "wof:placetype":"venue"
},
  "geometry": {"coordinates":[3.7240979671,50.4655227661],"type":"Point"}
}