{
  "type": "Feature",
  "properties": {
    "addr:full":"Pollareveld 32 Meise (wolvertem) Vlaams-Brabant 1861",
    "addr:housenumber":"32",
    "addr:postcode":"1861",
    "addr:street":"Pollareveld",
    "iso:country":"BE",
    "sg:address":"Pollareveld 32",
    "sg:city":"Meise (wolvertem)",
    "sg:classifiers":[
        {
            "category":"Building & Trades",
            "subcategory":"Electrical",
            "type":"Services"
        }
    ],
    "sg:phone":"+32 52 30 25 05",
    "sg:postcode":"1861",
    "sg:province":"Vlaams-Brabant",
    "sg:tags":[
        "electric",
        "-",
        "housewiring",
        "contractor"
    ],
    "wof:name":"Luypaert E",
    "wof:placetype":"venue"
},
  "geometry": {"coordinates":[4.3277301788,50.9858283997],"type":"Point"}
}