{
  "type": "Feature",
  "properties": {
    "iso:country":"BE",
    "sg:address":"Stationsstraat 80",
    "sg:city":"Stekene",
    "sg:orig_category":"Woningbouw",
    "sg:phone":"+32 3 779 70 94",
    "sg:postcode":"9190",
    "sg:province":"Oost-Vlaanderen",
    "wof:name":"De Wachter",
    "wof:placetype":"venue"
},
  "geometry": {"coordinates":[4.0725831985,51.2108192444],"type":"Point"}
}