{
  "type": "Feature",
  "properties": {
    "addr:full":"Plockroy 30 Meeuwen-gruitrode (wijshagen) Limburg 3670",
    "addr:housenumber":"30",
    "addr:postcode":"3670",
    "addr:street":"Plockroy",
    "iso:country":"BE",
    "sg:address":"Plockroy 30",
    "sg:city":"Meeuwen-gruitrode (wijshagen)",
    "sg:classifiers":[
        {
            "category":"Food & Beverages",
            "subcategory":"Meat & Fish",
            "type":"Retail Goods"
        }
    ],
    "sg:phone":"+32 11 79 28 91",
    "sg:postcode":"3670",
    "sg:province":"Limburg",
    "sg:tags":[
        "-",
        "livestock"
    ],
    "wof:name":"Geusens J",
    "wof:placetype":"venue"
},
  "geometry": {"coordinates":[5.5265498161,51.0798797607],"type":"Point"}
}