{
  "type": "Feature",
  "properties": {
    "iso:country":"BE",
    "sg:address":"Weldoenstraat 78",
    "sg:city":"Watermaal-bosvoorde/watermael-boitsfort",
    "sg:classifiers":[
        {
            "category":"Fast Food",
            "type":"Food & Drink"
        }
    ],
    "sg:phone":"+32 2 672 52 39",
    "sg:postcode":"1170",
    "sg:province":"Bruxelles-Capitale",
    "sg:tags":[
        "meeneem",
        "restaurant"
    ],
    "wof:name":"Le Bien Faire",
    "wof:placetype":"venue"
},
  "geometry": {"coordinates":[4.431429863,50.7936401367],"type":"Point"}
}