{
  "type": "Feature",
  "properties": {
    "addr:full":"Quai Churchill 7 Li\u00e8ge 1 (li\u00e8ge 2) Li\u00e8ge 4020",
    "addr:housenumber":"7;1;2",
    "addr:postcode":"4020",
    "addr:street":"Quai Churchill",
    "iso:country":"BE",
    "sg:address":"Quai Churchill 7",
    "sg:city":"Li\u00e8ge 1 (li\u00e8ge 2)",
    "sg:classifiers":[
        {
            "category":"Health Services",
            "subcategory":"Health Practitioner",
            "type":"Services"
        }
    ],
    "sg:phone":"+32 4 343 43 43",
    "sg:postcode":"4020",
    "sg:province":"Li\u00e8ge",
    "sg:tags":[
        "physiotherapist"
    ],
    "wof:name":"Van Laar Jacques",
    "wof:placetype":"venue"
},
  "geometry": {"coordinates":[5.5768780708,50.6362533569],"type":"Point"}
}