{
  "type": "Feature",
  "properties": {
    "addr:full":"Maarschalk Frenchlaan 40 Ieper West-Vlaanderen 8900",
    "addr:housenumber":"40",
    "addr:postcode":"8900",
    "addr:street":"Maarschalk Frenchlaan",
    "iso:country":"BE",
    "sg:address":"Maarschalk Frenchlaan 40",
    "sg:city":"Ieper",
    "sg:classifiers":[
        {
            "category":"Quarry",
            "type":"Physical Feature"
        }
    ],
    "sg:phone":"+32 57 20 10 21",
    "sg:postcode":"8900",
    "sg:province":"West-Vlaanderen",
    "sg:tags":[
        "granite",
        "work",
        "marble"
    ],
    "wof:name":"Timmerman",
    "wof:placetype":"venue"
},
  "geometry": {"coordinates":[2.8942670822,50.8529624939],"type":"Point"}
}