{
  "type": "Feature",
  "properties": {
    "iso:country":"BE",
    "sg:address":"Gullegemsesteenweg 91",
    "sg:city":"Kortrijk (bissegem)",
    "sg:classifiers":[
        {
            "category":"Animal Shelter",
            "type":"Public Place"
        }
    ],
    "sg:phone":"+32 56 35 38 68",
    "sg:postcode":"8501",
    "sg:province":"West-Vlaanderen",
    "wof:name":"Kattenpension 'de Modelhoeve'",
    "wof:placetype":"venue"
},
  "geometry": {"coordinates":[3.2141499519,50.8329086304],"type":"Point"}
}