{
  "type": "Feature",
  "properties": {
    "iso:country":"BE",
    "sg:address":"Verte Voie 44 Box 101",
    "sg:city":"Ottignies-louvain-la-neuve (louvain-la-neuve)",
    "sg:classifiers":[
        {
            "category":"Building & Trades",
            "subcategory":"Landscaping Services",
            "type":"Services"
        }
    ],
    "sg:phone":"+32 495 89 80 60",
    "sg:postcode":"1348",
    "sg:province":"Brabant Wallon",
    "sg:tags":[
        "gardening",
        "garden",
        "maintenance"
    ],
    "wof:name":"Jardins Amenia Entret",
    "wof:placetype":"venue"
},
  "geometry": {"coordinates":[4.6155028343,50.671913147],"type":"Point"}
}