{
  "type": "Feature",
  "properties": {
    "addr:full":"Humbeeksesteenweg 233 Grimbergen Vlaams-Brabant 1850",
    "addr:housenumber":"233",
    "addr:postcode":"1850",
    "addr:street":"Humbeeksesteenweg",
    "iso:country":"BE",
    "sg:address":"Humbeeksesteenweg 233",
    "sg:city":"Grimbergen",
    "sg:orig_category":"Groententeelt",
    "sg:phone":"+32 2 251 45 71",
    "sg:postcode":"1850",
    "sg:province":"Vlaams-Brabant",
    "wof:name":"Francois Van Lint",
    "wof:placetype":"venue"
},
  "geometry": {"coordinates":[4.3982200623,50.9437217712],"type":"Point"}
}