{
  "type": "Feature",
  "properties": {
    "iso:country":"BE",
    "sg:address":"Chauss\u00c9e De Braine 47",
    "sg:city":"Soignies",
    "sg:orig_category":"Rusthuizen and serviceflats",
    "sg:phone":"+32 67 34 82 00",
    "sg:postcode":"7060",
    "sg:province":"Hainaut",
    "wof:name":"Maison De Repos",
    "wof:placetype":"venue"
},
  "geometry": {"coordinates":[4.0776400566,50.5814285278],"type":"Point"}
}