{
  "type": "Feature",
  "properties": {
    "addr:full":"Rozelaarstraat 18 Ninove Oost-Vlaanderen 9400",
    "addr:housenumber":"18",
    "addr:postcode":"9400",
    "addr:street":"Rozelaarstraat",
    "iso:country":"BE",
    "sg:address":"Rozelaarstraat 18",
    "sg:city":"Ninove",
    "sg:orig_category":"Eleveurs de bovins",
    "sg:phone":"+32 54 33 36 62",
    "sg:postcode":"9400",
    "sg:province":"Oost-Vlaanderen",
    "wof:name":"Willy Vanderlinden",
    "wof:placetype":"venue"
},
  "geometry": {"coordinates":[4.0270299911,50.7893447876],"type":"Point"}
}