{
  "type": "Feature",
  "properties": {
    "addr:full":"Rue Des Fabriques 28-30 Bruxelles Bruxelles-Capitale 1000",
    "addr:postcode":"28-30;1000",
    "addr:street":"Rue Des Fabriques",
    "iso:country":"BE",
    "sg:address":"Rue Des Fabriques 28-30",
    "sg:city":"Bruxelles",
    "sg:classifiers":[
        {
            "category":"Professional",
            "subcategory":"Art Services",
            "type":"Services"
        }
    ],
    "sg:phone":"+32 2 513 28 38",
    "sg:postcode":"1000",
    "sg:province":"Bruxelles-Capitale",
    "sg:tags":[
        "automobile",
        "transit",
        "-",
        "export",
        "import"
    ],
    "wof:name":"Car Trends International",
    "wof:placetype":"venue"
},
  "geometry": {"coordinates":[4.3416028023,50.8484611511],"type":"Point"}
}