{
  "type": "Feature",
  "properties": {
    "addr:full":"Rue Des Deux Gares 80 Bruxelles (anderlecht) Bruxelles-Capitale 1070",
    "addr:housenumber":"80",
    "addr:postcode":"1070",
    "addr:street":"Rue Des Deux Gares",
    "iso:country":"BE",
    "sg:address":"Rue Des Deux Gares 80",
    "sg:city":"Bruxelles (anderlecht)",
    "sg:orig_category":"Non-Classified Establishments",
    "sg:phone":"+32 2 525 62 50",
    "sg:postcode":"1070",
    "sg:province":"Bruxelles-Capitale",
    "wof:name":"Philips Communication Security & Imaging",
    "wof:placetype":"venue"
},
  "geometry": {"coordinates":[4.3277158737,50.8323402405],"type":"Point"}
}