{
  "type": "Feature",
  "properties": {
    "addr:full":"Zuidstraat 19 Torhout West-Vlaanderen 8820",
    "addr:housenumber":"19",
    "addr:postcode":"8820",
    "addr:street":"Zuidstraat",
    "iso:country":"BE",
    "sg:address":"Zuidstraat 19",
    "sg:city":"Torhout",
    "sg:orig_category":"Dameskledingzaken Kleding",
    "sg:phone":"+32 50 21 30 62",
    "sg:postcode":"8820",
    "sg:province":"West-Vlaanderen",
    "wof:name":"Couture Versailles",
    "wof:placetype":"venue"
},
  "geometry": {"coordinates":[3.101829052,51.0637168884],"type":"Point"}
}