{
  "type": "Feature",
  "properties": {
    "addr:full":"Lange Munte 36 Oosterzele Oost-Vlaanderen 9860",
    "addr:housenumber":"36",
    "addr:postcode":"9860",
    "addr:street":"Lange Munte;Oost-Vlaanderen",
    "iso:country":"BE",
    "sg:address":"Lange Munte 36",
    "sg:city":"Oosterzele",
    "sg:orig_category":"Loodgieterij, verwarming and sanitaire installaties",
    "sg:phone":"+32 9 362 64 00",
    "sg:postcode":"9860",
    "sg:province":"Oost-Vlaanderen",
    "wof:name":"De Pelseneer E. & Zn",
    "wof:placetype":"venue"
},
  "geometry": {"coordinates":[3.7661919594,50.9286308289],"type":"Point"}
}