{
  "type": "Feature",
  "properties": {
    "addr:full":"Leemstraat 75 Sint-katelijne-waver Antwerpen 2861",
    "addr:housenumber":"75",
    "addr:postcode":"2861",
    "addr:street":"Leemstraat",
    "iso:country":"BE",
    "sg:address":"Leemstraat 75",
    "sg:city":"Sint-katelijne-waver",
    "sg:orig_category":"Ordinateurs and \u00e9quipement informatique",
    "sg:phone":"+32 15 75 49 11",
    "sg:postcode":"2861",
    "sg:province":"Antwerpen",
    "wof:name":"Myrdhin",
    "wof:placetype":"venue"
},
  "geometry": {"coordinates":[4.5900769234,51.059173584],"type":"Point"}
}