{
  "type": "Feature",
  "properties": {
    "iso:country":"BE",
    "sg:address":"Jean B\u00e9thunestraat 1",
    "sg:city":"Gent (sint-amandsberg)",
    "sg:classifiers":[
        {
            "category":"Bakery",
            "type":"Food & Drink"
        }
    ],
    "sg:phone":"+32 9 228 22 33",
    "sg:postcode":"9040",
    "sg:province":"Oost-Vlaanderen",
    "sg:tags":[
        "confectioner",
        "baker"
    ],
    "wof:name":"De Deurwaerder A",
    "wof:placetype":"venue"
},
  "geometry": {"coordinates":[3.7468760014,51.0544929504],"type":"Point"}
}