{
  "type": "Feature",
  "properties": {
    "addr:full":"De Villegas De Clercampstraat 177 Grimbergen (strombeek-bever) Vlaams-Brabant 1853",
    "addr:housenumber":"177",
    "addr:postcode":"1853",
    "addr:street":"De Villegas De Clercampstraat",
    "iso:country":"BE",
    "sg:address":"De Villegas De Clercampstraat 177",
    "sg:city":"Grimbergen (strombeek-bever)",
    "sg:classifiers":[
        {
            "category":"Health Services",
            "subcategory":"Doctor",
            "type":"Services"
        }
    ],
    "sg:phone":"+32 2 267 68 99",
    "sg:postcode":"1853",
    "sg:province":"Vlaams-Brabant",
    "sg:tags":[
        "medicinephysicians",
        "surgeon"
    ],
    "wof:name":"Goossens M Mevr",
    "wof:placetype":"venue"
},
  "geometry": {"coordinates":[4.3469290733,50.9085960388],"type":"Point"}
}