{
  "type": "Feature",
  "properties": {
    "addr:full":"Kardinaal Micaralaan 6 Oudergem/auderghem Bruxelles-Capitale 1160",
    "addr:housenumber":"6",
    "addr:postcode":"1160",
    "addr:street":"Kardinaal Micaralaan;/",
    "iso:country":"BE",
    "sg:address":"Kardinaal Micaralaan 6",
    "sg:city":"Oudergem/auderghem",
    "sg:orig_category":"Dierenartsen",
    "sg:phone":"+32 2 673 51 52",
    "sg:postcode":"1160",
    "sg:province":"Bruxelles-Capitale",
    "wof:name":"Jacques Suain",
    "wof:placetype":"venue"
},
  "geometry": {"coordinates":[4.4371910095,50.8184432983],"type":"Point"}
}