{
  "type": "Feature",
  "properties": {
    "addr:full":"Broekbosstraat 8 Kontich Antwerpen 2550",
    "addr:housenumber":"8",
    "addr:postcode":"2550",
    "addr:street":"Broekbosstraat",
    "iso:country":"BE",
    "sg:address":"Broekbosstraat 8",
    "sg:city":"Kontich",
    "sg:classifiers":[
        {
            "category":"Professional",
            "subcategory":"Art Services",
            "type":"Services"
        }
    ],
    "sg:phone":"+32 3 457 76 96",
    "sg:postcode":"2550",
    "sg:province":"Antwerpen",
    "sg:tags":[
        "-",
        "painter",
        "artist"
    ],
    "wof:name":"Walter Sijs",
    "wof:placetype":"venue"
},
  "geometry": {"coordinates":[4.4670119286,51.1341056824],"type":"Point"}
}