{
  "type": "Feature",
  "properties": {
    "iso:country":"BE",
    "sg:address":"Molenstraat 7",
    "sg:city":"Wichelen",
    "sg:orig_category":"Afbraak- and draineerwerken Antiek",
    "sg:phone":"+32 9 369 29 10",
    "sg:postcode":"9260",
    "sg:province":"Oost-Vlaanderen",
    "wof:name":"De Ridder En Zonen",
    "wof:placetype":"venue"
},
  "geometry": {"coordinates":[3.916572094,51.0096702576],"type":"Point"}
}