{
  "type": "Feature",
  "properties": {
    "addr:full":"Kasteelstraat 97 Tielt West-Vlaanderen 8700",
    "addr:housenumber":"97",
    "addr:postcode":"8700",
    "addr:street":"Kasteelstraat",
    "iso:country":"BE",
    "sg:address":"Kasteelstraat 97",
    "sg:city":"Tielt",
    "sg:classifiers":[
        {
            "category":"Wholesale",
            "subcategory":"Books, Periodicals, & Newspapers",
            "type":"Manufacturing & Wholesale Goods"
        }
    ],
    "sg:phone":"+32 51 42 42 11",
    "sg:postcode":"8700",
    "sg:province":"West-Vlaanderen",
    "sg:tags":[
        "publisher"
    ],
    "wof:name":"Lannoo Editions",
    "wof:placetype":"venue"
},
  "geometry": {"coordinates":[3.3214590549,50.9919395447],"type":"Point"}
}