{
  "type": "Feature",
  "properties": {
    "iso:country":"BE",
    "sg:address":"Grand'rue 74",
    "sg:city":"Antoing",
    "sg:classifiers":[
        {
            "category":"Real Estate",
            "subcategory":"Real Estate Services",
            "type":"Services"
        }
    ],
    "sg:phone":"+32 69 44 13 01",
    "sg:postcode":"7640",
    "sg:province":"Hainaut",
    "wof:name":"Valemberg Immobilier",
    "wof:placetype":"venue"
},
  "geometry": {"coordinates":[3.503205061,50.542514801],"type":"Point"}
}