{
  "type": "Feature",
  "properties": {
    "iso:country":"BE",
    "sg:address":"Hofdreef 55",
    "sg:city":"Kasterlee",
    "sg:orig_category":"Gespecialiseerde residenti\u00eble bouw",
    "sg:phone":"+32 14 55 62 22",
    "sg:postcode":"2460",
    "sg:province":"Antwerpen",
    "wof:name":"Thys J. & Zn",
    "wof:placetype":"venue"
},
  "geometry": {"coordinates":[4.8969211578,51.2493934631],"type":"Point"}
}