{
  "type": "Feature",
  "properties": {
    "addr:full":"Rue De L'ecole 15 Chaumont-gistoux (dion-valmont) Brabant Wallon 1325",
    "addr:housenumber":"15;1325",
    "addr:street":"Rue De L'Ecole;Dion-Valmont;Wallon",
    "iso:country":"BE",
    "sg:address":"Rue De L'ecole 15",
    "sg:city":"Chaumont-gistoux (dion-valmont)",
    "sg:classifiers":[
        {
            "category":"Banks & Credit Unions",
            "subcategory":"Financial Services",
            "type":"Services"
        }
    ],
    "sg:phone":"+32 10 24 25 25",
    "sg:postcode":"1325",
    "sg:province":"Brabant Wallon",
    "sg:tags":[
        "loan",
        "mortgage"
    ],
    "wof:name":"Cr\u00e9diconseil Scrl",
    "wof:placetype":"venue"
},
  "geometry": {"coordinates":[4.7142491341,50.7195053101],"type":"Point"}
}