{
  "type": "Feature",
  "properties": {
    "addr:full":"Schendekouterstraat 28 Wervik West-Vlaanderen 8940",
    "addr:housenumber":"28",
    "addr:postcode":"8940",
    "addr:street":"Schendekouterstraat",
    "iso:country":"BE",
    "sg:address":"Schendekouterstraat 28",
    "sg:city":"Wervik",
    "sg:orig_category":"Varkenskwekers",
    "sg:phone":"+32 56 51 18 17",
    "sg:postcode":"8940",
    "sg:province":"West-Vlaanderen",
    "wof:name":"Walther Decruyenaere",
    "wof:placetype":"venue"
},
  "geometry": {"coordinates":[3.1013309956,50.8221588135],"type":"Point"}
}