{
  "type": "Feature",
  "properties": {
    "iso:country":"BE",
    "sg:address":"Grand'place 22",
    "sg:city":"Leuze-en-hainaut",
    "sg:orig_category":"Kapsalons",
    "sg:phone":"+32 69 66 24 00",
    "sg:postcode":"7900",
    "sg:province":"Hainaut",
    "wof:name":"Coiffure Leonce & Natacha",
    "wof:placetype":"venue"
},
  "geometry": {"coordinates":[3.6204679012,50.6003341675],"type":"Point"}
}