{
  "type": "Feature",
  "properties": {
    "iso:country":"BE",
    "sg:address":"Rue De Marcasse 74",
    "sg:city":"Colfontaine",
    "sg:orig_category":"Dakwerken",
    "sg:phone":"+32 65 66 38 28",
    "sg:postcode":"7340",
    "sg:province":"Hainaut",
    "wof:name":"J.i.g.e.",
    "wof:placetype":"venue"
},
  "geometry": {"coordinates":[3.8302299976,50.4109306335],"type":"Point"}
}