{
  "type": "Feature",
  "properties": {
    "addr:full":"Rue De La Tulipe 17 Bruxelles (ixelles) Bruxelles-Capitale 1050",
    "addr:housenumber":"17",
    "addr:postcode":"1050",
    "addr:street":"Rue De La Tulipe",
    "iso:country":"BE",
    "sg:address":"Rue De La Tulipe 17",
    "sg:city":"Bruxelles (ixelles)",
    "sg:classifiers":[
        {
            "category":"Health Services",
            "subcategory":"Health Practitioner",
            "type":"Services"
        }
    ],
    "sg:phone":"+32 2 502 51 31",
    "sg:postcode":"1050",
    "sg:province":"Bruxelles-Capitale",
    "sg:tags":[
        "physiotherapist"
    ],
    "wof:name":"Bodart Wivine",
    "wof:placetype":"venue"
},
  "geometry": {"coordinates":[4.3671050072,50.834022522],"type":"Point"}
}