{
  "type": "Feature",
  "properties": {
    "iso:country":"BE",
    "sg:address":"Broekstraat 1",
    "sg:city":"Beveren",
    "sg:orig_category":"Eleveurs and marchands de porcs. Eleveurs de bovins",
    "sg:phone":"+32 3 775 60 25",
    "sg:postcode":"9120",
    "sg:province":"Oost-Vlaanderen",
    "wof:name":"Maurits De Bock",
    "wof:placetype":"venue"
},
  "geometry": {"coordinates":[4.2233638763,51.2310180664],"type":"Point"}
}