{
  "type": "Feature",
  "properties": {
    "iso:country":"BE",
    "sg:address":"Rue De L'am\u00c9rique 55",
    "sg:city":"Charleroi",
    "sg:orig_category":"Kapsalons",
    "sg:phone":"+32 71 36 63 69",
    "sg:postcode":"6010",
    "sg:province":"Hainaut",
    "wof:name":"Coiffure Arlette",
    "wof:placetype":"venue"
},
  "geometry": {"coordinates":[4.4619679451,50.3813667297],"type":"Point"}
}