{
  "type": "Feature",
  "properties": {
    "addr:full":"Chauss\u00c9e D'audenarde 352 Pecq Hainaut 7742",
    "addr:housenumber":"352",
    "addr:postcode":"7742",
    "addr:street":"Chausse\u0301E D'Audenarde",
    "iso:country":"BE",
    "sg:address":"Chauss\u00c9e D'audenarde 352",
    "sg:city":"Pecq",
    "sg:classifiers":[
        {
            "category":"Cafe",
            "type":"Food & Drink"
        }
    ],
    "sg:phone":"+32 69 55 90 64",
    "sg:postcode":"7742",
    "sg:province":"Hainaut",
    "sg:tags":[
        "caf\u00e9s"
    ],
    "wof:name":"Luc Malghem",
    "wof:placetype":"venue"
},
  "geometry": {"coordinates":[3.3640599251,50.7021865845],"type":"Point"}
}