{
  "type": "Feature",
  "properties": {
    "addr:full":"Chemin Du Four 29 Namur (malonne) Namur 5020",
    "addr:housenumber":"29",
    "addr:postcode":"5020",
    "addr:street":"Chemin Du Four",
    "iso:country":"BE",
    "sg:address":"Chemin Du Four 29",
    "sg:city":"Namur (malonne)",
    "sg:classifiers":[
        {
            "category":"Building & Trades",
            "subcategory":"Pest Control",
            "type":"Services"
        }
    ],
    "sg:phone":"+32 81 44 05 64",
    "sg:postcode":"5020",
    "sg:province":"Namur",
    "sg:tags":[
        "painting",
        "contractor"
    ],
    "wof:name":"Entreprise Ronchi",
    "wof:placetype":"venue"
},
  "geometry": {"coordinates":[4.7952418327,50.4352035522],"type":"Point"}
}