{
  "type": "Feature",
  "properties": {
    "addr:full":"Kerkstraat 23 Knokke-heist West-Vlaanderen 8301",
    "addr:housenumber":"23",
    "addr:postcode":"8301",
    "addr:street":"Kerkstraat",
    "iso:country":"BE",
    "sg:address":"Kerkstraat 23",
    "sg:city":"Knokke-heist",
    "sg:orig_category":"Herstelling leer and schoeisel",
    "sg:phone":"+32 50 51 63 63",
    "sg:postcode":"8301",
    "sg:province":"West-Vlaanderen",
    "wof:name":"Huis Geert",
    "wof:placetype":"venue"
},
  "geometry": {"coordinates":[3.2639000416,51.3396911621],"type":"Point"}
}