{
  "type": "Feature",
  "properties": {
    "iso:country":"BE",
    "sg:address":"Rue Du Pont 16",
    "sg:city":"Hamoir",
    "sg:classifiers":[
        {
            "category":"Health Services",
            "subcategory":"Dentist",
            "type":"Services"
        }
    ],
    "sg:phone":"+32 86 38 96 99",
    "sg:postcode":"4180",
    "sg:province":"Li\u00e8ge",
    "wof:name":"Hermia Anne-fran\u00e7oise",
    "wof:placetype":"venue"
},
  "geometry": {"coordinates":[5.5346899033,50.4262161255],"type":"Point"}
}