{
  "type": "Feature",
  "properties": {
    "iso:country":"BE",
    "sg:address":"Rue De L'abbaye 140",
    "sg:city":"Herstal",
    "sg:orig_category":"Airconditioning and ventilatie Winkelinrichting and handelsuitrusting Gh",
    "sg:phone":"+32 4 248 34 17",
    "sg:postcode":"4040",
    "sg:province":"Li\u00e8ge",
    "wof:name":"R\u00c9fricar",
    "wof:placetype":"venue"
},
  "geometry": {"coordinates":[5.6297369003,50.6961860657],"type":"Point"}
}