{
  "type": "Feature",
  "properties": {
    "iso:country":"BE",
    "sg:address":"Hendrik Van Veldekesingel 150 Box 46",
    "sg:city":"Hasselt",
    "sg:classifiers":[
        {
            "category":"Wholesale",
            "subcategory":"Books, Periodicals, & Newspapers",
            "type":"Manufacturing & Wholesale Goods"
        }
    ],
    "sg:phone":"+32 11 87 08 91",
    "sg:postcode":"3500",
    "sg:province":"Limburg",
    "sg:tags":[
        "publisher"
    ],
    "wof:name":"Publi Center Bvba",
    "wof:placetype":"venue"
},
  "geometry": {"coordinates":[5.3152570724,50.9355430603],"type":"Point"}
}