{
  "type": "Feature",
  "properties": {
    "addr:full":". Crisn\u00c9e (groot) Li\u00e8ge 4367",
    "addr:postcode":"4367",
    "addr:street":"Groot Lie\u0300Ge",
    "iso:country":"BE",
    "sg:address":".",
    "sg:city":"Crisn\u00c9e (groot)",
    "sg:orig_category":"Apotheken",
    "sg:phone":"+32 900 10 500",
    "sg:postcode":"4367",
    "sg:province":"Li\u00e8ge",
    "wof:name":"Apothekers Van Wacht",
    "wof:placetype":"venue"
},
  "geometry": {"coordinates":[5.3976340294,50.716632843],"type":"Point"}
}