{
  "type": "Feature",
  "properties": {
    "addr:full":"Begijnengracht 64 Gent Oost-Vlaanderen 9000",
    "addr:housenumber":"64",
    "addr:postcode":"9000",
    "addr:street":"Begijnengracht;Oost-Vlaanderen",
    "iso:country":"BE",
    "sg:address":"Begijnengracht 64",
    "sg:city":"Gent",
    "sg:orig_category":"Paramedische behandelingen",
    "sg:phone":"+32 9 233 76 21",
    "sg:postcode":"9000",
    "sg:province":"Oost-Vlaanderen",
    "wof:name":"A. Vastmans",
    "wof:placetype":"venue"
},
  "geometry": {"coordinates":[3.7124459743,51.0563240051],"type":"Point"}
}