{
  "type": "Feature",
  "properties": {
    "addr:full":"Kasteelstraat 24 Duffel Antwerpen 2570",
    "addr:housenumber":"24",
    "addr:postcode":"2570",
    "addr:street":"Kasteelstraat",
    "iso:country":"BE",
    "sg:address":"Kasteelstraat 24",
    "sg:city":"Duffel",
    "sg:orig_category":"Enseignement maternel and primaire",
    "sg:phone":"+32 15 31 85 00",
    "sg:postcode":"2570",
    "sg:province":"Antwerpen",
    "wof:name":"B.s.b.o.",
    "wof:placetype":"venue"
},
  "geometry": {"coordinates":[4.4975471497,51.095375061],"type":"Point"}
}