{
  "type": "Feature",
  "properties": {
    "addr:full":"Paalstraat 285 Schoten Antwerpen 2900",
    "addr:housenumber":"285",
    "addr:postcode":"2900",
    "addr:street":"Paalstraat",
    "iso:country":"BE",
    "sg:address":"Paalstraat 285",
    "sg:city":"Schoten",
    "sg:orig_category":"Enseignement maternel and primaire",
    "sg:phone":"+32 3 658 79 45",
    "sg:postcode":"2900",
    "sg:province":"Antwerpen",
    "wof:name":"Vrije Basisschool",
    "wof:placetype":"venue"
},
  "geometry": {"coordinates":[4.5063171387,51.2596244812],"type":"Point"}
}