{
  "type": "Feature",
  "properties": {
    "addr:full":"Steenweg Op Turnhout 117 Merksplas Antwerpen 2330",
    "addr:housenumber":"117",
    "addr:postcode":"2330",
    "addr:street":"Steenweg Op Turnhout",
    "iso:country":"BE",
    "sg:address":"Steenweg Op Turnhout 117",
    "sg:city":"Merksplas",
    "sg:classifiers":[
        {
            "category":"Banks & Credit Unions",
            "subcategory":"Investment Brokerage",
            "type":"Services"
        }
    ],
    "sg:phone":"+32 14 71 04 25",
    "sg:postcode":"2330",
    "sg:province":"Antwerpen",
    "sg:tags":[
        "repair",
        "-",
        "installation",
        "sanitary",
        "article"
    ],
    "wof:name":"Ne-re-build Bvba",
    "wof:placetype":"venue"
},
  "geometry": {"coordinates":[4.8757162094,51.3495597839],"type":"Point"}
}