{
  "type": "Feature",
  "properties": {
    "addr:full":"Kattenberg 19 Antwerpen Antwerpen 2140",
    "addr:housenumber":"19",
    "addr:postcode":"2140",
    "addr:street":"Kattenberg",
    "iso:country":"BE",
    "sg:address":"Kattenberg 19",
    "sg:city":"Antwerpen",
    "sg:orig_category":"Agences de publicit\u00e9. Bureaux d'\u00e9tudes de march\u00e9. Services de publipostage",
    "sg:phone":"+32 3 235 09 02",
    "sg:postcode":"2140",
    "sg:province":"Antwerpen",
    "wof:name":"Multilist",
    "wof:placetype":"venue"
},
  "geometry": {"coordinates":[4.4116339684,51.2216720581],"type":"Point"}
}