{
  "type": "Feature",
  "properties": {
    "iso:country":"BE",
    "sg:address":"Rue D'anderlues 138",
    "sg:city":"Morlanwelz",
    "sg:classifiers":[
        {
            "category":"Manufacturing",
            "subcategory":"Metals",
            "type":"Manufacturing & Wholesale Goods"
        }
    ],
    "sg:phone":"+32 64 43 14 00",
    "sg:postcode":"7140",
    "sg:province":"Hainaut",
    "sg:tags":[
        "processing"
    ],
    "wof:name":"Eav S.a.",
    "wof:placetype":"venue"
},
  "geometry": {"coordinates":[4.2687897682,50.4625015259],"type":"Point"}
}