{
  "type": "Feature",
  "properties": {
    "iso:country":"BE",
    "sg:address":"Interleuvenlaan 62",
    "sg:city":"Leuven",
    "sg:classifiers":[
        {
            "category":"Banks & Credit Unions",
            "subcategory":"Atm",
            "type":"Services"
        }
    ],
    "sg:phone":"+32 16 40 02 18",
    "sg:postcode":"3001",
    "sg:province":"Vlaams-Brabant",
    "sg:tags":[
        "d'entreprises",
        "de",
        "bureau"
    ],
    "wof:name":"Bedrijvencentrum Leuven",
    "wof:placetype":"venue"
},
  "geometry": {"coordinates":[4.7360210419,50.849067688],"type":"Point"}
}