{
  "type": "Feature",
  "properties": {
    "iso:country":"BE",
    "sg:address":"Raapbreukstraat 18",
    "sg:city":"Herentals",
    "sg:orig_category":"Non-Classified Establishments",
    "sg:phone":"+32 14 70 71 36",
    "sg:postcode":"2200",
    "sg:province":"Antwerpen",
    "wof:name":"Wafelhuisje ('t)",
    "wof:placetype":"venue"
},
  "geometry": {"coordinates":[4.8406319618,51.1883430481],"type":"Point"}
}