{
  "type": "Feature",
  "properties": {
    "iso:country":"BE",
    "sg:address":"Chemin Des Pr\u00c9s 14",
    "sg:city":"Beauvechain",
    "sg:orig_category":"Installatie van houten of kunststof schrijnwerk",
    "sg:phone":"+32 10 86 13 85",
    "sg:postcode":"1320",
    "sg:province":"Brabant Wallon",
    "wof:name":"Bernard Hotat",
    "wof:placetype":"venue"
},
  "geometry": {"coordinates":[4.7366080284,50.7744636536],"type":"Point"}
}