{
  "type": "Feature",
  "properties": {
    "iso:country":"BE",
    "sg:address":"Emsenslaan 30",
    "sg:city":"Mol",
    "sg:orig_category":"Sportclubs",
    "sg:phone":"+32 14 81 10 67",
    "sg:postcode":"2400",
    "sg:province":"Antwerpen",
    "wof:name":"De Blauwe Duif",
    "wof:placetype":"venue"
},
  "geometry": {"coordinates":[5.212952137,51.2187995911],"type":"Point"}
}