{
  "type": "Feature",
  "properties": {
    "iso:country":"BE",
    "sg:address":"Koning Albertstraat 12",
    "sg:city":"Waregem (beveren-leie)",
    "sg:classifiers":[
        {
            "category":"Professional",
            "subcategory":"Management & Consulting",
            "type":"Services"
        }
    ],
    "sg:phone":"+32 56 60 78 78",
    "sg:postcode":"8791",
    "sg:province":"West-Vlaanderen",
    "sg:tags":[
        "consultant",
        "law"
    ],
    "wof:name":"J.b.f.",
    "wof:placetype":"venue"
},
  "geometry": {"coordinates":[3.3448650837,50.8743438721],"type":"Point"}
}