{
  "type": "Feature",
  "properties": {
    "addr:full":"Daaleindestraat 79 Kortessem Limburg 3720",
    "addr:housenumber":"79",
    "addr:postcode":"3720",
    "addr:street":"Daaleindestraat",
    "iso:country":"BE",
    "sg:address":"Daaleindestraat 79",
    "sg:city":"Kortessem",
    "sg:orig_category":"Quincailleries. Charpentes and couvertures",
    "sg:phone":"+32 11 37 53 48",
    "sg:postcode":"3720",
    "sg:province":"Limburg",
    "wof:name":"Bouwmarkt Ketelslegers",
    "wof:placetype":"venue"
},
  "geometry": {"coordinates":[5.4020972252,50.8652763367],"type":"Point"}
}