{
  "type": "Feature",
  "properties": {
    "addr:full":"Vrijheidsplein 19b1 Lokeren Oost-Vlaanderen 9160",
    "addr:housenumber":"19b1",
    "addr:postcode":"9160",
    "addr:street":"Vrijheidsplein",
    "iso:country":"BE",
    "sg:address":"Vrijheidsplein 19b1",
    "sg:city":"Lokeren",
    "sg:orig_category":"Immobili\u00ebnkantoren",
    "sg:phone":"+32 9 349 29 50",
    "sg:postcode":"9160",
    "sg:province":"Oost-Vlaanderen",
    "wof:name":"Immo Marc Everaert",
    "wof:placetype":"venue"
},
  "geometry": {"coordinates":[3.9867749214,51.1014595032],"type":"Point"}
}