{
  "type": "Feature",
  "properties": {
    "iso:country":"BE",
    "sg:address":"Chaussee De Tongres 259 (cora)",
    "sg:city":"Liege",
    "sg:orig_category":"Telecommunicatieapparaten",
    "sg:phone":"+32 4 239 89 60",
    "sg:postcode":"4000",
    "sg:province":"Li\u00e8ge",
    "wof:name":"The Phone House",
    "wof:placetype":"venue"
},
  "geometry": {"coordinates":[5.5500450134,50.6698379517],"type":"Point"}
}