{
  "type": "Feature",
  "properties": {
    "addr:full":"Rue D'ath 51 Chi\u00e8vres Hainaut 7950",
    "addr:housenumber":"51",
    "addr:postcode":"7950",
    "addr:street":"Rue D'Ath;Hainaut",
    "iso:country":"BE",
    "sg:address":"Rue D'ath 51",
    "sg:city":"Chi\u00e8vres",
    "sg:classifiers":[
        {
            "category":"Community Center",
            "subcategory":"Youth",
            "type":"Public Place"
        }
    ],
    "sg:phone":"+32 68 65 84 24",
    "sg:postcode":"7950",
    "sg:province":"Hainaut",
    "sg:tags":[
        "club"
    ],
    "wof:name":"Cellule D'intervention Lecture-ecriture Sociale Asbl",
    "wof:placetype":"venue"
},
  "geometry": {"coordinates":[3.8057699203,50.593120575],"type":"Point"}
}