{
  "type": "Feature",
  "properties": {
    "iso:country":"BE",
    "sg:address":"Rue St.-jean N\u00c9pomuc\u00c8ne 30",
    "sg:city":"Brussel/bruxelles",
    "sg:orig_category":"M\u00e9decins and sp\u00e9cialistes",
    "sg:phone":"+32 2 219 48 66",
    "sg:postcode":"1000",
    "sg:province":"Bruxelles-Capitale",
    "wof:name":"Michel Verraes",
    "wof:placetype":"venue"
},
  "geometry": {"coordinates":[4.3531460762,50.855682373],"type":"Point"}
}