{
  "type": "Feature",
  "properties": {
    "iso:country":"BE",
    "sg:address":"Kortrijksestraat 83",
    "sg:city":"Ardooie",
    "sg:classifiers":[
        {
            "category":"Building & Trades",
            "subcategory":"Pest Control",
            "type":"Services"
        }
    ],
    "sg:phone":"+32 51 74 47 28",
    "sg:postcode":"8850",
    "sg:province":"West-Vlaanderen",
    "sg:tags":[
        "painting",
        "contractor"
    ],
    "wof:name":"Kindt Decoratiebedrijf Bvba",
    "wof:placetype":"venue"
},
  "geometry": {"coordinates":[3.1970469952,50.9745063782],"type":"Point"}
}