{
  "type": "Feature",
  "properties": {
    "iso:country":"BE",
    "sg:address":"Galgstraat 15",
    "sg:city":"Sint-niklaas",
    "sg:classifiers":[
        {
            "category":"Building & Trades",
            "subcategory":"Construction",
            "type":"Services"
        }
    ],
    "sg:phone":"+32 3 777 73 46",
    "sg:postcode":"9100",
    "sg:province":"Oost-Vlaanderen",
    "sg:tags":[
        "scaffolding"
    ],
    "wof:name":"Jedy",
    "wof:placetype":"venue"
},
  "geometry": {"coordinates":[4.1850848198,51.1502113342],"type":"Point"}
}