{
  "type": "Feature",
  "properties": {
    "addr:full":"Rue De La L\u00e9gia 62b Ans Li\u00e8ge 4430",
    "addr:housenumber":"62b",
    "addr:postcode":"4430",
    "addr:street":"Rue De La Le\u0301Gia",
    "iso:country":"BE",
    "sg:address":"Rue De La L\u00e9gia 62b",
    "sg:city":"Ans",
    "sg:classifiers":[
        {
            "category":"Professional",
            "type":"Services"
        }
    ],
    "sg:phone":"+32 4 226 73 17",
    "sg:postcode":"4430",
    "sg:province":"Li\u00e8ge",
    "sg:tags":[
        "entertainer"
    ],
    "wof:name":"Henderson Gianni",
    "wof:placetype":"venue"
},
  "geometry": {"coordinates":[5.5474820137,50.6508674622],"type":"Point"}
}