{
  "type": "Feature",
  "properties": {
    "addr:full":"Korte Massemsesteenweg 29b Wetteren Oost-Vlaanderen 9230",
    "addr:housenumber":"29b",
    "addr:postcode":"9230",
    "addr:street":"Korte Massemsesteenweg",
    "iso:country":"BE",
    "sg:address":"Korte Massemsesteenweg 29b",
    "sg:city":"Wetteren",
    "sg:classifiers":[
        {
            "category":"Bakery",
            "type":"Food & Drink"
        }
    ],
    "sg:phone":"+32 9 369 95 01",
    "sg:postcode":"9230",
    "sg:province":"Oost-Vlaanderen",
    "sg:tags":[
        "confectioner",
        "baker"
    ],
    "wof:name":"Van Imschoot M",
    "wof:placetype":"venue"
},
  "geometry": {"coordinates":[3.8830759525,51.0002403259],"type":"Point"}
}