{
  "type": "Feature",
  "properties": {
    "addr:full":"Boekweitstraat 1 Jabbeke West-Vlaanderen 8490",
    "addr:housenumber":"1",
    "addr:postcode":"8490",
    "addr:street":"Boekweitstraat",
    "iso:country":"BE",
    "sg:address":"Boekweitstraat 1",
    "sg:city":"Jabbeke",
    "sg:orig_category":"Woningbouw",
    "sg:phone":"+32 50 81 19 18",
    "sg:postcode":"8490",
    "sg:province":"West-Vlaanderen",
    "wof:name":"Gunther Jonckheere",
    "wof:placetype":"venue"
},
  "geometry": {"coordinates":[3.0838699341,51.1752586365],"type":"Point"}
}