{
  "type": "Feature",
  "properties": {
    "addr:full":"Bavegemstraat 61a Oosterzele Oost-Vlaanderen 9860",
    "addr:housenumber":"61a",
    "addr:postcode":"9860",
    "addr:street":"Bavegemstraat;Oost-Vlaanderen",
    "iso:country":"BE",
    "sg:address":"Bavegemstraat 61a",
    "sg:city":"Oosterzele",
    "sg:classifiers":[
        {
            "category":"Retail",
            "subcategory":"Funeral Services",
            "type":"Services"
        }
    ],
    "sg:phone":"+32 9 362 45 30",
    "sg:postcode":"9860",
    "sg:province":"Oost-Vlaanderen",
    "sg:tags":[
        "director"
    ],
    "wof:name":"Vandekerckhove Bvba",
    "wof:placetype":"venue"
},
  "geometry": {"coordinates":[3.8371379375,50.9528274536],"type":"Point"}
}