{
  "type": "Feature",
  "properties": {
    "addr:full":"Rue Des Ch\u00c2taignes 17 Vorst/forest Bruxelles-Capitale 1190",
    "addr:housenumber":"17",
    "addr:postcode":"1190",
    "addr:street":"Rue Des Cha\u0302Taignes;/ Forest",
    "iso:country":"BE",
    "sg:address":"Rue Des Ch\u00c2taignes 17",
    "sg:city":"Vorst/forest",
    "sg:orig_category":"M\u00e9decins and sp\u00e9cialistes",
    "sg:phone":"+32 2 347 19 78",
    "sg:postcode":"1190",
    "sg:province":"Bruxelles-Capitale",
    "wof:name":"Danielle Ooghe",
    "wof:placetype":"venue"
},
  "geometry": {"coordinates":[4.326166153,50.817363739],"type":"Point"}
}