{
  "type": "Feature",
  "properties": {
    "iso:country":"BE",
    "sg:address":"Rue Grande 37",
    "sg:city":"Qui\u00e9vrain",
    "sg:classifiers":[
        {
            "category":"Professional",
            "subcategory":"Testing Lab",
            "type":"Services"
        }
    ],
    "sg:phone":"+32 65 45 75 05",
    "sg:postcode":"7380",
    "sg:province":"Hainaut",
    "sg:tags":[
        "chemist"
    ],
    "wof:name":"Dufour J",
    "wof:placetype":"venue"
},
  "geometry": {"coordinates":[3.6829218864,50.4061164856],"type":"Point"}
}