{
  "type": "Feature",
  "properties": {
    "addr:full":"Kreupelstraat 3 Kortrijk West-Vlaanderen 8510",
    "addr:housenumber":"3",
    "addr:postcode":"8510",
    "addr:street":"Kreupelstraat",
    "iso:country":"BE",
    "sg:address":"Kreupelstraat 3",
    "sg:city":"Kortrijk",
    "sg:orig_category":"Passagiersvervoer over de weg Reisbureaus",
    "sg:phone":"+32 56 22 44 09",
    "sg:postcode":"8510",
    "sg:province":"West-Vlaanderen",
    "wof:name":"Demuynck-deveugle",
    "wof:placetype":"venue"
},
  "geometry": {"coordinates":[3.3027219772,50.7818870544],"type":"Point"}
}