{
  "type": "Feature",
  "properties": {
    "iso:country":"BE",
    "sg:address":"Kolvestraat 54",
    "sg:city":"Brugge",
    "sg:orig_category":"Industri\u00eble and commerci\u00eble bouw Woningbouw",
    "sg:phone":"+32 50 31 69 11",
    "sg:postcode":"8000",
    "sg:province":"West-Vlaanderen",
    "wof:name":"Algemene Bouwonderneming Leenhouts",
    "wof:placetype":"venue"
},
  "geometry": {"coordinates":[3.2025449276,51.2426719666],"type":"Point"}
}