{
  "type": "Feature",
  "properties": {
    "iso:country":"BE",
    "sg:address":"Avenue Mozart 4",
    "sg:city":"Ukkel/uccle",
    "sg:orig_category":"M\u00e9decins and sp\u00e9cialistes",
    "sg:phone":"+32 2 346 21 76",
    "sg:postcode":"1180",
    "sg:province":"Bruxelles-Capitale",
    "wof:name":"Seyd Mohammed Fazeli",
    "wof:placetype":"venue"
},
  "geometry": {"coordinates":[4.3356738091,50.8129119873],"type":"Point"}
}