{
  "type": "Feature",
  "properties": {
    "iso:country":"BE",
    "sg:address":"Driekapellenstraat 4",
    "sg:city":"Herne (sint-pieters-kapelle)",
    "sg:classifiers":[
        {
            "category":"Health Services",
            "subcategory":"Health Practitioner",
            "type":"Services"
        }
    ],
    "sg:phone":"+32 476 89 63 78",
    "sg:postcode":"1541",
    "sg:province":"Vlaams-Brabant",
    "sg:tags":[
        "physiotherapist"
    ],
    "wof:name":"Deneyer Anje",
    "wof:placetype":"venue"
},
  "geometry": {"coordinates":[3.985599041,50.7058105469],"type":"Point"}
}