{
  "type": "Feature",
  "properties": {
    "iso:country":"BE",
    "sg:address":"Chauss\u00e9e De Saint-job 272",
    "sg:city":"Bruxelles (uccle)",
    "sg:classifiers":[
        {
            "category":"Bakery",
            "type":"Food & Drink"
        }
    ],
    "sg:phone":"+32 2 374 30 85",
    "sg:postcode":"1180",
    "sg:province":"Bruxelles-Capitale",
    "sg:tags":[
        "confectioner",
        "baker"
    ],
    "wof:name":"Ackermans",
    "wof:placetype":"venue"
},
  "geometry": {"coordinates":[4.3453688622,50.7922477722],"type":"Point"}
}