{
  "type": "Feature",
  "properties": {
    "iso:country":"BE",
    "sg:address":"Rue Du Long Thier 20",
    "sg:city":"Huy",
    "sg:classifiers":[
        {
            "category":"Professional",
            "subcategory":"Lawyer & Legal Services",
            "type":"Services"
        }
    ],
    "sg:phone":"+32 85 82 87 72",
    "sg:postcode":"4500",
    "sg:province":"Li\u00e8ge",
    "wof:name":"Laflotte Jean-philippe",
    "wof:placetype":"venue"
},
  "geometry": {"coordinates":[5.2493429184,50.5195808411],"type":"Point"}
}