{
  "type": "Feature",
  "properties": {
    "iso:country":"BE",
    "sg:address":"Kerkstraat 53",
    "sg:city":"Houthulst",
    "sg:orig_category":"Brood, gebak and snoepgoed",
    "sg:phone":"+32 51 70 05 82",
    "sg:postcode":"8650",
    "sg:province":"West-Vlaanderen",
    "wof:name":"Jackie Becue",
    "wof:placetype":"venue"
},
  "geometry": {"coordinates":[2.9466860294,50.9774093628],"type":"Point"}
}