{
  "type": "Feature",
  "properties": {
    "iso:country":"BE",
    "sg:address":"Haag 6",
    "sg:city":"Geel",
    "sg:orig_category":"Rundveehouders",
    "sg:phone":"+32 14 58 31 48",
    "sg:postcode":"2440",
    "sg:province":"Antwerpen",
    "wof:name":"Georges Vande Perre",
    "wof:placetype":"venue"
},
  "geometry": {"coordinates":[4.9287881851,51.1595687866],"type":"Point"}
}