{
  "type": "Feature",
  "properties": {
    "addr:full":"Rue Mathieu Laensbergh 38 Li\u00c8ge Li\u00e8ge 4000",
    "addr:housenumber":"38",
    "addr:postcode":"4000",
    "addr:street":"Rue Mathieu Laensbergh",
    "iso:country":"BE",
    "sg:address":"Rue Mathieu Laensbergh 38",
    "sg:city":"Li\u00c8ge",
    "sg:orig_category":"Kapsalons",
    "sg:phone":"+32 4 227 11 49",
    "sg:postcode":"4000",
    "sg:province":"Li\u00e8ge",
    "wof:name":"Coiffure Ren\u00c9e",
    "wof:placetype":"venue"
},
  "geometry": {"coordinates":[5.584842205,50.6493644714],"type":"Point"}
}