{
  "type": "Feature",
  "properties": {
    "addr:full":"Mierdsedijk 23 Ravels (poppel) Antwerpen 2382",
    "addr:housenumber":"23",
    "addr:postcode":"2382",
    "addr:street":"Mierdsedijk",
    "iso:country":"BE",
    "sg:address":"Mierdsedijk 23",
    "sg:city":"Ravels (poppel)",
    "sg:classifiers":[
        {
            "category":"Building & Trades",
            "subcategory":"Construction",
            "type":"Services"
        }
    ],
    "sg:phone":"+32 14 65 85 15",
    "sg:postcode":"2382",
    "sg:province":"Antwerpen",
    "sg:tags":[
        "ecological"
    ],
    "wof:name":"Vloemans J",
    "wof:placetype":"venue"
},
  "geometry": {"coordinates":[5.041768074,51.4469108582],"type":"Point"}
}