{
  "type": "Feature",
  "properties": {
    "addr:full":"Antwerpse Steenweg 154 Temse Oost-Vlaanderen 9140",
    "addr:housenumber":"154",
    "addr:postcode":"9140",
    "addr:street":"Antwerpse Steenweg",
    "iso:country":"BE",
    "sg:address":"Antwerpse Steenweg 154",
    "sg:city":"Temse",
    "sg:classifiers":[
        {
            "category":"Arena",
            "subcategory":"Sports Club",
            "type":"Entertainment"
        }
    ],
    "sg:phone":"+32 3 771 17 85",
    "sg:postcode":"9140",
    "sg:province":"Oost-Vlaanderen",
    "sg:tags":[
        "de"
    ],
    "wof:name":"M.t.b. De Kroonvrienden",
    "wof:placetype":"venue"
},
  "geometry": {"coordinates":[4.1852412224,51.1150245667],"type":"Point"}
}