{
  "type": "Feature",
  "properties": {
    "addr:full":"Meersstraat 44 Waregem West-Vlaanderen 8790",
    "addr:housenumber":"44",
    "addr:postcode":"8790",
    "addr:street":"Meersstraat",
    "iso:country":"BE",
    "sg:address":"Meersstraat 44",
    "sg:city":"Waregem",
    "sg:classifiers":[
        {
            "category":"Personal",
            "subcategory":"Sauna",
            "type":"Services"
        }
    ],
    "sg:phone":"+32 56 60 14 12",
    "sg:postcode":"8790",
    "sg:province":"West-Vlaanderen",
    "wof:name":"Badhuis ('t)",
    "wof:placetype":"venue"
},
  "geometry": {"coordinates":[3.4286789894,50.8847541809],"type":"Point"}
}