{
  "type": "Feature",
  "properties": {
    "addr:full":"Rue Au Vin 28 Renaix Oost-Vlaanderen 9600",
    "addr:housenumber":"28",
    "addr:postcode":"9600",
    "addr:street":"Rue Au Vin",
    "iso:country":"BE",
    "sg:address":"Rue Au Vin 28",
    "sg:city":"Renaix",
    "sg:classifiers":[
        {
            "category":"Home & Garden",
            "subcategory":"Home Furnishings",
            "type":"Retail Goods"
        }
    ],
    "sg:phone":"+32 55 20 87 57",
    "sg:postcode":"9600",
    "sg:province":"Oost-Vlaanderen",
    "sg:tags":[
        "interior",
        "decoration"
    ],
    "wof:name":"Metamorfose",
    "wof:placetype":"venue"
},
  "geometry": {"coordinates":[3.5986349583,50.7476348877],"type":"Point"}
}