{
  "type": "Feature",
  "properties": {
    "addr:full":"Avenue Des Eoliennes 8-3 Bruxelles (woluwe-saint-lambert) Bruxelles-Capitale 1200",
    "addr:housenumber":"8-3",
    "addr:postcode":"1200",
    "addr:street":"Avenue Des Eoliennes",
    "iso:country":"BE",
    "sg:address":"Avenue Des Eoliennes 8-3",
    "sg:city":"Bruxelles (woluwe-saint-lambert)",
    "sg:classifiers":[
        {
            "category":"Professional",
            "subcategory":"Management & Consulting",
            "type":"Services"
        }
    ],
    "sg:phone":"+32 2 771 00 99",
    "sg:postcode":"1200",
    "sg:province":"Bruxelles-Capitale",
    "sg:tags":[
        "consultant",
        "agency",
        "advertising"
    ],
    "wof:name":"Col. And Graph. Nv",
    "wof:placetype":"venue"
},
  "geometry": {"coordinates":[4.4410290718,50.8542785645],"type":"Point"}
}