{
  "type": "Feature",
  "properties": {
    "addr:full":"Rue Saint-norbert 39 Box 1 Bruxelles (jette) Bruxelles-Capitale 1090",
    "addr:housenumber":"39;1",
    "addr:postcode":"1090",
    "addr:street":"Rue Saint-Norbert;Box",
    "iso:country":"BE",
    "sg:address":"Rue Saint-norbert 39 Box 1",
    "sg:city":"Bruxelles (jette)",
    "sg:classifiers":[
        {
            "category":"Education",
            "subcategory":"Special Training",
            "type":"Public Place"
        }
    ],
    "sg:phone":"+32 2 732 89 86",
    "sg:postcode":"1090",
    "sg:province":"Bruxelles-Capitale",
    "sg:tags":[
        "-",
        "processing",
        "data"
    ],
    "wof:name":"Skedion",
    "wof:placetype":"venue"
},
  "geometry": {"coordinates":[4.33689785,50.8818778992],"type":"Point"}
}