{
  "type": "Feature",
  "properties": {
    "addr:full":"Bois Du Foyau 130 Braine-le-ch\u00e2teau Brabant Wallon 1440",
    "addr:housenumber":"130",
    "addr:postcode":"1440",
    "addr:street":"Bois Du Foyau",
    "iso:country":"BE",
    "sg:address":"Bois Du Foyau 130",
    "sg:city":"Braine-le-ch\u00e2teau",
    "sg:classifiers":[
        {
            "category":"Professional",
            "subcategory":"Business Services",
            "type":"Services"
        }
    ],
    "sg:phone":"+32 2 366 42 70",
    "sg:postcode":"1440",
    "sg:province":"Brabant Wallon",
    "sg:tags":[
        "firm"
    ],
    "wof:name":"Vlaemynck A",
    "wof:placetype":"venue"
},
  "geometry": {"coordinates":[4.2823171616,50.6709403992],"type":"Point"}
}