{
  "type": "Feature",
  "properties": {
    "addr:full":"Diestsesteenweg 2 Herk-de-stad Limburg 3540",
    "addr:housenumber":"2",
    "addr:postcode":"3540",
    "addr:street":"Diestsesteenweg",
    "iso:country":"BE",
    "sg:address":"Diestsesteenweg 2",
    "sg:city":"Herk-de-stad",
    "sg:orig_category":"Pain, p\u00e2tisseries and confiseries",
    "sg:phone":"+32 13 55 10 54",
    "sg:postcode":"3540",
    "sg:province":"Limburg",
    "wof:name":"Rodiers Patrick",
    "wof:placetype":"venue"
},
  "geometry": {"coordinates":[5.16456604,50.9406013489],"type":"Point"}
}