{
  "type": "Feature",
  "properties": {
    "iso:country":"BE",
    "sg:address":"Buffonstraat 55",
    "sg:city":"Anderlecht",
    "sg:orig_category":"Binnenhuisarchitecten",
    "sg:phone":"+32 2 521 24 01",
    "sg:postcode":"1070",
    "sg:province":"Bruxelles-Capitale",
    "wof:name":"Alain Griffet",
    "wof:placetype":"venue"
},
  "geometry": {"coordinates":[4.2989068031,50.8399848938],"type":"Point"}
}