{
  "type": "Feature",
  "properties": {
    "addr:full":"Heilaarstraat 4 Beerse Antwerpen 2340",
    "addr:housenumber":"4",
    "addr:postcode":"2340",
    "addr:street":"Heilaarstraat",
    "iso:country":"BE",
    "sg:address":"Heilaarstraat 4",
    "sg:city":"Beerse",
    "sg:classifiers":[
        {
            "category":"Education",
            "subcategory":"Library",
            "type":"Public Place"
        }
    ],
    "sg:phone":"+32 14 61 56 15",
    "sg:postcode":"2340",
    "sg:province":"Antwerpen",
    "wof:name":"Openbare Bibliotheek Beerse",
    "wof:placetype":"venue"
},
  "geometry": {"coordinates":[4.8561301231,51.3247146606],"type":"Point"}
}