{
  "type": "Feature",
  "properties": {
    "iso:country":"BE",
    "sg:address":"Nieuwplaats 11",
    "sg:city":"Hooglede (gits)",
    "sg:classifiers":[
        {
            "category":"Bakery",
            "type":"Food & Drink"
        }
    ],
    "sg:phone":"+32 51 22 60 39",
    "sg:postcode":"8830",
    "sg:province":"West-Vlaanderen",
    "sg:tags":[
        "confectioner",
        "baker"
    ],
    "wof:name":"Nieuwplatse",
    "wof:placetype":"venue"
},
  "geometry": {"coordinates":[3.0971970558,50.9970016479],"type":"Point"}
}