{
  "type": "Feature",
  "properties": {
    "addr:full":"Rue Pestelin 27 Pont-a-celles Hainaut 6238",
    "addr:housenumber":"27",
    "addr:postcode":"6238",
    "addr:street":"Rue Pestelin",
    "iso:country":"BE",
    "sg:address":"Rue Pestelin 27",
    "sg:city":"Pont-a-celles",
    "sg:classifiers":[
        {
            "category":"Government",
            "subcategory":"Police Station",
            "type":"Public Place"
        }
    ],
    "sg:phone":"+32 71 84 40 32",
    "sg:postcode":"6238",
    "sg:province":"Hainaut",
    "sg:tags":[
        "gendarmerie"
    ],
    "wof:name":"Police F\u00c9d\u00c9rale",
    "wof:placetype":"venue"
},
  "geometry": {"coordinates":[4.399892807,50.513584137],"type":"Point"}
}