{
  "type": "Feature",
  "properties": {
    "addr:full":"Rue Rabelais 17 Ottignies-louvain-la-neuve Brabant Wallon 1348",
    "addr:housenumber":"17",
    "addr:postcode":"1348",
    "addr:street":"Rue Rabelais",
    "iso:country":"BE",
    "sg:address":"Rue Rabelais 17",
    "sg:city":"Ottignies-louvain-la-neuve",
    "sg:orig_category":"Diverse bedrijfsbeheeradviesbureaus",
    "sg:phone":"+32 10 45 28 46",
    "sg:postcode":"1348",
    "sg:province":"Brabant Wallon",
    "wof:name":"Bief",
    "wof:placetype":"venue"
},
  "geometry": {"coordinates":[4.613257885,50.6692886353],"type":"Point"}
}