{
  "type": "Feature",
  "properties": {
    "addr:full":"Cortil Des Grillons 21 Ottignies-louvain-la-neuve Brabant Wallon 1348",
    "addr:housenumber":"21",
    "addr:postcode":"1348",
    "addr:street":"Cortil Des Grillons",
    "iso:country":"BE",
    "sg:address":"Cortil Des Grillons 21",
    "sg:city":"Ottignies-louvain-la-neuve",
    "sg:classifiers":[
        {
            "category":"Wholesale",
            "subcategory":"Sporting Goods",
            "type":"Manufacturing & Wholesale Goods"
        }
    ],
    "sg:phone":"+32 10 45 17 11",
    "sg:postcode":"1348",
    "sg:province":"Brabant Wallon",
    "sg:tags":[
        "sport-",
        "kampeermateriaal"
    ],
    "wof:name":"Kot-et-scout",
    "wof:placetype":"venue"
},
  "geometry": {"coordinates":[4.6023797989,50.6693077087],"type":"Point"}
}