{
  "type": "Feature",
  "properties": {
    "addr:full":"Genutstraat 34 Bilzen Limburg 3740",
    "addr:housenumber":"34",
    "addr:postcode":"3740",
    "addr:street":"Genutstraat",
    "iso:country":"BE",
    "sg:address":"Genutstraat 34",
    "sg:city":"Bilzen",
    "sg:classifiers":[
        {
            "category":"Professional",
            "subcategory":"Accounting & Tax Preparation",
            "type":"Services"
        }
    ],
    "sg:phone":"+32 89 41 45 53",
    "sg:postcode":"3740",
    "sg:province":"Limburg",
    "sg:tags":[
        "accountant"
    ],
    "wof:name":"Francois Croux",
    "wof:placetype":"venue"
},
  "geometry": {"coordinates":[5.5143990517,50.8720550537],"type":"Point"}
}