{
  "type": "Feature",
  "properties": {
    "addr:full":"Victorialaan 69 Oostende West-Vlaanderen 8400",
    "addr:housenumber":"69",
    "addr:postcode":"8400",
    "addr:street":"Victorialaan",
    "iso:country":"BE",
    "sg:address":"Victorialaan 69",
    "sg:city":"Oostende",
    "sg:classifiers":[
        {
            "category":"Manufacturing",
            "subcategory":"Metals",
            "type":"Manufacturing & Wholesale Goods"
        }
    ],
    "sg:phone":"+32 59 32 10 99",
    "sg:postcode":"8400",
    "sg:province":"West-Vlaanderen",
    "sg:tags":[
        "foundry"
    ],
    "wof:name":"Debaedts",
    "wof:placetype":"venue"
},
  "geometry": {"coordinates":[2.9388771057,51.2319793701],"type":"Point"}
}