{
  "type": "Feature",
  "properties": {
    "addr:full":"Professor Dewulfstraat 204ba Poperinge West-Vlaanderen 8970",
    "addr:postcode":"8970",
    "addr:street":"Professor Dewulfstraat 204Ba",
    "iso:country":"BE",
    "sg:address":"Professor Dewulfstraat 204ba",
    "sg:city":"Poperinge",
    "sg:orig_category":"V\u00eatements. Textiles",
    "sg:phone":"+32 57 33 32 46",
    "sg:postcode":"8970",
    "sg:province":"West-Vlaanderen",
    "wof:name":"Wolboetiek",
    "wof:placetype":"venue"
},
  "geometry": {"coordinates":[2.7382290363,50.8488693237],"type":"Point"}
}