{
  "type": "Feature",
  "properties": {
    "addr:full":"Steenweg Op Jette 174 Koekelberg Bruxelles-Capitale 1081",
    "addr:housenumber":"174",
    "addr:postcode":"1081",
    "addr:street":"Steenweg Op Jette",
    "iso:country":"BE",
    "sg:address":"Steenweg Op Jette 174",
    "sg:city":"Koekelberg",
    "sg:orig_category":"Kapsalons",
    "sg:phone":"+32 2 411 87 63",
    "sg:postcode":"1081",
    "sg:province":"Bruxelles-Capitale",
    "wof:name":"Coiffure Jeanine",
    "wof:placetype":"venue"
},
  "geometry": {"coordinates":[4.3347659111,50.8600196838],"type":"Point"}
}