{
  "type": "Feature",
  "properties": {
    "iso:country":"BE",
    "sg:address":"Avenue Stienon 9",
    "sg:city":"Bruxelles",
    "sg:orig_category":"Artsen and specialisten",
    "sg:postcode":"1020",
    "sg:province":"Bruxelles-Capitale",
    "wof:name":"Postelmans Laurence",
    "wof:placetype":"venue"
},
  "geometry": {"coordinates":[4.3324260712,50.8923683167],"type":"Point"}
}