{
  "type": "Feature",
  "properties": {
    "addr:full":"Oude Markt 4-6 Leuven Vlaams-Brabant 3000",
    "addr:housenumber":"4-6",
    "addr:postcode":"3000",
    "addr:street":"Oude Markt",
    "iso:country":"BE",
    "sg:address":"Oude Markt 4-6",
    "sg:city":"Leuven",
    "sg:classifiers":[
        {
            "category":"Bars & Pubs",
            "type":"Food & Drink"
        }
    ],
    "sg:phone":"+32 16 20 06 38",
    "sg:postcode":"3000",
    "sg:province":"Vlaams-Brabant",
    "wof:name":"De Rector",
    "wof:placetype":"venue"
},
  "geometry": {"coordinates":[4.6998209953,50.8785514832],"type":"Point"}
}