{
  "type": "Feature",
  "properties": {
    "iso:country":"BE",
    "sg:address":"Quai Saint-brice 31",
    "sg:city":"Tournai",
    "sg:orig_category":"Notarissen",
    "sg:phone":"+32 69 22 41 91",
    "sg:postcode":"7500",
    "sg:province":"Hainaut",
    "wof:name":"Paul-emile Genin",
    "wof:placetype":"venue"
},
  "geometry": {"coordinates":[3.3903739452,50.6092224121],"type":"Point"}
}