{
  "type": "Feature",
  "properties": {
    "iso:country":"BE",
    "sg:address":"Merellaan 41",
    "sg:city":"Vosselaar",
    "sg:classifiers":[
        {
            "category":"Health Services",
            "subcategory":"Nursing And Care Facility",
            "type":"Services"
        }
    ],
    "sg:phone":"+32 14 61 34 15",
    "sg:postcode":"2350",
    "sg:province":"Antwerpen",
    "sg:tags":[
        "home"
    ],
    "wof:name":"Engelen-verswyvel Bvba",
    "wof:placetype":"venue"
},
  "geometry": {"coordinates":[4.8723530769,51.3063964844],"type":"Point"}
}