{
  "type": "Feature",
  "properties": {
    "iso:country":"BE",
    "sg:address":"Nieuwpoortsteenweg 115",
    "sg:city":"Koksijde (oostduinkerke)",
    "sg:classifiers":[
        {
            "category":"Building & Trades",
            "subcategory":"Construction",
            "type":"Services"
        }
    ],
    "sg:phone":"+32 58 23 24 08",
    "sg:postcode":"8670",
    "sg:province":"West-Vlaanderen",
    "sg:tags":[
        "carpenter"
    ],
    "wof:name":"Vandemaele G",
    "wof:placetype":"venue"
},
  "geometry": {"coordinates":[2.7028169632,51.1206054688],"type":"Point"}
}