{
  "type": "Feature",
  "properties": {
    "iso:country":"BE",
    "sg:address":"Schoendalestraat 32",
    "sg:city":"Waregem (sint-eloois-vijve)",
    "sg:classifiers":[
        {
            "category":"Utilities",
            "subcategory":"Fuel Oil & Lpg",
            "type":"Services"
        }
    ],
    "sg:phone":"+32 56 60 32 89",
    "sg:postcode":"8793",
    "sg:province":"West-Vlaanderen",
    "wof:name":"Vandererven",
    "wof:placetype":"venue"
},
  "geometry": {"coordinates":[3.4019019604,50.9054527283],"type":"Point"}
}