{
  "type": "Feature",
  "properties": {
    "addr:full":"Rue Reine Astrid 2 Erquelinnes Hainaut 6560",
    "addr:housenumber":"2",
    "addr:postcode":"6560",
    "addr:street":"Rue Reine Astrid",
    "iso:country":"BE",
    "sg:address":"Rue Reine Astrid 2",
    "sg:city":"Erquelinnes",
    "sg:orig_category":"Notarissen",
    "sg:phone":"+32 71 55 54 30",
    "sg:postcode":"6560",
    "sg:province":"Hainaut",
    "wof:name":"E. Losseau",
    "wof:placetype":"venue"
},
  "geometry": {"coordinates":[4.1499361992,50.3082427979],"type":"Point"}
}