{
  "type": "Feature",
  "properties": {
    "iso:country":"BE",
    "sg:address":"Sint-lucaslaan 29",
    "sg:city":"Brugge (assebroek)",
    "sg:classifiers":[
        {
            "category":"Health Services",
            "subcategory":"Hospital",
            "type":"Services"
        }
    ],
    "sg:phone":"+32 50 36 90 08",
    "sg:postcode":"8310",
    "sg:province":"West-Vlaanderen",
    "wof:name":"Az. St-lucas",
    "wof:placetype":"venue"
},
  "geometry": {"coordinates":[3.2476871014,51.1856117249],"type":"Point"}
}