{
  "type": "Feature",
  "properties": {
    "iso:country":"BE",
    "sg:address":"Carnotstraat 78",
    "sg:city":"Antwerpen",
    "sg:orig_category":"HERSTELLING ELEKTRISCHE HUISHOUDAPPARATEN Huishoudapparaten, televisies and radio's Telecommunicatie",
    "sg:phone":"+32 3 226 17 07",
    "sg:postcode":"2000",
    "sg:province":"Antwerpen",
    "wof:name":"Kr\u00cbfel",
    "wof:placetype":"venue"
},
  "geometry": {"coordinates":[4.4252138138,51.2181282043],"type":"Point"}
}