{
  "type": "Feature",
  "properties": {
    "iso:country":"BE",
    "sg:address":"Bredestraat 4",
    "sg:city":"Antwerpen",
    "sg:classifiers":[
        {
            "category":"Shopping",
            "type":"Retail Goods"
        }
    ],
    "sg:phone":"+32 3 227 44 44",
    "sg:postcode":"2000",
    "sg:province":"Antwerpen",
    "sg:tags":[
        "product",
        "cleaning",
        "maintenance"
    ],
    "wof:name":"Feem International Bvba",
    "wof:placetype":"venue"
},
  "geometry": {"coordinates":[4.4020428658,51.2151298523],"type":"Point"}
}