{
  "type": "Feature",
  "properties": {
    "iso:country":"BE",
    "sg:address":"J B Carnoyplaats 23",
    "sg:city":"Bruxelles (woluwe-saint-lambert)",
    "sg:classifiers":[
        {
            "category":"Education",
            "subcategory":"Library",
            "type":"Public Place"
        }
    ],
    "sg:phone":"+32 2 772 44 41",
    "sg:postcode":"1200",
    "sg:province":"Bruxelles-Capitale",
    "wof:name":"Carnoy",
    "wof:placetype":"venue"
},
  "geometry": {"coordinates":[4.4150009155,50.8514289856],"type":"Point"}
}