{
  "type": "Feature",
  "properties": {
    "iso:country":"BE",
    "sg:address":"Avenue De La Floride 32",
    "sg:city":"Ukkel/uccle",
    "sg:orig_category":"Eleveurs d'animaux divers",
    "sg:phone":"+32 2 374 44 64",
    "sg:postcode":"1180",
    "sg:province":"Bruxelles-Capitale",
    "wof:name":"P. Recorbet",
    "wof:placetype":"venue"
},
  "geometry": {"coordinates":[4.365778923,50.8089485168],"type":"Point"}
}