{
  "type": "Feature",
  "properties": {
    "iso:country":"BE",
    "sg:address":"Tiensesteenweg 88",
    "sg:city":"Bierbeek (korbeek-lo)",
    "sg:classifiers":[
        {
            "category":"Social Services",
            "subcategory":"Job Training",
            "type":"Services"
        }
    ],
    "sg:phone":"+32 16 46 59 00",
    "sg:postcode":"3360",
    "sg:province":"Vlaams-Brabant",
    "sg:tags":[
        "personnel"
    ],
    "wof:name":"Robeyns & Partners",
    "wof:placetype":"venue"
},
  "geometry": {"coordinates":[4.7609181404,50.8627281189],"type":"Point"}
}