{
  "type": "Feature",
  "properties": {
    "addr:full":"Lege Baan 55 Nijlen Antwerpen 2560",
    "addr:housenumber":"55",
    "addr:postcode":"2560",
    "addr:street":"Lege Baan",
    "iso:country":"BE",
    "sg:address":"Lege Baan 55",
    "sg:city":"Nijlen",
    "sg:orig_category":"Installatie van houten of kunststof schrijnwerk Installatie van metalen schrijnwerk",
    "sg:phone":"+32 3 481 94 19",
    "sg:postcode":"2560",
    "sg:province":"Antwerpen",
    "wof:name":"Erik Verlinden",
    "wof:placetype":"venue"
},
  "geometry": {"coordinates":[4.6648387909,51.152431488],"type":"Point"}
}