{
  "type": "Feature",
  "properties": {
    "addr:full":"Markt 30 Torhout West-Vlaanderen 8820",
    "addr:housenumber":"30",
    "addr:postcode":"8820",
    "addr:street":"Markt",
    "iso:country":"BE",
    "sg:address":"Markt 30",
    "sg:city":"Torhout",
    "sg:orig_category":"Disquaires",
    "sg:phone":"+32 50 21 64 62",
    "sg:postcode":"8820",
    "sg:province":"West-Vlaanderen",
    "wof:name":"Huis Topdisc",
    "wof:placetype":"venue"
},
  "geometry": {"coordinates":[3.1015899181,51.0640411377],"type":"Point"}
}