{
  "type": "Feature",
  "properties": {
    "iso:country":"BE",
    "sg:address":"Sterrekensstraat 1",
    "sg:city":"Lendelede",
    "sg:orig_category":"Rundveehouders Varkenskwekers",
    "sg:phone":"+32 51 30 14 33",
    "sg:postcode":"8860",
    "sg:province":"West-Vlaanderen",
    "wof:name":"Frans Devreese",
    "wof:placetype":"venue"
},
  "geometry": {"coordinates":[3.2291369438,50.8917579651],"type":"Point"}
}