{
  "type": "Feature",
  "properties": {
    "addr:full":"Gerheiden 1a Olen Antwerpen 2250",
    "addr:housenumber":"1a",
    "addr:postcode":"2250",
    "addr:street":"Gerheiden",
    "iso:country":"BE",
    "sg:address":"Gerheiden 1a",
    "sg:city":"Olen",
    "sg:classifiers":[
        {
            "category":"Shopping",
            "subcategory":"Baby Store",
            "type":"Retail Goods"
        }
    ],
    "sg:phone":"+32 14 22 36 20",
    "sg:postcode":"2250",
    "sg:province":"Antwerpen",
    "sg:tags":[
        "midwife"
    ],
    "wof:name":"Van Den Bossche L",
    "wof:placetype":"venue"
},
  "geometry": {"coordinates":[4.8902211189,51.1649627686],"type":"Point"}
}