{
  "type": "Feature",
  "properties": {
    "addr:full":"Rue De Biert 22 Florennes Namur 5620",
    "addr:housenumber":"22",
    "addr:postcode":"5620",
    "addr:street":"Rue De Biert",
    "iso:country":"BE",
    "sg:address":"Rue De Biert 22",
    "sg:city":"Florennes",
    "sg:orig_category":"Rundveehouders",
    "sg:phone":"+32 82 69 93 04",
    "sg:postcode":"5620",
    "sg:province":"Namur",
    "wof:name":"Gauthier M. & B.",
    "wof:placetype":"venue"
},
  "geometry": {"coordinates":[4.7518229485,50.2706565857],"type":"Point"}
}