{
  "type": "Feature",
  "properties": {
    "addr:full":"Schoolstraat 30 Berlaar Antwerpen 2590",
    "addr:housenumber":"30",
    "addr:postcode":"2590",
    "addr:street":"Schoolstraat",
    "iso:country":"BE",
    "sg:address":"Schoolstraat 30",
    "sg:city":"Berlaar",
    "sg:orig_category":"Openbare veiligheid",
    "sg:phone":"+32 3 482 42 42",
    "sg:postcode":"2590",
    "sg:province":"Antwerpen",
    "wof:name":"Federale Politie",
    "wof:placetype":"venue"
},
  "geometry": {"coordinates":[4.6580781937,51.1166000366],"type":"Point"}
}