{
  "type": "Feature",
  "properties": {
    "iso:country":"BE",
    "sg:address":"Rue De Les Waleffes 27",
    "sg:city":"Faimes",
    "sg:orig_category":"G\u00e9om\u00e8tres. Evaluation and estimation de biens immobiliers",
    "sg:phone":"+32 19 33 13 74",
    "sg:postcode":"4317",
    "sg:province":"Li\u00e8ge",
    "wof:name":"Jean-michel Bieswal",
    "wof:placetype":"venue"
},
  "geometry": {"coordinates":[5.2241029739,50.6434707642],"type":"Point"}
}