{
  "type": "Feature",
  "properties": {
    "iso:country":"BE",
    "sg:address":"Avenue Van Volxem 321",
    "sg:city":"Bruxelles (forest)",
    "sg:classifiers":[
        {
            "category":"Train Station",
            "subcategory":"Light Rail",
            "type":"Transportation"
        }
    ],
    "sg:phone":"+32 2 347 61 86",
    "sg:postcode":"1190",
    "sg:province":"Bruxelles-Capitale",
    "sg:tags":[
        "varnishing",
        "plasticizing",
        "document"
    ],
    "wof:name":"Euromatic",
    "wof:placetype":"venue"
},
  "geometry": {"coordinates":[4.326485157,50.8233566284],"type":"Point"}
}