{
  "type": "Feature",
  "properties": {
    "iso:country":"BE",
    "sg:address":"Rue Du Grand Air 19",
    "sg:city":"Chaudfontaine",
    "sg:orig_category":"Diensten voor huisdieren",
    "sg:phone":"+32 4 368 78 63",
    "sg:postcode":"4052",
    "sg:province":"Li\u00e8ge",
    "wof:name":"Toilettage Liliane",
    "wof:placetype":"venue"
},
  "geometry": {"coordinates":[5.6196341515,50.5656585693],"type":"Point"}
}