{
  "type": "Feature",
  "properties": {
    "iso:country":"BE",
    "sg:address":"Toemaathoek 31 A",
    "sg:city":"Mol",
    "sg:orig_category":"Services pour animaux domestiques",
    "sg:phone":"+32 14 32 19 78",
    "sg:postcode":"2400",
    "sg:province":"Antwerpen",
    "wof:name":"Kastor",
    "wof:placetype":"venue"
},
  "geometry": {"coordinates":[5.1449999809,51.1996917725],"type":"Point"}
}