{
  "type": "Feature",
  "properties": {
    "addr:full":"Handelsstraat 78 Roeselare West-Vlaanderen 8800",
    "addr:housenumber":"78",
    "addr:postcode":"8800",
    "addr:street":"Handelsstraat",
    "iso:country":"BE",
    "sg:address":"Handelsstraat 78",
    "sg:city":"Roeselare",
    "sg:classifiers":[
        {
            "category":"Government",
            "subcategory":"Fire Station",
            "type":"Public Place"
        }
    ],
    "sg:phone":"+32 51 22 44 63",
    "sg:postcode":"8800",
    "sg:province":"West-Vlaanderen",
    "sg:tags":[
        "fitting",
        "furniture",
        "kitchen"
    ],
    "wof:name":"Ygrek De Bruyne Patrick Nv",
    "wof:placetype":"venue"
},
  "geometry": {"coordinates":[3.1238319874,50.9570579529],"type":"Point"}
}