{
  "type": "Feature",
  "properties": {
    "addr:full":"Avenue Des Combattants 30 Jodoigne Brabant Wallon 1370",
    "addr:housenumber":"30",
    "addr:postcode":"1370",
    "addr:street":"Avenue Des Combattants",
    "iso:country":"BE",
    "sg:address":"Avenue Des Combattants 30",
    "sg:city":"Jodoigne",
    "sg:orig_category":"Tuinen",
    "sg:phone":"+32 10 81 20 63",
    "sg:postcode":"1370",
    "sg:province":"Brabant Wallon",
    "wof:name":"Jardin Anim\u00c9",
    "wof:placetype":"venue"
},
  "geometry": {"coordinates":[4.8706889153,50.7236709595],"type":"Point"}
}