{
  "type": "Feature",
  "properties": {
    "iso:country":"BE",
    "sg:address":"Bredabaan 165b7",
    "sg:city":"Brasschaat",
    "sg:orig_category":"Diverse intermediaire producten Gh",
    "sg:phone":"+32 3 651 82 91",
    "sg:postcode":"2930",
    "sg:province":"Antwerpen",
    "wof:name":"Eddy Van Houtven",
    "wof:placetype":"venue"
},
  "geometry": {"coordinates":[4.4845747948,51.2856407166],"type":"Point"}
}