{
  "type": "Feature",
  "properties": {
    "iso:country":"BE",
    "sg:address":"Ernest Claesstraat 73",
    "sg:city":"Scherpenheuvel-zichem",
    "sg:classifiers":[
        {
            "category":"Cafe",
            "type":"Food & Drink"
        }
    ],
    "sg:phone":"+32 13 78 30 68",
    "sg:postcode":"3271",
    "sg:province":"Vlaams-Brabant",
    "sg:tags":[
        "caf\u00e9s"
    ],
    "wof:name":"Caf\u00c9 Shar-pei",
    "wof:placetype":"venue"
},
  "geometry": {"coordinates":[4.9893269539,51.0056762695],"type":"Point"}
}