{
  "type": "Feature",
  "properties": {
    "addr:full":"Baljuwstraat 59 Elsene/ixelles Bruxelles-Capitale 1050",
    "addr:housenumber":"59",
    "addr:postcode":"1050",
    "addr:street":"Baljuwstraat",
    "iso:country":"BE",
    "sg:address":"Baljuwstraat 59",
    "sg:city":"Elsene/ixelles",
    "sg:orig_category":"Verlichting and huishoudartikelen",
    "sg:phone":"+32 2 537 96 30",
    "sg:postcode":"1050",
    "sg:province":"Bruxelles-Capitale",
    "wof:name":"New H",
    "wof:placetype":"venue"
},
  "geometry": {"coordinates":[4.3606710434,50.826133728],"type":"Point"}
}