{
  "type": "Feature",
  "properties": {
    "addr:full":"Ooststraat 28 Ronse/renaix Oost-Vlaanderen 9600",
    "addr:housenumber":"28",
    "addr:postcode":"9600",
    "addr:street":"Ooststraat",
    "iso:country":"BE",
    "sg:address":"Ooststraat 28",
    "sg:city":"Ronse/renaix",
    "sg:orig_category":"Artiesten and kunstenaars",
    "sg:phone":"+32 55 21 05 54",
    "sg:postcode":"9600",
    "sg:province":"Oost-Vlaanderen",
    "wof:name":"Pierre Ponnet",
    "wof:placetype":"venue"
},
  "geometry": {"coordinates":[3.6280879974,50.7388114929],"type":"Point"}
}