{
  "type": "Feature",
  "properties": {
    "iso:country":"BE",
    "sg:address":"Rue D'houchen\u00e9e 71",
    "sg:city":"Tinlot (fraiture)",
    "sg:classifiers":[
        {
            "category":"Sports & Exercise",
            "subcategory":"Stables",
            "type":"Entertainment"
        }
    ],
    "sg:phone":"+32 85 51 92 95",
    "sg:postcode":"4557",
    "sg:province":"Li\u00e8ge",
    "sg:tags":[
        "riding",
        "school"
    ],
    "wof:name":"Hippopassion Asbl",
    "wof:placetype":"venue"
},
  "geometry": {"coordinates":[5.434030056,50.4850502014],"type":"Point"}
}