{
  "type": "Feature",
  "properties": {
    "addr:full":"Odet 57 Clavier Li\u00e8ge 4560",
    "addr:housenumber":"57",
    "addr:postcode":"4560",
    "addr:street":"Odet",
    "iso:country":"BE",
    "sg:address":"Odet 57",
    "sg:city":"Clavier",
    "sg:orig_category":"Eleveurs de bovins",
    "sg:phone":"+32 83 63 31 79",
    "sg:postcode":"4560",
    "sg:province":"Li\u00e8ge",
    "wof:name":"Andre Kinet",
    "wof:placetype":"venue"
},
  "geometry": {"coordinates":[5.302259922,50.3845481873],"type":"Point"}
}