{
  "type": "Feature",
  "properties": {
    "iso:country":"BE",
    "sg:address":"Rue Plein-vent 18",
    "sg:city":"Baelen",
    "sg:orig_category":"Fabrication and montage de mobilier",
    "sg:phone":"+32 78 71 73 36",
    "sg:postcode":"4837",
    "sg:province":"Li\u00e8ge",
    "wof:name":"B.r.m. Sprl",
    "wof:placetype":"venue"
},
  "geometry": {"coordinates":[5.9705991745,50.6360473633],"type":"Point"}
}