{
  "type": "Feature",
  "properties": {
    "iso:country":"BE",
    "sg:address":"Aarlenstraat 92",
    "sg:city":"Bruxelles (etterbeek)",
    "sg:classifiers":[
        {
            "category":"Professional",
            "subcategory":"Lawyer & Legal Services",
            "type":"Services"
        }
    ],
    "sg:phone":"+32 2 230 65 30",
    "sg:postcode":"1040",
    "sg:province":"Bruxelles-Capitale",
    "wof:name":"De Boeck Claire",
    "wof:placetype":"venue"
},
  "geometry": {"coordinates":[4.3736791611,50.8426628113],"type":"Point"}
}