{
  "type": "Feature",
  "properties": {
    "iso:country":"BE",
    "sg:address":"Rot 41",
    "sg:city":"Holsbeek",
    "sg:orig_category":"Kapsalons",
    "sg:phone":"+32 16 56 27 79",
    "sg:postcode":"3221",
    "sg:province":"Vlaams-Brabant",
    "wof:name":"Lucia Van Uythem",
    "wof:placetype":"venue"
},
  "geometry": {"coordinates":[4.8178977966,50.9556808472],"type":"Point"}
}