{
  "type": "Feature",
  "properties": {
    "iso:country":"BE",
    "sg:address":"Turnhoutsebaan 356",
    "sg:city":"Wijnegem",
    "sg:classifiers":[
        {
            "category":"Personal",
            "subcategory":"Beauty Salon",
            "type":"Services"
        }
    ],
    "sg:phone":"+32 3 353 32 48",
    "sg:postcode":"2110",
    "sg:province":"Antwerpen",
    "sg:tags":[
        "lady",
        "-",
        "hairdressing"
    ],
    "wof:name":"Simone",
    "wof:placetype":"venue"
},
  "geometry": {"coordinates":[4.5190119743,51.2271308899],"type":"Point"}
}