{
  "type": "Feature",
  "properties": {
    "addr:full":"Aarschotsesteenweg 130 Begijnendijk (betekom) Vlaams-Brabant 3130",
    "addr:housenumber":"130",
    "addr:postcode":"3130",
    "addr:street":"Aarschotsesteenweg",
    "iso:country":"BE",
    "sg:address":"Aarschotsesteenweg 130",
    "sg:city":"Begijnendijk (betekom)",
    "sg:classifiers":[
        {
            "category":"Retail",
            "subcategory":"Auto Repair",
            "type":"Services"
        }
    ],
    "sg:phone":"+32 16 56 62 70",
    "sg:postcode":"3130",
    "sg:province":"Vlaams-Brabant",
    "sg:tags":[
        "garage"
    ],
    "wof:name":"Garage Van Roy Nv",
    "wof:placetype":"venue"
},
  "geometry": {"coordinates":[4.7937951088,51.0315628052],"type":"Point"}
}