{
  "type": "Feature",
  "properties": {
    "iso:country":"BE",
    "sg:address":"Place Du Petit March\u00c9 2",
    "sg:city":"Beaumont",
    "sg:orig_category":"Eclairage et \u00e9quipements du foyer",
    "sg:phone":"+32 71 58 72 72",
    "sg:postcode":"6500",
    "sg:province":"Hainaut",
    "wof:name":"Le March\u00c9 D\u00b4elisa",
    "wof:placetype":"venue"
},
  "geometry": {"coordinates":[4.2363071442,50.2366333008],"type":"Point"}
}