{
  "type": "Feature",
  "properties": {
    "addr:full":"Roerdompstraat 11 Diepenbeek Limburg 3590",
    "addr:housenumber":"11",
    "addr:postcode":"3590",
    "addr:street":"Roerdompstraat",
    "iso:country":"BE",
    "sg:address":"Roerdompstraat 11",
    "sg:city":"Diepenbeek",
    "sg:orig_category":"Serres and speciale beglazing",
    "sg:phone":"+32 11 23 33 37",
    "sg:postcode":"3590",
    "sg:province":"Limburg",
    "wof:name":"Eddy Fripont",
    "wof:placetype":"venue"
},
  "geometry": {"coordinates":[5.4231681824,50.9429702759],"type":"Point"}
}