{
  "type": "Feature",
  "properties": {
    "addr:full":"Postelsesteenweg 27 Mol Antwerpen 2400",
    "addr:housenumber":"27",
    "addr:postcode":"2400",
    "addr:street":"Postelsesteenweg",
    "iso:country":"BE",
    "sg:address":"Postelsesteenweg 27",
    "sg:city":"Mol",
    "sg:classifiers":[
        {
            "category":"Professional",
            "subcategory":"Business Services",
            "type":"Services"
        }
    ],
    "sg:phone":"+32 14 81 11 41",
    "sg:postcode":"2400",
    "sg:province":"Antwerpen",
    "sg:tags":[
        "travel",
        "transport",
        "road"
    ],
    "wof:name":"Carolus Reizen Bvba",
    "wof:placetype":"venue"
},
  "geometry": {"coordinates":[5.1817011833,51.2079582214],"type":"Point"}
}