{
  "type": "Feature",
  "properties": {
    "addr:full":"Ooststraat 6 Lo-reninge West-Vlaanderen 8647",
    "addr:housenumber":"6",
    "addr:postcode":"8647",
    "addr:street":"Ooststraat",
    "iso:country":"BE",
    "sg:address":"Ooststraat 6",
    "sg:city":"Lo-reninge",
    "sg:orig_category":"Auto-\u00e9coles",
    "sg:phone":"+32 58 51 12 21",
    "sg:postcode":"8647",
    "sg:province":"West-Vlaanderen",
    "wof:name":"Eureka",
    "wof:placetype":"venue"
},
  "geometry": {"coordinates":[2.7492120266,50.9808883667],"type":"Point"}
}