{
  "type": "Feature",
  "properties": {
    "iso:country":"BE",
    "sg:address":"Bijlokstraat 198",
    "sg:city":"Herent",
    "sg:orig_category":"Sportclubs",
    "sg:phone":"+32 16 20 48 88",
    "sg:postcode":"3020",
    "sg:province":"Vlaams-Brabant",
    "wof:name":"L.t.c. Herent",
    "wof:placetype":"venue"
},
  "geometry": {"coordinates":[4.6829509735,50.8992156982],"type":"Point"}
}