{
  "type": "Feature",
  "properties": {
    "addr:full":"Mariakerkelaan 166 Oostende West-Vlaanderen 8400",
    "addr:housenumber":"166",
    "addr:postcode":"8400",
    "addr:street":"Mariakerkelaan",
    "iso:country":"BE",
    "sg:address":"Mariakerkelaan 166",
    "sg:city":"Oostende",
    "sg:orig_category":"Airconditioning and ventilatie Loodgieterij, verwarming and sanitaire installaties",
    "sg:phone":"+32 59 80 13 92",
    "sg:postcode":"8400",
    "sg:province":"West-Vlaanderen",
    "wof:name":"Claeys-luteyn",
    "wof:placetype":"venue"
},
  "geometry": {"coordinates":[2.9039111137,51.2119293213],"type":"Point"}
}