{
  "type": "Feature",
  "properties": {
    "addr:full":"Staatsbaan 149f Zulte Oost-Vlaanderen 9870",
    "addr:housenumber":"149f",
    "addr:postcode":"9870",
    "addr:street":"Staatsbaan",
    "iso:country":"BE",
    "sg:address":"Staatsbaan 149f",
    "sg:city":"Zulte",
    "sg:classifiers":[
        {
            "category":"Banks & Credit Unions",
            "subcategory":"Investment Brokerage",
            "type":"Services"
        }
    ],
    "sg:phone":"+32 9 388 97 51",
    "sg:postcode":"9870",
    "sg:province":"Oost-Vlaanderen",
    "sg:tags":[
        "printing",
        "-"
    ],
    "wof:name":"Lagaisse W",
    "wof:placetype":"venue"
},
  "geometry": {"coordinates":[3.443240881,50.9211730957],"type":"Point"}
}