{
  "type": "Feature",
  "properties": {
    "addr:full":"Gruitroderbaan 74 Meeuwen-gruitrode Limburg 3670",
    "addr:housenumber":"74",
    "addr:postcode":"3670",
    "addr:street":"Gruitroderbaan",
    "iso:country":"BE",
    "sg:address":"Gruitroderbaan 74",
    "sg:city":"Meeuwen-gruitrode",
    "sg:classifiers":[
        {
            "category":"Food & Beverages",
            "subcategory":"Fruits & Vegetables",
            "type":"Retail Goods"
        }
    ],
    "sg:phone":"+32 11 79 31 35",
    "sg:postcode":"3670",
    "sg:province":"Limburg",
    "sg:tags":[
        "l\u00e9gumes",
        "gr"
    ],
    "wof:name":"Patrick Coenen",
    "wof:placetype":"venue"
},
  "geometry": {"coordinates":[5.5312161446,51.0939941406],"type":"Point"}
}