{
  "type": "Feature",
  "properties": {
    "addr:full":"Mont 46 Comblain-au-pont Li\u00e8ge 4170",
    "addr:housenumber":"46",
    "addr:postcode":"4170",
    "addr:street":"Mont",
    "iso:country":"BE",
    "sg:address":"Mont 46",
    "sg:city":"Comblain-au-pont",
    "sg:orig_category":"Rundveehouders",
    "sg:phone":"+32 4 369 11 22",
    "sg:postcode":"4170",
    "sg:province":"Li\u00e8ge",
    "wof:name":"Rene Pahaut",
    "wof:placetype":"venue"
},
  "geometry": {"coordinates":[5.5722699165,50.4899787903],"type":"Point"}
}