{
  "type": "Feature",
  "properties": {
    "iso:country":"BE",
    "sg:address":"Jean Van Horenbeecklaan 17",
    "sg:city":"Oudergem/auderghem",
    "sg:orig_category":"Begrafeniswezen",
    "sg:phone":"+32 2 660 26 48",
    "sg:postcode":"1160",
    "sg:province":"Bruxelles-Capitale",
    "wof:name":"Fun\u00c9r. Ergo & Poncelet",
    "wof:placetype":"venue"
},
  "geometry": {"coordinates":[4.4359788895,50.8090782166],"type":"Point"}
}