{
  "type": "Feature",
  "properties": {
    "addr:full":"Nieder-emmels 87 St-vith Li\u00e8ge 4784",
    "addr:housenumber":"87",
    "addr:postcode":"4784",
    "addr:street":"Nieder-Emmels",
    "iso:country":"BE",
    "sg:address":"Nieder-emmels 87",
    "sg:city":"St-vith",
    "sg:classifiers":[
        {
            "category":"Bakery",
            "type":"Food & Drink"
        }
    ],
    "sg:phone":"+32 80 22 83 38",
    "sg:postcode":"4784",
    "sg:province":"Li\u00e8ge",
    "sg:tags":[
        "cake",
        "product",
        "related",
        "bread"
    ],
    "wof:name":"Farinbel Ag",
    "wof:placetype":"venue"
},
  "geometry": {"coordinates":[6.0924601555,50.3102912903],"type":"Point"}
}