{
  "type": "Feature",
  "properties": {
    "addr:full":"Deinsesteenweg 100 Gent (drongen) Oost-Vlaanderen 9031",
    "addr:housenumber":"100",
    "addr:postcode":"9031",
    "addr:street":"Deinsesteenweg",
    "iso:country":"BE",
    "sg:address":"Deinsesteenweg 100",
    "sg:city":"Gent (drongen)",
    "sg:orig_category":"Non-Classified Establishments",
    "sg:phone":"+32 9 226 01 12",
    "sg:postcode":"9031",
    "sg:province":"Oost-Vlaanderen",
    "wof:name":"Servitex",
    "wof:placetype":"venue"
},
  "geometry": {"coordinates":[3.6630249023,51.0503692627],"type":"Point"}
}