{
  "type": "Feature",
  "properties": {
    "iso:country":"BE",
    "sg:address":"Rue De Bruxelles 48",
    "sg:city":"Enghien",
    "sg:classifiers":[
        {
            "category":"Travel",
            "subcategory":"Travel Agent",
            "type":"Entertainment"
        }
    ],
    "sg:phone":"+32 2 395 89 29",
    "sg:postcode":"7850",
    "sg:province":"Hainaut",
    "sg:tags":[
        "agency"
    ],
    "wof:name":"Abysse Tours",
    "wof:placetype":"venue"
},
  "geometry": {"coordinates":[4.0412697792,50.6945838928],"type":"Point"}
}