{
  "type": "Feature",
  "properties": {
    "iso:country":"BE",
    "sg:address":"Borrekent 36",
    "sg:city":"Haaltert (denderhoutem)",
    "sg:classifiers":[
        {
            "category":"Building & Trades",
            "subcategory":"Construction",
            "type":"Services"
        }
    ],
    "sg:phone":"+32 54 33 11 23",
    "sg:postcode":"9450",
    "sg:province":"Oost-Vlaanderen",
    "sg:tags":[
        "carpenter"
    ],
    "wof:name":"Van Hecke & Zonen",
    "wof:placetype":"venue"
},
  "geometry": {"coordinates":[4.0089430809,50.8749198914],"type":"Point"}
}