{
  "type": "Feature",
  "properties": {
    "addr:full":"Snellewindstraat 25 Bocholt Limburg 3950",
    "addr:housenumber":"25",
    "addr:postcode":"3950",
    "addr:street":"Snellewindstraat",
    "iso:country":"BE",
    "sg:address":"Snellewindstraat 25",
    "sg:city":"Bocholt",
    "sg:orig_category":"Installatie van houten of kunststof schrijnwerk",
    "sg:phone":"+32 11 62 14 27",
    "sg:postcode":"3950",
    "sg:province":"Limburg",
    "wof:name":"Servatius Ruttens",
    "wof:placetype":"venue"
},
  "geometry": {"coordinates":[5.5639891624,51.1931343079],"type":"Point"}
}