{
  "type": "Feature",
  "properties": {
    "iso:country":"BE",
    "sg:address":"Hanswijkstraat 17c",
    "sg:city":"Mechelen",
    "sg:classifiers":[
        {
            "category":"Health Services",
            "subcategory":"Doctor",
            "type":"Services"
        }
    ],
    "sg:phone":"+32 15 41 65 71",
    "sg:postcode":"2800",
    "sg:province":"Antwerpen",
    "sg:tags":[
        "medicinephysicians",
        "surgeon"
    ],
    "wof:name":"Coninx Sylvain",
    "wof:placetype":"venue"
},
  "geometry": {"coordinates":[4.4831738472,51.022518158],"type":"Point"}
}