{
  "type": "Feature",
  "properties": {
    "addr:full":"Ossenwegstraat 101 Zoutleeuw Vlaams-Brabant 3440",
    "addr:housenumber":"101",
    "addr:postcode":"3440",
    "addr:street":"Ossenwegstraat;Vlaams-Brabant",
    "iso:country":"BE",
    "sg:address":"Ossenwegstraat 101",
    "sg:city":"Zoutleeuw",
    "sg:classifiers":[
        {
            "category":"Education",
            "subcategory":"Special Training",
            "type":"Public Place"
        }
    ],
    "sg:phone":"+32 11 78 28 53",
    "sg:postcode":"3440",
    "sg:province":"Vlaams-Brabant",
    "sg:tags":[
        "-",
        "processing",
        "data"
    ],
    "wof:name":"Inkeja Consultants Vof",
    "wof:placetype":"venue"
},
  "geometry": {"coordinates":[5.1335787773,50.8476676941],"type":"Point"}
}