{
  "type": "Feature",
  "properties": {
    "iso:country":"BE",
    "sg:address":"Engelselei 50",
    "sg:city":"Kapellen",
    "sg:orig_category":"Boekhouders Verzekeringsmakelaars and experts",
    "sg:phone":"+32 3 665 26 35",
    "sg:postcode":"2950",
    "sg:province":"Antwerpen",
    "wof:name":"Rudy Boen",
    "wof:placetype":"venue"
},
  "geometry": {"coordinates":[4.4308919907,51.3172607422],"type":"Point"}
}