{
  "type": "Feature",
  "properties": {
    "addr:full":"Kerkstraat 89 Balen Antwerpen 2490",
    "addr:housenumber":"89",
    "addr:postcode":"2490",
    "addr:street":"Kerkstraat",
    "iso:country":"BE",
    "sg:address":"Kerkstraat 89",
    "sg:city":"Balen",
    "sg:orig_category":"R\u00e9parations d'appareils \u00e9lectrom\u00e9nagers. Electrom\u00e9nager, t\u00e9l\u00e9visions and radios",
    "sg:phone":"+32 14 81 17 01",
    "sg:postcode":"2490",
    "sg:province":"Antwerpen",
    "wof:name":"Gebrs Bruyninckx",
    "wof:placetype":"venue"
},
  "geometry": {"coordinates":[5.1724700928,51.1762390137],"type":"Point"}
}