{
  "type": "Feature",
  "properties": {
    "addr:full":"Burgerleenstraat 28 Ardooie (koolskamp) West-Vlaanderen 8851",
    "addr:housenumber":"28",
    "addr:postcode":"8851",
    "addr:street":"Burgerleenstraat",
    "iso:country":"BE",
    "sg:address":"Burgerleenstraat 28",
    "sg:city":"Ardooie (koolskamp)",
    "sg:classifiers":[
        {
            "category":"Building & Trades",
            "subcategory":"Cleaning & Sanitation",
            "type":"Services"
        }
    ],
    "sg:phone":"+32 51 74 60 29",
    "sg:postcode":"8851",
    "sg:province":"West-Vlaanderen",
    "sg:tags":[
        "fa\u00e7ade",
        "maintenance"
    ],
    "wof:name":"Renovatiebedrijf Devos Noel & Zoon",
    "wof:placetype":"venue"
},
  "geometry": {"coordinates":[3.1807351112,50.9973526001],"type":"Point"}
}