{
  "type": "Feature",
  "properties": {
    "addr:full":"Gullegemsesteenweg 21 Kortrijk West-Vlaanderen 8501",
    "addr:housenumber":"21",
    "addr:postcode":"8501",
    "addr:street":"Gullegemsesteenweg",
    "iso:country":"BE",
    "sg:address":"Gullegemsesteenweg 21",
    "sg:city":"Kortrijk",
    "sg:orig_category":"Pain, p\u00e2tisseries and confiseries",
    "sg:phone":"+32 56 35 39 05",
    "sg:postcode":"8501",
    "sg:province":"West-Vlaanderen",
    "wof:name":"Kurt Dierickx Visschers",
    "wof:placetype":"venue"
},
  "geometry": {"coordinates":[3.2141499519,50.8329086304],"type":"Point"}
}