{
  "type": "Feature",
  "properties": {
    "addr:full":"Smiskensveld 21 Asse Vlaams-Brabant 1731",
    "addr:housenumber":"21",
    "addr:postcode":"1731",
    "addr:street":"Smiskensveld",
    "iso:country":"BE",
    "sg:address":"Smiskensveld 21",
    "sg:city":"Asse",
    "sg:orig_category":"Producteurs de l\u00e9gumes",
    "sg:phone":"+32 2 460 09 10",
    "sg:postcode":"1731",
    "sg:province":"Vlaams-Brabant",
    "wof:name":"Rene Vanlierde",
    "wof:placetype":"venue"
},
  "geometry": {"coordinates":[4.2860321999,50.8947143555],"type":"Point"}
}