{
  "type": "Feature",
  "properties": {
    "addr:full":"Hertoginstraat 17 Antwerpen Antwerpen 2018",
    "addr:housenumber":"17",
    "addr:postcode":"2018",
    "addr:street":"Hertoginstraat",
    "iso:country":"BE",
    "sg:address":"Hertoginstraat 17",
    "sg:city":"Antwerpen",
    "sg:classifiers":[
        {
            "category":"Education",
            "subcategory":"School",
            "type":"Public Place"
        }
    ],
    "sg:phone":"+32 3 232 74 47",
    "sg:postcode":"2018",
    "sg:province":"Antwerpen",
    "sg:tags":[
        "secondary"
    ],
    "wof:name":"Koninklijk Lyceum",
    "wof:placetype":"venue"
},
  "geometry": {"coordinates":[4.4107761383,51.2082099915],"type":"Point"}
}