{
  "type": "Feature",
  "properties": {
    "iso:country":"BE",
    "sg:address":"Antwerpsesteenweg 288",
    "sg:city":"Gent",
    "sg:orig_category":"Beautyfarms, relaxatie and lichamelijk welzijn",
    "sg:phone":"+32 9 228 91 18",
    "sg:postcode":"9040",
    "sg:province":"Oost-Vlaanderen",
    "wof:name":"Joli Zonnecenter",
    "wof:placetype":"venue"
},
  "geometry": {"coordinates":[3.7473080158,51.0601463318],"type":"Point"}
}