{
  "type": "Feature",
  "properties": {
    "addr:full":"Mechelsesteenweg 296a Sint-katelijne-waver Antwerpen 2860",
    "addr:housenumber":"296a",
    "addr:postcode":"2860",
    "addr:street":"Mechelsesteenweg",
    "iso:country":"BE",
    "sg:address":"Mechelsesteenweg 296a",
    "sg:city":"Sint-katelijne-waver",
    "sg:classifiers":[
        {
            "category":"Shopping",
            "subcategory":"Bicycles & Sporting Goods",
            "type":"Retail Goods"
        }
    ],
    "sg:phone":"+32 473 29 98 57",
    "sg:postcode":"2860",
    "sg:province":"Antwerpen",
    "sg:tags":[
        "-"
    ],
    "wof:name":"Andro Parts",
    "wof:placetype":"venue"
},
  "geometry": {"coordinates":[4.5157952309,51.0507316589],"type":"Point"}
}