{
  "type": "Feature",
  "properties": {
    "iso:country":"BE",
    "sg:address":"Heirstraat 227",
    "sg:city":"Maasmechelen",
    "sg:classifiers":[
        {
            "category":"Insurance",
            "subcategory":"Insurance Agent",
            "type":"Services"
        }
    ],
    "sg:phone":"+32 89 77 29 77",
    "sg:postcode":"3630",
    "sg:province":"Limburg",
    "sg:tags":[
        "broker"
    ],
    "wof:name":"Rutten R",
    "wof:placetype":"venue"
},
  "geometry": {"coordinates":[5.6969890594,50.9636917114],"type":"Point"}
}