{
  "type": "Feature",
  "properties": {
    "iso:country":"BE",
    "sg:address":"Rotterij 256",
    "sg:city":"Ronse/renaix",
    "sg:classifiers":[
        {
            "category":"Travel",
            "subcategory":"Hotels & Motels",
            "type":"Entertainment"
        }
    ],
    "sg:phone":"+32 55 21 50 43",
    "sg:postcode":"9600",
    "sg:province":"Oost-Vlaanderen",
    "wof:name":"Jean Machet",
    "wof:placetype":"venue"
},
  "geometry": {"coordinates":[3.6310310364,50.7423324585],"type":"Point"}
}