{
  "type": "Feature",
  "properties": {
    "addr:full":"89 Leuvensesteenweg 3070 Kortenberg 89",
    "addr:housenumber":"89",
    "addr:postcode":"3070",
    "addr:street":"Leuvensesteenweg",
    "iso:country":"BE",
    "sg:address":"89",
    "sg:city":"Leuvensesteenweg 3070 Kortenberg",
    "sg:classifiers":[
        {
            "category":"Banks & Credit Unions",
            "subcategory":"Investment Brokerage",
            "type":"Services"
        }
    ],
    "sg:phone":"+32 2 759 71 11",
    "sg:postcode":"89",
    "sg:tags":[
        "-",
        "transport",
        "related"
    ],
    "wof:name":"S.t.a.c.a. (societe Transport Autobus Car Automobiel) Nv",
    "wof:placetype":"venue"
},
  "geometry": {"coordinates":[4.5415301323,50.8876647949],"type":"Point"}
}