{
  "type": "Feature",
  "properties": {
    "addr:full":"Strombeeklinde 1 Grimbergen Vlaams-Brabant 1853",
    "addr:housenumber":"1",
    "addr:postcode":"1853",
    "addr:street":"Strombeeklinde",
    "iso:country":"BE",
    "sg:address":"Strombeeklinde 1",
    "sg:city":"Grimbergen",
    "sg:orig_category":"S\u00e9curit\u00e9 sociale",
    "sg:phone":"+32 2 267 19 15",
    "sg:postcode":"1853",
    "sg:province":"Vlaams-Brabant",
    "wof:name":"Christelijke Mutualiteit",
    "wof:placetype":"venue"
},
  "geometry": {"coordinates":[4.3565688133,50.9080200195],"type":"Point"}
}