{
  "type": "Feature",
  "properties": {
    "iso:country":"BE",
    "sg:address":"Iepersestraat 465",
    "sg:city":"Roeselare",
    "sg:orig_category":"V\u00e9hicules automobiles. Entretien and r\u00e9parations de voitures",
    "sg:phone":"+32 51 21 14 28",
    "sg:postcode":"8800",
    "sg:province":"West-Vlaanderen",
    "wof:name":"Carrosserie Wijfels",
    "wof:placetype":"venue"
},
  "geometry": {"coordinates":[3.1011440754,50.9332733154],"type":"Point"}
}