{
  "type": "Feature",
  "properties": {
    "addr:full":"Molenstraat 82 Wielsbeke West-Vlaanderen 8710",
    "addr:housenumber":"82",
    "addr:postcode":"8710",
    "addr:street":"Molenstraat",
    "iso:country":"BE",
    "sg:address":"Molenstraat 82",
    "sg:city":"Wielsbeke",
    "sg:orig_category":"HERSTELLING ELEKTRISCHE HUISHOUDAPPARATEN Herstelling aan huis van elektrische huishoudapparaten Hui",
    "sg:phone":"+32 56 66 67 09",
    "sg:postcode":"8710",
    "sg:province":"West-Vlaanderen",
    "wof:name":"Fa. Deschrijvere H. & M.",
    "wof:placetype":"venue"
},
  "geometry": {"coordinates":[3.3646910191,50.9084663391],"type":"Point"}
}