{
  "type": "Feature",
  "properties": {
    "iso:country":"BE",
    "sg:address":"Esplanade",
    "sg:city":"Bruxelles",
    "sg:classifiers":[
        {
            "category":"Restaurant",
            "type":"Food & Drink"
        }
    ],
    "sg:phone":"+32 2 475 23 45",
    "sg:postcode":"1020",
    "sg:province":"Bruxelles-Capitale",
    "wof:name":"Ming Dynasty",
    "wof:placetype":"venue"
},
  "geometry": {"coordinates":[4.3433609009,50.9003372192],"type":"Point"}
}