{
  "type": "Feature",
  "properties": {
    "addr:full":"Rue De L'armistice 58 Li\u00e8ge 1 (bressoux) Li\u00e8ge 4020",
    "addr:housenumber":"58;1",
    "addr:postcode":"4020",
    "addr:street":"Rue De L'Armistice",
    "iso:country":"BE",
    "sg:address":"Rue De L'armistice 58",
    "sg:city":"Li\u00e8ge 1 (bressoux)",
    "sg:classifiers":[
        {
            "category":"Professional",
            "subcategory":"Computer Services",
            "type":"Services"
        }
    ],
    "sg:phone":"+32 4 342 30 45",
    "sg:postcode":"4020",
    "sg:province":"Li\u00e8ge",
    "sg:tags":[
        "repair",
        "processing",
        "-",
        "maintenance",
        "data"
    ],
    "wof:name":"Eis Ets",
    "wof:placetype":"venue"
},
  "geometry": {"coordinates":[5.5943012238,50.6391181946],"type":"Point"}
}