{
  "type": "Feature",
  "properties": {
    "iso:country":"BE",
    "sg:address":"Haachtsesteenweg 284",
    "sg:city":"Kampenhout",
    "sg:classifiers":[
        {
            "category":"Home & Garden",
            "subcategory":"Garden Supply",
            "type":"Retail Goods"
        }
    ],
    "sg:phone":"+32 16 65 59 86",
    "sg:postcode":"1910",
    "sg:province":"Vlaams-Brabant",
    "sg:tags":[
        "machine",
        "agricultural",
        "-"
    ],
    "wof:name":"Van Ingelgom W & S",
    "wof:placetype":"venue"
},
  "geometry": {"coordinates":[4.5560359955,50.9399757385],"type":"Point"}
}