{
  "type": "Feature",
  "properties": {
    "iso:country":"BE",
    "sg:address":"Trakelweg 72",
    "sg:city":"Roeselare",
    "sg:classifiers":[
        {
            "category":"Shopping",
            "subcategory":"Crafts & Fabrics",
            "type":"Retail Goods"
        }
    ],
    "sg:phone":"+32 51 22 70 63",
    "sg:postcode":"8800",
    "sg:province":"West-Vlaanderen",
    "sg:tags":[
        "textile",
        "clothing"
    ],
    "wof:name":"Flaxinvest Nv",
    "wof:placetype":"venue"
},
  "geometry": {"coordinates":[3.1402740479,50.9422340393],"type":"Point"}
}