{
  "type": "Feature",
  "properties": {
    "addr:full":"Haachtsesteenweg 187 Schaarbeek/schaerbeek Bruxelles-Capitale 1030",
    "addr:housenumber":"187",
    "addr:postcode":"1030",
    "addr:street":"Haachtsesteenweg",
    "iso:country":"BE",
    "sg:address":"Haachtsesteenweg 187",
    "sg:city":"Schaarbeek/schaerbeek",
    "sg:orig_category":"Reisbureaus",
    "sg:phone":"+32 2 223 03 03",
    "sg:postcode":"1030",
    "sg:province":"Bruxelles-Capitale",
    "wof:name":"Efes Voyages",
    "wof:placetype":"venue"
},
  "geometry": {"coordinates":[4.3712801933,50.8606567383],"type":"Point"}
}