{
  "type": "Feature",
  "properties": {
    "iso:country":"BE",
    "sg:address":"Rue Octave Battaille 128",
    "sg:city":"Beloeil",
    "sg:orig_category":"Begrafeniswezen",
    "sg:phone":"+32 69 56 27 09",
    "sg:postcode":"7971",
    "sg:province":"Hainaut",
    "wof:name":"Fe. Vandermest",
    "wof:placetype":"venue"
},
  "geometry": {"coordinates":[3.6385059357,50.5297889709],"type":"Point"}
}