{
  "type": "Feature",
  "properties": {
    "iso:country":"BE",
    "sg:address":"Rue Sambr\u00e9e 30",
    "sg:city":"Court-saint-etienne",
    "sg:classifiers":[
        {
            "category":"Banks & Credit Unions",
            "subcategory":"Investment Brokerage",
            "type":"Services"
        }
    ],
    "sg:phone":"+32 10 61 23 56",
    "sg:postcode":"1490",
    "sg:province":"Brabant Wallon",
    "sg:tags":[
        "printing",
        "-"
    ],
    "wof:name":"Calendriers E Oleffe",
    "wof:placetype":"venue"
},
  "geometry": {"coordinates":[4.5621547699,50.6400260925],"type":"Point"}
}