{
  "type": "Feature",
  "properties": {
    "addr:full":"Rue Gr\u00e9try 76 Li\u00e8ge 1 (li\u00e8ge 2) Li\u00e8ge 4020",
    "addr:housenumber":"76;1;2",
    "addr:postcode":"4020",
    "addr:street":"Rue Gre\u0301Try",
    "iso:country":"BE",
    "sg:address":"Rue Gr\u00e9try 76",
    "sg:city":"Li\u00e8ge 1 (li\u00e8ge 2)",
    "sg:classifiers":[
        {
            "category":"Shopping",
            "subcategory":"Clothing, Apparel, & Fashions",
            "type":"Retail Goods"
        }
    ],
    "sg:phone":"+32 4 342 00 05",
    "sg:postcode":"4020",
    "sg:province":"Li\u00e8ge",
    "sg:tags":[
        "-",
        "clothing",
        "child"
    ],
    "wof:name":"Pierre Perchy",
    "wof:placetype":"venue"
},
  "geometry": {"coordinates":[5.5843319893,50.6320381165],"type":"Point"}
}