{
  "type": "Feature",
  "properties": {
    "iso:country":"BE",
    "sg:address":"Olmendreef 2",
    "sg:city":"De Panne",
    "sg:classifiers":[
        {
            "category":"Arena",
            "subcategory":"Sports Club",
            "type":"Entertainment"
        }
    ],
    "sg:phone":"+32 58 41 19 47",
    "sg:postcode":"8660",
    "sg:province":"West-Vlaanderen",
    "sg:tags":[
        "terrain",
        "hors",
        "de",
        "installation",
        "sportifs"
    ],
    "wof:name":"Westhoek Tennisclub",
    "wof:placetype":"venue"
},
  "geometry": {"coordinates":[2.5952448845,51.0913047791],"type":"Point"}
}