{
  "type": "Feature",
  "properties": {
    "addr:full":"Chemin De La Valli\u00e8re 20 Mons Hainaut 7000",
    "addr:housenumber":"20",
    "addr:postcode":"7000",
    "addr:street":"Chemin De La Vallie\u0300Re;Hainaut",
    "iso:country":"BE",
    "sg:address":"Chemin De La Valli\u00e8re 20",
    "sg:city":"Mons",
    "sg:classifiers":[
        {
            "category":"Health Services",
            "subcategory":"Health Practitioner",
            "type":"Services"
        }
    ],
    "sg:phone":"+32 65 31 77 57",
    "sg:postcode":"7000",
    "sg:province":"Hainaut",
    "sg:tags":[
        "therapist",
        "speech"
    ],
    "wof:name":"De Wolf C Asbl Rep\u00e9rages",
    "wof:placetype":"venue"
},
  "geometry": {"coordinates":[3.9478719234,50.4419746399],"type":"Point"}
}