{
  "type": "Feature",
  "properties": {
    "iso:country":"BE",
    "sg:address":"Villadreef 9",
    "sg:city":"Tremelo",
    "sg:orig_category":"R\u00e9alisation de programmes and logiciels. Conseils en syst\u00e8mes informatiques. Formation and enseignem",
    "sg:phone":"+32 16 53 64 80",
    "sg:postcode":"3128",
    "sg:province":"Vlaams-Brabant",
    "wof:name":"Able",
    "wof:placetype":"venue"
},
  "geometry": {"coordinates":[4.7357478142,50.9938774109],"type":"Point"}
}