{
  "type": "Feature",
  "properties": {
    "iso:country":"BE",
    "sg:address":"Groenhovestraat 26",
    "sg:city":"Torhout",
    "sg:orig_category":"Diverse consumentenartikelen Gh",
    "sg:phone":"+32 50 21 44 67",
    "sg:postcode":"8820",
    "sg:province":"West-Vlaanderen",
    "wof:name":"T.r.s. Cold Water Fish",
    "wof:placetype":"venue"
},
  "geometry": {"coordinates":[3.1288499832,51.0727462769],"type":"Point"}
}