{
  "type": "Feature",
  "properties": {
    "iso:country":"BE",
    "sg:address":"Langestraat 65",
    "sg:city":"Kruibeke",
    "sg:orig_category":"Alimentation sp\u00e9cialis\u00e9e",
    "sg:phone":"+32 3 774 20 74",
    "sg:postcode":"9150",
    "sg:province":"Oost-Vlaanderen",
    "wof:name":"Traiteur Cantarel",
    "wof:placetype":"venue"
},
  "geometry": {"coordinates":[4.3141450882,51.1737251282],"type":"Point"}
}