{
  "type": "Feature",
  "properties": {
    "addr:full":"Rue De Namur 39 Wavre Brabant Wallon 1300",
    "addr:housenumber":"39;1300",
    "addr:street":"Rue De Namur",
    "iso:country":"BE",
    "sg:address":"Rue De Namur 39",
    "sg:city":"Wavre",
    "sg:classifiers":[
        {
            "category":"Education",
            "subcategory":"Special Training",
            "type":"Public Place"
        }
    ],
    "sg:phone":"+32 10 22 80 86",
    "sg:postcode":"1300",
    "sg:province":"Brabant Wallon",
    "sg:tags":[
        "school",
        "language"
    ],
    "wof:name":"Acad\u00e9mie Des Langues",
    "wof:placetype":"venue"
},
  "geometry": {"coordinates":[4.6120262146,50.7123222351],"type":"Point"}
}