{
  "type": "Feature",
  "properties": {
    "addr:full":"Rijselstraat 124 Menen West-Vlaanderen 8930",
    "addr:housenumber":"124",
    "addr:postcode":"8930",
    "addr:street":"Rijselstraat",
    "iso:country":"BE",
    "sg:address":"Rijselstraat 124",
    "sg:city":"Menen",
    "sg:orig_category":"Instituts de beaut\u00e9",
    "sg:phone":"+32 56 51 45 64",
    "sg:postcode":"8930",
    "sg:province":"West-Vlaanderen",
    "wof:name":"Instituut Art Et Beaut\u00c9",
    "wof:placetype":"venue"
},
  "geometry": {"coordinates":[3.1910409927,50.7558174133],"type":"Point"}
}