{
  "type": "Feature",
  "properties": {
    "addr:full":"Frankrijkstraat 35 Berlare Oost-Vlaanderen 9290",
    "addr:housenumber":"35",
    "addr:postcode":"9290",
    "addr:street":"Frankrijkstraat",
    "iso:country":"BE",
    "sg:address":"Frankrijkstraat 35",
    "sg:city":"Berlare",
    "sg:classifiers":[
        {
            "category":"Retail",
            "subcategory":"Repair Shop",
            "type":"Services"
        }
    ],
    "sg:phone":"+32 52 42 35 18",
    "sg:postcode":"9290",
    "sg:province":"Oost-Vlaanderen",
    "sg:tags":[
        "-",
        "mainten",
        "watch",
        "clock"
    ],
    "wof:name":"Van Der Haeghen",
    "wof:placetype":"venue"
},
  "geometry": {"coordinates":[4.0056219101,51.0217247009],"type":"Point"}
}