{
  "type": "Feature",
  "properties": {
    "addr:full":"Steenovenstraat 9a Gistel West-Vlaanderen 8470",
    "addr:housenumber":"9a",
    "addr:postcode":"8470",
    "addr:street":"Steenovenstraat",
    "iso:country":"BE",
    "sg:address":"Steenovenstraat 9a",
    "sg:city":"Gistel",
    "sg:orig_category":"Goederenvervoer over de weg Rundveehouders Varkenskwekers",
    "sg:phone":"+32 59 27 74 30",
    "sg:postcode":"8470",
    "sg:province":"West-Vlaanderen",
    "wof:name":"Urbain Dekeyser",
    "wof:placetype":"venue"
},
  "geometry": {"coordinates":[2.9347770214,51.1784667969],"type":"Point"}
}