{
  "type": "Feature",
  "properties": {
    "iso:country":"BE",
    "sg:address":"Rue Ma Campagne 127",
    "sg:city":"Verviers",
    "sg:orig_category":"Sportclubs",
    "sg:phone":"+32 87 33 29 03",
    "sg:postcode":"4801",
    "sg:province":"Li\u00e8ge",
    "wof:name":"Gym Club Les Provinciales",
    "wof:placetype":"venue"
},
  "geometry": {"coordinates":[5.8930549622,50.5922393799],"type":"Point"}
}