{
  "type": "Feature",
  "properties": {
    "addr:full":"Ginderbuiten 117 Mol Antwerpen 2400",
    "addr:housenumber":"117",
    "addr:postcode":"2400",
    "addr:street":"Ginderbuiten",
    "iso:country":"BE",
    "sg:address":"Ginderbuiten 117",
    "sg:city":"Mol",
    "sg:classifiers":[
        {
            "category":"Home & Garden",
            "subcategory":"Building Materials",
            "type":"Retail Goods"
        }
    ],
    "sg:phone":"+32 14 31 22 95",
    "sg:postcode":"2400",
    "sg:province":"Antwerpen",
    "sg:tags":[
        "rebuilding",
        "chimney"
    ],
    "wof:name":"Louis Swerts B.v.b.a.",
    "wof:placetype":"venue"
},
  "geometry": {"coordinates":[5.146900177,51.2030792236],"type":"Point"}
}