{
  "type": "Feature",
  "properties": {
    "addr:full":"Rue De Rocroi 37 Viroinval Namur 5670",
    "addr:housenumber":"37",
    "addr:postcode":"5670",
    "addr:street":"Rue De Rocroi",
    "iso:country":"BE",
    "sg:address":"Rue De Rocroi 37",
    "sg:city":"Viroinval",
    "sg:orig_category":"Enseignement maternel and primaire",
    "sg:phone":"+32 60 39 07 85",
    "sg:postcode":"5670",
    "sg:province":"Namur",
    "wof:name":"Ecole Fondamentale Libre",
    "wof:placetype":"venue"
},
  "geometry": {"coordinates":[4.634996891,50.0219688416],"type":"Point"}
}