{
  "type": "Feature",
  "properties": {
    "iso:country":"BE",
    "sg:address":"Florimond Leirensstraat 28",
    "sg:city":"Wetteren",
    "sg:classifiers":[
        {
            "category":"Health Services",
            "subcategory":"Dentist",
            "type":"Services"
        }
    ],
    "sg:phone":"+32 9 369 52 14",
    "sg:postcode":"9230",
    "sg:province":"Oost-Vlaanderen",
    "wof:name":"Symons J",
    "wof:placetype":"venue"
},
  "geometry": {"coordinates":[3.8840041161,51.0055274963],"type":"Point"}
}