{
  "type": "Feature",
  "properties": {
    "addr:full":"Puursesteenweg 389 Bornem Antwerpen 2880",
    "addr:housenumber":"389",
    "addr:postcode":"2880",
    "addr:street":"Puursesteenweg",
    "iso:country":"BE",
    "sg:address":"Puursesteenweg 389",
    "sg:city":"Bornem",
    "sg:orig_category":"Installation de menuiserie en bois and plastique. Travaux d'isolation. Mat\u00e9riaux de construction Gr",
    "sg:phone":"+32 3 889 07 37",
    "sg:postcode":"2880",
    "sg:province":"Antwerpen",
    "wof:name":"Van Pellicom N.v.",
    "wof:placetype":"venue"
},
  "geometry": {"coordinates":[4.2627058029,51.0858612061],"type":"Point"}
}