{
  "type": "Feature",
  "properties": {
    "addr:full":"Ridderstraat 22 Herk-de-stad Limburg 3540",
    "addr:housenumber":"22",
    "addr:postcode":"3540",
    "addr:street":"Ridderstraat",
    "iso:country":"BE",
    "sg:address":"Ridderstraat 22",
    "sg:city":"Herk-de-stad",
    "sg:classifiers":[
        {
            "category":"Bars & Pubs",
            "type":"Food & Drink"
        }
    ],
    "sg:phone":"+32 13 55 11 80",
    "sg:postcode":"3540",
    "sg:province":"Limburg",
    "wof:name":"Pallieterke",
    "wof:placetype":"venue"
},
  "geometry": {"coordinates":[5.168943882,50.9403991699],"type":"Point"}
}