{
  "type": "Feature",
  "properties": {
    "addr:full":"Rue De Soleilmont 53 Charleroi Hainaut 6043",
    "addr:housenumber":"53",
    "addr:postcode":"6043",
    "addr:street":"Rue De Soleilmont;Hainaut",
    "iso:country":"BE",
    "sg:address":"Rue De Soleilmont 53",
    "sg:city":"Charleroi",
    "sg:orig_category":"Catering and organisatie van feesten Restaurants Ruimtes voor conferenties, recepties and feesten",
    "sg:phone":"+32 71 37 37 17",
    "sg:postcode":"6043",
    "sg:province":"Hainaut",
    "wof:name":"La Table Des D\u00c9lices",
    "wof:placetype":"venue"
},
  "geometry": {"coordinates":[4.4839549065,50.4479637146],"type":"Point"}
}