{
  "type": "Feature",
  "properties": {
    "addr:full":"Poliaenstraat 1 Stekene Oost-Vlaanderen 9190",
    "addr:housenumber":"1",
    "addr:postcode":"9190",
    "addr:street":"Poliaenstraat",
    "iso:country":"BE",
    "sg:address":"Poliaenstraat 1",
    "sg:city":"Stekene",
    "sg:orig_category":"Eleveurs and marchands de porcs",
    "sg:phone":"+32 3 779 51 27",
    "sg:postcode":"9190",
    "sg:province":"Oost-Vlaanderen",
    "wof:name":"Hubert Linthout",
    "wof:placetype":"venue"
},
  "geometry": {"coordinates":[4.0053482056,51.1943054199],"type":"Point"}
}