{
  "type": "Feature",
  "properties": {
    "iso:country":"BE",
    "sg:address":"Rue De Corbais 47",
    "sg:city":"Mont-saint-guibert",
    "sg:classifiers":[
        {
            "category":"Health Services",
            "subcategory":"Health Practitioner",
            "type":"Services"
        }
    ],
    "sg:phone":"+32 10 65 88 43",
    "sg:postcode":"1435",
    "sg:province":"Brabant Wallon",
    "sg:tags":[
        "physiotherapist"
    ],
    "wof:name":"Gr\u00fcn Paul",
    "wof:placetype":"venue"
},
  "geometry": {"coordinates":[4.6198592186,50.6403923035],"type":"Point"}
}