{
  "type": "Feature",
  "properties": {
    "addr:full":"Rue Hoyoux 77 Herstal Li\u00e8ge 4040",
    "addr:housenumber":"77",
    "addr:postcode":"4040",
    "addr:street":"Rue Hoyoux",
    "iso:country":"BE",
    "sg:address":"Rue Hoyoux 77",
    "sg:city":"Herstal",
    "sg:classifiers":[
        {
            "category":"Military Area",
            "subcategory":"Air Force Base",
            "type":"Public Place"
        }
    ],
    "sg:phone":"+32 4 240 11 55",
    "sg:postcode":"4040",
    "sg:province":"Li\u00e8ge",
    "sg:tags":[
        "balustrade"
    ],
    "wof:name":"Le Boulenge P.",
    "wof:placetype":"venue"
},
  "geometry": {"coordinates":[5.6271510124,50.6615600586],"type":"Point"}
}