{
  "type": "Feature",
  "properties": {
    "addr:full":"Oudenaardsesteenweg 250 Kortrijk West-Vlaanderen 8500",
    "addr:housenumber":"250",
    "addr:postcode":"8500",
    "addr:street":"Oudenaardsesteenweg",
    "iso:country":"BE",
    "sg:address":"Oudenaardsesteenweg 250",
    "sg:city":"Kortrijk",
    "sg:orig_category":"Bloemen and planten",
    "sg:phone":"+32 56 22 34 71",
    "sg:postcode":"8500",
    "sg:province":"West-Vlaanderen",
    "wof:name":"Andre Blauwblomme",
    "wof:placetype":"venue"
},
  "geometry": {"coordinates":[3.2901461124,50.8207778931],"type":"Point"}
}