{
  "type": "Feature",
  "properties": {
    "addr:full":"Doylijkstraat 109 Dilbeek (itterbeek) Vlaams-Brabant 1701",
    "addr:housenumber":"109",
    "addr:postcode":"1701",
    "addr:street":"Doylijkstraat",
    "iso:country":"BE",
    "sg:address":"Doylijkstraat 109",
    "sg:city":"Dilbeek (itterbeek)",
    "sg:orig_category":"Ergotherapists",
    "sg:phone":"+32 2 569 67 50",
    "sg:postcode":"1701",
    "sg:province":"Vlaams-Brabant",
    "wof:name":"Wauthia H",
    "wof:placetype":"venue"
},
  "geometry": {"coordinates":[4.2211298943,50.8208312988],"type":"Point"}
}