{
  "type": "Feature",
  "properties": {
    "iso:country":"BE",
    "sg:address":"Markt 13",
    "sg:city":"Peer",
    "sg:classifiers":[
        {
            "category":"Home & Garden",
            "subcategory":"Home Furnishings",
            "type":"Retail Goods"
        }
    ],
    "sg:phone":"+32 11 63 54 40",
    "sg:postcode":"3990",
    "sg:province":"Limburg",
    "sg:tags":[
        "interior",
        "decoration"
    ],
    "wof:name":"Metamorphose",
    "wof:placetype":"venue"
},
  "geometry": {"coordinates":[5.4542050362,51.1326026917],"type":"Point"}
}