{
  "type": "Feature",
  "properties": {
    "addr:full":"Leiestraat 105 Box 3 Menen (lauwe) West-Vlaanderen 8930",
    "addr:housenumber":"105;3",
    "addr:postcode":"8930",
    "addr:street":"Leiestraat;Box",
    "iso:country":"BE",
    "sg:address":"Leiestraat 105 Box 3",
    "sg:city":"Menen (lauwe)",
    "sg:orig_category":"Beds - Mfg.& Whol",
    "sg:phone":"+32 56 42 22 50",
    "sg:postcode":"8930",
    "sg:province":"West-Vlaanderen",
    "wof:name":"Swissflex Belgium Bvba",
    "wof:placetype":"venue"
},
  "geometry": {"coordinates":[3.1209149361,50.7961845398],"type":"Point"}
}