{
  "type": "Feature",
  "properties": {
    "addr:full":"Kaulillerdorp 51 Bocholt Limburg 3950",
    "addr:housenumber":"51",
    "addr:postcode":"3950",
    "addr:street":"Kaulillerdorp",
    "iso:country":"BE",
    "sg:address":"Kaulillerdorp 51",
    "sg:city":"Bocholt",
    "sg:orig_category":"Enseignement maternel and primaire",
    "sg:phone":"+32 11 44 63 35",
    "sg:postcode":"3950",
    "sg:province":"Limburg",
    "wof:name":"Vrije Lagere School",
    "wof:placetype":"venue"
},
  "geometry": {"coordinates":[5.5197629929,51.1873016357],"type":"Point"}
}