{
  "type": "Feature",
  "properties": {
    "iso:country":"BE",
    "sg:address":"Oostberg 49",
    "sg:city":"Temse",
    "sg:classifiers":[
        {
            "category":"Freight",
            "type":"Transportation"
        }
    ],
    "sg:phone":"+32 3 771 03 77",
    "sg:postcode":"9140",
    "sg:province":"Oost-Vlaanderen",
    "sg:tags":[
        "-",
        "transport"
    ],
    "wof:name":"Meersman",
    "wof:placetype":"venue"
},
  "geometry": {"coordinates":[4.2393431664,51.1260147095],"type":"Point"}
}