{
  "type": "Feature",
  "properties": {
    "addr:full":"Scheldestraat 53 Antwerpen Antwerpen 2000",
    "addr:housenumber":"53",
    "addr:postcode":"2000",
    "addr:street":"Scheldestraat",
    "iso:country":"BE",
    "sg:address":"Scheldestraat 53",
    "sg:city":"Antwerpen",
    "sg:classifiers":[
        {
            "category":"Government",
            "subcategory":"Post Office",
            "type":"Public Place"
        }
    ],
    "sg:phone":"+32 3 244 13 14",
    "sg:postcode":"2000",
    "sg:province":"Antwerpen",
    "sg:tags":[
        "picture",
        "restoring"
    ],
    "wof:name":"De Wieuw Nv",
    "wof:placetype":"venue"
},
  "geometry": {"coordinates":[4.3950219154,51.2117080688],"type":"Point"}
}