{
  "type": "Feature",
  "properties": {
    "addr:full":"Rue Royale 41 Tournai Hainaut 7500",
    "addr:housenumber":"41",
    "addr:postcode":"7500",
    "addr:street":"Rue Royale",
    "iso:country":"BE",
    "sg:address":"Rue Royale 41",
    "sg:city":"Tournai",
    "sg:classifiers":[
        {
            "category":"Home & Garden",
            "subcategory":"Home Furnishings",
            "type":"Retail Goods"
        }
    ],
    "sg:phone":"+32 69 84 35 07",
    "sg:postcode":"7500",
    "sg:province":"Hainaut",
    "sg:tags":[
        "interior",
        "decoration"
    ],
    "wof:name":"Maison Mahdani",
    "wof:placetype":"venue"
},
  "geometry": {"coordinates":[3.3924639225,50.6092910767],"type":"Point"}
}