{
  "type": "Feature",
  "properties": {
    "addr:full":"Rue Louis De Brouck\u00c8re 105 La Louvi\u00c8re Hainaut 7100",
    "addr:housenumber":"105",
    "addr:postcode":"7100",
    "addr:street":"Rue Louis De Broucke\u0300Re",
    "iso:country":"BE",
    "sg:address":"Rue Louis De Brouck\u00c8re 105",
    "sg:city":"La Louvi\u00c8re",
    "sg:classifiers":[
        {
            "category":"Shopping",
            "subcategory":"Clothing, Apparel, & Fashions",
            "type":"Retail Goods"
        }
    ],
    "sg:phone":"+32 64 22 18 24",
    "sg:postcode":"7100",
    "sg:province":"Hainaut",
    "sg:tags":[
        "v\u00eatements",
        "pour",
        "dame"
    ],
    "wof:name":"Maison Madame Pierre",
    "wof:placetype":"venue"
},
  "geometry": {"coordinates":[4.1912631989,50.4806938171],"type":"Point"}
}