{
  "type": "Feature",
  "properties": {
    "addr:full":"Avenue Victor Maistriau 74 Mons Hainaut 7000",
    "addr:housenumber":"74",
    "addr:postcode":"7000",
    "addr:street":"Avenue Victor Maistriau;Hainaut",
    "iso:country":"BE",
    "sg:address":"Avenue Victor Maistriau 74",
    "sg:city":"Mons",
    "sg:orig_category":"Elektrische installaties voor woningen",
    "sg:phone":"+32 65 84 58 27",
    "sg:postcode":"7000",
    "sg:province":"Hainaut",
    "wof:name":"Michael Prestilio",
    "wof:placetype":"venue"
},
  "geometry": {"coordinates":[3.9581699371,50.4638710022],"type":"Point"}
}