{
  "type": "Feature",
  "properties": {
    "iso:country":"BE",
    "sg:address":"Chauss\u00e9e D'alsemberg 368-370",
    "sg:city":"Bruxelles (uccle)",
    "sg:orig_category":"Non-Classified Establishments",
    "sg:phone":"+32 2 346 84 42",
    "sg:postcode":"1180",
    "sg:province":"Bruxelles-Capitale",
    "wof:name":"Dyna-m\u00e9dical",
    "wof:placetype":"venue"
},
  "geometry": {"coordinates":[4.3395938873,50.8147277832],"type":"Point"}
}