{
  "type": "Feature",
  "properties": {
    "addr:full":"Labbelaan 46 Overijse Vlaams-Brabant 3090",
    "addr:housenumber":"46",
    "addr:postcode":"3090",
    "addr:street":"Labbelaan",
    "iso:country":"BE",
    "sg:address":"Labbelaan 46",
    "sg:city":"Overijse",
    "sg:orig_category":"Immobili\u00ebnkantoren",
    "sg:phone":"+32 2 688 23 70",
    "sg:postcode":"3090",
    "sg:province":"Vlaams-Brabant",
    "wof:name":"Eurem",
    "wof:placetype":"venue"
},
  "geometry": {"coordinates":[4.5085301399,50.7355918884],"type":"Point"}
}