{
  "type": "Feature",
  "properties": {
    "iso:country":"BE",
    "sg:address":"Dudzeelse Steenweg 321",
    "sg:city":"Brugge",
    "sg:classifiers":[
        {
            "category":"Health Services",
            "subcategory":"Doctor",
            "type":"Services"
        }
    ],
    "sg:phone":"+32 50 59 97 58",
    "sg:postcode":"8000",
    "sg:province":"West-Vlaanderen",
    "sg:tags":[
        "medicinephysicians",
        "surgeon"
    ],
    "wof:name":"Lust P",
    "wof:placetype":"venue"
},
  "geometry": {"coordinates":[3.2316861153,51.2407417297],"type":"Point"}
}