{
  "type": "Feature",
  "properties": {
    "iso:country":"BE",
    "sg:address":"Avenue Des Tilleuls 79",
    "sg:city":"Bruxelles (uccle)",
    "sg:classifiers":[
        {
            "category":"Professional",
            "subcategory":"Business Services",
            "type":"Services"
        }
    ],
    "sg:phone":"+32 2 374 61 66",
    "sg:postcode":"1180",
    "sg:province":"Bruxelles-Capitale",
    "sg:tags":[
        "firm"
    ],
    "wof:name":"Grosjean C",
    "wof:placetype":"venue"
},
  "geometry": {"coordinates":[4.3373222351,50.778591156],"type":"Point"}
}