{
  "type": "Feature",
  "properties": {
    "addr:full":"Aalsterse Steenweg 105 Aalst Oost-Vlaanderen 9310",
    "addr:housenumber":"105",
    "addr:postcode":"9310",
    "addr:street":"Steenweg",
    "iso:country":"BE",
    "sg:address":"Aalsterse Steenweg 105",
    "sg:city":"Aalst",
    "sg:orig_category":"Entretien and r\u00e9parations de voitures",
    "sg:phone":"+32 53 21 49 01",
    "sg:postcode":"9310",
    "sg:province":"Oost-Vlaanderen",
    "wof:name":"Benoni Carle",
    "wof:placetype":"venue"
},
  "geometry": {"coordinates":[4.098400116,50.9477767944],"type":"Point"}
}