{
  "type": "Feature",
  "properties": {
    "iso:country":"BE",
    "sg:address":"Rue Vandervelde 36",
    "sg:city":"Thuin",
    "sg:orig_category":"Quincailleries",
    "sg:phone":"+32 71 51 74 95",
    "sg:postcode":"6534",
    "sg:province":"Hainaut",
    "wof:name":"Cr\u00c9a-home",
    "wof:placetype":"venue"
},
  "geometry": {"coordinates":[4.3526148796,50.342464447],"type":"Point"}
}