{
  "type": "Feature",
  "properties": {
    "addr:full":"Lindestraat 65 Zedelgem West-Vlaanderen 8210",
    "addr:housenumber":"65",
    "addr:postcode":"8210",
    "addr:street":"Lindestraat",
    "iso:country":"BE",
    "sg:address":"Lindestraat 65",
    "sg:city":"Zedelgem",
    "sg:orig_category":"Boekhouders",
    "sg:phone":"+32 50 20 95 08",
    "sg:postcode":"8210",
    "sg:province":"West-Vlaanderen",
    "wof:name":"Johan Verplancke",
    "wof:placetype":"venue"
},
  "geometry": {"coordinates":[3.1440749168,51.135635376],"type":"Point"}
}