{
  "type": "Feature",
  "properties": {
    "addr:full":"Rue Du Commerce 17 Andenne Namur 5300",
    "addr:housenumber":"17",
    "addr:postcode":"5300",
    "addr:street":"Rue Du Commerce",
    "iso:country":"BE",
    "sg:address":"Rue Du Commerce 17",
    "sg:city":"Andenne",
    "sg:orig_category":"Foto-uitrusting Fotografen and fotostudio's",
    "sg:phone":"+32 85 84 11 20",
    "sg:postcode":"5300",
    "sg:province":"Namur",
    "wof:name":"Studio Pinon",
    "wof:placetype":"venue"
},
  "geometry": {"coordinates":[5.0975642204,50.4886322021],"type":"Point"}
}