{
  "type": "Feature",
  "properties": {
    "addr:full":"Stationsstraat 25 Sint-katelijne-waver Antwerpen 2860",
    "addr:housenumber":"25",
    "addr:postcode":"2860",
    "addr:street":"Stationsstraat",
    "iso:country":"BE",
    "sg:address":"Stationsstraat 25",
    "sg:city":"Sint-katelijne-waver",
    "sg:classifiers":[
        {
            "category":"Retail",
            "subcategory":"Animal Services",
            "type":"Services"
        }
    ],
    "sg:phone":"+32 15 31 55 50",
    "sg:postcode":"2860",
    "sg:province":"Antwerpen",
    "sg:tags":[
        "grooming",
        "-",
        "dog"
    ],
    "wof:name":"Ines",
    "wof:placetype":"venue"
},
  "geometry": {"coordinates":[4.5300178528,51.0704803467],"type":"Point"}
}