{
  "type": "Feature",
  "properties": {
    "iso:country":"BE",
    "sg:address":"Damstraat 89",
    "sg:city":"Zemst",
    "sg:orig_category":"M\u00e9decins and sp\u00e9cialistes",
    "sg:phone":"+32 15 61 32 22",
    "sg:postcode":"1982",
    "sg:province":"Vlaams-Brabant",
    "wof:name":"Hugo Vertongen",
    "wof:placetype":"venue"
},
  "geometry": {"coordinates":[4.4719610214,50.973197937],"type":"Point"}
}