{
  "type": "Feature",
  "properties": {
    "iso:country":"BE",
    "sg:address":"Godefriduskaai 12",
    "sg:city":"Antwerpen",
    "sg:orig_category":"Huishoudapparaten, televisies and radio's",
    "sg:phone":"+32 3 233 69 26",
    "sg:postcode":"2000",
    "sg:province":"Antwerpen",
    "wof:name":"Nani Ki Dukan",
    "wof:placetype":"venue"
},
  "geometry": {"coordinates":[4.4067687988,51.2278251648],"type":"Point"}
}