{
  "type": "Feature",
  "properties": {
    "iso:country":"BE",
    "sg:address":"Rue Wilmart 65",
    "sg:city":"Ch\u00e2telet (ch\u00e2telineau)",
    "sg:classifiers":[
        {
            "category":"Utilities",
            "subcategory":"Fuel Oil & Lpg",
            "type":"Services"
        }
    ],
    "sg:phone":"+32 71 40 10 50",
    "sg:postcode":"6200",
    "sg:province":"Hainaut",
    "wof:name":"Carbobois Sa",
    "wof:placetype":"venue"
},
  "geometry": {"coordinates":[4.5104250908,50.4074325562],"type":"Point"}
}