{
  "type": "Feature",
  "properties": {
    "iso:country":"BE",
    "sg:address":"Rue De March\u00c9 19",
    "sg:city":"Rochefort",
    "sg:classifiers":[
        {
            "category":"Travel",
            "subcategory":"Hotels & Motels",
            "type":"Entertainment"
        }
    ],
    "sg:phone":"+32 84 21 32 40",
    "sg:postcode":"5580",
    "sg:province":"Namur",
    "sg:tags":[
        "restaurant"
    ],
    "wof:name":"Trou Maulin",
    "wof:placetype":"venue"
},
  "geometry": {"coordinates":[5.2248220444,50.1577529907],"type":"Point"}
}