{
  "type": "Feature",
  "properties": {
    "addr:full":"Wijnegemsteenweg 9 Schilde ('s Gravenwezel) Antwerpen 2970",
    "addr:housenumber":"9",
    "addr:postcode":"2970",
    "addr:street":"Wijnegemsteenweg;S",
    "iso:country":"BE",
    "sg:address":"Wijnegemsteenweg 9",
    "sg:city":"Schilde ('s Gravenwezel)",
    "sg:classifiers":[
        {
            "category":"Health Services",
            "subcategory":"Health Practitioner",
            "type":"Services"
        }
    ],
    "sg:phone":"+32 3 658 08 45",
    "sg:postcode":"2970",
    "sg:province":"Antwerpen",
    "sg:tags":[
        "physiotherapist"
    ],
    "wof:name":"Pauwels Paul",
    "wof:placetype":"venue"
},
  "geometry": {"coordinates":[4.5505738258,51.2629203796],"type":"Point"}
}