{
  "type": "Feature",
  "properties": {
    "iso:country":"BE",
    "sg:address":"Pater Kenislaan 27",
    "sg:city":"Schilde",
    "sg:orig_category":"Maatschappelijke dienstverlening",
    "sg:phone":"+32 3 383 61 66",
    "sg:postcode":"2970",
    "sg:province":"Antwerpen",
    "wof:name":"Rode Kruis Schilde",
    "wof:placetype":"venue"
},
  "geometry": {"coordinates":[4.57543993,51.2476501465],"type":"Point"}
}