{
  "type": "Feature",
  "properties": {
    "addr:full":"Lange Munte 75ba Oosterzele Oost-Vlaanderen 9860",
    "addr:housenumber":"75ba",
    "addr:postcode":"9860",
    "addr:street":"Lange Munte;Oost-Vlaanderen",
    "iso:country":"BE",
    "sg:address":"Lange Munte 75ba",
    "sg:city":"Oosterzele",
    "sg:orig_category":"Boomkwekerijen",
    "sg:phone":"+32 9 362 90 54",
    "sg:postcode":"9860",
    "sg:province":"Oost-Vlaanderen",
    "wof:name":"Marc Calle",
    "wof:placetype":"venue"
},
  "geometry": {"coordinates":[3.756166935,50.9202537537],"type":"Point"}
}