{
  "type": "Feature",
  "properties": {
    "iso:country":"BE",
    "sg:address":"Bergstrasse 25",
    "sg:city":"Eupen",
    "sg:classifiers":[
        {
            "category":"Shopping",
            "subcategory":"Shoes",
            "type":"Retail Goods"
        }
    ],
    "sg:phone":"+32 87 55 24 32",
    "sg:postcode":"4700",
    "sg:province":"Li\u00e8ge",
    "sg:tags":[
        "slipper",
        "-"
    ],
    "wof:name":"Fischer",
    "wof:placetype":"venue"
},
  "geometry": {"coordinates":[6.0334057808,50.6293792725],"type":"Point"}
}