{
  "type": "Feature",
  "properties": {
    "addr:full":"Chauss\u00e9e De Marche 486 Namur (erpent) Namur 5101",
    "addr:housenumber":"486",
    "addr:postcode":"5101",
    "addr:street":"Chausse\u0301E De Marche",
    "iso:country":"BE",
    "sg:address":"Chauss\u00e9e De Marche 486",
    "sg:city":"Namur (erpent)",
    "sg:classifiers":[
        {
            "category":"Professional",
            "subcategory":"Lawyer & Legal Services",
            "type":"Services"
        }
    ],
    "sg:phone":"+32 81 22 63 83",
    "sg:postcode":"5101",
    "sg:province":"Namur",
    "wof:name":"Bodson A",
    "wof:placetype":"venue"
},
  "geometry": {"coordinates":[4.8996109962,50.4452819824],"type":"Point"}
}