{
  "type": "Feature",
  "properties": {
    "addr:full":"Boulevard Du Jubil\u00e9 172 Bruxelles (molenbeek-saint-jean) Bruxelles-Capitale 1080",
    "addr:housenumber":"172",
    "addr:postcode":"1080",
    "addr:street":"Boulevard Du Jubile\u0301",
    "iso:country":"BE",
    "sg:address":"Boulevard Du Jubil\u00e9 172",
    "sg:city":"Bruxelles (molenbeek-saint-jean)",
    "sg:classifiers":[
        {
            "category":"Personal",
            "subcategory":"Barber",
            "type":"Services"
        }
    ],
    "sg:phone":"+32 2 426 96 11",
    "sg:postcode":"1080",
    "sg:province":"Bruxelles-Capitale",
    "sg:tags":[
        "gentleman",
        "salon",
        "-",
        "hairdressing"
    ],
    "wof:name":"Elegance",
    "wof:placetype":"venue"
},
  "geometry": {"coordinates":[4.3408279419,50.8681564331],"type":"Point"}
}