{
  "type": "Feature",
  "properties": {
    "addr:full":"Nieuwstraat 18 Tienen Vlaams-Brabant 3300",
    "addr:housenumber":"18",
    "addr:postcode":"3300",
    "addr:street":"Nieuwstraat",
    "iso:country":"BE",
    "sg:address":"Nieuwstraat 18",
    "sg:city":"Tienen",
    "sg:orig_category":"Banken and kredietinstellingen",
    "sg:phone":"+32 16 81 35 36",
    "sg:postcode":"3300",
    "sg:province":"Vlaams-Brabant",
    "wof:name":"Fortis",
    "wof:placetype":"venue"
},
  "geometry": {"coordinates":[4.939098835,50.8068885803],"type":"Point"}
}