{
  "type": "Feature",
  "properties": {
    "addr:full":"Stationsstraat 19 Oostkamp West-Vlaanderen 8020",
    "addr:housenumber":"19",
    "addr:postcode":"8020",
    "addr:street":"Stationsstraat",
    "iso:country":"BE",
    "sg:address":"Stationsstraat 19",
    "sg:city":"Oostkamp",
    "sg:classifiers":[
        {
            "category":"Arena",
            "subcategory":"Sports Club",
            "type":"Entertainment"
        }
    ],
    "sg:phone":"+32 50 82 42 85",
    "sg:postcode":"8020",
    "sg:province":"West-Vlaanderen",
    "sg:tags":[
        "de"
    ],
    "wof:name":"Tortuga Divers Bredene",
    "wof:placetype":"venue"
},
  "geometry": {"coordinates":[3.2368381023,51.1544532776],"type":"Point"}
}