{
  "type": "Feature",
  "properties": {
    "addr:full":"Rue Du Cimeti\u00c8re 17ba Fl\u00c9ron Li\u00e8ge 4624",
    "addr:housenumber":"17ba",
    "addr:postcode":"4624",
    "addr:street":"Rue Du Cimetie\u0300Re",
    "iso:country":"BE",
    "sg:address":"Rue Du Cimeti\u00c8re 17ba",
    "sg:city":"Fl\u00c9ron",
    "sg:orig_category":"Boekhouders",
    "sg:phone":"+32 4 358 10 45",
    "sg:postcode":"4624",
    "sg:province":"Li\u00e8ge",
    "wof:name":"Cath\u00c9rine Grandidier",
    "wof:placetype":"venue"
},
  "geometry": {"coordinates":[5.6664028168,50.5999298096],"type":"Point"}
}