{
  "type": "Feature",
  "properties": {
    "addr:full":"Dorpsstraat 8 Brugge West-Vlaanderen 8200",
    "addr:housenumber":"8",
    "addr:postcode":"8200",
    "addr:street":"Dorpsstraat",
    "iso:country":"BE",
    "sg:address":"Dorpsstraat 8",
    "sg:city":"Brugge",
    "sg:orig_category":"Banques and organismes de cr\u00e9dit",
    "sg:phone":"+32 50 38 08 47",
    "sg:postcode":"8200",
    "sg:province":"West-Vlaanderen",
    "wof:name":"Bacob",
    "wof:placetype":"venue"
},
  "geometry": {"coordinates":[3.2125298977,51.1884613037],"type":"Point"}
}