{
  "type": "Feature",
  "properties": {
    "addr:full":"Blauwesteen 111 Ronse/renaix Oost-Vlaanderen 9600",
    "addr:housenumber":"111",
    "addr:postcode":"9600",
    "addr:street":"Blauwesteen",
    "iso:country":"BE",
    "sg:address":"Blauwesteen 111",
    "sg:city":"Ronse/renaix",
    "sg:orig_category":"Pain, p\u00e2tisseries and confiseries",
    "sg:phone":"+32 55 21 24 89",
    "sg:postcode":"9600",
    "sg:province":"Oost-Vlaanderen",
    "wof:name":"Erwin Elet",
    "wof:placetype":"venue"
},
  "geometry": {"coordinates":[3.6175780296,50.7438659668],"type":"Point"}
}