{
  "type": "Feature",
  "properties": {
    "iso:country":"BE",
    "sg:address":"Grote Hondstraat 44",
    "sg:city":"Antwerpen",
    "sg:classifiers":[
        {
            "category":"Banks & Credit Unions",
            "subcategory":"Investment Brokerage",
            "type":"Services"
        }
    ],
    "sg:phone":"+32 3 287 88 70",
    "sg:postcode":"2018",
    "sg:province":"Antwerpen",
    "wof:name":"Spaar Select Antwerpen Bvba",
    "wof:placetype":"venue"
},
  "geometry": {"coordinates":[4.4293160439,51.2058906555],"type":"Point"}
}