{
  "type": "Feature",
  "properties": {
    "iso:country":"BE",
    "sg:address":".",
    "sg:city":"Wijnegem",
    "sg:orig_category":"Dameskledingzaken",
    "sg:phone":"+32 3 353 12 95",
    "sg:postcode":"2110",
    "sg:province":"Antwerpen",
    "wof:name":"Caf\u00c9 Au Lait",
    "wof:placetype":"venue"
},
  "geometry": {"coordinates":[4.5248470306,51.2279434204],"type":"Point"}
}