{
  "type": "Feature",
  "properties": {
    "addr:full":"Rue De Graty 18 Silly Hainaut 7830",
    "addr:housenumber":"18",
    "addr:postcode":"7830",
    "addr:street":"Rue De Graty",
    "iso:country":"BE",
    "sg:address":"Rue De Graty 18",
    "sg:city":"Silly",
    "sg:classifiers":[
        {
            "category":"Arena",
            "subcategory":"Sports Club",
            "type":"Entertainment"
        }
    ],
    "sg:phone":"+32 477 22 82 55",
    "sg:postcode":"7830",
    "sg:province":"Hainaut",
    "sg:tags":[
        "de"
    ],
    "wof:name":"A.c Lessines-enghien",
    "wof:placetype":"venue"
},
  "geometry": {"coordinates":[4.033408165,50.6688194275],"type":"Point"}
}