{
  "type": "Feature",
  "properties": {
    "addr:full":"Groenestraat 19 Ieper (sint-jan) West-Vlaanderen 8900",
    "addr:housenumber":"19",
    "addr:postcode":"8900",
    "addr:street":"Groenestraat",
    "iso:country":"BE",
    "sg:address":"Groenestraat 19",
    "sg:city":"Ieper (sint-jan)",
    "sg:classifiers":[
        {
            "category":"Retail",
            "subcategory":"Auto Repair",
            "type":"Services"
        }
    ],
    "sg:phone":"+32 57 20 22 50",
    "sg:postcode":"8900",
    "sg:province":"West-Vlaanderen",
    "sg:tags":[
        "-",
        "motor",
        "overhauling"
    ],
    "wof:name":"Devos O & L",
    "wof:placetype":"venue"
},
  "geometry": {"coordinates":[2.9017000198,50.8668251038],"type":"Point"}
}