{
  "type": "Feature",
  "properties": {
    "addr:full":"Chauss\u00c9e De Bruxelles 354 Ath Hainaut 7822",
    "addr:housenumber":"354",
    "addr:postcode":"7822",
    "addr:street":"Chausse\u0301E De Bruxelles",
    "iso:country":"BE",
    "sg:address":"Chauss\u00c9e De Bruxelles 354",
    "sg:city":"Ath",
    "sg:orig_category":"Bloemen and planten",
    "sg:phone":"+32 68 28 10 58",
    "sg:postcode":"7822",
    "sg:province":"Hainaut",
    "wof:name":"Vannes Fleurs Lepoivre",
    "wof:placetype":"venue"
},
  "geometry": {"coordinates":[3.8858850002,50.6560249329],"type":"Point"}
}