{
  "type": "Feature",
  "properties": {
    "iso:country":"BE",
    "sg:address":"Avenue L\u00c9onard Legras 25",
    "sg:city":"Jalhay",
    "sg:orig_category":"Sportclubs",
    "sg:phone":"+32 87 47 52 38",
    "sg:postcode":"4845",
    "sg:province":"Li\u00e8ge",
    "wof:name":"Les Corsaires",
    "wof:placetype":"venue"
},
  "geometry": {"coordinates":[5.956908226,50.5016593933],"type":"Point"}
}