{
  "type": "Feature",
  "properties": {
    "iso:country":"BE",
    "sg:address":"Halensebaan 152",
    "sg:city":"Diest",
    "sg:classifiers":[
        {
            "category":"Travel",
            "subcategory":"Hotels & Motels",
            "type":"Entertainment"
        }
    ],
    "sg:phone":"+32 13 35 10 70",
    "sg:postcode":"3290",
    "sg:province":"Vlaams-Brabant",
    "wof:name":"Prins Van Oranje",
    "wof:placetype":"venue"
},
  "geometry": {"coordinates":[5.0781078339,50.9661026001],"type":"Point"}
}