{
  "type": "Feature",
  "properties": {
    "addr:full":"Bree\u00cbrsteenweg 248 Kinrooi Limburg 3640",
    "addr:housenumber":"248",
    "addr:postcode":"3640",
    "addr:street":"Breee\u0308Rsteenweg",
    "iso:country":"BE",
    "sg:address":"Bree\u00cbrsteenweg 248",
    "sg:city":"Kinrooi",
    "sg:orig_category":"Bouwmaterialen Gh Hout and afgeleiden Gh Houtbewerking and -behandeling IJzerwaren, bouw- and verfma",
    "sg:phone":"+32 89 70 33 86",
    "sg:postcode":"3640",
    "sg:province":"Limburg",
    "wof:name":"Zaveco",
    "wof:placetype":"venue"
},
  "geometry": {"coordinates":[5.7449808121,51.1457252502],"type":"Point"}
}