{
  "type": "Feature",
  "properties": {
    "iso:country":"BE",
    "sg:address":"Rue De Saint-paul 35",
    "sg:city":"Walhain",
    "sg:orig_category":"Banken and kredietinstellingen",
    "sg:phone":"+32 10 65 87 35",
    "sg:postcode":"1457",
    "sg:province":"Brabant Wallon",
    "wof:name":"Home Partners",
    "wof:placetype":"venue"
},
  "geometry": {"coordinates":[4.701321125,50.6285743713],"type":"Point"}
}