{
  "type": "Feature",
  "properties": {
    "iso:country":"BE",
    "sg:address":"Stationsstraat 38",
    "sg:city":"Linter (drieslinter)",
    "sg:classifiers":[
        {
            "category":"Health Services",
            "subcategory":"Health Practitioner",
            "type":"Services"
        }
    ],
    "sg:phone":"+32 11 78 15 76",
    "sg:postcode":"3350",
    "sg:province":"Vlaams-Brabant",
    "sg:tags":[
        "physiotherapist"
    ],
    "wof:name":"De Smedt L",
    "wof:placetype":"venue"
},
  "geometry": {"coordinates":[5.0555510521,50.8448257446],"type":"Point"}
}