{
  "type": "Feature",
  "properties": {
    "addr:full":"Keldermeersbaan 1 Ninove Oost-Vlaanderen 9400",
    "addr:housenumber":"1",
    "addr:postcode":"9400",
    "addr:street":"Keldermeersbaan",
    "iso:country":"BE",
    "sg:address":"Keldermeersbaan 1",
    "sg:city":"Ninove",
    "sg:orig_category":"Bouwmaterialen Gh Loodgieterij and centrale verwarming Gh",
    "sg:phone":"+32 54 33 28 79",
    "sg:postcode":"9400",
    "sg:province":"Oost-Vlaanderen",
    "wof:name":"Dortant 2001",
    "wof:placetype":"venue"
},
  "geometry": {"coordinates":[4.0332298279,50.8404808044],"type":"Point"}
}