{
  "type": "Feature",
  "properties": {
    "addr:full":"Hoogdorpsstraat 28 Alken Limburg 3570",
    "addr:housenumber":"28",
    "addr:postcode":"3570",
    "addr:street":"Hoogdorpsstraat",
    "iso:country":"BE",
    "sg:address":"Hoogdorpsstraat 28",
    "sg:city":"Alken",
    "sg:orig_category":"Banques and organismes de cr\u00e9dit",
    "sg:phone":"+32 11 31 12 34",
    "sg:postcode":"3570",
    "sg:province":"Limburg",
    "wof:name":"Fortis",
    "wof:placetype":"venue"
},
  "geometry": {"coordinates":[5.3062968254,50.8755531311],"type":"Point"}
}