{
  "type": "Feature",
  "properties": {
    "addr:full":"Rue Du Gruyer 20 Bruxelles (watermael-boitsfort) Bruxelles-Capitale 1170",
    "addr:housenumber":"20",
    "addr:postcode":"1170",
    "addr:street":"Rue Du Gruyer",
    "iso:country":"BE",
    "sg:address":"Rue Du Gruyer 20",
    "sg:city":"Bruxelles (watermael-boitsfort)",
    "sg:classifiers":[
        {
            "category":"Communications",
            "subcategory":"Film & Video Production",
            "type":"Services"
        }
    ],
    "sg:phone":"+32 2 660 65 22",
    "sg:postcode":"1170",
    "sg:province":"Bruxelles-Capitale",
    "sg:tags":[
        "producer",
        "realizators"
    ],
    "wof:name":"Xanadu",
    "wof:placetype":"venue"
},
  "geometry": {"coordinates":[4.4044399261,50.811050415],"type":"Point"}
}