{
  "type": "Feature",
  "properties": {
    "iso:country":"BE",
    "sg:address":"Broekstraat 126",
    "sg:city":"Sint-agatha-berchem/berchem-sainte-agathe",
    "sg:orig_category":"Boekhouders",
    "sg:phone":"+32 2 465 84 43",
    "sg:postcode":"1082",
    "sg:province":"Bruxelles-Capitale",
    "wof:name":"Murielle Withoeck",
    "wof:placetype":"venue"
},
  "geometry": {"coordinates":[4.287610054,50.8660621643],"type":"Point"}
}