{
  "type": "Feature",
  "properties": {
    "addr:full":"Avenue Des Combattants 0 Ottignies-louvain-la-neuve Brabant Wallon 1340",
    "addr:housenumber":"0",
    "addr:postcode":"1340",
    "addr:street":"Avenue Des Combattants",
    "iso:country":"BE",
    "sg:address":"Avenue Des Combattants 0",
    "sg:city":"Ottignies-louvain-la-neuve",
    "sg:classifiers":[
        {
            "category":"Restaurant",
            "type":"Food & Drink"
        }
    ],
    "sg:phone":"+32 10 61 16 64",
    "sg:postcode":"1340",
    "sg:province":"Brabant Wallon",
    "wof:name":"La Vigna",
    "wof:placetype":"venue"
},
  "geometry": {"coordinates":[4.5683560371,50.6675033569],"type":"Point"}
}