{
  "type": "Feature",
  "properties": {
    "iso:country":"BE",
    "sg:address":"Rue Alphonse Briart 25",
    "sg:city":"Chapelle-lez-herlaimont",
    "sg:orig_category":"Services pour animaux domestiques",
    "sg:phone":"+32 64 44 43 46",
    "sg:postcode":"7160",
    "sg:province":"Hainaut",
    "wof:name":"Cr\u00c9a Doc",
    "wof:placetype":"venue"
},
  "geometry": {"coordinates":[4.2822599411,50.4715881348],"type":"Point"}
}