{
  "type": "Feature",
  "properties": {
    "addr:full":"Rue Edgard Doneux 2 Flemalle Li\u00e8ge 4400",
    "addr:housenumber":"2",
    "addr:postcode":"4400",
    "addr:street":"Rue Edgard Doneux",
    "iso:country":"BE",
    "sg:address":"Rue Edgard Doneux 2",
    "sg:city":"Flemalle",
    "sg:orig_category":"Equipement photographique. Studios photographiques",
    "sg:phone":"+32 4 231 04 06",
    "sg:postcode":"4400",
    "sg:province":"Li\u00e8ge",
    "wof:name":"Photo Courtois",
    "wof:placetype":"venue"
},
  "geometry": {"coordinates":[5.4676408768,50.5985298157],"type":"Point"}
}