{
  "type": "Feature",
  "properties": {
    "iso:country":"BE",
    "sg:address":"Rue Des Hautes Hur\u00c9es 1",
    "sg:city":"Nivelles",
    "sg:orig_category":"Boekhouders",
    "sg:phone":"+32 67 21 10 33",
    "sg:postcode":"1400",
    "sg:province":"Brabant Wallon",
    "wof:name":"De Smet France & Philippe",
    "wof:placetype":"venue"
},
  "geometry": {"coordinates":[4.3121781349,50.5973358154],"type":"Point"}
}