{
  "type": "Feature",
  "properties": {
    "iso:country":"BE",
    "sg:address":"Hundelgemsesteenweg 519",
    "sg:city":"Merelbeke",
    "sg:classifiers":[
        {
            "category":"Real Estate",
            "subcategory":"Real Estate Services",
            "type":"Services"
        }
    ],
    "sg:phone":"+32 9 230 70 33",
    "sg:postcode":"9820",
    "sg:province":"Oost-Vlaanderen",
    "wof:name":"Verstraeten Peter Vastgoed",
    "wof:placetype":"venue"
},
  "geometry": {"coordinates":[3.7463030815,50.9861068726],"type":"Point"}
}