{
  "type": "Feature",
  "properties": {
    "addr:full":"Melkerijstraat 1ba Anderlecht Bruxelles-Capitale 1070",
    "addr:housenumber":"1ba",
    "addr:postcode":"1070",
    "addr:street":"Melkerijstraat",
    "iso:country":"BE",
    "sg:address":"Melkerijstraat 1ba",
    "sg:city":"Anderlecht",
    "sg:orig_category":"Koerierbedrijven",
    "sg:phone":"+32 2 415 99 37",
    "sg:postcode":"1070",
    "sg:province":"Bruxelles-Capitale",
    "wof:name":"Nicolas Papadopoulos",
    "wof:placetype":"venue"
},
  "geometry": {"coordinates":[4.3087887764,50.8479995728],"type":"Point"}
}