{
  "type": "Feature",
  "properties": {
    "addr:full":"Venusstraat 10 Ranst Antwerpen 2520",
    "addr:housenumber":"10",
    "addr:postcode":"2520",
    "addr:street":"Venusstraat",
    "iso:country":"BE",
    "sg:address":"Venusstraat 10",
    "sg:city":"Ranst",
    "sg:orig_category":"Salles de conf\u00e9rences and de r\u00e9ceptions",
    "sg:phone":"+32 3 384 11 87",
    "sg:postcode":"2520",
    "sg:province":"Antwerpen",
    "wof:name":"Parochiezaal",
    "wof:placetype":"venue"
},
  "geometry": {"coordinates":[4.5622401237,51.1892051697],"type":"Point"}
}