{
  "type": "Feature",
  "properties": {
    "addr:full":"Rue Du Ham 121 Bruxelles (uccle) Bruxelles-Capitale 1180",
    "addr:housenumber":"121",
    "addr:postcode":"1180",
    "addr:street":"Rue Du Ham",
    "iso:country":"BE",
    "sg:address":"Rue Du Ham 121",
    "sg:city":"Bruxelles (uccle)",
    "sg:classifiers":[
        {
            "category":"Education",
            "subcategory":"Special Training",
            "type":"Public Place"
        }
    ],
    "sg:phone":"+32 2 375 08 43",
    "sg:postcode":"1180",
    "sg:province":"Bruxelles-Capitale",
    "sg:tags":[
        "professional"
    ],
    "wof:name":"Finance Communicat. Management",
    "wof:placetype":"venue"
},
  "geometry": {"coordinates":[4.3696489334,50.7907676697],"type":"Point"}
}