{
  "type": "Feature",
  "properties": {
    "iso:country":"BE",
    "sg:address":"Fays 19a",
    "sg:city":"Ciney (ach\u00eane)",
    "sg:classifiers":[
        {
            "category":"Building & Trades",
            "subcategory":"Landscaping Services",
            "type":"Services"
        }
    ],
    "sg:phone":"+32 83 21 83 61",
    "sg:postcode":"5590",
    "sg:province":"Namur",
    "sg:tags":[
        "architect",
        "landscape"
    ],
    "wof:name":"Van Wanterghem",
    "wof:placetype":"venue"
},
  "geometry": {"coordinates":[5.1022520065,50.297088623],"type":"Point"}
}