{
  "type": "Feature",
  "properties": {
    "iso:country":"BE",
    "sg:address":"Rue De La Colline 118",
    "sg:city":"Frameries",
    "sg:classifiers":[
        {
            "category":"Fast Food",
            "type":"Food & Drink"
        }
    ],
    "sg:phone":"+32 65 66 32 07",
    "sg:postcode":"7080",
    "sg:province":"Hainaut",
    "sg:tags":[
        "\u00c0",
        "restaurants",
        "emporter",
        "restaurant"
    ],
    "wof:name":"Chalet Des Mignons",
    "wof:placetype":"venue"
},
  "geometry": {"coordinates":[3.8773651123,50.4034233093],"type":"Point"}
}