{
  "type": "Feature",
  "properties": {
    "iso:country":"BE",
    "sg:address":"Rue De L'epinette 95",
    "sg:city":"Mouscron (herseaux)",
    "sg:classifiers":[
        {
            "category":"Farming",
            "subcategory":"Farm & Veterinary Services",
            "type":"Manufacturing & Wholesale Goods"
        }
    ],
    "sg:phone":"+32 56 33 19 99",
    "sg:postcode":"7712",
    "sg:province":"Hainaut",
    "sg:tags":[
        "agricultural",
        "contractor"
    ],
    "wof:name":"Deschamps G",
    "wof:placetype":"venue"
},
  "geometry": {"coordinates":[3.2408099174,50.7238502502],"type":"Point"}
}