{
  "type": "Feature",
  "properties": {
    "addr:full":"Brakelsesteenweg 53 Ninove Oost-Vlaanderen 9400",
    "addr:housenumber":"53",
    "addr:postcode":"9400",
    "addr:street":"Brakelsesteenweg",
    "iso:country":"BE",
    "sg:address":"Brakelsesteenweg 53",
    "sg:city":"Ninove",
    "sg:classifiers":[
        {
            "category":"Banks & Credit Unions",
            "subcategory":"Financial Services",
            "type":"Services"
        }
    ],
    "sg:phone":"+32 54 33 17 72",
    "sg:postcode":"9400",
    "sg:province":"Oost-Vlaanderen",
    "sg:tags":[
        "loan",
        "mortgage"
    ],
    "wof:name":"Goessens Kredietgroep Nv",
    "wof:placetype":"venue"
},
  "geometry": {"coordinates":[4.0047898293,50.8361091614],"type":"Point"}
}