{
  "type": "Feature",
  "properties": {
    "addr:full":"Krijgsbaan 118 Wijnegem Antwerpen 2110",
    "addr:housenumber":"118",
    "addr:postcode":"2110",
    "addr:street":"Krijgsbaan",
    "iso:country":"BE",
    "sg:address":"Krijgsbaan 118",
    "sg:city":"Wijnegem",
    "sg:classifiers":[
        {
            "category":"Freight",
            "type":"Transportation"
        }
    ],
    "sg:phone":"+32 3 353 82 62",
    "sg:postcode":"2110",
    "sg:province":"Antwerpen",
    "sg:tags":[
        "-",
        "transport"
    ],
    "wof:name":"Transport Lenaerts Bvba",
    "wof:placetype":"venue"
},
  "geometry": {"coordinates":[4.4958882332,51.2178535461],"type":"Point"}
}