{
  "type": "Feature",
  "properties": {
    "iso:country":"BE",
    "sg:address":"Lange Zoutstraat 50",
    "sg:city":"Aalst",
    "sg:classifiers":[
        {
            "category":"Shopping",
            "subcategory":"Clothing, Apparel, & Fashions",
            "type":"Retail Goods"
        }
    ],
    "sg:phone":"+32 53 70 47 37",
    "sg:postcode":"9300",
    "sg:province":"Oost-Vlaanderen",
    "sg:tags":[
        "underwear",
        "lingerie",
        "-"
    ],
    "wof:name":"Jolie Jacqueline",
    "wof:placetype":"venue"
},
  "geometry": {"coordinates":[4.0398712158,50.9367523193],"type":"Point"}
}