{
  "type": "Feature",
  "properties": {
    "addr:full":"Noordstraat 54bb Maldegem Oost-Vlaanderen 9990",
    "addr:housenumber":"54bb",
    "addr:postcode":"9990",
    "addr:street":"Noordstraat",
    "iso:country":"BE",
    "sg:address":"Noordstraat 54bb",
    "sg:city":"Maldegem",
    "sg:orig_category":"Artsen and specialisten",
    "sg:phone":"+32 50 71 85 66",
    "sg:postcode":"9990",
    "sg:province":"Oost-Vlaanderen",
    "wof:name":"Filip Parmentier",
    "wof:placetype":"venue"
},
  "geometry": {"coordinates":[3.446819067,51.2111968994],"type":"Point"}
}