{
  "type": "Feature",
  "properties": {
    "addr:full":"Weg Naar Opoeteren 75 Opglabbeek Limburg 3660",
    "addr:housenumber":"75",
    "addr:postcode":"3660",
    "addr:street":"Weg Naar Opoeteren",
    "iso:country":"BE",
    "sg:address":"Weg Naar Opoeteren 75",
    "sg:city":"Opglabbeek",
    "sg:orig_category":"Herstellingen and onderhoud van auto's",
    "sg:phone":"+32 89 85 80 78",
    "sg:postcode":"3660",
    "sg:province":"Limburg",
    "wof:name":"Marc Vanbuel",
    "wof:placetype":"venue"
},
  "geometry": {"coordinates":[5.5933551788,51.0473976135],"type":"Point"}
}