{
  "type": "Feature",
  "properties": {
    "addr:full":"Chauss\u00e9e De Binche 145a Mons Hainaut 7000",
    "addr:housenumber":"145a",
    "addr:postcode":"7000",
    "addr:street":"Chausse\u0301E De Binche;Hainaut",
    "iso:country":"BE",
    "sg:address":"Chauss\u00e9e De Binche 145a",
    "sg:city":"Mons",
    "sg:classifiers":[
        {
            "category":"Banks & Credit Unions",
            "subcategory":"Financial Services",
            "type":"Services"
        }
    ],
    "sg:phone":"+32 65 31 82 00",
    "sg:postcode":"7000",
    "sg:province":"Hainaut",
    "sg:tags":[
        "loan",
        "mortgage"
    ],
    "wof:name":"Rizzoassur Sprl",
    "wof:placetype":"venue"
},
  "geometry": {"coordinates":[3.9796259403,50.452167511],"type":"Point"}
}