{
  "type": "Feature",
  "properties": {
    "addr:full":"Rue De Milmort 85 Oupeye (herm\u00e9e) Li\u00e8ge 4680",
    "addr:housenumber":"85",
    "addr:postcode":"4680",
    "addr:street":"Rue De Milmort",
    "iso:country":"BE",
    "sg:address":"Rue De Milmort 85",
    "sg:city":"Oupeye (herm\u00e9e)",
    "sg:classifiers":[
        {
            "category":"Building & Trades",
            "subcategory":"Plumbing",
            "type":"Services"
        }
    ],
    "sg:phone":"+32 4 278 63 59",
    "sg:postcode":"4680",
    "sg:province":"Li\u00e8ge",
    "sg:tags":[
        "repair",
        "mainten",
        "-",
        "central",
        "heating"
    ],
    "wof:name":"Graff J F",
    "wof:placetype":"venue"
},
  "geometry": {"coordinates":[5.6444120407,50.7089729309],"type":"Point"}
}