{
  "type": "Feature",
  "properties": {
    "addr:full":"Rue Du Bouleng 31 Ecaussinnes Hainaut 7190",
    "addr:housenumber":"31",
    "addr:postcode":"7190",
    "addr:street":"Rue Du Bouleng;Hainaut",
    "iso:country":"BE",
    "sg:address":"Rue Du Bouleng 31",
    "sg:city":"Ecaussinnes",
    "sg:classifiers":[
        {
            "category":"Personal",
            "subcategory":"Beauty Salon",
            "type":"Services"
        }
    ],
    "sg:phone":"+32 67 44 33 54",
    "sg:postcode":"7190",
    "sg:province":"Hainaut",
    "sg:tags":[
        "de",
        "coiffure"
    ],
    "wof:name":"Lorenzo Centrella",
    "wof:placetype":"venue"
},
  "geometry": {"coordinates":[4.1856899261,50.5352592468],"type":"Point"}
}