{
  "type": "Feature",
  "properties": {
    "iso:country":"BE",
    "sg:address":"Steenstraat 9",
    "sg:city":"Ieper (elverdinge)",
    "sg:classifiers":[
        {
            "category":"Health Services",
            "subcategory":"Health Practitioner",
            "type":"Services"
        }
    ],
    "sg:phone":"+32 57 36 01 32",
    "sg:postcode":"8906",
    "sg:province":"West-Vlaanderen",
    "sg:tags":[
        "therapist",
        "speech"
    ],
    "wof:name":"Malfait I",
    "wof:placetype":"venue"
},
  "geometry": {"coordinates":[2.8173549175,50.8895263672],"type":"Point"}
}