{
  "type": "Feature",
  "properties": {
    "iso:country":"BE",
    "sg:address":"Rupelstraat 24",
    "sg:city":"Torhout",
    "sg:orig_category":"Woningbouw",
    "sg:phone":"+32 50 21 57 81",
    "sg:postcode":"8820",
    "sg:province":"West-Vlaanderen",
    "wof:name":"Geert Verhoegstraete",
    "wof:placetype":"venue"
},
  "geometry": {"coordinates":[3.1125969887,51.0662879944],"type":"Point"}
}