{
  "type": "Feature",
  "properties": {
    "addr:full":"Rue Auguste Van Zande 19-23 Bruxelles Bruxelles-Capitale 1080",
    "addr:housenumber":"19-23",
    "addr:postcode":"1080",
    "addr:street":"Rue Auguste Van Zande",
    "iso:country":"BE",
    "sg:address":"Rue Auguste Van Zande 19-23",
    "sg:city":"Bruxelles",
    "sg:classifiers":[
        {
            "category":"Government",
            "subcategory":"Post Office",
            "type":"Public Place"
        }
    ],
    "sg:phone":"+32 2 465 32 45",
    "sg:postcode":"1080",
    "sg:province":"Bruxelles-Capitale",
    "sg:tags":[
        "lettering"
    ],
    "wof:name":"Publi-wash S.p.r.l.",
    "wof:placetype":"venue"
},
  "geometry": {"coordinates":[4.3061728477,50.8612213135],"type":"Point"}
}