{
  "type": "Feature",
  "properties": {
    "addr:full":"Heidestatiestraat 44 Kalmthout Antwerpen 2920",
    "addr:housenumber":"44",
    "addr:postcode":"2920",
    "addr:street":"Heidestatiestraat",
    "iso:country":"BE",
    "sg:address":"Heidestatiestraat 44",
    "sg:city":"Kalmthout",
    "sg:orig_category":"Fleurop Interflora. Fleurs and plantes",
    "sg:phone":"+32 3 666 35 60",
    "sg:postcode":"2920",
    "sg:province":"Antwerpen",
    "wof:name":"Bloemen Verlinden-gadisseur",
    "wof:placetype":"venue"
},
  "geometry": {"coordinates":[4.462471962,51.3651847839],"type":"Point"}
}