{
  "type": "Feature",
  "properties": {
    "addr:full":"Rue D'andrimont 172 Dison Li\u00e8ge 4821",
    "addr:housenumber":"172",
    "addr:postcode":"4821",
    "addr:street":"Rue D'Andrimont",
    "iso:country":"BE",
    "sg:address":"Rue D'andrimont 172",
    "sg:city":"Dison",
    "sg:orig_category":"Plomberie, chauffage and installations sanitaires",
    "sg:phone":"+32 87 33 87 67",
    "sg:postcode":"4821",
    "sg:province":"Li\u00e8ge",
    "wof:name":"Rene Magnery",
    "wof:placetype":"venue"
},
  "geometry": {"coordinates":[5.8629498482,50.6088027954],"type":"Point"}
}