{
  "type": "Feature",
  "properties": {
    "iso:country":"BE",
    "sg:address":"Lauwsestraat 28",
    "sg:city":"Kortrijk",
    "sg:orig_category":"Boucheries",
    "sg:phone":"+32 56 41 51 88",
    "sg:postcode":"8511",
    "sg:province":"West-Vlaanderen",
    "wof:name":"Jan Dobbels",
    "wof:placetype":"venue"
},
  "geometry": {"coordinates":[3.2285130024,50.7788925171],"type":"Point"}
}