{
  "type": "Feature",
  "properties": {
    "addr:full":"Krommedijk 57 Knokke-heist West-Vlaanderen 8301",
    "addr:housenumber":"57",
    "addr:postcode":"8301",
    "addr:street":"Krommedijk",
    "iso:country":"BE",
    "sg:address":"Krommedijk 57",
    "sg:city":"Knokke-heist",
    "sg:orig_category":"Industri\u00eble wasserijen and droogkuis",
    "sg:phone":"+32 50 51 68 96",
    "sg:postcode":"8301",
    "sg:province":"West-Vlaanderen",
    "wof:name":"Strijk - Service",
    "wof:placetype":"venue"
},
  "geometry": {"coordinates":[3.2561399937,51.3372688293],"type":"Point"}
}