{
  "type": "Feature",
  "properties": {
    "addr:full":"Egemstraat 126 Erpe-mere (ottergem) Oost-Vlaanderen 9420",
    "addr:housenumber":"126",
    "addr:postcode":"9420",
    "addr:street":"Egemstraat",
    "iso:country":"BE",
    "sg:address":"Egemstraat 126",
    "sg:city":"Erpe-mere (ottergem)",
    "sg:classifiers":[
        {
            "category":"Autos & Motor Vehicles",
            "subcategory":"Automobile Sales",
            "type":"Retail Goods"
        }
    ],
    "sg:phone":"+32 53 62 35 57",
    "sg:postcode":"9420",
    "sg:province":"Oost-Vlaanderen",
    "sg:tags":[
        "car",
        "used",
        "-"
    ],
    "wof:name":"Verhoeven Autohandel Bvba",
    "wof:placetype":"venue"
},
  "geometry": {"coordinates":[3.9376549721,50.928817749],"type":"Point"}
}