{
  "type": "Feature",
  "properties": {
    "iso:country":"BE",
    "sg:address":"Essenhoutstraat 7-9",
    "sg:city":"Kapellen",
    "sg:classifiers":[
        {
            "category":"Bars & Pubs",
            "type":"Food & Drink"
        }
    ],
    "sg:phone":"+32 3 664 27 55",
    "sg:postcode":"2950",
    "sg:province":"Antwerpen",
    "wof:name":"Accordeon",
    "wof:placetype":"venue"
},
  "geometry": {"coordinates":[4.4279279709,51.3139762878],"type":"Point"}
}