{
  "type": "Feature",
  "properties": {
    "addr:full":"Massemsesteenweg 21 Wetteren Oost-Vlaanderen 9230",
    "addr:housenumber":"21",
    "addr:postcode":"9230",
    "addr:street":"Massemsesteenweg",
    "iso:country":"BE",
    "sg:address":"Massemsesteenweg 21",
    "sg:city":"Wetteren",
    "sg:classifiers":[
        {
            "category":"Food & Beverages",
            "subcategory":"Specialty",
            "type":"Retail Goods"
        }
    ],
    "sg:phone":"+32 9 366 04 00",
    "sg:postcode":"9230",
    "sg:province":"Oost-Vlaanderen",
    "sg:tags":[
        "health",
        "dietary",
        "-",
        "biological"
    ],
    "wof:name":"De Blauwe Regen",
    "wof:placetype":"venue"
},
  "geometry": {"coordinates":[3.8804860115,50.997253418],"type":"Point"}
}