{
  "type": "Feature",
  "properties": {
    "addr:full":"Rue Antoine De Berghes 55 Verviers Li\u00e8ge 4801",
    "addr:housenumber":"55",
    "addr:postcode":"4801",
    "addr:street":"Rue Antoine De Berghes",
    "iso:country":"BE",
    "sg:address":"Rue Antoine De Berghes 55",
    "sg:city":"Verviers",
    "sg:orig_category":"Gespecialiseerde residenti\u00eble bouw Woningbouw",
    "sg:phone":"+32 87 33 98 87",
    "sg:postcode":"4801",
    "sg:province":"Li\u00e8ge",
    "wof:name":"Jean Marquet",
    "wof:placetype":"venue"
},
  "geometry": {"coordinates":[5.8930549622,50.5922393799],"type":"Point"}
}