{
  "type": "Feature",
  "properties": {
    "addr:full":"Rue Sur Meuse 2 Huy Li\u00e8ge 4500",
    "addr:housenumber":"2",
    "addr:postcode":"4500",
    "addr:street":"Rue Sur Meuse",
    "iso:country":"BE",
    "sg:address":"Rue Sur Meuse 2",
    "sg:city":"Huy",
    "sg:classifiers":[
        {
            "category":"Retail",
            "subcategory":"Storage",
            "type":"Services"
        }
    ],
    "sg:phone":"+32 85 23 42 89",
    "sg:postcode":"4500",
    "sg:province":"Li\u00e8ge",
    "sg:tags":[
        "display",
        "cabinet"
    ],
    "wof:name":"Septennales Huy Asbl",
    "wof:placetype":"venue"
},
  "geometry": {"coordinates":[5.235599041,50.5220985413],"type":"Point"}
}