{
  "type": "Feature",
  "properties": {
    "addr:full":"Groot-gelmenlaan 91 Groot-gelmen Limburg 3800",
    "addr:housenumber":"91",
    "addr:postcode":"3800",
    "addr:street":"Groot-Gelmenlaan",
    "iso:country":"BE",
    "sg:address":"Groot-gelmenlaan 91",
    "sg:city":"Groot-gelmen",
    "sg:classifiers":[
        {
            "category":"Shopping",
            "subcategory":"Gifts & Souvenirs",
            "type":"Retail Goods"
        }
    ],
    "sg:phone":"+32 11 48 59 57",
    "sg:postcode":"3800",
    "sg:province":"Limburg",
    "sg:tags":[
        "product",
        "miscellaneous"
    ],
    "wof:name":"Lowette Jean-marie Nv",
    "wof:placetype":"venue"
},
  "geometry": {"coordinates":[5.2591409683,50.7806777954],"type":"Point"}
}