{
  "type": "Feature",
  "properties": {
    "addr:full":"Kloosterstraat 13 Knesselare Oost-Vlaanderen 9910",
    "addr:housenumber":"13",
    "addr:postcode":"9910",
    "addr:street":"Kloosterstraat;Oost-Vlaanderen",
    "iso:country":"BE",
    "sg:address":"Kloosterstraat 13",
    "sg:city":"Knesselare",
    "sg:classifiers":[
        {
            "category":"Food & Beverages",
            "subcategory":"Specialty",
            "type":"Retail Goods"
        }
    ],
    "sg:phone":"+32 9 374 54 99",
    "sg:postcode":"9910",
    "sg:province":"Oost-Vlaanderen",
    "sg:tags":[
        "health",
        "dietary",
        "-",
        "biological"
    ],
    "wof:name":"Heidebloem",
    "wof:placetype":"venue"
},
  "geometry": {"coordinates":[3.4112679958,51.1400222778],"type":"Point"}
}