{
  "type": "Feature",
  "properties": {
    "addr:full":"Chauss\u00c9e De Lodelinsart 64 Charleroi Hainaut 6060",
    "addr:housenumber":"64",
    "addr:postcode":"6060",
    "addr:street":"Chausse\u0301E De Lodelinsart;Hainaut",
    "iso:country":"BE",
    "sg:address":"Chauss\u00c9e De Lodelinsart 64",
    "sg:city":"Charleroi",
    "sg:orig_category":"Diverse organisaties and verenigingen",
    "sg:phone":"+32 71 86 39 50",
    "sg:postcode":"6060",
    "sg:province":"Hainaut",
    "wof:name":"C.a.i.j.",
    "wof:placetype":"venue"
},
  "geometry": {"coordinates":[4.4498310089,50.4204826355],"type":"Point"}
}