{
  "type": "Feature",
  "properties": {
    "addr:full":"Bergbeemdenstraat 18 Houthalen-helchteren (houthalen) Limburg 3530",
    "addr:housenumber":"18",
    "addr:postcode":"3530",
    "addr:street":"Bergbeemdenstraat",
    "iso:country":"BE",
    "sg:address":"Bergbeemdenstraat 18",
    "sg:city":"Houthalen-helchteren (houthalen)",
    "sg:classifiers":[
        {
            "category":"Communications",
            "subcategory":"Television Station",
            "type":"Services"
        }
    ],
    "sg:phone":"+32 11 52 46 74",
    "sg:postcode":"3530",
    "sg:province":"Limburg",
    "sg:tags":[
        "report",
        "video"
    ],
    "wof:name":"Alfa-video-produkties Poel",
    "wof:placetype":"venue"
},
  "geometry": {"coordinates":[5.3654122353,51.0365562439],"type":"Point"}
}