{
  "type": "Feature",
  "properties": {
    "addr:full":"Oosterzelesteenweg 29 Wetteren Oost-Vlaanderen 9230",
    "addr:housenumber":"29",
    "addr:postcode":"9230",
    "addr:street":"Oosterzelesteenweg",
    "iso:country":"BE",
    "sg:address":"Oosterzelesteenweg 29",
    "sg:city":"Wetteren",
    "sg:classifiers":[
        {
            "category":"Personal",
            "subcategory":"Nail Salon",
            "type":"Services"
        }
    ],
    "sg:phone":"+32 9 366 12 86",
    "sg:postcode":"9230",
    "sg:province":"Oost-Vlaanderen",
    "sg:tags":[
        "pedicure"
    ],
    "wof:name":"Podos",
    "wof:placetype":"venue"
},
  "geometry": {"coordinates":[3.842361927,50.9785118103],"type":"Point"}
}