{
  "type": "Feature",
  "properties": {
    "addr:full":"Avenue Des Alouettes 14 Jemeppe-sur-sambre Namur 5190",
    "addr:housenumber":"14",
    "addr:postcode":"5190",
    "addr:street":"Avenue Des Alouettes",
    "iso:country":"BE",
    "sg:address":"Avenue Des Alouettes 14",
    "sg:city":"Jemeppe-sur-sambre",
    "sg:orig_category":"Epiceries",
    "sg:phone":"+32 71 78 70 48",
    "sg:postcode":"5190",
    "sg:province":"Namur",
    "wof:name":"Alouettes Services",
    "wof:placetype":"venue"
},
  "geometry": {"coordinates":[4.6501560211,50.4509735107],"type":"Point"}
}