{
  "type": "Feature",
  "properties": {
    "addr:full":"Briekhoekstraat 5 Moorslede West-Vlaanderen 8890",
    "addr:housenumber":"5",
    "addr:postcode":"8890",
    "addr:street":"Briekhoekstraat",
    "iso:country":"BE",
    "sg:address":"Briekhoekstraat 5",
    "sg:city":"Moorslede",
    "sg:classifiers":[
        {
            "category":"Professional",
            "type":"Services"
        }
    ],
    "sg:phone":"+32 51 78 82 82",
    "sg:postcode":"8890",
    "sg:province":"West-Vlaanderen",
    "sg:tags":[
        "transport"
    ],
    "wof:name":"Geldhof B.v.b.a.",
    "wof:placetype":"venue"
},
  "geometry": {"coordinates":[3.082365036,50.8874893188],"type":"Point"}
}