{
  "type": "Feature",
  "properties": {
    "addr:full":"Chauss\u00e9e De Namur 29 Hamois (natoye) Namur 5360",
    "addr:housenumber":"29",
    "addr:postcode":"5360",
    "addr:street":"Chausse\u0301E De Namur",
    "iso:country":"BE",
    "sg:address":"Chauss\u00e9e De Namur 29",
    "sg:city":"Hamois (natoye)",
    "sg:classifiers":[
        {
            "category":"Home & Garden",
            "subcategory":"Garden Supply",
            "type":"Retail Goods"
        }
    ],
    "sg:phone":"+32 83 21 23 88",
    "sg:postcode":"5360",
    "sg:province":"Namur",
    "sg:tags":[
        "lawn",
        "mower"
    ],
    "wof:name":"Martin P",
    "wof:placetype":"venue"
},
  "geometry": {"coordinates":[5.0677452087,50.3378562927],"type":"Point"}
}