{
  "type": "Feature",
  "properties": {
    "addr:full":"Boeregemstraat 34 Zingem Oost-Vlaanderen 9750",
    "addr:housenumber":"34",
    "addr:postcode":"9750",
    "addr:street":"Boeregemstraat",
    "iso:country":"BE",
    "sg:address":"Boeregemstraat 34",
    "sg:city":"Zingem",
    "sg:orig_category":"Drukkerijen and copyshops",
    "sg:phone":"+32 9 384 31 59",
    "sg:postcode":"9750",
    "sg:province":"Oost-Vlaanderen",
    "wof:name":"Abel Van Wassenhove",
    "wof:placetype":"venue"
},
  "geometry": {"coordinates":[3.6519870758,50.9060554504],"type":"Point"}
}