{
  "type": "Feature",
  "properties": {
    "addr:full":"Boulevard J.bertrand 35 Charleroi (grand) Hainaut 6000",
    "addr:housenumber":"35",
    "addr:postcode":"6000",
    "addr:street":"Boulevard J.Bertrand",
    "iso:country":"BE",
    "sg:address":"Boulevard J.bertrand 35",
    "sg:city":"Charleroi (grand)",
    "sg:classifiers":[
        {
            "category":"Restaurant",
            "type":"Food & Drink"
        }
    ],
    "sg:phone":"+32 71 31 76 43",
    "sg:postcode":"6000",
    "sg:province":"Hainaut",
    "wof:name":"El Greco",
    "wof:placetype":"venue"
},
  "geometry": {"coordinates":[4.4436221123,50.4139556885],"type":"Point"}
}