{
  "type": "Feature",
  "properties": {
    "addr:full":"Vorstermanstraat 4 Antwerpen Antwerpen 2000",
    "addr:housenumber":"4",
    "addr:postcode":"2000",
    "addr:street":"Vorstermanstraat",
    "iso:country":"BE",
    "sg:address":"Vorstermanstraat 4",
    "sg:city":"Antwerpen",
    "sg:classifiers":[
        {
            "category":"Wholesale",
            "subcategory":"Fruits & Vegetables",
            "type":"Manufacturing & Wholesale Goods"
        }
    ],
    "sg:phone":"+32 3 216 96 00",
    "sg:postcode":"2000",
    "sg:province":"Antwerpen",
    "sg:tags":[
        "whol",
        "-"
    ],
    "wof:name":"Angroha Bvba",
    "wof:placetype":"venue"
},
  "geometry": {"coordinates":[4.392824173,51.2109909058],"type":"Point"}
}