{
  "type": "Feature",
  "properties": {
    "addr:full":"Rietweg 1 Bocholt (kaulille) Limburg 3950",
    "addr:housenumber":"1",
    "addr:postcode":"3950",
    "addr:street":"Rietweg",
    "iso:country":"BE",
    "sg:address":"Rietweg 1",
    "sg:city":"Bocholt (kaulille)",
    "sg:classifiers":[
        {
            "category":"Health Services",
            "subcategory":"Health Practitioner",
            "type":"Services"
        }
    ],
    "sg:phone":"+32 89 48 11 80",
    "sg:postcode":"3950",
    "sg:province":"Limburg",
    "sg:tags":[
        "physiotherapist"
    ],
    "wof:name":"Nelissen Katrien",
    "wof:placetype":"venue"
},
  "geometry": {"coordinates":[5.5281291008,51.1825637817],"type":"Point"}
}