{
  "type": "Feature",
  "properties": {
    "addr:full":"Rue D'ellignies 2 Beloeil Hainaut 7972",
    "addr:housenumber":"2",
    "addr:postcode":"7972",
    "addr:street":"Rue D'Ellignies",
    "iso:country":"BE",
    "sg:address":"Rue D'ellignies 2",
    "sg:city":"Beloeil",
    "sg:orig_category":"V\u00e9t\u00e9rinaires",
    "sg:phone":"+32 69 68 94 22",
    "sg:postcode":"7972",
    "sg:province":"Hainaut",
    "wof:name":"Michel Van De Velde",
    "wof:placetype":"venue"
},
  "geometry": {"coordinates":[3.6726679802,50.5625801086],"type":"Point"}
}