{
  "type": "Feature",
  "properties": {
    "iso:country":"BE",
    "sg:address":"Vosveld 8a",
    "sg:city":"Wijnegem",
    "sg:classifiers":[
        {
            "category":"Professional",
            "subcategory":"Testing Lab",
            "type":"Services"
        }
    ],
    "sg:phone":"+32 3 328 05 40",
    "sg:postcode":"2110",
    "sg:province":"Antwerpen",
    "sg:tags":[
        "laboratory",
        "-"
    ],
    "wof:name":"Comexal Nv",
    "wof:placetype":"venue"
},
  "geometry": {"coordinates":[4.4961481094,51.2335166931],"type":"Point"}
}