{
  "type": "Feature",
  "properties": {
    "iso:country":"BE",
    "sg:address":"Avenue Prince Baudouin 20",
    "sg:city":"Verviers (heusy)",
    "sg:classifiers":[
        {
            "category":"Health Services",
            "subcategory":"Health Practitioner",
            "type":"Services"
        }
    ],
    "sg:phone":"+32 87 22 73 67",
    "sg:postcode":"4802",
    "sg:province":"Li\u00e8ge",
    "sg:tags":[
        "physiotherapist"
    ],
    "wof:name":"Zintzen P",
    "wof:placetype":"venue"
},
  "geometry": {"coordinates":[5.8649501801,50.5702133179],"type":"Point"}
}