{
  "type": "Feature",
  "properties": {
    "addr:full":"Rue De Gembloux 187 Namur (saint-servais) Namur 5002",
    "addr:housenumber":"187",
    "addr:postcode":"5002",
    "addr:street":"Rue De Gembloux",
    "iso:country":"BE",
    "sg:address":"Rue De Gembloux 187",
    "sg:city":"Namur (saint-servais)",
    "sg:classifiers":[
        {
            "category":"Bars & Pubs",
            "type":"Food & Drink"
        }
    ],
    "sg:phone":"+32 81 73 79 06",
    "sg:postcode":"5002",
    "sg:province":"Namur",
    "wof:name":"Kop (le)",
    "wof:placetype":"venue"
},
  "geometry": {"coordinates":[4.8462319374,50.4782791138],"type":"Point"}
}