{
  "type": "Feature",
  "properties": {
    "iso:country":"BE",
    "sg:address":"Nieuwburgstraat 57",
    "sg:city":"Assenede",
    "sg:orig_category":"Woningbouw",
    "sg:phone":"+32 9 344 89 02",
    "sg:postcode":"9960",
    "sg:province":"Oost-Vlaanderen",
    "wof:name":"Houtmeyers G.",
    "wof:placetype":"venue"
},
  "geometry": {"coordinates":[3.7290000916,51.2021255493],"type":"Point"}
}