{
  "type": "Feature",
  "properties": {
    "addr:full":"Rue Catherine 12 Naast Hainaut 7062",
    "addr:housenumber":"12",
    "addr:postcode":"7062",
    "addr:street":"Rue Catherine",
    "iso:country":"BE",
    "sg:address":"Rue Catherine 12",
    "sg:city":"Naast",
    "sg:classifiers":[
        {
            "category":"Manufacturing",
            "subcategory":"Wood Products",
            "type":"Manufacturing & Wholesale Goods"
        }
    ],
    "sg:phone":"+32 67 33 00 38",
    "sg:postcode":"7062",
    "sg:province":"Hainaut",
    "sg:tags":[
        "structure"
    ],
    "wof:name":"Colson S.a.",
    "wof:placetype":"venue"
},
  "geometry": {"coordinates":[4.0996851921,50.5541000366],"type":"Point"}
}