{
  "type": "Feature",
  "properties": {
    "addr:full":"Rue De Maissin Paliseul Luxembourg 6850",
    "addr:postcode":"6850",
    "addr:street":"Rue De Maissin",
    "iso:country":"BE",
    "sg:address":"Rue De Maissin",
    "sg:city":"Paliseul",
    "sg:orig_category":"Autombile concessionaires",
    "sg:phone":"+32 61 53 36 40",
    "sg:postcode":"6850",
    "sg:province":"Luxembourg",
    "wof:name":"Bodson",
    "wof:placetype":"venue"
},
  "geometry": {"coordinates":[5.1412348747,49.9083404541],"type":"Point"}
}