{
  "type": "Feature",
  "properties": {
    "addr:full":"Waaslandlaan 6 Lokeren Oost-Vlaanderen 9160",
    "addr:housenumber":"6",
    "addr:postcode":"9160",
    "addr:street":"Waaslandlaan",
    "iso:country":"BE",
    "sg:address":"Waaslandlaan 6",
    "sg:city":"Lokeren",
    "sg:orig_category":"Non-Classified Establishments",
    "sg:phone":"+32 9 348 57 42",
    "sg:postcode":"9160",
    "sg:province":"Oost-Vlaanderen",
    "wof:name":"Van Acker H Bvba",
    "wof:placetype":"venue"
},
  "geometry": {"coordinates":[4.0105438232,51.120513916],"type":"Point"}
}