{
  "type": "Feature",
  "properties": {
    "addr:full":"Karlapperstraat 1 Lokeren Oost-Vlaanderen 9160",
    "addr:housenumber":"1",
    "addr:postcode":"9160",
    "addr:street":"Karlapperstraat",
    "iso:country":"BE",
    "sg:address":"Karlapperstraat 1",
    "sg:city":"Lokeren",
    "sg:orig_category":"Boekhouders",
    "sg:phone":"+32 9 348 70 66",
    "sg:postcode":"9160",
    "sg:province":"Oost-Vlaanderen",
    "wof:name":"Antoon Drossens",
    "wof:placetype":"venue"
},
  "geometry": {"coordinates":[3.9732239246,51.1001968384],"type":"Point"}
}