{
  "type": "Feature",
  "properties": {
    "iso:country":"BE",
    "sg:address":"Rue De La Station 60",
    "sg:city":"Charleroi (ransart)",
    "sg:classifiers":[
        {
            "category":"Shopping",
            "subcategory":"Books",
            "type":"Retail Goods"
        }
    ],
    "sg:phone":"+32 71 35 33 93",
    "sg:postcode":"6043",
    "sg:province":"Hainaut",
    "sg:tags":[
        "bookseller"
    ],
    "wof:name":"Au Gai Savoir",
    "wof:placetype":"venue"
},
  "geometry": {"coordinates":[4.4859671593,50.4564666748],"type":"Point"}
}