{
  "type": "Feature",
  "properties": {
    "iso:country":"BE",
    "sg:address":"Maria-hendrikastraat 13",
    "sg:city":"Elsene/ixelles",
    "sg:orig_category":"Diverse grafische activiteiten",
    "sg:phone":"+32 2 649 05 02",
    "sg:postcode":"1050",
    "sg:province":"Bruxelles-Capitale",
    "wof:name":"Bureau Sign\u00c9 Lazer",
    "wof:placetype":"venue"
},
  "geometry": {"coordinates":[4.37433815,50.831035614],"type":"Point"}
}