{
  "type": "Feature",
  "properties": {
    "addr:full":"Vliergaarde 5 Sint-agatha-berchem/berchem-sainte-agathe Bruxelles-Capitale 1082",
    "addr:housenumber":"5",
    "addr:postcode":"1082",
    "addr:street":"Vliergaarde",
    "iso:country":"BE",
    "sg:address":"Vliergaarde 5",
    "sg:city":"Sint-agatha-berchem/berchem-sainte-agathe",
    "sg:orig_category":"Loodgieterij, verwarming and sanitaire installaties",
    "sg:phone":"+32 2 465 47 01",
    "sg:postcode":"1082",
    "sg:province":"Bruxelles-Capitale",
    "wof:name":"Robert Moens",
    "wof:placetype":"venue"
},
  "geometry": {"coordinates":[4.2819800377,50.860080719],"type":"Point"}
}