{
  "type": "Feature",
  "properties": {
    "addr:full":"Rue Des Dames 79 Frameries Hainaut 7080",
    "addr:housenumber":"79",
    "addr:postcode":"7080",
    "addr:street":"Rue Des Dames",
    "iso:country":"BE",
    "sg:address":"Rue Des Dames 79",
    "sg:city":"Frameries",
    "sg:classifiers":[
        {
            "category":"Arena",
            "subcategory":"Sports Club",
            "type":"Entertainment"
        }
    ],
    "sg:phone":"+32 65 67 77 15",
    "sg:postcode":"7080",
    "sg:province":"Hainaut",
    "wof:name":"Club Tennis La Vol\u00e9e Asbl",
    "wof:placetype":"venue"
},
  "geometry": {"coordinates":[3.8919439316,50.4133987427],"type":"Point"}
}