{
  "type": "Feature",
  "properties": {
    "addr:full":"Koningin Astridlaan 12 Leuven Vlaams-Brabant 3000",
    "addr:housenumber":"12",
    "addr:postcode":"3000",
    "addr:street":"Koningin Astridlaan",
    "iso:country":"BE",
    "sg:address":"Koningin Astridlaan 12",
    "sg:city":"Leuven",
    "sg:orig_category":"Beheer onroerend goed Immobili\u00ebnkantoren Verzekeringsmakelaars and experts",
    "sg:phone":"+32 16 22 81 18",
    "sg:postcode":"3000",
    "sg:province":"Vlaams-Brabant",
    "wof:name":"Jos\u00c9 Ruelens En Zoon",
    "wof:placetype":"venue"
},
  "geometry": {"coordinates":[4.7036700249,50.8793869019],"type":"Point"}
}