{
  "type": "Feature",
  "properties": {
    "addr:full":"Dautenstraat 42 Diepenbeek Limburg 3590",
    "addr:housenumber":"42",
    "addr:postcode":"3590",
    "addr:street":"Dautenstraat",
    "iso:country":"BE",
    "sg:address":"Dautenstraat 42",
    "sg:city":"Diepenbeek",
    "sg:orig_category":"M\u00e9decins and sp\u00e9cialistes",
    "sg:phone":"+32 11 32 43 82",
    "sg:postcode":"3590",
    "sg:province":"Limburg",
    "wof:name":"Willem Dieben",
    "wof:placetype":"venue"
},
  "geometry": {"coordinates":[5.4291620255,50.922542572],"type":"Point"}
}