{
  "type": "Feature",
  "properties": {
    "iso:country":"BE",
    "sg:address":"Boulevard Joseph Tirou 130",
    "sg:city":"Charleroi",
    "sg:classifiers":[
        {
            "category":"Education",
            "subcategory":"University",
            "type":"Public Place"
        }
    ],
    "sg:phone":"+32 71 20 71 50",
    "sg:postcode":"6000",
    "sg:province":"Hainaut",
    "sg:tags":[
        "higher"
    ],
    "wof:name":"Facult\u00e9s Universitaires Notre Dame De La Paix",
    "wof:placetype":"venue"
},
  "geometry": {"coordinates":[4.4463720322,50.4059371948],"type":"Point"}
}