{
  "type": "Feature",
  "properties": {
    "addr:full":"Sperlekestraat 20 Kortrijk West-Vlaanderen 8510",
    "addr:housenumber":"20",
    "addr:postcode":"8510",
    "addr:street":"Sperlekestraat",
    "iso:country":"BE",
    "sg:address":"Sperlekestraat 20",
    "sg:city":"Kortrijk",
    "sg:orig_category":"Hout and afgeleiden Gh IJzerwaren, bouw- and verfmaterialen",
    "sg:phone":"+32 56 22 59 92",
    "sg:postcode":"8510",
    "sg:province":"West-Vlaanderen",
    "wof:name":"Westhout",
    "wof:placetype":"venue"
},
  "geometry": {"coordinates":[3.2478039265,50.8015823364],"type":"Point"}
}