{
  "type": "Feature",
  "properties": {
    "iso:country":"BE",
    "sg:address":"Rue De Namur 15",
    "sg:city":"Wavre",
    "sg:orig_category":"Meubles D\u00e9taillants, Am\u00e9nagement de B\u00e2timents et de Cuisines",
    "sg:phone":"+32 10 24 32 10",
    "sg:postcode":"1300",
    "sg:province":"Brabant Wallon",
    "wof:name":"D. & M. Habitat",
    "wof:placetype":"venue"
},
  "geometry": {"coordinates":[4.6113181114,50.7128562927],"type":"Point"}
}