{
  "type": "Feature",
  "properties": {
    "iso:country":"BE",
    "sg:address":"Huidevettersstraat 67",
    "sg:city":"Houthalen-helchteren",
    "sg:orig_category":"Agences d'exp\u00e9dition",
    "sg:phone":"+32 11 60 54 49",
    "sg:postcode":"3530",
    "sg:province":"Limburg",
    "wof:name":"Eximag Intenational",
    "wof:placetype":"venue"
},
  "geometry": {"coordinates":[5.3929958344,51.0264816284],"type":"Point"}
}