{
  "type": "Feature",
  "properties": {
    "addr:full":"Van Rijswijcklaan 166a Antwerpen Antwerpen 2020",
    "addr:housenumber":"166a",
    "addr:postcode":"2020",
    "addr:street":"Van Rijswijcklaan",
    "iso:country":"BE",
    "sg:address":"Van Rijswijcklaan 166a",
    "sg:city":"Antwerpen",
    "sg:orig_category":"Agences d'exp\u00e9dition",
    "sg:phone":"+32 3 257 34 00",
    "sg:postcode":"2020",
    "sg:province":"Antwerpen",
    "wof:name":"Caspian Belga Construct",
    "wof:placetype":"venue"
},
  "geometry": {"coordinates":[4.3974981308,51.1911354065],"type":"Point"}
}