{
  "type": "Feature",
  "properties": {
    "addr:full":"Rue Des D\u00c9port\u00c9s 62 Arlon Luxembourg 6700",
    "addr:housenumber":"62",
    "addr:postcode":"6700",
    "addr:street":"Rue Des De\u0301Porte\u0301S",
    "iso:country":"BE",
    "sg:address":"Rue Des D\u00c9port\u00c9s 62",
    "sg:city":"Arlon",
    "sg:orig_category":"Brood, gebak and snoepgoed",
    "sg:phone":"+32 63 22 76 68",
    "sg:postcode":"6700",
    "sg:province":"Luxembourg",
    "wof:name":"Alain Clausse",
    "wof:placetype":"venue"
},
  "geometry": {"coordinates":[5.8208508492,49.6791954041],"type":"Point"}
}