{
  "type": "Feature",
  "properties": {
    "addr:full":"August Van Doorslaerlaan 23 Meise Vlaams-Brabant 1860",
    "addr:housenumber":"23",
    "addr:postcode":"1860",
    "addr:street":"August Van Doorslaerlaan",
    "iso:country":"BE",
    "sg:address":"August Van Doorslaerlaan 23",
    "sg:city":"Meise",
    "sg:orig_category":"Stations-service and carburants. V\u00e9hicules automobiles. Entretien and r\u00e9parations de voitures",
    "sg:phone":"+32 2 269 49 48",
    "sg:postcode":"1860",
    "sg:province":"Vlaams-Brabant",
    "wof:name":"Garage Decoster",
    "wof:placetype":"venue"
},
  "geometry": {"coordinates":[4.3257188797,50.9337501526],"type":"Point"}
}