{
  "type": "Feature",
  "properties": {
    "addr:full":"Reebergenlaan 4 Zandhoven Antwerpen 2242",
    "addr:housenumber":"4",
    "addr:postcode":"2242",
    "addr:street":"Reebergenlaan",
    "iso:country":"BE",
    "sg:address":"Reebergenlaan 4",
    "sg:city":"Zandhoven",
    "sg:orig_category":"Enseignement secondaire g\u00e9n\u00e9ral. Enseignement maternel and primaire",
    "sg:phone":"+32 3 484 36 00",
    "sg:postcode":"2242",
    "sg:province":"Antwerpen",
    "wof:name":"Bubao",
    "wof:placetype":"venue"
},
  "geometry": {"coordinates":[4.6916399002,51.2169342041],"type":"Point"}
}