{
  "type": "Feature",
  "properties": {
    "iso:country":"BE",
    "sg:address":"Place De La Victoire 10",
    "sg:city":"Braine-le-comte",
    "sg:classifiers":[
        {
            "category":"Real Estate",
            "subcategory":"Architect",
            "type":"Services"
        }
    ],
    "sg:phone":"+32 67 55 39 28",
    "sg:postcode":"7090",
    "sg:province":"Hainaut",
    "wof:name":"Eeckhoudt J-l",
    "wof:placetype":"venue"
},
  "geometry": {"coordinates":[4.1338682175,50.6055335999],"type":"Point"}
}