{
  "type": "Feature",
  "properties": {
    "addr:full":"Avenue Du Beau S\u00c9jour 38 Braine-le-chateau Brabant Wallon 1440",
    "addr:housenumber":"38",
    "addr:postcode":"1440",
    "addr:street":"Avenue Du Beau Se\u0301Jour;Brabant Wallon",
    "iso:country":"BE",
    "sg:address":"Avenue Du Beau S\u00c9jour 38",
    "sg:city":"Braine-le-chateau",
    "sg:orig_category":"Sportterreinen and installaties behalve sportcentra",
    "sg:phone":"+32 2 366 94 23",
    "sg:postcode":"1440",
    "sg:province":"Brabant Wallon",
    "wof:name":"Man\u00c8ge La Canardi\u00c8re",
    "wof:placetype":"venue"
},
  "geometry": {"coordinates":[4.2871479988,50.6896934509],"type":"Point"}
}