{
  "type": "Feature",
  "properties": {
    "addr:full":"Gentsesteenweg 121 Harelbeke West-Vlaanderen 8530",
    "addr:housenumber":"121",
    "addr:postcode":"8530",
    "addr:street":"Gentsesteenweg",
    "iso:country":"BE",
    "sg:address":"Gentsesteenweg 121",
    "sg:city":"Harelbeke",
    "sg:orig_category":"Plomberie, chauffage and installations sanitaires. Electrom\u00e9nager, t\u00e9l\u00e9visions and radios Air condit",
    "sg:phone":"+32 56 71 17 11",
    "sg:postcode":"8530",
    "sg:province":"West-Vlaanderen",
    "wof:name":"Vivox",
    "wof:placetype":"venue"
},
  "geometry": {"coordinates":[3.3287680149,50.8656044006],"type":"Point"}
}