{
  "type": "Feature",
  "properties": {
    "addr:full":"Rue Deltour 28 Ans (loncin) Li\u00e8ge 4431",
    "addr:housenumber":"28",
    "addr:postcode":"4431",
    "addr:street":"Rue Deltour",
    "iso:country":"BE",
    "sg:address":"Rue Deltour 28",
    "sg:city":"Ans (loncin)",
    "sg:classifiers":[
        {
            "category":"Health Services",
            "subcategory":"Doctor",
            "type":"Services"
        }
    ],
    "sg:phone":"+32 4 263 69 06",
    "sg:postcode":"4431",
    "sg:province":"Li\u00e8ge",
    "sg:tags":[
        "medicinephysicians",
        "surgeon"
    ],
    "wof:name":"Dengis G",
    "wof:placetype":"venue"
},
  "geometry": {"coordinates":[5.5052361488,50.6629447937],"type":"Point"}
}