{
  "type": "Feature",
  "properties": {
    "addr:full":"Rue De Sommethonne 64a Meix-devant-virton (villers-la-loue) Luxembourg 6769",
    "addr:housenumber":"64a",
    "addr:postcode":"6769",
    "addr:street":"Rue De Sommethonne",
    "iso:country":"BE",
    "sg:address":"Rue De Sommethonne 64a",
    "sg:city":"Meix-devant-virton (villers-la-loue)",
    "sg:classifiers":[
        {
            "category":"Health Services",
            "subcategory":"Doctor",
            "type":"Services"
        }
    ],
    "sg:phone":"+32 63 57 95 77",
    "sg:postcode":"6769",
    "sg:province":"Luxembourg",
    "sg:tags":[
        "medicinephysicians",
        "surgeon"
    ],
    "wof:name":"Marion C",
    "wof:placetype":"venue"
},
  "geometry": {"coordinates":[5.4800958633,49.6040344238],"type":"Point"}
}