{
  "type": "Feature",
  "properties": {
    "addr:full":"Baaigemstraat 69 Gavere Oost-Vlaanderen 9890",
    "addr:housenumber":"69",
    "addr:postcode":"9890",
    "addr:street":"Baaigemstraat",
    "iso:country":"BE",
    "sg:address":"Baaigemstraat 69",
    "sg:city":"Gavere",
    "sg:classifiers":[
        {
            "category":"Building & Trades",
            "subcategory":"Landscaping Services",
            "type":"Services"
        }
    ],
    "sg:phone":"+32 9 384 23 29",
    "sg:postcode":"9890",
    "sg:province":"Oost-Vlaanderen",
    "sg:tags":[
        "gardening",
        "garden",
        "maintenance"
    ],
    "wof:name":"Verlinden Y",
    "wof:placetype":"venue"
},
  "geometry": {"coordinates":[3.6685791016,50.9300765991],"type":"Point"}
}