{
  "type": "Feature",
  "properties": {
    "addr:full":"Ketenstraat 97 Moorslede West-Vlaanderen 8890",
    "addr:housenumber":"97",
    "addr:postcode":"8890",
    "addr:street":"Ketenstraat",
    "iso:country":"BE",
    "sg:address":"Ketenstraat 97",
    "sg:city":"Moorslede",
    "sg:orig_category":"Rev\u00eatements pour sols and murs. Peinture",
    "sg:phone":"+32 56 50 14 16",
    "sg:postcode":"8890",
    "sg:province":"West-Vlaanderen",
    "wof:name":"Marc Schotte",
    "wof:placetype":"venue"
},
  "geometry": {"coordinates":[3.0921730995,50.8475227356],"type":"Point"}
}