{
  "type": "Feature",
  "properties": {
    "iso:country":"BE",
    "sg:address":"Bld De La Sauveni\u00c8re 180",
    "sg:city":"Li\u00c8ge",
    "sg:orig_category":"Pharmaciens",
    "sg:phone":"+32 4 223 30 87",
    "sg:postcode":"4000",
    "sg:province":"Li\u00e8ge",
    "wof:name":"Danse",
    "wof:placetype":"venue"
},
  "geometry": {"coordinates":[5.5683121681,50.6402702332],"type":"Point"}
}