{
  "type": "Feature",
  "properties": {
    "iso:country":"BE",
    "sg:address":"Plaats 2",
    "sg:city":"Kasterlee",
    "sg:classifiers":[
        {
            "category":"Restaurant",
            "type":"Food & Drink"
        }
    ],
    "sg:phone":"+32 14 55 77 86",
    "sg:postcode":"2460",
    "sg:province":"Antwerpen",
    "wof:name":"De Pastorie",
    "wof:placetype":"venue"
},
  "geometry": {"coordinates":[4.9164028168,51.2269935608],"type":"Point"}
}