{
  "type": "Feature",
  "properties": {
    "addr:full":"Langestraat 48 Brugge West-Vlaanderen 8000",
    "addr:housenumber":"48",
    "addr:postcode":"8000",
    "addr:street":"Langestraat",
    "iso:country":"BE",
    "sg:address":"Langestraat 48",
    "sg:city":"Brugge",
    "sg:classifiers":[
        {
            "category":"Manufacturing",
            "subcategory":"Building Materials",
            "type":"Manufacturing & Wholesale Goods"
        }
    ],
    "sg:phone":"+32 50 33 25 22",
    "sg:postcode":"8000",
    "sg:province":"West-Vlaanderen",
    "sg:tags":[
        "wig",
        "hairworks"
    ],
    "wof:name":"Tourlamain F",
    "wof:placetype":"venue"
},
  "geometry": {"coordinates":[3.2339589596,51.2095947266],"type":"Point"}
}