{
  "type": "Feature",
  "properties": {
    "addr:full":"Place Franklin-delano Roosevelt 10 Courcelles Hainaut 6180",
    "addr:housenumber":"10",
    "addr:postcode":"6180",
    "addr:street":"Place Franklin-Delano Roosevelt",
    "iso:country":"BE",
    "sg:address":"Place Franklin-delano Roosevelt 10",
    "sg:city":"Courcelles",
    "sg:classifiers":[
        {
            "category":"Shopping",
            "subcategory":"Jewelry",
            "type":"Retail Goods"
        }
    ],
    "sg:phone":"+32 71 45 22 05",
    "sg:postcode":"6180",
    "sg:province":"Hainaut",
    "sg:tags":[
        "-",
        "imitation"
    ],
    "wof:name":"Vilain J & Loisse S",
    "wof:placetype":"venue"
},
  "geometry": {"coordinates":[4.3743700981,50.4565086365],"type":"Point"}
}