{
  "type": "Feature",
  "properties": {
    "addr:full":"Rue Du Fort 63 Soumagne Li\u00e8ge 4632",
    "addr:housenumber":"63",
    "addr:postcode":"4632",
    "addr:street":"Rue Du Fort",
    "iso:country":"BE",
    "sg:address":"Rue Du Fort 63",
    "sg:city":"Soumagne",
    "sg:orig_category":"HUISBRANDOLIE",
    "sg:phone":"+32 4 377 18 45",
    "sg:postcode":"4632",
    "sg:province":"Li\u00e8ge",
    "wof:name":"Brayeur-geron",
    "wof:placetype":"venue"
},
  "geometry": {"coordinates":[5.7202949524,50.6403579712],"type":"Point"}
}