{
  "type": "Feature",
  "properties": {
    "addr:full":"Rue De La Marli\u00c8re 12 Moeskroen/mouscron Hainaut 7700",
    "addr:housenumber":"12",
    "addr:postcode":"7700",
    "addr:street":"Rue De La Marlie\u0300Re",
    "iso:country":"BE",
    "sg:address":"Rue De La Marli\u00c8re 12",
    "sg:city":"Moeskroen/mouscron",
    "sg:orig_category":"Meubles D\u00e9taillants, Am\u00e9nagement de B\u00e2timents et de Cuisines",
    "sg:phone":"+32 56 34 02 78",
    "sg:postcode":"7700",
    "sg:province":"Hainaut",
    "wof:name":"La Literie",
    "wof:placetype":"venue"
},
  "geometry": {"coordinates":[3.2323200703,50.7400932312],"type":"Point"}
}