{
  "type": "Feature",
  "properties": {
    "iso:country":"BE",
    "sg:address":"Champagne 100",
    "sg:city":"Weismes/waimes",
    "sg:orig_category":"MEUBELONTWERP AND -INSTALLATIE",
    "sg:phone":"+32 80 67 82 51",
    "sg:postcode":"4950",
    "sg:province":"Li\u00e8ge",
    "wof:name":"St\u00c9phane Berthels",
    "wof:placetype":"venue"
},
  "geometry": {"coordinates":[6.1406908035,50.4036178589],"type":"Point"}
}