{
  "type": "Feature",
  "properties": {
    "iso:country":"BE",
    "sg:address":"Rue Fr\u00c9mineur 23",
    "sg:city":"Watermaal-bosvoorde/watermael-boitsfort",
    "sg:orig_category":"Traitements param\u00e9dicaux",
    "sg:phone":"+32 2 673 66 82",
    "sg:postcode":"1170",
    "sg:province":"Bruxelles-Capitale",
    "wof:name":"V. Morel",
    "wof:placetype":"venue"
},
  "geometry": {"coordinates":[4.4051909447,50.8053245544],"type":"Point"}
}