{
  "type": "Feature",
  "properties": {
    "addr:full":"Avenue D'arromanches 16 Waterloo Brabant Wallon 1410",
    "addr:housenumber":"16",
    "addr:postcode":"1410",
    "addr:street":"Avenue D'Arromanches",
    "iso:country":"BE",
    "sg:address":"Avenue D'arromanches 16",
    "sg:city":"Waterloo",
    "sg:classifiers":[
        {
            "category":"Professional",
            "subcategory":"Management & Consulting",
            "type":"Services"
        }
    ],
    "sg:phone":"+32 479 53 98 76",
    "sg:postcode":"1410",
    "sg:province":"Brabant Wallon",
    "sg:tags":[
        "consultant"
    ],
    "wof:name":"E C P I",
    "wof:placetype":"venue"
},
  "geometry": {"coordinates":[4.3685932159,50.7020492554],"type":"Point"}
}