{
  "type": "Feature",
  "properties": {
    "iso:country":"BE",
    "sg:address":"Steenweg Op Merchtem 62",
    "sg:city":"Wolvertem",
    "sg:orig_category":"Entretien and r\u00e9parations de voitures",
    "sg:phone":"+32 2 269 11 99",
    "sg:postcode":"1861",
    "sg:province":"Vlaams-Brabant",
    "wof:name":"Roelants",
    "wof:placetype":"venue"
},
  "geometry": {"coordinates":[4.3001317978,50.9522323608],"type":"Point"}
}