{
  "type": "Feature",
  "properties": {
    "addr:full":"Rue De La Hallette 66 Herstal Li\u00e8ge 4041",
    "addr:housenumber":"66",
    "addr:postcode":"4041",
    "addr:street":"Rue De La Hallette",
    "iso:country":"BE",
    "sg:address":"Rue De La Hallette 66",
    "sg:city":"Herstal",
    "sg:orig_category":"HERSTELLING ELEKTRISCHE HUISHOUDAPPARATEN Huishoudapparaten, televisies and radio's Telecommunicatie",
    "sg:phone":"+32 4 278 52 78",
    "sg:postcode":"4041",
    "sg:province":"Li\u00e8ge",
    "wof:name":"Michel Delrot",
    "wof:placetype":"venue"
},
  "geometry": {"coordinates":[5.587703228,50.687915802],"type":"Point"}
}