{
  "type": "Feature",
  "properties": {
    "addr:full":"Raffisstraat 30 Meeuwen-gruitrode (meeuwen) Limburg 3670",
    "addr:housenumber":"30",
    "addr:postcode":"3670",
    "addr:street":"Raffisstraat",
    "iso:country":"BE",
    "sg:address":"Raffisstraat 30",
    "sg:city":"Meeuwen-gruitrode (meeuwen)",
    "sg:classifiers":[
        {
            "category":"Building & Trades",
            "subcategory":"Electrical",
            "type":"Services"
        }
    ],
    "sg:phone":"+32 11 79 19 43",
    "sg:postcode":"3670",
    "sg:province":"Limburg",
    "sg:tags":[
        "electric",
        "-",
        "housewiring",
        "contractor"
    ],
    "wof:name":"Ewm",
    "wof:placetype":"venue"
},
  "geometry": {"coordinates":[5.490085125,51.0989379883],"type":"Point"}
}