{
  "type": "Feature",
  "properties": {
    "addr:full":"Prof. Scharpelaan 111 Begijnendijk Vlaams-Brabant 3130",
    "addr:housenumber":"111",
    "addr:postcode":"3130",
    "addr:street":"Scharpelaan",
    "iso:country":"BE",
    "sg:address":"Prof. Scharpelaan 111",
    "sg:city":"Begijnendijk",
    "sg:orig_category":"Producteurs de l\u00e9gumes",
    "sg:phone":"+32 16 56 03 01",
    "sg:postcode":"3130",
    "sg:province":"Vlaams-Brabant",
    "wof:name":"Marcus Adams",
    "wof:placetype":"venue"
},
  "geometry": {"coordinates":[4.7862548828,50.9936637878],"type":"Point"}
}