{
  "type": "Feature",
  "properties": {
    "addr:full":"Bagattenstraat 143 Gent Oost-Vlaanderen 9000",
    "addr:housenumber":"143",
    "addr:postcode":"9000",
    "addr:street":"Bagattenstraat;Oost-Vlaanderen",
    "iso:country":"BE",
    "sg:address":"Bagattenstraat 143",
    "sg:city":"Gent",
    "sg:classifiers":[
        {
            "category":"Shopping",
            "subcategory":"Optician",
            "type":"Retail Goods"
        }
    ],
    "sg:phone":"+32 9 225 46 63",
    "sg:postcode":"9000",
    "sg:province":"Oost-Vlaanderen",
    "sg:tags":[
        "-"
    ],
    "wof:name":"Jo De Groote",
    "wof:placetype":"venue"
},
  "geometry": {"coordinates":[3.7244091034,51.0475692749],"type":"Point"}
}