{
  "type": "Feature",
  "properties": {
    "addr:full":"Rue Damry 161 Seraing Li\u00e8ge 4100",
    "addr:housenumber":"161",
    "addr:postcode":"4100",
    "addr:street":"Rue Damry",
    "iso:country":"BE",
    "sg:address":"Rue Damry 161",
    "sg:city":"Seraing",
    "sg:orig_category":"Pleisterwerk",
    "sg:phone":"+32 4 336 95 32",
    "sg:postcode":"4100",
    "sg:province":"Li\u00e8ge",
    "wof:name":"J.l.h. Plafonnage",
    "wof:placetype":"venue"
},
  "geometry": {"coordinates":[5.5255098343,50.560798645],"type":"Point"}
}