{
  "type": "Feature",
  "properties": {
    "iso:country":"BE",
    "sg:address":"Duffelsestw 156",
    "sg:city":"Kontich",
    "sg:classifiers":[
        {
            "category":"Manufacturing",
            "subcategory":"Chemicals & Compounds",
            "type":"Manufacturing & Wholesale Goods"
        }
    ],
    "sg:phone":"+32 3 458 44 96",
    "sg:postcode":"2550",
    "sg:province":"Antwerpen",
    "sg:tags":[
        "pharmaceutical",
        "chemistry",
        "-",
        "by-product"
    ],
    "wof:name":"Eco-colors Nv",
    "wof:placetype":"venue"
},
  "geometry": {"coordinates":[4.462515831,51.1231880188],"type":"Point"}
}