{
  "type": "Feature",
  "properties": {
    "iso:country":"BE",
    "sg:address":"Lindemolen 9",
    "sg:city":"Alveringem",
    "sg:classifiers":[
        {
            "category":"Bars & Pubs",
            "type":"Food & Drink"
        }
    ],
    "sg:phone":"+32 58 28 95 11",
    "sg:postcode":"8690",
    "sg:province":"West-Vlaanderen",
    "wof:name":"De Lindemolen",
    "wof:placetype":"venue"
},
  "geometry": {"coordinates":[2.7097420692,51.0047721863],"type":"Point"}
}