{
  "type": "Feature",
  "properties": {
    "iso:country":"BE",
    "sg:address":"Postbus 8",
    "sg:city":"Zelzate1",
    "sg:orig_category":"Non-Classified Establishments",
    "sg:phone":"+32 9 342 80 40",
    "sg:postcode":"9060",
    "sg:province":"Oost-Vlaanderen",
    "wof:name":"Van Geertruij Coatings",
    "wof:placetype":"venue"
},
  "geometry": {"coordinates":[3.8146300316,51.1975288391],"type":"Point"}
}