{
  "type": "Feature",
  "properties": {
    "addr:full":"Merelbekestraat 21 Melle Oost-Vlaanderen 9090",
    "addr:housenumber":"21",
    "addr:postcode":"9090",
    "addr:street":"Merelbekestraat",
    "iso:country":"BE",
    "sg:address":"Merelbekestraat 21",
    "sg:city":"Melle",
    "sg:classifiers":[
        {
            "category":"Home & Garden",
            "subcategory":"Home Furnishings",
            "type":"Retail Goods"
        }
    ],
    "sg:phone":"+32 9 230 82 87",
    "sg:postcode":"9090",
    "sg:province":"Oost-Vlaanderen",
    "sg:tags":[
        "interior",
        "decoration"
    ],
    "wof:name":"M.l.design",
    "wof:placetype":"venue"
},
  "geometry": {"coordinates":[3.7718598843,51.023765564],"type":"Point"}
}