{
  "type": "Feature",
  "properties": {
    "addr:full":"Rue De Lahaut 14 Nassogne Luxembourg 6950",
    "addr:housenumber":"14",
    "addr:postcode":"6950",
    "addr:street":"Rue De Lahaut",
    "iso:country":"BE",
    "sg:address":"Rue De Lahaut 14",
    "sg:city":"Nassogne",
    "sg:classifiers":[
        {
            "category":"Insurance",
            "subcategory":"Life Insurance",
            "type":"Services"
        }
    ],
    "sg:phone":"+32 84 21 46 10",
    "sg:postcode":"6950",
    "sg:province":"Luxembourg",
    "sg:tags":[
        "assurance"
    ],
    "wof:name":"M. Magerotte",
    "wof:placetype":"venue"
},
  "geometry": {"coordinates":[5.343752861,50.1281814575],"type":"Point"}
}