{
  "type": "Feature",
  "properties": {
    "addr:full":"Onafhankelijkheidsstraat 127 Edegem Antwerpen 2650",
    "addr:housenumber":"127",
    "addr:postcode":"2650",
    "addr:street":"Onafhankelijkheidsstraat",
    "iso:country":"BE",
    "sg:address":"Onafhankelijkheidsstraat 127",
    "sg:city":"Edegem",
    "sg:orig_category":"D\u00e9taillants en pi\u00e8ces and accessoires de voitures",
    "sg:phone":"+32 3 457 80 03",
    "sg:postcode":"2650",
    "sg:province":"Antwerpen",
    "wof:name":"Ahmed Barhih",
    "wof:placetype":"venue"
},
  "geometry": {"coordinates":[4.4458808899,51.1600608826],"type":"Point"}
}