{
  "type": "Feature",
  "properties": {
    "iso:country":"BE",
    "sg:address":"Rue De L'eglise 11",
    "sg:city":"Florenville",
    "sg:classifiers":[
        {
            "category":"Food & Beverages",
            "subcategory":"Specialty",
            "type":"Retail Goods"
        }
    ],
    "sg:phone":"+32 61 31 49 39",
    "sg:postcode":"6820",
    "sg:province":"Luxembourg",
    "sg:tags":[
        "health",
        "dietary",
        "-",
        "biological"
    ],
    "wof:name":"Dame Nature",
    "wof:placetype":"venue"
},
  "geometry": {"coordinates":[5.3113641739,49.6995811462],"type":"Point"}
}