{
  "type": "Feature",
  "properties": {
    "addr:full":"Chauss\u00e9e De Grammont 79 Lessines Hainaut 7860",
    "addr:housenumber":"79",
    "addr:postcode":"7860",
    "addr:street":"Chausse\u0301E De Grammont;Hainaut",
    "iso:country":"BE",
    "sg:address":"Chauss\u00e9e De Grammont 79",
    "sg:city":"Lessines",
    "sg:classifiers":[
        {
            "category":"Professional",
            "subcategory":"Accounting & Tax Preparation",
            "type":"Services"
        }
    ],
    "sg:phone":"+32 68 33 42 86",
    "sg:postcode":"7860",
    "sg:province":"Hainaut",
    "sg:tags":[
        "accountant"
    ],
    "wof:name":"Euracor European Accounting & Corporations Consultant",
    "wof:placetype":"venue"
},
  "geometry": {"coordinates":[3.8280661106,50.7158241272],"type":"Point"}
}