{
  "type": "Feature",
  "properties": {
    "iso:country":"BE",
    "sg:address":"Brusselbaan 333",
    "sg:city":"Affligem (hekelgem)",
    "sg:classifiers":[
        {
            "category":"Health Services",
            "subcategory":"Health Practitioner",
            "type":"Services"
        }
    ],
    "sg:phone":"+32 53 66 07 69",
    "sg:postcode":"1790",
    "sg:province":"Vlaams-Brabant",
    "sg:tags":[
        "physiotherapist"
    ],
    "wof:name":"De Winter Caroline",
    "wof:placetype":"venue"
},
  "geometry": {"coordinates":[4.130879879,50.9117889404],"type":"Point"}
}