{
  "type": "Feature",
  "properties": {
    "addr:full":"Place Gilles G\u00c9rard 0 Herstal Li\u00e8ge 4041",
    "addr:housenumber":"0",
    "addr:postcode":"4041",
    "addr:street":"Place Gilles Ge\u0301Rard",
    "iso:country":"BE",
    "sg:address":"Place Gilles G\u00c9rard 0",
    "sg:city":"Herstal",
    "sg:classifiers":[
        {
            "category":"Government",
            "subcategory":"Police Station",
            "type":"Public Place"
        }
    ],
    "sg:phone":"+32 4 227 03 77",
    "sg:postcode":"4041",
    "sg:province":"Li\u00e8ge",
    "sg:tags":[
        "gendarmerie"
    ],
    "wof:name":"Police F\u00c9d\u00c9rale/federale Politie",
    "wof:placetype":"venue"
},
  "geometry": {"coordinates":[5.5849328041,50.6726036072],"type":"Point"}
}