{
  "type": "Feature",
  "properties": {
    "iso:country":"BE",
    "sg:address":"Baron Ruzettelaan 193",
    "sg:city":"Brugge (assebroek)",
    "sg:classifiers":[
        {
            "category":"Shopping",
            "subcategory":"Books",
            "type":"Retail Goods"
        }
    ],
    "sg:phone":"+32 50 35 39 25",
    "sg:postcode":"8310",
    "sg:province":"West-Vlaanderen",
    "sg:tags":[
        "antiquarian",
        "trade"
    ],
    "wof:name":"Cursief",
    "wof:placetype":"venue"
},
  "geometry": {"coordinates":[3.2325680256,51.1927833557],"type":"Point"}
}