{
  "type": "Feature",
  "properties": {
    "addr:full":"Sint-elisabethstraat 62 Beveren Oost-Vlaanderen 9120",
    "addr:housenumber":"62",
    "addr:postcode":"9120",
    "addr:street":"Sint-Elisabethstraat",
    "iso:country":"BE",
    "sg:address":"Sint-elisabethstraat 62",
    "sg:city":"Beveren",
    "sg:orig_category":"Enseignement maternel and primaire",
    "sg:phone":"+32 3 775 74 76",
    "sg:postcode":"9120",
    "sg:province":"Oost-Vlaanderen",
    "wof:name":"Vrije Kleuterschool",
    "wof:placetype":"venue"
},
  "geometry": {"coordinates":[4.2831511497,51.2214012146],"type":"Point"}
}