{
  "type": "Feature",
  "properties": {
    "addr:full":"Gustaaf Peetersstraat 32b Ranst (broechem) Antwerpen 2520",
    "addr:housenumber":"32b",
    "addr:postcode":"2520",
    "addr:street":"Gustaaf Peetersstraat",
    "iso:country":"BE",
    "sg:address":"Gustaaf Peetersstraat 32b",
    "sg:city":"Ranst (broechem)",
    "sg:classifiers":[
        {
            "category":"Building & Trades",
            "subcategory":"Electrical",
            "type":"Services"
        }
    ],
    "sg:phone":"+32 3 485 65 94",
    "sg:postcode":"2520",
    "sg:province":"Antwerpen",
    "sg:tags":[
        "heating"
    ],
    "wof:name":"Calotech",
    "wof:placetype":"venue"
},
  "geometry": {"coordinates":[4.6042408943,51.180355072],"type":"Point"}
}