{
  "type": "Feature",
  "properties": {
    "addr:full":"Beke Tuinwijk 5 Waarschoot Oost-Vlaanderen 9950",
    "addr:housenumber":"5",
    "addr:postcode":"9950",
    "addr:street":"Tuinwijk",
    "iso:country":"BE",
    "sg:address":"Beke Tuinwijk 5",
    "sg:city":"Waarschoot",
    "sg:orig_category":"Gespecialiseerde residenti\u00eble bouw",
    "sg:phone":"+32 9 378 44 58",
    "sg:postcode":"9950",
    "sg:province":"Oost-Vlaanderen",
    "wof:name":"Eric De Graeve",
    "wof:placetype":"venue"
},
  "geometry": {"coordinates":[3.6054570675,51.1403961182],"type":"Point"}
}