{
  "type": "Feature",
  "properties": {
    "iso:country":"BE",
    "sg:address":"Rue Alfred Defuisseaux 116",
    "sg:city":"Loncin",
    "sg:classifiers":[
        {
            "category":"Professional",
            "subcategory":"Accounting & Tax Preparation",
            "type":"Services"
        }
    ],
    "sg:phone":"+32 4 263 26 59",
    "sg:postcode":"4431",
    "sg:province":"Li\u00e8ge",
    "sg:tags":[
        "revision"
    ],
    "wof:name":"Dc & Co S.p.r.l.",
    "wof:placetype":"venue"
},
  "geometry": {"coordinates":[5.504119873,50.6656188965],"type":"Point"}
}