{
  "type": "Feature",
  "properties": {
    "iso:country":"BE",
    "sg:address":"Boezingsestraat 21",
    "sg:city":"Ieper",
    "sg:orig_category":"Kapsalons",
    "sg:phone":"+32 57 42 16 10",
    "sg:postcode":"8904",
    "sg:province":"West-Vlaanderen",
    "wof:name":"Coiffure Mieke",
    "wof:placetype":"venue"
},
  "geometry": {"coordinates":[2.8533320427,50.8959884644],"type":"Point"}
}