{
  "type": "Feature",
  "properties": {
    "addr:full":"St.kristoffelstraat 43 Londerzeel Vlaams-Brabant 1840",
    "addr:housenumber":"43",
    "addr:postcode":"1840",
    "addr:street":"St.Kristoffelstraat",
    "iso:country":"BE",
    "sg:address":"St.kristoffelstraat 43",
    "sg:city":"Londerzeel",
    "sg:classifiers":[
        {
            "category":"Manufacturing",
            "subcategory":"Paper Products",
            "type":"Manufacturing & Wholesale Goods"
        }
    ],
    "sg:phone":"+32 52 30 04 11",
    "sg:postcode":"1840",
    "sg:province":"Vlaams-Brabant",
    "sg:tags":[
        "packaging",
        "material",
        "-",
        "cardboard"
    ],
    "wof:name":"Drukkerijen En Cartonnage Imperama Nv",
    "wof:placetype":"venue"
},
  "geometry": {"coordinates":[4.3081941605,51.0072135925],"type":"Point"}
}