{
  "type": "Feature",
  "properties": {
    "iso:country":"BE",
    "sg:address":"Grote Veldstraat 146",
    "sg:city":"Staden",
    "sg:orig_category":"Producteurs de l\u00e9gumes",
    "sg:phone":"+32 51 70 13 61",
    "sg:postcode":"8840",
    "sg:province":"West-Vlaanderen",
    "wof:name":"Kris Deleu",
    "wof:placetype":"venue"
},
  "geometry": {"coordinates":[3.0269510746,50.9497528076],"type":"Point"}
}