{
  "type": "Feature",
  "properties": {
    "addr:full":"Sint-rochusstraat 16 Herzele Oost-Vlaanderen 9550",
    "addr:housenumber":"16",
    "addr:postcode":"9550",
    "addr:street":"Sint-Rochusstraat;Oost-Vlaanderen",
    "iso:country":"BE",
    "sg:address":"Sint-rochusstraat 16",
    "sg:city":"Herzele",
    "sg:classifiers":[
        {
            "category":"Building & Trades",
            "subcategory":"Cleaning & Sanitation",
            "type":"Services"
        }
    ],
    "sg:phone":"+32 53 62 78 10",
    "sg:postcode":"9550",
    "sg:province":"Oost-Vlaanderen",
    "sg:tags":[
        "janitor"
    ],
    "wof:name":"Goossens G",
    "wof:placetype":"venue"
},
  "geometry": {"coordinates":[3.886934042,50.892578125],"type":"Point"}
}