{
  "type": "Feature",
  "properties": {
    "addr:full":"Oude Baan 68 Bonheiden Antwerpen 2820",
    "addr:housenumber":"68",
    "addr:postcode":"2820",
    "addr:street":"Oude Baan",
    "iso:country":"BE",
    "sg:address":"Oude Baan 68",
    "sg:city":"Bonheiden",
    "sg:orig_category":"Instituts de beaut\u00e9",
    "sg:phone":"+32 15 33 63 67",
    "sg:postcode":"2820",
    "sg:province":"Antwerpen",
    "wof:name":"Charmides",
    "wof:placetype":"venue"
},
  "geometry": {"coordinates":[4.5274691582,51.0337486267],"type":"Point"}
}