{
  "type": "Feature",
  "properties": {
    "addr:full":"Rijkmakerlaan 19 Essen Antwerpen 2910",
    "addr:housenumber":"19",
    "addr:postcode":"2910",
    "addr:street":"Rijkmakerlaan",
    "iso:country":"BE",
    "sg:address":"Rijkmakerlaan 19",
    "sg:city":"Essen",
    "sg:classifiers":[
        {
            "category":"Retail",
            "subcategory":"Auto Rental",
            "type":"Services"
        }
    ],
    "sg:phone":"+32 3 667 76 46",
    "sg:postcode":"2910",
    "sg:province":"Antwerpen",
    "sg:tags":[
        "milking",
        "machine"
    ],
    "wof:name":"Javado Koeltechniek",
    "wof:placetype":"venue"
},
  "geometry": {"coordinates":[4.499396801,51.4459877014],"type":"Point"}
}