{
  "type": "Feature",
  "properties": {
    "iso:country":"BE",
    "sg:address":"Rue Du March\u00c9 2ba",
    "sg:city":"Chimay",
    "sg:classifiers":[
        {
            "category":"Arena",
            "subcategory":"Sports Club",
            "type":"Entertainment"
        }
    ],
    "sg:phone":"+32 60 21 15 54",
    "sg:postcode":"6461",
    "sg:province":"Hainaut",
    "sg:tags":[
        "de"
    ],
    "wof:name":"Les Marcheurs Imbrechies",
    "wof:placetype":"venue"
},
  "geometry": {"coordinates":[4.3338098526,50.0646820068],"type":"Point"}
}