{
  "type": "Feature",
  "properties": {
    "addr:full":"Stationsstraat 39 Overijse Vlaams-Brabant 3090",
    "addr:housenumber":"39",
    "addr:postcode":"3090",
    "addr:street":"Stationsstraat",
    "iso:country":"BE",
    "sg:address":"Stationsstraat 39",
    "sg:city":"Overijse",
    "sg:orig_category":"Eclairage et \u00e9quipements du foyer",
    "sg:phone":"+32 2 687 27 23",
    "sg:postcode":"3090",
    "sg:province":"Vlaams-Brabant",
    "wof:name":"Diffuus",
    "wof:placetype":"venue"
},
  "geometry": {"coordinates":[4.5353140831,50.7712097168],"type":"Point"}
}