{
  "type": "Feature",
  "properties": {
    "addr:full":"Reigerlaan 1 Bornem Antwerpen 2880",
    "addr:housenumber":"1",
    "addr:postcode":"2880",
    "addr:street":"Reigerlaan",
    "iso:country":"BE",
    "sg:address":"Reigerlaan 1",
    "sg:city":"Bornem",
    "sg:orig_category":"Agences de publicit\u00e9. Secr\u00e9tariats",
    "sg:phone":"+32 3 889 73 59",
    "sg:postcode":"2880",
    "sg:province":"Antwerpen",
    "wof:name":"Prestomail",
    "wof:placetype":"venue"
},
  "geometry": {"coordinates":[4.2067241669,51.0716362],"type":"Point"}
}