{
  "type": "Feature",
  "properties": {
    "iso:country":"BE",
    "sg:address":"Cit\u00c9 Du Champ St.-pierre 10",
    "sg:city":"Quaregnon",
    "sg:orig_category":"Paramedische behandelingen",
    "sg:phone":"+32 65 67 62 74",
    "sg:postcode":"7390",
    "sg:province":"Hainaut",
    "wof:name":"V. Jaye",
    "wof:placetype":"venue"
},
  "geometry": {"coordinates":[3.8727369308,50.4194145203],"type":"Point"}
}