{
  "type": "Feature",
  "properties": {
    "iso:country":"BE",
    "sg:address":"Rue Pierre Michaut 72",
    "sg:city":"Oupeye",
    "sg:orig_category":"Entretien and r\u00e9parations de voitures",
    "sg:phone":"+32 87 26 88 25",
    "sg:postcode":"4680",
    "sg:province":"Li\u00e8ge",
    "wof:name":"Thalassa Car",
    "wof:placetype":"venue"
},
  "geometry": {"coordinates":[5.6444120407,50.7089729309],"type":"Point"}
}