{
  "type": "Feature",
  "properties": {
    "iso:country":"BE",
    "sg:address":"Beekstraat 6ba",
    "sg:city":"Oud-heverlee",
    "sg:orig_category":"Boekhandels Krantenwinkels Rookartikelen",
    "sg:phone":"+32 16 47 28 92",
    "sg:postcode":"3051",
    "sg:province":"Vlaams-Brabant",
    "wof:name":"Huis Frana",
    "wof:placetype":"venue"
},
  "geometry": {"coordinates":[4.6513609886,50.8029174805],"type":"Point"}
}