{
  "type": "Feature",
  "properties": {
    "addr:full":"Dr Fr. Verhaeghestraat 1b4 Blankenberge West-Vlaanderen 8370",
    "addr:housenumber":"1b4",
    "addr:postcode":"8370",
    "addr:street":"Dr Fr. Verhaeghestraat",
    "iso:country":"BE",
    "sg:address":"Dr Fr. Verhaeghestraat 1b4",
    "sg:city":"Blankenberge",
    "sg:orig_category":"Maisons de repos and r\u00e9sidences",
    "sg:phone":"+32 50 43 46 00",
    "sg:postcode":"8370",
    "sg:province":"West-Vlaanderen",
    "wof:name":"Bejaardenzorg Lindenhove",
    "wof:placetype":"venue"
},
  "geometry": {"coordinates":[3.1249508858,51.3084259033],"type":"Point"}
}