{
  "type": "Feature",
  "properties": {
    "addr:full":"Avenue De Chenai 175 Ukkel/uccle Bruxelles-Capitale 1180",
    "addr:housenumber":"175",
    "addr:postcode":"1180",
    "addr:street":"Avenue De Chenai;/",
    "iso:country":"BE",
    "sg:address":"Avenue De Chenai 175",
    "sg:city":"Ukkel/uccle",
    "sg:orig_category":"Agences de publicit\u00e9. Editeurs de journaux. Editeurs de revues and p\u00e9riodiques",
    "sg:phone":"+32 2 374 10 89",
    "sg:postcode":"1180",
    "sg:province":"Bruxelles-Capitale",
    "wof:name":"Challenger Consult",
    "wof:placetype":"venue"
},
  "geometry": {"coordinates":[4.3570799828,50.7830505371],"type":"Point"}
}