{
  "type": "Feature",
  "properties": {
    "iso:country":"BE",
    "sg:address":"Tulpenstraat 86",
    "sg:city":"Houthalen-helchteren",
    "sg:orig_category":"Herstelling leer and schoeisel",
    "sg:phone":"+32 89 38 42 93",
    "sg:postcode":"3530",
    "sg:province":"Limburg",
    "wof:name":"Pieter Meus",
    "wof:placetype":"venue"
},
  "geometry": {"coordinates":[5.4717330933,51.0183677673],"type":"Point"}
}