{
  "type": "Feature",
  "properties": {
    "addr:full":"62 Jagersdal 1600 Sint-pieters-leeuw 62",
    "addr:housenumber":"62;1600;62",
    "addr:street":"Jagersdal;Sint-Pieters-Leeuw",
    "iso:country":"BE",
    "sg:address":"62",
    "sg:city":"Jagersdal 1600 Sint-pieters-leeuw",
    "sg:classifiers":[
        {
            "category":"Wholesale",
            "subcategory":"Medical Equipment & Supplies",
            "type":"Manufacturing & Wholesale Goods"
        }
    ],
    "sg:phone":"+32 2 377 47 74",
    "sg:postcode":"62",
    "sg:tags":[
        "instrument",
        "health",
        "-",
        "precision"
    ],
    "wof:name":"Bierman Albert M.",
    "wof:placetype":"venue"
},
  "geometry": {"coordinates":[4.262357235,50.8012580872],"type":"Point"}
}