{
  "type": "Feature",
  "properties": {
    "iso:country":"BE",
    "sg:address":"Rue Du Centre 22",
    "sg:city":"Herbeumont",
    "sg:orig_category":"Rundveehouders",
    "sg:phone":"+32 61 27 72 50",
    "sg:postcode":"6887",
    "sg:province":"Luxembourg",
    "wof:name":"Joseph Maron",
    "wof:placetype":"venue"
},
  "geometry": {"coordinates":[5.23706007,49.7813262939],"type":"Point"}
}