{
  "type": "Feature",
  "properties": {
    "addr:full":"Jorezstraat 32 Anderlecht Bruxelles-Capitale 1070",
    "addr:housenumber":"32",
    "addr:postcode":"1070",
    "addr:street":"Jorezstraat",
    "iso:country":"BE",
    "sg:address":"Jorezstraat 32",
    "sg:city":"Anderlecht",
    "sg:orig_category":"Artsen and specialisten",
    "sg:phone":"+32 477 24 22 00",
    "sg:postcode":"1070",
    "sg:province":"Bruxelles-Capitale",
    "wof:name":"Rose Doumbe",
    "wof:placetype":"venue"
},
  "geometry": {"coordinates":[4.3328199387,50.8395462036],"type":"Point"}
}