{
  "type": "Feature",
  "properties": {
    "iso:country":"BE",
    "sg:address":"Avenue Edmond Leburton 27b2",
    "sg:city":"Waremme",
    "sg:orig_category":"Banken and kredietinstellingen",
    "sg:phone":"+32 19 33 02 07",
    "sg:postcode":"4300",
    "sg:province":"Li\u00e8ge",
    "wof:name":"Groupe Argenta",
    "wof:placetype":"venue"
},
  "geometry": {"coordinates":[5.2607097626,50.698059082],"type":"Point"}
}