{
  "type": "Feature",
  "properties": {
    "addr:full":"Avenue Brugmann 384 Ukkel/uccle Bruxelles-Capitale 1180",
    "addr:housenumber":"384",
    "addr:postcode":"1180",
    "addr:street":"Avenue Brugmann;/",
    "iso:country":"BE",
    "sg:address":"Avenue Brugmann 384",
    "sg:city":"Ukkel/uccle",
    "sg:orig_category":"Beheer onroerend goed Immobili\u00ebnkantoren",
    "sg:phone":"+32 2 640 03 27",
    "sg:postcode":"1180",
    "sg:province":"Bruxelles-Capitale",
    "wof:name":"Bureau Elkaur Internat.",
    "wof:placetype":"venue"
},
  "geometry": {"coordinates":[4.343266964,50.8059120178],"type":"Point"}
}