{
  "type": "Feature",
  "properties": {
    "addr:full":"Rue De L'eglise 7 Frameries Hainaut 7080",
    "addr:housenumber":"7",
    "addr:postcode":"7080",
    "addr:street":"Rue De L'Eglise",
    "iso:country":"BE",
    "sg:address":"Rue De L'eglise 7",
    "sg:city":"Frameries",
    "sg:orig_category":"Avocats and conseillers juridiques",
    "sg:phone":"+32 65 67 39 85",
    "sg:postcode":"7080",
    "sg:province":"Hainaut",
    "wof:name":"F. Thonet",
    "wof:placetype":"venue"
},
  "geometry": {"coordinates":[3.8938519955,50.4108009338],"type":"Point"}
}