{
  "type": "Feature",
  "properties": {
    "iso:country":"BE",
    "sg:address":"Antoon Mouqu\u00e9straat 2",
    "sg:city":"Oostende",
    "sg:classifiers":[
        {
            "category":"Retail",
            "subcategory":"Auto Repair",
            "type":"Services"
        }
    ],
    "sg:phone":"+32 494 94 38 30",
    "sg:postcode":"8400",
    "sg:province":"West-Vlaanderen",
    "sg:tags":[
        "garage"
    ],
    "wof:name":"A.s. Service Center",
    "wof:placetype":"venue"
},
  "geometry": {"coordinates":[2.9126999378,51.2312583923],"type":"Point"}
}