{
  "type": "Feature",
  "properties": {
    "iso:country":"BE",
    "sg:address":"Kretenburgstraat 108",
    "sg:city":"Mortsel",
    "sg:classifiers":[
        {
            "category":"Shopping",
            "subcategory":"Party Supplies",
            "type":"Retail Goods"
        }
    ],
    "sg:phone":"+32 3 455 13 15",
    "sg:postcode":"2640",
    "sg:province":"Antwerpen",
    "sg:tags":[
        "technician",
        "equipment",
        "dental",
        "-",
        "dentist"
    ],
    "wof:name":"All-technics",
    "wof:placetype":"venue"
},
  "geometry": {"coordinates":[4.4684948921,51.1627807617],"type":"Point"}
}