{
  "type": "Feature",
  "properties": {
    "iso:country":"BE",
    "sg:address":"Rue Fran\u00e7ois-boudart 41",
    "sg:city":"Arlon",
    "sg:classifiers":[
        {
            "category":"Health Services",
            "subcategory":"Doctor",
            "type":"Services"
        }
    ],
    "sg:phone":"+32 63 21 68 80",
    "sg:postcode":"6700",
    "sg:province":"Luxembourg",
    "sg:tags":[
        "psychotherapist",
        "psychoanalyst"
    ],
    "wof:name":"Richard M",
    "wof:placetype":"venue"
},
  "geometry": {"coordinates":[5.8078079224,49.6889610291],"type":"Point"}
}