{
  "type": "Feature",
  "properties": {
    "addr:full":"Boelare 113 Eeklo Oost-Vlaanderen 9900",
    "addr:housenumber":"113",
    "addr:postcode":"9900",
    "iso:country":"BE",
    "sg:address":"Boelare 113",
    "sg:city":"Eeklo",
    "sg:orig_category":"Herstelling and restauratie van meubelen Textiel",
    "sg:phone":"+32 9 378 10 64",
    "sg:postcode":"9900",
    "sg:province":"Oost-Vlaanderen",
    "wof:name":"Modecoupon",
    "wof:placetype":"venue"
},
  "geometry": {"coordinates":[3.5675499439,51.1884117126],"type":"Point"}
}