{
  "type": "Feature",
  "properties": {
    "iso:country":"BE",
    "sg:address":"Kerkstraat 50",
    "sg:city":"De Haan",
    "sg:classifiers":[
        {
            "category":"Restaurant",
            "type":"Food & Drink"
        }
    ],
    "sg:phone":"+32 50 42 65 25",
    "sg:postcode":"8420",
    "sg:province":"West-Vlaanderen",
    "wof:name":"Bistro Picardie",
    "wof:placetype":"venue"
},
  "geometry": {"coordinates":[3.0811181068,51.2997741699],"type":"Point"}
}