{
  "type": "Feature",
  "properties": {
    "addr:full":"Keizer Karelstraat 33 Brugge West-Vlaanderen 8000",
    "addr:housenumber":"33",
    "addr:postcode":"8000",
    "addr:street":"Keizer Karelstraat",
    "iso:country":"BE",
    "sg:address":"Keizer Karelstraat 33",
    "sg:city":"Brugge",
    "sg:orig_category":"Installation \u00e9lectrique r\u00e9sidentielle. Eclairage et \u00e9quipements du foyer. Installation \u00e9lectrique in",
    "sg:phone":"+32 50 31 70 11",
    "sg:postcode":"8000",
    "sg:province":"West-Vlaanderen",
    "wof:name":"Electro Crappe",
    "wof:placetype":"venue"
},
  "geometry": {"coordinates":[3.2118959427,51.213218689],"type":"Point"}
}