{
  "type": "Feature",
  "properties": {
    "addr:full":"Hoek 115 Boom Antwerpen 2850",
    "addr:housenumber":"115",
    "addr:postcode":"2850",
    "addr:street":"Hoek",
    "iso:country":"BE",
    "sg:address":"Hoek 115",
    "sg:city":"Boom",
    "sg:orig_category":"Installatie van houten of kunststof schrijnwerk",
    "sg:phone":"+32 3 843 35 00",
    "sg:postcode":"2850",
    "sg:province":"Antwerpen",
    "wof:name":"Matrix Door",
    "wof:placetype":"venue"
},
  "geometry": {"coordinates":[4.3793430328,51.0834274292],"type":"Point"}
}