{
  "type": "Feature",
  "properties": {
    "addr:full":"Hanendreef 95 Brasschaat Antwerpen 2930",
    "addr:housenumber":"95",
    "addr:postcode":"2930",
    "addr:street":"Hanendreef",
    "iso:country":"BE",
    "sg:address":"Hanendreef 95",
    "sg:city":"Brasschaat",
    "sg:orig_category":"Elektrische installaties voor woningen Huishoudapparaten, televisies and radio's Verlichting and hui",
    "sg:phone":"+32 3 651 78 74",
    "sg:postcode":"2930",
    "sg:province":"Antwerpen",
    "wof:name":"Van Der Spiegel-leenaerts",
    "wof:placetype":"venue"
},
  "geometry": {"coordinates":[4.4795131683,51.2959289551],"type":"Point"}
}