{
  "type": "Feature",
  "properties": {
    "addr:full":"Bras 6ba Bastogne Luxembourg 6600",
    "addr:housenumber":"6ba",
    "addr:postcode":"6600",
    "addr:street":"Bras",
    "iso:country":"BE",
    "sg:address":"Bras 6ba",
    "sg:city":"Bastogne",
    "sg:orig_category":"Woningbouw",
    "sg:phone":"+32 61 21 47 05",
    "sg:postcode":"6600",
    "sg:province":"Luxembourg",
    "wof:name":"Thill Jean-marie",
    "wof:placetype":"venue"
},
  "geometry": {"coordinates":[5.7187590599,50.0037651062],"type":"Point"}
}