{
  "type": "Feature",
  "properties": {
    "addr:full":"Vijfde Havendok Noordkaai 367-369 Antwerpen Antwerpen 2030",
    "addr:housenumber":"367-369",
    "addr:postcode":"2030",
    "iso:country":"BE",
    "sg:address":"Vijfde Havendok Noordkaai 367-369",
    "sg:city":"Antwerpen",
    "sg:classifiers":[
        {
            "category":"Shopping",
            "subcategory":"Discount & Variety Stores",
            "type":"Retail Goods"
        }
    ],
    "sg:phone":"+32 3 542 43 10",
    "sg:postcode":"2030",
    "sg:province":"Antwerpen",
    "sg:tags":[
        "warehouse",
        "-",
        "merchandise"
    ],
    "wof:name":"Bma Nv",
    "wof:placetype":"venue"
},
  "geometry": {"coordinates":[4.350230217,51.2941017151],"type":"Point"}
}