{
  "type": "Feature",
  "properties": {
    "iso:country":"BE",
    "sg:address":"Rue Des Goujons 22",
    "sg:city":"Anderlecht",
    "sg:orig_category":"Ladies' Handbags",
    "sg:phone":"+32 2 521 14 25",
    "sg:postcode":"1070",
    "sg:province":"Bruxelles-Capitale",
    "wof:name":"Chomax S.p.r.l.",
    "wof:placetype":"venue"
},
  "geometry": {"coordinates":[4.3259129524,50.838470459],"type":"Point"}
}