{
  "type": "Feature",
  "properties": {
    "addr:full":"Rue De La Tombale 9 Eghez\u00e9e (aische-en-refail) Namur 5310",
    "addr:housenumber":"9",
    "addr:postcode":"5310",
    "addr:street":"Rue De La Tombale;Aische-En-Refail",
    "iso:country":"BE",
    "sg:address":"Rue De La Tombale 9",
    "sg:city":"Eghez\u00e9e (aische-en-refail)",
    "sg:classifiers":[
        {
            "category":"Food & Beverages",
            "subcategory":"Groceries & Convenience Stores",
            "type":"Retail Goods"
        }
    ],
    "sg:phone":"+32 81 65 72 56",
    "sg:postcode":"5310",
    "sg:province":"Namur",
    "sg:tags":[
        "grocer"
    ],
    "wof:name":"Bertrand Sprl",
    "wof:placetype":"venue"
},
  "geometry": {"coordinates":[4.8431158066,50.598903656],"type":"Point"}
}