{
  "type": "Feature",
  "properties": {
    "iso:country":"BE",
    "sg:address":"Kasteelpleinstraat 49",
    "sg:city":"Antwerpen",
    "sg:classifiers":[
        {
            "category":"Restaurant",
            "type":"Food & Drink"
        }
    ],
    "sg:phone":"+32 3 226 11 99",
    "sg:postcode":"2000",
    "sg:province":"Antwerpen",
    "wof:name":"Grand Caf\u00c9 Leroy",
    "wof:placetype":"venue"
},
  "geometry": {"coordinates":[4.4020562172,51.2102584839],"type":"Point"}
}