{
  "type": "Feature",
  "properties": {
    "addr:full":"Luikersteenweg 207 Sint-truiden (brustem) Limburg 3800",
    "addr:housenumber":"207",
    "addr:postcode":"3800",
    "addr:street":"Luikersteenweg",
    "iso:country":"BE",
    "sg:address":"Luikersteenweg 207",
    "sg:city":"Sint-truiden (brustem)",
    "sg:classifiers":[
        {
            "category":"Wholesale",
            "subcategory":"Beer",
            "type":"Manufacturing & Wholesale Goods"
        }
    ],
    "sg:phone":"+32 11 69 25 23",
    "sg:postcode":"3800",
    "sg:province":"Limburg",
    "sg:tags":[
        "ale",
        "-"
    ],
    "wof:name":"All-drinks Bungeneers",
    "wof:placetype":"venue"
},
  "geometry": {"coordinates":[5.2028431892,50.8036689758],"type":"Point"}
}