{
  "type": "Feature",
  "properties": {
    "iso:country":"BE",
    "sg:address":"Rue De Bambois 660",
    "sg:city":"Mettet",
    "sg:orig_category":"Sportclubs",
    "sg:phone":"+32 71 79 97 15",
    "sg:postcode":"5640",
    "sg:province":"Namur",
    "wof:name":"Ham Cyclo - Ham S./s.",
    "wof:placetype":"venue"
},
  "geometry": {"coordinates":[4.709980011,50.3684883118],"type":"Point"}
}