{
  "type": "Feature",
  "properties": {
    "addr:full":"Zarrenstraat 38 Kortemark (zarren-werken) West-Vlaanderen 8610",
    "addr:housenumber":"38",
    "addr:postcode":"8610",
    "addr:street":"Zarrenstraat",
    "iso:country":"BE",
    "sg:address":"Zarrenstraat 38",
    "sg:city":"Kortemark (zarren-werken)",
    "sg:classifiers":[
        {
            "category":"Personal",
            "subcategory":"Beauty Salon",
            "type":"Services"
        }
    ],
    "sg:phone":"+32 51 56 65 85",
    "sg:postcode":"8610",
    "sg:province":"West-Vlaanderen",
    "sg:tags":[
        "lady",
        "-",
        "hairdressing"
    ],
    "wof:name":"Vanhonsebrouck W",
    "wof:placetype":"venue"
},
  "geometry": {"coordinates":[2.9618399143,51.0241699219],"type":"Point"}
}