{
  "type": "Feature",
  "properties": {
    "iso:country":"BE",
    "sg:address":"Zuiderdijk 25",
    "sg:city":"Wetteren",
    "sg:classifiers":[
        {
            "category":"Shopping",
            "subcategory":"Bicycles & Sporting Goods",
            "type":"Retail Goods"
        }
    ],
    "sg:phone":"+32 9 369 25 80",
    "sg:postcode":"9230",
    "sg:province":"Oost-Vlaanderen",
    "sg:tags":[
        "accessory"
    ],
    "wof:name":"Rijwielen Prestige Nv",
    "wof:placetype":"venue"
},
  "geometry": {"coordinates":[3.8784201145,51.0075798035],"type":"Point"}
}