{
  "type": "Feature",
  "properties": {
    "iso:country":"BE",
    "sg:address":"Justus Lipsiusstraat 40 Box 2",
    "sg:city":"Leuven",
    "sg:classifiers":[
        {
            "category":"Organizations",
            "subcategory":"Professional Association",
            "type":"Services"
        }
    ],
    "sg:phone":"+32 16 23 08 90",
    "sg:postcode":"3000",
    "sg:province":"Vlaams-Brabant",
    "sg:tags":[
        "trade-union",
        "federation"
    ],
    "wof:name":"Syndicaat Van Vlaamse Huisartsen Vzw",
    "wof:placetype":"venue"
},
  "geometry": {"coordinates":[4.7148399353,50.8780403137],"type":"Point"}
}