{
  "type": "Feature",
  "properties": {
    "addr:full":"Rue Claie 71 Aubange (halanzy) Luxembourg 6792",
    "addr:housenumber":"71",
    "addr:postcode":"6792",
    "addr:street":"Rue Claie",
    "iso:country":"BE",
    "sg:address":"Rue Claie 71",
    "sg:city":"Aubange (halanzy)",
    "sg:classifiers":[
        {
            "category":"Farming",
            "subcategory":"Livestock Farm",
            "type":"Manufacturing & Wholesale Goods"
        }
    ],
    "sg:phone":"+32 63 38 83 24",
    "sg:postcode":"6792",
    "sg:province":"Luxembourg",
    "sg:tags":[
        "buyer"
    ],
    "wof:name":"Rollin N",
    "wof:placetype":"venue"
},
  "geometry": {"coordinates":[5.7793660164,49.5776481628],"type":"Point"}
}