{
  "type": "Feature",
  "properties": {
    "addr:full":"Gansterenstraat 17 Hoeselt Limburg 3730",
    "addr:housenumber":"17",
    "addr:postcode":"3730",
    "addr:street":"Gansterenstraat",
    "iso:country":"BE",
    "sg:address":"Gansterenstraat 17",
    "sg:city":"Hoeselt",
    "sg:orig_category":"Eleveurs de bovins",
    "sg:phone":"+32 89 41 64 57",
    "sg:postcode":"3730",
    "sg:province":"Limburg",
    "wof:name":"Petrus Vanhees",
    "wof:placetype":"venue"
},
  "geometry": {"coordinates":[5.4891839027,50.8529891968],"type":"Point"}
}