{
  "type": "Feature",
  "properties": {
    "addr:full":"Rue Hamoir 18 La Louviere Hainaut 7100",
    "addr:housenumber":"18",
    "addr:postcode":"7100",
    "addr:street":"Rue Hamoir",
    "iso:country":"BE",
    "sg:address":"Rue Hamoir 18",
    "sg:city":"La Louviere",
    "sg:orig_category":"Banken and kredietinstellingen",
    "sg:phone":"+32 64 22 10 47",
    "sg:postcode":"7100",
    "sg:province":"Hainaut",
    "wof:name":"Citibank",
    "wof:placetype":"venue"
},
  "geometry": {"coordinates":[4.193379879,50.4747123718],"type":"Point"}
}