{
  "type": "Feature",
  "properties": {
    "addr:full":"Neerbeekstraat 1 Anzegem West-Vlaanderen 8572",
    "addr:housenumber":"1",
    "addr:postcode":"8572",
    "addr:street":"Neerbeekstraat",
    "iso:country":"BE",
    "sg:address":"Neerbeekstraat 1",
    "sg:city":"Anzegem",
    "sg:orig_category":"Installation \u00e9lectrique r\u00e9sidentielle",
    "sg:phone":"+32 56 68 95 54",
    "sg:postcode":"8572",
    "sg:province":"West-Vlaanderen",
    "wof:name":"Clova",
    "wof:placetype":"venue"
},
  "geometry": {"coordinates":[3.4955999851,50.8192367554],"type":"Point"}
}