{
  "type": "Feature",
  "properties": {
    "addr:full":"Eikhof 1 Lint Antwerpen 2547",
    "addr:housenumber":"1",
    "addr:postcode":"2547",
    "addr:street":"Eikhof",
    "iso:country":"BE",
    "sg:address":"Eikhof 1",
    "sg:city":"Lint",
    "sg:orig_category":"Enseignement maternel and primaire",
    "sg:phone":"+32 3 455 39 80",
    "sg:postcode":"2547",
    "sg:province":"Antwerpen",
    "wof:name":"Basisschool",
    "wof:placetype":"venue"
},
  "geometry": {"coordinates":[4.4898300171,51.1269111633],"type":"Point"}
}