{
  "type": "Feature",
  "properties": {
    "addr:full":"Alexandre Markelbachstr. 82 Schaarbeek/schaerbeek Bruxelles-Capitale 1030",
    "addr:housenumber":"82",
    "addr:postcode":"1030",
    "iso:country":"BE",
    "sg:address":"Alexandre Markelbachstr. 82",
    "sg:city":"Schaarbeek/schaerbeek",
    "sg:orig_category":"Persagentschappen",
    "sg:phone":"+32 2 245 34 01",
    "sg:postcode":"1030",
    "sg:province":"Bruxelles-Capitale",
    "wof:name":"Fran\u00c7ois Janne D'othee",
    "wof:placetype":"venue"
},
  "geometry": {"coordinates":[4.3834061623,50.8553924561],"type":"Point"}
}