{
  "type": "Feature",
  "properties": {
    "addr:full":"Kunstlaan 12 Boom Antwerpen 2850",
    "addr:housenumber":"12",
    "addr:postcode":"2850",
    "addr:street":"Kunstlaan",
    "iso:country":"BE",
    "sg:address":"Kunstlaan 12",
    "sg:city":"Boom",
    "sg:classifiers":[
        {
            "category":"Recreation",
            "subcategory":"Amusement Park",
            "type":"Entertainment"
        }
    ],
    "sg:phone":"+32 3 888 37 14",
    "sg:postcode":"2850",
    "sg:province":"Antwerpen",
    "sg:tags":[
        "attraction",
        "-",
        "sale",
        "fair",
        "hiring"
    ],
    "wof:name":"Action Jump Bvba",
    "wof:placetype":"venue"
},
  "geometry": {"coordinates":[4.3698692322,51.1015357971],"type":"Point"}
}