{
  "type": "Feature",
  "properties": {
    "iso:country":"BE",
    "sg:address":"Gemeenteplaats 22",
    "sg:city":"Brecht",
    "sg:orig_category":"Slagers",
    "sg:phone":"+32 3 313 80 82",
    "sg:postcode":"2960",
    "sg:province":"Antwerpen",
    "wof:name":"Kris Van Helvert",
    "wof:placetype":"venue"
},
  "geometry": {"coordinates":[4.6428132057,51.3506469727],"type":"Point"}
}