{
  "type": "Feature",
  "properties": {
    "iso:country":"BE",
    "sg:address":"Rue De La Clawenne 90",
    "sg:city":"Herstal",
    "sg:orig_category":"Woningbouw",
    "sg:phone":"+32 4 264 63 43",
    "sg:postcode":"4040",
    "sg:province":"Li\u00e8ge",
    "wof:name":"City Home",
    "wof:placetype":"venue"
},
  "geometry": {"coordinates":[5.6373200417,50.6746444702],"type":"Point"}
}