{
  "type": "Feature",
  "properties": {
    "iso:country":"BE",
    "sg:address":"Kapel Ter Bede 86",
    "sg:city":"Kortrijk",
    "sg:classifiers":[
        {
            "category":"Wholesale",
            "subcategory":"Construction Materials",
            "type":"Manufacturing & Wholesale Goods"
        }
    ],
    "sg:phone":"+32 56 24 95 11",
    "sg:postcode":"8500",
    "sg:province":"West-Vlaanderen",
    "sg:tags":[
        "bituminous"
    ],
    "wof:name":"Koramic Building Product Nv",
    "wof:placetype":"venue"
},
  "geometry": {"coordinates":[3.2991828918,50.823764801],"type":"Point"}
}