{
  "type": "Feature",
  "properties": {
    "iso:country":"BE",
    "sg:address":"Zakstraat 19",
    "sg:city":"Antwerpen",
    "sg:classifiers":[
        {
            "category":"Cafe",
            "type":"Food & Drink"
        }
    ],
    "sg:phone":"+32 3 231 74 42",
    "sg:postcode":"2000",
    "sg:province":"Antwerpen",
    "sg:tags":[
        "caf\u00e9s"
    ],
    "wof:name":"Caf\u00c9 Jabeau",
    "wof:placetype":"venue"
},
  "geometry": {"coordinates":[4.3997159004,51.2232322693],"type":"Point"}
}