{
  "type": "Feature",
  "properties": {
    "iso:country":"BE",
    "sg:address":"Th. Wautersstraat 40",
    "sg:city":"Bertem",
    "sg:orig_category":"Elektrische installaties voor woningen Industri\u00eble elektrische installaties",
    "sg:phone":"+32 2 767 09 02",
    "sg:postcode":"3061",
    "sg:province":"Vlaams-Brabant",
    "wof:name":"A.m.e. Security",
    "wof:placetype":"venue"
},
  "geometry": {"coordinates":[4.5911397934,50.8475608826],"type":"Point"}
}