{
  "type": "Feature",
  "properties": {
    "iso:country":"BE",
    "sg:address":"Av. Franchet-d\u00b4esperey 1",
    "sg:city":"Dinant",
    "sg:classifiers":[
        {
            "category":"Restaurant",
            "type":"Food & Drink"
        }
    ],
    "sg:phone":"+32 82 22 64 67",
    "sg:postcode":"5500",
    "sg:province":"Namur",
    "sg:tags":[
        "caf\u00e9s"
    ],
    "wof:name":"Buffet De La Gare",
    "wof:placetype":"venue"
},
  "geometry": {"coordinates":[4.9047198296,50.2654762268],"type":"Point"}
}