{
  "type": "Feature",
  "properties": {
    "addr:full":"Avenue De La Lib\u00e9ration 55 Couvin Namur 5660",
    "addr:housenumber":"55",
    "addr:postcode":"5660",
    "addr:street":"Avenue De La Libe\u0301Ration",
    "iso:country":"BE",
    "sg:address":"Avenue De La Lib\u00e9ration 55",
    "sg:city":"Couvin",
    "sg:classifiers":[
        {
            "category":"Health Services",
            "subcategory":"Doctor",
            "type":"Services"
        }
    ],
    "sg:phone":"+32 60 34 62 45",
    "sg:postcode":"5660",
    "sg:province":"Namur",
    "sg:tags":[
        "psychotherapist",
        "psychoanalyst"
    ],
    "wof:name":"Cuvelier P",
    "wof:placetype":"venue"
},
  "geometry": {"coordinates":[4.4872789383,50.0549697876],"type":"Point"}
}