{
  "type": "Feature",
  "properties": {
    "addr:full":"Peperstraat 86 Kortenberg (erps-kwerps) Vlaams-Brabant 3071",
    "addr:housenumber":"86",
    "addr:postcode":"3071",
    "addr:street":"Peperstraat",
    "iso:country":"BE",
    "sg:address":"Peperstraat 86",
    "sg:city":"Kortenberg (erps-kwerps)",
    "sg:classifiers":[
        {
            "category":"Health Services",
            "subcategory":"Nursing And Care Facility",
            "type":"Services"
        }
    ],
    "sg:phone":"+32 2 757 96 76",
    "sg:postcode":"3071",
    "sg:province":"Vlaams-Brabant",
    "sg:tags":[
        "home"
    ],
    "wof:name":"De Groef P",
    "wof:placetype":"venue"
},
  "geometry": {"coordinates":[4.553935051,50.9030456543],"type":"Point"}
}