{
  "type": "Feature",
  "properties": {
    "addr:full":"Kastanjelaan 82 Zulte Oost-Vlaanderen 9870",
    "addr:housenumber":"82",
    "addr:postcode":"9870",
    "addr:street":"Kastanjelaan",
    "iso:country":"BE",
    "sg:address":"Kastanjelaan 82",
    "sg:city":"Zulte",
    "sg:orig_category":"Landmeters",
    "sg:phone":"+32 9 388 43 88",
    "sg:postcode":"9870",
    "sg:province":"Oost-Vlaanderen",
    "wof:name":"Tom Lippens",
    "wof:placetype":"venue"
},
  "geometry": {"coordinates":[3.447496891,50.918838501],"type":"Point"}
}