{
  "type": "Feature",
  "properties": {
    "addr:full":"Rue De Stalle 276 Bruxelles (uccle) Bruxelles-Capitale 1180",
    "addr:housenumber":"276",
    "addr:postcode":"1180",
    "addr:street":"Rue De Stalle",
    "iso:country":"BE",
    "sg:address":"Rue De Stalle 276",
    "sg:city":"Bruxelles (uccle)",
    "sg:classifiers":[
        {
            "category":"Shopping",
            "subcategory":"Computers & Home Electronics",
            "type":"Retail Goods"
        }
    ],
    "sg:phone":"+32 2 376 12 32",
    "sg:postcode":"1180",
    "sg:province":"Bruxelles-Capitale",
    "sg:tags":[
        "-",
        "television",
        "radio"
    ],
    "wof:name":"Techniradio",
    "wof:placetype":"venue"
},
  "geometry": {"coordinates":[4.3221330643,50.7959785461],"type":"Point"}
}