{
  "type": "Feature",
  "properties": {
    "addr:full":"Rue Douffet 98 Li\u00c8ge Li\u00e8ge 4020",
    "addr:housenumber":"98",
    "addr:postcode":"4020",
    "addr:street":"Rue Douffet",
    "iso:country":"BE",
    "sg:address":"Rue Douffet 98",
    "sg:city":"Li\u00c8ge",
    "sg:orig_category":"Apotheken",
    "sg:phone":"+32 4 342 52 62",
    "sg:postcode":"4020",
    "sg:province":"Li\u00e8ge",
    "wof:name":"Christiane Pondant",
    "wof:placetype":"venue"
},
  "geometry": {"coordinates":[5.5841012001,50.634437561],"type":"Point"}
}