{
  "type": "Feature",
  "properties": {
    "iso:country":"BE",
    "sg:address":"Mont 23",
    "sg:city":"Ellezelles",
    "sg:orig_category":"HUISBRANDOLIE",
    "sg:phone":"+32 68 54 25 31",
    "sg:postcode":"7890",
    "sg:province":"Hainaut",
    "wof:name":"Maison De Ridder",
    "wof:placetype":"venue"
},
  "geometry": {"coordinates":[3.674685955,50.7446250916],"type":"Point"}
}