{
  "type": "Feature",
  "properties": {
    "addr:full":"Rue Du Molinay 49 Seraing Li\u00e8ge 4100",
    "addr:housenumber":"49",
    "addr:postcode":"4100",
    "addr:street":"Rue Du Molinay",
    "iso:country":"BE",
    "sg:address":"Rue Du Molinay 49",
    "sg:city":"Seraing",
    "sg:classifiers":[
        {
            "category":"Manufacturing",
            "subcategory":"Textiles",
            "type":"Manufacturing & Wholesale Goods"
        }
    ],
    "sg:phone":"+32 4 337 55 29",
    "sg:postcode":"4100",
    "sg:province":"Li\u00e8ge",
    "wof:name":"Bernard Herman",
    "wof:placetype":"venue"
},
  "geometry": {"coordinates":[5.5137839317,50.6075515747],"type":"Point"}
}