{
  "type": "Feature",
  "properties": {
    "addr:full":"Oostendestraat 64 Torhout West-Vlaanderen 8820",
    "addr:housenumber":"64",
    "addr:postcode":"8820",
    "addr:street":"Oostendestraat",
    "iso:country":"BE",
    "sg:address":"Oostendestraat 64",
    "sg:city":"Torhout",
    "sg:orig_category":"Bloemen and planten",
    "sg:phone":"+32 50 22 07 00",
    "sg:postcode":"8820",
    "sg:province":"West-Vlaanderen",
    "wof:name":"Huis Bloemendale",
    "wof:placetype":"venue"
},
  "geometry": {"coordinates":[3.0969998837,51.0657958984],"type":"Point"}
}