{
  "type": "Feature",
  "properties": {
    "addr:full":"Sint-maurusweg 29 Tienen Vlaams-Brabant 3300",
    "addr:housenumber":"29",
    "addr:postcode":"3300",
    "addr:street":"Sint-Maurusweg",
    "iso:country":"BE",
    "sg:address":"Sint-maurusweg 29",
    "sg:city":"Tienen",
    "sg:orig_category":"Installatie van houten of kunststof schrijnwerk Installatie van metalen schrijnwerk",
    "sg:phone":"+32 16 82 52 56",
    "sg:postcode":"3300",
    "sg:province":"Vlaams-Brabant",
    "wof:name":"Wintek",
    "wof:placetype":"venue"
},
  "geometry": {"coordinates":[4.9594750404,50.7965545654],"type":"Point"}
}