{
  "type": "Feature",
  "properties": {
    "iso:country":"BE",
    "sg:address":"Kapelstraat 12",
    "sg:city":"Deerlijk",
    "sg:orig_category":"Entretien and r\u00e9parations de voitures",
    "sg:phone":"+32 56 77 74 76",
    "sg:postcode":"8540",
    "sg:province":"West-Vlaanderen",
    "wof:name":"Garage Delombaerde",
    "wof:placetype":"venue"
},
  "geometry": {"coordinates":[3.3773069382,50.8209533691],"type":"Point"}
}