{
  "type": "Feature",
  "properties": {
    "addr:full":"Place Des Combattants 18 Montigny-le-tilleul (landelies) Hainaut 6111",
    "addr:housenumber":"18",
    "addr:postcode":"6111",
    "addr:street":"Place Des Combattants",
    "iso:country":"BE",
    "sg:address":"Place Des Combattants 18",
    "sg:city":"Montigny-le-tilleul (landelies)",
    "sg:classifiers":[
        {
            "category":"Health Services",
            "subcategory":"Health Practitioner",
            "type":"Services"
        }
    ],
    "sg:phone":"+32 71 56 03 41",
    "sg:postcode":"6111",
    "sg:province":"Hainaut",
    "sg:tags":[
        "physiotherapist"
    ],
    "wof:name":"Jouret-baudry Annie",
    "wof:placetype":"venue"
},
  "geometry": {"coordinates":[4.3542132378,50.3787231445],"type":"Point"}
}