{
  "type": "Feature",
  "properties": {
    "iso:country":"BE",
    "sg:address":"Rue De La Poire D\u00b4or 7",
    "sg:city":"Mons",
    "sg:orig_category":"Entretien and r\u00e9parations de voitures. V\u00e9hicules automobiles",
    "sg:phone":"+32 65 34 88 78",
    "sg:postcode":"7033",
    "sg:province":"Hainaut",
    "wof:name":"Mascolo",
    "wof:placetype":"venue"
},
  "geometry": {"coordinates":[3.9253261089,50.4366378784],"type":"Point"}
}