{
  "type": "Feature",
  "properties": {
    "addr:full":"Rue De La Chapelle 88 Verviers Li\u00e8ge 4800",
    "addr:housenumber":"88",
    "addr:postcode":"4800",
    "addr:street":"Rue De La Chapelle",
    "iso:country":"BE",
    "sg:address":"Rue De La Chapelle 88",
    "sg:city":"Verviers",
    "sg:classifiers":[
        {
            "category":"Real Estate",
            "subcategory":"Surveying",
            "type":"Services"
        }
    ],
    "sg:phone":"+32 87 33 04 35",
    "sg:postcode":"4800",
    "sg:province":"Li\u00e8ge",
    "sg:tags":[
        "surveyor",
        "land"
    ],
    "wof:name":"Voos P",
    "wof:placetype":"venue"
},
  "geometry": {"coordinates":[5.8594508171,50.5917663574],"type":"Point"}
}