{
  "type": "Feature",
  "properties": {
    "iso:country":"BE",
    "sg:address":"Vander Aastraat 38",
    "sg:city":"Machelen",
    "sg:orig_category":"Epiceries",
    "sg:phone":"+32 2 720 09 53",
    "sg:postcode":"1831",
    "sg:province":"Vlaams-Brabant",
    "wof:name":"Ria Goovaerts",
    "wof:placetype":"venue"
},
  "geometry": {"coordinates":[4.4387159348,50.8931465149],"type":"Point"}
}