{
  "type": "Feature",
  "properties": {
    "addr:full":"Avenue Van Volxem 407 Bruxelles (forest) Bruxelles-Capitale 1190",
    "addr:housenumber":"407",
    "addr:postcode":"1190",
    "addr:street":"Avenue Van Volxem",
    "iso:country":"BE",
    "sg:address":"Avenue Van Volxem 407",
    "sg:city":"Bruxelles (forest)",
    "sg:classifiers":[
        {
            "category":"Retail",
            "subcategory":"Event Space",
            "type":"Services"
        }
    ],
    "sg:phone":"+32 2 543 09 30",
    "sg:postcode":"1190",
    "sg:province":"Bruxelles-Capitale",
    "sg:tags":[
        "organisation"
    ],
    "wof:name":"Concept + Sa",
    "wof:placetype":"venue"
},
  "geometry": {"coordinates":[4.3271269798,50.826385498],"type":"Point"}
}