{
  "type": "Feature",
  "properties": {
    "addr:full":"Rue Royale 36 Tournai Hainaut 7500",
    "addr:housenumber":"36",
    "addr:postcode":"7500",
    "addr:street":"Rue Royale",
    "iso:country":"BE",
    "sg:address":"Rue Royale 36",
    "sg:city":"Tournai",
    "sg:orig_category":"Huishoudapparaten, televisies and radio's",
    "sg:phone":"+32 69 22 43 79",
    "sg:postcode":"7500",
    "sg:province":"Hainaut",
    "wof:name":"Maison Merchez",
    "wof:placetype":"venue"
},
  "geometry": {"coordinates":[3.3929219246,50.6099281311],"type":"Point"}
}