{
  "type": "Feature",
  "properties": {
    "addr:full":"Zandvoortstraat C18 Mechelen Antwerpen 2800",
    "addr:housenumber":"c18",
    "addr:postcode":"2800",
    "addr:street":"Zandvoortstraat",
    "iso:country":"BE",
    "sg:address":"Zandvoortstraat C18",
    "sg:city":"Mechelen",
    "sg:orig_category":"Industri\u00eble elektrische installaties",
    "sg:phone":"+32 15 20 88 15",
    "sg:postcode":"2800",
    "sg:province":"Antwerpen",
    "wof:name":"E.c.s.",
    "wof:placetype":"venue"
},
  "geometry": {"coordinates":[4.4854397774,51.0289268494],"type":"Point"}
}