{
  "type": "Feature",
  "properties": {
    "addr:full":"Chauss\u00e9e D'alsemberg 183bis Linkebeek Vlaams-Brabant 1630",
    "addr:housenumber":"183bis",
    "addr:postcode":"1630",
    "addr:street":"Chausse\u0301E D'Alsemberg",
    "iso:country":"BE",
    "sg:address":"Chauss\u00e9e D'alsemberg 183bis",
    "sg:city":"Linkebeek",
    "sg:classifiers":[
        {
            "category":"Real Estate",
            "subcategory":"Architect",
            "type":"Services"
        }
    ],
    "sg:phone":"+32 2 380 49 85",
    "sg:postcode":"1630",
    "sg:province":"Vlaams-Brabant",
    "wof:name":"De Becker F",
    "wof:placetype":"venue"
},
  "geometry": {"coordinates":[4.3257470131,50.7787322998],"type":"Point"}
}