{
  "type": "Feature",
  "properties": {
    "addr:full":"Rue Neuve 37 Pepinster Li\u00e8ge 4860",
    "addr:housenumber":"37",
    "addr:postcode":"4860",
    "addr:street":"Rue Neuve",
    "iso:country":"BE",
    "sg:address":"Rue Neuve 37",
    "sg:city":"Pepinster",
    "sg:orig_category":"Openbare veiligheid",
    "sg:phone":"+32 87 46 03 21",
    "sg:postcode":"4860",
    "sg:province":"Li\u00e8ge",
    "wof:name":"Police F\u00c9d\u00c9rale",
    "wof:placetype":"venue"
},
  "geometry": {"coordinates":[5.8031949997,50.5668907166],"type":"Point"}
}