{
  "type": "Feature",
  "properties": {
    "iso:country":"BE",
    "sg:address":"Burgscheldestraat 25 Box 2",
    "sg:city":"Oudenaarde",
    "sg:classifiers":[
        {
            "category":"Professional",
            "subcategory":"Lawyer & Legal Services",
            "type":"Services"
        }
    ],
    "sg:phone":"+32 55 31 82 62",
    "sg:postcode":"9700",
    "sg:province":"Oost-Vlaanderen",
    "wof:name":"Lamon Jan",
    "wof:placetype":"venue"
},
  "geometry": {"coordinates":[3.6066539288,50.8437957764],"type":"Point"}
}