{
  "type": "Feature",
  "properties": {
    "iso:country":"BE",
    "sg:address":"Rue De Florennes 4ba",
    "sg:city":"Mettet",
    "sg:orig_category":"Opticiens",
    "sg:phone":"+32 71 72 71 59",
    "sg:postcode":"5640",
    "sg:province":"Namur",
    "wof:name":"Michel Loicq",
    "wof:placetype":"venue"
},
  "geometry": {"coordinates":[4.6578249931,50.3188362122],"type":"Point"}
}