{
  "type": "Feature",
  "properties": {
    "iso:country":"BE",
    "sg:address":"Chauss\u00e9e De Mons 1301",
    "sg:city":"Bruxelles (anderlecht)",
    "sg:classifiers":[
        {
            "category":"Health Services",
            "subcategory":"Nursing And Care Facility",
            "type":"Services"
        }
    ],
    "sg:phone":"+32 2 522 36 21",
    "sg:postcode":"1070",
    "sg:province":"Bruxelles-Capitale",
    "sg:tags":[
        "humidifiers",
        "dehydrating",
        "apparatus"
    ],
    "wof:name":"Locamat",
    "wof:placetype":"venue"
},
  "geometry": {"coordinates":[4.2912302017,50.8172416687],"type":"Point"}
}