{
  "type": "Feature",
  "properties": {
    "addr:full":"Mechelse Plein 20 Antwerpen Antwerpen 2000",
    "addr:housenumber":"20",
    "addr:postcode":"2000",
    "addr:street":"Plein",
    "iso:country":"BE",
    "sg:address":"Mechelse Plein 20",
    "sg:city":"Antwerpen",
    "sg:orig_category":"Boekhouders",
    "sg:phone":"+32 3 226 70 81",
    "sg:postcode":"2000",
    "sg:province":"Antwerpen",
    "wof:name":"Tom Van Berendoncks",
    "wof:placetype":"venue"
},
  "geometry": {"coordinates":[4.404938221,51.2132225037],"type":"Point"}
}