{
  "type": "Feature",
  "properties": {
    "iso:country":"BE",
    "sg:address":"Wilgenweg 3",
    "sg:city":"Sint-amands",
    "sg:orig_category":"Elektrische installaties voor woningen Industri\u00eble elektrische installaties",
    "sg:phone":"+32 3 889 36 71",
    "sg:postcode":"2890",
    "sg:province":"Antwerpen",
    "wof:name":"De Pauw Elektriciteitswerken",
    "wof:placetype":"venue"
},
  "geometry": {"coordinates":[4.2397661209,51.0651473999],"type":"Point"}
}