{
  "type": "Feature",
  "properties": {
    "iso:country":"BE",
    "sg:address":"Stationsstraat 26",
    "sg:city":"Kluisbergen (berchem)",
    "sg:classifiers":[
        {
            "category":"Shopping",
            "subcategory":"Clothing, Apparel, & Fashions",
            "type":"Retail Goods"
        }
    ],
    "sg:phone":"+32 55 38 54 60",
    "sg:postcode":"9690",
    "sg:province":"Oost-Vlaanderen",
    "sg:tags":[
        "-",
        "clothing",
        "child"
    ],
    "wof:name":"Harlekijntje ('t)",
    "wof:placetype":"venue"
},
  "geometry": {"coordinates":[3.5097439289,50.7898979187],"type":"Point"}
}