{
  "type": "Feature",
  "properties": {
    "addr:full":"Chem. Bois Des R\u00c9collets 56 Theux Li\u00e8ge 4910",
    "addr:housenumber":"56",
    "addr:postcode":"4910",
    "addr:street":"Chem. Bois Des Re\u0301Collets",
    "iso:country":"BE",
    "sg:address":"Chem. Bois Des R\u00c9collets 56",
    "sg:city":"Theux",
    "sg:orig_category":"Electrom\u00e9nager, t\u00e9l\u00e9visions and radios. R\u00e9parations d'appareils \u00e9lectrom\u00e9nagers. Eclairage et \u00e9quipe",
    "sg:phone":"+32 87 22 89 83",
    "sg:postcode":"4910",
    "sg:province":"Li\u00e8ge",
    "wof:name":"A.m. Electronic",
    "wof:placetype":"venue"
},
  "geometry": {"coordinates":[5.903231144,50.5568389893],"type":"Point"}
}