{
  "type": "Feature",
  "properties": {
    "addr:full":"Industrielaan 21 Zottegem Oost-Vlaanderen 9620",
    "addr:housenumber":"21",
    "addr:postcode":"9620",
    "addr:street":"Industrielaan",
    "iso:country":"BE",
    "sg:address":"Industrielaan 21",
    "sg:city":"Zottegem",
    "sg:classifiers":[
        {
            "category":"Manufacturing",
            "subcategory":"Wood Products",
            "type":"Manufacturing & Wholesale Goods"
        }
    ],
    "sg:phone":"+32 9 360 24 73",
    "sg:postcode":"9620",
    "sg:province":"Oost-Vlaanderen",
    "sg:tags":[
        "gate",
        "made",
        "door"
    ],
    "wof:name":"Maegerman W. B.v.b.a.",
    "wof:placetype":"venue"
},
  "geometry": {"coordinates":[3.8112111092,50.871181488],"type":"Point"}
}