{
  "type": "Feature",
  "properties": {
    "iso:country":"BE",
    "sg:address":"Lakweg 16",
    "sg:city":"Antwerpen",
    "sg:orig_category":"D\u00e9m\u00e9nagements",
    "sg:phone":"+32 3 646 81 19",
    "sg:postcode":"2020",
    "sg:province":"Antwerpen",
    "wof:name":"Make My Day",
    "wof:placetype":"venue"
},
  "geometry": {"coordinates":[4.3596401215,51.196559906],"type":"Point"}
}