{
  "type": "Feature",
  "properties": {
    "iso:country":"BE",
    "sg:address":"Rue De Porcheresse 78",
    "sg:city":"Daverdisse",
    "sg:orig_category":"Eleveurs de bovins",
    "sg:phone":"+32 61 51 12 32",
    "sg:postcode":"6929",
    "sg:province":"Luxembourg",
    "wof:name":"Philippe Wilvers",
    "wof:placetype":"venue"
},
  "geometry": {"coordinates":[5.0663127899,49.9943656921],"type":"Point"}
}