{
  "type": "Feature",
  "properties": {
    "addr:full":"Grand'place 38 P\u00e9ruwelz Hainaut 7600",
    "addr:housenumber":"38",
    "addr:postcode":"7600",
    "addr:street":"Grand'Place",
    "iso:country":"BE",
    "sg:address":"Grand'place 38",
    "sg:city":"P\u00e9ruwelz",
    "sg:classifiers":[
        {
            "category":"Professional",
            "subcategory":"Lawyer & Legal Services",
            "type":"Services"
        }
    ],
    "sg:phone":"+32 69 77 18 10",
    "sg:postcode":"7600",
    "sg:province":"Hainaut",
    "wof:name":"Taeke Philippe",
    "wof:placetype":"venue"
},
  "geometry": {"coordinates":[3.5923399925,50.5101509094],"type":"Point"}
}