{
  "type": "Feature",
  "properties": {
    "addr:full":"Rucaplein 2 Antwerpen (wilrijk) Antwerpen 2610",
    "addr:housenumber":"2",
    "addr:postcode":"2610",
    "addr:street":"Rucaplein;Antwerpen",
    "iso:country":"BE",
    "sg:address":"Rucaplein 2",
    "sg:city":"Antwerpen (wilrijk)",
    "sg:classifiers":[
        {
            "category":"Professional",
            "subcategory":"Engineering",
            "type":"Services"
        }
    ],
    "sg:phone":"+32 3 239 58 75",
    "sg:postcode":"2610",
    "sg:province":"Antwerpen",
    "sg:tags":[
        "-"
    ],
    "wof:name":"Arcade Nv",
    "wof:placetype":"venue"
},
  "geometry": {"coordinates":[4.4218611717,51.1779327393],"type":"Point"}
}