{
  "type": "Feature",
  "properties": {
    "iso:country":"BE",
    "sg:address":"Gerheide 180",
    "sg:city":"Balen",
    "sg:classifiers":[
        {
            "category":"Health Services",
            "subcategory":"Nursing And Care Facility",
            "type":"Services"
        }
    ],
    "sg:phone":"+32 14 81 76 66",
    "sg:postcode":"2490",
    "sg:province":"Antwerpen",
    "sg:tags":[
        "home",
        "rest"
    ],
    "wof:name":"Nethehof",
    "wof:placetype":"venue"
},
  "geometry": {"coordinates":[5.2256999016,51.1849708557],"type":"Point"}
}