{
  "type": "Feature",
  "properties": {
    "iso:country":"BE",
    "sg:address":"Avenue Des Petits Champs 123",
    "sg:city":"Waterloo",
    "sg:classifiers":[
        {
            "category":"Train Station",
            "subcategory":"Light Rail",
            "type":"Transportation"
        }
    ],
    "sg:phone":"+32 2 351 17 76",
    "sg:postcode":"1410",
    "sg:province":"Brabant Wallon",
    "sg:tags":[
        "luminous",
        "score-boards",
        "display"
    ],
    "wof:name":"Pam Diffusion Europe Sa",
    "wof:placetype":"venue"
},
  "geometry": {"coordinates":[4.4110770226,50.7224578857],"type":"Point"}
}