{
  "type": "Feature",
  "properties": {
    "iso:country":"BE",
    "sg:address":"Tongersesteenweg 152",
    "sg:city":"Sint-truiden",
    "sg:classifiers":[
        {
            "category":"Farming",
            "subcategory":"Fish & Marine Products",
            "type":"Manufacturing & Wholesale Goods"
        }
    ],
    "sg:phone":"+32 11 67 06 11",
    "sg:postcode":"3800",
    "sg:province":"Limburg",
    "sg:tags":[
        "livestock",
        "food",
        "related",
        "fruit",
        "vegetable",
        "agriculture"
    ],
    "wof:name":"Veiling Haspengouw Cv",
    "wof:placetype":"venue"
},
  "geometry": {"coordinates":[5.2028589249,50.8111686707],"type":"Point"}
}