{
  "type": "Feature",
  "properties": {
    "addr:full":"Rue Eug\u00c9nie P. Lothier 10 Charleroi Hainaut 6001",
    "addr:housenumber":"10",
    "addr:postcode":"6001",
    "addr:street":"Rue Euge\u0301Nie P. Lothier;Hainaut",
    "iso:country":"BE",
    "sg:address":"Rue Eug\u00c9nie P. Lothier 10",
    "sg:city":"Charleroi",
    "sg:orig_category":"Animations diverses. Agents artistiques",
    "sg:phone":"+32 71 36 85 33",
    "sg:postcode":"6001",
    "sg:province":"Hainaut",
    "wof:name":"Star Service",
    "wof:placetype":"venue"
},
  "geometry": {"coordinates":[4.4440507889,50.3898582458],"type":"Point"}
}