{
  "type": "Feature",
  "properties": {
    "addr:full":"Engelstraat 97ba Ichtegem West-Vlaanderen 8480",
    "addr:housenumber":"97ba",
    "addr:postcode":"8480",
    "addr:street":"Engelstraat",
    "iso:country":"BE",
    "sg:address":"Engelstraat 97ba",
    "sg:city":"Ichtegem",
    "sg:orig_category":"Travaux de pl\u00e2trage",
    "sg:phone":"+32 51 58 30 24",
    "sg:postcode":"8480",
    "sg:province":"West-Vlaanderen",
    "wof:name":"Nico Moerman",
    "wof:placetype":"venue"
},
  "geometry": {"coordinates":[3.0190958977,51.0950508118],"type":"Point"}
}