{
  "type": "Feature",
  "properties": {
    "iso:country":"BE",
    "sg:address":"Kantwerkersstraat 2",
    "sg:city":"Houthulst (klerken)",
    "sg:classifiers":[
        {
            "category":"Real Estate",
            "subcategory":"Architect",
            "type":"Services"
        }
    ],
    "sg:phone":"+32 51 50 58 89",
    "sg:postcode":"8650",
    "sg:province":"West-Vlaanderen",
    "wof:name":"Vande Candelaere A",
    "wof:placetype":"venue"
},
  "geometry": {"coordinates":[2.9119400978,50.9935302734],"type":"Point"}
}