{
  "type": "Feature",
  "properties": {
    "addr:full":"Rue De France 13 Erquelinnes Hainaut 6560",
    "addr:housenumber":"13",
    "addr:postcode":"6560",
    "addr:street":"Rue De France",
    "iso:country":"BE",
    "sg:address":"Rue De France 13",
    "sg:city":"Erquelinnes",
    "sg:orig_category":"Antiek",
    "sg:phone":"+32 71 55 76 26",
    "sg:postcode":"6560",
    "sg:province":"Hainaut",
    "wof:name":"Philippe Carrion",
    "wof:placetype":"venue"
},
  "geometry": {"coordinates":[4.1412930489,50.3066711426],"type":"Point"}
}