{
  "type": "Feature",
  "properties": {
    "addr:full":"Schapenstraat 138c Lennik (sint-martens-lennik) Vlaams-Brabant 1750",
    "addr:housenumber":"138c",
    "addr:postcode":"1750",
    "addr:street":"Schapenstraat",
    "iso:country":"BE",
    "sg:address":"Schapenstraat 138c",
    "sg:city":"Lennik (sint-martens-lennik)",
    "sg:classifiers":[
        {
            "category":"Shopping",
            "subcategory":"Pets & Pet Supplies",
            "type":"Retail Goods"
        }
    ],
    "sg:phone":"+32 2 532 19 73",
    "sg:postcode":"1750",
    "sg:province":"Vlaams-Brabant",
    "sg:tags":[
        "bird"
    ],
    "wof:name":"Barbe-nechelput",
    "wof:placetype":"venue"
},
  "geometry": {"coordinates":[4.1680002213,50.8277549744],"type":"Point"}
}