{
  "type": "Feature",
  "properties": {
    "iso:country":"BE",
    "sg:address":"Rue De L'est 29",
    "sg:city":"Verviers",
    "sg:classifiers":[
        {
            "category":"Wholesale",
            "subcategory":"Meat",
            "type":"Manufacturing & Wholesale Goods"
        }
    ],
    "sg:phone":"+32 87 22 72 23",
    "sg:postcode":"4800",
    "sg:province":"Li\u00e8ge",
    "sg:tags":[
        "whol",
        "-"
    ],
    "wof:name":"Defechereux Fils",
    "wof:placetype":"venue"
},
  "geometry": {"coordinates":[5.8755340576,50.5953216553],"type":"Point"}
}