{
  "type": "Feature",
  "properties": {
    "addr:full":"Rue Des Alli\u00e9s 33 Gr\u00e2ce-hollogne (gr\u00e2ce-berleur) Li\u00e8ge 4460",
    "addr:housenumber":"33",
    "addr:postcode":"4460",
    "addr:street":"Rue Des Allie\u0301S;Gra\u0302Ce-Berleur",
    "iso:country":"BE",
    "sg:address":"Rue Des Alli\u00e9s 33",
    "sg:city":"Gr\u00e2ce-hollogne (gr\u00e2ce-berleur)",
    "sg:classifiers":[
        {
            "category":"Education",
            "subcategory":"Library",
            "type":"Public Place"
        }
    ],
    "sg:phone":"+32 4 239 69 29",
    "sg:postcode":"4460",
    "sg:province":"Li\u00e8ge",
    "wof:name":"Bibliotheque Communale",
    "wof:placetype":"venue"
},
  "geometry": {"coordinates":[5.5038747787,50.6462745667],"type":"Point"}
}