{
  "type": "Feature",
  "properties": {
    "iso:country":"BE",
    "sg:address":"Speurtstraat 49",
    "sg:city":"Lede",
    "sg:orig_category":"Brood, gebak and snoepgoed",
    "sg:phone":"+32 9 369 06 71",
    "sg:postcode":"9340",
    "sg:province":"Oost-Vlaanderen",
    "wof:name":"Herv\u00c9 Mertens",
    "wof:placetype":"venue"
},
  "geometry": {"coordinates":[3.8987960815,50.9610061646],"type":"Point"}
}