{
  "type": "Feature",
  "properties": {
    "iso:country":"BE",
    "sg:address":"Dr\u00e8ve Colau Djirau 9",
    "sg:city":"Villers-la-ville",
    "sg:classifiers":[
        {
            "category":"Professional",
            "subcategory":"Management & Consulting",
            "type":"Services"
        }
    ],
    "sg:phone":"+32 71 87 87 42",
    "sg:postcode":"1495",
    "sg:province":"Brabant Wallon",
    "sg:tags":[
        "consultant"
    ],
    "wof:name":"Lepot J",
    "wof:placetype":"venue"
},
  "geometry": {"coordinates":[4.5470380783,50.5768356323],"type":"Point"}
}