{
  "type": "Feature",
  "properties": {
    "addr:full":"Molenstraat 2b Genk Limburg 3600",
    "addr:housenumber":"2b",
    "addr:postcode":"3600",
    "addr:street":"Molenstraat",
    "iso:country":"BE",
    "sg:address":"Molenstraat 2b",
    "sg:city":"Genk",
    "sg:classifiers":[
        {
            "category":"Shopping",
            "subcategory":"Clothing, Apparel, & Fashions",
            "type":"Retail Goods"
        }
    ],
    "sg:phone":"+32 89 65 10 00",
    "sg:postcode":"3600",
    "sg:province":"Limburg",
    "sg:tags":[
        "boutique"
    ],
    "wof:name":"Esprit Bvba",
    "wof:placetype":"venue"
},
  "geometry": {"coordinates":[5.5004792213,50.964302063],"type":"Point"}
}