{
  "type": "Feature",
  "properties": {
    "iso:country":"BE",
    "sg:address":"Tieltstraat 193",
    "sg:city":"Meulebeke",
    "sg:orig_category":"Producteurs de l\u00e9gumes. Fruits and l\u00e9gumes Gr",
    "sg:phone":"+32 51 40 16 01",
    "sg:postcode":"8760",
    "sg:province":"West-Vlaanderen",
    "wof:name":"Roland Vanhove",
    "wof:placetype":"venue"
},
  "geometry": {"coordinates":[3.303565979,50.9692268372],"type":"Point"}
}