{
  "type": "Feature",
  "properties": {
    "iso:country":"BE",
    "sg:address":"Leuvensesteenweg 148",
    "sg:city":"Aarschot (gelrode)",
    "sg:classifiers":[
        {
            "category":"Professional",
            "subcategory":"Management & Consulting",
            "type":"Services"
        }
    ],
    "sg:phone":"+32 486 64 24 22",
    "sg:postcode":"3200",
    "sg:province":"Vlaams-Brabant",
    "sg:tags":[
        "consultant"
    ],
    "wof:name":"Kris Vallons Management",
    "wof:placetype":"venue"
},
  "geometry": {"coordinates":[4.8208599091,50.9797706604],"type":"Point"}
}