{
  "type": "Feature",
  "properties": {
    "iso:country":"BE",
    "sg:address":"Onze-lieve-vrouweplein 13",
    "sg:city":"Boechout",
    "sg:classifiers":[
        {
            "category":"Home & Garden",
            "subcategory":"Home Furnishings",
            "type":"Retail Goods"
        }
    ],
    "sg:phone":"+32 3 455 21 59",
    "sg:postcode":"2530",
    "sg:province":"Antwerpen",
    "sg:tags":[
        "-",
        "furniture"
    ],
    "wof:name":"Jori-van Pee",
    "wof:placetype":"venue"
},
  "geometry": {"coordinates":[4.4912500381,51.1606330872],"type":"Point"}
}