{
  "type": "Feature",
  "properties": {
    "iso:country":"BE",
    "sg:address":"Larendries 62",
    "sg:city":"Sint-amands",
    "sg:classifiers":[
        {
            "category":"Arena",
            "subcategory":"Sports Club",
            "type":"Entertainment"
        }
    ],
    "sg:phone":"+32 52 34 04 21",
    "sg:postcode":"2890",
    "sg:province":"Antwerpen",
    "sg:tags":[
        "terrain",
        "hors",
        "de",
        "installation",
        "sportifs"
    ],
    "wof:name":"S.k. St.amands",
    "wof:placetype":"venue"
},
  "geometry": {"coordinates":[4.2135381699,51.0424880981],"type":"Point"}
}