{
  "type": "Feature",
  "properties": {
    "addr:full":"Chauss\u00c9e Romaine 10a Geer Li\u00e8ge 4252",
    "addr:housenumber":"10a",
    "addr:postcode":"4252",
    "addr:street":"Chausse\u0301E Romaine",
    "iso:country":"BE",
    "sg:address":"Chauss\u00c9e Romaine 10a",
    "sg:city":"Geer",
    "sg:orig_category":"Installatie van houten of kunststof schrijnwerk Installatie van metalen schrijnwerk",
    "sg:phone":"+32 19 58 83 75",
    "sg:postcode":"4252",
    "sg:province":"Li\u00e8ge",
    "wof:name":"J.m. Latour",
    "wof:placetype":"venue"
},
  "geometry": {"coordinates":[5.1947379112,50.6503143311],"type":"Point"}
}