{
  "type": "Feature",
  "properties": {
    "iso:country":"BE",
    "sg:address":"Hoefsmidstraat 18",
    "sg:city":"Londerzeel",
    "sg:orig_category":"G\u00e9om\u00e8tres",
    "sg:phone":"+32 52 33 77 97",
    "sg:postcode":"1840",
    "sg:province":"Vlaams-Brabant",
    "wof:name":"Jose Verpoucke",
    "wof:placetype":"venue"
},
  "geometry": {"coordinates":[4.2448577881,51.0163917542],"type":"Point"}
}