{
  "type": "Feature",
  "properties": {
    "addr:full":"Weterbeekstraat 4 Bierbeek Vlaams-Brabant 3360",
    "addr:housenumber":"4",
    "addr:postcode":"3360",
    "addr:street":"Weterbeekstraat",
    "iso:country":"BE",
    "sg:address":"Weterbeekstraat 4",
    "sg:city":"Bierbeek",
    "sg:classifiers":[
        {
            "category":"Cafe",
            "type":"Food & Drink"
        }
    ],
    "sg:phone":"+32 16 46 25 93",
    "sg:postcode":"3360",
    "sg:province":"Vlaams-Brabant",
    "sg:tags":[
        "caf\u00e9s"
    ],
    "wof:name":"Raymond Smets",
    "wof:placetype":"venue"
},
  "geometry": {"coordinates":[4.7924618721,50.8399505615],"type":"Point"}
}