{
  "type": "Feature",
  "properties": {
    "addr:full":"Oeverstraat 12 Lokeren Oost-Vlaanderen 9160",
    "addr:housenumber":"12",
    "addr:postcode":"9160",
    "addr:street":"Oeverstraat",
    "iso:country":"BE",
    "sg:address":"Oeverstraat 12",
    "sg:city":"Lokeren",
    "sg:orig_category":"Onderdelen and accessoires voor auto's",
    "sg:phone":"+32 9 348 78 55",
    "sg:postcode":"9160",
    "sg:province":"Oost-Vlaanderen",
    "wof:name":"Interband",
    "wof:placetype":"venue"
},
  "geometry": {"coordinates":[4.0184412003,51.0957641602],"type":"Point"}
}