{
  "type": "Feature",
  "properties": {
    "addr:full":"Rue De La Sir\u00c8ne 8 Li\u00c8ge Li\u00e8ge 4000",
    "addr:housenumber":"8",
    "addr:postcode":"4000",
    "addr:street":"Rue De La Sire\u0300Ne",
    "iso:country":"BE",
    "sg:address":"Rue De La Sir\u00c8ne 8",
    "sg:city":"Li\u00c8ge",
    "sg:orig_category":"Artsen and specialisten",
    "sg:phone":"+32 4 223 56 19",
    "sg:postcode":"4000",
    "sg:province":"Li\u00e8ge",
    "wof:name":"Andr\u00c9 Longchamps",
    "wof:placetype":"venue"
},
  "geometry": {"coordinates":[5.5725221634,50.6411705017],"type":"Point"}
}