{
  "type": "Feature",
  "properties": {
    "addr:full":"Steenstraat 105 Kortemark West-Vlaanderen 8610",
    "addr:housenumber":"105",
    "addr:postcode":"8610",
    "addr:street":"Steenstraat",
    "iso:country":"BE",
    "sg:address":"Steenstraat 105",
    "sg:city":"Kortemark",
    "sg:orig_category":"Eleveurs and marchands de porcs",
    "sg:phone":"+32 51 56 70 07",
    "sg:postcode":"8610",
    "sg:province":"West-Vlaanderen",
    "wof:name":"Willy Bolle",
    "wof:placetype":"venue"
},
  "geometry": {"coordinates":[2.9929740429,51.0536651611],"type":"Point"}
}