{
  "type": "Feature",
  "properties": {
    "iso:country":"BE",
    "sg:address":"Heikant 14",
    "sg:city":"Achel",
    "sg:classifiers":[
        {
            "category":"Bakery",
            "type":"Food & Drink"
        }
    ],
    "sg:phone":"+32 11 64 77 11",
    "sg:postcode":"3930",
    "sg:province":"Limburg",
    "sg:tags":[
        "cake",
        "product",
        "related",
        "bread"
    ],
    "wof:name":"Pb Snacks Nv",
    "wof:placetype":"venue"
},
  "geometry": {"coordinates":[5.4705162048,51.2780838013],"type":"Point"}
}