{
  "type": "Feature",
  "properties": {
    "addr:full":"Rue Emile Vandervelde 33 Lessines (ollignies) Hainaut 7866",
    "addr:housenumber":"33",
    "addr:postcode":"7866",
    "addr:street":"Rue Emile Vandervelde",
    "iso:country":"BE",
    "sg:address":"Rue Emile Vandervelde 33",
    "sg:city":"Lessines (ollignies)",
    "sg:classifiers":[
        {
            "category":"Health Services",
            "subcategory":"Doctor",
            "type":"Services"
        }
    ],
    "sg:phone":"+32 68 33 39 04",
    "sg:postcode":"7866",
    "sg:province":"Hainaut",
    "sg:tags":[
        "medicinephysicians",
        "surgeon"
    ],
    "wof:name":"Duchemin J P",
    "wof:placetype":"venue"
},
  "geometry": {"coordinates":[3.8611130714,50.6866531372],"type":"Point"}
}