{
  "type": "Feature",
  "properties": {
    "addr:full":"Rue Du Centre 11 Saint-georges-sur-meuse Li\u00e8ge 4470",
    "addr:housenumber":"11",
    "addr:postcode":"4470",
    "addr:street":"Rue Du Centre",
    "iso:country":"BE",
    "sg:address":"Rue Du Centre 11",
    "sg:city":"Saint-georges-sur-meuse",
    "sg:classifiers":[
        {
            "category":"Cafe",
            "type":"Food & Drink"
        }
    ],
    "sg:phone":"+32 4 259 52 20",
    "sg:postcode":"4470",
    "sg:province":"Li\u00e8ge",
    "sg:tags":[
        "caf\u00e9s"
    ],
    "wof:name":"Caf\u00c9 Wiliquet",
    "wof:placetype":"venue"
},
  "geometry": {"coordinates":[5.3579111099,50.6006660461],"type":"Point"}
}