{
  "type": "Feature",
  "properties": {
    "iso:country":"BE",
    "sg:address":"Keuzelingsstraat 26",
    "sg:city":"Kluisbergen",
    "sg:orig_category":"Entretien and r\u00e9parations de voitures",
    "sg:phone":"+32 55 38 98 10",
    "sg:postcode":"9690",
    "sg:province":"Oost-Vlaanderen",
    "wof:name":"Stefaan Beck",
    "wof:placetype":"venue"
},
  "geometry": {"coordinates":[3.5400409698,50.7848396301],"type":"Point"}
}