{
  "type": "Feature",
  "properties": {
    "addr:full":"Blijde Inkomststraat 130 Leuven Vlaams-Brabant 3000",
    "addr:housenumber":"130",
    "addr:postcode":"3000",
    "addr:street":"Blijde Inkomststraat",
    "iso:country":"BE",
    "sg:address":"Blijde Inkomststraat 130",
    "sg:city":"Leuven",
    "sg:classifiers":[
        {
            "category":"Parking",
            "subcategory":"Bicycle",
            "type":"Transportation"
        }
    ],
    "sg:phone":"+32 16 22 24 46",
    "sg:postcode":"3000",
    "sg:province":"Vlaams-Brabant",
    "sg:tags":[
        "chiropodist"
    ],
    "wof:name":"Hermans-meeus",
    "wof:placetype":"venue"
},
  "geometry": {"coordinates":[4.712638855,50.8745269775],"type":"Point"}
}