{
  "type": "Feature",
  "properties": {
    "iso:country":"BE",
    "sg:address":"Rochesterlaan 3",
    "sg:city":"Gistel",
    "sg:classifiers":[
        {
            "category":"Shopping",
            "subcategory":"Department Store",
            "type":"Retail Goods"
        }
    ],
    "sg:phone":"+32 59 27 61 79",
    "sg:postcode":"8470",
    "sg:province":"West-Vlaanderen",
    "sg:tags":[
        "surplus",
        "army"
    ],
    "wof:name":"Stock Super Shop Nv",
    "wof:placetype":"venue"
},
  "geometry": {"coordinates":[2.9465379715,51.1470413208],"type":"Point"}
}