{
  "type": "Feature",
  "properties": {
    "iso:country":"BE",
    "sg:address":"Zuidstationstraat 2ba",
    "sg:city":"Gent",
    "sg:orig_category":"Modellenbureaus",
    "sg:phone":"+32 9 224 32 23",
    "sg:postcode":"9000",
    "sg:province":"Oost-Vlaanderen",
    "wof:name":"People Choice",
    "wof:placetype":"venue"
},
  "geometry": {"coordinates":[3.7334220409,51.0493202209],"type":"Point"}
}