{
  "type": "Feature",
  "properties": {
    "addr:full":"Antwerpsesteenweg 293 Brussel/bruxelles Bruxelles-Capitale 1000",
    "addr:housenumber":"293",
    "addr:postcode":"1000",
    "addr:street":"Antwerpsesteenweg;/",
    "iso:country":"BE",
    "sg:address":"Antwerpsesteenweg 293",
    "sg:city":"Brussel/bruxelles",
    "sg:classifiers":[
        {
            "category":"Cafe",
            "type":"Food & Drink"
        }
    ],
    "sg:phone":"+32 2 203 41 56",
    "sg:postcode":"1000",
    "sg:province":"Bruxelles-Capitale",
    "sg:tags":[
        "caf\u00e9s"
    ],
    "wof:name":"Chez Monique",
    "wof:placetype":"venue"
},
  "geometry": {"coordinates":[4.3584451675,50.8656768799],"type":"Point"}
}