{
  "type": "Feature",
  "properties": {
    "addr:full":"Rue De Bayarmont 6 Grez-doiceau Brabant Wallon 1390",
    "addr:housenumber":"6",
    "addr:postcode":"1390",
    "addr:street":"Rue De Bayarmont",
    "iso:country":"BE",
    "sg:address":"Rue De Bayarmont 6",
    "sg:city":"Grez-doiceau",
    "sg:classifiers":[
        {
            "category":"Shopping",
            "subcategory":"Pets & Pet Supplies",
            "type":"Retail Goods"
        }
    ],
    "sg:phone":"+32 475 46 25 56",
    "sg:postcode":"1390",
    "sg:province":"Brabant Wallon",
    "sg:tags":[
        "horseriding"
    ],
    "wof:name":"Hathy & Macheco",
    "wof:placetype":"venue"
},
  "geometry": {"coordinates":[4.6921291351,50.7225341797],"type":"Point"}
}