{
  "type": "Feature",
  "properties": {
    "addr:full":"Albert Denystraat 2ba Beersel Vlaams-Brabant 1651",
    "addr:postcode":"1651",
    "addr:street":"Denystraat;Vlaams-Brabant",
    "iso:country":"BE",
    "sg:address":"Albert Denystraat 2ba",
    "sg:city":"Beersel",
    "sg:orig_category":"Verbruikerskredietinstellingen",
    "sg:phone":"+32 2 334 95 51",
    "sg:postcode":"1651",
    "sg:province":"Vlaams-Brabant",
    "wof:name":"Pas Belgium Ltd",
    "wof:placetype":"venue"
},
  "geometry": {"coordinates":[4.2724809647,50.761013031],"type":"Point"}
}