{
  "type": "Feature",
  "properties": {
    "addr:full":"Kortrijksesteenweg 63 Sint-martens-latem Oost-Vlaanderen 9830",
    "addr:housenumber":"63",
    "addr:postcode":"9830",
    "addr:street":"Kortrijksesteenweg",
    "iso:country":"BE",
    "sg:address":"Kortrijksesteenweg 63",
    "sg:city":"Sint-martens-latem",
    "sg:orig_category":"V\u00eatements",
    "sg:phone":"+32 95768070",
    "sg:postcode":"9830",
    "sg:province":"Oost-Vlaanderen",
    "wof:name":"Moens",
    "wof:placetype":"venue"
},
  "geometry": {"coordinates":[3.6443080902,51.0128517151],"type":"Point"}
}