{
  "type": "Feature",
  "properties": {
    "iso:country":"BE",
    "sg:address":"Ambachtstraat 2b",
    "sg:city":"Torhout",
    "sg:classifiers":[
        {
            "category":"Sports & Exercise",
            "subcategory":"Gym",
            "type":"Entertainment"
        }
    ],
    "sg:phone":"+32 50 22 22 69",
    "sg:postcode":"8820",
    "sg:province":"West-Vlaanderen",
    "sg:tags":[
        "fitness"
    ],
    "wof:name":"Campo Sportivo Sport & Fitness",
    "wof:placetype":"venue"
},
  "geometry": {"coordinates":[3.1039719582,51.0763473511],"type":"Point"}
}