{
  "type": "Feature",
  "properties": {
    "addr:full":"Place De La Foire 22 Neufchateau Luxembourg 6840",
    "addr:housenumber":"22",
    "addr:postcode":"6840",
    "addr:street":"Place De La Foire",
    "iso:country":"BE",
    "sg:address":"Place De La Foire 22",
    "sg:city":"Neufchateau",
    "sg:orig_category":"Traitements param\u00e9dicaux",
    "sg:phone":"+32 61 27 95 56",
    "sg:postcode":"6840",
    "sg:province":"Luxembourg",
    "wof:name":"M.p. Jacquemart",
    "wof:placetype":"venue"
},
  "geometry": {"coordinates":[5.4336481094,49.8415145874],"type":"Point"}
}