{
  "type": "Feature",
  "properties": {
    "iso:country":"BE",
    "sg:address":"L. Van Kerckhovenstraat 66",
    "sg:city":"Puurs",
    "sg:orig_category":"Diverse organisaties and verenigingen",
    "sg:phone":"+32 3 889 69 35",
    "sg:postcode":"2870",
    "sg:province":"Antwerpen",
    "wof:name":"Chirojeugd Kalfort",
    "wof:placetype":"venue"
},
  "geometry": {"coordinates":[4.296435833,51.075340271],"type":"Point"}
}