{
  "type": "Feature",
  "properties": {
    "iso:country":"BE",
    "sg:address":"Walgoedstraat 15",
    "sg:city":"Temse",
    "sg:orig_category":"Non-Classified Establishments",
    "sg:phone":"+32 3 711 18 76",
    "sg:postcode":"9140",
    "sg:province":"Oost-Vlaanderen",
    "wof:name":"Cesar Bvba",
    "wof:placetype":"venue"
},
  "geometry": {"coordinates":[4.1902418137,51.1402435303],"type":"Point"}
}