{
  "type": "Feature",
  "properties": {
    "iso:country":"BE",
    "sg:address":"Bruggestraat 47",
    "sg:city":"Torhout",
    "sg:classifiers":[
        {
            "category":"Social Services",
            "type":"Services"
        }
    ],
    "sg:phone":"+32 50 23 11 81",
    "sg:postcode":"8820",
    "sg:province":"West-Vlaanderen",
    "sg:tags":[
        "handicapped",
        "-"
    ],
    "wof:name":"Tordale Tehuis Voor Werkenden",
    "wof:placetype":"venue"
},
  "geometry": {"coordinates":[3.1072158813,51.072063446],"type":"Point"}
}