{
  "type": "Feature",
  "properties": {
    "addr:full":"Place Sabatier 7 Charleroi (monceau-sur-sambre) Hainaut 6031",
    "addr:housenumber":"7",
    "addr:postcode":"6031",
    "addr:street":"Place Sabatier",
    "iso:country":"BE",
    "sg:address":"Place Sabatier 7",
    "sg:city":"Charleroi (monceau-sur-sambre)",
    "sg:classifiers":[
        {
            "category":"Personal",
            "subcategory":"Barber",
            "type":"Services"
        }
    ],
    "sg:phone":"+32 71 32 84 32",
    "sg:postcode":"6031",
    "sg:province":"Hainaut",
    "sg:tags":[
        "gentleman",
        "salon",
        "-",
        "hairdressing"
    ],
    "wof:name":"Salvatore",
    "wof:placetype":"venue"
},
  "geometry": {"coordinates":[4.38022995,50.4121742249],"type":"Point"}
}