{
  "type": "Feature",
  "properties": {
    "addr:full":"Rue De La Station 68 Awans Li\u00e8ge 4340",
    "addr:housenumber":"68",
    "addr:postcode":"4340",
    "addr:street":"Rue De La Station",
    "iso:country":"BE",
    "sg:address":"Rue De La Station 68",
    "sg:city":"Awans",
    "sg:classifiers":[
        {
            "category":"Shopping",
            "subcategory":"Antiques",
            "type":"Retail Goods"
        }
    ],
    "sg:phone":"+32 4 246 44 43",
    "sg:postcode":"4340",
    "sg:province":"Li\u00e8ge",
    "wof:name":"Lou-jean",
    "wof:placetype":"venue"
},
  "geometry": {"coordinates":[5.4595432281,50.6606674194],"type":"Point"}
}