{
  "type": "Feature",
  "properties": {
    "addr:full":"Koningin Elisabethlei 2 Antwerpen Antwerpen 2018",
    "addr:housenumber":"2",
    "addr:postcode":"2018",
    "addr:street":"Koningin Elisabethlei",
    "iso:country":"BE",
    "sg:address":"Koningin Elisabethlei 2",
    "sg:city":"Antwerpen",
    "sg:orig_category":"M\u00e9decins and sp\u00e9cialistes",
    "sg:phone":"+32 3 238 47 38",
    "sg:postcode":"2018",
    "sg:province":"Antwerpen",
    "wof:name":"Jan Van Damme",
    "wof:placetype":"venue"
},
  "geometry": {"coordinates":[4.4116997719,51.2006225586],"type":"Point"}
}