{
  "type": "Feature",
  "properties": {
    "addr:full":"Zevensterstraat 1b Laarne Oost-Vlaanderen 9270",
    "addr:housenumber":"1b",
    "addr:postcode":"9270",
    "addr:street":"Zevensterstraat",
    "iso:country":"BE",
    "sg:address":"Zevensterstraat 1b",
    "sg:city":"Laarne",
    "sg:classifiers":[
        {
            "category":"Wholesale",
            "subcategory":"Plants",
            "type":"Manufacturing & Wholesale Goods"
        }
    ],
    "sg:phone":"+32 9 356 73 88",
    "sg:postcode":"9270",
    "sg:province":"Oost-Vlaanderen",
    "sg:tags":[
        "whol",
        "flower",
        "-",
        "grower"
    ],
    "wof:name":"De Jaeger S",
    "wof:placetype":"venue"
},
  "geometry": {"coordinates":[3.8652379513,51.0369300842],"type":"Point"}
}