{
  "type": "Feature",
  "properties": {
    "iso:country":"BE",
    "sg:address":"Wegvoeringstraat 79",
    "sg:city":"Wetteren",
    "sg:classifiers":[
        {
            "category":"Shopping",
            "subcategory":"Clothing, Apparel, & Fashions",
            "type":"Retail Goods"
        }
    ],
    "sg:phone":"+32 9 369 07 40",
    "sg:postcode":"9230",
    "sg:province":"Oost-Vlaanderen",
    "sg:tags":[
        "textile",
        "clothing",
        "clothes"
    ],
    "wof:name":"De Bing Gebroeders Guy & Serge Fv",
    "wof:placetype":"venue"
},
  "geometry": {"coordinates":[3.9004759789,51.0103149414],"type":"Point"}
}