{
  "type": "Feature",
  "properties": {
    "addr:full":"Chazallaan 41 Schaarbeek/schaerbeek Bruxelles-Capitale 1030",
    "addr:housenumber":"41",
    "addr:postcode":"1030",
    "addr:street":"Chazallaan",
    "iso:country":"BE",
    "sg:address":"Chazallaan 41",
    "sg:city":"Schaarbeek/schaerbeek",
    "sg:orig_category":"Kapsalons",
    "sg:phone":"+32 2 735 47 57",
    "sg:postcode":"1030",
    "sg:province":"Bruxelles-Capitale",
    "wof:name":"I.d. Coiffure",
    "wof:placetype":"venue"
},
  "geometry": {"coordinates":[4.389190197,50.8546829224],"type":"Point"}
}