{
  "type": "Feature",
  "properties": {
    "addr:full":"Rue Fr\u00c8res Vanbellinghen 28 Tubize Brabant Wallon 1480",
    "addr:housenumber":"28",
    "addr:postcode":"1480",
    "addr:street":"Rue Fre\u0300Res Vanbellinghen;Wallon",
    "iso:country":"BE",
    "sg:address":"Rue Fr\u00c8res Vanbellinghen 28",
    "sg:city":"Tubize",
    "sg:orig_category":"Installation \u00e9lectrique r\u00e9sidentielle",
    "sg:phone":"+32 2 355 28 58",
    "sg:postcode":"1480",
    "sg:province":"Brabant Wallon",
    "wof:name":"Di Prata",
    "wof:placetype":"venue"
},
  "geometry": {"coordinates":[4.1934161186,50.6884155273],"type":"Point"}
}