{
  "type": "Feature",
  "properties": {
    "addr:full":"Martijn Van Torhoutstraat 64 Oudenaarde Oost-Vlaanderen 9700",
    "addr:housenumber":"64",
    "addr:postcode":"9700",
    "addr:street":"Martijn Van Torhoutstraat",
    "iso:country":"BE",
    "sg:address":"Martijn Van Torhoutstraat 64",
    "sg:city":"Oudenaarde",
    "sg:classifiers":[
        {
            "category":"Banks & Credit Unions",
            "subcategory":"Investment Brokerage",
            "type":"Services"
        }
    ],
    "sg:postcode":"9700",
    "sg:province":"Oost-Vlaanderen",
    "sg:tags":[
        "repair",
        "-",
        "installation",
        "sanitary",
        "article"
    ],
    "wof:name":"Van Gansebeke Bvba",
    "wof:placetype":"venue"
},
  "geometry": {"coordinates":[3.6233758926,50.8490371704],"type":"Point"}
}