{
  "type": "Feature",
  "properties": {
    "addr:full":"Heilig-hartplein 2 Sint-truiden Limburg 3800",
    "addr:housenumber":"2",
    "addr:postcode":"3800",
    "addr:street":"Heilig-Hartplein",
    "iso:country":"BE",
    "sg:address":"Heilig-hartplein 2",
    "sg:city":"Sint-truiden",
    "sg:classifiers":[
        {
            "category":"Shopping",
            "subcategory":"Bicycles & Sporting Goods",
            "type":"Retail Goods"
        }
    ],
    "sg:phone":"+32 11 68 36 56",
    "sg:postcode":"3800",
    "sg:province":"Limburg",
    "sg:tags":[
        "sport",
        "-"
    ],
    "wof:name":"Diax-sports Bvba",
    "wof:placetype":"venue"
},
  "geometry": {"coordinates":[5.1871972084,50.8152427673],"type":"Point"}
}