{
  "type": "Feature",
  "properties": {
    "iso:country":"BE",
    "sg:address":"Vaartstraat 43",
    "sg:city":"Gistel",
    "sg:orig_category":"Eleveurs de bovins",
    "sg:phone":"+32 59 26 60 17",
    "sg:postcode":"8470",
    "sg:province":"West-Vlaanderen",
    "wof:name":"Jozef Minne",
    "wof:placetype":"venue"
},
  "geometry": {"coordinates":[2.9622189999,51.1795387268],"type":"Point"}
}