{
  "type": "Feature",
  "properties": {
    "iso:country":"BE",
    "sg:address":"Dampoortstraat 62",
    "sg:city":"Gent",
    "sg:classifiers":[
        {
            "category":"Food & Beverages",
            "subcategory":"Cheese",
            "type":"Retail Goods"
        }
    ],
    "sg:phone":"+32 9 225 49 06",
    "sg:postcode":"9000",
    "sg:province":"Oost-Vlaanderen",
    "sg:tags":[
        "-"
    ],
    "wof:name":"Kaashuisje ('t)",
    "wof:placetype":"venue"
},
  "geometry": {"coordinates":[3.7364211082,51.0567207336],"type":"Point"}
}