{
  "type": "Feature",
  "properties": {
    "iso:country":"BE",
    "sg:address":"Tongersestraat 58",
    "sg:city":"Bilzen",
    "sg:orig_category":"Fietsen Motorfietsen Tuinbenodigdheden Watersport-, Sport- and Kampeerbenodigdheden Verhuur",
    "sg:phone":"+32 89 41 19 18",
    "sg:postcode":"3740",
    "sg:province":"Limburg",
    "wof:name":"Vanoppen",
    "wof:placetype":"venue"
},
  "geometry": {"coordinates":[5.5071678162,50.8656425476],"type":"Point"}
}