{
  "type": "Feature",
  "properties": {
    "addr:full":"Rue Bon-dieu-de-maka 4ba La Roche-en-ardenne Luxembourg 6980",
    "addr:housenumber":"4ba",
    "addr:postcode":"6980",
    "addr:street":"Rue Bon-Dieu-De-Maka",
    "iso:country":"BE",
    "sg:address":"Rue Bon-dieu-de-maka 4ba",
    "sg:city":"La Roche-en-ardenne",
    "sg:orig_category":"Schoonheidssalons",
    "sg:phone":"+32 84 41 14 14",
    "sg:postcode":"6980",
    "sg:province":"Luxembourg",
    "wof:name":"Anna Grochalak",
    "wof:placetype":"venue"
},
  "geometry": {"coordinates":[5.5769691467,50.1799163818],"type":"Point"}
}