{
  "type": "Feature",
  "properties": {
    "addr:full":"Lascheterweg 19 Eupen Li\u00e8ge 4700",
    "addr:housenumber":"19",
    "addr:postcode":"4700",
    "addr:street":"Lascheterweg",
    "iso:country":"BE",
    "sg:address":"Lascheterweg 19",
    "sg:city":"Eupen",
    "sg:orig_category":"Installatie van houten of kunststof schrijnwerk Serres and speciale beglazing",
    "sg:phone":"+32 87 76 52 72",
    "sg:postcode":"4700",
    "sg:province":"Li\u00e8ge",
    "wof:name":"Fencon",
    "wof:placetype":"venue"
},
  "geometry": {"coordinates":[6.0240478516,50.6296081543],"type":"Point"}
}