{
  "type": "Feature",
  "properties": {
    "iso:country":"BE",
    "sg:address":"Rue Du Coll\u00c8ge 1",
    "sg:city":"Eghez\u00c9e",
    "sg:orig_category":"M\u00e9decins and sp\u00e9cialistes",
    "sg:phone":"+32 81 22 44 20",
    "sg:postcode":"5310",
    "sg:province":"Namur",
    "wof:name":"Philippe Blouard",
    "wof:placetype":"venue"
},
  "geometry": {"coordinates":[4.9096999168,50.5939216614],"type":"Point"}
}