{
  "type": "Feature",
  "properties": {
    "addr:full":"Waterloose Steenweg 715 Ukkel/uccle Bruxelles-Capitale 1180",
    "addr:housenumber":"715",
    "addr:postcode":"1180",
    "addr:street":"Waterloose Steenweg;/",
    "iso:country":"BE",
    "sg:address":"Waterloose Steenweg 715",
    "sg:city":"Ukkel/uccle",
    "sg:classifiers":[
        {
            "category":"Restaurant",
            "type":"Food & Drink"
        }
    ],
    "sg:phone":"+32 2 346 19 17",
    "sg:postcode":"1180",
    "sg:province":"Bruxelles-Capitale",
    "wof:name":"Crock\u00b4in",
    "wof:placetype":"venue"
},
  "geometry": {"coordinates":[4.3669800758,50.815700531],"type":"Point"}
}