{
  "type": "Feature",
  "properties": {
    "iso:country":"BE",
    "sg:address":"Rue De La Lib\u00c9ration 13",
    "sg:city":"Charleroi",
    "sg:classifiers":[
        {
            "category":"Food & Beverages",
            "subcategory":"Fruits & Vegetables",
            "type":"Retail Goods"
        }
    ],
    "sg:phone":"+32 71 35 81 45",
    "sg:postcode":"6040",
    "sg:province":"Hainaut",
    "sg:tags":[
        "l\u00e9gumes"
    ],
    "wof:name":"Danieli Domizio",
    "wof:placetype":"venue"
},
  "geometry": {"coordinates":[4.4061841965,50.4439582825],"type":"Point"}
}