{
  "type": "Feature",
  "properties": {
    "iso:country":"BE",
    "sg:address":"Gaverse Steenweg 81",
    "sg:city":"Oosterzele (scheldewindeke)",
    "sg:classifiers":[
        {
            "category":"Building & Trades",
            "subcategory":"Landscaping Services",
            "type":"Services"
        }
    ],
    "sg:phone":"+32 9 362 33 02",
    "sg:postcode":"9860",
    "sg:province":"Oost-Vlaanderen",
    "sg:tags":[
        "gardening",
        "garden",
        "maintenance"
    ],
    "wof:name":"Hulstaert C",
    "wof:placetype":"venue"
},
  "geometry": {"coordinates":[3.7530910969,50.9328918457],"type":"Point"}
}