{
  "type": "Feature",
  "properties": {
    "iso:country":"BE",
    "sg:address":"Mechelsesteenweg 139 Box 2",
    "sg:city":"Mortsel",
    "sg:classifiers":[
        {
            "category":"Health Services",
            "subcategory":"Health Practitioner",
            "type":"Services"
        }
    ],
    "sg:phone":"+32 3 448 33 36",
    "sg:postcode":"2640",
    "sg:province":"Antwerpen",
    "sg:tags":[
        "therapist",
        "speech"
    ],
    "wof:name":"Van Roosbroeck I",
    "wof:placetype":"venue"
},
  "geometry": {"coordinates":[4.4545321465,51.1655769348],"type":"Point"}
}