{
  "type": "Feature",
  "properties": {
    "addr:full":"Rue De Froidmenteau 12 Tournai (barry - Maulde) Hainaut 7534",
    "addr:housenumber":"12",
    "addr:postcode":"7534",
    "addr:street":"Rue De Froidmenteau",
    "iso:country":"BE",
    "sg:address":"Rue De Froidmenteau 12",
    "sg:city":"Tournai (barry - Maulde)",
    "sg:classifiers":[
        {
            "category":"Health Services",
            "subcategory":"Health Practitioner",
            "type":"Services"
        }
    ],
    "sg:phone":"+32 69 54 71 38",
    "sg:postcode":"7534",
    "sg:province":"Hainaut",
    "sg:tags":[
        "physiotherapist"
    ],
    "wof:name":"Deparis C",
    "wof:placetype":"venue"
},
  "geometry": {"coordinates":[3.5407619476,50.60779953],"type":"Point"}
}