{
  "type": "Feature",
  "properties": {
    "iso:country":"BE",
    "sg:address":"Rue Du Moulin Maisse 39",
    "sg:city":"Herstal (grand)",
    "sg:orig_category":"Banken and kredietinstellingen",
    "sg:phone":"+32 4 264 12 82",
    "sg:postcode":"4040",
    "sg:province":"Li\u00e8ge",
    "wof:name":"Charlet Mireille",
    "wof:placetype":"venue"
},
  "geometry": {"coordinates":[5.6154651642,50.665561676],"type":"Point"}
}