{
  "type": "Feature",
  "properties": {
    "addr:full":"Rue Combatt. & D\u00c9port\u00c9s 50 Thuin Hainaut 6536",
    "addr:housenumber":"50",
    "addr:postcode":"6536",
    "addr:street":"Rue Combatt. & De\u0301Porte\u0301S",
    "iso:country":"BE",
    "sg:address":"Rue Combatt. & D\u00c9port\u00c9s 50",
    "sg:city":"Thuin",
    "sg:orig_category":"Epiceries",
    "sg:phone":"+32 71 53 31 23",
    "sg:postcode":"6536",
    "sg:province":"Hainaut",
    "wof:name":"Maison Werry",
    "wof:placetype":"venue"
},
  "geometry": {"coordinates":[4.3341050148,50.2965507507],"type":"Point"}
}