{
  "type": "Feature",
  "properties": {
    "addr:full":"Rue Des Ecoles 16 Tournai Hainaut 7540",
    "addr:housenumber":"16",
    "addr:postcode":"7540",
    "addr:street":"Rue Des Ecoles",
    "iso:country":"BE",
    "sg:address":"Rue Des Ecoles 16",
    "sg:city":"Tournai",
    "sg:orig_category":"Elektrische installaties voor woningen",
    "sg:phone":"+32 69 21 51 00",
    "sg:postcode":"7540",
    "sg:province":"Hainaut",
    "wof:name":"Yves Gillot",
    "wof:placetype":"venue"
},
  "geometry": {"coordinates":[3.3921470642,50.6245002747],"type":"Point"}
}