{
  "type": "Feature",
  "properties": {
    "addr:full":"Chauss\u00e9e De Viesville 4 Pont-\u00e0-celles (thim\u00e9on) Hainaut 6230",
    "addr:housenumber":"4",
    "addr:postcode":"6230",
    "addr:street":"Chausse\u0301E De Viesville;Thime\u0301On Hainaut",
    "iso:country":"BE",
    "sg:address":"Chauss\u00e9e De Viesville 4",
    "sg:city":"Pont-\u00e0-celles (thim\u00e9on)",
    "sg:classifiers":[
        {
            "category":"Retail",
            "subcategory":"Animal Services",
            "type":"Services"
        }
    ],
    "sg:phone":"+32 71 35 06 77",
    "sg:postcode":"6230",
    "sg:province":"Hainaut",
    "sg:tags":[
        "grooming",
        "-",
        "dog"
    ],
    "wof:name":"Eric",
    "wof:placetype":"venue"
},
  "geometry": {"coordinates":[4.3707361221,50.507106781],"type":"Point"}
}