{
  "type": "Feature",
  "properties": {
    "iso:country":"BE",
    "sg:address":"Rue Du Noyer 137",
    "sg:city":"Bruxelles",
    "sg:classifiers":[
        {
            "category":"Building & Trades",
            "subcategory":"Locksmith",
            "type":"Services"
        }
    ],
    "sg:phone":"+32 2 736 51 84",
    "sg:postcode":"1000",
    "sg:province":"Bruxelles-Capitale",
    "sg:tags":[
        "lock",
        "key"
    ],
    "wof:name":"Tirone Security Loch",
    "wof:placetype":"venue"
},
  "geometry": {"coordinates":[4.3896298409,50.8491783142],"type":"Point"}
}