{
  "type": "Feature",
  "properties": {
    "addr:full":"Tongersesteenweg 44 Sint-truiden Limburg 3800",
    "addr:housenumber":"44",
    "addr:postcode":"3800",
    "addr:street":"Tongersesteenweg",
    "iso:country":"BE",
    "sg:address":"Tongersesteenweg 44",
    "sg:city":"Sint-truiden",
    "sg:orig_category":"Plomberie, chauffage and installations sanitaires. Electrom\u00e9nager, t\u00e9l\u00e9visions and radios Gr",
    "sg:phone":"+32 11 68 01 12",
    "sg:postcode":"3800",
    "sg:province":"Limburg",
    "wof:name":"Fevolac",
    "wof:placetype":"venue"
},
  "geometry": {"coordinates":[5.1920838356,50.8127403259],"type":"Point"}
}