{
  "type": "Feature",
  "properties": {
    "iso:country":"BE",
    "sg:address":"Tivolilaan 41",
    "sg:city":"Mechelen",
    "sg:classifiers":[
        {
            "category":"Arena",
            "subcategory":"Sports Club",
            "type":"Entertainment"
        }
    ],
    "sg:phone":"+32 15 20 11 99",
    "sg:postcode":"2800",
    "sg:province":"Antwerpen",
    "sg:tags":[
        "de"
    ],
    "wof:name":"Tafeltennisclub Sven",
    "wof:placetype":"venue"
},
  "geometry": {"coordinates":[4.4693050385,51.0488700867],"type":"Point"}
}