{
  "type": "Feature",
  "properties": {
    "addr:full":"Rue Fran\u00c7oise Bernheim 4 Li\u00c8ge Li\u00e8ge 4031",
    "addr:housenumber":"4",
    "addr:postcode":"4031",
    "addr:street":"Rue Franc\u0327Oise Bernheim",
    "iso:country":"BE",
    "sg:address":"Rue Fran\u00c7oise Bernheim 4",
    "sg:city":"Li\u00c8ge",
    "sg:orig_category":"Enseignement maternel and primaire",
    "sg:phone":"+32 4 365 40 40",
    "sg:postcode":"4031",
    "sg:province":"Li\u00e8ge",
    "wof:name":"Ecole Primaire Libre",
    "wof:placetype":"venue"
},
  "geometry": {"coordinates":[5.5702881813,50.592010498],"type":"Point"}
}