{
  "type": "Feature",
  "properties": {
    "addr:full":"Dr\u00c8ve Du Duc 122 Watermaal-bosvoorde/watermael-boitsfort Bruxelles-Capitale 1170",
    "addr:housenumber":"122;/",
    "addr:postcode":"1170",
    "addr:street":"Dre\u0300Ve Du Duc;Watermaal-Bosvoorde",
    "iso:country":"BE",
    "sg:address":"Dr\u00c8ve Du Duc 122",
    "sg:city":"Watermaal-bosvoorde/watermael-boitsfort",
    "sg:orig_category":"Artistes ind\u00e9pendants",
    "sg:phone":"+32 2 660 93 09",
    "sg:postcode":"1170",
    "sg:province":"Bruxelles-Capitale",
    "wof:name":"Fran\u00c7oise Moens",
    "wof:placetype":"venue"
},
  "geometry": {"coordinates":[4.4100022316,50.7960700989],"type":"Point"}
}