{
  "type": "Feature",
  "properties": {
    "addr:full":"Rue De La Providence 12 Charleroi (marchienne-au-pont) Hainaut 6030",
    "addr:housenumber":"12",
    "addr:postcode":"6030",
    "addr:street":"Rue De La Providence",
    "iso:country":"BE",
    "sg:address":"Rue De La Providence 12",
    "sg:city":"Charleroi (marchienne-au-pont)",
    "sg:classifiers":[
        {
            "category":"Professional",
            "subcategory":"Testing Lab",
            "type":"Services"
        }
    ],
    "sg:phone":"+32 71 32 13 19",
    "sg:postcode":"6030",
    "sg:province":"Hainaut",
    "sg:tags":[
        "chemist"
    ],
    "wof:name":"Debelle N",
    "wof:placetype":"venue"
},
  "geometry": {"coordinates":[4.3965039253,50.4115867615],"type":"Point"}
}