{
  "type": "Feature",
  "properties": {
    "iso:country":"BE",
    "sg:address":"Graethempoort 42",
    "sg:city":"Borgloon",
    "sg:classifiers":[
        {
            "category":"Building & Trades",
            "subcategory":"Electrical",
            "type":"Services"
        }
    ],
    "sg:phone":"+32 12 67 24 86",
    "sg:postcode":"3840",
    "sg:province":"Limburg",
    "sg:tags":[
        "-",
        "electric",
        "contractor"
    ],
    "wof:name":"Croughs P",
    "wof:placetype":"venue"
},
  "geometry": {"coordinates":[5.3373708725,50.8037376404],"type":"Point"}
}