{
  "type": "Feature",
  "properties": {
    "addr:full":"Legeweg 15 Beernem West-Vlaanderen 8730",
    "addr:housenumber":"15",
    "addr:postcode":"8730",
    "addr:street":"Legeweg",
    "iso:country":"BE",
    "sg:address":"Legeweg 15",
    "sg:city":"Beernem",
    "sg:orig_category":"Woningbouw",
    "sg:phone":"+32 50 78 85 13",
    "sg:postcode":"8730",
    "sg:province":"West-Vlaanderen",
    "wof:name":"Verfaillie",
    "wof:placetype":"venue"
},
  "geometry": {"coordinates":[3.3206679821,51.1423225403],"type":"Point"}
}