{
  "type": "Feature",
  "properties": {
    "addr:full":"Jan Van Rijswijcklaan 29 Antwerpen Antwerpen 2018",
    "addr:housenumber":"29",
    "addr:postcode":"2018",
    "addr:street":"Jan Van Rijswijcklaan",
    "iso:country":"BE",
    "sg:address":"Jan Van Rijswijcklaan 29",
    "sg:city":"Antwerpen",
    "sg:orig_category":"Electrom\u00e9nager, t\u00e9l\u00e9visions and radios",
    "sg:phone":"+32 3 237 47 32",
    "sg:postcode":"2018",
    "sg:province":"Antwerpen",
    "wof:name":"Jacques Goeyvaerts",
    "wof:placetype":"venue"
},
  "geometry": {"coordinates":[4.4082951546,51.1974639893],"type":"Point"}
}