{
  "type": "Feature",
  "properties": {
    "iso:country":"BE",
    "sg:address":"Bovenheide 33",
    "sg:city":"Ravels",
    "sg:classifiers":[
        {
            "category":"Building & Trades",
            "subcategory":"Pest Control",
            "type":"Services"
        }
    ],
    "sg:phone":"+32 14 43 18 28",
    "sg:postcode":"2380",
    "sg:province":"Antwerpen",
    "sg:tags":[
        "painting",
        "contractor"
    ],
    "wof:name":"Decot Schilder Decorateur",
    "wof:placetype":"venue"
},
  "geometry": {"coordinates":[4.9902391434,51.3670692444],"type":"Point"}
}