{
  "type": "Feature",
  "properties": {
    "addr:full":"Stadhuisstraat 28 Knokke-heist West-Vlaanderen 8301",
    "addr:housenumber":"28",
    "addr:postcode":"8301",
    "addr:street":"Stadhuisstraat",
    "iso:country":"BE",
    "sg:address":"Stadhuisstraat 28",
    "sg:city":"Knokke-heist",
    "sg:orig_category":"Banques and organismes de cr\u00e9dit",
    "sg:phone":"+32 50 51 48 63",
    "sg:postcode":"8301",
    "sg:province":"West-Vlaanderen",
    "wof:name":"Bacob",
    "wof:placetype":"venue"
},
  "geometry": {"coordinates":[3.2639000416,51.3396911621],"type":"Point"}
}