{
  "type": "Feature",
  "properties": {
    "addr:full":"Lombardenvest 31 Antwerpen Antwerpen 2000",
    "addr:housenumber":"31",
    "addr:postcode":"2000",
    "addr:street":"Lombardenvest",
    "iso:country":"BE",
    "sg:address":"Lombardenvest 31",
    "sg:city":"Antwerpen",
    "sg:orig_category":"RESTAURANTS: ALIMENTATION SP\u00c9CIALIS\u00c9E",
    "sg:phone":"+32 3 213 28 88",
    "sg:postcode":"2000",
    "sg:province":"Antwerpen",
    "wof:name":"Huis Pitten & Bonen",
    "wof:placetype":"venue"
},
  "geometry": {"coordinates":[4.4016909599,51.2174873352],"type":"Point"}
}