{
  "type": "Feature",
  "properties": {
    "addr:full":"Boulevard Walter De Marvis 22 Tournai Hainaut 7500",
    "addr:housenumber":"22",
    "addr:postcode":"7500",
    "addr:street":"Boulevard Walter De Marvis",
    "iso:country":"BE",
    "sg:address":"Boulevard Walter De Marvis 22",
    "sg:city":"Tournai",
    "sg:classifiers":[
        {
            "category":"Bars & Pubs",
            "type":"Food & Drink"
        }
    ],
    "sg:phone":"+32 69 23 45 80",
    "sg:postcode":"7500",
    "sg:province":"Hainaut",
    "sg:tags":[
        "tavern"
    ],
    "wof:name":"Gambrinus (le)",
    "wof:placetype":"venue"
},
  "geometry": {"coordinates":[3.399586916,50.6073875427],"type":"Point"}
}