{
  "type": "Feature",
  "properties": {
    "iso:country":"BE",
    "sg:address":"Rue Grande 6",
    "sg:city":"Yvoir",
    "sg:orig_category":"Rusthuizen and serviceflats",
    "sg:phone":"+32 82 61 12 52",
    "sg:postcode":"5530",
    "sg:province":"Namur",
    "wof:name":"Home Plein Soleil",
    "wof:placetype":"venue"
},
  "geometry": {"coordinates":[4.8682608604,50.3492164612],"type":"Point"}
}