{
  "type": "Feature",
  "properties": {
    "iso:country":"BE",
    "sg:address":"Rue De Cerfontaine 31",
    "sg:city":"Couvin",
    "sg:orig_category":"Eleveurs de bovins",
    "sg:phone":"+32 60 31 21 73",
    "sg:postcode":"5660",
    "sg:province":"Namur",
    "wof:name":"Marc Nicolas",
    "wof:placetype":"venue"
},
  "geometry": {"coordinates":[4.4081540108,50.1192398071],"type":"Point"}
}