{
  "type": "Feature",
  "properties": {
    "iso:country":"BE",
    "sg:address":"Avenue Marcel- Marion 2",
    "sg:city":"Neupr\u00e9 (plainevaux)",
    "sg:classifiers":[
        {
            "category":"Shopping",
            "subcategory":"Hobbies, Toys, & Games",
            "type":"Retail Goods"
        }
    ],
    "sg:phone":"+32 4 371 92 47",
    "sg:postcode":"4122",
    "sg:province":"Li\u00e8ge",
    "sg:tags":[
        "computer",
        "video"
    ],
    "wof:name":"Activemedias",
    "wof:placetype":"venue"
},
  "geometry": {"coordinates":[5.4902257919,50.5417556763],"type":"Point"}
}