{
  "type": "Feature",
  "properties": {
    "iso:country":"BE",
    "sg:address":"Moelieweg 9",
    "sg:city":"Roosdaal",
    "sg:classifiers":[
        {
            "category":"Farming",
            "subcategory":"Livestock Farm",
            "type":"Manufacturing & Wholesale Goods"
        }
    ],
    "sg:phone":"+32 54 34 24 31",
    "sg:postcode":"1760",
    "sg:province":"Vlaams-Brabant",
    "sg:tags":[
        "buyer"
    ],
    "wof:name":"Desmedt M",
    "wof:placetype":"venue"
},
  "geometry": {"coordinates":[4.0744271278,50.8435707092],"type":"Point"}
}