{
  "type": "Feature",
  "properties": {
    "iso:country":"BE",
    "sg:address":"Rue Saint-donat 9-11",
    "sg:city":"Namur (saint-servais)",
    "sg:classifiers":[
        {
            "category":"Retail",
            "subcategory":"Laundry & Dry Cleaning",
            "type":"Services"
        }
    ],
    "sg:postcode":"5002",
    "sg:province":"Namur",
    "sg:tags":[
        "dyer",
        "cleaner"
    ],
    "wof:name":"Blanche Neige",
    "wof:placetype":"venue"
},
  "geometry": {"coordinates":[4.8497028351,50.4733161926],"type":"Point"}
}