{
  "type": "Feature",
  "properties": {
    "iso:country":"BE",
    "sg:address":"Koningin Fabiolalaan 57ba",
    "sg:city":"Gent",
    "sg:orig_category":"M\u00e9decins and sp\u00e9cialistes",
    "sg:phone":"+32 9 222 04 57",
    "sg:postcode":"9000",
    "sg:province":"Oost-Vlaanderen",
    "wof:name":"Christiane De Bleecker",
    "wof:placetype":"venue"
},
  "geometry": {"coordinates":[3.7035470009,51.0385856628],"type":"Point"}
}