{
  "type": "Feature",
  "properties": {
    "addr:full":"Rue De La Montagne 2 Hoeilaart Vlaams-Brabant 1560",
    "addr:housenumber":"2",
    "addr:postcode":"1560",
    "addr:street":"Rue De La Montagne",
    "iso:country":"BE",
    "sg:address":"Rue De La Montagne 2",
    "sg:city":"Hoeilaart",
    "sg:classifiers":[
        {
            "category":"Arena",
            "subcategory":"Sports Club",
            "type":"Entertainment"
        }
    ],
    "sg:phone":"+32 2 657 28 15",
    "sg:postcode":"1560",
    "sg:province":"Vlaams-Brabant",
    "sg:tags":[
        "de"
    ],
    "wof:name":"Pc Hoeilaart",
    "wof:placetype":"venue"
},
  "geometry": {"coordinates":[4.472949028,50.76820755],"type":"Point"}
}