{
  "type": "Feature",
  "properties": {
    "iso:country":"BE",
    "sg:address":"Crutzenstraat 94",
    "sg:city":"Hasselt",
    "sg:orig_category":"Instituts pour adultes moins valides",
    "sg:phone":"+32 11 25 02 33",
    "sg:postcode":"3511",
    "sg:province":"Limburg",
    "wof:name":"T Roer",
    "wof:placetype":"venue"
},
  "geometry": {"coordinates":[5.3073849678,50.9424819946],"type":"Point"}
}