{
  "type": "Feature",
  "properties": {
    "addr:full":"Tongersesteenweg 150 Sint-truiden Limburg 3800",
    "addr:housenumber":"150",
    "addr:postcode":"3800",
    "addr:street":"Tongersesteenweg",
    "iso:country":"BE",
    "sg:address":"Tongersesteenweg 150",
    "sg:city":"Sint-truiden",
    "sg:orig_category":"Salles de conf\u00e9rences and de r\u00e9ceptions. Catering and organisation de f\u00eates",
    "sg:phone":"+32 11 68 16 72",
    "sg:postcode":"3800",
    "sg:province":"Limburg",
    "wof:name":"T Veilinghuis-traiteur En Feestzaal Luc Withofs",
    "wof:placetype":"venue"
},
  "geometry": {"coordinates":[5.2026891708,50.8111763],"type":"Point"}
}