{
  "type": "Feature",
  "properties": {
    "addr:full":"Avenue Dolez 506 Bruxelles (uccle) Bruxelles-Capitale 1180",
    "addr:housenumber":"506",
    "addr:postcode":"1180",
    "addr:street":"Avenue Dolez",
    "iso:country":"BE",
    "sg:address":"Avenue Dolez 506",
    "sg:city":"Bruxelles (uccle)",
    "sg:classifiers":[
        {
            "category":"Building & Trades",
            "subcategory":"Landscaping Services",
            "type":"Services"
        }
    ],
    "sg:phone":"+32 2 374 71 71",
    "sg:postcode":"1180",
    "sg:province":"Bruxelles-Capitale",
    "sg:tags":[
        "handicraft"
    ],
    "wof:name":"Latkovic D",
    "wof:placetype":"venue"
},
  "geometry": {"coordinates":[4.354036808,50.7768211365],"type":"Point"}
}