{
  "type": "Feature",
  "properties": {
    "addr:full":"Grande Rue 18 Ottignies-louvain-la-neuve Brabant Wallon 1348",
    "addr:housenumber":"18",
    "addr:postcode":"1348",
    "addr:street":"Grande Rue",
    "iso:country":"BE",
    "sg:address":"Grande Rue 18",
    "sg:city":"Ottignies-louvain-la-neuve",
    "sg:classifiers":[
        {
            "category":"Restaurant",
            "type":"Food & Drink"
        }
    ],
    "sg:phone":"+32 10 47 33 72",
    "sg:postcode":"1348",
    "sg:province":"Brabant Wallon",
    "wof:name":"La Bobinne",
    "wof:placetype":"venue"
},
  "geometry": {"coordinates":[4.6138830185,50.6690292358],"type":"Point"}
}