{
  "type": "Feature",
  "properties": {
    "addr:full":"Nauwstraat 9 Mechelen Antwerpen 2800",
    "addr:housenumber":"9",
    "addr:postcode":"2800",
    "addr:street":"Nauwstraat",
    "iso:country":"BE",
    "sg:address":"Nauwstraat 9",
    "sg:city":"Mechelen",
    "sg:classifiers":[
        {
            "category":"Restaurant",
            "type":"Food & Drink"
        }
    ],
    "sg:phone":"+32 15 21 95 04",
    "sg:postcode":"2800",
    "sg:province":"Antwerpen",
    "sg:tags":[
        "caf\u00e9s"
    ],
    "wof:name":"Den Stillen Genieter",
    "wof:placetype":"venue"
},
  "geometry": {"coordinates":[4.4769129753,51.0262413025],"type":"Point"}
}