{
  "type": "Feature",
  "properties": {
    "addr:full":"Driehoekstraat 270 Antwerpen Antwerpen 2180",
    "addr:housenumber":"270",
    "addr:postcode":"2180",
    "addr:street":"Driehoekstraat",
    "iso:country":"BE",
    "sg:address":"Driehoekstraat 270",
    "sg:city":"Antwerpen",
    "sg:orig_category":"Equipement divers pour commerces Installation de menuiserie m\u00e9tallique. Installation de menuiserie e",
    "sg:phone":"+32 3 664 26 96",
    "sg:postcode":"2180",
    "sg:province":"Antwerpen",
    "wof:name":"Werkhuizen De Bruyn",
    "wof:placetype":"venue"
},
  "geometry": {"coordinates":[4.4182572365,51.2778625488],"type":"Point"}
}