{
  "type": "Feature",
  "properties": {
    "iso:country":"BE",
    "sg:address":"Holvenstraat 111",
    "sg:city":"Overpelt",
    "sg:orig_category":"Charpentes and couvertures",
    "sg:phone":"+32 11 66 53 76",
    "sg:postcode":"3900",
    "sg:province":"Limburg",
    "wof:name":"Dakwerken Jacobs",
    "wof:placetype":"venue"
},
  "geometry": {"coordinates":[5.3792748451,51.2070617676],"type":"Point"}
}