{
  "type": "Feature",
  "properties": {
    "addr:full":"Eindhoutseweg 27 Geel Antwerpen 2440",
    "addr:housenumber":"27",
    "addr:postcode":"2440",
    "addr:street":"Eindhoutseweg",
    "iso:country":"BE",
    "sg:address":"Eindhoutseweg 27",
    "sg:city":"Geel",
    "sg:orig_category":"Enseignement maternel and primaire. Enseignement secondaire g\u00e9n\u00e9ral",
    "sg:phone":"+32 14 86 82 58",
    "sg:postcode":"2440",
    "sg:province":"Antwerpen",
    "wof:name":"Bubao",
    "wof:placetype":"venue"
},
  "geometry": {"coordinates":[4.990170002,51.1043891907],"type":"Point"}
}