{
  "type": "Feature",
  "properties": {
    "addr:full":"Sint-pieterskaai 40 Brugge West-Vlaanderen 8000",
    "addr:housenumber":"40",
    "addr:postcode":"8000",
    "addr:street":"Sint-Pieterskaai",
    "iso:country":"BE",
    "sg:address":"Sint-pieterskaai 40",
    "sg:city":"Brugge",
    "sg:orig_category":"Editeurs de journaux. Editeurs de revues and p\u00e9riodiques. Articles divers Fab",
    "sg:phone":"+32 50 31 61 65",
    "sg:postcode":"8000",
    "sg:province":"West-Vlaanderen",
    "wof:name":"Publi Shop",
    "wof:placetype":"venue"
},
  "geometry": {"coordinates":[3.2168359756,51.222568512],"type":"Point"}
}