{
  "type": "Feature",
  "properties": {
    "addr:full":"Moorselbaan 48 Aalst Oost-Vlaanderen 9300",
    "addr:housenumber":"48",
    "addr:postcode":"9300",
    "addr:street":"Moorselbaan",
    "iso:country":"BE",
    "sg:address":"Moorselbaan 48",
    "sg:city":"Aalst",
    "sg:orig_category":"Meubles D\u00e9taillants, Am\u00e9nagement de B\u00e2timents et de Cuisines",
    "sg:phone":"+32 53 78 52 53",
    "sg:postcode":"9300",
    "sg:province":"Oost-Vlaanderen",
    "wof:name":"Juliane Hanssens",
    "wof:placetype":"venue"
},
  "geometry": {"coordinates":[4.0480780602,50.9415512085],"type":"Point"}
}