{
  "type": "Feature",
  "properties": {
    "iso:country":"BE",
    "sg:address":"Rue De Herve 613",
    "sg:city":"Li\u00e8ge 1 (grivegn\u00e9e)",
    "sg:classifiers":[
        {
            "category":"Professional",
            "subcategory":"Advertising",
            "type":"Services"
        }
    ],
    "sg:phone":"+32 4 367 43 19",
    "sg:postcode":"4030",
    "sg:province":"Li\u00e8ge",
    "sg:tags":[
        "painter"
    ],
    "wof:name":"Brayeur Sprl",
    "wof:placetype":"venue"
},
  "geometry": {"coordinates":[5.6313991547,50.6272735596],"type":"Point"}
}