{
  "type": "Feature",
  "properties": {
    "addr:full":"Diksmuidseweg 407 Ieper West-Vlaanderen 8904",
    "addr:housenumber":"407",
    "addr:postcode":"8904",
    "iso:country":"BE",
    "sg:address":"Diksmuidseweg 407",
    "sg:city":"Ieper",
    "sg:orig_category":"Krantenwinkels Kruideniers Rookartikelen",
    "sg:phone":"+32 57 42 21 67",
    "sg:postcode":"8904",
    "sg:province":"West-Vlaanderen",
    "wof:name":"Vandenberghe Anne",
    "wof:placetype":"venue"
},
  "geometry": {"coordinates":[2.8568840027,50.8953781128],"type":"Point"}
}