{
  "type": "Feature",
  "properties": {
    "iso:country":"BE",
    "sg:address":"Brugse Steenweg 75ba",
    "sg:city":"Blankenberge",
    "sg:orig_category":"D\u00e9taillants en pi\u00e8ces and accessoires de voitures. Entretien and r\u00e9parations de voitures",
    "sg:phone":"+32 50 41 93 65",
    "sg:postcode":"8370",
    "sg:province":"West-Vlaanderen",
    "wof:name":"Patrick De Paep",
    "wof:placetype":"venue"
},
  "geometry": {"coordinates":[3.14803195,51.2990913391],"type":"Point"}
}