{
  "type": "Feature",
  "properties": {
    "iso:country":"BE",
    "sg:address":"Alexandre Bertrandlaan 31",
    "sg:city":"Vorst/forest",
    "sg:orig_category":"Etalage- and showroomontwerpers",
    "sg:phone":"+32 2 569 44 71",
    "sg:postcode":"1190",
    "sg:province":"Bruxelles-Capitale",
    "wof:name":"Etalages Showindow",
    "wof:placetype":"venue"
},
  "geometry": {"coordinates":[4.3367857933,50.8179016113],"type":"Point"}
}