{
  "type": "Feature",
  "properties": {
    "addr:full":"Scherpenberg 34 Malle (westmalle) Antwerpen 2390",
    "addr:housenumber":"34",
    "addr:postcode":"2390",
    "addr:street":"Scherpenberg",
    "iso:country":"BE",
    "sg:address":"Scherpenberg 34",
    "sg:city":"Malle (westmalle)",
    "sg:classifiers":[
        {
            "category":"Real Estate",
            "subcategory":"Architect",
            "type":"Services"
        }
    ],
    "sg:phone":"+32 3 312 27 98",
    "sg:postcode":"2390",
    "sg:province":"Antwerpen",
    "wof:name":"Van Zundert G",
    "wof:placetype":"venue"
},
  "geometry": {"coordinates":[4.679374218,51.2903327942],"type":"Point"}
}