{
  "type": "Feature",
  "properties": {
    "addr:full":"Rue Jules Cerexhe 12 Verviers Li\u00e8ge 4800",
    "addr:housenumber":"12",
    "addr:postcode":"4800",
    "addr:street":"Rue Jules Cerexhe",
    "iso:country":"BE",
    "sg:address":"Rue Jules Cerexhe 12",
    "sg:city":"Verviers",
    "sg:classifiers":[
        {
            "category":"Health Services",
            "subcategory":"Health Practitioner",
            "type":"Services"
        }
    ],
    "sg:phone":"+32 478 22 56 36",
    "sg:postcode":"4800",
    "sg:province":"Li\u00e8ge",
    "sg:tags":[
        "psychologist"
    ],
    "wof:name":"Wats N",
    "wof:placetype":"venue"
},
  "geometry": {"coordinates":[5.8504562378,50.5939331055],"type":"Point"}
}