{
  "type": "Feature",
  "properties": {
    "iso:country":"BE",
    "sg:address":"Rue De La Poterie 27",
    "sg:city":"Mons",
    "sg:classifiers":[
        {
            "category":"Professional",
            "type":"Services"
        }
    ],
    "sg:phone":"+32 65 84 36 53",
    "sg:postcode":"7000",
    "sg:province":"Hainaut",
    "sg:tags":[
        "organisation",
        "de",
        "restaurants",
        "f\u00cates",
        "catering"
    ],
    "wof:name":"La Coquille Saint-jacques",
    "wof:placetype":"venue"
},
  "geometry": {"coordinates":[3.9505898952,50.4531784058],"type":"Point"}
}