{
  "type": "Feature",
  "properties": {
    "addr:full":"Avenue Kamerdelle 103 Bruxelles Bruxelles-Capitale 1180",
    "addr:housenumber":"103",
    "addr:postcode":"1180",
    "addr:street":"Avenue Kamerdelle",
    "iso:country":"BE",
    "sg:address":"Avenue Kamerdelle 103",
    "sg:city":"Bruxelles",
    "sg:classifiers":[
        {
            "category":"Wholesale",
            "subcategory":"Home Furnishings",
            "type":"Manufacturing & Wholesale Goods"
        }
    ],
    "sg:phone":"+32 2 374 69 03",
    "sg:postcode":"1180",
    "sg:province":"Bruxelles-Capitale",
    "sg:tags":[
        "house",
        "paint"
    ],
    "wof:name":"Entr. Brankaer Et Michel S.a.",
    "wof:placetype":"venue"
},
  "geometry": {"coordinates":[4.3511800766,50.7984085083],"type":"Point"}
}