{
  "type": "Feature",
  "properties": {
    "iso:country":"BE",
    "sg:address":"Brugsesteenweg 350",
    "sg:city":"Roeselare",
    "sg:orig_category":"Herstellingen and onderhoud van auto's",
    "sg:phone":"+32 51 20 24 39",
    "sg:postcode":"8800",
    "sg:province":"West-Vlaanderen",
    "wof:name":"Carglass",
    "wof:placetype":"venue"
},
  "geometry": {"coordinates":[3.1204879284,50.9671630859],"type":"Point"}
}