{
  "type": "Feature",
  "properties": {
    "iso:country":"BE",
    "sg:address":"Kerkhofstraat 63",
    "sg:city":"Leopoldsburg",
    "sg:classifiers":[
        {
            "category":"Cafe",
            "type":"Food & Drink"
        }
    ],
    "sg:phone":"+32 11 34 44 58",
    "sg:postcode":"3970",
    "sg:province":"Limburg",
    "sg:tags":[
        "caf\u00e9s"
    ],
    "wof:name":"Caf\u00c9 Cheers",
    "wof:placetype":"venue"
},
  "geometry": {"coordinates":[5.2487502098,51.1157913208],"type":"Point"}
}