{
  "type": "Feature",
  "properties": {
    "iso:country":"BE",
    "sg:address":"Milcampslaan 176",
    "sg:city":"Schaarbeek/schaerbeek",
    "sg:orig_category":"Reclamebureaus",
    "sg:phone":"+32 2 736 45 06",
    "sg:postcode":"1030",
    "sg:province":"Bruxelles-Capitale",
    "wof:name":"I.t.e.m.",
    "wof:placetype":"venue"
},
  "geometry": {"coordinates":[4.3956809044,50.8536682129],"type":"Point"}
}