{
  "type": "Feature",
  "properties": {
    "addr:full":"Mechelsestraat 18 Londerzeel Vlaams-Brabant 1840",
    "addr:housenumber":"18",
    "addr:postcode":"1840",
    "addr:street":"Mechelsestraat",
    "iso:country":"BE",
    "sg:address":"Mechelsestraat 18",
    "sg:city":"Londerzeel",
    "sg:orig_category":"Pharmaciens",
    "sg:phone":"+32 52 30 91 42",
    "sg:postcode":"1840",
    "sg:province":"Vlaams-Brabant",
    "wof:name":"A. Deneve",
    "wof:placetype":"venue"
},
  "geometry": {"coordinates":[4.3037018776,51.0035476685],"type":"Point"}
}