{
  "type": "Feature",
  "properties": {
    "addr:full":"Koning Leopoldlaan 81b Maldegem Oost-Vlaanderen 9990",
    "addr:housenumber":"81b",
    "addr:postcode":"9990",
    "addr:street":"Koning Leopoldlaan",
    "iso:country":"BE",
    "sg:address":"Koning Leopoldlaan 81b",
    "sg:city":"Maldegem",
    "sg:classifiers":[
        {
            "category":"Home & Garden",
            "subcategory":"Building Materials",
            "type":"Retail Goods"
        }
    ],
    "sg:phone":"+32 50 71 18 93",
    "sg:postcode":"9990",
    "sg:province":"Oost-Vlaanderen",
    "sg:tags":[
        "aluminium",
        "construction",
        "-"
    ],
    "wof:name":"Van Hyfte Bvba",
    "wof:placetype":"venue"
},
  "geometry": {"coordinates":[3.4647979736,51.2040176392],"type":"Point"}
}