{
  "type": "Feature",
  "properties": {
    "iso:country":"BE",
    "sg:address":"Industriestrasse 43",
    "sg:city":"Eupen",
    "sg:classifiers":[
        {
            "category":"Airport",
            "subcategory":"International",
            "type":"Transportation"
        }
    ],
    "sg:phone":"+32 87 56 03 33",
    "sg:postcode":"4700",
    "sg:province":"Li\u00e8ge",
    "sg:tags":[
        "-",
        "transport"
    ],
    "wof:name":"Cremer-ren\u00e9 Translogistic Sa",
    "wof:placetype":"venue"
},
  "geometry": {"coordinates":[6.0050377846,50.6395988464],"type":"Point"}
}