{
  "type": "Feature",
  "properties": {
    "iso:country":"BE",
    "sg:address":"Vosveld 24",
    "sg:city":"Wijnegem",
    "sg:orig_category":"Installatie van metalen schrijnwerk Serres and speciale beglazing",
    "sg:phone":"+32 3 326 29 60",
    "sg:postcode":"2110",
    "sg:province":"Antwerpen",
    "wof:name":"Veiligheidsglas",
    "wof:placetype":"venue"
},
  "geometry": {"coordinates":[4.494579792,51.2318382263],"type":"Point"}
}