{
  "type": "Feature",
  "properties": {
    "iso:country":"BE",
    "sg:address":"Kewithdreef 52",
    "sg:city":"Lanaken",
    "sg:orig_category":"Herstellingen and onderhoud van auto's",
    "sg:phone":"+32 89 72 28 79",
    "sg:postcode":"3620",
    "sg:province":"Limburg",
    "wof:name":"Car Center Eric",
    "wof:placetype":"venue"
},
  "geometry": {"coordinates":[5.6188402176,50.891998291],"type":"Point"}
}