{
  "type": "Feature",
  "properties": {
    "addr:full":"Heirbaan 253 Hamme Oost-Vlaanderen 9220",
    "addr:housenumber":"253",
    "addr:postcode":"9220",
    "addr:street":"Heirbaan",
    "iso:country":"BE",
    "sg:address":"Heirbaan 253",
    "sg:city":"Hamme",
    "sg:orig_category":"Installatie van metalen schrijnwerk",
    "sg:phone":"+32 52 47 19 56",
    "sg:postcode":"9220",
    "sg:province":"Oost-Vlaanderen",
    "wof:name":"Jozef Vlassenroot",
    "wof:placetype":"venue"
},
  "geometry": {"coordinates":[4.0982189178,51.070602417],"type":"Point"}
}