{
  "type": "Feature",
  "properties": {
    "addr:full":"Rue Morchamps 130 Seraing Li\u00e8ge 4100",
    "addr:housenumber":"130",
    "addr:postcode":"4100",
    "addr:street":"Rue Morchamps",
    "iso:country":"BE",
    "sg:address":"Rue Morchamps 130",
    "sg:city":"Seraing",
    "sg:classifiers":[
        {
            "category":"Military Area",
            "subcategory":"Air Force Base",
            "type":"Public Place"
        }
    ],
    "sg:phone":"+32 4 338 34 40",
    "sg:postcode":"4100",
    "sg:province":"Li\u00e8ge",
    "sg:tags":[
        "water",
        "treatment"
    ],
    "wof:name":"Tetras",
    "wof:placetype":"venue"
},
  "geometry": {"coordinates":[5.5134239197,50.6020202637],"type":"Point"}
}