{
  "type": "Feature",
  "properties": {
    "addr:full":"Rue Vieux Thier 111 Beyne-heusay Li\u00e8ge 4610",
    "addr:housenumber":"111",
    "addr:postcode":"4610",
    "addr:street":"Rue Vieux Thier",
    "iso:country":"BE",
    "sg:address":"Rue Vieux Thier 111",
    "sg:city":"Beyne-heusay",
    "sg:orig_category":"Dakwerken Loodgieterij, verwarming and sanitaire installaties",
    "sg:phone":"+32 4 362 73 75",
    "sg:postcode":"4610",
    "sg:province":"Li\u00e8ge",
    "wof:name":"Fe. Plastic Patrick",
    "wof:placetype":"venue"
},
  "geometry": {"coordinates":[5.6595349312,50.645450592],"type":"Point"}
}