{
  "type": "Feature",
  "properties": {
    "addr:full":"Koning Ridderdijk 49-5 Middelkerke (westende) West-Vlaanderen 8434",
    "addr:housenumber":"49-5",
    "addr:postcode":"8434",
    "addr:street":"Koning Ridderdijk",
    "iso:country":"BE",
    "sg:address":"Koning Ridderdijk 49-5",
    "sg:city":"Middelkerke (westende)",
    "sg:classifiers":[
        {
            "category":"Building & Trades",
            "subcategory":"Cleaning & Sanitation",
            "type":"Services"
        }
    ],
    "sg:phone":"+32 59 30 23 63",
    "sg:postcode":"8434",
    "sg:province":"West-Vlaanderen",
    "sg:tags":[
        "janitor"
    ],
    "wof:name":"First Class Cleaning",
    "wof:placetype":"venue"
},
  "geometry": {"coordinates":[2.7569050789,51.1488685608],"type":"Point"}
}