{
  "type": "Feature",
  "properties": {
    "addr:full":"Avenue Brugmann 537 Bruxelles (uccle) Bruxelles-Capitale 1180",
    "addr:housenumber":"537",
    "addr:postcode":"1180",
    "addr:street":"Avenue Brugmann",
    "iso:country":"BE",
    "sg:address":"Avenue Brugmann 537",
    "sg:city":"Bruxelles (uccle)",
    "sg:classifiers":[
        {
            "category":"Professional",
            "subcategory":"Management & Consulting",
            "type":"Services"
        }
    ],
    "sg:phone":"+32 2 346 03 00",
    "sg:postcode":"1180",
    "sg:province":"Bruxelles-Capitale",
    "sg:tags":[
        "consultant",
        "agency",
        "advertising"
    ],
    "wof:name":"Mind Factory",
    "wof:placetype":"venue"
},
  "geometry": {"coordinates":[4.34060812,50.8023834229],"type":"Point"}
}