{
  "type": "Feature",
  "properties": {
    "addr:full":"Brieversweg 67 Brugge West-Vlaanderen 8310",
    "addr:housenumber":"67",
    "addr:postcode":"8310",
    "addr:street":"Brieversweg",
    "iso:country":"BE",
    "sg:address":"Brieversweg 67",
    "sg:city":"Brugge",
    "sg:orig_category":"Artsen and specialisten",
    "sg:phone":"+32 50 35 46 42",
    "sg:postcode":"8310",
    "sg:province":"West-Vlaanderen",
    "wof:name":"Romain Vienne",
    "wof:placetype":"venue"
},
  "geometry": {"coordinates":[3.2616090775,51.212802887],"type":"Point"}
}