{
  "type": "Feature",
  "properties": {
    "addr:full":"Rue De L\u00b4eglise 9 Sint-genesius-rode/rhode-saint-gen\u00c8se Vlaams-Brabant 1640",
    "addr:housenumber":"9",
    "addr:postcode":"1640",
    "addr:street":"Rue De L\u00b4Eglise",
    "iso:country":"BE",
    "sg:address":"Rue De L\u00b4eglise 9",
    "sg:city":"Sint-genesius-rode/rhode-saint-gen\u00c8se",
    "sg:orig_category":"Studios photographiques",
    "sg:phone":"+32 477 87 40 72",
    "sg:postcode":"1640",
    "sg:province":"Vlaams-Brabant",
    "wof:name":"Ronald Droesbeke",
    "wof:placetype":"venue"
},
  "geometry": {"coordinates":[4.3465838432,50.7447967529],"type":"Point"}
}