{
  "type": "Feature",
  "properties": {
    "addr:full":"Rue De La Fontaine 2 Bruxelles Bruxelles-Capitale 1000",
    "addr:housenumber":"2",
    "addr:postcode":"1000",
    "addr:street":"Rue De La Fontaine",
    "iso:country":"BE",
    "sg:address":"Rue De La Fontaine 2",
    "sg:city":"Bruxelles",
    "sg:classifiers":[
        {
            "category":"Education",
            "subcategory":"University",
            "type":"Public Place"
        }
    ],
    "sg:phone":"+32 2 513 47 55",
    "sg:postcode":"1000",
    "sg:province":"Bruxelles-Capitale",
    "sg:tags":[
        "adult"
    ],
    "wof:name":"Willemsfonds - Cours De N\u00e9erlandais",
    "wof:placetype":"venue"
},
  "geometry": {"coordinates":[4.3422198296,50.8407440186],"type":"Point"}
}