{
  "type": "Feature",
  "properties": {
    "iso:country":"BE",
    "sg:address":"Place De Bas\u00c8cles 7",
    "sg:city":"Beloeil",
    "sg:orig_category":"Enseignement maternel and primaire",
    "sg:phone":"+32 69 57 54 81",
    "sg:postcode":"7971",
    "sg:province":"Hainaut",
    "wof:name":"E.f.l. St.fran\u00c7ois",
    "wof:placetype":"venue"
},
  "geometry": {"coordinates":[3.6480550766,50.5259284973],"type":"Point"}
}