{
  "type": "Feature",
  "properties": {
    "iso:country":"BE",
    "sg:address":"De Keyserlei 34",
    "sg:city":"Antwerpen",
    "sg:orig_category":"Parfumeries",
    "sg:phone":"+32 3 234 07 01",
    "sg:postcode":"2018",
    "sg:province":"Antwerpen",
    "wof:name":"Planet Parfum",
    "wof:placetype":"venue"
},
  "geometry": {"coordinates":[4.417953968,51.2174797058],"type":"Point"}
}