{
  "type": "Feature",
  "properties": {
    "addr:full":"Ooststraat 33 Lo-reninge West-Vlaanderen 8647",
    "addr:housenumber":"33",
    "addr:postcode":"8647",
    "addr:street":"Ooststraat",
    "iso:country":"BE",
    "sg:address":"Ooststraat 33",
    "sg:city":"Lo-reninge",
    "sg:orig_category":"Apotheken",
    "sg:phone":"+32 58 28 83 65",
    "sg:postcode":"8647",
    "sg:province":"West-Vlaanderen",
    "wof:name":"Tardimav",
    "wof:placetype":"venue"
},
  "geometry": {"coordinates":[2.7514150143,50.9812545776],"type":"Point"}
}