{
  "type": "Feature",
  "properties": {
    "addr:full":"Chauss\u00e9e De Charleroi 735 Fleurus Hainaut 6220",
    "addr:housenumber":"735",
    "addr:postcode":"6220",
    "addr:street":"Chausse\u0301E De Charleroi",
    "iso:country":"BE",
    "sg:address":"Chauss\u00e9e De Charleroi 735",
    "sg:city":"Fleurus",
    "sg:classifiers":[
        {
            "category":"Building & Trades",
            "subcategory":"Landscaping Services",
            "type":"Services"
        }
    ],
    "sg:phone":"+32 71 80 08 29",
    "sg:postcode":"6220",
    "sg:province":"Hainaut",
    "sg:tags":[
        "nurseryman"
    ],
    "wof:name":"Philmaflore Sc",
    "wof:placetype":"venue"
},
  "geometry": {"coordinates":[4.5383300781,50.4679107666],"type":"Point"}
}