{
  "type": "Feature",
  "properties": {
    "iso:country":"BE",
    "sg:address":"Ingberthoeveweg 3a",
    "sg:city":"Aartselaar",
    "sg:orig_category":"Kantoormateriaal Verhuur kantoormateriaal Verhuur televisie- and audiovisuele apparatuur",
    "sg:phone":"+32 3 322 00 22",
    "sg:postcode":"2630",
    "sg:province":"Antwerpen",
    "wof:name":"Eye-d",
    "wof:placetype":"venue"
},
  "geometry": {"coordinates":[4.3969092369,51.1482505798],"type":"Point"}
}