{
  "type": "Feature",
  "properties": {
    "addr:full":"Oude Geelsebaan 114 Laakdal Antwerpen 2431",
    "addr:housenumber":"114",
    "addr:postcode":"2431",
    "addr:street":"Oude Geelsebaan",
    "iso:country":"BE",
    "sg:address":"Oude Geelsebaan 114",
    "sg:city":"Laakdal",
    "sg:classifiers":[
        {
            "category":"Cafe",
            "type":"Food & Drink"
        }
    ],
    "sg:phone":"+32 14 84 09 34",
    "sg:postcode":"2431",
    "sg:province":"Antwerpen",
    "sg:tags":[
        "caf\u00e9s"
    ],
    "wof:name":"Arlette Vandepaer",
    "wof:placetype":"venue"
},
  "geometry": {"coordinates":[4.9624810219,51.0738334656],"type":"Point"}
}