{
  "type": "Feature",
  "properties": {
    "addr:full":"Lidostraat 107 Leopoldsburg Limburg 3970",
    "addr:housenumber":"107",
    "addr:postcode":"3970",
    "addr:street":"Lidostraat",
    "iso:country":"BE",
    "sg:address":"Lidostraat 107",
    "sg:city":"Leopoldsburg",
    "sg:classifiers":[
        {
            "category":"Personal",
            "subcategory":"Nail Salon",
            "type":"Services"
        }
    ],
    "sg:phone":"+32 11 34 86 67",
    "sg:postcode":"3970",
    "sg:province":"Limburg",
    "sg:tags":[
        "pedicure"
    ],
    "wof:name":"Steurs E",
    "wof:placetype":"venue"
},
  "geometry": {"coordinates":[5.2469558716,51.131980896],"type":"Point"}
}