{
  "type": "Feature",
  "properties": {
    "iso:country":"BE",
    "sg:address":"Strijlandstraat 53ba",
    "sg:city":"Gooik",
    "sg:orig_category":"Plomberie, chauffage and installations sanitaires",
    "sg:phone":"+32 54 56 84 54",
    "sg:postcode":"1755",
    "sg:province":"Vlaams-Brabant",
    "wof:name":"Geert Kestens",
    "wof:placetype":"venue"
},
  "geometry": {"coordinates":[4.080329895,50.7920188904],"type":"Point"}
}