{
  "type": "Feature",
  "properties": {
    "addr:full":"Rue Des Sports 23 Box 8 Charleroi Hainaut 6000",
    "addr:housenumber":"23;8",
    "addr:postcode":"6000",
    "addr:street":"Rue Des Sports;Box;Hainaut",
    "iso:country":"BE",
    "sg:address":"Rue Des Sports 23 Box 8",
    "sg:city":"Charleroi",
    "sg:classifiers":[
        {
            "category":"Professional",
            "subcategory":"Accounting & Tax Preparation",
            "type":"Services"
        }
    ],
    "sg:phone":"+32 71 30 12 90",
    "sg:postcode":"6000",
    "sg:province":"Hainaut",
    "sg:tags":[
        "bookkeeper"
    ],
    "wof:name":"Gecfi Sprl",
    "wof:placetype":"venue"
},
  "geometry": {"coordinates":[4.4548587799,50.4140892029],"type":"Point"}
}