{
  "type": "Feature",
  "properties": {
    "iso:country":"BE",
    "sg:address":"Geraardsbergsestraat 5",
    "sg:city":"Lierde",
    "sg:orig_category":"Huishoudapparaten, televisies and radio's MEUBELONTWERP AND -INSTALLATIE Meubelzaken, woning- and ke",
    "sg:phone":"+32 54 41 11 74",
    "sg:postcode":"9570",
    "sg:province":"Oost-Vlaanderen",
    "wof:name":"Ignace De Pyper",
    "wof:placetype":"venue"
},
  "geometry": {"coordinates":[3.8463969231,50.783531189],"type":"Point"}
}