{
  "type": "Feature",
  "properties": {
    "iso:country":"BE",
    "sg:address":"Voortstraat 15",
    "sg:city":"Balen",
    "sg:classifiers":[
        {
            "category":"Airport",
            "subcategory":"International",
            "type":"Transportation"
        }
    ],
    "sg:phone":"+32 14 81 64 01",
    "sg:postcode":"2490",
    "sg:province":"Antwerpen",
    "sg:tags":[
        "-",
        "transport"
    ],
    "wof:name":"Transport Helsen",
    "wof:placetype":"venue"
},
  "geometry": {"coordinates":[5.1643128395,51.1970405579],"type":"Point"}
}