{
  "type": "Feature",
  "properties": {
    "addr:full":"Moleneindeweg 65 Zonhoven Limburg 3520",
    "addr:housenumber":"65",
    "addr:postcode":"3520",
    "addr:street":"Moleneindeweg",
    "iso:country":"BE",
    "sg:address":"Moleneindeweg 65",
    "sg:city":"Zonhoven",
    "sg:orig_category":"Articles de jardin. Pi\u00e8ces and accessoires de v\u00e9hicules automobiles Gr",
    "sg:phone":"+32 11 82 10 65",
    "sg:postcode":"3520",
    "sg:province":"Limburg",
    "wof:name":"Dalemans Industries",
    "wof:placetype":"venue"
},
  "geometry": {"coordinates":[5.4280557632,50.9807281494],"type":"Point"}
}