{
  "type": "Feature",
  "properties": {
    "addr:full":"Gustaaf Callierlaan 106 Gent Oost-Vlaanderen 9000",
    "addr:housenumber":"106",
    "addr:postcode":"9000",
    "addr:street":"Gustaaf Callierlaan;Oost-Vlaanderen",
    "iso:country":"BE",
    "sg:address":"Gustaaf Callierlaan 106",
    "sg:city":"Gent",
    "sg:orig_category":"Notarissen",
    "sg:phone":"+32 9 223 42 57",
    "sg:postcode":"9000",
    "sg:province":"Oost-Vlaanderen",
    "wof:name":"E. De Staercke",
    "wof:placetype":"venue"
},
  "geometry": {"coordinates":[3.7342600822,51.0410308838],"type":"Point"}
}