{
  "type": "Feature",
  "properties": {
    "iso:country":"BE",
    "sg:address":"Ledegemsestraat 103",
    "sg:city":"Wevelgem",
    "sg:orig_category":"Architectes",
    "sg:phone":"+32 56 50 06 75",
    "sg:postcode":"8560",
    "sg:province":"West-Vlaanderen",
    "wof:name":"Barbara Ostyn",
    "wof:placetype":"venue"
},
  "geometry": {"coordinates":[3.1494750977,50.8463401794],"type":"Point"}
}