{
  "type": "Feature",
  "properties": {
    "addr:full":"Warandelaan 124 Vilvoorde Vlaams-Brabant 1800",
    "addr:housenumber":"124",
    "addr:postcode":"1800",
    "addr:street":"Warandelaan",
    "iso:country":"BE",
    "sg:address":"Warandelaan 124",
    "sg:city":"Vilvoorde",
    "sg:orig_category":"Charpentes and couvertures",
    "sg:phone":"+32 2 267 86 18",
    "sg:postcode":"1800",
    "sg:province":"Vlaams-Brabant",
    "wof:name":"De Couvreur A. & Co",
    "wof:placetype":"venue"
},
  "geometry": {"coordinates":[4.3684201241,50.9020500183],"type":"Point"}
}