{
  "type": "Feature",
  "properties": {
    "iso:country":"BE",
    "sg:address":"Prekelindenlaan 55",
    "sg:city":"Sint-lambrechts-woluwe/woluwe-saint-lambert",
    "sg:orig_category":"Diverse bouwafwerking and reiniging Loodgieterij, verwarming and sanitaire installaties",
    "sg:phone":"+32 2 742 19 23",
    "sg:postcode":"1200",
    "sg:province":"Bruxelles-Capitale",
    "wof:name":"Serge Skrzypek",
    "wof:placetype":"venue"
},
  "geometry": {"coordinates":[4.4096698761,50.8410072327],"type":"Point"}
}