{
  "type": "Feature",
  "properties": {
    "addr:full":"Riemstraat 66 Schilde Antwerpen 2970",
    "addr:housenumber":"66",
    "addr:postcode":"2970",
    "addr:street":"Riemstraat",
    "iso:country":"BE",
    "sg:address":"Riemstraat 66",
    "sg:city":"Schilde",
    "sg:orig_category":"Non-Classified Establishments",
    "sg:phone":"+32 3 385 44 80",
    "sg:postcode":"2970",
    "sg:province":"Antwerpen",
    "wof:name":"Ago Cards & Gifts",
    "wof:placetype":"venue"
},
  "geometry": {"coordinates":[4.6000127792,51.259262085],"type":"Point"}
}