{
  "type": "Feature",
  "properties": {
    "iso:country":"BE",
    "sg:address":"Avenue De Norv\u00e8ge 4",
    "sg:city":"Malmedy",
    "sg:orig_category":"Non-Classified Establishments",
    "sg:phone":"+32 80 33 01 04",
    "sg:postcode":"4960",
    "sg:province":"Li\u00e8ge",
    "wof:name":"Cubiglace",
    "wof:placetype":"venue"
},
  "geometry": {"coordinates":[6.0048398972,50.4160308838],"type":"Point"}
}