{
  "type": "Feature",
  "properties": {
    "addr:full":"Grand Route 560-562 Beyne-heusay Li\u00e8ge 4610",
    "addr:postcode":"560-562;4610",
    "addr:street":"Grand Route",
    "iso:country":"BE",
    "sg:address":"Grand Route 560-562",
    "sg:city":"Beyne-heusay",
    "sg:orig_category":"Herstellingen and onderhoud van auto's Onderdelen and accessoires voor auto's",
    "sg:phone":"+32 4 355 18 55",
    "sg:postcode":"4610",
    "sg:province":"Li\u00e8ge",
    "wof:name":"Vantage",
    "wof:placetype":"venue"
},
  "geometry": {"coordinates":[5.664285183,50.6182556152],"type":"Point"}
}