{
  "type": "Feature",
  "properties": {
    "addr:full":"Oudenaardsesteenweg 478 Mere Oost-Vlaanderen 9420",
    "addr:housenumber":"478",
    "addr:postcode":"9420",
    "addr:street":"Oudenaardsesteenweg",
    "iso:country":"BE",
    "sg:address":"Oudenaardsesteenweg 478",
    "sg:city":"Mere",
    "sg:orig_category":"Royal Canin. Animaux domestiques and accessoires",
    "sg:phone":"+32 53 80 02 62",
    "sg:postcode":"9420",
    "sg:province":"Oost-Vlaanderen",
    "wof:name":"Garden Wizard",
    "wof:placetype":"venue"
},
  "geometry": {"coordinates":[3.9459469318,50.9219360352],"type":"Point"}
}