{
  "type": "Feature",
  "properties": {
    "addr:full":"Meulebeeksestraat 24 Izegem West-Vlaanderen 8870",
    "addr:housenumber":"24",
    "addr:postcode":"8870",
    "addr:street":"Meulebeeksestraat",
    "iso:country":"BE",
    "sg:address":"Meulebeeksestraat 24",
    "sg:city":"Izegem",
    "sg:orig_category":"Varkenskwekers",
    "sg:phone":"+32 51 30 10 74",
    "sg:postcode":"8870",
    "sg:province":"West-Vlaanderen",
    "wof:name":"Jean Semetier",
    "wof:placetype":"venue"
},
  "geometry": {"coordinates":[3.2175140381,50.945526123],"type":"Point"}
}