{
  "type": "Feature",
  "properties": {
    "iso:country":"BE",
    "sg:address":"Rue De Carignan 10",
    "sg:city":"Florenville",
    "sg:classifiers":[
        {
            "category":"Building & Trades",
            "subcategory":"Electrical",
            "type":"Services"
        }
    ],
    "sg:phone":"+32 61 27 07 40",
    "sg:postcode":"6820",
    "sg:province":"Luxembourg",
    "sg:tags":[
        "-",
        "electric",
        "contractor"
    ],
    "wof:name":"Electric Home",
    "wof:placetype":"venue"
},
  "geometry": {"coordinates":[5.3030929565,49.6970672607],"type":"Point"}
}