{
  "type": "Feature",
  "properties": {
    "addr:full":"Oude Aarschotsebaan 62 Booischot Antwerpen 2221",
    "addr:housenumber":"62",
    "addr:postcode":"2221",
    "addr:street":"Oude Aarschotsebaan",
    "iso:country":"BE",
    "sg:address":"Oude Aarschotsebaan 62",
    "sg:city":"Booischot",
    "sg:orig_category":"Verhuur diversen",
    "sg:phone":"+32 15 22 24 55",
    "sg:postcode":"2221",
    "sg:province":"Antwerpen",
    "wof:name":"Mt-rent",
    "wof:placetype":"venue"
},
  "geometry": {"coordinates":[4.7774300575,51.047164917],"type":"Point"}
}