{
  "type": "Feature",
  "properties": {
    "iso:country":"BE",
    "sg:address":"Ooststatiestraat 159",
    "sg:city":"Kontich",
    "sg:classifiers":[
        {
            "category":"Retail",
            "subcategory":"Veterinary Services",
            "type":"Services"
        }
    ],
    "sg:phone":"+32 3 457 45 07",
    "sg:postcode":"2550",
    "sg:province":"Antwerpen",
    "sg:tags":[
        "veterinarian"
    ],
    "wof:name":"Verhoeven D",
    "wof:placetype":"venue"
},
  "geometry": {"coordinates":[4.4561347961,51.1349449158],"type":"Point"}
}