{
  "type": "Feature",
  "properties": {
    "iso:country":"BE",
    "sg:address":"Galerie Du Douaire 1b",
    "sg:city":"Ottignies-louvain-la-neuve (ottignies)",
    "sg:classifiers":[
        {
            "category":"Shopping",
            "subcategory":"Clothing, Apparel, & Fashions",
            "type":"Retail Goods"
        }
    ],
    "sg:phone":"+32 10 41 00 90",
    "sg:postcode":"1340",
    "sg:province":"Brabant Wallon",
    "sg:tags":[
        "clothing",
        "-",
        "gentleman"
    ],
    "wof:name":"Cricket & Co",
    "wof:placetype":"venue"
},
  "geometry": {"coordinates":[4.567553997,50.6661262512],"type":"Point"}
}