{
  "type": "Feature",
  "properties": {
    "iso:country":"BE",
    "sg:address":"5-7 Rue Charles Parente",
    "sg:city":"Bruxelles",
    "sg:classifiers":[
        {
            "category":"Shopping",
            "subcategory":"Hobbies, Toys, & Games",
            "type":"Retail Goods"
        }
    ],
    "sg:phone":"+32 2 524 11 37",
    "sg:postcode":"1070",
    "sg:province":"Bruxelles-Capitale",
    "sg:tags":[
        "product",
        "miscellaneous",
        "entertainment"
    ],
    "wof:name":"Unibox Games Sa",
    "wof:placetype":"venue"
},
  "geometry": {"coordinates":[4.3302397728,50.8338432312],"type":"Point"}
}