{
  "type": "Feature",
  "properties": {
    "addr:full":"Fonteinstraat 68 Oud-heverlee Vlaams-Brabant 3050",
    "addr:housenumber":"68",
    "addr:postcode":"3050",
    "addr:street":"Fonteinstraat",
    "iso:country":"BE",
    "sg:address":"Fonteinstraat 68",
    "sg:city":"Oud-heverlee",
    "sg:orig_category":"Meubles D\u00e9taillants, Am\u00e9nagement de B\u00e2timents et de Cuisines",
    "sg:phone":"+32 16 40 72 22",
    "sg:postcode":"3050",
    "sg:province":"Vlaams-Brabant",
    "wof:name":"Fa. Hemelboom",
    "wof:placetype":"venue"
},
  "geometry": {"coordinates":[4.6671361923,50.8456382751],"type":"Point"}
}