{
  "type": "Feature",
  "properties": {
    "iso:country":"BE",
    "sg:address":"Sint-sebastiaanstraat 9",
    "sg:city":"Assenede (bassevelde)",
    "sg:classifiers":[
        {
            "category":"Building & Trades",
            "subcategory":"Construction",
            "type":"Services"
        }
    ],
    "sg:phone":"+32 9 373 79 01",
    "sg:postcode":"9968",
    "sg:province":"Oost-Vlaanderen",
    "sg:tags":[
        "stucco",
        "contractor"
    ],
    "wof:name":"Van Hoecke Christ",
    "wof:placetype":"venue"
},
  "geometry": {"coordinates":[3.6809420586,51.2336273193],"type":"Point"}
}