{
  "type": "Feature",
  "properties": {
    "addr:full":"Della Faillelaan 26 Antwerpen Antwerpen 2020",
    "addr:housenumber":"26",
    "addr:postcode":"2020",
    "addr:street":"Della Faillelaan",
    "iso:country":"BE",
    "sg:address":"Della Faillelaan 26",
    "sg:city":"Antwerpen",
    "sg:classifiers":[
        {
            "category":"Professional",
            "subcategory":"Management & Consulting",
            "type":"Services"
        }
    ],
    "sg:phone":"+32 3 830 58 99",
    "sg:postcode":"2020",
    "sg:province":"Antwerpen",
    "sg:tags":[
        "consultant"
    ],
    "wof:name":"Marc Roels Consulting And Trading Bvba",
    "wof:placetype":"venue"
},
  "geometry": {"coordinates":[4.3990221024,51.1816368103],"type":"Point"}
}