{
  "type": "Feature",
  "properties": {
    "addr:full":"Autobaan 2 Zedelgem (loppem) West-Vlaanderen 8210",
    "addr:housenumber":"2",
    "addr:postcode":"8210",
    "addr:street":"Autobaan",
    "iso:country":"BE",
    "sg:address":"Autobaan 2",
    "sg:city":"Zedelgem (loppem)",
    "sg:classifiers":[
        {
            "category":"Farming",
            "subcategory":"Livestock Farm",
            "type":"Manufacturing & Wholesale Goods"
        }
    ],
    "sg:phone":"+32 50 82 27 13",
    "sg:postcode":"8210",
    "sg:province":"West-Vlaanderen",
    "sg:tags":[
        "buyer"
    ],
    "wof:name":"Vande Kerckhove E",
    "wof:placetype":"venue"
},
  "geometry": {"coordinates":[3.1458399296,51.1376457214],"type":"Point"}
}