{
  "type": "Feature",
  "properties": {
    "addr:full":"St-janstr 1 St. Jan Oost-Vlaanderen 9982",
    "addr:housenumber":"1",
    "addr:postcode":"9982",
    "addr:street":"St-Janstr",
    "iso:country":"BE",
    "sg:address":"St-janstr 1",
    "sg:city":"St. Jan",
    "sg:classifiers":[
        {
            "category":"Banks & Credit Unions",
            "subcategory":"Bank",
            "type":"Services"
        }
    ],
    "sg:phone":"+32 52 79 82 22",
    "sg:postcode":"9982",
    "sg:province":"Oost-Vlaanderen",
    "wof:name":"Gemeentekrediet",
    "wof:placetype":"venue"
},
  "geometry": {"coordinates":[3.6019248962,51.2459182739],"type":"Point"}
}