{
  "type": "Feature",
  "properties": {
    "iso:country":"BE",
    "sg:address":"Gauwelstraat 60",
    "sg:city":"Zwevegem (heestert)",
    "sg:classifiers":[
        {
            "category":"Structure",
            "subcategory":"Office Building",
            "type":"Public Place"
        }
    ],
    "sg:phone":"+32 496 60 69 09",
    "sg:postcode":"8551",
    "sg:province":"West-Vlaanderen",
    "sg:tags":[
        "-",
        "type",
        "door",
        "sliding",
        "overhead"
    ],
    "wof:name":"De Waele J",
    "wof:placetype":"venue"
},
  "geometry": {"coordinates":[3.4015829563,50.7800941467],"type":"Point"}
}