{
  "type": "Feature",
  "properties": {
    "iso:country":"BE",
    "sg:address":"Hoevenweg 4",
    "sg:city":"Balen",
    "sg:orig_category":"Artsen and specialisten",
    "sg:phone":"+32 14 81 44 58",
    "sg:postcode":"2490",
    "sg:province":"Antwerpen",
    "wof:name":"Ruddy Swinnen",
    "wof:placetype":"venue"
},
  "geometry": {"coordinates":[5.1748781204,51.1906471252],"type":"Point"}
}