{
  "type": "Feature",
  "properties": {
    "addr:full":"Vaart Noord 17a Aalter (bellem) Oost-Vlaanderen 9881",
    "addr:housenumber":"17a",
    "addr:postcode":"9881",
    "addr:street":"Vaart Noord",
    "iso:country":"BE",
    "sg:address":"Vaart Noord 17a",
    "sg:city":"Aalter (bellem)",
    "sg:classifiers":[
        {
            "category":"Professional",
            "subcategory":"Accounting & Tax Preparation",
            "type":"Services"
        }
    ],
    "sg:phone":"+32 9 374 49 01",
    "sg:postcode":"9881",
    "sg:province":"Oost-Vlaanderen",
    "sg:tags":[
        "accountant"
    ],
    "wof:name":"De Clercq A",
    "wof:placetype":"venue"
},
  "geometry": {"coordinates":[3.5024120808,51.0960998535],"type":"Point"}
}