{
  "type": "Feature",
  "properties": {
    "addr:full":"Vicus Pontrave 49 Waasmunster Oost-Vlaanderen 9250",
    "addr:housenumber":"49",
    "addr:postcode":"9250",
    "iso:country":"BE",
    "sg:address":"Vicus Pontrave 49",
    "sg:city":"Waasmunster",
    "sg:orig_category":"Persagentschappen",
    "sg:phone":"+32 52 46 37 49",
    "sg:postcode":"9250",
    "sg:province":"Oost-Vlaanderen",
    "wof:name":"William Meerschaut",
    "wof:placetype":"venue"
},
  "geometry": {"coordinates":[4.07376194,51.1086235046],"type":"Point"}
}