{
  "type": "Feature",
  "properties": {
    "addr:full":"Brusselsestraat 24 Leuven Vlaams-Brabant 3000",
    "addr:housenumber":"24",
    "addr:postcode":"3000",
    "addr:street":"Brusselsestraat",
    "iso:country":"BE",
    "sg:address":"Brusselsestraat 24",
    "sg:city":"Leuven",
    "sg:classifiers":[
        {
            "category":"Professional",
            "subcategory":"Computer Services",
            "type":"Services"
        }
    ],
    "sg:phone":"+32 16 20 67 29",
    "sg:postcode":"3000",
    "sg:province":"Vlaams-Brabant",
    "sg:tags":[
        "-",
        "processing",
        "data",
        "software"
    ],
    "wof:name":"Mr10 Consulting Bvba",
    "wof:placetype":"venue"
},
  "geometry": {"coordinates":[4.6993308067,50.8796691895],"type":"Point"}
}