{
  "type": "Feature",
  "properties": {
    "iso:country":"BE",
    "sg:address":"Markt 13",
    "sg:city":"Dessel",
    "sg:classifiers":[
        {
            "category":"Banks & Credit Unions",
            "subcategory":"Investment Brokerage",
            "type":"Services"
        }
    ],
    "sg:phone":"+32 14 37 57 17",
    "sg:postcode":"2480",
    "sg:province":"Antwerpen",
    "sg:tags":[
        "repair",
        "-",
        "installation",
        "sanitary",
        "article"
    ],
    "wof:name":"Robeyns Bvba",
    "wof:placetype":"venue"
},
  "geometry": {"coordinates":[5.1176080704,51.2368812561],"type":"Point"}
}