{
  "type": "Feature",
  "properties": {
    "iso:country":"BE",
    "sg:address":"Route De Renipont 66",
    "sg:city":"Lasne",
    "sg:classifiers":[
        {
            "category":"Professional",
            "subcategory":"Credit Reporting & Collection",
            "type":"Services"
        }
    ],
    "sg:phone":"+32 2 652 18 01",
    "sg:postcode":"1380",
    "sg:province":"Brabant Wallon",
    "sg:tags":[
        "head-hunting",
        "consulting"
    ],
    "wof:name":"Search Europe S.p.r.l.",
    "wof:placetype":"venue"
},
  "geometry": {"coordinates":[4.4960207939,50.7018127441],"type":"Point"}
}