{
  "type": "Feature",
  "properties": {
    "addr:full":"Nobelstr 2 Hamont Limburg 3930",
    "addr:housenumber":"2",
    "addr:postcode":"3930",
    "addr:street":"Nobelstr",
    "iso:country":"BE",
    "sg:address":"Nobelstr 2",
    "sg:city":"Hamont",
    "sg:classifiers":[
        {
            "category":"Government",
            "subcategory":"Department Of Motor Vehicles",
            "type":"Public Place"
        }
    ],
    "sg:phone":"+32 11 44 03 00",
    "sg:postcode":"3930",
    "sg:province":"Limburg",
    "sg:tags":[
        "equipment",
        "industrial",
        "transport",
        "motor-cars"
    ],
    "wof:name":"Inalfa Nv",
    "wof:placetype":"venue"
},
  "geometry": {"coordinates":[5.5211210251,51.2614097595],"type":"Point"}
}