{
  "type": "Feature",
  "properties": {
    "iso:country":"BE",
    "sg:address":"Rue Des Ponts 1",
    "sg:city":"Oupeye (haccourt)",
    "sg:classifiers":[
        {
            "category":"Shopping",
            "subcategory":"Shoes",
            "type":"Retail Goods"
        }
    ],
    "sg:phone":"+32 4 379 15 93",
    "sg:postcode":"4684",
    "sg:province":"Li\u00e8ge",
    "sg:tags":[
        "slipper",
        "-"
    ],
    "wof:name":"Frere Chaussures",
    "wof:placetype":"venue"
},
  "geometry": {"coordinates":[5.6669411659,50.7332382202],"type":"Point"}
}