{
  "type": "Feature",
  "properties": {
    "addr:full":"Le Haut De La Chetteur 2 Florenville Luxembourg 6820",
    "addr:housenumber":"2",
    "addr:postcode":"6820",
    "iso:country":"BE",
    "sg:address":"Le Haut De La Chetteur 2",
    "sg:city":"Florenville",
    "sg:classifiers":[
        {
            "category":"Retail",
            "subcategory":"Veterinary Services",
            "type":"Services"
        }
    ],
    "sg:phone":"+32 61 31 12 26",
    "sg:postcode":"6820",
    "sg:province":"Luxembourg",
    "sg:tags":[
        "veterinarian"
    ],
    "wof:name":"Godefroid M",
    "wof:placetype":"venue"
},
  "geometry": {"coordinates":[5.3273849487,49.6875190735],"type":"Point"}
}