{
  "type": "Feature",
  "properties": {
    "addr:full":"Elsum 78 Geel Antwerpen 2440",
    "addr:housenumber":"78",
    "addr:postcode":"2440",
    "addr:street":"Elsum",
    "iso:country":"BE",
    "sg:address":"Elsum 78",
    "sg:city":"Geel",
    "sg:orig_category":"Electrom\u00e9nager, t\u00e9l\u00e9visions and radios",
    "sg:phone":"+32 14 58 98 76",
    "sg:postcode":"2440",
    "sg:province":"Antwerpen",
    "wof:name":"Gino Peeters",
    "wof:placetype":"venue"
},
  "geometry": {"coordinates":[4.9785809517,51.1639633179],"type":"Point"}
}