{
  "type": "Feature",
  "properties": {
    "addr:full":"Gaston Deruyverstraat 15 Sint-pieters-leeuw Vlaams-Brabant 1600",
    "addr:housenumber":"15",
    "addr:postcode":"1600",
    "addr:street":"Deruyverstraat",
    "iso:country":"BE",
    "sg:address":"Gaston Deruyverstraat 15",
    "sg:city":"Sint-pieters-leeuw",
    "sg:orig_category":"Herstelling aan huis van huishoudartikelen Loodgieterij, verwarming and sanitaire installaties",
    "sg:phone":"+32 2 377 26 74",
    "sg:postcode":"1600",
    "sg:province":"Vlaams-Brabant",
    "wof:name":"Inter-sanit",
    "wof:placetype":"venue"
},
  "geometry": {"coordinates":[4.2842969894,50.8040466309],"type":"Point"}
}