{
  "type": "Feature",
  "properties": {
    "addr:full":"Rue Chemin Vert 5 Fontaine-l'ev\u00eaque (leernes) Hainaut 6142",
    "addr:housenumber":"5",
    "addr:postcode":"6142",
    "addr:street":"Rue Chemin Vert;Hainaut",
    "iso:country":"BE",
    "sg:address":"Rue Chemin Vert 5",
    "sg:city":"Fontaine-l'ev\u00eaque (leernes)",
    "sg:classifiers":[
        {
            "category":"Health Services",
            "subcategory":"Nursing And Care Facility",
            "type":"Services"
        }
    ],
    "sg:phone":"+32 71 52 70 83",
    "sg:postcode":"6142",
    "sg:province":"Hainaut",
    "sg:tags":[
        "home"
    ],
    "wof:name":"Chalmagne Ch",
    "wof:placetype":"venue"
},
  "geometry": {"coordinates":[-111.9644622803,46.2507972717],"type":"Point"}
}