{
  "type": "Feature",
  "properties": {
    "iso:country":"BE",
    "sg:address":"Rue Am\u00c9ricaine 28",
    "sg:city":"Marche-en-famenne",
    "sg:orig_category":"Algemeen secundair onderwijs Technisch and beroeps secundair onderwijs",
    "sg:phone":"+32 84 32 01 40",
    "sg:postcode":"6900",
    "sg:province":"Luxembourg",
    "wof:name":"Institut Laurent",
    "wof:placetype":"venue"
},
  "geometry": {"coordinates":[5.347659111,50.2283325195],"type":"Point"}
}