{
  "type": "Feature",
  "properties": {
    "iso:country":"BE",
    "sg:address":"Lavendelweg 22",
    "sg:city":"Herentals",
    "sg:orig_category":"Epiceries",
    "sg:phone":"+32 14 21 84 51",
    "sg:postcode":"2200",
    "sg:province":"Antwerpen",
    "wof:name":"Olivia De Ridder",
    "wof:placetype":"venue"
},
  "geometry": {"coordinates":[4.8514080048,51.1955490112],"type":"Point"}
}