{
  "type": "Feature",
  "properties": {
    "iso:country":"BE",
    "sg:address":"Chemin Du Bois Des Dames 1",
    "sg:city":"La Hulpe",
    "sg:classifiers":[
        {
            "category":"Professional",
            "subcategory":"Management & Consulting",
            "type":"Services"
        }
    ],
    "sg:phone":"+32 2 652 33 93",
    "sg:postcode":"1310",
    "sg:province":"Brabant Wallon",
    "sg:tags":[
        "consultant",
        "agency",
        "advertising"
    ],
    "wof:name":"Davantage",
    "wof:placetype":"venue"
},
  "geometry": {"coordinates":[4.474407196,50.7276954651],"type":"Point"}
}