{
  "type": "Feature",
  "properties": {
    "addr:full":"Brusselsesteenweg 433 Asse Vlaams-Brabant 1731",
    "addr:housenumber":"433",
    "addr:postcode":"1731",
    "addr:street":"Brusselsesteenweg",
    "iso:country":"BE",
    "sg:address":"Brusselsesteenweg 433",
    "sg:city":"Asse",
    "sg:classifiers":[
        {
            "category":"Restaurant",
            "type":"Food & Drink"
        }
    ],
    "sg:phone":"+32 2 466 97 26",
    "sg:postcode":"1731",
    "sg:province":"Vlaams-Brabant",
    "wof:name":"Angelus",
    "wof:placetype":"venue"
},
  "geometry": {"coordinates":[4.277577877,50.8814468384],"type":"Point"}
}