{
  "type": "Feature",
  "properties": {
    "addr:full":"Mijlenmeersstraat 62 Anderlecht/anderlecht Bruxelles-Capitale 1070",
    "addr:housenumber":"62",
    "addr:postcode":"1070",
    "addr:street":"Mijlenmeersstraat",
    "iso:country":"BE",
    "sg:address":"Mijlenmeersstraat 62",
    "sg:city":"Anderlecht/anderlecht",
    "sg:orig_category":"Groententeelt",
    "sg:phone":"+32 2 569 27 42",
    "sg:postcode":"1070",
    "sg:province":"Bruxelles-Capitale",
    "wof:name":"Vanderpooten-anckaert",
    "wof:placetype":"venue"
},
  "geometry": {"coordinates":[4.2633910179,50.8121032715],"type":"Point"}
}