{
  "type": "Feature",
  "properties": {
    "addr:full":"Overwinningstraat 46 Willebroek Antwerpen 2830",
    "addr:housenumber":"46",
    "addr:postcode":"2830",
    "addr:street":"Overwinningstraat",
    "iso:country":"BE",
    "sg:address":"Overwinningstraat 46",
    "sg:city":"Willebroek",
    "sg:classifiers":[
        {
            "category":"Shopping",
            "subcategory":"Beauty & Cosmetics",
            "type":"Retail Goods"
        }
    ],
    "sg:phone":"+32 3 866 03 16",
    "sg:postcode":"2830",
    "sg:province":"Antwerpen",
    "sg:tags":[
        "-",
        "perfumery"
    ],
    "wof:name":"Baccaris",
    "wof:placetype":"venue"
},
  "geometry": {"coordinates":[4.3596301079,51.0587387085],"type":"Point"}
}