{
  "type": "Feature",
  "properties": {
    "iso:country":"BE",
    "sg:address":"Vandammestraat 9b",
    "sg:city":"Blankenberge",
    "sg:orig_category":"Afvalwaterverwerking and ontstoppingsdiensten Loodgieterij, verwarming and sanitaire installaties",
    "sg:phone":"+32 75911075",
    "sg:postcode":"8370",
    "sg:province":"West-Vlaanderen",
    "wof:name":"Algemene Ontstoppingswerken",
    "wof:placetype":"venue"
},
  "geometry": {"coordinates":[3.1404349804,51.3053131104],"type":"Point"}
}