{
  "type": "Feature",
  "properties": {
    "iso:country":"BE",
    "sg:address":"Rue Victor Dejardin 22",
    "sg:city":"Mons",
    "sg:orig_category":"Avocats and conseillers juridiques",
    "sg:phone":"+32 65 34 06 40",
    "sg:postcode":"7000",
    "sg:province":"Hainaut",
    "wof:name":"Anne Musimu",
    "wof:placetype":"venue"
},
  "geometry": {"coordinates":[3.9599719048,50.4480171204],"type":"Point"}
}