{
  "type": "Feature",
  "properties": {
    "addr:full":"De Castrodreef 1 Sint-niklaas Oost-Vlaanderen 9100",
    "addr:housenumber":"1",
    "addr:postcode":"9100",
    "addr:street":"Sint-Niklaas Oost-Vlaanderen",
    "iso:country":"BE",
    "sg:address":"De Castrodreef 1",
    "sg:city":"Sint-niklaas",
    "sg:orig_category":"Verplichte sociale verzekeringen",
    "sg:phone":"+32 3 760 38 11",
    "sg:postcode":"9100",
    "sg:province":"Oost-Vlaanderen",
    "wof:name":"Christelijke Mutualiteit",
    "wof:placetype":"venue"
},
  "geometry": {"coordinates":[4.1387910843,51.1625366211],"type":"Point"}
}