{
  "type": "Feature",
  "properties": {
    "iso:country":"BE",
    "sg:address":"Assesteenweg 117",
    "sg:city":"Ternat",
    "sg:classifiers":[
        {
            "category":"Banks & Credit Unions",
            "subcategory":"Bureau De Change",
            "type":"Services"
        }
    ],
    "sg:phone":"+32 2 581 09 32",
    "sg:postcode":"1740",
    "sg:province":"Vlaams-Brabant",
    "sg:tags":[
        "-",
        "household",
        "gas"
    ],
    "wof:name":"Federatie Butaan Propaan",
    "wof:placetype":"venue"
},
  "geometry": {"coordinates":[4.1677031517,50.8755073547],"type":"Point"}
}