{
  "type": "Feature",
  "properties": {
    "addr:full":"Place Charles Ii Charleroi Hainaut 6000",
    "addr:postcode":"6000",
    "addr:street":"Place Charles Ii;Hainaut",
    "iso:country":"BE",
    "sg:address":"Place Charles Ii",
    "sg:city":"Charleroi",
    "sg:classifiers":[
        {
            "category":"Museum",
            "type":"Entertainment"
        }
    ],
    "sg:phone":"+32 71 86 11 36",
    "sg:postcode":"6000",
    "sg:province":"Hainaut",
    "wof:name":"Beaux-arts (mus\u00e9e Des)",
    "wof:placetype":"venue"
},
  "geometry": {"coordinates":[4.4446649551,50.411895752],"type":"Point"}
}