{
  "type": "Feature",
  "properties": {
    "iso:country":"BE",
    "sg:address":"Hof Van Tichelen 35",
    "sg:city":"Antwerpen",
    "sg:classifiers":[
        {
            "category":"Banks & Credit Unions",
            "subcategory":"Investment Brokerage",
            "type":"Services"
        }
    ],
    "sg:phone":"+32 3 828 24 22",
    "sg:postcode":"2020",
    "sg:province":"Antwerpen",
    "sg:tags":[
        "repair",
        "-",
        "installation",
        "sanitary",
        "article"
    ],
    "wof:name":"Janssens J",
    "wof:placetype":"venue"
},
  "geometry": {"coordinates":[4.3856959343,51.1822853088],"type":"Point"}
}