{
  "type": "Feature",
  "properties": {
    "addr:full":"Rue Emile Vandervelde 19 Le Roeulx Hainaut 7070",
    "addr:housenumber":"19",
    "addr:postcode":"7070",
    "addr:street":"Rue Emile Vandervelde",
    "iso:country":"BE",
    "sg:address":"Rue Emile Vandervelde 19",
    "sg:city":"Le Roeulx",
    "sg:orig_category":"Bloemen and planten",
    "sg:phone":"+32 64 67 61 61",
    "sg:postcode":"7070",
    "sg:province":"Hainaut",
    "wof:name":"New Capucine",
    "wof:placetype":"venue"
},
  "geometry": {"coordinates":[4.1094408035,50.5034637451],"type":"Point"}
}