{
  "type": "Feature",
  "properties": {
    "iso:country":"BE",
    "sg:address":"Rue Du Coq 20",
    "sg:city":"Amay",
    "sg:classifiers":[
        {
            "category":"Cafe",
            "type":"Food & Drink"
        }
    ],
    "sg:phone":"+32 85 31 29 44",
    "sg:postcode":"4540",
    "sg:province":"Li\u00e8ge",
    "sg:tags":[
        "caf\u00e9s"
    ],
    "wof:name":"Marina Legros",
    "wof:placetype":"venue"
},
  "geometry": {"coordinates":[5.3083372116,50.5516853333],"type":"Point"}
}