{
  "type": "Feature",
  "properties": {
    "addr:full":"Tulpenstraat 1 Riemst Limburg 3770",
    "addr:housenumber":"1",
    "addr:postcode":"3770",
    "addr:street":"Tulpenstraat",
    "iso:country":"BE",
    "sg:address":"Tulpenstraat 1",
    "sg:city":"Riemst",
    "sg:orig_category":"Travaux de pl\u00e2trage",
    "sg:phone":"+32 12 45 44 57",
    "sg:postcode":"3770",
    "sg:province":"Limburg",
    "wof:name":"Petrus Schuffelers",
    "wof:placetype":"venue"
},
  "geometry": {"coordinates":[5.6078820229,50.8094978333],"type":"Point"}
}