{
  "type": "Feature",
  "properties": {
    "iso:country":"BE",
    "sg:address":"Bootsveld 7",
    "sg:city":"Riemst",
    "sg:classifiers":[
        {
            "category":"Manufacturing",
            "subcategory":"Rubber & Plastics",
            "type":"Manufacturing & Wholesale Goods"
        }
    ],
    "sg:phone":"+32 12 45 57 40",
    "sg:postcode":"3770",
    "sg:province":"Limburg",
    "sg:tags":[
        "packaging",
        "material",
        "-"
    ],
    "wof:name":"Industrial Electrical Contracting Nv",
    "wof:placetype":"venue"
},
  "geometry": {"coordinates":[5.6013278961,50.8170433044],"type":"Point"}
}