{
  "type": "Feature",
  "properties": {
    "iso:country":"BE",
    "sg:address":"Nekke 17b",
    "sg:city":"Zomergem",
    "sg:orig_category":"Herstellingen and onderhoud van auto's",
    "sg:phone":"+32 9 372 95 23",
    "sg:postcode":"9930",
    "sg:province":"Oost-Vlaanderen",
    "wof:name":"Garage Van Volsem",
    "wof:placetype":"venue"
},
  "geometry": {"coordinates":[3.5436389446,51.1152420044],"type":"Point"}
}