{
  "type": "Feature",
  "properties": {
    "iso:country":"BE",
    "sg:address":"Rue Cr\u00c9tias 99",
    "sg:city":"Dinant",
    "sg:classifiers":[
        {
            "category":"Restaurant",
            "type":"Food & Drink"
        }
    ],
    "sg:phone":"+32 82 74 42 11",
    "sg:postcode":"5500",
    "sg:province":"Namur",
    "wof:name":"Les Cr\u00c9tias",
    "wof:placetype":"venue"
},
  "geometry": {"coordinates":[4.8879718781,50.2033653259],"type":"Point"}
}