{
  "type": "Feature",
  "properties": {
    "addr:full":"Herentalse Steenweg 124 Grobbendonk Antwerpen 2280",
    "addr:housenumber":"124",
    "addr:postcode":"2280",
    "addr:street":"Herentalse Steenweg",
    "iso:country":"BE",
    "sg:address":"Herentalse Steenweg 124",
    "sg:city":"Grobbendonk",
    "sg:classifiers":[
        {
            "category":"Bars & Pubs",
            "type":"Food & Drink"
        }
    ],
    "sg:phone":"+32 14 21 67 20",
    "sg:postcode":"2280",
    "sg:province":"Antwerpen",
    "wof:name":"De Kijkuit",
    "wof:placetype":"venue"
},
  "geometry": {"coordinates":[4.776309967,51.1763801575],"type":"Point"}
}