{
  "type": "Feature",
  "properties": {
    "iso:country":"BE",
    "sg:address":"Rue De Saint-hubert 19",
    "sg:city":"Rochefort",
    "sg:classifiers":[
        {
            "category":"Bars & Pubs",
            "subcategory":"Hookah Bar",
            "type":"Food & Drink"
        }
    ],
    "sg:phone":"+32 84 21 12 43",
    "sg:postcode":"5580",
    "sg:province":"Namur",
    "sg:tags":[
        "product",
        "livestock",
        "related",
        "grain",
        "cereal",
        "agriculture"
    ],
    "wof:name":"Denis Sa",
    "wof:placetype":"venue"
},
  "geometry": {"coordinates":[5.2209877968,50.1430053711],"type":"Point"}
}