{
  "type": "Feature",
  "properties": {
    "iso:country":"BE",
    "sg:address":"Rue Du Vivier 78",
    "sg:city":"Virton",
    "sg:orig_category":"Onderdelen and accessoires voor auto's",
    "sg:phone":"+32 63 58 27 07",
    "sg:postcode":"6761",
    "sg:province":"Luxembourg",
    "wof:name":"Dabbour Pneus Services",
    "wof:placetype":"venue"
},
  "geometry": {"coordinates":[5.5631828308,49.5579185486],"type":"Point"}
}