{
  "type": "Feature",
  "properties": {
    "addr:full":"Baan Naar Bree 33 Peer Limburg 3990",
    "addr:housenumber":"33",
    "addr:postcode":"3990",
    "addr:street":"Baan Naar Bree",
    "iso:country":"BE",
    "sg:address":"Baan Naar Bree 33",
    "sg:city":"Peer",
    "sg:classifiers":[
        {
            "category":"Autos & Motor Vehicles",
            "subcategory":"Fuel & Gas Station",
            "type":"Retail Goods"
        }
    ],
    "sg:phone":"+32 11 63 16 79",
    "sg:postcode":"3990",
    "sg:province":"Limburg",
    "wof:name":"Maes Schreurs",
    "wof:placetype":"venue"
},
  "geometry": {"coordinates":[5.4631819725,51.131980896],"type":"Point"}
}