{
  "type": "Feature",
  "properties": {
    "iso:country":"BE",
    "sg:address":"Mont-saint-martin 45",
    "sg:city":"Li\u00e8ge 1",
    "sg:classifiers":[
        {
            "category":"Education",
            "subcategory":"University",
            "type":"Public Place"
        }
    ],
    "sg:phone":"+32 4 223 42 74",
    "sg:postcode":"4000",
    "sg:province":"Li\u00e8ge",
    "sg:tags":[
        "higher"
    ],
    "wof:name":"Isell-st-martin",
    "wof:placetype":"venue"
},
  "geometry": {"coordinates":[5.5652070045,50.6442832947],"type":"Point"}
}