{
  "type": "Feature",
  "properties": {
    "addr:full":"Rue Des Trois Piliers 40 Namur Namur 5002",
    "addr:housenumber":"40",
    "addr:postcode":"5002",
    "addr:street":"Rue Des Trois Piliers",
    "iso:country":"BE",
    "sg:address":"Rue Des Trois Piliers 40",
    "sg:city":"Namur",
    "sg:classifiers":[
        {
            "category":"Arena",
            "subcategory":"Sports Club",
            "type":"Entertainment"
        }
    ],
    "sg:phone":"+32 81 73 37 83",
    "sg:postcode":"5002",
    "sg:province":"Namur",
    "sg:tags":[
        "de"
    ],
    "wof:name":"Mieux-etre - St.marc",
    "wof:placetype":"venue"
},
  "geometry": {"coordinates":[4.8462319374,50.4782791138],"type":"Point"}
}