{
  "type": "Feature",
  "properties": {
    "iso:country":"BE",
    "sg:address":"Rue De La Pirire 1",
    "sg:city":"Marche-en-famenne",
    "sg:orig_category":"Fabrication and montage de mobilier",
    "sg:phone":"+32 78 71 73 46",
    "sg:postcode":"6900",
    "sg:province":"Luxembourg",
    "wof:name":"Sanidel Sa",
    "wof:placetype":"venue"
},
  "geometry": {"coordinates":[5.338570118,50.2225418091],"type":"Point"}
}