{
  "type": "Feature",
  "properties": {
    "addr:full":"Bassinstraat 12 Torhout West-Vlaanderen 8820",
    "addr:housenumber":"12",
    "addr:postcode":"8820",
    "addr:street":"Bassinstraat",
    "iso:country":"BE",
    "sg:address":"Bassinstraat 12",
    "sg:city":"Torhout",
    "sg:classifiers":[
        {
            "category":"Communications",
            "type":"Services"
        }
    ],
    "sg:phone":"+32 50 21 53 51",
    "sg:postcode":"8820",
    "sg:province":"West-Vlaanderen",
    "sg:tags":[
        "translator"
    ],
    "wof:name":"Leuridan B",
    "wof:placetype":"venue"
},
  "geometry": {"coordinates":[3.104460001,51.0632247925],"type":"Point"}
}