{
  "type": "Feature",
  "properties": {
    "iso:country":"BE",
    "sg:address":"Schaapsdreef 8b",
    "sg:city":"Wingene",
    "sg:classifiers":[
        {
            "category":"Building & Trades",
            "subcategory":"Construction",
            "type":"Services"
        }
    ],
    "sg:phone":"+32 71 41 18 79",
    "sg:postcode":"8750",
    "sg:province":"West-Vlaanderen",
    "sg:tags":[
        "ceiling"
    ],
    "wof:name":"Oppenbrouwer Michel",
    "wof:placetype":"venue"
},
  "geometry": {"coordinates":[4.4805011749,50.4259109497],"type":"Point"}
}