{
  "type": "Feature",
  "properties": {
    "iso:country":"BE",
    "sg:address":"Val. De Saedeleerstr. 16",
    "sg:city":"Aalst",
    "sg:orig_category":"Brood, gebak and snoepgoed",
    "sg:phone":"+32 53 77 47 92",
    "sg:postcode":"9300",
    "sg:province":"Oost-Vlaanderen",
    "wof:name":"Willy Roelandt",
    "wof:placetype":"venue"
},
  "geometry": {"coordinates":[4.0332651138,50.9446792603],"type":"Point"}
}