{
  "type": "Feature",
  "properties": {
    "addr:full":"Naamsestraat 5 Sint-truiden Limburg 3800",
    "addr:housenumber":"5",
    "addr:postcode":"3800",
    "addr:street":"Naamsestraat",
    "iso:country":"BE",
    "sg:address":"Naamsestraat 5",
    "sg:city":"Sint-truiden",
    "sg:orig_category":"Musea and historische gebouwen",
    "sg:phone":"+32 11 68 23 56",
    "sg:postcode":"3800",
    "sg:province":"Limburg",
    "wof:name":"Kantmuseum",
    "wof:placetype":"venue"
},
  "geometry": {"coordinates":[5.1888999939,50.8130912781],"type":"Point"}
}