{
  "type": "Feature",
  "properties": {
    "iso:country":"BE",
    "sg:address":"Edelinckstraat 25",
    "sg:city":"Antwerpen",
    "sg:classifiers":[
        {
            "category":"Health Services",
            "subcategory":"Doctor",
            "type":"Services"
        }
    ],
    "sg:phone":"+32 3 226 24 30",
    "sg:postcode":"2018",
    "sg:province":"Antwerpen",
    "sg:tags":[
        "medicinephysicians",
        "surgeon"
    ],
    "wof:name":"De Mahieu C",
    "wof:placetype":"venue"
},
  "geometry": {"coordinates":[4.4104089737,51.2097663879],"type":"Point"}
}