{
  "type": "Feature",
  "properties": {
    "addr:full":"Rue Du Vivier 1 Marche-en-famenne Luxembourg 6900",
    "addr:housenumber":"1",
    "addr:postcode":"6900",
    "addr:street":"Rue Du Vivier",
    "iso:country":"BE",
    "sg:address":"Rue Du Vivier 1",
    "sg:city":"Marche-en-famenne",
    "sg:classifiers":[
        {
            "category":"Health Services",
            "subcategory":"Health Practitioner",
            "type":"Services"
        }
    ],
    "sg:phone":"+32 83 63 39 62",
    "sg:postcode":"6900",
    "sg:province":"Luxembourg",
    "sg:tags":[
        "psychologist"
    ],
    "wof:name":"Pitz I",
    "wof:placetype":"venue"
},
  "geometry": {"coordinates":[5.3292279243,50.2291297913],"type":"Point"}
}