{
  "type": "Feature",
  "properties": {
    "addr:full":"Kortrijksesteenweg 37 Wingene West-Vlaanderen 8750",
    "addr:housenumber":"37",
    "addr:postcode":"8750",
    "addr:street":"Kortrijksesteenweg",
    "iso:country":"BE",
    "sg:address":"Kortrijksesteenweg 37",
    "sg:city":"Wingene",
    "sg:classifiers":[
        {
            "category":"Restaurant",
            "type":"Food & Drink"
        }
    ],
    "sg:phone":"+32 51 61 30 38",
    "sg:postcode":"8750",
    "sg:province":"West-Vlaanderen",
    "wof:name":"Restaurant Amadeus",
    "wof:placetype":"venue"
},
  "geometry": {"coordinates":[3.2303190231,51.028465271],"type":"Point"}
}