{
  "type": "Feature",
  "properties": {
    "addr:full":"Chauss\u00e9e Brunehaut 325 Juprelle (villers-saint-sim\u00e9on) Li\u00e8ge 4453",
    "addr:housenumber":"325",
    "addr:postcode":"4453",
    "addr:street":"Chausse\u0301E Brunehaut;Villers-Saint-Sime\u0301On",
    "iso:country":"BE",
    "sg:address":"Chauss\u00e9e Brunehaut 325",
    "sg:city":"Juprelle (villers-saint-sim\u00e9on)",
    "sg:classifiers":[
        {
            "category":"Real Estate",
            "subcategory":"Architect",
            "type":"Services"
        }
    ],
    "sg:phone":"+32 4 278 63 22",
    "sg:postcode":"4453",
    "sg:province":"Li\u00e8ge",
    "wof:name":"Tromme F",
    "wof:placetype":"venue"
},
  "geometry": {"coordinates":[5.5409731865,50.7097930908],"type":"Point"}
}