{
  "type": "Feature",
  "properties": {
    "addr:full":"Crenaertstraat 10 Grimbergen Vlaams-Brabant 1851",
    "addr:housenumber":"10",
    "addr:postcode":"1851",
    "addr:street":"Crenaertstraat",
    "iso:country":"BE",
    "sg:address":"Crenaertstraat 10",
    "sg:city":"Grimbergen",
    "sg:orig_category":"Animations diverses",
    "sg:phone":"+32 2 269 59 49",
    "sg:postcode":"1851",
    "sg:province":"Vlaams-Brabant",
    "wof:name":"Van Brabant",
    "wof:placetype":"venue"
},
  "geometry": {"coordinates":[4.3661680222,50.9660491943],"type":"Point"}
}