{
  "type": "Feature",
  "properties": {
    "iso:country":"BE",
    "sg:address":"Broodstraat 7",
    "sg:city":"Oudenaarde",
    "sg:orig_category":"V\u00eatements pour Dames. V\u00eatements pour Hommes",
    "sg:phone":"+32 55 31 18 41",
    "sg:postcode":"9700",
    "sg:province":"Oost-Vlaanderen",
    "wof:name":"Boetiek New Dc",
    "wof:placetype":"venue"
},
  "geometry": {"coordinates":[3.60542202,50.842754364],"type":"Point"}
}