{
  "type": "Feature",
  "properties": {
    "iso:country":"BE",
    "sg:address":"Oud Arenberg 57",
    "sg:city":"Beveren (kieldrecht)",
    "sg:classifiers":[
        {
            "category":"Home & Garden",
            "subcategory":"Garden Supply",
            "type":"Retail Goods"
        }
    ],
    "sg:phone":"+32 3 773 40 13",
    "sg:postcode":"9130",
    "sg:province":"Oost-Vlaanderen",
    "sg:tags":[
        "machine",
        "agricultural",
        "-"
    ],
    "wof:name":"Ann\u00e9-van Dijck",
    "wof:placetype":"venue"
},
  "geometry": {"coordinates":[4.1906280518,51.2888259888],"type":"Point"}
}