{
  "type": "Feature",
  "properties": {
    "addr:full":"Sportln 20 Overijse Vlaams-Brabant 3090",
    "addr:housenumber":"20",
    "addr:postcode":"3090",
    "addr:street":"Sportln",
    "iso:country":"BE",
    "sg:address":"Sportln 20",
    "sg:city":"Overijse",
    "sg:orig_category":"Gestion de portefeuilles and fortunes, conseils en placements",
    "sg:phone":"+32 2 688 11 22",
    "sg:postcode":"3090",
    "sg:province":"Vlaams-Brabant",
    "wof:name":"I.t.c.s",
    "wof:placetype":"venue"
},
  "geometry": {"coordinates":[4.537779808,50.7731971741],"type":"Point"}
}