{
  "type": "Feature",
  "properties": {
    "iso:country":"BE",
    "sg:address":"Middelburgstraat 98",
    "sg:city":"Watermaal-bosvoorde/watermael-boitsfort",
    "sg:orig_category":"Verplichte sociale verzekeringen",
    "sg:phone":"+32 2 660 68 02",
    "sg:postcode":"1170",
    "sg:province":"Bruxelles-Capitale",
    "wof:name":"Mutualit\u00c9 Socialiste",
    "wof:placetype":"venue"
},
  "geometry": {"coordinates":[4.4184389114,50.7947883606],"type":"Point"}
}