{
  "type": "Feature",
  "properties": {
    "addr:full":"Wouters Lefebvreplein 32 Willebroek (blaasveld) Antwerpen 2830",
    "addr:housenumber":"32",
    "addr:postcode":"2830",
    "iso:country":"BE",
    "sg:address":"Wouters Lefebvreplein 32",
    "sg:city":"Willebroek (blaasveld)",
    "sg:classifiers":[
        {
            "category":"Health Services",
            "subcategory":"Dentist",
            "type":"Services"
        }
    ],
    "sg:phone":"+32 3 886 47 50",
    "sg:postcode":"2830",
    "sg:province":"Antwerpen",
    "wof:name":"Scheers Elke",
    "wof:placetype":"venue"
},
  "geometry": {"coordinates":[4.3726348877,51.0556602478],"type":"Point"}
}