{
  "type": "Feature",
  "properties": {
    "addr:full":"Gruuthusestraat 2 Waregem (beveren-leie) West-Vlaanderen 8791",
    "addr:housenumber":"2",
    "addr:postcode":"8791",
    "addr:street":"Gruuthusestraat",
    "iso:country":"BE",
    "sg:address":"Gruuthusestraat 2",
    "sg:city":"Waregem (beveren-leie)",
    "sg:classifiers":[
        {
            "category":"Shopping",
            "subcategory":"Jewelry",
            "type":"Retail Goods"
        }
    ],
    "sg:phone":"+32 56 70 50 79",
    "sg:postcode":"8791",
    "sg:province":"West-Vlaanderen",
    "sg:tags":[
        "jeweller",
        "-"
    ],
    "wof:name":"Debeuf M",
    "wof:placetype":"venue"
},
  "geometry": {"coordinates":[3.3368220329,50.874256134],"type":"Point"}
}