{
  "type": "Feature",
  "properties": {
    "addr:full":"3790 Voeren Limburg 3790",
    "addr:postcode":"3790 voeren;3790",
    "iso:country":"BE",
    "sg:address":"3790",
    "sg:city":"Voeren",
    "sg:orig_category":"Pharmaciens",
    "sg:phone":"+32 900 10 500",
    "sg:postcode":"3790",
    "sg:province":"Limburg",
    "wof:name":"Pharmacies De Garde",
    "wof:placetype":"venue"
},
  "geometry": {"coordinates":[5.829870224,50.7409210205],"type":"Point"}
}