{
  "type": "Feature",
  "properties": {
    "addr:full":"Rue De La Hurtrie 58 P\u00e9ruwelz Hainaut 7600",
    "addr:housenumber":"58",
    "addr:postcode":"7600",
    "addr:street":"Rue De La Hurtrie",
    "iso:country":"BE",
    "sg:address":"Rue De La Hurtrie 58",
    "sg:city":"P\u00e9ruwelz",
    "sg:classifiers":[
        {
            "category":"Education",
            "subcategory":"School",
            "type":"Public Place"
        }
    ],
    "sg:phone":"+32 69 77 65 12",
    "sg:postcode":"7600",
    "sg:province":"Hainaut",
    "sg:tags":[
        "-",
        "private"
    ],
    "wof:name":"Carabistouille Asbl",
    "wof:placetype":"venue"
},
  "geometry": {"coordinates":[3.6136260033,50.5154190063],"type":"Point"}
}