{
  "type": "Feature",
  "properties": {
    "iso:country":"BE",
    "sg:address":"Lauwestraat 51",
    "sg:city":"Wevelgem",
    "sg:orig_category":"Alimentation sp\u00e9cialis\u00e9e",
    "sg:phone":"+32 56 41 44 78",
    "sg:postcode":"8560",
    "sg:province":"West-Vlaanderen",
    "wof:name":"Leven & Gezondheid",
    "wof:placetype":"venue"
},
  "geometry": {"coordinates":[3.1864790916,50.8069343567],"type":"Point"}
}