{
  "type": "Feature",
  "properties": {
    "addr:full":"Waterloose Steenweg 198 Sint-genesius-rode/rhode-saint-genese Vlaams-Brabant 1640",
    "addr:housenumber":"198",
    "addr:postcode":"1640",
    "addr:street":"Waterloose Steenweg",
    "iso:country":"BE",
    "sg:address":"Waterloose Steenweg 198",
    "sg:city":"Sint-genesius-rode/rhode-saint-genese",
    "sg:orig_category":"Diverse opleidingen and onderwijs",
    "sg:phone":"+32 2 359 96 90",
    "sg:postcode":"1640",
    "sg:province":"Vlaams-Brabant",
    "wof:name":"Krauthammer International/krauthammer Eric",
    "wof:placetype":"venue"
},
  "geometry": {"coordinates":[4.3945999146,50.7476196289],"type":"Point"}
}