{
  "type": "Feature",
  "properties": {
    "addr:full":"Dijkstraat 8 Aartselaar Antwerpen 2630",
    "addr:housenumber":"8",
    "addr:postcode":"2630",
    "addr:street":"Dijkstraat",
    "iso:country":"BE",
    "sg:address":"Dijkstraat 8",
    "sg:city":"Aartselaar",
    "sg:classifiers":[
        {
            "category":"Professional",
            "subcategory":"Engineering",
            "type":"Services"
        }
    ],
    "sg:phone":"+32 3 450 45 11",
    "sg:postcode":"2630",
    "sg:province":"Antwerpen",
    "sg:tags":[
        "machine",
        "-",
        "environment",
        "equipment",
        "machinery",
        "mechanical"
    ],
    "wof:name":"Aquafin Nv",
    "wof:placetype":"venue"
},
  "geometry": {"coordinates":[4.3952531815,51.1464881897],"type":"Point"}
}