{
  "type": "Feature",
  "properties": {
    "addr:full":"Avenue Henri Conscience 212 Evere Bruxelles-Capitale 1140",
    "addr:housenumber":"212",
    "addr:postcode":"1140",
    "addr:street":"Avenue Henri Conscience",
    "iso:country":"BE",
    "sg:address":"Avenue Henri Conscience 212",
    "sg:city":"Evere",
    "sg:orig_category":"Epiceries",
    "sg:phone":"+32 2 215 41 40",
    "sg:postcode":"1140",
    "sg:province":"Bruxelles-Capitale",
    "wof:name":"Ahmad Laique",
    "wof:placetype":"venue"
},
  "geometry": {"coordinates":[4.4006109238,50.8725814819],"type":"Point"}
}