{
  "type": "Feature",
  "properties": {
    "iso:country":"BE",
    "sg:address":"Lijsterbessenbomenlaan 21",
    "sg:city":"Kraainem/kraainem",
    "sg:orig_category":"Boekbinderijen and afwerking",
    "sg:phone":"+32 2 720 15 25",
    "sg:postcode":"1950",
    "sg:province":"Vlaams-Brabant",
    "wof:name":"Boekbinderij Vandenplas",
    "wof:placetype":"venue"
},
  "geometry": {"coordinates":[4.4604759216,50.8621788025],"type":"Point"}
}