{
  "type": "Feature",
  "properties": {
    "iso:country":"BE",
    "sg:address":"Rue Du Champ De La Couronne 21",
    "sg:city":"Bruxelles",
    "sg:classifiers":[
        {
            "category":"Sports & Exercise",
            "subcategory":"Gym",
            "type":"Entertainment"
        }
    ],
    "sg:phone":"+32 2 479 59 25",
    "sg:postcode":"1020",
    "sg:province":"Bruxelles-Capitale",
    "sg:tags":[
        "fitness"
    ],
    "wof:name":"Score Ten",
    "wof:placetype":"venue"
},
  "geometry": {"coordinates":[4.3506298065,50.8790664673],"type":"Point"}
}