{
  "type": "Feature",
  "properties": {
    "addr:full":"Korte Veldstraat 21 Turnhout Antwerpen 2300",
    "addr:housenumber":"21",
    "addr:postcode":"2300",
    "addr:street":"Korte Veldstraat",
    "iso:country":"BE",
    "sg:address":"Korte Veldstraat 21",
    "sg:city":"Turnhout",
    "sg:classifiers":[
        {
            "category":"Communications",
            "type":"Services"
        }
    ],
    "sg:phone":"+32 14 42 37 93",
    "sg:postcode":"2300",
    "sg:province":"Antwerpen",
    "sg:tags":[
        "translator"
    ],
    "wof:name":"Van Poppel",
    "wof:placetype":"venue"
},
  "geometry": {"coordinates":[4.9539780617,51.3204689026],"type":"Point"}
}