{
  "type": "Feature",
  "properties": {
    "addr:full":"Zwevegemstraat 35 Zwevegem (otegem) West-Vlaanderen 8553",
    "addr:housenumber":"35",
    "addr:postcode":"8553",
    "addr:street":"Zwevegemstraat",
    "iso:country":"BE",
    "sg:address":"Zwevegemstraat 35",
    "sg:city":"Zwevegem (otegem)",
    "sg:classifiers":[
        {
            "category":"Insurance",
            "subcategory":"Insurance Agent",
            "type":"Services"
        }
    ],
    "sg:phone":"+32 56 77 67 57",
    "sg:postcode":"8553",
    "sg:province":"West-Vlaanderen",
    "sg:tags":[
        "broker"
    ],
    "wof:name":"Hollebecq K",
    "wof:placetype":"venue"
},
  "geometry": {"coordinates":[3.4189898968,50.8081626892],"type":"Point"}
}