{
  "type": "Feature",
  "properties": {
    "addr:full":"Steenweg Op Leopoldsburg 28 Balen Antwerpen 2490",
    "addr:housenumber":"28",
    "addr:postcode":"2490",
    "addr:street":"Steenweg Op Leopoldsburg",
    "iso:country":"BE",
    "sg:address":"Steenweg Op Leopoldsburg 28",
    "sg:city":"Balen",
    "sg:orig_category":"Mat\u00e9riaux de construction Construction industrielle and commerciale. Plomberie, chauffage and instal",
    "sg:phone":"+32 14 81 14 01",
    "sg:postcode":"2490",
    "sg:province":"Antwerpen",
    "wof:name":"Metaalkonstrukties Sleurs",
    "wof:placetype":"venue"
},
  "geometry": {"coordinates":[5.2379307747,51.1353340149],"type":"Point"}
}