{
  "type": "Feature",
  "properties": {
    "iso:country":"BE",
    "sg:address":"Diestsebaan 33",
    "sg:city":"Herselt",
    "sg:classifiers":[
        {
            "category":"Bars & Pubs",
            "type":"Food & Drink"
        }
    ],
    "sg:phone":"+32 14 54 01 29",
    "sg:postcode":"2230",
    "sg:province":"Antwerpen",
    "wof:name":"Bergomhof",
    "wof:placetype":"venue"
},
  "geometry": {"coordinates":[4.9165210724,51.0756568909],"type":"Point"}
}