{
  "type": "Feature",
  "properties": {
    "addr:full":"Grobbendonkseweg 33 Nijlen Antwerpen 2560",
    "addr:housenumber":"33",
    "addr:postcode":"2560",
    "addr:street":"Grobbendonkseweg",
    "iso:country":"BE",
    "sg:address":"Grobbendonkseweg 33",
    "sg:city":"Nijlen",
    "sg:orig_category":"Diensten voor huisdieren",
    "sg:phone":"+32 3 411 01 83",
    "sg:postcode":"2560",
    "sg:province":"Antwerpen",
    "wof:name":"Hondenkapsalon Boebi",
    "wof:placetype":"venue"
},
  "geometry": {"coordinates":[4.692647934,51.1665992737],"type":"Point"}
}