{
  "type": "Feature",
  "properties": {
    "iso:country":"BE",
    "sg:address":"Chauss\u00c9e De Charlemagne 154",
    "sg:city":"Thimister-clermont",
    "sg:orig_category":"Meubles Fab. Meubles D\u00e9taillants, Am\u00e9nagement de B\u00e2timents et de Cuisines",
    "sg:phone":"+32 87 44 61 28",
    "sg:postcode":"4890",
    "sg:province":"Li\u00e8ge",
    "wof:name":"Meubles C\u00c9zar",
    "wof:placetype":"venue"
},
  "geometry": {"coordinates":[5.8866658211,50.655128479],"type":"Point"}
}