{
  "type": "Feature",
  "properties": {
    "addr:full":"Daalstraat 9 Zutendaal Limburg 3690",
    "addr:housenumber":"9",
    "addr:postcode":"3690",
    "addr:street":"Daalstraat",
    "iso:country":"BE",
    "sg:address":"Daalstraat 9",
    "sg:city":"Zutendaal",
    "sg:classifiers":[
        {
            "category":"Travel",
            "subcategory":"Hotels & Motels",
            "type":"Entertainment"
        }
    ],
    "sg:phone":"+32 89 61 11 31",
    "sg:postcode":"3690",
    "sg:province":"Limburg",
    "wof:name":"De Klok Nv",
    "wof:placetype":"venue"
},
  "geometry": {"coordinates":[5.571313858,50.9313697815],"type":"Point"}
}