{
  "type": "Feature",
  "properties": {
    "iso:country":"BE",
    "sg:address":"Rue Maurice Des Ombiaux 2",
    "sg:city":"Thuin",
    "sg:classifiers":[
        {
            "category":"Professional",
            "subcategory":"Art Services",
            "type":"Services"
        }
    ],
    "sg:phone":"+32 71 59 48 18",
    "sg:postcode":"6530",
    "sg:province":"Hainaut",
    "sg:tags":[
        "interior",
        "designer"
    ],
    "wof:name":"Meylemans G",
    "wof:placetype":"venue"
},
  "geometry": {"coordinates":[4.2877278328,50.3391342163],"type":"Point"}
}