{
  "type": "Feature",
  "properties": {
    "iso:country":"BE",
    "sg:address":"Rue De M\u00c9ry 11",
    "sg:city":"Sprimont",
    "sg:orig_category":"Ramassage and traitement des d\u00e9chets m\u00e9nagers",
    "sg:phone":"+32 4 368 67 17",
    "sg:postcode":"4140",
    "sg:province":"Li\u00e8ge",
    "wof:name":"Habitat-multiservice",
    "wof:placetype":"venue"
},
  "geometry": {"coordinates":[5.628513813,50.5376815796],"type":"Point"}
}