{
  "type": "Feature",
  "properties": {
    "iso:country":"BE",
    "sg:address":"Sint Truiderstraat 58",
    "sg:city":"Tongeren",
    "sg:classifiers":[
        {
            "category":"Cafe",
            "type":"Food & Drink"
        }
    ],
    "sg:phone":"+32 12 23 91 72",
    "sg:postcode":"3700",
    "sg:province":"Limburg",
    "sg:tags":[
        "caf\u00e9s"
    ],
    "wof:name":"The Ozone",
    "wof:placetype":"venue"
},
  "geometry": {"coordinates":[5.4538741112,50.7786064148],"type":"Point"}
}