{
  "type": "Feature",
  "properties": {
    "addr:full":"Boulevard Emile Schevenels 4 Lessines Hainaut 7860",
    "addr:housenumber":"4",
    "addr:postcode":"7860",
    "addr:street":"Boulevard Emile Schevenels;Hainaut",
    "iso:country":"BE",
    "sg:address":"Boulevard Emile Schevenels 4",
    "sg:city":"Lessines",
    "sg:classifiers":[
        {
            "category":"Shopping",
            "subcategory":"Baby Store",
            "type":"Retail Goods"
        }
    ],
    "sg:phone":"+32 68 33 66 12",
    "sg:postcode":"7860",
    "sg:province":"Hainaut",
    "sg:tags":[
        "-",
        "accessory"
    ],
    "wof:name":"Petitom",
    "wof:placetype":"venue"
},
  "geometry": {"coordinates":[3.827755928,50.7158966064],"type":"Point"}
}