{
  "type": "Feature",
  "properties": {
    "addr:full":"Avenue Van Overbeke 134 Bruxelles (ganshoren) Bruxelles-Capitale 1083",
    "addr:housenumber":"134",
    "addr:postcode":"1083",
    "addr:street":"Avenue Van Overbeke",
    "iso:country":"BE",
    "sg:address":"Avenue Van Overbeke 134",
    "sg:city":"Bruxelles (ganshoren)",
    "sg:classifiers":[
        {
            "category":"Health Services",
            "subcategory":"Health Practitioner",
            "type":"Services"
        }
    ],
    "sg:phone":"+32 2 469 17 17",
    "sg:postcode":"1083",
    "sg:province":"Bruxelles-Capitale",
    "sg:tags":[
        "osteopath"
    ],
    "wof:name":"De Langhe P",
    "wof:placetype":"venue"
},
  "geometry": {"coordinates":[4.3133921623,50.8726348877],"type":"Point"}
}