{
  "type": "Feature",
  "properties": {
    "iso:country":"BE",
    "sg:address":"Rue Du Petit Baty 11",
    "sg:city":"Mont-saint-guibert (corbais)",
    "sg:classifiers":[
        {
            "category":"Freight",
            "type":"Transportation"
        }
    ],
    "sg:phone":"+32 10 65 57 49",
    "sg:postcode":"1435",
    "sg:province":"Brabant Wallon",
    "sg:tags":[
        "express",
        "transport"
    ],
    "wof:name":"Dema Trans",
    "wof:placetype":"venue"
},
  "geometry": {"coordinates":[4.6431331635,50.6443023682],"type":"Point"}
}