{
  "type": "Feature",
  "properties": {
    "addr:full":"Gapaardstraat 6 Heuvelland (wijtschate) West-Vlaanderen 8953",
    "addr:housenumber":"6",
    "addr:postcode":"8953",
    "addr:street":"Gapaardstraat",
    "iso:country":"BE",
    "sg:address":"Gapaardstraat 6",
    "sg:city":"Heuvelland (wijtschate)",
    "sg:classifiers":[
        {
            "category":"Manufacturing",
            "subcategory":"Metals",
            "type":"Manufacturing & Wholesale Goods"
        }
    ],
    "sg:phone":"+32 57 44 59 63",
    "sg:postcode":"8953",
    "sg:province":"West-Vlaanderen",
    "sg:tags":[
        "steel",
        "stainless"
    ],
    "wof:name":"Deklerck F",
    "wof:placetype":"venue"
},
  "geometry": {"coordinates":[2.9094259739,50.7709732056],"type":"Point"}
}