{
  "type": "Feature",
  "properties": {
    "addr:full":"Avenue Frans Van Kalken 18 Box 183 Bruxelles (anderlecht) Bruxelles-Capitale 1070",
    "addr:housenumber":"18",
    "addr:postcode":"1070",
    "addr:street":"Avenue Frans Van Kalken;Box 183",
    "iso:country":"BE",
    "sg:address":"Avenue Frans Van Kalken 18 Box 183",
    "sg:city":"Bruxelles (anderlecht)",
    "sg:classifiers":[
        {
            "category":"Professional",
            "subcategory":"Accounting & Tax Preparation",
            "type":"Services"
        }
    ],
    "sg:phone":"+32 2 527 34 24",
    "sg:postcode":"1070",
    "sg:province":"Bruxelles-Capitale",
    "sg:tags":[
        "bookkeeper"
    ],
    "wof:name":"Godfroid B",
    "wof:placetype":"venue"
},
  "geometry": {"coordinates":[4.3057518005,50.8255157471],"type":"Point"}
}