{
  "type": "Feature",
  "properties": {
    "addr:full":"Grand'rue 49 Walhain (walhain-saint-paul) Brabant Wallon 1457",
    "addr:housenumber":"49",
    "addr:postcode":"1457",
    "addr:street":"Grand'Rue;Wallon",
    "iso:country":"BE",
    "sg:address":"Grand'rue 49",
    "sg:city":"Walhain (walhain-saint-paul)",
    "sg:classifiers":[
        {
            "category":"Banks & Credit Unions",
            "subcategory":"Investment Brokerage",
            "type":"Services"
        }
    ],
    "sg:phone":"+32 10 65 84 96",
    "sg:postcode":"1457",
    "sg:province":"Brabant Wallon",
    "sg:tags":[
        "repair",
        "-",
        "installation",
        "sanitary",
        "article"
    ],
    "wof:name":"Edl Sanitaires",
    "wof:placetype":"venue"
},
  "geometry": {"coordinates":[4.6581568718,50.6102600098],"type":"Point"}
}