{
  "type": "Feature",
  "properties": {
    "iso:country":"BE",
    "sg:address":"Samr\u00c9e 4ba",
    "sg:city":"La Roche-en-ardenne",
    "sg:orig_category":"Entretien and r\u00e9parations de voitures",
    "sg:phone":"+32 84 44 43 08",
    "sg:postcode":"6982",
    "sg:province":"Luxembourg",
    "wof:name":"Garage Tahay B.",
    "wof:placetype":"venue"
},
  "geometry": {"coordinates":[5.638133049,50.2120666504],"type":"Point"}
}