{
  "type": "Feature",
  "properties": {
    "addr:full":"Laan Op Vurten 120 Beringen Limburg 3580",
    "addr:housenumber":"120",
    "addr:postcode":"3580",
    "addr:street":"Laan Op Vurten",
    "iso:country":"BE",
    "sg:address":"Laan Op Vurten 120",
    "sg:city":"Beringen",
    "sg:classifiers":[
        {
            "category":"Autos & Motor Vehicles",
            "subcategory":"Auto Supplies",
            "type":"Retail Goods"
        }
    ],
    "sg:phone":"+32 11 40 34 74",
    "sg:postcode":"3580",
    "sg:province":"Limburg",
    "sg:tags":[
        "access",
        "automobile",
        "part",
        "-"
    ],
    "wof:name":"Cenik Bulent",
    "wof:placetype":"venue"
},
  "geometry": {"coordinates":[5.2290701866,51.072517395],"type":"Point"}
}