{
  "type": "Feature",
  "properties": {
    "addr:full":"Vijfseweg 38 Waregem West-Vlaanderen 8790",
    "addr:housenumber":"38",
    "addr:postcode":"8790",
    "addr:street":"Vijfseweg",
    "iso:country":"BE",
    "sg:address":"Vijfseweg 38",
    "sg:city":"Waregem",
    "sg:classifiers":[
        {
            "category":"Shopping",
            "subcategory":"Florist",
            "type":"Retail Goods"
        }
    ],
    "sg:phone":"+32 56 60 19 14",
    "sg:postcode":"8790",
    "sg:province":"West-Vlaanderen",
    "wof:name":"Verbeke M",
    "wof:placetype":"venue"
},
  "geometry": {"coordinates":[3.4245989323,50.8949165344],"type":"Point"}
}