{
  "type": "Feature",
  "properties": {
    "addr:full":"Avenue D'hougoumont 17a Ukkel/uccle Bruxelles-Capitale 1180",
    "addr:housenumber":"17a",
    "addr:postcode":"1180",
    "addr:street":"Avenue D'Hougoumont;/",
    "iso:country":"BE",
    "sg:address":"Avenue D'hougoumont 17a",
    "sg:city":"Ukkel/uccle",
    "sg:orig_category":"Agences immobili\u00e8res",
    "sg:phone":"+32 2 375 30 86",
    "sg:postcode":"1180",
    "sg:province":"Bruxelles-Capitale",
    "wof:name":"Turbo Rose Ltd",
    "wof:placetype":"venue"
},
  "geometry": {"coordinates":[4.3809800148,50.7726860046],"type":"Point"}
}