{
  "type": "Feature",
  "properties": {
    "addr:full":"Dikkebeuklaan 115 Brussel/bruxelles Bruxelles-Capitale 1020",
    "addr:housenumber":"115",
    "addr:postcode":"1020",
    "addr:street":"Dikkebeuklaan;/",
    "iso:country":"BE",
    "sg:address":"Dikkebeuklaan 115",
    "sg:city":"Brussel/bruxelles",
    "sg:orig_category":"Apotheken",
    "sg:phone":"+32 2 478 52 11",
    "sg:postcode":"1020",
    "sg:province":"Bruxelles-Capitale",
    "wof:name":"Pharmacie N. Jacques",
    "wof:placetype":"venue"
},
  "geometry": {"coordinates":[4.3211770058,50.8939437866],"type":"Point"}
}