{
  "type": "Feature",
  "properties": {
    "iso:country":"BE",
    "sg:address":"Rue Des Battys 16",
    "sg:city":"Gedinne",
    "sg:orig_category":"Mus\u00e9es and patrimoine culturel",
    "sg:phone":"+32 61 58 94 29",
    "sg:postcode":"5575",
    "sg:province":"Namur",
    "wof:name":"Mus\u00c9e A La Plume D'oie",
    "wof:placetype":"venue"
},
  "geometry": {"coordinates":[4.9335680008,49.980178833],"type":"Point"}
}