{
  "type": "Feature",
  "properties": {
    "iso:country":"BE",
    "sg:address":"Walbrugstraat 17",
    "sg:city":"Oostkamp",
    "sg:orig_category":"Architecten",
    "sg:phone":"+32 50 82 38 07",
    "sg:postcode":"8020",
    "sg:province":"West-Vlaanderen",
    "wof:name":"Els Verzele",
    "wof:placetype":"venue"
},
  "geometry": {"coordinates":[3.2551419735,51.1398010254],"type":"Point"}
}