{
  "type": "Feature",
  "properties": {
    "addr:full":"Rue De La Vall\u00e9e 11 Remicourt (pousset) Li\u00e8ge 4350",
    "addr:housenumber":"11",
    "addr:postcode":"4350",
    "addr:street":"Rue De La Valle\u0301E;Pousset",
    "iso:country":"BE",
    "sg:address":"Rue De La Vall\u00e9e 11",
    "sg:city":"Remicourt (pousset)",
    "sg:classifiers":[
        {
            "category":"Organizations",
            "subcategory":"Community Association",
            "type":"Services"
        }
    ],
    "sg:phone":"+32 19 54 54 87",
    "sg:postcode":"4350",
    "sg:province":"Li\u00e8ge",
    "sg:tags":[
        "cultural"
    ],
    "wof:name":"Ferme 140",
    "wof:placetype":"venue"
},
  "geometry": {"coordinates":[5.3064379692,50.6942100525],"type":"Point"}
}