{
  "type": "Feature",
  "properties": {
    "addr:full":"Bahnhofstrasse 1a Eupen Li\u00e8ge 4700",
    "addr:housenumber":"1a",
    "addr:postcode":"4700",
    "addr:street":"Bahnhofstrasse",
    "iso:country":"BE",
    "sg:address":"Bahnhofstrasse 1a",
    "sg:city":"Eupen",
    "sg:classifiers":[
        {
            "category":"Personal",
            "subcategory":"Beauty Salon",
            "type":"Services"
        }
    ],
    "sg:phone":"+32 87 55 70 60",
    "sg:postcode":"4700",
    "sg:province":"Li\u00e8ge",
    "sg:tags":[
        "lady",
        "-",
        "hairdressing"
    ],
    "wof:name":"Gaby (salon)",
    "wof:placetype":"venue"
},
  "geometry": {"coordinates":[6.0361790657,50.6348800659],"type":"Point"}
}