{
  "type": "Feature",
  "properties": {
    "addr:full":"Hellenenstraat 23 Elsene/ixelles Bruxelles-Capitale 1050",
    "addr:housenumber":"23",
    "addr:postcode":"1050",
    "addr:street":"Hellenenstraat",
    "iso:country":"BE",
    "sg:address":"Hellenenstraat 23",
    "sg:city":"Elsene/ixelles",
    "sg:orig_category":"Artsen and specialisten",
    "sg:phone":"+32 2 648 63 93",
    "sg:postcode":"1050",
    "sg:province":"Bruxelles-Capitale",
    "wof:name":"Giao Nguyen-ngoc",
    "wof:placetype":"venue"
},
  "geometry": {"coordinates":[4.3875169754,50.8162307739],"type":"Point"}
}