{
  "type": "Feature",
  "properties": {
    "iso:country":"BE",
    "sg:address":"Louis De Naeyerplein 26",
    "sg:city":"Willebroek",
    "sg:classifiers":[
        {
            "category":"Shopping",
            "subcategory":"Clothing, Apparel, & Fashions",
            "type":"Retail Goods"
        }
    ],
    "sg:phone":"+32 3 886 92 89",
    "sg:postcode":"2830",
    "sg:province":"Antwerpen",
    "sg:tags":[
        "boutique"
    ],
    "wof:name":"Miss Jolly",
    "wof:placetype":"venue"
},
  "geometry": {"coordinates":[4.3608798981,51.0613174438],"type":"Point"}
}