{
  "type": "Feature",
  "properties": {
    "addr:full":"Baden Powelllaan 2 Sint-lambrechts-woluwe/woluwe-saint-lambert Bruxelles-Capitale 1200",
    "addr:housenumber":"2",
    "addr:postcode":"1200",
    "addr:street":"Baden Powelllaan",
    "iso:country":"BE",
    "sg:address":"Baden Powelllaan 2",
    "sg:city":"Sint-lambrechts-woluwe/woluwe-saint-lambert",
    "sg:orig_category":"Fotografen and fotostudio's",
    "sg:phone":"+32 2 538 91 56",
    "sg:postcode":"1200",
    "sg:province":"Bruxelles-Capitale",
    "wof:name":"Didier Bauweraerts/",
    "wof:placetype":"venue"
},
  "geometry": {"coordinates":[4.430077076,50.8443565369],"type":"Point"}
}