{
  "type": "Feature",
  "properties": {
    "iso:country":"BE",
    "sg:address":"Gustaaf Woutersstraat 8",
    "sg:city":"Balen",
    "sg:classifiers":[
        {
            "category":"Health Services",
            "subcategory":"Dentist",
            "type":"Services"
        }
    ],
    "sg:phone":"+32 14 81 73 58",
    "sg:postcode":"2490",
    "sg:province":"Antwerpen",
    "wof:name":"Vandenputte Riet",
    "wof:placetype":"venue"
},
  "geometry": {"coordinates":[5.1708788872,51.1700286865],"type":"Point"}
}