{
  "type": "Feature",
  "properties": {
    "iso:country":"BE",
    "sg:address":"Eikenlei 54",
    "sg:city":"Grobbendonk",
    "sg:classifiers":[
        {
            "category":"Health Services",
            "subcategory":"Nursing And Care Facility",
            "type":"Services"
        }
    ],
    "sg:phone":"+32 14 51 74 39",
    "sg:postcode":"2280",
    "sg:province":"Antwerpen",
    "sg:tags":[
        "home"
    ],
    "wof:name":"Liekens Koen",
    "wof:placetype":"venue"
},
  "geometry": {"coordinates":[4.7213568687,51.1894454956],"type":"Point"}
}