{
  "type": "Feature",
  "properties": {
    "addr:full":"Fonteinstraat 9 Sint-genesius-rode/rhode-saint-genese Vlaams-Brabant 1640",
    "addr:housenumber":"9",
    "addr:postcode":"1640",
    "addr:street":"Fonteinstraat",
    "iso:country":"BE",
    "sg:address":"Fonteinstraat 9",
    "sg:city":"Sint-genesius-rode/rhode-saint-genese",
    "sg:orig_category":"Opticiens",
    "sg:phone":"+32 2 380 70 20",
    "sg:postcode":"1640",
    "sg:province":"Vlaams-Brabant",
    "wof:name":"Vandiest Opticien",
    "wof:placetype":"venue"
},
  "geometry": {"coordinates":[4.3461098671,50.7443809509],"type":"Point"}
}