{
  "type": "Feature",
  "properties": {
    "iso:country":"BE",
    "sg:address":"Antwerpsestraat 75",
    "sg:city":"Lier",
    "sg:orig_category":"Schoenen",
    "sg:phone":"+32 3 488 33 05",
    "sg:postcode":"2500",
    "sg:province":"Antwerpen",
    "wof:name":"Benjamine",
    "wof:placetype":"venue"
},
  "geometry": {"coordinates":[4.5670318604,51.1335945129],"type":"Point"}
}