{
  "type": "Feature",
  "properties": {
    "addr:full":"Brusselsesteenweg 133 Edingen/enghien Hainaut 7850",
    "addr:housenumber":"133",
    "addr:postcode":"7850",
    "addr:street":"Brusselsesteenweg",
    "iso:country":"BE",
    "sg:address":"Brusselsesteenweg 133",
    "sg:city":"Edingen/enghien",
    "sg:orig_category":"Elektrische installaties voor woningen",
    "sg:phone":"+32 2 395 54 28",
    "sg:postcode":"7850",
    "sg:province":"Hainaut",
    "wof:name":"C.v. Electricit\u00c9",
    "wof:placetype":"venue"
},
  "geometry": {"coordinates":[4.084965229,50.6917228699],"type":"Point"}
}