{
  "type": "Feature",
  "properties": {
    "addr:full":"Staatsbaan 2ba Maldegem Oost-Vlaanderen 9991",
    "addr:housenumber":"2ba",
    "addr:postcode":"9991",
    "addr:street":"Staatsbaan",
    "iso:country":"BE",
    "sg:address":"Staatsbaan 2ba",
    "sg:city":"Maldegem",
    "sg:orig_category":"V\u00eatements",
    "sg:phone":"+32 50 71 10 50",
    "sg:postcode":"9991",
    "sg:province":"Oost-Vlaanderen",
    "wof:name":"In De Nerts",
    "wof:placetype":"venue"
},
  "geometry": {"coordinates":[3.4716451168,51.2044639587],"type":"Point"}
}