{
  "type": "Feature",
  "properties": {
    "iso:country":"BE",
    "sg:address":"Stationsstraat 33",
    "sg:city":"Hamont-achel",
    "sg:classifiers":[
        {
            "category":"Autos & Motor Vehicles",
            "subcategory":"Fuel & Gas Station",
            "type":"Retail Goods"
        }
    ],
    "sg:phone":"+32 11 44 70 68",
    "sg:postcode":"3930",
    "sg:province":"Limburg",
    "sg:tags":[
        "stations-service",
        "carburants"
    ],
    "wof:name":"Umans-winters",
    "wof:placetype":"venue"
},
  "geometry": {"coordinates":[5.5450549126,51.2511863708],"type":"Point"}
}