{
  "type": "Feature",
  "properties": {
    "addr:full":"De Gerlachestraat 13b3 Hasselt Limburg 3500",
    "addr:housenumber":"13b3",
    "addr:postcode":"3500",
    "addr:street":"De Gerlachestraat",
    "iso:country":"BE",
    "sg:address":"De Gerlachestraat 13b3",
    "sg:city":"Hasselt",
    "sg:orig_category":"Artistes ind\u00e9pendants. Activit\u00e9s diverses d'imprimerie",
    "sg:phone":"+32 11 22 10 77",
    "sg:postcode":"3500",
    "sg:province":"Limburg",
    "wof:name":"R. Rappoort",
    "wof:placetype":"venue"
},
  "geometry": {"coordinates":[5.341506958,50.9268608093],"type":"Point"}
}