{
  "type": "Feature",
  "properties": {
    "iso:country":"BE",
    "sg:address":"Place De La Libert\u00c9 6",
    "sg:city":"Waremme",
    "sg:orig_category":"Artsen and specialisten",
    "sg:phone":"+32 19 33 18 32",
    "sg:postcode":"4300",
    "sg:province":"Li\u00e8ge",
    "wof:name":"Yoko Proph\u00c8te",
    "wof:placetype":"venue"
},
  "geometry": {"coordinates":[5.280151844,50.7123374939],"type":"Point"}
}