{
  "type": "Feature",
  "properties": {
    "addr:full":"Avenue Huldergem 30 Brussel/bruxelles Bruxelles-Capitale 1020",
    "addr:housenumber":"30",
    "addr:postcode":"1020",
    "addr:street":"Avenue Huldergem;/",
    "iso:country":"BE",
    "sg:address":"Avenue Huldergem 30",
    "sg:city":"Brussel/bruxelles",
    "sg:classifiers":[
        {
            "category":"Shopping",
            "subcategory":"Clothing, Apparel, & Fashions",
            "type":"Retail Goods"
        }
    ],
    "sg:phone":"+32 2 268 56 69",
    "sg:postcode":"1020",
    "sg:province":"Bruxelles-Capitale",
    "sg:tags":[
        "v\u00eatements",
        "pour",
        "dame"
    ],
    "wof:name":"Fabienne Sagal",
    "wof:placetype":"venue"
},
  "geometry": {"coordinates":[4.3676481247,50.8992271423],"type":"Point"}
}