{
  "type": "Feature",
  "properties": {
    "iso:country":"BE",
    "sg:address":"Brugstraat 6",
    "sg:city":"Knesselare",
    "sg:orig_category":"Eleveurs de bovins. Eleveurs and marchands de porcs",
    "sg:phone":"+32 9 374 25 64",
    "sg:postcode":"9910",
    "sg:province":"Oost-Vlaanderen",
    "wof:name":"Alfons Bral Geerard",
    "wof:placetype":"venue"
},
  "geometry": {"coordinates":[3.4962689877,51.1411323547],"type":"Point"}
}