{
  "type": "Feature",
  "properties": {
    "iso:country":"BE",
    "sg:address":"Avenue Provinciale",
    "sg:city":"Ceroux-mousty",
    "sg:orig_category":"Diensten voor huisdieren Huisdieren and benodigdheden Royal Canin",
    "sg:phone":"+32 10 61 41 70",
    "sg:postcode":"1341",
    "sg:province":"Brabant Wallon",
    "wof:name":"Jussy",
    "wof:placetype":"venue"
},
  "geometry": {"coordinates":[4.5635180473,50.655002594],"type":"Point"}
}