{
  "type": "Feature",
  "properties": {
    "addr:full":"Rue Des Prisonniers 4 Froidchapelle Hainaut 6440",
    "addr:housenumber":"4",
    "addr:postcode":"6440",
    "addr:street":"Rue Des Prisonniers",
    "iso:country":"BE",
    "sg:address":"Rue Des Prisonniers 4",
    "sg:city":"Froidchapelle",
    "sg:orig_category":"Dranken",
    "sg:phone":"+32 60 41 17 42",
    "sg:postcode":"6440",
    "sg:province":"Hainaut",
    "wof:name":"Stephane Jullien",
    "wof:placetype":"venue"
},
  "geometry": {"coordinates":[4.3299379349,50.1496620178],"type":"Point"}
}