{
  "type": "Feature",
  "properties": {
    "iso:country":"BE",
    "sg:address":"Rue Du Cerf 85",
    "sg:city":"Genval",
    "sg:classifiers":[
        {
            "category":"Wholesale",
            "subcategory":"Durable Goods & Equipment",
            "type":"Manufacturing & Wholesale Goods"
        }
    ],
    "sg:phone":"+32 2 652 02 20",
    "sg:postcode":"1332",
    "sg:province":"Brabant Wallon",
    "sg:tags":[
        "merchandising"
    ],
    "wof:name":"International Merchandising & Promotion Services S.a.",
    "wof:placetype":"venue"
},
  "geometry": {"coordinates":[4.5084271431,50.7294807434],"type":"Point"}
}