{
  "type": "Feature",
  "properties": {
    "addr:full":"Vijfseweg 44 Waregem West-Vlaanderen 8790",
    "addr:housenumber":"44",
    "addr:postcode":"8790",
    "addr:street":"Vijfseweg",
    "iso:country":"BE",
    "sg:address":"Vijfseweg 44",
    "sg:city":"Waregem",
    "sg:classifiers":[
        {
            "category":"Real Estate",
            "subcategory":"Real Estate Services",
            "type":"Services"
        }
    ],
    "sg:phone":"+32 56 61 16 16",
    "sg:postcode":"8790",
    "sg:province":"West-Vlaanderen",
    "wof:name":"Ysowe (immo)",
    "wof:placetype":"venue"
},
  "geometry": {"coordinates":[3.4244670868,50.8950576782],"type":"Point"}
}