{
  "type": "Feature",
  "properties": {
    "iso:country":"BE",
    "sg:address":"Rue Dampremy 75",
    "sg:city":"Charleroi",
    "sg:orig_category":"Disneyland Paris. Agences de voyages",
    "sg:phone":"+32 71 31 78 22",
    "sg:postcode":"6000",
    "sg:province":"Hainaut",
    "wof:name":"C.i.c.",
    "wof:placetype":"venue"
},
  "geometry": {"coordinates":[4.4396691322,50.409412384],"type":"Point"}
}