{
  "type": "Feature",
  "properties": {
    "addr:full":"Sint-baafskouterstraat 79 Gent Oost-Vlaanderen 9040",
    "addr:housenumber":"79",
    "addr:postcode":"9040",
    "addr:street":"Sint-Baafskouterstraat;Oost-Vlaanderen",
    "iso:country":"BE",
    "sg:address":"Sint-baafskouterstraat 79",
    "sg:city":"Gent",
    "sg:orig_category":"Plomberie, chauffage and installations sanitaires",
    "sg:phone":"+32 9 228 60 25",
    "sg:postcode":"9040",
    "sg:province":"Oost-Vlaanderen",
    "wof:name":"Rudolphe Francois",
    "wof:placetype":"venue"
},
  "geometry": {"coordinates":[3.7548389435,51.0565452576],"type":"Point"}
}