{
  "type": "Feature",
  "properties": {
    "addr:full":"Dorp 109 Herselt Antwerpen 2230",
    "addr:housenumber":"109",
    "addr:postcode":"2230",
    "addr:street":"Dorp",
    "iso:country":"BE",
    "sg:address":"Dorp 109",
    "sg:city":"Herselt",
    "sg:classifiers":[
        {
            "category":"Cafe",
            "type":"Food & Drink"
        }
    ],
    "sg:phone":"+32 14 54 86 86",
    "sg:postcode":"2230",
    "sg:province":"Antwerpen",
    "sg:tags":[
        "caf\u00e9s"
    ],
    "wof:name":"Kristiaan Bloemmen",
    "wof:placetype":"venue"
},
  "geometry": {"coordinates":[4.8842959404,51.0544815063],"type":"Point"}
}