{
  "type": "Feature",
  "properties": {
    "addr:full":"Avenue De La Salm 27 Vielsalm Luxembourg 6690",
    "addr:housenumber":"27",
    "addr:postcode":"6690",
    "addr:street":"Avenue De La Salm",
    "iso:country":"BE",
    "sg:address":"Avenue De La Salm 27",
    "sg:city":"Vielsalm",
    "sg:orig_category":"Notarissen",
    "sg:phone":"+32 80 21 64 12",
    "sg:postcode":"6690",
    "sg:province":"Luxembourg",
    "wof:name":"P. Cottin",
    "wof:placetype":"venue"
},
  "geometry": {"coordinates":[5.9124560356,50.2811088562],"type":"Point"}
}