{
  "type": "Feature",
  "properties": {
    "iso:country":"BE",
    "sg:address":"Fikkeplas 24",
    "sg:city":"Hasselt",
    "sg:orig_category":"Diensten voor huisdieren",
    "sg:phone":"+32 11 31 32 52",
    "sg:postcode":"3512",
    "sg:province":"Limburg",
    "wof:name":"Pension De Kleine Soethem",
    "wof:placetype":"venue"
},
  "geometry": {"coordinates":[5.2399988174,50.9282035828],"type":"Point"}
}