{
  "type": "Feature",
  "properties": {
    "addr:full":"Van Eycklaan 58 Maaseik Limburg 3680",
    "addr:housenumber":"58",
    "addr:postcode":"3680",
    "addr:street":"Van Eycklaan",
    "iso:country":"BE",
    "sg:address":"Van Eycklaan 58",
    "sg:city":"Maaseik",
    "sg:classifiers":[
        {
            "category":"Insurance",
            "subcategory":"Insurance Agent",
            "type":"Services"
        }
    ],
    "sg:phone":"+32 89 70 22 03",
    "sg:postcode":"3680",
    "sg:province":"Limburg",
    "sg:tags":[
        "broker"
    ],
    "wof:name":"Raemen Louis Bvba",
    "wof:placetype":"venue"
},
  "geometry": {"coordinates":[5.791331768,51.0997047424],"type":"Point"}
}