{
  "type": "Feature",
  "properties": {
    "iso:country":"BE",
    "sg:address":"Rue Du Marais 35",
    "sg:city":"Seraing",
    "sg:orig_category":"Activit\u00e9s d\u00b4action sociale sans h\u00e9bergement",
    "sg:phone":"+32 4 336 66 79",
    "sg:postcode":"4100",
    "sg:province":"Li\u00e8ge",
    "wof:name":"Centre P.m.s.",
    "wof:placetype":"venue"
},
  "geometry": {"coordinates":[5.5063657761,50.6108436584],"type":"Point"}
}