{
  "type": "Feature",
  "properties": {
    "iso:country":"BE",
    "sg:address":"Avenue Du Golf 26",
    "sg:city":"Sint-genesius-rode/rhode-saint-gen\u00c8se",
    "sg:orig_category":"M\u00e9decins and sp\u00e9cialistes",
    "sg:phone":"+32 2 358 24 31",
    "sg:postcode":"1640",
    "sg:province":"Vlaams-Brabant",
    "wof:name":"Ga\u00cbtan Willemart",
    "wof:placetype":"venue"
},
  "geometry": {"coordinates":[4.3978300095,50.7416381836],"type":"Point"}
}