{
  "type": "Feature",
  "properties": {
    "addr:full":"Kerselaarstraat 16 Hoegaarden (honsem) Vlaams-Brabant 3320",
    "addr:housenumber":"16",
    "addr:postcode":"3320",
    "addr:street":"Kerselaarstraat",
    "iso:country":"BE",
    "sg:address":"Kerselaarstraat 16",
    "sg:city":"Hoegaarden (honsem)",
    "sg:classifiers":[
        {
            "category":"Professional",
            "subcategory":"Testing Lab",
            "type":"Services"
        }
    ],
    "sg:phone":"+32 16 76 71 58",
    "sg:postcode":"3320",
    "sg:province":"Vlaams-Brabant",
    "sg:tags":[
        "chemist"
    ],
    "wof:name":"Treckels C",
    "wof:placetype":"venue"
},
  "geometry": {"coordinates":[4.8348340988,50.7901763916],"type":"Point"}
}