{
  "type": "Feature",
  "properties": {
    "iso:country":"BE",
    "sg:address":"Sint-anna 25bb",
    "sg:city":"Hamme",
    "sg:orig_category":"Producteurs de l\u00e9gumes",
    "sg:phone":"+32 52 47 64 21",
    "sg:postcode":"9220",
    "sg:province":"Oost-Vlaanderen",
    "wof:name":"Pierre Van Erdeghem",
    "wof:placetype":"venue"
},
  "geometry": {"coordinates":[4.0808358192,51.0947723389],"type":"Point"}
}