{
  "type": "Feature",
  "properties": {
    "addr:full":"Bosvoordse Steenweg 40 Elsene/ixelles Bruxelles-Capitale 1050",
    "addr:housenumber":"40",
    "addr:postcode":"1050",
    "addr:street":"Bosvoordse Steenweg",
    "iso:country":"BE",
    "sg:address":"Bosvoordse Steenweg 40",
    "sg:city":"Elsene/ixelles",
    "sg:orig_category":"Algemeen secundair onderwijs",
    "sg:phone":"+32 2 672 59 54",
    "sg:postcode":"1050",
    "sg:province":"Bruxelles-Capitale",
    "wof:name":"Ces St.vincent De Paul",
    "wof:placetype":"venue"
},
  "geometry": {"coordinates":[4.3945021629,50.8055915833],"type":"Point"}
}