{
  "type": "Feature",
  "properties": {
    "addr:full":"Chauss\u00c9e De Charleroi 152 Charleroi Hainaut 6060",
    "addr:housenumber":"152",
    "addr:postcode":"6060",
    "addr:street":"Chausse\u0301E De Charleroi;Hainaut",
    "iso:country":"BE",
    "sg:address":"Chauss\u00c9e De Charleroi 152",
    "sg:city":"Charleroi",
    "sg:orig_category":"Herstellingen and onderhoud van auto's",
    "sg:phone":"+32 71 48 65 66",
    "sg:postcode":"6060",
    "sg:province":"Hainaut",
    "wof:name":"Garage Euro 97",
    "wof:placetype":"venue"
},
  "geometry": {"coordinates":[4.4677867889,50.403137207],"type":"Point"}
}