{
  "type": "Feature",
  "properties": {
    "iso:country":"BE",
    "sg:address":"Rue Marcel Vandy 4",
    "sg:city":"Namur",
    "sg:orig_category":"Kapsalons",
    "sg:phone":"+32 81 73 49 56",
    "sg:postcode":"5020",
    "sg:province":"Namur",
    "wof:name":"Denis Colin",
    "wof:placetype":"venue"
},
  "geometry": {"coordinates":[4.7952418327,50.4352035522],"type":"Point"}
}