{
  "type": "Feature",
  "properties": {
    "addr:full":"Rue Du T\u00c9nimont 9 Durbuy Luxembourg 6940",
    "addr:housenumber":"9",
    "addr:postcode":"6940",
    "addr:street":"Rue Du Te\u0301Nimont",
    "iso:country":"BE",
    "sg:address":"Rue Du T\u00c9nimont 9",
    "sg:city":"Durbuy",
    "sg:classifiers":[
        {
            "category":"Personal",
            "subcategory":"Beauty Salon",
            "type":"Services"
        }
    ],
    "sg:phone":"+32 86 21 42 54",
    "sg:postcode":"6940",
    "sg:province":"Luxembourg",
    "sg:tags":[
        "de",
        "coiffure"
    ],
    "wof:name":"Coiffure Christine",
    "wof:placetype":"venue"
},
  "geometry": {"coordinates":[5.4979228973,50.3495826721],"type":"Point"}
}