{
  "type": "Feature",
  "properties": {
    "iso:country":"BE",
    "sg:address":"Avenue De Grand'peine 8b1",
    "sg:city":"Seneffe",
    "sg:orig_category":"Rundveehouders",
    "sg:phone":"+32 67 87 83 74",
    "sg:postcode":"7181",
    "sg:province":"Hainaut",
    "wof:name":"Fabiola Michils",
    "wof:placetype":"venue"
},
  "geometry": {"coordinates":[4.2853589058,50.566734314],"type":"Point"}
}