{
  "type": "Feature",
  "properties": {
    "addr:full":"Hendrik Consciencelaan 48 Box 1 Waarschoot Oost-Vlaanderen 9950",
    "addr:housenumber":"48;1",
    "addr:postcode":"9950",
    "addr:street":"Hendrik Consciencelaan;Box",
    "iso:country":"BE",
    "sg:address":"Hendrik Consciencelaan 48 Box 1",
    "sg:city":"Waarschoot",
    "sg:classifiers":[
        {
            "category":"Personal",
            "subcategory":"Beauty Salon",
            "type":"Services"
        }
    ],
    "sg:phone":"+32 9 378 05 33",
    "sg:postcode":"9950",
    "sg:province":"Oost-Vlaanderen",
    "sg:tags":[
        "lady",
        "-",
        "hairdressing"
    ],
    "wof:name":"Vermeulen P",
    "wof:placetype":"venue"
},
  "geometry": {"coordinates":[3.6006510258,51.1476097107],"type":"Point"}
}