{
  "type": "Feature",
  "properties": {
    "iso:country":"BE",
    "sg:address":"Stadsvest 51 Box 2",
    "sg:city":"Leuven (wilsele)",
    "sg:classifiers":[
        {
            "category":"Professional",
            "subcategory":"Management & Consulting",
            "type":"Services"
        }
    ],
    "sg:phone":"+32 475 71 36 02",
    "sg:postcode":"3012",
    "sg:province":"Vlaams-Brabant",
    "sg:tags":[
        "marketing",
        "-",
        "consultant"
    ],
    "wof:name":"Seldeslachts U",
    "wof:placetype":"venue"
},
  "geometry": {"coordinates":[4.7009677887,50.8899116516],"type":"Point"}
}