{
  "type": "Feature",
  "properties": {
    "iso:country":"BE",
    "sg:address":"Rue Du Centre 29",
    "sg:city":"Walcourt",
    "sg:orig_category":"Benzinestations and brandstoffen",
    "sg:phone":"+32 71 21 62 34",
    "sg:postcode":"5651",
    "sg:province":"Namur",
    "wof:name":"Tarcienne Gaz",
    "wof:placetype":"venue"
},
  "geometry": {"coordinates":[4.5016951561,50.3152389526],"type":"Point"}
}