{
  "type": "Feature",
  "properties": {
    "iso:country":"BE",
    "sg:address":"Oude Aalbeeksestraat 6",
    "sg:city":"Kortrijk",
    "sg:orig_category":"Herstelling leer and schoeisel",
    "sg:phone":"+32 56 21 18 54",
    "sg:postcode":"8510",
    "sg:province":"West-Vlaanderen",
    "wof:name":"Oswald Vanderdonck",
    "wof:placetype":"venue"
},
  "geometry": {"coordinates":[3.2617580891,50.7690467834],"type":"Point"}
}