{
  "type": "Feature",
  "properties": {
    "iso:country":"BE",
    "sg:address":"Noordstraat 15",
    "sg:city":"Roeselare",
    "sg:classifiers":[
        {
            "category":"Bakery",
            "type":"Food & Drink"
        }
    ],
    "sg:phone":"+32 51 22 85 25",
    "sg:postcode":"8800",
    "sg:province":"West-Vlaanderen",
    "sg:tags":[
        "confectioner",
        "baker"
    ],
    "wof:name":"Garde (de)",
    "wof:placetype":"venue"
},
  "geometry": {"coordinates":[3.1231780052,50.9455451965],"type":"Point"}
}