{
  "type": "Feature",
  "properties": {
    "iso:country":"BE",
    "sg:address":"Liersesteenweg 100 -102",
    "sg:city":"Mechelen",
    "sg:classifiers":[
        {
            "category":"Personal",
            "subcategory":"Beauty Salon",
            "type":"Services"
        }
    ],
    "sg:phone":"+32 15 21 61 38",
    "sg:postcode":"2800",
    "sg:province":"Antwerpen",
    "sg:tags":[
        "de",
        "coiffure"
    ],
    "wof:name":"Hair Styling Ann",
    "wof:placetype":"venue"
},
  "geometry": {"coordinates":[4.4814538956,51.0373001099],"type":"Point"}
}