{
  "type": "Feature",
  "properties": {
    "iso:country":"BE",
    "sg:address":"Dijk 3",
    "sg:city":"De Panne (adinkerke)",
    "sg:orig_category":"Non-Classified Establishments",
    "sg:phone":"+32 58 42 00 27",
    "sg:postcode":"8660",
    "sg:province":"West-Vlaanderen",
    "wof:name":"Chocolaterie P & J",
    "wof:placetype":"venue"
},
  "geometry": {"coordinates":[2.6020829678,51.0721168518],"type":"Point"}
}