{
  "type": "Feature",
  "properties": {
    "iso:country":"BE",
    "sg:address":"Liersesteenweg 238",
    "sg:city":"Heist-op-den-berg",
    "sg:orig_category":"Herstellingen and onderhoud van auto's Voertuigen",
    "sg:phone":"+32 15 24 73 55",
    "sg:postcode":"2220",
    "sg:province":"Antwerpen",
    "wof:name":"Lepage",
    "wof:placetype":"venue"
},
  "geometry": {"coordinates":[4.7134408951,51.0603103638],"type":"Point"}
}