{
  "type": "Feature",
  "properties": {
    "iso:country":"BE",
    "sg:address":"Route D'arlon 3",
    "sg:city":"Martelange",
    "sg:orig_category":"Quincailleries. Drogueries",
    "sg:phone":"+32 63 60 11 38",
    "sg:postcode":"6630",
    "sg:province":"Luxembourg",
    "wof:name":"Nic-d\u00c9cor",
    "wof:placetype":"venue"
},
  "geometry": {"coordinates":[5.7431521416,49.8208007812],"type":"Point"}
}