{
  "type": "Feature",
  "properties": {
    "iso:country":"BE",
    "sg:address":"Dr\u00c8ve De Colipain 163",
    "sg:city":"Braine-l\u00b4alleud",
    "sg:orig_category":"Matrassen Fab",
    "sg:phone":"+32 2 366 90 04",
    "sg:postcode":"1420",
    "sg:province":"Brabant Wallon",
    "wof:name":"New Trado",
    "wof:placetype":"venue"
},
  "geometry": {"coordinates":[4.3156509399,50.7036209106],"type":"Point"}
}