{
  "type": "Feature",
  "properties": {
    "addr:full":"Muizelstraat 162 Harelbeke (hulste) West-Vlaanderen 8531",
    "addr:housenumber":"162",
    "addr:postcode":"8531",
    "addr:street":"Muizelstraat",
    "iso:country":"BE",
    "sg:address":"Muizelstraat 162",
    "sg:city":"Harelbeke (hulste)",
    "sg:classifiers":[
        {
            "category":"Transit Center",
            "subcategory":"Freight",
            "type":"Transportation"
        }
    ],
    "sg:phone":"+32 56 66 31 36",
    "sg:postcode":"8531",
    "sg:province":"West-Vlaanderen",
    "sg:tags":[
        "tennis court",
        "construction",
        "-"
    ],
    "wof:name":"Tennis Perdaen Nv",
    "wof:placetype":"venue"
},
  "geometry": {"coordinates":[3.294989109,50.9040336609],"type":"Point"}
}