{
  "type": "Feature",
  "properties": {
    "iso:country":"BE",
    "sg:address":"Rue Am\u00c9ricaine 12-14",
    "sg:city":"Sint-gillis/saint-gilles",
    "sg:orig_category":"V\u00e9hicules automobiles. Entretien and r\u00e9parations de voitures",
    "sg:phone":"+32 2 538 26 88",
    "sg:postcode":"1060",
    "sg:province":"Bruxelles-Capitale",
    "wof:name":"Carrosserie Vanspringel",
    "wof:placetype":"venue"
},
  "geometry": {"coordinates":[4.3550281525,50.8246002197],"type":"Point"}
}