{
  "type": "Feature",
  "properties": {
    "addr:full":"Molenstraat 22 Moerbeke Oost-Vlaanderen 9180",
    "addr:housenumber":"22",
    "addr:postcode":"9180",
    "addr:street":"Molenstraat",
    "iso:country":"BE",
    "sg:address":"Molenstraat 22",
    "sg:city":"Moerbeke",
    "sg:classifiers":[
        {
            "category":"Arena",
            "subcategory":"Sports Club",
            "type":"Entertainment"
        }
    ],
    "sg:phone":"+32 9 346 77 08",
    "sg:postcode":"9180",
    "sg:province":"Oost-Vlaanderen",
    "sg:tags":[
        "de"
    ],
    "wof:name":"Sportcomit\u00c9 Moerbeke-waas",
    "wof:placetype":"venue"
},
  "geometry": {"coordinates":[3.9172070026,51.1954040527],"type":"Point"}
}