{
  "type": "Feature",
  "properties": {
    "iso:country":"BE",
    "sg:address":"Lendedreef 6",
    "sg:city":"Anzegem",
    "sg:orig_category":"Sportclubs Sportterreinen and installaties behalve sportcentra",
    "sg:phone":"+32 56 77 33 51",
    "sg:postcode":"8570",
    "sg:province":"West-Vlaanderen",
    "wof:name":"Damesvoetbal Davo Waregem",
    "wof:placetype":"venue"
},
  "geometry": {"coordinates":[3.3920710087,50.8351173401],"type":"Point"}
}