{
  "type": "Feature",
  "properties": {
    "addr:full":"Rue De L'abbaye De Dieleghem 8 Jette Bruxelles-Capitale 1090",
    "addr:housenumber":"8",
    "addr:postcode":"1090",
    "addr:street":"Rue De L'Abbaye De Dieleghem",
    "iso:country":"BE",
    "sg:address":"Rue De L'abbaye De Dieleghem 8",
    "sg:city":"Jette",
    "sg:orig_category":"Diverse bedrijfsbeheeradviesbureaus",
    "sg:phone":"+32 2 479 23 63",
    "sg:postcode":"1090",
    "sg:province":"Bruxelles-Capitale",
    "wof:name":"International Corporate Management",
    "wof:placetype":"venue"
},
  "geometry": {"coordinates":[4.3216190338,50.8825073242],"type":"Point"}
}