{
  "type": "Feature",
  "properties": {
    "iso:country":"BE",
    "sg:address":"August Nihoulstraat 79",
    "sg:city":"Scherpenheuvel-zichem (scherpenheuvel)",
    "sg:classifiers":[
        {
            "category":"Bars & Pubs",
            "type":"Food & Drink"
        }
    ],
    "sg:phone":"+32 13 78 58 08",
    "sg:postcode":"3270",
    "sg:province":"Vlaams-Brabant",
    "wof:name":"The Corner",
    "wof:placetype":"venue"
},
  "geometry": {"coordinates":[4.9790902138,50.9785232544],"type":"Point"}
}