{
  "type": "Feature",
  "properties": {
    "addr:full":"Avenue Louis Lepoutre 2 Elsene/ixelles Bruxelles-Capitale 1050",
    "addr:housenumber":"2",
    "addr:postcode":"1050",
    "addr:street":"Avenue Louis Lepoutre",
    "iso:country":"BE",
    "sg:address":"Avenue Louis Lepoutre 2",
    "sg:city":"Elsene/ixelles",
    "sg:orig_category":"Journaux. Tabac. Fournitures de bureau",
    "sg:phone":"+32 2 343 42 70",
    "sg:postcode":"1050",
    "sg:province":"Bruxelles-Capitale",
    "wof:name":"Librairie Monfort Sorgeloos",
    "wof:placetype":"venue"
},
  "geometry": {"coordinates":[4.3596558571,50.8199577332],"type":"Point"}
}