{
  "type": "Feature",
  "properties": {
    "addr:full":"Rue Serge De Bruyne 41 Anderlecht Bruxelles-Capitale 1070",
    "addr:housenumber":"41",
    "addr:postcode":"1070",
    "addr:street":"Rue Serge De Bruyne",
    "iso:country":"BE",
    "sg:address":"Rue Serge De Bruyne 41",
    "sg:city":"Anderlecht",
    "sg:orig_category":"Mat\u00e9riel de T\u00e9l\u00e9communication",
    "sg:phone":"+32 2 521 07 70",
    "sg:postcode":"1070",
    "sg:province":"Bruxelles-Capitale",
    "wof:name":"Mouna Trading",
    "wof:placetype":"venue"
},
  "geometry": {"coordinates":[4.3330330849,50.8400421143],"type":"Point"}
}