{
  "type": "Feature",
  "properties": {
    "iso:country":"BE",
    "sg:address":"Deerlijkstraat 30",
    "sg:city":"Anzegem (vichte)",
    "sg:classifiers":[
        {
            "category":"Personal",
            "subcategory":"Sauna",
            "type":"Services"
        }
    ],
    "sg:phone":"+32 56 77 70 69",
    "sg:postcode":"8570",
    "sg:province":"West-Vlaanderen",
    "wof:name":"Sauna Pool Cv",
    "wof:placetype":"venue"
},
  "geometry": {"coordinates":[3.3955581188,50.8402175903],"type":"Point"}
}