{
  "type": "Feature",
  "properties": {
    "iso:country":"BE",
    "sg:address":"Beernemsteenweg 55",
    "sg:city":"Wingene",
    "sg:classifiers":[
        {
            "category":"Retail",
            "subcategory":"Auto Repair",
            "type":"Services"
        }
    ],
    "sg:postcode":"8750",
    "sg:province":"West-Vlaanderen",
    "sg:tags":[
        "automobile",
        "-",
        "wrecking"
    ],
    "wof:name":"Auto Bedrijf Eric De Kort",
    "wof:placetype":"venue"
},
  "geometry": {"coordinates":[5.0394730568,51.6583900452],"type":"Point"}
}