{
  "type": "Feature",
  "properties": {
    "iso:country":"BE",
    "sg:address":"40",
    "sg:city":"Keerbergsesteenweg 3150 Haacht",
    "sg:classifiers":[
        {
            "category":"Autos & Motor Vehicles",
            "subcategory":"Automobile Sales",
            "type":"Retail Goods"
        }
    ],
    "sg:phone":"+32 16 60 58 10",
    "sg:postcode":"40",
    "sg:tags":[
        "equipment",
        "motor-cars",
        "transport"
    ],
    "wof:name":"Garage De Dijle Bvba",
    "wof:placetype":"venue"
},
  "geometry": {"coordinates":[4.6431131363,50.9848442078],"type":"Point"}
}