{
  "type": "Feature",
  "properties": {
    "addr:full":"Markt 1 Rumst Antwerpen 2840",
    "addr:housenumber":"1",
    "addr:postcode":"2840",
    "addr:street":"Markt",
    "iso:country":"BE",
    "sg:address":"Markt 1",
    "sg:city":"Rumst",
    "sg:orig_category":"Openbare veiligheid",
    "sg:phone":"+32 3 888 00 67",
    "sg:postcode":"2840",
    "sg:province":"Antwerpen",
    "wof:name":"Federale Politie",
    "wof:placetype":"venue"
},
  "geometry": {"coordinates":[4.4249429703,51.0771064758],"type":"Point"}
}