{
  "type": "Feature",
  "properties": {
    "addr:full":"Rue De Herve 71 Li\u00e8ge 1 (grivegn\u00e9e) Li\u00e8ge 4030",
    "addr:housenumber":"71;1",
    "addr:postcode":"4030",
    "addr:street":"Rue De Herve",
    "iso:country":"BE",
    "sg:address":"Rue De Herve 71",
    "sg:city":"Li\u00e8ge 1 (grivegn\u00e9e)",
    "sg:classifiers":[
        {
            "category":"Shopping",
            "subcategory":"Florist",
            "type":"Retail Goods"
        }
    ],
    "sg:phone":"+32 4 343 55 11",
    "sg:postcode":"4030",
    "sg:province":"Li\u00e8ge",
    "wof:name":"Corhay J",
    "wof:placetype":"venue"
},
  "geometry": {"coordinates":[5.6049180031,50.6326217651],"type":"Point"}
}