{
  "type": "Feature",
  "properties": {
    "iso:country":"BE",
    "sg:address":"Petermansstraat 33",
    "sg:city":"Beringen (paal)",
    "sg:classifiers":[
        {
            "category":"Professional",
            "subcategory":"Management & Consulting",
            "type":"Services"
        }
    ],
    "sg:phone":"+32 11 42 53 61",
    "sg:postcode":"3583",
    "sg:province":"Limburg",
    "sg:tags":[
        "-",
        "processing",
        "data",
        "consultant"
    ],
    "wof:name":"The Bridge Consulting Bvba",
    "wof:placetype":"venue"
},
  "geometry": {"coordinates":[5.1706700325,51.0389442444],"type":"Point"}
}