{
  "type": "Feature",
  "properties": {
    "iso:country":"BE",
    "sg:address":"Rue De Gourdinne 51",
    "sg:city":"Walcourt (thy-le-ch\u00e2teau)",
    "sg:classifiers":[
        {
            "category":"Retail",
            "subcategory":"Auto Repair",
            "type":"Services"
        }
    ],
    "sg:phone":"+32 71 61 18 36",
    "sg:postcode":"5651",
    "sg:province":"Namur",
    "sg:tags":[
        "garage"
    ],
    "wof:name":"Garage Stillemant & Fils Sprl",
    "wof:placetype":"venue"
},
  "geometry": {"coordinates":[4.4262080193,50.2824401855],"type":"Point"}
}