{
  "type": "Feature",
  "properties": {
    "iso:country":"BE",
    "sg:address":"Smedenstraat 74",
    "sg:city":"Knokke-heist",
    "sg:orig_category":"Caf\u00e9s Taxi's Taxi's speciale diensten",
    "sg:phone":"+32 50 60 60 90",
    "sg:postcode":"8300",
    "sg:province":"West-Vlaanderen",
    "wof:name":"In De Smisse",
    "wof:placetype":"venue"
},
  "geometry": {"coordinates":[3.2882258892,51.3382911682],"type":"Point"}
}