{
  "type": "Feature",
  "properties": {
    "addr:full":"Abelenstraat 15 Hasselt Limburg 3500",
    "addr:housenumber":"15",
    "addr:postcode":"3500",
    "addr:street":"Abelenstraat",
    "iso:country":"BE",
    "sg:address":"Abelenstraat 15",
    "sg:city":"Hasselt",
    "sg:classifiers":[
        {
            "category":"Taxi",
            "type":"Transportation"
        }
    ],
    "sg:phone":"+32 11 27 20 06",
    "sg:postcode":"3500",
    "sg:province":"Limburg",
    "sg:tags":[
        "taxicab"
    ],
    "wof:name":"Freddy Taxi",
    "wof:placetype":"venue"
},
  "geometry": {"coordinates":[5.328250885,50.9246788025],"type":"Point"}
}