{
  "type": "Feature",
  "properties": {
    "iso:country":"BE",
    "sg:address":"Veurnseweg 535",
    "sg:city":"Ieper",
    "sg:orig_category":"Banken and kredietinstellingen",
    "sg:phone":"+32 57 42 37 77",
    "sg:postcode":"8906",
    "sg:province":"West-Vlaanderen",
    "wof:name":"Kbc",
    "wof:placetype":"venue"
},
  "geometry": {"coordinates":[2.8162069321,50.885761261],"type":"Point"}
}