{
  "type": "Feature",
  "properties": {
    "addr:full":"Rue Du Centre 3 Li\u00e8ge 1 (sclessin) Li\u00e8ge 4000",
    "addr:housenumber":"3;1",
    "addr:postcode":"4000",
    "addr:street":"Rue Du Centre;Sclessin Lie\u0300Ge",
    "iso:country":"BE",
    "sg:address":"Rue Du Centre 3",
    "sg:city":"Li\u00e8ge 1 (sclessin)",
    "sg:classifiers":[
        {
            "category":"Social Services",
            "type":"Services"
        }
    ],
    "sg:phone":"+32 4 253 37 14",
    "sg:postcode":"4000",
    "sg:province":"Li\u00e8ge",
    "wof:name":"Ya Basta! Asbl",
    "wof:placetype":"venue"
},
  "geometry": {"coordinates":[5.5530610085,50.6097602844],"type":"Point"}
}