{
  "type": "Feature",
  "properties": {
    "addr:full":"Rozendalestraat 65 Wingene West-Vlaanderen 8750",
    "addr:housenumber":"65",
    "addr:postcode":"8750",
    "addr:street":"Rozendalestraat",
    "iso:country":"BE",
    "sg:address":"Rozendalestraat 65",
    "sg:city":"Wingene",
    "sg:orig_category":"Enseignement maternel and primaire",
    "sg:phone":"+32 51 65 75 78",
    "sg:postcode":"8750",
    "sg:province":"West-Vlaanderen",
    "wof:name":"Vrije Basisschool",
    "wof:placetype":"venue"
},
  "geometry": {"coordinates":[3.2561581135,51.076385498],"type":"Point"}
}