{
  "type": "Feature",
  "properties": {
    "iso:country":"BE",
    "sg:address":"Emiel Hertecantlaan 41",
    "sg:city":"Berlare",
    "sg:classifiers":[
        {
            "category":"Communications",
            "subcategory":"Radio Station",
            "type":"Services"
        }
    ],
    "sg:phone":"+32 52 20 06 33",
    "sg:postcode":"9290",
    "sg:province":"Oost-Vlaanderen",
    "sg:tags":[
        "local"
    ],
    "wof:name":"Top Radio Primera",
    "wof:placetype":"venue"
},
  "geometry": {"coordinates":[4.0059380531,51.0170783997],"type":"Point"}
}