{
  "type": "Feature",
  "properties": {
    "addr:full":"Rue Jules Hagnoul 69 Orp-jauche Brabant Wallon 1350",
    "addr:housenumber":"69",
    "addr:postcode":"1350",
    "addr:street":"Rue Jules Hagnoul",
    "iso:country":"BE",
    "sg:address":"Rue Jules Hagnoul 69",
    "sg:city":"Orp-jauche",
    "sg:orig_category":"Peinture. Rev\u00eatements pour sols and murs",
    "sg:phone":"+32 19 63 33 00",
    "sg:postcode":"1350",
    "sg:province":"Brabant Wallon",
    "wof:name":"Deville",
    "wof:placetype":"venue"
},
  "geometry": {"coordinates":[4.97920084,50.6738891602],"type":"Point"}
}