{
  "type": "Feature",
  "properties": {
    "addr:full":"Berkenstraat 6 Ruiselede West-Vlaanderen 8755",
    "addr:housenumber":"6",
    "addr:postcode":"8755",
    "addr:street":"Berkenstraat",
    "iso:country":"BE",
    "sg:address":"Berkenstraat 6",
    "sg:city":"Ruiselede",
    "sg:classifiers":[
        {
            "category":"Building & Trades",
            "subcategory":"Landscaping Services",
            "type":"Services"
        }
    ],
    "sg:phone":"+32 51 68 93 42",
    "sg:postcode":"8755",
    "sg:province":"West-Vlaanderen",
    "sg:tags":[
        "gardening",
        "garden",
        "maintenance"
    ],
    "wof:name":"Lampaert F",
    "wof:placetype":"venue"
},
  "geometry": {"coordinates":[3.3893289566,51.0406417847],"type":"Point"}
}