{
  "type": "Feature",
  "properties": {
    "addr:full":"De Locht 33 Tongeren Limburg 3700",
    "addr:housenumber":"33",
    "addr:postcode":"3700",
    "addr:street":"De Locht",
    "iso:country":"BE",
    "sg:address":"De Locht 33",
    "sg:city":"Tongeren",
    "sg:classifiers":[
        {
            "category":"Retail",
            "subcategory":"Veterinary Services",
            "type":"Services"
        }
    ],
    "sg:phone":"+32 12 23 07 51",
    "sg:postcode":"3700",
    "sg:province":"Limburg",
    "sg:tags":[
        "veterinarian"
    ],
    "wof:name":"Wybo J",
    "wof:placetype":"venue"
},
  "geometry": {"coordinates":[5.445040226,50.7894592285],"type":"Point"}
}