{
  "type": "Feature",
  "properties": {
    "iso:country":"BE",
    "sg:address":"Rue Du Boisrond 22",
    "sg:city":"Habay",
    "sg:orig_category":"Airconditioning and ventilatie",
    "sg:phone":"+32 63 42 44 66",
    "sg:postcode":"6720",
    "sg:province":"Luxembourg",
    "wof:name":"E.r.t.b.",
    "wof:placetype":"venue"
},
  "geometry": {"coordinates":[5.6468100548,49.7278633118],"type":"Point"}
}