{
  "type": "Feature",
  "properties": {
    "addr:full":"Mechelsesteenweg 402a Herent Vlaams-Brabant 3020",
    "addr:housenumber":"402a",
    "addr:postcode":"3020",
    "addr:street":"Mechelsesteenweg",
    "iso:country":"BE",
    "sg:address":"Mechelsesteenweg 402a",
    "sg:city":"Herent",
    "sg:classifiers":[
        {
            "category":"Home & Garden",
            "subcategory":"Household Appliances",
            "type":"Retail Goods"
        }
    ],
    "sg:phone":"+32 16 22 29 27",
    "sg:postcode":"3020",
    "sg:province":"Vlaams-Brabant",
    "sg:tags":[
        "repair",
        "mainten",
        "-",
        "electric"
    ],
    "wof:name":"Van Essche P",
    "wof:placetype":"venue"
},
  "geometry": {"coordinates":[4.6719059944,50.9052467346],"type":"Point"}
}