{
  "type": "Feature",
  "properties": {
    "iso:country":"BE",
    "sg:address":"Terhulpensesteenweg 475",
    "sg:city":"Overijse",
    "sg:classifiers":[
        {
            "category":"Health Services",
            "subcategory":"Health Practitioner",
            "type":"Services"
        }
    ],
    "sg:phone":"+32 2 688 00 25",
    "sg:postcode":"3090",
    "sg:province":"Vlaams-Brabant",
    "sg:tags":[
        "physiotherapist"
    ],
    "wof:name":"Van Meines Henri",
    "wof:placetype":"venue"
},
  "geometry": {"coordinates":[4.5366621017,50.7620811462],"type":"Point"}
}