{
  "type": "Feature",
  "properties": {
    "addr:full":"Bergendriesstraat 85 Lokeren Oost-Vlaanderen 9160",
    "addr:housenumber":"85",
    "addr:postcode":"9160",
    "addr:street":"Bergendriesstraat",
    "iso:country":"BE",
    "sg:address":"Bergendriesstraat 85",
    "sg:city":"Lokeren",
    "sg:orig_category":"Herstelling and restauratie van meubelen",
    "sg:phone":"+32 9 348 36 57",
    "sg:postcode":"9160",
    "sg:province":"Oost-Vlaanderen",
    "wof:name":"Robert Van De Wiele",
    "wof:placetype":"venue"
},
  "geometry": {"coordinates":[3.9880619049,51.1126174927],"type":"Point"}
}