{
  "type": "Feature",
  "properties": {
    "iso:country":"BE",
    "sg:address":"Stationsstraat 60",
    "sg:city":"Oudenaarde",
    "sg:classifiers":[
        {
            "category":"Travel",
            "subcategory":"Hotels & Motels",
            "type":"Entertainment"
        }
    ],
    "sg:phone":"+32 55 31 84 88",
    "sg:postcode":"9700",
    "sg:province":"Oost-Vlaanderen",
    "sg:tags":[
        "caf\u00e9s"
    ],
    "wof:name":"Hotel Tijl",
    "wof:placetype":"venue"
},
  "geometry": {"coordinates":[3.6008470058,50.8495368958],"type":"Point"}
}