{
  "type": "Feature",
  "properties": {
    "addr:full":"Amerikalei 219 Antwerpen Antwerpen 2000",
    "addr:housenumber":"219",
    "addr:postcode":"2000",
    "addr:street":"Amerikalei",
    "iso:country":"BE",
    "sg:address":"Amerikalei 219",
    "sg:city":"Antwerpen",
    "sg:classifiers":[
        {
            "category":"Building & Trades",
            "subcategory":"Pest Control",
            "type":"Services"
        }
    ],
    "sg:phone":"+32 3 248 34 20",
    "sg:postcode":"2000",
    "sg:province":"Antwerpen",
    "sg:tags":[
        "painting",
        "contractor"
    ],
    "wof:name":"Van Der Borght A",
    "wof:placetype":"venue"
},
  "geometry": {"coordinates":[4.3900837898,51.204498291],"type":"Point"}
}