{
  "type": "Feature",
  "properties": {
    "iso:country":"BE",
    "sg:address":"Place Des D\u00c9port\u00c9s 4",
    "sg:city":"Li\u00c8ge",
    "sg:orig_category":"Plomberie, chauffage and installations sanitaires",
    "sg:phone":"+32 4 342 91 66",
    "sg:postcode":"4000",
    "sg:province":"Li\u00e8ge",
    "wof:name":"Moubayed Ousama",
    "wof:placetype":"venue"
},
  "geometry": {"coordinates":[5.5861611366,50.6481781006],"type":"Point"}
}