{
  "type": "Feature",
  "properties": {
    "iso:country":"BE",
    "sg:address":"Place Albert Ier 15",
    "sg:city":"Aubel",
    "sg:orig_category":"Pain, p\u00e2tisseries and confiseries",
    "sg:phone":"+32 87 68 76 90",
    "sg:postcode":"4880",
    "sg:province":"Li\u00e8ge",
    "wof:name":"P\u00c2tisserie Delhalle",
    "wof:placetype":"venue"
},
  "geometry": {"coordinates":[5.8583078384,50.7041244507],"type":"Point"}
}