{
  "type": "Feature",
  "properties": {
    "addr:full":"Hermann Debrouxlaan 48 - Brussels Bruxelles-Capitale 1160",
    "addr:housenumber":"48",
    "addr:postcode":"1160",
    "addr:street":"Debrouxlaan",
    "iso:country":"BE",
    "sg:address":"Hermann Debrouxlaan 48 -",
    "sg:city":"Brussels",
    "sg:classifiers":[
        {
            "category":"Professional",
            "subcategory":"Art Services",
            "type":"Services"
        }
    ],
    "sg:phone":"+32 2 679 17 11",
    "sg:postcode":"1160",
    "sg:province":"Bruxelles-Capitale",
    "sg:tags":[
        "export-import"
    ],
    "wof:name":"Royal Netherlands Embassy",
    "wof:placetype":"venue"
},
  "geometry": {"coordinates":[4.4330787659,50.8135108948],"type":"Point"}
}