{
  "type": "Feature",
  "properties": {
    "addr:full":"Rue Du Parc Industriel 6 Waremme Li\u00e8ge 4300",
    "addr:housenumber":"6",
    "addr:postcode":"4300",
    "addr:street":"Rue Du Parc Industriel",
    "iso:country":"BE",
    "sg:address":"Rue Du Parc Industriel 6",
    "sg:city":"Waremme",
    "sg:orig_category":"Fresh Vegetables, Lettuces, And Potatoes",
    "sg:phone":"+32 19 32 77 07",
    "sg:postcode":"4300",
    "sg:province":"Li\u00e8ge",
    "wof:name":"L'yerne S.c.r.l.",
    "wof:placetype":"venue"
},
  "geometry": {"coordinates":[5.2679729462,50.6912498474],"type":"Point"}
}