{
  "type": "Feature",
  "properties": {
    "iso:country":"BE",
    "sg:address":"Charleroise Steenweg 228",
    "sg:city":"Sint-gillis/saint-gilles",
    "sg:orig_category":"Diverse zakelijke dienstverlening",
    "sg:phone":"+32 2 534 78 12",
    "sg:postcode":"1060",
    "sg:province":"Bruxelles-Capitale",
    "wof:name":"Pierre Gortz",
    "wof:placetype":"venue"
},
  "geometry": {"coordinates":[4.354268074,50.8236427307],"type":"Point"}
}