{
  "type": "Feature",
  "properties": {
    "addr:full":"Burgemeester Potiaulaan 36 Dendermonde Oost-Vlaanderen 9200",
    "addr:housenumber":"36",
    "addr:postcode":"9200",
    "addr:street":"Burgemeester Potiaulaan;Oost-Vlaanderen",
    "iso:country":"BE",
    "sg:address":"Burgemeester Potiaulaan 36",
    "sg:city":"Dendermonde",
    "sg:orig_category":"Kapsalons",
    "sg:phone":"+32 52 21 39 85",
    "sg:postcode":"9200",
    "sg:province":"Oost-Vlaanderen",
    "wof:name":"Coiffure Nina Style",
    "wof:placetype":"venue"
},
  "geometry": {"coordinates":[4.1123170853,51.0201568604],"type":"Point"}
}