{
  "type": "Feature",
  "properties": {
    "addr:full":"Avenue L Gribaumont 27 Sint-pieters-woluwe/woluwe-sai Bruxelles-Capitale 1150",
    "addr:housenumber":"27",
    "addr:postcode":"1150",
    "addr:street":"Avenue L Gribaumont",
    "iso:country":"BE",
    "sg:address":"Avenue L Gribaumont 27",
    "sg:city":"Sint-pieters-woluwe/woluwe-sai",
    "sg:orig_category":"Bloemen and planten",
    "sg:phone":"+32 2 779 28 03",
    "sg:postcode":"1150",
    "sg:province":"Bruxelles-Capitale",
    "wof:name":"Renato",
    "wof:placetype":"venue"
},
  "geometry": {"coordinates":[4.4160208702,50.8374671936],"type":"Point"}
}