{
  "type": "Feature",
  "properties": {
    "iso:country":"BE",
    "sg:address":"Route Provinciale 35",
    "sg:city":"Tournai",
    "sg:orig_category":"Pain, p\u00e2tisseries and confiseries",
    "sg:phone":"+32 69 23 24 75",
    "sg:postcode":"7543",
    "sg:province":"Hainaut",
    "wof:name":"Au Vieux Fournil",
    "wof:placetype":"venue"
},
  "geometry": {"coordinates":[3.4210779667,50.643737793],"type":"Point"}
}