{
  "type": "Feature",
  "properties": {
    "iso:country":"BE",
    "sg:address":"Passtraat 212",
    "sg:city":"Sint-niklaas",
    "sg:orig_category":"Herstellingen and onderhoud van auto's",
    "sg:phone":"+32 3 776 68 62",
    "sg:postcode":"9100",
    "sg:province":"Oost-Vlaanderen",
    "wof:name":"Roland Rooselaer",
    "wof:placetype":"venue"
},
  "geometry": {"coordinates":[4.1736187935,51.1673316956],"type":"Point"}
}