{
  "type": "Feature",
  "properties": {
    "addr:full":"Franklin Rooseveltlaan 348-p Gent Oost-Vlaanderen 9000",
    "addr:housenumber":"348-p",
    "addr:postcode":"9000",
    "addr:street":"Franklin Rooseveltlaan;Oost-Vlaanderen",
    "iso:country":"BE",
    "sg:address":"Franklin Rooseveltlaan 348-p",
    "sg:city":"Gent",
    "sg:classifiers":[
        {
            "category":"Professional",
            "type":"Services"
        }
    ],
    "sg:phone":"+32 9 265 02 28",
    "sg:postcode":"9000",
    "sg:province":"Oost-Vlaanderen",
    "sg:tags":[
        "surveyor",
        "-",
        "valuer"
    ],
    "wof:name":"Wuylens P",
    "wof:placetype":"venue"
},
  "geometry": {"coordinates":[3.7285690308,51.0556335449],"type":"Point"}
}