{
  "type": "Feature",
  "properties": {
    "addr:full":"Rue De L'harmonie 3 Verviers Li\u00e8ge 4800",
    "addr:housenumber":"3",
    "addr:postcode":"4800",
    "addr:street":"Rue De L'Harmonie",
    "iso:country":"BE",
    "sg:address":"Rue De L'harmonie 3",
    "sg:city":"Verviers",
    "sg:orig_category":"Non-Classified Establishments",
    "sg:phone":"+32 87 34 00 02",
    "sg:postcode":"4800",
    "sg:province":"Li\u00e8ge",
    "wof:name":"Efde Chocolatier",
    "wof:placetype":"venue"
},
  "geometry": {"coordinates":[5.8755340576,50.5953216553],"type":"Point"}
}