{
  "type": "Feature",
  "properties": {
    "addr:full":"Gemeentestraat 96 Lubbeek (linden) Vlaams-Brabant 3210",
    "addr:housenumber":"96",
    "addr:postcode":"3210",
    "addr:street":"Gemeentestraat",
    "iso:country":"BE",
    "sg:address":"Gemeentestraat 96",
    "sg:city":"Lubbeek (linden)",
    "sg:classifiers":[
        {
            "category":"Insurance",
            "subcategory":"Insurance Agent",
            "type":"Services"
        }
    ],
    "sg:phone":"+32 16 62 20 77",
    "sg:postcode":"3210",
    "sg:province":"Vlaams-Brabant",
    "sg:tags":[
        "broker"
    ],
    "wof:name":"Meys Rigo Bvba",
    "wof:placetype":"venue"
},
  "geometry": {"coordinates":[4.7755122185,50.8925018311],"type":"Point"}
}