{
  "type": "Feature",
  "properties": {
    "iso:country":"BE",
    "sg:address":"Rue Des Cailloux 1-3",
    "sg:city":"Rixensart",
    "sg:classifiers":[
        {
            "category":"Home & Garden",
            "subcategory":"Home Furnishings",
            "type":"Retail Goods"
        }
    ],
    "sg:phone":"+32 2 653 89 43",
    "sg:postcode":"1330",
    "sg:province":"Brabant Wallon",
    "sg:tags":[
        "-",
        "bed",
        "mattress"
    ],
    "wof:name":"Van Den Wyngaert",
    "wof:placetype":"venue"
},
  "geometry": {"coordinates":[4.510447979,50.7095870972],"type":"Point"}
}