{
  "type": "Feature",
  "properties": {
    "iso:country":"BE",
    "sg:address":"Lotelinglaan 57",
    "sg:city":"Zoersel (halle)",
    "sg:classifiers":[
        {
            "category":"Shopping",
            "subcategory":"Bicycles & Sporting Goods",
            "type":"Retail Goods"
        }
    ],
    "sg:phone":"+32 3 383 36 17",
    "sg:postcode":"2980",
    "sg:province":"Antwerpen",
    "sg:tags":[
        "-"
    ],
    "wof:name":"Garrousse W",
    "wof:placetype":"venue"
},
  "geometry": {"coordinates":[4.6431732178,51.2412109375],"type":"Point"}
}