{
  "type": "Feature",
  "properties": {
    "iso:country":"BE",
    "sg:address":"Tarantellastraat 20",
    "sg:city":"Anderlecht",
    "sg:orig_category":"Sportclubs",
    "sg:phone":"+32 2 520 13 43",
    "sg:postcode":"1070",
    "sg:province":"Bruxelles-Capitale",
    "wof:name":"T.c. Ring",
    "wof:placetype":"venue"
},
  "geometry": {"coordinates":[4.2950239182,50.8467521667],"type":"Point"}
}