{
  "type": "Feature",
  "properties": {
    "addr:full":"Provinciebaan 34 Laarne (kalken) Oost-Vlaanderen 9270",
    "addr:housenumber":"34",
    "addr:postcode":"9270",
    "addr:street":"Provinciebaan",
    "iso:country":"BE",
    "sg:address":"Provinciebaan 34",
    "sg:city":"Laarne (kalken)",
    "sg:classifiers":[
        {
            "category":"Freight",
            "type":"Transportation"
        }
    ],
    "sg:phone":"+32 9 369 27 64",
    "sg:postcode":"9270",
    "sg:province":"Oost-Vlaanderen",
    "sg:tags":[
        "-",
        "transport"
    ],
    "wof:name":"Beyl Transport Bvba",
    "wof:placetype":"venue"
},
  "geometry": {"coordinates":[3.9023659229,51.0305480957],"type":"Point"}
}