{
  "type": "Feature",
  "properties": {
    "addr:full":"Olmstraat 68a Waregem West-Vlaanderen 8790",
    "addr:housenumber":"68a",
    "addr:postcode":"8790",
    "addr:street":"Olmstraat",
    "iso:country":"BE",
    "sg:address":"Olmstraat 68a",
    "sg:city":"Waregem",
    "sg:classifiers":[
        {
            "category":"Professional",
            "subcategory":"Engineering",
            "type":"Services"
        }
    ],
    "sg:phone":"+32 56 61 54 80",
    "sg:postcode":"8790",
    "sg:province":"West-Vlaanderen",
    "sg:tags":[
        "technical",
        "industrial",
        "-",
        "subcontracting"
    ],
    "wof:name":"Transit East Europe",
    "wof:placetype":"venue"
},
  "geometry": {"coordinates":[3.4256598949,50.8902740479],"type":"Point"}
}