{
  "type": "Feature",
  "properties": {
    "iso:country":"BE",
    "sg:address":"Iepersestraat 14",
    "sg:city":"Harelbeke",
    "sg:classifiers":[
        {
            "category":"Building & Trades",
            "subcategory":"Construction",
            "type":"Services"
        }
    ],
    "sg:phone":"+32 56 21 43 10",
    "sg:postcode":"8530",
    "sg:province":"West-Vlaanderen",
    "sg:tags":[
        "carpenter"
    ],
    "wof:name":"Depamelaere G",
    "wof:placetype":"venue"
},
  "geometry": {"coordinates":[3.3302209377,50.8338088989],"type":"Point"}
}