{
  "type": "Feature",
  "properties": {
    "iso:country":"BE",
    "sg:address":"Sint-annalaan 126",
    "sg:city":"Aalst",
    "sg:orig_category":"Speelgoed",
    "sg:phone":"+32 53 78 15 42",
    "sg:postcode":"9300",
    "sg:province":"Oost-Vlaanderen",
    "wof:name":"Game Mania",
    "wof:placetype":"venue"
},
  "geometry": {"coordinates":[4.0266361237,50.9411354065],"type":"Point"}
}