{
  "type": "Feature",
  "properties": {
    "iso:country":"BE",
    "sg:address":"All\u00c9e Des Bleuets 15",
    "sg:city":"Nivelles",
    "sg:orig_category":"Cr\u00e9dit \u00e0 la consommation",
    "sg:phone":"+32 67 84 37 30",
    "sg:postcode":"1400",
    "sg:province":"Brabant Wallon",
    "wof:name":"Fikass",
    "wof:placetype":"venue"
},
  "geometry": {"coordinates":[4.3466320038,50.6039123535],"type":"Point"}
}