{
  "type": "Feature",
  "properties": {
    "addr:full":"Zuidkaai 1 Izegem West-Vlaanderen 8870",
    "addr:housenumber":"1",
    "addr:postcode":"8870",
    "addr:street":"Zuidkaai",
    "iso:country":"BE",
    "sg:address":"Zuidkaai 1",
    "sg:city":"Izegem",
    "sg:classifiers":[
        {
            "category":"Airport",
            "subcategory":"International",
            "type":"Transportation"
        }
    ],
    "sg:phone":"+32 51 30 77 22",
    "sg:postcode":"8870",
    "sg:province":"West-Vlaanderen",
    "sg:tags":[
        "-",
        "transport"
    ],
    "wof:name":"Ameye J-p Bvba",
    "wof:placetype":"venue"
},
  "geometry": {"coordinates":[3.2190771103,50.9216194153],"type":"Point"}
}