{
  "type": "Feature",
  "properties": {
    "addr:full":"Rue Montoyer 18b Bruxelles Bruxelles-Capitale 1000",
    "addr:housenumber":"18b",
    "addr:postcode":"1000",
    "addr:street":"Rue Montoyer",
    "iso:country":"BE",
    "sg:address":"Rue Montoyer 18b",
    "sg:city":"Bruxelles",
    "sg:classifiers":[
        {
            "category":"Banks & Credit Unions",
            "subcategory":"Investment Brokerage",
            "type":"Services"
        }
    ],
    "sg:phone":"+32 2 280 29 20",
    "sg:postcode":"1000",
    "sg:province":"Bruxelles-Capitale",
    "sg:tags":[
        "development",
        "economic",
        "institution"
    ],
    "wof:name":"Provincia Di Treviso",
    "wof:placetype":"venue"
},
  "geometry": {"coordinates":[4.3696198463,50.8413848877],"type":"Point"}
}