{
  "type": "Feature",
  "properties": {
    "addr:full":"Sint-truidersteenweg 144 Borgloon Limburg 3840",
    "addr:housenumber":"144",
    "addr:postcode":"3840",
    "addr:street":"Sint-Truidersteenweg",
    "iso:country":"BE",
    "sg:address":"Sint-truidersteenweg 144",
    "sg:city":"Borgloon",
    "sg:classifiers":[
        {
            "category":"Retail",
            "subcategory":"Auto Repair",
            "type":"Services"
        }
    ],
    "sg:phone":"+32 12 74 17 24",
    "sg:postcode":"3840",
    "sg:province":"Limburg",
    "sg:tags":[
        "garage"
    ],
    "wof:name":"Baeten (garage)",
    "wof:placetype":"venue"
},
  "geometry": {"coordinates":[5.3210082054,50.8049087524],"type":"Point"}
}