{
  "type": "Feature",
  "properties": {
    "iso:country":"BE",
    "sg:address":"Stationsstraat 25",
    "sg:city":"Lanaken",
    "sg:orig_category":"Speelgoed Verlichting and huishoudartikelen",
    "sg:phone":"+32 89 71 42 38",
    "sg:postcode":"3620",
    "sg:province":"Limburg",
    "wof:name":"Dello",
    "wof:placetype":"venue"
},
  "geometry": {"coordinates":[5.6504840851,50.8884353638],"type":"Point"}
}