{
  "type": "Feature",
  "properties": {
    "addr:full":"Lindenstrasse 30 B\u00dctgenbach/b\u00dctgenbach Li\u00e8ge 4750",
    "addr:housenumber":"30",
    "addr:postcode":"4750",
    "addr:street":"Lindenstrasse",
    "iso:country":"BE",
    "sg:address":"Lindenstrasse 30",
    "sg:city":"B\u00dctgenbach/b\u00dctgenbach",
    "sg:orig_category":"Dameskledingzaken",
    "sg:phone":"+32 80 44 50 88",
    "sg:postcode":"4750",
    "sg:province":"Li\u00e8ge",
    "wof:name":"Haus Christine",
    "wof:placetype":"venue"
},
  "geometry": {"coordinates":[6.2206501961,50.457408905],"type":"Point"}
}