{
  "type": "Feature",
  "properties": {
    "iso:country":"BE",
    "sg:address":"Kleine Zouterdreef 4",
    "sg:city":"Aalter",
    "sg:orig_category":"Plomberie, chauffage and installations sanitaires",
    "sg:phone":"+32 9 374 37 66",
    "sg:postcode":"9880",
    "sg:province":"Oost-Vlaanderen",
    "wof:name":"Koen Windels",
    "wof:placetype":"venue"
},
  "geometry": {"coordinates":[3.3685870171,51.0917015076],"type":"Point"}
}