{
  "type": "Feature",
  "properties": {
    "addr:full":"Avenue Schlogel 92 Ciney Namur 5590",
    "addr:housenumber":"92",
    "addr:postcode":"5590",
    "addr:street":"Avenue Schlogel",
    "iso:country":"BE",
    "sg:address":"Avenue Schlogel 92",
    "sg:city":"Ciney",
    "sg:classifiers":[
        {
            "category":"Professional",
            "subcategory":"Lawyer & Legal Services",
            "type":"Services"
        }
    ],
    "sg:phone":"+32 83 21 10 16",
    "sg:postcode":"5590",
    "sg:province":"Namur",
    "sg:tags":[
        "notary"
    ],
    "wof:name":"Van Bever P",
    "wof:placetype":"venue"
},
  "geometry": {"coordinates":[5.1106171608,50.2996444702],"type":"Point"}
}