{
  "type": "Feature",
  "properties": {
    "iso:country":"BE",
    "sg:address":"President Kennedypark 16b",
    "sg:city":"Kortrijk",
    "sg:classifiers":[
        {
            "category":"Professional",
            "subcategory":"Engineering",
            "type":"Services"
        }
    ],
    "sg:phone":"+32 56 20 30 76",
    "sg:postcode":"8500",
    "sg:province":"West-Vlaanderen",
    "sg:tags":[
        "-"
    ],
    "wof:name":"D & V Consulting Nv",
    "wof:placetype":"venue"
},
  "geometry": {"coordinates":[3.272521019,50.8000564575],"type":"Point"}
}