{
  "type": "Feature",
  "properties": {
    "iso:country":"BE",
    "sg:address":"Rue Du Touquet 267ba",
    "sg:city":"Komen-waasten/comines-warneton",
    "sg:orig_category":"Installation \u00e9lectrique r\u00e9sidentielle",
    "sg:phone":"+32 56 58 77 95",
    "sg:postcode":"7784",
    "sg:province":"Hainaut",
    "wof:name":"Henrik Bruyneel",
    "wof:placetype":"venue"
},
  "geometry": {"coordinates":[2.9210169315,50.7134780884],"type":"Point"}
}