{
  "type": "Feature",
  "properties": {
    "iso:country":"BE",
    "sg:address":"Biezenstraat 18",
    "sg:city":"Ninove",
    "sg:classifiers":[
        {
            "category":"Travel",
            "subcategory":"Travel Agent",
            "type":"Entertainment"
        }
    ],
    "sg:phone":"+32 54 32 24 70",
    "sg:postcode":"9400",
    "sg:province":"Oost-Vlaanderen",
    "sg:tags":[
        "voyage",
        "de",
        "agences",
        "flash",
        "holidays",
        "plus"
    ],
    "wof:name":"Flash Travel",
    "wof:placetype":"venue"
},
  "geometry": {"coordinates":[4.0218410492,50.8371086121],"type":"Point"}
}