{
  "type": "Feature",
  "properties": {
    "addr:full":"Stelen 74 Geel Antwerpen 2440",
    "addr:housenumber":"74",
    "addr:postcode":"2440",
    "addr:street":"Stelen",
    "iso:country":"BE",
    "sg:address":"Stelen 74",
    "sg:city":"Geel",
    "sg:classifiers":[
        {
            "category":"Building & Trades",
            "subcategory":"Landscaping Services",
            "type":"Services"
        }
    ],
    "sg:phone":"+32 14 86 77 66",
    "sg:postcode":"2440",
    "sg:province":"Antwerpen",
    "sg:tags":[
        "gardening",
        "garden",
        "maintenance"
    ],
    "wof:name":"Groencreatie Vermeer Bvba",
    "wof:placetype":"venue"
},
  "geometry": {"coordinates":[4.9846282005,51.1540603638],"type":"Point"}
}