{
  "type": "Feature",
  "properties": {
    "addr:full":"Brugstraat 32 Hoegaarden Vlaams-Brabant 3321",
    "addr:housenumber":"32",
    "addr:postcode":"3321",
    "addr:street":"Brugstraat",
    "iso:country":"BE",
    "sg:address":"Brugstraat 32",
    "sg:city":"Hoegaarden",
    "sg:orig_category":"Rundveehouders",
    "sg:phone":"+32 16 76 72 59",
    "sg:postcode":"3321",
    "sg:province":"Vlaams-Brabant",
    "wof:name":"Joseph Steenwinckels",
    "wof:placetype":"venue"
},
  "geometry": {"coordinates":[4.9200019836,50.7681655884],"type":"Point"}
}