{
  "type": "Feature",
  "properties": {
    "addr:full":"Lindedreef 18 Zoersel Antwerpen 2980",
    "addr:housenumber":"18",
    "addr:postcode":"2980",
    "addr:street":"Lindedreef",
    "iso:country":"BE",
    "sg:address":"Lindedreef 18",
    "sg:city":"Zoersel",
    "sg:orig_category":"Enseignement maternel and primaire",
    "sg:phone":"+32 3 383 50 30",
    "sg:postcode":"2980",
    "sg:province":"Antwerpen",
    "wof:name":"Vrije Basisschool",
    "wof:placetype":"venue"
},
  "geometry": {"coordinates":[4.6470170021,51.2408103943],"type":"Point"}
}