{
  "type": "Feature",
  "properties": {
    "addr:full":"La-barri\u00c8re 6 Vresse-sur-semois Namur 5550",
    "addr:housenumber":"6",
    "addr:postcode":"vresse-sur-semois;5550",
    "addr:street":"La-Barrie\u0300Re",
    "iso:country":"BE",
    "sg:address":"La-barri\u00c8re 6",
    "sg:city":"Vresse-sur-semois",
    "sg:orig_category":"Woningbouw",
    "sg:phone":"+32 61 50 01 51",
    "sg:postcode":"5550",
    "sg:province":"Namur",
    "wof:name":"Charles Copine",
    "wof:placetype":"venue"
},
  "geometry": {"coordinates":[4.8923392296,49.9105453491],"type":"Point"}
}