{
  "type": "Feature",
  "properties": {
    "iso:country":"BE",
    "sg:address":"Sint-geertruistraat 126",
    "sg:city":"Tongeren",
    "sg:orig_category":"Elektrische installaties voor woningen",
    "sg:phone":"+32 12 23 34 49",
    "sg:postcode":"3700",
    "sg:province":"Limburg",
    "wof:name":"John Proesmans",
    "wof:placetype":"venue"
},
  "geometry": {"coordinates":[5.4505610466,50.8108940125],"type":"Point"}
}