{
  "type": "Feature",
  "properties": {
    "addr:full":"De Royaertstraat 3 Diksmuide West-Vlaanderen 8600",
    "addr:housenumber":"3",
    "addr:postcode":"8600",
    "addr:street":"Royaertstraat",
    "iso:country":"BE",
    "sg:address":"De Royaertstraat 3",
    "sg:city":"Diksmuide",
    "sg:orig_category":"Erotische Etablissementen",
    "sg:phone":"+32 51 50 30 15",
    "sg:postcode":"8600",
    "sg:province":"West-Vlaanderen",
    "wof:name":"Eric Seurynck",
    "wof:placetype":"venue"
},
  "geometry": {"coordinates":[2.866147995,51.0273323059],"type":"Point"}
}