{
  "type": "Feature",
  "properties": {
    "addr:full":"Edward Staintonstraat 52 Heusden-zolder (heusden) Limburg 3550",
    "addr:housenumber":"52",
    "addr:postcode":"3550",
    "addr:street":"Staintonstraat",
    "iso:country":"BE",
    "sg:address":"Edward Staintonstraat 52",
    "sg:city":"Heusden-zolder (heusden)",
    "sg:classifiers":[
        {
            "category":"Food & Beverages",
            "subcategory":"Groceries & Convenience Stores",
            "type":"Retail Goods"
        }
    ],
    "sg:phone":"+32 11 57 18 82",
    "sg:postcode":"3550",
    "sg:province":"Limburg",
    "sg:tags":[
        "grocer"
    ],
    "wof:name":"Balci Serena",
    "wof:placetype":"venue"
},
  "geometry": {"coordinates":[5.3061699867,51.0394821167],"type":"Point"}
}