{
  "type": "Feature",
  "properties": {
    "addr:full":"Avenue Du Hoef 19 Bruxelles (uccle) Bruxelles-Capitale 1180",
    "addr:housenumber":"19",
    "addr:postcode":"1180",
    "addr:street":"Avenue Du Hoef",
    "iso:country":"BE",
    "sg:address":"Avenue Du Hoef 19",
    "sg:city":"Bruxelles (uccle)",
    "sg:orig_category":"Non-Classified Establishments",
    "sg:phone":"+32 2 375 44 46",
    "sg:postcode":"1180",
    "sg:province":"Bruxelles-Capitale",
    "wof:name":"Buroshop",
    "wof:placetype":"venue"
},
  "geometry": {"coordinates":[4.3596258163,50.8052749634],"type":"Point"}
}