{
  "type": "Feature",
  "properties": {
    "iso:country":"BE",
    "sg:address":"Zwanestraat 11",
    "sg:city":"Tielt",
    "sg:classifiers":[
        {
            "category":"Arena",
            "subcategory":"Sports Club",
            "type":"Entertainment"
        }
    ],
    "sg:phone":"+32 51 40 35 13",
    "sg:postcode":"8700",
    "sg:province":"West-Vlaanderen",
    "sg:tags":[
        "de"
    ],
    "wof:name":"B.c. Euro Tielt",
    "wof:placetype":"venue"
},
  "geometry": {"coordinates":[3.3316988945,50.9815673828],"type":"Point"}
}