{
  "type": "Feature",
  "properties": {
    "addr:full":"Linkhoutstraat 155 Lummen Limburg 3560",
    "addr:housenumber":"155",
    "addr:postcode":"3560",
    "addr:street":"Linkhoutstraat",
    "iso:country":"BE",
    "sg:address":"Linkhoutstraat 155",
    "sg:city":"Lummen",
    "sg:classifiers":[
        {
            "category":"Personal",
            "subcategory":"Beauty Salon",
            "type":"Services"
        }
    ],
    "sg:phone":"+32 13 44 18 65",
    "sg:postcode":"3560",
    "sg:province":"Limburg",
    "sg:tags":[
        "de",
        "coiffure"
    ],
    "wof:name":"Coiffure Alda",
    "wof:placetype":"venue"
},
  "geometry": {"coordinates":[5.1438789368,50.965839386],"type":"Point"}
}