{
  "type": "Feature",
  "properties": {
    "iso:country":"BE",
    "sg:address":"Place Communale 11",
    "sg:city":"Trois-ponts",
    "sg:orig_category":"Opticiens",
    "sg:phone":"+32 80 68 52 09",
    "sg:postcode":"4980",
    "sg:province":"Li\u00e8ge",
    "wof:name":"Comptoir D'optique",
    "wof:placetype":"venue"
},
  "geometry": {"coordinates":[5.8713479042,50.3717346191],"type":"Point"}
}