{
  "type": "Feature",
  "properties": {
    "iso:country":"BE",
    "sg:address":"Boslaan 13",
    "sg:city":"Mol",
    "sg:orig_category":"Goederenvervoer over de weg",
    "sg:phone":"+32 14 81 67 94",
    "sg:postcode":"2400",
    "sg:province":"Antwerpen",
    "wof:name":"Wezel Transport",
    "wof:placetype":"venue"
},
  "geometry": {"coordinates":[5.2184481621,51.1939849854],"type":"Point"}
}