{
  "type": "Feature",
  "properties": {
    "iso:country":"BE",
    "sg:address":"Waterstraat 46",
    "sg:city":"Begijnendijk",
    "sg:orig_category":"Gespecialiseerde residenti\u00eble bouw",
    "sg:phone":"+32 16 53 22 51",
    "sg:postcode":"3130",
    "sg:province":"Vlaams-Brabant",
    "wof:name":"Pelgrims Felix & Zn",
    "wof:placetype":"venue"
},
  "geometry": {"coordinates":[4.8028278351,51.0183525085],"type":"Point"}
}