{
  "type": "Feature",
  "properties": {
    "iso:country":"BE",
    "sg:address":"Avenue De Forest 1",
    "sg:city":"Rochefort",
    "sg:classifiers":[
        {
            "category":"Shopping",
            "subcategory":"Clothing, Apparel, & Fashions",
            "type":"Retail Goods"
        }
    ],
    "sg:phone":"+32 84 21 18 00",
    "sg:postcode":"5580",
    "sg:province":"Namur",
    "sg:tags":[
        "lady",
        "clothing",
        "-"
    ],
    "wof:name":"Cape Cod Bis",
    "wof:placetype":"venue"
},
  "geometry": {"coordinates":[5.2229409218,50.1578216553],"type":"Point"}
}