{
  "type": "Feature",
  "properties": {
    "iso:country":"BE",
    "sg:address":"Rue De Warneton 35",
    "sg:city":"Mouscron",
    "sg:orig_category":"Schoonheidssalons",
    "sg:phone":"+32 475 57 86 15",
    "sg:postcode":"7700",
    "sg:province":"Hainaut",
    "wof:name":"Vanlerberghe J.",
    "wof:placetype":"venue"
},
  "geometry": {"coordinates":[3.1886808872,50.7461738586],"type":"Point"}
}