{
  "type": "Feature",
  "properties": {
    "addr:full":"Rue Tournibouge 17 Silly Hainaut 7830",
    "addr:housenumber":"17",
    "addr:postcode":"7830",
    "addr:street":"Rue Tournibouge",
    "iso:country":"BE",
    "sg:address":"Rue Tournibouge 17",
    "sg:city":"Silly",
    "sg:orig_category":"Rundveehouders",
    "sg:phone":"+32 68 55 11 56",
    "sg:postcode":"7830",
    "sg:province":"Hainaut",
    "wof:name":"Roger Waroquier",
    "wof:placetype":"venue"
},
  "geometry": {"coordinates":[3.8920791149,50.6724624634],"type":"Point"}
}