{
  "type": "Feature",
  "properties": {
    "iso:country":"BE",
    "sg:address":"Pr\u00e9 Fleuri 67",
    "sg:city":"Jemeppe-sur-sambre",
    "sg:classifiers":[
        {
            "category":"Building & Trades",
            "subcategory":"Pest Control",
            "type":"Services"
        }
    ],
    "sg:phone":"+32 71 78 89 48",
    "sg:postcode":"5190",
    "sg:province":"Namur",
    "sg:tags":[
        "painting",
        "contractor"
    ],
    "wof:name":"Lacage J-c",
    "wof:placetype":"venue"
},
  "geometry": {"coordinates":[4.6463451385,50.4615592957],"type":"Point"}
}