{
  "type": "Feature",
  "properties": {
    "iso:country":"BE",
    "sg:address":"Keizer Karellaan 1",
    "sg:city":"Ganshoren/ganshoren",
    "sg:orig_category":"Diverse kredietdiensten",
    "sg:postcode":"1083",
    "sg:province":"Bruxelles-Capitale",
    "wof:name":"Bancontact-mister Cash",
    "wof:placetype":"venue"
},
  "geometry": {"coordinates":[4.3147921562,50.8676376343],"type":"Point"}
}