{
  "type": "Feature",
  "properties": {
    "addr:full":"Keizer Karellaan 1 Ganshoren/ganshoren Bruxelles-Capitale 1083",
    "addr:housenumber":"1",
    "addr:postcode":"1083",
    "addr:street":"Keizer Karellaan",
    "iso:country":"BE",
    "sg:address":"Keizer Karellaan 1",
    "sg:city":"Ganshoren/ganshoren",
    "sg:orig_category":"Diverse kredietdiensten",
    "sg:postcode":"1083",
    "sg:province":"Bruxelles-Capitale",
    "wof:name":"Bancontact-mister Cash",
    "wof:placetype":"venue"
},
  "geometry": {"coordinates":[4.3147921562,50.8676376343],"type":"Point"}
}