{
  "type": "Feature",
  "properties": {
    "iso:country":"BE",
    "sg:address":"Rue Ropaix 46",
    "sg:city":"Dour",
    "sg:classifiers":[
        {
            "category":"Retail",
            "subcategory":"Event Space",
            "type":"Services"
        }
    ],
    "sg:phone":"+32 497 45 26 09",
    "sg:postcode":"7370",
    "sg:province":"Hainaut",
    "sg:tags":[
        "rental",
        "-",
        "hall"
    ],
    "wof:name":"Ripaillons (le)",
    "wof:placetype":"venue"
},
  "geometry": {"coordinates":[3.8091790676,50.3794631958],"type":"Point"}
}