{
  "type": "Feature",
  "properties": {
    "addr:full":"Rue Emile Carlier 111 Bernissart Hainaut 7321",
    "addr:housenumber":"111",
    "addr:postcode":"7321",
    "addr:street":"Rue Emile Carlier",
    "iso:country":"BE",
    "sg:address":"Rue Emile Carlier 111",
    "sg:city":"Bernissart",
    "sg:orig_category":"Dranken Gh",
    "sg:phone":"+32 69 57 66 78",
    "sg:postcode":"7321",
    "sg:province":"Hainaut",
    "wof:name":"Accaputo",
    "wof:placetype":"venue"
},
  "geometry": {"coordinates":[3.6722269058,50.4961509705],"type":"Point"}
}