{
  "type": "Feature",
  "properties": {
    "addr:full":"Noorderlaan 139 Antwerpen Antwerpen 2030",
    "addr:housenumber":"139",
    "addr:postcode":"2030",
    "addr:street":"Noorderlaan",
    "iso:country":"BE",
    "sg:address":"Noorderlaan 139",
    "sg:city":"Antwerpen",
    "sg:orig_category":"Levensverzekeringsmaatschappijen Verzekeringen vastgoed",
    "sg:phone":"+32 3 543 72 11",
    "sg:postcode":"2030",
    "sg:province":"Antwerpen",
    "wof:name":"Sea Lloyd",
    "wof:placetype":"venue"
},
  "geometry": {"coordinates":[4.4007821083,51.2644691467],"type":"Point"}
}