{
  "type": "Feature",
  "properties": {
    "iso:country":"BE",
    "sg:address":"Vrijheidsplein 6",
    "sg:city":"Menen",
    "sg:orig_category":"Caf\u00e9s Kruideniers",
    "sg:phone":"+32 56 51 06 83",
    "sg:postcode":"8930",
    "sg:province":"West-Vlaanderen",
    "wof:name":"Huis Platteau",
    "wof:placetype":"venue"
},
  "geometry": {"coordinates":[3.1109700203,50.8053627014],"type":"Point"}
}