{
  "type": "Feature",
  "properties": {
    "addr:full":"Kapellestraat 115 Deinze (astene) Oost-Vlaanderen 9800",
    "addr:housenumber":"115",
    "addr:postcode":"9800",
    "addr:street":"Kapellestraat",
    "iso:country":"BE",
    "sg:address":"Kapellestraat 115",
    "sg:city":"Deinze (astene)",
    "sg:classifiers":[
        {
            "category":"Health Services",
            "subcategory":"Dentist",
            "type":"Services"
        }
    ],
    "sg:phone":"+32 9 386 59 80",
    "sg:postcode":"9800",
    "sg:province":"Oost-Vlaanderen",
    "wof:name":"De Vos Eddy",
    "wof:placetype":"venue"
},
  "geometry": {"coordinates":[3.5470950603,50.9814109802],"type":"Point"}
}