{
  "type": "Feature",
  "properties": {
    "addr:full":"Rue Chant Des Oiseaux 51 Walcourt Namur 5651",
    "addr:housenumber":"51",
    "addr:postcode":"5651",
    "addr:street":"Rue Chant Des Oiseaux",
    "iso:country":"BE",
    "sg:address":"Rue Chant Des Oiseaux 51",
    "sg:city":"Walcourt",
    "sg:orig_category":"Jardinage",
    "sg:phone":"+32 71 21 54 35",
    "sg:postcode":"5651",
    "sg:province":"Namur",
    "wof:name":"Fish-house",
    "wof:placetype":"venue"
},
  "geometry": {"coordinates":[4.4921588898,50.3216400146],"type":"Point"}
}