{
  "type": "Feature",
  "properties": {
    "addr:full":"Vitseroelstr 74 Ternat Vlaams-Brabant 1740",
    "addr:housenumber":"74",
    "addr:postcode":"1740",
    "addr:street":"Vitseroelstr",
    "iso:country":"BE",
    "sg:address":"Vitseroelstr 74",
    "sg:city":"Ternat",
    "sg:classifiers":[
        {
            "category":"Food & Beverages",
            "subcategory":"Groceries & Convenience Stores",
            "type":"Retail Goods"
        }
    ],
    "sg:phone":"+32 2 583 82 50",
    "sg:postcode":"1740",
    "sg:province":"Vlaams-Brabant",
    "sg:tags":[
        "product",
        "related"
    ],
    "wof:name":"Quality Food Products Bnl Nv",
    "wof:placetype":"venue"
},
  "geometry": {"coordinates":[4.1802749634,50.8818473816],"type":"Point"}
}