{
  "type": "Feature",
  "properties": {
    "iso:country":"BE",
    "sg:address":"Rue D\u00b4arlon 220",
    "sg:city":"Messancy",
    "sg:orig_category":"Eclairage et \u00e9quipements du foyer",
    "sg:phone":"+32 63 38 92 30",
    "sg:postcode":"6780",
    "sg:province":"Luxembourg",
    "wof:name":"Burg M.c. S\u00c9lection",
    "wof:placetype":"venue"
},
  "geometry": {"coordinates":[5.8121910095,49.6143112183],"type":"Point"}
}