{
  "type": "Feature",
  "properties": {
    "addr:full":"Petite Rue Des Bouchers 6 Brussel/bruxelles Bruxelles-Capitale 1000",
    "addr:housenumber":"6",
    "addr:postcode":"1000",
    "addr:street":"Petite Rue Des Bouchers;/",
    "iso:country":"BE",
    "sg:address":"Petite Rue Des Bouchers 6",
    "sg:city":"Brussel/bruxelles",
    "sg:classifiers":[
        {
            "category":"Cafe",
            "type":"Food & Drink"
        }
    ],
    "sg:phone":"+32 2 217 17 53",
    "sg:postcode":"1000",
    "sg:province":"Bruxelles-Capitale",
    "sg:tags":[
        "caf\u00e9s"
    ],
    "wof:name":"Estaminet Du Th\u00c9\u00c2tre De Toone",
    "wof:placetype":"venue"
},
  "geometry": {"coordinates":[4.3529348373,50.8475608826],"type":"Point"}
}