{
  "type": "Feature",
  "properties": {
    "addr:full":"Mechelsesteenweg 277 Vilvoorde Vlaams-Brabant 1800",
    "addr:housenumber":"277",
    "addr:postcode":"1800",
    "addr:street":"Mechelsesteenweg",
    "iso:country":"BE",
    "sg:address":"Mechelsesteenweg 277",
    "sg:city":"Vilvoorde",
    "sg:classifiers":[
        {
            "category":"Banks & Credit Unions",
            "subcategory":"Atm",
            "type":"Services"
        }
    ],
    "sg:phone":"+32 2 252 52 55",
    "sg:postcode":"1800",
    "sg:province":"Vlaams-Brabant",
    "sg:tags":[
        "d'entreprises",
        "de",
        "bureau"
    ],
    "wof:name":"Bedrijvencentrum Vilvoorde",
    "wof:placetype":"venue"
},
  "geometry": {"coordinates":[4.4394698143,50.9427185059],"type":"Point"}
}