{
  "type": "Feature",
  "properties": {
    "addr:full":"Kieldrechtsebaan 33 Beveren (verrebroek) Oost-Vlaanderen 9130",
    "addr:housenumber":"33",
    "addr:postcode":"9130",
    "addr:street":"Kieldrechtsebaan",
    "iso:country":"BE",
    "sg:address":"Kieldrechtsebaan 33",
    "sg:city":"Beveren (verrebroek)",
    "sg:classifiers":[
        {
            "category":"Real Estate",
            "subcategory":"Real Estate Services",
            "type":"Services"
        }
    ],
    "sg:phone":"+32 3 735 04 10",
    "sg:postcode":"9130",
    "sg:province":"Oost-Vlaanderen",
    "wof:name":"Agro Inve Nv",
    "wof:placetype":"venue"
},
  "geometry": {"coordinates":[4.1887021065,51.2575263977],"type":"Point"}
}