{
  "type": "Feature",
  "properties": {
    "addr:full":"Veurnestraat 177 De Panne West-Vlaanderen 8660",
    "addr:housenumber":"177",
    "addr:postcode":"8660",
    "addr:street":"Veurnestraat",
    "iso:country":"BE",
    "sg:address":"Veurnestraat 177",
    "sg:city":"De Panne",
    "sg:orig_category":"Epiceries. Terrains de camping",
    "sg:phone":"+32 58 42 01 06",
    "sg:postcode":"8660",
    "sg:province":"West-Vlaanderen",
    "wof:name":"Greenpark",
    "wof:placetype":"venue"
},
  "geometry": {"coordinates":[2.5992588997,51.095375061],"type":"Point"}
}