{
  "type": "Feature",
  "properties": {
    "addr:full":"Baksveld 26 Westerlo Antwerpen 2260",
    "addr:housenumber":"26",
    "addr:postcode":"2260",
    "addr:street":"Baksveld",
    "iso:country":"BE",
    "sg:address":"Baksveld 26",
    "sg:city":"Westerlo",
    "sg:orig_category":"Huwelijks- and Relatiebureaus",
    "sg:phone":"+32 14 54 17 36",
    "sg:postcode":"2260",
    "sg:province":"Antwerpen",
    "wof:name":"Happy People",
    "wof:placetype":"venue"
},
  "geometry": {"coordinates":[4.9170489311,51.0924873352],"type":"Point"}
}