{
  "type": "Feature",
  "properties": {
    "iso:country":"BE",
    "sg:address":"Rue Moineresse 1",
    "sg:city":"Andenne (thon)",
    "sg:classifiers":[
        {
            "category":"Professional",
            "subcategory":"Accounting & Tax Preparation",
            "type":"Services"
        }
    ],
    "sg:phone":"+32 81 58 93 02",
    "sg:postcode":"5300",
    "sg:province":"Namur",
    "sg:tags":[
        "bookkeeper"
    ],
    "wof:name":"Martin C",
    "wof:placetype":"venue"
},
  "geometry": {"coordinates":[5.0093269348,50.4681777954],"type":"Point"}
}