{
  "type": "Feature",
  "properties": {
    "iso:country":"BE",
    "sg:address":"Klossestraat 11ba",
    "sg:city":"De Pinte",
    "sg:orig_category":"Artsen and specialisten",
    "sg:phone":"+32 9 220 53 27",
    "sg:postcode":"9840",
    "sg:province":"Oost-Vlaanderen",
    "wof:name":"Ludo Vanmarsnille",
    "wof:placetype":"venue"
},
  "geometry": {"coordinates":[3.6708180904,51.0078659058],"type":"Point"}
}