{
  "type": "Feature",
  "properties": {
    "iso:country":"BE",
    "sg:address":"Rue De Maire 1ba",
    "sg:city":"Tournai",
    "sg:orig_category":"Kantoormateriaal",
    "sg:phone":"+32 69 84 69 38",
    "sg:postcode":"7503",
    "sg:province":"Hainaut",
    "wof:name":"Fe. Mattco",
    "wof:placetype":"venue"
},
  "geometry": {"coordinates":[3.3700020313,50.6228599548],"type":"Point"}
}