{
  "type": "Feature",
  "properties": {
    "addr:full":"Leeuwerikenstraat 3 Anderlecht/anderlecht Bruxelles-Capitale 1070",
    "addr:housenumber":"3",
    "addr:postcode":"1070",
    "addr:street":"Leeuwerikenstraat",
    "iso:country":"BE",
    "sg:address":"Leeuwerikenstraat 3",
    "sg:city":"Anderlecht/anderlecht",
    "sg:orig_category":"Verlichting and huishoudartikelen",
    "sg:phone":"+32 2 522 75 64",
    "sg:postcode":"1070",
    "sg:province":"Bruxelles-Capitale",
    "wof:name":"Cado-bizet",
    "wof:placetype":"venue"
},
  "geometry": {"coordinates":[4.2967672348,50.8250961304],"type":"Point"}
}