{
  "type": "Feature",
  "properties": {
    "addr:full":"Kuipersakkerstraat 11-13 Schoten Antwerpen 2900",
    "addr:postcode":"11-13;2900",
    "addr:street":"Kuipersakkerstraat",
    "iso:country":"BE",
    "sg:address":"Kuipersakkerstraat 11-13",
    "sg:city":"Schoten",
    "sg:orig_category":"Installation \u00e9lectrique r\u00e9sidentielle. Installation \u00e9lectrique industrielle",
    "sg:phone":"+32 3 685 25 55",
    "sg:postcode":"2900",
    "sg:province":"Antwerpen",
    "wof:name":"Failsafe Security Team",
    "wof:placetype":"venue"
},
  "geometry": {"coordinates":[4.5097260475,51.2515525818],"type":"Point"}
}