{
  "type": "Feature",
  "properties": {
    "addr:full":"Avenue Charles Deli\u00c8ge 48 Binche Hainaut 7130",
    "addr:housenumber":"48",
    "addr:postcode":"7130",
    "addr:street":"Avenue Charles Delie\u0300Ge",
    "iso:country":"BE",
    "sg:address":"Avenue Charles Deli\u00c8ge 48",
    "sg:city":"Binche",
    "sg:orig_category":"Diverse financi\u00eble diensten",
    "sg:phone":"+32 64 34 19 54",
    "sg:postcode":"7130",
    "sg:province":"Hainaut",
    "wof:name":"Bur.van Moer-santerre Cie",
    "wof:placetype":"venue"
},
  "geometry": {"coordinates":[4.1661720276,50.4127655029],"type":"Point"}
}