{
  "type": "Feature",
  "properties": {
    "addr:full":"Hogestraat 17 Torhout West-Vlaanderen 8820",
    "addr:housenumber":"17",
    "addr:postcode":"8820",
    "addr:street":"Hogestraat",
    "iso:country":"BE",
    "sg:address":"Hogestraat 17",
    "sg:city":"Torhout",
    "sg:orig_category":"Installation de menuiserie en bois and plastique",
    "sg:phone":"+32 50 21 54 36",
    "sg:postcode":"8820",
    "sg:province":"West-Vlaanderen",
    "wof:name":"Fa. Denova",
    "wof:placetype":"venue"
},
  "geometry": {"coordinates":[3.0894179344,51.0701751709],"type":"Point"}
}