{
  "type": "Feature",
  "properties": {
    "addr:full":"Alliers 16 Ranst (emblem) Antwerpen 2520",
    "addr:housenumber":"16",
    "addr:postcode":"2520",
    "addr:street":"Alliers",
    "iso:country":"BE",
    "sg:address":"Alliers 16",
    "sg:city":"Ranst (emblem)",
    "sg:classifiers":[
        {
            "category":"Home & Garden",
            "subcategory":"Household Appliances",
            "type":"Retail Goods"
        }
    ],
    "sg:phone":"+32 3 489 02 03",
    "sg:postcode":"2520",
    "sg:province":"Antwerpen",
    "sg:tags":[
        "repair",
        "mainten",
        "-",
        "electric"
    ],
    "wof:name":"Meeus L",
    "wof:placetype":"venue"
},
  "geometry": {"coordinates":[4.5717802048,51.1530227661],"type":"Point"}
}