{
  "type": "Feature",
  "properties": {
    "iso:country":"BE",
    "sg:address":"Chauss\u00c9e De Mons 58",
    "sg:city":"Anderlues",
    "sg:orig_category":"Editeurs de journaux. Editeurs de revues and p\u00e9riodiques. Enseignement secondaire technique and prof",
    "sg:phone":"+32 2 735 35 25",
    "sg:postcode":"6150",
    "sg:province":"Hainaut",
    "wof:name":"Soc.roy.belge Hom\u00c9opathie",
    "wof:placetype":"venue"
},
  "geometry": {"coordinates":[4.2286968231,50.4077949524],"type":"Point"}
}