{
  "type": "Feature",
  "properties": {
    "addr:full":"Ouland 73haven Antwerpen Antwerpen 2030",
    "addr:postcode":"2030",
    "addr:street":"Ouland 73Haven",
    "iso:country":"BE",
    "sg:address":"Ouland 73haven",
    "sg:city":"Antwerpen",
    "sg:classifiers":[
        {
            "category":"Freight",
            "type":"Transportation"
        }
    ],
    "sg:phone":"+32 3 541 94 68",
    "sg:postcode":"2030",
    "sg:province":"Antwerpen",
    "sg:tags":[
        "-",
        "transport"
    ],
    "wof:name":"Cementnatie Cv",
    "wof:placetype":"venue"
},
  "geometry": {"coordinates":[4.4000902176,51.2454605103],"type":"Point"}
}