{
  "type": "Feature",
  "properties": {
    "addr:full":"Rue Ferrer 157 Manage Hainaut 7170",
    "addr:housenumber":"157",
    "addr:postcode":"7170",
    "addr:street":"Rue Ferrer",
    "iso:country":"BE",
    "sg:address":"Rue Ferrer 157",
    "sg:city":"Manage",
    "sg:orig_category":"Cabinets d\u00b4huissiers",
    "sg:phone":"+32 64 26 63 79",
    "sg:postcode":"7170",
    "sg:province":"Hainaut",
    "wof:name":"J.m. Skwara",
    "wof:placetype":"venue"
},
  "geometry": {"coordinates":[4.2344789505,50.4733123779],"type":"Point"}
}