{
  "type": "Feature",
  "properties": {
    "iso:country":"BE",
    "sg:address":"Zandberg 27",
    "sg:city":"Westerlo",
    "sg:orig_category":"Beautyfarms, relaxatie and lichamelijk welzijn",
    "sg:phone":"+32 14 54 27 09",
    "sg:postcode":"2260",
    "sg:province":"Antwerpen",
    "wof:name":"Sauna Het Vijfde Seizoen",
    "wof:placetype":"venue"
},
  "geometry": {"coordinates":[4.934191227,51.0941734314],"type":"Point"}
}