{
  "type": "Feature",
  "properties": {
    "addr:full":"Rue Vignoul 2 Li\u00e8ge 1 (grivegn\u00e9e) Li\u00e8ge 4030",
    "addr:housenumber":"2;1",
    "addr:postcode":"4030",
    "addr:street":"Rue Vignoul",
    "iso:country":"BE",
    "sg:address":"Rue Vignoul 2",
    "sg:city":"Li\u00e8ge 1 (grivegn\u00e9e)",
    "sg:classifiers":[
        {
            "category":"Building & Trades",
            "subcategory":"Plumbing",
            "type":"Services"
        }
    ],
    "sg:phone":"+32 4 341 32 58",
    "sg:postcode":"4030",
    "sg:province":"Li\u00e8ge",
    "sg:tags":[
        "repair",
        "mainten",
        "-",
        "central",
        "heating"
    ],
    "wof:name":"Adec Sprl",
    "wof:placetype":"venue"
},
  "geometry": {"coordinates":[5.6016559601,50.6202926636],"type":"Point"}
}