{
  "type": "Feature",
  "properties": {
    "iso:country":"BE",
    "sg:address":"Eendrachtstraat 48",
    "sg:city":"Elsene/ixelles",
    "sg:orig_category":"Advocaten and juridische adviseurs",
    "sg:phone":"+32 2 384 44 66",
    "sg:postcode":"1050",
    "sg:province":"Bruxelles-Capitale",
    "wof:name":"A. Cauvin",
    "wof:placetype":"venue"
},
  "geometry": {"coordinates":[4.360640049,50.8327293396],"type":"Point"}
}