{
  "type": "Feature",
  "properties": {
    "iso:country":"BE",
    "sg:address":"Steenweg Op Vilvoorde 67",
    "sg:city":"Steenokkerzeel",
    "sg:orig_category":"Herstellingen and onderhoud van auto's Voertuigen",
    "sg:phone":"+32 2 751 74 54",
    "sg:postcode":"1820",
    "sg:province":"Vlaams-Brabant",
    "wof:name":"Caliber En Zoon",
    "wof:placetype":"venue"
},
  "geometry": {"coordinates":[4.4884238243,50.9347686768],"type":"Point"}
}