{
  "type": "Feature",
  "properties": {
    "addr:full":"'s Gravenstraat 34 Nazareth Oost-Vlaanderen 9810",
    "addr:housenumber":"34",
    "addr:postcode":"9810",
    "addr:street":"' S Gravenstraat",
    "iso:country":"BE",
    "sg:address":"'s Gravenstraat 34",
    "sg:city":"Nazareth",
    "sg:orig_category":"V\u00e9t\u00e9rinaires",
    "sg:phone":"+32 9 385 85 65",
    "sg:postcode":"9810",
    "sg:province":"Oost-Vlaanderen",
    "wof:name":"Ann Van Wassenhove",
    "wof:placetype":"venue"
},
  "geometry": {"coordinates":[3.5954720974,50.9616508484],"type":"Point"}
}