{
  "type": "Feature",
  "properties": {
    "addr:full":"Ham 24 Laakdal (eindhout) Antwerpen 2430",
    "addr:housenumber":"24",
    "addr:postcode":"2430",
    "addr:street":"Ham",
    "iso:country":"BE",
    "sg:address":"Ham 24",
    "sg:city":"Laakdal (eindhout)",
    "sg:classifiers":[
        {
            "category":"Bars & Pubs",
            "type":"Food & Drink"
        }
    ],
    "sg:phone":"+32 14 86 63 13",
    "sg:postcode":"2430",
    "sg:province":"Antwerpen",
    "sg:tags":[
        "tavern"
    ],
    "wof:name":"Kapelhof",
    "wof:placetype":"venue"
},
  "geometry": {"coordinates":[4.9959130287,51.0961799622],"type":"Point"}
}