{
  "type": "Feature",
  "properties": {
    "iso:country":"BE",
    "sg:address":"Entrepotstraat 20a",
    "sg:city":"Sint-niklaas",
    "sg:orig_category":"Non-Classified Establishments",
    "sg:phone":"+32 3 766 42 05",
    "sg:postcode":"9100",
    "sg:province":"Oost-Vlaanderen",
    "wof:name":"Heininger Bvba",
    "wof:placetype":"venue"
},
  "geometry": {"coordinates":[4.1672339439,51.174987793],"type":"Point"}
}