{
  "type": "Feature",
  "properties": {
    "iso:country":"BE",
    "sg:address":"Bergenstraat 100",
    "sg:city":"Alveringem (beveren-aan-de-ijzer)",
    "sg:classifiers":[
        {
            "category":"Bars & Pubs",
            "type":"Food & Drink"
        }
    ],
    "sg:phone":"+32 57 30 01 34",
    "sg:postcode":"8691",
    "sg:province":"West-Vlaanderen",
    "wof:name":"Las Vegas",
    "wof:placetype":"venue"
},
  "geometry": {"coordinates":[2.6024580002,50.9251441956],"type":"Point"}
}