{
  "type": "Feature",
  "properties": {
    "iso:country":"BE",
    "sg:address":"Eikenlei 102",
    "sg:city":"Brecht (sint-job-in-'t Goor)",
    "sg:classifiers":[
        {
            "category":"Retail",
            "subcategory":"Auto Repair",
            "type":"Services"
        }
    ],
    "sg:phone":"+32 3 633 85 85",
    "sg:postcode":"2960",
    "sg:province":"Antwerpen",
    "sg:tags":[
        "garage"
    ],
    "wof:name":"Audi/vw Leuris",
    "wof:placetype":"venue"
},
  "geometry": {"coordinates":[4.5568828583,51.2993164062],"type":"Point"}
}