{
  "type": "Feature",
  "properties": {
    "addr:full":"Route De Rocroi 44 Walcourt (fraire) Namur 5650",
    "addr:housenumber":"44",
    "addr:postcode":"5650",
    "addr:street":"Route De Rocroi",
    "iso:country":"BE",
    "sg:address":"Route De Rocroi 44",
    "sg:city":"Walcourt (fraire)",
    "sg:classifiers":[
        {
            "category":"Personal",
            "subcategory":"Psychics & Astrologers",
            "type":"Services"
        }
    ],
    "sg:phone":"+32 71 61 46 64",
    "sg:postcode":"5650",
    "sg:province":"Namur",
    "sg:tags":[
        "astrology"
    ],
    "wof:name":"Lorent J",
    "wof:placetype":"venue"
},
  "geometry": {"coordinates":[4.4313349724,50.2514762878],"type":"Point"}
}