{
  "type": "Feature",
  "properties": {
    "addr:full":"Langenbos 9 Waregem (beveren-leie) West-Vlaanderen 8791",
    "addr:housenumber":"9",
    "addr:postcode":"8791",
    "addr:street":"Langenbos",
    "iso:country":"BE",
    "sg:address":"Langenbos 9",
    "sg:city":"Waregem (beveren-leie)",
    "sg:classifiers":[
        {
            "category":"Professional",
            "subcategory":"Detective & Security Services",
            "type":"Services"
        }
    ],
    "sg:phone":"+32 56 72 76 97",
    "sg:postcode":"8791",
    "sg:province":"West-Vlaanderen",
    "sg:tags":[
        "agency"
    ],
    "wof:name":"Cheops International Nv",
    "wof:placetype":"venue"
},
  "geometry": {"coordinates":[3.3507609367,50.864074707],"type":"Point"}
}