{
  "type": "Feature",
  "properties": {
    "iso:country":"BE",
    "sg:address":"Salisburylaan 74",
    "sg:city":"Merelbeke",
    "sg:classifiers":[
        {
            "category":"Cafe",
            "type":"Food & Drink"
        }
    ],
    "sg:phone":"+32 9 252 58 32",
    "sg:postcode":"9820",
    "sg:province":"Oost-Vlaanderen",
    "sg:tags":[
        "caf\u00e9s"
    ],
    "wof:name":"Dirk Braeckman",
    "wof:placetype":"venue"
},
  "geometry": {"coordinates":[3.7675969601,50.9958152771],"type":"Point"}
}