{
  "type": "Feature",
  "properties": {
    "addr:full":"Churchilllaan 57 Schoten Antwerpen 2900",
    "addr:housenumber":"57",
    "addr:postcode":"2900",
    "addr:street":"Churchilllaan",
    "iso:country":"BE",
    "sg:address":"Churchilllaan 57",
    "sg:city":"Schoten",
    "sg:orig_category":"Mus\u00e9es and patrimoine culturel",
    "sg:phone":"+32 3 658 62 83",
    "sg:postcode":"2900",
    "sg:province":"Antwerpen",
    "wof:name":"Museum Voor Mineralogie",
    "wof:placetype":"venue"
},
  "geometry": {"coordinates":[4.4940280914,51.2504768372],"type":"Point"}
}