{
  "type": "Feature",
  "properties": {
    "iso:country":"BE",
    "sg:address":"Chemin De Saint-ghislain 157",
    "sg:city":"Chi\u00e8vres",
    "sg:classifiers":[
        {
            "category":"Food & Beverages",
            "subcategory":"Groceries & Convenience Stores",
            "type":"Retail Goods"
        }
    ],
    "sg:phone":"+32 68 65 84 48",
    "sg:postcode":"7950",
    "sg:province":"Hainaut",
    "sg:tags":[
        "grocer"
    ],
    "wof:name":"Elephant (l')",
    "wof:placetype":"venue"
},
  "geometry": {"coordinates":[3.8061699867,50.5644493103],"type":"Point"}
}