{
  "type": "Feature",
  "properties": {
    "addr:full":"Mons. Trudo Jansstraat 7 Riemst Limburg 3770",
    "addr:housenumber":"7",
    "addr:postcode":"3770",
    "addr:street":"Jansstraat",
    "iso:country":"BE",
    "sg:address":"Mons. Trudo Jansstraat 7",
    "sg:city":"Riemst",
    "sg:orig_category":"Eleveurs and marchands de porcs",
    "sg:phone":"+32 12 45 44 89",
    "sg:postcode":"3770",
    "sg:province":"Limburg",
    "wof:name":"Emile Meers",
    "wof:placetype":"venue"
},
  "geometry": {"coordinates":[5.5719690323,50.8069877625],"type":"Point"}
}