{
  "type": "Feature",
  "properties": {
    "iso:country":"BE",
    "sg:address":"Rue De La Bonnette 6",
    "sg:city":"Thuin",
    "sg:orig_category":"V\u00eatements pour b\u00e9b\u00e9s and enfants",
    "sg:phone":"+32 71 59 39 51",
    "sg:postcode":"6533",
    "sg:province":"Hainaut",
    "wof:name":"Michelle Chartier",
    "wof:placetype":"venue"
},
  "geometry": {"coordinates":[4.2605991364,50.3283081055],"type":"Point"}
}