{
  "type": "Feature",
  "properties": {
    "addr:full":"Kapellestraat 32-34 Oostende West-Vlaanderen 8400",
    "addr:postcode":"32-34;8400",
    "addr:street":"Kapellestraat",
    "iso:country":"BE",
    "sg:address":"Kapellestraat 32-34",
    "sg:city":"Oostende",
    "sg:classifiers":[
        {
            "category":"Tea Room",
            "subcategory":"None",
            "type":"Food & Drink"
        }
    ],
    "sg:phone":"+32 59 70 05 64",
    "sg:postcode":"8400",
    "sg:province":"West-Vlaanderen",
    "wof:name":"Dewulf (emlo/nv)",
    "wof:placetype":"venue"
},
  "geometry": {"coordinates":[2.9190289974,51.2304344177],"type":"Point"}
}