{
  "type": "Feature",
  "properties": {
    "addr:full":"Chauss\u00e9e De Tirlemont 66 Gembloux-sur-orneau (gembloux) Namur 5030",
    "addr:housenumber":"66",
    "addr:postcode":"5030",
    "addr:street":"Chausse\u0301E De Tirlemont;Namur",
    "iso:country":"BE",
    "sg:address":"Chauss\u00e9e De Tirlemont 66",
    "sg:city":"Gembloux-sur-orneau (gembloux)",
    "sg:orig_category":"Non-Classified Establishments",
    "sg:phone":"+32 81 61 25 32",
    "sg:postcode":"5030",
    "sg:province":"Namur",
    "wof:name":"Eternum Sa",
    "wof:placetype":"venue"
},
  "geometry": {"coordinates":[4.705201149,50.5780448914],"type":"Point"}
}