{
  "type": "Feature",
  "properties": {
    "iso:country":"BE",
    "sg:address":"Rue De La Station 26ba",
    "sg:city":"Frasnes-lez-anvaing",
    "sg:orig_category":"Banques and organismes de cr\u00e9dit",
    "sg:phone":"+32 69 76 86 75",
    "sg:postcode":"7912",
    "sg:province":"Hainaut",
    "wof:name":"Fortis",
    "wof:placetype":"venue"
},
  "geometry": {"coordinates":[3.5842890739,50.7147789001],"type":"Point"}
}