{
  "type": "Feature",
  "properties": {
    "iso:country":"BE",
    "sg:address":"Rue Lambert Crickx 11",
    "sg:city":"Bruxelles (anderlecht)",
    "sg:orig_category":"Non-Classified Establishments",
    "sg:phone":"+32 2 527 35 80",
    "sg:postcode":"1070",
    "sg:province":"Bruxelles-Capitale",
    "wof:name":"Bichou",
    "wof:placetype":"venue"
},
  "geometry": {"coordinates":[4.3378348351,50.8409614563],"type":"Point"}
}