{
  "type": "Feature",
  "properties": {
    "addr:full":"Avenue Du Forum 17b30 Brussel/bruxelles Bruxelles-Capitale 1020",
    "addr:housenumber":"17b30",
    "addr:postcode":"1020",
    "addr:street":"Avenue Du Forum;/",
    "iso:country":"BE",
    "sg:address":"Avenue Du Forum 17b30",
    "sg:city":"Brussel/bruxelles",
    "sg:classifiers":[
        {
            "category":"Restaurant",
            "type":"Food & Drink"
        }
    ],
    "sg:phone":"+32 2 268 45 12",
    "sg:postcode":"1020",
    "sg:province":"Bruxelles-Capitale",
    "wof:name":"Thierry Vandevelde",
    "wof:placetype":"venue"
},
  "geometry": {"coordinates":[4.3541250229,50.9000854492],"type":"Point"}
}