{
  "type": "Feature",
  "properties": {
    "addr:full":"Torenstraat 14 Box 7 Hasselt Limburg 3500",
    "addr:housenumber":"14;7",
    "addr:postcode":"3500",
    "addr:street":"Torenstraat;Box",
    "iso:country":"BE",
    "sg:address":"Torenstraat 14 Box 7",
    "sg:city":"Hasselt",
    "sg:classifiers":[
        {
            "category":"Professional",
            "subcategory":"Art Services",
            "type":"Services"
        }
    ],
    "sg:phone":"+32 11 28 18 96",
    "sg:postcode":"3500",
    "sg:province":"Limburg",
    "sg:tags":[
        "graphic",
        "designer"
    ],
    "wof:name":"Jo Knoops Vormgeving",
    "wof:placetype":"venue"
},
  "geometry": {"coordinates":[5.3292689323,50.9256362915],"type":"Point"}
}