{
  "type": "Feature",
  "properties": {
    "iso:country":"BE",
    "sg:address":"Eddastraat 31",
    "sg:city":"Gent (desteldonk)",
    "sg:classifiers":[
        {
            "category":"Freight",
            "type":"Transportation"
        }
    ],
    "sg:phone":"+32 9 251 55 30",
    "sg:postcode":"9042",
    "sg:province":"Oost-Vlaanderen",
    "sg:tags":[
        "-",
        "transport"
    ],
    "wof:name":"Van Hove & Co Bvba",
    "wof:placetype":"venue"
},
  "geometry": {"coordinates":[3.7816700935,51.1223831177],"type":"Point"}
}