{
  "type": "Feature",
  "properties": {
    "addr:full":"Moeskroenstraat 681 Menen West-Vlaanderen 8930",
    "addr:housenumber":"681",
    "addr:postcode":"8930",
    "addr:street":"Moeskroenstraat",
    "iso:country":"BE",
    "sg:address":"Moeskroenstraat 681",
    "sg:city":"Menen",
    "sg:classifiers":[
        {
            "category":"Personal",
            "subcategory":"Beauty Salon",
            "type":"Services"
        }
    ],
    "sg:phone":"+32 56 42 27 39",
    "sg:postcode":"8930",
    "sg:province":"West-Vlaanderen",
    "sg:tags":[
        "de",
        "coiffure"
    ],
    "wof:name":"Coiffure Classique",
    "wof:placetype":"venue"
},
  "geometry": {"coordinates":[3.1586298943,50.787361145],"type":"Point"}
}