{
  "type": "Feature",
  "properties": {
    "addr:full":"Dreefstraat 10 Huldenberg Vlaams-Brabant 3040",
    "addr:housenumber":"10",
    "addr:postcode":"3040",
    "addr:street":"Dreefstraat",
    "iso:country":"BE",
    "sg:address":"Dreefstraat 10",
    "sg:city":"Huldenberg",
    "sg:orig_category":"Schoonheidssalons",
    "sg:phone":"+32 2 687 73 17",
    "sg:postcode":"3040",
    "sg:province":"Vlaams-Brabant",
    "wof:name":"Isabelle",
    "wof:placetype":"venue"
},
  "geometry": {"coordinates":[4.5788598061,50.7925643921],"type":"Point"}
}