{
  "type": "Feature",
  "properties": {
    "addr:full":"Rue Laurent Heirbaut 24-8b Bruxelles (ganshoren) Bruxelles-Capitale 1083",
    "addr:housenumber":"24-8b",
    "addr:postcode":"1083",
    "addr:street":"Rue Laurent Heirbaut",
    "iso:country":"BE",
    "sg:address":"Rue Laurent Heirbaut 24-8b",
    "sg:city":"Bruxelles (ganshoren)",
    "sg:classifiers":[
        {
            "category":"Professional",
            "subcategory":"Accounting & Tax Preparation",
            "type":"Services"
        }
    ],
    "sg:phone":"+32 2 465 28 34",
    "sg:postcode":"1083",
    "sg:province":"Bruxelles-Capitale",
    "sg:tags":[
        "accountant"
    ],
    "wof:name":"Raes M",
    "wof:placetype":"venue"
},
  "geometry": {"coordinates":[4.3053240776,50.8693389893],"type":"Point"}
}