{
  "type": "Feature",
  "properties": {
    "iso:country":"BE",
    "sg:address":"Spinnerijstraat 19",
    "sg:city":"Wetteren",
    "sg:classifiers":[
        {
            "category":"Wholesale",
            "subcategory":"Beer",
            "type":"Manufacturing & Wholesale Goods"
        }
    ],
    "sg:phone":"+32 9 369 01 75",
    "sg:postcode":"9230",
    "sg:province":"Oost-Vlaanderen",
    "sg:tags":[
        "ale",
        "-"
    ],
    "wof:name":"De Winter Gebr Bvba",
    "wof:placetype":"venue"
},
  "geometry": {"coordinates":[3.8649399281,50.9993896484],"type":"Point"}
}