{
  "type": "Feature",
  "properties": {
    "iso:country":"BE",
    "sg:address":"Generaal De Wittelaan 9b5",
    "sg:city":"Mechelen",
    "sg:classifiers":[
        {
            "category":"Health Services",
            "subcategory":"Medical Lab",
            "type":"Services"
        }
    ],
    "sg:phone":"+32 15 29 81 11",
    "sg:postcode":"2800",
    "sg:province":"Antwerpen",
    "sg:tags":[
        "adhesive",
        "tape"
    ],
    "wof:name":"Tyco Healthcare Belgium Nv",
    "wof:placetype":"venue"
},
  "geometry": {"coordinates":[4.4518809319,51.0549049377],"type":"Point"}
}