{
  "type": "Feature",
  "properties": {
    "iso:country":"BE",
    "sg:address":"Valkenputstraat 64",
    "sg:city":"Antwerpen (berchem)",
    "sg:orig_category":"Fiduciairies",
    "sg:phone":"+32 3 321 25 61",
    "sg:postcode":"2600",
    "sg:province":"Antwerpen",
    "wof:name":"Infacco Bvba",
    "wof:placetype":"venue"
},
  "geometry": {"coordinates":[4.4174151421,51.1974411011],"type":"Point"}
}