{
  "type": "Feature",
  "properties": {
    "iso:country":"BE",
    "sg:address":"Chemin Des Soeurs 24",
    "sg:city":"Beauvechain",
    "sg:classifiers":[
        {
            "category":"Professional",
            "subcategory":"Accounting & Tax Preparation",
            "type":"Services"
        }
    ],
    "sg:phone":"+32 10 86 74 67",
    "sg:postcode":"1320",
    "sg:province":"Brabant Wallon",
    "sg:tags":[
        "accountant"
    ],
    "wof:name":"Joseph Marko",
    "wof:placetype":"venue"
},
  "geometry": {"coordinates":[4.7399787903,50.7686271667],"type":"Point"}
}