{
  "type": "Feature",
  "properties": {
    "addr:full":"Rue Joseph Wauters 43 Waremme Li\u00e8ge 4300",
    "addr:housenumber":"43",
    "addr:postcode":"4300",
    "addr:street":"Rue Joseph Wauters",
    "iso:country":"BE",
    "sg:address":"Rue Joseph Wauters 43",
    "sg:city":"Waremme",
    "sg:classifiers":[
        {
            "category":"Personal",
            "subcategory":"Beauty Salon",
            "type":"Services"
        }
    ],
    "sg:phone":"+32 19 32 66 61",
    "sg:postcode":"4300",
    "sg:province":"Li\u00e8ge",
    "sg:tags":[
        "lady",
        "-",
        "hairdressing"
    ],
    "wof:name":"Bigoudis & Papillotes Sprl",
    "wof:placetype":"venue"
},
  "geometry": {"coordinates":[5.253921032,50.6967010498],"type":"Point"}
}