{
  "type": "Feature",
  "properties": {
    "iso:country":"BE",
    "sg:address":"Desselgemseweg 90",
    "sg:city":"Waregem",
    "sg:orig_category":"Eleveurs and marchands de porcs",
    "sg:phone":"+32 56 60 01 59",
    "sg:postcode":"8790",
    "sg:province":"West-Vlaanderen",
    "wof:name":"Filipe Himpe",
    "wof:placetype":"venue"
},
  "geometry": {"coordinates":[3.4080660343,50.8835830688],"type":"Point"}
}