{
  "type": "Feature",
  "properties": {
    "addr:full":"Rue De France 57 Aubange Luxembourg 6791",
    "addr:housenumber":"57",
    "addr:postcode":"6791",
    "addr:street":"Rue De France",
    "iso:country":"BE",
    "sg:address":"Rue De France 57",
    "sg:city":"Aubange",
    "sg:orig_category":"Artsen and specialisten",
    "sg:phone":"+32 63 37 06 49",
    "sg:postcode":"6791",
    "sg:province":"Luxembourg",
    "wof:name":"Stephan Kemp",
    "wof:placetype":"venue"
},
  "geometry": {"coordinates":[5.8242998123,49.56016922],"type":"Point"}
}