{
  "type": "Feature",
  "properties": {
    "addr:full":"Rue Neuve 111b4b Charleroi Hainaut 6061",
    "addr:postcode":"111b4b;6061",
    "addr:street":"Rue Neuve;Hainaut",
    "iso:country":"BE",
    "sg:address":"Rue Neuve 111b4b",
    "sg:city":"Charleroi",
    "sg:orig_category":"Experts-comptables",
    "sg:phone":"+32 477 86 31 21",
    "sg:postcode":"6061",
    "sg:province":"Hainaut",
    "wof:name":"Sarr El Hadji Mbaye",
    "wof:placetype":"venue"
},
  "geometry": {"coordinates":[4.4541711807,50.4082450867],"type":"Point"}
}