{
  "type": "Feature",
  "properties": {
    "addr:full":"Clement Heirmanstraat 1b Sint-niklaas Oost-Vlaanderen 9100",
    "addr:housenumber":"1b",
    "addr:postcode":"9100",
    "addr:street":"Clement Heirmanstraat",
    "iso:country":"BE",
    "sg:address":"Clement Heirmanstraat 1b",
    "sg:city":"Sint-niklaas",
    "sg:orig_category":"Newspapers, magazines, periodicals - Distribution",
    "sg:phone":"+32 3 776 04 39",
    "sg:postcode":"9100",
    "sg:province":"Oost-Vlaanderen",
    "wof:name":"De Vos D",
    "wof:placetype":"venue"
},
  "geometry": {"coordinates":[4.1477680206,51.1584892273],"type":"Point"}
}