{
  "type": "Feature",
  "properties": {
    "addr:full":"Clos Des Tarins 1 Mouscron (dottignies) Hainaut 7711",
    "addr:housenumber":"1",
    "addr:postcode":"7711",
    "addr:street":"Clos Des Tarins",
    "iso:country":"BE",
    "sg:address":"Clos Des Tarins 1",
    "sg:city":"Mouscron (dottignies)",
    "sg:classifiers":[
        {
            "category":"Health Services",
            "subcategory":"Nursing And Care Facility",
            "type":"Services"
        }
    ],
    "sg:phone":"+32 56 48 07 37",
    "sg:postcode":"7711",
    "sg:province":"Hainaut",
    "sg:tags":[
        "home"
    ],
    "wof:name":"Deconinck J",
    "wof:placetype":"venue"
},
  "geometry": {"coordinates":[3.3053131104,50.7347450256],"type":"Point"}
}