{
  "type": "Feature",
  "properties": {
    "addr:full":"Hendrik Consciencestraat 9 Kortrijk West-Vlaanderen 8500",
    "addr:housenumber":"9",
    "addr:postcode":"8500",
    "addr:street":"Hendrik Consciencestraat",
    "iso:country":"BE",
    "sg:address":"Hendrik Consciencestraat 9",
    "sg:city":"Kortrijk",
    "sg:classifiers":[
        {
            "category":"Insurance",
            "subcategory":"Life Insurance",
            "type":"Services"
        }
    ],
    "sg:phone":"+32 56 20 22 40",
    "sg:postcode":"8500",
    "sg:province":"West-Vlaanderen",
    "sg:tags":[
        "assurance"
    ],
    "wof:name":"Nuttin & Carette",
    "wof:placetype":"venue"
},
  "geometry": {"coordinates":[3.2598900795,50.8263053894],"type":"Point"}
}