{
  "type": "Feature",
  "properties": {
    "iso:country":"BE",
    "sg:address":"Sint-annaplein 26a",
    "sg:city":"Berlare",
    "sg:orig_category":"Schoonheidssalons",
    "sg:phone":"+32 52 42 21 79",
    "sg:postcode":"9290",
    "sg:province":"Oost-Vlaanderen",
    "wof:name":"Instituut V\u00c9",
    "wof:placetype":"venue"
},
  "geometry": {"coordinates":[4.0067501068,51.0202293396],"type":"Point"}
}