{
  "type": "Feature",
  "properties": {
    "addr:full":"Van Gorplaan 19 Putte Antwerpen 2580",
    "addr:housenumber":"19",
    "addr:postcode":"2580",
    "addr:street":"Van Gorplaan",
    "iso:country":"BE",
    "sg:address":"Van Gorplaan 19",
    "sg:city":"Putte",
    "sg:orig_category":"Juwelen and horloges",
    "sg:phone":"+32 15 75 22 98",
    "sg:postcode":"2580",
    "sg:province":"Antwerpen",
    "wof:name":"Ingrid Bourgeois",
    "wof:placetype":"venue"
},
  "geometry": {"coordinates":[4.634455204,51.0509681702],"type":"Point"}
}