{
  "type": "Feature",
  "properties": {
    "iso:country":"BE",
    "sg:address":"Oude Booischotsebaan 1",
    "sg:city":"Bonheiden (rijmenam)",
    "sg:orig_category":"Scenery Stage-, film-, and television",
    "sg:phone":"+32 15 51 81 56",
    "sg:postcode":"2820",
    "sg:province":"Antwerpen",
    "wof:name":"Filmcar-autocasting",
    "wof:placetype":"venue"
},
  "geometry": {"coordinates":[4.6045179367,51.0270423889],"type":"Point"}
}