{
  "type": "Feature",
  "properties": {
    "addr:full":"Ridderstraat 9 Herk-de-stad Limburg 3540",
    "addr:housenumber":"9",
    "addr:postcode":"3540",
    "addr:street":"Ridderstraat",
    "iso:country":"BE",
    "sg:address":"Ridderstraat 9",
    "sg:city":"Herk-de-stad",
    "sg:classifiers":[
        {
            "category":"Banks & Credit Unions",
            "subcategory":"Investment Brokerage",
            "type":"Services"
        }
    ],
    "sg:phone":"+32 13 55 46 22",
    "sg:postcode":"3540",
    "sg:province":"Limburg",
    "sg:tags":[
        "printing",
        "-"
    ],
    "wof:name":"Drukkerij Vanwing Bvba",
    "wof:placetype":"venue"
},
  "geometry": {"coordinates":[5.168170929,50.9408531189],"type":"Point"}
}