{
  "type": "Feature",
  "properties": {
    "addr:full":"Bijzondereweg 4 Bierbeek (lovenjoel) Vlaams-Brabant 3360",
    "addr:housenumber":"4",
    "addr:postcode":"3360",
    "addr:street":"Bijzondereweg",
    "iso:country":"BE",
    "sg:address":"Bijzondereweg 4",
    "sg:city":"Bierbeek (lovenjoel)",
    "sg:classifiers":[
        {
            "category":"Health Services",
            "subcategory":"Doctor",
            "type":"Services"
        }
    ],
    "sg:phone":"+32 16 46 08 57",
    "sg:postcode":"3360",
    "sg:province":"Vlaams-Brabant",
    "sg:tags":[
        "medicinephysicians",
        "surgeon"
    ],
    "wof:name":"Kongs G",
    "wof:placetype":"venue"
},
  "geometry": {"coordinates":[4.7752189636,50.8579673767],"type":"Point"}
}