{
  "type": "Feature",
  "properties": {
    "addr:full":"Soetebeek 79 Meeuwen-gruitrode (wijshagen) Limburg 3670",
    "addr:housenumber":"79",
    "addr:postcode":"3670",
    "addr:street":"Soetebeek",
    "iso:country":"BE",
    "sg:address":"Soetebeek 79",
    "sg:city":"Meeuwen-gruitrode (wijshagen)",
    "sg:classifiers":[
        {
            "category":"Farming",
            "subcategory":"Livestock Farm",
            "type":"Manufacturing & Wholesale Goods"
        }
    ],
    "sg:phone":"+32 89 46 87 25",
    "sg:postcode":"3670",
    "sg:province":"Limburg",
    "sg:tags":[
        "horse"
    ],
    "wof:name":"Lowlands Stud Bvba",
    "wof:placetype":"venue"
},
  "geometry": {"coordinates":[5.5505700111,51.1186714172],"type":"Point"}
}