{
  "type": "Feature",
  "properties": {
    "addr:full":"Cit\u00c9 Soucou 31 Rouvroy Luxembourg 6767",
    "addr:housenumber":"31",
    "addr:postcode":"6767",
    "addr:street":"Cite\u0301 Soucou",
    "iso:country":"BE",
    "sg:address":"Cit\u00c9 Soucou 31",
    "sg:city":"Rouvroy",
    "sg:orig_category":"Enseignement maternel and primaire",
    "sg:phone":"+32 63 57 18 91",
    "sg:postcode":"6767",
    "sg:province":"Luxembourg",
    "wof:name":"Ecole Fond. Communale",
    "wof:placetype":"venue"
},
  "geometry": {"coordinates":[5.4905800819,49.5384864807],"type":"Point"}
}