{
  "type": "Feature",
  "properties": {
    "addr:full":"Spoorweglaan 5 Temse Oost-Vlaanderen 9140",
    "addr:housenumber":"5",
    "addr:postcode":"9140",
    "addr:street":"Spoorweglaan",
    "iso:country":"BE",
    "sg:address":"Spoorweglaan 5",
    "sg:city":"Temse",
    "sg:classifiers":[
        {
            "category":"Building & Trades",
            "subcategory":"Plumbing",
            "type":"Services"
        }
    ],
    "sg:phone":"+32 3 771 06 15",
    "sg:postcode":"9140",
    "sg:province":"Oost-Vlaanderen",
    "sg:tags":[
        "contractor"
    ],
    "wof:name":"Michiels J",
    "wof:placetype":"venue"
},
  "geometry": {"coordinates":[4.2204031944,51.1305541992],"type":"Point"}
}