{
  "type": "Feature",
  "properties": {
    "addr:full":"Grand\u00b4place 0 Binche Hainaut 7130",
    "addr:housenumber":"0",
    "addr:postcode":"7130",
    "addr:street":"Grand\u00b4Place",
    "iso:country":"BE",
    "sg:address":"Grand\u00b4place 0",
    "sg:city":"Binche",
    "sg:orig_category":"Toeristische diensten",
    "sg:phone":"+32 64 33 67 27",
    "sg:postcode":"7130",
    "sg:province":"Hainaut",
    "wof:name":"Office Du Tourisme",
    "wof:placetype":"venue"
},
  "geometry": {"coordinates":[4.164949894,50.4109153748],"type":"Point"}
}