{
  "type": "Feature",
  "properties": {
    "iso:country":"BE",
    "sg:address":"Rue Des Ploquettes 8",
    "sg:city":"Verviers",
    "sg:orig_category":"Hypotheken and hypotheekbanken Immobili\u00ebnkantoren Verbruikerskredietinstellingen Verzekeringsmakelaa",
    "sg:phone":"+32 87 23 15 81",
    "sg:postcode":"4800",
    "sg:province":"Li\u00e8ge",
    "wof:name":"V.d.s. Luc Vanderstraeten",
    "wof:placetype":"venue"
},
  "geometry": {"coordinates":[5.8618121147,50.5907249451],"type":"Point"}
}