{
  "type": "Feature",
  "properties": {
    "addr:full":"Roeselaarsestraat 11 Izegem West-Vlaanderen 8870",
    "addr:housenumber":"11",
    "addr:postcode":"8870",
    "addr:street":"Roeselaarsestraat",
    "iso:country":"BE",
    "sg:address":"Roeselaarsestraat 11",
    "sg:city":"Izegem",
    "sg:classifiers":[
        {
            "category":"Shopping",
            "subcategory":"Luggage & Leather Goods",
            "type":"Retail Goods"
        }
    ],
    "sg:phone":"+32 51 30 27 26",
    "sg:postcode":"8870",
    "sg:province":"West-Vlaanderen",
    "sg:tags":[
        "-"
    ],
    "wof:name":"Seynaeve Lederwaren",
    "wof:placetype":"venue"
},
  "geometry": {"coordinates":[3.2134048939,50.917881012],"type":"Point"}
}