{
  "type": "Feature",
  "properties": {
    "iso:country":"BE",
    "sg:address":"Kabienstraat 3b",
    "sg:city":"Bocholt",
    "sg:orig_category":"Meubelzaken, woning- and keukeninrichting",
    "sg:phone":"+32 89 47 11 53",
    "sg:postcode":"3950",
    "sg:province":"Limburg",
    "wof:name":"Mebo",
    "wof:placetype":"venue"
},
  "geometry": {"coordinates":[5.5751018524,51.1898345947],"type":"Point"}
}