{
  "type": "Feature",
  "properties": {
    "iso:country":"BE",
    "sg:address":"Avenue Du Tennis 6b25",
    "sg:city":"Verviers",
    "sg:orig_category":"Beheer onroerend goed",
    "sg:phone":"+32 87 22 56 08",
    "sg:postcode":"4802",
    "sg:province":"Li\u00e8ge",
    "wof:name":"Beaudon",
    "wof:placetype":"venue"
},
  "geometry": {"coordinates":[5.8667669296,50.5762939453],"type":"Point"}
}