{
  "type": "Feature",
  "properties": {
    "iso:country":"BE",
    "sg:address":"Rue De La Gare 41",
    "sg:city":"Bievre",
    "sg:orig_category":"Gespecialiseerde niet-residenti\u00eble bouw",
    "sg:phone":"+32 61 51 22 90",
    "sg:postcode":"5555",
    "sg:province":"Namur",
    "wof:name":"Clarinval",
    "wof:placetype":"venue"
},
  "geometry": {"coordinates":[5.0299768448,49.9360466003],"type":"Point"}
}