{
  "type": "Feature",
  "properties": {
    "iso:country":"BE",
    "sg:address":"Markt 1",
    "sg:city":"Londerzeel",
    "sg:orig_category":"S\u00e9lection de personnel and placement",
    "sg:phone":"+32 52 30 36 16",
    "sg:postcode":"1840",
    "sg:province":"Vlaams-Brabant",
    "wof:name":"Pwa",
    "wof:placetype":"venue"
},
  "geometry": {"coordinates":[4.3015069962,51.0014076233],"type":"Point"}
}