{
  "type": "Feature",
  "properties": {
    "iso:country":"BE",
    "sg:address":"Pulmstraat 13",
    "sg:city":"Zingem",
    "sg:classifiers":[
        {
            "category":"Personal",
            "subcategory":"Beauty Salon",
            "type":"Services"
        }
    ],
    "sg:phone":"+32 9 384 60 49",
    "sg:postcode":"9750",
    "sg:province":"Oost-Vlaanderen",
    "sg:tags":[
        "lady",
        "-",
        "hairdressing"
    ],
    "wof:name":"Stefanie",
    "wof:placetype":"venue"
},
  "geometry": {"coordinates":[3.639662981,50.9068069458],"type":"Point"}
}