{
  "type": "Feature",
  "properties": {
    "iso:country":"BE",
    "sg:address":"Chazallaan 103",
    "sg:city":"Schaarbeek/schaerbeek",
    "sg:classifiers":[
        {
            "category":"Insurance",
            "subcategory":"Insurance Agent",
            "type":"Services"
        }
    ],
    "sg:phone":"+32 2 241 72 09",
    "sg:postcode":"1030",
    "sg:province":"Bruxelles-Capitale",
    "sg:tags":[
        "verzekeringsmakelaars",
        "expert"
    ],
    "wof:name":"E. De Cat",
    "wof:placetype":"venue"
},
  "geometry": {"coordinates":[4.3903889656,50.8570137024],"type":"Point"}
}