{
  "type": "Feature",
  "properties": {
    "iso:country":"BE",
    "sg:address":"Rue Saint-hilaire 82",
    "sg:city":"Morlanwelz",
    "sg:orig_category":"V\u00e9los",
    "sg:phone":"+32 64 44 59 77",
    "sg:postcode":"7141",
    "sg:province":"Hainaut",
    "wof:name":"Philippe Wins",
    "wof:placetype":"venue"
},
  "geometry": {"coordinates":[4.2498998642,50.4337806702],"type":"Point"}
}