{
  "type": "Feature",
  "properties": {
    "addr:full":"Rue Des Charrons 12 Ans (grand) Li\u00e8ge 4430",
    "addr:housenumber":"12",
    "addr:postcode":"4430",
    "addr:street":"Rue Des Charrons;Grand Lie\u0300Ge",
    "iso:country":"BE",
    "sg:address":"Rue Des Charrons 12",
    "sg:city":"Ans (grand)",
    "sg:orig_category":"Kapsalons",
    "sg:phone":"+32 4 263 18 64",
    "sg:postcode":"4430",
    "sg:province":"Li\u00e8ge",
    "wof:name":"Coiffure Dominique",
    "wof:placetype":"venue"
},
  "geometry": {"coordinates":[5.5046401024,50.6698265076],"type":"Point"}
}