{
  "type": "Feature",
  "properties": {
    "iso:country":"BE",
    "sg:address":"Gebroeders Aertslaan 15",
    "sg:city":"Puurs (ruisbroek)",
    "sg:classifiers":[
        {
            "category":"Structure",
            "subcategory":"Office Building",
            "type":"Public Place"
        }
    ],
    "sg:phone":"+32 3 889 79 73",
    "sg:postcode":"2870",
    "sg:province":"Antwerpen",
    "sg:tags":[
        "-",
        "type",
        "door",
        "sliding",
        "overhead"
    ],
    "wof:name":"Pauwels J",
    "wof:placetype":"venue"
},
  "geometry": {"coordinates":[4.3330187798,51.0787734985],"type":"Point"}
}