{
  "type": "Feature",
  "properties": {
    "addr:full":"Langestraat 185 Brugge West-Vlaanderen 8000",
    "addr:housenumber":"185",
    "addr:postcode":"8000",
    "addr:street":"Langestraat",
    "iso:country":"BE",
    "sg:address":"Langestraat 185",
    "sg:city":"Brugge",
    "sg:orig_category":"Biens d'occasion",
    "sg:phone":"+32 50 34 14 09",
    "sg:postcode":"8000",
    "sg:province":"West-Vlaanderen",
    "wof:name":"Sue Ryder Shop",
    "wof:placetype":"venue"
},
  "geometry": {"coordinates":[3.2395091057,51.2126541138],"type":"Point"}
}