{
  "type": "Feature",
  "properties": {
    "addr:full":"Koolskampstraat 48 Pittem West-Vlaanderen 8740",
    "addr:housenumber":"48",
    "addr:postcode":"8740",
    "addr:street":"Koolskampstraat",
    "iso:country":"BE",
    "sg:address":"Koolskampstraat 48",
    "sg:city":"Pittem",
    "sg:orig_category":"Maisons de repos and r\u00e9sidences",
    "sg:phone":"+32 51 46 60 77",
    "sg:postcode":"8740",
    "sg:province":"West-Vlaanderen",
    "wof:name":"Rusthuis St.remi",
    "wof:placetype":"venue"
},
  "geometry": {"coordinates":[3.2552530766,50.9967422485],"type":"Point"}
}