{
  "type": "Feature",
  "properties": {
    "addr:full":"Kasteeldreef 8-10 Lede Oost-Vlaanderen 9340",
    "addr:housenumber":"8-10",
    "addr:postcode":"9340",
    "addr:street":"Kasteeldreef",
    "iso:country":"BE",
    "sg:address":"Kasteeldreef 8-10",
    "sg:city":"Lede",
    "sg:classifiers":[
        {
            "category":"Shopping",
            "subcategory":"Computers & Home Electronics",
            "type":"Retail Goods"
        }
    ],
    "sg:phone":"+32 53 80 35 89",
    "sg:postcode":"9340",
    "sg:province":"Oost-Vlaanderen",
    "sg:tags":[
        "-",
        "television",
        "radio"
    ],
    "wof:name":"De Radiodokter Bvba",
    "wof:placetype":"venue"
},
  "geometry": {"coordinates":[3.9798429012,50.9664268494],"type":"Point"}
}