{
  "type": "Feature",
  "properties": {
    "iso:country":"BE",
    "sg:address":"Chemin De La Procession 11",
    "sg:city":"Lens",
    "sg:orig_category":"Installatie van houten of kunststof schrijnwerk",
    "sg:phone":"+32 68 45 44 41",
    "sg:postcode":"7870",
    "sg:province":"Hainaut",
    "wof:name":"Francis Carovis",
    "wof:placetype":"venue"
},
  "geometry": {"coordinates":[3.9001870155,50.5572738647],"type":"Point"}
}