{
  "type": "Feature",
  "properties": {
    "iso:country":"BE",
    "sg:address":"Rue Du Quinze Ao\u00fbt 176",
    "sg:city":"Ans",
    "sg:classifiers":[
        {
            "category":"Professional",
            "subcategory":"Accounting & Tax Preparation",
            "type":"Services"
        }
    ],
    "sg:phone":"+32 4 247 40 94",
    "sg:postcode":"4430",
    "sg:province":"Li\u00e8ge",
    "sg:tags":[
        "accountant"
    ],
    "wof:name":"Tilkin F",
    "wof:placetype":"venue"
},
  "geometry": {"coordinates":[5.5370001793,50.6580886841],"type":"Point"}
}