{
  "type": "Feature",
  "properties": {
    "addr:full":"Gobbelsrode 160 Holsbeek (kortrijk-dutsel) Vlaams-Brabant 3220",
    "addr:housenumber":"160",
    "addr:postcode":"3220",
    "addr:street":"Gobbelsrode",
    "iso:country":"BE",
    "sg:address":"Gobbelsrode 160",
    "sg:city":"Holsbeek (kortrijk-dutsel)",
    "sg:classifiers":[
        {
            "category":"Utilities",
            "subcategory":"Refuse",
            "type":"Services"
        }
    ],
    "sg:phone":"+32 16 62 33 95",
    "sg:postcode":"3220",
    "sg:province":"Vlaams-Brabant",
    "sg:tags":[
        "removal"
    ],
    "wof:name":"Jozef's Lift Service",
    "wof:placetype":"venue"
},
  "geometry": {"coordinates":[4.7575721741,50.9207267761],"type":"Point"}
}