{
  "type": "Feature",
  "properties": {
    "addr:full":"Leopoldstraat 25 Kalmthout Antwerpen 2920",
    "addr:housenumber":"25",
    "addr:postcode":"2920",
    "addr:street":"Leopoldstraat",
    "iso:country":"BE",
    "sg:address":"Leopoldstraat 25",
    "sg:city":"Kalmthout",
    "sg:orig_category":"Diverse opleidingen and onderwijs",
    "sg:phone":"+32 3 666 35 86",
    "sg:postcode":"2920",
    "sg:province":"Antwerpen",
    "wof:name":"Ingrid Antonissen",
    "wof:placetype":"venue"
},
  "geometry": {"coordinates":[4.464553833,51.366985321],"type":"Point"}
}