{
  "type": "Feature",
  "properties": {
    "addr:full":"Bougnimont 16 Libramont-chevigny Luxembourg 6800",
    "addr:housenumber":"16",
    "addr:postcode":"6800",
    "addr:street":"Bougnimont",
    "iso:country":"BE",
    "sg:address":"Bougnimont 16",
    "sg:city":"Libramont-chevigny",
    "sg:orig_category":"Eleveurs de bovins",
    "sg:phone":"+32 61 25 51 93",
    "sg:postcode":"6800",
    "sg:province":"Luxembourg",
    "wof:name":"Alain Delaisse",
    "wof:placetype":"venue"
},
  "geometry": {"coordinates":[5.3761348724,49.9199943542],"type":"Point"}
}