{
  "type": "Feature",
  "properties": {
    "iso:country":"BE",
    "sg:address":"Nilleveldstraat 17",
    "sg:city":"Hoeilaart",
    "sg:orig_category":"Studios photographiques",
    "sg:phone":"+32 2 657 42 47",
    "sg:postcode":"1560",
    "sg:province":"Vlaams-Brabant",
    "wof:name":"Ghislain Goossens",
    "wof:placetype":"venue"
},
  "geometry": {"coordinates":[4.4756407738,50.7595558167],"type":"Point"}
}