{
  "type": "Feature",
  "properties": {
    "iso:country":"BE",
    "sg:address":"Rue Trapp\u00c9 8",
    "sg:city":"Li\u00c8ge",
    "sg:orig_category":"Artsen and specialisten",
    "sg:phone":"+32 4 222 91 07",
    "sg:postcode":"4000",
    "sg:province":"Li\u00e8ge",
    "wof:name":"Bassam El-khouri Mikhael",
    "wof:placetype":"venue"
},
  "geometry": {"coordinates":[5.5645198822,50.6399688721],"type":"Point"}
}