{
  "type": "Feature",
  "properties": {
    "addr:full":"Meistraat 31 Evergem Oost-Vlaanderen 9940",
    "addr:housenumber":"31",
    "addr:postcode":"9940",
    "addr:street":"Meistraat;Oost-Vlaanderen",
    "iso:country":"BE",
    "sg:address":"Meistraat 31",
    "sg:city":"Evergem",
    "sg:orig_category":"Architecten",
    "sg:phone":"+32 9 357 45 07",
    "sg:postcode":"9940",
    "sg:province":"Oost-Vlaanderen",
    "wof:name":"Arnoud Hulpia",
    "wof:placetype":"venue"
},
  "geometry": {"coordinates":[3.6526019573,51.1193008423],"type":"Point"}
}