{
  "type": "Feature",
  "properties": {
    "iso:country":"BE",
    "sg:address":"Avenue Wellington 116",
    "sg:city":"Bruxelles (uccle)",
    "sg:classifiers":[
        {
            "category":"Professional",
            "subcategory":"Management & Consulting",
            "type":"Services"
        }
    ],
    "sg:phone":"+32 2 374 88 18",
    "sg:postcode":"1180",
    "sg:province":"Bruxelles-Capitale",
    "sg:tags":[
        "marketing",
        "-",
        "direct",
        "consultant"
    ],
    "wof:name":"C-link Colis",
    "wof:placetype":"venue"
},
  "geometry": {"coordinates":[4.3751010895,50.7827644348],"type":"Point"}
}