{
  "type": "Feature",
  "properties": {
    "addr:full":"31 Rue De La Station 7160 Chapelle-lez-herlaimont 31",
    "addr:housenumber":"31;31",
    "addr:postcode":"7160 chapelle-lez-herlaimont",
    "addr:street":"Rue De La Station",
    "iso:country":"BE",
    "sg:address":"31",
    "sg:city":"Rue De La Station 7160 Chapelle-lez-herlaimont",
    "sg:classifiers":[
        {
            "category":"Building & Trades",
            "subcategory":"Construction",
            "type":"Services"
        }
    ],
    "sg:phone":"+32 64 44 24 21",
    "sg:postcode":"31",
    "sg:tags":[
        "work",
        "public"
    ],
    "wof:name":"Entreprise Arille Baise Sa",
    "wof:placetype":"venue"
},
  "geometry": {"coordinates":[4.2777872086,50.4683303833],"type":"Point"}
}