{
  "type": "Feature",
  "properties": {
    "addr:full":"Rue D'elsenbosch 10 H\u00e9l\u00e9cine (opheylissem) Brabant Wallon 1357",
    "addr:housenumber":"10",
    "addr:postcode":"1357",
    "addr:street":"Rue D'Elsenbosch;Wallon",
    "iso:country":"BE",
    "sg:address":"Rue D'elsenbosch 10",
    "sg:city":"H\u00e9l\u00e9cine (opheylissem)",
    "sg:classifiers":[
        {
            "category":"Professional",
            "subcategory":"Art Services",
            "type":"Services"
        }
    ],
    "sg:phone":"+32 19 65 59 25",
    "sg:postcode":"1357",
    "sg:province":"Brabant Wallon",
    "sg:tags":[
        "photography",
        "reporting",
        "-"
    ],
    "wof:name":"Willocq G",
    "wof:placetype":"venue"
},
  "geometry": {"coordinates":[4.9850101471,50.7423744202],"type":"Point"}
}