{
  "type": "Feature",
  "properties": {
    "iso:country":"BE",
    "sg:address":"Alsembergse Steenweg 611",
    "sg:city":"Ukkel/uccle",
    "sg:orig_category":"Bloemen and planten",
    "sg:phone":"+32 2 345 21 36",
    "sg:postcode":"1180",
    "sg:province":"Bruxelles-Capitale",
    "wof:name":"D\u00c9cor Fleur Bleue",
    "wof:placetype":"venue"
},
  "geometry": {"coordinates":[4.3367462158,50.8083267212],"type":"Point"}
}