{
  "type": "Feature",
  "properties": {
    "addr:full":"Rue Grinchamps 1 Lobbes Hainaut 6543",
    "addr:housenumber":"1",
    "addr:postcode":"6543",
    "addr:street":"Rue Grinchamps",
    "iso:country":"BE",
    "sg:address":"Rue Grinchamps 1",
    "sg:city":"Lobbes",
    "sg:orig_category":"HUISBRANDOLIE",
    "sg:phone":"+32 71 59 30 37",
    "sg:postcode":"6543",
    "sg:province":"Hainaut",
    "wof:name":"Eric Dubois",
    "wof:placetype":"venue"
},
  "geometry": {"coordinates":[4.2217898369,50.3536605835],"type":"Point"}
}