{
  "type": "Feature",
  "properties": {
    "iso:country":"BE",
    "sg:address":"Nieuwe Kaai 41",
    "sg:city":"Turnhout",
    "sg:orig_category":"Jeux and jouets",
    "sg:phone":"+32 14 43 91 21",
    "sg:postcode":"2300",
    "sg:province":"Antwerpen",
    "wof:name":"Videospellenparadijs",
    "wof:placetype":"venue"
},
  "geometry": {"coordinates":[4.9306731224,51.3256950378],"type":"Point"}
}