{
  "type": "Feature",
  "properties": {
    "iso:country":"BE",
    "sg:address":"Adolf Buylstraat 1ba",
    "sg:city":"Oostende",
    "sg:classifiers":[
        {
            "category":"Restaurant",
            "type":"Food & Drink"
        }
    ],
    "sg:phone":"+32 59 70 08 37",
    "sg:postcode":"8400",
    "sg:province":"West-Vlaanderen",
    "wof:name":"Chopin",
    "wof:placetype":"venue"
},
  "geometry": {"coordinates":[2.9167850018,51.2320365906],"type":"Point"}
}