{
  "type": "Feature",
  "properties": {
    "addr:full":"Rue Reine Astrid 49b75 Seraing Li\u00e8ge 4100",
    "addr:housenumber":"49b75",
    "addr:postcode":"4100",
    "addr:street":"Rue Reine Astrid",
    "iso:country":"BE",
    "sg:address":"Rue Reine Astrid 49b75",
    "sg:city":"Seraing",
    "sg:orig_category":"Ordinateurs and \u00e9quipement informatique",
    "sg:phone":"+32 4 254 55 84",
    "sg:postcode":"4100",
    "sg:province":"Li\u00e8ge",
    "wof:name":"Philippe Bellefontaine",
    "wof:placetype":"venue"
},
  "geometry": {"coordinates":[5.5397801399,50.5721588135],"type":"Point"}
}