{
  "type": "Feature",
  "properties": {
    "addr:full":"Schimpstraat 46 Hoeilaart Vlaams-Brabant 1560",
    "addr:housenumber":"46",
    "addr:postcode":"1560",
    "addr:street":"Schimpstraat",
    "iso:country":"BE",
    "sg:address":"Schimpstraat 46",
    "sg:city":"Hoeilaart",
    "sg:classifiers":[
        {
            "category":"Professional",
            "subcategory":"Accounting & Tax Preparation",
            "type":"Services"
        }
    ],
    "sg:phone":"+32 2 657 05 80",
    "sg:postcode":"1560",
    "sg:province":"Vlaams-Brabant",
    "sg:tags":[
        "accountant"
    ],
    "wof:name":"Jean Boels",
    "wof:placetype":"venue"
},
  "geometry": {"coordinates":[4.4865198135,50.7535400391],"type":"Point"}
}