{
  "type": "Feature",
  "properties": {
    "addr:full":"Boomsesteenweg 347 Antwerpen (wilrijk) Antwerpen 2610",
    "addr:housenumber":"347",
    "addr:postcode":"2610",
    "addr:street":"Boomsesteenweg;Antwerpen",
    "iso:country":"BE",
    "sg:address":"Boomsesteenweg 347",
    "sg:city":"Antwerpen (wilrijk)",
    "sg:classifiers":[
        {
            "category":"Autos & Motor Vehicles",
            "subcategory":"Auto Supplies",
            "type":"Retail Goods"
        }
    ],
    "sg:phone":"+32 3 828 90 20",
    "sg:postcode":"2610",
    "sg:province":"Antwerpen",
    "sg:tags":[
        "automobile",
        "absorber",
        "shock",
        "-"
    ],
    "wof:name":"Boge-ottorem",
    "wof:placetype":"venue"
},
  "geometry": {"coordinates":[4.3884248734,51.1863555908],"type":"Point"}
}