{
  "type": "Feature",
  "properties": {
    "addr:full":"Kerkstraat 343 Blankenberge West-Vlaanderen 8370",
    "addr:housenumber":"343",
    "addr:postcode":"8370",
    "addr:street":"Kerkstraat",
    "iso:country":"BE",
    "sg:address":"Kerkstraat 343",
    "sg:city":"Blankenberge",
    "sg:orig_category":"Opticiens",
    "sg:phone":"+32 50 41 95 72",
    "sg:postcode":"8370",
    "sg:province":"West-Vlaanderen",
    "wof:name":"De Ridder Optiek",
    "wof:placetype":"venue"
},
  "geometry": {"coordinates":[3.1402010918,51.3058776855],"type":"Point"}
}