{
  "type": "Feature",
  "properties": {
    "addr:full":"Dorpheidestraat 71 Diepenbeek Limburg 3590",
    "addr:housenumber":"71",
    "addr:postcode":"3590",
    "addr:street":"Dorpheidestraat",
    "iso:country":"BE",
    "sg:address":"Dorpheidestraat 71",
    "sg:city":"Diepenbeek",
    "sg:orig_category":"Kapsalons",
    "sg:phone":"+32 11 33 22 21",
    "sg:postcode":"3590",
    "sg:province":"Limburg",
    "wof:name":"Cifa Hair Fashion",
    "wof:placetype":"venue"
},
  "geometry": {"coordinates":[5.4290800095,50.9280776978],"type":"Point"}
}