{
  "type": "Feature",
  "properties": {
    "iso:country":"BE",
    "sg:address":"Rue Guido Gezelle 57",
    "sg:city":"Bruxelles (schaerbeek)",
    "sg:classifiers":[
        {
            "category":"Bars & Pubs",
            "type":"Food & Drink"
        }
    ],
    "sg:phone":"+32 2 215 86 09",
    "sg:postcode":"1030",
    "sg:province":"Bruxelles-Capitale",
    "sg:tags":[
        "tavern"
    ],
    "wof:name":"Belved\u00e8re",
    "wof:placetype":"venue"
},
  "geometry": {"coordinates":[4.3928427696,50.8751029968],"type":"Point"}
}