{
  "type": "Feature",
  "properties": {
    "addr:full":"Universiteitstraat 8 Gent Oost-Vlaanderen 9000",
    "addr:housenumber":"8",
    "addr:postcode":"9000",
    "addr:street":"Universiteitstraat;Oost-Vlaanderen",
    "iso:country":"BE",
    "sg:address":"Universiteitstraat 8",
    "sg:city":"Gent",
    "sg:orig_category":"Zalen voor culturele evenementen",
    "sg:phone":"+32 9 264 68 77",
    "sg:postcode":"9000",
    "sg:province":"Oost-Vlaanderen",
    "wof:name":"Liga Voor Mensenrechten",
    "wof:placetype":"venue"
},
  "geometry": {"coordinates":[3.7243480682,51.0512428284],"type":"Point"}
}