{
  "type": "Feature",
  "properties": {
    "iso:country":"BE",
    "sg:address":"Werft 9",
    "sg:city":"Geel",
    "sg:orig_category":"V\u00eatements",
    "sg:phone":"+32 14 58 26 44",
    "sg:postcode":"2440",
    "sg:province":"Antwerpen",
    "wof:name":"Outfit",
    "wof:placetype":"venue"
},
  "geometry": {"coordinates":[4.989689827,51.162109375],"type":"Point"}
}