{
  "type": "Feature",
  "properties": {
    "addr:full":"Ernest Claeslaan 20 Rumst Antwerpen 2840",
    "addr:housenumber":"20",
    "addr:postcode":"2840",
    "addr:street":"Ernest Claeslaan",
    "iso:country":"BE",
    "sg:address":"Ernest Claeslaan 20",
    "sg:city":"Rumst",
    "sg:orig_category":"Sportclubs",
    "sg:phone":"+32 3 844 64 65",
    "sg:postcode":"2840",
    "sg:province":"Antwerpen",
    "wof:name":"Lenig En Vrij",
    "wof:placetype":"venue"
},
  "geometry": {"coordinates":[4.3664240837,51.1089248657],"type":"Point"}
}