{
  "type": "Feature",
  "properties": {
    "addr:full":"Aalbekesteenweg 253 Moeskroen/mouscron Hainaut 7700",
    "addr:housenumber":"253",
    "addr:postcode":"7700",
    "addr:street":"Aalbekesteenweg",
    "iso:country":"BE",
    "sg:address":"Aalbekesteenweg 253",
    "sg:city":"Moeskroen/mouscron",
    "sg:orig_category":"Beheer onroerend goed",
    "sg:phone":"+32 56 34 71 98",
    "sg:postcode":"7700",
    "sg:province":"Hainaut",
    "wof:name":"Antoon Van Nuffel",
    "wof:placetype":"venue"
},
  "geometry": {"coordinates":[3.2323200703,50.7400932312],"type":"Point"}
}