{
  "type": "Feature",
  "properties": {
    "addr:full":"Sint-thomasstraat 14 Antwerpen Antwerpen 2018",
    "addr:housenumber":"14",
    "addr:postcode":"2018",
    "addr:street":"Sint-Thomasstraat",
    "iso:country":"BE",
    "sg:address":"Sint-thomasstraat 14",
    "sg:city":"Antwerpen",
    "sg:orig_category":"Bloemen and planten",
    "sg:phone":"+32 3 218 91 40",
    "sg:postcode":"2018",
    "sg:province":"Antwerpen",
    "wof:name":"Eric Designs Bloemen En Planten",
    "wof:placetype":"venue"
},
  "geometry": {"coordinates":[4.4119968414,51.2043571472],"type":"Point"}
}