{
  "type": "Feature",
  "properties": {
    "iso:country":"BE",
    "sg:address":"Dam 36",
    "sg:city":"Izegem",
    "sg:orig_category":"D\u00e9corateurs d'int\u00e9rieur",
    "sg:phone":"+32 51 31 33 61",
    "sg:postcode":"8870",
    "sg:province":"West-Vlaanderen",
    "wof:name":"Patrick Vandoorne",
    "wof:placetype":"venue"
},
  "geometry": {"coordinates":[3.217124939,50.9243240356],"type":"Point"}
}