{
  "type": "Feature",
  "properties": {
    "addr:full":"Rue De La Lib\u00c9ration 63-65 Rochefort Namur 5580",
    "addr:postcode":"63-65 rochefort;5580",
    "addr:street":"Rue De La Libe\u0301Ration",
    "iso:country":"BE",
    "sg:address":"Rue De La Lib\u00c9ration 63-65",
    "sg:city":"Rochefort",
    "sg:orig_category":"Voertuigen",
    "sg:phone":"+32 84 21 11 72",
    "sg:postcode":"5580",
    "sg:province":"Namur",
    "wof:name":"Garage Sion",
    "wof:placetype":"venue"
},
  "geometry": {"coordinates":[5.2119131088,50.1655807495],"type":"Point"}
}