{
  "type": "Feature",
  "properties": {
    "iso:country":"BE",
    "sg:address":"Avenue Du Parc 118",
    "sg:city":"Bruxelles (forest)",
    "sg:classifiers":[
        {
            "category":"Bars & Pubs",
            "type":"Food & Drink"
        }
    ],
    "sg:phone":"+32 2 538 86 66",
    "sg:postcode":"1190",
    "sg:province":"Bruxelles-Capitale",
    "wof:name":"Villa Pouca",
    "wof:placetype":"venue"
},
  "geometry": {"coordinates":[4.3396940231,50.8253974915],"type":"Point"}
}