{
  "type": "Feature",
  "properties": {
    "addr:full":"Ingelmunstersteenweg 89 Oostrozebeke West-Vlaanderen 8780",
    "addr:housenumber":"89",
    "addr:postcode":"8780",
    "addr:street":"Ingelmunstersteenweg",
    "iso:country":"BE",
    "sg:address":"Ingelmunstersteenweg 89",
    "sg:city":"Oostrozebeke",
    "sg:orig_category":"Jardinage",
    "sg:phone":"+32 56 66 88 95",
    "sg:postcode":"8780",
    "sg:province":"West-Vlaanderen",
    "wof:name":"Christoph Soenens",
    "wof:placetype":"venue"
},
  "geometry": {"coordinates":[3.3161048889,50.9189758301],"type":"Point"}
}