{
  "type": "Feature",
  "properties": {
    "iso:country":"BE",
    "sg:address":"Belzeelsestraat 18",
    "sg:city":"Evergem",
    "sg:classifiers":[
        {
            "category":"Food & Beverages",
            "subcategory":"Supermarket",
            "type":"Retail Goods"
        }
    ],
    "sg:phone":"+32 9 253 02 44",
    "sg:postcode":"9940",
    "sg:province":"Oost-Vlaanderen",
    "sg:tags":[
        "department",
        "store"
    ],
    "wof:name":"Spar Evergem",
    "wof:placetype":"venue"
},
  "geometry": {"coordinates":[3.6596140862,51.1009407043],"type":"Point"}
}