{
  "type": "Feature",
  "properties": {
    "iso:country":"BE",
    "sg:address":"Merellaan 8",
    "sg:city":"Kalmthout",
    "sg:classifiers":[
        {
            "category":"Professional",
            "subcategory":"Management & Consulting",
            "type":"Services"
        }
    ],
    "sg:phone":"+32 3 666 27 72",
    "sg:postcode":"2920",
    "sg:province":"Antwerpen",
    "sg:tags":[
        "consultant"
    ],
    "wof:name":"Vetas Bvba",
    "wof:placetype":"venue"
},
  "geometry": {"coordinates":[4.4600567818,51.3593635559],"type":"Point"}
}