{
  "type": "Feature",
  "properties": {
    "iso:country":"BE",
    "sg:address":"Kleine Katelijnestraat 32",
    "sg:city":"Hulshout",
    "sg:classifiers":[
        {
            "category":"Cafe",
            "type":"Food & Drink"
        }
    ],
    "sg:phone":"+32 15 22 21 64",
    "sg:postcode":"2235",
    "sg:province":"Antwerpen",
    "sg:tags":[
        "caf\u00e9s"
    ],
    "wof:name":"Jan Papen",
    "wof:placetype":"venue"
},
  "geometry": {"coordinates":[4.8082880974,51.0658187866],"type":"Point"}
}