{
  "type": "Feature",
  "properties": {
    "iso:country":"BE",
    "sg:address":"Rue Dierin Patar 14",
    "sg:city":"Aywaille",
    "sg:classifiers":[
        {
            "category":"Cafe",
            "type":"Food & Drink"
        }
    ],
    "sg:phone":"+32 4 384 87 34",
    "sg:postcode":"4920",
    "sg:province":"Li\u00e8ge",
    "sg:tags":[
        "caf\u00e9s"
    ],
    "wof:name":"Bianca Dall'oca",
    "wof:placetype":"venue"
},
  "geometry": {"coordinates":[5.6743149757,50.4732933044],"type":"Point"}
}