{
  "type": "Feature",
  "properties": {
    "iso:country":"BE",
    "sg:address":"Rue Du Casino 13",
    "sg:city":"Tournai",
    "sg:orig_category":"Sportclubs",
    "sg:phone":"+32 69 22 39 08",
    "sg:postcode":"7500",
    "sg:province":"Hainaut",
    "wof:name":"Classic Racing Motocycle",
    "wof:placetype":"venue"
},
  "geometry": {"coordinates":[3.3711109161,50.6176071167],"type":"Point"}
}