{
  "type": "Feature",
  "properties": {
    "iso:country":"BE",
    "sg:address":"Pierstraat 406",
    "sg:city":"Aartselaar",
    "sg:classifiers":[
        {
            "category":"Cafe",
            "type":"Food & Drink"
        }
    ],
    "sg:phone":"+32 3 888 91 64",
    "sg:postcode":"2630",
    "sg:province":"Antwerpen",
    "sg:tags":[
        "caf\u00e9s"
    ],
    "wof:name":"Fa. Van Wouwe Gan",
    "wof:placetype":"venue"
},
  "geometry": {"coordinates":[4.357940197,51.1101226807],"type":"Point"}
}