{
  "type": "Feature",
  "properties": {
    "iso:country":"BE",
    "sg:address":"Nieuwland 11",
    "sg:city":"Gistel",
    "sg:orig_category":"Eleveurs de bovins. Eleveurs and marchands de porcs",
    "sg:phone":"+32 59 27 94 29",
    "sg:postcode":"8470",
    "sg:province":"West-Vlaanderen",
    "wof:name":"Gentiel Deklerck",
    "wof:placetype":"venue"
},
  "geometry": {"coordinates":[2.9867799282,51.1426696777],"type":"Point"}
}