{
  "type": "Feature",
  "properties": {
    "addr:full":"Aven Ackers 13 Verrebroek-beveren Oost-Vlaanderen 9130",
    "addr:housenumber":"13",
    "addr:postcode":"9130",
    "addr:street":"Aven Ackers;Oost-Vlaanderen",
    "iso:country":"BE",
    "sg:address":"Aven Ackers 13",
    "sg:city":"Verrebroek-beveren",
    "sg:classifiers":[
        {
            "category":"Building & Trades",
            "subcategory":"Construction",
            "type":"Services"
        }
    ],
    "sg:phone":"+32 3 735 03 80",
    "sg:postcode":"9130",
    "sg:province":"Oost-Vlaanderen",
    "sg:tags":[
        "work",
        "public"
    ],
    "wof:name":"V.m.b. Nv",
    "wof:placetype":"venue"
},
  "geometry": {"coordinates":[4.175344944,51.2897109985],"type":"Point"}
}