{
  "type": "Feature",
  "properties": {
    "iso:country":"BE",
    "sg:address":"Windmolenlaan 20",
    "sg:city":"Zaventem (sterrebeek)",
    "sg:classifiers":[
        {
            "category":"Professional",
            "subcategory":"Accounting & Tax Preparation",
            "type":"Services"
        }
    ],
    "sg:phone":"+32 2 731 62 15",
    "sg:postcode":"1933",
    "sg:province":"Vlaams-Brabant",
    "sg:tags":[
        "accountant"
    ],
    "wof:name":"De Craecker M",
    "wof:placetype":"venue"
},
  "geometry": {"coordinates":[4.510737896,50.8643035889],"type":"Point"}
}