{
  "type": "Feature",
  "properties": {
    "iso:country":"BE",
    "sg:address":"H. Teirlinck 15",
    "sg:city":"Gent",
    "sg:orig_category":"Mat\u00e9riel \u00e9lectrique and \u00e9lectronique Gr",
    "sg:phone":"+32 9 353 91 11",
    "sg:postcode":"9041",
    "sg:province":"Oost-Vlaanderen",
    "wof:name":"Rittal",
    "wof:placetype":"venue"
},
  "geometry": {"coordinates":[3.7895491123,51.0792732239],"type":"Point"}
}