{
  "type": "Feature",
  "properties": {
    "addr:full":"Avelgemstraat 2 Zwevegem West-Vlaanderen 8550",
    "addr:housenumber":"2",
    "addr:postcode":"8550",
    "addr:street":"Avelgemstraat",
    "iso:country":"BE",
    "sg:address":"Avelgemstraat 2",
    "sg:city":"Zwevegem",
    "sg:orig_category":"Herstelling horloges and juwelen Juwelen and horloges",
    "sg:phone":"+32 56 75 54 03",
    "sg:postcode":"8550",
    "sg:province":"West-Vlaanderen",
    "wof:name":"Tjoens",
    "wof:placetype":"venue"
},
  "geometry": {"coordinates":[3.355880022,50.7989501953],"type":"Point"}
}