{
  "type": "Feature",
  "properties": {
    "iso:country":"BE",
    "sg:address":"Avenue G\u00c9n\u00c9ral Cambronne 24",
    "sg:city":"Lasne",
    "sg:orig_category":"Landmeters",
    "sg:phone":"+32 2 633 26 46",
    "sg:postcode":"1380",
    "sg:province":"Brabant Wallon",
    "wof:name":"R. De Bruyne",
    "wof:placetype":"venue"
},
  "geometry": {"coordinates":[4.4150400162,50.6645507812],"type":"Point"}
}