{
  "type": "Feature",
  "properties": {
    "iso:country":"BE",
    "sg:address":"Kouterstraat 22",
    "sg:city":"Brakel",
    "sg:orig_category":"Alternatieve geneeskunde",
    "sg:phone":"+32 55 42 51 52",
    "sg:postcode":"9660",
    "sg:province":"Oost-Vlaanderen",
    "wof:name":"Di\u00cbtist Garez C.",
    "wof:placetype":"venue"
},
  "geometry": {"coordinates":[3.7487499714,50.8078651428],"type":"Point"}
}