{
  "type": "Feature",
  "properties": {
    "iso:country":"BE",
    "sg:address":"Sint-pietersstraat 46",
    "sg:city":"Maasmechelen",
    "sg:classifiers":[
        {
            "category":"Cafe",
            "type":"Food & Drink"
        }
    ],
    "sg:phone":"+32 89 75 57 21",
    "sg:postcode":"3630",
    "sg:province":"Limburg",
    "sg:tags":[
        "caf\u00e9s"
    ],
    "wof:name":"Caf\u00c9 Lindehof",
    "wof:placetype":"venue"
},
  "geometry": {"coordinates":[5.7357897758,50.9916725159],"type":"Point"}
}