{
  "type": "Feature",
  "properties": {
    "iso:country":"BE",
    "sg:address":"Astridlaan 118",
    "sg:city":"Overpelt",
    "sg:classifiers":[
        {
            "category":"Personal",
            "subcategory":"Beauty Salon",
            "type":"Services"
        }
    ],
    "sg:phone":"+32 11 66 36 63",
    "sg:postcode":"3900",
    "sg:province":"Limburg",
    "sg:tags":[
        "de",
        "coiffure"
    ],
    "wof:name":"Vive Hairstyliste",
    "wof:placetype":"venue"
},
  "geometry": {"coordinates":[5.4027929306,51.2098731995],"type":"Point"}
}