{
  "type": "Feature",
  "properties": {
    "addr:full":"Rue De L\u00b4eglise 2 Merbes-le-ch\u00c2teau Hainaut 6567",
    "addr:housenumber":"2",
    "addr:postcode":"6567",
    "addr:street":"Rue De L\u00b4Eglise",
    "iso:country":"BE",
    "sg:address":"Rue De L\u00b4eglise 2",
    "sg:city":"Merbes-le-ch\u00c2teau",
    "sg:orig_category":"Epiceries",
    "sg:phone":"+32 71 55 41 35",
    "sg:postcode":"6567",
    "sg:province":"Hainaut",
    "wof:name":"La Superette",
    "wof:placetype":"venue"
},
  "geometry": {"coordinates":[4.164850235,50.3238945007],"type":"Point"}
}