{
  "type": "Feature",
  "properties": {
    "iso:country":"BE",
    "sg:address":"Gaverlanddam 5",
    "sg:city":"Beveren",
    "sg:orig_category":"Artiesten and kunstenaars Decoratieve kunst and kunstbenodigdheden",
    "sg:phone":"+32 3 775 77 96",
    "sg:postcode":"9120",
    "sg:province":"Oost-Vlaanderen",
    "wof:name":"Nestor De Clerck",
    "wof:placetype":"venue"
},
  "geometry": {"coordinates":[4.2639050484,51.2234382629],"type":"Point"}
}