{
  "type": "Feature",
  "properties": {
    "addr:full":"Rue C\u00e9sar Despretz 98 Lessines Hainaut 7860",
    "addr:housenumber":"98",
    "addr:postcode":"7860",
    "addr:street":"Rue Ce\u0301Sar Despretz;Hainaut",
    "iso:country":"BE",
    "sg:address":"Rue C\u00e9sar Despretz 98",
    "sg:city":"Lessines",
    "sg:classifiers":[
        {
            "category":"Insurance",
            "subcategory":"Insurance Agent",
            "type":"Services"
        }
    ],
    "sg:phone":"+32 68 33 59 15",
    "sg:postcode":"7860",
    "sg:province":"Hainaut",
    "sg:tags":[
        "broker"
    ],
    "wof:name":"Counasse F",
    "wof:placetype":"venue"
},
  "geometry": {"coordinates":[3.8286099434,50.7103500366],"type":"Point"}
}