{
  "type": "Feature",
  "properties": {
    "addr:full":"Haldertstraat 177 Tielt-winge (houwaart) Vlaams-Brabant 3390",
    "addr:housenumber":"177",
    "addr:postcode":"3390",
    "addr:street":"Haldertstraat",
    "iso:country":"BE",
    "sg:address":"Haldertstraat 177",
    "sg:city":"Tielt-winge (houwaart)",
    "sg:classifiers":[
        {
            "category":"Building & Trades",
            "subcategory":"Plumbing",
            "type":"Services"
        }
    ],
    "sg:phone":"+32 16 47 48 00",
    "sg:postcode":"3390",
    "sg:province":"Vlaams-Brabant",
    "sg:tags":[
        "pipe",
        "drain",
        "unblocking"
    ],
    "wof:name":"A.a. Bergen Kris",
    "wof:placetype":"venue"
},
  "geometry": {"coordinates":[4.8795781136,50.9437980652],"type":"Point"}
}