{
  "type": "Feature",
  "properties": {
    "addr:full":"Rue Des Preys 28 Charleroi Hainaut 6061",
    "addr:housenumber":"28",
    "addr:postcode":"6061",
    "addr:street":"Rue Des Preys;Hainaut",
    "iso:country":"BE",
    "sg:address":"Rue Des Preys 28",
    "sg:city":"Charleroi",
    "sg:orig_category":"Notaires",
    "sg:phone":"+32 71 32 09 94",
    "sg:postcode":"6061",
    "sg:province":"Hainaut",
    "wof:name":"Bernard Lemaigre",
    "wof:placetype":"venue"
},
  "geometry": {"coordinates":[4.4833669662,50.4002151489],"type":"Point"}
}