{
  "type": "Feature",
  "properties": {
    "addr:full":"Kuwaardestraat 12 Deinze Oost-Vlaanderen 9800",
    "addr:housenumber":"12",
    "addr:postcode":"9800",
    "addr:street":"Kuwaardestraat",
    "iso:country":"BE",
    "sg:address":"Kuwaardestraat 12",
    "sg:city":"Deinze",
    "sg:classifiers":[
        {
            "category":"Arena",
            "subcategory":"Sports Club",
            "type":"Entertainment"
        }
    ],
    "sg:phone":"+32 9 386 29 75",
    "sg:postcode":"9800",
    "sg:province":"Oost-Vlaanderen",
    "sg:tags":[
        "de"
    ],
    "wof:name":"Judoclub Kiawazu Deinze",
    "wof:placetype":"venue"
},
  "geometry": {"coordinates":[3.5251510143,50.9915657043],"type":"Point"}
}