{
  "type": "Feature",
  "properties": {
    "addr:full":"Sint-martensommegangstraat 4a Hamme (moerzeke) Oost-Vlaanderen 9220",
    "addr:housenumber":"4a",
    "addr:postcode":"9220",
    "addr:street":"Sint-Martensommegangstraat",
    "iso:country":"BE",
    "sg:address":"Sint-martensommegangstraat 4a",
    "sg:city":"Hamme (moerzeke)",
    "sg:classifiers":[
        {
            "category":"Shopping",
            "subcategory":"Bicycles & Sporting Goods",
            "type":"Retail Goods"
        }
    ],
    "sg:phone":"+32 52 47 70 70",
    "sg:postcode":"9220",
    "sg:province":"Oost-Vlaanderen",
    "sg:tags":[
        "-"
    ],
    "wof:name":"Vermachelen C",
    "wof:placetype":"venue"
},
  "geometry": {"coordinates":[4.1516418457,51.0697441101],"type":"Point"}
}