{
  "type": "Feature",
  "properties": {
    "iso:country":"BE",
    "sg:address":"Botermarkt 20",
    "sg:city":"Hasselt",
    "sg:orig_category":"V\u00eatements pour Hommes",
    "sg:phone":"+32 11 26 17 25",
    "sg:postcode":"3500",
    "sg:province":"Limburg",
    "wof:name":"Huis Oldriver",
    "wof:placetype":"venue"
},
  "geometry": {"coordinates":[5.338698864,50.9306488037],"type":"Point"}
}