{
  "type": "Feature",
  "properties": {
    "addr:full":"Zone Artisanale Arlon Luxembourg 6700",
    "addr:postcode":"6700",
    "addr:street":"Zone Artisanale",
    "iso:country":"BE",
    "sg:address":"Zone Artisanale",
    "sg:city":"Arlon",
    "sg:classifiers":[
        {
            "category":"Retail",
            "subcategory":"Auto Repair",
            "type":"Services"
        }
    ],
    "sg:phone":"+32 63 22 30 57",
    "sg:postcode":"6700",
    "sg:province":"Luxembourg",
    "sg:tags":[
        "garage",
        "mainten",
        "-",
        "truck"
    ],
    "wof:name":"Megabel Sprl-guissart J-l",
    "wof:placetype":"venue"
},
  "geometry": {"coordinates":[5.8126749992,49.6823234558],"type":"Point"}
}