{
  "type": "Feature",
  "properties": {
    "addr:full":"Rue Bruy\u00c8re Seutine 12 Frasnes-lez-anvaing Hainaut 7912",
    "addr:housenumber":"12",
    "addr:postcode":"7912",
    "addr:street":"Rue Bruye\u0300Re Seutine",
    "iso:country":"BE",
    "sg:address":"Rue Bruy\u00c8re Seutine 12",
    "sg:city":"Frasnes-lez-anvaing",
    "sg:classifiers":[
        {
            "category":"Insurance",
            "subcategory":"Life Insurance",
            "type":"Services"
        }
    ],
    "sg:phone":"+32 69 76 80 99",
    "sg:postcode":"7912",
    "sg:province":"Hainaut",
    "sg:tags":[
        "assurance"
    ],
    "wof:name":"Assurances Schaessens",
    "wof:placetype":"venue"
},
  "geometry": {"coordinates":[3.6190719604,50.7103004456],"type":"Point"}
}