{
  "type": "Feature",
  "properties": {
    "addr:full":"Testeltsesteenweg 63a Averbode Vlaams-Brabant 3271",
    "addr:housenumber":"63a",
    "addr:postcode":"3271",
    "addr:street":"Testeltsesteenweg",
    "iso:country":"BE",
    "sg:address":"Testeltsesteenweg 63a",
    "sg:city":"Averbode",
    "sg:orig_category":"Installation \u00e9lectrique r\u00e9sidentielle",
    "sg:phone":"+32 475 93 16 76",
    "sg:postcode":"3271",
    "sg:province":"Vlaams-Brabant",
    "wof:name":"Michel Ickx Algemene Elektriciteitswerken",
    "wof:placetype":"venue"
},
  "geometry": {"coordinates":[4.9712290764,51.0247688293],"type":"Point"}
}