{
  "type": "Feature",
  "properties": {
    "iso:country":"BE",
    "sg:address":"Rue De La Rivelaine 28/31",
    "sg:city":"Charleroi",
    "sg:orig_category":"Advocaten and juridische adviseurs",
    "sg:phone":"+32 71 32 71 36",
    "sg:postcode":"6061",
    "sg:province":"Hainaut",
    "wof:name":"Bernard Thomas",
    "wof:placetype":"venue"
},
  "geometry": {"coordinates":[4.4565382004,50.4055404663],"type":"Point"}
}