{
  "type": "Feature",
  "properties": {
    "addr:full":"Bichur\u00e9es 8 Flobecq Hainaut 7880",
    "addr:housenumber":"8",
    "addr:postcode":"7880",
    "addr:street":"Bichure\u0301Es;Hainaut",
    "iso:country":"BE",
    "sg:address":"Bichur\u00e9es 8",
    "sg:city":"Flobecq",
    "sg:classifiers":[
        {
            "category":"Professional",
            "subcategory":"Engineering",
            "type":"Services"
        }
    ],
    "sg:phone":"+32 68 44 85 03",
    "sg:postcode":"7880",
    "sg:province":"Hainaut",
    "sg:tags":[
        "technical",
        "industrial",
        "-",
        "subcontracting"
    ],
    "wof:name":"L.f. Packing",
    "wof:placetype":"venue"
},
  "geometry": {"coordinates":[3.7670009136,50.7352371216],"type":"Point"}
}