{
  "type": "Feature",
  "properties": {
    "addr:full":"Schotlandstraat 32 Sint-gillis/saint-gilles Bruxelles-Capitale 1060",
    "addr:housenumber":"32",
    "addr:postcode":"1060",
    "addr:street":"Schotlandstraat",
    "iso:country":"BE",
    "sg:address":"Schotlandstraat 32",
    "sg:city":"Sint-gillis/saint-gilles",
    "sg:classifiers":[
        {
            "category":"Restaurant",
            "type":"Food & Drink"
        }
    ],
    "sg:phone":"+32 2 538 14 68",
    "sg:postcode":"1060",
    "sg:province":"Bruxelles-Capitale",
    "wof:name":"Chumadia",
    "wof:placetype":"venue"
},
  "geometry": {"coordinates":[4.3524870872,50.8325271606],"type":"Point"}
}