{
  "type": "Feature",
  "properties": {
    "addr:full":"Avenue Buysdelle 30 Ukkel/uccle Bruxelles-Capitale 1180",
    "addr:housenumber":"30",
    "addr:postcode":"1180",
    "addr:street":"Avenue Buysdelle;/",
    "iso:country":"BE",
    "sg:address":"Avenue Buysdelle 30",
    "sg:city":"Ukkel/uccle",
    "sg:orig_category":"Editeurs de livres",
    "sg:phone":"+32 2 374 40 29",
    "sg:postcode":"1180",
    "sg:province":"Bruxelles-Capitale",
    "wof:name":"Gaillard Editie",
    "wof:placetype":"venue"
},
  "geometry": {"coordinates":[4.3514289856,50.7767066956],"type":"Point"}
}