{
  "type": "Feature",
  "properties": {
    "addr:full":"Rue Leman 2 Mons Hainaut 7012",
    "addr:housenumber":"2",
    "addr:postcode":"7012",
    "addr:street":"Rue Leman;Hainaut",
    "iso:country":"BE",
    "sg:address":"Rue Leman 2",
    "sg:city":"Mons",
    "sg:classifiers":[
        {
            "category":"Cafe",
            "type":"Food & Drink"
        }
    ],
    "sg:phone":"+32 65 82 23 07",
    "sg:postcode":"7012",
    "sg:province":"Hainaut",
    "sg:tags":[
        "caf\u00e9s"
    ],
    "wof:name":"Caf\u00c9 Le Coup De D\u00c9s",
    "wof:placetype":"venue"
},
  "geometry": {"coordinates":[3.8894600868,50.4481964111],"type":"Point"}
}