{
  "type": "Feature",
  "properties": {
    "addr:full":"Kortrijksestraat 16 Ardooie West-Vlaanderen 8850",
    "addr:housenumber":"16",
    "addr:postcode":"8850",
    "addr:street":"Kortrijksestraat",
    "iso:country":"BE",
    "sg:address":"Kortrijksestraat 16",
    "sg:city":"Ardooie",
    "sg:orig_category":"Plomberie, chauffage and installations sanitaires",
    "sg:phone":"+32 51 74 41 19",
    "sg:postcode":"8850",
    "sg:province":"West-Vlaanderen",
    "wof:name":"Noel Vinckier",
    "wof:placetype":"venue"
},
  "geometry": {"coordinates":[3.1979169846,50.9774208069],"type":"Point"}
}