{
  "type": "Feature",
  "properties": {
    "addr:full":"Thier Saive 49 Dalhem (warsage) Li\u00e8ge 4608",
    "addr:housenumber":"49",
    "addr:postcode":"4608",
    "addr:street":"Thier Saive",
    "iso:country":"BE",
    "sg:address":"Thier Saive 49",
    "sg:city":"Dalhem (warsage)",
    "sg:classifiers":[
        {
            "category":"Health Services",
            "subcategory":"Doctor",
            "type":"Services"
        }
    ],
    "sg:phone":"+32 4 376 64 38",
    "sg:postcode":"4608",
    "sg:province":"Li\u00e8ge",
    "sg:tags":[
        "medicinephysicians",
        "surgeon"
    ],
    "wof:name":"Dedee Michel",
    "wof:placetype":"venue"
},
  "geometry": {"coordinates":[5.7721071243,50.7387771606],"type":"Point"}
}