{
  "type": "Feature",
  "properties": {
    "addr:full":"Frans Raatstraat 52 Kalmthout Antwerpen 2920",
    "addr:housenumber":"52",
    "addr:postcode":"2920",
    "addr:street":"Frans Raatstraat",
    "iso:country":"BE",
    "sg:address":"Frans Raatstraat 52",
    "sg:city":"Kalmthout",
    "sg:orig_category":"Location de voitures",
    "sg:phone":"+32 3 666 49 04",
    "sg:postcode":"2920",
    "sg:province":"Antwerpen",
    "wof:name":"Van Hees",
    "wof:placetype":"venue"
},
  "geometry": {"coordinates":[4.4640011787,51.4002761841],"type":"Point"}
}