{
  "type": "Feature",
  "properties": {
    "iso:country":"BE",
    "sg:address":"Place Du Vieux March\u00c9 48",
    "sg:city":"Edingen/enghien",
    "sg:orig_category":"Entretien and r\u00e9parations de voitures",
    "sg:phone":"+32 2 395 59 21",
    "sg:postcode":"7850",
    "sg:province":"Hainaut",
    "wof:name":"Jacquy Weemol",
    "wof:placetype":"venue"
},
  "geometry": {"coordinates":[4.0443282127,50.6951599121],"type":"Point"}
}