{
  "type": "Feature",
  "properties": {
    "iso:country":"BE",
    "sg:address":"Koning Albertstraat 58",
    "sg:city":"Mechelen (walem)",
    "sg:classifiers":[
        {
            "category":"Professional",
            "subcategory":"Testing Lab",
            "type":"Services"
        }
    ],
    "sg:phone":"+32 15 20 56 22",
    "sg:postcode":"2800",
    "sg:province":"Antwerpen",
    "sg:tags":[
        "chemist"
    ],
    "wof:name":"Goyvaerts",
    "wof:placetype":"venue"
},
  "geometry": {"coordinates":[4.4823541641,51.0175552368],"type":"Point"}
}