{
  "type": "Feature",
  "properties": {
    "iso:country":"BE",
    "sg:address":"Dorpsstraat 59",
    "sg:city":"Stekene",
    "sg:orig_category":"Schoenen",
    "sg:phone":"+32 3 779 76 24",
    "sg:postcode":"9190",
    "sg:province":"Oost-Vlaanderen",
    "wof:name":"Shoe Center",
    "wof:placetype":"venue"
},
  "geometry": {"coordinates":[4.0394701958,51.204460144],"type":"Point"}
}