{
  "type": "Feature",
  "properties": {
    "addr:full":"Ieperweg 161 Roeselare West-Vlaanderen 8800",
    "addr:housenumber":"161",
    "addr:postcode":"8800",
    "iso:country":"BE",
    "sg:address":"Ieperweg 161",
    "sg:city":"Roeselare",
    "sg:orig_category":"Varkenskwekers",
    "sg:phone":"+32 51 24 41 50",
    "sg:postcode":"8800",
    "sg:province":"West-Vlaanderen",
    "wof:name":"Etienne Witdouck",
    "wof:placetype":"venue"
},
  "geometry": {"coordinates":[3.1165940762,50.9401054382],"type":"Point"}
}