{
  "type": "Feature",
  "properties": {
    "addr:full":"Rue De Hann\u00cache 27 Wasseiges Li\u00e8ge 4219",
    "addr:housenumber":"27",
    "addr:postcode":"4219",
    "addr:street":"Rue De Hanne\u0302Che",
    "iso:country":"BE",
    "sg:address":"Rue De Hann\u00cache 27",
    "sg:city":"Wasseiges",
    "sg:orig_category":"Cr\u00e9meries",
    "sg:phone":"+32 81 83 40 57",
    "sg:postcode":"4219",
    "sg:province":"Li\u00e8ge",
    "wof:name":"Freddy Bouvier",
    "wof:placetype":"venue"
},
  "geometry": {"coordinates":[5.0460619926,50.5915985107],"type":"Point"}
}