{
  "type": "Feature",
  "properties": {
    "addr:full":"August Van Landeghemstraat 63 Willebroek Antwerpen 2830",
    "addr:housenumber":"63",
    "addr:postcode":"2830",
    "addr:street":"August Van Landeghemstraat",
    "iso:country":"BE",
    "sg:address":"August Van Landeghemstraat 63",
    "sg:city":"Willebroek",
    "sg:classifiers":[
        {
            "category":"Health Services",
            "subcategory":"Doctor",
            "type":"Services"
        }
    ],
    "sg:phone":"+32 3 886 34 34",
    "sg:postcode":"2830",
    "sg:province":"Antwerpen",
    "sg:tags":[
        "medicinephysicians",
        "surgeon"
    ],
    "wof:name":"De Boeck M",
    "wof:placetype":"venue"
},
  "geometry": {"coordinates":[4.3611121178,51.0623817444],"type":"Point"}
}