{
  "type": "Feature",
  "properties": {
    "addr:full":"Dalenstraat 6 Herent Vlaams-Brabant 3020",
    "addr:housenumber":"6",
    "addr:postcode":"3020",
    "addr:street":"Dalenstraat",
    "iso:country":"BE",
    "sg:address":"Dalenstraat 6",
    "sg:city":"Herent",
    "sg:orig_category":"Artiesten and kunstenaars",
    "sg:phone":"+32 16 48 96 84",
    "sg:postcode":"3020",
    "sg:province":"Vlaams-Brabant",
    "wof:name":"Elsje Vos",
    "wof:placetype":"venue"
},
  "geometry": {"coordinates":[4.6749200821,50.9079055786],"type":"Point"}
}