{
  "type": "Feature",
  "properties": {
    "iso:country":"BE",
    "sg:address":"Rue De La Station 70",
    "sg:city":"Herve",
    "sg:orig_category":"Assurances. Bureaux de poste",
    "sg:phone":"+32 87 67 42 31",
    "sg:postcode":"4650",
    "sg:province":"Li\u00e8ge",
    "wof:name":"La Poste",
    "wof:placetype":"venue"
},
  "geometry": {"coordinates":[5.7917761803,50.6412620544],"type":"Point"}
}