{
  "type": "Feature",
  "properties": {
    "addr:full":"Schaapsveld 25 Puurs Antwerpen 2870",
    "addr:housenumber":"25",
    "addr:postcode":"2870",
    "addr:street":"Schaapsveld",
    "iso:country":"BE",
    "sg:address":"Schaapsveld 25",
    "sg:city":"Puurs",
    "sg:orig_category":"Elektrische installaties voor woningen",
    "sg:phone":"+32 3 889 63 07",
    "sg:postcode":"2870",
    "sg:province":"Antwerpen",
    "wof:name":"Marc Hellemans",
    "wof:placetype":"venue"
},
  "geometry": {"coordinates":[4.2822890282,51.0801124573],"type":"Point"}
}