{
  "type": "Feature",
  "properties": {
    "iso:country":"BE",
    "sg:address":"Place Du March\u00c9 13",
    "sg:city":"La Roche-en-ardenne (grand)",
    "sg:orig_category":"Cr\u00e9dits divers",
    "sg:postcode":"6980",
    "sg:province":"Luxembourg",
    "wof:name":"Bancontact-mister Cash",
    "wof:placetype":"venue"
},
  "geometry": {"coordinates":[5.5752801895,50.1816101074],"type":"Point"}
}