{
  "type": "Feature",
  "properties": {
    "addr:full":"Bo\u00eete Postale 78 Tournai Hainaut 7500",
    "addr:housenumber":"78",
    "addr:postcode":"7500",
    "iso:country":"BE",
    "sg:address":"Bo\u00eete Postale 78",
    "sg:city":"Tournai",
    "sg:classifiers":[
        {
            "category":"Shopping",
            "subcategory":"Books",
            "type":"Retail Goods"
        }
    ],
    "sg:phone":"+32 69 22 38 66",
    "sg:postcode":"7500",
    "sg:province":"Hainaut",
    "sg:tags":[
        "bookseller"
    ],
    "wof:name":"Presse-express",
    "wof:placetype":"venue"
},
  "geometry": {"coordinates":[3.3867199421,50.606098175],"type":"Point"}
}