{
  "type": "Feature",
  "properties": {
    "iso:country":"BE",
    "sg:address":"Kloosterstraat 22b26",
    "sg:city":"Lommel",
    "sg:orig_category":"Supermarkten Warenhuizen",
    "sg:phone":"+32 11 54 91 00",
    "sg:postcode":"3920",
    "sg:province":"Limburg",
    "wof:name":"Alma",
    "wof:placetype":"venue"
},
  "geometry": {"coordinates":[5.3142552376,51.2297363281],"type":"Point"}
}