{
  "type": "Feature",
  "properties": {
    "addr:full":"Buurtstraat 2c Maldegem Oost-Vlaanderen 9990",
    "addr:housenumber":"2c",
    "addr:postcode":"9990",
    "addr:street":"Buurtstraat",
    "iso:country":"BE",
    "sg:address":"Buurtstraat 2c",
    "sg:city":"Maldegem",
    "sg:orig_category":"Promoteurs immobiliers",
    "sg:phone":"+32 50 71 23 93",
    "sg:postcode":"9990",
    "sg:province":"Oost-Vlaanderen",
    "wof:name":"Mabo",
    "wof:placetype":"venue"
},
  "geometry": {"coordinates":[3.4463779926,51.2168922424],"type":"Point"}
}