{
  "type": "Feature",
  "properties": {
    "iso:country":"BE",
    "sg:address":"Verdaelstraat 49",
    "sg:city":"Geetbets",
    "sg:orig_category":"Artsen and specialisten",
    "sg:phone":"+32 11 58 29 47",
    "sg:postcode":"3450",
    "sg:province":"Vlaams-Brabant",
    "wof:name":"Emiel Roosemont",
    "wof:placetype":"venue"
},
  "geometry": {"coordinates":[5.1333990097,50.8740882874],"type":"Point"}
}