{
  "type": "Feature",
  "properties": {
    "addr:full":"Kerkhoflei 105 Zoersel Antwerpen 2980",
    "addr:housenumber":"105",
    "addr:postcode":"2980",
    "addr:street":"Kerkhoflei",
    "iso:country":"BE",
    "sg:address":"Kerkhoflei 105",
    "sg:city":"Zoersel",
    "sg:classifiers":[
        {
            "category":"Professional",
            "subcategory":"Computer Services",
            "type":"Services"
        }
    ],
    "sg:phone":"+32 3 385 84 99",
    "sg:postcode":"2980",
    "sg:province":"Antwerpen",
    "sg:tags":[
        "-",
        "processing",
        "data",
        "software"
    ],
    "wof:name":"Bops Bvba",
    "wof:placetype":"venue"
},
  "geometry": {"coordinates":[4.713435173,51.269985199],"type":"Point"}
}