{
  "type": "Feature",
  "properties": {
    "iso:country":"BE",
    "sg:address":"Chauss\u00c9e D'arlon 11",
    "sg:city":"Bastogne",
    "sg:orig_category":"Auto-\u00e9coles",
    "sg:phone":"+32 61 21 35 73",
    "sg:postcode":"6600",
    "sg:province":"Luxembourg",
    "wof:name":"Centre Ecolage Automobile",
    "wof:placetype":"venue"
},
  "geometry": {"coordinates":[5.7174968719,49.996925354],"type":"Point"}
}