{
  "type": "Feature",
  "properties": {
    "iso:country":"BE",
    "sg:address":"Burg Reuland",
    "sg:city":"Burg-reuland",
    "sg:classifiers":[
        {
            "category":"Shopping",
            "subcategory":"Books",
            "type":"Retail Goods"
        }
    ],
    "sg:phone":"+32 80 32 91 32",
    "sg:postcode":"4790",
    "sg:province":"Li\u00e8ge",
    "sg:tags":[
        "bookseller"
    ],
    "wof:name":"Schmitz-berens",
    "wof:placetype":"venue"
},
  "geometry": {"coordinates":[6.1315698624,50.1943702698],"type":"Point"}
}