{
  "type": "Feature",
  "properties": {
    "iso:country":"BE",
    "sg:address":"Herentalsesteenweg 19",
    "sg:city":"Kasterlee (lichtaart)",
    "sg:classifiers":[
        {
            "category":"Home & Garden",
            "subcategory":"Home Furnishings",
            "type":"Retail Goods"
        }
    ],
    "sg:phone":"+32 14 55 41 09",
    "sg:postcode":"2460",
    "sg:province":"Antwerpen",
    "sg:tags":[
        "-",
        "furniture"
    ],
    "wof:name":"Van Ballaer",
    "wof:placetype":"venue"
},
  "geometry": {"coordinates":[4.894589901,51.2070617676],"type":"Point"}
}