{
  "type": "Feature",
  "properties": {
    "iso:country":"BE",
    "sg:address":"Rue Albert Dupuis 81",
    "sg:city":"Verviers",
    "sg:orig_category":"Artsen and specialisten",
    "sg:phone":"+32 87 33 04 25",
    "sg:postcode":"4801",
    "sg:province":"Li\u00e8ge",
    "wof:name":"Edmond Delcourt",
    "wof:placetype":"venue"
},
  "geometry": {"coordinates":[5.8930549622,50.5922393799],"type":"Point"}
}