{
  "type": "Feature",
  "properties": {
    "addr:full":"Poel 29 Haaltert Oost-Vlaanderen 9450",
    "addr:housenumber":"29",
    "addr:postcode":"9450",
    "addr:street":"Poel",
    "iso:country":"BE",
    "sg:address":"Poel 29",
    "sg:city":"Haaltert",
    "sg:orig_category":"Pleisterwerk",
    "sg:phone":"+32 54 33 31 31",
    "sg:postcode":"9450",
    "sg:province":"Oost-Vlaanderen",
    "wof:name":"Meert Frederik",
    "wof:placetype":"venue"
},
  "geometry": {"coordinates":[4.0206799507,50.8702125549],"type":"Point"}
}