{
  "type": "Feature",
  "properties": {
    "addr:full":"Boulevard Ernest Solvay 529 Li\u00e8ge 1 Li\u00e8ge 4000",
    "addr:housenumber":"529;1",
    "addr:postcode":"4000",
    "addr:street":"Boulevard Ernest Solvay",
    "iso:country":"BE",
    "sg:address":"Boulevard Ernest Solvay 529",
    "sg:city":"Li\u00e8ge 1",
    "sg:classifiers":[
        {
            "category":"Health Services",
            "subcategory":"Health Practitioner",
            "type":"Services"
        }
    ],
    "sg:phone":"+32 4 227 62 94",
    "sg:postcode":"4000",
    "sg:province":"Li\u00e8ge",
    "sg:tags":[
        "physiotherapist"
    ],
    "wof:name":"Chevremont J",
    "wof:placetype":"venue"
},
  "geometry": {"coordinates":[5.5957679749,50.6616134644],"type":"Point"}
}