{
  "type": "Feature",
  "properties": {
    "iso:country":"BE",
    "sg:address":"Richard Vandeveldestraat 19",
    "sg:city":"Schaarbeek/schaerbeek",
    "sg:classifiers":[
        {
            "category":"Restaurant",
            "type":"Food & Drink"
        }
    ],
    "sg:phone":"+32 2 215 22 09",
    "sg:postcode":"1030",
    "sg:province":"Bruxelles-Capitale",
    "wof:name":"Snack-bar La Terrasse",
    "wof:placetype":"venue"
},
  "geometry": {"coordinates":[4.3882508278,50.8735198975],"type":"Point"}
}