{
  "type": "Feature",
  "properties": {
    "iso:country":"BE",
    "sg:address":"Rue Emile Marcq 12a",
    "sg:city":"Genappe (ways)",
    "sg:classifiers":[
        {
            "category":"Home & Garden",
            "subcategory":"Kitchen Supply",
            "type":"Retail Goods"
        }
    ],
    "sg:phone":"+32 67 79 14 21",
    "sg:postcode":"1474",
    "sg:province":"Brabant Wallon",
    "sg:tags":[
        "installation"
    ],
    "wof:name":"Portas-restorbois",
    "wof:placetype":"venue"
},
  "geometry": {"coordinates":[4.4630827904,50.6126594543],"type":"Point"}
}