{
  "type": "Feature",
  "properties": {
    "iso:country":"BE",
    "sg:address":"Stationslaan 21",
    "sg:city":"Steenokkerzeel",
    "sg:classifiers":[
        {
            "category":"Restaurant",
            "type":"Food & Drink"
        }
    ],
    "sg:phone":"+32 2 751 70 64",
    "sg:postcode":"1820",
    "sg:province":"Vlaams-Brabant",
    "wof:name":"Rembrandt",
    "wof:placetype":"venue"
},
  "geometry": {"coordinates":[4.4765400887,50.9111175537],"type":"Point"}
}