{
  "type": "Feature",
  "properties": {
    "iso:country":"BE",
    "sg:address":"Groot Hagelkruis 174",
    "sg:city":"Antwerpen",
    "sg:orig_category":"Sportclubs",
    "sg:phone":"+32 3 542 24 37",
    "sg:postcode":"2030",
    "sg:province":"Antwerpen",
    "wof:name":"Kon. Klopstokia Rhc",
    "wof:placetype":"venue"
},
  "geometry": {"coordinates":[4.4103250504,51.2743377686],"type":"Point"}
}