{
  "type": "Feature",
  "properties": {
    "addr:full":"Lagesteenweg 73 Grimbergen Vlaams-Brabant 1850",
    "addr:housenumber":"73",
    "addr:postcode":"1850",
    "addr:street":"Lagesteenweg",
    "iso:country":"BE",
    "sg:address":"Lagesteenweg 73",
    "sg:city":"Grimbergen",
    "sg:classifiers":[
        {
            "category":"Food & Beverages",
            "subcategory":"Liquor & Beverages",
            "type":"Retail Goods"
        }
    ],
    "sg:phone":"+32 2 478 51 64",
    "sg:postcode":"1850",
    "sg:province":"Vlaams-Brabant",
    "sg:tags":[
        "-",
        "spirit",
        "wine"
    ],
    "wof:name":"Concept Vins",
    "wof:placetype":"venue"
},
  "geometry": {"coordinates":[4.3667597771,50.9326705933],"type":"Point"}
}