{
  "type": "Feature",
  "properties": {
    "addr:full":"Rue De Meaurain 37 Honnelles Hainaut 7387",
    "addr:housenumber":"37",
    "addr:postcode":"7387",
    "addr:street":"Rue De Meaurain;Hainaut",
    "iso:country":"BE",
    "sg:address":"Rue De Meaurain 37",
    "sg:city":"Honnelles",
    "sg:orig_category":"Landbouwmachines Gh",
    "sg:phone":"+32 65 75 93 66",
    "sg:postcode":"7387",
    "sg:province":"Hainaut",
    "wof:name":"Ets. Reignier",
    "wof:placetype":"venue"
},
  "geometry": {"coordinates":[3.7161719799,50.3318710327],"type":"Point"}
}