{
  "type": "Feature",
  "properties": {
    "addr:full":"J. Kennedyln Gent Oost-Vlaanderen 9042",
    "addr:postcode":"9042",
    "addr:street":"Oost-Vlaanderen",
    "iso:country":"BE",
    "sg:address":"J. Kennedyln",
    "sg:city":"Gent",
    "sg:orig_category":"Stortklaar beton Fab",
    "sg:phone":"+32 9 342 35 35",
    "sg:postcode":"9042",
    "sg:province":"Oost-Vlaanderen",
    "wof:name":"C.c.b",
    "wof:placetype":"venue"
},
  "geometry": {"coordinates":[3.7816700935,51.1223831177],"type":"Point"}
}