{
  "type": "Feature",
  "properties": {
    "addr:full":"Rue Egide Van Ophem 110 Bruxelles (uccle) Bruxelles-Capitale 1180",
    "addr:housenumber":"110",
    "addr:postcode":"1180",
    "addr:street":"Rue Egide Van Ophem",
    "iso:country":"BE",
    "sg:address":"Rue Egide Van Ophem 110",
    "sg:city":"Bruxelles (uccle)",
    "sg:classifiers":[
        {
            "category":"Manufacturing",
            "subcategory":"Chemicals & Compounds",
            "type":"Manufacturing & Wholesale Goods"
        }
    ],
    "sg:phone":"+32 2 370 48 11",
    "sg:postcode":"1180",
    "sg:province":"Bruxelles-Capitale",
    "sg:tags":[
        "pharmaceutical",
        "product"
    ],
    "wof:name":"Biothera/astrazeneca",
    "wof:placetype":"venue"
},
  "geometry": {"coordinates":[4.3284077644,50.7937278748],"type":"Point"}
}