{
  "type": "Feature",
  "properties": {
    "addr:full":"Putsesteenweg 123 Kalmthout Antwerpen 2920",
    "addr:housenumber":"123",
    "addr:postcode":"2920",
    "addr:street":"Putsesteenweg",
    "iso:country":"BE",
    "sg:address":"Putsesteenweg 123",
    "sg:city":"Kalmthout",
    "sg:classifiers":[
        {
            "category":"Cafe",
            "type":"Food & Drink"
        }
    ],
    "sg:phone":"+32 3 666 48 36",
    "sg:postcode":"2920",
    "sg:province":"Antwerpen",
    "sg:tags":[
        "snack-bars"
    ],
    "wof:name":"Passe-vite",
    "wof:placetype":"venue"
},
  "geometry": {"coordinates":[4.4502339363,51.3795166016],"type":"Point"}
}