{
  "type": "Feature",
  "properties": {
    "iso:country":"BE",
    "sg:address":"Rue Jean-bosly 16",
    "sg:city":"Li\u00e8ge 1 (wandre)",
    "sg:classifiers":[
        {
            "category":"Health Services",
            "subcategory":"Doctor",
            "type":"Services"
        }
    ],
    "sg:phone":"+32 4 370 27 27",
    "sg:postcode":"4020",
    "sg:province":"Li\u00e8ge",
    "sg:tags":[
        "medicinephysicians",
        "surgeon"
    ],
    "wof:name":"Kluser Ch",
    "wof:placetype":"venue"
},
  "geometry": {"coordinates":[5.6669340134,50.6650466919],"type":"Point"}
}