{
  "type": "Feature",
  "properties": {
    "iso:country":"BE",
    "sg:address":"Avenue Du Parc 32b",
    "sg:city":"Herve",
    "sg:orig_category":"Onderdelen and accessoires voor auto's",
    "sg:phone":"+32 87 35 22 55",
    "sg:postcode":"4650",
    "sg:province":"Li\u00e8ge",
    "wof:name":"Full Tires",
    "wof:placetype":"venue"
},
  "geometry": {"coordinates":[5.8391771317,50.6252250671],"type":"Point"}
}