{
  "type": "Feature",
  "properties": {
    "iso:country":"BE",
    "sg:address":"Westernieuwweg 33",
    "sg:city":"Jabbeke (varsenare)",
    "sg:classifiers":[
        {
            "category":"Professional",
            "subcategory":"Art Services",
            "type":"Services"
        }
    ],
    "sg:phone":"+32 50 38 15 26",
    "sg:postcode":"8490",
    "sg:province":"West-Vlaanderen",
    "sg:tags":[
        "graphic",
        "designer"
    ],
    "wof:name":"Van Couillie M",
    "wof:placetype":"venue"
},
  "geometry": {"coordinates":[3.1375689507,51.1920204163],"type":"Point"}
}