{
  "type": "Feature",
  "properties": {
    "addr:full":"Rue Arthur Roelandt 25 Moeskroen/mouscron Hainaut 7711",
    "addr:housenumber":"25",
    "addr:postcode":"7711",
    "addr:street":"Rue Arthur Roelandt",
    "iso:country":"BE",
    "sg:address":"Rue Arthur Roelandt 25",
    "sg:city":"Moeskroen/mouscron",
    "sg:orig_category":"Banques and organismes de cr\u00e9dit",
    "sg:phone":"+32 56 48 94 69",
    "sg:postcode":"7711",
    "sg:province":"Hainaut",
    "wof:name":"Kbc",
    "wof:placetype":"venue"
},
  "geometry": {"coordinates":[3.3035559654,50.7274971008],"type":"Point"}
}