{
  "type": "Feature",
  "properties": {
    "addr:full":"Visitatiestraat 84 Gent Oost-Vlaanderen 9040",
    "addr:housenumber":"84",
    "addr:postcode":"9040",
    "addr:street":"Visitatiestraat;Oost-Vlaanderen",
    "iso:country":"BE",
    "sg:address":"Visitatiestraat 84",
    "sg:city":"Gent",
    "sg:orig_category":"Elektrische installaties voor woningen Huishoudapparaten, televisies and radio's",
    "sg:phone":"+32 9 251 16 90",
    "sg:postcode":"9040",
    "sg:province":"Oost-Vlaanderen",
    "wof:name":"Urkens",
    "wof:placetype":"venue"
},
  "geometry": {"coordinates":[3.748871088,51.0657501221],"type":"Point"}
}