{
  "type": "Feature",
  "properties": {
    "addr:full":"Koning Albertlaan 123 Lanaken Limburg 3620",
    "addr:housenumber":"123",
    "addr:postcode":"3620",
    "addr:street":"Koning Albertlaan",
    "iso:country":"BE",
    "sg:address":"Koning Albertlaan 123",
    "sg:city":"Lanaken",
    "sg:classifiers":[
        {
            "category":"Health Services",
            "subcategory":"Dentist",
            "type":"Services"
        }
    ],
    "sg:phone":"+32 89 71 44 26",
    "sg:postcode":"3620",
    "sg:province":"Limburg",
    "wof:name":"Colson L",
    "wof:placetype":"venue"
},
  "geometry": {"coordinates":[5.6591749191,50.8928337097],"type":"Point"}
}