{
  "type": "Feature",
  "properties": {
    "addr:full":"Capellestraat 79 Komen-waasten/comines-warneton Hainaut 7780",
    "addr:housenumber":"79;7780",
    "addr:street":"Capellestraat",
    "iso:country":"BE",
    "sg:address":"Capellestraat 79",
    "sg:city":"Komen-waasten/comines-warneton",
    "sg:orig_category":"Rundveehouders Varkenskwekers",
    "sg:phone":"+32 56 55 55 92",
    "sg:postcode":"7780",
    "sg:province":"Hainaut",
    "wof:name":"Bernard Deprez",
    "wof:placetype":"venue"
},
  "geometry": {"coordinates":[2.9984300137,50.7863311768],"type":"Point"}
}