{
  "type": "Feature",
  "properties": {
    "addr:full":"Rue Des Cortils 9 Orp-jauche Brabant Wallon 1350",
    "addr:housenumber":"9",
    "addr:postcode":"1350",
    "addr:street":"Rue Des Cortils",
    "iso:country":"BE",
    "sg:address":"Rue Des Cortils 9",
    "sg:city":"Orp-jauche",
    "sg:orig_category":"Sportclubs Sportterreinen and installaties behalve sportcentra",
    "sg:phone":"+32 81 87 80 11",
    "sg:postcode":"1350",
    "sg:province":"Brabant Wallon",
    "wof:name":"Football Leopold Club",
    "wof:placetype":"venue"
},
  "geometry": {"coordinates":[4.97920084,50.6738891602],"type":"Point"}
}