{
  "type": "Feature",
  "properties": {
    "addr:full":"Antoin Van Cailliestraat 13 Middelkerke West-Vlaanderen 8430",
    "addr:housenumber":"13",
    "addr:postcode":"8430",
    "addr:street":"Antoin;Cailliestraat",
    "iso:country":"BE",
    "sg:address":"Antoin Van Cailliestraat 13",
    "sg:city":"Middelkerke",
    "sg:classifiers":[
        {
            "category":"Insurance",
            "subcategory":"Insurance Agent",
            "type":"Services"
        }
    ],
    "sg:phone":"+32 59 30 03 71",
    "sg:postcode":"8430",
    "sg:province":"West-Vlaanderen",
    "sg:tags":[
        "broker"
    ],
    "wof:name":"Van De Casteele Gcv Cv",
    "wof:placetype":"venue"
},
  "geometry": {"coordinates":[2.8138899803,51.1864814758],"type":"Point"}
}