{
  "type": "Feature",
  "properties": {
    "addr:full":"Rijselsteenweg 326 Moeskroen/mouscron Hainaut 7700",
    "addr:housenumber":"326",
    "addr:postcode":"7700",
    "addr:street":"Rijselsteenweg",
    "iso:country":"BE",
    "sg:address":"Rijselsteenweg 326",
    "sg:city":"Moeskroen/mouscron",
    "sg:classifiers":[
        {
            "category":"Food & Beverages",
            "subcategory":"Fruits & Vegetables",
            "type":"Retail Goods"
        }
    ],
    "sg:phone":"+32 56 34 29 40",
    "sg:postcode":"7700",
    "sg:province":"Hainaut",
    "sg:tags":[
        "groenten"
    ],
    "wof:name":"Emmanuel Callens",
    "wof:placetype":"venue"
},
  "geometry": {"coordinates":[3.2323200703,50.7400932312],"type":"Point"}
}