{
  "type": "Feature",
  "properties": {
    "addr:full":"Hoogstraat 67 Deerlijk West-Vlaanderen 8540",
    "addr:housenumber":"67",
    "addr:postcode":"8540",
    "addr:street":"Hoogstraat",
    "iso:country":"BE",
    "sg:address":"Hoogstraat 67",
    "sg:city":"Deerlijk",
    "sg:classifiers":[
        {
            "category":"Personal",
            "subcategory":"Beauty Salon",
            "type":"Services"
        }
    ],
    "sg:phone":"+32 56 70 44 63",
    "sg:postcode":"8540",
    "sg:province":"West-Vlaanderen",
    "wof:name":"Blush",
    "wof:placetype":"venue"
},
  "geometry": {"coordinates":[3.3557949066,50.8540153503],"type":"Point"}
}