{
  "type": "Feature",
  "properties": {
    "iso:country":"BE",
    "sg:address":"Grote Nieuwedijkstraat 98",
    "sg:city":"Mechelen",
    "sg:classifiers":[
        {
            "category":"Health Services",
            "subcategory":"Dentist",
            "type":"Services"
        }
    ],
    "sg:phone":"+32 15 55 50 10",
    "sg:postcode":"2800",
    "sg:province":"Antwerpen",
    "wof:name":"Magriet Beata",
    "wof:placetype":"venue"
},
  "geometry": {"coordinates":[4.4945502281,51.0337982178],"type":"Point"}
}