{
  "type": "Feature",
  "properties": {
    "addr:full":"Beverlodorp 16 Beringen Limburg 3581",
    "addr:housenumber":"16",
    "addr:postcode":"3581",
    "addr:street":"Beverlodorp",
    "iso:country":"BE",
    "sg:address":"Beverlodorp 16",
    "sg:city":"Beringen",
    "sg:orig_category":"Postkantoren Verzekeringsmakelaars and experts",
    "sg:phone":"+32 11 34 17 62",
    "sg:postcode":"3581",
    "sg:province":"Limburg",
    "wof:name":"De Post",
    "wof:placetype":"venue"
},
  "geometry": {"coordinates":[5.221683979,51.0878677368],"type":"Point"}
}