{
  "type": "Feature",
  "properties": {
    "addr:full":"Peperstraat 24 Zwalm Oost-Vlaanderen 9636",
    "addr:housenumber":"24",
    "addr:postcode":"9636",
    "addr:street":"Peperstraat;Oost-Vlaanderen",
    "iso:country":"BE",
    "sg:address":"Peperstraat 24",
    "sg:city":"Zwalm",
    "sg:orig_category":"Sportclubs",
    "sg:phone":"+32 55 49 97 96",
    "sg:postcode":"9636",
    "sg:province":"Oost-Vlaanderen",
    "wof:name":"Stripem Cycling Team",
    "wof:placetype":"venue"
},
  "geometry": {"coordinates":[3.6812839508,50.8938102722],"type":"Point"}
}