{
  "type": "Feature",
  "properties": {
    "addr:full":"Sint-janstraat 25 Langemark-poelkapelle West-Vlaanderen 8920",
    "addr:housenumber":"25",
    "addr:postcode":"8920",
    "addr:street":"Sint-Janstraat",
    "iso:country":"BE",
    "sg:address":"Sint-janstraat 25",
    "sg:city":"Langemark-poelkapelle",
    "sg:orig_category":"Eleveurs and marchands de porcs",
    "sg:phone":"+32 51 54 46 49",
    "sg:postcode":"8920",
    "sg:province":"West-Vlaanderen",
    "wof:name":"Chris Geldof",
    "wof:placetype":"venue"
},
  "geometry": {"coordinates":[2.919770956,50.9132423401],"type":"Point"}
}