{
  "type": "Feature",
  "properties": {
    "addr:full":"Stationsplein 11 Box 1 Lokeren Oost-Vlaanderen 9160",
    "addr:housenumber":"11;1",
    "addr:postcode":"9160",
    "addr:street":"Stationsplein;Box",
    "iso:country":"BE",
    "sg:address":"Stationsplein 11 Box 1",
    "sg:city":"Lokeren",
    "sg:classifiers":[
        {
            "category":"Professional",
            "subcategory":"Lawyer & Legal Services",
            "type":"Services"
        }
    ],
    "sg:phone":"+32 9 348 11 81",
    "sg:postcode":"9160",
    "sg:province":"Oost-Vlaanderen",
    "sg:tags":[
        "notary"
    ],
    "wof:name":"Van Der Cruysse F",
    "wof:placetype":"venue"
},
  "geometry": {"coordinates":[3.9881470203,51.1061172485],"type":"Point"}
}