{
  "type": "Feature",
  "properties": {
    "addr:full":"Brugmannlaan 267 Ukkel/uccle Bruxelles-Capitale 1180",
    "addr:housenumber":"267",
    "addr:postcode":"1180",
    "addr:street":"Brugmannlaan;/",
    "iso:country":"BE",
    "sg:address":"Brugmannlaan 267",
    "sg:city":"Ukkel/uccle",
    "sg:orig_category":"Banken and kredietinstellingen",
    "sg:phone":"+32 2 340 61 30",
    "sg:postcode":"1180",
    "sg:province":"Bruxelles-Capitale",
    "wof:name":"Cr\u00c9dit G\u00c9n\u00c9ral De Banque",
    "wof:placetype":"venue"
},
  "geometry": {"coordinates":[4.3471999168,50.8128242493],"type":"Point"}
}