{
  "type": "Feature",
  "properties": {
    "addr:full":"Rue Du 1er D\u00c9cembre 79 Ch\u00c2telet Hainaut 6200",
    "addr:housenumber":"79",
    "addr:postcode":"6200",
    "addr:street":"Rue Du 1Er De\u0301Cembre",
    "iso:country":"BE",
    "sg:address":"Rue Du 1er D\u00c9cembre 79",
    "sg:city":"Ch\u00c2telet",
    "sg:orig_category":"V\u00e9hicules automobiles",
    "sg:phone":"+32 71 40 51 80",
    "sg:postcode":"6200",
    "sg:province":"Hainaut",
    "wof:name":"Occasions Michel",
    "wof:placetype":"venue"
},
  "geometry": {"coordinates":[4.5218482018,50.4381484985],"type":"Point"}
}