{
  "type": "Feature",
  "properties": {
    "iso:country":"BE",
    "sg:address":"Brugstraat 116a",
    "sg:city":"Brecht",
    "sg:orig_category":"Beautyfarms, relaxatie and lichamelijk welzijn Schoonheidssalons",
    "sg:phone":"+32 3 636 20 19",
    "sg:postcode":"2960",
    "sg:province":"Antwerpen",
    "wof:name":"Instituut Afrodite",
    "wof:placetype":"venue"
},
  "geometry": {"coordinates":[4.5737299919,51.297706604],"type":"Point"}
}