{
  "type": "Feature",
  "properties": {
    "iso:country":"BE",
    "sg:address":"R Albert 1er 342",
    "sg:city":"Erquelinnes",
    "sg:classifiers":[
        {
            "category":"Shopping",
            "subcategory":"Clothing, Apparel, & Fashions",
            "type":"Retail Goods"
        }
    ],
    "sg:phone":"+32 71 55 51 63",
    "sg:postcode":"6560",
    "sg:province":"Hainaut",
    "sg:tags":[
        "textile",
        "clothing",
        "clothes"
    ],
    "wof:name":"Justeprix Sa",
    "wof:placetype":"venue"
},
  "geometry": {"coordinates":[4.1240048409,50.3106956482],"type":"Point"}
}