{
  "type": "Feature",
  "properties": {
    "iso:country":"BE",
    "sg:address":"Rue Joseph Lef\u00c8bvre 23",
    "sg:city":"Fleurus",
    "sg:orig_category":"Paramedische behandelingen",
    "sg:phone":"+32 71 81 96 66",
    "sg:postcode":"6220",
    "sg:province":"Hainaut",
    "wof:name":"M. Denis",
    "wof:placetype":"venue"
},
  "geometry": {"coordinates":[4.5531821251,50.4826698303],"type":"Point"}
}