{
  "type": "Feature",
  "properties": {
    "addr:full":"Rue Andr\u00c9 Renard 2ba Andenne Namur 5300",
    "addr:housenumber":"2ba",
    "addr:postcode":"5300",
    "addr:street":"Rue Andre\u0301 Renard",
    "iso:country":"BE",
    "sg:address":"Rue Andr\u00c9 Renard 2ba",
    "sg:city":"Andenne",
    "sg:orig_category":"Travail and traitement du bois. Mat\u00e9riaux de construction Gr",
    "sg:phone":"+32 85 82 65 51",
    "sg:postcode":"5300",
    "sg:province":"Namur",
    "wof:name":"Fe. Bodet",
    "wof:placetype":"venue"
},
  "geometry": {"coordinates":[5.0982642174,50.4863739014],"type":"Point"}
}