{
  "type": "Feature",
  "properties": {
    "iso:country":"BE",
    "sg:address":"Chauss\u00e9e De Verviers 148",
    "sg:city":"Verviers (polleur)",
    "sg:orig_category":"Autombile concessionaires",
    "sg:phone":"+32 87 54 15 46",
    "sg:postcode":"4910",
    "sg:province":"Li\u00e8ge",
    "wof:name":"Gar Goblet F",
    "wof:placetype":"venue"
},
  "geometry": {"coordinates":[5.8130488396,50.5356216431],"type":"Point"}
}