{
  "type": "Feature",
  "properties": {
    "addr:full":"Rieu Baron 48 La Louvi\u00e8re (houdeng-goegnies) Hainaut 7110",
    "addr:housenumber":"48",
    "addr:postcode":"7110",
    "addr:street":"Baron",
    "iso:country":"BE",
    "sg:address":"Rieu Baron 48",
    "sg:city":"La Louvi\u00e8re (houdeng-goegnies)",
    "sg:classifiers":[
        {
            "category":"Real Estate",
            "subcategory":"Architect",
            "type":"Services"
        }
    ],
    "sg:phone":"+32 64 84 97 41",
    "sg:postcode":"7110",
    "sg:province":"Hainaut",
    "wof:name":"Chatzistiliadis D",
    "wof:placetype":"venue"
},
  "geometry": {"coordinates":[4.1595678329,50.4883422852],"type":"Point"}
}