{
  "type": "Feature",
  "properties": {
    "iso:country":"BE",
    "sg:address":"Miskruisstraat 33",
    "sg:city":"Tielt-winge",
    "sg:orig_category":"Sportclubs",
    "sg:phone":"+32 16 50 19 56",
    "sg:postcode":"3390",
    "sg:province":"Vlaams-Brabant",
    "wof:name":"Schoonderbuukse Trappers",
    "wof:placetype":"venue"
},
  "geometry": {"coordinates":[4.9340791702,50.9594268799],"type":"Point"}
}