{
  "type": "Feature",
  "properties": {
    "addr:full":"Vital Decosterstraat 46 Box 6 Leuven Vlaams-Brabant 3000",
    "addr:housenumber":"46;6",
    "addr:postcode":"3000",
    "addr:street":"Vital Decosterstraat;Box",
    "iso:country":"BE",
    "sg:address":"Vital Decosterstraat 46 Box 6",
    "sg:city":"Leuven",
    "sg:classifiers":[
        {
            "category":"Professional",
            "subcategory":"Lawyer & Legal Services",
            "type":"Services"
        }
    ],
    "sg:phone":"+32 16 50 14 90",
    "sg:postcode":"3000",
    "sg:province":"Vlaams-Brabant",
    "wof:name":"De Schryver Andreas",
    "wof:placetype":"venue"
},
  "geometry": {"coordinates":[4.7043910027,50.8815841675],"type":"Point"}
}