{
  "type": "Feature",
  "properties": {
    "iso:country":"BE",
    "sg:address":"Avenue Ferdinand Nicolay 4",
    "sg:city":"Stavelot",
    "sg:orig_category":"Openbare veiligheid",
    "sg:phone":"+32 80 86 21 25",
    "sg:postcode":"4970",
    "sg:province":"Li\u00e8ge",
    "wof:name":"Police F\u00c9d\u00c9rale",
    "wof:placetype":"venue"
},
  "geometry": {"coordinates":[5.9305911064,50.394329071],"type":"Point"}
}