{
  "type": "Feature",
  "properties": {
    "addr:full":"Onderstraat 21 Bus 7 Hoeselt Limburg 3730",
    "addr:housenumber":"21 bus 7",
    "addr:postcode":"3730",
    "addr:street":"Onderstraat",
    "iso:country":"BE",
    "sg:address":"Onderstraat 21 Bus 7",
    "sg:city":"Hoeselt",
    "sg:orig_category":"Elektrische installaties voor woningen",
    "sg:phone":"+32 475 30 77 27",
    "sg:postcode":"3730",
    "sg:province":"Limburg",
    "wof:name":"Gijsen Algemene Electriciteitswerken",
    "wof:placetype":"venue"
},
  "geometry": {"coordinates":[5.4773731232,50.8340377808],"type":"Point"}
}