{
  "type": "Feature",
  "properties": {
    "addr:full":"Oude Leestsebaan 56 Mechelen Antwerpen 2800",
    "addr:housenumber":"56",
    "addr:postcode":"2800",
    "addr:street":"Oude Leestsebaan",
    "iso:country":"BE",
    "sg:address":"Oude Leestsebaan 56",
    "sg:city":"Mechelen",
    "sg:orig_category":"Kapsalons",
    "sg:phone":"+32 15 27 17 98",
    "sg:postcode":"2800",
    "sg:province":"Antwerpen",
    "wof:name":"Ivan De Wit",
    "wof:placetype":"venue"
},
  "geometry": {"coordinates":[4.4423890114,51.036857605],"type":"Point"}
}