{
  "type": "Feature",
  "properties": {
    "addr:full":"Schooldreef 19 Oostkamp West-Vlaanderen 8020",
    "addr:housenumber":"19",
    "addr:postcode":"8020",
    "addr:street":"Schooldreef",
    "iso:country":"BE",
    "sg:address":"Schooldreef 19",
    "sg:city":"Oostkamp",
    "sg:orig_category":"Banques and organismes de cr\u00e9dit",
    "sg:phone":"+32 50 84 10 90",
    "sg:postcode":"8020",
    "sg:province":"West-Vlaanderen",
    "wof:name":"Groep Argenta",
    "wof:placetype":"venue"
},
  "geometry": {"coordinates":[3.2371339798,51.1534042358],"type":"Point"}
}