{
  "type": "Feature",
  "properties": {
    "addr:full":"Rue G\u00e9n\u00e9ral Leman 110 Bruxelles (etterbeek) Bruxelles-Capitale 1040",
    "addr:housenumber":"110",
    "addr:postcode":"1040",
    "addr:street":"Rue Ge\u0301Ne\u0301Ral Leman",
    "iso:country":"BE",
    "sg:address":"Rue G\u00e9n\u00e9ral Leman 110",
    "sg:city":"Bruxelles (etterbeek)",
    "sg:classifiers":[
        {
            "category":"Social Services",
            "type":"Services"
        }
    ],
    "sg:phone":"+32 2 230 10 30",
    "sg:postcode":"1040",
    "sg:province":"Bruxelles-Capitale",
    "wof:name":"Centres De Planning Familial",
    "wof:placetype":"venue"
},
  "geometry": {"coordinates":[4.3862051964,50.8368873596],"type":"Point"}
}