{
  "type": "Feature",
  "properties": {
    "addr:full":"Wittestraat 79 Antwerpen Antwerpen 2020",
    "addr:housenumber":"79",
    "addr:postcode":"2020",
    "addr:street":"Wittestraat",
    "iso:country":"BE",
    "sg:address":"Wittestraat 79",
    "sg:city":"Antwerpen",
    "sg:classifiers":[
        {
            "category":"Health Services",
            "subcategory":"Health Practitioner",
            "type":"Services"
        }
    ],
    "sg:phone":"+32 3 238 29 95",
    "sg:postcode":"2020",
    "sg:province":"Antwerpen",
    "sg:tags":[
        "osteopath"
    ],
    "wof:name":"Beyens P (do)",
    "wof:placetype":"venue"
},
  "geometry": {"coordinates":[4.3851428032,51.1882514954],"type":"Point"}
}