{
  "type": "Feature",
  "properties": {
    "addr:full":"Rue Saint-hilaire 1 Malmedy (beverc\u00e9) Li\u00e8ge 4960",
    "addr:housenumber":"1",
    "addr:postcode":"4960",
    "addr:street":"Rue Saint-Hilaire",
    "iso:country":"BE",
    "sg:address":"Rue Saint-hilaire 1",
    "sg:city":"Malmedy (beverc\u00e9)",
    "sg:classifiers":[
        {
            "category":"Sports & Exercise",
            "subcategory":"Swimming Pool",
            "type":"Entertainment"
        }
    ],
    "sg:phone":"+32 80 33 06 03",
    "sg:postcode":"4960",
    "sg:province":"Li\u00e8ge",
    "sg:tags":[
        "cover",
        "-"
    ],
    "wof:name":"Ondine (piscines) Sa",
    "wof:placetype":"venue"
},
  "geometry": {"coordinates":[6.0005731583,50.4250717163],"type":"Point"}
}