{
  "type": "Feature",
  "properties": {
    "iso:country":"BE",
    "sg:address":"Kerkstraat 15ba",
    "sg:city":"Arendonk",
    "sg:orig_category":"Boissons",
    "sg:phone":"+32 14 67 74 19",
    "sg:postcode":"2370",
    "sg:province":"Antwerpen",
    "wof:name":"Kempendrinks",
    "wof:placetype":"venue"
},
  "geometry": {"coordinates":[5.0843458176,51.3164176941],"type":"Point"}
}