{
  "type": "Feature",
  "properties": {
    "addr:full":"Rue Africaine 16 Bruxelles (saint-gilles) Bruxelles-Capitale 1060",
    "addr:housenumber":"16",
    "addr:postcode":"1060",
    "addr:street":"Rue Africaine",
    "iso:country":"BE",
    "sg:address":"Rue Africaine 16",
    "sg:city":"Bruxelles (saint-gilles)",
    "sg:classifiers":[
        {
            "category":"Real Estate",
            "subcategory":"Architect",
            "type":"Services"
        }
    ],
    "sg:phone":"+32 2 537 52 54",
    "sg:postcode":"1060",
    "sg:province":"Bruxelles-Capitale",
    "wof:name":"Houde J",
    "wof:placetype":"venue"
},
  "geometry": {"coordinates":[4.3544611931,50.8230133057],"type":"Point"}
}