{
  "type": "Feature",
  "properties": {
    "addr:full":"Schranshoeveweg 12ba Ranst Antwerpen 2520",
    "addr:housenumber":"12ba",
    "addr:postcode":"2520",
    "addr:street":"Schranshoeveweg",
    "iso:country":"BE",
    "sg:address":"Schranshoeveweg 12ba",
    "sg:city":"Ranst",
    "sg:orig_category":"Elektrische installaties voor woningen",
    "sg:phone":"+32 3 480 34 36",
    "sg:postcode":"2520",
    "sg:province":"Antwerpen",
    "wof:name":"Beirinckx",
    "wof:placetype":"venue"
},
  "geometry": {"coordinates":[4.5751209259,51.1550216675],"type":"Point"}
}