{
  "type": "Feature",
  "properties": {
    "addr:full":"Stationsplein 7 Herentals Antwerpen 2200",
    "addr:housenumber":"7",
    "addr:postcode":"2200",
    "addr:street":"Stationsplein",
    "iso:country":"BE",
    "sg:address":"Stationsplein 7",
    "sg:city":"Herentals",
    "sg:classifiers":[
        {
            "category":"Building & Trades",
            "subcategory":"Construction",
            "type":"Services"
        }
    ],
    "sg:phone":"+32 14 21 11 60",
    "sg:postcode":"2200",
    "sg:province":"Antwerpen",
    "sg:tags":[
        "carpenter"
    ],
    "wof:name":"Van Gelder Bvba",
    "wof:placetype":"venue"
},
  "geometry": {"coordinates":[4.8281641006,51.1804008484],"type":"Point"}
}