{
  "type": "Feature",
  "properties": {
    "addr:full":"Westmoere 35 Jabbeke West-Vlaanderen 8490",
    "addr:housenumber":"35",
    "addr:postcode":"8490",
    "addr:street":"Westmoere",
    "iso:country":"BE",
    "sg:address":"Westmoere 35",
    "sg:city":"Jabbeke",
    "sg:orig_category":"Drukkerijen and copyshops",
    "sg:phone":"+32 50 81 31 91",
    "sg:postcode":"8490",
    "sg:province":"West-Vlaanderen",
    "wof:name":"Ansa Print",
    "wof:placetype":"venue"
},
  "geometry": {"coordinates":[3.1206541061,51.1661186218],"type":"Point"}
}