{
  "type": "Feature",
  "properties": {
    "addr:full":"Dambruggestraat 223 Antwerpen Antwerpen 2060",
    "addr:housenumber":"223",
    "addr:postcode":"2060",
    "addr:street":"Dambruggestraat",
    "iso:country":"BE",
    "sg:address":"Dambruggestraat 223",
    "sg:city":"Antwerpen",
    "sg:orig_category":"Erotische Etablissementen",
    "sg:phone":"+32 3 233 02 52",
    "sg:postcode":"2060",
    "sg:province":"Antwerpen",
    "wof:name":"Vrede Sint-amands",
    "wof:placetype":"venue"
},
  "geometry": {"coordinates":[4.4217810631,51.2258415222],"type":"Point"}
}