{
  "type": "Feature",
  "properties": {
    "iso:country":"BE",
    "sg:address":"Olmsebaan 26",
    "sg:city":"Meerhout",
    "sg:orig_category":"Services pour animaux domestiques",
    "sg:phone":"+32 14 30 15 30",
    "sg:postcode":"2450",
    "sg:province":"Antwerpen",
    "wof:name":"Willy Keersmaekers",
    "wof:placetype":"venue"
},
  "geometry": {"coordinates":[5.0905160904,51.1291809082],"type":"Point"}
}