{
  "type": "Feature",
  "properties": {
    "addr:full":"Avenue De Castillion 71 Chastre Brabant Wallon 1450",
    "addr:housenumber":"71",
    "addr:postcode":"1450",
    "addr:street":"Avenue De Castillion",
    "iso:country":"BE",
    "sg:address":"Avenue De Castillion 71",
    "sg:city":"Chastre",
    "sg:orig_category":"Maatschappelijke dienstverlening",
    "sg:phone":"+32 10 65 75 01",
    "sg:postcode":"1450",
    "sg:province":"Brabant Wallon",
    "wof:name":"Infor Jeunes",
    "wof:placetype":"venue"
},
  "geometry": {"coordinates":[4.644382,50.6103401184],"type":"Point"}
}