{
  "type": "Feature",
  "properties": {
    "iso:country":"BE",
    "sg:address":"Hoevensebaan 179",
    "sg:city":"Kapellen",
    "sg:classifiers":[
        {
            "category":"Banks & Credit Unions",
            "subcategory":"Investment Brokerage",
            "type":"Services"
        }
    ],
    "sg:phone":"+32 3 665 26 48",
    "sg:postcode":"2950",
    "sg:province":"Antwerpen",
    "sg:tags":[
        "printing",
        "-"
    ],
    "wof:name":"Wivipro",
    "wof:placetype":"venue"
},
  "geometry": {"coordinates":[4.4217920303,51.3118629456],"type":"Point"}
}