{
  "type": "Feature",
  "properties": {
    "addr:full":"Legrellestraat 104 Berlaar Antwerpen 2590",
    "addr:housenumber":"104",
    "addr:postcode":"2590",
    "addr:street":"Legrellestraat",
    "iso:country":"BE",
    "sg:address":"Legrellestraat 104",
    "sg:city":"Berlaar",
    "sg:classifiers":[
        {
            "category":"Shopping",
            "subcategory":"Florist",
            "type":"Retail Goods"
        }
    ],
    "sg:phone":"+32 3 482 14 04",
    "sg:postcode":"2590",
    "sg:province":"Antwerpen",
    "wof:name":"Mari\u00cbn (bloemen)",
    "wof:placetype":"venue"
},
  "geometry": {"coordinates":[4.6574501991,51.1232032776],"type":"Point"}
}