{
  "type": "Feature",
  "properties": {
    "iso:country":"BE",
    "sg:address":"Diestsebaan 136",
    "sg:city":"Diest",
    "sg:orig_category":"V\u00e9hicules automobiles",
    "sg:phone":"+32 13 31 18 60",
    "sg:postcode":"3290",
    "sg:province":"Vlaams-Brabant",
    "wof:name":"Garage Van Den Broeck",
    "wof:placetype":"venue"
},
  "geometry": {"coordinates":[5.0739378929,50.9965553284],"type":"Point"}
}