{
  "type": "Feature",
  "properties": {
    "addr:full":"Avenue De Batta 8b Huy Li\u00e8ge 4500",
    "addr:housenumber":"8b",
    "addr:postcode":"4500",
    "addr:street":"Avenue De Batta",
    "iso:country":"BE",
    "sg:address":"Avenue De Batta 8b",
    "sg:city":"Huy",
    "sg:classifiers":[
        {
            "category":"Wholesale",
            "subcategory":"Plants",
            "type":"Manufacturing & Wholesale Goods"
        }
    ],
    "sg:phone":"+32 85 71 13 31",
    "sg:postcode":"4500",
    "sg:province":"Li\u00e8ge",
    "sg:tags":[
        "decoration",
        "flower",
        "-"
    ],
    "wof:name":"Coloris-fleurs",
    "wof:placetype":"venue"
},
  "geometry": {"coordinates":[5.2359280586,50.5201911926],"type":"Point"}
}