{
  "type": "Feature",
  "properties": {
    "addr:full":"Hubert Fr\u00c8re-orbanlaan 93 Gent Oost-Vlaanderen 9000",
    "addr:housenumber":"93",
    "addr:postcode":"9000",
    "addr:street":"Hubert Fre\u0300Re-Orbanlaan;Oost-Vlaanderen",
    "iso:country":"BE",
    "sg:address":"Hubert Fr\u00c8re-orbanlaan 93",
    "sg:city":"Gent",
    "sg:orig_category":"Activit\u00e9s d\u00b4action sociale sans h\u00e9bergement",
    "sg:phone":"+32 9 233 91 42",
    "sg:postcode":"9000",
    "sg:province":"Oost-Vlaanderen",
    "wof:name":"Guidance Centrum",
    "wof:placetype":"venue"
},
  "geometry": {"coordinates":[3.7336299419,51.0452079773],"type":"Point"}
}