{
  "type": "Feature",
  "properties": {
    "addr:full":"Polderstraat 19 Westerlo Antwerpen 2260",
    "addr:housenumber":"19",
    "addr:postcode":"2260",
    "addr:street":"Polderstraat",
    "iso:country":"BE",
    "sg:address":"Polderstraat 19",
    "sg:city":"Westerlo",
    "sg:orig_category":"Dameskledingzaken Herenkledingzaken",
    "sg:phone":"+32 14 54 40 85",
    "sg:postcode":"2260",
    "sg:province":"Antwerpen",
    "wof:name":"De Lange",
    "wof:placetype":"venue"
},
  "geometry": {"coordinates":[4.9146142006,51.0838279724],"type":"Point"}
}