{
  "type": "Feature",
  "properties": {
    "iso:country":"BE",
    "sg:address":"Rue De La Montagne 63",
    "sg:city":"Montigny-le-tilleul",
    "sg:classifiers":[
        {
            "category":"Professional",
            "subcategory":"Accounting & Tax Preparation",
            "type":"Services"
        }
    ],
    "sg:phone":"+32 71 51 16 24",
    "sg:postcode":"6110",
    "sg:province":"Hainaut",
    "sg:tags":[
        "accountant"
    ],
    "wof:name":"Bosquet C",
    "wof:placetype":"venue"
},
  "geometry": {"coordinates":[4.3838200569,50.3730888367],"type":"Point"}
}