{
  "type": "Feature",
  "properties": {
    "iso:country":"BE",
    "sg:address":"Diksmuidseweg 117",
    "sg:city":"Ieper",
    "sg:classifiers":[
        {
            "category":"Communications",
            "subcategory":"Television Station",
            "type":"Services"
        }
    ],
    "sg:phone":"+32 57 20 34 19",
    "sg:postcode":"8900",
    "sg:province":"West-Vlaanderen",
    "sg:tags":[
        "report",
        "video"
    ],
    "wof:name":"Image",
    "wof:placetype":"venue"
},
  "geometry": {"coordinates":[2.8763010502,50.8644981384],"type":"Point"}
}