{
  "type": "Feature",
  "properties": {
    "addr:full":"Rue Des Claviats 4 Dinant Namur 5504",
    "addr:housenumber":"4",
    "addr:postcode":"5504",
    "addr:street":"Rue Des Claviats",
    "iso:country":"BE",
    "sg:address":"Rue Des Claviats 4",
    "sg:city":"Dinant",
    "sg:orig_category":"Musea and historische gebouwen",
    "sg:phone":"+32 82 22 23 35",
    "sg:postcode":"5504",
    "sg:province":"Namur",
    "wof:name":"Foy Notre Dame",
    "wof:placetype":"venue"
},
  "geometry": {"coordinates":[4.9890499115,50.2480125427],"type":"Point"}
}