{
  "type": "Feature",
  "properties": {
    "iso:country":"BE",
    "sg:address":"Neromstraat 81",
    "sg:city":"Meise (wolvertem)",
    "sg:classifiers":[
        {
            "category":"Wholesale",
            "subcategory":"Fruits & Vegetables",
            "type":"Manufacturing & Wholesale Goods"
        }
    ],
    "sg:phone":"+32 2 269 25 74",
    "sg:postcode":"1861",
    "sg:province":"Vlaams-Brabant",
    "sg:tags":[
        "whol",
        "-"
    ],
    "wof:name":"Goossens Bvba",
    "wof:placetype":"venue"
},
  "geometry": {"coordinates":[4.3283400536,50.9709815979],"type":"Point"}
}