{
  "type": "Feature",
  "properties": {
    "iso:country":"BE",
    "sg:address":"Chemin De Mont Saint-jean 140",
    "sg:city":"Braine L'alleud (braine-l'alleud)",
    "sg:classifiers":[
        {
            "category":"Personal",
            "subcategory":"Sauna",
            "type":"Services"
        }
    ],
    "sg:phone":"+32 2 387 38 10",
    "sg:postcode":"1420",
    "sg:province":"Brabant Wallon",
    "wof:name":"Shavasana",
    "wof:placetype":"venue"
},
  "geometry": {"coordinates":[-0.2026470006,48.1579208374],"type":"Point"}
}