{
  "type": "Feature",
  "properties": {
    "iso:country":"BE",
    "sg:address":"Acacialaan 20",
    "sg:city":"Gistel",
    "sg:orig_category":"V\u00e9t\u00e9rinaires",
    "sg:phone":"+32 59 27 41 82",
    "sg:postcode":"8470",
    "sg:province":"West-Vlaanderen",
    "wof:name":"Hugo Gelders",
    "wof:placetype":"venue"
},
  "geometry": {"coordinates":[2.964370966,51.159198761],"type":"Point"}
}