{
  "type": "Feature",
  "properties": {
    "iso:country":"BE",
    "sg:address":"Steenberg 118",
    "sg:city":"Bekkevoort",
    "sg:classifiers":[
        {
            "category":"Farming",
            "subcategory":"Livestock Farm",
            "type":"Manufacturing & Wholesale Goods"
        }
    ],
    "sg:phone":"+32 13 77 27 86",
    "sg:postcode":"3460",
    "sg:province":"Vlaams-Brabant",
    "sg:tags":[
        "breeding"
    ],
    "wof:name":"Lemmens M",
    "wof:placetype":"venue"
},
  "geometry": {"coordinates":[4.9729537964,50.9594535828],"type":"Point"}
}