{
  "type": "Feature",
  "properties": {
    "iso:country":"BE",
    "sg:address":"Molenkouterslag 19",
    "sg:city":"Nevele (merendree)",
    "sg:classifiers":[
        {
            "category":"Professional",
            "subcategory":"Management & Consulting",
            "type":"Services"
        }
    ],
    "sg:phone":"+32 9 371 97 95",
    "sg:postcode":"9850",
    "sg:province":"Oost-Vlaanderen",
    "sg:tags":[
        "consultant"
    ],
    "wof:name":"Ansema Bvba",
    "wof:placetype":"venue"
},
  "geometry": {"coordinates":[3.5701019764,51.0793190002],"type":"Point"}
}