{
  "type": "Feature",
  "properties": {
    "iso:country":"BE",
    "sg:address":"Jan Van Rijswijcklaan 230",
    "sg:city":"Antwerpen",
    "sg:classifiers":[
        {
            "category":"Health Services",
            "subcategory":"Hospital",
            "type":"Services"
        }
    ],
    "sg:phone":"+32 3 226 40 00",
    "sg:postcode":"2020",
    "sg:province":"Antwerpen",
    "wof:name":"Vlaamse Liga Tegen Kanker",
    "wof:placetype":"venue"
},
  "geometry": {"coordinates":[4.3930301666,51.1874885559],"type":"Point"}
}