{
  "type": "Feature",
  "properties": {
    "iso:country":"BE",
    "sg:address":"Rue Du Joncquoy 36",
    "sg:city":"Peruwelz",
    "sg:orig_category":"Enseignement maternel and primaire",
    "sg:phone":"+32 69 77 62 70",
    "sg:postcode":"7602",
    "sg:province":"Hainaut",
    "wof:name":"Ecole Prim. Communale",
    "wof:placetype":"venue"
},
  "geometry": {"coordinates":[3.5913720131,50.5427932739],"type":"Point"}
}