{
  "type": "Feature",
  "properties": {
    "iso:country":"BE",
    "sg:address":"Leopold Vanderkelenstraat 28",
    "sg:city":"Leuven",
    "sg:classifiers":[
        {
            "category":"Education",
            "subcategory":"Library",
            "type":"Public Place"
        }
    ],
    "sg:phone":"+32 16 22 65 22",
    "sg:postcode":"3000",
    "sg:province":"Vlaams-Brabant",
    "wof:name":"Centrale Openbare Bibliotheek En Discotheek",
    "wof:placetype":"venue"
},
  "geometry": {"coordinates":[4.7048640251,50.8787193298],"type":"Point"}
}