{
  "type": "Feature",
  "properties": {
    "addr:full":"Stelen 34 Geel Antwerpen 2440",
    "addr:housenumber":"34",
    "addr:postcode":"2440",
    "addr:street":"Stelen",
    "iso:country":"BE",
    "sg:address":"Stelen 34",
    "sg:city":"Geel",
    "sg:classifiers":[
        {
            "category":"Wholesale",
            "subcategory":"Beer",
            "type":"Manufacturing & Wholesale Goods"
        }
    ],
    "sg:phone":"+32 14 86 78 55",
    "sg:postcode":"2440",
    "sg:province":"Antwerpen",
    "sg:tags":[
        "ale",
        "-"
    ],
    "wof:name":"Luyten",
    "wof:placetype":"venue"
},
  "geometry": {"coordinates":[4.9864931107,51.1560745239],"type":"Point"}
}