{
  "type": "Feature",
  "properties": {
    "addr:full":"Brouwerijstraat 45 Waregem West-Vlaanderen 8790",
    "addr:housenumber":"45",
    "addr:postcode":"8790",
    "addr:street":"Brouwerijstraat",
    "iso:country":"BE",
    "sg:address":"Brouwerijstraat 45",
    "sg:city":"Waregem",
    "sg:classifiers":[
        {
            "category":"Retail",
            "subcategory":"Repair Shop",
            "type":"Services"
        }
    ],
    "sg:phone":"+32 56 61 23 78",
    "sg:postcode":"8790",
    "sg:province":"West-Vlaanderen",
    "sg:tags":[
        "-",
        "clothing",
        "alteration"
    ],
    "wof:name":"Moerman T",
    "wof:placetype":"venue"
},
  "geometry": {"coordinates":[3.4458470345,50.8802185059],"type":"Point"}
}