{
  "type": "Feature",
  "properties": {
    "iso:country":"BE",
    "sg:address":"Blockxstraat 7",
    "sg:city":"Antwerpen",
    "sg:orig_category":"Krantenuitgeverijen Tijdschriftenuitgeverijen",
    "sg:phone":"+32 3 247 45 11",
    "sg:postcode":"2018",
    "sg:province":"Antwerpen",
    "wof:name":"Story",
    "wof:placetype":"venue"
},
  "geometry": {"coordinates":[4.4069809914,51.2048530579],"type":"Point"}
}