{
  "type": "Feature",
  "properties": {
    "addr:full":"Vieux-chemin-de-jupille 116 Beyne-heusay Li\u00e8ge 4610",
    "addr:housenumber":"116",
    "addr:postcode":"4610",
    "addr:street":"Beyne-Heusay Lie\u0300Ge",
    "iso:country":"BE",
    "sg:address":"Vieux-chemin-de-jupille 116",
    "sg:city":"Beyne-heusay",
    "sg:orig_category":"Agences immobili\u00e8res. Assurances",
    "sg:phone":"+32 4 362 94 55",
    "sg:postcode":"4610",
    "sg:province":"Li\u00e8ge",
    "wof:name":"Jacques Pierre Bertrand",
    "wof:placetype":"venue"
},
  "geometry": {"coordinates":[5.6527581215,50.6269721985],"type":"Point"}
}