{
  "type": "Feature",
  "properties": {
    "iso:country":"BE",
    "sg:address":"Chauss\u00c9e De Ramioul 1",
    "sg:city":"Fl\u00c9malle",
    "sg:orig_category":"Huisvuilophaling and -verwerking",
    "sg:phone":"+32 4 275 68 54",
    "sg:postcode":"4400",
    "sg:province":"Li\u00e8ge",
    "wof:name":"Fe. Intradel",
    "wof:placetype":"venue"
},
  "geometry": {"coordinates":[5.4576430321,50.5693130493],"type":"Point"}
}