{
  "type": "Feature",
  "properties": {
    "addr:full":"Strooistraat 34 Meise Vlaams-Brabant 1860",
    "addr:housenumber":"34",
    "addr:postcode":"1860",
    "addr:street":"Strooistraat",
    "iso:country":"BE",
    "sg:address":"Strooistraat 34",
    "sg:city":"Meise",
    "sg:classifiers":[
        {
            "category":"Professional",
            "subcategory":"Engineering",
            "type":"Services"
        }
    ],
    "sg:phone":"+32 475 32 37 26",
    "sg:postcode":"1860",
    "sg:province":"Vlaams-Brabant",
    "sg:tags":[
        "civil",
        "offices-"
    ],
    "wof:name":"Potoms G",
    "wof:placetype":"venue"
},
  "geometry": {"coordinates":[4.3054389954,50.9353752136],"type":"Point"}
}