{
  "type": "Feature",
  "properties": {
    "iso:country":"BE",
    "sg:address":"Mechelsesteenweg 26",
    "sg:city":"Dendermonde",
    "sg:orig_category":"V\u00eatements pour Dames. V\u00eatements pour Hommes. V\u00eatements pour b\u00e9b\u00e9s and enfants",
    "sg:phone":"+32 52 20 16 09",
    "sg:postcode":"9200",
    "sg:province":"Oost-Vlaanderen",
    "wof:name":"Superconfex",
    "wof:placetype":"venue"
},
  "geometry": {"coordinates":[4.1102819443,51.0332183838],"type":"Point"}
}