{
  "type": "Feature",
  "properties": {
    "addr:full":"Weg Naar As 165 Genk Limburg 3600",
    "addr:housenumber":"165",
    "addr:postcode":"3600",
    "addr:street":"Weg Naar As",
    "iso:country":"BE",
    "sg:address":"Weg Naar As 165",
    "sg:city":"Genk",
    "sg:orig_category":"Apotheken",
    "sg:phone":"+32 89 35 26 25",
    "sg:postcode":"3600",
    "sg:province":"Limburg",
    "wof:name":"Apotheek Theunissen M.",
    "wof:placetype":"venue"
},
  "geometry": {"coordinates":[5.5160660744,50.9725456238],"type":"Point"}
}