{
  "type": "Feature",
  "properties": {
    "addr:full":"Fazantendreef 9 Balen Antwerpen 2490",
    "addr:housenumber":"9",
    "addr:postcode":"2490",
    "addr:street":"Fazantendreef",
    "iso:country":"BE",
    "sg:address":"Fazantendreef 9",
    "sg:city":"Balen",
    "sg:classifiers":[
        {
            "category":"Professional",
            "subcategory":"Management & Consulting",
            "type":"Services"
        }
    ],
    "sg:phone":"+32 14 81 79 56",
    "sg:postcode":"2490",
    "sg:province":"Antwerpen",
    "sg:tags":[
        "tax-consultants"
    ],
    "wof:name":"Bosmans D",
    "wof:placetype":"venue"
},
  "geometry": {"coordinates":[5.1873002052,51.1958808899],"type":"Point"}
}