{
  "type": "Feature",
  "properties": {
    "iso:country":"BE",
    "sg:address":"Acacialaan 79",
    "sg:city":"Lochristi",
    "sg:classifiers":[
        {
            "category":"Shopping",
            "subcategory":"Crafts & Fabrics",
            "type":"Retail Goods"
        }
    ],
    "sg:phone":"+32 9 356 90 57",
    "sg:postcode":"9080",
    "sg:province":"Oost-Vlaanderen",
    "sg:tags":[
        "silk",
        "-"
    ],
    "wof:name":"Geerardijn",
    "wof:placetype":"venue"
},
  "geometry": {"coordinates":[3.8224411011,51.0859565735],"type":"Point"}
}