{
  "type": "Feature",
  "properties": {
    "addr:full":"Chauss\u00e9e De Neerstalle 440a Bruxelles (uccle) Bruxelles-Capitale 1180",
    "addr:housenumber":"440a",
    "addr:postcode":"1180",
    "addr:street":"Chausse\u0301E De Neerstalle",
    "iso:country":"BE",
    "sg:address":"Chauss\u00e9e De Neerstalle 440a",
    "sg:city":"Bruxelles (uccle)",
    "sg:classifiers":[
        {
            "category":"Shopping",
            "subcategory":"Books",
            "type":"Retail Goods"
        }
    ],
    "sg:phone":"+32 2 376 56 08",
    "sg:postcode":"1180",
    "sg:province":"Bruxelles-Capitale",
    "sg:tags":[
        "bookseller"
    ],
    "wof:name":"Geeraerts B",
    "wof:placetype":"venue"
},
  "geometry": {"coordinates":[4.3207321167,50.7973861694],"type":"Point"}
}