{
  "type": "Feature",
  "properties": {
    "iso:country":"BE",
    "sg:address":"Rooigemlaan 274",
    "sg:city":"Gent",
    "sg:classifiers":[
        {
            "category":"Real Estate",
            "subcategory":"Real Estate Services",
            "type":"Services"
        }
    ],
    "sg:phone":"+32 9 236 21 41",
    "sg:postcode":"9000",
    "sg:province":"Oost-Vlaanderen",
    "wof:name":"Belima Bvba",
    "wof:placetype":"venue"
},
  "geometry": {"coordinates":[3.6931970119,51.0587310791],"type":"Point"}
}