{
  "type": "Feature",
  "properties": {
    "iso:country":"BE",
    "sg:address":"Wondelgemstraat 157",
    "sg:city":"Gent",
    "sg:classifiers":[
        {
            "category":"Shopping",
            "subcategory":"Clothing, Apparel, & Fashions",
            "type":"Retail Goods"
        }
    ],
    "sg:phone":"+32 9 223 84 94",
    "sg:postcode":"9000",
    "sg:province":"Oost-Vlaanderen",
    "sg:tags":[
        "boutique"
    ],
    "wof:name":"Gilan",
    "wof:placetype":"venue"
},
  "geometry": {"coordinates":[3.7095370293,51.0639533997],"type":"Point"}
}