{
  "type": "Feature",
  "properties": {
    "iso:country":"BE",
    "sg:address":"Zandputlaan 64",
    "sg:city":"Mol",
    "sg:orig_category":"Epiceries",
    "sg:phone":"+32 14 31 01 78",
    "sg:postcode":"2400",
    "sg:province":"Antwerpen",
    "wof:name":"Spar",
    "wof:placetype":"venue"
},
  "geometry": {"coordinates":[5.1135249138,51.215511322],"type":"Point"}
}