{
  "type": "Feature",
  "properties": {
    "addr:full":"Avenue Winston Churchill 165bd Ukkel/uccle Bruxelles-Capitale 1180",
    "addr:postcode":"1180",
    "addr:street":"Avenue Winston Churchill 165Bd",
    "iso:country":"BE",
    "sg:address":"Avenue Winston Churchill 165bd",
    "sg:city":"Ukkel/uccle",
    "sg:orig_category":"Administration d'immeubles",
    "sg:phone":"+32 2 344 21 92",
    "sg:postcode":"1180",
    "sg:province":"Bruxelles-Capitale",
    "wof:name":"Marie Pinson Chenot",
    "wof:placetype":"venue"
},
  "geometry": {"coordinates":[4.360874176,50.811214447],"type":"Point"}
}