{
  "type": "Feature",
  "properties": {
    "iso:country":"BE",
    "sg:address":"Bosdreef 15",
    "sg:city":"Houthulst",
    "sg:orig_category":"Installation \u00e9lectrique r\u00e9sidentielle",
    "sg:phone":"+32 51 54 52 86",
    "sg:postcode":"8650",
    "sg:province":"West-Vlaanderen",
    "wof:name":"Bjorn Van Gelder",
    "wof:placetype":"venue"
},
  "geometry": {"coordinates":[2.9158389568,50.9663352966],"type":"Point"}
}