{
  "type": "Feature",
  "properties": {
    "iso:country":"BE",
    "sg:address":"Kte Rijakkerstraat 5",
    "sg:city":"Gent",
    "sg:orig_category":"Diverse bedrijfsbeheeradviesbureaus",
    "sg:phone":"+32 9 226 01 50",
    "sg:postcode":"9030",
    "sg:province":"Oost-Vlaanderen",
    "wof:name":"Belgian Senior Consultants",
    "wof:placetype":"venue"
},
  "geometry": {"coordinates":[3.670773983,51.0723266602],"type":"Point"}
}