{
  "type": "Feature",
  "properties": {
    "addr:full":"Maria Doolaeghestraat 4 Diksmuide West-Vlaanderen 8600",
    "addr:housenumber":"4",
    "addr:postcode":"8600",
    "addr:street":"Doolaeghestraat",
    "iso:country":"BE",
    "sg:address":"Maria Doolaeghestraat 4",
    "sg:city":"Diksmuide",
    "sg:orig_category":"Royal Canin Tuinbenodigdheden",
    "sg:phone":"+32 51 50 12 24",
    "sg:postcode":"8600",
    "sg:province":"West-Vlaanderen",
    "wof:name":"Dedeurwaerder Guido",
    "wof:placetype":"venue"
},
  "geometry": {"coordinates":[2.8655378819,51.0317306519],"type":"Point"}
}