{
  "type": "Feature",
  "properties": {
    "addr:full":"Vijverstraat 26a Huldenberg (sint-agatha-rode) Vlaams-Brabant 3040",
    "addr:housenumber":"26a",
    "addr:postcode":"3040",
    "addr:street":"Vijverstraat",
    "iso:country":"BE",
    "sg:address":"Vijverstraat 26a",
    "sg:city":"Huldenberg (sint-agatha-rode)",
    "sg:classifiers":[
        {
            "category":"Professional",
            "subcategory":"Employment Agencies",
            "type":"Services"
        }
    ],
    "sg:phone":"+32 16 20 04 38",
    "sg:postcode":"3040",
    "sg:province":"Vlaams-Brabant",
    "sg:tags":[
        "market",
        "research"
    ],
    "wof:name":"Homo Sapiens Sapiens",
    "wof:placetype":"venue"
},
  "geometry": {"coordinates":[4.6344919205,50.7761535645],"type":"Point"}
}