{
  "type": "Feature",
  "properties": {
    "iso:country":"BE",
    "sg:address":"Rue Fernand Neuray 8",
    "sg:city":"Sint-pieters-woluwe/woluwe-sai",
    "sg:orig_category":"Production and \u00e9mission de programmes de t\u00e9l\u00e9vision",
    "sg:phone":"+32 2 340 79 60",
    "sg:postcode":"1050",
    "sg:province":"Bruxelles-Capitale",
    "wof:name":"Lta-le Tel\u00c9-achat",
    "wof:placetype":"venue"
},
  "geometry": {"coordinates":[-0.0125010004,48.7456130981],"type":"Point"}
}