{
  "type": "Feature",
  "properties": {
    "addr:full":"Avenue Am\u00c9lie 9ba Rixensart Brabant Wallon 1330",
    "addr:housenumber":"9ba",
    "addr:postcode":"1330",
    "addr:street":"Avenue Ame\u0301Lie;Wallon",
    "iso:country":"BE",
    "sg:address":"Avenue Am\u00c9lie 9ba",
    "sg:city":"Rixensart",
    "sg:orig_category":"Editeurs de livres",
    "sg:phone":"+32 2 653 14 07",
    "sg:postcode":"1330",
    "sg:province":"Brabant Wallon",
    "wof:name":"Amelie Melo",
    "wof:placetype":"venue"
},
  "geometry": {"coordinates":[4.5245041847,50.7064361572],"type":"Point"}
}