{
  "type": "Feature",
  "properties": {
    "addr:full":"Heirbaan 94 Dendermonde (sint-gillis-bij-dendermonde) Oost-Vlaanderen 9200",
    "addr:housenumber":"94",
    "addr:postcode":"9200",
    "addr:street":"Heirbaan",
    "iso:country":"BE",
    "sg:address":"Heirbaan 94",
    "sg:city":"Dendermonde (sint-gillis-bij-dendermonde)",
    "sg:classifiers":[
        {
            "category":"Bars & Pubs",
            "type":"Food & Drink"
        }
    ],
    "sg:phone":"+32 475 28 17 28",
    "sg:postcode":"9200",
    "sg:province":"Oost-Vlaanderen",
    "sg:tags":[
        "tavern"
    ],
    "wof:name":"Atrium",
    "wof:placetype":"venue"
},
  "geometry": {"coordinates":[4.1134800911,51.0159339905],"type":"Point"}
}