{
  "type": "Feature",
  "properties": {
    "addr:full":"Rue De La Station 70 Awans Li\u00e8ge 4340",
    "addr:housenumber":"70",
    "addr:postcode":"4340",
    "addr:street":"Rue De La Station",
    "iso:country":"BE",
    "sg:address":"Rue De La Station 70",
    "sg:city":"Awans",
    "sg:classifiers":[
        {
            "category":"Manufacturing",
            "subcategory":"Tools & Machinery",
            "type":"Manufacturing & Wholesale Goods"
        }
    ],
    "sg:phone":"+32 4 246 54 76",
    "sg:postcode":"4340",
    "sg:province":"Li\u00e8ge",
    "sg:tags":[
        "cnc",
        "grinding",
        "circular"
    ],
    "wof:name":"Technoval S.a.",
    "wof:placetype":"venue"
},
  "geometry": {"coordinates":[5.4594449997,50.6605911255],"type":"Point"}
}