{
  "type": "Feature",
  "properties": {
    "addr:full":"Heiken 48 Sint-amands Antwerpen 2890",
    "addr:housenumber":"48",
    "addr:postcode":"2890",
    "addr:street":"Heiken",
    "iso:country":"BE",
    "sg:address":"Heiken 48",
    "sg:city":"Sint-amands",
    "sg:orig_category":"Beautyfarms, relaxatie and lichamelijk welzijn Schoonheidssalons",
    "sg:phone":"+32 52 34 09 58",
    "sg:postcode":"2890",
    "sg:province":"Antwerpen",
    "wof:name":"Rosette Veyt",
    "wof:placetype":"venue"
},
  "geometry": {"coordinates":[4.214630127,51.0472946167],"type":"Point"}
}