{
  "type": "Feature",
  "properties": {
    "iso:country":"BE",
    "sg:address":"Korte Gasthuisstraat 7",
    "sg:city":"Antwerpen",
    "sg:classifiers":[
        {
            "category":"Shopping",
            "subcategory":"Clothing, Apparel, & Fashions",
            "type":"Retail Goods"
        }
    ],
    "sg:phone":"+32 3 226 23 08",
    "sg:postcode":"2000",
    "sg:province":"Antwerpen",
    "sg:tags":[
        "clothing",
        "-",
        "gentleman"
    ],
    "wof:name":"Dkny",
    "wof:placetype":"venue"
},
  "geometry": {"coordinates":[4.4043149948,51.2172431946],"type":"Point"}
}