{
  "type": "Feature",
  "properties": {
    "addr:full":"Weeldestraat 93 Ravels Antwerpen 2381",
    "addr:housenumber":"93",
    "addr:postcode":"2381",
    "addr:street":"Weeldestraat",
    "iso:country":"BE",
    "sg:address":"Weeldestraat 93",
    "sg:city":"Ravels",
    "sg:classifiers":[
        {
            "category":"Fast Food",
            "type":"Food & Drink"
        }
    ],
    "sg:phone":"+32 14 65 55 87",
    "sg:postcode":"2381",
    "sg:province":"Antwerpen",
    "sg:tags":[
        "meeneem",
        "restaurant"
    ],
    "wof:name":"Frituur De Lekkerbek",
    "wof:placetype":"venue"
},
  "geometry": {"coordinates":[5.006374836,51.4099845886],"type":"Point"}
}