{
  "type": "Feature",
  "properties": {
    "addr:full":"Grote Markt 23 Mechelen Antwerpen 2800",
    "addr:housenumber":"23",
    "addr:postcode":"2800",
    "addr:street":"Grote Markt",
    "iso:country":"BE",
    "sg:address":"Grote Markt 23",
    "sg:city":"Mechelen",
    "sg:orig_category":"Catering and organisatie van feesten Fast food and meeneem restaurants Levering aan huis restaurants",
    "sg:phone":"+32 15 20 19 52",
    "sg:postcode":"2800",
    "sg:province":"Antwerpen",
    "wof:name":"Mytilus",
    "wof:placetype":"venue"
},
  "geometry": {"coordinates":[4.4805679321,51.0276870728],"type":"Point"}
}