{
  "type": "Feature",
  "properties": {
    "addr:full":"Vieux Moulin 42 Ellezelles (wodecq) Hainaut 7890",
    "addr:housenumber":"42",
    "addr:postcode":"7890",
    "addr:street":"Vieux Moulin",
    "iso:country":"BE",
    "sg:address":"Vieux Moulin 42",
    "sg:city":"Ellezelles (wodecq)",
    "sg:classifiers":[
        {
            "category":"Farming",
            "subcategory":"Livestock Farm",
            "type":"Manufacturing & Wholesale Goods"
        }
    ],
    "sg:phone":"+32 68 44 75 93",
    "sg:postcode":"7890",
    "sg:province":"Hainaut",
    "sg:tags":[
        "buyer"
    ],
    "wof:name":"De Boever J",
    "wof:placetype":"venue"
},
  "geometry": {"coordinates":[3.726929903,50.7186355591],"type":"Point"}
}