{
  "type": "Feature",
  "properties": {
    "addr:full":"Laagland 20 Lille Antwerpen 2275",
    "addr:housenumber":"20",
    "addr:postcode":"2275",
    "addr:street":"Laagland",
    "iso:country":"BE",
    "sg:address":"Laagland 20",
    "sg:city":"Lille",
    "sg:orig_category":"Non-Classified Establishments",
    "sg:phone":"+32 14 88 22 02",
    "sg:postcode":"2275",
    "sg:province":"Antwerpen",
    "wof:name":"De Peuter E",
    "wof:placetype":"venue"
},
  "geometry": {"coordinates":[4.8294200897,51.2314186096],"type":"Point"}
}