{
  "type": "Feature",
  "properties": {
    "addr:full":"Place Charles Ii 0 Charleroi Hainaut 6000",
    "addr:housenumber":"0",
    "addr:postcode":"6000",
    "addr:street":"Place Charles Ii;Hainaut",
    "iso:country":"BE",
    "sg:address":"Place Charles Ii 0",
    "sg:city":"Charleroi",
    "sg:orig_category":"Mus\u00e9es and patrimoine culturel",
    "sg:phone":"+32 71 23 02 97",
    "sg:postcode":"6000",
    "sg:province":"Hainaut",
    "wof:name":"Mus\u00c9e Jules Destr\u00c9e",
    "wof:placetype":"venue"
},
  "geometry": {"coordinates":[4.4446959496,50.4119758606],"type":"Point"}
}