{
  "type": "Feature",
  "properties": {
    "addr:full":"Rue De La Montante Roye 22 Tintigny (bellefontaine) Luxembourg 6730",
    "addr:housenumber":"22",
    "addr:postcode":"6730",
    "addr:street":"Rue De La Montante Roye",
    "iso:country":"BE",
    "sg:address":"Rue De La Montante Roye 22",
    "sg:city":"Tintigny (bellefontaine)",
    "sg:classifiers":[
        {
            "category":"Banks & Credit Unions",
            "subcategory":"Investment Brokerage",
            "type":"Services"
        }
    ],
    "sg:phone":"+32 63 44 42 29",
    "sg:postcode":"6730",
    "sg:province":"Luxembourg",
    "wof:name":"Dessoy",
    "wof:placetype":"venue"
},
  "geometry": {"coordinates":[5.5024690628,49.6705474854],"type":"Point"}
}