{
  "type": "Feature",
  "properties": {
    "iso:country":"BE",
    "sg:address":"Kerkhovensesteenweg 253",
    "sg:city":"Lommel",
    "sg:orig_category":"Installatie van houten of kunststof schrijnwerk",
    "sg:phone":"+32 11 34 18 01",
    "sg:postcode":"3920",
    "sg:province":"Limburg",
    "wof:name":"Diepvens J. & R.",
    "wof:placetype":"venue"
},
  "geometry": {"coordinates":[5.2798829079,51.1690597534],"type":"Point"}
}