{
  "type": "Feature",
  "properties": {
    "iso:country":"BE",
    "sg:address":"Chauss\u00e9e Roosevelt 24",
    "sg:city":"Amay",
    "sg:classifiers":[
        {
            "category":"Fast Food",
            "type":"Food & Drink"
        }
    ],
    "sg:phone":"+32 85 31 62 25",
    "sg:postcode":"4540",
    "sg:province":"Li\u00e8ge",
    "sg:tags":[
        "fried",
        "stand",
        "potato"
    ],
    "wof:name":"Routier (le)",
    "wof:placetype":"venue"
},
  "geometry": {"coordinates":[5.3163218498,50.5472373962],"type":"Point"}
}