{
  "type": "Feature",
  "properties": {
    "iso:country":"BE",
    "sg:address":"Wolfstraat 2",
    "sg:city":"Zedelgem (veldegem)",
    "sg:classifiers":[
        {
            "category":"Retail",
            "subcategory":"Veterinary Services",
            "type":"Services"
        }
    ],
    "sg:phone":"+32 50 28 02 11",
    "sg:postcode":"8210",
    "sg:province":"West-Vlaanderen",
    "sg:tags":[
        "veterinarian"
    ],
    "wof:name":"Keereman H",
    "wof:placetype":"venue"
},
  "geometry": {"coordinates":[3.1285839081,51.1163024902],"type":"Point"}
}