{
  "type": "Feature",
  "properties": {
    "addr:full":"Rue Royale 12 Tournai Hainaut 7500",
    "addr:housenumber":"12",
    "addr:postcode":"7500",
    "addr:street":"Rue Royale",
    "iso:country":"BE",
    "sg:address":"Rue Royale 12",
    "sg:city":"Tournai",
    "sg:classifiers":[
        {
            "category":"Shopping",
            "subcategory":"Optician",
            "type":"Retail Goods"
        }
    ],
    "sg:phone":"+32 69 22 13 55",
    "sg:postcode":"7500",
    "sg:province":"Hainaut",
    "sg:tags":[
        "-"
    ],
    "wof:name":"Nitelet Opticiens",
    "wof:placetype":"venue"
},
  "geometry": {"coordinates":[3.3917119503,50.6090087891],"type":"Point"}
}