{
  "type": "Feature",
  "properties": {
    "addr:full":"Rue De L\u00b4agriculture 104 Herstal Li\u00e8ge 4040",
    "addr:housenumber":"104",
    "addr:postcode":"4040",
    "addr:street":"Rue De L\u00b4Agriculture",
    "iso:country":"BE",
    "sg:address":"Rue De L\u00b4agriculture 104",
    "sg:city":"Herstal",
    "sg:classifiers":[
        {
            "category":"Personal",
            "subcategory":"Beauty Salon",
            "type":"Services"
        }
    ],
    "sg:phone":"+32 4 264 12 44",
    "sg:postcode":"4040",
    "sg:province":"Li\u00e8ge",
    "sg:tags":[
        "de",
        "coiffure"
    ],
    "wof:name":"Coiffure L. & V.",
    "wof:placetype":"venue"
},
  "geometry": {"coordinates":[5.6165437698,50.6732826233],"type":"Point"}
}