{
  "type": "Feature",
  "properties": {
    "addr:full":"Molenstraat 12 Herenthout Antwerpen 2270",
    "addr:housenumber":"12",
    "addr:postcode":"2270",
    "addr:street":"Molenstraat",
    "iso:country":"BE",
    "sg:address":"Molenstraat 12",
    "sg:city":"Herenthout",
    "sg:orig_category":"Opticiens",
    "sg:phone":"+32 15 51 45 04",
    "sg:postcode":"2270",
    "sg:province":"Antwerpen",
    "wof:name":"Vos",
    "wof:placetype":"venue"
},
  "geometry": {"coordinates":[4.7574372292,51.1395645142],"type":"Point"}
}