{
  "type": "Feature",
  "properties": {
    "iso:country":"BE",
    "sg:address":"Rue Jean Robie 43",
    "sg:city":"Saint-gilles",
    "sg:orig_category":"Mat\u00e9riel m\u00e9dical and orthop\u00e9dique and proth\u00e8ses Fab",
    "sg:phone":"+32 2 538 32 22",
    "sg:postcode":"1060",
    "sg:province":"Bruxelles-Capitale",
    "wof:name":"Technident",
    "wof:placetype":"venue"
},
  "geometry": {"coordinates":[4.3417258263,50.8256225586],"type":"Point"}
}