{
  "type": "Feature",
  "properties": {
    "addr:full":"Venneweg 18 Hoogstraten (meer) Antwerpen 2321",
    "addr:housenumber":"18",
    "addr:postcode":"2321",
    "addr:street":"Venneweg;Meer",
    "iso:country":"BE",
    "sg:address":"Venneweg 18",
    "sg:city":"Hoogstraten (meer)",
    "sg:classifiers":[
        {
            "category":"Farming",
            "subcategory":"Livestock Farm",
            "type":"Manufacturing & Wholesale Goods"
        }
    ],
    "sg:phone":"+32 3 315 09 23",
    "sg:postcode":"2321",
    "sg:province":"Antwerpen",
    "sg:tags":[
        "stud"
    ],
    "wof:name":"Voeten W",
    "wof:placetype":"venue"
},
  "geometry": {"coordinates":[4.7327427864,51.4324913025],"type":"Point"}
}