{
  "type": "Feature",
  "properties": {
    "addr:full":"Bellegemsestraat 42 Kortrijk (bellegem) West-Vlaanderen 8510",
    "addr:housenumber":"42",
    "addr:postcode":"8510",
    "addr:street":"Bellegemsestraat",
    "iso:country":"BE",
    "sg:address":"Bellegemsestraat 42",
    "sg:city":"Kortrijk (bellegem)",
    "sg:classifiers":[
        {
            "category":"Health Services",
            "subcategory":"Dentist",
            "type":"Services"
        }
    ],
    "sg:phone":"+32 56 22 40 99",
    "sg:postcode":"8510",
    "sg:province":"West-Vlaanderen",
    "wof:name":"Dubaere C",
    "wof:placetype":"venue"
},
  "geometry": {"coordinates":[3.283288002,50.7773284912],"type":"Point"}
}