{
  "type": "Feature",
  "properties": {
    "iso:country":"BE",
    "sg:address":"Wakkensesteenweg 1",
    "sg:city":"Tielt",
    "sg:orig_category":"Voertuigen",
    "sg:phone":"+32 51 40 16 83",
    "sg:postcode":"8700",
    "sg:province":"West-Vlaanderen",
    "wof:name":"Garage Bert",
    "wof:placetype":"venue"
},
  "geometry": {"coordinates":[3.3365650177,50.988243103],"type":"Point"}
}