{
  "type": "Feature",
  "properties": {
    "addr:full":"Stormestraat 69 Waregem West-Vlaanderen 8790",
    "addr:housenumber":"69",
    "addr:postcode":"8790",
    "addr:street":"Stormestraat",
    "iso:country":"BE",
    "sg:address":"Stormestraat 69",
    "sg:city":"Waregem",
    "sg:orig_category":"Telecommunicatieapparaten",
    "sg:phone":"+32 800 22 800",
    "sg:postcode":"8790",
    "sg:province":"West-Vlaanderen",
    "wof:name":"Teleboetiek",
    "wof:placetype":"venue"
},
  "geometry": {"coordinates":[3.428278923,50.8853988647],"type":"Point"}
}