{
  "type": "Feature",
  "properties": {
    "iso:country":"BE",
    "sg:address":"Rue De L'acad\u00e9mie 49",
    "sg:city":"Li\u00e8ge 1",
    "sg:classifiers":[
        {
            "category":"Real Estate",
            "subcategory":"Architect",
            "type":"Services"
        }
    ],
    "sg:phone":"+32 4 221 43 04",
    "sg:postcode":"4000",
    "sg:province":"Li\u00e8ge",
    "wof:name":"Gtf 2 - Architecture",
    "wof:placetype":"venue"
},
  "geometry": {"coordinates":[5.5668010712,50.6467781067],"type":"Point"}
}