{
  "type": "Feature",
  "properties": {
    "addr:full":"Grote Baan 183 Aalst (herdersem) Oost-Vlaanderen 9310",
    "addr:housenumber":"183",
    "addr:postcode":"9310",
    "addr:street":"Grote Baan",
    "iso:country":"BE",
    "sg:address":"Grote Baan 183",
    "sg:city":"Aalst (herdersem)",
    "sg:classifiers":[
        {
            "category":"Bars & Pubs",
            "type":"Food & Drink"
        }
    ],
    "sg:phone":"+32 53 70 13 62",
    "sg:postcode":"9310",
    "sg:province":"Oost-Vlaanderen",
    "wof:name":"Kletser (de)",
    "wof:placetype":"venue"
},
  "geometry": {"coordinates":[4.0655999184,50.9698028564],"type":"Point"}
}