{
  "type": "Feature",
  "properties": {
    "addr:full":"Luikersteenweg 568 Sint-truiden Limburg 3800",
    "addr:housenumber":"568",
    "addr:postcode":"sint-truiden;3800",
    "addr:street":"Luikersteenweg",
    "iso:country":"BE",
    "sg:address":"Luikersteenweg 568",
    "sg:city":"Sint-truiden",
    "sg:classifiers":[
        {
            "category":"Shopping",
            "subcategory":"Antiques",
            "type":"Retail Goods"
        }
    ],
    "sg:phone":"+32 11 48 58 76",
    "sg:postcode":"3800",
    "sg:province":"Limburg",
    "wof:name":"Antiek Romantica",
    "wof:placetype":"venue"
},
  "geometry": {"coordinates":[5.2029700279,50.8036193848],"type":"Point"}
}