{
  "type": "Feature",
  "properties": {
    "addr:full":"Rue De L'industrie 22 Nivelles Brabant Wallon 1400",
    "addr:housenumber":"22",
    "addr:postcode":"1400",
    "addr:street":"Rue De L'Industrie",
    "iso:country":"BE",
    "sg:address":"Rue De L'industrie 22",
    "sg:city":"Nivelles",
    "sg:classifiers":[
        {
            "category":"Autos & Motor Vehicles",
            "subcategory":"Automobile Sales",
            "type":"Retail Goods"
        }
    ],
    "sg:phone":"+32 2 356 29 26",
    "sg:postcode":"1400",
    "sg:province":"Brabant Wallon",
    "sg:tags":[
        "car",
        "used",
        "-"
    ],
    "wof:name":"Peugeot Belgique-luxembourg",
    "wof:placetype":"venue"
},
  "geometry": {"coordinates":[4.3549251556,50.5853271484],"type":"Point"}
}