{
  "type": "Feature",
  "properties": {
    "iso:country":"BE",
    "sg:address":"Rue De Houtain 19",
    "sg:city":"Oupeye",
    "sg:orig_category":"Ramassage and traitement des d\u00e9chets m\u00e9nagers. Gestion des d\u00e9charges and sites d\u00e9finitifs de stockag",
    "sg:phone":"+32 4 286 91 90",
    "sg:postcode":"4682",
    "sg:province":"Li\u00e8ge",
    "wof:name":"Sotrali\u00c8ge",
    "wof:placetype":"venue"
},
  "geometry": {"coordinates":[5.6338701248,50.7312393188],"type":"Point"}
}