{
  "type": "Feature",
  "properties": {
    "addr:full":"Kasteelstraat 1 Sint-gillis-waas Oost-Vlaanderen 9170",
    "addr:housenumber":"1",
    "addr:postcode":"9170",
    "addr:street":"Kasteelstraat",
    "iso:country":"BE",
    "sg:address":"Kasteelstraat 1",
    "sg:city":"Sint-gillis-waas",
    "sg:orig_category":"Schoenen",
    "sg:phone":"+32 3 770 70 03",
    "sg:postcode":"9170",
    "sg:province":"Oost-Vlaanderen",
    "wof:name":"Huis Van Kemseke",
    "wof:placetype":"venue"
},
  "geometry": {"coordinates":[4.1300139427,51.2151412964],"type":"Point"}
}