{
  "type": "Feature",
  "properties": {
    "addr:full":"Kesselsesteenweg 27 Box 6 Lier Antwerpen 2500",
    "addr:housenumber":"27;6",
    "addr:postcode":"2500",
    "addr:street":"Kesselsesteenweg;Box",
    "iso:country":"BE",
    "sg:address":"Kesselsesteenweg 27 Box 6",
    "sg:city":"Lier",
    "sg:classifiers":[
        {
            "category":"Retail",
            "subcategory":"Auto Rental",
            "type":"Services"
        }
    ],
    "sg:phone":"+32 3 491 90 54",
    "sg:postcode":"2500",
    "sg:province":"Antwerpen",
    "sg:tags":[
        "automobile",
        "-",
        "car",
        "self-drive"
    ],
    "wof:name":"Jos Plas & Cie",
    "wof:placetype":"venue"
},
  "geometry": {"coordinates":[4.5879850388,51.1298370361],"type":"Point"}
}