{
  "type": "Feature",
  "properties": {
    "addr:full":"Pijpenbeek 82 Aalst (nieuwerkerken) Oost-Vlaanderen 9320",
    "addr:housenumber":"82",
    "addr:postcode":"9320",
    "addr:street":"Pijpenbeek",
    "iso:country":"BE",
    "sg:address":"Pijpenbeek 82",
    "sg:city":"Aalst (nieuwerkerken)",
    "sg:classifiers":[
        {
            "category":"Structure",
            "subcategory":"Building",
            "type":"Public Place"
        }
    ],
    "sg:phone":"+32 53 83 90 40",
    "sg:postcode":"9320",
    "sg:province":"Oost-Vlaanderen",
    "sg:tags":[
        "door"
    ],
    "wof:name":"Huylebrouck Deuren Nv",
    "wof:placetype":"venue"
},
  "geometry": {"coordinates":[4.0553851128,50.9209976196],"type":"Point"}
}