{
  "type": "Feature",
  "properties": {
    "addr:full":"Heulsestraat 18ba Lendelede West-Vlaanderen 8860",
    "addr:housenumber":"18ba",
    "addr:postcode":"8860",
    "addr:street":"Heulsestraat",
    "iso:country":"BE",
    "sg:address":"Heulsestraat 18ba",
    "sg:city":"Lendelede",
    "sg:orig_category":"Paramedische behandelingen",
    "sg:phone":"+32 51 32 21 91",
    "sg:postcode":"8860",
    "sg:province":"West-Vlaanderen",
    "wof:name":"S. Roelens",
    "wof:placetype":"venue"
},
  "geometry": {"coordinates":[3.2371449471,50.8847427368],"type":"Point"}
}