{
  "type": "Feature",
  "properties": {
    "addr:full":"Ruelle Adam 9 Malmedy Li\u00e8ge 4960",
    "addr:housenumber":"9",
    "addr:postcode":"4960",
    "addr:street":"Ruelle Adam",
    "iso:country":"BE",
    "sg:address":"Ruelle Adam 9",
    "sg:city":"Malmedy",
    "sg:orig_category":"Syndicats",
    "sg:phone":"+32 80 77 04 63",
    "sg:postcode":"4960",
    "sg:province":"Li\u00e8ge",
    "wof:name":"C.n.c. R\u00c9gion Li\u00c8ge",
    "wof:placetype":"venue"
},
  "geometry": {"coordinates":[6.0725011826,50.4602088928],"type":"Point"}
}