{
  "type": "Feature",
  "properties": {
    "addr:full":"Rue G\u00c9n\u00c9ral Lotz 25 Ukkel/uccle Bruxelles-Capitale 1180",
    "addr:housenumber":"25",
    "addr:postcode":"1180",
    "addr:street":"Rue Ge\u0301Ne\u0301Ral Lotz;/",
    "iso:country":"BE",
    "sg:address":"Rue G\u00c9n\u00c9ral Lotz 25",
    "sg:city":"Ukkel/uccle",
    "sg:orig_category":"Woningbouw",
    "sg:phone":"+32 2 345 60 14",
    "sg:postcode":"1180",
    "sg:province":"Bruxelles-Capitale",
    "wof:name":"Debroux L. & Fils",
    "wof:placetype":"venue"
},
  "geometry": {"coordinates":[4.3576889038,50.8146514893],"type":"Point"}
}