{
  "type": "Feature",
  "properties": {
    "addr:full":"Chauss\u00e9e De Philippeville 7 Gerpinnes Hainaut 6280",
    "addr:housenumber":"7",
    "addr:postcode":"6280",
    "addr:street":"Chausse\u0301E De Philippeville;Hainaut",
    "iso:country":"BE",
    "sg:address":"Chauss\u00e9e De Philippeville 7",
    "sg:city":"Gerpinnes",
    "sg:classifiers":[
        {
            "category":"Building & Trades",
            "subcategory":"Electrical",
            "type":"Services"
        }
    ],
    "sg:phone":"+32 71 47 23 88",
    "sg:postcode":"6280",
    "sg:province":"Hainaut",
    "sg:tags":[
        "plants",
        "plant",
        "industrial",
        "buildings",
        "construction"
    ],
    "wof:name":"Cerib S.p.r.l.",
    "wof:placetype":"venue"
},
  "geometry": {"coordinates":[4.4702749252,50.3601760864],"type":"Point"}
}