{
  "type": "Feature",
  "properties": {
    "iso:country":"BE",
    "sg:address":"Rue Jean-baptiste Ledoux 28",
    "sg:city":"Charleroi",
    "sg:orig_category":"Tabac. Eclairage et \u00e9quipements du foyer. Journaux. Fournitures de bureau",
    "sg:phone":"+32 71 35 08 44",
    "sg:postcode":"6040",
    "sg:province":"Hainaut",
    "wof:name":"Librairie Le Campus",
    "wof:placetype":"venue"
},
  "geometry": {"coordinates":[4.4306821823,50.4400215149],"type":"Point"}
}