{
  "type": "Feature",
  "properties": {
    "addr:full":"Chauss\u00c9e De Waterloo 825 Uccle (bruxelles) Bruxelles-Capitale 1180",
    "addr:housenumber":"825",
    "addr:postcode":"1180",
    "addr:street":"Chausse\u0301E De Waterloo",
    "iso:country":"BE",
    "sg:address":"Chauss\u00c9e De Waterloo 825",
    "sg:city":"Uccle (bruxelles)",
    "sg:orig_category":"Artistes ind\u00e9pendants",
    "sg:phone":"+32 2 372 30 23",
    "sg:postcode":"1180",
    "sg:province":"Bruxelles-Capitale",
    "wof:name":"Gipsy Orch\u00c8stre Tzigana",
    "wof:placetype":"venue"
},
  "geometry": {"coordinates":[4.3688788414,50.8103866577],"type":"Point"}
}