{
  "type": "Feature",
  "properties": {
    "addr:full":"Lambeaulaan 24 Sint-lambrechts-woluwe/woluwe-saint-lambert Bruxelles-Capitale 1200",
    "addr:housenumber":"24",
    "addr:postcode":"1200",
    "addr:street":"Lambeaulaan",
    "iso:country":"BE",
    "sg:address":"Lambeaulaan 24",
    "sg:city":"Sint-lambrechts-woluwe/woluwe-saint-lambert",
    "sg:orig_category":"Artsen and specialisten",
    "sg:phone":"+32 2 736 51 01",
    "sg:postcode":"1200",
    "sg:province":"Bruxelles-Capitale",
    "wof:name":"Catherine Markstein",
    "wof:placetype":"venue"
},
  "geometry": {"coordinates":[4.4119200706,50.8462219238],"type":"Point"}
}