{
  "type": "Feature",
  "properties": {
    "addr:full":"Chauss\u00c9e De Ninove 466 Ronse/renaix Oost-Vlaanderen 9600",
    "addr:housenumber":"466",
    "addr:postcode":"9600",
    "addr:street":"Chausse\u0301E De Ninove",
    "iso:country":"BE",
    "sg:address":"Chauss\u00c9e De Ninove 466",
    "sg:city":"Ronse/renaix",
    "sg:orig_category":"Installation \u00e9lectrique r\u00e9sidentielle",
    "sg:phone":"+32 55 21 76 33",
    "sg:postcode":"9600",
    "sg:province":"Oost-Vlaanderen",
    "wof:name":"Peter De Weer",
    "wof:placetype":"venue"
},
  "geometry": {"coordinates":[3.6592409611,50.754611969],"type":"Point"}
}