{
  "type": "Feature",
  "properties": {
    "iso:country":"BE",
    "sg:address":"Sint-jansherenplein 14",
    "sg:city":"Maldegem",
    "sg:orig_category":"Installation de menuiserie en bois and plastique",
    "sg:phone":"+32 50 71 26 10",
    "sg:postcode":"9990",
    "sg:province":"Oost-Vlaanderen",
    "wof:name":"Dhont",
    "wof:placetype":"venue"
},
  "geometry": {"coordinates":[3.3842859268,51.2111320496],"type":"Point"}
}