{
  "type": "Feature",
  "properties": {
    "addr:full":"Chauss\u00e9e De Ninove 322 Renaix Oost-Vlaanderen 9600",
    "addr:housenumber":"322",
    "addr:postcode":"9600",
    "addr:street":"Chausse\u0301E De Ninove",
    "iso:country":"BE",
    "sg:address":"Chauss\u00e9e De Ninove 322",
    "sg:city":"Renaix",
    "sg:classifiers":[
        {
            "category":"Retail",
            "subcategory":"Auto Repair",
            "type":"Services"
        }
    ],
    "sg:phone":"+32 55 21 85 62",
    "sg:postcode":"9600",
    "sg:province":"Oost-Vlaanderen",
    "sg:tags":[
        "garage"
    ],
    "wof:name":"Vanhauwere-steeland Bvba",
    "wof:placetype":"venue"
},
  "geometry": {"coordinates":[3.6344161034,50.7531852722],"type":"Point"}
}