{
  "type": "Feature",
  "properties": {
    "iso:country":"BE",
    "sg:address":"Vijfde Januaristraat 13",
    "sg:city":"Dendermonde (sint-gillis-bij-dendermonde)",
    "sg:classifiers":[
        {
            "category":"Shopping",
            "subcategory":"Computers & Home Electronics",
            "type":"Retail Goods"
        }
    ],
    "sg:phone":"+32 52 21 26 41",
    "sg:postcode":"9200",
    "sg:province":"Oost-Vlaanderen",
    "sg:tags":[
        "-",
        "television",
        "radio"
    ],
    "wof:name":"Elektro Boon Bvba",
    "wof:placetype":"venue"
},
  "geometry": {"coordinates":[4.1150817871,51.019657135],"type":"Point"}
}