{
  "type": "Feature",
  "properties": {
    "addr:full":"Avenue De L'araucaria 109 Bruxelles Bruxelles-Capitale 1020",
    "addr:housenumber":"109",
    "addr:postcode":"1020",
    "addr:street":"Avenue De L'Araucaria",
    "iso:country":"BE",
    "sg:address":"Avenue De L'araucaria 109",
    "sg:city":"Bruxelles",
    "sg:classifiers":[
        {
            "category":"Health Services",
            "subcategory":"Doctor",
            "type":"Services"
        }
    ],
    "sg:phone":"+32 2 268 22 76",
    "sg:postcode":"1020",
    "sg:province":"Bruxelles-Capitale",
    "sg:tags":[
        "medicinephysicians",
        "surgeon"
    ],
    "wof:name":"Andr\u00e9 Jacqueline",
    "wof:placetype":"venue"
},
  "geometry": {"coordinates":[4.362965107,50.8968849182],"type":"Point"}
}