{
  "type": "Feature",
  "properties": {
    "addr:full":"Brugstraat 11 Wevelgem West-Vlaanderen 8560",
    "addr:housenumber":"11",
    "addr:postcode":"8560",
    "addr:street":"Brugstraat",
    "iso:country":"BE",
    "sg:address":"Brugstraat 11",
    "sg:city":"Wevelgem",
    "sg:orig_category":"Jeux and jouets",
    "sg:phone":"+32 56 42 34 79",
    "sg:postcode":"8560",
    "sg:province":"West-Vlaanderen",
    "wof:name":"The Paddock",
    "wof:placetype":"venue"
},
  "geometry": {"coordinates":[3.1852300167,50.8098869324],"type":"Point"}
}