{
  "type": "Feature",
  "properties": {
    "iso:country":"BE",
    "sg:address":"Verbindingsweg 83",
    "sg:city":"Riemst (valmeer)",
    "sg:classifiers":[
        {
            "category":"Professional",
            "subcategory":"Computer Services",
            "type":"Services"
        }
    ],
    "sg:phone":"+32 12 44 12 97",
    "sg:postcode":"3770",
    "sg:province":"Limburg",
    "sg:tags":[
        "-",
        "processing",
        "data",
        "software"
    ],
    "wof:name":"Inforjans Bvba",
    "wof:placetype":"venue"
},
  "geometry": {"coordinates":[5.6017279625,50.7819213867],"type":"Point"}
}