{
  "type": "Feature",
  "properties": {
    "addr:full":"Bareelstraat 55 Geraardsbergen Oost-Vlaanderen 9506",
    "addr:housenumber":"55",
    "addr:postcode":"9506",
    "addr:street":"Bareelstraat",
    "iso:country":"BE",
    "sg:address":"Bareelstraat 55",
    "sg:city":"Geraardsbergen",
    "sg:orig_category":"Catering and organisatie van feesten Ruimtes voor conferenties, recepties and feesten",
    "sg:phone":"+32 54 50 31 13",
    "sg:postcode":"9506",
    "sg:province":"Oost-Vlaanderen",
    "wof:name":"Paraplu",
    "wof:placetype":"venue"
},
  "geometry": {"coordinates":[3.8985300064,50.7987060547],"type":"Point"}
}