{
  "type": "Feature",
  "properties": {
    "addr:full":"Avenue De La Belle Voie 10 Wavre Brabant Wallon 1300",
    "addr:housenumber":"10;1300",
    "addr:street":"Avenue De La Belle Voie",
    "iso:country":"BE",
    "sg:address":"Avenue De La Belle Voie 10",
    "sg:city":"Wavre",
    "sg:classifiers":[
        {
            "category":"Real Estate",
            "subcategory":"Architect",
            "type":"Services"
        }
    ],
    "sg:phone":"+32 10 24 34 32",
    "sg:postcode":"1300",
    "sg:province":"Brabant Wallon",
    "wof:name":"Bureau D'architecture Pierre J\u00fcckler Sprl",
    "wof:placetype":"venue"
},
  "geometry": {"coordinates":[4.6165041924,50.7194633484],"type":"Point"}
}