{
  "type": "Feature",
  "properties": {
    "addr:full":"Kempische Steenweg 606 Hasselt Limburg 3500",
    "addr:housenumber":"606",
    "addr:postcode":"3500",
    "addr:street":"Kempische Steenweg",
    "iso:country":"BE",
    "sg:address":"Kempische Steenweg 606",
    "sg:city":"Hasselt",
    "sg:classifiers":[
        {
            "category":"Home & Garden",
            "subcategory":"Garden Supply",
            "type":"Retail Goods"
        }
    ],
    "sg:phone":"+32 11 26 24 24",
    "sg:postcode":"3500",
    "sg:province":"Limburg",
    "sg:tags":[
        "wood"
    ],
    "wof:name":"A.d.b. Vandeput Nv",
    "wof:placetype":"venue"
},
  "geometry": {"coordinates":[5.3410902023,50.9396095276],"type":"Point"}
}