{
  "type": "Feature",
  "properties": {
    "addr:full":"Avenue Du Cosmonaute 22 Sint-pieters-woluwe/woluwe-saint-pierre Bruxelles-Capitale 1150",
    "addr:housenumber":"22",
    "addr:postcode":"1150",
    "addr:street":"Avenue Du Cosmonaute;/",
    "iso:country":"BE",
    "sg:address":"Avenue Du Cosmonaute 22",
    "sg:city":"Sint-pieters-woluwe/woluwe-saint-pierre",
    "sg:orig_category":"M\u00e9decins and sp\u00e9cialistes",
    "sg:phone":"+32 2 762 25 49",
    "sg:postcode":"1150",
    "sg:province":"Bruxelles-Capitale",
    "wof:name":"Maryse Wanlin",
    "wof:placetype":"venue"
},
  "geometry": {"coordinates":[4.4428200722,50.8377799988],"type":"Point"}
}