{
  "type": "Feature",
  "properties": {
    "iso:country":"BE",
    "sg:address":"Dijlestraat 16",
    "sg:city":"Keerbergen",
    "sg:classifiers":[
        {
            "category":"Personal",
            "type":"Services"
        }
    ],
    "sg:phone":"+32 15 52 95 03",
    "sg:postcode":"3140",
    "sg:province":"Vlaams-Brabant",
    "sg:tags":[
        "party",
        "planning"
    ],
    "wof:name":"Pres De Chez Vous",
    "wof:placetype":"venue"
},
  "geometry": {"coordinates":[4.6415109634,50.9937019348],"type":"Point"}
}