{
  "type": "Feature",
  "properties": {
    "addr:full":"Industrielaan 19 Torhout West-Vlaanderen 8820",
    "addr:housenumber":"19",
    "addr:postcode":"8820",
    "addr:street":"Industrielaan",
    "iso:country":"BE",
    "sg:address":"Industrielaan 19",
    "sg:city":"Torhout",
    "sg:classifiers":[
        {
            "category":"Home & Garden",
            "subcategory":"Furniture",
            "type":"Retail Goods"
        }
    ],
    "sg:phone":"+32 50 21 24 24",
    "sg:postcode":"8820",
    "sg:province":"West-Vlaanderen",
    "sg:tags":[
        "household",
        "wood"
    ],
    "wof:name":"Meubelfabriek Thor Nv",
    "wof:placetype":"venue"
},
  "geometry": {"coordinates":[3.103566885,51.0716590881],"type":"Point"}
}