{
  "type": "Feature",
  "properties": {
    "addr:full":"Rue Warmonceau 318 Charleroi Hainaut 6000",
    "addr:housenumber":"318",
    "addr:postcode":"6000",
    "addr:street":"Rue Warmonceau;Hainaut",
    "iso:country":"BE",
    "sg:address":"Rue Warmonceau 318",
    "sg:city":"Charleroi",
    "sg:classifiers":[
        {
            "category":"Organizations",
            "subcategory":"Professional Association",
            "type":"Services"
        }
    ],
    "sg:phone":"+32 71 48 84 00",
    "sg:postcode":"6000",
    "sg:province":"Hainaut",
    "sg:tags":[
        "trade-union",
        "federation"
    ],
    "wof:name":"Caisse Wallonne",
    "wof:placetype":"venue"
},
  "geometry": {"coordinates":[4.4608998299,50.4296188354],"type":"Point"}
}