{
  "type": "Feature",
  "properties": {
    "addr:full":"Stationsstraat 2 Ravels (weelde) Antwerpen 2381",
    "addr:housenumber":"2",
    "addr:postcode":"2381",
    "addr:street":"Stationsstraat",
    "iso:country":"BE",
    "sg:address":"Stationsstraat 2",
    "sg:city":"Ravels (weelde)",
    "sg:classifiers":[
        {
            "category":"Government",
            "subcategory":"Fire Station",
            "type":"Public Place"
        }
    ],
    "sg:phone":"+32 14 65 04 82",
    "sg:postcode":"2381",
    "sg:province":"Antwerpen",
    "sg:tags":[
        "installation",
        "-",
        "air conditioning"
    ],
    "wof:name":"Van De Mierop",
    "wof:placetype":"venue"
},
  "geometry": {"coordinates":[4.9368271828,51.3991127014],"type":"Point"}
}