{
  "type": "Feature",
  "properties": {
    "addr:full":"Phlippostraat 5 Zulte (machelen) Oost-Vlaanderen 9870",
    "addr:housenumber":"5",
    "addr:postcode":"9870",
    "addr:street":"Phlippostraat",
    "iso:country":"BE",
    "sg:address":"Phlippostraat 5",
    "sg:city":"Zulte (machelen)",
    "sg:classifiers":[
        {
            "category":"Professional",
            "subcategory":"Testing Lab",
            "type":"Services"
        }
    ],
    "sg:phone":"+32 9 380 06 47",
    "sg:postcode":"9870",
    "sg:province":"Oost-Vlaanderen",
    "sg:tags":[
        "laboratory",
        "-",
        "machines",
        "apparatus",
        "supply"
    ],
    "wof:name":"Achrom Nv",
    "wof:placetype":"venue"
},
  "geometry": {"coordinates":[3.4901890755,50.9562339783],"type":"Point"}
}