{
  "type": "Feature",
  "properties": {
    "iso:country":"BE",
    "sg:address":"Overwinningsstraat 1ba",
    "sg:city":"Willebroek",
    "sg:orig_category":"Dierenartsen",
    "sg:phone":"+32 3 886 57 29",
    "sg:postcode":"2830",
    "sg:province":"Antwerpen",
    "wof:name":"Marleen Thys",
    "wof:placetype":"venue"
},
  "geometry": {"coordinates":[4.3603010178,51.0598068237],"type":"Point"}
}