{
  "type": "Feature",
  "properties": {
    "iso:country":"BE",
    "sg:address":"Diepeweg 4",
    "sg:city":"Heusden-zolder",
    "sg:orig_category":"Herstellingen and onderhoud van auto's Voertuigen",
    "sg:phone":"+32 11 53 77 34",
    "sg:postcode":"3550",
    "sg:province":"Limburg",
    "wof:name":"Autohandel Rian",
    "wof:placetype":"venue"
},
  "geometry": {"coordinates":[5.2733821869,51.0137634277],"type":"Point"}
}