{
  "type": "Feature",
  "properties": {
    "addr:full":"Rue Georges Simenon 13 Li\u00c8ge Li\u00e8ge 4020",
    "addr:housenumber":"13",
    "addr:postcode":"4020",
    "addr:street":"Rue Georges Simenon",
    "iso:country":"BE",
    "sg:address":"Rue Georges Simenon 13",
    "sg:city":"Li\u00c8ge",
    "sg:orig_category":"Technisch and beroeps secundair onderwijs",
    "sg:phone":"+32 4 343 55 77",
    "sg:postcode":"4020",
    "sg:province":"Li\u00e8ge",
    "wof:name":"Ecole Commerce & S\u00c9cr\u00c9t.",
    "wof:placetype":"venue"
},
  "geometry": {"coordinates":[5.5844039917,50.6417694092],"type":"Point"}
}