{
  "type": "Feature",
  "properties": {
    "iso:country":"BE",
    "sg:address":"Vermaesenplein",
    "sg:city":"Londerzeel",
    "sg:classifiers":[
        {
            "category":"Fast Food",
            "type":"Food & Drink"
        }
    ],
    "sg:phone":"+32 52 30 29 62",
    "sg:postcode":"1840",
    "sg:province":"Vlaams-Brabant",
    "sg:tags":[
        "meeneem",
        "restaurant"
    ],
    "wof:name":"Eddy Lauwers",
    "wof:placetype":"venue"
},
  "geometry": {"coordinates":[4.2435002327,51.0203475952],"type":"Point"}
}