{
  "type": "Feature",
  "properties": {
    "iso:country":"BE",
    "sg:address":"E. Eylenboschstraat 81",
    "sg:city":"Dilbeek",
    "sg:orig_category":"Epiceries",
    "sg:phone":"+32 2 569 21 02",
    "sg:postcode":"1703",
    "sg:province":"Vlaams-Brabant",
    "wof:name":"De 4 Seizoenen",
    "wof:placetype":"venue"
},
  "geometry": {"coordinates":[4.1951651573,50.8379478455],"type":"Point"}
}