{
  "type": "Feature",
  "properties": {
    "addr:full":"Rue Cl\u00e9ment Grenier 7 Mons (baudour) Hainaut 7331",
    "addr:housenumber":"7",
    "addr:postcode":"7331",
    "addr:street":"Rue Cle\u0301Ment Grenier",
    "iso:country":"BE",
    "sg:address":"Rue Cl\u00e9ment Grenier 7",
    "sg:city":"Mons (baudour)",
    "sg:classifiers":[
        {
            "category":"Personal",
            "subcategory":"Nail Salon",
            "type":"Services"
        }
    ],
    "sg:phone":"+32 65 60 04 42",
    "sg:postcode":"7331",
    "sg:province":"Hainaut",
    "sg:tags":[
        "pedicure"
    ],
    "wof:name":"Leblanc S",
    "wof:placetype":"venue"
},
  "geometry": {"coordinates":[3.832367897,50.4841804504],"type":"Point"}
}