{
  "type": "Feature",
  "properties": {
    "iso:country":"BE",
    "sg:address":"Oude Mechelbaan 10",
    "sg:city":"Heist-op-den-berg",
    "sg:orig_category":"Installatie van metalen schrijnwerk",
    "sg:phone":"+32 15 24 14 95",
    "sg:postcode":"2220",
    "sg:province":"Antwerpen",
    "wof:name":"Alois Van Loo En Zoon",
    "wof:placetype":"venue"
},
  "geometry": {"coordinates":[4.7064552307,51.0754776001],"type":"Point"}
}