{
  "type": "Feature",
  "properties": {
    "addr:full":"Rue Point Du Jour 11 Peruwelz Hainaut 7600",
    "addr:housenumber":"11",
    "addr:postcode":"7600",
    "addr:street":"Rue Point Du Jour;Hainaut",
    "iso:country":"BE",
    "sg:address":"Rue Point Du Jour 11",
    "sg:city":"Peruwelz",
    "sg:orig_category":"Messageries",
    "sg:phone":"+32 69 77 57 33",
    "sg:postcode":"7600",
    "sg:province":"Hainaut",
    "wof:name":"C.m.i.p.",
    "wof:placetype":"venue"
},
  "geometry": {"coordinates":[3.6124250889,50.5105018616],"type":"Point"}
}