{
  "type": "Feature",
  "properties": {
    "addr:full":"Bertogne 139 Bertogne Luxembourg 6687",
    "addr:housenumber":"139",
    "addr:postcode":"6687",
    "addr:street":"Bertogne",
    "iso:country":"BE",
    "sg:address":"Bertogne 139",
    "sg:city":"Bertogne",
    "sg:classifiers":[
        {
            "category":"Wholesale",
            "subcategory":"Farm Supplies",
            "type":"Manufacturing & Wholesale Goods"
        }
    ],
    "sg:phone":"+32 61 21 40 49",
    "sg:postcode":"6687",
    "sg:province":"Luxembourg",
    "sg:tags":[
        "machine",
        "agricoles",
        "mat\u00e9riel",
        "gr"
    ],
    "wof:name":"Fe. Preser Fr\u00c8res",
    "wof:placetype":"venue"
},
  "geometry": {"coordinates":[5.6689548492,50.0833511353],"type":"Point"}
}