{
  "type": "Feature",
  "properties": {
    "addr:full":"Bredaseweg 33 Ravels (weelde) Antwerpen 2381",
    "addr:housenumber":"33",
    "addr:postcode":"2381",
    "addr:street":"Bredaseweg",
    "iso:country":"BE",
    "sg:address":"Bredaseweg 33",
    "sg:city":"Ravels (weelde)",
    "sg:classifiers":[
        {
            "category":"Manufacturing",
            "subcategory":"Lumber",
            "type":"Manufacturing & Wholesale Goods"
        }
    ],
    "sg:phone":"+32 14 65 01 83",
    "sg:postcode":"2381",
    "sg:province":"Antwerpen",
    "sg:tags":[
        "timber"
    ],
    "wof:name":"Martin's Houthandel Nv",
    "wof:placetype":"venue"
},
  "geometry": {"coordinates":[5.006374836,51.4099845886],"type":"Point"}
}