{
  "type": "Feature",
  "properties": {
    "addr:full":"Steenstraat 39 Lede Oost-Vlaanderen 9340",
    "addr:housenumber":"39",
    "addr:postcode":"9340",
    "addr:street":"Steenstraat",
    "iso:country":"BE",
    "sg:address":"Steenstraat 39",
    "sg:city":"Lede",
    "sg:orig_category":"V\u00eatements sur mesure Fab",
    "sg:phone":"+32 53 80 58 90",
    "sg:postcode":"9340",
    "sg:province":"Oost-Vlaanderen",
    "wof:name":"Leona Ponnet",
    "wof:placetype":"venue"
},
  "geometry": {"coordinates":[4.0012001991,50.9635658264],"type":"Point"}
}