{
  "type": "Feature",
  "properties": {
    "addr:full":"Chauss\u00e9e De Bruxelles 29 Ath Hainaut 7800",
    "addr:housenumber":"29",
    "addr:postcode":"7800",
    "addr:street":"Chausse\u0301E De Bruxelles",
    "iso:country":"BE",
    "sg:address":"Chauss\u00e9e De Bruxelles 29",
    "sg:city":"Ath",
    "sg:classifiers":[
        {
            "category":"Health Services",
            "subcategory":"Health Practitioner",
            "type":"Services"
        }
    ],
    "sg:phone":"+32 68 28 33 36",
    "sg:postcode":"7800",
    "sg:province":"Hainaut",
    "sg:tags":[
        "physiotherapist"
    ],
    "wof:name":"Gorlia G\u00e9rard",
    "wof:placetype":"venue"
},
  "geometry": {"coordinates":[3.7855069637,50.6315498352],"type":"Point"}
}