{
  "type": "Feature",
  "properties": {
    "addr:full":"Place Edouard Bantigny 0 Manage Hainaut 7170",
    "addr:housenumber":"0",
    "addr:postcode":"7170",
    "addr:street":"Place Edouard Bantigny",
    "iso:country":"BE",
    "sg:address":"Place Edouard Bantigny 0",
    "sg:city":"Manage",
    "sg:orig_category":"M\u00e9decins and sp\u00e9cialistes",
    "sg:phone":"+32 64 55 55 21",
    "sg:postcode":"7170",
    "sg:province":"Hainaut",
    "wof:name":"Consultation Nourrissons",
    "wof:placetype":"venue"
},
  "geometry": {"coordinates":[4.2354521751,50.5024681091],"type":"Point"}
}