{
  "type": "Feature",
  "properties": {
    "addr:full":"Geraardsbergsesteenweg 609 Ninove Oost-Vlaanderen 9400",
    "addr:housenumber":"609",
    "addr:postcode":"9400",
    "addr:street":"Geraardsbergsesteenweg",
    "iso:country":"BE",
    "sg:address":"Geraardsbergsesteenweg 609",
    "sg:city":"Ninove",
    "sg:orig_category":"Enseignement maternel and primaire",
    "sg:phone":"+32 54 50 03 84",
    "sg:postcode":"9400",
    "sg:province":"Oost-Vlaanderen",
    "wof:name":"Gemeentelijke Basisschool",
    "wof:placetype":"venue"
},
  "geometry": {"coordinates":[4.0141401291,50.8364601135],"type":"Point"}
}