{
  "type": "Feature",
  "properties": {
    "addr:full":"Avenue Des M\u00dbriers 0 Watermaal-bosvoorde/watermael- Bruxelles-Capitale 1170",
    "addr:housenumber":"0",
    "addr:postcode":"1170",
    "addr:street":"Avenue Des Mu\u0302Riers",
    "iso:country":"BE",
    "sg:address":"Avenue Des M\u00dbriers 0",
    "sg:city":"Watermaal-bosvoorde/watermael-",
    "sg:classifiers":[
        {
            "category":"Insurance",
            "subcategory":"Life Insurance",
            "type":"Services"
        }
    ],
    "sg:phone":"+32 2 673 98 77",
    "sg:postcode":"1170",
    "sg:province":"Bruxelles-Capitale",
    "sg:tags":[
        "assurance"
    ],
    "wof:name":"Catry Christian",
    "wof:placetype":"venue"
},
  "geometry": {"coordinates":[4.3950948715,50.8105163574],"type":"Point"}
}