{
  "type": "Feature",
  "properties": {
    "iso:country":"BE",
    "sg:address":"Nelemolenstraat 11",
    "sg:city":"Dilbeek",
    "sg:classifiers":[
        {
            "category":"Health Services",
            "subcategory":"Doctor",
            "type":"Services"
        }
    ],
    "sg:phone":"+32 2 463 04 00",
    "sg:postcode":"1700",
    "sg:province":"Vlaams-Brabant",
    "sg:tags":[
        "medicinephysicians",
        "surgeon"
    ],
    "wof:name":"De Mey Johan",
    "wof:placetype":"venue"
},
  "geometry": {"coordinates":[4.2661509514,50.8549919128],"type":"Point"}
}