{
  "type": "Feature",
  "properties": {
    "addr:full":"Avenue Reine Astrid 1 Limbourg Li\u00e8ge 4831",
    "addr:housenumber":"1",
    "addr:postcode":"4831",
    "addr:street":"Avenue Reine Astrid",
    "iso:country":"BE",
    "sg:address":"Avenue Reine Astrid 1",
    "sg:city":"Limbourg",
    "sg:orig_category":"Entretien and r\u00e9parations de voitures",
    "sg:phone":"+32 87 76 20 63",
    "sg:postcode":"4831",
    "sg:province":"Li\u00e8ge",
    "wof:name":"A. Raway",
    "wof:placetype":"venue"
},
  "geometry": {"coordinates":[5.9386529922,50.6175003052],"type":"Point"}
}