{
  "type": "Feature",
  "properties": {
    "iso:country":"BE",
    "sg:address":"Dr\u00c8ve De L'hostellerie 101",
    "sg:city":"Wavre",
    "sg:classifiers":[
        {
            "category":"Travel",
            "subcategory":"Hotels & Motels",
            "type":"Entertainment"
        }
    ],
    "sg:phone":"+32 10 24 24 57",
    "sg:postcode":"1300",
    "sg:province":"Brabant Wallon",
    "sg:tags":[
        "restaurant"
    ],
    "wof:name":"Ferme De L'host\u00c9",
    "wof:placetype":"venue"
},
  "geometry": {"coordinates":[4.6202859879,50.7250518799],"type":"Point"}
}