{
  "type": "Feature",
  "properties": {
    "iso:country":"BE",
    "sg:address":"Engsbergseweg 107",
    "sg:city":"Tessenderlo",
    "sg:classifiers":[
        {
            "category":"Retail",
            "subcategory":"Event Space",
            "type":"Services"
        }
    ],
    "sg:phone":"+32 13 32 28 08",
    "sg:postcode":"3980",
    "sg:province":"Limburg",
    "sg:tags":[
        "rental",
        "-",
        "hall"
    ],
    "wof:name":"Buurthuis 't Goor",
    "wof:placetype":"venue"
},
  "geometry": {"coordinates":[5.0376701355,51.028629303],"type":"Point"}
}