{
  "type": "Feature",
  "properties": {
    "addr:full":"Bevrijdingslaan 163 Dendermonde (appels) Oost-Vlaanderen 9200",
    "addr:housenumber":"163",
    "addr:postcode":"9200",
    "addr:street":"Bevrijdingslaan;Appels Oost-Vlaanderen",
    "iso:country":"BE",
    "sg:address":"Bevrijdingslaan 163",
    "sg:city":"Dendermonde (appels)",
    "sg:classifiers":[
        {
            "category":"Building & Trades",
            "subcategory":"Construction",
            "type":"Services"
        }
    ],
    "sg:phone":"+32 52 22 10 52",
    "sg:postcode":"9200",
    "sg:province":"Oost-Vlaanderen",
    "sg:tags":[
        "roofing",
        "material",
        "-"
    ],
    "wof:name":"Opalfvens Dirk",
    "wof:placetype":"venue"
},
  "geometry": {"coordinates":[4.0523738861,51.0240325928],"type":"Point"}
}