{
  "type": "Feature",
  "properties": {
    "addr:full":"Rue Laixheau 19 Herstal Li\u00e8ge 4040",
    "addr:housenumber":"19",
    "addr:postcode":"4040",
    "addr:street":"Rue Laixheau",
    "iso:country":"BE",
    "sg:address":"Rue Laixheau 19",
    "sg:city":"Herstal",
    "sg:orig_category":"Mat\u00e9riel pour plomberie and chauffage Electrom\u00e9nager, t\u00e9l\u00e9visions and radios",
    "sg:phone":"+32 4 264 93 19",
    "sg:postcode":"4040",
    "sg:province":"Li\u00e8ge",
    "wof:name":"Vrijens",
    "wof:placetype":"venue"
},
  "geometry": {"coordinates":[5.6289291382,50.6665458679],"type":"Point"}
}