{
  "type": "Feature",
  "properties": {
    "addr:full":"Kapelstraat 30b4 2 Genk Limburg 3600",
    "addr:housenumber":"30b4 2",
    "addr:postcode":"3600",
    "addr:street":"Kapelstraat",
    "iso:country":"BE",
    "sg:address":"Kapelstraat 30b4 2",
    "sg:city":"Genk",
    "sg:orig_category":"Installatie van metalen schrijnwerk",
    "sg:phone":"+32 89 35 89 06",
    "sg:postcode":"3600",
    "sg:province":"Limburg",
    "wof:name":"Damiano Magnani",
    "wof:placetype":"venue"
},
  "geometry": {"coordinates":[5.5006299019,50.96667099],"type":"Point"}
}