{
  "type": "Feature",
  "properties": {
    "iso:country":"BE",
    "sg:address":"Square Vergote 1",
    "sg:city":"Bruxelles (woluwe-saint-lambert)",
    "sg:classifiers":[
        {
            "category":"Real Estate",
            "subcategory":"Architect",
            "type":"Services"
        }
    ],
    "sg:phone":"+32 2 735 24 58",
    "sg:postcode":"1200",
    "sg:province":"Bruxelles-Capitale",
    "wof:name":"Atelier D'architecture Michel De Visscher & Associ\u00e9s",
    "wof:placetype":"venue"
},
  "geometry": {"coordinates":[4.4043512344,50.8448028564],"type":"Point"}
}