{
  "type": "Feature",
  "properties": {
    "addr:full":"Boulevard De La Sauveni\u00e8re 77 Li\u00e8ge 1 Li\u00e8ge 4000",
    "addr:housenumber":"77;1",
    "addr:postcode":"4000",
    "addr:street":"Boulevard De La Sauvenie\u0300Re",
    "iso:country":"BE",
    "sg:address":"Boulevard De La Sauveni\u00e8re 77",
    "sg:city":"Li\u00e8ge 1",
    "sg:classifiers":[
        {
            "category":"Government",
            "subcategory":"Office",
            "type":"Public Place"
        }
    ],
    "sg:phone":"+32 4 232 65 10",
    "sg:postcode":"4000",
    "sg:province":"Li\u00e8ge",
    "sg:tags":[
        "-",
        "tourism",
        "federation"
    ],
    "wof:name":"Federation Du Tourisme",
    "wof:placetype":"venue"
},
  "geometry": {"coordinates":[5.5663599968,50.6432609558],"type":"Point"}
}