{
  "type": "Feature",
  "properties": {
    "iso:country":"BE",
    "sg:address":"Ten Bos 17",
    "sg:city":"Sint-niklaas",
    "sg:orig_category":"Meubles D\u00e9taillants, Am\u00e9nagement de B\u00e2timents et de Cuisines",
    "sg:phone":"+32 3 777 54 20",
    "sg:postcode":"9100",
    "sg:province":"Oost-Vlaanderen",
    "wof:name":"Huis Integra Swiss",
    "wof:placetype":"venue"
},
  "geometry": {"coordinates":[4.1785650253,51.1939620972],"type":"Point"}
}