{
  "type": "Feature",
  "properties": {
    "addr:full":"Generaal Eenensstraat 81 Schaarbeek/schaerbeek Bruxelles-Capitale 1030",
    "addr:housenumber":"81",
    "addr:postcode":"1030",
    "addr:street":"Generaal Eenensstraat",
    "iso:country":"BE",
    "sg:address":"Generaal Eenensstraat 81",
    "sg:city":"Schaarbeek/schaerbeek",
    "sg:orig_category":"Installatie van houten of kunststof schrijnwerk",
    "sg:phone":"+32 2 242 75 00",
    "sg:postcode":"1030",
    "sg:province":"Bruxelles-Capitale",
    "wof:name":"Fe. Batiplast",
    "wof:placetype":"venue"
},
  "geometry": {"coordinates":[4.3781847954,50.8688011169],"type":"Point"}
}