{
  "type": "Feature",
  "properties": {
    "addr:full":"Groot Veerle 40 Brecht Antwerpen 2960",
    "addr:housenumber":"40",
    "addr:postcode":"2960",
    "addr:street":"Groot Veerle",
    "iso:country":"BE",
    "sg:address":"Groot Veerle 40",
    "sg:city":"Brecht",
    "sg:orig_category":"Eleveurs de bovins",
    "sg:phone":"+32 3 313 99 62",
    "sg:postcode":"2960",
    "sg:province":"Antwerpen",
    "wof:name":"Tony Rombouts",
    "wof:placetype":"venue"
},
  "geometry": {"coordinates":[4.6781859398,51.3257026672],"type":"Point"}
}