{
  "type": "Feature",
  "properties": {
    "addr:full":"Avenue Du Sacr\u00c9 Coeur 81 Jette Bruxelles-Capitale 1090",
    "addr:housenumber":"81",
    "addr:postcode":"1090",
    "addr:street":"Avenue Du Sacre\u0301 Coeur",
    "iso:country":"BE",
    "sg:address":"Avenue Du Sacr\u00c9 Coeur 81",
    "sg:city":"Jette",
    "sg:orig_category":"Magasins de r\u00e9parations d'articles personnels et m\u00e9nagers divers. Installation de menuiserie m\u00e9talli",
    "sg:phone":"+32 495 52 57 98",
    "sg:postcode":"1090",
    "sg:province":"Bruxelles-Capitale",
    "wof:name":"Serrurier Michel",
    "wof:placetype":"venue"
},
  "geometry": {"coordinates":[4.3307042122,50.8843040466],"type":"Point"}
}