{
  "type": "Feature",
  "properties": {
    "iso:country":"BE",
    "sg:address":"Zinkvalstraat 76",
    "sg:city":"Aartselaar",
    "sg:classifiers":[
        {
            "category":"Professional",
            "subcategory":"Management & Consulting",
            "type":"Services"
        }
    ],
    "sg:phone":"+32 474 83 46 96",
    "sg:postcode":"2630",
    "sg:province":"Antwerpen",
    "sg:tags":[
        "consultant"
    ],
    "wof:name":"Dynamic Consultancy Services Bvba",
    "wof:placetype":"venue"
},
  "geometry": {"coordinates":[4.3696098328,51.1237983704],"type":"Point"}
}