{
  "type": "Feature",
  "properties": {
    "addr:full":"Rue Deneumoustier 15 Belgrade Namur 5001",
    "addr:housenumber":"15",
    "addr:postcode":"5001",
    "addr:street":"Rue Deneumoustier;Namur",
    "iso:country":"BE",
    "sg:address":"Rue Deneumoustier 15",
    "sg:city":"Belgrade",
    "sg:classifiers":[
        {
            "category":"Banks & Credit Unions",
            "subcategory":"Bank",
            "type":"Services"
        }
    ],
    "sg:phone":"+32 81 73 05 30",
    "sg:postcode":"5001",
    "sg:province":"Namur",
    "wof:name":"Aslk-cger Bank",
    "wof:placetype":"venue"
},
  "geometry": {"coordinates":[4.8261389732,50.4710464478],"type":"Point"}
}