{
  "type": "Feature",
  "properties": {
    "addr:full":"Avenue Peltzer 33b8 Verviers Li\u00e8ge 4800",
    "addr:housenumber":"33b8",
    "addr:postcode":"4800",
    "addr:street":"Avenue Peltzer",
    "iso:country":"BE",
    "sg:address":"Avenue Peltzer 33b8",
    "sg:city":"Verviers",
    "sg:orig_category":"Beheer onroerend goed",
    "sg:phone":"+32 87 22 00 43",
    "sg:postcode":"4800",
    "sg:province":"Li\u00e8ge",
    "wof:name":"Michel Delrez",
    "wof:placetype":"venue"
},
  "geometry": {"coordinates":[5.8543591499,50.5826148987],"type":"Point"}
}