{
  "type": "Feature",
  "properties": {
    "iso:country":"BE",
    "sg:address":"Moerplas 77",
    "sg:city":"Puurs",
    "sg:classifiers":[
        {
            "category":"Home & Garden",
            "subcategory":"Building Materials",
            "type":"Retail Goods"
        }
    ],
    "sg:phone":"+32 3 889 40 48",
    "sg:postcode":"2870",
    "sg:province":"Antwerpen",
    "sg:tags":[
        "veranda"
    ],
    "wof:name":"Daman Ramen",
    "wof:placetype":"venue"
},
  "geometry": {"coordinates":[4.3151421547,51.0820846558],"type":"Point"}
}