{
  "type": "Feature",
  "properties": {
    "iso:country":"BE",
    "sg:address":"D'overschielaan 11",
    "sg:city":"Grimbergen",
    "sg:classifiers":[
        {
            "category":"Health Services",
            "subcategory":"Doctor",
            "type":"Services"
        }
    ],
    "sg:phone":"+32 2 269 06 63",
    "sg:postcode":"1850",
    "sg:province":"Vlaams-Brabant",
    "sg:tags":[
        "medicinephysicians",
        "surgeon"
    ],
    "wof:name":"De Backer M",
    "wof:placetype":"venue"
},
  "geometry": {"coordinates":[4.3708257675,50.9386444092],"type":"Point"}
}