{
  "type": "Feature",
  "properties": {
    "iso:country":"BE",
    "sg:address":"Bommelstraat 56",
    "sg:city":"De Pinte",
    "sg:orig_category":"Elektrische installaties voor woningen",
    "sg:phone":"+32 9 282 71 64",
    "sg:postcode":"9840",
    "sg:province":"Oost-Vlaanderen",
    "wof:name":"Steven De Meulemeester",
    "wof:placetype":"venue"
},
  "geometry": {"coordinates":[3.6360490322,50.9900817871],"type":"Point"}
}