{
  "type": "Feature",
  "properties": {
    "iso:country":"BE",
    "sg:address":"Avenue Georges-truffaut 47",
    "sg:city":"Li\u00e8ge",
    "sg:classifiers":[
        {
            "category":"Home & Garden",
            "subcategory":"Building Materials",
            "type":"Retail Goods"
        }
    ],
    "sg:phone":"+32 4 362 42 61",
    "sg:postcode":"4020",
    "sg:province":"Li\u00e8ge",
    "sg:tags":[
        "cementing",
        "mortar"
    ],
    "wof:name":"Cloquette Etablissements S.p.r.l.",
    "wof:placetype":"venue"
},
  "geometry": {"coordinates":[5.6144499779,50.6504936218],"type":"Point"}
}