{
  "type": "Feature",
  "properties": {
    "addr:full":"Rue De Fosses 97 Aiseau-presles (presles) Hainaut 6250",
    "addr:housenumber":"97",
    "addr:postcode":"6250",
    "addr:street":"Rue De Fosses",
    "iso:country":"BE",
    "sg:address":"Rue De Fosses 97",
    "sg:city":"Aiseau-presles (presles)",
    "sg:classifiers":[
        {
            "category":"Home & Garden",
            "subcategory":"Building Materials",
            "type":"Retail Goods"
        }
    ],
    "sg:phone":"+32 71 38 35 11",
    "sg:postcode":"6250",
    "sg:province":"Hainaut",
    "sg:tags":[
        "-",
        "fireplace",
        "open",
        "ornamental"
    ],
    "wof:name":"Marbrerie Marpla",
    "wof:placetype":"venue"
},
  "geometry": {"coordinates":[4.5863847733,50.40990448],"type":"Point"}
}