{
  "type": "Feature",
  "properties": {
    "iso:country":"BE",
    "sg:address":"Stegerweg 60",
    "sg:city":"Opglabbeek",
    "sg:orig_category":"Sportclubs",
    "sg:phone":"+32 89 85 48 68",
    "sg:postcode":"3660",
    "sg:province":"Limburg",
    "wof:name":"W.s.v. De Boskabouters",
    "wof:placetype":"venue"
},
  "geometry": {"coordinates":[5.5782418251,51.0363883972],"type":"Point"}
}