{
  "type": "Feature",
  "properties": {
    "addr:full":"2235 Hulshout (groot) Antwerpen 2235",
    "addr:postcode":"2235;2235",
    "addr:street":"Groot Antwerpen",
    "iso:country":"BE",
    "sg:address":"2235",
    "sg:city":"Hulshout (groot)",
    "sg:orig_category":"Pharmaciens",
    "sg:phone":"+32 900 10 500",
    "sg:postcode":"2235",
    "sg:province":"Antwerpen",
    "wof:name":"Pharmacies De Garde",
    "wof:placetype":"venue"
},
  "geometry": {"coordinates":[4.8178200722,51.0582809448],"type":"Point"}
}