{
  "type": "Feature",
  "properties": {
    "addr:full":"Place De Bauffe 11 Lens Hainaut 7870",
    "addr:housenumber":"11",
    "addr:postcode":"7870",
    "addr:street":"Place De Bauffe",
    "iso:country":"BE",
    "sg:address":"Place De Bauffe 11",
    "sg:city":"Lens",
    "sg:orig_category":"Boucheries",
    "sg:phone":"+32 68 65 74 30",
    "sg:postcode":"7870",
    "sg:province":"Hainaut",
    "wof:name":"Francis Lartiller",
    "wof:placetype":"venue"
},
  "geometry": {"coordinates":[3.8544700146,50.5702438354],"type":"Point"}
}