{
  "type": "Feature",
  "properties": {
    "addr:full":"Nieuwpoortstraat 29 Lier Antwerpen 2500",
    "addr:housenumber":"29",
    "addr:postcode":"2500",
    "addr:street":"Nieuwpoortstraat",
    "iso:country":"BE",
    "sg:address":"Nieuwpoortstraat 29",
    "sg:city":"Lier",
    "sg:orig_category":"Elektrische installaties voor woningen",
    "sg:phone":"+32 3 480 42 41",
    "sg:postcode":"2500",
    "sg:province":"Antwerpen",
    "wof:name":"Bureau Van Damme",
    "wof:placetype":"venue"
},
  "geometry": {"coordinates":[4.5717058182,51.1418914795],"type":"Point"}
}