{
  "type": "Feature",
  "properties": {
    "addr:full":"Rue De La Poste 17 Arlon Luxembourg 6700",
    "addr:housenumber":"17",
    "addr:postcode":"6700",
    "addr:street":"Rue De La Poste",
    "iso:country":"BE",
    "sg:address":"Rue De La Poste 17",
    "sg:city":"Arlon",
    "sg:orig_category":"Non-Classified Establishments",
    "sg:phone":"+32 63 22 40 19",
    "sg:postcode":"6700",
    "sg:province":"Luxembourg",
    "wof:name":"Fach (chocolatier)",
    "wof:placetype":"venue"
},
  "geometry": {"coordinates":[5.8145189285,49.6827964783],"type":"Point"}
}