{
  "type": "Feature",
  "properties": {
    "addr:full":"Heerdweg 128 Deinze (meigem) Oost-Vlaanderen 9800",
    "addr:housenumber":"128",
    "addr:postcode":"9800",
    "addr:street":"Heerdweg",
    "iso:country":"BE",
    "sg:address":"Heerdweg 128",
    "sg:city":"Deinze (meigem)",
    "sg:classifiers":[
        {
            "category":"Home & Garden",
            "subcategory":"Carpets & Floor Coverings",
            "type":"Retail Goods"
        }
    ],
    "sg:phone":"+32 478 27 38 76",
    "sg:postcode":"9800",
    "sg:province":"Oost-Vlaanderen",
    "sg:tags":[
        "tile"
    ],
    "wof:name":"Provijn R",
    "wof:placetype":"venue"
},
  "geometry": {"coordinates":[3.5059649944,51.0162353516],"type":"Point"}
}