{
  "type": "Feature",
  "properties": {
    "addr:full":"Kloosterbosstraat 4a Nazareth Oost-Vlaanderen 9810",
    "addr:housenumber":"4a",
    "addr:postcode":"9810",
    "addr:street":"Kloosterbosstraat",
    "iso:country":"BE",
    "sg:address":"Kloosterbosstraat 4a",
    "sg:city":"Nazareth",
    "sg:orig_category":"Woningbouw",
    "sg:phone":"+32 9 386 75 04",
    "sg:postcode":"9810",
    "sg:province":"Oost-Vlaanderen",
    "wof:name":"Beils Gebrs",
    "wof:placetype":"venue"
},
  "geometry": {"coordinates":[3.563215971,50.9508094788],"type":"Point"}
}