{
  "type": "Feature",
  "properties": {
    "addr:full":"51 Bredabaan 2990 Wuustwezel 51",
    "addr:housenumber":"51;51",
    "addr:postcode":"2990",
    "addr:street":"Bredabaan",
    "iso:country":"BE",
    "sg:address":"51",
    "sg:city":"Bredabaan 2990 Wuustwezel",
    "sg:classifiers":[
        {
            "category":"Professional",
            "type":"Services"
        }
    ],
    "sg:phone":"+32 3 669 81 91",
    "sg:postcode":"51",
    "sg:tags":[
        "transport",
        "road"
    ],
    "wof:name":"Transport Geys Nv",
    "wof:placetype":"venue"
},
  "geometry": {"coordinates":[4.6183462143,51.4183311462],"type":"Point"}
}