{
  "type": "Feature",
  "properties": {
    "addr:full":"Bovenrij 16 Herentals Antwerpen 2200",
    "addr:housenumber":"16",
    "addr:postcode":"2200",
    "addr:street":"Bovenrij",
    "iso:country":"BE",
    "sg:address":"Bovenrij 16",
    "sg:city":"Herentals",
    "sg:orig_category":"Dameskledingzaken",
    "sg:phone":"+32 14 21 07 77",
    "sg:postcode":"2200",
    "sg:province":"Antwerpen",
    "wof:name":"Huis Carr\u00c9",
    "wof:placetype":"venue"
},
  "geometry": {"coordinates":[4.8379597664,51.1745986938],"type":"Point"}
}