{
  "type": "Feature",
  "properties": {
    "iso:country":"BE",
    "sg:address":"Avenue Joseph Chaudron 118",
    "sg:city":"Bruxelles (auderghem)",
    "sg:classifiers":[
        {
            "category":"Food & Beverages",
            "subcategory":"Supermarket",
            "type":"Retail Goods"
        }
    ],
    "sg:phone":"+32 2 672 88 52",
    "sg:postcode":"1160",
    "sg:province":"Bruxelles-Capitale",
    "sg:tags":[
        "frozen",
        "-"
    ],
    "wof:name":"Wanly Belgium",
    "wof:placetype":"venue"
},
  "geometry": {"coordinates":[4.4355611801,50.8106117249],"type":"Point"}
}