{
  "type": "Feature",
  "properties": {
    "iso:country":"BE",
    "sg:address":"Burkel 90",
    "sg:city":"Peer",
    "sg:orig_category":"Kapsalons",
    "sg:phone":"+32 11 63 18 64",
    "sg:postcode":"3990",
    "sg:province":"Limburg",
    "wof:name":"Liliane De Meersman",
    "wof:placetype":"venue"
},
  "geometry": {"coordinates":[5.4565711021,51.1212692261],"type":"Point"}
}