{
  "type": "Feature",
  "properties": {
    "addr:full":"Kardinaal Mercierstraat 53 Brugge West-Vlaanderen 8000",
    "addr:housenumber":"53",
    "addr:postcode":"8000",
    "addr:street":"Kardinaal Mercierstraat",
    "iso:country":"BE",
    "sg:address":"Kardinaal Mercierstraat 53",
    "sg:city":"Brugge",
    "sg:classifiers":[
        {
            "category":"Transit Center",
            "subcategory":"Freight",
            "type":"Transportation"
        }
    ],
    "sg:phone":"+32 50 33 49 38",
    "sg:postcode":"8000",
    "sg:province":"West-Vlaanderen",
    "sg:tags":[
        "import",
        "export",
        "-"
    ],
    "wof:name":"Beirens Handelsmaatschappij",
    "wof:placetype":"venue"
},
  "geometry": {"coordinates":[3.2159759998,51.218296051],"type":"Point"}
}