{
  "type": "Feature",
  "properties": {
    "addr:full":"Paardenmarkt 21 Antwerpen Antwerpen 2000",
    "addr:housenumber":"21",
    "addr:postcode":"2000",
    "addr:street":"Paardenmarkt",
    "iso:country":"BE",
    "sg:address":"Paardenmarkt 21",
    "sg:city":"Antwerpen",
    "sg:classifiers":[
        {
            "category":"Autos & Motor Vehicles",
            "subcategory":"Recreational Vehicle Sales",
            "type":"Retail Goods"
        }
    ],
    "sg:phone":"+32 3 233 14 86",
    "sg:postcode":"2000",
    "sg:province":"Antwerpen",
    "sg:tags":[
        "caravan",
        "accessory"
    ],
    "wof:name":"Van Laere R",
    "wof:placetype":"venue"
},
  "geometry": {"coordinates":[4.4082689285,51.2250976562],"type":"Point"}
}