{
  "type": "Feature",
  "properties": {
    "addr:full":"Brusselsesteenweg 455 Melle Oost-Vlaanderen 9090",
    "addr:housenumber":"455",
    "addr:postcode":"9090",
    "addr:street":"Brusselsesteenweg",
    "iso:country":"BE",
    "sg:address":"Brusselsesteenweg 455",
    "sg:city":"Melle",
    "sg:classifiers":[
        {
            "category":"Manufacturing",
            "subcategory":"Textiles",
            "type":"Manufacturing & Wholesale Goods"
        }
    ],
    "sg:phone":"+32 9 252 42 72",
    "sg:postcode":"9090",
    "sg:province":"Oost-Vlaanderen",
    "sg:tags":[
        "fab",
        "diver"
    ],
    "wof:name":"Calin",
    "wof:placetype":"venue"
},
  "geometry": {"coordinates":[3.808909893,50.9992332458],"type":"Point"}
}