{
  "type": "Feature",
  "properties": {
    "addr:full":"Eikenlei 51a Brecht (sint-job-in-'t Goor) Antwerpen 2960",
    "addr:housenumber":"51a",
    "addr:postcode":"2960",
    "addr:street":"Eikenlei;' T Goor",
    "iso:country":"BE",
    "sg:address":"Eikenlei 51a",
    "sg:city":"Brecht (sint-job-in-'t Goor)",
    "sg:classifiers":[
        {
            "category":"Shopping",
            "subcategory":"Used Merchandise",
            "type":"Retail Goods"
        }
    ],
    "sg:phone":"+32 3 633 36 74",
    "sg:postcode":"2960",
    "sg:province":"Antwerpen",
    "sg:tags":[
        "salvage",
        "surplus"
    ],
    "wof:name":"Van Cauwenberghe Bvba",
    "wof:placetype":"venue"
},
  "geometry": {"coordinates":[4.5637931824,51.3022346497],"type":"Point"}
}