{
  "type": "Feature",
  "properties": {
    "addr:full":"Rue De Wez 4 Incourt Brabant Wallon 1315",
    "addr:housenumber":"4",
    "addr:postcode":"1315",
    "addr:street":"Rue De Wez",
    "iso:country":"BE",
    "sg:address":"Rue De Wez 4",
    "sg:city":"Incourt",
    "sg:orig_category":"Eleveurs de bovins",
    "sg:phone":"+32 10 88 90 20",
    "sg:postcode":"1315",
    "sg:province":"Brabant Wallon",
    "wof:name":"Jean-joseph Rigo",
    "wof:placetype":"venue"
},
  "geometry": {"coordinates":[4.8065371513,50.6795921326],"type":"Point"}
}