{
  "type": "Feature",
  "properties": {
    "addr:full":"Badderijstraat 8 Hasselt Limburg 3500",
    "addr:housenumber":"8",
    "addr:postcode":"3500",
    "addr:street":"Badderijstraat",
    "iso:country":"BE",
    "sg:address":"Badderijstraat 8",
    "sg:city":"Hasselt",
    "sg:classifiers":[
        {
            "category":"Personal",
            "subcategory":"Beauty Salon",
            "type":"Services"
        }
    ],
    "sg:phone":"+32 11 22 31 49",
    "sg:postcode":"3500",
    "sg:province":"Limburg",
    "sg:tags":[
        "de",
        "coiffure"
    ],
    "wof:name":"Atelier 8",
    "wof:placetype":"venue"
},
  "geometry": {"coordinates":[5.3408827782,50.9316635132],"type":"Point"}
}