{
  "type": "Feature",
  "properties": {
    "iso:country":"BE",
    "sg:address":"De Gheeststraat 16",
    "sg:city":"Aalst",
    "sg:orig_category":"Imprimeries and copyshops",
    "sg:phone":"+32 53 71 07 21",
    "sg:postcode":"9300",
    "sg:province":"Oost-Vlaanderen",
    "wof:name":"Drukkerij De Kern",
    "wof:placetype":"venue"
},
  "geometry": {"coordinates":[4.0457239151,50.9342880249],"type":"Point"}
}