{
  "type": "Feature",
  "properties": {
    "addr:full":"Steenweg Op Mol 47 Turnhout Antwerpen 2300",
    "addr:housenumber":"47",
    "addr:postcode":"2300",
    "addr:street":"Steenweg Op Mol",
    "iso:country":"BE",
    "sg:address":"Steenweg Op Mol 47",
    "sg:city":"Turnhout",
    "sg:orig_category":"Drukkerijen and copyshops Secretariaatsdiensten",
    "sg:phone":"+32 14 41 16 46",
    "sg:postcode":"2300",
    "sg:province":"Antwerpen",
    "wof:name":"Drukkerij Matthys - Beccu",
    "wof:placetype":"venue"
},
  "geometry": {"coordinates":[4.9620800018,51.3214797974],"type":"Point"}
}