{
  "type": "Feature",
  "properties": {
    "addr:full":"Lodewijk De Raetlaan 56 Izegem West-Vlaanderen 8870",
    "addr:housenumber":"56",
    "addr:postcode":"8870",
    "addr:street":"Lodewijk De Raetlaan",
    "iso:country":"BE",
    "sg:address":"Lodewijk De Raetlaan 56",
    "sg:city":"Izegem",
    "sg:orig_category":"Dakwerken",
    "sg:phone":"+32 51 30 31 80",
    "sg:postcode":"8870",
    "sg:province":"West-Vlaanderen",
    "wof:name":"Soc Ver Dak",
    "wof:placetype":"venue"
},
  "geometry": {"coordinates":[3.1883759499,50.9308662415],"type":"Point"}
}