{
  "type": "Feature",
  "properties": {
    "addr:full":"2000 Antwerpen Antwerpen 2000",
    "addr:postcode":"2000;2000",
    "iso:country":"BE",
    "sg:address":"2000",
    "sg:city":"Antwerpen",
    "sg:orig_category":"Animations diverses",
    "sg:phone":"+32 476 67 64 33",
    "sg:postcode":"2000",
    "sg:province":"Antwerpen",
    "wof:name":"Dj Devanos",
    "wof:placetype":"venue"
},
  "geometry": {"coordinates":[4.3935499191,51.218788147],"type":"Point"}
}