{
  "type": "Feature",
  "properties": {
    "addr:full":"Rue Louis Albert 5 Namur (champion - Cognel\u00e9e) Namur 5020",
    "addr:housenumber":"5",
    "addr:postcode":"cognele\u0301e;5020",
    "addr:street":"Rue Louis Albert",
    "iso:country":"BE",
    "sg:address":"Rue Louis Albert 5",
    "sg:city":"Namur (champion - Cognel\u00e9e)",
    "sg:classifiers":[
        {
            "category":"Retail",
            "subcategory":"Auto Repair",
            "type":"Services"
        }
    ],
    "sg:phone":"+32 81 20 77 55",
    "sg:postcode":"5020",
    "sg:province":"Namur",
    "sg:tags":[
        "garage"
    ],
    "wof:name":"S A A B Namur",
    "wof:placetype":"venue"
},
  "geometry": {"coordinates":[4.7952418327,50.4352035522],"type":"Point"}
}