{
  "type": "Feature",
  "properties": {
    "iso:country":"BE",
    "sg:address":"Stijn Streuvelslaan 114",
    "sg:city":"Zemst",
    "sg:orig_category":"Artsen and specialisten",
    "sg:phone":"+32 15 61 06 00",
    "sg:postcode":"1980",
    "sg:province":"Vlaams-Brabant",
    "wof:name":"Gerda Adriaens",
    "wof:placetype":"venue"
},
  "geometry": {"coordinates":[4.4373598099,50.9709281921],"type":"Point"}
}