{
  "type": "Feature",
  "properties": {
    "addr:full":"Koning Albertstraat 6 Kortrijk West-Vlaanderen 8500",
    "addr:housenumber":"6",
    "addr:postcode":"8500",
    "addr:street":"Koning Albertstraat",
    "iso:country":"BE",
    "sg:address":"Koning Albertstraat 6",
    "sg:city":"Kortrijk",
    "sg:orig_category":"M\u00e9decins and sp\u00e9cialistes. Chaussures",
    "sg:phone":"+32 56 21 40 76",
    "sg:postcode":"8500",
    "sg:province":"West-Vlaanderen",
    "wof:name":"Eric Flo",
    "wof:placetype":"venue"
},
  "geometry": {"coordinates":[3.26375103,50.8253669739],"type":"Point"}
}