{
  "type": "Feature",
  "properties": {
    "addr:full":"Driebekenweg 4 (industrieter. Jagersborg 1308) Maaseik Limburg 3680",
    "addr:housenumber":"4;1308",
    "addr:postcode":"maaseik;3680",
    "addr:street":"Driebekenweg",
    "iso:country":"BE",
    "sg:address":"Driebekenweg 4 (industrieter. Jagersborg 1308)",
    "sg:city":"Maaseik",
    "sg:orig_category":"Plomberie, chauffage and installations sanitaires. Air conditionn\u00e9 and ventilation",
    "sg:phone":"+32 89 56 18 55",
    "sg:postcode":"3680",
    "sg:province":"Limburg",
    "wof:name":"V.s.a. Systems",
    "wof:placetype":"venue"
},
  "geometry": {"coordinates":[5.748939991,51.1036186218],"type":"Point"}
}