{
  "type": "Feature",
  "properties": {
    "addr:full":"Boulevard Georges Deryck 70 Tubize Brabant Wallon 1480",
    "addr:housenumber":"70",
    "addr:postcode":"1480",
    "addr:street":"Boulevard Georges Deryck;Wallon",
    "iso:country":"BE",
    "sg:address":"Boulevard Georges Deryck 70",
    "sg:city":"Tubize",
    "sg:classifiers":[
        {
            "category":"Arena",
            "subcategory":"Sports Club",
            "type":"Entertainment"
        }
    ],
    "sg:phone":"+32 2 355 96 12",
    "sg:postcode":"1480",
    "sg:province":"Brabant Wallon",
    "sg:tags":[
        "de"
    ],
    "wof:name":"Tubize B.c.",
    "wof:placetype":"venue"
},
  "geometry": {"coordinates":[4.2020640373,50.6934509277],"type":"Point"}
}