{
  "type": "Feature",
  "properties": {
    "iso:country":"BE",
    "sg:address":"37",
    "sg:city":"Rue Gotto-roiau 6900 Marche-en-famenne",
    "sg:classifiers":[
        {
            "category":"Professional",
            "subcategory":"Engineering",
            "type":"Services"
        }
    ],
    "sg:phone":"+32 84 31 26 67",
    "sg:postcode":"37",
    "sg:tags":[
        "machine",
        "-",
        "mechanical"
    ],
    "wof:name":"Pantarei Sa",
    "wof:placetype":"venue"
},
  "geometry": {"coordinates":[5.282189846,50.2252044678],"type":"Point"}
}