{
  "type": "Feature",
  "properties": {
    "iso:country":"BE",
    "sg:address":"Tabakstraat 13",
    "sg:city":"Deinze (wontergem)",
    "sg:classifiers":[
        {
            "category":"Building & Trades",
            "subcategory":"Landscaping Services",
            "type":"Services"
        }
    ],
    "sg:phone":"+32 51 63 60 77",
    "sg:postcode":"9800",
    "sg:province":"Oost-Vlaanderen",
    "sg:tags":[
        "slaughterer"
    ],
    "wof:name":"Deneve M",
    "wof:placetype":"venue"
},
  "geometry": {"coordinates":[3.443625927,50.9816970825],"type":"Point"}
}