{
  "type": "Feature",
  "properties": {
    "addr:full":"Albertlaan 178 Ninove Oost-Vlaanderen 9400",
    "addr:housenumber":"178",
    "addr:postcode":"9400",
    "addr:street":"Albertlaan",
    "iso:country":"BE",
    "sg:address":"Albertlaan 178",
    "sg:city":"Ninove",
    "sg:orig_category":"Epiceries",
    "sg:phone":"+32 54 33 85 02",
    "sg:postcode":"9400",
    "sg:province":"Oost-Vlaanderen",
    "wof:name":"Chris Goossens",
    "wof:placetype":"venue"
},
  "geometry": {"coordinates":[4.0147352219,50.8392868042],"type":"Point"}
}