{
  "type": "Feature",
  "properties": {
    "addr:full":"272 Oostendelaan 8430 Middelkerke 272",
    "addr:housenumber":"272",
    "addr:postcode":"8430;272",
    "addr:street":"Oostendelaan",
    "iso:country":"BE",
    "sg:address":"272",
    "sg:city":"Oostendelaan 8430 Middelkerke",
    "sg:classifiers":[
        {
            "category":"Farming",
            "subcategory":"Livestock Farm",
            "type":"Manufacturing & Wholesale Goods"
        }
    ],
    "sg:phone":"+32 59 31 15 15",
    "sg:postcode":"272",
    "sg:tags":[
        "breeding",
        "agriculture",
        "animal"
    ],
    "wof:name":"Depot Vanhoutte Nv",
    "wof:placetype":"venue"
},
  "geometry": {"coordinates":[2.8215179443,51.1853942871],"type":"Point"}
}