{
  "type": "Feature",
  "properties": {
    "iso:country":"BE",
    "sg:address":"Hoogstraat 1",
    "sg:city":"Hamme",
    "sg:classifiers":[
        {
            "category":"Professional",
            "subcategory":"Testing Lab",
            "type":"Services"
        }
    ],
    "sg:phone":"+32 52 47 74 47",
    "sg:postcode":"9220",
    "sg:province":"Oost-Vlaanderen",
    "sg:tags":[
        "chemist"
    ],
    "wof:name":"Wanzeele L",
    "wof:placetype":"venue"
},
  "geometry": {"coordinates":[4.1331548691,51.098285675],"type":"Point"}
}