{
  "type": "Feature",
  "properties": {
    "addr:full":"Rue Vanden Bossche 40 Evere Bruxelles-Capitale 1140",
    "addr:housenumber":"40",
    "addr:postcode":"1140",
    "addr:street":"Rue Vanden Bossche",
    "iso:country":"BE",
    "sg:address":"Rue Vanden Bossche 40",
    "sg:city":"Evere",
    "sg:orig_category":"Rev\u00eatements de sols and murs",
    "sg:phone":"+32 2 215 89 45",
    "sg:postcode":"1140",
    "sg:province":"Bruxelles-Capitale",
    "wof:name":"A.m. Parquets",
    "wof:placetype":"venue"
},
  "geometry": {"coordinates":[4.4015412331,50.8716621399],"type":"Point"}
}