{
  "type": "Feature",
  "properties": {
    "addr:full":"Schoonbeekstraat 43 Bilzen (beverst) Limburg 3740",
    "addr:housenumber":"43",
    "addr:postcode":"3740",
    "addr:street":"Schoonbeekstraat",
    "iso:country":"BE",
    "sg:address":"Schoonbeekstraat 43",
    "sg:city":"Bilzen (beverst)",
    "sg:classifiers":[
        {
            "category":"Health Services",
            "subcategory":"Doctor",
            "type":"Services"
        }
    ],
    "sg:phone":"+32 89 50 23 24",
    "sg:postcode":"3740",
    "sg:province":"Limburg",
    "sg:tags":[
        "medicinephysicians",
        "surgeon"
    ],
    "wof:name":"Ketelslegers Linda",
    "wof:placetype":"venue"
},
  "geometry": {"coordinates":[5.4722380638,50.9015388489],"type":"Point"}
}