{
  "type": "Feature",
  "properties": {
    "addr:full":"Zonnestraat 13-15 Lokeren Oost-Vlaanderen 9160",
    "addr:postcode":"13-15;9160",
    "addr:street":"Zonnestraat",
    "iso:country":"BE",
    "sg:address":"Zonnestraat 13-15",
    "sg:city":"Lokeren",
    "sg:classifiers":[
        {
            "category":"Structure",
            "subcategory":"Building",
            "type":"Public Place"
        }
    ],
    "sg:phone":"+32 9 349 18 44",
    "sg:postcode":"9160",
    "sg:province":"Oost-Vlaanderen",
    "sg:tags":[
        "door"
    ],
    "wof:name":"De Messemaeker A",
    "wof:placetype":"venue"
},
  "geometry": {"coordinates":[3.987210989,51.0937995911],"type":"Point"}
}