{
  "type": "Feature",
  "properties": {
    "addr:full":"Past. Van Kerckhovenwijk 33 Sint-amands Antwerpen 2890",
    "addr:housenumber":"33",
    "addr:postcode":"2890",
    "addr:street":"Past.;Kerckhovenwijk",
    "iso:country":"BE",
    "sg:address":"Past. Van Kerckhovenwijk 33",
    "sg:city":"Sint-amands",
    "sg:orig_category":"Travaux de pl\u00e2trage",
    "sg:phone":"+32 52 33 80 10",
    "sg:postcode":"2890",
    "sg:province":"Antwerpen",
    "wof:name":"Attila Rozsa",
    "wof:placetype":"venue"
},
  "geometry": {"coordinates":[4.2099747658,51.0564537048],"type":"Point"}
}