{
  "type": "Feature",
  "properties": {
    "iso:country":"BE",
    "sg:address":"Chauss\u00e9e De Tirlemont 97",
    "sg:city":"Wanze",
    "sg:classifiers":[
        {
            "category":"Home & Garden",
            "subcategory":"Building Materials",
            "type":"Retail Goods"
        }
    ],
    "sg:phone":"+32 85 23 48 54",
    "sg:postcode":"4520",
    "sg:province":"Li\u00e8ge",
    "sg:tags":[
        "article",
        "-",
        "do-it-yourself"
    ],
    "wof:name":"Bricomat",
    "wof:placetype":"venue"
},
  "geometry": {"coordinates":[5.2203631401,50.5384712219],"type":"Point"}
}