{
  "type": "Feature",
  "properties": {
    "addr:full":"Zoetewei 15 Putte Antwerpen 2580",
    "addr:housenumber":"15",
    "addr:postcode":"2580",
    "addr:street":"Zoetewei",
    "iso:country":"BE",
    "sg:address":"Zoetewei 15",
    "sg:city":"Putte",
    "sg:classifiers":[
        {
            "category":"Personal",
            "subcategory":"Beauty Salon",
            "type":"Services"
        }
    ],
    "sg:phone":"+32 15 75 34 96",
    "sg:postcode":"2580",
    "sg:province":"Antwerpen",
    "sg:tags":[
        "lady",
        "-",
        "hairdressing"
    ],
    "wof:name":"Carine",
    "wof:placetype":"venue"
},
  "geometry": {"coordinates":[4.6288099289,51.0548591614],"type":"Point"}
}