{
  "type": "Feature",
  "properties": {
    "addr:full":"Alhoumont 31 Houffalize Luxembourg 6662",
    "addr:housenumber":"31",
    "addr:postcode":"6662",
    "addr:street":"Alhoumont",
    "iso:country":"BE",
    "sg:address":"Alhoumont 31",
    "sg:city":"Houffalize",
    "sg:orig_category":"Charpentes and couvertures",
    "sg:phone":"+32 61 28 93 67",
    "sg:postcode":"6662",
    "sg:province":"Luxembourg",
    "wof:name":"Philippe Claude",
    "wof:placetype":"venue"
},
  "geometry": {"coordinates":[5.8163762093,50.1169700623],"type":"Point"}
}