{
  "type": "Feature",
  "properties": {
    "addr:full":"Buitenland 18 Bornem Antwerpen 2880",
    "addr:housenumber":"18",
    "addr:postcode":"2880",
    "addr:street":"Buitenland",
    "iso:country":"BE",
    "sg:address":"Buitenland 18",
    "sg:city":"Bornem",
    "sg:classifiers":[
        {
            "category":"Real Estate",
            "subcategory":"Architect",
            "type":"Services"
        }
    ],
    "sg:phone":"+32 3 899 21 09",
    "sg:postcode":"2880",
    "sg:province":"Antwerpen",
    "wof:name":"Mans I",
    "wof:placetype":"venue"
},
  "geometry": {"coordinates":[4.2221360207,51.1166763306],"type":"Point"}
}