{
  "type": "Feature",
  "properties": {
    "addr:full":"Schaaflaan 46 Zandhoven Antwerpen 2242",
    "addr:housenumber":"46",
    "addr:postcode":"2242",
    "addr:street":"Schaaflaan",
    "iso:country":"BE",
    "sg:address":"Schaaflaan 46",
    "sg:city":"Zandhoven",
    "sg:orig_category":"Articles m\u00e9dicaux and orthop\u00e9diques",
    "sg:phone":"+32 475 42 60 77",
    "sg:postcode":"2242",
    "sg:province":"Antwerpen",
    "wof:name":"De Landtsheer D.",
    "wof:placetype":"venue"
},
  "geometry": {"coordinates":[4.700802803,51.2196235657],"type":"Point"}
}