{
  "type": "Feature",
  "properties": {
    "addr:full":"Molendreef 23 Sint-niklaas Oost-Vlaanderen 9111",
    "addr:housenumber":"23",
    "addr:postcode":"9111",
    "addr:street":"Molendreef",
    "iso:country":"BE",
    "sg:address":"Molendreef 23",
    "sg:city":"Sint-niklaas",
    "sg:orig_category":"Installatie van houten of kunststof schrijnwerk",
    "sg:phone":"+32 3 772 28 55",
    "sg:postcode":"9111",
    "sg:province":"Oost-Vlaanderen",
    "wof:name":"Boudewijn Van Havere",
    "wof:placetype":"venue"
},
  "geometry": {"coordinates":[4.0933909416,51.1473007202],"type":"Point"}
}