{
  "type": "Feature",
  "properties": {
    "addr:full":"Smedenstr 32-34 Brugge West-Vlaanderen 8000",
    "addr:postcode":"32-34;8000",
    "iso:country":"BE",
    "sg:address":"Smedenstr 32-34",
    "sg:city":"Brugge",
    "sg:classifiers":[
        {
            "category":"Shopping",
            "subcategory":"Clothing, Apparel, & Fashions",
            "type":"Retail Goods"
        }
    ],
    "sg:phone":"+32 50 33 42 51",
    "sg:postcode":"8000",
    "sg:province":"West-Vlaanderen",
    "sg:tags":[
        "textile",
        "clothing",
        "clothes"
    ],
    "wof:name":"Noteboom Lederwarenhuis Nv",
    "wof:placetype":"venue"
},
  "geometry": {"coordinates":[3.2151679993,51.2055664062],"type":"Point"}
}