{
  "type": "Feature",
  "properties": {
    "addr:full":"Avenue Huart Hamoir 1 Box 3 Bruxelles (schaerbeek) Bruxelles-Capitale 1030",
    "addr:housenumber":"1;3",
    "addr:postcode":"1030",
    "addr:street":"Avenue Huart Hamoir;Box",
    "iso:country":"BE",
    "sg:address":"Avenue Huart Hamoir 1 Box 3",
    "sg:city":"Bruxelles (schaerbeek)",
    "sg:classifiers":[
        {
            "category":"Utilities",
            "subcategory":"Telephone",
            "type":"Services"
        }
    ],
    "sg:phone":"+32 2 640 78 72",
    "sg:postcode":"1030",
    "sg:province":"Bruxelles-Capitale",
    "sg:tags":[
        "-",
        "internet"
    ],
    "wof:name":"European Telematic System Sa",
    "wof:placetype":"venue"
},
  "geometry": {"coordinates":[4.3803710938,50.8772277832],"type":"Point"}
}