{
  "type": "Feature",
  "properties": {
    "addr:full":"Chasse De Saint-ghislain 34-36 Boussu Hainaut 7300",
    "addr:housenumber":"34-36",
    "addr:postcode":"7300",
    "iso:country":"BE",
    "sg:address":"Chasse De Saint-ghislain 34-36",
    "sg:city":"Boussu",
    "sg:classifiers":[
        {
            "category":"Professional",
            "subcategory":"Business Services",
            "type":"Services"
        }
    ],
    "sg:phone":"+32 65 65 92 48",
    "sg:postcode":"7300",
    "sg:province":"Hainaut",
    "sg:tags":[
        "automobile",
        "-",
        "assessor"
    ],
    "wof:name":"Granata A",
    "wof:placetype":"venue"
},
  "geometry": {"coordinates":[3.8019731045,50.4364013672],"type":"Point"}
}