{
  "type": "Feature",
  "properties": {
    "addr:full":"T Hofveld 6 Dilbeek Vlaams-Brabant 1702",
    "addr:housenumber":"6",
    "addr:postcode":"1702",
    "addr:street":"T Hofveld",
    "iso:country":"BE",
    "sg:address":"T Hofveld 6",
    "sg:city":"Dilbeek",
    "sg:classifiers":[
        {
            "category":"Banks & Credit Unions",
            "subcategory":"Financial Services",
            "type":"Services"
        }
    ],
    "sg:phone":"+32 2 774 98 11",
    "sg:postcode":"1702",
    "sg:province":"Vlaams-Brabant",
    "sg:tags":[
        "banking",
        "finance",
        "insurance"
    ],
    "wof:name":"Rahier Vanpoyer Lacroix Vanhoye Vancutsem & C Scrl",
    "wof:placetype":"venue"
},
  "geometry": {"coordinates":[4.4343948364,50.8568267822],"type":"Point"}
}