{
  "type": "Feature",
  "properties": {
    "addr:full":"Cl. Robinson 3 Vis\u00c9 Li\u00e8ge 4600",
    "addr:housenumber":"3",
    "addr:postcode":"4600",
    "addr:street":"Robinson",
    "iso:country":"BE",
    "sg:address":"Cl. Robinson 3",
    "sg:city":"Vis\u00c9",
    "sg:orig_category":"Traitements param\u00e9dicaux",
    "sg:phone":"+32 4 379 78 55",
    "sg:postcode":"4600",
    "sg:province":"Li\u00e8ge",
    "wof:name":"N. Spigarelli",
    "wof:placetype":"venue"
},
  "geometry": {"coordinates":[5.6839299202,50.7334365845],"type":"Point"}
}