{
  "type": "Feature",
  "properties": {
    "addr:full":"Modderstraat 8 Ninove Oost-Vlaanderen 9402",
    "addr:housenumber":"8",
    "addr:postcode":"9402",
    "addr:street":"Modderstraat",
    "iso:country":"BE",
    "sg:address":"Modderstraat 8",
    "sg:city":"Ninove",
    "sg:orig_category":"Sportclubs",
    "sg:phone":"+32 54 34 16 93",
    "sg:postcode":"9402",
    "sg:province":"Oost-Vlaanderen",
    "wof:name":"Flanders Motor Club",
    "wof:placetype":"venue"
},
  "geometry": {"coordinates":[4.0395750999,50.8249015808],"type":"Point"}
}