{
  "type": "Feature",
  "properties": {
    "iso:country":"BE",
    "sg:address":"Rue Brun 4",
    "sg:city":"Andenne",
    "sg:orig_category":"Maroquinerie and articles de voyage",
    "sg:phone":"+32 85 84 34 40",
    "sg:postcode":"5300",
    "sg:province":"Namur",
    "wof:name":"Les Ma\u00cetres Maroquiniers",
    "wof:placetype":"venue"
},
  "geometry": {"coordinates":[5.0974597931,50.4882888794],"type":"Point"}
}