{
  "type": "Feature",
  "properties": {
    "addr:full":"Rue De L'eglise 15 Habay (rulles) Luxembourg 6724",
    "addr:housenumber":"15",
    "addr:postcode":"6724",
    "addr:street":"Rue De L'Eglise",
    "iso:country":"BE",
    "sg:address":"Rue De L'eglise 15",
    "sg:city":"Habay (rulles)",
    "sg:classifiers":[
        {
            "category":"Shopping",
            "subcategory":"Optician",
            "type":"Retail Goods"
        }
    ],
    "sg:phone":"+32 63 41 18 68",
    "sg:postcode":"6724",
    "sg:province":"Luxembourg",
    "sg:tags":[
        "-"
    ],
    "wof:name":"Meert Optique",
    "wof:placetype":"venue"
},
  "geometry": {"coordinates":[5.5353169441,49.7250862122],"type":"Point"}
}