{
  "type": "Feature",
  "properties": {
    "addr:full":"Moeder Tiburcestraat 8 Ninove Oost-Vlaanderen 9400",
    "addr:housenumber":"8",
    "addr:postcode":"9400",
    "addr:street":"Tiburcestraat",
    "iso:country":"BE",
    "sg:address":"Moeder Tiburcestraat 8",
    "sg:city":"Ninove",
    "sg:orig_category":"HUISBRANDOLIE",
    "sg:phone":"+32 54 33 28 45",
    "sg:postcode":"9400",
    "sg:province":"Oost-Vlaanderen",
    "wof:name":"Ninove Branstoffencentrale",
    "wof:placetype":"venue"
},
  "geometry": {"coordinates":[4.0308890343,50.8385276794],"type":"Point"}
}