{
  "type": "Feature",
  "properties": {
    "addr:full":"Rue De Mons 17 Nivelles Brabant Wallon 1400",
    "addr:housenumber":"17",
    "addr:postcode":"1400",
    "addr:street":"Rue De Mons",
    "iso:country":"BE",
    "sg:address":"Rue De Mons 17",
    "sg:city":"Nivelles",
    "sg:classifiers":[
        {
            "category":"Personal",
            "subcategory":"Barber",
            "type":"Services"
        }
    ],
    "sg:phone":"+32 67 21 50 07",
    "sg:postcode":"1400",
    "sg:province":"Brabant Wallon",
    "sg:tags":[
        "gentleman",
        "salon",
        "-",
        "hairdressing"
    ],
    "wof:name":"Lory A",
    "wof:placetype":"venue"
},
  "geometry": {"coordinates":[4.3223881721,50.5963935852],"type":"Point"}
}