{
  "type": "Feature",
  "properties": {
    "addr:full":"Sint-katelijnestraat 87 Mechelen Antwerpen 2800",
    "addr:housenumber":"87",
    "addr:postcode":"2800",
    "addr:street":"Sint-Katelijnestraat",
    "iso:country":"BE",
    "sg:address":"Sint-katelijnestraat 87",
    "sg:city":"Mechelen",
    "sg:classifiers":[
        {
            "category":"Health Services",
            "subcategory":"Doctor",
            "type":"Services"
        }
    ],
    "sg:phone":"+32 15 20 92 35",
    "sg:postcode":"2800",
    "sg:province":"Antwerpen",
    "sg:tags":[
        "medicinephysicians",
        "surgeon"
    ],
    "wof:name":"Joos Karel",
    "wof:placetype":"venue"
},
  "geometry": {"coordinates":[4.4753990173,51.0321311951],"type":"Point"}
}