{
  "type": "Feature",
  "properties": {
    "addr:full":"Oorlogskruisenlaan 3 Brussel/bruxelles Bruxelles-Capitale 1120",
    "addr:housenumber":"3",
    "addr:postcode":"1120",
    "addr:street":"Oorlogskruisenlaan;/",
    "iso:country":"BE",
    "sg:address":"Oorlogskruisenlaan 3",
    "sg:city":"Brussel/bruxelles",
    "sg:orig_category":"Sportcentra",
    "sg:phone":"+32 2 216 02 37",
    "sg:postcode":"1120",
    "sg:province":"Bruxelles-Capitale",
    "wof:name":"Sportcentrum/centre Sportif",
    "wof:placetype":"venue"
},
  "geometry": {"coordinates":[4.3815197945,50.8900794983],"type":"Point"}
}