{
  "type": "Feature",
  "properties": {
    "iso:country":"BE",
    "sg:address":"Toeristenlaan 39",
    "sg:city":"Sint-pieters-woluwe/woluwe-saint-pierre",
    "sg:orig_category":"Advocaten and juridische adviseurs",
    "sg:phone":"+32 2 772 02 78",
    "sg:postcode":"1150",
    "sg:province":"Bruxelles-Capitale",
    "wof:name":"D. Dassonville",
    "wof:placetype":"venue"
},
  "geometry": {"coordinates":[4.45626688,50.837852478],"type":"Point"}
}