{
  "type": "Feature",
  "properties": {
    "addr:full":"Wittemoer 88 Evergem Oost-Vlaanderen 9940",
    "addr:housenumber":"88",
    "addr:postcode":"9940",
    "addr:street":"Wittemoer;Oost-Vlaanderen",
    "iso:country":"BE",
    "sg:address":"Wittemoer 88",
    "sg:city":"Evergem",
    "sg:orig_category":"Rundveehouders Varkenskwekers",
    "sg:phone":"+32 9 357 59 91",
    "sg:postcode":"9940",
    "sg:province":"Oost-Vlaanderen",
    "wof:name":"Antoine Temmerman",
    "wof:placetype":"venue"
},
  "geometry": {"coordinates":[3.6466720104,51.1622123718],"type":"Point"}
}