{
  "type": "Feature",
  "properties": {
    "addr:full":"Oudeleeuwenrui 7-11 Bus 7 Antwerpen Antwerpen 2000",
    "addr:housenumber":"7-11 bus 7",
    "addr:postcode":"2000",
    "addr:street":"Oudeleeuwenrui",
    "iso:country":"BE",
    "sg:address":"Oudeleeuwenrui 7-11 Bus 7",
    "sg:city":"Antwerpen",
    "sg:classifiers":[
        {
            "category":"Place Of Worship",
            "subcategory":"Church",
            "type":"Public Place"
        }
    ],
    "sg:phone":"+32 3 226 12 87",
    "sg:postcode":"2000",
    "sg:province":"Antwerpen",
    "sg:tags":[
        "restoration"
    ],
    "wof:name":"Ir-archi F.v.",
    "wof:placetype":"venue"
},
  "geometry": {"coordinates":[4.4058218002,51.227191925],"type":"Point"}
}