{
  "type": "Feature",
  "properties": {
    "addr:full":"Merksemsebaan 227 Wijnegem Antwerpen 2110",
    "addr:housenumber":"227",
    "addr:postcode":"2110",
    "addr:street":"Merksemsebaan",
    "iso:country":"BE",
    "sg:address":"Merksemsebaan 227",
    "sg:city":"Wijnegem",
    "sg:orig_category":"HERSTELLING ELEKTRISCHE HUISHOUDAPPARATEN Huishoudapparaten, televisies and radio's",
    "sg:phone":"+32 3 354 00 95",
    "sg:postcode":"2110",
    "sg:province":"Antwerpen",
    "wof:name":"Huis Carpentier",
    "wof:placetype":"venue"
},
  "geometry": {"coordinates":[4.5040597916,51.2310905457],"type":"Point"}
}