{
  "type": "Feature",
  "properties": {
    "addr:full":"Weverstraat 14 Boechout Antwerpen 2531",
    "addr:housenumber":"14",
    "addr:postcode":"2531",
    "addr:street":"Weverstraat",
    "iso:country":"BE",
    "sg:address":"Weverstraat 14",
    "sg:city":"Boechout",
    "sg:classifiers":[
        {
            "category":"Insurance",
            "subcategory":"Insurance Agent",
            "type":"Services"
        }
    ],
    "sg:phone":"+32 3 455 94 94",
    "sg:postcode":"2531",
    "sg:province":"Antwerpen",
    "sg:tags":[
        "verzekeringsmakelaars",
        "expert"
    ],
    "wof:name":"Keersmaekers",
    "wof:placetype":"venue"
},
  "geometry": {"coordinates":[4.5221099854,51.1758384705],"type":"Point"}
}