{
  "type": "Feature",
  "properties": {
    "addr:full":"Burgstraat 1 Brugge West-Vlaanderen 8000",
    "addr:housenumber":"1",
    "addr:postcode":"8000",
    "addr:street":"Burgstraat",
    "iso:country":"BE",
    "sg:address":"Burgstraat 1",
    "sg:city":"Brugge",
    "sg:classifiers":[
        {
            "category":"Restaurant",
            "type":"Food & Drink"
        }
    ],
    "sg:phone":"+32 50 67 87 07",
    "sg:postcode":"8000",
    "sg:province":"West-Vlaanderen",
    "wof:name":"Ter Burg",
    "wof:placetype":"venue"
},
  "geometry": {"coordinates":[3.2264149189,51.2094192505],"type":"Point"}
}