{
  "type": "Feature",
  "properties": {
    "addr:full":"Rue Charles Parent\u00e9 28b Bruxelles (anderlecht) Bruxelles-Capitale 1070",
    "addr:housenumber":"28b",
    "addr:postcode":"1070",
    "addr:street":"Rue Charles Parente\u0301",
    "iso:country":"BE",
    "sg:address":"Rue Charles Parent\u00e9 28b",
    "sg:city":"Bruxelles (anderlecht)",
    "sg:classifiers":[
        {
            "category":"Professional",
            "subcategory":"Computer Services",
            "type":"Services"
        }
    ],
    "sg:phone":"+32 2 558 30 00",
    "sg:postcode":"1070",
    "sg:province":"Bruxelles-Capitale",
    "sg:tags":[
        "-",
        "processing",
        "data"
    ],
    "wof:name":"Redcorp Sa",
    "wof:placetype":"venue"
},
  "geometry": {"coordinates":[4.330534935,50.8339691162],"type":"Point"}
}