{
  "type": "Feature",
  "properties": {
    "addr:full":"Rue Des Bouderets 16a Brunehaut (wez-velvain) Hainaut 7620",
    "addr:housenumber":"16a",
    "addr:postcode":"7620",
    "addr:street":"Rue Des Bouderets",
    "iso:country":"BE",
    "sg:address":"Rue Des Bouderets 16a",
    "sg:city":"Brunehaut (wez-velvain)",
    "sg:classifiers":[
        {
            "category":"Building & Trades",
            "subcategory":"Landscaping Services",
            "type":"Services"
        }
    ],
    "sg:phone":"+32 69 34 65 34",
    "sg:postcode":"7620",
    "sg:province":"Hainaut",
    "sg:tags":[
        "nurseryman"
    ],
    "wof:name":"Legrain O",
    "wof:placetype":"venue"
},
  "geometry": {"coordinates":[3.3866250515,50.5350799561],"type":"Point"}
}