{
  "type": "Feature",
  "properties": {
    "iso:country":"BE",
    "sg:address":"Verbindingsstraat 73b1",
    "sg:city":"Vilvoorde",
    "sg:orig_category":"Avocats and conseillers juridiques",
    "sg:phone":"+32 2 253 39 89",
    "sg:postcode":"1800",
    "sg:province":"Vlaams-Brabant",
    "wof:name":"A. Simoens",
    "wof:placetype":"venue"
},
  "geometry": {"coordinates":[4.4368357658,50.9408302307],"type":"Point"}
}