{
  "type": "Feature",
  "properties": {
    "addr:full":"Aldestraat 46 Hasselt Limburg 3500",
    "addr:housenumber":"46",
    "addr:postcode":"3500",
    "addr:street":"Aldestraat",
    "iso:country":"BE",
    "sg:address":"Aldestraat 46",
    "sg:city":"Hasselt",
    "sg:orig_category":"Location de v\u00eatements, chaussures and textiles",
    "sg:phone":"+32 11 22 74 15",
    "sg:postcode":"3500",
    "sg:province":"Limburg",
    "wof:name":"Tailors Smets",
    "wof:placetype":"venue"
},
  "geometry": {"coordinates":[5.3348650932,50.9304351807],"type":"Point"}
}