{
  "type": "Feature",
  "properties": {
    "addr:full":"Astenstraat 4 Zwevegem (heestert) West-Vlaanderen 8551",
    "addr:housenumber":"4",
    "addr:postcode":"8551",
    "addr:street":"Astenstraat",
    "iso:country":"BE",
    "sg:address":"Astenstraat 4",
    "sg:city":"Zwevegem (heestert)",
    "sg:classifiers":[
        {
            "category":"Building & Trades",
            "subcategory":"Construction",
            "type":"Services"
        }
    ],
    "sg:phone":"+32 56 77 14 54",
    "sg:postcode":"8551",
    "sg:province":"West-Vlaanderen",
    "sg:tags":[
        "tool",
        "cutting"
    ],
    "wof:name":"Benelux Saw Service",
    "wof:placetype":"venue"
},
  "geometry": {"coordinates":[3.4109840393,50.782283783],"type":"Point"}
}