{
  "type": "Feature",
  "properties": {
    "addr:full":"Steenweg Op Turnhout 105 Merksplas Antwerpen 2330",
    "addr:housenumber":"105",
    "addr:postcode":"2330",
    "addr:street":"Steenweg Op Turnhout",
    "iso:country":"BE",
    "sg:address":"Steenweg Op Turnhout 105",
    "sg:city":"Merksplas",
    "sg:orig_category":"Herstellingen and onderhoud aan huis voor voertuigen",
    "sg:phone":"+32 14 63 41 05",
    "sg:postcode":"2330",
    "sg:province":"Antwerpen",
    "wof:name":"L\u00c9opold Jacobs",
    "wof:placetype":"venue"
},
  "geometry": {"coordinates":[4.8740239143,51.3502616882],"type":"Point"}
}