{
  "type": "Feature",
  "properties": {
    "addr:full":"Groendreef 181 Gent Oost-Vlaanderen 9000",
    "addr:housenumber":"181",
    "addr:postcode":"9000",
    "addr:street":"Groendreef;Oost-Vlaanderen",
    "iso:country":"BE",
    "sg:address":"Groendreef 181",
    "sg:city":"Gent",
    "sg:classifiers":[
        {
            "category":"Government",
            "subcategory":"Police Station",
            "type":"Public Place"
        }
    ],
    "sg:phone":"+32 9 237 13 10",
    "sg:postcode":"9000",
    "sg:province":"Oost-Vlaanderen",
    "sg:tags":[
        "gendarmerie"
    ],
    "wof:name":"Federale Politie/police F\u00c9d\u00c9rale",
    "wof:placetype":"venue"
},
  "geometry": {"coordinates":[3.697259903,51.0673141479],"type":"Point"}
}