{
  "type": "Feature",
  "properties": {
    "iso:country":"BE",
    "sg:address":"Zultseweg 200",
    "sg:city":"Waregem",
    "sg:classifiers":[
        {
            "category":"Government",
            "subcategory":"Department Of Motor Vehicles",
            "type":"Public Place"
        }
    ],
    "sg:phone":"+32 56 62 00 31",
    "sg:postcode":"8790",
    "sg:province":"West-Vlaanderen",
    "sg:tags":[
        "equipment",
        "industrial",
        "transport",
        "motor-cars"
    ],
    "wof:name":"Galle Nv",
    "wof:placetype":"venue"
},
  "geometry": {"coordinates":[3.4446880817,50.9000244141],"type":"Point"}
}