{
  "type": "Feature",
  "properties": {
    "addr:full":"Brusselsesteenweg 708 Gentbrugge Oost-Vlaanderen 9050",
    "addr:housenumber":"708",
    "addr:postcode":"9050",
    "addr:street":"Brusselsesteenweg",
    "iso:country":"BE",
    "sg:address":"Brusselsesteenweg 708",
    "sg:city":"Gentbrugge",
    "sg:classifiers":[
        {
            "category":"Government",
            "subcategory":"Fire Station",
            "type":"Public Place"
        }
    ],
    "sg:phone":"+32 9 231 07 90",
    "sg:postcode":"9050",
    "sg:province":"Oost-Vlaanderen",
    "sg:tags":[
        "development",
        "hardware",
        "soft"
    ],
    "wof:name":"Dekimo Nv",
    "wof:placetype":"venue"
},
  "geometry": {"coordinates":[3.768955946,51.0273704529],"type":"Point"}
}