{
  "type": "Feature",
  "properties": {
    "addr:full":"Paul Hankarstraat 32 Ukkel/uccle Bruxelles-Capitale 1180",
    "addr:housenumber":"32",
    "addr:postcode":"1180",
    "addr:street":"Paul Hankarstraat;/",
    "iso:country":"BE",
    "sg:address":"Paul Hankarstraat 32",
    "sg:city":"Ukkel/uccle",
    "sg:orig_category":"Loodgieterij, verwarming and sanitaire installaties",
    "sg:phone":"+32 2 375 33 86",
    "sg:postcode":"1180",
    "sg:province":"Bruxelles-Capitale",
    "wof:name":"Siskovski Zoran",
    "wof:placetype":"venue"
},
  "geometry": {"coordinates":[4.3407077789,50.7985725403],"type":"Point"}
}