{
  "type": "Feature",
  "properties": {
    "addr:full":"Sint-martensstraat 16 Gent Oost-Vlaanderen 9000",
    "addr:housenumber":"16",
    "addr:postcode":"9000",
    "addr:street":"Sint-Martensstraat;Oost-Vlaanderen",
    "iso:country":"BE",
    "sg:address":"Sint-martensstraat 16",
    "sg:city":"Gent",
    "sg:orig_category":"Avocats and conseillers juridiques",
    "sg:phone":"+32 9 223 04 41",
    "sg:postcode":"9000",
    "sg:province":"Oost-Vlaanderen",
    "wof:name":"Sara Torrekens",
    "wof:placetype":"venue"
},
  "geometry": {"coordinates":[3.7182500362,51.0505905151],"type":"Point"}
}