{
  "type": "Feature",
  "properties": {
    "addr:full":"Rue Des Trois Piliers 116 Namur (saint-servais) Namur 5002",
    "addr:housenumber":"116",
    "addr:postcode":"5002",
    "addr:street":"Rue Des Trois Piliers",
    "iso:country":"BE",
    "sg:address":"Rue Des Trois Piliers 116",
    "sg:city":"Namur (saint-servais)",
    "sg:classifiers":[
        {
            "category":"Home & Garden",
            "subcategory":"Kitchen Supply",
            "type":"Retail Goods"
        }
    ],
    "sg:phone":"+32 81 73 37 44",
    "sg:postcode":"5002",
    "sg:province":"Namur",
    "sg:tags":[
        "installation"
    ],
    "wof:name":"Hanse & Fils",
    "wof:placetype":"venue"
},
  "geometry": {"coordinates":[4.8462319374,50.4782791138],"type":"Point"}
}