{
  "type": "Feature",
  "properties": {
    "addr:full":"Achtelsestraat 25 Hoogstraten Antwerpen 2320",
    "addr:housenumber":"25",
    "addr:postcode":"2320",
    "addr:street":"Achtelsestraat",
    "iso:country":"BE",
    "sg:address":"Achtelsestraat 25",
    "sg:city":"Hoogstraten",
    "sg:classifiers":[
        {
            "category":"Taxi",
            "type":"Transportation"
        }
    ],
    "sg:phone":"+32 3 314 69 30",
    "sg:postcode":"2320",
    "sg:province":"Antwerpen",
    "sg:tags":[
        "taxicab"
    ],
    "wof:name":"Taxi Hoogstraten",
    "wof:placetype":"venue"
},
  "geometry": {"coordinates":[4.7618350983,51.3969268799],"type":"Point"}
}