{
  "type": "Feature",
  "properties": {
    "addr:full":"Bosstraat 39 Westerlo Antwerpen 2260",
    "addr:housenumber":"39",
    "addr:postcode":"2260",
    "addr:street":"Bosstraat",
    "iso:country":"BE",
    "sg:address":"Bosstraat 39",
    "sg:city":"Westerlo",
    "sg:orig_category":"Rundveehouders",
    "sg:phone":"+32 14 23 41 07",
    "sg:postcode":"2260",
    "sg:province":"Antwerpen",
    "wof:name":"Paul Dierickx",
    "wof:placetype":"venue"
},
  "geometry": {"coordinates":[4.9025650024,51.1187210083],"type":"Point"}
}