{
  "type": "Feature",
  "properties": {
    "iso:country":"BE",
    "sg:address":"Kerkstraat 37",
    "sg:city":"Sint-gillis-waas",
    "sg:classifiers":[
        {
            "category":"Food & Beverages",
            "subcategory":"Fruits & Vegetables",
            "type":"Retail Goods"
        }
    ],
    "sg:phone":"+32 3 727 01 54",
    "sg:postcode":"9170",
    "sg:province":"Oost-Vlaanderen",
    "sg:tags":[
        "l\u00e9gumes",
        "gr"
    ],
    "wof:name":"Fa. Haegro-fruit",
    "wof:placetype":"venue"
},
  "geometry": {"coordinates":[4.1289248466,51.217124939],"type":"Point"}
}