{
  "type": "Feature",
  "properties": {
    "addr:full":"Avenue Adolphe Lacombl\u00e9 29-31 Bruxelles (schaerbeek) Bruxelles-Capitale 1030",
    "addr:housenumber":"29-31",
    "addr:postcode":"1030",
    "addr:street":"Avenue Adolphe Lacomble\u0301",
    "iso:country":"BE",
    "sg:address":"Avenue Adolphe Lacombl\u00e9 29-31",
    "sg:city":"Bruxelles (schaerbeek)",
    "sg:classifiers":[
        {
            "category":"Professional",
            "subcategory":"Management & Consulting",
            "type":"Services"
        }
    ],
    "sg:phone":"+32 2 743 83 83",
    "sg:postcode":"1030",
    "sg:province":"Bruxelles-Capitale",
    "sg:tags":[
        "consultant",
        "-",
        "legislation",
        "social"
    ],
    "wof:name":"Ucm",
    "wof:placetype":"venue"
},
  "geometry": {"coordinates":[4.4000310898,50.8493423462],"type":"Point"}
}