{
  "type": "Feature",
  "properties": {
    "iso:country":"BE",
    "sg:address":"Pachecolaan 44",
    "sg:city":"Bruxelles",
    "sg:classifiers":[
        {
            "category":"Banks & Credit Unions",
            "subcategory":"Bank",
            "type":"Services"
        }
    ],
    "sg:phone":"+32 2 222 11 11",
    "sg:postcode":"1000",
    "sg:province":"Bruxelles-Capitale",
    "wof:name":"Cr\u00e9dit Communal Sa",
    "wof:placetype":"venue"
},
  "geometry": {"coordinates":[4.3626542091,50.8531723022],"type":"Point"}
}