{
  "type": "Feature",
  "properties": {
    "iso:country":"BE",
    "sg:address":"Rue Du Onze Novembre 24",
    "sg:city":"Mons",
    "sg:orig_category":"Enseignement sup\u00e9rieur",
    "sg:phone":"+32 65 35 55 03",
    "sg:postcode":"7000",
    "sg:province":"Hainaut",
    "wof:name":"Inst.ens.sup.p\u00c9dagogique",
    "wof:placetype":"venue"
},
  "geometry": {"coordinates":[3.9520089626,50.4567184448],"type":"Point"}
}