{
  "type": "Feature",
  "properties": {
    "addr:full":"Rue De M\u00e9rode 118 Bruxelles (saint-gilles) Bruxelles-Capitale 1060",
    "addr:housenumber":"118",
    "addr:postcode":"1060",
    "addr:street":"Rue De Me\u0301Rode",
    "iso:country":"BE",
    "sg:address":"Rue De M\u00e9rode 118",
    "sg:city":"Bruxelles (saint-gilles)",
    "sg:classifiers":[
        {
            "category":"Building & Trades",
            "subcategory":"Construction",
            "type":"Services"
        }
    ],
    "sg:phone":"+32 2 534 41 80",
    "sg:postcode":"1060",
    "sg:province":"Bruxelles-Capitale",
    "sg:tags":[
        "installation",
        "-",
        "central",
        "heating"
    ],
    "wof:name":"Sanilook",
    "wof:placetype":"venue"
},
  "geometry": {"coordinates":[4.3369569778,50.8331108093],"type":"Point"}
}