{
  "type": "Feature",
  "properties": {
    "iso:country":"BE",
    "sg:address":"Meensesteenweg 233",
    "sg:city":"Roeselare",
    "sg:classifiers":[
        {
            "category":"Wholesale",
            "subcategory":"Vending Machines",
            "type":"Manufacturing & Wholesale Goods"
        }
    ],
    "sg:phone":"+32 51 27 28 29",
    "sg:postcode":"8800",
    "sg:province":"West-Vlaanderen",
    "sg:tags":[
        "document",
        "destruction"
    ],
    "wof:name":"A. Duyvejonck-belaen",
    "wof:placetype":"venue"
},
  "geometry": {"coordinates":[3.1207470894,50.934223175],"type":"Point"}
}