{
  "type": "Feature",
  "properties": {
    "iso:country":"BE",
    "sg:address":"Beulkensstraat 15",
    "sg:city":"Tremelo (baal)",
    "sg:classifiers":[
        {
            "category":"Home & Garden",
            "subcategory":"Building Materials",
            "type":"Retail Goods"
        }
    ],
    "sg:phone":"+32 16 53 27 80",
    "sg:postcode":"3128",
    "sg:province":"Vlaams-Brabant",
    "sg:tags":[
        "veranda"
    ],
    "wof:name":"Claes Marcel & Zn Nv",
    "wof:placetype":"venue"
},
  "geometry": {"coordinates":[4.7539200783,50.9992027283],"type":"Point"}
}