{
  "type": "Feature",
  "properties": {
    "iso:country":"BE",
    "sg:address":"Kaai 869 130",
    "sg:city":"Antwerpen",
    "sg:classifiers":[
        {
            "category":"Manufacturing",
            "subcategory":"Building Materials",
            "type":"Manufacturing & Wholesale Goods"
        }
    ],
    "sg:phone":"+32 3 541 29 74",
    "sg:postcode":"2030",
    "sg:province":"Antwerpen",
    "sg:tags":[
        "cement"
    ],
    "wof:name":"Obourg Cement",
    "wof:placetype":"venue"
},
  "geometry": {"coordinates":[4.3637099266,51.2742385864],"type":"Point"}
}