{
  "type": "Feature",
  "properties": {
    "addr:full":"Hazelaarstraat 8 Kortrijk West-Vlaanderen 8500",
    "addr:housenumber":"8",
    "addr:postcode":"8500",
    "addr:street":"Hazelaarstraat",
    "iso:country":"BE",
    "sg:address":"Hazelaarstraat 8",
    "sg:city":"Kortrijk",
    "sg:classifiers":[
        {
            "category":"Building & Trades",
            "subcategory":"Landscaping Services",
            "type":"Services"
        }
    ],
    "sg:phone":"+32 56 22 20 69",
    "sg:postcode":"8500",
    "sg:province":"West-Vlaanderen",
    "sg:tags":[
        "gardening",
        "garden",
        "maintenance"
    ],
    "wof:name":"Desimpel V",
    "wof:placetype":"venue"
},
  "geometry": {"coordinates":[3.2652869225,50.8260688782],"type":"Point"}
}