{
  "type": "Feature",
  "properties": {
    "iso:country":"BE",
    "sg:address":"Kluizerdijk 162",
    "sg:city":"Hamont-achel",
    "sg:classifiers":[
        {
            "category":"Autos & Motor Vehicles",
            "subcategory":"Fuel & Gas Station",
            "type":"Retail Goods"
        }
    ],
    "sg:phone":"+32 11 66 11 57",
    "sg:postcode":"3930",
    "sg:province":"Limburg",
    "sg:tags":[
        "stations-service",
        "carburants"
    ],
    "wof:name":"W. Van Den Dungen",
    "wof:placetype":"venue"
},
  "geometry": {"coordinates":[5.4807248116,51.2905693054],"type":"Point"}
}