{
  "type": "Feature",
  "properties": {
    "addr:full":"Rootenstraat 13 Box 2 Genk Limburg 3600",
    "addr:housenumber":"13;2",
    "addr:postcode":"3600",
    "addr:street":"Rootenstraat;Box",
    "iso:country":"BE",
    "sg:address":"Rootenstraat 13 Box 2",
    "sg:city":"Genk",
    "sg:classifiers":[
        {
            "category":"Banks & Credit Unions",
            "subcategory":"Investment Brokerage",
            "type":"Services"
        }
    ],
    "sg:phone":"+32 89 35 09 42",
    "sg:postcode":"3600",
    "sg:province":"Limburg",
    "sg:tags":[
        "jean",
        "casual",
        "wear"
    ],
    "wof:name":"Team Spirit Bvba",
    "wof:placetype":"venue"
},
  "geometry": {"coordinates":[5.5028338432,50.9652481079],"type":"Point"}
}