{
  "type": "Feature",
  "properties": {
    "iso:country":"BE",
    "sg:address":"Mopertingenstraat 47",
    "sg:city":"Bilzen",
    "sg:classifiers":[
        {
            "category":"Arena",
            "subcategory":"Sports Club",
            "type":"Entertainment"
        }
    ],
    "sg:phone":"+32 11 41 43 00",
    "sg:postcode":"3740",
    "sg:province":"Limburg",
    "sg:tags":[
        "terrain",
        "hors",
        "de",
        "installation",
        "sportifs"
    ],
    "wof:name":"G.s. Mopertingen",
    "wof:placetype":"venue"
},
  "geometry": {"coordinates":[5.5773501396,50.8656959534],"type":"Point"}
}