{
  "type": "Feature",
  "properties": {
    "addr:full":"Place Xavier-neujean 1 Li\u00e8ge 1 Li\u00e8ge 4000",
    "addr:housenumber":"1;1",
    "addr:postcode":"4000",
    "addr:street":"Place Xavier-Neujean",
    "iso:country":"BE",
    "sg:address":"Place Xavier-neujean 1",
    "sg:city":"Li\u00e8ge 1",
    "sg:classifiers":[
        {
            "category":"Banks & Credit Unions",
            "subcategory":"Financial Services",
            "type":"Services"
        }
    ],
    "sg:phone":"+32 4 222 07 37",
    "sg:postcode":"4000",
    "sg:province":"Li\u00e8ge",
    "sg:tags":[
        "financing"
    ],
    "wof:name":"Adea Sa",
    "wof:placetype":"venue"
},
  "geometry": {"coordinates":[5.5694031715,50.6432495117],"type":"Point"}
}