{
  "type": "Feature",
  "properties": {
    "iso:country":"BE",
    "sg:address":"Parklaan 18",
    "sg:city":"Oostende",
    "sg:orig_category":"Dierenartsen",
    "sg:phone":"+32 59 50 94 53",
    "sg:postcode":"8400",
    "sg:province":"West-Vlaanderen",
    "wof:name":"Francis Burrick",
    "wof:placetype":"venue"
},
  "geometry": {"coordinates":[2.9160249233,51.2161750793],"type":"Point"}
}