{
  "type": "Feature",
  "properties": {
    "addr:full":"Albert Meuricestraat 5 Etterbeek/etterbeek Bruxelles-Capitale 1040",
    "addr:housenumber":"5",
    "addr:postcode":"1040",
    "addr:street":"Albert Meuricestraat",
    "iso:country":"BE",
    "sg:address":"Albert Meuricestraat 5",
    "sg:city":"Etterbeek/etterbeek",
    "sg:orig_category":"Verlichting and huishoudartikelen",
    "sg:phone":"+32 2 733 78 05",
    "sg:postcode":"1040",
    "sg:province":"Bruxelles-Capitale",
    "wof:name":"Brussels Decor",
    "wof:placetype":"venue"
},
  "geometry": {"coordinates":[4.3888449669,50.836643219],"type":"Point"}
}