{
  "type": "Feature",
  "properties": {
    "iso:country":"BE",
    "sg:address":"Nekkersput 11",
    "sg:city":"Ninove (pollare)",
    "sg:classifiers":[
        {
            "category":"Structure",
            "subcategory":"Office Building",
            "type":"Public Place"
        }
    ],
    "sg:phone":"+32 54 33 11 08",
    "sg:postcode":"9401",
    "sg:province":"Oost-Vlaanderen",
    "sg:tags":[
        "drawing"
    ],
    "wof:name":"Van Londersele P",
    "wof:placetype":"venue"
},
  "geometry": {"coordinates":[4.0013818741,50.819984436],"type":"Point"}
}