{
  "type": "Feature",
  "properties": {
    "iso:country":"BE",
    "sg:address":"Rue Cyclistes Fronti\u00c8re 24",
    "sg:city":"Vis\u00c9",
    "sg:orig_category":"Activit\u00e9s diverses d'imprimerie",
    "sg:phone":"+32 4 374 00 66",
    "sg:postcode":"4600",
    "sg:province":"Li\u00e8ge",
    "wof:name":"J.c.p. Design Studio",
    "wof:placetype":"venue"
},
  "geometry": {"coordinates":[5.7067060471,50.74609375],"type":"Point"}
}