{
  "type": "Feature",
  "properties": {
    "iso:country":"BE",
    "sg:address":"Rue Du Champ Du Loup 40",
    "sg:city":"Lobbes",
    "sg:classifiers":[
        {
            "category":"Health Services",
            "subcategory":"Health Practitioner",
            "type":"Services"
        }
    ],
    "sg:phone":"+32 71 59 13 78",
    "sg:postcode":"6540",
    "sg:province":"Hainaut",
    "sg:tags":[
        "physiotherapist"
    ],
    "wof:name":"Colin B",
    "wof:placetype":"venue"
},
  "geometry": {"coordinates":[4.279706955,50.3563308716],"type":"Point"}
}