{
  "type": "Feature",
  "properties": {
    "iso:country":"BE",
    "sg:address":"Graanmarkt 12",
    "sg:city":"Ninove",
    "sg:classifiers":[
        {
            "category":"Social Services",
            "type":"Services"
        }
    ],
    "sg:phone":"+32 54 34 10 01",
    "sg:postcode":"9400",
    "sg:province":"Oost-Vlaanderen",
    "wof:name":"Cultureel Centrum De Plomblom",
    "wof:placetype":"venue"
},
  "geometry": {"coordinates":[4.0240731239,50.8355178833],"type":"Point"}
}