{
  "type": "Feature",
  "properties": {
    "addr:full":"Dorpsstraat 79 Nieuwerkerken Limburg 3850",
    "addr:housenumber":"79",
    "addr:postcode":"3850",
    "addr:street":"Dorpsstraat",
    "iso:country":"BE",
    "sg:address":"Dorpsstraat 79",
    "sg:city":"Nieuwerkerken",
    "sg:orig_category":"Producteurs de fruits",
    "sg:phone":"+32 11 31 24 13",
    "sg:postcode":"3850",
    "sg:province":"Limburg",
    "wof:name":"Joseph Jeuris",
    "wof:placetype":"venue"
},
  "geometry": {"coordinates":[5.2440638542,50.8779983521],"type":"Point"}
}