{
  "type": "Feature",
  "properties": {
    "addr:full":"Meensesteenweg 290 Kortrijk (bissegem) West-Vlaanderen 8501",
    "addr:housenumber":"290",
    "addr:postcode":"8501",
    "addr:street":"Meensesteenweg",
    "iso:country":"BE",
    "sg:address":"Meensesteenweg 290",
    "sg:city":"Kortrijk (bissegem)",
    "sg:classifiers":[
        {
            "category":"Bars & Pubs",
            "type":"Food & Drink"
        }
    ],
    "sg:phone":"+32 56 36 06 64",
    "sg:postcode":"8501",
    "sg:province":"West-Vlaanderen",
    "wof:name":"Crazy-love (le)",
    "wof:placetype":"venue"
},
  "geometry": {"coordinates":[3.2293379307,50.824344635],"type":"Point"}
}