{
  "type": "Feature",
  "properties": {
    "addr:full":"Aardseweg 159 Geel Antwerpen 2440",
    "addr:housenumber":"159",
    "addr:postcode":"2440",
    "addr:street":"Aardseweg",
    "iso:country":"BE",
    "sg:address":"Aardseweg 159",
    "sg:city":"Geel",
    "sg:classifiers":[
        {
            "category":"Building & Trades",
            "subcategory":"Construction",
            "type":"Services"
        }
    ],
    "sg:phone":"+32 14 85 27 14",
    "sg:postcode":"2440",
    "sg:province":"Antwerpen",
    "sg:tags":[
        "carpenter"
    ],
    "wof:name":"P & L Dakwerken Bvba",
    "wof:placetype":"venue"
},
  "geometry": {"coordinates":[5.0070700645,51.2123603821],"type":"Point"}
}