{
  "type": "Feature",
  "properties": {
    "iso:country":"BE",
    "sg:address":"Avenue Edmond Parmentier 19",
    "sg:city":"Bruxelles (woluwe-saint-pierre)",
    "sg:classifiers":[
        {
            "category":"Travel",
            "subcategory":"Resort",
            "type":"Entertainment"
        }
    ],
    "sg:phone":"+32 2 770 22 95",
    "sg:postcode":"1150",
    "sg:province":"Bruxelles-Capitale",
    "sg:tags":[
        "vacation"
    ],
    "wof:name":"Parc Parmentier",
    "wof:placetype":"venue"
},
  "geometry": {"coordinates":[4.43775177,50.8312339783],"type":"Point"}
}