{
  "type": "Feature",
  "properties": {
    "addr:full":"Eggenpad 3 Vilvoorde Vlaams-Brabant 1800",
    "addr:housenumber":"3",
    "addr:postcode":"1800",
    "addr:street":"Eggenpad",
    "iso:country":"BE",
    "sg:address":"Eggenpad 3",
    "sg:city":"Vilvoorde",
    "sg:classifiers":[
        {
            "category":"Health Services",
            "subcategory":"Dentist",
            "type":"Services"
        }
    ],
    "sg:phone":"+32 2 251 32 06",
    "sg:postcode":"1800",
    "sg:province":"Vlaams-Brabant",
    "wof:name":"Soetanto B",
    "wof:placetype":"venue"
},
  "geometry": {"coordinates":[4.4693341255,50.9469223022],"type":"Point"}
}