{
  "type": "Feature",
  "properties": {
    "addr:full":"Mechelsesteenweg 389a Herent Vlaams-Brabant 3020",
    "addr:housenumber":"389a",
    "addr:postcode":"3020",
    "addr:street":"Mechelsesteenweg",
    "iso:country":"BE",
    "sg:address":"Mechelsesteenweg 389a",
    "sg:city":"Herent",
    "sg:classifiers":[
        {
            "category":"Insurance",
            "subcategory":"Insurance Agent",
            "type":"Services"
        }
    ],
    "sg:phone":"+32 16 29 01 91",
    "sg:postcode":"3020",
    "sg:province":"Vlaams-Brabant",
    "sg:tags":[
        "broker"
    ],
    "wof:name":"Beersaerts Verzekeringkantoor",
    "wof:placetype":"venue"
},
  "geometry": {"coordinates":[4.6726841927,50.9047431946],"type":"Point"}
}