{
  "type": "Feature",
  "properties": {
    "iso:country":"BE",
    "sg:address":"Domien Ingelsstraat 4-6",
    "sg:city":"Gent (drongen)",
    "sg:classifiers":[
        {
            "category":"Shopping",
            "subcategory":"Shoes",
            "type":"Retail Goods"
        }
    ],
    "sg:phone":"+32 9 226 45 77",
    "sg:postcode":"9031",
    "sg:province":"Oost-Vlaanderen",
    "sg:tags":[
        "slipper",
        "-"
    ],
    "wof:name":"Vera Shoe",
    "wof:placetype":"venue"
},
  "geometry": {"coordinates":[3.6643929482,51.0506973267],"type":"Point"}
}