{
  "type": "Feature",
  "properties": {
    "addr:full":"Chauss\u00c9e De Ghislenghien 4 Silly Hainaut 7830",
    "addr:housenumber":"4",
    "addr:postcode":"7830",
    "addr:street":"Chausse\u0301E De Ghislenghien",
    "iso:country":"BE",
    "sg:address":"Chauss\u00c9e De Ghislenghien 4",
    "sg:city":"Silly",
    "sg:orig_category":"Eleveurs de bovins",
    "sg:phone":"+32 68 55 16 79",
    "sg:postcode":"7830",
    "sg:province":"Hainaut",
    "wof:name":"Elevage Parent",
    "wof:placetype":"venue"
},
  "geometry": {"coordinates":[3.9160089493,50.6423873901],"type":"Point"}
}