{
  "type": "Feature",
  "properties": {
    "addr:full":"Europaweg 293 Zottegem (grotenberge) Oost-Vlaanderen 9620",
    "addr:housenumber":"293",
    "addr:postcode":"9620",
    "addr:street":"Europaweg",
    "iso:country":"BE",
    "sg:address":"Europaweg 293",
    "sg:city":"Zottegem (grotenberge)",
    "sg:classifiers":[
        {
            "category":"Personal",
            "subcategory":"Barber",
            "type":"Services"
        }
    ],
    "sg:phone":"+32 9 360 08 76",
    "sg:postcode":"9620",
    "sg:province":"Oost-Vlaanderen",
    "sg:tags":[
        "gentleman",
        "salon",
        "-",
        "hairdressing"
    ],
    "wof:name":"Yvan Haute-coiffure",
    "wof:placetype":"venue"
},
  "geometry": {"coordinates":[3.8112111092,50.871181488],"type":"Point"}
}