{
  "type": "Feature",
  "properties": {
    "iso:country":"BE",
    "sg:address":"Rue Reynier 3",
    "sg:city":"Li\u00e8ge 1",
    "sg:classifiers":[
        {
            "category":"Health Services",
            "subcategory":"Health Practitioner",
            "type":"Services"
        }
    ],
    "sg:phone":"+32 4 222 24 30",
    "sg:postcode":"4000",
    "sg:province":"Li\u00e8ge",
    "sg:tags":[
        "physiotherapist"
    ],
    "wof:name":"Thiry M",
    "wof:placetype":"venue"
},
  "geometry": {"coordinates":[5.5613069534,50.6373291016],"type":"Point"}
}