{
  "type": "Feature",
  "properties": {
    "iso:country":"BE",
    "sg:address":"Rue Du Bru 132",
    "sg:city":"Etalle (vance)",
    "sg:classifiers":[
        {
            "category":"Manufacturing",
            "subcategory":"Metals",
            "type":"Manufacturing & Wholesale Goods"
        }
    ],
    "sg:phone":"+32 63 45 57 97",
    "sg:postcode":"6741",
    "sg:province":"Luxembourg",
    "sg:tags":[
        "non-ferrous",
        "-"
    ],
    "wof:name":"Devillet D",
    "wof:placetype":"venue"
},
  "geometry": {"coordinates":[5.6673212051,49.6705703735],"type":"Point"}
}