{
  "type": "Feature",
  "properties": {
    "iso:country":"BE",
    "sg:address":"Rue Adrien Materne 90b",
    "sg:city":"Grace-hollogne",
    "sg:orig_category":"Supermarch\u00e9s",
    "sg:phone":"+32 4 247 40 24",
    "sg:postcode":"4460",
    "sg:province":"Li\u00e8ge",
    "wof:name":"Intermarch\u00c9",
    "wof:placetype":"venue"
},
  "geometry": {"coordinates":[5.5107598305,50.6455039978],"type":"Point"}
}