{
  "type": "Feature",
  "properties": {
    "addr:full":"Vaart Links 15 Nevele Oost-Vlaanderen 9850",
    "addr:housenumber":"15",
    "addr:postcode":"9850",
    "addr:street":"Vaart Links",
    "iso:country":"BE",
    "sg:address":"Vaart Links 15",
    "sg:city":"Nevele",
    "sg:orig_category":"Protection civile",
    "sg:phone":"+32 9 371 81 82",
    "sg:postcode":"9850",
    "sg:province":"Oost-Vlaanderen",
    "wof:name":"Brandweerkazerne",
    "wof:placetype":"venue"
},
  "geometry": {"coordinates":[3.5483720303,51.0289535522],"type":"Point"}
}