{
  "type": "Feature",
  "properties": {
    "iso:country":"BE",
    "sg:address":"Grote Markt 23",
    "sg:city":"Aarschot",
    "sg:orig_category":"Telecommunicatieapparaten",
    "sg:phone":"+32 800 22 800",
    "sg:postcode":"3200",
    "sg:province":"Vlaams-Brabant",
    "wof:name":"Teleboetiek",
    "wof:placetype":"venue"
},
  "geometry": {"coordinates":[4.8368611336,50.9843444824],"type":"Point"}
}