{
  "type": "Feature",
  "properties": {
    "addr:full":"Tomberg 7 Bruxelles (woluwe-saint-lambert) Bruxelles-Capitale 1200",
    "addr:housenumber":"7",
    "addr:postcode":"1200",
    "addr:street":"Tomberg",
    "iso:country":"BE",
    "sg:address":"Tomberg 7",
    "sg:city":"Bruxelles (woluwe-saint-lambert)",
    "sg:classifiers":[
        {
            "category":"Manufacturing",
            "subcategory":"Leather Goods",
            "type":"Manufacturing & Wholesale Goods"
        }
    ],
    "sg:phone":"+32 2 772 81 81",
    "sg:postcode":"1200",
    "sg:province":"Bruxelles-Capitale",
    "sg:tags":[
        "repair",
        "buckskin",
        "-",
        "fur",
        "cleaning"
    ],
    "wof:name":"Van Woensel-saverwijns Sprl",
    "wof:placetype":"venue"
},
  "geometry": {"coordinates":[4.4310741425,50.8414039612],"type":"Point"}
}