{
  "type": "Feature",
  "properties": {
    "iso:country":"BE",
    "sg:address":"Bakendonk 7",
    "sg:city":"Herentals",
    "sg:classifiers":[
        {
            "category":"Real Estate",
            "subcategory":"Architect",
            "type":"Services"
        }
    ],
    "sg:phone":"+32 14 22 54 11",
    "sg:postcode":"2200",
    "sg:province":"Antwerpen",
    "wof:name":"Callaerts B",
    "wof:placetype":"venue"
},
  "geometry": {"coordinates":[4.8198971748,51.1834754944],"type":"Point"}
}