{
  "type": "Feature",
  "properties": {
    "iso:country":"BE",
    "sg:address":"Helenaveldstraat 100",
    "sg:city":"Kontich",
    "sg:orig_category":"Boekhouders",
    "sg:phone":"+32 3 458 32 20",
    "sg:postcode":"2550",
    "sg:province":"Antwerpen",
    "wof:name":"Kris Pyl",
    "wof:placetype":"venue"
},
  "geometry": {"coordinates":[4.4486250877,51.1432228088],"type":"Point"}
}