{
  "type": "Feature",
  "properties": {
    "iso:country":"BE",
    "sg:address":"Fort Verboomstraat 2",
    "sg:city":"Beveren (kieldrecht)",
    "sg:classifiers":[
        {
            "category":"Building & Trades",
            "subcategory":"Pest Control",
            "type":"Services"
        }
    ],
    "sg:phone":"+32 3 773 55 03",
    "sg:postcode":"9130",
    "sg:province":"Oost-Vlaanderen",
    "sg:tags":[
        "painting",
        "contractor"
    ],
    "wof:name":"De Maayer R",
    "wof:placetype":"venue"
},
  "geometry": {"coordinates":[4.1690630913,51.2883682251],"type":"Point"}
}