{
  "type": "Feature",
  "properties": {
    "iso:country":"BE",
    "sg:address":"Dan. De Haenelaan 22",
    "sg:city":"Veurne",
    "sg:classifiers":[
        {
            "category":"Building & Trades",
            "subcategory":"Pest Control",
            "type":"Services"
        }
    ],
    "sg:phone":"+32 58 28 71 69",
    "sg:postcode":"8630",
    "sg:province":"West-Vlaanderen",
    "sg:tags":[
        "painting",
        "contractor"
    ],
    "wof:name":"Art Decor",
    "wof:placetype":"venue"
},
  "geometry": {"coordinates":[2.6584470272,51.0735321045],"type":"Point"}
}