{
  "type": "Feature",
  "properties": {
    "addr:full":"Rue De Grandrieu 54 Beaumont Hainaut 6500",
    "addr:housenumber":"54",
    "addr:postcode":"6500",
    "addr:street":"Rue De Grandrieu;Hainaut",
    "iso:country":"BE",
    "sg:address":"Rue De Grandrieu 54",
    "sg:city":"Beaumont",
    "sg:orig_category":"Decoratieve kunst and kunstbenodigdheden",
    "sg:phone":"+32 71 58 96 92",
    "sg:postcode":"6500",
    "sg:province":"Hainaut",
    "wof:name":"Alain Boulet",
    "wof:placetype":"venue"
},
  "geometry": {"coordinates":[4.2394800186,50.2149009705],"type":"Point"}
}