{
  "type": "Feature",
  "properties": {
    "addr:full":"Rue De Champles 50 Wavre (bierges) Brabant Wallon 1301",
    "addr:housenumber":"50;1301",
    "addr:street":"Rue De Champles",
    "iso:country":"BE",
    "sg:address":"Rue De Champles 50",
    "sg:city":"Wavre (bierges)",
    "sg:classifiers":[
        {
            "category":"Home & Garden",
            "subcategory":"Carpets & Floor Coverings",
            "type":"Retail Goods"
        }
    ],
    "sg:phone":"+32 10 24 16 50",
    "sg:postcode":"1301",
    "sg:province":"Brabant Wallon",
    "sg:tags":[
        "prefab",
        "element"
    ],
    "wof:name":"Dynabat Sa",
    "wof:placetype":"venue"
},
  "geometry": {"coordinates":[4.5767788887,50.7221298218],"type":"Point"}
}