{
  "type": "Feature",
  "properties": {
    "addr:full":"Terschuerenlaan 7 Ledegem West-Vlaanderen 8880",
    "addr:housenumber":"7",
    "addr:postcode":"8880",
    "addr:street":"Terschuerenlaan",
    "iso:country":"BE",
    "sg:address":"Terschuerenlaan 7",
    "sg:city":"Ledegem",
    "sg:orig_category":"Traitement and rev\u00eatement des m\u00e9taux",
    "sg:phone":"+32 56 50 27 88",
    "sg:postcode":"8880",
    "sg:province":"West-Vlaanderen",
    "wof:name":"V.d.s. Mechaniek",
    "wof:placetype":"venue"
},
  "geometry": {"coordinates":[3.1783719063,50.8731689453],"type":"Point"}
}