{
  "type": "Feature",
  "properties": {
    "addr:full":"Nieuwstraat 169 Diepenbeek Limburg 3590",
    "addr:housenumber":"169",
    "addr:postcode":"3590",
    "addr:street":"Nieuwstraat",
    "iso:country":"BE",
    "sg:address":"Nieuwstraat 169",
    "sg:city":"Diepenbeek",
    "sg:classifiers":[
        {
            "category":"Food & Beverages",
            "subcategory":"Groceries & Convenience Stores",
            "type":"Retail Goods"
        }
    ],
    "sg:phone":"+32 11 33 30 08",
    "sg:postcode":"3590",
    "sg:province":"Limburg",
    "sg:tags":[
        "grocer"
    ],
    "wof:name":"Kebo Supermarkt Nv",
    "wof:placetype":"venue"
},
  "geometry": {"coordinates":[5.4519538879,50.9244728088],"type":"Point"}
}