{
  "type": "Feature",
  "properties": {
    "addr:full":"Spiegelstraat 22 Box 1 Ternat (wambeek) Vlaams-Brabant 1741",
    "addr:housenumber":"22;1",
    "addr:postcode":"1741",
    "addr:street":"Spiegelstraat;Box",
    "iso:country":"BE",
    "sg:address":"Spiegelstraat 22 Box 1",
    "sg:city":"Ternat (wambeek)",
    "sg:classifiers":[
        {
            "category":"Manufacturing",
            "subcategory":"Musical Instruments",
            "type":"Manufacturing & Wholesale Goods"
        }
    ],
    "sg:phone":"+32 2 582 71 80",
    "sg:postcode":"1741",
    "sg:province":"Vlaams-Brabant",
    "sg:tags":[
        "piano"
    ],
    "wof:name":"Milton Bvba",
    "wof:placetype":"venue"
},
  "geometry": {"coordinates":[4.1562027931,50.8565711975],"type":"Point"}
}