{
  "type": "Feature",
  "properties": {
    "addr:full":"Reservorenstraat 37 Beringen (beverlo) Limburg 3581",
    "addr:housenumber":"37",
    "addr:postcode":"3581",
    "addr:street":"Reservorenstraat",
    "iso:country":"BE",
    "sg:address":"Reservorenstraat 37",
    "sg:city":"Beringen (beverlo)",
    "sg:orig_category":"Non-Classified Establishments",
    "sg:phone":"+32 11 40 12 01",
    "sg:postcode":"3581",
    "sg:province":"Limburg",
    "wof:name":"Rezytex Bvba",
    "wof:placetype":"venue"
},
  "geometry": {"coordinates":[5.235188961,51.0936317444],"type":"Point"}
}