{
  "type": "Feature",
  "properties": {
    "iso:country":"BE",
    "sg:address":"Avenue De L'espinette Centrale 1",
    "sg:city":"Rhode-saint-genese",
    "sg:orig_category":"Diverse bedrijfsbeheeradviesbureaus",
    "sg:phone":"+32 2 358 59 61",
    "sg:postcode":"1640",
    "sg:province":"Vlaams-Brabant",
    "wof:name":"Project Coordination Center",
    "wof:placetype":"venue"
},
  "geometry": {"coordinates":[4.3832178116,50.7609329224],"type":"Point"}
}