{
  "type": "Feature",
  "properties": {
    "addr:full":"Lamorinierestraat 199 Antwerpen Antwerpen 2018",
    "addr:housenumber":"199",
    "addr:postcode":"2018",
    "addr:street":"Lamorinierestraat",
    "iso:country":"BE",
    "sg:address":"Lamorinierestraat 199",
    "sg:city":"Antwerpen",
    "sg:orig_category":"Non-Classified Establishments",
    "sg:phone":"+32 3 281 37 33",
    "sg:postcode":"2018",
    "sg:province":"Antwerpen",
    "wof:name":"M.s. Distribution-tivall",
    "wof:placetype":"venue"
},
  "geometry": {"coordinates":[4.4194178581,51.2020111084],"type":"Point"}
}