{
  "type": "Feature",
  "properties": {
    "iso:country":"BE",
    "sg:address":"Remparden 27",
    "sg:city":"Oudenaarde",
    "sg:classifiers":[
        {
            "category":"Professional",
            "subcategory":"Advertising",
            "type":"Services"
        }
    ],
    "sg:phone":"+32 55 30 18 32",
    "sg:postcode":"9700",
    "sg:province":"Oost-Vlaanderen",
    "sg:tags":[
        "clothes"
    ],
    "wof:name":"Screentex",
    "wof:placetype":"venue"
},
  "geometry": {"coordinates":[3.6094930172,50.8400382996],"type":"Point"}
}