{
  "type": "Feature",
  "properties": {
    "addr:full":"Brederodestraat 154 Antwerpen Antwerpen 2018",
    "addr:housenumber":"154",
    "addr:postcode":"2018",
    "addr:street":"Brederodestraat",
    "iso:country":"BE",
    "sg:address":"Brederodestraat 154",
    "sg:city":"Antwerpen",
    "sg:classifiers":[
        {
            "category":"Home & Garden",
            "subcategory":"Home Furnishings",
            "type":"Retail Goods"
        }
    ],
    "sg:phone":"+32 3 216 12 74",
    "sg:postcode":"2018",
    "sg:province":"Antwerpen",
    "sg:tags":[
        "-",
        "furniture"
    ],
    "wof:name":"European Decor",
    "wof:placetype":"venue"
},
  "geometry": {"coordinates":[4.3922691345,51.2020111084],"type":"Point"}
}