{
  "type": "Feature",
  "properties": {
    "addr:full":"Posthoornstraat 17b5 Hamont-achel Limburg 3930",
    "addr:housenumber":"17b5",
    "addr:postcode":"3930",
    "addr:street":"Posthoornstraat",
    "iso:country":"BE",
    "sg:address":"Posthoornstraat 17b5",
    "sg:city":"Hamont-achel",
    "sg:classifiers":[
        {
            "category":"Arena",
            "subcategory":"Sports Club",
            "type":"Entertainment"
        }
    ],
    "sg:phone":"+32 11 44 13 98",
    "sg:postcode":"3930",
    "sg:province":"Limburg",
    "sg:tags":[
        "terrain",
        "hors",
        "de",
        "installation",
        "sportifs"
    ],
    "wof:name":"S.k. Hamont",
    "wof:placetype":"venue"
},
  "geometry": {"coordinates":[5.5450549126,51.2511863708],"type":"Point"}
}