{
  "type": "Feature",
  "properties": {
    "iso:country":"BE",
    "sg:address":"Tongersestraat 43ba",
    "sg:city":"Bilzen",
    "sg:classifiers":[
        {
            "category":"Cafe",
            "type":"Food & Drink"
        }
    ],
    "sg:phone":"+32 89 50 11 64",
    "sg:postcode":"3740",
    "sg:province":"Limburg",
    "sg:tags":[
        "caf\u00e9s"
    ],
    "wof:name":"Aleksandrovna Bondareva Ekaterin",
    "wof:placetype":"venue"
},
  "geometry": {"coordinates":[5.5064730644,50.8654747009],"type":"Point"}
}