{
  "type": "Feature",
  "properties": {
    "addr:full":"'t Hofveld 8 Dilbeek (groot - Bijgaarden) Vlaams-Brabant 1702",
    "addr:housenumber":"8;1702",
    "addr:street":"' T Hofveld;Groot Bijgaarden Vlaams-Brabant",
    "iso:country":"BE",
    "sg:address":"'t Hofveld 8",
    "sg:city":"Dilbeek (groot - Bijgaarden)",
    "sg:classifiers":[
        {
            "category":"Organizations",
            "subcategory":"Professional Association",
            "type":"Services"
        }
    ],
    "sg:phone":"+32 2 466 94 30",
    "sg:postcode":"1702",
    "sg:province":"Vlaams-Brabant",
    "sg:tags":[
        "trade-union",
        "federation"
    ],
    "wof:name":"Emc Belgium",
    "wof:placetype":"venue"
},
  "geometry": {"coordinates":[4.2734560966,50.8700866699],"type":"Point"}
}