{
  "type": "Feature",
  "properties": {
    "iso:country":"BE",
    "sg:address":"Graaf Gwijde Van Namenstraat 7",
    "sg:city":"Kortrijk",
    "sg:orig_category":"Mutualities",
    "sg:phone":"+32 56 22 56 98",
    "sg:postcode":"8500",
    "sg:province":"West-Vlaanderen",
    "wof:name":"Vlaams Ziekenfonds West-flandria Kortrijk",
    "wof:placetype":"venue"
},
  "geometry": {"coordinates":[3.282351017,50.8307914734],"type":"Point"}
}