{
  "type": "Feature",
  "properties": {
    "addr:full":"Route De Neufchateau 570 Arlon Luxembourg 6700",
    "addr:housenumber":"570",
    "addr:postcode":"6700",
    "addr:street":"Route De Neufchateau",
    "iso:country":"BE",
    "sg:address":"Route De Neufchateau 570",
    "sg:city":"Arlon",
    "sg:orig_category":"Elektrische installaties voor woningen Loodgieterij, verwarming and sanitaire installaties",
    "sg:phone":"+32 63 23 49 74",
    "sg:postcode":"6700",
    "sg:province":"Luxembourg",
    "wof:name":"Arlon Calotherm",
    "wof:placetype":"venue"
},
  "geometry": {"coordinates":[5.8042387962,49.689666748],"type":"Point"}
}