{
  "type": "Feature",
  "properties": {
    "iso:country":"BE",
    "sg:address":"Floris Verbraekenlei 58",
    "sg:city":"Brasschaat",
    "sg:classifiers":[
        {
            "category":"Arena",
            "subcategory":"Sports Club",
            "type":"Entertainment"
        }
    ],
    "sg:phone":"+32 3 605 44 07",
    "sg:postcode":"2930",
    "sg:province":"Antwerpen",
    "sg:tags":[
        "de"
    ],
    "wof:name":"B.b.c. Makeba Rudy Rent",
    "wof:placetype":"venue"
},
  "geometry": {"coordinates":[4.4452810287,51.2968406677],"type":"Point"}
}