{
  "type": "Feature",
  "properties": {
    "addr:full":"Belgradestraat 54 Mechelen Antwerpen 2800",
    "addr:housenumber":"54",
    "addr:postcode":"2800",
    "addr:street":"Belgradestraat",
    "iso:country":"BE",
    "sg:address":"Belgradestraat 54",
    "sg:city":"Mechelen",
    "sg:classifiers":[
        {
            "category":"Building & Trades",
            "subcategory":"Construction",
            "type":"Services"
        }
    ],
    "sg:phone":"+32 15 41 97 26",
    "sg:postcode":"2800",
    "sg:province":"Antwerpen",
    "sg:tags":[
        "installation",
        "-",
        "central",
        "heating"
    ],
    "wof:name":"Devos Kris Installatiebedrijf",
    "wof:placetype":"venue"
},
  "geometry": {"coordinates":[4.4758048058,51.0148887634],"type":"Point"}
}