{
  "type": "Feature",
  "properties": {
    "addr:full":"Stationsstraat 70 Waregem West-Vlaanderen 8790",
    "addr:housenumber":"70",
    "addr:postcode":"8790",
    "addr:street":"Stationsstraat",
    "iso:country":"BE",
    "sg:address":"Stationsstraat 70",
    "sg:city":"Waregem",
    "sg:classifiers":[
        {
            "category":"Shopping",
            "subcategory":"Clothing, Apparel, & Fashions",
            "type":"Retail Goods"
        }
    ],
    "sg:phone":"+32 56 61 32 55",
    "sg:postcode":"8790",
    "sg:province":"West-Vlaanderen",
    "sg:tags":[
        "v\u00eatements",
        "pour",
        "dame"
    ],
    "wof:name":"Huis St.trop",
    "wof:placetype":"venue"
},
  "geometry": {"coordinates":[3.4300079346,50.8893852234],"type":"Point"}
}