{
  "type": "Feature",
  "properties": {
    "addr:full":"Iers-kruisstraat 91 Riemst Limburg 3770",
    "addr:housenumber":"91",
    "addr:postcode":"3770",
    "addr:street":"Iers-Kruisstraat",
    "iso:country":"BE",
    "sg:address":"Iers-kruisstraat 91",
    "sg:city":"Riemst",
    "sg:classifiers":[
        {
            "category":"Arena",
            "subcategory":"Sports Club",
            "type":"Entertainment"
        }
    ],
    "sg:phone":"+32 12 45 39 28",
    "sg:postcode":"3770",
    "sg:province":"Limburg",
    "sg:tags":[
        "de"
    ],
    "wof:name":"Lavoc Lafelt",
    "wof:placetype":"venue"
},
  "geometry": {"coordinates":[5.6140570641,50.8285560608],"type":"Point"}
}