{
  "type": "Feature",
  "properties": {
    "addr:full":"Gouden-hoofdstraat 3 Kortemark (handzame) West-Vlaanderen 8610",
    "addr:housenumber":"3",
    "addr:postcode":"8610",
    "addr:street":"Gouden-Hoofdstraat",
    "iso:country":"BE",
    "sg:address":"Gouden-hoofdstraat 3",
    "sg:city":"Kortemark (handzame)",
    "sg:classifiers":[
        {
            "category":"Real Estate",
            "subcategory":"Architect",
            "type":"Services"
        }
    ],
    "sg:phone":"+32 51 56 74 74",
    "sg:postcode":"8610",
    "sg:province":"West-Vlaanderen",
    "wof:name":"Declerck R",
    "wof:placetype":"venue"
},
  "geometry": {"coordinates":[3.0009469986,51.0187988281],"type":"Point"}
}