{
  "type": "Feature",
  "properties": {
    "iso:country":"BE",
    "sg:address":"Quai Du Commerce 17-25",
    "sg:city":"Brussel/bruxelles",
    "sg:orig_category":"R\u00e9parations d'appareils \u00e9lectrom\u00e9nagers. Electrom\u00e9nager, t\u00e9l\u00e9visions and radios",
    "sg:phone":"+32 2 217 84 62",
    "sg:postcode":"1000",
    "sg:province":"Bruxelles-Capitale",
    "wof:name":"Maison Servicadet",
    "wof:placetype":"venue"
},
  "geometry": {"coordinates":[4.3485488892,50.8565368652],"type":"Point"}
}