{
  "type": "Feature",
  "properties": {
    "addr:full":"Chauss\u00c9e De Tubize 65 Braine-l'alleud Brabant Wallon 1420",
    "addr:housenumber":"65",
    "addr:postcode":"1420",
    "addr:street":"Chausse\u0301E De Tubize",
    "iso:country":"BE",
    "sg:address":"Chauss\u00c9e De Tubize 65",
    "sg:city":"Braine-l'alleud",
    "sg:orig_category":"D\u00e9taillants en pi\u00e8ces and accessoires de voitures. Pi\u00e8ces and accessoires de v\u00e9hicules automobiles G",
    "sg:phone":"+32 2 384 80 15",
    "sg:postcode":"1420",
    "sg:province":"Brabant Wallon",
    "wof:name":"Sabiex International",
    "wof:placetype":"venue"
},
  "geometry": {"coordinates":[4.1952600479,50.6840705872],"type":"Point"}
}