{
  "type": "Feature",
  "properties": {
    "iso:country":"BE",
    "sg:address":"Hertogstraat 150",
    "sg:city":"Leuven",
    "sg:orig_category":"Traducteurs and interpr\u00e8tes",
    "sg:phone":"+32 16 23 19 42",
    "sg:postcode":"3001",
    "sg:province":"Vlaams-Brabant",
    "wof:name":"Deceuninck Vertaalbureau",
    "wof:placetype":"venue"
},
  "geometry": {"coordinates":[4.6989049911,50.8597640991],"type":"Point"}
}