{
  "type": "Feature",
  "properties": {
    "iso:country":"BE",
    "sg:address":"Reepkenslei 3",
    "sg:city":"Kontich",
    "sg:classifiers":[
        {
            "category":"Health Services",
            "subcategory":"Health Practitioner",
            "type":"Services"
        }
    ],
    "sg:phone":"+32 3 457 77 14",
    "sg:postcode":"2550",
    "sg:province":"Antwerpen",
    "sg:tags":[
        "therapist",
        "speech"
    ],
    "wof:name":"Jaspers",
    "wof:placetype":"venue"
},
  "geometry": {"coordinates":[4.4483709335,51.1237373352],"type":"Point"}
}