{
  "type": "Feature",
  "properties": {
    "iso:country":"BE",
    "sg:address":"Turnhoutsebaan 381",
    "sg:city":"Schilde",
    "sg:orig_category":"Autoverhuur Tuinbenodigdheden Voertuigen",
    "sg:phone":"+32 3 384 20 00",
    "sg:postcode":"2970",
    "sg:province":"Antwerpen",
    "wof:name":"Yves Beirens Busines & Co",
    "wof:placetype":"venue"
},
  "geometry": {"coordinates":[4.6005568504,51.2478141785],"type":"Point"}
}