{
  "type": "Feature",
  "properties": {
    "addr:full":"Rijksweg 780 Dilsen-stokkem Limburg 3650",
    "addr:housenumber":"780",
    "addr:postcode":"3650",
    "addr:street":"Rijksweg",
    "iso:country":"BE",
    "sg:address":"Rijksweg 780",
    "sg:city":"Dilsen-stokkem",
    "sg:orig_category":"V\u00e9hicules automobiles",
    "sg:phone":"+32 89 75 20 31",
    "sg:postcode":"3650",
    "sg:province":"Limburg",
    "wof:name":"Europa Motor",
    "wof:placetype":"venue"
},
  "geometry": {"coordinates":[5.7444372177,51.0579376221],"type":"Point"}
}