{
  "type": "Feature",
  "properties": {
    "addr:full":"Doorslaardorp 85 Lokeren (eksaarde) Oost-Vlaanderen 9160",
    "addr:housenumber":"85",
    "addr:postcode":"9160",
    "addr:street":"Doorslaardorp;Lokeren Eksaarde Oost-Vlaanderen",
    "iso:country":"BE",
    "sg:address":"Doorslaardorp 85",
    "sg:city":"Lokeren (eksaarde)",
    "sg:classifiers":[
        {
            "category":"Professional",
            "subcategory":"Testing Lab",
            "type":"Services"
        }
    ],
    "sg:phone":"+32 9 348 74 16",
    "sg:postcode":"9160",
    "sg:province":"Oost-Vlaanderen",
    "sg:tags":[
        "chemist"
    ],
    "wof:name":"Van Eetvelde M",
    "wof:placetype":"venue"
},
  "geometry": {"coordinates":[3.9864850044,51.1047401428],"type":"Point"}
}