{
  "type": "Feature",
  "properties": {
    "iso:country":"BE",
    "sg:address":"Mutsaertplaats 11",
    "sg:city":"Vilvoorde",
    "sg:orig_category":"Installatie van houten of kunststof schrijnwerk Meubelzaken, woning- and keukeninrichting",
    "sg:phone":"+32 2 267 33 05",
    "sg:postcode":"1800",
    "sg:province":"Vlaams-Brabant",
    "wof:name":"D-klik Box System",
    "wof:placetype":"venue"
},
  "geometry": {"coordinates":[4.3608670235,50.9014282227],"type":"Point"}
}