{
  "type": "Feature",
  "properties": {
    "addr:full":"Lammerdries 21b Olen Antwerpen 2250",
    "addr:housenumber":"21b",
    "addr:postcode":"2250",
    "addr:street":"Lammerdries",
    "iso:country":"BE",
    "sg:address":"Lammerdries 21b",
    "sg:city":"Olen",
    "sg:classifiers":[
        {
            "category":"Professional",
            "type":"Services"
        }
    ],
    "sg:phone":"+32 14 28 54 80",
    "sg:postcode":"2250",
    "sg:province":"Antwerpen",
    "sg:tags":[
        "industrial",
        "work",
        "-",
        "maintenance"
    ],
    "wof:name":"Comatec Nv",
    "wof:placetype":"venue"
},
  "geometry": {"coordinates":[4.9147100449,51.1488685608],"type":"Point"}
}