{
  "type": "Feature",
  "properties": {
    "iso:country":"BE",
    "sg:address":"Leo Baekelandlaan 15",
    "sg:city":"Overpelt",
    "sg:orig_category":"Steel, Wear-Resistant",
    "sg:phone":"+32 11 80 04 50",
    "sg:postcode":"3900",
    "sg:province":"Limburg",
    "wof:name":"Fildra Nv",
    "wof:placetype":"venue"
},
  "geometry": {"coordinates":[5.3914570808,51.2148895264],"type":"Point"}
}