{
  "type": "Feature",
  "properties": {
    "iso:country":"BE",
    "sg:address":"Kortedreef 5",
    "sg:city":"Schilde",
    "sg:orig_category":"Vertalers and tolken",
    "sg:phone":"+32 3 354 10 26",
    "sg:postcode":"2970",
    "sg:province":"Antwerpen",
    "wof:name":"Poolse Taalservice",
    "wof:placetype":"venue"
},
  "geometry": {"coordinates":[4.5532660484,51.2292175293],"type":"Point"}
}