{
  "type": "Feature",
  "properties": {
    "addr:full":"Minervalaan 21b47 Vorst/forest Bruxelles-Capitale 1190",
    "addr:housenumber":"21b47",
    "addr:postcode":"1190",
    "addr:street":"Minervalaan;/ Forest",
    "iso:country":"BE",
    "sg:address":"Minervalaan 21b47",
    "sg:city":"Vorst/forest",
    "sg:orig_category":"Artiesten and kunstenaars",
    "sg:phone":"+32 2 345 96 58",
    "sg:postcode":"1190",
    "sg:province":"Bruxelles-Capitale",
    "wof:name":"Bardiau",
    "wof:placetype":"venue"
},
  "geometry": {"coordinates":[4.3304991722,50.8104820251],"type":"Point"}
}