{
  "type": "Feature",
  "properties": {
    "iso:country":"BE",
    "sg:address":"Place L\u00c9opold Wiener 7bb",
    "sg:city":"Watermaal-bosvoorde/watermael-boitsfort",
    "sg:classifiers":[
        {
            "category":"Restaurant",
            "type":"Food & Drink"
        }
    ],
    "sg:phone":"+32 2 675 26 55",
    "sg:postcode":"1170",
    "sg:province":"Bruxelles-Capitale",
    "sg:tags":[
        "caf\u00e9s"
    ],
    "wof:name":"Taverne Le Club",
    "wof:placetype":"venue"
},
  "geometry": {"coordinates":[4.4183030128,50.7978858948],"type":"Point"}
}