{
  "type": "Feature",
  "properties": {
    "iso:country":"BE",
    "sg:address":"Kerkplein 14",
    "sg:city":"Bonheiden",
    "sg:orig_category":"Pain, p\u00e2tisseries and confiseries",
    "sg:phone":"+32 15 51 12 06",
    "sg:postcode":"2820",
    "sg:province":"Antwerpen",
    "wof:name":"W. Van Den Brande",
    "wof:placetype":"venue"
},
  "geometry": {"coordinates":[4.5487217903,51.0227737427],"type":"Point"}
}