{
  "type": "Feature",
  "properties": {
    "addr:full":"Bisschoppenhoflei 16 Brasschaat Antwerpen 2930",
    "addr:housenumber":"16",
    "addr:postcode":"2930",
    "addr:street":"Bisschoppenhoflei",
    "iso:country":"BE",
    "sg:address":"Bisschoppenhoflei 16",
    "sg:city":"Brasschaat",
    "sg:classifiers":[
        {
            "category":"Health Services",
            "subcategory":"Dentist",
            "type":"Services"
        }
    ],
    "sg:phone":"+32 3 645 27 94",
    "sg:postcode":"2930",
    "sg:province":"Antwerpen",
    "wof:name":"Huynen J",
    "wof:placetype":"venue"
},
  "geometry": {"coordinates":[4.455242157,51.2859230042],"type":"Point"}
}