{
  "type": "Feature",
  "properties": {
    "iso:country":"BE",
    "sg:address":"Vurstjen 3",
    "sg:city":"Evergem",
    "sg:orig_category":"Ordinateurs and \u00e9quipement informatique",
    "sg:phone":"+32 9 253 63 23",
    "sg:postcode":"9940",
    "sg:province":"Oost-Vlaanderen",
    "wof:name":"Eagle Programming",
    "wof:placetype":"venue"
},
  "geometry": {"coordinates":[3.701679945,51.1051597595],"type":"Point"}
}