{
  "type": "Feature",
  "properties": {
    "iso:country":"BE",
    "sg:address":"Rue De Genval 2",
    "sg:city":"Rixensart",
    "sg:orig_category":"V\u00e9t\u00e9rinaires",
    "sg:phone":"+32 2 653 66 36",
    "sg:postcode":"1331",
    "sg:province":"Brabant Wallon",
    "wof:name":"Ludovic Henry",
    "wof:placetype":"venue"
},
  "geometry": {"coordinates":[4.5345821381,50.7348747253],"type":"Point"}
}