{
  "type": "Feature",
  "properties": {
    "iso:country":"BE",
    "sg:address":"Rue Sur Les Marys",
    "sg:city":"Beyne-heusay (queue-du-bois)",
    "sg:classifiers":[
        {
            "category":"Health Services",
            "subcategory":"Health Practitioner",
            "type":"Services"
        }
    ],
    "sg:phone":"+32 4 370 12 62",
    "sg:postcode":"4610",
    "sg:province":"Li\u00e8ge",
    "sg:tags":[
        "physiotherapist"
    ],
    "wof:name":"Thiry M",
    "wof:placetype":"venue"
},
  "geometry": {"coordinates":[5.6611189842,50.6181983948],"type":"Point"}
}