{
  "type": "Feature",
  "properties": {
    "iso:country":"BE",
    "sg:address":"Terbeek 124",
    "sg:city":"Sint-truiden",
    "sg:orig_category":"Eleveurs and marchands de porcs",
    "sg:phone":"+32 11 68 20 32",
    "sg:postcode":"3800",
    "sg:province":"Limburg",
    "wof:name":"Michel Vanderhoeven",
    "wof:placetype":"venue"
},
  "geometry": {"coordinates":[5.1682100296,50.847442627],"type":"Point"}
}