{
  "type": "Feature",
  "properties": {
    "addr:full":"Chauss\u00c9e De Louvain 825 Evere Bruxelles-Capitale 1140",
    "addr:housenumber":"825",
    "addr:postcode":"1140",
    "addr:street":"Chausse\u0301E De Louvain",
    "iso:country":"BE",
    "sg:address":"Chauss\u00c9e De Louvain 825",
    "sg:city":"Evere",
    "sg:orig_category":"Blanchisseries and teintureries",
    "sg:phone":"+32 2 726 60 56",
    "sg:postcode":"1140",
    "sg:province":"Bruxelles-Capitale",
    "wof:name":"Ipsomat",
    "wof:placetype":"venue"
},
  "geometry": {"coordinates":[4.4150691032,50.859375],"type":"Point"}
}