{
  "type": "Feature",
  "properties": {
    "iso:country":"BE",
    "sg:address":"Begijnhof 22",
    "sg:city":"Bilzen",
    "sg:orig_category":"Brandweer and civiele bescherming",
    "sg:phone":"+32 89 41 25 72",
    "sg:postcode":"3740",
    "sg:province":"Limburg",
    "wof:name":"Brandweerkazerne",
    "wof:placetype":"venue"
},
  "geometry": {"coordinates":[5.520029068,50.8697891235],"type":"Point"}
}