{
  "type": "Feature",
  "properties": {
    "addr:full":"Alsembergse Steenweg 791 Ukkel/uccle Bruxelles-Capitale 1180",
    "addr:housenumber":"791",
    "addr:postcode":"1180",
    "addr:street":"Alsembergse Steenweg;/",
    "iso:country":"BE",
    "sg:address":"Alsembergse Steenweg 791",
    "sg:city":"Ukkel/uccle",
    "sg:orig_category":"Schoenen",
    "sg:phone":"+32 2 376 14 63",
    "sg:postcode":"1180",
    "sg:province":"Bruxelles-Capitale",
    "wof:name":"Avance",
    "wof:placetype":"venue"
},
  "geometry": {"coordinates":[4.3364629745,50.8023262024],"type":"Point"}
}