{
  "type": "Feature",
  "properties": {
    "addr:full":"Chauss\u00c9e De Gilly 241 Fleurus Hainaut 6220",
    "addr:housenumber":"241",
    "addr:postcode":"6220",
    "addr:street":"Chausse\u0301E De Gilly",
    "iso:country":"BE",
    "sg:address":"Chauss\u00c9e De Gilly 241",
    "sg:city":"Fleurus",
    "sg:orig_category":"Dranken",
    "sg:phone":"+32 71 38 03 24",
    "sg:postcode":"6220",
    "sg:province":"Hainaut",
    "wof:name":"Brasserie Baccus",
    "wof:placetype":"venue"
},
  "geometry": {"coordinates":[4.5209197998,50.4487724304],"type":"Point"}
}