{
  "type": "Feature",
  "properties": {
    "iso:country":"BE",
    "sg:address":"Koningin Fabiolaplein 6 -1",
    "sg:city":"Ganshoren (brussel)",
    "sg:orig_category":"Diverse juridische dienstverlening",
    "sg:phone":"+32 2 426 38 10",
    "sg:postcode":"1083",
    "sg:province":"Bruxelles-Capitale",
    "wof:name":"Van Malderen Office",
    "wof:placetype":"venue"
},
  "geometry": {"coordinates":[4.3143582344,50.8726730347],"type":"Point"}
}