{
  "type": "Feature",
  "properties": {
    "addr:full":"Gaaiendreef 4 Schoten Antwerpen 2900",
    "addr:housenumber":"4",
    "addr:postcode":"2900",
    "addr:street":"Gaaiendreef",
    "iso:country":"BE",
    "sg:address":"Gaaiendreef 4",
    "sg:city":"Schoten",
    "sg:orig_category":"Gespecialiseerde residenti\u00eble bouw",
    "sg:phone":"+32 3 290 70 19",
    "sg:postcode":"2900",
    "sg:province":"Antwerpen",
    "wof:name":"Marc Neirynck",
    "wof:placetype":"venue"
},
  "geometry": {"coordinates":[4.5086078644,51.2779884338],"type":"Point"}
}