{
  "type": "Feature",
  "properties": {
    "addr:full":"Merebaaistraat 31 Oosterzele Oost-Vlaanderen 9860",
    "addr:housenumber":"31",
    "addr:postcode":"9860",
    "addr:street":"Merebaaistraat;Oost-Vlaanderen",
    "iso:country":"BE",
    "sg:address":"Merebaaistraat 31",
    "sg:city":"Oosterzele",
    "sg:orig_category":"Woningbouw",
    "sg:phone":"+32 9 362 94 58",
    "sg:postcode":"9860",
    "sg:province":"Oost-Vlaanderen",
    "wof:name":"Wall-bouw",
    "wof:placetype":"venue"
},
  "geometry": {"coordinates":[3.8198370934,50.9570808411],"type":"Point"}
}