{
  "type": "Feature",
  "properties": {
    "iso:country":"BE",
    "sg:address":"L. Carr\u00c9straat 21",
    "sg:city":"Heist-op-den-berg",
    "sg:orig_category":"Advocaten and juridische adviseurs",
    "sg:phone":"+32 15 24 40 58",
    "sg:postcode":"2220",
    "sg:province":"Antwerpen",
    "wof:name":"D. De Cuyper",
    "wof:placetype":"venue"
},
  "geometry": {"coordinates":[4.7290501595,51.0851974487],"type":"Point"}
}