{
  "type": "Feature",
  "properties": {
    "iso:country":"BE",
    "sg:address":"Slijkstraat 43",
    "sg:city":"Retie",
    "sg:orig_category":"Ordinateurs and \u00e9quipement informatique",
    "sg:phone":"+32 14 37 80 34",
    "sg:postcode":"2470",
    "sg:province":"Antwerpen",
    "wof:name":"Artware",
    "wof:placetype":"venue"
},
  "geometry": {"coordinates":[5.0834898949,51.2777900696],"type":"Point"}
}