{
  "type": "Feature",
  "properties": {
    "iso:country":"BE",
    "sg:address":"Grote Baan 566",
    "sg:city":"Helchteren",
    "sg:classifiers":[
        {
            "category":"Retail",
            "subcategory":"Event Space",
            "type":"Services"
        }
    ],
    "sg:phone":"+32 11 52 10 56",
    "sg:postcode":"3530",
    "sg:province":"Limburg",
    "sg:tags":[
        "box",
        "stall"
    ],
    "wof:name":"Aerts Metalen Nv",
    "wof:placetype":"venue"
},
  "geometry": {"coordinates":[5.380423069,51.0754318237],"type":"Point"}
}