{
  "type": "Feature",
  "properties": {
    "iso:country":"BE",
    "sg:address":"Rue Julien Dulait 52-54",
    "sg:city":"Charleroi",
    "sg:orig_category":"Installation de menuiserie m\u00e9tallique",
    "sg:phone":"+32 71 36 23 27",
    "sg:postcode":"6001",
    "sg:province":"Hainaut",
    "wof:name":"Martin & Fils",
    "wof:placetype":"venue"
},
  "geometry": {"coordinates":[4.433298111,50.4031524658],"type":"Point"}
}