{
  "type": "Feature",
  "properties": {
    "addr:full":"Roosbloemstraat 20 Oosterzele Oost-Vlaanderen 9860",
    "addr:housenumber":"20",
    "addr:postcode":"9860",
    "addr:street":"Roosbloemstraat;Oost-Vlaanderen",
    "iso:country":"BE",
    "sg:address":"Roosbloemstraat 20",
    "sg:city":"Oosterzele",
    "sg:orig_category":"Equipement divers pour commerces Installation \u00e9lectrique r\u00e9sidentielle",
    "sg:phone":"+32 9 362 45 88",
    "sg:postcode":"9860",
    "sg:province":"Oost-Vlaanderen",
    "wof:name":"Koeltechniek Smekens",
    "wof:placetype":"venue"
},
  "geometry": {"coordinates":[3.8207149506,50.9462547302],"type":"Point"}
}