{
  "type": "Feature",
  "properties": {
    "iso:country":"BE",
    "sg:address":"Rue De Dampremy 1",
    "sg:city":"Charleroi (jumet)",
    "sg:orig_category":"Fiduciairies",
    "sg:phone":"+32 71 31 56 56",
    "sg:postcode":"6040",
    "sg:province":"Hainaut",
    "wof:name":"Casefi Scrl",
    "wof:placetype":"venue"
},
  "geometry": {"coordinates":[4.4156961441,50.4324531555],"type":"Point"}
}