{
  "type": "Feature",
  "properties": {
    "addr:full":"Torhoutsestraat 36 Oostkamp West-Vlaanderen 8020",
    "addr:housenumber":"36",
    "addr:postcode":"8020",
    "addr:street":"Torhoutsestraat",
    "iso:country":"BE",
    "sg:address":"Torhoutsestraat 36",
    "sg:city":"Oostkamp",
    "sg:orig_category":"Begrafeniswezen Installatie van houten of kunststof schrijnwerk",
    "sg:phone":"+32 50 27 74 31",
    "sg:postcode":"8020",
    "sg:province":"West-Vlaanderen",
    "wof:name":"Couffez Gebroeders",
    "wof:placetype":"venue"
},
  "geometry": {"coordinates":[3.2055358887,51.0938911438],"type":"Point"}
}