{
  "type": "Feature",
  "properties": {
    "iso:country":"BE",
    "sg:address":"Bankelindeweg 56",
    "sg:city":"Poperinge",
    "sg:orig_category":"Eleveurs de bovins",
    "sg:phone":"+32 57 33 33 13",
    "sg:postcode":"8972",
    "sg:province":"West-Vlaanderen",
    "wof:name":"Paul Deschuytter",
    "wof:placetype":"venue"
},
  "geometry": {"coordinates":[2.6944639683,50.8983306885],"type":"Point"}
}