{
  "type": "Feature",
  "properties": {
    "addr:full":"Gentsesteenweg 102 Harelbeke West-Vlaanderen 8530",
    "addr:housenumber":"102",
    "addr:postcode":"8530",
    "addr:street":"Gentsesteenweg",
    "iso:country":"BE",
    "sg:address":"Gentsesteenweg 102",
    "sg:city":"Harelbeke",
    "sg:orig_category":"Mat\u00e9riel de T\u00e9l\u00e9communication. R\u00e9parations d'appareils \u00e9lectrom\u00e9nagers. Electrom\u00e9nager, t\u00e9l\u00e9visions ",
    "sg:phone":"+32 56 70 31 81",
    "sg:postcode":"8530",
    "sg:province":"West-Vlaanderen",
    "wof:name":"Eldi",
    "wof:placetype":"venue"
},
  "geometry": {"coordinates":[3.3211209774,50.8616027832],"type":"Point"}
}