{
  "type": "Feature",
  "properties": {
    "addr:full":"Petite Rue De Nord 13 Brussel/bruxelles Bruxelles-Capitale 1000",
    "addr:housenumber":"13",
    "addr:postcode":"1000",
    "addr:street":"Petite Rue De Nord;/",
    "iso:country":"BE",
    "sg:address":"Petite Rue De Nord 13",
    "sg:city":"Brussel/bruxelles",
    "sg:classifiers":[
        {
            "category":"Recreation",
            "type":"Entertainment"
        }
    ],
    "sg:phone":"+32 2 502 36 66",
    "sg:postcode":"1000",
    "sg:province":"Bruxelles-Capitale",
    "sg:tags":[
        "diver",
        "amusement"
    ],
    "wof:name":"Loty Lyra",
    "wof:placetype":"venue"
},
  "geometry": {"coordinates":[4.368309021,50.8495063782],"type":"Point"}
}