{
  "type": "Feature",
  "properties": {
    "iso:country":"BE",
    "sg:address":"Rue De Vis\u00c9 105",
    "sg:city":"Vise",
    "sg:orig_category":"Sportclubs",
    "sg:phone":"+32 475 31 89 71",
    "sg:postcode":"4600",
    "sg:province":"Li\u00e8ge",
    "wof:name":"Revatech",
    "wof:placetype":"venue"
},
  "geometry": {"coordinates":[5.6937770844,50.7329750061],"type":"Point"}
}