{
  "type": "Feature",
  "properties": {
    "addr:full":"Avenue Eug\u00e8ne Mascaux 373 Charleroi (marcinelle) Hainaut 6001",
    "addr:housenumber":"373",
    "addr:postcode":"6001",
    "addr:street":"Avenue Euge\u0300Ne Mascaux",
    "iso:country":"BE",
    "sg:address":"Avenue Eug\u00e8ne Mascaux 373",
    "sg:city":"Charleroi (marcinelle)",
    "sg:orig_category":"Non-Classified Establishments",
    "sg:phone":"+32 71 21 36 79",
    "sg:postcode":"6001",
    "sg:province":"Hainaut",
    "wof:name":"Feger Sprl",
    "wof:placetype":"venue"
},
  "geometry": {"coordinates":[4.4386410713,50.3916015625],"type":"Point"}
}