{
  "type": "Feature",
  "properties": {
    "addr:full":"Dendermondse Steenweg 23a Aalst Oost-Vlaanderen 9300",
    "addr:housenumber":"23a",
    "addr:postcode":"9300",
    "addr:street":"Steenweg",
    "iso:country":"BE",
    "sg:address":"Dendermondse Steenweg 23a",
    "sg:city":"Aalst",
    "sg:classifiers":[
        {
            "category":"Professional",
            "subcategory":"Lawyer & Legal Services",
            "type":"Services"
        }
    ],
    "sg:phone":"+32 53 71 03 51",
    "sg:postcode":"9300",
    "sg:province":"Oost-Vlaanderen",
    "wof:name":"Buysse Peggy",
    "wof:placetype":"venue"
},
  "geometry": {"coordinates":[4.0351758003,50.9432754517],"type":"Point"}
}