{
  "type": "Feature",
  "properties": {
    "iso:country":"BE",
    "sg:address":"Verlatdreef 7b201",
    "sg:city":"Beveren",
    "sg:orig_category":"Informaticaconsulenten",
    "sg:phone":"+32 3 755 33 51",
    "sg:postcode":"9120",
    "sg:province":"Oost-Vlaanderen",
    "wof:name":"Q-soft",
    "wof:placetype":"venue"
},
  "geometry": {"coordinates":[4.2641730309,51.2105751038],"type":"Point"}
}