{
  "type": "Feature",
  "properties": {
    "iso:country":"BE",
    "sg:address":"Molenbeemd 1",
    "sg:city":"Schilde",
    "sg:orig_category":"Sportclubs",
    "sg:phone":"+32 3 385 27 71",
    "sg:postcode":"2970",
    "sg:province":"Antwerpen",
    "wof:name":"Wsc Vooruit-st.antonius",
    "wof:placetype":"venue"
},
  "geometry": {"coordinates":[4.576406002,51.2448196411],"type":"Point"}
}