{
  "type": "Feature",
  "properties": {
    "iso:country":"BE",
    "sg:address":"Rue De L'hotellerie 41",
    "sg:city":"Lessines",
    "sg:orig_category":"Journaux",
    "sg:phone":"+32 68 33 64 20",
    "sg:postcode":"7860",
    "sg:province":"Hainaut",
    "wof:name":"Page Henri",
    "wof:placetype":"venue"
},
  "geometry": {"coordinates":[3.8377330303,50.710521698],"type":"Point"}
}