{
  "type": "Feature",
  "properties": {
    "addr:full":"Robert Vandammestraat 242 Koksijde West-Vlaanderen 8670",
    "addr:housenumber":"242",
    "addr:postcode":"8670",
    "addr:street":"Vandammestraat",
    "iso:country":"BE",
    "sg:address":"Robert Vandammestraat 242",
    "sg:city":"Koksijde",
    "sg:classifiers":[
        {
            "category":"Retail",
            "subcategory":"Auto Repair",
            "type":"Services"
        }
    ],
    "sg:phone":"+32 58 52 25 45",
    "sg:postcode":"8670",
    "sg:province":"West-Vlaanderen",
    "sg:tags":[
        "garage"
    ],
    "wof:name":"Vandenbroucke Garage & Co Bvba",
    "wof:placetype":"venue"
},
  "geometry": {"coordinates":[2.6321001053,51.0998306274],"type":"Point"}
}