{
  "type": "Feature",
  "properties": {
    "iso:country":"BE",
    "sg:address":"Lindebosstraat 25",
    "sg:city":"Genk",
    "sg:classifiers":[
        {
            "category":"Real Estate",
            "subcategory":"Architect",
            "type":"Services"
        }
    ],
    "sg:phone":"+32 89 36 70 01",
    "sg:postcode":"3600",
    "sg:province":"Limburg",
    "wof:name":"Vos Architect Bvba",
    "wof:placetype":"venue"
},
  "geometry": {"coordinates":[5.5423851013,50.9651908875],"type":"Point"}
}