{
  "type": "Feature",
  "properties": {
    "iso:country":"BE",
    "sg:address":"Oude Brusselsestraat 10",
    "sg:city":"Lennik",
    "sg:orig_category":"Eleveurs de bovins",
    "sg:phone":"+32 2 532 42 01",
    "sg:postcode":"1750",
    "sg:province":"Vlaams-Brabant",
    "wof:name":"Louis Limbourg",
    "wof:placetype":"venue"
},
  "geometry": {"coordinates":[4.1692638397,50.8099098206],"type":"Point"}
}