{
  "type": "Feature",
  "properties": {
    "iso:country":"BE",
    "sg:address":"Aalterweg 8",
    "sg:city":"Aalter",
    "sg:classifiers":[
        {
            "category":"Shopping",
            "subcategory":"Florist",
            "type":"Retail Goods"
        }
    ],
    "sg:phone":"+32 9 374 06 83",
    "sg:postcode":"9880",
    "sg:province":"Oost-Vlaanderen",
    "wof:name":"Perle Bloemen",
    "wof:placetype":"venue"
},
  "geometry": {"coordinates":[3.427120924,51.121673584],"type":"Point"}
}