{
  "type": "Feature",
  "properties": {
    "addr:full":"Korspelsesteenweg 39 Beringen (beverlo) Limburg 3581",
    "addr:housenumber":"39",
    "addr:postcode":"3581",
    "addr:street":"Korspelsesteenweg",
    "iso:country":"BE",
    "sg:address":"Korspelsesteenweg 39",
    "sg:city":"Beringen (beverlo)",
    "sg:classifiers":[
        {
            "category":"Insurance",
            "subcategory":"Insurance Agent",
            "type":"Services"
        }
    ],
    "sg:phone":"+32 11 39 12 18",
    "sg:postcode":"3581",
    "sg:province":"Limburg",
    "sg:tags":[
        "broker"
    ],
    "wof:name":"Vanierschot M",
    "wof:placetype":"venue"
},
  "geometry": {"coordinates":[5.228705883,51.0883903503],"type":"Point"}
}