{
  "type": "Feature",
  "properties": {
    "iso:country":"BE",
    "sg:address":"Oosthoekstraat 18",
    "sg:city":"Tielt",
    "sg:orig_category":"Artsen and specialisten",
    "sg:phone":"+32 51 68 71 47",
    "sg:postcode":"8700",
    "sg:province":"West-Vlaanderen",
    "wof:name":"Dirk Martens",
    "wof:placetype":"venue"
},
  "geometry": {"coordinates":[3.4138069153,51.0175018311],"type":"Point"}
}