{
  "type": "Feature",
  "properties": {
    "addr:full":"Avenue Georges Henri 62a Bruxelles (woluwe-saint-lambert) Bruxelles-Capitale 1200",
    "addr:housenumber":"62a",
    "addr:postcode":"1200",
    "addr:street":"Avenue Georges Henri",
    "iso:country":"BE",
    "sg:address":"Avenue Georges Henri 62a",
    "sg:city":"Bruxelles (woluwe-saint-lambert)",
    "sg:classifiers":[
        {
            "category":"Shopping",
            "subcategory":"Computers & Home Electronics",
            "type":"Retail Goods"
        }
    ],
    "sg:phone":"+32 2 770 05 65",
    "sg:postcode":"1200",
    "sg:province":"Bruxelles-Capitale",
    "sg:tags":[
        "telephone",
        "apparatus",
        "accessory"
    ],
    "wof:name":"Sonauto Sprl",
    "wof:placetype":"venue"
},
  "geometry": {"coordinates":[4.4216618538,50.8473091125],"type":"Point"}
}