{
  "type": "Feature",
  "properties": {
    "addr:full":"Borsbeeksesteenweg 94 Boechout Antwerpen 2530",
    "addr:housenumber":"94",
    "addr:postcode":"2530",
    "addr:street":"Borsbeeksesteenweg",
    "iso:country":"BE",
    "sg:address":"Borsbeeksesteenweg 94",
    "sg:city":"Boechout",
    "sg:orig_category":"Pain, p\u00e2tisseries and confiseries",
    "sg:phone":"+32 3 455 82 26",
    "sg:postcode":"2530",
    "sg:province":"Antwerpen",
    "wof:name":"Bakkerij Mari\u00cbn",
    "wof:placetype":"venue"
},
  "geometry": {"coordinates":[4.492246151,51.1707878113],"type":"Point"}
}