{
  "type": "Feature",
  "properties": {
    "iso:country":"BE",
    "sg:address":"Winkelomseheide 78",
    "sg:city":"Geel",
    "sg:classifiers":[
        {
            "category":"Health Services",
            "subcategory":"Health Practitioner",
            "type":"Services"
        }
    ],
    "sg:phone":"+32 14 58 20 76",
    "sg:postcode":"2440",
    "sg:province":"Antwerpen",
    "sg:tags":[
        "therapist",
        "speech"
    ],
    "wof:name":"Geens M",
    "wof:placetype":"venue"
},
  "geometry": {"coordinates":[5.0106301308,51.1373100281],"type":"Point"}
}