{
  "type": "Feature",
  "properties": {
    "iso:country":"BE",
    "sg:address":"Mechelsestraat 144",
    "sg:city":"Londerzeel",
    "sg:orig_category":"Boucheries",
    "sg:phone":"+32 52 30 99 59",
    "sg:postcode":"1840",
    "sg:province":"Vlaams-Brabant",
    "wof:name":"Gaston Mertens",
    "wof:placetype":"venue"
},
  "geometry": {"coordinates":[4.3124442101,51.0069847107],"type":"Point"}
}