{
  "type": "Feature",
  "properties": {
    "addr:full":"Rue Des Cerisiers 14 Marche-en-famenne Luxembourg 6900",
    "addr:housenumber":"14",
    "addr:postcode":"6900",
    "addr:street":"Rue Des Cerisiers",
    "iso:country":"BE",
    "sg:address":"Rue Des Cerisiers 14",
    "sg:city":"Marche-en-famenne",
    "sg:classifiers":[
        {
            "category":"Insurance",
            "subcategory":"Life Insurance",
            "type":"Services"
        }
    ],
    "sg:phone":"+32 84 31 38 39",
    "sg:postcode":"6900",
    "sg:province":"Luxembourg",
    "sg:tags":[
        "assurance"
    ],
    "wof:name":"Andr\u00c9 Dock",
    "wof:placetype":"venue"
},
  "geometry": {"coordinates":[5.3516798019,50.2226333618],"type":"Point"}
}