{
  "type": "Feature",
  "properties": {
    "addr:full":"Rue Des Ombelles 13 Marche-en-famenne (aye) Luxembourg 6900",
    "addr:housenumber":"13",
    "addr:postcode":"6900",
    "addr:street":"Rue Des Ombelles",
    "iso:country":"BE",
    "sg:address":"Rue Des Ombelles 13",
    "sg:city":"Marche-en-famenne (aye)",
    "sg:classifiers":[
        {
            "category":"Utilities",
            "subcategory":"Electric",
            "type":"Services"
        }
    ],
    "sg:phone":"+32 84 32 15 35",
    "sg:postcode":"6900",
    "sg:province":"Luxembourg",
    "sg:tags":[
        "energy",
        "renewable"
    ],
    "wof:name":"Mouzon J-m",
    "wof:placetype":"venue"
},
  "geometry": {"coordinates":[5.3430151939,50.2273483276],"type":"Point"}
}