{
  "type": "Feature",
  "properties": {
    "addr:full":"Nieuwpoortlaan 85 De Panne West-Vlaanderen 8660",
    "addr:housenumber":"85",
    "addr:postcode":"8660",
    "addr:street":"Nieuwpoortlaan",
    "iso:country":"BE",
    "sg:address":"Nieuwpoortlaan 85",
    "sg:city":"De Panne",
    "sg:classifiers":[
        {
            "category":"Bars & Pubs",
            "type":"Food & Drink"
        }
    ],
    "sg:phone":"+32 58 41 06 91",
    "sg:postcode":"8660",
    "sg:province":"West-Vlaanderen",
    "sg:tags":[
        "tavern"
    ],
    "wof:name":"Marcy (le)",
    "wof:placetype":"venue"
},
  "geometry": {"coordinates":[2.5947499275,51.1046066284],"type":"Point"}
}