{
  "type": "Feature",
  "properties": {
    "addr:full":"Mechelse Steenweg 150 Antwerpen Antwerpen 2018",
    "addr:housenumber":"150",
    "addr:postcode":"2018",
    "addr:street":"Steenweg",
    "iso:country":"BE",
    "sg:address":"Mechelse Steenweg 150",
    "sg:city":"Antwerpen",
    "sg:classifiers":[
        {
            "category":"Banks & Credit Unions",
            "subcategory":"Financial Services",
            "type":"Services"
        }
    ],
    "sg:phone":"+32 3 247 84 11",
    "sg:postcode":"2018",
    "sg:province":"Antwerpen",
    "sg:tags":[
        "loan",
        "mortgage"
    ],
    "wof:name":"Krefima Nv",
    "wof:placetype":"venue"
},
  "geometry": {"coordinates":[4.4097070694,51.2056388855],"type":"Point"}
}