{
  "type": "Feature",
  "properties": {
    "iso:country":"BE",
    "sg:address":"Chemin De Silly 6",
    "sg:city":"Ath",
    "sg:orig_category":"Rundveehouders",
    "sg:phone":"+32 68 55 15 69",
    "sg:postcode":"7823",
    "sg:province":"Hainaut",
    "wof:name":"Michel Vanconeghem",
    "wof:placetype":"venue"
},
  "geometry": {"coordinates":[3.9106829166,50.6435852051],"type":"Point"}
}