{
  "type": "Feature",
  "properties": {
    "addr:full":"Kerkstr 4 Oostende West-Vlaanderen 8400",
    "addr:housenumber":"4",
    "addr:postcode":"8400",
    "addr:street":"Kerkstr",
    "iso:country":"BE",
    "sg:address":"Kerkstr 4",
    "sg:city":"Oostende",
    "sg:classifiers":[
        {
            "category":"Banks & Credit Unions",
            "subcategory":"Bank",
            "type":"Services"
        }
    ],
    "sg:phone":"+32 59 70 04 09",
    "sg:postcode":"8400",
    "sg:province":"West-Vlaanderen",
    "wof:name":"Banque Cr\u00e9dit Commercial",
    "wof:placetype":"venue"
},
  "geometry": {"coordinates":[2.9186599255,51.2319374084],"type":"Point"}
}