{
  "type": "Feature",
  "properties": {
    "iso:country":"BE",
    "sg:address":"Dendermondsesteenweg 173",
    "sg:city":"Gent",
    "sg:classifiers":[
        {
            "category":"Personal",
            "subcategory":"Beauty Salon",
            "type":"Services"
        }
    ],
    "sg:phone":"+32 9 228 05 93",
    "sg:postcode":"9000",
    "sg:province":"Oost-Vlaanderen",
    "sg:tags":[
        "de",
        "coiffure"
    ],
    "wof:name":"Pepe Hair Method",
    "wof:placetype":"venue"
},
  "geometry": {"coordinates":[3.7445459366,51.0535812378],"type":"Point"}
}