{
  "type": "Feature",
  "properties": {
    "iso:country":"BE",
    "sg:address":"Rue De L' Etuve 12b",
    "sg:city":"Li\u00c8ge",
    "sg:orig_category":"Salles de spectacles",
    "sg:phone":"+32 4 222 02 15",
    "sg:postcode":"4000",
    "sg:province":"Li\u00e8ge",
    "wof:name":"Th\u00c9\u00c2tre De L'etuve",
    "wof:placetype":"venue"
},
  "geometry": {"coordinates":[5.5746850967,50.6418533325],"type":"Point"}
}