{
  "type": "Feature",
  "properties": {
    "iso:country":"BE",
    "sg:address":"Rue Chapelle \u00e0 La Lice 7b",
    "sg:city":"Fl\u00e9ron (retinne)",
    "sg:classifiers":[
        {
            "category":"Wholesale",
            "subcategory":"Meat",
            "type":"Manufacturing & Wholesale Goods"
        }
    ],
    "sg:phone":"+32 4 263 36 66",
    "sg:postcode":"4621",
    "sg:province":"Li\u00e8ge",
    "sg:tags":[
        "whol",
        "-"
    ],
    "wof:name":"Esposito E",
    "wof:placetype":"venue"
},
  "geometry": {"coordinates":[5.6973171234,50.6176643372],"type":"Point"}
}