{
  "type": "Feature",
  "properties": {
    "addr:full":"Rue De Villers 13 Hannut Li\u00e8ge 4280",
    "addr:housenumber":"13",
    "addr:postcode":"4280",
    "addr:street":"Rue De Villers",
    "iso:country":"BE",
    "sg:address":"Rue De Villers 13",
    "sg:city":"Hannut",
    "sg:orig_category":"Eleveurs d'animaux domestiques",
    "sg:phone":"+32 19 51 35 88",
    "sg:postcode":"4280",
    "sg:province":"Li\u00e8ge",
    "wof:name":"Elevage Du Val Warrego",
    "wof:placetype":"venue"
},
  "geometry": {"coordinates":[5.0885062218,50.6638946533],"type":"Point"}
}