{
  "type": "Feature",
  "properties": {
    "addr:full":"Eindhoutdorp 19 Laakdal (eindhout) Antwerpen 2430",
    "addr:housenumber":"19",
    "addr:postcode":"2430",
    "addr:street":"Eindhoutdorp",
    "iso:country":"BE",
    "sg:address":"Eindhoutdorp 19",
    "sg:city":"Laakdal (eindhout)",
    "sg:classifiers":[
        {
            "category":"Bars & Pubs",
            "type":"Food & Drink"
        }
    ],
    "sg:phone":"+32 14 86 67 35",
    "sg:postcode":"2430",
    "sg:province":"Antwerpen",
    "wof:name":"Ceusters W",
    "wof:placetype":"venue"
},
  "geometry": {"coordinates":[5.0687851906,51.0857543945],"type":"Point"}
}