{
  "type": "Feature",
  "properties": {
    "iso:country":"BE",
    "sg:address":"Moerkantsebaan 88",
    "sg:city":"Essen",
    "sg:orig_category":"V\u00e9hicules automobiles. Entretien and r\u00e9parations de voitures",
    "sg:phone":"+32 3 667 29 64",
    "sg:postcode":"2910",
    "sg:province":"Antwerpen",
    "wof:name":"Walter Konings",
    "wof:placetype":"venue"
},
  "geometry": {"coordinates":[4.4294600487,51.4521026611],"type":"Point"}
}