{
  "type": "Feature",
  "properties": {
    "addr:full":"Rue Du Marathon 2 Ottignies-louvain-la-neuve Brabant Wallon 1348",
    "addr:housenumber":"2",
    "addr:postcode":"1348",
    "addr:street":"Rue Du Marathon",
    "iso:country":"BE",
    "sg:address":"Rue Du Marathon 2",
    "sg:city":"Ottignies-louvain-la-neuve",
    "sg:orig_category":"Huishoudapparaten, televisies and radio's",
    "sg:phone":"+32 10 45 49 06",
    "sg:postcode":"1348",
    "sg:province":"Brabant Wallon",
    "wof:name":"Greenwich Electronics",
    "wof:placetype":"venue"
},
  "geometry": {"coordinates":[4.6071920395,50.66979599],"type":"Point"}
}