{
  "type": "Feature",
  "properties": {
    "addr:full":"Sint-jobsstraat 25 Ba Herentals Antwerpen 2200",
    "addr:housenumber":"25",
    "addr:postcode":"2200",
    "addr:street":"Sint-Jobsstraat",
    "iso:country":"BE",
    "sg:address":"Sint-jobsstraat 25 Ba",
    "sg:city":"Herentals",
    "sg:orig_category":"Boekhandels",
    "sg:phone":"+32 14 22 15 54",
    "sg:postcode":"2200",
    "sg:province":"Antwerpen",
    "wof:name":"R.g. Visualia",
    "wof:placetype":"venue"
},
  "geometry": {"coordinates":[4.8198971748,51.1834754944],"type":"Point"}
}