{
  "type": "Feature",
  "properties": {
    "iso:country":"BE",
    "sg:address":"Rue Des Carri\u00c8res 25",
    "sg:city":"Charleroi",
    "sg:orig_category":"Plomberie, chauffage and installations sanitaires. Charpentes and couvertures",
    "sg:phone":"+32 71 43 80 53",
    "sg:postcode":"6032",
    "sg:province":"Hainaut",
    "wof:name":"Schelfaut Ren\u00c9 Et Fils",
    "wof:placetype":"venue"
},
  "geometry": {"coordinates":[4.4014978409,50.3848419189],"type":"Point"}
}