{
  "type": "Feature",
  "properties": {
    "iso:country":"BE",
    "sg:address":"Broeder De Saedeleerstr. 36",
    "sg:city":"Lede",
    "sg:orig_category":"Woningbouw",
    "sg:phone":"+32 53 80 16 42",
    "sg:postcode":"9340",
    "sg:province":"Oost-Vlaanderen",
    "wof:name":"M D Building",
    "wof:placetype":"venue"
},
  "geometry": {"coordinates":[3.9867401123,50.9649887085],"type":"Point"}
}