{
  "type": "Feature",
  "properties": {
    "iso:country":"BE",
    "sg:address":"Nekkerspoelstraat 278",
    "sg:city":"Mechelen",
    "sg:classifiers":[
        {
            "category":"Retail",
            "subcategory":"Laundry & Dry Cleaning",
            "type":"Services"
        }
    ],
    "sg:phone":"+32 15 55 61 00",
    "sg:postcode":"2800",
    "sg:province":"Antwerpen",
    "wof:name":"Wasserij Nekkerspoel",
    "wof:placetype":"venue"
},
  "geometry": {"coordinates":[4.5012888908,51.0323905945],"type":"Point"}
}