{
  "type": "Feature",
  "properties": {
    "addr:full":"Alphonse Renardstraat 37 Elsene/ixelles Bruxelles-Capitale 1050",
    "addr:housenumber":"37",
    "addr:postcode":"1050",
    "addr:street":"Alphonse Renardstraat",
    "iso:country":"BE",
    "sg:address":"Alphonse Renardstraat 37",
    "sg:city":"Elsene/ixelles",
    "sg:orig_category":"Binnenhuisarchitecten Verlichting and huishoudartikelen",
    "sg:phone":"+32 2 347 11 16",
    "sg:postcode":"1050",
    "sg:province":"Bruxelles-Capitale",
    "wof:name":"Creazio",
    "wof:placetype":"venue"
},
  "geometry": {"coordinates":[4.3580927849,50.8177680969],"type":"Point"}
}