{
  "type": "Feature",
  "properties": {
    "addr:full":"Boulevard Fr\u00e8re-orban 21 Li\u00e8ge 1 Li\u00e8ge 4000",
    "addr:housenumber":"21;1",
    "addr:postcode":"4000",
    "addr:street":"Boulevard Fre\u0300Re-Orban",
    "iso:country":"BE",
    "sg:address":"Boulevard Fr\u00e8re-orban 21",
    "sg:city":"Li\u00e8ge 1",
    "sg:classifiers":[
        {
            "category":"Health Services",
            "subcategory":"Health Practitioner",
            "type":"Services"
        }
    ],
    "sg:phone":"+32 4 221 44 94",
    "sg:postcode":"4000",
    "sg:province":"Li\u00e8ge",
    "sg:tags":[
        "physiotherapist"
    ],
    "wof:name":"Mersch Nathalie",
    "wof:placetype":"venue"
},
  "geometry": {"coordinates":[5.5709080696,50.6335525513],"type":"Point"}
}