{
  "type": "Feature",
  "properties": {
    "iso:country":"BE",
    "sg:address":"Lattenbosweg 2",
    "sg:city":"Meise (wolvertem)",
    "sg:classifiers":[
        {
            "category":"Home & Garden",
            "subcategory":"Carpets & Floor Coverings",
            "type":"Retail Goods"
        }
    ],
    "sg:phone":"+32 52 31 21 98",
    "sg:postcode":"1861",
    "sg:province":"Vlaams-Brabant",
    "sg:tags":[
        "layer",
        "mosaicists"
    ],
    "wof:name":"Belgrado J",
    "wof:placetype":"venue"
},
  "geometry": {"coordinates":[4.3273301125,50.9860038757],"type":"Point"}
}