{
  "type": "Feature",
  "properties": {
    "iso:country":"BE",
    "sg:address":"Kapelsesteenweg 509",
    "sg:city":"Antwerpen (ekeren)",
    "sg:classifiers":[
        {
            "category":"Social Services",
            "subcategory":"Job Training",
            "type":"Services"
        }
    ],
    "sg:phone":"+32 3 660 20 05",
    "sg:postcode":"2180",
    "sg:province":"Antwerpen",
    "sg:tags":[
        "personnel"
    ],
    "wof:name":"Top Safety Education Bvba",
    "wof:placetype":"venue"
},
  "geometry": {"coordinates":[4.4586000443,51.2716217041],"type":"Point"}
}