{
  "type": "Feature",
  "properties": {
    "addr:full":"Neerveldstraat 25 Maasmechelen Limburg 3630",
    "addr:housenumber":"25",
    "addr:postcode":"3630",
    "addr:street":"Neerveldstraat",
    "iso:country":"BE",
    "sg:address":"Neerveldstraat 25",
    "sg:city":"Maasmechelen",
    "sg:classifiers":[
        {
            "category":"Insurance",
            "subcategory":"Life Insurance",
            "type":"Services"
        }
    ],
    "sg:phone":"+32 89 76 41 33",
    "sg:postcode":"3630",
    "sg:province":"Limburg",
    "sg:tags":[
        "assurance"
    ],
    "wof:name":"Nijsten",
    "wof:placetype":"venue"
},
  "geometry": {"coordinates":[5.703248024,50.9634513855],"type":"Point"}
}