{
  "type": "Feature",
  "properties": {
    "iso:country":"BE",
    "sg:address":"Chauss\u00c9e De Wavre 800",
    "sg:city":"Etterbeek/etterbeek",
    "sg:orig_category":"Chaussures",
    "sg:phone":"+32 2 640 48 96",
    "sg:postcode":"1040",
    "sg:province":"Bruxelles-Capitale",
    "wof:name":"Chaussures Prado",
    "wof:placetype":"venue"
},
  "geometry": {"coordinates":[4.3925170898,50.8291473389],"type":"Point"}
}