{
  "type": "Feature",
  "properties": {
    "iso:country":"BE",
    "sg:address":"Chauss\u00e9e De Bruxelles 97",
    "sg:city":"Charleroi (lodelinsart)",
    "sg:classifiers":[
        {
            "category":"Health Services",
            "subcategory":"Nursing And Care Facility",
            "type":"Services"
        }
    ],
    "sg:phone":"+32 476 88 15 95",
    "sg:postcode":"6042",
    "sg:province":"Hainaut",
    "sg:tags":[
        "home"
    ],
    "wof:name":"Cabinet Infirmiere Lemont",
    "wof:placetype":"venue"
},
  "geometry": {"coordinates":[4.438680172,50.4383468628],"type":"Point"}
}