{
  "type": "Feature",
  "properties": {
    "addr:full":"Grand'rue 121 Pecq Hainaut 7743",
    "addr:housenumber":"121",
    "addr:postcode":"7743",
    "addr:street":"Grand'Rue",
    "iso:country":"BE",
    "sg:address":"Grand'rue 121",
    "sg:city":"Pecq",
    "sg:orig_category":"Slagers",
    "sg:phone":"+32 69 55 62 93",
    "sg:postcode":"7743",
    "sg:province":"Hainaut",
    "wof:name":"V. Moerman",
    "wof:placetype":"venue"
},
  "geometry": {"coordinates":[3.3619999886,50.6531715393],"type":"Point"}
}