{
  "type": "Feature",
  "properties": {
    "addr:full":"Merksplassebaan 36 Malle Antwerpen 2390",
    "addr:housenumber":"36",
    "addr:postcode":"2390",
    "addr:street":"Merksplassebaan",
    "iso:country":"BE",
    "sg:address":"Merksplassebaan 36",
    "sg:city":"Malle",
    "sg:orig_category":"Sportclubs",
    "sg:phone":"+32 3 309 34 70",
    "sg:postcode":"2390",
    "sg:province":"Antwerpen",
    "wof:name":"J.c. Fudoshin Zoersel",
    "wof:placetype":"venue"
},
  "geometry": {"coordinates":[4.7412858009,51.3065757751],"type":"Point"}
}