{
  "type": "Feature",
  "properties": {
    "iso:country":"BE",
    "sg:address":"Avenue Facult\u00c9-d'agronomie 65",
    "sg:city":"Gembloux",
    "sg:orig_category":"R\u00e9parations de chaussures and articles en cuir. R\u00e9parations \u00e0 domicile d'articles divers. Magasins d",
    "sg:phone":"+32 81 61 36 07",
    "sg:postcode":"5030",
    "sg:province":"Namur",
    "wof:name":"Cordonnerie De La Facult\u00c9",
    "wof:placetype":"venue"
},
  "geometry": {"coordinates":[4.6948099136,50.5668869019],"type":"Point"}
}