{
  "type": "Feature",
  "properties": {
    "addr:full":"Hondschotestraat 140 Wevelgem West-Vlaanderen 8560",
    "addr:housenumber":"140",
    "addr:postcode":"8560",
    "addr:street":"Hondschotestraat",
    "iso:country":"BE",
    "sg:address":"Hondschotestraat 140",
    "sg:city":"Wevelgem",
    "sg:orig_category":"Artistes ind\u00e9pendants",
    "sg:phone":"+32 56 41 19 41",
    "sg:postcode":"8560",
    "sg:province":"West-Vlaanderen",
    "wof:name":"Expeel",
    "wof:placetype":"venue"
},
  "geometry": {"coordinates":[3.1883940697,50.8444519043],"type":"Point"}
}