{
  "type": "Feature",
  "properties": {
    "addr:full":"Rue De Tongres 29 Etterbeek Bruxelles-Capitale 1040",
    "addr:housenumber":"29",
    "addr:postcode":"1040",
    "addr:street":"Rue De Tongres",
    "iso:country":"BE",
    "sg:address":"Rue De Tongres 29",
    "sg:city":"Etterbeek",
    "sg:orig_category":"Schoenen",
    "sg:phone":"+32 2 736 34 66",
    "sg:postcode":"1040",
    "sg:province":"Bruxelles-Capitale",
    "wof:name":"Su\u00c8de Brussels",
    "wof:placetype":"venue"
},
  "geometry": {"coordinates":[4.4000220299,50.8397293091],"type":"Point"}
}