{
  "type": "Feature",
  "properties": {
    "addr:full":"Klijtstraat 2 Izegem West-Vlaanderen 8870",
    "addr:housenumber":"2",
    "addr:postcode":"8870",
    "addr:street":"Klijtstraat",
    "iso:country":"BE",
    "sg:address":"Klijtstraat 2",
    "sg:city":"Izegem",
    "sg:orig_category":"Herstellingen and onderhoud van auto's",
    "sg:phone":"+32 51 31 94 04",
    "sg:postcode":"8870",
    "sg:province":"West-Vlaanderen",
    "wof:name":"Garage Vandemaele",
    "wof:placetype":"venue"
},
  "geometry": {"coordinates":[3.2009110451,50.9123535156],"type":"Point"}
}