{
  "type": "Feature",
  "properties": {
    "iso:country":"BE",
    "sg:address":"Rue Fontaine Saint-pierre 1c",
    "sg:city":"Assesse",
    "sg:classifiers":[
        {
            "category":"Building & Trades",
            "subcategory":"Landscaping Services",
            "type":"Services"
        }
    ],
    "sg:phone":"+32 81 22 39 49",
    "sg:postcode":"5330",
    "sg:province":"Namur",
    "sg:tags":[
        "equipment",
        "swimming",
        "-",
        "pool",
        "contractor"
    ],
    "wof:name":"Honnay Ets",
    "wof:placetype":"venue"
},
  "geometry": {"coordinates":[5.0442857742,50.3694496155],"type":"Point"}
}