{
  "type": "Feature",
  "properties": {
    "addr:full":"Rue Jean Ester 150 Charleroi Hainaut 6030",
    "addr:housenumber":"150",
    "addr:postcode":"6030",
    "addr:street":"Rue Jean Ester;Hainaut",
    "iso:country":"BE",
    "sg:address":"Rue Jean Ester 150",
    "sg:city":"Charleroi",
    "sg:orig_category":"Boucheries",
    "sg:phone":"+32 71 32 05 90",
    "sg:postcode":"6030",
    "sg:province":"Hainaut",
    "wof:name":"Christian De Leeuw",
    "wof:placetype":"venue"
},
  "geometry": {"coordinates":[4.4056630135,50.4245834351],"type":"Point"}
}