{
  "type": "Feature",
  "properties": {
    "iso:country":"BE",
    "sg:address":"Lindekensveldstraat 7",
    "sg:city":"Hasselt",
    "sg:orig_category":"Vitrage. R\u00e9paration and restauration de meubles. Antiquit\u00e9s",
    "sg:phone":"+32 11 25 46 02",
    "sg:postcode":"3510",
    "sg:province":"Limburg",
    "wof:name":"Huis 't Karrewiel",
    "wof:placetype":"venue"
},
  "geometry": {"coordinates":[5.2531552315,50.9474906921],"type":"Point"}
}