{
  "type": "Feature",
  "properties": {
    "iso:country":"BE",
    "sg:address":"Poeldendries 11",
    "sg:city":"Nevele (landegem)",
    "sg:classifiers":[
        {
            "category":"Utilities",
            "subcategory":"Refuse",
            "type":"Services"
        }
    ],
    "sg:phone":"+32 475 79 56 96",
    "sg:postcode":"9850",
    "sg:province":"Oost-Vlaanderen",
    "sg:tags":[
        "boiler",
        "-",
        "heating",
        "steam"
    ],
    "wof:name":"Van Damme Bvba",
    "wof:placetype":"venue"
},
  "geometry": {"coordinates":[3.5799379349,51.058052063],"type":"Point"}
}