{
  "type": "Feature",
  "properties": {
    "iso:country":"BE",
    "sg:address":"Oppemstraat 7",
    "sg:city":"Meise (wolvertem)",
    "sg:classifiers":[
        {
            "category":"Professional",
            "subcategory":"Detective & Security Services",
            "type":"Services"
        }
    ],
    "sg:phone":"+32 2 270 58 80",
    "sg:postcode":"1861",
    "sg:province":"Vlaams-Brabant",
    "sg:tags":[
        "-",
        "system",
        "apparatus",
        "surveillance"
    ],
    "wof:name":"Buyse Beveiliging Bvba",
    "wof:placetype":"venue"
},
  "geometry": {"coordinates":[4.3084058762,50.9501686096],"type":"Point"}
}