{
  "type": "Feature",
  "properties": {
    "iso:country":"BE",
    "sg:address":"Noordkaai 33",
    "sg:city":"Izegem",
    "sg:orig_category":"Non-Classified Establishments",
    "sg:phone":"+32 51 30 34 89",
    "sg:postcode":"8870",
    "sg:province":"West-Vlaanderen",
    "wof:name":"Stubbe Agnes Linnen Stoffen",
    "wof:placetype":"venue"
},
  "geometry": {"coordinates":[3.1898100376,50.9288406372],"type":"Point"}
}