{
  "type": "Feature",
  "properties": {
    "addr:full":"Route De Marche 37 Durbuy Luxembourg 6941",
    "addr:housenumber":"37",
    "addr:postcode":"6941",
    "addr:street":"Route De Marche",
    "iso:country":"BE",
    "sg:address":"Route De Marche 37",
    "sg:city":"Durbuy",
    "sg:orig_category":"Banken and kredietinstellingen",
    "sg:phone":"+32 86 21 19 44",
    "sg:postcode":"6941",
    "sg:province":"Luxembourg",
    "wof:name":"Banque Cr\u00c9dit Professionel",
    "wof:placetype":"venue"
},
  "geometry": {"coordinates":[5.524184227,50.3770332336],"type":"Point"}
}