{
  "type": "Feature",
  "properties": {
    "iso:country":"BE",
    "sg:address":"Heysellaan 31",
    "sg:city":"Vilvoorde",
    "sg:classifiers":[
        {
            "category":"Health Services",
            "subcategory":"Health Practitioner",
            "type":"Services"
        }
    ],
    "sg:phone":"+32 2 267 72 88",
    "sg:postcode":"1800",
    "sg:province":"Vlaams-Brabant",
    "sg:tags":[
        "physiotherapist"
    ],
    "wof:name":"Weyers Annick",
    "wof:placetype":"venue"
},
  "geometry": {"coordinates":[4.3689861298,50.9005470276],"type":"Point"}
}