{
  "type": "Feature",
  "properties": {
    "iso:country":"BE",
    "sg:address":"Rue Ortmans-hauzeur 16",
    "sg:city":"Verviers",
    "sg:orig_category":"Timbres, monnaies and troph\u00e9es",
    "sg:phone":"+32 87 34 11 80",
    "sg:postcode":"4800",
    "sg:province":"Li\u00e8ge",
    "wof:name":"Philat\u00c9lie Deom",
    "wof:placetype":"venue"
},
  "geometry": {"coordinates":[5.8658227921,50.59349823],"type":"Point"}
}