{
  "type": "Feature",
  "properties": {
    "iso:country":"BE",
    "sg:address":"Bevrijdersstraat 34",
    "sg:city":"Moerbeke",
    "sg:orig_category":"Pharmaciens",
    "sg:phone":"+32 9 346 81 09",
    "sg:postcode":"9180",
    "sg:province":"Oost-Vlaanderen",
    "wof:name":"Joris Baeke",
    "wof:placetype":"venue"
},
  "geometry": {"coordinates":[3.9393749237,51.1739959717],"type":"Point"}
}