{
  "type": "Feature",
  "properties": {
    "addr:full":"Sint-hubrechtsstraat 80 Roeselare West-Vlaanderen 8800",
    "addr:housenumber":"80",
    "addr:postcode":"8800",
    "addr:street":"Sint-Hubrechtsstraat",
    "iso:country":"BE",
    "sg:address":"Sint-hubrechtsstraat 80",
    "sg:city":"Roeselare",
    "sg:orig_category":"Cr\u00e8ches and garderies d'enfants",
    "sg:phone":"+32 51 24 60 98",
    "sg:postcode":"8800",
    "sg:province":"West-Vlaanderen",
    "wof:name":"Kribbe Knuffel",
    "wof:placetype":"venue"
},
  "geometry": {"coordinates":[3.1335639954,50.9468917847],"type":"Point"}
}