{
  "type": "Feature",
  "properties": {
    "addr:full":"Jan Van Rijswijcklaan 194c Antwerpen Antwerpen 2020",
    "addr:housenumber":"194c",
    "addr:postcode":"2020",
    "addr:street":"Jan Van Rijswijcklaan",
    "iso:country":"BE",
    "sg:address":"Jan Van Rijswijcklaan 194c",
    "sg:city":"Antwerpen",
    "sg:classifiers":[
        {
            "category":"Manufacturing",
            "subcategory":"Paper Products",
            "type":"Manufacturing & Wholesale Goods"
        }
    ],
    "sg:phone":"+32 3 237 39 87",
    "sg:postcode":"2020",
    "sg:province":"Antwerpen",
    "sg:tags":[
        "-"
    ],
    "wof:name":"Alap Speciality Products",
    "wof:placetype":"venue"
},
  "geometry": {"coordinates":[4.3951158524,51.1893310547],"type":"Point"}
}