{
  "type": "Feature",
  "properties": {
    "iso:country":"BE",
    "sg:address":"Aarschotsesteenweg 674",
    "sg:city":"Leuven",
    "sg:orig_category":"Charpentes and couvertures",
    "sg:phone":"+32 16 44 95 86",
    "sg:postcode":"3012",
    "sg:province":"Vlaams-Brabant",
    "wof:name":"Hartwig Marien",
    "wof:placetype":"venue"
},
  "geometry": {"coordinates":[4.7221741676,50.9255981445],"type":"Point"}
}