{
  "type": "Feature",
  "properties": {
    "iso:country":"BE",
    "sg:address":"Bergstraat 86",
    "sg:city":"Heist-op-den-berg",
    "sg:classifiers":[
        {
            "category":"Personal",
            "subcategory":"Beauty Salon",
            "type":"Services"
        }
    ],
    "sg:phone":"+32 15 24 49 68",
    "sg:postcode":"2220",
    "sg:province":"Antwerpen",
    "wof:name":"Charme",
    "wof:placetype":"venue"
},
  "geometry": {"coordinates":[4.7211489677,51.0764656067],"type":"Point"}
}