{
  "type": "Feature",
  "properties": {
    "addr:full":"Avenue Du Plein-vent 5 Theux Li\u00e8ge 4910",
    "addr:housenumber":"5",
    "addr:postcode":"4910",
    "addr:street":"Avenue Du Plein-Vent",
    "iso:country":"BE",
    "sg:address":"Avenue Du Plein-vent 5",
    "sg:city":"Theux",
    "sg:orig_category":"Editeurs de journaux. Editeurs de revues and p\u00e9riodiques",
    "sg:phone":"+32 87 22 79 07",
    "sg:postcode":"4910",
    "sg:province":"Li\u00e8ge",
    "wof:name":"Adrien Delatte Jean-rene",
    "wof:placetype":"venue"
},
  "geometry": {"coordinates":[5.8634090424,50.5387115479],"type":"Point"}
}