{
  "type": "Feature",
  "properties": {
    "iso:country":"BE",
    "sg:address":"Grote Markt 53-57",
    "sg:city":"Zelzate",
    "sg:classifiers":[
        {
            "category":"Shopping",
            "subcategory":"Jewelry",
            "type":"Retail Goods"
        }
    ],
    "sg:phone":"+32 9 345 85 03",
    "sg:postcode":"9060",
    "sg:province":"Oost-Vlaanderen",
    "sg:tags":[
        "jeweller",
        "-"
    ],
    "wof:name":"Van Overstraeten F",
    "wof:placetype":"venue"
},
  "geometry": {"coordinates":[3.8110809326,51.2008972168],"type":"Point"}
}