{
  "type": "Feature",
  "properties": {
    "iso:country":"BE",
    "sg:address":"Tiensevest 17",
    "sg:city":"Leuven (kessel-lo)",
    "sg:classifiers":[
        {
            "category":"Social Services",
            "type":"Services"
        }
    ],
    "sg:phone":"+32 16 22 96 13",
    "sg:postcode":"3010",
    "sg:province":"Vlaams-Brabant",
    "wof:name":"Oikonde Vzw",
    "wof:placetype":"venue"
},
  "geometry": {"coordinates":[4.7332701683,50.8693008423],"type":"Point"}
}