{
  "type": "Feature",
  "properties": {
    "iso:country":"BE",
    "sg:address":"Rue De La Baille 28",
    "sg:city":"Lens",
    "sg:orig_category":"S\u00e9curit\u00e9 sociale",
    "sg:phone":"+32 65 22 77 51",
    "sg:postcode":"7870",
    "sg:province":"Hainaut",
    "wof:name":"Mutualit\u00c9 Socialiste",
    "wof:placetype":"venue"
},
  "geometry": {"coordinates":[3.9021530151,50.5593605042],"type":"Point"}
}