{
  "type": "Feature",
  "properties": {
    "addr:full":"Fabriekstraat 8 Aarschot Vlaams-Brabant 3200",
    "addr:housenumber":"8",
    "addr:postcode":"3200",
    "addr:street":"Fabriekstraat",
    "iso:country":"BE",
    "sg:address":"Fabriekstraat 8",
    "sg:city":"Aarschot",
    "sg:orig_category":"M\u00e9decins and sp\u00e9cialistes",
    "sg:phone":"+32 16 57 07 15",
    "sg:postcode":"3200",
    "sg:province":"Vlaams-Brabant",
    "wof:name":"Marina Coeckaerts",
    "wof:placetype":"venue"
},
  "geometry": {"coordinates":[4.8277568817,50.9843711853],"type":"Point"}
}