{
  "type": "Feature",
  "properties": {
    "iso:country":"BE",
    "sg:address":"Hoek 126",
    "sg:city":"Boom",
    "sg:orig_category":"Installations and terrains de sport hors centres sportifs. Centres de fitness. Clubs de sport",
    "sg:phone":"+32 3 844 71 70",
    "sg:postcode":"2850",
    "sg:province":"Antwerpen",
    "wof:name":"S.p.o.r.t.",
    "wof:placetype":"venue"
},
  "geometry": {"coordinates":[4.3796038628,51.0829734802],"type":"Point"}
}