{
  "type": "Feature",
  "properties": {
    "iso:country":"BE",
    "sg:address":"Avenue Du 10e-de-ligne 19",
    "sg:city":"Arlon",
    "sg:classifiers":[
        {
            "category":"Manufacturing",
            "subcategory":"Glass & Minerals",
            "type":"Manufacturing & Wholesale Goods"
        }
    ],
    "sg:phone":"+32 63 22 02 41",
    "sg:postcode":"6700",
    "sg:province":"Luxembourg",
    "sg:tags":[
        "decorative",
        "artistic"
    ],
    "wof:name":"Le Comptoir Des Glaces Arlon S.p.r.l.",
    "wof:placetype":"venue"
},
  "geometry": {"coordinates":[5.8203349113,49.6863098145],"type":"Point"}
}