{
  "type": "Feature",
  "properties": {
    "addr:full":"Grotendries 21 Lubbeek Vlaams-Brabant 3210",
    "addr:housenumber":"21",
    "addr:postcode":"3210",
    "addr:street":"Grotendries",
    "iso:country":"BE",
    "sg:address":"Grotendries 21",
    "sg:city":"Lubbeek",
    "sg:classifiers":[
        {
            "category":"Shopping",
            "subcategory":"Clothing, Apparel, & Fashions",
            "type":"Retail Goods"
        }
    ],
    "sg:phone":"+32 16 63 43 15",
    "sg:postcode":"3210",
    "sg:province":"Vlaams-Brabant",
    "sg:tags":[
        "v\u00eatements",
        "pour",
        "dame"
    ],
    "wof:name":"Schoonbergen",
    "wof:placetype":"venue"
},
  "geometry": {"coordinates":[4.8596940041,50.8889503479],"type":"Point"}
}