{
  "type": "Feature",
  "properties": {
    "iso:country":"BE",
    "sg:address":"Biezestraat 12",
    "sg:city":"Nevele (merendree)",
    "sg:classifiers":[
        {
            "category":"Arena",
            "subcategory":"Sports Club",
            "type":"Entertainment"
        }
    ],
    "sg:phone":"+32 9 371 91 93",
    "sg:postcode":"9850",
    "sg:province":"Oost-Vlaanderen",
    "wof:name":"Diving School Ghent/patraco Bvba",
    "wof:placetype":"venue"
},
  "geometry": {"coordinates":[3.587569952,51.0753669739],"type":"Point"}
}