{
  "type": "Feature",
  "properties": {
    "iso:country":"BE",
    "sg:address":"Gentstraat 96",
    "sg:city":"Temse",
    "sg:orig_category":"Rev\u00eatements de sols and murs",
    "sg:phone":"+32 3 711 14 72",
    "sg:postcode":"9140",
    "sg:province":"Oost-Vlaanderen",
    "wof:name":"Europarket",
    "wof:placetype":"venue"
},
  "geometry": {"coordinates":[4.1666879654,51.1143608093],"type":"Point"}
}