{
  "type": "Feature",
  "properties": {
    "iso:country":"BE",
    "sg:address":"Rue De Baudemont 28",
    "sg:city":"Itter",
    "sg:orig_category":"Tuinen",
    "sg:phone":"+32 67 64 91 07",
    "sg:postcode":"1460",
    "sg:province":"Brabant Wallon",
    "wof:name":"Les Jardins De Baudemont",
    "wof:placetype":"venue"
},
  "geometry": {"coordinates":[4.2678151131,50.6471481323],"type":"Point"}
}