{
  "type": "Feature",
  "properties": {
    "iso:country":"BE",
    "sg:address":"Rue Fief 4",
    "sg:city":"Olne",
    "sg:classifiers":[
        {
            "category":"Parking",
            "subcategory":"Bicycle",
            "type":"Transportation"
        }
    ],
    "sg:phone":"+32 477 34 25 09",
    "sg:postcode":"4877",
    "sg:province":"Li\u00e8ge",
    "sg:tags":[
        "chiropodist"
    ],
    "wof:name":"Pirard E",
    "wof:placetype":"venue"
},
  "geometry": {"coordinates":[5.7476530075,50.5905456543],"type":"Point"}
}