{
  "type": "Feature",
  "properties": {
    "addr:full":"Rue Hubert Halet 46 Pepinster Li\u00e8ge 4860",
    "addr:housenumber":"46",
    "addr:postcode":"4860",
    "addr:street":"Rue Hubert Halet",
    "iso:country":"BE",
    "sg:address":"Rue Hubert Halet 46",
    "sg:city":"Pepinster",
    "sg:orig_category":"Mat\u00e9riaux de construction Gr",
    "sg:phone":"+32 87 46 02 92",
    "sg:postcode":"4860",
    "sg:province":"Li\u00e8ge",
    "wof:name":"Maison Grosjean",
    "wof:placetype":"venue"
},
  "geometry": {"coordinates":[5.8059401512,50.5698013306],"type":"Point"}
}