{
  "type": "Feature",
  "properties": {
    "addr:full":"Voie De L'ardenne 94 Chaudfontaine Li\u00e8ge 4053",
    "addr:housenumber":"94",
    "addr:postcode":"4053",
    "addr:street":"Voie De L'Ardenne",
    "iso:country":"BE",
    "sg:address":"Voie De L'ardenne 94",
    "sg:city":"Chaudfontaine",
    "sg:orig_category":"Blanchisseries and teintureries",
    "sg:phone":"+32 4 231 01 69",
    "sg:postcode":"4053",
    "sg:province":"Li\u00e8ge",
    "wof:name":"Ipsomat",
    "wof:placetype":"venue"
},
  "geometry": {"coordinates":[5.6061811447,50.5911140442],"type":"Point"}
}