{
  "type": "Feature",
  "properties": {
    "iso:country":"BE",
    "sg:address":"Avenue Des Combattants 66",
    "sg:city":"Court-saint-etienne",
    "sg:orig_category":"Banques and organismes de cr\u00e9dit",
    "sg:phone":"+32 10 61 22 34",
    "sg:postcode":"1490",
    "sg:province":"Brabant Wallon",
    "wof:name":"Fortis",
    "wof:placetype":"venue"
},
  "geometry": {"coordinates":[4.5626811981,50.6478347778],"type":"Point"}
}