{
  "type": "Feature",
  "properties": {
    "iso:country":"BE",
    "sg:address":"Chemin Du Trou-du-bois 3",
    "sg:city":"Nivelles",
    "sg:orig_category":"Entretien and r\u00e9parations de voitures",
    "sg:phone":"+32 67 77 38 02",
    "sg:postcode":"1401",
    "sg:province":"Brabant Wallon",
    "wof:name":"Nestor Gossiaux",
    "wof:placetype":"venue"
},
  "geometry": {"coordinates":[4.3504548073,50.6128311157],"type":"Point"}
}