{
  "type": "Feature",
  "properties": {
    "iso:country":"BE",
    "sg:address":"Industrielaan 7",
    "sg:city":"Diepenbeek",
    "sg:orig_category":"Disneyland Paris. Transports terrestres de voyageurs. Agences de voyages",
    "sg:phone":"+32 11 35 04 04",
    "sg:postcode":"3590",
    "sg:province":"Limburg",
    "wof:name":"De Zigeuner",
    "wof:placetype":"venue"
},
  "geometry": {"coordinates":[5.4231038094,50.9099807739],"type":"Point"}
}