{
  "type": "Feature",
  "properties": {
    "iso:country":"BE",
    "sg:address":"Vaalvijverstraat 47",
    "sg:city":"Beringen (paal)",
    "sg:classifiers":[
        {
            "category":"Health Services",
            "subcategory":"Nursing And Care Facility",
            "type":"Services"
        }
    ],
    "sg:phone":"+32 478 49 53 78",
    "sg:postcode":"3583",
    "sg:province":"Limburg",
    "sg:tags":[
        "home"
    ],
    "wof:name":"Thuisverpleging Conny Schrijvers",
    "wof:placetype":"venue"
},
  "geometry": {"coordinates":[5.1706700325,51.0389442444],"type":"Point"}
}