{
  "type": "Feature",
  "properties": {
    "addr:full":"Annuntiatenstraat 41 Brugge West-Vlaanderen 8000",
    "addr:housenumber":"41",
    "addr:postcode":"8000",
    "addr:street":"Annuntiatenstraat",
    "iso:country":"BE",
    "sg:address":"Annuntiatenstraat 41",
    "sg:city":"Brugge",
    "sg:orig_category":"M\u00e9decins and sp\u00e9cialistes",
    "sg:phone":"+32 50 34 17 45",
    "sg:postcode":"8000",
    "sg:province":"West-Vlaanderen",
    "wof:name":"Hilde Loeters",
    "wof:placetype":"venue"
},
  "geometry": {"coordinates":[3.2245459557,51.2158699036],"type":"Point"}
}