{
  "type": "Feature",
  "properties": {
    "addr:full":"Rue De La Loi 57 Bruxelles 1041",
    "addr:housenumber":"57",
    "addr:postcode":"1041",
    "addr:street":"Rue De La Loi",
    "iso:country":"BE",
    "sg:address":"Rue De La Loi 57",
    "sg:city":"Bruxelles",
    "sg:classifiers":[
        {
            "category":"Communications",
            "subcategory":"Film & Video Production",
            "type":"Services"
        }
    ],
    "sg:phone":"+32 2 735 09 71",
    "sg:postcode":"1041",
    "sg:tags":[
        "audio-visual"
    ],
    "wof:name":"Keynews Television S.p.r.l.",
    "wof:placetype":"venue"
},
  "geometry": {"coordinates":[4.3733158112,50.8444824219],"type":"Point"}
}