{
  "type": "Feature",
  "properties": {
    "addr:full":"Rue Des Ecomines 17 Spa Li\u00e8ge 4900",
    "addr:housenumber":"17",
    "addr:postcode":"4900",
    "addr:street":"Rue Des Ecomines",
    "iso:country":"BE",
    "sg:address":"Rue Des Ecomines 17",
    "sg:city":"Spa",
    "sg:classifiers":[
        {
            "category":"Personal",
            "subcategory":"Piercing",
            "type":"Services"
        }
    ],
    "sg:phone":"+32 87 77 63 39",
    "sg:postcode":"4900",
    "sg:province":"Li\u00e8ge",
    "sg:tags":[
        "piercings",
        "tatouages"
    ],
    "wof:name":"E. Ceda",
    "wof:placetype":"venue"
},
  "geometry": {"coordinates":[5.8653669357,50.4908294678],"type":"Point"}
}