{
  "type": "Feature",
  "properties": {
    "iso:country":"BE",
    "sg:address":"Rue Julie Billiart 7",
    "sg:city":"Namur",
    "sg:classifiers":[
        {
            "category":"Personal",
            "subcategory":"Beauty Salon",
            "type":"Services"
        }
    ],
    "sg:phone":"+32 81 22 72 86",
    "sg:postcode":"5000",
    "sg:province":"Namur",
    "sg:tags":[
        "de",
        "coiffure"
    ],
    "wof:name":"Paulette Bubbe",
    "wof:placetype":"venue"
},
  "geometry": {"coordinates":[4.868639946,50.4637908936],"type":"Point"}
}