{
  "type": "Feature",
  "properties": {
    "addr:full":"Avenue De La Salm 14 Vielsalm Luxembourg 6690",
    "addr:housenumber":"14",
    "addr:postcode":"6690",
    "addr:street":"Avenue De La Salm",
    "iso:country":"BE",
    "sg:address":"Avenue De La Salm 14",
    "sg:city":"Vielsalm",
    "sg:classifiers":[
        {
            "category":"Banks & Credit Unions",
            "subcategory":"Investment Brokerage",
            "type":"Services"
        }
    ],
    "sg:phone":"+32 80 21 61 10",
    "sg:postcode":"6690",
    "sg:province":"Luxembourg",
    "sg:tags":[
        "printing",
        "-"
    ],
    "wof:name":"Andrianne-chauveheid (imprimerie)",
    "wof:placetype":"venue"
},
  "geometry": {"coordinates":[5.9134287834,50.2827110291],"type":"Point"}
}