{
  "type": "Feature",
  "properties": {
    "iso:country":"BE",
    "sg:address":"Chauss\u00e9e Du Roeulx 230",
    "sg:city":"Soignies",
    "sg:classifiers":[
        {
            "category":"Shopping",
            "subcategory":"Pets & Pet Supplies",
            "type":"Retail Goods"
        }
    ],
    "sg:phone":"+32 67 33 09 63",
    "sg:postcode":"7060",
    "sg:province":"Hainaut",
    "sg:tags":[
        "aquarium",
        "accessory"
    ],
    "wof:name":"A B G Diffusion",
    "wof:placetype":"venue"
},
  "geometry": {"coordinates":[4.0788779259,50.5596580505],"type":"Point"}
}