{
  "type": "Feature",
  "properties": {
    "iso:country":"BE",
    "sg:address":"Avenue D'elsenborn 5",
    "sg:city":"Rixensart (genval)",
    "sg:classifiers":[
        {
            "category":"Wholesale",
            "subcategory":"Construction Materials",
            "type":"Manufacturing & Wholesale Goods"
        }
    ],
    "sg:phone":"+32 2 653 58 30",
    "sg:postcode":"1332",
    "sg:province":"Brabant Wallon",
    "sg:tags":[
        "elevator"
    ],
    "wof:name":"Gall\u00e9e B",
    "wof:placetype":"venue"
},
  "geometry": {"coordinates":[4.4928541183,50.7134628296],"type":"Point"}
}