{
  "type": "Feature",
  "properties": {
    "addr:full":"Rue De Li\u00c8ge 7a Nandrin Li\u00e8ge 4550",
    "addr:housenumber":"7a",
    "addr:postcode":"4550",
    "addr:street":"Rue De Lie\u0300Ge",
    "iso:country":"BE",
    "sg:address":"Rue De Li\u00c8ge 7a",
    "sg:city":"Nandrin",
    "sg:orig_category":"Winkelinrichting and handelsuitrusting Gh",
    "sg:phone":"+32 4 371 29 52",
    "sg:postcode":"4550",
    "sg:province":"Li\u00e8ge",
    "wof:name":"Rihon J",
    "wof:placetype":"venue"
},
  "geometry": {"coordinates":[5.4204249382,50.5065155029],"type":"Point"}
}