{
  "type": "Feature",
  "properties": {
    "iso:country":"BE",
    "sg:address":"Pav\u00e9 De Soignies 87",
    "sg:city":"Enghien",
    "sg:classifiers":[
        {
            "category":"Home & Garden",
            "subcategory":"Home Furnishings",
            "type":"Retail Goods"
        }
    ],
    "sg:phone":"+32 2 395 80 11",
    "sg:postcode":"7850",
    "sg:province":"Hainaut",
    "sg:tags":[
        "-",
        "furniture"
    ],
    "wof:name":"Verbiest (meubles)",
    "wof:placetype":"venue"
},
  "geometry": {"coordinates":[4.0316939354,50.6822471619],"type":"Point"}
}