{
  "type": "Feature",
  "properties": {
    "iso:country":"BE",
    "sg:address":"Korenlei 24",
    "sg:city":"Gent",
    "sg:classifiers":[
        {
            "category":"Restaurant",
            "type":"Food & Drink"
        }
    ],
    "sg:phone":"+32 9 225 89 02",
    "sg:postcode":"9000",
    "sg:province":"Oost-Vlaanderen",
    "wof:name":"The Gost",
    "wof:placetype":"venue"
},
  "geometry": {"coordinates":[3.7201290131,51.0539054871],"type":"Point"}
}