{
  "type": "Feature",
  "properties": {
    "addr:full":"Brusselsesteenweg 31 Edingen/enghien Hainaut 7850",
    "addr:housenumber":"31",
    "addr:postcode":"7850",
    "addr:street":"Brusselsesteenweg",
    "iso:country":"BE",
    "sg:address":"Brusselsesteenweg 31",
    "sg:city":"Edingen/enghien",
    "sg:orig_category":"Kapsalons",
    "sg:phone":"+32 2 395 85 23",
    "sg:postcode":"7850",
    "sg:province":"Hainaut",
    "wof:name":"Sylvie (coiffure)",
    "wof:placetype":"venue"
},
  "geometry": {"coordinates":[4.0961170197,50.6919212341],"type":"Point"}
}