{
  "type": "Feature",
  "properties": {
    "addr:full":"Keltenlaan 37 Etterbeek/etterbeek Bruxelles-Capitale 1040",
    "addr:housenumber":"37",
    "addr:postcode":"1040",
    "addr:street":"Keltenlaan",
    "iso:country":"BE",
    "sg:address":"Keltenlaan 37",
    "sg:city":"Etterbeek/etterbeek",
    "sg:classifiers":[
        {
            "category":"Fast Food",
            "type":"Food & Drink"
        }
    ],
    "sg:phone":"+32 2 734 76 99",
    "sg:postcode":"1040",
    "sg:province":"Bruxelles-Capitale",
    "sg:tags":[
        "meeneem",
        "restaurant"
    ],
    "wof:name":"Ellinikon",
    "wof:placetype":"venue"
},
  "geometry": {"coordinates":[4.3971538544,50.8381004333],"type":"Point"}
}