{
  "type": "Feature",
  "properties": {
    "addr:full":"Rue De L'yser 24 Namur (vedrin - Daussoulx) Namur 5020",
    "addr:housenumber":"24",
    "addr:postcode":"5020",
    "addr:street":"Rue De L'Yser",
    "iso:country":"BE",
    "sg:address":"Rue De L'yser 24",
    "sg:city":"Namur (vedrin - Daussoulx)",
    "sg:classifiers":[
        {
            "category":"Building & Trades",
            "subcategory":"Construction",
            "type":"Services"
        }
    ],
    "sg:phone":"+32 81 21 23 05",
    "sg:postcode":"5020",
    "sg:province":"Namur",
    "sg:tags":[
        "installation",
        "-",
        "central",
        "heating"
    ],
    "wof:name":"Collard Sprl",
    "wof:placetype":"venue"
},
  "geometry": {"coordinates":[4.8874487877,50.4908370972],"type":"Point"}
}