{
  "type": "Feature",
  "properties": {
    "iso:country":"BE",
    "sg:address":"Boulevard Du Coq 55",
    "sg:city":"La Louviere",
    "sg:orig_category":"Elektrische installaties voor woningen",
    "sg:phone":"+32 64 21 65 30",
    "sg:postcode":"7100",
    "sg:province":"Hainaut",
    "wof:name":"Giuseppe Milioto",
    "wof:placetype":"venue"
},
  "geometry": {"coordinates":[4.1850848198,50.4748649597],"type":"Point"}
}