{
  "type": "Feature",
  "properties": {
    "addr:full":"Drogenbroodstraat 3 Aalter Oost-Vlaanderen 9880",
    "addr:housenumber":"3",
    "addr:postcode":"9880",
    "addr:street":"Drogenbroodstraat",
    "iso:country":"BE",
    "sg:address":"Drogenbroodstraat 3",
    "sg:city":"Aalter",
    "sg:orig_category":"Artsen and specialisten",
    "sg:phone":"+32 9 374 25 70",
    "sg:postcode":"9880",
    "sg:province":"Oost-Vlaanderen",
    "wof:name":"Christian Demuynck",
    "wof:placetype":"venue"
},
  "geometry": {"coordinates":[3.4466791153,51.0939216614],"type":"Point"}
}