{
  "type": "Feature",
  "properties": {
    "addr:full":"Aartrijkestraat 70 Torhout West-Vlaanderen 8820",
    "addr:housenumber":"70",
    "addr:postcode":"8820",
    "addr:street":"Aartrijkestraat",
    "iso:country":"BE",
    "sg:address":"Aartrijkestraat 70",
    "sg:city":"Torhout",
    "sg:orig_category":"Plomberie, chauffage and installations sanitaires",
    "sg:phone":"+32 50 22 19 57",
    "sg:postcode":"8820",
    "sg:province":"West-Vlaanderen",
    "wof:name":"Baekelandt Noel",
    "wof:placetype":"venue"
},
  "geometry": {"coordinates":[3.0992159843,51.0729942322],"type":"Point"}
}