{
  "type": "Feature",
  "properties": {
    "iso:country":"BE",
    "sg:address":"Rue Du Grand Central 8",
    "sg:city":"Charleroi",
    "sg:classifiers":[
        {
            "category":"Shopping",
            "subcategory":"Computers & Home Electronics",
            "type":"Retail Goods"
        }
    ],
    "sg:phone":"+32 71 32 12 78",
    "sg:postcode":"6000",
    "sg:province":"Hainaut",
    "sg:tags":[
        "-",
        "typewriter"
    ],
    "wof:name":"Brother-remtech",
    "wof:placetype":"venue"
},
  "geometry": {"coordinates":[4.4378709793,50.4111251831],"type":"Point"}
}