{
  "type": "Feature",
  "properties": {
    "iso:country":"BE",
    "sg:address":"Gistelse Steenweg 29",
    "sg:city":"Brugge",
    "sg:orig_category":"Boucheries",
    "sg:phone":"+32 50 38 65 41",
    "sg:postcode":"8200",
    "sg:province":"West-Vlaanderen",
    "wof:name":"Slagerij Jobo",
    "wof:placetype":"venue"
},
  "geometry": {"coordinates":[3.2084219456,51.203666687],"type":"Point"}
}