{
  "type": "Feature",
  "properties": {
    "addr:full":"Neerveldstraat 45 Opwijk Vlaams-Brabant 1745",
    "addr:housenumber":"45",
    "addr:postcode":"1745",
    "addr:street":"Neerveldstraat",
    "iso:country":"BE",
    "sg:address":"Neerveldstraat 45",
    "sg:city":"Opwijk",
    "sg:orig_category":"Instituts de beaut\u00e9",
    "sg:phone":"+32 52 35 87 07",
    "sg:postcode":"1745",
    "sg:province":"Vlaams-Brabant",
    "wof:name":"Orchidee",
    "wof:placetype":"venue"
},
  "geometry": {"coordinates":[4.1863222122,50.9769058228],"type":"Point"}
}