{
  "type": "Feature",
  "properties": {
    "addr:full":"Rue De La Chapelle 86 Verviers Li\u00e8ge 4800",
    "addr:housenumber":"86",
    "addr:postcode":"4800",
    "addr:street":"Rue De La Chapelle",
    "iso:country":"BE",
    "sg:address":"Rue De La Chapelle 86",
    "sg:city":"Verviers",
    "sg:classifiers":[
        {
            "category":"Shopping",
            "subcategory":"Crafts & Fabrics",
            "type":"Retail Goods"
        }
    ],
    "sg:phone":"+32 87 31 21 36",
    "sg:postcode":"4800",
    "sg:province":"Li\u00e8ge",
    "sg:tags":[
        "silk",
        "-"
    ],
    "wof:name":"Belgorient-cocoon's",
    "wof:placetype":"venue"
},
  "geometry": {"coordinates":[5.8594508171,50.5917663574],"type":"Point"}
}