{
  "type": "Feature",
  "properties": {
    "addr:full":"Abdijstraat 95 Oudenaarde Oost-Vlaanderen 9700",
    "addr:housenumber":"95",
    "addr:postcode":"9700",
    "addr:street":"Abdijstraat",
    "iso:country":"BE",
    "sg:address":"Abdijstraat 95",
    "sg:city":"Oudenaarde",
    "sg:classifiers":[
        {
            "category":"Insurance",
            "subcategory":"Insurance Agent",
            "type":"Services"
        }
    ],
    "sg:phone":"+32 55 31 00 77",
    "sg:postcode":"9700",
    "sg:province":"Oost-Vlaanderen",
    "sg:tags":[
        "broker"
    ],
    "wof:name":"Groep Assurfin Nv",
    "wof:placetype":"venue"
},
  "geometry": {"coordinates":[3.6337730885,50.859664917],"type":"Point"}
}