{
  "type": "Feature",
  "properties": {
    "iso:country":"BE",
    "sg:address":"Rue De La Station 4",
    "sg:city":"Thimister-clermont",
    "sg:orig_category":"Boekhouders",
    "sg:phone":"+32 87 44 51 42",
    "sg:postcode":"4890",
    "sg:province":"Li\u00e8ge",
    "wof:name":"Fabrice Royen",
    "wof:placetype":"venue"
},
  "geometry": {"coordinates":[5.8673171997,50.6532402039],"type":"Point"}
}