{
  "type": "Feature",
  "properties": {
    "iso:country":"BE",
    "sg:address":"Rue Emile Carlier 32",
    "sg:city":"Bernissart (blaton)",
    "sg:classifiers":[
        {
            "category":"Health Services",
            "subcategory":"Health Practitioner",
            "type":"Services"
        }
    ],
    "sg:phone":"+32 69 56 10 32",
    "sg:postcode":"7321",
    "sg:province":"Hainaut",
    "sg:tags":[
        "physiotherapist"
    ],
    "wof:name":"Ilijas D",
    "wof:placetype":"venue"
},
  "geometry": {"coordinates":[3.6661140919,50.4984169006],"type":"Point"}
}