{
  "type": "Feature",
  "properties": {
    "addr:full":"Place Des Combattants 11 Lessines (ogy) Hainaut 7862",
    "addr:housenumber":"11",
    "addr:postcode":"7862",
    "addr:street":"Place Des Combattants",
    "iso:country":"BE",
    "sg:address":"Place Des Combattants 11",
    "sg:city":"Lessines (ogy)",
    "sg:classifiers":[
        {
            "category":"Freight",
            "type":"Transportation"
        }
    ],
    "sg:phone":"+32 68 44 96 43",
    "sg:postcode":"7862",
    "sg:province":"Hainaut",
    "sg:tags":[
        "-",
        "transport"
    ],
    "wof:name":"Teletrans",
    "wof:placetype":"venue"
},
  "geometry": {"coordinates":[3.7811019421,50.7205734253],"type":"Point"}
}