{
  "type": "Feature",
  "properties": {
    "iso:country":"BE",
    "sg:address":"Rue De Rolleghem 171",
    "sg:city":"Mouscron",
    "sg:classifiers":[
        {
            "category":"Manufacturing",
            "subcategory":"Wood Products",
            "type":"Manufacturing & Wholesale Goods"
        }
    ],
    "sg:phone":"+32 56 33 17 00",
    "sg:postcode":"7700",
    "sg:province":"Hainaut",
    "sg:tags":[
        "turning",
        "carving"
    ],
    "wof:name":"De Deurwaerder G",
    "wof:placetype":"venue"
},
  "geometry": {"coordinates":[3.2145800591,50.7437934875],"type":"Point"}
}