{
  "type": "Feature",
  "properties": {
    "iso:country":"BE",
    "sg:address":"Romain Steppestraat 97",
    "sg:city":"Sint-amands",
    "sg:classifiers":[
        {
            "category":"Shopping",
            "subcategory":"Jewelry",
            "type":"Retail Goods"
        }
    ],
    "sg:phone":"+32 52 33 13 88",
    "sg:postcode":"2890",
    "sg:province":"Antwerpen",
    "sg:tags":[
        "jeweller",
        "-"
    ],
    "wof:name":"A En A",
    "wof:placetype":"venue"
},
  "geometry": {"coordinates":[4.2039690018,51.0551147461],"type":"Point"}
}