{
  "type": "Feature",
  "properties": {
    "iso:country":"BE",
    "sg:address":"Rue De Marche 159",
    "sg:city":"Bastogne",
    "sg:orig_category":"Entretien and r\u00e9parations de voitures. Stations-service and carburants. Combustibles",
    "sg:phone":"+32 61 21 12 20",
    "sg:postcode":"6600",
    "sg:province":"Luxembourg",
    "wof:name":"Station De Renval",
    "wof:placetype":"venue"
},
  "geometry": {"coordinates":[5.6953701973,50.0022277832],"type":"Point"}
}