{
  "type": "Feature",
  "properties": {
    "iso:country":"BE",
    "sg:address":"Het Moer 14",
    "sg:city":"Zoersel",
    "sg:orig_category":"Travaux d\u00b4installation divers",
    "sg:phone":"+32 3 385 37 59",
    "sg:postcode":"2980",
    "sg:province":"Antwerpen",
    "wof:name":"Afspanning Driesen",
    "wof:placetype":"venue"
},
  "geometry": {"coordinates":[4.6652531624,51.2637634277],"type":"Point"}
}