{
  "type": "Feature",
  "properties": {
    "addr:full":"Boulevard Edmond Machtens 130 Sint-jans-molenbeek/molenbeek- Bruxelles-Capitale 1080",
    "addr:housenumber":"130",
    "addr:postcode":"1080",
    "addr:street":"Boulevard Edmond Machtens;Molenbeek",
    "iso:country":"BE",
    "sg:address":"Boulevard Edmond Machtens 130",
    "sg:city":"Sint-jans-molenbeek/molenbeek-",
    "sg:orig_category":"Banques and organismes de cr\u00e9dit",
    "sg:phone":"+32 2 410 53 10",
    "sg:postcode":"1080",
    "sg:province":"Bruxelles-Capitale",
    "wof:name":"Fortis",
    "wof:placetype":"venue"
},
  "geometry": {"coordinates":[4.309278965,50.8509254456],"type":"Point"}
}