{
  "type": "Feature",
  "properties": {
    "addr:full":"Molenstraat 44 Oudenaarde Oost-Vlaanderen 9700",
    "addr:housenumber":"44",
    "addr:postcode":"9700",
    "addr:street":"Molenstraat",
    "iso:country":"BE",
    "sg:address":"Molenstraat 44",
    "sg:city":"Oudenaarde",
    "sg:orig_category":"Catering and organisatie van feesten Fast food and meeneem restaurants Restaurants Ruimtes voor conf",
    "sg:phone":"+32 55 31 17 10",
    "sg:postcode":"9700",
    "sg:province":"Oost-Vlaanderen",
    "wof:name":"Molenhuis",
    "wof:placetype":"venue"
},
  "geometry": {"coordinates":[3.6122500896,50.8751716614],"type":"Point"}
}