{
  "type": "Feature",
  "properties": {
    "addr:full":"Bergdal 54 Hooglede (gits) West-Vlaanderen 8830",
    "addr:housenumber":"54",
    "addr:postcode":"8830",
    "addr:street":"Bergdal",
    "iso:country":"BE",
    "sg:address":"Bergdal 54",
    "sg:city":"Hooglede (gits)",
    "sg:classifiers":[
        {
            "category":"Building & Trades",
            "subcategory":"Pest Control",
            "type":"Services"
        }
    ],
    "sg:phone":"+32 51 25 27 19",
    "sg:postcode":"8830",
    "sg:province":"West-Vlaanderen",
    "sg:tags":[
        "painting",
        "contractor"
    ],
    "wof:name":"David C",
    "wof:placetype":"venue"
},
  "geometry": {"coordinates":[3.1050970554,50.9959907532],"type":"Point"}
}