{
  "type": "Feature",
  "properties": {
    "addr:full":"Avenue Des Combattants 67 Gembloux-sur-orneau (gembloux) Namur 5030",
    "addr:housenumber":"67",
    "addr:postcode":"5030",
    "addr:street":"Avenue Des Combattants;Namur",
    "iso:country":"BE",
    "sg:address":"Avenue Des Combattants 67",
    "sg:city":"Gembloux-sur-orneau (gembloux)",
    "sg:classifiers":[
        {
            "category":"Health Services",
            "subcategory":"Doctor",
            "type":"Services"
        }
    ],
    "sg:phone":"+32 81 61 22 33",
    "sg:postcode":"5030",
    "sg:province":"Namur",
    "sg:tags":[
        "medicinephysicians",
        "surgeon"
    ],
    "wof:name":"Garnir J-j",
    "wof:placetype":"venue"
},
  "geometry": {"coordinates":[4.7018017769,50.5578994751],"type":"Point"}
}