{
  "type": "Feature",
  "properties": {
    "addr:full":"Wolvertemsesteenweg Grimbergen Vlaams-Brabant 1850",
    "addr:postcode":"1850",
    "addr:street":"Wolvertemsesteenweg",
    "iso:country":"BE",
    "sg:address":"Wolvertemsesteenweg",
    "sg:city":"Grimbergen",
    "sg:orig_category":"R\u00e9parations d'appareils \u00e9lectrom\u00e9nagers. Electrom\u00e9nager, t\u00e9l\u00e9visions and radios. Mat\u00e9riel de T\u00e9l\u00e9com",
    "sg:phone":"+32 2 269 52 82",
    "sg:postcode":"1850",
    "sg:province":"Vlaams-Brabant",
    "wof:name":"Kr\u00cbfel",
    "wof:placetype":"venue"
},
  "geometry": {"coordinates":[4.3479800224,50.9396781921],"type":"Point"}
}