{
  "type": "Feature",
  "properties": {
    "addr:full":"Rue Thiniheid 56 Verviers (stembert) Li\u00e8ge 4801",
    "addr:housenumber":"56",
    "addr:postcode":"4801",
    "addr:street":"Rue Thiniheid",
    "iso:country":"BE",
    "sg:address":"Rue Thiniheid 56",
    "sg:city":"Verviers (stembert)",
    "sg:classifiers":[
        {
            "category":"Social Services",
            "type":"Services"
        }
    ],
    "sg:phone":"+32 87 27 91 40",
    "sg:postcode":"4801",
    "sg:province":"Li\u00e8ge",
    "sg:tags":[
        "handicapped",
        "-"
    ],
    "wof:name":"Le Thiniheid Asbl",
    "wof:placetype":"venue"
},
  "geometry": {"coordinates":[5.8918118477,50.5852622986],"type":"Point"}
}