{
  "type": "Feature",
  "properties": {
    "iso:country":"BE",
    "sg:address":"Aalmoezenijestraat 66",
    "sg:city":"Oosterzele",
    "sg:orig_category":"Elektrische installaties voor woningen",
    "sg:phone":"+32 9 362 12 02",
    "sg:postcode":"9860",
    "sg:province":"Oost-Vlaanderen",
    "wof:name":"Fa. Piron-van Damme",
    "wof:placetype":"venue"
},
  "geometry": {"coordinates":[3.8022069931,50.9731254578],"type":"Point"}
}