{
  "type": "Feature",
  "properties": {
    "iso:country":"BE",
    "sg:address":"Haandorpweg 1",
    "sg:city":"Beveren (verrebroek)",
    "sg:classifiers":[
        {
            "category":"Utilities",
            "subcategory":"Fuel Oil & Lpg",
            "type":"Services"
        }
    ],
    "sg:phone":"+32 2 689 12 11",
    "sg:postcode":"9130",
    "sg:province":"Oost-Vlaanderen",
    "wof:name":"Chevron Phillips Chemicals International",
    "wof:placetype":"venue"
},
  "geometry": {"coordinates":[4.2173299789,51.2569503784],"type":"Point"}
}