{
  "type": "Feature",
  "properties": {
    "addr:full":"Vieille Route De Li\u00e8ge 91 Marche-en-famenne Luxembourg 6900",
    "addr:housenumber":"91",
    "addr:postcode":"6900",
    "addr:street":"Vieille Route De Lie\u0300Ge",
    "iso:country":"BE",
    "sg:address":"Vieille Route De Li\u00e8ge 91",
    "sg:city":"Marche-en-famenne",
    "sg:classifiers":[
        {
            "category":"Shopping",
            "subcategory":"Jewelry",
            "type":"Retail Goods"
        }
    ],
    "sg:phone":"+32 84 32 20 12",
    "sg:postcode":"6900",
    "sg:province":"Luxembourg",
    "sg:tags":[
        "-",
        "imitation"
    ],
    "wof:name":"Ecosource Scrl Scrl",
    "wof:placetype":"venue"
},
  "geometry": {"coordinates":[5.3433637619,50.2403144836],"type":"Point"}
}