{
  "type": "Feature",
  "properties": {
    "addr:full":"Rue Provinciale 59 Herstal (liers) Li\u00e8ge 4042",
    "addr:housenumber":"59",
    "addr:postcode":"4042",
    "addr:street":"Rue Provinciale",
    "iso:country":"BE",
    "sg:address":"Rue Provinciale 59",
    "sg:city":"Herstal (liers)",
    "sg:classifiers":[
        {
            "category":"Personal",
            "subcategory":"Beauty Salon",
            "type":"Services"
        }
    ],
    "sg:phone":"+32 4 278 25 24",
    "sg:postcode":"4042",
    "sg:province":"Li\u00e8ge",
    "sg:tags":[
        "lady",
        "-",
        "hairdressing"
    ],
    "wof:name":"Nad's Studio",
    "wof:placetype":"venue"
},
  "geometry": {"coordinates":[5.5636811256,50.6935806274],"type":"Point"}
}