{
  "type": "Feature",
  "properties": {
    "addr:full":"Rue De La Renaissance 1 Juprelle (voroux-lez-liers) Li\u00e8ge 4451",
    "addr:housenumber":"1",
    "addr:postcode":"4451",
    "addr:street":"Rue De La Renaissance;Voroux-Lez-Liers",
    "iso:country":"BE",
    "sg:address":"Rue De La Renaissance 1",
    "sg:city":"Juprelle (voroux-lez-liers)",
    "sg:classifiers":[
        {
            "category":"Real Estate",
            "subcategory":"Real Estate Services",
            "type":"Services"
        }
    ],
    "sg:phone":"+32 4 278 35 20",
    "sg:postcode":"4451",
    "sg:province":"Li\u00e8ge",
    "wof:name":"Batibaum Sa",
    "wof:placetype":"venue"
},
  "geometry": {"coordinates":[5.5561738014,50.6879310608],"type":"Point"}
}