{
  "type": "Feature",
  "properties": {
    "iso:country":"BE",
    "sg:address":"Eugeen Verelstlei 54",
    "sg:city":"Borsbeek",
    "sg:orig_category":"Secr\u00e9tariats sociaux",
    "sg:phone":"+32 3 321 02 05",
    "sg:postcode":"2150",
    "sg:province":"Antwerpen",
    "wof:name":"Sodiwe",
    "wof:placetype":"venue"
},
  "geometry": {"coordinates":[4.4935669899,51.1968383789],"type":"Point"}
}