{
  "type": "Feature",
  "properties": {
    "addr:full":"Rue Libotte 6 Li\u00c8ge Li\u00e8ge 4020",
    "addr:housenumber":"6",
    "addr:postcode":"4020",
    "addr:street":"Rue Libotte",
    "iso:country":"BE",
    "sg:address":"Rue Libotte 6",
    "sg:city":"Li\u00c8ge",
    "sg:orig_category":"M\u00e9decins and sp\u00e9cialistes",
    "sg:phone":"+32 4 342 34 84",
    "sg:postcode":"4020",
    "sg:province":"Li\u00e8ge",
    "wof:name":"Jean-daniel Degreef",
    "wof:placetype":"venue"
},
  "geometry": {"coordinates":[5.5798602104,50.6357078552],"type":"Point"}
}