{
  "type": "Feature",
  "properties": {
    "addr:full":"Rue De Joncret 44 Gerpinnes (acoz) Hainaut 6280",
    "addr:housenumber":"44",
    "addr:postcode":"6280",
    "addr:street":"Rue De Joncret",
    "iso:country":"BE",
    "sg:address":"Rue De Joncret 44",
    "sg:city":"Gerpinnes (acoz)",
    "sg:classifiers":[
        {
            "category":"Health Services",
            "subcategory":"Health Practitioner",
            "type":"Services"
        }
    ],
    "sg:phone":"+32 71 50 34 47",
    "sg:postcode":"6280",
    "sg:province":"Hainaut",
    "sg:tags":[
        "physiotherapist"
    ],
    "wof:name":"Delvigne France",
    "wof:placetype":"venue"
},
  "geometry": {"coordinates":[4.5133180618,50.3535842896],"type":"Point"}
}