{
  "type": "Feature",
  "properties": {
    "addr:full":"Rue Blaes 146 Brussel Bruxelles-Capitale 1000",
    "addr:housenumber":"146",
    "addr:postcode":"1000",
    "addr:street":"Rue Blaes",
    "iso:country":"BE",
    "sg:address":"Rue Blaes 146",
    "sg:city":"Brussel",
    "sg:orig_category":"Rev\u00eatements de sols and murs",
    "sg:phone":"+32 2 514 31 40",
    "sg:postcode":"1000",
    "sg:province":"Bruxelles-Capitale",
    "wof:name":"Reves D'art & D'orient Kilim",
    "wof:placetype":"venue"
},
  "geometry": {"coordinates":[4.3476009369,50.8377952576],"type":"Point"}
}