{
  "type": "Feature",
  "properties": {
    "iso:country":"BE",
    "sg:address":"Haerinckstraat 10",
    "sg:city":"Waregem",
    "sg:orig_category":"Tuinen",
    "sg:phone":"+32 56 60 83 22",
    "sg:postcode":"8790",
    "sg:province":"West-Vlaanderen",
    "wof:name":"Verhaeghe",
    "wof:placetype":"venue"
},
  "geometry": {"coordinates":[3.4314749241,50.8873558044],"type":"Point"}
}