{
  "type": "Feature",
  "properties": {
    "addr:full":"Sint-annaplein 4 Brugge West-Vlaanderen 8000",
    "addr:housenumber":"4",
    "addr:postcode":"8000",
    "addr:street":"Sint-Annaplein",
    "iso:country":"BE",
    "sg:address":"Sint-annaplein 4",
    "sg:city":"Brugge",
    "sg:orig_category":"Artiesten and kunstenaars",
    "sg:phone":"+32 50 33 42 90",
    "sg:postcode":"8000",
    "sg:province":"West-Vlaanderen",
    "wof:name":"Gilbert Swimberghe",
    "wof:placetype":"venue"
},
  "geometry": {"coordinates":[3.2315039635,51.2121315002],"type":"Point"}
}