{
  "type": "Feature",
  "properties": {
    "iso:country":"BE",
    "sg:address":"Chauss\u00e9e De Wavre 1314",
    "sg:city":"Bruxelles (auderghem)",
    "sg:orig_category":"Non-Classified Establishments",
    "sg:phone":"+32 2 672 14 36",
    "sg:postcode":"1160",
    "sg:province":"Bruxelles-Capitale",
    "wof:name":"Deco Ligot Sa",
    "wof:placetype":"venue"
},
  "geometry": {"coordinates":[4.4116768837,50.8201446533],"type":"Point"}
}