{
  "type": "Feature",
  "properties": {
    "addr:full":"Heirbaan 64 Mortsel Antwerpen 2640",
    "addr:housenumber":"64",
    "addr:postcode":"2640",
    "addr:street":"Heirbaan",
    "iso:country":"BE",
    "sg:address":"Heirbaan 64",
    "sg:city":"Mortsel",
    "sg:orig_category":"Autoverhuur",
    "sg:phone":"+32 3 440 69 05",
    "sg:postcode":"2640",
    "sg:province":"Antwerpen",
    "wof:name":"Fraikin",
    "wof:placetype":"venue"
},
  "geometry": {"coordinates":[4.4648799896,51.1793403625],"type":"Point"}
}