{
  "type": "Feature",
  "properties": {
    "addr:full":"Peperstraat 33 Riemst Limburg 3770",
    "addr:housenumber":"33",
    "addr:postcode":"3770",
    "addr:street":"Peperstraat",
    "iso:country":"BE",
    "sg:address":"Peperstraat 33",
    "sg:city":"Riemst",
    "sg:classifiers":[
        {
            "category":"Fast Food",
            "type":"Food & Drink"
        }
    ],
    "sg:phone":"+32 12 23 34 27",
    "sg:postcode":"3770",
    "sg:province":"Limburg",
    "sg:tags":[
        "\u00c0",
        "emporter",
        "restaurants"
    ],
    "wof:name":"Frituur 't Snekske",
    "wof:placetype":"venue"
},
  "geometry": {"coordinates":[5.5605869293,50.7912902832],"type":"Point"}
}