{
  "type": "Feature",
  "properties": {
    "addr:full":"Rue De Fr\u00e9gimont 5b Floreffe (floriffoux) Namur 5150",
    "addr:housenumber":"5b",
    "addr:postcode":"5150",
    "addr:street":"Rue De Fre\u0301Gimont",
    "iso:country":"BE",
    "sg:address":"Rue De Fr\u00e9gimont 5b",
    "sg:city":"Floreffe (floriffoux)",
    "sg:classifiers":[
        {
            "category":"Building & Trades",
            "subcategory":"Plumbing",
            "type":"Services"
        }
    ],
    "sg:phone":"+32 81 44 48 94",
    "sg:postcode":"5150",
    "sg:province":"Namur",
    "sg:tags":[
        "contractor"
    ],
    "wof:name":"Hobe R",
    "wof:placetype":"venue"
},
  "geometry": {"coordinates":[4.7707037926,50.4546508789],"type":"Point"}
}