{
  "type": "Feature",
  "properties": {
    "addr:full":"Boomkensstraat 190 Hasselt Limburg 3500",
    "addr:housenumber":"190",
    "addr:postcode":"3500",
    "addr:street":"Boomkensstraat",
    "iso:country":"BE",
    "sg:address":"Boomkensstraat 190",
    "sg:city":"Hasselt",
    "sg:classifiers":[
        {
            "category":"Personal",
            "subcategory":"Beauty Salon",
            "type":"Services"
        }
    ],
    "sg:phone":"+32 11 32 27 56",
    "sg:postcode":"3500",
    "sg:province":"Limburg",
    "sg:tags":[
        "lady",
        "-",
        "hairdressing"
    ],
    "wof:name":"Marie Therese",
    "wof:placetype":"venue"
},
  "geometry": {"coordinates":[5.3295550346,50.9217453003],"type":"Point"}
}