{
  "type": "Feature",
  "properties": {
    "addr:full":"Pauwhoflaan 29 Bredene West-Vlaanderen 8450",
    "addr:housenumber":"29",
    "addr:postcode":"8450",
    "addr:street":"Pauwhoflaan",
    "iso:country":"BE",
    "sg:address":"Pauwhoflaan 29",
    "sg:city":"Bredene",
    "sg:orig_category":"Woningbouw",
    "sg:phone":"+32 59 32 02 76",
    "sg:postcode":"8450",
    "sg:province":"West-Vlaanderen",
    "wof:name":"Seynaeve Peter",
    "wof:placetype":"venue"
},
  "geometry": {"coordinates":[2.9569940567,51.2407875061],"type":"Point"}
}