{
  "type": "Feature",
  "properties": {
    "addr:full":"Sinaaidorp 17 Sinaai Oost-Vlaanderen 9112",
    "addr:housenumber":"17",
    "addr:postcode":"9112",
    "addr:street":"Sinaaidorp;Oost-Vlaanderen",
    "iso:country":"BE",
    "sg:address":"Sinaaidorp 17",
    "sg:city":"Sinaai",
    "sg:classifiers":[
        {
            "category":"Retail",
            "subcategory":"Car Wash",
            "type":"Services"
        }
    ],
    "sg:postcode":"9112",
    "sg:province":"Oost-Vlaanderen",
    "sg:tags":[
        "automobile",
        "-",
        "washing",
        "truck",
        "equipment"
    ],
    "wof:name":"Auto Cleaning Service Pro-wash",
    "wof:placetype":"venue"
},
  "geometry": {"coordinates":[4.0390257835,51.1573677063],"type":"Point"}
}