{
  "type": "Feature",
  "properties": {
    "iso:country":"BE",
    "sg:address":"Rue Jules Coisman 18a",
    "sg:city":"Beauvechain (hamme-mille)",
    "sg:classifiers":[
        {
            "category":"Retail",
            "subcategory":"Repair Shop",
            "type":"Services"
        }
    ],
    "sg:phone":"+32 10 86 05 58",
    "sg:postcode":"1320",
    "sg:province":"Brabant Wallon",
    "sg:tags":[
        "-",
        "clothing",
        "alteration"
    ],
    "wof:name":"Coup D'oeil",
    "wof:placetype":"venue"
},
  "geometry": {"coordinates":[4.7457208633,50.7931671143],"type":"Point"}
}