{
  "type": "Feature",
  "properties": {
    "iso:country":"BE",
    "sg:address":"Bruul 21",
    "sg:city":"Mechelen",
    "sg:orig_category":"Brood, gebak and snoepgoed",
    "sg:phone":"+32 15 21 92 42",
    "sg:postcode":"2800",
    "sg:province":"Antwerpen",
    "wof:name":"Van De Kerkhove J.",
    "wof:placetype":"venue"
},
  "geometry": {"coordinates":[4.4810628891,51.0266952515],"type":"Point"}
}