{
  "type": "Feature",
  "properties": {
    "addr:full":"Route De Frasnes 132a Mainvault Hainaut 7812",
    "addr:housenumber":"132a",
    "addr:postcode":"7812",
    "addr:street":"Route De Frasnes;Hainaut",
    "iso:country":"BE",
    "sg:address":"Route De Frasnes 132a",
    "sg:city":"Mainvault",
    "sg:classifiers":[
        {
            "category":"Cafe",
            "type":"Food & Drink"
        }
    ],
    "sg:phone":"+32 475 52 28 59",
    "sg:postcode":"7812",
    "sg:province":"Hainaut",
    "sg:tags":[
        "caf\u00e9s"
    ],
    "wof:name":"Le Centaure",
    "wof:placetype":"venue"
},
  "geometry": {"coordinates":[3.6734309196,50.6524047852],"type":"Point"}
}