{
  "type": "Feature",
  "properties": {
    "iso:country":"BE",
    "sg:address":"Frankrijklei 57b6",
    "sg:city":"Antwerpen",
    "sg:orig_category":"Administration d'immeubles",
    "sg:phone":"+32 3 231 25 52",
    "sg:postcode":"2000",
    "sg:province":"Antwerpen",
    "wof:name":"Eric Verleysen",
    "wof:placetype":"venue"
},
  "geometry": {"coordinates":[4.4146680832,51.2160186768],"type":"Point"}
}