{
  "type": "Feature",
  "properties": {
    "addr:full":"Grote Steenweg 97 Lede Oost-Vlaanderen 9340",
    "addr:housenumber":"97",
    "addr:postcode":"9340",
    "addr:street":"Grote Steenweg",
    "iso:country":"BE",
    "sg:address":"Grote Steenweg 97",
    "sg:city":"Lede",
    "sg:orig_category":"Rev\u00eatements de sols and murs. Traitement and fa\u00e7onnage de la pierre",
    "sg:phone":"+32 9 369 59 65",
    "sg:postcode":"9340",
    "sg:province":"Oost-Vlaanderen",
    "wof:name":"Beurms Dirk",
    "wof:placetype":"venue"
},
  "geometry": {"coordinates":[4.0051641464,50.9625015259],"type":"Point"}
}