{
  "type": "Feature",
  "properties": {
    "iso:country":"BE",
    "sg:address":"Luikersteenweg 406",
    "sg:city":"Tongeren",
    "sg:orig_category":"Antiek",
    "sg:phone":"+32 12 23 40 50",
    "sg:postcode":"3700",
    "sg:province":"Limburg",
    "wof:name":"Yvon Vanseer",
    "wof:placetype":"venue"
},
  "geometry": {"coordinates":[5.4735560417,50.7634391785],"type":"Point"}
}