{
  "type": "Feature",
  "properties": {
    "addr:full":"Zandbergerstraat 22 Maaseik Limburg 3680",
    "addr:housenumber":"22",
    "addr:postcode":"3680",
    "addr:street":"Zandbergerstraat",
    "iso:country":"BE",
    "sg:address":"Zandbergerstraat 22",
    "sg:city":"Maaseik",
    "sg:orig_category":"Instituts de beaut\u00e9",
    "sg:phone":"+32 89 86 44 02",
    "sg:postcode":"3680",
    "sg:province":"Limburg",
    "wof:name":"Instituut Ann",
    "wof:placetype":"venue"
},
  "geometry": {"coordinates":[5.791285038,51.0954208374],"type":"Point"}
}