{
  "type": "Feature",
  "properties": {
    "iso:country":"BE",
    "sg:address":"Rue Victor Gondat 9",
    "sg:city":"La Louvi\u00e8re (saint-vaast)",
    "sg:classifiers":[
        {
            "category":"Bars & Pubs",
            "type":"Food & Drink"
        }
    ],
    "sg:phone":"+32 64 21 23 51",
    "sg:postcode":"7100",
    "sg:province":"Hainaut",
    "wof:name":"Jo (chez)",
    "wof:placetype":"venue"
},
  "geometry": {"coordinates":[4.2004199028,50.4743995667],"type":"Point"}
}