{
  "type": "Feature",
  "properties": {
    "iso:country":"BE",
    "sg:address":"Bergense Steenweg 988",
    "sg:city":"Anderlecht/anderlecht",
    "sg:orig_category":"Artsen and specialisten Schoenen",
    "sg:phone":"+32 2 521 14 02",
    "sg:postcode":"1070",
    "sg:province":"Bruxelles-Capitale",
    "wof:name":"Orthopedie Wieme",
    "wof:placetype":"venue"
},
  "geometry": {"coordinates":[4.2967400551,50.8246002197],"type":"Point"}
}