{
  "type": "Feature",
  "properties": {
    "iso:country":"BE",
    "sg:address":"Bushaye 278",
    "sg:city":"Aubel",
    "sg:orig_category":"Beheer onroerend goed",
    "sg:phone":"+32 87 68 67 66",
    "sg:postcode":"4880",
    "sg:province":"Li\u00e8ge",
    "wof:name":"Immo-wache",
    "wof:placetype":"venue"
},
  "geometry": {"coordinates":[5.8202857971,50.6979827881],"type":"Point"}
}