{
  "type": "Feature",
  "properties": {
    "addr:full":"Rue De Messancy 50 Aubange Luxembourg 6790",
    "addr:housenumber":"50",
    "addr:postcode":"6790",
    "addr:street":"Rue De Messancy",
    "iso:country":"BE",
    "sg:address":"Rue De Messancy 50",
    "sg:city":"Aubange",
    "sg:orig_category":"Verbruikerskredietinstellingen",
    "sg:phone":"+32 63 38 01 01",
    "sg:postcode":"6790",
    "sg:province":"Luxembourg",
    "wof:name":"Cr\u00c9dit Du Luxembourg",
    "wof:placetype":"venue"
},
  "geometry": {"coordinates":[5.8042750359,49.5730247498],"type":"Point"}
}