{
  "type": "Feature",
  "properties": {
    "addr:full":"Grote Markt 40 Ronse/renaix Oost-Vlaanderen 9600",
    "addr:housenumber":"40",
    "addr:postcode":"9600",
    "addr:street":"Grote Markt",
    "iso:country":"BE",
    "sg:address":"Grote Markt 40",
    "sg:city":"Ronse/renaix",
    "sg:classifiers":[
        {
            "category":"Travel",
            "subcategory":"Hotels & Motels",
            "type":"Entertainment"
        }
    ],
    "sg:phone":"+32 55 21 38 46",
    "sg:postcode":"9600",
    "sg:province":"Oost-Vlaanderen",
    "sg:tags":[
        "restaurant"
    ],
    "wof:name":"Hotel Alfa",
    "wof:placetype":"venue"
},
  "geometry": {"coordinates":[3.5992999077,50.7470397949],"type":"Point"}
}