{
  "type": "Feature",
  "properties": {
    "addr:full":"Peerderbaan 49 Box 4 Hechtel-eksel (hechtel) Limburg 3940",
    "addr:housenumber":"49;4",
    "addr:postcode":"3940",
    "addr:street":"Peerderbaan;Box",
    "iso:country":"BE",
    "sg:address":"Peerderbaan 49 Box 4",
    "sg:city":"Hechtel-eksel (hechtel)",
    "sg:classifiers":[
        {
            "category":"Professional",
            "subcategory":"Accounting & Tax Preparation",
            "type":"Services"
        }
    ],
    "sg:phone":"+32 11 73 56 25",
    "sg:postcode":"3940",
    "sg:province":"Limburg",
    "sg:tags":[
        "bookkeeper"
    ],
    "wof:name":"Huybrechts R",
    "wof:placetype":"venue"
},
  "geometry": {"coordinates":[5.364795208,51.1255340576],"type":"Point"}
}