{
  "type": "Feature",
  "properties": {
    "addr:full":"Watertorenlaan 77ba Zaventem Vlaams-Brabant 1930",
    "addr:housenumber":"77ba",
    "addr:postcode":"1930",
    "addr:street":"Watertorenlaan",
    "iso:country":"BE",
    "sg:address":"Watertorenlaan 77ba",
    "sg:city":"Zaventem",
    "sg:orig_category":"M\u00e9decins and sp\u00e9cialistes",
    "sg:phone":"+32 2 720 65 26",
    "sg:postcode":"1930",
    "sg:province":"Vlaams-Brabant",
    "wof:name":"Martine Van Audenhaeghe",
    "wof:placetype":"venue"
},
  "geometry": {"coordinates":[4.4757761955,50.8864898682],"type":"Point"}
}