{
  "type": "Feature",
  "properties": {
    "addr:full":"Vossenstraat 63 Melle Oost-Vlaanderen 9090",
    "addr:housenumber":"63",
    "addr:postcode":"9090",
    "addr:street":"Vossenstraat",
    "iso:country":"BE",
    "sg:address":"Vossenstraat 63",
    "sg:city":"Melle",
    "sg:classifiers":[
        {
            "category":"Arts & Performance",
            "subcategory":"Music",
            "type":"Entertainment"
        }
    ],
    "sg:phone":"+32 475 63 08 07",
    "sg:postcode":"9090",
    "sg:province":"Oost-Vlaanderen",
    "sg:tags":[
        "disc-jockeys"
    ],
    "wof:name":"Star Music",
    "wof:placetype":"venue"
},
  "geometry": {"coordinates":[3.7941710949,50.9993629456],"type":"Point"}
}