{
  "type": "Feature",
  "properties": {
    "iso:country":"BE",
    "sg:address":"Made Straat 2",
    "sg:city":"Ramsel",
    "sg:orig_category":"Huisdieren and benodigdheden Royal Canin Sport- and kampeermateriaal",
    "sg:phone":"+32 16 57 11 91",
    "sg:postcode":"2230",
    "sg:province":"Antwerpen",
    "wof:name":"Ps.ost",
    "wof:placetype":"venue"
},
  "geometry": {"coordinates":[4.822906971,51.0200119019],"type":"Point"}
}