{
  "type": "Feature",
  "properties": {
    "addr:full":"Groenstraat 111 Zelzate Oost-Vlaanderen 9060",
    "addr:housenumber":"111",
    "addr:postcode":"9060",
    "addr:street":"Groenstraat",
    "iso:country":"BE",
    "sg:address":"Groenstraat 111",
    "sg:city":"Zelzate",
    "sg:orig_category":"D\u00e9chets and d\u00e9bris Gr",
    "sg:phone":"+32 9 345 50 37",
    "sg:postcode":"9060",
    "sg:province":"Oost-Vlaanderen",
    "wof:name":"Roland Bruggeman",
    "wof:placetype":"venue"
},
  "geometry": {"coordinates":[3.8039228916,51.1976585388],"type":"Point"}
}