{
  "type": "Feature",
  "properties": {
    "addr:full":"Grand Place 39 Paliseul Luxembourg 6850",
    "addr:housenumber":"39",
    "addr:postcode":"6850",
    "addr:street":"Grand Place",
    "iso:country":"BE",
    "sg:address":"Grand Place 39",
    "sg:city":"Paliseul",
    "sg:classifiers":[
        {
            "category":"Shopping",
            "subcategory":"Bridal",
            "type":"Retail Goods"
        }
    ],
    "sg:phone":"+32 61 53 30 25",
    "sg:postcode":"6850",
    "sg:province":"Luxembourg",
    "sg:tags":[
        "list",
        "-",
        "present",
        "wedding"
    ],
    "wof:name":"Maison Douret",
    "wof:placetype":"venue"
},
  "geometry": {"coordinates":[5.1369299889,49.9039382935],"type":"Point"}
}