{
  "type": "Feature",
  "properties": {
    "addr:full":"Molenstraat 61 Waasmunster Oost-Vlaanderen 9250",
    "addr:housenumber":"61",
    "addr:postcode":"9250",
    "addr:street":"Molenstraat",
    "iso:country":"BE",
    "sg:address":"Molenstraat 61",
    "sg:city":"Waasmunster",
    "sg:classifiers":[
        {
            "category":"Real Estate",
            "subcategory":"Real Estate Services",
            "type":"Services"
        }
    ],
    "sg:phone":"+32 52 46 15 64",
    "sg:postcode":"9250",
    "sg:province":"Oost-Vlaanderen",
    "wof:name":"Molenheide",
    "wof:placetype":"venue"
},
  "geometry": {"coordinates":[4.0906248093,51.1170082092],"type":"Point"}
}