{
  "type": "Feature",
  "properties": {
    "addr:full":"Werkenplein 6 Kortemark West-Vlaanderen 8610",
    "addr:housenumber":"6",
    "addr:postcode":"8610",
    "addr:street":"Werkenplein",
    "iso:country":"BE",
    "sg:address":"Werkenplein 6",
    "sg:city":"Kortemark",
    "sg:orig_category":"Metaalbehandeling and -bekleding",
    "sg:phone":"+32 51 56 77 13",
    "sg:postcode":"8610",
    "sg:province":"West-Vlaanderen",
    "wof:name":"Albrecht",
    "wof:placetype":"venue"
},
  "geometry": {"coordinates":[3.0018539429,51.0261573792],"type":"Point"}
}