{
  "type": "Feature",
  "properties": {
    "addr:full":"Morenhoekstraat 18b Rumst Antwerpen 2840",
    "addr:housenumber":"18b",
    "addr:postcode":"2840",
    "addr:street":"Morenhoekstraat",
    "iso:country":"BE",
    "sg:address":"Morenhoekstraat 18b",
    "sg:city":"Rumst",
    "sg:classifiers":[
        {
            "category":"Farming",
            "subcategory":"Crops",
            "type":"Manufacturing & Wholesale Goods"
        }
    ],
    "sg:phone":"+32 15 31 68 01",
    "sg:postcode":"2840",
    "sg:province":"Antwerpen",
    "sg:tags":[
        "vegetable",
        "fruit",
        "-",
        "grower"
    ],
    "wof:name":"Kennes L",
    "wof:placetype":"venue"
},
  "geometry": {"coordinates":[4.447892189,51.0878562927],"type":"Point"}
}