{
  "type": "Feature",
  "properties": {
    "iso:country":"BE",
    "sg:address":"Place Nestor-outer 4",
    "sg:city":"Virton",
    "sg:orig_category":"Fournitures de bureau. Journaux. Librairies. Tabac",
    "sg:phone":"+32 63 57 81 34",
    "sg:postcode":"6760",
    "sg:province":"Luxembourg",
    "wof:name":"Centre De Presse",
    "wof:placetype":"venue"
},
  "geometry": {"coordinates":[5.5324621201,49.5673751831],"type":"Point"}
}