{
  "type": "Feature",
  "properties": {
    "iso:country":"BE",
    "sg:address":"Aarselestraat 25",
    "sg:city":"Tielt (aarsele)",
    "sg:classifiers":[
        {
            "category":"Professional",
            "subcategory":"Accounting & Tax Preparation",
            "type":"Services"
        }
    ],
    "sg:phone":"+32 51 63 56 93",
    "sg:postcode":"8700",
    "sg:province":"West-Vlaanderen",
    "sg:tags":[
        "bookkeeper"
    ],
    "wof:name":"Keerman C",
    "wof:placetype":"venue"
},
  "geometry": {"coordinates":[3.421900034,50.9940452576],"type":"Point"}
}