{
  "type": "Feature",
  "properties": {
    "iso:country":"BE",
    "sg:address":"Cit\u00e9 Nouvelle 18",
    "sg:city":"Anderlues",
    "sg:classifiers":[
        {
            "category":"Home & Garden",
            "subcategory":"Building Materials",
            "type":"Retail Goods"
        }
    ],
    "sg:phone":"+32 71 52 81 26",
    "sg:postcode":"6150",
    "sg:province":"Hainaut",
    "sg:tags":[
        "granite",
        "stone",
        "natural",
        "marble"
    ],
    "wof:name":"Graniti\u00e8re",
    "wof:placetype":"venue"
},
  "geometry": {"coordinates":[4.2660999298,50.4147605896],"type":"Point"}
}