{
  "type": "Feature",
  "properties": {
    "iso:country":"BE",
    "sg:address":"Avenue De L'informatique 9b",
    "sg:city":"Alleur",
    "sg:classifiers":[
        {
            "category":"Banks & Credit Unions",
            "subcategory":"Investment Brokerage",
            "type":"Services"
        }
    ],
    "sg:phone":"+32 4 239 91 50",
    "sg:postcode":"4432",
    "sg:province":"Li\u00e8ge",
    "sg:tags":[
        "processing",
        "data",
        "system"
    ],
    "wof:name":"N.s.i. Nouvelles Solutions Informatiques S.a.",
    "wof:placetype":"venue"
},
  "geometry": {"coordinates":[5.5307779312,50.673789978],"type":"Point"}
}