{
  "type": "Feature",
  "properties": {
    "iso:country":"BE",
    "sg:address":"Snikbergstraat 156",
    "sg:city":"Dilbeek",
    "sg:orig_category":"Electrom\u00e9nager, t\u00e9l\u00e9visions and radios",
    "sg:phone":"+32 2 569 42 83",
    "sg:postcode":"1701",
    "sg:province":"Vlaams-Brabant",
    "wof:name":"Luc Aerssens",
    "wof:placetype":"venue"
},
  "geometry": {"coordinates":[4.2229070663,50.8437232971],"type":"Point"}
}