{
  "type": "Feature",
  "properties": {
    "iso:country":"BE",
    "sg:address":"Kempische Kaai 49",
    "sg:city":"Hasselt",
    "sg:classifiers":[
        {
            "category":"Fast Food",
            "type":"Food & Drink"
        }
    ],
    "sg:phone":"+32 11 26 17 45",
    "sg:postcode":"3500",
    "sg:province":"Limburg",
    "sg:tags":[
        "\u00c0",
        "emporter",
        "restaurants"
    ],
    "wof:name":"the Ritz-diners",
    "wof:placetype":"venue"
},
  "geometry": {"coordinates":[5.3374209404,50.9376564026],"type":"Point"}
}