{
  "type": "Feature",
  "properties": {
    "iso:country":"BE",
    "sg:address":"Rue De Bignault 24",
    "sg:city":"La Louvi\u00c8re",
    "sg:orig_category":"Herstellingen and onderhoud aan huis voor voertuigen Metaalafval, schrootrecyclage and sloperijen",
    "sg:phone":"+32 64 26 11 40",
    "sg:postcode":"7110",
    "sg:province":"Hainaut",
    "wof:name":"Serge Vanolland",
    "wof:placetype":"venue"
},
  "geometry": {"coordinates":[4.1505050659,50.4826698303],"type":"Point"}
}