{
  "type": "Feature",
  "properties": {
    "iso:country":"BE",
    "sg:address":"Place Saint-aubain 1",
    "sg:city":"Namur",
    "sg:orig_category":"Enseignement sup\u00e9rieur",
    "sg:phone":"+32 81 22 77 96",
    "sg:postcode":"5000",
    "sg:province":"Namur",
    "wof:name":"I.e.s.e.t.",
    "wof:placetype":"venue"
},
  "geometry": {"coordinates":[4.8603720665,50.4642524719],"type":"Point"}
}