{
  "type": "Feature",
  "properties": {
    "addr:full":"Mechelsesteenweg 371 Herent Vlaams-Brabant 3020",
    "addr:housenumber":"371",
    "addr:postcode":"3020",
    "addr:street":"Mechelsesteenweg",
    "iso:country":"BE",
    "sg:address":"Mechelsesteenweg 371",
    "sg:city":"Herent",
    "sg:orig_category":"Banken and kredietinstellingen",
    "sg:phone":"+32 16 22 87 28",
    "sg:postcode":"3020",
    "sg:province":"Vlaams-Brabant",
    "wof:name":"Fortis",
    "wof:placetype":"venue"
},
  "geometry": {"coordinates":[4.673514843,50.9042129517],"type":"Point"}
}