{
  "type": "Feature",
  "properties": {
    "iso:country":"BE",
    "sg:address":"Maalstraat 3",
    "sg:city":"Wevelgem",
    "sg:orig_category":"Woningbouw",
    "sg:phone":"+32 56 50 40 02",
    "sg:postcode":"8560",
    "sg:province":"West-Vlaanderen",
    "wof:name":"Bouwwerken Johan Lezy",
    "wof:placetype":"venue"
},
  "geometry": {"coordinates":[3.1566278934,50.8547744751],"type":"Point"}
}