{
  "type": "Feature",
  "properties": {
    "addr:full":"Tinnenpotstraat 61 Izegem West-Vlaanderen 8870",
    "addr:housenumber":"61",
    "addr:postcode":"8870",
    "addr:street":"Tinnenpotstraat",
    "iso:country":"BE",
    "sg:address":"Tinnenpotstraat 61",
    "sg:city":"Izegem",
    "sg:orig_category":"Epiceries",
    "sg:phone":"+32 51 30 17 72",
    "sg:postcode":"8870",
    "sg:province":"West-Vlaanderen",
    "wof:name":"Victor Debackere",
    "wof:placetype":"venue"
},
  "geometry": {"coordinates":[3.2115809917,50.9435386658],"type":"Point"}
}