{
  "type": "Feature",
  "properties": {
    "addr:full":"Bisschoppenhoflaan 583 Deurne Antwerpen 2100",
    "addr:housenumber":"583",
    "addr:postcode":"2100",
    "addr:street":"Bisschoppenhoflaan",
    "iso:country":"BE",
    "sg:address":"Bisschoppenhoflaan 583",
    "sg:city":"Deurne",
    "sg:classifiers":[
        {
            "category":"Utilities",
            "subcategory":"Natural Gas",
            "type":"Services"
        }
    ],
    "sg:phone":"+32 3 328 06 60",
    "sg:postcode":"2100",
    "sg:province":"Antwerpen",
    "sg:tags":[
        "current",
        "converter"
    ],
    "wof:name":"Ysebaert Nv",
    "wof:placetype":"venue"
},
  "geometry": {"coordinates":[4.4767751694,51.2361068726],"type":"Point"}
}