{
  "type": "Feature",
  "properties": {
    "addr:full":"Dorpsstraat 79 Aalst (baardegem) Oost-Vlaanderen 9310",
    "addr:housenumber":"79",
    "addr:postcode":"9310",
    "addr:street":"Dorpsstraat",
    "iso:country":"BE",
    "sg:address":"Dorpsstraat 79",
    "sg:city":"Aalst (baardegem)",
    "sg:classifiers":[
        {
            "category":"Health Services",
            "subcategory":"Doctor",
            "type":"Services"
        }
    ],
    "sg:phone":"+32 52 35 92 98",
    "sg:postcode":"9310",
    "sg:province":"Oost-Vlaanderen",
    "sg:tags":[
        "medicinephysicians",
        "surgeon"
    ],
    "wof:name":"Blondeel J",
    "wof:placetype":"venue"
},
  "geometry": {"coordinates":[4.098400116,50.9477767944],"type":"Point"}
}