{
  "type": "Feature",
  "properties": {
    "addr:full":"Achttiende Oogstwal 37 Box 1 Tongeren Limburg 3700",
    "addr:housenumber":"37;1",
    "addr:postcode":"3700",
    "addr:street":"Box",
    "iso:country":"BE",
    "sg:address":"Achttiende Oogstwal 37 Box 1",
    "sg:city":"Tongeren",
    "sg:classifiers":[
        {
            "category":"Professional",
            "subcategory":"Lawyer & Legal Services",
            "type":"Services"
        }
    ],
    "sg:phone":"+32 12 39 83 70",
    "sg:postcode":"3700",
    "sg:province":"Limburg",
    "wof:name":"Alofs G",
    "wof:placetype":"venue"
},
  "geometry": {"coordinates":[5.4694180489,50.7848205566],"type":"Point"}
}