{
  "type": "Feature",
  "properties": {
    "addr:full":"Rue Des Hamendes 19b3 Charleroi Hainaut 6042",
    "addr:housenumber":"19b3",
    "addr:postcode":"6042",
    "addr:street":"Rue Des Hamendes;Hainaut",
    "iso:country":"BE",
    "sg:address":"Rue Des Hamendes 19b3",
    "sg:city":"Charleroi",
    "sg:orig_category":"Epiceries",
    "sg:phone":"+32 71 41 78 60",
    "sg:postcode":"6042",
    "sg:province":"Hainaut",
    "wof:name":"Silvestrin",
    "wof:placetype":"venue"
},
  "geometry": {"coordinates":[4.4671020508,50.4382019043],"type":"Point"}
}