{
  "type": "Feature",
  "properties": {
    "addr:full":"Gemeenschappenlaan 101 Bruxelles-woluwe-saint-lambert Bruxelles-Capitale 1200",
    "addr:housenumber":"101",
    "addr:postcode":"1200",
    "addr:street":"Gemeenschappenlaan",
    "iso:country":"BE",
    "sg:address":"Gemeenschappenlaan 101",
    "sg:city":"Bruxelles-woluwe-saint-lambert",
    "sg:classifiers":[
        {
            "category":"Shopping",
            "subcategory":"Computers & Home Electronics",
            "type":"Retail Goods"
        }
    ],
    "sg:phone":"+32 2 778 18 63",
    "sg:postcode":"1200",
    "sg:province":"Bruxelles-Capitale",
    "sg:tags":[
        "computerapparatuur",
        "microsoft"
    ],
    "wof:name":"Cora Woluwe",
    "wof:placetype":"venue"
},
  "geometry": {"coordinates":[4.4266371727,50.8568687439],"type":"Point"}
}