{
  "type": "Feature",
  "properties": {
    "iso:country":"BE",
    "sg:address":"Weverstraat 107",
    "sg:city":"Sint-niklaas",
    "sg:classifiers":[
        {
            "category":"Insurance",
            "subcategory":"Life Insurance",
            "type":"Services"
        }
    ],
    "sg:phone":"+32 3 777 01 35",
    "sg:postcode":"9100",
    "sg:province":"Oost-Vlaanderen",
    "sg:tags":[
        "assurance"
    ],
    "wof:name":"Ora Consulting",
    "wof:placetype":"venue"
},
  "geometry": {"coordinates":[4.131775856,51.1299819946],"type":"Point"}
}