{
  "type": "Feature",
  "properties": {
    "addr:full":"Rue De La Ros\u00e9e 12 Bruxelles (anderlecht) Bruxelles-Capitale 1070",
    "addr:housenumber":"12",
    "addr:postcode":"1070",
    "addr:street":"Rue De La Rose\u0301E",
    "iso:country":"BE",
    "sg:address":"Rue De La Ros\u00e9e 12",
    "sg:city":"Bruxelles (anderlecht)",
    "sg:classifiers":[
        {
            "category":"Utilities",
            "subcategory":"Fuel Oil & Lpg",
            "type":"Services"
        }
    ],
    "sg:phone":"+32 78 15 21 50",
    "sg:postcode":"1070",
    "sg:province":"Bruxelles-Capitale",
    "wof:name":"Informazout Vzw",
    "wof:placetype":"venue"
},
  "geometry": {"coordinates":[4.3368468285,50.8462753296],"type":"Point"}
}