{
  "type": "Feature",
  "properties": {
    "addr:full":"Woestendorp 39ba Vleteren West-Vlaanderen 8640",
    "addr:housenumber":"39ba",
    "addr:postcode":"8640",
    "addr:street":"Woestendorp",
    "iso:country":"BE",
    "sg:address":"Woestendorp 39ba",
    "sg:city":"Vleteren",
    "sg:orig_category":"Plaatsen van vloer- and muurbekleding Schilders Winkelinrichting and handelsuitrusting Gh",
    "sg:phone":"+32 57 42 11 07",
    "sg:postcode":"8640",
    "sg:province":"West-Vlaanderen",
    "wof:name":"Allinco",
    "wof:placetype":"venue"
},
  "geometry": {"coordinates":[2.7884690762,50.9011764526],"type":"Point"}
}