{
  "type": "Feature",
  "properties": {
    "iso:country":"BE",
    "sg:address":"Kwerpsebaan 370",
    "sg:city":"Kortenberg (erps-kwerps)",
    "sg:classifiers":[
        {
            "category":"Professional",
            "type":"Services"
        }
    ],
    "sg:phone":"+32 2 757 62 66",
    "sg:postcode":"3071",
    "sg:province":"Vlaams-Brabant",
    "sg:tags":[
        "surveyor",
        "-",
        "valuer"
    ],
    "wof:name":"Baudemprez L",
    "wof:placetype":"venue"
},
  "geometry": {"coordinates":[4.5695719719,50.9047393799],"type":"Point"}
}