{
  "type": "Feature",
  "properties": {
    "iso:country":"BE",
    "sg:address":"Dr\u00e8ve Nantaise 7",
    "sg:city":"Genappe (bousval)",
    "sg:classifiers":[
        {
            "category":"Social Services",
            "subcategory":"Job Training",
            "type":"Services"
        }
    ],
    "sg:phone":"+32 10 61 17 32",
    "sg:postcode":"1470",
    "sg:province":"Brabant Wallon",
    "sg:tags":[
        "personnel"
    ],
    "wof:name":"Lambrexhe J",
    "wof:placetype":"venue"
},
  "geometry": {"coordinates":[4.5374178886,50.6416931152],"type":"Point"}
}