{
  "type": "Feature",
  "properties": {
    "addr:full":"Stationsplein 3 Tielt West-Vlaanderen 8700",
    "addr:housenumber":"3",
    "addr:postcode":"8700",
    "addr:street":"Stationsplein",
    "iso:country":"BE",
    "sg:address":"Stationsplein 3",
    "sg:city":"Tielt",
    "sg:orig_category":"Journaux. Tabac. Imprimeries and copyshops",
    "sg:phone":"+32 51 40 45 21",
    "sg:postcode":"8700",
    "sg:province":"West-Vlaanderen",
    "wof:name":"Drukkerij 't Schrijverke",
    "wof:placetype":"venue"
},
  "geometry": {"coordinates":[3.3302071095,50.9912414551],"type":"Point"}
}