{
  "type": "Feature",
  "properties": {
    "addr:full":"Plantin En Moretuslei 174b5 Antwerpen Antwerpen 2018",
    "addr:housenumber":"174b5",
    "addr:postcode":"2018",
    "addr:street":"Plantin En Moretuslei",
    "iso:country":"BE",
    "sg:address":"Plantin En Moretuslei 174b5",
    "sg:city":"Antwerpen",
    "sg:orig_category":"Marketingbureaus",
    "sg:phone":"+32 3 272 20 07",
    "sg:postcode":"2018",
    "sg:province":"Antwerpen",
    "wof:name":"Mcness",
    "wof:placetype":"venue"
},
  "geometry": {"coordinates":[4.4334301949,51.2088813782],"type":"Point"}
}