{
  "type": "Feature",
  "properties": {
    "iso:country":"BE",
    "sg:address":"Polbroek 4",
    "sg:city":"Sint-lievens-houtem",
    "sg:orig_category":"Avocats and conseillers juridiques",
    "sg:phone":"+32 53 62 75 06",
    "sg:postcode":"9520",
    "sg:province":"Oost-Vlaanderen",
    "wof:name":"Eric Flamee",
    "wof:placetype":"venue"
},
  "geometry": {"coordinates":[3.8539121151,50.9203948975],"type":"Point"}
}