{
  "type": "Feature",
  "properties": {
    "addr:full":"Moorseelsestwg 228 Roeselare West-Vlaanderen 8800",
    "addr:housenumber":"228",
    "addr:postcode":"8800",
    "iso:country":"BE",
    "sg:address":"Moorseelsestwg 228",
    "sg:city":"Roeselare",
    "sg:classifiers":[
        {
            "category":"Wholesale",
            "subcategory":"Meat",
            "type":"Manufacturing & Wholesale Goods"
        }
    ],
    "sg:phone":"+32 51 26 95 95",
    "sg:postcode":"8800",
    "sg:province":"West-Vlaanderen",
    "sg:tags":[
        "chicken"
    ],
    "wof:name":"Lapere Pluimveeslachterij Nv",
    "wof:placetype":"venue"
},
  "geometry": {"coordinates":[3.145483017,50.8933792114],"type":"Point"}
}