{
  "type": "Feature",
  "properties": {
    "iso:country":"BE",
    "sg:address":"Eksterstraat 32",
    "sg:city":"Putte",
    "sg:orig_category":"Artistes ind\u00e9pendants",
    "sg:phone":"+32 15 75 42 64",
    "sg:postcode":"2580",
    "sg:province":"Antwerpen",
    "wof:name":"Rita Vervoort",
    "wof:placetype":"venue"
},
  "geometry": {"coordinates":[4.6357941628,51.0530204773],"type":"Point"}
}