{
  "type": "Feature",
  "properties": {
    "addr:full":"Quai Des Tanneurs 14 Li\u00c8ge Li\u00e8ge 4020",
    "addr:housenumber":"14",
    "addr:postcode":"4020",
    "addr:street":"Quai Des Tanneurs",
    "iso:country":"BE",
    "sg:address":"Quai Des Tanneurs 14",
    "sg:city":"Li\u00c8ge",
    "sg:orig_category":"HERSTELLING ELEKTRISCHE HUISHOUDAPPARATEN Huishoudapparaten, televisies and radio's",
    "sg:phone":"+32 4 342 56 61",
    "sg:postcode":"4020",
    "sg:province":"Li\u00e8ge",
    "wof:name":"Ho.ca.pi. Marec",
    "wof:placetype":"venue"
},
  "geometry": {"coordinates":[5.5809459686,50.6439857483],"type":"Point"}
}