{
  "type": "Feature",
  "properties": {
    "iso:country":"BE",
    "sg:address":"Rue De Bellaire 17",
    "sg:city":"Gesves",
    "sg:orig_category":"Herstellingen and onderhoud van auto's",
    "sg:phone":"+32 85 84 36 17",
    "sg:postcode":"5340",
    "sg:province":"Namur",
    "wof:name":"Andre Paulet",
    "wof:placetype":"venue"
},
  "geometry": {"coordinates":[5.0737371445,50.4602928162],"type":"Point"}
}