{
  "type": "Feature",
  "properties": {
    "iso:country":"BE",
    "sg:address":"Leenstraat 34",
    "sg:city":"Roeselare",
    "sg:orig_category":"Auto-\u00e9coles",
    "sg:phone":"+32 51 20 59 09",
    "sg:postcode":"8800",
    "sg:province":"West-Vlaanderen",
    "wof:name":"Autorijschool V.t.i.",
    "wof:placetype":"venue"
},
  "geometry": {"coordinates":[3.1288599968,50.9451599121],"type":"Point"}
}