{
  "type": "Feature",
  "properties": {
    "addr:full":"Lievevrouwestraat 27 Ranst Antwerpen 2520",
    "addr:housenumber":"27",
    "addr:postcode":"2520",
    "addr:street":"Lievevrouwestraat",
    "iso:country":"BE",
    "sg:address":"Lievevrouwestraat 27",
    "sg:city":"Ranst",
    "sg:classifiers":[
        {
            "category":"Personal",
            "subcategory":"Beauty Salon",
            "type":"Services"
        }
    ],
    "sg:phone":"+32 3 233 06 00",
    "sg:postcode":"2520",
    "sg:province":"Antwerpen",
    "wof:name":"Nagelateljee ('t)",
    "wof:placetype":"venue"
},
  "geometry": {"coordinates":[4.5618572235,51.1892852783],"type":"Point"}
}