{
  "type": "Feature",
  "properties": {
    "iso:country":"BE",
    "sg:address":"Station 19",
    "sg:city":"Gedinne",
    "sg:classifiers":[
        {
            "category":"Travel",
            "subcategory":"Hotels & Motels",
            "type":"Entertainment"
        }
    ],
    "sg:phone":"+32 61 58 70 31",
    "sg:postcode":"5575",
    "sg:province":"Namur",
    "wof:name":"Jacoby (h\u00f4tel)",
    "wof:placetype":"venue"
},
  "geometry": {"coordinates":[4.9778900146,49.9842605591],"type":"Point"}
}