{
  "type": "Feature",
  "properties": {
    "addr:full":"Schaluin 76 Aarschot Vlaams-Brabant 3200",
    "addr:housenumber":"76",
    "addr:postcode":"3200",
    "addr:street":"Schaluin",
    "iso:country":"BE",
    "sg:address":"Schaluin 76",
    "sg:city":"Aarschot",
    "sg:classifiers":[
        {
            "category":"Shopping",
            "subcategory":"Crafts & Fabrics",
            "type":"Retail Goods"
        }
    ],
    "sg:phone":"+32 16 56 01 50",
    "sg:postcode":"3200",
    "sg:province":"Vlaams-Brabant",
    "sg:tags":[
        "graphic",
        "art",
        "supply",
        "-",
        "painting",
        "drawing"
    ],
    "wof:name":"Kunstof Nv",
    "wof:placetype":"venue"
},
  "geometry": {"coordinates":[4.8405690193,50.9909133911],"type":"Point"}
}