{
  "type": "Feature",
  "properties": {
    "addr:full":"Rue De Ronqui\u00c8res 81 Braine-le-comte Hainaut 7090",
    "addr:housenumber":"81",
    "addr:postcode":"7090",
    "addr:street":"Rue De Ronquie\u0300Res",
    "iso:country":"BE",
    "sg:address":"Rue De Ronqui\u00c8res 81",
    "sg:city":"Braine-le-comte",
    "sg:orig_category":"Instituts de beaut\u00e9",
    "sg:phone":"+32 67 55 31 89",
    "sg:postcode":"7090",
    "sg:province":"Hainaut",
    "wof:name":"V\u00c9ronique Mestag",
    "wof:placetype":"venue"
},
  "geometry": {"coordinates":[4.1475758553,50.6096076965],"type":"Point"}
}