{
  "type": "Feature",
  "properties": {
    "iso:country":"BE",
    "sg:address":"Spoorwegstraat 76",
    "sg:city":"Hasselt",
    "sg:classifiers":[
        {
            "category":"Wholesale",
            "subcategory":"Medical Equipment & Supplies",
            "type":"Manufacturing & Wholesale Goods"
        }
    ],
    "sg:phone":"+32 11 27 04 17",
    "sg:postcode":"3500",
    "sg:province":"Limburg",
    "sg:tags":[
        "instrument",
        "apparatus"
    ],
    "wof:name":"Opus Medical Bvba",
    "wof:placetype":"venue"
},
  "geometry": {"coordinates":[5.3262457848,50.9297981262],"type":"Point"}
}