{
  "type": "Feature",
  "properties": {
    "addr:full":"Diestersteenweg 98 Diest (kaggevinne) Vlaams-Brabant 3293",
    "addr:housenumber":"98",
    "addr:postcode":"3293",
    "addr:street":"Diestersteenweg",
    "iso:country":"BE",
    "sg:address":"Diestersteenweg 98",
    "sg:city":"Diest (kaggevinne)",
    "sg:classifiers":[
        {
            "category":"Retail",
            "subcategory":"Veterinary Services",
            "type":"Services"
        }
    ],
    "sg:phone":"+32 13 31 13 48",
    "sg:postcode":"3293",
    "sg:province":"Vlaams-Brabant",
    "sg:tags":[
        "veterinarian"
    ],
    "wof:name":"Lemmens A",
    "wof:placetype":"venue"
},
  "geometry": {"coordinates":[5.0367951393,50.9798164368],"type":"Point"}
}