{
  "type": "Feature",
  "properties": {
    "addr:full":"Rue Alphonse Poullet 6 Moeskroen/mouscron Hainaut 7711",
    "addr:housenumber":"6",
    "addr:postcode":"7711",
    "addr:street":"Rue Alphonse Poullet",
    "iso:country":"BE",
    "sg:address":"Rue Alphonse Poullet 6",
    "sg:city":"Moeskroen/mouscron",
    "sg:classifiers":[
        {
            "category":"Insurance",
            "subcategory":"Life Insurance",
            "type":"Services"
        }
    ],
    "sg:phone":"+32 56 48 80 50",
    "sg:postcode":"7711",
    "sg:province":"Hainaut",
    "sg:tags":[
        "assurance"
    ],
    "wof:name":"A. Van Leynseele",
    "wof:placetype":"venue"
},
  "geometry": {"coordinates":[3.3048770428,50.7283706665],"type":"Point"}
}