{
  "type": "Feature",
  "properties": {
    "iso:country":"BE",
    "sg:address":"Rue Des Templiers 82",
    "sg:city":"Donceel",
    "sg:orig_category":"Producteurs de fruits",
    "sg:phone":"+32 4 259 59 13",
    "sg:postcode":"4357",
    "sg:province":"Li\u00e8ge",
    "wof:name":"Philippe Tirtiaux",
    "wof:placetype":"venue"
},
  "geometry": {"coordinates":[5.2938342094,50.6448020935],"type":"Point"}
}