{
  "type": "Feature",
  "properties": {
    "addr:full":"Rerum Novarumlaan 1a Malle (westmalle) Antwerpen 2390",
    "addr:housenumber":"1a",
    "addr:postcode":"2390",
    "addr:street":"Rerum Novarumlaan",
    "iso:country":"BE",
    "sg:address":"Rerum Novarumlaan 1a",
    "sg:city":"Malle (westmalle)",
    "sg:classifiers":[
        {
            "category":"Social Services",
            "subcategory":"Child Care",
            "type":"Services"
        }
    ],
    "sg:phone":"+32 3 312 27 50",
    "sg:postcode":"2390",
    "sg:province":"Antwerpen",
    "sg:tags":[
        "baby",
        "nursery",
        "day",
        "sitting"
    ],
    "wof:name":"Janneman",
    "wof:placetype":"venue"
},
  "geometry": {"coordinates":[4.6896247864,51.3010406494],"type":"Point"}
}