{
  "type": "Feature",
  "properties": {
    "iso:country":"BE",
    "sg:address":"Lariksenstraat 23",
    "sg:city":"Elsene/ixelles",
    "sg:orig_category":"Advocaten and juridische adviseurs",
    "sg:phone":"+32 2 648 39 14",
    "sg:postcode":"1050",
    "sg:province":"Bruxelles-Capitale",
    "wof:name":"E. Derclaye",
    "wof:placetype":"venue"
},
  "geometry": {"coordinates":[4.363904953,50.8208312988],"type":"Point"}
}