{
  "type": "Feature",
  "properties": {
    "addr:full":"Chauss\u00c9e De Charleroi 95 Charleroi Hainaut 6060",
    "addr:housenumber":"95",
    "addr:postcode":"6060",
    "addr:street":"Chausse\u0301E De Charleroi;Hainaut",
    "iso:country":"BE",
    "sg:address":"Chauss\u00c9e De Charleroi 95",
    "sg:city":"Charleroi",
    "sg:orig_category":"Dakwerken",
    "sg:phone":"+32 71 48 60 24",
    "sg:postcode":"6060",
    "sg:province":"Hainaut",
    "wof:name":"C.e.k.",
    "wof:placetype":"venue"
},
  "geometry": {"coordinates":[4.4736452103,50.401638031],"type":"Point"}
}