{
  "type": "Feature",
  "properties": {
    "addr:full":"Edith Cavellstraat 4 Oostende West-Vlaanderen 8400",
    "addr:housenumber":"4",
    "addr:postcode":"8400",
    "addr:street":"Edith Cavellstraat",
    "iso:country":"BE",
    "sg:address":"Edith Cavellstraat 4",
    "sg:city":"Oostende",
    "sg:classifiers":[
        {
            "category":"Health Services",
            "subcategory":"Dentist",
            "type":"Services"
        }
    ],
    "sg:phone":"+32 59 50 81 14",
    "sg:postcode":"8400",
    "sg:province":"West-Vlaanderen",
    "wof:name":"Delva Johan",
    "wof:placetype":"venue"
},
  "geometry": {"coordinates":[2.9142830372,51.2244148254],"type":"Point"}
}