{
  "type": "Feature",
  "properties": {
    "addr:full":"Processieweg 7a Ranst Antwerpen 2520",
    "addr:housenumber":"7a",
    "addr:postcode":"2520",
    "addr:street":"Processieweg",
    "iso:country":"BE",
    "sg:address":"Processieweg 7a",
    "sg:city":"Ranst",
    "sg:orig_category":"Installation \u00e9lectrique industrielle. Installation \u00e9lectrique r\u00e9sidentielle",
    "sg:phone":"+32 3 475 00 62",
    "sg:postcode":"2520",
    "sg:province":"Antwerpen",
    "wof:name":"Elektro Van Den Branden",
    "wof:placetype":"venue"
},
  "geometry": {"coordinates":[4.566013813,51.1910972595],"type":"Point"}
}