{
  "type": "Feature",
  "properties": {
    "addr:full":"Rue De Biomont 10 Herve (grand-rechain) Li\u00e8ge 4650",
    "addr:housenumber":"10",
    "addr:postcode":"4650",
    "addr:street":"Rue De Biomont;Grand-Rechain",
    "iso:country":"BE",
    "sg:address":"Rue De Biomont 10",
    "sg:city":"Herve (grand-rechain)",
    "sg:classifiers":[
        {
            "category":"Professional",
            "subcategory":"Computer Services",
            "type":"Services"
        }
    ],
    "sg:phone":"+32 87 46 02 39",
    "sg:postcode":"4650",
    "sg:province":"Li\u00e8ge",
    "sg:tags":[
        "webdesign",
        "-",
        "internet"
    ],
    "wof:name":"Tpt Van Renterghem E",
    "wof:placetype":"venue"
},
  "geometry": {"coordinates":[5.7941417694,50.6130561829],"type":"Point"}
}