{
  "type": "Feature",
  "properties": {
    "addr:full":"Baaigemstraat 63 Gavere Oost-Vlaanderen 9890",
    "addr:housenumber":"63",
    "addr:postcode":"9890",
    "addr:street":"Baaigemstraat",
    "iso:country":"BE",
    "sg:address":"Baaigemstraat 63",
    "sg:city":"Gavere",
    "sg:classifiers":[
        {
            "category":"Utilities",
            "subcategory":"Recycling",
            "type":"Services"
        }
    ],
    "sg:phone":"+32 9 384 81 79",
    "sg:postcode":"9890",
    "sg:province":"Oost-Vlaanderen",
    "wof:name":"Mosaic Bvba",
    "wof:placetype":"venue"
},
  "geometry": {"coordinates":[3.6682019234,50.9300003052],"type":"Point"}
}