{
  "type": "Feature",
  "properties": {
    "iso:country":"BE",
    "sg:address":"Houtemsesteenweg 287",
    "sg:city":"Vilvoorde",
    "sg:classifiers":[
        {
            "category":"Banks & Credit Unions",
            "subcategory":"Investment Brokerage",
            "type":"Services"
        }
    ],
    "sg:phone":"+32 2 251 55 63",
    "sg:postcode":"1800",
    "sg:province":"Vlaams-Brabant",
    "sg:tags":[
        "printing",
        "-"
    ],
    "wof:name":"Imbrechts J",
    "wof:placetype":"venue"
},
  "geometry": {"coordinates":[4.4576401711,50.9405441284],"type":"Point"}
}