{
  "type": "Feature",
  "properties": {
    "addr:full":"Vennestraat 9 Waregem West-Vlaanderen 8790",
    "addr:housenumber":"9",
    "addr:postcode":"8790",
    "addr:street":"Vennestraat",
    "iso:country":"BE",
    "sg:address":"Vennestraat 9",
    "sg:city":"Waregem",
    "sg:classifiers":[
        {
            "category":"Cafe",
            "type":"Food & Drink"
        }
    ],
    "sg:phone":"+32 56 60 99 38",
    "sg:postcode":"8790",
    "sg:province":"West-Vlaanderen",
    "sg:tags":[
        "caf\u00e9s"
    ],
    "wof:name":"Azuri",
    "wof:placetype":"venue"
},
  "geometry": {"coordinates":[3.4249899387,50.8845100403],"type":"Point"}
}