{
  "type": "Feature",
  "properties": {
    "addr:full":"Rue Bevan 2 Seraing (ougr\u00e9e) Li\u00e8ge 4102",
    "addr:housenumber":"2",
    "addr:postcode":"4102",
    "addr:street":"Rue Bevan",
    "iso:country":"BE",
    "sg:address":"Rue Bevan 2",
    "sg:city":"Seraing (ougr\u00e9e)",
    "sg:classifiers":[
        {
            "category":"Health Services",
            "subcategory":"Doctor",
            "type":"Services"
        }
    ],
    "sg:phone":"+32 4 336 79 46",
    "sg:postcode":"4102",
    "sg:province":"Li\u00e8ge",
    "sg:tags":[
        "medicinephysicians",
        "surgeon"
    ],
    "wof:name":"Hubert G",
    "wof:placetype":"venue"
},
  "geometry": {"coordinates":[5.5480828285,50.5826530457],"type":"Point"}
}