{
  "type": "Feature",
  "properties": {
    "iso:country":"BE",
    "sg:address":"Prins Albertstraat 58",
    "sg:city":"Sint-niklaas",
    "sg:orig_category":"Studios photographiques",
    "sg:phone":"+32 3 777 35 53",
    "sg:postcode":"9100",
    "sg:province":"Oost-Vlaanderen",
    "wof:name":"Heirbaut",
    "wof:placetype":"venue"
},
  "geometry": {"coordinates":[4.1444878578,51.1691131592],"type":"Point"}
}