{
  "type": "Feature",
  "properties": {
    "iso:country":"BE",
    "sg:address":"Rue Vandam 41",
    "sg:city":"Charleroi (jumet)",
    "sg:classifiers":[
        {
            "category":"Building & Trades",
            "subcategory":"Locksmith",
            "type":"Services"
        }
    ],
    "sg:phone":"+32 71 30 72 30",
    "sg:postcode":"6040",
    "sg:province":"Hainaut",
    "sg:tags":[
        "material",
        "road"
    ],
    "wof:name":"Prorest",
    "wof:placetype":"venue"
},
  "geometry": {"coordinates":[4.4204421043,50.4325752258],"type":"Point"}
}