{
  "type": "Feature",
  "properties": {
    "iso:country":"BE",
    "sg:address":"Rue D'acoz 164",
    "sg:city":"Chatelet",
    "sg:classifiers":[
        {
            "category":"Manufacturing",
            "subcategory":"Petroleum Products",
            "type":"Manufacturing & Wholesale Goods"
        }
    ],
    "sg:phone":"+32 71 38 19 99",
    "sg:postcode":"6200",
    "sg:province":"Hainaut",
    "sg:tags":[
        "double",
        "glazing"
    ],
    "wof:name":"Aubert & Fils",
    "wof:placetype":"venue"
},
  "geometry": {"coordinates":[4.5221810341,50.4000167847],"type":"Point"}
}