{
  "type": "Feature",
  "properties": {
    "iso:country":"BE",
    "sg:address":"Rietlaan 3",
    "sg:city":"Dilbeek",
    "sg:orig_category":"Artistes ind\u00e9pendants",
    "sg:phone":"+32 2 466 10 03",
    "sg:postcode":"1702",
    "sg:province":"Vlaams-Brabant",
    "wof:name":"Jacques Dubois",
    "wof:placetype":"venue"
},
  "geometry": {"coordinates":[4.2633609772,50.8656616211],"type":"Point"}
}