{
  "type": "Feature",
  "properties": {
    "iso:country":"BE",
    "sg:address":"Landvoogddreef 60",
    "sg:city":"Ukkel/uccle",
    "sg:orig_category":"Loodgieterij, verwarming and sanitaire installaties",
    "sg:phone":"+32 2 375 04 85",
    "sg:postcode":"1180",
    "sg:province":"Bruxelles-Capitale",
    "wof:name":"Michel Vandendriessche",
    "wof:placetype":"venue"
},
  "geometry": {"coordinates":[4.377696991,50.7948570251],"type":"Point"}
}