{
  "type": "Feature",
  "properties": {
    "iso:country":"BE",
    "sg:address":"Rue E. Vandevelde 44",
    "sg:city":"Marchienne-au-pont",
    "sg:orig_category":"Computers and computerapparatuur Huishoudapparaten, televisies and radio's Telecommunicatieapparaten",
    "sg:phone":"+32 71 31 79 18",
    "sg:postcode":"6030",
    "sg:province":"Hainaut",
    "wof:name":"Cascio Electronics",
    "wof:placetype":"venue"
},
  "geometry": {"coordinates":[4.3940000534,50.4093475342],"type":"Point"}
}