{
  "type": "Feature",
  "properties": {
    "iso:country":"BE",
    "sg:address":"Zaubeekstraat 17",
    "sg:city":"Zulte",
    "sg:classifiers":[
        {
            "category":"Retail",
            "subcategory":"Auto Repair",
            "type":"Services"
        }
    ],
    "sg:phone":"+32 9 388 47 91",
    "sg:postcode":"9870",
    "sg:province":"Oost-Vlaanderen",
    "sg:tags":[
        "automobile-body"
    ],
    "wof:name":"Willemijns K",
    "wof:placetype":"venue"
},
  "geometry": {"coordinates":[3.4466350079,50.9219322205],"type":"Point"}
}