{
  "type": "Feature",
  "properties": {
    "iso:country":"BE",
    "sg:address":"Buskruitstraat",
    "sg:city":"Oostende",
    "sg:classifiers":[
        {
            "category":"Metro Station",
            "type":"Transportation"
        }
    ],
    "sg:phone":"+32 59 32 57 58",
    "sg:postcode":"8400",
    "sg:province":"West-Vlaanderen",
    "sg:tags":[
        "repair",
        "ship",
        "mainten",
        "-"
    ],
    "wof:name":"Snipe Bvba",
    "wof:placetype":"venue"
},
  "geometry": {"coordinates":[2.9285449982,51.2363891602],"type":"Point"}
}