{
  "type": "Feature",
  "properties": {
    "iso:country":"BE",
    "sg:address":"Rue La Cav\u00c9e 13",
    "sg:city":"Mont-de-l'enclus",
    "sg:orig_category":"Eleveurs de bovins",
    "sg:phone":"+32 69 76 80 86",
    "sg:postcode":"7750",
    "sg:province":"Hainaut",
    "wof:name":"A. Van Pevenaeyge",
    "wof:placetype":"venue"
},
  "geometry": {"coordinates":[5.8103728294,50.5340766907],"type":"Point"}
}