{
  "type": "Feature",
  "properties": {
    "iso:country":"BE",
    "sg:address":"Dorpsstraat 178",
    "sg:city":"Overpelt",
    "sg:classifiers":[
        {
            "category":"Insurance",
            "subcategory":"Insurance Agent",
            "type":"Services"
        }
    ],
    "sg:phone":"+32 11 80 57 80",
    "sg:postcode":"3900",
    "sg:province":"Limburg",
    "sg:tags":[
        "broker"
    ],
    "wof:name":"Van Hoof & Schruers Nv",
    "wof:placetype":"venue"
},
  "geometry": {"coordinates":[5.4205589294,51.2099723816],"type":"Point"}
}