{
  "type": "Feature",
  "properties": {
    "iso:country":"BE",
    "sg:address":"Captain Trippstraat 3",
    "sg:city":"Willebroek",
    "sg:classifiers":[
        {
            "category":"Health Services",
            "subcategory":"Doctor",
            "type":"Services"
        }
    ],
    "sg:phone":"+32 3 866 20 20",
    "sg:postcode":"2830",
    "sg:province":"Antwerpen",
    "sg:tags":[
        "medicinephysicians",
        "surgeon"
    ],
    "wof:name":"Geerts Sonja",
    "wof:placetype":"venue"
},
  "geometry": {"coordinates":[4.3586540222,51.0590934753],"type":"Point"}
}