{
  "type": "Feature",
  "properties": {
    "iso:country":"BE",
    "sg:address":"Zone Plantis Des Aisements",
    "sg:city":"Momignies",
    "sg:classifiers":[
        {
            "category":"Airport",
            "subcategory":"International",
            "type":"Transportation"
        }
    ],
    "sg:phone":"+32 60 51 12 21",
    "sg:postcode":"6590",
    "sg:province":"Hainaut",
    "sg:tags":[
        "-",
        "transport"
    ],
    "wof:name":"Raux Sprl",
    "wof:placetype":"venue"
},
  "geometry": {"coordinates":[4.1657729149,50.02967453],"type":"Point"}
}