{
  "type": "Feature",
  "properties": {
    "addr:full":"Rue Emmanuel Mertens 29 Bruxelles (woluwe-saint-pierre) Bruxelles-Capitale 1150",
    "addr:housenumber":"29",
    "addr:postcode":"1150",
    "addr:street":"Rue Emmanuel Mertens",
    "iso:country":"BE",
    "sg:address":"Rue Emmanuel Mertens 29",
    "sg:city":"Bruxelles (woluwe-saint-pierre)",
    "sg:classifiers":[
        {
            "category":"Professional",
            "subcategory":"Advertising",
            "type":"Services"
        }
    ],
    "sg:phone":"+32 2 762 86 57",
    "sg:postcode":"1150",
    "sg:province":"Bruxelles-Capitale",
    "sg:tags":[
        "item",
        "-",
        "business",
        "gift",
        "promotional"
    ],
    "wof:name":"Stercotex",
    "wof:placetype":"venue"
},
  "geometry": {"coordinates":[4.441133976,50.8320617676],"type":"Point"}
}