{
  "type": "Feature",
  "properties": {
    "iso:country":"BE",
    "sg:address":"Ettersten 15",
    "sg:city":"Eupen",
    "sg:orig_category":"Travaux de pl\u00e2trage. Construction de maisons",
    "sg:phone":"+32 87 55 43 24",
    "sg:postcode":"4700",
    "sg:province":"Li\u00e8ge",
    "wof:name":"Ganser Heinz",
    "wof:placetype":"venue"
},
  "geometry": {"coordinates":[6.0289959908,50.6245651245],"type":"Point"}
}