{
  "type": "Feature",
  "properties": {
    "iso:country":"BE",
    "sg:address":"Rue Philippe Monnoyer 86",
    "sg:city":"Courcelles",
    "sg:classifiers":[
        {
            "category":"Shopping",
            "subcategory":"Books",
            "type":"Retail Goods"
        }
    ],
    "sg:phone":"+32 71 45 96 73",
    "sg:postcode":"6180",
    "sg:province":"Hainaut",
    "sg:tags":[
        "bookseller"
    ],
    "wof:name":"Courcelloise (la)",
    "wof:placetype":"venue"
},
  "geometry": {"coordinates":[4.3753290176,50.4634780884],"type":"Point"}
}