{
  "type": "Feature",
  "properties": {
    "addr:full":"Rollegemkapelsestraat 86 Ledegem (sint-eloois-winkel) West-Vlaanderen 8880",
    "addr:housenumber":"86",
    "addr:postcode":"8880",
    "addr:street":"Rollegemkapelsestraat",
    "iso:country":"BE",
    "sg:address":"Rollegemkapelsestraat 86",
    "sg:city":"Ledegem (sint-eloois-winkel)",
    "sg:classifiers":[
        {
            "category":"Freight",
            "type":"Transportation"
        }
    ],
    "sg:phone":"+32 56 50 62 71",
    "sg:postcode":"8880",
    "sg:province":"West-Vlaanderen",
    "sg:tags":[
        "-",
        "transport"
    ],
    "wof:name":"Transledegem",
    "wof:placetype":"venue"
},
  "geometry": {"coordinates":[3.1527690887,50.8697090149],"type":"Point"}
}