{
  "type": "Feature",
  "properties": {
    "addr:full":"Oudstrijdersstraat 42 Ranst Antwerpen 2520",
    "addr:housenumber":"42",
    "addr:postcode":"2520",
    "addr:street":"Oudstrijdersstraat",
    "iso:country":"BE",
    "sg:address":"Oudstrijdersstraat 42",
    "sg:city":"Ranst",
    "sg:orig_category":"Herstellingen and onderhoud van auto's",
    "sg:phone":"+32 3 383 57 34",
    "sg:postcode":"2520",
    "sg:province":"Antwerpen",
    "wof:name":"Garage Van Staeyen",
    "wof:placetype":"venue"
},
  "geometry": {"coordinates":[4.5935940742,51.2117881775],"type":"Point"}
}