{
  "type": "Feature",
  "properties": {
    "addr:full":"Stationsstraat 3 Gistel West-Vlaanderen 8470",
    "addr:housenumber":"3",
    "addr:postcode":"8470",
    "addr:street":"Stationsstraat",
    "iso:country":"BE",
    "sg:address":"Stationsstraat 3",
    "sg:city":"Gistel",
    "sg:orig_category":"Diverse kredietdiensten",
    "sg:postcode":"8470",
    "sg:province":"West-Vlaanderen",
    "wof:name":"Bancontact-mister Cash",
    "wof:placetype":"venue"
},
  "geometry": {"coordinates":[2.9669160843,51.1559715271],"type":"Point"}
}