{
  "type": "Feature",
  "properties": {
    "addr:full":"Misstraat 134 Lier (koningshooikt) Antwerpen 2500",
    "addr:housenumber":"134",
    "addr:postcode":"2500",
    "addr:street":"Misstraat",
    "iso:country":"BE",
    "sg:address":"Misstraat 134",
    "sg:city":"Lier (koningshooikt)",
    "sg:classifiers":[
        {
            "category":"Insurance",
            "subcategory":"Insurance Agent",
            "type":"Services"
        }
    ],
    "sg:phone":"+32 3 482 12 09",
    "sg:postcode":"2500",
    "sg:province":"Antwerpen",
    "sg:tags":[
        "broker"
    ],
    "wof:name":"Van Hool - Raets Bvba",
    "wof:placetype":"venue"
},
  "geometry": {"coordinates":[4.6211891174,51.1025009155],"type":"Point"}
}