{
  "type": "Feature",
  "properties": {
    "addr:full":"Eikestraat 48 Herzele Oost-Vlaanderen 9550",
    "addr:housenumber":"48",
    "addr:postcode":"9550",
    "addr:street":"Eikestraat;Oost-Vlaanderen",
    "iso:country":"BE",
    "sg:address":"Eikestraat 48",
    "sg:city":"Herzele",
    "sg:orig_category":"Woningbouw",
    "sg:phone":"+32 54 50 15 62",
    "sg:postcode":"9550",
    "sg:province":"Oost-Vlaanderen",
    "wof:name":"Jan Van Damme",
    "wof:placetype":"venue"
},
  "geometry": {"coordinates":[3.905424118,50.8294448853],"type":"Point"}
}