{
  "type": "Feature",
  "properties": {
    "addr:full":"Rue Du Saule 1 Bruxelles (jette) Bruxelles-Capitale 1090",
    "addr:housenumber":"1",
    "addr:postcode":"1090",
    "addr:street":"Rue Du Saule",
    "iso:country":"BE",
    "sg:address":"Rue Du Saule 1",
    "sg:city":"Bruxelles (jette)",
    "sg:classifiers":[
        {
            "category":"Education",
            "subcategory":"School",
            "type":"Public Place"
        }
    ],
    "sg:phone":"+32 2 427 60 72",
    "sg:postcode":"1090",
    "sg:province":"Bruxelles-Capitale",
    "sg:tags":[
        "secondary"
    ],
    "wof:name":"Acad\u00e9mie Communale De Musique",
    "wof:placetype":"venue"
},
  "geometry": {"coordinates":[4.3220658302,50.8774452209],"type":"Point"}
}