{
  "type": "Feature",
  "properties": {
    "iso:country":"BE",
    "sg:address":"Ch De Ch\u00e2telineau 280",
    "sg:city":"Charleroi",
    "sg:classifiers":[
        {
            "category":"Autos & Motor Vehicles",
            "subcategory":"Automobile Sales",
            "type":"Retail Goods"
        }
    ],
    "sg:phone":"+32 71 32 90 65",
    "sg:postcode":"6061",
    "sg:province":"Hainaut",
    "sg:tags":[
        "equipment",
        "motor-cars",
        "transport"
    ],
    "wof:name":"Nvx Ets Bernabe Sa",
    "wof:placetype":"venue"
},
  "geometry": {"coordinates":[4.4960708618,50.4049186707],"type":"Point"}
}