{
  "type": "Feature",
  "properties": {
    "iso:country":"BE",
    "sg:address":"Sint-sebastiaanstraat 28",
    "sg:city":"Beringen",
    "sg:classifiers":[
        {
            "category":"Cafe",
            "type":"Food & Drink"
        }
    ],
    "sg:phone":"+32 11 43 43 93",
    "sg:postcode":"3583",
    "sg:province":"Limburg",
    "sg:tags":[
        "caf\u00e9s"
    ],
    "wof:name":"Bart Vaes",
    "wof:placetype":"venue"
},
  "geometry": {"coordinates":[5.171061039,51.046257019],"type":"Point"}
}