{
  "type": "Feature",
  "properties": {
    "addr:full":"Doornhoek 5 Gistel West-Vlaanderen 8460",
    "addr:housenumber":"5",
    "addr:postcode":"8460",
    "addr:street":"Doornhoek",
    "iso:country":"BE",
    "sg:address":"Doornhoek 5",
    "sg:city":"Gistel",
    "sg:orig_category":"Pluimveekwekers Rundveehouders",
    "sg:phone":"+32 59 27 83 47",
    "sg:postcode":"8460",
    "sg:province":"West-Vlaanderen",
    "wof:name":"Basilius Inghelbrecht",
    "wof:placetype":"venue"
},
  "geometry": {"coordinates":[2.9825499058,51.1686782837],"type":"Point"}
}