{
  "type": "Feature",
  "properties": {
    "addr:full":"Avenue De La Couronne 257 Elsene/ixelles Bruxelles-Capitale 1050",
    "addr:housenumber":"257",
    "addr:postcode":"1050",
    "addr:street":"Avenue De La Couronne",
    "iso:country":"BE",
    "sg:address":"Avenue De La Couronne 257",
    "sg:city":"Elsene/ixelles",
    "sg:classifiers":[
        {
            "category":"Cafe",
            "type":"Food & Drink"
        }
    ],
    "sg:phone":"+32 2 644 52 01",
    "sg:postcode":"1050",
    "sg:province":"Bruxelles-Capitale",
    "sg:tags":[
        "caf\u00e9s"
    ],
    "wof:name":"Ar Games",
    "wof:placetype":"venue"
},
  "geometry": {"coordinates":[4.3892140388,50.8212356567],"type":"Point"}
}