{
  "type": "Feature",
  "properties": {
    "addr:full":"Crombionstraat 2 Moeskroen/mouscron Hainaut 7700",
    "addr:housenumber":"2",
    "addr:postcode":"7700",
    "addr:street":"Crombionstraat",
    "iso:country":"BE",
    "sg:address":"Crombionstraat 2",
    "sg:city":"Moeskroen/mouscron",
    "sg:orig_category":"Textiel",
    "sg:phone":"+32 56 33 22 09",
    "sg:postcode":"7700",
    "sg:province":"Hainaut",
    "wof:name":"Maison Fibrex",
    "wof:placetype":"venue"
},
  "geometry": {"coordinates":[3.2323200703,50.7400932312],"type":"Point"}
}