{
  "type": "Feature",
  "properties": {
    "addr:full":"Am Walckerstal 54 Butgenbach Li\u00e8ge 4750",
    "addr:housenumber":"54",
    "addr:postcode":"4750",
    "addr:street":"Am Walckerstal",
    "iso:country":"BE",
    "sg:address":"Am Walckerstal 54",
    "sg:city":"Butgenbach",
    "sg:orig_category":"Maisons de vacances",
    "sg:phone":"+32 80 44 69 32",
    "sg:postcode":"4750",
    "sg:province":"Li\u00e8ge",
    "wof:name":"J. Heck",
    "wof:placetype":"venue"
},
  "geometry": {"coordinates":[6.1992769241,50.4310531616],"type":"Point"}
}