{
  "type": "Feature",
  "properties": {
    "addr:full":"Rue De Merbes 8b2 Binche Hainaut 7130",
    "addr:housenumber":"8b2",
    "addr:postcode":"7130",
    "addr:street":"Rue De Merbes",
    "iso:country":"BE",
    "sg:address":"Rue De Merbes 8b2",
    "sg:city":"Binche",
    "sg:orig_category":"Diverse grafische activiteiten",
    "sg:phone":"+32 64 33 66 82",
    "sg:postcode":"7130",
    "sg:province":"Hainaut",
    "wof:name":"Barbara Duriaux",
    "wof:placetype":"venue"
},
  "geometry": {"coordinates":[4.1710710526,50.4111175537],"type":"Point"}
}