{
  "type": "Feature",
  "properties": {
    "addr:full":"Rue Du Marcht Aux Herbes 105b75 Brussel/bruxelles Bruxelles-Capitale 1000",
    "addr:housenumber":"105b75",
    "addr:postcode":"1000",
    "addr:street":"Rue Du Marcht Aux Herbes;/",
    "iso:country":"BE",
    "sg:address":"Rue Du Marcht Aux Herbes 105b75",
    "sg:city":"Brussel/bruxelles",
    "sg:orig_category":"Tabac",
    "sg:phone":"+32 2 511 55 71",
    "sg:postcode":"1000",
    "sg:province":"Bruxelles-Capitale",
    "wof:name":"Maison Du Fumeur",
    "wof:placetype":"venue"
},
  "geometry": {"coordinates":[4.3543372154,50.8464202881],"type":"Point"}
}