{
  "type": "Feature",
  "properties": {
    "iso:country":"BE",
    "sg:address":"Voetpad 32",
    "sg:city":"Heusden-zolder",
    "sg:classifiers":[
        {
            "category":"Shopping",
            "subcategory":"Clothing, Apparel, & Fashions",
            "type":"Retail Goods"
        }
    ],
    "sg:phone":"+32 11 53 30 61",
    "sg:postcode":"3550",
    "sg:province":"Limburg",
    "sg:tags":[
        "v\u00eatements",
        "pour",
        "dame"
    ],
    "wof:name":"Jozef Fraiponts",
    "wof:placetype":"venue"
},
  "geometry": {"coordinates":[5.309841156,51.022277832],"type":"Point"}
}