{
  "type": "Feature",
  "properties": {
    "addr:full":"Rue Du Village 10 Braives Li\u00e8ge 4260",
    "addr:housenumber":"10",
    "addr:postcode":"4260",
    "addr:street":"Rue Du Village",
    "iso:country":"BE",
    "sg:address":"Rue Du Village 10",
    "sg:city":"Braives",
    "sg:classifiers":[
        {
            "category":"Arena",
            "subcategory":"Sports Club",
            "type":"Entertainment"
        }
    ],
    "sg:phone":"+32 19 56 68 25",
    "sg:postcode":"4260",
    "sg:province":"Li\u00e8ge",
    "sg:tags":[
        "de"
    ],
    "wof:name":"Club Sportif Fumalois",
    "wof:placetype":"venue"
},
  "geometry": {"coordinates":[5.1830787659,50.584777832],"type":"Point"}
}