{
  "type": "Feature",
  "properties": {
    "addr:full":"Rijselsestraat 92 Zedelgem (loppem) West-Vlaanderen 8210",
    "addr:housenumber":"92",
    "addr:postcode":"8210",
    "addr:street":"Rijselsestraat",
    "iso:country":"BE",
    "sg:address":"Rijselsestraat 92",
    "sg:city":"Zedelgem (loppem)",
    "sg:classifiers":[
        {
            "category":"Shopping",
            "subcategory":"Antiques",
            "type":"Retail Goods"
        }
    ],
    "sg:phone":"+32 50 82 33 66",
    "sg:postcode":"8210",
    "sg:province":"West-Vlaanderen",
    "wof:name":"Vermeulen",
    "wof:placetype":"venue"
},
  "geometry": {"coordinates":[3.1458399296,51.1376457214],"type":"Point"}
}