{
  "type": "Feature",
  "properties": {
    "addr:full":"Avenue Des M\u00c9sanges 4 Wavre Brabant Wallon 1300",
    "addr:housenumber":"4;1300",
    "addr:street":"Avenue Des Me\u0301Sanges",
    "iso:country":"BE",
    "sg:address":"Avenue Des M\u00c9sanges 4",
    "sg:city":"Wavre",
    "sg:orig_category":"Notaires",
    "sg:phone":"+32 10 22 23 54",
    "sg:postcode":"1300",
    "sg:province":"Brabant Wallon",
    "wof:name":"Philippe Jentges",
    "wof:placetype":"venue"
},
  "geometry": {"coordinates":[4.6103172302,50.7201347351],"type":"Point"}
}