{
  "type": "Feature",
  "properties": {
    "addr:full":"Alfred Verweeplein 15 Knokke-heist West-Vlaanderen 8300",
    "addr:housenumber":"15",
    "addr:postcode":"8300",
    "addr:street":"Knokke-Heist West-Vlaanderen",
    "iso:country":"BE",
    "sg:address":"Alfred Verweeplein 15",
    "sg:city":"Knokke-heist",
    "sg:orig_category":"Begrafeniswezen",
    "sg:phone":"+32 50 60 57 87",
    "sg:postcode":"8300",
    "sg:province":"West-Vlaanderen",
    "wof:name":"Fa. De Coster & Zonen",
    "wof:placetype":"venue"
},
  "geometry": {"coordinates":[3.2883160114,51.343006134],"type":"Point"}
}