{
  "type": "Feature",
  "properties": {
    "iso:country":"BE",
    "sg:address":"Evangeliestraat 41",
    "sg:city":"Harelbeke",
    "sg:orig_category":"Woningbouw",
    "sg:phone":"+32 56 71 65 31",
    "sg:postcode":"8530",
    "sg:province":"West-Vlaanderen",
    "wof:name":"Fa. Duyck",
    "wof:placetype":"venue"
},
  "geometry": {"coordinates":[3.3307640553,50.8636436462],"type":"Point"}
}