{
  "type": "Feature",
  "properties": {
    "addr:full":"Kapelanielaan 2 Temse Oost-Vlaanderen 9140",
    "addr:housenumber":"2",
    "addr:postcode":"9140",
    "addr:street":"Kapelanielaan",
    "iso:country":"BE",
    "sg:address":"Kapelanielaan 2",
    "sg:city":"Temse",
    "sg:orig_category":"Non-Classified Establishments",
    "sg:phone":"+32 3 710 63 04",
    "sg:postcode":"9140",
    "sg:province":"Oost-Vlaanderen",
    "wof:name":"Intramet Noord",
    "wof:placetype":"venue"
},
  "geometry": {"coordinates":[4.1761097908,51.1385383606],"type":"Point"}
}