{
  "type": "Feature",
  "properties": {
    "addr:full":"Aalststraat 147 Oudenaarde Oost-Vlaanderen 9700",
    "addr:housenumber":"147",
    "addr:postcode":"9700",
    "addr:street":"Aalststraat",
    "iso:country":"BE",
    "sg:address":"Aalststraat 147",
    "sg:city":"Oudenaarde",
    "sg:classifiers":[
        {
            "category":"Bars & Pubs",
            "type":"Food & Drink"
        }
    ],
    "sg:phone":"+32 55 31 74 91",
    "sg:postcode":"9700",
    "sg:province":"Oost-Vlaanderen",
    "wof:name":"Eiland ('t)",
    "wof:placetype":"venue"
},
  "geometry": {"coordinates":[3.6160728931,50.8412818909],"type":"Point"}
}