{
  "type": "Feature",
  "properties": {
    "iso:country":"BE",
    "sg:address":"Rodestraat 1",
    "sg:city":"Veurne",
    "sg:orig_category":"Benzinestations and brandstoffen Herstellingen and onderhoud aan huis voor voertuigen Metaalafval, s",
    "sg:phone":"+32 58 31 15 40",
    "sg:postcode":"8630",
    "sg:province":"West-Vlaanderen",
    "wof:name":"Fa. De Jaegher",
    "wof:placetype":"venue"
},
  "geometry": {"coordinates":[2.6719460487,51.0727386475],"type":"Point"}
}