{
  "type": "Feature",
  "properties": {
    "addr:full":"Chaamseweg 31bb Baarle-hertog Antwerpen 2387",
    "addr:housenumber":"31bb",
    "addr:postcode":"2387",
    "addr:street":"Chaamseweg",
    "iso:country":"BE",
    "sg:address":"Chaamseweg 31bb",
    "sg:city":"Baarle-hertog",
    "sg:orig_category":"MEUBELONTWERP AND -INSTALLATIE",
    "sg:phone":"+32 14 69 92 45",
    "sg:postcode":"2387",
    "sg:province":"Antwerpen",
    "wof:name":"De Keukenconcurrent Belg.",
    "wof:placetype":"venue"
},
  "geometry": {"coordinates":[4.9215040207,51.4457893372],"type":"Point"}
}