{
  "type": "Feature",
  "properties": {
    "iso:country":"BE",
    "sg:address":"Krijgsbaan 128",
    "sg:city":"Zandhoven",
    "sg:orig_category":"Machines and mat\u00e9riel de bureau Ordinateurs and \u00e9quipement informatique. Fournitures de bureau. E-ac",
    "sg:phone":"+32 3 443 94 80",
    "sg:postcode":"2640",
    "sg:province":"Antwerpen",
    "wof:name":"Compaq - Office Automation",
    "wof:placetype":"venue"
},
  "geometry": {"coordinates":[4.4624400139,51.1656799316],"type":"Point"}
}