{
  "type": "Feature",
  "properties": {
    "iso:country":"BE",
    "sg:address":"Veldstraat 4",
    "sg:city":"Jabbeke",
    "sg:orig_category":"Installation \u00e9lectrique r\u00e9sidentielle",
    "sg:phone":"+32 486 71 51 89",
    "sg:postcode":"8490",
    "sg:province":"West-Vlaanderen",
    "wof:name":"Boddin Pascal",
    "wof:placetype":"venue"
},
  "geometry": {"coordinates":[3.0987188816,51.1792068481],"type":"Point"}
}