{
  "type": "Feature",
  "properties": {
    "iso:country":"BE",
    "sg:address":"Rue Houlette 19",
    "sg:city":"Villers-la-ville (sart-dames-avelines)",
    "sg:classifiers":[
        {
            "category":"Professional",
            "subcategory":"Management & Consulting",
            "type":"Services"
        }
    ],
    "sg:phone":"+32 71 87 66 44",
    "sg:postcode":"1495",
    "sg:province":"Brabant Wallon",
    "sg:tags":[
        "-",
        "processing",
        "data",
        "consultant"
    ],
    "wof:name":"Infomatic",
    "wof:placetype":"venue"
},
  "geometry": {"coordinates":[4.5023450851,50.5755119324],"type":"Point"}
}