{
  "type": "Feature",
  "properties": {
    "iso:country":"BE",
    "sg:address":"Kauwstraat 10",
    "sg:city":"Pittem",
    "sg:orig_category":"Plomberie, chauffage and installations sanitaires. Quincailleries",
    "sg:phone":"+32 51 46 75 75",
    "sg:postcode":"8740",
    "sg:province":"West-Vlaanderen",
    "wof:name":"Ronny De Brabandere",
    "wof:placetype":"venue"
},
  "geometry": {"coordinates":[3.2648301125,50.993888855],"type":"Point"}
}