{
  "type": "Feature",
  "properties": {
    "addr:full":"Tieltstraat 39 Wingene West-Vlaanderen 8750",
    "addr:housenumber":"39",
    "addr:postcode":"8750",
    "addr:street":"Tieltstraat",
    "iso:country":"BE",
    "sg:address":"Tieltstraat 39",
    "sg:city":"Wingene",
    "sg:orig_category":"Domotics",
    "sg:phone":"+32 51 54 58 12",
    "sg:postcode":"8750",
    "sg:province":"West-Vlaanderen",
    "wof:name":"Domotica & Lifestyle Center",
    "wof:placetype":"venue"
},
  "geometry": {"coordinates":[3.2824349403,51.0568771362],"type":"Point"}
}