{
  "type": "Feature",
  "properties": {
    "addr:full":"Betekomsesteenweg 23 Begijnendijk Vlaams-Brabant 3130",
    "addr:housenumber":"23",
    "addr:postcode":"3130",
    "addr:street":"Betekomsesteenweg",
    "iso:country":"BE",
    "sg:address":"Betekomsesteenweg 23",
    "sg:city":"Begijnendijk",
    "sg:orig_category":"Drogisterijen Plaatsen van vloer- and muurbekleding Schilders",
    "sg:phone":"+32 16 53 26 68",
    "sg:postcode":"3130",
    "sg:province":"Vlaams-Brabant",
    "wof:name":"Willy Van Rompuy",
    "wof:placetype":"venue"
},
  "geometry": {"coordinates":[4.7835931778,51.0177383423],"type":"Point"}
}