{
  "type": "Feature",
  "properties": {
    "addr:full":"Rue L\u00c9opold-roger 13 Couvin Namur 5660",
    "addr:housenumber":"13",
    "addr:postcode":"5660",
    "addr:street":"Rue Le\u0301Opold-Roger",
    "iso:country":"BE",
    "sg:address":"Rue L\u00c9opold-roger 13",
    "sg:city":"Couvin",
    "sg:orig_category":"Opticiens",
    "sg:phone":"+32 60 31 24 92",
    "sg:postcode":"5660",
    "sg:province":"Namur",
    "wof:name":"A. Collard",
    "wof:placetype":"venue"
},
  "geometry": {"coordinates":[4.5219697952,50.0951004028],"type":"Point"}
}