{
  "type": "Feature",
  "properties": {
    "addr:full":"Rue Dandois 91 Charleroi (ransart) Hainaut 6043",
    "addr:housenumber":"91",
    "addr:postcode":"6043",
    "addr:street":"Rue Dandois",
    "iso:country":"BE",
    "sg:address":"Rue Dandois 91",
    "sg:city":"Charleroi (ransart)",
    "sg:classifiers":[
        {
            "category":"Shopping",
            "subcategory":"Florist",
            "type":"Retail Goods"
        }
    ],
    "sg:phone":"+32 71 35 21 15",
    "sg:postcode":"6043",
    "sg:province":"Hainaut",
    "wof:name":"Tilman Fils",
    "wof:placetype":"venue"
},
  "geometry": {"coordinates":[4.4839549065,50.4479637146],"type":"Point"}
}