{
  "type": "Feature",
  "properties": {
    "iso:country":"BE",
    "sg:address":"Rue Entre-deux-portes 32",
    "sg:city":"Huy",
    "sg:classifiers":[
        {
            "category":"Restaurant",
            "type":"Food & Drink"
        }
    ],
    "sg:phone":"+32 85 23 02 84",
    "sg:postcode":"4500",
    "sg:province":"Li\u00e8ge",
    "wof:name":"Le Citron Press\u00c9",
    "wof:placetype":"venue"
},
  "geometry": {"coordinates":[5.2306399345,50.524974823],"type":"Point"}
}