{
  "type": "Feature",
  "properties": {
    "iso:country":"BE",
    "sg:address":"Verboekt 188",
    "sg:city":"Laakdal (forest)",
    "sg:classifiers":[
        {
            "category":"Building & Trades",
            "subcategory":"Equipment Rental",
            "type":"Services"
        }
    ],
    "sg:phone":"+32 13 66 48 61",
    "sg:postcode":"2430",
    "sg:province":"Antwerpen",
    "sg:tags":[
        "sound",
        "-",
        "system"
    ],
    "wof:name":"V.a.b.",
    "wof:placetype":"venue"
},
  "geometry": {"coordinates":[5.0825800896,51.0855293274],"type":"Point"}
}