{
  "type": "Feature",
  "properties": {
    "addr:full":"Regentiestraat 33ba Stekene Oost-Vlaanderen 9190",
    "addr:housenumber":"33ba",
    "addr:postcode":"9190",
    "addr:street":"Regentiestraat",
    "iso:country":"BE",
    "sg:address":"Regentiestraat 33ba",
    "sg:city":"Stekene",
    "sg:orig_category":"Epiceries",
    "sg:phone":"+32 3 789 23 14",
    "sg:postcode":"9190",
    "sg:province":"Oost-Vlaanderen",
    "wof:name":"'t Winkelken",
    "wof:placetype":"venue"
},
  "geometry": {"coordinates":[4.0729250908,51.2050247192],"type":"Point"}
}