{
  "type": "Feature",
  "properties": {
    "addr:full":"Sudermanstraat 2b Antwerpen Antwerpen 2000",
    "addr:housenumber":"2b",
    "addr:postcode":"2000",
    "addr:street":"Sudermanstraat",
    "iso:country":"BE",
    "sg:address":"Sudermanstraat 2b",
    "sg:city":"Antwerpen",
    "sg:classifiers":[
        {
            "category":"Personal",
            "subcategory":"Beauty Salon",
            "type":"Services"
        }
    ],
    "sg:phone":"+32 3 233 15 66",
    "sg:postcode":"2000",
    "sg:province":"Antwerpen",
    "sg:tags":[
        "lady",
        "-",
        "hairdressing"
    ],
    "wof:name":"Hair",
    "wof:placetype":"venue"
},
  "geometry": {"coordinates":[4.4042100906,51.2196617126],"type":"Point"}
}