{
  "type": "Feature",
  "properties": {
    "addr:full":"Rijsenbergstraat 37 Gent Oost-Vlaanderen 9000",
    "addr:housenumber":"37",
    "addr:postcode":"9000",
    "addr:street":"Rijsenbergstraat;Oost-Vlaanderen",
    "iso:country":"BE",
    "sg:address":"Rijsenbergstraat 37",
    "sg:city":"Gent",
    "sg:classifiers":[
        {
            "category":"Professional",
            "subcategory":"Lawyer & Legal Services",
            "type":"Services"
        }
    ],
    "sg:phone":"+32 9 245 10 28",
    "sg:postcode":"9000",
    "sg:province":"Oost-Vlaanderen",
    "wof:name":"De Schryver Helena",
    "wof:placetype":"venue"
},
  "geometry": {"coordinates":[3.7053160667,51.0399475098],"type":"Point"}
}