{
  "type": "Feature",
  "properties": {
    "addr:full":"Grand'rue 27 Habay (rulles) Luxembourg 6724",
    "addr:housenumber":"27",
    "addr:postcode":"6724",
    "addr:street":"Grand'Rue",
    "iso:country":"BE",
    "sg:address":"Grand'rue 27",
    "sg:city":"Habay (rulles)",
    "sg:classifiers":[
        {
            "category":"Home & Garden",
            "subcategory":"Home Furnishings",
            "type":"Retail Goods"
        }
    ],
    "sg:phone":"+32 63 41 11 22",
    "sg:postcode":"6724",
    "sg:province":"Luxembourg",
    "sg:tags":[
        "-",
        "bed",
        "mattress"
    ],
    "wof:name":"Draux Meubles",
    "wof:placetype":"venue"
},
  "geometry": {"coordinates":[5.5386037827,49.7265663147],"type":"Point"}
}