{
  "type": "Feature",
  "properties": {
    "addr:full":"Diestersteenweg 14 Diest (kaggevinne) Vlaams-Brabant 3293",
    "addr:housenumber":"14",
    "addr:postcode":"3293",
    "addr:street":"Diestersteenweg",
    "iso:country":"BE",
    "sg:address":"Diestersteenweg 14",
    "sg:city":"Diest (kaggevinne)",
    "sg:classifiers":[
        {
            "category":"Professional",
            "subcategory":"Management & Consulting",
            "type":"Services"
        }
    ],
    "sg:phone":"+32 13 31 18 79",
    "sg:postcode":"3293",
    "sg:province":"Vlaams-Brabant",
    "sg:tags":[
        "-",
        "processing",
        "data",
        "consultant"
    ],
    "wof:name":"Quadrivium",
    "wof:placetype":"venue"
},
  "geometry": {"coordinates":[5.0367951393,50.9798164368],"type":"Point"}
}