{
  "type": "Feature",
  "properties": {
    "iso:country":"BE",
    "sg:address":"Rue Des Abliaux 41",
    "sg:city":"Tournai",
    "sg:orig_category":"Epiceries",
    "sg:phone":"+32 69 22 63 85",
    "sg:postcode":"7536",
    "sg:province":"Hainaut",
    "wof:name":"J.p. Jacob",
    "wof:placetype":"venue"
},
  "geometry": {"coordinates":[3.4295599461,50.5903930664],"type":"Point"}
}