{
  "type": "Feature",
  "properties": {
    "addr:full":"Rue Des Trieux 32 La Louvi\u00e8re (houdeng-goegnies) Hainaut 7110",
    "addr:housenumber":"32",
    "addr:postcode":"7110",
    "addr:street":"Rue Des Trieux",
    "iso:country":"BE",
    "sg:address":"Rue Des Trieux 32",
    "sg:city":"La Louvi\u00e8re (houdeng-goegnies)",
    "sg:classifiers":[
        {
            "category":"Retail",
            "subcategory":"Veterinary Services",
            "type":"Services"
        }
    ],
    "sg:phone":"+32 64 22 48 49",
    "sg:postcode":"7110",
    "sg:province":"Hainaut",
    "sg:tags":[
        "veterinarian"
    ],
    "wof:name":"Pierreux A",
    "wof:placetype":"venue"
},
  "geometry": {"coordinates":[4.1505050659,50.4826698303],"type":"Point"}
}