{
  "type": "Feature",
  "properties": {
    "addr:full":"Tildonksesteenweg 155a Herent Vlaams-Brabant 3020",
    "addr:housenumber":"155a",
    "addr:postcode":"3020",
    "addr:street":"Tildonksesteenweg",
    "iso:country":"BE",
    "sg:address":"Tildonksesteenweg 155a",
    "sg:city":"Herent",
    "sg:classifiers":[
        {
            "category":"Retail",
            "subcategory":"Storage",
            "type":"Services"
        }
    ],
    "sg:phone":"+32 16 29 48 24",
    "sg:postcode":"3020",
    "sg:province":"Vlaams-Brabant",
    "sg:tags":[
        "access",
        "-",
        "pigeon",
        "fancier"
    ],
    "wof:name":"Sans Peur Vzw",
    "wof:placetype":"venue"
},
  "geometry": {"coordinates":[4.6656098366,50.9184455872],"type":"Point"}
}