{
  "type": "Feature",
  "properties": {
    "addr:full":"Bevelsesteenweg 4a Nijlen Antwerpen 2560",
    "addr:housenumber":"4a",
    "addr:postcode":"2560",
    "addr:street":"Bevelsesteenweg",
    "iso:country":"BE",
    "sg:address":"Bevelsesteenweg 4a",
    "sg:city":"Nijlen",
    "sg:classifiers":[
        {
            "category":"Insurance",
            "subcategory":"Insurance Agent",
            "type":"Services"
        }
    ],
    "sg:phone":"+32 3 481 86 50",
    "sg:postcode":"2560",
    "sg:province":"Antwerpen",
    "sg:tags":[
        "broker"
    ],
    "wof:name":"Van Roey-michiels",
    "wof:placetype":"venue"
},
  "geometry": {"coordinates":[4.6715230942,51.1597824097],"type":"Point"}
}