{
  "type": "Feature",
  "properties": {
    "addr:full":"Florimond Leirensstraat 26 Wetteren Oost-Vlaanderen 9230",
    "addr:housenumber":"26",
    "addr:postcode":"9230",
    "addr:street":"Florimond Leirensstraat",
    "iso:country":"BE",
    "sg:address":"Florimond Leirensstraat 26",
    "sg:city":"Wetteren",
    "sg:classifiers":[
        {
            "category":"Home & Garden",
            "subcategory":"Household Appliances",
            "type":"Retail Goods"
        }
    ],
    "sg:phone":"+32 9 369 00 94",
    "sg:postcode":"9230",
    "sg:province":"Oost-Vlaanderen",
    "sg:tags":[
        "repair",
        "stove",
        "-"
    ],
    "wof:name":"De Vos",
    "wof:placetype":"venue"
},
  "geometry": {"coordinates":[3.8840210438,51.0055770874],"type":"Point"}
}