{
  "type": "Feature",
  "properties": {
    "iso:country":"BE",
    "sg:address":"Rue Neuve 106",
    "sg:city":"Rhode-saint-gen\u00e8se",
    "sg:classifiers":[
        {
            "category":"Retail",
            "subcategory":"Repair Shop",
            "type":"Services"
        }
    ],
    "sg:phone":"+32 2 380 85 85",
    "sg:postcode":"1640",
    "sg:province":"Vlaams-Brabant",
    "sg:tags":[
        "photographic",
        "equipment",
        "-",
        "accessory"
    ],
    "wof:name":"Flahs Service Center Sprl",
    "wof:placetype":"venue"
},
  "geometry": {"coordinates":[4.3593797684,50.7398757935],"type":"Point"}
}