{
  "type": "Feature",
  "properties": {
    "iso:country":"BE",
    "sg:address":"Rue Du Moulin 2",
    "sg:city":"Etalle",
    "sg:classifiers":[
        {
            "category":"Structure",
            "subcategory":"Office Building",
            "type":"Public Place"
        }
    ],
    "sg:phone":"+32 63 45 62 19",
    "sg:postcode":"6740",
    "sg:province":"Luxembourg",
    "sg:tags":[
        "roofing",
        "slate"
    ],
    "wof:name":"Scor-toitures",
    "wof:placetype":"venue"
},
  "geometry": {"coordinates":[5.6038398743,49.6744613647],"type":"Point"}
}