{
  "type": "Feature",
  "properties": {
    "addr:full":"Jeneverbomenstraat 32 Brussel/bruxelles Bruxelles-Capitale 1020",
    "addr:housenumber":"32",
    "addr:postcode":"1020",
    "addr:street":"Jeneverbomenstraat;/",
    "iso:country":"BE",
    "sg:address":"Jeneverbomenstraat 32",
    "sg:city":"Brussel/bruxelles",
    "sg:orig_category":"Secretariaatsdiensten",
    "sg:phone":"+32 2 479 36 47",
    "sg:postcode":"1020",
    "sg:province":"Bruxelles-Capitale",
    "wof:name":"Fe. Safran",
    "wof:placetype":"venue"
},
  "geometry": {"coordinates":[4.3304238319,50.8993301392],"type":"Point"}
}