{
  "type": "Feature",
  "properties": {
    "addr:full":"Christinastraat 79 Oostende West-Vlaanderen 8400",
    "addr:housenumber":"79",
    "addr:postcode":"8400",
    "addr:street":"Christinastraat",
    "iso:country":"BE",
    "sg:address":"Christinastraat 79",
    "sg:city":"Oostende",
    "sg:classifiers":[
        {
            "category":"Retail",
            "subcategory":"Animal Services",
            "type":"Services"
        }
    ],
    "sg:phone":"+32 59 70 58 25",
    "sg:postcode":"8400",
    "sg:province":"West-Vlaanderen",
    "sg:tags":[
        "grooming",
        "-",
        "dog"
    ],
    "wof:name":"Daisy",
    "wof:placetype":"venue"
},
  "geometry": {"coordinates":[2.917388916,51.2303085327],"type":"Point"}
}