{
  "type": "Feature",
  "properties": {
    "addr:full":"Stevennekens 179 Rijkevorsel Antwerpen 2310",
    "addr:housenumber":"179",
    "addr:postcode":"2310",
    "iso:country":"BE",
    "sg:address":"Stevennekens 179",
    "sg:city":"Rijkevorsel",
    "sg:orig_category":"Benzinestations and brandstoffen",
    "sg:phone":"+32 3 309 12 12",
    "sg:postcode":"2310",
    "sg:province":"Antwerpen",
    "wof:name":"Ota",
    "wof:placetype":"venue"
},
  "geometry": {"coordinates":[4.7701501846,51.3403816223],"type":"Point"}
}