{
  "type": "Feature",
  "properties": {
    "addr:full":"Rue Collet 24 Fernelmont (noville-les-bois) Namur 5380",
    "addr:housenumber":"24",
    "addr:postcode":"5380",
    "addr:street":"Rue Collet",
    "iso:country":"BE",
    "sg:address":"Rue Collet 24",
    "sg:city":"Fernelmont (noville-les-bois)",
    "sg:classifiers":[
        {
            "category":"Professional",
            "subcategory":"Management & Consulting",
            "type":"Services"
        }
    ],
    "sg:phone":"+32 81 83 46 00",
    "sg:postcode":"5380",
    "sg:province":"Namur",
    "sg:tags":[
        "consultant",
        "law"
    ],
    "wof:name":"Delmar",
    "wof:placetype":"venue"
},
  "geometry": {"coordinates":[4.9877681732,50.5602531433],"type":"Point"}
}