{
  "type": "Feature",
  "properties": {
    "iso:country":"BE",
    "sg:address":"Petite Rue Des Loups 34",
    "sg:city":"Anderlecht",
    "sg:orig_category":"Enregistrements sonores. Location d'appareils audio-visuels",
    "sg:phone":"+32 2 520 08 27",
    "sg:postcode":"1070",
    "sg:province":"Bruxelles-Capitale",
    "wof:name":"Fe. Shure",
    "wof:placetype":"venue"
},
  "geometry": {"coordinates":[4.2974348068,50.823638916],"type":"Point"}
}