{
  "type": "Feature",
  "properties": {
    "iso:country":"BE",
    "sg:address":"Zoutelaan 14abc",
    "sg:city":"Knokke-heist",
    "sg:orig_category":"Binnenhuisarchitecten Verlichting and huishoudartikelen Zalen voor culturele evenementen",
    "sg:phone":"+32 50 62 99 97",
    "sg:postcode":"8300",
    "sg:province":"West-Vlaanderen",
    "wof:name":"Atelier Du Zoute",
    "wof:placetype":"venue"
},
  "geometry": {"coordinates":[3.2894608974,51.3489112854],"type":"Point"}
}