{
  "type": "Feature",
  "properties": {
    "addr:full":"Paanhuisstraat 11b2 Diepenbeek Limburg 3590",
    "addr:housenumber":"11b2",
    "addr:postcode":"3590",
    "addr:street":"Paanhuisstraat",
    "iso:country":"BE",
    "sg:address":"Paanhuisstraat 11b2",
    "sg:city":"Diepenbeek",
    "sg:orig_category":"M\u00e9decins and sp\u00e9cialistes",
    "sg:phone":"+32 11 33 19 69",
    "sg:postcode":"3590",
    "sg:province":"Limburg",
    "wof:name":"Tom Smets",
    "wof:placetype":"venue"
},
  "geometry": {"coordinates":[5.4184799194,50.906337738],"type":"Point"}
}