{
  "type": "Feature",
  "properties": {
    "addr:full":"Markgravelei 61 Antwerpen Antwerpen 2018",
    "addr:housenumber":"61",
    "addr:postcode":"2018",
    "addr:street":"Markgravelei",
    "iso:country":"BE",
    "sg:address":"Markgravelei 61",
    "sg:city":"Antwerpen",
    "sg:orig_category":"Pain, p\u00e2tisseries and confiseries",
    "sg:phone":"+32 3 237 81 27",
    "sg:postcode":"2018",
    "sg:province":"Antwerpen",
    "wof:name":"Patisserie Paul",
    "wof:placetype":"venue"
},
  "geometry": {"coordinates":[4.4005889893,51.1997337341],"type":"Point"}
}