{
  "type": "Feature",
  "properties": {
    "addr:full":"Brugse Heirweg 111 Zedelgem West-Vlaanderen 8211",
    "addr:housenumber":"111",
    "addr:postcode":"8211",
    "addr:street":"Brugse Heirweg",
    "iso:country":"BE",
    "sg:address":"Brugse Heirweg 111",
    "sg:city":"Zedelgem",
    "sg:orig_category":"Eleveurs and marchands de porcs. Eleveurs de bovins",
    "sg:phone":"+32 50 20 94 01",
    "sg:postcode":"8211",
    "sg:province":"West-Vlaanderen",
    "wof:name":"Guido Vandamme",
    "wof:placetype":"venue"
},
  "geometry": {"coordinates":[3.1073229313,51.1344451904],"type":"Point"}
}