{
  "type": "Feature",
  "properties": {
    "addr:full":"Rue De Givet 73 Beauraing Namur 5570",
    "addr:housenumber":"73",
    "addr:postcode":"5570",
    "addr:street":"Rue De Givet",
    "iso:country":"BE",
    "sg:address":"Rue De Givet 73",
    "sg:city":"Beauraing",
    "sg:classifiers":[
        {
            "category":"Retail",
            "subcategory":"Veterinary Services",
            "type":"Services"
        }
    ],
    "sg:phone":"+32 82 71 20 10",
    "sg:postcode":"5570",
    "sg:province":"Namur",
    "sg:tags":[
        "veterinarian"
    ],
    "wof:name":"Lambert M",
    "wof:placetype":"venue"
},
  "geometry": {"coordinates":[4.9488239288,50.1128768921],"type":"Point"}
}