{
  "type": "Feature",
  "properties": {
    "addr:full":"Markt 55 Mol Antwerpen 2400",
    "addr:housenumber":"55",
    "addr:postcode":"2400",
    "addr:street":"Markt",
    "iso:country":"BE",
    "sg:address":"Markt 55",
    "sg:city":"Mol",
    "sg:classifiers":[
        {
            "category":"Banks & Credit Unions",
            "subcategory":"Bank",
            "type":"Services"
        }
    ],
    "sg:phone":"+32 14 31 44 47",
    "sg:postcode":"2400",
    "sg:province":"Antwerpen",
    "wof:name":"Caisse Nationale De, Cr\u00e9dit Professionnel",
    "wof:placetype":"venue"
},
  "geometry": {"coordinates":[5.116517067,51.1846046448],"type":"Point"}
}