{
  "type": "Feature",
  "properties": {
    "addr:full":"Dr. Loriersstraat 23 Genk Limburg 3600",
    "addr:housenumber":"23",
    "addr:postcode":"3600",
    "addr:street":"Dr. Loriersstraat",
    "iso:country":"BE",
    "sg:address":"Dr. Loriersstraat 23",
    "sg:city":"Genk",
    "sg:orig_category":"Salles de conf\u00e9rences and de r\u00e9ceptions",
    "sg:phone":"+32 11 22 92 87",
    "sg:postcode":"3600",
    "sg:province":"Limburg",
    "wof:name":"Berk & Brem",
    "wof:placetype":"venue"
},
  "geometry": {"coordinates":[5.4241819382,50.9535827637],"type":"Point"}
}