{
  "type": "Feature",
  "properties": {
    "iso:country":"BE",
    "sg:address":"Rue Duvivier 23",
    "sg:city":"Morlanwelz",
    "sg:orig_category":"Boekhouders",
    "sg:phone":"+32 64 44 45 17",
    "sg:postcode":"7141",
    "sg:province":"Hainaut",
    "wof:name":"Moons Christian",
    "wof:placetype":"venue"
},
  "geometry": {"coordinates":[4.2577199936,50.4433898926],"type":"Point"}
}