{
  "type": "Feature",
  "properties": {
    "iso:country":"BE",
    "sg:address":"Rue Fran\u00c7ois Dewiest 121",
    "sg:city":"Charleroi",
    "sg:orig_category":"Loodgieterij, verwarming and sanitaire installaties",
    "sg:phone":"+32 71 35 55 47",
    "sg:postcode":"6040",
    "sg:province":"Hainaut",
    "wof:name":"Alain Baudaux",
    "wof:placetype":"venue"
},
  "geometry": {"coordinates":[4.4158768654,50.43567276],"type":"Point"}
}