{
  "type": "Feature",
  "properties": {
    "iso:country":"BE",
    "sg:address":"Doncklaan 24",
    "sg:city":"Schoten",
    "sg:classifiers":[
        {
            "category":"Professional",
            "subcategory":"Management & Consulting",
            "type":"Services"
        }
    ],
    "sg:phone":"+32 3 685 66 42",
    "sg:postcode":"2900",
    "sg:province":"Antwerpen",
    "sg:tags":[
        "consultant"
    ],
    "wof:name":"Conscius Bvba",
    "wof:placetype":"venue"
},
  "geometry": {"coordinates":[4.5134878159,51.2540855408],"type":"Point"}
}