{
  "type": "Feature",
  "properties": {
    "iso:country":"BE",
    "sg:address":"Alf.van Den Sandelaan 10",
    "sg:city":"Schilde",
    "sg:orig_category":"V\u00e9t\u00e9rinaires",
    "sg:phone":"+32 3 383 30 85",
    "sg:postcode":"2970",
    "sg:province":"Antwerpen",
    "wof:name":"Bart Wolfs",
    "wof:placetype":"venue"
},
  "geometry": {"coordinates":[4.5912528038,51.2359428406],"type":"Point"}
}