{
  "type": "Feature",
  "properties": {
    "iso:country":"BE",
    "sg:address":"Fays 16ba",
    "sg:city":"Ciney",
    "sg:classifiers":[
        {
            "category":"Professional",
            "subcategory":"Accounting & Tax Preparation",
            "type":"Services"
        }
    ],
    "sg:phone":"+32 83 21 58 43",
    "sg:postcode":"5590",
    "sg:province":"Namur",
    "sg:tags":[
        "accountant"
    ],
    "wof:name":"Joseph Sonnet",
    "wof:placetype":"venue"
},
  "geometry": {"coordinates":[5.0724601746,50.2760314941],"type":"Point"}
}