{
  "type": "Feature",
  "properties": {
    "addr:full":"Smetledestraat 32 Lede (impe) Oost-Vlaanderen 9340",
    "addr:housenumber":"32",
    "addr:postcode":"9340",
    "addr:street":"Smetledestraat",
    "iso:country":"BE",
    "sg:address":"Smetledestraat 32",
    "sg:city":"Lede (impe)",
    "sg:classifiers":[
        {
            "category":"Parking",
            "subcategory":"Lot",
            "type":"Transportation"
        }
    ],
    "sg:phone":"+32 53 80 02 94",
    "sg:postcode":"9340",
    "sg:province":"Oost-Vlaanderen",
    "sg:tags":[
        "-",
        "livestock",
        "transport"
    ],
    "wof:name":"De Smet K",
    "wof:placetype":"venue"
},
  "geometry": {"coordinates":[3.9411430359,50.9667358398],"type":"Point"}
}