{
  "type": "Feature",
  "properties": {
    "addr:full":"J.-b. Labarrestraat 12 Ukkel/uccle Bruxelles-Capitale 1180",
    "addr:housenumber":"12",
    "addr:postcode":"1180",
    "addr:street":"J.-B. Labarrestraat;/",
    "iso:country":"BE",
    "sg:address":"J.-b. Labarrestraat 12",
    "sg:city":"Ukkel/uccle",
    "sg:orig_category":"Geluidsopnames",
    "sg:phone":"+32 2 376 24 11",
    "sg:postcode":"1180",
    "sg:province":"Bruxelles-Capitale",
    "wof:name":"Arrogant Music",
    "wof:placetype":"venue"
},
  "geometry": {"coordinates":[4.3357481956,50.800819397],"type":"Point"}
}