{
  "type": "Feature",
  "properties": {
    "iso:country":"BE",
    "sg:address":"De Heyderstraat 2",
    "sg:city":"Lier",
    "sg:classifiers":[
        {
            "category":"Professional",
            "subcategory":"Accounting & Tax Preparation",
            "type":"Services"
        }
    ],
    "sg:phone":"+32 3 480 07 00",
    "sg:postcode":"2500",
    "sg:province":"Antwerpen",
    "sg:tags":[
        "bookkeeper"
    ],
    "wof:name":"A & C Keppens Bvba",
    "wof:placetype":"venue"
},
  "geometry": {"coordinates":[4.5748038292,51.1317825317],"type":"Point"}
}