{
  "type": "Feature",
  "properties": {
    "addr:full":"Vlamingenstraat 15 Wervik West-Vlaanderen 8940",
    "addr:housenumber":"15",
    "addr:postcode":"8940",
    "addr:street":"Vlamingenstraat",
    "iso:country":"BE",
    "sg:address":"Vlamingenstraat 15",
    "sg:city":"Wervik",
    "sg:orig_category":"Ice-cream parlours",
    "sg:phone":"+32 56 31 20 58",
    "sg:postcode":"8940",
    "sg:province":"West-Vlaanderen",
    "wof:name":"Kapoentje ('t)",
    "wof:placetype":"venue"
},
  "geometry": {"coordinates":[3.0440371037,50.7793083191],"type":"Point"}
}