{
  "type": "Feature",
  "properties": {
    "iso:country":"BE",
    "sg:address":"Avenue Mar\u00e9chal Joffre 147",
    "sg:city":"Bruxelles (uccle)",
    "sg:classifiers":[
        {
            "category":"Personal",
            "subcategory":"Beauty Salon",
            "type":"Services"
        }
    ],
    "sg:postcode":"1180",
    "sg:province":"Bruxelles-Capitale",
    "wof:name":"Frimousse",
    "wof:placetype":"venue"
},
  "geometry": {"coordinates":[4.3381209373,50.8144569397],"type":"Point"}
}