{
  "type": "Feature",
  "properties": {
    "addr:full":"Rue De Void 2 Braives Li\u00e8ge 4260",
    "addr:housenumber":"2",
    "addr:postcode":"4260",
    "addr:street":"Rue De Void",
    "iso:country":"BE",
    "sg:address":"Rue De Void 2",
    "sg:city":"Braives",
    "sg:orig_category":"Cr\u00e8ches and garderies d'enfants",
    "sg:phone":"+32 19 69 89 07",
    "sg:postcode":"4260",
    "sg:province":"Li\u00e8ge",
    "wof:name":"Cr\u00c8che Le Tilleul",
    "wof:placetype":"venue"
},
  "geometry": {"coordinates":[5.0918321609,50.6189842224],"type":"Point"}
}