{
  "type": "Feature",
  "properties": {
    "iso:country":"BE",
    "sg:address":"Avenue De Longwy 0",
    "sg:city":"Arlon",
    "sg:orig_category":"Foto-uitrusting",
    "sg:phone":"+32 63 21 28 81",
    "sg:postcode":"6700",
    "sg:province":"Luxembourg",
    "wof:name":"Gb Centers",
    "wof:placetype":"venue"
},
  "geometry": {"coordinates":[5.82396698,49.6750679016],"type":"Point"}
}