{
  "type": "Feature",
  "properties": {
    "iso:country":"BE",
    "sg:address":"Gentweg 80",
    "sg:city":"Gavere",
    "sg:classifiers":[
        {
            "category":"Retail",
            "subcategory":"Laundry & Dry Cleaning",
            "type":"Services"
        }
    ],
    "sg:phone":"+32 9 384 14 00",
    "sg:postcode":"9890",
    "sg:province":"Oost-Vlaanderen",
    "sg:tags":[
        "dyer",
        "cleaner"
    ],
    "wof:name":"De Clippele",
    "wof:placetype":"venue"
},
  "geometry": {"coordinates":[3.684969902,50.9319114685],"type":"Point"}
}