{
  "type": "Feature",
  "properties": {
    "iso:country":"BE",
    "sg:address":"Rue De Raeren 112",
    "sg:city":"Raeren/raeren",
    "sg:classifiers":[
        {
            "category":"Cafe",
            "type":"Food & Drink"
        }
    ],
    "sg:phone":"+32 87 85 13 86",
    "sg:postcode":"4731",
    "sg:province":"Li\u00e8ge",
    "sg:tags":[
        "caf\u00e9s"
    ],
    "wof:name":"Gastst\u00c4tte Schumacher",
    "wof:placetype":"venue"
},
  "geometry": {"coordinates":[6.0926098824,50.6976699829],"type":"Point"}
}