{
  "type": "Feature",
  "properties": {
    "iso:country":"BE",
    "sg:address":"Rue De Herve 73-75",
    "sg:city":"Herve (battice)",
    "sg:classifiers":[
        {
            "category":"Professional",
            "subcategory":"Management & Consulting",
            "type":"Services"
        }
    ],
    "sg:phone":"+32 87 67 40 95",
    "sg:postcode":"4651",
    "sg:province":"Li\u00e8ge",
    "sg:tags":[
        "tax-consultants"
    ],
    "wof:name":"Paulus L",
    "wof:placetype":"venue"
},
  "geometry": {"coordinates":[5.8114390373,50.646648407],"type":"Point"}
}