{
  "type": "Feature",
  "properties": {
    "iso:country":"BE",
    "sg:address":"Hameau De La Houz\u00e9e 19",
    "sg:city":"Thuin (thuillies)",
    "sg:classifiers":[
        {
            "category":"Professional",
            "subcategory":"Management & Consulting",
            "type":"Services"
        }
    ],
    "sg:phone":"+32 71 53 45 99",
    "sg:postcode":"6536",
    "sg:province":"Hainaut",
    "sg:tags":[
        "consultant"
    ],
    "wof:name":"Tces",
    "wof:placetype":"venue"
},
  "geometry": {"coordinates":[4.3290910721,50.2941627502],"type":"Point"}
}