{
  "type": "Feature",
  "properties": {
    "iso:country":"BE",
    "sg:address":"Rue Des Gaux 13a",
    "sg:city":"Ham-sur-heure-nalinnes (nalinnes)",
    "sg:classifiers":[
        {
            "category":"Landmark",
            "subcategory":"Scenic View",
            "type":"Public Place"
        }
    ],
    "sg:phone":"+32 71 21 35 18",
    "sg:postcode":"6120",
    "sg:province":"Hainaut",
    "sg:tags":[
        "setting",
        "photographic"
    ],
    "wof:name":"Tamigniaux J-m",
    "wof:placetype":"venue"
},
  "geometry": {"coordinates":[4.4506239891,50.3257751465],"type":"Point"}
}