{
  "type": "Feature",
  "properties": {
    "addr:full":"Plantenstraat 44 Hasselt Limburg 3500",
    "addr:housenumber":"44",
    "addr:postcode":"3500",
    "addr:street":"Plantenstraat",
    "iso:country":"BE",
    "sg:address":"Plantenstraat 44",
    "sg:city":"Hasselt",
    "sg:orig_category":"Blanchisseries and teintureries",
    "sg:phone":"+32 11 25 34 15",
    "sg:postcode":"3500",
    "sg:province":"Limburg",
    "wof:name":"Wassalon Cleva",
    "wof:placetype":"venue"
},
  "geometry": {"coordinates":[5.3255691528,50.9353103638],"type":"Point"}
}