{
  "type": "Feature",
  "properties": {
    "iso:country":"BE",
    "sg:address":"Hippokrateslaan 10",
    "sg:city":"Sint-lambrechts-woluwe/woluwe-saint-lambert",
    "sg:orig_category":"Kinderopvang",
    "sg:phone":"+32 2 764 16 64",
    "sg:postcode":"1200",
    "sg:province":"Bruxelles-Capitale",
    "wof:name":"Cr\u00c8che Les Coccinelles",
    "wof:placetype":"venue"
},
  "geometry": {"coordinates":[4.4520468712,50.8528404236],"type":"Point"}
}