{
  "type": "Feature",
  "properties": {
    "iso:country":"BE",
    "sg:address":"Koningen Fabiolalaan 25",
    "sg:city":"Wemmel",
    "sg:orig_category":"Microsoft. Ordinateurs and \u00e9quipement informatique",
    "sg:phone":"+32 2 461 16 29",
    "sg:postcode":"1780",
    "sg:province":"Vlaams-Brabant",
    "wof:name":"Data Networks Belgium",
    "wof:placetype":"venue"
},
  "geometry": {"coordinates":[4.3223400116,50.9025001526],"type":"Point"}
}