{
  "type": "Feature",
  "properties": {
    "iso:country":"BE",
    "sg:address":"Suikerstraat 18",
    "sg:city":"Lede",
    "sg:classifiers":[
        {
            "category":"Building & Trades",
            "subcategory":"Cleaning & Sanitation",
            "type":"Services"
        }
    ],
    "sg:phone":"+32 53 80 63 26",
    "sg:postcode":"9340",
    "sg:province":"Oost-Vlaanderen",
    "sg:tags":[
        "fa\u00e7ade",
        "maintenance"
    ],
    "wof:name":"Vergucht P",
    "wof:placetype":"venue"
},
  "geometry": {"coordinates":[3.9991149902,50.979549408],"type":"Point"}
}