{
  "type": "Feature",
  "properties": {
    "iso:country":"BE",
    "sg:address":"Leeuwerikenstraat 53b3b",
    "sg:city":"Leuven",
    "sg:orig_category":"M\u00e9decins and sp\u00e9cialistes",
    "sg:phone":"+32 16 40 62 47",
    "sg:postcode":"3001",
    "sg:province":"Vlaams-Brabant",
    "wof:name":"Valerie Verhelle",
    "wof:placetype":"venue"
},
  "geometry": {"coordinates":[4.7004652023,50.8609161377],"type":"Point"}
}