{
  "type": "Feature",
  "properties": {
    "iso:country":"BE",
    "sg:address":"Galgestraat 48",
    "sg:city":"Sint-truiden (duras)",
    "sg:classifiers":[
        {
            "category":"Professional",
            "subcategory":"Management & Consulting",
            "type":"Services"
        }
    ],
    "sg:phone":"+32 475 76 54 72",
    "sg:postcode":"3803",
    "sg:province":"Limburg",
    "sg:tags":[
        "consultant",
        "law"
    ],
    "wof:name":"Lode Blokken Bvba",
    "wof:placetype":"venue"
},
  "geometry": {"coordinates":[5.1446142197,50.8306274414],"type":"Point"}
}