{
  "type": "Feature",
  "properties": {
    "iso:country":"BE",
    "sg:address":"'s Gravenstraat 170",
    "sg:city":"Nazareth",
    "sg:classifiers":[
        {
            "category":"Home & Garden",
            "subcategory":"Building Materials",
            "type":"Retail Goods"
        }
    ],
    "sg:phone":"+32 9 385 59 42",
    "sg:postcode":"9810",
    "sg:province":"Oost-Vlaanderen",
    "sg:tags":[
        "granite",
        "stone",
        "natural",
        "marble"
    ],
    "wof:name":"Coryn Bvba",
    "wof:placetype":"venue"
},
  "geometry": {"coordinates":[3.5935280323,50.9525985718],"type":"Point"}
}