{
  "type": "Feature",
  "properties": {
    "addr:full":"Groenstraat 11a Wortegem-petegem (wortegem) Oost-Vlaanderen 9790",
    "addr:housenumber":"11a",
    "addr:postcode":"9790",
    "addr:street":"Groenstraat",
    "iso:country":"BE",
    "sg:address":"Groenstraat 11a",
    "sg:city":"Wortegem-petegem (wortegem)",
    "sg:classifiers":[
        {
            "category":"Health Services",
            "subcategory":"Doctor",
            "type":"Services"
        }
    ],
    "sg:phone":"+32 56 68 04 71",
    "sg:postcode":"9790",
    "sg:province":"Oost-Vlaanderen",
    "sg:tags":[
        "medicinephysicians",
        "surgeon"
    ],
    "wof:name":"Fonteyne K",
    "wof:placetype":"venue"
},
  "geometry": {"coordinates":[3.5184209347,50.8529052734],"type":"Point"}
}