{
  "type": "Feature",
  "properties": {
    "addr:full":"Bieststraat 276 Boortmeerbeek Vlaams-Brabant 3191",
    "addr:housenumber":"276",
    "addr:postcode":"3191",
    "addr:street":"Bieststraat",
    "iso:country":"BE",
    "sg:address":"Bieststraat 276",
    "sg:city":"Boortmeerbeek",
    "sg:orig_category":"Artsen and specialisten",
    "sg:phone":"+32 15 62 30 44",
    "sg:postcode":"3191",
    "sg:province":"Vlaams-Brabant",
    "wof:name":"J. Van Gansberghe",
    "wof:placetype":"venue"
},
  "geometry": {"coordinates":[4.5490899086,50.9831085205],"type":"Point"}
}