{
  "type": "Feature",
  "properties": {
    "iso:country":"BE",
    "sg:address":"Rue Naniot 178",
    "sg:city":"Li\u00c8ge",
    "sg:orig_category":"Art and fournitures artistiques. Reliure and finition",
    "sg:phone":"+32 4 226 14 75",
    "sg:postcode":"4000",
    "sg:province":"Li\u00e8ge",
    "wof:name":"Fe. Jamar V. & J.l.",
    "wof:placetype":"venue"
},
  "geometry": {"coordinates":[5.5586819649,50.6550483704],"type":"Point"}
}