{
  "type": "Feature",
  "properties": {
    "addr:full":"Avenue Du Cimeti\u00c8re De Bruxelles 155 Evere Bruxelles-Capitale 1140",
    "addr:housenumber":"155",
    "addr:postcode":"1140",
    "addr:street":"Avenue Du Cimetie\u0300Re De Bruxelles",
    "iso:country":"BE",
    "sg:address":"Avenue Du Cimeti\u00c8re De Bruxelles 155",
    "sg:city":"Evere",
    "sg:orig_category":"Salles de conf\u00e9rences and de r\u00e9ceptions. Restaurants",
    "sg:phone":"+32 2 726 16 48",
    "sg:postcode":"1140",
    "sg:province":"Bruxelles-Capitale",
    "wof:name":"Les Brasseries Rustiques",
    "wof:placetype":"venue"
},
  "geometry": {"coordinates":[4.4167537689,50.863697052],"type":"Point"}
}