{
  "type": "Feature",
  "properties": {
    "addr:full":"Rue De La Tourette 3 Leuze-en-hainaut Hainaut 7901",
    "addr:housenumber":"3",
    "addr:postcode":"7901",
    "addr:street":"Rue De La Tourette",
    "iso:country":"BE",
    "sg:address":"Rue De La Tourette 3",
    "sg:city":"Leuze-en-hainaut",
    "sg:orig_category":"Traitements param\u00e9dicaux",
    "sg:phone":"+32 69 66 40 32",
    "sg:postcode":"7901",
    "sg:province":"Hainaut",
    "wof:name":"M.a. Wibaut",
    "wof:placetype":"venue"
},
  "geometry": {"coordinates":[3.6091809273,50.617767334],"type":"Point"}
}