{
  "type": "Feature",
  "properties": {
    "iso:country":"BE",
    "sg:address":"Korte Gasthuisstraat 50",
    "sg:city":"Turnhout",
    "sg:orig_category":"Industri\u00eble wasserijen and droogkuis",
    "sg:phone":"+32 14 43 82 52",
    "sg:postcode":"2300",
    "sg:province":"Antwerpen",
    "wof:name":"Washcenter",
    "wof:placetype":"venue"
},
  "geometry": {"coordinates":[4.9446620941,51.3225288391],"type":"Point"}
}