{
  "type": "Feature",
  "properties": {
    "addr:full":"Huisepontweg 107 Nazareth Oost-Vlaanderen 9810",
    "addr:housenumber":"107",
    "addr:postcode":"9810",
    "iso:country":"BE",
    "sg:address":"Huisepontweg 107",
    "sg:city":"Nazareth",
    "sg:orig_category":"Eleveurs and marchands de porcs",
    "sg:phone":"+32 9 386 47 64",
    "sg:postcode":"9810",
    "sg:province":"Oost-Vlaanderen",
    "wof:name":"Johan Clauwaert",
    "wof:placetype":"venue"
},
  "geometry": {"coordinates":[3.5738310814,50.9361190796],"type":"Point"}
}