{
  "type": "Feature",
  "properties": {
    "iso:country":"BE",
    "sg:address":"Chauss\u00c9e D'enghien 177",
    "sg:city":"Soignies",
    "sg:classifiers":[
        {
            "category":"Restaurant",
            "type":"Food & Drink"
        }
    ],
    "sg:phone":"+32 67 34 06 20",
    "sg:postcode":"7060",
    "sg:province":"Hainaut",
    "sg:tags":[
        "caf\u00e9s"
    ],
    "wof:name":"Taverne Le Joncquois",
    "wof:placetype":"venue"
},
  "geometry": {"coordinates":[4.0641870499,50.586643219],"type":"Point"}
}