{
  "type": "Feature",
  "properties": {
    "iso:country":"BE",
    "sg:address":"Herritakkerlaan 3",
    "sg:city":"Evergem (sleidinge)",
    "sg:classifiers":[
        {
            "category":"Health Services",
            "subcategory":"Health Practitioner",
            "type":"Services"
        }
    ],
    "sg:phone":"+32 9 357 26 23",
    "sg:postcode":"9940",
    "sg:province":"Oost-Vlaanderen",
    "sg:tags":[
        "physiotherapist"
    ],
    "wof:name":"Reyniers Sofie",
    "wof:placetype":"venue"
},
  "geometry": {"coordinates":[3.6746640205,51.1300086975],"type":"Point"}
}