{
  "type": "Feature",
  "properties": {
    "iso:country":"BE",
    "sg:address":"Rue De Faisan 16",
    "sg:city":"Mouscron",
    "sg:orig_category":"Procesbesturingssystemen Fab",
    "sg:phone":"+32 56 34 72 29",
    "sg:postcode":"7700",
    "sg:province":"Hainaut",
    "wof:name":"Mazure Guy",
    "wof:placetype":"venue"
},
  "geometry": {"coordinates":[3.2207450867,50.7562904358],"type":"Point"}
}