{
  "type": "Feature",
  "properties": {
    "iso:country":"BE",
    "sg:address":"Rue Duysburgh 26",
    "sg:city":"Bruxelles (jette)",
    "sg:classifiers":[
        {
            "category":"Real Estate",
            "subcategory":"Surveying",
            "type":"Services"
        }
    ],
    "sg:phone":"+32 2 478 00 64",
    "sg:postcode":"1090",
    "sg:province":"Bruxelles-Capitale",
    "sg:tags":[
        "surveyor",
        "land"
    ],
    "wof:name":"De Grave M",
    "wof:placetype":"venue"
},
  "geometry": {"coordinates":[4.3363242149,50.8828964233],"type":"Point"}
}