{
  "type": "Feature",
  "properties": {
    "addr:full":"De Roten 4 Genk Limburg 3600",
    "addr:housenumber":"4",
    "addr:postcode":"3600",
    "addr:street":"De Roten",
    "iso:country":"BE",
    "sg:address":"De Roten 4",
    "sg:city":"Genk",
    "sg:orig_category":"Brood, gebak and snoepgoed",
    "sg:phone":"+32 89 30 65 50",
    "sg:postcode":"3600",
    "sg:province":"Limburg",
    "wof:name":"Stefan Lormans",
    "wof:placetype":"venue"
},
  "geometry": {"coordinates":[5.437432766,50.959236145],"type":"Point"}
}