{
  "type": "Feature",
  "properties": {
    "addr:full":"Rue Du Moulin 5 Pecq Hainaut 7743",
    "addr:housenumber":"5",
    "addr:postcode":"7743",
    "addr:street":"Rue Du Moulin",
    "iso:country":"BE",
    "sg:address":"Rue Du Moulin 5",
    "sg:city":"Pecq",
    "sg:orig_category":"D\u00e9taillants en pi\u00e8ces and accessoires de voitures. Entretien and r\u00e9parations de voitures",
    "sg:phone":"+32 69 55 77 55",
    "sg:postcode":"7743",
    "sg:province":"Hainaut",
    "wof:name":"Jean Menart",
    "wof:placetype":"venue"
},
  "geometry": {"coordinates":[3.361025095,50.6532173157],"type":"Point"}
}