{
  "type": "Feature",
  "properties": {
    "iso:country":"BE",
    "sg:address":"Rue Rey Ain\u00c9 46",
    "sg:city":"Braine-le-comte",
    "sg:orig_category":"M\u00e9decins and sp\u00e9cialistes",
    "sg:phone":"+32 67 55 27 65",
    "sg:postcode":"7090",
    "sg:province":"Hainaut",
    "wof:name":"V. Bruyninx",
    "wof:placetype":"venue"
},
  "geometry": {"coordinates":[4.1404571533,50.6090393066],"type":"Point"}
}