{
  "type": "Feature",
  "properties": {
    "iso:country":"BE",
    "sg:address":"Strandlaan 172b10",
    "sg:city":"Koksijde",
    "sg:orig_category":"Boekhouders",
    "sg:phone":"+32 58 51 97 45",
    "sg:postcode":"8670",
    "sg:province":"West-Vlaanderen",
    "wof:name":"Luc Callebert",
    "wof:placetype":"venue"
},
  "geometry": {"coordinates":[2.6492800713,51.1061401367],"type":"Point"}
}