{
  "type": "Feature",
  "properties": {
    "iso:country":"BE",
    "sg:address":"Sint-truidensesteenweg 95",
    "sg:city":"Linter (orsmaal-gussenhoven)",
    "sg:classifiers":[
        {
            "category":"Bars & Pubs",
            "type":"Food & Drink"
        }
    ],
    "sg:phone":"+32 16 78 20 19",
    "sg:postcode":"3350",
    "sg:province":"Vlaams-Brabant",
    "sg:tags":[
        "tavern"
    ],
    "wof:name":"De Wachtzaal",
    "wof:placetype":"venue"
},
  "geometry": {"coordinates":[5.0503330231,50.8022422791],"type":"Point"}
}