{
  "type": "Feature",
  "properties": {
    "addr:full":"Kopkapelstraat 20 Lokeren Oost-Vlaanderen 9160",
    "addr:housenumber":"20",
    "addr:postcode":"9160",
    "addr:street":"Kopkapelstraat",
    "iso:country":"BE",
    "sg:address":"Kopkapelstraat 20",
    "sg:city":"Lokeren",
    "sg:classifiers":[
        {
            "category":"Health Services",
            "subcategory":"Doctor",
            "type":"Services"
        }
    ],
    "sg:phone":"+32 9 348 57 91",
    "sg:postcode":"9160",
    "sg:province":"Oost-Vlaanderen",
    "sg:tags":[
        "medicinephysicians",
        "surgeon"
    ],
    "wof:name":"Eeckhaute Marc",
    "wof:placetype":"venue"
},
  "geometry": {"coordinates":[4.0001368523,51.116317749],"type":"Point"}
}