{
  "type": "Feature",
  "properties": {
    "addr:full":"Venakker 55 Aalter Oost-Vlaanderen 9880",
    "addr:housenumber":"55",
    "addr:postcode":"9880",
    "addr:street":"Venakker",
    "iso:country":"BE",
    "sg:address":"Venakker 55",
    "sg:city":"Aalter",
    "sg:classifiers":[
        {
            "category":"Arena",
            "subcategory":"Sports Club",
            "type":"Entertainment"
        }
    ],
    "sg:phone":"+32 9 374 48 24",
    "sg:postcode":"9880",
    "sg:province":"Oost-Vlaanderen",
    "sg:tags":[
        "de"
    ],
    "wof:name":"Aalter Sportief",
    "wof:placetype":"venue"
},
  "geometry": {"coordinates":[3.4461390972,51.0990829468],"type":"Point"}
}