{
  "type": "Feature",
  "properties": {
    "iso:country":"BE",
    "sg:address":"Parklaan 19",
    "sg:city":"Turnhout",
    "sg:classifiers":[
        {
            "category":"Restaurant",
            "type":"Food & Drink"
        }
    ],
    "sg:phone":"+32 14 43 00 86",
    "sg:postcode":"2300",
    "sg:province":"Antwerpen",
    "wof:name":"Cr\u00capes \u00b4n Greens",
    "wof:placetype":"venue"
},
  "geometry": {"coordinates":[4.9486398697,51.3125495911],"type":"Point"}
}