{
  "type": "Feature",
  "properties": {
    "iso:country":"BE",
    "sg:address":"Av. Bourg. Jean Materne 112",
    "sg:city":"Namur",
    "sg:orig_category":"Pain, p\u00e2tisseries and confiseries",
    "sg:phone":"+32 81 30 01 99",
    "sg:postcode":"5100",
    "sg:province":"Namur",
    "wof:name":"Maison Pirson",
    "wof:placetype":"venue"
},
  "geometry": {"coordinates":[4.8713750839,50.4566345215],"type":"Point"}
}