{
  "type": "Feature",
  "properties": {
    "iso:country":"BE",
    "sg:address":"Hoekweg 100",
    "sg:city":"Haacht",
    "sg:classifiers":[
        {
            "category":"Building & Trades",
            "subcategory":"Locksmith",
            "type":"Services"
        }
    ],
    "sg:phone":"+32 16 65 71 40",
    "sg:postcode":"3150",
    "sg:province":"Vlaams-Brabant",
    "sg:tags":[
        "lock",
        "key"
    ],
    "wof:name":"Meneve Luc",
    "wof:placetype":"venue"
},
  "geometry": {"coordinates":[4.6214299202,50.983089447],"type":"Point"}
}