{
  "type": "Feature",
  "properties": {
    "iso:country":"BE",
    "sg:address":"Poelstraat 272",
    "sg:city":"Merelbeke (bottelare)",
    "sg:classifiers":[
        {
            "category":"Professional",
            "type":"Services"
        }
    ],
    "sg:phone":"+32 9 233 17 40",
    "sg:postcode":"9820",
    "sg:province":"Oost-Vlaanderen",
    "sg:tags":[
        "forwarding",
        "agency"
    ],
    "wof:name":"Belgian Consulting Company Bvba",
    "wof:placetype":"venue"
},
  "geometry": {"coordinates":[3.7597000599,50.9731407166],"type":"Point"}
}