{
  "type": "Feature",
  "properties": {
    "addr:full":"Kuilensstraat 6 Bree Limburg 3960",
    "addr:housenumber":"6",
    "addr:postcode":"3960",
    "addr:street":"Kuilensstraat",
    "iso:country":"BE",
    "sg:address":"Kuilensstraat 6",
    "sg:city":"Bree",
    "sg:orig_category":"Afbraak- and draineerwerken",
    "sg:phone":"+32 89 47 38 27",
    "sg:postcode":"3960",
    "sg:province":"Limburg",
    "wof:name":"J. Didden",
    "wof:placetype":"venue"
},
  "geometry": {"coordinates":[5.6358880997,51.1464920044],"type":"Point"}
}