{
  "type": "Feature",
  "properties": {
    "iso:country":"BE",
    "sg:address":"E. Blangenoisstraat 65",
    "sg:city":"Schoten",
    "sg:orig_category":"Computers and computerapparatuur Informaticaconsulenten Software ontwikkeling and ontwerp",
    "sg:phone":"+32 3 288 91 72",
    "sg:postcode":"2900",
    "sg:province":"Antwerpen",
    "wof:name":"Kppc",
    "wof:placetype":"venue"
},
  "geometry": {"coordinates":[4.501499176,51.2564315796],"type":"Point"}
}