{
  "type": "Feature",
  "properties": {
    "addr:full":"Behetsstraat 2 Steenokkerzeel Vlaams-Brabant 1820",
    "addr:housenumber":"2",
    "addr:postcode":"1820",
    "addr:street":"Behetsstraat",
    "iso:country":"BE",
    "sg:address":"Behetsstraat 2",
    "sg:city":"Steenokkerzeel",
    "sg:orig_category":"RESTAURANTS: CAF\u00c9S",
    "sg:phone":"+32 2 759 96 21",
    "sg:postcode":"1820",
    "sg:province":"Vlaams-Brabant",
    "wof:name":"Taverne De Markt",
    "wof:placetype":"venue"
},
  "geometry": {"coordinates":[4.5128288269,50.9092292786],"type":"Point"}
}