{
  "type": "Feature",
  "properties": {
    "iso:country":"BE",
    "sg:address":"Klingedorp 61",
    "sg:city":"Sint-gillis-waas",
    "sg:orig_category":"Boucheries",
    "sg:phone":"+32 3 770 81 08",
    "sg:postcode":"9170",
    "sg:province":"Oost-Vlaanderen",
    "wof:name":"Slagerij Dirk",
    "wof:placetype":"venue"
},
  "geometry": {"coordinates":[4.0909938812,51.2581062317],"type":"Point"}
}