{
  "type": "Feature",
  "properties": {
    "addr:full":"Avenue Emile Herman 444b66 Manage Hainaut 7170",
    "addr:housenumber":"444b66",
    "addr:postcode":"7170",
    "addr:street":"Avenue Emile Herman",
    "iso:country":"BE",
    "sg:address":"Avenue Emile Herman 444b66",
    "sg:city":"Manage",
    "sg:orig_category":"Traitements param\u00e9dicaux",
    "sg:phone":"+32 64 22 50 72",
    "sg:postcode":"7170",
    "sg:province":"Hainaut",
    "wof:name":"J. Maes",
    "wof:placetype":"venue"
},
  "geometry": {"coordinates":[4.2269849777,50.4885101318],"type":"Point"}
}