{
  "type": "Feature",
  "properties": {
    "iso:country":"BE",
    "sg:address":"Hertstraat 49",
    "sg:city":"Denderleeuw",
    "sg:orig_category":"Brood, gebak and snoepgoed",
    "sg:phone":"+32 53 68 19 92",
    "sg:postcode":"9473",
    "sg:province":"Oost-Vlaanderen",
    "wof:name":"David Clement",
    "wof:placetype":"venue"
},
  "geometry": {"coordinates":[4.0490150452,50.9022216797],"type":"Point"}
}