{
  "type": "Feature",
  "properties": {
    "iso:country":"BE",
    "sg:address":"Grote Steenweg 54",
    "sg:city":"Nijlen",
    "sg:orig_category":"Rev\u00eatements pour sols and murs. Constructions r\u00e9sidentielles sp\u00e9cifiques. Construction de maisons",
    "sg:phone":"+32 3 480 77 43",
    "sg:postcode":"2560",
    "sg:province":"Antwerpen",
    "wof:name":"Vermeerbergen",
    "wof:placetype":"venue"
},
  "geometry": {"coordinates":[4.636464119,51.1459846497],"type":"Point"}
}