{
  "type": "Feature",
  "properties": {
    "iso:country":"BE",
    "sg:address":"Grand\u00b4place 14",
    "sg:city":"Chimay",
    "sg:orig_category":"Schoenen",
    "sg:phone":"+32 60 21 35 11",
    "sg:postcode":"6460",
    "sg:province":"Hainaut",
    "wof:name":"Shoes In The Box",
    "wof:placetype":"venue"
},
  "geometry": {"coordinates":[4.3148198128,50.0489082336],"type":"Point"}
}