{
  "type": "Feature",
  "properties": {
    "addr:full":"Toc H-straat 37 Poperinge West-Vlaanderen 8970",
    "addr:housenumber":"37",
    "addr:postcode":"8970",
    "iso:country":"BE",
    "sg:address":"Toc H-straat 37",
    "sg:city":"Poperinge",
    "sg:classifiers":[
        {
            "category":"Home & Garden",
            "subcategory":"Kitchen Supply",
            "type":"Retail Goods"
        }
    ],
    "sg:phone":"+32 57 33 50 87",
    "sg:postcode":"8970",
    "sg:province":"West-Vlaanderen",
    "sg:tags":[
        "installation"
    ],
    "wof:name":"Beun Lempiere",
    "wof:placetype":"venue"
},
  "geometry": {"coordinates":[2.7317130566,50.8509101868],"type":"Point"}
}