{
  "type": "Feature",
  "properties": {
    "iso:country":"BE",
    "sg:address":"Hundelgemsesteenweg 575a",
    "sg:city":"Merelbeke",
    "sg:classifiers":[
        {
            "category":"Insurance",
            "subcategory":"Insurance Agent",
            "type":"Services"
        }
    ],
    "sg:phone":"+32 9 252 17 53",
    "sg:postcode":"9820",
    "sg:province":"Oost-Vlaanderen",
    "sg:tags":[
        "broker"
    ],
    "wof:name":"Van Den Berghe W & Zn Bvba",
    "wof:placetype":"venue"
},
  "geometry": {"coordinates":[3.7456901073,50.9828720093],"type":"Point"}
}