{
  "type": "Feature",
  "properties": {
    "addr:full":"Rue Des Ecoles 19 Beloeil (bas\u00e8cles) Hainaut 7971",
    "addr:housenumber":"19",
    "addr:postcode":"7971",
    "addr:street":"Rue Des Ecoles",
    "iso:country":"BE",
    "sg:address":"Rue Des Ecoles 19",
    "sg:city":"Beloeil (bas\u00e8cles)",
    "sg:classifiers":[
        {
            "category":"Shopping",
            "subcategory":"Pharmacy",
            "type":"Retail Goods"
        }
    ],
    "sg:phone":"+32 69 57 78 43",
    "sg:postcode":"7971",
    "sg:province":"Hainaut",
    "sg:tags":[
        "store",
        "drug"
    ],
    "wof:name":"Super Drogueries",
    "wof:placetype":"venue"
},
  "geometry": {"coordinates":[3.6495120525,50.5247383118],"type":"Point"}
}