{
  "type": "Feature",
  "properties": {
    "addr:full":"Rue Des Alli\u00c9s 40 Nassogne Luxembourg 6953",
    "addr:housenumber":"40",
    "addr:postcode":"6953",
    "addr:street":"Rue Des Allie\u0301S",
    "iso:country":"BE",
    "sg:address":"Rue Des Alli\u00c9s 40",
    "sg:city":"Nassogne",
    "sg:orig_category":"Postkantoren Verzekeringsmakelaars and experts",
    "sg:phone":"+32 84 21 18 67",
    "sg:postcode":"6953",
    "sg:province":"Luxembourg",
    "wof:name":"La Poste",
    "wof:placetype":"venue"
},
  "geometry": {"coordinates":[5.2774748802,50.1315689087],"type":"Point"}
}