{
  "type": "Feature",
  "properties": {
    "addr:full":"Waversesteenweg 11 Bonheiden Antwerpen 2820",
    "addr:housenumber":"11",
    "addr:postcode":"2820",
    "addr:street":"Waversesteenweg",
    "iso:country":"BE",
    "sg:address":"Waversesteenweg 11",
    "sg:city":"Bonheiden",
    "sg:classifiers":[
        {
            "category":"Bars & Pubs",
            "type":"Food & Drink"
        }
    ],
    "sg:phone":"+32 15 51 50 16",
    "sg:postcode":"2820",
    "sg:province":"Antwerpen",
    "sg:tags":[
        "tavern"
    ],
    "wof:name":"Blikveld ('t)",
    "wof:placetype":"venue"
},
  "geometry": {"coordinates":[4.5489439964,51.0246086121],"type":"Point"}
}