{
  "type": "Feature",
  "properties": {
    "addr:full":"Dorp 26 Wichelen (schellebelle) Oost-Vlaanderen 9260",
    "addr:housenumber":"26",
    "addr:postcode":"9260",
    "addr:street":"Dorp",
    "iso:country":"BE",
    "sg:address":"Dorp 26",
    "sg:city":"Wichelen (schellebelle)",
    "sg:classifiers":[
        {
            "category":"Bars & Pubs",
            "type":"Food & Drink"
        }
    ],
    "sg:phone":"+32 9 369 16 61",
    "sg:postcode":"9260",
    "sg:province":"Oost-Vlaanderen",
    "wof:name":"Drie Koningen",
    "wof:placetype":"venue"
},
  "geometry": {"coordinates":[3.9714560509,51.0123252869],"type":"Point"}
}