{
  "type": "Feature",
  "properties": {
    "iso:country":"BE",
    "sg:address":"Rue De L'infante 184",
    "sg:city":"Waterloo",
    "sg:orig_category":"Loodgieterij, verwarming and sanitaire installaties",
    "sg:phone":"+32 2 351 17 96",
    "sg:postcode":"1410",
    "sg:province":"Brabant Wallon",
    "wof:name":"Schaekers Jean-michel",
    "wof:placetype":"venue"
},
  "geometry": {"coordinates":[4.3832821846,50.70911026],"type":"Point"}
}