{
  "type": "Feature",
  "properties": {
    "iso:country":"BE",
    "sg:address":"Chee G Richet 157",
    "sg:city":"Lessines",
    "sg:classifiers":[
        {
            "category":"Banks & Credit Unions",
            "subcategory":"Bank",
            "type":"Services"
        }
    ],
    "sg:phone":"+32 68 33 71 70",
    "sg:postcode":"7860",
    "sg:province":"Hainaut",
    "wof:name":"Cr\u00e9dit Agricole",
    "wof:placetype":"venue"
},
  "geometry": {"coordinates":[3.842854023,50.7059440613],"type":"Point"}
}