{
  "type": "Feature",
  "properties": {
    "iso:country":"BE",
    "sg:address":"Phoenixstraat 166",
    "sg:city":"Gent",
    "sg:orig_category":"Kapsalons",
    "sg:phone":"+32 9 226 03 09",
    "sg:postcode":"9000",
    "sg:province":"Oost-Vlaanderen",
    "wof:name":"Coiffure Didier",
    "wof:placetype":"venue"
},
  "geometry": {"coordinates":[3.7046558857,51.0586776733],"type":"Point"}
}