{
  "type": "Feature",
  "properties": {
    "iso:country":"BE",
    "sg:address":"Borgerhoutsendijk 168",
    "sg:city":"Mol",
    "sg:classifiers":[
        {
            "category":"Insurance",
            "subcategory":"Insurance Agent",
            "type":"Services"
        }
    ],
    "sg:phone":"+32 14 31 85 52",
    "sg:postcode":"2400",
    "sg:province":"Antwerpen",
    "sg:tags":[
        "broker"
    ],
    "wof:name":"V A V Bvba",
    "wof:placetype":"venue"
},
  "geometry": {"coordinates":[5.1055397987,51.1689987183],"type":"Point"}
}