{
  "type": "Feature",
  "properties": {
    "iso:country":"BE",
    "sg:address":"Rue De La Fontaine 2ba",
    "sg:city":"Libramont-chevigny",
    "sg:orig_category":"Cr\u00e8ches and garderies d'enfants",
    "sg:phone":"+32 61 22 57 31",
    "sg:postcode":"6800",
    "sg:province":"Luxembourg",
    "wof:name":"Cr\u00c8che Aline Bernard",
    "wof:placetype":"venue"
},
  "geometry": {"coordinates":[5.3761348724,49.9199943542],"type":"Point"}
}