{
  "type": "Feature",
  "properties": {
    "iso:country":"BE",
    "sg:address":"Battelsesteenweg 311",
    "sg:city":"Mechelen",
    "sg:orig_category":"Meubles D\u00e9taillants, Am\u00e9nagement de B\u00e2timents et de Cuisines",
    "sg:phone":"+32 15 42 32 09",
    "sg:postcode":"2800",
    "sg:province":"Antwerpen",
    "wof:name":"Massiform Collection",
    "wof:placetype":"venue"
},
  "geometry": {"coordinates":[4.458591938,51.0326461792],"type":"Point"}
}