{
  "type": "Feature",
  "properties": {
    "iso:country":"BE",
    "sg:address":"Rue D'oth\u00c9e 38",
    "sg:city":"Ans",
    "sg:orig_category":"Cr\u00e9meries. Restaurants",
    "sg:phone":"+32 4 263 02 05",
    "sg:postcode":"4430",
    "sg:province":"Li\u00e8ge",
    "wof:name":"Pasquale Abiuso",
    "wof:placetype":"venue"
},
  "geometry": {"coordinates":[5.5344200134,50.6642570496],"type":"Point"}
}