{
  "type": "Feature",
  "properties": {
    "addr:full":"Parc De La Gotte 38 Nandrin Li\u00e8ge 4550",
    "addr:housenumber":"38",
    "addr:postcode":"4550",
    "addr:street":"Parc De La Gotte",
    "iso:country":"BE",
    "sg:address":"Parc De La Gotte 38",
    "sg:city":"Nandrin",
    "sg:orig_category":"Installation de menuiserie en bois and plastique",
    "sg:phone":"+32 4 372 00 81",
    "sg:postcode":"4550",
    "sg:province":"Li\u00e8ge",
    "wof:name":"Jacques Gaspard",
    "wof:placetype":"venue"
},
  "geometry": {"coordinates":[5.4316239357,50.5248641968],"type":"Point"}
}