{
  "type": "Feature",
  "properties": {
    "iso:country":"BE",
    "sg:address":"Fransveld 49",
    "sg:city":"Mol",
    "sg:classifiers":[
        {
            "category":"Professional",
            "subcategory":"Computer Services",
            "type":"Services"
        }
    ],
    "sg:phone":"+32 14 70 40 10",
    "sg:postcode":"2400",
    "sg:province":"Antwerpen",
    "sg:tags":[
        "-",
        "processing",
        "data"
    ],
    "wof:name":"Technicom Computers",
    "wof:placetype":"venue"
},
  "geometry": {"coordinates":[5.1386442184,51.204284668],"type":"Point"}
}