{
  "type": "Feature",
  "properties": {
    "addr:full":"Puttenhoflaan 14 Schilde Antwerpen 2970",
    "addr:housenumber":"14",
    "addr:postcode":"2970",
    "addr:street":"Puttenhoflaan",
    "iso:country":"BE",
    "sg:address":"Puttenhoflaan 14",
    "sg:city":"Schilde",
    "sg:orig_category":"R\u00e9paration and restauration de meubles",
    "sg:phone":"+32 3 383 03 47",
    "sg:postcode":"2970",
    "sg:province":"Antwerpen",
    "wof:name":"Frank Verschueren",
    "wof:placetype":"venue"
},
  "geometry": {"coordinates":[4.5858941078,51.2324333191],"type":"Point"}
}