{
  "type": "Feature",
  "properties": {
    "addr:full":"Heirstraat 243 Maasmechelen Limburg 3630",
    "addr:housenumber":"243",
    "addr:postcode":"3630",
    "addr:street":"Heirstraat",
    "iso:country":"BE",
    "sg:address":"Heirstraat 243",
    "sg:city":"Maasmechelen",
    "sg:classifiers":[
        {
            "category":"Cafe",
            "type":"Food & Drink"
        }
    ],
    "sg:phone":"+32 89 76 43 57",
    "sg:postcode":"3630",
    "sg:province":"Limburg",
    "sg:tags":[
        "caf\u00e9s"
    ],
    "wof:name":"Jacxav",
    "wof:placetype":"venue"
},
  "geometry": {"coordinates":[5.6933288574,50.9604225159],"type":"Point"}
}