{
  "type": "Feature",
  "properties": {
    "iso:country":"BE",
    "sg:address":"Rue De Nivelles 30",
    "sg:city":"Braine-le-comte",
    "sg:orig_category":"Salles de conf\u00e9rences and de r\u00e9ceptions",
    "sg:phone":"+32 67 64 80 82",
    "sg:postcode":"7090",
    "sg:province":"Hainaut",
    "wof:name":"La Belle Vue Restaurant",
    "wof:placetype":"venue"
},
  "geometry": {"coordinates":[4.228700161,50.6063308716],"type":"Point"}
}