{
  "type": "Feature",
  "properties": {
    "addr:full":"Steenweg Op Turnhout 153 Oud-turnhout Antwerpen 2360",
    "addr:housenumber":"153",
    "addr:postcode":"2360",
    "addr:street":"Steenweg Op Turnhout",
    "iso:country":"BE",
    "sg:address":"Steenweg Op Turnhout 153",
    "sg:city":"Oud-turnhout",
    "sg:orig_category":"Benzinestations and brandstoffen",
    "sg:phone":"+32 14 45 39 08",
    "sg:postcode":"2360",
    "sg:province":"Antwerpen",
    "wof:name":"Jet",
    "wof:placetype":"venue"
},
  "geometry": {"coordinates":[5.0336179733,51.2961120605],"type":"Point"}
}