{
  "type": "Feature",
  "properties": {
    "addr:full":"Grote Heide 2 Bilzen (eigenbilzen) Limburg 3740",
    "addr:housenumber":"2",
    "addr:postcode":"3740",
    "addr:street":"Grote Heide",
    "iso:country":"BE",
    "sg:address":"Grote Heide 2",
    "sg:city":"Bilzen (eigenbilzen)",
    "sg:classifiers":[
        {
            "category":"Farming",
            "subcategory":"Livestock Farm",
            "type":"Manufacturing & Wholesale Goods"
        }
    ],
    "sg:phone":"+32 89 71 46 55",
    "sg:postcode":"3740",
    "sg:province":"Limburg",
    "sg:tags":[
        "poultry",
        "rabbit"
    ],
    "wof:name":"Droogmans R & Zn",
    "wof:placetype":"venue"
},
  "geometry": {"coordinates":[5.5662550926,50.9037780762],"type":"Point"}
}