{
  "type": "Feature",
  "properties": {
    "iso:country":"BE",
    "sg:address":"Tiensesteenweg 328",
    "sg:city":"Bierbeek",
    "sg:orig_category":"M\u00e9decines alternatives. M\u00e9decins and sp\u00e9cialistes",
    "sg:phone":"+32 16 46 19 10",
    "sg:postcode":"3360",
    "sg:province":"Vlaams-Brabant",
    "wof:name":"J. Vanderlinden",
    "wof:placetype":"venue"
},
  "geometry": {"coordinates":[4.797606945,50.8542022705],"type":"Point"}
}