{
  "type": "Feature",
  "properties": {
    "addr:full":"Avenue Des Chevaliers 32 Chaumont-gistoux (dion-valmont) Brabant Wallon 1325",
    "addr:housenumber":"32",
    "addr:postcode":"1325",
    "addr:street":"Avenue Des Chevaliers;Wallon",
    "iso:country":"BE",
    "sg:address":"Avenue Des Chevaliers 32",
    "sg:city":"Chaumont-gistoux (dion-valmont)",
    "sg:classifiers":[
        {
            "category":"Health Services",
            "subcategory":"Doctor",
            "type":"Services"
        }
    ],
    "sg:phone":"+32 10 22 53 35",
    "sg:postcode":"1325",
    "sg:province":"Brabant Wallon",
    "sg:tags":[
        "medicinephysicians",
        "surgeon"
    ],
    "wof:name":"Duchateau Baudouin",
    "wof:placetype":"venue"
},
  "geometry": {"coordinates":[4.638586998,50.6889686584],"type":"Point"}
}