{
  "type": "Feature",
  "properties": {
    "iso:country":"BE",
    "sg:address":"Heiplasweg 31",
    "sg:city":"Lede",
    "sg:classifiers":[
        {
            "category":"Health Services",
            "subcategory":"Doctor",
            "type":"Services"
        }
    ],
    "sg:phone":"+32 53 80 36 10",
    "sg:postcode":"9340",
    "sg:province":"Oost-Vlaanderen",
    "sg:tags":[
        "medicinephysicians",
        "surgeon"
    ],
    "wof:name":"De Bruecker Geert",
    "wof:placetype":"venue"
},
  "geometry": {"coordinates":[3.9777228832,50.9779014587],"type":"Point"}
}