{
  "type": "Feature",
  "properties": {
    "addr:full":"Soef 44 Balen Antwerpen 2490",
    "addr:housenumber":"44",
    "addr:postcode":"2490",
    "addr:street":"Soef",
    "iso:country":"BE",
    "sg:address":"Soef 44",
    "sg:city":"Balen",
    "sg:orig_category":"Installation \u00e9lectrique r\u00e9sidentielle. Installation \u00e9lectrique industrielle",
    "sg:phone":"+32 14 81 21 20",
    "sg:postcode":"2490",
    "sg:province":"Antwerpen",
    "wof:name":"Nuyts",
    "wof:placetype":"venue"
},
  "geometry": {"coordinates":[5.1796569824,51.1781616211],"type":"Point"}
}