{
  "type": "Feature",
  "properties": {
    "addr:full":"Rue Camil Toussaint 96 Mons Hainaut 7021",
    "addr:housenumber":"96",
    "addr:postcode":"7021",
    "addr:street":"Rue Camil Toussaint;Hainaut",
    "iso:country":"BE",
    "sg:address":"Rue Camil Toussaint 96",
    "sg:city":"Mons",
    "sg:orig_category":"Eleveurs de bovins",
    "sg:phone":"+32 65 87 16 63",
    "sg:postcode":"7021",
    "sg:province":"Hainaut",
    "wof:name":"Julien Van Hecke",
    "wof:placetype":"venue"
},
  "geometry": {"coordinates":[4.0456829071,50.4640655518],"type":"Point"}
}