{
  "type": "Feature",
  "properties": {
    "addr:full":"Plaats Vondel 19 Testelt 3288",
    "addr:housenumber":"19",
    "addr:postcode":"3288",
    "addr:street":"Vondel",
    "iso:country":"BE",
    "sg:address":"Plaats Vondel 19",
    "sg:city":"Testelt",
    "sg:classifiers":[
        {
            "category":"Banks & Credit Unions",
            "subcategory":"Bank",
            "type":"Services"
        }
    ],
    "sg:phone":"+32 13 77 53 00",
    "sg:postcode":"3288",
    "wof:name":"Aslk-cger Bank",
    "wof:placetype":"venue"
},
  "geometry": {"coordinates":[4.9548740387,51.0167198181],"type":"Point"}
}