{
  "type": "Feature",
  "properties": {
    "addr:full":"Traveins 107 Box 2 Zottegem (strijpen) Oost-Vlaanderen 9620",
    "addr:housenumber":"107;2",
    "addr:postcode":"9620",
    "addr:street":"Box",
    "iso:country":"BE",
    "sg:address":"Traveins 107 Box 2",
    "sg:city":"Zottegem (strijpen)",
    "sg:orig_category":"Fa\u00e7ade covering",
    "sg:phone":"+32 9 361 17 56",
    "sg:postcode":"9620",
    "sg:province":"Oost-Vlaanderen",
    "wof:name":"Dak-o-gama",
    "wof:placetype":"venue"
},
  "geometry": {"coordinates":[3.8112111092,50.871181488],"type":"Point"}
}