{
  "type": "Feature",
  "properties": {
    "iso:country":"BE",
    "sg:address":"Paleisstraat 7",
    "sg:city":"Antwerpen",
    "sg:classifiers":[
        {
            "category":"Real Estate",
            "subcategory":"Real Estate Services",
            "type":"Services"
        }
    ],
    "sg:phone":"+32 3 248 53 48",
    "sg:postcode":"2018",
    "sg:province":"Antwerpen",
    "wof:name":"Arv Bvba",
    "wof:placetype":"venue"
},
  "geometry": {"coordinates":[4.4026789665,51.2077713013],"type":"Point"}
}