{
  "type": "Feature",
  "properties": {
    "addr:full":"Industriepark-noord 19 Sint-niklaas Oost-Vlaanderen 9100",
    "addr:housenumber":"19",
    "addr:postcode":"9100",
    "addr:street":"Industriepark-Noord",
    "iso:country":"BE",
    "sg:address":"Industriepark-noord 19",
    "sg:city":"Sint-niklaas",
    "sg:orig_category":"Pre-Press Machinery",
    "sg:phone":"+32 3 780 70 70",
    "sg:postcode":"9100",
    "sg:province":"Oost-Vlaanderen",
    "wof:name":"Stralfors Nv",
    "wof:placetype":"venue"
},
  "geometry": {"coordinates":[4.1701412201,51.1496086121],"type":"Point"}
}