{
  "type": "Feature",
  "properties": {
    "addr:full":"Kempische Kaai 89 Hasselt Limburg 3500",
    "addr:housenumber":"89",
    "addr:postcode":"3500",
    "addr:street":"Kempische Kaai",
    "iso:country":"BE",
    "sg:address":"Kempische Kaai 89",
    "sg:city":"Hasselt",
    "sg:orig_category":"Non-Classified Establishments",
    "sg:phone":"+32 11 26 35 71",
    "sg:postcode":"3500",
    "sg:province":"Limburg",
    "wof:name":"Quartes",
    "wof:placetype":"venue"
},
  "geometry": {"coordinates":[5.3408379555,50.9373664856],"type":"Point"}
}