{
  "type": "Feature",
  "properties": {
    "iso:country":"BE",
    "sg:address":"Nieuwstraat 7",
    "sg:city":"Bornem",
    "sg:classifiers":[
        {
            "category":"Shopping",
            "subcategory":"Bicycles & Sporting Goods",
            "type":"Retail Goods"
        }
    ],
    "sg:phone":"+32 3 889 39 20",
    "sg:postcode":"2880",
    "sg:province":"Antwerpen",
    "sg:tags":[
        "article",
        "de",
        "sport",
        "camping"
    ],
    "wof:name":"Birgersport",
    "wof:placetype":"venue"
},
  "geometry": {"coordinates":[4.2350740433,51.0979385376],"type":"Point"}
}