{
  "type": "Feature",
  "properties": {
    "iso:country":"BE",
    "sg:address":"Gr.l.de Lichterveldestr. 61",
    "sg:city":"Dikkelvenne",
    "sg:classifiers":[
        {
            "category":"Shopping",
            "subcategory":"Computers & Home Electronics",
            "type":"Retail Goods"
        }
    ],
    "sg:phone":"+32 9 384 17 01",
    "sg:postcode":"9890",
    "sg:province":"Oost-Vlaanderen",
    "sg:tags":[
        "electric",
        "electricity",
        "component",
        "equipment",
        "electrical",
        "electronic"
    ],
    "wof:name":"L B K International Bvba",
    "wof:placetype":"venue"
},
  "geometry": {"coordinates":[3.7101459503,50.9255447388],"type":"Point"}
}