{
  "type": "Feature",
  "properties": {
    "addr:full":"Molenvloed 2 Herselt Antwerpen 2230",
    "addr:housenumber":"2",
    "addr:postcode":"2230",
    "addr:street":"Molenvloed",
    "iso:country":"BE",
    "sg:address":"Molenvloed 2",
    "sg:city":"Herselt",
    "sg:classifiers":[
        {
            "category":"Retail",
            "subcategory":"Event Space",
            "type":"Services"
        }
    ],
    "sg:phone":"+32 16 56 23 72",
    "sg:postcode":"2230",
    "sg:province":"Antwerpen",
    "sg:tags":[
        "rental",
        "-",
        "hall"
    ],
    "wof:name":"Millfleet Hall",
    "wof:placetype":"venue"
},
  "geometry": {"coordinates":[4.8621687889,51.0406913757],"type":"Point"}
}