{
  "type": "Feature",
  "properties": {
    "addr:full":"Putmanstraat 2ba Waregem West-Vlaanderen 8790",
    "addr:housenumber":"2ba",
    "addr:postcode":"8790",
    "addr:street":"Putmanstraat",
    "iso:country":"BE",
    "sg:address":"Putmanstraat 2ba",
    "sg:city":"Waregem",
    "sg:orig_category":"Installation de menuiserie en bois and plastique",
    "sg:phone":"+32 56 60 87 21",
    "sg:postcode":"8790",
    "sg:province":"West-Vlaanderen",
    "wof:name":"Walter Derammelaere",
    "wof:placetype":"venue"
},
  "geometry": {"coordinates":[3.4279770851,50.8915100098],"type":"Point"}
}