{
  "type": "Feature",
  "properties": {
    "addr:full":"Clos Des Fourboutiers 2 Ath Hainaut 7800",
    "addr:housenumber":"2",
    "addr:postcode":"7800",
    "addr:street":"Clos Des Fourboutiers",
    "iso:country":"BE",
    "sg:address":"Clos Des Fourboutiers 2",
    "sg:city":"Ath",
    "sg:orig_category":"Kapsalons",
    "sg:phone":"+32 68 28 29 25",
    "sg:postcode":"7800",
    "sg:province":"Hainaut",
    "wof:name":"Nadia Auquier",
    "wof:placetype":"venue"
},
  "geometry": {"coordinates":[3.7835769653,50.6164894104],"type":"Point"}
}