{
  "type": "Feature",
  "properties": {
    "addr:full":"Place Emile De Lalieux 42 Nivelles Brabant Wallon 1400",
    "addr:housenumber":"42",
    "addr:postcode":"1400",
    "addr:street":"Place Emile De Lalieux",
    "iso:country":"BE",
    "sg:address":"Place Emile De Lalieux 42",
    "sg:city":"Nivelles",
    "sg:classifiers":[
        {
            "category":"Bars & Pubs",
            "type":"Food & Drink"
        }
    ],
    "sg:phone":"+32 67 22 02 71",
    "sg:postcode":"1400",
    "sg:province":"Brabant Wallon",
    "wof:name":"Charleston (le)",
    "wof:placetype":"venue"
},
  "geometry": {"coordinates":[4.3283481598,50.5979537964],"type":"Point"}
}