{
  "type": "Feature",
  "properties": {
    "iso:country":"BE",
    "sg:address":"Frans Van Der Steenstr. 24",
    "sg:city":"Lennik",
    "sg:orig_category":"M\u00e9decins and sp\u00e9cialistes",
    "sg:phone":"+32 2 532 57 28",
    "sg:postcode":"1750",
    "sg:province":"Vlaams-Brabant",
    "wof:name":"Jean De Leener",
    "wof:placetype":"venue"
},
  "geometry": {"coordinates":[4.1550807953,50.8039131165],"type":"Point"}
}