{
  "type": "Feature",
  "properties": {
    "addr:full":"Rue De Stalle 222 Ukkel/uccle Bruxelles-Capitale 1180",
    "addr:housenumber":"222",
    "addr:postcode":"1180",
    "addr:street":"Rue De Stalle;/",
    "iso:country":"BE",
    "sg:address":"Rue De Stalle 222",
    "sg:city":"Ukkel/uccle",
    "sg:orig_category":"Drukkerijen and copyshops",
    "sg:phone":"+32 2 333 75 90",
    "sg:postcode":"1180",
    "sg:province":"Bruxelles-Capitale",
    "wof:name":"Mister Copy",
    "wof:placetype":"venue"
},
  "geometry": {"coordinates":[4.3251729012,50.7960472107],"type":"Point"}
}