{
  "type": "Feature",
  "properties": {
    "addr:full":"Lange Dijkstraat 3 Dendermonde Oost-Vlaanderen 9200",
    "addr:housenumber":"3",
    "addr:postcode":"9200",
    "addr:street":"Lange Dijkstraat;Oost-Vlaanderen",
    "iso:country":"BE",
    "sg:address":"Lange Dijkstraat 3",
    "sg:city":"Dendermonde",
    "sg:classifiers":[
        {
            "category":"Insurance",
            "subcategory":"Life Insurance",
            "type":"Services"
        }
    ],
    "sg:phone":"+32 52 20 02 16",
    "sg:postcode":"9200",
    "sg:province":"Oost-Vlaanderen",
    "sg:tags":[
        "assurance"
    ],
    "wof:name":"Groep V-invest",
    "wof:placetype":"venue"
},
  "geometry": {"coordinates":[4.1022939682,51.0309104919],"type":"Point"}
}