{
  "type": "Feature",
  "properties": {
    "addr:full":"Diependale 24 Oudenaarde Oost-Vlaanderen 9700",
    "addr:housenumber":"24",
    "addr:postcode":"9700",
    "addr:street":"Diependale",
    "iso:country":"BE",
    "sg:address":"Diependale 24",
    "sg:city":"Oudenaarde",
    "sg:classifiers":[
        {
            "category":"Military Area",
            "subcategory":"Air Force Base",
            "type":"Public Place"
        }
    ],
    "sg:phone":"+32 55 42 42 29",
    "sg:postcode":"9700",
    "sg:province":"Oost-Vlaanderen",
    "sg:tags":[
        "water",
        "treatment"
    ],
    "wof:name":"Gh-systems Bvba",
    "wof:placetype":"venue"
},
  "geometry": {"coordinates":[3.6072199345,50.8375282288],"type":"Point"}
}