{
  "type": "Feature",
  "properties": {
    "addr:full":"Driehoekstraat 88 Haaltert (kerksken) Oost-Vlaanderen 9451",
    "addr:housenumber":"88",
    "addr:postcode":"9451",
    "addr:street":"Driehoekstraat",
    "iso:country":"BE",
    "sg:address":"Driehoekstraat 88",
    "sg:city":"Haaltert (kerksken)",
    "sg:classifiers":[
        {
            "category":"Shopping",
            "subcategory":"Computers & Home Electronics",
            "type":"Retail Goods"
        }
    ],
    "sg:phone":"+32 53 83 29 50",
    "sg:postcode":"9451",
    "sg:province":"Oost-Vlaanderen",
    "sg:tags":[
        "equipment",
        "-"
    ],
    "wof:name":"Optotronics Bvba",
    "wof:placetype":"venue"
},
  "geometry": {"coordinates":[3.9812839031,50.8864326477],"type":"Point"}
}