{
  "type": "Feature",
  "properties": {
    "iso:country":"BE",
    "sg:address":"Rue Auguste Scohy 82",
    "sg:city":"Aiseau-presles",
    "sg:orig_category":"Dakwerken Diverse bouwafwerking and reiniging Gespecialiseerde residenti\u00eble bouw Schilders Schoonmaa",
    "sg:phone":"+32 71 39 70 54",
    "sg:postcode":"6250",
    "sg:province":"Hainaut",
    "wof:name":"Ramotub",
    "wof:placetype":"venue"
},
  "geometry": {"coordinates":[4.5446782112,50.4097595215],"type":"Point"}
}