{
  "type": "Feature",
  "properties": {
    "iso:country":"BE",
    "sg:address":"De Pomp 26",
    "sg:city":"Vilvoorde",
    "sg:classifiers":[
        {
            "category":"Professional",
            "subcategory":"Management & Consulting",
            "type":"Services"
        }
    ],
    "sg:phone":"+32 2 267 31 88",
    "sg:postcode":"1800",
    "sg:province":"Vlaams-Brabant",
    "sg:tags":[
        "tax-consultants"
    ],
    "wof:name":"Gansemans M",
    "wof:placetype":"venue"
},
  "geometry": {"coordinates":[4.3806238174,50.9051055908],"type":"Point"}
}