{
  "type": "Feature",
  "properties": {
    "addr:full":"Rue Des Maquisards 28 Anhee Namur 5537",
    "addr:housenumber":"28",
    "addr:postcode":"5537",
    "addr:street":"Rue Des Maquisards;Namur",
    "iso:country":"BE",
    "sg:address":"Rue Des Maquisards 28",
    "sg:city":"Anhee",
    "sg:orig_category":"Loodgieterij, verwarming and sanitaire installaties",
    "sg:phone":"+32 82 61 25 47",
    "sg:postcode":"5537",
    "sg:province":"Namur",
    "wof:name":"Fernand Botton",
    "wof:placetype":"venue"
},
  "geometry": {"coordinates":[4.8774051666,50.3070144653],"type":"Point"}
}