{
  "type": "Feature",
  "properties": {
    "iso:country":"BE",
    "sg:address":"Xavier De Buestraat 57",
    "sg:city":"Ukkel/uccle",
    "sg:orig_category":"Dameskledingzaken",
    "sg:phone":"+32 2 344 53 29",
    "sg:postcode":"1180",
    "sg:province":"Bruxelles-Capitale",
    "wof:name":"Maison Message",
    "wof:placetype":"venue"
},
  "geometry": {"coordinates":[4.3379969597,50.8032836914],"type":"Point"}
}