{
  "type": "Feature",
  "properties": {
    "addr:full":"Prelaat Deckersstraat 4 Kalmthout Antwerpen 2920",
    "addr:housenumber":"4",
    "addr:postcode":"2920",
    "addr:street":"Prelaat Deckersstraat",
    "iso:country":"BE",
    "sg:address":"Prelaat Deckersstraat 4",
    "sg:city":"Kalmthout",
    "sg:classifiers":[
        {
            "category":"Real Estate",
            "subcategory":"Real Estate Services",
            "type":"Services"
        }
    ],
    "sg:phone":"+32 3 667 33 52",
    "sg:postcode":"2920",
    "sg:province":"Antwerpen",
    "wof:name":"Immo Mathijssen J",
    "wof:placetype":"venue"
},
  "geometry": {"coordinates":[4.5173401833,51.43542099],"type":"Point"}
}