{
  "type": "Feature",
  "properties": {
    "iso:country":"BE",
    "sg:address":"Boulevard D\u00b4avroy 182",
    "sg:city":"Li\u00c8ge",
    "sg:classifiers":[
        {
            "category":"Fast Food",
            "type":"Food & Drink"
        }
    ],
    "sg:phone":"+32 4 222 42 92",
    "sg:postcode":"4000",
    "sg:province":"Li\u00e8ge",
    "sg:tags":[
        "\u00c0",
        "restaurants",
        "emporter",
        "restaurant"
    ],
    "wof:name":"Light Of India",
    "wof:placetype":"venue"
},
  "geometry": {"coordinates":[5.5669460297,50.6335525513],"type":"Point"}
}