{
  "type": "Feature",
  "properties": {
    "iso:country":"BE",
    "sg:address":"Vikingstraat 37",
    "sg:city":"Roeselare",
    "sg:orig_category":"Enseignement maternel and primaire",
    "sg:phone":"+32 51 20 33 12",
    "sg:postcode":"8800",
    "sg:province":"West-Vlaanderen",
    "wof:name":"Bulo De Hagewinde",
    "wof:placetype":"venue"
},
  "geometry": {"coordinates":[3.1076800823,50.9406166077],"type":"Point"}
}