{
  "type": "Feature",
  "properties": {
    "addr:full":"Grand Rue 44 Leuze-en-hainaut Hainaut 7900",
    "addr:housenumber":"44",
    "addr:postcode":"7900",
    "addr:street":"Grand Rue",
    "iso:country":"BE",
    "sg:address":"Grand Rue 44",
    "sg:city":"Leuze-en-hainaut",
    "sg:classifiers":[
        {
            "category":"Autos & Motor Vehicles",
            "subcategory":"Auto Supplies",
            "type":"Retail Goods"
        }
    ],
    "sg:phone":"+32 69 66 43 23",
    "sg:postcode":"7900",
    "sg:province":"Hainaut",
    "sg:tags":[
        "automobile",
        "-",
        "radio"
    ],
    "wof:name":"Videlec Sprl",
    "wof:placetype":"venue"
},
  "geometry": {"coordinates":[3.6188809872,50.5998878479],"type":"Point"}
}