{
  "type": "Feature",
  "properties": {
    "addr:full":"Place Communale 1 Libramont-chevigny Luxembourg 6800",
    "addr:housenumber":"1",
    "addr:postcode":"6800",
    "addr:street":"Place Communale",
    "iso:country":"BE",
    "sg:address":"Place Communale 1",
    "sg:city":"Libramont-chevigny",
    "sg:orig_category":"Mus\u00e9es and patrimoine culturel",
    "sg:phone":"+32 61 22 49 76",
    "sg:postcode":"6800",
    "sg:province":"Luxembourg",
    "wof:name":"Mus\u00c9e Des Celtes",
    "wof:placetype":"venue"
},
  "geometry": {"coordinates":[5.3761348724,49.9199943542],"type":"Point"}
}