{
  "type": "Feature",
  "properties": {
    "addr:full":"All\u00e9e Du Broc \u00e0 L'aye 20 Nivelles Brabant Wallon 1400",
    "addr:housenumber":"20",
    "addr:postcode":"1400",
    "addr:street":"Alle\u0301E Du Broc A\u0300 L'Aye",
    "iso:country":"BE",
    "sg:address":"All\u00e9e Du Broc \u00e0 L'aye 20",
    "sg:city":"Nivelles",
    "sg:classifiers":[
        {
            "category":"Health Services",
            "subcategory":"Doctor",
            "type":"Services"
        }
    ],
    "sg:phone":"+32 67 21 10 56",
    "sg:postcode":"1400",
    "sg:province":"Brabant Wallon",
    "sg:tags":[
        "medicinephysicians",
        "surgeon"
    ],
    "wof:name":"Linard De Guertechin J",
    "wof:placetype":"venue"
},
  "geometry": {"coordinates":[4.3190031052,50.6076011658],"type":"Point"}
}