{
  "type": "Feature",
  "properties": {
    "iso:country":"BE",
    "sg:address":"Huis Ten Halve 35",
    "sg:city":"Zele",
    "sg:classifiers":[
        {
            "category":"Personal",
            "subcategory":"Beauty Salon",
            "type":"Services"
        }
    ],
    "sg:phone":"+32 52 44 74 83",
    "sg:postcode":"9240",
    "sg:province":"Oost-Vlaanderen",
    "sg:tags":[
        "lady",
        "-",
        "hairdressing"
    ],
    "wof:name":"Hair-corner",
    "wof:placetype":"venue"
},
  "geometry": {"coordinates":[4.0424008369,51.0791549683],"type":"Point"}
}