{
  "type": "Feature",
  "properties": {
    "addr:full":"Chauss\u00e9e De Haecht 20 Bruxelles (saint-josse-ten-noode) Bruxelles-Capitale 1210",
    "addr:housenumber":"20",
    "addr:postcode":"1210",
    "addr:street":"Chausse\u0301E De Haecht",
    "iso:country":"BE",
    "sg:address":"Chauss\u00e9e De Haecht 20",
    "sg:city":"Bruxelles (saint-josse-ten-noode)",
    "sg:classifiers":[
        {
            "category":"Home & Garden",
            "subcategory":"Hardware",
            "type":"Retail Goods"
        }
    ],
    "sg:phone":"+32 70 22 40 07",
    "sg:postcode":"1210",
    "sg:province":"Bruxelles-Capitale",
    "sg:tags":[
        "gate",
        "opener",
        "door",
        "automatic"
    ],
    "wof:name":"Carrosserie Saglam Sprl",
    "wof:placetype":"venue"
},
  "geometry": {"coordinates":[4.3673148155,50.8548088074],"type":"Point"}
}