{
  "type": "Feature",
  "properties": {
    "addr:full":"Koppelstraat 45a Dilsen-stokkem (stokkem) Limburg 3650",
    "addr:housenumber":"45a",
    "addr:postcode":"3650",
    "addr:street":"Koppelstraat",
    "iso:country":"BE",
    "sg:address":"Koppelstraat 45a",
    "sg:city":"Dilsen-stokkem (stokkem)",
    "sg:classifiers":[
        {
            "category":"Professional",
            "subcategory":"Engineering",
            "type":"Services"
        }
    ],
    "sg:phone":"+32 89 79 80 70",
    "sg:postcode":"3650",
    "sg:province":"Limburg",
    "sg:tags":[
        "environmental",
        "technique",
        "-"
    ],
    "wof:name":"Vdc Milieu-advies",
    "wof:placetype":"venue"
},
  "geometry": {"coordinates":[5.7247400284,51.0162506104],"type":"Point"}
}