{
  "type": "Feature",
  "properties": {
    "iso:country":"BE",
    "sg:address":"Rue De La Station 15",
    "sg:city":"Beaumont",
    "sg:orig_category":"Voertuigen",
    "sg:phone":"+32 71 53 33 05",
    "sg:postcode":"6511",
    "sg:province":"Hainaut",
    "wof:name":"Gerard Delaunois",
    "wof:placetype":"venue"
},
  "geometry": {"coordinates":[4.3016400337,50.2744750977],"type":"Point"}
}