{
  "type": "Feature",
  "properties": {
    "iso:country":"BE",
    "sg:address":"Bondgenotenlaan 6",
    "sg:city":"Leuven",
    "sg:orig_category":"Baby- and kinderkleding Babyspullen Dameskledingzaken",
    "sg:phone":"+32 16 22 78 30",
    "sg:postcode":"3000",
    "sg:province":"Vlaams-Brabant",
    "wof:name":"Pr\u00c9maman",
    "wof:placetype":"venue"
},
  "geometry": {"coordinates":[4.7036547661,50.8792457581],"type":"Point"}
}