{
  "type": "Feature",
  "properties": {
    "iso:country":"BE",
    "sg:address":"Barbierstraat 20",
    "sg:city":"Kruibeke",
    "sg:orig_category":"Eleveurs and marchands de porcs",
    "sg:phone":"+32 3 774 53 71",
    "sg:postcode":"9150",
    "sg:province":"Oost-Vlaanderen",
    "wof:name":"Alfons Wittock",
    "wof:placetype":"venue"
},
  "geometry": {"coordinates":[4.2950081825,51.1555023193],"type":"Point"}
}