{
  "type": "Feature",
  "properties": {
    "iso:country":"BE",
    "sg:address":"Rue De Landen 12",
    "sg:city":"Hannut",
    "sg:orig_category":"Animaux domestiques and accessoires. Eleveurs d'animaux domestiques",
    "sg:phone":"+32 19 51 38 79",
    "sg:postcode":"4280",
    "sg:province":"Li\u00e8ge",
    "wof:name":"Au Petit Elevage",
    "wof:placetype":"venue"
},
  "geometry": {"coordinates":[5.0793399811,50.672832489],"type":"Point"}
}