{
  "type": "Feature",
  "properties": {
    "addr:full":"Avenue Dolez 103 Box 2 Bruxelles (uccle) Bruxelles-Capitale 1180",
    "addr:housenumber":"103;2",
    "addr:postcode":"1180",
    "addr:street":"Avenue Dolez;Box",
    "iso:country":"BE",
    "sg:address":"Avenue Dolez 103 Box 2",
    "sg:city":"Bruxelles (uccle)",
    "sg:classifiers":[
        {
            "category":"Professional",
            "subcategory":"Art Services",
            "type":"Services"
        }
    ],
    "sg:phone":"+32 2 375 58 25",
    "sg:postcode":"1180",
    "sg:province":"Bruxelles-Capitale",
    "sg:tags":[
        "graphic",
        "designer"
    ],
    "wof:name":"Packmans D",
    "wof:placetype":"venue"
},
  "geometry": {"coordinates":[4.359172821,50.7896537781],"type":"Point"}
}