{
  "type": "Feature",
  "properties": {
    "iso:country":"BE",
    "sg:address":"Schuttersstraat 13",
    "sg:city":"Peer (grote Brogel)",
    "sg:classifiers":[
        {
            "category":"Health Services",
            "subcategory":"Doctor",
            "type":"Services"
        }
    ],
    "sg:phone":"+32 11 63 35 31",
    "sg:postcode":"3990",
    "sg:province":"Limburg",
    "sg:tags":[
        "medicinephysicians",
        "surgeon"
    ],
    "wof:name":"Avontroodt Marnix",
    "wof:placetype":"venue"
},
  "geometry": {"coordinates":[5.5109977722,51.1561965942],"type":"Point"}
}