{
  "type": "Feature",
  "properties": {
    "addr:full":"S Moriytlaan 5b71 Antwerpen Antwerpen 2050",
    "addr:housenumber":"5b71",
    "addr:postcode":"2050",
    "addr:street":"Moriytlaan",
    "iso:country":"BE",
    "sg:address":"S Moriytlaan 5b71",
    "sg:city":"Antwerpen",
    "sg:orig_category":"Diverse grafische activiteiten Film-, tv- and videoproductie Fotografen and fotostudio's",
    "sg:phone":"+32 3 219 18 18",
    "sg:postcode":"2050",
    "sg:province":"Antwerpen",
    "wof:name":"Jp Joined - Productions",
    "wof:placetype":"venue"
},
  "geometry": {"coordinates":[4.3689899445,51.2226295471],"type":"Point"}
}