{
  "type": "Feature",
  "properties": {
    "iso:country":"BE",
    "sg:address":"Rogierlaan 379",
    "sg:city":"Schaarbeek/schaerbeek",
    "sg:orig_category":"Artsen and specialisten",
    "sg:phone":"+32 2 732 28 28",
    "sg:postcode":"1030",
    "sg:province":"Bruxelles-Capitale",
    "wof:name":"Serge Degand",
    "wof:placetype":"venue"
},
  "geometry": {"coordinates":[4.3943839073,50.8555297852],"type":"Point"}
}