{
  "type": "Feature",
  "properties": {
    "iso:country":"BE",
    "sg:address":"Rue De Mont St.-guibert 31",
    "sg:city":"Court-saint-etienne",
    "sg:orig_category":"Enseignement secondaire g\u00e9n\u00e9ral",
    "sg:phone":"+32 10 65 89 69",
    "sg:postcode":"1490",
    "sg:province":"Brabant Wallon",
    "wof:name":"Institut St.etienne",
    "wof:placetype":"venue"
},
  "geometry": {"coordinates":[4.5966491699,50.639995575],"type":"Point"}
}