{
  "type": "Feature",
  "properties": {
    "iso:country":"BE",
    "sg:address":"Drongendreef 44",
    "sg:city":"Moerbeke",
    "sg:orig_category":"Begrafeniswezen Pleisterwerk",
    "sg:phone":"+32 9 346 85 18",
    "sg:postcode":"9180",
    "sg:province":"Oost-Vlaanderen",
    "wof:name":"Gilbert Aerens",
    "wof:placetype":"venue"
},
  "geometry": {"coordinates":[3.941090107,51.1770629883],"type":"Point"}
}