{
  "type": "Feature",
  "properties": {
    "iso:country":"BE",
    "sg:address":"Hoogstraat 15",
    "sg:city":"Gistel",
    "sg:orig_category":"Juwelen and horloges",
    "sg:phone":"+32 59 27 87 70",
    "sg:postcode":"8470",
    "sg:province":"West-Vlaanderen",
    "wof:name":"Mimi Juwelen",
    "wof:placetype":"venue"
},
  "geometry": {"coordinates":[2.9653189182,51.1561546326],"type":"Point"}
}