{
  "type": "Feature",
  "properties": {
    "iso:country":"BE",
    "sg:address":"Rue D'evrehailles 12",
    "sg:city":"Yvoir",
    "sg:classifiers":[
        {
            "category":"Health Services",
            "subcategory":"Health Practitioner",
            "type":"Services"
        }
    ],
    "sg:phone":"+32 82 61 36 21",
    "sg:postcode":"5530",
    "sg:province":"Namur",
    "sg:tags":[
        "physiotherapist"
    ],
    "wof:name":"De Bolle Eric",
    "wof:placetype":"venue"
},
  "geometry": {"coordinates":[4.8794670105,50.3237533569],"type":"Point"}
}