{
  "type": "Feature",
  "properties": {
    "addr:full":"Rue Frenay 1 Bassenge Li\u00e8ge 4690",
    "addr:housenumber":"1",
    "addr:postcode":"4690",
    "addr:street":"Rue Frenay",
    "iso:country":"BE",
    "sg:address":"Rue Frenay 1",
    "sg:city":"Bassenge",
    "sg:classifiers":[
        {
            "category":"Professional",
            "subcategory":"Accounting & Tax Preparation",
            "type":"Services"
        }
    ],
    "sg:phone":"+32 4 286 29 02",
    "sg:postcode":"4690",
    "sg:province":"Li\u00e8ge",
    "sg:tags":[
        "accountant"
    ],
    "wof:name":"Roger Onclin",
    "wof:placetype":"venue"
},
  "geometry": {"coordinates":[5.6109318733,50.7532577515],"type":"Point"}
}