{
  "type": "Feature",
  "properties": {
    "addr:full":"Rue De Charleroi 54 Genappe Brabant Wallon 1470",
    "addr:housenumber":"54",
    "addr:postcode":"1470",
    "addr:street":"Rue De Charleroi;Wallon",
    "iso:country":"BE",
    "sg:address":"Rue De Charleroi 54",
    "sg:city":"Genappe",
    "sg:classifiers":[
        {
            "category":"Restaurant",
            "type":"Food & Drink"
        }
    ],
    "sg:phone":"+32 67 79 01 33",
    "sg:postcode":"1470",
    "sg:province":"Brabant Wallon",
    "wof:name":"Snack Bar Amandine",
    "wof:placetype":"venue"
},
  "geometry": {"coordinates":[4.450111866,50.6089477539],"type":"Point"}
}