{
  "type": "Feature",
  "properties": {
    "iso:country":"BE",
    "sg:address":"Avenue Du Monde 75",
    "sg:city":"Nivelles",
    "sg:classifiers":[
        {
            "category":"Home & Garden",
            "subcategory":"Building Materials",
            "type":"Retail Goods"
        }
    ],
    "sg:phone":"+32 67 22 04 97",
    "sg:postcode":"1400",
    "sg:province":"Brabant Wallon",
    "sg:tags":[
        "insulation",
        "thermical"
    ],
    "wof:name":"Isotrade",
    "wof:placetype":"venue"
},
  "geometry": {"coordinates":[4.3165431023,50.587348938],"type":"Point"}
}