{
  "type": "Feature",
  "properties": {
    "iso:country":"BE",
    "sg:address":"Rue Arthur Oleffe 131",
    "sg:city":"Fleurus (heppignies)",
    "sg:classifiers":[
        {
            "category":"Shopping",
            "subcategory":"Discount & Variety Stores",
            "type":"Retail Goods"
        }
    ],
    "sg:phone":"+32 71 85 15 95",
    "sg:postcode":"6220",
    "sg:province":"Hainaut",
    "sg:tags":[
        "shop",
        "clearers",
        "curiosity",
        "furniture"
    ],
    "wof:name":"Guimin M",
    "wof:placetype":"venue"
},
  "geometry": {"coordinates":[4.4965720177,50.4837303162],"type":"Point"}
}