{
  "type": "Feature",
  "properties": {
    "addr:full":"Vlierlaan 7 De Panne West-Vlaanderen 8660",
    "addr:housenumber":"7",
    "addr:postcode":"8660",
    "addr:street":"Vlierlaan",
    "iso:country":"BE",
    "sg:address":"Vlierlaan 7",
    "sg:city":"De Panne",
    "sg:orig_category":"Rev\u00eatements pour sols and murs. Peinture",
    "sg:phone":"+32 58 42 25 29",
    "sg:postcode":"8660",
    "sg:province":"West-Vlaanderen",
    "wof:name":"Audrey Mortier",
    "wof:placetype":"venue"
},
  "geometry": {"coordinates":[2.5764920712,51.0933876038],"type":"Point"}
}