{
  "type": "Feature",
  "properties": {
    "addr:full":"Rue Benne-brul\u00c9e 76ba Florennes Namur 5621",
    "addr:housenumber":"76ba",
    "addr:postcode":"5621",
    "addr:street":"Rue Benne-Brule\u0301E",
    "iso:country":"BE",
    "sg:address":"Rue Benne-brul\u00c9e 76ba",
    "sg:city":"Florennes",
    "sg:orig_category":"Installation de menuiserie en bois and plastique",
    "sg:phone":"+32 71 68 85 61",
    "sg:postcode":"5621",
    "sg:province":"Namur",
    "wof:name":"E. Charles",
    "wof:placetype":"venue"
},
  "geometry": {"coordinates":[4.5681548119,50.2739334106],"type":"Point"}
}