{
  "type": "Feature",
  "properties": {
    "addr:full":"Rue De La Colline 14 Seraing Li\u00e8ge 4100",
    "addr:housenumber":"14",
    "addr:postcode":"4100",
    "addr:street":"Rue De La Colline",
    "iso:country":"BE",
    "sg:address":"Rue De La Colline 14",
    "sg:city":"Seraing",
    "sg:orig_category":"Gespecialiseerde residenti\u00eble bouw Pleisterwerk",
    "sg:phone":"+32 4 337 19 47",
    "sg:postcode":"4100",
    "sg:province":"Li\u00e8ge",
    "wof:name":"Giovanni Selis",
    "wof:placetype":"venue"
},
  "geometry": {"coordinates":[5.5091061592,50.5951728821],"type":"Point"}
}