{
  "type": "Feature",
  "properties": {
    "iso:country":"BE",
    "sg:address":"Place Notre-dame 5",
    "sg:city":"Pepinster",
    "sg:classifiers":[
        {
            "category":"Communications",
            "subcategory":"Television Station",
            "type":"Services"
        }
    ],
    "sg:phone":"+32 87 46 06 41",
    "sg:postcode":"4860",
    "sg:province":"Li\u00e8ge",
    "sg:tags":[
        "antenna"
    ],
    "wof:name":"Denne",
    "wof:placetype":"venue"
},
  "geometry": {"coordinates":[5.7908802032,50.5746459961],"type":"Point"}
}