{
  "type": "Feature",
  "properties": {
    "addr:full":"Rue Du Pont 14 Huy Li\u00e8ge 4500",
    "addr:housenumber":"14",
    "addr:postcode":"4500",
    "addr:street":"Rue Du Pont",
    "iso:country":"BE",
    "sg:address":"Rue Du Pont 14",
    "sg:city":"Huy",
    "sg:orig_category":"Tijdelijke werkgelegenheid and uitzendkantoren",
    "sg:phone":"+32 85 27 01 56",
    "sg:postcode":"4500",
    "sg:province":"Li\u00e8ge",
    "wof:name":"Sicom Int\u00c9rim",
    "wof:placetype":"venue"
},
  "geometry": {"coordinates":[5.2389068604,50.5190734863],"type":"Point"}
}