{
  "type": "Feature",
  "properties": {
    "addr:full":"Rue Notre-dame De Lorette 3a Qu\u00e9vy (bougnies) Hainaut 7040",
    "addr:housenumber":"3a",
    "addr:postcode":"7040",
    "addr:street":"Rue Notre-Dame De Lorette",
    "iso:country":"BE",
    "sg:address":"Rue Notre-dame De Lorette 3a",
    "sg:city":"Qu\u00e9vy (bougnies)",
    "sg:classifiers":[
        {
            "category":"Home & Garden",
            "subcategory":"Garden Supply",
            "type":"Retail Goods"
        }
    ],
    "sg:phone":"+32 65 56 85 02",
    "sg:postcode":"7040",
    "sg:province":"Hainaut",
    "sg:tags":[
        "machine",
        "agricultural",
        "-"
    ],
    "wof:name":"Gaston Et Fils",
    "wof:placetype":"venue"
},
  "geometry": {"coordinates":[3.9338951111,50.3892555237],"type":"Point"}
}