{
  "type": "Feature",
  "properties": {
    "iso:country":"BE",
    "sg:address":"Avenue Des Combattants 67",
    "sg:city":"Ottignies-louvain-la-neuve",
    "sg:orig_category":"Rijscholen",
    "sg:phone":"+32 10 41 64 43",
    "sg:postcode":"1340",
    "sg:province":"Brabant Wallon",
    "wof:name":"Auto-ecole Raty",
    "wof:placetype":"venue"
},
  "geometry": {"coordinates":[4.5682430267,50.6677627563],"type":"Point"}
}