{
  "type": "Feature",
  "properties": {
    "iso:country":"BE",
    "sg:address":"Doorniksesteenweg 11",
    "sg:city":"Avelgem",
    "sg:classifiers":[
        {
            "category":"Professional",
            "subcategory":"Testing Lab",
            "type":"Services"
        }
    ],
    "sg:phone":"+32 56 64 41 38",
    "sg:postcode":"8580",
    "sg:province":"West-Vlaanderen",
    "sg:tags":[
        "chemist"
    ],
    "wof:name":"Dias - Rodenbach",
    "wof:placetype":"venue"
},
  "geometry": {"coordinates":[3.4447529316,50.7755622864],"type":"Point"}
}