{
  "type": "Feature",
  "properties": {
    "iso:country":"BE",
    "sg:address":"Frans Smeyersstraat 33",
    "sg:city":"Scherpenheuvel-zichem",
    "sg:orig_category":"HUISBRANDOLIE",
    "sg:phone":"+32 13 77 27 74",
    "sg:postcode":"3270",
    "sg:province":"Vlaams-Brabant",
    "wof:name":"Andre Jacquemyn",
    "wof:placetype":"venue"
},
  "geometry": {"coordinates":[4.983962059,50.9706802368],"type":"Point"}
}