{
  "type": "Feature",
  "properties": {
    "addr:full":"Werchtersesteenweg 94 Haacht Vlaams-Brabant 3150",
    "addr:housenumber":"94",
    "addr:postcode":"3150",
    "addr:street":"Werchtersesteenweg",
    "iso:country":"BE",
    "sg:address":"Werchtersesteenweg 94",
    "sg:city":"Haacht",
    "sg:classifiers":[
        {
            "category":"Professional",
            "subcategory":"Printing & Photocopies",
            "type":"Services"
        }
    ],
    "sg:phone":"+32 16 60 01 34",
    "sg:postcode":"3150",
    "sg:province":"Vlaams-Brabant",
    "sg:tags":[
        "-",
        "offset"
    ],
    "wof:name":"Dvf",
    "wof:placetype":"venue"
},
  "geometry": {"coordinates":[4.6475601196,50.9737434387],"type":"Point"}
}