{
  "type": "Feature",
  "properties": {
    "iso:country":"BE",
    "sg:address":"Onteigeningsstraat 41bb",
    "sg:city":"Zelzate",
    "sg:orig_category":"Activit\u00e9s d\u00b4action sociale sans h\u00e9bergement",
    "sg:phone":"+32 9 345 70 35",
    "sg:postcode":"9060",
    "sg:province":"Oost-Vlaanderen",
    "wof:name":"Vclb Rijkscentrum",
    "wof:placetype":"venue"
},
  "geometry": {"coordinates":[3.8158349991,51.1981315613],"type":"Point"}
}