{
  "type": "Feature",
  "properties": {
    "addr:full":"R M 5 Waimes Li\u00e8ge 4950",
    "addr:housenumber":"5",
    "addr:postcode":"4950",
    "iso:country":"BE",
    "sg:address":"R M 5",
    "sg:city":"Waimes",
    "sg:orig_category":"Benzinestations and brandstoffen Herstellingen and onderhoud van auto's Voertuigen",
    "sg:phone":"+32 80 67 81 98",
    "sg:postcode":"4950",
    "sg:province":"Li\u00e8ge",
    "wof:name":"G W",
    "wof:placetype":"venue"
},
  "geometry": {"coordinates":[6.1110301018,50.4149055481],"type":"Point"}
}