{
  "type": "Feature",
  "properties": {
    "addr:full":"Aerts Steyvers Bree Limburg 3690",
    "addr:postcode":"3690",
    "addr:street":"Bree Limburg",
    "iso:country":"BE",
    "sg:address":"Aerts Steyvers",
    "sg:city":"Bree",
    "sg:classifiers":[
        {
            "category":"Banks & Credit Unions",
            "subcategory":"Bank",
            "type":"Services"
        }
    ],
    "sg:phone":"+32 11 46 27 59",
    "sg:postcode":"3690",
    "sg:province":"Limburg",
    "wof:name":"Famibank",
    "wof:placetype":"venue"
},
  "geometry": {"coordinates":[146.84840393069999,-36.1168785095],"type":"Point"}
}