{
  "type": "Feature",
  "properties": {
    "addr:full":"Rue De Gerpinnes 118bb Florennes Namur 5621",
    "addr:housenumber":"118bb",
    "addr:postcode":"5621",
    "addr:street":"Rue De Gerpinnes",
    "iso:country":"BE",
    "sg:address":"Rue De Gerpinnes 118bb",
    "sg:city":"Florennes",
    "sg:orig_category":"M\u00e9decines alternatives",
    "sg:phone":"+32 71 50 10 45",
    "sg:postcode":"5621",
    "sg:province":"Namur",
    "wof:name":"Ost\u00c9opathe Benedini S.",
    "wof:placetype":"venue"
},
  "geometry": {"coordinates":[4.5402498245,50.3101882935],"type":"Point"}
}