{
  "type": "Feature",
  "properties": {
    "addr:full":"Bernard Spaelaan 83 Gent Oost-Vlaanderen 9000",
    "addr:housenumber":"83",
    "addr:postcode":"9000",
    "addr:street":"Bernard Spaelaan;Oost-Vlaanderen",
    "iso:country":"BE",
    "sg:address":"Bernard Spaelaan 83",
    "sg:city":"Gent",
    "sg:orig_category":"Avocats and conseillers juridiques. Balie van Gent",
    "sg:phone":"+32 9 225 30 54",
    "sg:postcode":"9000",
    "sg:province":"Oost-Vlaanderen",
    "wof:name":"Pisart Jos\u00c9",
    "wof:placetype":"venue"
},
  "geometry": {"coordinates":[3.7101569176,51.0492973328],"type":"Point"}
}