{
  "type": "Feature",
  "properties": {
    "iso:country":"BE",
    "sg:address":"Westkaai 5ba",
    "sg:city":"Ieper",
    "sg:orig_category":"Peinture. Rev\u00eatements pour sols and murs",
    "sg:phone":"+32 57 20 68 68",
    "sg:postcode":"8900",
    "sg:province":"West-Vlaanderen",
    "wof:name":"Eric Robeir",
    "wof:placetype":"venue"
},
  "geometry": {"coordinates":[2.8837869167,50.8583526611],"type":"Point"}
}