{
  "type": "Feature",
  "properties": {
    "addr:full":"Torkonjestraat 21f Kortrijk West-Vlaanderen 8510",
    "addr:housenumber":"21f",
    "addr:postcode":"8510",
    "addr:street":"Torkonjestraat",
    "iso:country":"BE",
    "sg:address":"Torkonjestraat 21f",
    "sg:city":"Kortrijk",
    "sg:orig_category":"Mat\u00e9riel scientifique and technique Fab. Installation \u00e9lectrique industrielle. Installation de menui",
    "sg:phone":"+32 56 20 02 40",
    "sg:postcode":"8510",
    "sg:province":"West-Vlaanderen",
    "wof:name":"R.a.s.",
    "wof:placetype":"venue"
},
  "geometry": {"coordinates":[3.2410149574,50.795501709],"type":"Point"}
}