{
  "type": "Feature",
  "properties": {
    "iso:country":"BE",
    "sg:address":"Chauss\u00c9e De Mons 42",
    "sg:city":"La Louviere",
    "sg:orig_category":"MEUBELONTWERP AND -INSTALLATIE",
    "sg:phone":"+32 64 21 19 19",
    "sg:postcode":"7100",
    "sg:province":"Hainaut",
    "wof:name":"Cuisines Top Model",
    "wof:placetype":"venue"
},
  "geometry": {"coordinates":[4.1995410919,50.4645805359],"type":"Point"}
}