{
  "type": "Feature",
  "properties": {
    "iso:country":"BE",
    "sg:address":"Ten Dries 11",
    "sg:city":"Menen",
    "sg:classifiers":[
        {
            "category":"Cafe",
            "type":"Food & Drink"
        }
    ],
    "sg:phone":"+32 56 42 60 90",
    "sg:postcode":"8930",
    "sg:province":"West-Vlaanderen",
    "sg:tags":[
        "caf\u00e9s"
    ],
    "wof:name":"Marc Coussens",
    "wof:placetype":"venue"
},
  "geometry": {"coordinates":[3.1600809097,50.7824478149],"type":"Point"}
}