{
  "type": "Feature",
  "properties": {
    "iso:country":"BE",
    "sg:address":"Sint-michielstraat 38",
    "sg:city":"Tielt",
    "sg:classifiers":[
        {
            "category":"Real Estate",
            "subcategory":"Architect",
            "type":"Services"
        }
    ],
    "sg:phone":"+32 51 40 47 17",
    "sg:postcode":"8700",
    "sg:province":"West-Vlaanderen",
    "wof:name":"Crevits A Mevr",
    "wof:placetype":"venue"
},
  "geometry": {"coordinates":[3.3217248917,50.9976615906],"type":"Point"}
}