{
  "type": "Feature",
  "properties": {
    "iso:country":"BE",
    "sg:address":"Maria Coolstraat 72",
    "sg:city":"Heist-op-den-berg",
    "sg:orig_category":"Groententeelt",
    "sg:phone":"+32 15 23 40 91",
    "sg:postcode":"2223",
    "sg:province":"Antwerpen",
    "wof:name":"Jan Volckaerts",
    "wof:placetype":"venue"
},
  "geometry": {"coordinates":[4.7313241959,51.0295639038],"type":"Point"}
}