{
  "type": "Feature",
  "properties": {
    "addr:full":"Rue Royale 13 Marchienne-au-pont (la Docherie) Hainaut 6030",
    "addr:housenumber":"13",
    "addr:postcode":"6030",
    "addr:street":"Rue Royale;La;Hainaut",
    "iso:country":"BE",
    "sg:address":"Rue Royale 13",
    "sg:city":"Marchienne-au-pont (la Docherie)",
    "sg:orig_category":"Studios photographiques",
    "sg:phone":"+32 71 32 51 68",
    "sg:postcode":"6030",
    "sg:province":"Hainaut",
    "wof:name":"Doll\u00c9 Jean-marie",
    "wof:placetype":"venue"
},
  "geometry": {"coordinates":[4.4113378525,50.4254608154],"type":"Point"}
}