{
  "type": "Feature",
  "properties": {
    "iso:country":"BE",
    "sg:address":"Rue Du Centenaire 68",
    "sg:city":"Boussu",
    "sg:classifiers":[
        {
            "category":"Arena",
            "subcategory":"Sports Club",
            "type":"Entertainment"
        }
    ],
    "sg:phone":"+32 65 77 06 76",
    "sg:postcode":"7300",
    "sg:province":"Hainaut",
    "sg:tags":[
        "de"
    ],
    "wof:name":"B.c. Bouverisois",
    "wof:placetype":"venue"
},
  "geometry": {"coordinates":[3.7956209183,50.4298553467],"type":"Point"}
}