{
  "type": "Feature",
  "properties": {
    "addr:full":"Iepersteenweg 98 Diksmuide (woumen) West-Vlaanderen 8600",
    "addr:housenumber":"98",
    "addr:postcode":"8600",
    "addr:street":"Iepersteenweg",
    "iso:country":"BE",
    "sg:address":"Iepersteenweg 98",
    "sg:city":"Diksmuide (woumen)",
    "sg:classifiers":[
        {
            "category":"Real Estate",
            "subcategory":"Surveying",
            "type":"Services"
        }
    ],
    "sg:phone":"+32 51 54 55 37",
    "sg:postcode":"8600",
    "sg:province":"West-Vlaanderen",
    "sg:tags":[
        "surveyor",
        "land"
    ],
    "wof:name":"Depoorter R",
    "wof:placetype":"venue"
},
  "geometry": {"coordinates":[2.8738849163,50.9861564636],"type":"Point"}
}