{
  "type": "Feature",
  "properties": {
    "addr:full":"\u00b4s Herenbaan 92 Rumst Antwerpen 2840",
    "addr:housenumber":"92",
    "addr:postcode":"2840",
    "addr:street":"\u00b4S Herenbaan",
    "iso:country":"BE",
    "sg:address":"\u00b4s Herenbaan 92",
    "sg:city":"Rumst",
    "sg:orig_category":"Groenten and fruit Gh",
    "sg:phone":"+32 3 844 80 10",
    "sg:postcode":"2840",
    "sg:province":"Antwerpen",
    "wof:name":"Vegromix",
    "wof:placetype":"venue"
},
  "geometry": {"coordinates":[4.3833899498,51.1029930115],"type":"Point"}
}