{
  "type": "Feature",
  "properties": {
    "iso:country":"BE",
    "sg:address":"Vispluk 10",
    "sg:city":"Vorselaar",
    "sg:orig_category":"Rundveehouders",
    "sg:phone":"+32 14 51 18 18",
    "sg:postcode":"2290",
    "sg:province":"Antwerpen",
    "wof:name":"Guido Hendrickx",
    "wof:placetype":"venue"
},
  "geometry": {"coordinates":[4.7798480988,51.2166099548],"type":"Point"}
}