{
  "type": "Feature",
  "properties": {
    "addr:full":"Winterstraat 33 Aarschot Vlaams-Brabant 3201",
    "addr:housenumber":"33",
    "addr:postcode":"3201",
    "addr:street":"Winterstraat",
    "iso:country":"BE",
    "sg:address":"Winterstraat 33",
    "sg:city":"Aarschot",
    "sg:classifiers":[
        {
            "category":"Arena",
            "subcategory":"Sports Club",
            "type":"Entertainment"
        }
    ],
    "sg:phone":"+32 16 56 64 63",
    "sg:postcode":"3201",
    "sg:province":"Vlaams-Brabant",
    "sg:tags":[
        "de"
    ],
    "wof:name":"Goorbikers - Langdorp",
    "wof:placetype":"venue"
},
  "geometry": {"coordinates":[4.8721528053,51.0007286072],"type":"Point"}
}