{
  "type": "Feature",
  "properties": {
    "addr:full":"Avenue De Roodebeek 41 Schaarbeek/schaerbeek Bruxelles-Capitale 1030",
    "addr:housenumber":"41",
    "addr:postcode":"1030",
    "addr:street":"Avenue De Roodebeek",
    "iso:country":"BE",
    "sg:address":"Avenue De Roodebeek 41",
    "sg:city":"Schaarbeek/schaerbeek",
    "sg:orig_category":"Agences de mannequins and h\u00f4tesses",
    "sg:phone":"+32 2 743 45 45",
    "sg:postcode":"1030",
    "sg:province":"Bruxelles-Capitale",
    "wof:name":"Field & Concept",
    "wof:placetype":"venue"
},
  "geometry": {"coordinates":[4.3966751099,50.8475456238],"type":"Point"}
}