{
  "type": "Feature",
  "properties": {
    "addr:full":"Rue Warichet 13 Gembloux-sur-orneau (grand-leez) Namur 5031",
    "addr:housenumber":"13",
    "addr:postcode":"5031",
    "addr:street":"Rue Warichet;Grand-Leez",
    "iso:country":"BE",
    "sg:address":"Rue Warichet 13",
    "sg:city":"Gembloux-sur-orneau (grand-leez)",
    "sg:classifiers":[
        {
            "category":"Professional",
            "subcategory":"Management & Consulting",
            "type":"Services"
        }
    ],
    "sg:phone":"+32 81 22 05 14",
    "sg:postcode":"5031",
    "sg:province":"Namur",
    "sg:tags":[
        "-",
        "processing",
        "data",
        "consultant"
    ],
    "wof:name":"Belhomme P",
    "wof:placetype":"venue"
},
  "geometry": {"coordinates":[4.7852168083,50.5833396912],"type":"Point"}
}