{
  "type": "Feature",
  "properties": {
    "addr:full":"Hoogstraat 17 Meeuwen-gruitrode (meeuwen) Limburg 3670",
    "addr:housenumber":"17",
    "addr:postcode":"3670",
    "addr:street":"Hoogstraat",
    "iso:country":"BE",
    "sg:address":"Hoogstraat 17",
    "sg:city":"Meeuwen-gruitrode (meeuwen)",
    "sg:classifiers":[
        {
            "category":"Bakery",
            "type":"Food & Drink"
        }
    ],
    "sg:phone":"+32 11 79 26 94",
    "sg:postcode":"3670",
    "sg:province":"Limburg",
    "sg:tags":[
        "confectioner",
        "baker"
    ],
    "wof:name":"Fonteyn E",
    "wof:placetype":"venue"
},
  "geometry": {"coordinates":[5.5225458145,51.0948181152],"type":"Point"}
}