{
  "type": "Feature",
  "properties": {
    "iso:country":"BE",
    "sg:address":"Ternatsestraat 68",
    "sg:city":"Affligem (essene)",
    "sg:classifiers":[
        {
            "category":"Real Estate",
            "subcategory":"Architect",
            "type":"Services"
        }
    ],
    "sg:phone":"+32 2 582 07 59",
    "sg:postcode":"1790",
    "sg:province":"Vlaams-Brabant",
    "wof:name":"Paul L",
    "wof:placetype":"venue"
},
  "geometry": {"coordinates":[4.1375179291,50.8983879089],"type":"Point"}
}