{
  "type": "Feature",
  "properties": {
    "addr:full":"Chauss\u00e9e De Nivelles 130 Sombreffe Namur 5140",
    "addr:housenumber":"130",
    "addr:postcode":"5140",
    "addr:street":"Chausse\u0301E De Nivelles",
    "iso:country":"BE",
    "sg:address":"Chauss\u00e9e De Nivelles 130",
    "sg:city":"Sombreffe",
    "sg:classifiers":[
        {
            "category":"Retail",
            "subcategory":"Auto Repair",
            "type":"Services"
        }
    ],
    "sg:phone":"+32 71 88 89 21",
    "sg:postcode":"5140",
    "sg:province":"Namur",
    "sg:tags":[
        "garage"
    ],
    "wof:name":"Gadisseur",
    "wof:placetype":"venue"
},
  "geometry": {"coordinates":[4.5904970169,50.5280265808],"type":"Point"}
}