{
  "type": "Feature",
  "properties": {
    "addr:full":"Dolfijnstraat 71 Antwerpen Antwerpen 2018",
    "addr:housenumber":"71",
    "addr:postcode":"2018",
    "addr:street":"Dolfijnstraat",
    "iso:country":"BE",
    "sg:address":"Dolfijnstraat 71",
    "sg:city":"Antwerpen",
    "sg:classifiers":[
        {
            "category":"Health Services",
            "subcategory":"Health Practitioner",
            "type":"Services"
        }
    ],
    "sg:phone":"+32 3 235 73 54",
    "sg:postcode":"2018",
    "sg:province":"Antwerpen",
    "sg:tags":[
        "physiotherapist"
    ],
    "wof:name":"Haazen Karin",
    "wof:placetype":"venue"
},
  "geometry": {"coordinates":[4.4345569611,51.2085113525],"type":"Point"}
}