{
  "type": "Feature",
  "properties": {
    "addr:full":"Rue Beauvolers 10 Frasnes-lez-anvaing Hainaut 7912",
    "addr:housenumber":"10",
    "addr:postcode":"7912",
    "addr:street":"Rue Beauvolers",
    "iso:country":"BE",
    "sg:address":"Rue Beauvolers 10",
    "sg:city":"Frasnes-lez-anvaing",
    "sg:orig_category":"Rundveehouders",
    "sg:phone":"+32 69 76 70 16",
    "sg:postcode":"7912",
    "sg:province":"Hainaut",
    "wof:name":"Denis Borighem",
    "wof:placetype":"venue"
},
  "geometry": {"coordinates":[3.5919909477,50.7055664062],"type":"Point"}
}