{
  "type": "Feature",
  "properties": {
    "iso:country":"BE",
    "sg:address":"Rue Du Marais 19",
    "sg:city":"Antoing (maubray)",
    "sg:classifiers":[
        {
            "category":"Building & Trades",
            "subcategory":"Electrical",
            "type":"Services"
        }
    ],
    "sg:phone":"+32 69 44 16 10",
    "sg:postcode":"7640",
    "sg:province":"Hainaut",
    "sg:tags":[
        "-",
        "electric",
        "contractor"
    ],
    "wof:name":"A.e.s.",
    "wof:placetype":"venue"
},
  "geometry": {"coordinates":[3.4519898891,50.565738678],"type":"Point"}
}