{
  "type": "Feature",
  "properties": {
    "iso:country":"BE",
    "sg:address":"Beneluxplein 3",
    "sg:city":"Gent",
    "sg:orig_category":"Artsen and specialisten",
    "sg:phone":"+32 9 233 39 69",
    "sg:postcode":"9000",
    "sg:province":"Oost-Vlaanderen",
    "wof:name":"Barbara De Moerloose",
    "wof:placetype":"venue"
},
  "geometry": {"coordinates":[3.7031199932,51.0499839783],"type":"Point"}
}