{
  "type": "Feature",
  "properties": {
    "addr:full":"Rue Du Vicinal 30 Manhay Luxembourg 6960",
    "addr:housenumber":"30",
    "addr:postcode":"6960",
    "addr:street":"Rue Du Vicinal",
    "iso:country":"BE",
    "sg:address":"Rue Du Vicinal 30",
    "sg:city":"Manhay",
    "sg:classifiers":[
        {
            "category":"Fast Food",
            "type":"Food & Drink"
        }
    ],
    "sg:phone":"+32 86 45 56 88",
    "sg:postcode":"6960",
    "sg:province":"Luxembourg",
    "sg:tags":[
        "meeneem",
        "restaurant"
    ],
    "wof:name":"Restaurant Au P'tit Creux",
    "wof:placetype":"venue"
},
  "geometry": {"coordinates":[5.6748971939,50.2928276062],"type":"Point"}
}