{
  "type": "Feature",
  "properties": {
    "addr:full":"Place De Flandre 7 Mons Hainaut 7000",
    "addr:housenumber":"7",
    "addr:postcode":"7000",
    "addr:street":"Place De Flandre;Hainaut",
    "iso:country":"BE",
    "sg:address":"Place De Flandre 7",
    "sg:city":"Mons",
    "sg:classifiers":[
        {
            "category":"Insurance",
            "subcategory":"Life Insurance",
            "type":"Services"
        }
    ],
    "sg:phone":"+32 65 36 30 43",
    "sg:postcode":"7000",
    "sg:province":"Hainaut",
    "sg:tags":[
        "assurance"
    ],
    "wof:name":"Occh",
    "wof:placetype":"venue"
},
  "geometry": {"coordinates":[3.9614961147,50.4532165527],"type":"Point"}
}