{
  "type": "Feature",
  "properties": {
    "iso:country":"BE",
    "sg:address":"Rue Breesch 40",
    "sg:city":"Bruxelles",
    "sg:classifiers":[
        {
            "category":"Professional",
            "subcategory":"Accounting & Tax Preparation",
            "type":"Services"
        }
    ],
    "sg:phone":"+32 2 424 24 55",
    "sg:postcode":"1020",
    "sg:province":"Bruxelles-Capitale",
    "sg:tags":[
        "bookkeeper"
    ],
    "wof:name":"Mordenga M-l",
    "wof:placetype":"venue"
},
  "geometry": {"coordinates":[4.3426141739,50.8773612976],"type":"Point"}
}