{
  "type": "Feature",
  "properties": {
    "addr:full":"Maatheide 104 Lommel Limburg 3920",
    "addr:housenumber":"104",
    "addr:postcode":"3920",
    "addr:street":"Maatheide",
    "iso:country":"BE",
    "sg:address":"Maatheide 104",
    "sg:city":"Lommel",
    "sg:classifiers":[
        {
            "category":"Manufacturing",
            "subcategory":"Tools & Machinery",
            "type":"Manufacturing & Wholesale Goods"
        }
    ],
    "sg:phone":"+32 11 55 17 26",
    "sg:postcode":"3920",
    "sg:province":"Limburg",
    "sg:tags":[
        "metallurgy",
        "metalworking"
    ],
    "wof:name":"Mtb Metal Techniek Belgi\u00cb",
    "wof:placetype":"venue"
},
  "geometry": {"coordinates":[5.2657299042,51.234539032],"type":"Point"}
}