{
  "type": "Feature",
  "properties": {
    "iso:country":"BE",
    "sg:address":"Courtil 65b",
    "sg:city":"Gouvy (bovigny)",
    "sg:classifiers":[
        {
            "category":"Building & Trades",
            "subcategory":"Landscaping Services",
            "type":"Services"
        }
    ],
    "sg:phone":"+32 80 21 43 32",
    "sg:postcode":"6671",
    "sg:province":"Luxembourg",
    "sg:tags":[
        "forestry"
    ],
    "wof:name":"Ista P",
    "wof:placetype":"venue"
},
  "geometry": {"coordinates":[5.9093580246,50.2132911682],"type":"Point"}
}