{
  "type": "Feature",
  "properties": {
    "addr:full":"All\u00c9e Des Cortils 20 Herstal Li\u00e8ge 4041",
    "addr:housenumber":"20",
    "addr:postcode":"4041",
    "addr:street":"Alle\u0301E Des Cortils",
    "iso:country":"BE",
    "sg:address":"All\u00c9e Des Cortils 20",
    "sg:city":"Herstal",
    "sg:orig_category":"M\u00e9decins and sp\u00e9cialistes",
    "sg:phone":"+32 4 228 07 71",
    "sg:postcode":"4041",
    "sg:province":"Li\u00e8ge",
    "wof:name":"P. Hansen",
    "wof:placetype":"venue"
},
  "geometry": {"coordinates":[5.5849199295,50.6724891663],"type":"Point"}
}