{
  "type": "Feature",
  "properties": {
    "addr:full":"Rue Adolphe Braas 26 Faimes Li\u00e8ge 4317",
    "addr:housenumber":"26",
    "addr:postcode":"4317",
    "addr:street":"Rue Adolphe Braas",
    "iso:country":"BE",
    "sg:address":"Rue Adolphe Braas 26",
    "sg:city":"Faimes",
    "sg:classifiers":[
        {
            "category":"Health Services",
            "subcategory":"Nursing And Care Facility",
            "type":"Services"
        }
    ],
    "sg:phone":"+32 19 32 57 57",
    "sg:postcode":"4317",
    "sg:province":"Li\u00e8ge",
    "sg:tags":[
        "public"
    ],
    "wof:name":"C.p.a.s.",
    "wof:placetype":"venue"
},
  "geometry": {"coordinates":[5.25395298,50.6581993103],"type":"Point"}
}