{
  "type": "Feature",
  "properties": {
    "addr:full":"Emiel Clausstraat 35 Waregem (sint-eloois-vijve) West-Vlaanderen 8793",
    "addr:housenumber":"35",
    "addr:postcode":"8793",
    "addr:street":"Emiel Clausstraat",
    "iso:country":"BE",
    "sg:address":"Emiel Clausstraat 35",
    "sg:city":"Waregem (sint-eloois-vijve)",
    "sg:orig_category":"Non-Classified Establishments",
    "sg:phone":"+32 56 32 84 95",
    "sg:postcode":"8793",
    "sg:province":"West-Vlaanderen",
    "wof:name":"M & F",
    "wof:placetype":"venue"
},
  "geometry": {"coordinates":[3.4088089466,50.9098243713],"type":"Point"}
}