{
  "type": "Feature",
  "properties": {
    "iso:country":"BE",
    "sg:address":"Sint-ermelindisstraat 19",
    "sg:city":"Hoegaarden",
    "sg:classifiers":[
        {
            "category":"Cafe",
            "type":"Food & Drink"
        }
    ],
    "sg:phone":"+32 16 76 56 00",
    "sg:postcode":"3320",
    "sg:province":"Vlaams-Brabant",
    "sg:tags":[
        "caf\u00e9s"
    ],
    "wof:name":"Taverne Den Broeder",
    "wof:placetype":"venue"
},
  "geometry": {"coordinates":[4.8372712135,50.7875862122],"type":"Point"}
}