{
  "type": "Feature",
  "properties": {
    "iso:country":"BE",
    "sg:address":"Bissegemsestraat 128",
    "sg:city":"Kortrijk (bissegem)",
    "sg:classifiers":[
        {
            "category":"Building & Trades",
            "subcategory":"Landscaping Services",
            "type":"Services"
        }
    ],
    "sg:phone":"+32 56 37 30 27",
    "sg:postcode":"8501",
    "sg:province":"West-Vlaanderen",
    "sg:tags":[
        "gardening",
        "garden",
        "maintenance"
    ],
    "wof:name":"De Deene G",
    "wof:placetype":"venue"
},
  "geometry": {"coordinates":[3.234126091,50.8269577026],"type":"Point"}
}