{
  "type": "Feature",
  "properties": {
    "iso:country":"BE",
    "sg:address":"Route Du R\u00f4teu 12",
    "sg:city":"Malmedy (beverc\u00e9)",
    "sg:classifiers":[
        {
            "category":"Manufacturing",
            "subcategory":"Lumber",
            "type":"Manufacturing & Wholesale Goods"
        }
    ],
    "sg:phone":"+32 80 33 72 63",
    "sg:postcode":"4960",
    "sg:province":"Li\u00e8ge",
    "sg:tags":[
        "timber"
    ],
    "wof:name":"Scholzen-dehottay Ets Sa",
    "wof:placetype":"venue"
},
  "geometry": {"coordinates":[6.04961586,50.4511909485],"type":"Point"}
}