{
  "type": "Feature",
  "properties": {
    "iso:country":"BE",
    "sg:address":"Nati\u00cbnlaan 159ba",
    "sg:city":"Knokke-heist",
    "sg:orig_category":"Benzinestations and brandstoffen",
    "sg:phone":"+32 50 60 38 85",
    "sg:postcode":"8300",
    "sg:province":"West-Vlaanderen",
    "wof:name":"Boon",
    "wof:placetype":"venue"
},
  "geometry": {"coordinates":[3.2890501022,51.3361816406],"type":"Point"}
}