{
  "type": "Feature",
  "properties": {
    "iso:country":"BE",
    "sg:address":"Tiensestraat 81",
    "sg:city":"Hoegaarden",
    "sg:classifiers":[
        {
            "category":"Bars & Pubs",
            "type":"Food & Drink"
        }
    ],
    "sg:phone":"+32 16 76 73 46",
    "sg:postcode":"3320",
    "sg:province":"Vlaams-Brabant",
    "wof:name":"Pax",
    "wof:placetype":"venue"
},
  "geometry": {"coordinates":[4.8937621117,50.7773551941],"type":"Point"}
}