{
  "type": "Feature",
  "properties": {
    "iso:country":"BE",
    "sg:address":"Nollekensstraat 43",
    "sg:city":"Essen",
    "sg:orig_category":"Installation de menuiserie en bois and plastique",
    "sg:phone":"+32 3 667 64 90",
    "sg:postcode":"2910",
    "sg:province":"Antwerpen",
    "wof:name":"Luc Peeters",
    "wof:placetype":"venue"
},
  "geometry": {"coordinates":[4.4725670815,51.471824646],"type":"Point"}
}