{
  "type": "Feature",
  "properties": {
    "iso:country":"BE",
    "sg:address":"Hofstraat 6-6",
    "sg:city":"Herk-de-stad",
    "sg:classifiers":[
        {
            "category":"Building & Trades",
            "subcategory":"Construction",
            "type":"Services"
        }
    ],
    "sg:phone":"+32 13 55 20 34",
    "sg:postcode":"3540",
    "sg:province":"Limburg",
    "sg:tags":[
        "stucco",
        "contractor"
    ],
    "wof:name":"Heynen Nv",
    "wof:placetype":"venue"
},
  "geometry": {"coordinates":[5.1675348282,50.9399452209],"type":"Point"}
}