{
  "type": "Feature",
  "properties": {
    "addr:full":"Rue Des Champs Verts 69 Namur Namur 5020",
    "addr:housenumber":"69",
    "addr:postcode":"5020",
    "addr:street":"Rue Des Champs Verts",
    "iso:country":"BE",
    "sg:address":"Rue Des Champs Verts 69",
    "sg:city":"Namur",
    "sg:orig_category":"Woningbouw",
    "sg:phone":"+32 81 21 55 97",
    "sg:postcode":"5020",
    "sg:province":"Namur",
    "wof:name":"Champion Construct",
    "wof:placetype":"venue"
},
  "geometry": {"coordinates":[4.8897199631,50.4960289001],"type":"Point"}
}