{
  "type": "Feature",
  "properties": {
    "iso:country":"BE",
    "sg:address":"Puvinagestraat 15",
    "sg:city":"Vloesberg/flobecq",
    "sg:classifiers":[
        {
            "category":"Restaurant",
            "type":"Food & Drink"
        }
    ],
    "sg:phone":"+32 68 44 75 18",
    "sg:postcode":"7880",
    "sg:province":"Hainaut",
    "sg:tags":[
        "caf\u00e9s"
    ],
    "wof:name":"Taverne Le Puvinage",
    "wof:placetype":"venue"
},
  "geometry": {"coordinates":[3.7384300232,50.7368011475],"type":"Point"}
}