{
  "type": "Feature",
  "properties": {
    "iso:country":"BE",
    "sg:address":"Place Bara 7",
    "sg:city":"Bruxelles (anderlecht)",
    "sg:orig_category":"Non-Classified Establishments",
    "sg:phone":"+32 2 522 05 19",
    "sg:postcode":"1070",
    "sg:province":"Bruxelles-Capitale",
    "wof:name":"Atmosphere Bvba",
    "wof:placetype":"venue"
},
  "geometry": {"coordinates":[4.336160183,50.8396110535],"type":"Point"}
}