{
  "type": "Feature",
  "properties": {
    "iso:country":"BE",
    "sg:address":"Sint-guthagostraat 2",
    "sg:city":"Damme",
    "sg:orig_category":"Enseignement maternel and primaire",
    "sg:phone":"+32 50 60 77 14",
    "sg:postcode":"8340",
    "sg:province":"West-Vlaanderen",
    "wof:name":"Vrije Basisschool",
    "wof:placetype":"venue"
},
  "geometry": {"coordinates":[3.2955999374,51.2785301208],"type":"Point"}
}