{
  "type": "Feature",
  "properties": {
    "addr:full":"Sint-katharinastraat 131 Kortrijk (heule) West-Vlaanderen 8501",
    "addr:housenumber":"131",
    "addr:postcode":"8501",
    "addr:street":"Sint-Katharinastraat",
    "iso:country":"BE",
    "sg:address":"Sint-katharinastraat 131",
    "sg:city":"Kortrijk (heule)",
    "sg:classifiers":[
        {
            "category":"Bars & Pubs",
            "type":"Food & Drink"
        }
    ],
    "sg:phone":"+32 56 35 19 95",
    "sg:postcode":"8501",
    "sg:province":"West-Vlaanderen",
    "wof:name":"De Groene Dreve",
    "wof:placetype":"venue"
},
  "geometry": {"coordinates":[3.2366600037,50.8696746826],"type":"Point"}
}