{
  "type": "Feature",
  "properties": {
    "iso:country":"BE",
    "sg:address":"Landbouwersstraat 29",
    "sg:city":"De Panne",
    "sg:classifiers":[
        {
            "category":"Building & Trades",
            "subcategory":"Pest Control",
            "type":"Services"
        }
    ],
    "sg:phone":"+32 486 34 30 04",
    "sg:postcode":"8660",
    "sg:province":"West-Vlaanderen",
    "sg:tags":[
        "painting",
        "contractor"
    ],
    "wof:name":"De Buyst F",
    "wof:placetype":"venue"
},
  "geometry": {"coordinates":[2.6157400608,51.0937614441],"type":"Point"}
}