{
  "type": "Feature",
  "properties": {
    "addr:full":"De Keyserlei 30b6 Antwerpen Antwerpen 2018",
    "addr:housenumber":"30b6",
    "addr:postcode":"2018",
    "addr:street":"De Keyserlei",
    "iso:country":"BE",
    "sg:address":"De Keyserlei 30b6",
    "sg:city":"Antwerpen",
    "sg:orig_category":"Brood, gebak and snoepgoed",
    "sg:phone":"+32 3 226 88 00",
    "sg:postcode":"2018",
    "sg:province":"Antwerpen",
    "wof:name":"Godiva",
    "wof:placetype":"venue"
},
  "geometry": {"coordinates":[4.4183340073,51.2176971436],"type":"Point"}
}