{
  "type": "Feature",
  "properties": {
    "iso:country":"BE",
    "sg:address":"Ten Berg 76",
    "sg:city":"Aalst",
    "sg:classifiers":[
        {
            "category":"Retail",
            "subcategory":"Repair Shop",
            "type":"Services"
        }
    ],
    "sg:phone":"+32 53 77 21 27",
    "sg:postcode":"9300",
    "sg:province":"Oost-Vlaanderen",
    "sg:tags":[
        "upholsterer"
    ],
    "wof:name":"Tancker\u00e9 R",
    "wof:placetype":"venue"
},
  "geometry": {"coordinates":[4.0659780502,50.9367103577],"type":"Point"}
}