{
  "type": "Feature",
  "properties": {
    "addr:full":"Afrikalaan 203 Gent Oost-Vlaanderen 9000",
    "addr:housenumber":"203",
    "addr:postcode":"9000",
    "addr:street":"Afrikalaan;Oost-Vlaanderen",
    "iso:country":"BE",
    "sg:address":"Afrikalaan 203",
    "sg:city":"Gent",
    "sg:orig_category":"Mat\u00e9riel pour plomberie and chauffage Machines-outils Gr",
    "sg:phone":"+32 9 255 55 55",
    "sg:postcode":"9000",
    "sg:province":"Oost-Vlaanderen",
    "wof:name":"Verkoop Carnoy Negoce",
    "wof:placetype":"venue"
},
  "geometry": {"coordinates":[3.7376730442,51.070526123],"type":"Point"}
}