{
  "type": "Feature",
  "properties": {
    "iso:country":"BE",
    "sg:address":"Wijngaardstraat 5",
    "sg:city":"Oudenaarde",
    "sg:classifiers":[
        {
            "category":"Insurance",
            "subcategory":"Insurance Agent",
            "type":"Services"
        }
    ],
    "sg:phone":"+32 55 31 65 65",
    "sg:postcode":"9700",
    "sg:province":"Oost-Vlaanderen",
    "sg:tags":[
        "verzekeringsmakelaars",
        "expert"
    ],
    "wof:name":"Herberigs Verzekeringen",
    "wof:placetype":"venue"
},
  "geometry": {"coordinates":[3.6028399467,50.8460121155],"type":"Point"}
}