{
  "type": "Feature",
  "properties": {
    "addr:full":"Heistraat 28 Geel Antwerpen 2440",
    "addr:housenumber":"28",
    "addr:postcode":"2440",
    "addr:street":"Heistraat",
    "iso:country":"BE",
    "sg:address":"Heistraat 28",
    "sg:city":"Geel",
    "sg:classifiers":[
        {
            "category":"Health Services",
            "subcategory":"Health Practitioner",
            "type":"Services"
        }
    ],
    "sg:phone":"+32 14 58 70 21",
    "sg:postcode":"2440",
    "sg:province":"Antwerpen",
    "sg:tags":[
        "physiotherapist"
    ],
    "wof:name":"Bauters Isabelle",
    "wof:placetype":"venue"
},
  "geometry": {"coordinates":[4.9903850555,51.1693496704],"type":"Point"}
}