{
  "type": "Feature",
  "properties": {
    "addr:full":"Baronstraat 34 Middelkerke West-Vlaanderen 8434",
    "addr:housenumber":"34",
    "addr:postcode":"8434",
    "addr:street":"Baronstraat",
    "iso:country":"BE",
    "sg:address":"Baronstraat 34",
    "sg:city":"Middelkerke",
    "sg:classifiers":[
        {
            "category":"Arena",
            "subcategory":"Sports Club",
            "type":"Entertainment"
        }
    ],
    "sg:phone":"+32 58 23 70 13",
    "sg:postcode":"8434",
    "sg:province":"West-Vlaanderen",
    "sg:tags":[
        "de"
    ],
    "wof:name":"B.b.c. Gistel",
    "wof:placetype":"venue"
},
  "geometry": {"coordinates":[2.7617299557,51.1500587463],"type":"Point"}
}