{
  "type": "Feature",
  "properties": {
    "addr:full":"Brusselsesteenweg 608 Asse Vlaams-Brabant 1731",
    "addr:housenumber":"608",
    "addr:postcode":"1731",
    "addr:street":"Brusselsesteenweg",
    "iso:country":"BE",
    "sg:address":"Brusselsesteenweg 608",
    "sg:city":"Asse",
    "sg:orig_category":"Krantenwinkels Rookartikelen",
    "sg:phone":"+32 2 466 22 51",
    "sg:postcode":"1731",
    "sg:province":"Vlaams-Brabant",
    "wof:name":"Boekhandel Eulaerts",
    "wof:placetype":"venue"
},
  "geometry": {"coordinates":[4.2746667862,50.8837432861],"type":"Point"}
}