{
  "type": "Feature",
  "properties": {
    "addr:full":"Hoveniersstraat 21 Rumst Antwerpen 2840",
    "addr:housenumber":"21",
    "addr:postcode":"2840",
    "addr:street":"Hoveniersstraat",
    "iso:country":"BE",
    "sg:address":"Hoveniersstraat 21",
    "sg:city":"Rumst",
    "sg:classifiers":[
        {
            "category":"Retail",
            "subcategory":"Event Space",
            "type":"Services"
        }
    ],
    "sg:phone":"+32 15 32 26 28",
    "sg:postcode":"2840",
    "sg:province":"Antwerpen",
    "sg:tags":[
        "organisation"
    ],
    "wof:name":"D & C Events",
    "wof:placetype":"venue"
},
  "geometry": {"coordinates":[4.4646978378,51.0853042603],"type":"Point"}
}