{
  "type": "Feature",
  "properties": {
    "iso:country":"BE",
    "sg:address":"Hoornstraat 8",
    "sg:city":"Antwerpen",
    "sg:orig_category":"Artistes ind\u00e9pendants",
    "sg:phone":"+32 3 233 63 07",
    "sg:postcode":"2000",
    "sg:province":"Antwerpen",
    "wof:name":"Scheepmaker",
    "wof:placetype":"venue"
},
  "geometry": {"coordinates":[4.4072542191,51.2242660522],"type":"Point"}
}