{
  "type": "Feature",
  "properties": {
    "iso:country":"BE",
    "sg:address":"Rue De Warnoumont 3",
    "sg:city":"Sprimont",
    "sg:orig_category":"Rusthuizen and serviceflats",
    "sg:phone":"+32 4 382 41 93",
    "sg:postcode":"4140",
    "sg:province":"Li\u00e8ge",
    "wof:name":"Multi Services +",
    "wof:placetype":"venue"
},
  "geometry": {"coordinates":[5.6597499847,50.5072059631],"type":"Point"}
}