{
  "type": "Feature",
  "properties": {
    "addr:full":"Gildenstraat 15 Brussel/bruxelles Bruxelles-Capitale 1000",
    "addr:housenumber":"15",
    "addr:postcode":"1000",
    "addr:street":"Gildenstraat;/",
    "iso:country":"BE",
    "sg:address":"Gildenstraat 15",
    "sg:city":"Brussel/bruxelles",
    "sg:orig_category":"Decoratieve kunst and kunstbenodigdheden Etalage- and showroomontwerpers IJzerwaren, bouw- and verfm",
    "sg:phone":"+32 2 230 32 65",
    "sg:postcode":"1000",
    "sg:province":"Bruxelles-Capitale",
    "wof:name":"Karl Gerniers",
    "wof:placetype":"venue"
},
  "geometry": {"coordinates":[4.3768339157,50.8485603333],"type":"Point"}
}