{
  "type": "Feature",
  "properties": {
    "iso:country":"BE",
    "sg:address":"Beekstraat 65",
    "sg:city":"Zemst (eppegem)",
    "sg:classifiers":[
        {
            "category":"Home & Garden",
            "subcategory":"Carpets & Floor Coverings",
            "type":"Retail Goods"
        }
    ],
    "sg:phone":"+32 15 61 53 32",
    "sg:postcode":"1980",
    "sg:province":"Vlaams-Brabant",
    "sg:tags":[
        "layer",
        "mosaicists"
    ],
    "wof:name":"Loos H",
    "wof:placetype":"venue"
},
  "geometry": {"coordinates":[4.4522218704,50.9686355591],"type":"Point"}
}