{
  "type": "Feature",
  "properties": {
    "iso:country":"BE",
    "sg:address":"Rue Brunehaut 37",
    "sg:city":"Mons (mesvin)",
    "sg:classifiers":[
        {
            "category":"Community Center",
            "subcategory":"Youth",
            "type":"Public Place"
        }
    ],
    "sg:phone":"+32 65 34 63 01",
    "sg:postcode":"7022",
    "sg:province":"Hainaut",
    "sg:tags":[
        "club"
    ],
    "wof:name":"Action Cine-medias Jeunes",
    "wof:placetype":"venue"
},
  "geometry": {"coordinates":[3.9601359367,50.4271202087],"type":"Point"}
}