{
  "type": "Feature",
  "properties": {
    "iso:country":"BE",
    "sg:address":"Statiestraat 48",
    "sg:city":"Lichtervelde",
    "sg:orig_category":"Fietsen",
    "sg:phone":"+32 51 72 30 70",
    "sg:postcode":"8810",
    "sg:province":"West-Vlaanderen",
    "wof:name":"Huis Deseruelle",
    "wof:placetype":"venue"
},
  "geometry": {"coordinates":[3.1361820698,51.0256576538],"type":"Point"}
}