{
  "type": "Feature",
  "properties": {
    "iso:country":"BE",
    "sg:address":"G. Gezellestraat 10",
    "sg:city":"Waregem",
    "sg:orig_category":"Diverse zakelijke dienstverlening Rijscholen Verhuur voertuigen behalve auto's",
    "sg:phone":"+32 56 61 19 88",
    "sg:postcode":"8790",
    "sg:province":"West-Vlaanderen",
    "wof:name":"Pro Move",
    "wof:placetype":"venue"
},
  "geometry": {"coordinates":[3.4360499382,50.8855857849],"type":"Point"}
}