{
  "type": "Feature",
  "properties": {
    "addr:full":"Chemin De Triher\u00e9e 12 Ecaussinnes (ecaussinnes-d'enghien) Hainaut 7190",
    "addr:housenumber":"12",
    "addr:postcode":"7190",
    "addr:street":"Chemin De Trihere\u0301E;Ecaussinnes-D'Enghien Hainaut",
    "iso:country":"BE",
    "sg:address":"Chemin De Triher\u00e9e 12",
    "sg:city":"Ecaussinnes (ecaussinnes-d'enghien)",
    "sg:classifiers":[
        {
            "category":"Professional",
            "type":"Services"
        }
    ],
    "sg:phone":"+32 67 49 10 92",
    "sg:postcode":"7190",
    "sg:province":"Hainaut",
    "sg:tags":[
        "industrial",
        "work",
        "-",
        "maintenance"
    ],
    "wof:name":"Debont B",
    "wof:placetype":"venue"
},
  "geometry": {"coordinates":[4.1685972214,50.5906219482],"type":"Point"}
}