{
  "type": "Feature",
  "properties": {
    "iso:country":"BE",
    "sg:address":"Place D'arc 19",
    "sg:city":"Frasnes-lez-anvaing",
    "sg:classifiers":[
        {
            "category":"Personal",
            "subcategory":"Beauty Salon",
            "type":"Services"
        }
    ],
    "sg:phone":"+32 69 76 98 16",
    "sg:postcode":"7910",
    "sg:province":"Hainaut",
    "sg:tags":[
        "de",
        "coiffure"
    ],
    "wof:name":"Danielle Duhaut",
    "wof:placetype":"venue"
},
  "geometry": {"coordinates":[3.5349440575,50.7005844116],"type":"Point"}
}