{
  "type": "Feature",
  "properties": {
    "iso:country":"BE",
    "sg:address":"All\u00c9e Verte 22",
    "sg:city":"Welkenraedt/welkenraedt",
    "sg:orig_category":"Sportclubs",
    "sg:phone":"+32 87 88 19 80",
    "sg:postcode":"4840",
    "sg:province":"Li\u00e8ge",
    "wof:name":"Pomona Trotters",
    "wof:placetype":"venue"
},
  "geometry": {"coordinates":[5.9796700478,50.6616210938],"type":"Point"}
}