{
  "type": "Feature",
  "properties": {
    "addr:full":"Enneven 89 Lommel Limburg 3920",
    "addr:housenumber":"89",
    "addr:postcode":"3920",
    "addr:street":"Enneven",
    "iso:country":"BE",
    "sg:address":"Enneven 89",
    "sg:city":"Lommel",
    "sg:classifiers":[
        {
            "category":"Manufacturing",
            "subcategory":"Metals",
            "type":"Manufacturing & Wholesale Goods"
        }
    ],
    "sg:phone":"+32 11 55 11 90",
    "sg:postcode":"3920",
    "sg:province":"Limburg",
    "sg:tags":[
        "turning"
    ],
    "wof:name":"Janssenswillen Metaalbewerking",
    "wof:placetype":"venue"
},
  "geometry": {"coordinates":[5.3479189873,51.2347564697],"type":"Point"}
}