{
  "type": "Feature",
  "properties": {
    "iso:country":"BE",
    "sg:address":"Provinciale Steenweg 125",
    "sg:city":"Schelle",
    "sg:classifiers":[
        {
            "category":"Shopping",
            "subcategory":"Books",
            "type":"Retail Goods"
        }
    ],
    "sg:phone":"+32 3 887 79 75",
    "sg:postcode":"2627",
    "sg:province":"Antwerpen",
    "sg:tags":[
        "bookseller"
    ],
    "wof:name":"Keyen",
    "wof:placetype":"venue"
},
  "geometry": {"coordinates":[4.3392062187,51.1266708374],"type":"Point"}
}