{
  "type": "Feature",
  "properties": {
    "addr:full":"Rue De Givet 39 Beauraing Namur 5570",
    "addr:housenumber":"39",
    "addr:postcode":"5570",
    "addr:street":"Rue De Givet",
    "iso:country":"BE",
    "sg:address":"Rue De Givet 39",
    "sg:city":"Beauraing",
    "sg:orig_category":"Fleurs and plantes",
    "sg:phone":"+32 82 71 20 07",
    "sg:postcode":"5570",
    "sg:province":"Namur",
    "wof:name":"Gillet",
    "wof:placetype":"venue"
},
  "geometry": {"coordinates":[4.9529180527,50.1112098694],"type":"Point"}
}