{
  "type": "Feature",
  "properties": {
    "iso:country":"BE",
    "sg:address":"St - Jansstraat 25",
    "sg:city":"Staden",
    "sg:orig_category":"Elektrische installaties voor woningen Huishoudapparaten, televisies and radio's Telecommunicatieapp",
    "sg:phone":"+32 51 70 27 76",
    "sg:postcode":"8840",
    "sg:province":"West-Vlaanderen",
    "wof:name":"Crombez",
    "wof:placetype":"venue"
},
  "geometry": {"coordinates":[3.0156478882,50.9737434387],"type":"Point"}
}