{
  "type": "Feature",
  "properties": {
    "iso:country":"BE",
    "sg:address":"Stationslaan 13",
    "sg:city":"Nieuwpoort",
    "sg:orig_category":"Bouwmaterialen Gh Dakwerken Isolatiewerk",
    "sg:phone":"+32 58 23 71 76",
    "sg:postcode":"8620",
    "sg:province":"West-Vlaanderen",
    "wof:name":"Gallenco",
    "wof:placetype":"venue"
},
  "geometry": {"coordinates":[2.7444210052,51.1315536499],"type":"Point"}
}