{
  "type": "Feature",
  "properties": {
    "addr:full":"Rue De Baume 181 La Louviere Hainaut 7100",
    "addr:housenumber":"181",
    "addr:postcode":"7100",
    "addr:street":"Rue De Baume",
    "iso:country":"BE",
    "sg:address":"Rue De Baume 181",
    "sg:city":"La Louviere",
    "sg:orig_category":"Entretien and r\u00e9parations de voitures",
    "sg:phone":"+32 64 22 19 20",
    "sg:postcode":"7100",
    "sg:province":"Hainaut",
    "wof:name":"Garage Rapide",
    "wof:placetype":"venue"
},
  "geometry": {"coordinates":[4.2052650452,50.4733352661],"type":"Point"}
}