{
  "type": "Feature",
  "properties": {
    "iso:country":"BE",
    "sg:address":"Rue Dethy 67",
    "sg:city":"Sint-gillis/saint-gilles",
    "sg:orig_category":"Imprimeries and copyshops",
    "sg:phone":"+32 2 537 48 63",
    "sg:postcode":"1060",
    "sg:province":"Bruxelles-Capitale",
    "wof:name":"Pissens",
    "wof:placetype":"venue"
},
  "geometry": {"coordinates":[4.3403811455,50.829788208],"type":"Point"}
}