{
  "type": "Feature",
  "properties": {
    "addr:full":"Steenweg Op Kleine Brogel 2 Bocholt (kaulille) Limburg 3950",
    "addr:housenumber":"2",
    "addr:postcode":"3950",
    "addr:street":"Steenweg Op Kleine Brogel",
    "iso:country":"BE",
    "sg:address":"Steenweg Op Kleine Brogel 2",
    "sg:city":"Bocholt (kaulille)",
    "sg:classifiers":[
        {
            "category":"Bakery",
            "type":"Food & Drink"
        }
    ],
    "sg:phone":"+32 11 44 70 25",
    "sg:postcode":"3950",
    "sg:province":"Limburg",
    "sg:tags":[
        "confectioner",
        "baker"
    ],
    "wof:name":"Pateeke ('t)",
    "wof:placetype":"venue"
},
  "geometry": {"coordinates":[5.51440382,51.1917648315],"type":"Point"}
}