{
  "type": "Feature",
  "properties": {
    "iso:country":"BE",
    "sg:address":"Kapucijnenvoer 108",
    "sg:city":"Leuven",
    "sg:orig_category":"Apotheken",
    "sg:phone":"+32 16 20 09 21",
    "sg:postcode":"3000",
    "sg:province":"Vlaams-Brabant",
    "wof:name":"Apoteek Vincke-detiege",
    "wof:placetype":"venue"
},
  "geometry": {"coordinates":[4.6909542084,50.8749046326],"type":"Point"}
}