{
  "type": "Feature",
  "properties": {
    "iso:country":"BE",
    "sg:address":"Route De Diekirch 307",
    "sg:city":"Arlon (bonnert)",
    "sg:classifiers":[
        {
            "category":"Building & Trades",
            "subcategory":"Equipment Rental",
            "type":"Services"
        }
    ],
    "sg:phone":"+32 63 23 43 12",
    "sg:postcode":"6700",
    "sg:province":"Luxembourg",
    "sg:tags":[
        "safety",
        "collective",
        "individual",
        "-"
    ],
    "wof:name":"Secura",
    "wof:placetype":"venue"
},
  "geometry": {"coordinates":[5.8174500465,49.6897201538],"type":"Point"}
}