{
  "type": "Feature",
  "properties": {
    "addr:full":"Voskapelstraat 43 Zaventem Vlaams-Brabant 1933",
    "addr:housenumber":"43",
    "addr:postcode":"1933",
    "addr:street":"Voskapelstraat",
    "iso:country":"BE",
    "sg:address":"Voskapelstraat 43",
    "sg:city":"Zaventem",
    "sg:orig_category":"Etalage- and showroomontwerpers",
    "sg:phone":"+32 2 731 23 43",
    "sg:postcode":"1933",
    "sg:province":"Vlaams-Brabant",
    "wof:name":"Frank Vos",
    "wof:placetype":"venue"
},
  "geometry": {"coordinates":[4.5179548264,50.8668136597],"type":"Point"}
}