{
  "type": "Feature",
  "properties": {
    "addr:full":"Industrielaan 1 Zottegem (grotenberge) Oost-Vlaanderen 9620",
    "addr:housenumber":"1",
    "addr:postcode":"9620",
    "addr:street":"Industrielaan",
    "iso:country":"BE",
    "sg:address":"Industrielaan 1",
    "sg:city":"Zottegem (grotenberge)",
    "sg:classifiers":[
        {
            "category":"Government",
            "subcategory":"Post Office",
            "type":"Public Place"
        }
    ],
    "sg:phone":"+32 9 360 24 01",
    "sg:postcode":"9620",
    "sg:province":"Oost-Vlaanderen",
    "sg:tags":[
        "box",
        "mail"
    ],
    "wof:name":"Sidalux",
    "wof:placetype":"venue"
},
  "geometry": {"coordinates":[3.8112111092,50.871181488],"type":"Point"}
}