{
  "type": "Feature",
  "properties": {
    "addr:full":"Rue Basse Campagne 41 Herstal Li\u00e8ge 4040",
    "addr:housenumber":"41",
    "addr:postcode":"4040",
    "addr:street":"Rue Basse Campagne",
    "iso:country":"BE",
    "sg:address":"Rue Basse Campagne 41",
    "sg:city":"Herstal",
    "sg:orig_category":"Supermarkten",
    "sg:phone":"+32 4 264 44 39",
    "sg:postcode":"4040",
    "sg:province":"Li\u00e8ge",
    "wof:name":"Delhaize",
    "wof:placetype":"venue"
},
  "geometry": {"coordinates":[5.6449608803,50.6869087219],"type":"Point"}
}