{
  "type": "Feature",
  "properties": {
    "iso:country":"BE",
    "sg:address":"Ouburg 103",
    "sg:city":"Dendermonde",
    "sg:orig_category":"V\u00e9hicules automobiles. Entretien and r\u00e9parations de voitures",
    "sg:phone":"+32 52 21 82 48",
    "sg:postcode":"9200",
    "sg:province":"Oost-Vlaanderen",
    "wof:name":"Hubert Van Eetvelde",
    "wof:placetype":"venue"
},
  "geometry": {"coordinates":[4.0573949814,50.9987106323],"type":"Point"}
}