{
  "type": "Feature",
  "properties": {
    "addr:full":"Rue De Villers 6 Charleroi Hainaut 6010",
    "addr:housenumber":"6",
    "addr:postcode":"6010",
    "addr:street":"Rue De Villers;Hainaut",
    "iso:country":"BE",
    "sg:address":"Rue De Villers 6",
    "sg:city":"Charleroi",
    "sg:classifiers":[
        {
            "category":"Restaurant",
            "type":"Food & Drink"
        }
    ],
    "sg:phone":"+32 71 36 90 39",
    "sg:postcode":"6010",
    "sg:province":"Hainaut",
    "wof:name":"Chez Lanza",
    "wof:placetype":"venue"
},
  "geometry": {"coordinates":[4.4707517624,50.39037323],"type":"Point"}
}