{
  "type": "Feature",
  "properties": {
    "iso:country":"BE",
    "sg:address":"Jozef Dedobbeleerstraat 6",
    "sg:city":"Sint-pieters-leeuw",
    "sg:orig_category":"Cr\u00e9meries",
    "sg:phone":"+32 2 377 73 89",
    "sg:postcode":"1600",
    "sg:province":"Vlaams-Brabant",
    "wof:name":"Lucien Denayer",
    "wof:placetype":"venue"
},
  "geometry": {"coordinates":[4.2313938141,50.777507782],"type":"Point"}
}