{
  "type": "Feature",
  "properties": {
    "addr:full":"Rue De La Poste 4 Martelange Luxembourg 6630",
    "addr:housenumber":"4",
    "addr:postcode":"6630",
    "addr:street":"Rue De La Poste",
    "iso:country":"BE",
    "sg:address":"Rue De La Poste 4",
    "sg:city":"Martelange",
    "sg:classifiers":[
        {
            "category":"Health Services",
            "subcategory":"Health Practitioner",
            "type":"Services"
        }
    ],
    "sg:phone":"+32 63 60 01 28",
    "sg:postcode":"6630",
    "sg:province":"Luxembourg",
    "sg:tags":[
        "physiotherapist"
    ],
    "wof:name":"Buchet Jean-pierre",
    "wof:placetype":"venue"
},
  "geometry": {"coordinates":[5.738296032,49.8332176208],"type":"Point"}
}