{
  "type": "Feature",
  "properties": {
    "addr:full":"Kortedagsteeg 2 Gent Oost-Vlaanderen 9000",
    "addr:housenumber":"2",
    "addr:postcode":"9000",
    "addr:street":"Kortedagsteeg;Oost-Vlaanderen",
    "iso:country":"BE",
    "sg:address":"Kortedagsteeg 2",
    "sg:city":"Gent",
    "sg:classifiers":[
        {
            "category":"Fast Food",
            "type":"Food & Drink"
        }
    ],
    "sg:phone":"+32 9 225 55 57",
    "sg:postcode":"9000",
    "sg:province":"Oost-Vlaanderen",
    "sg:tags":[
        "meeneem",
        "restaurant"
    ],
    "wof:name":"Snack-bar Come Inn",
    "wof:placetype":"venue"
},
  "geometry": {"coordinates":[3.7261650562,51.0505027771],"type":"Point"}
}