{
  "type": "Feature",
  "properties": {
    "iso:country":"BE",
    "sg:address":"Maalse Steenweg 423",
    "sg:city":"Brugge",
    "sg:orig_category":"V\u00eatements pour Dames. V\u00eatements de mariage and c\u00e9r\u00e9monies",
    "sg:phone":"+32 50 35 22 88",
    "sg:postcode":"8310",
    "sg:province":"West-Vlaanderen",
    "wof:name":"Huis Miss Sheila",
    "wof:placetype":"venue"
},
  "geometry": {"coordinates":[3.2677900791,51.2075195312],"type":"Point"}
}