{
  "type": "Feature",
  "properties": {
    "addr:full":"Place Emile De Lalieux 34 Nivelles Brabant Wallon 1400",
    "addr:housenumber":"34",
    "addr:postcode":"1400",
    "addr:street":"Place Emile De Lalieux",
    "iso:country":"BE",
    "sg:address":"Place Emile De Lalieux 34",
    "sg:city":"Nivelles",
    "sg:classifiers":[
        {
            "category":"Bars & Pubs",
            "type":"Food & Drink"
        }
    ],
    "sg:phone":"+32 67 22 15 00",
    "sg:postcode":"1400",
    "sg:province":"Brabant Wallon",
    "sg:tags":[
        "tavern"
    ],
    "wof:name":"New Inn Taverne",
    "wof:placetype":"venue"
},
  "geometry": {"coordinates":[4.3282690048,50.5979957581],"type":"Point"}
}