{
  "type": "Feature",
  "properties": {
    "addr:full":"Jules De Cocklaan 67 Gent Oost-Vlaanderen 9050",
    "addr:housenumber":"67",
    "addr:postcode":"9050",
    "addr:street":"Jules De Cocklaan;Oost-Vlaanderen",
    "iso:country":"BE",
    "sg:address":"Jules De Cocklaan 67",
    "sg:city":"Gent",
    "sg:orig_category":"Boomkwekerijen",
    "sg:phone":"+32 9 231 53 81",
    "sg:postcode":"9050",
    "sg:province":"Oost-Vlaanderen",
    "wof:name":"Pyck Marc",
    "wof:placetype":"venue"
},
  "geometry": {"coordinates":[3.7518749237,51.0250282288],"type":"Point"}
}