{
  "type": "Feature",
  "properties": {
    "iso:country":"BE",
    "sg:address":"Avenue Roi Albert 88",
    "sg:city":"Ciney",
    "sg:orig_category":"R\u00e9alisation de programmes and logiciels. Ordinateurs and \u00e9quipement informatique. Entretien and r\u00e9pa",
    "sg:phone":"+32 83 21 76 59",
    "sg:postcode":"5590",
    "sg:province":"Namur",
    "wof:name":"Marti - Informatique",
    "wof:placetype":"venue"
},
  "geometry": {"coordinates":[5.0944471359,50.2873153687],"type":"Point"}
}