{
  "type": "Feature",
  "properties": {
    "addr:full":"Anselmostraat 58 Antwerpen Antwerpen 2018",
    "addr:housenumber":"58",
    "addr:postcode":"2018",
    "addr:street":"Anselmostraat",
    "iso:country":"BE",
    "sg:address":"Anselmostraat 58",
    "sg:city":"Antwerpen",
    "sg:classifiers":[
        {
            "category":"Home & Garden",
            "subcategory":"Home Furnishings",
            "type":"Retail Goods"
        }
    ],
    "sg:phone":"+32 3 248 66 86",
    "sg:postcode":"2018",
    "sg:province":"Antwerpen",
    "sg:tags":[
        "interior",
        "decoration"
    ],
    "wof:name":"Ansel Beau & Co",
    "wof:placetype":"venue"
},
  "geometry": {"coordinates":[4.4038238525,51.2065010071],"type":"Point"}
}