{
  "type": "Feature",
  "properties": {
    "iso:country":"BE",
    "sg:address":"Avenue Louise 1",
    "sg:city":"Bruxelles (ixelles)",
    "sg:classifiers":[
        {
            "category":"Shopping",
            "subcategory":"Jewelry",
            "type":"Retail Goods"
        }
    ],
    "sg:phone":"+32 2 537 51 61",
    "sg:postcode":"1050",
    "sg:province":"Bruxelles-Capitale",
    "sg:tags":[
        "jeweller",
        "-"
    ],
    "wof:name":"Cartier",
    "wof:placetype":"venue"
},
  "geometry": {"coordinates":[4.3554821014,50.8356742859],"type":"Point"}
}