{
  "type": "Feature",
  "properties": {
    "addr:full":"Rue De Merbe 128 Binche Hainaut 7130",
    "addr:housenumber":"128",
    "addr:postcode":"7130",
    "addr:street":"Rue De Merbe",
    "iso:country":"BE",
    "sg:address":"Rue De Merbe 128",
    "sg:city":"Binche",
    "sg:classifiers":[
        {
            "category":"Personal",
            "subcategory":"Beauty Salon",
            "type":"Services"
        }
    ],
    "sg:phone":"+32 64 36 66 09",
    "sg:postcode":"7130",
    "sg:province":"Hainaut",
    "sg:tags":[
        "de",
        "coiffure"
    ],
    "wof:name":"Coiffure Cr\u00c9ation Mode",
    "wof:placetype":"venue"
},
  "geometry": {"coordinates":[4.1707210541,50.4069252014],"type":"Point"}
}