{
  "type": "Feature",
  "properties": {
    "addr:full":"Franklin Rooseveltlaan 51 Brussel/bruxelles Bruxelles-Capitale 1050",
    "addr:housenumber":"51",
    "addr:postcode":"1050",
    "addr:street":"Franklin Rooseveltlaan;/",
    "iso:country":"BE",
    "sg:address":"Franklin Rooseveltlaan 51",
    "sg:city":"Brussel/bruxelles",
    "sg:orig_category":"Advocaten and juridische adviseurs",
    "sg:phone":"+32 2 649 95 46",
    "sg:postcode":"1050",
    "sg:province":"Bruxelles-Capitale",
    "wof:name":"Piero Ferire",
    "wof:placetype":"venue"
},
  "geometry": {"coordinates":[4.3833627701,50.8091011047],"type":"Point"}
}