{
  "type": "Feature",
  "properties": {
    "addr:full":"Rue Neuvice 58 Li\u00c8ge Li\u00e8ge 4000",
    "addr:housenumber":"58",
    "addr:postcode":"4000",
    "addr:street":"Rue Neuvice",
    "iso:country":"BE",
    "sg:address":"Rue Neuvice 58",
    "sg:city":"Li\u00c8ge",
    "sg:orig_category":"Verbruikerskredietinstellingen",
    "sg:phone":"+32 4 223 13 38",
    "sg:postcode":"4000",
    "sg:province":"Li\u00e8ge",
    "wof:name":"La Financi\u00c8re Li\u00c9geoise",
    "wof:placetype":"venue"
},
  "geometry": {"coordinates":[5.5774211884,50.6443634033],"type":"Point"}
}