{
  "type": "Feature",
  "properties": {
    "addr:full":"Place Du Centenaire 45 Libin Luxembourg 6890",
    "addr:housenumber":"45",
    "addr:postcode":"6890",
    "addr:street":"Place Du Centenaire",
    "iso:country":"BE",
    "sg:address":"Place Du Centenaire 45",
    "sg:city":"Libin",
    "sg:orig_category":"Tuinen",
    "sg:phone":"+32 61 22 32 45",
    "sg:postcode":"6890",
    "sg:province":"Luxembourg",
    "wof:name":"Martial Perraux",
    "wof:placetype":"venue"
},
  "geometry": {"coordinates":[5.2752351761,49.9256248474],"type":"Point"}
}