{
  "type": "Feature",
  "properties": {
    "iso:country":"BE",
    "sg:address":"Smissenhoekstraat 7",
    "sg:city":"Westerlo",
    "sg:orig_category":"Salles de spectacles",
    "sg:phone":"+32 14 54 65 92",
    "sg:postcode":"2260",
    "sg:province":"Antwerpen",
    "wof:name":"Ontmoetingscentrum",
    "wof:placetype":"venue"
},
  "geometry": {"coordinates":[4.9112768173,51.0883636475],"type":"Point"}
}