{
  "type": "Feature",
  "properties": {
    "addr:full":"Citadelpark Gent-centrum Oost-Vlaanderen 9000",
    "addr:postcode":"9000",
    "addr:street":"Oost-Vlaanderen",
    "iso:country":"BE",
    "sg:address":"Citadelpark",
    "sg:city":"Gent-centrum",
    "sg:orig_category":"Salles de conf\u00e9rences and de r\u00e9ceptions",
    "sg:phone":"+32 9 221 74 97",
    "sg:postcode":"9000",
    "sg:province":"Oost-Vlaanderen",
    "wof:name":"Icc",
    "wof:placetype":"venue"
},
  "geometry": {"coordinates":[3.7281730175,51.0385284424],"type":"Point"}
}