{
  "type": "Feature",
  "properties": {
    "iso:country":"BE",
    "sg:address":"Papenaardekenstraat 214",
    "sg:city":"Schoten",
    "sg:classifiers":[
        {
            "category":"Manufacturing",
            "subcategory":"Metals",
            "type":"Manufacturing & Wholesale Goods"
        }
    ],
    "sg:phone":"+32 3 685 51 71",
    "sg:postcode":"2900",
    "sg:province":"Antwerpen",
    "sg:tags":[
        "turning"
    ],
    "wof:name":"Verschueren Adf Bvba",
    "wof:placetype":"venue"
},
  "geometry": {"coordinates":[4.4916501045,51.2420005798],"type":"Point"}
}