{
  "type": "Feature",
  "properties": {
    "addr:full":"Rue Saint-gilles 81 Li\u00e8ge 1 Li\u00e8ge 4000",
    "addr:housenumber":"81;1",
    "addr:postcode":"4000",
    "addr:street":"Rue Saint-Gilles",
    "iso:country":"BE",
    "sg:address":"Rue Saint-gilles 81",
    "sg:city":"Li\u00e8ge 1",
    "sg:classifiers":[
        {
            "category":"Health Services",
            "subcategory":"Health Practitioner",
            "type":"Services"
        }
    ],
    "sg:phone":"+32 4 223 78 88",
    "sg:postcode":"4000",
    "sg:province":"Li\u00e8ge",
    "sg:tags":[
        "physiotherapist"
    ],
    "wof:name":"Dervaux Olivier",
    "wof:placetype":"venue"
},
  "geometry": {"coordinates":[5.5635128021,50.6380195618],"type":"Point"}
}