{
  "type": "Feature",
  "properties": {
    "addr:full":"Atealaan 1 Herenthout Antwerpen 2270",
    "addr:housenumber":"1",
    "addr:postcode":"2270",
    "addr:street":"Atealaan",
    "iso:country":"BE",
    "sg:address":"Atealaan 1",
    "sg:city":"Herenthout",
    "sg:classifiers":[
        {
            "category":"Building & Trades",
            "subcategory":"Construction",
            "type":"Services"
        }
    ],
    "sg:phone":"+32 14 23 10 23",
    "sg:postcode":"2270",
    "sg:province":"Antwerpen",
    "sg:tags":[
        "interior",
        "design"
    ],
    "wof:name":"Mundial Decor International Nv",
    "wof:placetype":"venue"
},
  "geometry": {"coordinates":[4.8044819832,51.1542854309],"type":"Point"}
}