{
  "type": "Feature",
  "properties": {
    "addr:full":"Bissegemsestraat 74 Kortrijk West-Vlaanderen 8501",
    "addr:housenumber":"74",
    "addr:postcode":"8501",
    "addr:street":"Bissegemsestraat",
    "iso:country":"BE",
    "sg:address":"Bissegemsestraat 74",
    "sg:city":"Kortrijk",
    "sg:orig_category":"Blanchisseries and teintureries",
    "sg:phone":"+32 56 35 69 65",
    "sg:postcode":"8501",
    "sg:province":"West-Vlaanderen",
    "wof:name":"Linnenservice Leuven",
    "wof:placetype":"venue"
},
  "geometry": {"coordinates":[3.2383770943,50.8290328979],"type":"Point"}
}