{
  "type": "Feature",
  "properties": {
    "iso:country":"BE",
    "sg:address":"Rue De L'industrie 145",
    "sg:city":"Frameries (la Bouverie)",
    "sg:classifiers":[
        {
            "category":"Home & Garden",
            "subcategory":"Garden Supply",
            "type":"Retail Goods"
        }
    ],
    "sg:phone":"+32 65 67 93 50",
    "sg:postcode":"7080",
    "sg:province":"Hainaut",
    "sg:tags":[
        "seed",
        "-"
    ],
    "wof:name":"Attaque (graineterie)",
    "wof:placetype":"venue"
},
  "geometry": {"coordinates":[3.8813900948,50.4092674255],"type":"Point"}
}