{
  "type": "Feature",
  "properties": {
    "iso:country":"BE",
    "sg:address":"Veldstraat 158",
    "sg:city":"Brecht",
    "sg:orig_category":"Transports routiers de marchandises",
    "sg:phone":"+32 3 313 87 64",
    "sg:postcode":"2960",
    "sg:province":"Antwerpen",
    "wof:name":"Joosi Trans",
    "wof:placetype":"venue"
},
  "geometry": {"coordinates":[4.6441698074,51.3734054565],"type":"Point"}
}