{
  "type": "Feature",
  "properties": {
    "addr:full":"Engelstraat 177 Ichtegem West-Vlaanderen 8480",
    "addr:housenumber":"177",
    "addr:postcode":"8480",
    "addr:street":"Engelstraat",
    "iso:country":"BE",
    "sg:address":"Engelstraat 177",
    "sg:city":"Ichtegem",
    "sg:orig_category":"Loodgieterij, verwarming and sanitaire installaties",
    "sg:phone":"+32 51 58 01 38",
    "sg:postcode":"8480",
    "sg:province":"West-Vlaanderen",
    "wof:name":"Mattheus",
    "wof:placetype":"venue"
},
  "geometry": {"coordinates":[3.0269060135,51.0982017517],"type":"Point"}
}