{
  "type": "Feature",
  "properties": {
    "addr:full":"Mechelseweg 96 Kapelle-op-den-bos Vlaams-Brabant 1880",
    "addr:housenumber":"96",
    "addr:postcode":"1880",
    "addr:street":"Mechelseweg",
    "iso:country":"BE",
    "sg:address":"Mechelseweg 96",
    "sg:city":"Kapelle-op-den-bos",
    "sg:orig_category":"Enseignement maternel and primaire",
    "sg:phone":"+32 15 71 18 01",
    "sg:postcode":"1880",
    "sg:province":"Vlaams-Brabant",
    "wof:name":"Vrije Basisschool",
    "wof:placetype":"venue"
},
  "geometry": {"coordinates":[4.3548321724,51.0133666992],"type":"Point"}
}