{
  "type": "Feature",
  "properties": {
    "addr:full":"Zandstraat 147 Beveren (haasdonk) Oost-Vlaanderen 9120",
    "addr:housenumber":"147",
    "addr:postcode":"9120",
    "addr:street":"Zandstraat",
    "iso:country":"BE",
    "sg:address":"Zandstraat 147",
    "sg:city":"Beveren (haasdonk)",
    "sg:classifiers":[
        {
            "category":"Bars & Pubs",
            "type":"Food & Drink"
        }
    ],
    "sg:phone":"+32 3 775 56 50",
    "sg:postcode":"9120",
    "sg:province":"Oost-Vlaanderen",
    "wof:name":"Den Buiten",
    "wof:placetype":"venue"
},
  "geometry": {"coordinates":[4.2364411354,51.1938858032],"type":"Point"}
}