{
  "type": "Feature",
  "properties": {
    "addr:full":"Jonker Van Der Nootstraat 18 Antwerpen Antwerpen 2050",
    "addr:housenumber":"18",
    "addr:postcode":"2050",
    "addr:street":"Jonker Van Der Nootstraat",
    "iso:country":"BE",
    "sg:address":"Jonker Van Der Nootstraat 18",
    "sg:city":"Antwerpen",
    "sg:classifiers":[
        {
            "category":"Insurance",
            "subcategory":"Insurance Agent",
            "type":"Services"
        }
    ],
    "sg:phone":"+32 3 219 29 08",
    "sg:postcode":"2050",
    "sg:province":"Antwerpen",
    "sg:tags":[
        "broker"
    ],
    "wof:name":"Verzekeringskantoor Lauwers & Partners Nv",
    "wof:placetype":"venue"
},
  "geometry": {"coordinates":[4.3844451904,51.218536377],"type":"Point"}
}