{
  "type": "Feature",
  "properties": {
    "addr:full":"Nijverseelveld 8 Opwijk Vlaams-Brabant 1745",
    "addr:housenumber":"8",
    "addr:postcode":"1745",
    "addr:street":"Nijverseelveld",
    "iso:country":"BE",
    "sg:address":"Nijverseelveld 8",
    "sg:city":"Opwijk",
    "sg:orig_category":"Woningbouw",
    "sg:phone":"+32 52 35 51 42",
    "sg:postcode":"1745",
    "sg:province":"Vlaams-Brabant",
    "wof:name":"Van Den Abbeele",
    "wof:placetype":"venue"
},
  "geometry": {"coordinates":[4.1541252136,50.9660415649],"type":"Point"}
}