{
  "type": "Feature",
  "properties": {
    "addr:full":"Bosstraat 12 Maaseik Limburg 3680",
    "addr:housenumber":"12",
    "addr:postcode":"3680",
    "addr:street":"Bosstraat",
    "iso:country":"BE",
    "sg:address":"Bosstraat 12",
    "sg:city":"Maaseik",
    "sg:classifiers":[
        {
            "category":"Shopping",
            "subcategory":"Optician",
            "type":"Retail Goods"
        }
    ],
    "sg:phone":"+32 89 56 46 63",
    "sg:postcode":"3680",
    "sg:province":"Limburg",
    "sg:tags":[
        "-"
    ],
    "wof:name":"Berry Locht",
    "wof:placetype":"venue"
},
  "geometry": {"coordinates":[5.7903580666,51.0947952271],"type":"Point"}
}