{
  "type": "Feature",
  "properties": {
    "addr:full":"Leopoldstraat 29 Merksplas Antwerpen 2330",
    "addr:housenumber":"29",
    "addr:postcode":"2330",
    "addr:street":"Leopoldstraat",
    "iso:country":"BE",
    "sg:address":"Leopoldstraat 29",
    "sg:city":"Merksplas",
    "sg:classifiers":[
        {
            "category":"Home & Garden",
            "subcategory":"Home Furnishings",
            "type":"Retail Goods"
        }
    ],
    "sg:phone":"+32 14 63 29 97",
    "sg:postcode":"2330",
    "sg:province":"Antwerpen",
    "sg:tags":[
        "curtain",
        "-",
        "fixture"
    ],
    "wof:name":"Ilse Gordijnen",
    "wof:placetype":"venue"
},
  "geometry": {"coordinates":[4.8649201393,51.3563575745],"type":"Point"}
}