{
  "type": "Feature",
  "properties": {
    "addr:full":"Vriesenrot 4 Dendermonde (sint-gillis-bij-dendermonde) Oost-Vlaanderen 9200",
    "addr:housenumber":"4",
    "addr:postcode":"9200",
    "addr:street":"Vriesenrot",
    "iso:country":"BE",
    "sg:address":"Vriesenrot 4",
    "sg:city":"Dendermonde (sint-gillis-bij-dendermonde)",
    "sg:classifiers":[
        {
            "category":"Shopping",
            "subcategory":"Used Merchandise",
            "type":"Retail Goods"
        }
    ],
    "sg:phone":"+32 52 20 04 07",
    "sg:postcode":"9200",
    "sg:province":"Oost-Vlaanderen",
    "sg:tags":[
        "salvage",
        "surplus"
    ],
    "wof:name":"Vabeco Nv",
    "wof:placetype":"venue"
},
  "geometry": {"coordinates":[4.1289191246,51.033908844],"type":"Point"}
}