{
  "type": "Feature",
  "properties": {
    "addr:full":"Plein Sud 1 Walcourt (somz\u00e9e) Namur 5651",
    "addr:housenumber":"1",
    "addr:postcode":"5651",
    "addr:street":"Plein;Somze\u0301E",
    "iso:country":"BE",
    "sg:address":"Plein Sud 1",
    "sg:city":"Walcourt (somz\u00e9e)",
    "sg:classifiers":[
        {
            "category":"Communications",
            "type":"Services"
        }
    ],
    "sg:phone":"+32 71 22 18 62",
    "sg:postcode":"5651",
    "sg:province":"Namur",
    "sg:tags":[
        "translator"
    ],
    "wof:name":"A S A P",
    "wof:placetype":"venue"
},
  "geometry": {"coordinates":[4.4764661789,50.2909126282],"type":"Point"}
}