{
  "type": "Feature",
  "properties": {
    "addr:full":"Rue Du Manypr\u00e9 101 Chaumont-gistoux (corroy-le-grand) Brabant Wallon 1325",
    "addr:housenumber":"101",
    "addr:postcode":"1325",
    "addr:street":"Rue Du Manypre\u0301",
    "iso:country":"BE",
    "sg:address":"Rue Du Manypr\u00e9 101",
    "sg:city":"Chaumont-gistoux (corroy-le-grand)",
    "sg:classifiers":[
        {
            "category":"Health Services",
            "subcategory":"Doctor",
            "type":"Services"
        }
    ],
    "sg:phone":"+32 10 68 83 91",
    "sg:postcode":"1325",
    "sg:province":"Brabant Wallon",
    "sg:tags":[
        "medicinephysicians",
        "surgeon"
    ],
    "wof:name":"Kozyreff V",
    "wof:placetype":"venue"
},
  "geometry": {"coordinates":[4.6830840111,50.6720504761],"type":"Point"}
}