{
  "type": "Feature",
  "properties": {
    "addr:full":"Rue De Colivrenne 12 Beauraing Namur 5570",
    "addr:housenumber":"12",
    "addr:postcode":"5570",
    "addr:street":"Rue De Colivrenne",
    "iso:country":"BE",
    "sg:address":"Rue De Colivrenne 12",
    "sg:city":"Beauraing",
    "sg:orig_category":"Huisdierenkwekers",
    "sg:phone":"+32 82 71 10 61",
    "sg:postcode":"5570",
    "sg:province":"Namur",
    "wof:name":"Elevage Domaine Princier",
    "wof:placetype":"venue"
},
  "geometry": {"coordinates":[4.8461232185,50.0683937073],"type":"Point"}
}