{
  "type": "Feature",
  "properties": {
    "addr:full":"Mechelsestraat 52 Vilvoorde Vlaams-Brabant 1800",
    "addr:housenumber":"52",
    "addr:postcode":"1800",
    "addr:street":"Mechelsestraat",
    "iso:country":"BE",
    "sg:address":"Mechelsestraat 52",
    "sg:city":"Vilvoorde",
    "sg:orig_category":"Art and fournitures artistiques",
    "sg:phone":"+32 2 251 81 66",
    "sg:postcode":"1800",
    "sg:province":"Vlaams-Brabant",
    "wof:name":"Kunstparadijs De Leeuw",
    "wof:placetype":"venue"
},
  "geometry": {"coordinates":[4.4246501923,50.9323997498],"type":"Point"}
}