{
  "type": "Feature",
  "properties": {
    "addr:full":"Boulevard Leopold Iii 4 P\u00e9ruwelz Hainaut 7600",
    "addr:housenumber":"4",
    "addr:postcode":"7600",
    "addr:street":"Boulevard Leopold Iii",
    "iso:country":"BE",
    "sg:address":"Boulevard Leopold Iii 4",
    "sg:city":"P\u00e9ruwelz",
    "sg:classifiers":[
        {
            "category":"Professional",
            "subcategory":"Lawyer & Legal Services",
            "type":"Services"
        }
    ],
    "sg:phone":"+32 69 77 20 68",
    "sg:postcode":"7600",
    "sg:province":"Hainaut",
    "sg:tags":[
        "notary"
    ],
    "wof:name":"Carlier E",
    "wof:placetype":"venue"
},
  "geometry": {"coordinates":[3.5906350613,50.5071105957],"type":"Point"}
}