{
  "type": "Feature",
  "properties": {
    "addr:full":"Rue De Marcinelle 41 Charleroi Hainaut 6000",
    "addr:housenumber":"41",
    "addr:postcode":"6000",
    "addr:street":"Rue De Marcinelle;Hainaut",
    "iso:country":"BE",
    "sg:address":"Rue De Marcinelle 41",
    "sg:city":"Charleroi",
    "sg:orig_category":"Enseignement maternel and primaire",
    "sg:phone":"+32 71 31 29 30",
    "sg:postcode":"6000",
    "sg:province":"Hainaut",
    "wof:name":"Ecole Primaire Libre",
    "wof:placetype":"venue"
},
  "geometry": {"coordinates":[4.4441041946,50.4064826965],"type":"Point"}
}