{
  "type": "Feature",
  "properties": {
    "addr:full":"Rue Jules Cousin 104a Frameries (la Bouverie) Hainaut 7080",
    "addr:housenumber":"104a",
    "addr:postcode":"7080",
    "addr:street":"Rue Jules Cousin",
    "iso:country":"BE",
    "sg:address":"Rue Jules Cousin 104a",
    "sg:city":"Frameries (la Bouverie)",
    "sg:classifiers":[
        {
            "category":"Real Estate",
            "subcategory":"Architect",
            "type":"Services"
        }
    ],
    "sg:phone":"+32 65 66 71 49",
    "sg:postcode":"7080",
    "sg:province":"Hainaut",
    "wof:name":"Mercier B",
    "wof:placetype":"venue"
},
  "geometry": {"coordinates":[3.8831000328,50.3984451294],"type":"Point"}
}