{
  "type": "Feature",
  "properties": {
    "addr:full":"Axpoelmolenstraat 5 Ruiselede West-Vlaanderen 8755",
    "addr:housenumber":"5",
    "addr:postcode":"8755",
    "addr:street":"Axpoelmolenstraat",
    "iso:country":"BE",
    "sg:address":"Axpoelmolenstraat 5",
    "sg:city":"Ruiselede",
    "sg:orig_category":"Woningbouw",
    "sg:phone":"+32 51 68 92 25",
    "sg:postcode":"8755",
    "sg:province":"West-Vlaanderen",
    "wof:name":"Alg. Bouwwerken Dirk Slos",
    "wof:placetype":"venue"
},
  "geometry": {"coordinates":[3.4063160419,51.0564880371],"type":"Point"}
}