{
  "type": "Feature",
  "properties": {
    "addr:full":"Zoutelaan 280 Knokke-heist West-Vlaanderen 8300",
    "addr:housenumber":"280",
    "addr:postcode":"8300",
    "addr:street":"Zoutelaan",
    "iso:country":"BE",
    "sg:address":"Zoutelaan 280",
    "sg:city":"Knokke-heist",
    "sg:orig_category":"Artistes ind\u00e9pendants",
    "sg:phone":"+32 50 60 15 00",
    "sg:postcode":"8300",
    "sg:province":"West-Vlaanderen",
    "wof:name":"Roger Nellens",
    "wof:placetype":"venue"
},
  "geometry": {"coordinates":[3.3233029842,51.350353241],"type":"Point"}
}