{
  "type": "Feature",
  "properties": {
    "iso:country":"BE",
    "sg:address":"Lentelaan 9",
    "sg:city":"Sint-pieters-leeuw",
    "sg:classifiers":[
        {
            "category":"Building & Trades",
            "subcategory":"Electrical",
            "type":"Services"
        }
    ],
    "sg:phone":"+32 2 377 88 84",
    "sg:postcode":"1600",
    "sg:province":"Vlaams-Brabant",
    "sg:tags":[
        "electric",
        "-",
        "housewiring",
        "contractor"
    ],
    "wof:name":"Vanhaelen J",
    "wof:placetype":"venue"
},
  "geometry": {"coordinates":[4.2717761993,50.7814102173],"type":"Point"}
}