{
  "type": "Feature",
  "properties": {
    "iso:country":"BE",
    "sg:address":"Rue De La Croix Rouge 109",
    "sg:city":"Tinlot",
    "sg:orig_category":"Boekhouders",
    "sg:phone":"+32 4 383 77 01",
    "sg:postcode":"4557",
    "sg:province":"Li\u00e8ge",
    "wof:name":"M.e.c.",
    "wof:placetype":"venue"
},
  "geometry": {"coordinates":[5.4150938988,50.4851722717],"type":"Point"}
}