{
  "type": "Feature",
  "properties": {
    "addr:full":"Stationstraat 106 Ardooie West-Vlaanderen 8850",
    "addr:housenumber":"106",
    "addr:postcode":"8850",
    "addr:street":"Stationstraat",
    "iso:country":"BE",
    "sg:address":"Stationstraat 106",
    "sg:city":"Ardooie",
    "sg:orig_category":"Verplichte sociale verzekeringen",
    "sg:phone":"+32 51 74 71 57",
    "sg:postcode":"8850",
    "sg:province":"West-Vlaanderen",
    "wof:name":"Socialist. Mutualiteit",
    "wof:placetype":"venue"
},
  "geometry": {"coordinates":[3.2014389038,50.9824981689],"type":"Point"}
}