{
  "type": "Feature",
  "properties": {
    "addr:full":"Van De Reydtlaan 30 Brecht Antwerpen 2960",
    "addr:housenumber":"30",
    "addr:postcode":"2960",
    "addr:street":"Van;Reydtlaan",
    "iso:country":"BE",
    "sg:address":"Van De Reydtlaan 30",
    "sg:city":"Brecht",
    "sg:classifiers":[
        {
            "category":"Communications",
            "type":"Services"
        }
    ],
    "sg:phone":"+32 3 636 06 38",
    "sg:postcode":"2960",
    "sg:province":"Antwerpen",
    "sg:tags":[
        "telecommunication"
    ],
    "wof:name":"Dinamic International",
    "wof:placetype":"venue"
},
  "geometry": {"coordinates":[4.594078064,51.3254241943],"type":"Point"}
}