{
  "type": "Feature",
  "properties": {
    "iso:country":"BE",
    "sg:address":"Markt 51a",
    "sg:city":"Mol",
    "sg:orig_category":"Schoonheidssalons",
    "sg:phone":"+32 14 31 94 59",
    "sg:postcode":"2400",
    "sg:province":"Antwerpen",
    "wof:name":"Christel Mertens",
    "wof:placetype":"venue"
},
  "geometry": {"coordinates":[5.116517067,51.1846046448],"type":"Point"}
}