{
  "type": "Feature",
  "properties": {
    "iso:country":"BE",
    "sg:address":"Vijfseweg 96",
    "sg:city":"Waregem",
    "sg:classifiers":[
        {
            "category":"Personal",
            "subcategory":"Beauty Salon",
            "type":"Services"
        }
    ],
    "sg:phone":"+32 56 61 22 58",
    "sg:postcode":"8790",
    "sg:province":"West-Vlaanderen",
    "wof:name":"Belle",
    "wof:placetype":"venue"
},
  "geometry": {"coordinates":[3.4231240749,50.8963241577],"type":"Point"}
}