{
  "type": "Feature",
  "properties": {
    "addr:full":"Oude Godstraat 82 Edegem Antwerpen 2650",
    "addr:housenumber":"82",
    "addr:postcode":"2650",
    "addr:street":"Oude Godstraat",
    "iso:country":"BE",
    "sg:address":"Oude Godstraat 82",
    "sg:city":"Edegem",
    "sg:classifiers":[
        {
            "category":"Shopping",
            "subcategory":"Computers & Home Electronics",
            "type":"Retail Goods"
        }
    ],
    "sg:phone":"+32 3 457 83 42",
    "sg:postcode":"2650",
    "sg:province":"Antwerpen",
    "sg:tags":[
        "automobile",
        "-",
        "navigation",
        "system"
    ],
    "wof:name":"Car Electro",
    "wof:placetype":"venue"
},
  "geometry": {"coordinates":[4.4442520142,51.1608085632],"type":"Point"}
}