{
  "type": "Feature",
  "properties": {
    "addr:full":"Kronevoordestraat 53 Kortemark (handzame) West-Vlaanderen 8610",
    "addr:housenumber":"53",
    "addr:postcode":"8610",
    "addr:street":"Kronevoordestraat",
    "iso:country":"BE",
    "sg:address":"Kronevoordestraat 53",
    "sg:city":"Kortemark (handzame)",
    "sg:classifiers":[
        {
            "category":"Building & Trades",
            "subcategory":"Pest Control",
            "type":"Services"
        }
    ],
    "sg:phone":"+32 51 56 69 86",
    "sg:postcode":"8610",
    "sg:province":"West-Vlaanderen",
    "sg:tags":[
        "painting",
        "contractor"
    ],
    "wof:name":"Barra Decoratie",
    "wof:placetype":"venue"
},
  "geometry": {"coordinates":[3.0045819283,51.021232605],"type":"Point"}
}