{
  "type": "Feature",
  "properties": {
    "iso:country":"BE",
    "sg:address":"Springstraat 60",
    "sg:city":"Houthalen-helchteren",
    "sg:orig_category":"RESTAURANTS: CAF\u00c9S",
    "sg:phone":"+32 11 60 38 77",
    "sg:postcode":"3530",
    "sg:province":"Limburg",
    "wof:name":"Taverne Miniluna",
    "wof:placetype":"venue"
},
  "geometry": {"coordinates":[5.3981838226,51.0200424194],"type":"Point"}
}