{
  "type": "Feature",
  "properties": {
    "addr:full":"Kerselarenlaan 31 Liedekerke Vlaams-Brabant 1770",
    "addr:housenumber":"31",
    "addr:postcode":"1770",
    "addr:street":"Kerselarenlaan;Vlaams-Brabant",
    "iso:country":"BE",
    "sg:address":"Kerselarenlaan 31",
    "sg:city":"Liedekerke",
    "sg:orig_category":"Mat\u00e9riel \u00e9lectrique and \u00e9lectronique Gr",
    "sg:phone":"+32 53 66 26 18",
    "sg:postcode":"1770",
    "sg:province":"Vlaams-Brabant",
    "wof:name":"Elmeco Services Belgium",
    "wof:placetype":"venue"
},
  "geometry": {"coordinates":[4.1224131584,50.8574714661],"type":"Point"}
}