{
  "type": "Feature",
  "properties": {
    "addr:full":"Rue De L'eglise 33 Vise Li\u00e8ge 4602",
    "addr:housenumber":"33",
    "addr:postcode":"4602",
    "addr:street":"Rue De L'Eglise",
    "iso:country":"BE",
    "sg:address":"Rue De L'eglise 33",
    "sg:city":"Vise",
    "sg:orig_category":"Artsen and specialisten",
    "sg:phone":"+32 4 362 57 53",
    "sg:postcode":"4602",
    "sg:province":"Li\u00e8ge",
    "wof:name":"Raymond Courtois",
    "wof:placetype":"venue"
},
  "geometry": {"coordinates":[5.581829071,50.6424331665],"type":"Point"}
}