{
  "type": "Feature",
  "properties": {
    "iso:country":"BE",
    "sg:address":"Kauwlei 15",
    "sg:city":"Kontich (groot)",
    "sg:orig_category":"Plomberie, chauffage and installations sanitaires",
    "sg:phone":"+32 3 457 62 79",
    "sg:postcode":"2550",
    "sg:province":"Antwerpen",
    "wof:name":"Deservis",
    "wof:placetype":"venue"
},
  "geometry": {"coordinates":[4.4719758034,51.1331291199],"type":"Point"}
}