{
  "type": "Feature",
  "properties": {
    "addr:full":"Koningin Astridplein 14 Antwerpen Antwerpen 2018",
    "addr:housenumber":"14",
    "addr:postcode":"2018",
    "addr:street":"Koningin Astridplein",
    "iso:country":"BE",
    "sg:address":"Koningin Astridplein 14",
    "sg:city":"Antwerpen",
    "sg:classifiers":[
        {
            "category":"Travel",
            "subcategory":"Hotels & Motels",
            "type":"Entertainment"
        }
    ],
    "sg:phone":"+32 3 203 09 19",
    "sg:postcode":"2018",
    "sg:province":"Antwerpen",
    "wof:name":"Atlanta Hotel",
    "wof:placetype":"venue"
},
  "geometry": {"coordinates":[4.421889782,51.2183876038],"type":"Point"}
}