{
  "type": "Feature",
  "properties": {
    "addr:full":"Gentsesteenweg 119 Wetteren Oost-Vlaanderen 9230",
    "addr:housenumber":"119",
    "addr:postcode":"9230",
    "addr:street":"Gentsesteenweg",
    "iso:country":"BE",
    "sg:address":"Gentsesteenweg 119",
    "sg:city":"Wetteren",
    "sg:orig_category":"Kapsalons",
    "sg:phone":"+32 9 369 10 20",
    "sg:postcode":"9230",
    "sg:province":"Oost-Vlaanderen",
    "wof:name":"Jan Van Brussel",
    "wof:placetype":"venue"
},
  "geometry": {"coordinates":[3.8696980476,50.9999275208],"type":"Point"}
}