{
  "type": "Feature",
  "properties": {
    "addr:full":"Hoevensebaan 45 Kapellen Antwerpen 2950",
    "addr:housenumber":"45",
    "addr:postcode":"2950",
    "addr:street":"Hoevensebaan",
    "iso:country":"BE",
    "sg:address":"Hoevensebaan 45",
    "sg:city":"Kapellen",
    "sg:classifiers":[
        {
            "category":"Food & Beverages",
            "subcategory":"Fruits & Vegetables",
            "type":"Retail Goods"
        }
    ],
    "sg:phone":"+32 3 664 24 12",
    "sg:postcode":"2950",
    "sg:province":"Antwerpen",
    "sg:tags":[
        "l\u00e9gumes"
    ],
    "wof:name":"Andre De Schutter",
    "wof:placetype":"venue"
},
  "geometry": {"coordinates":[4.4268198013,51.3138847351],"type":"Point"}
}