{
  "type": "Feature",
  "properties": {
    "addr:full":"Gistelstraat 122 Ingelmunster West-Vlaanderen 8770",
    "addr:housenumber":"122",
    "addr:postcode":"8770",
    "addr:street":"Gistelstraat",
    "iso:country":"BE",
    "sg:address":"Gistelstraat 122",
    "sg:city":"Ingelmunster",
    "sg:orig_category":"Travaux de finition and nettoyage de b\u00e2timents. Construction de maisons. Constructions r\u00e9sidentielle",
    "sg:phone":"+32 51 31 25 76",
    "sg:postcode":"8770",
    "sg:province":"West-Vlaanderen",
    "wof:name":"Philippe Eeckhout",
    "wof:placetype":"venue"
},
  "geometry": {"coordinates":[3.2383298874,50.9334106445],"type":"Point"}
}