{
  "type": "Feature",
  "properties": {
    "iso:country":"BE",
    "sg:address":"Casterstraat 52",
    "sg:city":"Hasselt",
    "sg:orig_category":"Woningbouw",
    "sg:phone":"+32 11 22 65 99",
    "sg:postcode":"3500",
    "sg:province":"Limburg",
    "wof:name":"Alfons Davidts",
    "wof:placetype":"venue"
},
  "geometry": {"coordinates":[5.3493227959,50.927646637],"type":"Point"}
}