{
  "type": "Feature",
  "properties": {
    "addr:full":"Centrum Zuid 2004 B1 Houthalen-helchteren Limburg 3530",
    "addr:housenumber":"2004 b1",
    "addr:postcode":"3530",
    "addr:street":"Centrum Zuid",
    "iso:country":"BE",
    "sg:address":"Centrum Zuid 2004 B1",
    "sg:city":"Houthalen-helchteren",
    "sg:orig_category":"Ramassage and traitement des d\u00e9chets m\u00e9nagers. Collecte and \u00e9puration des eaux us\u00e9es",
    "sg:phone":"+32 11 52 37 32",
    "sg:postcode":"3530",
    "sg:province":"Limburg",
    "wof:name":"Biffa",
    "wof:placetype":"venue"
},
  "geometry": {"coordinates":[5.3719201088,51.0310020447],"type":"Point"}
}