{
  "type": "Feature",
  "properties": {
    "iso:country":"BE",
    "sg:address":"Place Des Trieux 14b",
    "sg:city":"Cerfontaine (daussois)",
    "sg:classifiers":[
        {
            "category":"Building & Trades",
            "subcategory":"Construction",
            "type":"Services"
        }
    ],
    "sg:phone":"+32 71 61 31 27",
    "sg:postcode":"5630",
    "sg:province":"Namur",
    "sg:tags":[
        "carpenter"
    ],
    "wof:name":"Marangon B",
    "wof:placetype":"venue"
},
  "geometry": {"coordinates":[4.459485054,50.2195587158],"type":"Point"}
}