{
  "type": "Feature",
  "properties": {
    "addr:full":"Rue De Tilff 0 Seraing Li\u00e8ge 4100",
    "addr:housenumber":"0",
    "addr:postcode":"4100",
    "addr:street":"Rue De Tilff",
    "iso:country":"BE",
    "sg:address":"Rue De Tilff 0",
    "sg:city":"Seraing",
    "sg:orig_category":"V\u00eatements pour Hommes. V\u00eatements pour b\u00e9b\u00e9s and enfants. V\u00eatements pour Dames",
    "sg:phone":"+32 4 337 68 88",
    "sg:postcode":"4100",
    "sg:province":"Li\u00e8ge",
    "wof:name":"Superconfex",
    "wof:placetype":"venue"
},
  "geometry": {"coordinates":[5.5135030746,50.6105766296],"type":"Point"}
}