{
  "type": "Feature",
  "properties": {
    "addr:full":"Leuvenseweg 8 Aarschot (rillaar) Vlaams-Brabant 3202",
    "addr:housenumber":"8",
    "addr:postcode":"3202",
    "addr:street":"Leuvenseweg",
    "iso:country":"BE",
    "sg:address":"Leuvenseweg 8",
    "sg:city":"Aarschot (rillaar)",
    "sg:classifiers":[
        {
            "category":"Health Services",
            "subcategory":"Dentist",
            "type":"Services"
        }
    ],
    "sg:phone":"+32 16 50 03 93",
    "sg:postcode":"3202",
    "sg:province":"Vlaams-Brabant",
    "wof:name":"Wauman G",
    "wof:placetype":"venue"
},
  "geometry": {"coordinates":[4.8915147781,50.9733848572],"type":"Point"}
}