{
  "type": "Feature",
  "properties": {
    "iso:country":"BE",
    "sg:address":"Hoogstadestraat 2",
    "sg:city":"Alveringem",
    "sg:orig_category":"Eleveurs and marchands de porcs. Eleveurs de bovins",
    "sg:phone":"+32 58 29 95 59",
    "sg:postcode":"8690",
    "sg:province":"West-Vlaanderen",
    "wof:name":"Marcel Derycke",
    "wof:placetype":"venue"
},
  "geometry": {"coordinates":[2.6850340366,51.0017242432],"type":"Point"}
}