{
  "type": "Feature",
  "properties": {
    "addr:full":"Chemin D'oeudeghien 92 Ath (ostiches) Hainaut 7804",
    "addr:housenumber":"92",
    "addr:postcode":"7804",
    "addr:street":"Chemin D'Oeudeghien",
    "iso:country":"BE",
    "sg:address":"Chemin D'oeudeghien 92",
    "sg:city":"Ath (ostiches)",
    "sg:classifiers":[
        {
            "category":"Banks & Credit Unions",
            "subcategory":"Investment Brokerage",
            "type":"Services"
        }
    ],
    "sg:phone":"+32 68 64 50 89",
    "sg:postcode":"7804",
    "sg:province":"Hainaut",
    "sg:tags":[
        "repair",
        "-",
        "installation",
        "sanitary",
        "article"
    ],
    "wof:name":"Terrasse Michel",
    "wof:placetype":"venue"
},
  "geometry": {"coordinates":[3.7348849773,50.667175293],"type":"Point"}
}