{
  "type": "Feature",
  "properties": {
    "iso:country":"BE",
    "sg:address":"Kapelstraat 1",
    "sg:city":"Harelbeke",
    "sg:orig_category":"Warenhuizen",
    "sg:phone":"+32 56 70 26 57",
    "sg:postcode":"8531",
    "sg:province":"West-Vlaanderen",
    "wof:name":"Xavier Callens",
    "wof:placetype":"venue"
},
  "geometry": {"coordinates":[3.2941710949,50.8820991516],"type":"Point"}
}