{
  "type": "Feature",
  "properties": {
    "iso:country":"BE",
    "sg:address":"Rotterdamstraat 36",
    "sg:city":"Antwerpen",
    "sg:classifiers":[
        {
            "category":"Building & Trades",
            "subcategory":"Construction",
            "type":"Services"
        }
    ],
    "sg:phone":"+32 3 225 28 11",
    "sg:postcode":"2060",
    "sg:province":"Antwerpen",
    "sg:tags":[
        "industrial",
        "design"
    ],
    "wof:name":"Airoc Bvba",
    "wof:placetype":"venue"
},
  "geometry": {"coordinates":[4.4188289642,51.223613739],"type":"Point"}
}