{
  "type": "Feature",
  "properties": {
    "iso:country":"BE",
    "sg:address":"Rue Defalque 37",
    "sg:city":"Court-saint-etienne",
    "sg:orig_category":"Rusthuizen and serviceflats",
    "sg:phone":"+32 10 61 21 64",
    "sg:postcode":"1490",
    "sg:province":"Brabant Wallon",
    "wof:name":"Home Libouton",
    "wof:placetype":"venue"
},
  "geometry": {"coordinates":[4.5658950806,50.6407737732],"type":"Point"}
}