{
  "type": "Feature",
  "properties": {
    "iso:country":"BE",
    "sg:address":"Beerzelse Steenweg 21",
    "sg:city":"Putte (beerzel)",
    "sg:classifiers":[
        {
            "category":"Farming",
            "subcategory":"Crops",
            "type":"Manufacturing & Wholesale Goods"
        }
    ],
    "sg:phone":"+32 15 75 48 90",
    "sg:postcode":"2580",
    "sg:province":"Antwerpen",
    "sg:tags":[
        "vegetable",
        "fruit",
        "-",
        "grower"
    ],
    "wof:name":"Francken L",
    "wof:placetype":"venue"
},
  "geometry": {"coordinates":[4.6850152016,51.0668678284],"type":"Point"}
}