{
  "type": "Feature",
  "properties": {
    "addr:full":"Berkenstraat 4 Heist-op-den-berg Antwerpen 2220",
    "addr:housenumber":"4",
    "addr:postcode":"2220",
    "addr:street":"Berkenstraat",
    "iso:country":"BE",
    "sg:address":"Berkenstraat 4",
    "sg:city":"Heist-op-den-berg",
    "sg:classifiers":[
        {
            "category":"Fast Food",
            "type":"Food & Drink"
        }
    ],
    "sg:phone":"+32 15 24 25 68",
    "sg:postcode":"2220",
    "sg:province":"Antwerpen",
    "sg:tags":[
        "fried",
        "stand",
        "potato"
    ],
    "wof:name":"Meenemerke ('t)",
    "wof:placetype":"venue"
},
  "geometry": {"coordinates":[4.717031002,51.0763015747],"type":"Point"}
}