{
  "type": "Feature",
  "properties": {
    "iso:country":"BE",
    "sg:address":"Koninklijke Jachtstraat 10",
    "sg:city":"Oudergem/auderghem",
    "sg:orig_category":"Benzinestations and brandstoffen",
    "sg:phone":"+32 2 660 10 56",
    "sg:postcode":"1160",
    "sg:province":"Bruxelles-Capitale",
    "wof:name":"Etienne Pierrard",
    "wof:placetype":"venue"
},
  "geometry": {"coordinates":[4.4038639069,50.8218917847],"type":"Point"}
}