{
  "type": "Feature",
  "properties": {
    "iso:country":"BE",
    "sg:address":"Nijverheidstraat 14",
    "sg:city":"Diksmuide",
    "sg:orig_category":"Peinture",
    "sg:phone":"+32 51 50 05 01",
    "sg:postcode":"8600",
    "sg:province":"West-Vlaanderen",
    "wof:name":"Cyclo Color Herreman",
    "wof:placetype":"venue"
},
  "geometry": {"coordinates":[2.8591310978,51.0270347595],"type":"Point"}
}