{
  "type": "Feature",
  "properties": {
    "iso:country":"BE",
    "sg:address":"Doornstraat 34",
    "sg:city":"Sint-gillis-waas",
    "sg:classifiers":[
        {
            "category":"Professional",
            "subcategory":"Advertising",
            "type":"Services"
        }
    ],
    "sg:phone":"+32 3 770 78 09",
    "sg:postcode":"9170",
    "sg:province":"Oost-Vlaanderen",
    "sg:tags":[
        "painter"
    ],
    "wof:name":"Prisma Sign Bvba",
    "wof:placetype":"venue"
},
  "geometry": {"coordinates":[4.1302609444,51.2103996277],"type":"Point"}
}