{
  "type": "Feature",
  "properties": {
    "iso:country":"BE",
    "sg:address":"Alsembergse Steenweg 869",
    "sg:city":"Ukkel/uccle",
    "sg:orig_category":"Antiek",
    "sg:phone":"+32 2 376 87 47",
    "sg:postcode":"1180",
    "sg:province":"Bruxelles-Capitale",
    "wof:name":"Maison L\u00b4amboine",
    "wof:placetype":"venue"
},
  "geometry": {"coordinates":[4.3363361359,50.8000602722],"type":"Point"}
}