{
  "type": "Feature",
  "properties": {
    "addr:full":"Twee Leeuwenstraat 2 Kortenberg (everberg) Vlaams-Brabant 3078",
    "addr:housenumber":"2",
    "addr:postcode":"3078",
    "addr:street":"Twee Leeuwenstraat",
    "iso:country":"BE",
    "sg:address":"Twee Leeuwenstraat 2",
    "sg:city":"Kortenberg (everberg)",
    "sg:classifiers":[
        {
            "category":"Professional",
            "subcategory":"Management & Consulting",
            "type":"Services"
        }
    ],
    "sg:phone":"+32 2 759 52 08",
    "sg:postcode":"3078",
    "sg:province":"Vlaams-Brabant",
    "sg:tags":[
        "-",
        "processing",
        "data",
        "consultant"
    ],
    "wof:name":"Baudemprez",
    "wof:placetype":"venue"
},
  "geometry": {"coordinates":[4.5724301338,50.8780708313],"type":"Point"}
}