{
  "type": "Feature",
  "properties": {
    "addr:full":"Rue Du Melkriek 3 Ukkel/uccle Bruxelles-Capitale 1180",
    "addr:housenumber":"3",
    "addr:postcode":"1180",
    "addr:street":"Rue Du Melkriek;/",
    "iso:country":"BE",
    "sg:address":"Rue Du Melkriek 3",
    "sg:city":"Ukkel/uccle",
    "sg:orig_category":"Enseignement maternel and primaire",
    "sg:phone":"+32 2 376 11 76",
    "sg:postcode":"1180",
    "sg:province":"Bruxelles-Capitale",
    "wof:name":"Ecole Fondamentale Libre",
    "wof:placetype":"venue"
},
  "geometry": {"coordinates":[4.3260321617,50.7876014709],"type":"Point"}
}