{
  "type": "Feature",
  "properties": {
    "iso:country":"BE",
    "sg:address":"Chauss\u00c9e De Bruxelles 253",
    "sg:city":"Wemmel",
    "sg:orig_category":"V\u00e9hicules automobiles. Entretien and r\u00e9parations de voitures",
    "sg:phone":"+32 2 460 77 67",
    "sg:postcode":"1780",
    "sg:province":"Vlaams-Brabant",
    "wof:name":"Abrumatrans",
    "wof:placetype":"venue"
},
  "geometry": {"coordinates":[4.3096108437,50.8998451233],"type":"Point"}
}