{
  "type": "Feature",
  "properties": {
    "iso:country":"BE",
    "sg:address":"Rue Des Fran\u00e7ais 37",
    "sg:city":"Charleroi (dampremy)",
    "sg:classifiers":[
        {
            "category":"Recreation",
            "subcategory":"Dance Hall",
            "type":"Entertainment"
        }
    ],
    "sg:phone":"+32 71 32 26 59",
    "sg:postcode":"6020",
    "sg:province":"Hainaut",
    "sg:tags":[
        "discotheque"
    ],
    "wof:name":"New Plaza",
    "wof:placetype":"venue"
},
  "geometry": {"coordinates":[4.4384660721,50.4220085144],"type":"Point"}
}