{
  "type": "Feature",
  "properties": {
    "addr:full":"Sint-antoniusbaan 386 Zoersel Antwerpen 2980",
    "addr:housenumber":"386",
    "addr:postcode":"2980",
    "iso:country":"BE",
    "sg:address":"Sint-antoniusbaan 386",
    "sg:city":"Zoersel",
    "sg:classifiers":[
        {
            "category":"Autos & Motor Vehicles",
            "subcategory":"Fuel & Gas Station",
            "type":"Retail Goods"
        }
    ],
    "sg:phone":"+32 3 383 21 12",
    "sg:postcode":"2980",
    "sg:province":"Antwerpen",
    "wof:name":"Bel Oil",
    "wof:placetype":"venue"
},
  "geometry": {"coordinates":[4.6506819725,51.2670288086],"type":"Point"}
}