{
  "type": "Feature",
  "properties": {
    "addr:full":"Rue Du Souverain 24 Charleroi Hainaut 6040",
    "addr:housenumber":"24",
    "addr:postcode":"6040",
    "addr:street":"Rue Du Souverain;Hainaut",
    "iso:country":"BE",
    "sg:address":"Rue Du Souverain 24",
    "sg:city":"Charleroi",
    "sg:orig_category":"Plomberie, chauffage and installations sanitaires",
    "sg:phone":"+32 71 34 35 76",
    "sg:postcode":"6040",
    "sg:province":"Hainaut",
    "wof:name":"Riccardo Rinaldi",
    "wof:placetype":"venue"
},
  "geometry": {"coordinates":[4.42441082,50.4393768311],"type":"Point"}
}