{
  "type": "Feature",
  "properties": {
    "iso:country":"BE",
    "sg:address":"Phoenixstraat 65",
    "sg:city":"Gent",
    "sg:orig_category":"Chaussures",
    "sg:phone":"+32 9 226 42 27",
    "sg:postcode":"9000",
    "sg:province":"Oost-Vlaanderen",
    "wof:name":"Phoenix-shoe",
    "wof:placetype":"venue"
},
  "geometry": {"coordinates":[3.7056159973,51.0580673218],"type":"Point"}
}