{
  "type": "Feature",
  "properties": {
    "addr:full":"Sint-truidersteenweg 151 Hasselt Limburg 3500",
    "addr:housenumber":"151",
    "addr:postcode":"3500",
    "addr:street":"Sint-Truidersteenweg",
    "iso:country":"BE",
    "sg:address":"Sint-truidersteenweg 151",
    "sg:city":"Hasselt",
    "sg:classifiers":[
        {
            "category":"Shopping",
            "subcategory":"Florist",
            "type":"Retail Goods"
        }
    ],
    "sg:phone":"+32 11 27 06 41",
    "sg:postcode":"3500",
    "sg:province":"Limburg",
    "wof:name":"Florina",
    "wof:placetype":"venue"
},
  "geometry": {"coordinates":[5.3311572075,50.9222679138],"type":"Point"}
}