{
  "type": "Feature",
  "properties": {
    "iso:country":"BE",
    "sg:address":"Mispelbilk 13",
    "sg:city":"Gent (mariakerke)",
    "sg:classifiers":[
        {
            "category":"Home & Garden",
            "subcategory":"Home Furnishings",
            "type":"Retail Goods"
        }
    ],
    "sg:phone":"+32 9 227 81 02",
    "sg:postcode":"9030",
    "sg:province":"Oost-Vlaanderen",
    "sg:tags":[
        "interior",
        "decoration"
    ],
    "wof:name":"Godema Cvba",
    "wof:placetype":"venue"
},
  "geometry": {"coordinates":[3.6886100769,51.0867156982],"type":"Point"}
}