{
  "type": "Feature",
  "properties": {
    "addr:full":"Rue De La Passerelle 121 Mouscron Hainaut 7700",
    "addr:housenumber":"121",
    "addr:postcode":"7700",
    "addr:street":"Rue De La Passerelle",
    "iso:country":"BE",
    "sg:address":"Rue De La Passerelle 121",
    "sg:city":"Mouscron",
    "sg:classifiers":[
        {
            "category":"Manufacturing",
            "subcategory":"Printing",
            "type":"Manufacturing & Wholesale Goods"
        }
    ],
    "sg:phone":"+32 56 85 75 00",
    "sg:postcode":"7700",
    "sg:province":"Hainaut",
    "sg:tags":[
        "textile",
        "-"
    ],
    "wof:name":"Beechin's & Texim Sa",
    "wof:placetype":"venue"
},
  "geometry": {"coordinates":[3.2309200764,50.7449302673],"type":"Point"}
}