{
  "type": "Feature",
  "properties": {
    "iso:country":"BE",
    "sg:address":"Chauss\u00e9e Churchill 79",
    "sg:city":"Saint-nicolas (montegn\u00e9e)",
    "sg:classifiers":[
        {
            "category":"Community Center",
            "type":"Public Place"
        }
    ],
    "sg:phone":"+32 4 263 90 96",
    "sg:postcode":"4420",
    "sg:province":"Li\u00e8ge",
    "sg:tags":[
        "medical"
    ],
    "wof:name":"Centre M\u00e9dical D'audio-phonologie Asbl",
    "wof:placetype":"venue"
},
  "geometry": {"coordinates":[5.5244197845,50.6453590393],"type":"Point"}
}