{
  "type": "Feature",
  "properties": {
    "addr:full":"Rempart Vieux Cimeti\u00c8re 5 Zinnik Hainaut 7060",
    "addr:housenumber":"5",
    "addr:postcode":"7060",
    "addr:street":"Rempart Vieux Cimetie\u0300Re;Hainaut",
    "iso:country":"BE",
    "sg:address":"Rempart Vieux Cimeti\u00c8re 5",
    "sg:city":"Zinnik",
    "sg:orig_category":"Sociale secretariaten Verplichte sociale verzekeringen",
    "sg:phone":"+32 67 33 20 78",
    "sg:postcode":"7060",
    "sg:province":"Hainaut",
    "wof:name":"Partena",
    "wof:placetype":"venue"
},
  "geometry": {"coordinates":[4.071808815,50.5813560486],"type":"Point"}
}