{
  "type": "Feature",
  "properties": {
    "addr:full":"Bovigny 54 Gouvy Luxembourg 6671",
    "addr:housenumber":"54",
    "addr:postcode":"6671",
    "addr:street":"Bovigny",
    "iso:country":"BE",
    "sg:address":"Bovigny 54",
    "sg:city":"Gouvy",
    "sg:orig_category":"Overheidsdiensten",
    "sg:phone":"+32 80 29 29 21",
    "sg:postcode":"6671",
    "sg:province":"Luxembourg",
    "wof:name":"Administration Communale",
    "wof:placetype":"venue"
},
  "geometry": {"coordinates":[5.9151639938,50.2191238403],"type":"Point"}
}