{
  "type": "Feature",
  "properties": {
    "addr:full":"Place Communale 3 Beauvechain Brabant Wallon 1320",
    "addr:housenumber":"3",
    "addr:postcode":"1320",
    "addr:street":"Place Communale",
    "iso:country":"BE",
    "sg:address":"Place Communale 3",
    "sg:city":"Beauvechain",
    "sg:classifiers":[
        {
            "category":"Government",
            "subcategory":"Police Station",
            "type":"Public Place"
        }
    ],
    "sg:phone":"+32 10 86 02 05",
    "sg:postcode":"1320",
    "sg:province":"Brabant Wallon",
    "sg:tags":[
        "gendarmerie"
    ],
    "wof:name":"Police F\u00c9d\u00c9rale",
    "wof:placetype":"venue"
},
  "geometry": {"coordinates":[4.7723550797,50.7806587219],"type":"Point"}
}