{
  "type": "Feature",
  "properties": {
    "iso:country":"BE",
    "sg:address":"Rue Saint-jean 2",
    "sg:city":"Tubize",
    "sg:orig_category":"Elektrische installaties voor woningen",
    "sg:phone":"+32 2 355 31 56",
    "sg:postcode":"1480",
    "sg:province":"Brabant Wallon",
    "wof:name":"Eddy Walravens",
    "wof:placetype":"venue"
},
  "geometry": {"coordinates":[4.2229800224,50.6902885437],"type":"Point"}
}