{
  "type": "Feature",
  "properties": {
    "addr:full":"Rue Du Pr\u00e9sident 74 Bruxelles (ixelles) Bruxelles-Capitale 1050",
    "addr:housenumber":"74",
    "addr:postcode":"1050",
    "addr:street":"Rue Du Pre\u0301Sident",
    "iso:country":"BE",
    "sg:address":"Rue Du Pr\u00e9sident 74",
    "sg:city":"Bruxelles (ixelles)",
    "sg:classifiers":[
        {
            "category":"Professional",
            "subcategory":"Art Services",
            "type":"Services"
        }
    ],
    "sg:phone":"+32 2 512 22 35",
    "sg:postcode":"1050",
    "sg:province":"Bruxelles-Capitale",
    "sg:tags":[
        "interior",
        "designer"
    ],
    "wof:name":"Delacroix Et Friant Sprl",
    "wof:placetype":"venue"
},
  "geometry": {"coordinates":[4.3603777885,50.8315238953],"type":"Point"}
}