{
  "type": "Feature",
  "properties": {
    "iso:country":"BE",
    "sg:address":"Place De Buissenal 25",
    "sg:city":"Frasnes-lez-anvaing",
    "sg:orig_category":"Brood, gebak and snoepgoed",
    "sg:phone":"+32 69 86 62 12",
    "sg:postcode":"7911",
    "sg:province":"Hainaut",
    "wof:name":"Edgard Willocq",
    "wof:placetype":"venue"
},
  "geometry": {"coordinates":[3.6534318924,50.6638565063],"type":"Point"}
}