{
  "type": "Feature",
  "properties": {
    "iso:country":"BE",
    "sg:address":"Mgr. Van Waeyenberghlaan 3",
    "sg:city":"Leuven",
    "sg:orig_category":"Banken and kredietinstellingen",
    "sg:phone":"+32 16 29 42 16",
    "sg:postcode":"3000",
    "sg:province":"Vlaams-Brabant",
    "wof:name":"Groep Argenta",
    "wof:placetype":"venue"
},
  "geometry": {"coordinates":[4.6887588501,50.879486084],"type":"Point"}
}