{
  "type": "Feature",
  "properties": {
    "addr:full":"Blauwstraat 13 Boom Antwerpen 2850",
    "addr:housenumber":"13",
    "addr:postcode":"2850",
    "addr:street":"Blauwstraat",
    "iso:country":"BE",
    "sg:address":"Blauwstraat 13",
    "sg:city":"Boom",
    "sg:classifiers":[
        {
            "category":"Shopping",
            "subcategory":"Clothing, Apparel, & Fashions",
            "type":"Retail Goods"
        }
    ],
    "sg:phone":"+32 3 844 57 67",
    "sg:postcode":"2850",
    "sg:province":"Antwerpen",
    "sg:tags":[
        "-",
        "clothing",
        "child"
    ],
    "wof:name":"Axelyntje",
    "wof:placetype":"venue"
},
  "geometry": {"coordinates":[4.3668727875,51.0864257812],"type":"Point"}
}