{
  "type": "Feature",
  "properties": {
    "iso:country":"BE",
    "sg:address":"Vanderstichelenstraat 42",
    "sg:city":"Sint-jans-molenbeek/molenbeek-saint-jean",
    "sg:orig_category":"Drukkerijen and copyshops",
    "sg:phone":"+32 2 425 06 20",
    "sg:postcode":"1080",
    "sg:province":"Bruxelles-Capitale",
    "wof:name":"U.p.o.",
    "wof:placetype":"venue"
},
  "geometry": {"coordinates":[4.3411679268,50.8623466492],"type":"Point"}
}