{
  "type": "Feature",
  "properties": {
    "addr:full":"Koning Leopold Iii Plein 12 Blankenberge West-Vlaanderen 8370",
    "addr:housenumber":"12",
    "addr:postcode":"8370",
    "addr:street":"Koning Leopold Iii Plein",
    "iso:country":"BE",
    "sg:address":"Koning Leopold Iii Plein 12",
    "sg:city":"Blankenberge",
    "sg:classifiers":[
        {
            "category":"Travel",
            "subcategory":"Hotels & Motels",
            "type":"Entertainment"
        }
    ],
    "sg:phone":"+32 50 41 79 24",
    "sg:postcode":"8370",
    "sg:province":"West-Vlaanderen",
    "sg:tags":[
        "caf\u00e9s"
    ],
    "wof:name":"Hotel Fl\u00cache D'or",
    "wof:placetype":"venue"
},
  "geometry": {"coordinates":[3.1331410408,51.313419342],"type":"Point"}
}