{
  "type": "Feature",
  "properties": {
    "addr:full":"Wippelgemdorp 50 Evergem Oost-Vlaanderen 9940",
    "addr:housenumber":"50",
    "addr:postcode":"9940",
    "addr:street":"Wippelgemdorp;Oost-Vlaanderen",
    "iso:country":"BE",
    "sg:address":"Wippelgemdorp 50",
    "sg:city":"Evergem",
    "sg:classifiers":[
        {
            "category":"Cafe",
            "type":"Food & Drink"
        }
    ],
    "sg:phone":"+32 9 357 42 71",
    "sg:postcode":"9940",
    "sg:province":"Oost-Vlaanderen",
    "sg:tags":[
        "caf\u00e9s"
    ],
    "wof:name":"Caf\u00c9 Santana",
    "wof:placetype":"venue"
},
  "geometry": {"coordinates":[3.7317099571,51.1429786682],"type":"Point"}
}