{
  "type": "Feature",
  "properties": {
    "iso:country":"BE",
    "sg:address":"Kinderstraat 178",
    "sg:city":"Lint",
    "sg:orig_category":"Installatie van metalen schrijnwerk",
    "sg:phone":"+32 3 454 38 94",
    "sg:postcode":"2547",
    "sg:province":"Antwerpen",
    "wof:name":"Dymotech Services",
    "wof:placetype":"venue"
},
  "geometry": {"coordinates":[4.5037670135,51.1183509827],"type":"Point"}
}