{
  "type": "Feature",
  "properties": {
    "addr:full":"Engelse Wandeling 25f Kortrijk West-Vlaanderen 8500",
    "addr:housenumber":"25f",
    "addr:postcode":"8500",
    "addr:street":"Engelse Wandeling",
    "iso:country":"BE",
    "sg:address":"Engelse Wandeling 25f",
    "sg:city":"Kortrijk",
    "sg:classifiers":[
        {
            "category":"Home & Garden",
            "subcategory":"Home Furnishings",
            "type":"Retail Goods"
        }
    ],
    "sg:phone":"+32 56 21 19 99",
    "sg:postcode":"8500",
    "sg:province":"West-Vlaanderen",
    "sg:tags":[
        "interior",
        "decoration"
    ],
    "wof:name":"Tex Decor Nv",
    "wof:placetype":"venue"
},
  "geometry": {"coordinates":[3.276184082,50.8263282776],"type":"Point"}
}