{
  "type": "Feature",
  "properties": {
    "addr:full":"Diksmuidestraat 16 Houthulst West-Vlaanderen 8650",
    "addr:housenumber":"16",
    "addr:postcode":"8650",
    "addr:street":"Diksmuidestraat",
    "iso:country":"BE",
    "sg:address":"Diksmuidestraat 16",
    "sg:city":"Houthulst",
    "sg:orig_category":"Divers amusement Huishoudapparaten, televisies and radio's Verhuur televisie- and audiovisuele appar",
    "sg:phone":"+32 51 54 55 03",
    "sg:postcode":"8650",
    "sg:province":"West-Vlaanderen",
    "wof:name":"Disco Speedo",
    "wof:placetype":"venue"
},
  "geometry": {"coordinates":[2.9509439468,50.9778862],"type":"Point"}
}