{
  "type": "Feature",
  "properties": {
    "addr:full":"Rue De La Croisette 188 La Louviere Hainaut 7110",
    "addr:housenumber":"188",
    "addr:postcode":"7110",
    "addr:street":"Rue De La Croisette",
    "iso:country":"BE",
    "sg:address":"Rue De La Croisette 188",
    "sg:city":"La Louviere",
    "sg:orig_category":"Bouwmaterialen Gh",
    "sg:phone":"+32 64 66 43 79",
    "sg:postcode":"7110",
    "sg:province":"Hainaut",
    "wof:name":"Timos",
    "wof:placetype":"venue"
},
  "geometry": {"coordinates":[4.1505050659,50.4826698303],"type":"Point"}
}