{
  "type": "Feature",
  "properties": {
    "addr:full":"Pl De La Cath\u00e9drale 10 Li\u00e8ge Li\u00e8ge 4000",
    "addr:housenumber":"10",
    "addr:postcode":"4000",
    "addr:street":"Pl De La Cathe\u0301Drale",
    "iso:country":"BE",
    "sg:address":"Pl De La Cath\u00e9drale 10",
    "sg:city":"Li\u00e8ge",
    "sg:classifiers":[
        {
            "category":"Shopping",
            "subcategory":"Luggage & Leather Goods",
            "type":"Retail Goods"
        }
    ],
    "sg:phone":"+32 4 223 27 07",
    "sg:postcode":"4000",
    "sg:province":"Li\u00e8ge",
    "sg:tags":[
        "shoe"
    ],
    "wof:name":"Germaine Collard Sprl",
    "wof:placetype":"venue"
},
  "geometry": {"coordinates":[5.5708670616,50.6410064697],"type":"Point"}
}