{
  "type": "Feature",
  "properties": {
    "addr:full":"Rue Des Guildes 14 Bruxelles Bruxelles-Capitale 1000",
    "addr:housenumber":"14",
    "addr:postcode":"1000",
    "addr:street":"Rue Des Guildes",
    "iso:country":"BE",
    "sg:address":"Rue Des Guildes 14",
    "sg:city":"Bruxelles",
    "sg:classifiers":[
        {
            "category":"Organizations",
            "subcategory":"Professional Association",
            "type":"Services"
        }
    ],
    "sg:phone":"+32 2 230 92 33",
    "sg:postcode":"1000",
    "sg:province":"Bruxelles-Capitale",
    "sg:tags":[
        "trade-union",
        "federation"
    ],
    "wof:name":"Conf\u00e9d\u00e9ration Des Associ\u00e9s Kurdes En Europe",
    "wof:placetype":"venue"
},
  "geometry": {"coordinates":[4.3765439987,50.848777771],"type":"Point"}
}