{
  "type": "Feature",
  "properties": {
    "iso:country":"BE",
    "sg:address":"Chemin Des Postes 151a",
    "sg:city":"Waterloo",
    "sg:orig_category":"Quincailleries",
    "sg:phone":"+32 2 354 93 44",
    "sg:postcode":"1410",
    "sg:province":"Brabant Wallon",
    "wof:name":"Sorex Int.",
    "wof:placetype":"venue"
},
  "geometry": {"coordinates":[4.3711857796,50.7076644897],"type":"Point"}
}