{
  "type": "Feature",
  "properties": {
    "iso:country":"BE",
    "sg:address":"Avenue L\u00c9on Jourez 4",
    "sg:city":"Braine-l'alleud",
    "sg:orig_category":"Alimentation sp\u00e9cialis\u00e9e. Catering and organisation de f\u00eates",
    "sg:phone":"+32 2 387 34 52",
    "sg:postcode":"1420",
    "sg:province":"Brabant Wallon",
    "wof:name":"Christophe Polleunis",
    "wof:placetype":"venue"
},
  "geometry": {"coordinates":[-0.7004899979,47.369140625],"type":"Point"}
}