{
  "type": "Feature",
  "properties": {
    "addr:full":"Zandrede 22 Destelbergen (heusden) Oost-Vlaanderen 9070",
    "addr:housenumber":"22",
    "addr:postcode":"9070",
    "addr:street":"Zandrede",
    "iso:country":"BE",
    "sg:address":"Zandrede 22",
    "sg:city":"Destelbergen (heusden)",
    "sg:orig_category":"Non-Classified Establishments",
    "sg:phone":"+32 9 232 00 19",
    "sg:postcode":"9070",
    "sg:province":"Oost-Vlaanderen",
    "wof:name":"Modistyle",
    "wof:placetype":"venue"
},
  "geometry": {"coordinates":[3.8036749363,51.029384613],"type":"Point"}
}