{
  "type": "Feature",
  "properties": {
    "iso:country":"BE",
    "sg:address":"Rue De Lichtenbusch 201",
    "sg:city":"Raeren",
    "sg:orig_category":"Mat\u00e9riaux de construction Gr",
    "sg:phone":"+32 87 86 68 07",
    "sg:postcode":"4731",
    "sg:province":"Li\u00e8ge",
    "wof:name":"Theodor Diederichs",
    "wof:placetype":"venue"
},
  "geometry": {"coordinates":[6.1127710342,50.7143287659],"type":"Point"}
}