{
  "type": "Feature",
  "properties": {
    "iso:country":"BE",
    "sg:address":"Pittemstraat 85",
    "sg:city":"Meulebeke",
    "sg:orig_category":"Varkenskwekers",
    "sg:phone":"+32 51 48 91 80",
    "sg:postcode":"8760",
    "sg:province":"West-Vlaanderen",
    "wof:name":"Hubert Dobbels",
    "wof:placetype":"venue"
},
  "geometry": {"coordinates":[3.2809329033,50.954574585],"type":"Point"}
}