{
  "type": "Feature",
  "properties": {
    "addr:full":"Haachtse Steenweg 41 Brussel/bruxelles Bruxelles-Capitale 1210",
    "addr:housenumber":"41",
    "addr:postcode":"1210",
    "addr:street":"Haachtse Steenweg;/",
    "iso:country":"BE",
    "sg:address":"Haachtse Steenweg 41",
    "sg:city":"Brussel/bruxelles",
    "sg:orig_category":"Bloemen and planten",
    "sg:phone":"+32 2 217 84 61",
    "sg:postcode":"1210",
    "sg:province":"Bruxelles-Capitale",
    "wof:name":"Fleuranne",
    "wof:placetype":"venue"
},
  "geometry": {"coordinates":[4.3682818413,50.8558998108],"type":"Point"}
}