{
  "type": "Feature",
  "properties": {
    "addr:full":"Meulekensstraat 15 Ronse Oost-Vlaanderen 9600",
    "addr:housenumber":"15",
    "addr:postcode":"9600",
    "addr:street":"Meulekensstraat",
    "iso:country":"BE",
    "sg:address":"Meulekensstraat 15",
    "sg:city":"Ronse",
    "sg:orig_category":"Ordinateurs and \u00e9quipement informatique. Traitement de donn\u00e9es",
    "sg:phone":"+32 55 21 71 40",
    "sg:postcode":"9600",
    "sg:province":"Oost-Vlaanderen",
    "wof:name":"Berco",
    "wof:placetype":"venue"
},
  "geometry": {"coordinates":[3.5993049145,50.7470397949],"type":"Point"}
}