{
  "type": "Feature",
  "properties": {
    "addr:full":"Patersplein 3ba Diepenbeek Limburg 3590",
    "addr:housenumber":"3ba",
    "addr:postcode":"3590",
    "addr:street":"Patersplein",
    "iso:country":"BE",
    "sg:address":"Patersplein 3ba",
    "sg:city":"Diepenbeek",
    "sg:orig_category":"Pain, p\u00e2tisseries and confiseries",
    "sg:phone":"+32 11 32 45 97",
    "sg:postcode":"3590",
    "sg:province":"Limburg",
    "wof:name":"Bakkerij Windmolders",
    "wof:placetype":"venue"
},
  "geometry": {"coordinates":[5.4180469513,50.9365615845],"type":"Point"}
}