{
  "type": "Feature",
  "properties": {
    "iso:country":"BE",
    "sg:address":"Rue Du G\u00c9n\u00c9ral Jacques 250",
    "sg:city":"Chaudfontaine",
    "sg:orig_category":"Installation de menuiserie en bois and plastique",
    "sg:phone":"+32 4 365 01 65",
    "sg:postcode":"4051",
    "sg:province":"Li\u00e8ge",
    "wof:name":"Henri De Seny",
    "wof:placetype":"venue"
},
  "geometry": {"coordinates":[5.6319718361,50.5948143005],"type":"Point"}
}