{
  "type": "Feature",
  "properties": {
    "iso:country":"BE",
    "sg:address":"Rue D'iseghem 167",
    "sg:city":"Mouscron",
    "sg:classifiers":[
        {
            "category":"Retail",
            "subcategory":"Auto Repair",
            "type":"Services"
        }
    ],
    "sg:phone":"+32 56 84 59 75",
    "sg:postcode":"7700",
    "sg:province":"Hainaut",
    "sg:tags":[
        "automobile",
        "servic",
        "electrical",
        "-"
    ],
    "wof:name":"Acma",
    "wof:placetype":"venue"
},
  "geometry": {"coordinates":[3.2043321133,50.7467498779],"type":"Point"}
}