{
  "type": "Feature",
  "properties": {
    "addr:full":"Rue De L'escalette 88 Tournai Hainaut 7500",
    "addr:housenumber":"88",
    "addr:postcode":"7500",
    "addr:street":"Rue De L'Escalette",
    "iso:country":"BE",
    "sg:address":"Rue De L'escalette 88",
    "sg:city":"Tournai",
    "sg:classifiers":[
        {
            "category":"Health Services",
            "subcategory":"Doctor",
            "type":"Services"
        }
    ],
    "sg:phone":"+32 69 21 41 07",
    "sg:postcode":"7500",
    "sg:province":"Hainaut",
    "sg:tags":[
        "medicinephysicians",
        "surgeon"
    ],
    "wof:name":"Huicq Pierre",
    "wof:placetype":"venue"
},
  "geometry": {"coordinates":[3.3700699806,50.6168365479],"type":"Point"}
}