{
  "type": "Feature",
  "properties": {
    "iso:country":"BE",
    "sg:address":"Steenweg Op Zevendonk 281",
    "sg:city":"Turnhout",
    "sg:classifiers":[
        {
            "category":"Wholesale",
            "subcategory":"Vending Machines",
            "type":"Manufacturing & Wholesale Goods"
        }
    ],
    "sg:phone":"+32 14 41 08 33",
    "sg:postcode":"2300",
    "sg:province":"Antwerpen",
    "sg:tags":[
        "labeling"
    ],
    "wof:name":"Moris Nv",
    "wof:placetype":"venue"
},
  "geometry": {"coordinates":[4.9553952217,51.2986106873],"type":"Point"}
}