{
  "type": "Feature",
  "properties": {
    "iso:country":"BE",
    "sg:address":"Affligemdreef 143",
    "sg:city":"Aalst",
    "sg:orig_category":"M\u00e9decins and sp\u00e9cialistes",
    "sg:phone":"+32 53 78 00 53",
    "sg:postcode":"9300",
    "sg:province":"Oost-Vlaanderen",
    "wof:name":"Paul Devroey",
    "wof:placetype":"venue"
},
  "geometry": {"coordinates":[4.0729861259,50.9363517761],"type":"Point"}
}