{
  "type": "Feature",
  "properties": {
    "iso:country":"BE",
    "sg:address":"Noorderlaan 133b3",
    "sg:city":"Antwerpen",
    "sg:orig_category":"Goederenvervoer over de weg Vrachtvervoer",
    "sg:phone":"+32 3 542 00 43",
    "sg:postcode":"2030",
    "sg:province":"Antwerpen",
    "wof:name":"Andrea Merzario",
    "wof:placetype":"venue"
},
  "geometry": {"coordinates":[4.402130127,51.2644462585],"type":"Point"}
}