{
  "type": "Feature",
  "properties": {
    "addr:full":"Roeselarestraat 46 Staden West-Vlaanderen 8840",
    "addr:housenumber":"46",
    "addr:postcode":"8840",
    "addr:street":"Roeselarestraat",
    "iso:country":"BE",
    "sg:address":"Roeselarestraat 46",
    "sg:city":"Staden",
    "sg:orig_category":"Apotheken",
    "sg:phone":"+32 51 20 32 29",
    "sg:postcode":"8840",
    "sg:province":"West-Vlaanderen",
    "wof:name":"Sofie Walcarius",
    "wof:placetype":"venue"
},
  "geometry": {"coordinates":[3.0127930641,50.9751815796],"type":"Point"}
}