{
  "type": "Feature",
  "properties": {
    "iso:country":"BE",
    "sg:address":"Industrieweg 5",
    "sg:city":"Grimbergen",
    "sg:orig_category":"Chemicali\u00ebn Gh",
    "sg:phone":"+32 2 255 94 35",
    "sg:postcode":"1850",
    "sg:province":"Vlaams-Brabant",
    "wof:name":"Certified Laboratories",
    "wof:placetype":"venue"
},
  "geometry": {"coordinates":[4.4096798897,50.9438934326],"type":"Point"}
}