{
  "type": "Feature",
  "properties": {
    "addr:full":". Poperinge (groot) West-Vlaanderen 8970",
    "addr:postcode":"8970",
    "addr:street":"Groot West-Vlaanderen",
    "iso:country":"BE",
    "sg:address":".",
    "sg:city":"Poperinge (groot)",
    "sg:orig_category":"Apotheken",
    "sg:phone":"+32 900 10 500",
    "sg:postcode":"8970",
    "sg:province":"West-Vlaanderen",
    "wof:name":"Apothekers Van Wacht",
    "wof:placetype":"venue"
},
  "geometry": {"coordinates":[2.7263898849,50.8555984497],"type":"Point"}
}