{
  "type": "Feature",
  "properties": {
    "iso:country":"BE",
    "sg:address":"Komenstraat 49bis",
    "sg:city":"Wervik",
    "sg:classifiers":[
        {
            "category":"Real Estate",
            "subcategory":"Architect",
            "type":"Services"
        }
    ],
    "sg:phone":"+32 56 31 20 20",
    "sg:postcode":"8940",
    "sg:province":"West-Vlaanderen",
    "wof:name":"Lannoy W",
    "wof:placetype":"venue"
},
  "geometry": {"coordinates":[3.0349678993,50.7802581787],"type":"Point"}
}