{
  "type": "Feature",
  "properties": {
    "iso:country":"BE",
    "sg:address":"Rue Antoine Andr\u00e9 68a",
    "sg:city":"Wavre (limal)",
    "sg:classifiers":[
        {
            "category":"Wholesale",
            "subcategory":"Tobacco Products",
            "type":"Manufacturing & Wholesale Goods"
        }
    ],
    "sg:phone":"+32 10 62 01 29",
    "sg:postcode":"1300",
    "sg:province":"Brabant Wallon",
    "sg:tags":[
        "-",
        "biotechnology",
        "installation",
        "equipment"
    ],
    "wof:name":"Cp Diag",
    "wof:placetype":"venue"
},
  "geometry": {"coordinates":[4.5906839371,50.6874313354],"type":"Point"}
}