{
  "type": "Feature",
  "properties": {
    "addr:full":"Bosdreef 121ba Kapellen Antwerpen 2950",
    "addr:housenumber":"121ba",
    "addr:postcode":"2950",
    "addr:street":"Bosdreef",
    "iso:country":"BE",
    "sg:address":"Bosdreef 121ba",
    "sg:city":"Kapellen",
    "sg:orig_category":"Hout and afgeleiden Gh IJzerwaren, bouw- and verfmaterialen",
    "sg:phone":"+32 3 605 10 04",
    "sg:postcode":"2950",
    "sg:province":"Antwerpen",
    "wof:name":"Fa. Van Regemortel",
    "wof:placetype":"venue"
},
  "geometry": {"coordinates":[4.450466156,51.3275604248],"type":"Point"}
}