{
  "type": "Feature",
  "properties": {
    "addr:full":"Consciencestraat 5 Antwerpen Antwerpen 2018",
    "addr:housenumber":"5",
    "addr:postcode":"2018",
    "addr:street":"Consciencestraat",
    "iso:country":"BE",
    "sg:address":"Consciencestraat 5",
    "sg:city":"Antwerpen",
    "sg:orig_category":"Produits interm\u00e9diaires Gr",
    "sg:phone":"+32 3 239 62 91",
    "sg:postcode":"2018",
    "sg:province":"Antwerpen",
    "wof:name":"Harry Gittler",
    "wof:placetype":"venue"
},
  "geometry": {"coordinates":[4.4183511734,51.2080841064],"type":"Point"}
}