{
  "type": "Feature",
  "properties": {
    "addr:full":"Rue Grande 36 Dinant Namur 5500",
    "addr:housenumber":"36",
    "addr:postcode":"5500",
    "addr:street":"Rue Grande",
    "iso:country":"BE",
    "sg:address":"Rue Grande 36",
    "sg:city":"Dinant",
    "sg:classifiers":[
        {
            "category":"Bakery",
            "type":"Food & Drink"
        }
    ],
    "sg:phone":"+32 82 22 30 80",
    "sg:postcode":"5500",
    "sg:province":"Namur",
    "sg:tags":[
        "confectioner",
        "baker"
    ],
    "wof:name":"Marchal M",
    "wof:placetype":"venue"
},
  "geometry": {"coordinates":[4.9149050713,50.2570991516],"type":"Point"}
}