{
  "type": "Feature",
  "properties": {
    "addr:full":"Zuidlaan 2 Zwalm Oost-Vlaanderen 9630",
    "addr:housenumber":"2",
    "addr:postcode":"9630",
    "addr:street":"Zuidlaan;Oost-Vlaanderen",
    "iso:country":"BE",
    "sg:address":"Zuidlaan 2",
    "sg:city":"Zwalm",
    "sg:orig_category":"Banques and organismes de cr\u00e9dit",
    "sg:phone":"+32 55 49 58 82",
    "sg:postcode":"9630",
    "sg:province":"Oost-Vlaanderen",
    "wof:name":"Groep Argenta",
    "wof:placetype":"venue"
},
  "geometry": {"coordinates":[3.7370500565,50.8601913452],"type":"Point"}
}