{
  "type": "Feature",
  "properties": {
    "addr:full":"Rue De L'hotellerie 26-28 Lessines Hainaut 7860",
    "addr:housenumber":"26-28",
    "addr:postcode":"7860",
    "addr:street":"Rue De L'Hotellerie;Hainaut",
    "iso:country":"BE",
    "sg:address":"Rue De L'hotellerie 26-28",
    "sg:city":"Lessines",
    "sg:classifiers":[
        {
            "category":"Military Area",
            "subcategory":"Air Force Base",
            "type":"Public Place"
        }
    ],
    "sg:phone":"+32 68 33 84 19",
    "sg:postcode":"7860",
    "sg:province":"Hainaut",
    "sg:tags":[
        "herb",
        "-",
        "medicinal"
    ],
    "wof:name":"Pharmacie Des Plantes",
    "wof:placetype":"venue"
},
  "geometry": {"coordinates":[3.8369259834,50.7107162476],"type":"Point"}
}