{
  "type": "Feature",
  "properties": {
    "addr:full":"Lostraat 91 Aalter Oost-Vlaanderen 9880",
    "addr:housenumber":"91",
    "addr:postcode":"9880",
    "addr:street":"Lostraat",
    "iso:country":"BE",
    "sg:address":"Lostraat 91",
    "sg:city":"Aalter",
    "sg:classifiers":[
        {
            "category":"Autos & Motor Vehicles",
            "subcategory":"Fuel & Gas Station",
            "type":"Retail Goods"
        }
    ],
    "sg:phone":"+32 9 375 21 62",
    "sg:postcode":"9880",
    "sg:province":"Oost-Vlaanderen",
    "wof:name":"Burmah",
    "wof:placetype":"venue"
},
  "geometry": {"coordinates":[3.4500589371,51.0781784058],"type":"Point"}
}