{
  "type": "Feature",
  "properties": {
    "iso:country":"BE",
    "sg:address":"Rue De Diekirch 62",
    "sg:city":"Arlon",
    "sg:classifiers":[
        {
            "category":"Professional",
            "subcategory":"Lawyer & Legal Services",
            "type":"Services"
        }
    ],
    "sg:phone":"+32 63 23 60 20",
    "sg:postcode":"6700",
    "sg:province":"Luxembourg",
    "wof:name":"Lefebvre Fabian",
    "wof:placetype":"venue"
},
  "geometry": {"coordinates":[5.8149991035,49.6861457825],"type":"Point"}
}