{
  "type": "Feature",
  "properties": {
    "addr:full":"Roelsstraat 9 Koksijde West-Vlaanderen 8670",
    "addr:housenumber":"9",
    "addr:postcode":"8670",
    "addr:street":"Roelsstraat",
    "iso:country":"BE",
    "sg:address":"Roelsstraat 9",
    "sg:city":"Koksijde",
    "sg:orig_category":"Pluimveekwekers Varkenskwekers",
    "sg:phone":"+32 58 51 11 75",
    "sg:postcode":"8670",
    "sg:province":"West-Vlaanderen",
    "wof:name":"Robert Derinck",
    "wof:placetype":"venue"
},
  "geometry": {"coordinates":[2.676265955,51.113445282],"type":"Point"}
}