{
  "type": "Feature",
  "properties": {
    "addr:full":"Lindenlaan 26 Beveren (beveren-waas) Oost-Vlaanderen 9120",
    "addr:housenumber":"26",
    "addr:postcode":"9120",
    "addr:street":"Lindenlaan;Oost-Vlaanderen",
    "iso:country":"BE",
    "sg:address":"Lindenlaan 26",
    "sg:city":"Beveren (beveren-waas)",
    "sg:classifiers":[
        {
            "category":"Manufacturing",
            "subcategory":"Wood Products",
            "type":"Manufacturing & Wholesale Goods"
        }
    ],
    "sg:phone":"+32 3 775 98 32",
    "sg:postcode":"9120",
    "sg:province":"Oost-Vlaanderen",
    "sg:tags":[
        "firewood"
    ],
    "wof:name":"Standaert J",
    "wof:placetype":"venue"
},
  "geometry": {"coordinates":[4.243461132,51.2161903381],"type":"Point"}
}