{
  "type": "Feature",
  "properties": {
    "iso:country":"BE",
    "sg:address":"Berkenhoflaan 23",
    "sg:city":"Leuven",
    "sg:classifiers":[
        {
            "category":"Personal",
            "subcategory":"Beauty Salon",
            "type":"Services"
        }
    ],
    "sg:phone":"+32 16 40 71 97",
    "sg:postcode":"3001",
    "sg:province":"Vlaams-Brabant",
    "sg:tags":[
        "de",
        "coiffure"
    ],
    "wof:name":"Claire Mertens",
    "wof:placetype":"venue"
},
  "geometry": {"coordinates":[4.6935482025,50.8563461304],"type":"Point"}
}