{
  "type": "Feature",
  "properties": {
    "iso:country":"BE",
    "sg:address":"Boulevard Maurice Lemonnier 50",
    "sg:city":"Brussel/bruxelles",
    "sg:orig_category":"Jeux and jouets",
    "sg:phone":"+32 2 512 74 18",
    "sg:postcode":"1000",
    "sg:province":"Bruxelles-Capitale",
    "wof:name":"Maison Point 50",
    "wof:placetype":"venue"
},
  "geometry": {"coordinates":[4.3451051712,50.8437614441],"type":"Point"}
}