{
  "type": "Feature",
  "properties": {
    "addr:full":"Rue Martimont 17 Leuze-en-hainaut Hainaut 7903",
    "addr:housenumber":"17",
    "addr:postcode":"7903",
    "addr:street":"Rue Martimont",
    "iso:country":"BE",
    "sg:address":"Rue Martimont 17",
    "sg:city":"Leuze-en-hainaut",
    "sg:orig_category":"Eleveurs de bovins",
    "sg:phone":"+32 69 67 10 79",
    "sg:postcode":"7903",
    "sg:province":"Hainaut",
    "wof:name":"Jacques Dumoulin",
    "wof:placetype":"venue"
},
  "geometry": {"coordinates":[3.6706740856,50.576915741],"type":"Point"}
}