{
  "type": "Feature",
  "properties": {
    "iso:country":"BE",
    "sg:address":"Nijverheidsstraat 2",
    "sg:city":"Pittem",
    "sg:orig_category":"Non-Classified Establishments",
    "sg:phone":"+32 51 46 67 78",
    "sg:postcode":"8740",
    "sg:province":"West-Vlaanderen",
    "wof:name":"Vandenhende J",
    "wof:placetype":"venue"
},
  "geometry": {"coordinates":[3.2535159588,50.9917221069],"type":"Point"}
}