{
  "type": "Feature",
  "properties": {
    "addr:full":"Rue Joseph Cuylits 1 Ukkel/uccle Bruxelles-Capitale 1180",
    "addr:housenumber":"1",
    "addr:postcode":"1180",
    "addr:street":"Rue Joseph Cuylits;/",
    "iso:country":"BE",
    "sg:address":"Rue Joseph Cuylits 1",
    "sg:city":"Ukkel/uccle",
    "sg:orig_category":"Maisons de repos and r\u00e9sidences",
    "sg:phone":"+32 2 347 00 01",
    "sg:postcode":"1180",
    "sg:province":"Bruxelles-Capitale",
    "wof:name":"Maison Sagittaire",
    "wof:placetype":"venue"
},
  "geometry": {"coordinates":[4.3532590866,50.8139266968],"type":"Point"}
}