{
  "type": "Feature",
  "properties": {
    "addr:full":"Route De Philippeville 360 Charleroi (couillet) Hainaut 6010",
    "addr:housenumber":"360",
    "addr:postcode":"6010",
    "addr:street":"Route De Philippeville",
    "iso:country":"BE",
    "sg:address":"Route De Philippeville 360",
    "sg:city":"Charleroi (couillet)",
    "sg:classifiers":[
        {
            "category":"Communications",
            "subcategory":"Film & Video Production",
            "type":"Services"
        }
    ],
    "sg:phone":"+32 71 47 15 37",
    "sg:postcode":"6010",
    "sg:province":"Hainaut",
    "sg:tags":[
        "realisation",
        "-"
    ],
    "wof:name":"Polymedia Films",
    "wof:placetype":"venue"
},
  "geometry": {"coordinates":[4.4652209282,50.3822517395],"type":"Point"}
}