{
  "type": "Feature",
  "properties": {
    "addr:full":"Fabriekstraat 65b1 Sint-pieters-leeuw Vlaams-Brabant 1601",
    "addr:housenumber":"65b1",
    "addr:postcode":"1601",
    "addr:street":"Fabriekstraat",
    "iso:country":"BE",
    "sg:address":"Fabriekstraat 65b1",
    "sg:city":"Sint-pieters-leeuw",
    "sg:orig_category":"Brood, gebak and snoepgoed",
    "sg:phone":"+32 2 377 21 60",
    "sg:postcode":"1601",
    "sg:province":"Vlaams-Brabant",
    "wof:name":"Bakkerij Van Ruisbroek",
    "wof:placetype":"venue"
},
  "geometry": {"coordinates":[4.2929410934,50.7839851379],"type":"Point"}
}