{
  "type": "Feature",
  "properties": {
    "iso:country":"BE",
    "sg:address":"Kasteelstraat 55",
    "sg:city":"Tielt",
    "sg:orig_category":"V\u00eatements",
    "sg:phone":"+32 51 40 03 97",
    "sg:postcode":"8700",
    "sg:province":"West-Vlaanderen",
    "wof:name":"Georges Nemegheer",
    "wof:placetype":"venue"
},
  "geometry": {"coordinates":[3.3239290714,50.9927749634],"type":"Point"}
}