{
  "type": "Feature",
  "properties": {
    "addr:full":"Avenue Paul Pastur 96 Charleroi (mont-sur-marchienne) Hainaut 6032",
    "addr:housenumber":"96",
    "addr:postcode":"6032",
    "addr:street":"Avenue Paul Pastur",
    "iso:country":"BE",
    "sg:address":"Avenue Paul Pastur 96",
    "sg:city":"Charleroi (mont-sur-marchienne)",
    "sg:classifiers":[
        {
            "category":"Shopping",
            "subcategory":"Florist",
            "type":"Retail Goods"
        }
    ],
    "sg:phone":"+32 71 36 38 75",
    "sg:postcode":"6032",
    "sg:province":"Hainaut",
    "wof:name":"Chlorophylle",
    "wof:placetype":"venue"
},
  "geometry": {"coordinates":[4.4082589149,50.3907775879],"type":"Point"}
}