{
  "type": "Feature",
  "properties": {
    "addr:full":"Domaine Vincent Van Gogh 1b Boussu (hornu) Hainaut 7301",
    "addr:housenumber":"1b",
    "addr:postcode":"7301",
    "iso:country":"BE",
    "sg:address":"Domaine Vincent Van Gogh 1b",
    "sg:city":"Boussu (hornu)",
    "sg:classifiers":[
        {
            "category":"Health Services",
            "subcategory":"Dentist",
            "type":"Services"
        }
    ],
    "sg:phone":"+32 65 76 40 90",
    "sg:postcode":"7301",
    "sg:province":"Hainaut",
    "wof:name":"Tavcar A",
    "wof:placetype":"venue"
},
  "geometry": {"coordinates":[3.8276529312,50.4240646362],"type":"Point"}
}