{
  "type": "Feature",
  "properties": {
    "iso:country":"BE",
    "sg:address":"R. De La Basse Charlotte 44",
    "sg:city":"Jodoigne",
    "sg:orig_category":"Eleveurs and marchands de porcs",
    "sg:phone":"+32 10 81 07 37",
    "sg:postcode":"1370",
    "sg:province":"Brabant Wallon",
    "wof:name":"Noel Haumont",
    "wof:placetype":"venue"
},
  "geometry": {"coordinates":[4.8441672325,50.7089080811],"type":"Point"}
}