{
  "type": "Feature",
  "properties": {
    "addr:full":"Vredestraat 6 Beerse Antwerpen 2340",
    "addr:housenumber":"6",
    "addr:postcode":"2340",
    "addr:street":"Vredestraat",
    "iso:country":"BE",
    "sg:address":"Vredestraat 6",
    "sg:city":"Beerse",
    "sg:classifiers":[
        {
            "category":"Freight",
            "type":"Transportation"
        }
    ],
    "sg:phone":"+32 14 62 04 99",
    "sg:postcode":"2340",
    "sg:province":"Antwerpen",
    "sg:tags":[
        "-",
        "transport"
    ],
    "wof:name":"Transport Van Gorp Bvba",
    "wof:placetype":"venue"
},
  "geometry": {"coordinates":[4.8565039635,51.3196792603],"type":"Point"}
}