{
  "type": "Feature",
  "properties": {
    "addr:full":"Denderstraat 5-7 Aalst (erembodegem) Oost-Vlaanderen 9320",
    "addr:housenumber":"5-7",
    "addr:postcode":"9320",
    "addr:street":"Denderstraat",
    "iso:country":"BE",
    "sg:address":"Denderstraat 5-7",
    "sg:city":"Aalst (erembodegem)",
    "sg:orig_category":"Non-Classified Establishments",
    "sg:phone":"+32 53 21 64 41",
    "sg:postcode":"9320",
    "sg:province":"Oost-Vlaanderen",
    "wof:name":"Van Impe L",
    "wof:placetype":"venue"
},
  "geometry": {"coordinates":[4.0354800224,50.9426879883],"type":"Point"}
}