{
  "type": "Feature",
  "properties": {
    "iso:country":"BE",
    "sg:address":"Dries 29",
    "sg:city":"Bruxelles (watermael-boitsfort)",
    "sg:classifiers":[
        {
            "category":"Professional",
            "subcategory":"Management & Consulting",
            "type":"Services"
        }
    ],
    "sg:phone":"+32 2 736 25 41",
    "sg:postcode":"1170",
    "sg:province":"Bruxelles-Capitale",
    "sg:tags":[
        "consultant",
        "agency",
        "advertising"
    ],
    "wof:name":"Comm'back",
    "wof:placetype":"venue"
},
  "geometry": {"coordinates":[4.3983411789,50.8024177551],"type":"Point"}
}