{
  "type": "Feature",
  "properties": {
    "addr:full":"Tremelobaan 75 Keerbergen Vlaams-Brabant 3140",
    "addr:housenumber":"75",
    "addr:postcode":"3140",
    "addr:street":"Tremelobaan",
    "iso:country":"BE",
    "sg:address":"Tremelobaan 75",
    "sg:city":"Keerbergen",
    "sg:orig_category":"M\u00e9decins and sp\u00e9cialistes",
    "sg:phone":"+32 15 52 71 22",
    "sg:postcode":"3140",
    "sg:province":"Vlaams-Brabant",
    "wof:name":"Dirk Withofs",
    "wof:placetype":"venue"
},
  "geometry": {"coordinates":[4.6462230682,51.0013504028],"type":"Point"}
}