{
  "type": "Feature",
  "properties": {
    "addr:full":"Hof-ten-berglaan 98 Puurs Antwerpen 2870",
    "addr:housenumber":"98",
    "addr:postcode":"2870",
    "addr:street":"Hof-Ten-Berglaan",
    "iso:country":"BE",
    "sg:address":"Hof-ten-berglaan 98",
    "sg:city":"Puurs",
    "sg:orig_category":"Quincailleries. Plomberie, chauffage and installations sanitaires",
    "sg:phone":"+32 3 889 31 42",
    "sg:postcode":"2870",
    "sg:province":"Antwerpen",
    "wof:name":"Peeters",
    "wof:placetype":"venue"
},
  "geometry": {"coordinates":[4.2789292336,51.0702400208],"type":"Point"}
}