{
  "type": "Feature",
  "properties": {
    "addr:full":"Grote Markt 3 Boom Antwerpen 2850",
    "addr:housenumber":"3",
    "addr:postcode":"2850",
    "addr:street":"Grote Markt",
    "iso:country":"BE",
    "sg:address":"Grote Markt 3",
    "sg:city":"Boom",
    "sg:classifiers":[
        {
            "category":"Personal",
            "subcategory":"Beauty Salon",
            "type":"Services"
        }
    ],
    "sg:phone":"+32 3 888 76 29",
    "sg:postcode":"2850",
    "sg:province":"Antwerpen",
    "sg:tags":[
        "lady",
        "-",
        "hairdressing"
    ],
    "wof:name":"Fiorella",
    "wof:placetype":"venue"
},
  "geometry": {"coordinates":[4.3637290001,51.0859146118],"type":"Point"}
}