{
  "type": "Feature",
  "properties": {
    "addr:full":"Doorniksesteenweg 97 Kortrijk West-Vlaanderen 8500",
    "addr:housenumber":"97",
    "addr:postcode":"8500",
    "addr:street":"Doorniksesteenweg",
    "iso:country":"BE",
    "sg:address":"Doorniksesteenweg 97",
    "sg:city":"Kortrijk",
    "sg:classifiers":[
        {
            "category":"Bars & Pubs",
            "type":"Food & Drink"
        }
    ],
    "sg:phone":"+32 56 32 76 25",
    "sg:postcode":"8500",
    "sg:province":"West-Vlaanderen",
    "wof:name":"Belle's Place",
    "wof:placetype":"venue"
},
  "geometry": {"coordinates":[3.2789199352,50.8087387085],"type":"Point"}
}