{
  "type": "Feature",
  "properties": {
    "addr:full":"Kalmthoutsesteenweg 206 Essen Antwerpen 2910",
    "addr:housenumber":"206",
    "addr:postcode":"2910",
    "addr:street":"Kalmthoutsesteenweg",
    "iso:country":"BE",
    "sg:address":"Kalmthoutsesteenweg 206",
    "sg:city":"Essen",
    "sg:classifiers":[
        {
            "category":"Parking",
            "subcategory":"Lot",
            "type":"Transportation"
        }
    ],
    "sg:phone":"+32 3 667 39 84",
    "sg:postcode":"2910",
    "sg:province":"Antwerpen",
    "sg:tags":[
        "parking-places",
        "laying-out"
    ],
    "wof:name":"Van Dorst M",
    "wof:placetype":"venue"
},
  "geometry": {"coordinates":[4.4637298584,51.4214286804],"type":"Point"}
}