{
  "type": "Feature",
  "properties": {
    "addr:full":"Markt 6ba4 Moerbeke Oost-Vlaanderen 9180",
    "addr:postcode":"9180",
    "addr:street":"Markt;Oost-Vlaanderen",
    "iso:country":"BE",
    "sg:address":"Markt 6ba4",
    "sg:city":"Moerbeke",
    "sg:classifiers":[
        {
            "category":"Manufacturing",
            "subcategory":"Textiles",
            "type":"Manufacturing & Wholesale Goods"
        }
    ],
    "sg:phone":"+32 9 346 73 93",
    "sg:postcode":"9180",
    "sg:province":"Oost-Vlaanderen",
    "wof:name":"Kreatief Breimode",
    "wof:placetype":"venue"
},
  "geometry": {"coordinates":[3.9420149326,51.1741905212],"type":"Point"}
}