{
  "type": "Feature",
  "properties": {
    "addr:full":"Alsembergsesteenweg 100 Halle Vlaams-Brabant 1501",
    "addr:housenumber":"100",
    "addr:postcode":"1501",
    "addr:street":"Alsembergsesteenweg",
    "iso:country":"BE",
    "sg:address":"Alsembergsesteenweg 100",
    "sg:city":"Halle",
    "sg:orig_category":"S\u00e9curit\u00e9 sociale",
    "sg:phone":"+32 2 361 44 81",
    "sg:postcode":"1501",
    "sg:province":"Vlaams-Brabant",
    "wof:name":"Socialist. Mutualiteit",
    "wof:placetype":"venue"
},
  "geometry": {"coordinates":[4.2657089233,50.7466468811],"type":"Point"}
}