{
  "type": "Feature",
  "properties": {
    "iso:country":"BE",
    "sg:address":"Pastoriedreef 4",
    "sg:city":"Alveringem",
    "sg:orig_category":"Eleveurs de bovins",
    "sg:phone":"+32 58 29 94 84",
    "sg:postcode":"8691",
    "sg:province":"West-Vlaanderen",
    "wof:name":"Roger Becelaere",
    "wof:placetype":"venue"
},
  "geometry": {"coordinates":[2.6590459347,50.9935073853],"type":"Point"}
}