{
  "type": "Feature",
  "properties": {
    "addr:full":"Heuvelstraat 32 Hemiksem Antwerpen 2620",
    "addr:housenumber":"32",
    "addr:postcode":"2620",
    "addr:street":"Heuvelstraat",
    "iso:country":"BE",
    "sg:address":"Heuvelstraat 32",
    "sg:city":"Hemiksem",
    "sg:orig_category":"Banques and organismes de cr\u00e9dit",
    "sg:phone":"+32 3 887 42 93",
    "sg:postcode":"2620",
    "sg:province":"Antwerpen",
    "wof:name":"Fortis",
    "wof:placetype":"venue"
},
  "geometry": {"coordinates":[4.3375082016,51.1405715942],"type":"Point"}
}