{
  "type": "Feature",
  "properties": {
    "addr:full":"Rue De L'homme Chr\u00e9tien 2 Bruxelles Bruxelles-Capitale 1000",
    "addr:housenumber":"2",
    "addr:postcode":"1000",
    "addr:street":"Rue De L'Homme Chre\u0301Tien",
    "iso:country":"BE",
    "sg:address":"Rue De L'homme Chr\u00e9tien 2",
    "sg:city":"Bruxelles",
    "sg:classifiers":[
        {
            "category":"Travel",
            "subcategory":"Hotels & Motels",
            "type":"Entertainment"
        }
    ],
    "sg:phone":"+32 2 505 55 55",
    "sg:postcode":"1000",
    "sg:province":"Bruxelles-Capitale",
    "sg:tags":[
        "hotels",
        "business",
        "restaurant"
    ],
    "wof:name":"Restaurant Les 4 Saisons( Hotel Royal Windsor)",
    "wof:placetype":"venue"
},
  "geometry": {"coordinates":[4.3539261818,50.8452949524],"type":"Point"}
}