{
  "type": "Feature",
  "properties": {
    "iso:country":"BE",
    "sg:address":"Groene-herderstraat 50",
    "sg:city":"Roeselare",
    "sg:orig_category":"Boucheries",
    "sg:phone":"+32 51 20 23 07",
    "sg:postcode":"8800",
    "sg:province":"West-Vlaanderen",
    "wof:name":"Stefaan Decoussemaeker",
    "wof:placetype":"venue"
},
  "geometry": {"coordinates":[3.1407968998,50.9330101013],"type":"Point"}
}