{
  "type": "Feature",
  "properties": {
    "iso:country":"BE",
    "sg:address":"Kortrijkstraat 138",
    "sg:city":"Tielt",
    "sg:orig_category":"Dameskledingzaken Lingerie and ondergoed",
    "sg:phone":"+32 51 40 04 52",
    "sg:postcode":"8700",
    "sg:province":"West-Vlaanderen",
    "wof:name":"Segaert Foundations",
    "wof:placetype":"venue"
},
  "geometry": {"coordinates":[3.3258099556,50.995010376],"type":"Point"}
}