{
  "type": "Feature",
  "properties": {
    "addr:full":"Grondwetlaan 30 Gent Oost-Vlaanderen 9040",
    "addr:housenumber":"30",
    "addr:postcode":"9040",
    "addr:street":"Grondwetlaan;Oost-Vlaanderen",
    "iso:country":"BE",
    "sg:address":"Grondwetlaan 30",
    "sg:city":"Gent",
    "sg:orig_category":"Plomberie, chauffage and installations sanitaires",
    "sg:phone":"+32 9 251 50 58",
    "sg:postcode":"9040",
    "sg:province":"Oost-Vlaanderen",
    "wof:name":"Ronny De Smedt",
    "wof:placetype":"venue"
},
  "geometry": {"coordinates":[3.7523570061,51.0667381287],"type":"Point"}
}