{
  "type": "Feature",
  "properties": {
    "addr:full":"Barnumstraat 17 Meulebeke West-Vlaanderen 8760",
    "addr:housenumber":"17",
    "addr:postcode":"8760",
    "addr:street":"Barnumstraat",
    "iso:country":"BE",
    "sg:address":"Barnumstraat 17",
    "sg:city":"Meulebeke",
    "sg:classifiers":[
        {
            "category":"Building & Trades",
            "subcategory":"Pest Control",
            "type":"Services"
        }
    ],
    "sg:phone":"+32 51 48 84 69",
    "sg:postcode":"8760",
    "sg:province":"West-Vlaanderen",
    "sg:tags":[
        "painting",
        "contractor"
    ],
    "wof:name":"Vanglabeke Bvba",
    "wof:placetype":"venue"
},
  "geometry": {"coordinates":[3.2906830311,50.9463272095],"type":"Point"}
}