{
  "type": "Feature",
  "properties": {
    "addr:full":"Leeuwerikenlaan 1 Malle (oostmalle) Antwerpen 2390",
    "addr:housenumber":"1",
    "addr:postcode":"2390",
    "addr:street":"Leeuwerikenlaan",
    "iso:country":"BE",
    "sg:address":"Leeuwerikenlaan 1",
    "sg:city":"Malle (oostmalle)",
    "sg:classifiers":[
        {
            "category":"Professional",
            "type":"Services"
        }
    ],
    "sg:phone":"+32 3 312 01 68",
    "sg:postcode":"2390",
    "sg:province":"Antwerpen",
    "sg:tags":[
        "surveyor",
        "-",
        "valuer"
    ],
    "wof:name":"Assurex Nv",
    "wof:placetype":"venue"
},
  "geometry": {"coordinates":[4.7239289284,51.2856483459],"type":"Point"}
}