{
  "type": "Feature",
  "properties": {
    "iso:country":"BE",
    "sg:address":"Delften 23",
    "sg:city":"Malle (westmalle)",
    "sg:classifiers":[
        {
            "category":"Professional",
            "subcategory":"Management & Consulting",
            "type":"Services"
        }
    ],
    "sg:phone":"+32 3 309 25 50",
    "sg:postcode":"2390",
    "sg:province":"Antwerpen",
    "sg:tags":[
        "consultant",
        "promotion",
        "-",
        "sale"
    ],
    "wof:name":"B.o.s. Merchandising Bvba",
    "wof:placetype":"venue"
},
  "geometry": {"coordinates":[4.7112011909,51.2873764038],"type":"Point"}
}