{
  "type": "Feature",
  "properties": {
    "addr:full":"Kleine Molenstraat 5 Menen West-Vlaanderen 8930",
    "addr:housenumber":"5",
    "addr:postcode":"8930",
    "addr:street":"Kleine Molenstraat",
    "iso:country":"BE",
    "sg:address":"Kleine Molenstraat 5",
    "sg:city":"Menen",
    "sg:orig_category":"Studios photographiques",
    "sg:phone":"+32 56 40 15 13",
    "sg:postcode":"8930",
    "sg:province":"West-Vlaanderen",
    "wof:name":"Magda Christiaens",
    "wof:placetype":"venue"
},
  "geometry": {"coordinates":[3.1969549656,50.7806282043],"type":"Point"}
}