{
  "type": "Feature",
  "properties": {
    "addr:full":"Kortrijksesteenweg 725 Gent Oost-Vlaanderen 9000",
    "addr:housenumber":"725",
    "addr:postcode":"9000",
    "addr:street":"Kortrijksesteenweg;Oost-Vlaanderen",
    "iso:country":"BE",
    "sg:address":"Kortrijksesteenweg 725",
    "sg:city":"Gent",
    "sg:classifiers":[
        {
            "category":"Professional",
            "subcategory":"Lawyer & Legal Services",
            "type":"Services"
        }
    ],
    "sg:phone":"+32 9 221 28 86",
    "sg:postcode":"9000",
    "sg:province":"Oost-Vlaanderen",
    "wof:name":"De Bock F",
    "wof:placetype":"venue"
},
  "geometry": {"coordinates":[3.7122650146,51.0291252136],"type":"Point"}
}