{
  "type": "Feature",
  "properties": {
    "addr:full":"Mgr. Ladeuzeplein 27 Leuven Vlaams-Brabant 3000",
    "addr:housenumber":"27",
    "addr:postcode":"3000",
    "addr:street":"Mgr. Ladeuzeplein",
    "iso:country":"BE",
    "sg:address":"Mgr. Ladeuzeplein 27",
    "sg:city":"Leuven",
    "sg:orig_category":"M\u00e9decins and sp\u00e9cialistes",
    "sg:phone":"+32 16 22 12 99",
    "sg:postcode":"3000",
    "sg:province":"Vlaams-Brabant",
    "wof:name":"A. Geys",
    "wof:placetype":"venue"
},
  "geometry": {"coordinates":[4.7059412003,50.8781089783],"type":"Point"}
}