{
  "type": "Feature",
  "properties": {
    "addr:full":"Rue De Li\u00c8ge 10bb Andenne Namur 5300",
    "addr:housenumber":"10bb",
    "addr:postcode":"5300",
    "addr:street":"Rue De Lie\u0300Ge",
    "iso:country":"BE",
    "sg:address":"Rue De Li\u00c8ge 10bb",
    "sg:city":"Andenne",
    "sg:classifiers":[
        {
            "category":"Arena",
            "subcategory":"Sports Club",
            "type":"Entertainment"
        }
    ],
    "sg:phone":"+32 81 58 15 55",
    "sg:postcode":"5300",
    "sg:province":"Namur",
    "sg:tags":[
        "terrain",
        "hors",
        "de",
        "installation",
        "sportifs"
    ],
    "wof:name":"S.c. La Stella Groynnoise",
    "wof:placetype":"venue"
},
  "geometry": {"coordinates":[5.0982642174,50.4863739014],"type":"Point"}
}