{
  "type": "Feature",
  "properties": {
    "addr:full":"Rue Marie-christine 220 Bruxelles Bruxelles-Capitale 1020",
    "addr:housenumber":"220",
    "addr:postcode":"1020",
    "addr:street":"Rue Marie-Christine",
    "iso:country":"BE",
    "sg:address":"Rue Marie-christine 220",
    "sg:city":"Bruxelles",
    "sg:orig_category":"Cafetarias and selfservice restaurants",
    "sg:phone":"+32 2 420 34 61",
    "sg:postcode":"1020",
    "sg:province":"Bruxelles-Capitale",
    "wof:name":"Samoka",
    "wof:placetype":"venue"
},
  "geometry": {"coordinates":[4.3490557671,50.8768005371],"type":"Point"}
}