{
  "type": "Feature",
  "properties": {
    "iso:country":"BE",
    "sg:address":"Koekoekstraat 11ba",
    "sg:city":"Waregem",
    "sg:orig_category":"Banken and kredietinstellingen",
    "sg:phone":"+32 56 60 40 99",
    "sg:postcode":"8793",
    "sg:province":"West-Vlaanderen",
    "wof:name":"Bacob",
    "wof:placetype":"venue"
},
  "geometry": {"coordinates":[3.4043290615,50.9050941467],"type":"Point"}
}