{
  "type": "Feature",
  "properties": {
    "addr:full":"Luitenant Dobbelaerestraat 28 Zomergem Oost-Vlaanderen 9930",
    "addr:housenumber":"28",
    "addr:postcode":"9930",
    "addr:street":"Luitenant Dobbelaerestraat",
    "iso:country":"BE",
    "sg:address":"Luitenant Dobbelaerestraat 28",
    "sg:city":"Zomergem",
    "sg:classifiers":[
        {
            "category":"Building & Trades",
            "subcategory":"Construction",
            "type":"Services"
        }
    ],
    "sg:phone":"+32 476 95 64 91",
    "sg:postcode":"9930",
    "sg:province":"Oost-Vlaanderen",
    "sg:tags":[
        "stucco",
        "contractor"
    ],
    "wof:name":"Den Tyn",
    "wof:placetype":"venue"
},
  "geometry": {"coordinates":[3.5595090389,51.1208381653],"type":"Point"}
}