{
  "type": "Feature",
  "properties": {
    "iso:country":"BE",
    "sg:address":"Lappersfortstraat 16",
    "sg:city":"Brugge",
    "sg:orig_category":"Sportclubs",
    "sg:phone":"+32 50 35 99 13",
    "sg:postcode":"8310",
    "sg:province":"West-Vlaanderen",
    "wof:name":"The Cobra Brugge",
    "wof:placetype":"venue"
},
  "geometry": {"coordinates":[3.2308559418,51.1940078735],"type":"Point"}
}