{
  "type": "Feature",
  "properties": {
    "addr:full":"Baarbeek 1 Zwijndrecht Antwerpen 2070",
    "addr:housenumber":"1",
    "addr:postcode":"2070",
    "addr:street":"Baarbeek",
    "iso:country":"BE",
    "sg:address":"Baarbeek 1",
    "sg:city":"Zwijndrecht",
    "sg:classifiers":[
        {
            "category":"Professional",
            "subcategory":"Engineering",
            "type":"Services"
        }
    ],
    "sg:phone":"+32 3 641 12 12",
    "sg:postcode":"2070",
    "sg:province":"Antwerpen",
    "sg:tags":[
        "-"
    ],
    "wof:name":"Egemin Consulting Nv",
    "wof:placetype":"venue"
},
  "geometry": {"coordinates":[4.326734066,51.2184944153],"type":"Point"}
}