{
  "type": "Feature",
  "properties": {
    "addr:full":"Chauss\u00c9e De Namur 412 Eghezee Namur 5310",
    "addr:housenumber":"412",
    "addr:postcode":"5310",
    "addr:street":"Chausse\u0301E De Namur;Namur",
    "iso:country":"BE",
    "sg:address":"Chauss\u00c9e De Namur 412",
    "sg:city":"Eghezee",
    "sg:orig_category":"Brood, gebak and snoepgoed",
    "sg:phone":"+32 81 51 11 66",
    "sg:postcode":"5310",
    "sg:province":"Namur",
    "wof:name":"Michel Gerard",
    "wof:placetype":"venue"
},
  "geometry": {"coordinates":[4.9116740227,50.5860519409],"type":"Point"}
}