{
  "type": "Feature",
  "properties": {
    "iso:country":"BE",
    "sg:address":"Frederik Burvenichstraat 216",
    "sg:city":"Gent (gentbrugge)",
    "sg:classifiers":[
        {
            "category":"Food & Beverages",
            "subcategory":"Supermarket",
            "type":"Retail Goods"
        }
    ],
    "sg:phone":"+32 9 231 01 65",
    "sg:postcode":"9050",
    "sg:province":"Oost-Vlaanderen",
    "sg:tags":[
        "department",
        "store"
    ],
    "wof:name":"Gb-super Partner",
    "wof:placetype":"venue"
},
  "geometry": {"coordinates":[3.7572700977,51.0404281616],"type":"Point"}
}