{
  "type": "Feature",
  "properties": {
    "iso:country":"BE",
    "sg:address":"Karel Soetelaan 99",
    "sg:city":"Borsbeek",
    "sg:orig_category":"Elektrische installaties voor woningen",
    "sg:phone":"+32 3 366 23 96",
    "sg:postcode":"2150",
    "sg:province":"Antwerpen",
    "wof:name":"Erwin De Maesschalck",
    "wof:placetype":"venue"
},
  "geometry": {"coordinates":[4.4793829918,51.2021827698],"type":"Point"}
}