{
  "type": "Feature",
  "properties": {
    "iso:country":"BE",
    "sg:address":"Boterweegschaalstraat 13",
    "sg:city":"Veurne",
    "sg:classifiers":[
        {
            "category":"Personal",
            "subcategory":"Beauty Salon",
            "type":"Services"
        }
    ],
    "sg:phone":"+32 58 31 16 45",
    "sg:postcode":"8630",
    "sg:province":"West-Vlaanderen",
    "sg:tags":[
        "de",
        "coiffure"
    ],
    "wof:name":"Hugo Bouttry",
    "wof:placetype":"venue"
},
  "geometry": {"coordinates":[2.6635549068,51.0713729858],"type":"Point"}
}