{
  "type": "Feature",
  "properties": {
    "iso:country":"BE",
    "sg:address":"Plaats 17",
    "sg:city":"Moorslede",
    "sg:classifiers":[
        {
            "category":"Insurance",
            "subcategory":"Insurance Agent",
            "type":"Services"
        }
    ],
    "sg:phone":"+32 56 50 15 70",
    "sg:postcode":"8890",
    "sg:province":"West-Vlaanderen",
    "sg:tags":[
        "verzekeringsmakelaars",
        "expert"
    ],
    "wof:name":"Zakenkantoor Minne",
    "wof:placetype":"venue"
},
  "geometry": {"coordinates":[3.094630003,50.8516273499],"type":"Point"}
}