{
  "type": "Feature",
  "properties": {
    "iso:country":"BE",
    "sg:address":"Waregemstraat 441",
    "sg:city":"Deerlijk",
    "sg:orig_category":"Benzinestations and brandstoffen Herstellingen and onderhoud van auto's Voertuigen",
    "sg:phone":"+32 56 70 50 49",
    "sg:postcode":"8540",
    "sg:province":"West-Vlaanderen",
    "wof:name":"Garage Dessein",
    "wof:placetype":"venue"
},
  "geometry": {"coordinates":[3.3780748844,50.8597946167],"type":"Point"}
}