{
  "type": "Feature",
  "properties": {
    "iso:country":"BE",
    "sg:address":"Klipperstr 15",
    "sg:city":"Antwerpen",
    "sg:classifiers":[
        {
            "category":"Banks & Credit Unions",
            "subcategory":"Investment Brokerage",
            "type":"Services"
        }
    ],
    "sg:phone":"+32 3 545 35 11",
    "sg:postcode":"2030",
    "sg:province":"Antwerpen",
    "sg:tags":[
        "-",
        "transport",
        "related"
    ],
    "wof:name":"Acsa 92 Nv",
    "wof:placetype":"venue"
},
  "geometry": {"coordinates":[4.4244451523,51.2439994812],"type":"Point"}
}