{
  "type": "Feature",
  "properties": {
    "addr:full":"Janssen-pharmaceuticalaan 3a Geel Antwerpen 2440",
    "addr:housenumber":"3a",
    "addr:postcode":"2440",
    "addr:street":"Janssen-Pharmaceuticalaan",
    "iso:country":"BE",
    "sg:address":"Janssen-pharmaceuticalaan 3a",
    "sg:city":"Geel",
    "sg:classifiers":[
        {
            "category":"Manufacturing",
            "subcategory":"Chemicals & Compounds",
            "type":"Manufacturing & Wholesale Goods"
        }
    ],
    "sg:phone":"+32 52 47 05 36",
    "sg:postcode":"2440",
    "sg:province":"Antwerpen",
    "sg:tags":[
        "biochemicals"
    ],
    "wof:name":"Blue Star Chemicals Nv",
    "wof:placetype":"venue"
},
  "geometry": {"coordinates":[4.1338410378,51.0740356445],"type":"Point"}
}