{
  "type": "Feature",
  "properties": {
    "iso:country":"BE",
    "sg:address":"Maarschalk Frenchlaan 26",
    "sg:city":"Ieper",
    "sg:classifiers":[
        {
            "category":"Building & Trades",
            "subcategory":"Construction",
            "type":"Services"
        }
    ],
    "sg:phone":"+32 57 20 32 58",
    "sg:postcode":"8900",
    "sg:province":"West-Vlaanderen",
    "sg:tags":[
        "carpenter"
    ],
    "wof:name":"Dewagter M",
    "wof:placetype":"venue"
},
  "geometry": {"coordinates":[2.8936769962,50.8526725769],"type":"Point"}
}