{
  "type": "Feature",
  "properties": {
    "iso:country":"BE",
    "sg:address":"Bosstraat 150",
    "sg:city":"Buggenhout",
    "sg:classifiers":[
        {
            "category":"Restaurant",
            "type":"Food & Drink"
        }
    ],
    "sg:phone":"+32 52 34 55 22",
    "sg:postcode":"9255",
    "sg:province":"Oost-Vlaanderen",
    "wof:name":"Eikenhof",
    "wof:placetype":"venue"
},
  "geometry": {"coordinates":[4.2210040092,51.0078887939],"type":"Point"}
}