{
  "type": "Feature",
  "properties": {
    "iso:country":"BE",
    "sg:address":"Avenue D'auderghem 77",
    "sg:city":"Bruxelles (etterbeek)",
    "sg:classifiers":[
        {
            "category":"Education",
            "subcategory":"University",
            "type":"Public Place"
        }
    ],
    "sg:phone":"+32 2 231 01 00",
    "sg:postcode":"1040",
    "sg:province":"Bruxelles-Capitale",
    "sg:tags":[
        "higher"
    ],
    "wof:name":"Ecsedi-isalt",
    "wof:placetype":"venue"
},
  "geometry": {"coordinates":[4.386220932,50.8376426697],"type":"Point"}
}