{
  "type": "Feature",
  "properties": {
    "iso:country":"BE",
    "sg:address":"Velle 2ba",
    "sg:city":"Temse",
    "sg:orig_category":"Baby- and kinderkleding",
    "sg:phone":"+32 3 710 11 94",
    "sg:postcode":"9140",
    "sg:province":"Oost-Vlaanderen",
    "wof:name":"\u00b4t Magazijntje",
    "wof:placetype":"venue"
},
  "geometry": {"coordinates":[4.2016911507,51.1552352905],"type":"Point"}
}