{
  "type": "Feature",
  "properties": {
    "addr:full":"Zemstbaan 53 Mechelen Antwerpen 2800",
    "addr:housenumber":"53",
    "addr:postcode":"2800",
    "addr:street":"Zemstbaan",
    "iso:country":"BE",
    "sg:address":"Zemstbaan 53",
    "sg:city":"Mechelen",
    "sg:orig_category":"Magasins sp\u00e9cialis\u00e9s",
    "sg:phone":"+32 15 42 32 35",
    "sg:postcode":"2800",
    "sg:province":"Antwerpen",
    "wof:name":"Walraevens Ben",
    "wof:placetype":"venue"
},
  "geometry": {"coordinates":[4.472304821,51.0026397705],"type":"Point"}
}