{
  "type": "Feature",
  "properties": {
    "iso:country":"BE",
    "sg:address":"Drie Lindekens 84",
    "sg:city":"Beveren",
    "sg:orig_category":"Schoonheidssalons",
    "sg:phone":"+32 3 755 05 97",
    "sg:postcode":"9120",
    "sg:province":"Oost-Vlaanderen",
    "wof:name":"Krista De Paep",
    "wof:placetype":"venue"
},
  "geometry": {"coordinates":[4.2425889969,51.2186012268],"type":"Point"}
}