{
  "type": "Feature",
  "properties": {
    "addr:full":"Heirbaan 67-69 Sint-gillis-bij-dendermonde Oost-Vlaanderen 9200",
    "addr:housenumber":"67-69",
    "addr:postcode":"9200",
    "addr:street":"Heirbaan;Oost-Vlaanderen",
    "iso:country":"BE",
    "sg:address":"Heirbaan 67-69",
    "sg:city":"Sint-gillis-bij-dendermonde",
    "sg:orig_category":"Motorfietsen",
    "sg:phone":"+32 52 20 19 36",
    "sg:postcode":"9200",
    "sg:province":"Oost-Vlaanderen",
    "wof:name":"Heirbout-van Dijck",
    "wof:placetype":"venue"
},
  "geometry": {"coordinates":[4.1143832207,51.0153884888],"type":"Point"}
}