{
  "type": "Feature",
  "properties": {
    "addr:full":"Colonel Silvertopstraat 15 Boom Antwerpen 2850",
    "addr:housenumber":"15",
    "addr:postcode":"2850",
    "addr:street":"Silvertopstraat",
    "iso:country":"BE",
    "sg:address":"Colonel Silvertopstraat 15",
    "sg:city":"Boom",
    "sg:classifiers":[
        {
            "category":"Professional",
            "subcategory":"Employment Agencies",
            "type":"Services"
        }
    ],
    "sg:phone":"+32 3 880 58 25",
    "sg:postcode":"2850",
    "sg:province":"Antwerpen",
    "wof:name":"Pwa Rupelstreek Vzw",
    "wof:placetype":"venue"
},
  "geometry": {"coordinates":[4.3619680405,51.0860977173],"type":"Point"}
}