{
  "type": "Feature",
  "properties": {
    "addr:full":"Henegouwenstraat 121 Gent Oost-Vlaanderen 9000",
    "addr:housenumber":"121",
    "addr:postcode":"9000",
    "addr:street":"Henegouwenstraat;Oost-Vlaanderen",
    "iso:country":"BE",
    "sg:address":"Henegouwenstraat 121",
    "sg:city":"Gent",
    "sg:orig_category":"V\u00eatements pour b\u00e9b\u00e9s and enfants",
    "sg:phone":"+32 9 225 21 48",
    "sg:postcode":"9000",
    "sg:province":"Oost-Vlaanderen",
    "wof:name":"Huis De Verbeelding",
    "wof:placetype":"venue"
},
  "geometry": {"coordinates":[3.7277059555,51.0518264771],"type":"Point"}
}