{
  "type": "Feature",
  "properties": {
    "addr:full":"Kleine Izegemsestraat 9 Ledegem (sint-eloois-winkel) West-Vlaanderen 8880",
    "addr:housenumber":"9",
    "addr:postcode":"8880",
    "addr:street":"Kleine Izegemsestraat",
    "iso:country":"BE",
    "sg:address":"Kleine Izegemsestraat 9",
    "sg:city":"Ledegem (sint-eloois-winkel)",
    "sg:classifiers":[
        {
            "category":"Farming",
            "subcategory":"Livestock Farm",
            "type":"Manufacturing & Wholesale Goods"
        }
    ],
    "sg:phone":"+32 56 50 97 11",
    "sg:postcode":"8880",
    "sg:province":"West-Vlaanderen",
    "sg:tags":[
        "buyer"
    ],
    "wof:name":"Vandenbogaerde",
    "wof:placetype":"venue"
},
  "geometry": {"coordinates":[3.1814880371,50.878616333],"type":"Point"}
}