{
  "type": "Feature",
  "properties": {
    "addr:full":"Stationsstraat 245 Herzele Oost-Vlaanderen 9550",
    "addr:housenumber":"245",
    "addr:postcode":"9550",
    "addr:street":"Stationsstraat;Oost-Vlaanderen",
    "iso:country":"BE",
    "sg:address":"Stationsstraat 245",
    "sg:city":"Herzele",
    "sg:orig_category":"Aanleg van wegen, sportterreinen and vliegvelden Woningbouw",
    "sg:phone":"+32 53 63 15 81",
    "sg:postcode":"9550",
    "sg:province":"Oost-Vlaanderen",
    "wof:name":"Sr2b",
    "wof:placetype":"venue"
},
  "geometry": {"coordinates":[3.8805940151,50.8974533081],"type":"Point"}
}