{
  "type": "Feature",
  "properties": {
    "iso:country":"BE",
    "sg:address":"Bexstraat 1bb",
    "sg:city":"Antwerpen",
    "sg:orig_category":"Mat\u00e9riel \u00e9lectrique and \u00e9lectronique Gr",
    "sg:phone":"+32 3 233 75 94",
    "sg:postcode":"2018",
    "sg:province":"Antwerpen",
    "wof:name":"Zuckerman",
    "wof:placetype":"venue"
},
  "geometry": {"coordinates":[4.4139900208,51.2103347778],"type":"Point"}
}