{
  "type": "Feature",
  "properties": {
    "addr:full":"Begijnenstraat 40 Box 6 Turnhout Antwerpen 2300",
    "addr:housenumber":"40;6",
    "addr:postcode":"2300",
    "addr:street":"Begijnenstraat;Box",
    "iso:country":"BE",
    "sg:address":"Begijnenstraat 40 Box 6",
    "sg:city":"Turnhout",
    "sg:classifiers":[
        {
            "category":"Professional",
            "subcategory":"Engineering",
            "type":"Services"
        }
    ],
    "sg:phone":"+32 14 41 58 76",
    "sg:postcode":"2300",
    "sg:province":"Antwerpen",
    "sg:tags":[
        "civil",
        "offices-"
    ],
    "wof:name":"Studie- & Adviesbureau Baeten Bvba",
    "wof:placetype":"venue"
},
  "geometry": {"coordinates":[4.942855835,51.3279953003],"type":"Point"}
}