{
  "type": "Feature",
  "properties": {
    "addr:full":"Rue Joseph Wauters 85 Wavre Brabant Wallon 1300",
    "addr:housenumber":"85;1300",
    "addr:street":"Rue Joseph Wauters",
    "iso:country":"BE",
    "sg:address":"Rue Joseph Wauters 85",
    "sg:city":"Wavre",
    "sg:classifiers":[
        {
            "category":"Shopping",
            "subcategory":"Crafts & Fabrics",
            "type":"Retail Goods"
        }
    ],
    "sg:phone":"+32 10 22 48 61",
    "sg:postcode":"1300",
    "sg:province":"Brabant Wallon",
    "sg:tags":[
        "hi-fi",
        "equipment",
        "stereophonic",
        "-"
    ],
    "wof:name":"Vanden Borre",
    "wof:placetype":"venue"
},
  "geometry": {"coordinates":[4.6081700325,50.7107810974],"type":"Point"}
}