{
  "type": "Feature",
  "properties": {
    "iso:country":"BE",
    "sg:address":"Rue P\u00e8re Damien 46",
    "sg:city":"Bruxelles (evere)",
    "sg:classifiers":[
        {
            "category":"Health Services",
            "subcategory":"Health Practitioner",
            "type":"Services"
        }
    ],
    "sg:phone":"+32 2 216 51 45",
    "sg:postcode":"1140",
    "sg:province":"Bruxelles-Capitale",
    "sg:tags":[
        "physiotherapist"
    ],
    "wof:name":"Van De Gucht V\u00e9ronique",
    "wof:placetype":"venue"
},
  "geometry": {"coordinates":[4.4011387825,50.8701210022],"type":"Point"}
}