{
  "type": "Feature",
  "properties": {
    "addr:full":"Polderinstraat 14 Staden West-Vlaanderen 8840",
    "addr:housenumber":"14",
    "addr:postcode":"8840",
    "addr:street":"Polderinstraat",
    "iso:country":"BE",
    "sg:address":"Polderinstraat 14",
    "sg:city":"Staden",
    "sg:orig_category":"Producteurs de l\u00e9gumes",
    "sg:phone":"+32 51 20 65 91",
    "sg:postcode":"8840",
    "sg:province":"West-Vlaanderen",
    "wof:name":"Jozef Ceenaeme",
    "wof:placetype":"venue"
},
  "geometry": {"coordinates":[3.082326889,50.9479789734],"type":"Point"}
}