{
  "type": "Feature",
  "properties": {
    "addr:full":"R. Verbelenstraat 35 Puurs Antwerpen 2870",
    "addr:housenumber":"35",
    "addr:postcode":"2870",
    "addr:street":"Verbelenstraat",
    "iso:country":"BE",
    "sg:address":"R. Verbelenstraat 35",
    "sg:city":"Puurs",
    "sg:classifiers":[
        {
            "category":"Cafe",
            "type":"Food & Drink"
        }
    ],
    "sg:phone":"+32 3 889 38 80",
    "sg:postcode":"2870",
    "sg:province":"Antwerpen",
    "sg:tags":[
        "caf\u00e9s"
    ],
    "wof:name":"Marjolijn Quackels",
    "wof:placetype":"venue"
},
  "geometry": {"coordinates":[4.2764410973,51.0782279968],"type":"Point"}
}