{
  "type": "Feature",
  "properties": {
    "addr:full":"Industriepark-drongen 4e Gent (drongen) Oost-Vlaanderen 9031",
    "addr:housenumber":"4e",
    "addr:postcode":"9031",
    "addr:street":"Industriepark-Drongen",
    "iso:country":"BE",
    "sg:address":"Industriepark-drongen 4e",
    "sg:city":"Gent (drongen)",
    "sg:classifiers":[
        {
            "category":"Professional",
            "subcategory":"Testing Lab",
            "type":"Services"
        }
    ],
    "sg:phone":"+32 9 281 12 20",
    "sg:postcode":"9031",
    "sg:province":"Oost-Vlaanderen",
    "sg:tags":[
        "laboratory",
        "-",
        "machines",
        "apparatus",
        "supply"
    ],
    "wof:name":"Oxoid Nv",
    "wof:placetype":"venue"
},
  "geometry": {"coordinates":[3.5999770164,51.0435447693],"type":"Point"}
}