{
  "type": "Feature",
  "properties": {
    "iso:country":"BE",
    "sg:address":"Rue De L'eglise 127",
    "sg:city":"Raeren/raeren",
    "sg:orig_category":"Pain, p\u00e2tisseries and confiseries",
    "sg:phone":"+32 87 65 90 64",
    "sg:postcode":"4730",
    "sg:province":"Li\u00e8ge",
    "wof:name":"Bekodis",
    "wof:placetype":"venue"
},
  "geometry": {"coordinates":[6.1511101723,50.650188446],"type":"Point"}
}