{
  "type": "Feature",
  "properties": {
    "iso:country":"BE",
    "sg:address":"Rue Mattot 72",
    "sg:city":"Waterloo",
    "sg:orig_category":"Elektrische installaties voor woningen",
    "sg:phone":"+32 2 354 51 68",
    "sg:postcode":"1410",
    "sg:province":"Brabant Wallon",
    "wof:name":"Eric Tamise",
    "wof:placetype":"venue"
},
  "geometry": {"coordinates":[4.3790888786,50.7125244141],"type":"Point"}
}