{
  "type": "Feature",
  "properties": {
    "addr:full":"Tieltsesteenweg 35 Deinze Oost-Vlaanderen 9800",
    "addr:housenumber":"35",
    "addr:postcode":"9800",
    "addr:street":"Tieltsesteenweg",
    "iso:country":"BE",
    "sg:address":"Tieltsesteenweg 35",
    "sg:city":"Deinze",
    "sg:orig_category":"P\u00e9pini\u00e9ristes",
    "sg:phone":"+32 51 63 66 76",
    "sg:postcode":"9800",
    "sg:province":"Oost-Vlaanderen",
    "wof:name":"Maudyplant",
    "wof:placetype":"venue"
},
  "geometry": {"coordinates":[3.4534220695,50.9893074036],"type":"Point"}
}