{
  "type": "Feature",
  "properties": {
    "iso:country":"BE",
    "sg:address":"Brechtsebaan 265",
    "sg:city":"Schoten",
    "sg:classifiers":[
        {
            "category":"Building & Trades",
            "subcategory":"Landscaping Services",
            "type":"Services"
        }
    ],
    "sg:phone":"+32 3 651 95 05",
    "sg:postcode":"2900",
    "sg:province":"Antwerpen",
    "sg:tags":[
        "gardening",
        "garden",
        "maintenance"
    ],
    "wof:name":"Aquilegia",
    "wof:placetype":"venue"
},
  "geometry": {"coordinates":[4.5120401382,51.2662391663],"type":"Point"}
}