{
  "type": "Feature",
  "properties": {
    "addr:full":"Hoogeind 78 Stabroek Antwerpen 2940",
    "addr:housenumber":"78",
    "addr:postcode":"2940",
    "addr:street":"Hoogeind",
    "iso:country":"BE",
    "sg:address":"Hoogeind 78",
    "sg:city":"Stabroek",
    "sg:orig_category":"Plaatsen van vloer- and muurbekleding Schilders",
    "sg:phone":"+32 3 569 04 81",
    "sg:postcode":"2940",
    "sg:province":"Antwerpen",
    "wof:name":"Brkic",
    "wof:placetype":"venue"
},
  "geometry": {"coordinates":[4.3820500374,51.3395614624],"type":"Point"}
}