{
  "type": "Feature",
  "properties": {
    "addr:full":"Holleweg 2 Brecht Antwerpen 2960",
    "addr:housenumber":"2",
    "addr:postcode":"2960",
    "addr:street":"Holleweg",
    "iso:country":"BE",
    "sg:address":"Holleweg 2",
    "sg:city":"Brecht",
    "sg:orig_category":"Eleveurs d'animaux domestiques",
    "sg:phone":"+32 3 636 19 62",
    "sg:postcode":"2960",
    "sg:province":"Antwerpen",
    "wof:name":"Vereniging Vlaamse Koehonden",
    "wof:placetype":"venue"
},
  "geometry": {"coordinates":[4.5585532188,51.2942352295],"type":"Point"}
}