{
  "type": "Feature",
  "properties": {
    "iso:country":"BE",
    "sg:address":"Rue Wastinelle 19",
    "sg:city":"Silly",
    "sg:orig_category":"Rusthuizen and serviceflats",
    "sg:phone":"+32 68 25 04 00",
    "sg:postcode":"7830",
    "sg:province":"Hainaut",
    "wof:name":"Les Jardins De La Sille",
    "wof:placetype":"venue"
},
  "geometry": {"coordinates":[3.9232299328,50.6518058777],"type":"Point"}
}