{
  "type": "Feature",
  "properties": {
    "addr:full":"Obterrestraat 70 Poperinge West-Vlaanderen 8972",
    "addr:housenumber":"70",
    "addr:postcode":"8972",
    "addr:street":"Obterrestraat",
    "iso:country":"BE",
    "sg:address":"Obterrestraat 70",
    "sg:city":"Poperinge",
    "sg:orig_category":"Herstellingen and onderhoud van auto's Voertuigen",
    "sg:phone":"+32 57 30 07 83",
    "sg:postcode":"8972",
    "sg:province":"West-Vlaanderen",
    "wof:name":"Garage Deschodt",
    "wof:placetype":"venue"
},
  "geometry": {"coordinates":[2.6514649391,50.8932723999],"type":"Point"}
}