{
  "type": "Feature",
  "properties": {
    "addr:full":"Schrieksesteenweg 160 Heist-op-den-berg (booischot) Antwerpen 2221",
    "addr:housenumber":"160",
    "addr:postcode":"2221",
    "addr:street":"Schrieksesteenweg",
    "iso:country":"BE",
    "sg:address":"Schrieksesteenweg 160",
    "sg:city":"Heist-op-den-berg (booischot)",
    "sg:classifiers":[
        {
            "category":"Home & Garden",
            "subcategory":"Carpets & Floor Coverings",
            "type":"Retail Goods"
        }
    ],
    "sg:phone":"+32 15 23 31 10",
    "sg:postcode":"2221",
    "sg:province":"Antwerpen",
    "sg:tags":[
        "tile"
    ],
    "wof:name":"De Roover & Zonen Bvba",
    "wof:placetype":"venue"
},
  "geometry": {"coordinates":[4.7739758492,51.0512428284],"type":"Point"}
}