{
  "type": "Feature",
  "properties": {
    "addr:full":"Landriesstraat 3 Wellen Limburg 3832",
    "addr:housenumber":"3",
    "addr:postcode":"3832",
    "addr:street":"Landriesstraat",
    "iso:country":"BE",
    "sg:address":"Landriesstraat 3",
    "sg:city":"Wellen",
    "sg:orig_category":"Studios photographiques",
    "sg:phone":"+32 12 74 37 85",
    "sg:postcode":"3832",
    "sg:province":"Limburg",
    "wof:name":"Joseph Hansoul",
    "wof:placetype":"venue"
},
  "geometry": {"coordinates":[5.2886791229,50.8364982605],"type":"Point"}
}