{
  "type": "Feature",
  "properties": {
    "iso:country":"BE",
    "sg:address":"Parkstraat 71",
    "sg:city":"Kortenberg",
    "sg:orig_category":"Fa\u00e7ade covering",
    "sg:phone":"+32 2 252 52 90",
    "sg:postcode":"3070",
    "sg:province":"Vlaams-Brabant",
    "wof:name":"Dermul Bvba",
    "wof:placetype":"venue"
},
  "geometry": {"coordinates":[4.5416808128,50.8911361694],"type":"Point"}
}