{
  "type": "Feature",
  "properties": {
    "iso:country":"BE",
    "sg:address":"Liersesteenweg 31",
    "sg:city":"Ranst",
    "sg:orig_category":"Experts-comptables",
    "sg:phone":"+32 3 480 60 77",
    "sg:postcode":"2520",
    "sg:province":"Antwerpen",
    "wof:name":"A. Verhoeven",
    "wof:placetype":"venue"
},
  "geometry": {"coordinates":[4.5898389816,51.1574554443],"type":"Point"}
}