{
  "type": "Feature",
  "properties": {
    "iso:country":"BE",
    "sg:address":"Place La Vaux 2a",
    "sg:city":"Ferri\u00c8res",
    "sg:orig_category":"Epiceries",
    "sg:phone":"+32 4 369 31 64",
    "sg:postcode":"4190",
    "sg:province":"Li\u00e8ge",
    "wof:name":"Le Beaumarch\u00c9",
    "wof:placetype":"venue"
},
  "geometry": {"coordinates":[5.6024708748,50.4445075989],"type":"Point"}
}