{
  "type": "Feature",
  "properties": {
    "addr:full":"Rue Armand Jamoulle 1 Faimes Li\u00e8ge 4317",
    "addr:housenumber":"1",
    "addr:postcode":"4317",
    "addr:street":"Rue Armand Jamoulle",
    "iso:country":"BE",
    "sg:address":"Rue Armand Jamoulle 1",
    "sg:city":"Faimes",
    "sg:orig_category":"Dakwerken",
    "sg:phone":"+32 19 32 56 86",
    "sg:postcode":"4317",
    "sg:province":"Li\u00e8ge",
    "wof:name":"Pol Bayard",
    "wof:placetype":"venue"
},
  "geometry": {"coordinates":[5.2723550797,50.6471176147],"type":"Point"}
}