{
  "type": "Feature",
  "properties": {
    "iso:country":"BE",
    "sg:address":"Leyse Hoevestraat 5",
    "sg:city":"Westerlo",
    "sg:orig_category":"Animaux domestiques and accessoires",
    "sg:phone":"+32 14 54 75 21",
    "sg:postcode":"2260",
    "sg:province":"Antwerpen",
    "wof:name":"Cattery El Donna Evita",
    "wof:placetype":"venue"
},
  "geometry": {"coordinates":[4.8642258644,51.1044654846],"type":"Point"}
}