{
  "type": "Feature",
  "properties": {
    "addr:full":"Oude Dorpsstraat 37 Beveren Oost-Vlaanderen 9120",
    "addr:housenumber":"37",
    "addr:postcode":"9120",
    "addr:street":"Oude Dorpsstraat",
    "iso:country":"BE",
    "sg:address":"Oude Dorpsstraat 37",
    "sg:city":"Beveren",
    "sg:orig_category":"Cr\u00e9meries",
    "sg:phone":"+32 3 775 75 32",
    "sg:postcode":"9120",
    "sg:province":"Oost-Vlaanderen",
    "wof:name":"Carina Van Dorsselaer",
    "wof:placetype":"venue"
},
  "geometry": {"coordinates":[4.1918377876,51.2190589905],"type":"Point"}
}