{
  "type": "Feature",
  "properties": {
    "iso:country":"BE",
    "sg:address":"Place Camille Lemonnier 2",
    "sg:city":"La Hulpe",
    "sg:classifiers":[
        {
            "category":"Shopping",
            "subcategory":"Stationery & Office Supplies",
            "type":"Retail Goods"
        }
    ],
    "sg:phone":"+32 2 653 57 92",
    "sg:postcode":"1310",
    "sg:province":"Brabant Wallon",
    "sg:tags":[
        "partition"
    ],
    "wof:name":"Les Entreprises Strimelle",
    "wof:placetype":"venue"
},
  "geometry": {"coordinates":[4.4931559563,50.7333335876],"type":"Point"}
}