{
  "type": "Feature",
  "properties": {
    "addr:full":"Ooststraat 101 Roeselare West-Vlaanderen 8800",
    "addr:housenumber":"101",
    "addr:postcode":"8800",
    "addr:street":"Ooststraat",
    "iso:country":"BE",
    "sg:address":"Ooststraat 101",
    "sg:city":"Roeselare",
    "sg:classifiers":[
        {
            "category":"Shopping",
            "subcategory":"Clothing, Apparel, & Fashions",
            "type":"Retail Goods"
        }
    ],
    "sg:phone":"+32 51 20 45 71",
    "sg:postcode":"8800",
    "sg:province":"West-Vlaanderen",
    "sg:tags":[
        "v\u00eatements",
        "pour",
        "dame"
    ],
    "wof:name":"Huis Aubergine",
    "wof:placetype":"venue"
},
  "geometry": {"coordinates":[3.1282598972,50.9474754333],"type":"Point"}
}