{
  "type": "Feature",
  "properties": {
    "addr:full":"Vierkeerstraat 41 Zwevegem (heestert) West-Vlaanderen 8551",
    "addr:housenumber":"41",
    "addr:postcode":"8551",
    "addr:street":"Vierkeerstraat",
    "iso:country":"BE",
    "sg:address":"Vierkeerstraat 41",
    "sg:city":"Zwevegem (heestert)",
    "sg:classifiers":[
        {
            "category":"Personal",
            "subcategory":"Beauty Salon",
            "type":"Services"
        }
    ],
    "sg:phone":"+32 56 64 46 21",
    "sg:postcode":"8551",
    "sg:province":"West-Vlaanderen",
    "sg:tags":[
        "lady",
        "-",
        "hairdressing"
    ],
    "wof:name":"farouche Coussement Paula",
    "wof:placetype":"venue"
},
  "geometry": {"coordinates":[3.4109840393,50.782283783],"type":"Point"}
}