{
  "type": "Feature",
  "properties": {
    "iso:country":"BE",
    "sg:address":"Rue De Corbuha 13",
    "sg:city":"Chiny",
    "sg:orig_category":"G\u00e9om\u00e8tres",
    "sg:phone":"+32 61 32 05 17",
    "sg:postcode":"6810",
    "sg:province":"Luxembourg",
    "wof:name":"Vanden Dunghen",
    "wof:placetype":"venue"
},
  "geometry": {"coordinates":[5.3408951759,49.7371940613],"type":"Point"}
}