{
  "type": "Feature",
  "properties": {
    "addr:full":"Steenweg Wijchmaal 17 Box 2 Peer Limburg 3990",
    "addr:housenumber":"17;2",
    "addr:postcode":"3990",
    "addr:street":"Steenweg Wijchmaal;Box",
    "iso:country":"BE",
    "sg:address":"Steenweg Wijchmaal 17 Box 2",
    "sg:city":"Peer",
    "sg:orig_category":"Mutualities",
    "sg:phone":"+32 11 63 56 15",
    "sg:postcode":"3990",
    "sg:province":"Limburg",
    "wof:name":"Euromut",
    "wof:placetype":"venue"
},
  "geometry": {"coordinates":[5.4477171898,51.1325302124],"type":"Point"}
}