{
  "type": "Feature",
  "properties": {
    "addr:full":"Rue Du Sommet 32 Bouillon (corbion) Luxembourg 6838",
    "addr:housenumber":"32",
    "addr:postcode":"6838",
    "addr:street":"Rue Du Sommet",
    "iso:country":"BE",
    "sg:address":"Rue Du Sommet 32",
    "sg:city":"Bouillon (corbion)",
    "sg:classifiers":[
        {
            "category":"Home & Garden",
            "subcategory":"Kitchen Supply",
            "type":"Retail Goods"
        }
    ],
    "sg:phone":"+32 61 46 51 00",
    "sg:postcode":"6838",
    "sg:province":"Luxembourg",
    "sg:tags":[
        "equipment",
        "baker",
        "-"
    ],
    "wof:name":"Ateliers Pierret Sprl",
    "wof:placetype":"venue"
},
  "geometry": {"coordinates":[5.0141401291,49.7893829346],"type":"Point"}
}