{
  "type": "Feature",
  "properties": {
    "iso:country":"BE",
    "sg:address":"Dronkaertstraat 287",
    "sg:city":"Menen (lauwe)",
    "sg:classifiers":[
        {
            "category":"Professional",
            "subcategory":"Lawyer & Legal Services",
            "type":"Services"
        }
    ],
    "sg:phone":"+32 56 41 02 11",
    "sg:postcode":"8930",
    "sg:province":"West-Vlaanderen",
    "wof:name":"Mespreuve Wim",
    "wof:placetype":"venue"
},
  "geometry": {"coordinates":[3.1795890331,50.7781143188],"type":"Point"}
}