{
  "type": "Feature",
  "properties": {
    "addr:full":"Rue Du Ch\u00cane 7 Frasnes-lez-anvaing Hainaut 7911",
    "addr:housenumber":"7",
    "addr:postcode":"7911",
    "addr:street":"Rue Du Che\u0302Ne",
    "iso:country":"BE",
    "sg:address":"Rue Du Ch\u00cane 7",
    "sg:city":"Frasnes-lez-anvaing",
    "sg:orig_category":"Traitement and rev\u00eatement des m\u00e9taux",
    "sg:phone":"+32 69 86 82 05",
    "sg:postcode":"7911",
    "sg:province":"Hainaut",
    "wof:name":"Ramu Franck",
    "wof:placetype":"venue"
},
  "geometry": {"coordinates":[3.5811979771,50.6376914978],"type":"Point"}
}