{
  "type": "Feature",
  "properties": {
    "iso:country":"BE",
    "sg:address":"Quai De Coronmeuse 18",
    "sg:city":"Li\u00c8ge",
    "sg:orig_category":"Autoverhuur Voertuigen",
    "sg:phone":"+32 4 228 18 08",
    "sg:postcode":"4000",
    "sg:province":"Li\u00e8ge",
    "wof:name":"Privilege Auto",
    "wof:placetype":"venue"
},
  "geometry": {"coordinates":[5.6015110016,50.6512069702],"type":"Point"}
}