{
  "type": "Feature",
  "properties": {
    "addr:full":"Izegemsestraat 84 Roeselare (rumbeke) West-Vlaanderen 8800",
    "addr:housenumber":"84",
    "addr:postcode":"8800",
    "addr:street":"Izegemsestraat",
    "iso:country":"BE",
    "sg:address":"Izegemsestraat 84",
    "sg:city":"Roeselare (rumbeke)",
    "sg:classifiers":[
        {
            "category":"Building & Trades",
            "subcategory":"Construction",
            "type":"Services"
        }
    ],
    "sg:phone":"+32 51 26 52 52",
    "sg:postcode":"8800",
    "sg:province":"West-Vlaanderen",
    "sg:tags":[
        "roofing",
        "material",
        "-"
    ],
    "wof:name":"Olivier",
    "wof:placetype":"venue"
},
  "geometry": {"coordinates":[3.1652650833,50.9311485291],"type":"Point"}
}