{
  "type": "Feature",
  "properties": {
    "iso:country":"BE",
    "sg:address":"Rue De La Brasserie 162",
    "sg:city":"Florennes (saint-aubin)",
    "sg:classifiers":[
        {
            "category":"Professional",
            "subcategory":"Art Services",
            "type":"Services"
        }
    ],
    "sg:phone":"+32 71 68 85 18",
    "sg:postcode":"5620",
    "sg:province":"Namur",
    "sg:tags":[
        "-",
        "painter",
        "artist"
    ],
    "wof:name":"Willems C",
    "wof:placetype":"venue"
},
  "geometry": {"coordinates":[4.5787911415,50.2478065491],"type":"Point"}
}