{
  "type": "Feature",
  "properties": {
    "addr:full":"Korenmarkt 4 Gent Oost-Vlaanderen 9000",
    "addr:housenumber":"4",
    "addr:postcode":"9000",
    "addr:street":"Korenmarkt;Oost-Vlaanderen",
    "iso:country":"BE",
    "sg:address":"Korenmarkt 4",
    "sg:city":"Gent",
    "sg:classifiers":[
        {
            "category":"Restaurant",
            "type":"Food & Drink"
        }
    ],
    "sg:phone":"+32 9 233 64 04",
    "sg:postcode":"9000",
    "sg:province":"Oost-Vlaanderen",
    "wof:name":"Chez L\u00c9on 1893",
    "wof:placetype":"venue"
},
  "geometry": {"coordinates":[3.7220599651,51.0544013977],"type":"Point"}
}