{
  "type": "Feature",
  "properties": {
    "addr:full":"Rue De L'institut 8 Chiny Luxembourg 6810",
    "addr:housenumber":"8",
    "addr:postcode":"6810",
    "addr:street":"Rue De L'Institut",
    "iso:country":"BE",
    "sg:address":"Rue De L'institut 8",
    "sg:city":"Chiny",
    "sg:orig_category":"Eclairage et \u00e9quipements du foyer",
    "sg:phone":"+32 61 31 29 93",
    "sg:postcode":"6810",
    "sg:province":"Luxembourg",
    "wof:name":"Marianne Gobin",
    "wof:placetype":"venue"
},
  "geometry": {"coordinates":[5.3734750748,49.6934585571],"type":"Point"}
}