{
  "type": "Feature",
  "properties": {
    "iso:country":"BE",
    "sg:address":"Rue Ernest Solvay 192",
    "sg:city":"Li\u00c8ge",
    "sg:orig_category":"M\u00e9decins and sp\u00e9cialistes",
    "sg:phone":"+32 4 253 13 11",
    "sg:postcode":"4000",
    "sg:province":"Li\u00e8ge",
    "wof:name":"I. Farrauto",
    "wof:placetype":"venue"
},
  "geometry": {"coordinates":[5.5510730743,50.609916687],"type":"Point"}
}