{
  "type": "Feature",
  "properties": {
    "iso:country":"BE",
    "sg:address":"Rue Armand Bury 122",
    "sg:city":"Thuin",
    "sg:orig_category":"Ordinateurs and \u00e9quipement informatique",
    "sg:phone":"+32 71 51 20 64",
    "sg:postcode":"6534",
    "sg:province":"Hainaut",
    "wof:name":"M.v. Informatique",
    "wof:placetype":"venue"
},
  "geometry": {"coordinates":[4.3547592163,50.3442955017],"type":"Point"}
}