{
  "type": "Feature",
  "properties": {
    "iso:country":"BE",
    "sg:address":"Rue De La Barri\u00e8re De Fer 53",
    "sg:city":"Mouscron (dottignies)",
    "sg:classifiers":[
        {
            "category":"Personal",
            "subcategory":"Psychics & Astrologers",
            "type":"Services"
        }
    ],
    "sg:phone":"+32 56 48 49 52",
    "sg:postcode":"7711",
    "sg:province":"Hainaut",
    "sg:tags":[
        "astrology"
    ],
    "wof:name":"Para-astro",
    "wof:placetype":"venue"
},
  "geometry": {"coordinates":[3.3187088966,50.7274398804],"type":"Point"}
}