{
  "type": "Feature",
  "properties": {
    "addr:full":"Posterijstraat 4 Waregem West-Vlaanderen 8793",
    "addr:housenumber":"4",
    "addr:postcode":"8793",
    "addr:street":"Posterijstraat",
    "iso:country":"BE",
    "sg:address":"Posterijstraat 4",
    "sg:city":"Waregem",
    "sg:orig_category":"Industri\u00eble wasserijen and droogkuis",
    "sg:phone":"+32 56 61 01 22",
    "sg:postcode":"8793",
    "sg:province":"West-Vlaanderen",
    "wof:name":"Droogkuis Edelweiss",
    "wof:placetype":"venue"
},
  "geometry": {"coordinates":[3.4043591022,50.9057579041],"type":"Point"}
}