{
  "type": "Feature",
  "properties": {
    "addr:full":"Rue Piervenne 141b Ciney Namur 5590",
    "addr:housenumber":"141b",
    "addr:postcode":"5590",
    "addr:street":"Rue Piervenne",
    "iso:country":"BE",
    "sg:address":"Rue Piervenne 141b",
    "sg:city":"Ciney",
    "sg:classifiers":[
        {
            "category":"Health Services",
            "subcategory":"Dentist",
            "type":"Services"
        }
    ],
    "sg:phone":"+32 83 21 26 54",
    "sg:postcode":"5590",
    "sg:province":"Namur",
    "wof:name":"Paternostre Dominique",
    "wof:placetype":"venue"
},
  "geometry": {"coordinates":[5.0923008919,50.2917556763],"type":"Point"}
}