{
  "type": "Feature",
  "properties": {
    "iso:country":"BE",
    "sg:address":"Chauss\u00c9e D'ixelles 18",
    "sg:city":"Elsene/ixelles",
    "sg:orig_category":"V\u00eatements pour b\u00e9b\u00e9s and enfants. Articles pour b\u00e9b\u00e9s",
    "sg:phone":"+32 2 511 50 14",
    "sg:postcode":"1050",
    "sg:province":"Bruxelles-Capitale",
    "wof:name":"Natalys",
    "wof:placetype":"venue"
},
  "geometry": {"coordinates":[4.3622169495,50.8376922607],"type":"Point"}
}