{
  "type": "Feature",
  "properties": {
    "addr:full":"Rue Les Roches 3 Doische Namur 5680",
    "addr:housenumber":"3",
    "addr:postcode":"5680",
    "addr:street":"Rue Les Roches",
    "iso:country":"BE",
    "sg:address":"Rue Les Roches 3",
    "sg:city":"Doische",
    "sg:classifiers":[
        {
            "category":"Social Services",
            "subcategory":"Job Training",
            "type":"Services"
        }
    ],
    "sg:phone":"+32 82 67 80 63",
    "sg:postcode":"5680",
    "sg:province":"Namur",
    "sg:tags":[
        "de",
        "terrain",
        "camping"
    ],
    "wof:name":"Camping Vall\u00c9e Merveilleuse",
    "wof:placetype":"venue"
},
  "geometry": {"coordinates":[4.7245168686,50.1700782776],"type":"Point"}
}