{
  "type": "Feature",
  "properties": {
    "addr:full":"Zeedijk-centrum 481 Koksijde West-Vlaanderen 8670",
    "addr:housenumber":"481",
    "addr:postcode":"8670",
    "iso:country":"BE",
    "sg:address":"Zeedijk-centrum 481",
    "sg:city":"Koksijde",
    "sg:classifiers":[
        {
            "category":"Shopping",
            "subcategory":"Clothing, Apparel, & Fashions",
            "type":"Retail Goods"
        }
    ],
    "sg:phone":"+32 58 51 75 26",
    "sg:postcode":"8670",
    "sg:province":"West-Vlaanderen",
    "sg:tags":[
        "v\u00eatements",
        "pour",
        "dame"
    ],
    "wof:name":"Huis Harlekijn",
    "wof:placetype":"venue"
},
  "geometry": {"coordinates":[2.6492800713,51.1061401367],"type":"Point"}
}