{
  "type": "Feature",
  "properties": {
    "addr:full":"Dorpsstraat 3 Bocholt Limburg 3950",
    "addr:housenumber":"3",
    "addr:postcode":"3950",
    "addr:street":"Dorpsstraat",
    "iso:country":"BE",
    "sg:address":"Dorpsstraat 3",
    "sg:city":"Bocholt",
    "sg:orig_category":"Banken and kredietinstellingen",
    "sg:phone":"+32 89 46 26 23",
    "sg:postcode":"3950",
    "sg:province":"Limburg",
    "wof:name":"Dexia",
    "wof:placetype":"venue"
},
  "geometry": {"coordinates":[5.581179142,51.1741981506],"type":"Point"}
}