{
  "type": "Feature",
  "properties": {
    "iso:country":"BE",
    "sg:address":"Einestraat 99",
    "sg:city":"Leopoldsburg",
    "sg:classifiers":[
        {
            "category":"Restaurant",
            "type":"Food & Drink"
        }
    ],
    "sg:phone":"+32 11 34 71 62",
    "sg:postcode":"3971",
    "sg:province":"Limburg",
    "wof:name":"Coletje",
    "wof:placetype":"venue"
},
  "geometry": {"coordinates":[5.2143330574,51.1043243408],"type":"Point"}
}