{
  "type": "Feature",
  "properties": {
    "addr:full":"O L Vrouwpln 22 St. Niklaas 2700",
    "addr:housenumber":"22",
    "addr:postcode":"2700",
    "addr:street":"O;St. Niklaas",
    "iso:country":"BE",
    "sg:address":"O L Vrouwpln 22",
    "sg:city":"St. Niklaas",
    "sg:classifiers":[
        {
            "category":"Banks & Credit Unions",
            "subcategory":"Bank",
            "type":"Services"
        }
    ],
    "sg:phone":"+32 3 777 67 47",
    "sg:postcode":"2700",
    "wof:name":"Caisse Nationale De, Cr\u00e9dit Professionnel",
    "wof:placetype":"venue"
},
  "geometry": {"coordinates":[4.1414899826,51.1644592285],"type":"Point"}
}