{
  "type": "Feature",
  "properties": {
    "addr:full":"Chemin Du Gros Tienne 14 La Hulpe Brabant Wallon 1310",
    "addr:housenumber":"14",
    "addr:postcode":"1310",
    "addr:street":"Chemin Du Gros Tienne",
    "iso:country":"BE",
    "sg:address":"Chemin Du Gros Tienne 14",
    "sg:city":"La Hulpe",
    "sg:classifiers":[
        {
            "category":"Arena",
            "subcategory":"Sports Club",
            "type":"Entertainment"
        }
    ],
    "sg:phone":"+32 2 654 18 31",
    "sg:postcode":"1310",
    "sg:province":"Brabant Wallon",
    "sg:tags":[
        "terrain",
        "hors",
        "de",
        "installation",
        "sportifs"
    ],
    "wof:name":"Marin D'eau Douce",
    "wof:placetype":"venue"
},
  "geometry": {"coordinates":[4.4698228836,50.720905304],"type":"Point"}
}