{
  "type": "Feature",
  "properties": {
    "addr:full":"Route De Couvin 68 Walcourt (somz\u00e9e) Namur 5651",
    "addr:housenumber":"68",
    "addr:postcode":"5651",
    "addr:street":"Route De Couvin",
    "iso:country":"BE",
    "sg:address":"Route De Couvin 68",
    "sg:city":"Walcourt (somz\u00e9e)",
    "sg:classifiers":[
        {
            "category":"Manufacturing",
            "subcategory":"Glass & Minerals",
            "type":"Manufacturing & Wholesale Goods"
        }
    ],
    "sg:phone":"+32 71 22 15 34",
    "sg:postcode":"5651",
    "sg:province":"Namur",
    "sg:tags":[
        "automobile",
        "-"
    ],
    "wof:name":"Auto Vitre Express",
    "wof:placetype":"venue"
},
  "geometry": {"coordinates":[4.4262080193,50.2824401855],"type":"Point"}
}