{
  "type": "Feature",
  "properties": {
    "iso:country":"BE",
    "sg:address":"Place De Belle Vue 3",
    "sg:city":"Aiseau-presles (presles)",
    "sg:classifiers":[
        {
            "category":"Shopping",
            "subcategory":"Bicycles & Sporting Goods",
            "type":"Retail Goods"
        }
    ],
    "sg:phone":"+32 71 40 21 20",
    "sg:postcode":"6250",
    "sg:province":"Hainaut",
    "sg:tags":[
        "-"
    ],
    "wof:name":"Giga Bike",
    "wof:placetype":"venue"
},
  "geometry": {"coordinates":[4.5863847733,50.40990448],"type":"Point"}
}