{
  "type": "Feature",
  "properties": {
    "addr:full":"Rue S. Malaise 23 Grivegnee Li\u00e8ge 4030",
    "addr:housenumber":"23",
    "addr:postcode":"4030",
    "addr:street":"Rue S. Malaise",
    "iso:country":"BE",
    "sg:address":"Rue S. Malaise 23",
    "sg:city":"Grivegnee",
    "sg:orig_category":"Royal Canin",
    "sg:phone":"+32 4 361 15 05",
    "sg:postcode":"4030",
    "sg:province":"Li\u00e8ge",
    "wof:name":"Tom & Co",
    "wof:placetype":"venue"
},
  "geometry": {"coordinates":[5.6244859695,50.6293411255],"type":"Point"}
}