{
  "type": "Feature",
  "properties": {
    "addr:full":"Rot 40 Holsbeek (nieuwrode) Vlaams-Brabant 3221",
    "addr:housenumber":"40",
    "addr:postcode":"3221",
    "addr:street":"Rot",
    "iso:country":"BE",
    "sg:address":"Rot 40",
    "sg:city":"Holsbeek (nieuwrode)",
    "sg:classifiers":[
        {
            "category":"Home & Garden",
            "subcategory":"Household Appliances",
            "type":"Retail Goods"
        }
    ],
    "sg:phone":"+32 16 56 75 19",
    "sg:postcode":"3221",
    "sg:province":"Vlaams-Brabant",
    "sg:tags":[
        "repair",
        "mainten",
        "-",
        "electric"
    ],
    "wof:name":"Vandermolen Dirk Elektro-service",
    "wof:placetype":"venue"
},
  "geometry": {"coordinates":[4.8174929619,50.9555854797],"type":"Point"}
}