{
  "type": "Feature",
  "properties": {
    "iso:country":"BE",
    "sg:address":"Avenue Du Roi 22",
    "sg:city":"Saint-gilles",
    "sg:orig_category":"Diverse bedrijfsbeheeradviesbureaus",
    "sg:phone":"+32 2 534 40 31",
    "sg:postcode":"1060",
    "sg:province":"Bruxelles-Capitale",
    "wof:name":"Formagest",
    "wof:placetype":"venue"
},
  "geometry": {"coordinates":[4.3336229324,50.8312110901],"type":"Point"}
}