{
  "type": "Feature",
  "properties": {
    "addr:full":"Kortrijksesteenweg 64 Sint-martens-latem Oost-Vlaanderen 9830",
    "addr:housenumber":"64",
    "addr:postcode":"9830",
    "addr:street":"Kortrijksesteenweg",
    "iso:country":"BE",
    "sg:address":"Kortrijksesteenweg 64",
    "sg:city":"Sint-martens-latem",
    "sg:orig_category":"Meubles D\u00e9taillants, Am\u00e9nagement de B\u00e2timents et de Cuisines",
    "sg:phone":"+32 9 282 41 87",
    "sg:postcode":"9830",
    "sg:province":"Oost-Vlaanderen",
    "wof:name":"Meubelen Canape",
    "wof:placetype":"venue"
},
  "geometry": {"coordinates":[3.6442739964,51.012840271],"type":"Point"}
}