{
  "type": "Feature",
  "properties": {
    "iso:country":"BE",
    "sg:address":"'t Serclaeslaan 1a",
    "sg:city":"Sint-pieters-leeuw",
    "sg:classifiers":[
        {
            "category":"Building & Trades",
            "subcategory":"Electrical",
            "type":"Services"
        }
    ],
    "sg:phone":"+32 2 378 28 08",
    "sg:postcode":"1600",
    "sg:province":"Vlaams-Brabant",
    "sg:tags":[
        "electric",
        "-",
        "housewiring",
        "contractor"
    ],
    "wof:name":"Suenens Bvba",
    "wof:placetype":"venue"
},
  "geometry": {"coordinates":[4.2636790276,50.7989425659],"type":"Point"}
}