{
  "type": "Feature",
  "properties": {
    "addr:full":"Nijverheidszone 'begijnenmeers' 23 Liedekerke Vlaams-Brabant 1770",
    "addr:postcode":"1770",
    "addr:street":"Vlaams-Brabant",
    "iso:country":"BE",
    "sg:address":"Nijverheidszone 'begijnenmeers' 23",
    "sg:city":"Liedekerke",
    "sg:classifiers":[
        {
            "category":"Retail",
            "subcategory":"Auto Repair",
            "type":"Services"
        }
    ],
    "sg:phone":"+32 53 66 82 54",
    "sg:postcode":"1770",
    "sg:province":"Vlaams-Brabant",
    "sg:tags":[
        "garage"
    ],
    "wof:name":"Van Den Wyngaerde A Bvba",
    "wof:placetype":"venue"
},
  "geometry": {"coordinates":[4.0872688293,50.8854942322],"type":"Point"}
}