{
  "type": "Feature",
  "properties": {
    "iso:country":"BE",
    "sg:address":"Rue De L\u00b4eglise 26ba",
    "sg:city":"Welkenraedt",
    "sg:orig_category":"Enseignement maternel and primaire",
    "sg:phone":"+32 87 88 04 40",
    "sg:postcode":"4840",
    "sg:province":"Li\u00e8ge",
    "wof:name":"E.f.l. St.joseph",
    "wof:placetype":"venue"
},
  "geometry": {"coordinates":[5.9702172279,50.6603088379],"type":"Point"}
}