{
  "type": "Feature",
  "properties": {
    "addr:full":"Antwerpsestraat 19-21 Lier (groot) Antwerpen 2500",
    "addr:postcode":"19-21;2500",
    "addr:street":"Antwerpsestraat;Groot Antwerpen",
    "iso:country":"BE",
    "sg:address":"Antwerpsestraat 19-21",
    "sg:city":"Lier (groot)",
    "sg:orig_category":"V\u00eatements. Textiles",
    "sg:phone":"+32 3 480 02 03",
    "sg:postcode":"2500",
    "sg:province":"Antwerpen",
    "wof:name":"Veritas",
    "wof:placetype":"venue"
},
  "geometry": {"coordinates":[4.5686011314,51.1322059631],"type":"Point"}
}