{
  "type": "Feature",
  "properties": {
    "addr:full":"Rue De La Tannerie 19 Bruxelles (koekelberg) Bruxelles-Capitale 1081",
    "addr:housenumber":"19",
    "addr:postcode":"1081",
    "addr:street":"Rue De La Tannerie",
    "iso:country":"BE",
    "sg:address":"Rue De La Tannerie 19",
    "sg:city":"Bruxelles (koekelberg)",
    "sg:classifiers":[
        {
            "category":"Shopping",
            "subcategory":"Computers & Home Electronics",
            "type":"Retail Goods"
        }
    ],
    "sg:phone":"+32 475 57 02 15",
    "sg:postcode":"1081",
    "sg:province":"Bruxelles-Capitale",
    "sg:tags":[
        "-",
        "television",
        "radio"
    ],
    "wof:name":"Taac Info",
    "wof:placetype":"venue"
},
  "geometry": {"coordinates":[4.3301310539,50.8605232239],"type":"Point"}
}