{
  "type": "Feature",
  "properties": {
    "iso:country":"BE",
    "sg:address":"Herresbach 13",
    "sg:city":"Amel (meyerode)",
    "sg:classifiers":[
        {
            "category":"Airport",
            "subcategory":"International",
            "type":"Transportation"
        }
    ],
    "sg:phone":"+32 80 54 87 18",
    "sg:postcode":"4770",
    "sg:province":"Li\u00e8ge",
    "sg:tags":[
        "-",
        "transport"
    ],
    "wof:name":"Peiffer W",
    "wof:placetype":"venue"
},
  "geometry": {"coordinates":[6.2553100586,50.3189506531],"type":"Point"}
}