{
  "type": "Feature",
  "properties": {
    "iso:country":"BE",
    "sg:address":"Rue De Rixensart 18b17",
    "sg:city":"Rixensart",
    "sg:orig_category":"Tuinen",
    "sg:phone":"+32 2 653 30 24",
    "sg:postcode":"1332",
    "sg:province":"Brabant Wallon",
    "wof:name":"Espaces Roskam & Partners",
    "wof:placetype":"venue"
},
  "geometry": {"coordinates":[4.5144748688,50.7222442627],"type":"Point"}
}