{
  "type": "Feature",
  "properties": {
    "iso:country":"BE",
    "sg:address":"Vosveld 4",
    "sg:city":"Wijnegem",
    "sg:classifiers":[
        {
            "category":"Professional",
            "subcategory":"Testing Lab",
            "type":"Services"
        }
    ],
    "sg:phone":"+32 3 360 97 90",
    "sg:postcode":"2110",
    "sg:province":"Antwerpen",
    "sg:tags":[
        "laboratory",
        "furniture"
    ],
    "wof:name":"K\u00f6ttermann Bvba",
    "wof:placetype":"venue"
},
  "geometry": {"coordinates":[4.4947528839,51.2331466675],"type":"Point"}
}