{
  "type": "Feature",
  "properties": {
    "addr:full":"Rue De Nivelles 71 Wavre Brabant Wallon 1300",
    "addr:housenumber":"71;1300",
    "addr:street":"Rue De Nivelles",
    "iso:country":"BE",
    "sg:address":"Rue De Nivelles 71",
    "sg:city":"Wavre",
    "sg:classifiers":[
        {
            "category":"Shopping",
            "subcategory":"Crafts & Fabrics",
            "type":"Retail Goods"
        }
    ],
    "sg:phone":"+32 10 22 57 61",
    "sg:postcode":"1300",
    "sg:province":"Brabant Wallon",
    "sg:tags":[
        "-",
        "wool",
        "knitting",
        "yarn"
    ],
    "wof:name":"Anny Blatt-bouton D'or",
    "wof:placetype":"venue"
},
  "geometry": {"coordinates":[4.6071858406,50.714427948],"type":"Point"}
}