{
  "type": "Feature",
  "properties": {
    "iso:country":"BE",
    "sg:address":"Rue Du Relais 26",
    "sg:city":"Jodoigne (z\u00e9trud-lumay)",
    "sg:classifiers":[
        {
            "category":"Organizations",
            "subcategory":"Professional Association",
            "type":"Services"
        }
    ],
    "sg:phone":"+32 10 81 30 60",
    "sg:postcode":"1370",
    "sg:province":"Brabant Wallon",
    "sg:tags":[
        "trade-union",
        "federation"
    ],
    "wof:name":"Prl Secr\u00e9tariat L Michel",
    "wof:placetype":"venue"
},
  "geometry": {"coordinates":[4.8829760551,50.759021759],"type":"Point"}
}