{
  "type": "Feature",
  "properties": {
    "iso:country":"BE",
    "sg:address":"Rue Des Villas 95",
    "sg:city":"Hasti\u00c8re",
    "sg:orig_category":"Epiceries",
    "sg:phone":"+32 82 64 72 27",
    "sg:postcode":"5540",
    "sg:province":"Namur",
    "wof:name":"Epicerie Du Puits",
    "wof:placetype":"venue"
},
  "geometry": {"coordinates":[4.8646478653,50.2046699524],"type":"Point"}
}