{
  "type": "Feature",
  "properties": {
    "addr:full":"Rue Au Vin 38 Ronse/renaix Oost-Vlaanderen 9600",
    "addr:housenumber":"38",
    "addr:postcode":"9600",
    "addr:street":"Rue Au Vin",
    "iso:country":"BE",
    "sg:address":"Rue Au Vin 38",
    "sg:city":"Ronse/renaix",
    "sg:orig_category":"Salons de coiffure. Instituts de beaut\u00e9",
    "sg:phone":"+32 55 21 35 58",
    "sg:postcode":"9600",
    "sg:province":"Oost-Vlaanderen",
    "wof:name":"Christiane De Wolf",
    "wof:placetype":"venue"
},
  "geometry": {"coordinates":[3.5977070332,50.7489242554],"type":"Point"}
}