{
  "type": "Feature",
  "properties": {
    "iso:country":"BE",
    "sg:address":"Rue De La Gare 6",
    "sg:city":"Ottignies-louvain-la-neuve (louvain-la-neuve)",
    "sg:classifiers":[
        {
            "category":"Travel",
            "subcategory":"Hotels & Motels",
            "type":"Entertainment"
        }
    ],
    "sg:phone":"+32 10 48 65 65",
    "sg:postcode":"1348",
    "sg:province":"Brabant Wallon",
    "wof:name":"Relais (le)",
    "wof:placetype":"venue"
},
  "geometry": {"coordinates":[4.615582943,50.6710662842],"type":"Point"}
}