{
  "type": "Feature",
  "properties": {
    "iso:country":"BE",
    "sg:address":"Oude Baan 4",
    "sg:city":"Lokeren",
    "sg:orig_category":"Non-Classified Establishments",
    "sg:phone":"+32 9 348 42 65",
    "sg:postcode":"9160",
    "sg:province":"Oost-Vlaanderen",
    "wof:name":"Window Luxe Bvba",
    "wof:placetype":"venue"
},
  "geometry": {"coordinates":[4.003054142,51.104801178],"type":"Point"}
}