{
  "type": "Feature",
  "properties": {
    "iso:country":"BE",
    "sg:address":"Rue De Bordeaux 45b15",
    "sg:city":"Sint-gillis/saint-gilles",
    "sg:orig_category":"Instituts de beaut\u00e9",
    "sg:phone":"+32 2 538 18 43",
    "sg:postcode":"1060",
    "sg:province":"Bruxelles-Capitale",
    "wof:name":"P\u00c9dicure De Decker",
    "wof:placetype":"venue"
},
  "geometry": {"coordinates":[4.3532061577,50.8294715881],"type":"Point"}
}