{
  "type": "Feature",
  "properties": {
    "iso:country":"BE",
    "sg:address":"Duinenstraat 294",
    "sg:city":"Bredene",
    "sg:classifiers":[
        {
            "category":"Food & Beverages",
            "subcategory":"Fruits & Vegetables",
            "type":"Retail Goods"
        }
    ],
    "sg:phone":"+32 59 33 11 34",
    "sg:postcode":"8450",
    "sg:province":"West-Vlaanderen",
    "sg:tags":[
        "-"
    ],
    "wof:name":"Fruitpaleis ('t)",
    "wof:placetype":"venue"
},
  "geometry": {"coordinates":[2.9630610943,51.2455825806],"type":"Point"}
}