{
  "type": "Feature",
  "properties": {
    "addr:full":"Vekenstraat 12 Nijlen Antwerpen 2560",
    "addr:housenumber":"12",
    "addr:postcode":"2560",
    "addr:street":"Vekenstraat",
    "iso:country":"BE",
    "sg:address":"Vekenstraat 12",
    "sg:city":"Nijlen",
    "sg:classifiers":[
        {
            "category":"Building & Trades",
            "subcategory":"Pest Control",
            "type":"Services"
        }
    ],
    "sg:phone":"+32 3 411 24 04",
    "sg:postcode":"2560",
    "sg:province":"Antwerpen",
    "sg:tags":[
        "painting",
        "contractor"
    ],
    "wof:name":"Algemene Schilderwerken A.s.m.k. Bvba",
    "wof:placetype":"venue"
},
  "geometry": {"coordinates":[4.6647348404,51.1561126709],"type":"Point"}
}