{
  "type": "Feature",
  "properties": {
    "iso:country":"BE",
    "sg:address":"Eikevelden 21",
    "sg:city":"Geel",
    "sg:orig_category":"HUISBRANDOLIE",
    "sg:phone":"+32 14 58 80 74",
    "sg:postcode":"2440",
    "sg:province":"Antwerpen",
    "wof:name":"Joris",
    "wof:placetype":"venue"
},
  "geometry": {"coordinates":[4.9958372116,51.154800415],"type":"Point"}
}