{
  "type": "Feature",
  "properties": {
    "addr:full":"Veldeke 3 Dilbeek Vlaams-Brabant 1700",
    "addr:housenumber":"3",
    "addr:postcode":"1700",
    "addr:street":"Veldeke",
    "iso:country":"BE",
    "sg:address":"Veldeke 3",
    "sg:city":"Dilbeek",
    "sg:orig_category":"Woningbouw",
    "sg:phone":"+32 2 466 77 17",
    "sg:postcode":"1700",
    "sg:province":"Vlaams-Brabant",
    "wof:name":"Dilbeco",
    "wof:placetype":"venue"
},
  "geometry": {"coordinates":[4.2373681068,50.8580932617],"type":"Point"}
}