{
  "type": "Feature",
  "properties": {
    "addr:full":"Fonteinstraat 137 Box 2 Leuven Vlaams-Brabant 3000",
    "addr:housenumber":"137;2",
    "addr:postcode":"3000",
    "addr:street":"Fonteinstraat;Box",
    "iso:country":"BE",
    "sg:address":"Fonteinstraat 137 Box 2",
    "sg:city":"Leuven",
    "sg:classifiers":[
        {
            "category":"Professional",
            "subcategory":"Art Services",
            "type":"Services"
        }
    ],
    "sg:phone":"+32 16 20 35 32",
    "sg:postcode":"3000",
    "sg:province":"Vlaams-Brabant",
    "sg:tags":[
        "-",
        "painter",
        "artist"
    ],
    "wof:name":"Sperans F",
    "wof:placetype":"venue"
},
  "geometry": {"coordinates":[4.6936531067,50.8812141418],"type":"Point"}
}