{
  "type": "Feature",
  "properties": {
    "addr:full":"Kachtemsestraat 292 Roeselare West-Vlaanderen 8800",
    "addr:housenumber":"292",
    "addr:postcode":"8800",
    "addr:street":"Kachtemsestraat",
    "iso:country":"BE",
    "sg:address":"Kachtemsestraat 292",
    "sg:city":"Roeselare",
    "sg:classifiers":[
        {
            "category":"Retail",
            "subcategory":"Repair Shop",
            "type":"Services"
        }
    ],
    "sg:phone":"+32 51 22 91 27",
    "sg:postcode":"8800",
    "sg:province":"West-Vlaanderen",
    "sg:tags":[
        "jobbing",
        "tailoring",
        "-"
    ],
    "wof:name":"Wamotex",
    "wof:placetype":"venue"
},
  "geometry": {"coordinates":[3.1624639034,50.9460830688],"type":"Point"}
}