{
  "type": "Feature",
  "properties": {
    "addr:full":"Boulevard Adolphe Max 105 Bruxelles Bruxelles-Capitale 1000",
    "addr:housenumber":"105",
    "addr:postcode":"1000",
    "addr:street":"Boulevard Adolphe Max",
    "iso:country":"BE",
    "sg:address":"Boulevard Adolphe Max 105",
    "sg:city":"Bruxelles",
    "sg:classifiers":[
        {
            "category":"Shopping",
            "subcategory":"Antiques",
            "type":"Retail Goods"
        }
    ],
    "sg:phone":"+32 2 223 02 41",
    "sg:postcode":"1000",
    "sg:province":"Bruxelles-Capitale",
    "wof:name":"Tshuapa",
    "wof:placetype":"venue"
},
  "geometry": {"coordinates":[4.356607914,50.8541717529],"type":"Point"}
}