{
  "type": "Feature",
  "properties": {
    "addr:full":"Rue Du Beau-vallon 218 Namur Namur 5002",
    "addr:housenumber":"218",
    "addr:postcode":"5002",
    "addr:street":"Rue Du Beau-Vallon",
    "iso:country":"BE",
    "sg:address":"Rue Du Beau-vallon 218",
    "sg:city":"Namur",
    "sg:orig_category":"Epiceries",
    "sg:phone":"+32 81 74 04 82",
    "sg:postcode":"5002",
    "sg:province":"Namur",
    "wof:name":"Pascal Maeck",
    "wof:placetype":"venue"
},
  "geometry": {"coordinates":[4.838572979,50.4757652283],"type":"Point"}
}