{
  "type": "Feature",
  "properties": {
    "iso:country":"BE",
    "sg:address":"Rue Des Bach\u00c8res 128",
    "sg:city":"Sambreville",
    "sg:orig_category":"Epiceries",
    "sg:phone":"+32 71 77 43 51",
    "sg:postcode":"5060",
    "sg:province":"Namur",
    "wof:name":"Carat",
    "wof:placetype":"venue"
},
  "geometry": {"coordinates":[4.58893013,50.4367599487],"type":"Point"}
}