{
  "type": "Feature",
  "properties": {
    "iso:country":"BE",
    "sg:address":"Reytstraat 232",
    "sg:city":"Oudenaarde",
    "sg:classifiers":[
        {
            "category":"Bakery",
            "type":"Food & Drink"
        }
    ],
    "sg:phone":"+32 55 49 92 12",
    "sg:postcode":"9700",
    "sg:province":"Oost-Vlaanderen",
    "sg:tags":[
        "confectioner",
        "baker"
    ],
    "wof:name":"Contreras Bvba",
    "wof:placetype":"venue"
},
  "geometry": {"coordinates":[3.6475811005,50.8763847351],"type":"Point"}
}