{
  "type": "Feature",
  "properties": {
    "iso:country":"BE",
    "sg:address":"Rinfosse 10",
    "sg:city":"Gesves",
    "sg:orig_category":"Artsen and specialisten",
    "sg:phone":"+32 83 67 83 79",
    "sg:postcode":"5340",
    "sg:province":"Namur",
    "wof:name":"Guy Jacob",
    "wof:placetype":"venue"
},
  "geometry": {"coordinates":[5.0721411705,50.4166641235],"type":"Point"}
}