{
  "type": "Feature",
  "properties": {
    "addr:full":"Overheulestraat 2 Wevelgem West-Vlaanderen 8560",
    "addr:housenumber":"2",
    "addr:postcode":"8560",
    "addr:street":"Overheulestraat",
    "iso:country":"BE",
    "sg:address":"Overheulestraat 2",
    "sg:city":"Wevelgem",
    "sg:orig_category":"Fournitures de bureau. Journaux. Tabac",
    "sg:phone":"+32 56 41 19 21",
    "sg:postcode":"8560",
    "sg:province":"West-Vlaanderen",
    "wof:name":"Decroix",
    "wof:placetype":"venue"
},
  "geometry": {"coordinates":[3.1646180153,50.8407096863],"type":"Point"}
}