{
  "type": "Feature",
  "properties": {
    "iso:country":"BE",
    "sg:address":"Quai Du Barrage 45",
    "sg:city":"Vis\u00e9",
    "sg:classifiers":[
        {
            "category":"Freight",
            "type":"Transportation"
        }
    ],
    "sg:phone":"+32 4 379 55 25",
    "sg:postcode":"4600",
    "sg:province":"Li\u00e8ge",
    "sg:tags":[
        "express",
        "transport"
    ],
    "wof:name":"Gedy Transport Express",
    "wof:placetype":"venue"
},
  "geometry": {"coordinates":[5.6952648163,50.7378158569],"type":"Point"}
}