{
  "type": "Feature",
  "properties": {
    "addr:full":"Oppiterpoort 13b2 Bree Limburg 3960",
    "addr:housenumber":"13b2",
    "addr:postcode":"3960",
    "addr:street":"Oppiterpoort",
    "iso:country":"BE",
    "sg:address":"Oppiterpoort 13b2",
    "sg:city":"Bree",
    "sg:orig_category":"M\u00e9decines alternatives",
    "sg:phone":"+32 89 46 70 46",
    "sg:postcode":"3960",
    "sg:province":"Limburg",
    "wof:name":"Dokter Kimpe Emmanuel",
    "wof:placetype":"venue"
},
  "geometry": {"coordinates":[5.6019349098,51.1401557922],"type":"Point"}
}