{
  "type": "Feature",
  "properties": {
    "addr:full":"Sint-amandsplein 25 Grimbergen Vlaams-Brabant 1853",
    "addr:housenumber":"25",
    "addr:postcode":"1853",
    "addr:street":"Sint-Amandsplein",
    "iso:country":"BE",
    "sg:address":"Sint-amandsplein 25",
    "sg:city":"Grimbergen",
    "sg:classifiers":[
        {
            "category":"Cafe",
            "type":"Food & Drink"
        }
    ],
    "sg:phone":"+32 2 267 78 23",
    "sg:postcode":"1853",
    "sg:province":"Vlaams-Brabant",
    "sg:tags":[
        "caf\u00e9s"
    ],
    "wof:name":"Caf\u00c9 Studs",
    "wof:placetype":"venue"
},
  "geometry": {"coordinates":[4.3553171158,50.9102973938],"type":"Point"}
}