{
  "type": "Feature",
  "properties": {
    "iso:country":"BE",
    "sg:address":"Jozef Suv\u00c9estraat 1b1",
    "sg:city":"Brugge",
    "sg:orig_category":"Hout and afgeleiden Gh IJzerwaren, bouw- and verfmaterialen",
    "sg:phone":"+32 50 33 14 39",
    "sg:postcode":"8000",
    "sg:province":"West-Vlaanderen",
    "wof:name":"Guy Plasschaert",
    "wof:placetype":"venue"
},
  "geometry": {"coordinates":[3.2286849022,51.2075881958],"type":"Point"}
}