{
  "type": "Feature",
  "properties": {
    "iso:country":"BE",
    "sg:address":"Steenovenstraat 57",
    "sg:city":"Tielt",
    "sg:orig_category":"Stations-service and carburants. Articles de jardin",
    "sg:phone":"+32 51 40 26 72",
    "sg:postcode":"8700",
    "sg:province":"West-Vlaanderen",
    "wof:name":"Vanbiesbrouck E. & P.",
    "wof:placetype":"venue"
},
  "geometry": {"coordinates":[3.3203930855,50.9956626892],"type":"Point"}
}