{
  "type": "Feature",
  "properties": {
    "addr:full":"Rue De Dinant 5 Ophain-bois-seigneur-isaac Brabant Wallon 1421",
    "addr:housenumber":"5",
    "addr:postcode":"1421",
    "addr:street":"Rue De Dinant",
    "iso:country":"BE",
    "sg:address":"Rue De Dinant 5",
    "sg:city":"Ophain-bois-seigneur-isaac",
    "sg:orig_category":"Office, Building, Fa\u00e7ade, Industry, Hospital Cleaning Services",
    "sg:phone":"+32 2 384 98 76",
    "sg:postcode":"1421",
    "sg:province":"Brabant Wallon",
    "wof:name":"Clean-up S.a.",
    "wof:placetype":"venue"
},
  "geometry": {"coordinates":[4.3447260857,50.6623802185],"type":"Point"}
}