{
  "type": "Feature",
  "properties": {
    "addr:full":"Achteraard 5 Hoogstraten Antwerpen 2322",
    "addr:housenumber":"5",
    "addr:postcode":"2322",
    "addr:street":"Achteraard",
    "iso:country":"BE",
    "sg:address":"Achteraard 5",
    "sg:city":"Hoogstraten",
    "sg:orig_category":"Eleveurs and marchands de porcs",
    "sg:phone":"+32 3 314 54 76",
    "sg:postcode":"2322",
    "sg:province":"Antwerpen",
    "wof:name":"Jozef Adams",
    "wof:placetype":"venue"
},
  "geometry": {"coordinates":[4.763384819,51.4160041809],"type":"Point"}
}