{
  "type": "Feature",
  "properties": {
    "iso:country":"BE",
    "sg:address":"Statiestraat 39",
    "sg:city":"Moerbeke (moerbeke-waas)",
    "sg:classifiers":[
        {
            "category":"Professional",
            "subcategory":"Accounting & Tax Preparation",
            "type":"Services"
        }
    ],
    "sg:phone":"+32 9 346 65 14",
    "sg:postcode":"9180",
    "sg:province":"Oost-Vlaanderen",
    "sg:tags":[
        "bookkeeper"
    ],
    "wof:name":"B-fak Bvba - De Maesschalck P",
    "wof:placetype":"venue"
},
  "geometry": {"coordinates":[3.9333848953,51.174949646],"type":"Point"}
}