{
  "type": "Feature",
  "properties": {
    "iso:country":"BE",
    "sg:address":"Rue De Limbourg 214",
    "sg:city":"Verviers",
    "sg:classifiers":[
        {
            "category":"Retail",
            "subcategory":"Auto Repair",
            "type":"Services"
        }
    ],
    "sg:phone":"+32 87 44 77 55",
    "sg:postcode":"4800",
    "sg:province":"Li\u00e8ge",
    "sg:tags":[
        "garage"
    ],
    "wof:name":"Garage Du Rocher",
    "wof:placetype":"venue"
},
  "geometry": {"coordinates":[5.889289856,50.6020317078],"type":"Point"}
}