{
  "type": "Feature",
  "properties": {
    "iso:country":"BE",
    "sg:address":"Chauss\u00e9e De Wavre 39",
    "sg:city":"Jodoigne",
    "sg:classifiers":[
        {
            "category":"Government",
            "subcategory":"Post Office",
            "type":"Public Place"
        }
    ],
    "sg:phone":"+32 10 81 40 70",
    "sg:postcode":"1370",
    "sg:province":"Brabant Wallon",
    "sg:tags":[
        "yoga"
    ],
    "wof:name":"Centre Santosha Asbl",
    "wof:placetype":"venue"
},
  "geometry": {"coordinates":[4.8606729507,50.7237663269],"type":"Point"}
}