{
  "type": "Feature",
  "properties": {
    "addr:full":"Oostereindestraat 46 Lummen Limburg 3560",
    "addr:housenumber":"46",
    "addr:postcode":"3560",
    "addr:street":"Oostereindestraat",
    "iso:country":"BE",
    "sg:address":"Oostereindestraat 46",
    "sg:city":"Lummen",
    "sg:orig_category":"Fournitures de bureau. Syst\u00e8mes de t\u00e9l\u00e9communications. Mat\u00e9riel de T\u00e9l\u00e9communication. Ordinateurs an",
    "sg:phone":"+32 13 53 13 83",
    "sg:postcode":"3560",
    "sg:province":"Limburg",
    "wof:name":"Pressmatic",
    "wof:placetype":"venue"
},
  "geometry": {"coordinates":[5.1998181343,50.9886436462],"type":"Point"}
}