{
  "type": "Feature",
  "properties": {
    "iso:country":"BE",
    "sg:address":"Chauss\u00e9e Du Roi Baudouin 276",
    "sg:city":"Mons (saint-symphorien)",
    "sg:classifiers":[
        {
            "category":"Home & Garden",
            "subcategory":"Building Materials",
            "type":"Retail Goods"
        }
    ],
    "sg:phone":"+32 65 32 85 00",
    "sg:postcode":"7030",
    "sg:province":"Hainaut",
    "sg:tags":[
        "wall",
        "cupboard"
    ],
    "wof:name":"Espace Int\u00e9rieur",
    "wof:placetype":"venue"
},
  "geometry": {"coordinates":[4.0108299255,50.4393882751],"type":"Point"}
}