{
  "type": "Feature",
  "properties": {
    "addr:full":"Boulevard De L'europe 29b14 Braine-l'alleud Brabant Wallon 1420",
    "addr:housenumber":"29b14",
    "addr:postcode":"1420",
    "addr:street":"Boulevard De L'Europe",
    "iso:country":"BE",
    "sg:address":"Boulevard De L'europe 29b14",
    "sg:city":"Braine-l'alleud",
    "sg:orig_category":"Installatie van houten of kunststof schrijnwerk Loodgieterij, verwarming and sanitaire installaties",
    "sg:phone":"+32 2 385 06 45",
    "sg:postcode":"1420",
    "sg:province":"Brabant Wallon",
    "wof:name":"Philippe Halin",
    "wof:placetype":"venue"
},
  "geometry": {"coordinates":[7.8578400612,52.9761810303],"type":"Point"}
}