{
  "type": "Feature",
  "properties": {
    "addr:full":"Grand Route 99 Sprimont (rouvreux) Li\u00e8ge 4140",
    "addr:postcode":"4140",
    "addr:street":"Grand Route 99;Rouvreux",
    "iso:country":"BE",
    "sg:address":"Grand Route 99",
    "sg:city":"Sprimont (rouvreux)",
    "sg:classifiers":[
        {
            "category":"Sports & Exercise",
            "subcategory":"Gym",
            "type":"Entertainment"
        }
    ],
    "sg:phone":"+32 4 384 88 08",
    "sg:postcode":"4140",
    "sg:province":"Li\u00e8ge",
    "sg:tags":[
        "fitness"
    ],
    "wof:name":"Fitness Form",
    "wof:placetype":"venue"
},
  "geometry": {"coordinates":[5.665140152,50.4807319641],"type":"Point"}
}