{
  "type": "Feature",
  "properties": {
    "addr:full":"Rue Grande 46 Tellin Luxembourg 6927",
    "addr:housenumber":"46",
    "addr:postcode":"6927",
    "addr:street":"Rue Grande",
    "iso:country":"BE",
    "sg:address":"Rue Grande 46",
    "sg:city":"Tellin",
    "sg:orig_category":"Postkantoren Verzekeringsmakelaars and experts",
    "sg:phone":"+32 84 36 61 29",
    "sg:postcode":"6927",
    "sg:province":"Luxembourg",
    "wof:name":"La Poste",
    "wof:placetype":"venue"
},
  "geometry": {"coordinates":[5.2213277817,50.0823059082],"type":"Point"}
}