{
  "type": "Feature",
  "properties": {
    "iso:country":"BE",
    "sg:address":"Duinenstraat 245",
    "sg:city":"Bredene",
    "sg:orig_category":"Sportclubs",
    "sg:phone":"+32 59 32 22 51",
    "sg:postcode":"8450",
    "sg:province":"West-Vlaanderen",
    "wof:name":"Vriendenkring Maria-duyne",
    "wof:placetype":"venue"
},
  "geometry": {"coordinates":[2.964097023,51.2436752319],"type":"Point"}
}