{
  "type": "Feature",
  "properties": {
    "addr:full":"Strooiendorp 18 Evergem (sleidinge) Oost-Vlaanderen 9940",
    "addr:housenumber":"18",
    "addr:postcode":"9940",
    "addr:street":"Strooiendorp",
    "iso:country":"BE",
    "sg:address":"Strooiendorp 18",
    "sg:city":"Evergem (sleidinge)",
    "sg:classifiers":[
        {
            "category":"Professional",
            "subcategory":"Management & Consulting",
            "type":"Services"
        }
    ],
    "sg:phone":"+32 9 259 89 96",
    "sg:postcode":"9940",
    "sg:province":"Oost-Vlaanderen",
    "sg:tags":[
        "consultant",
        "agency",
        "advertising"
    ],
    "wof:name":"Bravura",
    "wof:placetype":"venue"
},
  "geometry": {"coordinates":[3.6641030312,51.1226577759],"type":"Point"}
}