{
  "type": "Feature",
  "properties": {
    "addr:full":"Appelkantstraat 10 Boechout Antwerpen 2530",
    "addr:housenumber":"10",
    "addr:postcode":"2530",
    "addr:street":"Appelkantstraat",
    "iso:country":"BE",
    "sg:address":"Appelkantstraat 10",
    "sg:city":"Boechout",
    "sg:classifiers":[
        {
            "category":"Professional",
            "subcategory":"Art Services",
            "type":"Services"
        }
    ],
    "sg:phone":"+32 3 455 10 61",
    "sg:postcode":"2530",
    "sg:province":"Antwerpen",
    "sg:tags":[
        "-",
        "painter",
        "artist"
    ],
    "wof:name":"Blommaerts F",
    "wof:placetype":"venue"
},
  "geometry": {"coordinates":[4.4897518158,51.1605453491],"type":"Point"}
}