{
  "type": "Feature",
  "properties": {
    "iso:country":"BE",
    "sg:address":"Chauss\u00e9e De Charleroi 425",
    "sg:city":"Fosses-la-ville",
    "sg:classifiers":[
        {
            "category":"Building & Trades",
            "subcategory":"Electrical",
            "type":"Services"
        }
    ],
    "sg:phone":"+32 71 71 30 31",
    "sg:postcode":"5070",
    "sg:province":"Namur",
    "sg:tags":[
        "electric",
        "-",
        "housewiring",
        "contractor"
    ],
    "wof:name":"Saublens M",
    "wof:placetype":"venue"
},
  "geometry": {"coordinates":[4.6720647812,50.3931503296],"type":"Point"}
}