{
  "type": "Feature",
  "properties": {
    "addr:full":"Rue Groeselenberg 37 Ukkel/uccle Bruxelles-Capitale 1180",
    "addr:housenumber":"37",
    "addr:postcode":"1180",
    "addr:street":"Rue Groeselenberg;/",
    "iso:country":"BE",
    "sg:address":"Rue Groeselenberg 37",
    "sg:city":"Ukkel/uccle",
    "sg:orig_category":"Agences de relations publiques",
    "sg:phone":"+32 2 375 58 02",
    "sg:postcode":"1180",
    "sg:province":"Bruxelles-Capitale",
    "wof:name":"Vandenkerckhove",
    "wof:placetype":"venue"
},
  "geometry": {"coordinates":[4.3518371582,50.8025512695],"type":"Point"}
}