{
  "type": "Feature",
  "properties": {
    "iso:country":"BE",
    "sg:address":"Gentbruggestraat 12",
    "sg:city":"Gent (sint-amandsberg)",
    "sg:classifiers":[
        {
            "category":"Retail",
            "subcategory":"Auto Repair",
            "type":"Services"
        }
    ],
    "sg:phone":"+32 9 228 64 45",
    "sg:postcode":"9040",
    "sg:province":"Oost-Vlaanderen",
    "sg:tags":[
        "automobile-body"
    ],
    "wof:name":"Van De Woestijne J",
    "wof:placetype":"venue"
},
  "geometry": {"coordinates":[3.7520420551,51.0518951416],"type":"Point"}
}