{
  "type": "Feature",
  "properties": {
    "addr:full":"Dambruggestraat 255 Antwerpen Antwerpen 2060",
    "addr:housenumber":"255",
    "addr:postcode":"2060",
    "addr:street":"Dambruggestraat",
    "iso:country":"BE",
    "sg:address":"Dambruggestraat 255",
    "sg:city":"Antwerpen",
    "sg:classifiers":[
        {
            "category":"Insurance",
            "subcategory":"Insurance Agent",
            "type":"Services"
        }
    ],
    "sg:phone":"+32 3 233 29 32",
    "sg:postcode":"2060",
    "sg:province":"Antwerpen",
    "sg:tags":[
        "broker"
    ],
    "wof:name":"Safa",
    "wof:placetype":"venue"
},
  "geometry": {"coordinates":[4.4218139648,51.2265548706],"type":"Point"}
}