{
  "type": "Feature",
  "properties": {
    "addr:full":"Avenue Du Centenaire 12 Charleroi Hainaut 6061",
    "addr:housenumber":"12",
    "addr:postcode":"6061",
    "addr:street":"Avenue Du Centenaire;Hainaut",
    "iso:country":"BE",
    "sg:address":"Avenue Du Centenaire 12",
    "sg:city":"Charleroi",
    "sg:orig_category":"Quincailleries",
    "sg:phone":"+32 71 31 11 11",
    "sg:postcode":"6061",
    "sg:province":"Hainaut",
    "wof:name":"Balleux",
    "wof:placetype":"venue"
},
  "geometry": {"coordinates":[4.479224205,50.4014396667],"type":"Point"}
}