{
  "type": "Feature",
  "properties": {
    "iso:country":"BE",
    "sg:address":"Huivelde 108",
    "sg:city":"Zele",
    "sg:orig_category":"Services pour animaux domestiques",
    "sg:phone":"+32 52 45 27 46",
    "sg:postcode":"9240",
    "sg:province":"Oost-Vlaanderen",
    "wof:name":"K.belg.verb.besch.vogels",
    "wof:placetype":"venue"
},
  "geometry": {"coordinates":[4.0672960281,51.0637893677],"type":"Point"}
}