{
  "type": "Feature",
  "properties": {
    "addr:full":"Mandeldreef 66 Roeselare West-Vlaanderen 8800",
    "addr:housenumber":"66",
    "addr:postcode":"8800",
    "addr:street":"Mandeldreef",
    "iso:country":"BE",
    "sg:address":"Mandeldreef 66",
    "sg:city":"Roeselare",
    "sg:orig_category":"Cr\u00e8ches and garderies d'enfants",
    "sg:phone":"+32 51 20 34 18",
    "sg:postcode":"8800",
    "sg:province":"West-Vlaanderen",
    "wof:name":"Kribbe Schanulleke",
    "wof:placetype":"venue"
},
  "geometry": {"coordinates":[3.1349229813,50.9536552429],"type":"Point"}
}