{
  "type": "Feature",
  "properties": {
    "iso:country":"BE",
    "sg:address":"Hamonterweg 134",
    "sg:city":"Neerpelt",
    "sg:classifiers":[
        {
            "category":"Retail",
            "subcategory":"Auto Repair",
            "type":"Services"
        }
    ],
    "sg:phone":"+32 11 64 14 82",
    "sg:postcode":"3910",
    "sg:province":"Limburg",
    "sg:tags":[
        "garage"
    ],
    "wof:name":"Hendrikx Bvba",
    "wof:placetype":"venue"
},
  "geometry": {"coordinates":[5.463739872,51.2380409241],"type":"Point"}
}