{
  "type": "Feature",
  "properties": {
    "addr:full":"Kraaienhoflaan 5 Zwijndrecht Antwerpen 2070",
    "addr:housenumber":"5",
    "addr:postcode":"2070",
    "addr:street":"Kraaienhoflaan",
    "iso:country":"BE",
    "sg:address":"Kraaienhoflaan 5",
    "sg:city":"Zwijndrecht",
    "sg:classifiers":[
        {
            "category":"Arena",
            "subcategory":"Sports Club",
            "type":"Entertainment"
        }
    ],
    "sg:phone":"+32 3 252 63 85",
    "sg:postcode":"2070",
    "sg:province":"Antwerpen",
    "sg:tags":[
        "de"
    ],
    "wof:name":"International Dive School Antwerp",
    "wof:placetype":"venue"
},
  "geometry": {"coordinates":[4.3429732323,51.2068367004],"type":"Point"}
}