{
  "type": "Feature",
  "properties": {
    "addr:full":"Raerenerstrasse 26 Raeren Li\u00e8ge 4731",
    "addr:housenumber":"26",
    "addr:postcode":"4731",
    "addr:street":"Raerenerstrasse",
    "iso:country":"BE",
    "sg:address":"Raerenerstrasse 26",
    "sg:city":"Raeren",
    "sg:orig_category":"Slagers",
    "sg:phone":"+32 87 85 24 76",
    "sg:postcode":"4731",
    "sg:province":"Li\u00e8ge",
    "wof:name":"Metzgerei Schoorel",
    "wof:placetype":"venue"
},
  "geometry": {"coordinates":[6.0827941895,50.6918411255],"type":"Point"}
}