{
  "type": "Feature",
  "properties": {
    "addr:full":"Rue De Scailmont 56 Manage Hainaut 7170",
    "addr:housenumber":"56",
    "addr:postcode":"7170",
    "addr:street":"Rue De Scailmont",
    "iso:country":"BE",
    "sg:address":"Rue De Scailmont 56",
    "sg:city":"Manage",
    "sg:orig_category":"Enseignement secondaire technique and professionnel",
    "sg:phone":"+32 64 57 03 24",
    "sg:postcode":"7170",
    "sg:province":"Hainaut",
    "wof:name":"Inst. Prov. De Nursing",
    "wof:placetype":"venue"
},
  "geometry": {"coordinates":[4.2327899933,50.5008239746],"type":"Point"}
}