{
  "type": "Feature",
  "properties": {
    "iso:country":"BE",
    "sg:address":"Sint-hubertstraat 283",
    "sg:city":"Deinze",
    "sg:orig_category":"Woningbouw",
    "sg:phone":"+32 9 386 83 28",
    "sg:postcode":"9800",
    "sg:province":"Oost-Vlaanderen",
    "wof:name":"Teirlinck",
    "wof:placetype":"venue"
},
  "geometry": {"coordinates":[3.512305975,50.9616317749],"type":"Point"}
}