{
  "type": "Feature",
  "properties": {
    "iso:country":"BE",
    "sg:address":"Tintange 0",
    "sg:city":"Fauvillers",
    "sg:orig_category":"H\u00f4tels. Restaurants",
    "sg:phone":"+32 63 60 02 11",
    "sg:postcode":"6637",
    "sg:province":"Luxembourg",
    "wof:name":"Hostellerie Moulin D'oeil",
    "wof:placetype":"venue"
},
  "geometry": {"coordinates":[5.7504038811,49.8822898865],"type":"Point"}
}