{
  "type": "Feature",
  "properties": {
    "iso:country":"BE",
    "sg:address":"Rue De Chi\u00c8vres 291",
    "sg:city":"Saint-ghislain",
    "sg:classifiers":[
        {
            "category":"Fast Food",
            "type":"Food & Drink"
        }
    ],
    "sg:phone":"+32 65 62 13 74",
    "sg:postcode":"7332",
    "sg:province":"Hainaut",
    "sg:tags":[
        "restaurant",
        "\u00c0",
        "domicile",
        "emporter",
        "livraison",
        "restaurants"
    ],
    "wof:name":"Le Noir Bonnet",
    "wof:placetype":"venue"
},
  "geometry": {"coordinates":[3.786839962,50.5054969788],"type":"Point"}
}