{
  "type": "Feature",
  "properties": {
    "iso:country":"BE",
    "sg:address":"Steenpaal 11",
    "sg:city":"Essen",
    "sg:orig_category":"HUISBRANDOLIE",
    "sg:phone":"+32 3 677 00 45",
    "sg:postcode":"2910",
    "sg:province":"Antwerpen",
    "wof:name":"Van Aert Ludovicus",
    "wof:placetype":"venue"
},
  "geometry": {"coordinates":[4.4897818565,51.4751586914],"type":"Point"}
}