{
  "type": "Feature",
  "properties": {
    "iso:country":"BE",
    "sg:address":"Noordstraat 170",
    "sg:city":"Maldegem",
    "sg:orig_category":"Entretien and r\u00e9parations de voitures",
    "sg:phone":"+32 50 71 45 62",
    "sg:postcode":"9990",
    "sg:province":"Oost-Vlaanderen",
    "wof:name":"Rik Missiaen",
    "wof:placetype":"venue"
},
  "geometry": {"coordinates":[3.4467511177,51.2159500122],"type":"Point"}
}