{
  "type": "Feature",
  "properties": {
    "iso:country":"BE",
    "sg:address":"Rue De Marcinelle 93",
    "sg:city":"Charleroi (mont-sur-marchienne)",
    "sg:classifiers":[
        {
            "category":"Fast Food",
            "type":"Food & Drink"
        }
    ],
    "sg:phone":"+32 71 36 65 15",
    "sg:postcode":"6032",
    "sg:province":"Hainaut",
    "sg:tags":[
        "fried",
        "stand",
        "potato"
    ],
    "wof:name":"Terrasse (la)",
    "wof:placetype":"venue"
},
  "geometry": {"coordinates":[4.4172282219,50.375705719],"type":"Point"}
}