{
  "type": "Feature",
  "properties": {
    "iso:country":"BE",
    "sg:address":"Koning Leopold 1 Straat 1 A 25",
    "sg:city":"Leuven",
    "sg:orig_category":"Microsoft. Ordinateurs and \u00e9quipement informatique",
    "sg:phone":"+32 16 28 49 70",
    "sg:postcode":"3000",
    "sg:province":"Vlaams-Brabant",
    "wof:name":"Hegreso",
    "wof:placetype":"venue"
},
  "geometry": {"coordinates":[4.7080302238,50.8788490295],"type":"Point"}
}