{
  "type": "Feature",
  "properties": {
    "addr:full":"Driftweg 77 De Haan West-Vlaanderen 8420",
    "addr:housenumber":"77",
    "addr:postcode":"8420",
    "addr:street":"Driftweg",
    "iso:country":"BE",
    "sg:address":"Driftweg 77",
    "sg:city":"De Haan",
    "sg:orig_category":"Sportclubs",
    "sg:phone":"+32 59 23 54 05",
    "sg:postcode":"8420",
    "sg:province":"West-Vlaanderen",
    "wof:name":"Steunkr.opvangcentr.mpigo",
    "wof:placetype":"venue"
},
  "geometry": {"coordinates":[3.0214669704,51.2676849365],"type":"Point"}
}