{
  "type": "Feature",
  "properties": {
    "addr:full":"Moerestraat 5 Koekelare West-Vlaanderen 8680",
    "addr:housenumber":"5",
    "addr:postcode":"8680",
    "addr:street":"Moerestraat",
    "iso:country":"BE",
    "sg:address":"Moerestraat 5",
    "sg:city":"Koekelare",
    "sg:orig_category":"Pharmaciens",
    "sg:phone":"+32 51 58 80 39",
    "sg:postcode":"8680",
    "sg:province":"West-Vlaanderen",
    "wof:name":"Norbert Debruyne",
    "wof:placetype":"venue"
},
  "geometry": {"coordinates":[2.9780390263,51.0905990601],"type":"Point"}
}