{
  "type": "Feature",
  "properties": {
    "iso:country":"BE",
    "sg:address":"Rue Du Postillon 31",
    "sg:city":"Bruxelles (uccle)",
    "sg:classifiers":[
        {
            "category":"Transit Center",
            "subcategory":"Freight",
            "type":"Transportation"
        }
    ],
    "sg:phone":"+32 2 343 42 49",
    "sg:postcode":"1180",
    "sg:province":"Bruxelles-Capitale",
    "sg:tags":[
        "import",
        "export",
        "-"
    ],
    "wof:name":"M.a.i.",
    "wof:placetype":"venue"
},
  "geometry": {"coordinates":[4.3398799896,50.8021430969],"type":"Point"}
}