{
  "type": "Feature",
  "properties": {
    "iso:country":"BE",
    "sg:address":"Nieuwstraat 60",
    "sg:city":"Denderleeuw",
    "sg:orig_category":"Kunstonderwijs",
    "sg:phone":"+32 53 66 21 11",
    "sg:postcode":"9470",
    "sg:province":"Oost-Vlaanderen",
    "wof:name":"Academie Voor Muziek, Woord En Dans",
    "wof:placetype":"venue"
},
  "geometry": {"coordinates":[4.0725479126,50.8796043396],"type":"Point"}
}