{
  "type": "Feature",
  "properties": {
    "addr:full":"Groenstraat 12 Laarne Oost-Vlaanderen 9270",
    "addr:housenumber":"12",
    "addr:postcode":"9270",
    "addr:street":"Groenstraat",
    "iso:country":"BE",
    "sg:address":"Groenstraat 12",
    "sg:city":"Laarne",
    "sg:orig_category":"Afbraak- and draineerwerken",
    "sg:phone":"+32 9 355 10 90",
    "sg:postcode":"9270",
    "sg:province":"Oost-Vlaanderen",
    "wof:name":"Franky Roegiest",
    "wof:placetype":"venue"
},
  "geometry": {"coordinates":[3.8494389057,51.0541572571],"type":"Point"}
}