{
  "type": "Feature",
  "properties": {
    "addr:full":"Marktplein 12 Hechtel-eksel Limburg 3941",
    "addr:housenumber":"12",
    "addr:postcode":"3941",
    "addr:street":"Marktplein",
    "iso:country":"BE",
    "sg:address":"Marktplein 12",
    "sg:city":"Hechtel-eksel",
    "sg:classifiers":[
        {
            "category":"Autos & Motor Vehicles",
            "subcategory":"Fuel & Gas Station",
            "type":"Retail Goods"
        }
    ],
    "sg:phone":"+32 11 73 49 07",
    "sg:postcode":"3941",
    "sg:province":"Limburg",
    "sg:tags":[
        "stations-service",
        "carburants"
    ],
    "wof:name":"Pompstation Irliek",
    "wof:placetype":"venue"
},
  "geometry": {"coordinates":[5.394862175,51.1539764404],"type":"Point"}
}