{
  "type": "Feature",
  "properties": {
    "addr:full":"Rue Mont Saint-roch 19 Nivelles Brabant Wallon 1400",
    "addr:housenumber":"19",
    "addr:postcode":"1400",
    "addr:street":"Rue Mont Saint-Roch",
    "iso:country":"BE",
    "sg:address":"Rue Mont Saint-roch 19",
    "sg:city":"Nivelles",
    "sg:classifiers":[
        {
            "category":"Insurance",
            "subcategory":"Insurance Agent",
            "type":"Services"
        }
    ],
    "sg:phone":"+32 67 21 61 01",
    "sg:postcode":"1400",
    "sg:province":"Brabant Wallon",
    "sg:tags":[
        "verzekeringsmakelaars",
        "expert"
    ],
    "wof:name":"Tegias Gillard",
    "wof:placetype":"venue"
},
  "geometry": {"coordinates":[4.3197398186,50.6010284424],"type":"Point"}
}