{
  "type": "Feature",
  "properties": {
    "addr:full":"Rue De Wand 127 Bruxelles Bruxelles-Capitale 1020",
    "addr:housenumber":"127",
    "addr:postcode":"1020",
    "addr:street":"Rue De Wand",
    "iso:country":"BE",
    "sg:address":"Rue De Wand 127",
    "sg:city":"Bruxelles",
    "sg:classifiers":[
        {
            "category":"Building & Trades",
            "subcategory":"Locksmith",
            "type":"Services"
        }
    ],
    "sg:phone":"+32 2 262 05 21",
    "sg:postcode":"1020",
    "sg:province":"Bruxelles-Capitale",
    "sg:tags":[
        "lock",
        "key"
    ],
    "wof:name":"A. Vincent",
    "wof:placetype":"venue"
},
  "geometry": {"coordinates":[4.3597807884,50.8986320496],"type":"Point"}
}