{
  "type": "Feature",
  "properties": {
    "addr:full":"Brusselsesteenweg 72 Merchtem Vlaams-Brabant 1785",
    "addr:housenumber":"72",
    "addr:postcode":"1785",
    "addr:street":"Brusselsesteenweg",
    "iso:country":"BE",
    "sg:address":"Brusselsesteenweg 72",
    "sg:city":"Merchtem",
    "sg:orig_category":"Benzinestations and brandstoffen Herstellingen and onderhoud van auto's",
    "sg:phone":"+32 52 37 27 35",
    "sg:postcode":"1785",
    "sg:province":"Vlaams-Brabant",
    "wof:name":"All Car Yannick",
    "wof:placetype":"venue"
},
  "geometry": {"coordinates":[4.2405061722,50.9536476135],"type":"Point"}
}