{
  "type": "Feature",
  "properties": {
    "iso:country":"BE",
    "sg:address":"Abdijdreef 7bb",
    "sg:city":"Leuven",
    "sg:orig_category":"Enseignement sup\u00e9rieur",
    "sg:phone":"+32 16 39 86 60",
    "sg:postcode":"3001",
    "sg:province":"Vlaams-Brabant",
    "wof:name":"Katholieke Hogeschool",
    "wof:placetype":"venue"
},
  "geometry": {"coordinates":[4.7132549286,50.8618812561],"type":"Point"}
}