{
  "type": "Feature",
  "properties": {
    "iso:country":"BE",
    "sg:address":"Rue Des Marcottes 30",
    "sg:city":"Mons",
    "sg:classifiers":[
        {
            "category":"Professional",
            "subcategory":"Lawyer & Legal Services",
            "type":"Services"
        }
    ],
    "sg:phone":"+32 65 35 52 79",
    "sg:postcode":"7000",
    "sg:province":"Hainaut",
    "wof:name":"Brulard Y",
    "wof:placetype":"venue"
},
  "geometry": {"coordinates":[3.953660965,50.4580574036],"type":"Point"}
}