{
  "type": "Feature",
  "properties": {
    "iso:country":"BE",
    "sg:address":"Zandstraat 26",
    "sg:city":"Wijnegem",
    "sg:classifiers":[
        {
            "category":"Building & Trades",
            "subcategory":"Construction",
            "type":"Services"
        }
    ],
    "sg:phone":"+32 3 353 72 75",
    "sg:postcode":"2110",
    "sg:province":"Antwerpen",
    "sg:tags":[
        "carpenter"
    ],
    "wof:name":"Verhoeven & Zn",
    "wof:placetype":"venue"
},
  "geometry": {"coordinates":[4.5146551132,51.2299118042],"type":"Point"}
}