{
  "type": "Feature",
  "properties": {
    "addr:full":"Rue Des Clarisses 60b41 Li\u00c8ge Li\u00e8ge 4000",
    "addr:housenumber":"60b41",
    "addr:postcode":"4000",
    "addr:street":"Rue Des Clarisses",
    "iso:country":"BE",
    "sg:address":"Rue Des Clarisses 60b41",
    "sg:city":"Li\u00c8ge",
    "sg:orig_category":"Fotolaboratoria",
    "sg:phone":"+32 4 221 00 74",
    "sg:postcode":"4000",
    "sg:province":"Li\u00e8ge",
    "wof:name":"Ornella Flaiano",
    "wof:placetype":"venue"
},
  "geometry": {"coordinates":[5.5704870224,50.6385307312],"type":"Point"}
}