{
  "type": "Feature",
  "properties": {
    "iso:country":"BE",
    "sg:address":"Omgangstraat 170",
    "sg:city":"Zingem",
    "sg:classifiers":[
        {
            "category":"Retail",
            "subcategory":"Auto Repair",
            "type":"Services"
        }
    ],
    "sg:phone":"+32 9 390 80 64",
    "sg:postcode":"9750",
    "sg:province":"Oost-Vlaanderen",
    "sg:tags":[
        "garage"
    ],
    "wof:name":"Van Den Broecke M",
    "wof:placetype":"venue"
},
  "geometry": {"coordinates":[3.6530840397,50.8971748352],"type":"Point"}
}