{
  "type": "Feature",
  "properties": {
    "addr:full":"Grensstraat 6 Keerbergen Vlaams-Brabant 3140",
    "addr:housenumber":"6",
    "addr:postcode":"3140",
    "addr:street":"Grensstraat",
    "iso:country":"BE",
    "sg:address":"Grensstraat 6",
    "sg:city":"Keerbergen",
    "sg:orig_category":"Miscellaneous Products Paper and Cardboard Paper and cardboard - raw materials Printing",
    "sg:phone":"+32 15 50 41 90",
    "sg:postcode":"3140",
    "sg:province":"Vlaams-Brabant",
    "wof:name":"Demaran Nv",
    "wof:placetype":"venue"
},
  "geometry": {"coordinates":[4.6331119537,51.0158462524],"type":"Point"}
}