{
  "type": "Feature",
  "properties": {
    "iso:country":"BE",
    "sg:address":"Tinstraat 42",
    "sg:city":"Putte",
    "sg:orig_category":"Clubs de sport. Installations and terrains de sport hors centres sportifs. Centres sportifs. Caf\u00e9s. ",
    "sg:phone":"+32 15 76 76 00",
    "sg:postcode":"2580",
    "sg:province":"Antwerpen",
    "wof:name":"Greenhill",
    "wof:placetype":"venue"
},
  "geometry": {"coordinates":[4.6286678314,51.0405464172],"type":"Point"}
}