{
  "type": "Feature",
  "properties": {
    "iso:country":"BE",
    "sg:address":"Bosheidestraat 11",
    "sg:city":"Lummen",
    "sg:classifiers":[
        {
            "category":"Insurance",
            "subcategory":"Life Insurance",
            "type":"Services"
        }
    ],
    "sg:phone":"+32 11 43 12 02",
    "sg:postcode":"3560",
    "sg:province":"Limburg",
    "sg:tags":[
        "assurance"
    ],
    "wof:name":"Alenus & Partners",
    "wof:placetype":"venue"
},
  "geometry": {"coordinates":[5.2192292213,51.0076026917],"type":"Point"}
}