{
  "type": "Feature",
  "properties": {
    "addr:full":"Rue Fonds Delvaux 17 Profondeville (lustin) Namur 5170",
    "addr:housenumber":"17",
    "addr:postcode":"5170",
    "addr:street":"Rue Fonds Delvaux",
    "iso:country":"BE",
    "sg:address":"Rue Fonds Delvaux 17",
    "sg:city":"Profondeville (lustin)",
    "sg:orig_category":"Non-Classified Establishments",
    "sg:phone":"+32 81 41 25 03",
    "sg:postcode":"5170",
    "sg:province":"Namur",
    "wof:name":"Simon-tecnico",
    "wof:placetype":"venue"
},
  "geometry": {"coordinates":[4.8787870407,50.3618507385],"type":"Point"}
}