{
  "type": "Feature",
  "properties": {
    "addr:full":"Kruisekestraat 207 Wervik West-Vlaanderen 8940",
    "addr:housenumber":"207",
    "addr:postcode":"8940",
    "addr:street":"Kruisekestraat",
    "iso:country":"BE",
    "sg:address":"Kruisekestraat 207",
    "sg:city":"Wervik",
    "sg:orig_category":"Installatie van houten of kunststof schrijnwerk Installatie van metalen schrijnwerk Vloer- and muurb",
    "sg:phone":"+32 56 31 10 22",
    "sg:postcode":"8940",
    "sg:province":"West-Vlaanderen",
    "wof:name":"Vandaele",
    "wof:placetype":"venue"
},
  "geometry": {"coordinates":[3.0322630405,50.7899551392],"type":"Point"}
}