{
  "type": "Feature",
  "properties": {
    "addr:full":"Kloosterstraat 17 Lille Antwerpen 2275",
    "addr:housenumber":"17",
    "addr:postcode":"2275",
    "addr:street":"Kloosterstraat",
    "iso:country":"BE",
    "sg:address":"Kloosterstraat 17",
    "sg:city":"Lille",
    "sg:orig_category":"Banken and kredietinstellingen",
    "sg:phone":"+32 14 55 84 90",
    "sg:postcode":"2275",
    "sg:province":"Antwerpen",
    "wof:name":"Kbc",
    "wof:placetype":"venue"
},
  "geometry": {"coordinates":[4.8659219742,51.2655601501],"type":"Point"}
}