{
  "type": "Feature",
  "properties": {
    "addr:full":"Rue Joseph Leclercq 146 Beyne-heusay Li\u00e8ge 4610",
    "addr:housenumber":"146",
    "addr:postcode":"4610",
    "addr:street":"Rue Joseph Leclercq",
    "iso:country":"BE",
    "sg:address":"Rue Joseph Leclercq 146",
    "sg:city":"Beyne-heusay",
    "sg:classifiers":[
        {
            "category":"Government",
            "subcategory":"Fire Station",
            "type":"Public Place"
        }
    ],
    "sg:phone":"+32 2 410 25 45",
    "sg:postcode":"4610",
    "sg:province":"Li\u00e8ge",
    "sg:tags":[
        "heating",
        "accessory",
        "ventilation",
        "air conditioning"
    ],
    "wof:name":"Cevai Sprl / Bvba",
    "wof:placetype":"venue"
},
  "geometry": {"coordinates":[5.6675271988,50.626663208],"type":"Point"}
}