{
  "type": "Feature",
  "properties": {
    "iso:country":"BE",
    "sg:address":"Rue Pepin 32",
    "sg:city":"Pepinster",
    "sg:orig_category":"Plomberie, chauffage and installations sanitaires",
    "sg:phone":"+32 87 46 03 40",
    "sg:postcode":"4860",
    "sg:province":"Li\u00e8ge",
    "wof:name":"Ets. Welter-pelzer",
    "wof:placetype":"venue"
},
  "geometry": {"coordinates":[5.804008007,50.5671768188],"type":"Point"}
}