{
  "type": "Feature",
  "properties": {
    "addr:full":"Hoogboomsteenweg 94 Kapellen Antwerpen 2950",
    "addr:housenumber":"94",
    "addr:postcode":"2950",
    "addr:street":"Hoogboomsteenweg",
    "iso:country":"BE",
    "sg:address":"Hoogboomsteenweg 94",
    "sg:city":"Kapellen",
    "sg:classifiers":[
        {
            "category":"Restaurant",
            "type":"Food & Drink"
        }
    ],
    "sg:phone":"+32 3 605 95 00",
    "sg:postcode":"2950",
    "sg:province":"Antwerpen",
    "sg:tags":[
        "caf\u00e9s"
    ],
    "wof:name":"B.a.z. Invest",
    "wof:placetype":"venue"
},
  "geometry": {"coordinates":[4.4469342232,51.309879303],"type":"Point"}
}