{
  "type": "Feature",
  "properties": {
    "addr:full":"Tervuursesteenweg 84 Steenokkerzeel (perk) Vlaams-Brabant 1820",
    "addr:housenumber":"84",
    "addr:postcode":"1820",
    "addr:street":"Tervuursesteenweg",
    "iso:country":"BE",
    "sg:address":"Tervuursesteenweg 84",
    "sg:city":"Steenokkerzeel (perk)",
    "sg:classifiers":[
        {
            "category":"Health Services",
            "subcategory":"Dentist",
            "type":"Services"
        }
    ],
    "sg:phone":"+32 2 751 89 48",
    "sg:postcode":"1820",
    "sg:province":"Vlaams-Brabant",
    "wof:name":"Hendrickx E",
    "wof:placetype":"venue"
},
  "geometry": {"coordinates":[4.4991898537,50.9219589233],"type":"Point"}
}