{
  "type": "Feature",
  "properties": {
    "iso:country":"BE",
    "sg:address":"Heulentakstraat 10",
    "sg:city":"Dilsen-stokkem (dilsen)",
    "sg:classifiers":[
        {
            "category":"Building & Trades",
            "subcategory":"Construction",
            "type":"Services"
        }
    ],
    "sg:phone":"+32 89 79 13 41",
    "sg:postcode":"3650",
    "sg:province":"Limburg",
    "sg:tags":[
        "duct",
        "underground",
        "ducting"
    ],
    "wof:name":"Apc Nv",
    "wof:placetype":"venue"
},
  "geometry": {"coordinates":[5.6973948479,51.0471992493],"type":"Point"}
}