{
  "type": "Feature",
  "properties": {
    "iso:country":"BE",
    "sg:address":"Rue Beeckman 22",
    "sg:city":"Li\u00c8ge",
    "sg:orig_category":"Artsen and specialisten",
    "sg:phone":"+32 4 223 67 30",
    "sg:postcode":"4000",
    "sg:province":"Li\u00e8ge",
    "wof:name":"A. Courban",
    "wof:placetype":"venue"
},
  "geometry": {"coordinates":[5.5649957657,50.6359176636],"type":"Point"}
}