{
  "type": "Feature",
  "properties": {
    "addr:full":"Bergkapelstraat 38 Londerzeel Vlaams-Brabant 1840",
    "addr:housenumber":"38",
    "addr:postcode":"1840",
    "addr:street":"Bergkapelstraat",
    "iso:country":"BE",
    "sg:address":"Bergkapelstraat 38",
    "sg:city":"Londerzeel",
    "sg:classifiers":[
        {
            "category":"Manufacturing",
            "subcategory":"Glass & Minerals",
            "type":"Manufacturing & Wholesale Goods"
        }
    ],
    "sg:phone":"+32 477 33 23 89",
    "sg:postcode":"1840",
    "sg:province":"Vlaams-Brabant",
    "sg:tags":[
        "automobile",
        "-"
    ],
    "wof:name":"Auto Vitro",
    "wof:placetype":"venue"
},
  "geometry": {"coordinates":[4.3210310936,51.0075187683],"type":"Point"}
}