{
  "type": "Feature",
  "properties": {
    "iso:country":"BE",
    "sg:address":"Torenveld 3",
    "sg:city":"Tessenderlo",
    "sg:classifiers":[
        {
            "category":"Retail",
            "subcategory":"Auto Repair",
            "type":"Services"
        }
    ],
    "sg:phone":"+32 13 67 50 93",
    "sg:postcode":"3980",
    "sg:province":"Limburg",
    "sg:tags":[
        "lpg",
        "automobile",
        "-",
        "system"
    ],
    "wof:name":"Lpg Cars",
    "wof:placetype":"venue"
},
  "geometry": {"coordinates":[5.0799951553,51.0580062866],"type":"Point"}
}