{
  "type": "Feature",
  "properties": {
    "iso:country":"BE",
    "sg:address":"Chauss\u00c9e De Boondael 433",
    "sg:city":"Bruxelles-ixelles",
    "sg:orig_category":"Mat\u00e9riel de T\u00e9l\u00e9communication",
    "sg:phone":"+32 2 644 64 30",
    "sg:postcode":"1050",
    "sg:province":"Bruxelles-Capitale",
    "wof:name":"Mobistar Center Mobile Electronics",
    "wof:placetype":"venue"
},
  "geometry": {"coordinates":[4.3886408806,50.8169631958],"type":"Point"}
}