{
  "type": "Feature",
  "properties": {
    "addr:full":"Van Meterenkaai 4 Box 12 Antwerpen Antwerpen 2000",
    "addr:housenumber":"4 box 12",
    "addr:postcode":"2000",
    "iso:country":"BE",
    "sg:address":"Van Meterenkaai 4 Box 12",
    "sg:city":"Antwerpen",
    "sg:classifiers":[
        {
            "category":"Retail",
            "subcategory":"Event Space",
            "type":"Services"
        }
    ],
    "sg:phone":"+32 3 226 30 45",
    "sg:postcode":"2000",
    "sg:province":"Antwerpen",
    "sg:tags":[
        "organisation"
    ],
    "wof:name":"First Class Intl",
    "wof:placetype":"venue"
},
  "geometry": {"coordinates":[4.4002699852,51.2261581421],"type":"Point"}
}