{
  "type": "Feature",
  "properties": {
    "addr:full":"Montfort 30 Esneux Li\u00e8ge 4130",
    "addr:housenumber":"30",
    "addr:postcode":"4130",
    "addr:street":"Montfort",
    "iso:country":"BE",
    "sg:address":"Montfort 30",
    "sg:city":"Esneux",
    "sg:orig_category":"Activit\u00e9s d\u00b4action sociale sans h\u00e9bergement",
    "sg:phone":"+32 41803491",
    "sg:postcode":"4130",
    "sg:province":"Li\u00e8ge",
    "wof:name":"Parents Enf. Homosexuels",
    "wof:placetype":"venue"
},
  "geometry": {"coordinates":[5.5725622177,50.5120887756],"type":"Point"}
}