{
  "type": "Feature",
  "properties": {
    "addr:full":"Rue Du Pont D'arcole 14 Colfontaine Hainaut 7340",
    "addr:housenumber":"14",
    "addr:postcode":"7340",
    "addr:street":"Rue Du Pont D'Arcole",
    "iso:country":"BE",
    "sg:address":"Rue Du Pont D'arcole 14",
    "sg:city":"Colfontaine",
    "sg:orig_category":"Imprimeries and copyshops",
    "sg:phone":"+32 65 79 48 86",
    "sg:postcode":"7340",
    "sg:province":"Hainaut",
    "wof:name":"Creaprint",
    "wof:placetype":"venue"
},
  "geometry": {"coordinates":[3.8404619694,50.424495697],"type":"Point"}
}