{
  "type": "Feature",
  "properties": {
    "iso:country":"BE",
    "sg:address":"Avenue Eug\u00e8ne Mascaux 4",
    "sg:city":"Charleroi (marcinelle)",
    "sg:classifiers":[
        {
            "category":"Wholesale",
            "subcategory":"Medical Equipment & Supplies",
            "type":"Manufacturing & Wholesale Goods"
        }
    ],
    "sg:phone":"+32 71 43 47 48",
    "sg:postcode":"6001",
    "sg:province":"Hainaut",
    "sg:tags":[
        "aid",
        "hearing"
    ],
    "wof:name":"Centroptique Et Fils Sa",
    "wof:placetype":"venue"
},
  "geometry": {"coordinates":[4.4475708008,50.4000205994],"type":"Point"}
}