{
  "type": "Feature",
  "properties": {
    "iso:country":"BE",
    "sg:address":"Leopoldlaan 26",
    "sg:city":"De Haan",
    "sg:orig_category":"Dameskledingzaken",
    "sg:phone":"+32 59 23 69 69",
    "sg:postcode":"8420",
    "sg:province":"West-Vlaanderen",
    "wof:name":"Boetiek Tropic",
    "wof:placetype":"venue"
},
  "geometry": {"coordinates":[3.0297420025,51.2763175964],"type":"Point"}
}