{
  "type": "Feature",
  "properties": {
    "iso:country":"BE",
    "sg:address":"Kraneveld 81",
    "sg:city":"Oudenaarde",
    "sg:orig_category":"Herstellingen and onderhoud van auto's Voertuigen",
    "sg:phone":"+32 55 31 53 60",
    "sg:postcode":"9700",
    "sg:province":"Oost-Vlaanderen",
    "wof:name":"Garage Vanwelden",
    "wof:placetype":"venue"
},
  "geometry": {"coordinates":[3.6100239754,50.8735313416],"type":"Point"}
}