{
  "type": "Feature",
  "properties": {
    "iso:country":"BE",
    "sg:address":"Rue Du Monument 7",
    "sg:city":"Esneux",
    "sg:orig_category":"Traitements param\u00e9dicaux",
    "sg:phone":"+32 4 380 02 20",
    "sg:postcode":"4130",
    "sg:province":"Li\u00e8ge",
    "wof:name":"N. Huque",
    "wof:placetype":"venue"
},
  "geometry": {"coordinates":[5.5662798882,50.5351905823],"type":"Point"}
}