{
  "type": "Feature",
  "properties": {
    "addr:full":"Nederstraat 68 Oudenaarde Oost-Vlaanderen 9700",
    "addr:housenumber":"68",
    "addr:postcode":"9700",
    "addr:street":"Nederstraat",
    "iso:country":"BE",
    "sg:address":"Nederstraat 68",
    "sg:city":"Oudenaarde",
    "sg:orig_category":"Herstelling leer and schoeisel Herstellingswinkels voor diverse persoonlijke and huishoudartikelen",
    "sg:phone":"+32 55 31 32 36",
    "sg:postcode":"9700",
    "sg:province":"Oost-Vlaanderen",
    "wof:name":"Schoenmakerij Blinki",
    "wof:placetype":"venue"
},
  "geometry": {"coordinates":[3.6023340225,50.8456726074],"type":"Point"}
}