{
  "type": "Feature",
  "properties": {
    "addr:full":"Hasseltsesteenweg 611 Tongeren Limburg 3700",
    "addr:housenumber":"611",
    "addr:postcode":"3700",
    "addr:street":"Hasseltsesteenweg",
    "iso:country":"BE",
    "sg:address":"Hasseltsesteenweg 611",
    "sg:city":"Tongeren",
    "sg:orig_category":"Boissons",
    "sg:phone":"+32 12 23 65 84",
    "sg:postcode":"3700",
    "sg:province":"Limburg",
    "wof:name":"Daniels Drinkmarket",
    "wof:placetype":"venue"
},
  "geometry": {"coordinates":[5.459335804,50.7829055786],"type":"Point"}
}