{
  "type": "Feature",
  "properties": {
    "addr:full":"Celestijnenlaan 9b71 Leuven Vlaams-Brabant 3001",
    "addr:housenumber":"9b71",
    "addr:postcode":"3001",
    "addr:street":"Celestijnenlaan",
    "iso:country":"BE",
    "sg:address":"Celestijnenlaan 9b71",
    "sg:city":"Leuven",
    "sg:orig_category":"Rev\u00eatements pour sols and murs. Peinture",
    "sg:phone":"+32 16 23 02 57",
    "sg:postcode":"3001",
    "sg:province":"Vlaams-Brabant",
    "wof:name":"Tony Willems",
    "wof:placetype":"venue"
},
  "geometry": {"coordinates":[4.6744790077,50.8719749451],"type":"Point"}
}