{
  "type": "Feature",
  "properties": {
    "iso:country":"BE",
    "sg:address":"Kleine Moorsledestraat 19",
    "sg:city":"Ledegem",
    "sg:orig_category":"Antiquit\u00e9s",
    "sg:phone":"+32 56 50 08 36",
    "sg:postcode":"8880",
    "sg:province":"West-Vlaanderen",
    "wof:name":"Marc Cauwelier",
    "wof:placetype":"venue"
},
  "geometry": {"coordinates":[3.1089010239,50.8761634827],"type":"Point"}
}