{
  "type": "Feature",
  "properties": {
    "addr:full":"Baljuwweg 1 Lochristi Oost-Vlaanderen 9080",
    "addr:housenumber":"1",
    "addr:postcode":"9080",
    "addr:street":"Baljuwweg",
    "iso:country":"BE",
    "sg:address":"Baljuwweg 1",
    "sg:city":"Lochristi",
    "sg:orig_category":"Film-, tv- and videoproductie",
    "sg:phone":"+32 9 355 71 14",
    "sg:postcode":"9080",
    "sg:province":"Oost-Vlaanderen",
    "wof:name":"Smalfilm- En Videoclub Spotlicht",
    "wof:placetype":"venue"
},
  "geometry": {"coordinates":[3.8549740314,51.0862731934],"type":"Point"}
}