{
  "type": "Feature",
  "properties": {
    "addr:full":"Rue Saint-gilles 24 Li\u00c8ge Li\u00e8ge 4000",
    "addr:housenumber":"24",
    "addr:postcode":"4000",
    "addr:street":"Rue Saint-Gilles",
    "iso:country":"BE",
    "sg:address":"Rue Saint-gilles 24",
    "sg:city":"Li\u00c8ge",
    "sg:orig_category":"Brood, gebak and snoepgoed",
    "sg:phone":"+32 4 223 04 60",
    "sg:postcode":"4000",
    "sg:province":"Li\u00e8ge",
    "wof:name":"Au Panier Gourmand",
    "wof:placetype":"venue"
},
  "geometry": {"coordinates":[5.5671892166,50.639755249],"type":"Point"}
}