{
  "type": "Feature",
  "properties": {
    "addr:full":"Cour Bonaparte 4 Villers-la-ville Brabant Wallon 1495",
    "addr:housenumber":"4",
    "addr:postcode":"1495",
    "addr:street":"Cour Bonaparte",
    "iso:country":"BE",
    "sg:address":"Cour Bonaparte 4",
    "sg:city":"Villers-la-ville",
    "sg:orig_category":"Loodgieterij, verwarming and sanitaire installaties",
    "sg:phone":"+32 67 77 21 24",
    "sg:postcode":"1495",
    "sg:province":"Brabant Wallon",
    "wof:name":"Termico Chauffage Radiant",
    "wof:placetype":"venue"
},
  "geometry": {"coordinates":[4.4614257812,50.5723686218],"type":"Point"}
}