{
  "type": "Feature",
  "properties": {
    "iso:country":"BE",
    "sg:address":"Grote Baan 58b1",
    "sg:city":"Houthalen-helchteren",
    "sg:orig_category":"Agences d\u00b4interim and personnel temporaire",
    "sg:phone":"+32 11 60 55 50",
    "sg:postcode":"3530",
    "sg:province":"Limburg",
    "wof:name":"Bik Interim",
    "wof:placetype":"venue"
},
  "geometry": {"coordinates":[5.3754911423,51.0261192322],"type":"Point"}
}