{
  "type": "Feature",
  "properties": {
    "addr:full":"R Camille Hubert 15 Isnes-gembloux Namur 5032",
    "addr:housenumber":"15",
    "addr:postcode":"5032",
    "addr:street":"Isnes-Gembloux Namur",
    "iso:country":"BE",
    "sg:address":"R Camille Hubert 15",
    "sg:city":"Isnes-gembloux",
    "sg:classifiers":[
        {
            "category":"Professional",
            "subcategory":"Computer Services",
            "type":"Services"
        }
    ],
    "sg:phone":"+32 81 72 01 90",
    "sg:postcode":"5032",
    "sg:province":"Namur",
    "sg:tags":[
        "-",
        "processing",
        "data",
        "software"
    ],
    "wof:name":"Arpaweb Sprl",
    "wof:placetype":"venue"
},
  "geometry": {"coordinates":[4.7132849693,50.501209259],"type":"Point"}
}