{
  "type": "Feature",
  "properties": {
    "addr:full":"Veldstraat 1 Ingelmunster West-Vlaanderen 8770",
    "addr:housenumber":"1",
    "addr:postcode":"8770",
    "addr:street":"Veldstraat",
    "iso:country":"BE",
    "sg:address":"Veldstraat 1",
    "sg:city":"Ingelmunster",
    "sg:orig_category":"Non-Classified Establishments",
    "sg:phone":"+32 51 30 27 79",
    "sg:postcode":"8770",
    "sg:province":"West-Vlaanderen",
    "wof:name":"Desmet R",
    "wof:placetype":"venue"
},
  "geometry": {"coordinates":[3.2420899868,50.9373893738],"type":"Point"}
}