{
  "type": "Feature",
  "properties": {
    "iso:country":"BE",
    "sg:address":"Holleweg 115",
    "sg:city":"Kapellen",
    "sg:classifiers":[
        {
            "category":"Building & Trades",
            "subcategory":"Construction",
            "type":"Services"
        }
    ],
    "sg:phone":"+32 475 67 35 77",
    "sg:postcode":"2950",
    "sg:province":"Antwerpen",
    "sg:tags":[
        "carpenter"
    ],
    "wof:name":"Cuypers",
    "wof:placetype":"venue"
},
  "geometry": {"coordinates":[4.4618468285,51.3078765869],"type":"Point"}
}