{
  "type": "Feature",
  "properties": {
    "addr:full":"Noorderlaan 100 Antwerpen Antwerpen 2030",
    "addr:housenumber":"100",
    "addr:postcode":"2030",
    "addr:street":"Noorderlaan",
    "iso:country":"BE",
    "sg:address":"Noorderlaan 100",
    "sg:city":"Antwerpen",
    "sg:orig_category":"Newspapers, magazines, periodicals - Publishers",
    "sg:phone":"+32 3 542 02 02",
    "sg:postcode":"2030",
    "sg:province":"Antwerpen",
    "wof:name":"Motorrijder",
    "wof:placetype":"venue"
},
  "geometry": {"coordinates":[4.4209518433,51.2441139221],"type":"Point"}
}