{
  "type": "Feature",
  "properties": {
    "iso:country":"BE",
    "sg:address":"Munkendoornstraat 260",
    "sg:city":"Kortrijk (rollegem)",
    "sg:classifiers":[
        {
            "category":"Health Services",
            "subcategory":"Health Practitioner",
            "type":"Services"
        }
    ],
    "sg:phone":"+32 56 21 07 91",
    "sg:postcode":"8510",
    "sg:province":"West-Vlaanderen",
    "sg:tags":[
        "physiotherapist"
    ],
    "wof:name":"Soenen J",
    "wof:placetype":"venue"
},
  "geometry": {"coordinates":[3.2724859715,50.7732810974],"type":"Point"}
}