{
  "type": "Feature",
  "properties": {
    "addr:full":"Chauss\u00c9e De Beaumont 91 Froidchapelle Hainaut 6440",
    "addr:housenumber":"91",
    "addr:postcode":"6440",
    "addr:street":"Chausse\u0301E De Beaumont",
    "iso:country":"BE",
    "sg:address":"Chauss\u00c9e De Beaumont 91",
    "sg:city":"Froidchapelle",
    "sg:classifiers":[
        {
            "category":"Restaurant",
            "type":"Food & Drink"
        }
    ],
    "sg:phone":"+32 71 63 34 59",
    "sg:postcode":"6440",
    "sg:province":"Hainaut",
    "wof:name":"La Bonne Eau D\u00b4heure",
    "wof:placetype":"venue"
},
  "geometry": {"coordinates":[4.3780288696,50.2284469604],"type":"Point"}
}