{
  "type": "Feature",
  "properties": {
    "addr:full":"6041 Charleroi (grand) Hainaut 6041",
    "addr:postcode":"6041;6041",
    "addr:street":"Charleroi;Hainaut",
    "iso:country":"BE",
    "sg:address":"6041",
    "sg:city":"Charleroi (grand)",
    "sg:orig_category":"Transports a\u00e9riens r\u00e9guliers",
    "sg:phone":"+32 71 25 12 51",
    "sg:postcode":"6041",
    "sg:province":"Hainaut",
    "wof:name":"Ryanair",
    "wof:placetype":"venue"
},
  "geometry": {"coordinates":[4.4405298233,50.4735984802],"type":"Point"}
}