{
  "type": "Feature",
  "properties": {
    "iso:country":"BE",
    "sg:address":"Ten Ede 86",
    "sg:city":"Zottegem",
    "sg:orig_category":"Brood, gebak and snoepgoed",
    "sg:phone":"+32 9 360 11 63",
    "sg:postcode":"9620",
    "sg:province":"Oost-Vlaanderen",
    "wof:name":"Franceus",
    "wof:placetype":"venue"
},
  "geometry": {"coordinates":[3.8020060062,50.8342170715],"type":"Point"}
}