{
  "type": "Feature",
  "properties": {
    "addr:full":"Rue Des Eglantines 23 Blegny Li\u00e8ge 4670",
    "addr:housenumber":"23",
    "addr:postcode":"4670",
    "addr:street":"Rue Des Eglantines",
    "iso:country":"BE",
    "sg:address":"Rue Des Eglantines 23",
    "sg:city":"Blegny",
    "sg:orig_category":"Huishoudapparaten, televisies and radio's",
    "sg:phone":"+32 4 387 57 01",
    "sg:postcode":"4670",
    "sg:province":"Li\u00e8ge",
    "wof:name":"Yvelise Haine",
    "wof:placetype":"venue"
},
  "geometry": {"coordinates":[5.7408428192,50.688369751],"type":"Point"}
}