{
  "type": "Feature",
  "properties": {
    "addr:full":"Oude-pastoriedreef 56 Opwijk Vlaams-Brabant 1745",
    "addr:housenumber":"56",
    "addr:postcode":"1745",
    "addr:street":"Oude-Pastoriedreef",
    "iso:country":"BE",
    "sg:address":"Oude-pastoriedreef 56",
    "sg:city":"Opwijk",
    "sg:orig_category":"Paramedische behandelingen Schoonheidssalons",
    "sg:phone":"+32 52 35 12 91",
    "sg:postcode":"1745",
    "sg:province":"Vlaams-Brabant",
    "wof:name":"Lieve Beerens",
    "wof:placetype":"venue"
},
  "geometry": {"coordinates":[4.1905679703,50.9655723572],"type":"Point"}
}