{
  "type": "Feature",
  "properties": {
    "addr:full":"Langerbrugsestraat 51 Evergem Oost-Vlaanderen 9940",
    "addr:housenumber":"51",
    "addr:postcode":"9940",
    "addr:street":"Langerbrugsestraat;Oost-Vlaanderen",
    "iso:country":"BE",
    "sg:address":"Langerbrugsestraat 51",
    "sg:city":"Evergem",
    "sg:orig_category":"Artsen and specialisten",
    "sg:phone":"+32 9 253 86 33",
    "sg:postcode":"9940",
    "sg:province":"Oost-Vlaanderen",
    "wof:name":"J. De Pourcq",
    "wof:placetype":"venue"
},
  "geometry": {"coordinates":[3.7174379826,51.1113128662],"type":"Point"}
}