{
  "type": "Feature",
  "properties": {
    "addr:full":"Luttrebruglaan 5 Vorst/forest Bruxelles-Capitale 1190",
    "addr:housenumber":"5",
    "addr:postcode":"1190",
    "addr:street":"Luttrebruglaan;/ Forest",
    "iso:country":"BE",
    "sg:address":"Luttrebruglaan 5",
    "sg:city":"Vorst/forest",
    "sg:orig_category":"Industri\u00eble elektrische installaties",
    "sg:phone":"+32 2 344 18 55",
    "sg:postcode":"1190",
    "sg:province":"Bruxelles-Capitale",
    "wof:name":"Treize",
    "wof:placetype":"venue"
},
  "geometry": {"coordinates":[4.3213768005,50.82056427],"type":"Point"}
}