{
  "type": "Feature",
  "properties": {
    "addr:full":"Rue De France 13 Nassogne Luxembourg 6953",
    "addr:housenumber":"13",
    "addr:postcode":"6953",
    "addr:street":"Rue De France",
    "iso:country":"BE",
    "sg:address":"Rue De France 13",
    "sg:city":"Nassogne",
    "sg:orig_category":"Brood, gebak and snoepgoed",
    "sg:phone":"+32 84 21 26 95",
    "sg:postcode":"6953",
    "sg:province":"Luxembourg",
    "wof:name":"Le Temps Retrouv\u00c9",
    "wof:placetype":"venue"
},
  "geometry": {"coordinates":[5.2725801468,50.1309700012],"type":"Point"}
}