{
  "type": "Feature",
  "properties": {
    "addr:full":"Misweg 69 Riemst Limburg 3770",
    "addr:housenumber":"69",
    "addr:postcode":"3770",
    "addr:street":"Misweg",
    "iso:country":"BE",
    "sg:address":"Misweg 69",
    "sg:city":"Riemst",
    "sg:orig_category":"Diverse meubelen Fab Installatie van houten of kunststof schrijnwerk MEUBELONTWERP AND -INSTALLATIE ",
    "sg:phone":"+32 12 45 32 03",
    "sg:postcode":"3770",
    "sg:province":"Limburg",
    "wof:name":"Interieurbouw Slangen",
    "wof:placetype":"venue"
},
  "geometry": {"coordinates":[5.5969901085,50.8109016418],"type":"Point"}
}