{
  "type": "Feature",
  "properties": {
    "iso:country":"BE",
    "sg:address":"Rue De La Station 71",
    "sg:city":"Froidchapelle",
    "sg:orig_category":"HUISBRANDOLIE",
    "sg:phone":"+32 60 41 10 58",
    "sg:postcode":"6440",
    "sg:province":"Hainaut",
    "wof:name":"Marc Marijsse",
    "wof:placetype":"venue"
},
  "geometry": {"coordinates":[4.3250198364,50.1426887512],"type":"Point"}
}