{
  "type": "Feature",
  "properties": {
    "addr:full":"Langestraat 60 Oostende West-Vlaanderen 8400",
    "addr:housenumber":"60",
    "addr:postcode":"8400",
    "addr:street":"Langestraat",
    "iso:country":"BE",
    "sg:address":"Langestraat 60",
    "sg:city":"Oostende",
    "sg:orig_category":"Pain, p\u00e2tisseries and confiseries",
    "sg:phone":"+32 59 70 31 73",
    "sg:postcode":"8400",
    "sg:province":"West-Vlaanderen",
    "wof:name":"Gilbert Ingelbrecht",
    "wof:placetype":"venue"
},
  "geometry": {"coordinates":[2.9170589447,51.2331161499],"type":"Point"}
}