{
  "type": "Feature",
  "properties": {
    "addr:full":"Sint-omaarsstraat 10 Koekelare West-Vlaanderen 8680",
    "addr:housenumber":"10",
    "addr:postcode":"8680",
    "addr:street":"Sint-Omaarsstraat",
    "iso:country":"BE",
    "sg:address":"Sint-omaarsstraat 10",
    "sg:city":"Koekelare",
    "sg:classifiers":[
        {
            "category":"Cafe",
            "type":"Food & Drink"
        }
    ],
    "sg:phone":"+32 51 58 27 34",
    "sg:postcode":"8680",
    "sg:province":"West-Vlaanderen",
    "sg:tags":[
        "caf\u00e9s"
    ],
    "wof:name":"Marc Dulster",
    "wof:placetype":"venue"
},
  "geometry": {"coordinates":[2.9740281105,51.0949478149],"type":"Point"}
}