{
  "type": "Feature",
  "properties": {
    "addr:full":"Wijngaardstraat 18 Gooik Vlaams-Brabant 1755",
    "addr:housenumber":"18",
    "addr:postcode":"1755",
    "addr:street":"Wijngaardstraat",
    "iso:country":"BE",
    "sg:address":"Wijngaardstraat 18",
    "sg:city":"Gooik",
    "sg:orig_category":"Bouwmaterialen Gh HUISBRANDOLIE",
    "sg:phone":"+32 2 532 43 09",
    "sg:postcode":"1755",
    "sg:province":"Vlaams-Brabant",
    "wof:name":"Albert Tiels",
    "wof:placetype":"venue"
},
  "geometry": {"coordinates":[4.1207227707,50.7955207825],"type":"Point"}
}