{
  "type": "Feature",
  "properties": {
    "addr:full":"Rue De Bironfosse 42 Cerfontaine (soumoy) Namur 5630",
    "addr:housenumber":"42",
    "addr:postcode":"5630",
    "addr:street":"Rue De Bironfosse",
    "iso:country":"BE",
    "sg:address":"Rue De Bironfosse 42",
    "sg:city":"Cerfontaine (soumoy)",
    "sg:classifiers":[
        {
            "category":"Professional",
            "subcategory":"Accounting & Tax Preparation",
            "type":"Services"
        }
    ],
    "sg:phone":"+32 71 64 43 71",
    "sg:postcode":"5630",
    "sg:province":"Namur",
    "sg:tags":[
        "bookkeeper"
    ],
    "wof:name":"Daxhelet D",
    "wof:placetype":"venue"
},
  "geometry": {"coordinates":[4.4401707649,50.1908416748],"type":"Point"}
}