{
  "type": "Feature",
  "properties": {
    "iso:country":"BE",
    "sg:address":"Chauss\u00c9e V Lampe 195",
    "sg:city":"Lessines",
    "sg:orig_category":"D\u00e9molition d\u00b4immeubles and terrassements",
    "sg:phone":"+32 68 33 46 95",
    "sg:postcode":"7866",
    "sg:province":"Hainaut",
    "wof:name":"Van Wonterghem",
    "wof:placetype":"venue"
},
  "geometry": {"coordinates":[3.8628020287,50.6883163452],"type":"Point"}
}