{
  "type": "Feature",
  "properties": {
    "iso:country":"BE",
    "sg:address":"Consciencestraat 7",
    "sg:city":"Antwerpen",
    "sg:classifiers":[
        {
            "category":"Professional",
            "subcategory":"Lawyer & Legal Services",
            "type":"Services"
        }
    ],
    "sg:phone":"+32 3 287 60 93",
    "sg:postcode":"2018",
    "sg:province":"Antwerpen",
    "wof:name":"Leten N",
    "wof:placetype":"venue"
},
  "geometry": {"coordinates":[4.4182610512,51.2080421448],"type":"Point"}
}