{
  "type": "Feature",
  "properties": {
    "addr:full":"Papenstraat 18 Linter (neerlinter) Vlaams-Brabant 3350",
    "addr:housenumber":"18",
    "addr:postcode":"3350",
    "addr:street":"Papenstraat",
    "iso:country":"BE",
    "sg:address":"Papenstraat 18",
    "sg:city":"Linter (neerlinter)",
    "sg:classifiers":[
        {
            "category":"Retail",
            "subcategory":"Auto Repair",
            "type":"Services"
        }
    ],
    "sg:phone":"+32 16 77 81 46",
    "sg:postcode":"3350",
    "sg:province":"Vlaams-Brabant",
    "sg:tags":[
        "garage"
    ],
    "wof:name":"Garage Geert Nv",
    "wof:placetype":"venue"
},
  "geometry": {"coordinates":[5.0643911362,50.8061676025],"type":"Point"}
}