{
  "type": "Feature",
  "properties": {
    "iso:country":"BE",
    "sg:address":"Geraardsbergsesteenweg 385",
    "sg:city":"Ninove",
    "sg:orig_category":"Entretien and r\u00e9parations de voitures",
    "sg:phone":"+32 54 50 27 39",
    "sg:postcode":"9404",
    "sg:province":"Oost-Vlaanderen",
    "wof:name":"Alain Triest",
    "wof:placetype":"venue"
},
  "geometry": {"coordinates":[3.9570000172,50.8419036865],"type":"Point"}
}