{
  "type": "Feature",
  "properties": {
    "iso:country":"BE",
    "sg:address":"Baanstknokstraat 5b",
    "sg:city":"Waregem",
    "sg:classifiers":[
        {
            "category":"Bakery",
            "type":"Food & Drink"
        }
    ],
    "sg:phone":"+32 56 61 73 35",
    "sg:postcode":"8790",
    "sg:province":"West-Vlaanderen",
    "sg:tags":[
        "confectioner",
        "baker"
    ],
    "wof:name":"Smullerietje ('t)",
    "wof:placetype":"venue"
},
  "geometry": {"coordinates":[3.418571949,50.8914375305],"type":"Point"}
}