{
  "type": "Feature",
  "properties": {
    "addr:full":"Alsembergse Steenweg 606 Ukkel/uccle Bruxelles-Capitale 1180",
    "addr:housenumber":"606",
    "addr:postcode":"1180",
    "addr:street":"Alsembergse Steenweg;/",
    "iso:country":"BE",
    "sg:address":"Alsembergse Steenweg 606",
    "sg:city":"Ukkel/uccle",
    "sg:orig_category":"Boekenuitgeverijen Film-, tv- and videoproductie",
    "sg:phone":"+32 2 343 06 65",
    "sg:postcode":"1180",
    "sg:province":"Bruxelles-Capitale",
    "wof:name":"Aaa Les Films Belges",
    "wof:placetype":"venue"
},
  "geometry": {"coordinates":[4.3370261192,50.8055419922],"type":"Point"}
}