{
  "type": "Feature",
  "properties": {
    "addr:full":"Fonteinstraat 7ba Gingelom Limburg 3890",
    "addr:housenumber":"7ba",
    "addr:postcode":"3890",
    "addr:street":"Fonteinstraat",
    "iso:country":"BE",
    "sg:address":"Fonteinstraat 7ba",
    "sg:city":"Gingelom",
    "sg:orig_category":"P\u00e9pini\u00e9ristes",
    "sg:phone":"+32 11 88 66 14",
    "sg:postcode":"3890",
    "sg:province":"Limburg",
    "wof:name":"Annie Santermans",
    "wof:placetype":"venue"
},
  "geometry": {"coordinates":[5.1432590485,50.7401351929],"type":"Point"}
}