{
  "type": "Feature",
  "properties": {
    "iso:country":"BE",
    "sg:address":"Albert Van Heckelaan 2",
    "sg:city":"Hamme",
    "sg:orig_category":"Gespecialiseerde residenti\u00eble bouw",
    "sg:phone":"+32 52 47 35 29",
    "sg:postcode":"9220",
    "sg:province":"Oost-Vlaanderen",
    "wof:name":"Jacques Schepens",
    "wof:placetype":"venue"
},
  "geometry": {"coordinates":[4.1296858788,51.0845565796],"type":"Point"}
}