{
  "type": "Feature",
  "properties": {
    "addr:full":"Barones Ludwine De Borrekenslaan 83 Aartselaar Antwerpen 2630",
    "addr:housenumber":"83",
    "addr:postcode":"2630",
    "addr:street":"Barones Ludwine De Borrekenslaan",
    "iso:country":"BE",
    "sg:address":"Barones Ludwine De Borrekenslaan 83",
    "sg:city":"Aartselaar",
    "sg:classifiers":[
        {
            "category":"Professional",
            "subcategory":"Management & Consulting",
            "type":"Services"
        }
    ],
    "sg:phone":"+32 3 877 09 13",
    "sg:postcode":"2630",
    "sg:province":"Antwerpen",
    "sg:tags":[
        "consultant"
    ],
    "wof:name":"Marcel Ysewijn-consulting",
    "wof:placetype":"venue"
},
  "geometry": {"coordinates":[4.3827581406,51.1408653259],"type":"Point"}
}