{
  "type": "Feature",
  "properties": {
    "iso:country":"BE",
    "sg:address":"Daalstraat 2",
    "sg:city":"Hoeselt",
    "sg:orig_category":"Elektrische installaties voor woningen",
    "sg:phone":"+32 89 49 15 17",
    "sg:postcode":"3730",
    "sg:province":"Limburg",
    "wof:name":"Henri Van Schijndel",
    "wof:placetype":"venue"
},
  "geometry": {"coordinates":[5.4787149429,50.8622360229],"type":"Point"}
}