{
  "type": "Feature",
  "properties": {
    "iso:country":"BE",
    "sg:address":"Beverhoutsveldstraat 79",
    "sg:city":"Beernem (oedelem)",
    "sg:classifiers":[
        {
            "category":"Building & Trades",
            "subcategory":"Landscaping Services",
            "type":"Services"
        }
    ],
    "sg:phone":"+32 50 78 00 33",
    "sg:postcode":"8730",
    "sg:province":"West-Vlaanderen",
    "sg:tags":[
        "gardening",
        "garden",
        "maintenance"
    ],
    "wof:name":"Tuinen Gchesquiere",
    "wof:placetype":"venue"
},
  "geometry": {"coordinates":[3.3146879673,51.1643714905],"type":"Point"}
}