{
  "type": "Feature",
  "properties": {
    "addr:full":"Rue De La Fosse 10 Mont-saint-guibert Brabant Wallon 1435",
    "addr:housenumber":"10",
    "addr:postcode":"1435",
    "addr:street":"Rue De La Fosse",
    "iso:country":"BE",
    "sg:address":"Rue De La Fosse 10",
    "sg:city":"Mont-saint-guibert",
    "sg:classifiers":[
        {
            "category":"Building & Trades",
            "subcategory":"Landscaping Services",
            "type":"Services"
        }
    ],
    "sg:phone":"+32 10 65 18 12",
    "sg:postcode":"1435",
    "sg:province":"Brabant Wallon",
    "sg:tags":[
        "gardening",
        "garden",
        "maintenance"
    ],
    "wof:name":"Delfosse R",
    "wof:placetype":"venue"
},
  "geometry": {"coordinates":[4.6116871834,50.6349563599],"type":"Point"}
}