{
  "type": "Feature",
  "properties": {
    "iso:country":"BE",
    "sg:address":"Chauss\u00c9e De Mons 219",
    "sg:city":"Anderlecht",
    "sg:orig_category":"Epiceries",
    "sg:phone":"+32 2 522 11 82",
    "sg:postcode":"1070",
    "sg:province":"Bruxelles-Capitale",
    "wof:name":"Nourddine Dehou",
    "wof:placetype":"venue"
},
  "geometry": {"coordinates":[4.3281989098,50.8411979675],"type":"Point"}
}