{
  "type": "Feature",
  "properties": {
    "addr:full":"Avenue Du Mar\u00c9chal 22 Ukkel/uccle Bruxelles-Capitale 1180",
    "addr:housenumber":"22",
    "addr:postcode":"1180",
    "addr:street":"Avenue Du Mare\u0301Chal;/",
    "iso:country":"BE",
    "sg:address":"Avenue Du Mar\u00c9chal 22",
    "sg:city":"Ukkel/uccle",
    "sg:orig_category":"D\u00e9corateurs d'int\u00e9rieur",
    "sg:phone":"+32 2 374 00 78",
    "sg:postcode":"1180",
    "sg:province":"Bruxelles-Capitale",
    "wof:name":"Stand Up",
    "wof:placetype":"venue"
},
  "geometry": {"coordinates":[4.370557785,50.7800636292],"type":"Point"}
}