{
  "type": "Feature",
  "properties": {
    "addr:full":"Landmansstraat 10 Roeselare West-Vlaanderen 8800",
    "addr:housenumber":"10",
    "addr:postcode":"8800",
    "addr:street":"Landmansstraat",
    "iso:country":"BE",
    "sg:address":"Landmansstraat 10",
    "sg:city":"Roeselare",
    "sg:orig_category":"Producteurs de l\u00e9gumes",
    "sg:phone":"+32 56 50 97 02",
    "sg:postcode":"8800",
    "sg:province":"West-Vlaanderen",
    "wof:name":"Wilfried Lammers",
    "wof:placetype":"venue"
},
  "geometry": {"coordinates":[3.1182949543,50.8923339844],"type":"Point"}
}