{
  "type": "Feature",
  "properties": {
    "iso:country":"BE",
    "sg:address":"Blauwdreef 187",
    "sg:city":"Zulte",
    "sg:orig_category":"Diverse bouwafwerking and reiniging",
    "sg:phone":"+32 9 388 57 58",
    "sg:postcode":"9870",
    "sg:province":"Oost-Vlaanderen",
    "wof:name":"Wallcleaning",
    "wof:placetype":"venue"
},
  "geometry": {"coordinates":[3.4766750336,50.9132499695],"type":"Point"}
}