{
  "type": "Feature",
  "properties": {
    "addr:full":"Rue De Dinant 71 Beauraing Namur 5570",
    "addr:housenumber":"71",
    "addr:postcode":"5570",
    "addr:street":"Rue De Dinant",
    "iso:country":"BE",
    "sg:address":"Rue De Dinant 71",
    "sg:city":"Beauraing",
    "sg:classifiers":[
        {
            "category":"Shopping",
            "subcategory":"Bridal",
            "type":"Retail Goods"
        }
    ],
    "sg:phone":"+32 82 71 12 16",
    "sg:postcode":"5570",
    "sg:province":"Namur",
    "sg:tags":[
        "list",
        "-",
        "present",
        "wedding"
    ],
    "wof:name":"Culot S.",
    "wof:placetype":"venue"
},
  "geometry": {"coordinates":[4.9551072121,50.1135787964],"type":"Point"}
}