{
  "type": "Feature",
  "properties": {
    "addr:full":"Avenue Charles Quint 135 Bruxelles (berchem-sainte-agathe) Bruxelles-Capitale 1082",
    "addr:housenumber":"135",
    "addr:postcode":"1082",
    "addr:street":"Avenue Charles Quint",
    "iso:country":"BE",
    "sg:address":"Avenue Charles Quint 135",
    "sg:city":"Bruxelles (berchem-sainte-agathe)",
    "sg:classifiers":[
        {
            "category":"Health Services",
            "subcategory":"Chiropractor",
            "type":"Services"
        }
    ],
    "sg:phone":"+32 2 465 14 06",
    "sg:postcode":"1082",
    "sg:province":"Bruxelles-Capitale",
    "wof:name":"Nelis M",
    "wof:placetype":"venue"
},
  "geometry": {"coordinates":[4.3096728325,50.8690071106],"type":"Point"}
}