{
  "type": "Feature",
  "properties": {
    "iso:country":"BE",
    "sg:address":"Zelestraat 2 (show Room)",
    "sg:city":"Lokeren",
    "sg:orig_category":"Herstelling aan huis van huishoudartikelen Herstellingswinkels voor diverse persoonlijke and huishou",
    "sg:phone":"+32 475 28 28 28",
    "sg:postcode":"9160",
    "sg:province":"Oost-Vlaanderen",
    "wof:name":"Daenekindt-safe",
    "wof:placetype":"venue"
},
  "geometry": {"coordinates":[3.995994091,51.1022987366],"type":"Point"}
}