{
  "type": "Feature",
  "properties": {
    "addr:full":"Groenstraat 9 Neerpelt Limburg 3910",
    "addr:housenumber":"9",
    "addr:postcode":"3910",
    "addr:street":"Groenstraat",
    "iso:country":"BE",
    "sg:address":"Groenstraat 9",
    "sg:city":"Neerpelt",
    "sg:orig_category":"Supermarkten",
    "sg:phone":"+32 11 64 27 03",
    "sg:postcode":"3910",
    "sg:province":"Limburg",
    "wof:name":"Unic",
    "wof:placetype":"venue"
},
  "geometry": {"coordinates":[5.4336071014,51.2290306091],"type":"Point"}
}