{
  "type": "Feature",
  "properties": {
    "addr:full":"Halmaalweg 59 Sint-truiden Limburg 3800",
    "addr:housenumber":"59",
    "addr:postcode":"3800",
    "addr:street":"Halmaalweg",
    "iso:country":"BE",
    "sg:address":"Halmaalweg 59",
    "sg:city":"Sint-truiden",
    "sg:orig_category":"Sportclubs",
    "sg:phone":"+32 11 67 28 16",
    "sg:postcode":"3800",
    "sg:province":"Limburg",
    "wof:name":"New Halma",
    "wof:placetype":"venue"
},
  "geometry": {"coordinates":[5.1544299126,50.8042488098],"type":"Point"}
}