{
  "type": "Feature",
  "properties": {
    "addr:full":"Galeries Cathedrale 96 Li\u00e8ge Li\u00e8ge 4000",
    "addr:housenumber":"96",
    "addr:postcode":"4000",
    "iso:country":"BE",
    "sg:address":"Galeries Cathedrale 96",
    "sg:city":"Li\u00e8ge",
    "sg:classifiers":[
        {
            "category":"Wholesale",
            "subcategory":"Office Equipment",
            "type":"Manufacturing & Wholesale Goods"
        }
    ],
    "sg:phone":"+32 4 222 16 83",
    "sg:postcode":"4000",
    "sg:province":"Li\u00e8ge",
    "sg:tags":[
        "agency",
        "internet"
    ],
    "wof:name":"Clair Et Net Snc",
    "wof:placetype":"venue"
},
  "geometry": {"coordinates":[5.5724220276,50.6416397095],"type":"Point"}
}