{
  "type": "Feature",
  "properties": {
    "iso:country":"BE",
    "sg:address":"Chauss\u00c9e De Bruxelles 98",
    "sg:city":"Charleroi",
    "sg:orig_category":"Artsen and specialisten",
    "sg:phone":"+32 71 31 57 71",
    "sg:postcode":"6042",
    "sg:province":"Hainaut",
    "wof:name":"Jean-pierre Masset",
    "wof:placetype":"venue"
},
  "geometry": {"coordinates":[4.4391741753,50.438205719],"type":"Point"}
}