{
  "type": "Feature",
  "properties": {
    "iso:country":"BE",
    "sg:address":"Coron Des Indes 17",
    "sg:city":"Courcelles",
    "sg:orig_category":"Taxi's speciale diensten",
    "sg:phone":"+32 71 46 14 98",
    "sg:postcode":"6182",
    "sg:province":"Hainaut",
    "wof:name":"Willy Minneker",
    "wof:placetype":"venue"
},
  "geometry": {"coordinates":[4.3546910286,50.4466094971],"type":"Point"}
}