{
  "type": "Feature",
  "properties": {
    "iso:country":"BE",
    "sg:address":"Gerdingerstraat 12a",
    "sg:city":"Bree",
    "sg:classifiers":[
        {
            "category":"Health Services",
            "subcategory":"Health Practitioner",
            "type":"Services"
        }
    ],
    "sg:phone":"+32 89 46 45 41",
    "sg:postcode":"3960",
    "sg:province":"Limburg",
    "sg:tags":[
        "physiotherapist"
    ],
    "wof:name":"Beynsberger Wendy",
    "wof:placetype":"venue"
},
  "geometry": {"coordinates":[5.5957131386,51.1420021057],"type":"Point"}
}