{
  "type": "Feature",
  "properties": {
    "addr:full":"Sint-stevensstraat 28 Sint-pieters-leeuw Vlaams-Brabant 1600",
    "addr:housenumber":"28",
    "addr:postcode":"1600",
    "addr:street":"Sint-Stevensstraat",
    "iso:country":"BE",
    "sg:address":"Sint-stevensstraat 28",
    "sg:city":"Sint-pieters-leeuw",
    "sg:orig_category":"Artiesten and kunstenaars",
    "sg:phone":"+32 2 377 62 19",
    "sg:postcode":"1600",
    "sg:province":"Vlaams-Brabant",
    "wof:name":"Aerts",
    "wof:placetype":"venue"
},
  "geometry": {"coordinates":[4.2872772217,50.8050956726],"type":"Point"}
}