{
  "type": "Feature",
  "properties": {
    "iso:country":"BE",
    "sg:address":"Rue Du Charreau 179",
    "sg:city":"Hasti\u00e8re (waulsort)",
    "sg:classifiers":[
        {
            "category":"Professional",
            "subcategory":"Engineering",
            "type":"Services"
        }
    ],
    "sg:phone":"+32 82 64 58 74",
    "sg:postcode":"5540",
    "sg:province":"Namur",
    "sg:tags":[
        "-"
    ],
    "wof:name":"Pylot Engineering",
    "wof:placetype":"venue"
},
  "geometry": {"coordinates":[4.8594079018,50.2060432434],"type":"Point"}
}