{
  "type": "Feature",
  "properties": {
    "iso:country":"BE",
    "sg:address":"Schoolstraat 73",
    "sg:city":"Lokeren",
    "sg:classifiers":[
        {
            "category":"Utilities",
            "subcategory":"Natural Gas",
            "type":"Services"
        }
    ],
    "sg:phone":"+32 9 349 51 74",
    "sg:postcode":"9160",
    "sg:province":"Oost-Vlaanderen",
    "sg:tags":[
        "industrial",
        "-"
    ],
    "wof:name":"Gasap Bvba",
    "wof:placetype":"venue"
},
  "geometry": {"coordinates":[3.9896800518,51.1024551392],"type":"Point"}
}