{
  "type": "Feature",
  "properties": {
    "addr:full":"Ontmijnersstraat 35 Blankenberge West-Vlaanderen 8370",
    "addr:housenumber":"35",
    "addr:postcode":"8370",
    "addr:street":"Ontmijnersstraat",
    "iso:country":"BE",
    "sg:address":"Ontmijnersstraat 35",
    "sg:city":"Blankenberge",
    "sg:classifiers":[
        {
            "category":"Health Services",
            "subcategory":"Health Practitioner",
            "type":"Services"
        }
    ],
    "sg:phone":"+32 50 41 81 56",
    "sg:postcode":"8370",
    "sg:province":"West-Vlaanderen",
    "sg:tags":[
        "physiotherapist"
    ],
    "wof:name":"De Keyser Marc",
    "wof:placetype":"venue"
},
  "geometry": {"coordinates":[3.131757021,51.3111419678],"type":"Point"}
}