{
  "type": "Feature",
  "properties": {
    "addr:full":"Rue Sainte-marguerite 359 Li\u00c8ge Li\u00e8ge 4000",
    "addr:housenumber":"359",
    "addr:postcode":"4000",
    "addr:street":"Rue Sainte-Marguerite",
    "iso:country":"BE",
    "sg:address":"Rue Sainte-marguerite 359",
    "sg:city":"Li\u00c8ge",
    "sg:classifiers":[
        {
            "category":"Manufacturing",
            "subcategory":"Textiles",
            "type":"Manufacturing & Wholesale Goods"
        }
    ],
    "sg:phone":"+32 4 226 45 45",
    "sg:postcode":"4000",
    "sg:province":"Li\u00e8ge",
    "wof:name":"Maison Clobus",
    "wof:placetype":"venue"
},
  "geometry": {"coordinates":[5.5630731583,50.6621170044],"type":"Point"}
}