{
  "type": "Feature",
  "properties": {
    "addr:full":"Eksaardserijweg 173 Gent (oostakker) Oost-Vlaanderen 9041",
    "addr:housenumber":"173",
    "addr:postcode":"9041",
    "iso:country":"BE",
    "sg:address":"Eksaardserijweg 173",
    "sg:city":"Gent (oostakker)",
    "sg:classifiers":[
        {
            "category":"Retail",
            "subcategory":"Auto Repair",
            "type":"Services"
        }
    ],
    "sg:phone":"+32 9 251 53 36",
    "sg:postcode":"9041",
    "sg:province":"Oost-Vlaanderen",
    "sg:tags":[
        "garage"
    ],
    "wof:name":"Goossens Garage Carrosserie Nv",
    "wof:placetype":"venue"
},
  "geometry": {"coordinates":[3.7770678997,51.0939064026],"type":"Point"}
}