{
  "type": "Feature",
  "properties": {
    "addr:full":"Chemin De La Saussaie 1 Verviers Li\u00e8ge 4802",
    "addr:housenumber":"1",
    "addr:postcode":"4802",
    "addr:street":"Chemin De La Saussaie",
    "iso:country":"BE",
    "sg:address":"Chemin De La Saussaie 1",
    "sg:city":"Verviers",
    "sg:orig_category":"Dakwerken",
    "sg:phone":"+32 87 23 04 26",
    "sg:postcode":"4802",
    "sg:province":"Li\u00e8ge",
    "wof:name":"Karls",
    "wof:placetype":"venue"
},
  "geometry": {"coordinates":[5.8834519386,50.5747184753],"type":"Point"}
}