{
  "type": "Feature",
  "properties": {
    "iso:country":"BE",
    "sg:address":"Joos De Ter Beerstlaan 5",
    "sg:city":"Pittem",
    "sg:orig_category":"Pain, p\u00e2tisseries and confiseries",
    "sg:phone":"+32 51 46 65 35",
    "sg:postcode":"8740",
    "sg:province":"West-Vlaanderen",
    "wof:name":"Bakkerij Martine",
    "wof:placetype":"venue"
},
  "geometry": {"coordinates":[3.2594380379,50.9923973083],"type":"Point"}
}