{
  "type": "Feature",
  "properties": {
    "iso:country":"BE",
    "sg:address":"Rue P\u00e9trias 75",
    "sg:city":"Ham-sur-heure-nalinnes (nalinnes)",
    "sg:classifiers":[
        {
            "category":"Arts & Performance",
            "subcategory":"Music",
            "type":"Entertainment"
        }
    ],
    "sg:phone":"+32 495 74 73 58",
    "sg:postcode":"6120",
    "sg:province":"Hainaut",
    "sg:tags":[
        "disc-jockeys"
    ],
    "wof:name":"Disco In Flame",
    "wof:placetype":"venue"
},
  "geometry": {"coordinates":[4.4327487946,50.3404006958],"type":"Point"}
}