{
  "type": "Feature",
  "properties": {
    "addr:full":"Dries 14 Lede (oordegem) Oost-Vlaanderen 9340",
    "addr:housenumber":"14",
    "addr:postcode":"9340",
    "addr:street":"Dries",
    "iso:country":"BE",
    "sg:address":"Dries 14",
    "sg:city":"Lede (oordegem)",
    "sg:classifiers":[
        {
            "category":"Education",
            "subcategory":"Special Training",
            "type":"Public Place"
        }
    ],
    "sg:phone":"+32 9 368 19 71",
    "sg:postcode":"9340",
    "sg:province":"Oost-Vlaanderen",
    "sg:tags":[
        "-",
        "processing",
        "data"
    ],
    "wof:name":"Luyckx K",
    "wof:placetype":"venue"
},
  "geometry": {"coordinates":[3.9773280621,50.9667625427],"type":"Point"}
}