{
  "type": "Feature",
  "properties": {
    "iso:country":"BE",
    "sg:address":"Place Communale 22",
    "sg:city":"Silly",
    "sg:classifiers":[
        {
            "category":"Real Estate",
            "subcategory":"Architect",
            "type":"Services"
        }
    ],
    "sg:phone":"+32 68 57 00 88",
    "sg:postcode":"7830",
    "sg:province":"Hainaut",
    "wof:name":"Jonet B",
    "wof:placetype":"venue"
},
  "geometry": {"coordinates":[3.9231760502,50.6487083435],"type":"Point"}
}