{
  "type": "Feature",
  "properties": {
    "addr:full":"Industrieweg 118 Gent (wondelgem) Oost-Vlaanderen 9032",
    "addr:housenumber":"118",
    "addr:postcode":"9032",
    "addr:street":"Industrieweg",
    "iso:country":"BE",
    "sg:address":"Industrieweg 118",
    "sg:city":"Gent (wondelgem)",
    "sg:classifiers":[
        {
            "category":"Utilities",
            "subcategory":"Refuse",
            "type":"Services"
        }
    ],
    "sg:phone":"+32 9 236 62 51",
    "sg:postcode":"9032",
    "sg:province":"Oost-Vlaanderen",
    "sg:tags":[
        "boiler",
        "-",
        "heating",
        "steam"
    ],
    "wof:name":"S.r.m. Nv",
    "wof:placetype":"venue"
},
  "geometry": {"coordinates":[3.6899850368,51.0904388428],"type":"Point"}
}