{
  "type": "Feature",
  "properties": {
    "addr:full":"Rue Des Villas 1 Montigny-le-tilleul (landelies) Hainaut 6111",
    "addr:housenumber":"1",
    "addr:postcode":"6111",
    "addr:street":"Rue Des Villas",
    "iso:country":"BE",
    "sg:address":"Rue Des Villas 1",
    "sg:city":"Montigny-le-tilleul (landelies)",
    "sg:classifiers":[
        {
            "category":"Building & Trades",
            "subcategory":"Landscaping Services",
            "type":"Services"
        }
    ],
    "sg:phone":"+32 71 51 18 14",
    "sg:postcode":"6111",
    "sg:province":"Hainaut",
    "sg:tags":[
        "gardening",
        "garden",
        "maintenance"
    ],
    "wof:name":"Heuchamps P",
    "wof:placetype":"venue"
},
  "geometry": {"coordinates":[4.3506112099,50.3798561096],"type":"Point"}
}