{
  "type": "Feature",
  "properties": {
    "addr:full":"Vrijwilligersstraat 60 Beerse Antwerpen 2340",
    "addr:housenumber":"60",
    "addr:postcode":"2340",
    "addr:street":"Vrijwilligersstraat",
    "iso:country":"BE",
    "sg:address":"Vrijwilligersstraat 60",
    "sg:city":"Beerse",
    "sg:classifiers":[
        {
            "category":"Health Services",
            "subcategory":"Health Practitioner",
            "type":"Services"
        }
    ],
    "sg:phone":"+32 14 61 59 48",
    "sg:postcode":"2340",
    "sg:province":"Antwerpen",
    "sg:tags":[
        "therapist",
        "speech"
    ],
    "wof:name":"Decostere C",
    "wof:placetype":"venue"
},
  "geometry": {"coordinates":[4.859577179,51.3230628967],"type":"Point"}
}