{
  "type": "Feature",
  "properties": {
    "addr:full":"Petrus Van Bavegemstraat 4 Dendermonde (baasrode) Oost-Vlaanderen 9200",
    "addr:housenumber":"4",
    "addr:postcode":"9200",
    "addr:street":"Petrus;Bavegemstraat",
    "iso:country":"BE",
    "sg:address":"Petrus Van Bavegemstraat 4",
    "sg:city":"Dendermonde (baasrode)",
    "sg:classifiers":[
        {
            "category":"Food & Beverages",
            "subcategory":"Groceries & Convenience Stores",
            "type":"Retail Goods"
        }
    ],
    "sg:phone":"+32 52 33 10 81",
    "sg:postcode":"9200",
    "sg:province":"Oost-Vlaanderen",
    "sg:tags":[
        "grocer"
    ],
    "wof:name":"Versmarkt Maes",
    "wof:placetype":"venue"
},
  "geometry": {"coordinates":[4.0983099937,51.0315208435],"type":"Point"}
}