{
  "type": "Feature",
  "properties": {
    "addr:full":"De Moystraat 17a Antwerpen Antwerpen 2018",
    "addr:housenumber":"17a",
    "addr:postcode":"2018",
    "addr:street":"Moystraat",
    "iso:country":"BE",
    "sg:address":"De Moystraat 17a",
    "sg:city":"Antwerpen",
    "sg:classifiers":[
        {
            "category":"Professional",
            "subcategory":"Art Services",
            "type":"Services"
        }
    ],
    "sg:phone":"+32 3 238 23 84",
    "sg:postcode":"2018",
    "sg:province":"Antwerpen",
    "sg:tags":[
        "photography",
        "reporting",
        "-"
    ],
    "wof:name":"Shooter (the) Bvba",
    "wof:placetype":"venue"
},
  "geometry": {"coordinates":[4.4065937996,51.2078170776],"type":"Point"}
}