{
  "type": "Feature",
  "properties": {
    "addr:full":"Avenue G\u00e9n\u00e9ral Eisenhower 105-107 Bruxelles (schaerbeek) Bruxelles-Capitale 1030",
    "addr:postcode":"105-107;1030",
    "addr:street":"Avenue Ge\u0301Ne\u0301Ral Eisenhower",
    "iso:country":"BE",
    "sg:address":"Avenue G\u00e9n\u00e9ral Eisenhower 105-107",
    "sg:city":"Bruxelles (schaerbeek)",
    "sg:classifiers":[
        {
            "category":"Social Services",
            "subcategory":"Job Training",
            "type":"Services"
        }
    ],
    "sg:phone":"+32 2 245 02 40",
    "sg:postcode":"1030",
    "sg:province":"Bruxelles-Capitale",
    "sg:tags":[
        "personnel"
    ],
    "wof:name":"Mercuri Internationaal Nv",
    "wof:placetype":"venue"
},
  "geometry": {"coordinates":[4.3862857819,50.8595161438],"type":"Point"}
}