{
  "type": "Feature",
  "properties": {
    "addr:full":"Kasteelstraat 53 Herzele (woubrechtegem) Oost-Vlaanderen 9550",
    "addr:housenumber":"53",
    "addr:postcode":"9550",
    "addr:street":"Kasteelstraat;Woubrechtegem Oost-Vlaanderen",
    "iso:country":"BE",
    "sg:address":"Kasteelstraat 53",
    "sg:city":"Herzele (woubrechtegem)",
    "sg:classifiers":[
        {
            "category":"Personal",
            "subcategory":"Beauty Salon",
            "type":"Services"
        }
    ],
    "sg:phone":"+32 53 62 73 20",
    "sg:postcode":"9550",
    "sg:province":"Oost-Vlaanderen",
    "wof:name":"Gerda",
    "wof:placetype":"venue"
},
  "geometry": {"coordinates":[3.9097459316,50.8707122803],"type":"Point"}
}