{
  "type": "Feature",
  "properties": {
    "iso:country":"BE",
    "sg:address":"Boulevard Maurice Lemonnier 69",
    "sg:city":"Bruxelles",
    "sg:classifiers":[
        {
            "category":"Professional",
            "subcategory":"Lawyer & Legal Services",
            "type":"Services"
        }
    ],
    "sg:phone":"+32 2 511 53 63",
    "sg:postcode":"1000",
    "sg:province":"Bruxelles-Capitale",
    "wof:name":"Chaya Elie",
    "wof:placetype":"venue"
},
  "geometry": {"coordinates":[4.3448472023,50.8439674377],"type":"Point"}
}