{
  "type": "Feature",
  "properties": {
    "addr:full":"Rue De La Charrette 119 Esneux Li\u00e8ge 4130",
    "addr:housenumber":"119",
    "addr:postcode":"4130",
    "addr:street":"Rue De La Charrette",
    "iso:country":"BE",
    "sg:address":"Rue De La Charrette 119",
    "sg:city":"Esneux",
    "sg:classifiers":[
        {
            "category":"Insurance",
            "subcategory":"Life Insurance",
            "type":"Services"
        }
    ],
    "sg:phone":"+32 4 388 16 04",
    "sg:postcode":"4130",
    "sg:province":"Li\u00e8ge",
    "sg:tags":[
        "assurance"
    ],
    "wof:name":"Cabinet Jamin P.",
    "wof:placetype":"venue"
},
  "geometry": {"coordinates":[5.5787830353,50.5727806091],"type":"Point"}
}