{
  "type": "Feature",
  "properties": {
    "addr:full":"Lescheret 6 Vaux-sur-sure Luxembourg 6642",
    "addr:housenumber":"6",
    "addr:postcode":"6642",
    "addr:street":"Lescheret",
    "iso:country":"BE",
    "sg:address":"Lescheret 6",
    "sg:city":"Vaux-sur-sure",
    "sg:orig_category":"Rundveehouders",
    "sg:phone":"+32 61 25 59 18",
    "sg:postcode":"6642",
    "sg:province":"Luxembourg",
    "wof:name":"Bock Joseph & Rene",
    "wof:placetype":"venue"
},
  "geometry": {"coordinates":[5.5497012138,49.8756828308],"type":"Point"}
}