{
  "type": "Feature",
  "properties": {
    "iso:country":"BE",
    "sg:address":"Albertlaan 38",
    "sg:city":"Knokke-heist (knokke)",
    "sg:classifiers":[
        {
            "category":"Bakery",
            "type":"Food & Drink"
        }
    ],
    "sg:phone":"+32 50 60 17 55",
    "sg:postcode":"8300",
    "sg:province":"West-Vlaanderen",
    "sg:tags":[
        "confectioner",
        "baker"
    ],
    "wof:name":"Devooght M",
    "wof:placetype":"venue"
},
  "geometry": {"coordinates":[3.2899808884,51.3422241211],"type":"Point"}
}