{
  "type": "Feature",
  "properties": {
    "iso:country":"BE",
    "sg:address":"Brugsesteenweg 90",
    "sg:city":"Kuurne",
    "sg:orig_category":"V\u00eatements pour Hommes. V\u00eatements pour Dames. V\u00eatements pour b\u00e9b\u00e9s and enfants",
    "sg:phone":"+32 56 37 16 20",
    "sg:postcode":"8520",
    "sg:province":"West-Vlaanderen",
    "wof:name":"Pecotex",
    "wof:placetype":"venue"
},
  "geometry": {"coordinates":[3.2699730396,50.850189209],"type":"Point"}
}