{
  "type": "Feature",
  "properties": {
    "iso:country":"BE",
    "sg:address":"St.-patrice 2",
    "sg:city":"La Louviere",
    "sg:orig_category":"Diverse bouwinstallaties Gespecialiseerde niet-residenti\u00eble bouw",
    "sg:phone":"+32 64 28 37 47",
    "sg:postcode":"7110",
    "sg:province":"Hainaut",
    "wof:name":"Eurafor",
    "wof:placetype":"venue"
},
  "geometry": {"coordinates":[4.1505050659,50.4826698303],"type":"Point"}
}