{
  "type": "Feature",
  "properties": {
    "iso:country":"BE",
    "sg:address":"Parc Industriel D'ivoz-ramet 1",
    "sg:city":"Flemalle",
    "sg:classifiers":[
        {
            "category":"Manufacturing",
            "subcategory":"Metals",
            "type":"Manufacturing & Wholesale Goods"
        }
    ],
    "sg:phone":"+32 4 337 79 62",
    "sg:postcode":"4400",
    "sg:province":"Li\u00e8ge",
    "sg:tags":[
        "work",
        "sheet"
    ],
    "wof:name":"Metal Forming Sa",
    "wof:placetype":"venue"
},
  "geometry": {"coordinates":[5.4603190422,50.5873031616],"type":"Point"}
}