{
  "type": "Feature",
  "properties": {
    "addr:full":"Jan Van Rijswijcklaan 103 Antwerpen Antwerpen 2018",
    "addr:housenumber":"103",
    "addr:postcode":"2018",
    "addr:street":"Jan Van Rijswijcklaan",
    "iso:country":"BE",
    "sg:address":"Jan Van Rijswijcklaan 103",
    "sg:city":"Antwerpen",
    "sg:classifiers":[
        {
            "category":"Health Services",
            "subcategory":"Doctor",
            "type":"Services"
        }
    ],
    "sg:phone":"+32 3 237 16 88",
    "sg:postcode":"2018",
    "sg:province":"Antwerpen",
    "sg:tags":[
        "medicinephysicians",
        "surgeon"
    ],
    "wof:name":"De Bruyne Antoine",
    "wof:placetype":"venue"
},
  "geometry": {"coordinates":[4.4050078392,51.1957931519],"type":"Point"}
}