{
  "type": "Feature",
  "properties": {
    "iso:country":"BE",
    "sg:address":"Chauss\u00c9e De Vleurgat 98",
    "sg:city":"Elsene/ixelles",
    "sg:orig_category":"Activit\u00e9s d\u00b4action sociale sans h\u00e9bergement",
    "sg:phone":"+32 2 645 44 11",
    "sg:postcode":"1050",
    "sg:province":"Bruxelles-Capitale",
    "wof:name":"Croix-rouge",
    "wof:placetype":"venue"
},
  "geometry": {"coordinates":[4.3688192368,50.8246879578],"type":"Point"}
}