{
  "type": "Feature",
  "properties": {
    "addr:full":"Stadswaag 34 Hamont-achel (hamont) Limburg 3930",
    "addr:housenumber":"34",
    "addr:postcode":"3930",
    "addr:street":"Stadswaag",
    "iso:country":"BE",
    "sg:address":"Stadswaag 34",
    "sg:city":"Hamont-achel (hamont)",
    "sg:classifiers":[
        {
            "category":"Real Estate",
            "subcategory":"Surveying",
            "type":"Services"
        }
    ],
    "sg:phone":"+32 11 62 23 40",
    "sg:postcode":"3930",
    "sg:province":"Limburg",
    "sg:tags":[
        "lettering",
        "letter"
    ],
    "wof:name":"Diomedes Design",
    "wof:placetype":"venue"
},
  "geometry": {"coordinates":[5.5450549126,51.2511863708],"type":"Point"}
}