{
  "type": "Feature",
  "properties": {
    "iso:country":"BE",
    "sg:address":"Rogierlaan 69",
    "sg:city":"Oostende",
    "sg:orig_category":"Installation Of Hot-Air Heating Systems Supraregional",
    "sg:phone":"+32 59 70 33 97",
    "sg:postcode":"8400",
    "sg:province":"West-Vlaanderen",
    "wof:name":"Bakker Ch. B.v.b.a.",
    "wof:placetype":"venue"
},
  "geometry": {"coordinates":[2.9122879505,51.2259178162],"type":"Point"}
}