{
  "type": "Feature",
  "properties": {
    "addr:full":"Marktstraat 24 Maldegem Oost-Vlaanderen 9990",
    "addr:housenumber":"24",
    "addr:postcode":"9990",
    "addr:street":"Marktstraat",
    "iso:country":"BE",
    "sg:address":"Marktstraat 24",
    "sg:city":"Maldegem",
    "sg:classifiers":[
        {
            "category":"Recreation",
            "subcategory":"Theme Park",
            "type":"Entertainment"
        }
    ],
    "sg:phone":"+32 50 71 39 05",
    "sg:postcode":"9990",
    "sg:province":"Oost-Vlaanderen",
    "sg:tags":[
        "paris",
        "disneyland"
    ],
    "wof:name":"Maldo Reizen",
    "wof:placetype":"venue"
},
  "geometry": {"coordinates":[3.4464230537,51.2091140747],"type":"Point"}
}