{
  "type": "Feature",
  "properties": {
    "addr:full":"Klingedijkstraat 14 Sint-gillis-waas Oost-Vlaanderen 9170",
    "addr:housenumber":"14",
    "addr:postcode":"9170",
    "addr:street":"Klingedijkstraat",
    "iso:country":"BE",
    "sg:address":"Klingedijkstraat 14",
    "sg:city":"Sint-gillis-waas",
    "sg:classifiers":[
        {
            "category":"Cafe",
            "type":"Food & Drink"
        }
    ],
    "sg:phone":"+32 3 770 54 42",
    "sg:postcode":"9170",
    "sg:province":"Oost-Vlaanderen",
    "sg:tags":[
        "caf\u00e9s"
    ],
    "wof:name":"Caf\u00c9 Congo",
    "wof:placetype":"venue"
},
  "geometry": {"coordinates":[4.0923600197,51.2446098328],"type":"Point"}
}