{
  "type": "Feature",
  "properties": {
    "addr:full":"Bormenville 12 Havelange (flostoy) Namur 5370",
    "addr:housenumber":"12",
    "addr:postcode":"5370",
    "addr:street":"Bormenville",
    "iso:country":"BE",
    "sg:address":"Bormenville 12",
    "sg:city":"Havelange (flostoy)",
    "sg:classifiers":[
        {
            "category":"Professional",
            "type":"Services"
        }
    ],
    "sg:phone":"+32 83 61 17 15",
    "sg:postcode":"5370",
    "sg:province":"Namur",
    "sg:tags":[
        "forestry",
        "agriculture",
        "-",
        "auctioneer"
    ],
    "wof:name":"De Francquen Charles",
    "wof:placetype":"venue"
},
  "geometry": {"coordinates":[5.1858358383,50.3659667969],"type":"Point"}
}