{
  "type": "Feature",
  "properties": {
    "addr:full":"Donkerstraat 3 Bonheiden (rijmenam) Antwerpen 2820",
    "addr:housenumber":"3",
    "addr:postcode":"2820",
    "addr:street":"Donkerstraat",
    "iso:country":"BE",
    "sg:address":"Donkerstraat 3",
    "sg:city":"Bonheiden (rijmenam)",
    "sg:classifiers":[
        {
            "category":"Building & Trades",
            "subcategory":"Construction",
            "type":"Services"
        }
    ],
    "sg:phone":"+32 15 51 22 96",
    "sg:postcode":"2820",
    "sg:province":"Antwerpen",
    "sg:tags":[
        "stucco",
        "contractor"
    ],
    "wof:name":"Sweeck Andre & Zoon",
    "wof:placetype":"venue"
},
  "geometry": {"coordinates":[4.5496602058,51.0218009949],"type":"Point"}
}