{
  "type": "Feature",
  "properties": {
    "iso:country":"BE",
    "sg:address":"Guldenzandstraat 8",
    "sg:city":"Koksijde (oostduinkerke)",
    "sg:orig_category":"Non-Classified Establishments",
    "sg:phone":"+32 58 52 45 90",
    "sg:postcode":"8670",
    "sg:province":"West-Vlaanderen",
    "wof:name":"Job Tex Bvba",
    "wof:placetype":"venue"
},
  "geometry": {"coordinates":[2.6787769794,51.1180458069],"type":"Point"}
}