{
  "type": "Feature",
  "properties": {
    "addr:full":"Duinhoevelaan 4 Bredene West-Vlaanderen 8450",
    "addr:housenumber":"4",
    "addr:postcode":"8450",
    "addr:street":"Duinhoevelaan",
    "iso:country":"BE",
    "sg:address":"Duinhoevelaan 4",
    "sg:city":"Bredene",
    "sg:orig_category":"RESTAURANTS: CAF\u00c9S",
    "sg:phone":"+32 59 33 13 99",
    "sg:postcode":"8450",
    "sg:province":"West-Vlaanderen",
    "wof:name":"Taverne Boerhof",
    "wof:placetype":"venue"
},
  "geometry": {"coordinates":[2.9869580269,51.2542877197],"type":"Point"}
}