{
  "type": "Feature",
  "properties": {
    "addr:full":"Atealaan 55 Herenthout Antwerpen 2270",
    "addr:housenumber":"55",
    "addr:postcode":"2270",
    "addr:street":"Atealaan",
    "iso:country":"BE",
    "sg:address":"Atealaan 55",
    "sg:city":"Herenthout",
    "sg:classifiers":[
        {
            "category":"Shopping",
            "subcategory":"Discount & Variety Stores",
            "type":"Retail Goods"
        }
    ],
    "sg:phone":"+32 14 22 05 47",
    "sg:postcode":"2270",
    "sg:province":"Antwerpen",
    "sg:tags":[
        "warehouse",
        "-",
        "merchandise"
    ],
    "wof:name":"Jugetra Logistiek En Distributie",
    "wof:placetype":"venue"
},
  "geometry": {"coordinates":[4.7885699272,51.1608581543],"type":"Point"}
}