{
  "type": "Feature",
  "properties": {
    "iso:country":"BE",
    "sg:address":"Wielendaalstraat 3a",
    "sg:city":"Brakel",
    "sg:orig_category":"Chaussures",
    "sg:phone":"+32 55 42 53 82",
    "sg:postcode":"9660",
    "sg:province":"Oost-Vlaanderen",
    "wof:name":"Huis Scarpina",
    "wof:placetype":"venue"
},
  "geometry": {"coordinates":[3.7634279728,50.8028297424],"type":"Point"}
}