{
  "type": "Feature",
  "properties": {
    "iso:country":"BE",
    "sg:address":"Rue Neuve 1",
    "sg:city":"Jamoigne",
    "sg:classifiers":[
        {
            "category":"Airport",
            "subcategory":"International",
            "type":"Transportation"
        }
    ],
    "sg:phone":"+32 61 32 95 62",
    "sg:postcode":"6810",
    "sg:province":"Luxembourg",
    "sg:tags":[
        "transport"
    ],
    "wof:name":"Eurogaume S.a.",
    "wof:placetype":"venue"
},
  "geometry": {"coordinates":[5.419344902,49.6951332092],"type":"Point"}
}