{
  "type": "Feature",
  "properties": {
    "addr:full":"Stationsstraat 55 Gistel West-Vlaanderen 8470",
    "addr:housenumber":"55",
    "addr:postcode":"8470",
    "addr:street":"Stationsstraat",
    "iso:country":"BE",
    "sg:address":"Stationsstraat 55",
    "sg:city":"Gistel",
    "sg:orig_category":"Schoonheidssalons",
    "sg:phone":"+32 59 27 65 57",
    "sg:postcode":"8470",
    "sg:province":"West-Vlaanderen",
    "wof:name":"F. Vandekerckhove",
    "wof:placetype":"venue"
},
  "geometry": {"coordinates":[2.9639549255,51.154876709],"type":"Point"}
}