{
  "type": "Feature",
  "properties": {
    "iso:country":"BE",
    "sg:address":"Rue De La Gourmette 10",
    "sg:city":"Braine-le-comte",
    "sg:orig_category":"Installation de menuiserie en bois and plastique",
    "sg:phone":"+32 67 67 09 00",
    "sg:postcode":"7090",
    "sg:province":"Hainaut",
    "wof:name":"Verdoodt",
    "wof:placetype":"venue"
},
  "geometry": {"coordinates":[4.1759262085,50.6464271545],"type":"Point"}
}