{
  "type": "Feature",
  "properties": {
    "iso:country":"BE",
    "sg:address":"Steenovenstraat 14bc",
    "sg:city":"Hechtel-eksel",
    "sg:orig_category":"Aardappelproducten Gh Groenten and fruit Gh",
    "sg:phone":"+32 11 73 30 59",
    "sg:postcode":"3941",
    "sg:province":"Limburg",
    "wof:name":"Agga",
    "wof:placetype":"venue"
},
  "geometry": {"coordinates":[5.3824920654,51.1497039795],"type":"Point"}
}