{
  "type": "Feature",
  "properties": {
    "addr:full":"Bergensesteenweg 92 Sint-pieters-leeuw Vlaams-Brabant 1600",
    "addr:housenumber":"92",
    "addr:postcode":"1600",
    "addr:street":"Bergensesteenweg",
    "iso:country":"BE",
    "sg:address":"Bergensesteenweg 92",
    "sg:city":"Sint-pieters-leeuw",
    "sg:orig_category":"Herstellingen and onderhoud van auto's Voertuigen",
    "sg:phone":"+32 2 377 13 41",
    "sg:postcode":"1600",
    "sg:province":"Vlaams-Brabant",
    "wof:name":"Jos Auto",
    "wof:placetype":"venue"
},
  "geometry": {"coordinates":[4.2887802124,50.8051681519],"type":"Point"}
}