{
  "type": "Feature",
  "properties": {
    "addr:full":"Bullange 334 B\u00dcllingen/bullange Li\u00e8ge 4760",
    "addr:housenumber":"334",
    "addr:postcode":"4760",
    "addr:street":"Bullange",
    "iso:country":"BE",
    "sg:address":"Bullange 334",
    "sg:city":"B\u00dcllingen/bullange",
    "sg:orig_category":"Avocats and conseillers juridiques",
    "sg:phone":"+32 80 64 77 82",
    "sg:postcode":"4760",
    "sg:province":"Li\u00e8ge",
    "wof:name":"A. Haas",
    "wof:placetype":"venue"
},
  "geometry": {"coordinates":[6.304910183,50.4083137512],"type":"Point"}
}