{
  "type": "Feature",
  "properties": {
    "addr:full":"Hof Somergem 45 Aalst Oost-Vlaanderen 9300",
    "addr:housenumber":"45",
    "addr:postcode":"9300",
    "addr:street":"Somergem",
    "iso:country":"BE",
    "sg:address":"Hof Somergem 45",
    "sg:city":"Aalst",
    "sg:orig_category":"Artsen and specialisten",
    "sg:phone":"+32 53 71 19 69",
    "sg:postcode":"9300",
    "sg:province":"Oost-Vlaanderen",
    "wof:name":"R. Musch",
    "wof:placetype":"venue"
},
  "geometry": {"coordinates":[4.0828609467,50.9318351746],"type":"Point"}
}