{
  "type": "Feature",
  "properties": {
    "iso:country":"BE",
    "sg:address":"Academiestraat 7-9",
    "sg:city":"Brugge",
    "sg:classifiers":[
        {
            "category":"Manufacturing",
            "subcategory":"Furniture",
            "type":"Manufacturing & Wholesale Goods"
        }
    ],
    "sg:phone":"+32 50 33 84 24",
    "sg:postcode":"8000",
    "sg:province":"West-Vlaanderen",
    "sg:tags":[
        "design",
        "-"
    ],
    "wof:name":"Du Foss\u00e9 Bvba",
    "wof:placetype":"venue"
},
  "geometry": {"coordinates":[3.2243790627,51.2114105225],"type":"Point"}
}