{
  "type": "Feature",
  "properties": {
    "iso:country":"BE",
    "sg:address":"Nethestraat 18",
    "sg:city":"Hechtel-eksel",
    "sg:orig_category":"Meubles D\u00e9taillants, Am\u00e9nagement de B\u00e2timents et de Cuisines",
    "sg:phone":"+32 11 73 46 57",
    "sg:postcode":"3941",
    "sg:province":"Limburg",
    "wof:name":"Haegebaert Meubel Agent.",
    "wof:placetype":"venue"
},
  "geometry": {"coordinates":[5.3616042137,51.1471214294],"type":"Point"}
}