{
  "type": "Feature",
  "properties": {
    "iso:country":"BE",
    "sg:address":"Rue Henri Petit 2",
    "sg:city":"La Louviere",
    "sg:orig_category":"Foto-uitrusting Fotografen and fotostudio's",
    "sg:phone":"+32 64 21 57 61",
    "sg:postcode":"7100",
    "sg:province":"Hainaut",
    "wof:name":"Studio Arfeli",
    "wof:placetype":"venue"
},
  "geometry": {"coordinates":[4.2073302269,50.485408783],"type":"Point"}
}