{
  "type": "Feature",
  "properties": {
    "iso:country":"BE",
    "sg:address":"Kindekensstraat 14c",
    "sg:city":"Gooik",
    "sg:classifiers":[
        {
            "category":"Health Services",
            "subcategory":"Dentist",
            "type":"Services"
        }
    ],
    "sg:phone":"+32 54 34 12 83",
    "sg:postcode":"1755",
    "sg:province":"Vlaams-Brabant",
    "wof:name":"Pappaert Karen",
    "wof:placetype":"venue"
},
  "geometry": {"coordinates":[4.0861940384,50.8006248474],"type":"Point"}
}