{
  "type": "Feature",
  "properties": {
    "addr:full":"Kamperbaan 8 Hechtel-eksel (hechtel) Limburg 3940",
    "addr:housenumber":"8",
    "addr:postcode":"3940",
    "addr:street":"Kamperbaan",
    "iso:country":"BE",
    "sg:address":"Kamperbaan 8",
    "sg:city":"Hechtel-eksel (hechtel)",
    "sg:classifiers":[
        {
            "category":"Food & Beverages",
            "subcategory":"Supermarket",
            "type":"Retail Goods"
        }
    ],
    "sg:phone":"+32 11 73 23 75",
    "sg:postcode":"3940",
    "sg:province":"Limburg",
    "sg:tags":[
        "department",
        "store"
    ],
    "wof:name":"Primi",
    "wof:placetype":"venue"
},
  "geometry": {"coordinates":[5.364795208,51.1255340576],"type":"Point"}
}