{
  "type": "Feature",
  "properties": {
    "iso:country":"BE",
    "sg:address":"Raveschootstraat 19",
    "sg:city":"Gent",
    "sg:classifiers":[
        {
            "category":"Insurance",
            "subcategory":"Life Insurance",
            "type":"Services"
        }
    ],
    "sg:phone":"+32 9 225 94 06",
    "sg:postcode":"9000",
    "sg:province":"Oost-Vlaanderen",
    "sg:tags":[
        "assurance"
    ],
    "wof:name":"Verzekeringen De Kerchove",
    "wof:placetype":"venue"
},
  "geometry": {"coordinates":[3.7339909077,51.0412902832],"type":"Point"}
}