{
  "type": "Feature",
  "properties": {
    "addr:full":"Martelarenstraat 13 Vilvoorde Vlaams-Brabant 1800",
    "addr:housenumber":"13",
    "addr:postcode":"1800",
    "addr:street":"Martelarenstraat",
    "iso:country":"BE",
    "sg:address":"Martelarenstraat 13",
    "sg:city":"Vilvoorde",
    "sg:orig_category":"Kapsalons",
    "sg:phone":"+32 2 252 00 93",
    "sg:postcode":"1800",
    "sg:province":"Vlaams-Brabant",
    "wof:name":"Coiffure Chantal",
    "wof:placetype":"venue"
},
  "geometry": {"coordinates":[4.4523100853,50.9296989441],"type":"Point"}
}