{
  "type": "Feature",
  "properties": {
    "addr:full":"Chauss\u00e9e De Tirlemont 4 Braives Li\u00e8ge 4260",
    "addr:housenumber":"4",
    "addr:postcode":"4260",
    "addr:street":"Chausse\u0301E De Tirlemont",
    "iso:country":"BE",
    "sg:address":"Chauss\u00e9e De Tirlemont 4",
    "sg:city":"Braives",
    "sg:classifiers":[
        {
            "category":"Building & Trades",
            "subcategory":"Equipment Rental",
            "type":"Services"
        }
    ],
    "sg:phone":"+32 19 69 71 36",
    "sg:postcode":"4260",
    "sg:province":"Li\u00e8ge",
    "sg:tags":[
        "use",
        "apparatus",
        "tool",
        "-",
        "professional",
        "machines"
    ],
    "wof:name":"Hesbaye Location Sprl",
    "wof:placetype":"venue"
},
  "geometry": {"coordinates":[5.1542711258,50.6364097595],"type":"Point"}
}