{
  "type": "Feature",
  "properties": {
    "addr:full":"Industrielaan 135 Brussel Bruxelles-Capitale 1070",
    "addr:housenumber":"135",
    "addr:postcode":"1070",
    "addr:street":"Industrielaan",
    "iso:country":"BE",
    "sg:address":"Industrielaan 135",
    "sg:city":"Brussel",
    "sg:orig_category":"Picnic Coolers",
    "sg:phone":"+32 2 582 81 70",
    "sg:postcode":"1070",
    "sg:province":"Bruxelles-Capitale",
    "wof:name":"Coolstar Nv",
    "wof:placetype":"venue"
},
  "geometry": {"coordinates":[4.3078942299,50.8185272217],"type":"Point"}
}