{
  "type": "Feature",
  "properties": {
    "addr:full":"Rue De L'astia 8 Gerpinnes Hainaut 6280",
    "addr:housenumber":"8",
    "addr:postcode":"6280",
    "addr:street":"Rue De L'Astia;Hainaut",
    "iso:country":"BE",
    "sg:address":"Rue De L'astia 8",
    "sg:city":"Gerpinnes",
    "sg:classifiers":[
        {
            "category":"Real Estate",
            "subcategory":"Architect",
            "type":"Services"
        }
    ],
    "sg:phone":"+32 71 50 27 48",
    "sg:postcode":"6280",
    "sg:province":"Hainaut",
    "wof:name":"Busine Ph",
    "wof:placetype":"venue"
},
  "geometry": {"coordinates":[4.5401329994,50.3254966736],"type":"Point"}
}