{
  "type": "Feature",
  "properties": {
    "addr:full":"Rue De La Libert\u00c9 12 Charleroi Hainaut 6044",
    "addr:housenumber":"12",
    "addr:postcode":"6044",
    "addr:street":"Rue De La Liberte\u0301;Hainaut",
    "iso:country":"BE",
    "sg:address":"Rue De La Libert\u00c9 12",
    "sg:city":"Charleroi",
    "sg:orig_category":"Sociale huisvestingsmaatschappijen",
    "sg:phone":"+32 71 46 80 81",
    "sg:postcode":"6044",
    "sg:province":"Hainaut",
    "wof:name":"Maisons Roviennes",
    "wof:placetype":"venue"
},
  "geometry": {"coordinates":[4.3921627998,50.4473266602],"type":"Point"}
}