{
  "type": "Feature",
  "properties": {
    "iso:country":"BE",
    "sg:address":"Aux Roches 4",
    "sg:city":"Herbeumont",
    "sg:orig_category":"Installation de menuiserie en bois and plastique",
    "sg:phone":"+32 61 27 87 73",
    "sg:postcode":"6887",
    "sg:province":"Luxembourg",
    "wof:name":"Jean-jacques Brevery",
    "wof:placetype":"venue"
},
  "geometry": {"coordinates":[5.2345151901,49.7819862366],"type":"Point"}
}