{
  "type": "Feature",
  "properties": {
    "iso:country":"BE",
    "sg:address":"Kard. Cardijnlaan 65b2",
    "sg:city":"Sint-niklaas",
    "sg:orig_category":"Avocats and conseillers juridiques",
    "sg:phone":"+32 3 776 77 92",
    "sg:postcode":"9100",
    "sg:province":"Oost-Vlaanderen",
    "wof:name":"Maes F.",
    "wof:placetype":"venue"
},
  "geometry": {"coordinates":[4.1402330399,51.1532363892],"type":"Point"}
}