{
  "type": "Feature",
  "properties": {
    "iso:country":"BE",
    "sg:address":"Rue Du Commerce 45ba",
    "sg:city":"Ciney",
    "sg:orig_category":"Parfumeries. Drogueries",
    "sg:phone":"+32 83 22 06 25",
    "sg:postcode":"5590",
    "sg:province":"Namur",
    "wof:name":"Di",
    "wof:placetype":"venue"
},
  "geometry": {"coordinates":[5.098608017,50.2937355042],"type":"Point"}
}