{
  "type": "Feature",
  "properties": {
    "addr:full":"Rue Des Mays 27 Fontaine-l\u00b4ev\u00caque Hainaut 6140",
    "addr:housenumber":"27",
    "addr:postcode":"6140",
    "addr:street":"Rue Des Mays;Hainaut",
    "iso:country":"BE",
    "sg:address":"Rue Des Mays 27",
    "sg:city":"Fontaine-l\u00b4ev\u00caque",
    "sg:orig_category":"Services pour animaux domestiques",
    "sg:phone":"+32 71 54 27 61",
    "sg:postcode":"6140",
    "sg:province":"Hainaut",
    "wof:name":"Chenil Des Mays",
    "wof:placetype":"venue"
},
  "geometry": {"coordinates":[4.3356318474,50.4196586609],"type":"Point"}
}