{
  "type": "Feature",
  "properties": {
    "addr:full":"J. Demolderlaan 5 De Panne West-Vlaanderen 8660",
    "addr:housenumber":"5",
    "addr:postcode":"8660",
    "addr:street":"J. Demolderlaan",
    "iso:country":"BE",
    "sg:address":"J. Demolderlaan 5",
    "sg:city":"De Panne",
    "sg:classifiers":[
        {
            "category":"Personal",
            "subcategory":"Beauty Salon",
            "type":"Services"
        }
    ],
    "sg:phone":"+32 58 41 26 41",
    "sg:postcode":"8660",
    "sg:province":"West-Vlaanderen",
    "sg:tags":[
        "lady",
        "-",
        "hairdressing"
    ],
    "wof:name":"Chris",
    "wof:placetype":"venue"
},
  "geometry": {"coordinates":[2.5930120945,51.1007614136],"type":"Point"}
}