{
  "type": "Feature",
  "properties": {
    "iso:country":"BE",
    "sg:address":"Rue Du Village 3",
    "sg:city":"Oreye",
    "sg:classifiers":[
        {
            "category":"Parking",
            "subcategory":"Lot",
            "type":"Transportation"
        }
    ],
    "sg:phone":"+32 19 67 81 43",
    "sg:postcode":"4360",
    "sg:province":"Li\u00e8ge",
    "sg:tags":[
        "parking-places",
        "laying-out"
    ],
    "wof:name":"Ch\u00e8vremont G",
    "wof:placetype":"venue"
},
  "geometry": {"coordinates":[5.3404579163,50.7210845947],"type":"Point"}
}