{
  "type": "Feature",
  "properties": {
    "addr:full":"Steenweg 201 Denderleeuw Oost-Vlaanderen 9473",
    "addr:housenumber":"201",
    "addr:postcode":"9473",
    "addr:street":"Steenweg",
    "iso:country":"BE",
    "sg:address":"Steenweg 201",
    "sg:city":"Denderleeuw",
    "sg:orig_category":"Afval and schroot Gh Voertuigen",
    "sg:phone":"+32 53 66 56 79",
    "sg:postcode":"9473",
    "sg:province":"Oost-Vlaanderen",
    "wof:name":"Garage De Cock",
    "wof:placetype":"venue"
},
  "geometry": {"coordinates":[4.05935812,50.8961372375],"type":"Point"}
}