{
  "type": "Feature",
  "properties": {
    "iso:country":"BE",
    "sg:address":"Engelstraat 44",
    "sg:city":"Ichtegem",
    "sg:classifiers":[
        {
            "category":"Insurance",
            "subcategory":"Insurance Agent",
            "type":"Services"
        }
    ],
    "sg:phone":"+32 51 58 05 40",
    "sg:postcode":"8480",
    "sg:province":"West-Vlaanderen",
    "sg:tags":[
        "verzekeringsmakelaars",
        "expert"
    ],
    "wof:name":"Luc Roelens",
    "wof:placetype":"venue"
},
  "geometry": {"coordinates":[3.0147500038,51.0930595398],"type":"Point"}
}