{
  "type": "Feature",
  "properties": {
    "addr:full":"Stationsstraat 76 Zaventem Vlaams-Brabant 1930",
    "addr:housenumber":"76",
    "addr:postcode":"1930",
    "addr:street":"Stationsstraat",
    "iso:country":"BE",
    "sg:address":"Stationsstraat 76",
    "sg:city":"Zaventem",
    "sg:orig_category":"Notarissen",
    "sg:phone":"+32 2 721 45 94",
    "sg:postcode":"1930",
    "sg:province":"Vlaams-Brabant",
    "wof:name":"M. Robberechts",
    "wof:placetype":"venue"
},
  "geometry": {"coordinates":[4.4715819359,50.8837738037],"type":"Point"}
}