{
  "type": "Feature",
  "properties": {
    "addr:full":"Huidevettersstraat 7-9 Antwerpen Antwerpen 2000",
    "addr:housenumber":"7-9",
    "addr:postcode":"2000",
    "addr:street":"Huidevettersstraat",
    "iso:country":"BE",
    "sg:address":"Huidevettersstraat 7-9",
    "sg:city":"Antwerpen",
    "sg:classifiers":[
        {
            "category":"Retail",
            "subcategory":"Repair Shop",
            "type":"Services"
        }
    ],
    "sg:phone":"+32 3 231 98 98",
    "sg:postcode":"2000",
    "sg:province":"Antwerpen",
    "sg:tags":[
        "-",
        "mainten",
        "watch",
        "clock"
    ],
    "wof:name":"Tensen Juweliers",
    "wof:placetype":"venue"
},
  "geometry": {"coordinates":[4.4055709839,51.2181930542],"type":"Point"}
}