{
  "type": "Feature",
  "properties": {
    "iso:country":"BE",
    "sg:address":"Rue De La Sault 43",
    "sg:city":"Florennes",
    "sg:classifiers":[
        {
            "category":"Arena",
            "subcategory":"Sports Club",
            "type":"Entertainment"
        }
    ],
    "sg:phone":"+32 71 68 85 30",
    "sg:postcode":"5620",
    "sg:province":"Namur",
    "sg:tags":[
        "terrain",
        "hors",
        "de",
        "installation",
        "sportifs"
    ],
    "wof:name":"R.c.s. Florennois",
    "wof:placetype":"venue"
},
  "geometry": {"coordinates":[4.6040768623,50.2552032471],"type":"Point"}
}