{
  "type": "Feature",
  "properties": {
    "iso:country":"BE",
    "sg:address":"Hendrik Consciencestraat 46",
    "sg:city":"Mechelen",
    "sg:orig_category":"Meubles D\u00e9taillants, Am\u00e9nagement de B\u00e2timents et de Cuisines",
    "sg:phone":"+32 15 45 10 63",
    "sg:postcode":"2800",
    "sg:province":"Antwerpen",
    "wof:name":"Meub. Smartline By Veka",
    "wof:placetype":"venue"
},
  "geometry": {"coordinates":[4.4823050499,51.0187187195],"type":"Point"}
}