{
  "type": "Feature",
  "properties": {
    "iso:country":"BE",
    "sg:address":"Rue De Wangenies 79",
    "sg:city":"Fleurus",
    "sg:orig_category":"Artsen and specialisten",
    "sg:phone":"+32 71 81 48 06",
    "sg:postcode":"6220",
    "sg:province":"Hainaut",
    "wof:name":"Rudy De Roover",
    "wof:placetype":"venue"
},
  "geometry": {"coordinates":[4.5265002251,50.4568710327],"type":"Point"}
}