{
  "type": "Feature",
  "properties": {
    "iso:country":"BE",
    "sg:address":"Heikant 10",
    "sg:city":"Hamont-achel (achel)",
    "sg:classifiers":[
        {
            "category":"Home & Garden",
            "subcategory":"Carpets & Floor Coverings",
            "type":"Retail Goods"
        }
    ],
    "sg:phone":"+32 11 64 48 22",
    "sg:postcode":"3930",
    "sg:province":"Limburg",
    "sg:tags":[
        "merchant",
        "iron"
    ],
    "wof:name":"Bloem Bvba",
    "wof:placetype":"venue"
},
  "geometry": {"coordinates":[5.4705700874,51.2787513733],"type":"Point"}
}