{
  "type": "Feature",
  "properties": {
    "addr:full":"Chauss\u00c9e De Namur 34 Eghez\u00c9e Namur 5310",
    "addr:housenumber":"34",
    "addr:postcode":"5310",
    "addr:street":"Chausse\u0301E De Namur",
    "iso:country":"BE",
    "sg:address":"Chauss\u00c9e De Namur 34",
    "sg:city":"Eghez\u00c9e",
    "sg:orig_category":"Epiceries",
    "sg:phone":"+32 81 81 16 04",
    "sg:postcode":"5310",
    "sg:province":"Namur",
    "wof:name":"Gb Contact",
    "wof:placetype":"venue"
},
  "geometry": {"coordinates":[4.9120731354,50.5888977051],"type":"Point"}
}