{
  "type": "Feature",
  "properties": {
    "addr:full":"Wilgenlaan 6 Ternat Vlaams-Brabant 1740",
    "addr:housenumber":"6",
    "addr:postcode":"1740",
    "addr:street":"Wilgenlaan",
    "iso:country":"BE",
    "sg:address":"Wilgenlaan 6",
    "sg:city":"Ternat",
    "sg:orig_category":"Parfumeries",
    "sg:phone":"+32 2 582 50 56",
    "sg:postcode":"1740",
    "sg:province":"Vlaams-Brabant",
    "wof:name":"Luc De Geyndt",
    "wof:placetype":"venue"
},
  "geometry": {"coordinates":[4.1885519028,50.8759384155],"type":"Point"}
}