{
  "type": "Feature",
  "properties": {
    "iso:country":"BE",
    "sg:address":"Rue De La Sablonni\u00c8re 168",
    "sg:city":"Quaregnon",
    "sg:orig_category":"Jardinage",
    "sg:phone":"+32 65 78 44 03",
    "sg:postcode":"7390",
    "sg:province":"Hainaut",
    "wof:name":"Jean Belenger",
    "wof:placetype":"venue"
},
  "geometry": {"coordinates":[3.8416140079,50.4400100708],"type":"Point"}
}