{
  "type": "Feature",
  "properties": {
    "iso:country":"BE",
    "sg:address":"Rue Des Hetres 14",
    "sg:city":"Leglise",
    "sg:orig_category":"Rundveehouders",
    "sg:phone":"+32 63 43 33 10",
    "sg:postcode":"6860",
    "sg:province":"Luxembourg",
    "wof:name":"Jose Legras",
    "wof:placetype":"venue"
},
  "geometry": {"coordinates":[5.5558691025,49.8113098145],"type":"Point"}
}