{
  "type": "Feature",
  "properties": {
    "addr:full":"Zwevegemstraat 113 Zwevegem (otegem) West-Vlaanderen 8553",
    "addr:housenumber":"113",
    "addr:postcode":"8553",
    "addr:street":"Zwevegemstraat",
    "iso:country":"BE",
    "sg:address":"Zwevegemstraat 113",
    "sg:city":"Zwevegem (otegem)",
    "sg:classifiers":[
        {
            "category":"Food & Beverages",
            "subcategory":"Groceries & Convenience Stores",
            "type":"Retail Goods"
        }
    ],
    "sg:phone":"+32 56 77 81 57",
    "sg:postcode":"8553",
    "sg:province":"West-Vlaanderen",
    "sg:tags":[
        "grocer"
    ],
    "wof:name":"Vivo",
    "wof:placetype":"venue"
},
  "geometry": {"coordinates":[3.3974099159,50.8163528442],"type":"Point"}
}