{
  "type": "Feature",
  "properties": {
    "addr:full":"Zagerijstraat 17 Tongeren Limburg 3700",
    "addr:housenumber":"17",
    "addr:postcode":"3700",
    "addr:street":"Zagerijstraat",
    "iso:country":"BE",
    "sg:address":"Zagerijstraat 17",
    "sg:city":"Tongeren",
    "sg:orig_category":"Paramedische behandelingen",
    "sg:phone":"+32 12 23 36 20",
    "sg:postcode":"3700",
    "sg:province":"Limburg",
    "wof:name":"H. Goffin",
    "wof:placetype":"venue"
},
  "geometry": {"coordinates":[5.4723238945,50.7855529785],"type":"Point"}
}