{
  "type": "Feature",
  "properties": {
    "iso:country":"BE",
    "sg:address":"Steenstraat 12",
    "sg:city":"Kortrijk",
    "sg:orig_category":"Enseignement maternel and primaire",
    "sg:phone":"+32 56 35 57 53",
    "sg:postcode":"8501",
    "sg:province":"West-Vlaanderen",
    "wof:name":"Vrije Kleuterschool",
    "wof:placetype":"venue"
},
  "geometry": {"coordinates":[3.2695770264,50.827003479],"type":"Point"}
}