{
  "type": "Feature",
  "properties": {
    "addr:full":"Rue Des Scieries 8 Weismes (robertville) Li\u00e8ge 4950",
    "addr:housenumber":"8",
    "addr:postcode":"4950",
    "addr:street":"Rue Des Scieries;Robertville",
    "iso:country":"BE",
    "sg:address":"Rue Des Scieries 8",
    "sg:city":"Weismes (robertville)",
    "sg:classifiers":[
        {
            "category":"Building & Trades",
            "subcategory":"Construction",
            "type":"Services"
        }
    ],
    "sg:phone":"+32 80 44 60 79",
    "sg:postcode":"4950",
    "sg:province":"Li\u00e8ge",
    "sg:tags":[
        "carpenter"
    ],
    "wof:name":"Andres",
    "wof:placetype":"venue"
},
  "geometry": {"coordinates":[6.1423997879,50.4709396362],"type":"Point"}
}