{
  "type": "Feature",
  "properties": {
    "addr:full":"Berteneinde 3 Herentals Antwerpen 2200",
    "addr:housenumber":"3",
    "addr:postcode":"2200",
    "addr:street":"Berteneinde",
    "iso:country":"BE",
    "sg:address":"Berteneinde 3",
    "sg:city":"Herentals",
    "sg:orig_category":"Eleveurs de bovins",
    "sg:phone":"+32 14 26 11 62",
    "sg:postcode":"2200",
    "sg:province":"Antwerpen",
    "wof:name":"Ludovicus Verswijvel",
    "wof:placetype":"venue"
},
  "geometry": {"coordinates":[4.8119840622,51.1110191345],"type":"Point"}
}