{
  "type": "Feature",
  "properties": {
    "addr:full":"Amersveldestraat 160 Kortemark West-Vlaanderen 8610",
    "addr:housenumber":"160",
    "addr:postcode":"8610",
    "addr:street":"Amersveldestraat",
    "iso:country":"BE",
    "sg:address":"Amersveldestraat 160",
    "sg:city":"Kortemark",
    "sg:orig_category":"Quincailleries. Plomberie, chauffage and installations sanitaires. Forge, Moulage and Profilage des ",
    "sg:phone":"+32 51 56 60 64",
    "sg:postcode":"8610",
    "sg:province":"West-Vlaanderen",
    "wof:name":"Vandoorne",
    "wof:placetype":"venue"
},
  "geometry": {"coordinates":[3.0153899193,51.0114479065],"type":"Point"}
}