{
  "type": "Feature",
  "properties": {
    "iso:country":"BE",
    "sg:address":"Brugsesteenweg 23",
    "sg:city":"Kuurne",
    "sg:orig_category":"Chaussures",
    "sg:phone":"+32 56 37 15 67",
    "sg:postcode":"8520",
    "sg:province":"West-Vlaanderen",
    "wof:name":"Brantano",
    "wof:placetype":"venue"
},
  "geometry": {"coordinates":[3.2693269253,50.8475952148],"type":"Point"}
}