{
  "type": "Feature",
  "properties": {
    "iso:country":"BE",
    "sg:address":"Rue D'envoz 36ba",
    "sg:city":"Heron",
    "sg:orig_category":"Entretien and r\u00e9parations de voitures",
    "sg:phone":"+32 85 71 10 98",
    "sg:postcode":"4218",
    "sg:province":"Li\u00e8ge",
    "wof:name":"Guy Delgaudine",
    "wof:placetype":"venue"
},
  "geometry": {"coordinates":[5.1461248398,50.5343971252],"type":"Point"}
}