{
  "type": "Feature",
  "properties": {
    "addr:full":"Gerheide 48 Balen Antwerpen 2490",
    "addr:housenumber":"48",
    "addr:postcode":"2490",
    "addr:street":"Gerheide",
    "iso:country":"BE",
    "sg:address":"Gerheide 48",
    "sg:city":"Balen",
    "sg:classifiers":[
        {
            "category":"Sports & Exercise",
            "subcategory":"Bowling",
            "type":"Entertainment"
        }
    ],
    "sg:phone":"+32 14 81 20 93",
    "sg:postcode":"2490",
    "sg:province":"Antwerpen",
    "sg:tags":[
        "skittle",
        "alley"
    ],
    "wof:name":"Keiheuvel",
    "wof:placetype":"venue"
},
  "geometry": {"coordinates":[5.2016320229,51.1810035706],"type":"Point"}
}