{
  "type": "Feature",
  "properties": {
    "addr:full":"Rue De Taiz\u00c9 6 Hannut Li\u00e8ge 4280",
    "addr:housenumber":"6",
    "addr:postcode":"4280",
    "addr:street":"Rue De Taize\u0301",
    "iso:country":"BE",
    "sg:address":"Rue De Taiz\u00c9 6",
    "sg:city":"Hannut",
    "sg:orig_category":"M\u00e9decins and sp\u00e9cialistes",
    "sg:phone":"+32 19 69 87 67",
    "sg:postcode":"4280",
    "sg:province":"Li\u00e8ge",
    "wof:name":"Jean-fran\u00c7ois Rosoux",
    "wof:placetype":"venue"
},
  "geometry": {"coordinates":[5.0687260628,50.6173934937],"type":"Point"}
}