{
  "type": "Feature",
  "properties": {
    "addr:full":"Heyerstraat 11 Lokeren Oost-Vlaanderen 9160",
    "addr:housenumber":"11",
    "addr:postcode":"9160",
    "addr:street":"Heyerstraat",
    "iso:country":"BE",
    "sg:address":"Heyerstraat 11",
    "sg:city":"Lokeren",
    "sg:classifiers":[
        {
            "category":"Utilities",
            "subcategory":"Natural Gas",
            "type":"Services"
        }
    ],
    "sg:phone":"+32 475 46 13 98",
    "sg:postcode":"9160",
    "sg:province":"Oost-Vlaanderen",
    "sg:tags":[
        "control",
        "tank"
    ],
    "wof:name":"Thaann Engineering Bvba",
    "wof:placetype":"venue"
},
  "geometry": {"coordinates":[3.9520978928,51.108707428],"type":"Point"}
}