{
  "type": "Feature",
  "properties": {
    "addr:full":"Rue Christian Mendiaux 33 Courcelles Hainaut 6180",
    "addr:housenumber":"33",
    "addr:postcode":"6180",
    "addr:street":"Rue Christian Mendiaux",
    "iso:country":"BE",
    "sg:address":"Rue Christian Mendiaux 33",
    "sg:city":"Courcelles",
    "sg:classifiers":[
        {
            "category":"Food & Beverages",
            "subcategory":"Groceries & Convenience Stores",
            "type":"Retail Goods"
        }
    ],
    "sg:phone":"+32 71 45 03 24",
    "sg:postcode":"6180",
    "sg:province":"Hainaut",
    "sg:tags":[
        "grocer"
    ],
    "wof:name":"Marjolaine (la)",
    "wof:placetype":"venue"
},
  "geometry": {"coordinates":[4.3667759895,50.4496421814],"type":"Point"}
}