{
  "type": "Feature",
  "properties": {
    "iso:country":"BE",
    "sg:address":"Chauss\u00c9e De Namur 15",
    "sg:city":"Eghezee",
    "sg:orig_category":"V\u00eatements",
    "sg:phone":"+32 81 81 13 84",
    "sg:postcode":"5310",
    "sg:province":"Namur",
    "wof:name":"J. Wautelet-ravignat",
    "wof:placetype":"venue"
},
  "geometry": {"coordinates":[4.9126420021,50.5899772644],"type":"Point"}
}