{
  "type": "Feature",
  "properties": {
    "addr:full":"Rue Jacquet 41bc Rochefort Namur 5580",
    "addr:housenumber":"41bc",
    "addr:postcode":"5580",
    "addr:street":"Rue Jacquet",
    "iso:country":"BE",
    "sg:address":"Rue Jacquet 41bc",
    "sg:city":"Rochefort",
    "sg:orig_category":"G\u00e9om\u00e8tres",
    "sg:phone":"+32 84 22 26 40",
    "sg:postcode":"5580",
    "sg:province":"Namur",
    "wof:name":"Olivier Blariaux",
    "wof:placetype":"venue"
},
  "geometry": {"coordinates":[5.2224521637,50.1556777954],"type":"Point"}
}