{
  "type": "Feature",
  "properties": {
    "iso:country":"BE",
    "sg:address":"Abdijstraat 6",
    "sg:city":"Sint-truiden",
    "sg:classifiers":[
        {
            "category":"Personal",
            "subcategory":"Beauty Salon",
            "type":"Services"
        }
    ],
    "sg:phone":"+32 11 69 18 19",
    "sg:postcode":"3800",
    "sg:province":"Limburg",
    "sg:tags":[
        "lady",
        "-",
        "hairdressing"
    ],
    "wof:name":"Art Coiffure Jochem",
    "wof:placetype":"venue"
},
  "geometry": {"coordinates":[5.186548233,50.8172454834],"type":"Point"}
}