{
  "type": "Feature",
  "properties": {
    "addr:full":"Franklin Rooseveltlaan 110 Brussel/bruxelles Bruxelles-Capitale 1050",
    "addr:housenumber":"110",
    "addr:postcode":"1050",
    "addr:street":"Franklin Rooseveltlaan;/",
    "iso:country":"BE",
    "sg:address":"Franklin Rooseveltlaan 110",
    "sg:city":"Brussel/bruxelles",
    "sg:orig_category":"Artsen and specialisten",
    "sg:phone":"+32 2 347 34 00",
    "sg:postcode":"1050",
    "sg:province":"Bruxelles-Capitale",
    "wof:name":"A. Flausch",
    "wof:placetype":"venue"
},
  "geometry": {"coordinates":[4.3853740692,50.8073577881],"type":"Point"}
}