{
  "type": "Feature",
  "properties": {
    "addr:full":"Stationsstraat 188 Lommel Limburg 3920",
    "addr:housenumber":"188",
    "addr:postcode":"3920",
    "addr:street":"Stationsstraat",
    "iso:country":"BE",
    "sg:address":"Stationsstraat 188",
    "sg:city":"Lommel",
    "sg:orig_category":"Pain, p\u00e2tisseries and confiseries",
    "sg:phone":"+32 11 54 40 86",
    "sg:postcode":"3920",
    "sg:province":"Limburg",
    "wof:name":"Bakkerij Kadetje",
    "wof:placetype":"venue"
},
  "geometry": {"coordinates":[5.3132300377,51.2176589966],"type":"Point"}
}