{
  "type": "Feature",
  "properties": {
    "iso:country":"BE",
    "sg:address":"Oudekapellestraat 16",
    "sg:city":"Diksmuide",
    "sg:classifiers":[
        {
            "category":"Professional",
            "subcategory":"Management & Consulting",
            "type":"Services"
        }
    ],
    "sg:phone":"+32 51 51 06 56",
    "sg:postcode":"8600",
    "sg:province":"West-Vlaanderen",
    "sg:tags":[
        "consultant"
    ],
    "wof:name":"Beltec Bvba",
    "wof:placetype":"venue"
},
  "geometry": {"coordinates":[2.8246901035,51.0308113098],"type":"Point"}
}