{
  "type": "Feature",
  "properties": {
    "addr:full":"Koning Albert I Laan 13 Nieuwpoort West-Vlaanderen 8620",
    "addr:housenumber":"13",
    "addr:postcode":"8620",
    "addr:street":"Koning Albert I Laan",
    "iso:country":"BE",
    "sg:address":"Koning Albert I Laan 13",
    "sg:city":"Nieuwpoort",
    "sg:orig_category":"Supermarkten",
    "sg:postcode":"8620",
    "sg:province":"West-Vlaanderen",
    "wof:name":"Aldi",
    "wof:placetype":"venue"
},
  "geometry": {"coordinates":[2.7401540279,51.1380119324],"type":"Point"}
}