{
  "type": "Feature",
  "properties": {
    "addr:full":"Dorpsstraat 69 Erpe-mere Oost-Vlaanderen 9420",
    "addr:housenumber":"69",
    "addr:postcode":"9420",
    "addr:street":"Dorpsstraat",
    "iso:country":"BE",
    "sg:address":"Dorpsstraat 69",
    "sg:city":"Erpe-mere",
    "sg:classifiers":[
        {
            "category":"Personal",
            "subcategory":"Beauty Salon",
            "type":"Services"
        }
    ],
    "sg:phone":"+32 53 80 09 77",
    "sg:postcode":"9420",
    "sg:province":"Oost-Vlaanderen",
    "sg:tags":[
        "de",
        "coiffure"
    ],
    "wof:name":"Coiffure Anita",
    "wof:placetype":"venue"
},
  "geometry": {"coordinates":[3.9778990746,50.9348526001],"type":"Point"}
}