{
  "type": "Feature",
  "properties": {
    "addr:full":"Avenue Fran\u00e7ois Cornesse 48 Aywaille Li\u00e8ge 4920",
    "addr:housenumber":"48",
    "addr:postcode":"4920",
    "addr:street":"Avenue Franc\u0327Ois Cornesse",
    "iso:country":"BE",
    "sg:address":"Avenue Fran\u00e7ois Cornesse 48",
    "sg:city":"Aywaille",
    "sg:classifiers":[
        {
            "category":"Education",
            "subcategory":"School",
            "type":"Public Place"
        }
    ],
    "sg:phone":"+32 4 384 43 84",
    "sg:postcode":"4920",
    "sg:province":"Li\u00e8ge",
    "sg:tags":[
        "boarding"
    ],
    "wof:name":"Athen\u00e9e Royal D'aywaille",
    "wof:placetype":"venue"
},
  "geometry": {"coordinates":[5.6728978157,50.4746055603],"type":"Point"}
}