{
  "type": "Feature",
  "properties": {
    "iso:country":"BE",
    "sg:address":"Reytenstraat 63",
    "sg:city":"Geel",
    "sg:orig_category":"Fruitteelt",
    "sg:phone":"+32 14 58 61 13",
    "sg:postcode":"2440",
    "sg:province":"Antwerpen",
    "wof:name":"Guy Cools",
    "wof:placetype":"venue"
},
  "geometry": {"coordinates":[4.9387879372,51.1791038513],"type":"Point"}
}