{
  "type": "Feature",
  "properties": {
    "iso:country":"BE",
    "sg:address":"Brusselsesteenweg 49",
    "sg:city":"Halle",
    "sg:orig_category":"Peinture. Rev\u00eatements pour sols and murs",
    "sg:phone":"+32 2 356 30 04",
    "sg:postcode":"1500",
    "sg:province":"Vlaams-Brabant",
    "wof:name":"Luc Destrycker Decorette",
    "wof:placetype":"venue"
},
  "geometry": {"coordinates":[4.2379350662,50.7387084961],"type":"Point"}
}