{
  "type": "Feature",
  "properties": {
    "iso:country":"BE",
    "sg:address":"Bremelshoef 7",
    "sg:city":"Retie",
    "sg:orig_category":"Varkenskwekers",
    "sg:phone":"+32 14 37 98 09",
    "sg:postcode":"2470",
    "sg:province":"Antwerpen",
    "wof:name":"Viktor Van Bael",
    "wof:placetype":"venue"
},
  "geometry": {"coordinates":[5.0288858414,51.2747192383],"type":"Point"}
}