{
  "type": "Feature",
  "properties": {
    "iso:country":"BE",
    "sg:address":"Rue De Clavier 16",
    "sg:city":"Clavier",
    "sg:orig_category":"Paramedische behandelingen Schoonheidssalons",
    "sg:phone":"+32 85 41 25 56",
    "sg:postcode":"4560",
    "sg:province":"Li\u00e8ge",
    "wof:name":"Septon",
    "wof:placetype":"venue"
},
  "geometry": {"coordinates":[5.3144369125,50.4218521118],"type":"Point"}
}