{
  "type": "Feature",
  "properties": {
    "addr:full":"Stagestraat 4 Waregem West-Vlaanderen 8791",
    "addr:housenumber":"4",
    "addr:postcode":"8791",
    "addr:street":"Stagestraat",
    "iso:country":"BE",
    "sg:address":"Stagestraat 4",
    "sg:city":"Waregem",
    "sg:orig_category":"Sportclubs",
    "sg:phone":"+32 56 71 77 15",
    "sg:postcode":"8791",
    "sg:province":"West-Vlaanderen",
    "wof:name":"W.c. Sport Na Arbeid",
    "wof:placetype":"venue"
},
  "geometry": {"coordinates":[3.3561561108,50.8778533936],"type":"Point"}
}