{
  "type": "Feature",
  "properties": {
    "iso:country":"BE",
    "sg:address":"Rue De Remicourt 63",
    "sg:city":"Donceel (limont)",
    "sg:classifiers":[
        {
            "category":"Professional",
            "subcategory":"Computer Services",
            "type":"Services"
        }
    ],
    "sg:phone":"+32 495 30 45 51",
    "sg:postcode":"4357",
    "sg:province":"Li\u00e8ge",
    "sg:tags":[
        "repair",
        "processing",
        "-",
        "maintenance",
        "data"
    ],
    "wof:name":"Picchi M",
    "wof:placetype":"venue"
},
  "geometry": {"coordinates":[5.3206958771,50.6466445923],"type":"Point"}
}