{
  "type": "Feature",
  "properties": {
    "addr:full":"Schilsweg 83 Eupen/eupen Li\u00e8ge 4700",
    "addr:housenumber":"83",
    "addr:postcode":"4700",
    "addr:street":"Schilsweg",
    "iso:country":"BE",
    "sg:address":"Schilsweg 83",
    "sg:city":"Eupen/eupen",
    "sg:orig_category":"Artistes ind\u00e9pendants",
    "sg:phone":"+32 87 74 40 89",
    "sg:postcode":"4700",
    "sg:province":"Li\u00e8ge",
    "wof:name":"Hugh Blyth",
    "wof:placetype":"venue"
},
  "geometry": {"coordinates":[6.0427799225,50.6202507019],"type":"Point"}
}