{
  "type": "Feature",
  "properties": {
    "iso:country":"BE",
    "sg:address":"Sonnistraat 105",
    "sg:city":"Houthalen-helchteren",
    "sg:orig_category":"Woningbouw",
    "sg:phone":"+32 11 52 50 95",
    "sg:postcode":"3530",
    "sg:province":"Limburg",
    "wof:name":"Winters",
    "wof:placetype":"venue"
},
  "geometry": {"coordinates":[5.3719201088,51.0310020447],"type":"Point"}
}