{
  "type": "Feature",
  "properties": {
    "addr:full":"Rue Des Trieux 17-19 Houdeng-goegnies Hainaut 7110",
    "addr:housenumber":"17-19",
    "addr:postcode":"7110",
    "addr:street":"Rue Des Trieux",
    "iso:country":"BE",
    "sg:address":"Rue Des Trieux 17-19",
    "sg:city":"Houdeng-goegnies",
    "sg:orig_category":"HERSTELLING ELEKTRISCHE HUISHOUDAPPARATEN Huishoudapparaten, televisies and radio's Verlichting and ",
    "sg:phone":"+32 64 22 29 04",
    "sg:postcode":"7110",
    "sg:province":"Hainaut",
    "wof:name":"Cauchie",
    "wof:placetype":"venue"
},
  "geometry": {"coordinates":[4.1562519073,50.4878883362],"type":"Point"}
}