{
  "type": "Feature",
  "properties": {
    "addr:full":"Westhoeklaan 46 De Panne West-Vlaanderen 8660",
    "addr:housenumber":"46",
    "addr:postcode":"8660",
    "addr:street":"Westhoeklaan",
    "iso:country":"BE",
    "sg:address":"Westhoeklaan 46",
    "sg:city":"De Panne",
    "sg:orig_category":"Catering and organisatie van feesten Fast food and meeneem restaurants Levering aan huis restaurants",
    "sg:phone":"+32 58 42 05 42",
    "sg:postcode":"8660",
    "sg:province":"West-Vlaanderen",
    "wof:name":"De Peperbusse",
    "wof:placetype":"venue"
},
  "geometry": {"coordinates":[2.5835440159,51.0939407349],"type":"Point"}
}