{
  "type": "Feature",
  "properties": {
    "iso:country":"BE",
    "sg:address":"Rue Du Mont 32",
    "sg:city":"Saint-hubert",
    "sg:orig_category":"Woningbouw",
    "sg:phone":"+32 61 61 19 12",
    "sg:postcode":"6870",
    "sg:province":"Luxembourg",
    "wof:name":"Legrand Freddy",
    "wof:placetype":"venue"
},
  "geometry": {"coordinates":[5.3746390343,50.0246047974],"type":"Point"}
}