{
  "type": "Feature",
  "properties": {
    "addr:full":"Wippelgem Dorp 48 Evergem Oost-Vlaanderen 9940",
    "addr:housenumber":"48",
    "addr:postcode":"9940",
    "addr:street":"Wippelgem Dorp;Oost-Vlaanderen",
    "iso:country":"BE",
    "sg:address":"Wippelgem Dorp 48",
    "sg:city":"Evergem",
    "sg:classifiers":[
        {
            "category":"Shopping",
            "subcategory":"Bicycles & Sporting Goods",
            "type":"Retail Goods"
        }
    ],
    "sg:phone":"+32 9 357 62 35",
    "sg:postcode":"9940",
    "sg:province":"Oost-Vlaanderen",
    "sg:tags":[
        "-"
    ],
    "wof:name":"Van Hecke M",
    "wof:placetype":"venue"
},
  "geometry": {"coordinates":[3.7316761017,51.142868042],"type":"Point"}
}