{
  "type": "Feature",
  "properties": {
    "addr:full":"Diepestraat 9 Ukkel Bruxelles-Capitale 1180",
    "addr:housenumber":"9",
    "addr:postcode":"1180",
    "addr:street":"Diepestraat",
    "iso:country":"BE",
    "sg:address":"Diepestraat 9",
    "sg:city":"Ukkel",
    "sg:classifiers":[
        {
            "category":"Fast Food",
            "type":"Food & Drink"
        }
    ],
    "sg:phone":"+32 2 375 40 93",
    "sg:postcode":"1180",
    "sg:province":"Bruxelles-Capitale",
    "sg:tags":[
        "meeneem",
        "restaurant"
    ],
    "wof:name":"Restaurant Le Siamois",
    "wof:placetype":"venue"
},
  "geometry": {"coordinates":[4.3524250984,50.7920036316],"type":"Point"}
}