{
  "type": "Feature",
  "properties": {
    "iso:country":"BE",
    "sg:address":"Place De La Vaillance 12",
    "sg:city":"Anderlecht",
    "sg:orig_category":"RESTAURANTS: CAF\u00c9S",
    "sg:phone":"+32 2 522 06 03",
    "sg:postcode":"1070",
    "sg:province":"Bruxelles-Capitale",
    "wof:name":"Taverne Le Vincennes",
    "wof:placetype":"venue"
},
  "geometry": {"coordinates":[4.3065848351,50.8360786438],"type":"Point"}
}