{
  "type": "Feature",
  "properties": {
    "iso:country":"BE",
    "sg:address":"Elderberg 41",
    "sg:city":"Aalst (baardegem)",
    "sg:classifiers":[
        {
            "category":"Banks & Credit Unions",
            "subcategory":"Investment Brokerage",
            "type":"Services"
        }
    ],
    "sg:phone":"+32 52 35 01 45",
    "sg:postcode":"9310",
    "sg:province":"Oost-Vlaanderen",
    "sg:tags":[
        "-",
        "plastic"
    ],
    "wof:name":"Rmd Plastiek",
    "wof:placetype":"venue"
},
  "geometry": {"coordinates":[4.1341500282,50.9514045715],"type":"Point"}
}