{
  "type": "Feature",
  "properties": {
    "addr:full":"Tervuursesteenweg 2 Mechelen Antwerpen 2800",
    "addr:housenumber":"2",
    "addr:postcode":"2800",
    "addr:street":"Tervuursesteenweg",
    "iso:country":"BE",
    "sg:address":"Tervuursesteenweg 2",
    "sg:city":"Mechelen",
    "sg:orig_category":"Technisch and beroeps secundair onderwijs",
    "sg:phone":"+32 15 42 27 03",
    "sg:postcode":"2800",
    "sg:province":"Antwerpen",
    "wof:name":"Instituut Coloma",
    "wof:placetype":"venue"
},
  "geometry": {"coordinates":[4.483066082,51.0139884949],"type":"Point"}
}