{
  "type": "Feature",
  "properties": {
    "addr:full":"Rue Des Acacias 16 Ciney Namur 5590",
    "addr:housenumber":"16",
    "addr:postcode":"5590",
    "addr:street":"Rue Des Acacias",
    "iso:country":"BE",
    "sg:address":"Rue Des Acacias 16",
    "sg:city":"Ciney",
    "sg:classifiers":[
        {
            "category":"Arena",
            "subcategory":"Sports Club",
            "type":"Entertainment"
        }
    ],
    "sg:phone":"+32 83 21 37 01",
    "sg:postcode":"5590",
    "sg:province":"Namur",
    "sg:tags":[
        "terrain",
        "hors",
        "de",
        "installation",
        "sportifs"
    ],
    "wof:name":"F.l.t. Sports Et Loisirs",
    "wof:placetype":"venue"
},
  "geometry": {"coordinates":[5.1022520065,50.297088623],"type":"Point"}
}