{
  "type": "Feature",
  "properties": {
    "addr:full":"Kiewitstraat 192 Hasselt Limburg 3500",
    "addr:housenumber":"192",
    "addr:postcode":"3500",
    "addr:street":"Kiewitstraat",
    "iso:country":"BE",
    "sg:address":"Kiewitstraat 192",
    "sg:city":"Hasselt",
    "sg:orig_category":"Transports terrestres de voyageurs",
    "sg:phone":"+32 11 21 22 11",
    "sg:postcode":"3500",
    "sg:province":"Limburg",
    "wof:name":"St Catharina Cars",
    "wof:placetype":"venue"
},
  "geometry": {"coordinates":[5.389070034,50.9657783508],"type":"Point"}
}