{
  "type": "Feature",
  "properties": {
    "iso:country":"BE",
    "sg:address":"Rue Fays 4",
    "sg:city":"Flemalle",
    "sg:orig_category":"Ruimtes voor conferenties, recepties and feesten",
    "sg:phone":"+32 4 275 14 16",
    "sg:postcode":"4400",
    "sg:province":"Li\u00e8ge",
    "wof:name":"Salons Li Vi Fays",
    "wof:placetype":"venue"
},
  "geometry": {"coordinates":[5.4435310364,50.5835533142],"type":"Point"}
}