{
  "type": "Feature",
  "properties": {
    "iso:country":"BE",
    "sg:address":"Zoning Ouest 11",
    "sg:city":"Lessines",
    "sg:classifiers":[
        {
            "category":"Manufacturing",
            "subcategory":"Signs",
            "type":"Manufacturing & Wholesale Goods"
        }
    ],
    "sg:phone":"+32 68 33 64 24",
    "sg:postcode":"7860",
    "sg:province":"Hainaut",
    "sg:tags":[
        "-",
        "illuminated"
    ],
    "wof:name":"Color Design",
    "wof:placetype":"venue"
},
  "geometry": {"coordinates":[3.8223800659,50.7023658752],"type":"Point"}
}