{
  "type": "Feature",
  "properties": {
    "iso:country":"BE",
    "sg:address":"Place Du 12\u00c8me De Ligne 2",
    "sg:city":"Herstal",
    "sg:orig_category":"RESTAURANTS: LIVRAISON \u00c0 DOMICILE",
    "sg:phone":"+32 4 264 87 47",
    "sg:postcode":"4040",
    "sg:province":"Li\u00e8ge",
    "wof:name":"Pizza-bona",
    "wof:placetype":"venue"
},
  "geometry": {"coordinates":[5.6404471397,50.67345047],"type":"Point"}
}