{
  "type": "Feature",
  "properties": {
    "addr:full":"Bergstraat 67 Overijse Vlaams-Brabant 3090",
    "addr:housenumber":"67",
    "addr:postcode":"3090",
    "addr:street":"Bergstraat",
    "iso:country":"BE",
    "sg:address":"Bergstraat 67",
    "sg:city":"Overijse",
    "sg:orig_category":"Fruitteelt",
    "sg:phone":"+32 2 687 46 01",
    "sg:postcode":"3090",
    "sg:province":"Vlaams-Brabant",
    "wof:name":"Vanderlinden",
    "wof:placetype":"venue"
},
  "geometry": {"coordinates":[4.554831028,50.7533569336],"type":"Point"}
}