{
  "type": "Feature",
  "properties": {
    "iso:country":"BE",
    "sg:address":"Stationsstraat 83",
    "sg:city":"Lanaken",
    "sg:classifiers":[
        {
            "category":"Restaurant",
            "type":"Food & Drink"
        }
    ],
    "sg:phone":"+32 89 73 17 92",
    "sg:postcode":"3620",
    "sg:province":"Limburg",
    "sg:tags":[
        "caf\u00e9s"
    ],
    "wof:name":"The New Remember",
    "wof:placetype":"venue"
},
  "geometry": {"coordinates":[5.6480250359,50.8874168396],"type":"Point"}
}