{
  "type": "Feature",
  "properties": {
    "addr:full":"Rooshaegenweg 69 Maasmechelen Limburg 3630",
    "addr:housenumber":"69",
    "addr:postcode":"3630",
    "addr:street":"Rooshaegenweg",
    "iso:country":"BE",
    "sg:address":"Rooshaegenweg 69",
    "sg:city":"Maasmechelen",
    "sg:orig_category":"M\u00e9decins and sp\u00e9cialistes",
    "sg:phone":"+32 89 76 47 35",
    "sg:postcode":"3630",
    "sg:province":"Limburg",
    "wof:name":"Michel Bollen",
    "wof:placetype":"venue"
},
  "geometry": {"coordinates":[5.6948890686,50.9709472656],"type":"Point"}
}