{
  "type": "Feature",
  "properties": {
    "addr:full":"Haaggatstraat 59 Kortenberg (erps-kwerps) Vlaams-Brabant 3071",
    "addr:housenumber":"59",
    "addr:postcode":"3071",
    "addr:street":"Haaggatstraat",
    "iso:country":"BE",
    "sg:address":"Haaggatstraat 59",
    "sg:city":"Kortenberg (erps-kwerps)",
    "sg:classifiers":[
        {
            "category":"Building & Trades",
            "subcategory":"Pest Control",
            "type":"Services"
        }
    ],
    "sg:phone":"+32 2 757 00 34",
    "sg:postcode":"3071",
    "sg:province":"Vlaams-Brabant",
    "sg:tags":[
        "painting",
        "contractor"
    ],
    "wof:name":"Borremans R",
    "wof:placetype":"venue"
},
  "geometry": {"coordinates":[4.5806617737,50.9064598083],"type":"Point"}
}