{
  "type": "Feature",
  "properties": {
    "addr:full":"Rue Du Temple 6 Brunehaut Hainaut 7623",
    "addr:housenumber":"6",
    "addr:postcode":"7623",
    "addr:street":"Rue Du Temple",
    "iso:country":"BE",
    "sg:address":"Rue Du Temple 6",
    "sg:city":"Brunehaut",
    "sg:orig_category":"P\u00e9pini\u00e9ristes",
    "sg:phone":"+32 69 34 44 41",
    "sg:postcode":"7623",
    "sg:province":"Hainaut",
    "wof:name":"Fe. Legrain-duhem",
    "wof:placetype":"venue"
},
  "geometry": {"coordinates":[3.3935689926,50.5068626404],"type":"Point"}
}