{
  "type": "Feature",
  "properties": {
    "iso:country":"BE",
    "sg:address":"Patersveld 32",
    "sg:city":"Beringen",
    "sg:orig_category":"Eclairage et \u00e9quipements du foyer",
    "sg:phone":"+32 475 38 00 61",
    "sg:postcode":"3583",
    "sg:province":"Limburg",
    "wof:name":"Barrez I",
    "wof:placetype":"venue"
},
  "geometry": {"coordinates":[5.1706700325,51.0389442444],"type":"Point"}
}