{
  "type": "Feature",
  "properties": {
    "iso:country":"BE",
    "sg:address":"Rue Bel Horizon 9",
    "sg:city":"Hotton",
    "sg:classifiers":[
        {
            "category":"Building & Trades",
            "subcategory":"Landscaping Services",
            "type":"Services"
        }
    ],
    "sg:phone":"+32 84 46 66 28",
    "sg:postcode":"6990",
    "sg:province":"Luxembourg",
    "sg:tags":[
        "etude",
        "technique",
        "ing\u00e9nierie"
    ],
    "wof:name":"Etudes Techniques",
    "wof:placetype":"venue"
},
  "geometry": {"coordinates":[5.4393692017,50.2650985718],"type":"Point"}
}