{
  "type": "Feature",
  "properties": {
    "iso:country":"BE",
    "sg:address":"Leeuwerikstraat 24",
    "sg:city":"Antwerpen",
    "sg:orig_category":"Drogueries",
    "sg:phone":"+32 3 231 62 84",
    "sg:postcode":"2018",
    "sg:province":"Antwerpen",
    "wof:name":"Huis Van De Zande",
    "wof:placetype":"venue"
},
  "geometry": {"coordinates":[4.4241948128,51.2126922607],"type":"Point"}
}