{
  "type": "Feature",
  "properties": {
    "iso:country":"BE",
    "sg:address":"Cit\u00c9 Delr\u00c9e 28",
    "sg:city":"Esneux",
    "sg:orig_category":"V\u00e9t\u00e9rinaires",
    "sg:phone":"+32 4 366 40 33",
    "sg:postcode":"4130",
    "sg:province":"Li\u00e8ge",
    "wof:name":"Dominique Votion",
    "wof:placetype":"venue"
},
  "geometry": {"coordinates":[5.5669360161,50.5327568054],"type":"Point"}
}