{
  "type": "Feature",
  "properties": {
    "addr:full":"Hopmarkt 35 Aalst Oost-Vlaanderen 9300",
    "addr:housenumber":"35",
    "addr:postcode":"9300",
    "addr:street":"Hopmarkt",
    "iso:country":"BE",
    "sg:address":"Hopmarkt 35",
    "sg:city":"Aalst",
    "sg:orig_category":"Epiceries",
    "sg:phone":"+32 53 70 95 65",
    "sg:postcode":"9300",
    "sg:province":"Oost-Vlaanderen",
    "wof:name":"Mila",
    "wof:placetype":"venue"
},
  "geometry": {"coordinates":[4.0364289284,50.9371643066],"type":"Point"}
}