{
  "type": "Feature",
  "properties": {
    "iso:country":"BE",
    "sg:address":"Oude Bruglaan 27a",
    "sg:city":"Lokeren",
    "sg:classifiers":[
        {
            "category":"Health Services",
            "subcategory":"Health Practitioner",
            "type":"Services"
        }
    ],
    "sg:phone":"+32 9 348 36 78",
    "sg:postcode":"9160",
    "sg:province":"Oost-Vlaanderen",
    "sg:tags":[
        "physiotherapist"
    ],
    "wof:name":"Hillaert E",
    "wof:placetype":"venue"
},
  "geometry": {"coordinates":[4.0013561249,51.1037979126],"type":"Point"}
}