{
  "type": "Feature",
  "properties": {
    "addr:full":"Oranjestraat 107 Antwerpen Antwerpen 2060",
    "addr:housenumber":"107",
    "addr:postcode":"2060",
    "addr:street":"Oranjestraat",
    "iso:country":"BE",
    "sg:address":"Oranjestraat 107",
    "sg:city":"Antwerpen",
    "sg:classifiers":[
        {
            "category":"Building & Trades",
            "subcategory":"Construction",
            "type":"Services"
        }
    ],
    "sg:phone":"+32 3 664 32 82",
    "sg:postcode":"2060",
    "sg:province":"Antwerpen",
    "sg:tags":[
        "ceiling"
    ],
    "wof:name":"Kab Bvba",
    "wof:placetype":"venue"
},
  "geometry": {"coordinates":[4.4238739014,51.2283325195],"type":"Point"}
}