{
  "type": "Feature",
  "properties": {
    "iso:country":"BE",
    "sg:address":"Rechtestraat 65",
    "sg:city":"Lille",
    "sg:classifiers":[
        {
            "category":"Professional",
            "subcategory":"Testing Lab",
            "type":"Services"
        }
    ],
    "sg:phone":"+32 14 88 19 12",
    "sg:postcode":"2275",
    "sg:province":"Antwerpen",
    "sg:tags":[
        "chemist"
    ],
    "wof:name":"Apotheek Sas Nv",
    "wof:placetype":"venue"
},
  "geometry": {"coordinates":[4.8230471611,51.2409973145],"type":"Point"}
}