{
  "type": "Feature",
  "properties": {
    "iso:country":"BE",
    "sg:address":"Hoogstraat 35",
    "sg:city":"Brasschaat",
    "sg:classifiers":[
        {
            "category":"Arena",
            "subcategory":"Sports Club",
            "type":"Entertainment"
        }
    ],
    "sg:phone":"+32 3 652 03 09",
    "sg:postcode":"2930",
    "sg:province":"Antwerpen",
    "sg:tags":[
        "de"
    ],
    "wof:name":"Olse Merksem T.c.",
    "wof:placetype":"venue"
},
  "geometry": {"coordinates":[4.4728951454,51.3089561462],"type":"Point"}
}