{
  "type": "Feature",
  "properties": {
    "addr:full":"Neerpedestraat 180 Anderlecht/anderlecht Bruxelles-Capitale 1070",
    "addr:housenumber":"180",
    "addr:postcode":"1070",
    "addr:street":"Neerpedestraat",
    "iso:country":"BE",
    "sg:address":"Neerpedestraat 180",
    "sg:city":"Anderlecht/anderlecht",
    "sg:orig_category":"Krantenwinkels Rookartikelen",
    "sg:phone":"+32 2 521 35 83",
    "sg:postcode":"1070",
    "sg:province":"Bruxelles-Capitale",
    "wof:name":"Samuel Frydman",
    "wof:placetype":"venue"
},
  "geometry": {"coordinates":[4.2923240662,50.8319854736],"type":"Point"}
}