{
  "type": "Feature",
  "properties": {
    "iso:country":"BE",
    "sg:address":"Rue Des Alli\u00c9s 40",
    "sg:city":"Merbes-le-chateau",
    "sg:orig_category":"HUISBRANDOLIE",
    "sg:phone":"+32 64 77 25 19",
    "sg:postcode":"6567",
    "sg:province":"Hainaut",
    "wof:name":"Douillez",
    "wof:placetype":"venue"
},
  "geometry": {"coordinates":[4.1712460518,50.3618736267],"type":"Point"}
}