{
  "type": "Feature",
  "properties": {
    "addr:full":"Steenberghoekstraat 12b1 Rumst Antwerpen 2840",
    "addr:housenumber":"12b1",
    "addr:postcode":"2840",
    "addr:street":"Steenberghoekstraat",
    "iso:country":"BE",
    "sg:address":"Steenberghoekstraat 12b1",
    "sg:city":"Rumst",
    "sg:orig_category":"Loodgieterij, verwarming and sanitaire installaties",
    "sg:phone":"+32 3 288 52 75",
    "sg:postcode":"2840",
    "sg:province":"Antwerpen",
    "wof:name":"Kerremans",
    "wof:placetype":"venue"
},
  "geometry": {"coordinates":[4.4207229614,51.0802345276],"type":"Point"}
}