{
  "type": "Feature",
  "properties": {
    "iso:country":"BE",
    "sg:address":"Rue Haute 147",
    "sg:city":"Bruxelles",
    "sg:classifiers":[
        {
            "category":"Social Services",
            "type":"Services"
        }
    ],
    "sg:phone":"+32 2 505 37 00",
    "sg:postcode":"1000",
    "sg:province":"Bruxelles-Capitale",
    "wof:name":"Belgische Technische Co\u00f6rperatie (btc)",
    "wof:placetype":"venue"
},
  "geometry": {"coordinates":[4.3499631882,50.8384208679],"type":"Point"}
}