{
  "type": "Feature",
  "properties": {
    "iso:country":"BE",
    "sg:address":"Kalsbergstraat 43",
    "sg:city":"Landen",
    "sg:orig_category":"Installation de menuiserie en bois and plastique",
    "sg:phone":"+32 11 88 13 63",
    "sg:postcode":"3400",
    "sg:province":"Vlaams-Brabant",
    "wof:name":"Pascal Clos",
    "wof:placetype":"venue"
},
  "geometry": {"coordinates":[5.0726418495,50.7448196411],"type":"Point"}
}