{
  "type": "Feature",
  "properties": {
    "addr:full":"Moverkensstraat 63a Zonhoven Limburg 3520",
    "addr:housenumber":"63a",
    "addr:postcode":"3520",
    "addr:street":"Moverkensstraat",
    "iso:country":"BE",
    "sg:address":"Moverkensstraat 63a",
    "sg:city":"Zonhoven",
    "sg:orig_category":"Charpentes and couvertures",
    "sg:phone":"+32 11 82 52 31",
    "sg:postcode":"3520",
    "sg:province":"Limburg",
    "wof:name":"Adrien Jordens",
    "wof:placetype":"venue"
},
  "geometry": {"coordinates":[5.3319468498,50.9923858643],"type":"Point"}
}