{
  "type": "Feature",
  "properties": {
    "addr:full":"Terre A Briques 5 Marquain Hainaut 7522",
    "addr:housenumber":"5",
    "addr:postcode":"7522",
    "addr:street":"Marquain Hainaut",
    "iso:country":"BE",
    "sg:address":"Terre A Briques 5",
    "sg:city":"Marquain",
    "sg:orig_category":"Royal Canin. Royal Canin. Animaux domestiques and accessoires",
    "sg:phone":"+32 69 21 45 23",
    "sg:postcode":"7522",
    "sg:province":"Hainaut",
    "wof:name":"Aux 1000 Poissons",
    "wof:placetype":"venue"
},
  "geometry": {"coordinates":[3.3337230682,50.6075363159],"type":"Point"}
}