{
  "type": "Feature",
  "properties": {
    "addr:full":"Grote Baan 96 Ravels Antwerpen 2380",
    "addr:housenumber":"96",
    "addr:postcode":"2380",
    "addr:street":"Grote Baan",
    "iso:country":"BE",
    "sg:address":"Grote Baan 96",
    "sg:city":"Ravels",
    "sg:orig_category":"Apotheken",
    "sg:phone":"+32 14 65 53 42",
    "sg:postcode":"2380",
    "sg:province":"Antwerpen",
    "wof:name":"Apotheek Dehaene-pouillon",
    "wof:placetype":"venue"
},
  "geometry": {"coordinates":[4.992046833,51.3662796021],"type":"Point"}
}