{
  "type": "Feature",
  "properties": {
    "addr:full":"Rue Rodolphe Bernard 9 Sprimont Li\u00e8ge 4140",
    "addr:housenumber":"9",
    "addr:postcode":"4140",
    "addr:street":"Rue Rodolphe Bernard",
    "iso:country":"BE",
    "sg:address":"Rue Rodolphe Bernard 9",
    "sg:city":"Sprimont",
    "sg:classifiers":[
        {
            "category":"Bakery",
            "type":"Food & Drink"
        }
    ],
    "sg:phone":"+32 4 369 32 49",
    "sg:postcode":"4140",
    "sg:province":"Li\u00e8ge",
    "sg:tags":[
        "confectioner",
        "baker"
    ],
    "wof:name":"Damhaut F",
    "wof:placetype":"venue"
},
  "geometry": {"coordinates":[5.5968151093,50.5026359558],"type":"Point"}
}