{
  "type": "Feature",
  "properties": {
    "addr:full":"Rue De L'institut 45 Soumagne Li\u00e8ge 4632",
    "addr:housenumber":"45",
    "addr:postcode":"4632",
    "addr:street":"Rue De L'Institut",
    "iso:country":"BE",
    "sg:address":"Rue De L'institut 45",
    "sg:city":"Soumagne",
    "sg:orig_category":"Artsen and specialisten",
    "sg:phone":"+32 4 377 31 31",
    "sg:postcode":"4632",
    "sg:province":"Li\u00e8ge",
    "wof:name":"Patricia Pottier",
    "wof:placetype":"venue"
},
  "geometry": {"coordinates":[5.7184491158,50.6559028625],"type":"Point"}
}