{
  "type": "Feature",
  "properties": {
    "addr:full":"Lange Zoutstraat 43 Aalst Oost-Vlaanderen 9300",
    "addr:housenumber":"43",
    "addr:postcode":"9300",
    "addr:street":"Lange Zoutstraat",
    "iso:country":"BE",
    "sg:address":"Lange Zoutstraat 43",
    "sg:city":"Aalst",
    "sg:classifiers":[
        {
            "category":"Utilities",
            "subcategory":"Telephone",
            "type":"Services"
        }
    ],
    "sg:phone":"+32 53 72 97 80",
    "sg:postcode":"9300",
    "sg:province":"Oost-Vlaanderen",
    "sg:tags":[
        "house",
        "phone",
        "telecommunicatieapparaten"
    ],
    "wof:name":"The Phone House",
    "wof:placetype":"venue"
},
  "geometry": {"coordinates":[4.0394148827,50.9368019104],"type":"Point"}
}