{
  "type": "Feature",
  "properties": {
    "addr:full":"Rue De Marbais 1a Villers-la-ville Brabant Wallon 1495",
    "addr:housenumber":"1a",
    "addr:postcode":"1495",
    "addr:street":"Rue De Marbais",
    "iso:country":"BE",
    "sg:address":"Rue De Marbais 1a",
    "sg:city":"Villers-la-ville",
    "sg:classifiers":[
        {
            "category":"Fast Food",
            "type":"Food & Drink"
        }
    ],
    "sg:phone":"+32 71 87 54 01",
    "sg:postcode":"1495",
    "sg:province":"Brabant Wallon",
    "sg:tags":[
        "fried",
        "stand",
        "potato"
    ],
    "wof:name":"Ibis",
    "wof:placetype":"venue"
},
  "geometry": {"coordinates":[4.5312042236,50.5769958496],"type":"Point"}
}