{
  "type": "Feature",
  "properties": {
    "addr:full":"Rue Du Pont 44 Li\u00c8ge Li\u00e8ge 4000",
    "addr:housenumber":"44",
    "addr:postcode":"4000",
    "addr:street":"Rue Du Pont",
    "iso:country":"BE",
    "sg:address":"Rue Du Pont 44",
    "sg:city":"Li\u00c8ge",
    "sg:orig_category":"Slagers",
    "sg:phone":"+32 4 223 53 47",
    "sg:postcode":"4000",
    "sg:province":"Li\u00e8ge",
    "wof:name":"Boucherie Moustaquim",
    "wof:placetype":"venue"
},
  "geometry": {"coordinates":[5.5776281357,50.6447525024],"type":"Point"}
}