{
  "type": "Feature",
  "properties": {
    "addr:full":"Avenue Bl\u00fccher 199 Bruxelles (uccle) Bruxelles-Capitale 1180",
    "addr:housenumber":"199",
    "addr:postcode":"1180",
    "addr:street":"Avenue Bluecher",
    "iso:country":"BE",
    "sg:address":"Avenue Bl\u00fccher 199",
    "sg:city":"Bruxelles (uccle)",
    "sg:classifiers":[
        {
            "category":"Retail",
            "subcategory":"Veterinary Services",
            "type":"Services"
        }
    ],
    "sg:phone":"+32 2 375 43 63",
    "sg:postcode":"1180",
    "sg:province":"Bruxelles-Capitale",
    "sg:tags":[
        "veterinarian"
    ],
    "wof:name":"Massart S",
    "wof:placetype":"venue"
},
  "geometry": {"coordinates":[4.3664851189,50.7748908997],"type":"Point"}
}