{
  "type": "Feature",
  "properties": {
    "addr:full":"Groenstraat 2 Ingelmunster West-Vlaanderen 8770",
    "addr:housenumber":"2",
    "addr:postcode":"8770",
    "addr:street":"Groenstraat",
    "iso:country":"BE",
    "sg:address":"Groenstraat 2",
    "sg:city":"Ingelmunster",
    "sg:orig_category":"Plomberie, chauffage and installations sanitaires",
    "sg:phone":"+32 51 30 23 77",
    "sg:postcode":"8770",
    "sg:province":"West-Vlaanderen",
    "wof:name":"Willy Maes",
    "wof:placetype":"venue"
},
  "geometry": {"coordinates":[3.2485909462,50.9288978577],"type":"Point"}
}