{
  "type": "Feature",
  "properties": {
    "addr:full":"Rue Reine Astrid 83-b Charleroi (dampremy) Hainaut 6020",
    "addr:housenumber":"83-b",
    "addr:postcode":"6020",
    "addr:street":"Rue Reine Astrid",
    "iso:country":"BE",
    "sg:address":"Rue Reine Astrid 83-b",
    "sg:city":"Charleroi (dampremy)",
    "sg:classifiers":[
        {
            "category":"Personal",
            "subcategory":"Beauty Salon",
            "type":"Services"
        }
    ],
    "sg:phone":"+32 71 30 27 67",
    "sg:postcode":"6020",
    "sg:province":"Hainaut",
    "sg:tags":[
        "lady",
        "-",
        "hairdressing"
    ],
    "wof:name":"Top Mod\u00e8le",
    "wof:placetype":"venue"
},
  "geometry": {"coordinates":[4.4170761108,50.4195976257],"type":"Point"}
}