{
  "type": "Feature",
  "properties": {
    "iso:country":"BE",
    "sg:address":"Bld S. Dupuis",
    "sg:city":"Anderlecht",
    "sg:orig_category":"R\u00e9parations d'appareils \u00e9lectrom\u00e9nagers. Mat\u00e9riel de T\u00e9l\u00e9communication. Electrom\u00e9nager, t\u00e9l\u00e9visions ",
    "sg:phone":"+32 2 524 00 50",
    "sg:postcode":"1070",
    "sg:province":"Bruxelles-Capitale",
    "wof:name":"Vandenborre",
    "wof:placetype":"venue"
},
  "geometry": {"coordinates":[4.2849850655,50.8378715515],"type":"Point"}
}