{
  "type": "Feature",
  "properties": {
    "addr:full":"Chauss\u00c9e De Louvain 79 Eghezee Namur 5310",
    "addr:housenumber":"79",
    "addr:postcode":"5310",
    "addr:street":"Chausse\u0301E De Louvain;Namur",
    "iso:country":"BE",
    "sg:address":"Chauss\u00c9e De Louvain 79",
    "sg:city":"Eghezee",
    "sg:orig_category":"Benzinestations and brandstoffen",
    "sg:phone":"+32 81 81 16 80",
    "sg:postcode":"5310",
    "sg:province":"Namur",
    "wof:name":"Car Motor Service",
    "wof:placetype":"venue"
},
  "geometry": {"coordinates":[4.9067211151,50.5966644287],"type":"Point"}
}