{
  "type": "Feature",
  "properties": {
    "iso:country":"BE",
    "sg:address":"Schooldreef 100",
    "sg:city":"Mol",
    "sg:orig_category":"Kapsalons",
    "sg:phone":"+32 14 81 11 00",
    "sg:postcode":"2400",
    "sg:province":"Antwerpen",
    "wof:name":"Kapsalon Godelieve",
    "wof:placetype":"venue"
},
  "geometry": {"coordinates":[5.2065730095,51.2086105347],"type":"Point"}
}