{
  "type": "Feature",
  "properties": {
    "addr:full":"Chauss\u00c9e De Bruxelles 93 Charleroi Hainaut 6020",
    "addr:housenumber":"93",
    "addr:postcode":"6020",
    "addr:street":"Chausse\u0301E De Bruxelles;Hainaut",
    "iso:country":"BE",
    "sg:address":"Chauss\u00c9e De Bruxelles 93",
    "sg:city":"Charleroi",
    "sg:orig_category":"HUISBRANDOLIE Loodgieterij, verwarming and sanitaire installaties",
    "sg:phone":"+32 71 70 14 96",
    "sg:postcode":"6020",
    "sg:province":"Hainaut",
    "wof:name":"Amoroso-petroleum Serv.",
    "wof:placetype":"venue"
},
  "geometry": {"coordinates":[4.4371790886,50.4141082764],"type":"Point"}
}