{
  "type": "Feature",
  "properties": {
    "addr:full":"Herrebeekstraat 50 Kortenaken Vlaams-Brabant 3471",
    "addr:housenumber":"50",
    "addr:postcode":"3471",
    "addr:street":"Herrebeekstraat",
    "iso:country":"BE",
    "sg:address":"Herrebeekstraat 50",
    "sg:city":"Kortenaken",
    "sg:orig_category":"Etalage- and showroomontwerpers",
    "sg:phone":"+32 475 56 83 71",
    "sg:postcode":"3471",
    "sg:province":"Vlaams-Brabant",
    "wof:name":"Etalages Tensy",
    "wof:placetype":"venue"
},
  "geometry": {"coordinates":[5.0043921471,50.8596420288],"type":"Point"}
}