{
  "type": "Feature",
  "properties": {
    "iso:country":"BE",
    "sg:address":"Nederstraat 52",
    "sg:city":"Oudenaarde",
    "sg:classifiers":[
        {
            "category":"Shopping",
            "subcategory":"Clothing, Apparel, & Fashions",
            "type":"Retail Goods"
        }
    ],
    "sg:phone":"+32 55 31 20 06",
    "sg:postcode":"9700",
    "sg:province":"Oost-Vlaanderen",
    "sg:tags":[
        "lady",
        "clothing",
        "-"
    ],
    "wof:name":"Van Der Haeghen",
    "wof:placetype":"venue"
},
  "geometry": {"coordinates":[3.6027269363,50.845199585],"type":"Point"}
}