{
  "type": "Feature",
  "properties": {
    "addr:full":"Rue D\u00b4astenet 19 Lontzen Li\u00e8ge 4711",
    "addr:housenumber":"19",
    "addr:postcode":"4711",
    "addr:street":"Rue D\u00b4Astenet",
    "iso:country":"BE",
    "sg:address":"Rue D\u00b4astenet 19",
    "sg:city":"Lontzen",
    "sg:classifiers":[
        {
            "category":"Arena",
            "subcategory":"Sports Club",
            "type":"Entertainment"
        }
    ],
    "sg:phone":"+32 87 65 85 79",
    "sg:postcode":"4711",
    "sg:province":"Li\u00e8ge",
    "sg:tags":[
        "de"
    ],
    "wof:name":"Schwimverein Delphin",
    "wof:placetype":"venue"
},
  "geometry": {"coordinates":[6.0351700783,50.6874504089],"type":"Point"}
}