{
  "type": "Feature",
  "properties": {
    "addr:full":"Zeebruggestraat 57 Lier Antwerpen 2500",
    "addr:housenumber":"57",
    "addr:postcode":"2500",
    "addr:street":"Zeebruggestraat",
    "iso:country":"BE",
    "sg:address":"Zeebruggestraat 57",
    "sg:city":"Lier",
    "sg:classifiers":[
        {
            "category":"Health Services",
            "subcategory":"Doctor",
            "type":"Services"
        }
    ],
    "sg:phone":"+32 3 480 28 63",
    "sg:postcode":"2500",
    "sg:province":"Antwerpen",
    "sg:tags":[
        "medicinephysicians",
        "surgeon"
    ],
    "wof:name":"Docx Martine",
    "wof:placetype":"venue"
},
  "geometry": {"coordinates":[4.569229126,51.1413574219],"type":"Point"}
}