{
  "type": "Feature",
  "properties": {
    "addr:full":"Nerenbroekstraat 34 Erpe-mere Oost-Vlaanderen 9420",
    "addr:housenumber":"34",
    "addr:postcode":"9420",
    "addr:street":"Nerenbroekstraat",
    "iso:country":"BE",
    "sg:address":"Nerenbroekstraat 34",
    "sg:city":"Erpe-mere",
    "sg:orig_category":"Eclairage et \u00e9quipements du foyer. Electrom\u00e9nager, t\u00e9l\u00e9visions and radios",
    "sg:phone":"+32 53 80 07 10",
    "sg:postcode":"9420",
    "sg:province":"Oost-Vlaanderen",
    "wof:name":"Flight Cases",
    "wof:placetype":"venue"
},
  "geometry": {"coordinates":[3.9732680321,50.9434127808],"type":"Point"}
}