{
  "type": "Feature",
  "properties": {
    "addr:full":"Kleine Laan 11 Sint-niklaas Oost-Vlaanderen 9100",
    "addr:housenumber":"11",
    "addr:postcode":"9100",
    "addr:street":"Kleine Laan",
    "iso:country":"BE",
    "sg:address":"Kleine Laan 11",
    "sg:city":"Sint-niklaas",
    "sg:classifiers":[
        {
            "category":"Cafe",
            "type":"Food & Drink"
        }
    ],
    "sg:phone":"+32 3 776 78 13",
    "sg:postcode":"9100",
    "sg:province":"Oost-Vlaanderen",
    "sg:tags":[
        "caf\u00e9s"
    ],
    "wof:name":"Viviane Vercauteren",
    "wof:placetype":"venue"
},
  "geometry": {"coordinates":[4.1399641037,51.1698722839],"type":"Point"}
}