{
  "type": "Feature",
  "properties": {
    "iso:country":"BE",
    "sg:address":"Rue De La Moinerie 12",
    "sg:city":"Verviers",
    "sg:orig_category":"Industri\u00eble wasserijen and droogkuis",
    "sg:phone":"+32 87 31 06 29",
    "sg:postcode":"4800",
    "sg:province":"Li\u00e8ge",
    "wof:name":"Pressing Service",
    "wof:placetype":"venue"
},
  "geometry": {"coordinates":[5.857940197,50.5888633728],"type":"Point"}
}