{
  "type": "Feature",
  "properties": {
    "iso:country":"BE",
    "sg:address":"Rue Juslenville-petite 14",
    "sg:city":"Theux",
    "sg:classifiers":[
        {
            "category":"Arena",
            "subcategory":"Sports Club",
            "type":"Entertainment"
        }
    ],
    "sg:phone":"+32 87 46 02 41",
    "sg:postcode":"4910",
    "sg:province":"Li\u00e8ge",
    "wof:name":"Forges Thiry (man\u00e8ge)",
    "wof:placetype":"venue"
},
  "geometry": {"coordinates":[5.8046588898,50.5463371277],"type":"Point"}
}