{
  "type": "Feature",
  "properties": {
    "addr:full":"Avenue Georges Henri 295 Sint-lambrechts-woluwe/woluwe-saint-lambert Bruxelles-Capitale 1200",
    "addr:housenumber":"295;/",
    "addr:postcode":"1200",
    "addr:street":"Avenue Georges Henri;Sint-Lambrechts-Woluwe",
    "iso:country":"BE",
    "sg:address":"Avenue Georges Henri 295",
    "sg:city":"Sint-lambrechts-woluwe/woluwe-saint-lambert",
    "sg:orig_category":"V\u00e9hicules automobiles. Entretien and r\u00e9parations de voitures",
    "sg:phone":"+32 2 733 50 47",
    "sg:postcode":"1200",
    "sg:province":"Bruxelles-Capitale",
    "wof:name":"Garage Vandeweerd",
    "wof:placetype":"venue"
},
  "geometry": {"coordinates":[4.4124889374,50.8436584473],"type":"Point"}
}