{
  "type": "Feature",
  "properties": {
    "iso:country":"BE",
    "sg:address":"Clarissenstraat 0",
    "sg:city":"Tongeren",
    "sg:orig_category":"Sportcentra",
    "sg:phone":"+32 12 23 86 72",
    "sg:postcode":"3700",
    "sg:province":"Limburg",
    "wof:name":"Eburonenhal",
    "wof:placetype":"venue"
},
  "geometry": {"coordinates":[5.4697608948,50.7817420959],"type":"Point"}
}