{
  "type": "Feature",
  "properties": {
    "addr:full":"A. Rodenbachstraat 73ba Denderleeuw Oost-Vlaanderen 9470",
    "addr:housenumber":"73ba",
    "addr:postcode":"9470",
    "addr:street":"A. Rodenbachstraat",
    "iso:country":"BE",
    "sg:address":"A. Rodenbachstraat 73ba",
    "sg:city":"Denderleeuw",
    "sg:orig_category":"M\u00e9decins and sp\u00e9cialistes",
    "sg:phone":"+32 53 66 33 78",
    "sg:postcode":"9470",
    "sg:province":"Oost-Vlaanderen",
    "wof:name":"J. De Dier",
    "wof:placetype":"venue"
},
  "geometry": {"coordinates":[4.0680589676,50.8951454163],"type":"Point"}
}