{
  "type": "Feature",
  "properties": {
    "addr:full":"Statiestraat 3 Zwijndrecht Antwerpen 2070",
    "addr:housenumber":"3",
    "addr:postcode":"2070",
    "addr:street":"Statiestraat",
    "iso:country":"BE",
    "sg:address":"Statiestraat 3",
    "sg:city":"Zwijndrecht",
    "sg:classifiers":[
        {
            "category":"Cafe",
            "type":"Food & Drink"
        }
    ],
    "sg:phone":"+32 3 252 64 97",
    "sg:postcode":"2070",
    "sg:province":"Antwerpen",
    "sg:tags":[
        "caf\u00e9s"
    ],
    "wof:name":"Caf\u00c9 De Oude Werf",
    "wof:placetype":"venue"
},
  "geometry": {"coordinates":[4.3263230324,51.2188568115],"type":"Point"}
}