{
  "type": "Feature",
  "properties": {
    "iso:country":"BE",
    "sg:address":"Rue Des Pr\u00c9s 2",
    "sg:city":"Hamois",
    "sg:orig_category":"Kapsalons",
    "sg:phone":"+32 83 61 21 82",
    "sg:postcode":"5364",
    "sg:province":"Namur",
    "wof:name":"Mady",
    "wof:placetype":"venue"
},
  "geometry": {"coordinates":[5.1259012222,50.3584022522],"type":"Point"}
}