{
  "type": "Feature",
  "properties": {
    "iso:country":"BE",
    "sg:address":"Rue Faurieux 72",
    "sg:city":"Herstal",
    "sg:classifiers":[
        {
            "category":"Professional",
            "subcategory":"Art Services",
            "type":"Services"
        }
    ],
    "sg:phone":"+32 475 25 57 29",
    "sg:postcode":"4040",
    "sg:province":"Li\u00e8ge",
    "sg:tags":[
        "automobile",
        "transit",
        "-",
        "export",
        "import"
    ],
    "wof:name":"Cartoine",
    "wof:placetype":"venue"
},
  "geometry": {"coordinates":[5.6269497871,50.6658287048],"type":"Point"}
}