{
  "type": "Feature",
  "properties": {
    "iso:country":"BE",
    "sg:address":"Mechelsesteenweg 190",
    "sg:city":"Zaventem",
    "sg:orig_category":"Dameskledingzaken Herenkledingzaken",
    "sg:phone":"+32 2 731 23 44",
    "sg:postcode":"1930",
    "sg:province":"Vlaams-Brabant",
    "wof:name":"Textiel Paula",
    "wof:placetype":"venue"
},
  "geometry": {"coordinates":[4.5100698471,50.8712692261],"type":"Point"}
}