{
  "type": "Feature",
  "properties": {
    "addr:full":"Rue De Birmingham 131 Bruxelles (anderlecht) Bruxelles-Capitale 1070",
    "addr:housenumber":"131",
    "addr:postcode":"1070",
    "addr:street":"Rue De Birmingham",
    "iso:country":"BE",
    "sg:address":"Rue De Birmingham 131",
    "sg:city":"Bruxelles (anderlecht)",
    "sg:classifiers":[
        {
            "category":"Professional",
            "subcategory":"Management & Consulting",
            "type":"Services"
        }
    ],
    "sg:phone":"+32 2 526 55 11",
    "sg:postcode":"1070",
    "sg:province":"Bruxelles-Capitale",
    "sg:tags":[
        "consultant",
        "agency",
        "advertising"
    ],
    "wof:name":"Echo (l')",
    "wof:placetype":"venue"
},
  "geometry": {"coordinates":[4.3221869469,50.8454627991],"type":"Point"}
}