{
  "type": "Feature",
  "properties": {
    "addr:full":"Stationsstraat 85 Hamont-achel Limburg 3930",
    "addr:housenumber":"85",
    "addr:postcode":"3930",
    "addr:street":"Stationsstraat",
    "iso:country":"BE",
    "sg:address":"Stationsstraat 85",
    "sg:city":"Hamont-achel",
    "sg:orig_category":"Pharmaciens",
    "sg:phone":"+32 11 44 67 92",
    "sg:postcode":"3930",
    "sg:province":"Limburg",
    "wof:name":"Apotheek Plessers",
    "wof:placetype":"venue"
},
  "geometry": {"coordinates":[5.5450549126,51.2511863708],"type":"Point"}
}