{
  "type": "Feature",
  "properties": {
    "addr:full":"Gentsesteenweg 64 Zingem (ouwegem) Oost-Vlaanderen 9750",
    "addr:housenumber":"64",
    "addr:postcode":"9750",
    "addr:street":"Gentsesteenweg",
    "iso:country":"BE",
    "sg:address":"Gentsesteenweg 64",
    "sg:city":"Zingem (ouwegem)",
    "sg:classifiers":[
        {
            "category":"Home & Garden",
            "subcategory":"Carpets & Floor Coverings",
            "type":"Retail Goods"
        }
    ],
    "sg:phone":"+32 9 384 94 37",
    "sg:postcode":"9750",
    "sg:province":"Oost-Vlaanderen",
    "sg:tags":[
        "parquet"
    ],
    "wof:name":"Demeyer",
    "wof:placetype":"venue"
},
  "geometry": {"coordinates":[3.6178469658,50.9111328125],"type":"Point"}
}