{
  "type": "Feature",
  "properties": {
    "addr:full":"Heuveneindeweg 85 Zonhoven Limburg 3520",
    "addr:housenumber":"85",
    "addr:postcode":"3520",
    "addr:street":"Heuveneindeweg",
    "iso:country":"BE",
    "sg:address":"Heuveneindeweg 85",
    "sg:city":"Zonhoven",
    "sg:classifiers":[
        {
            "category":"Shopping",
            "subcategory":"Crafts & Fabrics",
            "type":"Retail Goods"
        }
    ],
    "sg:phone":"+32 11 81 87 12",
    "sg:postcode":"3520",
    "sg:province":"Limburg",
    "sg:tags":[
        "silk",
        "-"
    ],
    "wof:name":"Buretex",
    "wof:placetype":"venue"
},
  "geometry": {"coordinates":[5.3641290665,50.975944519],"type":"Point"}
}