{
  "type": "Feature",
  "properties": {
    "iso:country":"BE",
    "sg:address":"Rue De Goz\u00c9e 426",
    "sg:city":"Montigny-le-tilleul",
    "sg:orig_category":"Ordinateurs and \u00e9quipement informatique",
    "sg:phone":"+32 71 51 95 14",
    "sg:postcode":"6110",
    "sg:province":"Hainaut",
    "wof:name":"D.s.a.",
    "wof:placetype":"venue"
},
  "geometry": {"coordinates":[4.3699789047,50.3768768311],"type":"Point"}
}