{
  "type": "Feature",
  "properties": {
    "addr:full":"Chauss\u00e9e De Mons 205 Beaumont Hainaut 6500",
    "addr:housenumber":"205",
    "addr:postcode":"6500",
    "addr:street":"Chausse\u0301E De Mons;Hainaut",
    "iso:country":"BE",
    "sg:address":"Chauss\u00e9e De Mons 205",
    "sg:city":"Beaumont",
    "sg:classifiers":[
        {
            "category":"Health Services",
            "subcategory":"Doctor",
            "type":"Services"
        }
    ],
    "sg:phone":"+32 71 58 94 04",
    "sg:postcode":"6500",
    "sg:province":"Hainaut",
    "sg:tags":[
        "medicinephysicians",
        "surgeon"
    ],
    "wof:name":"Leclercq Alfred",
    "wof:placetype":"venue"
},
  "geometry": {"coordinates":[4.2353157997,50.2410697937],"type":"Point"}
}