{
  "type": "Feature",
  "properties": {
    "addr:full":"Hoogstraat 5 Haaltert Oost-Vlaanderen 9450",
    "addr:housenumber":"5",
    "addr:postcode":"9450",
    "addr:street":"Hoogstraat",
    "iso:country":"BE",
    "sg:address":"Hoogstraat 5",
    "sg:city":"Haaltert",
    "sg:classifiers":[
        {
            "category":"Shopping",
            "subcategory":"Clothing, Apparel, & Fashions",
            "type":"Retail Goods"
        }
    ],
    "sg:phone":"+32 53 84 82 00",
    "sg:postcode":"9450",
    "sg:province":"Oost-Vlaanderen",
    "sg:tags":[
        "lingerie",
        "sous-v\u00eatements"
    ],
    "wof:name":"Begi\u00b4s Lingerie",
    "wof:placetype":"venue"
},
  "geometry": {"coordinates":[3.9973220825,50.8941040039],"type":"Point"}
}