{
  "type": "Feature",
  "properties": {
    "addr:full":"Meensesteenweg 487 Kortrijk (bissegem) West-Vlaanderen 8501",
    "addr:housenumber":"487",
    "addr:postcode":"8501",
    "addr:street":"Meensesteenweg",
    "iso:country":"BE",
    "sg:address":"Meensesteenweg 487",
    "sg:city":"Kortrijk (bissegem)",
    "sg:classifiers":[
        {
            "category":"Freight",
            "type":"Transportation"
        }
    ],
    "sg:phone":"+32 56 35 92 79",
    "sg:postcode":"8501",
    "sg:province":"West-Vlaanderen",
    "sg:tags":[
        "-",
        "refrigerated",
        "transport"
    ],
    "wof:name":"Rino Trans",
    "wof:placetype":"venue"
},
  "geometry": {"coordinates":[3.2218830585,50.8201370239],"type":"Point"}
}