{
  "type": "Feature",
  "properties": {
    "addr:full":"Haaggatstraat 30 Kortenberg (erps-kwerps) Vlaams-Brabant 3071",
    "addr:housenumber":"30",
    "addr:postcode":"3071",
    "addr:street":"Haaggatstraat",
    "iso:country":"BE",
    "sg:address":"Haaggatstraat 30",
    "sg:city":"Kortenberg (erps-kwerps)",
    "sg:classifiers":[
        {
            "category":"Building & Trades",
            "subcategory":"Landscaping Services",
            "type":"Services"
        }
    ],
    "sg:phone":"+32 2 757 24 04",
    "sg:postcode":"3071",
    "sg:province":"Vlaams-Brabant",
    "sg:tags":[
        "gardening",
        "garden",
        "maintenance"
    ],
    "wof:name":"Olbrechts F",
    "wof:placetype":"venue"
},
  "geometry": {"coordinates":[4.5756258965,50.9052963257],"type":"Point"}
}