{
  "type": "Feature",
  "properties": {
    "iso:country":"BE",
    "sg:address":"Avenue Gustave Demey 72-74",
    "sg:city":"Bruxelles (auderghem)",
    "sg:classifiers":[
        {
            "category":"Building & Trades",
            "subcategory":"Construction",
            "type":"Services"
        }
    ],
    "sg:phone":"+32 2 663 43 83",
    "sg:postcode":"1160",
    "sg:province":"Bruxelles-Capitale",
    "sg:tags":[
        "surveyor",
        "-"
    ],
    "wof:name":"De Crombrugghe & Partners Nv",
    "wof:placetype":"venue"
},
  "geometry": {"coordinates":[4.4231028557,50.8123931885],"type":"Point"}
}