{
  "type": "Feature",
  "properties": {
    "iso:country":"BE",
    "sg:address":"Dennenweg 34",
    "sg:city":"Haacht",
    "sg:orig_category":"Charpentes and couvertures",
    "sg:phone":"+32 16 60 39 37",
    "sg:postcode":"3150",
    "sg:province":"Vlaams-Brabant",
    "wof:name":"Dak-o-plast",
    "wof:placetype":"venue"
},
  "geometry": {"coordinates":[4.6266489029,50.9780769348],"type":"Point"}
}