{
  "type": "Feature",
  "properties": {
    "iso:country":"BE",
    "sg:address":"Rue De La Barri\u00e8re 5",
    "sg:city":"Florenville (chassepierre)",
    "sg:classifiers":[
        {
            "category":"Wholesale",
            "subcategory":"Fruits & Vegetables",
            "type":"Manufacturing & Wholesale Goods"
        }
    ],
    "sg:phone":"+32 61 31 14 85",
    "sg:postcode":"6824",
    "sg:province":"Luxembourg",
    "sg:tags":[
        "whol",
        "-",
        "potato"
    ],
    "wof:name":"Emond V & Fils",
    "wof:placetype":"venue"
},
  "geometry": {"coordinates":[5.2590451241,49.708404541],"type":"Point"}
}