{
  "type": "Feature",
  "properties": {
    "iso:country":"BE",
    "sg:address":"Route Provinciale 104",
    "sg:city":"Mont-de-l'enclus (anseroeul)",
    "sg:classifiers":[
        {
            "category":"Food & Beverages",
            "subcategory":"Meat & Fish",
            "type":"Retail Goods"
        }
    ],
    "sg:phone":"+32 69 45 42 14",
    "sg:postcode":"7750",
    "sg:province":"Hainaut",
    "sg:tags":[
        "-",
        "livestock"
    ],
    "wof:name":"A La Claire Fontaine",
    "wof:placetype":"venue"
},
  "geometry": {"coordinates":[2.6025109291,46.3370933533],"type":"Point"}
}