{
  "type": "Feature",
  "properties": {
    "iso:country":"BE",
    "sg:address":"Havermarkt 39b6",
    "sg:city":"Hasselt",
    "sg:orig_category":"Artistes ind\u00e9pendants",
    "sg:phone":"+32 11 22 95 50",
    "sg:postcode":"3500",
    "sg:province":"Limburg",
    "wof:name":"Encyclorama",
    "wof:placetype":"venue"
},
  "geometry": {"coordinates":[5.3345217705,50.9294395447],"type":"Point"}
}