{
  "type": "Feature",
  "properties": {
    "addr:full":"Rue Des Trois Burettes 24 Mont-saint-guibert Brabant Wallon 1435",
    "addr:housenumber":"24",
    "addr:postcode":"1435",
    "addr:street":"Rue Des Trois Burettes",
    "iso:country":"BE",
    "sg:address":"Rue Des Trois Burettes 24",
    "sg:city":"Mont-saint-guibert",
    "sg:classifiers":[
        {
            "category":"Shopping",
            "subcategory":"Baby Store",
            "type":"Retail Goods"
        }
    ],
    "sg:phone":"+32 10 65 55 38",
    "sg:postcode":"1435",
    "sg:province":"Brabant Wallon",
    "sg:tags":[
        "midwife"
    ],
    "wof:name":"Van Meensel C",
    "wof:placetype":"venue"
},
  "geometry": {"coordinates":[4.6112499237,50.6436538696],"type":"Point"}
}