{
  "type": "Feature",
  "properties": {
    "addr:full":"Nieuwlandlaan 15b Aarschot Vlaams-Brabant 3200",
    "addr:housenumber":"15b",
    "addr:postcode":"3200",
    "addr:street":"Nieuwlandlaan",
    "iso:country":"BE",
    "sg:address":"Nieuwlandlaan 15b",
    "sg:city":"Aarschot",
    "sg:classifiers":[
        {
            "category":"Military Area",
            "subcategory":"Air Force Base",
            "type":"Public Place"
        }
    ],
    "sg:phone":"+32 16 55 36 00",
    "sg:postcode":"3200",
    "sg:province":"Vlaams-Brabant",
    "sg:tags":[
        "corrosion",
        "prevention",
        "rust"
    ],
    "wof:name":"Tyco Adhesives Bvba",
    "wof:placetype":"venue"
},
  "geometry": {"coordinates":[4.8163728714,50.9833831787],"type":"Point"}
}