{
  "type": "Feature",
  "properties": {
    "addr:full":"Westkaai 6b Ieper West-Vlaanderen 8900",
    "addr:housenumber":"6b",
    "addr:postcode":"8900",
    "addr:street":"Westkaai",
    "iso:country":"BE",
    "sg:address":"Westkaai 6b",
    "sg:city":"Ieper",
    "sg:classifiers":[
        {
            "category":"Shopping",
            "subcategory":"Antiques",
            "type":"Retail Goods"
        }
    ],
    "sg:phone":"+32 57 44 82 84",
    "sg:postcode":"8900",
    "sg:province":"West-Vlaanderen",
    "wof:name":"Brocante Van A Tot Z",
    "wof:placetype":"venue"
},
  "geometry": {"coordinates":[2.8837409019,50.8584861755],"type":"Point"}
}