{
  "type": "Feature",
  "properties": {
    "iso:country":"BE",
    "sg:address":"Vlamingstraat 15-17",
    "sg:city":"Poperinge",
    "sg:classifiers":[
        {
            "category":"Food & Beverages",
            "subcategory":"Liquor & Beverages",
            "type":"Retail Goods"
        }
    ],
    "sg:phone":"+32 57 33 31 24",
    "sg:postcode":"8970",
    "sg:province":"West-Vlaanderen",
    "sg:tags":[
        "-",
        "spirit",
        "wine"
    ],
    "wof:name":"De Rynck-haghedooren Wijnkelder",
    "wof:placetype":"venue"
},
  "geometry": {"coordinates":[2.7249701023,50.8552970886],"type":"Point"}
}