{
  "type": "Feature",
  "properties": {
    "addr:full":"Grensstraat 16b Bertem (leefdaal) Vlaams-Brabant 3061",
    "addr:housenumber":"16b",
    "addr:postcode":"3061",
    "addr:street":"Grensstraat",
    "iso:country":"BE",
    "sg:address":"Grensstraat 16b",
    "sg:city":"Bertem (leefdaal)",
    "sg:classifiers":[
        {
            "category":"Professional",
            "subcategory":"Secretarial Services",
            "type":"Services"
        }
    ],
    "sg:phone":"+32 2 759 36 94",
    "sg:postcode":"3061",
    "sg:province":"Vlaams-Brabant",
    "sg:tags":[
        "firm"
    ],
    "wof:name":"Frenay B",
    "wof:placetype":"venue"
},
  "geometry": {"coordinates":[4.5574269295,50.8571090698],"type":"Point"}
}