{
  "type": "Feature",
  "properties": {
    "addr:full":"Oostrozebekestraat 16 Meulebeke West-Vlaanderen 8760",
    "addr:housenumber":"16",
    "addr:postcode":"8760",
    "addr:street":"Oostrozebekestraat",
    "iso:country":"BE",
    "sg:address":"Oostrozebekestraat 16",
    "sg:city":"Meulebeke",
    "sg:classifiers":[
        {
            "category":"Shopping",
            "subcategory":"Optician",
            "type":"Retail Goods"
        }
    ],
    "sg:phone":"+32 51 48 69 57",
    "sg:postcode":"8760",
    "sg:province":"West-Vlaanderen",
    "sg:tags":[
        "-"
    ],
    "wof:name":"Optiek Kurt",
    "wof:placetype":"venue"
},
  "geometry": {"coordinates":[3.2891979218,50.9490966797],"type":"Point"}
}