{
  "type": "Feature",
  "properties": {
    "addr:full":"Rue Osseghem 39 Bruxelles (molenbeek-saint-jean) Bruxelles-Capitale 1080",
    "addr:housenumber":"39",
    "addr:postcode":"1080",
    "addr:street":"Rue Osseghem",
    "iso:country":"BE",
    "sg:address":"Rue Osseghem 39",
    "sg:city":"Bruxelles (molenbeek-saint-jean)",
    "sg:classifiers":[
        {
            "category":"Shopping",
            "subcategory":"Optician",
            "type":"Retail Goods"
        }
    ],
    "sg:phone":"+32 2 410 17 46",
    "sg:postcode":"1080",
    "sg:province":"Bruxelles-Capitale",
    "sg:tags":[
        "-"
    ],
    "wof:name":"Hock T",
    "wof:placetype":"venue"
},
  "geometry": {"coordinates":[4.3224511147,50.8556480408],"type":"Point"}
}