{
  "type": "Feature",
  "properties": {
    "addr:full":"Rue Des Ecoles 9 Verviers Li\u00e8ge 4800",
    "addr:housenumber":"9",
    "addr:postcode":"4800",
    "addr:street":"Rue Des Ecoles",
    "iso:country":"BE",
    "sg:address":"Rue Des Ecoles 9",
    "sg:city":"Verviers",
    "sg:classifiers":[
        {
            "category":"Personal",
            "subcategory":"Nail Salon",
            "type":"Services"
        }
    ],
    "sg:phone":"+32 87 22 12 06",
    "sg:postcode":"4800",
    "sg:province":"Li\u00e8ge",
    "sg:tags":[
        "pedicure"
    ],
    "wof:name":"Studio Diana",
    "wof:placetype":"venue"
},
  "geometry": {"coordinates":[5.8649888039,50.5903091431],"type":"Point"}
}