{
  "type": "Feature",
  "properties": {
    "iso:country":"BE",
    "sg:address":"Avenue Adolphe Buyl 47",
    "sg:city":"Elsene/ixelles",
    "sg:orig_category":"R\u00e9paration and restauration de meubles",
    "sg:phone":"+32 2 649 05 34",
    "sg:postcode":"1050",
    "sg:province":"Bruxelles-Capitale",
    "wof:name":"Jan Dunin-karwicki",
    "wof:placetype":"venue"
},
  "geometry": {"coordinates":[4.3809862137,50.8170547485],"type":"Point"}
}