{
  "type": "Feature",
  "properties": {
    "addr:full":"Chemin Des Cr\u00eates 3b Dalhem (saint-andr\u00e9) Li\u00e8ge 4606",
    "addr:housenumber":"3b",
    "addr:postcode":"4606",
    "addr:street":"Chemin Des Cre\u0302Tes",
    "iso:country":"BE",
    "sg:address":"Chemin Des Cr\u00eates 3b",
    "sg:city":"Dalhem (saint-andr\u00e9)",
    "sg:classifiers":[
        {
            "category":"Home & Garden",
            "subcategory":"Building Materials",
            "type":"Retail Goods"
        }
    ],
    "sg:phone":"+32 4 387 40 90",
    "sg:postcode":"4606",
    "sg:province":"Li\u00e8ge",
    "sg:tags":[
        "water",
        "heater"
    ],
    "wof:name":"Anzalone",
    "wof:placetype":"venue"
},
  "geometry": {"coordinates":[5.736219883,50.7036895752],"type":"Point"}
}