{
  "type": "Feature",
  "properties": {
    "iso:country":"BE",
    "sg:address":"Rue D'angleterre 70",
    "sg:city":"Bruxelles",
    "sg:classifiers":[
        {
            "category":"Education",
            "subcategory":"Special Training",
            "type":"Public Place"
        }
    ],
    "sg:phone":"+32 2 521 28 96",
    "sg:postcode":"1060",
    "sg:province":"Bruxelles-Capitale",
    "sg:tags":[
        "chemical"
    ],
    "wof:name":"Continental Structures S.p.r.l.",
    "wof:placetype":"venue"
},
  "geometry": {"coordinates":[4.3434867859,50.8297462463],"type":"Point"}
}