{
  "type": "Feature",
  "properties": {
    "iso:country":"BE",
    "sg:address":"Avenue Cardinal Mercier 64",
    "sg:city":"Namur",
    "sg:classifiers":[
        {
            "category":"Education",
            "subcategory":"Library",
            "type":"Public Place"
        }
    ],
    "sg:phone":"+32 81 74 12 52",
    "sg:postcode":"5000",
    "sg:province":"Namur",
    "sg:tags":[
        "equipment",
        "-"
    ],
    "wof:name":"Proplacard",
    "wof:placetype":"venue"
},
  "geometry": {"coordinates":[4.8499751091,50.4650306702],"type":"Point"}
}