{
  "type": "Feature",
  "properties": {
    "addr:full":"Kaulillerweg 69b3 Neerpelt Limburg 3910",
    "addr:housenumber":"69b3",
    "addr:postcode":"3910",
    "addr:street":"Kaulillerweg",
    "iso:country":"BE",
    "sg:address":"Kaulillerweg 69b3",
    "sg:city":"Neerpelt",
    "sg:classifiers":[
        {
            "category":"Restaurant",
            "type":"Food & Drink"
        }
    ],
    "sg:phone":"+32 11 80 15 97",
    "sg:postcode":"3910",
    "sg:province":"Limburg",
    "sg:tags":[
        "caf\u00e9s"
    ],
    "wof:name":"Papillote",
    "wof:placetype":"venue"
},
  "geometry": {"coordinates":[5.4902091026,51.218875885],"type":"Point"}
}