{
  "type": "Feature",
  "properties": {
    "addr:full":"Rue Du Village 30 Estinnes (croix-lez-rouveroy) Hainaut 7120",
    "addr:housenumber":"30",
    "addr:postcode":"7120",
    "addr:street":"Rue Du Village",
    "iso:country":"BE",
    "sg:address":"Rue Du Village 30",
    "sg:city":"Estinnes (croix-lez-rouveroy)",
    "sg:classifiers":[
        {
            "category":"Manufacturing",
            "subcategory":"Tobacco Products",
            "type":"Manufacturing & Wholesale Goods"
        }
    ],
    "sg:phone":"+32 64 77 17 05",
    "sg:postcode":"7120",
    "sg:province":"Hainaut",
    "sg:tags":[
        "fertilizer",
        "merchant",
        "-"
    ],
    "wof:name":"Semaille (engrais)",
    "wof:placetype":"venue"
},
  "geometry": {"coordinates":[4.0791320801,50.3571968079],"type":"Point"}
}