{
  "type": "Feature",
  "properties": {
    "addr:full":"Chauss\u00c9e Brunehaut 292 Beloeil Hainaut 7972",
    "addr:housenumber":"292",
    "addr:postcode":"7972",
    "addr:street":"Chausse\u0301E Brunehaut",
    "iso:country":"BE",
    "sg:address":"Chauss\u00c9e Brunehaut 292",
    "sg:city":"Beloeil",
    "sg:orig_category":"Rundveehouders",
    "sg:phone":"+32 69 68 91 50",
    "sg:postcode":"7972",
    "sg:province":"Hainaut",
    "wof:name":"Delobelle Et Fils",
    "wof:placetype":"venue"
},
  "geometry": {"coordinates":[3.6907989979,50.5417861938],"type":"Point"}
}