{
  "type": "Feature",
  "properties": {
    "iso:country":"BE",
    "sg:address":"Kempische Steenweg 434",
    "sg:city":"Hasselt",
    "sg:classifiers":[
        {
            "category":"Travel",
            "subcategory":"Resort",
            "type":"Entertainment"
        }
    ],
    "sg:phone":"+32 11 37 19 86",
    "sg:postcode":"3500",
    "sg:province":"Limburg",
    "sg:tags":[
        "health"
    ],
    "wof:name":"Sento",
    "wof:placetype":"venue"
},
  "geometry": {"coordinates":[5.3410902023,50.9396095276],"type":"Point"}
}