{
  "type": "Feature",
  "properties": {
    "iso:country":"BE",
    "sg:address":"Avenue D\u00b4auderghem 3",
    "sg:city":"Brussel/bruxelles",
    "sg:classifiers":[
        {
            "category":"Insurance",
            "subcategory":"Life Insurance",
            "type":"Services"
        }
    ],
    "sg:phone":"+32 2 230 29 59",
    "sg:postcode":"1040",
    "sg:province":"Bruxelles-Capitale",
    "sg:tags":[
        "assurance"
    ],
    "wof:name":"Sarton & Associ\u00c9s",
    "wof:placetype":"venue"
},
  "geometry": {"coordinates":[4.3853039742,50.8394050598],"type":"Point"}
}