{
  "type": "Feature",
  "properties": {
    "addr:full":"Sint-lievenslaan 138 Gent Oost-Vlaanderen 9000",
    "addr:housenumber":"138",
    "addr:postcode":"9000",
    "addr:street":"Sint-Lievenslaan;Oost-Vlaanderen",
    "iso:country":"BE",
    "sg:address":"Sint-lievenslaan 138",
    "sg:city":"Gent",
    "sg:orig_category":"Etablissements Erotiques",
    "sg:phone":"+32 9 224 20 76",
    "sg:postcode":"9000",
    "sg:province":"Oost-Vlaanderen",
    "wof:name":"Steffi & Angel",
    "wof:placetype":"venue"
},
  "geometry": {"coordinates":[3.7355298996,51.0415916443],"type":"Point"}
}