{
  "type": "Feature",
  "properties": {
    "addr:full":"Rue Vis\u00e9-voie 4 Oupeye Li\u00e8ge 4680",
    "addr:housenumber":"4",
    "addr:postcode":"4680",
    "addr:street":"Rue Vise\u0301-Voie",
    "iso:country":"BE",
    "sg:address":"Rue Vis\u00e9-voie 4",
    "sg:city":"Oupeye",
    "sg:classifiers":[
        {
            "category":"Shopping",
            "subcategory":"Books",
            "type":"Retail Goods"
        }
    ],
    "sg:phone":"+32 4 264 65 74",
    "sg:postcode":"4680",
    "sg:province":"Li\u00e8ge",
    "sg:tags":[
        "bookseller"
    ],
    "wof:name":"Librairie Marechal Sprl",
    "wof:placetype":"venue"
},
  "geometry": {"coordinates":[5.6435108185,50.7089767456],"type":"Point"}
}