{
  "type": "Feature",
  "properties": {
    "addr:full":"Amerikalei 27 Box 8 Antwerpen Antwerpen 2000",
    "addr:housenumber":"27;8",
    "addr:postcode":"2000",
    "addr:street":"Amerikalei;Box",
    "iso:country":"BE",
    "sg:address":"Amerikalei 27 Box 8",
    "sg:city":"Antwerpen",
    "sg:classifiers":[
        {
            "category":"Professional",
            "subcategory":"Lawyer & Legal Services",
            "type":"Services"
        }
    ],
    "sg:phone":"+32 3 248 25 35",
    "sg:postcode":"2000",
    "sg:province":"Antwerpen",
    "wof:name":"De Backer Barbara",
    "wof:placetype":"venue"
},
  "geometry": {"coordinates":[4.4009699821,51.2080116272],"type":"Point"}
}