{
  "type": "Feature",
  "properties": {
    "iso:country":"BE",
    "sg:address":"Zagerijstraat 57",
    "sg:city":"Lier",
    "sg:classifiers":[
        {
            "category":"Personal",
            "subcategory":"Beauty Salon",
            "type":"Services"
        }
    ],
    "sg:phone":"+32 3 480 49 86",
    "sg:postcode":"2500",
    "sg:province":"Antwerpen",
    "sg:tags":[
        "lady",
        "-",
        "hairdressing"
    ],
    "wof:name":"Anfra",
    "wof:placetype":"venue"
},
  "geometry": {"coordinates":[4.562620163,51.1382904053],"type":"Point"}
}