{
  "type": "Feature",
  "properties": {
    "addr:full":"Wouwerstraat 19 Dessel Antwerpen 2480",
    "addr:housenumber":"19",
    "addr:postcode":"2480",
    "addr:street":"Wouwerstraat",
    "iso:country":"BE",
    "sg:address":"Wouwerstraat 19",
    "sg:city":"Dessel",
    "sg:orig_category":"Installation \u00e9lectrique r\u00e9sidentielle",
    "sg:phone":"+32 14 37 11 91",
    "sg:postcode":"2480",
    "sg:province":"Antwerpen",
    "wof:name":"Ro Electro",
    "wof:placetype":"venue"
},
  "geometry": {"coordinates":[5.1568098068,51.2458190918],"type":"Point"}
}