{
  "type": "Feature",
  "properties": {
    "addr:full":"Stationsstraat 93 Lendelede West-Vlaanderen 8860",
    "addr:housenumber":"93",
    "addr:postcode":"8860",
    "addr:street":"Stationsstraat",
    "iso:country":"BE",
    "sg:address":"Stationsstraat 93",
    "sg:city":"Lendelede",
    "sg:classifiers":[
        {
            "category":"Cafe",
            "type":"Food & Drink"
        }
    ],
    "sg:phone":"+32 51 31 45 77",
    "sg:postcode":"8860",
    "sg:province":"West-Vlaanderen",
    "sg:tags":[
        "caf\u00e9s"
    ],
    "wof:name":"Caf\u00c9 Belle Vue",
    "wof:placetype":"venue"
},
  "geometry": {"coordinates":[3.2490749359,50.8855895996],"type":"Point"}
}