{
  "type": "Feature",
  "properties": {
    "addr:full":"Satenrozen 10 Kontich Antwerpen 2550",
    "addr:housenumber":"10",
    "addr:postcode":"2550",
    "addr:street":"Satenrozen",
    "iso:country":"BE",
    "sg:address":"Satenrozen 10",
    "sg:city":"Kontich",
    "sg:classifiers":[
        {
            "category":"Building & Trades",
            "subcategory":"Construction",
            "type":"Services"
        }
    ],
    "sg:phone":"+32 3 458 59 10",
    "sg:postcode":"2550",
    "sg:province":"Antwerpen",
    "sg:tags":[
        "stucco",
        "contractor"
    ],
    "wof:name":"Algemene Bezettingswerken Herman",
    "wof:placetype":"venue"
},
  "geometry": {"coordinates":[4.4137301445,51.1232795715],"type":"Point"}
}