{
  "type": "Feature",
  "properties": {
    "iso:country":"BE",
    "sg:address":"Looflaan 28",
    "sg:city":"Ukkel/uccle",
    "sg:orig_category":"Artsen and specialisten",
    "sg:phone":"+32 2 346 01 99",
    "sg:postcode":"1180",
    "sg:province":"Bruxelles-Capitale",
    "wof:name":"Bruno Coessens",
    "wof:placetype":"venue"
},
  "geometry": {"coordinates":[4.3445467949,50.8057785034],"type":"Point"}
}