{
  "type": "Feature",
  "properties": {
    "iso:country":"BE",
    "sg:address":"Rue Des Gen\u00cats 46",
    "sg:city":"Li\u00c8ge",
    "sg:orig_category":"Verlichting and huishoudartikelen",
    "sg:phone":"+32 4 226 99 31",
    "sg:postcode":"4000",
    "sg:province":"Li\u00e8ge",
    "wof:name":"Huguette Legrand",
    "wof:placetype":"venue"
},
  "geometry": {"coordinates":[5.557612896,50.6550598145],"type":"Point"}
}