{
  "type": "Feature",
  "properties": {
    "iso:country":"BE",
    "sg:address":"Molenpad 86",
    "sg:city":"Lille",
    "sg:orig_category":"Elektrische installaties voor woningen",
    "sg:phone":"+32 14 55 18 22",
    "sg:postcode":"2275",
    "sg:province":"Antwerpen",
    "wof:name":"Luc Willems",
    "wof:placetype":"venue"
},
  "geometry": {"coordinates":[4.8685541153,51.2762336731],"type":"Point"}
}