{
  "type": "Feature",
  "properties": {
    "addr:full":"Oudenaardsesteenweg 242 Kortrijk West-Vlaanderen 8500",
    "addr:housenumber":"242",
    "addr:postcode":"8500",
    "addr:street":"Oudenaardsesteenweg",
    "iso:country":"BE",
    "sg:address":"Oudenaardsesteenweg 242",
    "sg:city":"Kortrijk",
    "sg:orig_category":"Articles de sport, camping and jouets V\u00e9los",
    "sg:phone":"+32 56 21 00 78",
    "sg:postcode":"8500",
    "sg:province":"West-Vlaanderen",
    "wof:name":"M. De Keyser",
    "wof:placetype":"venue"
},
  "geometry": {"coordinates":[3.2890379429,50.8207359314],"type":"Point"}
}