{
  "type": "Feature",
  "properties": {
    "addr:full":"Kardinaal Mercierplein 13 Lier Antwerpen 2500",
    "addr:housenumber":"13",
    "addr:postcode":"2500",
    "addr:street":"Kardinaal Mercierplein",
    "iso:country":"BE",
    "sg:address":"Kardinaal Mercierplein 13",
    "sg:city":"Lier",
    "sg:orig_category":"Maatschappelijke dienstverlening",
    "sg:phone":"+32 3 480 17 81",
    "sg:postcode":"2500",
    "sg:province":"Antwerpen",
    "wof:name":"Vclb-centrum",
    "wof:placetype":"venue"
},
  "geometry": {"coordinates":[4.5750827789,51.1296310425],"type":"Point"}
}