{
  "type": "Feature",
  "properties": {
    "addr:full":"Grote Baan 156-158 Beersel Vlaams-Brabant 1650",
    "addr:postcode":"156-158;1650",
    "addr:street":"Grote Baan",
    "iso:country":"BE",
    "sg:address":"Grote Baan 156-158",
    "sg:city":"Beersel",
    "sg:classifiers":[
        {
            "category":"Health Services",
            "subcategory":"Nursing And Care Facility",
            "type":"Services"
        }
    ],
    "sg:phone":"+32 2 331 07 54",
    "sg:postcode":"1650",
    "sg:province":"Vlaams-Brabant",
    "sg:tags":[
        "home",
        "rest"
    ],
    "wof:name":"R\u00e9sidentie Ter Heide",
    "wof:placetype":"venue"
},
  "geometry": {"coordinates":[4.3176689148,50.7667312622],"type":"Point"}
}