{
  "type": "Feature",
  "properties": {
    "addr:full":"Rue De Roubaix 292 Moeskroen/mouscron Hainaut 7700",
    "addr:housenumber":"292",
    "addr:postcode":"7700",
    "addr:street":"Rue De Roubaix",
    "iso:country":"BE",
    "sg:address":"Rue De Roubaix 292",
    "sg:city":"Moeskroen/mouscron",
    "sg:orig_category":"Reliure and finition. Imprimeries and copyshops",
    "sg:phone":"+32 56 85 75 15",
    "sg:postcode":"7700",
    "sg:province":"Hainaut",
    "wof:name":"Imprim'tout",
    "wof:placetype":"venue"
},
  "geometry": {"coordinates":[3.2323200703,50.7400932312],"type":"Point"}
}