{
  "type": "Feature",
  "properties": {
    "iso:country":"BE",
    "sg:address":"Roterijstraat 160",
    "sg:city":"Waregem",
    "sg:orig_category":"Entretien and r\u00e9parations de voitures. V\u00e9hicules automobiles",
    "sg:phone":"+32 56 60 00 65",
    "sg:postcode":"8790",
    "sg:province":"West-Vlaanderen",
    "wof:name":"Garage Clairhout",
    "wof:placetype":"venue"
},
  "geometry": {"coordinates":[3.4061200619,50.8947181702],"type":"Point"}
}