{
  "type": "Feature",
  "properties": {
    "addr:full":"Molenstraat 34 Stabroek Antwerpen 2940",
    "addr:housenumber":"34",
    "addr:postcode":"2940",
    "addr:street":"Molenstraat",
    "iso:country":"BE",
    "sg:address":"Molenstraat 34",
    "sg:city":"Stabroek",
    "sg:orig_category":"Librairies. Journaux. Fournitures de bureau. Tabac",
    "sg:phone":"+32 3 664 35 50",
    "sg:postcode":"2940",
    "sg:province":"Antwerpen",
    "wof:name":"P. & M.",
    "wof:placetype":"venue"
},
  "geometry": {"coordinates":[4.3970031738,51.3443717957],"type":"Point"}
}