{
  "type": "Feature",
  "properties": {
    "iso:country":"BE",
    "sg:address":"Ekelstraat 111",
    "sg:city":"Herentals",
    "sg:orig_category":"Woningbouw",
    "sg:phone":"+32 14 21 87 62",
    "sg:postcode":"2200",
    "sg:province":"Antwerpen",
    "wof:name":"Algebo",
    "wof:placetype":"venue"
},
  "geometry": {"coordinates":[4.8119859695,51.1777648926],"type":"Point"}
}