{
  "type": "Feature",
  "properties": {
    "iso:country":"BE",
    "sg:address":"Royennestraat 51 Rue De La Royenne",
    "sg:city":"Moeskroen/mouscron",
    "sg:classifiers":[
        {
            "category":"Professional",
            "subcategory":"Detective & Security Services",
            "type":"Services"
        }
    ],
    "sg:phone":"+32 3 325 58 00",
    "sg:postcode":"7700",
    "sg:province":"Hainaut",
    "sg:tags":[
        "alarm",
        "clock"
    ],
    "wof:name":"Batrim B.v.b.a.",
    "wof:placetype":"venue"
},
  "geometry": {"coordinates":[4.4754629135,51.236995697],"type":"Point"}
}