{
  "type": "Feature",
  "properties": {
    "addr:full":"Woluwelaan 100-102 Bruxelles-woluwe-saint-lambert Bruxelles-Capitale 1200",
    "addr:housenumber":"100-102",
    "addr:postcode":"1200",
    "addr:street":"Woluwelaan",
    "iso:country":"BE",
    "sg:address":"Woluwelaan 100-102",
    "sg:city":"Bruxelles-woluwe-saint-lambert",
    "sg:orig_category":"Microsoft. Ordinateurs and \u00e9quipement informatique",
    "sg:phone":"+32 2 763 06 13",
    "sg:postcode":"1200",
    "sg:province":"Bruxelles-Capitale",
    "wof:name":"Hewlett-packard, Belgium",
    "wof:placetype":"venue"
},
  "geometry": {"coordinates":[4.4443011284,50.8546409607],"type":"Point"}
}