{
  "type": "Feature",
  "properties": {
    "addr:full":"Rue Saint-martin 17 Leuze-en-hainaut Hainaut 7900",
    "addr:housenumber":"17",
    "addr:postcode":"7900",
    "addr:street":"Rue Saint-Martin",
    "iso:country":"BE",
    "sg:address":"Rue Saint-martin 17",
    "sg:city":"Leuze-en-hainaut",
    "sg:orig_category":"Non-Classified Establishments",
    "sg:phone":"+32 69 66 21 68",
    "sg:postcode":"7900",
    "sg:province":"Hainaut",
    "wof:name":"Trico-fran\u00e7ois",
    "wof:placetype":"venue"
},
  "geometry": {"coordinates":[3.6257181168,50.5974464417],"type":"Point"}
}