{
  "type": "Feature",
  "properties": {
    "iso:country":"BE",
    "sg:address":"Rue Cortyl Moray 4",
    "sg:city":"Bl\u00e9gny (saive)",
    "sg:classifiers":[
        {
            "category":"Retail",
            "subcategory":"Veterinary Services",
            "type":"Services"
        }
    ],
    "sg:phone":"+32 4 370 66 30",
    "sg:postcode":"4671",
    "sg:province":"Li\u00e8ge",
    "sg:tags":[
        "veterinarian"
    ],
    "wof:name":"Demars Y",
    "wof:placetype":"venue"
},
  "geometry": {"coordinates":[5.6833300591,50.652721405],"type":"Point"}
}