{
  "type": "Feature",
  "properties": {
    "addr:full":"Zandstraat 69 Dendermonde (appels) Oost-Vlaanderen 9200",
    "addr:housenumber":"69",
    "addr:postcode":"9200",
    "addr:street":"Zandstraat;Appels Oost-Vlaanderen",
    "iso:country":"BE",
    "sg:address":"Zandstraat 69",
    "sg:city":"Dendermonde (appels)",
    "sg:classifiers":[
        {
            "category":"Autos & Motor Vehicles",
            "subcategory":"Automobile Sales",
            "type":"Retail Goods"
        }
    ],
    "sg:phone":"+32 52 21 45 79",
    "sg:postcode":"9200",
    "sg:province":"Oost-Vlaanderen",
    "sg:tags":[
        "ceremony",
        "car"
    ],
    "wof:name":"D'houwer R Garage",
    "wof:placetype":"venue"
},
  "geometry": {"coordinates":[4.0697622299,51.0306968689],"type":"Point"}
}