{
  "type": "Feature",
  "properties": {
    "addr:full":"Rue De La Colline 9 Namur Namur 5000",
    "addr:housenumber":"9",
    "addr:postcode":"5000",
    "addr:street":"Rue De La Colline",
    "iso:country":"BE",
    "sg:address":"Rue De La Colline 9",
    "sg:city":"Namur",
    "sg:orig_category":"Transports routiers de marchandises",
    "sg:phone":"+32 81 74 00 98",
    "sg:postcode":"5000",
    "sg:province":"Namur",
    "wof:name":"C.i.m. Trans",
    "wof:placetype":"venue"
},
  "geometry": {"coordinates":[4.8457241058,50.4627799988],"type":"Point"}
}