{
  "type": "Feature",
  "properties": {
    "iso:country":"BE",
    "sg:address":"Secretaris Vanmarckelaan 57",
    "sg:city":"Wevelgem",
    "sg:classifiers":[
        {
            "category":"Cafe",
            "type":"Food & Drink"
        }
    ],
    "sg:phone":"+32 56 42 19 64",
    "sg:postcode":"8560",
    "sg:province":"West-Vlaanderen",
    "sg:tags":[
        "caf\u00e9s"
    ],
    "wof:name":"Cafetaria Zwembad",
    "wof:placetype":"venue"
},
  "geometry": {"coordinates":[3.1712241173,50.8416023254],"type":"Point"}
}