{
  "type": "Feature",
  "properties": {
    "iso:country":"BE",
    "sg:address":"Sylvain Dupuislaan 245",
    "sg:city":"Anderlecht",
    "sg:orig_category":"Huishoudapparaten, televisies and radio's",
    "sg:phone":"+32 2 524 35 43",
    "sg:postcode":"1070",
    "sg:province":"Bruxelles-Capitale",
    "wof:name":"Kr\u00cbfel",
    "wof:placetype":"venue"
},
  "geometry": {"coordinates":[4.2906608582,50.8376464844],"type":"Point"}
}