{
  "type": "Feature",
  "properties": {
    "addr:full":"Langestraat 187 Affligem Vlaams-Brabant 1790",
    "addr:housenumber":"187",
    "addr:postcode":"1790",
    "addr:street":"Langestraat",
    "iso:country":"BE",
    "sg:address":"Langestraat 187",
    "sg:city":"Affligem",
    "sg:orig_category":"Enseignement maternel and primaire",
    "sg:phone":"+32 53 68 15 09",
    "sg:postcode":"1790",
    "sg:province":"Vlaams-Brabant",
    "wof:name":"Vrije Kleuterschool",
    "wof:placetype":"venue"
},
  "geometry": {"coordinates":[4.1060800552,50.9206466675],"type":"Point"}
}