{
  "type": "Feature",
  "properties": {
    "addr:full":"Wetenschapspark 1 Diepenbeek Limburg 3590",
    "addr:housenumber":"1",
    "addr:postcode":"3590",
    "addr:street":"Wetenschapspark",
    "iso:country":"BE",
    "sg:address":"Wetenschapspark 1",
    "sg:city":"Diepenbeek",
    "sg:classifiers":[
        {
            "category":"Home & Garden",
            "subcategory":"Building Materials",
            "type":"Retail Goods"
        }
    ],
    "sg:phone":"+32 11 26 89 15",
    "sg:postcode":"3590",
    "sg:province":"Limburg",
    "sg:tags":[
        "testing"
    ],
    "wof:name":"I.m.c.e. Nv",
    "wof:placetype":"venue"
},
  "geometry": {"coordinates":[5.3944878578,50.9313354492],"type":"Point"}
}