{
  "type": "Feature",
  "properties": {
    "addr:full":"Rue De Florent 62 Rumes Hainaut 7618",
    "addr:housenumber":"62",
    "addr:postcode":"7618",
    "addr:street":"Rue De Florent",
    "iso:country":"BE",
    "sg:address":"Rue De Florent 62",
    "sg:city":"Rumes",
    "sg:orig_category":"Rusthuizen and serviceflats",
    "sg:phone":"+32 69 64 81 84",
    "sg:postcode":"7618",
    "sg:province":"Hainaut",
    "wof:name":"Home Notre Maison",
    "wof:placetype":"venue"
},
  "geometry": {"coordinates":[3.3415100574,50.549156189],"type":"Point"}
}