{
  "type": "Feature",
  "properties": {
    "addr:full":"Gevaertlaan 34 Boom Antwerpen 2850",
    "addr:housenumber":"34",
    "addr:postcode":"2850",
    "addr:street":"Gevaertlaan",
    "iso:country":"BE",
    "sg:address":"Gevaertlaan 34",
    "sg:city":"Boom",
    "sg:orig_category":"M\u00e9decins and sp\u00e9cialistes",
    "sg:phone":"+32 3 844 79 00",
    "sg:postcode":"2850",
    "sg:province":"Antwerpen",
    "wof:name":"Inge Peelman",
    "wof:placetype":"venue"
},
  "geometry": {"coordinates":[4.375767231,51.095375061],"type":"Point"}
}