{
  "type": "Feature",
  "properties": {
    "iso:country":"BE",
    "sg:address":"Balsemboomstraat 29 Box 4",
    "sg:city":"Brugge",
    "sg:classifiers":[
        {
            "category":"Health Services",
            "subcategory":"Nursing And Care Facility",
            "type":"Services"
        }
    ],
    "sg:phone":"+32 50 34 99 70",
    "sg:postcode":"8000",
    "sg:province":"West-Vlaanderen",
    "sg:tags":[
        "home"
    ],
    "wof:name":"Hugaert L",
    "wof:placetype":"venue"
},
  "geometry": {"coordinates":[3.2375791073,51.2102584839],"type":"Point"}
}