{
  "type": "Feature",
  "properties": {
    "addr:full":"Tramstraat 91 Tielt West-Vlaanderen 8700",
    "addr:housenumber":"91",
    "addr:postcode":"8700",
    "addr:street":"Tramstraat",
    "iso:country":"BE",
    "sg:address":"Tramstraat 91",
    "sg:city":"Tielt",
    "sg:classifiers":[
        {
            "category":"Food & Beverages",
            "subcategory":"Chocolate",
            "type":"Retail Goods"
        }
    ],
    "sg:phone":"+32 51 40 64 30",
    "sg:postcode":"8700",
    "sg:province":"West-Vlaanderen",
    "sg:tags":[
        "confectionery",
        "-"
    ],
    "wof:name":"Pia's",
    "wof:placetype":"venue"
},
  "geometry": {"coordinates":[3.334510088,51.0039405823],"type":"Point"}
}