{
  "type": "Feature",
  "properties": {
    "iso:country":"BE",
    "sg:address":"Rue Lintermans 18",
    "sg:city":"Seneffe",
    "sg:orig_category":"Epiceries",
    "sg:phone":"+32 64 54 92 69",
    "sg:postcode":"7180",
    "sg:province":"Hainaut",
    "wof:name":"Maison Bellemans",
    "wof:placetype":"venue"
},
  "geometry": {"coordinates":[4.2569952011,50.5298118591],"type":"Point"}
}