{
  "type": "Feature",
  "properties": {
    "addr:full":"Hoogton 60 Herentals Antwerpen 2200",
    "addr:housenumber":"60",
    "addr:postcode":"2200",
    "addr:street":"Hoogton",
    "iso:country":"BE",
    "sg:address":"Hoogton 60",
    "sg:city":"Herentals",
    "sg:orig_category":"Fabrication and montage de mobilier. Quincailleries. Installation de menuiserie en bois and plastiqu",
    "sg:phone":"+32 14 26 15 90",
    "sg:postcode":"2200",
    "sg:province":"Antwerpen",
    "wof:name":"Keukens Anguma Janssens",
    "wof:placetype":"venue"
},
  "geometry": {"coordinates":[4.8345460892,51.1273994446],"type":"Point"}
}