{
  "type": "Feature",
  "properties": {
    "iso:country":"BE",
    "sg:address":"Rue D\u00b4enghien 45",
    "sg:city":"Mons",
    "sg:orig_category":"Zalen voor culturele evenementen",
    "sg:phone":"+32 65 31 44 40",
    "sg:postcode":"7000",
    "sg:province":"Hainaut",
    "wof:name":"Renard Gallery",
    "wof:placetype":"venue"
},
  "geometry": {"coordinates":[3.9505839348,50.4550971985],"type":"Point"}
}