{
  "type": "Feature",
  "properties": {
    "addr:full":"Rozendaalstraat 6 Ieper West-Vlaanderen 8900",
    "addr:housenumber":"6",
    "addr:postcode":"8900",
    "addr:street":"Rozendaalstraat",
    "iso:country":"BE",
    "sg:address":"Rozendaalstraat 6",
    "sg:city":"Ieper",
    "sg:classifiers":[
        {
            "category":"Professional",
            "type":"Services"
        }
    ],
    "sg:phone":"+32 57 21 94 57",
    "sg:postcode":"8900",
    "sg:province":"West-Vlaanderen",
    "sg:tags":[
        "industrial",
        "automation"
    ],
    "wof:name":"Robosoft",
    "wof:placetype":"venue"
},
  "geometry": {"coordinates":[2.8832950592,50.8750762939],"type":"Point"}
}