{
  "type": "Feature",
  "properties": {
    "addr:full":"Rue Pont \u00e0 L'haye 57 Celles (escanaffles) Hainaut 7760",
    "addr:housenumber":"57",
    "addr:postcode":"7760",
    "addr:street":"Rue Pont A\u0300 L'Haye",
    "iso:country":"BE",
    "sg:address":"Rue Pont \u00e0 L'haye 57",
    "sg:city":"Celles (escanaffles)",
    "sg:classifiers":[
        {
            "category":"Health Services",
            "subcategory":"Doctor",
            "type":"Services"
        }
    ],
    "sg:phone":"+32 69 45 45 49",
    "sg:postcode":"7760",
    "sg:province":"Hainaut",
    "sg:tags":[
        "medicinephysicians",
        "surgeon"
    ],
    "wof:name":"Dekeyser A",
    "wof:placetype":"venue"
},
  "geometry": {"coordinates":[3.433506012,50.7470703125],"type":"Point"}
}