{
  "type": "Feature",
  "properties": {
    "addr:full":"Waregemseweg 28 Wortegem-petegem Oost-Vlaanderen 9790",
    "addr:housenumber":"28",
    "addr:postcode":"9790",
    "addr:street":"Waregemseweg",
    "iso:country":"BE",
    "sg:address":"Waregemseweg 28",
    "sg:city":"Wortegem-petegem",
    "sg:classifiers":[
        {
            "category":"Food & Beverages",
            "subcategory":"Meat & Fish",
            "type":"Retail Goods"
        }
    ],
    "sg:phone":"+32 56 68 95 75",
    "sg:postcode":"9790",
    "sg:province":"Oost-Vlaanderen",
    "sg:tags":[
        "preserve"
    ],
    "wof:name":"Franky Nv",
    "wof:placetype":"venue"
},
  "geometry": {"coordinates":[3.504707098,50.8542327881],"type":"Point"}
}