{
  "type": "Feature",
  "properties": {
    "addr:full":"Chemin Willems 2 Tournai Hainaut 7500",
    "addr:housenumber":"2",
    "addr:postcode":"7500",
    "addr:street":"Chemin Willems",
    "iso:country":"BE",
    "sg:address":"Chemin Willems 2",
    "sg:city":"Tournai",
    "sg:classifiers":[
        {
            "category":"Travel",
            "subcategory":"Resort",
            "type":"Entertainment"
        }
    ],
    "sg:phone":"+32 69 21 28 12",
    "sg:postcode":"7500",
    "sg:province":"Hainaut",
    "sg:tags":[
        "vacation"
    ],
    "wof:name":"Arc-en-ciel Asbl",
    "wof:placetype":"venue"
},
  "geometry": {"coordinates":[3.3611690998,50.6121635437],"type":"Point"}
}