{
  "type": "Feature",
  "properties": {
    "iso:country":"BE",
    "sg:address":"Populierenstraat 16",
    "sg:city":"Hoeselt",
    "sg:orig_category":"Eleveurs and marchands de porcs",
    "sg:phone":"+32 89 51 18 01",
    "sg:postcode":"3730",
    "sg:province":"Limburg",
    "wof:name":"Yves Clercx",
    "wof:placetype":"venue"
},
  "geometry": {"coordinates":[5.4788980484,50.8539085388],"type":"Point"}
}