{
  "type": "Feature",
  "properties": {
    "addr:full":"Hemelingenstraat 62 Tongeren Limburg 3700",
    "addr:housenumber":"62",
    "addr:postcode":"3700",
    "addr:street":"Hemelingenstraat",
    "iso:country":"BE",
    "sg:address":"Hemelingenstraat 62",
    "sg:city":"Tongeren",
    "sg:orig_category":"Imprimeries and copyshops",
    "sg:phone":"+32 12 23 14 33",
    "sg:postcode":"3700",
    "sg:province":"Limburg",
    "wof:name":"Marcel Champagne",
    "wof:placetype":"venue"
},
  "geometry": {"coordinates":[5.4616222382,50.7820091248],"type":"Point"}
}