{
  "type": "Feature",
  "properties": {
    "addr:full":"Rue Ferrer 220 Frameries Hainaut 7080",
    "addr:housenumber":"220",
    "addr:postcode":"7080",
    "addr:street":"Rue Ferrer",
    "iso:country":"BE",
    "sg:address":"Rue Ferrer 220",
    "sg:city":"Frameries",
    "sg:classifiers":[
        {
            "category":"Retail",
            "subcategory":"Event Space",
            "type":"Services"
        }
    ],
    "sg:phone":"+32 65 51 50 90",
    "sg:postcode":"7080",
    "sg:province":"Hainaut",
    "sg:tags":[
        "rental",
        "-",
        "hall"
    ],
    "wof:name":"Prevot Traiteur",
    "wof:placetype":"venue"
},
  "geometry": {"coordinates":[3.9049370289,50.4046325684],"type":"Point"}
}