{
  "type": "Feature",
  "properties": {
    "addr:full":"Gelmelstraat 96 Hoogstraten Antwerpen 2320",
    "addr:housenumber":"96",
    "addr:postcode":"2320",
    "addr:street":"Gelmelstraat",
    "iso:country":"BE",
    "sg:address":"Gelmelstraat 96",
    "sg:city":"Hoogstraten",
    "sg:orig_category":"Disposable Surgical Stockings",
    "sg:phone":"+32 63 23 96 24",
    "sg:postcode":"2320",
    "sg:province":"Antwerpen",
    "wof:name":"Varodem S.a.",
    "wof:placetype":"venue"
},
  "geometry": {"coordinates":[5.6644678116,49.6161575317],"type":"Point"}
}