{
  "type": "Feature",
  "properties": {
    "addr:full":"Belgi\u00eblei 130 Antwerpen Antwerpen 2018",
    "addr:housenumber":"130",
    "addr:postcode":"2018",
    "addr:street":"Belgie\u0308Lei",
    "iso:country":"BE",
    "sg:address":"Belgi\u00eblei 130",
    "sg:city":"Antwerpen",
    "sg:classifiers":[
        {
            "category":"Bars & Pubs",
            "type":"Food & Drink"
        }
    ],
    "sg:phone":"+32 3 218 90 66",
    "sg:postcode":"2018",
    "sg:province":"Antwerpen",
    "wof:name":"Royal",
    "wof:placetype":"venue"
},
  "geometry": {"coordinates":[4.4166870117,51.2051467896],"type":"Point"}
}