{
  "type": "Feature",
  "properties": {
    "addr:full":"Trappistenweg 31ba Poperinge West-Vlaanderen 8978",
    "addr:housenumber":"31ba",
    "addr:postcode":"8978",
    "addr:street":"Trappistenweg",
    "iso:country":"BE",
    "sg:address":"Trappistenweg 31ba",
    "sg:city":"Poperinge",
    "sg:orig_category":"Rundveehouders",
    "sg:phone":"+32 57 38 88 02",
    "sg:postcode":"8978",
    "sg:province":"West-Vlaanderen",
    "wof:name":"Theo Devos",
    "wof:placetype":"venue"
},
  "geometry": {"coordinates":[2.659539938,50.8264083862],"type":"Point"}
}