{
  "type": "Feature",
  "properties": {
    "addr:full":"Ledegemstraat 6 Moorslede (dadizele) West-Vlaanderen 8890",
    "addr:housenumber":"6",
    "addr:postcode":"8890",
    "addr:street":"Ledegemstraat",
    "iso:country":"BE",
    "sg:address":"Ledegemstraat 6",
    "sg:city":"Moorslede (dadizele)",
    "sg:classifiers":[
        {
            "category":"Building & Trades",
            "subcategory":"Electrical",
            "type":"Services"
        }
    ],
    "sg:phone":"+32 56 50 91 83",
    "sg:postcode":"8890",
    "sg:province":"West-Vlaanderen",
    "sg:tags":[
        "electric",
        "-",
        "housewiring",
        "contractor"
    ],
    "wof:name":"Rondelez",
    "wof:placetype":"venue"
},
  "geometry": {"coordinates":[3.0977129936,50.8519020081],"type":"Point"}
}