{
  "type": "Feature",
  "properties": {
    "iso:country":"BE",
    "sg:address":"Boulevard De La Meuse 9",
    "sg:city":"Namur (jambes)",
    "sg:classifiers":[
        {
            "category":"Shopping",
            "subcategory":"Bicycles & Sporting Goods",
            "type":"Retail Goods"
        }
    ],
    "sg:phone":"+32 81 30 71 84",
    "sg:postcode":"5100",
    "sg:province":"Namur",
    "sg:tags":[
        "sport",
        "-"
    ],
    "wof:name":"Sport Nature",
    "wof:placetype":"venue"
},
  "geometry": {"coordinates":[4.8713750839,50.4566345215],"type":"Point"}
}