{
  "type": "Feature",
  "properties": {
    "addr:full":"Avenue Des Croix De Guerre 343 Box 7 Bruxelles Bruxelles-Capitale 1120",
    "addr:housenumber":"343;7",
    "addr:postcode":"1120",
    "addr:street":"Avenue Des Croix De Guerre;Box",
    "iso:country":"BE",
    "sg:address":"Avenue Des Croix De Guerre 343 Box 7",
    "sg:city":"Bruxelles",
    "sg:classifiers":[
        {
            "category":"Home & Garden",
            "subcategory":"Building Materials",
            "type":"Retail Goods"
        }
    ],
    "sg:phone":"+32 495 57 89 11",
    "sg:postcode":"1120",
    "sg:province":"Bruxelles-Capitale",
    "sg:tags":[
        "window"
    ],
    "wof:name":"Queral Colours",
    "wof:placetype":"venue"
},
  "geometry": {"coordinates":[4.3918499947,50.8949279785],"type":"Point"}
}