{
  "type": "Feature",
  "properties": {
    "addr:full":"Reepkenslei 10 Kontich Antwerpen 2550",
    "addr:housenumber":"10",
    "addr:postcode":"2550",
    "addr:street":"Reepkenslei",
    "iso:country":"BE",
    "sg:address":"Reepkenslei 10",
    "sg:city":"Kontich",
    "sg:orig_category":"Oldtimers",
    "sg:phone":"+32 3 458 04 57",
    "sg:postcode":"2550",
    "sg:province":"Antwerpen",
    "wof:name":"Van Roosenbroek & Zonen",
    "wof:placetype":"venue"
},
  "geometry": {"coordinates":[4.4475917816,51.1229248047],"type":"Point"}
}