{
  "type": "Feature",
  "properties": {
    "iso:country":"BE",
    "sg:address":"Rue Large Voie 228",
    "sg:city":"Herstal",
    "sg:orig_category":"Notaires",
    "sg:phone":"+32 4 264 06 80",
    "sg:postcode":"4040",
    "sg:province":"Li\u00e8ge",
    "wof:name":"Etienne Bozet",
    "wof:placetype":"venue"
},
  "geometry": {"coordinates":[5.6386709213,50.6694030762],"type":"Point"}
}