{
  "type": "Feature",
  "properties": {
    "addr:full":"Martinus V-straat 29 Sint-lambrechts-woluwe/woluwe-saint-lambert Bruxelles-Capitale 1200",
    "addr:housenumber":"29",
    "addr:postcode":"1200",
    "addr:street":"Martinus V-Straat",
    "iso:country":"BE",
    "sg:address":"Martinus V-straat 29",
    "sg:city":"Sint-lambrechts-woluwe/woluwe-saint-lambert",
    "sg:orig_category":"Drukkerijen and copyshops Kantoormateriaal",
    "sg:phone":"+32 2 762 35 85",
    "sg:postcode":"1200",
    "sg:province":"Bruxelles-Capitale",
    "wof:name":"Ciaco Papeterie",
    "wof:placetype":"venue"
},
  "geometry": {"coordinates":[4.4528942108,50.8498077393],"type":"Point"}
}