{
  "type": "Feature",
  "properties": {
    "addr:full":"Rue L\u00e9on Hachez 35 Soignies Hainaut 7060",
    "addr:housenumber":"35",
    "addr:postcode":"7060",
    "addr:street":"Rue Le\u0301On Hachez",
    "iso:country":"BE",
    "sg:address":"Rue L\u00e9on Hachez 35",
    "sg:city":"Soignies",
    "sg:classifiers":[
        {
            "category":"Home & Garden",
            "subcategory":"Kitchen Supply",
            "type":"Retail Goods"
        }
    ],
    "sg:phone":"+32 67 34 00 81",
    "sg:postcode":"7060",
    "sg:province":"Hainaut",
    "sg:tags":[
        "installation"
    ],
    "wof:name":"Adam P.m",
    "wof:placetype":"venue"
},
  "geometry": {"coordinates":[4.0692691803,50.5812034607],"type":"Point"}
}