{
  "type": "Feature",
  "properties": {
    "addr:full":"Rue Arsenal 72 Pont-a-celles Hainaut 6230",
    "addr:housenumber":"72",
    "addr:postcode":"6230",
    "addr:street":"Rue Arsenal",
    "iso:country":"BE",
    "sg:address":"Rue Arsenal 72",
    "sg:city":"Pont-a-celles",
    "sg:orig_category":"Motos",
    "sg:phone":"+32 71 84 47 29",
    "sg:postcode":"6230",
    "sg:province":"Hainaut",
    "wof:name":"Jeannine Detournay",
    "wof:placetype":"venue"
},
  "geometry": {"coordinates":[4.3752961159,50.5055770874],"type":"Point"}
}