{
  "type": "Feature",
  "properties": {
    "addr:full":"Schawijkstraat 39 Ranst Antwerpen 2520",
    "addr:housenumber":"39",
    "addr:postcode":"2520",
    "addr:street":"Schawijkstraat",
    "iso:country":"BE",
    "sg:address":"Schawijkstraat 39",
    "sg:city":"Ranst",
    "sg:classifiers":[
        {
            "category":"Shopping",
            "subcategory":"Gifts & Souvenirs",
            "type":"Retail Goods"
        }
    ],
    "sg:phone":"+32 3 353 19 87",
    "sg:postcode":"2520",
    "sg:province":"Antwerpen",
    "sg:tags":[
        "-"
    ],
    "wof:name":"La Pi\u00e8ce Unique",
    "wof:placetype":"venue"
},
  "geometry": {"coordinates":[4.5428218842,51.1953468323],"type":"Point"}
}