{
  "type": "Feature",
  "properties": {
    "iso:country":"BE",
    "sg:address":"Luchthavenlaan 16",
    "sg:city":"Vilvoorde",
    "sg:classifiers":[
        {
            "category":"Utilities",
            "subcategory":"Natural Gas",
            "type":"Services"
        }
    ],
    "sg:phone":"+32 3 321 54 32",
    "sg:postcode":"1800",
    "sg:province":"Vlaams-Brabant",
    "sg:tags":[
        "equipment",
        "heating",
        "system",
        "air"
    ],
    "wof:name":"Mcv Air-comfort B.v.b.a.",
    "wof:placetype":"venue"
},
  "geometry": {"coordinates":[4.4764637947,51.2098503113],"type":"Point"}
}