{
  "type": "Feature",
  "properties": {
    "iso:country":"BE",
    "sg:address":"Rue Autribu 4",
    "sg:city":"Ecaussinnes",
    "sg:orig_category":"Eleveurs de bovins",
    "sg:phone":"+32 67 49 12 87",
    "sg:postcode":"7190",
    "sg:province":"Hainaut",
    "wof:name":"Christian Duveillez",
    "wof:placetype":"venue"
},
  "geometry": {"coordinates":[4.163561821,50.5855522156],"type":"Point"}
}