{
  "type": "Feature",
  "properties": {
    "iso:country":"BE",
    "sg:address":"Breulstraat 94",
    "sg:city":"Moorslede",
    "sg:classifiers":[
        {
            "category":"Arena",
            "subcategory":"Sports Club",
            "type":"Entertainment"
        }
    ],
    "sg:phone":"+32 51 77 01 17",
    "sg:postcode":"8890",
    "sg:province":"West-Vlaanderen",
    "sg:tags":[
        "de"
    ],
    "wof:name":"Gympie Moorslede",
    "wof:placetype":"venue"
},
  "geometry": {"coordinates":[3.0728499889,50.8889884949],"type":"Point"}
}