{
  "type": "Feature",
  "properties": {
    "iso:country":"BE",
    "sg:address":"Place Du Monument 24",
    "sg:city":"Spa",
    "sg:orig_category":"Banken and kredietinstellingen",
    "sg:phone":"+32 87 77 25 86",
    "sg:postcode":"4900",
    "sg:province":"Li\u00e8ge",
    "wof:name":"Fortis",
    "wof:placetype":"venue"
},
  "geometry": {"coordinates":[5.863088131,50.4919967651],"type":"Point"}
}