{
  "type": "Feature",
  "properties": {
    "iso:country":"BE",
    "sg:address":"Bredabaan 1000",
    "sg:city":"Brasschaat",
    "sg:orig_category":"Experts-comptables",
    "sg:phone":"+32 3 633 06 60",
    "sg:postcode":"2930",
    "sg:province":"Antwerpen",
    "wof:name":"N. Slegers",
    "wof:placetype":"venue"
},
  "geometry": {"coordinates":[4.5318889618,51.3415489197],"type":"Point"}
}