{
  "type": "Feature",
  "properties": {
    "addr:full":"Keukeldam 60 Waregem West-Vlaanderen 8790",
    "addr:housenumber":"60",
    "addr:postcode":"8790",
    "addr:street":"Keukeldam",
    "iso:country":"BE",
    "sg:address":"Keukeldam 60",
    "sg:city":"Waregem",
    "sg:orig_category":"Sportclubs",
    "sg:phone":"+32 56 60 33 18",
    "sg:postcode":"8790",
    "sg:province":"West-Vlaanderen",
    "wof:name":"Waregemse Duikersclub",
    "wof:placetype":"venue"
},
  "geometry": {"coordinates":[3.4361379147,50.8881492615],"type":"Point"}
}