{
  "type": "Feature",
  "properties": {
    "iso:country":"BE",
    "sg:address":"Molenstraat 32",
    "sg:city":"Beveren (kieldrecht)",
    "sg:classifiers":[
        {
            "category":"Health Services",
            "subcategory":"Nursing And Care Facility",
            "type":"Services"
        }
    ],
    "sg:phone":"+32 3 773 42 29",
    "sg:postcode":"9130",
    "sg:province":"Oost-Vlaanderen",
    "sg:tags":[
        "home",
        "rest"
    ],
    "wof:name":"Vives",
    "wof:placetype":"venue"
},
  "geometry": {"coordinates":[4.1730179787,51.2905731201],"type":"Point"}
}