{
  "type": "Feature",
  "properties": {
    "iso:country":"BE",
    "sg:address":"Lindestraat 5bb",
    "sg:city":"Wortegem-petegem",
    "sg:orig_category":"Drukkerijen and copyshops",
    "sg:phone":"+32 55 31 27 91",
    "sg:postcode":"9790",
    "sg:province":"Oost-Vlaanderen",
    "wof:name":"Lelieur-van Lancker",
    "wof:placetype":"venue"
},
  "geometry": {"coordinates":[3.5514569283,50.8442649841],"type":"Point"}
}