{
  "type": "Feature",
  "properties": {
    "addr:full":"Chauss\u00c9e D\u00b4ixelles 296 Elsene/ixelles Bruxelles-Capitale 1050",
    "addr:housenumber":"296",
    "addr:postcode":"1050",
    "addr:street":"Chausse\u0301E D\u00b4Ixelles",
    "iso:country":"BE",
    "sg:address":"Chauss\u00c9e D\u00b4ixelles 296",
    "sg:city":"Elsene/ixelles",
    "sg:orig_category":"Rev\u00eatements de sols and murs. Rev\u00eatements pour sols and murs. Peinture. Eclairage et \u00e9quipements du ",
    "sg:phone":"+32 2 647 93 29",
    "sg:postcode":"1050",
    "sg:province":"Bruxelles-Capitale",
    "wof:name":"Xl Decor",
    "wof:placetype":"venue"
},
  "geometry": {"coordinates":[4.3709359169,50.8287353516],"type":"Point"}
}