{
  "type": "Feature",
  "properties": {
    "iso:country":"BE",
    "sg:address":"Luikersteenweg 367",
    "sg:city":"Hasselt",
    "sg:orig_category":"Verhuur bouwmachines",
    "sg:phone":"+32 11 28 14 74",
    "sg:postcode":"3500",
    "sg:province":"Limburg",
    "wof:name":"Mommers Jcb",
    "wof:placetype":"venue"
},
  "geometry": {"coordinates":[5.3548398018,50.909450531],"type":"Point"}
}