{
  "type": "Feature",
  "properties": {
    "addr:full":"Weststraat 26 Evergem (sleidinge) Oost-Vlaanderen 9940",
    "addr:housenumber":"26",
    "addr:postcode":"9940",
    "addr:street":"Weststraat",
    "iso:country":"BE",
    "sg:address":"Weststraat 26",
    "sg:city":"Evergem (sleidinge)",
    "sg:classifiers":[
        {
            "category":"Shopping",
            "subcategory":"Shoes",
            "type":"Retail Goods"
        }
    ],
    "sg:phone":"+32 9 357 49 48",
    "sg:postcode":"9940",
    "sg:province":"Oost-Vlaanderen",
    "sg:tags":[
        "slipper",
        "-"
    ],
    "wof:name":"Chantal",
    "wof:placetype":"venue"
},
  "geometry": {"coordinates":[3.6770761013,51.1315460205],"type":"Point"}
}