{
  "type": "Feature",
  "properties": {
    "iso:country":"BE",
    "sg:address":"Av. La Nouvelle Synth\u00c8se 12ba",
    "sg:city":"Binche",
    "sg:orig_category":"Bouwmaterialen Gh",
    "sg:phone":"+32 64 33 82 12",
    "sg:postcode":"7134",
    "sg:province":"Hainaut",
    "wof:name":"S.a.t.e.a.",
    "wof:placetype":"venue"
},
  "geometry": {"coordinates":[4.1985259056,50.4328231812],"type":"Point"}
}