{
  "type": "Feature",
  "properties": {
    "iso:country":"BE",
    "sg:address":"Route Des H\u00e8s 10",
    "sg:city":"Neufch\u00e2teau (longlier)",
    "sg:classifiers":[
        {
            "category":"Parking",
            "subcategory":"Garage",
            "type":"Transportation"
        }
    ],
    "sg:phone":"+32 61 27 91 53",
    "sg:postcode":"6840",
    "sg:province":"Luxembourg",
    "sg:tags":[
        "truck",
        "-",
        "dump",
        "transport"
    ],
    "wof:name":"Tinant Transport",
    "wof:placetype":"venue"
},
  "geometry": {"coordinates":[5.4584469795,49.8632888794],"type":"Point"}
}