{
  "type": "Feature",
  "properties": {
    "iso:country":"BE",
    "sg:address":"Staatsbladsstraat 7",
    "sg:city":"Brussel/bruxelles",
    "sg:orig_category":"Boekhandels",
    "sg:phone":"+32 2 217 10 72",
    "sg:postcode":"1000",
    "sg:province":"Bruxelles-Capitale",
    "wof:name":"Le Bon Livre",
    "wof:placetype":"venue"
},
  "geometry": {"coordinates":[4.364221096,50.8489151001],"type":"Point"}
}