{
  "type": "Feature",
  "properties": {
    "iso:country":"BE",
    "sg:address":"Rue Du Stocquy 41",
    "sg:city":"Fontaine-l'ev\u00eaque (forchies-la-marche)",
    "sg:classifiers":[
        {
            "category":"Professional",
            "subcategory":"Detective & Security Services",
            "type":"Services"
        }
    ],
    "sg:phone":"+32 71 52 06 13",
    "sg:postcode":"6141",
    "sg:province":"Hainaut",
    "sg:tags":[
        "access-control",
        "system"
    ],
    "wof:name":"Faccinetto",
    "wof:placetype":"venue"
},
  "geometry": {"coordinates":[4.33689785,50.4333610535],"type":"Point"}
}