{
  "type": "Feature",
  "properties": {
    "addr:full":"All\u00c9e De La Picherotte 28 Chaudfontaine Li\u00e8ge 4053",
    "addr:housenumber":"28",
    "addr:postcode":"4053",
    "addr:street":"Alle\u0301E De La Picherotte",
    "iso:country":"BE",
    "sg:address":"All\u00c9e De La Picherotte 28",
    "sg:city":"Chaudfontaine",
    "sg:orig_category":"Installatie van metalen schrijnwerk",
    "sg:phone":"+32 4 365 17 00",
    "sg:postcode":"4053",
    "sg:province":"Li\u00e8ge",
    "wof:name":"Raymond Vandeninden",
    "wof:placetype":"venue"
},
  "geometry": {"coordinates":[5.5965499878,50.5863685608],"type":"Point"}
}