{
  "type": "Feature",
  "properties": {
    "addr:full":"Rue Wittmann 64 Belgium Bruxelles-Capitale 1030",
    "addr:housenumber":"64",
    "addr:postcode":"1030",
    "addr:street":"Rue Wittmann",
    "iso:country":"BE",
    "sg:address":"Rue Wittmann 64",
    "sg:city":"Belgium",
    "sg:orig_category":"Etablissements Erotiques",
    "sg:phone":"+32 2 734 30 21",
    "sg:postcode":"1030",
    "sg:province":"Bruxelles-Capitale",
    "wof:name":"Studio A",
    "wof:placetype":"venue"
},
  "geometry": {"coordinates":[4.3919839859,50.8560447693],"type":"Point"}
}