{
  "type": "Feature",
  "properties": {
    "iso:country":"BE",
    "sg:address":"Rue Grande 27",
    "sg:city":"Viroinval",
    "sg:orig_category":"Sportclubs",
    "sg:phone":"+32 60 31 23 63",
    "sg:postcode":"5670",
    "sg:province":"Namur",
    "wof:name":"Les Crayas Du Thiry",
    "wof:placetype":"venue"
},
  "geometry": {"coordinates":[4.549726963,50.0728569031],"type":"Point"}
}