{
  "type": "Feature",
  "properties": {
    "iso:country":"BE",
    "sg:address":"Zwevegemsestraat 15",
    "sg:city":"Kortrijk",
    "sg:orig_category":"Tijdelijke werkgelegenheid and uitzendkantoren",
    "sg:phone":"+32 56 22 89 30",
    "sg:postcode":"8500",
    "sg:province":"West-Vlaanderen",
    "wof:name":"Alpha Interim",
    "wof:placetype":"venue"
},
  "geometry": {"coordinates":[3.2722539902,50.8258666992],"type":"Point"}
}