{
  "type": "Feature",
  "properties": {
    "addr:full":"Tombergstraat 7 Roosdaal Vlaams-Brabant 1760",
    "addr:housenumber":"7",
    "addr:postcode":"1760",
    "addr:street":"Tombergstraat",
    "iso:country":"BE",
    "sg:address":"Tombergstraat 7",
    "sg:city":"Roosdaal",
    "sg:classifiers":[
        {
            "category":"Professional",
            "subcategory":"Management & Consulting",
            "type":"Services"
        }
    ],
    "sg:phone":"+32 54 33 73 73",
    "sg:postcode":"1760",
    "sg:province":"Vlaams-Brabant",
    "sg:tags":[
        "-",
        "processing",
        "data",
        "consultant"
    ],
    "wof:name":"Marc's Services & Engineering",
    "wof:placetype":"venue"
},
  "geometry": {"coordinates":[4.0744271278,50.8435707092],"type":"Point"}
}