{
  "type": "Feature",
  "properties": {
    "addr:full":"Rue De Fayt 11 Jodoigne Brabant Wallon 1370",
    "addr:housenumber":"11",
    "addr:postcode":"1370",
    "addr:street":"Rue De Fayt",
    "iso:country":"BE",
    "sg:address":"Rue De Fayt 11",
    "sg:city":"Jodoigne",
    "sg:orig_category":"Services de Nettoyage and de D\u00e9sinfection",
    "sg:phone":"+32 10 88 99 63",
    "sg:postcode":"1370",
    "sg:province":"Brabant Wallon",
    "wof:name":"Jean-pierre Guffens",
    "wof:placetype":"venue"
},
  "geometry": {"coordinates":[4.8156290054,50.6951446533],"type":"Point"}
}