{
  "type": "Feature",
  "properties": {
    "addr:full":"Vaartkom 9 Leuven Vlaams-Brabant 3000",
    "addr:housenumber":"9",
    "addr:postcode":"3000",
    "addr:street":"Vaartkom",
    "iso:country":"BE",
    "sg:address":"Vaartkom 9",
    "sg:city":"Leuven",
    "sg:classifiers":[
        {
            "category":"Retail",
            "subcategory":"Car Wash",
            "type":"Services"
        }
    ],
    "sg:phone":"+32 16 23 92 39",
    "sg:postcode":"3000",
    "sg:province":"Vlaams-Brabant",
    "sg:tags":[
        "automobile",
        "washing",
        "-",
        "truck"
    ],
    "wof:name":"De Wasstraat",
    "wof:placetype":"venue"
},
  "geometry": {"coordinates":[4.7014579773,50.8879127502],"type":"Point"}
}