{
  "type": "Feature",
  "properties": {
    "addr:full":"En Hurbise 160 Herstal Li\u00e8ge 4040",
    "addr:housenumber":"160",
    "addr:postcode":"4040",
    "iso:country":"BE",
    "sg:address":"En Hurbise 160",
    "sg:city":"Herstal",
    "sg:classifiers":[
        {
            "category":"Travel",
            "subcategory":"Hotels & Motels",
            "type":"Entertainment"
        }
    ],
    "sg:phone":"+32 4 264 64 00",
    "sg:postcode":"4040",
    "sg:province":"Li\u00e8ge",
    "wof:name":"Post H\u00d4tel",
    "wof:placetype":"venue"
},
  "geometry": {"coordinates":[5.6282658577,50.6872558594],"type":"Point"}
}