{
  "type": "Feature",
  "properties": {
    "addr:full":"Pieter Lansensstraat 2 Koekelare West-Vlaanderen 8680",
    "addr:housenumber":"2",
    "addr:postcode":"8680",
    "addr:street":"Pieter Lansensstraat",
    "iso:country":"BE",
    "sg:address":"Pieter Lansensstraat 2",
    "sg:city":"Koekelare",
    "sg:classifiers":[
        {
            "category":"Insurance",
            "subcategory":"Insurance Agent",
            "type":"Services"
        }
    ],
    "sg:phone":"+32 51 58 11 21",
    "sg:postcode":"8680",
    "sg:province":"West-Vlaanderen",
    "sg:tags":[
        "broker"
    ],
    "wof:name":"Volcke Kantoor",
    "wof:placetype":"venue"
},
  "geometry": {"coordinates":[2.980700016,51.0904579163],"type":"Point"}
}