{
  "type": "Feature",
  "properties": {
    "addr:full":"Rue Des Choraux 1-5 Nivelles Brabant Wallon 1400",
    "addr:housenumber":"1-5",
    "addr:postcode":"1400",
    "addr:street":"Rue Des Choraux",
    "iso:country":"BE",
    "sg:address":"Rue Des Choraux 1-5",
    "sg:city":"Nivelles",
    "sg:classifiers":[
        {
            "category":"Building & Trades",
            "subcategory":"Landscaping Services",
            "type":"Services"
        }
    ],
    "sg:phone":"+32 67 21 23 42",
    "sg:postcode":"1400",
    "sg:province":"Brabant Wallon",
    "sg:tags":[
        "architect",
        "landscape"
    ],
    "wof:name":"L'atelier Paysager",
    "wof:placetype":"venue"
},
  "geometry": {"coordinates":[4.3225622177,50.5985298157],"type":"Point"}
}