{
  "type": "Feature",
  "properties": {
    "iso:country":"BE",
    "sg:address":"Vina Bovypark 9/2c",
    "sg:city":"Gent-centrum",
    "sg:orig_category":"Advocaten and juridische adviseurs Balie van Gent",
    "sg:phone":"+32 9 220 31 61",
    "sg:postcode":"9000",
    "sg:province":"Oost-Vlaanderen",
    "wof:name":"Markey Kristiaan",
    "wof:placetype":"venue"
},
  "geometry": {"coordinates":[3.7071759701,51.0350914001],"type":"Point"}
}