{
  "type": "Feature",
  "properties": {
    "iso:country":"BE",
    "sg:address":"Route Custinne 5",
    "sg:city":"Houyet",
    "sg:orig_category":"M\u00e9decins and sp\u00e9cialistes",
    "sg:phone":"+32 82 66 69 53",
    "sg:postcode":"5562",
    "sg:province":"Namur",
    "wof:name":"A. Rosoux",
    "wof:placetype":"venue"
},
  "geometry": {"coordinates":[5.0506510735,50.2102928162],"type":"Point"}
}