{
  "type": "Feature",
  "properties": {
    "iso:country":"BE",
    "sg:address":"Florisstraat 4",
    "sg:city":"Antwerpen",
    "sg:classifiers":[
        {
            "category":"Health Services",
            "subcategory":"Health Practitioner",
            "type":"Services"
        }
    ],
    "sg:phone":"+32 3 233 54 51",
    "sg:postcode":"2018",
    "sg:province":"Antwerpen",
    "sg:tags":[
        "physiotherapist"
    ],
    "wof:name":"Schlenker Mary",
    "wof:placetype":"venue"
},
  "geometry": {"coordinates":[4.4128727913,51.2093544006],"type":"Point"}
}