{
  "type": "Feature",
  "properties": {
    "iso:country":"BE",
    "sg:address":"Moonsstraat 60",
    "sg:city":"Antwerpen",
    "sg:orig_category":"Catering and organisation de f\u00eates",
    "sg:phone":"+32 3 237 29 71",
    "sg:postcode":"2018",
    "sg:province":"Antwerpen",
    "wof:name":"Venezia-heido",
    "wof:placetype":"venue"
},
  "geometry": {"coordinates":[4.397796154,51.2008628845],"type":"Point"}
}