{
  "type": "Feature",
  "properties": {
    "iso:country":"BE",
    "sg:address":"Quai Saint-l\u00c9onard 36bi",
    "sg:city":"Li\u00c8ge",
    "sg:orig_category":"Apotheken",
    "sg:phone":"+32 4 227 41 43",
    "sg:postcode":"4000",
    "sg:province":"Li\u00e8ge",
    "wof:name":"Pharmacie St.l\u00c9onard",
    "wof:placetype":"venue"
},
  "geometry": {"coordinates":[5.5910701752,50.6479072571],"type":"Point"}
}