{
  "type": "Feature",
  "properties": {
    "iso:country":"BE",
    "sg:address":"Chauss\u00c9e De Bruxelles 216",
    "sg:city":"Charleroi",
    "sg:orig_category":"Artistes ind\u00e9pendants",
    "sg:phone":"+32 71 35 05 63",
    "sg:postcode":"6040",
    "sg:province":"Hainaut",
    "wof:name":"M. Persoons",
    "wof:placetype":"venue"
},
  "geometry": {"coordinates":[4.436727047,50.4439582825],"type":"Point"}
}