{
  "type": "Feature",
  "properties": {
    "iso:country":"BE",
    "sg:address":"Molendries 19",
    "sg:city":"Aalst",
    "sg:classifiers":[
        {
            "category":"Cafe",
            "type":"Food & Drink"
        }
    ],
    "sg:phone":"+32 53 78 18 71",
    "sg:postcode":"9300",
    "sg:province":"Oost-Vlaanderen",
    "sg:tags":[
        "caf\u00e9s"
    ],
    "wof:name":"Caf\u00c9 Play-boy",
    "wof:placetype":"venue"
},
  "geometry": {"coordinates":[4.0445427895,50.9415130615],"type":"Point"}
}