{
  "type": "Feature",
  "properties": {
    "iso:country":"BE",
    "sg:address":"Neusepln 23",
    "sg:city":"Gent",
    "sg:orig_category":"Kapsalons",
    "sg:phone":"+32 9 225 02 75",
    "sg:postcode":"9000",
    "sg:province":"Oost-Vlaanderen",
    "wof:name":"Nanette",
    "wof:placetype":"venue"
},
  "geometry": {"coordinates":[3.7270450592,51.0673904419],"type":"Point"}
}