{
  "type": "Feature",
  "properties": {
    "addr:full":"Koning Boudewijnhof 31 Bornem Antwerpen 2880",
    "addr:housenumber":"31",
    "addr:postcode":"2880",
    "addr:street":"Koning Boudewijnhof",
    "iso:country":"BE",
    "sg:address":"Koning Boudewijnhof 31",
    "sg:city":"Bornem",
    "sg:orig_category":"Woningbouw",
    "sg:phone":"+32 3 889 63 12",
    "sg:postcode":"2880",
    "sg:province":"Antwerpen",
    "wof:name":"Marc Drossaert",
    "wof:placetype":"venue"
},
  "geometry": {"coordinates":[4.2989168167,51.1043205261],"type":"Point"}
}