{
  "type": "Feature",
  "properties": {
    "addr:full":"Maria-theresiastraat 14b1c Leuven Vlaams-Brabant 3000",
    "addr:housenumber":"14b1c",
    "addr:postcode":"3000",
    "addr:street":"Maria-Theresiastraat",
    "iso:country":"BE",
    "sg:address":"Maria-theresiastraat 14b1c",
    "sg:city":"Leuven",
    "sg:orig_category":"Ordinateurs and \u00e9quipement informatique",
    "sg:phone":"+32 16 20 57 38",
    "sg:postcode":"3000",
    "sg:province":"Vlaams-Brabant",
    "wof:name":"Fa. Solutions",
    "wof:placetype":"venue"
},
  "geometry": {"coordinates":[4.7098269463,50.8765602112],"type":"Point"}
}