{
  "type": "Feature",
  "properties": {
    "iso:country":"BE",
    "sg:address":"Place De L'h\u00d4tel De Ville",
    "sg:city":"Gembloux",
    "sg:orig_category":"Rijscholen",
    "sg:phone":"+32 10 41 64 43",
    "sg:postcode":"5030",
    "sg:province":"Namur",
    "wof:name":"Auto-ecole Raty",
    "wof:placetype":"venue"
},
  "geometry": {"coordinates":[4.6945400238,50.5666313171],"type":"Point"}
}