{
  "type": "Feature",
  "properties": {
    "iso:country":"BE",
    "sg:address":"Clemenceaulaan 63",
    "sg:city":"Anderlecht/anderlecht",
    "sg:orig_category":"Advocaten and juridische adviseurs",
    "sg:phone":"+32 2 522 32 99",
    "sg:postcode":"1070",
    "sg:province":"Bruxelles-Capitale",
    "wof:name":"Y. L\u00c9onard",
    "wof:placetype":"venue"
},
  "geometry": {"coordinates":[4.3337869644,50.8408813477],"type":"Point"}
}