{
  "type": "Feature",
  "properties": {
    "addr:full":"Clos Du Vivier 8 Soignies Hainaut 7061",
    "addr:housenumber":"8",
    "addr:postcode":"7061",
    "addr:street":"Clos Du Vivier",
    "iso:country":"BE",
    "sg:address":"Clos Du Vivier 8",
    "sg:city":"Soignies",
    "sg:orig_category":"Artsen and specialisten",
    "sg:phone":"+32 65 72 87 93",
    "sg:postcode":"7061",
    "sg:province":"Hainaut",
    "wof:name":"Andr\u00c9 Quenon",
    "wof:placetype":"venue"
},
  "geometry": {"coordinates":[4.0133500099,50.5159416199],"type":"Point"}
}