{
  "type": "Feature",
  "properties": {
    "iso:country":"BE",
    "sg:address":"Rue De Linthout 188",
    "sg:city":"Bruxelles (etterbeek)",
    "sg:classifiers":[
        {
            "category":"Banks & Credit Unions",
            "subcategory":"Financial Services",
            "type":"Services"
        }
    ],
    "sg:phone":"+32 2 647 58 20",
    "sg:postcode":"1040",
    "sg:province":"Bruxelles-Capitale",
    "sg:tags":[
        "loan",
        "mortgage"
    ],
    "wof:name":"Gs Finance",
    "wof:placetype":"venue"
},
  "geometry": {"coordinates":[4.4011898041,50.8420181274],"type":"Point"}
}