{
  "type": "Feature",
  "properties": {
    "addr:full":"Rue Haute 218 Bruxelles Bruxelles-Capitale 1000",
    "addr:housenumber":"218",
    "addr:postcode":"1000",
    "addr:street":"Rue Haute",
    "iso:country":"BE",
    "sg:address":"Rue Haute 218",
    "sg:city":"Bruxelles",
    "sg:classifiers":[
        {
            "category":"Shopping",
            "subcategory":"Clothing, Apparel, & Fashions",
            "type":"Retail Goods"
        }
    ],
    "sg:phone":"+32 2 512 55 14",
    "sg:postcode":"1000",
    "sg:province":"Bruxelles-Capitale",
    "sg:tags":[
        "clothing",
        "-",
        "gentleman"
    ],
    "wof:name":"Ciseaux D'or (aux)",
    "wof:placetype":"venue"
},
  "geometry": {"coordinates":[4.3489718437,50.8371543884],"type":"Point"}
}