{
  "type": "Feature",
  "properties": {
    "iso:country":"BE",
    "sg:address":"Rue Comte D'ursel 31",
    "sg:city":"Durbuy",
    "sg:orig_category":"Herenkledingzaken Textiel",
    "sg:phone":"+32 86 21 39 84",
    "sg:postcode":"6940",
    "sg:province":"Luxembourg",
    "wof:name":"Maison Atmosph\u00c8re",
    "wof:placetype":"venue"
},
  "geometry": {"coordinates":[5.4546108246,50.3515815735],"type":"Point"}
}