{
  "type": "Feature",
  "properties": {
    "iso:country":"BE",
    "sg:address":"Avenue Charles Plisnier 5",
    "sg:city":"Wavre",
    "sg:classifiers":[
        {
            "category":"Health Services",
            "subcategory":"Health Practitioner",
            "type":"Services"
        }
    ],
    "sg:phone":"+32 10 45 36 02",
    "sg:postcode":"1300",
    "sg:province":"Brabant Wallon",
    "sg:tags":[
        "physiotherapist"
    ],
    "wof:name":"Johnson Florence",
    "wof:placetype":"venue"
},
  "geometry": {"coordinates":[4.6381850243,50.7091751099],"type":"Point"}
}