{
  "type": "Feature",
  "properties": {
    "iso:country":"BE",
    "sg:address":"5",
    "sg:city":"Schouwkensstraat 2030 Antwerpen",
    "sg:classifiers":[
        {
            "category":"Autos & Motor Vehicles",
            "subcategory":"Automobile Sales",
            "type":"Retail Goods"
        }
    ],
    "sg:phone":"+32 3 541 75 50",
    "sg:postcode":"5",
    "sg:tags":[
        "equipment",
        "motor-cars",
        "transport"
    ],
    "wof:name":"Garage Kant Antwerpen Nv",
    "wof:placetype":"venue"
},
  "geometry": {"coordinates":[4.387565136,51.2720298767],"type":"Point"}
}