{
  "type": "Feature",
  "properties": {
    "iso:country":"BE",
    "sg:address":"Auguste Van Ooststraat 8",
    "sg:city":"Gent (ledeberg)",
    "sg:classifiers":[
        {
            "category":"Social Services",
            "type":"Services"
        }
    ],
    "sg:phone":"+32 9 231 35 92",
    "sg:postcode":"9050",
    "sg:province":"Oost-Vlaanderen",
    "wof:name":"Vrije Familiekring De Ronde",
    "wof:placetype":"venue"
},
  "geometry": {"coordinates":[3.7468490601,51.0437736511],"type":"Point"}
}