{
  "type": "Feature",
  "properties": {
    "iso:country":"BE",
    "sg:address":"Rue Du Ch\u00c2teau 1",
    "sg:city":"Marche-en-famenne",
    "sg:orig_category":"Avocats and conseillers juridiques",
    "sg:phone":"+32 84 32 27 52",
    "sg:postcode":"6900",
    "sg:province":"Luxembourg",
    "wof:name":"C. Munaut",
    "wof:placetype":"venue"
},
  "geometry": {"coordinates":[5.3430151939,50.2273483276],"type":"Point"}
}