{
  "type": "Feature",
  "properties": {
    "iso:country":"BE",
    "sg:address":"Duivenstraat 86",
    "sg:city":"Mechelen",
    "sg:orig_category":"D\u00e9chets and d\u00e9bris Gr",
    "sg:phone":"+32 15 20 17 21",
    "sg:postcode":"2800",
    "sg:province":"Antwerpen",
    "wof:name":"Bonaugure J",
    "wof:placetype":"venue"
},
  "geometry": {"coordinates":[4.4860401154,51.0467643738],"type":"Point"}
}