{
  "type": "Feature",
  "properties": {
    "addr:full":"Archimedeslaan 11b3 Edegem Antwerpen 2650",
    "addr:housenumber":"11b3",
    "addr:postcode":"2650",
    "addr:street":"Archimedeslaan",
    "iso:country":"BE",
    "sg:address":"Archimedeslaan 11b3",
    "sg:city":"Edegem",
    "sg:orig_category":"Informaticaconsulenten",
    "sg:phone":"+32 16 25 06 34",
    "sg:postcode":"2650",
    "sg:province":"Antwerpen",
    "wof:name":"Com'in Services",
    "wof:placetype":"venue"
},
  "geometry": {"coordinates":[4.4411129951,51.151309967],"type":"Point"}
}