{
  "type": "Feature",
  "properties": {
    "addr:full":"Hauwerstraat 23 Brugge West-Vlaanderen 8000",
    "addr:housenumber":"23",
    "addr:postcode":"8000",
    "addr:street":"Hauwerstraat",
    "iso:country":"BE",
    "sg:address":"Hauwerstraat 23",
    "sg:city":"Brugge",
    "sg:classifiers":[
        {
            "category":"Education",
            "subcategory":"School",
            "type":"Public Place"
        }
    ],
    "sg:phone":"+32 50 33 62 26",
    "sg:postcode":"8000",
    "sg:province":"West-Vlaanderen",
    "sg:tags":[
        "boarding"
    ],
    "wof:name":"Elckerlyc",
    "wof:placetype":"venue"
},
  "geometry": {"coordinates":[3.2144939899,51.2036209106],"type":"Point"}
}