{
  "type": "Feature",
  "properties": {
    "iso:country":"BE",
    "sg:address":"Kortrijkstraat 381",
    "sg:city":"Wevelgem",
    "sg:orig_category":"Pain, p\u00e2tisseries and confiseries",
    "sg:phone":"+32 56 37 02 02",
    "sg:postcode":"8560",
    "sg:province":"West-Vlaanderen",
    "wof:name":"Dessert Club",
    "wof:placetype":"venue"
},
  "geometry": {"coordinates":[3.2201550007,50.8194961548],"type":"Point"}
}