{
  "type": "Feature",
  "properties": {
    "addr:full":"Avenue Winston Churchill 238 Bruxelles (uccle) Bruxelles-Capitale 1180",
    "addr:housenumber":"238",
    "addr:postcode":"1180",
    "addr:street":"Avenue Winston Churchill",
    "iso:country":"BE",
    "sg:address":"Avenue Winston Churchill 238",
    "sg:city":"Bruxelles (uccle)",
    "sg:classifiers":[
        {
            "category":"Insurance",
            "subcategory":"Insurance Agent",
            "type":"Services"
        }
    ],
    "sg:phone":"+32 2 347 75 06",
    "sg:postcode":"1180",
    "sg:province":"Bruxelles-Capitale",
    "sg:tags":[
        "broker"
    ],
    "wof:name":"De Jonghe D'ardoye E",
    "wof:placetype":"venue"
},
  "geometry": {"coordinates":[4.366150856,50.81199646],"type":"Point"}
}