{
  "type": "Feature",
  "properties": {
    "addr:full":"Stationstraat 0 Haacht Vlaams-Brabant 3150",
    "addr:housenumber":"0",
    "addr:postcode":"3150",
    "addr:street":"Stationstraat",
    "iso:country":"BE",
    "sg:address":"Stationstraat 0",
    "sg:city":"Haacht",
    "sg:orig_category":"Services pour animaux domestiques",
    "sg:phone":"+32 16 53 32 88",
    "sg:postcode":"3150",
    "sg:province":"Vlaams-Brabant",
    "wof:name":"Haachtse Hondenclub Thor",
    "wof:placetype":"venue"
},
  "geometry": {"coordinates":[4.636223793,50.9767684937],"type":"Point"}
}