{
  "type": "Feature",
  "properties": {
    "iso:country":"BE",
    "sg:address":"Albert I Laan 50",
    "sg:city":"Veurne",
    "sg:orig_category":"Non-Classified Establishments",
    "sg:phone":"+32 58 31 45 31",
    "sg:postcode":"8630",
    "sg:province":"West-Vlaanderen",
    "wof:name":"Dekeyser Bvba",
    "wof:placetype":"venue"
},
  "geometry": {"coordinates":[2.679224968,51.0631141663],"type":"Point"}
}