{
  "type": "Feature",
  "properties": {
    "addr:full":"Rue De Sendrogne 134a Sprimont Li\u00e8ge 4140",
    "addr:housenumber":"134a",
    "addr:postcode":"4140",
    "addr:street":"Rue De Sendrogne",
    "iso:country":"BE",
    "sg:address":"Rue De Sendrogne 134a",
    "sg:city":"Sprimont",
    "sg:classifiers":[
        {
            "category":"Health Services",
            "subcategory":"Nursing And Care Facility",
            "type":"Services"
        }
    ],
    "sg:phone":"+32 4 360 94 33",
    "sg:postcode":"4140",
    "sg:province":"Li\u00e8ge",
    "sg:tags":[
        "home"
    ],
    "wof:name":"Gavage L",
    "wof:placetype":"venue"
},
  "geometry": {"coordinates":[5.6676001549,50.5203781128],"type":"Point"}
}