{
  "type": "Feature",
  "properties": {
    "iso:country":"BE",
    "sg:address":"Tweede Carabinierslaan 145",
    "sg:city":"Lanaken (veldwezelt)",
    "sg:classifiers":[
        {
            "category":"Manufacturing",
            "subcategory":"Pottery",
            "type":"Manufacturing & Wholesale Goods"
        }
    ],
    "sg:phone":"+32 89 71 51 38",
    "sg:postcode":"3620",
    "sg:province":"Limburg",
    "sg:tags":[
        "facing",
        "brick"
    ],
    "wof:name":"Heylen Bricks",
    "wof:placetype":"venue"
},
  "geometry": {"coordinates":[5.6551351547,50.8912277222],"type":"Point"}
}