{
  "type": "Feature",
  "properties": {
    "addr:full":"302 Kortrijksesteenweg 9000 Gent 302",
    "addr:housenumber":"302",
    "addr:postcode":"9000;302",
    "addr:street":"Kortrijksesteenweg",
    "iso:country":"BE",
    "sg:address":"302",
    "sg:city":"Kortrijksesteenweg 9000 Gent",
    "sg:classifiers":[
        {
            "category":"Banks & Credit Unions",
            "subcategory":"Financial Services",
            "type":"Services"
        }
    ],
    "sg:phone":"+32 9 242 37 11",
    "sg:postcode":"302",
    "sg:tags":[
        "banking",
        "finance",
        "insurance"
    ],
    "wof:name":"Mercator & Noordstar Nv",
    "wof:placetype":"venue"
},
  "geometry": {"coordinates":[3.7162899971,51.0357093811],"type":"Point"}
}