{
  "type": "Feature",
  "properties": {
    "addr:full":"Rue De La Limite 6 Bruxelles (saint-josse-ten-noode) Bruxelles-Capitale 1210",
    "addr:housenumber":"6",
    "addr:postcode":"1210",
    "addr:street":"Rue De La Limite",
    "iso:country":"BE",
    "sg:address":"Rue De La Limite 6",
    "sg:city":"Bruxelles (saint-josse-ten-noode)",
    "sg:classifiers":[
        {
            "category":"Professional",
            "subcategory":"Engineering",
            "type":"Services"
        }
    ],
    "sg:phone":"+32 2 223 46 86",
    "sg:postcode":"1210",
    "sg:province":"Bruxelles-Capitale",
    "sg:tags":[
        "-"
    ],
    "wof:name":"Ati",
    "wof:placetype":"venue"
},
  "geometry": {"coordinates":[4.3701090813,50.8524971008],"type":"Point"}
}