{
  "type": "Feature",
  "properties": {
    "addr:full":"Hengelhoefstraat 172 Genk Limburg 3600",
    "addr:housenumber":"172",
    "addr:postcode":"3600",
    "addr:street":"Hengelhoefstraat",
    "iso:country":"BE",
    "sg:address":"Hengelhoefstraat 172",
    "sg:city":"Genk",
    "sg:classifiers":[
        {
            "category":"Wholesale",
            "subcategory":"Machinery & Supplies",
            "type":"Manufacturing & Wholesale Goods"
        }
    ],
    "sg:phone":"+32 89 38 69 86",
    "sg:postcode":"3600",
    "sg:province":"Limburg",
    "sg:tags":[
        "refrigeration",
        "-",
        "industrial",
        "commercial",
        "equipment"
    ],
    "wof:name":"Evk Airconditioning Nv",
    "wof:placetype":"venue"
},
  "geometry": {"coordinates":[5.4692401886,51.0023651123],"type":"Point"}
}