{
  "type": "Feature",
  "properties": {
    "iso:country":"BE",
    "sg:address":"Visbeekstraat 26",
    "sg:city":"Turnhout",
    "sg:classifiers":[
        {
            "category":"Home & Garden",
            "subcategory":"Carpets & Floor Coverings",
            "type":"Retail Goods"
        }
    ],
    "sg:phone":"+32 14 44 35 70",
    "sg:postcode":"2300",
    "sg:province":"Antwerpen",
    "sg:tags":[
        "parquet"
    ],
    "wof:name":"Turnhoutse Schrijn- En Bouwwerken Nv",
    "wof:placetype":"venue"
},
  "geometry": {"coordinates":[4.9111061096,51.3062896729],"type":"Point"}
}