{
  "type": "Feature",
  "properties": {
    "addr:full":"Rue Joseph Ii 36-38 Bruxelles Bruxelles-Capitale 1000",
    "addr:housenumber":"36-38",
    "addr:postcode":"1000",
    "addr:street":"Rue Joseph Ii",
    "iso:country":"BE",
    "sg:address":"Rue Joseph Ii 36-38",
    "sg:city":"Bruxelles",
    "sg:classifiers":[
        {
            "category":"Organizations",
            "subcategory":"Professional Association",
            "type":"Services"
        }
    ],
    "sg:phone":"+32 2 230 91 07",
    "sg:postcode":"1000",
    "sg:province":"Bruxelles-Capitale",
    "sg:tags":[
        "trade-union",
        "federation"
    ],
    "wof:name":"Reti",
    "wof:placetype":"venue"
},
  "geometry": {"coordinates":[4.3721108437,50.8459587097],"type":"Point"}
}