{
  "type": "Feature",
  "properties": {
    "iso:country":"BE",
    "sg:address":"Dorp 5",
    "sg:city":"Holsbeek",
    "sg:orig_category":"Caf\u00e9s Ruimtes voor conferenties, recepties and feesten",
    "sg:phone":"+32 16 56 56 79",
    "sg:postcode":"3221",
    "sg:province":"Vlaams-Brabant",
    "wof:name":"Buurthuis De Veldbazuin",
    "wof:placetype":"venue"
},
  "geometry": {"coordinates":[4.8336501122,50.9500007629],"type":"Point"}
}