{
  "type": "Feature",
  "properties": {
    "iso:country":"BE",
    "sg:address":"Rue De La Coupe 11",
    "sg:city":"Mons",
    "sg:classifiers":[
        {
            "category":"Shopping",
            "subcategory":"Clothing, Apparel, & Fashions",
            "type":"Retail Goods"
        }
    ],
    "sg:phone":"+32 65 87 48 03",
    "sg:postcode":"7000",
    "sg:province":"Hainaut",
    "sg:tags":[
        "boutique"
    ],
    "wof:name":"Evasion Espace Tintin",
    "wof:placetype":"venue"
},
  "geometry": {"coordinates":[3.9522829056,50.4535636902],"type":"Point"}
}