{
  "type": "Feature",
  "properties": {
    "iso:country":"BE",
    "sg:address":"Mariastraat 38",
    "sg:city":"Brugge",
    "sg:orig_category":"Diverse persoonlijke diensten",
    "sg:phone":"+32 50 34 86 46",
    "sg:postcode":"8000",
    "sg:province":"West-Vlaanderen",
    "wof:name":"Dominique Lemey",
    "wof:placetype":"venue"
},
  "geometry": {"coordinates":[3.2239830494,51.2041854858],"type":"Point"}
}