{
  "type": "Feature",
  "properties": {
    "addr:full":"Gentsesteenweg 38 Mechelen Antwerpen 2800",
    "addr:housenumber":"38",
    "addr:postcode":"2800",
    "addr:street":"Gentsesteenweg",
    "iso:country":"BE",
    "sg:address":"Gentsesteenweg 38",
    "sg:city":"Mechelen",
    "sg:classifiers":[
        {
            "category":"Restaurant",
            "type":"Food & Drink"
        }
    ],
    "sg:phone":"+32 15 43 32 44",
    "sg:postcode":"2800",
    "sg:province":"Antwerpen",
    "wof:name":"Nino's",
    "wof:placetype":"venue"
},
  "geometry": {"coordinates":[4.434800148,51.0416412354],"type":"Point"}
}