{
  "type": "Feature",
  "properties": {
    "iso:country":"BE",
    "sg:address":"Tiensevest 180",
    "sg:city":"Leuven",
    "sg:orig_category":"Avocats and conseillers juridiques",
    "sg:phone":"+32 16 23 84 53",
    "sg:postcode":"3000",
    "sg:province":"Vlaams-Brabant",
    "wof:name":"V. Wortelaers",
    "wof:placetype":"venue"
},
  "geometry": {"coordinates":[4.7143192291,50.8742332458],"type":"Point"}
}