{
  "type": "Feature",
  "properties": {
    "iso:country":"BE",
    "sg:address":"Rue Van Schoor 93",
    "sg:city":"Schaarbeek/schaerbeek",
    "sg:orig_category":"M\u00e9decins and sp\u00e9cialistes",
    "sg:phone":"+32 2 242 53 25",
    "sg:postcode":"1030",
    "sg:province":"Bruxelles-Capitale",
    "wof:name":"Spiros Xanthos",
    "wof:placetype":"venue"
},
  "geometry": {"coordinates":[4.3685359955,50.8701705933],"type":"Point"}
}