{
  "type": "Feature",
  "properties": {
    "addr:full":"Sasplein 10 Willebroek Antwerpen 2830",
    "addr:housenumber":"10",
    "addr:postcode":"2830",
    "addr:street":"Sasplein",
    "iso:country":"BE",
    "sg:address":"Sasplein 10",
    "sg:city":"Willebroek",
    "sg:orig_category":"M\u00e9decins and sp\u00e9cialistes",
    "sg:phone":"+32 3 844 60 79",
    "sg:postcode":"2830",
    "sg:province":"Antwerpen",
    "wof:name":"N. Merckx",
    "wof:placetype":"venue"
},
  "geometry": {"coordinates":[4.3633098602,51.0605506897],"type":"Point"}
}