{
  "type": "Feature",
  "properties": {
    "iso:country":"BE",
    "sg:address":"Wijnheuvelenstraat 216",
    "sg:city":"Schaarbeek/schaerbeek",
    "sg:orig_category":"Onderdelen and accessoires voor auto's",
    "sg:phone":"+32 2 245 82 24",
    "sg:postcode":"1030",
    "sg:province":"Bruxelles-Capitale",
    "wof:name":"Rho - Delta/g.t. Belgium",
    "wof:placetype":"venue"
},
  "geometry": {"coordinates":[4.3783679008,50.8605690002],"type":"Point"}
}