{
  "type": "Feature",
  "properties": {
    "iso:country":"BE",
    "sg:address":"Populierenlaan 38",
    "sg:city":"Liedekerke",
    "sg:orig_category":"Mat\u00e9riaux de construction Gr",
    "sg:phone":"+32 53 66 69 84",
    "sg:postcode":"1770",
    "sg:province":"Vlaams-Brabant",
    "wof:name":"Tijd.ver. S.d.m.-f.i.v.b.",
    "wof:placetype":"venue"
},
  "geometry": {"coordinates":[4.1018099785,50.8607788086],"type":"Point"}
}