{
  "type": "Feature",
  "properties": {
    "iso:country":"BE",
    "sg:address":"Dronckaertstraat 360",
    "sg:city":"Menen",
    "sg:classifiers":[
        {
            "category":"Insurance",
            "subcategory":"Life Insurance",
            "type":"Services"
        }
    ],
    "sg:phone":"+32 56 41 81 08",
    "sg:postcode":"8930",
    "sg:province":"West-Vlaanderen",
    "sg:tags":[
        "assurance"
    ],
    "wof:name":"Soens",
    "wof:placetype":"venue"
},
  "geometry": {"coordinates":[3.1636819839,50.7693557739],"type":"Point"}
}