{
  "type": "Feature",
  "properties": {
    "iso:country":"BE",
    "sg:address":"Industriestraat 26",
    "sg:city":"Ichtegem",
    "sg:orig_category":"Boissons",
    "sg:phone":"+32 51 58 21 72",
    "sg:postcode":"8480",
    "sg:province":"West-Vlaanderen",
    "wof:name":"Drank Mart",
    "wof:placetype":"venue"
},
  "geometry": {"coordinates":[3.0242950916,51.0980148315],"type":"Point"}
}