{
  "type": "Feature",
  "properties": {
    "iso:country":"BE",
    "sg:address":"Houthulstseweg 100b",
    "sg:city":"Langemark-poelkapelle (poelkapelle)",
    "sg:classifiers":[
        {
            "category":"Health Services",
            "subcategory":"Nursing And Care Facility",
            "type":"Services"
        }
    ],
    "sg:phone":"+32 57 48 53 83",
    "sg:postcode":"8920",
    "sg:province":"West-Vlaanderen",
    "sg:tags":[
        "home"
    ],
    "wof:name":"Debeer P",
    "wof:placetype":"venue"
},
  "geometry": {"coordinates":[2.9423949718,50.9353179932],"type":"Point"}
}