{
  "type": "Feature",
  "properties": {
    "addr:full":"Nederstraat 29 Oudenaarde Oost-Vlaanderen 9700",
    "addr:housenumber":"29",
    "addr:postcode":"9700",
    "addr:street":"Nederstraat",
    "iso:country":"BE",
    "sg:address":"Nederstraat 29",
    "sg:city":"Oudenaarde",
    "sg:orig_category":"Pharmaciens",
    "sg:phone":"+32 55 31 69 34",
    "sg:postcode":"9700",
    "sg:province":"Oost-Vlaanderen",
    "wof:name":"Myriam Gykiere",
    "wof:placetype":"venue"
},
  "geometry": {"coordinates":[3.6034669876,50.844783783],"type":"Point"}
}