{
  "type": "Feature",
  "properties": {
    "iso:country":"BE",
    "sg:address":"Place L\u00c9opold 15",
    "sg:city":"Mons",
    "sg:classifiers":[
        {
            "category":"Restaurant",
            "type":"Food & Drink"
        }
    ],
    "sg:phone":"+32 65 84 09 76",
    "sg:postcode":"7000",
    "sg:province":"Hainaut",
    "wof:name":"Le Belvedere",
    "wof:placetype":"venue"
},
  "geometry": {"coordinates":[3.9431838989,50.4530754089],"type":"Point"}
}