{
  "type": "Feature",
  "properties": {
    "addr:full":"Ijzerstraat 4 Beerse Antwerpen 2340",
    "addr:housenumber":"4",
    "addr:postcode":"2340",
    "addr:street":"Ijzerstraat",
    "iso:country":"BE",
    "sg:address":"Ijzerstraat 4",
    "sg:city":"Beerse",
    "sg:orig_category":"Dansscholen",
    "sg:phone":"+32 14 61 19 37",
    "sg:postcode":"2340",
    "sg:province":"Antwerpen",
    "wof:name":"Dansliga Sportfederatie",
    "wof:placetype":"venue"
},
  "geometry": {"coordinates":[4.8574051857,51.3206558228],"type":"Point"}
}