{
  "type": "Feature",
  "properties": {
    "iso:country":"BE",
    "sg:address":"Winterslagstraat 51-53",
    "sg:city":"Genk",
    "sg:classifiers":[
        {
            "category":"Restaurant",
            "type":"Food & Drink"
        }
    ],
    "sg:phone":"+32 89 35 16 91",
    "sg:postcode":"3600",
    "sg:province":"Limburg",
    "wof:name":"Oud Genck",
    "wof:placetype":"venue"
},
  "geometry": {"coordinates":[5.4987211227,50.9659156799],"type":"Point"}
}