{
  "type": "Feature",
  "properties": {
    "addr:full":"Canada Ln 73 Nieuwpoort West-Vlaanderen 8620",
    "addr:housenumber":"73",
    "addr:postcode":"8620",
    "addr:street":"Canada Ln",
    "iso:country":"BE",
    "sg:address":"Canada Ln 73",
    "sg:city":"Nieuwpoort",
    "sg:classifiers":[
        {
            "category":"Shopping",
            "type":"Retail Goods"
        }
    ],
    "sg:phone":"+32 58 23 41 01",
    "sg:postcode":"8620",
    "sg:province":"West-Vlaanderen",
    "sg:tags":[
        "metallurgy",
        "finished",
        "-",
        "metalworking",
        "metallic"
    ],
    "wof:name":"Litto Nv",
    "wof:placetype":"venue"
},
  "geometry": {"coordinates":[2.7507851124,51.1285133362],"type":"Point"}
}