{
  "type": "Feature",
  "properties": {
    "addr:full":"Tongersesteenweg 382 Borgloon Limburg 3840",
    "addr:housenumber":"382",
    "addr:postcode":"3840",
    "addr:street":"Tongersesteenweg",
    "iso:country":"BE",
    "sg:address":"Tongersesteenweg 382",
    "sg:city":"Borgloon",
    "sg:orig_category":"Artistes ind\u00e9pendants. Traitement and fa\u00e7onnage de la pierre",
    "sg:phone":"+32 12 74 43 64",
    "sg:postcode":"3840",
    "sg:province":"Limburg",
    "wof:name":"Karl Syben - Boes",
    "wof:placetype":"venue"
},
  "geometry": {"coordinates":[5.3611898422,50.798210144],"type":"Point"}
}