{
  "type": "Feature",
  "properties": {
    "addr:full":"Wijngaardstraat 2a Haaltert (kerksken) Oost-Vlaanderen 9451",
    "addr:housenumber":"2a",
    "addr:postcode":"9451",
    "addr:street":"Wijngaardstraat",
    "iso:country":"BE",
    "sg:address":"Wijngaardstraat 2a",
    "sg:city":"Haaltert (kerksken)",
    "sg:classifiers":[
        {
            "category":"Insurance",
            "subcategory":"Insurance Agent",
            "type":"Services"
        }
    ],
    "sg:phone":"+32 53 78 22 26",
    "sg:postcode":"9451",
    "sg:province":"Oost-Vlaanderen",
    "sg:tags":[
        "broker"
    ],
    "wof:name":"Assumar Zakenkantoor Nv",
    "wof:placetype":"venue"
},
  "geometry": {"coordinates":[3.9932549,50.8901939392],"type":"Point"}
}