{
  "type": "Feature",
  "properties": {
    "addr:full":"Rue Sainte-walburge 107 Li\u00c8ge Li\u00e8ge 4000",
    "addr:housenumber":"107",
    "addr:postcode":"4000",
    "addr:street":"Rue Sainte-Walburge",
    "iso:country":"BE",
    "sg:address":"Rue Sainte-walburge 107",
    "sg:city":"Li\u00c8ge",
    "sg:orig_category":"Pain, p\u00e2tisseries and confiseries",
    "sg:phone":"+32 4 226 04 99",
    "sg:postcode":"4000",
    "sg:province":"Li\u00e8ge",
    "wof:name":"Boulangerie Arnold",
    "wof:placetype":"venue"
},
  "geometry": {"coordinates":[5.5706419945,50.6564445496],"type":"Point"}
}