{
  "type": "Feature",
  "properties": {
    "addr:full":"5 Rue Camille Duray 7190 Ecaussinnes 5",
    "addr:housenumber":"5",
    "addr:postcode":"7190",
    "addr:street":"Rue Camille Duray",
    "iso:country":"BE",
    "sg:address":"5",
    "sg:city":"Rue Camille Duray 7190 Ecaussinnes",
    "sg:classifiers":[
        {
            "category":"Manufacturing",
            "subcategory":"Jewelry",
            "type":"Manufacturing & Wholesale Goods"
        }
    ],
    "sg:phone":"+32 67 44 30 83",
    "sg:postcode":"5",
    "sg:tags":[
        "product",
        "miscellaneous",
        "jewellery"
    ],
    "wof:name":"Chantier Godeau Sprl",
    "wof:placetype":"venue"
},
  "geometry": {"coordinates":[4.1611847878,50.5609664917],"type":"Point"}
}