{
  "type": "Feature",
  "properties": {
    "addr:full":"Rue Du Viernois 1 Chapelle-lez-herlaimont Hainaut 7160",
    "addr:housenumber":"1",
    "addr:postcode":"7160",
    "addr:street":"Rue Du Viernois",
    "iso:country":"BE",
    "sg:address":"Rue Du Viernois 1",
    "sg:city":"Chapelle-lez-herlaimont",
    "sg:orig_category":"Eleveurs de bovins",
    "sg:phone":"+32 71 52 31 95",
    "sg:postcode":"7160",
    "sg:province":"Hainaut",
    "wof:name":"Michel Demunck",
    "wof:placetype":"venue"
},
  "geometry": {"coordinates":[4.2810049057,50.4714736938],"type":"Point"}
}