{
  "type": "Feature",
  "properties": {
    "iso:country":"BE",
    "sg:address":"Elsensegalerij 31-32",
    "sg:city":"Bruxelles (ixelles)",
    "sg:classifiers":[
        {
            "category":"Shopping",
            "subcategory":"Clothing, Apparel, & Fashions",
            "type":"Retail Goods"
        }
    ],
    "sg:phone":"+32 2 512 80 32",
    "sg:postcode":"1050",
    "sg:province":"Bruxelles-Capitale",
    "sg:tags":[
        "boutique"
    ],
    "wof:name":"Essor (l')",
    "wof:placetype":"venue"
},
  "geometry": {"coordinates":[4.3622097969,50.8369483948],"type":"Point"}
}