{
  "type": "Feature",
  "properties": {
    "iso:country":"BE",
    "sg:address":"Gaverstraat 51",
    "sg:city":"Geraardsbergen",
    "sg:orig_category":"Dakwerken",
    "sg:phone":"+32 54 41 75 54",
    "sg:postcode":"9500",
    "sg:province":"Oost-Vlaanderen",
    "wof:name":"Foubert & Courbet",
    "wof:placetype":"venue"
},
  "geometry": {"coordinates":[3.872699976,50.7594985962],"type":"Point"}
}