{
  "type": "Feature",
  "properties": {
    "iso:country":"BE",
    "sg:address":"Rue Plein-vent 14",
    "sg:city":"Baelen",
    "sg:orig_category":"Toeristische diensten",
    "sg:phone":"+32 87 76 29 63",
    "sg:postcode":"4837",
    "sg:province":"Li\u00e8ge",
    "wof:name":"Syndicat D\u00b4initiative",
    "wof:placetype":"venue"
},
  "geometry": {"coordinates":[5.9707288742,50.6356697083],"type":"Point"}
}