{
  "type": "Feature",
  "properties": {
    "iso:country":"BE",
    "sg:address":"Mortierstraat 15",
    "sg:city":"Nevele (poesele)",
    "sg:classifiers":[
        {
            "category":"Building & Trades",
            "subcategory":"Landscaping Services",
            "type":"Services"
        }
    ],
    "sg:phone":"+32 9 371 54 71",
    "sg:postcode":"9850",
    "sg:province":"Oost-Vlaanderen",
    "sg:tags":[
        "gardening",
        "garden",
        "maintenance"
    ],
    "wof:name":"Van Wonterghem E",
    "wof:placetype":"venue"
},
  "geometry": {"coordinates":[3.5139501095,51.0311393738],"type":"Point"}
}