{
  "type": "Feature",
  "properties": {
    "iso:country":"BE",
    "sg:address":"Raerenstr 32",
    "sg:city":"Raeren",
    "sg:orig_category":"Beautyfarms, relaxatie and lichamelijk welzijn",
    "sg:phone":"+32 87 85 14 36",
    "sg:postcode":"4731",
    "sg:province":"Li\u00e8ge",
    "wof:name":"Oliver Bergmann",
    "wof:placetype":"venue"
},
  "geometry": {"coordinates":[6.0827941895,50.6918411255],"type":"Point"}
}