{
  "type": "Feature",
  "properties": {
    "iso:country":"BE",
    "sg:address":"Van Der Schuerenstraat 16",
    "sg:city":"Ninove",
    "sg:classifiers":[
        {
            "category":"Building & Trades",
            "subcategory":"Construction",
            "type":"Services"
        }
    ],
    "sg:phone":"+32 54 33 67 35",
    "sg:postcode":"9400",
    "sg:province":"Oost-Vlaanderen",
    "sg:tags":[
        "gr",
        "la",
        "de",
        "\u00e9quipement",
        "pour",
        "machine",
        "location",
        "mat\u00e9riaux"
    ],
    "wof:name":"Eeman",
    "wof:placetype":"venue"
},
  "geometry": {"coordinates":[3.9697670937,50.8478126526],"type":"Point"}
}