{
  "type": "Feature",
  "properties": {
    "addr:full":"Autolei 224 Wommelgem Antwerpen 2160",
    "addr:housenumber":"224",
    "addr:postcode":"2160",
    "iso:country":"BE",
    "sg:address":"Autolei 224",
    "sg:city":"Wommelgem",
    "sg:classifiers":[
        {
            "category":"Professional",
            "subcategory":"Management & Consulting",
            "type":"Services"
        }
    ],
    "sg:phone":"+32 3 322 76 00",
    "sg:postcode":"2160",
    "sg:province":"Antwerpen",
    "sg:tags":[
        "tax-consultants"
    ],
    "wof:name":"Van Gool P",
    "wof:placetype":"venue"
},
  "geometry": {"coordinates":[4.4903402328,51.2080612183],"type":"Point"}
}