{
  "type": "Feature",
  "properties": {
    "addr:full":"Rue Duvivier 26 Li\u00c8ge Li\u00e8ge 4000",
    "addr:housenumber":"26",
    "addr:postcode":"4000",
    "addr:street":"Rue Duvivier",
    "iso:country":"BE",
    "sg:address":"Rue Duvivier 26",
    "sg:city":"Li\u00c8ge",
    "sg:orig_category":"Advocaten and juridische adviseurs",
    "sg:phone":"+32 4 223 70 47",
    "sg:postcode":"4000",
    "sg:province":"Li\u00e8ge",
    "wof:name":"V. Hissel",
    "wof:placetype":"venue"
},
  "geometry": {"coordinates":[5.5606360435,50.6359443665],"type":"Point"}
}