{
  "type": "Feature",
  "properties": {
    "addr:full":"Place Galil\u00e9e 2 Ottignies-louvain-la-neuve (louvain-la-neuve) Brabant Wallon 1348",
    "addr:housenumber":"2",
    "addr:postcode":"1348",
    "addr:street":"Place Galile\u0301E",
    "iso:country":"BE",
    "sg:address":"Place Galil\u00e9e 2",
    "sg:city":"Ottignies-louvain-la-neuve (louvain-la-neuve)",
    "sg:classifiers":[
        {
            "category":"Organizations",
            "subcategory":"Community Association",
            "type":"Services"
        }
    ],
    "sg:phone":"+32 10 45 33 51",
    "sg:postcode":"1348",
    "sg:province":"Brabant Wallon",
    "sg:tags":[
        "cultural"
    ],
    "wof:name":"Carolo (le) Asbl",
    "wof:placetype":"venue"
},
  "geometry": {"coordinates":[4.6187300682,50.6677017212],"type":"Point"}
}