{
  "type": "Feature",
  "properties": {
    "iso:country":"BE",
    "sg:address":"Merghelynckstraat 1",
    "sg:city":"Ieper",
    "sg:orig_category":"Vertalers and tolken",
    "sg:phone":"+32 57 20 71 97",
    "sg:postcode":"8900",
    "sg:province":"West-Vlaanderen",
    "wof:name":"Cavallier F. Cbtip/bkvtf",
    "wof:placetype":"venue"
},
  "geometry": {"coordinates":[2.8872900009,50.8490180969],"type":"Point"}
}