{
  "type": "Feature",
  "properties": {
    "addr:full":"Elsstraat 7 Gent Oost-Vlaanderen 9000",
    "addr:housenumber":"7",
    "addr:postcode":"9000",
    "addr:street":"Elsstraat;Oost-Vlaanderen",
    "iso:country":"BE",
    "sg:address":"Elsstraat 7",
    "sg:city":"Gent",
    "sg:orig_category":"Art and fournitures artistiques",
    "sg:phone":"+32 9 233 08 16",
    "sg:postcode":"9000",
    "sg:province":"Oost-Vlaanderen",
    "wof:name":"Marc Van Heesvelde",
    "wof:placetype":"venue"
},
  "geometry": {"coordinates":[3.7127010822,51.0638961792],"type":"Point"}
}