{
  "type": "Feature",
  "properties": {
    "iso:country":"BE",
    "sg:address":"Drieslaan 29",
    "sg:city":"Wevelgem (gullegem)",
    "sg:classifiers":[
        {
            "category":"Manufacturing",
            "subcategory":"Metals",
            "type":"Manufacturing & Wholesale Goods"
        }
    ],
    "sg:phone":"+32 56 41 29 42",
    "sg:postcode":"8560",
    "sg:province":"West-Vlaanderen",
    "sg:tags":[
        "alloy",
        "aluminium"
    ],
    "wof:name":"Boal Aluminium Extrusions",
    "wof:placetype":"venue"
},
  "geometry": {"coordinates":[3.1884129047,50.84923172],"type":"Point"}
}