{
  "type": "Feature",
  "properties": {
    "addr:full":"Rue Grande 12 Quievrain Hainaut 7380",
    "addr:housenumber":"12",
    "addr:postcode":"7380",
    "addr:street":"Rue Grande;Hainaut",
    "iso:country":"BE",
    "sg:address":"Rue Grande 12",
    "sg:city":"Quievrain",
    "sg:orig_category":"Fleurs and plantes",
    "sg:phone":"+32 65 45 76 28",
    "sg:postcode":"7380",
    "sg:province":"Hainaut",
    "wof:name":"La Charette Fleurie",
    "wof:placetype":"venue"
},
  "geometry": {"coordinates":[3.6825211048,50.4072685242],"type":"Point"}
}