{
  "type": "Feature",
  "properties": {
    "addr:full":"Hollandstraat 155b Heist-op-den-berg Antwerpen 2220",
    "addr:housenumber":"155b",
    "addr:postcode":"2220",
    "addr:street":"Hollandstraat",
    "iso:country":"BE",
    "sg:address":"Hollandstraat 155b",
    "sg:city":"Heist-op-den-berg",
    "sg:classifiers":[
        {
            "category":"Personal",
            "subcategory":"Beauty Salon",
            "type":"Services"
        }
    ],
    "sg:phone":"+32 15 76 01 83",
    "sg:postcode":"2220",
    "sg:province":"Antwerpen",
    "wof:name":"Herleen",
    "wof:placetype":"venue"
},
  "geometry": {"coordinates":[4.7096500397,51.046169281],"type":"Point"}
}