{
  "type": "Feature",
  "properties": {
    "addr:full":"Chauss\u00e9e De Wavre 270 Grez-doiceau Brabant Wallon 1390",
    "addr:housenumber":"270",
    "addr:postcode":"1390",
    "addr:street":"Chausse\u0301E De Wavre",
    "iso:country":"BE",
    "sg:address":"Chauss\u00e9e De Wavre 270",
    "sg:city":"Grez-doiceau",
    "sg:classifiers":[
        {
            "category":"Professional",
            "subcategory":"Accounting & Tax Preparation",
            "type":"Services"
        }
    ],
    "sg:phone":"+32 10 84 59 33",
    "sg:postcode":"1390",
    "sg:province":"Brabant Wallon",
    "sg:tags":[
        "bookkeeper"
    ],
    "wof:name":"Streuve Ph",
    "wof:placetype":"venue"
},
  "geometry": {"coordinates":[4.6626000404,50.7380981445],"type":"Point"}
}