{
  "type": "Feature",
  "properties": {
    "addr:full":"Rue De La Baronne 54 Seneffe (feluy) Hainaut 7181",
    "addr:housenumber":"54",
    "addr:postcode":"7181",
    "addr:street":"Rue De La Baronne",
    "iso:country":"BE",
    "sg:address":"Rue De La Baronne 54",
    "sg:city":"Seneffe (feluy)",
    "sg:classifiers":[
        {
            "category":"Manufacturing",
            "subcategory":"Tools & Machinery",
            "type":"Manufacturing & Wholesale Goods"
        }
    ],
    "sg:phone":"+32 67 87 81 59",
    "sg:postcode":"7181",
    "sg:province":"Hainaut",
    "sg:tags":[
        "builder"
    ],
    "wof:name":"Moriau R",
    "wof:placetype":"venue"
},
  "geometry": {"coordinates":[4.2671971321,50.5649108887],"type":"Point"}
}