{
  "type": "Feature",
  "properties": {
    "addr:full":"Barelstraat 17 Aalter Oost-Vlaanderen 9880",
    "addr:housenumber":"17",
    "addr:postcode":"9880",
    "addr:street":"Barelstraat",
    "iso:country":"BE",
    "sg:address":"Barelstraat 17",
    "sg:city":"Aalter",
    "sg:orig_category":"Eleveurs and marchands de porcs. Eleveurs de bovins",
    "sg:phone":"+32 51 68 83 44",
    "sg:postcode":"9880",
    "sg:province":"Oost-Vlaanderen",
    "wof:name":"Marcel Vervenne",
    "wof:placetype":"venue"
},
  "geometry": {"coordinates":[3.4365959167,51.0560302734],"type":"Point"}
}