{
  "type": "Feature",
  "properties": {
    "addr:full":"Rue De L'eglise 84 Raeren/raeren Li\u00e8ge 4730",
    "addr:housenumber":"84",
    "addr:postcode":"4730",
    "addr:street":"Rue De L'Eglise",
    "iso:country":"BE",
    "sg:address":"Rue De L'eglise 84",
    "sg:city":"Raeren/raeren",
    "sg:orig_category":"M\u00e9decins and sp\u00e9cialistes",
    "sg:phone":"+32 87 65 78 78",
    "sg:postcode":"4730",
    "sg:province":"Li\u00e8ge",
    "wof:name":"Ch. Schirdewahn/christa Schirdewahn",
    "wof:placetype":"venue"
},
  "geometry": {"coordinates":[6.1511101723,50.650188446],"type":"Point"}
}