{
  "type": "Feature",
  "properties": {
    "addr:full":"Bree\u00ebrsteenweg 262 Kinrooi Limburg 3640",
    "addr:housenumber":"262",
    "addr:postcode":"3640",
    "addr:street":"Breee\u0308Rsteenweg",
    "iso:country":"BE",
    "sg:address":"Bree\u00ebrsteenweg 262",
    "sg:city":"Kinrooi",
    "sg:classifiers":[
        {
            "category":"Cafe",
            "type":"Food & Drink"
        }
    ],
    "sg:phone":"+32 89 70 24 15",
    "sg:postcode":"3640",
    "sg:province":"Limburg",
    "sg:tags":[
        "snack-bars"
    ],
    "wof:name":"De Limburger",
    "wof:placetype":"venue"
},
  "geometry": {"coordinates":[5.7433190346,51.1459236145],"type":"Point"}
}