{
  "type": "Feature",
  "properties": {
    "addr:full":"Molenstraat 37 Neerpelt Limburg 3910",
    "addr:housenumber":"37",
    "addr:postcode":"3910",
    "addr:street":"Molenstraat",
    "iso:country":"BE",
    "sg:address":"Molenstraat 37",
    "sg:city":"Neerpelt",
    "sg:orig_category":"Dierenartsen",
    "sg:phone":"+32 11 64 39 27",
    "sg:postcode":"3910",
    "sg:province":"Limburg",
    "wof:name":"Eric Hannes",
    "wof:placetype":"venue"
},
  "geometry": {"coordinates":[5.4448599815,51.2289009094],"type":"Point"}
}