{
  "type": "Feature",
  "properties": {
    "iso:country":"BE",
    "sg:address":"Stationsstraat 74",
    "sg:city":"Halen",
    "sg:orig_category":"Apotheken",
    "sg:phone":"+32 13 44 17 36",
    "sg:postcode":"3545",
    "sg:province":"Limburg",
    "wof:name":"Luc Neven",
    "wof:placetype":"venue"
},
  "geometry": {"coordinates":[5.1180582047,50.9768981934],"type":"Point"}
}