{
  "type": "Feature",
  "properties": {
    "iso:country":"BE",
    "sg:address":"Ninoofsesteenweg 383",
    "sg:city":"Dilbeek",
    "sg:orig_category":"Supermarkten",
    "sg:postcode":"1700",
    "sg:province":"Vlaams-Brabant",
    "wof:name":"Aldi",
    "wof:placetype":"venue"
},
  "geometry": {"coordinates":[4.2574319839,50.8432197571],"type":"Point"}
}