{
  "type": "Feature",
  "properties": {
    "iso:country":"BE",
    "sg:address":"Rue Basse Bourlotte 2",
    "sg:city":"Silly",
    "sg:orig_category":"Rundveehouders",
    "sg:phone":"+32 2 395 80 51",
    "sg:postcode":"7830",
    "sg:province":"Hainaut",
    "wof:name":"Luc Dewaele",
    "wof:placetype":"venue"
},
  "geometry": {"coordinates":[4.059887886,50.6636390686],"type":"Point"}
}