{
  "type": "Feature",
  "properties": {
    "iso:country":"BE",
    "sg:address":"Sentier De L'escouffiaux 76",
    "sg:city":"Boussu",
    "sg:orig_category":"Postkantoren Verzekeringsmakelaars and experts",
    "sg:phone":"+32 65 65 47 69",
    "sg:postcode":"7301",
    "sg:province":"Hainaut",
    "wof:name":"La Poste",
    "wof:placetype":"venue"
},
  "geometry": {"coordinates":[3.8101689816,50.4013061523],"type":"Point"}
}