{
  "type": "Feature",
  "properties": {
    "iso:country":"BE",
    "sg:address":"Rue Louis Snyers 14a",
    "sg:city":"Hannut",
    "sg:classifiers":[
        {
            "category":"Health Services",
            "subcategory":"Dentist",
            "type":"Services"
        }
    ],
    "sg:phone":"+32 19 51 17 28",
    "sg:postcode":"4280",
    "sg:province":"Li\u00e8ge",
    "wof:name":"Op De Beeck Marc",
    "wof:placetype":"venue"
},
  "geometry": {"coordinates":[5.0849471092,50.6695632935],"type":"Point"}
}