{
  "type": "Feature",
  "properties": {
    "addr:full":"Rue Champ Rodange 72 Waterloo Brabant Wallon 1410",
    "addr:housenumber":"72",
    "addr:postcode":"1410",
    "addr:street":"Rue Champ Rodange",
    "iso:country":"BE",
    "sg:address":"Rue Champ Rodange 72",
    "sg:city":"Waterloo",
    "sg:orig_category":"Studios photographiques",
    "sg:phone":"+32 2 354 12 32",
    "sg:postcode":"1410",
    "sg:province":"Brabant Wallon",
    "wof:name":"P.c.m. Studio",
    "wof:placetype":"venue"
},
  "geometry": {"coordinates":[4.3682589531,50.7117652893],"type":"Point"}
}