{
  "type": "Feature",
  "properties": {
    "addr:full":"Avenue Reine Astrid 22 Namur Namur 5000",
    "addr:housenumber":"22",
    "addr:postcode":"5000",
    "addr:street":"Avenue Reine Astrid",
    "iso:country":"BE",
    "sg:address":"Avenue Reine Astrid 22",
    "sg:city":"Namur",
    "sg:classifiers":[
        {
            "category":"Organizations",
            "subcategory":"Community Association",
            "type":"Services"
        }
    ],
    "sg:phone":"+32 81 73 11 16",
    "sg:postcode":"5000",
    "sg:province":"Namur",
    "sg:tags":[
        "environment",
        "organisation",
        "-"
    ],
    "wof:name":"Fondation Gouverneur Ren\u00e9 Close Asbl",
    "wof:placetype":"venue"
},
  "geometry": {"coordinates":[4.8563699722,50.4621162415],"type":"Point"}
}