{
  "type": "Feature",
  "properties": {
    "iso:country":"BE",
    "sg:address":"Rue Brunehaut 57",
    "sg:city":"Mons",
    "sg:classifiers":[
        {
            "category":"Cafe",
            "type":"Food & Drink"
        }
    ],
    "sg:phone":"+32 65 35 25 63",
    "sg:postcode":"7022",
    "sg:province":"Hainaut",
    "sg:tags":[
        "caf\u00e9s"
    ],
    "wof:name":"Georgine Nicodeme",
    "wof:placetype":"venue"
},
  "geometry": {"coordinates":[3.958865881,50.4261932373],"type":"Point"}
}