{
  "type": "Feature",
  "properties": {
    "addr:full":"Arendsstraat 110 Harelbeke West-Vlaanderen 8530",
    "addr:housenumber":"110",
    "addr:postcode":"8530",
    "addr:street":"Arendsstraat",
    "iso:country":"BE",
    "sg:address":"Arendsstraat 110",
    "sg:city":"Harelbeke",
    "sg:classifiers":[
        {
            "category":"Home & Garden",
            "subcategory":"Home Furnishings",
            "type":"Retail Goods"
        }
    ],
    "sg:phone":"+32 56 71 11 45",
    "sg:postcode":"8530",
    "sg:province":"West-Vlaanderen",
    "sg:tags":[
        "interior",
        "decoration"
    ],
    "wof:name":"De Cocon",
    "wof:placetype":"venue"
},
  "geometry": {"coordinates":[3.3232400417,50.8531074524],"type":"Point"}
}