{
  "type": "Feature",
  "properties": {
    "iso:country":"BE",
    "sg:address":"Bergstraat 39",
    "sg:city":"Grobbendonk",
    "sg:classifiers":[
        {
            "category":"Retail",
            "subcategory":"Veterinary Services",
            "type":"Services"
        }
    ],
    "sg:phone":"+32 14 51 57 09",
    "sg:postcode":"2280",
    "sg:province":"Antwerpen",
    "sg:tags":[
        "veterinarian"
    ],
    "wof:name":"Vrints W",
    "wof:placetype":"venue"
},
  "geometry": {"coordinates":[4.7375221252,51.1926956177],"type":"Point"}
}