{
  "type": "Feature",
  "properties": {
    "addr:full":"Rue Du Septi\u00c8me Wing 2 Chievres Hainaut 7950",
    "addr:housenumber":"2",
    "addr:postcode":"7950",
    "addr:street":"Rue Du Septie\u0300Me Wing;Hainaut",
    "iso:country":"BE",
    "sg:address":"Rue Du Septi\u00c8me Wing 2",
    "sg:city":"Chievres",
    "sg:orig_category":"Supermarch\u00e9s",
    "sg:phone":"+32 68 65 75 74",
    "sg:postcode":"7950",
    "sg:province":"Hainaut",
    "wof:name":"Battard",
    "wof:placetype":"venue"
},
  "geometry": {"coordinates":[3.8170239925,50.5886116028],"type":"Point"}
}