{
  "type": "Feature",
  "properties": {
    "iso:country":"BE",
    "sg:address":"Rue Camille Lemonnier 30",
    "sg:city":"Moeskroen/mouscron",
    "sg:orig_category":"Rev\u00eatements pour sols and murs. Magasins sp\u00e9cialis\u00e9s",
    "sg:phone":"+32 56 33 52 64",
    "sg:postcode":"7700",
    "sg:province":"Hainaut",
    "wof:name":"Germain Hayart",
    "wof:placetype":"venue"
},
  "geometry": {"coordinates":[3.2323200703,50.7400932312],"type":"Point"}
}