{
  "type": "Feature",
  "properties": {
    "addr:full":"Kerkstraat 18 Diest (schaffen) Vlaams-Brabant 3290",
    "addr:housenumber":"18",
    "addr:postcode":"3290",
    "addr:street":"Kerkstraat",
    "iso:country":"BE",
    "sg:address":"Kerkstraat 18",
    "sg:city":"Diest (schaffen)",
    "sg:classifiers":[
        {
            "category":"Bars & Pubs",
            "type":"Food & Drink"
        }
    ],
    "sg:phone":"+32 13 33 32 40",
    "sg:postcode":"3290",
    "sg:province":"Vlaams-Brabant",
    "sg:tags":[
        "tavern"
    ],
    "wof:name":"Gasthof 1618",
    "wof:placetype":"venue"
},
  "geometry": {"coordinates":[5.0812277794,51.0014610291],"type":"Point"}
}