{
  "type": "Feature",
  "properties": {
    "addr:full":"Rue J.mullie 35 Mouscron Hainaut 7711",
    "addr:housenumber":"35",
    "addr:postcode":"7711",
    "addr:street":"Rue J.Mullie",
    "iso:country":"BE",
    "sg:address":"Rue J.mullie 35",
    "sg:city":"Mouscron",
    "sg:orig_category":"Openbare bibliotheken and archieven",
    "sg:phone":"+32 56 48 98 92",
    "sg:postcode":"7711",
    "sg:province":"Hainaut",
    "wof:name":"Biblioth\u00c8que Publique",
    "wof:placetype":"venue"
},
  "geometry": {"coordinates":[3.3080399036,50.7282752991],"type":"Point"}
}