{
  "type": "Feature",
  "properties": {
    "addr:full":"Tolpoortstraat 35 Deinze (groot) Oost-Vlaanderen 9800",
    "addr:housenumber":"35",
    "addr:postcode":"9800",
    "addr:street":"Tolpoortstraat;Groot Oost-Vlaanderen",
    "iso:country":"BE",
    "sg:address":"Tolpoortstraat 35",
    "sg:city":"Deinze (groot)",
    "sg:orig_category":"V\u00eatements pour Dames. V\u00eatements pour Hommes. V\u00eatements pour b\u00e9b\u00e9s and enfants",
    "sg:phone":"+32 9 380 14 15",
    "sg:postcode":"9800",
    "sg:province":"Oost-Vlaanderen",
    "wof:name":"Benetton",
    "wof:placetype":"venue"
},
  "geometry": {"coordinates":[3.5291509628,50.9814376831],"type":"Point"}
}