{
  "type": "Feature",
  "properties": {
    "iso:country":"BE",
    "sg:address":"Stationsstraat 2",
    "sg:city":"Nevele",
    "sg:orig_category":"Producteurs de fruits",
    "sg:phone":"+32 9 371 78 76",
    "sg:postcode":"9850",
    "sg:province":"Oost-Vlaanderen",
    "wof:name":"Etienne Willems",
    "wof:placetype":"venue"
},
  "geometry": {"coordinates":[3.5737299919,51.0577011108],"type":"Point"}
}