{
  "type": "Feature",
  "properties": {
    "addr:full":"Rue Du Labyrinthe 252 Mouscron Hainaut 7700",
    "addr:housenumber":"252",
    "addr:postcode":"7700",
    "addr:street":"Rue Du Labyrinthe",
    "iso:country":"BE",
    "sg:address":"Rue Du Labyrinthe 252",
    "sg:city":"Mouscron",
    "sg:classifiers":[
        {
            "category":"Personal",
            "subcategory":"Beauty Salon",
            "type":"Services"
        }
    ],
    "sg:phone":"+32 56 54 59 84",
    "sg:postcode":"7700",
    "sg:province":"Hainaut",
    "sg:tags":[
        "lady",
        "-",
        "hairdressing"
    ],
    "wof:name":"M.s. Coiffure",
    "wof:placetype":"venue"
},
  "geometry": {"coordinates":[3.188726902,50.743560791],"type":"Point"}
}