{
  "type": "Feature",
  "properties": {
    "iso:country":"BE",
    "sg:address":"Chauss\u00e9e De Charleroi 19",
    "sg:city":"Gembloux-sur-orneau (gembloux)",
    "sg:orig_category":"Non-Classified Establishments",
    "sg:phone":"+32 81 61 49 68",
    "sg:postcode":"5030",
    "sg:province":"Namur",
    "wof:name":"Thielens J.p.",
    "wof:placetype":"venue"
},
  "geometry": {"coordinates":[4.6916999817,50.5675544739],"type":"Point"}
}