{
  "type": "Feature",
  "properties": {
    "iso:country":"BE",
    "sg:address":"Hoogstraat 13",
    "sg:city":"Nieuwpoort",
    "sg:orig_category":"Epiceries",
    "sg:phone":"+32 58 23 09 04",
    "sg:postcode":"8620",
    "sg:province":"West-Vlaanderen",
    "wof:name":"Huis Kolibrie",
    "wof:placetype":"venue"
},
  "geometry": {"coordinates":[2.7496640682,51.1317558289],"type":"Point"}
}