{
  "type": "Feature",
  "properties": {
    "addr:full":"Maaltekouter 1 Gent (sint-denijs-westrem - Afsnee) Oost-Vlaanderen 9051",
    "addr:housenumber":"1",
    "addr:postcode":"9051",
    "addr:street":"Maaltekouter;Oost-Vlaanderen",
    "iso:country":"BE",
    "sg:address":"Maaltekouter 1",
    "sg:city":"Gent (sint-denijs-westrem - Afsnee)",
    "sg:orig_category":"Fairs, shows, exhibitions",
    "sg:phone":"+32 9 241 92 11",
    "sg:postcode":"9051",
    "sg:province":"Oost-Vlaanderen",
    "wof:name":"Flanders Expo Nv",
    "wof:placetype":"venue"
},
  "geometry": {"coordinates":[3.690048933,51.0246810913],"type":"Point"}
}