{
  "type": "Feature",
  "properties": {
    "iso:country":"BE",
    "sg:address":"Chauss\u00c9e De Tournai 196",
    "sg:city":"Ath",
    "sg:orig_category":"Articles non-alimentaires",
    "sg:phone":"+32 68 26 98 00",
    "sg:postcode":"7800",
    "sg:province":"Hainaut",
    "wof:name":"Stock Am\u00c9ricain",
    "wof:placetype":"venue"
},
  "geometry": {"coordinates":[3.756953001,50.6310577393],"type":"Point"}
}