{
  "type": "Feature",
  "properties": {
    "iso:country":"BE",
    "sg:address":"Corbautstraat 1",
    "sg:city":"Sint-niklaas",
    "sg:classifiers":[
        {
            "category":"Arena",
            "subcategory":"Sports Club",
            "type":"Entertainment"
        }
    ],
    "sg:phone":"+32 3 772 56 50",
    "sg:postcode":"9111",
    "sg:province":"Oost-Vlaanderen",
    "sg:tags":[
        "de"
    ],
    "wof:name":"T.c. De Houtmuis",
    "wof:placetype":"venue"
},
  "geometry": {"coordinates":[4.0917329788,51.1402015686],"type":"Point"}
}