{
  "type": "Feature",
  "properties": {
    "addr:full":"Route De La P\u00e9lette 9 Bertrix (orgeo) Luxembourg 6880",
    "addr:housenumber":"9",
    "addr:postcode":"6880",
    "addr:street":"Route De La Pe\u0301Lette",
    "iso:country":"BE",
    "sg:address":"Route De La P\u00e9lette 9",
    "sg:city":"Bertrix (orgeo)",
    "sg:classifiers":[
        {
            "category":"Manufacturing",
            "subcategory":"Paper Products",
            "type":"Manufacturing & Wholesale Goods"
        }
    ],
    "sg:phone":"+32 61 61 31 76",
    "sg:postcode":"6880",
    "sg:province":"Luxembourg",
    "sg:tags":[
        "bookbinding"
    ],
    "wof:name":"Atelier De Reliure Van Mol V",
    "wof:placetype":"venue"
},
  "geometry": {"coordinates":[5.2535948753,49.8544845581],"type":"Point"}
}