{
  "type": "Feature",
  "properties": {
    "addr:full":"Rekkemsestraat 109 Kortrijk West-Vlaanderen 8510",
    "addr:housenumber":"109",
    "addr:postcode":"8510",
    "addr:street":"Rekkemsestraat",
    "iso:country":"BE",
    "sg:address":"Rekkemsestraat 109",
    "sg:city":"Kortrijk",
    "sg:orig_category":"Installation de menuiserie en bois and plastique. Installation de menuiserie m\u00e9tallique. Constructio",
    "sg:phone":"+32 56 21 88 55",
    "sg:postcode":"8510",
    "sg:province":"West-Vlaanderen",
    "wof:name":"Veranda's Clochet",
    "wof:placetype":"venue"
},
  "geometry": {"coordinates":[3.2291340828,50.808631897],"type":"Point"}
}