{
  "type": "Feature",
  "properties": {
    "addr:full":"Rupelmondestraat 31 Kruibeke (bazel) Oost-Vlaanderen 9150",
    "addr:housenumber":"31",
    "addr:postcode":"9150",
    "addr:street":"Rupelmondestraat",
    "iso:country":"BE",
    "sg:address":"Rupelmondestraat 31",
    "sg:city":"Kruibeke (bazel)",
    "sg:classifiers":[
        {
            "category":"Shopping",
            "subcategory":"Bicycles & Sporting Goods",
            "type":"Retail Goods"
        }
    ],
    "sg:phone":"+32 3 774 10 56",
    "sg:postcode":"9150",
    "sg:province":"Oost-Vlaanderen",
    "sg:tags":[
        "-"
    ],
    "wof:name":"Van Den Bosch-daelman",
    "wof:placetype":"venue"
},
  "geometry": {"coordinates":[4.29773283,51.1463851929],"type":"Point"}
}