{
  "type": "Feature",
  "properties": {
    "addr:full":"Vieux Chemin D'ere 9 Tournai Hainaut 7500",
    "addr:housenumber":"9",
    "addr:postcode":"7500",
    "addr:street":"Vieux Chemin D'Ere",
    "iso:country":"BE",
    "sg:address":"Vieux Chemin D'ere 9",
    "sg:city":"Tournai",
    "sg:orig_category":"Artsen and specialisten",
    "sg:phone":"+32 69 22 60 93",
    "sg:postcode":"7500",
    "sg:province":"Hainaut",
    "wof:name":"Alex Forro",
    "wof:placetype":"venue"
},
  "geometry": {"coordinates":[3.3841369152,50.5961036682],"type":"Point"}
}