{
  "type": "Feature",
  "properties": {
    "addr:full":"Ossogne 28 Thuin (thuillies) Hainaut 6536",
    "addr:housenumber":"28",
    "addr:postcode":"6536",
    "addr:street":"Ossogne",
    "iso:country":"BE",
    "sg:address":"Ossogne 28",
    "sg:city":"Thuin (thuillies)",
    "sg:classifiers":[
        {
            "category":"Retail",
            "subcategory":"Animal Services",
            "type":"Services"
        }
    ],
    "sg:phone":"+32 495 25 94 12",
    "sg:postcode":"6536",
    "sg:province":"Hainaut",
    "sg:tags":[
        "farrier"
    ],
    "wof:name":"Blommaert J-p",
    "wof:placetype":"venue"
},
  "geometry": {"coordinates":[4.3438329697,50.2889556885],"type":"Point"}
}