{
  "type": "Feature",
  "properties": {
    "addr:full":"Stationsstraat 103 Damme West-Vlaanderen 8340",
    "addr:housenumber":"103",
    "addr:postcode":"8340",
    "addr:street":"Stationsstraat",
    "iso:country":"BE",
    "sg:address":"Stationsstraat 103",
    "sg:city":"Damme",
    "sg:orig_category":"Pain, p\u00e2tisseries and confiseries",
    "sg:phone":"+32 50 36 09 35",
    "sg:postcode":"8340",
    "sg:province":"West-Vlaanderen",
    "wof:name":"Frank Cornille",
    "wof:placetype":"venue"
},
  "geometry": {"coordinates":[3.3163199425,51.2099266052],"type":"Point"}
}