{
  "type": "Feature",
  "properties": {
    "addr:full":"Rue Des Tilleuls 31 Kelmis/la Calamine Li\u00e8ge 4720",
    "addr:housenumber":"31",
    "addr:postcode":"4720",
    "addr:street":"Rue Des Tilleuls",
    "iso:country":"BE",
    "sg:address":"Rue Des Tilleuls 31",
    "sg:city":"Kelmis/la Calamine",
    "sg:orig_category":"Plomberie, chauffage and installations sanitaires",
    "sg:phone":"+32 87 65 95 95",
    "sg:postcode":"4720",
    "sg:province":"Li\u00e8ge",
    "wof:name":"Remy Nyssen",
    "wof:placetype":"venue"
},
  "geometry": {"coordinates":[6.0111298561,50.7128143311],"type":"Point"}
}