{
  "type": "Feature",
  "properties": {
    "iso:country":"BE",
    "sg:address":"Rue Sainte-catherine 4",
    "sg:city":"Lasne",
    "sg:orig_category":"Jardinage",
    "sg:phone":"+32 2 633 38 83",
    "sg:postcode":"1380",
    "sg:province":"Brabant Wallon",
    "wof:name":"Fe. Ewbank",
    "wof:placetype":"venue"
},
  "geometry": {"coordinates":[4.4286627769,50.660282135],"type":"Point"}
}