{
  "type": "Feature",
  "properties": {
    "addr:full":"Brouwersvliet 44 Antwerpen Antwerpen 2000",
    "addr:housenumber":"44",
    "addr:postcode":"2000",
    "addr:street":"Brouwersvliet",
    "iso:country":"BE",
    "sg:address":"Brouwersvliet 44",
    "sg:city":"Antwerpen",
    "sg:classifiers":[
        {
            "category":"Banks & Credit Unions",
            "subcategory":"Financial Services",
            "type":"Services"
        }
    ],
    "sg:phone":"+32 3 233 55 44",
    "sg:postcode":"2000",
    "sg:province":"Antwerpen",
    "sg:tags":[
        "financier"
    ],
    "wof:name":"Bm Universal Investments",
    "wof:placetype":"venue"
},
  "geometry": {"coordinates":[4.4049119949,51.2267341614],"type":"Point"}
}