{
  "type": "Feature",
  "properties": {
    "addr:full":"Centre Commercial Du Bultia 7 Gerpinnes Hainaut 6280",
    "addr:housenumber":"7",
    "addr:postcode":"6280",
    "addr:street":"Hainaut",
    "iso:country":"BE",
    "sg:address":"Centre Commercial Du Bultia 7",
    "sg:city":"Gerpinnes",
    "sg:classifiers":[
        {
            "category":"Shopping",
            "subcategory":"Gifts & Souvenirs",
            "type":"Retail Goods"
        }
    ],
    "sg:phone":"+32 71 21 67 93",
    "sg:postcode":"6280",
    "sg:province":"Hainaut",
    "sg:tags":[
        "-"
    ],
    "wof:name":"C\u00e2lin-c\u00e2line",
    "wof:placetype":"venue"
},
  "geometry": {"coordinates":[4.4873261452,50.3421173096],"type":"Point"}
}