{
  "type": "Feature",
  "properties": {
    "iso:country":"BE",
    "sg:address":"Begijnhof 26",
    "sg:city":"Arendonk",
    "sg:orig_category":"Artsen and specialisten",
    "sg:phone":"+32 14 67 11 12",
    "sg:postcode":"2370",
    "sg:province":"Antwerpen",
    "wof:name":"P. Franken",
    "wof:placetype":"venue"
},
  "geometry": {"coordinates":[5.0914587975,51.3241348267],"type":"Point"}
}