{
  "type": "Feature",
  "properties": {
    "iso:country":"BE",
    "sg:address":"Tumulusstraat 35",
    "sg:city":"Sint-truiden",
    "sg:orig_category":"P\u00e9pini\u00e9ristes. Jardinage",
    "sg:phone":"+32 11 68 00 23",
    "sg:postcode":"3800",
    "sg:province":"Limburg",
    "wof:name":"Swerts",
    "wof:placetype":"venue"
},
  "geometry": {"coordinates":[5.1863641739,50.8153343201],"type":"Point"}
}