{
  "type": "Feature",
  "properties": {
    "addr:full":"Denderstraat 11 Aalst Oost-Vlaanderen 9320",
    "addr:housenumber":"11",
    "addr:postcode":"9320",
    "addr:street":"Denderstraat",
    "iso:country":"BE",
    "sg:address":"Denderstraat 11",
    "sg:city":"Aalst",
    "sg:classifiers":[
        {
            "category":"Arena",
            "subcategory":"Sports Club",
            "type":"Entertainment"
        }
    ],
    "sg:phone":"+32 53 70 22 91",
    "sg:postcode":"9320",
    "sg:province":"Oost-Vlaanderen",
    "sg:tags":[
        "de"
    ],
    "wof:name":"Ttc Erembodegem",
    "wof:placetype":"venue"
},
  "geometry": {"coordinates":[4.0356378555,50.942817688],"type":"Point"}
}