{
  "type": "Feature",
  "properties": {
    "iso:country":"BE",
    "sg:address":"Kapelhof 14",
    "sg:city":"Zonhoven",
    "sg:classifiers":[
        {
            "category":"Cafe",
            "type":"Food & Drink"
        }
    ],
    "sg:phone":"+32 11 82 19 53",
    "sg:postcode":"3520",
    "sg:province":"Limburg",
    "sg:tags":[
        "caf\u00e9s"
    ],
    "wof:name":"Caf\u00c9 Kapelhof",
    "wof:placetype":"venue"
},
  "geometry": {"coordinates":[5.3685460091,50.987071991],"type":"Point"}
}