{
  "type": "Feature",
  "properties": {
    "iso:country":"BE",
    "sg:address":"Doornlaarstraat 58",
    "sg:city":"Bonheiden (rijmenam)",
    "sg:classifiers":[
        {
            "category":"Utilities",
            "subcategory":"Natural Gas",
            "type":"Services"
        }
    ],
    "sg:phone":"+32 15 51 37 43",
    "sg:postcode":"2820",
    "sg:province":"Antwerpen",
    "sg:tags":[
        "control",
        "tank"
    ],
    "wof:name":"Geens Leon Bvba",
    "wof:placetype":"venue"
},
  "geometry": {"coordinates":[4.6324548721,51.0157661438],"type":"Point"}
}