{
  "type": "Feature",
  "properties": {
    "addr:full":"Rue Des Piges 3 Charleroi Hainaut 6031",
    "addr:housenumber":"3",
    "addr:postcode":"6031",
    "addr:street":"Rue Des Piges;Hainaut",
    "iso:country":"BE",
    "sg:address":"Rue Des Piges 3",
    "sg:city":"Charleroi",
    "sg:orig_category":"M\u00e9decins and sp\u00e9cialistes",
    "sg:phone":"+32 71 31 83 14",
    "sg:postcode":"6031",
    "sg:province":"Hainaut",
    "wof:name":"Bernard Metz",
    "wof:placetype":"venue"
},
  "geometry": {"coordinates":[4.4414172173,50.394985199],"type":"Point"}
}