{
  "type": "Feature",
  "properties": {
    "iso:country":"BE",
    "sg:address":"Doornplasstraat 98",
    "sg:city":"Gent",
    "sg:orig_category":"Producteurs de l\u00e9gumes",
    "sg:phone":"+32 9 226 82 29",
    "sg:postcode":"9031",
    "sg:province":"Oost-Vlaanderen",
    "wof:name":"Luc Blanchaert",
    "wof:placetype":"venue"
},
  "geometry": {"coordinates":[3.6241021156,51.0638084412],"type":"Point"}
}