{
  "type": "Feature",
  "properties": {
    "addr:full":"Rue De L'ecorcheur 27 Villers-la-ville (sart-dames-avelines) Brabant Wallon 1495",
    "addr:housenumber":"27",
    "addr:postcode":"1495",
    "addr:street":"Rue De L'Ecorcheur",
    "iso:country":"BE",
    "sg:address":"Rue De L'ecorcheur 27",
    "sg:city":"Villers-la-ville (sart-dames-avelines)",
    "sg:classifiers":[
        {
            "category":"Retail",
            "subcategory":"Auto Repair",
            "type":"Services"
        }
    ],
    "sg:phone":"+32 71 88 68 80",
    "sg:postcode":"1495",
    "sg:province":"Brabant Wallon",
    "sg:tags":[
        "garage"
    ],
    "wof:name":"Ad Geeraerts (garage)",
    "wof:placetype":"venue"
},
  "geometry": {"coordinates":[4.5009741783,50.5584449768],"type":"Point"}
}