{
  "type": "Feature",
  "properties": {
    "addr:full":"Avenue De L'arc D'airain 10 Gembloux Namur 5030",
    "addr:housenumber":"10",
    "addr:postcode":"5030",
    "addr:street":"Avenue De L'Arc D'Airain;Namur",
    "iso:country":"BE",
    "sg:address":"Avenue De L'arc D'airain 10",
    "sg:city":"Gembloux",
    "sg:classifiers":[
        {
            "category":"Arena",
            "subcategory":"Sports Club",
            "type":"Entertainment"
        }
    ],
    "sg:phone":"+32 81 61 09 72",
    "sg:postcode":"5030",
    "sg:province":"Namur",
    "sg:tags":[
        "de"
    ],
    "wof:name":"Aquarius Plong\u00c9e Gembloux",
    "wof:placetype":"venue"
},
  "geometry": {"coordinates":[4.6828408241,50.5667533875],"type":"Point"}
}