{
  "type": "Feature",
  "properties": {
    "addr:full":"Nijverheidsstraat 43 Beringen Limburg 3580",
    "addr:housenumber":"43",
    "addr:postcode":"3580",
    "addr:street":"Nijverheidsstraat",
    "iso:country":"BE",
    "sg:address":"Nijverheidsstraat 43",
    "sg:city":"Beringen",
    "sg:classifiers":[
        {
            "category":"Home & Garden",
            "subcategory":"Building Materials",
            "type":"Retail Goods"
        }
    ],
    "sg:phone":"+32 11 42 27 70",
    "sg:postcode":"3580",
    "sg:province":"Limburg",
    "sg:tags":[
        "window"
    ],
    "wof:name":"Bogaerts D",
    "wof:placetype":"venue"
},
  "geometry": {"coordinates":[5.2163419724,51.0511627197],"type":"Point"}
}