{
  "type": "Feature",
  "properties": {
    "addr:full":"Kruisstraat 135 Kortenberg Vlaams-Brabant 3078",
    "addr:housenumber":"135",
    "addr:postcode":"3078",
    "addr:street":"Kruisstraat;Vlaams-Brabant",
    "iso:country":"BE",
    "sg:address":"Kruisstraat 135",
    "sg:city":"Kortenberg",
    "sg:orig_category":"Artsen and specialisten",
    "sg:phone":"+32 2 757 15 10",
    "sg:postcode":"3078",
    "sg:province":"Vlaams-Brabant",
    "wof:name":"Erwin Annys",
    "wof:placetype":"venue"
},
  "geometry": {"coordinates":[4.5415000916,50.8758735657],"type":"Point"}
}