{
  "type": "Feature",
  "properties": {
    "addr:full":"Avenue Du Centenaire 107 Seraing Li\u00e8ge 4102",
    "addr:housenumber":"107",
    "addr:postcode":"4102",
    "addr:street":"Avenue Du Centenaire",
    "iso:country":"BE",
    "sg:address":"Avenue Du Centenaire 107",
    "sg:city":"Seraing",
    "sg:orig_category":"Brood, gebak and snoepgoed",
    "sg:phone":"+32 4 337 80 68",
    "sg:postcode":"4102",
    "sg:province":"Li\u00e8ge",
    "wof:name":"Christophe Wechseler",
    "wof:placetype":"venue"
},
  "geometry": {"coordinates":[5.5408959389,50.5912361145],"type":"Point"}
}