{
  "type": "Feature",
  "properties": {
    "iso:country":"BE",
    "sg:address":"Postbus 139",
    "sg:city":"Waregem1",
    "sg:classifiers":[
        {
            "category":"Community Center",
            "type":"Public Place"
        }
    ],
    "sg:phone":"+32 56 61 12 87",
    "sg:postcode":"8790",
    "sg:province":"West-Vlaanderen",
    "sg:tags":[
        "medical"
    ],
    "wof:name":"Rode Kruis",
    "wof:placetype":"venue"
},
  "geometry": {"coordinates":[170.94201660159999,-44.5585098267],"type":"Point"}
}