{
  "type": "Feature",
  "properties": {
    "addr:full":"Mellestraat 309 Kortrijk West-Vlaanderen 8501",
    "addr:housenumber":"309",
    "addr:postcode":"8501",
    "addr:street":"Mellestraat",
    "iso:country":"BE",
    "sg:address":"Mellestraat 309",
    "sg:city":"Kortrijk",
    "sg:orig_category":"Eleveurs de bovins",
    "sg:phone":"+32 56 35 18 33",
    "sg:postcode":"8501",
    "sg:province":"West-Vlaanderen",
    "wof:name":"Devriendt Guido-fabian",
    "wof:placetype":"venue"
},
  "geometry": {"coordinates":[3.2232708931,50.8597221375],"type":"Point"}
}