{
  "type": "Feature",
  "properties": {
    "addr:full":"Rue De Bo\u00eblhe 32 Geer Li\u00e8ge 4250",
    "addr:housenumber":"32",
    "addr:postcode":"4250",
    "addr:street":"Rue De Boe\u0308Lhe",
    "iso:country":"BE",
    "sg:address":"Rue De Bo\u00eblhe 32",
    "sg:city":"Geer",
    "sg:classifiers":[
        {
            "category":"Wholesale",
            "subcategory":"Fruits & Vegetables",
            "type":"Manufacturing & Wholesale Goods"
        }
    ],
    "sg:phone":"+32 19 58 85 68",
    "sg:postcode":"4250",
    "sg:province":"Li\u00e8ge",
    "sg:tags":[
        "whol",
        "-",
        "potato"
    ],
    "wof:name":"Societe Du Terroir De Geer Scrl",
    "wof:placetype":"venue"
},
  "geometry": {"coordinates":[5.1721892357,50.6734809875],"type":"Point"}
}