{
  "type": "Feature",
  "properties": {
    "iso:country":"BE",
    "sg:address":"Kolenhavenstraat 1",
    "sg:city":"Genk",
    "sg:classifiers":[
        {
            "category":"Building & Trades",
            "subcategory":"Cleaning & Sanitation",
            "type":"Services"
        }
    ],
    "sg:phone":"+32 89 36 25 34",
    "sg:postcode":"3600",
    "sg:province":"Limburg",
    "sg:tags":[
        "equipment",
        "industrial",
        "maintenance"
    ],
    "wof:name":"Keroma Techniek Nv",
    "wof:placetype":"venue"
},
  "geometry": {"coordinates":[5.4947681427,50.9441833496],"type":"Point"}
}