{
  "type": "Feature",
  "properties": {
    "iso:country":"BE",
    "sg:address":"Peter Benoitstraat 42",
    "sg:city":"Anzegem",
    "sg:orig_category":"D\u00e9corateurs d'int\u00e9rieur",
    "sg:phone":"+32 56 77 70 60",
    "sg:postcode":"8570",
    "sg:province":"West-Vlaanderen",
    "wof:name":"Decoratie Derek Wilson",
    "wof:placetype":"venue"
},
  "geometry": {"coordinates":[3.478826046,50.8326339722],"type":"Point"}
}