{
  "type": "Feature",
  "properties": {
    "addr:full":"Atomiumlaan Brussel/bruxelles Bruxelles-Capitale 1020",
    "addr:postcode":"1020",
    "addr:street":"Atomiumlaan",
    "iso:country":"BE",
    "sg:address":"Atomiumlaan",
    "sg:city":"Brussel/bruxelles",
    "sg:orig_category":"Meubles D\u00e9taillants, Am\u00e9nagement de B\u00e2timents et de Cuisines",
    "sg:phone":"+32 2 478 76 01",
    "sg:postcode":"1020",
    "sg:province":"Bruxelles-Capitale",
    "wof:name":"Corleen",
    "wof:placetype":"venue"
},
  "geometry": {"coordinates":[4.3418998718,50.8951759338],"type":"Point"}
}