{
  "type": "Feature",
  "properties": {
    "addr:full":"Rue Francs Arquebusiers 15 Vise Li\u00e8ge 4600",
    "addr:housenumber":"15",
    "addr:postcode":"4600",
    "addr:street":"Rue Francs Arquebusiers",
    "iso:country":"BE",
    "sg:address":"Rue Francs Arquebusiers 15",
    "sg:city":"Vise",
    "sg:orig_category":"DIVERSE RECREATIEVE ACTIVITEITEN",
    "sg:phone":"+32 4 379 26 16",
    "sg:postcode":"4600",
    "sg:province":"Li\u00e8ge",
    "wof:name":"Cercle Royal Philat\u00c9lique",
    "wof:placetype":"venue"
},
  "geometry": {"coordinates":[5.6935458183,50.7386169434],"type":"Point"}
}