{
  "type": "Feature",
  "properties": {
    "iso:country":"BE",
    "sg:address":"Avenue Guillaume Joachim 1bd",
    "sg:city":"Waremme",
    "sg:orig_category":"Artsen and specialisten",
    "sg:phone":"+32 19 32 39 42",
    "sg:postcode":"4300",
    "sg:province":"Li\u00e8ge",
    "wof:name":"Isabelle Bodson",
    "wof:placetype":"venue"
},
  "geometry": {"coordinates":[5.2600479126,50.6977996826],"type":"Point"}
}