{
  "type": "Feature",
  "properties": {
    "addr:full":"Rue Du Moustier 2 Florenville Luxembourg 6820",
    "addr:housenumber":"2",
    "addr:postcode":"6820",
    "addr:street":"Rue Du Moustier",
    "iso:country":"BE",
    "sg:address":"Rue Du Moustier 2",
    "sg:city":"Florenville",
    "sg:orig_category":"Woningbouw",
    "sg:phone":"+32 61 31 29 66",
    "sg:postcode":"6820",
    "sg:province":"Luxembourg",
    "wof:name":"Fe. Mignon J.m.-hubert L.",
    "wof:placetype":"venue"
},
  "geometry": {"coordinates":[5.2327427864,49.7115402222],"type":"Point"}
}