{
  "type": "Feature",
  "properties": {
    "addr:full":"Klythoek 2 Zedelgem West-Vlaanderen 8210",
    "addr:housenumber":"2",
    "addr:postcode":"8210",
    "addr:street":"Klythoek",
    "iso:country":"BE",
    "sg:address":"Klythoek 2",
    "sg:city":"Zedelgem",
    "sg:classifiers":[
        {
            "category":"Building & Trades",
            "subcategory":"Cleaning & Sanitation",
            "type":"Services"
        }
    ],
    "sg:phone":"+32 50 20 99 32",
    "sg:postcode":"8210",
    "sg:province":"West-Vlaanderen",
    "sg:tags":[
        "industrial",
        "-"
    ],
    "wof:name":"Dampkampreiniging Kuijer Cv",
    "wof:placetype":"venue"
},
  "geometry": {"coordinates":[3.1249139309,51.1264648438],"type":"Point"}
}