{
  "type": "Feature",
  "properties": {
    "addr:full":"Meensesteenweg 578 Roeselare West-Vlaanderen 8800",
    "addr:housenumber":"578",
    "addr:postcode":"8800",
    "addr:street":"Meensesteenweg",
    "iso:country":"BE",
    "sg:address":"Meensesteenweg 578",
    "sg:city":"Roeselare",
    "sg:orig_category":"Industri\u00eble and commerci\u00eble bouw",
    "sg:phone":"+32 51 24 40 16",
    "sg:postcode":"8800",
    "sg:province":"West-Vlaanderen",
    "wof:name":"Boucon West",
    "wof:placetype":"venue"
},
  "geometry": {"coordinates":[3.1153390408,50.9091453552],"type":"Point"}
}