{
  "type": "Feature",
  "properties": {
    "addr:full":"Bredabaan 234 Brasschaat Antwerpen 2930",
    "addr:housenumber":"234",
    "addr:postcode":"2930",
    "addr:street":"Bredabaan",
    "iso:country":"BE",
    "sg:address":"Bredabaan 234",
    "sg:city":"Brasschaat",
    "sg:orig_category":"Chaussures",
    "sg:phone":"+32 3 651 71 99",
    "sg:postcode":"2930",
    "sg:province":"Antwerpen",
    "wof:name":"Maison Junior & J.r.bis",
    "wof:placetype":"venue"
},
  "geometry": {"coordinates":[4.489812851,51.2893791199],"type":"Point"}
}