{
  "type": "Feature",
  "properties": {
    "iso:country":"BE",
    "sg:address":"Bullinger Strasse 29",
    "sg:city":"Bntgenbach/bntgenbach",
    "sg:orig_category":"Huisdieren and benodigdheden Tuinbenodigdheden",
    "sg:phone":"+32 80 44 41 27",
    "sg:postcode":"4750",
    "sg:province":"Li\u00e8ge",
    "wof:name":"Aveve",
    "wof:placetype":"venue"
},
  "geometry": {"coordinates":[7.9098901749,50.5943183899],"type":"Point"}
}