{
  "type": "Feature",
  "properties": {
    "iso:country":"BE",
    "sg:address":"Kruisbeeldstraat 113",
    "sg:city":"Hamme",
    "sg:orig_category":"Dakwerken",
    "sg:phone":"+32 52 47 00 87",
    "sg:postcode":"9220",
    "sg:province":"Oost-Vlaanderen",
    "wof:name":"Fa. Segers",
    "wof:placetype":"venue"
},
  "geometry": {"coordinates":[4.1158981323,51.0960235596],"type":"Point"}
}