{
  "type": "Feature",
  "properties": {
    "addr:full":"Rue De Lottert 15 Arlon Luxembourg 6700",
    "addr:housenumber":"15",
    "addr:postcode":"6700",
    "addr:street":"Rue De Lottert",
    "iso:country":"BE",
    "sg:address":"Rue De Lottert 15",
    "sg:city":"Arlon",
    "sg:orig_category":"Eleveurs de bovins",
    "sg:phone":"+32 63 21 87 11",
    "sg:postcode":"6700",
    "sg:province":"Luxembourg",
    "wof:name":"Emile Mathay",
    "wof:placetype":"venue"
},
  "geometry": {"coordinates":[5.8126749992,49.6823234558],"type":"Point"}
}