{
  "type": "Feature",
  "properties": {
    "addr:full":"Rue Du Grand-pr\u00c9 33 Dinant Namur 5500",
    "addr:housenumber":"33",
    "addr:postcode":"5500",
    "addr:street":"Rue Du Grand-Pre\u0301",
    "iso:country":"BE",
    "sg:address":"Rue Du Grand-pr\u00c9 33",
    "sg:city":"Dinant",
    "sg:orig_category":"Plomberie, chauffage and installations sanitaires",
    "sg:phone":"+32 82 22 64 42",
    "sg:postcode":"5500",
    "sg:province":"Namur",
    "wof:name":"Jean-pierre Deville",
    "wof:placetype":"venue"
},
  "geometry": {"coordinates":[4.9271349907,50.2543487549],"type":"Point"}
}