{
  "type": "Feature",
  "properties": {
    "iso:country":"BE",
    "sg:address":"De Vlasvink 18",
    "sg:city":"Wevelgem",
    "sg:orig_category":"Schoonheidssalons",
    "sg:phone":"+32 56 41 63 83",
    "sg:postcode":"8560",
    "sg:province":"West-Vlaanderen",
    "wof:name":"Dominique Foucart",
    "wof:placetype":"venue"
},
  "geometry": {"coordinates":[3.1797859669,50.8238868713],"type":"Point"}
}