{
  "type": "Feature",
  "properties": {
    "addr:full":"Wideumont-village 182 Libramont-chevigny Luxembourg 6800",
    "addr:housenumber":"182",
    "addr:postcode":"6800",
    "addr:street":"Libramont-Chevigny Luxembourg",
    "iso:country":"BE",
    "sg:address":"Wideumont-village 182",
    "sg:city":"Libramont-chevigny",
    "sg:orig_category":"Rundveehouders",
    "sg:phone":"+32 61 25 53 78",
    "sg:postcode":"6800",
    "sg:province":"Luxembourg",
    "wof:name":"Gerard Coibion",
    "wof:placetype":"venue"
},
  "geometry": {"coordinates":[5.3761348724,49.9199943542],"type":"Point"}
}