{
  "type": "Feature",
  "properties": {
    "addr:full":"Vijversstraat 24-4 Hasselt Limburg 3500",
    "addr:housenumber":"24-4",
    "addr:postcode":"3500",
    "addr:street":"Vijversstraat",
    "iso:country":"BE",
    "sg:address":"Vijversstraat 24-4",
    "sg:city":"Hasselt",
    "sg:classifiers":[
        {
            "category":"Wholesale",
            "subcategory":"Medical Equipment & Supplies",
            "type":"Manufacturing & Wholesale Goods"
        }
    ],
    "sg:phone":"+32 11 20 16 34",
    "sg:postcode":"3500",
    "sg:province":"Limburg",
    "sg:tags":[
        "-",
        "imaging"
    ],
    "wof:name":"N.d.a.",
    "wof:placetype":"venue"
},
  "geometry": {"coordinates":[5.3506212234,50.9636306763],"type":"Point"}
}