{
  "type": "Feature",
  "properties": {
    "addr:full":"Nijverheidsstraat 5 Brugge West-Vlaanderen 8310",
    "addr:housenumber":"5",
    "addr:postcode":"8310",
    "addr:street":"Nijverheidsstraat",
    "iso:country":"BE",
    "sg:address":"Nijverheidsstraat 5",
    "sg:city":"Brugge",
    "sg:classifiers":[
        {
            "category":"Restaurant",
            "type":"Food & Drink"
        }
    ],
    "sg:phone":"+32 50 35 43 45",
    "sg:postcode":"8310",
    "sg:province":"West-Vlaanderen",
    "wof:name":"Joma Snacks",
    "wof:placetype":"venue"
},
  "geometry": {"coordinates":[3.2378189564,51.2042274475],"type":"Point"}
}