{
  "type": "Feature",
  "properties": {
    "addr:full":"Leopold Ii-laan 87 Sint-niklaas Oost-Vlaanderen 9100",
    "addr:housenumber":"87",
    "addr:postcode":"9100",
    "addr:street":"Leopold Ii-Laan",
    "iso:country":"BE",
    "sg:address":"Leopold Ii-laan 87",
    "sg:city":"Sint-niklaas",
    "sg:classifiers":[
        {
            "category":"Restaurant",
            "type":"Food & Drink"
        }
    ],
    "sg:phone":"+32 3 766 15 51",
    "sg:postcode":"9100",
    "sg:province":"Oost-Vlaanderen",
    "wof:name":"'t Parksken",
    "wof:placetype":"venue"
},
  "geometry": {"coordinates":[4.1491589546,51.172252655],"type":"Point"}
}