{
  "type": "Feature",
  "properties": {
    "iso:country":"BE",
    "sg:address":"Emile Van Becelaerelaan 28bb",
    "sg:city":"Watermaal-bosvoorde/watermael-boitsfort",
    "sg:orig_category":"Reclamebureaus",
    "sg:phone":"+32 2 675 79 39",
    "sg:postcode":"1170",
    "sg:province":"Bruxelles-Capitale",
    "wof:name":"The Big Bang Company",
    "wof:placetype":"venue"
},
  "geometry": {"coordinates":[4.4052500725,50.7999076843],"type":"Point"}
}