{
  "type": "Feature",
  "properties": {
    "iso:country":"BE",
    "sg:address":"Leuvensestraat 53",
    "sg:city":"Tienen",
    "sg:orig_category":"Slagers",
    "sg:phone":"+32 16 81 21 02",
    "sg:postcode":"3300",
    "sg:province":"Vlaams-Brabant",
    "wof:name":"Julien Cartois",
    "wof:placetype":"venue"
},
  "geometry": {"coordinates":[4.9339990616,50.8092498779],"type":"Point"}
}