{
  "type": "Feature",
  "properties": {
    "addr:full":"Lamorini\u00c8restraat 124 Antwerpen Antwerpen 2018",
    "addr:housenumber":"124",
    "addr:postcode":"2018",
    "addr:street":"Lamorinie\u0300Restraat",
    "iso:country":"BE",
    "sg:address":"Lamorini\u00c8restraat 124",
    "sg:city":"Antwerpen",
    "sg:orig_category":"Kapsalons",
    "sg:phone":"+32 3 230 39 38",
    "sg:postcode":"2018",
    "sg:province":"Antwerpen",
    "wof:name":"Coiffure Elan",
    "wof:placetype":"venue"
},
  "geometry": {"coordinates":[4.4213118553,51.2047424316],"type":"Point"}
}