{
  "type": "Feature",
  "properties": {
    "iso:country":"BE",
    "sg:address":"Rijerstraat 1",
    "sg:city":"Kluisbergen (ruien)",
    "sg:classifiers":[
        {
            "category":"Health Services",
            "subcategory":"Health Practitioner",
            "type":"Services"
        }
    ],
    "sg:phone":"+32 55 38 94 19",
    "sg:postcode":"9690",
    "sg:province":"Oost-Vlaanderen",
    "sg:tags":[
        "physiotherapist"
    ],
    "wof:name":"Van Malderen J",
    "wof:placetype":"venue"
},
  "geometry": {"coordinates":[3.4918019772,50.7718048096],"type":"Point"}
}