{
  "type": "Feature",
  "properties": {
    "iso:country":"BE",
    "sg:address":"Fosse Des Biays 78",
    "sg:city":"Libin",
    "sg:classifiers":[
        {
            "category":"Arts & Performance",
            "subcategory":"Music",
            "type":"Entertainment"
        }
    ],
    "sg:phone":"+32 61 65 58 13",
    "sg:postcode":"6890",
    "sg:province":"Luxembourg",
    "sg:tags":[
        "freelance",
        "musician"
    ],
    "wof:name":"Selis D",
    "wof:placetype":"venue"
},
  "geometry": {"coordinates":[5.2668600082,49.9814376831],"type":"Point"}
}