{
  "type": "Feature",
  "properties": {
    "iso:country":"BE",
    "sg:address":"Avenue De Jette 328",
    "sg:city":"Bruxelles (jette)",
    "sg:classifiers":[
        {
            "category":"Shopping",
            "subcategory":"Shoes",
            "type":"Retail Goods"
        }
    ],
    "sg:phone":"+32 2 426 52 88",
    "sg:postcode":"1090",
    "sg:province":"Bruxelles-Capitale",
    "sg:tags":[
        "slipper",
        "-"
    ],
    "wof:name":"Mony-shoe",
    "wof:placetype":"venue"
},
  "geometry": {"coordinates":[4.3230891228,50.8736534119],"type":"Point"}
}