{
  "type": "Feature",
  "properties": {
    "iso:country":"BE",
    "sg:address":"Rue De Beaumont 211",
    "sg:city":"Charleroi",
    "sg:classifiers":[
        {
            "category":"Arena",
            "subcategory":"Sports Club",
            "type":"Entertainment"
        }
    ],
    "sg:phone":"+32 71 51 29 15",
    "sg:postcode":"6030",
    "sg:province":"Hainaut",
    "sg:tags":[
        "de"
    ],
    "wof:name":"Marcheurs Hautes-roches",
    "wof:placetype":"venue"
},
  "geometry": {"coordinates":[4.3941950798,50.4002952576],"type":"Point"}
}