{
  "type": "Feature",
  "properties": {
    "iso:country":"BE",
    "sg:address":"Avenue Henri B\u00c9riot 37",
    "sg:city":"Boussu",
    "sg:orig_category":"Paramedische behandelingen",
    "sg:phone":"+32 65 77 74 46",
    "sg:postcode":"7301",
    "sg:province":"Hainaut",
    "wof:name":"R. Horlin",
    "wof:placetype":"venue"
},
  "geometry": {"coordinates":[3.8273460865,50.4402694702],"type":"Point"}
}