{
  "type": "Feature",
  "properties": {
    "addr:full":"Konkelstraat 181 Z Brussel/bruxelles Bruxelles-Capitale 1200",
    "addr:housenumber":"181 z",
    "addr:postcode":"1200",
    "addr:street":"Konkelstraat;/",
    "iso:country":"BE",
    "sg:address":"Konkelstraat 181 Z",
    "sg:city":"Brussel/bruxelles",
    "sg:orig_category":"Banken and kredietinstellingen",
    "sg:phone":"+32 2 771 81 22",
    "sg:postcode":"1200",
    "sg:province":"Bruxelles-Capitale",
    "wof:name":"Fortis",
    "wof:placetype":"venue"
},
  "geometry": {"coordinates":[4.4252500534,50.8438148499],"type":"Point"}
}