{
  "type": "Feature",
  "properties": {
    "iso:country":"BE",
    "sg:address":"Nieuwpoortsesteenweg 288",
    "sg:city":"Oostende",
    "sg:classifiers":[
        {
            "category":"Arena",
            "subcategory":"Sports Club",
            "type":"Entertainment"
        }
    ],
    "sg:phone":"+32 59 70 22 13",
    "sg:postcode":"8400",
    "sg:province":"West-Vlaanderen",
    "sg:tags":[
        "terrain",
        "hors",
        "de",
        "installation",
        "sportifs"
    ],
    "wof:name":"V.v. Vladslo",
    "wof:placetype":"venue"
},
  "geometry": {"coordinates":[2.891315937,51.2168045044],"type":"Point"}
}