{
  "type": "Feature",
  "properties": {
    "iso:country":"BE",
    "sg:address":"Driegoenstraat 6",
    "sg:city":"Poperinge (reningelst)",
    "sg:classifiers":[
        {
            "category":"Retail",
            "subcategory":"Veterinary Services",
            "type":"Services"
        }
    ],
    "sg:phone":"+32 57 33 37 39",
    "sg:postcode":"8970",
    "sg:province":"West-Vlaanderen",
    "sg:tags":[
        "veterinarian"
    ],
    "wof:name":"Devos M",
    "wof:placetype":"venue"
},
  "geometry": {"coordinates":[2.7898368835,50.8349151611],"type":"Point"}
}