{
  "type": "Feature",
  "properties": {
    "addr:full":"Kuringersteenweg 299ba1 Hasselt Limburg 3500",
    "addr:housenumber":"299ba1",
    "addr:postcode":"3500",
    "addr:street":"Kuringersteenweg",
    "iso:country":"BE",
    "sg:address":"Kuringersteenweg 299ba1",
    "sg:city":"Hasselt",
    "sg:orig_category":"Rijscholen",
    "sg:phone":"+32 11 85 13 30",
    "sg:postcode":"3500",
    "sg:province":"Limburg",
    "wof:name":"Hendriks",
    "wof:placetype":"venue"
},
  "geometry": {"coordinates":[5.3128972054,50.9381065369],"type":"Point"}
}