{
  "type": "Feature",
  "properties": {
    "iso:country":"BE",
    "sg:address":"Picardi\u00eblaan 11",
    "sg:city":"Schilde",
    "sg:classifiers":[
        {
            "category":"Professional",
            "subcategory":"Management & Consulting",
            "type":"Services"
        }
    ],
    "sg:phone":"+32 3 385 04 19",
    "sg:postcode":"2970",
    "sg:province":"Antwerpen",
    "sg:tags":[
        "consultant"
    ],
    "wof:name":"Leatrop Management",
    "wof:placetype":"venue"
},
  "geometry": {"coordinates":[4.5831899643,51.242729187],"type":"Point"}
}