{
  "type": "Feature",
  "properties": {
    "iso:country":"BE",
    "sg:address":"Hoogstraat 279",
    "sg:city":"Duffel",
    "sg:orig_category":"Jardinage",
    "sg:phone":"+32 15 31 62 66",
    "sg:postcode":"2570",
    "sg:province":"Antwerpen",
    "wof:name":"Liekens",
    "wof:placetype":"venue"
},
  "geometry": {"coordinates":[4.5333809853,51.0914421082],"type":"Point"}
}