{
  "type": "Feature",
  "properties": {
    "addr:full":"Avenue De Namur 59 Ciney Namur 5590",
    "addr:housenumber":"59",
    "addr:postcode":"5590",
    "addr:street":"Avenue De Namur",
    "iso:country":"BE",
    "sg:address":"Avenue De Namur 59",
    "sg:city":"Ciney",
    "sg:orig_category":"Eclairage et \u00e9quipements du foyer. Rev\u00eatements de sols and murs",
    "sg:phone":"+32 83 21 11 37",
    "sg:postcode":"5590",
    "sg:province":"Namur",
    "wof:name":"Hobby D\u00c9co",
    "wof:placetype":"venue"
},
  "geometry": {"coordinates":[5.0989198685,50.303565979],"type":"Point"}
}