{
  "type": "Feature",
  "properties": {
    "iso:country":"BE",
    "sg:address":"Blaubergsesteenweg 71",
    "sg:city":"Herselt",
    "sg:orig_category":"Autombile concessionaires",
    "sg:phone":"+32 14 54 42 54",
    "sg:postcode":"2230",
    "sg:province":"Antwerpen",
    "wof:name":"Gebr Aerts Bvba",
    "wof:placetype":"venue"
},
  "geometry": {"coordinates":[4.9035229683,51.0480308533],"type":"Point"}
}