{
  "type": "Feature",
  "properties": {
    "iso:country":"BE",
    "sg:address":"Rue Des Quatre Vents 92",
    "sg:city":"Bruxelles (molenbeek-saint-jean)",
    "sg:classifiers":[
        {
            "category":"Professional",
            "subcategory":"Engineering",
            "type":"Services"
        }
    ],
    "sg:phone":"+32 2 410 25 35",
    "sg:postcode":"1080",
    "sg:province":"Bruxelles-Capitale",
    "sg:tags":[
        "precision"
    ],
    "wof:name":"Meca Hi-tec Sprl",
    "wof:placetype":"venue"
},
  "geometry": {"coordinates":[4.3318519592,50.853302002],"type":"Point"}
}