{
  "type": "Feature",
  "properties": {
    "addr:full":"Haasroodsestraat 76 Oud-heverlee (blanden) Vlaams-Brabant 3052",
    "addr:housenumber":"76",
    "addr:postcode":"3052",
    "addr:street":"Haasroodsestraat",
    "iso:country":"BE",
    "sg:address":"Haasroodsestraat 76",
    "sg:city":"Oud-heverlee (blanden)",
    "sg:classifiers":[
        {
            "category":"Communications",
            "subcategory":"Film & Video Production",
            "type":"Services"
        }
    ],
    "sg:phone":"+32 16 40 13 08",
    "sg:postcode":"3052",
    "sg:province":"Vlaams-Brabant",
    "sg:tags":[
        "sound",
        "recording",
        "studio"
    ],
    "wof:name":"Studio C Bvba",
    "wof:placetype":"venue"
},
  "geometry": {"coordinates":[4.7187948227,50.8281898499],"type":"Point"}
}