{
  "type": "Feature",
  "properties": {
    "iso:country":"BE",
    "sg:address":"Olsensesteenweg 57",
    "sg:city":"Kruishoutem",
    "sg:orig_category":"Domotics",
    "sg:phone":"+32 9 383 54 14",
    "sg:postcode":"9770",
    "sg:province":"Oost-Vlaanderen",
    "wof:name":"Van Den Broecke Wim Bvba",
    "wof:placetype":"venue"
},
  "geometry": {"coordinates":[3.4994060993,50.9126167297],"type":"Point"}
}