{
  "type": "Feature",
  "properties": {
    "addr:full":"Pitsemburgstraat 4 Putte Antwerpen 2580",
    "addr:housenumber":"4",
    "addr:postcode":"2580",
    "addr:street":"Pitsemburgstraat",
    "iso:country":"BE",
    "sg:address":"Pitsemburgstraat 4",
    "sg:city":"Putte",
    "sg:orig_category":"Woningbouw",
    "sg:phone":"+32 15 75 68 42",
    "sg:postcode":"2580",
    "sg:province":"Antwerpen",
    "wof:name":"Wouters Alg. Aannemingen",
    "wof:placetype":"venue"
},
  "geometry": {"coordinates":[4.6454992294,51.0530700684],"type":"Point"}
}