{
  "type": "Feature",
  "properties": {
    "iso:country":"BE",
    "sg:address":"Kalvariestr 20",
    "sg:city":"Marke",
    "sg:classifiers":[
        {
            "category":"Manufacturing",
            "subcategory":"Printing",
            "type":"Manufacturing & Wholesale Goods"
        }
    ],
    "sg:phone":"+32 56 84 10 00",
    "sg:postcode":"8510",
    "sg:province":"West-Vlaanderen",
    "sg:tags":[
        "publishing"
    ],
    "wof:name":"Delabie",
    "wof:placetype":"venue"
},
  "geometry": {"coordinates":[3.2190279961,50.7275848389],"type":"Point"}
}