{
  "type": "Feature",
  "properties": {
    "iso:country":"BE",
    "sg:address":"Astridlaan 74",
    "sg:city":"Overpelt",
    "sg:classifiers":[
        {
            "category":"Arena",
            "subcategory":"Sports Club",
            "type":"Entertainment"
        }
    ],
    "sg:phone":"+32 11 64 37 48",
    "sg:postcode":"3900",
    "sg:province":"Limburg",
    "sg:tags":[
        "terrain",
        "hors",
        "de",
        "installation",
        "sportifs"
    ],
    "wof:name":"Kadijk S.k. Overpelt",
    "wof:placetype":"venue"
},
  "geometry": {"coordinates":[5.4086852074,51.2099266052],"type":"Point"}
}