{
  "type": "Feature",
  "properties": {
    "iso:country":"BE",
    "sg:address":"Rue De La Rivi\u00c8re 33",
    "sg:city":"Fernelmont",
    "sg:orig_category":"Woningbouw",
    "sg:phone":"+32 81 83 39 81",
    "sg:postcode":"5380",
    "sg:province":"Namur",
    "wof:name":"Christian Demarthe",
    "wof:placetype":"venue"
},
  "geometry": {"coordinates":[4.9861078262,50.5531463623],"type":"Point"}
}