{
  "type": "Feature",
  "properties": {
    "iso:country":"BE",
    "sg:address":"Rue Du Pont Du Christ 42",
    "sg:city":"Wavre",
    "sg:orig_category":"Geschenken and souvenirs Textiel",
    "sg:phone":"+32 10 22 22 78",
    "sg:postcode":"1300",
    "sg:province":"Brabant Wallon",
    "wof:name":"Jeu De Dames",
    "wof:placetype":"venue"
},
  "geometry": {"coordinates":[4.6094608307,50.7158088684],"type":"Point"}
}