{
  "type": "Feature",
  "properties": {
    "addr:full":"Avenue Du Douaire 2 Ottignies-louvain-la-neuve (ottignies) Brabant Wallon 1340",
    "addr:housenumber":"2",
    "addr:postcode":"1340",
    "addr:street":"Avenue Du Douaire",
    "iso:country":"BE",
    "sg:address":"Avenue Du Douaire 2",
    "sg:city":"Ottignies-louvain-la-neuve (ottignies)",
    "sg:classifiers":[
        {
            "category":"Food & Beverages",
            "subcategory":"Supermarket",
            "type":"Retail Goods"
        }
    ],
    "sg:phone":"+32 10 41 72 47",
    "sg:postcode":"1340",
    "sg:province":"Brabant Wallon",
    "sg:tags":[
        "department",
        "store"
    ],
    "wof:name":"Les Commer\u00e7ants Du Douaire Asbl",
    "wof:placetype":"venue"
},
  "geometry": {"coordinates":[4.5672249794,50.6636390686],"type":"Point"}
}