{
  "type": "Feature",
  "properties": {
    "iso:country":"BE",
    "sg:address":"Bevrijdingslaan 113",
    "sg:city":"Gent",
    "sg:classifiers":[
        {
            "category":"Cafe",
            "type":"Food & Drink"
        }
    ],
    "sg:phone":"+32 9 227 12 14",
    "sg:postcode":"9000",
    "sg:province":"Oost-Vlaanderen",
    "sg:tags":[
        "caf\u00e9s"
    ],
    "wof:name":"Caf\u00c9 Bonappetit",
    "wof:placetype":"venue"
},
  "geometry": {"coordinates":[3.6992030144,51.0620994568],"type":"Point"}
}