{
  "type": "Feature",
  "properties": {
    "addr:full":"Rue De L'eglise Saint-pierre 7a Andenne Namur 5300",
    "addr:housenumber":"7a",
    "addr:postcode":"5300",
    "addr:street":"Rue De L'Eglise Saint-Pierre",
    "iso:country":"BE",
    "sg:address":"Rue De L'eglise Saint-pierre 7a",
    "sg:city":"Andenne",
    "sg:classifiers":[
        {
            "category":"Personal",
            "subcategory":"Beauty Salon",
            "type":"Services"
        }
    ],
    "sg:phone":"+32 85 84 23 35",
    "sg:postcode":"5300",
    "sg:province":"Namur",
    "sg:tags":[
        "lady",
        "-",
        "hairdressing"
    ],
    "wof:name":"Leroy C",
    "wof:placetype":"venue"
},
  "geometry": {"coordinates":[5.1131691933,50.4947357178],"type":"Point"}
}