{
  "type": "Feature",
  "properties": {
    "addr:full":"Koning Boudewijnstraat 45 Izegem West-Vlaanderen 8870",
    "addr:housenumber":"45",
    "addr:postcode":"8870",
    "addr:street":"Koning Boudewijnstraat",
    "iso:country":"BE",
    "sg:address":"Koning Boudewijnstraat 45",
    "sg:city":"Izegem",
    "sg:classifiers":[
        {
            "category":"Parking",
            "subcategory":"Lot",
            "type":"Transportation"
        }
    ],
    "sg:phone":"+32 477 20 27 59",
    "sg:postcode":"8870",
    "sg:province":"West-Vlaanderen",
    "sg:tags":[
        "parking-places",
        "laying-out"
    ],
    "wof:name":"Werbrouck K",
    "wof:placetype":"venue"
},
  "geometry": {"coordinates":[3.2372059822,50.9243927002],"type":"Point"}
}