{
  "type": "Feature",
  "properties": {
    "addr:full":"Rue Du Soldat Larivi\u00e8re 47 Jodoigne Brabant Wallon 1370",
    "addr:housenumber":"47",
    "addr:postcode":"1370",
    "addr:street":"Rue Du Soldat Larivie\u0300Re",
    "iso:country":"BE",
    "sg:address":"Rue Du Soldat Larivi\u00e8re 47",
    "sg:city":"Jodoigne",
    "sg:classifiers":[
        {
            "category":"Professional",
            "subcategory":"Art Services",
            "type":"Services"
        }
    ],
    "sg:phone":"+32 10 81 14 78",
    "sg:postcode":"1370",
    "sg:province":"Brabant Wallon",
    "sg:tags":[
        "graphic",
        "designer"
    ],
    "wof:name":"Harmignies O",
    "wof:placetype":"venue"
},
  "geometry": {"coordinates":[4.8730649948,50.7188682556],"type":"Point"}
}