{
  "type": "Feature",
  "properties": {
    "addr:full":"Frans Beirenslaan 61 Borsbeek Antwerpen 2150",
    "addr:housenumber":"61",
    "addr:postcode":"2150",
    "addr:street":"Frans Beirenslaan",
    "iso:country":"BE",
    "sg:address":"Frans Beirenslaan 61",
    "sg:city":"Borsbeek",
    "sg:classifiers":[
        {
            "category":"Bars & Pubs",
            "type":"Food & Drink"
        }
    ],
    "sg:phone":"+32 3 322 56 62",
    "sg:postcode":"2150",
    "sg:province":"Antwerpen",
    "wof:name":"Eclips",
    "wof:placetype":"venue"
},
  "geometry": {"coordinates":[4.4791231155,51.1948471069],"type":"Point"}
}