{
  "type": "Feature",
  "properties": {
    "iso:country":"BE",
    "sg:address":"Renier Sniedersstraat 93",
    "sg:city":"Turnhout",
    "sg:orig_category":"Herstellingen and onderhoud van auto's Motorfietsen",
    "sg:phone":"+32 14 41 26 51",
    "sg:postcode":"2300",
    "sg:province":"Antwerpen",
    "wof:name":"Marheussen Jan",
    "wof:placetype":"venue"
},
  "geometry": {"coordinates":[4.9395561218,51.3245239258],"type":"Point"}
}