{
  "type": "Feature",
  "properties": {
    "iso:country":"BE",
    "sg:address":"De Gotelaar 69",
    "sg:city":"Roeselare",
    "sg:orig_category":"D\u00e9corateurs d'int\u00e9rieur",
    "sg:phone":"+32 51 24 72 24",
    "sg:postcode":"8800",
    "sg:province":"West-Vlaanderen",
    "wof:name":"Cocoon Projects",
    "wof:placetype":"venue"
},
  "geometry": {"coordinates":[3.1051249504,50.9680480957],"type":"Point"}
}