{
  "type": "Feature",
  "properties": {
    "addr:full":"Moeskroensesteenweg 275 Kortrijk West-Vlaanderen 8511",
    "addr:housenumber":"275",
    "addr:postcode":"8511",
    "addr:street":"Moeskroensesteenweg",
    "iso:country":"BE",
    "sg:address":"Moeskroensesteenweg 275",
    "sg:city":"Kortrijk",
    "sg:classifiers":[
        {
            "category":"Arena",
            "subcategory":"Sports Club",
            "type":"Entertainment"
        }
    ],
    "sg:phone":"+32 56 42 72 84",
    "sg:postcode":"8511",
    "sg:province":"West-Vlaanderen",
    "sg:tags":[
        "terrain",
        "hors",
        "de",
        "installation",
        "sportifs"
    ],
    "wof:name":"Kfc Ver. Aalbeke-rollegem",
    "wof:placetype":"venue"
},
  "geometry": {"coordinates":[3.2255599499,50.7683639526],"type":"Point"}
}