{
  "type": "Feature",
  "properties": {
    "iso:country":"BE",
    "sg:address":"Brugsebaan 4be",
    "sg:city":"Ardooie",
    "sg:orig_category":"Reclamebureaus",
    "sg:phone":"+32 51 46 64 00",
    "sg:postcode":"8850",
    "sg:province":"West-Vlaanderen",
    "wof:name":"Prima Lettering",
    "wof:placetype":"venue"
},
  "geometry": {"coordinates":[3.2401070595,50.9826812744],"type":"Point"}
}