{
  "type": "Feature",
  "properties": {
    "iso:country":"BE",
    "sg:address":"Gemeenschappenlaan 5",
    "sg:city":"Evere",
    "sg:orig_category":"Informaticaconsulenten",
    "sg:phone":"+32 2 726 43 30",
    "sg:postcode":"1140",
    "sg:province":"Bruxelles-Capitale",
    "wof:name":"A.d.p.-g.s.i.",
    "wof:placetype":"venue"
},
  "geometry": {"coordinates":[4.4231319427,50.8599205017],"type":"Point"}
}