{
  "type": "Feature",
  "properties": {
    "iso:country":"BE",
    "sg:address":"Diepenbekerweg 11",
    "sg:city":"Hasselt",
    "sg:orig_category":"Installation \u00e9lectrique industrielle",
    "sg:phone":"+32 11 26 03 70",
    "sg:postcode":"3500",
    "sg:province":"Limburg",
    "wof:name":"Anca-tech",
    "wof:placetype":"venue"
},
  "geometry": {"coordinates":[5.3631811142,50.9247245789],"type":"Point"}
}