{
  "type": "Feature",
  "properties": {
    "iso:country":"BE",
    "sg:address":"Antwerpseweg 85",
    "sg:city":"Geel",
    "sg:orig_category":"Entretien and r\u00e9parations de voitures",
    "sg:phone":"+32 14 58 54 60",
    "sg:postcode":"2440",
    "sg:province":"Antwerpen",
    "wof:name":"Car-wash Cleaning Center",
    "wof:placetype":"venue"
},
  "geometry": {"coordinates":[4.9560418129,51.1458473206],"type":"Point"}
}