{
  "type": "Feature",
  "properties": {
    "addr:full":"Suikerkaai 10 Zelzate Oost-Vlaanderen 9060",
    "addr:housenumber":"10",
    "addr:postcode":"9060",
    "addr:street":"Suikerkaai",
    "iso:country":"BE",
    "sg:address":"Suikerkaai 10",
    "sg:city":"Zelzate",
    "sg:orig_category":"Postkantoren Verzekeringsmakelaars and experts",
    "sg:phone":"+32 9 345 53 56",
    "sg:postcode":"9060",
    "sg:province":"Oost-Vlaanderen",
    "wof:name":"De Post",
    "wof:placetype":"venue"
},
  "geometry": {"coordinates":[3.8114991188,51.196685791],"type":"Point"}
}