{
  "type": "Feature",
  "properties": {
    "iso:country":"BE",
    "sg:address":"Lange Steenstraat 13a",
    "sg:city":"Kortrijk",
    "sg:classifiers":[
        {
            "category":"Shopping",
            "subcategory":"Clothing, Apparel, & Fashions",
            "type":"Retail Goods"
        }
    ],
    "sg:phone":"+32 56 22 53 21",
    "sg:postcode":"8500",
    "sg:province":"West-Vlaanderen",
    "sg:tags":[
        "lady",
        "clothing",
        "-"
    ],
    "wof:name":"Tangram",
    "wof:placetype":"venue"
},
  "geometry": {"coordinates":[3.2673890591,50.826423645],"type":"Point"}
}