{
  "type": "Feature",
  "properties": {
    "addr:full":"Rue Du K\u00eane \u00e0 Caimont 7 Mons (ciply) Hainaut 7024",
    "addr:housenumber":"7",
    "addr:postcode":"7024",
    "addr:street":"Rue Du Ke\u0302Ne A\u0300 Caimont",
    "iso:country":"BE",
    "sg:address":"Rue Du K\u00eane \u00e0 Caimont 7",
    "sg:city":"Mons (ciply)",
    "sg:orig_category":"Solariums",
    "sg:phone":"+32 65 31 10 86",
    "sg:postcode":"7024",
    "sg:province":"Hainaut",
    "wof:name":"Esth\u00e9tique Katty",
    "wof:placetype":"venue"
},
  "geometry": {"coordinates":[3.9458470345,50.4220848083],"type":"Point"}
}