{
  "type": "Feature",
  "properties": {
    "addr:full":"Haven 1025 Zwijndrecht Antwerpen 2070",
    "addr:postcode":"1025;2070",
    "addr:street":"Haven",
    "iso:country":"BE",
    "sg:address":"Haven 1025",
    "sg:city":"Zwijndrecht",
    "sg:orig_category":"Ramassage and traitement des d\u00e9chets agricoles, industriels and de construction. Ramassage and trait",
    "sg:phone":"+32 3 250 55 11",
    "sg:postcode":"2070",
    "sg:province":"Antwerpen",
    "wof:name":"Soils",
    "wof:placetype":"venue"
},
  "geometry": {"coordinates":[4.3302612305,51.2464179993],"type":"Point"}
}