{
  "type": "Feature",
  "properties": {
    "iso:country":"BE",
    "sg:address":"Grote Markt 34",
    "sg:city":"Beveren",
    "sg:orig_category":"Avocats and conseillers juridiques",
    "sg:phone":"+32 3 775 49 94",
    "sg:postcode":"9120",
    "sg:province":"Oost-Vlaanderen",
    "wof:name":"Gustaaf Deckers",
    "wof:placetype":"venue"
},
  "geometry": {"coordinates":[4.2579760551,51.2131614685],"type":"Point"}
}