{
  "type": "Feature",
  "properties": {
    "addr:full":"Rue Du Try Bara 8 Lasne (ohain) Brabant Wallon 1380",
    "addr:housenumber":"8",
    "addr:postcode":"1380",
    "addr:street":"Rue Du Try Bara;Wallon",
    "iso:country":"BE",
    "sg:address":"Rue Du Try Bara 8",
    "sg:city":"Lasne (ohain)",
    "sg:classifiers":[
        {
            "category":"Professional",
            "subcategory":"Management & Consulting",
            "type":"Services"
        }
    ],
    "sg:phone":"+32 2 633 44 03",
    "sg:postcode":"1380",
    "sg:province":"Brabant Wallon",
    "sg:tags":[
        "consultant"
    ],
    "wof:name":"Van Overmeiren E",
    "wof:placetype":"venue"
},
  "geometry": {"coordinates":[4.4679422379,50.7006225586],"type":"Point"}
}