{
  "type": "Feature",
  "properties": {
    "iso:country":"BE",
    "sg:address":"Pont Aux Lions 19",
    "sg:city":"Verviers",
    "sg:classifiers":[
        {
            "category":"Banks & Credit Unions",
            "subcategory":"Investment Brokerage",
            "type":"Services"
        }
    ],
    "sg:phone":"+32 87 35 33 10",
    "sg:postcode":"4800",
    "sg:province":"Li\u00e8ge",
    "sg:tags":[
        "jean",
        "casual",
        "wear"
    ],
    "wof:name":"Outline",
    "wof:placetype":"venue"
},
  "geometry": {"coordinates":[5.8619771004,50.5930557251],"type":"Point"}
}