{
  "type": "Feature",
  "properties": {
    "iso:country":"BE",
    "sg:address":"Industrieweg 16",
    "sg:city":"Peer",
    "sg:classifiers":[
        {
            "category":"Shopping",
            "subcategory":"Bicycles & Sporting Goods",
            "type":"Retail Goods"
        }
    ],
    "sg:phone":"+32 11 66 67 45",
    "sg:postcode":"3990",
    "sg:province":"Limburg",
    "sg:tags":[
        "tyre"
    ],
    "wof:name":"A.c.m.",
    "wof:placetype":"venue"
},
  "geometry": {"coordinates":[5.4458189011,51.1371803284],"type":"Point"}
}