{
  "type": "Feature",
  "properties": {
    "addr:full":"Rue Baudouin Leprince 157 Ham-sur-heure-nalinnes Hainaut 6120",
    "addr:housenumber":"157",
    "addr:postcode":"6120",
    "addr:street":"Rue Baudouin Leprince;Hainaut",
    "iso:country":"BE",
    "sg:address":"Rue Baudouin Leprince 157",
    "sg:city":"Ham-sur-heure-nalinnes",
    "sg:orig_category":"Plomberie, chauffage and installations sanitaires",
    "sg:phone":"+32 71 22 00 54",
    "sg:postcode":"6120",
    "sg:province":"Hainaut",
    "wof:name":"Gagliardini Bernard",
    "wof:placetype":"venue"
},
  "geometry": {"coordinates":[4.3970208168,50.341342926],"type":"Point"}
}