{
  "type": "Feature",
  "properties": {
    "addr:full":"Bollewerkstraat 19 Berlare Oost-Vlaanderen 9290",
    "addr:housenumber":"19",
    "addr:postcode":"9290",
    "addr:street":"Bollewerkstraat",
    "iso:country":"BE",
    "sg:address":"Bollewerkstraat 19",
    "sg:city":"Berlare",
    "sg:orig_category":"Diverse intermediaire producten Gh",
    "sg:phone":"+32 52 42 69 75",
    "sg:postcode":"9290",
    "sg:province":"Oost-Vlaanderen",
    "wof:name":"Gold Jewellery",
    "wof:placetype":"venue"
},
  "geometry": {"coordinates":[4.0043721199,51.0204277039],"type":"Point"}
}