{
  "type": "Feature",
  "properties": {
    "addr:full":"Place Hollenfeltz 25 Arlon Luxembourg 6700",
    "addr:housenumber":"25",
    "addr:postcode":"6700",
    "addr:street":"Place Hollenfeltz",
    "iso:country":"BE",
    "sg:address":"Place Hollenfeltz 25",
    "sg:city":"Arlon",
    "sg:orig_category":"Fleurs and plantes",
    "sg:phone":"+32 63 22 23 42",
    "sg:postcode":"6700",
    "sg:province":"Luxembourg",
    "wof:name":"Passiflore",
    "wof:placetype":"venue"
},
  "geometry": {"coordinates":[5.8134098053,49.684261322],"type":"Point"}
}