{
  "type": "Feature",
  "properties": {
    "addr:full":"Rue Ch\u00c2mont 24 La Roche-en-ardenne Luxembourg 6980",
    "addr:housenumber":"24",
    "addr:postcode":"6980",
    "addr:street":"Rue Cha\u0302Mont",
    "iso:country":"BE",
    "sg:address":"Rue Ch\u00c2mont 24",
    "sg:city":"La Roche-en-ardenne",
    "sg:orig_category":"Agences de publicit\u00e9. Imprimeries and copyshops",
    "sg:phone":"+32 84 41 28 36",
    "sg:postcode":"6980",
    "sg:province":"Luxembourg",
    "wof:name":"Click Service",
    "wof:placetype":"venue"
},
  "geometry": {"coordinates":[5.577600956,50.1843185425],"type":"Point"}
}