{
  "type": "Feature",
  "properties": {
    "iso:country":"BE",
    "sg:address":"Oedelemse Steenweg 41",
    "sg:city":"Damme (sijsele)",
    "sg:classifiers":[
        {
            "category":"Building & Trades",
            "subcategory":"Construction",
            "type":"Services"
        }
    ],
    "sg:phone":"+32 50 37 76 40",
    "sg:postcode":"8340",
    "sg:province":"West-Vlaanderen",
    "sg:tags":[
        "installation",
        "-",
        "central",
        "heating"
    ],
    "wof:name":"Vdb-woningservice",
    "wof:placetype":"venue"
},
  "geometry": {"coordinates":[3.3281779289,51.198589325],"type":"Point"}
}