{
  "type": "Feature",
  "properties": {
    "iso:country":"BE",
    "sg:address":"Rue Au Bois 21",
    "sg:city":"Drogenbos",
    "sg:classifiers":[
        {
            "category":"Retail",
            "subcategory":"Auto Rental",
            "type":"Services"
        }
    ],
    "sg:phone":"+32 2 344 03 26",
    "sg:postcode":"1620",
    "sg:province":"Vlaams-Brabant",
    "sg:tags":[
        "chauffeur",
        "automobile",
        "driven",
        "-",
        "car"
    ],
    "wof:name":"Breugelmans Limousines Sprl",
    "wof:placetype":"venue"
},
  "geometry": {"coordinates":[4.3208851814,50.7821960449],"type":"Point"}
}