{
  "type": "Feature",
  "properties": {
    "iso:country":"BE",
    "sg:address":"Everhoek 2",
    "sg:city":"Oelegem",
    "sg:classifiers":[
        {
            "category":"Building & Trades",
            "subcategory":"Construction",
            "type":"Services"
        }
    ],
    "sg:phone":"+32 52 47 98 48",
    "sg:postcode":"2520",
    "sg:province":"Antwerpen",
    "sg:tags":[
        "work",
        "skeleton"
    ],
    "wof:name":"Vadebo Algemene Bouwonderneming Nv",
    "wof:placetype":"venue"
},
  "geometry": {"coordinates":[4.1536798477,51.0875968933],"type":"Point"}
}