{
  "type": "Feature",
  "properties": {
    "addr:full":"Diesterstraat 14 Tessenderlo Limburg 3980",
    "addr:housenumber":"14",
    "addr:postcode":"3980",
    "addr:street":"Diesterstraat",
    "iso:country":"BE",
    "sg:address":"Diesterstraat 14",
    "sg:city":"Tessenderlo",
    "sg:orig_category":"Dameskledingzaken",
    "sg:phone":"+32 13 66 20 89",
    "sg:postcode":"3980",
    "sg:province":"Limburg",
    "wof:name":"Huis Charme",
    "wof:placetype":"venue"
},
  "geometry": {"coordinates":[5.0874319077,51.0669593811],"type":"Point"}
}