{
  "type": "Feature",
  "properties": {
    "iso:country":"BE",
    "sg:address":"Meulegoor 46z",
    "sg:city":"Arendonk",
    "sg:classifiers":[
        {
            "category":"Arena",
            "subcategory":"Sports Club",
            "type":"Entertainment"
        }
    ],
    "sg:phone":"+32 14 67 94 91",
    "sg:postcode":"2370",
    "sg:province":"Antwerpen",
    "wof:name":"Fc Vrij Arendonk Vzw",
    "wof:placetype":"venue"
},
  "geometry": {"coordinates":[5.0871219635,51.3336334229],"type":"Point"}
}