{
  "type": "Feature",
  "properties": {
    "addr:full":"Grand'rue Des Bouchers 8 Ath Hainaut 7800",
    "addr:housenumber":"8",
    "addr:postcode":"7800",
    "addr:street":"Grand'Rue Des Bouchers",
    "iso:country":"BE",
    "sg:address":"Grand'rue Des Bouchers 8",
    "sg:city":"Ath",
    "sg:classifiers":[
        {
            "category":"Insurance",
            "subcategory":"Life Insurance",
            "type":"Services"
        }
    ],
    "sg:phone":"+32 68 28 69 65",
    "sg:postcode":"7800",
    "sg:province":"Hainaut",
    "sg:tags":[
        "assurance"
    ],
    "wof:name":"Lemoine Et Huguet",
    "wof:placetype":"venue"
},
  "geometry": {"coordinates":[3.7766048908,50.6278038025],"type":"Point"}
}