{
  "type": "Feature",
  "properties": {
    "iso:country":"BE",
    "sg:address":"Poedermagazijnstraat 59b2",
    "sg:city":"Menen",
    "sg:classifiers":[
        {
            "category":"Real Estate",
            "subcategory":"Developer",
            "type":"Services"
        }
    ],
    "sg:phone":"+32 57 46 68 34",
    "sg:postcode":"8930",
    "sg:province":"West-Vlaanderen",
    "sg:tags":[
        "plomberie",
        "chauffage",
        "mat\u00e9riel",
        "gr",
        "pour"
    ],
    "wof:name":"Klima-service",
    "wof:placetype":"venue"
},
  "geometry": {"coordinates":[3.1206769943,50.80052948],"type":"Point"}
}