{
  "type": "Feature",
  "properties": {
    "addr:full":"Laarstraat 43 Boortmeerbeek Vlaams-Brabant 3190",
    "addr:housenumber":"43",
    "addr:postcode":"3190",
    "addr:street":"Laarstraat",
    "iso:country":"BE",
    "sg:address":"Laarstraat 43",
    "sg:city":"Boortmeerbeek",
    "sg:orig_category":"Mayonnaise - Mfg.& Whol",
    "sg:phone":"+32 16 60 61 44",
    "sg:postcode":"3190",
    "sg:province":"Vlaams-Brabant",
    "wof:name":"Anda Nv",
    "wof:placetype":"venue"
},
  "geometry": {"coordinates":[4.5790228844,50.9682044983],"type":"Point"}
}