{
  "type": "Feature",
  "properties": {
    "iso:country":"BE",
    "sg:address":"Chauss\u00c9e De Bruxelles 33",
    "sg:city":"Wemmel",
    "sg:orig_category":"Imprimeries and copyshops",
    "sg:phone":"+32 2 460 22 71",
    "sg:postcode":"1780",
    "sg:province":"Vlaams-Brabant",
    "wof:name":"Drukkerij Leleu",
    "wof:placetype":"venue"
},
  "geometry": {"coordinates":[4.3072328568,50.9064178467],"type":"Point"}
}