{
  "type": "Feature",
  "properties": {
    "addr:full":"Nijverheidslaan 3 Box 1 Grimbergen (strombeek-bever) Vlaams-Brabant 1853",
    "addr:housenumber":"3;1",
    "addr:postcode":"1853",
    "addr:street":"Nijverheidslaan;Box",
    "iso:country":"BE",
    "sg:address":"Nijverheidslaan 3 Box 1",
    "sg:city":"Grimbergen (strombeek-bever)",
    "sg:orig_category":"Non-Classified Establishments",
    "sg:phone":"+32 2 263 32 11",
    "sg:postcode":"1853",
    "sg:province":"Vlaams-Brabant",
    "wof:name":"Bauknecht",
    "wof:placetype":"venue"
},
  "geometry": {"coordinates":[4.3613090515,50.9115524292],"type":"Point"}
}