{
  "type": "Feature",
  "properties": {
    "addr:full":"Begoniapark 21 Heuvelland West-Vlaanderen 8954",
    "addr:housenumber":"21",
    "addr:postcode":"8954",
    "addr:street":"Begoniapark",
    "iso:country":"BE",
    "sg:address":"Begoniapark 21",
    "sg:city":"Heuvelland",
    "sg:orig_category":"Gespecialiseerde residenti\u00eble bouw",
    "sg:phone":"+32 57 44 69 81",
    "sg:postcode":"8954",
    "sg:province":"West-Vlaanderen",
    "wof:name":"Eric Caron",
    "wof:placetype":"venue"
},
  "geometry": {"coordinates":[2.7472150326,50.8018264771],"type":"Point"}
}