{
  "type": "Feature",
  "properties": {
    "iso:country":"BE",
    "sg:address":"Oude Heirbaan 180",
    "sg:city":"Deinze",
    "sg:orig_category":"Afval and schroot Gh Verhuur doe-het-zelf materiaal",
    "sg:phone":"+32 51 63 60 33",
    "sg:postcode":"9800",
    "sg:province":"Oost-Vlaanderen",
    "wof:name":"Kurt De Boever",
    "wof:placetype":"venue"
},
  "geometry": {"coordinates":[3.4562449455,50.9600410461],"type":"Point"}
}