{
  "type": "Feature",
  "properties": {
    "addr:full":"Rue Des Combattants 52 Anderlues Hainaut 6150",
    "addr:housenumber":"52",
    "addr:postcode":"6150",
    "addr:street":"Rue Des Combattants",
    "iso:country":"BE",
    "sg:address":"Rue Des Combattants 52",
    "sg:city":"Anderlues",
    "sg:orig_category":"Traitements param\u00e9dicaux",
    "sg:phone":"+32 71 54 43 89",
    "sg:postcode":"6150",
    "sg:province":"Hainaut",
    "wof:name":"M. Laurent",
    "wof:placetype":"venue"
},
  "geometry": {"coordinates":[4.2608680725,50.4092750549],"type":"Point"}
}