{
  "type": "Feature",
  "properties": {
    "addr:full":"Merellaan 14 Meise Vlaams-Brabant 1860",
    "addr:housenumber":"14",
    "addr:postcode":"1860",
    "addr:street":"Merellaan",
    "iso:country":"BE",
    "sg:address":"Merellaan 14",
    "sg:city":"Meise",
    "sg:orig_category":"Loodgieterij, verwarming and sanitaire installaties",
    "sg:phone":"+32 2 270 34 86",
    "sg:postcode":"1860",
    "sg:province":"Vlaams-Brabant",
    "wof:name":"Anthony Vanderstichelen",
    "wof:placetype":"venue"
},
  "geometry": {"coordinates":[4.3403382301,50.9262657166],"type":"Point"}
}