{
  "type": "Feature",
  "properties": {
    "iso:country":"BE",
    "sg:address":"Albert I Laan 288 B 38",
    "sg:city":"Nieuwpoort",
    "sg:orig_category":"Goederenvervoer over de weg Koerierbedrijven Vrachtvervoer",
    "sg:phone":"+32 58 23 24 69",
    "sg:postcode":"8620",
    "sg:province":"West-Vlaanderen",
    "wof:name":"Speed Express",
    "wof:placetype":"venue"
},
  "geometry": {"coordinates":[2.7093770504,51.1456947327],"type":"Point"}
}