{
  "type": "Feature",
  "properties": {
    "addr:full":"Ruiseleedsesteenweg 42b Tielt West-Vlaanderen 8700",
    "addr:housenumber":"42b",
    "addr:postcode":"8700",
    "addr:street":"Ruiseleedsesteenweg",
    "iso:country":"BE",
    "sg:address":"Ruiseleedsesteenweg 42b",
    "sg:city":"Tielt",
    "sg:classifiers":[
        {
            "category":"Personal",
            "subcategory":"Beauty Salon",
            "type":"Services"
        }
    ],
    "sg:phone":"+32 51 40 73 74",
    "sg:postcode":"8700",
    "sg:province":"West-Vlaanderen",
    "sg:tags":[
        "lady",
        "-",
        "hairdressing"
    ],
    "wof:name":"Taelman",
    "wof:placetype":"venue"
},
  "geometry": {"coordinates":[3.3609490395,51.011089325],"type":"Point"}
}