{
  "type": "Feature",
  "properties": {
    "addr:full":"Ch De Tournai 82 Ath Hainaut 7800",
    "addr:housenumber":"82",
    "addr:postcode":"7800",
    "addr:street":"Ch De Tournai",
    "iso:country":"BE",
    "sg:address":"Ch De Tournai 82",
    "sg:city":"Ath",
    "sg:classifiers":[
        {
            "category":"Autos & Motor Vehicles",
            "subcategory":"Automobile Sales",
            "type":"Retail Goods"
        }
    ],
    "sg:phone":"+32 68 26 86 86",
    "sg:postcode":"7800",
    "sg:province":"Hainaut",
    "sg:tags":[
        "equipment",
        "motor-cars",
        "transport"
    ],
    "wof:name":"Ets Paeleman Sa",
    "wof:placetype":"venue"
},
  "geometry": {"coordinates":[3.7654020786,50.6330223083],"type":"Point"}
}