{
  "type": "Feature",
  "properties": {
    "addr:full":"Ruandadreef 46ba Keerbergen Vlaams-Brabant 3140",
    "addr:housenumber":"46ba",
    "addr:postcode":"3140",
    "addr:street":"Ruandadreef",
    "iso:country":"BE",
    "sg:address":"Ruandadreef 46ba",
    "sg:city":"Keerbergen",
    "sg:orig_category":"Artiesten and kunstenaars",
    "sg:phone":"+32 16 53 32 94",
    "sg:postcode":"3140",
    "sg:province":"Vlaams-Brabant",
    "wof:name":"David De Graef",
    "wof:placetype":"venue"
},
  "geometry": {"coordinates":[4.6969242096,51.0004920959],"type":"Point"}
}