{
  "type": "Feature",
  "properties": {
    "addr:full":"Meerkensstraat 29 Dilsen-stokkem (lanklaar) Limburg 3650",
    "addr:housenumber":"29",
    "addr:postcode":"3650",
    "addr:street":"Meerkensstraat",
    "iso:country":"BE",
    "sg:address":"Meerkensstraat 29",
    "sg:city":"Dilsen-stokkem (lanklaar)",
    "sg:classifiers":[
        {
            "category":"Home & Garden",
            "subcategory":"Hardware",
            "type":"Retail Goods"
        }
    ],
    "sg:phone":"+32 89 75 54 69",
    "sg:postcode":"3650",
    "sg:province":"Limburg",
    "sg:tags":[
        "builders'",
        "-",
        "furniture"
    ],
    "wof:name":"Gerstij",
    "wof:placetype":"venue"
},
  "geometry": {"coordinates":[5.727396965,51.0364189148],"type":"Point"}
}