{
  "type": "Feature",
  "properties": {
    "addr:full":"Koning Albertlaan 33 Sint-agatha-berchem/berchem-sainte-agathe Bruxelles-Capitale 1082",
    "addr:housenumber":"33",
    "addr:postcode":"1082",
    "addr:street":"Koning Albertlaan;/",
    "iso:country":"BE",
    "sg:address":"Koning Albertlaan 33",
    "sg:city":"Sint-agatha-berchem/berchem-sainte-agathe",
    "sg:orig_category":"Beheer van afvalopslag- and stortplaatsen Overheidsdiensten",
    "sg:phone":"+32 2 464 04 11",
    "sg:postcode":"1082",
    "sg:province":"Bruxelles-Capitale",
    "wof:name":"Gemeentebestuur/admin. Communale",
    "wof:placetype":"venue"
},
  "geometry": {"coordinates":[4.2948470116,50.864818573],"type":"Point"}
}