{
  "type": "Feature",
  "properties": {
    "iso:country":"BE",
    "sg:address":"Dr\u00c8ve De Champagne 13",
    "sg:city":"Vorst/forest",
    "sg:orig_category":"Boissons",
    "sg:phone":"+32 2 376 06 72",
    "sg:postcode":"1190",
    "sg:province":"Bruxelles-Capitale",
    "wof:name":"Le Cep",
    "wof:placetype":"venue"
},
  "geometry": {"coordinates":[4.3258910179,50.8063049316],"type":"Point"}
}