{
  "type": "Feature",
  "properties": {
    "iso:country":"BE",
    "sg:address":"Rue Du Centre 48",
    "sg:city":"Attert (nobressart)",
    "sg:classifiers":[
        {
            "category":"Health Services",
            "subcategory":"Doctor",
            "type":"Services"
        }
    ],
    "sg:phone":"+32 63 23 53 03",
    "sg:postcode":"6717",
    "sg:province":"Luxembourg",
    "sg:tags":[
        "medicinephysicians",
        "surgeon"
    ],
    "wof:name":"Deschutter A",
    "wof:placetype":"venue"
},
  "geometry": {"coordinates":[5.7888741493,49.7506217957],"type":"Point"}
}