{
  "type": "Feature",
  "properties": {
    "addr:full":"Avenue Du Prince H\u00c9ritier 55 Sint-lambrechts-woluwe/woluwe-saint-lambert Bruxelles-Capitale 1200",
    "addr:housenumber":"55",
    "addr:postcode":"1200",
    "addr:street":"Avenue Du Prince He\u0301Ritier",
    "iso:country":"BE",
    "sg:address":"Avenue Du Prince H\u00c9ritier 55",
    "sg:city":"Sint-lambrechts-woluwe/woluwe-saint-lambert",
    "sg:orig_category":"Alimentation sp\u00e9cialis\u00e9e. Epiceries",
    "sg:phone":"+32 2 734 68 26",
    "sg:postcode":"1200",
    "sg:province":"Bruxelles-Capitale",
    "wof:name":"L'epicerie Hoeilaartoise",
    "wof:placetype":"venue"
},
  "geometry": {"coordinates":[4.4108910561,50.8421134949],"type":"Point"}
}