{
  "type": "Feature",
  "properties": {
    "addr:full":"Sint-katriensteenweg 83 Kuurne West-Vlaanderen 8520",
    "addr:housenumber":"83",
    "addr:postcode":"8520",
    "addr:street":"Sint-Katriensteenweg",
    "iso:country":"BE",
    "sg:address":"Sint-katriensteenweg 83",
    "sg:city":"Kuurne",
    "sg:classifiers":[
        {
            "category":"Manufacturing",
            "subcategory":"Metals",
            "type":"Manufacturing & Wholesale Goods"
        }
    ],
    "sg:phone":"+32 56 35 87 98",
    "sg:postcode":"8520",
    "sg:province":"West-Vlaanderen",
    "sg:tags":[
        "nickel",
        "plating",
        "chromium"
    ],
    "wof:name":"J.p.o. Galvanotechniek Bvba",
    "wof:placetype":"venue"
},
  "geometry": {"coordinates":[3.2537119389,50.8671417236],"type":"Point"}
}