{
  "type": "Feature",
  "properties": {
    "addr:full":"Visserskaai 45 Oostende West-Vlaanderen 8400",
    "addr:housenumber":"45",
    "addr:postcode":"8400",
    "addr:street":"Visserskaai",
    "iso:country":"BE",
    "sg:address":"Visserskaai 45",
    "sg:city":"Oostende",
    "sg:classifiers":[
        {
            "category":"Fast Food",
            "type":"Food & Drink"
        }
    ],
    "sg:phone":"+32 59 70 26 38",
    "sg:postcode":"8400",
    "sg:province":"West-Vlaanderen",
    "sg:tags":[
        "meeneem",
        "restaurant"
    ],
    "wof:name":"'t Ankertje",
    "wof:placetype":"venue"
},
  "geometry": {"coordinates":[2.9213359356,51.2342300415],"type":"Point"}
}