{
  "type": "Feature",
  "properties": {
    "addr:full":"Rue L\u00e9on Lepage 34 Bruxelles Bruxelles-Capitale 1000",
    "addr:housenumber":"34",
    "addr:postcode":"1000",
    "addr:street":"Rue Le\u0301On Lepage",
    "iso:country":"BE",
    "sg:address":"Rue L\u00e9on Lepage 34",
    "sg:city":"Bruxelles",
    "sg:classifiers":[
        {
            "category":"Social Services",
            "subcategory":"Job Training",
            "type":"Services"
        }
    ],
    "sg:phone":"+32 2 502 02 27",
    "sg:postcode":"1000",
    "sg:province":"Bruxelles-Capitale",
    "sg:tags":[
        "interpreter"
    ],
    "wof:name":"Mior V",
    "wof:placetype":"venue"
},
  "geometry": {"coordinates":[4.3450188637,50.8523406982],"type":"Point"}
}