{
  "type": "Feature",
  "properties": {
    "addr:full":"Bloemenstraat 50 Wellen Limburg 3830",
    "addr:housenumber":"50",
    "addr:postcode":"3830",
    "addr:street":"Bloemenstraat",
    "iso:country":"BE",
    "sg:address":"Bloemenstraat 50",
    "sg:city":"Wellen",
    "sg:orig_category":"Installation \u00e9lectrique r\u00e9sidentielle",
    "sg:phone":"+32 12 74 23 16",
    "sg:postcode":"3830",
    "sg:province":"Limburg",
    "wof:name":"Erwin Vendrickx",
    "wof:placetype":"venue"
},
  "geometry": {"coordinates":[5.3394842148,50.8439407349],"type":"Point"}
}