{
  "type": "Feature",
  "properties": {
    "addr:full":"Roterijstraat 76 Wevelgem West-Vlaanderen 8560",
    "addr:housenumber":"76",
    "addr:postcode":"8560",
    "addr:street":"Roterijstraat",
    "iso:country":"BE",
    "sg:address":"Roterijstraat 76",
    "sg:city":"Wevelgem",
    "sg:orig_category":"Huishoudapparaten, televisies and radio's",
    "sg:phone":"+32 56 41 28 04",
    "sg:postcode":"8560",
    "sg:province":"West-Vlaanderen",
    "wof:name":"Lucien Depoorter",
    "wof:placetype":"venue"
},
  "geometry": {"coordinates":[3.1853680611,50.8153991699],"type":"Point"}
}