{
  "type": "Feature",
  "properties": {
    "iso:country":"BE",
    "sg:address":"Wingepark 5ba",
    "sg:city":"Rotselaar",
    "sg:orig_category":"Traitement and fa\u00e7onnage de la pierre. Rev\u00eatements de sols and murs",
    "sg:phone":"+32 16 44 66 84",
    "sg:postcode":"3110",
    "sg:province":"Vlaams-Brabant",
    "wof:name":"Natuursteen Rotselaar",
    "wof:placetype":"venue"
},
  "geometry": {"coordinates":[4.7439618111,50.9398460388],"type":"Point"}
}