{
  "type": "Feature",
  "properties": {
    "addr:full":"Clos Des Bouleaux 19 Wezembeek-oppem/wezembeek-oppem Vlaams-Brabant 1970",
    "addr:housenumber":"19",
    "addr:postcode":"1970",
    "addr:street":"Clos Des Bouleaux",
    "iso:country":"BE",
    "sg:address":"Clos Des Bouleaux 19",
    "sg:city":"Wezembeek-oppem/wezembeek-oppem",
    "sg:orig_category":"M\u00e9decins and sp\u00e9cialistes",
    "sg:phone":"+32 2 731 96 61",
    "sg:postcode":"1970",
    "sg:province":"Vlaams-Brabant",
    "wof:name":"A. Wauthy",
    "wof:placetype":"venue"
},
  "geometry": {"coordinates":[4.4919548035,50.8482704163],"type":"Point"}
}