{
  "type": "Feature",
  "properties": {
    "iso:country":"BE",
    "sg:address":"Rue De La Poste 54",
    "sg:city":"Eghez\u00e9e (leuze)",
    "sg:classifiers":[
        {
            "category":"Building & Trades",
            "subcategory":"Landscaping Services",
            "type":"Services"
        }
    ],
    "sg:phone":"+32 81 20 06 87",
    "sg:postcode":"5310",
    "sg:province":"Namur",
    "sg:tags":[
        "nurseryman"
    ],
    "wof:name":"Denil Y",
    "wof:placetype":"venue"
},
  "geometry": {"coordinates":[4.9070439339,50.5612945557],"type":"Point"}
}