{
  "type": "Feature",
  "properties": {
    "iso:country":"BE",
    "sg:address":"Rue De Marche 169",
    "sg:city":"Bastogne",
    "sg:classifiers":[
        {
            "category":"Insurance",
            "subcategory":"Insurance Agent",
            "type":"Services"
        }
    ],
    "sg:phone":"+32 61 21 62 90",
    "sg:postcode":"6600",
    "sg:province":"Luxembourg",
    "sg:tags":[
        "verzekeringsmakelaars",
        "expert"
    ],
    "wof:name":"A. Charneux",
    "wof:placetype":"venue"
},
  "geometry": {"coordinates":[5.6943922043,50.0022735596],"type":"Point"}
}