{
  "type": "Feature",
  "properties": {
    "iso:country":"BE",
    "sg:address":"Trichterweg 39",
    "sg:city":"Zutendaal",
    "sg:classifiers":[
        {
            "category":"Banks & Credit Unions",
            "subcategory":"Investment Brokerage",
            "type":"Services"
        }
    ],
    "sg:phone":"+32 89 71 56 65",
    "sg:postcode":"3690",
    "sg:province":"Limburg",
    "sg:tags":[
        "repair",
        "-",
        "installation",
        "sanitary",
        "article"
    ],
    "wof:name":"Peters P",
    "wof:placetype":"venue"
},
  "geometry": {"coordinates":[5.5971441269,50.9289054871],"type":"Point"}
}