{
  "type": "Feature",
  "properties": {
    "addr:full":"Steenland 2 Brakel (michelbeke) Oost-Vlaanderen 9660",
    "addr:housenumber":"2",
    "addr:postcode":"9660",
    "addr:street":"Steenland",
    "iso:country":"BE",
    "sg:address":"Steenland 2",
    "sg:city":"Brakel (michelbeke)",
    "sg:classifiers":[
        {
            "category":"Health Services",
            "subcategory":"Doctor",
            "type":"Services"
        }
    ],
    "sg:phone":"+32 55 49 91 29",
    "sg:postcode":"9660",
    "sg:province":"Oost-Vlaanderen",
    "sg:tags":[
        "medicinephysicians",
        "surgeon"
    ],
    "wof:name":"Machtelinckx L",
    "wof:placetype":"venue"
},
  "geometry": {"coordinates":[3.7642250061,50.8031082153],"type":"Point"}
}