{
  "type": "Feature",
  "properties": {
    "addr:full":"Kortekeer 10 Vleteren West-Vlaanderen 8640",
    "addr:housenumber":"10",
    "addr:postcode":"8640",
    "addr:street":"Kortekeer",
    "iso:country":"BE",
    "sg:address":"Kortekeer 10",
    "sg:city":"Vleteren",
    "sg:classifiers":[
        {
            "category":"Insurance",
            "subcategory":"Insurance Agent",
            "type":"Services"
        }
    ],
    "sg:phone":"+32 57 40 03 01",
    "sg:postcode":"8640",
    "sg:province":"West-Vlaanderen",
    "sg:tags":[
        "verzekeringsmakelaars",
        "expert"
    ],
    "wof:name":"Bureau Nicolaes-verhille",
    "wof:placetype":"venue"
},
  "geometry": {"coordinates":[2.7383799553,50.9309120178],"type":"Point"}
}