{
  "type": "Feature",
  "properties": {
    "addr:full":"Steenovenstraat 10 Overpelt Limburg 3900",
    "addr:housenumber":"10",
    "addr:postcode":"3900",
    "addr:street":"Steenovenstraat",
    "iso:country":"BE",
    "sg:address":"Steenovenstraat 10",
    "sg:city":"Overpelt",
    "sg:orig_category":"Installatie van houten of kunststof schrijnwerk",
    "sg:phone":"+32 11 66 16 01",
    "sg:postcode":"3900",
    "sg:province":"Limburg",
    "wof:name":"Bouwbedrijf Gilco",
    "wof:placetype":"venue"
},
  "geometry": {"coordinates":[5.4273729324,51.1960144043],"type":"Point"}
}