{
  "type": "Feature",
  "properties": {
    "addr:full":"Merkenstraat 16 Tongeren Limburg 3700",
    "addr:housenumber":"16",
    "addr:postcode":"3700",
    "addr:street":"Merkenstraat",
    "iso:country":"BE",
    "sg:address":"Merkenstraat 16",
    "sg:city":"Tongeren",
    "sg:orig_category":"Fitnesscentra Sportclubs",
    "sg:phone":"+32 12 23 71 52",
    "sg:postcode":"3700",
    "sg:province":"Limburg",
    "wof:name":"Ghymi's Fitness Center",
    "wof:placetype":"venue"
},
  "geometry": {"coordinates":[5.4784989357,50.7857627869],"type":"Point"}
}