{
  "type": "Feature",
  "properties": {
    "iso:country":"BE",
    "sg:address":"Avenue Du Printemps 17",
    "sg:city":"Waterloo",
    "sg:orig_category":"M\u00e9decines alternatives",
    "sg:phone":"+32 2 354 74 36",
    "sg:postcode":"1410",
    "sg:province":"Brabant Wallon",
    "wof:name":"M. Job",
    "wof:placetype":"venue"
},
  "geometry": {"coordinates":[4.3953881264,50.7085990906],"type":"Point"}
}