{
  "type": "Feature",
  "properties": {
    "addr:full":"Bareelstraat 8 Kalmthout Antwerpen 2920",
    "addr:housenumber":"8",
    "addr:postcode":"2920",
    "addr:street":"Bareelstraat",
    "iso:country":"BE",
    "sg:address":"Bareelstraat 8",
    "sg:city":"Kalmthout",
    "sg:classifiers":[
        {
            "category":"Arena",
            "subcategory":"Sports Club",
            "type":"Entertainment"
        }
    ],
    "sg:phone":"+32 3 666 91 72",
    "sg:postcode":"2920",
    "sg:province":"Antwerpen",
    "sg:tags":[
        "de"
    ],
    "wof:name":"H.c. Royal Antwerp",
    "wof:placetype":"venue"
},
  "geometry": {"coordinates":[4.4716992378,51.3750343323],"type":"Point"}
}