{
  "type": "Feature",
  "properties": {
    "addr:full":"Esenstraat 64ba Kortemark West-Vlaanderen 8610",
    "addr:postcode":"8610",
    "addr:street":"Esenstraat",
    "iso:country":"BE",
    "sg:address":"Esenstraat 64ba",
    "sg:city":"Kortemark",
    "sg:orig_category":"Begrafeniswezen",
    "sg:phone":"+32 51 57 03 03",
    "sg:postcode":"8610",
    "sg:province":"West-Vlaanderen",
    "wof:name":"Geert Logghe",
    "wof:placetype":"venue"
},
  "geometry": {"coordinates":[2.9525930882,51.0171966553],"type":"Point"}
}