{
  "type": "Feature",
  "properties": {
    "iso:country":"BE",
    "sg:address":"Van Schoonhovenstraat 21-23",
    "sg:city":"Antwerpen",
    "sg:classifiers":[
        {
            "category":"Food & Beverages",
            "subcategory":"Groceries & Convenience Stores",
            "type":"Retail Goods"
        }
    ],
    "sg:phone":"+32 3 225 29 38",
    "sg:postcode":"2060",
    "sg:province":"Antwerpen",
    "sg:tags":[
        "grocer"
    ],
    "wof:name":"Voedingsmarkt Nv Bastijns",
    "wof:placetype":"venue"
},
  "geometry": {"coordinates":[4.4216828346,51.2200164795],"type":"Point"}
}