{
  "type": "Feature",
  "properties": {
    "addr:full":"Vlieghavenlaan 69 Keerbergen Vlaams-Brabant 3140",
    "addr:housenumber":"69",
    "addr:postcode":"3140",
    "addr:street":"Vlieghavenlaan",
    "iso:country":"BE",
    "sg:address":"Vlieghavenlaan 69",
    "sg:city":"Keerbergen",
    "sg:orig_category":"Artsen and specialisten",
    "sg:phone":"+32 15 23 62 59",
    "sg:postcode":"3140",
    "sg:province":"Vlaams-Brabant",
    "wof:name":"Gilbert Vanderborght",
    "wof:placetype":"venue"
},
  "geometry": {"coordinates":[4.6779880524,51.0062141418],"type":"Point"}
}