{
  "type": "Feature",
  "properties": {
    "addr:full":"Kerkeblok 48 Herentals (noorderwijk) Antwerpen 2200",
    "addr:housenumber":"48",
    "addr:postcode":"2200",
    "addr:street":"Kerkeblok",
    "iso:country":"BE",
    "sg:address":"Kerkeblok 48",
    "sg:city":"Herentals (noorderwijk)",
    "sg:classifiers":[
        {
            "category":"Government",
            "subcategory":"Fire Station",
            "type":"Public Place"
        }
    ],
    "sg:phone":"+32 14 26 56 99",
    "sg:postcode":"2200",
    "sg:province":"Antwerpen",
    "sg:tags":[
        "water",
        "restoration",
        "damage"
    ],
    "wof:name":"Technische Expertise Consulting En Onderhoudmanagement",
    "wof:placetype":"venue"
},
  "geometry": {"coordinates":[4.8452181816,51.1386070251],"type":"Point"}
}