{
  "type": "Feature",
  "properties": {
    "addr:full":"Avenue Fran\u00c7ois Cornesse 63 Aywaille Li\u00e8ge 4920",
    "addr:housenumber":"63",
    "addr:postcode":"4920",
    "addr:street":"Avenue Franc\u0327Ois Cornesse",
    "iso:country":"BE",
    "sg:address":"Avenue Fran\u00c7ois Cornesse 63",
    "sg:city":"Aywaille",
    "sg:orig_category":"Enseignement maternel and primaire",
    "sg:phone":"+32 4 384 48 51",
    "sg:postcode":"4920",
    "sg:province":"Li\u00e8ge",
    "wof:name":"Ecole Primaire Libre",
    "wof:placetype":"venue"
},
  "geometry": {"coordinates":[5.6707987785,50.473991394],"type":"Point"}
}