{
  "type": "Feature",
  "properties": {
    "addr:full":"Marktstraat 102 Kortrijk (marke) West-Vlaanderen 8510",
    "addr:housenumber":"102",
    "addr:postcode":"8510",
    "addr:street":"Marktstraat",
    "iso:country":"BE",
    "sg:address":"Marktstraat 102",
    "sg:city":"Kortrijk (marke)",
    "sg:classifiers":[
        {
            "category":"Personal",
            "subcategory":"Beauty Salon",
            "type":"Services"
        }
    ],
    "sg:phone":"+32 56 21 36 80",
    "sg:postcode":"8510",
    "sg:province":"West-Vlaanderen",
    "sg:tags":[
        "lady",
        "-",
        "hairdressing"
    ],
    "wof:name":"Charmy",
    "wof:placetype":"venue"
},
  "geometry": {"coordinates":[3.234926939,50.8092956543],"type":"Point"}
}