{
  "type": "Feature",
  "properties": {
    "addr:full":"Fonteinstraat 16bb Sint-genesius-rode/rhode-saint-genese Vlaams-Brabant 1640",
    "addr:housenumber":"16bb",
    "addr:postcode":"1640",
    "addr:street":"Fonteinstraat",
    "iso:country":"BE",
    "sg:address":"Fonteinstraat 16bb",
    "sg:city":"Sint-genesius-rode/rhode-saint-genese",
    "sg:orig_category":"Slagers",
    "sg:phone":"+32 2 380 23 10",
    "sg:postcode":"1640",
    "sg:province":"Vlaams-Brabant",
    "wof:name":"Renmans",
    "wof:placetype":"venue"
},
  "geometry": {"coordinates":[4.3441500664,50.7446784973],"type":"Point"}
}