{
  "type": "Feature",
  "properties": {
    "addr:full":"Sint-jobstraat 57 Heusden-zolder (zolder) Limburg 3550",
    "addr:housenumber":"57",
    "addr:postcode":"3550",
    "addr:street":"Sint-Jobstraat",
    "iso:country":"BE",
    "sg:address":"Sint-jobstraat 57",
    "sg:city":"Heusden-zolder (zolder)",
    "sg:classifiers":[
        {
            "category":"Professional",
            "subcategory":"Testing Lab",
            "type":"Services"
        }
    ],
    "sg:phone":"+32 11 85 18 62",
    "sg:postcode":"3550",
    "sg:province":"Limburg",
    "sg:tags":[
        "chemist"
    ],
    "wof:name":"Baudewyn A",
    "wof:placetype":"venue"
},
  "geometry": {"coordinates":[5.2736678123,50.9888916016],"type":"Point"}
}