{
  "type": "Feature",
  "properties": {
    "iso:country":"BE",
    "sg:address":"Rue Marie Depage 62",
    "sg:city":"Ukkel/uccle",
    "sg:classifiers":[
        {
            "category":"Taxi",
            "type":"Transportation"
        }
    ],
    "sg:phone":"+32 2 344 86 07",
    "sg:postcode":"1180",
    "sg:province":"Bruxelles-Capitale",
    "wof:name":"Shakeb",
    "wof:placetype":"venue"
},
  "geometry": {"coordinates":[4.35912323,50.8143196106],"type":"Point"}
}