{
  "type": "Feature",
  "properties": {
    "addr:full":"Rue Saint-jean 31 Arlon Luxembourg 6700",
    "addr:housenumber":"31",
    "addr:postcode":"6700",
    "addr:street":"Rue Saint-Jean",
    "iso:country":"BE",
    "sg:address":"Rue Saint-jean 31",
    "sg:city":"Arlon",
    "sg:orig_category":"Non-Classified Establishments",
    "sg:phone":"+32 63 22 44 00",
    "sg:postcode":"6700",
    "sg:province":"Luxembourg",
    "wof:name":"Hanzen J Sprl",
    "wof:placetype":"venue"
},
  "geometry": {"coordinates":[5.8189458847,49.6834526062],"type":"Point"}
}