{
  "type": "Feature",
  "properties": {
    "iso:country":"BE",
    "sg:address":"Rue De La Sablonni\u00e8re 9-11",
    "sg:city":"Bruxelles",
    "sg:classifiers":[
        {
            "category":"Travel",
            "subcategory":"Hotels & Motels",
            "type":"Entertainment"
        }
    ],
    "sg:phone":"+32 2 223 33 59",
    "sg:postcode":"1000",
    "sg:province":"Bruxelles-Capitale",
    "wof:name":"R\u00e9sidence Sablonni\u00e8re",
    "wof:placetype":"venue"
},
  "geometry": {"coordinates":[4.3657598495,50.8520965576],"type":"Point"}
}