{
  "type": "Feature",
  "properties": {
    "addr:full":"Rode Kruislaan 152 Bilzen (grote-spouwen) Limburg 3740",
    "addr:housenumber":"152",
    "addr:postcode":"3740",
    "addr:street":"Rode Kruislaan",
    "iso:country":"BE",
    "sg:address":"Rode Kruislaan 152",
    "sg:city":"Bilzen (grote-spouwen)",
    "sg:classifiers":[
        {
            "category":"Building & Trades",
            "subcategory":"Construction",
            "type":"Services"
        }
    ],
    "sg:phone":"+32 12 45 43 13",
    "sg:postcode":"3740",
    "sg:province":"Limburg",
    "sg:tags":[
        "industrial",
        "design"
    ],
    "wof:name":"Thysen Design & Engineering",
    "wof:placetype":"venue"
},
  "geometry": {"coordinates":[5.5520801544,50.8363609314],"type":"Point"}
}