{
  "type": "Feature",
  "properties": {
    "addr:full":"Bredabaan 103 Wuustwezel Antwerpen 2990",
    "addr:housenumber":"103",
    "addr:postcode":"2990",
    "addr:street":"Bredabaan",
    "iso:country":"BE",
    "sg:address":"Bredabaan 103",
    "sg:city":"Wuustwezel",
    "sg:classifiers":[
        {
            "category":"Personal",
            "subcategory":"Beauty Salon",
            "type":"Services"
        }
    ],
    "sg:phone":"+32 3 669 68 50",
    "sg:postcode":"2990",
    "sg:province":"Antwerpen",
    "sg:tags":[
        "lady",
        "-",
        "hairdressing"
    ],
    "wof:name":"Francine",
    "wof:placetype":"venue"
},
  "geometry": {"coordinates":[4.6177201271,51.4174003601],"type":"Point"}
}