{
  "type": "Feature",
  "properties": {
    "addr:full":"Prinsenbos 160 Halle Vlaams-Brabant 1502",
    "addr:housenumber":"160;1502",
    "iso:country":"BE",
    "sg:address":"Prinsenbos 160",
    "sg:city":"Halle",
    "sg:orig_category":"M\u00e9decins and sp\u00e9cialistes",
    "sg:phone":"+32 2 356 11 34",
    "sg:postcode":"1502",
    "sg:province":"Vlaams-Brabant",
    "wof:name":"L. Van Parys",
    "wof:placetype":"venue"
},
  "geometry": {"coordinates":[4.2153401375,50.7194137573],"type":"Point"}
}