{
  "type": "Feature",
  "properties": {
    "addr:full":"Brugsestraat 7 Oostkamp West-Vlaanderen 8020",
    "addr:housenumber":"7",
    "addr:postcode":"8020",
    "addr:street":"Brugsestraat",
    "iso:country":"BE",
    "sg:address":"Brugsestraat 7",
    "sg:city":"Oostkamp",
    "sg:classifiers":[
        {
            "category":"Home & Garden",
            "subcategory":"Household Appliances",
            "type":"Retail Goods"
        }
    ],
    "sg:phone":"+32 50 82 38 18",
    "sg:postcode":"8020",
    "sg:province":"West-Vlaanderen",
    "sg:tags":[
        "repair",
        "mainten",
        "-",
        "electric"
    ],
    "wof:name":"Deva Elektro Bvba",
    "wof:placetype":"venue"
},
  "geometry": {"coordinates":[3.2356328964,51.155544281],"type":"Point"}
}