{
  "type": "Feature",
  "properties": {
    "iso:country":"BE",
    "sg:address":"Rue Astrid 62-64",
    "sg:city":"P\u00e9ruwelz",
    "sg:classifiers":[
        {
            "category":"Restaurant",
            "type":"Food & Drink"
        }
    ],
    "sg:phone":"+32 69 77 57 34",
    "sg:postcode":"7600",
    "sg:province":"Hainaut",
    "wof:name":"Pizzarella",
    "wof:placetype":"venue"
},
  "geometry": {"coordinates":[3.591780901,50.5129318237],"type":"Point"}
}