{
  "type": "Feature",
  "properties": {
    "addr:full":"Iepersestraat 225 Roeselare West-Vlaanderen 8800",
    "addr:housenumber":"225",
    "addr:postcode":"8800",
    "addr:street":"Iepersestraat",
    "iso:country":"BE",
    "sg:address":"Iepersestraat 225",
    "sg:city":"Roeselare",
    "sg:classifiers":[
        {
            "category":"Bars & Pubs",
            "type":"Food & Drink"
        }
    ],
    "sg:phone":"+32 51 24 00 50",
    "sg:postcode":"8800",
    "sg:province":"West-Vlaanderen",
    "wof:name":"Rustoord ('t)",
    "wof:placetype":"venue"
},
  "geometry": {"coordinates":[3.1134800911,50.9389724731],"type":"Point"}
}