{
  "type": "Feature",
  "properties": {
    "iso:country":"BE",
    "sg:address":"Gebroeders Legrainlaan 101",
    "sg:city":"Sint-pieters-woluwe/woluwe-saint-pierre",
    "sg:orig_category":"Slagers",
    "sg:phone":"+32 2 660 30 71",
    "sg:postcode":"1150",
    "sg:province":"Bruxelles-Capitale",
    "wof:name":"Slagerij Peter & Sabine",
    "wof:placetype":"venue"
},
  "geometry": {"coordinates":[4.4125351906,50.825969696],"type":"Point"}
}