{
  "type": "Feature",
  "properties": {
    "iso:country":"BE",
    "sg:address":"Square Sainctelette 19",
    "sg:city":"Bruxelles",
    "sg:classifiers":[
        {
            "category":"Organizations",
            "subcategory":"Non-profit Organization",
            "type":"Services"
        }
    ],
    "sg:phone":"+32 2 201 09 15",
    "sg:postcode":"1000",
    "sg:province":"Bruxelles-Capitale",
    "sg:tags":[
        "international",
        "organisation"
    ],
    "wof:name":"Ietm",
    "wof:placetype":"venue"
},
  "geometry": {"coordinates":[4.3479962349,50.8586502075],"type":"Point"}
}