{
  "type": "Feature",
  "properties": {
    "addr:full":"Engelstraat 136ba Gent Oost-Vlaanderen 9040",
    "addr:housenumber":"136ba",
    "addr:postcode":"9040",
    "addr:street":"Engelstraat;Oost-Vlaanderen",
    "iso:country":"BE",
    "sg:address":"Engelstraat 136ba",
    "sg:city":"Gent",
    "sg:orig_category":"Artsen and specialisten",
    "sg:phone":"+32 9 228 04 44",
    "sg:postcode":"9040",
    "sg:province":"Oost-Vlaanderen",
    "wof:name":"Thisbe Vanrijsselberghe",
    "wof:placetype":"venue"
},
  "geometry": {"coordinates":[3.7511720657,51.0528945923],"type":"Point"}
}