{
  "type": "Feature",
  "properties": {
    "iso:country":"BE",
    "sg:address":"Europalaan 27",
    "sg:city":"Lichtervelde",
    "sg:classifiers":[
        {
            "category":"Professional",
            "subcategory":"Art Services",
            "type":"Services"
        }
    ],
    "sg:phone":"+32 51 72 67 39",
    "sg:postcode":"8810",
    "sg:province":"West-Vlaanderen",
    "sg:tags":[
        "photographer"
    ],
    "wof:name":"Foto Kurt",
    "wof:placetype":"venue"
},
  "geometry": {"coordinates":[3.1256430149,51.0277023315],"type":"Point"}
}