{
  "type": "Feature",
  "properties": {
    "iso:country":"BE",
    "sg:address":"Rue De Maestricht 1",
    "sg:city":"Herve",
    "sg:orig_category":"Epiceries",
    "sg:phone":"+32 87 67 44 42",
    "sg:postcode":"4651",
    "sg:province":"Li\u00e8ge",
    "wof:name":"Maison Dormans-kroonen",
    "wof:placetype":"venue"
},
  "geometry": {"coordinates":[5.8162698746,50.6495094299],"type":"Point"}
}