{
  "type": "Feature",
  "properties": {
    "iso:country":"BE",
    "sg:address":"Damsevaart - Noord 34",
    "sg:city":"Damme",
    "sg:orig_category":"H\u00f4tels. Restaurants",
    "sg:phone":"+32 50 62 30 40",
    "sg:postcode":"8340",
    "sg:province":"West-Vlaanderen",
    "wof:name":"Welkom",
    "wof:placetype":"venue"
},
  "geometry": {"coordinates":[3.3379070759,51.2922935486],"type":"Point"}
}