{
  "type": "Feature",
  "properties": {
    "addr:full":"Loddershoekstraat 3 Ternat Vlaams-Brabant 1741",
    "addr:housenumber":"3",
    "addr:postcode":"1741",
    "addr:street":"Loddershoekstraat",
    "iso:country":"BE",
    "sg:address":"Loddershoekstraat 3",
    "sg:city":"Ternat",
    "sg:orig_category":"Woningbouw",
    "sg:phone":"+32 2 582 71 67",
    "sg:postcode":"1741",
    "sg:province":"Vlaams-Brabant",
    "wof:name":"Dakran",
    "wof:placetype":"venue"
},
  "geometry": {"coordinates":[4.1424269676,50.8601417542],"type":"Point"}
}