{
  "type": "Feature",
  "properties": {
    "addr:full":"Mechelsesteenweg 120 Sint-katelijne-waver Antwerpen 2860",
    "addr:housenumber":"120",
    "addr:postcode":"2860",
    "addr:street":"Mechelsesteenweg",
    "iso:country":"BE",
    "sg:address":"Mechelsesteenweg 120",
    "sg:city":"Sint-katelijne-waver",
    "sg:orig_category":"Groenten and fruit Gh",
    "sg:phone":"+32 15 55 20 58",
    "sg:postcode":"2860",
    "sg:province":"Antwerpen",
    "wof:name":"Jacques Remy & Fils",
    "wof:placetype":"venue"
},
  "geometry": {"coordinates":[4.5251097679,51.0579872131],"type":"Point"}
}