{
  "type": "Feature",
  "properties": {
    "addr:full":"Rue De La Station 13 Bouillon Luxembourg 6830",
    "addr:housenumber":"13",
    "addr:postcode":"6830",
    "addr:street":"Rue De La Station",
    "iso:country":"BE",
    "sg:address":"Rue De La Station 13",
    "sg:city":"Bouillon",
    "sg:classifiers":[
        {
            "category":"Restaurant",
            "type":"Food & Drink"
        }
    ],
    "sg:phone":"+32 61 46 64 20",
    "sg:postcode":"6830",
    "sg:province":"Luxembourg",
    "wof:name":"Aux Armes De Bouillon",
    "wof:placetype":"venue"
},
  "geometry": {"coordinates":[5.0676159859,49.7910804749],"type":"Point"}
}