{
  "type": "Feature",
  "properties": {
    "addr:full":"Sint-elooistraat 49 Staden West-Vlaanderen 8840",
    "addr:housenumber":"49",
    "addr:postcode":"8840",
    "addr:street":"Sint-Elooistraat",
    "iso:country":"BE",
    "sg:address":"Sint-elooistraat 49",
    "sg:city":"Staden",
    "sg:orig_category":"Rev\u00eatements pour sols and murs. Construction de maisons",
    "sg:phone":"+32 51 70 10 67",
    "sg:postcode":"8840",
    "sg:province":"West-Vlaanderen",
    "wof:name":"Bouttelisier G.",
    "wof:placetype":"venue"
},
  "geometry": {"coordinates":[2.9876549244,50.9422340393],"type":"Point"}
}