{
  "type": "Feature",
  "properties": {
    "iso:country":"BE",
    "sg:address":"Diestsesteenweg 10",
    "sg:city":"Leuven",
    "sg:orig_category":"Magasins de r\u00e9parations d'articles personnels et m\u00e9nagers divers",
    "sg:phone":"+32 16 25 49 60",
    "sg:postcode":"3010",
    "sg:province":"Vlaams-Brabant",
    "wof:name":"De Knip",
    "wof:placetype":"venue"
},
  "geometry": {"coordinates":[4.7140917778,50.8826522827],"type":"Point"}
}