{
  "type": "Feature",
  "properties": {
    "addr:full":"Dopheide 12 Leopoldsburg Limburg 3970",
    "addr:housenumber":"12",
    "addr:postcode":"3970",
    "addr:street":"Dopheide",
    "iso:country":"BE",
    "sg:address":"Dopheide 12",
    "sg:city":"Leopoldsburg",
    "sg:classifiers":[
        {
            "category":"Professional",
            "subcategory":"Computer Services",
            "type":"Services"
        }
    ],
    "sg:phone":"+32 11 40 11 50",
    "sg:postcode":"3970",
    "sg:province":"Limburg",
    "sg:tags":[
        "webdesign",
        "-",
        "internet"
    ],
    "wof:name":"Fiction Industries",
    "wof:placetype":"venue"
},
  "geometry": {"coordinates":[5.25025177,51.1168861389],"type":"Point"}
}