{
  "type": "Feature",
  "properties": {
    "addr:full":"Driehoekstraat 42ba Brakel Oost-Vlaanderen 9660",
    "addr:housenumber":"42ba",
    "addr:postcode":"9660",
    "addr:street":"Driehoekstraat",
    "iso:country":"BE",
    "sg:address":"Driehoekstraat 42ba",
    "sg:city":"Brakel",
    "sg:orig_category":"Enseignement maternel and primaire",
    "sg:phone":"+32 55 42 35 79",
    "sg:postcode":"9660",
    "sg:province":"Oost-Vlaanderen",
    "wof:name":"Vrije Lagere School",
    "wof:placetype":"venue"
},
  "geometry": {"coordinates":[3.7642800808,50.8063163757],"type":"Point"}
}