{
  "type": "Feature",
  "properties": {
    "addr:full":"Petunialaan 13 Middelkerke West-Vlaanderen 8430",
    "addr:housenumber":"13",
    "addr:postcode":"8430",
    "addr:street":"Petunialaan",
    "iso:country":"BE",
    "sg:address":"Petunialaan 13",
    "sg:city":"Middelkerke",
    "sg:classifiers":[
        {
            "category":"Health Services",
            "subcategory":"Health Practitioner",
            "type":"Services"
        }
    ],
    "sg:phone":"+32 59 30 21 41",
    "sg:postcode":"8430",
    "sg:province":"West-Vlaanderen",
    "sg:tags":[
        "therapist",
        "speech"
    ],
    "wof:name":"Goethals C",
    "wof:placetype":"venue"
},
  "geometry": {"coordinates":[2.8148229122,51.1843948364],"type":"Point"}
}