{
  "type": "Feature",
  "properties": {
    "addr:full":"Rue Saint-jacques 35 Tournai Hainaut 7500",
    "addr:housenumber":"35",
    "addr:postcode":"7500",
    "addr:street":"Rue Saint-Jacques",
    "iso:country":"BE",
    "sg:address":"Rue Saint-jacques 35",
    "sg:city":"Tournai",
    "sg:orig_category":"Auto-\u00e9coles",
    "sg:phone":"+32 69 22 30 50",
    "sg:postcode":"7500",
    "sg:province":"Hainaut",
    "wof:name":"Auto-ecole Cath\u00c9drale",
    "wof:placetype":"venue"
},
  "geometry": {"coordinates":[3.3835580349,50.6096763611],"type":"Point"}
}