{
  "type": "Feature",
  "properties": {
    "addr:full":"Sint-denijsestraat 103 Kortrijk West-Vlaanderen 8500",
    "addr:housenumber":"103",
    "addr:postcode":"8500",
    "iso:country":"BE",
    "sg:address":"Sint-denijsestraat 103",
    "sg:city":"Kortrijk",
    "sg:orig_category":"Slagers",
    "sg:phone":"+32 56 25 82 07",
    "sg:postcode":"8500",
    "sg:province":"West-Vlaanderen",
    "wof:name":"Renmans",
    "wof:placetype":"venue"
},
  "geometry": {"coordinates":[3.2736001015,50.8206596375],"type":"Point"}
}