{
  "type": "Feature",
  "properties": {
    "addr:full":"Heuvellandseweg 3 Poperinge West-Vlaanderen 8970",
    "addr:housenumber":"3",
    "addr:postcode":"8970",
    "addr:street":"Heuvellandseweg",
    "iso:country":"BE",
    "sg:address":"Heuvellandseweg 3",
    "sg:city":"Poperinge",
    "sg:orig_category":"Eleveurs de bovins. Eleveurs and marchands de porcs",
    "sg:phone":"+32 57 33 50 59",
    "sg:postcode":"8970",
    "sg:province":"West-Vlaanderen",
    "wof:name":"Yvan Couemaeker",
    "wof:placetype":"venue"
},
  "geometry": {"coordinates":[2.7263898849,50.8555984497],"type":"Point"}
}