{
  "type": "Feature",
  "properties": {
    "addr:full":"Rue Eugene Dubois 3 La Louviere Hainaut 7100",
    "addr:housenumber":"3",
    "addr:postcode":"7100",
    "addr:street":"Rue Eugene Dubois",
    "iso:country":"BE",
    "sg:address":"Rue Eugene Dubois 3",
    "sg:city":"La Louviere",
    "sg:orig_category":"Journaux. Tabac",
    "sg:phone":"+32 64 21 18 91",
    "sg:postcode":"7100",
    "sg:province":"Hainaut",
    "wof:name":"Librairie La Croy\u00c8re",
    "wof:placetype":"venue"
},
  "geometry": {"coordinates":[4.2022900581,50.4899520874],"type":"Point"}
}