{
  "type": "Feature",
  "properties": {
    "addr:full":"Chemin Avijl 40 Bruxelles (uccle) Bruxelles-Capitale 1180",
    "addr:housenumber":"40",
    "addr:postcode":"1180",
    "addr:street":"Chemin Avijl",
    "iso:country":"BE",
    "sg:address":"Chemin Avijl 40",
    "sg:city":"Bruxelles (uccle)",
    "sg:classifiers":[
        {
            "category":"Social Services",
            "subcategory":"Job Training",
            "type":"Services"
        }
    ],
    "sg:phone":"+32 2 539 02 95",
    "sg:postcode":"1180",
    "sg:province":"Bruxelles-Capitale",
    "sg:tags":[
        "interpreter"
    ],
    "wof:name":"Onofrei A",
    "wof:placetype":"venue"
},
  "geometry": {"coordinates":[4.364511013,50.7922706604],"type":"Point"}
}