{
  "type": "Feature",
  "properties": {
    "addr:full":"Rue Jean Chot 64 Viroinval (olloy-sur-viroin) Namur 5670",
    "addr:housenumber":"64",
    "addr:postcode":"5670",
    "addr:street":"Rue Jean Chot",
    "iso:country":"BE",
    "sg:address":"Rue Jean Chot 64",
    "sg:city":"Viroinval (olloy-sur-viroin)",
    "sg:classifiers":[
        {
            "category":"Recreation",
            "subcategory":"Arcade",
            "type":"Entertainment"
        }
    ],
    "sg:phone":"+32 60 39 04 04",
    "sg:postcode":"5670",
    "sg:province":"Namur",
    "sg:tags":[
        "machine",
        "amusement"
    ],
    "wof:name":"Henry B",
    "wof:placetype":"venue"
},
  "geometry": {"coordinates":[4.6017241478,50.07371521],"type":"Point"}
}