{
  "type": "Feature",
  "properties": {
    "addr:full":"Heerweg 3 Sint-gillis-waas (sint-pauwels) Oost-Vlaanderen 9170",
    "addr:housenumber":"3",
    "addr:postcode":"9170",
    "addr:street":"Heerweg;Sint-Pauwels",
    "iso:country":"BE",
    "sg:address":"Heerweg 3",
    "sg:city":"Sint-gillis-waas (sint-pauwels)",
    "sg:classifiers":[
        {
            "category":"Farming",
            "subcategory":"Crops",
            "type":"Manufacturing & Wholesale Goods"
        }
    ],
    "sg:phone":"+32 3 770 67 65",
    "sg:postcode":"9170",
    "sg:province":"Oost-Vlaanderen",
    "sg:tags":[
        "vegetable",
        "fruit",
        "-",
        "grower"
    ],
    "wof:name":"Oelbrandt R",
    "wof:placetype":"venue"
},
  "geometry": {"coordinates":[4.0967259407,51.2072677612],"type":"Point"}
}