{
  "type": "Feature",
  "properties": {
    "iso:country":"BE",
    "sg:address":"Postweg 2",
    "sg:city":"Vlezenbeek",
    "sg:classifiers":[
        {
            "category":"Food & Beverages",
            "subcategory":"Bakery",
            "type":"Retail Goods"
        }
    ],
    "sg:phone":"+32 2 426 12 42",
    "sg:postcode":"1602",
    "sg:province":"Vlaams-Brabant",
    "sg:tags":[
        "biscuit"
    ],
    "wof:name":"Astrio Biscuiterie S.a.",
    "wof:placetype":"venue"
},
  "geometry": {"coordinates":[4.2587618828,50.8138389587],"type":"Point"}
}