{
  "type": "Feature",
  "properties": {
    "iso:country":"BE",
    "sg:address":"Stevennekens 161",
    "sg:city":"Rijkevorsel",
    "sg:classifiers":[
        {
            "category":"Shopping",
            "subcategory":"Stationery & Office Supplies",
            "type":"Retail Goods"
        }
    ],
    "sg:phone":"+32 3 314 43 15",
    "sg:postcode":"2310",
    "sg:province":"Antwerpen",
    "sg:tags":[
        "partition"
    ],
    "wof:name":"Lb-plafonds",
    "wof:placetype":"venue"
},
  "geometry": {"coordinates":[4.7701501846,51.3403816223],"type":"Point"}
}