{
  "type": "Feature",
  "properties": {
    "iso:country":"BE",
    "sg:address":"Bordiaustraat 13",
    "sg:city":"Brussel/bruxelles",
    "sg:orig_category":"Diverse bouwafwerking and reiniging Gespecialiseerde residenti\u00eble bouw Woningbouw",
    "sg:phone":"+32 2 733 59 43",
    "sg:postcode":"1000",
    "sg:province":"Bruxelles-Capitale",
    "wof:name":"Facabel",
    "wof:placetype":"venue"
},
  "geometry": {"coordinates":[4.388669014,50.8475494385],"type":"Point"}
}