{
  "type": "Feature",
  "properties": {
    "iso:country":"BE",
    "sg:address":"Stationsplein 12",
    "sg:city":"Lokeren",
    "sg:classifiers":[
        {
            "category":"Shopping",
            "subcategory":"Gifts & Souvenirs",
            "type":"Retail Goods"
        }
    ],
    "sg:phone":"+32 9 348 70 84",
    "sg:postcode":"9160",
    "sg:province":"Oost-Vlaanderen",
    "sg:tags":[
        "-"
    ],
    "wof:name":"Potterije (de)",
    "wof:placetype":"venue"
},
  "geometry": {"coordinates":[3.9877939224,51.1059646606],"type":"Point"}
}