{
  "type": "Feature",
  "properties": {
    "iso:country":"BE",
    "sg:address":"Kardinaal Cardijnlaan 17",
    "sg:city":"Zoersel",
    "sg:orig_category":"Elektrische installaties voor woningen Huishoudapparaten, televisies and radio's",
    "sg:phone":"+32 3 383 61 77",
    "sg:postcode":"2980",
    "sg:province":"Antwerpen",
    "wof:name":"Victor Willems",
    "wof:placetype":"venue"
},
  "geometry": {"coordinates":[4.6260309219,51.2697792053],"type":"Point"}
}