{
  "type": "Feature",
  "properties": {
    "iso:country":"BE",
    "sg:address":"Rue Saint-gilles 353ba/34",
    "sg:city":"Li\u00c8ge",
    "sg:orig_category":"Herstelling and restauratie van meubelen",
    "sg:phone":"+32 4 253 30 07",
    "sg:postcode":"4000",
    "sg:province":"Li\u00e8ge",
    "wof:name":"Philippe Guillemin",
    "wof:placetype":"venue"
},
  "geometry": {"coordinates":[5.5508499146,50.633518219],"type":"Point"}
}