{
  "type": "Feature",
  "properties": {
    "iso:country":"BE",
    "sg:address":"Lomre 10b",
    "sg:city":"Montleban",
    "sg:classifiers":[
        {
            "category":"Professional",
            "subcategory":"Business Services",
            "type":"Services"
        }
    ],
    "sg:phone":"+32 80 51 77 70",
    "sg:postcode":"6674",
    "sg:province":"Luxembourg",
    "sg:tags":[
        "marketing",
        "agency"
    ],
    "wof:name":"Syne & Partners S.c.",
    "wof:placetype":"venue"
},
  "geometry": {"coordinates":[5.8349738121,50.202041626],"type":"Point"}
}