{
  "type": "Feature",
  "properties": {
    "addr:full":"Ijzerenkruisstraat 25b28 Sint-truiden Limburg 3800",
    "addr:housenumber":"25b28",
    "addr:postcode":"3800",
    "addr:street":"Ijzerenkruisstraat",
    "iso:country":"BE",
    "sg:address":"Ijzerenkruisstraat 25b28",
    "sg:city":"Sint-truiden",
    "sg:orig_category":"Dranken",
    "sg:phone":"+32 11 67 45 95",
    "sg:postcode":"3800",
    "sg:province":"Limburg",
    "wof:name":"Fa. Thijs",
    "wof:placetype":"venue"
},
  "geometry": {"coordinates":[5.2542028427,50.8223190308],"type":"Point"}
}