{
  "type": "Feature",
  "properties": {
    "iso:country":"BE",
    "sg:address":"Basilix Shopping Center",
    "sg:city":"Bruxelles (berchem-sainte-agathe)",
    "sg:classifiers":[
        {
            "category":"Shopping",
            "subcategory":"Clothing, Apparel, & Fashions",
            "type":"Retail Goods"
        }
    ],
    "sg:phone":"+32 2 468 24 57",
    "sg:postcode":"1082",
    "sg:province":"Bruxelles-Capitale",
    "sg:tags":[
        "lady",
        "clothing",
        "-"
    ],
    "wof:name":"Werly",
    "wof:placetype":"venue"
},
  "geometry": {"coordinates":[4.2954311371,50.8645133972],"type":"Point"}
}