{
  "type": "Feature",
  "properties": {
    "addr:full":"Mechelbaan 676a Putte Antwerpen 2580",
    "addr:housenumber":"676a",
    "addr:postcode":"2580",
    "addr:street":"Mechelbaan",
    "iso:country":"BE",
    "sg:address":"Mechelbaan 676a",
    "sg:city":"Putte",
    "sg:classifiers":[
        {
            "category":"Insurance",
            "subcategory":"Insurance Agent",
            "type":"Services"
        }
    ],
    "sg:phone":"+32 15 75 60 95",
    "sg:postcode":"2580",
    "sg:province":"Antwerpen",
    "sg:tags":[
        "broker"
    ],
    "wof:name":"Dockx Zakenkantoor",
    "wof:placetype":"venue"
},
  "geometry": {"coordinates":[4.58725214,51.0387954712],"type":"Point"}
}