{
  "type": "Feature",
  "properties": {
    "iso:country":"BE",
    "sg:address":"Adegemdorp 15",
    "sg:city":"Maldegem",
    "sg:classifiers":[
        {
            "category":"Cafe",
            "type":"Food & Drink"
        }
    ],
    "sg:phone":"+32 50 71 14 19",
    "sg:postcode":"9991",
    "sg:province":"Oost-Vlaanderen",
    "sg:tags":[
        "caf\u00e9s"
    ],
    "wof:name":"Caf\u00c9 Damberd",
    "wof:placetype":"venue"
},
  "geometry": {"coordinates":[3.4865539074,51.2028541565],"type":"Point"}
}