{
  "type": "Feature",
  "properties": {
    "addr:full":"Kattenberg 118 Kasterlee Antwerpen 2460",
    "addr:housenumber":"118",
    "addr:postcode":"2460",
    "addr:street":"Kattenberg",
    "iso:country":"BE",
    "sg:address":"Kattenberg 118",
    "sg:city":"Kasterlee",
    "sg:classifiers":[
        {
            "category":"Freight",
            "type":"Transportation"
        }
    ],
    "sg:phone":"+32 475 65 47 26",
    "sg:postcode":"2460",
    "sg:province":"Antwerpen",
    "sg:tags":[
        "-",
        "transport"
    ],
    "wof:name":"Pelgroms Bvba",
    "wof:placetype":"venue"
},
  "geometry": {"coordinates":[4.9664092064,51.2560157776],"type":"Point"}
}