{
  "type": "Feature",
  "properties": {
    "iso:country":"BE",
    "sg:address":"Rue Albert Ier 191",
    "sg:city":"Erquelinnes",
    "sg:classifiers":[
        {
            "category":"Wholesale",
            "subcategory":"Sporting Goods",
            "type":"Manufacturing & Wholesale Goods"
        }
    ],
    "sg:phone":"+32 71 55 52 25",
    "sg:postcode":"6560",
    "sg:province":"Hainaut",
    "sg:tags":[
        "sport-",
        "kampeermateriaal"
    ],
    "wof:name":"Maison Larbasports",
    "wof:placetype":"venue"
},
  "geometry": {"coordinates":[4.1159200668,50.3059844971],"type":"Point"}
}