{
  "type": "Feature",
  "properties": {
    "iso:country":"BE",
    "sg:address":"Rue Grande 39",
    "sg:city":"Grace-hollogne",
    "sg:orig_category":"Cr\u00e9dits divers",
    "sg:postcode":"4460",
    "sg:province":"Li\u00e8ge",
    "wof:name":"Postomat Grace-hollogne",
    "wof:placetype":"venue"
},
  "geometry": {"coordinates":[5.4756789207,50.6340446472],"type":"Point"}
}