{
  "type": "Feature",
  "properties": {
    "iso:country":"BE",
    "sg:address":"Huiseplein 21",
    "sg:city":"Zingem (huise)",
    "sg:classifiers":[
        {
            "category":"Professional",
            "subcategory":"Testing Lab",
            "type":"Services"
        }
    ],
    "sg:phone":"+32 9 383 75 19",
    "sg:postcode":"9750",
    "sg:province":"Oost-Vlaanderen",
    "sg:tags":[
        "chemist"
    ],
    "wof:name":"Van Poucke G",
    "wof:placetype":"venue"
},
  "geometry": {"coordinates":[3.5907399654,50.8996810913],"type":"Point"}
}