{
  "type": "Feature",
  "properties": {
    "iso:country":"BE",
    "sg:address":"Rue Du Canada 13",
    "sg:city":"Vorst/forest",
    "sg:orig_category":"Avocats and conseillers juridiques",
    "sg:phone":"+32 2 534 83 81",
    "sg:postcode":"1190",
    "sg:province":"Bruxelles-Capitale",
    "wof:name":"Fran\u00c7ois De Grave",
    "wof:placetype":"venue"
},
  "geometry": {"coordinates":[4.3355779648,50.826625824],"type":"Point"}
}