{
  "type": "Feature",
  "properties": {
    "iso:country":"BE",
    "sg:address":"Rue Albert I 96",
    "sg:city":"Mettet",
    "sg:classifiers":[
        {
            "category":"Health Services",
            "subcategory":"Health Practitioner",
            "type":"Services"
        }
    ],
    "sg:phone":"+32 71 72 71 68",
    "sg:postcode":"5640",
    "sg:province":"Namur",
    "sg:tags":[
        "physiotherapist"
    ],
    "wof:name":"Houyoux St\u00e9phanie",
    "wof:placetype":"venue"
},
  "geometry": {"coordinates":[4.6565670967,50.325302124],"type":"Point"}
}