{
  "type": "Feature",
  "properties": {
    "addr:full":"Alsembergse Steenweg 1015 Ukkel/uccle Bruxelles-Capitale 1180",
    "addr:housenumber":"1015",
    "addr:postcode":"1180",
    "addr:street":"Alsembergse Steenweg;/",
    "iso:country":"BE",
    "sg:address":"Alsembergse Steenweg 1015",
    "sg:city":"Ukkel/uccle",
    "sg:orig_category":"Foto-uitrusting Fotografen and fotostudio's Secretariaatsdiensten",
    "sg:phone":"+32 2 376 09 00",
    "sg:postcode":"1180",
    "sg:province":"Bruxelles-Capitale",
    "wof:name":"Art & Techn. Photogr. Photo Noir Et Blanc",
    "wof:placetype":"venue"
},
  "geometry": {"coordinates":[4.3348908424,50.7954483032],"type":"Point"}
}