{
  "type": "Feature",
  "properties": {
    "iso:country":"BE",
    "sg:address":"Langestraat 78",
    "sg:city":"Oostende",
    "sg:classifiers":[
        {
            "category":"Fast Food",
            "type":"Food & Drink"
        }
    ],
    "sg:phone":"+32 59 70 94 68",
    "sg:postcode":"8400",
    "sg:province":"West-Vlaanderen",
    "sg:tags":[
        "meeneem",
        "restaurant"
    ],
    "wof:name":"Frituur Old Ham",
    "wof:placetype":"venue"
},
  "geometry": {"coordinates":[2.9184811115,51.233631134],"type":"Point"}
}