{
  "type": "Feature",
  "properties": {
    "addr:full":"Azaleastraat 2 Ardooie West-Vlaanderen 8850",
    "addr:housenumber":"2",
    "addr:postcode":"8850",
    "addr:street":"Azaleastraat",
    "iso:country":"BE",
    "sg:address":"Azaleastraat 2",
    "sg:city":"Ardooie",
    "sg:orig_category":"Sportclubs",
    "sg:phone":"+32 51 74 53 66",
    "sg:postcode":"8850",
    "sg:province":"West-Vlaanderen",
    "wof:name":"W.c. Jong & Moedig",
    "wof:placetype":"venue"
},
  "geometry": {"coordinates":[3.1920979023,50.9791412354],"type":"Point"}
}