{
  "type": "Feature",
  "properties": {
    "iso:country":"BE",
    "sg:address":"Vieux-chemin-de-jupille 96",
    "sg:city":"Beyne-heusay",
    "sg:orig_category":"Installation de menuiserie en bois and plastique",
    "sg:phone":"+32 4 370 63 52",
    "sg:postcode":"4610",
    "sg:province":"Li\u00e8ge",
    "wof:name":"Xavier Forthomme",
    "wof:placetype":"venue"
},
  "geometry": {"coordinates":[5.6526417732,50.6265487671],"type":"Point"}
}