{
  "type": "Feature",
  "properties": {
    "iso:country":"BE",
    "sg:address":"Grote Steenweg 77",
    "sg:city":"Zoutleeuw",
    "sg:orig_category":"Articles de jardin",
    "sg:phone":"+32 11 78 47 74",
    "sg:postcode":"3440",
    "sg:province":"Vlaams-Brabant",
    "wof:name":"Algeno",
    "wof:placetype":"venue"
},
  "geometry": {"coordinates":[5.105910778,50.8081207275],"type":"Point"}
}