{
  "type": "Feature",
  "properties": {
    "addr:full":"Chapelle Aux Splingles 2 Walcourt Namur 5650",
    "addr:housenumber":"2",
    "addr:postcode":"5650",
    "iso:country":"BE",
    "sg:address":"Chapelle Aux Splingles 2",
    "sg:city":"Walcourt",
    "sg:orig_category":"Installatie van houten of kunststof schrijnwerk",
    "sg:phone":"+32 71 61 47 70",
    "sg:postcode":"5650",
    "sg:province":"Namur",
    "wof:name":"Dubois",
    "wof:placetype":"venue"
},
  "geometry": {"coordinates":[4.4313349724,50.2514762878],"type":"Point"}
}