{
  "type": "Feature",
  "properties": {
    "addr:full":"Kwadestraat 62 Roeselare West-Vlaanderen 8800",
    "addr:housenumber":"62",
    "addr:postcode":"8800",
    "addr:street":"Kwadestraat",
    "iso:country":"BE",
    "sg:address":"Kwadestraat 62",
    "sg:city":"Roeselare",
    "sg:orig_category":"Installation \u00e9lectrique r\u00e9sidentielle",
    "sg:phone":"+32 51 24 49 12",
    "sg:postcode":"8800",
    "sg:province":"West-Vlaanderen",
    "wof:name":"Jimmy Vanslambrouck",
    "wof:placetype":"venue"
},
  "geometry": {"coordinates":[3.1230149269,50.9443435669],"type":"Point"}
}