{
  "type": "Feature",
  "properties": {
    "iso:country":"BE",
    "sg:address":"Molendries 1",
    "sg:city":"Aalst",
    "sg:orig_category":"Apotheken",
    "sg:phone":"+32 53 21 10 57",
    "sg:postcode":"9300",
    "sg:province":"Oost-Vlaanderen",
    "wof:name":"Multipharma",
    "wof:placetype":"venue"
},
  "geometry": {"coordinates":[4.0440030098,50.9409751892],"type":"Point"}
}