{
  "type": "Feature",
  "properties": {
    "iso:country":"BE",
    "sg:address":"Vestingstraat 66",
    "sg:city":"Antwerpen",
    "sg:orig_category":"Bijouteries and horlogeries",
    "sg:phone":"+32 3 227 26 56",
    "sg:postcode":"2018",
    "sg:province":"Antwerpen",
    "wof:name":"C & C",
    "wof:placetype":"venue"
},
  "geometry": {"coordinates":[4.4198241234,51.2156448364],"type":"Point"}
}