{
  "type": "Feature",
  "properties": {
    "addr:full":"Meerstraat 1 Anzegem West-Vlaanderen 8573",
    "addr:housenumber":"1",
    "addr:postcode":"8573",
    "addr:street":"Meerstraat",
    "iso:country":"BE",
    "sg:address":"Meerstraat 1",
    "sg:city":"Anzegem",
    "sg:orig_category":"Boomkwekerijen",
    "sg:phone":"+32 56 68 74 77",
    "sg:postcode":"8573",
    "sg:province":"West-Vlaanderen",
    "wof:name":"P. Hellin",
    "wof:placetype":"venue"
},
  "geometry": {"coordinates":[3.4528269768,50.8030815125],"type":"Point"}
}