{
  "type": "Feature",
  "properties": {
    "iso:country":"BE",
    "sg:address":"Overwinningstraat 74",
    "sg:city":"Willebroek",
    "sg:classifiers":[
        {
            "category":"Shopping",
            "subcategory":"Clothing, Apparel, & Fashions",
            "type":"Retail Goods"
        }
    ],
    "sg:phone":"+32 3 866 03 07",
    "sg:postcode":"2830",
    "sg:province":"Antwerpen",
    "sg:tags":[
        "-",
        "clothing",
        "child"
    ],
    "wof:name":"Ken",
    "wof:placetype":"venue"
},
  "geometry": {"coordinates":[4.3596301079,51.0587387085],"type":"Point"}
}