{
  "type": "Feature",
  "properties": {
    "addr:full":"Avenue De L'echevinage 18 Bruxelles (uccle) Bruxelles-Capitale 1180",
    "addr:housenumber":"18",
    "addr:postcode":"1180",
    "addr:street":"Avenue De L'Echevinage",
    "iso:country":"BE",
    "sg:address":"Avenue De L'echevinage 18",
    "sg:city":"Bruxelles (uccle)",
    "sg:classifiers":[
        {
            "category":"Health Services",
            "subcategory":"Doctor",
            "type":"Services"
        }
    ],
    "sg:phone":"+32 2 374 66 69",
    "sg:postcode":"1180",
    "sg:province":"Bruxelles-Capitale",
    "sg:tags":[
        "medicinephysicians",
        "surgeon"
    ],
    "wof:name":"Bernheim Jan",
    "wof:placetype":"venue"
},
  "geometry": {"coordinates":[4.3435611725,50.8042068481],"type":"Point"}
}