{
  "type": "Feature",
  "properties": {
    "addr:full":"Bel 127 Geel Antwerpen 2440",
    "addr:housenumber":"127",
    "addr:postcode":"2440",
    "addr:street":"Bel",
    "iso:country":"BE",
    "sg:address":"Bel 127",
    "sg:city":"Geel",
    "sg:classifiers":[
        {
            "category":"Real Estate",
            "subcategory":"Architect",
            "type":"Services"
        }
    ],
    "sg:phone":"+32 14 58 28 38",
    "sg:postcode":"2440",
    "sg:province":"Antwerpen",
    "wof:name":"Craps E",
    "wof:placetype":"venue"
},
  "geometry": {"coordinates":[5.0489997864,51.1636505127],"type":"Point"}
}