{
  "type": "Feature",
  "properties": {
    "addr:full":"Grand-place 1 Paliseul Luxembourg 6850",
    "addr:housenumber":"1",
    "addr:postcode":"6850",
    "addr:street":"Grand-Place",
    "iso:country":"BE",
    "sg:address":"Grand-place 1",
    "sg:city":"Paliseul",
    "sg:orig_category":"Overheidsdiensten",
    "sg:phone":"+32 61 53 38 94",
    "sg:postcode":"6850",
    "sg:province":"Luxembourg",
    "wof:name":"Administration Communale",
    "wof:placetype":"venue"
},
  "geometry": {"coordinates":[5.1367688179,49.9036521912],"type":"Point"}
}