{
  "type": "Feature",
  "properties": {
    "iso:country":"BE",
    "sg:address":"Baliestraat 27",
    "sg:city":"Brugge",
    "sg:orig_category":"Woningbouw",
    "sg:phone":"+32 50 33 38 95",
    "sg:postcode":"8000",
    "sg:province":"West-Vlaanderen",
    "wof:name":"Koenraad De Smet",
    "wof:placetype":"venue"
},
  "geometry": {"coordinates":[3.2258939743,51.2167854309],"type":"Point"}
}