{
  "type": "Feature",
  "properties": {
    "iso:country":"BE",
    "sg:address":"Burgemeester Capellelaan 64",
    "sg:city":"Damme (sijsele)",
    "sg:classifiers":[
        {
            "category":"Building & Trades",
            "subcategory":"Pest Control",
            "type":"Services"
        }
    ],
    "sg:phone":"+32 50 36 38 74",
    "sg:postcode":"8340",
    "sg:province":"West-Vlaanderen",
    "sg:tags":[
        "painting",
        "contractor"
    ],
    "wof:name":"Dalle G",
    "wof:placetype":"venue"
},
  "geometry": {"coordinates":[3.3113899231,51.2103233337],"type":"Point"}
}