{
  "type": "Feature",
  "properties": {
    "addr:full":"Oudenaardsesteenweg 501 Erpe-mere Oost-Vlaanderen 9420",
    "addr:housenumber":"501",
    "addr:postcode":"9420",
    "addr:street":"Oudenaardsesteenweg",
    "iso:country":"BE",
    "sg:address":"Oudenaardsesteenweg 501",
    "sg:city":"Erpe-mere",
    "sg:orig_category":"Catering and organisation de f\u00eates",
    "sg:phone":"+32 53 62 13 51",
    "sg:postcode":"9420",
    "sg:province":"Oost-Vlaanderen",
    "wof:name":"Paul Ottoy",
    "wof:placetype":"venue"
},
  "geometry": {"coordinates":[3.944286108,50.9210510254],"type":"Point"}
}