{
  "type": "Feature",
  "properties": {
    "iso:country":"BE",
    "sg:address":"Rue De L'eglise St.gilles 59",
    "sg:city":"Sint-gillis/saint-gilles",
    "sg:orig_category":"Activit\u00e9s d\u00b4action sociale sans h\u00e9bergement",
    "sg:phone":"+32 2 538 36 27",
    "sg:postcode":"1060",
    "sg:province":"Bruxelles-Capitale",
    "wof:name":"Centre De Sant\u00c9 Libre",
    "wof:placetype":"venue"
},
  "geometry": {"coordinates":[4.3421602249,50.8302116394],"type":"Point"}
}