{
  "type": "Feature",
  "properties": {
    "addr:full":"Heiveldstraat 86 Beveren Oost-Vlaanderen 9120",
    "addr:housenumber":"86",
    "addr:postcode":"9120",
    "addr:street":"Heiveldstraat",
    "iso:country":"BE",
    "sg:address":"Heiveldstraat 86",
    "sg:city":"Beveren",
    "sg:orig_category":"Elektrische installaties voor woningen",
    "sg:phone":"+32 3 775 06 40",
    "sg:postcode":"9120",
    "sg:province":"Oost-Vlaanderen",
    "wof:name":"Gino Cornelis",
    "wof:placetype":"venue"
},
  "geometry": {"coordinates":[4.2481818199,51.2240943909],"type":"Point"}
}