{
  "type": "Feature",
  "properties": {
    "addr:full":"Nieuwbaan 55 Merchtem Vlaams-Brabant 1785",
    "addr:housenumber":"55",
    "addr:postcode":"1785",
    "addr:street":"Nieuwbaan",
    "iso:country":"BE",
    "sg:address":"Nieuwbaan 55",
    "sg:city":"Merchtem",
    "sg:classifiers":[
        {
            "category":"Bars & Pubs",
            "type":"Food & Drink"
        }
    ],
    "sg:phone":"+32 486 39 49 82",
    "sg:postcode":"1785",
    "sg:province":"Vlaams-Brabant",
    "sg:tags":[
        "tavern"
    ],
    "wof:name":"Babbelkip (de)",
    "wof:placetype":"venue"
},
  "geometry": {"coordinates":[4.2248158455,50.9833641052],"type":"Point"}
}