{
  "type": "Feature",
  "properties": {
    "iso:country":"BE",
    "sg:address":"Roobeek 80",
    "sg:city":"Arendonk",
    "sg:orig_category":"Charpentes and couvertures",
    "sg:phone":"+32 14 67 12 70",
    "sg:postcode":"2370",
    "sg:province":"Antwerpen",
    "wof:name":"Herman Blockx",
    "wof:placetype":"venue"
},
  "geometry": {"coordinates":[5.0831041336,51.3091125488],"type":"Point"}
}