{
  "type": "Feature",
  "properties": {
    "iso:country":"BE",
    "sg:address":"Eikenlaan 5",
    "sg:city":"Neerpelt",
    "sg:orig_category":"Animations diverses",
    "sg:phone":"+32 11 64 51 68",
    "sg:postcode":"3910",
    "sg:province":"Limburg",
    "wof:name":"A. Baeken",
    "wof:placetype":"venue"
},
  "geometry": {"coordinates":[5.4449281693,51.2187042236],"type":"Point"}
}