{
  "type": "Feature",
  "properties": {
    "iso:country":"BE",
    "sg:address":"Bosdel 44a",
    "sg:city":"Genk",
    "sg:classifiers":[
        {
            "category":"Building & Trades",
            "subcategory":"Construction",
            "type":"Services"
        }
    ],
    "sg:phone":"+32 89 30 40 42",
    "sg:postcode":"3600",
    "sg:province":"Limburg",
    "sg:tags":[
        "carpenter"
    ],
    "wof:name":"Moors J",
    "wof:placetype":"venue"
},
  "geometry": {"coordinates":[5.4793448448,50.9511146545],"type":"Point"}
}