{
  "type": "Feature",
  "properties": {
    "addr:full":"Dendermondse Steenweg 267 Sint-niklaas Oost-Vlaanderen 9100",
    "addr:housenumber":"267",
    "addr:postcode":"9100",
    "addr:street":"Steenweg",
    "iso:country":"BE",
    "sg:address":"Dendermondse Steenweg 267",
    "sg:city":"Sint-niklaas",
    "sg:classifiers":[
        {
            "category":"Shopping",
            "subcategory":"Florist",
            "type":"Retail Goods"
        }
    ],
    "sg:phone":"+32 3 766 69 90",
    "sg:postcode":"9100",
    "sg:province":"Oost-Vlaanderen",
    "wof:name":"Casa Verde",
    "wof:placetype":"venue"
},
  "geometry": {"coordinates":[4.1501131058,51.1391372681],"type":"Point"}
}