{
  "type": "Feature",
  "properties": {
    "iso:country":"BE",
    "sg:address":"Monnikenhofstraat 151",
    "sg:city":"Antwerpen",
    "sg:orig_category":"M\u00e9decins and sp\u00e9cialistes",
    "sg:phone":"+32 3 568 89 80",
    "sg:postcode":"2040",
    "sg:province":"Antwerpen",
    "wof:name":"L. Bril",
    "wof:placetype":"venue"
},
  "geometry": {"coordinates":[4.3280501366,51.3489608765],"type":"Point"}
}