{
  "type": "Feature",
  "properties": {
    "addr:full":"Grand\u00b4rue 28 Charleroi Hainaut 6000",
    "addr:housenumber":"28",
    "addr:postcode":"6000",
    "addr:street":"Grand\u00b4Rue;Hainaut",
    "iso:country":"BE",
    "sg:address":"Grand\u00b4rue 28",
    "sg:city":"Charleroi",
    "sg:classifiers":[
        {
            "category":"Fast Food",
            "type":"Food & Drink"
        }
    ],
    "sg:phone":"+32 71 41 75 26",
    "sg:postcode":"6000",
    "sg:province":"Hainaut",
    "sg:tags":[
        "meeneem",
        "restaurant"
    ],
    "wof:name":"Chez Pascale",
    "wof:placetype":"venue"
},
  "geometry": {"coordinates":[4.4519791603,50.418006897],"type":"Point"}
}