{
  "type": "Feature",
  "properties": {
    "addr:full":"Kleine Weg 19 Roeselare West-Vlaanderen 8800",
    "addr:housenumber":"19",
    "addr:postcode":"8800",
    "addr:street":"Kleine Weg",
    "iso:country":"BE",
    "sg:address":"Kleine Weg 19",
    "sg:city":"Roeselare",
    "sg:classifiers":[
        {
            "category":"Communications",
            "subcategory":"Television Station",
            "type":"Services"
        }
    ],
    "sg:phone":"+32 3 270 99 30",
    "sg:postcode":"8800",
    "sg:province":"West-Vlaanderen",
    "sg:tags":[
        "colour",
        "set",
        "sets"
    ],
    "wof:name":"Loewe Opta Benelux Nv",
    "wof:placetype":"venue"
},
  "geometry": {"coordinates":[4.4479179382,51.2091751099],"type":"Point"}
}