{
  "type": "Feature",
  "properties": {
    "iso:country":"BE",
    "sg:address":"Chauss\u00c9e De Tubize 121",
    "sg:city":"Kasteelbrakel",
    "sg:orig_category":"Immobili\u00ebnkantoren",
    "sg:phone":"+32 2 355 15 15",
    "sg:postcode":"1440",
    "sg:province":"Brabant Wallon",
    "wof:name":"Imesver",
    "wof:placetype":"venue"
},
  "geometry": {"coordinates":[4.2505578995,50.6807098389],"type":"Point"}
}