{
  "type": "Feature",
  "properties": {
    "addr:full":"Quai De Compiegne 61 Huy Li\u00e8ge 4500",
    "addr:housenumber":"61",
    "addr:postcode":"4500",
    "addr:street":"Quai De Compiegne",
    "iso:country":"BE",
    "sg:address":"Quai De Compiegne 61",
    "sg:city":"Huy",
    "sg:orig_category":"Meubelzaken, woning- and keukeninrichting",
    "sg:phone":"+32 85 21 22 49",
    "sg:postcode":"4500",
    "sg:province":"Li\u00e8ge",
    "wof:name":"Offidecor",
    "wof:placetype":"venue"
},
  "geometry": {"coordinates":[5.2411608696,50.5298156738],"type":"Point"}
}