{
  "type": "Feature",
  "properties": {
    "addr:full":"Pastoor Dergentlaan 62 Aarschot Vlaams-Brabant 3200",
    "addr:housenumber":"62",
    "addr:postcode":"3200",
    "addr:street":"Pastoor Dergentlaan",
    "iso:country":"BE",
    "sg:address":"Pastoor Dergentlaan 62",
    "sg:city":"Aarschot",
    "sg:orig_category":"Enseignement secondaire technique and professionnel",
    "sg:phone":"+32 16 56 70 50",
    "sg:postcode":"3200",
    "sg:province":"Vlaams-Brabant",
    "wof:name":"S.i.b.a.",
    "wof:placetype":"venue"
},
  "geometry": {"coordinates":[4.7980999947,50.964389801],"type":"Point"}
}