{
  "type": "Feature",
  "properties": {
    "iso:country":"BE",
    "sg:address":"Rue Des Champs D'h\u00e9blon 7",
    "sg:city":"Hotton",
    "sg:classifiers":[
        {
            "category":"Building & Trades",
            "subcategory":"Construction",
            "type":"Services"
        }
    ],
    "sg:phone":"+32 84 46 63 03",
    "sg:postcode":"6990",
    "sg:province":"Luxembourg",
    "sg:tags":[
        "ceiling"
    ],
    "wof:name":"Vander Vennet D",
    "wof:placetype":"venue"
},
  "geometry": {"coordinates":[5.4777188301,50.2602958679],"type":"Point"}
}