{
  "type": "Feature",
  "properties": {
    "addr:full":"Zur Kaiserbaracke 15 Sankt Vith (recht) Li\u00e8ge 4780",
    "addr:housenumber":"15",
    "addr:postcode":"4780",
    "addr:street":"Zur Kaiserbaracke",
    "iso:country":"BE",
    "sg:address":"Zur Kaiserbaracke 15",
    "sg:city":"Sankt Vith (recht)",
    "sg:classifiers":[
        {
            "category":"Home & Garden",
            "subcategory":"Household Appliances",
            "type":"Retail Goods"
        }
    ],
    "sg:phone":"+32 80 57 02 95",
    "sg:postcode":"4780",
    "sg:province":"Li\u00e8ge",
    "sg:tags":[
        "heating",
        "apparatus"
    ],
    "wof:name":"Mws-schaus (ets)",
    "wof:placetype":"venue"
},
  "geometry": {"coordinates":[6.1256680489,50.2810821533],"type":"Point"}
}