{
  "type": "Feature",
  "properties": {
    "addr:full":"Venakker 76 Aalter Oost-Vlaanderen 9880",
    "addr:housenumber":"76",
    "addr:postcode":"9880",
    "addr:street":"Venakker",
    "iso:country":"BE",
    "sg:address":"Venakker 76",
    "sg:city":"Aalter",
    "sg:orig_category":"Installatie van houten of kunststof schrijnwerk",
    "sg:phone":"+32 9 374 43 20",
    "sg:postcode":"9880",
    "sg:province":"Oost-Vlaanderen",
    "wof:name":"Marc Gardin",
    "wof:placetype":"venue"
},
  "geometry": {"coordinates":[3.4473729134,51.0978050232],"type":"Point"}
}