{
  "type": "Feature",
  "properties": {
    "iso:country":"BE",
    "sg:address":"Chauss\u00e9e De Waterloo 481",
    "sg:city":"Namur (saint-servais)",
    "sg:classifiers":[
        {
            "category":"Professional",
            "subcategory":"Art Services",
            "type":"Services"
        }
    ],
    "sg:phone":"+32 81 58 10 18",
    "sg:postcode":"5002",
    "sg:province":"Namur",
    "sg:tags":[
        "photographer"
    ],
    "wof:name":"Coin Photo (au)",
    "wof:placetype":"venue"
},
  "geometry": {"coordinates":[4.8462319374,50.4782791138],"type":"Point"}
}