{
  "type": "Feature",
  "properties": {
    "iso:country":"BE",
    "sg:address":"Rue Pieter 72",
    "sg:city":"Bruxelles (forest)",
    "sg:classifiers":[
        {
            "category":"Social Services",
            "type":"Services"
        }
    ],
    "sg:phone":"+32 2 376 40 88",
    "sg:postcode":"1190",
    "sg:province":"Bruxelles-Capitale",
    "wof:name":"Service Et Culture",
    "wof:placetype":"venue"
},
  "geometry": {"coordinates":[4.3190898895,50.80834198],"type":"Point"}
}