{
  "type": "Feature",
  "properties": {
    "iso:country":"BE",
    "sg:address":"Bellemansheide 27",
    "sg:city":"Rhode-saint-gen\u00e8se",
    "sg:classifiers":[
        {
            "category":"Health Services",
            "subcategory":"Health Practitioner",
            "type":"Services"
        }
    ],
    "sg:phone":"+32 2 381 17 40",
    "sg:postcode":"1640",
    "sg:province":"Vlaams-Brabant",
    "sg:tags":[
        "psychologist"
    ],
    "wof:name":"Appaerts M",
    "wof:placetype":"venue"
},
  "geometry": {"coordinates":[4.3598918915,50.741809845],"type":"Point"}
}