{
  "type": "Feature",
  "properties": {
    "addr:full":"Rue Bidaut 16 Verviers Li\u00e8ge 4800",
    "addr:housenumber":"16",
    "addr:postcode":"4800",
    "addr:street":"Rue Bidaut",
    "iso:country":"BE",
    "sg:address":"Rue Bidaut 16",
    "sg:city":"Verviers",
    "sg:orig_category":"Agences de marketing",
    "sg:phone":"+32 87 23 20 23",
    "sg:postcode":"4800",
    "sg:province":"Li\u00e8ge",
    "wof:name":"Van Ruynbeke",
    "wof:placetype":"venue"
},
  "geometry": {"coordinates":[5.8624739647,50.5872917175],"type":"Point"}
}