{
  "type": "Feature",
  "properties": {
    "iso:country":"BE",
    "sg:address":"St Pieterstraat 27",
    "sg:city":"Woumen",
    "sg:orig_category":"Huisdieren and benodigdheden Tuinbenodigdheden",
    "sg:phone":"+32 51 50 02 72",
    "sg:postcode":"8600",
    "sg:province":"West-Vlaanderen",
    "wof:name":"Boeraeve Jan",
    "wof:placetype":"venue"
},
  "geometry": {"coordinates":[2.8799939156,50.9960021973],"type":"Point"}
}