{
  "type": "Feature",
  "properties": {
    "addr:full":"Rue Joseph Dethier 1 Awans Li\u00e8ge 4340",
    "addr:housenumber":"1",
    "addr:postcode":"4340",
    "addr:street":"Rue Joseph Dethier",
    "iso:country":"BE",
    "sg:address":"Rue Joseph Dethier 1",
    "sg:city":"Awans",
    "sg:orig_category":"Eleveurs de bovins. Eleveurs and marchands de porcs",
    "sg:phone":"+32 4 257 42 17",
    "sg:postcode":"4340",
    "sg:province":"Li\u00e8ge",
    "wof:name":"Pierre Fastre",
    "wof:placetype":"venue"
},
  "geometry": {"coordinates":[5.4447360039,50.7034873962],"type":"Point"}
}