{
  "type": "Feature",
  "properties": {
    "addr:full":"Plein 37 Kaprijke Oost-Vlaanderen 9970",
    "addr:housenumber":"37",
    "addr:postcode":"9970",
    "addr:street":"Plein",
    "iso:country":"BE",
    "sg:address":"Plein 37",
    "sg:city":"Kaprijke",
    "sg:classifiers":[
        {
            "category":"Fast Food",
            "type":"Food & Drink"
        }
    ],
    "sg:phone":"+32 9 373 56 46",
    "sg:postcode":"9970",
    "sg:province":"Oost-Vlaanderen",
    "sg:tags":[
        "meeneem",
        "restaurant"
    ],
    "wof:name":"'t Friethuisje",
    "wof:placetype":"venue"
},
  "geometry": {"coordinates":[3.620071888,51.2190437317],"type":"Point"}
}