{
  "type": "Feature",
  "properties": {
    "iso:country":"BE",
    "sg:address":"Gentse Steenweg 203",
    "sg:city":"Maldegem",
    "sg:classifiers":[
        {
            "category":"Community Center",
            "subcategory":"Social",
            "type":"Public Place"
        }
    ],
    "sg:phone":"+32 50 71 23 31",
    "sg:postcode":"9990",
    "sg:province":"Oost-Vlaanderen",
    "sg:tags":[
        "-",
        "haute",
        "clothing",
        "couture"
    ],
    "wof:name":"Aphrodite Couture",
    "wof:placetype":"venue"
},
  "geometry": {"coordinates":[3.467261076,51.2050971985],"type":"Point"}
}