{
  "type": "Feature",
  "properties": {
    "addr:full":"Rue De La Briqueterie 8 Somme-leuze Namur 5377",
    "addr:housenumber":"8",
    "addr:postcode":"5377",
    "addr:street":"Rue De La Briqueterie",
    "iso:country":"BE",
    "sg:address":"Rue De La Briqueterie 8",
    "sg:city":"Somme-leuze",
    "sg:orig_category":"Rundveehouders",
    "sg:phone":"+32 84 31 45 85",
    "sg:postcode":"5377",
    "sg:province":"Namur",
    "wof:name":"Nestor Nutal",
    "wof:placetype":"venue"
},
  "geometry": {"coordinates":[5.3060097694,50.2594833374],"type":"Point"}
}