{
  "type": "Feature",
  "properties": {
    "addr:full":"Rue Du Fayt 28 Floreffe (soye) Namur 5150",
    "addr:housenumber":"28",
    "addr:postcode":"5150",
    "addr:street":"Rue Du Fayt",
    "iso:country":"BE",
    "sg:address":"Rue Du Fayt 28",
    "sg:city":"Floreffe (soye)",
    "sg:classifiers":[
        {
            "category":"Professional",
            "subcategory":"Engineering",
            "type":"Services"
        }
    ],
    "sg:phone":"+32 81 44 47 93",
    "sg:postcode":"5150",
    "sg:province":"Namur",
    "sg:tags":[
        "-"
    ],
    "wof:name":"Collectif Erasme Sc",
    "wof:placetype":"venue"
},
  "geometry": {"coordinates":[4.7362599373,50.4654388428],"type":"Point"}
}