{
  "type": "Feature",
  "properties": {
    "addr:full":"Rue Du Masy 6 Soignies (neufvilles) Hainaut 7063",
    "addr:housenumber":"6",
    "addr:postcode":"7063",
    "addr:street":"Rue Du Masy",
    "iso:country":"BE",
    "sg:address":"Rue Du Masy 6",
    "sg:city":"Soignies (neufvilles)",
    "sg:classifiers":[
        {
            "category":"Health Services",
            "subcategory":"Health Practitioner",
            "type":"Services"
        }
    ],
    "sg:phone":"+32 67 33 28 84",
    "sg:postcode":"7063",
    "sg:province":"Hainaut",
    "sg:tags":[
        "physiotherapist"
    ],
    "wof:name":"Massion P",
    "wof:placetype":"venue"
},
  "geometry": {"coordinates":[3.993940115,50.5837898254],"type":"Point"}
}