{
  "type": "Feature",
  "properties": {
    "addr:full":"Rue Du Palais 8 Charleroi Hainaut 6000",
    "addr:housenumber":"8",
    "addr:postcode":"6000",
    "addr:street":"Rue Du Palais;Hainaut",
    "iso:country":"BE",
    "sg:address":"Rue Du Palais 8",
    "sg:city":"Charleroi",
    "sg:classifiers":[
        {
            "category":"Utilities",
            "subcategory":"Natural Gas",
            "type":"Services"
        }
    ],
    "sg:phone":"+32 71 31 31 56",
    "sg:postcode":"6000",
    "sg:province":"Hainaut",
    "sg:tags":[
        "hide",
        "skin"
    ],
    "wof:name":"Claeys Cuirs-sellerie Sa",
    "wof:placetype":"venue"
},
  "geometry": {"coordinates":[4.4426951408,50.4097061157],"type":"Point"}
}