{
  "type": "Feature",
  "properties": {
    "addr:full":"Mudakkers 86 Lommel Limburg 3920",
    "addr:housenumber":"86",
    "addr:postcode":"3920",
    "addr:street":"Mudakkers",
    "iso:country":"BE",
    "sg:address":"Mudakkers 86",
    "sg:city":"Lommel",
    "sg:orig_category":"Sportclubs",
    "sg:phone":"+32 11 54 14 31",
    "sg:postcode":"3920",
    "sg:province":"Limburg",
    "wof:name":"B.b.c. Lommel",
    "wof:placetype":"venue"
},
  "geometry": {"coordinates":[5.320250988,51.2319869995],"type":"Point"}
}