{
  "type": "Feature",
  "properties": {
    "addr:full":"Rue Des Emmanuel 15 Brunehaut Hainaut 7620",
    "addr:housenumber":"15",
    "addr:postcode":"7620",
    "addr:street":"Rue Des Emmanuel",
    "iso:country":"BE",
    "sg:address":"Rue Des Emmanuel 15",
    "sg:city":"Brunehaut",
    "sg:orig_category":"Epiceries",
    "sg:phone":"+32 69 34 47 74",
    "sg:postcode":"7620",
    "sg:province":"Hainaut",
    "wof:name":"Lemaire M - Caulier F",
    "wof:placetype":"venue"
},
  "geometry": {"coordinates":[3.4210350513,50.5150413513],"type":"Point"}
}