{
  "type": "Feature",
  "properties": {
    "iso:country":"BE",
    "sg:address":"Mechelbaan 703",
    "sg:city":"Putte",
    "sg:classifiers":[
        {
            "category":"Freight",
            "type":"Transportation"
        }
    ],
    "sg:phone":"+32 15 75 33 95",
    "sg:postcode":"2580",
    "sg:province":"Antwerpen",
    "sg:tags":[
        "-",
        "transport"
    ],
    "wof:name":"De Wachter E",
    "wof:placetype":"venue"
},
  "geometry": {"coordinates":[4.5965471268,51.0401229858],"type":"Point"}
}