{
  "type": "Feature",
  "properties": {
    "iso:country":"BE",
    "sg:address":"Puitstraat 4",
    "sg:city":"Moorslede",
    "sg:orig_category":"Rundveehouders",
    "sg:phone":"+32 51 77 77 91",
    "sg:postcode":"8890",
    "sg:province":"West-Vlaanderen",
    "wof:name":"Jean-pierre Remmery",
    "wof:placetype":"venue"
},
  "geometry": {"coordinates":[3.0857570171,50.9029769897],"type":"Point"}
}