{
  "type": "Feature",
  "properties": {
    "iso:country":"BE",
    "sg:address":"Speistraat 13",
    "sg:city":"Herzele",
    "sg:orig_category":"Eleveurs de bovins",
    "sg:phone":"+32 54 50 04 64",
    "sg:postcode":"9550",
    "sg:province":"Oost-Vlaanderen",
    "wof:name":"Wim De Middeleer",
    "wof:placetype":"venue"
},
  "geometry": {"coordinates":[3.883024931,50.8633537292],"type":"Point"}
}