{
  "type": "Feature",
  "properties": {
    "iso:country":"BE",
    "sg:address":"Rue Du Coll\u00c8ge 6",
    "sg:city":"Ath",
    "sg:orig_category":"Schoenen",
    "sg:phone":"+32 68 28 25 00",
    "sg:postcode":"7800",
    "sg:province":"Hainaut",
    "wof:name":"A La Botte Rouge",
    "wof:placetype":"venue"
},
  "geometry": {"coordinates":[3.777066946,50.6288261414],"type":"Point"}
}