{
  "type": "Feature",
  "properties": {
    "addr:full":"Chauss\u00e9e De Charleroi 60 Charleroi (gilly) Hainaut 6060",
    "addr:housenumber":"60",
    "addr:postcode":"6060",
    "addr:street":"Chausse\u0301E De Charleroi",
    "iso:country":"BE",
    "sg:address":"Chauss\u00e9e De Charleroi 60",
    "sg:city":"Charleroi (gilly)",
    "sg:classifiers":[
        {
            "category":"Health Services",
            "subcategory":"Health Practitioner",
            "type":"Services"
        }
    ],
    "sg:phone":"+32 71 48 69 60",
    "sg:postcode":"6060",
    "sg:province":"Hainaut",
    "sg:tags":[
        "physiotherapist"
    ],
    "wof:name":"Monnom C",
    "wof:placetype":"venue"
},
  "geometry": {"coordinates":[4.4754638672,50.4015884399],"type":"Point"}
}