{
  "type": "Feature",
  "properties": {
    "addr:full":"Korbeekdamstraat 24 Oud-heverlee Vlaams-Brabant 3050",
    "addr:housenumber":"24",
    "addr:postcode":"3050",
    "addr:street":"Korbeekdamstraat",
    "iso:country":"BE",
    "sg:address":"Korbeekdamstraat 24",
    "sg:city":"Oud-heverlee",
    "sg:classifiers":[
        {
            "category":"Health Services",
            "subcategory":"Doctor",
            "type":"Services"
        }
    ],
    "sg:phone":"+32 16 47 70 34",
    "sg:postcode":"3050",
    "sg:province":"Vlaams-Brabant",
    "sg:tags":[
        "medicinephysicians",
        "surgeon"
    ],
    "wof:name":"Lemaire P",
    "wof:placetype":"venue"
},
  "geometry": {"coordinates":[4.6561717987,50.8328323364],"type":"Point"}
}