{
  "type": "Feature",
  "properties": {
    "iso:country":"BE",
    "sg:address":"Grote Noordstraat 93",
    "sg:city":"Hooglede",
    "sg:orig_category":"P\u00e9pini\u00e9ristes. Jardinage",
    "sg:phone":"+32 51 72 65 88",
    "sg:postcode":"8830",
    "sg:province":"West-Vlaanderen",
    "wof:name":"Neels Jean-pierre",
    "wof:placetype":"venue"
},
  "geometry": {"coordinates":[3.0646910667,51.0064582825],"type":"Point"}
}