{
  "type": "Feature",
  "properties": {
    "addr:full":"Kleine Warande 25 Gistel West-Vlaanderen 8470",
    "addr:housenumber":"25",
    "addr:postcode":"8470",
    "addr:street":"Kleine Warande",
    "iso:country":"BE",
    "sg:address":"Kleine Warande 25",
    "sg:city":"Gistel",
    "sg:orig_category":"Woningbouw",
    "sg:phone":"+32 59 27 85 75",
    "sg:postcode":"8470",
    "sg:province":"West-Vlaanderen",
    "wof:name":"Gistels Karweibedrijf",
    "wof:placetype":"venue"
},
  "geometry": {"coordinates":[2.9742119312,51.163318634],"type":"Point"}
}