{
  "type": "Feature",
  "properties": {
    "addr:full":"Rue Du Rond Point 283 Chimay Hainaut 6464",
    "addr:housenumber":"283",
    "addr:postcode":"6464",
    "addr:street":"Rue Du Rond",
    "iso:country":"BE",
    "sg:address":"Rue Du Rond Point 283",
    "sg:city":"Chimay",
    "sg:orig_category":"Catering and organisatie van feesten Fast food and meeneem restaurants Kampeerterreinen Restaurants",
    "sg:phone":"+32 60 21 18 02",
    "sg:postcode":"6464",
    "sg:province":"Hainaut",
    "wof:name":"La Camargue",
    "wof:placetype":"venue"
},
  "geometry": {"coordinates":[4.3212881088,50.0024223328],"type":"Point"}
}