{
  "type": "Feature",
  "properties": {
    "addr:full":"Rue De Florival 2 Grez-doiceau (archennes) Brabant Wallon 1390",
    "addr:housenumber":"2",
    "addr:postcode":"1390",
    "addr:street":"Rue De Florival;Wallon",
    "iso:country":"BE",
    "sg:address":"Rue De Florival 2",
    "sg:city":"Grez-doiceau (archennes)",
    "sg:classifiers":[
        {
            "category":"Personal",
            "subcategory":"Nail Salon",
            "type":"Services"
        }
    ],
    "sg:phone":"+32 10 84 43 67",
    "sg:postcode":"1390",
    "sg:province":"Brabant Wallon",
    "sg:tags":[
        "pedicure"
    ],
    "wof:name":"Portier G",
    "wof:placetype":"venue"
},
  "geometry": {"coordinates":[4.6717500687,50.751449585],"type":"Point"}
}