{
  "type": "Feature",
  "properties": {
    "addr:full":"Lodewijk De Raetplein 13 Lokeren Oost-Vlaanderen 9160",
    "addr:housenumber":"13",
    "addr:postcode":"9160",
    "addr:street":"Lodewijk De Raetplein",
    "iso:country":"BE",
    "sg:address":"Lodewijk De Raetplein 13",
    "sg:city":"Lokeren",
    "sg:orig_category":"Peinture. Rev\u00eatements pour sols and murs",
    "sg:phone":"+32 9 349 08 02",
    "sg:postcode":"9160",
    "sg:province":"Oost-Vlaanderen",
    "wof:name":"De Wilde Gebroeders",
    "wof:placetype":"venue"
},
  "geometry": {"coordinates":[4.0000901222,51.0993309021],"type":"Point"}
}