{
  "type": "Feature",
  "properties": {
    "iso:country":"BE",
    "sg:address":"Place Nicolas Jenart 26",
    "sg:city":"Quaregnon",
    "sg:classifiers":[
        {
            "category":"Real Estate",
            "subcategory":"Architect",
            "type":"Services"
        }
    ],
    "sg:phone":"+32 65 63 36 63",
    "sg:postcode":"7390",
    "sg:province":"Hainaut",
    "wof:name":"Cornant P",
    "wof:placetype":"venue"
},
  "geometry": {"coordinates":[3.8684129715,50.4427680969],"type":"Point"}
}