{
  "type": "Feature",
  "properties": {
    "addr:full":"Bierbeekstraat 110 Leuven Vlaams-Brabant 3001",
    "addr:housenumber":"110",
    "addr:postcode":"3001",
    "addr:street":"Bierbeekstraat",
    "iso:country":"BE",
    "sg:address":"Bierbeekstraat 110",
    "sg:city":"Leuven",
    "sg:orig_category":"Enregistrements sonores",
    "sg:phone":"+32 16 29 47 47",
    "sg:postcode":"3001",
    "sg:province":"Vlaams-Brabant",
    "wof:name":"L.i.s.",
    "wof:placetype":"venue"
},
  "geometry": {"coordinates":[4.7173581123,50.871307373],"type":"Point"}
}