{
  "type": "Feature",
  "properties": {
    "addr:full":"Place Abb\u00c9 Goffinet 20 Musson Luxembourg 6750",
    "addr:housenumber":"20",
    "addr:postcode":"6750",
    "addr:street":"Place Abbe\u0301 Goffinet",
    "iso:country":"BE",
    "sg:address":"Place Abb\u00c9 Goffinet 20",
    "sg:city":"Musson",
    "sg:orig_category":"Plaatsen van vloer- and muurbekleding Vloer- and muurbekleding",
    "sg:phone":"+32 63 67 70 07",
    "sg:postcode":"6750",
    "sg:province":"Luxembourg",
    "wof:name":"Fe. Lentini",
    "wof:placetype":"venue"
},
  "geometry": {"coordinates":[5.7052731514,49.5576133728],"type":"Point"}
}