{
  "type": "Feature",
  "properties": {
    "iso:country":"BE",
    "sg:address":"Rue Des Ecoles 9",
    "sg:city":"Tenneville",
    "sg:orig_category":"Offices du tourisme",
    "sg:phone":"+32 84 45 51 55",
    "sg:postcode":"6971",
    "sg:province":"Luxembourg",
    "wof:name":"Syndicat D'initiative",
    "wof:placetype":"venue"
},
  "geometry": {"coordinates":[5.5016188622,50.1078453064],"type":"Point"}
}