{
  "type": "Feature",
  "properties": {
    "addr:full":"Veldstraat 158 Temse Oost-Vlaanderen 9140",
    "addr:housenumber":"158",
    "addr:postcode":"9140",
    "addr:street":"Veldstraat",
    "iso:country":"BE",
    "sg:address":"Veldstraat 158",
    "sg:city":"Temse",
    "sg:orig_category":"Experts-comptables",
    "sg:phone":"+32 3 771 12 74",
    "sg:postcode":"9140",
    "sg:province":"Oost-Vlaanderen",
    "wof:name":"R. De Vleeschouwer",
    "wof:placetype":"venue"
},
  "geometry": {"coordinates":[4.2197751999,51.1402626038],"type":"Point"}
}