{
  "type": "Feature",
  "properties": {
    "iso:country":"BE",
    "sg:address":"Avenue Reine Elisabeth 103",
    "sg:city":"Andenne",
    "sg:classifiers":[
        {
            "category":"Health Services",
            "subcategory":"Doctor",
            "type":"Services"
        }
    ],
    "sg:phone":"+32 85 84 51 28",
    "sg:postcode":"5300",
    "sg:province":"Namur",
    "sg:tags":[
        "medicinephysicians",
        "surgeon"
    ],
    "wof:name":"Denis Brigitte",
    "wof:placetype":"venue"
},
  "geometry": {"coordinates":[5.0908389091,50.4910850525],"type":"Point"}
}