{
  "type": "Feature",
  "properties": {
    "iso:country":"BE",
    "sg:address":"Rue Stevin 174",
    "sg:city":"Bruxelles",
    "sg:classifiers":[
        {
            "category":"Building & Trades",
            "subcategory":"Pest Control",
            "type":"Services"
        }
    ],
    "sg:phone":"+32 2 736 96 26",
    "sg:postcode":"1000",
    "sg:province":"Bruxelles-Capitale",
    "sg:tags":[
        "machine",
        "vending"
    ],
    "wof:name":"Schuler Food Matic",
    "wof:placetype":"venue"
},
  "geometry": {"coordinates":[4.384185791,50.8441772461],"type":"Point"}
}