{
  "type": "Feature",
  "properties": {
    "addr:full":"Clos Des Gen\u00eats Chaumont-gistoux Brabant Wallon 1325",
    "addr:postcode":"1325",
    "addr:street":"Clos Des Gene\u0302Ts",
    "iso:country":"BE",
    "sg:address":"Clos Des Gen\u00eats",
    "sg:city":"Chaumont-gistoux",
    "sg:classifiers":[
        {
            "category":"Building & Trades",
            "subcategory":"Landscaping Services",
            "type":"Services"
        }
    ],
    "sg:phone":"+32 10 68 01 24",
    "sg:postcode":"1325",
    "sg:province":"Brabant Wallon",
    "sg:tags":[
        "gardening",
        "garden",
        "maintenance"
    ],
    "wof:name":"Hpl Garden",
    "wof:placetype":"venue"
},
  "geometry": {"coordinates":[4.7109708786,50.6885147095],"type":"Point"}
}