{
  "type": "Feature",
  "properties": {
    "iso:country":"BE",
    "sg:address":"Herentalsebaan 731",
    "sg:city":"Wommelgem",
    "sg:orig_category":"Notarissen",
    "sg:phone":"+32 3 353 63 60",
    "sg:postcode":"2160",
    "sg:province":"Antwerpen",
    "wof:name":"Wim De Smedt",
    "wof:placetype":"venue"
},
  "geometry": {"coordinates":[4.5270090103,51.1975326538],"type":"Point"}
}