{
  "type": "Feature",
  "properties": {
    "iso:country":"BE",
    "sg:address":"Belseledorp 96",
    "sg:city":"Sint-niklaas",
    "sg:orig_category":"Services fun\u00e9raires",
    "sg:phone":"+32 3 772 50 66",
    "sg:postcode":"9111",
    "sg:province":"Oost-Vlaanderen",
    "wof:name":"Begrafenissen Van Dael",
    "wof:placetype":"venue"
},
  "geometry": {"coordinates":[4.0914978981,51.1462173462],"type":"Point"}
}