{
  "type": "Feature",
  "properties": {
    "addr:full":"Avenue De Grand'peine 9 Seneffe (arquennes) Hainaut 7181",
    "addr:housenumber":"9",
    "addr:postcode":"7181",
    "addr:street":"Avenue De Grand'Peine",
    "iso:country":"BE",
    "sg:address":"Avenue De Grand'peine 9",
    "sg:city":"Seneffe (arquennes)",
    "sg:classifiers":[
        {
            "category":"Building & Trades",
            "subcategory":"Landscaping Services",
            "type":"Services"
        }
    ],
    "sg:phone":"+32 67 87 70 07",
    "sg:postcode":"7181",
    "sg:province":"Hainaut",
    "sg:tags":[
        "handicraft"
    ],
    "wof:name":"Ferme \u00e0 Arquennes (une)",
    "wof:placetype":"venue"
},
  "geometry": {"coordinates":[4.2853589058,50.566734314],"type":"Point"}
}