{
  "type": "Feature",
  "properties": {
    "iso:country":"BE",
    "sg:address":"Antwerpsedreef 97ba",
    "sg:city":"Zoersel",
    "sg:orig_category":"Installatie van houten of kunststof schrijnwerk",
    "sg:phone":"+32 3 384 09 73",
    "sg:postcode":"2980",
    "sg:province":"Antwerpen",
    "wof:name":"Pemen Dirk",
    "wof:placetype":"venue"
},
  "geometry": {"coordinates":[4.6699051857,51.2633361816],"type":"Point"}
}