{
  "type": "Feature",
  "properties": {
    "addr:full":"Preulegem 40 Ninove Oost-Vlaanderen 9400",
    "addr:housenumber":"40",
    "addr:postcode":"9400",
    "addr:street":"Preulegem",
    "iso:country":"BE",
    "sg:address":"Preulegem 40",
    "sg:city":"Ninove",
    "sg:orig_category":"Quincailleries. Drogueries",
    "sg:phone":"+32 54 33 15 23",
    "sg:postcode":"9400",
    "sg:province":"Oost-Vlaanderen",
    "wof:name":"Hans Scheerlinck",
    "wof:placetype":"venue"
},
  "geometry": {"coordinates":[4.0118708611,50.8363952637],"type":"Point"}
}