{
  "type": "Feature",
  "properties": {
    "iso:country":"BE",
    "sg:address":"Schurhovenveld 2602",
    "sg:city":"Sint-truiden",
    "sg:orig_category":"Location de voitures",
    "sg:phone":"+32 11 68 22 26",
    "sg:postcode":"3800",
    "sg:province":"Limburg",
    "wof:name":"Top Rent",
    "wof:placetype":"venue"
},
  "geometry": {"coordinates":[5.1863641739,50.8153343201],"type":"Point"}
}