{
  "type": "Feature",
  "properties": {
    "addr:full":"Rue Lieutenant-lozet 12 Neufch\u00c2teau Luxembourg 6840",
    "addr:housenumber":"12",
    "addr:postcode":"6840",
    "addr:street":"Rue Lieutenant-Lozet",
    "iso:country":"BE",
    "sg:address":"Rue Lieutenant-lozet 12",
    "sg:city":"Neufch\u00c2teau",
    "sg:orig_category":"Enseignement maternel and primaire",
    "sg:phone":"+32 61 27 73 85",
    "sg:postcode":"6840",
    "sg:province":"Luxembourg",
    "wof:name":"Ecole Fondamentale Libre",
    "wof:placetype":"venue"
},
  "geometry": {"coordinates":[5.4359288216,49.8430557251],"type":"Point"}
}