{
  "type": "Feature",
  "properties": {
    "iso:country":"BE",
    "sg:address":"Holstraat 45",
    "sg:city":"Waregem",
    "sg:orig_category":"Verplichte sociale verzekeringen",
    "sg:phone":"+32 56 61 51 10",
    "sg:postcode":"8790",
    "sg:province":"West-Vlaanderen",
    "wof:name":"Westvl. Liberaal Ziekenf.",
    "wof:placetype":"venue"
},
  "geometry": {"coordinates":[3.4357869625,50.8850021362],"type":"Point"}
}