{
  "type": "Feature",
  "properties": {
    "addr:full":"Lindestraat 18 Westerlo Antwerpen 2260",
    "addr:housenumber":"18",
    "addr:postcode":"2260",
    "addr:street":"Lindestraat",
    "iso:country":"BE",
    "sg:address":"Lindestraat 18",
    "sg:city":"Westerlo",
    "sg:classifiers":[
        {
            "category":"Bars & Pubs",
            "type":"Food & Drink"
        }
    ],
    "sg:phone":"+32 14 23 74 44",
    "sg:postcode":"2260",
    "sg:province":"Antwerpen",
    "wof:name":"Oki-doki",
    "wof:placetype":"venue"
},
  "geometry": {"coordinates":[4.9037327766,51.1406440735],"type":"Point"}
}