{
  "type": "Feature",
  "properties": {
    "addr:full":"Rue De La Tete D'argent 18 Tournai Hainaut 7500",
    "addr:housenumber":"18",
    "addr:postcode":"7500",
    "addr:street":"Rue De La Tete D'Argent",
    "iso:country":"BE",
    "sg:address":"Rue De La Tete D'argent 18",
    "sg:city":"Tournai",
    "sg:classifiers":[
        {
            "category":"Insurance",
            "subcategory":"Insurance Agent",
            "type":"Services"
        }
    ],
    "sg:phone":"+32 69 22 78 01",
    "sg:postcode":"7500",
    "sg:province":"Hainaut",
    "sg:tags":[
        "broker"
    ],
    "wof:name":"Agence Internationale De L'assurance Sprl",
    "wof:placetype":"venue"
},
  "geometry": {"coordinates":[3.3863639832,50.6082191467],"type":"Point"}
}