{
  "type": "Feature",
  "properties": {
    "iso:country":"BE",
    "sg:address":"Rue De Tournai 23",
    "sg:city":"Tournai",
    "sg:orig_category":"Plaatsen van vloer- and muurbekleding Schilders",
    "sg:phone":"+32 69 35 10 54",
    "sg:postcode":"7520",
    "sg:province":"Hainaut",
    "wof:name":"Dominique Vanderbiest",
    "wof:placetype":"venue"
},
  "geometry": {"coordinates":[3.288795948,50.6434669495],"type":"Point"}
}