{
  "type": "Feature",
  "properties": {
    "addr:full":"Zeedijk 666 Knokke West-Vlaanderen 8300",
    "addr:housenumber":"666",
    "addr:postcode":"8300",
    "addr:street":"Zeedijk",
    "iso:country":"BE",
    "sg:address":"Zeedijk 666",
    "sg:city":"Knokke",
    "sg:classifiers":[
        {
            "category":"Restaurant",
            "type":"Food & Drink"
        }
    ],
    "sg:phone":"+32 50 60 46 82",
    "sg:postcode":"8300",
    "sg:province":"West-Vlaanderen",
    "wof:name":"Mercator",
    "wof:placetype":"venue"
},
  "geometry": {"coordinates":[3.2888350487,51.3460388184],"type":"Point"}
}