{
  "type": "Feature",
  "properties": {
    "addr:full":"Place Joseph Thiry 13 Aywaille Li\u00e8ge 4920",
    "addr:housenumber":"13",
    "addr:postcode":"4920",
    "addr:street":"Place Joseph Thiry",
    "iso:country":"BE",
    "sg:address":"Place Joseph Thiry 13",
    "sg:city":"Aywaille",
    "sg:classifiers":[
        {
            "category":"Bars & Pubs",
            "type":"Food & Drink"
        }
    ],
    "sg:phone":"+32 4 384 40 25",
    "sg:postcode":"4920",
    "sg:province":"Li\u00e8ge",
    "sg:tags":[
        "tavern"
    ],
    "wof:name":"Orme (brasserie De L')",
    "wof:placetype":"venue"
},
  "geometry": {"coordinates":[5.6751389503,50.4739685059],"type":"Point"}
}