{
  "type": "Feature",
  "properties": {
    "addr:full":"Pl Albert I. Anderlues Hainaut 6500",
    "addr:postcode":"6500",
    "addr:street":"Pl Albert I.;Hainaut",
    "iso:country":"BE",
    "sg:address":"Pl Albert I.",
    "sg:city":"Anderlues",
    "sg:classifiers":[
        {
            "category":"Banks & Credit Unions",
            "subcategory":"Bank",
            "type":"Services"
        }
    ],
    "sg:phone":"+32 85 52 43 61",
    "sg:postcode":"6500",
    "sg:province":"Hainaut",
    "wof:name":"Banque Bruxelles Lambert Sa",
    "wof:placetype":"venue"
},
  "geometry": {"coordinates":[4.2353200912,50.2372131348],"type":"Point"}
}