{
  "type": "Feature",
  "properties": {
    "iso:country":"BE",
    "sg:address":"Nieuwe-heidestraat 107",
    "sg:city":"Hasselt",
    "sg:orig_category":"Drukkerijen and copyshops",
    "sg:phone":"+32 11 22 64 41",
    "sg:postcode":"3500",
    "sg:province":"Limburg",
    "wof:name":"Drukkerij Gecom",
    "wof:placetype":"venue"
},
  "geometry": {"coordinates":[5.3826599121,50.9567527771],"type":"Point"}
}