{
  "type": "Feature",
  "properties": {
    "iso:country":"BE",
    "sg:address":"Opstalstraat 32-34",
    "sg:city":"Waregem (desselgem)",
    "sg:classifiers":[
        {
            "category":"Shopping",
            "subcategory":"Crafts & Fabrics",
            "type":"Retail Goods"
        }
    ],
    "sg:phone":"+32 56 71 21 97",
    "sg:postcode":"8792",
    "sg:province":"West-Vlaanderen",
    "sg:tags":[
        "graphic",
        "art",
        "supply",
        "-",
        "painting",
        "drawing"
    ],
    "wof:name":"Dhondt Hobby Products Bvba",
    "wof:placetype":"venue"
},
  "geometry": {"coordinates":[3.3597478867,50.8899230957],"type":"Point"}
}