{
  "type": "Feature",
  "properties": {
    "addr:full":"Rue De La Laiterie 16 Malmedy (bellevaux-lignueville) Li\u00e8ge 4960",
    "addr:housenumber":"16",
    "addr:postcode":"4960",
    "addr:street":"Rue De La Laiterie",
    "iso:country":"BE",
    "sg:address":"Rue De La Laiterie 16",
    "sg:city":"Malmedy (bellevaux-lignueville)",
    "sg:classifiers":[
        {
            "category":"Building & Trades",
            "subcategory":"Landscaping Services",
            "type":"Services"
        }
    ],
    "sg:phone":"+32 80 44 84 42",
    "sg:postcode":"4960",
    "sg:province":"Li\u00e8ge",
    "sg:tags":[
        "forestry"
    ],
    "wof:name":"Gerardy J",
    "wof:placetype":"venue"
},
  "geometry": {"coordinates":[6.0493841171,50.3759880066],"type":"Point"}
}