{
  "type": "Feature",
  "properties": {
    "addr:full":"Rue De Pommard 221 Stavelot Li\u00e8ge 4970",
    "addr:housenumber":"221",
    "addr:postcode":"4970",
    "addr:street":"Rue De Pommard",
    "iso:country":"BE",
    "sg:address":"Rue De Pommard 221",
    "sg:city":"Stavelot",
    "sg:orig_category":"Plaatsen van vloer- and muurbekleding Schilders",
    "sg:phone":"+32 87 27 50 56",
    "sg:postcode":"4970",
    "sg:province":"Li\u00e8ge",
    "wof:name":"Jose Leduc",
    "wof:placetype":"venue"
},
  "geometry": {"coordinates":[5.9544448853,50.4541091919],"type":"Point"}
}