{
  "type": "Feature",
  "properties": {
    "iso:country":"BE",
    "sg:address":"Rue De La Gare 26",
    "sg:city":"Aiseau",
    "sg:orig_category":"Voertuigen",
    "sg:phone":"+32 475 44 03 00",
    "sg:postcode":"6250",
    "sg:province":"Hainaut",
    "wof:name":"Hakan Karakilic",
    "wof:placetype":"venue"
},
  "geometry": {"coordinates":[4.5856871605,50.4260139465],"type":"Point"}
}