{
  "type": "Feature",
  "properties": {
    "addr:full":"Rue Gr\u00e9goire N\u00e9lis 6 Jodoigne Brabant Wallon 1370",
    "addr:housenumber":"6",
    "addr:postcode":"1370",
    "addr:street":"Rue Gre\u0301Goire Ne\u0301Lis",
    "iso:country":"BE",
    "sg:address":"Rue Gr\u00e9goire N\u00e9lis 6",
    "sg:city":"Jodoigne",
    "sg:classifiers":[
        {
            "category":"Retail",
            "subcategory":"Repair Shop",
            "type":"Services"
        }
    ],
    "sg:phone":"+32 10 81 05 26",
    "sg:postcode":"1370",
    "sg:province":"Brabant Wallon",
    "sg:tags":[
        "-",
        "clothing",
        "alteration"
    ],
    "wof:name":"Cousette (la)",
    "wof:placetype":"venue"
},
  "geometry": {"coordinates":[4.8677392006,50.7237930298],"type":"Point"}
}