{
  "type": "Feature",
  "properties": {
    "addr:full":"Molendreef 33 Anzegem (vichte) West-Vlaanderen 8570",
    "addr:housenumber":"33",
    "addr:postcode":"8570",
    "addr:street":"Molendreef",
    "iso:country":"BE",
    "sg:address":"Molendreef 33",
    "sg:city":"Anzegem (vichte)",
    "sg:classifiers":[
        {
            "category":"Real Estate",
            "subcategory":"Surveying",
            "type":"Services"
        }
    ],
    "sg:phone":"+32 56 77 45 50",
    "sg:postcode":"8570",
    "sg:province":"West-Vlaanderen",
    "sg:tags":[
        "surveyor",
        "land"
    ],
    "wof:name":"Degezelle B",
    "wof:placetype":"venue"
},
  "geometry": {"coordinates":[3.478826046,50.8326339722],"type":"Point"}
}