{
  "type": "Feature",
  "properties": {
    "addr:full":"Begaardenbosstraat 58 Sint-truiden Limburg 3800",
    "addr:housenumber":"58",
    "addr:postcode":"3800",
    "addr:street":"Begaardenbosstraat",
    "iso:country":"BE",
    "sg:address":"Begaardenbosstraat 58",
    "sg:city":"Sint-truiden",
    "sg:orig_category":"Enseignement maternel and primaire",
    "sg:phone":"+32 11 31 46 09",
    "sg:postcode":"3800",
    "sg:province":"Limburg",
    "wof:name":"Vrije Kleuterschool",
    "wof:placetype":"venue"
},
  "geometry": {"coordinates":[5.1863641739,50.8153343201],"type":"Point"}
}