{
  "type": "Feature",
  "properties": {
    "iso:country":"BE",
    "sg:address":"Tervuursesteenweg 27",
    "sg:city":"Bertem",
    "sg:orig_category":"Kapsalons",
    "sg:phone":"+32 16 48 93 70",
    "sg:postcode":"3060",
    "sg:province":"Vlaams-Brabant",
    "wof:name":"Coiffure Hugo & Nancy",
    "wof:placetype":"venue"
},
  "geometry": {"coordinates":[4.6443648338,50.8684997559],"type":"Point"}
}