{
  "type": "Feature",
  "properties": {
    "addr:full":"Grote Markt 30 Diksmuide West-Vlaanderen 8600",
    "addr:housenumber":"30",
    "addr:postcode":"8600",
    "addr:street":"Grote Markt",
    "iso:country":"BE",
    "sg:address":"Grote Markt 30",
    "sg:city":"Diksmuide",
    "sg:orig_category":"Banques and organismes de cr\u00e9dit",
    "sg:phone":"+32 51 50 18 71",
    "sg:postcode":"8600",
    "sg:province":"West-Vlaanderen",
    "wof:name":"Fortis",
    "wof:placetype":"venue"
},
  "geometry": {"coordinates":[2.8648180962,51.0334739685],"type":"Point"}
}