{
  "type": "Feature",
  "properties": {
    "iso:country":"BE",
    "sg:address":"Rue Du Village 61",
    "sg:city":"Florennes (morialm\u00e9)",
    "sg:classifiers":[
        {
            "category":"Banks & Credit Unions",
            "subcategory":"Investment Brokerage",
            "type":"Services"
        }
    ],
    "sg:phone":"+32 71 65 50 33",
    "sg:postcode":"5621",
    "sg:province":"Namur",
    "sg:tags":[
        "repair",
        "-",
        "installation",
        "sanitary",
        "article"
    ],
    "wof:name":"A-bis",
    "wof:placetype":"venue"
},
  "geometry": {"coordinates":[4.5234379768,50.2944030762],"type":"Point"}
}