{
  "type": "Feature",
  "properties": {
    "iso:country":"BE",
    "sg:address":"Collegestraat 28b1",
    "sg:city":"Sint-niklaas",
    "sg:classifiers":[
        {
            "category":"Professional",
            "subcategory":"Business Services",
            "type":"Services"
        }
    ],
    "sg:phone":"+32 3 777 11 52",
    "sg:postcode":"9100",
    "sg:province":"Oost-Vlaanderen",
    "sg:tags":[
        "aux",
        "diver",
        "entreprises"
    ],
    "wof:name":"Agimmo",
    "wof:placetype":"venue"
},
  "geometry": {"coordinates":[4.1396369934,51.1663093567],"type":"Point"}
}