{
  "type": "Feature",
  "properties": {
    "addr:full":"Boulevard Ren\u00c9 Branquart 80 Lessines Hainaut 7860",
    "addr:housenumber":"80",
    "addr:postcode":"7860",
    "addr:street":"Boulevard Rene\u0301 Branquart;Hainaut",
    "iso:country":"BE",
    "sg:address":"Boulevard Ren\u00c9 Branquart 80",
    "sg:city":"Lessines",
    "sg:classifiers":[
        {
            "category":"Cafe",
            "type":"Food & Drink"
        }
    ],
    "sg:phone":"+32 68 33 61 61",
    "sg:postcode":"7860",
    "sg:province":"Hainaut",
    "sg:tags":[
        "caf\u00e9s"
    ],
    "wof:name":"Travenol Laboratories",
    "wof:placetype":"venue"
},
  "geometry": {"coordinates":[3.8306291103,50.6969413757],"type":"Point"}
}