{
  "type": "Feature",
  "properties": {
    "addr:full":"Armentierssteenweg 26 Mesen/messines West-Vlaanderen 8957",
    "addr:housenumber":"26",
    "addr:postcode":"8957",
    "addr:street":"Armentierssteenweg",
    "iso:country":"BE",
    "sg:address":"Armentierssteenweg 26",
    "sg:city":"Mesen/messines",
    "sg:orig_category":"Rundveehouders",
    "sg:phone":"+32 57 44 49 23",
    "sg:postcode":"8957",
    "sg:province":"West-Vlaanderen",
    "wof:name":"Roger Mahieu",
    "wof:placetype":"venue"
},
  "geometry": {"coordinates":[2.8944399357,50.7570075989],"type":"Point"}
}