{
  "type": "Feature",
  "properties": {
    "addr:full":"Sprinkelestraat 54 Zutendaal Limburg 3690",
    "addr:housenumber":"54",
    "addr:postcode":"3690",
    "addr:street":"Sprinkelestraat",
    "iso:country":"BE",
    "sg:address":"Sprinkelestraat 54",
    "sg:city":"Zutendaal",
    "sg:orig_category":"Banken and kredietinstellingen Verzekeringsmakelaars and experts",
    "sg:phone":"+32 89 61 15 57",
    "sg:postcode":"3690",
    "sg:province":"Limburg",
    "wof:name":"Anhyp",
    "wof:placetype":"venue"
},
  "geometry": {"coordinates":[5.5787191391,50.9344596863],"type":"Point"}
}