{
  "type": "Feature",
  "properties": {
    "iso:country":"BE",
    "sg:address":"Rijsvennenstraat 45",
    "sg:city":"Wuustwezel",
    "sg:orig_category":"Sportclubs",
    "sg:phone":"+32 3 669 75 67",
    "sg:postcode":"2990",
    "sg:province":"Antwerpen",
    "wof:name":"Wuustwezel B.b.c.",
    "wof:placetype":"venue"
},
  "geometry": {"coordinates":[4.589507103,51.3917427063],"type":"Point"}
}