{
  "type": "Feature",
  "properties": {
    "addr:full":"Rue Ch\u00e9niat 1b Genappe (baisy-thy) Brabant Wallon 1470",
    "addr:housenumber":"1b",
    "addr:postcode":"1470",
    "addr:street":"Rue Che\u0301Niat",
    "iso:country":"BE",
    "sg:address":"Rue Ch\u00e9niat 1b",
    "sg:city":"Genappe (baisy-thy)",
    "sg:classifiers":[
        {
            "category":"Shopping",
            "subcategory":"Hobbies, Toys, & Games",
            "type":"Retail Goods"
        }
    ],
    "sg:phone":"+32 67 77 29 46",
    "sg:postcode":"1470",
    "sg:province":"Brabant Wallon",
    "sg:tags":[
        "toy",
        "-"
    ],
    "wof:name":"Oliver-toys",
    "wof:placetype":"venue"
},
  "geometry": {"coordinates":[4.4810471535,50.5953521729],"type":"Point"}
}