{
  "type": "Feature",
  "properties": {
    "iso:country":"BE",
    "sg:address":"Avenue Jupiter 11",
    "sg:city":"Chastre",
    "sg:orig_category":"Animations diverses. Location d'appareils audio-visuels",
    "sg:phone":"+32 10 65 73 12",
    "sg:postcode":"1450",
    "sg:province":"Brabant Wallon",
    "wof:name":"Gregory Close",
    "wof:placetype":"venue"
},
  "geometry": {"coordinates":[4.6402711868,50.6087875366],"type":"Point"}
}