{
  "type": "Feature",
  "properties": {
    "addr:full":"Begoniastraat 30bb Nazareth Oost-Vlaanderen 9810",
    "addr:housenumber":"30bb",
    "addr:postcode":"9810",
    "addr:street":"Begoniastraat",
    "iso:country":"BE",
    "sg:address":"Begoniastraat 30bb",
    "sg:city":"Nazareth",
    "sg:classifiers":[
        {
            "category":"Fast Food",
            "type":"Food & Drink"
        }
    ],
    "sg:phone":"+32 9 385 87 43",
    "sg:postcode":"9810",
    "sg:province":"Oost-Vlaanderen",
    "sg:tags":[
        "meeneem",
        "restaurant"
    ],
    "wof:name":"Quick",
    "wof:placetype":"venue"
},
  "geometry": {"coordinates":[3.6608450413,50.9754981995],"type":"Point"}
}