{
  "type": "Feature",
  "properties": {
    "iso:country":"BE",
    "sg:address":"Avenue Des Alli\u00e9s 64",
    "sg:city":"Malmedy",
    "sg:classifiers":[
        {
            "category":"Retail",
            "subcategory":"Funeral Services",
            "type":"Services"
        }
    ],
    "sg:phone":"+32 80 33 01 59",
    "sg:postcode":"4960",
    "sg:province":"Li\u00e8ge",
    "sg:tags":[
        "director"
    ],
    "wof:name":"Fontaine",
    "wof:placetype":"venue"
},
  "geometry": {"coordinates":[6.0192279816,50.4238471985],"type":"Point"}
}