{
  "type": "Feature",
  "properties": {
    "iso:country":"BE",
    "sg:address":"Boskant 18",
    "sg:city":"Westerlo",
    "sg:classifiers":[
        {
            "category":"Recreation",
            "subcategory":"Dance Hall",
            "type":"Entertainment"
        }
    ],
    "sg:phone":"+32 14 54 99 11",
    "sg:postcode":"2260",
    "sg:province":"Antwerpen",
    "sg:tags":[
        "discotheque"
    ],
    "wof:name":"Reflex",
    "wof:placetype":"venue"
},
  "geometry": {"coordinates":[4.9105520248,51.0952262878],"type":"Point"}
}