{
  "type": "Feature",
  "properties": {
    "iso:country":"BE",
    "sg:address":"Constabelstraat 1",
    "sg:city":"Dendermonde",
    "sg:orig_category":"Entretien and r\u00e9parations de voitures. V\u00e9hicules automobiles",
    "sg:phone":"+32 52 42 61 29",
    "sg:postcode":"9200",
    "sg:province":"Oost-Vlaanderen",
    "wof:name":"Garage Decoensel",
    "wof:placetype":"venue"
},
  "geometry": {"coordinates":[4.0234780312,51.0086708069],"type":"Point"}
}