{
  "type": "Feature",
  "properties": {
    "addr:full":"Impasse De Hamme 1 Beauvechain Brabant Wallon 1320",
    "addr:housenumber":"1",
    "addr:postcode":"1320",
    "addr:street":"Impasse De Hamme",
    "iso:country":"BE",
    "sg:address":"Impasse De Hamme 1",
    "sg:city":"Beauvechain",
    "sg:orig_category":"M\u00e9decins and sp\u00e9cialistes",
    "sg:phone":"+32 10 86 07 45",
    "sg:postcode":"1320",
    "sg:province":"Brabant Wallon",
    "wof:name":"Yasmine Sere",
    "wof:placetype":"venue"
},
  "geometry": {"coordinates":[4.7135782242,50.7849235535],"type":"Point"}
}