{
  "type": "Feature",
  "properties": {
    "iso:country":"BE",
    "sg:address":"Kakemanstraat 1",
    "sg:city":"Lebbeke",
    "sg:orig_category":"Alternatieve geneeskunde",
    "sg:phone":"+32 52 35 98 70",
    "sg:postcode":"9280",
    "sg:province":"Oost-Vlaanderen",
    "wof:name":"Luc Uyttenhove",
    "wof:placetype":"venue"
},
  "geometry": {"coordinates":[4.1579751968,50.9928855896],"type":"Point"}
}