{
  "type": "Feature",
  "properties": {
    "iso:country":"BE",
    "sg:address":"Rue Remy-ronse 7",
    "sg:city":"Incourt",
    "sg:orig_category":"Producteurs de l\u00e9gumes",
    "sg:phone":"+32 10 88 88 23",
    "sg:postcode":"1315",
    "sg:province":"Brabant Wallon",
    "wof:name":"Andre Fermier",
    "wof:placetype":"venue"
},
  "geometry": {"coordinates":[4.8397321701,50.6774673462],"type":"Point"}
}