{
  "type": "Feature",
  "properties": {
    "addr:full":"Haagdoornlaan 26 Stabroek (hoevenen) Antwerpen 2940",
    "addr:housenumber":"26",
    "addr:postcode":"2940",
    "addr:street":"Haagdoornlaan",
    "iso:country":"BE",
    "sg:address":"Haagdoornlaan 26",
    "sg:city":"Stabroek (hoevenen)",
    "sg:classifiers":[
        {
            "category":"Home & Garden",
            "subcategory":"Carpets & Floor Coverings",
            "type":"Retail Goods"
        }
    ],
    "sg:phone":"+32 3 605 62 39",
    "sg:postcode":"2940",
    "sg:province":"Antwerpen",
    "sg:tags":[
        "layer",
        "mosaicists"
    ],
    "wof:name":"Van Ackeleyen P",
    "wof:placetype":"venue"
},
  "geometry": {"coordinates":[4.3649148941,51.331943512],"type":"Point"}
}