{
  "type": "Feature",
  "properties": {
    "iso:country":"BE",
    "sg:address":"Paulusstraat 2",
    "sg:city":"Brasschaat",
    "sg:orig_category":"M\u00e9decins and sp\u00e9cialistes",
    "sg:phone":"+32 3 651 30 47",
    "sg:postcode":"2930",
    "sg:province":"Antwerpen",
    "wof:name":"Hilde Daems",
    "wof:placetype":"venue"
},
  "geometry": {"coordinates":[4.4699721336,51.2986907959],"type":"Point"}
}