{
  "type": "Feature",
  "properties": {
    "iso:country":"BE",
    "sg:address":"Altenberger Strasse 1",
    "sg:city":"Kelmis/la Calamine",
    "sg:orig_category":"Kapsalons",
    "sg:phone":"+32 87 65 60 97",
    "sg:postcode":"4728",
    "sg:province":"Li\u00e8ge",
    "wof:name":"Jean-marie\u00b4s Hairshop",
    "wof:placetype":"venue"
},
  "geometry": {"coordinates":[6.0291538239,50.7084617615],"type":"Point"}
}