{
  "type": "Feature",
  "properties": {
    "addr:full":"Pater Segersstraat 22 Sint-niklaas Oost-Vlaanderen 9100",
    "addr:housenumber":"22",
    "addr:postcode":"9100",
    "addr:street":"Pater Segersstraat",
    "iso:country":"BE",
    "sg:address":"Pater Segersstraat 22",
    "sg:city":"Sint-niklaas",
    "sg:classifiers":[
        {
            "category":"Personal",
            "subcategory":"Beauty Salon",
            "type":"Services"
        }
    ],
    "sg:phone":"+32 3 765 06 64",
    "sg:postcode":"9100",
    "sg:province":"Oost-Vlaanderen",
    "wof:name":"Dream Body Center",
    "wof:placetype":"venue"
},
  "geometry": {"coordinates":[4.1364531517,51.1562042236],"type":"Point"}
}