{
  "type": "Feature",
  "properties": {
    "iso:country":"BE",
    "sg:address":"Heimolenstraat 18",
    "sg:city":"Sint-niklaas",
    "sg:orig_category":"Eleveurs de volaille. Eleveurs and marchands de porcs",
    "sg:phone":"+32 3 776 36 52",
    "sg:postcode":"9100",
    "sg:province":"Oost-Vlaanderen",
    "wof:name":"Eddy Van Raemdonck",
    "wof:placetype":"venue"
},
  "geometry": {"coordinates":[4.1322488785,51.1479911804],"type":"Point"}
}