{
  "type": "Feature",
  "properties": {
    "iso:country":"BE",
    "sg:address":"Kapellestraat 73",
    "sg:city":"Aartselaar",
    "sg:orig_category":"Begrafeniswezen",
    "sg:phone":"+32 3 887 52 75",
    "sg:postcode":"2630",
    "sg:province":"Antwerpen",
    "wof:name":"Fa. De Meerleire Mathieu",
    "wof:placetype":"venue"
},
  "geometry": {"coordinates":[4.3894329071,51.1313400269],"type":"Point"}
}