{
  "type": "Feature",
  "properties": {
    "iso:country":"BE",
    "sg:address":"Leegheid 3",
    "sg:city":"Mechelen",
    "sg:classifiers":[
        {
            "category":"Professional",
            "subcategory":"Management & Consulting",
            "type":"Services"
        }
    ],
    "sg:phone":"+32 15 29 00 19",
    "sg:postcode":"2800",
    "sg:province":"Antwerpen",
    "sg:tags":[
        "consultant",
        "agency",
        "advertising"
    ],
    "wof:name":"Van Royen Consulting",
    "wof:placetype":"venue"
},
  "geometry": {"coordinates":[4.4839658737,51.0282592773],"type":"Point"}
}