{
  "type": "Feature",
  "properties": {
    "addr:full":"1014 Peerderbaan 3960 Bree 1014",
    "addr:housenumber":"1014",
    "addr:postcode":"3960;1014",
    "addr:street":"Peerderbaan",
    "iso:country":"BE",
    "sg:address":"1014",
    "sg:city":"Peerderbaan 3960 Bree",
    "sg:classifiers":[
        {
            "category":"Autos & Motor Vehicles",
            "subcategory":"Automobile Sales",
            "type":"Retail Goods"
        }
    ],
    "sg:phone":"+32 71 36 40 50",
    "sg:postcode":"1014",
    "sg:tags":[
        "equipment",
        "motor-cars",
        "transport"
    ],
    "wof:name":"Garage Du Stade Sa",
    "wof:placetype":"venue"
},
  "geometry": {"coordinates":[4.4600768089,50.3901557922],"type":"Point"}
}