{
  "type": "Feature",
  "properties": {
    "addr:full":"Dorpsstraat 90 Overpelt Limburg 3900",
    "addr:housenumber":"90",
    "addr:postcode":"3900",
    "addr:street":"Dorpsstraat",
    "iso:country":"BE",
    "sg:address":"Dorpsstraat 90",
    "sg:city":"Overpelt",
    "sg:classifiers":[
        {
            "category":"Fast Food",
            "type":"Food & Drink"
        }
    ],
    "sg:phone":"+32 11 66 21 75",
    "sg:postcode":"3900",
    "sg:province":"Limburg",
    "sg:tags":[
        "meeneem",
        "restaurant"
    ],
    "wof:name":"Restaurant Kota Radja",
    "wof:placetype":"venue"
},
  "geometry": {"coordinates":[5.4228239059,51.2123298645],"type":"Point"}
}