{
  "type": "Feature",
  "properties": {
    "iso:country":"BE",
    "sg:address":"Lombaardstraat 11b2a",
    "sg:city":"Ieper",
    "sg:classifiers":[
        {
            "category":"Arena",
            "subcategory":"Sports Club",
            "type":"Entertainment"
        }
    ],
    "sg:phone":"+32 57 20 75 32",
    "sg:postcode":"8900",
    "sg:province":"West-Vlaanderen",
    "sg:tags":[
        "de"
    ],
    "wof:name":"B.b.c. Iebac Ieper",
    "wof:placetype":"venue"
},
  "geometry": {"coordinates":[2.8871569633,50.8476257324],"type":"Point"}
}