{
  "type": "Feature",
  "properties": {
    "addr:full":"Doornzeelsestraat 172 Evergem Oost-Vlaanderen 9940",
    "addr:housenumber":"172",
    "addr:postcode":"9940",
    "addr:street":"Doornzeelsestraat;Oost-Vlaanderen",
    "iso:country":"BE",
    "sg:address":"Doornzeelsestraat 172",
    "sg:city":"Evergem",
    "sg:orig_category":"Plantes and fleurs Gr",
    "sg:phone":"+32 9 253 88 24",
    "sg:postcode":"9940",
    "sg:province":"Oost-Vlaanderen",
    "wof:name":"Heungens",
    "wof:placetype":"venue"
},
  "geometry": {"coordinates":[3.7575750351,51.1385650635],"type":"Point"}
}