{
  "type": "Feature",
  "properties": {
    "iso:country":"BE",
    "sg:address":"Blijde-inkomststraat 113",
    "sg:city":"Leuven",
    "sg:classifiers":[
        {
            "category":"Shopping",
            "subcategory":"Clothing, Apparel, & Fashions",
            "type":"Retail Goods"
        }
    ],
    "sg:phone":"+32 16 22 81 88",
    "sg:postcode":"3000",
    "sg:province":"Vlaams-Brabant",
    "sg:tags":[
        "v\u00eatements",
        "pour",
        "dame"
    ],
    "wof:name":"Les Chemisiers Associes",
    "wof:placetype":"venue"
},
  "geometry": {"coordinates":[4.7130742073,50.8746452332],"type":"Point"}
}