{
  "type": "Feature",
  "properties": {
    "iso:country":"BE",
    "sg:address":"Blauwepoortstraat 38",
    "sg:city":"Ieper (zillebeke)",
    "sg:classifiers":[
        {
            "category":"Professional",
            "subcategory":"Printing & Photocopies",
            "type":"Services"
        }
    ],
    "sg:phone":"+32 57 21 86 79",
    "sg:postcode":"8902",
    "sg:province":"West-Vlaanderen",
    "sg:tags":[
        "-",
        "publishing",
        "desktop"
    ],
    "wof:name":"Jered Publishing Bvba",
    "wof:placetype":"venue"
},
  "geometry": {"coordinates":[2.9188089371,50.8332595825],"type":"Point"}
}