{
  "type": "Feature",
  "properties": {
    "iso:country":"BE",
    "sg:address":"Rue De La Marcelle 3",
    "sg:city":"Couvin",
    "sg:orig_category":"Biens d'occasion",
    "sg:phone":"+32 60 39 17 80",
    "sg:postcode":"5660",
    "sg:province":"Namur",
    "wof:name":"Belle Pour Si Peu",
    "wof:placetype":"venue"
},
  "geometry": {"coordinates":[4.496969223,50.048915863],"type":"Point"}
}