{
  "type": "Feature",
  "properties": {
    "iso:country":"BE",
    "sg:address":"Rue De Bonneville 96",
    "sg:city":"Andenne",
    "sg:classifiers":[
        {
            "category":"Professional",
            "type":"Services"
        }
    ],
    "sg:phone":"+32 85 84 18 71",
    "sg:postcode":"5300",
    "sg:province":"Namur",
    "sg:tags":[
        "surveyor",
        "-",
        "valuer"
    ],
    "wof:name":"3e Consult Sprl",
    "wof:placetype":"venue"
},
  "geometry": {"coordinates":[5.0785608292,50.4815216064],"type":"Point"}
}