{
  "type": "Feature",
  "properties": {
    "addr:full":"Kogelstraat 19 Tongeren Limburg 3700",
    "addr:housenumber":"19",
    "addr:postcode":"3700",
    "addr:street":"Kogelstraat",
    "iso:country":"BE",
    "sg:address":"Kogelstraat 19",
    "sg:city":"Tongeren",
    "sg:classifiers":[
        {
            "category":"Professional",
            "subcategory":"Lawyer & Legal Services",
            "type":"Services"
        }
    ],
    "sg:phone":"+32 12 23 23 91",
    "sg:postcode":"3700",
    "sg:province":"Limburg",
    "wof:name":"Meers Werner",
    "wof:placetype":"venue"
},
  "geometry": {"coordinates":[5.4588909149,50.7788505554],"type":"Point"}
}