{
  "type": "Feature",
  "properties": {
    "iso:country":"BE",
    "sg:address":"J De Keersmaekerstraat 21",
    "sg:city":"Asse",
    "sg:orig_category":"Agences d'exp\u00e9dition",
    "sg:phone":"+32 2 463 11 42",
    "sg:postcode":"1731",
    "sg:province":"Vlaams-Brabant",
    "wof:name":"Stilimpex",
    "wof:placetype":"venue"
},
  "geometry": {"coordinates":[4.2614269257,50.8872566223],"type":"Point"}
}