{
  "type": "Feature",
  "properties": {
    "addr:full":"Gordunakaai 60 Gent Oost-Vlaanderen 9000",
    "addr:housenumber":"60",
    "addr:postcode":"9000",
    "addr:street":"Gordunakaai;Oost-Vlaanderen",
    "iso:country":"BE",
    "sg:address":"Gordunakaai 60",
    "sg:city":"Gent",
    "sg:classifiers":[
        {
            "category":"Health Services",
            "subcategory":"Doctor",
            "type":"Services"
        }
    ],
    "sg:phone":"+32 9 222 02 72",
    "sg:postcode":"9000",
    "sg:province":"Oost-Vlaanderen",
    "sg:tags":[
        "medicinephysicians",
        "surgeon"
    ],
    "wof:name":"Cuigniez Philippe",
    "wof:placetype":"venue"
},
  "geometry": {"coordinates":[3.7043850422,51.0433273315],"type":"Point"}
}