{
  "type": "Feature",
  "properties": {
    "iso:country":"BE",
    "sg:address":"Koning Boudewijnlaan 4",
    "sg:city":"Olen",
    "sg:classifiers":[
        {
            "category":"Insurance",
            "subcategory":"Insurance Agent",
            "type":"Services"
        }
    ],
    "sg:phone":"+32 14 27 99 11",
    "sg:postcode":"2250",
    "sg:province":"Antwerpen",
    "sg:tags":[
        "broker"
    ],
    "wof:name":"Zakenkantoor Hermans Andr\u00e9",
    "wof:placetype":"venue"
},
  "geometry": {"coordinates":[4.8588018417,51.1472663879],"type":"Point"}
}