{
  "type": "Feature",
  "properties": {
    "iso:country":"BE",
    "sg:address":"Montagne D\u00b4aisemont 115",
    "sg:city":"Wavre",
    "sg:orig_category":"Begrafeniswezen",
    "sg:phone":"+32 10 22 98 99",
    "sg:postcode":"1300",
    "sg:province":"Brabant Wallon",
    "wof:name":"Fun\u00c9railles F.g.",
    "wof:placetype":"venue"
},
  "geometry": {"coordinates":[4.6154460907,50.71118927],"type":"Point"}
}