{
  "type": "Feature",
  "properties": {
    "addr:full":"Rue De L'aqueduc 38-40 Bruxelles (saint-gilles) Bruxelles-Capitale 1060",
    "addr:housenumber":"38-40",
    "addr:postcode":"1060",
    "addr:street":"Rue De L'Aqueduc",
    "iso:country":"BE",
    "sg:address":"Rue De L'aqueduc 38-40",
    "sg:city":"Bruxelles (saint-gilles)",
    "sg:classifiers":[
        {
            "category":"Shopping",
            "subcategory":"Books",
            "type":"Retail Goods"
        }
    ],
    "sg:phone":"+32 2 544 10 55",
    "sg:postcode":"1060",
    "sg:province":"Bruxelles-Capitale",
    "sg:tags":[
        "antiquarian",
        "trade"
    ],
    "wof:name":"The Romantic Agony Book Auctions",
    "wof:placetype":"venue"
},
  "geometry": {"coordinates":[4.3565797806,50.8252410889],"type":"Point"}
}