{
  "type": "Feature",
  "properties": {
    "addr:full":"Kaai 25 Nieuwpoort West-Vlaanderen 8620",
    "addr:housenumber":"25",
    "addr:postcode":"8620",
    "addr:street":"Kaai",
    "iso:country":"BE",
    "sg:address":"Kaai 25",
    "sg:city":"Nieuwpoort",
    "sg:orig_category":"Sportclubs",
    "sg:phone":"+32 58 23 99 39",
    "sg:postcode":"8620",
    "sg:province":"West-Vlaanderen",
    "wof:name":"De Ijzerbode",
    "wof:placetype":"venue"
},
  "geometry": {"coordinates":[2.7504310608,51.1332054138],"type":"Point"}
}