{
  "type": "Feature",
  "properties": {
    "iso:country":"BE",
    "sg:address":"Rue Toussaint Beaujean 36",
    "sg:city":"Li\u00e8ge 1",
    "sg:classifiers":[
        {
            "category":"Professional",
            "subcategory":"Art Services",
            "type":"Services"
        }
    ],
    "sg:phone":"+32 4 224 31 12",
    "sg:postcode":"4000",
    "sg:province":"Li\u00e8ge",
    "sg:tags":[
        "graphic",
        "designer"
    ],
    "wof:name":"Rico Garcia J",
    "wof:placetype":"venue"
},
  "geometry": {"coordinates":[5.5558400154,50.6499633789],"type":"Point"}
}