{
  "type": "Feature",
  "properties": {
    "addr:full":"Vierde Regiment Karabiniersstraat 25 Zonnebeke (passendale) West-Vlaanderen 8980",
    "addr:housenumber":"25",
    "addr:postcode":"8980",
    "addr:street":"Vierde Regiment Karabiniersstraat",
    "iso:country":"BE",
    "sg:address":"Vierde Regiment Karabiniersstraat 25",
    "sg:city":"Zonnebeke (passendale)",
    "sg:classifiers":[
        {
            "category":"Shopping",
            "subcategory":"Clothing, Apparel, & Fashions",
            "type":"Retail Goods"
        }
    ],
    "sg:phone":"+32 51 77 92 11",
    "sg:postcode":"8980",
    "sg:province":"West-Vlaanderen",
    "sg:tags":[
        "boutique"
    ],
    "wof:name":"Martien",
    "wof:placetype":"venue"
},
  "geometry": {"coordinates":[2.9872550964,50.8730812073],"type":"Point"}
}