{
  "type": "Feature",
  "properties": {
    "iso:country":"BE",
    "sg:address":"Gloriantlaan 64 Box 5",
    "sg:city":"Antwerpen",
    "sg:classifiers":[
        {
            "category":"Real Estate",
            "subcategory":"Architect",
            "type":"Services"
        }
    ],
    "sg:phone":"+32 3 219 58 90",
    "sg:postcode":"2050",
    "sg:province":"Antwerpen",
    "wof:name":"Van Grimbergen K",
    "wof:placetype":"venue"
},
  "geometry": {"coordinates":[4.3859901428,51.2237892151],"type":"Point"}
}