{
  "type": "Feature",
  "properties": {
    "iso:country":"BE",
    "sg:address":"Stallestraat 94",
    "sg:city":"Ukkel/uccle",
    "sg:classifiers":[
        {
            "category":"Restaurant",
            "type":"Food & Drink"
        }
    ],
    "sg:phone":"+32 2 376 57 61",
    "sg:postcode":"1180",
    "sg:province":"Bruxelles-Capitale",
    "wof:name":"La Becquee",
    "wof:placetype":"venue"
},
  "geometry": {"coordinates":[4.331679821,50.7974510193],"type":"Point"}
}