{
  "type": "Feature",
  "properties": {
    "iso:country":"BE",
    "sg:address":"Deuzeldlaan 205",
    "sg:city":"Schoten",
    "sg:orig_category":"Kapsalons",
    "sg:phone":"+32 3 645 97 81",
    "sg:postcode":"2900",
    "sg:province":"Antwerpen",
    "wof:name":"Kristel's Kapsalon",
    "wof:placetype":"venue"
},
  "geometry": {"coordinates":[4.46961689,51.2454452515],"type":"Point"}
}