{
  "type": "Feature",
  "properties": {
    "addr:full":"Brusselsesteenweg 450 Zemst Vlaams-Brabant 1980",
    "addr:housenumber":"450",
    "addr:postcode":"1980",
    "addr:street":"Brusselsesteenweg;Vlaams-Brabant",
    "iso:country":"BE",
    "sg:address":"Brusselsesteenweg 450",
    "sg:city":"Zemst",
    "sg:orig_category":"Bloemen and planten",
    "sg:phone":"+32 15 61 79 52",
    "sg:postcode":"1980",
    "sg:province":"Vlaams-Brabant",
    "wof:name":"'t Zonneke",
    "wof:placetype":"venue"
},
  "geometry": {"coordinates":[4.4552798271,50.9738502502],"type":"Point"}
}