{
  "type": "Feature",
  "properties": {
    "iso:country":"BE",
    "sg:address":"Rue De Paris 15",
    "sg:city":"Tournai",
    "sg:classifiers":[
        {
            "category":"Insurance",
            "subcategory":"Life Insurance",
            "type":"Services"
        }
    ],
    "sg:phone":"+32 69 89 02 40",
    "sg:postcode":"7500",
    "sg:province":"Hainaut",
    "sg:tags":[
        "assurance"
    ],
    "wof:name":"Benoit Hoyos",
    "wof:placetype":"venue"
},
  "geometry": {"coordinates":[3.3933250904,50.6117019653],"type":"Point"}
}