{
  "type": "Feature",
  "properties": {
    "addr:full":"Dokter Maurice Timmermanslaan 13b Antwerpen (merksem) Antwerpen 2170",
    "addr:housenumber":"13b",
    "addr:postcode":"2170",
    "addr:street":"Dokter Maurice Timmermanslaan",
    "iso:country":"BE",
    "sg:address":"Dokter Maurice Timmermanslaan 13b",
    "sg:city":"Antwerpen (merksem)",
    "sg:classifiers":[
        {
            "category":"Professional",
            "subcategory":"Accounting & Tax Preparation",
            "type":"Services"
        }
    ],
    "sg:phone":"+32 3 646 82 86",
    "sg:postcode":"2170",
    "sg:province":"Antwerpen",
    "sg:tags":[
        "bookkeeper"
    ],
    "wof:name":"Neefs L",
    "wof:placetype":"venue"
},
  "geometry": {"coordinates":[4.4505147934,51.246723175],"type":"Point"}
}