{
  "type": "Feature",
  "properties": {
    "addr:full":"Kerkplein 13 Izegem West-Vlaanderen 8870",
    "addr:housenumber":"13",
    "addr:postcode":"8870",
    "addr:street":"Kerkplein",
    "iso:country":"BE",
    "sg:address":"Kerkplein 13",
    "sg:city":"Izegem",
    "sg:orig_category":"Diverse kredietdiensten",
    "sg:postcode":"8870",
    "sg:province":"West-Vlaanderen",
    "wof:name":"Bancontact-mister Cash",
    "wof:placetype":"venue"
},
  "geometry": {"coordinates":[3.2153429985,50.9163970947],"type":"Point"}
}