{
  "type": "Feature",
  "properties": {
    "iso:country":"BE",
    "sg:address":"Place 10",
    "sg:city":"Incourt (opprebais)",
    "sg:classifiers":[
        {
            "category":"Home & Garden",
            "subcategory":"Garden Supply",
            "type":"Retail Goods"
        }
    ],
    "sg:phone":"+32 477 88 80 65",
    "sg:postcode":"1315",
    "sg:province":"Brabant Wallon",
    "sg:tags":[
        "machine",
        "agricultural",
        "-"
    ],
    "wof:name":"Du Champs Des Allouettes Scrl",
    "wof:placetype":"venue"
},
  "geometry": {"coordinates":[4.7959899902,50.6823196411],"type":"Point"}
}