{
  "type": "Feature",
  "properties": {
    "iso:country":"BE",
    "sg:address":"Hoeksken 66",
    "sg:city":"Evergem",
    "sg:orig_category":"Opticiens",
    "sg:phone":"+32 9 253 92 90",
    "sg:postcode":"9940",
    "sg:province":"Oost-Vlaanderen",
    "wof:name":"Van Bossele M.",
    "wof:placetype":"venue"
},
  "geometry": {"coordinates":[3.7041540146,51.1110305786],"type":"Point"}
}