{
  "type": "Feature",
  "properties": {
    "iso:country":"BE",
    "sg:address":"Rue Du Sarrazin 0",
    "sg:city":"Beloeil",
    "sg:orig_category":"Gestion des d\u00e9charges and sites d\u00e9finitifs de stockage",
    "sg:phone":"+32 69 56 20 56",
    "sg:postcode":"7972",
    "sg:province":"Hainaut",
    "wof:name":"Parcs A Conteneurs Beloeil",
    "wof:placetype":"venue"
},
  "geometry": {"coordinates":[3.6921050549,50.5274238586],"type":"Point"}
}