{
  "type": "Feature",
  "properties": {
    "addr:full":"Bosmanslei 29 Antwerpen Antwerpen 2018",
    "addr:housenumber":"29",
    "addr:postcode":"2018",
    "addr:street":"Bosmanslei",
    "iso:country":"BE",
    "sg:address":"Bosmanslei 29",
    "sg:city":"Antwerpen",
    "sg:classifiers":[
        {
            "category":"Banks & Credit Unions",
            "subcategory":"Financial Services",
            "type":"Services"
        }
    ],
    "sg:phone":"+32 3 238 60 34",
    "sg:postcode":"2018",
    "sg:province":"Antwerpen",
    "sg:tags":[
        "loan",
        "mortgage"
    ],
    "wof:name":"Vlaams Woningfonds Van De Grote Gezinnen Cvba",
    "wof:placetype":"venue"
},
  "geometry": {"coordinates":[4.4023141861,51.194606781],"type":"Point"}
}