{
  "type": "Feature",
  "properties": {
    "iso:country":"BE",
    "sg:address":"Rue Naniot 142",
    "sg:city":"Li\u00e8ge 1",
    "sg:classifiers":[
        {
            "category":"Building & Trades",
            "subcategory":"Construction",
            "type":"Services"
        }
    ],
    "sg:phone":"+32 4 224 30 21",
    "sg:postcode":"4000",
    "sg:province":"Li\u00e8ge",
    "sg:tags":[
        "installation",
        "-",
        "central",
        "heating"
    ],
    "wof:name":"Dehasse R",
    "wof:placetype":"venue"
},
  "geometry": {"coordinates":[5.5577440262,50.6539611816],"type":"Point"}
}