{
  "type": "Feature",
  "properties": {
    "addr:full":"Singel 76 Borsbeek Antwerpen 2150",
    "addr:housenumber":"76",
    "addr:postcode":"2150",
    "addr:street":"Singel",
    "iso:country":"BE",
    "sg:address":"Singel 76",
    "sg:city":"Borsbeek",
    "sg:orig_category":"Installation de menuiserie en bois and plastique",
    "sg:phone":"+32 3 322 55 08",
    "sg:postcode":"2150",
    "sg:province":"Antwerpen",
    "wof:name":"Johan De Vocht",
    "wof:placetype":"venue"
},
  "geometry": {"coordinates":[4.4861040115,51.2007064819],"type":"Point"}
}