{
  "type": "Feature",
  "properties": {
    "iso:country":"BE",
    "sg:address":"Oude Stationstraat 5",
    "sg:city":"Herne",
    "sg:classifiers":[
        {
            "category":"Bars & Pubs",
            "type":"Food & Drink"
        }
    ],
    "sg:phone":"+32 2 396 25 56",
    "sg:postcode":"1540",
    "sg:province":"Vlaams-Brabant",
    "wof:name":"Lib\u00e9rale Harmonie",
    "wof:placetype":"venue"
},
  "geometry": {"coordinates":[4.0206570625,50.7255249023],"type":"Point"}
}