{
  "type": "Feature",
  "properties": {
    "iso:country":"BE",
    "sg:address":"Rue De L'int\u00c9rieur 162",
    "sg:city":"Perwez",
    "sg:orig_category":"Jardinage",
    "sg:phone":"+32 81 65 67 87",
    "sg:postcode":"1360",
    "sg:province":"Brabant Wallon",
    "wof:name":"Vandernelde Ph.",
    "wof:placetype":"venue"
},
  "geometry": {"coordinates":[4.7699589729,50.619594574],"type":"Point"}
}