{
  "type": "Feature",
  "properties": {
    "iso:country":"BE",
    "sg:address":"L\u00c9on Theodorstraat 217",
    "sg:city":"Jette",
    "sg:orig_category":"Brood, gebak and snoepgoed Slagers",
    "sg:phone":"+32 2 426 41 77",
    "sg:postcode":"1090",
    "sg:province":"Bruxelles-Capitale",
    "wof:name":"Guy Boon",
    "wof:placetype":"venue"
},
  "geometry": {"coordinates":[4.3293371201,50.8789978027],"type":"Point"}
}