{
  "type": "Feature",
  "properties": {
    "iso:country":"BE",
    "sg:address":"Rue Du Centre 25",
    "sg:city":"Trois-ponts - Fosse",
    "sg:classifiers":[
        {
            "category":"Farming",
            "subcategory":"Livestock Farm",
            "type":"Manufacturing & Wholesale Goods"
        }
    ],
    "sg:phone":"+32 80 86 23 82",
    "sg:postcode":"4980",
    "sg:province":"Li\u00e8ge",
    "sg:tags":[
        "buyer"
    ],
    "wof:name":"Mignon M",
    "wof:placetype":"venue"
},
  "geometry": {"coordinates":[5.9202442169,50.3550033569],"type":"Point"}
}