{
  "type": "Feature",
  "properties": {
    "iso:country":"BE",
    "sg:address":"Varendonksebaan 7",
    "sg:city":"Laakdal",
    "sg:orig_category":"Producteurs de l\u00e9gumes. Fleurs and plantes",
    "sg:phone":"+32 14 54 85 42",
    "sg:postcode":"2431",
    "sg:province":"Antwerpen",
    "wof:name":"Ludovicus Rens",
    "wof:placetype":"venue"
},
  "geometry": {"coordinates":[4.9452548027,51.0718688965],"type":"Point"}
}