{
  "type": "Feature",
  "properties": {
    "addr:full":"Rue Jean-charles De Hugo 100a Tintigny (bellefontaine) Luxembourg 6730",
    "addr:housenumber":"100a",
    "addr:postcode":"6730",
    "addr:street":"Rue Jean-Charles De Hugo",
    "iso:country":"BE",
    "sg:address":"Rue Jean-charles De Hugo 100a",
    "sg:city":"Tintigny (bellefontaine)",
    "sg:classifiers":[
        {
            "category":"Shopping",
            "subcategory":"Clothing, Apparel, & Fashions",
            "type":"Retail Goods"
        }
    ],
    "sg:phone":"+32 63 44 41 09",
    "sg:postcode":"6730",
    "sg:province":"Luxembourg",
    "sg:tags":[
        "boutique"
    ],
    "wof:name":"New Solutex",
    "wof:placetype":"venue"
},
  "geometry": {"coordinates":[5.4965991974,49.6642570496],"type":"Point"}
}