{
  "type": "Feature",
  "properties": {
    "iso:country":"BE",
    "sg:address":"Opitterstraat 7",
    "sg:city":"Bree",
    "sg:classifiers":[
        {
            "category":"Restaurant",
            "type":"Food & Drink"
        }
    ],
    "sg:phone":"+32 89 46 46 27",
    "sg:postcode":"3960",
    "sg:province":"Limburg",
    "wof:name":"De Keyzer",
    "wof:placetype":"venue"
},
  "geometry": {"coordinates":[5.5996809006,51.1412963867],"type":"Point"}
}