{
  "type": "Feature",
  "properties": {
    "iso:country":"BE",
    "sg:address":"Hekkouterstraat 21",
    "sg:city":"Lierde",
    "sg:orig_category":"Verplichte sociale verzekeringen",
    "sg:phone":"+32 54 41 58 30",
    "sg:postcode":"9570",
    "sg:province":"Oost-Vlaanderen",
    "wof:name":"Chistelijke Mutualiteit",
    "wof:placetype":"venue"
},
  "geometry": {"coordinates":[3.8463759422,50.7869033813],"type":"Point"}
}