{
  "type": "Feature",
  "properties": {
    "addr:full":"Place Du Sud 50 Quaregnon Hainaut 7390",
    "addr:housenumber":"50",
    "addr:postcode":"7390",
    "addr:street":"Place Du Sud",
    "iso:country":"BE",
    "sg:address":"Place Du Sud 50",
    "sg:city":"Quaregnon",
    "sg:classifiers":[
        {
            "category":"Education",
            "subcategory":"School",
            "type":"Public Place"
        }
    ],
    "sg:phone":"+32 65 66 70 27",
    "sg:postcode":"7390",
    "sg:province":"Hainaut",
    "sg:tags":[
        "primary"
    ],
    "wof:name":"Ecole Sainte-bernadette",
    "wof:placetype":"venue"
},
  "geometry": {"coordinates":[3.8673799038,50.4234580994],"type":"Point"}
}