{
  "type": "Feature",
  "properties": {
    "iso:country":"BE",
    "sg:address":"Pylyserlaan 48",
    "sg:city":"Koksijde",
    "sg:classifiers":[
        {
            "category":"Building & Trades",
            "subcategory":"Landscaping Services",
            "type":"Services"
        }
    ],
    "sg:phone":"+32 58 51 13 94",
    "sg:postcode":"8670",
    "sg:province":"West-Vlaanderen",
    "sg:tags":[
        "gardening",
        "garden",
        "maintenance"
    ],
    "wof:name":"Willaert",
    "wof:placetype":"venue"
},
  "geometry": {"coordinates":[2.6513850689,51.1087226868],"type":"Point"}
}