{
  "type": "Feature",
  "properties": {
    "addr:full":"Bleuckeveldlaan 69 Tervuren Vlaams-Brabant 3080",
    "addr:housenumber":"69",
    "addr:postcode":"3080",
    "addr:street":"Bleuckeveldlaan",
    "iso:country":"BE",
    "sg:address":"Bleuckeveldlaan 69",
    "sg:city":"Tervuren",
    "sg:classifiers":[
        {
            "category":"Arena",
            "subcategory":"Sports Club",
            "type":"Entertainment"
        }
    ],
    "sg:phone":"+32 2 767 99 21",
    "sg:postcode":"3080",
    "sg:province":"Vlaams-Brabant",
    "sg:tags":[
        "de"
    ],
    "wof:name":"V.c. Don Bosco",
    "wof:placetype":"venue"
},
  "geometry": {"coordinates":[4.5376391411,50.8493614197],"type":"Point"}
}