{
  "type": "Feature",
  "properties": {
    "iso:country":"BE",
    "sg:address":"Schansstraat 27",
    "sg:city":"Kortenaken",
    "sg:classifiers":[
        {
            "category":"Insurance",
            "subcategory":"Life Insurance",
            "type":"Services"
        }
    ],
    "sg:phone":"+32 11 58 31 83",
    "sg:postcode":"3470",
    "sg:province":"Vlaams-Brabant",
    "sg:tags":[
        "assurance"
    ],
    "wof:name":"D. Schollen",
    "wof:placetype":"venue"
},
  "geometry": {"coordinates":[5.0662789345,50.9075393677],"type":"Point"}
}