{
  "type": "Feature",
  "properties": {
    "addr:full":"Driemastenstraat 1 Sint-eloois-winkel West-Vlaanderen 8880",
    "addr:housenumber":"1",
    "addr:postcode":"8880",
    "addr:street":"Driemastenstraat;West-Vlaanderen",
    "iso:country":"BE",
    "sg:address":"Driemastenstraat 1",
    "sg:city":"Sint-eloois-winkel",
    "sg:orig_category":"MEUBELONTWERP AND -INSTALLATIE",
    "sg:phone":"+32 56 50 52 83",
    "sg:postcode":"8880",
    "sg:province":"West-Vlaanderen",
    "wof:name":"De Bruyne Patrick",
    "wof:placetype":"venue"
},
  "geometry": {"coordinates":[3.1746048927,50.8664665222],"type":"Point"}
}