{
  "type": "Feature",
  "properties": {
    "addr:full":"Boulevard Paul Janson 49 Box 36 Charleroi Hainaut 6000",
    "addr:housenumber":"49 box 36",
    "addr:postcode":"6000",
    "addr:street":"Boulevard Paul Janson;Hainaut",
    "iso:country":"BE",
    "sg:address":"Boulevard Paul Janson 49 Box 36",
    "sg:city":"Charleroi",
    "sg:classifiers":[
        {
            "category":"Insurance",
            "subcategory":"Insurance Agent",
            "type":"Services"
        }
    ],
    "sg:phone":"+32 71 32 33 47",
    "sg:postcode":"6000",
    "sg:province":"Hainaut",
    "sg:tags":[
        "broker"
    ],
    "wof:name":"Roba J.m.",
    "wof:placetype":"venue"
},
  "geometry": {"coordinates":[4.4477591515,50.4137229919],"type":"Point"}
}