{
  "type": "Feature",
  "properties": {
    "iso:country":"BE",
    "sg:address":"Vise Voie 76",
    "sg:city":"Li\u00c8ge",
    "sg:orig_category":"Artsen and specialisten",
    "sg:phone":"+32 4 226 98 47",
    "sg:postcode":"4000",
    "sg:province":"Li\u00e8ge",
    "wof:name":"Anne-marie Flamand",
    "wof:placetype":"venue"
},
  "geometry": {"coordinates":[5.5646100044,50.6647720337],"type":"Point"}
}