{
  "type": "Feature",
  "properties": {
    "addr:full":"Rozenlaan 4 Kampenhout Vlaams-Brabant 1910",
    "addr:housenumber":"4",
    "addr:postcode":"1910",
    "addr:street":"Rozenlaan",
    "iso:country":"BE",
    "sg:address":"Rozenlaan 4",
    "sg:city":"Kampenhout",
    "sg:orig_category":"Fietsen Fab",
    "sg:phone":"+32 16 65 71 25",
    "sg:postcode":"1910",
    "sg:province":"Vlaams-Brabant",
    "wof:name":"Koga - Miyata",
    "wof:placetype":"venue"
},
  "geometry": {"coordinates":[4.5246338844,50.9217033386],"type":"Point"}
}