{
  "type": "Feature",
  "properties": {
    "iso:country":"BE",
    "sg:address":"Rue F\u00e9lix Maigret De Priches 7",
    "sg:city":"Mons (saint-symphorien)",
    "sg:classifiers":[
        {
            "category":"Building & Trades",
            "subcategory":"Construction",
            "type":"Services"
        }
    ],
    "sg:phone":"+32 65 35 49 09",
    "sg:postcode":"7030",
    "sg:province":"Hainaut",
    "sg:tags":[
        "installation",
        "-",
        "central",
        "heating"
    ],
    "wof:name":"Az Confor Sprl",
    "wof:placetype":"venue"
},
  "geometry": {"coordinates":[4.0108299255,50.4393882751],"type":"Point"}
}