{
  "type": "Feature",
  "properties": {
    "addr:full":"Albertpl 23 Knokke-heist West-Vlaanderen 8300",
    "addr:housenumber":"23",
    "addr:postcode":"8300",
    "addr:street":"Albertpl",
    "iso:country":"BE",
    "sg:address":"Albertpl 23",
    "sg:city":"Knokke-heist",
    "sg:classifiers":[
        {
            "category":"Travel",
            "subcategory":"Hotels & Motels",
            "type":"Entertainment"
        }
    ],
    "sg:phone":"+32 50 60 11 34",
    "sg:postcode":"8300",
    "sg:province":"West-Vlaanderen",
    "sg:tags":[
        "fair",
        "business",
        "restaurant",
        "game",
        "professional",
        "sport",
        "hotels"
    ],
    "wof:name":"Memlinc Hotel Nv",
    "wof:placetype":"venue"
},
  "geometry": {"coordinates":[3.2903289795,51.3418731689],"type":"Point"}
}