{
  "type": "Feature",
  "properties": {
    "addr:full":"Baaigemstraat 274 Gavere Oost-Vlaanderen 9890",
    "addr:housenumber":"274",
    "addr:postcode":"9890",
    "addr:street":"Baaigemstraat",
    "iso:country":"BE",
    "sg:address":"Baaigemstraat 274",
    "sg:city":"Gavere",
    "sg:orig_category":"Eleveurs de bovins",
    "sg:phone":"+32 9 384 15 51",
    "sg:postcode":"9890",
    "sg:province":"Oost-Vlaanderen",
    "wof:name":"Herve Verhoye",
    "wof:placetype":"venue"
},
  "geometry": {"coordinates":[3.7030360699,50.9335746765],"type":"Point"}
}