{
  "type": "Feature",
  "properties": {
    "addr:full":"Jukschot 23 Zoersel Antwerpen 2980",
    "addr:housenumber":"23",
    "addr:postcode":"2980",
    "addr:street":"Jukschot",
    "iso:country":"BE",
    "sg:address":"Jukschot 23",
    "sg:city":"Zoersel",
    "sg:orig_category":"Travaux de pl\u00e2trage",
    "sg:phone":"+32 3 385 18 20",
    "sg:postcode":"2980",
    "sg:province":"Antwerpen",
    "wof:name":"Remon",
    "wof:placetype":"venue"
},
  "geometry": {"coordinates":[4.713435173,51.269985199],"type":"Point"}
}