{
  "type": "Feature",
  "properties": {
    "iso:country":"BE",
    "sg:address":"Rue Des C\u00c8dres 20",
    "sg:city":"Frameries",
    "sg:orig_category":"Artistes ind\u00e9pendants",
    "sg:phone":"+32 65 66 30 46",
    "sg:postcode":"7080",
    "sg:province":"Hainaut",
    "wof:name":"Bertiaux",
    "wof:placetype":"venue"
},
  "geometry": {"coordinates":[3.8811039925,50.4013633728],"type":"Point"}
}