{
  "type": "Feature",
  "properties": {
    "addr:full":"Diksmuidsestraat 19 Ieper West-Vlaanderen 8900",
    "addr:housenumber":"19",
    "addr:postcode":"8900",
    "addr:street":"Diksmuidsestraat",
    "iso:country":"BE",
    "sg:address":"Diksmuidsestraat 19",
    "sg:city":"Ieper",
    "sg:orig_category":"Bloemen and planten",
    "sg:phone":"+32 57 20 37 79",
    "sg:postcode":"8900",
    "sg:province":"West-Vlaanderen",
    "wof:name":"Huis Ilo-flor",
    "wof:placetype":"venue"
},
  "geometry": {"coordinates":[2.8862841129,50.8523712158],"type":"Point"}
}