{
  "type": "Feature",
  "properties": {
    "addr:full":"Avenue Victor Rousseau 14 Bruxelles (forest) Bruxelles-Capitale 1190",
    "addr:housenumber":"14",
    "addr:postcode":"1190",
    "addr:street":"Avenue Victor Rousseau",
    "iso:country":"BE",
    "sg:address":"Avenue Victor Rousseau 14",
    "sg:city":"Bruxelles (forest)",
    "sg:classifiers":[
        {
            "category":"Shopping",
            "subcategory":"Clothing, Apparel, & Fashions",
            "type":"Retail Goods"
        }
    ],
    "sg:phone":"+32 2 345 36 30",
    "sg:postcode":"1190",
    "sg:province":"Bruxelles-Capitale",
    "sg:tags":[
        "uniform"
    ],
    "wof:name":"Show Room",
    "wof:placetype":"venue"
},
  "geometry": {"coordinates":[4.3358368874,50.8160629272],"type":"Point"}
}