{
  "type": "Feature",
  "properties": {
    "iso:country":"BE",
    "sg:address":"Claesplein 21",
    "sg:city":"Halle (lembeek)",
    "sg:classifiers":[
        {
            "category":"Bars & Pubs",
            "type":"Food & Drink"
        }
    ],
    "sg:phone":"+32 2 356 71 63",
    "sg:postcode":"1502",
    "sg:province":"Vlaams-Brabant",
    "wof:name":"Centrum",
    "wof:placetype":"venue"
},
  "geometry": {"coordinates":[4.2227578163,50.7136077881],"type":"Point"}
}