{
  "type": "Feature",
  "properties": {
    "addr:full":"Faubourg De Bruxelles 25 Charleroi (gosselies) Hainaut 6041",
    "addr:housenumber":"25",
    "addr:postcode":"6041",
    "addr:street":"Faubourg De Bruxelles",
    "iso:country":"BE",
    "sg:address":"Faubourg De Bruxelles 25",
    "sg:city":"Charleroi (gosselies)",
    "sg:classifiers":[
        {
            "category":"Professional",
            "subcategory":"Credit Reporting & Collection",
            "type":"Services"
        }
    ],
    "sg:phone":"+32 71 35 24 65",
    "sg:postcode":"6041",
    "sg:province":"Hainaut",
    "sg:tags":[
        "bailiff"
    ],
    "wof:name":"Conotte A",
    "wof:placetype":"venue"
},
  "geometry": {"coordinates":[4.4314317703,50.4685935974],"type":"Point"}
}