{
  "type": "Feature",
  "properties": {
    "addr:full":"Molenstraat 31 Wuustwezel Antwerpen 2990",
    "addr:housenumber":"31",
    "addr:postcode":"2990",
    "addr:street":"Molenstraat",
    "iso:country":"BE",
    "sg:address":"Molenstraat 31",
    "sg:city":"Wuustwezel",
    "sg:orig_category":"Eleveurs de volaille",
    "sg:phone":"+32 3 669 84 17",
    "sg:postcode":"2990",
    "sg:province":"Antwerpen",
    "wof:name":"Jozef Rombouts",
    "wof:placetype":"venue"
},
  "geometry": {"coordinates":[4.5784220695,51.3978652954],"type":"Point"}
}