{
  "type": "Feature",
  "properties": {
    "iso:country":"BE",
    "sg:address":"Le Grand Closin 4",
    "sg:city":"Lasne (ohain)",
    "sg:classifiers":[
        {
            "category":"Real Estate",
            "subcategory":"Developer",
            "type":"Services"
        }
    ],
    "sg:phone":"+32 2 351 37 27",
    "sg:postcode":"1380",
    "sg:province":"Brabant Wallon",
    "sg:tags":[
        "project"
    ],
    "wof:name":"Lasne Village Sa",
    "wof:placetype":"venue"
},
  "geometry": {"coordinates":[4.483235836,50.6850166321],"type":"Point"}
}