{
  "type": "Feature",
  "properties": {
    "iso:country":"BE",
    "sg:address":"Nieuwstraat 21",
    "sg:city":"Mol",
    "sg:orig_category":"Boekhouders",
    "sg:phone":"+32 14 34 63 41",
    "sg:postcode":"2400",
    "sg:province":"Antwerpen",
    "wof:name":"Johan Swinnen",
    "wof:placetype":"venue"
},
  "geometry": {"coordinates":[5.1145739555,51.1836624146],"type":"Point"}
}