{
  "type": "Feature",
  "properties": {
    "iso:country":"BE",
    "sg:address":"Poperingseweg 341",
    "sg:city":"Ieper",
    "sg:orig_category":"Schoenen",
    "sg:phone":"+32 57 20 13 25",
    "sg:postcode":"8908",
    "sg:province":"West-Vlaanderen",
    "wof:name":"Gisele Delahaye",
    "wof:placetype":"venue"
},
  "geometry": {"coordinates":[2.8248291016,50.8534622192],"type":"Point"}
}