{
  "type": "Feature",
  "properties": {
    "iso:country":"BE",
    "sg:address":"Stendrich 21",
    "sg:city":"Eupen",
    "sg:classifiers":[
        {
            "category":"Communications",
            "subcategory":"Television Station",
            "type":"Services"
        }
    ],
    "sg:phone":"+32 87 76 02 20",
    "sg:postcode":"4700",
    "sg:province":"Li\u00e8ge",
    "sg:tags":[
        "use",
        "transmission",
        "cables",
        "finished",
        "ready",
        "data"
    ],
    "wof:name":"Eltec S.a.",
    "wof:placetype":"venue"
},
  "geometry": {"coordinates":[6.022465229,50.6267318726],"type":"Point"}
}