{
  "type": "Feature",
  "properties": {
    "iso:country":"BE",
    "sg:address":"Pieter Van Maldereplein 8",
    "sg:city":"Edegem",
    "sg:orig_category":"Enseignement maternel and primaire",
    "sg:phone":"+32 3 449 41 22",
    "sg:postcode":"2650",
    "sg:province":"Antwerpen",
    "wof:name":"Vrije Kleuterschool",
    "wof:placetype":"venue"
},
  "geometry": {"coordinates":[4.4197878838,51.1575050354],"type":"Point"}
}