{
  "type": "Feature",
  "properties": {
    "addr:full":"Drogenbroodstraat 28 Evergem Oost-Vlaanderen 9940",
    "addr:housenumber":"28",
    "addr:postcode":"9940",
    "addr:street":"Drogenbroodstraat;Oost-Vlaanderen",
    "iso:country":"BE",
    "sg:address":"Drogenbroodstraat 28",
    "sg:city":"Evergem",
    "sg:orig_category":"Newspapers, magazines, periodicals - Distribution",
    "sg:phone":"+32 9 357 39 59",
    "sg:postcode":"9940",
    "sg:province":"Oost-Vlaanderen",
    "wof:name":"De Leeuwerik Bvba",
    "wof:placetype":"venue"
},
  "geometry": {"coordinates":[3.7329649925,51.1327819824],"type":"Point"}
}