{
  "type": "Feature",
  "properties": {
    "addr:full":"Vijfwegenstraat 5 Izegem West-Vlaanderen 8870",
    "addr:housenumber":"5",
    "addr:postcode":"8870",
    "addr:street":"Vijfwegenstraat",
    "iso:country":"BE",
    "sg:address":"Vijfwegenstraat 5",
    "sg:city":"Izegem",
    "sg:orig_category":"Boucheries",
    "sg:phone":"+32 51 30 20 88",
    "sg:postcode":"8870",
    "sg:province":"West-Vlaanderen",
    "wof:name":"Beenhouwerij Chris",
    "wof:placetype":"venue"
},
  "geometry": {"coordinates":[3.216408968,50.9251899719],"type":"Point"}
}