{
  "type": "Feature",
  "properties": {
    "iso:country":"BE",
    "sg:address":"Chaussee Gabrielle Richet 231",
    "sg:city":"Lessines",
    "sg:orig_category":"Gelatine Capsules",
    "sg:phone":"+32 68 33 22 33",
    "sg:postcode":"7860",
    "sg:province":"Hainaut",
    "wof:name":"Les Planteurs R\u00e9unis 2000 S.a.",
    "wof:placetype":"venue"
},
  "geometry": {"coordinates":[3.8529770374,50.6940345764],"type":"Point"}
}