{
  "type": "Feature",
  "properties": {
    "addr:full":"Kruishoefstr 52 Dilsen-stokkem Limburg 3650",
    "addr:housenumber":"52",
    "addr:postcode":"3650",
    "addr:street":"Kruishoefstr",
    "iso:country":"BE",
    "sg:address":"Kruishoefstr 52",
    "sg:city":"Dilsen-stokkem",
    "sg:classifiers":[
        {
            "category":"Manufacturing",
            "subcategory":"Metals",
            "type":"Manufacturing & Wholesale Goods"
        }
    ],
    "sg:phone":"+32 89 79 01 01",
    "sg:postcode":"3650",
    "sg:province":"Limburg",
    "sg:tags":[
        "metallurgy",
        "metalworking",
        "processing"
    ],
    "wof:name":"Alro Nv",
    "wof:placetype":"venue"
},
  "geometry": {"coordinates":[5.6905617714,51.0419578552],"type":"Point"}
}