{
  "type": "Feature",
  "properties": {
    "addr:full":"Dorpsstraat 107 Brecht Antwerpen 2960",
    "addr:housenumber":"107",
    "addr:postcode":"2960",
    "addr:street":"Dorpsstraat",
    "iso:country":"BE",
    "sg:address":"Dorpsstraat 107",
    "sg:city":"Brecht",
    "sg:orig_category":"Drogueries",
    "sg:phone":"+32 3 313 70 76",
    "sg:postcode":"2960",
    "sg:province":"Antwerpen",
    "wof:name":"Marc Anthonissen",
    "wof:placetype":"venue"
},
  "geometry": {"coordinates":[4.6415200233,51.3512115479],"type":"Point"}
}