{
  "type": "Feature",
  "properties": {
    "addr:full":"Smisstraat 20 Zottegem (sint-goriks-oudenhove) Oost-Vlaanderen 9620",
    "addr:housenumber":"20",
    "addr:postcode":"9620",
    "addr:street":"Smisstraat",
    "iso:country":"BE",
    "sg:address":"Smisstraat 20",
    "sg:city":"Zottegem (sint-goriks-oudenhove)",
    "sg:classifiers":[
        {
            "category":"Retail",
            "subcategory":"Auto Repair",
            "type":"Services"
        }
    ],
    "sg:phone":"+32 9 361 09 40",
    "sg:postcode":"9620",
    "sg:province":"Oost-Vlaanderen",
    "sg:tags":[
        "automobile-body"
    ],
    "wof:name":"Filip Carrosserie",
    "wof:placetype":"venue"
},
  "geometry": {"coordinates":[3.7830250263,50.8530044556],"type":"Point"}
}