{
  "type": "Feature",
  "properties": {
    "iso:country":"BE",
    "sg:address":"2150",
    "sg:city":"Borsbeek (grand)",
    "sg:orig_category":"Pharmaciens",
    "sg:phone":"+32 900 10 500",
    "sg:postcode":"2150",
    "sg:province":"Antwerpen",
    "wof:name":"Pharmacies De Garde",
    "wof:placetype":"venue"
},
  "geometry": {"coordinates":[4.4843549728,51.1943016052],"type":"Point"}
}