{
  "type": "Feature",
  "properties": {
    "iso:country":"BE",
    "sg:address":"Chauss\u00c9e De Namur 67",
    "sg:city":"Nivelles",
    "sg:orig_category":"Herstellingen and onderhoud van auto's Voertuigen",
    "sg:phone":"+32 67 21 51 11",
    "sg:postcode":"1400",
    "sg:province":"Brabant Wallon",
    "wof:name":"Garage Christian Weber",
    "wof:placetype":"venue"
},
  "geometry": {"coordinates":[4.3584051132,50.5973587036],"type":"Point"}
}