{
  "type": "Feature",
  "properties": {
    "addr:full":"Avenue Du G\u00e9n\u00e9ral De Gaulle 44 Mons Hainaut 7000",
    "addr:housenumber":"44",
    "addr:postcode":"7000",
    "addr:street":"Avenue Du Ge\u0301Ne\u0301Ral De Gaulle;Hainaut",
    "iso:country":"BE",
    "sg:address":"Avenue Du G\u00e9n\u00e9ral De Gaulle 44",
    "sg:city":"Mons",
    "sg:classifiers":[
        {
            "category":"Health Services",
            "subcategory":"Health Practitioner",
            "type":"Services"
        }
    ],
    "sg:phone":"+32 65 31 14 47",
    "sg:postcode":"7000",
    "sg:province":"Hainaut",
    "sg:tags":[
        "psychologist"
    ],
    "wof:name":"Martroye K",
    "wof:placetype":"venue"
},
  "geometry": {"coordinates":[3.9468688965,50.4444999695],"type":"Point"}
}