{
  "type": "Feature",
  "properties": {
    "addr:full":"Av. Emile Rousseau 1 Charleroi Hainaut 6000",
    "addr:housenumber":"1",
    "addr:postcode":"6000",
    "addr:street":"Av. Emile Rousseau;Hainaut",
    "iso:country":"BE",
    "sg:address":"Av. Emile Rousseau 1",
    "sg:city":"Charleroi",
    "sg:orig_category":"Flash Butt Welding Machines",
    "sg:phone":"+32 71 44 60 20",
    "sg:postcode":"6000",
    "sg:province":"Hainaut",
    "wof:name":"Coil Joining International S.a.",
    "wof:placetype":"venue"
},
  "geometry": {"coordinates":[4.4501590729,50.4260139465],"type":"Point"}
}