{
  "type": "Feature",
  "properties": {
    "addr:full":"Buitensteinde 10 Geel Antwerpen 2440",
    "addr:housenumber":"10",
    "addr:postcode":"2440",
    "addr:street":"Buitensteinde",
    "iso:country":"BE",
    "sg:address":"Buitensteinde 10",
    "sg:city":"Geel",
    "sg:classifiers":[
        {
            "category":"Real Estate",
            "subcategory":"Architect",
            "type":"Services"
        }
    ],
    "sg:phone":"+32 14 58 94 83",
    "sg:postcode":"2440",
    "sg:province":"Antwerpen",
    "wof:name":"Beneens J",
    "wof:placetype":"venue"
},
  "geometry": {"coordinates":[4.9339962006,51.1677131653],"type":"Point"}
}