{
  "type": "Feature",
  "properties": {
    "iso:country":"BE",
    "sg:address":"Molendreef 68ba",
    "sg:city":"Anzegem",
    "sg:orig_category":"Entretien et r\u00e9parations de v\u00e9hicules \u00e0 domicile. R\u00e9cup\u00e9ration de mati\u00e8res m\u00e9talliques recyclables a",
    "sg:phone":"+32 56 77 89 96",
    "sg:postcode":"8570",
    "sg:province":"West-Vlaanderen",
    "wof:name":"Fa. Bekaert",
    "wof:placetype":"venue"
},
  "geometry": {"coordinates":[3.4000720978,50.8409767151],"type":"Point"}
}