{
  "type": "Feature",
  "properties": {
    "iso:country":"BE",
    "sg:address":"Hulstedorp 16",
    "sg:city":"Harelbeke (hulste)",
    "sg:classifiers":[
        {
            "category":"Food & Beverages",
            "subcategory":"Groceries & Convenience Stores",
            "type":"Retail Goods"
        }
    ],
    "sg:phone":"+32 56 71 26 09",
    "sg:postcode":"8531",
    "sg:province":"West-Vlaanderen",
    "sg:tags":[
        "grocer"
    ],
    "wof:name":"Desmet",
    "wof:placetype":"venue"
},
  "geometry": {"coordinates":[3.3104400635,50.8748130798],"type":"Point"}
}