{
  "type": "Feature",
  "properties": {
    "addr:full":"Rue De Herve 76 Li\u00c8ge Li\u00e8ge 4030",
    "addr:housenumber":"76",
    "addr:postcode":"4030",
    "addr:street":"Rue De Herve",
    "iso:country":"BE",
    "sg:address":"Rue De Herve 76",
    "sg:city":"Li\u00c8ge",
    "sg:orig_category":"M\u00e9decins and sp\u00e9cialistes",
    "sg:phone":"+32 4 361 18 02",
    "sg:postcode":"4030",
    "sg:province":"Li\u00e8ge",
    "wof:name":"H\u00c9l\u00c8ne Maud\u00b4huy",
    "wof:placetype":"venue"
},
  "geometry": {"coordinates":[5.6046648026,50.6188240051],"type":"Point"}
}