{
  "type": "Feature",
  "properties": {
    "addr:full":"Vissersstraat 55-59 Blankenberge West-Vlaanderen 8370",
    "addr:housenumber":"55-59",
    "addr:postcode":"8370",
    "addr:street":"Vissersstraat",
    "iso:country":"BE",
    "sg:address":"Vissersstraat 55-59",
    "sg:city":"Blankenberge",
    "sg:classifiers":[
        {
            "category":"Bars & Pubs",
            "type":"Food & Drink"
        }
    ],
    "sg:phone":"+32 50 41 85 02",
    "sg:postcode":"8370",
    "sg:province":"West-Vlaanderen",
    "sg:tags":[
        "tavern"
    ],
    "wof:name":"Tommies",
    "wof:placetype":"venue"
},
  "geometry": {"coordinates":[3.1282119751,51.3155021667],"type":"Point"}
}