{
  "type": "Feature",
  "properties": {
    "addr:full":"Molenheidebaan 111 Boortmeerbeek Vlaams-Brabant 3191",
    "addr:housenumber":"111",
    "addr:postcode":"3191",
    "addr:street":"Molenheidebaan",
    "iso:country":"BE",
    "sg:address":"Molenheidebaan 111",
    "sg:city":"Boortmeerbeek",
    "sg:orig_category":"Rev\u00eatements pour sols and murs. Peinture",
    "sg:phone":"+32 15 61 39 22",
    "sg:postcode":"3191",
    "sg:province":"Vlaams-Brabant",
    "wof:name":"Emiel Kiebooms",
    "wof:placetype":"venue"
},
  "geometry": {"coordinates":[4.5218400955,50.9872512817],"type":"Point"}
}