{
  "type": "Feature",
  "properties": {
    "addr:full":"Avenue Charles Madoux 13 Oudergem/auderghem Bruxelles-Capitale 1160",
    "addr:housenumber":"13",
    "addr:postcode":"1160",
    "addr:street":"Avenue Charles Madoux;/",
    "iso:country":"BE",
    "sg:address":"Avenue Charles Madoux 13",
    "sg:city":"Oudergem/auderghem",
    "sg:orig_category":"Avocats and conseillers juridiques",
    "sg:phone":"+32 2 740 00 41",
    "sg:postcode":"1160",
    "sg:province":"Bruxelles-Capitale",
    "wof:name":"Isabelle Hock",
    "wof:placetype":"venue"
},
  "geometry": {"coordinates":[4.4013609886,50.8241729736],"type":"Point"}
}