{
  "type": "Feature",
  "properties": {
    "iso:country":"BE",
    "sg:address":"Rue Bonne-femme 13",
    "sg:city":"Li\u00c8ge",
    "sg:orig_category":"Kapsalons",
    "sg:phone":"+32 4 343 82 66",
    "sg:postcode":"4030",
    "sg:province":"Li\u00e8ge",
    "wof:name":"Coiffure Marie",
    "wof:placetype":"venue"
},
  "geometry": {"coordinates":[5.5885910988,50.6283302307],"type":"Point"}
}