{
  "type": "Feature",
  "properties": {
    "addr:full":"Rue Egide Van Ophem 2 Bruxelles (uccle) Bruxelles-Capitale 1180",
    "addr:housenumber":"2",
    "addr:postcode":"1180",
    "addr:street":"Rue Egide Van Ophem",
    "iso:country":"BE",
    "sg:address":"Rue Egide Van Ophem 2",
    "sg:city":"Bruxelles (uccle)",
    "sg:classifiers":[
        {
            "category":"Bars & Pubs",
            "type":"Food & Drink"
        }
    ],
    "sg:phone":"+32 2 376 45 29",
    "sg:postcode":"1180",
    "sg:province":"Bruxelles-Capitale",
    "sg:tags":[
        "tavern"
    ],
    "wof:name":"Softy (le)",
    "wof:placetype":"venue"
},
  "geometry": {"coordinates":[4.3320951462,50.7911186218],"type":"Point"}
}