{
  "type": "Feature",
  "properties": {
    "iso:country":"BE",
    "sg:address":"Jagersweg 103",
    "sg:city":"Meerhout",
    "sg:orig_category":"Instituts de beaut\u00e9",
    "sg:phone":"+32 14 30 10 69",
    "sg:postcode":"2450",
    "sg:province":"Antwerpen",
    "wof:name":"Pedicure Martine",
    "wof:placetype":"venue"
},
  "geometry": {"coordinates":[5.0586800575,51.1319503784],"type":"Point"}
}