{
  "type": "Feature",
  "properties": {
    "iso:country":"BE",
    "sg:address":"Rue Des Foug\u00c8res 179",
    "sg:city":"Charleroi",
    "sg:orig_category":"V\u00e9t\u00e9rinaires",
    "sg:phone":"+32 71 43 94 44",
    "sg:postcode":"6010",
    "sg:province":"Hainaut",
    "wof:name":"Colette Sinon",
    "wof:placetype":"venue"
},
  "geometry": {"coordinates":[4.4563860893,50.3848724365],"type":"Point"}
}