{
  "type": "Feature",
  "properties": {
    "addr:full":"Nieuwkerkestraat 2 Heuvelland West-Vlaanderen 8952",
    "addr:housenumber":"2",
    "addr:postcode":"8952",
    "addr:street":"Nieuwkerkestraat",
    "iso:country":"BE",
    "sg:address":"Nieuwkerkestraat 2",
    "sg:city":"Heuvelland",
    "sg:orig_category":"Rookartikelen",
    "sg:phone":"+32 57 44 42 31",
    "sg:postcode":"8952",
    "sg:province":"West-Vlaanderen",
    "wof:name":"Mario Vermeulen",
    "wof:placetype":"venue"
},
  "geometry": {"coordinates":[2.8515300751,50.7591896057],"type":"Point"}
}