{
  "type": "Feature",
  "properties": {
    "addr:full":"Place Sainte-v\u00e9ronique 2 Li\u00e8ge 1 Li\u00e8ge 4000",
    "addr:housenumber":"2;1",
    "addr:postcode":"4000",
    "addr:street":"Place Sainte-Ve\u0301Ronique",
    "iso:country":"BE",
    "sg:address":"Place Sainte-v\u00e9ronique 2",
    "sg:city":"Li\u00e8ge 1",
    "sg:classifiers":[
        {
            "category":"Shopping",
            "subcategory":"Books",
            "type":"Retail Goods"
        }
    ],
    "sg:phone":"+32 4 252 23 63",
    "sg:postcode":"4000",
    "sg:province":"Li\u00e8ge",
    "sg:tags":[
        "bookseller"
    ],
    "wof:name":"Ste V\u00e9ronique (librairie)",
    "wof:placetype":"venue"
},
  "geometry": {"coordinates":[5.5655632019,50.6318321228],"type":"Point"}
}