{
  "type": "Feature",
  "properties": {
    "addr:full":"Vinkenlaan 26 Ternat Vlaams-Brabant 1742",
    "addr:housenumber":"26",
    "addr:postcode":"1742",
    "addr:street":"Vinkenlaan",
    "iso:country":"BE",
    "sg:address":"Vinkenlaan 26",
    "sg:city":"Ternat",
    "sg:orig_category":"Imprimeries and copyshops",
    "sg:phone":"+32 2 582 43 74",
    "sg:postcode":"1742",
    "sg:province":"Vlaams-Brabant",
    "wof:name":"Andre Goessens",
    "wof:placetype":"venue"
},
  "geometry": {"coordinates":[4.1571450233,50.8688087463],"type":"Point"}
}