{
  "type": "Feature",
  "properties": {
    "iso:country":"BE",
    "sg:address":"Rue De La Duch\u00e8re 149",
    "sg:city":"Charleroi (montignies-sur-sambre)",
    "sg:classifiers":[
        {
            "category":"Health Services",
            "subcategory":"Nursing And Care Facility",
            "type":"Services"
        }
    ],
    "sg:phone":"+32 71 32 16 36",
    "sg:postcode":"6061",
    "sg:province":"Hainaut",
    "sg:tags":[
        "home"
    ],
    "wof:name":"Thiebaut Fr.",
    "wof:placetype":"venue"
},
  "geometry": {"coordinates":[4.4870429039,50.4077033997],"type":"Point"}
}