{
  "type": "Feature",
  "properties": {
    "iso:country":"BE",
    "sg:address":"Groeningenlei 65 Box 2",
    "sg:city":"Kontich",
    "sg:classifiers":[
        {
            "category":"Professional",
            "subcategory":"Computer Services",
            "type":"Services"
        }
    ],
    "sg:phone":"+32 3 457 43 17",
    "sg:postcode":"2550",
    "sg:province":"Antwerpen",
    "sg:tags":[
        "-",
        "processing",
        "data",
        "software"
    ],
    "wof:name":"Jofe -soft Cvba",
    "wof:placetype":"venue"
},
  "geometry": {"coordinates":[4.4348659515,51.1384353638],"type":"Point"}
}