{
  "type": "Feature",
  "properties": {
    "addr:full":"Korspelsesteenweg 179 Beringen (beverlo) Limburg 3581",
    "addr:housenumber":"179",
    "addr:postcode":"3581",
    "addr:street":"Korspelsesteenweg",
    "iso:country":"BE",
    "sg:address":"Korspelsesteenweg 179",
    "sg:city":"Beringen (beverlo)",
    "sg:classifiers":[
        {
            "category":"Personal",
            "subcategory":"Beauty Salon",
            "type":"Services"
        }
    ],
    "sg:phone":"+32 11 39 33 16",
    "sg:postcode":"3581",
    "sg:province":"Limburg",
    "sg:tags":[
        "lady",
        "-",
        "hairdressing"
    ],
    "wof:name":"Lowet W",
    "wof:placetype":"venue"
},
  "geometry": {"coordinates":[5.2345099449,51.0883598328],"type":"Point"}
}