{
  "type": "Feature",
  "properties": {
    "addr:full":"Malosewaver 107 Geel Antwerpen 2440",
    "addr:housenumber":"107",
    "addr:postcode":"2440",
    "addr:street":"Malosewaver",
    "iso:country":"BE",
    "sg:address":"Malosewaver 107",
    "sg:city":"Geel",
    "sg:orig_category":"V\u00eatements",
    "sg:phone":"+32 14 58 92 59",
    "sg:postcode":"2440",
    "sg:province":"Antwerpen",
    "wof:name":"Almatex",
    "wof:placetype":"venue"
},
  "geometry": {"coordinates":[5.0484972,51.1619949341],"type":"Point"}
}