{
  "type": "Feature",
  "properties": {
    "addr:full":"Rue Courtois 32 Li\u00c8ge Li\u00e8ge 4000",
    "addr:housenumber":"32",
    "addr:postcode":"4000",
    "addr:street":"Rue Courtois",
    "iso:country":"BE",
    "sg:address":"Rue Courtois 32",
    "sg:city":"Li\u00c8ge",
    "sg:orig_category":"Advocaten and juridische adviseurs",
    "sg:phone":"+32 4 223 38 97",
    "sg:postcode":"4000",
    "sg:province":"Li\u00e8ge",
    "wof:name":"Yves Richard",
    "wof:placetype":"venue"
},
  "geometry": {"coordinates":[5.5608291626,50.6342887878],"type":"Point"}
}