{
  "type": "Feature",
  "properties": {
    "iso:country":"BE",
    "sg:address":"Rue Des Soeurs Grises 8bb",
    "sg:city":"Mons",
    "sg:orig_category":"Magasins de r\u00e9parations d'articles personnels et m\u00e9nagers divers",
    "sg:phone":"+32 65 34 85 42",
    "sg:postcode":"7000",
    "sg:province":"Hainaut",
    "wof:name":"Boutique Retouches",
    "wof:placetype":"venue"
},
  "geometry": {"coordinates":[3.9462850094,50.4515419006],"type":"Point"}
}