{
  "type": "Feature",
  "properties": {
    "iso:country":"BE",
    "sg:address":"Chauss\u00e9e De Louvain 740",
    "sg:city":"Namur (champion - Cognel\u00e9e)",
    "sg:classifiers":[
        {
            "category":"Autos & Motor Vehicles",
            "subcategory":"Automobile Sales",
            "type":"Retail Goods"
        }
    ],
    "sg:phone":"+32 81 21 41 03",
    "sg:postcode":"5020",
    "sg:province":"Namur",
    "sg:tags":[
        "car",
        "used",
        "-"
    ],
    "wof:name":"Michel Cars",
    "wof:placetype":"venue"
},
  "geometry": {"coordinates":[4.7952418327,50.4352035522],"type":"Point"}
}