{
  "type": "Feature",
  "properties": {
    "iso:country":"BE",
    "sg:address":"Markt 11",
    "sg:city":"Gavere",
    "sg:classifiers":[
        {
            "category":"Insurance",
            "subcategory":"Insurance Agent",
            "type":"Services"
        }
    ],
    "sg:phone":"+32 9 384 10 86",
    "sg:postcode":"9890",
    "sg:province":"Oost-Vlaanderen",
    "sg:tags":[
        "broker"
    ],
    "wof:name":"Stevens Verzekeringen Nv",
    "wof:placetype":"venue"
},
  "geometry": {"coordinates":[3.6601479053,50.9286842346],"type":"Point"}
}