{
  "type": "Feature",
  "properties": {
    "addr:full":"Rue Albert Ier 34 Ransart Hainaut 6043",
    "addr:housenumber":"34",
    "addr:postcode":"6043",
    "addr:street":"Rue Albert Ier;Hainaut",
    "iso:country":"BE",
    "sg:address":"Rue Albert Ier 34",
    "sg:city":"Ransart",
    "sg:classifiers":[
        {
            "category":"Home & Garden",
            "subcategory":"Furniture",
            "type":"Retail Goods"
        }
    ],
    "sg:phone":"+32 71 35 24 10",
    "sg:postcode":"6043",
    "sg:province":"Hainaut",
    "sg:tags":[
        "bathroom"
    ],
    "wof:name":"Dullier Et Fils S.p.r.l.",
    "wof:placetype":"venue"
},
  "geometry": {"coordinates":[4.4785909653,50.4609985352],"type":"Point"}
}