{
  "type": "Feature",
  "properties": {
    "addr:full":"Langestraat 20 Gent (ledeberg) Oost-Vlaanderen 9050",
    "addr:housenumber":"20",
    "addr:postcode":"9050",
    "addr:street":"Langestraat",
    "iso:country":"BE",
    "sg:address":"Langestraat 20",
    "sg:city":"Gent (ledeberg)",
    "sg:classifiers":[
        {
            "category":"Health Services",
            "subcategory":"Health Practitioner",
            "type":"Services"
        }
    ],
    "sg:phone":"+32 9 232 48 00",
    "sg:postcode":"9050",
    "sg:province":"Oost-Vlaanderen",
    "sg:tags":[
        "therapist",
        "speech"
    ],
    "wof:name":"Logomug Bvba",
    "wof:placetype":"venue"
},
  "geometry": {"coordinates":[3.7447669506,51.0389938354],"type":"Point"}
}