{
  "type": "Feature",
  "properties": {
    "iso:country":"BE",
    "sg:address":"Frederik Lintsstraat 154",
    "sg:city":"Leuven",
    "sg:classifiers":[
        {
            "category":"Health Services",
            "subcategory":"Doctor",
            "type":"Services"
        }
    ],
    "sg:phone":"+32 16 23 36 20",
    "sg:postcode":"3000",
    "sg:province":"Vlaams-Brabant",
    "sg:tags":[
        "medicinephysicians",
        "surgeon"
    ],
    "wof:name":"Deglin Griet",
    "wof:placetype":"venue"
},
  "geometry": {"coordinates":[4.7065792084,50.8711891174],"type":"Point"}
}