{
  "type": "Feature",
  "properties": {
    "addr:full":"Mottestraat 32 Meise (wolvertem) Vlaams-Brabant 1861",
    "addr:housenumber":"32",
    "addr:postcode":"1861",
    "addr:street":"Mottestraat",
    "iso:country":"BE",
    "sg:address":"Mottestraat 32",
    "sg:city":"Meise (wolvertem)",
    "sg:classifiers":[
        {
            "category":"Bars & Pubs",
            "type":"Food & Drink"
        }
    ],
    "sg:phone":"+32 2 269 44 54",
    "sg:postcode":"1861",
    "sg:province":"Vlaams-Brabant",
    "wof:name":"Jeanneke (bij)",
    "wof:placetype":"venue"
},
  "geometry": {"coordinates":[4.3073401451,50.9526138306],"type":"Point"}
}