{
  "type": "Feature",
  "properties": {
    "iso:country":"BE",
    "sg:address":"Ouderdomseweg 18",
    "sg:city":"Ieper",
    "sg:orig_category":"Eleveurs and marchands de porcs. Production and transformation de viande",
    "sg:phone":"+32 57 44 46 02",
    "sg:postcode":"8900",
    "sg:province":"West-Vlaanderen",
    "wof:name":"Daniel Deceuninck",
    "wof:placetype":"venue"
},
  "geometry": {"coordinates":[2.8119530678,50.8159942627],"type":"Point"}
}