{
  "type": "Feature",
  "properties": {
    "iso:country":"BE",
    "sg:address":"Rue De Ploegsteert 118",
    "sg:city":"Comines-warneton (ploegsteert)",
    "sg:classifiers":[
        {
            "category":"Bars & Pubs",
            "type":"Food & Drink"
        }
    ],
    "sg:phone":"+32 56 58 81 97",
    "sg:postcode":"7782",
    "sg:province":"Hainaut",
    "wof:name":"Pomme D'or (la)",
    "wof:placetype":"venue"
},
  "geometry": {"coordinates":[2.8795371056,50.7278747559],"type":"Point"}
}