{
  "type": "Feature",
  "properties": {
    "addr:full":"Rue Charles Martel 64 Bruxelles Bruxelles-Capitale 1000",
    "addr:housenumber":"64",
    "addr:postcode":"1000",
    "addr:street":"Rue Charles Martel",
    "iso:country":"BE",
    "sg:address":"Rue Charles Martel 64",
    "sg:city":"Bruxelles",
    "sg:classifiers":[
        {
            "category":"Shopping",
            "subcategory":"Florist",
            "type":"Retail Goods"
        }
    ],
    "sg:phone":"+32 2 231 16 86",
    "sg:postcode":"1000",
    "sg:province":"Bruxelles-Capitale",
    "wof:name":"Herbes & Petales Sprl",
    "wof:placetype":"venue"
},
  "geometry": {"coordinates":[4.3820829391,50.8464126587],"type":"Point"}
}