{
  "type": "Feature",
  "properties": {
    "iso:country":"BE",
    "sg:address":"Winterstraat 19",
    "sg:city":"Bilzen",
    "sg:classifiers":[
        {
            "category":"Health Services",
            "subcategory":"Dentist",
            "type":"Services"
        }
    ],
    "sg:phone":"+32 89 49 14 11",
    "sg:postcode":"3740",
    "sg:province":"Limburg",
    "wof:name":"Kellens D",
    "wof:placetype":"venue"
},
  "geometry": {"coordinates":[5.5179162025,50.8745117188],"type":"Point"}
}