{
  "type": "Feature",
  "properties": {
    "addr:full":"Zakstraat 13 Mechelen Antwerpen 2800",
    "addr:housenumber":"13",
    "addr:postcode":"2800",
    "addr:street":"Zakstraat",
    "iso:country":"BE",
    "sg:address":"Zakstraat 13",
    "sg:city":"Mechelen",
    "sg:classifiers":[
        {
            "category":"Professional",
            "subcategory":"Management & Consulting",
            "type":"Services"
        }
    ],
    "sg:phone":"+32 15 20 84 09",
    "sg:postcode":"2800",
    "sg:province":"Antwerpen",
    "sg:tags":[
        "-",
        "processing",
        "data",
        "consultant"
    ],
    "wof:name":"Pcsystems",
    "wof:placetype":"venue"
},
  "geometry": {"coordinates":[4.482749939,51.02784729],"type":"Point"}
}