{
  "type": "Feature",
  "properties": {
    "addr:full":"Oude Aarschotsebaan 22a Heist-op-den-berg (booischot) Antwerpen 2221",
    "addr:housenumber":"22a",
    "addr:postcode":"2221",
    "addr:street":"Oude Aarschotsebaan",
    "iso:country":"BE",
    "sg:address":"Oude Aarschotsebaan 22a",
    "sg:city":"Heist-op-den-berg (booischot)",
    "sg:classifiers":[
        {
            "category":"Health Services",
            "subcategory":"Health Practitioner",
            "type":"Services"
        }
    ],
    "sg:phone":"+32 15 22 43 70",
    "sg:postcode":"2221",
    "sg:province":"Antwerpen",
    "sg:tags":[
        "physiotherapist"
    ],
    "wof:name":"Van Dessel Paul",
    "wof:placetype":"venue"
},
  "geometry": {"coordinates":[4.7739758492,51.0512428284],"type":"Point"}
}