{
  "type": "Feature",
  "properties": {
    "addr:full":"Ftroul 1 Onhaye (weillen) Namur 5523",
    "addr:housenumber":"1",
    "addr:postcode":"5523",
    "addr:street":"Ftroul;Weillen",
    "iso:country":"BE",
    "sg:address":"Ftroul 1",
    "sg:city":"Onhaye (weillen)",
    "sg:classifiers":[
        {
            "category":"Building & Trades",
            "subcategory":"Construction",
            "type":"Services"
        }
    ],
    "sg:phone":"+32 82 69 96 42",
    "sg:postcode":"5523",
    "sg:province":"Namur",
    "sg:tags":[
        "carpenter"
    ],
    "wof:name":"Arte E",
    "wof:placetype":"venue"
},
  "geometry": {"coordinates":[4.8000969887,50.2619590759],"type":"Point"}
}