{
  "type": "Feature",
  "properties": {
    "addr:full":"Rue Vigneron 31b Charleroi (ransart) Hainaut 6043",
    "addr:housenumber":"31b",
    "addr:postcode":"6043",
    "addr:street":"Rue Vigneron",
    "iso:country":"BE",
    "sg:address":"Rue Vigneron 31b",
    "sg:city":"Charleroi (ransart)",
    "sg:classifiers":[
        {
            "category":"Home & Garden",
            "subcategory":"Building Materials",
            "type":"Retail Goods"
        }
    ],
    "sg:phone":"+32 71 35 23 19",
    "sg:postcode":"6043",
    "sg:province":"Hainaut",
    "sg:tags":[
        "window"
    ],
    "wof:name":"Lefevre Clovis Pvc",
    "wof:placetype":"venue"
},
  "geometry": {"coordinates":[4.4204950333,50.4460105896],"type":"Point"}
}