{
  "type": "Feature",
  "properties": {
    "addr:full":"Sint-kristoffelsstraat 30 Brussel/bruxelles Bruxelles-Capitale 1000",
    "addr:housenumber":"30",
    "addr:postcode":"1000",
    "addr:street":"Sint-Kristoffelsstraat;/",
    "iso:country":"BE",
    "sg:address":"Sint-kristoffelsstraat 30",
    "sg:city":"Brussel/bruxelles",
    "sg:orig_category":"Boekenuitgeverijen Platenmaatschappijen",
    "sg:phone":"+32 2 512 73 61",
    "sg:postcode":"1000",
    "sg:province":"Bruxelles-Capitale",
    "wof:name":"Vedette",
    "wof:placetype":"venue"
},
  "geometry": {"coordinates":[4.3461079597,50.84740448],"type":"Point"}
}