{
  "type": "Feature",
  "properties": {
    "addr:full":"Rue Du Couvent 5 Li\u00e8ge 1 (jupille-sur-meuse) Li\u00e8ge 4020",
    "addr:housenumber":"5;1",
    "addr:postcode":"4020",
    "addr:street":"Rue Du Couvent;Jupille-Sur-Meuse Lie\u0300Ge",
    "iso:country":"BE",
    "sg:address":"Rue Du Couvent 5",
    "sg:city":"Li\u00e8ge 1 (jupille-sur-meuse)",
    "sg:classifiers":[
        {
            "category":"Shopping",
            "subcategory":"Jewelry",
            "type":"Retail Goods"
        }
    ],
    "sg:phone":"+32 4 370 26 36",
    "sg:postcode":"4020",
    "sg:province":"Li\u00e8ge",
    "sg:tags":[
        "jeweller",
        "-"
    ],
    "wof:name":"M & M",
    "wof:placetype":"venue"
},
  "geometry": {"coordinates":[5.6417012215,50.6418075562],"type":"Point"}
}