{
  "type": "Feature",
  "properties": {
    "addr:full":"Chauss\u00c9e De Charleroi 149 Genappe Brabant Wallon 1470",
    "addr:housenumber":"149",
    "addr:postcode":"1470",
    "addr:street":"Chausse\u0301E De Charleroi;Wallon",
    "iso:country":"BE",
    "sg:address":"Chauss\u00c9e De Charleroi 149",
    "sg:city":"Genappe",
    "sg:orig_category":"V\u00e9t\u00e9rinaires",
    "sg:phone":"+32 67 79 01 25",
    "sg:postcode":"1470",
    "sg:province":"Brabant Wallon",
    "wof:name":"Willy Vermaut",
    "wof:placetype":"venue"
},
  "geometry": {"coordinates":[4.4512500763,50.6069488525],"type":"Point"}
}