{
  "type": "Feature",
  "properties": {
    "iso:country":"BE",
    "sg:address":"Rue Catherine 1",
    "sg:city":"Soignies",
    "sg:orig_category":"Quincailleries",
    "sg:phone":"+32 67 33 15 16",
    "sg:postcode":"7062",
    "sg:province":"Hainaut",
    "wof:name":"Michel Mabille",
    "wof:placetype":"venue"
},
  "geometry": {"coordinates":[4.0996851921,50.5541000366],"type":"Point"}
}