{
  "type": "Feature",
  "properties": {
    "addr:full":"Chauss\u00c9e De March\u00c9 796 Namur Namur 5100",
    "addr:housenumber":"796",
    "addr:postcode":"5100",
    "addr:street":"Chausse\u0301E De Marche\u0301",
    "iso:country":"BE",
    "sg:address":"Chauss\u00c9e De March\u00c9 796",
    "sg:city":"Namur",
    "sg:orig_category":"Rev\u00eatements de sols and murs",
    "sg:phone":"+32 81 40 26 45",
    "sg:postcode":"5100",
    "sg:province":"Namur",
    "wof:name":"Discount Carrelages 2000",
    "wof:placetype":"venue"
},
  "geometry": {"coordinates":[4.8713750839,50.4566345215],"type":"Point"}
}