{
  "type": "Feature",
  "properties": {
    "iso:country":"BE",
    "sg:address":"Scheldestraat 18",
    "sg:city":"Bornem",
    "sg:orig_category":"Toeristische diensten",
    "sg:phone":"+32 3 889 06 03",
    "sg:postcode":"2880",
    "sg:province":"Antwerpen",
    "wof:name":"V.v.v.",
    "wof:placetype":"venue"
},
  "geometry": {"coordinates":[4.1918568611,51.1025505066],"type":"Point"}
}