{
  "type": "Feature",
  "properties": {
    "iso:country":"BE",
    "sg:address":"Avenue De Ch\u00e9r\u00e9mont 17",
    "sg:city":"Wavre",
    "sg:classifiers":[
        {
            "category":"Government",
            "subcategory":"Fire Station",
            "type":"Public Place"
        }
    ],
    "sg:phone":"+32 10 22 95 38",
    "sg:postcode":"1300",
    "sg:province":"Brabant Wallon",
    "sg:tags":[
        "extinguisher"
    ],
    "wof:name":"Borlee G",
    "wof:placetype":"venue"
},
  "geometry": {"coordinates":[4.625535965,50.7073898315],"type":"Point"}
}