{
  "type": "Feature",
  "properties": {
    "addr:full":"Rue Du Bassin Collecteur 9 Bruxelles Bruxelles-Capitale 1130",
    "addr:housenumber":"9",
    "addr:postcode":"1130",
    "addr:street":"Rue Du Bassin Collecteur",
    "iso:country":"BE",
    "sg:address":"Rue Du Bassin Collecteur 9",
    "sg:city":"Bruxelles",
    "sg:classifiers":[
        {
            "category":"Manufacturing",
            "subcategory":"Signs",
            "type":"Manufacturing & Wholesale Goods"
        }
    ],
    "sg:phone":"+32 2 215 13 00",
    "sg:postcode":"1130",
    "sg:province":"Bruxelles-Capitale",
    "sg:tags":[
        "-",
        "illuminated"
    ],
    "wof:name":"Copel Sa",
    "wof:placetype":"venue"
},
  "geometry": {"coordinates":[4.4206228256,50.8851318359],"type":"Point"}
}