{
  "type": "Feature",
  "properties": {
    "addr:full":"Chauss\u00e9e De Li\u00e8ge Nandrin Li\u00e8ge 4550",
    "addr:postcode":"4550",
    "addr:street":"Chausse\u0301E De Lie\u0300Ge",
    "iso:country":"BE",
    "sg:address":"Chauss\u00e9e De Li\u00e8ge",
    "sg:city":"Nandrin",
    "sg:classifiers":[
        {
            "category":"Fast Food",
            "type":"Food & Drink"
        }
    ],
    "sg:phone":"+32 4 371 33 51",
    "sg:postcode":"4550",
    "sg:province":"Li\u00e8ge",
    "sg:tags":[
        "fried",
        "stand",
        "potato"
    ],
    "wof:name":"Routiers (les)",
    "wof:placetype":"venue"
},
  "geometry": {"coordinates":[5.4204249382,50.5065155029],"type":"Point"}
}