{
  "type": "Feature",
  "properties": {
    "addr:full":"Jules Moretuslei 480 Antwerpen (wilrijk) Antwerpen 2610",
    "addr:housenumber":"480",
    "addr:postcode":"2610",
    "addr:street":"Jules Moretuslei;Antwerpen",
    "iso:country":"BE",
    "sg:address":"Jules Moretuslei 480",
    "sg:city":"Antwerpen (wilrijk)",
    "sg:classifiers":[
        {
            "category":"Landmark",
            "subcategory":"Memorial",
            "type":"Public Place"
        }
    ],
    "sg:phone":"+32 3 827 10 47",
    "sg:postcode":"2610",
    "sg:province":"Antwerpen",
    "sg:tags":[
        "-",
        "monument"
    ],
    "wof:name":"Opdebeeck Bvba",
    "wof:placetype":"venue"
},
  "geometry": {"coordinates":[4.3946051598,51.1691131592],"type":"Point"}
}