{
  "type": "Feature",
  "properties": {
    "addr:full":"Rue Trenchon 47 Tournai Hainaut 7502",
    "addr:housenumber":"47",
    "addr:postcode":"7502",
    "addr:street":"Rue Trenchon",
    "iso:country":"BE",
    "sg:address":"Rue Trenchon 47",
    "sg:city":"Tournai",
    "sg:orig_category":"Woningbouw",
    "sg:phone":"+32 69 64 86 03",
    "sg:postcode":"7502",
    "sg:province":"Hainaut",
    "wof:name":"D.v.",
    "wof:placetype":"venue"
},
  "geometry": {"coordinates":[3.3103508949,50.5760421753],"type":"Point"}
}