{
  "type": "Feature",
  "properties": {
    "iso:country":"BE",
    "sg:address":"Rue Grande 5",
    "sg:city":"Fosses-la-ville",
    "sg:orig_category":"Boissons",
    "sg:phone":"+32 71 71 39 97",
    "sg:postcode":"5070",
    "sg:province":"Namur",
    "wof:name":"Marie-ange Porphyre",
    "wof:placetype":"venue"
},
  "geometry": {"coordinates":[4.6232500076,50.3886146545],"type":"Point"}
}