{
  "type": "Feature",
  "properties": {
    "addr:full":"Rue De La Paix 26 Komen-waasten/comines-warneton Hainaut 7780",
    "addr:housenumber":"26;7780",
    "addr:street":"Rue De La Paix",
    "iso:country":"BE",
    "sg:address":"Rue De La Paix 26",
    "sg:city":"Komen-waasten/comines-warneton",
    "sg:orig_category":"Cr\u00e9meries",
    "sg:phone":"+32 56 55 59 88",
    "sg:postcode":"7780",
    "sg:province":"Hainaut",
    "wof:name":"Didier Vandesteene",
    "wof:placetype":"venue"
},
  "geometry": {"coordinates":[2.9994850159,50.7709083557],"type":"Point"}
}