{
  "type": "Feature",
  "properties": {
    "iso:country":"BE",
    "sg:address":"Avenue Rogier 191",
    "sg:city":"Schaarbeek/schaerbeek",
    "sg:orig_category":"Biens d'occasion",
    "sg:phone":"+32 2 215 05 48",
    "sg:postcode":"1030",
    "sg:province":"Bruxelles-Capitale",
    "wof:name":"Bronet",
    "wof:placetype":"venue"
},
  "geometry": {"coordinates":[4.3820900917,50.8583068848],"type":"Point"}
}