{
  "type": "Feature",
  "properties": {
    "addr:full":"Oostveld Kouter 154 Lovendegem Oost-Vlaanderen 9920",
    "addr:housenumber":"154",
    "addr:postcode":"9920",
    "addr:street":"Oostveld Kouter",
    "iso:country":"BE",
    "sg:address":"Oostveld Kouter 154",
    "sg:city":"Lovendegem",
    "sg:orig_category":"Artsen and specialisten",
    "sg:phone":"+32 9 372 89 00",
    "sg:postcode":"9920",
    "sg:province":"Oost-Vlaanderen",
    "wof:name":"Gerrit Van Brabandt",
    "wof:placetype":"venue"
},
  "geometry": {"coordinates":[3.6097290516,51.0944099426],"type":"Point"}
}