{
  "type": "Feature",
  "properties": {
    "addr:full":"Avenue Reine Astrid 77 Spa Li\u00e8ge 4900",
    "addr:housenumber":"77",
    "addr:postcode":"4900",
    "addr:street":"Avenue Reine Astrid",
    "iso:country":"BE",
    "sg:address":"Avenue Reine Astrid 77",
    "sg:city":"Spa",
    "sg:orig_category":"Rechtbanken",
    "sg:phone":"+32 87 77 19 92",
    "sg:postcode":"4900",
    "sg:province":"Li\u00e8ge",
    "wof:name":"Justice De Paix",
    "wof:placetype":"venue"
},
  "geometry": {"coordinates":[5.8576421738,50.4917449951],"type":"Point"}
}