{
  "type": "Feature",
  "properties": {
    "iso:country":"BE",
    "sg:address":"Rue De L'hommal 26",
    "sg:city":"Libramont-chevigny (bras)",
    "sg:classifiers":[
        {
            "category":"Building & Trades",
            "subcategory":"Construction",
            "type":"Services"
        }
    ],
    "sg:phone":"+32 61 61 40 63",
    "sg:postcode":"6800",
    "sg:province":"Luxembourg",
    "sg:tags":[
        "carpenter"
    ],
    "wof:name":"Borcy Menuiserie",
    "wof:placetype":"venue"
},
  "geometry": {"coordinates":[5.4226698875,49.950088501],"type":"Point"}
}