{
  "type": "Feature",
  "properties": {
    "iso:country":"BE",
    "sg:address":"Rue De La Ahani\u00c8re 9",
    "sg:city":"Jodoigne",
    "sg:orig_category":"Bouwmaterialen Gh Loodgieterij and centrale verwarming Gh Loodgieterij, verwarming and sanitaire ins",
    "sg:phone":"+32 10 81 02 29",
    "sg:postcode":"1370",
    "sg:province":"Brabant Wallon",
    "wof:name":"Georges Houyet",
    "wof:placetype":"venue"
},
  "geometry": {"coordinates":[4.8871798515,50.7576560974],"type":"Point"}
}