{
  "type": "Feature",
  "properties": {
    "iso:country":"BE",
    "sg:address":"Schoolstraat 3",
    "sg:city":"Neerpelt",
    "sg:orig_category":"S\u00e9curit\u00e9 sociale",
    "sg:phone":"+32 11 64 40 70",
    "sg:postcode":"3910",
    "sg:province":"Limburg",
    "wof:name":"Christelijke Mutualiteit",
    "wof:placetype":"venue"
},
  "geometry": {"coordinates":[5.4841561317,51.2259902954],"type":"Point"}
}