{
  "type": "Feature",
  "properties": {
    "addr:full":"Kruisstraat 155 Brakel Oost-Vlaanderen 9660",
    "addr:housenumber":"155",
    "addr:postcode":"9660",
    "addr:street":"Kruisstraat",
    "iso:country":"BE",
    "sg:address":"Kruisstraat 155",
    "sg:city":"Brakel",
    "sg:orig_category":"Rundveehouders",
    "sg:phone":"+32 55 42 31 95",
    "sg:postcode":"9660",
    "sg:province":"Oost-Vlaanderen",
    "wof:name":"Marc Beerens",
    "wof:placetype":"venue"
},
  "geometry": {"coordinates":[3.7794799805,50.8004188538],"type":"Point"}
}