{
  "type": "Feature",
  "properties": {
    "iso:country":"BE",
    "sg:address":"Rue Henri Van Hamme 125",
    "sg:city":"Bruxelles (evere)",
    "sg:classifiers":[
        {
            "category":"Building & Trades",
            "subcategory":"Construction",
            "type":"Services"
        }
    ],
    "sg:phone":"+32 2 242 99 07",
    "sg:postcode":"1140",
    "sg:province":"Bruxelles-Capitale",
    "sg:tags":[
        "insulation",
        "thermical",
        "work",
        "acoustical"
    ],
    "wof:name":"C.g. Gokas Sprl",
    "wof:placetype":"venue"
},
  "geometry": {"coordinates":[4.3977298737,50.8764762878],"type":"Point"}
}