{
  "type": "Feature",
  "properties": {
    "addr:full":"Rue De L'hippodrome 148 Liege Li\u00e8ge 4000",
    "addr:housenumber":"148",
    "addr:postcode":"4000",
    "addr:street":"Rue De L'Hippodrome",
    "iso:country":"BE",
    "sg:address":"Rue De L'hippodrome 148",
    "sg:city":"Liege",
    "sg:orig_category":"Location de machines-outils and de mat\u00e9riel de bricolage",
    "sg:phone":"+32 4 254 19 59",
    "sg:postcode":"4000",
    "sg:province":"Li\u00e8ge",
    "wof:name":"Mondial Machines",
    "wof:placetype":"venue"
},
  "geometry": {"coordinates":[5.5569009781,50.6106338501],"type":"Point"}
}