{
  "type": "Feature",
  "properties": {
    "iso:country":"BE",
    "sg:address":"Avenue Van Bever 8",
    "sg:city":"Ukkel/uccle",
    "sg:orig_category":"Production de films, t\u00e9l\u00e9films and vid\u00e9os",
    "sg:phone":"+32 2 375 01 75",
    "sg:postcode":"1180",
    "sg:province":"Bruxelles-Capitale",
    "wof:name":"Production Team",
    "wof:placetype":"venue"
},
  "geometry": {"coordinates":[4.380012989,50.7841377258],"type":"Point"}
}