{
  "type": "Feature",
  "properties": {
    "iso:country":"BE",
    "sg:address":"Lodewijk De Raetlaan 24a",
    "sg:city":"Izegem",
    "sg:classifiers":[
        {
            "category":"Farming",
            "subcategory":"Farm & Veterinary Services",
            "type":"Manufacturing & Wholesale Goods"
        }
    ],
    "sg:phone":"+32 51 32 03 33",
    "sg:postcode":"8870",
    "sg:province":"West-Vlaanderen",
    "sg:tags":[
        "material",
        "cattle-breeding"
    ],
    "wof:name":"Kawimpex Trading Company Nv",
    "wof:placetype":"venue"
},
  "geometry": {"coordinates":[3.2004890442,50.9295196533],"type":"Point"}
}