{
  "type": "Feature",
  "properties": {
    "addr:full":"Taverneux 42 Houffalize Luxembourg 6660",
    "addr:housenumber":"42",
    "addr:postcode":"6660",
    "addr:street":"Taverneux",
    "iso:country":"BE",
    "sg:address":"Taverneux 42",
    "sg:city":"Houffalize",
    "sg:classifiers":[
        {
            "category":"Building & Trades",
            "subcategory":"Landscaping Services",
            "type":"Services"
        }
    ],
    "sg:phone":"+32 61 28 93 50",
    "sg:postcode":"6660",
    "sg:province":"Luxembourg",
    "sg:tags":[
        "earth",
        "moving"
    ],
    "wof:name":"Entreprises Bernard Deumer S.a.",
    "wof:placetype":"venue"
},
  "geometry": {"coordinates":[5.802754879,50.138671875],"type":"Point"}
}