{
  "type": "Feature",
  "properties": {
    "addr:full":"Grote Baan 160 Lovendegem Oost-Vlaanderen 9920",
    "addr:housenumber":"160",
    "addr:postcode":"9920",
    "addr:street":"Grote Baan",
    "iso:country":"BE",
    "sg:address":"Grote Baan 160",
    "sg:city":"Lovendegem",
    "sg:orig_category":"Woningbouw",
    "sg:phone":"+32 9 372 68 34",
    "sg:postcode":"9920",
    "sg:province":"Oost-Vlaanderen",
    "wof:name":"Marc Van Hecke",
    "wof:placetype":"venue"
},
  "geometry": {"coordinates":[3.6270549297,51.1041717529],"type":"Point"}
}