{
  "type": "Feature",
  "properties": {
    "addr:full":"Dorpsstraat 216 Overpelt Limburg 3900",
    "addr:housenumber":"216",
    "addr:postcode":"3900",
    "addr:street":"Dorpsstraat",
    "iso:country":"BE",
    "sg:address":"Dorpsstraat 216",
    "sg:city":"Overpelt",
    "sg:orig_category":"S\u00e9lection de personnel and placement. Assurances. Bureaux de poste",
    "sg:phone":"+32 11 66 41 59",
    "sg:postcode":"3900",
    "sg:province":"Limburg",
    "wof:name":"De Post",
    "wof:placetype":"venue"
},
  "geometry": {"coordinates":[5.4183278084,51.2092857361],"type":"Point"}
}