{
  "type": "Feature",
  "properties": {
    "addr:full":"Rue D'arlon 21ba Florenville Luxembourg 6820",
    "addr:housenumber":"21ba",
    "addr:postcode":"6820",
    "addr:street":"Rue D'Arlon",
    "iso:country":"BE",
    "sg:address":"Rue D'arlon 21ba",
    "sg:city":"Florenville",
    "sg:orig_category":"Slagers",
    "sg:phone":"+32 61 31 57 59",
    "sg:postcode":"6820",
    "sg:province":"Luxembourg",
    "wof:name":"Protin",
    "wof:placetype":"venue"
},
  "geometry": {"coordinates":[5.3194952011,49.6963500977],"type":"Point"}
}