{
  "type": "Feature",
  "properties": {
    "iso:country":"BE",
    "sg:address":"Durmelaan 7",
    "sg:city":"Lokeren",
    "sg:orig_category":"Avocats and conseillers juridiques",
    "sg:phone":"+32 9 348 52 04",
    "sg:postcode":"9160",
    "sg:province":"Oost-Vlaanderen",
    "wof:name":"Luc Marechal",
    "wof:placetype":"venue"
},
  "geometry": {"coordinates":[3.982006073,51.1047172546],"type":"Point"}
}