{
  "type": "Feature",
  "properties": {
    "addr:full":"Rue Des Alli\u00e9s 31 Lens Hainaut 7870",
    "addr:housenumber":"31",
    "addr:postcode":"7870",
    "addr:street":"Rue Des Allie\u0301S",
    "iso:country":"BE",
    "sg:address":"Rue Des Alli\u00e9s 31",
    "sg:city":"Lens",
    "sg:classifiers":[
        {
            "category":"Home & Garden",
            "subcategory":"Garden Supply",
            "type":"Retail Goods"
        }
    ],
    "sg:phone":"+32 65 22 98 53",
    "sg:postcode":"7870",
    "sg:province":"Hainaut",
    "sg:tags":[
        "lawn",
        "mower"
    ],
    "wof:name":"Let\u00e9 A",
    "wof:placetype":"venue"
},
  "geometry": {"coordinates":[3.8756229877,50.5516777039],"type":"Point"}
}