{
  "type": "Feature",
  "properties": {
    "iso:country":"BE",
    "sg:address":"Rue Griange 3",
    "sg:city":"Huy",
    "sg:classifiers":[
        {
            "category":"Food & Beverages",
            "subcategory":"Specialty",
            "type":"Retail Goods"
        }
    ],
    "sg:phone":"+32 85 21 47 93",
    "sg:postcode":"4500",
    "sg:province":"Li\u00e8ge",
    "sg:tags":[
        "health",
        "dietary",
        "-",
        "biological"
    ],
    "wof:name":"Au Rythme Des Saisons",
    "wof:placetype":"venue"
},
  "geometry": {"coordinates":[5.2413601875,50.5178184509],"type":"Point"}
}