{
  "type": "Feature",
  "properties": {
    "iso:country":"BE",
    "sg:address":"Reigerlostraat 25",
    "sg:city":"Beernem",
    "sg:classifiers":[
        {
            "category":"Travel",
            "subcategory":"Hotels & Motels",
            "type":"Entertainment"
        }
    ],
    "sg:phone":"+32 50 79 10 00",
    "sg:postcode":"8730",
    "sg:province":"West-Vlaanderen",
    "wof:name":"Ten Lande",
    "wof:placetype":"venue"
},
  "geometry": {"coordinates":[3.3213739395,51.1172866821],"type":"Point"}
}