{
  "type": "Feature",
  "properties": {
    "iso:country":"BE",
    "sg:address":"Rue Brasserie 8",
    "sg:city":"Chimay",
    "sg:orig_category":"Dranken",
    "sg:phone":"+32 60 21 11 48",
    "sg:postcode":"6464",
    "sg:province":"Hainaut",
    "wof:name":"Cousot-fassiaux",
    "wof:placetype":"venue"
},
  "geometry": {"coordinates":[4.3385448456,50.0275764465],"type":"Point"}
}