{
  "type": "Feature",
  "properties": {
    "addr:full":"Autolei 218b220 Wommelgem Antwerpen 2160",
    "addr:housenumber":"218b220",
    "addr:postcode":"2160",
    "addr:street":"Autolei",
    "iso:country":"BE",
    "sg:address":"Autolei 218b220",
    "sg:city":"Wommelgem",
    "sg:orig_category":"Electrom\u00e9nager, t\u00e9l\u00e9visions and radios",
    "sg:phone":"+32 3 322 60 30",
    "sg:postcode":"2160",
    "sg:province":"Antwerpen",
    "wof:name":"Gam Hifi",
    "wof:placetype":"venue"
},
  "geometry": {"coordinates":[4.4903402328,51.2080612183],"type":"Point"}
}