{
  "type": "Feature",
  "properties": {
    "addr:full":"Gentsestraat 97 Aalst Oost-Vlaanderen 9300",
    "addr:housenumber":"97",
    "addr:postcode":"9300",
    "addr:street":"Gentsestraat",
    "iso:country":"BE",
    "sg:address":"Gentsestraat 97",
    "sg:city":"Aalst",
    "sg:classifiers":[
        {
            "category":"Health Services",
            "subcategory":"Health Practitioner",
            "type":"Services"
        }
    ],
    "sg:phone":"+32 53 77 44 37",
    "sg:postcode":"9300",
    "sg:province":"Oost-Vlaanderen",
    "sg:tags":[
        "physiotherapist"
    ],
    "wof:name":"Van Geert Anne",
    "wof:placetype":"venue"
},
  "geometry": {"coordinates":[4.0297021866,50.937713623],"type":"Point"}
}