{
  "type": "Feature",
  "properties": {
    "iso:country":"BE",
    "sg:address":"Dorpsstr 114",
    "sg:city":"St. Laureins",
    "sg:classifiers":[
        {
            "category":"Banks & Credit Unions",
            "subcategory":"Bank",
            "type":"Services"
        }
    ],
    "sg:phone":"+32 54 79 80 55",
    "sg:postcode":"9980",
    "sg:province":"Oost-Vlaanderen",
    "wof:name":"Banque Bruxelles Lambert",
    "wof:placetype":"venue"
},
  "geometry": {"coordinates":[3.5256710052,51.2417526245],"type":"Point"}
}