{
  "type": "Feature",
  "properties": {
    "iso:country":"BE",
    "sg:address":"De Keyserlei 58 Box 1",
    "sg:city":"Antwerpen",
    "sg:orig_category":"Non-Classified Establishments",
    "sg:phone":"+32 3 206 08 20",
    "sg:postcode":"2018",
    "sg:province":"Antwerpen",
    "wof:name":"A S E Chemicals Nv",
    "wof:placetype":"venue"
},
  "geometry": {"coordinates":[4.4192619324,51.2173309326],"type":"Point"}
}