{
  "type": "Feature",
  "properties": {
    "iso:country":"BE",
    "sg:address":"Hefveldstraat 90",
    "sg:city":"Hasselt",
    "sg:classifiers":[
        {
            "category":"Real Estate",
            "subcategory":"Architect",
            "type":"Services"
        }
    ],
    "sg:phone":"+32 11 28 45 94",
    "sg:postcode":"3500",
    "sg:province":"Limburg",
    "wof:name":"Tielens E",
    "wof:placetype":"venue"
},
  "geometry": {"coordinates":[5.3340768814,50.9204597473],"type":"Point"}
}