{
  "type": "Feature",
  "properties": {
    "iso:country":"BE",
    "sg:address":"Place De L'orneau 28 A",
    "sg:city":"Gembloux",
    "sg:orig_category":"Royal Canin. Services pour animaux domestiques",
    "sg:phone":"+32 81 61 11 82",
    "sg:postcode":"5030",
    "sg:province":"Namur",
    "wof:name":"Mr.vanderstichelen",
    "wof:placetype":"venue"
},
  "geometry": {"coordinates":[4.6922240257,50.5608406067],"type":"Point"}
}