{
  "type": "Feature",
  "properties": {
    "addr:full":"Spechtendreef 31 Zoersel (halle) Antwerpen 2980",
    "addr:housenumber":"31",
    "addr:postcode":"2980",
    "addr:street":"Spechtendreef",
    "iso:country":"BE",
    "sg:address":"Spechtendreef 31",
    "sg:city":"Zoersel (halle)",
    "sg:classifiers":[
        {
            "category":"Professional",
            "subcategory":"Management & Consulting",
            "type":"Services"
        }
    ],
    "sg:phone":"+32 3 383 06 25",
    "sg:postcode":"2980",
    "sg:province":"Antwerpen",
    "sg:tags":[
        "tax-consultants"
    ],
    "wof:name":"Van Uffel M-j",
    "wof:placetype":"venue"
},
  "geometry": {"coordinates":[4.713435173,51.269985199],"type":"Point"}
}