{
  "type": "Feature",
  "properties": {
    "addr:full":"Schaffensestraat 29 Diest Vlaams-Brabant 3290",
    "addr:housenumber":"29",
    "addr:postcode":"3290",
    "addr:street":"Schaffensestraat",
    "iso:country":"BE",
    "sg:address":"Schaffensestraat 29",
    "sg:city":"Diest",
    "sg:classifiers":[
        {
            "category":"Real Estate",
            "subcategory":"Architect",
            "type":"Services"
        }
    ],
    "sg:phone":"+32 13 33 42 54",
    "sg:postcode":"3290",
    "sg:province":"Vlaams-Brabant",
    "wof:name":"Mees L",
    "wof:placetype":"venue"
},
  "geometry": {"coordinates":[5.0562138557,50.9885177612],"type":"Point"}
}