{
  "type": "Feature",
  "properties": {
    "addr:full":"Luxemburgstraat 16 Moeskroen/mouscron Hainaut 7700",
    "addr:housenumber":"16",
    "addr:postcode":"7700",
    "addr:street":"Luxemburgstraat",
    "iso:country":"BE",
    "sg:address":"Luxemburgstraat 16",
    "sg:city":"Moeskroen/mouscron",
    "sg:orig_category":"Artsen and specialisten",
    "sg:phone":"+32 56 33 42 82",
    "sg:postcode":"7700",
    "sg:province":"Hainaut",
    "wof:name":"J. Van Hende",
    "wof:placetype":"venue"
},
  "geometry": {"coordinates":[3.2323200703,50.7400932312],"type":"Point"}
}