{
  "type": "Feature",
  "properties": {
    "addr:full":"Rue Du Manypr\u00c9 82 Chaumont-gistoux Brabant Wallon 1325",
    "addr:housenumber":"82",
    "addr:postcode":"1325",
    "addr:street":"Rue Du Manypre\u0301",
    "iso:country":"BE",
    "sg:address":"Rue Du Manypr\u00c9 82",
    "sg:city":"Chaumont-gistoux",
    "sg:orig_category":"Gespecialiseerde residenti\u00eble bouw Woningbouw",
    "sg:phone":"+32 10 68 82 51",
    "sg:postcode":"1325",
    "sg:province":"Brabant Wallon",
    "wof:name":"Entreprises Flemal",
    "wof:placetype":"venue"
},
  "geometry": {"coordinates":[4.6859512329,50.6755981445],"type":"Point"}
}