{
  "type": "Feature",
  "properties": {
    "addr:full":"Grote Markt 1 Vilvoorde Vlaams-Brabant 1800",
    "addr:housenumber":"1",
    "addr:postcode":"1800",
    "addr:street":"Grote Markt",
    "iso:country":"BE",
    "sg:address":"Grote Markt 1",
    "sg:city":"Vilvoorde",
    "sg:orig_category":"Opvangtehuizen and vluchthuizen",
    "sg:phone":"+32 2 546 14 40",
    "sg:postcode":"1800",
    "sg:province":"Vlaams-Brabant",
    "wof:name":"Dienst Maatschapp. Werk",
    "wof:placetype":"venue"
},
  "geometry": {"coordinates":[4.4220128059,50.9293060303],"type":"Point"}
}