{
  "type": "Feature",
  "properties": {
    "addr:full":"Aartrijksestraat 127 Zedelgem West-Vlaanderen 8211",
    "addr:housenumber":"127",
    "addr:postcode":"8211",
    "addr:street":"Aartrijksestraat",
    "iso:country":"BE",
    "sg:address":"Aartrijksestraat 127",
    "sg:city":"Zedelgem",
    "sg:orig_category":"Eleveurs de bovins. Eleveurs and marchands de porcs",
    "sg:phone":"+32 50 21 29 42",
    "sg:postcode":"8211",
    "sg:province":"West-Vlaanderen",
    "wof:name":"Marcel Vanneste",
    "wof:placetype":"venue"
},
  "geometry": {"coordinates":[3.0889649391,51.1200408936],"type":"Point"}
}