{
  "type": "Feature",
  "properties": {
    "addr:full":"Zwaluwenlaan 3 Beersel Vlaams-Brabant 1650",
    "addr:housenumber":"3",
    "addr:postcode":"1650",
    "addr:street":"Zwaluwenlaan",
    "iso:country":"BE",
    "sg:address":"Zwaluwenlaan 3",
    "sg:city":"Beersel",
    "sg:classifiers":[
        {
            "category":"Health Services",
            "subcategory":"Doctor",
            "type":"Services"
        }
    ],
    "sg:phone":"+32 2 380 10 23",
    "sg:postcode":"1650",
    "sg:province":"Vlaams-Brabant",
    "sg:tags":[
        "psychotherapist",
        "psychoanalyst"
    ],
    "wof:name":"Luttringer I",
    "wof:placetype":"venue"
},
  "geometry": {"coordinates":[4.3330659866,50.7646064758],"type":"Point"}
}