{
  "type": "Feature",
  "properties": {
    "iso:country":"BE",
    "sg:address":"Vissersstraat 23",
    "sg:city":"De Haan",
    "sg:orig_category":"Varkenskwekers",
    "sg:phone":"+32 59 23 37 44",
    "sg:postcode":"8420",
    "sg:province":"West-Vlaanderen",
    "wof:name":"Andre Borny",
    "wof:placetype":"venue"
},
  "geometry": {"coordinates":[3.0022308826,51.2593765259],"type":"Point"}
}