{
  "type": "Feature",
  "properties": {
    "iso:country":"BE",
    "sg:address":"Baron R. De Vironlaan 83",
    "sg:city":"Dilbeek",
    "sg:orig_category":"Artsen and specialisten",
    "sg:phone":"+32 2 569 31 08",
    "sg:postcode":"1700",
    "sg:province":"Vlaams-Brabant",
    "wof:name":"H. Tiebout",
    "wof:placetype":"venue"
},
  "geometry": {"coordinates":[4.2708640099,50.8462867737],"type":"Point"}
}