{
  "type": "Feature",
  "properties": {
    "iso:country":"BE",
    "sg:address":"Petites-rues 1",
    "sg:city":"Florenville",
    "sg:orig_category":"S\u00e9curit\u00e9 sociale",
    "sg:phone":"+32 61 32 01 91",
    "sg:postcode":"6820",
    "sg:province":"Luxembourg",
    "wof:name":"Mutualit\u00c9 Neutre",
    "wof:placetype":"venue"
},
  "geometry": {"coordinates":[5.3100390434,49.6983375549],"type":"Point"}
}