{
  "type": "Feature",
  "properties": {
    "addr:full":"Rue Du Fronia 5 Froidchapelle Hainaut 6440",
    "addr:housenumber":"5",
    "addr:postcode":"6440",
    "addr:street":"Rue Du Fronia",
    "iso:country":"BE",
    "sg:address":"Rue Du Fronia 5",
    "sg:city":"Froidchapelle",
    "sg:orig_category":"Dierenartsen",
    "sg:phone":"+32 60 41 17 38",
    "sg:postcode":"6440",
    "sg:province":"Hainaut",
    "wof:name":"Michel Stiennon",
    "wof:placetype":"venue"
},
  "geometry": {"coordinates":[4.3750071526,50.2253875732],"type":"Point"}
}