{
  "type": "Feature",
  "properties": {
    "addr:full":"Deerlijkseweg 116 Waregem West-Vlaanderen 8790",
    "addr:housenumber":"116",
    "addr:postcode":"8790",
    "iso:country":"BE",
    "sg:address":"Deerlijkseweg 116",
    "sg:city":"Waregem",
    "sg:orig_category":"Articles textiles and tissus de d\u00e9coration Fab",
    "sg:phone":"+32 56 60 69 47",
    "sg:postcode":"8790",
    "sg:province":"West-Vlaanderen",
    "wof:name":"De Bo",
    "wof:placetype":"venue"
},
  "geometry": {"coordinates":[3.4023430347,50.8688812256],"type":"Point"}
}