{
  "type": "Feature",
  "properties": {
    "addr:full":"Diesterstraat 62 Sint-truiden Limburg 3800",
    "addr:housenumber":"62",
    "addr:postcode":"3800",
    "addr:street":"Diesterstraat",
    "iso:country":"BE",
    "sg:address":"Diesterstraat 62",
    "sg:city":"Sint-truiden",
    "sg:orig_category":"Newspapers, magazines, periodicals - Distribution",
    "sg:phone":"+32 11 68 29 02",
    "sg:postcode":"3800",
    "sg:province":"Limburg",
    "wof:name":"Boekhandel Somi",
    "wof:placetype":"venue"
},
  "geometry": {"coordinates":[5.1836137772,50.818069458],"type":"Point"}
}