{
  "type": "Feature",
  "properties": {
    "addr:full":"Kiezelweg 17 Mol Antwerpen 2400",
    "addr:housenumber":"17",
    "addr:postcode":"2400",
    "addr:street":"Kiezelweg",
    "iso:country":"BE",
    "sg:address":"Kiezelweg 17",
    "sg:city":"Mol",
    "sg:orig_category":"Villages de vacances. Installations and terrains de sport hors centres sportifs. Maisons de vacances",
    "sg:phone":"+32 14 81 00 98",
    "sg:postcode":"2400",
    "sg:province":"Antwerpen",
    "wof:name":"Recreatiecentrum Zilverstrand",
    "wof:placetype":"venue"
},
  "geometry": {"coordinates":[5.1717228889,51.2095298767],"type":"Point"}
}