{
  "type": "Feature",
  "properties": {
    "addr:full":"Rue De La Paix 41 Bruxelles (ixelles) Bruxelles-Capitale 1050",
    "addr:housenumber":"41",
    "addr:postcode":"1050",
    "addr:street":"Rue De La Paix",
    "iso:country":"BE",
    "sg:address":"Rue De La Paix 41",
    "sg:city":"Bruxelles (ixelles)",
    "sg:classifiers":[
        {
            "category":"Shopping",
            "subcategory":"Clothing, Apparel, & Fashions",
            "type":"Retail Goods"
        }
    ],
    "sg:phone":"+32 2 512 64 86",
    "sg:postcode":"1050",
    "sg:province":"Bruxelles-Capitale",
    "sg:tags":[
        "boutique"
    ],
    "wof:name":"Cocoon",
    "wof:placetype":"venue"
},
  "geometry": {"coordinates":[4.3658080101,50.8361282349],"type":"Point"}
}