{
  "type": "Feature",
  "properties": {
    "iso:country":"BE",
    "sg:address":"Rue De Jupille 153",
    "sg:city":"Fl\u00c9ron",
    "sg:orig_category":"Medische apparatuur, orthopedische artikelen and prothesen Fab",
    "sg:phone":"+32 4 358 74 10",
    "sg:postcode":"4620",
    "sg:province":"Li\u00e8ge",
    "wof:name":"Roger Weickmans",
    "wof:placetype":"venue"
},
  "geometry": {"coordinates":[5.6765499115,50.62865448],"type":"Point"}
}