{
  "type": "Feature",
  "properties": {
    "addr:full":"Avenue Emile De Beco 102 Box 10 Bruxelles (ixelles) Bruxelles-Capitale 1050",
    "addr:housenumber":"102 box 10",
    "addr:postcode":"1050",
    "addr:street":"Avenue Emile De Beco",
    "iso:country":"BE",
    "sg:address":"Avenue Emile De Beco 102 Box 10",
    "sg:city":"Bruxelles (ixelles)",
    "sg:classifiers":[
        {
            "category":"Building & Trades",
            "subcategory":"Plumbing",
            "type":"Services"
        }
    ],
    "sg:phone":"+32 2 772 30 30",
    "sg:postcode":"1050",
    "sg:province":"Bruxelles-Capitale",
    "sg:tags":[
        "repair",
        "mainten",
        "-",
        "central",
        "heating"
    ],
    "wof:name":"Lichtert A",
    "wof:placetype":"venue"
},
  "geometry": {"coordinates":[4.3840961456,50.8212623596],"type":"Point"}
}