{
  "type": "Feature",
  "properties": {
    "addr:full":"Nobelstraat 134 Tremelo Vlaams-Brabant 3128",
    "addr:housenumber":"134",
    "addr:postcode":"3128",
    "addr:street":"Nobelstraat",
    "iso:country":"BE",
    "sg:address":"Nobelstraat 134",
    "sg:city":"Tremelo",
    "sg:orig_category":"Enseignement maternel and primaire",
    "sg:phone":"+32 16 53 39 73",
    "sg:postcode":"3128",
    "sg:province":"Vlaams-Brabant",
    "wof:name":"Vrije Lagere School",
    "wof:placetype":"venue"
},
  "geometry": {"coordinates":[4.7453508377,51.0133247375],"type":"Point"}
}