{
  "type": "Feature",
  "properties": {
    "iso:country":"BE",
    "sg:address":"Rue De Wandstraat 148",
    "sg:city":"Brussel",
    "sg:orig_category":"Boekhandels",
    "sg:phone":"+32 2 268 01 57",
    "sg:postcode":"1020",
    "sg:province":"Bruxelles-Capitale",
    "wof:name":"D\u00c9 Lecteur",
    "wof:placetype":"venue"
},
  "geometry": {"coordinates":[4.3604211807,50.9006233215],"type":"Point"}
}