{
  "type": "Feature",
  "properties": {
    "iso:country":"BE",
    "sg:address":"Rue Du Lavoir 19",
    "sg:city":"Chimay (bourlers)",
    "sg:classifiers":[
        {
            "category":"Home & Garden",
            "subcategory":"Carpets & Floor Coverings",
            "type":"Retail Goods"
        }
    ],
    "sg:phone":"+32 60 21 47 96",
    "sg:postcode":"6464",
    "sg:province":"Hainaut",
    "sg:tags":[
        "tile"
    ],
    "wof:name":"Mat\u00e9riaux Du Pavillon",
    "wof:placetype":"venue"
},
  "geometry": {"coordinates":[4.3395338058,50.0263214111],"type":"Point"}
}