{
  "type": "Feature",
  "properties": {
    "addr:full":"Rue Puissant 201 Charleroi Hainaut 6040",
    "addr:housenumber":"201",
    "addr:postcode":"6040",
    "addr:street":"Rue Puissant;Hainaut",
    "iso:country":"BE",
    "sg:address":"Rue Puissant 201",
    "sg:city":"Charleroi",
    "sg:orig_category":"Bloemen and planten Gh",
    "sg:phone":"+32 71 32 56 64",
    "sg:postcode":"6040",
    "sg:province":"Hainaut",
    "wof:name":"Lepinne M",
    "wof:placetype":"venue"
},
  "geometry": {"coordinates":[4.4258980751,50.4318008423],"type":"Point"}
}