{
  "type": "Feature",
  "properties": {
    "iso:country":"BE",
    "sg:address":"Rue Du Zoning 17",
    "sg:city":"Ans",
    "sg:classifiers":[
        {
            "category":"Health Services",
            "subcategory":"Doctor",
            "type":"Services"
        }
    ],
    "sg:phone":"+32 4 247 47 12",
    "sg:postcode":"4430",
    "sg:province":"Li\u00e8ge",
    "sg:tags":[
        "medicinephysicians",
        "surgeon"
    ],
    "wof:name":"Hanz\u00e9 Marc",
    "wof:placetype":"venue"
},
  "geometry": {"coordinates":[5.535779953,50.6641197205],"type":"Point"}
}