{
  "type": "Feature",
  "properties": {
    "addr:full":"Wespelarebaan 43 -45 Boortmeerbeek Vlaams-Brabant 3190",
    "addr:housenumber":"43 -45",
    "addr:postcode":"3190",
    "addr:street":"Wespelarebaan",
    "iso:country":"BE",
    "sg:address":"Wespelarebaan 43 -45",
    "sg:city":"Boortmeerbeek",
    "sg:orig_category":"Bloemen and planten",
    "sg:phone":"+32 15 51 38 27",
    "sg:postcode":"3190",
    "sg:province":"Vlaams-Brabant",
    "wof:name":"Van Parijs - Crauwels",
    "wof:placetype":"venue"
},
  "geometry": {"coordinates":[4.577644825,50.9788818359],"type":"Point"}
}