{
  "type": "Feature",
  "properties": {
    "iso:country":"BE",
    "sg:address":"Kokstraat 16",
    "sg:city":"Aalst",
    "sg:classifiers":[
        {
            "category":"Food & Beverages",
            "subcategory":"Fruits & Vegetables",
            "type":"Retail Goods"
        }
    ],
    "sg:phone":"+32 53 77 55 19",
    "sg:postcode":"9310",
    "sg:province":"Oost-Vlaanderen",
    "sg:tags":[
        "groenten"
    ],
    "wof:name":"Katelijn",
    "wof:placetype":"venue"
},
  "geometry": {"coordinates":[4.1090340614,50.9609718323],"type":"Point"}
}