{
  "type": "Feature",
  "properties": {
    "addr:full":"Pontstraat 65 Aalst Oost-Vlaanderen 9300",
    "addr:housenumber":"65",
    "addr:postcode":"9300",
    "addr:street":"Pontstraat",
    "iso:country":"BE",
    "sg:address":"Pontstraat 65",
    "sg:city":"Aalst",
    "sg:orig_category":"Antiek",
    "sg:phone":"+32 53 70 02 31",
    "sg:postcode":"9300",
    "sg:province":"Oost-Vlaanderen",
    "wof:name":"De Eenhoorn",
    "wof:placetype":"venue"
},
  "geometry": {"coordinates":[4.0434541702,50.9353218079],"type":"Point"}
}