{
  "type": "Feature",
  "properties": {
    "iso:country":"BE",
    "sg:address":"Scheihagenstraat 45",
    "sg:city":"Kontich",
    "sg:classifiers":[
        {
            "category":"Building & Trades",
            "subcategory":"Landscaping Services",
            "type":"Services"
        }
    ],
    "sg:phone":"+32 3 458 56 12",
    "sg:postcode":"2550",
    "sg:province":"Antwerpen",
    "sg:tags":[
        "architect",
        "landscape"
    ],
    "wof:name":"Meysmans G",
    "wof:placetype":"venue"
},
  "geometry": {"coordinates":[4.4682269096,51.1246337891],"type":"Point"}
}