{
  "type": "Feature",
  "properties": {
    "iso:country":"BE",
    "sg:address":"Beneluxlaan 12",
    "sg:city":"Harelbeke",
    "sg:classifiers":[
        {
            "category":"Personal",
            "subcategory":"Beauty Salon",
            "type":"Services"
        }
    ],
    "sg:phone":"+32 56 22 84 76",
    "sg:postcode":"8530",
    "sg:province":"West-Vlaanderen",
    "sg:tags":[
        "de",
        "coiffure"
    ],
    "wof:name":"Coiffure Ann",
    "wof:placetype":"venue"
},
  "geometry": {"coordinates":[3.3150720596,50.8350143433],"type":"Point"}
}