{
  "type": "Feature",
  "properties": {
    "iso:country":"BE",
    "sg:address":"Boulevard Des Invalides 263",
    "sg:city":"Oudergem/auderghem",
    "sg:orig_category":"Architectes",
    "sg:phone":"+32 2 660 97 41",
    "sg:postcode":"1160",
    "sg:province":"Bruxelles-Capitale",
    "wof:name":"Dominique Nihoul",
    "wof:placetype":"venue"
},
  "geometry": {"coordinates":[4.4054808617,50.8184928894],"type":"Point"}
}