{
  "type": "Feature",
  "properties": {
    "addr:full":"Gistelsteenweg 327 Jabbeke West-Vlaanderen 8490",
    "addr:housenumber":"327",
    "addr:postcode":"8490",
    "addr:street":"Gistelsteenweg",
    "iso:country":"BE",
    "sg:address":"Gistelsteenweg 327",
    "sg:city":"Jabbeke",
    "sg:orig_category":"Dierenartsen",
    "sg:phone":"+32 50 81 34 29",
    "sg:postcode":"8490",
    "sg:province":"West-Vlaanderen",
    "wof:name":"Marc Moyaert",
    "wof:placetype":"venue"
},
  "geometry": {"coordinates":[3.1030650139,51.1789741516],"type":"Point"}
}