{
  "type": "Feature",
  "properties": {
    "iso:country":"BE",
    "sg:address":"Rue Du Bois L'ev\u00eaque 4",
    "sg:city":"Andenne",
    "sg:classifiers":[
        {
            "category":"Professional",
            "type":"Services"
        }
    ],
    "sg:phone":"+32 81 58 53 53",
    "sg:postcode":"5300",
    "sg:province":"Namur",
    "sg:tags":[
        "transport",
        "road"
    ],
    "wof:name":"Sandri Mario Sprl",
    "wof:placetype":"venue"
},
  "geometry": {"coordinates":[4.9988970757,50.4720611572],"type":"Point"}
}