{
  "type": "Feature",
  "properties": {
    "addr:full":"Markt 16 Nevele Oost-Vlaanderen 9850",
    "addr:housenumber":"16",
    "addr:postcode":"9850",
    "addr:street":"Markt",
    "iso:country":"BE",
    "sg:address":"Markt 16",
    "sg:city":"Nevele",
    "sg:orig_category":"Schoenen",
    "sg:phone":"+32 9 371 51 10",
    "sg:postcode":"9850",
    "sg:province":"Oost-Vlaanderen",
    "wof:name":"Schoenen Cleve",
    "wof:placetype":"venue"
},
  "geometry": {"coordinates":[3.5494019985,51.0329589844],"type":"Point"}
}