{
  "type": "Feature",
  "properties": {
    "addr:full":"Boulevard Jean-th\u00e9odore Radoux 15 Li\u00e8ge 1 Li\u00e8ge 4000",
    "addr:housenumber":"15;1",
    "addr:postcode":"4000",
    "addr:street":"Boulevard Jean-The\u0301Odore Radoux",
    "iso:country":"BE",
    "sg:address":"Boulevard Jean-th\u00e9odore Radoux 15",
    "sg:city":"Li\u00e8ge 1",
    "sg:classifiers":[
        {
            "category":"Health Services",
            "subcategory":"Health Practitioner",
            "type":"Services"
        }
    ],
    "sg:phone":"+32 4 226 61 27",
    "sg:postcode":"4000",
    "sg:province":"Li\u00e8ge",
    "sg:tags":[
        "physiotherapist"
    ],
    "wof:name":"Mottet P",
    "wof:placetype":"venue"
},
  "geometry": {"coordinates":[5.5530438423,50.6517868042],"type":"Point"}
}