{
  "type": "Feature",
  "properties": {
    "iso:country":"BE",
    "sg:address":"Nieuwendorpe 16",
    "sg:city":"Eeklo",
    "sg:orig_category":"Rundveehouders",
    "sg:phone":"+32 9 378 07 59",
    "sg:postcode":"9900",
    "sg:province":"Oost-Vlaanderen",
    "wof:name":"Laurent Haers",
    "wof:placetype":"venue"
},
  "geometry": {"coordinates":[3.5411369801,51.178768158],"type":"Point"}
}