{
  "type": "Feature",
  "properties": {
    "addr:full":"Chemin De Naast 37 Braine-le-comte Hainaut 7090",
    "addr:housenumber":"37",
    "addr:postcode":"7090",
    "addr:street":"Chemin De Naast",
    "iso:country":"BE",
    "sg:address":"Chemin De Naast 37",
    "sg:city":"Braine-le-comte",
    "sg:orig_category":"Eleveurs de bovins",
    "sg:phone":"+32 67 33 02 33",
    "sg:postcode":"7090",
    "sg:province":"Hainaut",
    "wof:name":"Michel Lebrun",
    "wof:placetype":"venue"
},
  "geometry": {"coordinates":[4.1247348785,50.5805015564],"type":"Point"}
}