{
  "type": "Feature",
  "properties": {
    "iso:country":"BE",
    "sg:address":"Avenue Brugmann 255",
    "sg:city":"Bruxelles (uccle)",
    "sg:classifiers":[
        {
            "category":"Home & Garden",
            "subcategory":"Home Furnishings",
            "type":"Retail Goods"
        }
    ],
    "sg:phone":"+32 2 343 17 82",
    "sg:postcode":"1180",
    "sg:province":"Bruxelles-Capitale",
    "sg:tags":[
        "interior",
        "decoration"
    ],
    "wof:name":"De Lamine De Bex S",
    "wof:placetype":"venue"
},
  "geometry": {"coordinates":[4.3474202156,50.8131599426],"type":"Point"}
}