{
  "type": "Feature",
  "properties": {
    "iso:country":"BE",
    "sg:address":"Staatsbaan 14",
    "sg:city":"Halen",
    "sg:classifiers":[
        {
            "category":"Shopping",
            "subcategory":"Clothing, Apparel, & Fashions",
            "type":"Retail Goods"
        }
    ],
    "sg:phone":"+32 13 44 34 09",
    "sg:postcode":"3545",
    "sg:province":"Limburg",
    "sg:tags":[
        "boutique"
    ],
    "wof:name":"Jomi",
    "wof:placetype":"venue"
},
  "geometry": {"coordinates":[5.1146478653,50.9495544434],"type":"Point"}
}