{
  "type": "Feature",
  "properties": {
    "iso:country":"BE",
    "sg:address":"Schansstraat 1",
    "sg:city":"Kortenaken",
    "sg:orig_category":"Banken and kredietinstellingen Verzekeringsmakelaars and experts",
    "sg:phone":"+32 11 58 17 14",
    "sg:postcode":"3470",
    "sg:province":"Vlaams-Brabant",
    "wof:name":"Arckens B.",
    "wof:placetype":"venue"
},
  "geometry": {"coordinates":[5.0629072189,50.9083900452],"type":"Point"}
}