{
  "type": "Feature",
  "properties": {
    "addr:full":"Rue D'ecosse 18 Sint-gillis/saint-gilles Bruxelles-Capitale 1060",
    "addr:housenumber":"18",
    "addr:postcode":"1060",
    "addr:street":"Rue D'Ecosse",
    "iso:country":"BE",
    "sg:address":"Rue D'ecosse 18",
    "sg:city":"Sint-gillis/saint-gilles",
    "sg:orig_category":"M\u00e9decins and sp\u00e9cialistes",
    "sg:phone":"+32 2 539 15 29",
    "sg:postcode":"1060",
    "sg:province":"Bruxelles-Capitale",
    "wof:name":"Michel Camus",
    "wof:placetype":"venue"
},
  "geometry": {"coordinates":[4.3525810242,50.8329200745],"type":"Point"}
}