{
  "type": "Feature",
  "properties": {
    "addr:full":"Rue Armand-dewolf 25b1 Helecine Brabant Wallon 1357",
    "addr:housenumber":"25b1",
    "addr:postcode":"1357",
    "addr:street":"Rue Armand-Dewolf",
    "iso:country":"BE",
    "sg:address":"Rue Armand-dewolf 25b1",
    "sg:city":"Helecine",
    "sg:orig_category":"Supermarch\u00e9s",
    "sg:phone":"+32 19 65 62 23",
    "sg:postcode":"1357",
    "sg:province":"Brabant Wallon",
    "wof:name":"Spar",
    "wof:placetype":"venue"
},
  "geometry": {"coordinates":[4.9743118286,50.7473831177],"type":"Point"}
}