{
  "type": "Feature",
  "properties": {
    "addr:full":"Leuvensesteenweg 200 Boutersem Vlaams-Brabant 3370",
    "addr:housenumber":"200",
    "addr:postcode":"3370",
    "addr:street":"Leuvensesteenweg",
    "iso:country":"BE",
    "sg:address":"Leuvensesteenweg 200",
    "sg:city":"Boutersem",
    "sg:orig_category":"Chip Etching Machines",
    "sg:phone":"+32 16 72 04 92",
    "sg:postcode":"3370",
    "sg:province":"Vlaams-Brabant",
    "wof:name":"Matrix Nv",
    "wof:placetype":"venue"
},
  "geometry": {"coordinates":[4.8485898972,50.8361816406],"type":"Point"}
}