{
  "type": "Feature",
  "properties": {
    "iso:country":"BE",
    "sg:address":"Rue D'ortey 39",
    "sg:city":"Namur",
    "sg:orig_category":"Schoonmaakbedrijven and ongediertebestrijding Wasserijen, Reiniging and Droogkuis",
    "sg:phone":"+32 81 73 69 06",
    "sg:postcode":"5020",
    "sg:province":"Namur",
    "wof:name":"Marc Ernotte",
    "wof:placetype":"venue"
},
  "geometry": {"coordinates":[4.8753781319,50.5016975403],"type":"Point"}
}