{
  "type": "Feature",
  "properties": {
    "iso:country":"BE",
    "sg:address":"Rue Dorez 22",
    "sg:city":"Tournai",
    "sg:classifiers":[
        {
            "category":"Personal",
            "subcategory":"Beauty Salon",
            "type":"Services"
        }
    ],
    "sg:phone":"+32 69 22 12 49",
    "sg:postcode":"7500",
    "sg:province":"Hainaut",
    "sg:tags":[
        "lady",
        "-",
        "hairdressing"
    ],
    "wof:name":"Gerard & Rene",
    "wof:placetype":"venue"
},
  "geometry": {"coordinates":[3.3826808929,50.606502533],"type":"Point"}
}