{
  "type": "Feature",
  "properties": {
    "addr:full":"Louis Delebecquelaan 34 Gent Oost-Vlaanderen 9051",
    "addr:housenumber":"34",
    "addr:postcode":"9051",
    "addr:street":"Delebecquelaan;Oost-Vlaanderen",
    "iso:country":"BE",
    "sg:address":"Louis Delebecquelaan 34",
    "sg:city":"Gent",
    "sg:orig_category":"Woningbouw",
    "sg:phone":"+32 9 220 00 42",
    "sg:postcode":"9051",
    "sg:province":"Oost-Vlaanderen",
    "wof:name":"Gorit",
    "wof:placetype":"venue"
},
  "geometry": {"coordinates":[3.6755239964,51.0240402222],"type":"Point"}
}