{
  "type": "Feature",
  "properties": {
    "iso:country":"BE",
    "sg:address":"R De L'esplanade 52",
    "sg:city":"Sprimont",
    "sg:classifiers":[
        {
            "category":"Travel",
            "subcategory":"Hotels & Motels",
            "type":"Entertainment"
        }
    ],
    "sg:phone":"+32 4 360 82 17",
    "sg:postcode":"4141",
    "sg:province":"Li\u00e8ge",
    "sg:tags":[
        "hotels",
        "business",
        "restaurant"
    ],
    "wof:name":"Demblon Renee",
    "wof:placetype":"venue"
},
  "geometry": {"coordinates":[5.739525795,50.5378112793],"type":"Point"}
}