{
  "type": "Feature",
  "properties": {
    "addr:full":"Liersesteenweg 237 Lint Antwerpen 2547",
    "addr:housenumber":"237",
    "addr:postcode":"2547",
    "addr:street":"Liersesteenweg",
    "iso:country":"BE",
    "sg:address":"Liersesteenweg 237",
    "sg:city":"Lint",
    "sg:orig_category":"Fotografen and fotostudio's",
    "sg:phone":"+32 3 491 94 96",
    "sg:postcode":"2547",
    "sg:province":"Antwerpen",
    "wof:name":"Colour Circus",
    "wof:placetype":"venue"
},
  "geometry": {"coordinates":[4.5111961365,51.1257324219],"type":"Point"}
}