{
  "type": "Feature",
  "properties": {
    "iso:country":"BE",
    "sg:address":"Rue Fr\u00e9d\u00e9ric Pelletier 56",
    "sg:city":"Bruxelles (schaerbeek)",
    "sg:classifiers":[
        {
            "category":"Banks & Credit Unions",
            "subcategory":"Bureau De Change",
            "type":"Services"
        }
    ],
    "sg:phone":"+32 2 736 89 60",
    "sg:postcode":"1030",
    "sg:province":"Bruxelles-Capitale",
    "sg:tags":[
        "measuring",
        "control",
        "apparatus"
    ],
    "wof:name":"Emtec",
    "wof:placetype":"venue"
},
  "geometry": {"coordinates":[4.4009289742,50.8458404541],"type":"Point"}
}