{
  "type": "Feature",
  "properties": {
    "addr:full":"Place De L'h\u00d4tel De Ville 16 Herve Li\u00e8ge 4650",
    "addr:housenumber":"16",
    "addr:postcode":"4650",
    "addr:street":"Place De L'Ho \u0302Tel De Ville",
    "iso:country":"BE",
    "sg:address":"Place De L'h\u00d4tel De Ville 16",
    "sg:city":"Herve",
    "sg:orig_category":"Brood, gebak and snoepgoed",
    "sg:phone":"+32 87 66 18 55",
    "sg:postcode":"4650",
    "sg:province":"Li\u00e8ge",
    "wof:name":"Boulangerie Hick",
    "wof:placetype":"venue"
},
  "geometry": {"coordinates":[-0.9248610139,48.1741142273],"type":"Point"}
}