{
  "type": "Feature",
  "properties": {
    "addr:full":"Rue Des Foulons 6 Brussel/bruxelles Bruxelles-Capitale 1000",
    "addr:housenumber":"6",
    "addr:postcode":"1000",
    "addr:street":"Rue Des Foulons;/",
    "iso:country":"BE",
    "sg:address":"Rue Des Foulons 6",
    "sg:city":"Brussel/bruxelles",
    "sg:classifiers":[
        {
            "category":"Cafe",
            "type":"Food & Drink"
        }
    ],
    "sg:phone":"+32 2 502 57 02",
    "sg:postcode":"1000",
    "sg:province":"Bruxelles-Capitale",
    "sg:tags":[
        "caf\u00e9s"
    ],
    "wof:name":"Tihad",
    "wof:placetype":"venue"
},
  "geometry": {"coordinates":[4.3428478241,50.8422317505],"type":"Point"}
}