{
  "type": "Feature",
  "properties": {
    "iso:country":"BE",
    "sg:address":"Geraardsbergsesteenweg 45ba",
    "sg:city":"Aalst",
    "sg:orig_category":"Herstellingen and onderhoud van auto's",
    "sg:phone":"+32 53 83 43 22",
    "sg:postcode":"9320",
    "sg:province":"Oost-Vlaanderen",
    "wof:name":"Carrosserie Teck",
    "wof:placetype":"venue"
},
  "geometry": {"coordinates":[4.0364499092,50.9333992004],"type":"Point"}
}