{
  "type": "Feature",
  "properties": {
    "iso:country":"BE",
    "sg:address":"Dreef 79",
    "sg:city":"Hoogstraten (meerle)",
    "sg:classifiers":[
        {
            "category":"Bakery",
            "type":"Food & Drink"
        }
    ],
    "sg:phone":"+32 3 315 70 54",
    "sg:postcode":"2328",
    "sg:province":"Antwerpen",
    "sg:tags":[
        "confectioner",
        "baker"
    ],
    "wof:name":"Van Den Broek N",
    "wof:placetype":"venue"
},
  "geometry": {"coordinates":[4.8041949272,51.4741134644],"type":"Point"}
}