{
  "type": "Feature",
  "properties": {
    "addr:full":"Rue Des D\u00e9port\u00e9s 26a Rixensart (genval) Brabant Wallon 1332",
    "addr:housenumber":"26a",
    "addr:postcode":"1332",
    "addr:street":"Rue Des De\u0301Porte\u0301S",
    "iso:country":"BE",
    "sg:address":"Rue Des D\u00e9port\u00e9s 26a",
    "sg:city":"Rixensart (genval)",
    "sg:classifiers":[
        {
            "category":"Building & Trades",
            "subcategory":"Construction",
            "type":"Services"
        }
    ],
    "sg:phone":"+32 2 652 25 02",
    "sg:postcode":"1332",
    "sg:province":"Brabant Wallon",
    "sg:tags":[
        "carpenter"
    ],
    "wof:name":"Vanbaelen Ph",
    "wof:placetype":"venue"
},
  "geometry": {"coordinates":[4.4954338074,50.716884613],"type":"Point"}
}