{
  "type": "Feature",
  "properties": {
    "iso:country":"BE",
    "sg:address":"Boonhof 26",
    "sg:city":"Lille (wechelderzande)",
    "sg:classifiers":[
        {
            "category":"Personal",
            "subcategory":"Massage",
            "type":"Services"
        }
    ],
    "sg:phone":"+32 3 309 16 52",
    "sg:postcode":"2275",
    "sg:province":"Antwerpen",
    "wof:name":"Emversport",
    "wof:placetype":"venue"
},
  "geometry": {"coordinates":[4.7880702019,51.2588729858],"type":"Point"}
}