{
  "type": "Feature",
  "properties": {
    "addr:full":"Rue Yvonne Vieslet 10 Charleroi Hainaut 6031",
    "addr:housenumber":"10",
    "addr:postcode":"6031",
    "addr:street":"Rue Yvonne Vieslet;Hainaut",
    "iso:country":"BE",
    "sg:address":"Rue Yvonne Vieslet 10",
    "sg:city":"Charleroi",
    "sg:orig_category":"Enseignement maternel and primaire",
    "sg:phone":"+32 71 31 72 59",
    "sg:postcode":"6031",
    "sg:province":"Hainaut",
    "wof:name":"Ecole Matern. Communale",
    "wof:placetype":"venue"
},
  "geometry": {"coordinates":[4.3984851837,50.4071273804],"type":"Point"}
}