{
  "type": "Feature",
  "properties": {
    "iso:country":"BE",
    "sg:address":"Rue De La Grande Campagne 6",
    "sg:city":"Hornu",
    "sg:orig_category":"Cartographical Institutes",
    "sg:phone":"+32 65 71 52 11",
    "sg:postcode":"7301",
    "sg:province":"Hainaut",
    "wof:name":"Cap Gemini Ernst & Young Psi S.a.",
    "wof:placetype":"venue"
},
  "geometry": {"coordinates":[3.8394799232,50.4331092834],"type":"Point"}
}