{
  "type": "Feature",
  "properties": {
    "addr:full":"Walkurenstraat 30 Roeselare West-Vlaanderen 8800",
    "addr:housenumber":"30",
    "addr:postcode":"8800",
    "addr:street":"Walkurenstraat",
    "iso:country":"BE",
    "sg:address":"Walkurenstraat 30",
    "sg:city":"Roeselare",
    "sg:orig_category":"Studios photographiques. Activit\u00e9s diverses d'imprimerie",
    "sg:phone":"+32 51 24 18 08",
    "sg:postcode":"8800",
    "sg:province":"West-Vlaanderen",
    "wof:name":"Filip Ramon",
    "wof:placetype":"venue"
},
  "geometry": {"coordinates":[3.1076788902,50.9390869141],"type":"Point"}
}