{
  "type": "Feature",
  "properties": {
    "iso:country":"BE",
    "sg:address":"Daalstraat 121",
    "sg:city":"Grimbergen",
    "sg:orig_category":"Zuivelproducten and spijsolie Gh",
    "sg:phone":"+32 2 269 28 80",
    "sg:postcode":"1852",
    "sg:province":"Vlaams-Brabant",
    "wof:name":"Hof Ter Lint-de Clercq",
    "wof:placetype":"venue"
},
  "geometry": {"coordinates":[4.3774709702,50.9545974731],"type":"Point"}
}