{
  "type": "Feature",
  "properties": {
    "addr:full":"Schurhovenveld 3213 Sint-truiden Limburg 3800",
    "addr:postcode":"3213;3800",
    "addr:street":"Schurhovenveld",
    "iso:country":"BE",
    "sg:address":"Schurhovenveld 3213",
    "sg:city":"Sint-truiden",
    "sg:classifiers":[
        {
            "category":"Food & Beverages",
            "subcategory":"Fruits & Vegetables",
            "type":"Retail Goods"
        }
    ],
    "sg:phone":"+32 11 69 40 58",
    "sg:postcode":"3800",
    "sg:province":"Limburg",
    "sg:tags":[
        "l\u00e9gumes",
        "gr"
    ],
    "wof:name":"G.b.v.",
    "wof:placetype":"venue"
},
  "geometry": {"coordinates":[5.1863641739,50.8153343201],"type":"Point"}
}