{
  "type": "Feature",
  "properties": {
    "addr:full":"Stationsstraat 7 Zedelgem West-Vlaanderen 8210",
    "addr:housenumber":"7",
    "addr:postcode":"8210",
    "addr:street":"Stationsstraat",
    "iso:country":"BE",
    "sg:address":"Stationsstraat 7",
    "sg:city":"Zedelgem",
    "sg:orig_category":"Pharmaciens",
    "sg:phone":"+32 50 82 24 31",
    "sg:postcode":"8210",
    "sg:province":"West-Vlaanderen",
    "wof:name":"Luc Meulemeester",
    "wof:placetype":"venue"
},
  "geometry": {"coordinates":[3.1486570835,51.13804245],"type":"Point"}
}