{
  "type": "Feature",
  "properties": {
    "addr:full":"Charles Thielemanslaan 72 Sint-pieters-woluwe/woluwe-saint-pierre Bruxelles-Capitale 1150",
    "addr:housenumber":"72",
    "addr:postcode":"1150",
    "addr:street":"Thielemanslaan;/",
    "iso:country":"BE",
    "sg:address":"Charles Thielemanslaan 72",
    "sg:city":"Sint-pieters-woluwe/woluwe-saint-pierre",
    "sg:orig_category":"Kapsalons",
    "sg:phone":"+32 2 771 90 48",
    "sg:postcode":"1150",
    "sg:province":"Bruxelles-Capitale",
    "wof:name":"Coiffure Jodaly",
    "wof:placetype":"venue"
},
  "geometry": {"coordinates":[4.4283561707,50.836643219],"type":"Point"}
}