{
  "type": "Feature",
  "properties": {
    "iso:country":"BE",
    "sg:address":"Rue Abb\u00e9 Bastin 20",
    "sg:city":"Malmedy",
    "sg:classifiers":[
        {
            "category":"Building & Trades",
            "subcategory":"Electrical",
            "type":"Services"
        }
    ],
    "sg:phone":"+32 80 77 06 02",
    "sg:postcode":"4960",
    "sg:province":"Li\u00e8ge",
    "sg:tags":[
        "-",
        "electric",
        "contractor"
    ],
    "wof:name":"Gerard F",
    "wof:placetype":"venue"
},
  "geometry": {"coordinates":[6.0357780457,50.4220619202],"type":"Point"}
}