{
  "type": "Feature",
  "properties": {
    "addr:full":"Grote Molenweg 13 Zemst Vlaams-Brabant 1980",
    "addr:housenumber":"13",
    "addr:postcode":"1980",
    "addr:street":"Grote Molenweg;Vlaams-Brabant",
    "iso:country":"BE",
    "sg:address":"Grote Molenweg 13",
    "sg:city":"Zemst",
    "sg:orig_category":"Diverse bouwafwerking and reiniging",
    "sg:phone":"+32 15 61 22 14",
    "sg:postcode":"1980",
    "sg:province":"Vlaams-Brabant",
    "wof:name":"Julien Schoreels",
    "wof:placetype":"venue"
},
  "geometry": {"coordinates":[4.4460887909,50.9864807129],"type":"Point"}
}