{
  "type": "Feature",
  "properties": {
    "iso:country":"BE",
    "sg:address":"Rue Des Chasseurs 22",
    "sg:city":"Soignies",
    "sg:orig_category":"Artsen and specialisten",
    "sg:phone":"+32 67 33 39 78",
    "sg:postcode":"7060",
    "sg:province":"Hainaut",
    "wof:name":"P. Dancart",
    "wof:placetype":"venue"
},
  "geometry": {"coordinates":[4.0550370216,50.5830764771],"type":"Point"}
}