{
  "type": "Feature",
  "properties": {
    "iso:country":"BE",
    "sg:address":"Rue Fran\u00e7ois-boudart 12",
    "sg:city":"Arlon",
    "sg:classifiers":[
        {
            "category":"Health Services",
            "subcategory":"Doctor",
            "type":"Services"
        }
    ],
    "sg:phone":"+32 63 21 98 00",
    "sg:postcode":"6700",
    "sg:province":"Luxembourg",
    "sg:tags":[
        "psychotherapist",
        "psychoanalyst"
    ],
    "wof:name":"Delacollette A",
    "wof:placetype":"venue"
},
  "geometry": {"coordinates":[5.8091411591,49.6876487732],"type":"Point"}
}