{
  "type": "Feature",
  "properties": {
    "addr:full":"Vlaanderenstraat 11 Oostende West-Vlaanderen 8400",
    "addr:housenumber":"11",
    "addr:postcode":"8400",
    "addr:street":"Vlaanderenstraat",
    "iso:country":"BE",
    "sg:address":"Vlaanderenstraat 11",
    "sg:city":"Oostende",
    "sg:orig_category":"Brood, gebak and snoepgoed Speelgoed",
    "sg:phone":"+32 59 80 49 63",
    "sg:postcode":"8400",
    "sg:province":"West-Vlaanderen",
    "wof:name":"Timm's",
    "wof:placetype":"venue"
},
  "geometry": {"coordinates":[2.9166419506,51.2326583862],"type":"Point"}
}