{
  "type": "Feature",
  "properties": {
    "addr:full":"Heistraat 9 Sint-laureins Oost-Vlaanderen 9988",
    "addr:housenumber":"9",
    "addr:postcode":"9988",
    "addr:street":"Heistraat",
    "iso:country":"BE",
    "sg:address":"Heistraat 9",
    "sg:city":"Sint-laureins",
    "sg:orig_category":"Eleveurs de bovins",
    "sg:phone":"+32 9 379 89 07",
    "sg:postcode":"9988",
    "sg:province":"Oost-Vlaanderen",
    "wof:name":"Ivan Van Loo",
    "wof:placetype":"venue"
},
  "geometry": {"coordinates":[3.6185560226,51.250415802],"type":"Point"}
}