{
  "type": "Feature",
  "properties": {
    "addr:full":"Chauss\u00c9e De Bruxelles 9 Wavre Brabant Wallon 1300",
    "addr:housenumber":"9;1300",
    "addr:street":"Chausse\u0301E De Bruxelles",
    "iso:country":"BE",
    "sg:address":"Chauss\u00c9e De Bruxelles 9",
    "sg:city":"Wavre",
    "sg:orig_category":"Architecten",
    "sg:phone":"+32 10 24 25 26",
    "sg:postcode":"1300",
    "sg:province":"Brabant Wallon",
    "wof:name":"Bureau Riga & Associ\u00c9s",
    "wof:placetype":"venue"
},
  "geometry": {"coordinates":[4.6129360199,50.7191238403],"type":"Point"}
}