{
  "type": "Feature",
  "properties": {
    "addr:full":"Kluisstraat 86 Elsene/ixelles Bruxelles-Capitale 1050",
    "addr:housenumber":"86",
    "addr:postcode":"1050",
    "addr:street":"Kluisstraat",
    "iso:country":"BE",
    "sg:address":"Kluisstraat 86",
    "sg:city":"Elsene/ixelles",
    "sg:orig_category":"Boekenuitgeverijen Musea and historische gebouwen",
    "sg:phone":"+32 2 649 86 65",
    "sg:postcode":"1050",
    "sg:province":"Bruxelles-Capitale",
    "wof:name":"Mus\u00c9e Arch. Archit. Mod.",
    "wof:placetype":"venue"
},
  "geometry": {"coordinates":[4.3658590317,50.8285446167],"type":"Point"}
}