{
  "type": "Feature",
  "properties": {
    "addr:full":"Bergense Steenweg 7 Herenthout Antwerpen 2270",
    "addr:housenumber":"7",
    "addr:postcode":"2270",
    "addr:street":"Bergense Steenweg",
    "iso:country":"BE",
    "sg:address":"Bergense Steenweg 7",
    "sg:city":"Herenthout",
    "sg:orig_category":"Boekhouders",
    "sg:phone":"+32 14 51 48 98",
    "sg:postcode":"2270",
    "sg:province":"Antwerpen",
    "wof:name":"Koenraad Kelber",
    "wof:placetype":"venue"
},
  "geometry": {"coordinates":[4.7598390579,51.1436004639],"type":"Point"}
}