{
  "type": "Feature",
  "properties": {
    "addr:full":"Place Josse Goffin 34 Tubize (clabecq) Brabant Wallon 1480",
    "addr:housenumber":"34",
    "addr:postcode":"1480",
    "addr:street":"Place Josse Goffin;Wallon",
    "iso:country":"BE",
    "sg:address":"Place Josse Goffin 34",
    "sg:city":"Tubize (clabecq)",
    "sg:classifiers":[
        {
            "category":"Food & Beverages",
            "subcategory":"Groceries & Convenience Stores",
            "type":"Retail Goods"
        }
    ],
    "sg:phone":"+32 2 355 65 78",
    "sg:postcode":"1480",
    "sg:province":"Brabant Wallon",
    "sg:tags":[
        "grocer"
    ],
    "wof:name":"Regali\u00e8re (la)",
    "wof:placetype":"venue"
},
  "geometry": {"coordinates":[4.2221617699,50.6894378662],"type":"Point"}
}