{
  "type": "Feature",
  "properties": {
    "iso:country":"BE",
    "sg:address":"Sint-lenaartsebaan 29",
    "sg:city":"Malle (oostmalle)",
    "sg:classifiers":[
        {
            "category":"Social Services",
            "type":"Services"
        }
    ],
    "sg:phone":"+32 3 309 97 57",
    "sg:postcode":"2390",
    "sg:province":"Antwerpen",
    "wof:name":"Katholiek Vormingswerk Van Landelijke Vrouwen",
    "wof:placetype":"venue"
},
  "geometry": {"coordinates":[4.7292118073,51.3039627075],"type":"Point"}
}