{
  "type": "Feature",
  "properties": {
    "addr:full":"Guido Gezellestraat 2 Kortrijk West-Vlaanderen 8500",
    "addr:housenumber":"2",
    "addr:postcode":"8500",
    "addr:street":"Guido Gezellestraat",
    "iso:country":"BE",
    "sg:address":"Guido Gezellestraat 2",
    "sg:city":"Kortrijk",
    "sg:classifiers":[
        {
            "category":"Cafe",
            "type":"Food & Drink"
        }
    ],
    "sg:phone":"+32 56 25 62 45",
    "sg:postcode":"8500",
    "sg:province":"West-Vlaanderen",
    "sg:tags":[
        "caf\u00e9s"
    ],
    "wof:name":"Marc Decubber",
    "wof:placetype":"venue"
},
  "geometry": {"coordinates":[3.2672240734,50.8297767639],"type":"Point"}
}