{
  "type": "Feature",
  "properties": {
    "addr:full":"Kerkstraat 26 Londerzeel Vlaams-Brabant 1840",
    "addr:housenumber":"26",
    "addr:postcode":"1840",
    "addr:street":"Kerkstraat",
    "iso:country":"BE",
    "sg:address":"Kerkstraat 26",
    "sg:city":"Londerzeel",
    "sg:classifiers":[
        {
            "category":"Travel",
            "subcategory":"Travel Agent",
            "type":"Entertainment"
        }
    ],
    "sg:phone":"+32 52 30 38 48",
    "sg:postcode":"1840",
    "sg:province":"Vlaams-Brabant",
    "sg:tags":[
        "agency"
    ],
    "wof:name":"Reisburo Walter & Co Bvba",
    "wof:placetype":"venue"
},
  "geometry": {"coordinates":[4.3022680283,51.0029144287],"type":"Point"}
}