{
  "type": "Feature",
  "properties": {
    "iso:country":"BE",
    "sg:address":"Schuttersvest 23",
    "sg:city":"Mechelen",
    "sg:orig_category":"M\u00e9decins and sp\u00e9cialistes",
    "sg:phone":"+32 15 41 14 25",
    "sg:postcode":"2800",
    "sg:province":"Antwerpen",
    "wof:name":"D. Muzsnay",
    "wof:placetype":"venue"
},
  "geometry": {"coordinates":[4.4785108566,51.0210456848],"type":"Point"}
}