{
  "type": "Feature",
  "properties": {
    "iso:country":"BE",
    "sg:address":"Tienne De Boussu 26",
    "sg:city":"Couvin",
    "sg:orig_category":"M\u00e9decins and sp\u00e9cialistes",
    "sg:phone":"+32 60 34 42 33",
    "sg:postcode":"5660",
    "sg:province":"Namur",
    "wof:name":"Catherine Derminot",
    "wof:placetype":"venue"
},
  "geometry": {"coordinates":[4.4904751778,50.056060791],"type":"Point"}
}