{
  "type": "Feature",
  "properties": {
    "iso:country":"BE",
    "sg:address":"Rue Centrale 37",
    "sg:city":"Erquelinnes",
    "sg:orig_category":"S\u00e9curit\u00e9 sociale",
    "sg:phone":"+32 71 55 60 57",
    "sg:postcode":"6560",
    "sg:province":"Hainaut",
    "wof:name":"Mutualit\u00c9 Lib\u00c9rale",
    "wof:placetype":"venue"
},
  "geometry": {"coordinates":[4.1160740852,50.310005188],"type":"Point"}
}