{
  "type": "Feature",
  "properties": {
    "addr:full":"Avenue Louise 52 Elsene/ixelles Bruxelles-Capitale 1050",
    "addr:housenumber":"52",
    "addr:postcode":"1050",
    "addr:street":"Avenue Louise",
    "iso:country":"BE",
    "sg:address":"Avenue Louise 52",
    "sg:city":"Elsene/ixelles",
    "sg:classifiers":[
        {
            "category":"Shopping",
            "subcategory":"Clothing, Apparel, & Fashions",
            "type":"Retail Goods"
        }
    ],
    "sg:phone":"+32 2 513 84 97",
    "sg:postcode":"1050",
    "sg:province":"Bruxelles-Capitale",
    "sg:tags":[
        "v\u00eatements",
        "pour",
        "dame"
    ],
    "wof:name":"Scherrer Boutique",
    "wof:placetype":"venue"
},
  "geometry": {"coordinates":[4.3563308716,50.8357887268],"type":"Point"}
}