{
  "type": "Feature",
  "properties": {
    "iso:country":"BE",
    "sg:address":"Ninovesteenweg 198",
    "sg:city":"Aalst",
    "sg:orig_category":"Formation and enseignement. Traitement de donn\u00e9es",
    "sg:phone":"+32 53 70 61 26",
    "sg:postcode":"9320",
    "sg:province":"Oost-Vlaanderen",
    "wof:name":"Axxent Information Services",
    "wof:placetype":"venue"
},
  "geometry": {"coordinates":[4.0553851128,50.9209976196],"type":"Point"}
}