{
  "type": "Feature",
  "properties": {
    "iso:country":"BE",
    "sg:address":"Potaardestraat 8",
    "sg:city":"Izegem",
    "sg:orig_category":"Installatie van houten of kunststof schrijnwerk",
    "sg:phone":"+32 51 30 71 38",
    "sg:postcode":"8870",
    "sg:province":"West-Vlaanderen",
    "wof:name":"Verbrugghe Patrick",
    "wof:placetype":"venue"
},
  "geometry": {"coordinates":[3.2146790028,50.9205284119],"type":"Point"}
}