{
  "type": "Feature",
  "properties": {
    "addr:full":"Eindhovenlaan 10 Hasselt Limburg 3500",
    "addr:housenumber":"10",
    "addr:postcode":"3500",
    "addr:street":"Eindhovenlaan",
    "iso:country":"BE",
    "sg:address":"Eindhovenlaan 10",
    "sg:city":"Hasselt",
    "sg:classifiers":[
        {
            "category":"Building & Trades",
            "subcategory":"Construction",
            "type":"Services"
        }
    ],
    "sg:phone":"+32 11 21 29 40",
    "sg:postcode":"3500",
    "sg:province":"Limburg",
    "sg:tags":[
        "industrial",
        "design"
    ],
    "wof:name":"Skap Product Design Bvba",
    "wof:placetype":"venue"
},
  "geometry": {"coordinates":[5.3639259338,50.9462852478],"type":"Point"}
}