{
  "type": "Feature",
  "properties": {
    "addr:full":"Holt 112 Bilzen Limburg 3740",
    "addr:housenumber":"112",
    "addr:postcode":"3740",
    "iso:country":"BE",
    "sg:address":"Holt 112",
    "sg:city":"Bilzen",
    "sg:orig_category":"Epiceries",
    "sg:phone":"+32 89 49 18 72",
    "sg:postcode":"3740",
    "sg:province":"Limburg",
    "wof:name":"Jozef Briers",
    "wof:placetype":"venue"
},
  "geometry": {"coordinates":[5.4772481918,50.8893280029],"type":"Point"}
}