{
  "type": "Feature",
  "properties": {
    "iso:country":"BE",
    "sg:address":"Sint-pieterskerkstraat 8b10",
    "sg:city":"Jette/jette",
    "sg:classifiers":[
        {
            "category":"Cafe",
            "type":"Food & Drink"
        }
    ],
    "sg:phone":"+32 2 426 46 62",
    "sg:postcode":"1090",
    "sg:province":"Bruxelles-Capitale",
    "sg:tags":[
        "caf\u00e9s"
    ],
    "wof:name":"Caf\u00c9 Excelsior",
    "wof:placetype":"venue"
},
  "geometry": {"coordinates":[4.3269171715,50.8803901672],"type":"Point"}
}