{
  "type": "Feature",
  "properties": {
    "iso:country":"BE",
    "sg:address":"Pantserschipstr 183",
    "sg:city":"Gent",
    "sg:classifiers":[
        {
            "category":"Government",
            "subcategory":"Department Of Motor Vehicles",
            "type":"Public Place"
        }
    ],
    "sg:phone":"+32 9 253 96 76",
    "sg:postcode":"9000",
    "sg:province":"Oost-Vlaanderen",
    "sg:tags":[
        "equipment",
        "industrial",
        "transport",
        "motor-cars"
    ],
    "wof:name":"Werkhuizen Sovalee Nv",
    "wof:placetype":"venue"
},
  "geometry": {"coordinates":[3.727866888,51.0922698975],"type":"Point"}
}