{
  "type": "Feature",
  "properties": {
    "iso:country":"BE",
    "sg:address":"Legeweg 12ba",
    "sg:city":"Beernem",
    "sg:orig_category":"Eleveurs and marchands de porcs",
    "sg:phone":"+32 50 78 08 30",
    "sg:postcode":"8730",
    "sg:province":"West-Vlaanderen",
    "wof:name":"Bart Vanhaecke",
    "wof:placetype":"venue"
},
  "geometry": {"coordinates":[3.3240659237,51.1421661377],"type":"Point"}
}