{
  "type": "Feature",
  "properties": {
    "addr:full":"Donckstraat 30 Beringen (paal) Limburg 3583",
    "addr:housenumber":"30",
    "addr:postcode":"3583",
    "addr:street":"Donckstraat",
    "iso:country":"BE",
    "sg:address":"Donckstraat 30",
    "sg:city":"Beringen (paal)",
    "sg:classifiers":[
        {
            "category":"Arena",
            "subcategory":"Sports Club",
            "type":"Entertainment"
        }
    ],
    "sg:phone":"+32 13 61 89 50",
    "sg:postcode":"3583",
    "sg:province":"Limburg",
    "wof:name":"Millenium Golf",
    "wof:placetype":"venue"
},
  "geometry": {"coordinates":[5.1706700325,51.0389442444],"type":"Point"}
}