{
  "type": "Feature",
  "properties": {
    "iso:country":"BE",
    "sg:address":"Veerledorp 60",
    "sg:city":"Laakdal",
    "sg:orig_category":"Boucheries",
    "sg:phone":"+32 14 84 12 13",
    "sg:postcode":"2431",
    "sg:province":"Antwerpen",
    "wof:name":"Eddy Janssens",
    "wof:placetype":"venue"
},
  "geometry": {"coordinates":[4.9866828918,51.0694541931],"type":"Point"}
}