{
  "type": "Feature",
  "properties": {
    "addr:full":"Stationssteenweg 248 Nijlen (kessel) Antwerpen 2560",
    "addr:housenumber":"248",
    "addr:postcode":"2560",
    "addr:street":"Stationssteenweg",
    "iso:country":"BE",
    "sg:address":"Stationssteenweg 248",
    "sg:city":"Nijlen (kessel)",
    "sg:orig_category":"Newspapers, magazines, periodicals - Distribution",
    "sg:phone":"+32 3 480 68 42",
    "sg:postcode":"2560",
    "sg:province":"Antwerpen",
    "wof:name":"Kroniek Bvba",
    "wof:placetype":"venue"
},
  "geometry": {"coordinates":[4.6196699142,51.149887085],"type":"Point"}
}