{
  "type": "Feature",
  "properties": {
    "addr:full":"Rue Theophillepiat Wavre Brabant Wallon 1300",
    "addr:housenumber":"1300",
    "addr:street":"Rue Theophillepiat",
    "iso:country":"BE",
    "sg:address":"Rue Theophillepiat",
    "sg:city":"Wavre",
    "sg:orig_category":"Fujitsu Siemens. Ordinateurs and \u00e9quipement informatique. R\u00e9alisation de programmes and logiciels. C",
    "sg:phone":"+32 10 22 67 00",
    "sg:postcode":"1300",
    "sg:province":"Brabant Wallon",
    "wof:name":"Micro Design",
    "wof:placetype":"venue"
},
  "geometry": {"coordinates":[4.6060080528,50.7151184082],"type":"Point"}
}