{
  "type": "Feature",
  "properties": {
    "addr:full":"Rue D'hanzinne 24 Gerpinnes Hainaut 6280",
    "addr:housenumber":"24",
    "addr:postcode":"6280",
    "addr:street":"Rue D'Hanzinne;Hainaut",
    "iso:country":"BE",
    "sg:address":"Rue D'hanzinne 24",
    "sg:city":"Gerpinnes",
    "sg:classifiers":[
        {
            "category":"Farming",
            "subcategory":"Livestock Farm",
            "type":"Manufacturing & Wholesale Goods"
        }
    ],
    "sg:phone":"+32 71 50 31 46",
    "sg:postcode":"6280",
    "sg:province":"Hainaut",
    "sg:tags":[
        "buyer"
    ],
    "wof:name":"Gillain E",
    "wof:placetype":"venue"
},
  "geometry": {"coordinates":[4.5425581932,50.318862915],"type":"Point"}
}