{
  "type": "Feature",
  "properties": {
    "iso:country":"BE",
    "sg:address":"Avenue Jean Volders 39",
    "sg:city":"Sint-gillis/saint-gilles",
    "sg:orig_category":"Electrom\u00e9nager, t\u00e9l\u00e9visions and radios",
    "sg:phone":"+32 2 537 75 73",
    "sg:postcode":"1060",
    "sg:province":"Bruxelles-Capitale",
    "wof:name":"Farida Angri",
    "wof:placetype":"venue"
},
  "geometry": {"coordinates":[4.3431410789,50.8316917419],"type":"Point"}
}