{
  "type": "Feature",
  "properties": {
    "addr:full":"Rue De Birmingham 110 Anderlecht Bruxelles-Capitale 1070",
    "addr:housenumber":"110",
    "addr:postcode":"1070",
    "addr:street":"Rue De Birmingham",
    "iso:country":"BE",
    "sg:address":"Rue De Birmingham 110",
    "sg:city":"Anderlecht",
    "sg:orig_category":"Services de s\u00e9curit\u00e9 and entreprises de gardiennage",
    "sg:phone":"+32 2 556 04 00",
    "sg:postcode":"1070",
    "sg:province":"Bruxelles-Capitale",
    "wof:name":"Nomos",
    "wof:placetype":"venue"
},
  "geometry": {"coordinates":[4.3218722343,50.8449020386],"type":"Point"}
}