{
  "type": "Feature",
  "properties": {
    "addr:full":"Le Routeux 11 Herbeumont Luxembourg 6887",
    "addr:housenumber":"11",
    "addr:postcode":"6887",
    "iso:country":"BE",
    "sg:address":"Le Routeux 11",
    "sg:city":"Herbeumont",
    "sg:orig_category":"Brood, gebak and snoepgoed",
    "sg:phone":"+32 61 41 16 60",
    "sg:postcode":"6887",
    "sg:province":"Luxembourg",
    "wof:name":"Boulangerie L\u00b4ardennaise",
    "wof:placetype":"venue"
},
  "geometry": {"coordinates":[5.23706007,49.7813262939],"type":"Point"}
}