{
  "type": "Feature",
  "properties": {
    "iso:country":"BE",
    "sg:address":"Toekomststraat 32",
    "sg:city":"Hasselt",
    "sg:orig_category":"Avocats and conseillers juridiques",
    "sg:phone":"+32 11 22 68 84",
    "sg:postcode":"3500",
    "sg:province":"Limburg",
    "wof:name":"Annick Schruers",
    "wof:placetype":"venue"
},
  "geometry": {"coordinates":[5.3392710686,50.9259185791],"type":"Point"}
}