{
  "type": "Feature",
  "properties": {
    "addr:full":"Rue Fonds De For\u00cat 14 Fleron Li\u00e8ge 4623",
    "addr:housenumber":"14",
    "addr:postcode":"4623",
    "addr:street":"Rue Fonds De Fore\u0302T",
    "iso:country":"BE",
    "sg:address":"Rue Fonds De For\u00cat 14",
    "sg:city":"Fleron",
    "sg:orig_category":"M\u00e9decins and sp\u00e9cialistes",
    "sg:phone":"+32 4 358 76 30",
    "sg:postcode":"4623",
    "sg:province":"Li\u00e8ge",
    "wof:name":"Jeannine Bosson",
    "wof:placetype":"venue"
},
  "geometry": {"coordinates":[5.6838269234,50.6018867493],"type":"Point"}
}