{
  "type": "Feature",
  "properties": {
    "iso:country":"BE",
    "sg:address":"Heidestraat 15",
    "sg:city":"Kinrooi (ophoven)",
    "sg:classifiers":[
        {
            "category":"Retail",
            "subcategory":"Auto Repair",
            "type":"Services"
        }
    ],
    "sg:phone":"+32 89 56 22 02",
    "sg:postcode":"3640",
    "sg:province":"Limburg",
    "sg:tags":[
        "lpg",
        "automobile",
        "-",
        "system"
    ],
    "wof:name":"Vandeweerdt Ivo Garage Bvba",
    "wof:placetype":"venue"
},
  "geometry": {"coordinates":[5.7916898727,51.136089325],"type":"Point"}
}