{
  "type": "Feature",
  "properties": {
    "iso:country":"BE",
    "sg:address":"Rue De Boussoit",
    "sg:city":"Maurage",
    "sg:orig_category":"Huisdieren and benodigdheden Royal Canin",
    "sg:phone":"+32 64 67 60 90",
    "sg:postcode":"7010",
    "wof:name":"Ets Au Grain De Folie",
    "wof:placetype":"venue"
},
  "geometry": {"coordinates":[4.0969810486,50.4567756653],"type":"Point"}
}