{
  "type": "Feature",
  "properties": {
    "iso:country":"BE",
    "sg:address":"Rue De La Digue 2",
    "sg:city":"Amay",
    "sg:orig_category":"Sportclubs Sportterreinen and installaties behalve sportcentra",
    "sg:phone":"+32 85 31 19 86",
    "sg:postcode":"4540",
    "sg:province":"Li\u00e8ge",
    "wof:name":"F.c. Jehaytois",
    "wof:placetype":"venue"
},
  "geometry": {"coordinates":[5.3056540489,50.5518226624],"type":"Point"}
}