{
  "type": "Feature",
  "properties": {
    "iso:country":"BE",
    "sg:address":"Brusselsesteenweg 471",
    "sg:city":"Edingen/enghien",
    "sg:orig_category":"Taxi's Taxi's speciale diensten",
    "sg:phone":"+32 2 395 95 00",
    "sg:postcode":"7850",
    "sg:province":"Hainaut",
    "wof:name":"Taxi Roger",
    "wof:placetype":"venue"
},
  "geometry": {"coordinates":[4.0470499992,50.6943321228],"type":"Point"}
}