{
  "type": "Feature",
  "properties": {
    "addr:full":"De Nayerstraat 11ba Denderleeuw Oost-Vlaanderen 9470",
    "addr:postcode":"9470",
    "addr:street":"Nayerstraat",
    "iso:country":"BE",
    "sg:address":"De Nayerstraat 11ba",
    "sg:city":"Denderleeuw",
    "sg:orig_category":"Enseignement maternel and primaire",
    "sg:phone":"+32 53 64 78 71",
    "sg:postcode":"9470",
    "sg:province":"Oost-Vlaanderen",
    "wof:name":"Basisschool",
    "wof:placetype":"venue"
},
  "geometry": {"coordinates":[4.0780367851,50.8906936646],"type":"Point"}
}