{
  "type": "Feature",
  "properties": {
    "iso:country":"BE",
    "sg:address":"Boslaan 193",
    "sg:city":"Halle",
    "sg:orig_category":"Epiceries",
    "sg:phone":"+32 2 361 06 61",
    "sg:postcode":"1502",
    "sg:province":"Vlaams-Brabant",
    "wof:name":"Herremans",
    "wof:placetype":"venue"
},
  "geometry": {"coordinates":[4.231716156,50.7041015625],"type":"Point"}
}