{
  "type": "Feature",
  "properties": {
    "addr:full":"Rue Fontaine St Martin 1 Lillois 5428",
    "addr:housenumber":"1",
    "addr:postcode":"5428",
    "addr:street":"Rue Fontaine St;Lillois",
    "iso:country":"BE",
    "sg:address":"Rue Fontaine St Martin 1",
    "sg:city":"Lillois",
    "sg:classifiers":[
        {
            "category":"Food & Beverages",
            "subcategory":"Groceries & Convenience Stores",
            "type":"Retail Goods"
        }
    ],
    "sg:phone":"+32 2 343 25 92",
    "sg:postcode":"5428",
    "sg:tags":[
        "product",
        "related"
    ],
    "wof:name":"Thierry Kreusch Sa",
    "wof:placetype":"venue"
},
  "geometry": {"coordinates":[5.7167801857,45.2013511658],"type":"Point"}
}