{
  "type": "Feature",
  "properties": {
    "addr:full":"Lange Weverstraat 23 Lebbeke Oost-Vlaanderen 9280",
    "addr:housenumber":"23",
    "addr:postcode":"9280",
    "addr:street":"Lange Weverstraat",
    "iso:country":"BE",
    "sg:address":"Lange Weverstraat 23",
    "sg:city":"Lebbeke",
    "sg:classifiers":[
        {
            "category":"Food & Beverages",
            "subcategory":"Fruits & Vegetables",
            "type":"Retail Goods"
        }
    ],
    "sg:phone":"+32 52 41 05 32",
    "sg:postcode":"9280",
    "sg:province":"Oost-Vlaanderen",
    "sg:tags":[
        "l\u00e9gumes",
        "gr"
    ],
    "wof:name":"Vanweyenberge-v.d.meersch",
    "wof:placetype":"venue"
},
  "geometry": {"coordinates":[4.1359839439,50.9883728027],"type":"Point"}
}