{
  "type": "Feature",
  "properties": {
    "iso:country":"BE",
    "sg:address":"Rue De La Gendarmerie 41",
    "sg:city":"Quevy",
    "sg:classifiers":[
        {
            "category":"Arena",
            "subcategory":"Sports Club",
            "type":"Entertainment"
        }
    ],
    "sg:phone":"+32 65 56 95 34",
    "sg:postcode":"7040",
    "sg:province":"Hainaut",
    "sg:tags":[
        "de"
    ],
    "wof:name":"Les Dauphins De Mons",
    "wof:placetype":"venue"
},
  "geometry": {"coordinates":[3.9032840729,50.3416862488],"type":"Point"}
}