{
  "type": "Feature",
  "properties": {
    "addr:full":"Dendermondsesteenweg 61bbis Laarne Oost-Vlaanderen 9270",
    "addr:housenumber":"61bbis",
    "addr:postcode":"9270",
    "addr:street":"Dendermondsesteenweg",
    "iso:country":"BE",
    "sg:address":"Dendermondsesteenweg 61bbis",
    "sg:city":"Laarne",
    "sg:orig_category":"V\u00e9hicules automobiles. Entretien and r\u00e9parations de voitures",
    "sg:phone":"+32 9 367 50 48",
    "sg:postcode":"9270",
    "sg:province":"Oost-Vlaanderen",
    "wof:name":"Autocenter Necra",
    "wof:placetype":"venue"
},
  "geometry": {"coordinates":[3.9215369225,51.0458335876],"type":"Point"}
}