{
  "type": "Feature",
  "properties": {
    "addr:full":"Noordheuvel 84 Wuustwezel Antwerpen 2990",
    "addr:housenumber":"84",
    "addr:postcode":"2990",
    "addr:street":"Noordheuvel",
    "iso:country":"BE",
    "sg:address":"Noordheuvel 84",
    "sg:city":"Wuustwezel",
    "sg:orig_category":"Transports terrestres de voyageurs",
    "sg:phone":"+32 3 666 28 85",
    "sg:postcode":"2990",
    "sg:province":"Antwerpen",
    "wof:name":"Verheyden & Co",
    "wof:placetype":"venue"
},
  "geometry": {"coordinates":[4.5204358101,51.3739280701],"type":"Point"}
}