{
  "type": "Feature",
  "properties": {
    "addr:full":"Rue Des Mini\u00c8res 11 Bertrix Luxembourg 6880",
    "addr:housenumber":"11",
    "addr:postcode":"6880",
    "addr:street":"Rue Des Minie\u0300Res",
    "iso:country":"BE",
    "sg:address":"Rue Des Mini\u00c8res 11",
    "sg:city":"Bertrix",
    "sg:orig_category":"Installation de menuiserie en bois and plastique",
    "sg:phone":"+32 61 41 18 12",
    "sg:postcode":"6880",
    "sg:province":"Luxembourg",
    "wof:name":"Paul Faes",
    "wof:placetype":"venue"
},
  "geometry": {"coordinates":[5.2535948753,49.8544845581],"type":"Point"}
}