{
  "type": "Feature",
  "properties": {
    "iso:country":"BE",
    "sg:address":"R Verheyden 39",
    "sg:city":"Bruxelles",
    "sg:classifiers":[
        {
            "category":"Utilities",
            "subcategory":"Telephone",
            "type":"Services"
        }
    ],
    "sg:phone":"+32 2 529 62 11",
    "sg:postcode":"1070",
    "sg:province":"Bruxelles-Capitale",
    "sg:tags":[
        "electricity",
        "equipment",
        "electrical",
        "telecommunication",
        "electronic"
    ],
    "wof:name":"Aeg (belge) Sa",
    "wof:placetype":"venue"
},
  "geometry": {"coordinates":[4.317440033,50.846321106],"type":"Point"}
}