{
  "type": "Feature",
  "properties": {
    "addr:full":"Rue Du March\u00c9 Dour Hainaut 7370",
    "addr:postcode":"7370",
    "addr:street":"Rue Du Marche\u0301;Hainaut",
    "iso:country":"BE",
    "sg:address":"Rue Du March\u00c9",
    "sg:city":"Dour",
    "sg:orig_category":"Bioscopen",
    "sg:phone":"+32 65 31 16 39",
    "sg:postcode":"7370",
    "sg:province":"Hainaut",
    "wof:name":"Cin\u00c9 Dour",
    "wof:placetype":"venue"
},
  "geometry": {"coordinates":[3.7822709084,50.3954238892],"type":"Point"}
}