{
  "type": "Feature",
  "properties": {
    "addr:full":"Borluutplein 4 Gent (sint-denijs-westrem - Afsnee) Oost-Vlaanderen 9051",
    "addr:housenumber":"4",
    "addr:postcode":"9051",
    "addr:street":"Borluutplein;Oost-Vlaanderen",
    "iso:country":"BE",
    "sg:address":"Borluutplein 4",
    "sg:city":"Gent (sint-denijs-westrem - Afsnee)",
    "sg:classifiers":[
        {
            "category":"Professional",
            "subcategory":"Art Services",
            "type":"Services"
        }
    ],
    "sg:phone":"+32 9 245 21 20",
    "sg:postcode":"9051",
    "sg:province":"Oost-Vlaanderen",
    "sg:tags":[
        "photographer"
    ],
    "wof:name":"A.v.d.v. Fotostudio",
    "wof:placetype":"venue"
},
  "geometry": {"coordinates":[3.6669859886,51.0217895508],"type":"Point"}
}