{
  "type": "Feature",
  "properties": {
    "iso:country":"BE",
    "sg:address":"Engsbergseweg 118",
    "sg:city":"Tessenderlo",
    "sg:orig_category":"Passagiersvervoer over de weg Reisbureaus",
    "sg:phone":"+32 13 33 32 61",
    "sg:postcode":"3980",
    "sg:province":"Limburg",
    "wof:name":"Gery Tours",
    "wof:placetype":"venue"
},
  "geometry": {"coordinates":[5.0376701355,51.028629303],"type":"Point"}
}