{
  "type": "Feature",
  "properties": {
    "addr:full":"Konijnenboslaan 22 Gistel West-Vlaanderen 8470",
    "addr:housenumber":"22",
    "addr:postcode":"8470",
    "addr:street":"Konijnenboslaan",
    "iso:country":"BE",
    "sg:address":"Konijnenboslaan 22",
    "sg:city":"Gistel",
    "sg:classifiers":[
        {
            "category":"Building & Trades",
            "subcategory":"Landscaping Services",
            "type":"Services"
        }
    ],
    "sg:phone":"+32 59 27 74 16",
    "sg:postcode":"8470",
    "sg:province":"West-Vlaanderen",
    "sg:tags":[
        "gardening",
        "garden",
        "maintenance"
    ],
    "wof:name":"Tuinen Beyne Bvba",
    "wof:placetype":"venue"
},
  "geometry": {"coordinates":[2.9479138851,51.1506958008],"type":"Point"}
}