{
  "type": "Feature",
  "properties": {
    "iso:country":"BE",
    "sg:address":"Rue Bois Des Conins 15",
    "sg:city":"Genappe (bousval)",
    "sg:classifiers":[
        {
            "category":"Retail",
            "subcategory":"Event Space",
            "type":"Services"
        }
    ],
    "sg:phone":"+32 10 61 39 63",
    "sg:postcode":"1470",
    "sg:province":"Brabant Wallon",
    "sg:tags":[
        "rental",
        "-",
        "hall"
    ],
    "wof:name":"Ch\u00e2teau De Pallandt",
    "wof:placetype":"venue"
},
  "geometry": {"coordinates":[4.5122451782,50.6456871033],"type":"Point"}
}