{
  "type": "Feature",
  "properties": {
    "iso:country":"BE",
    "sg:address":"Westdorp 65",
    "sg:city":"Anzegem",
    "sg:classifiers":[
        {
            "category":"Personal",
            "subcategory":"Beauty Salon",
            "type":"Services"
        }
    ],
    "sg:phone":"+32 56 68 92 30",
    "sg:postcode":"8573",
    "sg:province":"West-Vlaanderen",
    "sg:tags":[
        "de",
        "coiffure"
    ],
    "wof:name":"Passchier",
    "wof:placetype":"venue"
},
  "geometry": {"coordinates":[3.4696938992,50.8075141907],"type":"Point"}
}