{
  "type": "Feature",
  "properties": {
    "iso:country":"BE",
    "sg:address":"Rue De Bruxelles 42",
    "sg:city":"Namur",
    "sg:classifiers":[
        {
            "category":"Personal",
            "subcategory":"Beauty Salon",
            "type":"Services"
        }
    ],
    "sg:phone":"+32 81 22 23 54",
    "sg:postcode":"5000",
    "sg:province":"Namur",
    "sg:tags":[
        "de",
        "coiffure"
    ],
    "wof:name":"Dominique Desneux",
    "wof:placetype":"venue"
},
  "geometry": {"coordinates":[4.8619160652,50.4658279419],"type":"Point"}
}