{
  "type": "Feature",
  "properties": {
    "addr:full":"R D'omez\u00e9e 135a Florennes Namur 5620",
    "addr:housenumber":"135a",
    "addr:postcode":"5620",
    "iso:country":"BE",
    "sg:address":"R D'omez\u00e9e 135a",
    "sg:city":"Florennes",
    "sg:classifiers":[
        {
            "category":"Farming",
            "subcategory":"Farm",
            "type":"Manufacturing & Wholesale Goods"
        }
    ],
    "sg:phone":"+32 82 68 89 73",
    "sg:postcode":"5620",
    "sg:province":"Namur",
    "sg:tags":[
        "horticulture",
        "agriculture",
        "livestock"
    ],
    "wof:name":"Sapins De Noel Dufour Scrl",
    "wof:placetype":"venue"
},
  "geometry": {"coordinates":[4.7431349754,50.2308425903],"type":"Point"}
}