{
  "type": "Feature",
  "properties": {
    "addr:full":"Place Verte 6b Florennes Namur 5620",
    "addr:housenumber":"6b",
    "addr:postcode":"5620",
    "addr:street":"Place Verte",
    "iso:country":"BE",
    "sg:address":"Place Verte 6b",
    "sg:city":"Florennes",
    "sg:classifiers":[
        {
            "category":"Shopping",
            "subcategory":"Clothing, Apparel, & Fashions",
            "type":"Retail Goods"
        }
    ],
    "sg:phone":"+32 71 68 62 94",
    "sg:postcode":"5620",
    "sg:province":"Namur",
    "sg:tags":[
        "underwear",
        "lingerie",
        "-"
    ],
    "wof:name":"Nuit & Jour",
    "wof:placetype":"venue"
},
  "geometry": {"coordinates":[4.6049799919,50.2500953674],"type":"Point"}
}