{
  "type": "Feature",
  "properties": {
    "iso:country":"BE",
    "sg:address":"Chrisantenlaan 15",
    "sg:city":"Koksijde",
    "sg:orig_category":"Industri\u00eble wasserijen and droogkuis",
    "sg:phone":"+32 58 51 46 29",
    "sg:postcode":"8670",
    "sg:province":"West-Vlaanderen",
    "wof:name":"De Meyer & Co",
    "wof:placetype":"venue"
},
  "geometry": {"coordinates":[2.6291348934,51.1104850769],"type":"Point"}
}