{
  "type": "Feature",
  "properties": {
    "addr:full":"Rue Du Roi Albert 198 Oupeye Li\u00e8ge 4680",
    "addr:housenumber":"198",
    "addr:postcode":"4680",
    "addr:street":"Rue Du Roi Albert",
    "iso:country":"BE",
    "sg:address":"Rue Du Roi Albert 198",
    "sg:city":"Oupeye",
    "sg:orig_category":"Herstelling leer and schoeisel Schoenen",
    "sg:phone":"+32 4 264 27 63",
    "sg:postcode":"4680",
    "sg:province":"Li\u00e8ge",
    "wof:name":"Ioannis Varveris",
    "wof:placetype":"venue"
},
  "geometry": {"coordinates":[5.6441497803,50.7090110779],"type":"Point"}
}