{
  "type": "Feature",
  "properties": {
    "iso:country":"BE",
    "sg:address":"Brederodestraat 25",
    "sg:city":"Brussel/bruxelles",
    "sg:orig_category":"Meubelzaken, woning- and keukeninrichting Verlichting and huishoudartikelen",
    "sg:phone":"+32 2 502 51 98",
    "sg:postcode":"1000",
    "sg:province":"Bruxelles-Capitale",
    "wof:name":"Swaliber",
    "wof:placetype":"venue"
},
  "geometry": {"coordinates":[4.3625831604,50.8403015137],"type":"Point"}
}