{
  "type": "Feature",
  "properties": {
    "addr:full":"Brusselsesteenweg 54 Mechelen Antwerpen 2800",
    "addr:housenumber":"54",
    "addr:postcode":"2800",
    "addr:street":"Brusselsesteenweg",
    "iso:country":"BE",
    "sg:address":"Brusselsesteenweg 54",
    "sg:city":"Mechelen",
    "sg:classifiers":[
        {
            "category":"Personal",
            "subcategory":"Beauty Salon",
            "type":"Services"
        }
    ],
    "sg:phone":"+32 15 41 21 73",
    "sg:postcode":"2800",
    "sg:province":"Antwerpen",
    "sg:tags":[
        "lady",
        "-",
        "hairdressing"
    ],
    "wof:name":"Jean Paul",
    "wof:placetype":"venue"
},
  "geometry": {"coordinates":[4.4724040031,51.0193786621],"type":"Point"}
}