{
  "type": "Feature",
  "properties": {
    "addr:full":"Stestertstrasse 21 Raeren (eynatten) Li\u00e8ge 4731",
    "addr:housenumber":"21",
    "addr:postcode":"4731",
    "addr:street":"Stestertstrasse",
    "iso:country":"BE",
    "sg:address":"Stestertstrasse 21",
    "sg:city":"Raeren (eynatten)",
    "sg:classifiers":[
        {
            "category":"Sports & Exercise",
            "subcategory":"Stables",
            "type":"Entertainment"
        }
    ],
    "sg:phone":"+32 87 85 15 71",
    "sg:postcode":"4731",
    "sg:province":"Li\u00e8ge",
    "sg:tags":[
        "riding",
        "school"
    ],
    "wof:name":"Gut Charolie",
    "wof:placetype":"venue"
},
  "geometry": {"coordinates":[6.1065602303,50.6964607239],"type":"Point"}
}