{
  "type": "Feature",
  "properties": {
    "addr:full":"Rue Houtart 14bb Charleroi Hainaut 6040",
    "addr:housenumber":"14bb",
    "addr:postcode":"6040",
    "addr:street":"Rue Houtart;Hainaut",
    "iso:country":"BE",
    "sg:address":"Rue Houtart 14bb",
    "sg:city":"Charleroi",
    "sg:classifiers":[
        {
            "category":"Communications",
            "subcategory":"Radio Station",
            "type":"Services"
        }
    ],
    "sg:phone":"+32 71 35 61 66",
    "sg:postcode":"6040",
    "sg:province":"Hainaut",
    "sg:tags":[
        "diffusion",
        "production",
        "de",
        "programme"
    ],
    "wof:name":"Radio J. 600",
    "wof:placetype":"venue"
},
  "geometry": {"coordinates":[4.4080810547,50.4456291199],"type":"Point"}
}