{
  "type": "Feature",
  "properties": {
    "addr:full":"Bissegemstraat 100 Wevelgem West-Vlaanderen 8560",
    "addr:housenumber":"100",
    "addr:postcode":"8560",
    "addr:street":"Bissegemstraat",
    "iso:country":"BE",
    "sg:address":"Bissegemstraat 100",
    "sg:city":"Wevelgem",
    "sg:classifiers":[
        {
            "category":"Insurance",
            "subcategory":"Insurance Agent",
            "type":"Services"
        }
    ],
    "sg:phone":"+32 56 41 91 22",
    "sg:postcode":"8560",
    "sg:province":"West-Vlaanderen",
    "sg:tags":[
        "verzekeringsmakelaars",
        "expert"
    ],
    "wof:name":"Verzekeringen Soubry",
    "wof:placetype":"venue"
},
  "geometry": {"coordinates":[3.2085540295,50.839427948],"type":"Point"}
}