{
  "type": "Feature",
  "properties": {
    "addr:full":"Verheydenstraat 51 Dilbeek Vlaams-Brabant 1700",
    "addr:housenumber":"51",
    "addr:postcode":"1700",
    "addr:street":"Verheydenstraat",
    "iso:country":"BE",
    "sg:address":"Verheydenstraat 51",
    "sg:city":"Dilbeek",
    "sg:orig_category":"Opticiens",
    "sg:phone":"+32 2 569 21 15",
    "sg:postcode":"1700",
    "sg:province":"Vlaams-Brabant",
    "wof:name":"Nadia Depril",
    "wof:placetype":"venue"
},
  "geometry": {"coordinates":[4.2613558769,50.8447761536],"type":"Point"}
}