{
  "type": "Feature",
  "properties": {
    "iso:country":"BE",
    "sg:address":"Rue Charles Magnette 22",
    "sg:city":"Li\u00e8ge 1",
    "sg:classifiers":[
        {
            "category":"Shopping",
            "subcategory":"Clothing, Apparel, & Fashions",
            "type":"Retail Goods"
        }
    ],
    "sg:phone":"+32 4 223 69 03",
    "sg:postcode":"4000",
    "sg:province":"Li\u00e8ge",
    "sg:tags":[
        "hosiery"
    ],
    "wof:name":"Wolford Boutique",
    "wof:placetype":"venue"
},
  "geometry": {"coordinates":[5.5724859238,50.6408081055],"type":"Point"}
}