{
  "type": "Feature",
  "properties": {
    "addr:full":"Chauss\u00c9e De Ten-brielen 58b4 Komen-waasten/comines-warneton Hainaut 7780",
    "addr:housenumber":"58b4;7780",
    "addr:street":"Chausse\u0301E De Ten-Brielen",
    "iso:country":"BE",
    "sg:address":"Chauss\u00c9e De Ten-brielen 58b4",
    "sg:city":"Komen-waasten/comines-warneton",
    "sg:orig_category":"Epiceries",
    "sg:phone":"+32 56 55 55 52",
    "sg:postcode":"7780",
    "sg:province":"Hainaut",
    "wof:name":"Very Good Product",
    "wof:placetype":"venue"
},
  "geometry": {"coordinates":[2.9990000725,50.7806243896],"type":"Point"}
}