{
  "type": "Feature",
  "properties": {
    "addr:full":"Hoevestraat 7 Gooik Vlaams-Brabant 1755",
    "addr:housenumber":"7",
    "addr:postcode":"1755",
    "addr:street":"Hoevestraat",
    "iso:country":"BE",
    "sg:address":"Hoevestraat 7",
    "sg:city":"Gooik",
    "sg:orig_category":"Eleveurs and marchands de porcs. Eleveurs de bovins",
    "sg:phone":"+32 54 56 65 64",
    "sg:postcode":"1755",
    "sg:province":"Vlaams-Brabant",
    "wof:name":"Van Heghe",
    "wof:placetype":"venue"
},
  "geometry": {"coordinates":[4.0697398186,50.7906608582],"type":"Point"}
}