{
  "type": "Feature",
  "properties": {
    "iso:country":"BE",
    "sg:address":"Busselenbergstraat 28",
    "sg:city":"Anderlecht",
    "sg:orig_category":"Artsen and specialisten",
    "sg:phone":"+32 2 522 38 58",
    "sg:postcode":"1070",
    "sg:province":"Bruxelles-Capitale",
    "wof:name":"Marianne Lauwers",
    "wof:placetype":"venue"
},
  "geometry": {"coordinates":[4.3020629883,50.8294181824],"type":"Point"}
}