{
  "type": "Feature",
  "properties": {
    "addr:full":"Rue D'anderlues 8 Thuin Hainaut 6530",
    "addr:housenumber":"8",
    "addr:postcode":"6530",
    "addr:street":"Rue D'Anderlues",
    "iso:country":"BE",
    "sg:address":"Rue D'anderlues 8",
    "sg:city":"Thuin",
    "sg:classifiers":[
        {
            "category":"Sports & Exercise",
            "subcategory":"Gym",
            "type":"Entertainment"
        }
    ],
    "sg:phone":"+32 475 95 11 95",
    "sg:postcode":"6530",
    "sg:province":"Hainaut",
    "sg:tags":[
        "fitness"
    ],
    "wof:name":"Body Style",
    "wof:placetype":"venue"
},
  "geometry": {"coordinates":[4.2874817848,50.3434333801],"type":"Point"}
}