{
  "type": "Feature",
  "properties": {
    "addr:full":"Kapittelstraat 10 Ninove (appelterre-eichem) Oost-Vlaanderen 9400",
    "addr:housenumber":"10",
    "addr:postcode":"9400",
    "addr:street":"Kapittelstraat",
    "iso:country":"BE",
    "sg:address":"Kapittelstraat 10",
    "sg:city":"Ninove (appelterre-eichem)",
    "sg:classifiers":[
        {
            "category":"Autos & Motor Vehicles",
            "subcategory":"Automobile Sales",
            "type":"Retail Goods"
        }
    ],
    "sg:phone":"+32 54 33 37 51",
    "sg:postcode":"9400",
    "sg:province":"Oost-Vlaanderen",
    "sg:tags":[
        "car",
        "used",
        "-"
    ],
    "wof:name":"Cromphout J",
    "wof:placetype":"venue"
},
  "geometry": {"coordinates":[4.0232000351,50.8349113464],"type":"Point"}
}