{
  "type": "Feature",
  "properties": {
    "addr:full":"Oostkade 24 Zelzate Oost-Vlaanderen 9060",
    "addr:housenumber":"24",
    "addr:postcode":"9060",
    "addr:street":"Oostkade",
    "iso:country":"BE",
    "sg:address":"Oostkade 24",
    "sg:city":"Zelzate",
    "sg:orig_category":"Verplichte sociale verzekeringen",
    "sg:phone":"+32 9 345 55 75",
    "sg:postcode":"9060",
    "sg:province":"Oost-Vlaanderen",
    "wof:name":"Christelijke Mutualiteit",
    "wof:placetype":"venue"
},
  "geometry": {"coordinates":[3.8102009296,51.199432373],"type":"Point"}
}