{
  "type": "Feature",
  "properties": {
    "addr:full":"Rue Dr. Parent 399ba Andenne Namur 5300",
    "addr:postcode":"5300",
    "addr:street":"Rue Dr.;399Ba",
    "iso:country":"BE",
    "sg:address":"Rue Dr. Parent 399ba",
    "sg:city":"Andenne",
    "sg:orig_category":"Herstellingen and onderhoud van auto's",
    "sg:phone":"+32 81 58 04 55",
    "sg:postcode":"5300",
    "sg:province":"Namur",
    "wof:name":"Carrosserie Lumarvel",
    "wof:placetype":"venue"
},
  "geometry": {"coordinates":[5.0386018753,50.4935569763],"type":"Point"}
}