{
  "type": "Feature",
  "properties": {
    "addr:full":"Dorpsstraat 73 Middelkerke West-Vlaanderen 8432",
    "addr:housenumber":"73",
    "addr:postcode":"8432",
    "addr:street":"Dorpsstraat",
    "iso:country":"BE",
    "sg:address":"Dorpsstraat 73",
    "sg:city":"Middelkerke",
    "sg:orig_category":"Plaatsen van vloer- and muurbekleding Schilders",
    "sg:phone":"+32 59 30 03 05",
    "sg:postcode":"8432",
    "sg:province":"West-Vlaanderen",
    "wof:name":"Marcel Vaneessen",
    "wof:placetype":"venue"
},
  "geometry": {"coordinates":[2.8768401146,51.1755104065],"type":"Point"}
}