{
  "type": "Feature",
  "properties": {
    "addr:full":"Avenue Des D\u00c9mineurs 28 Stavelot Li\u00e8ge 4970",
    "addr:housenumber":"28",
    "addr:postcode":"4970",
    "addr:street":"Avenue Des De\u0301Mineurs",
    "iso:country":"BE",
    "sg:address":"Avenue Des D\u00c9mineurs 28",
    "sg:city":"Stavelot",
    "sg:classifiers":[
        {
            "category":"Autos & Motor Vehicles",
            "subcategory":"Fuel & Gas Station",
            "type":"Retail Goods"
        }
    ],
    "sg:phone":"+32 80 86 24 91",
    "sg:postcode":"4970",
    "sg:province":"Li\u00e8ge",
    "sg:tags":[
        "stations-service",
        "carburants"
    ],
    "wof:name":"Avia",
    "wof:placetype":"venue"
},
  "geometry": {"coordinates":[5.9355602264,50.3963890076],"type":"Point"}
}