{
  "type": "Feature",
  "properties": {
    "iso:country":"BE",
    "sg:address":"Rijksweg 558a",
    "sg:city":"Maasmechelen",
    "sg:orig_category":"Articles de jardin. Fleurs and plantes. Meubles D\u00e9taillants, Am\u00e9nagement de B\u00e2timents et de Cuisines",
    "sg:phone":"+32 89 76 29 90",
    "sg:postcode":"3630",
    "sg:province":"Limburg",
    "wof:name":"Tuincentrum De Vlotten",
    "wof:placetype":"venue"
},
  "geometry": {"coordinates":[5.6942400932,50.956161499],"type":"Point"}
}