{
  "type": "Feature",
  "properties": {
    "addr:full":"Leiestraat 5 Wervik West-Vlaanderen 8940",
    "addr:housenumber":"5",
    "addr:postcode":"8940",
    "addr:street":"Leiestraat",
    "iso:country":"BE",
    "sg:address":"Leiestraat 5",
    "sg:city":"Wervik",
    "sg:orig_category":"Agences immobili\u00e8res. Promoteurs immobiliers. Evaluation and estimation de biens immobiliers. Admini",
    "sg:phone":"+32 56 31 15 41",
    "sg:postcode":"8940",
    "sg:province":"West-Vlaanderen",
    "wof:name":"Marimo",
    "wof:placetype":"venue"
},
  "geometry": {"coordinates":[3.0421578884,50.7774963379],"type":"Point"}
}