{
  "type": "Feature",
  "properties": {
    "addr:full":"Haagweg 25 Meeuwen-gruitrode Limburg 3670",
    "addr:housenumber":"25",
    "addr:postcode":"3670",
    "addr:street":"Haagweg",
    "iso:country":"BE",
    "sg:address":"Haagweg 25",
    "sg:city":"Meeuwen-gruitrode",
    "sg:orig_category":"Entretien and r\u00e9parations de voitures",
    "sg:phone":"+32 89 85 62 23",
    "sg:postcode":"3670",
    "sg:province":"Limburg",
    "wof:name":"Guido Bosmans",
    "wof:placetype":"venue"
},
  "geometry": {"coordinates":[5.6092767715,51.0878372192],"type":"Point"}
}