{
  "type": "Feature",
  "properties": {
    "iso:country":"BE",
    "sg:address":"Rue M Thilges 7",
    "sg:city":"Wiltz",
    "sg:classifiers":[
        {
            "category":"Real Estate",
            "subcategory":"Architect",
            "type":"Services"
        }
    ],
    "sg:phone":"+352 21166654",
    "sg:postcode":"9573",
    "wof:name":"Bureau Ab+ De Barsy B",
    "wof:placetype":"venue"
},
  "geometry": {"coordinates":[5.9297327995,49.9662361145],"type":"Point"}
}