{
  "type": "Feature",
  "properties": {
    "iso:country":"BE",
    "sg:address":"Iepersestraat 110",
    "sg:city":"Roeselare",
    "sg:orig_category":"Sociale secretariaten",
    "sg:phone":"+32 51 22 43 04",
    "sg:postcode":"8800",
    "sg:province":"West-Vlaanderen",
    "wof:name":"De Eekhoorn",
    "wof:placetype":"venue"
},
  "geometry": {"coordinates":[3.1193480492,50.9415130615],"type":"Point"}
}