{
  "type": "Feature",
  "properties": {
    "addr:full":"Huidevetterskaai 32 Gent Oost-Vlaanderen 9000",
    "addr:housenumber":"32",
    "addr:postcode":"9000",
    "addr:street":"Huidevetterskaai;Oost-Vlaanderen",
    "iso:country":"BE",
    "sg:address":"Huidevetterskaai 32",
    "sg:city":"Gent",
    "sg:classifiers":[
        {
            "category":"Health Services",
            "subcategory":"Doctor",
            "type":"Services"
        }
    ],
    "sg:phone":"+32 9 225 28 98",
    "sg:postcode":"9000",
    "sg:province":"Oost-Vlaanderen",
    "sg:tags":[
        "medicinephysicians",
        "surgeon"
    ],
    "wof:name":"Hach\u00e9 Raoul",
    "wof:placetype":"venue"
},
  "geometry": {"coordinates":[3.7283859253,51.0606384277],"type":"Point"}
}