{
  "type": "Feature",
  "properties": {
    "iso:country":"BE",
    "sg:address":"Bondgenotenstraat 120",
    "sg:city":"Vorst/forest",
    "sg:orig_category":"Herstellingen and onderhoud van auto's Voertuigen",
    "sg:phone":"+32 2 345 45 98",
    "sg:postcode":"1190",
    "sg:province":"Bruxelles-Capitale",
    "wof:name":"Carrosserie Grugeon",
    "wof:placetype":"venue"
},
  "geometry": {"coordinates":[4.326649189,50.8178443909],"type":"Point"}
}