{
  "type": "Feature",
  "properties": {
    "iso:country":"BE",
    "sg:address":"Groenestraat 9",
    "sg:city":"Lo-reninge",
    "sg:orig_category":"Eleveurs de bovins. Eleveurs and marchands de porcs",
    "sg:phone":"+32 57 42 26 14",
    "sg:postcode":"8647",
    "sg:province":"West-Vlaanderen",
    "wof:name":"Andre Vermeulen",
    "wof:placetype":"venue"
},
  "geometry": {"coordinates":[2.8058960438,50.9143295288],"type":"Point"}
}