{
  "type": "Feature",
  "properties": {
    "addr:full":"Avenue De Houffalize 42 Libramont-chevigny Luxembourg 6800",
    "addr:housenumber":"42",
    "addr:postcode":"6800",
    "addr:street":"Avenue De Houffalize",
    "iso:country":"BE",
    "sg:address":"Avenue De Houffalize 42",
    "sg:city":"Libramont-chevigny",
    "sg:orig_category":"M\u00e9decins and sp\u00e9cialistes",
    "sg:phone":"+32 61 22 26 89",
    "sg:postcode":"6800",
    "sg:province":"Luxembourg",
    "wof:name":"Carol Huberty",
    "wof:placetype":"venue"
},
  "geometry": {"coordinates":[5.3761348724,49.9199943542],"type":"Point"}
}