{
  "type": "Feature",
  "properties": {
    "iso:country":"BE",
    "sg:address":"Beekstraat 84",
    "sg:city":"Kortrijk",
    "sg:classifiers":[
        {
            "category":"Food & Beverages",
            "subcategory":"Supermarket",
            "type":"Retail Goods"
        }
    ],
    "sg:phone":"+32 56 22 90 90",
    "sg:postcode":"8500",
    "sg:province":"West-Vlaanderen",
    "sg:tags":[
        "department",
        "store"
    ],
    "wof:name":"Rivan",
    "wof:placetype":"venue"
},
  "geometry": {"coordinates":[3.2856919765,50.8178405762],"type":"Point"}
}