{
  "type": "Feature",
  "properties": {
    "iso:country":"BE",
    "sg:address":"Markt 52",
    "sg:city":"Oudenaarde",
    "sg:orig_category":"Banken and kredietinstellingen",
    "sg:phone":"+32 55 30 20 59",
    "sg:postcode":"9700",
    "sg:province":"Oost-Vlaanderen",
    "wof:name":"Bank De Maertelaere",
    "wof:placetype":"venue"
},
  "geometry": {"coordinates":[3.6035029888,50.843421936],"type":"Point"}
}