{
  "type": "Feature",
  "properties": {
    "iso:country":"BE",
    "sg:address":"Kremerstraat 12",
    "sg:city":"Zonhoven",
    "sg:classifiers":[
        {
            "category":"Banks & Credit Unions",
            "subcategory":"Investment Brokerage",
            "type":"Services"
        }
    ],
    "sg:phone":"+32 11 72 85 83",
    "sg:postcode":"3520",
    "sg:province":"Limburg",
    "sg:tags":[
        "printing",
        "-"
    ],
    "wof:name":"Prommid Bvba",
    "wof:placetype":"venue"
},
  "geometry": {"coordinates":[5.3785028458,50.9970436096],"type":"Point"}
}