{
  "type": "Feature",
  "properties": {
    "iso:country":"BE",
    "sg:address":"Rue Campagne 5-7",
    "sg:city":"Amay (ampsin)",
    "sg:orig_category":"Non-Classified Establishments",
    "sg:phone":"+32 85 31 25 21",
    "sg:postcode":"4540",
    "sg:province":"Li\u00e8ge",
    "wof:name":"Sanima Sa",
    "wof:placetype":"venue"
},
  "geometry": {"coordinates":[5.3180990219,50.5478668213],"type":"Point"}
}