{
  "type": "Feature",
  "properties": {
    "addr:full":"Avenue De Cortenbergh 71 Bruxelles Bruxelles-Capitale 1000",
    "addr:housenumber":"71",
    "addr:postcode":"1000",
    "addr:street":"Avenue De Cortenbergh",
    "iso:country":"BE",
    "sg:address":"Avenue De Cortenbergh 71",
    "sg:city":"Bruxelles",
    "sg:classifiers":[
        {
            "category":"Retail",
            "subcategory":"Auto Rental",
            "type":"Services"
        }
    ],
    "sg:phone":"+32 2 790 06 00",
    "sg:postcode":"1000",
    "sg:province":"Bruxelles-Capitale",
    "sg:tags":[
        "term",
        "van",
        "cars",
        "-",
        "long",
        "delivery",
        "truck"
    ],
    "wof:name":"Locabel Truck",
    "wof:placetype":"venue"
},
  "geometry": {"coordinates":[4.389043808,50.844543457],"type":"Point"}
}