{
  "type": "Feature",
  "properties": {
    "iso:country":"BE",
    "sg:address":"Rue De Namur 136",
    "sg:city":"Hannut (moxhe)",
    "sg:classifiers":[
        {
            "category":"Building & Trades",
            "subcategory":"Construction",
            "type":"Services"
        }
    ],
    "sg:phone":"+32 19 69 86 65",
    "sg:postcode":"4280",
    "sg:province":"Li\u00e8ge",
    "sg:tags":[
        "carpenter"
    ],
    "wof:name":"Riga J-l",
    "wof:placetype":"venue"
},
  "geometry": {"coordinates":[5.0750999451,50.6651802063],"type":"Point"}
}