{
  "type": "Feature",
  "properties": {
    "addr:full":"Wijngaardstraat 26bb1 Gooik Vlaams-Brabant 1755",
    "addr:housenumber":"26bb1",
    "addr:postcode":"1755",
    "addr:street":"Wijngaardstraat",
    "iso:country":"BE",
    "sg:address":"Wijngaardstraat 26bb1",
    "sg:city":"Gooik",
    "sg:orig_category":"Gespecialiseerde residenti\u00eble bouw",
    "sg:phone":"+32 2 532 48 28",
    "sg:postcode":"1755",
    "sg:province":"Vlaams-Brabant",
    "wof:name":"Johny Thielemans",
    "wof:placetype":"venue"
},
  "geometry": {"coordinates":[4.122964859,50.7963447571],"type":"Point"}
}