{
  "type": "Feature",
  "properties": {
    "addr:full":"Elzenbroekstraat 27 Oud-heverlee Vlaams-Brabant 3053",
    "addr:housenumber":"27",
    "addr:postcode":"3053",
    "addr:street":"Elzenbroekstraat",
    "iso:country":"BE",
    "sg:address":"Elzenbroekstraat 27",
    "sg:city":"Oud-heverlee",
    "sg:orig_category":"Banken and kredietinstellingen",
    "sg:phone":"+32 16 40 18 87",
    "sg:postcode":"3053",
    "sg:province":"Vlaams-Brabant",
    "wof:name":"Citibank",
    "wof:placetype":"venue"
},
  "geometry": {"coordinates":[4.7274580002,50.8360290527],"type":"Point"}
}