{
  "type": "Feature",
  "properties": {
    "addr:full":"Route De Str\u00e9e 28 Modave (str\u00e9e-lez-huy) Li\u00e8ge 4577",
    "addr:housenumber":"28",
    "addr:postcode":"4577",
    "addr:street":"Route De Stre\u0301E;Stre\u0301E-Lez-Huy",
    "iso:country":"BE",
    "sg:address":"Route De Str\u00e9e 28",
    "sg:city":"Modave (str\u00e9e-lez-huy)",
    "sg:classifiers":[
        {
            "category":"Farming",
            "subcategory":"Farm & Veterinary Services",
            "type":"Manufacturing & Wholesale Goods"
        }
    ],
    "sg:phone":"+32 85 51 26 77",
    "sg:postcode":"4577",
    "sg:province":"Li\u00e8ge",
    "sg:tags":[
        "agricultural",
        "contractor"
    ],
    "wof:name":"Kerkhofs G",
    "wof:placetype":"venue"
},
  "geometry": {"coordinates":[5.3196558952,50.4926834106],"type":"Point"}
}