{
  "type": "Feature",
  "properties": {
    "addr:full":"Rue De L\u00b4encloitre 4 Les Bons Villers Hainaut 6210",
    "addr:housenumber":"4",
    "addr:postcode":"6210",
    "addr:street":"Rue De L\u00b4Encloitre",
    "iso:country":"BE",
    "sg:address":"Rue De L\u00b4encloitre 4",
    "sg:city":"Les Bons Villers",
    "sg:orig_category":"Rusthuizen and serviceflats",
    "sg:phone":"+32 71 85 13 81",
    "sg:postcode":"6210",
    "sg:province":"Hainaut",
    "wof:name":"R\u00c9sidence Alpha Ii",
    "wof:placetype":"venue"
},
  "geometry": {"coordinates":[4.4511561394,50.5378227234],"type":"Point"}
}