{
  "type": "Feature",
  "properties": {
    "addr:full":"Jan Frans Willemsstraat 4 Koksijde West-Vlaanderen 8670",
    "addr:housenumber":"4",
    "addr:postcode":"8670",
    "addr:street":"Jan Frans Willemsstraat",
    "iso:country":"BE",
    "sg:address":"Jan Frans Willemsstraat 4",
    "sg:city":"Koksijde",
    "sg:classifiers":[
        {
            "category":"Fast Food",
            "type":"Food & Drink"
        }
    ],
    "sg:phone":"+32 58 51 04 42",
    "sg:postcode":"8670",
    "sg:province":"West-Vlaanderen",
    "sg:tags":[
        "fried",
        "stand",
        "potato"
    ],
    "wof:name":"Pacha",
    "wof:placetype":"venue"
},
  "geometry": {"coordinates":[2.6355021,51.121131897],"type":"Point"}
}