{
  "type": "Feature",
  "properties": {
    "addr:full":"Rue Des Savoyards 2 Marche-en-famenne (grand) Luxembourg 6900",
    "addr:housenumber":"2",
    "addr:postcode":"6900",
    "addr:street":"Rue Des Savoyards",
    "iso:country":"BE",
    "sg:address":"Rue Des Savoyards 2",
    "sg:city":"Marche-en-famenne (grand)",
    "sg:orig_category":"Ziekenhuizen and zorginstellingen",
    "sg:phone":"+32 84 32 00 95",
    "sg:postcode":"6900",
    "sg:province":"Luxembourg",
    "wof:name":"Centre De Planning Familial Des Fps",
    "wof:placetype":"venue"
},
  "geometry": {"coordinates":[5.3450498581,50.2274513245],"type":"Point"}
}