{
  "type": "Feature",
  "properties": {
    "addr:full":"Langendijkstraat 5a Zutendaal Limburg 3690",
    "addr:housenumber":"5a",
    "addr:postcode":"3690",
    "addr:street":"Langendijkstraat",
    "iso:country":"BE",
    "sg:address":"Langendijkstraat 5a",
    "sg:city":"Zutendaal",
    "sg:orig_category":"Mobilier and \u00e9quipement m\u00e9nager Equipement divers pour commerces Gr",
    "sg:phone":"+32 89 61 27 50",
    "sg:postcode":"3690",
    "sg:province":"Limburg",
    "wof:name":"Contract & Project Furn.",
    "wof:placetype":"venue"
},
  "geometry": {"coordinates":[5.5394611359,50.9190979004],"type":"Point"}
}