{
  "type": "Feature",
  "properties": {
    "addr:full":"Rue De Li\u00c8ge 112 Oupeye Li\u00e8ge 4684",
    "addr:housenumber":"112",
    "addr:postcode":"4684",
    "addr:street":"Rue De Lie\u0300Ge",
    "iso:country":"BE",
    "sg:address":"Rue De Li\u00c8ge 112",
    "sg:city":"Oupeye",
    "sg:orig_category":"Sportclubs",
    "sg:phone":"+32 4 379 39 99",
    "sg:postcode":"4684",
    "sg:province":"Li\u00e8ge",
    "wof:name":"Tritons Haccourt Natation",
    "wof:placetype":"venue"
},
  "geometry": {"coordinates":[5.6688542366,50.7276039124],"type":"Point"}
}