{
  "type": "Feature",
  "properties": {
    "iso:country":"BE",
    "sg:address":"Heerbaan 56",
    "sg:city":"Harelbeke",
    "sg:orig_category":"Newspapers, magazines, periodicals - Distribution",
    "sg:phone":"+32 56 70 21 38",
    "sg:postcode":"8530",
    "sg:province":"West-Vlaanderen",
    "wof:name":"Ryssaert C",
    "wof:placetype":"venue"
},
  "geometry": {"coordinates":[3.3121950626,50.8470878601],"type":"Point"}
}