{
  "type": "Feature",
  "properties": {
    "iso:country":"BE",
    "sg:address":"Rue De Libramont 1d",
    "sg:city":"Houffalize",
    "sg:classifiers":[
        {
            "category":"Personal",
            "subcategory":"Beauty Salon",
            "type":"Services"
        }
    ],
    "sg:phone":"+32 61 28 91 53",
    "sg:postcode":"6660",
    "sg:province":"Luxembourg",
    "sg:tags":[
        "lady",
        "-",
        "hairdressing"
    ],
    "wof:name":"Deryck V",
    "wof:placetype":"venue"
},
  "geometry": {"coordinates":[5.7736558914,50.1179275513],"type":"Point"}
}