{
  "type": "Feature",
  "properties": {
    "iso:country":"BE",
    "sg:address":"Sint-annastraat 4",
    "sg:city":"Overijse",
    "sg:classifiers":[
        {
            "category":"Manufacturing",
            "subcategory":"Food",
            "type":"Manufacturing & Wholesale Goods"
        }
    ],
    "sg:phone":"+32 2 688 07 27",
    "sg:postcode":"3090",
    "sg:province":"Vlaams-Brabant",
    "sg:tags":[
        "industry",
        "-",
        "ingredient"
    ],
    "wof:name":"Biolin Sa",
    "wof:placetype":"venue"
},
  "geometry": {"coordinates":[4.5207471848,50.7779846191],"type":"Point"}
}