{
  "type": "Feature",
  "properties": {
    "iso:country":"BE",
    "sg:address":"Vlaamsesteenweg 162",
    "sg:city":"Brussel/bruxelles",
    "sg:orig_category":"Brood, gebak and snoepgoed",
    "sg:phone":"+32 2 218 15 55",
    "sg:postcode":"1000",
    "sg:province":"Bruxelles-Capitale",
    "wof:name":"Icram",
    "wof:placetype":"venue"
},
  "geometry": {"coordinates":[4.3434710503,50.8529930115],"type":"Point"}
}