{
  "type": "Feature",
  "properties": {
    "iso:country":"BE",
    "sg:address":"Rue Le Long Du Ch\u00c2teau 173",
    "sg:city":"Ohey",
    "sg:orig_category":"Woningbouw",
    "sg:phone":"+32 85 61 10 23",
    "sg:postcode":"5350",
    "sg:province":"Namur",
    "wof:name":"Thierry Loeckx",
    "wof:placetype":"venue"
},
  "geometry": {"coordinates":[5.1974029541,50.4140014648],"type":"Point"}
}