{
  "type": "Feature",
  "properties": {
    "iso:country":"BE",
    "sg:address":"Chauss\u00e9e De Gand 1222",
    "sg:city":"Bruxelles (berchem-sainte-agathe)",
    "sg:classifiers":[
        {
            "category":"Home & Garden",
            "subcategory":"Building Materials",
            "type":"Retail Goods"
        }
    ],
    "sg:phone":"+32 2 465 26 02",
    "sg:postcode":"1082",
    "sg:province":"Bruxelles-Capitale",
    "sg:tags":[
        "window"
    ],
    "wof:name":"Schoreels Sprl",
    "wof:placetype":"venue"
},
  "geometry": {"coordinates":[4.2955560684,50.8657341003],"type":"Point"}
}