{
  "type": "Feature",
  "properties": {
    "iso:country":"BE",
    "sg:address":"Caverstraat 11",
    "sg:city":"Jabbeke",
    "sg:classifiers":[
        {
            "category":"Travel",
            "subcategory":"Hotels & Motels",
            "type":"Entertainment"
        }
    ],
    "sg:phone":"+32 50 81 48 00",
    "sg:postcode":"8490",
    "sg:province":"West-Vlaanderen",
    "sg:tags":[
        "supply",
        "hotels",
        "catering"
    ],
    "wof:name":"Fourier J",
    "wof:placetype":"venue"
},
  "geometry": {"coordinates":[3.0913529396,51.1835441589],"type":"Point"}
}