{
  "type": "Feature",
  "properties": {
    "addr:full":"Blancefloerlaan 6 Antwerpen Antwerpen 2050",
    "addr:housenumber":"6",
    "addr:postcode":"2050",
    "addr:street":"Blancefloerlaan",
    "iso:country":"BE",
    "sg:address":"Blancefloerlaan 6",
    "sg:city":"Antwerpen",
    "sg:orig_category":"Verplichte sociale verzekeringen",
    "sg:phone":"+32 3 219 42 12",
    "sg:postcode":"2050",
    "sg:province":"Antwerpen",
    "wof:name":"Socialist. Mutualiteit",
    "wof:placetype":"venue"
},
  "geometry": {"coordinates":[4.3849658966,51.2207527161],"type":"Point"}
}