{
  "type": "Feature",
  "properties": {
    "addr:full":"Oudstrijdersplein 9 Ninove Oost-Vlaanderen 9400",
    "addr:housenumber":"9",
    "addr:postcode":"9400",
    "addr:street":"Oudstrijdersplein",
    "iso:country":"BE",
    "sg:address":"Oudstrijdersplein 9",
    "sg:city":"Ninove",
    "sg:orig_category":"Extrazone and HVH Speelgoed",
    "sg:phone":"+32 54 33 11 00",
    "sg:postcode":"9400",
    "sg:province":"Oost-Vlaanderen",
    "wof:name":"Extrazone Ninove",
    "wof:placetype":"venue"
},
  "geometry": {"coordinates":[4.0224270821,50.8350715637],"type":"Point"}
}