{
  "type": "Feature",
  "properties": {
    "iso:country":"BE",
    "sg:address":"Waterhoek 25",
    "sg:city":"Berlare",
    "sg:classifiers":[
        {
            "category":"Bars & Pubs",
            "type":"Food & Drink"
        }
    ],
    "sg:phone":"+32 52 42 56 76",
    "sg:postcode":"9290",
    "sg:province":"Oost-Vlaanderen",
    "sg:tags":[
        "tavern"
    ],
    "wof:name":"Waterhoek (de)",
    "wof:placetype":"venue"
},
  "geometry": {"coordinates":[4.0398650169,51.0315132141],"type":"Point"}
}