{
  "type": "Feature",
  "properties": {
    "iso:country":"BE",
    "sg:address":"Leuvenselaan 172",
    "sg:city":"Tienen",
    "sg:orig_category":"Agences d'exp\u00e9dition",
    "sg:phone":"+32 16 82 12 36",
    "sg:postcode":"3300",
    "sg:province":"Vlaams-Brabant",
    "wof:name":"Arli",
    "wof:placetype":"venue"
},
  "geometry": {"coordinates":[4.9303297997,50.8096694946],"type":"Point"}
}