{
  "type": "Feature",
  "properties": {
    "addr:full":"Visvijverstraat 55 Herselt Antwerpen 2230",
    "addr:housenumber":"55",
    "addr:postcode":"2230",
    "addr:street":"Visvijverstraat",
    "iso:country":"BE",
    "sg:address":"Visvijverstraat 55",
    "sg:city":"Herselt",
    "sg:orig_category":"Cr\u00e9meries",
    "sg:phone":"+32 16 69 72 93",
    "sg:postcode":"2230",
    "sg:province":"Antwerpen",
    "wof:name":"Stefaan Hermans",
    "wof:placetype":"venue"
},
  "geometry": {"coordinates":[4.8219380379,51.0420265198],"type":"Point"}
}