{
  "type": "Feature",
  "properties": {
    "iso:country":"BE",
    "sg:address":"Abeelestraat 26b",
    "sg:city":"Wielsbeke",
    "sg:classifiers":[
        {
            "category":"Real Estate",
            "subcategory":"Surveying",
            "type":"Services"
        }
    ],
    "sg:phone":"+32 56 66 52 80",
    "sg:postcode":"8710",
    "sg:province":"West-Vlaanderen",
    "sg:tags":[
        "surveyor",
        "land"
    ],
    "wof:name":"De Bie M",
    "wof:placetype":"venue"
},
  "geometry": {"coordinates":[3.3831191063,50.914352417],"type":"Point"}
}