{
  "type": "Feature",
  "properties": {
    "addr:full":"Rue Sauveni\u00e8re 4 Ouffet Li\u00e8ge 4590",
    "addr:housenumber":"4",
    "addr:postcode":"4590",
    "addr:street":"Rue Sauvenie\u0300Re",
    "iso:country":"BE",
    "sg:address":"Rue Sauveni\u00e8re 4",
    "sg:city":"Ouffet",
    "sg:classifiers":[
        {
            "category":"Shopping",
            "subcategory":"Gifts & Souvenirs",
            "type":"Retail Goods"
        }
    ],
    "sg:phone":"+32 86 36 61 59",
    "sg:postcode":"4590",
    "sg:province":"Li\u00e8ge",
    "sg:tags":[
        "-"
    ],
    "wof:name":"Lafontaine Aux Cadeaux",
    "wof:placetype":"venue"
},
  "geometry": {"coordinates":[5.4641780853,50.4383964539],"type":"Point"}
}