{
  "type": "Feature",
  "properties": {
    "addr:full":"Nieuwpoortsesteenweg 62 Oostende West-Vlaanderen 8400",
    "addr:housenumber":"62",
    "addr:postcode":"8400",
    "addr:street":"Nieuwpoortsesteenweg",
    "iso:country":"BE",
    "sg:address":"Nieuwpoortsesteenweg 62",
    "sg:city":"Oostende",
    "sg:classifiers":[
        {
            "category":"Manufacturing",
            "subcategory":"Textiles",
            "type":"Manufacturing & Wholesale Goods"
        }
    ],
    "sg:phone":"+32 59 51 16 15",
    "sg:postcode":"8400",
    "sg:province":"West-Vlaanderen",
    "sg:tags":[
        "retail",
        "-"
    ],
    "wof:name":"Family Shop",
    "wof:placetype":"venue"
},
  "geometry": {"coordinates":[2.906099081,51.2233886719],"type":"Point"}
}