{
  "type": "Feature",
  "properties": {
    "iso:country":"BE",
    "sg:address":"Halfdreef 35",
    "sg:city":"Beveren",
    "sg:orig_category":"Motos",
    "sg:phone":"+32 3 755 19 56",
    "sg:postcode":"9120",
    "sg:province":"Oost-Vlaanderen",
    "wof:name":"Bob Van Puyvelde",
    "wof:placetype":"venue"
},
  "geometry": {"coordinates":[4.2546682358,51.2228546143],"type":"Point"}
}