{
  "type": "Feature",
  "properties": {
    "addr:full":"Square Albert Premier 22 Anderlecht Bruxelles-Capitale 1070",
    "addr:housenumber":"22",
    "addr:postcode":"1070",
    "addr:street":"Square Albert Premier",
    "iso:country":"BE",
    "sg:address":"Square Albert Premier 22",
    "sg:city":"Anderlecht",
    "sg:orig_category":"Speelgoed, sport- and kampeermateriaal Gh",
    "sg:phone":"+32 2 520 47 95",
    "sg:postcode":"1070",
    "sg:province":"Bruxelles-Capitale",
    "wof:name":"Dynamic Classic Europe",
    "wof:placetype":"venue"
},
  "geometry": {"coordinates":[4.322909832,50.838973999],"type":"Point"}
}