{
  "type": "Feature",
  "properties": {
    "addr:full":"Rue Morel 22-24 Tournai Hainaut 7500",
    "addr:housenumber":"22-24",
    "addr:postcode":"7500",
    "addr:street":"Rue Morel",
    "iso:country":"BE",
    "sg:address":"Rue Morel 22-24",
    "sg:city":"Tournai",
    "sg:classifiers":[
        {
            "category":"Autos & Motor Vehicles",
            "subcategory":"Auto Supplies",
            "type":"Retail Goods"
        }
    ],
    "sg:phone":"+32 69 21 66 11",
    "sg:postcode":"7500",
    "sg:province":"Hainaut",
    "sg:tags":[
        "automobile",
        "-",
        "equipment",
        "air conditioning"
    ],
    "wof:name":"Telle Sa",
    "wof:placetype":"venue"
},
  "geometry": {"coordinates":[3.3983559608,50.6100654602],"type":"Point"}
}