{
  "type": "Feature",
  "properties": {
    "iso:country":"BE",
    "sg:address":"Hoevenzavellaan 43",
    "sg:city":"Genk (waterschei)",
    "sg:classifiers":[
        {
            "category":"Recreation",
            "subcategory":"Arcade",
            "type":"Entertainment"
        }
    ],
    "sg:phone":"+32 89 24 93 31",
    "sg:postcode":"3600",
    "sg:province":"Limburg",
    "sg:tags":[
        "machine",
        "amusement"
    ],
    "wof:name":"Fortuna",
    "wof:placetype":"venue"
},
  "geometry": {"coordinates":[5.5068411827,51.0004005432],"type":"Point"}
}