{
  "type": "Feature",
  "properties": {
    "iso:country":"BE",
    "sg:address":"En Mi-ville 6ba",
    "sg:city":"Verviers",
    "sg:orig_category":"Instituts de beaut\u00e9. Traitements param\u00e9dicaux",
    "sg:phone":"+32 87 34 08 70",
    "sg:postcode":"4800",
    "sg:province":"Li\u00e8ge",
    "wof:name":"Flemal",
    "wof:placetype":"venue"
},
  "geometry": {"coordinates":[5.8394670486,50.5813064575],"type":"Point"}
}