{
  "type": "Feature",
  "properties": {
    "addr:full":"Neustrasse 46 Eupen Li\u00e8ge 4700",
    "addr:housenumber":"46",
    "addr:postcode":"4700",
    "addr:street":"Neustrasse",
    "iso:country":"BE",
    "sg:address":"Neustrasse 46",
    "sg:city":"Eupen",
    "sg:classifiers":[
        {
            "category":"Health Services",
            "subcategory":"Dentist",
            "type":"Services"
        }
    ],
    "sg:phone":"+32 87 74 33 66",
    "sg:postcode":"4700",
    "sg:province":"Li\u00e8ge",
    "wof:name":"Munnix B",
    "wof:placetype":"venue"
},
  "geometry": {"coordinates":[6.0318508148,50.6264839172],"type":"Point"}
}