{
  "type": "Feature",
  "properties": {
    "iso:country":"BE",
    "sg:address":"Oude Bruglaan 57",
    "sg:city":"Lokeren",
    "sg:classifiers":[
        {
            "category":"Bars & Pubs",
            "type":"Food & Drink"
        }
    ],
    "sg:phone":"+32 9 348 92 86",
    "sg:postcode":"9160",
    "sg:province":"Oost-Vlaanderen",
    "wof:name":"Nieuw Slachthuis",
    "wof:placetype":"venue"
},
  "geometry": {"coordinates":[4.0032281876,51.1047325134],"type":"Point"}
}