{
  "type": "Feature",
  "properties": {
    "iso:country":"BE",
    "sg:address":"Kapellensteenweg 482",
    "sg:city":"Kalmthout",
    "sg:orig_category":"Benzinestations and brandstoffen",
    "sg:phone":"+32 3 666 98 57",
    "sg:postcode":"2920",
    "sg:province":"Antwerpen",
    "wof:name":"Esso",
    "wof:placetype":"venue"
},
  "geometry": {"coordinates":[4.4669117928,51.366153717],"type":"Point"}
}