{
  "type": "Feature",
  "properties": {
    "iso:country":"BE",
    "sg:address":"Rue Des Fermes 1",
    "sg:city":"H\u00c9ron",
    "sg:classifiers":[
        {
            "category":"Insurance",
            "subcategory":"Insurance Agent",
            "type":"Services"
        }
    ],
    "sg:phone":"+32 85 71 13 29",
    "sg:postcode":"4218",
    "sg:province":"Li\u00e8ge",
    "sg:tags":[
        "verzekeringsmakelaars",
        "expert"
    ],
    "wof:name":"J.m.c.",
    "wof:placetype":"venue"
},
  "geometry": {"coordinates":[5.1463999748,50.5327033997],"type":"Point"}
}