{
  "type": "Feature",
  "properties": {
    "iso:country":"BE",
    "sg:address":"Heiendestraat 26",
    "sg:city":"Lokeren",
    "sg:classifiers":[
        {
            "category":"Professional",
            "subcategory":"Art Services",
            "type":"Services"
        }
    ],
    "sg:phone":"+32 9 348 82 16",
    "sg:postcode":"9160",
    "sg:province":"Oost-Vlaanderen",
    "sg:tags":[
        "photography",
        "reporting",
        "-"
    ],
    "wof:name":"Fotoburo Liliane Van Den Broeck",
    "wof:placetype":"venue"
},
  "geometry": {"coordinates":[3.9573230743,51.0854797363],"type":"Point"}
}