{
  "type": "Feature",
  "properties": {
    "addr:full":"Grand-rue 108 Courcelles Hainaut 6183",
    "addr:housenumber":"108",
    "addr:postcode":"6183",
    "addr:street":"Grand-Rue",
    "iso:country":"BE",
    "sg:address":"Grand-rue 108",
    "sg:city":"Courcelles",
    "sg:classifiers":[
        {
            "category":"Insurance",
            "subcategory":"Life Insurance",
            "type":"Services"
        }
    ],
    "sg:phone":"+32 71 45 15 07",
    "sg:postcode":"6183",
    "sg:province":"Hainaut",
    "sg:tags":[
        "assurance"
    ],
    "wof:name":"Jacques Druine",
    "wof:placetype":"venue"
},
  "geometry": {"coordinates":[4.3350520134,50.4609794617],"type":"Point"}
}