{
  "type": "Feature",
  "properties": {
    "iso:country":"BE",
    "sg:address":"Welzijnstraat 106",
    "sg:city":"Zottegem",
    "sg:classifiers":[
        {
            "category":"Professional",
            "subcategory":"Computer Services",
            "type":"Services"
        }
    ],
    "sg:phone":"+32 9 361 32 24",
    "sg:postcode":"9620",
    "sg:province":"Oost-Vlaanderen",
    "sg:tags":[
        "-",
        "processing",
        "data",
        "software"
    ],
    "wof:name":"Itineris Bvba",
    "wof:placetype":"venue"
},
  "geometry": {"coordinates":[3.8179891109,50.8689002991],"type":"Point"}
}