{
  "type": "Feature",
  "properties": {
    "addr:full":"Broek 21 Oosterzele Oost-Vlaanderen 9860",
    "addr:housenumber":"21",
    "addr:postcode":"9860",
    "addr:street":"Broek;Oost-Vlaanderen",
    "iso:country":"BE",
    "sg:address":"Broek 21",
    "sg:city":"Oosterzele",
    "sg:orig_category":"Producteurs de l\u00e9gumes",
    "sg:phone":"+32 9 362 00 56",
    "sg:postcode":"9860",
    "sg:province":"Oost-Vlaanderen",
    "wof:name":"Freddy Van Wijnsberge",
    "wof:placetype":"venue"
},
  "geometry": {"coordinates":[3.8020119667,50.9158935547],"type":"Point"}
}