{
  "type": "Feature",
  "properties": {
    "iso:country":"BE",
    "sg:address":"Rue De Franquenies 72",
    "sg:city":"Ottignies-louvain-la-neuve",
    "sg:orig_category":"Technische studies and ingenieursactiviteiten",
    "sg:phone":"+32 10 41 22 40",
    "sg:postcode":"1340",
    "sg:province":"Brabant Wallon",
    "wof:name":"Gamaco Ing\u00c9nieurs Conseils",
    "wof:placetype":"venue"
},
  "geometry": {"coordinates":[4.5713272095,50.659160614],"type":"Point"}
}