{
  "type": "Feature",
  "properties": {
    "iso:country":"BE",
    "sg:address":"Maastrichterstraat 139",
    "sg:city":"Bilzen",
    "sg:classifiers":[
        {
            "category":"Health Services",
            "subcategory":"Nursing And Care Facility",
            "type":"Services"
        }
    ],
    "sg:phone":"+32 89 41 13 64",
    "sg:postcode":"3740",
    "sg:province":"Limburg",
    "sg:tags":[
        "home"
    ],
    "wof:name":"Partoens H",
    "wof:placetype":"venue"
},
  "geometry": {"coordinates":[5.5271902084,50.8648300171],"type":"Point"}
}