{
  "type": "Feature",
  "properties": {
    "iso:country":"BE",
    "sg:address":"Heikantstraat 203",
    "sg:city":"Schoten",
    "sg:orig_category":"Plaatsen van vloer- and muurbekleding",
    "sg:phone":"+32 3 658 17 67",
    "sg:postcode":"2900",
    "sg:province":"Antwerpen",
    "wof:name":"Vloeren Lissens",
    "wof:placetype":"venue"
},
  "geometry": {"coordinates":[4.51167202,51.2597541809],"type":"Point"}
}