{
  "type": "Feature",
  "properties": {
    "iso:country":"BE",
    "sg:address":"Rue C\u00c9sar Franck 45",
    "sg:city":"Li\u00c8ge",
    "sg:orig_category":"Artistes ind\u00e9pendants",
    "sg:phone":"+32 4 223 50 32",
    "sg:postcode":"4000",
    "sg:province":"Li\u00e8ge",
    "wof:name":"Pauline Claude",
    "wof:placetype":"venue"
},
  "geometry": {"coordinates":[5.5599889755,50.6386260986],"type":"Point"}
}