{
  "type": "Feature",
  "properties": {
    "iso:country":"BE",
    "sg:address":"Rue Albert 1er 46",
    "sg:city":"Peruwelz",
    "sg:orig_category":"Textiel",
    "sg:phone":"+32 69 77 02 23",
    "sg:postcode":"7600",
    "sg:province":"Hainaut",
    "wof:name":"Maison Daisy",
    "wof:placetype":"venue"
},
  "geometry": {"coordinates":[3.5908920765,50.508441925],"type":"Point"}
}