{
  "type": "Feature",
  "properties": {
    "addr:full":"Dorpsstraat 67 Gooik Vlaams-Brabant 1755",
    "addr:housenumber":"67",
    "addr:postcode":"1755",
    "addr:street":"Dorpsstraat",
    "iso:country":"BE",
    "sg:address":"Dorpsstraat 67",
    "sg:city":"Gooik",
    "sg:classifiers":[
        {
            "category":"Recreation",
            "type":"Entertainment"
        }
    ],
    "sg:phone":"+32 2 532 28 38",
    "sg:postcode":"1755",
    "sg:province":"Vlaams-Brabant",
    "sg:tags":[
        "diver",
        "amusement"
    ],
    "wof:name":"De Roskam",
    "wof:placetype":"venue"
},
  "geometry": {"coordinates":[4.1140780449,50.7956352234],"type":"Point"}
}