{
  "type": "Feature",
  "properties": {
    "iso:country":"BE",
    "sg:address":"Rue Servais-malaise 107",
    "sg:city":"Li\u00e8ge 1 (grivegn\u00e9e)",
    "sg:classifiers":[
        {
            "category":"Organizations",
            "subcategory":"Professional Association",
            "type":"Services"
        }
    ],
    "sg:phone":"+32 4 361 23 42",
    "sg:postcode":"4030",
    "sg:province":"Li\u00e8ge",
    "sg:tags":[
        "trade-union",
        "federation"
    ],
    "wof:name":"Parti Rattachiste France",
    "wof:placetype":"venue"
},
  "geometry": {"coordinates":[5.6250510216,50.6314506531],"type":"Point"}
}