{
  "type": "Feature",
  "properties": {
    "iso:country":"BE",
    "sg:address":"Rue Albert I 66",
    "sg:city":"Lobbes",
    "sg:classifiers":[
        {
            "category":"Real Estate",
            "subcategory":"Architect",
            "type":"Services"
        }
    ],
    "sg:phone":"+32 71 59 61 80",
    "sg:postcode":"6540",
    "sg:province":"Hainaut",
    "wof:name":"Sion G",
    "wof:placetype":"venue"
},
  "geometry": {"coordinates":[4.2652897835,50.3482704163],"type":"Point"}
}