{
  "type": "Feature",
  "properties": {
    "iso:country":"BE",
    "sg:address":"Rue De H\u00c9blon 1",
    "sg:city":"Hotton",
    "sg:classifiers":[
        {
            "category":"Travel",
            "subcategory":"Hotels & Motels",
            "type":"Entertainment"
        }
    ],
    "sg:phone":"+32 84 46 65 73",
    "sg:postcode":"6990",
    "sg:province":"Luxembourg",
    "sg:tags":[
        "restaurant"
    ],
    "wof:name":"Le Ch\u00c2teau D'h\u00c9blon",
    "wof:placetype":"venue"
},
  "geometry": {"coordinates":[5.466231823,50.2601051331],"type":"Point"}
}