{
  "type": "Feature",
  "properties": {
    "addr:full":"Martelarenstraat 19 Boutersem Vlaams-Brabant 3370",
    "addr:housenumber":"19",
    "addr:postcode":"3370",
    "addr:street":"Martelarenstraat",
    "iso:country":"BE",
    "sg:address":"Martelarenstraat 19",
    "sg:city":"Boutersem",
    "sg:classifiers":[
        {
            "category":"Building & Trades",
            "subcategory":"Electrical",
            "type":"Services"
        }
    ],
    "sg:phone":"+32 476 70 15 48",
    "sg:postcode":"3370",
    "sg:province":"Vlaams-Brabant",
    "sg:tags":[
        "electric",
        "-",
        "housewiring",
        "contractor"
    ],
    "wof:name":"Deweerdt T",
    "wof:placetype":"venue"
},
  "geometry": {"coordinates":[4.8324580193,50.8408813477],"type":"Point"}
}