{
  "type": "Feature",
  "properties": {
    "iso:country":"BE",
    "sg:address":"Place Anneessens 21-22",
    "sg:city":"Bruxelles",
    "sg:classifiers":[
        {
            "category":"Professional",
            "type":"Services"
        }
    ],
    "sg:phone":"+32 2 513 34 47",
    "sg:postcode":"1000",
    "sg:province":"Bruxelles-Capitale",
    "sg:tags":[
        "auction",
        "room"
    ],
    "wof:name":"Salle De Vente Des Huissiers De Justice De Bruxelles Sc",
    "wof:placetype":"venue"
},
  "geometry": {"coordinates":[4.3444519043,50.8440589905],"type":"Point"}
}