{
  "type": "Feature",
  "properties": {
    "iso:country":"BE",
    "sg:address":"Brabantdam 116",
    "sg:city":"Gent",
    "sg:classifiers":[
        {
            "category":"Cinema",
            "subcategory":"Movie Rental",
            "type":"Entertainment"
        }
    ],
    "sg:phone":"+32 9 233 02 77",
    "sg:postcode":"9000",
    "sg:province":"Oost-Vlaanderen",
    "sg:tags":[
        "de",
        "cassette",
        "location",
        "vid\u00e9o",
        "audio"
    ],
    "wof:name":"Videotheek Brotherhood",
    "wof:placetype":"venue"
},
  "geometry": {"coordinates":[3.7319819927,51.0495796204],"type":"Point"}
}