{
  "type": "Feature",
  "properties": {
    "addr:full":"Sint-gillislaan 71-3 Dendermonde Oost-Vlaanderen 9200",
    "addr:housenumber":"71-3",
    "addr:postcode":"9200",
    "addr:street":"Sint-Gillislaan;Oost-Vlaanderen",
    "iso:country":"BE",
    "sg:address":"Sint-gillislaan 71-3",
    "sg:city":"Dendermonde",
    "sg:classifiers":[
        {
            "category":"Building & Trades",
            "subcategory":"Pest Control",
            "type":"Services"
        }
    ],
    "sg:phone":"+32 52 21 38 39",
    "sg:postcode":"9200",
    "sg:province":"Oost-Vlaanderen",
    "sg:tags":[
        "painting",
        "contractor"
    ],
    "wof:name":"De Graef B",
    "wof:placetype":"venue"
},
  "geometry": {"coordinates":[4.1091680527,51.0208358765],"type":"Point"}
}