{
  "type": "Feature",
  "properties": {
    "addr:full":"Rue Winston Churchill 336 Courcelles Hainaut 6180",
    "addr:housenumber":"336",
    "addr:postcode":"6180",
    "addr:street":"Rue Winston Churchill",
    "iso:country":"BE",
    "sg:address":"Rue Winston Churchill 336",
    "sg:city":"Courcelles",
    "sg:classifiers":[
        {
            "category":"Professional",
            "subcategory":"Accounting & Tax Preparation",
            "type":"Services"
        }
    ],
    "sg:phone":"+32 71 45 70 91",
    "sg:postcode":"6180",
    "sg:province":"Hainaut",
    "sg:tags":[
        "accountant"
    ],
    "wof:name":"G. La Delfa",
    "wof:placetype":"venue"
},
  "geometry": {"coordinates":[4.396946907,50.4633026123],"type":"Point"}
}