{
  "type": "Feature",
  "properties": {
    "addr:full":"Hoek 20 Kasterlee Antwerpen 2460",
    "addr:housenumber":"20",
    "addr:postcode":"2460",
    "addr:street":"Hoek",
    "iso:country":"BE",
    "sg:address":"Hoek 20",
    "sg:city":"Kasterlee",
    "sg:classifiers":[
        {
            "category":"Personal",
            "subcategory":"Beauty Salon",
            "type":"Services"
        }
    ],
    "sg:phone":"+32 14 55 21 58",
    "sg:postcode":"2460",
    "sg:province":"Antwerpen",
    "sg:tags":[
        "de",
        "coiffure"
    ],
    "wof:name":"Haarstudio Xxl",
    "wof:placetype":"venue"
},
  "geometry": {"coordinates":[4.8879938126,51.2390022278],"type":"Point"}
}