{
  "type": "Feature",
  "properties": {
    "addr:full":"Ruiseledesteenweg 67ba Wingene West-Vlaanderen 8750",
    "addr:postcode":"8750",
    "addr:street":"Ruiseledesteenweg",
    "iso:country":"BE",
    "sg:address":"Ruiseledesteenweg 67ba",
    "sg:city":"Wingene",
    "sg:orig_category":"Installation de menuiserie en bois and plastique",
    "sg:phone":"+32 51 65 78 89",
    "sg:postcode":"8750",
    "sg:province":"West-Vlaanderen",
    "wof:name":"Filip Haeck",
    "wof:placetype":"venue"
},
  "geometry": {"coordinates":[3.3257200718,51.0568885803],"type":"Point"}
}