{
  "type": "Feature",
  "properties": {
    "iso:country":"BE",
    "sg:address":"Gentseweg 53",
    "sg:city":"Waregem (desselgem)",
    "sg:classifiers":[
        {
            "category":"Manufacturing",
            "subcategory":"Furniture",
            "type":"Manufacturing & Wholesale Goods"
        }
    ],
    "sg:phone":"+32 56 72 30 72",
    "sg:postcode":"8792",
    "sg:province":"West-Vlaanderen",
    "sg:tags":[
        "made",
        "-",
        "custom"
    ],
    "wof:name":"Deniere P",
    "wof:placetype":"venue"
},
  "geometry": {"coordinates":[3.3634810448,50.8820838928],"type":"Point"}
}