{
  "type": "Feature",
  "properties": {
    "addr:full":"Lindendreef 78 Ninove Oost-Vlaanderen 9400",
    "addr:housenumber":"78",
    "addr:postcode":"9400",
    "addr:street":"Lindendreef",
    "iso:country":"BE",
    "sg:address":"Lindendreef 78",
    "sg:city":"Ninove",
    "sg:orig_category":"Fabrication and montage de mobilier. Installation de menuiserie en bois and plastique",
    "sg:phone":"+32 54 33 28 02",
    "sg:postcode":"9400",
    "sg:province":"Oost-Vlaanderen",
    "wof:name":"De Dobbeleer Frans",
    "wof:placetype":"venue"
},
  "geometry": {"coordinates":[4.016119957,50.8511734009],"type":"Point"}
}