{
  "type": "Feature",
  "properties": {
    "addr:full":"Rue Bizeury 56 Aubange (rachecourt) Luxembourg 6792",
    "addr:housenumber":"56",
    "addr:postcode":"6792",
    "addr:street":"Rue Bizeury",
    "iso:country":"BE",
    "sg:address":"Rue Bizeury 56",
    "sg:city":"Aubange (rachecourt)",
    "sg:classifiers":[
        {
            "category":"Building & Trades",
            "subcategory":"Landscaping Services",
            "type":"Services"
        }
    ],
    "sg:phone":"+32 63 67 77 17",
    "sg:postcode":"6792",
    "sg:province":"Luxembourg",
    "sg:tags":[
        "-",
        "lopping",
        "work",
        "tree",
        "felling"
    ],
    "wof:name":"Aubertin P",
    "wof:placetype":"venue"
},
  "geometry": {"coordinates":[5.7191500664,49.5866394043],"type":"Point"}
}