{
  "type": "Feature",
  "properties": {
    "iso:country":"BE",
    "sg:address":"Rue De La Station 68a",
    "sg:city":"Perwez",
    "sg:classifiers":[
        {
            "category":"Insurance",
            "subcategory":"Insurance Agent",
            "type":"Services"
        }
    ],
    "sg:phone":"+32 81 65 62 68",
    "sg:postcode":"1360",
    "sg:province":"Brabant Wallon",
    "sg:tags":[
        "broker"
    ],
    "wof:name":"Agri-est Brabant Wallon Scrl Scrl",
    "wof:placetype":"venue"
},
  "geometry": {"coordinates":[4.8117909431,50.6253585815],"type":"Point"}
}