{
  "type": "Feature",
  "properties": {
    "iso:country":"BE",
    "sg:address":"Grand\u00b4place 51",
    "sg:city":"Nivelles",
    "sg:orig_category":"Avocats and conseillers juridiques",
    "sg:phone":"+32 67 21 68 56",
    "sg:postcode":"1400",
    "sg:province":"Brabant Wallon",
    "wof:name":"Benjamin Auquier",
    "wof:placetype":"venue"
},
  "geometry": {"coordinates":[4.3227558136,50.5971450806],"type":"Point"}
}