{
  "type": "Feature",
  "properties": {
    "addr:full":"Rue De La Coupe 7 Mons (grand) Hainaut 7000",
    "addr:housenumber":"7",
    "addr:postcode":"7000",
    "addr:street":"Rue De La Coupe",
    "iso:country":"BE",
    "sg:address":"Rue De La Coupe 7",
    "sg:city":"Mons (grand)",
    "sg:classifiers":[
        {
            "category":"Personal",
            "subcategory":"Beauty Salon",
            "type":"Services"
        }
    ],
    "sg:phone":"+32 65 33 72 73",
    "sg:postcode":"7000",
    "sg:province":"Hainaut",
    "sg:tags":[
        "de",
        "coiffure"
    ],
    "wof:name":"Herman",
    "wof:placetype":"venue"
},
  "geometry": {"coordinates":[3.9522719383,50.4536323547],"type":"Point"}
}