{
  "type": "Feature",
  "properties": {
    "iso:country":"BE",
    "sg:address":"Rue De L'eglise 28",
    "sg:city":"Sint-genesius-rode/rhode-saint-genese",
    "sg:orig_category":"Boucheries",
    "sg:phone":"+32 2 380 55 64",
    "sg:postcode":"1640",
    "sg:province":"Vlaams-Brabant",
    "wof:name":"Beenhouwerij De Gelas",
    "wof:placetype":"venue"
},
  "geometry": {"coordinates":[4.3479661942,50.7444000244],"type":"Point"}
}