{
  "type": "Feature",
  "properties": {
    "addr:full":"93 Avenue Des Rogations 1200 Bruxelles 93",
    "addr:housenumber":"93",
    "addr:postcode":"1200;93",
    "addr:street":"Avenue Des Rogations",
    "iso:country":"BE",
    "sg:address":"93",
    "sg:city":"Avenue Des Rogations 1200 Bruxelles",
    "sg:classifiers":[
        {
            "category":"Professional",
            "subcategory":"Advertising",
            "type":"Services"
        }
    ],
    "sg:phone":"+32 2 736 28 59",
    "sg:postcode":"93",
    "sg:tags":[
        "information",
        "medium",
        "communication"
    ],
    "wof:name":"Aa Veldeman Photo Brussels",
    "wof:placetype":"venue"
},
  "geometry": {"coordinates":[4.4033899307,50.842540741],"type":"Point"}
}