{
  "type": "Feature",
  "properties": {
    "addr:full":"Pater Vanweertplein 31 Riemst (vlijtingen) Limburg 3770",
    "addr:housenumber":"31",
    "addr:postcode":"3770",
    "addr:street":"Pater Vanweertplein",
    "iso:country":"BE",
    "sg:address":"Pater Vanweertplein 31",
    "sg:city":"Riemst (vlijtingen)",
    "sg:classifiers":[
        {
            "category":"Home & Garden",
            "subcategory":"Carpets & Floor Coverings",
            "type":"Retail Goods"
        }
    ],
    "sg:phone":"+32 12 45 70 51",
    "sg:postcode":"3770",
    "sg:province":"Limburg",
    "sg:tags":[
        "armoring"
    ],
    "wof:name":"Jorissen J",
    "wof:placetype":"venue"
},
  "geometry": {"coordinates":[5.5881748199,50.8339385986],"type":"Point"}
}