{
  "type": "Feature",
  "properties": {
    "iso:country":"BE",
    "sg:address":"Stijn Streuvelsstraat 18",
    "sg:city":"Izegem",
    "sg:orig_category":"Banken and kredietinstellingen",
    "sg:phone":"+32 51 30 82 51",
    "sg:postcode":"8870",
    "sg:province":"West-Vlaanderen",
    "wof:name":"Bacob",
    "wof:placetype":"venue"
},
  "geometry": {"coordinates":[3.2307329178,50.9233283997],"type":"Point"}
}