{
  "type": "Feature",
  "properties": {
    "iso:country":"BE",
    "sg:address":"Rode Kruislaan 14",
    "sg:city":"Malle (westmalle)",
    "sg:classifiers":[
        {
            "category":"Industrial Area",
            "type":"Public Place"
        }
    ],
    "sg:phone":"+32 3 311 79 62",
    "sg:postcode":"2390",
    "sg:province":"Antwerpen",
    "sg:tags":[
        "-",
        "lighting"
    ],
    "wof:name":"Mega Lichtechniek Nv",
    "wof:placetype":"venue"
},
  "geometry": {"coordinates":[4.6657857895,51.2793693542],"type":"Point"}
}