{
  "type": "Feature",
  "properties": {
    "iso:country":"BE",
    "sg:address":"Wolfgang D'urselstraat 7",
    "sg:city":"Bornem (hingene)",
    "sg:classifiers":[
        {
            "category":"Community Center",
            "subcategory":"Youth",
            "type":"Public Place"
        }
    ],
    "sg:phone":"+32 3 889 59 66",
    "sg:postcode":"2880",
    "sg:province":"Antwerpen",
    "sg:tags":[
        "club"
    ],
    "wof:name":"Laathof (het)",
    "wof:placetype":"venue"
},
  "geometry": {"coordinates":[4.2701888084,51.1033592224],"type":"Point"}
}