{
  "type": "Feature",
  "properties": {
    "addr:full":"Zavelstraat 8 Lennik Vlaams-Brabant 1750",
    "addr:housenumber":"8;1750",
    "addr:street":"Zavelstraat;Vlaams-Brabant",
    "iso:country":"BE",
    "sg:address":"Zavelstraat 8",
    "sg:city":"Lennik",
    "sg:orig_category":"Advocaten and juridische adviseurs",
    "sg:phone":"+32 2 532 47 88",
    "sg:postcode":"1750",
    "sg:province":"Vlaams-Brabant",
    "wof:name":"F. Van Ginderdeuren",
    "wof:placetype":"venue"
},
  "geometry": {"coordinates":[4.1522941589,50.8051376343],"type":"Point"}
}