{
  "type": "Feature",
  "properties": {
    "addr:full":"Rue De La Belle-vue 1 Arlon Luxembourg 6700",
    "addr:housenumber":"1",
    "addr:postcode":"6700",
    "addr:street":"Rue De La Belle-Vue",
    "iso:country":"BE",
    "sg:address":"Rue De La Belle-vue 1",
    "sg:city":"Arlon",
    "sg:orig_category":"Fabrication and montage de mobilier",
    "sg:phone":"+32 63 23 34 46",
    "sg:postcode":"6700",
    "sg:province":"Luxembourg",
    "wof:name":"Meubles Maxime",
    "wof:placetype":"venue"
},
  "geometry": {"coordinates":[5.8244600296,49.6971092224],"type":"Point"}
}