{
  "type": "Feature",
  "properties": {
    "addr:full":"Burgemeester Heymansplein 6 Beringen (beverlo) Limburg 3581",
    "addr:housenumber":"6",
    "addr:postcode":"3581",
    "addr:street":"Burgemeester Heymansplein",
    "iso:country":"BE",
    "sg:address":"Burgemeester Heymansplein 6",
    "sg:city":"Beringen (beverlo)",
    "sg:classifiers":[
        {
            "category":"Banks & Credit Unions",
            "subcategory":"Bank",
            "type":"Services"
        }
    ],
    "sg:phone":"+32 11 34 87 50",
    "sg:postcode":"3581",
    "sg:province":"Limburg",
    "sg:tags":[
        "savings-banks"
    ],
    "wof:name":"Argenta/marika Hansen",
    "wof:placetype":"venue"
},
  "geometry": {"coordinates":[5.2241549492,51.0880432129],"type":"Point"}
}