{
  "type": "Feature",
  "properties": {
    "addr:full":"Gouv. A. Galopinstraat 19 Genk Limburg 3600",
    "addr:housenumber":"19",
    "addr:postcode":"3600",
    "addr:street":"Galopinstraat",
    "iso:country":"BE",
    "sg:address":"Gouv. A. Galopinstraat 19",
    "sg:city":"Genk",
    "sg:orig_category":"Diverse organisaties and verenigingen",
    "sg:phone":"+32 89 38 40 19",
    "sg:postcode":"3600",
    "sg:province":"Limburg",
    "wof:name":"Jeugdhuis Pionier",
    "wof:placetype":"venue"
},
  "geometry": {"coordinates":[5.5058789253,51.0051498413],"type":"Point"}
}