{
  "type": "Feature",
  "properties": {
    "iso:country":"BE",
    "sg:address":"Roskotstraat 65",
    "sg:city":"Zele",
    "sg:orig_category":"Plaatsen van vloer- and muurbekleding Schilders",
    "sg:phone":"+32 52 44 84 60",
    "sg:postcode":"9240",
    "sg:province":"Oost-Vlaanderen",
    "wof:name":"Patrik Dauwe",
    "wof:placetype":"venue"
},
  "geometry": {"coordinates":[4.0373368263,51.0648078918],"type":"Point"}
}