{
  "type": "Feature",
  "properties": {
    "iso:country":"BE",
    "sg:address":"Chauss\u00e9e De Bruxelles 13",
    "sg:city":"Wavre",
    "sg:classifiers":[
        {
            "category":"Professional",
            "subcategory":"Lawyer & Legal Services",
            "type":"Services"
        }
    ],
    "sg:phone":"+32 10 22 31 25",
    "sg:postcode":"1300",
    "sg:province":"Brabant Wallon",
    "wof:name":"Massion-pochet B",
    "wof:placetype":"venue"
},
  "geometry": {"coordinates":[4.6125860214,50.7192764282],"type":"Point"}
}