{
  "type": "Feature",
  "properties": {
    "addr:full":"Rue Matteoti 7 Li\u00e8ge 1 (grivegn\u00e9e) Li\u00e8ge 4030",
    "addr:housenumber":"7;1",
    "addr:postcode":"4030",
    "addr:street":"Rue Matteoti",
    "iso:country":"BE",
    "sg:address":"Rue Matteoti 7",
    "sg:city":"Li\u00e8ge 1 (grivegn\u00e9e)",
    "sg:classifiers":[
        {
            "category":"Health Services",
            "subcategory":"Doctor",
            "type":"Services"
        }
    ],
    "sg:phone":"+32 4 371 94 14",
    "sg:postcode":"4030",
    "sg:province":"Li\u00e8ge",
    "sg:tags":[
        "medicinephysicians",
        "surgeon"
    ],
    "wof:name":"Devos Philippe",
    "wof:placetype":"venue"
},
  "geometry": {"coordinates":[5.6105508804,50.6198959351],"type":"Point"}
}