{
  "type": "Feature",
  "properties": {
    "iso:country":"BE",
    "sg:address":"Bresstraat 18",
    "sg:city":"Antwerpen",
    "sg:orig_category":"Pharmaciens",
    "sg:phone":"+32 3 248 54 39",
    "sg:postcode":"2018",
    "sg:province":"Antwerpen",
    "wof:name":"Pharma Thierie",
    "wof:placetype":"venue"
},
  "geometry": {"coordinates":[4.397960186,51.2064094543],"type":"Point"}
}