{
  "type": "Feature",
  "properties": {
    "addr:full":"Hansbekedorp 54 Nevele (hansbeke) Oost-Vlaanderen 9850",
    "addr:housenumber":"54",
    "addr:postcode":"9850",
    "addr:street":"Hansbekedorp",
    "iso:country":"BE",
    "sg:address":"Hansbekedorp 54",
    "sg:city":"Nevele (hansbeke)",
    "sg:classifiers":[
        {
            "category":"Retail",
            "subcategory":"Event Space",
            "type":"Services"
        }
    ],
    "sg:phone":"+32 9 371 52 07",
    "sg:postcode":"9850",
    "sg:province":"Oost-Vlaanderen",
    "sg:tags":[
        "rental",
        "-",
        "hall"
    ],
    "wof:name":"Zaal Schuttershof",
    "wof:placetype":"venue"
},
  "geometry": {"coordinates":[3.5355000496,51.0762252808],"type":"Point"}
}