{
  "type": "Feature",
  "properties": {
    "iso:country":"BE",
    "sg:address":"Kapellestraat 47",
    "sg:city":"Aartselaar",
    "sg:classifiers":[
        {
            "category":"Real Estate",
            "subcategory":"Surveying",
            "type":"Services"
        }
    ],
    "sg:phone":"+32 3 887 49 98",
    "sg:postcode":"2630",
    "sg:province":"Antwerpen",
    "sg:tags":[
        "surveyor",
        "land"
    ],
    "wof:name":"Vermeulen K & E",
    "wof:placetype":"venue"
},
  "geometry": {"coordinates":[4.389067173,51.1323623657],"type":"Point"}
}