{
  "type": "Feature",
  "properties": {
    "iso:country":"BE",
    "sg:address":"Rue De Namur 265",
    "sg:city":"Ch\u00e2telet",
    "sg:classifiers":[
        {
            "category":"Utilities",
            "subcategory":"Natural Gas",
            "type":"Services"
        }
    ],
    "sg:phone":"+32 9 386 16 08",
    "sg:postcode":"6200",
    "sg:province":"Hainaut",
    "sg:tags":[
        "cast",
        "stone",
        "working"
    ],
    "wof:name":"Natuursteenbedrijf Duym B.v.b.a.",
    "wof:placetype":"venue"
},
  "geometry": {"coordinates":[3.5014050007,50.9602737427],"type":"Point"}
}