{
  "type": "Feature",
  "properties": {
    "iso:country":"BE",
    "sg:address":"Woudstraat 2",
    "sg:city":"Genk",
    "sg:classifiers":[
        {
            "category":"Home & Garden",
            "subcategory":"Building Materials",
            "type":"Retail Goods"
        }
    ],
    "sg:phone":"+32 89 84 02 22",
    "sg:postcode":"3600",
    "sg:province":"Limburg",
    "sg:tags":[
        "steel",
        "metal",
        "made",
        "door",
        "gate"
    ],
    "wof:name":"H\u00f6rmann Belgium Nv",
    "wof:placetype":"venue"
},
  "geometry": {"coordinates":[5.4761052132,51.0021018982],"type":"Point"}
}