{
  "type": "Feature",
  "properties": {
    "iso:country":"BE",
    "sg:address":"Reetsesteenweg 214",
    "sg:city":"Aartselaar",
    "sg:orig_category":"Herstellingen and onderhoud van auto's Voertuigen",
    "sg:phone":"+32 3 844 22 77",
    "sg:postcode":"2630",
    "sg:province":"Antwerpen",
    "wof:name":"Garage Selleslaghs",
    "wof:placetype":"venue"
},
  "geometry": {"coordinates":[4.3940029144,51.1174812317],"type":"Point"}
}