{
  "type": "Feature",
  "properties": {
    "iso:country":"BE",
    "sg:address":"Lindestraat 32b1",
    "sg:city":"Herk-de-stad",
    "sg:classifiers":[
        {
            "category":"Sports & Exercise",
            "subcategory":"Sports Center",
            "type":"Entertainment"
        }
    ],
    "sg:phone":"+32 13 55 54 49",
    "sg:postcode":"3540",
    "sg:province":"Limburg",
    "sg:tags":[
        "de",
        "fitness"
    ],
    "wof:name":"Fyt-o-gym",
    "wof:placetype":"venue"
},
  "geometry": {"coordinates":[5.1659698486,50.9407691956],"type":"Point"}
}