{
  "type": "Feature",
  "properties": {
    "iso:country":"BE",
    "sg:address":"Nijverheidslaan 7",
    "sg:city":"Maldegem",
    "sg:orig_category":"Non-Classified Establishments",
    "sg:phone":"+32 50 71 70 20",
    "sg:postcode":"9990",
    "sg:province":"Oost-Vlaanderen",
    "wof:name":"De Hobbit Nv",
    "wof:placetype":"venue"
},
  "geometry": {"coordinates":[3.475249052,51.1949577332],"type":"Point"}
}