{
  "type": "Feature",
  "properties": {
    "iso:country":"BE",
    "sg:address":"Rue Haie De Barse 24",
    "sg:city":"Modave (vierset-barse)",
    "sg:classifiers":[
        {
            "category":"Wholesale",
            "subcategory":"Painting Supplies",
            "type":"Manufacturing & Wholesale Goods"
        }
    ],
    "sg:phone":"+32 85 41 21 94",
    "sg:postcode":"4577",
    "sg:province":"Li\u00e8ge",
    "sg:tags":[
        "industrial",
        "-"
    ],
    "wof:name":"Hemricourt",
    "wof:placetype":"venue"
},
  "geometry": {"coordinates":[5.2979922295,50.4443855286],"type":"Point"}
}