{
  "type": "Feature",
  "properties": {
    "iso:country":"BE",
    "sg:address":"J Janssensstraat 13",
    "sg:city":"Wuustwezel",
    "sg:orig_category":"Transports routiers de marchandises",
    "sg:phone":"+32 3 663 17 56",
    "sg:postcode":"2990",
    "sg:province":"Antwerpen",
    "wof:name":"Mertens Veetransport",
    "wof:placetype":"venue"
},
  "geometry": {"coordinates":[4.5388679504,51.3580703735],"type":"Point"}
}