{
  "type": "Feature",
  "properties": {
    "iso:country":"BE",
    "sg:address":"Rue Emile-vandervelde 37",
    "sg:city":"Jemeppe-sur-sambre",
    "sg:orig_category":"M\u00e9decins and sp\u00e9cialistes",
    "sg:phone":"+32 71 78 53 33",
    "sg:postcode":"5190",
    "sg:province":"Namur",
    "wof:name":"P. Fosseur",
    "wof:placetype":"venue"
},
  "geometry": {"coordinates":[4.6703448296,50.4645042419],"type":"Point"}
}