{
  "type": "Feature",
  "properties": {
    "addr:full":"Sint-pietersvliet 15 Antwerpen Antwerpen 2000",
    "addr:housenumber":"15",
    "addr:postcode":"2000",
    "addr:street":"Sint-Pietersvliet",
    "iso:country":"BE",
    "sg:address":"Sint-pietersvliet 15",
    "sg:city":"Antwerpen",
    "sg:classifiers":[
        {
            "category":"Banks & Credit Unions",
            "subcategory":"Bank",
            "type":"Services"
        }
    ],
    "sg:phone":"+32 3 220 03 33",
    "sg:postcode":"2000",
    "sg:province":"Antwerpen",
    "sg:tags":[
        "sea",
        "transport",
        "road"
    ],
    "wof:name":"Zebra Transport Nv",
    "wof:placetype":"venue"
},
  "geometry": {"coordinates":[4.4011278152,51.225856781],"type":"Point"}
}