{
  "type": "Feature",
  "properties": {
    "iso:country":"BE",
    "sg:address":"Hof Te Bollebeeklaan 7",
    "sg:city":"Asse (mollem)",
    "sg:classifiers":[
        {
            "category":"Building & Trades",
            "subcategory":"Construction",
            "type":"Services"
        }
    ],
    "sg:phone":"+32 2 452 47 86",
    "sg:postcode":"1730",
    "sg:province":"Vlaams-Brabant",
    "sg:tags":[
        "asphalt",
        "contractor"
    ],
    "wof:name":"De Ridder Gebr Bvba",
    "wof:placetype":"venue"
},
  "geometry": {"coordinates":[4.2295718193,50.9164276123],"type":"Point"}
}