{
  "type": "Feature",
  "properties": {
    "addr:full":"Eksterstraat 27 Vilvoorde Vlaams-Brabant 1800",
    "addr:housenumber":"27",
    "addr:postcode":"1800",
    "addr:street":"Eksterstraat",
    "iso:country":"BE",
    "sg:address":"Eksterstraat 27",
    "sg:city":"Vilvoorde",
    "sg:classifiers":[
        {
            "category":"Health Services",
            "subcategory":"Health Practitioner",
            "type":"Services"
        }
    ],
    "sg:phone":"+32 2 267 56 25",
    "sg:postcode":"1800",
    "sg:province":"Vlaams-Brabant",
    "sg:tags":[
        "physiotherapist"
    ],
    "wof:name":"De Kleermaeker Eric",
    "wof:placetype":"venue"
},
  "geometry": {"coordinates":[4.3739418983,50.9153327942],"type":"Point"}
}