{
  "type": "Feature",
  "properties": {
    "addr:full":"Chauss\u00c9e D\u00b4anvers 315 Brussel/bruxelles Bruxelles-Capitale 1000",
    "addr:housenumber":"315",
    "addr:postcode":"1000",
    "addr:street":"Chausse\u0301E D\u00b4Anvers;/",
    "iso:country":"BE",
    "sg:address":"Chauss\u00c9e D\u00b4anvers 315",
    "sg:city":"Brussel/bruxelles",
    "sg:orig_category":"D\u00e9taillants en pi\u00e8ces and accessoires de voitures",
    "sg:phone":"+32 2 784 37 11",
    "sg:postcode":"1000",
    "sg:province":"Bruxelles-Capitale",
    "wof:name":"N.r.j. Pneus",
    "wof:placetype":"venue"
},
  "geometry": {"coordinates":[4.3586168289,50.8661842346],"type":"Point"}
}