{
  "type": "Feature",
  "properties": {
    "addr:full":"Stienonlaan 36 Brussel-laken Bruxelles-Capitale 1020",
    "addr:housenumber":"36",
    "addr:postcode":"1020",
    "addr:street":"Stienonlaan",
    "iso:country":"BE",
    "sg:address":"Stienonlaan 36",
    "sg:city":"Brussel-laken",
    "sg:orig_category":"Catering and organisatie van feesten Voedingsspeciaalzaken",
    "sg:phone":"+32 2 478 39 18",
    "sg:postcode":"1020",
    "sg:province":"Bruxelles-Capitale",
    "wof:name":"Novelty Traiteur",
    "wof:placetype":"venue"
},
  "geometry": {"coordinates":[4.3320322037,50.8918304443],"type":"Point"}
}