{
  "type": "Feature",
  "properties": {
    "addr:full":"Brusselse Steenweg 80 Aalst Oost-Vlaanderen 9300",
    "addr:housenumber":"80",
    "addr:postcode":"9300",
    "addr:street":"Brusselse Steenweg",
    "iso:country":"BE",
    "sg:address":"Brusselse Steenweg 80",
    "sg:city":"Aalst",
    "sg:classifiers":[
        {
            "category":"Shopping",
            "subcategory":"Antiques",
            "type":"Retail Goods"
        }
    ],
    "sg:phone":"+32 53 70 48 06",
    "sg:postcode":"9300",
    "sg:province":"Oost-Vlaanderen",
    "wof:name":"Deconinck",
    "wof:placetype":"venue"
},
  "geometry": {"coordinates":[4.0604510307,50.9311523438],"type":"Point"}
}