{
  "type": "Feature",
  "properties": {
    "addr:full":"Achterheide 7 Puurs Antwerpen 2870",
    "addr:housenumber":"7",
    "addr:postcode":"2870",
    "addr:street":"Achterheide",
    "iso:country":"BE",
    "sg:address":"Achterheide 7",
    "sg:city":"Puurs",
    "sg:orig_category":"Groententeelt",
    "sg:phone":"+32 3 889 38 36",
    "sg:postcode":"2870",
    "sg:province":"Antwerpen",
    "wof:name":"Eugeen Van Nimmen",
    "wof:placetype":"venue"
},
  "geometry": {"coordinates":[4.2631821632,51.056186676],"type":"Point"}
}