{
  "type": "Feature",
  "properties": {
    "addr:full":"Hulsterstraat Noord 1 Stekene Oost-Vlaanderen 9190",
    "addr:housenumber":"1",
    "addr:postcode":"9190",
    "addr:street":"Hulsterstraat Noord",
    "iso:country":"BE",
    "sg:address":"Hulsterstraat Noord 1",
    "sg:city":"Stekene",
    "sg:classifiers":[
        {
            "category":"Professional",
            "type":"Services"
        }
    ],
    "sg:phone":"+32 3 860 71 30",
    "sg:postcode":"9190",
    "sg:province":"Oost-Vlaanderen",
    "sg:tags":[
        "transport"
    ],
    "wof:name":"Vegetra B.v.b.a.",
    "wof:placetype":"venue"
},
  "geometry": {"coordinates":[4.0574841499,51.2169151306],"type":"Point"}
}