{
  "type": "Feature",
  "properties": {
    "addr:full":"Corbiestraat 79 Mol Antwerpen 2400",
    "addr:housenumber":"79",
    "addr:postcode":"2400",
    "addr:street":"Corbiestraat",
    "iso:country":"BE",
    "sg:address":"Corbiestraat 79",
    "sg:city":"Mol",
    "sg:classifiers":[
        {
            "category":"Bars & Pubs",
            "type":"Food & Drink"
        }
    ],
    "sg:phone":"+32 14 31 37 77",
    "sg:postcode":"2400",
    "sg:province":"Antwerpen",
    "wof:name":"Boulevard Cafe",
    "wof:placetype":"venue"
},
  "geometry": {"coordinates":[5.1167612076,51.1883964539],"type":"Point"}
}