{
  "type": "Feature",
  "properties": {
    "iso:country":"BE",
    "sg:address":"Vaartstraat 4",
    "sg:city":"Zandhoven",
    "sg:orig_category":"Transports routiers de marchandises",
    "sg:phone":"+32 3 484 55 69",
    "sg:postcode":"2240",
    "sg:province":"Antwerpen",
    "wof:name":"Verbiest",
    "wof:placetype":"venue"
},
  "geometry": {"coordinates":[4.6431679726,51.197052002],"type":"Point"}
}