{
  "type": "Feature",
  "properties": {
    "addr:full":"Hoevelei 167 Aartselaar Antwerpen 2630",
    "addr:housenumber":"167",
    "addr:postcode":"2630",
    "addr:street":"Hoevelei",
    "iso:country":"BE",
    "sg:address":"Hoevelei 167",
    "sg:city":"Aartselaar",
    "sg:orig_category":"HERSTELLING ELEKTRISCHE HUISHOUDAPPARATEN",
    "sg:phone":"+32 3 887 06 24",
    "sg:postcode":"2630",
    "sg:province":"Antwerpen",
    "wof:name":"Edilbert Broothaers",
    "wof:placetype":"venue"
},
  "geometry": {"coordinates":[4.3799757957,51.1391372681],"type":"Point"}
}