{
  "type": "Feature",
  "properties": {
    "addr:full":"Ringlaan 67-22 Opwijk Vlaams-Brabant 1745",
    "addr:postcode":"67-22;1745",
    "addr:street":"Ringlaan",
    "iso:country":"BE",
    "sg:address":"Ringlaan 67-22",
    "sg:city":"Opwijk",
    "sg:classifiers":[
        {
            "category":"Building & Trades",
            "subcategory":"Electrical",
            "type":"Services"
        }
    ],
    "sg:phone":"+32 52 35 21 34",
    "sg:postcode":"1745",
    "sg:province":"Vlaams-Brabant",
    "sg:tags":[
        "electric",
        "-",
        "housewiring",
        "contractor"
    ],
    "wof:name":"Saerens Johan",
    "wof:placetype":"venue"
},
  "geometry": {"coordinates":[4.1909618378,50.9712219238],"type":"Point"}
}