{
  "type": "Feature",
  "properties": {
    "iso:country":"BE",
    "sg:address":"Oude Baan 27",
    "sg:city":"Zandhoven",
    "sg:classifiers":[
        {
            "category":"Shopping",
            "subcategory":"Jewelry",
            "type":"Retail Goods"
        }
    ],
    "sg:phone":"+32 3 484 35 56",
    "sg:postcode":"2240",
    "sg:province":"Antwerpen",
    "sg:tags":[
        "fab",
        "bijou"
    ],
    "wof:name":"Diazan",
    "wof:placetype":"venue"
},
  "geometry": {"coordinates":[4.6719489098,51.2233924866],"type":"Point"}
}