{
  "type": "Feature",
  "properties": {
    "iso:country":"BE",
    "sg:address":"Place Du Tombois 58",
    "sg:city":"Philippeville (franchimont)",
    "sg:classifiers":[
        {
            "category":"Building & Trades",
            "subcategory":"Plumbing",
            "type":"Services"
        }
    ],
    "sg:phone":"+32 71 66 83 68",
    "sg:postcode":"5600",
    "sg:province":"Namur",
    "sg:tags":[
        "tank"
    ],
    "wof:name":"Scaillet C",
    "wof:placetype":"venue"
},
  "geometry": {"coordinates":[4.6363639832,50.1900749207],"type":"Point"}
}