{
  "type": "Feature",
  "properties": {
    "addr:full":"Handzameplein 3 Kortemark (handzame) West-Vlaanderen 8610",
    "addr:housenumber":"3",
    "addr:postcode":"8610",
    "addr:street":"Handzameplein",
    "iso:country":"BE",
    "sg:address":"Handzameplein 3",
    "sg:city":"Kortemark (handzame)",
    "sg:classifiers":[
        {
            "category":"Banks & Credit Unions",
            "subcategory":"Investment Brokerage",
            "type":"Services"
        }
    ],
    "sg:phone":"+32 51 57 06 89",
    "sg:postcode":"8610",
    "sg:province":"West-Vlaanderen",
    "sg:tags":[
        "printing",
        "-"
    ],
    "wof:name":"Delanoye R",
    "wof:placetype":"venue"
},
  "geometry": {"coordinates":[3.0408840179,51.0284767151],"type":"Point"}
}