{
  "type": "Feature",
  "properties": {
    "iso:country":"BE",
    "sg:address":"Wakkenstraat 3",
    "sg:city":"Dentergem (markegem)",
    "sg:classifiers":[
        {
            "category":"Food & Beverages",
            "subcategory":"Meat & Fish",
            "type":"Retail Goods"
        }
    ],
    "sg:phone":"+32 51 63 32 13",
    "sg:postcode":"8720",
    "sg:province":"West-Vlaanderen",
    "sg:tags":[
        "-",
        "livestock"
    ],
    "wof:name":"Goetry I",
    "wof:placetype":"venue"
},
  "geometry": {"coordinates":[3.4021570683,50.9458580017],"type":"Point"}
}