{
  "type": "Feature",
  "properties": {
    "addr:full":"Grotehoeveweg 50 Boechout Antwerpen 2531",
    "addr:housenumber":"50",
    "addr:postcode":"2531",
    "addr:street":"Grotehoeveweg",
    "iso:country":"BE",
    "sg:address":"Grotehoeveweg 50",
    "sg:city":"Boechout",
    "sg:orig_category":"Groententeelt",
    "sg:phone":"+32 3 480 44 01",
    "sg:postcode":"2531",
    "sg:province":"Antwerpen",
    "wof:name":"Josikem",
    "wof:placetype":"venue"
},
  "geometry": {"coordinates":[4.5581440926,51.1691856384],"type":"Point"}
}