{
  "type": "Feature",
  "properties": {
    "addr:full":"Steenweg Op Papenbroek 62 Diest Vlaams-Brabant 3290",
    "addr:housenumber":"62",
    "addr:postcode":"3290",
    "addr:street":"Steenweg Op Papenbroek",
    "iso:country":"BE",
    "sg:address":"Steenweg Op Papenbroek 62",
    "sg:city":"Diest",
    "sg:classifiers":[
        {
            "category":"Retail",
            "subcategory":"Repair Shop",
            "type":"Services"
        }
    ],
    "sg:phone":"+32 13 31 40 55",
    "sg:postcode":"3290",
    "sg:province":"Vlaams-Brabant",
    "wof:name":"Leemans D",
    "wof:placetype":"venue"
},
  "geometry": {"coordinates":[5.0593700409,50.9759750366],"type":"Point"}
}