{
  "type": "Feature",
  "properties": {
    "addr:full":"Kapucinessenstraat 25 Antwerpen Antwerpen 2000",
    "addr:housenumber":"25",
    "addr:postcode":"2000",
    "addr:street":"Kapucinessenstraat",
    "iso:country":"BE",
    "sg:address":"Kapucinessenstraat 25",
    "sg:city":"Antwerpen",
    "sg:classifiers":[
        {
            "category":"Education",
            "subcategory":"University",
            "type":"Public Place"
        }
    ],
    "sg:phone":"+32 3 233 27 35",
    "sg:postcode":"2000",
    "sg:province":"Antwerpen",
    "sg:tags":[
        "adult"
    ],
    "wof:name":"Athena",
    "wof:placetype":"venue"
},
  "geometry": {"coordinates":[4.404209137,51.2111282349],"type":"Point"}
}