{
  "type": "Feature",
  "properties": {
    "addr:full":"Veldenstraat 5b Retie Antwerpen 2470",
    "addr:housenumber":"5b",
    "addr:postcode":"2470",
    "addr:street":"Veldenstraat",
    "iso:country":"BE",
    "sg:address":"Veldenstraat 5b",
    "sg:city":"Retie",
    "sg:classifiers":[
        {
            "category":"Home & Garden",
            "subcategory":"Building Materials",
            "type":"Retail Goods"
        }
    ],
    "sg:phone":"+32 14 37 05 52",
    "sg:postcode":"2470",
    "sg:province":"Antwerpen",
    "sg:tags":[
        "window"
    ],
    "wof:name":"Wens Ronny",
    "wof:placetype":"venue"
},
  "geometry": {"coordinates":[5.0771341324,51.2727279663],"type":"Point"}
}