{
  "type": "Feature",
  "properties": {
    "addr:full":"Eendrachtstraat 27b2 Elsene/ixelles Bruxelles-Capitale 1050",
    "addr:housenumber":"27b2",
    "addr:postcode":"1050",
    "addr:street":"Eendrachtstraat",
    "iso:country":"BE",
    "sg:address":"Eendrachtstraat 27b2",
    "sg:city":"Elsene/ixelles",
    "sg:orig_category":"Artiesten and kunstenaars",
    "sg:phone":"+32 2 502 33 35",
    "sg:postcode":"1050",
    "sg:province":"Bruxelles-Capitale",
    "wof:name":"Beatrice Flameng",
    "wof:placetype":"venue"
},
  "geometry": {"coordinates":[4.3610367775,50.8334465027],"type":"Point"}
}