{
  "type": "Feature",
  "properties": {
    "iso:country":"BE",
    "sg:address":"Oudstrijderslaan 7",
    "sg:city":"Ledegem",
    "sg:orig_category":"Rev\u00eatements pour sols and murs. Construction de maisons",
    "sg:phone":"+32 56 50 00 37",
    "sg:postcode":"8880",
    "sg:province":"West-Vlaanderen",
    "wof:name":"Daniel Douvere-seynaeve",
    "wof:placetype":"venue"
},
  "geometry": {"coordinates":[3.184032917,50.8741722107],"type":"Point"}
}