{
  "type": "Feature",
  "properties": {
    "iso:country":"BE",
    "sg:address":"Avenue Princesse Paola 10a",
    "sg:city":"Mons (saint-symphorien)",
    "sg:classifiers":[
        {
            "category":"Health Services",
            "subcategory":"Doctor",
            "type":"Services"
        }
    ],
    "sg:phone":"+32 65 33 93 67",
    "sg:postcode":"7030",
    "sg:province":"Hainaut",
    "sg:tags":[
        "medicinephysicians",
        "surgeon"
    ],
    "wof:name":"Leroy Philippe",
    "wof:placetype":"venue"
},
  "geometry": {"coordinates":[4.0108299255,50.4393882751],"type":"Point"}
}