{
  "type": "Feature",
  "properties": {
    "addr:full":"Kattestraat 38 Haaltert Oost-Vlaanderen 9450",
    "addr:housenumber":"38",
    "addr:postcode":"9450",
    "addr:street":"Kattestraat",
    "iso:country":"BE",
    "sg:address":"Kattestraat 38",
    "sg:city":"Haaltert",
    "sg:orig_category":"Rundveehouders",
    "sg:phone":"+32 53 83 20 40",
    "sg:postcode":"9450",
    "sg:province":"Oost-Vlaanderen",
    "wof:name":"Gilbert De Pauw",
    "wof:placetype":"venue"
},
  "geometry": {"coordinates":[3.9989869595,50.9041137695],"type":"Point"}
}