{
  "type": "Feature",
  "properties": {
    "addr:full":"Salinusstraat 41 Wevelgem West-Vlaanderen 8560",
    "addr:housenumber":"41",
    "addr:postcode":"8560",
    "addr:street":"Salinusstraat",
    "iso:country":"BE",
    "sg:address":"Salinusstraat 41",
    "sg:city":"Wevelgem",
    "sg:orig_category":"Maroquinerie and articles de voyage. Chaussures",
    "sg:phone":"+32 56 41 11 72",
    "sg:postcode":"8560",
    "sg:province":"West-Vlaanderen",
    "wof:name":"Veronica",
    "wof:placetype":"venue"
},
  "geometry": {"coordinates":[3.164493084,50.8395690918],"type":"Point"}
}