{
  "type": "Feature",
  "properties": {
    "addr:full":"Ch De Tubize 65 Braine-l'alleud Brabant Wallon 1420",
    "addr:housenumber":"65",
    "addr:postcode":"1420",
    "addr:street":"Ch De Tubize",
    "iso:country":"BE",
    "sg:address":"Ch De Tubize 65",
    "sg:city":"Braine-l'alleud",
    "sg:classifiers":[
        {
            "category":"Autos & Motor Vehicles",
            "subcategory":"Automobile Sales",
            "type":"Retail Goods"
        }
    ],
    "sg:phone":"+32 2 384 80 15",
    "sg:postcode":"1420",
    "sg:province":"Brabant Wallon",
    "sg:tags":[
        "equipment",
        "industrial",
        "transport"
    ],
    "wof:name":"Sabiex International Sa",
    "wof:placetype":"venue"
},
  "geometry": {"coordinates":[4.1567811966,50.7084236145],"type":"Point"}
}