{
  "type": "Feature",
  "properties": {
    "addr:full":"Kasteelstraat 70 Meulebeke West-Vlaanderen 8760",
    "addr:housenumber":"70",
    "addr:postcode":"8760",
    "addr:street":"Kasteelstraat",
    "iso:country":"BE",
    "sg:address":"Kasteelstraat 70",
    "sg:city":"Meulebeke",
    "sg:classifiers":[
        {
            "category":"Personal",
            "subcategory":"Beauty Salon",
            "type":"Services"
        }
    ],
    "sg:phone":"+32 51 48 87 06",
    "sg:postcode":"8760",
    "sg:province":"West-Vlaanderen",
    "sg:tags":[
        "de",
        "coiffure"
    ],
    "wof:name":"Coiffure Roland",
    "wof:placetype":"venue"
},
  "geometry": {"coordinates":[3.2819590569,50.9497108459],"type":"Point"}
}