{
  "type": "Feature",
  "properties": {
    "addr:full":"Hellestraat 91 Stekene Oost-Vlaanderen 9190",
    "addr:housenumber":"91",
    "addr:postcode":"9190",
    "addr:street":"Hellestraat",
    "iso:country":"BE",
    "sg:address":"Hellestraat 91",
    "sg:city":"Stekene",
    "sg:classifiers":[
        {
            "category":"Insurance",
            "subcategory":"Insurance Agent",
            "type":"Services"
        }
    ],
    "sg:phone":"+32 3 789 21 66",
    "sg:postcode":"9190",
    "sg:province":"Oost-Vlaanderen",
    "sg:tags":[
        "broker"
    ],
    "wof:name":"Hauspy M",
    "wof:placetype":"venue"
},
  "geometry": {"coordinates":[4.0402359962,51.2283096313],"type":"Point"}
}