{
  "type": "Feature",
  "properties": {
    "iso:country":"BE",
    "sg:address":"Frans Van Haelenstraat 19",
    "sg:city":"Bornem (hingene)",
    "sg:classifiers":[
        {
            "category":"Retail",
            "subcategory":"Animal Services",
            "type":"Services"
        }
    ],
    "sg:phone":"+32 3 899 65 76",
    "sg:postcode":"2880",
    "sg:province":"Antwerpen",
    "sg:tags":[
        "grooming",
        "-",
        "dog"
    ],
    "wof:name":"Farah Hondenkapsalon",
    "wof:placetype":"venue"
},
  "geometry": {"coordinates":[4.2672100067,51.1030464172],"type":"Point"}
}