{
  "type": "Feature",
  "properties": {
    "addr:full":"Groenstraat 124 Halle (buizingen) Vlaams-Brabant 1501",
    "addr:housenumber":"124",
    "addr:postcode":"1501",
    "addr:street":"Groenstraat",
    "iso:country":"BE",
    "sg:address":"Groenstraat 124",
    "sg:city":"Halle (buizingen)",
    "sg:classifiers":[
        {
            "category":"Real Estate",
            "subcategory":"Surveying",
            "type":"Services"
        }
    ],
    "sg:phone":"+32 2 356 87 08",
    "sg:postcode":"1501",
    "sg:province":"Vlaams-Brabant",
    "sg:tags":[
        "lettering",
        "letter"
    ],
    "wof:name":"Expo Service Lettering Bvba",
    "wof:placetype":"venue"
},
  "geometry": {"coordinates":[4.2635741234,50.7390823364],"type":"Point"}
}