{
  "type": "Feature",
  "properties": {
    "iso:country":"BE",
    "sg:address":"Heidebaan 101",
    "sg:city":"Sint-niklaas",
    "sg:classifiers":[
        {
            "category":"Travel",
            "subcategory":"Hotels & Motels",
            "type":"Entertainment"
        }
    ],
    "sg:phone":"+32 3 766 44 10",
    "sg:postcode":"9100",
    "sg:province":"Oost-Vlaanderen",
    "sg:tags":[
        "hotels",
        "business",
        "restaurant"
    ],
    "wof:name":"Bells Cafe Waasland Nv",
    "wof:placetype":"venue"
},
  "geometry": {"coordinates":[4.1897678375,51.175994873],"type":"Point"}
}