{
  "type": "Feature",
  "properties": {
    "addr:full":"Hazepad 29 Waregem West-Vlaanderen 8790",
    "addr:housenumber":"29",
    "addr:postcode":"8790",
    "addr:street":"Hazepad",
    "iso:country":"BE",
    "sg:address":"Hazepad 29",
    "sg:city":"Waregem",
    "sg:classifiers":[
        {
            "category":"Building & Trades",
            "subcategory":"Electrical",
            "type":"Services"
        }
    ],
    "sg:phone":"+32 56 61 12 94",
    "sg:postcode":"8790",
    "sg:province":"West-Vlaanderen",
    "sg:tags":[
        "electric",
        "-",
        "housewiring",
        "contractor"
    ],
    "wof:name":"Rogge M",
    "wof:placetype":"venue"
},
  "geometry": {"coordinates":[3.4458179474,50.8915405273],"type":"Point"}
}