{
  "type": "Feature",
  "properties": {
    "iso:country":"BE",
    "sg:address":"Place Cardinal Mercier 10",
    "sg:city":"Jette",
    "sg:orig_category":"Biblioth\u00e8ques and archives publiques",
    "sg:phone":"+32 2 426 05 05",
    "sg:postcode":"1090",
    "sg:province":"Bruxelles-Capitale",
    "wof:name":"Gemeent. Plaatsel. Bibl./biblioth\u00c8que Communale",
    "wof:placetype":"venue"
},
  "geometry": {"coordinates":[4.3272361755,50.8799476624],"type":"Point"}
}