{
  "type": "Feature",
  "properties": {
    "addr:full":"Rue De La Fontaine 60 Quaregnon Hainaut 7390",
    "addr:housenumber":"60",
    "addr:postcode":"7390",
    "addr:street":"Rue De La Fontaine",
    "iso:country":"BE",
    "sg:address":"Rue De La Fontaine 60",
    "sg:city":"Quaregnon",
    "sg:orig_category":"Installatie van houten of kunststof schrijnwerk Installatie van metalen schrijnwerk",
    "sg:phone":"+32 65 77 90 80",
    "sg:postcode":"7390",
    "sg:province":"Hainaut",
    "wof:name":"Angelo Unali",
    "wof:placetype":"venue"
},
  "geometry": {"coordinates":[3.8425118923,50.4455451965],"type":"Point"}
}