{
  "type": "Feature",
  "properties": {
    "iso:country":"BE",
    "sg:address":"Grote Baan 40",
    "sg:city":"Hulshout",
    "sg:orig_category":"Caf\u00e9s Sportterreinen and installaties behalve sportcentra",
    "sg:phone":"+32 15 22 25 35",
    "sg:postcode":"2235",
    "sg:province":"Antwerpen",
    "wof:name":"Tenniscentrum De Raket",
    "wof:placetype":"venue"
},
  "geometry": {"coordinates":[4.7829909325,51.0776939392],"type":"Point"}
}