{
  "type": "Feature",
  "properties": {
    "addr:full":"Marktstraat 10 Izegem West-Vlaanderen 8870",
    "addr:housenumber":"10",
    "addr:postcode":"8870",
    "addr:street":"Marktstraat",
    "iso:country":"BE",
    "sg:address":"Marktstraat 10",
    "sg:city":"Izegem",
    "sg:orig_category":"Banken and kredietinstellingen",
    "sg:phone":"+32 51 30 78 24",
    "sg:postcode":"8870",
    "sg:province":"West-Vlaanderen",
    "wof:name":"Citibank",
    "wof:placetype":"venue"
},
  "geometry": {"coordinates":[3.215157032,50.9180450439],"type":"Point"}
}