{
  "type": "Feature",
  "properties": {
    "iso:country":"BE",
    "sg:address":"Burchtlaan 62 Box 1",
    "sg:city":"Merchtem",
    "sg:classifiers":[
        {
            "category":"Health Services",
            "subcategory":"Dentist",
            "type":"Services"
        }
    ],
    "sg:phone":"+32 52 37 07 41",
    "sg:postcode":"1785",
    "sg:province":"Vlaams-Brabant",
    "wof:name":"De Mars Greet",
    "wof:placetype":"venue"
},
  "geometry": {"coordinates":[4.2338228226,50.960647583],"type":"Point"}
}