{
  "type": "Feature",
  "properties": {
    "iso:country":"BE",
    "sg:address":"Rue Du Coll\u00e8ge 55",
    "sg:city":"Bruxelles (ixelles)",
    "sg:classifiers":[
        {
            "category":"Health Services",
            "subcategory":"Hospital",
            "type":"Services"
        }
    ],
    "sg:phone":"+32 2 645 00 70",
    "sg:postcode":"1050",
    "sg:province":"Bruxelles-Capitale",
    "wof:name":"Sanatia Asbl/vzw Clinique/kliniek Centre De Jour le Canevas",
    "wof:placetype":"venue"
},
  "geometry": {"coordinates":[4.3702330589,50.8316612244],"type":"Point"}
}