{
  "type": "Feature",
  "properties": {
    "addr:full":"Grand'place 16 Sint-truiden Limburg 3800",
    "addr:housenumber":"16",
    "addr:postcode":"3800",
    "addr:street":"Grand'Place",
    "iso:country":"BE",
    "sg:address":"Grand'place 16",
    "sg:city":"Sint-truiden",
    "sg:classifiers":[
        {
            "category":"Restaurant",
            "type":"Food & Drink"
        }
    ],
    "sg:phone":"+32 19 51 38 54",
    "sg:postcode":"3800",
    "sg:province":"Limburg",
    "wof:name":"La Gondola",
    "wof:placetype":"venue"
},
  "geometry": {"coordinates":[5.2097201347,50.8130111694],"type":"Point"}
}