{
  "type": "Feature",
  "properties": {
    "iso:country":"BE",
    "sg:address":"Dorpsweg 13",
    "sg:city":"Malle (oostmalle)",
    "sg:classifiers":[
        {
            "category":"Cemetery",
            "type":"Public Place"
        }
    ],
    "sg:phone":"+32 3 312 22 09",
    "sg:postcode":"2390",
    "sg:province":"Antwerpen",
    "sg:tags":[
        "crematory"
    ],
    "wof:name":"Ixia",
    "wof:placetype":"venue"
},
  "geometry": {"coordinates":[4.7326130867,51.3020629883],"type":"Point"}
}