{
  "type": "Feature",
  "properties": {
    "addr:full":"Werkstraat 67 Gent Oost-Vlaanderen 9000",
    "addr:housenumber":"67",
    "addr:postcode":"9000",
    "addr:street":"Werkstraat;Oost-Vlaanderen",
    "iso:country":"BE",
    "sg:address":"Werkstraat 67",
    "sg:city":"Gent",
    "sg:classifiers":[
        {
            "category":"Building & Trades",
            "subcategory":"Cleaning & Sanitation",
            "type":"Services"
        }
    ],
    "sg:phone":"+32 9 227 96 09",
    "sg:postcode":"9000",
    "sg:province":"Oost-Vlaanderen",
    "sg:tags":[
        "sweep",
        "chimney"
    ],
    "wof:name":"Boma",
    "wof:placetype":"venue"
},
  "geometry": {"coordinates":[3.688231945,51.0695571899],"type":"Point"}
}