{
  "type": "Feature",
  "properties": {
    "iso:country":"BE",
    "sg:address":"Jubelfeestlaan 200",
    "sg:city":"Sint-jans-molenbeek",
    "sg:orig_category":"Informaticaconsulenten",
    "sg:phone":"+32 2 420 06 76",
    "sg:postcode":"1080",
    "sg:province":"Bruxelles-Capitale",
    "wof:name":"Vertex",
    "wof:placetype":"venue"
},
  "geometry": {"coordinates":[4.3418421745,50.8690872192],"type":"Point"}
}