{
  "type": "Feature",
  "properties": {
    "iso:country":"BE",
    "sg:address":"Boomse Steenweg 31",
    "sg:city":"Schelle",
    "sg:classifiers":[
        {
            "category":"Government",
            "subcategory":"Office",
            "type":"Public Place"
        }
    ],
    "sg:phone":"+32 3 888 03 69",
    "sg:postcode":"2627",
    "sg:province":"Antwerpen",
    "sg:tags":[
        "chamber",
        "industry",
        "commerce"
    ],
    "wof:name":"Be.ne.lux. Centrum",
    "wof:placetype":"venue"
},
  "geometry": {"coordinates":[4.3734021187,51.1188201904],"type":"Point"}
}