{
  "type": "Feature",
  "properties": {
    "iso:country":"BE",
    "sg:address":"Avenue Rogier 14",
    "sg:city":"Li\u00e8ge 1",
    "sg:classifiers":[
        {
            "category":"Health Services",
            "subcategory":"Dentist",
            "type":"Services"
        }
    ],
    "sg:phone":"+32 4 221 28 68",
    "sg:postcode":"4000",
    "sg:province":"Li\u00e8ge",
    "wof:name":"Defays Jean",
    "wof:placetype":"venue"
},
  "geometry": {"coordinates":[5.5698871613,50.6337661743],"type":"Point"}
}