{
  "type": "Feature",
  "properties": {
    "addr:full":"Rue Maurice G\u00e9menne 83 Profondeville Namur 5170",
    "addr:housenumber":"83",
    "addr:postcode":"5170",
    "addr:street":"Rue Maurice Ge\u0301Menne",
    "iso:country":"BE",
    "sg:address":"Rue Maurice G\u00e9menne 83",
    "sg:city":"Profondeville",
    "sg:classifiers":[
        {
            "category":"Health Services",
            "subcategory":"Nursing And Care Facility",
            "type":"Services"
        }
    ],
    "sg:phone":"+32 81 41 24 34",
    "sg:postcode":"5170",
    "sg:province":"Namur",
    "sg:tags":[
        "humidifiers",
        "dehydrating",
        "apparatus"
    ],
    "wof:name":"Alto Kew Technoly-sabva",
    "wof:placetype":"venue"
},
  "geometry": {"coordinates":[4.8566222191,50.3845024109],"type":"Point"}
}