{
  "type": "Feature",
  "properties": {
    "iso:country":"BE",
    "sg:address":"Marktstraat 28",
    "sg:city":"Izegem",
    "sg:orig_category":"Supermarkten",
    "sg:phone":"+32 51 30 08 38",
    "sg:postcode":"8870",
    "sg:province":"West-Vlaanderen",
    "wof:name":"Huis Miblo",
    "wof:placetype":"venue"
},
  "geometry": {"coordinates":[3.2153880596,50.9185333252],"type":"Point"}
}