{
  "type": "Feature",
  "properties": {
    "iso:country":"BE",
    "sg:address":"Kerkstraat 137",
    "sg:city":"Buggenhout",
    "sg:orig_category":"Schoonheidssalons",
    "sg:phone":"+32 52 33 67 55",
    "sg:postcode":"9255",
    "sg:province":"Oost-Vlaanderen",
    "wof:name":"Lady",
    "wof:placetype":"venue"
},
  "geometry": {"coordinates":[4.2018399239,51.0136108398],"type":"Point"}
}