{
  "type": "Feature",
  "properties": {
    "addr:full":"Sint-bernadettestraat 60 Gent (sint-amandsberg) Oost-Vlaanderen 9040",
    "addr:housenumber":"60",
    "addr:postcode":"9040",
    "addr:street":"Sint-Bernadettestraat",
    "iso:country":"BE",
    "sg:address":"Sint-bernadettestraat 60",
    "sg:city":"Gent (sint-amandsberg)",
    "sg:classifiers":[
        {
            "category":"Social Services",
            "subcategory":"Child Care",
            "type":"Services"
        }
    ],
    "sg:phone":"+32 9 251 75 47",
    "sg:postcode":"9040",
    "sg:province":"Oost-Vlaanderen",
    "sg:tags":[
        "baby",
        "nursery",
        "day",
        "sitting"
    ],
    "wof:name":"Klim-op",
    "wof:placetype":"venue"
},
  "geometry": {"coordinates":[3.751388073,51.0698623657],"type":"Point"}
}