{
  "type": "Feature",
  "properties": {
    "addr:full":"Kapucinessenstraat 48 Antwerpen Antwerpen 2000",
    "addr:housenumber":"48",
    "addr:postcode":"2000",
    "addr:street":"Kapucinessenstraat",
    "iso:country":"BE",
    "sg:address":"Kapucinessenstraat 48",
    "sg:city":"Antwerpen",
    "sg:orig_category":"Deurwaarders",
    "sg:phone":"+32 3 226 51 13",
    "sg:postcode":"2000",
    "sg:province":"Antwerpen",
    "wof:name":"P. Greeve",
    "wof:placetype":"venue"
},
  "geometry": {"coordinates":[4.4041318893,51.210193634],"type":"Point"}
}