{
  "type": "Feature",
  "properties": {
    "iso:country":"BE",
    "sg:address":"August Michielsstraat 19-21",
    "sg:city":"Antwerpen",
    "sg:classifiers":[
        {
            "category":"Building & Trades",
            "subcategory":"Pest Control",
            "type":"Services"
        }
    ],
    "sg:phone":"+32 3 221 86 11",
    "sg:postcode":"2000",
    "sg:province":"Antwerpen",
    "sg:tags":[
        "quality"
    ],
    "wof:name":"Aib Vincotte V.z.w.",
    "wof:placetype":"venue"
},
  "geometry": {"coordinates":[4.4117331505,51.2317237854],"type":"Point"}
}