{
  "type": "Feature",
  "properties": {
    "addr:full":"Van Naemenstraat 29 Sint-niklaas Oost-Vlaanderen 9100",
    "addr:housenumber":"29",
    "addr:postcode":"9100",
    "addr:street":"Naemenstraat",
    "iso:country":"BE",
    "sg:address":"Van Naemenstraat 29",
    "sg:city":"Sint-niklaas",
    "sg:classifiers":[
        {
            "category":"Professional",
            "subcategory":"Art Services",
            "type":"Services"
        }
    ],
    "sg:phone":"+32 3 766 09 04",
    "sg:postcode":"9100",
    "sg:province":"Oost-Vlaanderen",
    "sg:tags":[
        "graphic",
        "designer"
    ],
    "wof:name":"Puntgaaf",
    "wof:placetype":"venue"
},
  "geometry": {"coordinates":[4.1511697769,51.1697654724],"type":"Point"}
}