{
  "type": "Feature",
  "properties": {
    "addr:full":"Gentse Steenweg 51 Lierde Oost-Vlaanderen 9571",
    "addr:housenumber":"51",
    "addr:postcode":"9571",
    "addr:street":"Gentse Steenweg",
    "iso:country":"BE",
    "sg:address":"Gentse Steenweg 51",
    "sg:city":"Lierde",
    "sg:orig_category":"Ruimtes voor conferenties, recepties and feesten",
    "sg:phone":"+32 54 50 10 00",
    "sg:postcode":"9571",
    "sg:province":"Oost-Vlaanderen",
    "wof:name":"De Vlaschaard",
    "wof:placetype":"venue"
},
  "geometry": {"coordinates":[3.8817999363,50.8140983582],"type":"Point"}
}