{
  "type": "Feature",
  "properties": {
    "addr:full":"Hamdreef 27 Steenokkerzeel Vlaams-Brabant 1820",
    "addr:housenumber":"27",
    "addr:postcode":"1820",
    "addr:street":"Hamdreef",
    "iso:country":"BE",
    "sg:address":"Hamdreef 27",
    "sg:city":"Steenokkerzeel",
    "sg:classifiers":[
        {
            "category":"Health Services",
            "subcategory":"Health Practitioner",
            "type":"Services"
        }
    ],
    "sg:phone":"+32 2 759 65 12",
    "sg:postcode":"1820",
    "sg:province":"Vlaams-Brabant",
    "sg:tags":[
        "physiotherapist"
    ],
    "wof:name":"Acke Francis",
    "wof:placetype":"venue"
},
  "geometry": {"coordinates":[4.5134091377,50.911907196],"type":"Point"}
}