{
  "type": "Feature",
  "properties": {
    "addr:full":"Dorpsstraat 109 Heist-op-den-berg (booischot) Antwerpen 2221",
    "addr:housenumber":"109",
    "addr:postcode":"2221",
    "addr:street":"Dorpsstraat",
    "iso:country":"BE",
    "sg:address":"Dorpsstraat 109",
    "sg:city":"Heist-op-den-berg (booischot)",
    "sg:classifiers":[
        {
            "category":"Professional",
            "subcategory":"Testing Lab",
            "type":"Services"
        }
    ],
    "sg:phone":"+32 15 22 21 69",
    "sg:postcode":"2221",
    "sg:province":"Antwerpen",
    "sg:tags":[
        "chemist"
    ],
    "wof:name":"Peeters",
    "wof:placetype":"venue"
},
  "geometry": {"coordinates":[4.7739758492,51.0512428284],"type":"Point"}
}