{
  "type": "Feature",
  "properties": {
    "addr:full":"Dorpsstraat 1 Bus 1 Achel Limburg 3590",
    "addr:housenumber":"1 bus 1",
    "addr:postcode":"3590",
    "addr:street":"Dorpsstraat",
    "iso:country":"BE",
    "sg:address":"Dorpsstraat 1 Bus 1",
    "sg:city":"Achel",
    "sg:classifiers":[
        {
            "category":"Banks & Credit Unions",
            "subcategory":"Bank",
            "type":"Services"
        }
    ],
    "sg:phone":"+32 11 64 05 36",
    "sg:postcode":"3590",
    "sg:province":"Limburg",
    "wof:name":"Aslk-cger Bank",
    "wof:placetype":"venue"
},
  "geometry": {"coordinates":[5.4200778008,50.9089431763],"type":"Point"}
}