{
  "type": "Feature",
  "properties": {
    "iso:country":"BE",
    "sg:address":"Avenue Des Platanes 18",
    "sg:city":"Li\u00e8ge",
    "sg:classifiers":[
        {
            "category":"Banks & Credit Unions",
            "subcategory":"Investment Brokerage",
            "type":"Services"
        }
    ],
    "sg:phone":"+32 4 221 42 42",
    "sg:postcode":"4000",
    "sg:province":"Li\u00e8ge",
    "sg:tags":[
        "big",
        "bag"
    ],
    "wof:name":"Ecosystems S.a.",
    "wof:placetype":"venue"
},
  "geometry": {"coordinates":[5.5609951019,50.6172142029],"type":"Point"}
}