{
  "type": "Feature",
  "properties": {
    "addr:full":"A. Biebuyckstraat 5 Waregem West-Vlaanderen 8793",
    "addr:housenumber":"5",
    "addr:postcode":"8793",
    "addr:street":"A. Biebuyckstraat",
    "iso:country":"BE",
    "sg:address":"A. Biebuyckstraat 5",
    "sg:city":"Waregem",
    "sg:orig_category":"Opticiens",
    "sg:phone":"+32 56 60 24 15",
    "sg:postcode":"8793",
    "sg:province":"West-Vlaanderen",
    "wof:name":"Delarue",
    "wof:placetype":"venue"
},
  "geometry": {"coordinates":[3.4043390751,50.9063491821],"type":"Point"}
}