{
  "type": "Feature",
  "properties": {
    "iso:country":"BE",
    "sg:address":"Av. Eug\u00c8ne Mullendorff 37b39",
    "sg:city":"Verviers",
    "sg:classifiers":[
        {
            "category":"Manufacturing",
            "subcategory":"Textiles",
            "type":"Manufacturing & Wholesale Goods"
        }
    ],
    "sg:phone":"+32 87 33 31 20",
    "sg:postcode":"4800",
    "sg:province":"Li\u00e8ge",
    "wof:name":"El\u00c9gance Tissus",
    "wof:placetype":"venue"
},
  "geometry": {"coordinates":[5.8683838844,50.5895042419],"type":"Point"}
}