{
  "type": "Feature",
  "properties": {
    "addr:full":"Avenue De La Tenderie 62a Bruxelles (watermael-boitsfort) Bruxelles-Capitale 1170",
    "addr:housenumber":"62a",
    "addr:postcode":"1170",
    "addr:street":"Avenue De La Tenderie",
    "iso:country":"BE",
    "sg:address":"Avenue De La Tenderie 62a",
    "sg:city":"Bruxelles (watermael-boitsfort)",
    "sg:classifiers":[
        {
            "category":"Health Services",
            "subcategory":"Health Practitioner",
            "type":"Services"
        }
    ],
    "sg:phone":"+32 2 673 48 41",
    "sg:postcode":"1170",
    "sg:province":"Bruxelles-Capitale",
    "sg:tags":[
        "physiotherapist"
    ],
    "wof:name":"Mormont M",
    "wof:placetype":"venue"
},
  "geometry": {"coordinates":[4.4079918861,50.8002281189],"type":"Point"}
}