{
  "type": "Feature",
  "properties": {
    "addr:full":"Rogierlaan 18 Oostende West-Vlaanderen 8400",
    "addr:housenumber":"18",
    "addr:postcode":"8400",
    "addr:street":"Rogierlaan",
    "iso:country":"BE",
    "sg:address":"Rogierlaan 18",
    "sg:city":"Oostende",
    "sg:orig_category":"Enseignement maternel and primaire",
    "sg:phone":"+32 59 70 16 92",
    "sg:postcode":"8400",
    "sg:province":"West-Vlaanderen",
    "wof:name":"Lagere School",
    "wof:placetype":"venue"
},
  "geometry": {"coordinates":[2.9114160538,51.2272644043],"type":"Point"}
}