{
  "type": "Feature",
  "properties": {
    "addr:full":"Avenue Eug\u00c8ne Mascaux 6 Charleroi Hainaut 6001",
    "addr:housenumber":"6",
    "addr:postcode":"6001",
    "addr:street":"Avenue Euge\u0300Ne Mascaux;Hainaut",
    "iso:country":"BE",
    "sg:address":"Avenue Eug\u00c8ne Mascaux 6",
    "sg:city":"Charleroi",
    "sg:orig_category":"Kansspelen",
    "sg:phone":"+32 71 36 85 15",
    "sg:postcode":"6001",
    "sg:province":"Hainaut",
    "wof:name":"Ladbrokes",
    "wof:placetype":"venue"
},
  "geometry": {"coordinates":[4.4474577904,50.3999938965],"type":"Point"}
}