{
  "type": "Feature",
  "properties": {
    "iso:country":"BE",
    "sg:address":"Frans Vekemansstraat 22",
    "sg:city":"Bruxelles",
    "sg:classifiers":[
        {
            "category":"Insurance",
            "subcategory":"Insurance Agent",
            "type":"Services"
        }
    ],
    "sg:phone":"+32 2 268 04 93",
    "sg:postcode":"1120",
    "sg:province":"Bruxelles-Capitale",
    "sg:tags":[
        "verzekeringsmakelaars",
        "expert"
    ],
    "wof:name":"Bureau Maurice Willems",
    "wof:placetype":"venue"
},
  "geometry": {"coordinates":[4.3916501999,50.8961448669],"type":"Point"}
}