{
  "type": "Feature",
  "properties": {
    "iso:country":"BE",
    "sg:address":"Rue Du Tordoir 6",
    "sg:city":"Jurbise",
    "sg:orig_category":"Eleveurs de bovins",
    "sg:phone":"+32 65 22 95 37",
    "sg:postcode":"7050",
    "sg:province":"Hainaut",
    "wof:name":"Marie Goret",
    "wof:placetype":"venue"
},
  "geometry": {"coordinates":[3.8918058872,50.5342330933],"type":"Point"}
}