{
  "type": "Feature",
  "properties": {
    "addr:full":"Avenue De La Gare 46 Fleurus Hainaut 6220",
    "addr:housenumber":"46",
    "addr:postcode":"6220",
    "addr:street":"Avenue De La Gare",
    "iso:country":"BE",
    "sg:address":"Avenue De La Gare 46",
    "sg:city":"Fleurus",
    "sg:classifiers":[
        {
            "category":"Insurance",
            "subcategory":"Insurance Agent",
            "type":"Services"
        }
    ],
    "sg:phone":"+32 71 81 31 69",
    "sg:postcode":"6220",
    "sg:province":"Hainaut",
    "sg:tags":[
        "-",
        "representative"
    ],
    "wof:name":"Tilmant R",
    "wof:placetype":"venue"
},
  "geometry": {"coordinates":[4.544465065,50.4820823669],"type":"Point"}
}