{
  "type": "Feature",
  "properties": {
    "iso:country":"BE",
    "sg:address":"Bremstraat 45a",
    "sg:city":"Sint-niklaas",
    "sg:classifiers":[
        {
            "category":"Social Services",
            "type":"Services"
        }
    ],
    "sg:phone":"+32 3 777 02 49",
    "sg:postcode":"9100",
    "sg:province":"Oost-Vlaanderen",
    "wof:name":"Caw Waasland Vzw",
    "wof:placetype":"venue"
},
  "geometry": {"coordinates":[4.1378159523,51.1741905212],"type":"Point"}
}