{
  "type": "Feature",
  "properties": {
    "iso:country":"BE",
    "sg:address":"Neerveldstraat 29",
    "sg:city":"Erpe-mere",
    "sg:orig_category":"Informaticaconsulenten Software ontwikkeling and ontwerp",
    "sg:phone":"+32 53 77 21 24",
    "sg:postcode":"9420",
    "sg:province":"Oost-Vlaanderen",
    "wof:name":"Van Vlaenderen J",
    "wof:placetype":"venue"
},
  "geometry": {"coordinates":[4.0029430389,50.9462623596],"type":"Point"}
}