{
  "type": "Feature",
  "properties": {
    "iso:country":"BE",
    "sg:address":"Oude Markt 22",
    "sg:city":"Leuven",
    "sg:classifiers":[
        {
            "category":"Bars & Pubs",
            "type":"Food & Drink"
        }
    ],
    "sg:phone":"+32 16 22 18 92",
    "sg:postcode":"3000",
    "sg:province":"Vlaams-Brabant",
    "wof:name":"Forum (het)",
    "wof:placetype":"venue"
},
  "geometry": {"coordinates":[4.7443299294,50.8633918762],"type":"Point"}
}