{
  "type": "Feature",
  "properties": {
    "addr:full":"Poederleeseweg 164 Herentals Antwerpen 2200",
    "addr:housenumber":"164",
    "addr:postcode":"2200",
    "iso:country":"BE",
    "sg:address":"Poederleeseweg 164",
    "sg:city":"Herentals",
    "sg:classifiers":[
        {
            "category":"Sports & Exercise",
            "subcategory":"Sports Center",
            "type":"Entertainment"
        }
    ],
    "sg:phone":"+32 14 23 01 56",
    "sg:postcode":"2200",
    "sg:province":"Antwerpen",
    "sg:tags":[
        "terrain",
        "hors",
        "de",
        "installation",
        "sportifs"
    ],
    "wof:name":"Manege Wittenberg-vanden Bulcke",
    "wof:placetype":"venue"
},
  "geometry": {"coordinates":[4.8286061287,51.193813324],"type":"Point"}
}