{
  "type": "Feature",
  "properties": {
    "iso:country":"BE",
    "sg:address":"Laagweg 3",
    "sg:city":"Wervik",
    "sg:orig_category":"Enseignement maternel and primaire",
    "sg:phone":"+32 56 31 12 14",
    "sg:postcode":"8940",
    "sg:province":"West-Vlaanderen",
    "wof:name":"Vrije Kleuterschool",
    "wof:placetype":"venue"
},
  "geometry": {"coordinates":[3.0654830933,50.781993866],"type":"Point"}
}