{
  "type": "Feature",
  "properties": {
    "addr:full":"Hazestraat 41 Zottegem Oost-Vlaanderen 9620",
    "addr:housenumber":"41",
    "addr:postcode":"9620",
    "addr:street":"Hazestraat",
    "iso:country":"BE",
    "sg:address":"Hazestraat 41",
    "sg:city":"Zottegem",
    "sg:orig_category":"Sportclubs",
    "sg:phone":"+32 9 360 20 72",
    "sg:postcode":"9620",
    "sg:province":"Oost-Vlaanderen",
    "wof:name":"Karateclub",
    "wof:placetype":"venue"
},
  "geometry": {"coordinates":[3.8112111092,50.871181488],"type":"Point"}
}