{
  "type": "Feature",
  "properties": {
    "addr:full":"Ijzerenmolenstraat 30 Box 453 Leuven (heverlee) Vlaams-Brabant 3001",
    "addr:housenumber":"30",
    "addr:postcode":"3001",
    "addr:street":"Ijzerenmolenstraat;Box 453",
    "iso:country":"BE",
    "sg:address":"Ijzerenmolenstraat 30 Box 453",
    "sg:city":"Leuven (heverlee)",
    "sg:classifiers":[
        {
            "category":"Professional",
            "subcategory":"Management & Consulting",
            "type":"Services"
        }
    ],
    "sg:phone":"+32 16 23 72 95",
    "sg:postcode":"3001",
    "sg:province":"Vlaams-Brabant",
    "sg:tags":[
        "consultant"
    ],
    "wof:name":"Improvio",
    "wof:placetype":"venue"
},
  "geometry": {"coordinates":[4.6871829033,50.8719978333],"type":"Point"}
}