{
  "type": "Feature",
  "properties": {
    "iso:country":"BE",
    "sg:address":"Rue Des Combattants 10",
    "sg:city":"Montigny-le-tilleul",
    "sg:classifiers":[
        {
            "category":"Cafe",
            "type":"Food & Drink"
        }
    ],
    "sg:phone":"+32 71 51 95 70",
    "sg:postcode":"6110",
    "sg:province":"Hainaut",
    "sg:tags":[
        "caf\u00e9s"
    ],
    "wof:name":"Laurent Toegaert",
    "wof:placetype":"venue"
},
  "geometry": {"coordinates":[4.3780479431,50.3622512817],"type":"Point"}
}