{
  "type": "Feature",
  "properties": {
    "addr:full":"Chemin Du Stoquoi 62 Ath (meslin - L'ev\u00eaque) Hainaut 7822",
    "addr:housenumber":"62;meslin",
    "addr:postcode":"7822",
    "addr:street":"Chemin Du Stoquoi;\u0302Que Hainaut",
    "iso:country":"BE",
    "sg:address":"Chemin Du Stoquoi 62",
    "sg:city":"Ath (meslin - L'ev\u00eaque)",
    "sg:classifiers":[
        {
            "category":"Building & Trades",
            "subcategory":"Landscaping Services",
            "type":"Services"
        }
    ],
    "sg:phone":"+32 68 57 20 01",
    "sg:postcode":"7822",
    "sg:province":"Hainaut",
    "sg:tags":[
        "gardening",
        "garden",
        "maintenance"
    ],
    "wof:name":"Durand B",
    "wof:placetype":"venue"
},
  "geometry": {"coordinates":[3.8452620506,50.6482391357],"type":"Point"}
}