{
  "type": "Feature",
  "properties": {
    "addr:full":"Europaplein 13 Maasmechelen (eisden) Limburg 3630",
    "addr:housenumber":"13",
    "addr:postcode":"3630",
    "addr:street":"Europaplein",
    "iso:country":"BE",
    "sg:address":"Europaplein 13",
    "sg:city":"Maasmechelen (eisden)",
    "sg:classifiers":[
        {
            "category":"Professional",
            "subcategory":"Lawyer & Legal Services",
            "type":"Services"
        }
    ],
    "sg:phone":"+32 89 76 32 88",
    "sg:postcode":"3630",
    "sg:province":"Limburg",
    "wof:name":"Craybex Guy",
    "wof:placetype":"venue"
},
  "geometry": {"coordinates":[5.6961350441,50.963848114],"type":"Point"}
}