{
  "type": "Feature",
  "properties": {
    "iso:country":"BE",
    "sg:address":"Chauss\u00c9e De Charleroi 24",
    "sg:city":"Charleroi",
    "sg:orig_category":"Artsen and specialisten",
    "sg:phone":"+32 71 30 20 33",
    "sg:postcode":"6061",
    "sg:province":"Hainaut",
    "wof:name":"F. Melon",
    "wof:placetype":"venue"
},
  "geometry": {"coordinates":[4.4776468277,50.4012870789],"type":"Point"}
}