{
  "type": "Feature",
  "properties": {
    "addr:full":"Oeverstraat 13 Temse Oost-Vlaanderen 9140",
    "addr:housenumber":"13",
    "addr:postcode":"9140",
    "addr:street":"Oeverstraat",
    "iso:country":"BE",
    "sg:address":"Oeverstraat 13",
    "sg:city":"Temse",
    "sg:classifiers":[
        {
            "category":"Health Services",
            "subcategory":"Health Practitioner",
            "type":"Services"
        }
    ],
    "sg:phone":"+32 3 711 11 34",
    "sg:postcode":"9140",
    "sg:province":"Oost-Vlaanderen",
    "sg:tags":[
        "osteopath"
    ],
    "wof:name":"Feron Ann",
    "wof:placetype":"venue"
},
  "geometry": {"coordinates":[4.2121601105,51.1247787476],"type":"Point"}
}