{
  "type": "Feature",
  "properties": {
    "iso:country":"BE",
    "sg:address":"Rue Defacqz 154",
    "sg:city":"Bruxelles (saint-gilles)",
    "sg:classifiers":[
        {
            "category":"Professional",
            "subcategory":"Testing Lab",
            "type":"Services"
        }
    ],
    "sg:phone":"+32 2 537 05 58",
    "sg:postcode":"1060",
    "sg:province":"Bruxelles-Capitale",
    "sg:tags":[
        "chemist"
    ],
    "wof:name":"Palm",
    "wof:placetype":"venue"
},
  "geometry": {"coordinates":[4.3552188873,50.8257980347],"type":"Point"}
}