{
  "type": "Feature",
  "properties": {
    "addr:full":"Godshuisstraat 2ba Wachtebeke Oost-Vlaanderen 9185",
    "addr:housenumber":"2ba",
    "addr:postcode":"9185",
    "addr:street":"Godshuisstraat",
    "iso:country":"BE",
    "sg:address":"Godshuisstraat 2ba",
    "sg:city":"Wachtebeke",
    "sg:classifiers":[
        {
            "category":"Restaurant",
            "type":"Food & Drink"
        }
    ],
    "sg:phone":"+32 9 342 85 22",
    "sg:postcode":"9185",
    "sg:province":"Oost-Vlaanderen",
    "wof:name":"Sophie's Tearoom",
    "wof:placetype":"venue"
},
  "geometry": {"coordinates":[3.8599159718,51.1699981689],"type":"Point"}
}