{
  "type": "Feature",
  "properties": {
    "iso:country":"BE",
    "sg:address":"Rue De La Concorde 8",
    "sg:city":"Bruxelles (ixelles)",
    "sg:classifiers":[
        {
            "category":"Professional",
            "subcategory":"Art Services",
            "type":"Services"
        }
    ],
    "sg:phone":"+32 2 511 76 31",
    "sg:postcode":"1050",
    "sg:province":"Bruxelles-Capitale",
    "sg:tags":[
        "children's",
        "animation"
    ],
    "wof:name":"Gino's-clowns",
    "wof:placetype":"venue"
},
  "geometry": {"coordinates":[4.3620061874,50.8337554932],"type":"Point"}
}