{
  "type": "Feature",
  "properties": {
    "addr:full":"Rue Du Vivier 162 Bastogne Luxembourg 6600",
    "addr:housenumber":"162",
    "addr:postcode":"6600",
    "addr:street":"Rue Du Vivier",
    "iso:country":"BE",
    "sg:address":"Rue Du Vivier 162",
    "sg:city":"Bastogne",
    "sg:orig_category":"Belastingconsulenten Diverse juridische dienstverlening",
    "sg:phone":"+32 61 21 38 32",
    "sg:postcode":"6600",
    "sg:province":"Luxembourg",
    "wof:name":"Jaspar A.",
    "wof:placetype":"venue"
},
  "geometry": {"coordinates":[5.7173857689,50.0019989014],"type":"Point"}
}