{
  "type": "Feature",
  "properties": {
    "iso:country":"BE",
    "sg:address":"Rue Du Parc 51",
    "sg:city":"Tubize",
    "sg:classifiers":[
        {
            "category":"Personal",
            "subcategory":"Beauty Salon",
            "type":"Services"
        }
    ],
    "sg:postcode":"1480",
    "sg:province":"Brabant Wallon",
    "sg:tags":[
        "de",
        "coiffure"
    ],
    "wof:name":"Martine Roosens",
    "wof:placetype":"venue"
},
  "geometry": {"coordinates":[4.204308033,50.6932029724],"type":"Point"}
}