{
  "type": "Feature",
  "properties": {
    "iso:country":"BE",
    "sg:address":"Eik 38",
    "sg:city":"Bilzen",
    "sg:orig_category":"Fotografen and fotostudio's",
    "sg:phone":"+32 89 41 69 53",
    "sg:postcode":"3740",
    "sg:province":"Limburg",
    "wof:name":"Sourbron Fotografie",
    "wof:placetype":"venue"
},
  "geometry": {"coordinates":[5.5093960762,50.8976593018],"type":"Point"}
}