{
  "type": "Feature",
  "properties": {
    "addr:full":"Honthem 61 Baelen Li\u00e8ge 4837",
    "addr:housenumber":"61",
    "addr:postcode":"4837",
    "addr:street":"Honthem",
    "iso:country":"BE",
    "sg:address":"Honthem 61",
    "sg:city":"Baelen",
    "sg:classifiers":[
        {
            "category":"Professional",
            "subcategory":"Secretarial Services",
            "type":"Services"
        }
    ],
    "sg:phone":"+32 87 76 31 86",
    "sg:postcode":"4837",
    "sg:province":"Li\u00e8ge",
    "sg:tags":[
        "firm"
    ],
    "wof:name":"Renkin M-c",
    "wof:placetype":"venue"
},
  "geometry": {"coordinates":[5.9466810226,50.6269798279],"type":"Point"}
}