{
  "type": "Feature",
  "properties": {
    "addr:full":"Kouter 54 Deinze Oost-Vlaanderen 9800",
    "addr:housenumber":"54",
    "addr:postcode":"9800",
    "addr:street":"Kouter",
    "iso:country":"BE",
    "sg:address":"Kouter 54",
    "sg:city":"Deinze",
    "sg:orig_category":"Woningbouw",
    "sg:phone":"+32 9 386 89 53",
    "sg:postcode":"9800",
    "sg:province":"Oost-Vlaanderen",
    "wof:name":"Wullaert P & M",
    "wof:placetype":"venue"
},
  "geometry": {"coordinates":[3.5105469227,50.9904708862],"type":"Point"}
}