{
  "type": "Feature",
  "properties": {
    "addr:full":"Rue De La Fus\u00c9e 66 Bruxelles Bruxelles-Capitale 1130",
    "addr:housenumber":"66",
    "addr:postcode":"1130",
    "addr:street":"Rue De La Fuse\u0301E",
    "iso:country":"BE",
    "sg:address":"Rue De La Fus\u00c9e 66",
    "sg:city":"Bruxelles",
    "sg:orig_category":"Databanken Informaticaconsulenten",
    "sg:phone":"+32 2 745 04 45",
    "sg:postcode":"1130",
    "sg:province":"Bruxelles-Capitale",
    "wof:name":"Dimension Data N.a. Holding",
    "wof:placetype":"venue"
},
  "geometry": {"coordinates":[4.4208512306,50.8777656555],"type":"Point"}
}