{
  "type": "Feature",
  "properties": {
    "addr:full":"Rue Clerbeau 28 Herstal Li\u00e8ge 4041",
    "addr:housenumber":"28",
    "addr:postcode":"4041",
    "addr:street":"Rue Clerbeau",
    "iso:country":"BE",
    "sg:address":"Rue Clerbeau 28",
    "sg:city":"Herstal",
    "sg:orig_category":"Eleveurs de bovins",
    "sg:phone":"+32 4 278 57 92",
    "sg:postcode":"4041",
    "sg:province":"Li\u00e8ge",
    "wof:name":"Hermesse",
    "wof:placetype":"venue"
},
  "geometry": {"coordinates":[5.594865799,50.6910247803],"type":"Point"}
}