{
  "type": "Feature",
  "properties": {
    "addr:full":"Jan Baptist Tassynsstr. 90 Zwijndrecht Antwerpen 2070",
    "addr:housenumber":"90",
    "addr:postcode":"2070",
    "addr:street":"Jan Baptist Tassynsstr.",
    "iso:country":"BE",
    "sg:address":"Jan Baptist Tassynsstr. 90",
    "sg:city":"Zwijndrecht",
    "sg:orig_category":"Fabrication and montage de mobilier. Installation de menuiserie en bois and plastique. Meubles D\u00e9tai",
    "sg:phone":"+32 3 252 90 90",
    "sg:postcode":"2070",
    "sg:province":"Antwerpen",
    "wof:name":"Henri Janssens",
    "wof:placetype":"venue"
},
  "geometry": {"coordinates":[4.3337788582,51.2172546387],"type":"Point"}
}