{
  "type": "Feature",
  "properties": {
    "iso:country":"BE",
    "sg:address":"Bellaertstraat 100",
    "sg:city":"Lede",
    "sg:classifiers":[
        {
            "category":"Building & Trades",
            "subcategory":"Electrical",
            "type":"Services"
        }
    ],
    "sg:phone":"+32 53 80 36 86",
    "sg:postcode":"9340",
    "sg:province":"Oost-Vlaanderen",
    "sg:tags":[
        "electric",
        "-",
        "housewiring",
        "contractor"
    ],
    "wof:name":"Van Daele P",
    "wof:placetype":"venue"
},
  "geometry": {"coordinates":[3.9833660126,50.9606437683],"type":"Point"}
}