{
  "type": "Feature",
  "properties": {
    "iso:country":"BE",
    "sg:address":"Veurnseweg 11",
    "sg:city":"Ieper",
    "sg:classifiers":[
        {
            "category":"Home & Garden",
            "subcategory":"Furniture",
            "type":"Retail Goods"
        }
    ],
    "sg:phone":"+32 57 20 08 68",
    "sg:postcode":"8900",
    "sg:province":"West-Vlaanderen",
    "sg:tags":[
        "-"
    ],
    "wof:name":"Six F",
    "wof:placetype":"venue"
},
  "geometry": {"coordinates":[2.8703269958,50.8582420349],"type":"Point"}
}