{
  "type": "Feature",
  "properties": {
    "addr:full":"Bourcy 9 Bastogne Luxembourg 6600",
    "addr:housenumber":"9",
    "addr:postcode":"6600",
    "addr:street":"Bourcy",
    "iso:country":"BE",
    "sg:address":"Bourcy 9",
    "sg:city":"Bastogne",
    "sg:orig_category":"Herstellingen and onderhoud van auto's",
    "sg:phone":"+32 61 21 52 41",
    "sg:postcode":"6600",
    "sg:province":"Luxembourg",
    "wof:name":"Christian Meunier",
    "wof:placetype":"venue"
},
  "geometry": {"coordinates":[5.8075881004,50.0566291809],"type":"Point"}
}