{
  "type": "Feature",
  "properties": {
    "iso:country":"BE",
    "sg:address":"Justitiestr 2 Bp 11",
    "sg:city":"Antwerpen",
    "sg:classifiers":[
        {
            "category":"Professional",
            "subcategory":"Advertising",
            "type":"Services"
        }
    ],
    "sg:phone":"+32 3 248 70 78",
    "sg:postcode":"2018",
    "sg:province":"Antwerpen",
    "sg:tags":[
        "information",
        "medium",
        "communication"
    ],
    "wof:name":"Ada Uilenspiegel Bvba",
    "wof:placetype":"venue"
},
  "geometry": {"coordinates":[4.4076981544,51.2097625732],"type":"Point"}
}