{
  "type": "Feature",
  "properties": {
    "addr:full":"Rue Bonnier Du Ch\u00c8ne 32 Herstal Li\u00e8ge 4041",
    "addr:housenumber":"32",
    "addr:postcode":"4041",
    "addr:street":"Rue Bonnier Du Che\u0300Ne",
    "iso:country":"BE",
    "sg:address":"Rue Bonnier Du Ch\u00c8ne 32",
    "sg:city":"Herstal",
    "sg:orig_category":"Schoonheidssalons",
    "sg:phone":"+32 4 227 32 80",
    "sg:postcode":"4041",
    "sg:province":"Li\u00e8ge",
    "wof:name":"Marie-rose Grandjean",
    "wof:placetype":"venue"
},
  "geometry": {"coordinates":[5.5849199295,50.6724891663],"type":"Point"}
}