{
  "type": "Feature",
  "properties": {
    "iso:country":"BE",
    "sg:address":"De Merodedreef 25",
    "sg:city":"Westerlo",
    "sg:classifiers":[
        {
            "category":"Insurance",
            "subcategory":"Insurance Agent",
            "type":"Services"
        }
    ],
    "sg:phone":"+32 14 54 75 24",
    "sg:postcode":"2260",
    "sg:province":"Antwerpen",
    "sg:tags":[
        "broker"
    ],
    "wof:name":"Debruyne B",
    "wof:placetype":"venue"
},
  "geometry": {"coordinates":[4.912006855,51.0838356018],"type":"Point"}
}