{
  "type": "Feature",
  "properties": {
    "addr:full":"Chauss\u00e9e De Marche 48 Neupr\u00e9 (neuville-en-condroz) Li\u00e8ge 4121",
    "addr:housenumber":"48",
    "addr:postcode":"4121",
    "addr:street":"Chausse\u0301E De Marche",
    "iso:country":"BE",
    "sg:address":"Chauss\u00e9e De Marche 48",
    "sg:city":"Neupr\u00e9 (neuville-en-condroz)",
    "sg:classifiers":[
        {
            "category":"Health Services",
            "subcategory":"Hospital",
            "type":"Services"
        }
    ],
    "sg:phone":"+32 4 336 80 80",
    "sg:postcode":"4121",
    "sg:province":"Li\u00e8ge",
    "sg:tags":[
        "ambulance"
    ],
    "wof:name":"Emergency Service Asbl",
    "wof:placetype":"venue"
},
  "geometry": {"coordinates":[5.4512500763,50.5538635254],"type":"Point"}
}