{
  "type": "Feature",
  "properties": {
    "addr:full":"Maarschalk Haiglaan 15 Ieper West-Vlaanderen 8900",
    "addr:housenumber":"15",
    "addr:postcode":"8900",
    "addr:street":"Maarschalk Haiglaan",
    "iso:country":"BE",
    "sg:address":"Maarschalk Haiglaan 15",
    "sg:city":"Ieper",
    "sg:classifiers":[
        {
            "category":"Bakery",
            "type":"Food & Drink"
        }
    ],
    "sg:phone":"+32 57 20 35 32",
    "sg:postcode":"8900",
    "sg:province":"West-Vlaanderen",
    "sg:tags":[
        "confectioner",
        "baker"
    ],
    "wof:name":"Rousseau L",
    "wof:placetype":"venue"
},
  "geometry": {"coordinates":[2.8757510185,50.8517913818],"type":"Point"}
}