{
  "type": "Feature",
  "properties": {
    "addr:full":"Rue Abb\u00c9 P\u00c9ters 49ba2 Malmedy/malmedy Li\u00e8ge 4960",
    "addr:postcode":"4960",
    "addr:street":"Rue Abbe\u0301 Pe\u0301Ters 49Ba2",
    "iso:country":"BE",
    "sg:address":"Rue Abb\u00c9 P\u00c9ters 49ba2",
    "sg:city":"Malmedy/malmedy",
    "sg:orig_category":"Maatschappelijke dienstverlening",
    "sg:phone":"+32 80 33 03 36",
    "sg:postcode":"4960",
    "sg:province":"Li\u00e8ge",
    "wof:name":"Centre P.m.s.",
    "wof:placetype":"venue"
},
  "geometry": {"coordinates":[6.0551772118,50.37657547],"type":"Point"}
}