{
  "type": "Feature",
  "properties": {
    "addr:full":"Zottegemstraat 4 Maarkedal Oost-Vlaanderen 9688",
    "addr:housenumber":"4",
    "addr:postcode":"9688",
    "addr:street":"Zottegemstraat",
    "iso:country":"BE",
    "sg:address":"Zottegemstraat 4",
    "sg:city":"Maarkedal",
    "sg:classifiers":[
        {
            "category":"Cafe",
            "type":"Food & Drink"
        }
    ],
    "sg:phone":"+32 55 45 65 27",
    "sg:postcode":"9688",
    "sg:province":"Oost-Vlaanderen",
    "sg:tags":[
        "caf\u00e9s"
    ],
    "wof:name":"Caf\u00c9 De Kring",
    "wof:placetype":"venue"
},
  "geometry": {"coordinates":[3.6783790588,50.8056106567],"type":"Point"}
}