{
  "type": "Feature",
  "properties": {
    "addr:full":"Rue Heyvaert 134 Bruxelles (molenbeek-saint-jean) Bruxelles-Capitale 1080",
    "addr:housenumber":"134",
    "addr:postcode":"1080",
    "addr:street":"Rue Heyvaert",
    "iso:country":"BE",
    "sg:address":"Rue Heyvaert 134",
    "sg:city":"Bruxelles (molenbeek-saint-jean)",
    "sg:classifiers":[
        {
            "category":"Freight",
            "type":"Transportation"
        }
    ],
    "sg:phone":"+32 2 527 16 35",
    "sg:postcode":"1080",
    "sg:province":"Bruxelles-Capitale",
    "sg:tags":[
        "express",
        "transport"
    ],
    "wof:name":"Mercury Express Sprl",
    "wof:placetype":"venue"
},
  "geometry": {"coordinates":[4.3302111626,50.8451538086],"type":"Point"}
}