{
  "type": "Feature",
  "properties": {
    "addr:full":"Bosschelweg 27 Bocholt Limburg 3950",
    "addr:housenumber":"27",
    "addr:postcode":"3950",
    "addr:street":"Bosschelweg",
    "iso:country":"BE",
    "sg:address":"Bosschelweg 27",
    "sg:city":"Bocholt",
    "sg:orig_category":"Dranken",
    "sg:phone":"+32 11 44 51 78",
    "sg:postcode":"3950",
    "sg:province":"Limburg",
    "wof:name":"Eric Vliegen",
    "wof:placetype":"venue"
},
  "geometry": {"coordinates":[5.5164961815,51.1887359619],"type":"Point"}
}