{
  "type": "Feature",
  "properties": {
    "iso:country":"BE",
    "sg:address":"Rue De Lavaux 7",
    "sg:city":"Saint-hubert",
    "sg:orig_category":"Slagers",
    "sg:phone":"+32 61 61 30 01",
    "sg:postcode":"6870",
    "sg:province":"Luxembourg",
    "wof:name":"Boucherie Le Marcassin",
    "wof:placetype":"venue"
},
  "geometry": {"coordinates":[5.3770198822,50.0258102417],"type":"Point"}
}