{
  "type": "Feature",
  "properties": {
    "iso:country":"BE",
    "sg:address":"M. Van Torhoutstraat 63",
    "sg:city":"Oudenaarde",
    "sg:classifiers":[
        {
            "category":"Personal",
            "subcategory":"Beauty Salon",
            "type":"Services"
        }
    ],
    "sg:phone":"+32 55 31 62 65",
    "sg:postcode":"9700",
    "sg:province":"Oost-Vlaanderen",
    "sg:tags":[
        "de",
        "coiffure"
    ],
    "wof:name":"Kapsalon Mireille",
    "wof:placetype":"venue"
},
  "geometry": {"coordinates":[3.6234810352,50.8487434387],"type":"Point"}
}