{
  "type": "Feature",
  "properties": {
    "iso:country":"BE",
    "sg:address":"Lepelstraat 5",
    "sg:city":"Hooglede",
    "sg:orig_category":"Eleveurs de bovins",
    "sg:phone":"+32 51 20 61 90",
    "sg:postcode":"8830",
    "sg:province":"West-Vlaanderen",
    "wof:name":"Hendrik Clarysse",
    "wof:placetype":"venue"
},
  "geometry": {"coordinates":[3.0904619694,50.984210968],"type":"Point"}
}