{
  "type": "Feature",
  "properties": {
    "iso:country":"BE",
    "sg:address":"Bosdel 42a",
    "sg:city":"Genk",
    "sg:classifiers":[
        {
            "category":"Building & Trades",
            "subcategory":"Electrical",
            "type":"Services"
        }
    ],
    "sg:phone":"+32 89 30 08 30",
    "sg:postcode":"3600",
    "sg:province":"Limburg",
    "sg:tags":[
        "tool",
        "electric"
    ],
    "wof:name":"Fabory Centre Genk",
    "wof:placetype":"venue"
},
  "geometry": {"coordinates":[5.4807667732,50.9505195618],"type":"Point"}
}