{
  "type": "Feature",
  "properties": {
    "addr:full":"Rue Du Ch\u00e2teau 40 Herve Li\u00e8ge 4650",
    "addr:housenumber":"40",
    "addr:postcode":"4650",
    "addr:street":"Rue Du Cha\u0302Teau",
    "iso:country":"BE",
    "sg:address":"Rue Du Ch\u00e2teau 40",
    "sg:city":"Herve",
    "sg:classifiers":[
        {
            "category":"Home & Garden",
            "subcategory":"Carpets & Floor Coverings",
            "type":"Retail Goods"
        }
    ],
    "sg:phone":"+32 87 67 98 98",
    "sg:postcode":"4650",
    "sg:province":"Li\u00e8ge",
    "sg:tags":[
        "parquet"
    ],
    "wof:name":"Schyns J-c",
    "wof:placetype":"venue"
},
  "geometry": {"coordinates":[5.79205513,50.6336097717],"type":"Point"}
}