{
  "type": "Feature",
  "properties": {
    "iso:country":"BE",
    "sg:address":"Rue De Jemeppe 105b1",
    "sg:city":"Ans",
    "sg:orig_category":"Biens d'occasion",
    "sg:phone":"+32 4 263 97 45",
    "sg:postcode":"4431",
    "sg:province":"Li\u00e8ge",
    "wof:name":"Maison Devrin",
    "wof:placetype":"venue"
},
  "geometry": {"coordinates":[5.501086235,50.6632461548],"type":"Point"}
}