{
  "type": "Feature",
  "properties": {
    "iso:country":"BE",
    "sg:address":"Rue Du Christ 29",
    "sg:city":"Mouscron",
    "sg:orig_category":"V\u00eatements pour b\u00e9b\u00e9s and enfants",
    "sg:phone":"+32 56 34 37 08",
    "sg:postcode":"7700",
    "sg:province":"Hainaut",
    "wof:name":"Domino",
    "wof:placetype":"venue"
},
  "geometry": {"coordinates":[3.2084000111,50.744178772],"type":"Point"}
}