{
  "type": "Feature",
  "properties": {
    "iso:country":"BE",
    "sg:address":"Tinstraat 36",
    "sg:city":"Putte",
    "sg:orig_category":"Dakwerken Installatie van houten of kunststof schrijnwerk",
    "sg:phone":"+32 15 75 62 44",
    "sg:postcode":"2580",
    "sg:province":"Antwerpen",
    "wof:name":"Van Den Acker J",
    "wof:placetype":"venue"
},
  "geometry": {"coordinates":[4.6296920776,51.0406646729],"type":"Point"}
}