{
  "type": "Feature",
  "properties": {
    "iso:country":"BE",
    "sg:address":"Rue De Bouvy 14",
    "sg:city":"La Louviere",
    "sg:classifiers":[
        {
            "category":"Communications",
            "subcategory":"Radio Station",
            "type":"Services"
        }
    ],
    "sg:phone":"+32 64 26 29 31",
    "sg:postcode":"7100",
    "sg:province":"Hainaut",
    "sg:tags":[
        "diffusion",
        "production",
        "de",
        "programme"
    ],
    "wof:name":"Fun Radio Ciel",
    "wof:placetype":"venue"
},
  "geometry": {"coordinates":[4.1792459488,50.4672355652],"type":"Point"}
}