{
  "type": "Feature",
  "properties": {
    "iso:country":"BE",
    "sg:address":"Truilingenstraat 36",
    "sg:city":"Gingelom",
    "sg:orig_category":"Bloemen and planten",
    "sg:phone":"+32 11 88 26 82",
    "sg:postcode":"3891",
    "sg:province":"Limburg",
    "wof:name":"Graindor R",
    "wof:placetype":"venue"
},
  "geometry": {"coordinates":[5.1736459732,50.7545776367],"type":"Point"}
}