{
  "type": "Feature",
  "properties": {
    "iso:country":"BE",
    "sg:address":"Stoepestraat 38",
    "sg:city":"Assenede",
    "sg:classifiers":[
        {
            "category":"Education",
            "subcategory":"University",
            "type":"Public Place"
        }
    ],
    "sg:phone":"+32 9 377 32 01",
    "sg:postcode":"9960",
    "sg:province":"Oost-Vlaanderen",
    "sg:tags":[
        "adult"
    ],
    "wof:name":"Pcvo Meetjesland",
    "wof:placetype":"venue"
},
  "geometry": {"coordinates":[3.7563099861,51.1929016113],"type":"Point"}
}