{
  "type": "Feature",
  "properties": {
    "iso:country":"BE",
    "sg:address":"Steegstraat 31",
    "sg:city":"Balen",
    "sg:orig_category":"Baby- and kinderkleding Brood, gebak and snoepgoed",
    "sg:phone":"+32 14 81 40 24",
    "sg:postcode":"2490",
    "sg:province":"Antwerpen",
    "wof:name":"Huis Elvi",
    "wof:placetype":"venue"
},
  "geometry": {"coordinates":[5.1701951027,51.1692619324],"type":"Point"}
}