{
  "type": "Feature",
  "properties": {
    "iso:country":"BE",
    "sg:address":"5537",
    "sg:city":"Anh\u00c9e (groot)",
    "sg:orig_category":"Pharmaciens",
    "sg:phone":"+32 900 10 500",
    "sg:postcode":"5537",
    "sg:province":"Namur",
    "wof:name":"Pharmacies De Garde",
    "wof:placetype":"venue"
},
  "geometry": {"coordinates":[4.8771848679,50.3114013672],"type":"Point"}
}