{
  "type": "Feature",
  "properties": {
    "addr:full":"Thonissenlaan 37 Hasselt Limburg 3500",
    "addr:housenumber":"37",
    "addr:postcode":"3500",
    "addr:street":"Thonissenlaan",
    "iso:country":"BE",
    "sg:address":"Thonissenlaan 37",
    "sg:city":"Hasselt",
    "sg:classifiers":[
        {
            "category":"Travel",
            "subcategory":"Hotels & Motels",
            "type":"Entertainment"
        }
    ],
    "sg:phone":"+32 11 37 93 00",
    "sg:postcode":"3500",
    "sg:province":"Limburg",
    "wof:name":"Express By Holiday Inn Hasselt",
    "wof:placetype":"venue"
},
  "geometry": {"coordinates":[5.3351311684,50.9328346252],"type":"Point"}
}