{
  "type": "Feature",
  "properties": {
    "addr:full":"Damstraat 112-114 Moerbeke (moerbeke-waas) Oost-Vlaanderen 9180",
    "addr:housenumber":"112-114",
    "addr:postcode":"9180",
    "addr:street":"Damstraat",
    "iso:country":"BE",
    "sg:address":"Damstraat 112-114",
    "sg:city":"Moerbeke (moerbeke-waas)",
    "sg:classifiers":[
        {
            "category":"Professional",
            "subcategory":"Art Services",
            "type":"Services"
        }
    ],
    "sg:phone":"+32 9 346 80 16",
    "sg:postcode":"9180",
    "sg:province":"Oost-Vlaanderen",
    "sg:tags":[
        "picture",
        "framer"
    ],
    "wof:name":"Cool Huis",
    "wof:placetype":"venue"
},
  "geometry": {"coordinates":[3.9462220669,51.172328949],"type":"Point"}
}