{
  "type": "Feature",
  "properties": {
    "iso:country":"BE",
    "sg:address":"Rue De La Fosse 54",
    "sg:city":"Mont-saint-guibert",
    "sg:orig_category":"Landmeters",
    "sg:phone":"+32 10 65 54 05",
    "sg:postcode":"1435",
    "sg:province":"Brabant Wallon",
    "wof:name":"Jean-jacques Dewitte",
    "wof:placetype":"venue"
},
  "geometry": {"coordinates":[4.6173729897,50.6350250244],"type":"Point"}
}