{
  "type": "Feature",
  "properties": {
    "iso:country":"BE",
    "sg:address":"Rue D'ab\u00c9e 15",
    "sg:city":"Tinlot",
    "sg:orig_category":"Eleveurs de bovins",
    "sg:phone":"+32 85 51 11 46",
    "sg:postcode":"4557",
    "sg:province":"Li\u00e8ge",
    "wof:name":"Camille Racelle",
    "wof:placetype":"venue"
},
  "geometry": {"coordinates":[5.3580369949,50.4734535217],"type":"Point"}
}