{
  "type": "Feature",
  "properties": {
    "addr:full":"Herritakkerlaan 23 Evergem (sleidinge) Oost-Vlaanderen 9940",
    "addr:housenumber":"23",
    "addr:postcode":"9940",
    "addr:street":"Herritakkerlaan",
    "iso:country":"BE",
    "sg:address":"Herritakkerlaan 23",
    "sg:city":"Evergem (sleidinge)",
    "sg:classifiers":[
        {
            "category":"Health Services",
            "subcategory":"Doctor",
            "type":"Services"
        }
    ],
    "sg:phone":"+32 9 358 20 35",
    "sg:postcode":"9940",
    "sg:province":"Oost-Vlaanderen",
    "sg:tags":[
        "medicinephysicians",
        "surgeon"
    ],
    "wof:name":"Florival Francis",
    "wof:placetype":"venue"
},
  "geometry": {"coordinates":[3.6757218838,51.1283493042],"type":"Point"}
}