{
  "type": "Feature",
  "properties": {
    "iso:country":"BE",
    "sg:address":"Zuidkaai 10bb",
    "sg:city":"Gent",
    "sg:orig_category":"Farmaceutische bereidingen and geneesmiddelen Fab Loodgieterij, verwarming and sanitaire installatie",
    "sg:phone":"+32 9 226 33 53",
    "sg:postcode":"9000",
    "sg:province":"Oost-Vlaanderen",
    "wof:name":"Fa. Demulco",
    "wof:placetype":"venue"
},
  "geometry": {"coordinates":[3.706428051,51.0582389832],"type":"Point"}
}