{
  "type": "Feature",
  "properties": {
    "iso:country":"BE",
    "sg:address":"Rue De L'hotellerie 84b",
    "sg:city":"Lessines",
    "sg:classifiers":[
        {
            "category":"Health Services",
            "subcategory":"Health Practitioner",
            "type":"Services"
        }
    ],
    "sg:phone":"+32 68 33 52 17",
    "sg:postcode":"7860",
    "sg:province":"Hainaut",
    "sg:tags":[
        "physiotherapist"
    ],
    "wof:name":"Verbruggen C",
    "wof:placetype":"venue"
},
  "geometry": {"coordinates":[3.8390030861,50.7099151611],"type":"Point"}
}