{
  "type": "Feature",
  "properties": {
    "iso:country":"BE",
    "sg:address":"Jetsesteenweg 572",
    "sg:city":"Jette",
    "sg:orig_category":"Plaatsen van vloer- and muurbekleding Schilders",
    "sg:phone":"+32 2 421 76 71",
    "sg:postcode":"1090",
    "sg:province":"Bruxelles-Capitale",
    "wof:name":"Eubaco",
    "wof:placetype":"venue"
},
  "geometry": {"coordinates":[4.3259758949,50.8713493347],"type":"Point"}
}