{
  "type": "Feature",
  "properties": {
    "iso:country":"BE",
    "sg:address":"Dorpsstraat 37",
    "sg:city":"Nieuwerkerken",
    "sg:orig_category":"Apotheken",
    "sg:phone":"+32 11 31 16 66",
    "sg:postcode":"3850",
    "sg:province":"Limburg",
    "wof:name":"Kamiel Gijsenbergs",
    "wof:placetype":"venue"
},
  "geometry": {"coordinates":[5.2414469719,50.8766708374],"type":"Point"}
}