{
  "type": "Feature",
  "properties": {
    "addr:full":"Rue Van Brusselt 22 Gerpinnes Hainaut 6280",
    "addr:housenumber":"22",
    "addr:postcode":"6280",
    "addr:street":"Rue Van Brusselt;Hainaut",
    "iso:country":"BE",
    "sg:address":"Rue Van Brusselt 22",
    "sg:city":"Gerpinnes",
    "sg:orig_category":"Viessmann. Plomberie, chauffage and installations sanitaires",
    "sg:phone":"+32 71 50 50 49",
    "sg:postcode":"6280",
    "sg:province":"Hainaut",
    "wof:name":"Vannox-heating",
    "wof:placetype":"venue"
},
  "geometry": {"coordinates":[4.4887161255,50.3375205994],"type":"Point"}
}