{
  "type": "Feature",
  "properties": {
    "addr:full":"Ahornbomenlaan 28 Kampenhout Vlaams-Brabant 1910",
    "addr:housenumber":"28",
    "addr:postcode":"1910",
    "addr:street":"Ahornbomenlaan",
    "iso:country":"BE",
    "sg:address":"Ahornbomenlaan 28",
    "sg:city":"Kampenhout",
    "sg:classifiers":[
        {
            "category":"Shopping",
            "subcategory":"Clothing, Apparel, & Fashions",
            "type":"Retail Goods"
        }
    ],
    "sg:phone":"+32 16 65 03 60",
    "sg:postcode":"1910",
    "sg:province":"Vlaams-Brabant",
    "sg:tags":[
        "lingerie",
        "sous-v\u00eatements"
    ],
    "wof:name":"Josee Kerstens",
    "wof:placetype":"venue"
},
  "geometry": {"coordinates":[4.5536580086,50.9297523499],"type":"Point"}
}