{
  "type": "Feature",
  "properties": {
    "iso:country":"BE",
    "sg:address":"Rue De Petit Axhe 45",
    "sg:city":"Waremme",
    "sg:classifiers":[
        {
            "category":"Professional",
            "subcategory":"Printing & Photocopies",
            "type":"Services"
        }
    ],
    "sg:phone":"+32 19 32 84 89",
    "sg:postcode":"4300",
    "sg:province":"Li\u00e8ge",
    "sg:tags":[
        "-",
        "offset"
    ],
    "wof:name":"Leemans P",
    "wof:placetype":"venue"
},
  "geometry": {"coordinates":[5.232614994,50.6832046509],"type":"Point"}
}