{
  "type": "Feature",
  "properties": {
    "addr:full":"Rue Des Tronces 4 Fosses-la-ville Namur 5070",
    "addr:housenumber":"4",
    "addr:postcode":"5070",
    "addr:street":"Rue Des Tronces",
    "iso:country":"BE",
    "sg:address":"Rue Des Tronces 4",
    "sg:city":"Fosses-la-ville",
    "sg:orig_category":"Kapsalons",
    "sg:phone":"+32 71 71 14 62",
    "sg:postcode":"5070",
    "sg:province":"Namur",
    "wof:name":"Carine Lambreghts",
    "wof:placetype":"venue"
},
  "geometry": {"coordinates":[4.6325788498,50.3802108765],"type":"Point"}
}