{
  "type": "Feature",
  "properties": {
    "addr:full":"Rue Les Tiennes 121 Namur Namur 5100",
    "addr:housenumber":"121",
    "addr:postcode":"5100",
    "addr:street":"Rue Les Tiennes",
    "iso:country":"BE",
    "sg:address":"Rue Les Tiennes 121",
    "sg:city":"Namur",
    "sg:orig_category":"Gespecialiseerde residenti\u00eble bouw Tuinen",
    "sg:phone":"+32 81 40 10 43",
    "sg:postcode":"5100",
    "sg:province":"Namur",
    "wof:name":"Alain Michiels",
    "wof:placetype":"venue"
},
  "geometry": {"coordinates":[4.8713750839,50.4566345215],"type":"Point"}
}