{
  "type": "Feature",
  "properties": {
    "iso:country":"BE",
    "sg:address":"Rue Du Ch\u00c2teau 2ba",
    "sg:city":"Brunehaut",
    "sg:orig_category":"Boomkwekerijen Tuinen",
    "sg:phone":"+32 69 34 40 44",
    "sg:postcode":"7621",
    "sg:province":"Hainaut",
    "wof:name":"Bernadette Remy",
    "wof:placetype":"venue"
},
  "geometry": {"coordinates":[3.3887519836,50.5198783875],"type":"Point"}
}