{
  "type": "Feature",
  "properties": {
    "addr:full":"Boomsesteenweg 255-259 Antwerpen (wilrijk) Antwerpen 2610",
    "addr:housenumber":"255-259",
    "addr:postcode":"2610",
    "addr:street":"Boomsesteenweg;Antwerpen",
    "iso:country":"BE",
    "sg:address":"Boomsesteenweg 255-259",
    "sg:city":"Antwerpen (wilrijk)",
    "sg:classifiers":[
        {
            "category":"Professional",
            "subcategory":"Printing & Photocopies",
            "type":"Services"
        }
    ],
    "sg:phone":"+32 3 248 08 04",
    "sg:postcode":"2610",
    "sg:province":"Antwerpen",
    "sg:tags":[
        "-",
        "publishing",
        "desktop"
    ],
    "wof:name":"Asap Photographic Services",
    "wof:placetype":"venue"
},
  "geometry": {"coordinates":[4.3870520592,51.1896514893],"type":"Point"}
}