{
  "type": "Feature",
  "properties": {
    "addr:full":"Sint-godelievestraat 17 Pittem West-Vlaanderen 8740",
    "addr:housenumber":"17",
    "addr:postcode":"8740",
    "addr:street":"Sint-Godelievestraat",
    "iso:country":"BE",
    "sg:address":"Sint-godelievestraat 17",
    "sg:city":"Pittem",
    "sg:orig_category":"Installatie van houten of kunststof schrijnwerk",
    "sg:phone":"+32 51 46 72 41",
    "sg:postcode":"8740",
    "sg:province":"West-Vlaanderen",
    "wof:name":"Patrick Kerkhof",
    "wof:placetype":"venue"
},
  "geometry": {"coordinates":[3.2576789856,50.9975814819],"type":"Point"}
}