{
  "type": "Feature",
  "properties": {
    "iso:country":"BE",
    "sg:address":"Cobreville 15",
    "sg:city":"Vaux-sur-sure",
    "sg:orig_category":"Rundveehouders",
    "sg:phone":"+32 61 26 62 79",
    "sg:postcode":"6640",
    "sg:province":"Luxembourg",
    "wof:name":"Michel Cornette",
    "wof:placetype":"venue"
},
  "geometry": {"coordinates":[5.6104850769,49.9149551392],"type":"Point"}
}