{
  "type": "Feature",
  "properties": {
    "addr:full":"Rue Couture Du Moulin 39 Mont-de-l'enclus Hainaut 7750",
    "addr:housenumber":"39",
    "addr:postcode":"7750",
    "addr:street":"Rue Couture Du Moulin;Hainaut",
    "iso:country":"BE",
    "sg:address":"Rue Couture Du Moulin 39",
    "sg:city":"Mont-de-l'enclus",
    "sg:orig_category":"Sportclubs",
    "sg:phone":"+32 69 76 97 18",
    "sg:postcode":"7750",
    "sg:province":"Hainaut",
    "wof:name":"J.c. Ichiro Abe",
    "wof:placetype":"venue"
},
  "geometry": {"coordinates":[5.7178230286,47.0204772949],"type":"Point"}
}