{
  "type": "Feature",
  "properties": {
    "iso:country":"BE",
    "sg:address":"Armoedestraat 61",
    "sg:city":"Rumbeke",
    "sg:classifiers":[
        {
            "category":"Farming",
            "subcategory":"Farm",
            "type":"Manufacturing & Wholesale Goods"
        }
    ],
    "sg:phone":"+32 51 24 41 61",
    "sg:postcode":"8800",
    "sg:province":"West-Vlaanderen",
    "sg:tags":[
        "horticulture",
        "agriculture",
        "livestock"
    ],
    "wof:name":"Donck A & Zn Nv",
    "wof:placetype":"venue"
},
  "geometry": {"coordinates":[3.171159029,50.9254989624],"type":"Point"}
}