{
  "type": "Feature",
  "properties": {
    "addr:full":"Liebaardstraat 155 Waregem West-Vlaanderen 8792",
    "addr:housenumber":"155",
    "addr:postcode":"8792",
    "addr:street":"Liebaardstraat",
    "iso:country":"BE",
    "sg:address":"Liebaardstraat 155",
    "sg:city":"Waregem",
    "sg:orig_category":"Banques and organismes de cr\u00e9dit",
    "sg:phone":"+32 56 71 19 86",
    "sg:postcode":"8792",
    "sg:province":"West-Vlaanderen",
    "wof:name":"Fortis",
    "wof:placetype":"venue"
},
  "geometry": {"coordinates":[3.3556859493,50.882358551],"type":"Point"}
}