{
  "type": "Feature",
  "properties": {
    "iso:country":"BE",
    "sg:address":"Rue De La Station 48",
    "sg:city":"Le Roeulx",
    "sg:orig_category":"Elektrische installaties voor woningen",
    "sg:phone":"+32 64 67 73 42",
    "sg:postcode":"7070",
    "sg:province":"Hainaut",
    "wof:name":"Christian Sirlereau",
    "wof:placetype":"venue"
},
  "geometry": {"coordinates":[4.1139550209,50.5060501099],"type":"Point"}
}