{
  "type": "Feature",
  "properties": {
    "iso:country":"BE",
    "sg:address":"Brusselsesteenweg 156",
    "sg:city":"Asse",
    "sg:orig_category":"Voertuigen",
    "sg:phone":"+32 2 452 88 76",
    "sg:postcode":"1730",
    "sg:province":"Vlaams-Brabant",
    "wof:name":"Serge Vervondel",
    "wof:placetype":"venue"
},
  "geometry": {"coordinates":[4.2150201797,50.9018516541],"type":"Point"}
}