{
  "type": "Feature",
  "properties": {
    "addr:full":"Oude Stationstraat 23 Tielt West-Vlaanderen 8700",
    "addr:housenumber":"23",
    "addr:postcode":"8700",
    "addr:street":"Oude Stationstraat",
    "iso:country":"BE",
    "sg:address":"Oude Stationstraat 23",
    "sg:city":"Tielt",
    "sg:orig_category":"Packard Bell Nec. Electrom\u00e9nager, t\u00e9l\u00e9visions and radios. Mat\u00e9riel de T\u00e9l\u00e9communication",
    "sg:phone":"+32 51 40 40 00",
    "sg:postcode":"8700",
    "sg:province":"West-Vlaanderen",
    "wof:name":"Pv Sound",
    "wof:placetype":"venue"
},
  "geometry": {"coordinates":[3.3269739151,50.9948005676],"type":"Point"}
}