{
  "type": "Feature",
  "properties": {
    "iso:country":"BE",
    "sg:address":"Lange Leemstraat 94-2",
    "sg:city":"Antwerpen",
    "sg:classifiers":[
        {
            "category":"Government",
            "subcategory":"Post Office",
            "type":"Public Place"
        }
    ],
    "sg:phone":"+32 3 281 28 12",
    "sg:postcode":"2018",
    "sg:province":"Antwerpen",
    "sg:tags":[
        "picture",
        "restoring"
    ],
    "wof:name":"Maes Herman",
    "wof:placetype":"venue"
},
  "geometry": {"coordinates":[4.4126000404,51.2080001831],"type":"Point"}
}