{
  "type": "Feature",
  "properties": {
    "iso:country":"BE",
    "sg:address":"Rue Neuve 14",
    "sg:city":"Malmedy",
    "sg:classifiers":[
        {
            "category":"Organizations",
            "subcategory":"Community Association",
            "type":"Services"
        }
    ],
    "sg:phone":"+32 80 77 09 96",
    "sg:postcode":"4960",
    "sg:province":"Li\u00e8ge",
    "sg:tags":[
        "cultural"
    ],
    "wof:name":"Belgo-turc",
    "wof:placetype":"venue"
},
  "geometry": {"coordinates":[6.0330109596,50.4247589111],"type":"Point"}
}