{
  "type": "Feature",
  "properties": {
    "iso:country":"BE",
    "sg:address":"Edewallestraat 94 - 96",
    "sg:city":"Kortemark",
    "sg:orig_category":"Babyspullen Computers and computerapparatuur HERSTELLING ELEKTRISCHE HUISHOUDAPPARATEN IJzerwaren, b",
    "sg:phone":"+32 51 57 52 18",
    "sg:postcode":"8610",
    "sg:province":"West-Vlaanderen",
    "wof:name":"Vermeersch - Deconinck",
    "wof:placetype":"venue"
},
  "geometry": {"coordinates":[3.0093529224,51.0457611084],"type":"Point"}
}