{
  "type": "Feature",
  "properties": {
    "iso:country":"BE",
    "sg:address":"Naamsesteenweg 407",
    "sg:city":"Leuven",
    "sg:orig_category":"Schoonmaakbedrijven and ongediertebestrijding",
    "sg:phone":"+32 16 40 63 12",
    "sg:postcode":"3001",
    "sg:province":"Vlaams-Brabant",
    "wof:name":"Ronny",
    "wof:placetype":"venue"
},
  "geometry": {"coordinates":[4.6959180832,50.8572311401],"type":"Point"}
}