{
  "type": "Feature",
  "properties": {
    "iso:country":"BE",
    "sg:address":"Vlezenbeeklaan 167",
    "sg:city":"Sint-pieters-leeuw (vlezenbeek)",
    "sg:classifiers":[
        {
            "category":"Building & Trades",
            "subcategory":"Construction",
            "type":"Services"
        }
    ],
    "sg:phone":"+32 2 569 07 20",
    "sg:postcode":"1602",
    "sg:province":"Vlaams-Brabant",
    "sg:tags":[
        "carpenter"
    ],
    "wof:name":"Van Nieuwenhoven H",
    "wof:placetype":"venue"
},
  "geometry": {"coordinates":[4.2332010269,50.8071479797],"type":"Point"}
}