{
  "type": "Feature",
  "properties": {
    "iso:country":"BE",
    "sg:address":"'s Gravenhagestraat 11",
    "sg:city":"Heist-op-den-berg",
    "sg:orig_category":"Fruitteelt",
    "sg:phone":"+32 15 24 00 07",
    "sg:postcode":"2220",
    "sg:province":"Antwerpen",
    "wof:name":"Paul Zegers",
    "wof:placetype":"venue"
},
  "geometry": {"coordinates":[4.7069940567,51.0483779907],"type":"Point"}
}