{
  "type": "Feature",
  "properties": {
    "addr:full":"Place Meunier 20 Mettet Namur 5640",
    "addr:housenumber":"20",
    "addr:postcode":"5640",
    "addr:street":"Place Meunier",
    "iso:country":"BE",
    "sg:address":"Place Meunier 20",
    "sg:city":"Mettet",
    "sg:orig_category":"Rijscholen",
    "sg:phone":"+32 71 72 95 05",
    "sg:postcode":"5640",
    "sg:province":"Namur",
    "wof:name":"Euro-permis",
    "wof:placetype":"venue"
},
  "geometry": {"coordinates":[4.6577119827,50.3204421997],"type":"Point"}
}