{
  "type": "Feature",
  "properties": {
    "iso:country":"BE",
    "sg:address":"Avenue Du Beau Site 5",
    "sg:city":"La Hulpe",
    "sg:classifiers":[
        {
            "category":"Education",
            "subcategory":"Special Training",
            "type":"Public Place"
        }
    ],
    "sg:phone":"+32 2 653 68 57",
    "sg:postcode":"1310",
    "sg:province":"Brabant Wallon",
    "sg:tags":[
        "school",
        "language"
    ],
    "wof:name":"Alphalingua-ecole De Langues",
    "wof:placetype":"venue"
},
  "geometry": {"coordinates":[4.4838581085,50.7330932617],"type":"Point"}
}