{
  "type": "Feature",
  "properties": {
    "iso:country":"BE",
    "sg:address":"Kapellestraat 16",
    "sg:city":"Dentergem",
    "sg:orig_category":"Herstellingen and onderhoud van auto's",
    "sg:phone":"+32 56 60 51 32",
    "sg:postcode":"8720",
    "sg:province":"West-Vlaanderen",
    "wof:name":"Carlos Deconinck",
    "wof:placetype":"venue"
},
  "geometry": {"coordinates":[3.3961350918,50.9312286377],"type":"Point"}
}