{
  "type": "Feature",
  "properties": {
    "addr:full":"Boulevard Zenobe Gramme 35 Herstal Li\u00e8ge 4040",
    "addr:housenumber":"35",
    "addr:postcode":"4040",
    "addr:street":"Boulevard Zenobe Gramme",
    "iso:country":"BE",
    "sg:address":"Boulevard Zenobe Gramme 35",
    "sg:city":"Herstal",
    "sg:orig_category":"V\u00e9hicules automobiles",
    "sg:phone":"+32 4 264 50 10",
    "sg:postcode":"4040",
    "sg:province":"Li\u00e8ge",
    "wof:name":"Ets. Martin G. & O.",
    "wof:placetype":"venue"
},
  "geometry": {"coordinates":[5.6340208054,50.6634254456],"type":"Point"}
}