{
  "type": "Feature",
  "properties": {
    "addr:full":"Rue De La Forge 14 Leuze-en-hainaut Hainaut 7904",
    "addr:housenumber":"14",
    "addr:postcode":"7904",
    "addr:street":"Rue De La Forge",
    "iso:country":"BE",
    "sg:address":"Rue De La Forge 14",
    "sg:city":"Leuze-en-hainaut",
    "sg:orig_category":"Sportclubs",
    "sg:phone":"+32 69 66 20 87",
    "sg:postcode":"7904",
    "sg:province":"Hainaut",
    "wof:name":"Union Cycl.vieux-leuzoise",
    "wof:placetype":"venue"
},
  "geometry": {"coordinates":[3.6061298847,50.5644798279],"type":"Point"}
}