{
  "type": "Feature",
  "properties": {
    "addr:full":"Koestraat 21 Roeselare (rumbeke) West-Vlaanderen 8800",
    "addr:housenumber":"21",
    "addr:postcode":"8800",
    "addr:street":"Koestraat",
    "iso:country":"BE",
    "sg:address":"Koestraat 21",
    "sg:city":"Roeselare (rumbeke)",
    "sg:classifiers":[
        {
            "category":"Building & Trades",
            "subcategory":"Electrical",
            "type":"Services"
        }
    ],
    "sg:phone":"+32 51 25 03 64",
    "sg:postcode":"8800",
    "sg:province":"West-Vlaanderen",
    "sg:tags":[
        "electric",
        "-",
        "housewiring",
        "contractor"
    ],
    "wof:name":"Desmet Elektro Bvba",
    "wof:placetype":"venue"
},
  "geometry": {"coordinates":[3.1495800018,50.9244117737],"type":"Point"}
}