{
  "type": "Feature",
  "properties": {
    "addr:full":"Joossensgang 4 Antwerpen Antwerpen 2060",
    "addr:housenumber":"4",
    "addr:postcode":"2060",
    "addr:street":"Joossensgang",
    "iso:country":"BE",
    "sg:address":"Joossensgang 4",
    "sg:city":"Antwerpen",
    "sg:classifiers":[
        {
            "category":"Food & Beverages",
            "subcategory":"Groceries & Convenience Stores",
            "type":"Retail Goods"
        }
    ],
    "sg:phone":"+32 3 226 59 65",
    "sg:postcode":"2060",
    "sg:province":"Antwerpen",
    "sg:tags":[
        "baker",
        "-",
        "ingredient"
    ],
    "wof:name":"Cumra",
    "wof:placetype":"venue"
},
  "geometry": {"coordinates":[4.4219179153,51.2328147888],"type":"Point"}
}