{
  "type": "Feature",
  "properties": {
    "iso:country":"BE",
    "sg:address":"Schuurstraat 2",
    "sg:city":"Gent (sint-amandsberg)",
    "sg:classifiers":[
        {
            "category":"Real Estate",
            "subcategory":"Real Estate Services",
            "type":"Services"
        }
    ],
    "sg:phone":"+32 9 218 84 40",
    "sg:postcode":"9040",
    "sg:province":"Oost-Vlaanderen",
    "wof:name":"Patriver Nv",
    "wof:placetype":"venue"
},
  "geometry": {"coordinates":[3.7758660316,51.0677108765],"type":"Point"}
}