{
  "type": "Feature",
  "properties": {
    "addr:full":"Pastoor Verwilghenplein 37 Beveren Oost-Vlaanderen 9120",
    "addr:housenumber":"37",
    "addr:postcode":"9120",
    "addr:street":"Pastoor Verwilghenplein",
    "iso:country":"BE",
    "sg:address":"Pastoor Verwilghenplein 37",
    "sg:city":"Beveren",
    "sg:orig_category":"Banques and organismes de cr\u00e9dit",
    "sg:phone":"+32 3 775 97 60",
    "sg:postcode":"9120",
    "sg:province":"Oost-Vlaanderen",
    "wof:name":"Fortis",
    "wof:placetype":"venue"
},
  "geometry": {"coordinates":[4.2400131226,51.1815986633],"type":"Point"}
}