{
  "type": "Feature",
  "properties": {
    "addr:full":"Mechelsesteenweg 761-763 Leuven Vlaams-Brabant 3000",
    "addr:housenumber":"761-763",
    "addr:postcode":"3000",
    "addr:street":"Mechelsesteenweg",
    "iso:country":"BE",
    "sg:address":"Mechelsesteenweg 761-763",
    "sg:city":"Leuven",
    "sg:classifiers":[
        {
            "category":"Sports & Exercise",
            "subcategory":"Gym",
            "type":"Entertainment"
        }
    ],
    "sg:phone":"+32 16 89 71 02",
    "sg:postcode":"3000",
    "sg:province":"Vlaams-Brabant",
    "sg:tags":[
        "fitness"
    ],
    "wof:name":"Fit Mix",
    "wof:placetype":"venue"
},
  "geometry": {"coordinates":[4.6889801025,50.8934707642],"type":"Point"}
}