{
  "type": "Feature",
  "properties": {
    "iso:country":"BE",
    "sg:address":"Kerkstraat 3",
    "sg:city":"Schilde",
    "sg:orig_category":"Agences immobili\u00e8res",
    "sg:phone":"+32 3 658 05 05",
    "sg:postcode":"2970",
    "sg:province":"Antwerpen",
    "wof:name":"M.v.g.",
    "wof:placetype":"venue"
},
  "geometry": {"coordinates":[4.5830001831,51.2402687073],"type":"Point"}
}