{
  "type": "Feature",
  "properties": {
    "addr:full":"Bras 6 Box 3a Bastogne (wardin) Luxembourg 6600",
    "addr:housenumber":"6;3a",
    "addr:postcode":"6600",
    "addr:street":"Bras;Box",
    "iso:country":"BE",
    "sg:address":"Bras 6 Box 3a",
    "sg:city":"Bastogne (wardin)",
    "sg:classifiers":[
        {
            "category":"Building & Trades",
            "subcategory":"Landscaping Services",
            "type":"Services"
        }
    ],
    "sg:phone":"+32 61 21 10 38",
    "sg:postcode":"6600",
    "sg:province":"Luxembourg",
    "sg:tags":[
        "gardening",
        "garden",
        "maintenance"
    ],
    "wof:name":"Abelux",
    "wof:placetype":"venue"
},
  "geometry": {"coordinates":[5.7148199081,50.0007820129],"type":"Point"}
}