{
  "type": "Feature",
  "properties": {
    "addr:full":"Haverhuisstraat 3 Izegem (kachtem) West-Vlaanderen 8870",
    "addr:housenumber":"3",
    "addr:postcode":"8870",
    "addr:street":"Haverhuisstraat",
    "iso:country":"BE",
    "sg:address":"Haverhuisstraat 3",
    "sg:city":"Izegem (kachtem)",
    "sg:classifiers":[
        {
            "category":"Banks & Credit Unions",
            "subcategory":"Investment Brokerage",
            "type":"Services"
        }
    ],
    "sg:phone":"+32 51 32 06 92",
    "sg:postcode":"8870",
    "sg:province":"West-Vlaanderen",
    "sg:tags":[
        "repair",
        "-",
        "installation",
        "sanitary",
        "article"
    ],
    "wof:name":"Sanifix Bvba",
    "wof:placetype":"venue"
},
  "geometry": {"coordinates":[3.1866769791,50.9343261719],"type":"Point"}
}