{
  "type": "Feature",
  "properties": {
    "addr:full":"Vrietselstraat 8 Dilsen-stokkem Limburg 3650",
    "addr:housenumber":"8",
    "addr:postcode":"3650",
    "addr:street":"Vrietselstraat",
    "iso:country":"BE",
    "sg:address":"Vrietselstraat 8",
    "sg:city":"Dilsen-stokkem",
    "sg:orig_category":"Entretien and r\u00e9parations de voitures",
    "sg:phone":"+32 89 75 67 43",
    "sg:postcode":"3650",
    "sg:province":"Limburg",
    "wof:name":"L\u00c9opold Giewald",
    "wof:placetype":"venue"
},
  "geometry": {"coordinates":[5.727396965,51.0364189148],"type":"Point"}
}