{
  "type": "Feature",
  "properties": {
    "iso:country":"BE",
    "sg:address":"Schoutenlaan 18",
    "sg:city":"Herentals",
    "sg:classifiers":[
        {
            "category":"Retail",
            "subcategory":"Repair Shop",
            "type":"Services"
        }
    ],
    "sg:phone":"+32 495 53 85 85",
    "sg:postcode":"2200",
    "sg:province":"Antwerpen",
    "sg:tags":[
        "mainten",
        "-",
        "parquet"
    ],
    "wof:name":"Mhm Partners",
    "wof:placetype":"venue"
},
  "geometry": {"coordinates":[4.8561611176,51.1936836243],"type":"Point"}
}