{
  "type": "Feature",
  "properties": {
    "iso:country":"BE",
    "sg:address":"Rue De Neufvilles 165",
    "sg:city":"Soignies",
    "sg:orig_category":"R\u00e9parations d'appareils \u00e9lectrom\u00e9nagers",
    "sg:phone":"+32 67 33 12 17",
    "sg:postcode":"7060",
    "sg:province":"Hainaut",
    "wof:name":"De Wulf Carlos",
    "wof:placetype":"venue"
},
  "geometry": {"coordinates":[4.0552158356,50.5778617859],"type":"Point"}
}