{
  "type": "Feature",
  "properties": {
    "addr:full":"Rue Charles Zoude 65 Namur Namur 5000",
    "addr:housenumber":"65",
    "addr:postcode":"5000",
    "addr:street":"Rue Charles Zoude",
    "iso:country":"BE",
    "sg:address":"Rue Charles Zoude 65",
    "sg:city":"Namur",
    "sg:classifiers":[
        {
            "category":"Manufacturing",
            "subcategory":"Signs",
            "type":"Manufacturing & Wholesale Goods"
        }
    ],
    "sg:phone":"+32 81 85 68 67",
    "sg:postcode":"5000",
    "sg:province":"Namur",
    "sg:tags":[
        "-",
        "illuminated"
    ],
    "wof:name":"M.b.p.",
    "wof:placetype":"venue"
},
  "geometry": {"coordinates":[4.8473191261,50.4627189636],"type":"Point"}
}