{
  "type": "Feature",
  "properties": {
    "iso:country":"BE",
    "sg:address":"Dr\u00e8ve Du Val Saint-pierre 6",
    "sg:city":"Rixensart (genval)",
    "sg:classifiers":[
        {
            "category":"Health Services",
            "subcategory":"Dentist",
            "type":"Services"
        }
    ],
    "sg:phone":"+32 2 654 15 19",
    "sg:postcode":"1332",
    "sg:province":"Brabant Wallon",
    "wof:name":"El Sayyed Tareq",
    "wof:placetype":"venue"
},
  "geometry": {"coordinates":[4.5099282265,50.7211608887],"type":"Point"}
}