{
  "type": "Feature",
  "properties": {
    "iso:country":"BE",
    "sg:address":"Houtmolenstraat 116",
    "sg:city":"Overpelt",
    "sg:orig_category":"Entretien and r\u00e9parations de voitures",
    "sg:phone":"+32 11 64 85 41",
    "sg:postcode":"3900",
    "sg:province":"Limburg",
    "wof:name":"Autohandel Gilbert Leeters",
    "wof:placetype":"venue"
},
  "geometry": {"coordinates":[5.4154858589,51.2224235535],"type":"Point"}
}