{
  "type": "Feature",
  "properties": {
    "addr:full":"Avenue Des M\u00c9risiers 8 Rixensart Brabant Wallon 1332",
    "addr:housenumber":"8",
    "addr:postcode":"1332",
    "addr:street":"Avenue Des Me\u0301Risiers;Wallon",
    "iso:country":"BE",
    "sg:address":"Avenue Des M\u00c9risiers 8",
    "sg:city":"Rixensart",
    "sg:orig_category":"Software ontwikkeling and ontwerp",
    "sg:phone":"+32 2 656 05 50",
    "sg:postcode":"1332",
    "sg:province":"Brabant Wallon",
    "wof:name":"Orsys",
    "wof:placetype":"venue"
},
  "geometry": {"coordinates":[4.5158162117,50.7285270691],"type":"Point"}
}