{
  "type": "Feature",
  "properties": {
    "iso:country":"BE",
    "sg:address":"Boulevard Du Nord 25",
    "sg:city":"Namur",
    "sg:orig_category":"Journaux. Tabac",
    "sg:phone":"+32 81 22 68 88",
    "sg:postcode":"5000",
    "sg:province":"Namur",
    "wof:name":"Press Shop",
    "wof:placetype":"venue"
},
  "geometry": {"coordinates":[4.8640789986,50.4702377319],"type":"Point"}
}