{
  "type": "Feature",
  "properties": {
    "iso:country":"BE",
    "sg:address":"Josse Biesmansstraat 36",
    "sg:city":"Hoeilaart",
    "sg:classifiers":[
        {
            "category":"Communications",
            "subcategory":"Film & Video Production",
            "type":"Services"
        }
    ],
    "sg:phone":"+32 2 657 19 09",
    "sg:postcode":"1560",
    "sg:province":"Vlaams-Brabant",
    "sg:tags":[
        "movie",
        "maker"
    ],
    "wof:name":"Van Leeuw P",
    "wof:placetype":"venue"
},
  "geometry": {"coordinates":[4.4683070183,50.7704658508],"type":"Point"}
}