{
  "type": "Feature",
  "properties": {
    "iso:country":"BE",
    "sg:address":"Koning Leopold Iii-laan 41",
    "sg:city":"Brugge",
    "sg:orig_category":"Traitement de donn\u00e9es",
    "sg:phone":"+32 50 38 88 78",
    "sg:postcode":"8200",
    "sg:province":"West-Vlaanderen",
    "wof:name":"Cevi",
    "wof:placetype":"venue"
},
  "geometry": {"coordinates":[3.1880040169,51.189868927],"type":"Point"}
}