{
  "type": "Feature",
  "properties": {
    "addr:full":"Statiestraat 41-5 Mol Antwerpen 2400",
    "addr:housenumber":"41-5",
    "addr:postcode":"2400",
    "addr:street":"Statiestraat",
    "iso:country":"BE",
    "sg:address":"Statiestraat 41-5",
    "sg:city":"Mol",
    "sg:classifiers":[
        {
            "category":"Health Services",
            "subcategory":"Doctor",
            "type":"Services"
        }
    ],
    "sg:phone":"+32 477 39 16 38",
    "sg:postcode":"2400",
    "sg:province":"Antwerpen",
    "sg:tags":[
        "medicinephysicians",
        "surgeon"
    ],
    "wof:name":"Lemmens Erwin",
    "wof:placetype":"venue"
},
  "geometry": {"coordinates":[5.1170978546,51.1912193298],"type":"Point"}
}