{
  "type": "Feature",
  "properties": {
    "addr:full":"Rue Xavier De Bue 58 Ukkel/uccle Bruxelles-Capitale 1180",
    "addr:housenumber":"58",
    "addr:postcode":"1180",
    "addr:street":"Rue Xavier De Bue;/",
    "iso:country":"BE",
    "sg:address":"Rue Xavier De Bue 58",
    "sg:city":"Ukkel/uccle",
    "sg:orig_category":"V\u00eatements pour Hommes",
    "sg:phone":"+32 2 343 08 97",
    "sg:postcode":"1180",
    "sg:province":"Bruxelles-Capitale",
    "wof:name":"Maison Clyde",
    "wof:placetype":"venue"
},
  "geometry": {"coordinates":[4.3384771347,50.8034934998],"type":"Point"}
}