{
  "type": "Feature",
  "properties": {
    "addr:full":"Langelostraat 111 Lubbeek Vlaams-Brabant 3212",
    "addr:housenumber":"111",
    "addr:postcode":"3212",
    "addr:street":"Langelostraat",
    "iso:country":"BE",
    "sg:address":"Langelostraat 111",
    "sg:city":"Lubbeek",
    "sg:orig_category":"Sportclubs",
    "sg:phone":"+32 16 25 28 63",
    "sg:postcode":"3212",
    "sg:province":"Vlaams-Brabant",
    "wof:name":"Sportcomite K.u.leuven - Waterpolo",
    "wof:placetype":"venue"
},
  "geometry": {"coordinates":[4.763903141,50.8772239685],"type":"Point"}
}