{
  "type": "Feature",
  "properties": {
    "iso:country":"BE",
    "sg:address":"Kon Astridln 138",
    "sg:city":"Gent",
    "sg:classifiers":[
        {
            "category":"Travel",
            "subcategory":"Hotels & Motels",
            "type":"Entertainment"
        }
    ],
    "sg:phone":"+32 9 222 88 36",
    "sg:postcode":"9000",
    "sg:province":"Oost-Vlaanderen",
    "sg:tags":[
        "hotels",
        "business",
        "restaurant"
    ],
    "wof:name":"Carlton Hotel",
    "wof:placetype":"venue"
},
  "geometry": {"coordinates":[3.7139511108,51.0364875793],"type":"Point"}
}