{
  "type": "Feature",
  "properties": {
    "addr:full":"Noordstraat 151 Roeselare West-Vlaanderen 8800",
    "addr:housenumber":"151",
    "addr:postcode":"8800",
    "addr:street":"Noordstraat",
    "iso:country":"BE",
    "sg:address":"Noordstraat 151",
    "sg:city":"Roeselare",
    "sg:orig_category":"Telecommunicatiesystemen",
    "sg:phone":"+32 51 25 34 04",
    "sg:postcode":"8800",
    "sg:province":"West-Vlaanderen",
    "wof:name":"Tele West Int Belgium",
    "wof:placetype":"venue"
},
  "geometry": {"coordinates":[3.1206579208,50.9491615295],"type":"Point"}
}