{
  "type": "Feature",
  "properties": {
    "iso:country":"BE",
    "sg:address":"Stationsstraat 30",
    "sg:city":"Waarschoot",
    "sg:orig_category":"Drukkerijen and copyshops",
    "sg:phone":"+32 9 377 14 54",
    "sg:postcode":"9950",
    "sg:province":"Oost-Vlaanderen",
    "wof:name":"Drukkerij Martens",
    "wof:placetype":"venue"
},
  "geometry": {"coordinates":[3.6089029312,51.1516265869],"type":"Point"}
}