{
  "type": "Feature",
  "properties": {
    "addr:full":"Veeweidestraat 60 Anderlecht Bruxelles-Capitale 1070",
    "addr:housenumber":"60",
    "addr:postcode":"1070",
    "addr:street":"Veeweidestraat",
    "iso:country":"BE",
    "sg:address":"Veeweidestraat 60",
    "sg:city":"Anderlecht",
    "sg:orig_category":"Maatschappelijke dienstverlening Opvangtehuizen and vluchthuizen",
    "sg:phone":"+32 2 523 50 36",
    "sg:postcode":"1070",
    "sg:province":"Bruxelles-Capitale",
    "wof:name":"L'equipe",
    "wof:placetype":"venue"
},
  "geometry": {"coordinates":[4.3057222366,50.8313598633],"type":"Point"}
}