{
  "type": "Feature",
  "properties": {
    "iso:country":"BE",
    "sg:address":"Roeselarestraat 125",
    "sg:city":"Ledegem",
    "sg:orig_category":"Rundveehouders",
    "sg:phone":"+32 56 50 94 93",
    "sg:postcode":"8880",
    "sg:province":"West-Vlaanderen",
    "wof:name":"Valeer Vantomme",
    "wof:placetype":"venue"
},
  "geometry": {"coordinates":[3.1478409767,50.8846054077],"type":"Point"}
}