{
  "type": "Feature",
  "properties": {
    "addr:full":"Waterschootstraat 17 Sint-niklaas Oost-Vlaanderen 9111",
    "addr:housenumber":"17",
    "addr:postcode":"9111",
    "addr:street":"Waterschootstraat",
    "iso:country":"BE",
    "sg:address":"Waterschootstraat 17",
    "sg:city":"Sint-niklaas",
    "sg:orig_category":"Eleveurs de bovins",
    "sg:phone":"+32 3 722 05 75",
    "sg:postcode":"9111",
    "sg:province":"Oost-Vlaanderen",
    "wof:name":"Rooms Johan-de Rijck Lea",
    "wof:placetype":"venue"
},
  "geometry": {"coordinates":[4.1010627747,51.1415519714],"type":"Point"}
}