{
  "type": "Feature",
  "properties": {
    "iso:country":"BE",
    "sg:address":"Rue De Pommard 210",
    "sg:city":"Stavelot",
    "sg:orig_category":"Brood, gebak and snoepgoed Restaurants Verlichting and huishoudartikelen",
    "sg:phone":"+32 87 27 57 08",
    "sg:postcode":"4970",
    "sg:province":"Li\u00e8ge",
    "wof:name":"Boulangerie Albert G.",
    "wof:placetype":"venue"
},
  "geometry": {"coordinates":[5.9531078339,50.4540100098],"type":"Point"}
}