{
  "type": "Feature",
  "properties": {
    "iso:country":"BE",
    "sg:address":"Nieuwstraat 61",
    "sg:city":"Brussel/bruxelles",
    "sg:orig_category":"Baby- and kinderkleding",
    "sg:phone":"+32 2 219 77 31",
    "sg:postcode":"1000",
    "sg:province":"Bruxelles-Capitale",
    "wof:name":"Morgan",
    "wof:placetype":"venue"
},
  "geometry": {"coordinates":[4.3558239937,50.852394104],"type":"Point"}
}