{
  "type": "Feature",
  "properties": {
    "iso:country":"BE",
    "sg:address":"Hertogstraat 198",
    "sg:city":"Leuven",
    "sg:classifiers":[
        {
            "category":"Cafe",
            "type":"Food & Drink"
        }
    ],
    "sg:phone":"+32 16 40 41 33",
    "sg:postcode":"3001",
    "sg:province":"Vlaams-Brabant",
    "sg:tags":[
        "caf\u00e9s"
    ],
    "wof:name":"Cafetaria Sporthal",
    "wof:placetype":"venue"
},
  "geometry": {"coordinates":[4.6959400177,50.8633499146],"type":"Point"}
}