{
  "type": "Feature",
  "properties": {
    "iso:country":"BE",
    "sg:address":"Rue Du Palais 76",
    "sg:city":"Verviers",
    "sg:classifiers":[
        {
            "category":"Health Services",
            "subcategory":"Dentist",
            "type":"Services"
        }
    ],
    "sg:phone":"+32 87 22 29 03",
    "sg:postcode":"4800",
    "sg:province":"Li\u00e8ge",
    "wof:name":"Mashshini J",
    "wof:placetype":"venue"
},
  "geometry": {"coordinates":[5.8602910042,50.5899238586],"type":"Point"}
}