{
  "type": "Feature",
  "properties": {
    "iso:country":"BE",
    "sg:address":"Avenue Des Foug\u00e8res 10",
    "sg:city":"Wavre (bierges)",
    "sg:classifiers":[
        {
            "category":"Real Estate",
            "subcategory":"Real Estate Services",
            "type":"Services"
        }
    ],
    "sg:phone":"+32 10 43 54 54",
    "sg:postcode":"1301",
    "sg:province":"Brabant Wallon",
    "wof:name":"Jacquemin Sprl",
    "wof:placetype":"venue"
},
  "geometry": {"coordinates":[4.6111979485,50.7019920349],"type":"Point"}
}