{
  "type": "Feature",
  "properties": {
    "iso:country":"BE",
    "sg:address":"Peter Becker Strasse 44",
    "sg:city":"Eupen",
    "sg:classifiers":[
        {
            "category":"Professional",
            "subcategory":"Management & Consulting",
            "type":"Services"
        }
    ],
    "sg:phone":"+32 87 55 85 14",
    "sg:postcode":"4700",
    "sg:province":"Li\u00e8ge",
    "sg:tags":[
        "consultant",
        "law"
    ],
    "wof:name":"Hilgers Rolf Gbr Sprlu",
    "wof:placetype":"venue"
},
  "geometry": {"coordinates":[6.0480628014,50.6288833618],"type":"Point"}
}