{
  "type": "Feature",
  "properties": {
    "iso:country":"BE",
    "sg:address":"Dorpstraat 128",
    "sg:city":"Bredene",
    "sg:orig_category":"Dierentuinen, botanische tuinen, sterrenwachten and natuurreservaten",
    "sg:phone":"+32 59 32 06 49",
    "sg:postcode":"8450",
    "sg:province":"West-Vlaanderen",
    "wof:name":"Paelsteenpanne (bredene)",
    "wof:placetype":"venue"
},
  "geometry": {"coordinates":[2.9779689312,51.2347450256],"type":"Point"}
}