{
  "type": "Feature",
  "properties": {
    "addr:full":"Gentseweg 567 Waregem West-Vlaanderen 8793",
    "addr:housenumber":"567",
    "addr:postcode":"8793",
    "addr:street":"Gentseweg",
    "iso:country":"BE",
    "sg:address":"Gentseweg 567",
    "sg:city":"Waregem",
    "sg:orig_category":"V\u00e9hicules automobiles",
    "sg:phone":"+32 56 60 44 37",
    "sg:postcode":"8793",
    "sg:province":"West-Vlaanderen",
    "wof:name":"Garage Lefevre Gebrs",
    "wof:placetype":"venue"
},
  "geometry": {"coordinates":[3.3988740444,50.8983840942],"type":"Point"}
}