{
  "type": "Feature",
  "properties": {
    "addr:full":"Kleineweg 227 Roeselare West-Vlaanderen 8800",
    "addr:housenumber":"227",
    "addr:postcode":"8800",
    "addr:street":"Kleineweg",
    "iso:country":"BE",
    "sg:address":"Kleineweg 227",
    "sg:city":"Roeselare",
    "sg:orig_category":"Groenten and fruit Gh",
    "sg:phone":"+32 51 22 43 92",
    "sg:postcode":"8800",
    "sg:province":"West-Vlaanderen",
    "wof:name":"Fa. Asselman Jozef & Zn",
    "wof:placetype":"venue"
},
  "geometry": {"coordinates":[3.1090180874,50.9280548096],"type":"Point"}
}