{
  "type": "Feature",
  "properties": {
    "iso:country":"BE",
    "sg:address":"Zoot 71",
    "sg:city":"Aarschot",
    "sg:orig_category":"Bijouteries and horlogeries",
    "sg:phone":"+32 16 50 16 67",
    "sg:postcode":"3202",
    "sg:province":"Vlaams-Brabant",
    "wof:name":"Crazy Or",
    "wof:placetype":"venue"
},
  "geometry": {"coordinates":[4.9167661667,50.9793624878],"type":"Point"}
}