{
  "type": "Feature",
  "properties": {
    "addr:full":"Rue Du Bac 23 Weismes Li\u00e8ge 4950",
    "addr:housenumber":"23",
    "addr:postcode":"4950",
    "addr:street":"Rue Du Bac",
    "iso:country":"BE",
    "sg:address":"Rue Du Bac 23",
    "sg:city":"Weismes",
    "sg:classifiers":[
        {
            "category":"Home & Garden",
            "subcategory":"Carpets & Floor Coverings",
            "type":"Retail Goods"
        }
    ],
    "sg:phone":"+32 80 67 80 45",
    "sg:postcode":"4950",
    "sg:province":"Li\u00e8ge",
    "sg:tags":[
        "tile"
    ],
    "wof:name":"Rosen Charles Sa",
    "wof:placetype":"venue"
},
  "geometry": {"coordinates":[6.1044912338,50.4124221802],"type":"Point"}
}