{
  "type": "Feature",
  "properties": {
    "addr:full":"Markt 38 Lokeren Oost-Vlaanderen 9160",
    "addr:housenumber":"38",
    "addr:postcode":"9160",
    "addr:street":"Markt",
    "iso:country":"BE",
    "sg:address":"Markt 38",
    "sg:city":"Lokeren",
    "sg:classifiers":[
        {
            "category":"Shopping",
            "subcategory":"Music",
            "type":"Retail Goods"
        }
    ],
    "sg:phone":"+32 9 348 39 03",
    "sg:postcode":"9160",
    "sg:province":"Oost-Vlaanderen",
    "sg:tags":[
        "-",
        "cd's",
        "recorded",
        "cassette"
    ],
    "wof:name":"Fonotheek/cd Discount",
    "wof:placetype":"venue"
},
  "geometry": {"coordinates":[3.9905600548,51.1041374207],"type":"Point"}
}