{
  "type": "Feature",
  "properties": {
    "addr:full":"Battelsesteenweg 291 Mechelen Antwerpen 2800",
    "addr:housenumber":"291",
    "addr:postcode":"2800",
    "addr:street":"Battelsesteenweg",
    "iso:country":"BE",
    "sg:address":"Battelsesteenweg 291",
    "sg:city":"Mechelen",
    "sg:orig_category":"R\u00e9parations d'appareils \u00e9lectrom\u00e9nagers. Electrom\u00e9nager, t\u00e9l\u00e9visions and radios",
    "sg:phone":"+32 15 27 73 32",
    "sg:postcode":"2800",
    "sg:province":"Antwerpen",
    "wof:name":"Makri",
    "wof:placetype":"venue"
},
  "geometry": {"coordinates":[4.4596338272,51.0320396423],"type":"Point"}
}