{
  "type": "Feature",
  "properties": {
    "iso:country":"BE",
    "sg:address":"Rue De La Pompe 10",
    "sg:city":"Pepinster",
    "sg:classifiers":[
        {
            "category":"Professional",
            "subcategory":"Art Services",
            "type":"Services"
        }
    ],
    "sg:phone":"+32 87 46 91 00",
    "sg:postcode":"4860",
    "sg:province":"Li\u00e8ge",
    "sg:tags":[
        "sculptor"
    ],
    "wof:name":"Dubois J",
    "wof:placetype":"venue"
},
  "geometry": {"coordinates":[5.8011240959,50.5680046082],"type":"Point"}
}