{
  "type": "Feature",
  "properties": {
    "iso:country":"BE",
    "sg:address":"Avenue Eug\u00c8ne Mascaux 274",
    "sg:city":"Charleroi",
    "sg:orig_category":"Supermarkten",
    "sg:postcode":"6001",
    "sg:province":"Hainaut",
    "wof:name":"Aldi",
    "wof:placetype":"venue"
},
  "geometry": {"coordinates":[4.4392380714,50.3925971985],"type":"Point"}
}