{
  "type": "Feature",
  "properties": {
    "iso:country":"BE",
    "sg:address":"Vijverlei 11",
    "sg:city":"Schoten",
    "sg:classifiers":[
        {
            "category":"Building & Trades",
            "subcategory":"Equipment Rental",
            "type":"Services"
        }
    ],
    "sg:phone":"+32 3 658 28 49",
    "sg:postcode":"2900",
    "sg:province":"Antwerpen",
    "sg:tags":[
        "sound",
        "-",
        "system"
    ],
    "wof:name":"Stage Support",
    "wof:placetype":"venue"
},
  "geometry": {"coordinates":[4.5324659348,51.2598152161],"type":"Point"}
}