{
  "type": "Feature",
  "properties": {
    "addr:full":"Weertersteenweg 433 Kinrooi Limburg 3640",
    "addr:housenumber":"433",
    "addr:postcode":"3640",
    "addr:street":"Weertersteenweg",
    "iso:country":"BE",
    "sg:address":"Weertersteenweg 433",
    "sg:city":"Kinrooi",
    "sg:orig_category":"Woningbouw",
    "sg:phone":"+32 89 70 36 65",
    "sg:postcode":"3640",
    "sg:province":"Limburg",
    "wof:name":"Jacobus Stultjens",
    "wof:placetype":"venue"
},
  "geometry": {"coordinates":[5.7421097755,51.1599807739],"type":"Point"}
}