{
  "type": "Feature",
  "properties": {
    "addr:full":"Nieuwstraat 80 Essen Antwerpen 2910",
    "addr:housenumber":"80",
    "addr:postcode":"2910",
    "addr:street":"Nieuwstraat",
    "iso:country":"BE",
    "sg:address":"Nieuwstraat 80",
    "sg:city":"Essen",
    "sg:orig_category":"RESTAURANTS: CR\u00c9MERIES",
    "sg:phone":"+32 3 667 41 89",
    "sg:postcode":"2910",
    "sg:province":"Antwerpen",
    "wof:name":"Ijssalon Rustique",
    "wof:placetype":"venue"
},
  "geometry": {"coordinates":[4.4669809341,51.4690628052],"type":"Point"}
}