{
  "type": "Feature",
  "properties": {
    "iso:country":"BE",
    "sg:address":"Vieux Chemin De Willems 40",
    "sg:city":"Tournai",
    "sg:classifiers":[
        {
            "category":"Health Services",
            "subcategory":"Doctor",
            "type":"Services"
        }
    ],
    "sg:phone":"+32 69 84 49 05",
    "sg:postcode":"7500",
    "sg:province":"Hainaut",
    "sg:tags":[
        "medicinephysicians",
        "surgeon"
    ],
    "wof:name":"Dailliet Alexandre",
    "wof:placetype":"venue"
},
  "geometry": {"coordinates":[3.3593800068,50.6126060486],"type":"Point"}
}