{
  "type": "Feature",
  "properties": {
    "addr:full":"Rue Montgommery 36 Kain Hainaut 7540",
    "addr:housenumber":"36",
    "addr:postcode":"7540",
    "addr:street":"Rue Montgommery",
    "iso:country":"BE",
    "sg:address":"Rue Montgommery 36",
    "sg:city":"Kain",
    "sg:classifiers":[
        {
            "category":"Government",
            "subcategory":"Fire Station",
            "type":"Public Place"
        }
    ],
    "sg:phone":"+32 69 84 29 35",
    "sg:postcode":"7540",
    "sg:province":"Hainaut",
    "sg:tags":[
        "packard",
        "nec",
        "bell"
    ],
    "wof:name":"Ati Informatique",
    "wof:placetype":"venue"
},
  "geometry": {"coordinates":[3.3823139668,50.6308479309],"type":"Point"}
}