{
  "type": "Feature",
  "properties": {
    "iso:country":"BE",
    "sg:address":"Rue Du Saupont 86",
    "sg:city":"Bertrix",
    "sg:orig_category":"Plaatsen van vloer- and muurbekleding Schilders",
    "sg:phone":"+32 61 41 52 13",
    "sg:postcode":"6880",
    "sg:province":"Luxembourg",
    "wof:name":"Philippe Cattrysse",
    "wof:placetype":"venue"
},
  "geometry": {"coordinates":[5.2777547836,49.851776123],"type":"Point"}
}