{
  "type": "Feature",
  "properties": {
    "iso:country":"BE",
    "sg:address":"Rue Fonds Cattelain 4",
    "sg:city":"Mont-saint-guibert",
    "sg:orig_category":"Autokeuringen",
    "sg:phone":"+32 10 65 45 30",
    "sg:postcode":"1435",
    "sg:province":"Brabant Wallon",
    "wof:name":"Contr\u00d4le Technique Automobile",
    "wof:placetype":"venue"
},
  "geometry": {"coordinates":[4.6253390312,50.6568222046],"type":"Point"}
}