{
  "type": "Feature",
  "properties": {
    "addr:full":"Zarrenstraat 4 Kortemark West-Vlaanderen 8610",
    "addr:housenumber":"4",
    "addr:postcode":"8610",
    "addr:street":"Zarrenstraat",
    "iso:country":"BE",
    "sg:address":"Zarrenstraat 4",
    "sg:city":"Kortemark",
    "sg:orig_category":"Binnenhuisarchitecten Diverse grafische activiteiten",
    "sg:phone":"+32 51 57 18 84",
    "sg:postcode":"8610",
    "sg:province":"West-Vlaanderen",
    "wof:name":"Ontwerpburo Jan Gerard",
    "wof:placetype":"venue"
},
  "geometry": {"coordinates":[2.959100008,51.0186653137],"type":"Point"}
}