{
  "type": "Feature",
  "properties": {
    "addr:full":"Zuidstraat 90 Brussel/bruxelles Bruxelles-Capitale 1000",
    "addr:housenumber":"90",
    "addr:postcode":"1000",
    "addr:street":"Zuidstraat;/",
    "iso:country":"BE",
    "sg:address":"Zuidstraat 90",
    "sg:city":"Brussel/bruxelles",
    "sg:orig_category":"Bloemen and planten",
    "sg:phone":"+32 2 513 99 96",
    "sg:postcode":"1000",
    "sg:province":"Bruxelles-Capitale",
    "wof:name":"Caloggero Fiori",
    "wof:placetype":"venue"
},
  "geometry": {"coordinates":[4.3420138359,50.837600708],"type":"Point"}
}