{
  "type": "Feature",
  "properties": {
    "iso:country":"BE",
    "sg:address":"Chemin Du Soyeureux 5",
    "sg:city":"Spa",
    "sg:classifiers":[
        {
            "category":"Travel",
            "subcategory":"Hotels & Motels",
            "type":"Entertainment"
        }
    ],
    "sg:phone":"+32 87 77 11 53",
    "sg:postcode":"4900",
    "sg:province":"Li\u00e8ge",
    "wof:name":"Pension Des Sources Sprl",
    "wof:placetype":"venue"
},
  "geometry": {"coordinates":[5.8916101456,50.499206543],"type":"Point"}
}