{
  "type": "Feature",
  "properties": {
    "addr:full":"Provinciaal Domein Genk Limburg 3600",
    "addr:postcode":"3600",
    "addr:street":"Limburg",
    "iso:country":"BE",
    "sg:address":"Provinciaal Domein",
    "sg:city":"Genk",
    "sg:orig_category":"Mus\u00e9es and patrimoine culturel. Installations and terrains de sport hors centres sportifs. Jardins b",
    "sg:phone":"+32 11 26 53 00",
    "sg:postcode":"3600",
    "sg:province":"Limburg",
    "wof:name":"Bokrijk",
    "wof:placetype":"venue"
},
  "geometry": {"coordinates":[5.4990148544,50.9635848999],"type":"Point"}
}