{
  "type": "Feature",
  "properties": {
    "addr:full":"Begijnenstraat 50 Turnhout Antwerpen 2300",
    "addr:housenumber":"50",
    "addr:postcode":"2300",
    "addr:street":"Begijnenstraat",
    "iso:country":"BE",
    "sg:address":"Begijnenstraat 50",
    "sg:city":"Turnhout",
    "sg:orig_category":"Activit\u00e9s d\u00b4action sociale sans h\u00e9bergement",
    "sg:phone":"+32 14 41 42 16",
    "sg:postcode":"2300",
    "sg:province":"Antwerpen",
    "wof:name":"Vclb-centrum",
    "wof:placetype":"venue"
},
  "geometry": {"coordinates":[4.9473347664,51.3255958557],"type":"Point"}
}