{
  "type": "Feature",
  "properties": {
    "iso:country":"BE",
    "sg:address":"Petite Rue 157",
    "sg:city":"Meix-devant-virton (g\u00e9rouville)",
    "sg:classifiers":[
        {
            "category":"Arts & Performance",
            "subcategory":"Theater",
            "type":"Entertainment"
        }
    ],
    "sg:phone":"+32 63 57 09 19",
    "sg:postcode":"6769",
    "sg:province":"Luxembourg",
    "sg:tags":[
        "group",
        "theatre"
    ],
    "wof:name":"Grand Asile (le)",
    "wof:placetype":"venue"
},
  "geometry": {"coordinates":[5.4277410507,49.6202812195],"type":"Point"}
}