{
  "type": "Feature",
  "properties": {
    "iso:country":"BE",
    "sg:address":"Chauss\u00c9e De Bruxelles 391",
    "sg:city":"Edingen/enghien",
    "sg:orig_category":"Disquaires",
    "sg:phone":"+32 2 395 35 17",
    "sg:postcode":"7850",
    "sg:province":"Hainaut",
    "wof:name":"Alexandre Ferrigolo",
    "wof:placetype":"venue"
},
  "geometry": {"coordinates":[4.0549092293,50.691619873],"type":"Point"}
}