{
  "type": "Feature",
  "properties": {
    "iso:country":"BE",
    "sg:address":"Rue Aux Cailloux 1",
    "sg:city":"Ittre",
    "sg:orig_category":"Installation \u00e9lectrique r\u00e9sidentielle",
    "sg:phone":"+32 67 21 51 98",
    "sg:postcode":"1461",
    "sg:province":"Brabant Wallon",
    "wof:name":"Fe. B. & C.",
    "wof:placetype":"venue"
},
  "geometry": {"coordinates":[4.2840380669,50.6547355652],"type":"Point"}
}