{
  "type": "Feature",
  "properties": {
    "addr:full":"Eksaarde Dorp 84 Lokeren (eksaarde) Oost-Vlaanderen 9160",
    "addr:housenumber":"84",
    "addr:postcode":"9160",
    "addr:street":"Eksaarde Dorp;Lokeren Eksaarde Oost-Vlaanderen",
    "iso:country":"BE",
    "sg:address":"Eksaarde Dorp 84",
    "sg:city":"Lokeren (eksaarde)",
    "sg:classifiers":[
        {
            "category":"Professional",
            "subcategory":"Lawyer & Legal Services",
            "type":"Services"
        }
    ],
    "sg:phone":"+32 9 346 82 93",
    "sg:postcode":"9160",
    "sg:province":"Oost-Vlaanderen",
    "sg:tags":[
        "notary"
    ],
    "wof:name":"De Brabander P",
    "wof:placetype":"venue"
},
  "geometry": {"coordinates":[3.9634549618,51.1214942932],"type":"Point"}
}