{
  "type": "Feature",
  "properties": {
    "addr:full":"Karel Van Manderstraat 4 Meulebeke West-Vlaanderen 8760",
    "addr:housenumber":"4",
    "addr:postcode":"8760",
    "addr:street":"Karel Van Manderstraat",
    "iso:country":"BE",
    "sg:address":"Karel Van Manderstraat 4",
    "sg:city":"Meulebeke",
    "sg:classifiers":[
        {
            "category":"Home & Garden",
            "subcategory":"Hardware",
            "type":"Retail Goods"
        }
    ],
    "sg:phone":"+32 51 48 81 90",
    "sg:postcode":"8760",
    "sg:province":"West-Vlaanderen",
    "sg:tags":[
        "gate",
        "opener",
        "door",
        "automatic"
    ],
    "wof:name":"Filiporter Bvba",
    "wof:placetype":"venue"
},
  "geometry": {"coordinates":[3.2895541191,50.9496002197],"type":"Point"}
}