{
  "type": "Feature",
  "properties": {
    "addr:full":"Rue De La Ferme 41b21 Ans Li\u00e8ge 4430",
    "addr:housenumber":"41b21",
    "addr:postcode":"4430",
    "addr:street":"Rue De La Ferme",
    "iso:country":"BE",
    "sg:address":"Rue De La Ferme 41b21",
    "sg:city":"Ans",
    "sg:classifiers":[
        {
            "category":"Arena",
            "subcategory":"Sports Club",
            "type":"Entertainment"
        }
    ],
    "sg:phone":"+32 4 246 35 57",
    "sg:postcode":"4430",
    "sg:province":"Li\u00e8ge",
    "sg:tags":[
        "terrain",
        "hors",
        "de",
        "installation",
        "sportifs"
    ],
    "wof:name":"C.r.s. De La B.b.l. Li\u00c8ge",
    "wof:placetype":"venue"
},
  "geometry": {"coordinates":[5.5185070038,50.6559371948],"type":"Point"}
}