{
  "type": "Feature",
  "properties": {
    "addr:full":"Trieu \u00c0 Vall\u00c9e 74 La Louvi\u00c8re (groot) Hainaut 7110",
    "addr:housenumber":"74",
    "addr:postcode":"7110",
    "addr:street":"La;Groot Hainaut",
    "iso:country":"BE",
    "sg:address":"Trieu \u00c0 Vall\u00c9e 74",
    "sg:city":"La Louvi\u00c8re (groot)",
    "sg:orig_category":"Kapsalons",
    "sg:phone":"+32 64 22 97 95",
    "sg:postcode":"7110",
    "sg:province":"Hainaut",
    "wof:name":"Coiffure Anne Marie",
    "wof:placetype":"venue"
},
  "geometry": {"coordinates":[4.1505050659,50.4826698303],"type":"Point"}
}