{
  "type": "Feature",
  "properties": {
    "iso:country":"BE",
    "sg:address":"Chauss\u00e9e De Gand 119",
    "sg:city":"Bruxelles (molenbeek-saint-jean)",
    "sg:classifiers":[
        {
            "category":"Shopping",
            "subcategory":"Music",
            "type":"Retail Goods"
        }
    ],
    "sg:phone":"+32 2 411 72 02",
    "sg:postcode":"1080",
    "sg:province":"Bruxelles-Capitale",
    "sg:tags":[
        "-",
        "cd's",
        "recorded",
        "cassette"
    ],
    "wof:name":"Atlas Music",
    "wof:placetype":"venue"
},
  "geometry": {"coordinates":[4.3359799385,50.8552093506],"type":"Point"}
}