{
  "type": "Feature",
  "properties": {
    "iso:country":"BE",
    "sg:address":"Populierenhof 72",
    "sg:city":"Sint-lambrechts-woluwe/woluwe-saint-lambert",
    "sg:orig_category":"Slagers",
    "sg:phone":"+32 2 770 83 68",
    "sg:postcode":"1200",
    "sg:province":"Bruxelles-Capitale",
    "wof:name":"Boucherie Bart",
    "wof:placetype":"venue"
},
  "geometry": {"coordinates":[4.4377241135,50.8530197144],"type":"Point"}
}