{
  "type": "Feature",
  "properties": {
    "addr:full":"Rue Du Pont Pavot 42 Couvin (frasnes) Namur 5660",
    "addr:housenumber":"42",
    "addr:postcode":"5660",
    "addr:street":"Rue Du Pont Pavot",
    "iso:country":"BE",
    "sg:address":"Rue Du Pont Pavot 42",
    "sg:city":"Couvin (frasnes)",
    "sg:classifiers":[
        {
            "category":"Home & Garden",
            "subcategory":"Home Furnishings",
            "type":"Retail Goods"
        }
    ],
    "sg:phone":"+32 60 31 16 38",
    "sg:postcode":"5660",
    "sg:province":"Namur",
    "sg:tags":[
        "-",
        "furniture"
    ],
    "wof:name":"Kennis Meubles",
    "wof:placetype":"venue"
},
  "geometry": {"coordinates":[4.4966731071,50.0532150269],"type":"Point"}
}