{
  "type": "Feature",
  "properties": {
    "addr:full":"Rue De La Copette 23 Houffalize (wibrin) Luxembourg 6666",
    "addr:housenumber":"23",
    "addr:postcode":"6666",
    "addr:street":"Rue De La Copette",
    "iso:country":"BE",
    "sg:address":"Rue De La Copette 23",
    "sg:city":"Houffalize (wibrin)",
    "sg:classifiers":[
        {
            "category":"Health Services",
            "subcategory":"Dentist",
            "type":"Services"
        }
    ],
    "sg:phone":"+32 61 28 86 03",
    "sg:postcode":"6666",
    "sg:province":"Luxembourg",
    "wof:name":"Docquier Marc",
    "wof:placetype":"venue"
},
  "geometry": {"coordinates":[5.7208809853,50.1656913757],"type":"Point"}
}