{
  "type": "Feature",
  "properties": {
    "iso:country":"BE",
    "sg:address":"Lijsterlaan 20",
    "sg:city":"Ternat (sint-katherina-lombeek)",
    "sg:classifiers":[
        {
            "category":"Social Services",
            "type":"Services"
        }
    ],
    "sg:phone":"+32 2 582 11 00",
    "sg:postcode":"1742",
    "sg:province":"Vlaams-Brabant",
    "wof:name":"Begeleid Wonen Pajottenland Vzw",
    "wof:placetype":"venue"
},
  "geometry": {"coordinates":[4.1567568779,50.8679428101],"type":"Point"}
}