{
  "type": "Feature",
  "properties": {
    "addr:full":"Varensbos 4 Lovendegem Oost-Vlaanderen 9920",
    "addr:housenumber":"4",
    "addr:postcode":"9920",
    "addr:street":"Varensbos",
    "iso:country":"BE",
    "sg:address":"Varensbos 4",
    "sg:city":"Lovendegem",
    "sg:classifiers":[
        {
            "category":"Home & Garden",
            "subcategory":"Carpets & Floor Coverings",
            "type":"Retail Goods"
        }
    ],
    "sg:phone":"+32 9 372 53 39",
    "sg:postcode":"9920",
    "sg:province":"Oost-Vlaanderen",
    "sg:tags":[
        "layer",
        "mosaicists"
    ],
    "wof:name":"Bogaert L",
    "wof:placetype":"venue"
},
  "geometry": {"coordinates":[3.6165568829,51.1171417236],"type":"Point"}
}