{
  "type": "Feature",
  "properties": {
    "iso:country":"BE",
    "sg:address":"Oude-hoeveweg 10",
    "sg:city":"Brasschaat",
    "sg:classifiers":[
        {
            "category":"Transit Center",
            "subcategory":"Freight",
            "type":"Transportation"
        }
    ],
    "sg:phone":"+32 3 295 62 68",
    "sg:postcode":"2930",
    "sg:province":"Antwerpen",
    "sg:tags":[
        "import",
        "export",
        "-"
    ],
    "wof:name":"Tracobel Bvba",
    "wof:placetype":"venue"
},
  "geometry": {"coordinates":[4.5058078766,51.2934532166],"type":"Point"}
}