{
  "type": "Feature",
  "properties": {
    "iso:country":"BE",
    "sg:address":"Hermans-lybaertstraat 35",
    "sg:city":"Knokke-heist",
    "sg:orig_category":"R\u00e9parations d'appareils \u00e9lectrom\u00e9nagers. Electrom\u00e9nager, t\u00e9l\u00e9visions and radios",
    "sg:phone":"+32 50 51 34 94",
    "sg:postcode":"8301",
    "sg:province":"West-Vlaanderen",
    "wof:name":"Roger Dewulf",
    "wof:placetype":"venue"
},
  "geometry": {"coordinates":[3.2639000416,51.3396911621],"type":"Point"}
}