{
  "type": "Feature",
  "properties": {
    "addr:full":"Kloosterstraat 42 Antwerpen (ekeren) Antwerpen 2180",
    "addr:housenumber":"42",
    "addr:postcode":"2180",
    "addr:street":"Kloosterstraat",
    "iso:country":"BE",
    "sg:address":"Kloosterstraat 42",
    "sg:city":"Antwerpen (ekeren)",
    "sg:classifiers":[
        {
            "category":"Shopping",
            "subcategory":"Clothing, Apparel, & Fashions",
            "type":"Retail Goods"
        }
    ],
    "sg:phone":"+32 3 541 09 60",
    "sg:postcode":"2180",
    "sg:province":"Antwerpen",
    "sg:tags":[
        "underwear",
        "lingerie",
        "-"
    ],
    "wof:name":"Bodyline",
    "wof:placetype":"venue"
},
  "geometry": {"coordinates":[4.3949217796,51.2163162231],"type":"Point"}
}