{
  "type": "Feature",
  "properties": {
    "iso:country":"BE",
    "sg:address":"Rue Alz\u00e9mont 33",
    "sg:city":"Nivelles (baulers)",
    "sg:classifiers":[
        {
            "category":"Manufacturing",
            "subcategory":"Pottery",
            "type":"Manufacturing & Wholesale Goods"
        }
    ],
    "sg:phone":"+32 67 21 42 63",
    "sg:postcode":"1401",
    "sg:province":"Brabant Wallon",
    "sg:tags":[
        "facing",
        "brick"
    ],
    "wof:name":"Marin",
    "wof:placetype":"venue"
},
  "geometry": {"coordinates":[4.3616948128,50.6088905334],"type":"Point"}
}