{
  "type": "Feature",
  "properties": {
    "addr:full":"Koningin Astridstraat 8 Tremelo Vlaams-Brabant 3120",
    "addr:housenumber":"8",
    "addr:postcode":"3120",
    "addr:street":"Koningin Astridstraat",
    "iso:country":"BE",
    "sg:address":"Koningin Astridstraat 8",
    "sg:city":"Tremelo",
    "sg:classifiers":[
        {
            "category":"Shopping",
            "subcategory":"Clothing, Apparel, & Fashions",
            "type":"Retail Goods"
        }
    ],
    "sg:phone":"+32 16 53 89 71",
    "sg:postcode":"3120",
    "sg:province":"Vlaams-Brabant",
    "sg:tags":[
        "underwear",
        "lingerie",
        "-"
    ],
    "wof:name":"Lauremi (lingerie)",
    "wof:placetype":"venue"
},
  "geometry": {"coordinates":[4.7061581612,50.9913864136],"type":"Point"}
}