{
  "type": "Feature",
  "properties": {
    "addr:full":"Rue De Courtrai 72 Mouscron Hainaut 7700",
    "addr:housenumber":"72",
    "addr:postcode":"7700",
    "addr:street":"Rue De Courtrai",
    "iso:country":"BE",
    "sg:address":"Rue De Courtrai 72",
    "sg:city":"Mouscron",
    "sg:classifiers":[
        {
            "category":"Building & Trades",
            "subcategory":"Construction",
            "type":"Services"
        }
    ],
    "sg:phone":"+32 56 33 24 09",
    "sg:postcode":"7700",
    "sg:province":"Hainaut",
    "sg:tags":[
        "truss-makers"
    ],
    "wof:name":"Baelen T",
    "wof:placetype":"venue"
},
  "geometry": {"coordinates":[3.2191009521,50.7457313538],"type":"Point"}
}