{
  "type": "Feature",
  "properties": {
    "addr:full":"Fran\u00e7ois Demarsinstraat 21 Leuven (wilsele) Vlaams-Brabant 3012",
    "addr:housenumber":"21",
    "addr:postcode":"3012",
    "addr:street":"Franc\u0327Ois Demarsinstraat",
    "iso:country":"BE",
    "sg:address":"Fran\u00e7ois Demarsinstraat 21",
    "sg:city":"Leuven (wilsele)",
    "sg:classifiers":[
        {
            "category":"Home & Garden",
            "subcategory":"Home Furnishings",
            "type":"Retail Goods"
        }
    ],
    "sg:phone":"+32 16 23 98 28",
    "sg:postcode":"3012",
    "sg:province":"Vlaams-Brabant",
    "sg:tags":[
        "interior",
        "decoration"
    ],
    "wof:name":"Carbon Design",
    "wof:placetype":"venue"
},
  "geometry": {"coordinates":[4.6954717636,50.9045143127],"type":"Point"}
}