{
  "type": "Feature",
  "properties": {
    "addr:full":"Rue E. Mathieu 38 Saint-ghislain Hainaut 7333",
    "addr:housenumber":"38",
    "addr:postcode":"7333",
    "addr:street":"Rue E. Mathieu;Hainaut",
    "iso:country":"BE",
    "sg:address":"Rue E. Mathieu 38",
    "sg:city":"Saint-ghislain",
    "sg:orig_category":"Ecoles de pilotage de bateaux and d\u00b4avions",
    "sg:phone":"+32 476 26 79 80",
    "sg:postcode":"7333",
    "sg:province":"Hainaut",
    "wof:name":"Les Ailes Du Levant",
    "wof:placetype":"venue"
},
  "geometry": {"coordinates":[3.8111400604,50.4655151367],"type":"Point"}
}