{
  "type": "Feature",
  "properties": {
    "iso:country":"BE",
    "sg:address":"Baron Ruzettelaan 266b4",
    "sg:city":"Brugge",
    "sg:orig_category":"Artsen and specialisten",
    "sg:phone":"+32 50 35 85 45",
    "sg:postcode":"8310",
    "sg:province":"West-Vlaanderen",
    "wof:name":"B. Smis",
    "wof:placetype":"venue"
},
  "geometry": {"coordinates":[3.2332749367,51.1899299622],"type":"Point"}
}