{
  "type": "Feature",
  "properties": {
    "iso:country":"BE",
    "sg:address":"Hallebaan 5",
    "sg:city":"Ranst (oelegem)",
    "sg:classifiers":[
        {
            "category":"Parking",
            "subcategory":"Lot",
            "type":"Transportation"
        }
    ],
    "sg:phone":"+32 3 385 41 44",
    "sg:postcode":"2520",
    "sg:province":"Antwerpen",
    "sg:tags":[
        "parking-places",
        "laying-out"
    ],
    "wof:name":"Huybrechts Ivo",
    "wof:placetype":"venue"
},
  "geometry": {"coordinates":[4.6166648865,51.2149047852],"type":"Point"}
}