{
  "type": "Feature",
  "properties": {
    "addr:full":"Kraaienhoflaan 23 Zwijndrecht (burcht) Antwerpen 2070",
    "addr:housenumber":"23",
    "addr:postcode":"2070",
    "addr:street":"Kraaienhoflaan;Burcht",
    "iso:country":"BE",
    "sg:address":"Kraaienhoflaan 23",
    "sg:city":"Zwijndrecht (burcht)",
    "sg:classifiers":[
        {
            "category":"Professional",
            "subcategory":"Engineering",
            "type":"Services"
        }
    ],
    "sg:phone":"+32 3 271 11 36",
    "sg:postcode":"2070",
    "sg:province":"Antwerpen",
    "sg:tags":[
        "industrial",
        "-",
        "automation"
    ],
    "wof:name":"Consutec",
    "wof:placetype":"venue"
},
  "geometry": {"coordinates":[4.3430900574,51.2075233459],"type":"Point"}
}