{
  "type": "Feature",
  "properties": {
    "iso:country":"BE",
    "sg:address":"Rue D'armenti\u00c8res 80",
    "sg:city":"Komen-waasten/comines-warneton",
    "sg:orig_category":"Eleveurs de bovins",
    "sg:phone":"+32 56 58 86 57",
    "sg:postcode":"7782",
    "sg:province":"Hainaut",
    "wof:name":"Lionel Taillieu/taillieu",
    "wof:placetype":"venue"
},
  "geometry": {"coordinates":[2.882627964,50.722076416],"type":"Point"}
}