{
  "type": "Feature",
  "properties": {
    "addr:full":"Avenue Seghers 105 Koekelberg Bruxelles-Capitale 1081",
    "addr:housenumber":"105",
    "addr:postcode":"1081",
    "addr:street":"Avenue Seghers",
    "iso:country":"BE",
    "sg:address":"Avenue Seghers 105",
    "sg:city":"Koekelberg",
    "sg:classifiers":[
        {
            "category":"Fast Food",
            "type":"Food & Drink"
        }
    ],
    "sg:phone":"+32 2 414 68 61",
    "sg:postcode":"1081",
    "sg:province":"Bruxelles-Capitale",
    "sg:tags":[
        "\u00c0",
        "restaurants",
        "emporter",
        "restaurant"
    ],
    "wof:name":"Le Liseron D'eau",
    "wof:placetype":"venue"
},
  "geometry": {"coordinates":[4.320130825,50.8647422791],"type":"Point"}
}