{
  "type": "Feature",
  "properties": {
    "iso:country":"BE",
    "sg:address":"Barri\u00c8re-hinck 2",
    "sg:city":"Sainte-ode",
    "sg:orig_category":"Entretien et r\u00e9parations de v\u00e9hicules \u00e0 domicile. Entretien and r\u00e9parations de voitures. R\u00e9cup\u00e9ratio",
    "sg:phone":"+32 61 68 86 45",
    "sg:postcode":"6680",
    "sg:province":"Luxembourg",
    "wof:name":"Bastien",
    "wof:placetype":"venue"
},
  "geometry": {"coordinates":[5.5657072067,50.0461959839],"type":"Point"}
}