{
  "type": "Feature",
  "properties": {
    "iso:country":"BE",
    "sg:address":"Bonair 5",
    "sg:city":"Onhaye",
    "sg:orig_category":"G\u00e9om\u00e8tres. Eleveurs de bovins",
    "sg:phone":"+32 82 64 45 88",
    "sg:postcode":"5520",
    "sg:province":"Namur",
    "wof:name":"Gerard Cox",
    "wof:placetype":"venue"
},
  "geometry": {"coordinates":[4.8413968086,50.2428703308],"type":"Point"}
}