{
  "type": "Feature",
  "properties": {
    "iso:country":"BE",
    "sg:address":"P. Steenssensstraat 41",
    "sg:city":"Beveren",
    "sg:orig_category":"Pain, p\u00e2tisseries and confiseries",
    "sg:phone":"+32 3 775 94 97",
    "sg:postcode":"9120",
    "sg:province":"Oost-Vlaanderen",
    "wof:name":"Vermeiren",
    "wof:placetype":"venue"
},
  "geometry": {"coordinates":[4.2381057739,51.2076187134],"type":"Point"}
}