{
  "type": "Feature",
  "properties": {
    "addr:full":"Tuinwijk 19 Zulte Oost-Vlaanderen 9870",
    "addr:housenumber":"19",
    "addr:postcode":"9870",
    "addr:street":"Tuinwijk",
    "iso:country":"BE",
    "sg:address":"Tuinwijk 19",
    "sg:city":"Zulte",
    "sg:classifiers":[
        {
            "category":"Arena",
            "subcategory":"Sports Club",
            "type":"Entertainment"
        }
    ],
    "sg:phone":"+32 9 386 81 55",
    "sg:postcode":"9870",
    "sg:province":"Oost-Vlaanderen",
    "sg:tags":[
        "de"
    ],
    "wof:name":"Joc De Mouterij",
    "wof:placetype":"venue"
},
  "geometry": {"coordinates":[3.4919779301,50.9614028931],"type":"Point"}
}