{
  "type": "Feature",
  "properties": {
    "iso:country":"BE",
    "sg:address":"Oekensestraat 115",
    "sg:city":"Roeselare",
    "sg:orig_category":"Installation \u00e9lectrique r\u00e9sidentielle",
    "sg:phone":"+32 51 24 66 68",
    "sg:postcode":"8800",
    "sg:province":"West-Vlaanderen",
    "wof:name":"Mike Devos",
    "wof:placetype":"venue"
},
  "geometry": {"coordinates":[3.156799078,50.926940918],"type":"Point"}
}