{
  "type": "Feature",
  "properties": {
    "addr:full":"Chauss\u00e9e De Marche 868 Namur (jambes) Namur 5100",
    "addr:housenumber":"868",
    "addr:postcode":"5100",
    "addr:street":"Chausse\u0301E De Marche",
    "iso:country":"BE",
    "sg:address":"Chauss\u00e9e De Marche 868",
    "sg:city":"Namur (jambes)",
    "sg:classifiers":[
        {
            "category":"Bars & Pubs",
            "type":"Food & Drink"
        }
    ],
    "sg:phone":"+32 81 40 17 79",
    "sg:postcode":"5100",
    "sg:province":"Namur",
    "sg:tags":[
        "tavern"
    ],
    "wof:name":"Cle Des Champs (la)",
    "wof:placetype":"venue"
},
  "geometry": {"coordinates":[4.8713750839,50.4566345215],"type":"Point"}
}