{
  "type": "Feature",
  "properties": {
    "iso:country":"BE",
    "sg:address":"Olmenstraat 55",
    "sg:city":"Zaventem",
    "sg:orig_category":"Gestion de media publicitaires",
    "sg:phone":"+32 2 725 16 90",
    "sg:postcode":"1930",
    "sg:province":"Vlaams-Brabant",
    "wof:name":"Span Diffusion",
    "wof:placetype":"venue"
},
  "geometry": {"coordinates":[4.4667749405,50.8915557861],"type":"Point"}
}