{
  "type": "Feature",
  "properties": {
    "addr:full":"Herbert Hooverplein 19 B12 Leuven Vlaams-Brabant 3000",
    "addr:housenumber":"19 b12",
    "addr:postcode":"3000",
    "iso:country":"BE",
    "sg:address":"Herbert Hooverplein 19 B12",
    "sg:city":"Leuven",
    "sg:orig_category":"Boekhouders",
    "sg:phone":"+32 16 22 20 17",
    "sg:postcode":"3000",
    "sg:province":"Vlaams-Brabant",
    "wof:name":"Koen Aerts",
    "wof:placetype":"venue"
},
  "geometry": {"coordinates":[4.7036700249,50.8793869019],"type":"Point"}
}