{
  "type": "Feature",
  "properties": {
    "iso:country":"BE",
    "sg:address":"Mosselerlaan 8",
    "sg:city":"Genk",
    "sg:classifiers":[
        {
            "category":"Retail",
            "subcategory":"Veterinary Services",
            "type":"Services"
        }
    ],
    "sg:phone":"+32 89 36 13 52",
    "sg:postcode":"3600",
    "sg:province":"Limburg",
    "sg:tags":[
        "veterinarian"
    ],
    "wof:name":"Roels I",
    "wof:placetype":"venue"
},
  "geometry": {"coordinates":[5.5053319931,50.9692649841],"type":"Point"}
}