{
  "type": "Feature",
  "properties": {
    "addr:full":"Nachtegaal 8 Sint-truiden Limburg 3800",
    "addr:housenumber":"8",
    "addr:postcode":"3800",
    "addr:street":"Nachtegaal",
    "iso:country":"BE",
    "sg:address":"Nachtegaal 8",
    "sg:city":"Sint-truiden",
    "sg:orig_category":"Producteurs de fruits. Eleveurs and marchands de porcs",
    "sg:phone":"+32 11 31 22 61",
    "sg:postcode":"3800",
    "sg:province":"Limburg",
    "wof:name":"Gert Nicolai",
    "wof:placetype":"venue"
},
  "geometry": {"coordinates":[5.2542672157,50.8464279175],"type":"Point"}
}