{
  "type": "Feature",
  "properties": {
    "iso:country":"BE",
    "sg:address":"Oude Pleinstraat 47",
    "sg:city":"Mechelen",
    "sg:classifiers":[
        {
            "category":"Professional",
            "subcategory":"Accounting & Tax Preparation",
            "type":"Services"
        }
    ],
    "sg:phone":"+32 15 33 01 44",
    "sg:postcode":"2800",
    "sg:province":"Antwerpen",
    "sg:tags":[
        "bookkeeper"
    ],
    "wof:name":"Verschueren W",
    "wof:placetype":"venue"
},
  "geometry": {"coordinates":[4.4686441422,51.0396842957],"type":"Point"}
}