{
  "type": "Feature",
  "properties": {
    "iso:country":"BE",
    "sg:address":"Maxburgdreef 51",
    "sg:city":"Hoogstraten",
    "sg:orig_category":"Boomkwekerijen",
    "sg:phone":"+32 3 315 87 75",
    "sg:postcode":"2321",
    "sg:province":"Antwerpen",
    "wof:name":"Frank Luyckx",
    "wof:placetype":"venue"
},
  "geometry": {"coordinates":[4.7366099358,51.442325592],"type":"Point"}
}