{
  "type": "Feature",
  "properties": {
    "addr:full":"Boulevard Des Canadiens 67 Moeskroen/mouscron Hainaut 7711",
    "addr:housenumber":"67",
    "addr:postcode":"7711",
    "addr:street":"Boulevard Des Canadiens",
    "iso:country":"BE",
    "sg:address":"Boulevard Des Canadiens 67",
    "sg:city":"Moeskroen/mouscron",
    "sg:classifiers":[
        {
            "category":"Insurance",
            "subcategory":"Life Insurance",
            "type":"Services"
        }
    ],
    "sg:phone":"+32 56 48 93 92",
    "sg:postcode":"7711",
    "sg:province":"Hainaut",
    "sg:tags":[
        "assurance"
    ],
    "wof:name":"A. Vercamer",
    "wof:placetype":"venue"
},
  "geometry": {"coordinates":[3.318406105,50.7299728394],"type":"Point"}
}