{
  "type": "Feature",
  "properties": {
    "iso:country":"BE",
    "sg:address":"Verbindingsstraat 38",
    "sg:city":"Hove",
    "sg:classifiers":[
        {
            "category":"Retail",
            "subcategory":"Auto Repair",
            "type":"Services"
        }
    ],
    "sg:phone":"+32 3 239 93 89",
    "sg:postcode":"2540",
    "sg:province":"Antwerpen",
    "sg:tags":[
        "automobile-body"
    ],
    "wof:name":"Decotec Bvba",
    "wof:placetype":"venue"
},
  "geometry": {"coordinates":[4.4691472054,51.1462249756],"type":"Point"}
}