{
  "type": "Feature",
  "properties": {
    "iso:country":"BE",
    "sg:address":"Steenweg Op Gelrode 106",
    "sg:city":"Rotselaar",
    "sg:orig_category":"Assistances juridiques. Conseillers fiscaux. Comptables",
    "sg:phone":"+32 16 58 12 49",
    "sg:postcode":"3110",
    "sg:province":"Vlaams-Brabant",
    "wof:name":"Fiduco",
    "wof:placetype":"venue"
},
  "geometry": {"coordinates":[4.7461972237,50.9695549011],"type":"Point"}
}