{
  "type": "Feature",
  "properties": {
    "iso:country":"BE",
    "sg:address":"Bastijnstraat 28",
    "sg:city":"Berlaar",
    "sg:classifiers":[
        {
            "category":"Food & Beverages",
            "subcategory":"Meat & Fish",
            "type":"Retail Goods"
        }
    ],
    "sg:phone":"+32 3 422 50 36",
    "sg:postcode":"2590",
    "sg:province":"Antwerpen",
    "sg:tags":[
        "-",
        "livestock"
    ],
    "wof:name":"Vervoort",
    "wof:placetype":"venue"
},
  "geometry": {"coordinates":[4.6301298141,51.1107711792],"type":"Point"}
}