{
  "type": "Feature",
  "properties": {
    "addr:full":"Marktplein 13 Nieuwpoort West-Vlaanderen 8620",
    "addr:housenumber":"13",
    "addr:postcode":"8620",
    "addr:street":"Marktplein",
    "iso:country":"BE",
    "sg:address":"Marktplein 13",
    "sg:city":"Nieuwpoort",
    "sg:classifiers":[
        {
            "category":"Insurance",
            "subcategory":"Life Insurance",
            "type":"Services"
        }
    ],
    "sg:phone":"+32 58 23 84 68",
    "sg:postcode":"8620",
    "sg:province":"West-Vlaanderen",
    "sg:tags":[
        "assurance"
    ],
    "wof:name":"Zakenkantoor Debruyne",
    "wof:placetype":"venue"
},
  "geometry": {"coordinates":[2.7511200905,51.1297492981],"type":"Point"}
}