{
  "type": "Feature",
  "properties": {
    "addr:full":"Fond Leval 34 Sprimont Li\u00e8ge 4140",
    "addr:housenumber":"34",
    "addr:postcode":"4140",
    "addr:street":"Leval",
    "iso:country":"BE",
    "sg:address":"Fond Leval 34",
    "sg:city":"Sprimont",
    "sg:orig_category":"Electrom\u00e9nager, t\u00e9l\u00e9visions and radios. Eclairage et \u00e9quipements du foyer. R\u00e9parations d'appareils \u00e9",
    "sg:phone":"+32 4 382 12 38",
    "sg:postcode":"4140",
    "sg:province":"Li\u00e8ge",
    "wof:name":"Schoofs",
    "wof:placetype":"venue"
},
  "geometry": {"coordinates":[5.6608681679,50.5073738098],"type":"Point"}
}