{
  "type": "Feature",
  "properties": {
    "iso:country":"BE",
    "sg:address":"Jacobs-fontainestraat 69",
    "sg:city":"Brussel/bruxelles",
    "sg:orig_category":"Boekhouders",
    "sg:postcode":"1020",
    "sg:province":"Bruxelles-Capitale",
    "wof:name":"Jacqueline Van Jean",
    "wof:placetype":"venue"
},
  "geometry": {"coordinates":[4.3399529457,50.8780975342],"type":"Point"}
}