{
  "type": "Feature",
  "properties": {
    "iso:country":"BE",
    "sg:address":"Kaardeloodstraat 37",
    "sg:city":"Ninove",
    "sg:orig_category":"Meubelzaken, woning- and keukeninrichting",
    "sg:phone":"+32 54 33 56 15",
    "sg:postcode":"9400",
    "sg:province":"Oost-Vlaanderen",
    "wof:name":"Eurepos",
    "wof:placetype":"venue"
},
  "geometry": {"coordinates":[4.0204601288,50.8364143372],"type":"Point"}
}