{
  "type": "Feature",
  "properties": {
    "addr:full":"Rue De La Briqueterie 24 Gesves (faulx-les-tombes) Namur 5340",
    "addr:housenumber":"24",
    "addr:postcode":"5340",
    "addr:street":"Rue De La Briqueterie",
    "iso:country":"BE",
    "sg:address":"Rue De La Briqueterie 24",
    "sg:city":"Gesves (faulx-les-tombes)",
    "sg:classifiers":[
        {
            "category":"Freight",
            "type":"Transportation"
        }
    ],
    "sg:phone":"+32 81 57 00 51",
    "sg:postcode":"5340",
    "sg:province":"Namur",
    "sg:tags":[
        "-",
        "refrigerated",
        "transport"
    ],
    "wof:name":"Marmignon Scrl",
    "wof:placetype":"venue"
},
  "geometry": {"coordinates":[5.0262570381,50.4246902466],"type":"Point"}
}