{
  "type": "Feature",
  "properties": {
    "iso:country":"BE",
    "sg:address":"Jan Rosierlaan 68",
    "sg:city":"Lanaken",
    "sg:orig_category":"Meubles D\u00e9taillants, Am\u00e9nagement de B\u00e2timents et de Cuisines",
    "sg:phone":"+32 89 71 51 35",
    "sg:postcode":"3620",
    "sg:province":"Limburg",
    "wof:name":"Ivo Hoste",
    "wof:placetype":"venue"
},
  "geometry": {"coordinates":[5.6552600861,50.8885116577],"type":"Point"}
}