{
  "type": "Feature",
  "properties": {
    "addr:full":"Boulevard De L'empereur 24 Bruxelles Bruxelles-Capitale 1000",
    "addr:housenumber":"24",
    "addr:postcode":"1000",
    "addr:street":"Boulevard De L'Empereur",
    "iso:country":"BE",
    "sg:address":"Boulevard De L'empereur 24",
    "sg:city":"Bruxelles",
    "sg:classifiers":[
        {
            "category":"Professional",
            "subcategory":"Lawyer & Legal Services",
            "type":"Services"
        }
    ],
    "sg:phone":"+32 2 513 37 23",
    "sg:postcode":"1000",
    "sg:province":"Bruxelles-Capitale",
    "wof:name":"Gecchele Antonio",
    "wof:placetype":"venue"
},
  "geometry": {"coordinates":[4.353290081,50.8426704407],"type":"Point"}
}