{
  "type": "Feature",
  "properties": {
    "addr:full":"Avenue Des Petites Epines 11 Bastogne Luxembourg 6600",
    "addr:housenumber":"11",
    "addr:postcode":"6600",
    "addr:street":"Avenue Des Petites Epines",
    "iso:country":"BE",
    "sg:address":"Avenue Des Petites Epines 11",
    "sg:city":"Bastogne",
    "sg:orig_category":"Fa\u00e7ade covering",
    "sg:phone":"+32 61 21 44 88",
    "sg:postcode":"6600",
    "sg:province":"Luxembourg",
    "wof:name":"Arre Vito",
    "wof:placetype":"venue"
},
  "geometry": {"coordinates":[5.7002940178,50.0012435913],"type":"Point"}
}