{
  "type": "Feature",
  "properties": {
    "iso:country":"BE",
    "sg:address":"Burgstrasse 103",
    "sg:city":"Raeren",
    "sg:classifiers":[
        {
            "category":"Museum",
            "type":"Entertainment"
        }
    ],
    "sg:phone":"+32 87 85 09 03",
    "sg:postcode":"4730",
    "sg:province":"Li\u00e8ge",
    "wof:name":"T\u00f6pfereimuseum",
    "wof:placetype":"venue"
},
  "geometry": {"coordinates":[6.1210207939,50.6789703369],"type":"Point"}
}