{
  "type": "Feature",
  "properties": {
    "iso:country":"BE",
    "sg:address":"Rue De Cond\u00c9 62",
    "sg:city":"Leuze-en-hainaut",
    "sg:orig_category":"Supermarkten",
    "sg:phone":"+32 69 66 39 49",
    "sg:postcode":"7900",
    "sg:province":"Hainaut",
    "wof:name":"Match",
    "wof:placetype":"venue"
},
  "geometry": {"coordinates":[3.6173019409,50.5953445435],"type":"Point"}
}