{
  "type": "Feature",
  "properties": {
    "addr:full":"Rue De Dave 239 Namur (jambes) Namur 5100",
    "addr:housenumber":"239",
    "addr:postcode":"5100",
    "addr:street":"Rue De Dave",
    "iso:country":"BE",
    "sg:address":"Rue De Dave 239",
    "sg:city":"Namur (jambes)",
    "sg:classifiers":[
        {
            "category":"Health Services",
            "subcategory":"Doctor",
            "type":"Services"
        }
    ],
    "sg:phone":"+32 81 31 28 12",
    "sg:postcode":"5100",
    "sg:province":"Namur",
    "sg:tags":[
        "medicinephysicians",
        "surgeon"
    ],
    "wof:name":"Dachelet Claire",
    "wof:placetype":"venue"
},
  "geometry": {"coordinates":[4.8713750839,50.4566345215],"type":"Point"}
}