{
  "type": "Feature",
  "properties": {
    "addr:full":"Koekoekstraat 140 Aartselaar Antwerpen 2630",
    "addr:housenumber":"140",
    "addr:postcode":"2630",
    "addr:street":"Koekoekstraat",
    "iso:country":"BE",
    "sg:address":"Koekoekstraat 140",
    "sg:city":"Aartselaar",
    "sg:orig_category":"Boekhouders",
    "sg:phone":"+32 3 241 08 96",
    "sg:postcode":"2630",
    "sg:province":"Antwerpen",
    "wof:name":"Axel Dellaert",
    "wof:placetype":"venue"
},
  "geometry": {"coordinates":[4.3643341064,51.1111488342],"type":"Point"}
}