{
  "type": "Feature",
  "properties": {
    "iso:country":"BE",
    "sg:address":"Kazernestraat 38",
    "sg:city":"Sint-niklaas",
    "sg:classifiers":[
        {
            "category":"Arena",
            "subcategory":"Sports Club",
            "type":"Entertainment"
        }
    ],
    "sg:phone":"+32 3 776 60 18",
    "sg:postcode":"9100",
    "sg:province":"Oost-Vlaanderen",
    "sg:tags":[
        "de"
    ],
    "wof:name":"Belgische Alpen Club",
    "wof:placetype":"venue"
},
  "geometry": {"coordinates":[4.1374502182,51.1717758179],"type":"Point"}
}