{
  "type": "Feature",
  "properties": {
    "addr:full":"Cottemweg 16 Oudenburg West-Vlaanderen 8460",
    "addr:housenumber":"16",
    "addr:postcode":"8460",
    "addr:street":"Cottemweg",
    "iso:country":"BE",
    "sg:address":"Cottemweg 16",
    "sg:city":"Oudenburg",
    "sg:classifiers":[
        {
            "category":"Health Services",
            "subcategory":"Health Practitioner",
            "type":"Services"
        }
    ],
    "sg:phone":"+32 59 26 71 64",
    "sg:postcode":"8460",
    "sg:province":"West-Vlaanderen",
    "sg:tags":[
        "physiotherapist"
    ],
    "wof:name":"Berton Rita",
    "wof:placetype":"venue"
},
  "geometry": {"coordinates":[3.0139040947,51.1856460571],"type":"Point"}
}