{
  "type": "Feature",
  "properties": {
    "addr:full":"Rue De Claire Fontaine 153 Chapelle-lez-herlaimont Hainaut 7160",
    "addr:housenumber":"153",
    "addr:postcode":"7160",
    "addr:street":"Rue De Claire Fontaine",
    "iso:country":"BE",
    "sg:address":"Rue De Claire Fontaine 153",
    "sg:city":"Chapelle-lez-herlaimont",
    "sg:orig_category":"Kapsalons",
    "sg:phone":"+32 64 44 63 32",
    "sg:postcode":"7160",
    "sg:province":"Hainaut",
    "wof:name":"Coiffure Batty",
    "wof:placetype":"venue"
},
  "geometry": {"coordinates":[4.2823991776,50.486164093],"type":"Point"}
}