{
  "type": "Feature",
  "properties": {
    "addr:full":"Heurnestraat 1 Oudenaarde Oost-Vlaanderen 9700",
    "addr:housenumber":"1",
    "addr:postcode":"9700",
    "addr:street":"Heurnestraat",
    "iso:country":"BE",
    "sg:address":"Heurnestraat 1",
    "sg:city":"Oudenaarde",
    "sg:classifiers":[
        {
            "category":"Food & Beverages",
            "subcategory":"Specialty",
            "type":"Retail Goods"
        }
    ],
    "sg:phone":"+32 55 30 43 30",
    "sg:postcode":"9700",
    "sg:province":"Oost-Vlaanderen",
    "sg:tags":[
        "health",
        "dietary",
        "-",
        "biological"
    ],
    "wof:name":"Ginkgo",
    "wof:placetype":"venue"
},
  "geometry": {"coordinates":[3.6228439808,50.8740882874],"type":"Point"}
}