{
  "type": "Feature",
  "properties": {
    "addr:full":"Veerstraat 14 Berlare Oost-Vlaanderen 9290",
    "addr:housenumber":"14",
    "addr:postcode":"9290",
    "addr:street":"Veerstraat",
    "iso:country":"BE",
    "sg:address":"Veerstraat 14",
    "sg:city":"Berlare",
    "sg:classifiers":[
        {
            "category":"Cafe",
            "type":"Food & Drink"
        }
    ],
    "sg:phone":"+32 9 367 90 27",
    "sg:postcode":"9290",
    "sg:province":"Oost-Vlaanderen",
    "sg:tags":[
        "caf\u00e9s"
    ],
    "wof:name":"Caf\u00c9 De Zwaan",
    "wof:placetype":"venue"
},
  "geometry": {"coordinates":[3.9499850273,51.029548645],"type":"Point"}
}