{
  "type": "Feature",
  "properties": {
    "addr:full":"Schaatsputte 2 Oudenaarde Oost-Vlaanderen 9700",
    "addr:housenumber":"2",
    "addr:postcode":"9700",
    "addr:street":"Schaatsputte",
    "iso:country":"BE",
    "sg:address":"Schaatsputte 2",
    "sg:city":"Oudenaarde",
    "sg:orig_category":"Eleveurs and marchands de porcs. Eleveurs de bovins",
    "sg:phone":"+32 55 38 81 09",
    "sg:postcode":"9700",
    "sg:province":"Oost-Vlaanderen",
    "wof:name":"Willy Capiau",
    "wof:placetype":"venue"
},
  "geometry": {"coordinates":[3.5678129196,50.8062057495],"type":"Point"}
}