{
  "type": "Feature",
  "properties": {
    "iso:country":"BE",
    "sg:address":"Kleiputtendreef 21",
    "sg:city":"Poperinge",
    "sg:classifiers":[
        {
            "category":"Real Estate",
            "subcategory":"Architect",
            "type":"Services"
        }
    ],
    "sg:phone":"+32 57 33 61 92",
    "sg:postcode":"8970",
    "sg:province":"West-Vlaanderen",
    "wof:name":"Vandewynckel Luc Bvba",
    "wof:placetype":"venue"
},
  "geometry": {"coordinates":[2.7285249233,50.8466796875],"type":"Point"}
}