{
  "type": "Feature",
  "properties": {
    "addr:full":"Veldkant 10 Boechout Antwerpen 2530",
    "addr:housenumber":"10",
    "addr:postcode":"2530",
    "addr:street":"Veldkant",
    "iso:country":"BE",
    "sg:address":"Veldkant 10",
    "sg:city":"Boechout",
    "sg:orig_category":"Installatie van houten of kunststof schrijnwerk Woningbouw",
    "sg:phone":"+32 3 455 57 77",
    "sg:postcode":"2530",
    "sg:province":"Antwerpen",
    "wof:name":"Archi-tec",
    "wof:placetype":"venue"
},
  "geometry": {"coordinates":[4.4848828316,51.1689453125],"type":"Point"}
}