{
  "type": "Feature",
  "properties": {
    "addr:full":"Ieperlaan 24 Brussel/bruxelles Bruxelles-Capitale 1000",
    "addr:housenumber":"24",
    "addr:postcode":"1000",
    "addr:street":"Ieperlaan;/",
    "iso:country":"BE",
    "sg:address":"Ieperlaan 24",
    "sg:city":"Brussel/bruxelles",
    "sg:orig_category":"Opvangtehuizen and vluchthuizen",
    "sg:phone":"+32 2 217 61 36",
    "sg:postcode":"1000",
    "sg:province":"Bruxelles-Capitale",
    "wof:name":"Arm\u00c9e Du Salut Fabiola",
    "wof:placetype":"venue"
},
  "geometry": {"coordinates":[4.3465847969,50.8561134338],"type":"Point"}
}