{
  "type": "Feature",
  "properties": {
    "iso:country":"BE",
    "sg:address":"Flessestraat 5",
    "sg:city":"Tielt",
    "sg:orig_category":"Rundveehouders Varkenskwekers",
    "sg:phone":"+32 51 40 23 58",
    "sg:postcode":"8700",
    "sg:province":"West-Vlaanderen",
    "wof:name":"Julien Vande Weghe",
    "wof:placetype":"venue"
},
  "geometry": {"coordinates":[3.3738958836,51.0114822388],"type":"Point"}
}