{
  "type": "Feature",
  "properties": {
    "iso:country":"BE",
    "sg:address":"Excelsiorlaan 39",
    "sg:city":"Zaventem",
    "sg:orig_category":"Bouwmaterialen Gh",
    "sg:phone":"+32 2 725 18 18",
    "sg:postcode":"1930",
    "sg:province":"Vlaams-Brabant",
    "wof:name":"Nynas",
    "wof:placetype":"venue"
},
  "geometry": {"coordinates":[4.4523711205,50.8820457458],"type":"Point"}
}