{
  "type": "Feature",
  "properties": {
    "addr:full":"Stationsstraat 104 Dilsen-stokkem (elen) Limburg 3650",
    "addr:housenumber":"104",
    "addr:postcode":"3650",
    "addr:street":"Stationsstraat;Elen Limburg",
    "iso:country":"BE",
    "sg:address":"Stationsstraat 104",
    "sg:city":"Dilsen-stokkem (elen)",
    "sg:classifiers":[
        {
            "category":"Utilities",
            "subcategory":"Fuel Oil & Lpg",
            "type":"Services"
        }
    ],
    "sg:phone":"+32 89 56 55 51",
    "sg:postcode":"3650",
    "sg:province":"Limburg",
    "wof:name":"Mathy Brandstoffen",
    "wof:placetype":"venue"
},
  "geometry": {"coordinates":[5.736038208,51.0690307617],"type":"Point"}
}