{
  "type": "Feature",
  "properties": {
    "iso:country":"BE",
    "sg:address":"Herresbach 6",
    "sg:city":"Amel",
    "sg:orig_category":"Vakantiehuizen",
    "sg:phone":"+32 80 54 89 49",
    "sg:postcode":"4770",
    "sg:province":"Li\u00e8ge",
    "wof:name":"A. Keller",
    "wof:placetype":"venue"
},
  "geometry": {"coordinates":[6.2551860809,50.3197746277],"type":"Point"}
}