{
  "type": "Feature",
  "properties": {
    "iso:country":"BE",
    "sg:address":"Place Maugr\u00e9tout 4",
    "sg:city":"La Louvi\u00e8re",
    "sg:classifiers":[
        {
            "category":"Professional",
            "subcategory":"Secretarial Services",
            "type":"Services"
        }
    ],
    "sg:phone":"+32 64 21 57 13",
    "sg:postcode":"7100",
    "sg:province":"Hainaut",
    "sg:tags":[
        "delivery",
        "messenger"
    ],
    "wof:name":"Communications Et Services",
    "wof:placetype":"venue"
},
  "geometry": {"coordinates":[4.1876797676,50.4781570435],"type":"Point"}
}