{
  "type": "Feature",
  "properties": {
    "iso:country":"BE",
    "sg:address":"Lange Lozanastraat 236",
    "sg:city":"Antwerpen",
    "sg:classifiers":[
        {
            "category":"Professional",
            "subcategory":"Management & Consulting",
            "type":"Services"
        }
    ],
    "sg:phone":"+32 3 240 11 90",
    "sg:postcode":"2018",
    "sg:province":"Antwerpen",
    "sg:tags":[
        "consultant"
    ],
    "wof:name":"The Hever Group Cvba",
    "wof:placetype":"venue"
},
  "geometry": {"coordinates":[4.4066400528,51.1998825073],"type":"Point"}
}