{
  "type": "Feature",
  "properties": {
    "addr:full":"Ter Coutere 1 Harelbeke (bavikhove) West-Vlaanderen 8531",
    "addr:housenumber":"1",
    "addr:postcode":"8531",
    "iso:country":"BE",
    "sg:address":"Ter Coutere 1",
    "sg:city":"Harelbeke (bavikhove)",
    "sg:classifiers":[
        {
            "category":"Health Services",
            "subcategory":"Dentist",
            "type":"Services"
        }
    ],
    "sg:phone":"+32 56 73 54 24",
    "sg:postcode":"8531",
    "sg:province":"West-Vlaanderen",
    "wof:name":"Gordjestani M",
    "wof:placetype":"venue"
},
  "geometry": {"coordinates":[3.3027019501,50.8630371094],"type":"Point"}
}