{
  "type": "Feature",
  "properties": {
    "iso:country":"BE",
    "sg:address":"Weldenstraat 42-44",
    "sg:city":"Oudenaarde (welden)",
    "sg:classifiers":[
        {
            "category":"Home & Garden",
            "subcategory":"Home Furnishings",
            "type":"Retail Goods"
        }
    ],
    "sg:phone":"+32 55 49 81 61",
    "sg:postcode":"9700",
    "sg:province":"Oost-Vlaanderen",
    "sg:tags":[
        "-",
        "furniture"
    ],
    "wof:name":"De Meulemeester",
    "wof:placetype":"venue"
},
  "geometry": {"coordinates":[3.6667640209,50.8753890991],"type":"Point"}
}