{
  "type": "Feature",
  "properties": {
    "iso:country":"BE",
    "sg:address":"Haantjen 41",
    "sg:city":"Assenede",
    "sg:orig_category":"Eclairage et \u00e9quipements du foyer",
    "sg:phone":"+32 9 373 73 03",
    "sg:postcode":"9968",
    "sg:province":"Oost-Vlaanderen",
    "wof:name":"Dc - Design",
    "wof:placetype":"venue"
},
  "geometry": {"coordinates":[3.6887938976,51.1923027039],"type":"Point"}
}