{
  "type": "Feature",
  "properties": {
    "addr:full":"Kloosterstraat 19b2 Neerpelt Limburg 3910",
    "addr:housenumber":"19b2",
    "addr:postcode":"3910",
    "addr:street":"Kloosterstraat",
    "iso:country":"BE",
    "sg:address":"Kloosterstraat 19b2",
    "sg:city":"Neerpelt",
    "sg:classifiers":[
        {
            "category":"Food & Beverages",
            "subcategory":"Fruits & Vegetables",
            "type":"Retail Goods"
        }
    ],
    "sg:phone":"+32 11 64 58 81",
    "sg:postcode":"3910",
    "sg:province":"Limburg",
    "sg:tags":[
        "l\u00e9gumes"
    ],
    "wof:name":"Huis Vitamientje",
    "wof:placetype":"venue"
},
  "geometry": {"coordinates":[5.4333600998,51.2297821045],"type":"Point"}
}