{
  "type": "Feature",
  "properties": {
    "addr:full":"Marktstraat 15 Maldegem Oost-Vlaanderen 9990",
    "addr:housenumber":"15",
    "addr:postcode":"9990",
    "addr:street":"Marktstraat",
    "iso:country":"BE",
    "sg:address":"Marktstraat 15",
    "sg:city":"Maldegem",
    "sg:orig_category":"Algemeen secundair onderwijs Technisch and beroeps secundair onderwijs",
    "sg:phone":"+32 50 71 11 44",
    "sg:postcode":"9990",
    "sg:province":"Oost-Vlaanderen",
    "wof:name":"Inst. Virgo Sapientiae",
    "wof:placetype":"venue"
},
  "geometry": {"coordinates":[3.4455959797,51.2083282471],"type":"Point"}
}