{
  "type": "Feature",
  "properties": {
    "addr:full":"Av Sergent Vrithoff 123-125 Namur Namur 5000",
    "addr:postcode":"123-125;5000",
    "addr:street":"Av Sergent Vrithoff",
    "iso:country":"BE",
    "sg:address":"Av Sergent Vrithoff 123-125",
    "sg:city":"Namur",
    "sg:classifiers":[
        {
            "category":"Utilities",
            "subcategory":"Electric",
            "type":"Services"
        }
    ],
    "sg:phone":"+32 81 73 64 22",
    "sg:postcode":"5000",
    "sg:province":"Namur",
    "sg:tags":[
        "electricity",
        "electronic",
        "electrical",
        "equipment"
    ],
    "wof:name":"Cebeo Sa",
    "wof:placetype":"venue"
},
  "geometry": {"coordinates":[4.8427519798,50.4661178589],"type":"Point"}
}