{
  "type": "Feature",
  "properties": {
    "addr:full":"Sint-pietersplein 7 Gooik (leerbeek) Vlaams-Brabant 1755",
    "addr:housenumber":"7",
    "addr:postcode":"1755",
    "addr:street":"Sint-Pietersplein",
    "iso:country":"BE",
    "sg:address":"Sint-pietersplein 7",
    "sg:city":"Gooik (leerbeek)",
    "sg:classifiers":[
        {
            "category":"Food & Beverages",
            "subcategory":"Groceries & Convenience Stores",
            "type":"Retail Goods"
        }
    ],
    "sg:phone":"+32 2 532 52 99",
    "sg:postcode":"1755",
    "sg:province":"Vlaams-Brabant",
    "sg:tags":[
        "grocer"
    ],
    "wof:name":"Voeding Viviane",
    "wof:placetype":"venue"
},
  "geometry": {"coordinates":[4.1180701256,50.7753791809],"type":"Point"}
}