{
  "type": "Feature",
  "properties": {
    "iso:country":"BE",
    "sg:address":"Schrijnwerkersstraat 16",
    "sg:city":"Hasselt",
    "sg:orig_category":"Decoratieve kunst and kunstbenodigdheden",
    "sg:phone":"+32 11 22 55 99",
    "sg:postcode":"3500",
    "sg:province":"Limburg",
    "wof:name":"De Oude Librije",
    "wof:placetype":"venue"
},
  "geometry": {"coordinates":[5.335943222,50.9320144653],"type":"Point"}
}