{
  "type": "Feature",
  "properties": {
    "addr:full":"Hingenesteenweg 33 Bornem Antwerpen 2880",
    "addr:housenumber":"33",
    "addr:postcode":"2880",
    "addr:street":"Hingenesteenweg",
    "iso:country":"BE",
    "sg:address":"Hingenesteenweg 33",
    "sg:city":"Bornem",
    "sg:orig_category":"Sportclubs",
    "sg:phone":"+32 3 889 19 16",
    "sg:postcode":"2880",
    "sg:province":"Antwerpen",
    "wof:name":"W.a.c. Sport En Steun",
    "wof:placetype":"venue"
},
  "geometry": {"coordinates":[4.2444958687,51.1002960205],"type":"Point"}
}