{
  "type": "Feature",
  "properties": {
    "iso:country":"BE",
    "sg:address":"Vieux Chemin De Nivelles 25d",
    "sg:city":"Braine-le-ch\u00e2teau",
    "sg:classifiers":[
        {
            "category":"Education",
            "subcategory":"Special Training",
            "type":"Public Place"
        }
    ],
    "sg:phone":"+32 2 366 14 94",
    "sg:postcode":"1440",
    "sg:province":"Brabant Wallon",
    "sg:tags":[
        "-",
        "processing",
        "data"
    ],
    "wof:name":"Cw Soft",
    "wof:placetype":"venue"
},
  "geometry": {"coordinates":[4.2750182152,50.6720275879],"type":"Point"}
}