{
  "type": "Feature",
  "properties": {
    "addr:full":"Sleidinge Dorp 101 Evergem (sleidinge) Oost-Vlaanderen 9940",
    "addr:housenumber":"101",
    "addr:postcode":"9940",
    "addr:street":"Dorp",
    "iso:country":"BE",
    "sg:address":"Sleidinge Dorp 101",
    "sg:city":"Evergem (sleidinge)",
    "sg:classifiers":[
        {
            "category":"Health Services",
            "subcategory":"Dentist",
            "type":"Services"
        }
    ],
    "sg:phone":"+32 9 357 56 77",
    "sg:postcode":"9940",
    "sg:province":"Oost-Vlaanderen",
    "wof:name":"Van Damme Heidi",
    "wof:placetype":"venue"
},
  "geometry": {"coordinates":[3.679776907,51.1356010437],"type":"Point"}
}