{
  "type": "Feature",
  "properties": {
    "addr:full":"Oostkaai 74 Ieper (boezinge) West-Vlaanderen 8904",
    "addr:housenumber":"74",
    "addr:postcode":"8904",
    "addr:street":"Oostkaai",
    "iso:country":"BE",
    "sg:address":"Oostkaai 74",
    "sg:city":"Ieper (boezinge)",
    "sg:classifiers":[
        {
            "category":"Building & Trades",
            "subcategory":"Pest Control",
            "type":"Services"
        }
    ],
    "sg:phone":"+32 57 48 62 48",
    "sg:postcode":"8904",
    "sg:province":"West-Vlaanderen",
    "sg:tags":[
        "painting",
        "contractor"
    ],
    "wof:name":"Vandenbriele",
    "wof:placetype":"venue"
},
  "geometry": {"coordinates":[2.8702180386,50.8901748657],"type":"Point"}
}