{
  "type": "Feature",
  "properties": {
    "iso:country":"BE",
    "sg:address":"Rue De La Collectivit\u00c9 68",
    "sg:city":"Saint-nicolas",
    "sg:classifiers":[
        {
            "category":"Personal",
            "subcategory":"Beauty Salon",
            "type":"Services"
        }
    ],
    "sg:phone":"+32 4 226 53 55",
    "sg:postcode":"4420",
    "sg:province":"Li\u00e8ge",
    "sg:tags":[
        "de",
        "coiffure"
    ],
    "wof:name":"Coiffure Denise",
    "wof:placetype":"venue"
},
  "geometry": {"coordinates":[5.5310921669,50.6386146545],"type":"Point"}
}