{
  "type": "Feature",
  "properties": {
    "addr:full":"Abdijstr 107 Antwerpen Antwerpen 2000",
    "addr:housenumber":"107",
    "addr:postcode":"2000",
    "iso:country":"BE",
    "sg:address":"Abdijstr 107",
    "sg:city":"Antwerpen",
    "sg:classifiers":[
        {
            "category":"Banks & Credit Unions",
            "subcategory":"Bank",
            "type":"Services"
        }
    ],
    "sg:phone":"+32 3 238 56 02",
    "sg:postcode":"2000",
    "sg:province":"Antwerpen",
    "wof:name":"G\u00e9n\u00e9rale De Banque Sa",
    "wof:placetype":"venue"
},
  "geometry": {"coordinates":[4.3821840286,51.1888046265],"type":"Point"}
}