{
  "type": "Feature",
  "properties": {
    "addr:full":"Felix Daelslaan 9 Aarschot Vlaams-Brabant 3200",
    "addr:housenumber":"9",
    "addr:postcode":"3200",
    "addr:street":"Daelslaan",
    "iso:country":"BE",
    "sg:address":"Felix Daelslaan 9",
    "sg:city":"Aarschot",
    "sg:orig_category":"Loodgieterij, verwarming and sanitaire installaties",
    "sg:phone":"+32 16 56 85 71",
    "sg:postcode":"3200",
    "sg:province":"Vlaams-Brabant",
    "wof:name":"Christiaan Cumps",
    "wof:placetype":"venue"
},
  "geometry": {"coordinates":[4.830491066,51.0057525635],"type":"Point"}
}