{
  "type": "Feature",
  "properties": {
    "iso:country":"BE",
    "sg:address":"Keienveld 10",
    "sg:city":"Huldenberg",
    "sg:orig_category":"Diverse organisaties and verenigingen",
    "sg:phone":"+32 2 687 65 88",
    "sg:postcode":"3040",
    "sg:province":"Vlaams-Brabant",
    "wof:name":"J.a. De Hoorn",
    "wof:placetype":"venue"
},
  "geometry": {"coordinates":[4.5900092125,50.7824668884],"type":"Point"}
}