{
  "type": "Feature",
  "properties": {
    "iso:country":"BE",
    "sg:address":"Beukenlaan 48",
    "sg:city":"Hoeilaart",
    "sg:orig_category":"Cad/Cam systems",
    "sg:phone":"+32 2 657 58 03",
    "sg:postcode":"1560",
    "sg:province":"Vlaams-Brabant",
    "wof:name":"Digital Multimedia Europe Sprl",
    "wof:placetype":"venue"
},
  "geometry": {"coordinates":[4.493478775,50.7614059448],"type":"Point"}
}