{
  "type": "Feature",
  "properties": {
    "iso:country":"BE",
    "sg:address":"Boulevard De La Plaine 2",
    "sg:city":"Elsene/ixelles",
    "sg:orig_category":"Banques and organismes de cr\u00e9dit. Cr\u00e9dits divers",
    "sg:phone":"+32 2 647 50 77",
    "sg:postcode":"1050",
    "sg:province":"Bruxelles-Capitale",
    "wof:name":"Fortis",
    "wof:placetype":"venue"
},
  "geometry": {"coordinates":[4.3929901123,50.8209838867],"type":"Point"}
}