{
  "type": "Feature",
  "properties": {
    "iso:country":"BE",
    "sg:address":"Acacialaan 4",
    "sg:city":"Harelbeke",
    "sg:orig_category":"Architecten",
    "sg:phone":"+32 56 25 88 89",
    "sg:postcode":"8530",
    "sg:province":"West-Vlaanderen",
    "wof:name":"Geert Vanherweghe",
    "wof:placetype":"venue"
},
  "geometry": {"coordinates":[3.3099560738,50.8390655518],"type":"Point"}
}