{
  "type": "Feature",
  "properties": {
    "addr:full":"Sint-truidersteenweg 97 Hasselt Limburg 3500",
    "addr:housenumber":"97",
    "addr:postcode":"3500",
    "addr:street":"Sint-Truidersteenweg",
    "iso:country":"BE",
    "sg:address":"Sint-truidersteenweg 97",
    "sg:city":"Hasselt",
    "sg:orig_category":"Diverse opleidingen and onderwijs Werk and personeelsselectie",
    "sg:phone":"+32 11 28 00 50",
    "sg:postcode":"3500",
    "sg:province":"Limburg",
    "wof:name":"Asc Advisor & Selection Center",
    "wof:placetype":"venue"
},
  "geometry": {"coordinates":[5.3324308395,50.9236946106],"type":"Point"}
}