{
  "type": "Feature",
  "properties": {
    "iso:country":"BE",
    "sg:address":"Burg.verstaenlaan 9",
    "sg:city":"Dentergem",
    "sg:orig_category":"Sportclubs",
    "sg:phone":"+32 56 61 33 82",
    "sg:postcode":"8720",
    "sg:province":"West-Vlaanderen",
    "wof:name":"Het Rijdend Wiel - Wakken",
    "wof:placetype":"venue"
},
  "geometry": {"coordinates":[3.4162099361,50.9655342102],"type":"Point"}
}