{
  "type": "Feature",
  "properties": {
    "iso:country":"BE",
    "sg:address":"Louis Pasteurlaan 24",
    "sg:city":"Kortrijk",
    "sg:orig_category":"Advocaten and juridische adviseurs",
    "sg:phone":"+32 56 21 03 75",
    "sg:postcode":"8500",
    "sg:province":"West-Vlaanderen",
    "wof:name":"Koenraad Hinnekens",
    "wof:placetype":"venue"
},
  "geometry": {"coordinates":[3.3022799492,50.8106117249],"type":"Point"}
}