{
  "type": "Feature",
  "properties": {
    "addr:full":"Vosmeer 14 I.p. Hoogveld Dendermonde Oost-Vlaanderen 9200",
    "addr:housenumber":"14 i.p.",
    "addr:postcode":"9200",
    "addr:street":"Vosmeer;Hoogveld",
    "iso:country":"BE",
    "sg:address":"Vosmeer 14 I.p. Hoogveld",
    "sg:city":"Dendermonde",
    "sg:classifiers":[
        {
            "category":"Government",
            "subcategory":"Court House",
            "type":"Public Place"
        }
    ],
    "sg:phone":"+32 52 22 49 47",
    "sg:postcode":"9200",
    "sg:province":"Oost-Vlaanderen",
    "sg:tags":[
        "stone",
        "paving"
    ],
    "wof:name":"De Coninck Wegenbouw Nv",
    "wof:placetype":"venue"
},
  "geometry": {"coordinates":[4.0983099937,51.0315208435],"type":"Point"}
}