{
  "type": "Feature",
  "properties": {
    "iso:country":"BE",
    "sg:address":"Rue Stepman 5",
    "sg:city":"Bruxelles (koekelberg)",
    "sg:classifiers":[
        {
            "category":"Retail",
            "subcategory":"Auto Repair",
            "type":"Services"
        }
    ],
    "sg:phone":"+32 2 411 46 22",
    "sg:postcode":"1081",
    "sg:province":"Bruxelles-Capitale",
    "sg:tags":[
        "garage"
    ],
    "wof:name":"Andr\u00e9 Vandeput (garage)",
    "wof:placetype":"venue"
},
  "geometry": {"coordinates":[4.3274359703,50.8589057922],"type":"Point"}
}