{
  "type": "Feature",
  "properties": {
    "addr:full":"Van Der Goes 101 Auderghem Bruxelles Bruxelles-Capitale 1160",
    "addr:housenumber":"101",
    "addr:postcode":"1160",
    "addr:street":"Van Der Goes",
    "iso:country":"BE",
    "sg:address":"Van Der Goes 101",
    "sg:city":"Auderghem Bruxelles",
    "sg:orig_category":"Installation \u00e9lectrique r\u00e9sidentielle",
    "sg:phone":"+32 2 387 43 32",
    "sg:postcode":"1160",
    "sg:province":"Bruxelles-Capitale",
    "wof:name":"Green Light Security",
    "wof:placetype":"venue"
},
  "geometry": {"coordinates":[4.4394540787,50.8088302612],"type":"Point"}
}