{
  "type": "Feature",
  "properties": {
    "iso:country":"BE",
    "sg:address":"Nijverheidslaan 1567",
    "sg:city":"Opglabbeek",
    "sg:classifiers":[
        {
            "category":"Food & Beverages",
            "subcategory":"Supermarket",
            "type":"Retail Goods"
        }
    ],
    "sg:phone":"+32 89 51 81 10",
    "sg:postcode":"3660",
    "sg:province":"Limburg",
    "sg:tags":[
        "frozen",
        "-"
    ],
    "wof:name":"Horeca Langens Nv",
    "wof:placetype":"venue"
},
  "geometry": {"coordinates":[5.5570778847,51.0423431396],"type":"Point"}
}