{
  "type": "Feature",
  "properties": {
    "iso:country":"BE",
    "sg:address":"Ninoofsesteenweg 8",
    "sg:city":"Pepingen",
    "sg:orig_category":"HUISBRANDOLIE",
    "sg:phone":"+32 2 356 12 81",
    "sg:postcode":"1670",
    "sg:province":"Vlaams-Brabant",
    "wof:name":"Hendrik Habils",
    "wof:placetype":"venue"
},
  "geometry": {"coordinates":[4.1891407967,50.7490119934],"type":"Point"}
}