{
  "type": "Feature",
  "properties": {
    "addr:full":"Rue Du Canada 6 Vorst/forest Bruxelles-Capitale 1190",
    "addr:housenumber":"6",
    "addr:postcode":"1190",
    "addr:street":"Rue Du Canada;/ Forest",
    "iso:country":"BE",
    "sg:address":"Rue Du Canada 6",
    "sg:city":"Vorst/forest",
    "sg:orig_category":"Salles de spectacles",
    "sg:phone":"+32 2 539 36 87",
    "sg:postcode":"1190",
    "sg:province":"Bruxelles-Capitale",
    "wof:name":"Brocoli Th\u00c9\u00c2tre",
    "wof:placetype":"venue"
},
  "geometry": {"coordinates":[4.3360118866,50.8267326355],"type":"Point"}
}