{
  "type": "Feature",
  "properties": {
    "iso:country":"BE",
    "sg:address":"Steenstraat 1",
    "sg:city":"Blankenberge",
    "sg:classifiers":[
        {
            "category":"Travel",
            "subcategory":"Hotels & Motels",
            "type":"Entertainment"
        }
    ],
    "sg:phone":"+32 50 41 22 12",
    "sg:postcode":"8370",
    "sg:province":"West-Vlaanderen",
    "wof:name":"Dhoore L",
    "wof:placetype":"venue"
},
  "geometry": {"coordinates":[3.1315441132,51.3133506775],"type":"Point"}
}