{
  "type": "Feature",
  "properties": {
    "iso:country":"BE",
    "sg:address":"Rue Des Avins 8",
    "sg:city":"Havelange",
    "sg:orig_category":"Boekhouders",
    "sg:phone":"+32 83 63 32 73",
    "sg:postcode":"5370",
    "sg:province":"Namur",
    "wof:name":"Ancion Christine",
    "wof:placetype":"venue"
},
  "geometry": {"coordinates":[5.2452921867,50.3887252808],"type":"Point"}
}