{
  "type": "Feature",
  "properties": {
    "iso:country":"BE",
    "sg:address":"Jan Palfijnstraat 4",
    "sg:city":"Kortrijk",
    "sg:orig_category":"Kapsalons",
    "sg:phone":"+32 56 22 00 71",
    "sg:postcode":"8500",
    "sg:province":"West-Vlaanderen",
    "wof:name":"J. Lefevre",
    "wof:placetype":"venue"
},
  "geometry": {"coordinates":[3.2636299133,50.8262290955],"type":"Point"}
}