{
  "type": "Feature",
  "properties": {
    "iso:country":"BE",
    "sg:address":"Vande Vennestraat 30",
    "sg:city":"Zwevegem",
    "sg:orig_category":"Kapsalons",
    "sg:phone":"+32 56 75 50 23",
    "sg:postcode":"8550",
    "sg:province":"West-Vlaanderen",
    "wof:name":"Coiffure Denise",
    "wof:placetype":"venue"
},
  "geometry": {"coordinates":[3.3293619156,50.8141860962],"type":"Point"}
}