{
  "type": "Feature",
  "properties": {
    "iso:country":"BE",
    "sg:address":"Putse Baan 91",
    "sg:city":"Antwerpen",
    "sg:classifiers":[
        {
            "category":"Personal",
            "subcategory":"Beauty Salon",
            "type":"Services"
        }
    ],
    "sg:phone":"+32 3 568 60 58",
    "sg:postcode":"2040",
    "sg:province":"Antwerpen",
    "sg:tags":[
        "lady",
        "-",
        "hairdressing"
    ],
    "wof:name":"Roger",
    "wof:placetype":"venue"
},
  "geometry": {"coordinates":[4.3311300278,51.3580284119],"type":"Point"}
}