{
  "type": "Feature",
  "properties": {
    "addr:full":"Quai De L'ourthe 0 La Roche-en-ardenne Luxembourg 6980",
    "addr:housenumber":"0",
    "addr:postcode":"6980",
    "addr:street":"Quai De L'Ourthe",
    "iso:country":"BE",
    "sg:address":"Quai De L'ourthe 0",
    "sg:city":"La Roche-en-ardenne",
    "sg:orig_category":"Openbare bibliotheken and archieven",
    "sg:phone":"+32 61 22 43 20",
    "sg:postcode":"6980",
    "sg:province":"Luxembourg",
    "wof:name":"Discobus",
    "wof:placetype":"venue"
},
  "geometry": {"coordinates":[5.5749511719,50.1830825806],"type":"Point"}
}