{
  "type": "Feature",
  "properties": {
    "iso:country":"BE",
    "sg:address":"Oliebergstraat 50",
    "sg:city":"Deerlijk",
    "sg:orig_category":"Solar protection - Outside",
    "sg:phone":"+32 56 77 80 62",
    "sg:postcode":"8540",
    "sg:province":"West-Vlaanderen",
    "wof:name":"Rudaplast Cv",
    "wof:placetype":"venue"
},
  "geometry": {"coordinates":[3.3667259216,50.8239402771],"type":"Point"}
}