{
  "type": "Feature",
  "properties": {
    "addr:full":"Gullegemsestraat 13 Kortrijk (heule) West-Vlaanderen 8501",
    "addr:housenumber":"13",
    "addr:postcode":"8501",
    "addr:street":"Gullegemsestraat",
    "iso:country":"BE",
    "sg:address":"Gullegemsestraat 13",
    "sg:city":"Kortrijk (heule)",
    "sg:classifiers":[
        {
            "category":"Professional",
            "subcategory":"Management & Consulting",
            "type":"Services"
        }
    ],
    "sg:phone":"+32 56 37 18 02",
    "sg:postcode":"8501",
    "sg:province":"West-Vlaanderen",
    "sg:tags":[
        "consultant"
    ],
    "wof:name":"Jbl Consulting Cv",
    "wof:placetype":"venue"
},
  "geometry": {"coordinates":[3.2279970646,50.8441352844],"type":"Point"}
}