{
  "type": "Feature",
  "properties": {
    "addr:full":"Rue De L'institut 12 Rixensart Brabant Wallon 1330",
    "addr:housenumber":"12",
    "addr:postcode":"1330",
    "addr:street":"Rue De L'Institut;Wallon",
    "iso:country":"BE",
    "sg:address":"Rue De L'institut 12",
    "sg:city":"Rixensart",
    "sg:classifiers":[
        {
            "category":"Health Services",
            "subcategory":"Health Practitioner",
            "type":"Services"
        }
    ],
    "sg:phone":"+32 2 653 63 31",
    "sg:postcode":"1330",
    "sg:province":"Brabant Wallon",
    "sg:tags":[
        "physiotherapist"
    ],
    "wof:name":"Francis C",
    "wof:placetype":"venue"
},
  "geometry": {"coordinates":[4.5305981636,50.7165184021],"type":"Point"}
}