{
  "type": "Feature",
  "properties": {
    "iso:country":"BE",
    "sg:address":"Eksterdreef 13",
    "sg:city":"Keerbergen",
    "sg:classifiers":[
        {
            "category":"Community Center",
            "subcategory":"Social",
            "type":"Public Place"
        }
    ],
    "sg:phone":"+32 15 23 01 90",
    "sg:postcode":"3140",
    "sg:province":"Vlaams-Brabant",
    "sg:tags":[
        "pencil",
        "pen"
    ],
    "wof:name":"Scribe Consult Bvba",
    "wof:placetype":"venue"
},
  "geometry": {"coordinates":[4.6646771431,51.0066757202],"type":"Point"}
}