{
  "type": "Feature",
  "properties": {
    "iso:country":"BE",
    "sg:address":"Smisstraat 14b1",
    "sg:city":"Riemst",
    "sg:orig_category":"Banques and organismes de cr\u00e9dit",
    "sg:phone":"+32 12 45 18 95",
    "sg:postcode":"3770",
    "sg:province":"Limburg",
    "wof:name":"Kbc",
    "wof:placetype":"venue"
},
  "geometry": {"coordinates":[5.5913767815,50.8335647583],"type":"Point"}
}