{
  "type": "Feature",
  "properties": {
    "iso:country":"BE",
    "sg:address":"Rue Des Aulnois 5",
    "sg:city":"Braine-le-comte (hennuy\u00e8res)",
    "sg:classifiers":[
        {
            "category":"Professional",
            "subcategory":"Detective & Security Services",
            "type":"Services"
        }
    ],
    "sg:phone":"+32 67 55 30 39",
    "sg:postcode":"7090",
    "sg:province":"Hainaut",
    "sg:tags":[
        "consultant"
    ],
    "wof:name":"Leroux P Consulting",
    "wof:placetype":"venue"
},
  "geometry": {"coordinates":[4.1848502159,50.6406860352],"type":"Point"}
}