{
  "type": "Feature",
  "properties": {
    "addr:full":"Rue De L'industrie 264 Frameries (la Bouverie) Hainaut 7080",
    "addr:housenumber":"264",
    "addr:postcode":"7080",
    "addr:street":"Rue De L'Industrie",
    "iso:country":"BE",
    "sg:address":"Rue De L'industrie 264",
    "sg:city":"Frameries (la Bouverie)",
    "sg:classifiers":[
        {
            "category":"Autos & Motor Vehicles",
            "subcategory":"Automobile Sales",
            "type":"Retail Goods"
        }
    ],
    "sg:phone":"+32 65 06 06 24",
    "sg:postcode":"7080",
    "sg:province":"Hainaut",
    "sg:tags":[
        "car",
        "used",
        "-"
    ],
    "wof:name":"Scoop-auto",
    "wof:placetype":"venue"
},
  "geometry": {"coordinates":[3.8863549232,50.408115387],"type":"Point"}
}