{
  "type": "Feature",
  "properties": {
    "iso:country":"BE",
    "sg:address":"Hoogkouter 39",
    "sg:city":"Anzegem",
    "sg:orig_category":"Installation de menuiserie m\u00e9tallique. Installation de menuiserie en bois and plastique",
    "sg:phone":"+32 56 68 13 02",
    "sg:postcode":"8573",
    "sg:province":"West-Vlaanderen",
    "wof:name":"Geco",
    "wof:placetype":"venue"
},
  "geometry": {"coordinates":[3.4706730843,50.8070106506],"type":"Point"}
}