{
  "type": "Feature",
  "properties": {
    "addr:full":"Leopold De Waelstraat 26 Antwerpen Antwerpen 2000",
    "addr:housenumber":"26",
    "addr:postcode":"2000",
    "addr:street":"Leopold De Waelstraat",
    "iso:country":"BE",
    "sg:address":"Leopold De Waelstraat 26",
    "sg:city":"Antwerpen",
    "sg:classifiers":[
        {
            "category":"Real Estate",
            "subcategory":"Architect",
            "type":"Services"
        }
    ],
    "sg:phone":"+32 3 237 94 56",
    "sg:postcode":"2000",
    "sg:province":"Antwerpen",
    "wof:name":"Aerts R",
    "wof:placetype":"venue"
},
  "geometry": {"coordinates":[4.3916211128,51.207736969],"type":"Point"}
}