{
  "type": "Feature",
  "properties": {
    "iso:country":"BE",
    "sg:address":"Avenue V\u00c9sale 34",
    "sg:city":"Wavre",
    "sg:orig_category":"Diverse bouwinstallaties Diverse metaalwaren Fab",
    "sg:phone":"+32 10 22 41 89",
    "sg:postcode":"1300",
    "sg:province":"Brabant Wallon",
    "wof:name":"Bertrand & Cie",
    "wof:placetype":"venue"
},
  "geometry": {"coordinates":[4.5807271004,50.7364997864],"type":"Point"}
}