{
  "type": "Feature",
  "properties": {
    "addr:full":"Pastoor Paquaylaan 186 Heusden-zolder (heusden) Limburg 3550",
    "addr:housenumber":"186",
    "addr:postcode":"3550",
    "addr:street":"Pastoor Paquaylaan",
    "iso:country":"BE",
    "sg:address":"Pastoor Paquaylaan 186",
    "sg:city":"Heusden-zolder (heusden)",
    "sg:classifiers":[
        {
            "category":"Professional",
            "subcategory":"Management & Consulting",
            "type":"Services"
        }
    ],
    "sg:phone":"+32 11 57 11 37",
    "sg:postcode":"3550",
    "sg:province":"Limburg",
    "sg:tags":[
        "tax-consultants"
    ],
    "wof:name":"Vanspauwen L",
    "wof:placetype":"venue"
},
  "geometry": {"coordinates":[5.3230891228,51.048084259],"type":"Point"}
}