{
  "type": "Feature",
  "properties": {
    "addr:full":"Avenue Du Monument 9 Marche-en-famenne Luxembourg 6900",
    "addr:housenumber":"9",
    "addr:postcode":"6900",
    "addr:street":"Avenue Du Monument",
    "iso:country":"BE",
    "sg:address":"Avenue Du Monument 9",
    "sg:city":"Marche-en-famenne",
    "sg:orig_category":"Traitements param\u00e9dicaux",
    "sg:phone":"+32 84 31 20 59",
    "sg:postcode":"6900",
    "sg:province":"Luxembourg",
    "wof:name":"Isabelle Lefevre",
    "wof:placetype":"venue"
},
  "geometry": {"coordinates":[5.3427119255,50.2248077393],"type":"Point"}
}