{
  "type": "Feature",
  "properties": {
    "iso:country":"BE",
    "sg:address":"5\u00e8me Avenue 44",
    "sg:city":"Charleroi (marcinelle)",
    "sg:classifiers":[
        {
            "category":"Communications",
            "type":"Services"
        }
    ],
    "sg:phone":"+32 71 36 41 56",
    "sg:postcode":"6001",
    "sg:province":"Hainaut",
    "sg:tags":[
        "translator"
    ],
    "wof:name":"C.a. Langues",
    "wof:placetype":"venue"
},
  "geometry": {"coordinates":[4.4393482208,50.3564758301],"type":"Point"}
}