{
  "type": "Feature",
  "properties": {
    "addr:full":"Rue Des Communes 76 Chastre (gentinnes) Brabant Wallon 1450",
    "addr:housenumber":"76",
    "addr:postcode":"1450",
    "addr:street":"Rue Des Communes;Wallon",
    "iso:country":"BE",
    "sg:address":"Rue Des Communes 76",
    "sg:city":"Chastre (gentinnes)",
    "sg:classifiers":[
        {
            "category":"Parking",
            "subcategory":"Lot",
            "type":"Transportation"
        }
    ],
    "sg:phone":"+32 71 87 59 83",
    "sg:postcode":"1450",
    "sg:province":"Brabant Wallon",
    "sg:tags":[
        "-",
        "livestock",
        "transport"
    ],
    "wof:name":"Colin C",
    "wof:placetype":"venue"
},
  "geometry": {"coordinates":[4.5967698097,50.5671768188],"type":"Point"}
}