{
  "type": "Feature",
  "properties": {
    "iso:country":"BE",
    "sg:address":"Rue Louis Delattre 35",
    "sg:city":"Fontaine-l'ev\u00eaque",
    "sg:classifiers":[
        {
            "category":"Retail",
            "subcategory":"Event Space",
            "type":"Services"
        }
    ],
    "sg:phone":"+32 71 54 19 07",
    "sg:postcode":"6140",
    "sg:province":"Hainaut",
    "sg:tags":[
        "rental",
        "-",
        "hall"
    ],
    "wof:name":"Le Grand Palais De Chine",
    "wof:placetype":"venue"
},
  "geometry": {"coordinates":[-111.9644622803,46.2507972717],"type":"Point"}
}