{
  "type": "Feature",
  "properties": {
    "addr:full":"Rue Dewez 47 Namur Namur 5000",
    "addr:housenumber":"47",
    "addr:postcode":"5000",
    "addr:street":"Rue Dewez",
    "iso:country":"BE",
    "sg:address":"Rue Dewez 47",
    "sg:city":"Namur",
    "sg:classifiers":[
        {
            "category":"Real Estate",
            "subcategory":"Architect",
            "type":"Services"
        }
    ],
    "sg:phone":"+32 81 26 21 34",
    "sg:postcode":"5000",
    "sg:province":"Namur",
    "wof:name":"Mouligneau R",
    "wof:placetype":"venue"
},
  "geometry": {"coordinates":[4.868748188,50.4682693481],"type":"Point"}
}