{
  "type": "Feature",
  "properties": {
    "addr:full":"Slypesteenweg 41 Middelkerke West-Vlaanderen 8433",
    "addr:housenumber":"41",
    "addr:postcode":"8433",
    "addr:street":"Slypesteenweg",
    "iso:country":"BE",
    "sg:address":"Slypesteenweg 41",
    "sg:city":"Middelkerke",
    "sg:orig_category":"Eleveurs de bovins",
    "sg:phone":"+32 59 30 09 61",
    "sg:postcode":"8433",
    "sg:province":"West-Vlaanderen",
    "wof:name":"Fa. Devriendt",
    "wof:placetype":"venue"
},
  "geometry": {"coordinates":[2.8475210667,51.1547775269],"type":"Point"}
}