{
  "type": "Feature",
  "properties": {
    "iso:country":"BE",
    "sg:address":"Rue Du Qu\u00c9niau 24",
    "sg:city":"Hensies",
    "sg:classifiers":[
        {
            "category":"Arena",
            "subcategory":"Sports Club",
            "type":"Entertainment"
        }
    ],
    "sg:phone":"+32 65 65 08 23",
    "sg:postcode":"7350",
    "sg:province":"Hainaut",
    "sg:tags":[
        "terrain",
        "hors",
        "de",
        "installation",
        "sportifs"
    ],
    "wof:name":"A.s. De Baisieux",
    "wof:placetype":"venue"
},
  "geometry": {"coordinates":[3.7475020885,50.4252586365],"type":"Point"}
}