{
  "type": "Feature",
  "properties": {
    "addr:full":"Sint-katarinalaan 9 Hasselt Limburg 3500",
    "addr:housenumber":"9",
    "addr:postcode":"3500",
    "addr:street":"Sint-Katarinalaan",
    "iso:country":"BE",
    "sg:address":"Sint-katarinalaan 9",
    "sg:city":"Hasselt",
    "sg:orig_category":"S\u00e9curit\u00e9 sociale",
    "sg:phone":"+32 11 26 27 98",
    "sg:postcode":"3500",
    "sg:province":"Limburg",
    "wof:name":"Onafhank. Ziekenfonds 503",
    "wof:placetype":"venue"
},
  "geometry": {"coordinates":[5.3496460915,50.9263687134],"type":"Point"}
}