{
  "type": "Feature",
  "properties": {
    "iso:country":"BE",
    "sg:address":"Rue Des Tuileries 7",
    "sg:city":"Mons",
    "sg:classifiers":[
        {
            "category":"Social Services",
            "type":"Services"
        }
    ],
    "sg:phone":"+32 65 34 94 51",
    "sg:postcode":"7000",
    "sg:province":"Hainaut",
    "wof:name":"Prisme (le)",
    "wof:placetype":"venue"
},
  "geometry": {"coordinates":[3.9620809555,50.4683494568],"type":"Point"}
}