{
  "type": "Feature",
  "properties": {
    "addr:full":"Zwevezeelsestraat 64 Ardooie West-Vlaanderen 8851",
    "addr:housenumber":"64",
    "addr:postcode":"8851",
    "addr:street":"Zwevezeelsestraat",
    "iso:country":"BE",
    "sg:address":"Zwevezeelsestraat 64",
    "sg:city":"Ardooie",
    "sg:orig_category":"Woningbouw",
    "sg:phone":"+32 51 74 52 22",
    "sg:postcode":"8851",
    "sg:province":"West-Vlaanderen",
    "wof:name":"Tack Michel & Roger",
    "wof:placetype":"venue"
},
  "geometry": {"coordinates":[3.2088680267,51.0051116943],"type":"Point"}
}