{
  "type": "Feature",
  "properties": {
    "iso:country":"BE",
    "sg:address":"Wingene Steenweg 32",
    "sg:city":"Beernem",
    "sg:orig_category":"Imprimeries and copyshops",
    "sg:phone":"+32 50 78 81 06",
    "sg:postcode":"8730",
    "sg:province":"West-Vlaanderen",
    "wof:name":"Drukkerij De Prest",
    "wof:placetype":"venue"
},
  "geometry": {"coordinates":[3.3271849155,51.1255493164],"type":"Point"}
}