{
  "type": "Feature",
  "properties": {
    "iso:country":"BE",
    "sg:address":"Rue Marie-christine 171",
    "sg:city":"Bruxelles",
    "sg:orig_category":"Ice-cream parlours",
    "sg:phone":"+32 2 425 01 42",
    "sg:postcode":"1020",
    "sg:province":"Bruxelles-Capitale",
    "wof:name":"Roma (glacier)",
    "wof:placetype":"venue"
},
  "geometry": {"coordinates":[4.3505549431,50.8765525818],"type":"Point"}
}