{
  "type": "Feature",
  "properties": {
    "iso:country":"BE",
    "sg:address":"Piers De Raveschootlaan 36",
    "sg:city":"Knokke-heist",
    "sg:orig_category":"Slagers",
    "sg:phone":"+32 50 60 18 39",
    "sg:postcode":"8300",
    "sg:province":"West-Vlaanderen",
    "wof:name":"Roger Desutter",
    "wof:placetype":"venue"
},
  "geometry": {"coordinates":[3.2889759541,51.3425369263],"type":"Point"}
}