{
  "type": "Feature",
  "properties": {
    "addr:full":"Gravin De Stembierstraat 20 Hasselt (sint-lambrechts-herk) Limburg 3500",
    "addr:housenumber":"20",
    "addr:postcode":"3500",
    "addr:street":"Gravin;Stembierstraat",
    "iso:country":"BE",
    "sg:address":"Gravin De Stembierstraat 20",
    "sg:city":"Hasselt (sint-lambrechts-herk)",
    "sg:classifiers":[
        {
            "category":"Health Services",
            "subcategory":"Health Practitioner",
            "type":"Services"
        }
    ],
    "sg:phone":"+32 11 31 19 27",
    "sg:postcode":"3500",
    "sg:province":"Limburg",
    "sg:tags":[
        "physiotherapist"
    ],
    "wof:name":"Jans E",
    "wof:placetype":"venue"
},
  "geometry": {"coordinates":[5.3049631119,50.9023132324],"type":"Point"}
}