{
  "type": "Feature",
  "properties": {
    "addr:full":"Sint-jansstraat 30 Brussel/bruxelles Bruxelles-Capitale 1000",
    "addr:housenumber":"30",
    "addr:postcode":"1000",
    "addr:street":"Sint-Jansstraat;/",
    "iso:country":"BE",
    "sg:address":"Sint-jansstraat 30",
    "sg:city":"Brussel/bruxelles",
    "sg:orig_category":"Boekenuitgeverijen Muziekinstrumenten",
    "sg:phone":"+32 2 512 39 80",
    "sg:postcode":"1000",
    "sg:province":"Bruxelles-Capitale",
    "wof:name":"Schott Fr\u00cares",
    "wof:placetype":"venue"
},
  "geometry": {"coordinates":[4.3538880348,50.8443603516],"type":"Point"}
}