{
  "type": "Feature",
  "properties": {
    "addr:full":"Vloeiweg 1 Wuustwezel Antwerpen 2990",
    "addr:housenumber":"1",
    "addr:postcode":"2990",
    "addr:street":"Vloeiweg",
    "iso:country":"BE",
    "sg:address":"Vloeiweg 1",
    "sg:city":"Wuustwezel",
    "sg:orig_category":"Boomkwekerijen",
    "sg:phone":"+32 3 669 58 07",
    "sg:postcode":"2990",
    "sg:province":"Antwerpen",
    "wof:name":"Hildegarde Van Hasselt",
    "wof:placetype":"venue"
},
  "geometry": {"coordinates":[4.6593332291,51.4057426453],"type":"Point"}
}