{
  "type": "Feature",
  "properties": {
    "iso:country":"BE",
    "sg:address":"Rijmenamsesteenweg 141",
    "sg:city":"Haacht",
    "sg:orig_category":"Enseignement maternel and primaire",
    "sg:phone":"+32 16 60 04 91",
    "sg:postcode":"3150",
    "sg:province":"Vlaams-Brabant",
    "wof:name":"Vrije Kleuterschool",
    "wof:placetype":"venue"
},
  "geometry": {"coordinates":[4.6151080132,50.9824066162],"type":"Point"}
}