{
  "type": "Feature",
  "properties": {
    "iso:country":"BE",
    "sg:address":"Rue Du Fort D'andoy 49",
    "sg:city":"Namur (wierde)",
    "sg:classifiers":[
        {
            "category":"Health Services",
            "subcategory":"Health Practitioner",
            "type":"Services"
        }
    ],
    "sg:phone":"+32 81 40 24 42",
    "sg:postcode":"5100",
    "sg:province":"Namur",
    "sg:tags":[
        "physiotherapist"
    ],
    "wof:name":"Fiasse Jacqueline",
    "wof:placetype":"venue"
},
  "geometry": {"coordinates":[4.9269809723,50.4379615784],"type":"Point"}
}