{
  "type": "Feature",
  "properties": {
    "addr:full":"Spoorwegstraat 45a Sint-truiden Limburg 3800",
    "addr:housenumber":"45a",
    "addr:postcode":"3800",
    "addr:street":"Spoorwegstraat",
    "iso:country":"BE",
    "sg:address":"Spoorwegstraat 45a",
    "sg:city":"Sint-truiden",
    "sg:classifiers":[
        {
            "category":"Professional",
            "type":"Services"
        }
    ],
    "sg:phone":"+32 11 67 17 01",
    "sg:postcode":"3800",
    "sg:province":"Limburg",
    "sg:tags":[
        "entertainer"
    ],
    "wof:name":"L & S Agency",
    "wof:placetype":"venue"
},
  "geometry": {"coordinates":[5.1782832146,50.8180656433],"type":"Point"}
}