{
  "type": "Feature",
  "properties": {
    "addr:full":"Chauss\u00c9e D'alsemberg 976 Ukkel/uccle Bruxelles-Capitale 1180",
    "addr:housenumber":"976",
    "addr:postcode":"1180",
    "addr:street":"Chausse\u0301E D'Alsemberg;/",
    "iso:country":"BE",
    "sg:address":"Chauss\u00c9e D'alsemberg 976",
    "sg:city":"Ukkel/uccle",
    "sg:orig_category":"Entretien and r\u00e9parations de voitures",
    "sg:phone":"+32 2 376 86 85",
    "sg:postcode":"1180",
    "sg:province":"Bruxelles-Capitale",
    "wof:name":"Carrosserie Week-end",
    "wof:placetype":"venue"
},
  "geometry": {"coordinates":[4.3334469795,50.7925643921],"type":"Point"}
}