{
  "type": "Feature",
  "properties": {
    "addr:full":"Hoogstraat 44bb Zutendaal Limburg 3690",
    "addr:housenumber":"44bb",
    "addr:postcode":"3690",
    "addr:street":"Hoogstraat",
    "iso:country":"BE",
    "sg:address":"Hoogstraat 44bb",
    "sg:city":"Zutendaal",
    "sg:orig_category":"Equipement photographique. Studios photographiques",
    "sg:phone":"+32 89 61 15 85",
    "sg:postcode":"3690",
    "sg:province":"Limburg",
    "wof:name":"Foto Sohl",
    "wof:placetype":"venue"
},
  "geometry": {"coordinates":[5.568862915,50.9345932007],"type":"Point"}
}