{
  "type": "Feature",
  "properties": {
    "iso:country":"BE",
    "sg:address":"Lieverstedestraat 14",
    "sg:city":"Oostkamp",
    "sg:orig_category":"Dakwerken",
    "sg:phone":"+32 50 82 66 89",
    "sg:postcode":"8020",
    "sg:province":"West-Vlaanderen",
    "wof:name":"Seydo",
    "wof:placetype":"venue"
},
  "geometry": {"coordinates":[3.2530910969,51.1684036255],"type":"Point"}
}