{
  "type": "Feature",
  "properties": {
    "addr:full":"Avenue L\u00c9opold Iii 31 Binche (groot) Hainaut 7134",
    "addr:housenumber":"31",
    "addr:postcode":"7134",
    "addr:street":"Avenue Le\u0301Opold Iii;Groot Hainaut",
    "iso:country":"BE",
    "sg:address":"Avenue L\u00c9opold Iii 31",
    "sg:city":"Binche (groot)",
    "sg:orig_category":"Plomberie, chauffage and installations sanitaires",
    "sg:phone":"+32 64 31 09 20",
    "sg:postcode":"7134",
    "sg:province":"Hainaut",
    "wof:name":"Druart",
    "wof:placetype":"venue"
},
  "geometry": {"coordinates":[4.2175779343,50.4159622192],"type":"Point"}
}