{
  "type": "Feature",
  "properties": {
    "iso:country":"BE",
    "sg:address":"Berlarij 74",
    "sg:city":"Lier",
    "sg:orig_category":"Diensten voor huisdieren",
    "sg:phone":"+32 3 489 17 46",
    "sg:postcode":"2500",
    "sg:province":"Antwerpen",
    "wof:name":"Hondenkapsalon Nancy",
    "wof:placetype":"venue"
},
  "geometry": {"coordinates":[4.5802431107,51.1283073425],"type":"Point"}
}