{
  "type": "Feature",
  "properties": {
    "addr:full":"G. Vandenheuvelstraat 129 Herselt (ramsel) Antwerpen 2230",
    "addr:housenumber":"129",
    "addr:postcode":"2230",
    "addr:street":"Vandenheuvelstraat",
    "iso:country":"BE",
    "sg:address":"G. Vandenheuvelstraat 129",
    "sg:city":"Herselt (ramsel)",
    "sg:classifiers":[
        {
            "category":"Mining & Drilling",
            "type":"Manufacturing & Wholesale Goods"
        }
    ],
    "sg:phone":"+32 13 77 81 96",
    "sg:postcode":"2230",
    "sg:province":"Antwerpen",
    "sg:tags":[
        "boring",
        "well"
    ],
    "wof:name":"V.t.s. Boringen Bvba",
    "wof:placetype":"venue"
},
  "geometry": {"coordinates":[4.8384580612,51.0239982605],"type":"Point"}
}