{
  "type": "Feature",
  "properties": {
    "addr:full":"Onze Lievenvrouwestraat 15b1 As Limburg 3668",
    "addr:housenumber":"3668",
    "addr:street":"Lievenvrouwestraat",
    "iso:country":"BE",
    "sg:address":"Onze Lievenvrouwestraat 15b1",
    "sg:city":"As",
    "sg:orig_category":"Gespecialiseerde residenti\u00eble bouw",
    "sg:phone":"+32 89 65 98 73",
    "sg:postcode":"3668",
    "sg:province":"Limburg",
    "wof:name":"Nys D.",
    "wof:placetype":"venue"
},
  "geometry": {"coordinates":[5.5994701385,51.0144691467],"type":"Point"}
}