{
  "type": "Feature",
  "properties": {
    "addr:full":"Waterhoekweg 34 Torhout West-Vlaanderen 8820",
    "addr:housenumber":"34",
    "addr:postcode":"8820",
    "addr:street":"Waterhoekweg",
    "iso:country":"BE",
    "sg:address":"Waterhoekweg 34",
    "sg:city":"Torhout",
    "sg:classifiers":[
        {
            "category":"Wholesale",
            "subcategory":"Medical Equipment & Supplies",
            "type":"Manufacturing & Wholesale Goods"
        }
    ],
    "sg:phone":"+32 50 21 23 20",
    "sg:postcode":"8820",
    "sg:province":"West-Vlaanderen",
    "sg:tags":[
        "aid",
        "hearing"
    ],
    "wof:name":"Hemeryck Bvba",
    "wof:placetype":"venue"
},
  "geometry": {"coordinates":[3.0844659805,51.0724487305],"type":"Point"}
}