{
  "type": "Feature",
  "properties": {
    "addr:full":"Groeningenveldstraat 6 Gooik Vlaams-Brabant 1755",
    "addr:housenumber":"6",
    "addr:postcode":"1755",
    "addr:street":"Groeningenveldstraat",
    "iso:country":"BE",
    "sg:address":"Groeningenveldstraat 6",
    "sg:city":"Gooik",
    "sg:orig_category":"Banques and organismes de cr\u00e9dit",
    "sg:phone":"+32 2 532 45 05",
    "sg:postcode":"1755",
    "sg:province":"Vlaams-Brabant",
    "wof:name":"Ippa",
    "wof:placetype":"venue"
},
  "geometry": {"coordinates":[4.1224040985,50.7834396362],"type":"Point"}
}