{
  "type": "Feature",
  "properties": {
    "addr:full":"Delaeystraat 27 Hooglede West-Vlaanderen 8830",
    "addr:housenumber":"27",
    "addr:postcode":"8830",
    "addr:street":"Delaeystraat",
    "iso:country":"BE",
    "sg:address":"Delaeystraat 27",
    "sg:city":"Hooglede",
    "sg:orig_category":"Airconditioning and ventilatie Diverse bouwafwerking and reiniging Installatie van houten of kunstst",
    "sg:phone":"+32 51 70 38 27",
    "sg:postcode":"8830",
    "sg:province":"West-Vlaanderen",
    "wof:name":"Frans Coghe",
    "wof:placetype":"venue"
},
  "geometry": {"coordinates":[3.0345630646,50.995765686],"type":"Point"}
}