{
  "type": "Feature",
  "properties": {
    "addr:full":"Rue Du Limbourg 22 Li\u00e8ge 1 Li\u00e8ge 4000",
    "addr:housenumber":"22;1",
    "addr:postcode":"4000",
    "addr:street":"Rue Du Limbourg",
    "iso:country":"BE",
    "sg:address":"Rue Du Limbourg 22",
    "sg:city":"Li\u00e8ge 1",
    "sg:classifiers":[
        {
            "category":"Communications",
            "type":"Services"
        }
    ],
    "sg:phone":"+32 4 224 24 31",
    "sg:postcode":"4000",
    "sg:province":"Li\u00e8ge",
    "sg:tags":[
        "translator"
    ],
    "wof:name":"Connexion Sc",
    "wof:placetype":"venue"
},
  "geometry": {"coordinates":[5.5652809143,50.6561584473],"type":"Point"}
}