{
  "type": "Feature",
  "properties": {
    "addr:full":"Brusselsesteenweg 840 Asse Vlaams-Brabant 1731",
    "addr:housenumber":"840",
    "addr:postcode":"1731",
    "addr:street":"Brusselsesteenweg",
    "iso:country":"BE",
    "sg:address":"Brusselsesteenweg 840",
    "sg:city":"Asse",
    "sg:orig_category":"Sportclubs",
    "sg:phone":"+32 2 466 89 20",
    "sg:postcode":"1731",
    "sg:province":"Vlaams-Brabant",
    "wof:name":"Sportkring Handbal",
    "wof:placetype":"venue"
},
  "geometry": {"coordinates":[4.2873268127,50.8745117188],"type":"Point"}
}