{
  "type": "Feature",
  "properties": {
    "addr:full":"Brusselsestraat 43 Dendermonde Oost-Vlaanderen 9200",
    "addr:housenumber":"43",
    "addr:postcode":"9200",
    "addr:street":"Brusselsestraat;Oost-Vlaanderen",
    "iso:country":"BE",
    "sg:address":"Brusselsestraat 43",
    "sg:city":"Dendermonde",
    "sg:classifiers":[
        {
            "category":"Shopping",
            "subcategory":"Clothing, Apparel, & Fashions",
            "type":"Retail Goods"
        }
    ],
    "sg:phone":"+32 52 21 94 92",
    "sg:postcode":"9200",
    "sg:province":"Oost-Vlaanderen",
    "sg:tags":[
        "v\u00eatements",
        "pour",
        "dame"
    ],
    "wof:name":"Huis Podium",
    "wof:placetype":"venue"
},
  "geometry": {"coordinates":[4.0996260643,51.027469635],"type":"Point"}
}