{
  "type": "Feature",
  "properties": {
    "addr:full":"Lange Nieuwstraat 43 Antwerpen Antwerpen 2000",
    "addr:housenumber":"43",
    "addr:postcode":"2000",
    "addr:street":"Lange Nieuwstraat",
    "iso:country":"BE",
    "sg:address":"Lange Nieuwstraat 43",
    "sg:city":"Antwerpen",
    "sg:orig_category":"Advocaten and juridische adviseurs",
    "sg:phone":"+32 3 206 78 78",
    "sg:postcode":"2000",
    "sg:province":"Antwerpen",
    "wof:name":"P. Van Geem",
    "wof:placetype":"venue"
},
  "geometry": {"coordinates":[4.4084711075,51.2198982239],"type":"Point"}
}