{
  "type": "Feature",
  "properties": {
    "addr:full":"Ophovenstraat 139 Meeuwen-gruitrode (gruitrode) Limburg 3670",
    "addr:housenumber":"139",
    "addr:postcode":"3670",
    "addr:street":"Ophovenstraat",
    "iso:country":"BE",
    "sg:address":"Ophovenstraat 139",
    "sg:city":"Meeuwen-gruitrode (gruitrode)",
    "sg:classifiers":[
        {
            "category":"Autos & Motor Vehicles",
            "subcategory":"Automobile Sales",
            "type":"Retail Goods"
        }
    ],
    "sg:phone":"+32 89 85 44 75",
    "sg:postcode":"3670",
    "sg:province":"Limburg",
    "sg:tags":[
        "car",
        "used",
        "-"
    ],
    "wof:name":"Kerkhofs J",
    "wof:placetype":"venue"
},
  "geometry": {"coordinates":[5.5348110199,51.0683021545],"type":"Point"}
}