{
  "type": "Feature",
  "properties": {
    "iso:country":"BE",
    "sg:address":"Liersesteenweg 9",
    "sg:city":"Nijlen",
    "sg:orig_category":"Pain, p\u00e2tisseries and confiseries",
    "sg:phone":"+32 3 480 12 65",
    "sg:postcode":"2560",
    "sg:province":"Antwerpen",
    "wof:name":"Godelieve Dockx",
    "wof:placetype":"venue"
},
  "geometry": {"coordinates":[4.6245760918,51.1390342712],"type":"Point"}
}