{
  "type": "Feature",
  "properties": {
    "addr:full":"Rue Du Herdeau 43 Couvin Namur 5660",
    "addr:housenumber":"43",
    "addr:postcode":"5660",
    "addr:street":"Rue Du Herdeau",
    "iso:country":"BE",
    "sg:address":"Rue Du Herdeau 43",
    "sg:city":"Couvin",
    "sg:classifiers":[
        {
            "category":"Health Services",
            "subcategory":"Health Practitioner",
            "type":"Services"
        }
    ],
    "sg:phone":"+32 60 34 75 06",
    "sg:postcode":"5660",
    "sg:province":"Namur",
    "sg:tags":[
        "physiotherapist"
    ],
    "wof:name":"Biard Th\u00e9r\u00e8se",
    "wof:placetype":"venue"
},
  "geometry": {"coordinates":[4.5026497841,50.0393218994],"type":"Point"}
}