{
  "type": "Feature",
  "properties": {
    "addr:full":"Avenue De La Coop\u00c9ration 49 Soumagne Li\u00e8ge 4630",
    "addr:housenumber":"49",
    "addr:postcode":"4630",
    "addr:street":"Avenue De La Coope\u0301Ration",
    "iso:country":"BE",
    "sg:address":"Avenue De La Coop\u00c9ration 49",
    "sg:city":"Soumagne",
    "sg:orig_category":"Catering and organisation de f\u00eates",
    "sg:phone":"+32 4 377 49 30",
    "sg:postcode":"4630",
    "sg:province":"Li\u00e8ge",
    "wof:name":"Raymond Vandermeulen",
    "wof:placetype":"venue"
},
  "geometry": {"coordinates":[5.7297840118,50.6337051392],"type":"Point"}
}