{
  "type": "Feature",
  "properties": {
    "addr:full":"Rue De Chimay 3 Sivry-rance Hainaut 6470",
    "addr:housenumber":"3",
    "addr:postcode":"6470",
    "addr:street":"Rue De Chimay",
    "iso:country":"BE",
    "sg:address":"Rue De Chimay 3",
    "sg:city":"Sivry-rance",
    "sg:orig_category":"Artsen and specialisten",
    "sg:phone":"+32 60 41 25 00",
    "sg:postcode":"6470",
    "sg:province":"Hainaut",
    "wof:name":"Andr\u00c9 Weverbergh",
    "wof:placetype":"venue"
},
  "geometry": {"coordinates":[4.2183971405,50.1861000061],"type":"Point"}
}