{
  "type": "Feature",
  "properties": {
    "addr:full":"Biesbosstraat 6 Meeuwen-gruitrode Limburg 3670",
    "addr:housenumber":"6",
    "addr:postcode":"3670",
    "addr:street":"Biesbosstraat",
    "iso:country":"BE",
    "sg:address":"Biesbosstraat 6",
    "sg:city":"Meeuwen-gruitrode",
    "sg:orig_category":"Industri\u00eble and commerci\u00eble bouw",
    "sg:phone":"+32 11 79 35 86",
    "sg:postcode":"3670",
    "sg:province":"Limburg",
    "wof:name":"Eddy Jehoul Industriebouw",
    "wof:placetype":"venue"
},
  "geometry": {"coordinates":[5.5397939682,51.1080360413],"type":"Point"}
}