{
  "type": "Feature",
  "properties": {
    "iso:country":"BE",
    "sg:address":"Schollebeekstraat 29",
    "sg:city":"Lier",
    "sg:classifiers":[
        {
            "category":"Organizations",
            "subcategory":"Community Association",
            "type":"Services"
        }
    ],
    "sg:phone":"+32 3 480 09 40",
    "sg:postcode":"2500",
    "sg:province":"Antwerpen",
    "sg:tags":[
        "box",
        "cardboard"
    ],
    "wof:name":"Donckers Cartonnages Nv",
    "wof:placetype":"venue"
},
  "geometry": {"coordinates":[4.5836958885,51.1185455322],"type":"Point"}
}