{
  "type": "Feature",
  "properties": {
    "iso:country":"BE",
    "sg:address":"Vleminckstraat 5",
    "sg:city":"Antwerpen",
    "sg:classifiers":[
        {
            "category":"Professional",
            "subcategory":"Management & Consulting",
            "type":"Services"
        }
    ],
    "sg:phone":"+32 3 224 83 93",
    "sg:postcode":"2000",
    "sg:province":"Antwerpen",
    "sg:tags":[
        "marketing",
        "-",
        "consultant"
    ],
    "wof:name":"Crea",
    "wof:placetype":"venue"
},
  "geometry": {"coordinates":[4.4033360481,51.220035553],"type":"Point"}
}