{
  "type": "Feature",
  "properties": {
    "iso:country":"BE",
    "sg:address":"Spoorwegstraat 1",
    "sg:city":"Waasmunster",
    "sg:classifiers":[
        {
            "category":"Cafe",
            "type":"Food & Drink"
        }
    ],
    "sg:phone":"+32 52 46 02 89",
    "sg:postcode":"9250",
    "sg:province":"Oost-Vlaanderen",
    "sg:tags":[
        "caf\u00e9s"
    ],
    "wof:name":"Caf\u00c9 Den Eyck",
    "wof:placetype":"venue"
},
  "geometry": {"coordinates":[4.100976944,51.1150932312],"type":"Point"}
}