{
  "type": "Feature",
  "properties": {
    "addr:full":"Galgestraat 3 Heuvelland West-Vlaanderen 8953",
    "addr:housenumber":"3",
    "addr:postcode":"8953",
    "addr:street":"Galgestraat",
    "iso:country":"BE",
    "sg:address":"Galgestraat 3",
    "sg:city":"Heuvelland",
    "sg:orig_category":"Eleveurs de volaille",
    "sg:phone":"+32 57 44 58 24",
    "sg:postcode":"8953",
    "sg:province":"West-Vlaanderen",
    "wof:name":"Erik Caignie",
    "wof:placetype":"venue"
},
  "geometry": {"coordinates":[2.8967330456,50.7724304199],"type":"Point"}
}