{
  "type": "Feature",
  "properties": {
    "addr:full":"Voie De L'ardenne 101 Chaudfontaine Li\u00e8ge 4053",
    "addr:housenumber":"101",
    "addr:postcode":"4053",
    "addr:street":"Voie De L'Ardenne",
    "iso:country":"BE",
    "sg:address":"Voie De L'ardenne 101",
    "sg:city":"Chaudfontaine",
    "sg:orig_category":"Onderdelen and accessoires voor auto's",
    "sg:phone":"+32 4 365 44 24",
    "sg:postcode":"4053",
    "sg:province":"Li\u00e8ge",
    "wof:name":"Embourg Pneu Service",
    "wof:placetype":"venue"
},
  "geometry": {"coordinates":[5.6067109108,50.5908546448],"type":"Point"}
}