{
  "type": "Feature",
  "properties": {
    "iso:country":"BE",
    "sg:address":"Rue Joseph Wauters 106",
    "sg:city":"Binche",
    "sg:orig_category":"Elektrische installaties voor woningen Paramedische behandelingen",
    "sg:phone":"+32 64 33 77 09",
    "sg:postcode":"7134",
    "sg:province":"Hainaut",
    "wof:name":"Logop\u00c9d. Colpaert-pistone",
    "wof:placetype":"venue"
},
  "geometry": {"coordinates":[4.1805801392,50.4309883118],"type":"Point"}
}