{
  "type": "Feature",
  "properties": {
    "iso:country":"BE",
    "sg:address":"Grand Place 21",
    "sg:city":"Paliseul",
    "sg:classifiers":[
        {
            "category":"Fast Food",
            "type":"Food & Drink"
        }
    ],
    "sg:phone":"+32 61 53 47 33",
    "sg:postcode":"6850",
    "sg:province":"Luxembourg",
    "sg:tags":[
        "fried",
        "stand",
        "potato"
    ],
    "wof:name":"Verlaine (friterie Le)",
    "wof:placetype":"venue"
},
  "geometry": {"coordinates":[5.1356158257,49.9039306641],"type":"Point"}
}