{
  "type": "Feature",
  "properties": {
    "addr:full":"Volderstr 46 Oeselgem 8788",
    "addr:housenumber":"46",
    "addr:postcode":"8788",
    "addr:street":"Volderstr;Oeselgem",
    "iso:country":"BE",
    "sg:address":"Volderstr 46",
    "sg:city":"Oeselgem",
    "sg:classifiers":[
        {
            "category":"Banks & Credit Unions",
            "subcategory":"Bank",
            "type":"Services"
        }
    ],
    "sg:phone":"+32 53 88 97 72",
    "sg:postcode":"8788",
    "wof:name":"Famibank",
    "wof:placetype":"venue"
},
  "geometry": {"coordinates":[3.422962904,50.9429168701],"type":"Point"}
}