{
  "type": "Feature",
  "properties": {
    "addr:full":"Rue Souverain-pont 9 Li\u00e8ge 1 Li\u00e8ge 4000",
    "addr:housenumber":"9;1",
    "addr:postcode":"4000",
    "addr:street":"Rue Souverain-Pont",
    "iso:country":"BE",
    "sg:address":"Rue Souverain-pont 9",
    "sg:city":"Li\u00e8ge 1",
    "sg:classifiers":[
        {
            "category":"Cafe",
            "type":"Food & Drink"
        }
    ],
    "sg:phone":"+32 4 223 27 13",
    "sg:postcode":"4000",
    "sg:province":"Li\u00e8ge",
    "sg:tags":[
        "snack-bars"
    ],
    "wof:name":"Pita Atlantic",
    "wof:placetype":"venue"
},
  "geometry": {"coordinates":[5.574848175,50.6444587708],"type":"Point"}
}