{
  "type": "Feature",
  "properties": {
    "iso:country":"BE",
    "sg:address":"Rue Joseph Lizon 34",
    "sg:city":"Chievres",
    "sg:orig_category":"Musea and historische gebouwen",
    "sg:phone":"+32 69 68 94 27",
    "sg:postcode":"7950",
    "sg:province":"Hainaut",
    "wof:name":"Mus\u00c9e De La Vie Rurale",
    "wof:placetype":"venue"
},
  "geometry": {"coordinates":[3.7478559017,50.568977356],"type":"Point"}
}