{
  "type": "Feature",
  "properties": {
    "iso:country":"BE",
    "sg:address":"Heilige-geeststraat 76",
    "sg:city":"Leuven",
    "sg:classifiers":[
        {
            "category":"Communications",
            "subcategory":"Film & Video Production",
            "type":"Services"
        }
    ],
    "sg:phone":"+32 16 23 83 93",
    "sg:postcode":"3000",
    "sg:province":"Vlaams-Brabant",
    "sg:tags":[
        "realisation",
        "-"
    ],
    "wof:name":"Hit The Road!",
    "wof:placetype":"venue"
},
  "geometry": {"coordinates":[4.6886949539,50.8766288757],"type":"Point"}
}