{
  "type": "Feature",
  "properties": {
    "addr:full":"Place Du Vingt-ao\u00dbt 19 Li\u00c8ge Li\u00e8ge 4000",
    "addr:housenumber":"19",
    "addr:postcode":"4000",
    "addr:street":"Place Du Vingt-Aou\u0302T",
    "iso:country":"BE",
    "sg:address":"Place Du Vingt-ao\u00dbt 19",
    "sg:city":"Li\u00c8ge",
    "sg:classifiers":[
        {
            "category":"Personal",
            "subcategory":"Beauty Salon",
            "type":"Services"
        }
    ],
    "sg:phone":"+32 4 221 05 31",
    "sg:postcode":"4000",
    "sg:province":"Li\u00e8ge",
    "sg:tags":[
        "de",
        "coiffure"
    ],
    "wof:name":"Coiffure Valentiny",
    "wof:placetype":"venue"
},
  "geometry": {"coordinates":[5.5763812065,50.6395721436],"type":"Point"}
}