{
  "type": "Feature",
  "properties": {
    "addr:full":"Nieuwedokstraat 34 Oostende (stene) West-Vlaanderen 8400",
    "addr:housenumber":"34",
    "addr:postcode":"8400",
    "addr:street":"Nieuwedokstraat",
    "iso:country":"BE",
    "sg:address":"Nieuwedokstraat 34",
    "sg:city":"Oostende (stene)",
    "sg:classifiers":[
        {
            "category":"Personal",
            "subcategory":"Beauty Salon",
            "type":"Services"
        }
    ],
    "sg:phone":"+32 59 70 01 73",
    "sg:postcode":"8400",
    "sg:province":"West-Vlaanderen",
    "sg:tags":[
        "lady",
        "-",
        "hairdressing"
    ],
    "wof:name":"Ingrid",
    "wof:placetype":"venue"
},
  "geometry": {"coordinates":[2.9345641136,51.2164077759],"type":"Point"}
}