{
  "type": "Feature",
  "properties": {
    "addr:full":"Handelsstraat 142 Londerzeel (malderen) Vlaams-Brabant 1840",
    "addr:housenumber":"142",
    "addr:postcode":"1840",
    "addr:street":"Handelsstraat",
    "iso:country":"BE",
    "sg:address":"Handelsstraat 142",
    "sg:city":"Londerzeel (malderen)",
    "sg:orig_category":"Newspapers, magazines, periodicals - Distribution",
    "sg:phone":"+32 52 33 27 65",
    "sg:postcode":"1840",
    "sg:province":"Vlaams-Brabant",
    "wof:name":"Dagbladhandel Kurt",
    "wof:placetype":"venue"
},
  "geometry": {"coordinates":[4.2302789688,51.0149726868],"type":"Point"}
}