{
  "type": "Feature",
  "properties": {
    "addr:full":"Rue Luciflore 16 Waremme Li\u00e8ge 4300",
    "addr:housenumber":"16",
    "addr:postcode":"4300",
    "addr:street":"Rue Luciflore",
    "iso:country":"BE",
    "sg:address":"Rue Luciflore 16",
    "sg:city":"Waremme",
    "sg:orig_category":"Pain, p\u00e2tisseries and confiseries",
    "sg:phone":"+32 19 32 85 41",
    "sg:postcode":"4300",
    "sg:province":"Li\u00e8ge",
    "wof:name":"M Velkeneers",
    "wof:placetype":"venue"
},
  "geometry": {"coordinates":[5.2513680458,50.6890258789],"type":"Point"}
}