{
  "type": "Feature",
  "properties": {
    "addr:full":"Pierstraat 442 Aartselaar Antwerpen 2630",
    "addr:housenumber":"442",
    "addr:postcode":"2630",
    "addr:street":"Pierstraat",
    "iso:country":"BE",
    "sg:address":"Pierstraat 442",
    "sg:city":"Aartselaar",
    "sg:orig_category":"Equipements divers pour l\u00b4industrie Gr. Locations de machines and \u00e9quipement pour la construction",
    "sg:phone":"+32 3 888 36 34",
    "sg:postcode":"2630",
    "sg:province":"Antwerpen",
    "wof:name":"Special Lifting Services",
    "wof:placetype":"venue"
},
  "geometry": {"coordinates":[4.3584480286,51.1099815369],"type":"Point"}
}