{
  "type": "Feature",
  "properties": {
    "addr:full":"Avenue G\u00e9n\u00e9ral De Longueville 20 Box 6 Bruxelles (woluwe-saint-pierre) Bruxelles-Capitale 1150",
    "addr:housenumber":"20;6",
    "addr:postcode":"1150",
    "addr:street":"Avenue Ge\u0301Ne\u0301Ral De Longueville;Box",
    "iso:country":"BE",
    "sg:address":"Avenue G\u00e9n\u00e9ral De Longueville 20 Box 6",
    "sg:city":"Bruxelles (woluwe-saint-pierre)",
    "sg:classifiers":[
        {
            "category":"Professional",
            "subcategory":"Management & Consulting",
            "type":"Services"
        }
    ],
    "sg:phone":"+32 2 762 14 70",
    "sg:postcode":"1150",
    "sg:province":"Bruxelles-Capitale",
    "sg:tags":[
        "marketing",
        "-",
        "consultant"
    ],
    "wof:name":"Heptagon Partners",
    "wof:placetype":"venue"
},
  "geometry": {"coordinates":[4.4134068489,50.8308334351],"type":"Point"}
}