{
  "type": "Feature",
  "properties": {
    "iso:country":"BE",
    "sg:address":"Chauss\u00c9e Philippeville 80",
    "sg:city":"Couvin",
    "sg:orig_category":"Installatie van houten of kunststof schrijnwerk",
    "sg:phone":"+32 60 31 36 90",
    "sg:postcode":"5660",
    "sg:province":"Namur",
    "wof:name":"Hallet Yves",
    "wof:placetype":"venue"
},
  "geometry": {"coordinates":[4.5215997696,50.0891494751],"type":"Point"}
}