{
  "type": "Feature",
  "properties": {
    "addr:full":"Bosquetstraat 77 Sint-gillis/saint-gilles Bruxelles-Capitale 1060",
    "addr:housenumber":"77",
    "addr:postcode":"1060",
    "addr:street":"Bosquetstraat",
    "iso:country":"BE",
    "sg:address":"Bosquetstraat 77",
    "sg:city":"Sint-gillis/saint-gilles",
    "sg:orig_category":"Artsen and specialisten",
    "sg:phone":"+32 2 534 32 62",
    "sg:postcode":"1060",
    "sg:province":"Bruxelles-Capitale",
    "wof:name":"Sandrine Deckers",
    "wof:placetype":"venue"
},
  "geometry": {"coordinates":[4.3518490791,50.8338394165],"type":"Point"}
}