{
  "type": "Feature",
  "properties": {
    "iso:country":"BE",
    "sg:address":"Chauss\u00c9e De Mons 1054",
    "sg:city":"Anderlecht/anderlecht",
    "sg:classifiers":[
        {
            "category":"Food & Beverages",
            "subcategory":"Fruits & Vegetables",
            "type":"Retail Goods"
        }
    ],
    "sg:phone":"+32 2 524 15 17",
    "sg:postcode":"1070",
    "sg:province":"Bruxelles-Capitale",
    "sg:tags":[
        "l\u00e9gumes"
    ],
    "wof:name":"Huis Thierry",
    "wof:placetype":"venue"
},
  "geometry": {"coordinates":[4.2950949669,50.8225708008],"type":"Point"}
}