{
  "type": "Feature",
  "properties": {
    "iso:country":"BE",
    "sg:address":"Grand-sart 23",
    "sg:city":"Lierneux",
    "sg:orig_category":"Rundveehouders",
    "sg:phone":"+32 80 41 87 84",
    "sg:postcode":"4990",
    "sg:province":"Li\u00e8ge",
    "wof:name":"Joseph Koop",
    "wof:placetype":"venue"
},
  "geometry": {"coordinates":[5.8544359207,50.272151947],"type":"Point"}
}