{
  "type": "Feature",
  "properties": {
    "iso:country":"BE",
    "sg:address":"Rue Molinvaux 151",
    "sg:city":"Li\u00c8ge",
    "sg:orig_category":"Services de Nettoyage and de D\u00e9sinfection",
    "sg:phone":"+32 4 226 88 61",
    "sg:postcode":"4000",
    "sg:province":"Li\u00e8ge",
    "wof:name":"La Raclette D'or",
    "wof:placetype":"venue"
},
  "geometry": {"coordinates":[5.5544400215,50.6542701721],"type":"Point"}
}