{
  "type": "Feature",
  "properties": {
    "iso:country":"BE",
    "sg:address":"Kolkstraat 37",
    "sg:city":"Sint-niklaas (nieuwkerken-waas)",
    "sg:classifiers":[
        {
            "category":"Professional",
            "subcategory":"Accounting & Tax Preparation",
            "type":"Services"
        }
    ],
    "sg:phone":"+32 3 766 58 32",
    "sg:postcode":"9100",
    "sg:province":"Oost-Vlaanderen",
    "sg:tags":[
        "bookkeeper"
    ],
    "wof:name":"Pieters Patrick Boekhoudkantoor Bvba",
    "wof:placetype":"venue"
},
  "geometry": {"coordinates":[4.1846618652,51.2020568848],"type":"Point"}
}