{
  "type": "Feature",
  "properties": {
    "iso:country":"BE",
    "sg:address":"Dorp 41",
    "sg:city":"Opwijk (mazenzele)",
    "sg:classifiers":[
        {
            "category":"Professional",
            "subcategory":"Engineering",
            "type":"Services"
        }
    ],
    "sg:phone":"+32 52 35 40 85",
    "sg:postcode":"1745",
    "sg:province":"Vlaams-Brabant",
    "sg:tags":[
        "-"
    ],
    "wof:name":"Van De Voorde F",
    "wof:placetype":"venue"
},
  "geometry": {"coordinates":[4.1717247963,50.9430160522],"type":"Point"}
}