{
  "type": "Feature",
  "properties": {
    "addr:full":"St.martensommegangstraat 4ba Hamme Oost-Vlaanderen 9220",
    "addr:postcode":"9220",
    "addr:street":"St.Martensommegangstraat",
    "iso:country":"BE",
    "sg:address":"St.martensommegangstraat 4ba",
    "sg:city":"Hamme",
    "sg:orig_category":"V\u00e9los. Motos",
    "sg:phone":"+32 52 47 70 70",
    "sg:postcode":"9220",
    "sg:province":"Oost-Vlaanderen",
    "wof:name":"All-sport",
    "wof:placetype":"venue"
},
  "geometry": {"coordinates":[4.1516418457,51.0697441101],"type":"Point"}
}