{
  "type": "Feature",
  "properties": {
    "addr:full":"Nationalestraat 39 Antwerpen Antwerpen 2000",
    "addr:housenumber":"39",
    "addr:postcode":"2000",
    "addr:street":"Nationalestraat",
    "iso:country":"BE",
    "sg:address":"Nationalestraat 39",
    "sg:city":"Antwerpen",
    "sg:orig_category":"Banques and organismes de cr\u00e9dit",
    "sg:phone":"+32 3 232 05 53",
    "sg:postcode":"2000",
    "sg:province":"Antwerpen",
    "wof:name":"Fortis",
    "wof:placetype":"venue"
},
  "geometry": {"coordinates":[4.3995218277,51.2164306641],"type":"Point"}
}