{
  "type": "Feature",
  "properties": {
    "iso:country":"BE",
    "sg:address":"Duinkerkelaan 41",
    "sg:city":"De Panne",
    "sg:classifiers":[
        {
            "category":"Travel",
            "subcategory":"Hotels & Motels",
            "type":"Entertainment"
        }
    ],
    "sg:phone":"+32 58 41 51 41",
    "sg:postcode":"8660",
    "sg:province":"West-Vlaanderen",
    "sg:tags":[
        "restaurant"
    ],
    "wof:name":"Iris",
    "wof:placetype":"venue"
},
  "geometry": {"coordinates":[2.5868289471,51.1013259888],"type":"Point"}
}