{
  "type": "Feature",
  "properties": {
    "addr:full":"Bodegemstraat 189 Dilbeek Vlaams-Brabant 1700",
    "addr:housenumber":"189",
    "addr:postcode":"1700",
    "addr:street":"Bodegemstraat",
    "iso:country":"BE",
    "sg:address":"Bodegemstraat 189",
    "sg:city":"Dilbeek",
    "sg:orig_category":"Reclamebureaus Vertalers and tolken",
    "sg:phone":"+32 2 569 78 88",
    "sg:postcode":"1700",
    "sg:province":"Vlaams-Brabant",
    "wof:name":"International Sales Service Agency",
    "wof:placetype":"venue"
},
  "geometry": {"coordinates":[4.2320098877,50.8499984741],"type":"Point"}
}