{
  "type": "Feature",
  "properties": {
    "addr:full":"Transportlaan 12 Genk Limburg 3600",
    "addr:housenumber":"12",
    "addr:postcode":"3600",
    "addr:street":"Transportlaan",
    "iso:country":"BE",
    "sg:address":"Transportlaan 12",
    "sg:city":"Genk",
    "sg:orig_category":"Goederenvervoer over de weg",
    "sg:phone":"+32 89 35 55 81",
    "sg:postcode":"3600",
    "sg:province":"Limburg",
    "wof:name":"T.r.w.",
    "wof:placetype":"venue"
},
  "geometry": {"coordinates":[5.458920002,50.9972686768],"type":"Point"}
}