{
  "type": "Feature",
  "properties": {
    "addr:full":"Akkervoorstraat 16 Asse Vlaams-Brabant 1731",
    "addr:housenumber":"16",
    "addr:postcode":"1731",
    "addr:street":"Akkervoorstraat",
    "iso:country":"BE",
    "sg:address":"Akkervoorstraat 16",
    "sg:city":"Asse",
    "sg:orig_category":"Schilders",
    "sg:phone":"+32 2 460 51 72",
    "sg:postcode":"1731",
    "sg:province":"Vlaams-Brabant",
    "wof:name":"Ave-peint",
    "wof:placetype":"venue"
},
  "geometry": {"coordinates":[4.2798547745,50.8909454346],"type":"Point"}
}