{
  "type": "Feature",
  "properties": {
    "iso:country":"BE",
    "sg:address":"Rue De Thy-le-bauduin 19",
    "sg:city":"Laneffe",
    "sg:classifiers":[
        {
            "category":"Professional",
            "subcategory":"Detective & Security Services",
            "type":"Services"
        }
    ],
    "sg:phone":"+32 71 65 09 65",
    "sg:postcode":"5651",
    "sg:province":"Namur",
    "sg:tags":[
        "system",
        "fence"
    ],
    "wof:name":"Magifer S.p.r.l.",
    "wof:placetype":"venue"
},
  "geometry": {"coordinates":[4.5022602081,50.2771110535],"type":"Point"}
}