{
  "type": "Feature",
  "properties": {
    "iso:country":"BE",
    "sg:address":"Weertersteenweg 149",
    "sg:city":"Maaseik",
    "sg:orig_category":"Articles de jardin. Installation de menuiserie en bois and plastique",
    "sg:phone":"+32 89 56 49 19",
    "sg:postcode":"3680",
    "sg:province":"Limburg",
    "wof:name":"Fincken",
    "wof:placetype":"venue"
},
  "geometry": {"coordinates":[5.7761120796,51.1087188721],"type":"Point"}
}