{
  "type": "Feature",
  "properties": {
    "addr:full":"Zutendaalweg 27b1 Bilzen Limburg 3740",
    "addr:housenumber":"27b1",
    "addr:postcode":"3740",
    "addr:street":"Zutendaalweg",
    "iso:country":"BE",
    "sg:address":"Zutendaalweg 27b1",
    "sg:city":"Bilzen",
    "sg:orig_category":"Dameskledingzaken",
    "sg:phone":"+32 89 41 60 47",
    "sg:postcode":"3740",
    "sg:province":"Limburg",
    "wof:name":"H. & B. Mode",
    "wof:placetype":"venue"
},
  "geometry": {"coordinates":[5.5281209946,50.90184021],"type":"Point"}
}