{
  "type": "Feature",
  "properties": {
    "addr:full":"Rue De Battice 160b1 Aubel Li\u00e8ge 4880",
    "addr:housenumber":"160b1",
    "addr:postcode":"4880",
    "addr:street":"Rue De Battice",
    "iso:country":"BE",
    "sg:address":"Rue De Battice 160b1",
    "sg:city":"Aubel",
    "sg:orig_category":"Charpentes and couvertures",
    "sg:phone":"+32 87 68 14 79",
    "sg:postcode":"4880",
    "sg:province":"Li\u00e8ge",
    "wof:name":"Vogts E.",
    "wof:placetype":"venue"
},
  "geometry": {"coordinates":[5.8543901443,50.6949996948],"type":"Point"}
}