{
  "type": "Feature",
  "properties": {
    "iso:country":"BE",
    "sg:address":"Rue De Belle-vue 37",
    "sg:city":"Tubize",
    "sg:orig_category":"Eclairage et \u00e9quipements du foyer. Magasins sp\u00e9cialis\u00e9s",
    "sg:phone":"+32 2 355 46 58",
    "sg:postcode":"1480",
    "sg:province":"Brabant Wallon",
    "wof:name":"Alain Vanhove",
    "wof:placetype":"venue"
},
  "geometry": {"coordinates":[4.1876010895,50.6966552734],"type":"Point"}
}