{
  "type": "Feature",
  "properties": {
    "iso:country":"BE",
    "sg:address":"Heerbaan 167",
    "sg:city":"Koersel",
    "sg:orig_category":"Dakwerken",
    "sg:phone":"+32 11 42 18 17",
    "sg:postcode":"3582",
    "sg:province":"Limburg",
    "wof:name":"Van Gossum- Briers",
    "wof:placetype":"venue"
},
  "geometry": {"coordinates":[5.2446107864,51.0698471069],"type":"Point"}
}