{
  "type": "Feature",
  "properties": {
    "iso:country":"BE",
    "sg:address":"Dalstraat 34",
    "sg:city":"Sint-niklaas",
    "sg:orig_category":"Diensten voor huisdieren",
    "sg:phone":"+32 3 777 36 16",
    "sg:postcode":"9100",
    "sg:province":"Oost-Vlaanderen",
    "wof:name":"Cane Picco Bello",
    "wof:placetype":"venue"
},
  "geometry": {"coordinates":[4.1354160309,51.1648635864],"type":"Point"}
}