{
  "type": "Feature",
  "properties": {
    "iso:country":"BE",
    "sg:address":"Rue Du Combattant L. Mahieu 12",
    "sg:city":"Hensies (thulin)",
    "sg:classifiers":[
        {
            "category":"Health Services",
            "subcategory":"Health Practitioner",
            "type":"Services"
        }
    ],
    "sg:phone":"+32 65 65 94 01",
    "sg:postcode":"7350",
    "sg:province":"Hainaut",
    "sg:tags":[
        "therapist",
        "speech"
    ],
    "wof:name":"Baudour S",
    "wof:placetype":"venue"
},
  "geometry": {"coordinates":[3.7420499325,50.4281158447],"type":"Point"}
}