{
  "type": "Feature",
  "properties": {
    "addr:full":"Rue Du Pr\u00c9sident Allende 75 Chapelle-lez-herlaimont Hainaut 7160",
    "addr:housenumber":"75",
    "addr:postcode":"7160",
    "addr:street":"Rue Du Pre\u0301Sident Allende;Hainaut",
    "iso:country":"BE",
    "sg:address":"Rue Du Pr\u00c9sident Allende 75",
    "sg:city":"Chapelle-lez-herlaimont",
    "sg:orig_category":"Traitements param\u00e9dicaux",
    "sg:phone":"+32 64 44 95 27",
    "sg:postcode":"7160",
    "sg:province":"Hainaut",
    "wof:name":"A. Vanh\u00c9e",
    "wof:placetype":"venue"
},
  "geometry": {"coordinates":[4.2872161865,50.4956741333],"type":"Point"}
}