{
  "type": "Feature",
  "properties": {
    "iso:country":"BE",
    "sg:address":"Rue De Gilly 393a",
    "sg:city":"Chatelet",
    "sg:orig_category":"V\u00e9hicules automobiles",
    "sg:phone":"+32 71 38 00 68",
    "sg:postcode":"6200",
    "sg:province":"Hainaut",
    "wof:name":"Garage Patricio",
    "wof:placetype":"venue"
},
  "geometry": {"coordinates":[4.5016078949,50.4123001099],"type":"Point"}
}