{
  "type": "Feature",
  "properties": {
    "iso:country":"BE",
    "sg:address":"Willem Van Haechtlaan 63",
    "sg:city":"Antwerpen",
    "sg:orig_category":"Epiceries",
    "sg:phone":"+32 3 219 12 25",
    "sg:postcode":"2050",
    "sg:province":"Antwerpen",
    "wof:name":"Mafalda De Wael",
    "wof:placetype":"venue"
},
  "geometry": {"coordinates":[4.385518074,51.2302284241],"type":"Point"}
}