{
  "type": "Feature",
  "properties": {
    "iso:country":"BE",
    "sg:address":"Vijverstraat 5a",
    "sg:city":"Geetbets (grazen)",
    "sg:classifiers":[
        {
            "category":"Building & Trades",
            "subcategory":"Pest Control",
            "type":"Services"
        }
    ],
    "sg:phone":"+32 11 58 10 45",
    "sg:postcode":"3450",
    "sg:province":"Vlaams-Brabant",
    "sg:tags":[
        "painting",
        "contractor"
    ],
    "wof:name":"Vanacken P",
    "wof:placetype":"venue"
},
  "geometry": {"coordinates":[5.1303768158,50.8743782043],"type":"Point"}
}