{
  "type": "Feature",
  "properties": {
    "addr:full":"Rue Bois De Graux 20 Profondeville (lesve) Namur 5170",
    "addr:housenumber":"20",
    "addr:postcode":"5170",
    "addr:street":"Rue Bois De Graux",
    "iso:country":"BE",
    "sg:address":"Rue Bois De Graux 20",
    "sg:city":"Profondeville (lesve)",
    "sg:classifiers":[
        {
            "category":"Government",
            "subcategory":"Department Of Motor Vehicles",
            "type":"Public Place"
        }
    ],
    "sg:phone":"+32 81 43 36 07",
    "sg:postcode":"5170",
    "sg:province":"Namur",
    "sg:tags":[
        "planing",
        "wood",
        "sawing"
    ],
    "wof:name":"Rolland Scierie Sa",
    "wof:placetype":"venue"
},
  "geometry": {"coordinates":[4.7713499069,50.3776626587],"type":"Point"}
}