{
  "type": "Feature",
  "properties": {
    "addr:full":"Rue De L\u00b4eglise 127 Sint-pieters-woluwe/woluwe-saint-pierre Bruxelles-Capitale 1150",
    "addr:housenumber":"127",
    "addr:postcode":"1150",
    "addr:street":"Rue De L\u00b4Eglise;/",
    "iso:country":"BE",
    "sg:address":"Rue De L\u00b4eglise 127",
    "sg:city":"Sint-pieters-woluwe/woluwe-saint-pierre",
    "sg:orig_category":"Chaussures. Maroquinerie and articles de voyage",
    "sg:phone":"+32 2 777 04 70",
    "sg:postcode":"1150",
    "sg:province":"Bruxelles-Capitale",
    "wof:name":"1001 Pattes",
    "wof:placetype":"venue"
},
  "geometry": {"coordinates":[4.4640631676,50.8403968811],"type":"Point"}
}