{
  "type": "Feature",
  "properties": {
    "addr:full":"Pontstraat 74 Aalst Oost-Vlaanderen 9300",
    "addr:housenumber":"74",
    "addr:postcode":"9300",
    "addr:street":"Pontstraat",
    "iso:country":"BE",
    "sg:address":"Pontstraat 74",
    "sg:city":"Aalst",
    "sg:classifiers":[
        {
            "category":"Bars & Pubs",
            "type":"Food & Drink"
        }
    ],
    "sg:phone":"+32 53 78 79 26",
    "sg:postcode":"9300",
    "sg:province":"Oost-Vlaanderen",
    "wof:name":"Land Van Aalst",
    "wof:placetype":"venue"
},
  "geometry": {"coordinates":[4.0439348221,50.9353599548],"type":"Point"}
}