{
  "type": "Feature",
  "properties": {
    "addr:full":"Bonderstraat 36 Riemst (vlijtingen) Limburg 3770",
    "addr:housenumber":"36",
    "addr:postcode":"3770",
    "addr:street":"Bonderstraat",
    "iso:country":"BE",
    "sg:address":"Bonderstraat 36",
    "sg:city":"Riemst (vlijtingen)",
    "sg:classifiers":[
        {
            "category":"Structure",
            "subcategory":"Office Building",
            "type":"Public Place"
        }
    ],
    "sg:phone":"+32 12 45 19 51",
    "sg:postcode":"3770",
    "sg:province":"Limburg",
    "sg:tags":[
        "-",
        "type",
        "door",
        "sliding",
        "overhead"
    ],
    "wof:name":"Ev-vanheusden & Zoon",
    "wof:placetype":"venue"
},
  "geometry": {"coordinates":[5.6121191978,50.8303794861],"type":"Point"}
}