{
  "type": "Feature",
  "properties": {
    "iso:country":"BE",
    "sg:address":"Rue Du Pont Neuf 39",
    "sg:city":"Bruxelles",
    "sg:classifiers":[
        {
            "category":"Education",
            "subcategory":"Dance Studio",
            "type":"Public Place"
        }
    ],
    "sg:phone":"+32 2 223 68 58",
    "sg:postcode":"1000",
    "sg:province":"Bruxelles-Capitale",
    "sg:tags":[
        "ballet",
        "school"
    ],
    "wof:name":"Attitude Asbl",
    "wof:placetype":"venue"
},
  "geometry": {"coordinates":[4.3549318314,50.8534812927],"type":"Point"}
}