{
  "type": "Feature",
  "properties": {
    "iso:country":"BE",
    "sg:address":"Avenue Reine Astrid 193",
    "sg:city":"Verviers",
    "sg:orig_category":"HERSTELLING ELEKTRISCHE HUISHOUDAPPARATEN Huishoudapparaten, televisies and radio's",
    "sg:phone":"+32 87 22 60 35",
    "sg:postcode":"4802",
    "sg:province":"Li\u00e8ge",
    "wof:name":"D. Demoulin",
    "wof:placetype":"venue"
},
  "geometry": {"coordinates":[5.8872442245,50.5832939148],"type":"Point"}
}