{
  "type": "Feature",
  "properties": {
    "iso:country":"BE",
    "sg:address":"Chauss\u00c9e De Mons 208",
    "sg:city":"La Louvi\u00c8re",
    "sg:orig_category":"Herstelling and restauratie van meubelen",
    "sg:phone":"+32 64 22 85 43",
    "sg:postcode":"7100",
    "sg:province":"Hainaut",
    "wof:name":"Fe. Voiturier J. & Fils",
    "wof:placetype":"venue"
},
  "geometry": {"coordinates":[4.1995410919,50.4645805359],"type":"Point"}
}