{
  "type": "Feature",
  "properties": {
    "iso:country":"BE",
    "sg:address":"Staatsbaan 126",
    "sg:city":"Halen",
    "sg:classifiers":[
        {
            "category":"Building & Trades",
            "subcategory":"Landscaping Services",
            "type":"Services"
        }
    ],
    "sg:phone":"+32 13 46 22 24",
    "sg:postcode":"3545",
    "sg:province":"Limburg",
    "sg:tags":[
        "equipment",
        "swimming",
        "-",
        "pool",
        "contractor"
    ],
    "wof:name":"Dreampool Zwembaden",
    "wof:placetype":"venue"
},
  "geometry": {"coordinates":[5.0837497711,50.9613609314],"type":"Point"}
}