{
  "type": "Feature",
  "properties": {
    "addr:full":"Steenweg 146 Heers Limburg 3870",
    "addr:housenumber":"146",
    "addr:postcode":"3870",
    "addr:street":"Steenweg",
    "iso:country":"BE",
    "sg:address":"Steenweg 146",
    "sg:city":"Heers",
    "sg:orig_category":"Biblioth\u00e8ques and archives publiques",
    "sg:phone":"+32 11 48 43 05",
    "sg:postcode":"3870",
    "sg:province":"Limburg",
    "wof:name":"Openbare Bibliotheek",
    "wof:placetype":"venue"
},
  "geometry": {"coordinates":[5.2956171036,50.7508277893],"type":"Point"}
}