{
  "type": "Feature",
  "properties": {
    "addr:full":"Rue Des Beaux Pr\u00e9s 100 Jodoigne (m\u00e9lin) Brabant Wallon 1370",
    "addr:housenumber":"100",
    "addr:postcode":"1370",
    "addr:street":"Rue Des Beaux Pre\u0301S;Wallon",
    "iso:country":"BE",
    "sg:address":"Rue Des Beaux Pr\u00e9s 100",
    "sg:city":"Jodoigne (m\u00e9lin)",
    "sg:classifiers":[
        {
            "category":"Professional",
            "subcategory":"Management & Consulting",
            "type":"Services"
        }
    ],
    "sg:phone":"+32 10 81 16 90",
    "sg:postcode":"1370",
    "sg:province":"Brabant Wallon",
    "sg:tags":[
        "consultant",
        "promotion",
        "-",
        "sale"
    ],
    "wof:name":"Training & Sales Partners Sprl",
    "wof:placetype":"venue"
},
  "geometry": {"coordinates":[4.8157749176,50.741985321],"type":"Point"}
}