{
  "type": "Feature",
  "properties": {
    "iso:country":"BE",
    "sg:address":"Nikelaan 1",
    "sg:city":"Laakdal",
    "sg:classifiers":[
        {
            "category":"Sports & Exercise",
            "subcategory":"Bicycle Rental",
            "type":"Entertainment"
        }
    ],
    "sg:phone":"+32 13 61 64 53",
    "sg:postcode":"2430",
    "sg:province":"Antwerpen",
    "sg:tags":[
        "boot",
        "shoes",
        "leisure"
    ],
    "wof:name":"Nike Europe Holding B.v.",
    "wof:placetype":"venue"
},
  "geometry": {"coordinates":[5.0823841095,51.0998725891],"type":"Point"}
}