{
  "type": "Feature",
  "properties": {
    "iso:country":"BE",
    "sg:address":"Place Du Rinsdelle 25",
    "sg:city":"Etterbeek/etterbeek",
    "sg:orig_category":"Pharmaciens",
    "sg:phone":"+32 2 736 21 01",
    "sg:postcode":"1040",
    "sg:province":"Bruxelles-Capitale",
    "wof:name":"Genevieve Somville",
    "wof:placetype":"venue"
},
  "geometry": {"coordinates":[4.3962831497,50.8337593079],"type":"Point"}
}