{
  "type": "Feature",
  "properties": {
    "iso:country":"BE",
    "sg:address":"Molendreef 33",
    "sg:city":"Aarschot (rillaar)",
    "sg:classifiers":[
        {
            "category":"Health Services",
            "subcategory":"Doctor",
            "type":"Services"
        }
    ],
    "sg:phone":"+32 16 50 07 37",
    "sg:postcode":"3202",
    "sg:province":"Vlaams-Brabant",
    "sg:tags":[
        "medicinephysicians",
        "surgeon"
    ],
    "wof:name":"Boogaerts Achiel",
    "wof:placetype":"venue"
},
  "geometry": {"coordinates":[4.8982892036,50.9770431519],"type":"Point"}
}