{
  "type": "Feature",
  "properties": {
    "iso:country":"BE",
    "sg:address":"Kapellestraat 24-61",
    "sg:city":"Evergem",
    "sg:classifiers":[
        {
            "category":"Insurance",
            "subcategory":"Insurance Agent",
            "type":"Services"
        }
    ],
    "sg:phone":"+32 9 253 75 53",
    "sg:postcode":"9940",
    "sg:province":"Oost-Vlaanderen",
    "sg:tags":[
        "broker"
    ],
    "wof:name":"Kantoor Raman-gaspaar",
    "wof:placetype":"venue"
},
  "geometry": {"coordinates":[3.7102560997,51.1105880737],"type":"Point"}
}