{
  "type": "Feature",
  "properties": {
    "iso:country":"BE",
    "sg:address":"Nieuwelaan 37",
    "sg:city":"Meise",
    "sg:orig_category":"Postkantoren Verzekeringsmakelaars and experts",
    "sg:phone":"+32 2 270 82 26",
    "sg:postcode":"1860",
    "sg:province":"Vlaams-Brabant",
    "wof:name":"De Post",
    "wof:placetype":"venue"
},
  "geometry": {"coordinates":[4.3277540207,50.9379920959],"type":"Point"}
}