{
  "type": "Feature",
  "properties": {
    "addr:full":"Alb. Rodenbachplantsoen 93 Turnhout Antwerpen 2300",
    "addr:housenumber":"93",
    "addr:postcode":"2300",
    "addr:street":"Rodenbachplantsoen",
    "iso:country":"BE",
    "sg:address":"Alb. Rodenbachplantsoen 93",
    "sg:city":"Turnhout",
    "sg:orig_category":"Pain, p\u00e2tisseries and confiseries",
    "sg:phone":"+32 14 41 79 38",
    "sg:postcode":"2300",
    "sg:province":"Antwerpen",
    "wof:name":"Bakkerij St Leonardus",
    "wof:placetype":"venue"
},
  "geometry": {"coordinates":[4.939412117,51.3030509949],"type":"Point"}
}