{
  "type": "Feature",
  "properties": {
    "addr:full":"Elderseweg 112 Tongeren Limburg 3700",
    "addr:housenumber":"112",
    "addr:postcode":"3700",
    "addr:street":"Elderseweg",
    "iso:country":"BE",
    "sg:address":"Elderseweg 112",
    "sg:city":"Tongeren",
    "sg:classifiers":[
        {
            "category":"Utilities",
            "subcategory":"Mobile Phone",
            "type":"Services"
        }
    ],
    "sg:phone":"+32 12 39 14 46",
    "sg:postcode":"3700",
    "sg:province":"Limburg",
    "sg:tags":[
        "-",
        "gsm"
    ],
    "wof:name":"Elektronic Repair & Training",
    "wof:placetype":"venue"
},
  "geometry": {"coordinates":[5.4780440331,50.7878684998],"type":"Point"}
}