{
  "type": "Feature",
  "properties": {
    "addr:full":"Burgemeester Jos. Lievensstraat 15b Zedelgem West-Vlaanderen 8210",
    "addr:housenumber":"15b",
    "addr:postcode":"8210",
    "addr:street":"Burgemeester Jos. Lievensstraat",
    "iso:country":"BE",
    "sg:address":"Burgemeester Jos. Lievensstraat 15b",
    "sg:city":"Zedelgem",
    "sg:orig_category":"Fa\u00e7ade covering",
    "sg:phone":"+32 50 27 08 81",
    "sg:postcode":"8210",
    "sg:province":"West-Vlaanderen",
    "wof:name":"Mascot Renovatie",
    "wof:placetype":"venue"
},
  "geometry": {"coordinates":[3.1357820034,51.1407318115],"type":"Point"}
}