{
  "type": "Feature",
  "properties": {
    "addr:full":"J.sweygersstraat 12 Diest Vlaams-Brabant 3290",
    "addr:housenumber":"12",
    "addr:postcode":"3290",
    "addr:street":"J.Sweygersstraat",
    "iso:country":"BE",
    "sg:address":"J.sweygersstraat 12",
    "sg:city":"Diest",
    "sg:orig_category":"Banken and kredietinstellingen Verzekeringsmakelaars and experts",
    "sg:phone":"+32 13 66 15 69",
    "sg:postcode":"3290",
    "sg:province":"Vlaams-Brabant",
    "wof:name":"L. Volders",
    "wof:placetype":"venue"
},
  "geometry": {"coordinates":[5.0968880653,51.0381278992],"type":"Point"}
}