{
  "type": "Feature",
  "properties": {
    "iso:country":"BE",
    "sg:address":"Chauss\u00c9e De Dinant 864",
    "sg:city":"Namur",
    "sg:orig_category":"Evaluation and estimation de biens immobiliers",
    "sg:phone":"+32 81 47 01 52",
    "sg:postcode":"5100",
    "sg:province":"Namur",
    "wof:name":"Michel Jeandrain",
    "wof:placetype":"venue"
},
  "geometry": {"coordinates":[4.8704309464,50.425491333],"type":"Point"}
}