{
  "type": "Feature",
  "properties": {
    "addr:full":"Avenue De L'energie 16 - Z.i. - Alleur Li\u00e8ge 4432",
    "addr:housenumber":"16",
    "addr:postcode":"4432",
    "addr:street":"Avenue De L'Energie;Z.I.",
    "iso:country":"BE",
    "sg:address":"Avenue De L'energie 16 - Z.i. -",
    "sg:city":"Alleur",
    "sg:classifiers":[
        {
            "category":"Wholesale",
            "subcategory":"Meat",
            "type":"Manufacturing & Wholesale Goods"
        }
    ],
    "sg:phone":"+32 4 247 01 01",
    "sg:postcode":"4432",
    "sg:province":"Li\u00e8ge",
    "sg:tags":[
        "food",
        "cooked",
        "product",
        "related"
    ],
    "wof:name":"Salaisons Du Condroz Marcotty Sa",
    "wof:placetype":"venue"
},
  "geometry": {"coordinates":[5.5301661491,50.6755104065],"type":"Point"}
}