{
  "type": "Feature",
  "properties": {
    "iso:country":"BE",
    "sg:address":"Koningsstraat 1",
    "sg:city":"Leopoldsburg",
    "sg:classifiers":[
        {
            "category":"Shopping",
            "subcategory":"Shoes",
            "type":"Retail Goods"
        }
    ],
    "sg:phone":"+32 11 34 14 66",
    "sg:postcode":"3970",
    "sg:province":"Limburg",
    "sg:tags":[
        "slipper",
        "-"
    ],
    "wof:name":"Madeleine",
    "wof:placetype":"venue"
},
  "geometry": {"coordinates":[5.261179924,51.1164474487],"type":"Point"}
}