{
  "type": "Feature",
  "properties": {
    "addr:full":"Froidbermont 32 Olne Li\u00e8ge 4877",
    "addr:housenumber":"32",
    "addr:postcode":"4877",
    "addr:street":"Froidbermont",
    "iso:country":"BE",
    "sg:address":"Froidbermont 32",
    "sg:city":"Olne",
    "sg:orig_category":"Eleveurs and marchands de porcs. Eleveurs de bovins",
    "sg:phone":"+32 87 26 86 62",
    "sg:postcode":"4877",
    "sg:province":"Li\u00e8ge",
    "wof:name":"Jean-pierre Vanwaarbeek",
    "wof:placetype":"venue"
},
  "geometry": {"coordinates":[5.756857872,50.5835723877],"type":"Point"}
}