{
  "type": "Feature",
  "properties": {
    "addr:full":"Hondstraat 64 Beringen Limburg 3582",
    "addr:housenumber":"64",
    "addr:postcode":"3582",
    "addr:street":"Hondstraat",
    "iso:country":"BE",
    "sg:address":"Hondstraat 64",
    "sg:city":"Beringen",
    "sg:orig_category":"Installation \u00e9lectrique r\u00e9sidentielle",
    "sg:phone":"+32 11 57 21 76",
    "sg:postcode":"3582",
    "sg:province":"Limburg",
    "wof:name":"Franky Daniels",
    "wof:placetype":"venue"
},
  "geometry": {"coordinates":[5.3046188354,51.0589141846],"type":"Point"}
}