{
  "type": "Feature",
  "properties": {
    "iso:country":"BE",
    "sg:address":"Loofblommestraat 30",
    "sg:city":"Gent (sint-denijs-westrem - Afsnee)",
    "sg:classifiers":[
        {
            "category":"Bars & Pubs",
            "type":"Food & Drink"
        }
    ],
    "sg:phone":"+32 9 221 86 84",
    "sg:postcode":"9051",
    "sg:province":"Oost-Vlaanderen",
    "wof:name":"Zwaantje ('t)",
    "wof:placetype":"venue"
},
  "geometry": {"coordinates":[3.6688299179,51.0238304138],"type":"Point"}
}