{
  "type": "Feature",
  "properties": {
    "addr:full":"Rue Bois Delawe 94 Seraing (ougr\u00e9e) Li\u00e8ge 4102",
    "addr:housenumber":"94",
    "addr:postcode":"4102",
    "addr:street":"Rue Bois Delawe",
    "iso:country":"BE",
    "sg:address":"Rue Bois Delawe 94",
    "sg:city":"Seraing (ougr\u00e9e)",
    "sg:classifiers":[
        {
            "category":"Professional",
            "subcategory":"Accounting & Tax Preparation",
            "type":"Services"
        }
    ],
    "sg:phone":"+32 476 55 30 06",
    "sg:postcode":"4102",
    "sg:province":"Li\u00e8ge",
    "sg:tags":[
        "bookkeeper"
    ],
    "wof:name":"Colombo M-l",
    "wof:placetype":"venue"
},
  "geometry": {"coordinates":[5.531126976,50.5961418152],"type":"Point"}
}