{
  "type": "Feature",
  "properties": {
    "addr:full":"270 Tiensesteenweg 3360 Bierbeek 270",
    "addr:housenumber":"270",
    "addr:postcode":"3360;270",
    "addr:street":"Tiensesteenweg",
    "iso:country":"BE",
    "sg:address":"270",
    "sg:city":"Tiensesteenweg 3360 Bierbeek",
    "sg:classifiers":[
        {
            "category":"Professional",
            "type":"Services"
        }
    ],
    "sg:phone":"+32 16 46 31 22",
    "sg:postcode":"270",
    "sg:tags":[
        "transport",
        "road"
    ],
    "wof:name":"Verhuizingen Coppens Nv",
    "wof:placetype":"venue"
},
  "geometry": {"coordinates":[4.7499132156,50.8654251099],"type":"Point"}
}