{
  "type": "Feature",
  "properties": {
    "addr:full":"Kartuizerstraat 20 Holsbeek Vlaams-Brabant 3220",
    "addr:housenumber":"20",
    "addr:postcode":"3220",
    "addr:street":"Kartuizerstraat",
    "iso:country":"BE",
    "sg:address":"Kartuizerstraat 20",
    "sg:city":"Holsbeek",
    "sg:classifiers":[
        {
            "category":"Building & Trades",
            "subcategory":"Construction",
            "type":"Services"
        }
    ],
    "sg:phone":"+32 16 44 01 53",
    "sg:postcode":"3220",
    "sg:province":"Vlaams-Brabant",
    "sg:tags":[
        "carpenter"
    ],
    "wof:name":"Vandenberghen G",
    "wof:placetype":"venue"
},
  "geometry": {"coordinates":[4.7623968124,50.918422699],"type":"Point"}
}