{
  "type": "Feature",
  "properties": {
    "iso:country":"BE",
    "sg:address":"Rue Des Grottes 8",
    "sg:city":"Rochefort",
    "sg:orig_category":"Boucheries",
    "sg:phone":"+32 84 37 72 17",
    "sg:postcode":"5580",
    "sg:province":"Namur",
    "wof:name":"Lebrun Cara",
    "wof:placetype":"venue"
},
  "geometry": {"coordinates":[5.2231431007,50.1608505249],"type":"Point"}
}