{
  "type": "Feature",
  "properties": {
    "iso:country":"BE",
    "sg:address":"Avenue De L'astronomie 31b14",
    "sg:city":"Sint-joost-ten-node/saint-joss",
    "sg:orig_category":"Beheer van reclamemedia",
    "sg:phone":"+32 2 217 90 59",
    "sg:postcode":"1210",
    "sg:province":"Bruxelles-Capitale",
    "wof:name":"More O'ferrall",
    "wof:placetype":"venue"
},
  "geometry": {"coordinates":[4.369863987,50.8521347046],"type":"Point"}
}