{
  "type": "Feature",
  "properties": {
    "addr:full":"Bettestraat 25 Stekene Oost-Vlaanderen 9190",
    "addr:housenumber":"25",
    "addr:postcode":"9190",
    "addr:street":"Bettestraat",
    "iso:country":"BE",
    "sg:address":"Bettestraat 25",
    "sg:city":"Stekene",
    "sg:orig_category":"Non-Classified Establishments",
    "sg:phone":"+32 3 778 06 46",
    "sg:postcode":"9190",
    "sg:province":"Oost-Vlaanderen",
    "wof:name":"First Fashion",
    "wof:placetype":"venue"
},
  "geometry": {"coordinates":[4.0528302193,51.2126998901],"type":"Point"}
}