{
  "type": "Feature",
  "properties": {
    "addr:full":"Rue D\u00b4anseremme 98 Dinant Namur 5500",
    "addr:housenumber":"98",
    "addr:postcode":"5500",
    "addr:street":"Rue D\u00b4Anseremme",
    "iso:country":"BE",
    "sg:address":"Rue D\u00b4anseremme 98",
    "sg:city":"Dinant",
    "sg:orig_category":"Travaux de pl\u00e2trage. Rev\u00eatements pour sols and murs",
    "sg:phone":"+32 82 22 32 54",
    "sg:postcode":"5500",
    "sg:province":"Namur",
    "wof:name":"Eric Jaumot",
    "wof:placetype":"venue"
},
  "geometry": {"coordinates":[4.9280328751,50.2350730896],"type":"Point"}
}