{
  "type": "Feature",
  "properties": {
    "iso:country":"BE",
    "sg:address":"Burgemeester Jos Chalmetlaan 87",
    "sg:city":"Zelzate",
    "sg:classifiers":[
        {
            "category":"Health Services",
            "subcategory":"Health Practitioner",
            "type":"Services"
        }
    ],
    "sg:phone":"+32 9 345 53 11",
    "sg:postcode":"9060",
    "sg:province":"Oost-Vlaanderen",
    "sg:tags":[
        "physiotherapist"
    ],
    "wof:name":"Standaert Christine",
    "wof:placetype":"venue"
},
  "geometry": {"coordinates":[3.8174118996,51.1968154907],"type":"Point"}
}