{
  "type": "Feature",
  "properties": {
    "addr:full":"Burg. Benedikt 't Kintln 23 Denderleeuw Oost-Vlaanderen 9473",
    "addr:housenumber":"23",
    "addr:postcode":"9473",
    "addr:street":"Burg.;'",
    "iso:country":"BE",
    "sg:address":"Burg. Benedikt 't Kintln 23",
    "sg:city":"Denderleeuw",
    "sg:orig_category":"Dakwerken",
    "sg:phone":"+32 53 67 19 59",
    "sg:postcode":"9473",
    "sg:province":"Oost-Vlaanderen",
    "wof:name":"William Robijns",
    "wof:placetype":"venue"
},
  "geometry": {"coordinates":[4.0514397621,50.8967399597],"type":"Point"}
}