{
  "type": "Feature",
  "properties": {
    "addr:full":"Chauss\u00e9e Fernand Deli\u00e8ge 66 Beaumont Hainaut 6500",
    "addr:housenumber":"66",
    "addr:postcode":"6500",
    "addr:street":"Chausse\u0301E Fernand Delie\u0300Ge;Hainaut",
    "iso:country":"BE",
    "sg:address":"Chauss\u00e9e Fernand Deli\u00e8ge 66",
    "sg:city":"Beaumont",
    "sg:classifiers":[
        {
            "category":"Building & Trades",
            "subcategory":"Construction",
            "type":"Services"
        }
    ],
    "sg:phone":"+32 71 58 95 11",
    "sg:postcode":"6500",
    "sg:province":"Hainaut",
    "sg:tags":[
        "installation",
        "-",
        "central",
        "heating"
    ],
    "wof:name":"Dossin Entreprise",
    "wof:placetype":"venue"
},
  "geometry": {"coordinates":[4.2497239113,50.2376022339],"type":"Point"}
}