{
  "type": "Feature",
  "properties": {
    "iso:country":"BE",
    "sg:address":"Verbertstraat 52",
    "sg:city":"Schoten",
    "sg:orig_category":"Herstellingen and onderhoud van auto's Voertuigen",
    "sg:phone":"+32 3 658 55 55",
    "sg:postcode":"2900",
    "sg:province":"Antwerpen",
    "wof:name":"J. Leurs",
    "wof:placetype":"venue"
},
  "geometry": {"coordinates":[4.4977807999,51.2479743958],"type":"Point"}
}