{
  "type": "Feature",
  "properties": {
    "iso:country":"BE",
    "sg:address":"Chemin Vert 3",
    "sg:city":"Tournai",
    "sg:orig_category":"Eleveurs de bovins",
    "sg:phone":"+32 69 22 27 67",
    "sg:postcode":"7501",
    "sg:province":"Hainaut",
    "wof:name":"Decock Michel Et Daniel",
    "wof:placetype":"venue"
},
  "geometry": {"coordinates":[3.3600959778,50.6030731201],"type":"Point"}
}