{
  "type": "Feature",
  "properties": {
    "iso:country":"BE",
    "sg:address":"Rue Des Eglantines 36",
    "sg:city":"Bl\u00e9gny (mortier)",
    "sg:classifiers":[
        {
            "category":"Arena",
            "subcategory":"Sports Club",
            "type":"Entertainment"
        }
    ],
    "sg:phone":"+32 4 387 74 96",
    "sg:postcode":"4670",
    "sg:province":"Li\u00e8ge",
    "wof:name":"Royale Entente Blegnytoise",
    "wof:placetype":"venue"
},
  "geometry": {"coordinates":[5.7406997681,50.6890640259],"type":"Point"}
}