{
  "type": "Feature",
  "properties": {
    "iso:country":"BE",
    "sg:address":"Boulevard St Michel 1",
    "sg:city":"Sint-pieters-woluwe (brussel)",
    "sg:classifiers":[
        {
            "category":"Personal",
            "subcategory":"Beauty Salon",
            "type":"Services"
        }
    ],
    "sg:phone":"+32 2 732 99 03",
    "sg:postcode":"1150",
    "sg:province":"Bruxelles-Capitale",
    "sg:tags":[
        "de",
        "coiffure"
    ],
    "wof:name":"Advanced Hair Studios Limited",
    "wof:placetype":"venue"
},
  "geometry": {"coordinates":[4.4068450928,50.8366508484],"type":"Point"}
}