{
  "type": "Feature",
  "properties": {
    "iso:country":"BE",
    "sg:address":"Place Des Capucins 5 Box 11",
    "sg:city":"Ath",
    "sg:classifiers":[
        {
            "category":"Government",
            "subcategory":"Post Office",
            "type":"Public Place"
        }
    ],
    "sg:phone":"+32 68 84 12 50",
    "sg:postcode":"7800",
    "sg:province":"Hainaut",
    "sg:tags":[
        "yoga"
    ],
    "wof:name":"Mieux Vivre Autrement Asbl",
    "wof:placetype":"venue"
},
  "geometry": {"coordinates":[3.7786970139,50.6330375671],"type":"Point"}
}