{
  "type": "Feature",
  "properties": {
    "addr:full":"Avenue Fran\u00c7ois Cornesse 6 Aywaille Li\u00e8ge 4920",
    "addr:housenumber":"6",
    "addr:postcode":"4920",
    "addr:street":"Avenue Franc\u0327Ois Cornesse",
    "iso:country":"BE",
    "sg:address":"Avenue Fran\u00c7ois Cornesse 6",
    "sg:city":"Aywaille",
    "sg:classifiers":[
        {
            "category":"Manufacturing",
            "subcategory":"Textiles",
            "type":"Manufacturing & Wholesale Goods"
        }
    ],
    "sg:phone":"+32 4 384 68 45",
    "sg:postcode":"4920",
    "sg:province":"Li\u00e8ge",
    "wof:name":"La Mercerie",
    "wof:placetype":"venue"
},
  "geometry": {"coordinates":[5.6746778488,50.4746932983],"type":"Point"}
}