{
  "type": "Feature",
  "properties": {
    "iso:country":"BE",
    "sg:address":"Dokter Dejaselaan 8",
    "sg:city":"Schaarbeek/schaerbeek",
    "sg:classifiers":[
        {
            "category":"Restaurant",
            "type":"Food & Drink"
        }
    ],
    "sg:phone":"+32 2 216 06 70",
    "sg:postcode":"1030",
    "sg:province":"Bruxelles-Capitale",
    "wof:name":"Snack-bar Le Palindrome",
    "wof:placetype":"venue"
},
  "geometry": {"coordinates":[4.3893079758,50.8695907593],"type":"Point"}
}