{
  "type": "Feature",
  "properties": {
    "addr:full":"Rue Du Teris 42 (z.i. De La Boverie) Seraing Li\u00e8ge 4100",
    "addr:housenumber":"42",
    "addr:postcode":"4100",
    "addr:street":"Rue Du Teris;Z.I. De La Boverie",
    "iso:country":"BE",
    "sg:address":"Rue Du Teris 42 (z.i. De La Boverie)",
    "sg:city":"Seraing",
    "sg:orig_category":"Bouwmaterialen Gh",
    "sg:phone":"+32 4 337 15 24",
    "sg:postcode":"4100",
    "sg:province":"Li\u00e8ge",
    "wof:name":"Lo.ve.mat",
    "wof:placetype":"venue"
},
  "geometry": {"coordinates":[5.4970769882,50.6005325317],"type":"Point"}
}