{
  "type": "Feature",
  "properties": {
    "iso:country":"BE",
    "sg:address":"Rue Po\u00e8te Folie 53",
    "sg:city":"Fleurus",
    "sg:classifiers":[
        {
            "category":"Health Services",
            "subcategory":"Doctor",
            "type":"Services"
        }
    ],
    "sg:phone":"+32 71 81 64 31",
    "sg:postcode":"6220",
    "sg:province":"Hainaut",
    "sg:tags":[
        "medicinephysicians",
        "surgeon"
    ],
    "wof:name":"Bouffioux Bernard",
    "wof:placetype":"venue"
},
  "geometry": {"coordinates":[4.5462827682,50.4812088013],"type":"Point"}
}