{
  "type": "Feature",
  "properties": {
    "iso:country":"BE",
    "sg:address":"Chemin Tambourin 14",
    "sg:city":"Rebecq (rebecq-rognon)",
    "sg:classifiers":[
        {
            "category":"Professional",
            "subcategory":"Management & Consulting",
            "type":"Services"
        }
    ],
    "sg:phone":"+32 67 63 73 29",
    "sg:postcode":"1430",
    "sg:province":"Brabant Wallon",
    "sg:tags":[
        "-",
        "processing",
        "data",
        "consultant"
    ],
    "wof:name":"Idb Consultance Sprl",
    "wof:placetype":"venue"
},
  "geometry": {"coordinates":[4.1222147942,50.6561889648],"type":"Point"}
}