{
  "type": "Feature",
  "properties": {
    "addr:full":"Plantinstr. 25 Brussel Bruxelles-Capitale 1070",
    "addr:housenumber":"25",
    "addr:postcode":"1070",
    "addr:street":"Plantinstr.",
    "iso:country":"BE",
    "sg:address":"Plantinstr. 25",
    "sg:city":"Brussel",
    "sg:classifiers":[
        {
            "category":"Professional",
            "subcategory":"Advertising",
            "type":"Services"
        }
    ],
    "sg:phone":"+32 2 523 19 11",
    "sg:postcode":"1070",
    "sg:province":"Bruxelles-Capitale",
    "sg:tags":[
        "communication",
        "medium"
    ],
    "wof:name":"Tequila Nv",
    "wof:placetype":"venue"
},
  "geometry": {"coordinates":[4.3374681473,50.8433494568],"type":"Point"}
}