{
  "type": "Feature",
  "properties": {
    "addr:full":"Ankerslaan 19 Gent (ledeberg) Oost-Vlaanderen 9050",
    "addr:housenumber":"19",
    "addr:postcode":"9050",
    "addr:street":"Ankerslaan",
    "iso:country":"BE",
    "sg:address":"Ankerslaan 19",
    "sg:city":"Gent (ledeberg)",
    "sg:classifiers":[
        {
            "category":"Health Services",
            "subcategory":"Dentist",
            "type":"Services"
        }
    ],
    "sg:phone":"+32 9 230 23 30",
    "sg:postcode":"9050",
    "sg:province":"Oost-Vlaanderen",
    "wof:name":"Pede J",
    "wof:placetype":"venue"
},
  "geometry": {"coordinates":[3.7496409416,51.0382995605],"type":"Point"}
}