{
  "type": "Feature",
  "properties": {
    "iso:country":"BE",
    "sg:address":"Stationsweg 1a",
    "sg:city":"Lede",
    "sg:classifiers":[
        {
            "category":"Health Services",
            "subcategory":"Health Practitioner",
            "type":"Services"
        }
    ],
    "sg:phone":"+32 53 80 31 54",
    "sg:postcode":"9340",
    "sg:province":"Oost-Vlaanderen",
    "sg:tags":[
        "physiotherapist"
    ],
    "wof:name":"Smekens E",
    "wof:placetype":"venue"
},
  "geometry": {"coordinates":[3.9794929028,50.9679298401],"type":"Point"}
}