{
  "type": "Feature",
  "properties": {
    "addr:full":"Meersstraat 19 Ingelmunster West-Vlaanderen 8770",
    "addr:housenumber":"19",
    "addr:postcode":"8770",
    "addr:street":"Meersstraat",
    "iso:country":"BE",
    "sg:address":"Meersstraat 19",
    "sg:city":"Ingelmunster",
    "sg:orig_category":"Woningbouw",
    "sg:phone":"+32 51 48 70 94",
    "sg:postcode":"8770",
    "sg:province":"West-Vlaanderen",
    "wof:name":"Fa. Vanglabeke & Zn.",
    "wof:placetype":"venue"
},
  "geometry": {"coordinates":[3.2544429302,50.9393615723],"type":"Point"}
}