{
  "type": "Feature",
  "properties": {
    "iso:country":"BE",
    "sg:address":"Leopoldlaan 119",
    "sg:city":"Middelkerke",
    "sg:orig_category":"Newspapers, magazines, periodicals - Distribution",
    "sg:phone":"+32 59 30 68 89",
    "sg:postcode":"8430",
    "sg:province":"West-Vlaanderen",
    "wof:name":"De Beuckelaere F",
    "wof:placetype":"venue"
},
  "geometry": {"coordinates":[2.8109900951,51.1859092712],"type":"Point"}
}