{
  "type": "Feature",
  "properties": {
    "addr:full":"Place L\u00e9opold 1 Namur Namur 5000",
    "addr:housenumber":"1",
    "addr:postcode":"5000",
    "addr:street":"Place Le\u0301Opold",
    "iso:country":"BE",
    "sg:address":"Place L\u00e9opold 1",
    "sg:city":"Namur",
    "sg:classifiers":[
        {
            "category":"Bars & Pubs",
            "type":"Food & Drink"
        }
    ],
    "sg:phone":"+32 81 23 09 24",
    "sg:postcode":"5000",
    "sg:province":"Namur",
    "wof:name":"Paris (cafe De)",
    "wof:placetype":"venue"
},
  "geometry": {"coordinates":[4.8675060272,50.4685058594],"type":"Point"}
}