{
  "type": "Feature",
  "properties": {
    "addr:full":"Stokstraat 116 Sint-truiden Limburg 3800",
    "addr:housenumber":"116",
    "addr:postcode":"3800",
    "addr:street":"Stokstraat",
    "iso:country":"BE",
    "sg:address":"Stokstraat 116",
    "sg:city":"Sint-truiden",
    "sg:orig_category":"Sportclubs Sportterreinen and installaties behalve sportcentra",
    "sg:phone":"+32 11 31 60 20",
    "sg:postcode":"3800",
    "sg:province":"Limburg",
    "wof:name":"V.k. Zepperen",
    "wof:placetype":"venue"
},
  "geometry": {"coordinates":[5.2548360825,50.8421821594],"type":"Point"}
}