{
  "type": "Feature",
  "properties": {
    "iso:country":"BE",
    "sg:address":"Holleweg 19",
    "sg:city":"Brecht (sint-job-in-'t Goor)",
    "sg:classifiers":[
        {
            "category":"Utilities",
            "subcategory":"Natural Gas",
            "type":"Services"
        }
    ],
    "sg:phone":"+32 3 605 09 67",
    "sg:postcode":"2960",
    "sg:province":"Antwerpen",
    "sg:tags":[
        "firework"
    ],
    "wof:name":"Edruco Cv",
    "wof:placetype":"venue"
},
  "geometry": {"coordinates":[4.5549311638,51.2948265076],"type":"Point"}
}