{
  "type": "Feature",
  "properties": {
    "iso:country":"BE",
    "sg:address":"Ring 13",
    "sg:city":"Pepingen (bogaarden)",
    "sg:orig_category":"Non-Classified Establishments",
    "sg:phone":"+32 2 356 48 52",
    "sg:postcode":"1670",
    "sg:province":"Vlaams-Brabant",
    "wof:name":"Matton-van Duerm J",
    "wof:placetype":"venue"
},
  "geometry": {"coordinates":[4.1349859238,50.7397766113],"type":"Point"}
}