{
  "type": "Feature",
  "properties": {
    "addr:full":"Rue Abb\u00c9 Dropsy 39 Tournai Hainaut 7540",
    "addr:housenumber":"39",
    "addr:postcode":"7540",
    "addr:street":"Rue Abbe\u0301 Dropsy",
    "iso:country":"BE",
    "sg:address":"Rue Abb\u00c9 Dropsy 39",
    "sg:city":"Tournai",
    "sg:orig_category":"Location de biens divers. Fleurs and plantes. Plantes and fleurs Gr",
    "sg:phone":"+32 69 22 65 20",
    "sg:postcode":"7540",
    "sg:province":"Hainaut",
    "wof:name":"Ren\u00c9 Vandevondele",
    "wof:placetype":"venue"
},
  "geometry": {"coordinates":[3.3916859627,50.6325836182],"type":"Point"}
}