{
  "type": "Feature",
  "properties": {
    "iso:country":"BE",
    "sg:address":"Leonard Moorsstraat 41",
    "sg:city":"Lanaken",
    "sg:orig_category":"Centres de relaxation and bien-\u00eatre. Instituts de beaut\u00e9",
    "sg:phone":"+32 89 73 25 84",
    "sg:postcode":"3620",
    "sg:province":"Limburg",
    "wof:name":"Instituut Jeunesse",
    "wof:placetype":"venue"
},
  "geometry": {"coordinates":[5.6213641167,50.8640098572],"type":"Point"}
}