{
  "type": "Feature",
  "properties": {
    "addr:full":"Grand Rue 3 Bouillon Luxembourg 6830",
    "addr:housenumber":"3",
    "addr:postcode":"6830",
    "addr:street":"Grand Rue",
    "iso:country":"BE",
    "sg:address":"Grand Rue 3",
    "sg:city":"Bouillon",
    "sg:classifiers":[
        {
            "category":"Professional",
            "subcategory":"Testing Lab",
            "type":"Services"
        }
    ],
    "sg:phone":"+32 61 46 62 14",
    "sg:postcode":"6830",
    "sg:province":"Luxembourg",
    "sg:tags":[
        "chemist"
    ],
    "wof:name":"Di Paolo J-c",
    "wof:placetype":"venue"
},
  "geometry": {"coordinates":[5.0694198608,49.7953491211],"type":"Point"}
}