{
  "type": "Feature",
  "properties": {
    "iso:country":"BE",
    "sg:address":"Rue Reine Astrid 277",
    "sg:city":"Estaimpuis",
    "sg:orig_category":"Pain, p\u00e2tisseries and confiseries",
    "sg:phone":"+32 69 35 10 12",
    "sg:postcode":"7730",
    "sg:province":"Hainaut",
    "wof:name":"Francis Vignoble",
    "wof:placetype":"venue"
},
  "geometry": {"coordinates":[3.2466919422,50.6635551453],"type":"Point"}
}