{
  "type": "Feature",
  "properties": {
    "addr:full":"Wiekenweg 2 Baarle-hertog Antwerpen 2387",
    "addr:housenumber":"2",
    "addr:postcode":"2387",
    "addr:street":"Wiekenweg",
    "iso:country":"BE",
    "sg:address":"Wiekenweg 2",
    "sg:city":"Baarle-hertog",
    "sg:classifiers":[
        {
            "category":"Food & Beverages",
            "subcategory":"Groceries & Convenience Stores",
            "type":"Retail Goods"
        }
    ],
    "sg:phone":"+32 14 69 93 93",
    "sg:postcode":"2387",
    "sg:province":"Antwerpen",
    "sg:tags":[
        "baker",
        "-",
        "ingredient"
    ],
    "wof:name":"Van Der Schoof Bvba",
    "wof:placetype":"venue"
},
  "geometry": {"coordinates":[4.9327077866,51.437374115],"type":"Point"}
}