{
  "type": "Feature",
  "properties": {
    "addr:full":"Onledegoedstraat 37 Roeselare West-Vlaanderen 8800",
    "addr:housenumber":"37",
    "addr:postcode":"8800",
    "addr:street":"Onledegoedstraat",
    "iso:country":"BE",
    "sg:address":"Onledegoedstraat 37",
    "sg:city":"Roeselare",
    "sg:orig_category":"Diverse zakelijke dienstverlening",
    "sg:phone":"+32 51 20 63 47",
    "sg:postcode":"8800",
    "sg:province":"West-Vlaanderen",
    "wof:name":"Bel-service",
    "wof:placetype":"venue"
},
  "geometry": {"coordinates":[3.1373400688,50.9749984741],"type":"Point"}
}