{
  "type": "Feature",
  "properties": {
    "iso:country":"BE",
    "sg:address":"Berkenstraat 6",
    "sg:city":"Merksplas",
    "sg:orig_category":"Ordinateurs and \u00e9quipement informatique",
    "sg:phone":"+32 14 63 58 30",
    "sg:postcode":"2330",
    "sg:province":"Antwerpen",
    "wof:name":"W.j. Systems",
    "wof:placetype":"venue"
},
  "geometry": {"coordinates":[4.8442120552,51.3685684204],"type":"Point"}
}