{
  "type": "Feature",
  "properties": {
    "iso:country":"BE",
    "sg:address":"Place De La Constitution 12",
    "sg:city":"Sint-gillis/saint-gilles",
    "sg:orig_category":"Agences de voyages",
    "sg:phone":"+32 2 537 10 47",
    "sg:postcode":"1060",
    "sg:province":"Bruxelles-Capitale",
    "wof:name":"Alsa Voyage",
    "wof:placetype":"venue"
},
  "geometry": {"coordinates":[4.3406019211,50.8375511169],"type":"Point"}
}