{
  "type": "Feature",
  "properties": {
    "iso:country":"BE",
    "sg:address":"Citadelstraat 2",
    "sg:city":"Moeskroen/mouscron",
    "sg:orig_category":"Diverse bouwafwerking and reiniging Gespecialiseerde residenti\u00eble bouw Woningbouw",
    "sg:phone":"+32 56 34 69 54",
    "sg:postcode":"7712",
    "sg:province":"Hainaut",
    "wof:name":"Her-ma-tra",
    "wof:placetype":"venue"
},
  "geometry": {"coordinates":[3.2535879612,50.714931488],"type":"Point"}
}