{
  "type": "Feature",
  "properties": {
    "addr:full":"Holle Eikaard 31 Kontich Antwerpen 2550",
    "addr:housenumber":"31",
    "addr:postcode":"2550",
    "iso:country":"BE",
    "sg:address":"Holle Eikaard 31",
    "sg:city":"Kontich",
    "sg:classifiers":[
        {
            "category":"Building & Trades",
            "subcategory":"Plumbing",
            "type":"Services"
        }
    ],
    "sg:phone":"+32 3 457 38 01",
    "sg:postcode":"2550",
    "sg:province":"Antwerpen",
    "sg:tags":[
        "contractor"
    ],
    "wof:name":"Dirk Welslau Bvba",
    "wof:placetype":"venue"
},
  "geometry": {"coordinates":[4.4542570114,51.1365776062],"type":"Point"}
}