{
  "type": "Feature",
  "properties": {
    "addr:full":"Avenue De La Liberation 39 Aubange Luxembourg 6791",
    "addr:housenumber":"39",
    "addr:postcode":"6791",
    "addr:street":"Avenue De La Liberation",
    "iso:country":"BE",
    "sg:address":"Avenue De La Liberation 39",
    "sg:city":"Aubange",
    "sg:orig_category":"Pharmaciens",
    "sg:phone":"+32 63 38 15 11",
    "sg:postcode":"6791",
    "sg:province":"Luxembourg",
    "wof:name":"Clinique Belle Vue",
    "wof:placetype":"venue"
},
  "geometry": {"coordinates":[5.8368301392,49.5627288818],"type":"Point"}
}