{
  "type": "Feature",
  "properties": {
    "addr:full":"Boulevard De Bryas 6 Couvin Namur 5660",
    "addr:housenumber":"6",
    "addr:postcode":"5660",
    "addr:street":"Boulevard De Bryas",
    "iso:country":"BE",
    "sg:address":"Boulevard De Bryas 6",
    "sg:city":"Couvin",
    "sg:orig_category":"Artistes ind\u00e9pendants",
    "sg:phone":"+32 60 31 24 46",
    "sg:postcode":"5660",
    "sg:province":"Namur",
    "wof:name":"Pascal Letoret",
    "wof:placetype":"venue"
},
  "geometry": {"coordinates":[4.5222020149,50.0933227539],"type":"Point"}
}