{
  "type": "Feature",
  "properties": {
    "iso:country":"BE",
    "sg:address":"Diestsestraat 3",
    "sg:city":"Aarschot",
    "sg:classifiers":[
        {
            "category":"Cafe",
            "type":"Food & Drink"
        }
    ],
    "sg:phone":"+32 16 57 29 09",
    "sg:postcode":"3200",
    "sg:province":"Vlaams-Brabant",
    "sg:tags":[
        "caf\u00e9s"
    ],
    "wof:name":"'t Kaffee",
    "wof:placetype":"venue"
},
  "geometry": {"coordinates":[4.8363518715,50.9837837219],"type":"Point"}
}