{
  "type": "Feature",
  "properties": {
    "iso:country":"BE",
    "sg:address":"Chauss\u00e9e De Marche 12",
    "sg:city":"Neupr\u00e9 (ehein)",
    "sg:classifiers":[
        {
            "category":"Retail",
            "subcategory":"Auto Repair",
            "type":"Services"
        }
    ],
    "sg:phone":"+32 4 371 55 35",
    "sg:postcode":"4120",
    "sg:province":"Li\u00e8ge",
    "sg:tags":[
        "garage"
    ],
    "wof:name":"Detry",
    "wof:placetype":"venue"
},
  "geometry": {"coordinates":[5.4429268837,50.5440635681],"type":"Point"}
}