{
  "type": "Feature",
  "properties": {
    "addr:full":"Rue Brasseur 5 Fleurus Hainaut 6221",
    "addr:housenumber":"5",
    "addr:postcode":"6221",
    "addr:street":"Rue Brasseur",
    "iso:country":"BE",
    "sg:address":"Rue Brasseur 5",
    "sg:city":"Fleurus",
    "sg:orig_category":"Journaux. Tabac. Librairies. Fournitures de bureau",
    "sg:phone":"+32 71 80 05 46",
    "sg:postcode":"6221",
    "sg:province":"Hainaut",
    "wof:name":"Maison Page \u00c0 Page",
    "wof:placetype":"venue"
},
  "geometry": {"coordinates":[4.5451278687,50.5142593384],"type":"Point"}
}