{
  "type": "Feature",
  "properties": {
    "iso:country":"BE",
    "sg:address":"Rue Provinciale 79",
    "sg:city":"Wavre (bierges)",
    "sg:classifiers":[
        {
            "category":"Professional",
            "subcategory":"Computer Services",
            "type":"Services"
        }
    ],
    "sg:phone":"+32 10 41 93 24",
    "sg:postcode":"1301",
    "sg:province":"Brabant Wallon",
    "sg:tags":[
        "-",
        "processing",
        "data"
    ],
    "wof:name":"C.s.b.o.",
    "wof:placetype":"venue"
},
  "geometry": {"coordinates":[4.5990991592,50.7114868164],"type":"Point"}
}