{
  "type": "Feature",
  "properties": {
    "addr:full":"Jef Vandermeulenstraat 126 Gent Oost-Vlaanderen 9050",
    "addr:housenumber":"126",
    "addr:postcode":"9050",
    "addr:street":"Jef Vandermeulenstraat;Oost-Vlaanderen",
    "iso:country":"BE",
    "sg:address":"Jef Vandermeulenstraat 126",
    "sg:city":"Gent",
    "sg:orig_category":"Herstellingen and onderhoud van auto's",
    "sg:phone":"+32 9 231 23 36",
    "sg:postcode":"9050",
    "sg:province":"Oost-Vlaanderen",
    "wof:name":"Marc Van Eenaeme",
    "wof:placetype":"venue"
},
  "geometry": {"coordinates":[3.7560811043,51.0410804749],"type":"Point"}
}