{
  "type": "Feature",
  "properties": {
    "iso:country":"BE",
    "sg:address":"Route Des Cr\u00eates 88",
    "sg:city":"Profondeville",
    "sg:classifiers":[
        {
            "category":"Shopping",
            "subcategory":"Gifts & Souvenirs",
            "type":"Retail Goods"
        }
    ],
    "sg:phone":"+32 81 41 24 24",
    "sg:postcode":"5170",
    "sg:province":"Namur",
    "sg:tags":[
        "-"
    ],
    "wof:name":"Metalflex Sprl",
    "wof:placetype":"venue"
},
  "geometry": {"coordinates":[4.8631658554,50.3870887756],"type":"Point"}
}