{
  "type": "Feature",
  "properties": {
    "iso:country":"BE",
    "sg:address":"Nieuwstraat 14",
    "sg:city":"De Haan (klemskerke)",
    "sg:classifiers":[
        {
            "category":"Building & Trades",
            "subcategory":"Pest Control",
            "type":"Services"
        }
    ],
    "sg:phone":"+32 59 23 31 83",
    "sg:postcode":"8420",
    "sg:province":"West-Vlaanderen",
    "sg:tags":[
        "painting",
        "contractor"
    ],
    "wof:name":"Dobbels W",
    "wof:placetype":"venue"
},
  "geometry": {"coordinates":[3.0353651047,51.272064209],"type":"Point"}
}