{
  "type": "Feature",
  "properties": {
    "addr:full":"Bergstraat 11 Hoeselt Limburg 3730",
    "addr:housenumber":"11",
    "addr:postcode":"3730",
    "addr:street":"Bergstraat",
    "iso:country":"BE",
    "sg:address":"Bergstraat 11",
    "sg:city":"Hoeselt",
    "sg:orig_category":"Sportclubs",
    "sg:phone":"+32 89 41 64 88",
    "sg:postcode":"3730",
    "sg:province":"Limburg",
    "wof:name":"Limburgse Kever Club",
    "wof:placetype":"venue"
},
  "geometry": {"coordinates":[5.4855599403,50.8532829285],"type":"Point"}
}