{
  "type": "Feature",
  "properties": {
    "addr:full":"Brouwerijstraat 22 Box 2c Aalter Oost-Vlaanderen 9880",
    "addr:housenumber":"22;2c",
    "addr:postcode":"9880",
    "addr:street":"Brouwerijstraat;Box",
    "iso:country":"BE",
    "sg:address":"Brouwerijstraat 22 Box 2c",
    "sg:city":"Aalter",
    "sg:classifiers":[
        {
            "category":"Health Services",
            "subcategory":"Doctor",
            "type":"Services"
        }
    ],
    "sg:phone":"+32 9 374 63 33",
    "sg:postcode":"9880",
    "sg:province":"Oost-Vlaanderen",
    "sg:tags":[
        "medicinephysicians",
        "surgeon"
    ],
    "wof:name":"Acke Ingrid",
    "wof:placetype":"venue"
},
  "geometry": {"coordinates":[3.4482300282,51.0872917175],"type":"Point"}
}