{
  "type": "Feature",
  "properties": {
    "addr:full":"Adolphe Buyllaan 110a Elsene/ixelles Bruxelles-Capitale 1050",
    "addr:housenumber":"110a",
    "addr:postcode":"1050",
    "addr:street":"Adolphe Buyllaan",
    "iso:country":"BE",
    "sg:address":"Adolphe Buyllaan 110a",
    "sg:city":"Elsene/ixelles",
    "sg:orig_category":"Artsen and specialisten",
    "sg:phone":"+32 2 649 81 15",
    "sg:postcode":"1050",
    "sg:province":"Bruxelles-Capitale",
    "wof:name":"Brigitte Schrurs",
    "wof:placetype":"venue"
},
  "geometry": {"coordinates":[4.383482933,50.8158531189],"type":"Point"}
}