{
  "type": "Feature",
  "properties": {
    "iso:country":"BE",
    "sg:address":"Rue Mab\u00ceme 58",
    "sg:city":"Ans",
    "sg:orig_category":"Installation de menuiserie en bois and plastique. Construction de maisons",
    "sg:phone":"+32 4 338 43 43",
    "sg:postcode":"4432",
    "sg:province":"Li\u00e8ge",
    "wof:name":"Immobat",
    "wof:placetype":"venue"
},
  "geometry": {"coordinates":[5.5202579498,50.6700973511],"type":"Point"}
}