{
  "type": "Feature",
  "properties": {
    "addr:full":"Rue Albert Meunier 64 Bruxelles (auderghem) Bruxelles-Capitale 1160",
    "addr:housenumber":"64",
    "addr:postcode":"1160",
    "addr:street":"Rue Albert Meunier",
    "iso:country":"BE",
    "sg:address":"Rue Albert Meunier 64",
    "sg:city":"Bruxelles (auderghem)",
    "sg:classifiers":[
        {
            "category":"Social Services",
            "type":"Services"
        }
    ],
    "sg:phone":"+32 2 662 23 33",
    "sg:postcode":"1160",
    "sg:province":"Bruxelles-Capitale",
    "wof:name":"Groupe Recherche Action En Soins Infirmiers",
    "wof:placetype":"venue"
},
  "geometry": {"coordinates":[4.4377179146,50.8105392456],"type":"Point"}
}