{
  "type": "Feature",
  "properties": {
    "iso:country":"BE",
    "sg:address":"Pont Du Christ 46",
    "sg:city":"Wavre",
    "sg:classifiers":[
        {
            "category":"Shopping",
            "subcategory":"Clothing, Apparel, & Fashions",
            "type":"Retail Goods"
        }
    ],
    "sg:phone":"+32 10 81 51 01",
    "sg:postcode":"1300",
    "sg:province":"Brabant Wallon",
    "sg:tags":[
        "-",
        "clothing",
        "child"
    ],
    "wof:name":"Orchestra",
    "wof:placetype":"venue"
},
  "geometry": {"coordinates":[4.6092939377,50.7159118652],"type":"Point"}
}