{
  "type": "Feature",
  "properties": {
    "addr:full":"Rue Du Moulin 61 Wasseiges Li\u00e8ge 4219",
    "addr:housenumber":"61",
    "addr:postcode":"4219",
    "addr:street":"Rue Du Moulin",
    "iso:country":"BE",
    "sg:address":"Rue Du Moulin 61",
    "sg:city":"Wasseiges",
    "sg:orig_category":"Enseignement maternel and primaire",
    "sg:phone":"+32 81 85 66 11",
    "sg:postcode":"4219",
    "sg:province":"Li\u00e8ge",
    "wof:name":"Ecole Fond. Communale",
    "wof:placetype":"venue"
},
  "geometry": {"coordinates":[5.0001702309,50.6243515015],"type":"Point"}
}