{
  "type": "Feature",
  "properties": {
    "addr:full":"Sint-pietersaalststraat 15 Gent Oost-Vlaanderen 9000",
    "addr:housenumber":"15",
    "addr:postcode":"9000",
    "addr:street":"Sint-Pietersaalststraat;Oost-Vlaanderen",
    "iso:country":"BE",
    "sg:address":"Sint-pietersaalststraat 15",
    "sg:city":"Gent",
    "sg:orig_category":"Artsen and specialisten",
    "sg:phone":"+32 9 221 24 19",
    "sg:postcode":"9000",
    "sg:province":"Oost-Vlaanderen",
    "wof:name":"M. Vervoort",
    "wof:placetype":"venue"
},
  "geometry": {"coordinates":[3.7143719196,51.0310745239],"type":"Point"}
}