{
  "type": "Feature",
  "properties": {
    "addr:full":"Rosweg 59b Lennik Vlaams-Brabant 1750",
    "addr:housenumber":"59b;1750",
    "addr:street":"Rosweg;Vlaams-Brabant",
    "iso:country":"BE",
    "sg:address":"Rosweg 59b",
    "sg:city":"Lennik",
    "sg:classifiers":[
        {
            "category":"Personal",
            "subcategory":"Beauty Salon",
            "type":"Services"
        }
    ],
    "sg:phone":"+32 2 569 42 86",
    "sg:postcode":"1750",
    "sg:province":"Vlaams-Brabant",
    "sg:tags":[
        "de",
        "coiffure"
    ],
    "wof:name":"Coiffure Claudia",
    "wof:placetype":"venue"
},
  "geometry": {"coordinates":[4.1986532211,50.8209648132],"type":"Point"}
}