{
  "type": "Feature",
  "properties": {
    "iso:country":"BE",
    "sg:address":"Kalfortdorp 43",
    "sg:city":"Puurs",
    "sg:classifiers":[
        {
            "category":"Bakery",
            "type":"Food & Drink"
        }
    ],
    "sg:phone":"+32 3 889 08 65",
    "sg:postcode":"2870",
    "sg:province":"Antwerpen",
    "sg:tags":[
        "confectioner",
        "baker"
    ],
    "wof:name":"Schampaert W Bvba",
    "wof:placetype":"venue"
},
  "geometry": {"coordinates":[4.2772698402,51.0763244629],"type":"Point"}
}