{
  "type": "Feature",
  "properties": {
    "addr:full":"Rue Baronne Lemonnier 3 Rochefort Namur 5580",
    "addr:housenumber":"3",
    "addr:postcode":"5580",
    "addr:street":"Rue Baronne Lemonnier",
    "iso:country":"BE",
    "sg:address":"Rue Baronne Lemonnier 3",
    "sg:city":"Rochefort",
    "sg:orig_category":"Charpentes and couvertures",
    "sg:phone":"+32 84 38 99 65",
    "sg:postcode":"5580",
    "sg:province":"Namur",
    "wof:name":"Philippe Morenville",
    "wof:placetype":"venue"
},
  "geometry": {"coordinates":[5.1015372276,50.1162376404],"type":"Point"}
}