{
  "type": "Feature",
  "properties": {
    "addr:full":"Rue Neuve 67 Brussel/bruxelles Bruxelles-Capitale 1000",
    "addr:housenumber":"67",
    "addr:postcode":"1000",
    "addr:street":"Rue Neuve;/",
    "iso:country":"BE",
    "sg:address":"Rue Neuve 67",
    "sg:city":"Brussel/bruxelles",
    "sg:classifiers":[
        {
            "category":"Shopping",
            "subcategory":"Clothing, Apparel, & Fashions",
            "type":"Retail Goods"
        }
    ],
    "sg:phone":"+32 2 217 40 04",
    "sg:postcode":"1000",
    "sg:province":"Bruxelles-Capitale",
    "sg:tags":[
        "v\u00eatements",
        "pour",
        "dame"
    ],
    "wof:name":"Etam",
    "wof:placetype":"venue"
},
  "geometry": {"coordinates":[4.355902195,50.8525238037],"type":"Point"}
}