{
  "type": "Feature",
  "properties": {
    "addr:full":"Peter Benoitlaan 31ba Kontich Antwerpen 2550",
    "addr:housenumber":"31ba",
    "addr:postcode":"2550",
    "addr:street":"Peter Benoitlaan",
    "iso:country":"BE",
    "sg:address":"Peter Benoitlaan 31ba",
    "sg:city":"Kontich",
    "sg:orig_category":"Activit\u00e9s diverses d'imprimerie",
    "sg:phone":"+32 3 457 72 04",
    "sg:postcode":"2550",
    "sg:province":"Antwerpen",
    "wof:name":"Cesart",
    "wof:placetype":"venue"
},
  "geometry": {"coordinates":[4.4441800117,51.1386299133],"type":"Point"}
}