{
  "type": "Feature",
  "properties": {
    "iso:country":"BE",
    "sg:address":"Dendermondesteenweg 656",
    "sg:city":"Destelbergen",
    "sg:classifiers":[
        {
            "category":"Fast Food",
            "type":"Food & Drink"
        }
    ],
    "sg:phone":"+32 9 228 44 90",
    "sg:postcode":"9070",
    "sg:province":"Oost-Vlaanderen",
    "sg:tags":[
        "\u00c0",
        "emporter",
        "restaurants"
    ],
    "wof:name":"De Max",
    "wof:placetype":"venue"
},
  "geometry": {"coordinates":[3.8185520172,51.0587806702],"type":"Point"}
}