{
  "type": "Feature",
  "properties": {
    "addr:full":"Otto Veniusstraat 11 Antwerpen Antwerpen 2000",
    "addr:housenumber":"11",
    "addr:postcode":"2000",
    "addr:street":"Otto Veniusstraat",
    "iso:country":"BE",
    "sg:address":"Otto Veniusstraat 11",
    "sg:city":"Antwerpen",
    "sg:classifiers":[
        {
            "category":"Home & Garden",
            "subcategory":"Home Furnishings",
            "type":"Retail Goods"
        }
    ],
    "sg:phone":"+32 3 232 02 61",
    "sg:postcode":"2000",
    "sg:province":"Antwerpen",
    "sg:tags":[
        "-",
        "furniture"
    ],
    "wof:name":"Lammers-van Mele Bvba",
    "wof:placetype":"venue"
},
  "geometry": {"coordinates":[4.4128441811,51.2176017761],"type":"Point"}
}