{
  "type": "Feature",
  "properties": {
    "addr:full":"Van Veldekelaan 2 Hasselt Limburg 3510",
    "addr:housenumber":"2",
    "addr:postcode":"3510",
    "addr:street":"Van Veldekelaan",
    "iso:country":"BE",
    "sg:address":"Van Veldekelaan 2",
    "sg:city":"Hasselt",
    "sg:orig_category":"Dranken Gh",
    "sg:phone":"+32 11 25 06 69",
    "sg:postcode":"3510",
    "sg:province":"Limburg",
    "wof:name":"Bierhandel Swinnen",
    "wof:placetype":"venue"
},
  "geometry": {"coordinates":[5.235145092,50.9479789734],"type":"Point"}
}