{
  "type": "Feature",
  "properties": {
    "iso:country":"BE",
    "sg:address":"Rue De Beho 30",
    "sg:city":"Gouvy",
    "sg:orig_category":"Antiquit\u00e9s",
    "sg:phone":"+32 80 51 78 80",
    "sg:postcode":"6670",
    "sg:province":"Luxembourg",
    "wof:name":"Maison Peters",
    "wof:placetype":"venue"
},
  "geometry": {"coordinates":[5.9584999084,50.1904296875],"type":"Point"}
}