{
  "type": "Feature",
  "properties": {
    "addr:full":"Monnikenwerve 66 Brugge West-Vlaanderen 8000",
    "addr:housenumber":"66",
    "addr:postcode":"8000",
    "addr:street":"Monnikenwerve",
    "iso:country":"BE",
    "sg:address":"Monnikenwerve 66",
    "sg:city":"Brugge",
    "sg:classifiers":[
        {
            "category":"Building & Trades",
            "subcategory":"Pest Control",
            "type":"Services"
        }
    ],
    "sg:phone":"+32 50 31 02 21",
    "sg:postcode":"8000",
    "sg:province":"West-Vlaanderen",
    "sg:tags":[
        "painting",
        "contractor"
    ],
    "wof:name":"D'hondt A",
    "wof:placetype":"venue"
},
  "geometry": {"coordinates":[3.202698946,51.2481231689],"type":"Point"}
}