{
  "type": "Feature",
  "properties": {
    "iso:country":"BE",
    "sg:address":"Donystraat 1",
    "sg:city":"Tienen",
    "sg:classifiers":[
        {
            "category":"Bars & Pubs",
            "type":"Food & Drink"
        }
    ],
    "sg:phone":"+32 16 82 06 43",
    "sg:postcode":"3300",
    "sg:province":"Vlaams-Brabant",
    "wof:name":"Wulk(de)",
    "wof:placetype":"venue"
},
  "geometry": {"coordinates":[4.9426321983,50.8059768677],"type":"Point"}
}