{
  "type": "Feature",
  "properties": {
    "iso:country":"BE",
    "sg:address":"De Keyserlei 51",
    "sg:city":"Antwerpen",
    "sg:classifiers":[
        {
            "category":"Fast Food",
            "type":"Food & Drink"
        }
    ],
    "sg:phone":"+32 3 233 68 10",
    "sg:postcode":"2018",
    "sg:province":"Antwerpen",
    "sg:tags":[
        "\u00c0",
        "restaurants",
        "emporter",
        "restaurant"
    ],
    "wof:name":"Pizza Hut",
    "wof:placetype":"venue"
},
  "geometry": {"coordinates":[4.4196801186,51.2174720764],"type":"Point"}
}