{
  "type": "Feature",
  "properties": {
    "addr:full":"Rue Gustave Delperdange 34 Bastogne Luxembourg 6600",
    "addr:housenumber":"34",
    "addr:postcode":"6600",
    "addr:street":"Rue Gustave Delperdange",
    "iso:country":"BE",
    "sg:address":"Rue Gustave Delperdange 34",
    "sg:city":"Bastogne",
    "sg:classifiers":[
        {
            "category":"Organizations",
            "subcategory":"Community Association",
            "type":"Services"
        }
    ],
    "sg:phone":"+32 61 21 65 30",
    "sg:postcode":"6600",
    "sg:province":"Luxembourg",
    "sg:tags":[
        "cultural"
    ],
    "wof:name":"Centre Culturel Bastogne Asbl",
    "wof:placetype":"venue"
},
  "geometry": {"coordinates":[5.726500988,50.0074234009],"type":"Point"}
}