{
  "type": "Feature",
  "properties": {
    "iso:country":"BE",
    "sg:address":"Alphonse De Hollainhof 1",
    "sg:city":"Gent",
    "sg:orig_category":"Cr\u00e8ches and garderies d'enfants",
    "sg:phone":"+32 9 224 35 99",
    "sg:postcode":"9000",
    "sg:province":"Oost-Vlaanderen",
    "wof:name":"Cr\u00c8che De Kleine Prins",
    "wof:placetype":"venue"
},
  "geometry": {"coordinates":[3.7365500927,51.0448112488],"type":"Point"}
}