{
  "type": "Feature",
  "properties": {
    "addr:full":"Zandstraat 26 Beveren Oost-Vlaanderen 9120",
    "addr:housenumber":"26",
    "addr:postcode":"9120",
    "addr:street":"Zandstraat",
    "iso:country":"BE",
    "sg:address":"Zandstraat 26",
    "sg:city":"Beveren",
    "sg:orig_category":"Woningbouw",
    "sg:phone":"+32 3 775 77 87",
    "sg:postcode":"9120",
    "sg:province":"Oost-Vlaanderen",
    "wof:name":"Van Steelandt Andr\u00c9",
    "wof:placetype":"venue"
},
  "geometry": {"coordinates":[4.2371897697,51.1824073792],"type":"Point"}
}