{
  "type": "Feature",
  "properties": {
    "iso:country":"BE",
    "sg:address":"Chauss\u00c9e De Renaix 39",
    "sg:city":"Tournai",
    "sg:orig_category":"Artsen and specialisten",
    "sg:phone":"+32 69 23 37 55",
    "sg:postcode":"7500",
    "sg:province":"Hainaut",
    "wof:name":"B. Conem",
    "wof:placetype":"venue"
},
  "geometry": {"coordinates":[3.4044480324,50.6129341125],"type":"Point"}
}