{
  "type": "Feature",
  "properties": {
    "addr:full":"Mechelsesteenweg 333 Lier Antwerpen 2500",
    "addr:housenumber":"333",
    "addr:postcode":"2500",
    "addr:street":"Mechelsesteenweg",
    "iso:country":"BE",
    "sg:address":"Mechelsesteenweg 333",
    "sg:city":"Lier",
    "sg:classifiers":[
        {
            "category":"Building & Trades",
            "subcategory":"Construction",
            "type":"Services"
        }
    ],
    "sg:phone":"+32 3 480 24 02",
    "sg:postcode":"2500",
    "sg:province":"Antwerpen",
    "sg:tags":[
        "machine",
        "hiring"
    ],
    "wof:name":"Vermeulen - Van Huffelen B.v.b.a.",
    "wof:placetype":"venue"
},
  "geometry": {"coordinates":[4.5311470032,51.1126480103],"type":"Point"}
}