{
  "type": "Feature",
  "properties": {
    "addr:full":"Amarantlaan 31 Brussel/bruxelles Bruxelles-Capitale 1020",
    "addr:housenumber":"31",
    "addr:postcode":"1020",
    "addr:street":"Amarantlaan;/",
    "iso:country":"BE",
    "sg:address":"Amarantlaan 31",
    "sg:city":"Brussel/bruxelles",
    "sg:classifiers":[
        {
            "category":"Insurance",
            "subcategory":"Insurance Agent",
            "type":"Services"
        }
    ],
    "sg:phone":"+32 2 268 04 46",
    "sg:postcode":"1020",
    "sg:province":"Bruxelles-Capitale",
    "sg:tags":[
        "verzekeringsmakelaars",
        "expert"
    ],
    "wof:name":"G.l. Insurance & Service",
    "wof:placetype":"venue"
},
  "geometry": {"coordinates":[4.3627700806,50.8952941895],"type":"Point"}
}