{
  "type": "Feature",
  "properties": {
    "iso:country":"BE",
    "sg:address":"Avenue Henri Conscience 169",
    "sg:city":"Evere/evere",
    "sg:orig_category":"Magasins de r\u00e9parations d'articles personnels et m\u00e9nagers divers",
    "sg:phone":"+32 2 241 94 75",
    "sg:postcode":"1140",
    "sg:province":"Bruxelles-Capitale",
    "wof:name":"M.t. Retouches",
    "wof:placetype":"venue"
},
  "geometry": {"coordinates":[4.3999009132,50.8720207214],"type":"Point"}
}