{
  "type": "Feature",
  "properties": {
    "iso:country":"BE",
    "sg:address":"Generaal De Ceuninckstr. 56",
    "sg:city":"Mechelen",
    "sg:orig_category":"Ordinateurs and \u00e9quipement informatique",
    "sg:phone":"+32 15 20 44 15",
    "sg:postcode":"2800",
    "sg:province":"Antwerpen",
    "wof:name":"Simplex",
    "wof:placetype":"venue"
},
  "geometry": {"coordinates":[4.4795742035,51.0355682373],"type":"Point"}
}