{
  "type": "Feature",
  "properties": {
    "addr:full":"Rue Saint-nicolas 392 Li\u00e8ge 1 Li\u00e8ge 4000",
    "addr:housenumber":"392;1",
    "addr:postcode":"4000",
    "addr:street":"Rue Saint-Nicolas",
    "iso:country":"BE",
    "sg:address":"Rue Saint-nicolas 392",
    "sg:city":"Li\u00e8ge 1",
    "sg:classifiers":[
        {
            "category":"Manufacturing",
            "subcategory":"Furniture",
            "type":"Manufacturing & Wholesale Goods"
        }
    ],
    "sg:phone":"+32 4 226 31 93",
    "sg:postcode":"4000",
    "sg:province":"Li\u00e8ge",
    "sg:tags":[
        "armchair",
        "-"
    ],
    "wof:name":"Mebelco",
    "wof:placetype":"venue"
},
  "geometry": {"coordinates":[5.5403428078,50.6392593384],"type":"Point"}
}