{
  "type": "Feature",
  "properties": {
    "addr:full":"Maastrichterstraat 1 Hasselt Limburg 3500",
    "addr:housenumber":"1",
    "addr:postcode":"3500",
    "addr:street":"Maastrichterstraat",
    "iso:country":"BE",
    "sg:address":"Maastrichterstraat 1",
    "sg:city":"Hasselt",
    "sg:classifiers":[
        {
            "category":"Shopping",
            "subcategory":"Clothing, Apparel, & Fashions",
            "type":"Retail Goods"
        }
    ],
    "sg:phone":"+32 11 24 14 04",
    "sg:postcode":"3500",
    "sg:province":"Limburg",
    "sg:tags":[
        "-",
        "clothing",
        "child"
    ],
    "wof:name":"Mar\u00e8se",
    "wof:placetype":"venue"
},
  "geometry": {"coordinates":[5.3379402161,50.9291534424],"type":"Point"}
}