{
  "type": "Feature",
  "properties": {
    "addr:full":"Industrieln 24 Hoeselt Limburg 3730",
    "addr:housenumber":"24",
    "addr:postcode":"3730",
    "addr:street":"Industrieln",
    "iso:country":"BE",
    "sg:address":"Industrieln 24",
    "sg:city":"Hoeselt",
    "sg:classifiers":[
        {
            "category":"Wholesale",
            "subcategory":"Machinery & Supplies",
            "type":"Manufacturing & Wholesale Goods"
        }
    ],
    "sg:phone":"+32 89 41 19 20",
    "sg:postcode":"3730",
    "sg:province":"Limburg",
    "sg:tags":[
        "food",
        "processing",
        "-",
        "machine",
        "equipment",
        "engineering",
        "mechanical"
    ],
    "wof:name":"Erens Nv",
    "wof:placetype":"venue"
},
  "geometry": {"coordinates":[5.4872760773,50.8583488464],"type":"Point"}
}