{
  "type": "Feature",
  "properties": {
    "iso:country":"BE",
    "sg:address":"Grote Markt 25",
    "sg:city":"Herentals",
    "sg:classifiers":[
        {
            "category":"Cafe",
            "type":"Food & Drink"
        }
    ],
    "sg:phone":"+32 14 22 04 33",
    "sg:postcode":"2200",
    "sg:province":"Antwerpen",
    "sg:tags":[
        "caf\u00e9s"
    ],
    "wof:name":"Gildenhuis",
    "wof:placetype":"venue"
},
  "geometry": {"coordinates":[4.8357629776,51.1768531799],"type":"Point"}
}