{
  "type": "Feature",
  "properties": {
    "iso:country":"BE",
    "sg:address":"Outre-cour 58",
    "sg:city":"Herve (battice)",
    "sg:classifiers":[
        {
            "category":"Retail",
            "subcategory":"Auto Repair",
            "type":"Services"
        }
    ],
    "sg:phone":"+32 87 67 98 80",
    "sg:postcode":"4651",
    "sg:province":"Li\u00e8ge",
    "sg:tags":[
        "breakdown",
        "automobile",
        "-",
        "recovery"
    ],
    "wof:name":"Garage Du Plateau Sprl",
    "wof:placetype":"venue"
},
  "geometry": {"coordinates":[5.7771539688,50.6385154724],"type":"Point"}
}