{
  "type": "Feature",
  "properties": {
    "iso:country":"BE",
    "sg:address":"Stationsstraat 17",
    "sg:city":"Haaltert",
    "sg:classifiers":[
        {
            "category":"Health Services",
            "subcategory":"Health Practitioner",
            "type":"Services"
        }
    ],
    "sg:phone":"+32 53 83 77 76",
    "sg:postcode":"9450",
    "sg:province":"Oost-Vlaanderen",
    "sg:tags":[
        "physiotherapist"
    ],
    "wof:name":"Degraeve E",
    "wof:placetype":"venue"
},
  "geometry": {"coordinates":[4.0077781677,50.9021949768],"type":"Point"}
}