{
  "type": "Feature",
  "properties": {
    "addr:full":"Rue Grande 106 Dour Hainaut 7370",
    "addr:housenumber":"106",
    "addr:postcode":"7370",
    "addr:street":"Rue Grande;Hainaut",
    "iso:country":"BE",
    "sg:address":"Rue Grande 106",
    "sg:city":"Dour",
    "sg:classifiers":[
        {
            "category":"Professional",
            "subcategory":"Art Services",
            "type":"Services"
        }
    ],
    "sg:phone":"+32 65 63 32 80",
    "sg:postcode":"7370",
    "sg:province":"Hainaut",
    "sg:tags":[
        "photographer"
    ],
    "wof:name":"Imagix",
    "wof:placetype":"venue"
},
  "geometry": {"coordinates":[3.7822210789,50.3999404907],"type":"Point"}
}