{
  "type": "Feature",
  "properties": {
    "iso:country":"BE",
    "sg:address":"Luikerstw 131",
    "sg:city":"Sint-truiden",
    "sg:classifiers":[
        {
            "category":"Professional",
            "subcategory":"Engineering",
            "type":"Services"
        }
    ],
    "sg:phone":"+32 11 68 68 52",
    "sg:postcode":"3800",
    "sg:province":"Limburg",
    "sg:tags":[
        "machine",
        "-",
        "mechanical"
    ],
    "wof:name":"Morren Motor Nv",
    "wof:placetype":"venue"
},
  "geometry": {"coordinates":[5.1863641739,50.8153343201],"type":"Point"}
}