{
  "type": "Feature",
  "properties": {
    "iso:country":"BE",
    "sg:address":"Steenstraat 107",
    "sg:city":"Meulebeke",
    "sg:orig_category":"Woningbouw",
    "sg:phone":"+32 51 48 63 81",
    "sg:postcode":"8760",
    "sg:province":"West-Vlaanderen",
    "wof:name":"Stemabouw",
    "wof:placetype":"venue"
},
  "geometry": {"coordinates":[3.2852890491,50.9419250488],"type":"Point"}
}