{
  "type": "Feature",
  "properties": {
    "iso:country":"BE",
    "sg:address":"Chauss\u00e9e De Ninove 1084",
    "sg:city":"Bruxelles (molenbeek-saint-jean)",
    "sg:classifiers":[
        {
            "category":"Shopping",
            "subcategory":"Clothing, Apparel, & Fashions",
            "type":"Retail Goods"
        }
    ],
    "sg:phone":"+32 2 522 44 64",
    "sg:postcode":"1080",
    "sg:province":"Bruxelles-Capitale",
    "sg:tags":[
        "designer",
        "stylist"
    ],
    "wof:name":"Jeanine",
    "wof:placetype":"venue"
},
  "geometry": {"coordinates":[4.2885198593,50.8459091187],"type":"Point"}
}