{
  "type": "Feature",
  "properties": {
    "addr:full":"Zevekotesteenweg 5 Middelkerke West-Vlaanderen 8432",
    "addr:housenumber":"5",
    "addr:postcode":"8432",
    "addr:street":"Zevekotesteenweg",
    "iso:country":"BE",
    "sg:address":"Zevekotesteenweg 5",
    "sg:city":"Middelkerke",
    "sg:orig_category":"Rundveehouders",
    "sg:phone":"+32 59 27 75 36",
    "sg:postcode":"8432",
    "sg:province":"West-Vlaanderen",
    "wof:name":"Gilbert Gunst",
    "wof:placetype":"venue"
},
  "geometry": {"coordinates":[2.8863449097,51.1537818909],"type":"Point"}
}