{
  "type": "Feature",
  "properties": {
    "addr:full":"Boekelbaan 129 Zwalm Oost-Vlaanderen 9630",
    "addr:housenumber":"129",
    "addr:postcode":"9630",
    "addr:street":"Zwalm Oost-Vlaanderen",
    "iso:country":"BE",
    "sg:address":"Boekelbaan 129",
    "sg:city":"Zwalm",
    "sg:orig_category":"Eleveurs de bovins",
    "sg:phone":"+32 55 49 86 76",
    "sg:postcode":"9630",
    "sg:province":"Oost-Vlaanderen",
    "wof:name":"Marcel Van Oortegem",
    "wof:placetype":"venue"
},
  "geometry": {"coordinates":[3.7217640877,50.8520812988],"type":"Point"}
}