{
  "type": "Feature",
  "properties": {
    "iso:country":"BE",
    "sg:address":"Villalaan 87",
    "sg:city":"Halle",
    "sg:orig_category":"M\u00e9decins and sp\u00e9cialistes",
    "sg:phone":"+32 2 361 21 11",
    "sg:postcode":"1500",
    "sg:province":"Vlaams-Brabant",
    "wof:name":"Katia Ville",
    "wof:placetype":"venue"
},
  "geometry": {"coordinates":[4.2480587959,50.7305259705],"type":"Point"}
}