{
  "type": "Feature",
  "properties": {
    "iso:country":"BE",
    "sg:address":"Chauss\u00c9e De Louvain 89",
    "sg:city":"Wavre",
    "sg:orig_category":"M\u00e9decines alternatives",
    "sg:phone":"+32 10 24 48 35",
    "sg:postcode":"1300",
    "sg:province":"Brabant Wallon",
    "wof:name":"L. Jossen",
    "wof:placetype":"venue"
},
  "geometry": {"coordinates":[4.6157221794,50.7146186829],"type":"Point"}
}