{
  "type": "Feature",
  "properties": {
    "iso:country":"BE",
    "sg:address":"Mosselstraat 79",
    "sg:city":"Gistel",
    "sg:orig_category":"Entretien and r\u00e9parations de voitures",
    "sg:phone":"+32 59 27 89 52",
    "sg:postcode":"8470",
    "sg:province":"West-Vlaanderen",
    "wof:name":"Garage Hermy",
    "wof:placetype":"venue"
},
  "geometry": {"coordinates":[2.9791119099,51.139251709],"type":"Point"}
}