{
  "type": "Feature",
  "properties": {
    "iso:country":"BE",
    "sg:address":"Rooseveltlaan 2",
    "sg:city":"Erpe-mere (erpe)",
    "sg:classifiers":[
        {
            "category":"Retail",
            "subcategory":"Storage",
            "type":"Services"
        }
    ],
    "sg:phone":"+32 53 80 32 80",
    "sg:postcode":"9420",
    "sg:province":"Oost-Vlaanderen",
    "sg:tags":[
        "access",
        "-",
        "pigeon",
        "fancier"
    ],
    "wof:name":"Algrano",
    "wof:placetype":"venue"
},
  "geometry": {"coordinates":[3.9753301144,50.9333953857],"type":"Point"}
}