{
  "type": "Feature",
  "properties": {
    "iso:country":"BE",
    "sg:address":"Roozelaarlaan 12",
    "sg:city":"Hoeilaart",
    "sg:orig_category":"Diverse bedrijfsbeheeradviesbureaus",
    "sg:phone":"+32 2 657 05 43",
    "sg:postcode":"1560",
    "sg:province":"Vlaams-Brabant",
    "wof:name":"Equipower International",
    "wof:placetype":"venue"
},
  "geometry": {"coordinates":[4.4575858116,50.760307312],"type":"Point"}
}