{
  "type": "Feature",
  "properties": {
    "iso:country":"BE",
    "sg:address":"Oude Zandstraat 8",
    "sg:city":"Beveren (beveren-waas)",
    "sg:classifiers":[
        {
            "category":"Manufacturing",
            "subcategory":"Textiles",
            "type":"Manufacturing & Wholesale Goods"
        }
    ],
    "sg:phone":"+32 3 775 44 16",
    "sg:postcode":"9120",
    "sg:province":"Oost-Vlaanderen",
    "sg:tags":[
        "retail",
        "-"
    ],
    "wof:name":"Weekers",
    "wof:placetype":"venue"
},
  "geometry": {"coordinates":[4.2547211647,51.2125778198],"type":"Point"}
}