{
  "type": "Feature",
  "properties": {
    "iso:country":"BE",
    "sg:address":"Schaapsdreef 7",
    "sg:city":"Eeklo",
    "sg:classifiers":[
        {
            "category":"Health Services",
            "subcategory":"Nursing And Care Facility",
            "type":"Services"
        }
    ],
    "sg:phone":"+32 9 377 88 70",
    "sg:postcode":"9900",
    "sg:province":"Oost-Vlaanderen",
    "sg:tags":[
        "home"
    ],
    "wof:name":"Helslander V",
    "wof:placetype":"venue"
},
  "geometry": {"coordinates":[3.5908999443,51.1766967773],"type":"Point"}
}