{
  "type": "Feature",
  "properties": {
    "addr:full":"Avenue De La Reine 31 La Hulpe Brabant Wallon 1310",
    "addr:housenumber":"31",
    "addr:postcode":"1310",
    "addr:street":"Avenue De La Reine",
    "iso:country":"BE",
    "sg:address":"Avenue De La Reine 31",
    "sg:city":"La Hulpe",
    "sg:classifiers":[
        {
            "category":"Food & Beverages",
            "subcategory":"Groceries & Convenience Stores",
            "type":"Retail Goods"
        }
    ],
    "sg:phone":"+32 2 653 86 66",
    "sg:postcode":"1310",
    "sg:province":"Brabant Wallon",
    "sg:tags":[
        "grocer"
    ],
    "wof:name":"Le Jardin Lorrain",
    "wof:placetype":"venue"
},
  "geometry": {"coordinates":[4.4929537773,50.7447853088],"type":"Point"}
}