{
  "type": "Feature",
  "properties": {
    "iso:country":"BE",
    "sg:address":"Notelaarslaan 18",
    "sg:city":"Harelbeke",
    "sg:orig_category":"Catering and organisation de f\u00eates",
    "sg:phone":"+32 56 70 37 18",
    "sg:postcode":"8530",
    "sg:province":"West-Vlaanderen",
    "wof:name":"Johan Terryn",
    "wof:placetype":"venue"
},
  "geometry": {"coordinates":[3.3032009602,50.8409042358],"type":"Point"}
}