{
  "type": "Feature",
  "properties": {
    "addr:full":"Kerkstraat 323 Blankenberge West-Vlaanderen 8370",
    "addr:housenumber":"323",
    "addr:postcode":"8370",
    "addr:street":"Kerkstraat",
    "iso:country":"BE",
    "sg:address":"Kerkstraat 323",
    "sg:city":"Blankenberge",
    "sg:classifiers":[
        {
            "category":"Insurance",
            "subcategory":"Insurance Agent",
            "type":"Services"
        }
    ],
    "sg:phone":"+32 50 42 87 77",
    "sg:postcode":"8370",
    "sg:province":"West-Vlaanderen",
    "sg:tags":[
        "verzekeringsmakelaars",
        "expert"
    ],
    "wof:name":"Kantoor Hosten",
    "wof:placetype":"venue"
},
  "geometry": {"coordinates":[3.1395440102,51.3064308167],"type":"Point"}
}