{
  "type": "Feature",
  "properties": {
    "iso:country":"BE",
    "sg:address":"Zeger Van Heulestraat 61",
    "sg:city":"Kortrijk",
    "sg:orig_category":"Slagers",
    "sg:phone":"+32 56 35 90 08",
    "sg:postcode":"8501",
    "sg:province":"West-Vlaanderen",
    "wof:name":"Vincent Cannaert",
    "wof:placetype":"venue"
},
  "geometry": {"coordinates":[3.2389509678,50.8451652527],"type":"Point"}
}