{
  "type": "Feature",
  "properties": {
    "addr:full":"Invalidenlaan 152b1 Oudergem/auderghem Bruxelles-Capitale 1160",
    "addr:housenumber":"152b1",
    "addr:postcode":"1160",
    "addr:street":"Invalidenlaan;/",
    "iso:country":"BE",
    "sg:address":"Invalidenlaan 152b1",
    "sg:city":"Oudergem/auderghem",
    "sg:orig_category":"Artsen and specialisten",
    "sg:phone":"+32 2 660 26 32",
    "sg:postcode":"1160",
    "sg:province":"Bruxelles-Capitale",
    "wof:name":"G\u00c9rald Vandervelden",
    "wof:placetype":"venue"
},
  "geometry": {"coordinates":[4.4109950066,50.8180084229],"type":"Point"}
}