{
  "type": "Feature",
  "properties": {
    "addr:full":"Rue Evrard 22 La Louvi\u00e8re (haine-saint-paul) Hainaut 7100",
    "addr:housenumber":"22",
    "addr:postcode":"7100",
    "addr:street":"Rue Evrard",
    "iso:country":"BE",
    "sg:address":"Rue Evrard 22",
    "sg:city":"La Louvi\u00e8re (haine-saint-paul)",
    "sg:classifiers":[
        {
            "category":"Autos & Motor Vehicles",
            "subcategory":"Fuel & Gas Station",
            "type":"Retail Goods"
        }
    ],
    "sg:phone":"+32 64 22 47 64",
    "sg:postcode":"7100",
    "sg:province":"Hainaut",
    "sg:tags":[
        "repair",
        "drier",
        "laundry",
        "-",
        "machine",
        "mainten",
        "washing",
        "automatic"
    ],
    "wof:name":"Jolimont Electro",
    "wof:placetype":"venue"
},
  "geometry": {"coordinates":[4.2127699852,50.4713478088],"type":"Point"}
}