{
  "type": "Feature",
  "properties": {
    "iso:country":"BE",
    "sg:address":"Rue Du Roi Chevalier 12",
    "sg:city":"Leuze-en-hainaut",
    "sg:orig_category":"Boissons",
    "sg:phone":"+32 69 66 52 95",
    "sg:postcode":"7904",
    "sg:province":"Hainaut",
    "wof:name":"Philippe Delhaye",
    "wof:placetype":"venue"
},
  "geometry": {"coordinates":[3.5993609428,50.5650138855],"type":"Point"}
}