{
  "type": "Feature",
  "properties": {
    "iso:country":"BE",
    "sg:address":"Doornlaarstraat 59bc",
    "sg:city":"Bonheiden",
    "sg:orig_category":"Geluidsopnames",
    "sg:phone":"+32 15 51 70 07",
    "sg:postcode":"2820",
    "sg:province":"Antwerpen",
    "wof:name":"D.v.r. Recording",
    "wof:placetype":"venue"
},
  "geometry": {"coordinates":[4.6324548721,51.0157661438],"type":"Point"}
}