{
  "type": "Feature",
  "properties": {
    "addr:full":"Rue De La Baume 37 Saint-georges-sur-meuse Li\u00e8ge 4470",
    "addr:housenumber":"37",
    "addr:postcode":"4470",
    "addr:street":"Rue De La Baume",
    "iso:country":"BE",
    "sg:address":"Rue De La Baume 37",
    "sg:city":"Saint-georges-sur-meuse",
    "sg:orig_category":"M\u00e9decins and sp\u00e9cialistes",
    "sg:phone":"+32 4 275 41 53",
    "sg:postcode":"4470",
    "sg:province":"Li\u00e8ge",
    "wof:name":"Carine Lupica",
    "wof:placetype":"venue"
},
  "geometry": {"coordinates":[5.3617339134,50.5759315491],"type":"Point"}
}