{
  "type": "Feature",
  "properties": {
    "iso:country":"BE",
    "sg:address":"391",
    "sg:city":"Avenue Louise 1050 Bruxelles",
    "sg:classifiers":[
        {
            "category":"Professional",
            "subcategory":"Advertising",
            "type":"Services"
        }
    ],
    "sg:phone":"+32 2 650 09 70",
    "sg:postcode":"391",
    "sg:tags":[
        "marketing",
        "medium",
        "communication"
    ],
    "wof:name":"Airinc Europe",
    "wof:placetype":"venue"
},
  "geometry": {"coordinates":[4.3568549156,50.8340911865],"type":"Point"}
}