{
  "type": "Feature",
  "properties": {
    "iso:country":"BE",
    "sg:address":"Chauss\u00c9e De Namur 109",
    "sg:city":"Gembloux",
    "sg:orig_category":"Installatie van houten of kunststof schrijnwerk Installatie van metalen schrijnwerk",
    "sg:phone":"+32 81 60 03 91",
    "sg:postcode":"5030",
    "sg:province":"Namur",
    "wof:name":"S.t.s.",
    "wof:placetype":"venue"
},
  "geometry": {"coordinates":[4.7087030411,50.5530014038],"type":"Point"}
}