{
  "type": "Feature",
  "properties": {
    "iso:country":"BE",
    "sg:address":"Molenstraat 100",
    "sg:city":"Genk",
    "sg:orig_category":"Meubles D\u00e9taillants, Am\u00e9nagement de B\u00e2timents et de Cuisines",
    "sg:phone":"+32 89 35 52 20",
    "sg:postcode":"3600",
    "sg:province":"Limburg",
    "wof:name":"Johanna Luykx",
    "wof:placetype":"venue"
},
  "geometry": {"coordinates":[5.5143260956,50.9639778137],"type":"Point"}
}