{
  "type": "Feature",
  "properties": {
    "iso:country":"BE",
    "sg:address":"Rue De Goz\u00c9e 706",
    "sg:city":"Montigny-le-tilleul",
    "sg:orig_category":"M\u00e9decins and sp\u00e9cialistes. Cliniques and h\u00f4pitaux. Blanchisseries and teintureries",
    "sg:phone":"+32 71 92 15 11",
    "sg:postcode":"6110",
    "sg:province":"Hainaut",
    "wof:name":"C.h.u Andr\u00c9 Vesale",
    "wof:placetype":"venue"
},
  "geometry": {"coordinates":[4.3695549965,50.3596229553],"type":"Point"}
}