{
  "type": "Feature",
  "properties": {
    "iso:country":"BE",
    "sg:address":"Rue Du Moulin 18",
    "sg:city":"Genappe (ways)",
    "sg:classifiers":[
        {
            "category":"Manufacturing",
            "subcategory":"Metals",
            "type":"Manufacturing & Wholesale Goods"
        }
    ],
    "sg:phone":"+32 10 41 54 51",
    "sg:postcode":"1474",
    "sg:province":"Brabant Wallon",
    "sg:tags":[
        "ornamental",
        "work",
        "-"
    ],
    "wof:name":"Legrand-delaunay (ateliers)",
    "wof:placetype":"venue"
},
  "geometry": {"coordinates":[4.4630827904,50.6126594543],"type":"Point"}
}