{
  "type": "Feature",
  "properties": {
    "addr:full":"Rue Du M\u00c9ridien 86ba Sint-joost-ten-node/saint-josse-ten-noode Bruxelles-Capitale 1210",
    "addr:housenumber":"86ba",
    "addr:postcode":"1210",
    "addr:street":"Rue Du Me\u0301Ridien",
    "iso:country":"BE",
    "sg:address":"Rue Du M\u00c9ridien 86ba",
    "sg:city":"Sint-joost-ten-node/saint-josse-ten-noode",
    "sg:orig_category":"Assurances. Cr\u00e9dit \u00e0 la consommation",
    "sg:phone":"+32 2 217 79 77",
    "sg:postcode":"1210",
    "sg:province":"Bruxelles-Capitale",
    "wof:name":"Deniz Assurance",
    "wof:placetype":"venue"
},
  "geometry": {"coordinates":[4.3690910339,50.8557624817],"type":"Point"}
}