{
  "type": "Feature",
  "properties": {
    "iso:country":"BE",
    "sg:address":"Hoogstraat 73",
    "sg:city":"Putte",
    "sg:classifiers":[
        {
            "category":"Restaurant",
            "type":"Food & Drink"
        }
    ],
    "sg:phone":"+32 15 75 81 83",
    "sg:postcode":"2580",
    "sg:province":"Antwerpen",
    "wof:name":"Restaurant Saigon",
    "wof:placetype":"venue"
},
  "geometry": {"coordinates":[4.6666250229,51.0579414368],"type":"Point"}
}