{
  "type": "Feature",
  "properties": {
    "addr:full":"Handelsstraat 124 Box 1 Londerzeel (malderen) Vlaams-Brabant 1840",
    "addr:housenumber":"124;1",
    "addr:postcode":"1840",
    "addr:street":"Handelsstraat;Box",
    "iso:country":"BE",
    "sg:address":"Handelsstraat 124 Box 1",
    "sg:city":"Londerzeel (malderen)",
    "sg:classifiers":[
        {
            "category":"Professional",
            "subcategory":"Engineering",
            "type":"Services"
        }
    ],
    "sg:phone":"+32 52 33 50 87",
    "sg:postcode":"1840",
    "sg:province":"Vlaams-Brabant",
    "sg:tags":[
        "workshop"
    ],
    "wof:name":"Debolas Bvba",
    "wof:placetype":"venue"
},
  "geometry": {"coordinates":[4.2312979698,51.0150146484],"type":"Point"}
}