{
  "type": "Feature",
  "properties": {
    "addr:full":"Brusselsesteenweg 128 Zemst Vlaams-Brabant 1980",
    "addr:housenumber":"128",
    "addr:postcode":"1980",
    "addr:street":"Brusselsesteenweg;Vlaams-Brabant",
    "iso:country":"BE",
    "sg:address":"Brusselsesteenweg 128",
    "sg:city":"Zemst",
    "sg:orig_category":"Cr\u00e9dits divers",
    "sg:postcode":"1980",
    "sg:province":"Vlaams-Brabant",
    "wof:name":"Bancontact-mister Cash",
    "wof:placetype":"venue"
},
  "geometry": {"coordinates":[4.4635190964,50.9845046997],"type":"Point"}
}