{
  "type": "Feature",
  "properties": {
    "iso:country":"BE",
    "sg:address":"Zijp 142",
    "sg:city":"Wemmel",
    "sg:orig_category":"Elektrische installaties voor woningen",
    "sg:phone":"+32 2 269 95 54",
    "sg:postcode":"1780",
    "sg:province":"Vlaams-Brabant",
    "wof:name":"Pascal Leblois",
    "wof:placetype":"venue"
},
  "geometry": {"coordinates":[4.3274002075,50.9169311523],"type":"Point"}
}