{
  "type": "Feature",
  "properties": {
    "iso:country":"BE",
    "sg:address":"Rue Pepin 22",
    "sg:city":"Namur",
    "sg:orig_category":"Overheidsdiensten",
    "sg:phone":"+32 81 23 16 66",
    "sg:postcode":"5000",
    "sg:province":"Namur",
    "wof:name":"Admin. Contrib. Directes",
    "wof:placetype":"venue"
},
  "geometry": {"coordinates":[4.8685770035,50.4654121399],"type":"Point"}
}