{
  "type": "Feature",
  "properties": {
    "iso:country":"BE",
    "sg:address":"Rue Thomas Vin\u00c7otte 57",
    "sg:city":"Schaarbeek/schaerbeek",
    "sg:orig_category":"Epiceries. Alimentation sp\u00e9cialis\u00e9e",
    "sg:phone":"+32 2 732 44 80",
    "sg:postcode":"1030",
    "sg:province":"Bruxelles-Capitale",
    "wof:name":"Sene",
    "wof:placetype":"venue"
},
  "geometry": {"coordinates":[4.3831090927,50.8523635864],"type":"Point"}
}