{
  "type": "Feature",
  "properties": {
    "addr:full":"Lierse Steenweg 114 Grobbendonk Antwerpen 2280",
    "addr:housenumber":"114",
    "addr:postcode":"2280",
    "addr:street":"Lierse Steenweg",
    "iso:country":"BE",
    "sg:address":"Lierse Steenweg 114",
    "sg:city":"Grobbendonk",
    "sg:orig_category":"Etablissements Erotiques",
    "sg:phone":"+32 14 51 56 60",
    "sg:postcode":"2280",
    "sg:province":"Antwerpen",
    "wof:name":"Tamido",
    "wof:placetype":"venue"
},
  "geometry": {"coordinates":[4.7114257812,51.1659851074],"type":"Point"}
}