{
  "type": "Feature",
  "properties": {
    "addr:full":"Generaal Jacqueslaan 20b31 Elsene/ixelles Bruxelles-Capitale 1050",
    "addr:housenumber":"20b31",
    "addr:postcode":"1050",
    "addr:street":"Generaal Jacqueslaan",
    "iso:country":"BE",
    "sg:address":"Generaal Jacqueslaan 20b31",
    "sg:city":"Elsene/ixelles",
    "sg:orig_category":"Advocaten and juridische adviseurs",
    "sg:phone":"+32 2 648 61 46",
    "sg:postcode":"1050",
    "sg:province":"Bruxelles-Capitale",
    "wof:name":"P. Fran\u00c7ois",
    "wof:placetype":"venue"
},
  "geometry": {"coordinates":[4.3779740334,50.8170433044],"type":"Point"}
}