{
  "type": "Feature",
  "properties": {
    "addr:full":"Stationsstraat 159 Waregem West-Vlaanderen 8790",
    "addr:housenumber":"159",
    "addr:postcode":"8790",
    "addr:street":"Stationsstraat",
    "iso:country":"BE",
    "sg:address":"Stationsstraat 159",
    "sg:city":"Waregem",
    "sg:orig_category":"HERSTELLING ELEKTRISCHE HUISHOUDAPPARATEN Herstelling aan huis van elektrische huishoudapparaten Hui",
    "sg:phone":"+32 56 60 17 84",
    "sg:postcode":"8790",
    "sg:province":"West-Vlaanderen",
    "wof:name":"Sona-meuleman",
    "wof:placetype":"venue"
},
  "geometry": {"coordinates":[3.4274120331,50.8916473389],"type":"Point"}
}