{
  "type": "Feature",
  "properties": {
    "iso:country":"BE",
    "sg:address":"Vichtesteenweg 65",
    "sg:city":"Deerlijk",
    "sg:orig_category":"Rundveehouders",
    "sg:phone":"+32 56 77 79 22",
    "sg:postcode":"8540",
    "sg:province":"West-Vlaanderen",
    "wof:name":"Mark Vandamme",
    "wof:placetype":"venue"
},
  "geometry": {"coordinates":[3.3672890663,50.8505134583],"type":"Point"}
}