{
  "type": "Feature",
  "properties": {
    "iso:country":"BE",
    "sg:address":"Rue De La Maitrise 9",
    "sg:city":"Nivelles",
    "sg:classifiers":[
        {
            "category":"Shopping",
            "subcategory":"Computers & Home Electronics",
            "type":"Retail Goods"
        }
    ],
    "sg:phone":"+32 67 88 82 50",
    "sg:postcode":"1400",
    "sg:province":"Brabant Wallon",
    "sg:tags":[
        "equipment",
        "-"
    ],
    "wof:name":"Trump Sprl",
    "wof:placetype":"venue"
},
  "geometry": {"coordinates":[4.3223419189,50.5976524353],"type":"Point"}
}