{
  "type": "Feature",
  "properties": {
    "addr:full":"Kleine Heimelinkstraat 2 Sint-niklaas Oost-Vlaanderen 9100",
    "addr:housenumber":"2",
    "addr:postcode":"9100",
    "addr:street":"Heimelinkstraat",
    "iso:country":"BE",
    "sg:address":"Kleine Heimelinkstraat 2",
    "sg:city":"Sint-niklaas",
    "sg:classifiers":[
        {
            "category":"Bars & Pubs",
            "type":"Food & Drink"
        }
    ],
    "sg:phone":"+32 3 765 02 80",
    "sg:postcode":"9100",
    "sg:province":"Oost-Vlaanderen",
    "wof:name":"Kleine Star",
    "wof:placetype":"venue"
},
  "geometry": {"coordinates":[4.1654047966,51.1724128723],"type":"Point"}
}