{
  "type": "Feature",
  "properties": {
    "addr:full":"Tessenderlosesteenweg 18 Beringen Limburg 3583",
    "addr:housenumber":"18",
    "addr:postcode":"3583",
    "addr:street":"Tessenderlosesteenweg",
    "iso:country":"BE",
    "sg:address":"Tessenderlosesteenweg 18",
    "sg:city":"Beringen",
    "sg:orig_category":"Salles de spectacles",
    "sg:phone":"+32 11 42 80 68",
    "sg:postcode":"3583",
    "sg:province":"Limburg",
    "wof:name":"Ontmoet.centr. De Buiting",
    "wof:placetype":"venue"
},
  "geometry": {"coordinates":[5.1706700325,51.0389442444],"type":"Point"}
}