{
  "type": "Feature",
  "properties": {
    "addr:full":"Kauterhof 16 Hoegaarden Vlaams-Brabant 3320",
    "addr:housenumber":"16",
    "addr:postcode":"3320",
    "addr:street":"Kauterhof",
    "iso:country":"BE",
    "sg:address":"Kauterhof 16",
    "sg:city":"Hoegaarden",
    "sg:classifiers":[
        {
            "category":"Banks & Credit Unions",
            "subcategory":"Investment Brokerage",
            "type":"Services"
        }
    ],
    "sg:phone":"+32 475 39 41 76",
    "sg:postcode":"3320",
    "sg:province":"Vlaams-Brabant",
    "wof:name":"Vlayen J",
    "wof:placetype":"venue"
},
  "geometry": {"coordinates":[4.8725099564,50.7787628174],"type":"Point"}
}