{
  "type": "Feature",
  "properties": {
    "addr:full":"Aartrijksestraat 92 Zedelgem (aartrijke) West-Vlaanderen 8211",
    "addr:housenumber":"92",
    "addr:postcode":"8211",
    "addr:street":"Aartrijksestraat",
    "iso:country":"BE",
    "sg:address":"Aartrijksestraat 92",
    "sg:city":"Zedelgem (aartrijke)",
    "sg:classifiers":[
        {
            "category":"Retail",
            "subcategory":"Auto Repair",
            "type":"Services"
        }
    ],
    "sg:phone":"+32 50 20 93 61",
    "sg:postcode":"8211",
    "sg:province":"West-Vlaanderen",
    "sg:tags":[
        "automobile-body"
    ],
    "wof:name":"Vanheste Gebr",
    "wof:placetype":"venue"
},
  "geometry": {"coordinates":[3.0889649391,51.1200408936],"type":"Point"}
}