{
  "type": "Feature",
  "properties": {
    "addr:full":"Molenstraat 19 Eeklo Oost-Vlaanderen 9900",
    "addr:housenumber":"19",
    "addr:postcode":"9900",
    "addr:street":"Molenstraat",
    "iso:country":"BE",
    "sg:address":"Molenstraat 19",
    "sg:city":"Eeklo",
    "sg:classifiers":[
        {
            "category":"Personal",
            "subcategory":"Beauty Salon",
            "type":"Services"
        }
    ],
    "sg:phone":"+32 9 378 58 09",
    "sg:postcode":"9900",
    "sg:province":"Oost-Vlaanderen",
    "sg:tags":[
        "lady",
        "-",
        "hairdressing"
    ],
    "wof:name":"Attitude (salon)",
    "wof:placetype":"venue"
},
  "geometry": {"coordinates":[3.562928915,51.1856575012],"type":"Point"}
}