{
  "type": "Feature",
  "properties": {
    "addr:full":"Brechtseweg 206 Wuustwezel Antwerpen 2990",
    "addr:housenumber":"206",
    "addr:postcode":"2990",
    "addr:street":"Brechtseweg",
    "iso:country":"BE",
    "sg:address":"Brechtseweg 206",
    "sg:city":"Wuustwezel",
    "sg:orig_category":"Varkenskwekers",
    "sg:phone":"+32 3 313 08 73",
    "sg:postcode":"2990",
    "sg:province":"Antwerpen",
    "wof:name":"Marc Vermeiren",
    "wof:placetype":"venue"
},
  "geometry": {"coordinates":[4.6449341774,51.3769645691],"type":"Point"}
}