{
  "type": "Feature",
  "properties": {
    "iso:country":"BE",
    "sg:address":"Avenue De Tervueren 55",
    "sg:city":"Etterbeek/etterbeek",
    "sg:orig_category":"Avocats and conseillers juridiques",
    "sg:phone":"+32 2 736 40 90",
    "sg:postcode":"1040",
    "sg:province":"Bruxelles-Capitale",
    "wof:name":"A. Freville",
    "wof:placetype":"venue"
},
  "geometry": {"coordinates":[4.4014601707,50.8383178711],"type":"Point"}
}