{
  "type": "Feature",
  "properties": {
    "addr:full":"Antwerpsestraat 247 Niel Antwerpen 2845",
    "addr:housenumber":"247",
    "addr:postcode":"2845",
    "addr:street":"Antwerpsestraat",
    "iso:country":"BE",
    "sg:address":"Antwerpsestraat 247",
    "sg:city":"Niel",
    "sg:classifiers":[
        {
            "category":"Insurance",
            "subcategory":"Life Insurance",
            "type":"Services"
        }
    ],
    "sg:phone":"+32 3 888 59 06",
    "sg:postcode":"2845",
    "sg:province":"Antwerpen",
    "sg:tags":[
        "assurance"
    ],
    "wof:name":"Van Den Neucker",
    "wof:placetype":"venue"
},
  "geometry": {"coordinates":[4.3307080269,51.1135177612],"type":"Point"}
}