{
  "type": "Feature",
  "properties": {
    "iso:country":"BE",
    "sg:address":"Korte Kamstraat 13",
    "sg:city":"Roosdaal",
    "sg:classifiers":[
        {
            "category":"Professional",
            "subcategory":"Art Services",
            "type":"Services"
        }
    ],
    "sg:phone":"+32 54 32 12 45",
    "sg:postcode":"1760",
    "sg:province":"Vlaams-Brabant",
    "sg:tags":[
        "photographer"
    ],
    "wof:name":"Foto Nathalie",
    "wof:placetype":"venue"
},
  "geometry": {"coordinates":[4.0914340019,50.8413467407],"type":"Point"}
}