{
  "type": "Feature",
  "properties": {
    "addr:full":"Stuivenbergvaart 17 Mechelen Antwerpen 2800",
    "addr:housenumber":"17",
    "addr:postcode":"2800",
    "addr:street":"Stuivenbergvaart",
    "iso:country":"BE",
    "sg:address":"Stuivenbergvaart 17",
    "sg:city":"Mechelen",
    "sg:classifiers":[
        {
            "category":"Real Estate",
            "subcategory":"Architect",
            "type":"Services"
        }
    ],
    "sg:phone":"+32 15 41 95 41",
    "sg:postcode":"2800",
    "sg:province":"Antwerpen",
    "wof:name":"Van Cutsem G",
    "wof:placetype":"venue"
},
  "geometry": {"coordinates":[4.4704041481,51.0215072632],"type":"Point"}
}