{
  "type": "Feature",
  "properties": {
    "addr:full":"Oudburg 42 Gent Oost-Vlaanderen 9000",
    "addr:housenumber":"42",
    "addr:postcode":"9000",
    "addr:street":"Oudburg;Oost-Vlaanderen",
    "iso:country":"BE",
    "sg:address":"Oudburg 42",
    "sg:city":"Gent",
    "sg:classifiers":[
        {
            "category":"Restaurant",
            "type":"Food & Drink"
        }
    ],
    "sg:phone":"+32 9 225 78 18",
    "sg:postcode":"9000",
    "sg:province":"Oost-Vlaanderen",
    "wof:name":"Restaurant Ankara",
    "wof:placetype":"venue"
},
  "geometry": {"coordinates":[3.7243750095,51.0583343506],"type":"Point"}
}