{
  "type": "Feature",
  "properties": {
    "addr:full":"Scheewege 19 Damme (moerkerke) West-Vlaanderen 8340",
    "addr:housenumber":"19",
    "addr:postcode":"8340",
    "addr:street":"Scheewege",
    "iso:country":"BE",
    "sg:address":"Scheewege 19",
    "sg:city":"Damme (moerkerke)",
    "sg:orig_category":"Non-Classified Establishments",
    "sg:phone":"+32 50 50 04 43",
    "sg:postcode":"8340",
    "sg:province":"West-Vlaanderen",
    "wof:name":"De Zwaef Bvba",
    "wof:placetype":"venue"
},
  "geometry": {"coordinates":[3.2815999985,51.2513160706],"type":"Point"}
}