{
  "type": "Feature",
  "properties": {
    "addr:full":"Pikkeleerstraat 16 Herk-de-stad Limburg 3540",
    "addr:housenumber":"16",
    "addr:postcode":"3540",
    "addr:street":"Pikkeleerstraat",
    "iso:country":"BE",
    "sg:address":"Pikkeleerstraat 16",
    "sg:city":"Herk-de-stad",
    "sg:classifiers":[
        {
            "category":"Restaurant",
            "type":"Food & Drink"
        }
    ],
    "sg:phone":"+32 13 55 39 19",
    "sg:postcode":"3540",
    "sg:province":"Limburg",
    "sg:tags":[
        "caf\u00e9s"
    ],
    "wof:name":"Taverne Olmenhof",
    "wof:placetype":"venue"
},
  "geometry": {"coordinates":[5.1661291122,50.9360198975],"type":"Point"}
}