{
  "type": "Feature",
  "properties": {
    "addr:full":"Groenlandstraat 17 Brugge (zeebrugge - Lissewege) West-Vlaanderen 8380",
    "addr:housenumber":"17",
    "addr:postcode":"8380",
    "addr:street":"Groenlandstraat",
    "iso:country":"BE",
    "sg:address":"Groenlandstraat 17",
    "sg:city":"Brugge (zeebrugge - Lissewege)",
    "sg:classifiers":[
        {
            "category":"Wholesale",
            "subcategory":"Seafood",
            "type":"Manufacturing & Wholesale Goods"
        }
    ],
    "sg:phone":"+32 50 55 75 30",
    "sg:postcode":"8380",
    "sg:province":"West-Vlaanderen",
    "sg:tags":[
        "whol",
        "fish",
        "-",
        "shellfish"
    ],
    "wof:name":"Andre Zeevisgroothandel Nv",
    "wof:placetype":"venue"
},
  "geometry": {"coordinates":[3.2288448811,51.2742958069],"type":"Point"}
}