{
  "type": "Feature",
  "properties": {
    "addr:full":"Chauss\u00c9e De Mons 39ba Chimay Hainaut 6460",
    "addr:housenumber":"39ba",
    "addr:postcode":"6460",
    "addr:street":"Chausse\u0301E De Mons",
    "iso:country":"BE",
    "sg:address":"Chauss\u00c9e De Mons 39ba",
    "sg:city":"Chimay",
    "sg:orig_category":"Eleveurs de bovins",
    "sg:phone":"+32 60 21 26 69",
    "sg:postcode":"6460",
    "sg:province":"Hainaut",
    "wof:name":"Guy Devaux",
    "wof:placetype":"venue"
},
  "geometry": {"coordinates":[4.3052358627,50.0574836731],"type":"Point"}
}