{
  "type": "Feature",
  "properties": {
    "addr:full":"Butswervestraat 19 Maldegem Oost-Vlaanderen 9990",
    "addr:housenumber":"19",
    "addr:postcode":"9990",
    "addr:street":"Butswervestraat",
    "iso:country":"BE",
    "sg:address":"Butswervestraat 19",
    "sg:city":"Maldegem",
    "sg:orig_category":"Eleveurs de bovins",
    "sg:phone":"+32 50 71 15 34",
    "sg:postcode":"9990",
    "sg:province":"Oost-Vlaanderen",
    "wof:name":"Daniel De Backer",
    "wof:placetype":"venue"
},
  "geometry": {"coordinates":[3.4062969685,51.212436676],"type":"Point"}
}