{
  "type": "Feature",
  "properties": {
    "iso:country":"BE",
    "sg:address":"Charles Woestelaan 201",
    "sg:city":"Jette",
    "sg:orig_category":"Alternatieve geneeskunde Artsen and specialisten",
    "sg:phone":"+32 2 428 03 70",
    "sg:postcode":"1090",
    "sg:province":"Bruxelles-Capitale",
    "wof:name":"Wuyts Daniel",
    "wof:placetype":"venue"
},
  "geometry": {"coordinates":[4.3340101242,50.8721656799],"type":"Point"}
}