{
  "type": "Feature",
  "properties": {
    "addr:full":"Rue De Rolleghem 195 Mouscron Hainaut 7700",
    "addr:housenumber":"195",
    "addr:postcode":"7700",
    "addr:street":"Rue De Rolleghem",
    "iso:country":"BE",
    "sg:address":"Rue De Rolleghem 195",
    "sg:city":"Mouscron",
    "sg:orig_category":"Solar protection - Outside",
    "sg:postcode":"7700",
    "sg:province":"Hainaut",
    "wof:name":"Damco Zonwering",
    "wof:placetype":"venue"
},
  "geometry": {"coordinates":[5.3300299644,51.3227386475],"type":"Point"}
}