{
  "type": "Feature",
  "properties": {
    "addr:full":"Rue De L'am\u00c9rique 79 Ham-sur-heure-nalinnes Hainaut 6120",
    "addr:housenumber":"79",
    "addr:postcode":"6120",
    "addr:street":"Rue De L'Ame \u0301Rique;Hainaut",
    "iso:country":"BE",
    "sg:address":"Rue De L'am\u00c9rique 79",
    "sg:city":"Ham-sur-heure-nalinnes",
    "sg:orig_category":"Sportclubs",
    "sg:phone":"+32 71 21 35 29",
    "sg:postcode":"6120",
    "sg:province":"Hainaut",
    "wof:name":"D'estoc Et De Taille",
    "wof:placetype":"venue"
},
  "geometry": {"coordinates":[4.3993740082,50.3382377625],"type":"Point"}
}