{
  "type": "Feature",
  "properties": {
    "iso:country":"BE",
    "sg:address":"Goor 69",
    "sg:city":"Kasterlee",
    "sg:classifiers":[
        {
            "category":"Insurance",
            "subcategory":"Insurance Agent",
            "type":"Services"
        }
    ],
    "sg:phone":"+32 14 85 24 63",
    "sg:postcode":"2460",
    "sg:province":"Antwerpen",
    "sg:tags":[
        "verzekeringsmakelaars",
        "expert"
    ],
    "wof:name":"Paulussen",
    "wof:placetype":"venue"
},
  "geometry": {"coordinates":[4.9482059479,51.2210540771],"type":"Point"}
}