{
  "type": "Feature",
  "properties": {
    "addr:full":"Val Villers 74 Chaumont-gistoux Brabant Wallon 1325",
    "addr:housenumber":"74",
    "addr:postcode":"1325",
    "addr:street":"Val Villers",
    "iso:country":"BE",
    "sg:address":"Val Villers 74",
    "sg:city":"Chaumont-gistoux",
    "sg:orig_category":"Installation \u00e9lectrique r\u00e9sidentielle",
    "sg:phone":"+32 10 22 73 14",
    "sg:postcode":"1325",
    "sg:province":"Brabant Wallon",
    "wof:name":"Daniel Derck",
    "wof:placetype":"venue"
},
  "geometry": {"coordinates":[4.6336450577,50.6870803833],"type":"Point"}
}