{
  "type": "Feature",
  "properties": {
    "iso:country":"BE",
    "sg:address":"Quai Aux Hu\u00eetres 8",
    "sg:city":"Wavre",
    "sg:classifiers":[
        {
            "category":"Shopping",
            "subcategory":"Jewelry",
            "type":"Retail Goods"
        }
    ],
    "sg:phone":"+32 10 24 80 87",
    "sg:postcode":"1300",
    "sg:province":"Brabant Wallon",
    "sg:tags":[
        "-",
        "imitation"
    ],
    "wof:name":"Christ'art Creation",
    "wof:placetype":"venue"
},
  "geometry": {"coordinates":[4.6110677719,50.7149391174],"type":"Point"}
}