{
  "type": "Feature",
  "properties": {
    "iso:country":"BE",
    "sg:address":"Place De L'h\u00f4tel De Ville 5",
    "sg:city":"Gembloux-sur-orneau (gembloux)",
    "sg:classifiers":[
        {
            "category":"Deli",
            "type":"Food & Drink"
        }
    ],
    "sg:phone":"+32 81 61 51 58",
    "sg:postcode":"5030",
    "sg:province":"Namur",
    "sg:tags":[
        "delicatessen"
    ],
    "wof:name":"Caprices Et Tentations",
    "wof:placetype":"venue"
},
  "geometry": {"coordinates":[4.6945400238,50.5666313171],"type":"Point"}
}