{
  "type": "Feature",
  "properties": {
    "addr:full":"Leopoldstraat 26 Bornem Antwerpen 2880",
    "addr:housenumber":"26",
    "addr:postcode":"2880",
    "addr:street":"Leopoldstraat",
    "iso:country":"BE",
    "sg:address":"Leopoldstraat 26",
    "sg:city":"Bornem",
    "sg:orig_category":"HUISBRANDOLIE",
    "sg:phone":"+32 3 889 03 44",
    "sg:postcode":"2880",
    "sg:province":"Antwerpen",
    "wof:name":"Maes",
    "wof:placetype":"venue"
},
  "geometry": {"coordinates":[4.242205143,51.0998497009],"type":"Point"}
}