{
  "type": "Feature",
  "properties": {
    "addr:full":"Wafelstraat 48 Zwalm Oost-Vlaanderen 9630",
    "addr:housenumber":"48",
    "addr:postcode":"9630",
    "addr:street":"Wafelstraat;Oost-Vlaanderen",
    "iso:country":"BE",
    "sg:address":"Wafelstraat 48",
    "sg:city":"Zwalm",
    "sg:orig_category":"Varkenskwekers",
    "sg:phone":"+32 55 49 78 44",
    "sg:postcode":"9630",
    "sg:province":"Oost-Vlaanderen",
    "wof:name":"Geert Polet",
    "wof:placetype":"venue"
},
  "geometry": {"coordinates":[3.7166891098,50.8814315796],"type":"Point"}
}