{
  "type": "Feature",
  "properties": {
    "iso:country":"BE",
    "sg:address":"Rue Du Ch\u00c2teau 9",
    "sg:city":"Brunehaut",
    "sg:orig_category":"Dansscholen",
    "sg:phone":"+32 69 34 58 97",
    "sg:postcode":"7621",
    "sg:province":"Hainaut",
    "wof:name":"Val\u00c9rie Schepens",
    "wof:placetype":"venue"
},
  "geometry": {"coordinates":[3.3876550198,50.5201873779],"type":"Point"}
}