{
  "type": "Feature",
  "properties": {
    "addr:full":"Witte Kaproenenstraat 27 Deinze Oost-Vlaanderen 9800",
    "addr:housenumber":"27",
    "addr:postcode":"9800",
    "addr:street":"Witte Kaproenenstraat",
    "iso:country":"BE",
    "sg:address":"Witte Kaproenenstraat 27",
    "sg:city":"Deinze",
    "sg:orig_category":"D\u00e9corateurs d'int\u00e9rieur",
    "sg:phone":"+32 9 386 31 26",
    "sg:postcode":"9800",
    "sg:province":"Oost-Vlaanderen",
    "wof:name":"Davy Van Damme",
    "wof:placetype":"venue"
},
  "geometry": {"coordinates":[3.5437180996,50.9870834351],"type":"Point"}
}