{
  "type": "Feature",
  "properties": {
    "iso:country":"BE",
    "sg:address":"Jozef Buyssestraat 39",
    "sg:city":"Wetteren",
    "sg:classifiers":[
        {
            "category":"Health Services",
            "subcategory":"Health Practitioner",
            "type":"Services"
        }
    ],
    "sg:phone":"+32 9 369 76 77",
    "sg:postcode":"9230",
    "sg:province":"Oost-Vlaanderen",
    "sg:tags":[
        "physiotherapist"
    ],
    "wof:name":"De Wilde D",
    "wof:placetype":"venue"
},
  "geometry": {"coordinates":[3.8879001141,51.0038757324],"type":"Point"}
}