{
  "type": "Feature",
  "properties": {
    "addr:full":"Zoutstraat 46 Sint-truiden Limburg 3800",
    "addr:housenumber":"46",
    "addr:postcode":"3800",
    "addr:street":"Zoutstraat",
    "iso:country":"BE",
    "sg:address":"Zoutstraat 46",
    "sg:city":"Sint-truiden",
    "sg:classifiers":[
        {
            "category":"Education",
            "subcategory":"School",
            "type":"Public Place"
        }
    ],
    "sg:phone":"+32 11 69 89 23",
    "sg:postcode":"3800",
    "sg:province":"Limburg",
    "sg:tags":[
        "-",
        "private"
    ],
    "wof:name":"Naschooltijd Leren",
    "wof:placetype":"venue"
},
  "geometry": {"coordinates":[5.1825041771,50.8169517517],"type":"Point"}
}