{
  "type": "Feature",
  "properties": {
    "addr:full":"Chauss\u00c9e De Vleurgat 102b7 Elsene/ixelles Bruxelles-Capitale 1050",
    "addr:housenumber":"102b7",
    "addr:postcode":"1050",
    "addr:street":"Chausse\u0301E De Vleurgat",
    "iso:country":"BE",
    "sg:address":"Chauss\u00c9e De Vleurgat 102b7",
    "sg:city":"Elsene/ixelles",
    "sg:orig_category":"Agences immobili\u00e8res",
    "sg:phone":"+32 2 648 00 08",
    "sg:postcode":"1050",
    "sg:province":"Bruxelles-Capitale",
    "wof:name":"Jean-claude Donies",
    "wof:placetype":"venue"
},
  "geometry": {"coordinates":[4.3687858582,50.8245506287],"type":"Point"}
}