{
  "type": "Feature",
  "properties": {
    "iso:country":"BE",
    "sg:address":"Kapelstraat 18",
    "sg:city":"Beerse",
    "sg:classifiers":[
        {
            "category":"Insurance",
            "subcategory":"Life Insurance",
            "type":"Services"
        }
    ],
    "sg:phone":"+32 14 61 61 03",
    "sg:postcode":"2340",
    "sg:province":"Antwerpen",
    "sg:tags":[
        "assurance"
    ],
    "wof:name":"G. Walbers",
    "wof:placetype":"venue"
},
  "geometry": {"coordinates":[4.8474721909,51.3192825317],"type":"Point"}
}