{
  "type": "Feature",
  "properties": {
    "iso:country":"BE",
    "sg:address":"Sint-paulusstraat 14b",
    "sg:city":"Retie",
    "sg:classifiers":[
        {
            "category":"Autos & Motor Vehicles",
            "subcategory":"Recreational Vehicle Sales",
            "type":"Retail Goods"
        }
    ],
    "sg:phone":"+32 14 37 99 59",
    "sg:postcode":"2470",
    "sg:province":"Antwerpen",
    "sg:tags":[
        "saw"
    ],
    "wof:name":"Van De Perre Wim-janssens Bvba",
    "wof:placetype":"venue"
},
  "geometry": {"coordinates":[5.0782718658,51.2631187439],"type":"Point"}
}