{
  "type": "Feature",
  "properties": {
    "iso:country":"BE",
    "sg:address":"Rue Charlemagne 62",
    "sg:city":"Herstal",
    "sg:classifiers":[
        {
            "category":"Arena",
            "subcategory":"Sports Club",
            "type":"Entertainment"
        }
    ],
    "sg:phone":"+32 4 240 33 98",
    "sg:postcode":"4040",
    "sg:province":"Li\u00e8ge",
    "sg:tags":[
        "de"
    ],
    "wof:name":"Les Armuriers Herstaliens",
    "wof:placetype":"venue"
},
  "geometry": {"coordinates":[5.6111068726,50.6689071655],"type":"Point"}
}