{
  "type": "Feature",
  "properties": {
    "iso:country":"BE",
    "sg:address":"Oudenaardsesteenweg 14",
    "sg:city":"Kortrijk",
    "sg:orig_category":"Artsen and specialisten",
    "sg:phone":"+32 56 20 19 55",
    "sg:postcode":"8500",
    "sg:province":"West-Vlaanderen",
    "wof:name":"J. Delanote",
    "wof:placetype":"venue"
},
  "geometry": {"coordinates":[3.2789049149,50.8219833374],"type":"Point"}
}