{
  "type": "Feature",
  "properties": {
    "iso:country":"BE",
    "sg:address":"Lispersteenweg 58",
    "sg:city":"Boechout",
    "sg:orig_category":"Sportclubs",
    "sg:phone":"+32 3 455 65 21",
    "sg:postcode":"2530",
    "sg:province":"Antwerpen",
    "wof:name":"T.c. Racing Kiel",
    "wof:placetype":"venue"
},
  "geometry": {"coordinates":[4.5181360245,51.1607971191],"type":"Point"}
}