{
  "type": "Feature",
  "properties": {
    "addr:full":"Rue De Tongres 17 Awans (oth\u00e9e) Li\u00e8ge 4340",
    "addr:housenumber":"17",
    "addr:postcode":"4340",
    "addr:street":"Rue De Tongres;Othe\u0301E",
    "iso:country":"BE",
    "sg:address":"Rue De Tongres 17",
    "sg:city":"Awans (oth\u00e9e)",
    "sg:classifiers":[
        {
            "category":"Health Services",
            "subcategory":"Health Practitioner",
            "type":"Services"
        }
    ],
    "sg:phone":"+32 4 257 55 85",
    "sg:postcode":"4340",
    "sg:province":"Li\u00e8ge",
    "sg:tags":[
        "physiotherapist"
    ],
    "wof:name":"Dumont Philippe",
    "wof:placetype":"venue"
},
  "geometry": {"coordinates":[5.4721131325,50.7203941345],"type":"Point"}
}