{
  "type": "Feature",
  "properties": {
    "addr:full":"Brouwerijstraat 69 Harelbeke West-Vlaanderen 8530",
    "addr:housenumber":"69",
    "addr:postcode":"8530",
    "addr:street":"Brouwerijstraat",
    "iso:country":"BE",
    "sg:address":"Brouwerijstraat 69",
    "sg:city":"Harelbeke",
    "sg:classifiers":[
        {
            "category":"Utilities",
            "subcategory":"Fuel Oil & Lpg",
            "type":"Services"
        }
    ],
    "sg:phone":"+32 56 21 37 71",
    "sg:postcode":"8530",
    "sg:province":"West-Vlaanderen",
    "sg:tags":[
        "product"
    ],
    "wof:name":"Brandstoffen Dejagere",
    "wof:placetype":"venue"
},
  "geometry": {"coordinates":[3.3176159859,50.8288002014],"type":"Point"}
}