{
  "type": "Feature",
  "properties": {
    "addr:full":"Petegemplein 24 Wortegem-petegem Oost-Vlaanderen 9790",
    "addr:housenumber":"24",
    "addr:postcode":"9790",
    "addr:street":"Petegemplein",
    "iso:country":"BE",
    "sg:address":"Petegemplein 24",
    "sg:city":"Wortegem-petegem",
    "sg:classifiers":[
        {
            "category":"Insurance",
            "subcategory":"Insurance Agent",
            "type":"Services"
        }
    ],
    "sg:phone":"+32 55 31 78 44",
    "sg:postcode":"9790",
    "sg:province":"Oost-Vlaanderen",
    "sg:tags":[
        "verzekeringsmakelaars",
        "expert"
    ],
    "wof:name":"D. Lelieur",
    "wof:placetype":"venue"
},
  "geometry": {"coordinates":[3.5569250584,50.8326721191],"type":"Point"}
}