{
  "type": "Feature",
  "properties": {
    "addr:full":"Guffenslaan 27 Hasselt Limburg 3500",
    "addr:housenumber":"27",
    "addr:postcode":"3500",
    "addr:street":"Guffenslaan",
    "iso:country":"BE",
    "sg:address":"Guffenslaan 27",
    "sg:city":"Hasselt",
    "sg:orig_category":"Enseignement secondaire g\u00e9n\u00e9ral. Enseignement secondaire technique and professionnel",
    "sg:phone":"+32 11 22 79 13",
    "sg:postcode":"3500",
    "sg:province":"Limburg",
    "wof:name":"St.jozefscollege",
    "wof:placetype":"venue"
},
  "geometry": {"coordinates":[5.339717865,50.927230835],"type":"Point"}
}