{
  "type": "Feature",
  "properties": {
    "addr:full":"Rue Des Bruy\u00c8res 3 Malmedy/malmedy Li\u00e8ge 4960",
    "addr:housenumber":"3",
    "addr:postcode":"4960",
    "addr:street":"Rue Des Bruye\u0300Res",
    "iso:country":"BE",
    "sg:address":"Rue Des Bruy\u00c8res 3",
    "sg:city":"Malmedy/malmedy",
    "sg:orig_category":"Artiesten and kunstenaars",
    "sg:phone":"+32 80 33 87 54",
    "sg:postcode":"4960",
    "sg:province":"Li\u00e8ge",
    "wof:name":"Robert Hoffmann",
    "wof:placetype":"venue"
},
  "geometry": {"coordinates":[6.0696368217,50.4206542969],"type":"Point"}
}