{
  "type": "Feature",
  "properties": {
    "iso:country":"BE",
    "sg:address":"Klein Laarstraat 44",
    "sg:city":"Beveren",
    "sg:orig_category":"Travaux de pl\u00e2trage",
    "sg:phone":"+32 3 775 07 80",
    "sg:postcode":"9120",
    "sg:province":"Oost-Vlaanderen",
    "wof:name":"Van De Voorde R.",
    "wof:placetype":"venue"
},
  "geometry": {"coordinates":[4.1705579758,51.2216453552],"type":"Point"}
}