{
  "type": "Feature",
  "properties": {
    "addr:full":"Avenue Hansens-soulie 42 Etterbeek Bruxelles-Capitale 1040",
    "addr:housenumber":"42",
    "addr:postcode":"1040",
    "addr:street":"Avenue Hansens-Soulie",
    "iso:country":"BE",
    "sg:address":"Avenue Hansens-soulie 42",
    "sg:city":"Etterbeek",
    "sg:classifiers":[
        {
            "category":"Fast Food",
            "type":"Food & Drink"
        }
    ],
    "sg:phone":"+32 2 732 73 30",
    "sg:postcode":"1040",
    "sg:province":"Bruxelles-Capitale",
    "sg:tags":[
        "meeneem",
        "restaurant"
    ],
    "wof:name":"Watchar\u00c9e Chimpibul",
    "wof:placetype":"venue"
},
  "geometry": {"coordinates":[4.3988051414,50.8311386108],"type":"Point"}
}