{
  "type": "Feature",
  "properties": {
    "iso:country":"BE",
    "sg:address":"Noordstraat 71",
    "sg:city":"Veurne",
    "sg:orig_category":"Slagers",
    "sg:phone":"+32 58 31 13 36",
    "sg:postcode":"8630",
    "sg:province":"West-Vlaanderen",
    "wof:name":"Jan Roggeman",
    "wof:placetype":"venue"
},
  "geometry": {"coordinates":[2.6624228954,51.0755767822],"type":"Point"}
}