{
  "type": "Feature",
  "properties": {
    "addr:full":"Rue De Sainte-ode 30 Sainte-ode (lavacherie) Luxembourg 6681",
    "addr:housenumber":"30",
    "addr:postcode":"6681",
    "addr:street":"Rue De Sainte-Ode;Lavacherie",
    "iso:country":"BE",
    "sg:address":"Rue De Sainte-ode 30",
    "sg:city":"Sainte-ode (lavacherie)",
    "sg:classifiers":[
        {
            "category":"Professional",
            "subcategory":"Accounting & Tax Preparation",
            "type":"Services"
        }
    ],
    "sg:phone":"+32 63 22 05 02",
    "sg:postcode":"6681",
    "sg:province":"Luxembourg",
    "sg:tags":[
        "accountant"
    ],
    "wof:name":"Bathy Guy Sprl",
    "wof:placetype":"venue"
},
  "geometry": {"coordinates":[5.5096869469,50.0554656982],"type":"Point"}
}