{
  "type": "Feature",
  "properties": {
    "iso:country":"BE",
    "sg:address":"Battelsesteenweg 376",
    "sg:city":"Mechelen",
    "sg:orig_category":"Avocats and conseillers juridiques",
    "sg:phone":"+32 15 27 18 24",
    "sg:postcode":"2800",
    "sg:province":"Antwerpen",
    "wof:name":"Gerry Verschuren",
    "wof:placetype":"venue"
},
  "geometry": {"coordinates":[4.4564428329,51.0342025757],"type":"Point"}
}