{
  "type": "Feature",
  "properties": {
    "iso:country":"BE",
    "sg:address":"Kerkstraat 29",
    "sg:city":"Sint-truiden",
    "sg:orig_category":"Producteurs de fruits. Eleveurs and marchands de porcs",
    "sg:phone":"+32 11 68 74 94",
    "sg:postcode":"3800",
    "sg:province":"Limburg",
    "wof:name":"Joseph Smets",
    "wof:placetype":"venue"
},
  "geometry": {"coordinates":[5.1814517975,50.7731513977],"type":"Point"}
}