{
  "type": "Feature",
  "properties": {
    "addr:full":"Rue De Bavay 91 Qu\u00c9vy Hainaut 7040",
    "addr:housenumber":"91",
    "addr:postcode":"7040",
    "addr:street":"Rue De Bavay;Hainaut",
    "iso:country":"BE",
    "sg:address":"Rue De Bavay 91",
    "sg:city":"Qu\u00c9vy",
    "sg:orig_category":"Maisons de repos and r\u00e9sidences",
    "sg:phone":"+32 65 56 87 34",
    "sg:postcode":"7040",
    "sg:province":"Hainaut",
    "wof:name":"France Zanders",
    "wof:placetype":"venue"
},
  "geometry": {"coordinates":[3.9034149647,50.3832206726],"type":"Point"}
}