{
  "type": "Feature",
  "properties": {
    "iso:country":"BE",
    "sg:address":"Chauss\u00e9e De Willemeau 278a",
    "sg:city":"Tournai",
    "sg:classifiers":[
        {
            "category":"Health Services",
            "subcategory":"Health Practitioner",
            "type":"Services"
        }
    ],
    "sg:phone":"+32 69 23 37 86",
    "sg:postcode":"7500",
    "sg:province":"Hainaut",
    "sg:tags":[
        "physiotherapist"
    ],
    "wof:name":"Meurisse P",
    "wof:placetype":"venue"
},
  "geometry": {"coordinates":[3.3714311123,50.5896263123],"type":"Point"}
}