{
  "type": "Feature",
  "properties": {
    "iso:country":"BE",
    "sg:address":"Oude Tramweg 2",
    "sg:city":"Hoogstraten",
    "sg:orig_category":"Fruitteelt",
    "sg:phone":"+32 3 315 76 66",
    "sg:postcode":"2321",
    "sg:province":"Antwerpen",
    "wof:name":"Piet Van Alphen",
    "wof:placetype":"venue"
},
  "geometry": {"coordinates":[4.7366099358,51.442325592],"type":"Point"}
}