{
  "type": "Feature",
  "properties": {
    "addr:full":"Landuitstraat 10 De Pinte Oost-Vlaanderen 9840",
    "addr:housenumber":"10",
    "addr:postcode":"9840",
    "addr:street":"Landuitstraat",
    "iso:country":"BE",
    "sg:address":"Landuitstraat 10",
    "sg:city":"De Pinte",
    "sg:orig_category":"Eleveurs and marchands de porcs",
    "sg:phone":"+32 9 385 47 17",
    "sg:postcode":"9840",
    "sg:province":"Oost-Vlaanderen",
    "wof:name":"Rene Beyaert",
    "wof:placetype":"venue"
},
  "geometry": {"coordinates":[3.6712460518,50.9716491699],"type":"Point"}
}