{
  "type": "Feature",
  "properties": {
    "iso:country":"BE",
    "sg:address":"Oude Spoorbaan 5",
    "sg:city":"Willebroek (tisselt)",
    "sg:classifiers":[
        {
            "category":"Personal",
            "type":"Services"
        }
    ],
    "sg:phone":"+32 3 293 31 92",
    "sg:postcode":"2830",
    "sg:province":"Antwerpen",
    "sg:tags":[
        "party",
        "planning"
    ],
    "wof:name":"Moons P",
    "wof:placetype":"venue"
},
  "geometry": {"coordinates":[4.3483400345,51.0369338989],"type":"Point"}
}