{
  "type": "Feature",
  "properties": {
    "iso:country":"BE",
    "sg:address":"Barkenlaan 38",
    "sg:city":"De Panne",
    "sg:classifiers":[
        {
            "category":"Building & Trades",
            "subcategory":"Electrical",
            "type":"Services"
        }
    ],
    "sg:phone":"+32 58 41 23 64",
    "sg:postcode":"8660",
    "sg:province":"West-Vlaanderen",
    "sg:tags":[
        "electric",
        "-",
        "housewiring",
        "contractor"
    ],
    "wof:name":"Elektro Verstraete",
    "wof:placetype":"venue"
},
  "geometry": {"coordinates":[2.5945010185,51.100112915],"type":"Point"}
}