{
  "type": "Feature",
  "properties": {
    "addr:full":"Grote Steenweg 101 Zulte Oost-Vlaanderen 9870",
    "addr:housenumber":"101",
    "addr:postcode":"9870",
    "addr:street":"Grote Steenweg",
    "iso:country":"BE",
    "sg:address":"Grote Steenweg 101",
    "sg:city":"Zulte",
    "sg:classifiers":[
        {
            "category":"Communications",
            "subcategory":"Newspaper",
            "type":"Services"
        }
    ],
    "sg:phone":"+32 9 388 80 56",
    "sg:postcode":"9870",
    "sg:province":"Oost-Vlaanderen",
    "sg:tags":[
        "paper",
        "local",
        "free"
    ],
    "wof:name":"De Cuyper",
    "wof:placetype":"venue"
},
  "geometry": {"coordinates":[3.4637670517,50.9348983765],"type":"Point"}
}