{
  "type": "Feature",
  "properties": {
    "addr:full":"Wijnveld 251 Sint-niklaas (sinaai) Oost-Vlaanderen 9112",
    "addr:housenumber":"251",
    "addr:postcode":"9112",
    "addr:street":"Wijnveld;Oost-Vlaanderen",
    "iso:country":"BE",
    "sg:address":"Wijnveld 251",
    "sg:city":"Sint-niklaas (sinaai)",
    "sg:classifiers":[
        {
            "category":"Social Services",
            "type":"Services"
        }
    ],
    "sg:phone":"+32 3 772 60 61",
    "sg:postcode":"9112",
    "sg:province":"Oost-Vlaanderen",
    "wof:name":"Centrum Voor Levensvorming",
    "wof:placetype":"venue"
},
  "geometry": {"coordinates":[4.0663990974,51.1437301636],"type":"Point"}
}