{
  "type": "Feature",
  "properties": {
    "addr:full":"Steenweg Op Mechelen 370 Kraainem/kraainem Vlaams-Brabant 1950",
    "addr:housenumber":"370",
    "addr:postcode":"1950",
    "addr:street":"Steenweg Op Mechelen",
    "iso:country":"BE",
    "sg:address":"Steenweg Op Mechelen 370",
    "sg:city":"Kraainem/kraainem",
    "sg:orig_category":"Benzinestations and brandstoffen Krantenwinkels",
    "sg:phone":"+32 2 767 12 93",
    "sg:postcode":"1950",
    "sg:province":"Vlaams-Brabant",
    "wof:name":"Q8",
    "wof:placetype":"venue"
},
  "geometry": {"coordinates":[4.4808688164,50.8252220154],"type":"Point"}
}