{
  "type": "Feature",
  "properties": {
    "iso:country":"BE",
    "sg:address":"Rue L\u00e9on Simon 15",
    "sg:city":"Andenne",
    "sg:classifiers":[
        {
            "category":"Health Services",
            "subcategory":"Doctor",
            "type":"Services"
        }
    ],
    "sg:phone":"+32 85 84 92 40",
    "sg:postcode":"5300",
    "sg:province":"Namur",
    "sg:tags":[
        "medicinephysicians",
        "surgeon"
    ],
    "wof:name":"Englebert Anne",
    "wof:placetype":"venue"
},
  "geometry": {"coordinates":[5.098077774,50.4871711731],"type":"Point"}
}