{
  "type": "Feature",
  "properties": {
    "addr:full":"Waaslandlaan 4 Lokeren Oost-Vlaanderen 9160",
    "addr:housenumber":"4",
    "addr:postcode":"9160",
    "addr:street":"Waaslandlaan",
    "iso:country":"BE",
    "sg:address":"Waaslandlaan 4",
    "sg:city":"Lokeren",
    "sg:classifiers":[
        {
            "category":"Building & Trades",
            "subcategory":"Equipment Rental",
            "type":"Services"
        }
    ],
    "sg:phone":"+32 9 348 92 92",
    "sg:postcode":"9160",
    "sg:province":"Oost-Vlaanderen",
    "sg:tags":[
        "sound",
        "-",
        "system"
    ],
    "wof:name":"Delta Audio Services Nv",
    "wof:placetype":"venue"
},
  "geometry": {"coordinates":[4.0102071762,51.1203689575],"type":"Point"}
}