{
  "type": "Feature",
  "properties": {
    "iso:country":"BE",
    "sg:address":"Rue Pierre Van Obberghen 92",
    "sg:city":"Bruxelles (evere)",
    "sg:classifiers":[
        {
            "category":"Arts & Performance",
            "subcategory":"Theater",
            "type":"Entertainment"
        }
    ],
    "sg:phone":"+32 2 245 28 10",
    "sg:postcode":"1140",
    "sg:province":"Bruxelles-Capitale",
    "sg:tags":[
        "theatrical",
        "agency"
    ],
    "wof:name":"Ubu Sprl",
    "wof:placetype":"venue"
},
  "geometry": {"coordinates":[4.3981890678,50.8727722168],"type":"Point"}
}