{
  "type": "Feature",
  "properties": {
    "iso:country":"BE",
    "sg:address":"Kerkstraat 24",
    "sg:city":"Ternat (sint-katherina-lombeek)",
    "sg:classifiers":[
        {
            "category":"Building & Trades",
            "subcategory":"Cleaning & Sanitation",
            "type":"Services"
        }
    ],
    "sg:phone":"+32 2 582 82 38",
    "sg:postcode":"1742",
    "sg:province":"Vlaams-Brabant",
    "sg:tags":[
        "cleaner",
        "window"
    ],
    "wof:name":"Window Cleaning",
    "wof:placetype":"venue"
},
  "geometry": {"coordinates":[4.1569662094,50.8724021912],"type":"Point"}
}