{
  "type": "Feature",
  "properties": {
    "iso:country":"BE",
    "sg:address":"Rue De Gourdinne 29",
    "sg:city":"Ham-sur-heure-nalinnes",
    "sg:classifiers":[
        {
            "category":"Utilities",
            "subcategory":"Electric",
            "type":"Services"
        }
    ],
    "sg:phone":"+32 71 21 73 11",
    "sg:postcode":"6120",
    "sg:province":"Hainaut",
    "sg:tags":[
        "discharge",
        "machining",
        "electrical",
        "edm"
    ],
    "wof:name":"Erolec Electro Erosion",
    "wof:placetype":"venue"
},
  "geometry": {"coordinates":[4.4466371536,50.3210639954],"type":"Point"}
}