{
  "type": "Feature",
  "properties": {
    "addr:full":"Avenue Baron Seutin 24 Waterloo Brabant Wallon 1410",
    "addr:housenumber":"24",
    "addr:postcode":"1410",
    "addr:street":"Avenue Baron Seutin",
    "iso:country":"BE",
    "sg:address":"Avenue Baron Seutin 24",
    "sg:city":"Waterloo",
    "sg:orig_category":"Paramedische behandelingen",
    "sg:phone":"+32 2 384 77 82",
    "sg:postcode":"1410",
    "sg:province":"Brabant Wallon",
    "wof:name":"De Ryckman",
    "wof:placetype":"venue"
},
  "geometry": {"coordinates":[4.375767231,50.7045021057],"type":"Point"}
}