{
  "type": "Feature",
  "properties": {
    "iso:country":"BE",
    "sg:address":"Brechtsebaan 14",
    "sg:city":"Schoten",
    "sg:classifiers":[
        {
            "category":"Retail",
            "subcategory":"Auto Repair",
            "type":"Services"
        }
    ],
    "sg:phone":"+32 3 658 42 30",
    "sg:postcode":"2900",
    "sg:province":"Antwerpen",
    "sg:tags":[
        "breakdown",
        "automobile",
        "-",
        "recovery"
    ],
    "wof:name":"Carrosserie De Backer R",
    "wof:placetype":"venue"
},
  "geometry": {"coordinates":[4.5100498199,51.2647094727],"type":"Point"}
}