{
  "type": "Feature",
  "properties": {
    "addr:full":"Rue Marie-henriette 92 Elsene/ixelles Bruxelles-Capitale 1050",
    "addr:housenumber":"92",
    "addr:postcode":"1050",
    "addr:street":"Rue Marie-Henriette",
    "iso:country":"BE",
    "sg:address":"Rue Marie-henriette 92",
    "sg:city":"Elsene/ixelles",
    "sg:orig_category":"Woningbouw",
    "sg:phone":"+32 2 646 30 35",
    "sg:postcode":"1050",
    "sg:province":"Bruxelles-Capitale",
    "wof:name":"Pinto-rui",
    "wof:placetype":"venue"
},
  "geometry": {"coordinates":[4.3749837875,50.8289413452],"type":"Point"}
}