{
  "type": "Feature",
  "properties": {
    "addr:full":"Dikkebusseweg 307 Ieper West-Vlaanderen 8908",
    "addr:housenumber":"307",
    "addr:postcode":"8908",
    "iso:country":"BE",
    "sg:address":"Dikkebusseweg 307",
    "sg:city":"Ieper",
    "sg:orig_category":"Openbare veiligheid",
    "sg:phone":"+32 57 20 88 45",
    "sg:postcode":"8908",
    "sg:province":"West-Vlaanderen",
    "wof:name":"Federale Politie",
    "wof:placetype":"venue"
},
  "geometry": {"coordinates":[2.8546459675,50.825504303],"type":"Point"}
}