{
  "type": "Feature",
  "properties": {
    "addr:full":"Rue Langeveld 20 Bruxelles (uccle) Bruxelles-Capitale 1180",
    "addr:housenumber":"20",
    "addr:postcode":"1180",
    "addr:street":"Rue Langeveld",
    "iso:country":"BE",
    "sg:address":"Rue Langeveld 20",
    "sg:city":"Bruxelles (uccle)",
    "sg:classifiers":[
        {
            "category":"Professional",
            "subcategory":"Management & Consulting",
            "type":"Services"
        }
    ],
    "sg:phone":"+32 2 372 18 35",
    "sg:postcode":"1180",
    "sg:province":"Bruxelles-Capitale",
    "sg:tags":[
        "consultant",
        "agency",
        "advertising"
    ],
    "wof:name":"P.p. Com",
    "wof:placetype":"venue"
},
  "geometry": {"coordinates":[4.358725071,50.8065109253],"type":"Point"}
}