{
  "type": "Feature",
  "properties": {
    "addr:full":"Avenue Saint-augustin 34 Bruxelles (forest) Bruxelles-Capitale 1190",
    "addr:housenumber":"34",
    "addr:postcode":"1190",
    "addr:street":"Avenue Saint-Augustin",
    "iso:country":"BE",
    "sg:address":"Avenue Saint-augustin 34",
    "sg:city":"Bruxelles (forest)",
    "sg:classifiers":[
        {
            "category":"Arena",
            "subcategory":"Sports Club",
            "type":"Entertainment"
        }
    ],
    "sg:phone":"+32 2 345 05 38",
    "sg:postcode":"1190",
    "sg:province":"Bruxelles-Capitale",
    "sg:tags":[
        "martial art",
        "accessory"
    ],
    "wof:name":"Prospero R",
    "wof:placetype":"venue"
},
  "geometry": {"coordinates":[4.3392891884,50.816783905],"type":"Point"}
}