{
  "type": "Feature",
  "properties": {
    "iso:country":"BE",
    "sg:address":"Rue De La Scierie 22",
    "sg:city":"Leglise",
    "sg:orig_category":"Rundveehouders",
    "sg:phone":"+32 63 60 13 05",
    "sg:postcode":"6860",
    "sg:province":"Luxembourg",
    "wof:name":"Andre Lemaire",
    "wof:placetype":"venue"
},
  "geometry": {"coordinates":[5.5960979462,49.8541908264],"type":"Point"}
}