{
  "type": "Feature",
  "properties": {
    "addr:full":"Rue De Tournai 1 Leuze-en-hainaut Hainaut 7900",
    "addr:housenumber":"1",
    "addr:postcode":"7900",
    "addr:street":"Rue De Tournai",
    "iso:country":"BE",
    "sg:address":"Rue De Tournai 1",
    "sg:city":"Leuze-en-hainaut",
    "sg:classifiers":[
        {
            "category":"Shopping",
            "subcategory":"Optician",
            "type":"Retail Goods"
        }
    ],
    "sg:phone":"+32 69 66 71 76",
    "sg:postcode":"7900",
    "sg:province":"Hainaut",
    "sg:tags":[
        "-"
    ],
    "wof:name":"Clin D'oeil",
    "wof:placetype":"venue"
},
  "geometry": {"coordinates":[3.6175649166,50.5989265442],"type":"Point"}
}