{
  "type": "Feature",
  "properties": {
    "addr:full":"Wakkensesteenweg 31 Tielt West-Vlaanderen 8700",
    "addr:housenumber":"31",
    "addr:postcode":"8700",
    "addr:street":"Wakkensesteenweg",
    "iso:country":"BE",
    "sg:address":"Wakkensesteenweg 31",
    "sg:city":"Tielt",
    "sg:classifiers":[
        {
            "category":"Cafe",
            "type":"Food & Drink"
        }
    ],
    "sg:phone":"+32 51 40 88 05",
    "sg:postcode":"8700",
    "sg:province":"West-Vlaanderen",
    "sg:tags":[
        "caf\u00e9s"
    ],
    "wof:name":"Caf\u00c9 Bij Martin",
    "wof:placetype":"venue"
},
  "geometry": {"coordinates":[3.338629961,50.9857749939],"type":"Point"}
}