{
  "type": "Feature",
  "properties": {
    "iso:country":"BE",
    "sg:address":"Rue De La Chapelle 13",
    "sg:city":"Antoing (p\u00e9ronnes-lez-antoing)",
    "sg:classifiers":[
        {
            "category":"Retail",
            "subcategory":"Auto Repair",
            "type":"Services"
        }
    ],
    "sg:phone":"+32 69 44 36 73",
    "sg:postcode":"7640",
    "sg:province":"Hainaut",
    "sg:tags":[
        "garage"
    ],
    "wof:name":"Delcourt M",
    "wof:placetype":"venue"
},
  "geometry": {"coordinates":[3.4518361092,50.5542259216],"type":"Point"}
}