{
  "type": "Feature",
  "properties": {
    "addr:full":"Stationsstraat 55 Aalter Oost-Vlaanderen 9880",
    "addr:housenumber":"55",
    "addr:postcode":"9880",
    "addr:street":"Stationsstraat",
    "iso:country":"BE",
    "sg:address":"Stationsstraat 55",
    "sg:city":"Aalter",
    "sg:orig_category":"Fournitures de bureau",
    "sg:phone":"+32 9 374 25 71",
    "sg:postcode":"9880",
    "sg:province":"Oost-Vlaanderen",
    "wof:name":"Huis De Maertelaere",
    "wof:placetype":"venue"
},
  "geometry": {"coordinates":[3.4479310513,51.085811615],"type":"Point"}
}