{
  "type": "Feature",
  "properties": {
    "addr:full":"Baron Ruzettelaan 36 Brugge West-Vlaanderen 8310",
    "addr:housenumber":"36",
    "addr:postcode":"8310",
    "addr:street":"Baron Ruzettelaan",
    "iso:country":"BE",
    "sg:address":"Baron Ruzettelaan 36",
    "sg:city":"Brugge",
    "sg:orig_category":"Activit\u00e9s d\u00b4action sociale sans h\u00e9bergement",
    "sg:phone":"+32 50 37 55 22",
    "sg:postcode":"8310",
    "sg:province":"West-Vlaanderen",
    "wof:name":"Medi Prevent",
    "wof:placetype":"venue"
},
  "geometry": {"coordinates":[3.2307429314,51.197353363],"type":"Point"}
}