{
  "type": "Feature",
  "properties": {
    "addr:full":"Nieuwstraat 19 Heuvelland West-Vlaanderen 8956",
    "addr:housenumber":"19",
    "addr:postcode":"8956",
    "addr:street":"Nieuwstraat",
    "iso:country":"BE",
    "sg:address":"Nieuwstraat 19",
    "sg:city":"Heuvelland",
    "sg:orig_category":"Rundveehouders",
    "sg:phone":"+32 57 44 44 20",
    "sg:postcode":"8956",
    "sg:province":"West-Vlaanderen",
    "wof:name":"Willy Callewaert",
    "wof:placetype":"venue"
},
  "geometry": {"coordinates":[2.8369390965,50.7961158752],"type":"Point"}
}