{
  "type": "Feature",
  "properties": {
    "iso:country":"BE",
    "sg:address":"Beenhouwersstraat 35",
    "sg:city":"Brussel/bruxelles",
    "sg:classifiers":[
        {
            "category":"Bars & Pubs",
            "type":"Food & Drink"
        }
    ],
    "sg:phone":"+32 2 511 54 67",
    "sg:postcode":"1000",
    "sg:province":"Bruxelles-Capitale",
    "sg:tags":[
        "caf\u00e9s"
    ],
    "wof:name":"Dali's Bar",
    "wof:placetype":"venue"
},
  "geometry": {"coordinates":[4.3545589447,50.8477478027],"type":"Point"}
}