{
  "type": "Feature",
  "properties": {
    "addr:full":"Chauss\u00e9e De Bruxelles 201 Tournai Hainaut 7500",
    "addr:housenumber":"201",
    "addr:postcode":"7500",
    "addr:street":"Chausse\u0301E De Bruxelles",
    "iso:country":"BE",
    "sg:address":"Chauss\u00e9e De Bruxelles 201",
    "sg:city":"Tournai",
    "sg:classifiers":[
        {
            "category":"Autos & Motor Vehicles",
            "subcategory":"Fuel & Gas Station",
            "type":"Retail Goods"
        }
    ],
    "sg:phone":"+32 69 22 33 93",
    "sg:postcode":"7500",
    "sg:province":"Hainaut",
    "wof:name":"Station Esso Luc",
    "wof:placetype":"venue"
},
  "geometry": {"coordinates":[3.426525116,50.6024513245],"type":"Point"}
}