{
  "type": "Feature",
  "properties": {
    "addr:full":"Port Arthurlaan 190 Gent Oost-Vlaanderen 9000",
    "addr:housenumber":"190",
    "addr:postcode":"9000",
    "addr:street":"Port Arthurlaan;Oost-Vlaanderen",
    "iso:country":"BE",
    "sg:address":"Port Arthurlaan 190",
    "sg:city":"Gent",
    "sg:orig_category":"Agences d'exp\u00e9dition. Agences maritimes",
    "sg:phone":"+32 9 251 63 63",
    "sg:postcode":"9000",
    "sg:province":"Oost-Vlaanderen",
    "wof:name":"Fasco",
    "wof:placetype":"venue"
},
  "geometry": {"coordinates":[3.7321560383,51.0877761841],"type":"Point"}
}