{
  "type": "Feature",
  "properties": {
    "addr:full":"Kaasmarkt 131 Wemmel Vlaams-Brabant 1780",
    "addr:housenumber":"131",
    "addr:postcode":"1780",
    "addr:street":"Kaasmarkt;Vlaams-Brabant",
    "iso:country":"BE",
    "sg:address":"Kaasmarkt 131",
    "sg:city":"Wemmel",
    "sg:orig_category":"Sport- and kampeermateriaal Watersport-, Sport- and Kampeerbenodigdheden Verhuur",
    "sg:phone":"+32 2 460 09 01",
    "sg:postcode":"1780",
    "sg:province":"Vlaams-Brabant",
    "wof:name":"Ivan's Sportshop",
    "wof:placetype":"venue"
},
  "geometry": {"coordinates":[4.3013310432,50.906791687],"type":"Point"}
}