{
  "type": "Feature",
  "properties": {
    "addr:full":"Rue Joseph Schepers 1 Orp-jauche Brabant Wallon 1350",
    "addr:housenumber":"1",
    "addr:postcode":"1350",
    "addr:street":"Rue Joseph Schepers",
    "iso:country":"BE",
    "sg:address":"Rue Joseph Schepers 1",
    "sg:city":"Orp-jauche",
    "sg:orig_category":"Eleveurs de bovins",
    "sg:phone":"+32 19 65 50 48",
    "sg:postcode":"1350",
    "sg:province":"Brabant Wallon",
    "wof:name":"Vandormael J.-luc & Jules",
    "wof:placetype":"venue"
},
  "geometry": {"coordinates":[4.97920084,50.6738891602],"type":"Point"}
}