{
  "type": "Feature",
  "properties": {
    "iso:country":"BE",
    "sg:address":"Stoktsebaan 22",
    "sg:city":"Vosselaar",
    "sg:orig_category":"Tuinen",
    "sg:phone":"+32 14 61 65 04",
    "sg:postcode":"2350",
    "sg:province":"Antwerpen",
    "wof:name":"Eyckerman",
    "wof:placetype":"venue"
},
  "geometry": {"coordinates":[4.8883748055,51.3195915222],"type":"Point"}
}