{
  "type": "Feature",
  "properties": {
    "addr:full":"Stationsstraat 3 Lebbeke Oost-Vlaanderen 9280",
    "addr:housenumber":"3",
    "addr:postcode":"9280",
    "addr:street":"Stationsstraat",
    "iso:country":"BE",
    "sg:address":"Stationsstraat 3",
    "sg:city":"Lebbeke",
    "sg:orig_category":"Mat\u00e9riel de T\u00e9l\u00e9communication. Equipement photographique. Studios photographiques",
    "sg:phone":"+32 52 41 06 06",
    "sg:postcode":"9280",
    "sg:province":"Oost-Vlaanderen",
    "wof:name":"Top Camera Foto Podevyn",
    "wof:placetype":"venue"
},
  "geometry": {"coordinates":[4.1339578629,51.0053367615],"type":"Point"}
}