{
  "type": "Feature",
  "properties": {
    "addr:full":"Rue De La Fontaine 9 Flemalle Li\u00e8ge 4400",
    "addr:housenumber":"9",
    "addr:postcode":"4400",
    "addr:street":"Rue De La Fontaine",
    "iso:country":"BE",
    "sg:address":"Rue De La Fontaine 9",
    "sg:city":"Flemalle",
    "sg:orig_category":"Fleurs and plantes",
    "sg:phone":"+32 4 233 65 31",
    "sg:postcode":"4400",
    "sg:province":"Li\u00e8ge",
    "wof:name":"Isabelle Chiodo",
    "wof:placetype":"venue"
},
  "geometry": {"coordinates":[5.478374958,50.6071052551],"type":"Point"}
}