{
  "type": "Feature",
  "properties": {
    "iso:country":"BE",
    "sg:address":"Rue De La Station 8",
    "sg:city":"Enghien",
    "sg:classifiers":[
        {
            "category":"Shopping",
            "subcategory":"Clothing, Apparel, & Fashions",
            "type":"Retail Goods"
        }
    ],
    "sg:phone":"+32 2 395 31 11",
    "sg:postcode":"7850",
    "sg:province":"Hainaut",
    "sg:tags":[
        "clothing",
        "-",
        "gentleman"
    ],
    "wof:name":"Armoire \u00e0 Chemises",
    "wof:placetype":"venue"
},
  "geometry": {"coordinates":[4.0438928604,50.6957206726],"type":"Point"}
}