{
  "type": "Feature",
  "properties": {
    "addr:full":"Dr\u00e8ve Du Docteur Du Triage De La Bruy\u00e8re 22 Braine L'alleud (braine-l'alleud) Brabant Wallon 1420",
    "addr:housenumber":"22",
    "addr:postcode":"1420",
    "addr:street":"Dre\u0300Ve Du Docteur Du Triage De La Bruye\u0300Re",
    "iso:country":"BE",
    "sg:address":"Dr\u00e8ve Du Docteur Du Triage De La Bruy\u00e8re 22",
    "sg:city":"Braine L'alleud (braine-l'alleud)",
    "sg:classifiers":[
        {
            "category":"Shopping",
            "subcategory":"Crafts & Fabrics",
            "type":"Retail Goods"
        }
    ],
    "sg:phone":"+32 2 351 40 93",
    "sg:postcode":"1420",
    "sg:province":"Brabant Wallon",
    "sg:tags":[
        "plant",
        "flower",
        "artificial"
    ],
    "wof:name":"Desi Sprl",
    "wof:placetype":"venue"
},
  "geometry": {"coordinates":[4.1110739708,43.6818313599],"type":"Point"}
}