{
  "type": "Feature",
  "properties": {
    "iso:country":"BE",
    "sg:address":"Stationstraat 91",
    "sg:city":"Sint-gillis-waas",
    "sg:classifiers":[
        {
            "category":"Professional",
            "subcategory":"Management & Consulting",
            "type":"Services"
        }
    ],
    "sg:phone":"+32 3 755 14 39",
    "sg:postcode":"9170",
    "sg:province":"Oost-Vlaanderen",
    "sg:tags":[
        "-",
        "processing",
        "data",
        "consultant"
    ],
    "wof:name":"De Munck Consulting",
    "wof:placetype":"venue"
},
  "geometry": {"coordinates":[4.1172661781,51.2185935974],"type":"Point"}
}