{
  "type": "Feature",
  "properties": {
    "iso:country":"BE",
    "sg:address":"Schapenbaan 19",
    "sg:city":"Asse (zellik)",
    "sg:classifiers":[
        {
            "category":"Wholesale",
            "subcategory":"Chemicals & Plastics",
            "type":"Manufacturing & Wholesale Goods"
        }
    ],
    "sg:phone":"+32 2 460 05 10",
    "sg:postcode":"1731",
    "sg:province":"Vlaams-Brabant",
    "sg:tags":[
        "packing"
    ],
    "wof:name":"Rkw Belgium",
    "wof:placetype":"venue"
},
  "geometry": {"coordinates":[4.2812390327,50.8926048279],"type":"Point"}
}