{
  "type": "Feature",
  "properties": {
    "iso:country":"BE",
    "sg:address":"Rue Du Bois 5",
    "sg:city":"Chi\u00e8vres",
    "sg:classifiers":[
        {
            "category":"Banks & Credit Unions",
            "subcategory":"Investment Brokerage",
            "type":"Services"
        }
    ],
    "sg:phone":"+32 68 65 76 26",
    "sg:postcode":"7950",
    "sg:province":"Hainaut",
    "sg:tags":[
        "repair",
        "-",
        "installation",
        "sanitary",
        "article"
    ],
    "wof:name":"Dewati Scrl",
    "wof:placetype":"venue"
},
  "geometry": {"coordinates":[3.788670063,50.5592651367],"type":"Point"}
}