{
  "type": "Feature",
  "properties": {
    "addr:full":"Jules Van Praetstraat 75 Brugge West-Vlaanderen 8000",
    "addr:housenumber":"75",
    "addr:postcode":"8000",
    "addr:street":"Jules Van Praetstraat",
    "iso:country":"BE",
    "sg:address":"Jules Van Praetstraat 75",
    "sg:city":"Brugge",
    "sg:classifiers":[
        {
            "category":"Fast Food",
            "type":"Food & Drink"
        }
    ],
    "sg:phone":"+32 50 33 77 97",
    "sg:postcode":"8000",
    "sg:province":"West-Vlaanderen",
    "sg:tags":[
        "\u00c0",
        "restaurants",
        "emporter",
        "restaurant"
    ],
    "wof:name":"Kleine Hap",
    "wof:placetype":"venue"
},
  "geometry": {"coordinates":[3.2395040989,51.2292060852],"type":"Point"}
}