{
  "type": "Feature",
  "properties": {
    "iso:country":"BE",
    "sg:address":"Lindestraat 4",
    "sg:city":"Lovendegem",
    "sg:orig_category":"Paramedische behandelingen",
    "sg:phone":"+32 9 372 01 08",
    "sg:postcode":"9920",
    "sg:province":"Oost-Vlaanderen",
    "wof:name":"Christel Van Speybroeck",
    "wof:placetype":"venue"
},
  "geometry": {"coordinates":[3.6272349358,51.1058235168],"type":"Point"}
}