{
  "type": "Feature",
  "properties": {
    "iso:country":"BE",
    "sg:address":"Mechelsesteenweg 6",
    "sg:city":"Mortsel",
    "sg:orig_category":"Disneyland Paris. Agences de voyages",
    "sg:phone":"+32 3 440 68 10",
    "sg:postcode":"2640",
    "sg:province":"Antwerpen",
    "wof:name":"Neckermann",
    "wof:placetype":"venue"
},
  "geometry": {"coordinates":[4.4501662254,51.169467926],"type":"Point"}
}