{
  "type": "Feature",
  "properties": {
    "iso:country":"BE",
    "sg:address":"Markt 85",
    "sg:city":"Deinze",
    "sg:orig_category":"Newspapers, magazines, periodicals - Distribution",
    "sg:phone":"+32 9 386 24 67",
    "sg:postcode":"9800",
    "sg:province":"Oost-Vlaanderen",
    "wof:name":"Press Shop",
    "wof:placetype":"venue"
},
  "geometry": {"coordinates":[3.5260720253,50.9857406616],"type":"Point"}
}