{
  "type": "Feature",
  "properties": {
    "iso:country":"BE",
    "sg:address":"Stationsstraat 37",
    "sg:city":"Dilbeek",
    "sg:orig_category":"Elektrische and elektronische apparatuur Gh",
    "sg:phone":"+32 2 463 00 67",
    "sg:postcode":"1702",
    "sg:province":"Vlaams-Brabant",
    "wof:name":"Elektra Brussel",
    "wof:placetype":"venue"
},
  "geometry": {"coordinates":[4.2765498161,50.8710403442],"type":"Point"}
}