{
  "type": "Feature",
  "properties": {
    "iso:country":"BE",
    "sg:address":"Rue De Bouillon 49",
    "sg:city":"Beauraing",
    "sg:classifiers":[
        {
            "category":"Shopping",
            "subcategory":"Optician",
            "type":"Retail Goods"
        }
    ],
    "sg:phone":"+32 82 71 47 70",
    "sg:postcode":"5570",
    "sg:province":"Namur",
    "sg:tags":[
        "-"
    ],
    "wof:name":"Optix",
    "wof:placetype":"venue"
},
  "geometry": {"coordinates":[4.9575128555,50.1087989807],"type":"Point"}
}