{
  "type": "Feature",
  "properties": {
    "iso:country":"BE",
    "sg:address":"Laaglandlei 33",
    "sg:city":"Schoten",
    "sg:classifiers":[
        {
            "category":"Retail",
            "subcategory":"Animal Services",
            "type":"Services"
        }
    ],
    "sg:phone":"+32 3 658 23 53",
    "sg:postcode":"2900",
    "sg:province":"Antwerpen",
    "sg:tags":[
        "training",
        "dog"
    ],
    "wof:name":"De Moedige Bijters Bvba",
    "wof:placetype":"venue"
},
  "geometry": {"coordinates":[4.5131821632,51.2510528564],"type":"Point"}
}