{
  "type": "Feature",
  "properties": {
    "addr:full":"Nieuwstraat 238 Keerbergen Vlaams-Brabant 3140",
    "addr:housenumber":"238",
    "addr:postcode":"3140",
    "addr:street":"Nieuwstraat",
    "iso:country":"BE",
    "sg:address":"Nieuwstraat 238",
    "sg:city":"Keerbergen",
    "sg:classifiers":[
        {
            "category":"Home & Garden",
            "subcategory":"Home Furnishings",
            "type":"Retail Goods"
        }
    ],
    "sg:phone":"+32 16 52 04 98",
    "sg:postcode":"3140",
    "sg:province":"Vlaams-Brabant",
    "sg:tags":[
        "interior",
        "decoration"
    ],
    "wof:name":"Immo Projects",
    "wof:placetype":"venue"
},
  "geometry": {"coordinates":[4.6879940033,50.9959831238],"type":"Point"}
}