{
  "type": "Feature",
  "properties": {
    "iso:country":"BE",
    "sg:address":"Boulevard De Smet De Naeyer 216",
    "sg:city":"Bruxelles (jette)",
    "sg:classifiers":[
        {
            "category":"Personal",
            "subcategory":"Beauty Salon",
            "type":"Services"
        }
    ],
    "sg:phone":"+32 2 428 41 83",
    "sg:postcode":"1090",
    "sg:province":"Bruxelles-Capitale",
    "wof:name":"Linssen C",
    "wof:placetype":"venue"
},
  "geometry": {"coordinates":[4.3311061859,50.8764572144],"type":"Point"}
}