{
  "type": "Feature",
  "properties": {
    "addr:full":"Avenue Reine Astrid 74 La Hulpe Brabant Wallon 1310",
    "addr:housenumber":"74",
    "addr:postcode":"1310",
    "addr:street":"Avenue Reine Astrid",
    "iso:country":"BE",
    "sg:address":"Avenue Reine Astrid 74",
    "sg:city":"La Hulpe",
    "sg:orig_category":"Entretien and r\u00e9parations de voitures",
    "sg:phone":"+32 2 653 80 87",
    "sg:postcode":"1310",
    "sg:province":"Brabant Wallon",
    "wof:name":"Delwasse",
    "wof:placetype":"venue"
},
  "geometry": {"coordinates":[4.4750900269,50.7285919189],"type":"Point"}
}