{
  "type": "Feature",
  "properties": {
    "iso:country":"BE",
    "sg:address":"Dokter J. Geensstraat 24",
    "sg:city":"Tienen",
    "sg:classifiers":[
        {
            "category":"Professional",
            "subcategory":"Computer Services",
            "type":"Services"
        }
    ],
    "sg:phone":"+32 16 82 21 20",
    "sg:postcode":"3300",
    "sg:province":"Vlaams-Brabant",
    "sg:tags":[
        "-",
        "processing",
        "data",
        "software"
    ],
    "wof:name":"O.b.a.s.i. Vzw",
    "wof:placetype":"venue"
},
  "geometry": {"coordinates":[4.9343829155,50.8074836731],"type":"Point"}
}