{
  "type": "Feature",
  "properties": {
    "addr:full":"Apostelstraat 29 Sint-niklaas Oost-Vlaanderen 9100",
    "addr:housenumber":"29",
    "addr:postcode":"9100",
    "addr:street":"Apostelstraat",
    "iso:country":"BE",
    "sg:address":"Apostelstraat 29",
    "sg:city":"Sint-niklaas",
    "sg:orig_category":"Avocats and conseillers juridiques",
    "sg:phone":"+32 3 776 57 73",
    "sg:postcode":"9100",
    "sg:province":"Oost-Vlaanderen",
    "wof:name":"Francine Pauwels",
    "wof:placetype":"venue"
},
  "geometry": {"coordinates":[4.143611908,51.1638908386],"type":"Point"}
}