{
  "type": "Feature",
  "properties": {
    "addr:full":"Tiensesteenweg 354 Korbeek-lo Vlaams-Brabant 3360",
    "addr:housenumber":"354",
    "addr:postcode":"3360",
    "addr:street":"Tiensesteenweg",
    "iso:country":"BE",
    "sg:address":"Tiensesteenweg 354",
    "sg:city":"Korbeek-lo",
    "sg:orig_category":"Verhuur voertuigen behalve auto's",
    "sg:phone":"+32 800 16 666",
    "sg:postcode":"3360",
    "sg:province":"Vlaams-Brabant",
    "wof:name":"Trend-rent",
    "wof:placetype":"venue"
},
  "geometry": {"coordinates":[4.7729101181,50.8600883484],"type":"Point"}
}