{
  "type": "Feature",
  "properties": {
    "iso:country":"BE",
    "sg:address":"J Pierrestraat 116",
    "sg:city":"Leuven",
    "sg:orig_category":"Agences d'exp\u00e9dition",
    "sg:phone":"+32 16 35 61 80",
    "sg:postcode":"3010",
    "sg:province":"Vlaams-Brabant",
    "wof:name":"Arte Novo",
    "wof:placetype":"venue"
},
  "geometry": {"coordinates":[4.724902153,50.8857154846],"type":"Point"}
}