{
  "type": "Feature",
  "properties": {
    "iso:country":"BE",
    "sg:address":"Sijzenlaan 17",
    "sg:city":"Essen",
    "sg:orig_category":"Electrom\u00e9nager, t\u00e9l\u00e9visions and radios",
    "sg:phone":"+32 3 667 49 00",
    "sg:postcode":"2910",
    "sg:province":"Antwerpen",
    "wof:name":"Tv Snel Service",
    "wof:placetype":"venue"
},
  "geometry": {"coordinates":[4.512283802,51.4554748535],"type":"Point"}
}