{
  "type": "Feature",
  "properties": {
    "addr:full":"Kerkstraat 4 De Haan West-Vlaanderen 8420",
    "addr:housenumber":"4",
    "addr:postcode":"8420",
    "addr:street":"Kerkstraat",
    "iso:country":"BE",
    "sg:address":"Kerkstraat 4",
    "sg:city":"De Haan",
    "sg:orig_category":"Sport- and kampeermateriaal Warenhuizen",
    "sg:phone":"+32 50 41 18 97",
    "sg:postcode":"8420",
    "sg:province":"West-Vlaanderen",
    "wof:name":"Huis Demaecker",
    "wof:placetype":"venue"
},
  "geometry": {"coordinates":[3.0795450211,51.3010559082],"type":"Point"}
}