{
  "type": "Feature",
  "properties": {
    "iso:country":"BE",
    "sg:address":"Slaaktestraat 5",
    "sg:city":"Ieper",
    "sg:orig_category":"Rundveehouders Varkenskwekers",
    "sg:phone":"+32 57 48 86 91",
    "sg:postcode":"8904",
    "sg:province":"West-Vlaanderen",
    "wof:name":"Rafael Vermeersch",
    "wof:placetype":"venue"
},
  "geometry": {"coordinates":[2.8740100861,50.9073905945],"type":"Point"}
}