{
  "type": "Feature",
  "properties": {
    "addr:full":"Singel 21 Lille Antwerpen 2275",
    "addr:housenumber":"21",
    "addr:postcode":"2275",
    "addr:street":"Singel",
    "iso:country":"BE",
    "sg:address":"Singel 21",
    "sg:city":"Lille",
    "sg:orig_category":"Maatkleding Fab",
    "sg:phone":"+32 14 55 65 69",
    "sg:postcode":"2275",
    "sg:province":"Antwerpen",
    "wof:name":"Renatus Van Laer",
    "wof:placetype":"venue"
},
  "geometry": {"coordinates":[4.8679451942,51.2678642273],"type":"Point"}
}