{
  "type": "Feature",
  "properties": {
    "addr:full":"Mechelsesteenweg 328 Herent Vlaams-Brabant 3020",
    "addr:housenumber":"328",
    "addr:postcode":"3020",
    "addr:street":"Mechelsesteenweg",
    "iso:country":"BE",
    "sg:address":"Mechelsesteenweg 328",
    "sg:city":"Herent",
    "sg:classifiers":[
        {
            "category":"Communications",
            "subcategory":"Film & Video Production",
            "type":"Services"
        }
    ],
    "sg:phone":"+32 16 20 16 15",
    "sg:postcode":"3020",
    "sg:province":"Vlaams-Brabant",
    "sg:tags":[
        "hiring",
        "-"
    ],
    "wof:name":"Mega-ster",
    "wof:placetype":"venue"
},
  "geometry": {"coordinates":[4.6758608818,50.9023895264],"type":"Point"}
}