{
  "type": "Feature",
  "properties": {
    "addr:full":"Paardemarkt 17 Sint-lievens-houtem Oost-Vlaanderen 9520",
    "addr:housenumber":"17",
    "addr:postcode":"9520",
    "addr:street":"Paardemarkt;Oost-Vlaanderen",
    "iso:country":"BE",
    "sg:address":"Paardemarkt 17",
    "sg:city":"Sint-lievens-houtem",
    "sg:orig_category":"S\u00e9curit\u00e9 sociale",
    "sg:phone":"+32 53 62 54 71",
    "sg:postcode":"9520",
    "sg:province":"Oost-Vlaanderen",
    "wof:name":"Liberale Mutualiteit",
    "wof:placetype":"venue"
},
  "geometry": {"coordinates":[3.8534231186,50.9207572937],"type":"Point"}
}