{
  "type": "Feature",
  "properties": {
    "addr:full":"Quai Nord 48 Mons Hainaut 7000",
    "addr:housenumber":"48",
    "addr:postcode":"7000",
    "addr:street":"Quai Nord;Hainaut",
    "iso:country":"BE",
    "sg:address":"Quai Nord 48",
    "sg:city":"Mons",
    "sg:classifiers":[
        {
            "category":"Bars & Pubs",
            "type":"Food & Drink"
        }
    ],
    "sg:phone":"+32 65 35 46 71",
    "sg:postcode":"7000",
    "sg:province":"Hainaut",
    "wof:name":"Ecluse (l')",
    "wof:placetype":"venue"
},
  "geometry": {"coordinates":[3.9327399731,50.453956604],"type":"Point"}
}