{
  "type": "Feature",
  "properties": {
    "iso:country":"BE",
    "sg:address":"Getestraat 64",
    "sg:city":"Tienen",
    "sg:orig_category":"Bijouteries and horlogeries",
    "sg:phone":"+32 16 81 70 83",
    "sg:postcode":"3300",
    "sg:province":"Vlaams-Brabant",
    "wof:name":"Julia Dons",
    "wof:placetype":"venue"
},
  "geometry": {"coordinates":[4.9319682121,50.798286438],"type":"Point"}
}