{
  "type": "Feature",
  "properties": {
    "addr:full":"Rue De Couillet 125 Chatelet Hainaut 6200",
    "addr:housenumber":"125",
    "addr:postcode":"chatelet;6200",
    "addr:street":"Rue De Couillet",
    "iso:country":"BE",
    "sg:address":"Rue De Couillet 125",
    "sg:city":"Chatelet",
    "sg:orig_category":"Huishoudapparaten, televisies and radio's Loodgieterij, verwarming and sanitaire installaties MEUBEL",
    "sg:phone":"+32 71 38 37 22",
    "sg:postcode":"6200",
    "sg:province":"Hainaut",
    "wof:name":"Guy Myter",
    "wof:placetype":"venue"
},
  "geometry": {"coordinates":[4.5100531578,50.4016189575],"type":"Point"}
}