{
  "type": "Feature",
  "properties": {
    "addr:full":"Platanenlaan 4 Steenokkerzeel Vlaams-Brabant 1820",
    "addr:housenumber":"4",
    "addr:postcode":"1820",
    "addr:street":"Platanenlaan",
    "iso:country":"BE",
    "sg:address":"Platanenlaan 4",
    "sg:city":"Steenokkerzeel",
    "sg:orig_category":"Artiesten and kunstenaars",
    "sg:phone":"+32 2 751 98 26",
    "sg:postcode":"1820",
    "sg:province":"Vlaams-Brabant",
    "wof:name":"Viviane Redant",
    "wof:placetype":"venue"
},
  "geometry": {"coordinates":[4.4936242104,50.9272689819],"type":"Point"}
}