{
  "type": "Feature",
  "properties": {
    "addr:full":"Grote Goddaerd 32 Antwerpen Antwerpen 2000",
    "addr:housenumber":"32",
    "addr:postcode":"2000",
    "addr:street":"Grote Goddaerd",
    "iso:country":"BE",
    "sg:address":"Grote Goddaerd 32",
    "sg:city":"Antwerpen",
    "sg:classifiers":[
        {
            "category":"Shopping",
            "subcategory":"Crafts & Fabrics",
            "type":"Retail Goods"
        }
    ],
    "sg:phone":"+32 3 231 06 30",
    "sg:postcode":"2000",
    "sg:province":"Antwerpen",
    "sg:tags":[
        "silk",
        "-"
    ],
    "wof:name":"Anver Sur Plus",
    "wof:placetype":"venue"
},
  "geometry": {"coordinates":[4.4045948982,51.2215538025],"type":"Point"}
}