{
  "type": "Feature",
  "properties": {
    "addr:full":"Koninginnelaan 3 Middelkerke West-Vlaanderen 8430",
    "addr:housenumber":"3",
    "addr:postcode":"8430",
    "addr:street":"Koninginnelaan",
    "iso:country":"BE",
    "sg:address":"Koninginnelaan 3",
    "sg:city":"Middelkerke",
    "sg:classifiers":[
        {
            "category":"Retail",
            "subcategory":"Auto Repair",
            "type":"Services"
        }
    ],
    "sg:phone":"+32 59 30 06 72",
    "sg:postcode":"8430",
    "sg:province":"West-Vlaanderen",
    "sg:tags":[
        "breakdown",
        "automobile",
        "-",
        "recovery"
    ],
    "wof:name":"Franco-belge",
    "wof:placetype":"venue"
},
  "geometry": {"coordinates":[2.8183379173,51.1875305176],"type":"Point"}
}