{
  "type": "Feature",
  "properties": {
    "iso:country":"BE",
    "sg:address":"Rue Abb\u00e9champs 17",
    "sg:city":"Andenne",
    "sg:classifiers":[
        {
            "category":"Personal",
            "subcategory":"Beauty Salon",
            "type":"Services"
        }
    ],
    "sg:phone":"+32 85 84 46 56",
    "sg:postcode":"5300",
    "sg:province":"Namur",
    "sg:tags":[
        "lady",
        "-",
        "hairdressing"
    ],
    "wof:name":"Hair Mode",
    "wof:placetype":"venue"
},
  "geometry": {"coordinates":[5.0951991081,50.4831581116],"type":"Point"}
}