{
  "type": "Feature",
  "properties": {
    "addr:full":"Antwerpsesteenweg 267 Westmalle Antwerpen 2390",
    "addr:housenumber":"267",
    "addr:postcode":"2390",
    "addr:street":"Antwerpsesteenweg",
    "iso:country":"BE",
    "sg:address":"Antwerpsesteenweg 267",
    "sg:city":"Westmalle",
    "sg:orig_category":"Randstad Tijdelijke werkgelegenheid and uitzendkantoren",
    "sg:phone":"+32 3 309 20 40",
    "sg:postcode":"2390",
    "sg:province":"Antwerpen",
    "wof:name":"Randstad",
    "wof:placetype":"venue"
},
  "geometry": {"coordinates":[4.6921319962,51.2967987061],"type":"Point"}
}