{
  "type": "Feature",
  "properties": {
    "addr:full":"Rue Rossini 19 Bruxelles (anderlecht) Bruxelles-Capitale 1070",
    "addr:housenumber":"19",
    "addr:postcode":"1070",
    "addr:street":"Rue Rossini",
    "iso:country":"BE",
    "sg:address":"Rue Rossini 19",
    "sg:city":"Bruxelles (anderlecht)",
    "sg:classifiers":[
        {
            "category":"Shopping",
            "subcategory":"Discount & Variety Stores",
            "type":"Retail Goods"
        }
    ],
    "sg:phone":"+32 475 80 88 50",
    "sg:postcode":"1070",
    "sg:province":"Bruxelles-Capitale",
    "sg:tags":[
        "shop",
        "clearers",
        "curiosity",
        "furniture"
    ],
    "wof:name":"Broc-a-neuf Sprl",
    "wof:placetype":"venue"
},
  "geometry": {"coordinates":[4.3307580948,50.8382911682],"type":"Point"}
}