{
  "type": "Feature",
  "properties": {
    "iso:country":"BE",
    "sg:address":"Sint-hubertusplein 22",
    "sg:city":"Zottegem (sint-maria-oudenhove)",
    "sg:classifiers":[
        {
            "category":"Food & Beverages",
            "subcategory":"Supermarket",
            "type":"Retail Goods"
        }
    ],
    "sg:phone":"+32 9 360 61 60",
    "sg:postcode":"9620",
    "sg:province":"Oost-Vlaanderen",
    "sg:tags":[
        "department",
        "store"
    ],
    "wof:name":"Spar",
    "wof:placetype":"venue"
},
  "geometry": {"coordinates":[3.7951030731,50.8340606689],"type":"Point"}
}