{
  "type": "Feature",
  "properties": {
    "iso:country":"BE",
    "sg:address":"Grote Veldstraat 114",
    "sg:city":"Staden",
    "sg:classifiers":[
        {
            "category":"Manufacturing",
            "subcategory":"Food",
            "type":"Manufacturing & Wholesale Goods"
        }
    ],
    "sg:phone":"+32 51 70 01 21",
    "sg:postcode":"8840",
    "sg:province":"West-Vlaanderen",
    "sg:tags":[
        "frozen"
    ],
    "wof:name":"Westfro Nv",
    "wof:placetype":"venue"
},
  "geometry": {"coordinates":[3.0225799084,50.962638855],"type":"Point"}
}