{
  "type": "Feature",
  "properties": {
    "addr:full":"Euphrosina Beernaertstr. 48 Oostende West-Vlaanderen 8400",
    "addr:housenumber":"48",
    "addr:postcode":"8400",
    "iso:country":"BE",
    "sg:address":"Euphrosina Beernaertstr. 48",
    "sg:city":"Oostende",
    "sg:orig_category":"Drukkerijen and copyshops",
    "sg:phone":"+32 59 51 27 44",
    "sg:postcode":"8400",
    "sg:province":"West-Vlaanderen",
    "wof:name":"Digital Copy",
    "wof:placetype":"venue"
},
  "geometry": {"coordinates":[2.9152379036,51.2273445129],"type":"Point"}
}