{
  "type": "Feature",
  "properties": {
    "iso:country":"BE",
    "sg:address":"Kazernebaan 34",
    "sg:city":"Helchteren",
    "sg:orig_category":"Huisdieren and benodigdheden Royal Canin",
    "sg:phone":"+32 11 52 19 65",
    "sg:postcode":"3530",
    "sg:province":"Limburg",
    "wof:name":"Vangansewinkel-lijnen&zn",
    "wof:placetype":"venue"
},
  "geometry": {"coordinates":[5.3883519173,51.0569267273],"type":"Point"}
}