{
  "type": "Feature",
  "properties": {
    "addr:full":"Rue De La Glacerie 112 Jemeppe-sur-sambre Namur 5190",
    "addr:housenumber":"112",
    "addr:postcode":"5190",
    "addr:street":"Rue De La Glacerie",
    "iso:country":"BE",
    "sg:address":"Rue De La Glacerie 112",
    "sg:city":"Jemeppe-sur-sambre",
    "sg:orig_category":"Entretien and r\u00e9parations de voitures",
    "sg:phone":"+32 71 78 81 53",
    "sg:postcode":"5190",
    "sg:province":"Namur",
    "wof:name":"New Vid\u00c9o Flash",
    "wof:placetype":"venue"
},
  "geometry": {"coordinates":[4.6906380653,50.4502105713],"type":"Point"}
}