{
  "type": "Feature",
  "properties": {
    "iso:country":"BE",
    "sg:address":"Keibergstraat 13",
    "sg:city":"Lierde (sint-martens-lierde)",
    "sg:classifiers":[
        {
            "category":"Shopping",
            "subcategory":"Clothing, Apparel, & Fashions",
            "type":"Retail Goods"
        }
    ],
    "sg:phone":"+32 54 41 32 44",
    "sg:postcode":"9572",
    "sg:province":"Oost-Vlaanderen",
    "sg:tags":[
        "boutique"
    ],
    "wof:name":"Ghyssels Kleding Nv",
    "wof:placetype":"venue"
},
  "geometry": {"coordinates":[3.8248550892,50.803730011],"type":"Point"}
}