{
  "type": "Feature",
  "properties": {
    "iso:country":"BE",
    "sg:address":"Ave De Hinnisdael 21",
    "sg:city":"Bruxelles",
    "sg:classifiers":[
        {
            "category":"Banks & Credit Unions",
            "subcategory":"Bank",
            "type":"Services"
        }
    ],
    "sg:phone":"+32 2 782 15 35",
    "sg:postcode":"1150",
    "sg:province":"Bruxelles-Capitale",
    "wof:name":"Banque Nagelmackers Sa",
    "wof:placetype":"venue"
},
  "geometry": {"coordinates":[4.4654479027,50.8412857056],"type":"Point"}
}