{
  "type": "Feature",
  "properties": {
    "addr:full":"Toekomststraat 9c Nijlen (kessel) Antwerpen 2560",
    "addr:housenumber":"9c",
    "addr:postcode":"2560",
    "addr:street":"Toekomststraat",
    "iso:country":"BE",
    "sg:address":"Toekomststraat 9c",
    "sg:city":"Nijlen (kessel)",
    "sg:orig_category":"Non-Classified Establishments",
    "sg:phone":"+32 3 480 12 97",
    "sg:postcode":"2560",
    "sg:province":"Antwerpen",
    "wof:name":"Prinzie M",
    "wof:placetype":"venue"
},
  "geometry": {"coordinates":[4.6258292198,51.1398391724],"type":"Point"}
}