{
  "type": "Feature",
  "properties": {
    "addr:full":"Maloulaan 3 Ieper West-Vlaanderen 8900",
    "addr:housenumber":"3",
    "addr:postcode":"8900",
    "addr:street":"Maloulaan",
    "iso:country":"BE",
    "sg:address":"Maloulaan 3",
    "sg:city":"Ieper",
    "sg:classifiers":[
        {
            "category":"Professional",
            "subcategory":"Art Services",
            "type":"Services"
        }
    ],
    "sg:phone":"+32 57 20 18 27",
    "sg:postcode":"8900",
    "sg:province":"West-Vlaanderen",
    "sg:tags":[
        "-",
        "painter",
        "artist"
    ],
    "wof:name":"De Bliquy",
    "wof:placetype":"venue"
},
  "geometry": {"coordinates":[2.8775579929,50.8493881226],"type":"Point"}
}