{
  "type": "Feature",
  "properties": {
    "iso:country":"BE",
    "sg:address":"Industrieweg 24",
    "sg:city":"Westmalle",
    "sg:classifiers":[
        {
            "category":"Military Area",
            "subcategory":"Air Force Base",
            "type":"Public Place"
        }
    ],
    "sg:phone":"+32 3 312 43 99",
    "sg:postcode":"2390",
    "sg:province":"Antwerpen",
    "sg:tags":[
        "precast",
        "component",
        "concrete"
    ],
    "wof:name":"Debo-welfsels B.v.b.a.",
    "wof:placetype":"venue"
},
  "geometry": {"coordinates":[4.7013349533,51.2927932739],"type":"Point"}
}