{
  "type": "Feature",
  "properties": {
    "iso:country":"BE",
    "sg:address":"Einde 3",
    "sg:city":"Sint-martens-voeren/fouron-saint-martin",
    "sg:orig_category":"Installation de menuiserie en bois and plastique",
    "sg:phone":"+32 4 381 14 14",
    "sg:postcode":"3790",
    "sg:province":"Limburg",
    "wof:name":"Philippe Pleyers",
    "wof:placetype":"venue"
},
  "geometry": {"coordinates":[5.7123317719,50.7558288574],"type":"Point"}
}