{
  "type": "Feature",
  "properties": {
    "iso:country":"BE",
    "sg:address":"Rue Forgeur 6b62",
    "sg:city":"Li\u00c8ge",
    "sg:orig_category":"Artsen and specialisten",
    "sg:phone":"+32 4 223 48 49",
    "sg:postcode":"4000",
    "sg:province":"Li\u00e8ge",
    "wof:name":"Pierre Henrard",
    "wof:placetype":"venue"
},
  "geometry": {"coordinates":[5.571023941,50.6348800659],"type":"Point"}
}