{
  "type": "Feature",
  "properties": {
    "addr:full":"Vestenstraat 50 Tervuren Vlaams-Brabant 3080",
    "addr:housenumber":"50",
    "addr:postcode":"3080",
    "addr:street":"Vestenstraat",
    "iso:country":"BE",
    "sg:address":"Vestenstraat 50",
    "sg:city":"Tervuren",
    "sg:orig_category":"Goederenvervoer over de weg",
    "sg:phone":"+32 2 767 42 48",
    "sg:postcode":"3080",
    "sg:province":"Vlaams-Brabant",
    "wof:name":"Smets G & B",
    "wof:placetype":"venue"
},
  "geometry": {"coordinates":[4.5051779747,50.8212661743],"type":"Point"}
}