{
  "type": "Feature",
  "properties": {
    "iso:country":"BE",
    "sg:address":"Place Emile Vandervelde 6",
    "sg:city":"Bernissart (blaton)",
    "sg:classifiers":[
        {
            "category":"Bars & Pubs",
            "type":"Food & Drink"
        }
    ],
    "sg:phone":"+32 69 57 75 91",
    "sg:postcode":"7321",
    "sg:province":"Hainaut",
    "wof:name":"Corsica (le)",
    "wof:placetype":"venue"
},
  "geometry": {"coordinates":[3.6898729801,50.4766578674],"type":"Point"}
}