{
  "type": "Feature",
  "properties": {
    "addr:full":"Bredabaan 37 Merksem Antwerpen 2170",
    "addr:housenumber":"37",
    "addr:postcode":"2170",
    "addr:street":"Bredabaan",
    "iso:country":"BE",
    "sg:address":"Bredabaan 37",
    "sg:city":"Merksem",
    "sg:orig_category":"Jardinage",
    "sg:phone":"+32 3 290 62 79",
    "sg:postcode":"2170",
    "sg:province":"Antwerpen",
    "wof:name":"Peter Heyens Tuinonderhoud",
    "wof:placetype":"venue"
},
  "geometry": {"coordinates":[4.4315180779,51.2376708984],"type":"Point"}
}