{
  "type": "Feature",
  "properties": {
    "iso:country":"BE",
    "sg:address":"Strateneinde 5",
    "sg:city":"Vorselaar",
    "sg:orig_category":"Eleveurs de bovins",
    "sg:phone":"+32 14 51 41 33",
    "sg:postcode":"2290",
    "sg:province":"Antwerpen",
    "wof:name":"Jozef Van Den Broeck",
    "wof:placetype":"venue"
},
  "geometry": {"coordinates":[4.7543201447,51.2290611267],"type":"Point"}
}