{
  "type": "Feature",
  "properties": {
    "iso:country":"BE",
    "sg:address":"Rue Du Sart 10",
    "sg:city":"Ittre",
    "sg:classifiers":[
        {
            "category":"Social Services",
            "subcategory":"Child Care",
            "type":"Services"
        }
    ],
    "sg:phone":"+32 67 64 62 52",
    "sg:postcode":"1460",
    "sg:province":"Brabant Wallon",
    "sg:tags":[
        "home"
    ],
    "wof:name":"Bauque (la)",
    "wof:placetype":"venue"
},
  "geometry": {"coordinates":[4.2406640053,50.6603240967],"type":"Point"}
}