{
  "type": "Feature",
  "properties": {
    "iso:country":"BE",
    "sg:address":"Ri\u00c9ssonsart 63ba",
    "sg:city":"Olne",
    "sg:orig_category":"Location de machines-outils and de mat\u00e9riel de bricolage",
    "sg:phone":"+32 4 355 02 29",
    "sg:postcode":"4877",
    "sg:province":"Li\u00e8ge",
    "wof:name":"M.f.a. Management",
    "wof:placetype":"venue"
},
  "geometry": {"coordinates":[5.7070951462,50.6008262634],"type":"Point"}
}