{
  "type": "Feature",
  "properties": {
    "iso:country":"BE",
    "sg:address":"Stappaertblokstraat 5a",
    "sg:city":"Tremelo (baal)",
    "sg:classifiers":[
        {
            "category":"Manufacturing",
            "subcategory":"Rubber & Plastics",
            "type":"Manufacturing & Wholesale Goods"
        }
    ],
    "sg:phone":"+32 16 60 84 28",
    "sg:postcode":"3128",
    "sg:province":"Vlaams-Brabant",
    "sg:tags":[
        "bag"
    ],
    "wof:name":"Polypak Europe",
    "wof:placetype":"venue"
},
  "geometry": {"coordinates":[4.7365150452,50.9957427979],"type":"Point"}
}