{
  "type": "Feature",
  "properties": {
    "iso:country":"BE",
    "sg:address":"Marie-jos\u00c9straat 40",
    "sg:city":"Koksijde",
    "sg:orig_category":"Instituts de beaut\u00e9",
    "sg:phone":"+32 477 43 66 36",
    "sg:postcode":"8670",
    "sg:province":"West-Vlaanderen",
    "wof:name":"Sofie Suber",
    "wof:placetype":"venue"
},
  "geometry": {"coordinates":[2.6403999329,51.1233901978],"type":"Point"}
}