{
  "type": "Feature",
  "properties": {
    "addr:full":"Lieve Moenssenslaan 1 Dilsen-stokkem Limburg 3650",
    "addr:housenumber":"1",
    "addr:postcode":"3650",
    "addr:street":"Moenssenslaan",
    "iso:country":"BE",
    "sg:address":"Lieve Moenssenslaan 1",
    "sg:city":"Dilsen-stokkem",
    "sg:orig_category":"Vakantiedorpen",
    "sg:phone":"+32 89 75 52 83",
    "sg:postcode":"3650",
    "sg:province":"Limburg",
    "wof:name":"De Kalei",
    "wof:placetype":"venue"
},
  "geometry": {"coordinates":[5.685988903,51.0240936279],"type":"Point"}
}