{
  "type": "Feature",
  "properties": {
    "addr:full":"Meerminlaan 22 Knokke-heist (knokke) West-Vlaanderen 8300",
    "addr:housenumber":"22",
    "addr:postcode":"8300",
    "addr:street":"Meerminlaan",
    "iso:country":"BE",
    "sg:address":"Meerminlaan 22",
    "sg:city":"Knokke-heist (knokke)",
    "sg:classifiers":[
        {
            "category":"Travel",
            "subcategory":"Hotels & Motels",
            "type":"Entertainment"
        }
    ],
    "sg:phone":"+32 50 60 59 64",
    "sg:postcode":"8300",
    "sg:province":"West-Vlaanderen",
    "wof:name":"Hotel Albert Plage",
    "wof:placetype":"venue"
},
  "geometry": {"coordinates":[3.287694931,51.3467254639],"type":"Point"}
}