{
  "type": "Feature",
  "properties": {
    "iso:country":"BE",
    "sg:address":"Bredestraat 33",
    "sg:city":"Overijse",
    "sg:orig_category":"Producteurs de fruits",
    "sg:phone":"+32 2 687 40 52",
    "sg:postcode":"3090",
    "sg:province":"Vlaams-Brabant",
    "wof:name":"Frans Nedergedaelt",
    "wof:placetype":"venue"
},
  "geometry": {"coordinates":[4.5258011818,50.7585067749],"type":"Point"}
}