{
  "type": "Feature",
  "properties": {
    "addr:full":"Rue Du Palais 147b1 Verviers Li\u00e8ge 4800",
    "addr:housenumber":"147b1",
    "addr:postcode":"4800",
    "addr:street":"Rue Du Palais",
    "iso:country":"BE",
    "sg:address":"Rue Du Palais 147b1",
    "sg:city":"Verviers",
    "sg:orig_category":"Alternatieve geneeskunde",
    "sg:phone":"+32 87 22 86 66",
    "sg:postcode":"4800",
    "sg:province":"Li\u00e8ge",
    "wof:name":"Ph. Hansroul",
    "wof:placetype":"venue"
},
  "geometry": {"coordinates":[5.8574819565,50.5891304016],"type":"Point"}
}