{
  "type": "Feature",
  "properties": {
    "iso:country":"BE",
    "sg:address":"Place Monseu 26",
    "sg:city":"Ciney",
    "sg:classifiers":[
        {
            "category":"Bars & Pubs",
            "type":"Food & Drink"
        }
    ],
    "sg:phone":"+32 83 21 73 06",
    "sg:postcode":"5590",
    "sg:province":"Namur",
    "wof:name":"Rivers Side",
    "wof:placetype":"venue"
},
  "geometry": {"coordinates":[5.0992779732,50.2959480286],"type":"Point"}
}