{
  "type": "Feature",
  "properties": {
    "iso:country":"BE",
    "sg:address":"Hamsesteenweg 76",
    "sg:city":"Leopoldsburg",
    "sg:orig_category":"Elektrische installaties voor woningen",
    "sg:phone":"+32 11 34 31 78",
    "sg:postcode":"3971",
    "sg:province":"Limburg",
    "wof:name":"Johan Koopmans",
    "wof:placetype":"venue"
},
  "geometry": {"coordinates":[5.2148861885,51.1073608398],"type":"Point"}
}