{
  "type": "Feature",
  "properties": {
    "iso:country":"BE",
    "sg:address":"L\u00e9once Roelsstraat 11",
    "sg:city":"Zottegem",
    "sg:classifiers":[
        {
            "category":"Health Services",
            "subcategory":"Health Practitioner",
            "type":"Services"
        }
    ],
    "sg:phone":"+32 9 360 61 74",
    "sg:postcode":"9620",
    "sg:province":"Oost-Vlaanderen",
    "sg:tags":[
        "physiotherapist"
    ],
    "wof:name":"De Coninck Mieke",
    "wof:placetype":"venue"
},
  "geometry": {"coordinates":[3.8129940033,50.8654785156],"type":"Point"}
}