{
  "type": "Feature",
  "properties": {
    "addr:full":"Rue De La Roche 53 Hotton (hampteau) Luxembourg 6990",
    "addr:housenumber":"53",
    "addr:postcode":"6990",
    "addr:street":"Rue De La",
    "iso:country":"BE",
    "sg:address":"Rue De La Roche 53",
    "sg:city":"Hotton (hampteau)",
    "sg:classifiers":[
        {
            "category":"Food & Beverages",
            "subcategory":"Meat & Fish",
            "type":"Retail Goods"
        }
    ],
    "sg:phone":"+32 84 46 62 49",
    "sg:postcode":"6990",
    "sg:province":"Luxembourg",
    "sg:tags":[
        "-",
        "livestock"
    ],
    "wof:name":"Paquet",
    "wof:placetype":"venue"
},
  "geometry": {"coordinates":[5.4725761414,50.2577056885],"type":"Point"}
}