{
  "type": "Feature",
  "properties": {
    "addr:full":"Sint-lievenslaan 38 Gent Oost-Vlaanderen 9000",
    "addr:housenumber":"38",
    "addr:postcode":"9000",
    "addr:street":"Sint-Lievenslaan;Oost-Vlaanderen",
    "iso:country":"BE",
    "sg:address":"Sint-lievenslaan 38",
    "sg:city":"Gent",
    "sg:classifiers":[
        {
            "category":"Food & Beverages",
            "subcategory":"Groceries & Convenience Stores",
            "type":"Retail Goods"
        }
    ],
    "sg:phone":"+32 9 225 96 79",
    "sg:postcode":"9000",
    "sg:province":"Oost-Vlaanderen",
    "sg:tags":[
        "grocer"
    ],
    "wof:name":"Never Closed Bvba",
    "wof:placetype":"venue"
},
  "geometry": {"coordinates":[3.7355298996,51.0415916443],"type":"Point"}
}