{
  "type": "Feature",
  "properties": {
    "addr:full":"Rode Kruislaan 54 Bree Limburg 3960",
    "addr:housenumber":"54",
    "addr:postcode":"3960",
    "addr:street":"Rode Kruislaan",
    "iso:country":"BE",
    "sg:address":"Rode Kruislaan 54",
    "sg:city":"Bree",
    "sg:classifiers":[
        {
            "category":"Professional",
            "subcategory":"Computer Services",
            "type":"Services"
        }
    ],
    "sg:phone":"+32 89 46 13 32",
    "sg:postcode":"3960",
    "sg:province":"Limburg",
    "sg:tags":[
        "-",
        "processing",
        "data"
    ],
    "wof:name":"Mobital Kantooruitrusting Nv",
    "wof:placetype":"venue"
},
  "geometry": {"coordinates":[5.6057062149,51.1376342773],"type":"Point"}
}