{
  "type": "Feature",
  "properties": {
    "iso:country":"BE",
    "sg:address":"Korte Mussepi 17",
    "sg:city":"Sint-katelijne-waver",
    "sg:orig_category":"Artiesten and kunstenaars",
    "sg:phone":"+32 15 20 92 18",
    "sg:postcode":"2860",
    "sg:province":"Antwerpen",
    "wof:name":"Jenny Tanghe",
    "wof:placetype":"venue"
},
  "geometry": {"coordinates":[4.5022611618,51.0572090149],"type":"Point"}
}