{
  "type": "Feature",
  "properties": {
    "addr:full":"Chemin D'hameau 128 Ham-sur-heure-nalinnes (ham-sur-heure) Hainaut 6120",
    "addr:housenumber":"128",
    "addr:postcode":"6120",
    "addr:street":"Chemin D'Hameau",
    "iso:country":"BE",
    "sg:address":"Chemin D'hameau 128",
    "sg:city":"Ham-sur-heure-nalinnes (ham-sur-heure)",
    "sg:classifiers":[
        {
            "category":"Health Services",
            "subcategory":"Health Practitioner",
            "type":"Services"
        }
    ],
    "sg:phone":"+32 71 21 62 92",
    "sg:postcode":"6120",
    "sg:province":"Hainaut",
    "sg:tags":[
        "physiotherapist"
    ],
    "wof:name":"Vanesse L",
    "wof:placetype":"venue"
},
  "geometry": {"coordinates":[4.4057078362,50.3193893433],"type":"Point"}
}