{
  "type": "Feature",
  "properties": {
    "addr:full":"Nijverheidsstraat 17 Londerzeel Vlaams-Brabant 1840",
    "addr:housenumber":"17",
    "addr:postcode":"1840",
    "addr:street":"Nijverheidsstraat",
    "iso:country":"BE",
    "sg:address":"Nijverheidsstraat 17",
    "sg:city":"Londerzeel",
    "sg:orig_category":"Film-, tv- and videoproductie",
    "sg:phone":"+32 52 30 76 17",
    "sg:postcode":"1840",
    "sg:province":"Vlaams-Brabant",
    "wof:name":"Sonotech Belgium",
    "wof:placetype":"venue"
},
  "geometry": {"coordinates":[4.3245778084,51.0114822388],"type":"Point"}
}