{
  "type": "Feature",
  "properties": {
    "addr:full":"Zuster Theresialaan 2 Bornem Antwerpen 2880",
    "addr:housenumber":"2",
    "addr:postcode":"2880",
    "addr:street":"Zuster Theresialaan",
    "iso:country":"BE",
    "sg:address":"Zuster Theresialaan 2",
    "sg:city":"Bornem",
    "sg:orig_category":"Boucheries",
    "sg:phone":"+32 52 34 02 58",
    "sg:postcode":"2880",
    "sg:province":"Antwerpen",
    "wof:name":"Johan Claus",
    "wof:placetype":"venue"
},
  "geometry": {"coordinates":[4.1943311691,51.0623207092],"type":"Point"}
}