{
  "type": "Feature",
  "properties": {
    "iso:country":"BE",
    "sg:address":"Galgestraat 32",
    "sg:city":"Waregem",
    "sg:orig_category":"Architecten",
    "sg:phone":"+32 56 60 76 05",
    "sg:postcode":"8790",
    "sg:province":"West-Vlaanderen",
    "wof:name":"Verschueren Gudrun",
    "wof:placetype":"venue"
},
  "geometry": {"coordinates":[3.450248003,50.8808631897],"type":"Point"}
}