{
  "type": "Feature",
  "properties": {
    "addr:full":"Hendrik Consciencestraat 9-2 Mechelen Antwerpen 2800",
    "addr:housenumber":"9-2",
    "addr:postcode":"2800",
    "addr:street":"Hendrik Consciencestraat",
    "iso:country":"BE",
    "sg:address":"Hendrik Consciencestraat 9-2",
    "sg:city":"Mechelen",
    "sg:classifiers":[
        {
            "category":"Real Estate",
            "subcategory":"Architect",
            "type":"Services"
        }
    ],
    "sg:phone":"+32 15 41 50 52",
    "sg:postcode":"2800",
    "sg:province":"Antwerpen",
    "wof:name":"Reubens K",
    "wof:placetype":"venue"
},
  "geometry": {"coordinates":[4.4825959206,51.0195808411],"type":"Point"}
}