{
  "type": "Feature",
  "properties": {
    "addr:full":"Avenue Henri Lepage 39 Wavre Brabant Wallon 1300",
    "addr:housenumber":"39;1300",
    "addr:street":"Avenue Henri Lepage",
    "iso:country":"BE",
    "sg:address":"Avenue Henri Lepage 39",
    "sg:city":"Wavre",
    "sg:classifiers":[
        {
            "category":"Real Estate",
            "subcategory":"Surveying",
            "type":"Services"
        }
    ],
    "sg:phone":"+32 10 81 63 00",
    "sg:postcode":"1300",
    "sg:province":"Brabant Wallon",
    "sg:tags":[
        "surveyor",
        "land"
    ],
    "wof:name":"Ducamp M",
    "wof:placetype":"venue"
},
  "geometry": {"coordinates":[4.6044120789,50.7203636169],"type":"Point"}
}