{
  "type": "Feature",
  "properties": {
    "addr:full":"Kortrijksesteenweg 431 Gent Oost-Vlaanderen 9000",
    "addr:housenumber":"431",
    "addr:postcode":"9000",
    "addr:street":"Kortrijksesteenweg;Oost-Vlaanderen",
    "iso:country":"BE",
    "sg:address":"Kortrijksesteenweg 431",
    "sg:city":"Gent",
    "sg:orig_category":"Opsporingsdiensten and detectivebureaus",
    "sg:phone":"+32 475 64 72 63",
    "sg:postcode":"9000",
    "sg:province":"Oost-Vlaanderen",
    "wof:name":"Ignace Dedeene",
    "wof:placetype":"venue"
},
  "geometry": {"coordinates":[3.716039896,51.0372085571],"type":"Point"}
}