{
  "type": "Feature",
  "properties": {
    "addr:full":"Gentsestraat 49 Aalst Oost-Vlaanderen 9300",
    "addr:housenumber":"49",
    "addr:postcode":"9300",
    "addr:street":"Gentsestraat",
    "iso:country":"BE",
    "sg:address":"Gentsestraat 49",
    "sg:city":"Aalst",
    "sg:classifiers":[
        {
            "category":"Bars & Pubs",
            "type":"Food & Drink"
        }
    ],
    "sg:phone":"+32 53 60 84 14",
    "sg:postcode":"9300",
    "sg:province":"Oost-Vlaanderen",
    "wof:name":"Ii Mattino",
    "wof:placetype":"venue"
},
  "geometry": {"coordinates":[4.0314130783,50.9378623962],"type":"Point"}
}