{
  "type": "Feature",
  "properties": {
    "addr:full":"Hofdreef 40 Wuustwezel (loenhout) Antwerpen 2990",
    "addr:housenumber":"40",
    "addr:postcode":"2990",
    "addr:street":"Hofdreef",
    "iso:country":"BE",
    "sg:address":"Hofdreef 40",
    "sg:city":"Wuustwezel (loenhout)",
    "sg:classifiers":[
        {
            "category":"Building & Trades",
            "subcategory":"Construction",
            "type":"Services"
        }
    ],
    "sg:phone":"+32 3 669 74 60",
    "sg:postcode":"2990",
    "sg:province":"Antwerpen",
    "sg:tags":[
        "paper",
        "hanger"
    ],
    "wof:name":"Buermans W",
    "wof:placetype":"venue"
},
  "geometry": {"coordinates":[4.6331648827,51.4033203125],"type":"Point"}
}