{
  "type": "Feature",
  "properties": {
    "iso:country":"BE",
    "sg:address":"Chauss\u00c9e De Neufch\u00c2teau 26",
    "sg:city":"Vaux-sur-sure",
    "sg:orig_category":"Begrafeniswezen",
    "sg:phone":"+32 61 25 54 33",
    "sg:postcode":"6640",
    "sg:province":"Luxembourg",
    "wof:name":"Albert Leonard",
    "wof:placetype":"venue"
},
  "geometry": {"coordinates":[5.5705971718,49.9115142822],"type":"Point"}
}