{
  "type": "Feature",
  "properties": {
    "addr:full":"Brugsesteenweg 109 De Haan (wenduine) West-Vlaanderen 8420",
    "addr:housenumber":"109",
    "addr:postcode":"8420",
    "addr:street":"Brugsesteenweg",
    "iso:country":"BE",
    "sg:address":"Brugsesteenweg 109",
    "sg:city":"De Haan (wenduine)",
    "sg:classifiers":[
        {
            "category":"Casinos & Gambling",
            "type":"Entertainment"
        }
    ],
    "sg:phone":"+32 50 43 29 19",
    "sg:postcode":"8420",
    "sg:province":"West-Vlaanderen",
    "wof:name":"Amurent Nv",
    "wof:placetype":"venue"
},
  "geometry": {"coordinates":[3.0876550674,51.2917327881],"type":"Point"}
}