{
  "type": "Feature",
  "properties": {
    "iso:country":"BE",
    "sg:address":"Rue Des Gaulx 40",
    "sg:city":"Courcelles",
    "sg:classifiers":[
        {
            "category":"Food & Beverages",
            "subcategory":"Fruits & Vegetables",
            "type":"Retail Goods"
        }
    ],
    "sg:phone":"+32 71 45 64 49",
    "sg:postcode":"6180",
    "sg:province":"Hainaut",
    "sg:tags":[
        "-"
    ],
    "wof:name":"Wauters P",
    "wof:placetype":"venue"
},
  "geometry": {"coordinates":[4.3662028313,50.458732605],"type":"Point"}
}