{
  "type": "Feature",
  "properties": {
    "addr:full":"Hoogstraat 27 Meeuwen-gruitrode (meeuwen) Limburg 3670",
    "addr:housenumber":"27",
    "addr:postcode":"3670",
    "addr:street":"Hoogstraat",
    "iso:country":"BE",
    "sg:address":"Hoogstraat 27",
    "sg:city":"Meeuwen-gruitrode (meeuwen)",
    "sg:classifiers":[
        {
            "category":"Personal",
            "subcategory":"Beauty Salon",
            "type":"Services"
        }
    ],
    "sg:phone":"+32 11 79 44 21",
    "sg:postcode":"3670",
    "sg:province":"Limburg",
    "sg:tags":[
        "lady",
        "-",
        "hairdressing"
    ],
    "wof:name":"Melotte",
    "wof:placetype":"venue"
},
  "geometry": {"coordinates":[5.5229139328,51.09425354],"type":"Point"}
}