{
  "type": "Feature",
  "properties": {
    "iso:country":"BE",
    "sg:address":"Minderhoutdorp 44",
    "sg:city":"Hoogstraten (minderhout)",
    "sg:classifiers":[
        {
            "category":"Farming",
            "subcategory":"Livestock Farm",
            "type":"Manufacturing & Wholesale Goods"
        }
    ],
    "sg:phone":"+32 3 314 51 80",
    "sg:postcode":"2322",
    "sg:province":"Antwerpen",
    "sg:tags":[
        "buyer"
    ],
    "wof:name":"De Meester P",
    "wof:placetype":"venue"
},
  "geometry": {"coordinates":[4.763384819,51.4160041809],"type":"Point"}
}