{
  "type": "Feature",
  "properties": {
    "iso:country":"BE",
    "sg:address":"Chauss\u00c9e De Li\u00c8ge 47",
    "sg:city":"Welkenraedt",
    "sg:orig_category":"Rusthuizen and serviceflats",
    "sg:phone":"+32 87 44 02 00",
    "sg:postcode":"4841",
    "sg:province":"Li\u00e8ge",
    "wof:name":"Maison Beloeil",
    "wof:placetype":"venue"
},
  "geometry": {"coordinates":[5.930724144,50.6766891479],"type":"Point"}
}