{
  "type": "Feature",
  "properties": {
    "iso:country":"BE",
    "sg:address":"Chauss\u00e9e De Wavre 101",
    "sg:city":"Jodoigne",
    "sg:classifiers":[
        {
            "category":"Building & Trades",
            "subcategory":"Cleaning & Sanitation",
            "type":"Services"
        }
    ],
    "sg:phone":"+32 10 86 79 37",
    "sg:postcode":"1370",
    "sg:province":"Brabant Wallon",
    "sg:tags":[
        "janitor"
    ],
    "wof:name":"Horvath M",
    "wof:placetype":"venue"
},
  "geometry": {"coordinates":[4.8552908897,50.7254600525],"type":"Point"}
}