{
  "type": "Feature",
  "properties": {
    "addr:full":"Rue De Monceau Fontaine 42 Charleroi Hainaut 6031",
    "addr:housenumber":"42",
    "addr:postcode":"6031",
    "addr:street":"Rue De Monceau Fontaine;Hainaut",
    "iso:country":"BE",
    "sg:address":"Rue De Monceau Fontaine 42",
    "sg:city":"Charleroi",
    "sg:orig_category":"Jardinage",
    "sg:phone":"+32 71 31 35 60",
    "sg:postcode":"6031",
    "sg:province":"Hainaut",
    "wof:name":"R\u00c9habil\u00c8s",
    "wof:placetype":"venue"
},
  "geometry": {"coordinates":[4.38022995,50.4121742249],"type":"Point"}
}