{
  "type": "Feature",
  "properties": {
    "iso:country":"BE",
    "sg:address":"Tielstraat 19",
    "sg:city":"Pittem",
    "sg:orig_category":"Opticiens",
    "sg:phone":"+32 51 46 68 61",
    "sg:postcode":"8740",
    "sg:province":"West-Vlaanderen",
    "wof:name":"Goethals Optiek",
    "wof:placetype":"venue"
},
  "geometry": {"coordinates":[3.2652060986,50.9929008484],"type":"Point"}
}