{
  "type": "Feature",
  "properties": {
    "addr:full":"Heide 38 Assenede Oost-Vlaanderen 9968",
    "addr:housenumber":"38",
    "addr:postcode":"9968",
    "addr:street":"Heide",
    "iso:country":"BE",
    "sg:address":"Heide 38",
    "sg:city":"Assenede",
    "sg:orig_category":"Eleveurs de bovins. Eleveurs and marchands de porcs",
    "sg:phone":"+32 9 373 53 26",
    "sg:postcode":"9968",
    "sg:province":"Oost-Vlaanderen",
    "wof:name":"Johan Buysse",
    "wof:placetype":"venue"
},
  "geometry": {"coordinates":[3.6716089249,51.1778564453],"type":"Point"}
}