{
  "type": "Feature",
  "properties": {
    "addr:full":"Brugstraat 36ba2 Bilzen Limburg 3740",
    "addr:postcode":"3740",
    "addr:street":"Brugstraat",
    "iso:country":"BE",
    "sg:address":"Brugstraat 36ba2",
    "sg:city":"Bilzen",
    "sg:orig_category":"Advocaten and juridische adviseurs",
    "sg:phone":"+32 89 41 38 49",
    "sg:postcode":"3740",
    "sg:province":"Limburg",
    "wof:name":"Elsje Gregoor",
    "wof:placetype":"venue"
},
  "geometry": {"coordinates":[5.5187678337,50.8677825928],"type":"Point"}
}