{
  "type": "Feature",
  "properties": {
    "addr:full":"Blauwhuisstraat 14 Izegem West-Vlaanderen 8870",
    "addr:housenumber":"14",
    "addr:postcode":"8870",
    "addr:street":"Blauwhuisstraat",
    "iso:country":"BE",
    "sg:address":"Blauwhuisstraat 14",
    "sg:city":"Izegem",
    "sg:orig_category":"Pain, p\u00e2tisseries and confiseries",
    "sg:phone":"+32 51 30 17 83",
    "sg:postcode":"8870",
    "sg:province":"West-Vlaanderen",
    "wof:name":"Luc Popelier",
    "wof:placetype":"venue"
},
  "geometry": {"coordinates":[3.2240409851,50.915096283],"type":"Point"}
}