{
  "type": "Feature",
  "properties": {
    "iso:country":"BE",
    "sg:address":"Cardijnstraat 11",
    "sg:city":"Zemst",
    "sg:orig_category":"Boucheries",
    "sg:phone":"+32 15 61 47 75",
    "sg:postcode":"1980",
    "sg:province":"Vlaams-Brabant",
    "wof:name":"Slagerij Dany",
    "wof:placetype":"venue"
},
  "geometry": {"coordinates":[4.4556918144,50.9616699219],"type":"Point"}
}