{
  "type": "Feature",
  "properties": {
    "addr:full":"Molenbergstraat 72 Rumst Antwerpen 2840",
    "addr:housenumber":"72",
    "addr:postcode":"2840",
    "addr:street":"Molenbergstraat",
    "iso:country":"BE",
    "sg:address":"Molenbergstraat 72",
    "sg:city":"Rumst",
    "sg:classifiers":[
        {
            "category":"Bars & Pubs",
            "type":"Food & Drink"
        }
    ],
    "sg:phone":"+32 3 888 18 63",
    "sg:postcode":"2840",
    "sg:province":"Antwerpen",
    "wof:name":"Volkshuis",
    "wof:placetype":"venue"
},
  "geometry": {"coordinates":[4.4227199554,51.0796585083],"type":"Point"}
}