{
  "type": "Feature",
  "properties": {
    "iso:country":"BE",
    "sg:address":"Dadizelestraat 4c",
    "sg:city":"Geluwe",
    "sg:orig_category":"Huisdieren and benodigdheden Royal Canin",
    "sg:phone":"+32 56 53 04 09",
    "sg:postcode":"8940",
    "sg:province":"West-Vlaanderen",
    "wof:name":"Salon Kathleen",
    "wof:placetype":"venue"
},
  "geometry": {"coordinates":[3.0795390606,50.8163032532],"type":"Point"}
}