{
  "type": "Feature",
  "properties": {
    "iso:country":"BE",
    "sg:address":"Graaf Van Egmontstraat 15-3",
    "sg:city":"Mechelen",
    "sg:classifiers":[
        {
            "category":"Real Estate",
            "subcategory":"Architect",
            "type":"Services"
        }
    ],
    "sg:phone":"+32 15 45 11 05",
    "sg:postcode":"2800",
    "sg:province":"Antwerpen",
    "wof:name":"Van Der Veken D",
    "wof:placetype":"venue"
},
  "geometry": {"coordinates":[4.4823908806,51.0218772888],"type":"Point"}
}