{
  "type": "Feature",
  "properties": {
    "addr:full":"Avenue Louise 391 Box 25 Bruxelles (ixelles) Bruxelles-Capitale 1050",
    "addr:housenumber":"391 box 25",
    "addr:postcode":"1050",
    "addr:street":"Avenue Louise",
    "iso:country":"BE",
    "sg:address":"Avenue Louise 391 Box 25",
    "sg:city":"Bruxelles (ixelles)",
    "sg:orig_category":"Non-Classified Establishments",
    "sg:phone":"+32 2 527 32 00",
    "sg:postcode":"1050",
    "sg:province":"Bruxelles-Capitale",
    "wof:name":"Plateco Sa",
    "wof:placetype":"venue"
},
  "geometry": {"coordinates":[4.3702440262,50.820148468],"type":"Point"}
}