{
  "type": "Feature",
  "properties": {
    "iso:country":"BE",
    "sg:address":"Geldenakenstraat 22",
    "sg:city":"Linter (orsmaal-gussenhoven)",
    "sg:classifiers":[
        {
            "category":"Bars & Pubs",
            "type":"Food & Drink"
        }
    ],
    "sg:phone":"+32 498 34 06 43",
    "sg:postcode":"3350",
    "sg:province":"Vlaams-Brabant",
    "wof:name":"Dennenhof",
    "wof:placetype":"venue"
},
  "geometry": {"coordinates":[5.0539288521,50.8010063171],"type":"Point"}
}