{
  "type": "Feature",
  "properties": {
    "addr:full":"Sint-jobsesteenweg 570 Ukkel/uccle Bruxelles-Capitale 1180",
    "addr:housenumber":"570",
    "addr:postcode":"1180",
    "addr:street":"Sint-Jobsesteenweg;/",
    "iso:country":"BE",
    "sg:address":"Sint-jobsesteenweg 570",
    "sg:city":"Ukkel/uccle",
    "sg:orig_category":"Huishoudapparaten, televisies and radio's Kapsalons",
    "sg:phone":"+32 2 374 04 78",
    "sg:postcode":"1180",
    "sg:province":"Bruxelles-Capitale",
    "wof:name":"Chord Europe",
    "wof:placetype":"venue"
},
  "geometry": {"coordinates":[4.360806942,50.7928924561],"type":"Point"}
}