{
  "type": "Feature",
  "properties": {
    "addr:full":"Rue Mac Donald 22 Mons Hainaut 7012",
    "addr:housenumber":"22",
    "addr:postcode":"7012",
    "addr:street":"Rue Mac Donald;Hainaut",
    "iso:country":"BE",
    "sg:address":"Rue Mac Donald 22",
    "sg:city":"Mons",
    "sg:orig_category":"Boekhouders",
    "sg:phone":"+32 65 82 53 53",
    "sg:postcode":"7012",
    "sg:province":"Hainaut",
    "wof:name":"Daniel Brouwez",
    "wof:placetype":"venue"
},
  "geometry": {"coordinates":[3.8894600868,50.4481964111],"type":"Point"}
}