{
  "type": "Feature",
  "properties": {
    "addr:full":"A. Ruzettelaan 138b80 Blankenberge West-Vlaanderen 8370",
    "addr:housenumber":"138b80",
    "addr:postcode":"8370",
    "addr:street":"A. Ruzettelaan",
    "iso:country":"BE",
    "sg:address":"A. Ruzettelaan 138b80",
    "sg:city":"Blankenberge",
    "sg:orig_category":"Vakantiehuizen",
    "sg:phone":"+32 50 42 43 10",
    "sg:postcode":"8370",
    "sg:province":"West-Vlaanderen",
    "wof:name":"Era-immo De Roeck",
    "wof:placetype":"venue"
},
  "geometry": {"coordinates":[3.1519010067,51.3210144043],"type":"Point"}
}