{
  "type": "Feature",
  "properties": {
    "addr:full":"Hoogmolenwegel 21 Waregem West-Vlaanderen 8790",
    "addr:housenumber":"21",
    "addr:postcode":"8790",
    "addr:street":"Hoogmolenwegel",
    "iso:country":"BE",
    "sg:address":"Hoogmolenwegel 21",
    "sg:city":"Waregem",
    "sg:orig_category":"D\u00e9taillants en pi\u00e8ces and accessoires de voitures",
    "sg:phone":"+32 56 60 42 12",
    "sg:postcode":"8790",
    "sg:province":"West-Vlaanderen",
    "wof:name":"G.d.w.",
    "wof:placetype":"venue"
},
  "geometry": {"coordinates":[3.4121389389,50.880569458],"type":"Point"}
}