{
  "type": "Feature",
  "properties": {
    "iso:country":"BE",
    "sg:address":"Grand'rue 103",
    "sg:city":"Habay",
    "sg:orig_category":"Herstellingen and onderhoud van auto's",
    "sg:phone":"+32 63 41 18 63",
    "sg:postcode":"6724",
    "sg:province":"Luxembourg",
    "wof:name":"Rectilux",
    "wof:placetype":"venue"
},
  "geometry": {"coordinates":[5.5386037827,49.7265663147],"type":"Point"}
}