{
  "type": "Feature",
  "properties": {
    "addr:full":"Rue Du Ch\u00e2teau Du Fay 6 Sombreffe Namur 5140",
    "addr:housenumber":"6",
    "addr:postcode":"5140",
    "addr:street":"Rue Du Cha\u0302Teau Du Fay",
    "iso:country":"BE",
    "sg:address":"Rue Du Ch\u00e2teau Du Fay 6",
    "sg:city":"Sombreffe",
    "sg:orig_category":"Non-Classified Establishments",
    "sg:phone":"+32 71 56 26 63",
    "sg:postcode":"5140",
    "sg:province":"Namur",
    "wof:name":"De Jelin",
    "wof:placetype":"venue"
},
  "geometry": {"coordinates":[4.593006134,50.4869232178],"type":"Point"}
}