{
  "type": "Feature",
  "properties": {
    "iso:country":"BE",
    "sg:address":"Meersstraat 41",
    "sg:city":"Wachtebeke",
    "sg:orig_category":"Eleveurs de volaille",
    "sg:phone":"+32 9 345 01 07",
    "sg:postcode":"9185",
    "sg:province":"Oost-Vlaanderen",
    "wof:name":"Ostrich Farm Overlede",
    "wof:placetype":"venue"
},
  "geometry": {"coordinates":[3.8610470295,51.1602973938],"type":"Point"}
}