{
  "type": "Feature",
  "properties": {
    "addr:full":"Rue Emile Vandervelde 17 Le Roeulx Hainaut 7070",
    "addr:housenumber":"17",
    "addr:postcode":"7070",
    "addr:street":"Rue Emile Vandervelde",
    "iso:country":"BE",
    "sg:address":"Rue Emile Vandervelde 17",
    "sg:city":"Le Roeulx",
    "sg:orig_category":"Banken and kredietinstellingen",
    "sg:phone":"+32 64 66 20 92",
    "sg:postcode":"7070",
    "sg:province":"Hainaut",
    "wof:name":"Fortis",
    "wof:placetype":"venue"
},
  "geometry": {"coordinates":[4.109372139,50.5034217834],"type":"Point"}
}