{
  "type": "Feature",
  "properties": {
    "iso:country":"BE",
    "sg:address":"Dijkstraat 11-13",
    "sg:city":"Lokeren",
    "sg:orig_category":"V\u00e9hicules automobiles",
    "sg:phone":"+32 9 384 88 11",
    "sg:postcode":"9160",
    "sg:province":"Oost-Vlaanderen",
    "wof:name":"Neyt Trucks",
    "wof:placetype":"venue"
},
  "geometry": {"coordinates":[4.0241069794,51.0924072266],"type":"Point"}
}