{
  "type": "Feature",
  "properties": {
    "iso:country":"BE",
    "sg:address":"Veedijk 56",
    "sg:city":"Turnhout",
    "sg:classifiers":[
        {
            "category":"Professional",
            "subcategory":"Computer Services",
            "type":"Services"
        }
    ],
    "sg:phone":"+32 14 68 39 00",
    "sg:postcode":"2300",
    "sg:province":"Antwerpen",
    "sg:tags":[
        "-",
        "processing",
        "data",
        "software"
    ],
    "wof:name":"L.d. Consulting Nv",
    "wof:placetype":"venue"
},
  "geometry": {"coordinates":[4.9170641899,51.2910270691],"type":"Point"}
}