{
  "type": "Feature",
  "properties": {
    "iso:country":"BE",
    "sg:address":"Everdal 1",
    "sg:city":"Erpe-mere",
    "sg:orig_category":"Woningbouw",
    "sg:phone":"+32 53 62 57 29",
    "sg:postcode":"9420",
    "sg:province":"Oost-Vlaanderen",
    "wof:name":"Van Nuffel Bouwonderneming",
    "wof:placetype":"venue"
},
  "geometry": {"coordinates":[3.9363410473,50.9259567261],"type":"Point"}
}