{
  "type": "Feature",
  "properties": {
    "iso:country":"BE",
    "sg:address":"Mollestraatje 2",
    "sg:city":"Kruishoutem",
    "sg:orig_category":"Eleveurs and marchands de porcs",
    "sg:phone":"+32 9 383 59 38",
    "sg:postcode":"9770",
    "sg:province":"Oost-Vlaanderen",
    "wof:name":"Leonce Van Der Beken",
    "wof:placetype":"venue"
},
  "geometry": {"coordinates":[3.4887421131,50.9008178711],"type":"Point"}
}