{
  "type": "Feature",
  "properties": {
    "addr:full":"Kliniekstraat 56b1 Tienen Vlaams-Brabant 3300",
    "addr:housenumber":"56b1",
    "addr:postcode":"3300",
    "addr:street":"Kliniekstraat",
    "iso:country":"BE",
    "sg:address":"Kliniekstraat 56b1",
    "sg:city":"Tienen",
    "sg:classifiers":[
        {
            "category":"Restaurant",
            "type":"Food & Drink"
        }
    ],
    "sg:phone":"+32 16 82 35 75",
    "sg:postcode":"3300",
    "sg:province":"Vlaams-Brabant",
    "wof:name":"Tearoom Primavera",
    "wof:placetype":"venue"
},
  "geometry": {"coordinates":[4.9323101044,50.8113594055],"type":"Point"}
}