{
  "type": "Feature",
  "properties": {
    "addr:full":"Verbindingsstraat 39 Willebroek Antwerpen 2830",
    "addr:housenumber":"39",
    "addr:postcode":"2830",
    "addr:street":"Verbindingsstraat",
    "iso:country":"BE",
    "sg:address":"Verbindingsstraat 39",
    "sg:city":"Willebroek",
    "sg:orig_category":"Woningbouw",
    "sg:phone":"+32 3 886 62 33",
    "sg:postcode":"2830",
    "sg:province":"Antwerpen",
    "wof:name":"Bouwonderneming De Keyzer",
    "wof:placetype":"venue"
},
  "geometry": {"coordinates":[4.3779377937,51.0538101196],"type":"Point"}
}