{
  "type": "Feature",
  "properties": {
    "addr:full":"Rue De Henri-chapelle 1 Herve Li\u00e8ge 4651",
    "addr:housenumber":"1",
    "addr:postcode":"4651",
    "addr:street":"Rue De Henri-Chapelle",
    "iso:country":"BE",
    "sg:address":"Rue De Henri-chapelle 1",
    "sg:city":"Herve",
    "sg:orig_category":"Slagers",
    "sg:phone":"+32 87 66 01 21",
    "sg:postcode":"4651",
    "sg:province":"Li\u00e8ge",
    "wof:name":"Boucherie Dufrais",
    "wof:placetype":"venue"
},
  "geometry": {"coordinates":[5.8261928558,50.6460227966],"type":"Point"}
}