{
  "type": "Feature",
  "properties": {
    "iso:country":"BE",
    "sg:address":"Rue Du Pr\u00e9 Louis 45a",
    "sg:city":"Weismes (robertville)",
    "sg:classifiers":[
        {
            "category":"Freight",
            "type":"Transportation"
        }
    ],
    "sg:phone":"+32 80 44 77 88",
    "sg:postcode":"4950",
    "sg:province":"Li\u00e8ge",
    "sg:tags":[
        "-",
        "transport"
    ],
    "wof:name":"Toussaint F",
    "wof:placetype":"venue"
},
  "geometry": {"coordinates":[6.1377768517,50.4760055542],"type":"Point"}
}