{
  "type": "Feature",
  "properties": {
    "addr:full":"Corneille De Clercqstr. 57 Jette/jette Bruxelles-Capitale 1090",
    "addr:housenumber":"57",
    "addr:postcode":"1090",
    "addr:street":"Corneille",
    "iso:country":"BE",
    "sg:address":"Corneille De Clercqstr. 57",
    "sg:city":"Jette/jette",
    "sg:orig_category":"Plaatsen van vloer- and muurbekleding Schilders",
    "sg:phone":"+32 2 427 73 57",
    "sg:postcode":"1090",
    "sg:province":"Bruxelles-Capitale",
    "wof:name":"Oltmans",
    "wof:placetype":"venue"
},
  "geometry": {"coordinates":[4.333343029,50.8711624146],"type":"Point"}
}