{
  "type": "Feature",
  "properties": {
    "addr:full":"Kasteelbrakelsesteenweg 492 Halle Vlaams-Brabant 1502",
    "addr:housenumber":"492;1502",
    "addr:street":"Kasteelbrakelsesteenweg",
    "iso:country":"BE",
    "sg:address":"Kasteelbrakelsesteenweg 492",
    "sg:city":"Halle",
    "sg:classifiers":[
        {
            "category":"Cafe",
            "type":"Food & Drink"
        }
    ],
    "sg:phone":"+32 2 356 12 21",
    "sg:postcode":"1502",
    "sg:province":"Vlaams-Brabant",
    "sg:tags":[
        "caf\u00e9s"
    ],
    "wof:name":"Congo Wereldcaf\u00c9",
    "wof:placetype":"venue"
},
  "geometry": {"coordinates":[4.2490649223,50.7034034729],"type":"Point"}
}