{
  "type": "Feature",
  "properties": {
    "iso:country":"BE",
    "sg:address":"Buissestraat 7",
    "sg:city":"Kluisbergen (ruien)",
    "sg:classifiers":[
        {
            "category":"Building & Trades",
            "subcategory":"Electrical",
            "type":"Services"
        }
    ],
    "sg:phone":"+32 55 38 87 56",
    "sg:postcode":"9690",
    "sg:province":"Oost-Vlaanderen",
    "sg:tags":[
        "-",
        "electric",
        "contractor"
    ],
    "wof:name":"De Baere A",
    "wof:placetype":"venue"
},
  "geometry": {"coordinates":[3.4844229221,50.7675666809],"type":"Point"}
}