{
  "type": "Feature",
  "properties": {
    "addr:full":"Emiel Hertecantlaan 18bc Berlare Oost-Vlaanderen 9290",
    "addr:housenumber":"18bc",
    "addr:postcode":"9290",
    "addr:street":"Emiel Hertecantlaan",
    "iso:country":"BE",
    "sg:address":"Emiel Hertecantlaan 18bc",
    "sg:city":"Berlare",
    "sg:orig_category":"Electrom\u00e9nager, t\u00e9l\u00e9visions and radios",
    "sg:phone":"+32 52 42 35 09",
    "sg:postcode":"9290",
    "sg:province":"Oost-Vlaanderen",
    "wof:name":"Marc Wydoodt",
    "wof:placetype":"venue"
},
  "geometry": {"coordinates":[4.0062718391,51.0201454163],"type":"Point"}
}