{
  "type": "Feature",
  "properties": {
    "iso:country":"BE",
    "sg:address":"Rollegemkapelsestraat 28",
    "sg:city":"Ledegem",
    "sg:orig_category":"M\u00e9decins and sp\u00e9cialistes",
    "sg:phone":"+32 56 50 50 91",
    "sg:postcode":"8880",
    "sg:province":"West-Vlaanderen",
    "wof:name":"Robert Carton",
    "wof:placetype":"venue"
},
  "geometry": {"coordinates":[3.1764891148,50.8745613098],"type":"Point"}
}