{
  "type": "Feature",
  "properties": {
    "addr:full":"Bosdel 52b3 Genk Limburg 3600",
    "addr:housenumber":"52b3",
    "addr:postcode":"3600",
    "addr:street":"Bosdel",
    "iso:country":"BE",
    "sg:address":"Bosdel 52b3",
    "sg:city":"Genk",
    "sg:orig_category":"Elektrische installaties voor woningen Geluidsopnames Verhuur televisie- and audiovisuele apparatuur",
    "sg:phone":"+32 89 30 63 13",
    "sg:postcode":"3600",
    "sg:province":"Limburg",
    "wof:name":"Apex",
    "wof:placetype":"venue"
},
  "geometry": {"coordinates":[5.478872776,50.9510955811],"type":"Point"}
}