{
  "type": "Feature",
  "properties": {
    "addr:full":"Wellenstraat 11 Borgloon Limburg 3840",
    "addr:housenumber":"11",
    "addr:postcode":"3840",
    "addr:street":"Wellenstraat",
    "iso:country":"BE",
    "sg:address":"Wellenstraat 11",
    "sg:city":"Borgloon",
    "sg:orig_category":"Rijscholen",
    "sg:phone":"+32 12 74 54 40",
    "sg:postcode":"3840",
    "sg:province":"Limburg",
    "wof:name":"Limburgse Autorijschool",
    "wof:placetype":"venue"
},
  "geometry": {"coordinates":[5.3420357704,50.8034744263],"type":"Point"}
}