{
  "type": "Feature",
  "properties": {
    "addr:full":"Burgemeester Van Acker Wijk G165 Zele Oost-Vlaanderen 9240",
    "addr:housenumber":"g165",
    "addr:postcode":"9240",
    "addr:street":"Burgemeester Van Acker",
    "iso:country":"BE",
    "sg:address":"Burgemeester Van Acker Wijk G165",
    "sg:city":"Zele",
    "sg:orig_category":"Organisation de salons, expositions and bourses",
    "sg:phone":"+32 479 92 10 70",
    "sg:postcode":"9240",
    "sg:province":"Oost-Vlaanderen",
    "wof:name":"Tb Action Timothy",
    "wof:placetype":"venue"
},
  "geometry": {"coordinates":[4.0341830254,51.0622444153],"type":"Point"}
}