{
  "type": "Feature",
  "properties": {
    "addr:full":"Dorp 46 Lille Antwerpen 2275",
    "addr:housenumber":"46",
    "addr:postcode":"2275",
    "addr:street":"Dorp",
    "iso:country":"BE",
    "sg:address":"Dorp 46",
    "sg:city":"Lille",
    "sg:orig_category":"Slagers",
    "sg:phone":"+32 14 88 29 32",
    "sg:postcode":"2275",
    "sg:province":"Antwerpen",
    "wof:name":"Beenhouwerij Vermetten",
    "wof:placetype":"venue"
},
  "geometry": {"coordinates":[4.8350539207,51.2292900085],"type":"Point"}
}