{
  "type": "Feature",
  "properties": {
    "addr:full":"Ringlaan Noord 8 Kuurne West-Vlaanderen 8520",
    "addr:housenumber":"8",
    "addr:postcode":"8520",
    "addr:street":"Ringlaan Noord",
    "iso:country":"BE",
    "sg:address":"Ringlaan Noord 8",
    "sg:city":"Kuurne",
    "sg:orig_category":"Rev\u00eatements pour sols and murs. Peinture. Rev\u00eatements de sols and murs. Eclairage et \u00e9quipements du ",
    "sg:phone":"+32 56 35 78 80",
    "sg:postcode":"8520",
    "sg:province":"West-Vlaanderen",
    "wof:name":"Carpet-land",
    "wof:placetype":"venue"
},
  "geometry": {"coordinates":[3.2589659691,50.8555908203],"type":"Point"}
}