{
  "type": "Feature",
  "properties": {
    "addr:full":"Provinciale Baan 111 Dendermonde Oost-Vlaanderen 9200",
    "addr:housenumber":"111",
    "addr:postcode":"9200",
    "addr:street":"Provinciale Baan;Oost-Vlaanderen",
    "iso:country":"BE",
    "sg:address":"Provinciale Baan 111",
    "sg:city":"Dendermonde",
    "sg:classifiers":[
        {
            "category":"Personal",
            "subcategory":"Beauty Salon",
            "type":"Services"
        }
    ],
    "sg:phone":"+32 52 33 51 11",
    "sg:postcode":"9200",
    "sg:province":"Oost-Vlaanderen",
    "sg:tags":[
        "de",
        "coiffure"
    ],
    "wof:name":"Coiffure Arlette",
    "wof:placetype":"venue"
},
  "geometry": {"coordinates":[4.0983099937,51.0315208435],"type":"Point"}
}