{
  "type": "Feature",
  "properties": {
    "addr:full":"Place J.b. Carnoy 16 Brussel/bruxelles Bruxelles-Capitale 1200",
    "addr:housenumber":"16",
    "addr:postcode":"1200",
    "addr:street":"Place J.B. Carnoy;/",
    "iso:country":"BE",
    "sg:address":"Place J.b. Carnoy 16",
    "sg:city":"Brussel/bruxelles",
    "sg:orig_category":"Activit\u00e9s d\u00b4action sociale sans h\u00e9bergement",
    "sg:phone":"+32 2 764 20 90",
    "sg:postcode":"1200",
    "sg:province":"Bruxelles-Capitale",
    "wof:name":"Sos Enfants-famille U.c.l.",
    "wof:placetype":"venue"
},
  "geometry": {"coordinates":[4.4252500534,50.8438148499],"type":"Point"}
}