{
  "type": "Feature",
  "properties": {
    "addr:full":"Doornikse Heerweg 54 Oudenaarde Oost-Vlaanderen 9700",
    "addr:housenumber":"54",
    "addr:postcode":"9700",
    "addr:street":"Heerweg",
    "iso:country":"BE",
    "sg:address":"Doornikse Heerweg 54",
    "sg:city":"Oudenaarde",
    "sg:classifiers":[
        {
            "category":"Arena",
            "subcategory":"Sports Club",
            "type":"Entertainment"
        }
    ],
    "sg:phone":"+32 55 30 00 39",
    "sg:postcode":"9700",
    "sg:province":"Oost-Vlaanderen",
    "sg:tags":[
        "de"
    ],
    "wof:name":"De Valk",
    "wof:placetype":"venue"
},
  "geometry": {"coordinates":[3.5934500694,50.853679657],"type":"Point"}
}