{
  "type": "Feature",
  "properties": {
    "addr:full":"Patersstraat 13 Eeklo Oost-Vlaanderen 9900",
    "addr:housenumber":"13",
    "addr:postcode":"9900",
    "addr:street":"Patersstraat",
    "iso:country":"BE",
    "sg:address":"Patersstraat 13",
    "sg:city":"Eeklo",
    "sg:orig_category":"Mat\u00e9riel m\u00e9dical and orthop\u00e9dique and proth\u00e8ses Fab",
    "sg:phone":"+32 9 377 26 33",
    "sg:postcode":"9900",
    "sg:province":"Oost-Vlaanderen",
    "wof:name":"Alfred Van Acker",
    "wof:placetype":"venue"
},
  "geometry": {"coordinates":[3.566493988,51.1820831299],"type":"Point"}
}