{
  "type": "Feature",
  "properties": {
    "addr:full":"Hooidonck 1a Zandhoven Antwerpen 2240",
    "addr:housenumber":"1a",
    "addr:postcode":"2240",
    "addr:street":"Hooidonck",
    "iso:country":"BE",
    "sg:address":"Hooidonck 1a",
    "sg:city":"Zandhoven",
    "sg:classifiers":[
        {
            "category":"Professional",
            "subcategory":"Accounting & Tax Preparation",
            "type":"Services"
        }
    ],
    "sg:phone":"+32 475 25 58 16",
    "sg:postcode":"2240",
    "sg:province":"Antwerpen",
    "sg:tags":[
        "accountant"
    ],
    "wof:name":"Van Den Broeck & Co Accountants",
    "wof:placetype":"venue"
},
  "geometry": {"coordinates":[4.6901688576,51.2362747192],"type":"Point"}
}