{
  "type": "Feature",
  "properties": {
    "iso:country":"BE",
    "sg:address":"Antwerpsesteenweg 568",
    "sg:city":"Gent",
    "sg:orig_category":"Blanchisseries and teintureries",
    "sg:phone":"+32 9 228 45 32",
    "sg:postcode":"9040",
    "sg:province":"Oost-Vlaanderen",
    "wof:name":"Wasserij Der Vlaanderen",
    "wof:placetype":"venue"
},
  "geometry": {"coordinates":[3.7534139156,51.0655097961],"type":"Point"}
}