{
  "type": "Feature",
  "properties": {
    "iso:country":"BE",
    "sg:address":"Markt 24",
    "sg:city":"Ruiselede",
    "sg:classifiers":[
        {
            "category":"Banks & Credit Unions",
            "subcategory":"Bank",
            "type":"Services"
        }
    ],
    "sg:phone":"+32 51 68 92 19",
    "sg:postcode":"8080",
    "wof:name":"Aslk-cger Bank",
    "wof:placetype":"venue"
},
  "geometry": {"coordinates":[3.3966720104,51.0416297913],"type":"Point"}
}