{
  "type": "Feature",
  "properties": {
    "addr:full":"Nanofstraat 102 Diepenbeek Limburg 3590",
    "addr:housenumber":"102",
    "addr:postcode":"3590",
    "addr:street":"Nanofstraat",
    "iso:country":"BE",
    "sg:address":"Nanofstraat 102",
    "sg:city":"Diepenbeek",
    "sg:orig_category":"Rev\u00eatements pour sols and murs. Peinture",
    "sg:phone":"+32 11 33 26 15",
    "sg:postcode":"3590",
    "sg:province":"Limburg",
    "wof:name":"Schilderwerken Erik Put",
    "wof:placetype":"venue"
},
  "geometry": {"coordinates":[5.4104070663,50.9045906067],"type":"Point"}
}