{
  "type": "Feature",
  "properties": {
    "addr:full":"Bosmanstraat 31 Lokeren Oost-Vlaanderen 9160",
    "addr:housenumber":"31",
    "addr:postcode":"9160",
    "addr:street":"Bosmanstraat",
    "iso:country":"BE",
    "sg:address":"Bosmanstraat 31",
    "sg:city":"Lokeren",
    "sg:classifiers":[
        {
            "category":"Banks & Credit Unions",
            "subcategory":"Bank",
            "type":"Services"
        }
    ],
    "sg:phone":"+32 9 348 22 48",
    "sg:postcode":"9160",
    "sg:province":"Oost-Vlaanderen",
    "sg:tags":[
        "savings-banks"
    ],
    "wof:name":"Philips-willems M",
    "wof:placetype":"venue"
},
  "geometry": {"coordinates":[3.9923760891,51.1011314392],"type":"Point"}
}