{
  "type": "Feature",
  "properties": {
    "iso:country":"BE",
    "sg:address":"Lupinenweg 8",
    "sg:city":"Keerbergen",
    "sg:classifiers":[
        {
            "category":"Building & Trades",
            "subcategory":"Electrical",
            "type":"Services"
        }
    ],
    "sg:phone":"+32 15 23 68 98",
    "sg:postcode":"3140",
    "sg:province":"Vlaams-Brabant",
    "sg:tags":[
        "electric",
        "-",
        "housewiring",
        "contractor"
    ],
    "wof:name":"Gielen P",
    "wof:placetype":"venue"
},
  "geometry": {"coordinates":[4.6895170212,51.0043029785],"type":"Point"}
}