{
  "type": "Feature",
  "properties": {
    "addr:full":"Vlaamsekaai 29ba Antwerpen Antwerpen 2000",
    "addr:housenumber":"29ba",
    "addr:postcode":"2000",
    "addr:street":"Vlaamsekaai",
    "iso:country":"BE",
    "sg:address":"Vlaamsekaai 29ba",
    "sg:city":"Antwerpen",
    "sg:orig_category":"Artsen and specialisten",
    "sg:phone":"+32 3 238 08 35",
    "sg:postcode":"2000",
    "sg:province":"Antwerpen",
    "wof:name":"Frans Noorman Van Der Dussen",
    "wof:placetype":"venue"
},
  "geometry": {"coordinates":[4.3917989731,51.2103881836],"type":"Point"}
}