{
  "type": "Feature",
  "properties": {
    "addr:full":"Avenue Gustave Latinis 152 Bruxelles (schaerbeek) Bruxelles-Capitale 1030",
    "addr:housenumber":"152",
    "addr:postcode":"1030",
    "addr:street":"Avenue Gustave Latinis",
    "iso:country":"BE",
    "sg:address":"Avenue Gustave Latinis 152",
    "sg:city":"Bruxelles (schaerbeek)",
    "sg:classifiers":[
        {
            "category":"Insurance",
            "subcategory":"Insurance Agent",
            "type":"Services"
        }
    ],
    "sg:phone":"+32 2 216 55 83",
    "sg:postcode":"1030",
    "sg:province":"Bruxelles-Capitale",
    "sg:tags":[
        "broker"
    ],
    "wof:name":"European Consulting Association",
    "wof:placetype":"venue"
},
  "geometry": {"coordinates":[4.3927221298,50.8614234924],"type":"Point"}
}