{
  "type": "Feature",
  "properties": {
    "iso:country":"BE",
    "sg:address":"Rue Du Prince 1",
    "sg:city":"Charleroi",
    "sg:orig_category":"Installation de menuiserie en bois and plastique. Installation de serres, double vitrage and fen\u00eatre",
    "sg:phone":"+32 71 34 33 12",
    "sg:postcode":"6040",
    "sg:province":"Hainaut",
    "wof:name":"Miroiterie - Vitrine De La Coupe",
    "wof:placetype":"venue"
},
  "geometry": {"coordinates":[4.4562048912,50.4200706482],"type":"Point"}
}