{
  "type": "Feature",
  "properties": {
    "iso:country":"BE",
    "sg:address":"Wijkstraat 27a",
    "sg:city":"Diepenbeek",
    "sg:orig_category":"Epiceries",
    "sg:postcode":"3590",
    "sg:province":"Limburg",
    "wof:name":"Automatische Muurwinkel",
    "wof:placetype":"venue"
},
  "geometry": {"coordinates":[5.4261212349,50.9072341919],"type":"Point"}
}