{
  "type": "Feature",
  "properties": {
    "iso:country":"BE",
    "sg:address":"Luikersteenweg 118",
    "sg:city":"Tongeren",
    "sg:classifiers":[
        {
            "category":"Shopping",
            "subcategory":"Antiques",
            "type":"Retail Goods"
        }
    ],
    "sg:phone":"+32 12 23 16 67",
    "sg:postcode":"3700",
    "sg:province":"Limburg",
    "wof:name":"Jorissen W",
    "wof:placetype":"venue"
},
  "geometry": {"coordinates":[5.4612770081,50.7719535828],"type":"Point"}
}