{
  "type": "Feature",
  "properties": {
    "addr:full":"Rue Du Centre 5 Sambreville Namur 5060",
    "addr:housenumber":"5",
    "addr:postcode":"5060",
    "addr:street":"Rue Du Centre",
    "iso:country":"BE",
    "sg:address":"Rue Du Centre 5",
    "sg:city":"Sambreville",
    "sg:orig_category":"Jeux de hasard",
    "sg:phone":"+32 71 77 56 81",
    "sg:postcode":"5060",
    "sg:province":"Namur",
    "wof:name":"Ladbrokes",
    "wof:placetype":"venue"
},
  "geometry": {"coordinates":[4.6285200119,50.4448738098],"type":"Point"}
}