{
  "type": "Feature",
  "properties": {
    "addr:full":"Rue De La Station 172 Rhode-saint-gen\u00e8se Vlaams-Brabant 1640",
    "addr:housenumber":"172",
    "addr:postcode":"1640",
    "addr:street":"Rue De La Station",
    "iso:country":"BE",
    "sg:address":"Rue De La Station 172",
    "sg:city":"Rhode-saint-gen\u00e8se",
    "sg:classifiers":[
        {
            "category":"Insurance",
            "subcategory":"Insurance Agent",
            "type":"Services"
        }
    ],
    "sg:postcode":"1640",
    "sg:province":"Vlaams-Brabant",
    "sg:tags":[
        "broker"
    ],
    "wof:name":"Sohr & Fils Sa",
    "wof:placetype":"venue"
},
  "geometry": {"coordinates":[4.3618597984,50.7474403381],"type":"Point"}
}