{
  "type": "Feature",
  "properties": {
    "addr:full":"Bosstraat 8 Herk-de-stad Limburg 3540",
    "addr:housenumber":"8",
    "addr:postcode":"3540",
    "addr:street":"Bosstraat",
    "iso:country":"BE",
    "sg:address":"Bosstraat 8",
    "sg:city":"Herk-de-stad",
    "sg:orig_category":"Entretien and r\u00e9parations de voitures",
    "sg:phone":"+32 13 55 40 30",
    "sg:postcode":"3540",
    "sg:province":"Limburg",
    "wof:name":"Tony Schepers",
    "wof:placetype":"venue"
},
  "geometry": {"coordinates":[5.2082371712,50.9462356567],"type":"Point"}
}