{
  "type": "Feature",
  "properties": {
    "addr:full":"Rue Des Combattants 48 Charleroi (monceau-sur-sambre) Hainaut 6031",
    "addr:housenumber":"48",
    "addr:postcode":"6031",
    "addr:street":"Rue Des Combattants",
    "iso:country":"BE",
    "sg:address":"Rue Des Combattants 48",
    "sg:city":"Charleroi (monceau-sur-sambre)",
    "sg:classifiers":[
        {
            "category":"Health Services",
            "subcategory":"Dentist",
            "type":"Services"
        }
    ],
    "sg:phone":"+32 71 32 72 56",
    "sg:postcode":"6031",
    "sg:province":"Hainaut",
    "wof:name":"Hubert Fabienne",
    "wof:placetype":"venue"
},
  "geometry": {"coordinates":[4.4224767685,50.4189796448],"type":"Point"}
}