{
  "type": "Feature",
  "properties": {
    "iso:country":"BE",
    "sg:address":"Stokrooieweg 3 Box 2",
    "sg:city":"Hasselt (kuringen)",
    "sg:classifiers":[
        {
            "category":"Health Services",
            "subcategory":"Doctor",
            "type":"Services"
        }
    ],
    "sg:phone":"+32 494 85 88 31",
    "sg:postcode":"3511",
    "sg:province":"Limburg",
    "sg:tags":[
        "psychotherapist",
        "psychoanalyst"
    ],
    "wof:name":"Heck Gabriella",
    "wof:placetype":"venue"
},
  "geometry": {"coordinates":[5.2654781342,50.9544868469],"type":"Point"}
}