{
  "type": "Feature",
  "properties": {
    "iso:country":"BE",
    "sg:address":"Toekomstlaan 9",
    "sg:city":"Herentals",
    "sg:classifiers":[
        {
            "category":"Manufacturing",
            "subcategory":"Tools & Machinery",
            "type":"Manufacturing & Wholesale Goods"
        }
    ],
    "sg:phone":"+32 14 22 47 03",
    "sg:postcode":"2200",
    "sg:province":"Antwerpen",
    "sg:tags":[
        "diamond"
    ],
    "wof:name":"Adamas Belgi\u00eb Nv",
    "wof:placetype":"venue"
},
  "geometry": {"coordinates":[4.8118610382,51.1603050232],"type":"Point"}
}