{
  "type": "Feature",
  "properties": {
    "addr:full":"Paul Gilsonlaan 45-49 Sint-pieters-leeuw Vlaams-Brabant 1601",
    "addr:housenumber":"45-49",
    "addr:postcode":"1601",
    "addr:street":"Paul Gilsonlaan",
    "iso:country":"BE",
    "sg:address":"Paul Gilsonlaan 45-49",
    "sg:city":"Sint-pieters-leeuw",
    "sg:orig_category":"Loodgieterij, verwarming and sanitaire installaties Zwembadinstallatie",
    "sg:phone":"+32 2 331 27 64",
    "sg:postcode":"1601",
    "sg:province":"Vlaams-Brabant",
    "wof:name":"Culligan",
    "wof:placetype":"venue"
},
  "geometry": {"coordinates":[4.3022499084,50.7919006348],"type":"Point"}
}