{
  "type": "Feature",
  "properties": {
    "addr:full":"Rue L\u00e9opold 38 Charleroi (gosselies) Hainaut 6041",
    "addr:housenumber":"38",
    "addr:postcode":"6041",
    "addr:street":"Rue Le\u0301Opold",
    "iso:country":"BE",
    "sg:address":"Rue L\u00e9opold 38",
    "sg:city":"Charleroi (gosselies)",
    "sg:classifiers":[
        {
            "category":"Personal",
            "subcategory":"Beauty Salon",
            "type":"Services"
        }
    ],
    "sg:phone":"+32 71 37 31 54",
    "sg:postcode":"6041",
    "sg:province":"Hainaut",
    "sg:tags":[
        "lady",
        "-",
        "hairdressing"
    ],
    "wof:name":"Cr\u00e9a Style",
    "wof:placetype":"venue"
},
  "geometry": {"coordinates":[4.4427142143,50.4064826965],"type":"Point"}
}