{
  "type": "Feature",
  "properties": {
    "addr:full":"Guldensporenlei 12-14 Turnhout Antwerpen 2300",
    "addr:postcode":"12-14;2300",
    "addr:street":"Guldensporenlei",
    "iso:country":"BE",
    "sg:address":"Guldensporenlei 12-14",
    "sg:city":"Turnhout",
    "sg:classifiers":[
        {
            "category":"Building & Trades",
            "subcategory":"Pest Control",
            "type":"Services"
        }
    ],
    "sg:phone":"+32 14 42 62 09",
    "sg:postcode":"2300",
    "sg:province":"Antwerpen",
    "sg:tags":[
        "painting",
        "contractor"
    ],
    "wof:name":"Kempische Schilderwerken Bvba",
    "wof:placetype":"venue"
},
  "geometry": {"coordinates":[4.9381980896,51.3254508972],"type":"Point"}
}