{
  "type": "Feature",
  "properties": {
    "iso:country":"BE",
    "sg:address":"Chauss\u00c9e De Beaumont 174",
    "sg:city":"Froidchapelle",
    "sg:orig_category":"Meubles D\u00e9taillants, Am\u00e9nagement de B\u00e2timents et de Cuisines",
    "sg:phone":"+32 71 63 34 11",
    "sg:postcode":"6440",
    "sg:province":"Hainaut",
    "wof:name":"Meubles De L'eau D'heure",
    "wof:placetype":"venue"
},
  "geometry": {"coordinates":[4.368885994,50.2282867432],"type":"Point"}
}