{
  "type": "Feature",
  "properties": {
    "iso:country":"BE",
    "sg:address":"Waterstraat 18",
    "sg:city":"Knesselare",
    "sg:orig_category":"Drogisterijen Plaatsen van vloer- and muurbekleding Schilders",
    "sg:phone":"+32 9 374 47 18",
    "sg:postcode":"9910",
    "sg:province":"Oost-Vlaanderen",
    "wof:name":"Hendrik Callier",
    "wof:placetype":"venue"
},
  "geometry": {"coordinates":[3.4310479164,51.1445808411],"type":"Point"}
}