{
  "type": "Feature",
  "properties": {
    "addr:full":"Blauwhuisstraat 1 Harelbeke (hulste) West-Vlaanderen 8531",
    "addr:housenumber":"1",
    "addr:postcode":"8531",
    "addr:street":"Blauwhuisstraat",
    "iso:country":"BE",
    "sg:address":"Blauwhuisstraat 1",
    "sg:city":"Harelbeke (hulste)",
    "sg:classifiers":[
        {
            "category":"Utilities",
            "subcategory":"Fuel Oil & Lpg",
            "type":"Services"
        }
    ],
    "sg:phone":"+32 56 71 35 44",
    "sg:postcode":"8531",
    "sg:province":"West-Vlaanderen",
    "wof:name":"Claerhout-delombaerde Bvba",
    "wof:placetype":"venue"
},
  "geometry": {"coordinates":[3.2903730869,50.8830986023],"type":"Point"}
}