{
  "type": "Feature",
  "properties": {
    "addr:full":"Vissersstraat 87 Moerkerke West-Vlaanderen 8340",
    "addr:housenumber":"87",
    "addr:postcode":"8340",
    "addr:street":"Vissersstraat",
    "iso:country":"BE",
    "sg:address":"Vissersstraat 87",
    "sg:city":"Moerkerke",
    "sg:classifiers":[
        {
            "category":"Military Area",
            "subcategory":"Air Force Base",
            "type":"Public Place"
        }
    ],
    "sg:phone":"+32 50 50 02 14",
    "sg:postcode":"8340",
    "sg:province":"West-Vlaanderen",
    "sg:tags":[
        "arrester",
        "system",
        "lightning"
    ],
    "wof:name":"Heleblitz B.v.b.a.",
    "wof:placetype":"venue"
},
  "geometry": {"coordinates":[3.3389179707,51.2452735901],"type":"Point"}
}