{
  "type": "Feature",
  "properties": {
    "addr:full":"Itali\u00eblei 205 Box 1 Antwerpen Antwerpen 2000",
    "addr:housenumber":"205;1",
    "addr:postcode":"2000",
    "addr:street":"Italie\u0308Lei;Box",
    "iso:country":"BE",
    "sg:address":"Itali\u00eblei 205 Box 1",
    "sg:city":"Antwerpen",
    "sg:classifiers":[
        {
            "category":"Professional",
            "subcategory":"Management & Consulting",
            "type":"Services"
        }
    ],
    "sg:phone":"+32 3 233 84 38",
    "sg:postcode":"2000",
    "sg:province":"Antwerpen",
    "sg:tags":[
        "tax-consultants"
    ],
    "wof:name":"Peirsman H",
    "wof:placetype":"venue"
},
  "geometry": {"coordinates":[4.4167399406,51.2220077515],"type":"Point"}
}