{
  "type": "Feature",
  "properties": {
    "iso:country":"BE",
    "sg:address":"Grootven 2",
    "sg:city":"Heusden-zolder (zolder)",
    "sg:classifiers":[
        {
            "category":"Professional",
            "subcategory":"Lawyer & Legal Services",
            "type":"Services"
        }
    ],
    "sg:postcode":"3550",
    "sg:province":"Limburg",
    "wof:name":"Veulemans Christel",
    "wof:placetype":"venue"
},
  "geometry": {"coordinates":[5.2971229553,51.0105018616],"type":"Point"}
}