{
  "type": "Feature",
  "properties": {
    "iso:country":"BE",
    "sg:address":"Wolvenstraat 18",
    "sg:city":"Kortrijk",
    "sg:orig_category":"Boekhouders",
    "sg:phone":"+32 56 23 58 82",
    "sg:postcode":"8500",
    "sg:province":"West-Vlaanderen",
    "wof:name":"Stefaan Nuytten",
    "wof:placetype":"venue"
},
  "geometry": {"coordinates":[3.2659580708,50.8148918152],"type":"Point"}
}