{
  "type": "Feature",
  "properties": {
    "iso:country":"BE",
    "sg:address":"Doornaardstraat 60",
    "sg:city":"Wommelgem",
    "sg:classifiers":[
        {
            "category":"Health Services",
            "subcategory":"Nursing And Care Facility",
            "type":"Services"
        }
    ],
    "sg:phone":"+32 3 350 08 11",
    "sg:postcode":"2160",
    "sg:province":"Antwerpen",
    "sg:tags":[
        "public"
    ],
    "wof:name":"I.g.e.a.n.",
    "wof:placetype":"venue"
},
  "geometry": {"coordinates":[4.5141510963,51.2112731934],"type":"Point"}
}