{
  "type": "Feature",
  "properties": {
    "iso:country":"BE",
    "sg:address":"Avenue Marius Meur\u00e9e 106",
    "sg:city":"Charleroi (marcinelle)",
    "sg:classifiers":[
        {
            "category":"Organizations",
            "subcategory":"Professional Association",
            "type":"Services"
        }
    ],
    "sg:phone":"+32 71 47 91 92",
    "sg:postcode":"6001",
    "sg:province":"Hainaut",
    "sg:tags":[
        "trade-union",
        "federation"
    ],
    "wof:name":"Syndicat National Des Propri\u00e9taires",
    "wof:placetype":"venue"
},
  "geometry": {"coordinates":[4.4450440407,50.4028358459],"type":"Point"}
}