{
  "type": "Feature",
  "properties": {
    "addr:full":"Bontinckstraat 31 Berlare (overmere) Oost-Vlaanderen 9290",
    "addr:housenumber":"31",
    "addr:postcode":"9290",
    "addr:street":"Bontinckstraat",
    "iso:country":"BE",
    "sg:address":"Bontinckstraat 31",
    "sg:city":"Berlare (overmere)",
    "sg:classifiers":[
        {
            "category":"Professional",
            "subcategory":"Computer Services",
            "type":"Services"
        }
    ],
    "sg:phone":"+32 9 367 97 28",
    "sg:postcode":"9290",
    "sg:province":"Oost-Vlaanderen",
    "sg:tags":[
        "-",
        "processing",
        "data",
        "software"
    ],
    "wof:name":"Micon Bvba",
    "wof:placetype":"venue"
},
  "geometry": {"coordinates":[3.9298799038,51.0685195923],"type":"Point"}
}