{
  "type": "Feature",
  "properties": {
    "addr:full":"Kempenstraat 186 Diepenbeek Limburg 3590",
    "addr:housenumber":"186",
    "addr:postcode":"3590",
    "addr:street":"Kempenstraat",
    "iso:country":"BE",
    "sg:address":"Kempenstraat 186",
    "sg:city":"Diepenbeek",
    "sg:orig_category":"Editeurs de journaux. Editeurs de revues and p\u00e9riodiques",
    "sg:phone":"+32 11 22 06 00",
    "sg:postcode":"3590",
    "sg:province":"Limburg",
    "wof:name":"Uitgeverij Dinolino",
    "wof:placetype":"venue"
},
  "geometry": {"coordinates":[5.4399561882,50.9302368164],"type":"Point"}
}