{
  "type": "Feature",
  "properties": {
    "iso:country":"BE",
    "sg:address":"Rerum Novarumlaan 1",
    "sg:city":"Schilde",
    "sg:orig_category":"Elektrische and elektronische apparatuur Gh",
    "sg:phone":"+32 3 353 87 95",
    "sg:postcode":"2970",
    "sg:province":"Antwerpen",
    "wof:name":"Vanderberghe",
    "wof:placetype":"venue"
},
  "geometry": {"coordinates":[4.5530171394,51.2278022766],"type":"Point"}
}