{
  "type": "Feature",
  "properties": {
    "iso:country":"BE",
    "sg:address":"Bois Chaffoux 16",
    "sg:city":"Herve (battice)",
    "sg:classifiers":[
        {
            "category":"Home & Garden",
            "subcategory":"Kitchen Supply",
            "type":"Retail Goods"
        }
    ],
    "sg:phone":"+32 87 67 59 17",
    "sg:postcode":"4651",
    "sg:province":"Li\u00e8ge",
    "sg:tags":[
        "installation"
    ],
    "wof:name":"Bugni J",
    "wof:placetype":"venue"
},
  "geometry": {"coordinates":[5.8071942329,50.615776062],"type":"Point"}
}