{
  "type": "Feature",
  "properties": {
    "addr:full":"2620 Hemiksem Antwerpen 2620",
    "addr:postcode":"2620;2620",
    "iso:country":"BE",
    "sg:address":"2620",
    "sg:city":"Hemiksem",
    "sg:orig_category":"Pharmaciens",
    "sg:phone":"+32 900 10 500",
    "sg:postcode":"2620",
    "sg:province":"Antwerpen",
    "wof:name":"Pharmacies De Garde",
    "wof:placetype":"venue"
},
  "geometry": {"coordinates":[4.340400219,51.1456489563],"type":"Point"}
}