{
  "type": "Feature",
  "properties": {
    "addr:full":"Rozebeeksestraat 3 Lendelede West-Vlaanderen 8860",
    "addr:housenumber":"3",
    "addr:postcode":"8860",
    "addr:street":"Rozebeeksestraat",
    "iso:country":"BE",
    "sg:address":"Rozebeeksestraat 3",
    "sg:city":"Lendelede",
    "sg:orig_category":"Epiceries",
    "sg:phone":"+32 51 30 41 36",
    "sg:postcode":"8860",
    "sg:province":"West-Vlaanderen",
    "wof:name":"Concordia Corporation",
    "wof:placetype":"venue"
},
  "geometry": {"coordinates":[3.2406110764,50.8871994019],"type":"Point"}
}