{
  "type": "Feature",
  "properties": {
    "iso:country":"BE",
    "sg:address":"Beukenlaan 158",
    "sg:city":"Boom",
    "sg:orig_category":"Display Development",
    "sg:phone":"+32 3 491 04 00",
    "sg:postcode":"2850",
    "sg:province":"Antwerpen",
    "wof:name":"Adda Communications Nv",
    "wof:placetype":"venue"
},
  "geometry": {"coordinates":[4.3819079399,51.1015014648],"type":"Point"}
}