{
  "type": "Feature",
  "properties": {
    "addr:full":"Kareelstr 132 Aalst Oost-Vlaanderen 9300",
    "addr:housenumber":"132",
    "addr:postcode":"9300",
    "iso:country":"BE",
    "sg:address":"Kareelstr 132",
    "sg:city":"Aalst",
    "sg:classifiers":[
        {
            "category":"Banks & Credit Unions",
            "subcategory":"Bank",
            "type":"Services"
        }
    ],
    "sg:phone":"+32 53 70 48 95",
    "sg:postcode":"9300",
    "sg:province":"Oost-Vlaanderen",
    "wof:name":"Sofibank",
    "wof:placetype":"venue"
},
  "geometry": {"coordinates":[4.0318307877,50.9226112366],"type":"Point"}
}