{
  "type": "Feature",
  "properties": {
    "addr:full":"Avenue Du P\u00c9rou 29 Brussel/bruxelles Bruxelles-Capitale 1000",
    "addr:housenumber":"29",
    "addr:postcode":"1000",
    "addr:street":"Avenue Du Pe\u0301Rou;/",
    "iso:country":"BE",
    "sg:address":"Avenue Du P\u00c9rou 29",
    "sg:city":"Brussel/bruxelles",
    "sg:orig_category":"M\u00e9decins and sp\u00e9cialistes",
    "sg:phone":"+32 2 675 30 21",
    "sg:postcode":"1000",
    "sg:province":"Bruxelles-Capitale",
    "wof:name":"Isabelle Sterling",
    "wof:placetype":"venue"
},
  "geometry": {"coordinates":[4.3970122337,50.8005485535],"type":"Point"}
}