{
  "type": "Feature",
  "properties": {
    "addr:full":"Sint-rochuswegel 35 Gavere Oost-Vlaanderen 9890",
    "addr:housenumber":"35",
    "addr:postcode":"9890",
    "addr:street":"Sint-Rochuswegel",
    "iso:country":"BE",
    "sg:address":"Sint-rochuswegel 35",
    "sg:city":"Gavere",
    "sg:classifiers":[
        {
            "category":"Home & Garden",
            "subcategory":"Household Appliances",
            "type":"Retail Goods"
        }
    ],
    "sg:phone":"+32 9 384 30 61",
    "sg:postcode":"9890",
    "sg:province":"Oost-Vlaanderen",
    "sg:tags":[
        "repair",
        "mainten",
        "-",
        "electric"
    ],
    "wof:name":"Bosch-de Smet J-p",
    "wof:placetype":"venue"
},
  "geometry": {"coordinates":[3.6607298851,50.9324607849],"type":"Point"}
}