{
  "type": "Feature",
  "properties": {
    "addr:full":"Obberg 149 Wemmel Vlaams-Brabant 1780",
    "addr:housenumber":"149",
    "addr:postcode":"1780",
    "addr:street":"Obberg;Vlaams-Brabant",
    "iso:country":"BE",
    "sg:address":"Obberg 149",
    "sg:city":"Wemmel",
    "sg:classifiers":[
        {
            "category":"Building & Trades",
            "subcategory":"Landscaping Services",
            "type":"Services"
        }
    ],
    "sg:phone":"+32 2 460 09 96",
    "sg:postcode":"1780",
    "sg:province":"Vlaams-Brabant",
    "sg:tags":[
        "gardening",
        "garden",
        "maintenance"
    ],
    "wof:name":"Van Rode P",
    "wof:placetype":"venue"
},
  "geometry": {"coordinates":[4.2985010147,50.8973693848],"type":"Point"}
}