{
  "type": "Feature",
  "properties": {
    "addr:full":"Pont D\u00b4ile 35 Li\u00c8ge Li\u00e8ge 4000",
    "addr:housenumber":"35",
    "addr:postcode":"4000",
    "addr:street":"Pont D\u00b4Ile",
    "iso:country":"BE",
    "sg:address":"Pont D\u00b4ile 35",
    "sg:city":"Li\u00c8ge",
    "sg:orig_category":"Herenkledingzaken",
    "sg:phone":"+32 4 221 36 46",
    "sg:postcode":"4000",
    "sg:province":"Li\u00e8ge",
    "wof:name":"Maison Maxx",
    "wof:placetype":"venue"
},
  "geometry": {"coordinates":[5.5716018677,50.642414093],"type":"Point"}
}