{
  "type": "Feature",
  "properties": {
    "iso:country":"BE",
    "sg:address":"Pr. Clementinalaan 89",
    "sg:city":"Gent",
    "sg:orig_category":"Erotische Etablissementen",
    "sg:phone":"+32 9 245 37 39",
    "sg:postcode":"9000",
    "sg:province":"Oost-Vlaanderen",
    "wof:name":"Instituut Isis",
    "wof:placetype":"venue"
},
  "geometry": {"coordinates":[3.7144389153,51.0350837708],"type":"Point"}
}