{
  "type": "Feature",
  "properties": {
    "iso:country":"BE",
    "sg:address":"Neuville 34 Box 6",
    "sg:city":"Vielsalm",
    "sg:orig_category":"Non-Classified Establishments",
    "sg:phone":"+32 80 21 74 92",
    "sg:postcode":"6690",
    "sg:province":"Luxembourg",
    "wof:name":"Plasimex",
    "wof:placetype":"venue"
},
  "geometry": {"coordinates":[5.9325327873,50.2807006836],"type":"Point"}
}