{
  "type": "Feature",
  "properties": {
    "addr:full":"Mechelsesteenweg 219 Dendermonde Oost-Vlaanderen 9200",
    "addr:housenumber":"219",
    "addr:postcode":"9200",
    "addr:street":"Mechelsesteenweg;Oost-Vlaanderen",
    "iso:country":"BE",
    "sg:address":"Mechelsesteenweg 219",
    "sg:city":"Dendermonde",
    "sg:classifiers":[
        {
            "category":"Autos & Motor Vehicles",
            "subcategory":"Automobile Sales",
            "type":"Retail Goods"
        }
    ],
    "sg:phone":"+32 52 21 58 65",
    "sg:postcode":"9200",
    "sg:province":"Oost-Vlaanderen",
    "sg:tags":[
        "car",
        "used",
        "-"
    ],
    "wof:name":"Weyn P",
    "wof:placetype":"venue"
},
  "geometry": {"coordinates":[4.1227798462,51.0367012024],"type":"Point"}
}