{
  "type": "Feature",
  "properties": {
    "addr:full":"Lijsterstraat 71 Rijkevorsel Antwerpen 2310",
    "addr:housenumber":"71",
    "addr:postcode":"2310",
    "addr:street":"Lijsterstraat",
    "iso:country":"BE",
    "sg:address":"Lijsterstraat 71",
    "sg:city":"Rijkevorsel",
    "sg:classifiers":[
        {
            "category":"Fast Food",
            "type":"Food & Drink"
        }
    ],
    "sg:phone":"+32 3 314 64 55",
    "sg:postcode":"2310",
    "sg:province":"Antwerpen",
    "sg:tags":[
        "\u00c0",
        "emporter",
        "restaurants"
    ],
    "wof:name":"Fa. Bevers Jos En Paul",
    "wof:placetype":"venue"
},
  "geometry": {"coordinates":[4.7677130699,51.3417282104],"type":"Point"}
}