{
  "type": "Feature",
  "properties": {
    "iso:country":"BE",
    "sg:address":"Bas V\u00e2 8",
    "sg:city":"Manhay (vaux-chavanne)",
    "sg:classifiers":[
        {
            "category":"Building & Trades",
            "subcategory":"Construction",
            "type":"Services"
        }
    ],
    "sg:phone":"+32 86 45 53 71",
    "sg:postcode":"6960",
    "sg:province":"Luxembourg",
    "sg:tags":[
        "fork",
        "lift",
        "truck"
    ],
    "wof:name":"Manutention Service",
    "wof:placetype":"venue"
},
  "geometry": {"coordinates":[5.6754698753,50.291759491],"type":"Point"}
}