{
  "type": "Feature",
  "properties": {
    "addr:full":"Poperingseweg 272 Ieper West-Vlaanderen 8908",
    "addr:housenumber":"272",
    "addr:postcode":"8908",
    "addr:street":"Poperingseweg",
    "iso:country":"BE",
    "sg:address":"Poperingseweg 272",
    "sg:city":"Ieper",
    "sg:classifiers":[
        {
            "category":"Cafe",
            "type":"Food & Drink"
        }
    ],
    "sg:phone":"+32 57 21 80 60",
    "sg:postcode":"8908",
    "sg:province":"West-Vlaanderen",
    "sg:tags":[
        "caf\u00e9s"
    ],
    "wof:name":"Caf\u00c9 Den Engel",
    "wof:placetype":"venue"
},
  "geometry": {"coordinates":[2.8194029331,50.8550033569],"type":"Point"}
}