{
  "type": "Feature",
  "properties": {
    "iso:country":"BE",
    "sg:address":"Excelsiorln 40-42",
    "sg:city":"Zaventem",
    "sg:classifiers":[
        {
            "category":"Wholesale",
            "subcategory":"Drugs",
            "type":"Manufacturing & Wholesale Goods"
        }
    ],
    "sg:phone":"+32 2 712 02 30",
    "sg:postcode":"1930",
    "sg:province":"Vlaams-Brabant",
    "sg:tags":[
        "chemical",
        "pharmaceutical"
    ],
    "wof:name":"Leo Pharma Nv",
    "wof:placetype":"venue"
},
  "geometry": {"coordinates":[4.456592083,50.8830528259],"type":"Point"}
}