{
  "type": "Feature",
  "properties": {
    "iso:country":"BE",
    "sg:address":"Pamelstraat 135",
    "sg:city":"Ninove",
    "sg:orig_category":"Gespecialiseerde residenti\u00eble bouw",
    "sg:phone":"+32 54 33 96 02",
    "sg:postcode":"9400",
    "sg:province":"Oost-Vlaanderen",
    "wof:name":"Daniel Paelinck",
    "wof:placetype":"venue"
},
  "geometry": {"coordinates":[4.0279269218,50.8371162415],"type":"Point"}
}