{
  "type": "Feature",
  "properties": {
    "addr:full":"Lichtelarestraat 53d Lochristi Oost-Vlaanderen 9080",
    "addr:housenumber":"53d",
    "addr:postcode":"9080",
    "addr:street":"Lichtelarestraat",
    "iso:country":"BE",
    "sg:address":"Lichtelarestraat 53d",
    "sg:city":"Lochristi",
    "sg:classifiers":[
        {
            "category":"Utilities",
            "subcategory":"Natural Gas",
            "type":"Services"
        }
    ],
    "sg:phone":"+32 9 355 83 60",
    "sg:postcode":"9080",
    "sg:province":"Oost-Vlaanderen",
    "sg:tags":[
        "welding"
    ],
    "wof:name":"Verloove L",
    "wof:placetype":"venue"
},
  "geometry": {"coordinates":[3.8177659512,51.085231781],"type":"Point"}
}