{
  "type": "Feature",
  "properties": {
    "addr:full":"Schuurhovenveld 3225 Sint-truiden Limburg 3800",
    "addr:postcode":"3225 sint-truiden;3800",
    "iso:country":"BE",
    "sg:address":"Schuurhovenveld 3225",
    "sg:city":"Sint-truiden",
    "sg:orig_category":"Mat\u00e9riaux de construction Gr",
    "sg:phone":"+32 11 67 47 37",
    "sg:postcode":"3800",
    "sg:province":"Limburg",
    "wof:name":"Van Marcke",
    "wof:placetype":"venue"
},
  "geometry": {"coordinates":[5.1863641739,50.8153343201],"type":"Point"}
}