{
  "type": "Feature",
  "properties": {
    "addr:full":"Biesemgoedstraat 2 Aalter Oost-Vlaanderen 9880",
    "addr:housenumber":"2",
    "addr:postcode":"9880",
    "addr:street":"Biesemgoedstraat",
    "iso:country":"BE",
    "sg:address":"Biesemgoedstraat 2",
    "sg:city":"Aalter",
    "sg:orig_category":"Installation de menuiserie en bois and plastique",
    "sg:phone":"+32 9 374 51 19",
    "sg:postcode":"9880",
    "sg:province":"Oost-Vlaanderen",
    "wof:name":"Luc Francoys",
    "wof:placetype":"venue"
},
  "geometry": {"coordinates":[3.4396750927,51.0708885193],"type":"Point"}
}