{
  "type": "Feature",
  "properties": {
    "addr:full":"Rue Victor Boch 42 La Louvi\u00e8re Hainaut 7100",
    "addr:housenumber":"42",
    "addr:postcode":"7100",
    "addr:street":"Rue Victor Boch",
    "iso:country":"BE",
    "sg:address":"Rue Victor Boch 42",
    "sg:city":"La Louvi\u00e8re",
    "sg:classifiers":[
        {
            "category":"Personal",
            "subcategory":"Barber",
            "type":"Services"
        }
    ],
    "sg:phone":"+32 64 22 82 74",
    "sg:postcode":"7100",
    "sg:province":"Hainaut",
    "sg:tags":[
        "gentleman",
        "salon",
        "-",
        "hairdressing"
    ],
    "wof:name":"Jean-marie",
    "wof:placetype":"venue"
},
  "geometry": {"coordinates":[4.1810908318,50.4729537964],"type":"Point"}
}