{
  "type": "Feature",
  "properties": {
    "addr:full":"Rue De Dublin 19 Bruxelles (ixelles) Bruxelles-Capitale 1050",
    "addr:housenumber":"19",
    "addr:postcode":"1050",
    "addr:street":"Rue De Dublin",
    "iso:country":"BE",
    "sg:address":"Rue De Dublin 19",
    "sg:city":"Bruxelles (ixelles)",
    "sg:classifiers":[
        {
            "category":"Sports & Exercise",
            "subcategory":"Gym",
            "type":"Entertainment"
        }
    ],
    "sg:phone":"+32 2 511 58 38",
    "sg:postcode":"1050",
    "sg:province":"Bruxelles-Capitale",
    "sg:tags":[
        "fitness"
    ],
    "wof:name":"Arts-beauty And Services Sa",
    "wof:placetype":"venue"
},
  "geometry": {"coordinates":[4.3672499657,50.8371315002],"type":"Point"}
}