{
  "type": "Feature",
  "properties": {
    "iso:country":"BE",
    "sg:address":"Avenue Des N\u00e9nuphars 12",
    "sg:city":"Bruxelles (auderghem)",
    "sg:orig_category":"Non-Classified Establishments",
    "sg:phone":"+32 2 672 69 94",
    "sg:postcode":"1160",
    "sg:province":"Bruxelles-Capitale",
    "wof:name":"T.d.r.ninaco Sprl",
    "wof:placetype":"venue"
},
  "geometry": {"coordinates":[4.4287037849,50.8214263916],"type":"Point"}
}