{
  "type": "Feature",
  "properties": {
    "iso:country":"BE",
    "sg:address":"Edith Cavellstraat 175",
    "sg:city":"Ukkel/uccle",
    "sg:orig_category":"Banken and kredietinstellingen",
    "sg:phone":"+32 2 375 28 86",
    "sg:postcode":"1180",
    "sg:province":"Bruxelles-Capitale",
    "wof:name":"Fortis",
    "wof:placetype":"venue"
},
  "geometry": {"coordinates":[4.3581609726,50.8054733276],"type":"Point"}
}