{
  "type": "Feature",
  "properties": {
    "addr:full":"Vijverstraat 1b1 Aalst Oost-Vlaanderen 9300",
    "addr:housenumber":"1b1",
    "addr:postcode":"9300",
    "addr:street":"Vijverstraat",
    "iso:country":"BE",
    "sg:address":"Vijverstraat 1b1",
    "sg:city":"Aalst",
    "sg:classifiers":[
        {
            "category":"Manufacturing",
            "subcategory":"Textiles",
            "type":"Manufacturing & Wholesale Goods"
        }
    ],
    "sg:phone":"+32 53 21 62 03",
    "sg:postcode":"9300",
    "sg:province":"Oost-Vlaanderen",
    "wof:name":"Huis Penelope",
    "wof:placetype":"venue"
},
  "geometry": {"coordinates":[4.0429601669,50.9359741211],"type":"Point"}
}