{
  "type": "Feature",
  "properties": {
    "addr:full":"Chemin De Sovet 65 Dinant Namur 5502",
    "addr:housenumber":"65",
    "addr:postcode":"5502",
    "addr:street":"Chemin De Sovet",
    "iso:country":"BE",
    "sg:address":"Chemin De Sovet 65",
    "sg:city":"Dinant",
    "sg:orig_category":"Peinture. Rev\u00eatements pour sols and murs",
    "sg:phone":"+32 82 22 30 61",
    "sg:postcode":"5502",
    "sg:province":"Namur",
    "wof:name":"Jean Briot",
    "wof:placetype":"venue"
},
  "geometry": {"coordinates":[4.9855251312,50.2803192139],"type":"Point"}
}