{
  "type": "Feature",
  "properties": {
    "addr:full":"Steenweg Op Wijchmaal 29 Peer Limburg 3990",
    "addr:housenumber":"29",
    "addr:postcode":"3990",
    "addr:street":"Steenweg Op Wijchmaal",
    "iso:country":"BE",
    "sg:address":"Steenweg Op Wijchmaal 29",
    "sg:city":"Peer",
    "sg:orig_category":"Rev\u00eatements de sols and murs. Rev\u00eatements pour sols and murs",
    "sg:phone":"+32 11 63 20 14",
    "sg:postcode":"3990",
    "sg:province":"Limburg",
    "wof:name":"Hermans",
    "wof:placetype":"venue"
},
  "geometry": {"coordinates":[5.4466547966,51.1324729919],"type":"Point"}
}