{
  "type": "Feature",
  "properties": {
    "iso:country":"BE",
    "sg:address":"Meensesteenweg 258",
    "sg:city":"Bissegem",
    "sg:orig_category":"Siematic. Eclairage et \u00e9quipements du foyer. Fabrication and montage de mobilier. Electrom\u00e9nager, t\u00e9",
    "sg:phone":"+32 56 36 00 66",
    "sg:postcode":"8501",
    "sg:province":"West-Vlaanderen",
    "wof:name":"Studio Rigole Kortrijk",
    "wof:placetype":"venue"
},
  "geometry": {"coordinates":[3.2311820984,50.8246955872],"type":"Point"}
}