{
  "type": "Feature",
  "properties": {
    "iso:country":"BE",
    "sg:address":"Rue Du Pairay 46",
    "sg:city":"Seraing",
    "sg:classifiers":[
        {
            "category":"Autos & Motor Vehicles",
            "subcategory":"Auto Supplies",
            "type":"Retail Goods"
        }
    ],
    "sg:phone":"+32 4 336 84 48",
    "sg:postcode":"4100",
    "sg:province":"Li\u00e8ge",
    "sg:tags":[
        "automobile",
        "alarm",
        "-",
        "system"
    ],
    "wof:name":"Seraing Pneus",
    "wof:placetype":"venue"
},
  "geometry": {"coordinates":[5.5108242035,50.5972671509],"type":"Point"}
}