{
  "type": "Feature",
  "properties": {
    "iso:country":"BE",
    "sg:address":"Vaartdijk 41",
    "sg:city":"Zemst",
    "sg:orig_category":"Film-, tv- and videoproductie",
    "sg:phone":"+32 15 42 08 44",
    "sg:postcode":"1981",
    "sg:province":"Vlaams-Brabant",
    "wof:name":"Jan Depoortere",
    "wof:placetype":"venue"
},
  "geometry": {"coordinates":[4.499434948,51.0053634644],"type":"Point"}
}