{
  "type": "Feature",
  "properties": {
    "addr:full":"Route D'andenne 21 Eghez\u00e9e Namur 5310",
    "addr:housenumber":"21",
    "addr:postcode":"5310",
    "addr:street":"Route D'Andenne;Namur",
    "iso:country":"BE",
    "sg:address":"Route D'andenne 21",
    "sg:city":"Eghez\u00e9e",
    "sg:classifiers":[
        {
            "category":"Health Services",
            "subcategory":"Doctor",
            "type":"Services"
        }
    ],
    "sg:phone":"+32 81 81 18 31",
    "sg:postcode":"5310",
    "sg:province":"Namur",
    "sg:tags":[
        "medicinephysicians",
        "surgeon"
    ],
    "wof:name":"Devyver B",
    "wof:placetype":"venue"
},
  "geometry": {"coordinates":[4.9163408279,50.5910148621],"type":"Point"}
}