{
  "type": "Feature",
  "properties": {
    "iso:country":"BE",
    "sg:address":"Koning Leopold I-straat 19",
    "sg:city":"Kortrijk",
    "sg:orig_category":"Advocaten and juridische adviseurs",
    "sg:phone":"+32 56 22 17 79",
    "sg:postcode":"8500",
    "sg:province":"West-Vlaanderen",
    "wof:name":"G. Van Den Berghe",
    "wof:placetype":"venue"
},
  "geometry": {"coordinates":[3.2595169544,50.8274421692],"type":"Point"}
}