{
  "type": "Feature",
  "properties": {
    "addr:full":"Place Prume 2 Stavelot Li\u00e8ge 4970",
    "addr:housenumber":"2",
    "addr:postcode":"4970",
    "addr:street":"Place Prume",
    "iso:country":"BE",
    "sg:address":"Place Prume 2",
    "sg:city":"Stavelot",
    "sg:orig_category":"Paramedische behandelingen",
    "sg:phone":"+32 80 86 23 55",
    "sg:postcode":"4970",
    "sg:province":"Li\u00e8ge",
    "wof:name":"B. Rensonnet Englebert",
    "wof:placetype":"venue"
},
  "geometry": {"coordinates":[5.931385994,50.3951568604],"type":"Point"}
}