{
  "type": "Feature",
  "properties": {
    "addr:full":"Antwerpsestraat 44 Boom Antwerpen 2850",
    "addr:housenumber":"44",
    "addr:postcode":"2850",
    "addr:street":"Antwerpsestraat",
    "iso:country":"BE",
    "sg:address":"Antwerpsestraat 44",
    "sg:city":"Boom",
    "sg:classifiers":[
        {
            "category":"Health Services",
            "subcategory":"Nursing And Care Facility",
            "type":"Services"
        }
    ],
    "sg:phone":"+32 3 880 18 15",
    "sg:postcode":"2850",
    "sg:province":"Antwerpen",
    "sg:tags":[
        "public"
    ],
    "wof:name":"Gemeentebestuur",
    "wof:placetype":"venue"
},
  "geometry": {"coordinates":[4.365896225,51.0875473022],"type":"Point"}
}