{
  "type": "Feature",
  "properties": {
    "iso:country":"BE",
    "sg:address":"Laie Du Veneur 3",
    "sg:city":"Wavre (limal)",
    "sg:classifiers":[
        {
            "category":"Professional",
            "subcategory":"Engineering",
            "type":"Services"
        }
    ],
    "sg:phone":"+32 10 40 19 25",
    "sg:postcode":"1300",
    "sg:province":"Brabant Wallon",
    "sg:tags":[
        "technical",
        "equipment",
        "offices-"
    ],
    "wof:name":"V.d.c. Engineering Sprl",
    "wof:placetype":"venue"
},
  "geometry": {"coordinates":[4.6116552353,50.7134132385],"type":"Point"}
}