{
  "type": "Feature",
  "properties": {
    "addr:full":"Sitsingenstraat 2 Hoeselt Limburg 3730",
    "addr:housenumber":"2",
    "addr:postcode":"3730",
    "addr:street":"Sitsingenstraat",
    "iso:country":"BE",
    "sg:address":"Sitsingenstraat 2",
    "sg:city":"Hoeselt",
    "sg:orig_category":"Eleveurs and marchands de porcs",
    "sg:phone":"+32 89 51 40 83",
    "sg:postcode":"3730",
    "sg:province":"Limburg",
    "wof:name":"Rene Vandebrouck",
    "wof:placetype":"venue"
},
  "geometry": {"coordinates":[5.4479370117,50.8652038574],"type":"Point"}
}