{
  "type": "Feature",
  "properties": {
    "iso:country":"BE",
    "sg:address":"Rue De Biber 11",
    "sg:city":"Amay",
    "sg:classifiers":[
        {
            "category":"Health Services",
            "subcategory":"Dentist",
            "type":"Services"
        }
    ],
    "sg:phone":"+32 85 31 36 08",
    "sg:postcode":"4540",
    "sg:province":"Li\u00e8ge",
    "wof:name":"Denis Guy",
    "wof:placetype":"venue"
},
  "geometry": {"coordinates":[5.3177499771,50.5469703674],"type":"Point"}
}