{
  "type": "Feature",
  "properties": {
    "iso:country":"BE",
    "sg:address":"Meilaan 215",
    "sg:city":"Sint-lambrechts-woluwe/woluwe-saint-lambert",
    "sg:orig_category":"Kapsalons",
    "sg:phone":"+32 2 770 68 08",
    "sg:postcode":"1200",
    "sg:province":"Bruxelles-Capitale",
    "wof:name":"Dominique Lammens",
    "wof:placetype":"venue"
},
  "geometry": {"coordinates":[4.4128742218,50.8481330872],"type":"Point"}
}