{
  "type": "Feature",
  "properties": {
    "addr:full":"Rue Saint-paul 36 Li\u00c8ge Li\u00e8ge 4000",
    "addr:housenumber":"36",
    "addr:postcode":"4000",
    "addr:street":"Rue Saint-Paul",
    "iso:country":"BE",
    "sg:address":"Rue Saint-paul 36",
    "sg:city":"Li\u00c8ge",
    "sg:orig_category":"Bijouteries and horlogeries. R\u00e9parations d'horloges, montres and bijoux",
    "sg:phone":"+32 4 223 11 54",
    "sg:postcode":"4000",
    "sg:province":"Li\u00e8ge",
    "wof:name":"Louis Willem",
    "wof:placetype":"venue"
},
  "geometry": {"coordinates":[5.5729789734,50.6395683289],"type":"Point"}
}