{
  "type": "Feature",
  "properties": {
    "addr:full":"Nachtegaalstraat 20 Stekene Oost-Vlaanderen 9190",
    "addr:housenumber":"20",
    "addr:postcode":"9190",
    "addr:street":"Nachtegaalstraat",
    "iso:country":"BE",
    "sg:address":"Nachtegaalstraat 20",
    "sg:city":"Stekene",
    "sg:orig_category":"Mat\u00e9riaux de construction Services de Nettoyage and de D\u00e9sinfection. Charpentes and couvertures. Con",
    "sg:phone":"+32 3 779 64 78",
    "sg:postcode":"9190",
    "sg:province":"Oost-Vlaanderen",
    "wof:name":"Rieten Daken Van Gasse",
    "wof:placetype":"venue"
},
  "geometry": {"coordinates":[4.0314679146,51.2182617188],"type":"Point"}
}