{
  "type": "Feature",
  "properties": {
    "iso:country":"BE",
    "sg:address":"Bruggestraat 212",
    "sg:city":"Wingene (zwevezele)",
    "sg:classifiers":[
        {
            "category":"Retail",
            "subcategory":"Funeral Services",
            "type":"Services"
        }
    ],
    "sg:phone":"+32 51 61 10 18",
    "sg:postcode":"8750",
    "sg:province":"West-Vlaanderen",
    "sg:tags":[
        "director"
    ],
    "wof:name":"Denolf Ronny",
    "wof:placetype":"venue"
},
  "geometry": {"coordinates":[3.2230730057,51.0438804626],"type":"Point"}
}