{
  "type": "Feature",
  "properties": {
    "iso:country":"BE",
    "sg:address":"Onderwijsstraat 58",
    "sg:city":"Zaventem",
    "sg:orig_category":"Paramedische behandelingen",
    "sg:phone":"+32 2 720 43 56",
    "sg:postcode":"1930",
    "sg:province":"Vlaams-Brabant",
    "wof:name":"Wit-gele Kruis",
    "wof:placetype":"venue"
},
  "geometry": {"coordinates":[4.4718928337,50.8880882263],"type":"Point"}
}