{
  "type": "Feature",
  "properties": {
    "iso:country":"BE",
    "sg:address":"Avenue Oscar Van Goidtsnoven 100",
    "sg:city":"Bruxelles (forest)",
    "sg:classifiers":[
        {
            "category":"Bakery",
            "type":"Food & Drink"
        }
    ],
    "sg:phone":"+32 2 344 32 37",
    "sg:postcode":"1190",
    "sg:province":"Bruxelles-Capitale",
    "sg:tags":[
        "confectioner",
        "baker"
    ],
    "wof:name":"Altitude 100",
    "wof:placetype":"venue"
},
  "geometry": {"coordinates":[4.3370141983,50.8159103394],"type":"Point"}
}