{
  "type": "Feature",
  "properties": {
    "iso:country":"BE",
    "sg:address":"Handzameplein 21",
    "sg:city":"Kortemark",
    "sg:orig_category":"Apotheken",
    "sg:phone":"+32 51 56 69 27",
    "sg:postcode":"8610",
    "sg:province":"West-Vlaanderen",
    "wof:name":"Franz Debeuckelaere",
    "wof:placetype":"venue"
},
  "geometry": {"coordinates":[3.039757967,51.028629303],"type":"Point"}
}