{
  "type": "Feature",
  "properties": {
    "addr:full":"Rue Maflot 1 Neupre Li\u00e8ge 4120",
    "addr:housenumber":"1",
    "addr:postcode":"4120",
    "addr:street":"Rue Maflot",
    "iso:country":"BE",
    "sg:address":"Rue Maflot 1",
    "sg:city":"Neupre",
    "sg:classifiers":[
        {
            "category":"Cafe",
            "type":"Food & Drink"
        }
    ],
    "sg:phone":"+32 4 371 35 86",
    "sg:postcode":"4120",
    "sg:province":"Li\u00e8ge",
    "sg:tags":[
        "caf\u00e9s"
    ],
    "wof:name":"Caf\u00c9 Des Sports",
    "wof:placetype":"venue"
},
  "geometry": {"coordinates":[5.4815359116,50.5341682434],"type":"Point"}
}