{
  "type": "Feature",
  "properties": {
    "iso:country":"BE",
    "sg:address":"Place Louis Morichar 1",
    "sg:city":"Bruxelles (saint-gilles)",
    "sg:classifiers":[
        {
            "category":"Professional",
            "subcategory":"Management & Consulting",
            "type":"Services"
        }
    ],
    "sg:phone":"+32 2 534 20 62",
    "sg:postcode":"1060",
    "sg:province":"Bruxelles-Capitale",
    "sg:tags":[
        "consultant",
        "agency",
        "advertising"
    ],
    "wof:name":"Agence Europ\u00e9enne De Publicit\u00e9",
    "wof:placetype":"venue"
},
  "geometry": {"coordinates":[4.3480758667,50.8279151917],"type":"Point"}
}