{
  "type": "Feature",
  "properties": {
    "addr:full":"Guido Gezellelaan 4 Kampenhout Vlaams-Brabant 1910",
    "addr:housenumber":"4",
    "addr:postcode":"1910",
    "addr:street":"Guido Gezellelaan",
    "iso:country":"BE",
    "sg:address":"Guido Gezellelaan 4",
    "sg:city":"Kampenhout",
    "sg:orig_category":"Sportclubs Sportterreinen and installaties behalve sportcentra",
    "sg:phone":"+32 16 65 78 14",
    "sg:postcode":"1910",
    "sg:province":"Vlaams-Brabant",
    "wof:name":"K. Kampenhout S.k.",
    "wof:placetype":"venue"
},
  "geometry": {"coordinates":[4.5606379509,50.9436264038],"type":"Point"}
}