{
  "type": "Feature",
  "properties": {
    "iso:country":"BE",
    "sg:address":"Place D'hastedon 4 Box 1",
    "sg:city":"Namur",
    "sg:classifiers":[
        {
            "category":"Professional",
            "subcategory":"Lawyer & Legal Services",
            "type":"Services"
        }
    ],
    "sg:phone":"+32 81 87 98 84",
    "sg:postcode":"5000",
    "sg:province":"Namur",
    "wof:name":"Delvaux Marie-am\u00e9lie",
    "wof:placetype":"venue"
},
  "geometry": {"coordinates":[4.8524532318,50.4707107544],"type":"Point"}
}