{
  "type": "Feature",
  "properties": {
    "iso:country":"BE",
    "sg:address":"Grand-place 12",
    "sg:city":"Ronse/renaix",
    "sg:orig_category":"Protection civile",
    "sg:phone":"+32 55 31 15 60",
    "sg:postcode":"9600",
    "sg:province":"Oost-Vlaanderen",
    "wof:name":"Brandweerkazerne",
    "wof:placetype":"venue"
},
  "geometry": {"coordinates":[3.6020750999,50.7479782104],"type":"Point"}
}