{
  "type": "Feature",
  "properties": {
    "addr:full":"Route De Signeulx 2a Virton Luxembourg 6760",
    "addr:housenumber":"2a",
    "addr:postcode":"6760",
    "addr:street":"Route De Signeulx",
    "iso:country":"BE",
    "sg:address":"Route De Signeulx 2a",
    "sg:city":"Virton",
    "sg:orig_category":"Dancings and bo\u00eetes de nuit",
    "sg:phone":"+32 63 58 35 41",
    "sg:postcode":"6760",
    "sg:province":"Luxembourg",
    "wof:name":"Le Cedex",
    "wof:placetype":"venue"
},
  "geometry": {"coordinates":[5.5347180367,49.5672607422],"type":"Point"}
}