{
  "type": "Feature",
  "properties": {
    "addr:full":"Hofstraat 5-7 Antwerpen Antwerpen 2000",
    "addr:housenumber":"5-7",
    "addr:postcode":"2000",
    "addr:street":"Hofstraat",
    "iso:country":"BE",
    "sg:address":"Hofstraat 5-7",
    "sg:city":"Antwerpen",
    "sg:classifiers":[
        {
            "category":"Arts & Performance",
            "subcategory":"Art Gallery",
            "type":"Entertainment"
        }
    ],
    "sg:phone":"+32 3 226 27 43",
    "sg:postcode":"2000",
    "sg:province":"Antwerpen",
    "wof:name":"Galerie Hilde Metz",
    "wof:placetype":"venue"
},
  "geometry": {"coordinates":[4.4014110565,51.2227897644],"type":"Point"}
}