{
  "type": "Feature",
  "properties": {
    "addr:full":"Markt 43 Stabroek (hoevenen) Antwerpen 2940",
    "addr:housenumber":"43",
    "addr:postcode":"2940",
    "addr:street":"Markt",
    "iso:country":"BE",
    "sg:address":"Markt 43",
    "sg:city":"Stabroek (hoevenen)",
    "sg:classifiers":[
        {
            "category":"Personal",
            "subcategory":"Beauty Salon",
            "type":"Services"
        }
    ],
    "sg:phone":"+32 3 665 37 66",
    "sg:postcode":"2940",
    "sg:province":"Antwerpen",
    "sg:tags":[
        "lady",
        "-",
        "hairdressing"
    ],
    "wof:name":"De Tey",
    "wof:placetype":"venue"
},
  "geometry": {"coordinates":[4.3649148941,51.331943512],"type":"Point"}
}