{
  "type": "Feature",
  "properties": {
    "iso:country":"BE",
    "sg:address":"Dadizeelsestraat 155",
    "sg:city":"Moorslede",
    "sg:orig_category":"Sportclubs",
    "sg:phone":"+32 51 77 23 55",
    "sg:postcode":"8890",
    "sg:province":"West-Vlaanderen",
    "wof:name":"A.m.c. Hinterland",
    "wof:placetype":"venue"
},
  "geometry": {"coordinates":[3.0655760765,50.8744316101],"type":"Point"}
}