{
  "type": "Feature",
  "properties": {
    "iso:country":"BE",
    "sg:address":"Kruipstraat 40",
    "sg:city":"Grimbergen",
    "sg:classifiers":[
        {
            "category":"Building & Trades",
            "subcategory":"Landscaping Services",
            "type":"Services"
        }
    ],
    "sg:phone":"+32 2 270 53 15",
    "sg:postcode":"1850",
    "sg:province":"Vlaams-Brabant",
    "sg:tags":[
        "architect",
        "landscape"
    ],
    "wof:name":"Foulon Els",
    "wof:placetype":"venue"
},
  "geometry": {"coordinates":[4.3687710762,50.9403343201],"type":"Point"}
}