{
  "type": "Feature",
  "properties": {
    "addr:full":"Kriesberg 51 Holsbeek Vlaams-Brabant 3221",
    "addr:housenumber":"51",
    "addr:postcode":"3221",
    "addr:street":"Kriesberg",
    "iso:country":"BE",
    "sg:address":"Kriesberg 51",
    "sg:city":"Holsbeek",
    "sg:orig_category":"Fruitteelt",
    "sg:phone":"+32 16 56 58 60",
    "sg:postcode":"3221",
    "sg:province":"Vlaams-Brabant",
    "wof:name":"Guido Van Passel",
    "wof:placetype":"venue"
},
  "geometry": {"coordinates":[4.856262207,50.949924469],"type":"Point"}
}