{
  "type": "Feature",
  "properties": {
    "iso:country":"BE",
    "sg:address":"Meensesteenweg 409",
    "sg:city":"Roeselare",
    "sg:orig_category":"Voertuigen",
    "sg:phone":"+32 51 24 86 54",
    "sg:postcode":"8800",
    "sg:province":"West-Vlaanderen",
    "wof:name":"Autohandel Chris",
    "wof:placetype":"venue"
},
  "geometry": {"coordinates":[3.1177129745,50.922252655],"type":"Point"}
}