{
  "type": "Feature",
  "properties": {
    "addr:full":"Guido Gezellestraat 7 Poperinge West-Vlaanderen 8970",
    "addr:housenumber":"7",
    "addr:postcode":"8970",
    "addr:street":"Guido Gezellestraat",
    "iso:country":"BE",
    "sg:address":"Guido Gezellestraat 7",
    "sg:city":"Poperinge",
    "sg:classifiers":[
        {
            "category":"Travel",
            "subcategory":"Hotels & Motels",
            "type":"Entertainment"
        }
    ],
    "sg:phone":"+32 57 33 57 25",
    "sg:postcode":"8970",
    "sg:province":"West-Vlaanderen",
    "wof:name":"Recour Hotel",
    "wof:placetype":"venue"
},
  "geometry": {"coordinates":[2.728153944,50.8555183411],"type":"Point"}
}