{
  "type": "Feature",
  "properties": {
    "iso:country":"BE",
    "sg:address":"Rue Prince Baudouin 43",
    "sg:city":"Bruxelles (ganshoren)",
    "sg:classifiers":[
        {
            "category":"Bars & Pubs",
            "type":"Food & Drink"
        }
    ],
    "sg:phone":"+32 2 428 16 21",
    "sg:postcode":"1083",
    "sg:province":"Bruxelles-Capitale",
    "sg:tags":[
        "tavern"
    ],
    "wof:name":"Patio",
    "wof:placetype":"venue"
},
  "geometry": {"coordinates":[4.3223209381,50.8726005554],"type":"Point"}
}