{
  "type": "Feature",
  "properties": {
    "addr:full":"Lange Steenstraat 6 Gent Oost-Vlaanderen 9000",
    "addr:housenumber":"6",
    "addr:postcode":"9000",
    "addr:street":"Lange Steenstraat;Oost-Vlaanderen",
    "iso:country":"BE",
    "sg:address":"Lange Steenstraat 6",
    "sg:city":"Gent",
    "sg:classifiers":[
        {
            "category":"Health Services",
            "subcategory":"Dentist",
            "type":"Services"
        }
    ],
    "sg:phone":"+32 9 224 03 72",
    "sg:postcode":"9000",
    "sg:province":"Oost-Vlaanderen",
    "wof:name":"De Jaeger N",
    "wof:placetype":"venue"
},
  "geometry": {"coordinates":[3.7289888859,51.0568313599],"type":"Point"}
}