{
  "type": "Feature",
  "properties": {
    "addr:full":"Kasteellei 77 Wijnegem Antwerpen 2110",
    "addr:housenumber":"77",
    "addr:postcode":"2110",
    "addr:street":"Kasteellei",
    "iso:country":"BE",
    "sg:address":"Kasteellei 77",
    "sg:city":"Wijnegem",
    "sg:orig_category":"Algemeen secundair onderwijs Kleuter- en basisonderwijs",
    "sg:phone":"+32 3 353 11 30",
    "sg:postcode":"2110",
    "sg:province":"Antwerpen",
    "wof:name":"Vrije Basisschool",
    "wof:placetype":"venue"
},
  "geometry": {"coordinates":[4.5354299545,51.2250404358],"type":"Point"}
}