{
  "type": "Feature",
  "properties": {
    "addr:full":"Tongersestraat 32 Borgloon Limburg 3840",
    "addr:housenumber":"32",
    "addr:postcode":"3840",
    "addr:street":"Tongersestraat",
    "iso:country":"BE",
    "sg:address":"Tongersestraat 32",
    "sg:city":"Borgloon",
    "sg:classifiers":[
        {
            "category":"Bars & Pubs",
            "type":"Food & Drink"
        }
    ],
    "sg:phone":"+32 12 74 14 80",
    "sg:postcode":"3840",
    "sg:province":"Limburg",
    "wof:name":"Atlethiek",
    "wof:placetype":"venue"
},
  "geometry": {"coordinates":[5.350206852,50.8016815186],"type":"Point"}
}