{
  "type": "Feature",
  "properties": {
    "iso:country":"BE",
    "sg:address":"Rue Fosses Berger 45",
    "sg:city":"Olne",
    "sg:classifiers":[
        {
            "category":"Insurance",
            "subcategory":"Insurance Agent",
            "type":"Services"
        }
    ],
    "sg:phone":"+32 4 358 00 52",
    "sg:postcode":"4877",
    "sg:province":"Li\u00e8ge",
    "sg:tags":[
        "broker"
    ],
    "wof:name":"Schmetz A",
    "wof:placetype":"venue"
},
  "geometry": {"coordinates":[5.7295751572,50.5894889832],"type":"Point"}
}