{
  "type": "Feature",
  "properties": {
    "addr:full":"Haachtsesteenweg 226 Brussel Bruxelles-Capitale 1030",
    "addr:housenumber":"226",
    "addr:postcode":"1030",
    "addr:street":"Haachtsesteenweg",
    "iso:country":"BE",
    "sg:address":"Haachtsesteenweg 226",
    "sg:city":"Brussel",
    "sg:classifiers":[
        {
            "category":"Shopping",
            "subcategory":"Pharmacy",
            "type":"Retail Goods"
        }
    ],
    "sg:phone":"+32 2 246 16 11",
    "sg:postcode":"1030",
    "sg:province":"Bruxelles-Capitale",
    "sg:tags":[
        "pharmaceutical"
    ],
    "wof:name":"Novartis Pharma Nv",
    "wof:placetype":"venue"
},
  "geometry": {"coordinates":[4.3721990585,50.8618431091],"type":"Point"}
}