{
  "type": "Feature",
  "properties": {
    "iso:country":"BE",
    "sg:address":"Werchtersesteenweg 157",
    "sg:city":"Begijnendijk",
    "sg:orig_category":"Slagers",
    "sg:phone":"+32 16 52 01 03",
    "sg:postcode":"3130",
    "sg:province":"Vlaams-Brabant",
    "wof:name":"Rony Van Den Bergh",
    "wof:placetype":"venue"
},
  "geometry": {"coordinates":[4.7645401955,50.9856185913],"type":"Point"}
}