{
  "type": "Feature",
  "properties": {
    "iso:country":"BE",
    "sg:address":"Vrijheidweg 4",
    "sg:city":"Tongeren",
    "sg:classifiers":[
        {
            "category":"Food & Beverages",
            "subcategory":"Fruits & Vegetables",
            "type":"Retail Goods"
        }
    ],
    "sg:phone":"+32 12 24 11 28",
    "sg:postcode":"3700",
    "sg:province":"Limburg",
    "sg:tags":[
        "l\u00e9gumes",
        "gr"
    ],
    "wof:name":"Sofrudis",
    "wof:placetype":"venue"
},
  "geometry": {"coordinates":[5.5176749229,50.7862815857],"type":"Point"}
}