{
  "type": "Feature",
  "properties": {
    "iso:country":"BE",
    "sg:address":"Groenstraat 8",
    "sg:city":"Erpe-mere",
    "sg:classifiers":[
        {
            "category":"Cafe",
            "type":"Food & Drink"
        }
    ],
    "sg:phone":"+32 53 80 08 36",
    "sg:postcode":"9420",
    "sg:province":"Oost-Vlaanderen",
    "sg:tags":[
        "caf\u00e9s"
    ],
    "wof:name":"Jouri Van De Sijpe",
    "wof:placetype":"venue"
},
  "geometry": {"coordinates":[3.9836490154,50.9524421692],"type":"Point"}
}