{
  "type": "Feature",
  "properties": {
    "iso:country":"BE",
    "sg:address":"Route De Wallonie 142",
    "sg:city":"Mons (baudour)",
    "sg:classifiers":[
        {
            "category":"Retail",
            "subcategory":"Car Wash",
            "type":"Services"
        }
    ],
    "sg:phone":"+32 65 66 22 42",
    "sg:postcode":"7331",
    "sg:province":"Hainaut",
    "sg:tags":[
        "automobile",
        "washing",
        "-",
        "truck"
    ],
    "wof:name":"Bell'car",
    "wof:placetype":"venue"
},
  "geometry": {"coordinates":[3.832367897,50.4841804504],"type":"Point"}
}