{
  "type": "Feature",
  "properties": {
    "iso:country":"BE",
    "sg:address":"Schansstraat 9",
    "sg:city":"Brasschaat",
    "sg:classifiers":[
        {
            "category":"Arena",
            "subcategory":"Sports Club",
            "type":"Entertainment"
        }
    ],
    "sg:phone":"+32 3 651 63 18",
    "sg:postcode":"2930",
    "sg:province":"Antwerpen",
    "sg:tags":[
        "de"
    ],
    "wof:name":"Octagon",
    "wof:placetype":"venue"
},
  "geometry": {"coordinates":[4.5088729858,51.3049545288],"type":"Point"}
}