{
  "type": "Feature",
  "properties": {
    "addr:full":"Markt 45 Eeklo Oost-Vlaanderen 9900",
    "addr:housenumber":"45",
    "addr:postcode":"9900",
    "addr:street":"Markt",
    "iso:country":"BE",
    "sg:address":"Markt 45",
    "sg:city":"Eeklo",
    "sg:classifiers":[
        {
            "category":"Shopping",
            "subcategory":"Optician",
            "type":"Retail Goods"
        }
    ],
    "sg:phone":"+32 9 377 18 79",
    "sg:postcode":"9900",
    "sg:province":"Oost-Vlaanderen",
    "sg:tags":[
        "-"
    ],
    "wof:name":"Demeester L",
    "wof:placetype":"venue"
},
  "geometry": {"coordinates":[3.5659060478,51.1841812134],"type":"Point"}
}