{
  "type": "Feature",
  "properties": {
    "iso:country":"BE",
    "sg:address":"Rue Des Postes 4",
    "sg:city":"Braine-le-comte",
    "sg:orig_category":"Schoonheidssalons",
    "sg:phone":"+32 67 55 37 19",
    "sg:postcode":"7090",
    "sg:province":"Hainaut",
    "wof:name":"G. Deremiens",
    "wof:placetype":"venue"
},
  "geometry": {"coordinates":[4.1336841583,50.6128921509],"type":"Point"}
}