{
  "type": "Feature",
  "properties": {
    "iso:country":"BE",
    "sg:address":"Rue Frisles 29",
    "sg:city":"Anhee",
    "sg:orig_category":"Eleveurs de bovins",
    "sg:phone":"+32 71 79 97 21",
    "sg:postcode":"5537",
    "sg:province":"Namur",
    "wof:name":"Maurice Crepin",
    "wof:placetype":"venue"
},
  "geometry": {"coordinates":[4.7906718254,50.3368415833],"type":"Point"}
}