{
  "type": "Feature",
  "properties": {
    "addr:full":"Brechtsebaan 2 Brecht Antwerpen 2960",
    "addr:housenumber":"2",
    "addr:postcode":"2960",
    "addr:street":"Brechtsebaan",
    "iso:country":"BE",
    "sg:address":"Brechtsebaan 2",
    "sg:city":"Brecht",
    "sg:orig_category":"Centres de relaxation and bien-\u00eatre",
    "sg:phone":"+32 3 636 41 31",
    "sg:postcode":"2960",
    "sg:province":"Antwerpen",
    "wof:name":"Angie-v.",
    "wof:placetype":"venue"
},
  "geometry": {"coordinates":[4.568253994,51.3041610718],"type":"Point"}
}