{
  "type": "Feature",
  "properties": {
    "addr:full":"Dorp West 17 Zwijndrecht Antwerpen 2070",
    "addr:housenumber":"17",
    "addr:postcode":"2070",
    "addr:street":"Dorp West",
    "iso:country":"BE",
    "sg:address":"Dorp West 17",
    "sg:city":"Zwijndrecht",
    "sg:orig_category":"Installation de menuiserie en bois and plastique",
    "sg:phone":"+32 3 252 68 06",
    "sg:postcode":"2070",
    "sg:province":"Antwerpen",
    "wof:name":"Vergauwen",
    "wof:placetype":"venue"
},
  "geometry": {"coordinates":[4.3328609467,51.2089538574],"type":"Point"}
}