{
  "type": "Feature",
  "properties": {
    "iso:country":"BE",
    "sg:address":"Avenue Mathieu De Jonge 7",
    "sg:city":"Ganshoren",
    "sg:orig_category":"M\u00e9decins and sp\u00e9cialistes",
    "sg:phone":"+32 2 425 98 24",
    "sg:postcode":"1083",
    "sg:province":"Bruxelles-Capitale",
    "wof:name":"Silvia De Briey",
    "wof:placetype":"venue"
},
  "geometry": {"coordinates":[4.3141040802,50.8768501282],"type":"Point"}
}