{
  "type": "Feature",
  "properties": {
    "addr:full":"Rue De L'agriculture 140 Moeskroen/mouscron Hainaut 7700",
    "addr:housenumber":"140",
    "addr:postcode":"7700",
    "addr:street":"Rue De L'Agriculture",
    "iso:country":"BE",
    "sg:address":"Rue De L'agriculture 140",
    "sg:city":"Moeskroen/mouscron",
    "sg:orig_category":"Boissons",
    "sg:phone":"+32 56 33 39 36",
    "sg:postcode":"7700",
    "sg:province":"Hainaut",
    "wof:name":"Vanmarcke",
    "wof:placetype":"venue"
},
  "geometry": {"coordinates":[3.2052919865,50.7481689453],"type":"Point"}
}