{
  "type": "Feature",
  "properties": {
    "addr:full":"Tervurenlaan 270 Sint-pieters-woluwe/woluwe-sai Bruxelles-Capitale 1150",
    "addr:housenumber":"270",
    "addr:postcode":"1150",
    "addr:street":"Tervurenlaan",
    "iso:country":"BE",
    "sg:address":"Tervurenlaan 270",
    "sg:city":"Sint-pieters-woluwe/woluwe-sai",
    "sg:orig_category":"Banken and kredietinstellingen",
    "sg:phone":"+32 2 770 25 09",
    "sg:postcode":"1150",
    "sg:province":"Bruxelles-Capitale",
    "wof:name":"Bbl",
    "wof:placetype":"venue"
},
  "geometry": {"coordinates":[4.4198570251,50.8352546692],"type":"Point"}
}