{
  "type": "Feature",
  "properties": {
    "iso:country":"BE",
    "sg:address":"Rue Neuve 2",
    "sg:city":"Ecaussinnes",
    "sg:orig_category":"Charpentes and couvertures. Construction de maisons",
    "sg:phone":"+32 67 44 26 13",
    "sg:postcode":"7190",
    "sg:province":"Hainaut",
    "wof:name":"Marcel Tenaerts",
    "wof:placetype":"venue"
},
  "geometry": {"coordinates":[4.1639990807,50.5660514832],"type":"Point"}
}