{
  "type": "Feature",
  "properties": {
    "addr:full":"Rue L'eglise St.-etienne 2 Lasne Brabant Wallon 1380",
    "addr:housenumber":"2",
    "addr:postcode":"1380",
    "addr:street":"Rue L'Eglise St.-Etienne",
    "iso:country":"BE",
    "sg:address":"Rue L'eglise St.-etienne 2",
    "sg:city":"Lasne",
    "sg:orig_category":"Rev\u00eatements pour sols and murs. Eclairage et \u00e9quipements du foyer. Peinture",
    "sg:phone":"+32 2 633 17 24",
    "sg:postcode":"1380",
    "sg:province":"Brabant Wallon",
    "wof:name":"Finext",
    "wof:placetype":"venue"
},
  "geometry": {"coordinates":[4.4707221985,50.6959648132],"type":"Point"}
}