{
  "type": "Feature",
  "properties": {
    "addr:full":"Heldenplein 42 Ham Limburg 3945",
    "addr:housenumber":"42",
    "addr:postcode":"3945",
    "addr:street":"Heldenplein",
    "iso:country":"BE",
    "sg:address":"Heldenplein 42",
    "sg:city":"Ham",
    "sg:orig_category":"Textiles. V\u00eatements",
    "sg:phone":"+32 11 34 13 06",
    "sg:postcode":"3945",
    "sg:province":"Limburg",
    "wof:name":"Phildar",
    "wof:placetype":"venue"
},
  "geometry": {"coordinates":[5.1776199341,51.1046104431],"type":"Point"}
}