{
  "type": "Feature",
  "properties": {
    "iso:country":"BE",
    "sg:address":"Kapitein Crespelstraat 50",
    "sg:city":"Elsene/ixelles",
    "sg:orig_category":"Advocaten and juridische adviseurs",
    "sg:phone":"+32 2 511 71 61",
    "sg:postcode":"1050",
    "sg:province":"Bruxelles-Capitale",
    "wof:name":"K. De Cuyper",
    "wof:placetype":"venue"
},
  "geometry": {"coordinates":[4.3584008217,50.8348236084],"type":"Point"}
}