{
  "type": "Feature",
  "properties": {
    "addr:full":"Tentoonstellingslaan 250 Jette Bruxelles-Capitale 1090",
    "addr:housenumber":"250",
    "addr:postcode":"1090",
    "addr:street":"Tentoonstellingslaan",
    "iso:country":"BE",
    "sg:address":"Tentoonstellingslaan 250",
    "sg:city":"Jette",
    "sg:orig_category":"Verhuisdiensten",
    "sg:phone":"+32 2 475 35 30",
    "sg:postcode":"1090",
    "sg:province":"Bruxelles-Capitale",
    "wof:name":"Shurgard Self-storage",
    "wof:placetype":"venue"
},
  "geometry": {"coordinates":[4.3171420097,50.8836898804],"type":"Point"}
}