{
  "type": "Feature",
  "properties": {
    "addr:full":"Holt 84 Bilzen (beverst) Limburg 3740",
    "addr:housenumber":"84",
    "addr:postcode":"3740",
    "addr:street":"Holt",
    "iso:country":"BE",
    "sg:address":"Holt 84",
    "sg:city":"Bilzen (beverst)",
    "sg:classifiers":[
        {
            "category":"Communications",
            "subcategory":"Film & Video Production",
            "type":"Services"
        }
    ],
    "sg:phone":"+32 89 41 80 61",
    "sg:postcode":"3740",
    "sg:province":"Limburg",
    "sg:tags":[
        "hiring",
        "-"
    ],
    "wof:name":"Sofa Scoop",
    "wof:placetype":"venue"
},
  "geometry": {"coordinates":[5.4800639153,50.8878097534],"type":"Point"}
}