{
  "type": "Feature",
  "properties": {
    "iso:country":"BE",
    "sg:address":"Rue De Sclimpr\u00e9 1",
    "sg:city":"Jodoigne (m\u00e9lin)",
    "sg:classifiers":[
        {
            "category":"Insurance",
            "subcategory":"Insurance Agent",
            "type":"Services"
        }
    ],
    "sg:phone":"+32 10 81 01 65",
    "sg:postcode":"1370",
    "sg:province":"Brabant Wallon",
    "sg:tags":[
        "broker"
    ],
    "wof:name":"Ang Insure Sprl",
    "wof:placetype":"venue"
},
  "geometry": {"coordinates":[4.8180189133,50.7602539062],"type":"Point"}
}