{
  "type": "Feature",
  "properties": {
    "addr:full":"Gemeenteplein 4 Melle Oost-Vlaanderen 9090",
    "addr:housenumber":"4",
    "addr:postcode":"9090",
    "addr:street":"Gemeenteplein",
    "iso:country":"BE",
    "sg:address":"Gemeenteplein 4",
    "sg:city":"Melle",
    "sg:classifiers":[
        {
            "category":"Bars & Pubs",
            "type":"Food & Drink"
        }
    ],
    "sg:phone":"+32 9 252 53 25",
    "sg:postcode":"9090",
    "sg:province":"Oost-Vlaanderen",
    "wof:name":"Plezanten Hoek (de)",
    "wof:placetype":"venue"
},
  "geometry": {"coordinates":[3.7985579967,51.0025062561],"type":"Point"}
}