{
  "type": "Feature",
  "properties": {
    "addr:full":"Rue Basse 7 Manage Hainaut 7170",
    "addr:housenumber":"7",
    "addr:postcode":"7170",
    "addr:street":"Rue Basse",
    "iso:country":"BE",
    "sg:address":"Rue Basse 7",
    "sg:city":"Manage",
    "sg:orig_category":"Evaluation and estimation de biens immobiliers",
    "sg:phone":"+32 64 55 55 14",
    "sg:postcode":"7170",
    "sg:province":"Hainaut",
    "wof:name":"Bureau D\u00b4etudes Stb Engineering",
    "wof:placetype":"venue"
},
  "geometry": {"coordinates":[4.2327899933,50.5008239746],"type":"Point"}
}