{
  "type": "Feature",
  "properties": {
    "addr:full":"Vlaanderenstraat 4 Oostende West-Vlaanderen 8400",
    "addr:housenumber":"4",
    "addr:postcode":"8400",
    "addr:street":"Vlaanderenstraat",
    "iso:country":"BE",
    "sg:address":"Vlaanderenstraat 4",
    "sg:city":"Oostende",
    "sg:orig_category":"V\u00eatements pour b\u00e9b\u00e9s and enfants",
    "sg:phone":"+32 59 50 99 13",
    "sg:postcode":"8400",
    "sg:province":"West-Vlaanderen",
    "wof:name":"Huis Kastaar",
    "wof:placetype":"venue"
},
  "geometry": {"coordinates":[2.9167230129,51.2321014404],"type":"Point"}
}