{
  "type": "Feature",
  "properties": {
    "iso:country":"BE",
    "sg:address":"Mina Telghuislaan 20",
    "sg:city":"Kontich",
    "sg:classifiers":[
        {
            "category":"Personal",
            "subcategory":"Beauty Salon",
            "type":"Services"
        }
    ],
    "sg:phone":"+32 3 457 62 57",
    "sg:postcode":"2550",
    "sg:province":"Antwerpen",
    "sg:tags":[
        "de",
        "coiffure"
    ],
    "wof:name":"Coiffure Ria",
    "wof:placetype":"venue"
},
  "geometry": {"coordinates":[4.4505648613,51.1409416199],"type":"Point"}
}