{
  "type": "Feature",
  "properties": {
    "addr:full":"Rue Des Bois 40 Saint-hubert Luxembourg 6870",
    "addr:housenumber":"40",
    "addr:postcode":"6870",
    "addr:street":"Rue Des Bois",
    "iso:country":"BE",
    "sg:address":"Rue Des Bois 40",
    "sg:city":"Saint-hubert",
    "sg:orig_category":"Herstellingen and onderhoud van auto's",
    "sg:phone":"+32 61 61 24 59",
    "sg:postcode":"6870",
    "sg:province":"Luxembourg",
    "wof:name":"Roland Schinckus",
    "wof:placetype":"venue"
},
  "geometry": {"coordinates":[5.3807120323,50.0321235657],"type":"Point"}
}