{
  "type": "Feature",
  "properties": {
    "addr:full":"Raketstraat 64 Brussel Bruxelles-Capitale 1130",
    "addr:housenumber":"64",
    "addr:postcode":"1130",
    "addr:street":"Raketstraat",
    "iso:country":"BE",
    "sg:address":"Raketstraat 64",
    "sg:city":"Brussel",
    "sg:classifiers":[
        {
            "category":"Retail",
            "subcategory":"Event Space",
            "type":"Services"
        }
    ],
    "sg:phone":"+32 2 727 14 11",
    "sg:postcode":"1130",
    "sg:province":"Bruxelles-Capitale",
    "sg:tags":[
        "telecommunication"
    ],
    "wof:name":"Ascom S.a.",
    "wof:placetype":"venue"
},
  "geometry": {"coordinates":[4.4203629494,50.8777351379],"type":"Point"}
}