{
  "type": "Feature",
  "properties": {
    "iso:country":"BE",
    "sg:address":"Eugeen Van De Vellaan 7",
    "sg:city":"Schilde",
    "sg:classifiers":[
        {
            "category":"Personal",
            "subcategory":"Beauty Salon",
            "type":"Services"
        }
    ],
    "sg:phone":"+32 3 383 27 18",
    "sg:postcode":"2970",
    "sg:province":"Antwerpen",
    "wof:name":"Catherine",
    "wof:placetype":"venue"
},
  "geometry": {"coordinates":[4.5761699677,51.2388305664],"type":"Point"}
}