{
  "type": "Feature",
  "properties": {
    "iso:country":"BE",
    "sg:address":"Kerklei 1",
    "sg:city":"Brecht (sint-job-in-'t Goor)",
    "sg:classifiers":[
        {
            "category":"Personal",
            "subcategory":"Beauty Salon",
            "type":"Services"
        }
    ],
    "sg:phone":"+32 478 57 15 89",
    "sg:postcode":"2960",
    "sg:province":"Antwerpen",
    "wof:name":"Pergola",
    "wof:placetype":"venue"
},
  "geometry": {"coordinates":[4.5786528587,51.2924346924],"type":"Point"}
}