{
  "type": "Feature",
  "properties": {
    "addr:full":"Luikersteenweg 365 Hasselt Limburg 3500",
    "addr:housenumber":"365",
    "addr:postcode":"3500",
    "addr:street":"Luikersteenweg",
    "iso:country":"BE",
    "sg:address":"Luikersteenweg 365",
    "sg:city":"Hasselt",
    "sg:orig_category":"RESTAURANTS: SUPPLIES",
    "sg:phone":"+32 11 27 03 36",
    "sg:postcode":"3500",
    "sg:province":"Limburg",
    "wof:name":"Mertens Faema Nv",
    "wof:placetype":"venue"
},
  "geometry": {"coordinates":[5.3548398018,50.909450531],"type":"Point"}
}