{
  "type": "Feature",
  "properties": {
    "iso:country":"BE",
    "sg:address":"Luzery 90",
    "sg:city":"Bastogne (noville)",
    "sg:classifiers":[
        {
            "category":"Wholesale",
            "subcategory":"Vending Machines",
            "type":"Manufacturing & Wholesale Goods"
        }
    ],
    "sg:phone":"+32 61 21 66 26",
    "sg:postcode":"6600",
    "sg:province":"Luxembourg",
    "sg:tags":[
        "-",
        "electric",
        "motor"
    ],
    "wof:name":"Motorcenter Sc",
    "wof:placetype":"venue"
},
  "geometry": {"coordinates":[5.7148199081,50.0007820129],"type":"Point"}
}