{
  "type": "Feature",
  "properties": {
    "iso:country":"BE",
    "sg:address":"Klijtestraat 16",
    "sg:city":"Ieper",
    "sg:orig_category":"Services de Nettoyage and de D\u00e9sinfection",
    "sg:phone":"+32 57 42 26 22",
    "sg:postcode":"8906",
    "sg:province":"West-Vlaanderen",
    "wof:name":"Nora Roelens",
    "wof:placetype":"venue"
},
  "geometry": {"coordinates":[2.8102989197,50.8892707825],"type":"Point"}
}