{
  "type": "Feature",
  "properties": {
    "addr:full":"Rue Du 8-septembre 34 Rouvroy Luxembourg 6767",
    "addr:housenumber":"34",
    "addr:postcode":"6767",
    "addr:street":"Rue Du 8-Septembre",
    "iso:country":"BE",
    "sg:address":"Rue Du 8-septembre 34",
    "sg:city":"Rouvroy",
    "sg:orig_category":"Eleveurs de bovins",
    "sg:phone":"+32 63 57 03 61",
    "sg:postcode":"6767",
    "sg:province":"Luxembourg",
    "wof:name":"Georges Noel-herbeuval",
    "wof:placetype":"venue"
},
  "geometry": {"coordinates":[5.4911298752,49.5393257141],"type":"Point"}
}