{
  "type": "Feature",
  "properties": {
    "iso:country":"BE",
    "sg:address":"Rue Du Centre 15",
    "sg:city":"Geer (hollogne-sur-geer)",
    "sg:classifiers":[
        {
            "category":"Food & Beverages",
            "subcategory":"Groceries & Convenience Stores",
            "type":"Retail Goods"
        }
    ],
    "sg:phone":"+32 19 32 77 58",
    "sg:postcode":"4250",
    "sg:province":"Li\u00e8ge",
    "sg:tags":[
        "grocer"
    ],
    "wof:name":"Delhaize Le Lion",
    "wof:placetype":"venue"
},
  "geometry": {"coordinates":[5.2115478516,50.6745796204],"type":"Point"}
}