{
  "type": "Feature",
  "properties": {
    "addr:full":"Witte Bergenstraat 33b Aarschot Vlaams-Brabant 3200",
    "addr:housenumber":"33b",
    "addr:postcode":"3200",
    "addr:street":"Witte Bergenstraat",
    "iso:country":"BE",
    "sg:address":"Witte Bergenstraat 33b",
    "sg:city":"Aarschot",
    "sg:classifiers":[
        {
            "category":"Banks & Credit Unions",
            "subcategory":"Investment Brokerage",
            "type":"Services"
        }
    ],
    "sg:phone":"+32 16 56 96 61",
    "sg:postcode":"3200",
    "sg:province":"Vlaams-Brabant",
    "sg:tags":[
        "repair",
        "-",
        "installation",
        "sanitary",
        "article"
    ],
    "wof:name":"Van Rompaey P",
    "wof:placetype":"venue"
},
  "geometry": {"coordinates":[4.8276219368,51.005607605],"type":"Point"}
}