{
  "type": "Feature",
  "properties": {
    "addr:full":"Kerkveldstraat 189 Beersel Vlaams-Brabant 1650",
    "addr:housenumber":"189",
    "addr:postcode":"1650",
    "addr:street":"Kerkveldstraat",
    "iso:country":"BE",
    "sg:address":"Kerkveldstraat 189",
    "sg:city":"Beersel",
    "sg:orig_category":"M\u00e9decins and sp\u00e9cialistes",
    "sg:phone":"+32 2 331 25 31",
    "sg:postcode":"1650",
    "sg:province":"Vlaams-Brabant",
    "wof:name":"P. Minner",
    "wof:placetype":"venue"
},
  "geometry": {"coordinates":[4.3194479942,50.7718658447],"type":"Point"}
}