{
  "type": "Feature",
  "properties": {
    "addr:full":"Daaleindestraat 22 Kortessem Limburg 3720",
    "addr:housenumber":"22",
    "addr:postcode":"3720",
    "addr:street":"Daaleindestraat;Limburg",
    "iso:country":"BE",
    "sg:address":"Daaleindestraat 22",
    "sg:city":"Kortessem",
    "sg:classifiers":[
        {
            "category":"Health Services",
            "subcategory":"Health Practitioner",
            "type":"Services"
        }
    ],
    "sg:phone":"+32 11 37 73 45",
    "sg:postcode":"3720",
    "sg:province":"Limburg",
    "sg:tags":[
        "physiotherapist"
    ],
    "wof:name":"Roosen Inge",
    "wof:placetype":"venue"
},
  "geometry": {"coordinates":[5.393447876,50.86095047],"type":"Point"}
}