{
  "type": "Feature",
  "properties": {
    "iso:country":"BE",
    "sg:address":"Industrieweg 12",
    "sg:city":"Balen",
    "sg:classifiers":[
        {
            "category":"Home & Garden",
            "subcategory":"Furniture",
            "type":"Retail Goods"
        }
    ],
    "sg:phone":"+32 14 81 38 82",
    "sg:postcode":"2490",
    "sg:province":"Antwerpen",
    "sg:tags":[
        "household",
        "wood"
    ],
    "wof:name":"Royal Antique Collection Nv",
    "wof:placetype":"venue"
},
  "geometry": {"coordinates":[5.1670098305,51.1999092102],"type":"Point"}
}