{
  "type": "Feature",
  "properties": {
    "iso:country":"BE",
    "sg:address":"Kokkelbeekplein 46",
    "sg:city":"Sint-niklaas",
    "sg:orig_category":"Non-Classified Establishments",
    "sg:phone":"+32 3 776 06 69",
    "sg:postcode":"9100",
    "sg:province":"Oost-Vlaanderen",
    "wof:name":"Roelant-lybeert M Bvba",
    "wof:placetype":"venue"
},
  "geometry": {"coordinates":[4.1447610855,51.1608085632],"type":"Point"}
}