{
  "type": "Feature",
  "properties": {
    "addr:full":"Basilieklaan 38b42 Scherpenheuvel-zichem Vlaams-Brabant 3270",
    "addr:housenumber":"38b42",
    "addr:postcode":"3270",
    "addr:street":"Basilieklaan",
    "iso:country":"BE",
    "sg:address":"Basilieklaan 38b42",
    "sg:city":"Scherpenheuvel-zichem",
    "sg:orig_category":"Stations-service and carburants. V\u00e9hicules automobiles",
    "sg:phone":"+32 13 77 13 22",
    "sg:postcode":"3270",
    "sg:province":"Vlaams-Brabant",
    "wof:name":"Garage Gemoets R. & Zonen",
    "wof:placetype":"venue"
},
  "geometry": {"coordinates":[4.9744319916,50.9798698425],"type":"Point"}
}