{
  "type": "Feature",
  "properties": {
    "addr:full":"Avenue De La Facult\u00c9 D'agronomie 18 Gembloux Namur 5030",
    "addr:housenumber":"18",
    "addr:postcode":"5030",
    "addr:street":"Avenue De La Faculte\u0301 D'Agronomie;Namur",
    "iso:country":"BE",
    "sg:address":"Avenue De La Facult\u00c9 D'agronomie 18",
    "sg:city":"Gembloux",
    "sg:classifiers":[
        {
            "category":"Insurance",
            "subcategory":"Insurance Agent",
            "type":"Services"
        }
    ],
    "sg:phone":"+32 81 62 03 03",
    "sg:postcode":"5030",
    "sg:province":"Namur",
    "sg:tags":[
        "verzekeringsmakelaars",
        "expert"
    ],
    "wof:name":"Drochmans Multiservices",
    "wof:placetype":"venue"
},
  "geometry": {"coordinates":[4.6956520081,50.5662994385],"type":"Point"}
}