{
  "type": "Feature",
  "properties": {
    "iso:country":"BE",
    "sg:address":"Avenue Charles Capelle 45",
    "sg:city":"Namur",
    "sg:orig_category":"Instituts de beaut\u00e9",
    "sg:phone":"+32 81 21 17 40",
    "sg:postcode":"5020",
    "sg:province":"Namur",
    "wof:name":"Wivine Brasseur",
    "wof:placetype":"venue"
},
  "geometry": {"coordinates":[4.7952418327,50.4352035522],"type":"Point"}
}