{
  "type": "Feature",
  "properties": {
    "addr:full":"Rue Des Alli\u00c9s 9 Lincent Li\u00e8ge 4287",
    "addr:housenumber":"9",
    "addr:postcode":"4287",
    "addr:street":"Rue Des Allie\u0301S",
    "iso:country":"BE",
    "sg:address":"Rue Des Alli\u00c9s 9",
    "sg:city":"Lincent",
    "sg:orig_category":"Kapsalons",
    "sg:phone":"+32 19 65 59 46",
    "sg:postcode":"4287",
    "sg:province":"Li\u00e8ge",
    "wof:name":"Renee Dardenne",
    "wof:placetype":"venue"
},
  "geometry": {"coordinates":[5.0072598457,50.7267723083],"type":"Point"}
}