{
  "type": "Feature",
  "properties": {
    "addr:full":"Molendreef 21 Sint-amands Antwerpen 2890",
    "addr:housenumber":"21",
    "addr:postcode":"2890",
    "addr:street":"Molendreef",
    "iso:country":"BE",
    "sg:address":"Molendreef 21",
    "sg:city":"Sint-amands",
    "sg:orig_category":"Artsen and specialisten",
    "sg:phone":"+32 52 33 06 22",
    "sg:postcode":"2890",
    "sg:province":"Antwerpen",
    "wof:name":"G. De Leeuw",
    "wof:placetype":"venue"
},
  "geometry": {"coordinates":[4.1936302185,51.0468292236],"type":"Point"}
}