{
  "type": "Feature",
  "properties": {
    "addr:full":"Goedingenstraat 33 Aalter Oost-Vlaanderen 9881",
    "addr:housenumber":"33",
    "addr:postcode":"9881",
    "addr:street":"Goedingenstraat",
    "iso:country":"BE",
    "sg:address":"Goedingenstraat 33",
    "sg:city":"Aalter",
    "sg:orig_category":"Apotheken",
    "sg:phone":"+32 9 374 41 02",
    "sg:postcode":"9881",
    "sg:province":"Oost-Vlaanderen",
    "wof:name":"Liliane De Baets",
    "wof:placetype":"venue"
},
  "geometry": {"coordinates":[3.4952909946,51.0923576355],"type":"Point"}
}