{
  "type": "Feature",
  "properties": {
    "iso:country":"BE",
    "sg:address":"Baron Ruzettelaan 415b1",
    "sg:city":"Brugge",
    "sg:orig_category":"Boucheries",
    "sg:phone":"+32 50 35 52 07",
    "sg:postcode":"8310",
    "sg:province":"West-Vlaanderen",
    "wof:name":"Beenhouwerij Hugo",
    "wof:placetype":"venue"
},
  "geometry": {"coordinates":[3.2342998981,51.1849594116],"type":"Point"}
}