{
  "type": "Feature",
  "properties": {
    "addr:full":"Mechelsestraat 106 Leuven Vlaams-Brabant 3000",
    "addr:housenumber":"106",
    "addr:postcode":"3000",
    "addr:street":"Mechelsestraat",
    "iso:country":"BE",
    "sg:address":"Mechelsestraat 106",
    "sg:city":"Leuven",
    "sg:classifiers":[
        {
            "category":"Cafe",
            "type":"Food & Drink"
        }
    ],
    "sg:phone":"+32 16 20 77 21",
    "sg:postcode":"3000",
    "sg:province":"Vlaams-Brabant",
    "sg:tags":[
        "snack-bars"
    ],
    "wof:name":"Eethuisje Beregoed",
    "wof:placetype":"venue"
},
  "geometry": {"coordinates":[4.6985549927,50.8829841614],"type":"Point"}
}