{
  "type": "Feature",
  "properties": {
    "iso:country":"BE",
    "sg:address":"Eendrachtstraat 73",
    "sg:city":"Gent",
    "sg:classifiers":[
        {
            "category":"Recreation",
            "subcategory":"Boat Charter",
            "type":"Entertainment"
        }
    ],
    "sg:phone":"+32 497 46 10 78",
    "sg:postcode":"9000",
    "sg:province":"Oost-Vlaanderen",
    "sg:tags":[
        "-",
        "builder",
        "yacht",
        "pleasure"
    ],
    "wof:name":"Tss",
    "wof:placetype":"venue"
},
  "geometry": {"coordinates":[3.7438910007,51.0481910706],"type":"Point"}
}