{
  "type": "Feature",
  "properties": {
    "addr:full":"Zagerijstraat 76 Lier Antwerpen 2500",
    "addr:housenumber":"76",
    "addr:postcode":"2500",
    "addr:street":"Zagerijstraat",
    "iso:country":"BE",
    "sg:address":"Zagerijstraat 76",
    "sg:city":"Lier",
    "sg:orig_category":"Pain, p\u00e2tisseries and confiseries",
    "sg:phone":"+32 3 489 32 37",
    "sg:postcode":"2500",
    "sg:province":"Antwerpen",
    "wof:name":"Sabine",
    "wof:placetype":"venue"
},
  "geometry": {"coordinates":[4.562620163,51.1382904053],"type":"Point"}
}