{
  "type": "Feature",
  "properties": {
    "addr:full":"March\u00c9-aux-toiles 13 Ath Hainaut 7800",
    "addr:housenumber":"13",
    "addr:postcode":"7800",
    "addr:street":"Marche\u0301-Aux-Toiles",
    "iso:country":"BE",
    "sg:address":"March\u00c9-aux-toiles 13",
    "sg:city":"Ath",
    "sg:orig_category":"Verlichting and huishoudartikelen",
    "sg:phone":"+32 68 84 03 04",
    "sg:postcode":"7800",
    "sg:province":"Hainaut",
    "wof:name":"Ma Cabane",
    "wof:placetype":"venue"
},
  "geometry": {"coordinates":[3.7753899097,50.631439209],"type":"Point"}
}