{
  "type": "Feature",
  "properties": {
    "iso:country":"BE",
    "sg:address":"Marktstraat 8",
    "sg:city":"Genk",
    "sg:orig_category":"Alimentation sp\u00e9cialis\u00e9e",
    "sg:phone":"+32 89 35 68 94",
    "sg:postcode":"36100",
    "wof:name":"Johanna Hoogsteder",
    "wof:placetype":"venue"
},
  "geometry": {"coordinates":[5.5002498627,50.9653968811],"type":"Point"}
}