{
  "type": "Feature",
  "properties": {
    "addr:full":"Rue De Barchon 101 Housse Li\u00e8ge 4671",
    "addr:housenumber":"101",
    "addr:postcode":"4671",
    "addr:street":"Rue De Barchon",
    "iso:country":"BE",
    "sg:address":"Rue De Barchon 101",
    "sg:city":"Housse",
    "sg:classifiers":[
        {
            "category":"Manufacturing",
            "subcategory":"Metals",
            "type":"Manufacturing & Wholesale Goods"
        }
    ],
    "sg:phone":"+32 4 387 42 91",
    "sg:postcode":"4671",
    "sg:province":"Li\u00e8ge",
    "sg:tags":[
        "alloy",
        "construction",
        "lightweight"
    ],
    "wof:name":"Ets L\u00e9onard Andr\u00e9 S.a.",
    "wof:placetype":"venue"
},
  "geometry": {"coordinates":[5.6959300041,50.6807441711],"type":"Point"}
}