{
  "type": "Feature",
  "properties": {
    "addr:full":"Vlamingdam 55 Brugge West-Vlaanderen 8000",
    "addr:housenumber":"55",
    "addr:postcode":"8000",
    "addr:street":"Vlamingdam",
    "iso:country":"BE",
    "sg:address":"Vlamingdam 55",
    "sg:city":"Brugge",
    "sg:classifiers":[
        {
            "category":"Social Services",
            "type":"Services"
        }
    ],
    "sg:phone":"+32 50 33 77 15",
    "sg:postcode":"8000",
    "sg:province":"West-Vlaanderen",
    "wof:name":"Huurdersbond Vzw",
    "wof:placetype":"venue"
},
  "geometry": {"coordinates":[3.2204120159,51.2170295715],"type":"Point"}
}