{
  "type": "Feature",
  "properties": {
    "addr:full":"Rue Belle Vue 6 Anthisnes Li\u00e8ge 4160",
    "addr:housenumber":"6",
    "addr:postcode":"4160",
    "addr:street":"Rue Belle Vue",
    "iso:country":"BE",
    "sg:address":"Rue Belle Vue 6",
    "sg:city":"Anthisnes",
    "sg:orig_category":"Fabrication and montage de mobilier",
    "sg:phone":"+32 4 383 70 07",
    "sg:postcode":"4160",
    "sg:province":"Li\u00e8ge",
    "wof:name":"P.j. Paulus",
    "wof:placetype":"venue"
},
  "geometry": {"coordinates":[5.5224709511,50.485118866],"type":"Point"}
}