{
  "type": "Feature",
  "properties": {
    "addr:full":"Nazaretdreef 99 Lier Antwerpen 2500",
    "addr:housenumber":"99",
    "addr:postcode":"2500",
    "addr:street":"Nazaretdreef",
    "iso:country":"BE",
    "sg:address":"Nazaretdreef 99",
    "sg:city":"Lier",
    "sg:classifiers":[
        {
            "category":"Retail",
            "subcategory":"Event Space",
            "type":"Services"
        }
    ],
    "sg:phone":"+32 3 489 34 05",
    "sg:postcode":"2500",
    "sg:province":"Antwerpen",
    "sg:tags":[
        "rental",
        "-",
        "hall"
    ],
    "wof:name":"Hof Van Beatrijs",
    "wof:placetype":"venue"
},
  "geometry": {"coordinates":[4.5832819939,51.1414718628],"type":"Point"}
}