{
  "type": "Feature",
  "properties": {
    "iso:country":"BE",
    "sg:address":"Rue Mogn\u00e9e 47",
    "sg:city":"Ouffet",
    "sg:classifiers":[
        {
            "category":"Bars & Pubs",
            "type":"Food & Drink"
        }
    ],
    "sg:phone":"+32 86 36 75 36",
    "sg:postcode":"4590",
    "sg:province":"Li\u00e8ge",
    "wof:name":"New Pub",
    "wof:placetype":"venue"
},
  "geometry": {"coordinates":[5.4641699791,50.4412612915],"type":"Point"}
}