{
  "type": "Feature",
  "properties": {
    "addr:full":"Keizersstraat 54 Harelbeke West-Vlaanderen 8530",
    "addr:housenumber":"54",
    "addr:postcode":"8530",
    "addr:street":"Keizersstraat",
    "iso:country":"BE",
    "sg:address":"Keizersstraat 54",
    "sg:city":"Harelbeke",
    "sg:orig_category":"Mat\u00e9riaux de construction Gr",
    "sg:phone":"+32 56 20 48 32",
    "sg:postcode":"8530",
    "sg:province":"West-Vlaanderen",
    "wof:name":"Industrial Dry Products",
    "wof:placetype":"venue"
},
  "geometry": {"coordinates":[3.3185100555,50.8257293701],"type":"Point"}
}