{
  "type": "Feature",
  "properties": {
    "addr:full":"Rue Anti\u00c9mont 85 Marche-en-famenne Luxembourg 6900",
    "addr:housenumber":"85",
    "addr:postcode":"6900",
    "addr:street":"Rue Antie\u0301Mont",
    "iso:country":"BE",
    "sg:address":"Rue Anti\u00c9mont 85",
    "sg:city":"Marche-en-famenne",
    "sg:orig_category":"Fleurs and plantes",
    "sg:phone":"+32 84 21 05 16",
    "sg:postcode":"6900",
    "sg:province":"Luxembourg",
    "wof:name":"Jardiflore",
    "wof:placetype":"venue"
},
  "geometry": {"coordinates":[5.2987041473,50.1791725159],"type":"Point"}
}