{
  "type": "Feature",
  "properties": {
    "addr:full":"Holenteerstraat 1a Genk Limburg 3600",
    "addr:housenumber":"1a",
    "addr:postcode":"3600",
    "addr:street":"Holenteerstraat",
    "iso:country":"BE",
    "sg:address":"Holenteerstraat 1a",
    "sg:city":"Genk",
    "sg:orig_category":"Non-Classified Establishments",
    "sg:phone":"+32 89 35 35 53",
    "sg:postcode":"3600",
    "sg:province":"Limburg",
    "wof:name":"Smeets Harie",
    "wof:placetype":"venue"
},
  "geometry": {"coordinates":[5.4855999947,50.9884490967],"type":"Point"}
}