{
  "type": "Feature",
  "properties": {
    "addr:full":"Haute-voie-de-march\u00c9 10 Nassogne Luxembourg 6950",
    "addr:housenumber":"10",
    "addr:postcode":"6950",
    "addr:street":"Haute-Voie-De-Marche\u0301",
    "iso:country":"BE",
    "sg:address":"Haute-voie-de-march\u00c9 10",
    "sg:city":"Nassogne",
    "sg:classifiers":[
        {
            "category":"Insurance",
            "subcategory":"Insurance Agent",
            "type":"Services"
        }
    ],
    "sg:phone":"+32 84 21 07 99",
    "sg:postcode":"6950",
    "sg:province":"Luxembourg",
    "sg:tags":[
        "verzekeringsmakelaars",
        "expert"
    ],
    "wof:name":"Bureau Magerotte M.",
    "wof:placetype":"venue"
},
  "geometry": {"coordinates":[5.3477082253,50.1329116821],"type":"Point"}
}