{
  "type": "Feature",
  "properties": {
    "iso:country":"BE",
    "sg:address":"Mont 74",
    "sg:city":"Ellezelles",
    "sg:orig_category":"Gespecialiseerde residenti\u00eble bouw",
    "sg:phone":"+32 68 54 23 78",
    "sg:postcode":"7890",
    "sg:province":"Hainaut",
    "wof:name":"Michel Van Oosthuyze",
    "wof:placetype":"venue"
},
  "geometry": {"coordinates":[3.676003933,50.7512702942],"type":"Point"}
}