{
  "type": "Feature",
  "properties": {
    "iso:country":"BE",
    "sg:address":"Rue Notre Dame De Gr\u00e2ces 11",
    "sg:city":"Marche-en-famenne",
    "sg:classifiers":[
        {
            "category":"Bars & Pubs",
            "type":"Food & Drink"
        }
    ],
    "sg:phone":"+32 84 31 62 99",
    "sg:postcode":"6900",
    "sg:province":"Luxembourg",
    "wof:name":"Picotin (au)",
    "wof:placetype":"venue"
},
  "geometry": {"coordinates":[5.3427791595,50.2302322388],"type":"Point"}
}