{
  "type": "Feature",
  "properties": {
    "addr:full":"Gebr. Vandeveldestraat 58 Gent Oost-Vlaanderen 9000",
    "addr:housenumber":"58",
    "addr:postcode":"9000",
    "addr:street":"Vandeveldestraat;Oost-Vlaanderen",
    "iso:country":"BE",
    "sg:address":"Gebr. Vandeveldestraat 58",
    "sg:city":"Gent",
    "sg:orig_category":"Instituts de beaut\u00e9",
    "sg:phone":"+32 9 225 07 73",
    "sg:postcode":"9000",
    "sg:province":"Oost-Vlaanderen",
    "wof:name":"Instituut Ambre",
    "wof:placetype":"venue"
},
  "geometry": {"coordinates":[3.7176539898,51.0504570007],"type":"Point"}
}