{
  "type": "Feature",
  "properties": {
    "iso:country":"BE",
    "sg:address":"Bavikhovedorp 17",
    "sg:city":"Harelbeke",
    "sg:orig_category":"V\u00e9hicules automobiles. Entretien and r\u00e9parations de voitures",
    "sg:phone":"+32 56 71 36 73",
    "sg:postcode":"8531",
    "sg:province":"West-Vlaanderen",
    "wof:name":"Daniel Tack",
    "wof:placetype":"venue"
},
  "geometry": {"coordinates":[3.3103899956,50.8749885559],"type":"Point"}
}