{
  "type": "Feature",
  "properties": {
    "iso:country":"BE",
    "sg:address":"Avenue Th\u00e9o Vanp\u00e9 16",
    "sg:city":"Bruxelles (auderghem)",
    "sg:classifiers":[
        {
            "category":"Health Services",
            "subcategory":"Dentist",
            "type":"Services"
        }
    ],
    "sg:phone":"+32 2 660 77 38",
    "sg:postcode":"1160",
    "sg:province":"Bruxelles-Capitale",
    "wof:name":"De Wagter Ch",
    "wof:placetype":"venue"
},
  "geometry": {"coordinates":[4.4270172119,50.8107719421],"type":"Point"}
}