{
  "type": "Feature",
  "properties": {
    "iso:country":"BE",
    "sg:address":"Hoging 38",
    "sg:city":"Lede",
    "sg:orig_category":"HUISBRANDOLIE",
    "sg:phone":"+32 9 369 68 64",
    "sg:postcode":"9340",
    "sg:province":"Oost-Vlaanderen",
    "wof:name":"Elka",
    "wof:placetype":"venue"
},
  "geometry": {"coordinates":[3.9003059864,50.952709198],"type":"Point"}
}