{
  "type": "Feature",
  "properties": {
    "addr:full":"Rue De La Station 23 Rixensart Brabant Wallon 1332",
    "addr:housenumber":"23",
    "addr:postcode":"1332",
    "addr:street":"Rue De La Station;Wallon",
    "iso:country":"BE",
    "sg:address":"Rue De La Station 23",
    "sg:city":"Rixensart",
    "sg:classifiers":[
        {
            "category":"Insurance",
            "subcategory":"Insurance Agent",
            "type":"Services"
        }
    ],
    "sg:phone":"+32 2 653 71 24",
    "sg:postcode":"1332",
    "sg:province":"Brabant Wallon",
    "sg:tags":[
        "verzekeringsmakelaars",
        "expert"
    ],
    "wof:name":"Andre Ph.",
    "wof:placetype":"venue"
},
  "geometry": {"coordinates":[4.5142159462,50.7247047424],"type":"Point"}
}