{
  "type": "Feature",
  "properties": {
    "iso:country":"BE",
    "sg:address":"Rue De Hanret 14",
    "sg:city":"Fernelmont",
    "sg:orig_category":"Informaticaconsulenten",
    "sg:phone":"+32 81 83 45 49",
    "sg:postcode":"5380",
    "sg:province":"Namur",
    "wof:name":"Emmanuel Forestieri",
    "wof:placetype":"venue"
},
  "geometry": {"coordinates":[4.9546132088,50.568523407],"type":"Point"}
}