{
  "type": "Feature",
  "properties": {
    "iso:country":"BE",
    "sg:address":"Rue Albert Ier 364",
    "sg:city":"Erquelinnes",
    "sg:classifiers":[
        {
            "category":"Restaurant",
            "type":"Food & Drink"
        }
    ],
    "sg:phone":"+32 71 55 38 28",
    "sg:postcode":"6560",
    "sg:province":"Hainaut",
    "sg:tags":[
        "caf\u00e9s"
    ],
    "wof:name":"Taverne Le Cocktails",
    "wof:placetype":"venue"
},
  "geometry": {"coordinates":[4.1112408638,50.3041000366],"type":"Point"}
}