{
  "type": "Feature",
  "properties": {
    "addr:full":"Rue De La Justice 8bb Tournai Hainaut 7500",
    "addr:housenumber":"8bb",
    "addr:postcode":"7500",
    "addr:street":"Rue De La Justice",
    "iso:country":"BE",
    "sg:address":"Rue De La Justice 8bb",
    "sg:city":"Tournai",
    "sg:orig_category":"Enseignement maternel and primaire",
    "sg:phone":"+32 69 22 95 94",
    "sg:postcode":"7500",
    "sg:province":"Hainaut",
    "wof:name":"Ecole Fond. Communale",
    "wof:placetype":"venue"
},
  "geometry": {"coordinates":[3.3954041004,50.602191925],"type":"Point"}
}