{
  "type": "Feature",
  "properties": {
    "iso:country":"BE",
    "sg:address":"Rue Bertrand 7",
    "sg:city":"Floreffe",
    "sg:classifiers":[
        {
            "category":"Building & Trades",
            "subcategory":"Equipment Rental",
            "type":"Services"
        }
    ],
    "sg:phone":"+32 81 44 58 15",
    "sg:postcode":"5150",
    "sg:province":"Namur",
    "sg:tags":[
        "sound",
        "-",
        "system"
    ],
    "wof:name":"B & D Sonorisation",
    "wof:placetype":"venue"
},
  "geometry": {"coordinates":[4.757019043,50.4291725159],"type":"Point"}
}