{
  "type": "Feature",
  "properties": {
    "iso:country":"BE",
    "sg:address":"Rue Du Coq 15",
    "sg:city":"Huy",
    "sg:orig_category":"Boekbinderijen and afwerking Drukkerijen and copyshops",
    "sg:phone":"+32 85 23 07 94",
    "sg:postcode":"4500",
    "sg:province":"Li\u00e8ge",
    "wof:name":"Copy Shop",
    "wof:placetype":"venue"
},
  "geometry": {"coordinates":[5.2415981293,50.5191688538],"type":"Point"}
}