{
  "type": "Feature",
  "properties": {
    "iso:country":"BE",
    "sg:address":"Avenue Arnold Delvaux 49",
    "sg:city":"Bruxelles (uccle)",
    "sg:classifiers":[
        {
            "category":"Health Services",
            "subcategory":"Nursing And Care Facility",
            "type":"Services"
        }
    ],
    "sg:phone":"+32 2 346 16 22",
    "sg:postcode":"1180",
    "sg:province":"Bruxelles-Capitale",
    "sg:tags":[
        "home"
    ],
    "wof:name":"Guillaumot N",
    "wof:placetype":"venue"
},
  "geometry": {"coordinates":[4.3391618729,50.7996711731],"type":"Point"}
}