{
  "type": "Feature",
  "properties": {
    "iso:country":"BE",
    "sg:address":"Nieuwstraat 56",
    "sg:city":"Brussel/bruxelles",
    "sg:orig_category":"Beautyfarms, relaxatie and lichamelijk welzijn Cosmetica and toiletartikelen Schoonheidssalons",
    "sg:phone":"+32 2 219 38 28",
    "sg:postcode":"1000",
    "sg:province":"Bruxelles-Capitale",
    "wof:name":"Planet Parfum",
    "wof:placetype":"venue"
},
  "geometry": {"coordinates":[4.3553261757,50.8536262512],"type":"Point"}
}