{
  "type": "Feature",
  "properties": {
    "addr:full":"Meerlaan 1 Zottegem Oost-Vlaanderen 9620",
    "addr:housenumber":"1",
    "addr:postcode":"9620",
    "addr:street":"Meerlaan",
    "iso:country":"BE",
    "sg:address":"Meerlaan 1",
    "sg:city":"Zottegem",
    "sg:classifiers":[
        {
            "category":"Cafe",
            "type":"Food & Drink"
        }
    ],
    "sg:phone":"+32 9 360 01 60",
    "sg:postcode":"9620",
    "sg:province":"Oost-Vlaanderen",
    "sg:tags":[
        "caf\u00e9s"
    ],
    "wof:name":"Caf\u00c9 Luchtbal",
    "wof:placetype":"venue"
},
  "geometry": {"coordinates":[3.8121500015,50.8595962524],"type":"Point"}
}