{
  "type": "Feature",
  "properties": {
    "addr:full":"Willem Matstraat 32 Hoeilaart Vlaams-Brabant 1560",
    "addr:housenumber":"32",
    "addr:postcode":"1560",
    "addr:street":"Willem Matstraat",
    "iso:country":"BE",
    "sg:address":"Willem Matstraat 32",
    "sg:city":"Hoeilaart",
    "sg:orig_category":"Fotografen and fotostudio's",
    "sg:phone":"+32 2 657 05 44",
    "sg:postcode":"1560",
    "sg:province":"Vlaams-Brabant",
    "wof:name":"Paul Bolsius",
    "wof:placetype":"venue"
},
  "geometry": {"coordinates":[4.482049942,50.7618255615],"type":"Point"}
}