{
  "type": "Feature",
  "properties": {
    "iso:country":"BE",
    "sg:address":"Haute Fontaine 2",
    "sg:city":"Namur",
    "sg:orig_category":"Pain, p\u00e2tisseries and confiseries",
    "sg:phone":"+32 81 44 06 01",
    "sg:postcode":"5020",
    "sg:province":"Namur",
    "wof:name":"Four \u00c0 Pain",
    "wof:placetype":"venue"
},
  "geometry": {"coordinates":[4.7952418327,50.4352035522],"type":"Point"}
}