{
  "type": "Feature",
  "properties": {
    "iso:country":"BE",
    "sg:address":"12",
    "sg:city":"Grote Markt 8800 Roeselare",
    "sg:classifiers":[
        {
            "category":"Shopping",
            "subcategory":"Clothing, Apparel, & Fashions",
            "type":"Retail Goods"
        }
    ],
    "sg:phone":"+32 51 20 21 96",
    "sg:postcode":"12",
    "sg:tags":[
        "textile",
        "clothing",
        "clothes"
    ],
    "wof:name":"Corsetfabriek Andrema Nv",
    "wof:placetype":"venue"
},
  "geometry": {"coordinates":[3.1237850189,50.9452781677],"type":"Point"}
}