{
  "type": "Feature",
  "properties": {
    "addr:full":"Beukenlaan 44 Zele Oost-Vlaanderen 9240",
    "addr:housenumber":"44",
    "addr:postcode":"9240",
    "addr:street":"Beukenlaan",
    "iso:country":"BE",
    "sg:address":"Beukenlaan 44",
    "sg:city":"Zele",
    "sg:classifiers":[
        {
            "category":"Bakery",
            "type":"Food & Drink"
        }
    ],
    "sg:phone":"+32 3 776 38 60",
    "sg:postcode":"9240",
    "sg:province":"Oost-Vlaanderen",
    "sg:tags":[
        "confectioner",
        "baker"
    ],
    "wof:name":"Kris Bakkerij",
    "wof:placetype":"venue"
},
  "geometry": {"coordinates":[4.0327248573,51.0742073059],"type":"Point"}
}