{
  "type": "Feature",
  "properties": {
    "addr:full":"Bloemendalestraat 71 Beernem West-Vlaanderen 8730",
    "addr:housenumber":"71",
    "addr:postcode":"8730",
    "addr:street":"Bloemendalestraat",
    "iso:country":"BE",
    "sg:address":"Bloemendalestraat 71",
    "sg:city":"Beernem",
    "sg:classifiers":[
        {
            "category":"Arena",
            "subcategory":"Sports Club",
            "type":"Entertainment"
        }
    ],
    "sg:phone":"+32 50 78 19 11",
    "sg:postcode":"8730",
    "sg:province":"West-Vlaanderen",
    "wof:name":"Bloemendale Tennisclub",
    "wof:placetype":"venue"
},
  "geometry": {"coordinates":[3.3376560211,51.1401023865],"type":"Point"}
}