{
  "type": "Feature",
  "properties": {
    "addr:full":"Provincialebaan 172 Buggenhout Oost-Vlaanderen 9255",
    "addr:housenumber":"172",
    "addr:postcode":"9255",
    "iso:country":"BE",
    "sg:address":"Provincialebaan 172",
    "sg:city":"Buggenhout",
    "sg:classifiers":[
        {
            "category":"Shopping",
            "subcategory":"Shoes",
            "type":"Retail Goods"
        }
    ],
    "sg:phone":"+32 52 33 37 86",
    "sg:postcode":"9255",
    "sg:province":"Oost-Vlaanderen",
    "sg:tags":[
        "children's"
    ],
    "wof:name":"Prabel Schoenfabriek Nv",
    "wof:placetype":"venue"
},
  "geometry": {"coordinates":[4.19190979,51.0308914185],"type":"Point"}
}