{
  "type": "Feature",
  "properties": {
    "iso:country":"BE",
    "sg:address":"Boerenlegerstraat 150-1",
    "sg:city":"Edegem",
    "sg:classifiers":[
        {
            "category":"Health Services",
            "subcategory":"Health Practitioner",
            "type":"Services"
        }
    ],
    "sg:phone":"+32 3 458 14 99",
    "sg:postcode":"2650",
    "sg:province":"Antwerpen",
    "sg:tags":[
        "therapist",
        "speech"
    ],
    "wof:name":"Van Oevelen A",
    "wof:placetype":"venue"
},
  "geometry": {"coordinates":[4.4410691261,51.1520614624],"type":"Point"}
}