{
  "type": "Feature",
  "properties": {
    "addr:full":"Grand'rue 101 Mouscron Hainaut 7700",
    "addr:housenumber":"101",
    "addr:postcode":"7700",
    "addr:street":"Grand'Rue",
    "iso:country":"BE",
    "sg:address":"Grand'rue 101",
    "sg:city":"Mouscron",
    "sg:orig_category":"Reisbureaus",
    "sg:phone":"+32 56 84 04 10",
    "sg:postcode":"7700",
    "sg:province":"Hainaut",
    "wof:name":"Folie's Travel",
    "wof:placetype":"venue"
},
  "geometry": {"coordinates":[3.2147009373,50.7433891296],"type":"Point"}
}