{
  "type": "Feature",
  "properties": {
    "iso:country":"BE",
    "sg:address":"J Van Haesendonckstraat 73",
    "sg:city":"Antwerpen",
    "sg:orig_category":"Traitement and rev\u00eatement des m\u00e9taux",
    "sg:phone":"+32 3 541 33 10",
    "sg:postcode":"2180",
    "sg:province":"Antwerpen",
    "wof:name":"A.d.f. Verschueren",
    "wof:placetype":"venue"
},
  "geometry": {"coordinates":[4.4182572365,51.2778625488],"type":"Point"}
}