{
  "type": "Feature",
  "properties": {
    "addr:full":"Rue Gachard 10 Bruxelles (ixelles) Bruxelles-Capitale 1050",
    "addr:housenumber":"10",
    "addr:postcode":"1050",
    "addr:street":"Rue Gachard",
    "iso:country":"BE",
    "sg:address":"Rue Gachard 10",
    "sg:city":"Bruxelles (ixelles)",
    "sg:classifiers":[
        {
            "category":"Education",
            "subcategory":"Special Training",
            "type":"Public Place"
        }
    ],
    "sg:phone":"+32 2 647 92 20",
    "sg:postcode":"1050",
    "sg:province":"Bruxelles-Capitale",
    "sg:tags":[
        "professional"
    ],
    "wof:name":"Sae Institute",
    "wof:placetype":"venue"
},
  "geometry": {"coordinates":[4.3694829941,50.827255249],"type":"Point"}
}