{
  "type": "Feature",
  "properties": {
    "iso:country":"BE",
    "sg:address":"Rue De Bierghes 4",
    "sg:city":"Rebecq (wisbecq)",
    "sg:classifiers":[
        {
            "category":"Farming",
            "subcategory":"Livestock Farm",
            "type":"Manufacturing & Wholesale Goods"
        }
    ],
    "sg:phone":"+32 479 85 90 59",
    "sg:postcode":"1430",
    "sg:province":"Brabant Wallon",
    "sg:tags":[
        "stud"
    ],
    "wof:name":"Haras Wisbecq",
    "wof:placetype":"venue"
},
  "geometry": {"coordinates":[4.1348910332,50.6832466125],"type":"Point"}
}