{
  "type": "Feature",
  "properties": {
    "addr:full":"Rue Du March\u00c9 Aux Herbes 3 Brussel/bruxelles Bruxelles-Capitale 1000",
    "addr:housenumber":"3",
    "addr:postcode":"1000",
    "addr:street":"Rue Du Marche\u0301 Aux Herbes;/",
    "iso:country":"BE",
    "sg:address":"Rue Du March\u00c9 Aux Herbes 3",
    "sg:city":"Brussel/bruxelles",
    "sg:orig_category":"Chaussures",
    "sg:phone":"+32 2 512 34 56",
    "sg:postcode":"1000",
    "sg:province":"Bruxelles-Capitale",
    "wof:name":"Maison Gonthier",
    "wof:placetype":"venue"
},
  "geometry": {"coordinates":[4.351858139,50.8482017517],"type":"Point"}
}