{
  "type": "Feature",
  "properties": {
    "addr:full":"De Tieckenstraat 23 Borgloon Limburg 3840",
    "addr:housenumber":"23",
    "addr:postcode":"3840",
    "addr:street":"De Tieckenstraat",
    "iso:country":"BE",
    "sg:address":"De Tieckenstraat 23",
    "sg:city":"Borgloon",
    "sg:orig_category":"Entretien and r\u00e9parations de voitures",
    "sg:phone":"+32 12 74 26 39",
    "sg:postcode":"3840",
    "sg:province":"Limburg",
    "wof:name":"Jean Vroonen",
    "wof:placetype":"venue"
},
  "geometry": {"coordinates":[5.3441700935,50.8012466431],"type":"Point"}
}