{
  "type": "Feature",
  "properties": {
    "iso:country":"BE",
    "sg:address":"J'stormestraat",
    "sg:city":"Waregem",
    "sg:orig_category":"Non-foodwinkels",
    "sg:phone":"+32 56 61 58 48",
    "sg:postcode":"8790",
    "sg:province":"West-Vlaanderen",
    "wof:name":"Liboe Volslanke Damesmode",
    "wof:placetype":"venue"
},
  "geometry": {"coordinates":[3.4297719002,50.8858604431],"type":"Point"}
}