{
  "type": "Feature",
  "properties": {
    "addr:full":"Torenweg 3 Beernem West-Vlaanderen 8730",
    "addr:housenumber":"3",
    "addr:postcode":"8730",
    "addr:street":"Torenweg",
    "iso:country":"BE",
    "sg:address":"Torenweg 3",
    "sg:city":"Beernem",
    "sg:orig_category":"Installatie van houten of kunststof schrijnwerk",
    "sg:phone":"+32 50 78 94 79",
    "sg:postcode":"8730",
    "sg:province":"West-Vlaanderen",
    "wof:name":"Johan Vandamme",
    "wof:placetype":"venue"
},
  "geometry": {"coordinates":[3.3209190369,51.1043167114],"type":"Point"}
}