{
  "type": "Feature",
  "properties": {
    "iso:country":"BE",
    "sg:address":"Putstraat 41",
    "sg:city":"Tongeren",
    "sg:classifiers":[
        {
            "category":"Professional",
            "subcategory":"Art Services",
            "type":"Services"
        }
    ],
    "sg:phone":"+32 12 39 17 04",
    "sg:postcode":"3700",
    "sg:province":"Limburg",
    "sg:tags":[
        "interior",
        "designer"
    ],
    "wof:name":"S.k.a.b.",
    "wof:placetype":"venue"
},
  "geometry": {"coordinates":[5.461151123,50.7787322998],"type":"Point"}
}