{
  "type": "Feature",
  "properties": {
    "addr:full":"Rue Charlemagne 109 Li\u00c8ge Li\u00e8ge 4020",
    "addr:housenumber":"109",
    "addr:postcode":"4020",
    "addr:street":"Rue Charlemagne",
    "iso:country":"BE",
    "sg:address":"Rue Charlemagne 109",
    "sg:city":"Li\u00c8ge",
    "sg:classifiers":[
        {
            "category":"Arena",
            "subcategory":"Sports Club",
            "type":"Entertainment"
        }
    ],
    "sg:phone":"+32 4 362 30 08",
    "sg:postcode":"4020",
    "sg:province":"Li\u00e8ge",
    "sg:tags":[
        "de"
    ],
    "wof:name":"E.p. Herstal-asep",
    "wof:placetype":"venue"
},
  "geometry": {"coordinates":[5.6346750259,50.6462516785],"type":"Point"}
}