{
  "type": "Feature",
  "properties": {
    "iso:country":"BE",
    "sg:address":"Moederhofstraat 33",
    "sg:city":"Lint",
    "sg:orig_category":"Rev\u00eatements de sols and murs",
    "sg:phone":"+32 3 455 41 25",
    "sg:postcode":"2547",
    "sg:province":"Antwerpen",
    "wof:name":"Van Camp",
    "wof:placetype":"venue"
},
  "geometry": {"coordinates":[4.4918007851,51.1232185364],"type":"Point"}
}