{
  "type": "Feature",
  "properties": {
    "iso:country":"BE",
    "sg:address":"Rue De Lonz\u00c9e 172",
    "sg:city":"Gembloux",
    "sg:orig_category":"Paramedische behandelingen",
    "sg:phone":"+32 81 61 04 81",
    "sg:postcode":"5030",
    "sg:province":"Namur",
    "wof:name":"H. De Beco",
    "wof:placetype":"venue"
},
  "geometry": {"coordinates":[4.7426581383,50.5587654114],"type":"Point"}
}