{
  "type": "Feature",
  "properties": {
    "iso:country":"BE",
    "sg:address":"Rue Des Alli\u00c9s 85",
    "sg:city":"Colfontaine",
    "sg:orig_category":"Apotheken",
    "sg:phone":"+32 65 67 16 88",
    "sg:postcode":"7340",
    "sg:province":"Hainaut",
    "wof:name":"Marie-paule Cavenaile",
    "wof:placetype":"venue"
},
  "geometry": {"coordinates":[3.8439118862,50.4191932678],"type":"Point"}
}