{
  "type": "Feature",
  "properties": {
    "addr:full":"Past Steensensstraat 13 Beveren Oost-Vlaanderen 9120",
    "addr:housenumber":"13",
    "addr:postcode":"9120",
    "addr:street":"Steensensstraat",
    "iso:country":"BE",
    "sg:address":"Past Steensensstraat 13",
    "sg:city":"Beveren",
    "sg:classifiers":[
        {
            "category":"Professional",
            "type":"Services"
        }
    ],
    "sg:phone":"+32 3 775 23 10",
    "sg:postcode":"9120",
    "sg:province":"Oost-Vlaanderen",
    "sg:tags":[
        "aux",
        "diver",
        "personnes"
    ],
    "wof:name":"Beck E.",
    "wof:placetype":"venue"
},
  "geometry": {"coordinates":[4.2389512062,51.2068634033],"type":"Point"}
}