{
  "type": "Feature",
  "properties": {
    "addr:full":"Kleinesteenweg 33 Begijnendijk Vlaams-Brabant 3130",
    "addr:housenumber":"33",
    "addr:postcode":"3130",
    "addr:street":"Kleinesteenweg",
    "iso:country":"BE",
    "sg:address":"Kleinesteenweg 33",
    "sg:city":"Begijnendijk",
    "sg:orig_category":"Brood, gebak and snoepgoed",
    "sg:phone":"+32 16 53 07 91",
    "sg:postcode":"3130",
    "sg:province":"Vlaams-Brabant",
    "wof:name":"Serneels Frans & Marcel",
    "wof:placetype":"venue"
},
  "geometry": {"coordinates":[4.7894821167,51.0195503235],"type":"Point"}
}