{
  "type": "Feature",
  "properties": {
    "addr:full":"Rue De Sugy 26 Vaux-sur-sure Luxembourg 6640",
    "addr:housenumber":"26",
    "addr:postcode":"6640",
    "addr:street":"Rue De Sugy",
    "iso:country":"BE",
    "sg:address":"Rue De Sugy 26",
    "sg:city":"Vaux-sur-sure",
    "sg:classifiers":[
        {
            "category":"Arena",
            "subcategory":"Sports Club",
            "type":"Entertainment"
        }
    ],
    "sg:phone":"+32 61 26 62 43",
    "sg:postcode":"6640",
    "sg:province":"Luxembourg",
    "sg:tags":[
        "terrain",
        "hors",
        "de",
        "installation",
        "sportifs"
    ],
    "wof:name":"Wallonia Club Sibret",
    "wof:placetype":"venue"
},
  "geometry": {"coordinates":[5.5671000481,49.91065979],"type":"Point"}
}