{
  "type": "Feature",
  "properties": {
    "addr:full":"Chauss\u00c9e D\u00b4argenteau 34 Vis\u00c9 Li\u00e8ge 4601",
    "addr:housenumber":"34",
    "addr:postcode":"4601",
    "addr:street":"Chausse\u0301E D\u00b4Argenteau",
    "iso:country":"BE",
    "sg:address":"Chauss\u00c9e D\u00b4argenteau 34",
    "sg:city":"Vis\u00c9",
    "sg:orig_category":"Ordinateurs and \u00e9quipement informatique",
    "sg:phone":"+32 4 374 92 74",
    "sg:postcode":"4601",
    "sg:province":"Li\u00e8ge",
    "wof:name":"Fe. Vis\u00c9logic",
    "wof:placetype":"venue"
},
  "geometry": {"coordinates":[5.6874017715,50.6957092285],"type":"Point"}
}