{
  "type": "Feature",
  "properties": {
    "iso:country":"BE",
    "sg:address":"Place De Limage 3",
    "sg:city":"Braives",
    "sg:orig_category":"Enseignement maternel and primaire",
    "sg:phone":"+32 19 56 62 21",
    "sg:postcode":"4260",
    "sg:province":"Li\u00e8ge",
    "wof:name":"Ecole Fondamentale Libre",
    "wof:placetype":"venue"
},
  "geometry": {"coordinates":[5.1478729248,50.6277618408],"type":"Point"}
}