{
  "type": "Feature",
  "properties": {
    "addr:full":"Rue Bollinckx 15a Bruxelles (anderlecht) Bruxelles-Capitale 1070",
    "addr:housenumber":"15a",
    "addr:postcode":"1070",
    "addr:street":"Rue Bollinckx",
    "iso:country":"BE",
    "sg:address":"Rue Bollinckx 15a",
    "sg:city":"Bruxelles (anderlecht)",
    "sg:classifiers":[
        {
            "category":"Shopping",
            "type":"Retail Goods"
        }
    ],
    "sg:phone":"+32 2 521 62 19",
    "sg:postcode":"1070",
    "sg:province":"Bruxelles-Capitale",
    "sg:tags":[
        "product",
        "cleaning",
        "maintenance"
    ],
    "wof:name":"Suneco Sa",
    "wof:placetype":"venue"
},
  "geometry": {"coordinates":[4.3051171303,50.820766449],"type":"Point"}
}