{
  "type": "Feature",
  "properties": {
    "addr:full":"Lebekestraat 69 Ninove (outer) Oost-Vlaanderen 9406",
    "addr:housenumber":"69",
    "addr:postcode":"9406",
    "addr:street":"Lebekestraat;Outer Oost-Vlaanderen",
    "iso:country":"BE",
    "sg:address":"Lebekestraat 69",
    "sg:city":"Ninove (outer)",
    "sg:classifiers":[
        {
            "category":"Autos & Motor Vehicles",
            "subcategory":"Automobile Sales",
            "type":"Retail Goods"
        }
    ],
    "sg:phone":"+32 54 32 33 83",
    "sg:postcode":"9406",
    "sg:province":"Oost-Vlaanderen",
    "sg:tags":[
        "car",
        "used",
        "-"
    ],
    "wof:name":"Soetaert H",
    "wof:placetype":"venue"
},
  "geometry": {"coordinates":[3.9847838879,50.8513717651],"type":"Point"}
}