{
  "type": "Feature",
  "properties": {
    "addr:full":"Bakkersdreef 25 Kalmthout Antwerpen 2920",
    "addr:housenumber":"25",
    "addr:postcode":"2920",
    "addr:street":"Bakkersdreef",
    "iso:country":"BE",
    "sg:address":"Bakkersdreef 25",
    "sg:city":"Kalmthout",
    "sg:classifiers":[
        {
            "category":"Building & Trades",
            "subcategory":"Equipment Rental",
            "type":"Services"
        }
    ],
    "sg:phone":"+32 3 666 31 27",
    "sg:postcode":"2920",
    "sg:province":"Antwerpen",
    "sg:tags":[
        "safety",
        "collective",
        "individual",
        "-"
    ],
    "wof:name":"Vdb Benelux",
    "wof:placetype":"venue"
},
  "geometry": {"coordinates":[4.47645998,51.3648147583],"type":"Point"}
}