{
  "type": "Feature",
  "properties": {
    "iso:country":"BE",
    "sg:address":"Vluchtenburgstraat 13",
    "sg:city":"Aartselaar",
    "sg:orig_category":"Installatie van houten of kunststof schrijnwerk Installatie van metalen schrijnwerk",
    "sg:phone":"+32 3 877 00 44",
    "sg:postcode":"2630",
    "sg:province":"Antwerpen",
    "wof:name":"Groven",
    "wof:placetype":"venue"
},
  "geometry": {"coordinates":[4.3731741905,51.1345901489],"type":"Point"}
}