{
  "type": "Feature",
  "properties": {
    "addr:full":"Kamershoek 31 Zele Oost-Vlaanderen 9240",
    "addr:housenumber":"31",
    "addr:postcode":"9240",
    "addr:street":"Kamershoek",
    "iso:country":"BE",
    "sg:address":"Kamershoek 31",
    "sg:city":"Zele",
    "sg:classifiers":[
        {
            "category":"Professional",
            "subcategory":"Computer Services",
            "type":"Services"
        }
    ],
    "sg:phone":"+32 495 20 21 18",
    "sg:postcode":"9240",
    "sg:province":"Oost-Vlaanderen",
    "sg:tags":[
        "network"
    ],
    "wof:name":"Lanworks Consulting",
    "wof:placetype":"venue"
},
  "geometry": {"coordinates":[4.0120358467,51.0530853271],"type":"Point"}
}