{
  "type": "Feature",
  "properties": {
    "addr:full":"Petit-audenardestraat 105 Moeskroen/mouscron Hainaut 7712",
    "addr:housenumber":"105 moeskroen;mouscron",
    "addr:postcode":"7712",
    "addr:street":"Hainaut",
    "iso:country":"BE",
    "sg:address":"Petit-audenardestraat 105",
    "sg:city":"Moeskroen/mouscron",
    "sg:orig_category":"Kansspelen",
    "sg:phone":"+32 56 33 42 66",
    "sg:postcode":"7712",
    "sg:province":"Hainaut",
    "wof:name":"Ladbroke",
    "wof:placetype":"venue"
},
  "geometry": {"coordinates":[3.2535879612,50.714931488],"type":"Point"}
}