{
  "type": "Feature",
  "properties": {
    "iso:country":"BE",
    "sg:address":"Chauss\u00c9e De Renaix 194",
    "sg:city":"Tournai",
    "sg:orig_category":"Apotheken",
    "sg:phone":"+32 69 84 44 10",
    "sg:postcode":"7500",
    "sg:province":"Hainaut",
    "wof:name":"Pharm. Verte-feuilleche",
    "wof:placetype":"venue"
},
  "geometry": {"coordinates":[3.4107730389,50.6156921387],"type":"Point"}
}