{
  "type": "Feature",
  "properties": {
    "iso:country":"BE",
    "sg:address":"Heuvelplein 23",
    "sg:city":"Essen",
    "sg:orig_category":"Protection civile",
    "sg:phone":"+32 3 667 58 38",
    "sg:postcode":"2910",
    "sg:province":"Antwerpen",
    "wof:name":"Brandweerkazerne",
    "wof:placetype":"venue"
},
  "geometry": {"coordinates":[4.4724788666,51.4647674561],"type":"Point"}
}