{
  "type": "Feature",
  "properties": {
    "addr:full":"Chauss\u00c9e De Saint-job 272 Ukkel/uccle Bruxelles-Capitale 1180",
    "addr:housenumber":"272",
    "addr:postcode":"1180",
    "addr:street":"Chausse\u0301E De Saint-Job;/",
    "iso:country":"BE",
    "sg:address":"Chauss\u00c9e De Saint-job 272",
    "sg:city":"Ukkel/uccle",
    "sg:orig_category":"Pain, p\u00e2tisseries and confiseries",
    "sg:phone":"+32 2 374 30 85",
    "sg:postcode":"1180",
    "sg:province":"Bruxelles-Capitale",
    "wof:name":"P\u00c2tisserie De Boose",
    "wof:placetype":"venue"
},
  "geometry": {"coordinates":[4.3453688622,50.7922477722],"type":"Point"}
}