{
  "type": "Feature",
  "properties": {
    "addr:full":"Za Rue De Hotleux 101 Waimes Li\u00e8ge 4950",
    "addr:housenumber":"101",
    "addr:postcode":"4950",
    "addr:street":"Za Rue De Hotleux",
    "iso:country":"BE",
    "sg:address":"Za Rue De Hotleux 101",
    "sg:city":"Waimes",
    "sg:classifiers":[
        {
            "category":"Manufacturing",
            "subcategory":"Rubber & Plastics",
            "type":"Manufacturing & Wholesale Goods"
        }
    ],
    "sg:phone":"+32 80 67 09 00",
    "sg:postcode":"4950",
    "sg:province":"Li\u00e8ge",
    "wof:name":"Bodarw\u00c9 Sa",
    "wof:placetype":"venue"
},
  "geometry": {"coordinates":[6.1110301018,50.4149055481],"type":"Point"}
}