{
  "type": "Feature",
  "properties": {
    "addr:full":"Rue De Libersart 64 Walhain (tourinnes-saint-lambert) Brabant Wallon 1457",
    "addr:housenumber":"64",
    "addr:postcode":"1457",
    "addr:street":"Rue De Libersart;Wallon",
    "iso:country":"BE",
    "sg:address":"Rue De Libersart 64",
    "sg:city":"Walhain (tourinnes-saint-lambert)",
    "sg:classifiers":[
        {
            "category":"Military Area",
            "subcategory":"Air Force Base",
            "type":"Public Place"
        }
    ],
    "sg:phone":"+32 10 68 05 85",
    "sg:postcode":"1457",
    "sg:province":"Brabant Wallon",
    "sg:tags":[
        "water",
        "treatment"
    ],
    "wof:name":"Culligan",
    "wof:placetype":"venue"
},
  "geometry": {"coordinates":[4.7175722122,50.6527671814],"type":"Point"}
}