{
  "type": "Feature",
  "properties": {
    "addr:full":"Kroonstraat 9 Evergem (ertvelde) Oost-Vlaanderen 9940",
    "addr:housenumber":"9",
    "addr:postcode":"9940",
    "addr:street":"Kroonstraat;Ertvelde Oost-Vlaanderen",
    "iso:country":"BE",
    "sg:address":"Kroonstraat 9",
    "sg:city":"Evergem (ertvelde)",
    "sg:classifiers":[
        {
            "category":"Manufacturing",
            "subcategory":"Signs",
            "type":"Manufacturing & Wholesale Goods"
        }
    ],
    "sg:phone":"+32 9 344 55 40",
    "sg:postcode":"9940",
    "sg:province":"Oost-Vlaanderen",
    "sg:tags":[
        "-",
        "illuminated"
    ],
    "wof:name":"Carlo (publi)",
    "wof:placetype":"venue"
},
  "geometry": {"coordinates":[3.7503650188,51.1802215576],"type":"Point"}
}