{
  "type": "Feature",
  "properties": {
    "addr:full":"Berlaarsestraat 26 Lier Antwerpen 2500",
    "addr:housenumber":"26",
    "addr:postcode":"2500",
    "addr:street":"Berlaarsestraat",
    "iso:country":"BE",
    "sg:address":"Berlaarsestraat 26",
    "sg:city":"Lier",
    "sg:orig_category":"Schoenen",
    "sg:phone":"+32 3 489 06 70",
    "sg:postcode":"2500",
    "sg:province":"Antwerpen",
    "wof:name":"De Korenbloem",
    "wof:placetype":"venue"
},
  "geometry": {"coordinates":[4.5760707855,51.1297149658],"type":"Point"}
}