{
  "type": "Feature",
  "properties": {
    "iso:country":"BE",
    "sg:address":"Nijverheidslaan 2",
    "sg:city":"Liedekerke",
    "sg:orig_category":"Entretien and r\u00e9parations de voitures. V\u00e9hicules automobiles",
    "sg:phone":"+32 53 66 65 49",
    "sg:postcode":"1770",
    "sg:province":"Vlaams-Brabant",
    "wof:name":"Garage De Vriendt",
    "wof:placetype":"venue"
},
  "geometry": {"coordinates":[4.0956110954,50.8845176697],"type":"Point"}
}