{
  "type": "Feature",
  "properties": {
    "iso:country":"BE",
    "sg:address":"31",
    "sg:city":"Vaart Links 9850 Nevele",
    "sg:classifiers":[
        {
            "category":"Food & Beverages",
            "subcategory":"Groceries & Convenience Stores",
            "type":"Retail Goods"
        }
    ],
    "sg:phone":"+32 9 371 63 13",
    "sg:postcode":"31",
    "sg:tags":[
        "product",
        "related"
    ],
    "wof:name":"Vital Nougat Nv",
    "wof:placetype":"venue"
},
  "geometry": {"coordinates":[3.5518009663,51.0343132019],"type":"Point"}
}