{
  "type": "Feature",
  "properties": {
    "addr:full":"R De La Vallee 53 Bouillon Luxembourg 6830",
    "addr:housenumber":"53",
    "addr:postcode":"6830",
    "addr:street":"Vallee",
    "iso:country":"BE",
    "sg:address":"R De La Vallee 53",
    "sg:city":"Bouillon",
    "sg:classifiers":[
        {
            "category":"Travel",
            "subcategory":"Resort",
            "type":"Entertainment"
        }
    ],
    "sg:phone":"+32 61 46 72 43",
    "sg:postcode":"6830",
    "sg:province":"Luxembourg",
    "sg:tags":[
        "farm",
        "house",
        "holiday",
        "guest"
    ],
    "wof:name":"Schneider",
    "wof:placetype":"venue"
},
  "geometry": {"coordinates":[5.0699849129,49.7954597473],"type":"Point"}
}