{
  "type": "Feature",
  "properties": {
    "addr:full":"Eeksken 40 Evergem Oost-Vlaanderen 9940",
    "addr:housenumber":"40",
    "addr:postcode":"9940",
    "addr:street":"Eeksken;Oost-Vlaanderen",
    "iso:country":"BE",
    "sg:address":"Eeksken 40",
    "sg:city":"Evergem",
    "sg:orig_category":"P\u00e9pini\u00e9ristes",
    "sg:phone":"+32 9 357 23 20",
    "sg:postcode":"9940",
    "sg:province":"Oost-Vlaanderen",
    "wof:name":"Nico Reynvoet",
    "wof:placetype":"venue"
},
  "geometry": {"coordinates":[3.6473200321,51.1362113953],"type":"Point"}
}