{
  "type": "Feature",
  "properties": {
    "addr:full":"Rue De La Colonne 3 Sint-jans-molenbeek/molenbeek-saint-jean Bruxelles-Capitale 1080",
    "addr:housenumber":"3",
    "addr:postcode":"1080",
    "addr:street":"Rue De La Colonne",
    "iso:country":"BE",
    "sg:address":"Rue De La Colonne 3",
    "sg:city":"Sint-jans-molenbeek/molenbeek-saint-jean",
    "sg:orig_category":"Architectes",
    "sg:phone":"+32 2 245 95 90",
    "sg:postcode":"1080",
    "sg:province":"Bruxelles-Capitale",
    "wof:name":"Ahmed Lassouli",
    "wof:placetype":"venue"
},
  "geometry": {"coordinates":[4.3363528252,50.8533248901],"type":"Point"}
}