{
  "type": "Feature",
  "properties": {
    "iso:country":"BE",
    "sg:address":"Breugelweg 8",
    "sg:city":"Overpelt",
    "sg:classifiers":[
        {
            "category":"Cafe",
            "type":"Food & Drink"
        }
    ],
    "sg:phone":"+32 11 66 16 32",
    "sg:postcode":"3900",
    "sg:province":"Limburg",
    "sg:tags":[
        "caf\u00e9s"
    ],
    "wof:name":"Jacobus Willekens",
    "wof:placetype":"venue"
},
  "geometry": {"coordinates":[5.4277000427,51.2072410583],"type":"Point"}
}