{
  "type": "Feature",
  "properties": {
    "iso:country":"BE",
    "sg:address":"Chauss\u00e9e De Waterloo 711",
    "sg:city":"Bruxelles (uccle)",
    "sg:classifiers":[
        {
            "category":"Shopping",
            "subcategory":"Clothing, Apparel, & Fashions",
            "type":"Retail Goods"
        }
    ],
    "sg:phone":"+32 2 345 51 33",
    "sg:postcode":"1180",
    "sg:province":"Bruxelles-Capitale",
    "sg:tags":[
        "lady",
        "clothing",
        "-"
    ],
    "wof:name":"C\u00f4t\u00e9 Maille",
    "wof:placetype":"venue"
},
  "geometry": {"coordinates":[4.3668951988,50.8157424927],"type":"Point"}
}