{
  "type": "Feature",
  "properties": {
    "addr:full":"Kerkhovensesteenweg 366 Lommel Limburg 3920",
    "addr:housenumber":"366",
    "addr:postcode":"3920",
    "addr:street":"Kerkhovensesteenweg",
    "iso:country":"BE",
    "sg:address":"Kerkhovensesteenweg 366",
    "sg:city":"Lommel",
    "sg:classifiers":[
        {
            "category":"Fast Food",
            "type":"Food & Drink"
        }
    ],
    "sg:phone":"+32 11 39 30 15",
    "sg:postcode":"3920",
    "sg:province":"Limburg",
    "sg:tags":[
        "meeneem",
        "restaurant"
    ],
    "wof:name":"Frituur Kris",
    "wof:placetype":"venue"
},
  "geometry": {"coordinates":[5.2699708939,51.1644363403],"type":"Point"}
}