{
  "type": "Feature",
  "properties": {
    "iso:country":"BE",
    "sg:address":"Sint-gilliskoorstraat 19",
    "sg:city":"Brugge",
    "sg:classifiers":[
        {
            "category":"Real Estate",
            "subcategory":"Architect",
            "type":"Services"
        }
    ],
    "sg:phone":"+32 50 33 12 08",
    "sg:postcode":"8000",
    "sg:province":"West-Vlaanderen",
    "wof:name":"Davans H",
    "wof:placetype":"venue"
},
  "geometry": {"coordinates":[3.2285490036,51.2145843506],"type":"Point"}
}