{
  "type": "Feature",
  "properties": {
    "addr:full":"Rue De Pr\u00c9t\u00c9ry Purnode Namur 5530",
    "addr:postcode":"5530",
    "addr:street":"Rue De Pre\u0301Te\u0301Ry",
    "iso:country":"BE",
    "sg:address":"Rue De Pr\u00c9t\u00c9ry",
    "sg:city":"Purnode",
    "sg:orig_category":"Royal Canin. Clubs de sport",
    "sg:phone":"+32 82 61 32 59",
    "sg:postcode":"5530",
    "sg:province":"Namur",
    "wof:name":"Fabaty Sa",
    "wof:placetype":"venue"
},
  "geometry": {"coordinates":[4.9418768883,50.3105773926],"type":"Point"}
}