{
  "type": "Feature",
  "properties": {
    "iso:country":"BE",
    "sg:address":"Chauss\u00c9e De Mons 122",
    "sg:city":"Braine-le-comte",
    "sg:orig_category":"Rundveehouders",
    "sg:phone":"+32 67 55 22 41",
    "sg:postcode":"7090",
    "sg:province":"Hainaut",
    "wof:name":"Louis Vincart",
    "wof:placetype":"venue"
},
  "geometry": {"coordinates":[4.1224598885,50.5999679565],"type":"Point"}
}