{
  "type": "Feature",
  "properties": {
    "addr:full":"Rue Gabrielle 63 Bruxelles (uccle) Bruxelles-Capitale 1180",
    "addr:housenumber":"63",
    "addr:postcode":"1180",
    "addr:street":"Rue Gabrielle",
    "iso:country":"BE",
    "sg:address":"Rue Gabrielle 63",
    "sg:city":"Bruxelles (uccle)",
    "sg:classifiers":[
        {
            "category":"Professional",
            "subcategory":"Art Services",
            "type":"Services"
        }
    ],
    "sg:phone":"+32 2 344 56 53",
    "sg:postcode":"1180",
    "sg:province":"Bruxelles-Capitale",
    "sg:tags":[
        "-",
        "painter",
        "artist"
    ],
    "wof:name":"Grand Jean R",
    "wof:placetype":"venue"
},
  "geometry": {"coordinates":[4.359539032,50.8135452271],"type":"Point"}
}