{
  "type": "Feature",
  "properties": {
    "addr:full":"Provinciesteenweg 707 Boechout Antwerpen 2530",
    "addr:housenumber":"707",
    "addr:postcode":"2530",
    "addr:street":"Provinciesteenweg",
    "iso:country":"BE",
    "sg:address":"Provinciesteenweg 707",
    "sg:city":"Boechout",
    "sg:orig_category":"Voertuigen",
    "sg:phone":"+32 3 454 12 29",
    "sg:postcode":"2530",
    "sg:province":"Antwerpen",
    "wof:name":"H.p. Cars",
    "wof:placetype":"venue"
},
  "geometry": {"coordinates":[4.5221319199,51.1547775269],"type":"Point"}
}