{
  "type": "Feature",
  "properties": {
    "addr:full":"Borgwormsesteenweg 31 Sint-truiden Limburg 3800",
    "addr:housenumber":"31",
    "addr:postcode":"3800",
    "addr:street":"Borgwormsesteenweg",
    "iso:country":"BE",
    "sg:address":"Borgwormsesteenweg 31",
    "sg:city":"Sint-truiden",
    "sg:classifiers":[
        {
            "category":"Personal",
            "subcategory":"Beauty Salon",
            "type":"Services"
        }
    ],
    "sg:phone":"+32 11 68 47 11",
    "sg:postcode":"3800",
    "sg:province":"Limburg",
    "sg:tags":[
        "de",
        "coiffure"
    ],
    "wof:name":"Godelieve Ramakers",
    "wof:placetype":"venue"
},
  "geometry": {"coordinates":[5.2148199081,50.7904586792],"type":"Point"}
}