{
  "type": "Feature",
  "properties": {
    "addr:full":"Professor Dewulfstraat 29 Poperinge West-Vlaanderen 8970",
    "addr:housenumber":"29",
    "addr:postcode":"8970",
    "addr:street":"Professor Dewulfstraat",
    "iso:country":"BE",
    "sg:address":"Professor Dewulfstraat 29",
    "sg:city":"Poperinge",
    "sg:orig_category":"Boucheries",
    "sg:phone":"+32 57 33 51 90",
    "sg:postcode":"8970",
    "sg:province":"West-Vlaanderen",
    "wof:name":"Wilfried Degeldere",
    "wof:placetype":"venue"
},
  "geometry": {"coordinates":[2.7304990292,50.8534355164],"type":"Point"}
}