{
  "type": "Feature",
  "properties": {
    "addr:full":"Eikenvelden 84 Geel Antwerpen 2440",
    "addr:housenumber":"84",
    "addr:postcode":"2440",
    "addr:street":"Eikenvelden",
    "iso:country":"BE",
    "sg:address":"Eikenvelden 84",
    "sg:city":"Geel",
    "sg:orig_category":"Technische studies and ingenieursactiviteiten",
    "sg:phone":"+32 14 58 76 10",
    "sg:postcode":"2440",
    "sg:province":"Antwerpen",
    "wof:name":"S.k.v.",
    "wof:placetype":"venue"
},
  "geometry": {"coordinates":[4.9906659126,51.1610794067],"type":"Point"}
}