{
  "type": "Feature",
  "properties": {
    "iso:country":"BE",
    "sg:address":"Rue Du Nouveau Monde 323",
    "sg:city":"Mouscron",
    "sg:classifiers":[
        {
            "category":"Cafe",
            "type":"Food & Drink"
        }
    ],
    "sg:phone":"+32 56 33 67 98",
    "sg:postcode":"7700",
    "sg:province":"Hainaut",
    "sg:tags":[
        "snack-bars"
    ],
    "wof:name":"Pain D'alouette",
    "wof:placetype":"venue"
},
  "geometry": {"coordinates":[3.1977388859,50.7521018982],"type":"Point"}
}