{
  "type": "Feature",
  "properties": {
    "addr:full":"Doornzele Dries 38 Evergem Oost-Vlaanderen 9940",
    "addr:housenumber":"38",
    "addr:postcode":"9940",
    "addr:street":"Dries;Oost-Vlaanderen",
    "iso:country":"BE",
    "sg:address":"Doornzele Dries 38",
    "sg:city":"Evergem",
    "sg:orig_category":"Installation de menuiserie en bois and plastique",
    "sg:phone":"+32 9 253 27 22",
    "sg:postcode":"9940",
    "sg:province":"Oost-Vlaanderen",
    "wof:name":"Koenraad Van Kersavond",
    "wof:placetype":"venue"
},
  "geometry": {"coordinates":[3.7627210617,51.1410827637],"type":"Point"}
}