{
  "type": "Feature",
  "properties": {
    "addr:full":"Avenue Brugmann 213b5 Elsene/ixelles Bruxelles-Capitale 1050",
    "addr:housenumber":"213b5",
    "addr:postcode":"1050",
    "addr:street":"Avenue Brugmann",
    "iso:country":"BE",
    "sg:address":"Avenue Brugmann 213b5",
    "sg:city":"Elsene/ixelles",
    "sg:orig_category":"Avocats and conseillers juridiques",
    "sg:phone":"+32 2 344 89 89",
    "sg:postcode":"1050",
    "sg:province":"Bruxelles-Capitale",
    "wof:name":"Ch. Ghijsbrecht",
    "wof:placetype":"venue"
},
  "geometry": {"coordinates":[4.3486409187,50.8150787354],"type":"Point"}
}