{
  "type": "Feature",
  "properties": {
    "addr:full":"Ganzenstr 33 Brugge West-Vlaanderen 8000",
    "addr:housenumber":"33",
    "addr:postcode":"8000",
    "addr:street":"Ganzenstr",
    "iso:country":"BE",
    "sg:address":"Ganzenstr 33",
    "sg:city":"Brugge",
    "sg:classifiers":[
        {
            "category":"Professional",
            "subcategory":"Business Services",
            "type":"Services"
        }
    ],
    "sg:phone":"+32 50 33 78 17",
    "sg:postcode":"8000",
    "sg:province":"West-Vlaanderen",
    "sg:tags":[
        "body",
        "advice"
    ],
    "wof:name":"Ocmw Brugge",
    "wof:placetype":"venue"
},
  "geometry": {"coordinates":[3.2353179455,51.2088813782],"type":"Point"}
}