{
  "type": "Feature",
  "properties": {
    "iso:country":"BE",
    "sg:address":"Drevestraat 10",
    "sg:city":"Staden",
    "sg:orig_category":"Rundveehouders",
    "sg:phone":"+32 51 70 18 09",
    "sg:postcode":"8840",
    "sg:province":"West-Vlaanderen",
    "wof:name":"Patrick Vynckier",
    "wof:placetype":"venue"
},
  "geometry": {"coordinates":[2.9940919876,50.9472694397],"type":"Point"}
}