{
  "type": "Feature",
  "properties": {
    "addr:full":"Beatestraat 46 Waasmunster Oost-Vlaanderen 9250",
    "addr:housenumber":"46",
    "addr:postcode":"9250",
    "addr:street":"Beatestraat",
    "iso:country":"BE",
    "sg:address":"Beatestraat 46",
    "sg:city":"Waasmunster",
    "sg:classifiers":[
        {
            "category":"Farming",
            "subcategory":"Livestock Farm",
            "type":"Manufacturing & Wholesale Goods"
        }
    ],
    "sg:phone":"+32 3 772 20 29",
    "sg:postcode":"9250",
    "sg:province":"Oost-Vlaanderen",
    "sg:tags":[
        "stud"
    ],
    "wof:name":"Heirhof ('t)",
    "wof:placetype":"venue"
},
  "geometry": {"coordinates":[4.0387411118,51.1327934265],"type":"Point"}
}