{
  "type": "Feature",
  "properties": {
    "addr:full":"Filip De Pillecynlaan 1 Hamme Oost-Vlaanderen 9220",
    "addr:housenumber":"1",
    "addr:postcode":"9220",
    "addr:street":"Filip De Pillecynlaan",
    "iso:country":"BE",
    "sg:address":"Filip De Pillecynlaan 1",
    "sg:city":"Hamme",
    "sg:orig_category":"Apotheken",
    "sg:phone":"+32 52 47 83 86",
    "sg:postcode":"9220",
    "sg:province":"Oost-Vlaanderen",
    "wof:name":"M. D'hondt",
    "wof:placetype":"venue"
},
  "geometry": {"coordinates":[4.1517300606,51.0899085999],"type":"Point"}
}