{
  "type": "Feature",
  "properties": {
    "iso:country":"BE",
    "sg:address":"Zavelbosstraat 3",
    "sg:city":"Herentals",
    "sg:classifiers":[
        {
            "category":"Manufacturing",
            "subcategory":"Metals",
            "type":"Manufacturing & Wholesale Goods"
        }
    ],
    "sg:phone":"+32 14 21 10 15",
    "sg:postcode":"2200",
    "sg:province":"Antwerpen",
    "sg:tags":[
        "treatment",
        "surface"
    ],
    "wof:name":"Peeters O.i.w. Nv",
    "wof:placetype":"venue"
},
  "geometry": {"coordinates":[4.8621878624,51.1822853088],"type":"Point"}
}