{
  "type": "Feature",
  "properties": {
    "iso:country":"BE",
    "sg:address":"Dorpstraat 41",
    "sg:city":"Leffinge",
    "sg:orig_category":"Royal Canin",
    "sg:phone":"+32 59 31 47 25",
    "sg:postcode":"8432",
    "sg:province":"West-Vlaanderen",
    "wof:name":"Het Meiklokje",
    "wof:placetype":"venue"
},
  "geometry": {"coordinates":[2.8768401146,51.1755104065],"type":"Point"}
}