{
  "type": "Feature",
  "properties": {
    "iso:country":"BE",
    "sg:address":"Place Du Touquet 4",
    "sg:city":"Mouscron",
    "sg:orig_category":"Catering and organisatie van feesten Fast food and meeneem restaurants Levering aan huis restaurants",
    "sg:phone":"+32 56 84 43 85",
    "sg:postcode":"7700",
    "sg:province":"Hainaut",
    "wof:name":"La Tourelle",
    "wof:placetype":"venue"
},
  "geometry": {"coordinates":[3.197840929,50.7406463623],"type":"Point"}
}