{
  "type": "Feature",
  "properties": {
    "addr:full":"Bergensesteenweg 3 Sint-pieters-leeuw Vlaams-Brabant 1600",
    "addr:housenumber":"3",
    "addr:postcode":"1600",
    "addr:street":"Bergensesteenweg",
    "iso:country":"BE",
    "sg:address":"Bergensesteenweg 3",
    "sg:city":"Sint-pieters-leeuw",
    "sg:classifiers":[
        {
            "category":"Restaurant",
            "type":"Food & Drink"
        }
    ],
    "sg:phone":"+32 2 331 13 68",
    "sg:postcode":"1600",
    "sg:province":"Vlaams-Brabant",
    "sg:tags":[
        "caf\u00e9s"
    ],
    "wof:name":"Taverne De Muelenbempt",
    "wof:placetype":"venue"
},
  "geometry": {"coordinates":[4.2445731163,50.780330658],"type":"Point"}
}