{
  "type": "Feature",
  "properties": {
    "iso:country":"BE",
    "sg:address":"Ruiten 7",
    "sg:city":"Turnhout",
    "sg:orig_category":"Postzegels, munten and trofee\u00ebn",
    "sg:phone":"+32 14 41 01 28",
    "sg:postcode":"2300",
    "sg:province":"Antwerpen",
    "wof:name":"Eric Roosen",
    "wof:placetype":"venue"
},
  "geometry": {"coordinates":[4.9199080467,51.310634613],"type":"Point"}
}