{
  "type": "Feature",
  "properties": {
    "addr:full":"Rue De J\u00e9rusalem 8-16 Bruxelles (schaerbeek) Bruxelles-Capitale 1030",
    "addr:housenumber":"8-16",
    "addr:postcode":"1030",
    "addr:street":"Rue De Je\u0301Rusalem",
    "iso:country":"BE",
    "sg:address":"Rue De J\u00e9rusalem 8-16",
    "sg:city":"Bruxelles (schaerbeek)",
    "sg:classifiers":[
        {
            "category":"Food & Beverages",
            "subcategory":"Supermarket",
            "type":"Retail Goods"
        }
    ],
    "sg:phone":"+32 2 215 57 99",
    "sg:postcode":"1030",
    "sg:province":"Bruxelles-Capitale",
    "sg:tags":[
        "department",
        "store"
    ],
    "wof:name":"Colruyt",
    "wof:placetype":"venue"
},
  "geometry": {"coordinates":[4.377448082,50.8673019409],"type":"Point"}
}