{
  "type": "Feature",
  "properties": {
    "addr:full":"Avenue Firmin Lecharlier 4 Bruxelles-jette Bruxelles-Capitale 1090",
    "addr:housenumber":"4",
    "addr:postcode":"1090",
    "addr:street":"Avenue Firmin Lecharlier",
    "iso:country":"BE",
    "sg:address":"Avenue Firmin Lecharlier 4",
    "sg:city":"Bruxelles-jette",
    "sg:orig_category":"Diverse bouwafwerking and reiniging Gespecialiseerde residenti\u00eble bouw Plaatsen van vloer- and muurb",
    "sg:phone":"+32 2 420 36 60",
    "sg:postcode":"1090",
    "sg:province":"Bruxelles-Capitale",
    "wof:name":"Fa\u00c7a-neuf",
    "wof:placetype":"venue"
},
  "geometry": {"coordinates":[4.3282928467,50.8720550537],"type":"Point"}
}