{
  "type": "Feature",
  "properties": {
    "addr:full":"Brechtsesteenweg 69 Malle (westmalle) Antwerpen 2390",
    "addr:housenumber":"69",
    "addr:postcode":"2390",
    "addr:street":"Brechtsesteenweg",
    "iso:country":"BE",
    "sg:address":"Brechtsesteenweg 69",
    "sg:city":"Malle (westmalle)",
    "sg:classifiers":[
        {
            "category":"Real Estate",
            "subcategory":"Surveying",
            "type":"Services"
        }
    ],
    "sg:phone":"+32 3 312 12 35",
    "sg:postcode":"2390",
    "sg:province":"Antwerpen",
    "sg:tags":[
        "lettering",
        "letter"
    ],
    "wof:name":"Arva",
    "wof:placetype":"venue"
},
  "geometry": {"coordinates":[4.6801958084,51.3005256653],"type":"Point"}
}