{
  "type": "Feature",
  "properties": {
    "iso:country":"BE",
    "sg:address":"Tongerenstraat 67",
    "sg:city":"Etterbeek/etterbeek",
    "sg:orig_category":"Slagers Voedingsspeciaalzaken",
    "sg:phone":"+32 2 733 04 36",
    "sg:postcode":"1040",
    "sg:province":"Bruxelles-Capitale",
    "wof:name":"Charcuterie Lanssens",
    "wof:placetype":"venue"
},
  "geometry": {"coordinates":[4.4009780884,50.840297699],"type":"Point"}
}