{
  "type": "Feature",
  "properties": {
    "addr:full":"Iepersestraat 465 Roeselare West-Vlaanderen 8800",
    "addr:housenumber":"465",
    "addr:postcode":"8800",
    "addr:street":"Iepersestraat",
    "iso:country":"BE",
    "sg:address":"Iepersestraat 465",
    "sg:city":"Roeselare",
    "sg:classifiers":[
        {
            "category":"Autos & Motor Vehicles",
            "subcategory":"Automobile Sales",
            "type":"Retail Goods"
        }
    ],
    "sg:phone":"+32 51 21 14 28",
    "sg:postcode":"8800",
    "sg:province":"West-Vlaanderen",
    "sg:tags":[
        "car",
        "used",
        "-"
    ],
    "wof:name":"Bmw-eddy Wyffels",
    "wof:placetype":"venue"
},
  "geometry": {"coordinates":[3.1011440754,50.9332733154],"type":"Point"}
}