{
  "type": "Feature",
  "properties": {
    "addr:full":"Rue De France 68 Rochefort Namur 5580",
    "addr:housenumber":"68",
    "addr:postcode":"5580",
    "addr:street":"Rue De France",
    "iso:country":"BE",
    "sg:address":"Rue De France 68",
    "sg:city":"Rochefort",
    "sg:orig_category":"Assurances. Comptables",
    "sg:phone":"+32 84 21 11 02",
    "sg:postcode":"5580",
    "sg:province":"Namur",
    "wof:name":"Fiduciaire Brolet",
    "wof:placetype":"venue"
},
  "geometry": {"coordinates":[5.2183260918,50.1558456421],"type":"Point"}
}