{
  "type": "Feature",
  "properties": {
    "addr:full":"Begoniastraat 75 Roeselare West-Vlaanderen 8800",
    "addr:housenumber":"75",
    "addr:postcode":"8800",
    "addr:street":"Begoniastraat",
    "iso:country":"BE",
    "sg:address":"Begoniastraat 75",
    "sg:city":"Roeselare",
    "sg:orig_category":"Imprimeries and copyshops",
    "sg:phone":"+32 51 25 21 07",
    "sg:postcode":"8800",
    "sg:province":"West-Vlaanderen",
    "wof:name":"Tom Ameye",
    "wof:placetype":"venue"
},
  "geometry": {"coordinates":[3.1416370869,50.9388275146],"type":"Point"}
}