{
  "type": "Feature",
  "properties": {
    "iso:country":"BE",
    "sg:address":"Noorderlaan 133bus 16",
    "sg:city":"Antwerpen",
    "sg:classifiers":[
        {
            "category":"Manufacturing",
            "subcategory":"Tools & Machinery",
            "type":"Manufacturing & Wholesale Goods"
        }
    ],
    "sg:phone":"+32 3 541 45 39",
    "sg:postcode":"2030",
    "sg:province":"Antwerpen",
    "sg:tags":[
        "technology",
        "plant",
        "appraisal"
    ],
    "wof:name":"Cunningham Lindsey Belgium Nv",
    "wof:placetype":"venue"
},
  "geometry": {"coordinates":[4.402130127,51.2644462585],"type":"Point"}
}