{
  "type": "Feature",
  "properties": {
    "iso:country":"BE",
    "sg:address":"Statiestraat 41",
    "sg:city":"Zwijndrecht",
    "sg:classifiers":[
        {
            "category":"Banks & Credit Unions",
            "subcategory":"Bank",
            "type":"Services"
        }
    ],
    "sg:phone":"+32 3 253 20 90",
    "sg:postcode":"2070",
    "sg:province":"Antwerpen",
    "sg:tags":[
        "savings-banks"
    ],
    "wof:name":"Centea Malschaert & Van Remoortere Bvba",
    "wof:placetype":"venue"
},
  "geometry": {"coordinates":[4.3272938728,51.2176208496],"type":"Point"}
}