{
  "type": "Feature",
  "properties": {
    "iso:country":"BE",
    "sg:address":"Rue De La Grande Ile 84",
    "sg:city":"Bruxelles",
    "sg:classifiers":[
        {
            "category":"Social Services",
            "type":"Services"
        }
    ],
    "sg:phone":"+32 2 502 66 00",
    "sg:postcode":"1000",
    "sg:province":"Bruxelles-Capitale",
    "wof:name":"Centrum Voor Algemeen Welzijnswerk/archipel-groot Eiland",
    "wof:placetype":"venue"
},
  "geometry": {"coordinates":[4.3462500572,50.8455696106],"type":"Point"}
}