{
  "type": "Feature",
  "properties": {
    "addr:full":"W.a. Mozartlaan 14 Moeskroen/mouscron Hainaut 7700",
    "addr:housenumber":"14",
    "addr:postcode":"7700",
    "addr:street":"W.A. Mozartlaan",
    "iso:country":"BE",
    "sg:address":"W.a. Mozartlaan 14",
    "sg:city":"Moeskroen/mouscron",
    "sg:orig_category":"Schoenen",
    "sg:phone":"+32 56 33 77 78",
    "sg:postcode":"7700",
    "sg:province":"Hainaut",
    "wof:name":"Primo",
    "wof:placetype":"venue"
},
  "geometry": {"coordinates":[3.2323200703,50.7400932312],"type":"Point"}
}