{
  "type": "Feature",
  "properties": {
    "addr:full":"Schoonaarde 54a Diest Vlaams-Brabant 3290",
    "addr:housenumber":"54a",
    "addr:postcode":"3290",
    "addr:street":"Schoonaarde",
    "iso:country":"BE",
    "sg:address":"Schoonaarde 54a",
    "sg:city":"Diest",
    "sg:orig_category":"Magasins de r\u00e9parations d'articles personnels et m\u00e9nagers divers. Blanchisserie, Nettoyage \u00e0 Sec and",
    "sg:phone":"+32 13 32 11 72",
    "sg:postcode":"3290",
    "sg:province":"Vlaams-Brabant",
    "wof:name":"Tapijtafwerking Schepers-baes",
    "wof:placetype":"venue"
},
  "geometry": {"coordinates":[5.0668759346,50.9932670593],"type":"Point"}
}