{
  "type": "Feature",
  "properties": {
    "addr:full":"Oude Beestenmarkt 5b6 Gent Oost-Vlaanderen 9000",
    "addr:housenumber":"5b6",
    "addr:postcode":"9000",
    "addr:street":"Oude Beestenmarkt;Oost-Vlaanderen",
    "iso:country":"BE",
    "sg:address":"Oude Beestenmarkt 5b6",
    "sg:city":"Gent",
    "sg:classifiers":[
        {
            "category":"Cafe",
            "type":"Food & Drink"
        }
    ],
    "sg:phone":"+32 9 225 56 56",
    "sg:postcode":"9000",
    "sg:province":"Oost-Vlaanderen",
    "sg:tags":[
        "caf\u00e9s"
    ],
    "wof:name":"Caf\u00c9 't Klein Zulleke",
    "wof:placetype":"venue"
},
  "geometry": {"coordinates":[3.7310390472,51.0543785095],"type":"Point"}
}