{
  "type": "Feature",
  "properties": {
    "addr:full":"Zwevegemsestraat 63 Harelbeke West-Vlaanderen 8530",
    "addr:housenumber":"63",
    "addr:postcode":"8530",
    "addr:street":"Zwevegemsestraat",
    "iso:country":"BE",
    "sg:address":"Zwevegemsestraat 63",
    "sg:city":"Harelbeke",
    "sg:orig_category":"HERSTELLING ELEKTRISCHE HUISHOUDAPPARATEN",
    "sg:phone":"+32 56 22 54 80",
    "sg:postcode":"8530",
    "sg:province":"West-Vlaanderen",
    "wof:name":"William Strobbe",
    "wof:placetype":"venue"
},
  "geometry": {"coordinates":[3.3209469318,50.8272323608],"type":"Point"}
}