{
  "type": "Feature",
  "properties": {
    "iso:country":"BE",
    "sg:address":"Zuidzandstraat 7",
    "sg:city":"Brugge",
    "sg:orig_category":"Base Shops. Mat\u00e9riel de T\u00e9l\u00e9communication",
    "sg:phone":"+32 50 33 75 18",
    "sg:postcode":"8000",
    "sg:province":"West-Vlaanderen",
    "wof:name":"Base Brugge",
    "wof:placetype":"venue"
},
  "geometry": {"coordinates":[3.2201869488,51.2054023743],"type":"Point"}
}