{
  "type": "Feature",
  "properties": {
    "addr:full":"Langenakker 6 Lede Oost-Vlaanderen 9340",
    "addr:housenumber":"6",
    "addr:postcode":"9340",
    "addr:street":"Langenakker",
    "iso:country":"BE",
    "sg:address":"Langenakker 6",
    "sg:city":"Lede",
    "sg:classifiers":[
        {
            "category":"Manufacturing",
            "subcategory":"Motor Vehicles & Parts",
            "type":"Manufacturing & Wholesale Goods"
        }
    ],
    "sg:phone":"+32 53 80 97 41",
    "sg:postcode":"9340",
    "sg:province":"Oost-Vlaanderen",
    "sg:tags":[
        "bearing"
    ],
    "wof:name":"Its & S/industrial Technical Supplies & Support Bvba",
    "wof:placetype":"venue"
},
  "geometry": {"coordinates":[3.979886055,50.9736824036],"type":"Point"}
}