{
  "type": "Feature",
  "properties": {
    "addr:full":"Koninginnelaan 66 Maasmechelen Limburg 3630",
    "addr:housenumber":"66",
    "addr:postcode":"3630",
    "addr:street":"Koninginnelaan",
    "iso:country":"BE",
    "sg:address":"Koninginnelaan 66",
    "sg:city":"Maasmechelen",
    "sg:orig_category":"Assistances juridiques. Conseillers fiscaux",
    "sg:phone":"+32 89 77 06 80",
    "sg:postcode":"3630",
    "sg:province":"Limburg",
    "wof:name":"Fiduciaire Thomassen",
    "wof:placetype":"venue"
},
  "geometry": {"coordinates":[5.7010197639,50.9807434082],"type":"Point"}
}