{
  "type": "Feature",
  "properties": {
    "iso:country":"BE",
    "sg:address":"Rue Des Briqueteries 10",
    "sg:city":"Ciney",
    "sg:orig_category":"Plaatsen van vloer- and muurbekleding Schilders Verlichting and huishoudartikelen Vloer- and muurbek",
    "sg:phone":"+32 83 21 12 57",
    "sg:postcode":"5590",
    "sg:province":"Namur",
    "wof:name":"Peintures Tirtiaux",
    "wof:placetype":"venue"
},
  "geometry": {"coordinates":[5.1135721207,50.2952308655],"type":"Point"}
}