{
  "type": "Feature",
  "properties": {
    "iso:country":"BE",
    "sg:address":"Heistraat 70ba",
    "sg:city":"Stekene",
    "sg:orig_category":"IJzerwaren, bouw- and verfmaterialen Tuinbenodigdheden Woningbouw",
    "sg:phone":"+32 3 779 50 01",
    "sg:postcode":"9190",
    "sg:province":"Oost-Vlaanderen",
    "wof:name":"Felke Prefabbouw",
    "wof:placetype":"venue"
},
  "geometry": {"coordinates":[4.0214099884,51.2171173096],"type":"Point"}
}