{
  "type": "Feature",
  "properties": {
    "iso:country":"BE",
    "sg:address":"Kruiskouterstraat 45",
    "sg:city":"Erpe-mere",
    "sg:orig_category":"HERSTELLING ELEKTRISCHE HUISHOUDAPPARATEN Huishoudapparaten, televisies and radio's",
    "sg:phone":"+32 53 83 27 18",
    "sg:postcode":"9420",
    "sg:province":"Oost-Vlaanderen",
    "wof:name":"Qm0025v.d.g. Center",
    "wof:placetype":"venue"
},
  "geometry": {"coordinates":[3.9671440125,50.9172973633],"type":"Point"}
}