{
  "type": "Feature",
  "properties": {
    "iso:country":"BE",
    "sg:address":"Ottervangerstraat 40",
    "sg:city":"Watermaal-bosvoorde/watermael-boitsfort",
    "sg:orig_category":"Artsen and specialisten",
    "sg:phone":"+32 2 672 40 54",
    "sg:postcode":"1170",
    "sg:province":"Bruxelles-Capitale",
    "wof:name":"Jean-pierre Van Aelst",
    "wof:placetype":"venue"
},
  "geometry": {"coordinates":[4.4051160812,50.8092575073],"type":"Point"}
}