{
  "type": "Feature",
  "properties": {
    "addr:full":"Hulshoekstraat 45 Lummen (linkhout) Limburg 3560",
    "addr:housenumber":"45",
    "addr:postcode":"3560",
    "addr:street":"Hulshoekstraat",
    "iso:country":"BE",
    "sg:address":"Hulshoekstraat 45",
    "sg:city":"Lummen (linkhout)",
    "sg:classifiers":[
        {
            "category":"Utilities",
            "subcategory":"Telephone",
            "type":"Services"
        }
    ],
    "sg:phone":"+32 477 35 84 25",
    "sg:postcode":"3560",
    "sg:province":"Limburg",
    "sg:tags":[
        "-",
        "internet"
    ],
    "wof:name":"Vandebroek B",
    "wof:placetype":"venue"
},
  "geometry": {"coordinates":[5.1466889381,50.9685821533],"type":"Point"}
}