{
  "type": "Feature",
  "properties": {
    "iso:country":"BE",
    "sg:address":"Rue D'oignies 145",
    "sg:city":"Aiseau-presles (aiseau)",
    "sg:classifiers":[
        {
            "category":"Personal",
            "subcategory":"Barber",
            "type":"Services"
        }
    ],
    "sg:phone":"+32 71 77 72 38",
    "sg:postcode":"6250",
    "sg:province":"Hainaut",
    "sg:tags":[
        "gentleman",
        "salon",
        "-",
        "hairdressing"
    ],
    "wof:name":"Technocoif'",
    "wof:placetype":"venue"
},
  "geometry": {"coordinates":[4.6094059944,50.4269485474],"type":"Point"}
}