{
  "type": "Feature",
  "properties": {
    "iso:country":"BE",
    "sg:address":"Avenue Du Stade 31",
    "sg:city":"Theux",
    "sg:classifiers":[
        {
            "category":"Building & Trades",
            "subcategory":"Construction",
            "type":"Services"
        }
    ],
    "sg:phone":"+32 496 86 72 83",
    "sg:postcode":"4910",
    "sg:province":"Li\u00e8ge",
    "sg:tags":[
        "carpenter"
    ],
    "wof:name":"Willems E",
    "wof:placetype":"venue"
},
  "geometry": {"coordinates":[5.8101530075,50.5398330688],"type":"Point"}
}