{
  "type": "Feature",
  "properties": {
    "addr:full":"Sluis 3 Nazareth (eke) Oost-Vlaanderen 9810",
    "addr:housenumber":"3",
    "addr:postcode":"9810",
    "addr:street":"Sluis",
    "iso:country":"BE",
    "sg:address":"Sluis 3",
    "sg:city":"Nazareth (eke)",
    "sg:orig_category":"Non-Classified Establishments",
    "sg:phone":"+32 9 382 90 90",
    "sg:postcode":"9810",
    "sg:province":"Oost-Vlaanderen",
    "wof:name":"Voeders Lauwers Nv",
    "wof:placetype":"venue"
},
  "geometry": {"coordinates":[3.6534159184,50.9555931091],"type":"Point"}
}