{
  "type": "Feature",
  "properties": {
    "iso:country":"BE",
    "sg:address":"Generaal Lotzstraat 40b8",
    "sg:city":"Ukkel/uccle",
    "sg:orig_category":"Architecten",
    "sg:phone":"+32 2 345 02 20",
    "sg:postcode":"1180",
    "sg:province":"Bruxelles-Capitale",
    "wof:name":"Olivier Michiels",
    "wof:placetype":"venue"
},
  "geometry": {"coordinates":[4.3583459854,50.8139190674],"type":"Point"}
}