{
  "type": "Feature",
  "properties": {
    "iso:country":"BE",
    "sg:address":"Rue De Temploux 47",
    "sg:city":"Jemeppe-sur-sambre",
    "sg:orig_category":"Entretien and r\u00e9parations de voitures",
    "sg:phone":"+32 71 78 50 91",
    "sg:postcode":"5190",
    "sg:province":"Namur",
    "wof:name":"Carrosserie Picavet",
    "wof:placetype":"venue"
},
  "geometry": {"coordinates":[4.7140650749,50.4817504883],"type":"Point"}
}