{
  "type": "Feature",
  "properties": {
    "addr:full":"208 Leugenberg 2180 Ekeren 208",
    "addr:housenumber":"208",
    "addr:postcode":"2180;208",
    "addr:street":"Leugenberg",
    "iso:country":"BE",
    "sg:address":"208",
    "sg:city":"Leugenberg 2180 Ekeren",
    "sg:classifiers":[
        {
            "category":"Manufacturing",
            "subcategory":"Glass & Minerals",
            "type":"Manufacturing & Wholesale Goods"
        }
    ],
    "sg:phone":"+32 3 605 18 28",
    "sg:postcode":"208",
    "sg:tags":[
        "building",
        "material"
    ],
    "wof:name":"Danny Lauryssens Nv",
    "wof:placetype":"venue"
},
  "geometry": {"coordinates":[4.411429882,51.2960700989],"type":"Point"}
}