{
  "type": "Feature",
  "properties": {
    "addr:full":"Rue Saint-denis 105 Bruxelles (forest) Bruxelles-Capitale 1190",
    "addr:housenumber":"105",
    "addr:postcode":"1190",
    "addr:street":"Rue Saint-Denis",
    "iso:country":"BE",
    "sg:address":"Rue Saint-denis 105",
    "sg:city":"Bruxelles (forest)",
    "sg:classifiers":[
        {
            "category":"Bus Stop",
            "subcategory":"None",
            "type":"Transportation"
        }
    ],
    "sg:phone":"+32 2 345 95 27",
    "sg:postcode":"1190",
    "sg:province":"Bruxelles-Capitale",
    "sg:tags":[
        "electricity",
        "-",
        "high",
        "low",
        "cabin",
        "voltage"
    ],
    "wof:name":"Getralux Sa",
    "wof:placetype":"venue"
},
  "geometry": {"coordinates":[4.3190350533,50.8146400452],"type":"Point"}
}