{
  "type": "Feature",
  "properties": {
    "addr:full":"Ducp\u00c9tiauxlaan 78 Sint-gillis/saint-gilles Bruxelles-Capitale 1060",
    "addr:housenumber":"78",
    "addr:postcode":"1060",
    "addr:street":"Ducpe\u0301Tiauxlaan",
    "iso:country":"BE",
    "sg:address":"Ducp\u00c9tiauxlaan 78",
    "sg:city":"Sint-gillis/saint-gilles",
    "sg:orig_category":"Advocaten and juridische adviseurs",
    "sg:phone":"+32 2 534 50 21",
    "sg:postcode":"1060",
    "sg:province":"Bruxelles-Capitale",
    "wof:name":"P.y. Coppin",
    "wof:placetype":"venue"
},
  "geometry": {"coordinates":[4.3500871658,50.8230018616],"type":"Point"}
}