{
  "type": "Feature",
  "properties": {
    "iso:country":"BE",
    "sg:address":"Sint-waldetrudisstraat 93",
    "sg:city":"Herentals",
    "sg:classifiers":[
        {
            "category":"Building & Trades",
            "subcategory":"Landscaping Services",
            "type":"Services"
        }
    ],
    "sg:phone":"+32 14 22 25 16",
    "sg:postcode":"2200",
    "sg:province":"Antwerpen",
    "sg:tags":[
        "gardening",
        "garden",
        "maintenance"
    ],
    "wof:name":"Vanhoutte K",
    "wof:placetype":"venue"
},
  "geometry": {"coordinates":[4.8359308243,51.1714286804],"type":"Point"}
}