{
  "type": "Feature",
  "properties": {
    "addr:full":"Lakstraat 77 Laakdal Antwerpen 2431",
    "addr:housenumber":"77",
    "addr:postcode":"2431",
    "addr:street":"Lakstraat",
    "iso:country":"BE",
    "sg:address":"Lakstraat 77",
    "sg:city":"Laakdal",
    "sg:orig_category":"Kapsalons",
    "sg:phone":"+32 14 84 12 25",
    "sg:postcode":"2431",
    "sg:province":"Antwerpen",
    "wof:name":"Fabienne Nobels",
    "wof:placetype":"venue"
},
  "geometry": {"coordinates":[4.9834132195,51.055015564],"type":"Point"}
}