{
  "type": "Feature",
  "properties": {
    "addr:full":"La Ch\u00eanaie 16 Grez-doiceau Brabant Wallon 1390",
    "addr:housenumber":"16",
    "addr:postcode":"1390",
    "addr:street":"La Che\u0302Naie",
    "iso:country":"BE",
    "sg:address":"La Ch\u00eanaie 16",
    "sg:city":"Grez-doiceau",
    "sg:classifiers":[
        {
            "category":"Real Estate",
            "subcategory":"Developer",
            "type":"Services"
        }
    ],
    "sg:phone":"+32 10 84 30 20",
    "sg:postcode":"1390",
    "sg:province":"Brabant Wallon",
    "sg:tags":[
        "project"
    ],
    "wof:name":"Groupe Constructions Et Promotions Sa",
    "wof:placetype":"venue"
},
  "geometry": {"coordinates":[4.6737098694,50.7209091187],"type":"Point"}
}