{
  "type": "Feature",
  "properties": {
    "addr:full":"Rue La Ville 18 Donceel Li\u00e8ge 4357",
    "addr:housenumber":"18",
    "addr:postcode":"4357",
    "addr:street":"Rue La Ville",
    "iso:country":"BE",
    "sg:address":"Rue La Ville 18",
    "sg:city":"Donceel",
    "sg:orig_category":"Eleveurs and marchands de porcs. Eleveurs de bovins",
    "sg:phone":"+32 4 250 26 32",
    "sg:postcode":"4357",
    "sg:province":"Li\u00e8ge",
    "wof:name":"Jaymaert Francois Et Eric",
    "wof:placetype":"venue"
},
  "geometry": {"coordinates":[5.3569288254,50.653213501],"type":"Point"}
}