{
  "type": "Feature",
  "properties": {
    "addr:full":"Rue Du Noly La Bruy\u00e8re (saint-denis) Namur 5081",
    "addr:postcode":"5081",
    "addr:street":"Rue Du Noly La Bruye\u0300Re",
    "iso:country":"BE",
    "sg:address":"Rue Du Noly",
    "sg:city":"La Bruy\u00e8re (saint-denis)",
    "sg:classifiers":[
        {
            "category":"Fast Food",
            "type":"Food & Drink"
        }
    ],
    "sg:phone":"+32 81 56 98 55",
    "sg:postcode":"5081",
    "sg:province":"Namur",
    "sg:tags":[
        "fried",
        "stand",
        "potato"
    ],
    "wof:name":"Daniel",
    "wof:placetype":"venue"
},
  "geometry": {"coordinates":[4.7729201317,50.5245246887],"type":"Point"}
}