{
  "type": "Feature",
  "properties": {
    "iso:country":"BE",
    "sg:address":"Antwerpsebaan 381",
    "sg:city":"Antwerpen",
    "sg:orig_category":"Afbraak- and draineerwerken",
    "sg:phone":"+32 3 568 63 15",
    "sg:postcode":"2040",
    "sg:province":"Antwerpen",
    "wof:name":"Cleiren",
    "wof:placetype":"venue"
},
  "geometry": {"coordinates":[4.3222289085,51.3673820496],"type":"Point"}
}