{
  "type": "Feature",
  "properties": {
    "iso:country":"BE",
    "sg:address":"Nivez\u00c9 Bas 217bh",
    "sg:city":"Jalhay",
    "sg:orig_category":"Woningbouw",
    "sg:phone":"+32 87 77 08 34",
    "sg:postcode":"4845",
    "sg:province":"Li\u00e8ge",
    "wof:name":"Label Construction",
    "wof:placetype":"venue"
},
  "geometry": {"coordinates":[5.8996210098,50.5005378723],"type":"Point"}
}