{
  "type": "Feature",
  "properties": {
    "addr:full":"Rue Lambert Dewonck 70 Juprelle (wihogne) Li\u00e8ge 4452",
    "addr:housenumber":"70",
    "addr:postcode":"4452",
    "addr:street":"Rue Lambert Dewonck;Wihogne",
    "iso:country":"BE",
    "sg:address":"Rue Lambert Dewonck 70",
    "sg:city":"Juprelle (wihogne)",
    "sg:classifiers":[
        {
            "category":"Communications",
            "subcategory":"Film & Video Production",
            "type":"Services"
        }
    ],
    "sg:phone":"+32 4 278 69 06",
    "sg:postcode":"4452",
    "sg:province":"Li\u00e8ge",
    "sg:tags":[
        "multimedia",
        "-",
        "system"
    ],
    "wof:name":"Rominet",
    "wof:placetype":"venue"
},
  "geometry": {"coordinates":[5.5091848373,50.7263183594],"type":"Point"}
}