{
  "type": "Feature",
  "properties": {
    "addr:full":"Chrysantenlaan 10 Mol Antwerpen 2400",
    "addr:housenumber":"10",
    "addr:postcode":"2400",
    "addr:street":"Chrysantenlaan",
    "iso:country":"BE",
    "sg:address":"Chrysantenlaan 10",
    "sg:city":"Mol",
    "sg:classifiers":[
        {
            "category":"Education",
            "subcategory":"School",
            "type":"Public Place"
        }
    ],
    "sg:phone":"+32 14 31 15 01",
    "sg:postcode":"2400",
    "sg:province":"Antwerpen",
    "sg:tags":[
        "secondary"
    ],
    "wof:name":"Koninklijk Atheneum",
    "wof:placetype":"venue"
},
  "geometry": {"coordinates":[5.1176919937,51.195022583],"type":"Point"}
}