{
  "type": "Feature",
  "properties": {
    "iso:country":"BE",
    "sg:address":"Dampoortstraat 113",
    "sg:city":"Brugge (sint-kruis)",
    "sg:classifiers":[
        {
            "category":"Food & Beverages",
            "subcategory":"Fruits & Vegetables",
            "type":"Retail Goods"
        }
    ],
    "sg:phone":"+32 50 35 08 09",
    "sg:postcode":"8310",
    "sg:province":"West-Vlaanderen",
    "sg:tags":[
        "-"
    ],
    "wof:name":"Fruitkorf (de)",
    "wof:placetype":"venue"
},
  "geometry": {"coordinates":[3.2396919727,51.2168159485],"type":"Point"}
}