{
  "type": "Feature",
  "properties": {
    "iso:country":"BE",
    "sg:address":"Rue De Houdain 12",
    "sg:city":"Mons",
    "sg:orig_category":"Kapsalons",
    "sg:phone":"+32 65 33 94 12",
    "sg:postcode":"7000",
    "sg:province":"Hainaut",
    "wof:name":"Coiffure Tony & Janine",
    "wof:placetype":"venue"
},
  "geometry": {"coordinates":[3.953097105,50.4523429871],"type":"Point"}
}