{
  "type": "Feature",
  "properties": {
    "iso:country":"BE",
    "sg:address":"Schorestraat 6ba",
    "sg:city":"Middelkerke",
    "sg:orig_category":"Dierenartsen",
    "sg:phone":"+32 51 55 53 55",
    "sg:postcode":"8433",
    "sg:province":"West-Vlaanderen",
    "wof:name":"Kamiel Simoens",
    "wof:placetype":"venue"
},
  "geometry": {"coordinates":[2.8475210667,51.1547775269],"type":"Point"}
}