{
  "type": "Feature",
  "properties": {
    "iso:country":"BE",
    "sg:address":"Avenue Maurice 5",
    "sg:city":"Elsene/ixelles",
    "sg:orig_category":"Avocats and conseillers juridiques",
    "sg:phone":"+32 2 647 98 80",
    "sg:postcode":"1050",
    "sg:province":"Bruxelles-Capitale",
    "wof:name":"N. Lucas",
    "wof:placetype":"venue"
},
  "geometry": {"coordinates":[4.3791251183,50.8163833618],"type":"Point"}
}