{
  "type": "Feature",
  "properties": {
    "addr:full":"Boulevard Charlemagne 1 Brussel/bruxelles 1041",
    "addr:housenumber":"1",
    "addr:postcode":"1041",
    "addr:street":"Boulevard Charlemagne;/ Bruxelles",
    "iso:country":"BE",
    "sg:address":"Boulevard Charlemagne 1",
    "sg:city":"Brussel/bruxelles",
    "sg:orig_category":"Production de films, t\u00e9l\u00e9films and vid\u00e9os",
    "sg:phone":"+32 2 285 08 74",
    "sg:postcode":"1041",
    "wof:name":"Krenotec",
    "wof:placetype":"venue"
},
  "geometry": {"coordinates":[4.3800802231,50.843711853],"type":"Point"}
}