{
  "type": "Feature",
  "properties": {
    "iso:country":"BE",
    "sg:address":"Molenstraat 12",
    "sg:city":"Ruiselede",
    "sg:orig_category":"Poissonniers and \u00e9caillers",
    "sg:phone":"+32 51 68 71 45",
    "sg:postcode":"8755",
    "sg:province":"West-Vlaanderen",
    "wof:name":"Geert Van Laere",
    "wof:placetype":"venue"
},
  "geometry": {"coordinates":[3.3930180073,51.0383415222],"type":"Point"}
}