{
  "type": "Feature",
  "properties": {
    "iso:country":"BE",
    "sg:address":"Postweg 33b-2",
    "sg:city":"Sint-pieters-leeuw (vlezenbeek)",
    "sg:classifiers":[
        {
            "category":"Social Services",
            "subcategory":"Job Training",
            "type":"Services"
        }
    ],
    "sg:phone":"+32 2 567 28 82",
    "sg:postcode":"1602",
    "sg:province":"Vlaams-Brabant",
    "sg:tags":[
        "interpreter"
    ],
    "wof:name":"De Bruyn B",
    "wof:placetype":"venue"
},
  "geometry": {"coordinates":[4.2516789436,50.8124275208],"type":"Point"}
}