{
  "type": "Feature",
  "properties": {
    "iso:country":"BE",
    "sg:address":"Rue G\u00c9n\u00c9ral Leman 148",
    "sg:city":"Etterbeek",
    "sg:classifiers":[
        {
            "category":"Restaurant",
            "type":"Food & Drink"
        }
    ],
    "sg:phone":"+32 2 735 19 47",
    "sg:postcode":"1040",
    "sg:province":"Bruxelles-Capitale",
    "wof:name":"Knossos",
    "wof:placetype":"venue"
},
  "geometry": {"coordinates":[4.3877749443,50.8369293213],"type":"Point"}
}