{
  "type": "Feature",
  "properties": {
    "iso:country":"BE",
    "sg:address":"Zandstraat 52",
    "sg:city":"Herentals",
    "sg:classifiers":[
        {
            "category":"Shopping",
            "subcategory":"Crafts & Fabrics",
            "type":"Retail Goods"
        }
    ],
    "sg:phone":"+32 14 21 33 52",
    "sg:postcode":"2200",
    "sg:province":"Antwerpen",
    "sg:tags":[
        "hi-fi",
        "equipment",
        "stereophonic",
        "-"
    ],
    "wof:name":"Cuylen Electronics Bvba",
    "wof:placetype":"venue"
},
  "geometry": {"coordinates":[4.8332619667,51.1769828796],"type":"Point"}
}