{
  "type": "Feature",
  "properties": {
    "iso:country":"BE",
    "sg:address":"Rue Vin\u00c2ve 29",
    "sg:city":"Engis",
    "sg:orig_category":"Industri\u00eble and commerci\u00eble bouw Metaalbehandeling and -bekleding",
    "sg:phone":"+32 4 275 10 11",
    "sg:postcode":"4480",
    "sg:province":"Li\u00e8ge",
    "wof:name":"Schutz Metal Product",
    "wof:placetype":"venue"
},
  "geometry": {"coordinates":[5.4090919495,50.5828933716],"type":"Point"}
}