{
  "type": "Feature",
  "properties": {
    "iso:country":"BE",
    "sg:address":"Rue Voie De Li\u00e8ge 6",
    "sg:city":"Oupeye (hermalle-sous-argenteau)",
    "sg:classifiers":[
        {
            "category":"Banks & Credit Unions",
            "subcategory":"Bureau De Change",
            "type":"Services"
        }
    ],
    "sg:phone":"+32 4 376 92 00",
    "sg:postcode":"4681",
    "sg:province":"Li\u00e8ge",
    "sg:tags":[
        "-",
        "household",
        "gas"
    ],
    "wof:name":"Zeevaert A",
    "wof:placetype":"venue"
},
  "geometry": {"coordinates":[5.6696949005,50.7144317627],"type":"Point"}
}