{
  "type": "Feature",
  "properties": {
    "addr:full":"Van Schoonbekestraat 29 Antwerpen Antwerpen 2018",
    "addr:housenumber":"29",
    "addr:postcode":"2018",
    "addr:street":"Van Schoonbekestraat",
    "iso:country":"BE",
    "sg:address":"Van Schoonbekestraat 29",
    "sg:city":"Antwerpen",
    "sg:orig_category":"Mat\u00e9riel m\u00e9dical and orthop\u00e9dique and proth\u00e8ses Fab",
    "sg:phone":"+32 3 216 09 65",
    "sg:postcode":"2018",
    "sg:province":"Antwerpen",
    "wof:name":"Dental Technik",
    "wof:placetype":"venue"
},
  "geometry": {"coordinates":[4.4085421562,51.2032966614],"type":"Point"}
}