{
  "type": "Feature",
  "properties": {
    "iso:country":"BE",
    "sg:address":"Diestse Steenweg 450",
    "sg:city":"Aarschot",
    "sg:classifiers":[
        {
            "category":"Professional",
            "subcategory":"Testing Lab",
            "type":"Services"
        }
    ],
    "sg:phone":"+32 16 50 01 55",
    "sg:postcode":"3200",
    "sg:province":"Vlaams-Brabant",
    "sg:tags":[
        "chemist"
    ],
    "wof:name":"Bladt F",
    "wof:placetype":"venue"
},
  "geometry": {"coordinates":[4.8655099869,50.9781112671],"type":"Point"}
}