{
  "type": "Feature",
  "properties": {
    "iso:country":"BE",
    "sg:address":"Parkstraat 10",
    "sg:city":"Sint-niklaas",
    "sg:classifiers":[
        {
            "category":"Shopping",
            "subcategory":"Jewelry",
            "type":"Retail Goods"
        }
    ],
    "sg:phone":"+32 3 777 83 44",
    "sg:postcode":"9100",
    "sg:province":"Oost-Vlaanderen",
    "sg:tags":[
        "purchase",
        "-",
        "sale",
        "gold"
    ],
    "wof:name":"Goudbank (de)",
    "wof:placetype":"venue"
},
  "geometry": {"coordinates":[4.1391448975,51.1651191711],"type":"Point"}
}