{
  "type": "Feature",
  "properties": {
    "iso:country":"BE",
    "sg:address":"Marktstraat 54",
    "sg:city":"Kortrijk",
    "sg:orig_category":"Parfumeries",
    "sg:phone":"+32 56 22 28 77",
    "sg:postcode":"8510",
    "sg:province":"West-Vlaanderen",
    "wof:name":"Jan Desmet",
    "wof:placetype":"venue"
},
  "geometry": {"coordinates":[3.234926939,50.8092956543],"type":"Point"}
}