{
  "type": "Feature",
  "properties": {
    "addr:full":"Koophandelstraat 19 Lokeren Oost-Vlaanderen 9160",
    "addr:housenumber":"19",
    "addr:postcode":"9160",
    "addr:street":"Koophandelstraat",
    "iso:country":"BE",
    "sg:address":"Koophandelstraat 19",
    "sg:city":"Lokeren",
    "sg:classifiers":[
        {
            "category":"Social Services",
            "type":"Services"
        }
    ],
    "sg:phone":"+32 9 348 83 81",
    "sg:postcode":"9160",
    "sg:province":"Oost-Vlaanderen",
    "wof:name":"Ver Turkse Kultuur Lokeren Vzw",
    "wof:placetype":"venue"
},
  "geometry": {"coordinates":[3.9894640446,51.1073417664],"type":"Point"}
}