{
  "type": "Feature",
  "properties": {
    "iso:country":"BE",
    "sg:address":"Rue De Bauce 65",
    "sg:city":"Namur",
    "sg:orig_category":"Entretien and r\u00e9parations de voitures",
    "sg:phone":"+32 81 44 40 25",
    "sg:postcode":"5020",
    "sg:province":"Namur",
    "wof:name":"Garage Renier",
    "wof:placetype":"venue"
},
  "geometry": {"coordinates":[4.7952418327,50.4352035522],"type":"Point"}
}