{
  "type": "Feature",
  "properties": {
    "iso:country":"BE",
    "sg:address":"Kerkstraat 12",
    "sg:city":"Boutersem (kerkom)",
    "sg:classifiers":[
        {
            "category":"Communications",
            "subcategory":"Film & Video Production",
            "type":"Services"
        }
    ],
    "sg:phone":"+32 16 72 04 70",
    "sg:postcode":"3370",
    "sg:province":"Vlaams-Brabant",
    "sg:tags":[
        "sound",
        "recording",
        "studio"
    ],
    "wof:name":"Castle Studio's",
    "wof:placetype":"venue"
},
  "geometry": {"coordinates":[4.8692479134,50.8547935486],"type":"Point"}
}