{
  "type": "Feature",
  "properties": {
    "addr:full":"Rue Des Alli\u00e9s 275 Bruxelles (forest) Bruxelles-Capitale 1190",
    "addr:housenumber":"275",
    "addr:postcode":"1190",
    "addr:street":"Rue Des Allie\u0301S",
    "iso:country":"BE",
    "sg:address":"Rue Des Alli\u00e9s 275",
    "sg:city":"Bruxelles (forest)",
    "sg:classifiers":[
        {
            "category":"Organizations",
            "subcategory":"Professional Association",
            "type":"Services"
        }
    ],
    "sg:phone":"+32 2 346 87 47",
    "sg:postcode":"1190",
    "sg:province":"Bruxelles-Capitale",
    "sg:tags":[
        "artist",
        "make-up"
    ],
    "wof:name":"Body Art Belgium",
    "wof:placetype":"venue"
},
  "geometry": {"coordinates":[4.3278169632,50.8236198425],"type":"Point"}
}