{
  "type": "Feature",
  "properties": {
    "addr:full":"Bergstraat 5 Wortegem-petegem Oost-Vlaanderen 9790",
    "addr:housenumber":"5",
    "addr:postcode":"9790",
    "addr:street":"Bergstraat",
    "iso:country":"BE",
    "sg:address":"Bergstraat 5",
    "sg:city":"Wortegem-petegem",
    "sg:orig_category":"Eleveurs de bovins. Eleveurs and marchands de porcs",
    "sg:phone":"+32 55 31 16 04",
    "sg:postcode":"9790",
    "sg:province":"Oost-Vlaanderen",
    "wof:name":"Hubert Vandeputte",
    "wof:placetype":"venue"
},
  "geometry": {"coordinates":[3.5380840302,50.8424377441],"type":"Point"}
}