{
  "type": "Feature",
  "properties": {
    "iso:country":"BE",
    "sg:address":"Rue Pr\u00c9 Saint-jean 31",
    "sg:city":"Eghez\u00c9e",
    "sg:orig_category":"Architectes",
    "sg:phone":"+32 81 65 60 03",
    "sg:postcode":"5310",
    "sg:province":"Namur",
    "wof:name":"Emmanuelle Romboux",
    "wof:placetype":"venue"
},
  "geometry": {"coordinates":[4.8288598061,50.5820808411],"type":"Point"}
}