{
  "type": "Feature",
  "properties": {
    "addr:full":"Rue Courte De La Station 3 Braine-le-chateau Brabant Wallon 1440",
    "addr:housenumber":"3",
    "addr:postcode":"1440",
    "addr:street":"Rue Courte De La Station;Brabant Wallon",
    "iso:country":"BE",
    "sg:address":"Rue Courte De La Station 3",
    "sg:city":"Braine-le-chateau",
    "sg:orig_category":"Boekbinderijen and afwerking Drukkerijen and copyshops Kantoormateriaal",
    "sg:phone":"+32 2 366 18 30",
    "sg:postcode":"1440",
    "sg:province":"Brabant Wallon",
    "wof:name":"Dynamic Services",
    "wof:placetype":"venue"
},
  "geometry": {"coordinates":[4.2728857994,50.6816215515],"type":"Point"}
}