{
  "type": "Feature",
  "properties": {
    "addr:full":"Sur Les Fontaines 50 Lierneux Li\u00e8ge 4990",
    "addr:housenumber":"50",
    "addr:postcode":"4990",
    "addr:street":"Sur Les Fontaines",
    "iso:country":"BE",
    "sg:address":"Sur Les Fontaines 50",
    "sg:city":"Lierneux",
    "sg:orig_category":"Boekhouders",
    "sg:phone":"+32 80 31 83 33",
    "sg:postcode":"4990",
    "sg:province":"Li\u00e8ge",
    "wof:name":"Luc Matz",
    "wof:placetype":"venue"
},
  "geometry": {"coordinates":[5.8133349419,50.3098564148],"type":"Point"}
}