{
  "type": "Feature",
  "properties": {
    "addr:full":"Molenstraat 59b1c Herentals Antwerpen 2200",
    "addr:housenumber":"59b1c",
    "addr:postcode":"2200",
    "addr:street":"Molenstraat",
    "iso:country":"BE",
    "sg:address":"Molenstraat 59b1c",
    "sg:city":"Herentals",
    "sg:orig_category":"Avocats and conseillers juridiques",
    "sg:phone":"+32 14 26 78 68",
    "sg:postcode":"2200",
    "sg:province":"Antwerpen",
    "wof:name":"Hilde Van Dijck",
    "wof:placetype":"venue"
},
  "geometry": {"coordinates":[4.8341670036,51.1742935181],"type":"Point"}
}