{
  "type": "Feature",
  "properties": {
    "addr:full":"Holstraat 9 Machelen Vlaams-Brabant 1831",
    "addr:housenumber":"9",
    "addr:postcode":"1831",
    "addr:street":"Holstraat",
    "iso:country":"BE",
    "sg:address":"Holstraat 9",
    "sg:city":"Machelen",
    "sg:orig_category":"Blanchisseries and teintureries",
    "sg:phone":"+32 2 251 15 70",
    "sg:postcode":"1831",
    "sg:province":"Vlaams-Brabant",
    "wof:name":"Wasserij Perfekt",
    "wof:placetype":"venue"
},
  "geometry": {"coordinates":[4.4251980782,50.9026794434],"type":"Point"}
}