{
  "type": "Feature",
  "properties": {
    "addr:full":"Avenue Reine Elisabeth 73 Namur Namur 5000",
    "addr:housenumber":"73",
    "addr:postcode":"5000",
    "addr:street":"Avenue Reine Elisabeth",
    "iso:country":"BE",
    "sg:address":"Avenue Reine Elisabeth 73",
    "sg:city":"Namur",
    "sg:orig_category":"Enseignement maternel and primaire",
    "sg:phone":"+32 81 23 14 06",
    "sg:postcode":"5000",
    "sg:province":"Namur",
    "wof:name":"Ecole Prim. Communale",
    "wof:placetype":"venue"
},
  "geometry": {"coordinates":[4.9248728752,50.4691963196],"type":"Point"}
}