{
  "type": "Feature",
  "properties": {
    "iso:country":"BE",
    "sg:address":"Rue D'omez\u00c9e 135a",
    "sg:city":"Florennes",
    "sg:orig_category":"Bloemen and planten Gh Boomkwekerijen",
    "sg:phone":"+32 82 68 89 73",
    "sg:postcode":"5620",
    "sg:province":"Namur",
    "wof:name":"Sapins De Noel Dufour",
    "wof:placetype":"venue"
},
  "geometry": {"coordinates":[4.7431349754,50.2308425903],"type":"Point"}
}