{
  "type": "Feature",
  "properties": {
    "iso:country":"BE",
    "sg:address":"Lage Kaart 64",
    "sg:city":"Brasschaat",
    "sg:orig_category":"Juwelen and horloges",
    "sg:phone":"+32 3 653 18 28",
    "sg:postcode":"2930",
    "sg:province":"Antwerpen",
    "wof:name":"Guido Daeseleire",
    "wof:placetype":"venue"
},
  "geometry": {"coordinates":[4.4595937729,51.294719696],"type":"Point"}
}