{
  "type": "Feature",
  "properties": {
    "addr:full":"Guido Gezellestraat 12 Hasselt Limburg 3500",
    "addr:housenumber":"12",
    "addr:postcode":"3500",
    "addr:street":"Guido Gezellestraat",
    "iso:country":"BE",
    "sg:address":"Guido Gezellestraat 12",
    "sg:city":"Hasselt",
    "sg:orig_category":"Architecten",
    "sg:phone":"+32 11 22 52 57",
    "sg:postcode":"3500",
    "sg:province":"Limburg",
    "wof:name":"Bloemen Winand & Govaerts",
    "wof:placetype":"venue"
},
  "geometry": {"coordinates":[5.3427357674,50.9294586182],"type":"Point"}
}