{
  "type": "Feature",
  "properties": {
    "iso:country":"BE",
    "sg:address":"Leuvensesteenweg 124",
    "sg:city":"Boutersem",
    "sg:orig_category":"Pleisterwerk",
    "sg:phone":"+32 16 73 36 94",
    "sg:postcode":"3370",
    "sg:province":"Vlaams-Brabant",
    "wof:name":"Richard Bamps",
    "wof:placetype":"venue"
},
  "geometry": {"coordinates":[4.8485898972,50.8361816406],"type":"Point"}
}