{
  "type": "Feature",
  "properties": {
    "addr:full":"Zeedijk 127 Blankenberge West-Vlaanderen 8370",
    "addr:housenumber":"127",
    "addr:postcode":"8370",
    "addr:street":"Zeedijk",
    "iso:country":"BE",
    "sg:address":"Zeedijk 127",
    "sg:city":"Blankenberge",
    "sg:classifiers":[
        {
            "category":"Travel",
            "subcategory":"Resort",
            "type":"Entertainment"
        }
    ],
    "sg:phone":"+32 50 43 50 43",
    "sg:postcode":"8370",
    "sg:province":"West-Vlaanderen",
    "sg:tags":[
        "vacation"
    ],
    "wof:name":"Petit Rouge",
    "wof:placetype":"venue"
},
  "geometry": {"coordinates":[3.1267869473,51.3157806396],"type":"Point"}
}