{
  "type": "Feature",
  "properties": {
    "addr:full":"Turnhoutseweg 34 Ravels (weelde) Antwerpen 2381",
    "addr:housenumber":"34",
    "addr:postcode":"2381",
    "addr:street":"Turnhoutseweg",
    "iso:country":"BE",
    "sg:address":"Turnhoutseweg 34",
    "sg:city":"Ravels (weelde)",
    "sg:classifiers":[
        {
            "category":"Wholesale",
            "subcategory":"Machinery & Supplies",
            "type":"Manufacturing & Wholesale Goods"
        }
    ],
    "sg:phone":"+32 14 65 86 98",
    "sg:postcode":"2381",
    "sg:province":"Antwerpen",
    "sg:tags":[
        "agricultural",
        "tractor"
    ],
    "wof:name":"Moeskops M",
    "wof:placetype":"venue"
},
  "geometry": {"coordinates":[5.006374836,51.4099845886],"type":"Point"}
}