{
  "type": "Feature",
  "properties": {
    "addr:full":"Edingsesteenweg 353 Ninove Oost-Vlaanderen 9400",
    "addr:housenumber":"353",
    "addr:postcode":"9400",
    "addr:street":"Edingsesteenweg",
    "iso:country":"BE",
    "sg:address":"Edingsesteenweg 353",
    "sg:city":"Ninove",
    "sg:orig_category":"Banques and organismes de cr\u00e9dit",
    "sg:phone":"+32 54 33 52 43",
    "sg:postcode":"9400",
    "sg:province":"Oost-Vlaanderen",
    "wof:name":"Kbc",
    "wof:placetype":"venue"
},
  "geometry": {"coordinates":[4.0263299942,50.8269996643],"type":"Point"}
}