{
  "type": "Feature",
  "properties": {
    "iso:country":"BE",
    "sg:address":"Meldertsestraat 40",
    "sg:city":"Halen",
    "sg:orig_category":"Banken and kredietinstellingen",
    "sg:phone":"+32 13 44 17 17",
    "sg:postcode":"3545",
    "sg:province":"Limburg",
    "wof:name":"Centea",
    "wof:placetype":"venue"
},
  "geometry": {"coordinates":[5.1251149178,50.9805183411],"type":"Point"}
}