{
  "type": "Feature",
  "properties": {
    "addr:full":"Antwerpsesteenweg 17 Malle (oostmalle) Antwerpen 2390",
    "addr:housenumber":"17",
    "addr:postcode":"2390",
    "addr:street":"Antwerpsesteenweg",
    "iso:country":"BE",
    "sg:address":"Antwerpsesteenweg 17",
    "sg:city":"Malle (oostmalle)",
    "sg:classifiers":[
        {
            "category":"Professional",
            "type":"Services"
        }
    ],
    "sg:phone":"+32 3 309 97 77",
    "sg:postcode":"2390",
    "sg:province":"Antwerpen",
    "sg:tags":[
        "surveyor",
        "-",
        "valuer"
    ],
    "wof:name":"Ravimo Nv",
    "wof:placetype":"venue"
},
  "geometry": {"coordinates":[4.7322587967,51.300945282],"type":"Point"}
}