{
  "type": "Feature",
  "properties": {
    "iso:country":"BE",
    "sg:address":"Route De Ciney 0",
    "sg:city":"Rochefort",
    "sg:orig_category":"Beheer van afvalopslag- and stortplaatsen",
    "sg:phone":"+32 84 22 11 95",
    "sg:postcode":"5580",
    "sg:province":"Namur",
    "wof:name":"Parcs A Conteneurs Rochefort",
    "wof:placetype":"venue"
},
  "geometry": {"coordinates":[5.2112751007,50.170539856],"type":"Point"}
}