{
  "type": "Feature",
  "properties": {
    "iso:country":"BE",
    "sg:address":"Wolvenstraat 5",
    "sg:city":"Harelbeke",
    "sg:orig_category":"Rev\u00eatements pour sols and murs. Construction de rev\u00eatements and voies d'acc\u00e8s r\u00e9sidentiels",
    "sg:phone":"+32 56 71 67 25",
    "sg:postcode":"8530",
    "sg:province":"West-Vlaanderen",
    "wof:name":"Marnix De Cock",
    "wof:placetype":"venue"
},
  "geometry": {"coordinates":[3.3196339607,50.8614883423],"type":"Point"}
}