{
  "type": "Feature",
  "properties": {
    "addr:full":"Rue Pimpernelle 21 Marche-en-famenne (aye) Luxembourg 6900",
    "addr:housenumber":"21",
    "addr:postcode":"6900",
    "addr:street":"Rue Pimpernelle",
    "iso:country":"BE",
    "sg:address":"Rue Pimpernelle 21",
    "sg:city":"Marche-en-famenne (aye)",
    "sg:classifiers":[
        {
            "category":"Real Estate",
            "subcategory":"Architect",
            "type":"Services"
        }
    ],
    "sg:phone":"+32 84 31 22 33",
    "sg:postcode":"6900",
    "sg:province":"Luxembourg",
    "wof:name":"Lecocq P",
    "wof:placetype":"venue"
},
  "geometry": {"coordinates":[5.3247327805,50.2236709595],"type":"Point"}
}