{
  "type": "Feature",
  "properties": {
    "addr:full":"Gatti De Gamondstraat 212 Ukkel/uccle Bruxelles-Capitale 1180",
    "addr:housenumber":"212",
    "addr:postcode":"1180",
    "addr:street":"Gamondstraat;/",
    "iso:country":"BE",
    "sg:address":"Gatti De Gamondstraat 212",
    "sg:city":"Ukkel/uccle",
    "sg:orig_category":"Textiel",
    "sg:phone":"+32 2 376 39 60",
    "sg:postcode":"1180",
    "sg:province":"Bruxelles-Capitale",
    "wof:name":"Roland Charlier",
    "wof:placetype":"venue"
},
  "geometry": {"coordinates":[4.3276548386,50.7991142273],"type":"Point"}
}