{
  "type": "Feature",
  "properties": {
    "addr:full":"Avenue Des Sept Bonniers 19 Ukkel/uccle Bruxelles-Capitale 1180",
    "addr:housenumber":"19",
    "addr:postcode":"1180",
    "addr:street":"Avenue Des Sept Bonniers;/",
    "iso:country":"BE",
    "sg:address":"Avenue Des Sept Bonniers 19",
    "sg:city":"Ukkel/uccle",
    "sg:orig_category":"R\u00e9cup\u00e9ration de mati\u00e8res m\u00e9talliques recyclables and d\u00e9molisseurs de voitures. Entretien and r\u00e9parat",
    "sg:phone":"+32 2 343 05 95",
    "sg:postcode":"1180",
    "sg:province":"Bruxelles-Capitale",
    "wof:name":"Garage Jacobs",
    "wof:placetype":"venue"
},
  "geometry": {"coordinates":[4.33791399,50.8136024475],"type":"Point"}
}