{
  "type": "Feature",
  "properties": {
    "iso:country":"BE",
    "sg:address":"Brugstraat 4",
    "sg:city":"Bierbeek",
    "sg:orig_category":"M\u00e9decins and sp\u00e9cialistes",
    "sg:phone":"+32 16 46 32 38",
    "sg:postcode":"3360",
    "sg:province":"Vlaams-Brabant",
    "wof:name":"Els Deloof",
    "wof:placetype":"venue"
},
  "geometry": {"coordinates":[4.795334816,50.8480453491],"type":"Point"}
}