{
  "type": "Feature",
  "properties": {
    "iso:country":"BE",
    "sg:address":"Place Charles Rogier 3",
    "sg:city":"Bruxelles (saint-josse-ten-noode)",
    "sg:classifiers":[
        {
            "category":"Bars & Pubs",
            "type":"Food & Drink"
        }
    ],
    "sg:phone":"+32 2 217 09 93",
    "sg:postcode":"1210",
    "sg:province":"Bruxelles-Capitale",
    "wof:name":"Take Five Pub",
    "wof:placetype":"venue"
},
  "geometry": {"coordinates":[4.3582291603,50.8560714722],"type":"Point"}
}