{
  "type": "Feature",
  "properties": {
    "iso:country":"BE",
    "sg:address":"Rue De L'eglise 28",
    "sg:city":"Bassenge (boirs)",
    "sg:classifiers":[
        {
            "category":"Retail",
            "subcategory":"Animal Services",
            "type":"Services"
        }
    ],
    "sg:phone":"+32 476 32 01 59",
    "sg:postcode":"4690",
    "sg:province":"Li\u00e8ge",
    "sg:tags":[
        "breeding",
        "selling",
        "-",
        "dog"
    ],
    "wof:name":"Dogy Dog",
    "wof:placetype":"venue"
},
  "geometry": {"coordinates":[5.5765209198,50.7509727478],"type":"Point"}
}