{
  "type": "Feature",
  "properties": {
    "addr:full":"Rue Emile Vandervelde 23 Beyne-heusay (queue-du-bois) Li\u00e8ge 4610",
    "addr:housenumber":"23",
    "addr:postcode":"4610",
    "addr:street":"Rue Emile Vandervelde",
    "iso:country":"BE",
    "sg:address":"Rue Emile Vandervelde 23",
    "sg:city":"Beyne-heusay (queue-du-bois)",
    "sg:classifiers":[
        {
            "category":"Professional",
            "subcategory":"Testing Lab",
            "type":"Services"
        }
    ],
    "sg:phone":"+32 4 362 43 83",
    "sg:postcode":"4610",
    "sg:province":"Li\u00e8ge",
    "sg:tags":[
        "chemist"
    ],
    "wof:name":"Fl\u00e9ron E",
    "wof:placetype":"venue"
},
  "geometry": {"coordinates":[5.6813440323,50.6363792419],"type":"Point"}
}