{
  "type": "Feature",
  "properties": {
    "iso:country":"BE",
    "sg:address":"Guldenzandstraat 3",
    "sg:city":"Koksijde",
    "sg:orig_category":"V\u00eatements. Equipement divers pour commerces V\u00eatements, chaussures and accessoires Gr",
    "sg:phone":"+32 58 51 78 22",
    "sg:postcode":"8670",
    "sg:province":"West-Vlaanderen",
    "wof:name":"De Roo G",
    "wof:placetype":"venue"
},
  "geometry": {"coordinates":[2.6687500477,51.115688324],"type":"Point"}
}