{
  "type": "Feature",
  "properties": {
    "addr:full":"Avenue Ren\u00e9 Stevens 111 Bruxelles (auderghem) Bruxelles-Capitale 1160",
    "addr:housenumber":"111",
    "addr:postcode":"1160",
    "addr:street":"Avenue Rene\u0301 Stevens",
    "iso:country":"BE",
    "sg:address":"Avenue Ren\u00e9 Stevens 111",
    "sg:city":"Bruxelles (auderghem)",
    "sg:classifiers":[
        {
            "category":"Health Services",
            "subcategory":"Dentist",
            "type":"Services"
        }
    ],
    "sg:phone":"+32 2 672 85 25",
    "sg:postcode":"1160",
    "sg:province":"Bruxelles-Capitale",
    "wof:name":"Mandoux Ph",
    "wof:placetype":"venue"
},
  "geometry": {"coordinates":[4.4324169159,50.8057250977],"type":"Point"}
}