{
  "type": "Feature",
  "properties": {
    "iso:country":"BE",
    "sg:address":"Processiestraat 6",
    "sg:city":"Kortrijk",
    "sg:orig_category":"Salles de spectacles",
    "sg:phone":"+32 56 25 95 71",
    "sg:postcode":"8510",
    "sg:province":"West-Vlaanderen",
    "wof:name":"Ontmoetingscentrum",
    "wof:placetype":"venue"
},
  "geometry": {"coordinates":[3.2810440063,50.7784156799],"type":"Point"}
}