{
  "type": "Feature",
  "properties": {
    "addr:full":"Rue De Fiennes 13 Bruxelles (anderlecht) Bruxelles-Capitale 1070",
    "addr:housenumber":"13",
    "addr:postcode":"1070",
    "addr:street":"Rue De Fiennes",
    "iso:country":"BE",
    "sg:address":"Rue De Fiennes 13",
    "sg:city":"Bruxelles (anderlecht)",
    "sg:classifiers":[
        {
            "category":"Cafe",
            "type":"Food & Drink"
        }
    ],
    "sg:phone":"+32 2 520 98 70",
    "sg:postcode":"1070",
    "sg:province":"Bruxelles-Capitale",
    "sg:tags":[
        "snack-bars"
    ],
    "wof:name":"Snack Deniz",
    "wof:placetype":"venue"
},
  "geometry": {"coordinates":[4.33477211,50.8391342163],"type":"Point"}
}