{
  "type": "Feature",
  "properties": {
    "iso:country":"BE",
    "sg:address":"Heidestraat 10",
    "sg:city":"Kapellen",
    "sg:classifiers":[
        {
            "category":"Personal",
            "subcategory":"Beauty Salon",
            "type":"Services"
        }
    ],
    "sg:phone":"+32 3 664 61 33",
    "sg:postcode":"2950",
    "sg:province":"Antwerpen",
    "wof:name":"Antigua",
    "wof:placetype":"venue"
},
  "geometry": {"coordinates":[4.4376502037,51.3207130432],"type":"Point"}
}