{
  "type": "Feature",
  "properties": {
    "addr:full":"Kerkelei 9 Kontich Antwerpen 2550",
    "addr:housenumber":"9",
    "addr:postcode":"2550",
    "addr:street":"Kerkelei",
    "iso:country":"BE",
    "sg:address":"Kerkelei 9",
    "sg:city":"Kontich",
    "sg:orig_category":"Banques and organismes de cr\u00e9dit",
    "sg:phone":"+32 15 31 70 28",
    "sg:postcode":"2550",
    "sg:province":"Antwerpen",
    "wof:name":"Groep Argenta",
    "wof:placetype":"venue"
},
  "geometry": {"coordinates":[4.453810215,51.1046447754],"type":"Point"}
}