{
  "type": "Feature",
  "properties": {
    "addr:full":"Vrouwleystraat 20 Kortenberg Vlaams-Brabant 3078",
    "addr:housenumber":"20",
    "addr:postcode":"3078",
    "addr:street":"Vrouwleystraat;Vlaams-Brabant",
    "iso:country":"BE",
    "sg:address":"Vrouwleystraat 20",
    "sg:city":"Kortenberg",
    "sg:orig_category":"D\u00e9corateurs d'int\u00e9rieur",
    "sg:phone":"+32 2 759 69 99",
    "sg:postcode":"3078",
    "sg:province":"Vlaams-Brabant",
    "wof:name":"Kristien Geurts",
    "wof:placetype":"venue"
},
  "geometry": {"coordinates":[4.583137989,50.879650116],"type":"Point"}
}