{
  "type": "Feature",
  "properties": {
    "addr:full":"Hannuitsesteenweg 59 Tienen Vlaams-Brabant 3300",
    "addr:housenumber":"59",
    "addr:postcode":"3300",
    "addr:street":"Hannuitsesteenweg",
    "iso:country":"BE",
    "sg:address":"Hannuitsesteenweg 59",
    "sg:city":"Tienen",
    "sg:orig_category":"Boissons",
    "sg:phone":"+32 16 81 90 72",
    "sg:postcode":"3300",
    "sg:province":"Vlaams-Brabant",
    "wof:name":"Rodolfo Maia Da Rocha",
    "wof:placetype":"venue"
},
  "geometry": {"coordinates":[4.930077076,50.8096694946],"type":"Point"}
}