{
  "type": "Feature",
  "properties": {
    "iso:country":"BE",
    "sg:address":"Rue Francois-lefebvre 220",
    "sg:city":"Li\u00c8ge",
    "sg:orig_category":"Tabac. Journaux",
    "sg:phone":"+32 4 263 16 28",
    "sg:postcode":"4000",
    "sg:province":"Li\u00e8ge",
    "wof:name":"Librairie Verdenne",
    "wof:placetype":"venue"
},
  "geometry": {"coordinates":[5.5507102013,50.6849937439],"type":"Point"}
}