{
  "type": "Feature",
  "properties": {
    "iso:country":"BE",
    "sg:address":"Houtemstraat 28a",
    "sg:city":"Zonnebeke (zandvoorde)",
    "sg:orig_category":"Non-Classified Establishments",
    "sg:phone":"+32 57 21 72 38",
    "sg:postcode":"8980",
    "sg:province":"West-Vlaanderen",
    "wof:name":"Voeders Vermes Nv",
    "wof:placetype":"venue"
},
  "geometry": {"coordinates":[2.9738650322,50.8099403381],"type":"Point"}
}