{
  "type": "Feature",
  "properties": {
    "iso:country":"BE",
    "sg:address":"Abdijlaan 18",
    "sg:city":"Oudenburg",
    "sg:classifiers":[
        {
            "category":"Personal",
            "subcategory":"Beauty Salon",
            "type":"Services"
        }
    ],
    "sg:phone":"+32 474 56 05 91",
    "sg:postcode":"8460",
    "sg:province":"West-Vlaanderen",
    "sg:tags":[
        "lady",
        "-",
        "hairdressing"
    ],
    "wof:name":"Hairline Yenka",
    "wof:placetype":"venue"
},
  "geometry": {"coordinates":[3.0105800629,51.1856307983],"type":"Point"}
}