{
  "type": "Feature",
  "properties": {
    "iso:country":"BE",
    "sg:address":"Rue Hocheporte 17",
    "sg:city":"Theux",
    "sg:orig_category":"Pain, p\u00e2tisseries and confiseries",
    "sg:phone":"+32 87 54 13 18",
    "sg:postcode":"4910",
    "sg:province":"Li\u00e8ge",
    "wof:name":"Didier Collard",
    "wof:placetype":"venue"
},
  "geometry": {"coordinates":[5.8132991791,50.5355300903],"type":"Point"}
}