{
  "type": "Feature",
  "properties": {
    "addr:full":"Landbouwstraat 48 Hamme Oost-Vlaanderen 9220",
    "addr:housenumber":"48",
    "addr:postcode":"9220",
    "addr:street":"Landbouwstraat",
    "iso:country":"BE",
    "sg:address":"Landbouwstraat 48",
    "sg:city":"Hamme",
    "sg:orig_category":"Sportclubs",
    "sg:phone":"+32 52 47 64 48",
    "sg:postcode":"9220",
    "sg:province":"Oost-Vlaanderen",
    "wof:name":"K.c. Temse Hoger Op",
    "wof:placetype":"venue"
},
  "geometry": {"coordinates":[4.1471581459,51.0925788879],"type":"Point"}
}