{
  "type": "Feature",
  "properties": {
    "iso:country":"BE",
    "sg:address":"Kerkstraat",
    "sg:city":"Lille",
    "sg:classifiers":[
        {
            "category":"Sports & Exercise",
            "subcategory":"Sports Center",
            "type":"Entertainment"
        }
    ],
    "sg:phone":"+32 14 88 30 40",
    "sg:postcode":"2275",
    "sg:province":"Antwerpen",
    "sg:tags":[
        "terrain",
        "hors",
        "de",
        "installation",
        "sportifs"
    ],
    "wof:name":"Gemeentelijk Zwembad De Dolfijn",
    "wof:placetype":"venue"
},
  "geometry": {"coordinates":[4.823764801,51.2383842468],"type":"Point"}
}