{
  "type": "Feature",
  "properties": {
    "iso:country":"BE",
    "sg:address":"Rue De Bruxelles 124",
    "sg:city":"Awans",
    "sg:classifiers":[
        {
            "category":"Travel",
            "subcategory":"Hotels & Motels",
            "type":"Entertainment"
        }
    ],
    "sg:phone":"+32 4 257 44 94",
    "sg:postcode":"4340",
    "sg:province":"Li\u00e8ge",
    "wof:name":"Gentry (la)",
    "wof:placetype":"venue"
},
  "geometry": {"coordinates":[5.4739398956,50.6776313782],"type":"Point"}
}