{
  "type": "Feature",
  "properties": {
    "iso:country":"BE",
    "sg:address":"Diestsebaan 5",
    "sg:city":"Diest",
    "sg:classifiers":[
        {
            "category":"Shopping",
            "subcategory":"Bicycles & Sporting Goods",
            "type":"Retail Goods"
        }
    ],
    "sg:phone":"+32 13 31 11 01",
    "sg:postcode":"3290",
    "sg:province":"Vlaams-Brabant",
    "sg:tags":[
        "article",
        "de",
        "sport",
        "camping"
    ],
    "wof:name":"Josse Brockmans",
    "wof:placetype":"venue"
},
  "geometry": {"coordinates":[5.0703630447,50.9960327148],"type":"Point"}
}