{
  "type": "Feature",
  "properties": {
    "addr:full":"T\u00c9l\u00c9machuslaan 32 Vorst/forest Bruxelles-Capitale 1190",
    "addr:housenumber":"32",
    "addr:postcode":"1190",
    "addr:street":"Te\u0301Le\u0301Machuslaan;/ Forest",
    "iso:country":"BE",
    "sg:address":"T\u00c9l\u00c9machuslaan 32",
    "sg:city":"Vorst/forest",
    "sg:orig_category":"Artsen and specialisten",
    "sg:phone":"+32 2 343 95 75",
    "sg:postcode":"1190",
    "sg:province":"Bruxelles-Capitale",
    "wof:name":"Willy Kostucki",
    "wof:placetype":"venue"
},
  "geometry": {"coordinates":[4.3316659927,50.8125495911],"type":"Point"}
}