{
  "type": "Feature",
  "properties": {
    "iso:country":"BE",
    "sg:address":"Hendrik Kuijpersstraat 33",
    "sg:city":"Mortsel",
    "sg:orig_category":"Sportclubs",
    "sg:phone":"+32 3 440 20 69",
    "sg:postcode":"2640",
    "sg:province":"Antwerpen",
    "wof:name":"Ski S B S",
    "wof:placetype":"venue"
},
  "geometry": {"coordinates":[4.4624400139,51.1656799316],"type":"Point"}
}