{
  "type": "Feature",
  "properties": {
    "addr:full":"Crapaurue 71 Verviers Li\u00e8ge 4800",
    "addr:housenumber":"71",
    "addr:postcode":"4800",
    "addr:street":"Crapaurue",
    "iso:country":"BE",
    "sg:address":"Crapaurue 71",
    "sg:city":"Verviers",
    "sg:classifiers":[
        {
            "category":"Home & Garden",
            "subcategory":"Household Appliances",
            "type":"Retail Goods"
        }
    ],
    "sg:phone":"+32 87 33 52 37",
    "sg:postcode":"4800",
    "sg:province":"Li\u00e8ge",
    "sg:tags":[
        "repair",
        "mainten",
        "-",
        "electric"
    ],
    "wof:name":"Cleban Edmond",
    "wof:placetype":"venue"
},
  "geometry": {"coordinates":[5.865254879,50.5926818848],"type":"Point"}
}