{
  "type": "Feature",
  "properties": {
    "addr:full":"Steenovenstraat 8 Antwerpen Antwerpen 2040",
    "addr:housenumber":"8",
    "addr:postcode":"2040",
    "addr:street":"Steenovenstraat",
    "iso:country":"BE",
    "sg:address":"Steenovenstraat 8",
    "sg:city":"Antwerpen",
    "sg:classifiers":[
        {
            "category":"Retail",
            "subcategory":"Auto Repair",
            "type":"Services"
        }
    ],
    "sg:phone":"+32 3 568 12 03",
    "sg:postcode":"2040",
    "sg:province":"Antwerpen",
    "sg:tags":[
        "garage"
    ],
    "wof:name":"Slegers-tuning",
    "wof:placetype":"venue"
},
  "geometry": {"coordinates":[4.3243727684,51.3519592285],"type":"Point"}
}