{
  "type": "Feature",
  "properties": {
    "iso:country":"BE",
    "sg:address":"Pulse Steenweg 28",
    "sg:city":"Grobbendonk",
    "sg:classifiers":[
        {
            "category":"Retail",
            "subcategory":"Auto Repair",
            "type":"Services"
        }
    ],
    "sg:phone":"+32 14 51 31 75",
    "sg:postcode":"2280",
    "sg:province":"Antwerpen",
    "sg:tags":[
        "automobile-body"
    ],
    "wof:name":"Verlinden A",
    "wof:placetype":"venue"
},
  "geometry": {"coordinates":[4.7178769112,51.197429657],"type":"Point"}
}