{
  "type": "Feature",
  "properties": {
    "iso:country":"BE",
    "sg:address":"Avenue Du Sainfoin 2",
    "sg:city":"Ciney",
    "sg:classifiers":[
        {
            "category":"Sports & Exercise",
            "subcategory":"Swimming Pool",
            "type":"Entertainment"
        }
    ],
    "sg:phone":"+32 83 21 28 12",
    "sg:postcode":"5590",
    "sg:province":"Namur",
    "sg:tags":[
        "organisaties",
        "verenigingen",
        "diverse",
        "diver",
        "amusement"
    ],
    "wof:name":"Relais St.roch",
    "wof:placetype":"venue"
},
  "geometry": {"coordinates":[5.1013059616,50.2897567749],"type":"Point"}
}