{
  "type": "Feature",
  "properties": {
    "addr:full":"Rue Emile Cornez 11 Honnelles Hainaut 7387",
    "addr:housenumber":"11",
    "addr:postcode":"7387",
    "addr:street":"Rue Emile Cornez;Hainaut",
    "iso:country":"BE",
    "sg:address":"Rue Emile Cornez 11",
    "sg:city":"Honnelles",
    "sg:classifiers":[
        {
            "category":"Cafe",
            "type":"Food & Drink"
        }
    ],
    "sg:phone":"+32 65 75 01 75",
    "sg:postcode":"7387",
    "sg:province":"Hainaut",
    "sg:tags":[
        "caf\u00e9s"
    ],
    "wof:name":"La Concorde",
    "wof:placetype":"venue"
},
  "geometry": {"coordinates":[3.6984329224,50.3704032898],"type":"Point"}
}