{
  "type": "Feature",
  "properties": {
    "iso:country":"BE",
    "sg:address":"Rue Marot 19",
    "sg:city":"Dinant (sorinnes)",
    "sg:classifiers":[
        {
            "category":"Professional",
            "subcategory":"Management & Consulting",
            "type":"Services"
        }
    ],
    "sg:phone":"+32 82 22 26 79",
    "sg:postcode":"5503",
    "sg:province":"Namur",
    "sg:tags":[
        "consultant"
    ],
    "wof:name":"China Ma-trading & Consultancy",
    "wof:placetype":"venue"
},
  "geometry": {"coordinates":[4.9810390472,50.257900238],"type":"Point"}
}