{
  "type": "Feature",
  "properties": {
    "iso:country":"BE",
    "sg:address":"Sint-lambertuslaan 11",
    "sg:city":"Bilzen",
    "sg:orig_category":"Supermarch\u00e9s",
    "sg:postcode":"3740",
    "sg:province":"Limburg",
    "wof:name":"Aldi",
    "wof:placetype":"venue"
},
  "geometry": {"coordinates":[5.5123391151,50.8729324341],"type":"Point"}
}