{
  "type": "Feature",
  "properties": {
    "addr:full":"Schaapsdreef 52 Kortrijk West-Vlaanderen 8500",
    "addr:housenumber":"52",
    "addr:postcode":"8500",
    "addr:street":"Schaapsdreef",
    "iso:country":"BE",
    "sg:address":"Schaapsdreef 52",
    "sg:city":"Kortrijk",
    "sg:classifiers":[
        {
            "category":"Insurance",
            "subcategory":"Insurance Agent",
            "type":"Services"
        }
    ],
    "sg:phone":"+32 56 21 05 15",
    "sg:postcode":"8500",
    "sg:province":"West-Vlaanderen",
    "sg:tags":[
        "broker"
    ],
    "wof:name":"Lamoral J",
    "wof:placetype":"venue"
},
  "geometry": {"coordinates":[3.292028904,50.8014602661],"type":"Point"}
}