{
  "type": "Feature",
  "properties": {
    "iso:country":"BE",
    "sg:address":"Bauwerwaan 62",
    "sg:city":"Zomergem",
    "sg:orig_category":"Traducteurs and interpr\u00e8tes",
    "sg:phone":"+32 9 372 07 81",
    "sg:postcode":"9930",
    "sg:province":"Oost-Vlaanderen",
    "wof:name":"Geens-crauwels G. Cbtip/bkvtf",
    "wof:placetype":"venue"
},
  "geometry": {"coordinates":[3.5275099277,51.1248893738],"type":"Point"}
}