{
  "type": "Feature",
  "properties": {
    "iso:country":"BE",
    "sg:address":"Boomgaardstraat 16",
    "sg:city":"Beveren (melsele)",
    "sg:classifiers":[
        {
            "category":"Professional",
            "subcategory":"Art Services",
            "type":"Services"
        }
    ],
    "sg:phone":"+32 3 775 52 88",
    "sg:postcode":"9120",
    "sg:province":"Oost-Vlaanderen",
    "sg:tags":[
        "photographer"
    ],
    "wof:name":"Van Raemdonck L",
    "wof:placetype":"venue"
},
  "geometry": {"coordinates":[4.2822289467,51.2156600952],"type":"Point"}
}