{
  "type": "Feature",
  "properties": {
    "addr:full":"Pierstraat 12ba Rumst Antwerpen 2840",
    "addr:housenumber":"12ba",
    "addr:postcode":"2840",
    "addr:street":"Pierstraat",
    "iso:country":"BE",
    "sg:address":"Pierstraat 12ba",
    "sg:city":"Rumst",
    "sg:classifiers":[
        {
            "category":"Fast Food",
            "type":"Food & Drink"
        }
    ],
    "sg:phone":"+32 3 888 81 34",
    "sg:postcode":"2840",
    "sg:province":"Antwerpen",
    "sg:tags":[
        "\u00c0",
        "emporter",
        "restaurants"
    ],
    "wof:name":"Frituur 't Containerke",
    "wof:placetype":"venue"
},
  "geometry": {"coordinates":[4.401447773,51.1163253784],"type":"Point"}
}