{
  "type": "Feature",
  "properties": {
    "addr:full":"Bredabaan 804 Brasschaat Antwerpen 2930",
    "addr:housenumber":"804",
    "addr:postcode":"2930",
    "addr:street":"Bredabaan",
    "iso:country":"BE",
    "sg:address":"Bredabaan 804",
    "sg:city":"Brasschaat",
    "sg:orig_category":"Belastingconsulenten Diverse juridische dienstverlening",
    "sg:phone":"+32 3 663 63 36",
    "sg:postcode":"2930",
    "sg:province":"Antwerpen",
    "wof:name":"S.b.b.",
    "wof:placetype":"venue"
},
  "geometry": {"coordinates":[4.5210700035,51.3253593445],"type":"Point"}
}