{
  "type": "Feature",
  "properties": {
    "addr:full":"Hellegatstr.6 Kmo-zone Misstr. Berlaar Antwerpen 2590",
    "addr:postcode":"2590",
    "addr:street":"Misstr.",
    "iso:country":"BE",
    "sg:address":"Hellegatstr.6 Kmo-zone Misstr.",
    "sg:city":"Berlaar",
    "sg:classifiers":[
        {
            "category":"Home & Garden",
            "subcategory":"Furniture",
            "type":"Retail Goods"
        }
    ],
    "sg:phone":"+32 3 482 10 56",
    "sg:postcode":"2590",
    "sg:province":"Antwerpen",
    "sg:tags":[
        "household",
        "wood"
    ],
    "wof:name":"Flora World Nv/sa",
    "wof:placetype":"venue"
},
  "geometry": {"coordinates":[4.6609649658,51.1182518005],"type":"Point"}
}