{
  "type": "Feature",
  "properties": {
    "addr:full":"Lambermontlaan 154 Schaarbeek/schaerbeek Bruxelles-Capitale 1030",
    "addr:housenumber":"154",
    "addr:postcode":"1030",
    "addr:street":"Lambermontlaan",
    "iso:country":"BE",
    "sg:address":"Lambermontlaan 154",
    "sg:city":"Schaarbeek/schaerbeek",
    "sg:orig_category":"Sportclubs",
    "sg:phone":"+32 2 242 11 63",
    "sg:postcode":"1030",
    "sg:province":"Bruxelles-Capitale",
    "wof:name":"C. Natation Nereus Gansh.",
    "wof:placetype":"venue"
},
  "geometry": {"coordinates":[4.3812332153,50.871799469],"type":"Point"}
}