{
  "type": "Feature",
  "properties": {
    "addr:full":"Brusselsestr 34 Dendermonde 9330",
    "addr:housenumber":"34",
    "addr:postcode":"9330",
    "addr:street":"Brusselsestr",
    "iso:country":"BE",
    "sg:address":"Brusselsestr 34",
    "sg:city":"Dendermonde",
    "sg:classifiers":[
        {
            "category":"Banks & Credit Unions",
            "subcategory":"Bank",
            "type":"Services"
        }
    ],
    "sg:phone":"+32 52 21 50 49",
    "sg:postcode":"9330",
    "wof:name":"Aslk-cger Bank",
    "wof:placetype":"venue"
},
  "geometry": {"coordinates":[4.0993618965,51.02784729],"type":"Point"}
}