{
  "type": "Feature",
  "properties": {
    "iso:country":"BE",
    "sg:address":"Chauss\u00c9e De Waterloo 616",
    "sg:city":"Elsene/ixelles",
    "sg:orig_category":"Eclairage et \u00e9quipements du foyer. Rev\u00eatements pour sols and murs. Peinture",
    "sg:phone":"+32 2 347 53 25",
    "sg:postcode":"1050",
    "sg:province":"Bruxelles-Capitale",
    "wof:name":"Actuel D\u00c9cor",
    "wof:placetype":"venue"
},
  "geometry": {"coordinates":[4.3648991585,50.8178825378],"type":"Point"}
}