{
  "type": "Feature",
  "properties": {
    "addr:full":"Vredelaan 35 Blankenberge West-Vlaanderen 8370",
    "addr:housenumber":"35",
    "addr:postcode":"8370",
    "addr:street":"Vredelaan",
    "iso:country":"BE",
    "sg:address":"Vredelaan 35",
    "sg:city":"Blankenberge",
    "sg:classifiers":[
        {
            "category":"Cafe",
            "type":"Food & Drink"
        }
    ],
    "sg:phone":"+32 50 41 07 55",
    "sg:postcode":"8370",
    "sg:province":"West-Vlaanderen",
    "sg:tags":[
        "caf\u00e9s"
    ],
    "wof:name":"Jean Bare",
    "wof:placetype":"venue"
},
  "geometry": {"coordinates":[3.1213290691,51.3099327087],"type":"Point"}
}