{
  "type": "Feature",
  "properties": {
    "addr:full":"Meidoornstraat 20 Lommel Limburg 3920",
    "addr:housenumber":"20",
    "addr:postcode":"3920",
    "addr:street":"Meidoornstraat",
    "iso:country":"BE",
    "sg:address":"Meidoornstraat 20",
    "sg:city":"Lommel",
    "sg:orig_category":"Charpentes and couvertures",
    "sg:phone":"+32 11 54 50 83",
    "sg:postcode":"3920",
    "sg:province":"Limburg",
    "wof:name":"Michel Nijssen",
    "wof:placetype":"venue"
},
  "geometry": {"coordinates":[5.3363881111,51.2327270508],"type":"Point"}
}