{
  "type": "Feature",
  "properties": {
    "iso:country":"BE",
    "sg:address":"Hundelgemsesteenweg 178",
    "sg:city":"Gent (ledeberg)",
    "sg:classifiers":[
        {
            "category":"Manufacturing",
            "subcategory":"Metals",
            "type":"Manufacturing & Wholesale Goods"
        }
    ],
    "sg:phone":"+32 9 231 38 35",
    "sg:postcode":"9050",
    "sg:province":"Oost-Vlaanderen",
    "sg:tags":[
        "nickel",
        "plating",
        "chromium"
    ],
    "wof:name":"Bellchroom",
    "wof:placetype":"venue"
},
  "geometry": {"coordinates":[3.7589480877,51.0448532104],"type":"Point"}
}