{
  "type": "Feature",
  "properties": {
    "addr:full":"Parklaan 159 Edegem Antwerpen 2650",
    "addr:housenumber":"159",
    "addr:postcode":"2650",
    "addr:street":"Parklaan",
    "iso:country":"BE",
    "sg:address":"Parklaan 159",
    "sg:city":"Edegem",
    "sg:classifiers":[
        {
            "category":"Community Center",
            "subcategory":"Youth",
            "type":"Public Place"
        }
    ],
    "sg:phone":"+32 3 440 64 40",
    "sg:postcode":"2650",
    "sg:province":"Antwerpen",
    "sg:tags":[
        "club"
    ],
    "wof:name":"Jeugdhuis Nootuitgang",
    "wof:placetype":"venue"
},
  "geometry": {"coordinates":[4.4276800156,51.1683197021],"type":"Point"}
}