{
  "type": "Feature",
  "properties": {
    "addr:full":"Rue De Tilleur 2 Luik (groot) Li\u00e8ge 4000",
    "addr:housenumber":"2",
    "addr:postcode":"4000",
    "addr:street":"Rue De Tilleur;Luik Groot Lie\u0300Ge",
    "iso:country":"BE",
    "sg:address":"Rue De Tilleur 2",
    "sg:city":"Luik (groot)",
    "sg:orig_category":"Kapsalons",
    "sg:phone":"+32 4 252 64 17",
    "sg:postcode":"4000",
    "sg:province":"Li\u00e8ge",
    "wof:name":"Coiffure Fa-sil",
    "wof:placetype":"venue"
},
  "geometry": {"coordinates":[5.5469908714,50.6323471069],"type":"Point"}
}