{
  "type": "Feature",
  "properties": {
    "addr:full":"Rue De Mahy-faux 98 Binche Hainaut 7133",
    "addr:housenumber":"98",
    "addr:postcode":"7133",
    "addr:street":"Rue De Mahy-Faux",
    "iso:country":"BE",
    "sg:address":"Rue De Mahy-faux 98",
    "sg:city":"Binche",
    "sg:classifiers":[
        {
            "category":"Arena",
            "subcategory":"Sports Club",
            "type":"Entertainment"
        }
    ],
    "sg:phone":"+32 64 33 82 48",
    "sg:postcode":"7133",
    "sg:province":"Hainaut",
    "sg:tags":[
        "de"
    ],
    "wof:name":"Marcheurs Police Binche",
    "wof:placetype":"venue"
},
  "geometry": {"coordinates":[4.1796030998,50.4021453857],"type":"Point"}
}