{
  "type": "Feature",
  "properties": {
    "iso:country":"BE",
    "sg:address":"Leernsesteenweg 136",
    "sg:city":"Deinze (bachte-maria-leerne)",
    "sg:classifiers":[
        {
            "category":"Building & Trades",
            "subcategory":"Electrical",
            "type":"Services"
        }
    ],
    "sg:phone":"+32 9 282 36 01",
    "sg:postcode":"9800",
    "sg:province":"Oost-Vlaanderen",
    "sg:tags":[
        "electric",
        "-",
        "housewiring",
        "contractor"
    ],
    "wof:name":"De Weirt Marc",
    "wof:placetype":"venue"
},
  "geometry": {"coordinates":[3.5759420395,51.0084342957],"type":"Point"}
}