{
  "type": "Feature",
  "properties": {
    "addr:full":"Rue En Rh\u00e9e 49 Dinant Namur 5500",
    "addr:housenumber":"49",
    "addr:postcode":"5500",
    "addr:street":"Rue En Rhe\u0301E",
    "iso:country":"BE",
    "sg:address":"Rue En Rh\u00e9e 49",
    "sg:city":"Dinant",
    "sg:classifiers":[
        {
            "category":"Professional",
            "subcategory":"Lawyer & Legal Services",
            "type":"Services"
        }
    ],
    "sg:phone":"+32 82 22 20 11",
    "sg:postcode":"5500",
    "sg:province":"Namur",
    "wof:name":"Vermer M-c",
    "wof:placetype":"venue"
},
  "geometry": {"coordinates":[4.9137358665,50.260181427],"type":"Point"}
}