{
  "type": "Feature",
  "properties": {
    "iso:country":"BE",
    "sg:address":"Dorp 32",
    "sg:city":"Asse",
    "sg:orig_category":"Pain, p\u00e2tisseries and confiseries",
    "sg:phone":"+32 2 452 67 22",
    "sg:postcode":"1730",
    "sg:province":"Vlaams-Brabant",
    "wof:name":"Magdalena Wijns",
    "wof:placetype":"venue"
},
  "geometry": {"coordinates":[4.1549081802,50.9234542847],"type":"Point"}
}