{
  "type": "Feature",
  "properties": {
    "addr:full":"Rue Saint-roch 20 Wavre Brabant Wallon 1300",
    "addr:housenumber":"20;1300",
    "addr:street":"Rue Saint-Roch",
    "iso:country":"BE",
    "sg:address":"Rue Saint-roch 20",
    "sg:city":"Wavre",
    "sg:classifiers":[
        {
            "category":"Home & Garden",
            "subcategory":"Household Appliances",
            "type":"Retail Goods"
        }
    ],
    "sg:phone":"+32 10 22 21 69",
    "sg:postcode":"1300",
    "sg:province":"Brabant Wallon",
    "sg:tags":[
        "repair",
        "mainten",
        "-",
        "electric"
    ],
    "wof:name":"Nouvel Adem Sa",
    "wof:placetype":"venue"
},
  "geometry": {"coordinates":[4.6139130592,50.7193756104],"type":"Point"}
}