{
  "type": "Feature",
  "properties": {
    "addr:full":"Avenue Ernest Solvay 76 La Hulpe Brabant Wallon 1310",
    "addr:housenumber":"76",
    "addr:postcode":"1310",
    "addr:street":"Avenue Ernest Solvay",
    "iso:country":"BE",
    "sg:address":"Avenue Ernest Solvay 76",
    "sg:city":"La Hulpe",
    "sg:orig_category":"Agences immobili\u00e8res",
    "sg:phone":"+32 2 653 00 02",
    "sg:postcode":"1310",
    "sg:province":"Brabant Wallon",
    "wof:name":"Cobra",
    "wof:placetype":"venue"
},
  "geometry": {"coordinates":[4.4845061302,50.7398605347],"type":"Point"}
}