{
  "type": "Feature",
  "properties": {
    "iso:country":"BE",
    "sg:address":"Eigenlostraat 21",
    "sg:city":"Sint-niklaas",
    "sg:classifiers":[
        {
            "category":"Professional",
            "subcategory":"Printing & Photocopies",
            "type":"Services"
        }
    ],
    "sg:phone":"+32 3 766 11 32",
    "sg:postcode":"9100",
    "sg:province":"Oost-Vlaanderen",
    "sg:tags":[
        "engraving"
    ],
    "wof:name":"Invent-plexi-view",
    "wof:placetype":"venue"
},
  "geometry": {"coordinates":[4.1829271317,51.1480484009],"type":"Point"}
}