{
  "type": "Feature",
  "properties": {
    "addr:full":"Rue De Stassart 20 Bruxelles (ixelles) Bruxelles-Capitale 1050",
    "addr:housenumber":"20",
    "addr:postcode":"1050",
    "addr:street":"Rue De Stassart",
    "iso:country":"BE",
    "sg:address":"Rue De Stassart 20",
    "sg:city":"Bruxelles (ixelles)",
    "sg:classifiers":[
        {
            "category":"Social Services",
            "type":"Services"
        }
    ],
    "sg:phone":"+32 2 511 02 63",
    "sg:postcode":"1050",
    "sg:province":"Bruxelles-Capitale",
    "wof:name":"A.f.a.c.",
    "wof:placetype":"venue"
},
  "geometry": {"coordinates":[4.3612890244,50.8372497559],"type":"Point"}
}