{
  "type": "Feature",
  "properties": {
    "iso:country":"BE",
    "sg:address":"Doorniksestraat 37",
    "sg:city":"Kortrijk",
    "sg:classifiers":[
        {
            "category":"Shopping",
            "subcategory":"Clothing, Apparel, & Fashions",
            "type":"Retail Goods"
        }
    ],
    "sg:phone":"+32 56 20 41 25",
    "sg:postcode":"8500",
    "sg:province":"West-Vlaanderen",
    "sg:tags":[
        "boutique"
    ],
    "wof:name":"Barbarella",
    "wof:placetype":"venue"
},
  "geometry": {"coordinates":[3.2673270702,50.825958252],"type":"Point"}
}