{
  "type": "Feature",
  "properties": {
    "addr:full":"Rue De La Couture 43 Beauraing Namur 5570",
    "addr:housenumber":"43",
    "addr:postcode":"5570",
    "addr:street":"Rue De La Couture",
    "iso:country":"BE",
    "sg:address":"Rue De La Couture 43",
    "sg:city":"Beauraing",
    "sg:classifiers":[
        {
            "category":"Sports & Exercise",
            "subcategory":"Sports Center",
            "type":"Entertainment"
        }
    ],
    "sg:phone":"+32 82 71 26 57",
    "sg:postcode":"5570",
    "sg:province":"Namur",
    "sg:tags":[
        "terrain",
        "hors",
        "de",
        "installation",
        "sportifs"
    ],
    "wof:name":"Piscine De L'ath\u00c9n\u00c9e Royal",
    "wof:placetype":"venue"
},
  "geometry": {"coordinates":[4.9485211372,50.110004425],"type":"Point"}
}