{
  "type": "Feature",
  "properties": {
    "iso:country":"BE",
    "sg:address":"Rue De La Station 55-59",
    "sg:city":"Soignies",
    "sg:classifiers":[
        {
            "category":"Education",
            "subcategory":"School",
            "type":"Public Place"
        }
    ],
    "sg:phone":"+32 67 34 79 70",
    "sg:postcode":"7060",
    "sg:province":"Hainaut",
    "sg:tags":[
        "secondary"
    ],
    "wof:name":"Lyc\u00e9e Technique Et Commercial De La Province De Hainaut",
    "wof:placetype":"venue"
},
  "geometry": {"coordinates":[4.0696229935,50.5757255554],"type":"Point"}
}