{
  "type": "Feature",
  "properties": {
    "addr:full":"Rue Lulay 41 Bassenge Li\u00e8ge 4690",
    "addr:housenumber":"41",
    "addr:postcode":"4690",
    "addr:street":"Rue Lulay",
    "iso:country":"BE",
    "sg:address":"Rue Lulay 41",
    "sg:city":"Bassenge",
    "sg:orig_category":"Plomberie, chauffage and installations sanitaires",
    "sg:phone":"+32 4 286 45 40",
    "sg:postcode":"4690",
    "sg:province":"Li\u00e8ge",
    "wof:name":"Egide Hermans",
    "wof:placetype":"venue"
},
  "geometry": {"coordinates":[5.5475478172,50.7494125366],"type":"Point"}
}