{
  "type": "Feature",
  "properties": {
    "addr:full":"Volmolenlaan 34 Box 101 Leuven Vlaams-Brabant 3000",
    "addr:housenumber":"34",
    "addr:postcode":"3000",
    "addr:street":"Volmolenlaan;Box 101",
    "iso:country":"BE",
    "sg:address":"Volmolenlaan 34 Box 101",
    "sg:city":"Leuven",
    "sg:classifiers":[
        {
            "category":"Health Services",
            "subcategory":"Health Practitioner",
            "type":"Services"
        }
    ],
    "sg:phone":"+32 477 20 13 67",
    "sg:postcode":"3000",
    "sg:province":"Vlaams-Brabant",
    "sg:tags":[
        "alternative",
        "therapy",
        "treatment"
    ],
    "wof:name":"Lenvain P",
    "wof:placetype":"venue"
},
  "geometry": {"coordinates":[4.693901062,50.8709602356],"type":"Point"}
}