{
  "type": "Feature",
  "properties": {
    "addr:full":"Rue Du Bois Imp\u00c9rial 83 Lasne Brabant Wallon 1380",
    "addr:housenumber":"83",
    "addr:postcode":"1380",
    "addr:street":"Rue Du Bois Impe\u0301Rial",
    "iso:country":"BE",
    "sg:address":"Rue Du Bois Imp\u00c9rial 83",
    "sg:city":"Lasne",
    "sg:orig_category":"Onderdelen and accessoires voertuigen Gh",
    "sg:phone":"+32 2 633 32 56",
    "sg:postcode":"1380",
    "sg:province":"Brabant Wallon",
    "wof:name":"Philippe Bernard",
    "wof:placetype":"venue"
},
  "geometry": {"coordinates":[4.4453420639,50.658782959],"type":"Point"}
}