{
  "type": "Feature",
  "properties": {
    "addr:full":"Rue Vanderlinden 50 Bruxelles (schaerbeek) Bruxelles-Capitale 1030",
    "addr:housenumber":"50",
    "addr:postcode":"1030",
    "addr:street":"Rue Vanderlinden",
    "iso:country":"BE",
    "sg:address":"Rue Vanderlinden 50",
    "sg:city":"Bruxelles (schaerbeek)",
    "sg:classifiers":[
        {
            "category":"Building & Trades",
            "subcategory":"Construction",
            "type":"Services"
        }
    ],
    "sg:phone":"+32 477 85 04 86",
    "sg:postcode":"1030",
    "sg:province":"Bruxelles-Capitale",
    "sg:tags":[
        "stucco",
        "contractor"
    ],
    "wof:name":"B\u00e2timent And Business Concept",
    "wof:placetype":"venue"
},
  "geometry": {"coordinates":[4.3673291206,50.8674049377],"type":"Point"}
}