{
  "type": "Feature",
  "properties": {
    "addr:full":"Am Wolfshof 12 Eupen Li\u00e8ge 4701",
    "addr:housenumber":"12",
    "addr:postcode":"4701",
    "addr:street":"Am Wolfshof",
    "iso:country":"BE",
    "sg:address":"Am Wolfshof 12",
    "sg:city":"Eupen",
    "sg:orig_category":"Installation de menuiserie en bois and plastique",
    "sg:phone":"+32 87 55 67 35",
    "sg:postcode":"4701",
    "sg:province":"Li\u00e8ge",
    "wof:name":"Paul Siemons",
    "wof:placetype":"venue"
},
  "geometry": {"coordinates":[6.0461649895,50.6460838318],"type":"Point"}
}