{
  "type": "Feature",
  "properties": {
    "addr:full":"Rue De La Corderie 22 Charleroi (montignies-sur-sambre) Hainaut 6061",
    "addr:housenumber":"22",
    "addr:postcode":"6061",
    "addr:street":"Rue De La Corderie",
    "iso:country":"BE",
    "sg:address":"Rue De La Corderie 22",
    "sg:city":"Charleroi (montignies-sur-sambre)",
    "sg:classifiers":[
        {
            "category":"Utilities",
            "subcategory":"Natural Gas",
            "type":"Services"
        }
    ],
    "sg:phone":"+32 71 20 73 20",
    "sg:postcode":"6061",
    "sg:province":"Hainaut",
    "sg:tags":[
        "industrial",
        "-"
    ],
    "wof:name":"Air Liquide Brabant Wallon",
    "wof:placetype":"venue"
},
  "geometry": {"coordinates":[4.4614009857,50.4031944275],"type":"Point"}
}