{
  "type": "Feature",
  "properties": {
    "addr:full":"Akkerstraat 84 Beernem West-Vlaanderen 8730",
    "addr:housenumber":"84",
    "addr:postcode":"8730",
    "addr:street":"Akkerstraat",
    "iso:country":"BE",
    "sg:address":"Akkerstraat 84",
    "sg:city":"Beernem",
    "sg:orig_category":"Postzegels, munten and trofee\u00ebn",
    "sg:phone":"+32 50 78 05 16",
    "sg:postcode":"8730",
    "sg:province":"West-Vlaanderen",
    "wof:name":"Fiorio Sport",
    "wof:placetype":"venue"
},
  "geometry": {"coordinates":[3.3268198967,51.154548645],"type":"Point"}
}