{
  "type": "Feature",
  "properties": {
    "addr:full":"Parc Industriel 11 Espierres-helchin (espierres) West-Vlaanderen 8587",
    "addr:housenumber":"11",
    "addr:postcode":"8587",
    "addr:street":"Parc Industriel;Espierres",
    "iso:country":"BE",
    "sg:address":"Parc Industriel 11",
    "sg:city":"Espierres-helchin (espierres)",
    "sg:classifiers":[
        {
            "category":"Building & Trades",
            "subcategory":"Construction",
            "type":"Services"
        }
    ],
    "sg:phone":"+32 56 45 77 25",
    "sg:postcode":"8587",
    "sg:province":"West-Vlaanderen",
    "sg:tags":[
        "fork",
        "lift",
        "truck"
    ],
    "wof:name":"Lauwers Heftruck Service Bvba",
    "wof:placetype":"venue"
},
  "geometry": {"coordinates":[3.3266971111,50.7228469849],"type":"Point"}
}