{
  "type": "Feature",
  "properties": {
    "iso:country":"BE",
    "sg:address":"Groenendijkstraat 143",
    "sg:city":"Bredene",
    "sg:orig_category":"Belastingconsulenten Boekhouders Diverse juridische dienstverlening Verzekeringsmakelaars and expert",
    "sg:phone":"+32 59 32 46 90",
    "sg:postcode":"8450",
    "sg:province":"West-Vlaanderen",
    "wof:name":"Willy Vandenbroucke",
    "wof:placetype":"venue"
},
  "geometry": {"coordinates":[2.9475290775,51.2381820679],"type":"Point"}
}