{
  "type": "Feature",
  "properties": {
    "addr:full":"Rue Notre-dame 45 Namur Namur 5000",
    "addr:housenumber":"45",
    "addr:postcode":"5000",
    "addr:street":"Rue Notre-Dame",
    "iso:country":"BE",
    "sg:address":"Rue Notre-dame 45",
    "sg:city":"Namur",
    "sg:classifiers":[
        {
            "category":"Banks & Credit Unions",
            "subcategory":"Financial Services",
            "type":"Services"
        }
    ],
    "sg:phone":"+32 81 22 61 84",
    "sg:postcode":"5000",
    "sg:province":"Namur",
    "sg:tags":[
        "loan",
        "mortgage"
    ],
    "wof:name":"Dachet",
    "wof:placetype":"venue"
},
  "geometry": {"coordinates":[4.866850853,50.4601364136],"type":"Point"}
}