{
  "type": "Feature",
  "properties": {
    "iso:country":"BE",
    "sg:address":"Rue De Hotton 33",
    "sg:city":"Rendeux",
    "sg:classifiers":[
        {
            "category":"Shopping",
            "subcategory":"Clothing, Apparel, & Fashions",
            "type":"Retail Goods"
        }
    ],
    "sg:phone":"+32 84 47 71 73",
    "sg:postcode":"6987",
    "sg:province":"Luxembourg",
    "sg:tags":[
        "-",
        "clothing",
        "child"
    ],
    "wof:name":"Goosse Confection",
    "wof:placetype":"venue"
},
  "geometry": {"coordinates":[5.5046601295,50.2384185791],"type":"Point"}
}