{
  "type": "Feature",
  "properties": {
    "iso:country":"BE",
    "sg:address":"Otegemstraat162",
    "sg:city":"Zwevegem",
    "sg:orig_category":"Drukkerijen and copyshops",
    "sg:phone":"+32 56 75 94 82",
    "sg:postcode":"8550",
    "sg:province":"West-Vlaanderen",
    "wof:name":"Copy-service Marcel",
    "wof:placetype":"venue"
},
  "geometry": {"coordinates":[3.3329548836,50.8128356934],"type":"Point"}
}