{
  "type": "Feature",
  "properties": {
    "addr:full":"Avenue Armand Forton 28 Kraainem/kraainem Vlaams-Brabant 1950",
    "addr:housenumber":"28",
    "addr:postcode":"1950",
    "addr:street":"Avenue Armand Forton",
    "iso:country":"BE",
    "sg:address":"Avenue Armand Forton 28",
    "sg:city":"Kraainem/kraainem",
    "sg:orig_category":"M\u00e9decins and sp\u00e9cialistes",
    "sg:phone":"+32 2 725 64 08",
    "sg:postcode":"1950",
    "sg:province":"Vlaams-Brabant",
    "wof:name":"Thierry Sluysmans",
    "wof:placetype":"venue"
},
  "geometry": {"coordinates":[4.4604878426,50.8604202271],"type":"Point"}
}