{
  "type": "Feature",
  "properties": {
    "iso:country":"BE",
    "sg:address":"Diestse Baan 23",
    "sg:city":"Laakdal",
    "sg:orig_category":"Slagers",
    "sg:phone":"+32 14 84 16 76",
    "sg:postcode":"2431",
    "sg:province":"Antwerpen",
    "wof:name":"Kippenshop",
    "wof:placetype":"venue"
},
  "geometry": {"coordinates":[4.9888310432,51.0680084229],"type":"Point"}
}