{
  "type": "Feature",
  "properties": {
    "iso:country":"BE",
    "sg:address":"Kasteelbrakelsesteenweg 437",
    "sg:city":"Halle (lembeek)",
    "sg:classifiers":[
        {
            "category":"Government",
            "subcategory":"Department Of Motor Vehicles",
            "type":"Public Place"
        }
    ],
    "sg:phone":"+32 2 361 00 92",
    "sg:postcode":"1502",
    "sg:province":"Vlaams-Brabant",
    "sg:tags":[
        "planing",
        "wood",
        "sawing"
    ],
    "wof:name":"Herinckx J",
    "wof:placetype":"venue"
},
  "geometry": {"coordinates":[4.2500538826,50.7034759521],"type":"Point"}
}