{
  "type": "Feature",
  "properties": {
    "addr:full":"Geraardsbergsesteenweg 8 Aalst (erembodegem) Oost-Vlaanderen 9320",
    "addr:housenumber":"8",
    "addr:postcode":"9320",
    "addr:street":"Geraardsbergsesteenweg",
    "iso:country":"BE",
    "sg:address":"Geraardsbergsesteenweg 8",
    "sg:city":"Aalst (erembodegem)",
    "sg:classifiers":[
        {
            "category":"Health Services",
            "subcategory":"Doctor",
            "type":"Services"
        }
    ],
    "sg:phone":"+32 53 83 12 42",
    "sg:postcode":"9320",
    "sg:province":"Oost-Vlaanderen",
    "sg:tags":[
        "orthopedist"
    ],
    "wof:name":"Staelens R",
    "wof:placetype":"venue"
},
  "geometry": {"coordinates":[4.0553851128,50.9209976196],"type":"Point"}
}