{
  "type": "Feature",
  "properties": {
    "addr:full":"Rozenstraat 28 Hasselt Limburg 3500",
    "addr:housenumber":"28",
    "addr:postcode":"3500",
    "addr:street":"Rozenstraat",
    "iso:country":"BE",
    "sg:address":"Rozenstraat 28",
    "sg:city":"Hasselt",
    "sg:classifiers":[
        {
            "category":"Insurance",
            "subcategory":"Insurance Agent",
            "type":"Services"
        }
    ],
    "sg:phone":"+32 11 87 04 11",
    "sg:postcode":"3500",
    "sg:province":"Limburg",
    "sg:tags":[
        "verzekeringsmakelaars",
        "expert"
    ],
    "wof:name":"L.d.b.",
    "wof:placetype":"venue"
},
  "geometry": {"coordinates":[5.3297581673,50.9340934753],"type":"Point"}
}