{
  "type": "Feature",
  "properties": {
    "iso:country":"BE",
    "sg:address":"Rue Racasse 3",
    "sg:city":"Aywaille (sougn\u00e9-remouchamps)",
    "sg:classifiers":[
        {
            "category":"Health Services",
            "subcategory":"Nursing And Care Facility",
            "type":"Services"
        }
    ],
    "sg:phone":"+32 496 13 39 30",
    "sg:postcode":"4920",
    "sg:province":"Li\u00e8ge",
    "sg:tags":[
        "home"
    ],
    "wof:name":"Capitaine B",
    "wof:placetype":"venue"
},
  "geometry": {"coordinates":[5.6782069206,50.4738540649],"type":"Point"}
}