{
  "type": "Feature",
  "properties": {
    "iso:country":"BE",
    "sg:address":"Lauwbergstraat 141a",
    "sg:city":"Menen (lauwe)",
    "sg:classifiers":[
        {
            "category":"Home & Garden",
            "subcategory":"Building Materials",
            "type":"Retail Goods"
        }
    ],
    "sg:phone":"+31 114 650 704",
    "sg:postcode":"8930",
    "sg:province":"West-Vlaanderen",
    "sg:tags":[
        "granite",
        "stone",
        "natural",
        "marble"
    ],
    "wof:name":"Han Deij Vof",
    "wof:placetype":"venue"
},
  "geometry": {"coordinates":[-107.8339996338,40.0480003357],"type":"Point"}
}