{
  "type": "Feature",
  "properties": {
    "iso:country":"BE",
    "sg:address":"Nieuwstraat 42",
    "sg:city":"Heuvelland (kemmel)",
    "sg:classifiers":[
        {
            "category":"Airport",
            "subcategory":"International",
            "type":"Transportation"
        }
    ],
    "sg:phone":"+32 57 45 24 24",
    "sg:postcode":"8956",
    "sg:province":"West-Vlaanderen",
    "sg:tags":[
        "-",
        "transport"
    ],
    "wof:name":"Vdm Trans Bvba",
    "wof:placetype":"venue"
},
  "geometry": {"coordinates":[2.8289039135,50.7871322632],"type":"Point"}
}