{
  "type": "Feature",
  "properties": {
    "addr:full":"Vijf Gezusterslaan 22 Brecht Antwerpen 2960",
    "addr:housenumber":"22",
    "addr:postcode":"2960",
    "addr:street":"Gezusterslaan",
    "iso:country":"BE",
    "sg:address":"Vijf Gezusterslaan 22",
    "sg:city":"Brecht",
    "sg:classifiers":[
        {
            "category":"Professional",
            "subcategory":"Computer Services",
            "type":"Services"
        }
    ],
    "sg:phone":"+32 3 636 27 91",
    "sg:postcode":"2960",
    "sg:province":"Antwerpen",
    "sg:tags":[
        "-",
        "processing",
        "data",
        "software"
    ],
    "wof:name":"De Vlaamse Fusievennootschap Nv",
    "wof:placetype":"venue"
},
  "geometry": {"coordinates":[4.5743498802,51.3052101135],"type":"Point"}
}