{
  "type": "Feature",
  "properties": {
    "iso:country":"BE",
    "sg:address":"Industriestraat 1",
    "sg:city":"Ruiselede",
    "sg:orig_category":"Herstellingen and onderhoud van auto's",
    "sg:phone":"+32 51 68 97 22",
    "sg:postcode":"8755",
    "sg:province":"West-Vlaanderen",
    "wof:name":"Garage Deleersnyder",
    "wof:placetype":"venue"
},
  "geometry": {"coordinates":[3.4112999439,51.0508003235],"type":"Point"}
}