{
  "type": "Feature",
  "properties": {
    "addr:full":"Rue Mahy Faux 181 Binche (buvrinnes) Hainaut 7133",
    "addr:housenumber":"181",
    "addr:postcode":"7133",
    "addr:street":"Rue Mahy Faux",
    "iso:country":"BE",
    "sg:address":"Rue Mahy Faux 181",
    "sg:city":"Binche (buvrinnes)",
    "sg:classifiers":[
        {
            "category":"Health Services",
            "subcategory":"Nursing And Care Facility",
            "type":"Services"
        }
    ],
    "sg:phone":"+32 64 34 03 45",
    "sg:postcode":"7133",
    "sg:province":"Hainaut",
    "sg:tags":[
        "home"
    ],
    "wof:name":"Falcomer N",
    "wof:placetype":"venue"
},
  "geometry": {"coordinates":[4.1973409653,50.3925018311],"type":"Point"}
}