{
  "type": "Feature",
  "properties": {
    "iso:country":"BE",
    "sg:address":"Gerechtsplein 4",
    "sg:city":"Oostende",
    "sg:orig_category":"Artsen and specialisten",
    "sg:phone":"+32 59 70 23 40",
    "sg:postcode":"8400",
    "sg:province":"West-Vlaanderen",
    "wof:name":"Marc Du Four",
    "wof:placetype":"venue"
},
  "geometry": {"coordinates":[2.902741909,51.21824646],"type":"Point"}
}