{
  "type": "Feature",
  "properties": {
    "iso:country":"BE",
    "sg:address":"Ninoofse Steenweg 744",
    "sg:city":"Anderlecht/anderlecht",
    "sg:orig_category":"Benzinestations and brandstoffen",
    "sg:phone":"+32 2 521 35 14",
    "sg:postcode":"1070",
    "sg:province":"Bruxelles-Capitale",
    "wof:name":"Jet",
    "wof:placetype":"venue"
},
  "geometry": {"coordinates":[4.2951211929,50.8463973999],"type":"Point"}
}