{
  "type": "Feature",
  "properties": {
    "iso:country":"BE",
    "sg:address":"Korte Nieuwstraat 33",
    "sg:city":"Antwerpen",
    "sg:orig_category":"Hoger onderwijs",
    "sg:phone":"+32 3 232 74 52",
    "sg:postcode":"2000",
    "sg:province":"Antwerpen",
    "wof:name":"Handelshogesch. Antwerpen",
    "wof:placetype":"venue"
},
  "geometry": {"coordinates":[4.4049859047,51.2202377319],"type":"Point"}
}