{
  "type": "Feature",
  "properties": {
    "addr:full":"Tervuursesteenweg 662 Zemst Vlaams-Brabant 1982",
    "addr:housenumber":"662",
    "addr:postcode":"1982",
    "addr:street":"Tervuursesteenweg;Vlaams-Brabant",
    "iso:country":"BE",
    "sg:address":"Tervuursesteenweg 662",
    "sg:city":"Zemst",
    "sg:classifiers":[
        {
            "category":"Cafe",
            "type":"Food & Drink"
        }
    ],
    "sg:phone":"+32 15 61 04 62",
    "sg:postcode":"1982",
    "sg:province":"Vlaams-Brabant",
    "sg:tags":[
        "caf\u00e9s"
    ],
    "wof:name":"Caf\u00c9 Don Quichotte",
    "wof:placetype":"venue"
},
  "geometry": {"coordinates":[4.4960641861,50.967048645],"type":"Point"}
}