{
  "type": "Feature",
  "properties": {
    "addr:full":"Rue Quevry 66 Pont-\u00c0-celles Hainaut 6238",
    "addr:housenumber":"66",
    "addr:postcode":"6238",
    "addr:street":"Rue Quevry",
    "iso:country":"BE",
    "sg:address":"Rue Quevry 66",
    "sg:city":"Pont-\u00c0-celles",
    "sg:orig_category":"Boekhouders",
    "sg:phone":"+32 71 84 21 30",
    "sg:postcode":"6238",
    "sg:province":"Hainaut",
    "wof:name":"Nathalie Carriere",
    "wof:placetype":"venue"
},
  "geometry": {"coordinates":[4.3969140053,50.5111083984],"type":"Point"}
}