{
  "type": "Feature",
  "properties": {
    "addr:full":"Viaduct-dam 2 Antwerpen Antwerpen 2060",
    "addr:housenumber":"2",
    "addr:postcode":"2060",
    "addr:street":"Viaduct-Dam",
    "iso:country":"BE",
    "sg:address":"Viaduct-dam 2",
    "sg:city":"Antwerpen",
    "sg:orig_category":"Epiceries",
    "sg:phone":"+32 3 227 14 24",
    "sg:postcode":"2060",
    "sg:province":"Antwerpen",
    "wof:name":"In 't Weegschaaltje",
    "wof:placetype":"venue"
},
  "geometry": {"coordinates":[4.4211740494,51.2297058105],"type":"Point"}
}