{
  "type": "Feature",
  "properties": {
    "addr:full":"Rue De Scoumont 27a Pont-\u00e0-celles (obaix) Hainaut 6230",
    "addr:housenumber":"27a",
    "addr:postcode":"6230",
    "addr:street":"Rue De Scoumont",
    "iso:country":"BE",
    "sg:address":"Rue De Scoumont 27a",
    "sg:city":"Pont-\u00e0-celles (obaix)",
    "sg:classifiers":[
        {
            "category":"Health Services",
            "subcategory":"Health Practitioner",
            "type":"Services"
        }
    ],
    "sg:phone":"+32 67 87 83 82",
    "sg:postcode":"6230",
    "sg:province":"Hainaut",
    "sg:tags":[
        "physiotherapist"
    ],
    "wof:name":"Gobert A-m",
    "wof:placetype":"venue"
},
  "geometry": {"coordinates":[4.3210248947,50.5404090881],"type":"Point"}
}