{
  "type": "Feature",
  "properties": {
    "iso:country":"BE",
    "sg:address":"Vliegveldlaan 130",
    "sg:city":"Sint-truiden",
    "sg:classifiers":[
        {
            "category":"Insurance",
            "subcategory":"Insurance Agent",
            "type":"Services"
        }
    ],
    "sg:phone":"+32 11 68 32 57",
    "sg:postcode":"3800",
    "sg:province":"Limburg",
    "sg:tags":[
        "verzekeringsmakelaars",
        "expert"
    ],
    "wof:name":"Poulus",
    "wof:placetype":"venue"
},
  "geometry": {"coordinates":[5.2249779701,50.8080978394],"type":"Point"}
}