{
  "type": "Feature",
  "properties": {
    "addr:full":"Rue Caporal Claes 38 Bruxelles (schaerbeek) Bruxelles-Capitale 1030",
    "addr:housenumber":"38",
    "addr:postcode":"1030",
    "addr:street":"Rue Caporal Claes",
    "iso:country":"BE",
    "sg:address":"Rue Caporal Claes 38",
    "sg:city":"Bruxelles (schaerbeek)",
    "sg:classifiers":[
        {
            "category":"Education",
            "subcategory":"School",
            "type":"Public Place"
        }
    ],
    "sg:phone":"+32 2 240 16 10",
    "sg:postcode":"1030",
    "sg:province":"Bruxelles-Capitale",
    "sg:tags":[
        "secondary"
    ],
    "wof:name":"Inst St Dominique",
    "wof:placetype":"venue"
},
  "geometry": {"coordinates":[4.3892998695,50.8668251038],"type":"Point"}
}