{
  "type": "Feature",
  "properties": {
    "addr:full":"Rue De La Chapelle 2 Gedinne Namur 5575",
    "addr:housenumber":"2",
    "addr:postcode":"5575",
    "addr:street":"Rue De La Chapelle",
    "iso:country":"BE",
    "sg:address":"Rue De La Chapelle 2",
    "sg:city":"Gedinne",
    "sg:orig_category":"Rundveehouders",
    "sg:phone":"+32 61 58 83 63",
    "sg:postcode":"5575",
    "sg:province":"Namur",
    "wof:name":"Jacques De Boel",
    "wof:placetype":"venue"
},
  "geometry": {"coordinates":[4.8479838371,49.9875946045],"type":"Point"}
}