{
  "type": "Feature",
  "properties": {
    "addr:full":"Boulevard Brand Whitlock 46 Bruxelles (woluwe-saint-lambert) Bruxelles-Capitale 1200",
    "addr:housenumber":"46",
    "addr:postcode":"1200",
    "addr:street":"Boulevard Brand Whitlock",
    "iso:country":"BE",
    "sg:address":"Boulevard Brand Whitlock 46",
    "sg:city":"Bruxelles (woluwe-saint-lambert)",
    "sg:classifiers":[
        {
            "category":"Real Estate",
            "subcategory":"Real Estate Agent",
            "type":"Services"
        }
    ],
    "sg:phone":"+32 2 732 90 01",
    "sg:postcode":"1200",
    "sg:province":"Bruxelles-Capitale",
    "sg:tags":[
        "importer",
        "champagne",
        "-"
    ],
    "wof:name":"Laurent-perrier Belgique",
    "wof:placetype":"venue"
},
  "geometry": {"coordinates":[4.407916069,50.8403358459],"type":"Point"}
}