{
  "type": "Feature",
  "properties": {
    "iso:country":"BE",
    "sg:address":"Kroonwinningstraat 127",
    "sg:city":"Hasselt",
    "sg:orig_category":"Avocats and conseillers juridiques",
    "sg:phone":"+32 11 28 57 88",
    "sg:postcode":"3500",
    "sg:province":"Limburg",
    "wof:name":"Mia Willems",
    "wof:placetype":"venue"
},
  "geometry": {"coordinates":[5.3588972092,50.9166259766],"type":"Point"}
}