{
  "type": "Feature",
  "properties": {
    "addr:full":"Dendermondsesteenweg 91 Laarne (kalken) Oost-Vlaanderen 9270",
    "addr:housenumber":"91",
    "addr:postcode":"9270",
    "addr:street":"Dendermondsesteenweg",
    "iso:country":"BE",
    "sg:address":"Dendermondsesteenweg 91",
    "sg:city":"Laarne (kalken)",
    "sg:orig_category":"Autombile concessionaires",
    "sg:phone":"+32 9 367 52 26",
    "sg:postcode":"9270",
    "sg:province":"Oost-Vlaanderen",
    "wof:name":"Gar Blancquart Bvba",
    "wof:placetype":"venue"
},
  "geometry": {"coordinates":[3.932708025,51.0464935303],"type":"Point"}
}