{
  "type": "Feature",
  "properties": {
    "addr:full":"Rue Saint-roch 24 Viroinval Namur 5670",
    "addr:housenumber":"24",
    "addr:postcode":"5670",
    "addr:street":"Rue Saint-Roch",
    "iso:country":"BE",
    "sg:address":"Rue Saint-roch 24",
    "sg:city":"Viroinval",
    "sg:orig_category":"Supermarch\u00e9s",
    "sg:phone":"+32 60 31 25 38",
    "sg:postcode":"5670",
    "sg:province":"Namur",
    "wof:name":"Battard",
    "wof:placetype":"venue"
},
  "geometry": {"coordinates":[4.5477252007,50.0760993958],"type":"Point"}
}