{
  "type": "Feature",
  "properties": {
    "iso:country":"BE",
    "sg:address":"Rue Haut-vinave 9",
    "sg:city":"Remicourt (momalle)",
    "sg:classifiers":[
        {
            "category":"Health Services",
            "subcategory":"Nursing And Care Facility",
            "type":"Services"
        }
    ],
    "sg:phone":"+32 4 230 28 40",
    "sg:postcode":"4350",
    "sg:province":"Li\u00e8ge",
    "sg:tags":[
        "home",
        "rest"
    ],
    "wof:name":"Quatre Saisons (les)",
    "wof:placetype":"venue"
},
  "geometry": {"coordinates":[5.3808999062,50.6824989319],"type":"Point"}
}