{
  "type": "Feature",
  "properties": {
    "iso:country":"BE",
    "sg:address":"Prins Boudewijnlaan 344",
    "sg:city":"Edegem",
    "sg:classifiers":[
        {
            "category":"Professional",
            "subcategory":"Management & Consulting",
            "type":"Services"
        }
    ],
    "sg:phone":"+32 3 449 88 38",
    "sg:postcode":"2650",
    "sg:province":"Antwerpen",
    "sg:tags":[
        "consultant"
    ],
    "wof:name":"Quintuplex Engineering Nv",
    "wof:placetype":"venue"
},
  "geometry": {"coordinates":[4.4263210297,51.1657142639],"type":"Point"}
}