{
  "type": "Feature",
  "properties": {
    "iso:country":"BE",
    "sg:address":"Rijckerstraat 14",
    "sg:city":"Riemst",
    "sg:orig_category":"Fruitteelt Varkenskwekers",
    "sg:phone":"+32 12 23 49 76",
    "sg:postcode":"3770",
    "sg:province":"Limburg",
    "wof:name":"Joannes Festjens",
    "wof:placetype":"venue"
},
  "geometry": {"coordinates":[5.5290398598,50.8177947998],"type":"Point"}
}