{
  "type": "Feature",
  "properties": {
    "addr:full":"Kortestraat 33 Izegem West-Vlaanderen 8870",
    "addr:housenumber":"33",
    "addr:postcode":"8870",
    "addr:street":"Kortestraat",
    "iso:country":"BE",
    "sg:address":"Kortestraat 33",
    "sg:city":"Izegem",
    "sg:classifiers":[
        {
            "category":"Retail",
            "subcategory":"Auto Repair",
            "type":"Services"
        }
    ],
    "sg:phone":"+32 51 32 12 58",
    "sg:postcode":"8870",
    "sg:province":"West-Vlaanderen",
    "sg:tags":[
        "garage"
    ],
    "wof:name":"Skoda/izegem Motors Nv",
    "wof:placetype":"venue"
},
  "geometry": {"coordinates":[3.2100090981,50.9087562561],"type":"Point"}
}