{
  "type": "Feature",
  "properties": {
    "addr:full":"Avenue De La Gare 137 Neufch\u00e2teau Luxembourg 6840",
    "addr:housenumber":"137",
    "addr:postcode":"6840",
    "addr:street":"Avenue De La Gare",
    "iso:country":"BE",
    "sg:address":"Avenue De La Gare 137",
    "sg:city":"Neufch\u00e2teau",
    "sg:classifiers":[
        {
            "category":"Building & Trades",
            "subcategory":"Landscaping Services",
            "type":"Services"
        }
    ],
    "sg:phone":"+32 61 27 72 71",
    "sg:postcode":"6840",
    "sg:province":"Luxembourg",
    "sg:tags":[
        "gardening",
        "garden",
        "maintenance"
    ],
    "wof:name":"Incourt N",
    "wof:placetype":"venue"
},
  "geometry": {"coordinates":[5.4451818466,49.8504219055],"type":"Point"}
}