{
  "type": "Feature",
  "properties": {
    "addr:full":"Rue Bout Troue 155 Thuin Hainaut 6536",
    "addr:housenumber":"155",
    "addr:postcode":"6536",
    "addr:street":"Rue Bout Troue",
    "iso:country":"BE",
    "sg:address":"Rue Bout Troue 155",
    "sg:city":"Thuin",
    "sg:orig_category":"Telecommunicatieapparaten",
    "sg:phone":"+32 71 53 49 28",
    "sg:postcode":"6536",
    "sg:province":"Hainaut",
    "wof:name":"Sablon Thierry",
    "wof:placetype":"venue"
},
  "geometry": {"coordinates":[4.3163580894,50.2754325867],"type":"Point"}
}