{
  "type": "Feature",
  "properties": {
    "iso:country":"BE",
    "sg:address":"De Costerstraat 32",
    "sg:city":"Haacht",
    "sg:orig_category":"Drukkerijen and copyshops",
    "sg:phone":"+32 16 60 35 33",
    "sg:postcode":"3150",
    "sg:province":"Vlaams-Brabant",
    "wof:name":"Dirk De Troy",
    "wof:placetype":"venue"
},
  "geometry": {"coordinates":[4.6393060684,50.9532852173],"type":"Point"}
}