{
  "type": "Feature",
  "properties": {
    "addr:full":"Route De Trazegnies 303 Charleroi Hainaut 6031",
    "addr:housenumber":"303",
    "addr:postcode":"6031",
    "addr:street":"Route De Trazegnies;Hainaut",
    "iso:country":"BE",
    "sg:address":"Route De Trazegnies 303",
    "sg:city":"Charleroi",
    "sg:orig_category":"Entretien and r\u00e9parations de voitures",
    "sg:phone":"+32 71 31 87 52",
    "sg:postcode":"6031",
    "sg:province":"Hainaut",
    "wof:name":"Garage Boschi",
    "wof:placetype":"venue"
},
  "geometry": {"coordinates":[4.38022995,50.4121742249],"type":"Point"}
}