{
  "type": "Feature",
  "properties": {
    "iso:country":"BE",
    "sg:address":"Schoolstraat 81",
    "sg:city":"Herk-de-stad",
    "sg:orig_category":"Fruitteelt",
    "sg:phone":"+32 13 55 16 50",
    "sg:postcode":"3540",
    "sg:province":"Limburg",
    "wof:name":"Linda Breems",
    "wof:placetype":"venue"
},
  "geometry": {"coordinates":[5.2074980736,50.9103393555],"type":"Point"}
}