{
  "type": "Feature",
  "properties": {
    "iso:country":"BE",
    "sg:address":"Rue De La Gare 135",
    "sg:city":"Bertrix",
    "sg:classifiers":[
        {
            "category":"Communications",
            "subcategory":"Film & Video Production",
            "type":"Services"
        }
    ],
    "sg:phone":"+32 61 41 29 63",
    "sg:postcode":"6880",
    "sg:province":"Luxembourg",
    "sg:tags":[
        "realisation",
        "-"
    ],
    "wof:name":"Davis Video Production-gamby H",
    "wof:placetype":"venue"
},
  "geometry": {"coordinates":[5.2640061378,49.8546676636],"type":"Point"}
}