{
  "type": "Feature",
  "properties": {
    "iso:country":"BE",
    "sg:address":"Rue Du Tr\u00d4ne 198",
    "sg:city":"Elsene/ixelles",
    "sg:orig_category":"Binnenhuisarchitecten",
    "sg:phone":"+32 2 640 58 01",
    "sg:postcode":"1050",
    "sg:province":"Bruxelles-Capitale",
    "wof:name":"Archizen",
    "wof:placetype":"venue"
},
  "geometry": {"coordinates":[4.3738379478,50.8340911865],"type":"Point"}
}