{
  "type": "Feature",
  "properties": {
    "addr:full":"Chauss\u00c9e De Fleurus 112 Charleroi Hainaut 6060",
    "addr:housenumber":"112",
    "addr:postcode":"6060",
    "addr:street":"Chausse\u0301E De Fleurus;Hainaut",
    "iso:country":"BE",
    "sg:address":"Chauss\u00c9e De Fleurus 112",
    "sg:city":"Charleroi",
    "sg:orig_category":"Pharmaciens",
    "sg:phone":"+32 71 41 57 21",
    "sg:postcode":"6060",
    "sg:province":"Hainaut",
    "wof:name":"Multipharma",
    "wof:placetype":"venue"
},
  "geometry": {"coordinates":[4.4735198021,50.4393844604],"type":"Point"}
}