{
  "type": "Feature",
  "properties": {
    "iso:country":"BE",
    "sg:address":"Herderstraat 10",
    "sg:city":"Zele",
    "sg:orig_category":"Smokers' supplies",
    "sg:phone":"+32 52 45 25 69",
    "sg:postcode":"9240",
    "sg:province":"Oost-Vlaanderen",
    "wof:name":"Zwartjes Bvba",
    "wof:placetype":"venue"
},
  "geometry": {"coordinates":[4.0546708107,51.0751953125],"type":"Point"}
}