{
  "type": "Feature",
  "properties": {
    "addr:full":"Hannuitsesteenweg 171 Landen Vlaams-Brabant 3401",
    "addr:housenumber":"171",
    "addr:postcode":"3401",
    "addr:street":"Hannuitsesteenweg",
    "iso:country":"BE",
    "sg:address":"Hannuitsesteenweg 171",
    "sg:city":"Landen",
    "sg:orig_category":"Herstellingen motorfietsen Motorfietsen",
    "sg:phone":"+32 11 83 23 43",
    "sg:postcode":"3401",
    "sg:province":"Vlaams-Brabant",
    "wof:name":"Motorshop G.s.m.",
    "wof:placetype":"venue"
},
  "geometry": {"coordinates":[5.081305027,50.7396469116],"type":"Point"}
}