{
  "type": "Feature",
  "properties": {
    "iso:country":"BE",
    "sg:address":"Rue De Belle Vue 50",
    "sg:city":"Dour",
    "sg:classifiers":[
        {
            "category":"Wholesale",
            "subcategory":"Fruits & Vegetables",
            "type":"Manufacturing & Wholesale Goods"
        }
    ],
    "sg:phone":"+32 65 69 02 26",
    "sg:postcode":"7370",
    "sg:province":"Hainaut",
    "sg:tags":[
        "whol",
        "-",
        "potato"
    ],
    "wof:name":"Liecopotatoes Sa",
    "wof:placetype":"venue"
},
  "geometry": {"coordinates":[3.7632880211,50.4059295654],"type":"Point"}
}