{
  "type": "Feature",
  "properties": {
    "addr:full":"Rue Jules Destr\u00c9e 11 Braine-l`alleud Brabant Wallon 1420",
    "addr:housenumber":"11",
    "addr:postcode":"1420",
    "addr:street":"Rue Jules Destre\u0301E;Brabant Wallon",
    "iso:country":"BE",
    "sg:address":"Rue Jules Destr\u00c9e 11",
    "sg:city":"Braine-l`alleud",
    "sg:orig_category":"Traducteurs and interpr\u00e8tes",
    "sg:phone":"+32 2 387 26 60",
    "sg:postcode":"1420",
    "sg:province":"Brabant Wallon",
    "wof:name":"Chavet C. Cbtip/bkvtf",
    "wof:placetype":"venue"
},
  "geometry": {"coordinates":[5.8036999702,45.9799995422],"type":"Point"}
}