{
  "type": "Feature",
  "properties": {
    "iso:country":"BE",
    "sg:address":"Manestraat 23",
    "sg:city":"Herk-de-stad",
    "sg:classifiers":[
        {
            "category":"Arena",
            "subcategory":"Sports Club",
            "type":"Entertainment"
        }
    ],
    "sg:phone":"+32 13 55 55 24",
    "sg:postcode":"3540",
    "sg:province":"Limburg",
    "sg:tags":[
        "de"
    ],
    "wof:name":"W.c. Hand In Hand",
    "wof:placetype":"venue"
},
  "geometry": {"coordinates":[5.1828479767,50.9537391663],"type":"Point"}
}