{
  "type": "Feature",
  "properties": {
    "iso:country":"BE",
    "sg:address":"Dorpsstraat 49",
    "sg:city":"Jabbeke",
    "sg:classifiers":[
        {
            "category":"Retail",
            "subcategory":"Repair Shop",
            "type":"Services"
        }
    ],
    "sg:phone":"+32 50 81 20 33",
    "sg:postcode":"8490",
    "sg:province":"West-Vlaanderen",
    "sg:tags":[
        "-",
        "mainten",
        "watch",
        "clock"
    ],
    "wof:name":"M'onyx's",
    "wof:placetype":"venue"
},
  "geometry": {"coordinates":[3.0897641182,51.1817207336],"type":"Point"}
}