{
  "type": "Feature",
  "properties": {
    "iso:country":"BE",
    "sg:address":"Mindersbroedersstraat 14",
    "sg:city":"Antwerpen",
    "sg:classifiers":[
        {
            "category":"Professional",
            "subcategory":"Advertising",
            "type":"Services"
        }
    ],
    "sg:phone":"+32 3 241 00 24",
    "sg:postcode":"2000",
    "sg:province":"Antwerpen",
    "sg:tags":[
        "marketing",
        "medium",
        "communication"
    ],
    "wof:name":"Yellow Window Management Consult Nv",
    "wof:placetype":"venue"
},
  "geometry": {"coordinates":[4.4049777985,51.2229385376],"type":"Point"}
}