{
  "type": "Feature",
  "properties": {
    "iso:country":"BE",
    "sg:address":"Brugsesteenweg 333",
    "sg:city":"Roeselare",
    "sg:orig_category":"Autombile concessionaires",
    "sg:phone":"+32 51 22 93 99",
    "sg:postcode":"8800",
    "sg:province":"West-Vlaanderen",
    "wof:name":"Gar Dejonghe",
    "wof:placetype":"venue"
},
  "geometry": {"coordinates":[3.1202919483,50.9662704468],"type":"Point"}
}