{
  "type": "Feature",
  "properties": {
    "addr:full":"Rue Arthur Maes 100 Bruxelles Bruxelles-Capitale 1130",
    "addr:housenumber":"100",
    "addr:postcode":"1130",
    "addr:street":"Rue Arthur Maes",
    "iso:country":"BE",
    "sg:address":"Rue Arthur Maes 100",
    "sg:city":"Bruxelles",
    "sg:classifiers":[
        {
            "category":"Autos & Motor Vehicles",
            "subcategory":"Motorcycle Sales",
            "type":"Retail Goods"
        }
    ],
    "sg:phone":"+32 2 724 90 90",
    "sg:postcode":"1130",
    "sg:province":"Bruxelles-Capitale",
    "sg:tags":[
        "motorbike"
    ],
    "wof:name":"Demimpex V.r.p.",
    "wof:placetype":"venue"
},
  "geometry": {"coordinates":[4.4233908653,50.8843765259],"type":"Point"}
}