{
  "type": "Feature",
  "properties": {
    "addr:full":"Avenue Delleur 17 Bruxelles (watermael-boitsfort) Bruxelles-Capitale 1170",
    "addr:housenumber":"17",
    "addr:postcode":"1170",
    "addr:street":"Avenue Delleur",
    "iso:country":"BE",
    "sg:address":"Avenue Delleur 17",
    "sg:city":"Bruxelles (watermael-boitsfort)",
    "sg:classifiers":[
        {
            "category":"Professional",
            "subcategory":"Management & Consulting",
            "type":"Services"
        }
    ],
    "sg:phone":"+32 2 675 71 01",
    "sg:postcode":"1170",
    "sg:province":"Bruxelles-Capitale",
    "sg:tags":[
        "consultant"
    ],
    "wof:name":"Afco Sprl",
    "wof:placetype":"venue"
},
  "geometry": {"coordinates":[4.4102478027,50.7952575684],"type":"Point"}
}