{
  "type": "Feature",
  "properties": {
    "addr:full":"Grand Ry Wegnez 276 Pepinster Li\u00e8ge 4860",
    "addr:housenumber":"276",
    "addr:postcode":"4860",
    "addr:street":"Wegnez",
    "iso:country":"BE",
    "sg:address":"Grand Ry Wegnez 276",
    "sg:city":"Pepinster",
    "sg:classifiers":[
        {
            "category":"Arena",
            "subcategory":"Sports Club",
            "type":"Entertainment"
        }
    ],
    "sg:phone":"+32 87 46 11 02",
    "sg:postcode":"4860",
    "sg:province":"Li\u00e8ge",
    "sg:tags":[
        "terrain",
        "hors",
        "de",
        "installation",
        "sportifs"
    ],
    "wof:name":"Cornesse F.c.",
    "wof:placetype":"venue"
},
  "geometry": {"coordinates":[5.8166232109,50.579158783],"type":"Point"}
}