{
  "type": "Feature",
  "properties": {
    "addr:full":"Molenwalstraat 64 Gent Oost-Vlaanderen 9030",
    "addr:housenumber":"64",
    "addr:postcode":"9030",
    "addr:street":"Molenwalstraat;Oost-Vlaanderen",
    "iso:country":"BE",
    "sg:address":"Molenwalstraat 64",
    "sg:city":"Gent",
    "sg:orig_category":"Produits surgel\u00e9s Gr",
    "sg:phone":"+32 9 226 75 05",
    "sg:postcode":"9030",
    "sg:province":"Oost-Vlaanderen",
    "wof:name":"Delicias",
    "wof:placetype":"venue"
},
  "geometry": {"coordinates":[3.6974520683,51.0753097534],"type":"Point"}
}