{
  "type": "Feature",
  "properties": {
    "iso:country":"BE",
    "sg:address":"Nati\u00ebnlaan 176",
    "sg:city":"Knokke-heist (knokke)",
    "sg:classifiers":[
        {
            "category":"Sports & Exercise",
            "subcategory":"Gym",
            "type":"Entertainment"
        }
    ],
    "sg:phone":"+32 50 62 25 24",
    "sg:postcode":"8300",
    "sg:province":"West-Vlaanderen",
    "sg:tags":[
        "fitness"
    ],
    "wof:name":"Karina's",
    "wof:placetype":"venue"
},
  "geometry": {"coordinates":[3.2888998985,51.3360900879],"type":"Point"}
}