{
  "type": "Feature",
  "properties": {
    "addr:full":"Grote Markt 13 Antwerpen Antwerpen 2000",
    "addr:housenumber":"13",
    "addr:postcode":"2000",
    "addr:street":"Grote Markt",
    "iso:country":"BE",
    "sg:address":"Grote Markt 13",
    "sg:city":"Antwerpen",
    "sg:classifiers":[
        {
            "category":"Museum",
            "type":"Entertainment"
        }
    ],
    "sg:phone":"+32 3 220 81 28",
    "sg:postcode":"2000",
    "sg:province":"Antwerpen",
    "wof:name":"Financieel Beheer Promotie Stad Antwerpen Vzw",
    "wof:placetype":"venue"
},
  "geometry": {"coordinates":[4.4001631737,51.2214317322],"type":"Point"}
}