{
  "type": "Feature",
  "properties": {
    "iso:country":"BE",
    "sg:address":"Adelbergpark 3",
    "sg:city":"Lommel",
    "sg:classifiers":[
        {
            "category":"Health Services",
            "subcategory":"Health Practitioner",
            "type":"Services"
        }
    ],
    "sg:phone":"+32 11 54 70 80",
    "sg:postcode":"3920",
    "sg:province":"Limburg",
    "sg:tags":[
        "dietitian"
    ],
    "wof:name":"Vitae",
    "wof:placetype":"venue"
},
  "geometry": {"coordinates":[5.3092951775,51.2315368652],"type":"Point"}
}