{
  "type": "Feature",
  "properties": {
    "iso:country":"BE",
    "sg:address":"Clos Du Drossart 13",
    "sg:city":"Bruxelles (uccle)",
    "sg:classifiers":[
        {
            "category":"Real Estate",
            "subcategory":"Architect",
            "type":"Services"
        }
    ],
    "sg:phone":"+32 2 375 27 50",
    "sg:postcode":"1180",
    "sg:province":"Bruxelles-Capitale",
    "wof:name":"Delwarde B",
    "wof:placetype":"venue"
},
  "geometry": {"coordinates":[4.3542561531,50.7935905457],"type":"Point"}
}