{
  "type": "Feature",
  "properties": {
    "iso:country":"BE",
    "sg:address":"Rue De La Paix 44",
    "sg:city":"Manage",
    "sg:classifiers":[
        {
            "category":"Wholesale",
            "subcategory":"Wine & Distilled Alcoholic Beverages",
            "type":"Manufacturing & Wholesale Goods"
        }
    ],
    "sg:phone":"+32 64 77 29 60",
    "sg:postcode":"7170",
    "sg:province":"Hainaut",
    "sg:tags":[
        "whol",
        "-",
        "spirit",
        "mfg"
    ],
    "wof:name":"Sitalvini",
    "wof:placetype":"venue"
},
  "geometry": {"coordinates":[4.2298150063,50.4924659729],"type":"Point"}
}