{
  "type": "Feature",
  "properties": {
    "addr:full":"Marktstraat 36 Opwijk Vlaams-Brabant 1745",
    "addr:housenumber":"36",
    "addr:postcode":"1745",
    "addr:street":"Marktstraat",
    "iso:country":"BE",
    "sg:address":"Marktstraat 36",
    "sg:city":"Opwijk",
    "sg:orig_category":"Banken and kredietinstellingen",
    "sg:phone":"+32 52 35 70 61",
    "sg:postcode":"1745",
    "sg:province":"Vlaams-Brabant",
    "wof:name":"Bbl",
    "wof:placetype":"venue"
},
  "geometry": {"coordinates":[4.1886200905,50.9701271057],"type":"Point"}
}