{
  "type": "Feature",
  "properties": {
    "addr:full":"Boulevard Eisenhower 23 Tournai Hainaut 7500",
    "addr:housenumber":"23",
    "addr:postcode":"7500",
    "addr:street":"Boulevard Eisenhower",
    "iso:country":"BE",
    "sg:address":"Boulevard Eisenhower 23",
    "sg:city":"Tournai",
    "sg:classifiers":[
        {
            "category":"Shopping",
            "subcategory":"Books",
            "type":"Retail Goods"
        }
    ],
    "sg:phone":"+32 69 21 30 13",
    "sg:postcode":"7500",
    "sg:province":"Hainaut",
    "sg:tags":[
        "bookseller"
    ],
    "wof:name":"Vastrat G",
    "wof:placetype":"venue"
},
  "geometry": {"coordinates":[3.3895521164,50.6161079407],"type":"Point"}
}