{
  "type": "Feature",
  "properties": {
    "iso:country":"BE",
    "sg:address":"Wemmelse Steenweg 114",
    "sg:city":"Jette",
    "sg:orig_category":"Tijdelijke werkgelegenheid and uitzendkantoren",
    "sg:phone":"+32 2 425 12 57",
    "sg:postcode":"1090",
    "sg:province":"Bruxelles-Capitale",
    "wof:name":"Action Interim",
    "wof:placetype":"venue"
},
  "geometry": {"coordinates":[4.3241782188,50.8763961792],"type":"Point"}
}