{
  "type": "Feature",
  "properties": {
    "iso:country":"BE",
    "sg:address":"Rue Du Paradis 22",
    "sg:city":"Gembloux-sur-orneau (gembloux)",
    "sg:classifiers":[
        {
            "category":"Health Services",
            "subcategory":"Health Practitioner",
            "type":"Services"
        }
    ],
    "sg:phone":"+32 81 60 06 15",
    "sg:postcode":"5030",
    "sg:province":"Namur",
    "sg:tags":[
        "physiotherapist"
    ],
    "wof:name":"Hourlay F",
    "wof:placetype":"venue"
},
  "geometry": {"coordinates":[4.6805157661,50.5593185425],"type":"Point"}
}