{
  "type": "Feature",
  "properties": {
    "iso:country":"BE",
    "sg:address":"Place Lt. Graff 10",
    "sg:city":"Wemmel/wemmel",
    "sg:orig_category":"Blanchisseries and teintureries",
    "sg:phone":"+32 2 460 47 99",
    "sg:postcode":"1780",
    "sg:province":"Vlaams-Brabant",
    "wof:name":"Dugardin Teinturier",
    "wof:placetype":"venue"
},
  "geometry": {"coordinates":[4.3125629425,50.904499054],"type":"Point"}
}