{
  "type": "Feature",
  "properties": {
    "iso:country":"BE",
    "sg:address":"Marionetten 39",
    "sg:city":"Kortrijk",
    "sg:classifiers":[
        {
            "category":"Shopping",
            "subcategory":"Clothing, Apparel, & Fashions",
            "type":"Retail Goods"
        }
    ],
    "sg:phone":"+32 56 20 06 79",
    "sg:postcode":"8500",
    "sg:province":"West-Vlaanderen",
    "sg:tags":[
        "lingerie",
        "sous-v\u00eatements"
    ],
    "wof:name":"Textiel Basyn",
    "wof:placetype":"venue"
},
  "geometry": {"coordinates":[3.2634930611,50.7954406738],"type":"Point"}
}