{
  "type": "Feature",
  "properties": {
    "addr:full":"Brusselbaan 76 Affligem (hekelgem) Vlaams-Brabant 1790",
    "addr:housenumber":"76",
    "addr:postcode":"1790",
    "addr:street":"Brusselbaan",
    "iso:country":"BE",
    "sg:address":"Brusselbaan 76",
    "sg:city":"Affligem (hekelgem)",
    "sg:classifiers":[
        {
            "category":"Retail",
            "subcategory":"Event Space",
            "type":"Services"
        }
    ],
    "sg:phone":"+32 53 66 89 31",
    "sg:postcode":"1790",
    "sg:province":"Vlaams-Brabant",
    "sg:tags":[
        "rental",
        "-",
        "hall"
    ],
    "wof:name":"'t Brouwershof Anno 1790",
    "wof:placetype":"venue"
},
  "geometry": {"coordinates":[4.1036219597,50.9135475159],"type":"Point"}
}