{
  "type": "Feature",
  "properties": {
    "addr:full":"Avenue Du Forum 40 Bruxelles Bruxelles-Capitale 1020",
    "addr:housenumber":"40",
    "addr:postcode":"1020",
    "addr:street":"Avenue Du Forum",
    "iso:country":"BE",
    "sg:address":"Avenue Du Forum 40",
    "sg:city":"Bruxelles",
    "sg:classifiers":[
        {
            "category":"Sports & Exercise",
            "subcategory":"Gym",
            "type":"Entertainment"
        }
    ],
    "sg:phone":"+32 2 268 74 47",
    "sg:postcode":"1020",
    "sg:province":"Bruxelles-Capitale",
    "sg:tags":[
        "fitness"
    ],
    "wof:name":"Centre De Mise En Condition Physique",
    "wof:placetype":"venue"
},
  "geometry": {"coordinates":[4.3535790443,50.9004707336],"type":"Point"}
}