{
  "type": "Feature",
  "properties": {
    "addr:full":"Rue R Elisabeth 10 Mettet Namur 5640",
    "addr:housenumber":"10",
    "addr:postcode":"5640",
    "addr:street":"Rue R Elisabeth",
    "iso:country":"BE",
    "sg:address":"Rue R Elisabeth 10",
    "sg:city":"Mettet",
    "sg:classifiers":[
        {
            "category":"Banks & Credit Unions",
            "subcategory":"Bank",
            "type":"Services"
        }
    ],
    "sg:phone":"+32 60 72 70 36",
    "sg:postcode":"5640",
    "sg:province":"Namur",
    "wof:name":"G\u00e9n\u00e9rale De Banque Sa",
    "wof:placetype":"venue"
},
  "geometry": {"coordinates":[4.6585001945,50.3200683594],"type":"Point"}
}