{
  "type": "Feature",
  "properties": {
    "iso:country":"BE",
    "sg:address":"Noordzandstraat 36",
    "sg:city":"Brugge",
    "sg:classifiers":[
        {
            "category":"Shopping",
            "subcategory":"Clothing, Apparel, & Fashions",
            "type":"Retail Goods"
        }
    ],
    "sg:phone":"+32 50 34 59 54",
    "sg:postcode":"8000",
    "sg:province":"West-Vlaanderen",
    "sg:tags":[
        "hosiery"
    ],
    "wof:name":"De Zokke Bvba",
    "wof:placetype":"venue"
},
  "geometry": {"coordinates":[3.2202119827,51.2075843811],"type":"Point"}
}