{
  "type": "Feature",
  "properties": {
    "iso:country":"BE",
    "sg:address":"Rue Basse Chauss\u00e9e 194",
    "sg:city":"Namur (cognel\u00e9e)",
    "sg:classifiers":[
        {
            "category":"Health Services",
            "subcategory":"Doctor",
            "type":"Services"
        }
    ],
    "sg:phone":"+32 81 21 50 40",
    "sg:postcode":"5022",
    "sg:province":"Namur",
    "sg:tags":[
        "medicinephysicians",
        "surgeon"
    ],
    "wof:name":"Malbecq S",
    "wof:placetype":"venue"
},
  "geometry": {"coordinates":[4.902985096,50.513671875],"type":"Point"}
}