{
  "type": "Feature",
  "properties": {
    "addr:full":"Weldadigheidsstraat 75 Leuven Vlaams-Brabant 3000",
    "addr:housenumber":"75",
    "addr:postcode":"3000",
    "addr:street":"Weldadigheidsstraat",
    "iso:country":"BE",
    "sg:address":"Weldadigheidsstraat 75",
    "sg:city":"Leuven",
    "sg:orig_category":"Artsen and specialisten",
    "sg:phone":"+32 16 23 58 28",
    "sg:postcode":"3000",
    "sg:province":"Vlaams-Brabant",
    "wof:name":"Karel Wuille",
    "wof:placetype":"venue"
},
  "geometry": {"coordinates":[4.7032952309,50.8707847595],"type":"Point"}
}