{
  "type": "Feature",
  "properties": {
    "addr:full":"Beverenstraat 91 Alveringem West-Vlaanderen 8691",
    "addr:housenumber":"91",
    "addr:postcode":"8691",
    "addr:street":"Beverenstraat",
    "iso:country":"BE",
    "sg:address":"Beverenstraat 91",
    "sg:city":"Alveringem",
    "sg:orig_category":"Eleveurs de bovins. Eleveurs and marchands de porcs",
    "sg:phone":"+32 58 29 93 06",
    "sg:postcode":"8691",
    "sg:province":"West-Vlaanderen",
    "wof:name":"Dirk Top",
    "wof:placetype":"venue"
},
  "geometry": {"coordinates":[2.6398348808,50.9585151672],"type":"Point"}
}