{
  "type": "Feature",
  "properties": {
    "addr:full":"Fabriekstraat 37 Sint-pieters-leeuw (ruisbroek) Vlaams-Brabant 1601",
    "addr:housenumber":"37",
    "addr:postcode":"1601",
    "addr:street":"Fabriekstraat",
    "iso:country":"BE",
    "sg:address":"Fabriekstraat 37",
    "sg:city":"Sint-pieters-leeuw (ruisbroek)",
    "sg:classifiers":[
        {
            "category":"Banks & Credit Unions",
            "subcategory":"Investment Brokerage",
            "type":"Services"
        }
    ],
    "sg:phone":"+32 2 331 30 75",
    "sg:postcode":"1601",
    "sg:province":"Vlaams-Brabant",
    "sg:tags":[
        "supply",
        "processing",
        "-",
        "access",
        "carrier",
        "data"
    ],
    "wof:name":"View Line Bvba",
    "wof:placetype":"venue"
},
  "geometry": {"coordinates":[4.2938280106,50.7846908569],"type":"Point"}
}