{
  "type": "Feature",
  "properties": {
    "addr:full":"Route Militaire 6 Amay Li\u00e8ge 4540",
    "addr:housenumber":"6",
    "addr:postcode":"4540",
    "addr:street":"Route Militaire",
    "iso:country":"BE",
    "sg:address":"Route Militaire 6",
    "sg:city":"Amay",
    "sg:orig_category":"Ordinateurs and \u00e9quipement informatique",
    "sg:phone":"+32 85 31 33 91",
    "sg:postcode":"4540",
    "sg:province":"Li\u00e8ge",
    "wof:name":"F.c.i.",
    "wof:placetype":"venue"
},
  "geometry": {"coordinates":[5.3180990219,50.5478668213],"type":"Point"}
}