{
  "type": "Feature",
  "properties": {
    "addr:full":"Industriezone De Meiren Vijversweg Rijkevorsel Antwerpen 2310",
    "addr:postcode":"2310",
    "addr:street":"Industriezone De Meiren Vijversweg",
    "iso:country":"BE",
    "sg:address":"Industriezone De Meiren Vijversweg",
    "sg:city":"Rijkevorsel",
    "sg:classifiers":[
        {
            "category":"Manufacturing",
            "subcategory":"Metals",
            "type":"Manufacturing & Wholesale Goods"
        }
    ],
    "sg:phone":"+32 3 314 79 18",
    "sg:postcode":"2310",
    "sg:province":"Antwerpen",
    "sg:tags":[
        "aluminium"
    ],
    "wof:name":"Pierre Stubbe Bvba",
    "wof:placetype":"venue"
},
  "geometry": {"coordinates":[4.7595419884,51.3500099182],"type":"Point"}
}