{
  "type": "Feature",
  "properties": {
    "iso:country":"BE",
    "sg:address":"Grote Baan 80",
    "sg:city":"Ravels",
    "sg:orig_category":"WAPENS AND MUNITIE",
    "sg:phone":"+32 14 65 53 64",
    "sg:postcode":"2380",
    "sg:province":"Antwerpen",
    "wof:name":"Fa. Van De Pol",
    "wof:placetype":"venue"
},
  "geometry": {"coordinates":[4.9924230576,51.3670043945],"type":"Point"}
}