{
  "type": "Feature",
  "properties": {
    "iso:country":"BE",
    "sg:address":"Rue Stevens-delannoy 101",
    "sg:city":"Brussel/bruxelles",
    "sg:orig_category":"Enseignement maternel and primaire",
    "sg:phone":"+32 2 478 50 51",
    "sg:postcode":"1020",
    "sg:province":"Bruxelles-Capitale",
    "wof:name":"Ecole Fondamentale Libre",
    "wof:placetype":"venue"
},
  "geometry": {"coordinates":[4.3414878845,50.8899230957],"type":"Point"}
}