{
  "type": "Feature",
  "properties": {
    "iso:country":"BE",
    "sg:address":"Herbaimont 24",
    "sg:city":"Sainte-ode",
    "sg:orig_category":"V\u00e9t\u00e9rinaires",
    "sg:phone":"+32 61 68 87 65",
    "sg:postcode":"6680",
    "sg:province":"Luxembourg",
    "wof:name":"Pierre Longueville",
    "wof:placetype":"venue"
},
  "geometry": {"coordinates":[5.5492959023,50.0522346497],"type":"Point"}
}