{
  "type": "Feature",
  "properties": {
    "iso:country":"BE",
    "sg:address":"Rue Entre-deux Portes 1",
    "sg:city":"Huy",
    "sg:orig_category":"Mat\u00e9riel de T\u00e9l\u00e9communication. Studios photographiques. Equipement photographique",
    "sg:phone":"+32 85 23 61 70",
    "sg:postcode":"4500",
    "sg:province":"Li\u00e8ge",
    "wof:name":"Positif Cr\u00c9ation Photo Gillet",
    "wof:placetype":"venue"
},
  "geometry": {"coordinates":[5.230325222,50.5251045227],"type":"Point"}
}