{
  "type": "Feature",
  "properties": {
    "addr:full":"Dellenweg 52 Rijkevorsel Antwerpen 2310",
    "addr:housenumber":"52",
    "addr:postcode":"2310",
    "addr:street":"Dellenweg",
    "iso:country":"BE",
    "sg:address":"Dellenweg 52",
    "sg:city":"Rijkevorsel",
    "sg:classifiers":[
        {
            "category":"Arena",
            "subcategory":"Sports Club",
            "type":"Entertainment"
        }
    ],
    "sg:phone":"+32 3 311 64 35",
    "sg:postcode":"2310",
    "sg:province":"Antwerpen",
    "sg:tags":[
        "de"
    ],
    "wof:name":"Verbroedering",
    "wof:placetype":"venue"
},
  "geometry": {"coordinates":[4.7845230103,51.3309936523],"type":"Point"}
}