{
  "type": "Feature",
  "properties": {
    "iso:country":"BE",
    "sg:address":"An Sankersborn 41",
    "sg:city":"B\u00fctgenbach",
    "sg:classifiers":[
        {
            "category":"Home & Garden",
            "subcategory":"Building Materials",
            "type":"Retail Goods"
        }
    ],
    "sg:phone":"+32 80 67 93 88",
    "sg:postcode":"4750",
    "sg:province":"Li\u00e8ge",
    "sg:tags":[
        "window"
    ],
    "wof:name":"Alu-pvc Sarlette Sprl",
    "wof:placetype":"venue"
},
  "geometry": {"coordinates":[6.1567502022,50.4235305786],"type":"Point"}
}