{
  "type": "Feature",
  "properties": {
    "addr:full":"Brabantstraat 34a Roeselare West-Vlaanderen 8800",
    "addr:housenumber":"34a",
    "addr:postcode":"8800",
    "addr:street":"Brabantstraat",
    "iso:country":"BE",
    "sg:address":"Brabantstraat 34a",
    "sg:city":"Roeselare",
    "sg:classifiers":[
        {
            "category":"Home & Garden",
            "subcategory":"Building Materials",
            "type":"Retail Goods"
        }
    ],
    "sg:phone":"+32 51 74 50 33",
    "sg:postcode":"8800",
    "sg:province":"West-Vlaanderen",
    "sg:tags":[
        "shutter"
    ],
    "wof:name":"Plastiek Guido Vancoillie",
    "wof:placetype":"venue"
},
  "geometry": {"coordinates":[3.1588699818,50.9813499451],"type":"Point"}
}