{
  "type": "Feature",
  "properties": {
    "iso:country":"BE",
    "sg:address":"Ch Dalsemberg 812a",
    "sg:city":"Uccle",
    "sg:classifiers":[
        {
            "category":"Travel",
            "subcategory":"Hotels & Motels",
            "type":"Entertainment"
        }
    ],
    "sg:phone":"+32 2 332 37 74",
    "sg:postcode":"1180",
    "sg:province":"Bruxelles-Capitale",
    "sg:tags":[
        "hotels",
        "business",
        "restaurant"
    ],
    "wof:name":"Le Pain Et Le Vin Sa",
    "wof:placetype":"venue"
},
  "geometry": {"coordinates":[4.3319702148,50.8036155701],"type":"Point"}
}