{
  "type": "Feature",
  "properties": {
    "addr:full":"Piezelstraat 108 Roosdaal Vlaams-Brabant 1760",
    "addr:housenumber":"108",
    "addr:postcode":"1760",
    "addr:street":"Piezelstraat",
    "iso:country":"BE",
    "sg:address":"Piezelstraat 108",
    "sg:city":"Roosdaal",
    "sg:orig_category":"Evaluation and estimation de biens immobiliers",
    "sg:phone":"+32 54 32 32 68",
    "sg:postcode":"1760",
    "sg:province":"Vlaams-Brabant",
    "wof:name":"Filip Vanderlinden",
    "wof:placetype":"venue"
},
  "geometry": {"coordinates":[4.0744271278,50.8435707092],"type":"Point"}
}