{
  "type": "Feature",
  "properties": {
    "iso:country":"BE",
    "sg:address":"Rue Pepin 33",
    "sg:city":"Pepinster",
    "sg:classifiers":[
        {
            "category":"Personal",
            "subcategory":"Beauty Salon",
            "type":"Services"
        }
    ],
    "sg:phone":"+32 87 46 04 24",
    "sg:postcode":"4860",
    "sg:province":"Li\u00e8ge",
    "wof:name":"Institut Bleu Marine",
    "wof:placetype":"venue"
},
  "geometry": {"coordinates":[5.8040928841,50.5671844482],"type":"Point"}
}