{
  "type": "Feature",
  "properties": {
    "addr:full":"Kapelhof 68 Kasterlee Antwerpen 2460",
    "addr:housenumber":"68",
    "addr:postcode":"2460",
    "addr:street":"Kapelhof",
    "iso:country":"BE",
    "sg:address":"Kapelhof 68",
    "sg:city":"Kasterlee",
    "sg:orig_category":"Travaux de pl\u00e2trage",
    "sg:phone":"+32 14 55 17 93",
    "sg:postcode":"2460",
    "sg:province":"Antwerpen",
    "wof:name":"Rudi Puts",
    "wof:placetype":"venue"
},
  "geometry": {"coordinates":[4.9582901001,51.2436103821],"type":"Point"}
}