{
  "type": "Feature",
  "properties": {
    "addr:full":"Maalse Steenweg 171 Brugge (sint-kruis) West-Vlaanderen 8310",
    "addr:housenumber":"171",
    "addr:postcode":"8310",
    "addr:street":"Maalse Steenweg",
    "iso:country":"BE",
    "sg:address":"Maalse Steenweg 171",
    "sg:city":"Brugge (sint-kruis)",
    "sg:classifiers":[
        {
            "category":"Organizations",
            "subcategory":"Professional Association",
            "type":"Services"
        }
    ],
    "sg:phone":"+32 50 28 85 20",
    "sg:postcode":"8310",
    "sg:province":"West-Vlaanderen",
    "sg:tags":[
        "trade-union",
        "federation"
    ],
    "wof:name":"Dienstencentrum Acv Sint-kruis",
    "wof:placetype":"venue"
},
  "geometry": {"coordinates":[3.2509829998,51.2097129822],"type":"Point"}
}