{
  "type": "Feature",
  "properties": {
    "iso:country":"BE",
    "sg:address":"Hendrik Consciencestraat 7",
    "sg:city":"Zwevegem",
    "sg:classifiers":[
        {
            "category":"Communications",
            "type":"Services"
        }
    ],
    "sg:phone":"+32 56 75 36 23",
    "sg:postcode":"8550",
    "sg:province":"West-Vlaanderen",
    "sg:tags":[
        "translator"
    ],
    "wof:name":"Jansens N",
    "wof:placetype":"venue"
},
  "geometry": {"coordinates":[3.3457579613,50.8112411499],"type":"Point"}
}