{
  "type": "Feature",
  "properties": {
    "iso:country":"BE",
    "sg:address":"Chauss\u00c9e De Mons 123",
    "sg:city":"Anderlecht",
    "sg:orig_category":"Production de films, t\u00e9l\u00e9films and vid\u00e9os",
    "sg:phone":"+32 2 527 03 22",
    "sg:postcode":"1070",
    "sg:province":"Bruxelles-Capitale",
    "wof:name":"Uppercut",
    "wof:placetype":"venue"
},
  "geometry": {"coordinates":[4.3326449394,50.8429832458],"type":"Point"}
}