{
  "type": "Feature",
  "properties": {
    "iso:country":"BE",
    "sg:address":"Place Roi Albert I 27",
    "sg:city":"Rochefort",
    "sg:classifiers":[
        {
            "category":"Insurance",
            "subcategory":"Insurance Agent",
            "type":"Services"
        }
    ],
    "sg:phone":"+32 84 21 38 85",
    "sg:postcode":"5580",
    "sg:province":"Namur",
    "sg:tags":[
        "broker"
    ],
    "wof:name":"Jacquemin M",
    "wof:placetype":"venue"
},
  "geometry": {"coordinates":[5.2229499817,50.1580924988],"type":"Point"}
}