{
  "type": "Feature",
  "properties": {
    "addr:full":"Rue Taravis\u00c9e 6 Gembloux Namur 5031",
    "addr:housenumber":"6",
    "addr:postcode":"5031",
    "addr:street":"Rue Taravise\u0301E;Namur",
    "iso:country":"BE",
    "sg:address":"Rue Taravis\u00c9e 6",
    "sg:city":"Gembloux",
    "sg:orig_category":"Installation de menuiserie en bois and plastique",
    "sg:phone":"+32 81 64 06 54",
    "sg:postcode":"5031",
    "sg:province":"Namur",
    "wof:name":"Alain Graindorge",
    "wof:placetype":"venue"
},
  "geometry": {"coordinates":[4.7744898796,50.5952301025],"type":"Point"}
}