{
  "type": "Feature",
  "properties": {
    "iso:country":"BE",
    "sg:address":"Rue De L'industrie 66",
    "sg:city":"Sambreville (auvelais)",
    "sg:classifiers":[
        {
            "category":"Real Estate",
            "subcategory":"Architect",
            "type":"Services"
        }
    ],
    "sg:phone":"+32 71 77 06 35",
    "sg:postcode":"5060",
    "sg:province":"Namur",
    "wof:name":"Lambert N",
    "wof:placetype":"venue"
},
  "geometry": {"coordinates":[4.6229572296,50.4529075623],"type":"Point"}
}