{
  "type": "Feature",
  "properties": {
    "addr:full":"Belgi\u00cblaan 23 Herentals Antwerpen 2200",
    "addr:housenumber":"23",
    "addr:postcode":"2200",
    "addr:street":"Belgie\u0308Laan",
    "iso:country":"BE",
    "sg:address":"Belgi\u00cblaan 23",
    "sg:city":"Herentals",
    "sg:orig_category":"Tijdelijke werkgelegenheid and uitzendkantoren",
    "sg:phone":"+32 14 23 09 41",
    "sg:postcode":"2200",
    "sg:province":"Antwerpen",
    "wof:name":"Molderez Interim",
    "wof:placetype":"venue"
},
  "geometry": {"coordinates":[4.8327198029,51.1793937683],"type":"Point"}
}