{
  "type": "Feature",
  "properties": {
    "addr:full":"Heusi\u00c8re 15 Herve Li\u00e8ge 4650",
    "addr:housenumber":"15",
    "addr:postcode":"4650",
    "addr:street":"Heusie\u0300Re",
    "iso:country":"BE",
    "sg:address":"Heusi\u00c8re 15",
    "sg:city":"Herve",
    "sg:orig_category":"Travaux d'isolation. Mat\u00e9riel pour plomberie and chauffage Plomberie, chauffage and installations sa",
    "sg:phone":"+32 4 387 50 22",
    "sg:postcode":"4650",
    "sg:province":"Li\u00e8ge",
    "wof:name":"J.otten",
    "wof:placetype":"venue"
},
  "geometry": {"coordinates":[5.7585859299,50.7008209229],"type":"Point"}
}