{
  "type": "Feature",
  "properties": {
    "iso:country":"BE",
    "sg:address":"Brieversweg 114",
    "sg:city":"Brugge (sint-kruis)",
    "sg:classifiers":[
        {
            "category":"Health Services",
            "subcategory":"Doctor",
            "type":"Services"
        }
    ],
    "sg:phone":"+32 50 35 12 01",
    "sg:postcode":"8310",
    "sg:province":"West-Vlaanderen",
    "sg:tags":[
        "psychotherapist",
        "psychoanalyst"
    ],
    "wof:name":"Depecker W",
    "wof:placetype":"venue"
},
  "geometry": {"coordinates":[3.2615709305,51.2130775452],"type":"Point"}
}