{
  "type": "Feature",
  "properties": {
    "iso:country":"BE",
    "sg:address":"Zwingelaarstraat 4",
    "sg:city":"Lendelede",
    "sg:classifiers":[
        {
            "category":"Government",
            "subcategory":"Fire Station",
            "type":"Public Place"
        }
    ],
    "sg:phone":"+32 51 31 03 45",
    "sg:postcode":"8860",
    "sg:province":"West-Vlaanderen",
    "sg:tags":[
        "extinguisher"
    ],
    "wof:name":"Vanlerberghe P",
    "wof:placetype":"venue"
},
  "geometry": {"coordinates":[3.2389659882,50.8907966614],"type":"Point"}
}