{
  "type": "Feature",
  "properties": {
    "iso:country":"BE",
    "sg:address":"Avenue Moine-olbert 8",
    "sg:city":"Gembloux",
    "sg:orig_category":"Cr\u00e9dit \u00e0 la consommation",
    "sg:phone":"+32 81 61 16 08",
    "sg:postcode":"5030",
    "sg:province":"Namur",
    "wof:name":"Agence Suray",
    "wof:placetype":"venue"
},
  "geometry": {"coordinates":[4.6854310036,50.5683898926],"type":"Point"}
}