{
  "type": "Feature",
  "properties": {
    "iso:country":"BE",
    "sg:address":"Hospitaalstraat 10",
    "sg:city":"Zottegem (groot)",
    "sg:classifiers":[
        {
            "category":"Restaurant",
            "type":"Food & Drink"
        }
    ],
    "sg:phone":"+32 9 360 02 40",
    "sg:postcode":"9620",
    "sg:province":"Oost-Vlaanderen",
    "sg:tags":[
        "brasserie"
    ],
    "wof:name":"Brouwerij Crombe",
    "wof:placetype":"venue"
},
  "geometry": {"coordinates":[3.8119020462,50.8698577881],"type":"Point"}
}