{
  "type": "Feature",
  "properties": {
    "addr:full":"Steinbach 92a Weismes Li\u00e8ge 4950",
    "addr:housenumber":"92a",
    "addr:postcode":"4950",
    "addr:street":"Steinbach",
    "iso:country":"BE",
    "sg:address":"Steinbach 92a",
    "sg:city":"Weismes",
    "sg:classifiers":[
        {
            "category":"Retail",
            "subcategory":"Veterinary Services",
            "type":"Services"
        }
    ],
    "sg:phone":"+32 80 67 96 52",
    "sg:postcode":"4950",
    "sg:province":"Li\u00e8ge",
    "sg:tags":[
        "veterinarian"
    ],
    "wof:name":"Pinson L",
    "wof:placetype":"venue"
},
  "geometry": {"coordinates":[6.1199598312,50.4066085815],"type":"Point"}
}