{
  "type": "Feature",
  "properties": {
    "iso:country":"BE",
    "sg:address":"Chauss\u00c9e D'ecaussinnes 75a",
    "sg:city":"Braine-le-comte",
    "sg:orig_category":"Jardinage. Rev\u00eatements pour sols and murs. Constructions r\u00e9sidentielles sp\u00e9cifiques",
    "sg:phone":"+32 67 55 60 48",
    "sg:postcode":"7090",
    "sg:province":"Hainaut",
    "wof:name":"Armand Magotteaux",
    "wof:placetype":"venue"
},
  "geometry": {"coordinates":[4.1751198769,50.5696792603],"type":"Point"}
}