{
  "type": "Feature",
  "properties": {
    "addr:full":"Houtemsesteenweg 268 Vilvoorde Vlaams-Brabant 1800",
    "addr:housenumber":"268",
    "addr:postcode":"1800",
    "addr:street":"Houtemsesteenweg",
    "iso:country":"BE",
    "sg:address":"Houtemsesteenweg 268",
    "sg:city":"Vilvoorde",
    "sg:orig_category":"Bedrijfscatering Catering and organisatie van feesten",
    "sg:phone":"+32 2 252 04 53",
    "sg:postcode":"1800",
    "sg:province":"Vlaams-Brabant",
    "wof:name":"Traiteur Gerrit",
    "wof:placetype":"venue"
},
  "geometry": {"coordinates":[4.4556398392,50.9360809326],"type":"Point"}
}