{
  "type": "Feature",
  "properties": {
    "addr:full":"Champs 801bc Bertogne Luxembourg 6688",
    "addr:postcode":"6688",
    "addr:street":"Champs",
    "iso:country":"BE",
    "sg:address":"Champs 801bc",
    "sg:city":"Bertogne",
    "sg:orig_category":"Kapsalons",
    "sg:phone":"+32 61 21 45 56",
    "sg:postcode":"6688",
    "sg:province":"Luxembourg",
    "wof:name":"Anne Deryckere",
    "wof:placetype":"venue"
},
  "geometry": {"coordinates":[5.6687469482,50.0405235291],"type":"Point"}
}