{
  "type": "Feature",
  "properties": {
    "addr:full":"Auguste Lambiottestraat 100 Schaarbeek/schaerbeek Bruxelles-Capitale 1030",
    "addr:housenumber":"100",
    "addr:postcode":"1030",
    "addr:street":"Auguste Lambiottestraat",
    "iso:country":"BE",
    "sg:address":"Auguste Lambiottestraat 100",
    "sg:city":"Schaarbeek/schaerbeek",
    "sg:orig_category":"Kapsalons",
    "sg:phone":"+32 2 734 16 96",
    "sg:postcode":"1030",
    "sg:province":"Bruxelles-Capitale",
    "wof:name":"Onofrio Campisi",
    "wof:placetype":"venue"
},
  "geometry": {"coordinates":[4.3897051811,50.8547363281],"type":"Point"}
}