{
  "type": "Feature",
  "properties": {
    "iso:country":"BE",
    "sg:address":"Rue Du Palais 27",
    "sg:city":"Verviers",
    "sg:orig_category":"Boekhouders",
    "sg:phone":"+32 87 23 15 67",
    "sg:postcode":"4800",
    "sg:province":"Li\u00e8ge",
    "wof:name":"Chr. Lejeune",
    "wof:placetype":"venue"
},
  "geometry": {"coordinates":[5.8637299538,50.5902900696],"type":"Point"}
}