{
  "type": "Feature",
  "properties": {
    "addr:full":"Rue Fran\u00c7ois Cloes 62 Saint-nicolas Li\u00e8ge 4420",
    "addr:housenumber":"62",
    "addr:postcode":"4420",
    "addr:street":"Rue Franc\u0327Ois Cloes",
    "iso:country":"BE",
    "sg:address":"Rue Fran\u00c7ois Cloes 62",
    "sg:city":"Saint-nicolas",
    "sg:orig_category":"Journaux. Tabac",
    "sg:phone":"+32 4 246 34 57",
    "sg:postcode":"4420",
    "sg:province":"Li\u00e8ge",
    "wof:name":"Librairie Cloese",
    "wof:placetype":"venue"
},
  "geometry": {"coordinates":[5.5174818039,50.6373710632],"type":"Point"}
}