{
  "type": "Feature",
  "properties": {
    "iso:country":"BE",
    "sg:address":"Grote Markt 12",
    "sg:city":"Westerlo",
    "sg:orig_category":"Tabac",
    "sg:phone":"+32 14 54 99 34",
    "sg:postcode":"2260",
    "sg:province":"Antwerpen",
    "wof:name":"De Marktlinde",
    "wof:placetype":"venue"
},
  "geometry": {"coordinates":[4.916533947,51.0869369507],"type":"Point"}
}