{
  "type": "Feature",
  "properties": {
    "addr:full":"Rue Fernand Houget 12 Verviers Li\u00e8ge 4800",
    "addr:housenumber":"12",
    "addr:postcode":"4800",
    "addr:street":"Rue Fernand Houget",
    "iso:country":"BE",
    "sg:address":"Rue Fernand Houget 12",
    "sg:city":"Verviers",
    "sg:classifiers":[
        {
            "category":"Professional",
            "subcategory":"Accounting & Tax Preparation",
            "type":"Services"
        }
    ],
    "sg:phone":"+32 87 33 10 15",
    "sg:postcode":"4800",
    "sg:province":"Li\u00e8ge",
    "sg:tags":[
        "pattern",
        "maker"
    ],
    "wof:name":"Mecanibois Sprl",
    "wof:placetype":"venue"
},
  "geometry": {"coordinates":[5.8457551003,50.5890426636],"type":"Point"}
}