{
  "type": "Feature",
  "properties": {
    "addr:full":"Kloosterbergstraat 33 Diest Vlaams-Brabant 3290",
    "addr:housenumber":"33",
    "addr:postcode":"3290",
    "addr:street":"Kloosterbergstraat",
    "iso:country":"BE",
    "sg:address":"Kloosterbergstraat 33",
    "sg:city":"Diest",
    "sg:classifiers":[
        {
            "category":"Insurance",
            "subcategory":"Insurance Agent",
            "type":"Services"
        }
    ],
    "sg:phone":"+32 13 33 40 73",
    "sg:postcode":"3290",
    "sg:province":"Vlaams-Brabant",
    "sg:tags":[
        "verzekeringsmakelaars",
        "expert"
    ],
    "wof:name":"Marcel En Staf Maes",
    "wof:placetype":"venue"
},
  "geometry": {"coordinates":[5.0584888458,50.974811554],"type":"Point"}
}