{
  "type": "Feature",
  "properties": {
    "iso:country":"BE",
    "sg:address":"Bredabaan 518",
    "sg:city":"Merksem",
    "sg:orig_category":"Ordinateurs and \u00e9quipement informatique",
    "sg:phone":"+32 3 645 64 66",
    "sg:postcode":"2170",
    "sg:province":"Antwerpen",
    "wof:name":"Atsys",
    "wof:placetype":"venue"
},
  "geometry": {"coordinates":[4.4468660355,51.245262146],"type":"Point"}
}