{
  "type": "Feature",
  "properties": {
    "addr:full":"Zeedijk Sint-idesbald 26 Koksijde West-Vlaanderen 8670",
    "addr:housenumber":"26",
    "addr:postcode":"8670",
    "addr:street":"Zeedijk Sint-Idesbald",
    "iso:country":"BE",
    "sg:address":"Zeedijk Sint-idesbald 26",
    "sg:city":"Koksijde",
    "sg:classifiers":[
        {
            "category":"Restaurant",
            "type":"Food & Drink"
        }
    ],
    "sg:phone":"+32 58 51 29 51",
    "sg:postcode":"8670",
    "sg:province":"West-Vlaanderen",
    "wof:name":"Tearoom Palermo",
    "wof:placetype":"venue"
},
  "geometry": {"coordinates":[2.6406180859,51.0854721069],"type":"Point"}
}