{
  "type": "Feature",
  "properties": {
    "addr:full":"Rue De La Barre 38 Chaumont-gistoux Brabant Wallon 1325",
    "addr:housenumber":"38",
    "addr:postcode":"1325",
    "addr:street":"Rue De La Barre",
    "iso:country":"BE",
    "sg:address":"Rue De La Barre 38",
    "sg:city":"Chaumont-gistoux",
    "sg:orig_category":"M\u00e9decins and sp\u00e9cialistes",
    "sg:phone":"+32 10 68 92 88",
    "sg:postcode":"1325",
    "sg:province":"Brabant Wallon",
    "wof:name":"Kerstin Heinzel",
    "wof:placetype":"venue"
},
  "geometry": {"coordinates":[4.7223548889,50.6729545593],"type":"Point"}
}