{
  "type": "Feature",
  "properties": {
    "addr:full":"Place De Station Namur Namur 5000",
    "addr:postcode":"5000",
    "addr:street":"Place De Station",
    "iso:country":"BE",
    "sg:address":"Place De Station",
    "sg:city":"Namur",
    "sg:classifiers":[
        {
            "category":"Restaurant",
            "type":"Food & Drink"
        }
    ],
    "sg:phone":"+32 81 22 17 63",
    "sg:postcode":"5000",
    "sg:province":"Namur",
    "wof:name":"La Coupole Gillain",
    "wof:placetype":"venue"
},
  "geometry": {"coordinates":[4.8636450768,50.4683494568],"type":"Point"}
}