{
  "type": "Feature",
  "properties": {
    "iso:country":"BE",
    "sg:address":"Persoonshoek 13",
    "sg:city":"Mechelen",
    "sg:classifiers":[
        {
            "category":"Cafe",
            "type":"Food & Drink"
        }
    ],
    "sg:phone":"+32 15 71 59 69",
    "sg:postcode":"2800",
    "sg:province":"Antwerpen",
    "sg:tags":[
        "snack-bars"
    ],
    "wof:name":"Hoekske ('t)",
    "wof:placetype":"venue"
},
  "geometry": {"coordinates":[4.475112915,51.0271568298],"type":"Point"}
}