{
  "type": "Feature",
  "properties": {
    "addr:full":"Merellaan 4 Puurs Antwerpen 2870",
    "addr:housenumber":"4",
    "addr:postcode":"2870",
    "addr:street":"Merellaan",
    "iso:country":"BE",
    "sg:address":"Merellaan 4",
    "sg:city":"Puurs",
    "sg:orig_category":"Fotografen and fotostudio's",
    "sg:phone":"+32 3 886 54 40",
    "sg:postcode":"2870",
    "sg:province":"Antwerpen",
    "wof:name":"De Bondt-de Jonghe",
    "wof:placetype":"venue"
},
  "geometry": {"coordinates":[4.3215069771,51.0425224304],"type":"Point"}
}