{
  "type": "Feature",
  "properties": {
    "addr:full":"Tiensesteenweg 356 Leuven (groot) Vlaams-Brabant 3000",
    "addr:housenumber":"356",
    "addr:postcode":"3000",
    "addr:street":"Tiensesteenweg;Groot Vlaams-Brabant",
    "iso:country":"BE",
    "sg:address":"Tiensesteenweg 356",
    "sg:city":"Leuven (groot)",
    "sg:orig_category":"Entretien and r\u00e9parations de voitures",
    "sg:phone":"+32 16 25 45 57",
    "sg:postcode":"3000",
    "sg:province":"Vlaams-Brabant",
    "wof:name":"Imo Car Wash",
    "wof:placetype":"venue"
},
  "geometry": {"coordinates":[4.7366142273,50.8683700562],"type":"Point"}
}