{
  "type": "Feature",
  "properties": {
    "iso:country":"BE",
    "sg:address":"Avenue De La Wallonie 66",
    "sg:city":"Leuze-en-hainaut",
    "sg:classifiers":[
        {
            "category":"Building & Trades",
            "subcategory":"Landscaping Services",
            "type":"Services"
        }
    ],
    "sg:phone":"+32 69 64 12 32",
    "sg:postcode":"7900",
    "sg:province":"Hainaut",
    "sg:tags":[
        "gardening",
        "garden",
        "maintenance"
    ],
    "wof:name":"Dujardin Ets",
    "wof:placetype":"venue"
},
  "geometry": {"coordinates":[3.62906003,50.5869903564],"type":"Point"}
}