{
  "type": "Feature",
  "properties": {
    "addr:full":"Rue Du Mont Chera 5 Seraing Li\u00e8ge 4100",
    "addr:housenumber":"5",
    "addr:postcode":"4100",
    "addr:street":"Rue Du Mont Chera",
    "iso:country":"BE",
    "sg:address":"Rue Du Mont Chera 5",
    "sg:city":"Seraing",
    "sg:orig_category":"Charpentes and couvertures. Plomberie, chauffage and installations sanitaires. Services de Nettoyage",
    "sg:phone":"+32 4 336 75 80",
    "sg:postcode":"4100",
    "sg:province":"Li\u00e8ge",
    "wof:name":"Mar\u00c9chal",
    "wof:placetype":"venue"
},
  "geometry": {"coordinates":[5.5022778511,50.5765304565],"type":"Point"}
}