{
  "type": "Feature",
  "properties": {
    "iso:country":"BE",
    "sg:address":"Rue Mar\u00e9chal Foch 33-35",
    "sg:city":"Dour",
    "sg:classifiers":[
        {
            "category":"Shopping",
            "subcategory":"Books",
            "type":"Retail Goods"
        }
    ],
    "sg:phone":"+32 65 65 21 32",
    "sg:postcode":"7370",
    "sg:province":"Hainaut",
    "sg:tags":[
        "bookseller"
    ],
    "wof:name":"Bortolini A",
    "wof:placetype":"venue"
},
  "geometry": {"coordinates":[3.7837290764,50.3996238708],"type":"Point"}
}