{
  "type": "Feature",
  "properties": {
    "iso:country":"BE",
    "sg:address":"Noordlaan 13",
    "sg:city":"Kuurne",
    "sg:classifiers":[
        {
            "category":"Professional",
            "subcategory":"Management & Consulting",
            "type":"Services"
        }
    ],
    "sg:phone":"+32 495 25 85 75",
    "sg:postcode":"8520",
    "sg:province":"West-Vlaanderen",
    "sg:tags":[
        "consultant",
        "agency",
        "advertising"
    ],
    "wof:name":"Florizoone & Partners Nv",
    "wof:placetype":"venue"
},
  "geometry": {"coordinates":[3.2577800751,50.8555335999],"type":"Point"}
}