{
  "type": "Feature",
  "properties": {
    "addr:full":"Rue Servais 25 Spa Li\u00e8ge 4900",
    "addr:housenumber":"25",
    "addr:postcode":"4900",
    "addr:street":"Rue Servais",
    "iso:country":"BE",
    "sg:address":"Rue Servais 25",
    "sg:city":"Spa",
    "sg:classifiers":[
        {
            "category":"Shopping",
            "subcategory":"Stationery & Office Supplies",
            "type":"Retail Goods"
        }
    ],
    "sg:phone":"+32 87 77 12 49",
    "sg:postcode":"4900",
    "sg:province":"Li\u00e8ge",
    "wof:name":"Pesesse J",
    "wof:placetype":"venue"
},
  "geometry": {"coordinates":[5.8643431664,50.4910888672],"type":"Point"}
}