{
  "type": "Feature",
  "properties": {
    "iso:country":"BE",
    "sg:address":"Gevaerts-zuid 18",
    "sg:city":"Beernem",
    "sg:orig_category":"Studios photographiques",
    "sg:phone":"+32 50 78 08 90",
    "sg:postcode":"8730",
    "sg:province":"West-Vlaanderen",
    "wof:name":"Silance P.",
    "wof:placetype":"venue"
},
  "geometry": {"coordinates":[3.3032150269,51.1413955688],"type":"Point"}
}