{
  "type": "Feature",
  "properties": {
    "addr:full":"Rue De Menuchamps 36 Paliseul Luxembourg 6856",
    "addr:housenumber":"36",
    "addr:postcode":"6856",
    "addr:street":"Rue De Menuchamps",
    "iso:country":"BE",
    "sg:address":"Rue De Menuchamps 36",
    "sg:city":"Paliseul",
    "sg:orig_category":"Installation de menuiserie en bois and plastique",
    "sg:phone":"+32 61 53 39 30",
    "sg:postcode":"6856",
    "sg:province":"Luxembourg",
    "wof:name":"Nemery F",
    "wof:placetype":"venue"
},
  "geometry": {"coordinates":[5.1621627808,49.8746833801],"type":"Point"}
}