{
  "type": "Feature",
  "properties": {
    "addr:full":"Rue Adolphe Sax 21 Dinant Namur 5500",
    "addr:housenumber":"21",
    "addr:postcode":"5500",
    "addr:street":"Rue Adolphe Sax",
    "iso:country":"BE",
    "sg:address":"Rue Adolphe Sax 21",
    "sg:city":"Dinant",
    "sg:orig_category":"Kapsalons",
    "sg:phone":"+32 82 22 29 13",
    "sg:postcode":"5500",
    "sg:province":"Namur",
    "wof:name":"Coiffure Robert",
    "wof:placetype":"venue"
},
  "geometry": {"coordinates":[4.9113559723,50.2617034912],"type":"Point"}
}