{
  "type": "Feature",
  "properties": {
    "addr:full":"Bosduiflaan 13 Brecht Antwerpen 2960",
    "addr:housenumber":"13",
    "addr:postcode":"2960",
    "addr:street":"Bosduiflaan",
    "iso:country":"BE",
    "sg:address":"Bosduiflaan 13",
    "sg:city":"Brecht",
    "sg:classifiers":[
        {
            "category":"Home & Garden",
            "subcategory":"Hardware",
            "type":"Retail Goods"
        }
    ],
    "sg:phone":"+32 477 45 98 14",
    "sg:postcode":"2960",
    "sg:province":"Antwerpen",
    "sg:tags":[
        "gate",
        "opener",
        "door",
        "automatic"
    ],
    "wof:name":"Pieters Luc Automatisaties",
    "wof:placetype":"venue"
},
  "geometry": {"coordinates":[4.5616378784,51.3075866699],"type":"Point"}
}