{
  "type": "Feature",
  "properties": {
    "addr:full":"Rue D\u00b4italie 2a Charleroi Hainaut 6000",
    "addr:housenumber":"2a",
    "addr:postcode":"6000",
    "addr:street":"Rue D\u00b4Italie;Hainaut",
    "iso:country":"BE",
    "sg:address":"Rue D\u00b4italie 2a",
    "sg:city":"Charleroi",
    "sg:orig_category":"Elektrische installaties voor woningen Telecommunicatieapparaten",
    "sg:phone":"+32 71 70 07 41",
    "sg:postcode":"6000",
    "sg:province":"Hainaut",
    "wof:name":"Fe. Technicom",
    "wof:placetype":"venue"
},
  "geometry": {"coordinates":[4.4497299194,50.4166603088],"type":"Point"}
}