{
  "type": "Feature",
  "properties": {
    "iso:country":"BE",
    "sg:address":"Place Sainte-anne 12",
    "sg:city":"Comines-warneton (comines)",
    "sg:classifiers":[
        {
            "category":"Bars & Pubs",
            "type":"Food & Drink"
        }
    ],
    "sg:phone":"+32 56 55 61 70",
    "sg:postcode":"7780",
    "sg:province":"Hainaut",
    "wof:name":"Buvette Du T\u00e9l\u00e9phone",
    "wof:placetype":"venue"
},
  "geometry": {"coordinates":[2.998511076,50.7684135437],"type":"Point"}
}