{
  "type": "Feature",
  "properties": {
    "addr:full":"44 Pastoor Boelstraat 9140 Temse 44",
    "addr:housenumber":"44",
    "addr:postcode":"9140",
    "addr:street":"Pastoor Boelstraat",
    "iso:country":"BE",
    "sg:address":"44",
    "sg:city":"Pastoor Boelstraat 9140 Temse",
    "sg:classifiers":[
        {
            "category":"Bakery",
            "type":"Food & Drink"
        }
    ],
    "sg:phone":"+32 3 771 03 45",
    "sg:postcode":"44",
    "sg:tags":[
        "cake",
        "product",
        "related",
        "bread"
    ],
    "wof:name":"Bakkerij Wauters Rony",
    "wof:placetype":"venue"
},
  "geometry": {"coordinates":[4.212184906,51.1273765564],"type":"Point"}
}