{
  "type": "Feature",
  "properties": {
    "addr:full":"Rue En Rh\u00e9e 39 Dinant Namur 5500",
    "addr:housenumber":"39",
    "addr:postcode":"5500",
    "addr:street":"Rue En Rhe\u0301E",
    "iso:country":"BE",
    "sg:address":"Rue En Rh\u00e9e 39",
    "sg:city":"Dinant",
    "sg:classifiers":[
        {
            "category":"Social Services",
            "type":"Services"
        }
    ],
    "sg:phone":"+32 82 22 43 63",
    "sg:postcode":"5500",
    "sg:province":"Namur",
    "wof:name":"Ecole De Devoirs S.a.d. Asbl",
    "wof:placetype":"venue"
},
  "geometry": {"coordinates":[4.9138817787,50.2600326538],"type":"Point"}
}