{
  "type": "Feature",
  "properties": {
    "addr:full":"Rue Georges Et Jacques Martin 11 Bruxelles (woluwe-saint-pierre) Bruxelles-Capitale 1150",
    "addr:housenumber":"11",
    "addr:postcode":"1150",
    "addr:street":"Rue Georges Et Jacques Martin",
    "iso:country":"BE",
    "sg:address":"Rue Georges Et Jacques Martin 11",
    "sg:city":"Bruxelles (woluwe-saint-pierre)",
    "sg:classifiers":[
        {
            "category":"Health Services",
            "subcategory":"Health Practitioner",
            "type":"Services"
        }
    ],
    "sg:phone":"+32 475 64 93 47",
    "sg:postcode":"1150",
    "sg:province":"Bruxelles-Capitale",
    "sg:tags":[
        "osteopath"
    ],
    "wof:name":"Demuynck F",
    "wof:placetype":"venue"
},
  "geometry": {"coordinates":[4.4122400284,50.8374824524],"type":"Point"}
}