{
  "type": "Feature",
  "properties": {
    "addr:full":"Kloosterstraat 9 Bilzen Limburg 3740",
    "addr:housenumber":"9",
    "addr:postcode":"3740",
    "addr:street":"Kloosterstraat",
    "iso:country":"BE",
    "sg:address":"Kloosterstraat 9",
    "sg:city":"Bilzen",
    "sg:orig_category":"Enseignement maternel and primaire. Enseignement secondaire g\u00e9n\u00e9ral",
    "sg:phone":"+32 89 41 26 17",
    "sg:postcode":"3740",
    "sg:province":"Limburg",
    "wof:name":"Vrije Lagere School",
    "wof:placetype":"venue"
},
  "geometry": {"coordinates":[5.5187830925,50.8712539673],"type":"Point"}
}