{
  "type": "Feature",
  "properties": {
    "addr:full":"Bist 100 Ekeren Antwerpen 2180",
    "addr:housenumber":"100",
    "addr:postcode":"2180",
    "addr:street":"Bist",
    "iso:country":"BE",
    "sg:address":"Bist 100",
    "sg:city":"Ekeren",
    "sg:orig_category":"Installation \u00e9lectrique r\u00e9sidentielle",
    "sg:phone":"+32 3 664 23 35",
    "sg:postcode":"2180",
    "sg:province":"Antwerpen",
    "wof:name":"Uw Elektrieker",
    "wof:placetype":"venue"
},
  "geometry": {"coordinates":[4.442568779,51.2894630432],"type":"Point"}
}