{
  "type": "Feature",
  "properties": {
    "iso:country":"BE",
    "sg:address":"Place Henri Collignon 2",
    "sg:city":"Onhaye",
    "sg:classifiers":[
        {
            "category":"Bakery",
            "type":"Food & Drink"
        }
    ],
    "sg:phone":"+32 82 64 44 81",
    "sg:postcode":"5520",
    "sg:province":"Namur",
    "sg:tags":[
        "confectioner",
        "baker"
    ],
    "wof:name":"Hosselet",
    "wof:placetype":"venue"
},
  "geometry": {"coordinates":[4.8402600288,50.2425193787],"type":"Point"}
}