{
  "type": "Feature",
  "properties": {
    "iso:country":"BE",
    "sg:address":"Rue Aux-fr\u00canes 9",
    "sg:city":"Li\u00c8ge",
    "sg:orig_category":"Rev\u00eatements de sols and murs",
    "sg:phone":"+32 4 343 41 20",
    "sg:postcode":"4020",
    "sg:province":"Li\u00e8ge",
    "wof:name":"Catherine Pougin",
    "wof:placetype":"venue"
},
  "geometry": {"coordinates":[5.5919690132,50.6397399902],"type":"Point"}
}