{
  "type": "Feature",
  "properties": {
    "addr:full":"Rue Jakob Smits 55 Bruxelles (anderlecht) Bruxelles-Capitale 1070",
    "addr:housenumber":"55",
    "addr:postcode":"1070",
    "addr:street":"Rue Jakob Smits",
    "iso:country":"BE",
    "sg:address":"Rue Jakob Smits 55",
    "sg:city":"Bruxelles (anderlecht)",
    "sg:classifiers":[
        {
            "category":"Building & Trades",
            "subcategory":"Electrical",
            "type":"Services"
        }
    ],
    "sg:phone":"+32 2 523 10 19",
    "sg:postcode":"1070",
    "sg:province":"Bruxelles-Capitale",
    "sg:tags":[
        "electric",
        "-",
        "housewiring",
        "contractor"
    ],
    "wof:name":"Raes W",
    "wof:placetype":"venue"
},
  "geometry": {"coordinates":[4.3090600967,50.842590332],"type":"Point"}
}