{
  "type": "Feature",
  "properties": {
    "iso:country":"BE",
    "sg:address":"Aarselestraat 41",
    "sg:city":"Tielt (aarsele)",
    "sg:classifiers":[
        {
            "category":"Professional",
            "subcategory":"Detective & Security Services",
            "type":"Services"
        }
    ],
    "sg:phone":"+32 51 63 80 40",
    "sg:postcode":"8700",
    "sg:province":"West-Vlaanderen",
    "sg:tags":[
        "guard"
    ],
    "wof:name":"Vlaams Instituut Voor Bewaking Bvba",
    "wof:placetype":"venue"
},
  "geometry": {"coordinates":[3.421612978,50.9929962158],"type":"Point"}
}