{
  "type": "Feature",
  "properties": {
    "addr:full":"Rue Du March\u00e9 Aux Herbes 39 Bruxelles Bruxelles-Capitale 1000",
    "addr:housenumber":"39",
    "addr:postcode":"1000",
    "addr:street":"Rue Du Marche\u0301 Aux Herbes",
    "iso:country":"BE",
    "sg:address":"Rue Du March\u00e9 Aux Herbes 39",
    "sg:city":"Bruxelles",
    "sg:classifiers":[
        {
            "category":"Shopping",
            "subcategory":"Hobbies, Toys, & Games",
            "type":"Retail Goods"
        }
    ],
    "sg:phone":"+32 2 511 96 22",
    "sg:postcode":"1000",
    "sg:province":"Bruxelles-Capitale",
    "sg:tags":[
        "toy",
        "-"
    ],
    "wof:name":"The Grasshopper",
    "wof:placetype":"venue"
},
  "geometry": {"coordinates":[4.3525600433,50.8475036621],"type":"Point"}
}