{
  "type": "Feature",
  "properties": {
    "addr:full":"Dries 60 Sint-lievens-houtem Oost-Vlaanderen 9520",
    "addr:housenumber":"60",
    "addr:postcode":"9520",
    "addr:street":"Dries;Oost-Vlaanderen",
    "iso:country":"BE",
    "sg:address":"Dries 60",
    "sg:city":"Sint-lievens-houtem",
    "sg:classifiers":[
        {
            "category":"Fast Food",
            "type":"Food & Drink"
        }
    ],
    "sg:phone":"+32 9 360 72 55",
    "sg:postcode":"9520",
    "sg:province":"Oost-Vlaanderen",
    "sg:tags":[
        "\u00c0",
        "emporter",
        "restaurants"
    ],
    "wof:name":"Frituur Ricki",
    "wof:placetype":"venue"
},
  "geometry": {"coordinates":[3.8740899563,50.9211921692],"type":"Point"}
}