{
  "type": "Feature",
  "properties": {
    "addr:full":"3 Heihoefke Brecht Antwerpen 2960",
    "addr:housenumber":"3",
    "addr:postcode":"2960",
    "addr:street":"Heihoefke",
    "iso:country":"BE",
    "sg:address":"3 Heihoefke",
    "sg:city":"Brecht",
    "sg:classifiers":[
        {
            "category":"Professional",
            "type":"Services"
        }
    ],
    "sg:phone":"+32 3 313 85 58",
    "sg:postcode":"2960",
    "sg:province":"Antwerpen",
    "sg:tags":[
        "transport",
        "road"
    ],
    "wof:name":"Transport Joosen Nv",
    "wof:placetype":"venue"
},
  "geometry": {"coordinates":[4.67497015,51.3316345215],"type":"Point"}
}