{
  "type": "Feature",
  "properties": {
    "addr:full":"Neustrasse 5 Eupen/eupen Li\u00e8ge 4700",
    "addr:housenumber":"5",
    "addr:postcode":"4700",
    "addr:street":"Neustrasse",
    "iso:country":"BE",
    "sg:address":"Neustrasse 5",
    "sg:city":"Eupen/eupen",
    "sg:orig_category":"Fotogravure and zetwerk",
    "sg:phone":"+32 87 74 22 60",
    "sg:postcode":"4700",
    "sg:province":"Li\u00e8ge",
    "wof:name":"G. Emonds",
    "wof:placetype":"venue"
},
  "geometry": {"coordinates":[6.0327939987,50.6282119751],"type":"Point"}
}