{
  "type": "Feature",
  "properties": {
    "addr:full":"Rue De L'institut 13 Bl\u00e9gny (trembleur) Li\u00e8ge 4670",
    "addr:housenumber":"13",
    "addr:postcode":"4670",
    "addr:street":"Rue De L'Institut;Trembleur",
    "iso:country":"BE",
    "sg:address":"Rue De L'institut 13",
    "sg:city":"Bl\u00e9gny (trembleur)",
    "sg:classifiers":[
        {
            "category":"Wholesale",
            "subcategory":"Beer",
            "type":"Manufacturing & Wholesale Goods"
        }
    ],
    "sg:phone":"+32 4 387 48 18",
    "sg:postcode":"4670",
    "sg:province":"Li\u00e8ge",
    "sg:tags":[
        "ale",
        "-"
    ],
    "wof:name":"Monami Sprl",
    "wof:placetype":"venue"
},
  "geometry": {"coordinates":[5.7234492302,50.6729507446],"type":"Point"}
}