{
  "type": "Feature",
  "properties": {
    "addr:full":"Rue De Wellin 189 Daverdisse (haut-fays) Luxembourg 6929",
    "addr:housenumber":"189",
    "addr:postcode":"6929",
    "addr:street":"Rue De Wellin",
    "iso:country":"BE",
    "sg:address":"Rue De Wellin 189",
    "sg:city":"Daverdisse (haut-fays)",
    "sg:classifiers":[
        {
            "category":"Structure",
            "subcategory":"Office Building",
            "type":"Public Place"
        }
    ],
    "sg:phone":"+32 61 58 70 64",
    "sg:postcode":"6929",
    "sg:province":"Luxembourg",
    "sg:tags":[
        "roofing",
        "slate"
    ],
    "wof:name":"L\u00e9onard R",
    "wof:placetype":"venue"
},
  "geometry": {"coordinates":[5.0224719048,50.0040740967],"type":"Point"}
}