{
  "type": "Feature",
  "properties": {
    "iso:country":"BE",
    "sg:address":"Heiweg 29",
    "sg:city":"Maasmechelen",
    "sg:orig_category":"Plomberie, chauffage and installations sanitaires",
    "sg:phone":"+32 89 86 74 65",
    "sg:postcode":"3680",
    "sg:province":"Limburg",
    "wof:name":"Power Technology Centre",
    "wof:placetype":"venue"
},
  "geometry": {"coordinates":[5.791285038,51.0954208374],"type":"Point"}
}