{
  "type": "Feature",
  "properties": {
    "addr:full":"Gelindenstraat 109 Heers (mechelen-bovelingen) Limburg 3870",
    "addr:housenumber":"109",
    "addr:postcode":"3870",
    "addr:street":"Gelindenstraat",
    "iso:country":"BE",
    "sg:address":"Gelindenstraat 109",
    "sg:city":"Heers (mechelen-bovelingen)",
    "sg:classifiers":[
        {
            "category":"Personal",
            "subcategory":"Beauty Salon",
            "type":"Services"
        }
    ],
    "sg:phone":"+32 11 48 10 75",
    "sg:postcode":"3870",
    "sg:province":"Limburg",
    "sg:tags":[
        "lady",
        "-",
        "hairdressing"
    ],
    "wof:name":"Hamers",
    "wof:placetype":"venue"
},
  "geometry": {"coordinates":[5.2562842369,50.7411956787],"type":"Point"}
}