{
  "type": "Feature",
  "properties": {
    "addr:full":"Del 7b7 Meerhout Antwerpen 2450",
    "addr:postcode":"2450",
    "addr:street":"Del 7B7",
    "iso:country":"BE",
    "sg:address":"Del 7b7",
    "sg:city":"Meerhout",
    "sg:classifiers":[
        {
            "category":"Personal",
            "subcategory":"Beauty Salon",
            "type":"Services"
        }
    ],
    "sg:phone":"+32 14 30 81 63",
    "sg:postcode":"2450",
    "sg:province":"Antwerpen",
    "sg:tags":[
        "de",
        "coiffure"
    ],
    "wof:name":"Coiffure Nicole",
    "wof:placetype":"venue"
},
  "geometry": {"coordinates":[5.0662579536,51.1334953308],"type":"Point"}
}