{
  "type": "Feature",
  "properties": {
    "addr:full":"Nukerkeplein 2 Maarkedal Oost-Vlaanderen 9681",
    "addr:housenumber":"2",
    "addr:postcode":"9681",
    "addr:street":"Nukerkeplein",
    "iso:country":"BE",
    "sg:address":"Nukerkeplein 2",
    "sg:city":"Maarkedal",
    "sg:orig_category":"Banken and kredietinstellingen",
    "sg:phone":"+32 55 21 12 34",
    "sg:postcode":"9681",
    "sg:province":"Oost-Vlaanderen",
    "wof:name":"Kbc",
    "wof:placetype":"venue"
},
  "geometry": {"coordinates":[3.5952050686,50.7969856262],"type":"Point"}
}