{
  "type": "Feature",
  "properties": {
    "addr:full":"Chauss\u00c9e De Bruxelles 57 Soignies Hainaut 7061",
    "addr:housenumber":"57",
    "addr:postcode":"7061",
    "addr:street":"Chausse\u0301E De Bruxelles",
    "iso:country":"BE",
    "sg:address":"Chauss\u00c9e De Bruxelles 57",
    "sg:city":"Soignies",
    "sg:orig_category":"Verplichte sociale verzekeringen",
    "sg:phone":"+32 65 72 43 43",
    "sg:postcode":"7061",
    "sg:province":"Hainaut",
    "wof:name":"Mutualit\u00c9 Libre",
    "wof:placetype":"venue"
},
  "geometry": {"coordinates":[4.0133500099,50.5159416199],"type":"Point"}
}