{
  "type": "Feature",
  "properties": {
    "addr:full":"Rue De Champles 8 Wavre (bierges) Brabant Wallon 1301",
    "addr:housenumber":"8;1301",
    "addr:street":"Rue De Champles",
    "iso:country":"BE",
    "sg:address":"Rue De Champles 8",
    "sg:city":"Wavre (bierges)",
    "sg:classifiers":[
        {
            "category":"Social Services",
            "subcategory":"Retirement Home",
            "type":"Services"
        }
    ],
    "sg:phone":"+32 10 42 07 10",
    "sg:postcode":"1301",
    "sg:province":"Brabant Wallon",
    "sg:tags":[
        "residence"
    ],
    "wof:name":"Residence le Point Du Jour Sa",
    "wof:placetype":"venue"
},
  "geometry": {"coordinates":[4.5782752037,50.7183151245],"type":"Point"}
}