{
  "type": "Feature",
  "properties": {
    "addr:full":"N. De Brauwerestraat 22 Vilvoorde Vlaams-Brabant 1800",
    "addr:housenumber":"22",
    "addr:postcode":"1800",
    "addr:street":"N.;Brauwerestraat",
    "iso:country":"BE",
    "sg:address":"N. De Brauwerestraat 22",
    "sg:city":"Vilvoorde",
    "sg:orig_category":"Vakbonden",
    "sg:phone":"+32 2 252 09 82",
    "sg:postcode":"1800",
    "sg:province":"Vlaams-Brabant",
    "wof:name":"Aclvb",
    "wof:placetype":"venue"
},
  "geometry": {"coordinates":[4.4236721992,50.929069519],"type":"Point"}
}