{
  "type": "Feature",
  "properties": {
    "iso:country":"BE",
    "sg:address":"Koolmeesstraat 2",
    "sg:city":"Gent",
    "sg:orig_category":"Banques and organismes de cr\u00e9dit",
    "sg:phone":"+32 9 222 60 02",
    "sg:postcode":"9000",
    "sg:province":"Oost-Vlaanderen",
    "wof:name":"Kbc",
    "wof:placetype":"venue"
},
  "geometry": {"coordinates":[3.7255530357,51.0285873413],"type":"Point"}
}