{
  "type": "Feature",
  "properties": {
    "iso:country":"BE",
    "sg:address":"Rue De Vitrival 22",
    "sg:city":"Fosses-la-ville",
    "sg:orig_category":"Pain, p\u00e2tisseries and confiseries",
    "sg:phone":"+32 71 71 11 99",
    "sg:postcode":"5070",
    "sg:province":"Namur",
    "wof:name":"Hector Gosset",
    "wof:placetype":"venue"
},
  "geometry": {"coordinates":[4.694507122,50.3952903748],"type":"Point"}
}