{
  "type": "Feature",
  "properties": {
    "iso:country":"BE",
    "sg:address":"Mon Passage 10",
    "sg:city":"Lessines",
    "sg:orig_category":"Eleveurs de bovins",
    "sg:phone":"+32 68 33 31 38",
    "sg:postcode":"7863",
    "sg:province":"Hainaut",
    "wof:name":"Jean Couvreur",
    "wof:placetype":"venue"
},
  "geometry": {"coordinates":[3.8190460205,50.7445106506],"type":"Point"}
}