{
  "type": "Feature",
  "properties": {
    "addr:full":"4 Stuikberg Londerzeel Vlaams-Brabant 1840",
    "addr:housenumber":"4",
    "addr:postcode":"1840",
    "addr:street":"Stuikberg",
    "iso:country":"BE",
    "sg:address":"4 Stuikberg",
    "sg:city":"Londerzeel",
    "sg:classifiers":[
        {
            "category":"Home & Garden",
            "subcategory":"Furniture",
            "type":"Retail Goods"
        }
    ],
    "sg:phone":"+32 52 31 77 33",
    "sg:postcode":"1840",
    "sg:province":"Vlaams-Brabant",
    "sg:tags":[
        "household",
        "wood"
    ],
    "wof:name":"The Fresh Connection Nv",
    "wof:placetype":"venue"
},
  "geometry": {"coordinates":[4.3165078163,51.0280342102],"type":"Point"}
}