{
  "type": "Feature",
  "properties": {
    "addr:full":"Hanenberg 52 Scherpenheuvel-zichem (testelt) Vlaams-Brabant 3272",
    "addr:housenumber":"52",
    "addr:postcode":"3272",
    "addr:street":"Hanenberg",
    "iso:country":"BE",
    "sg:address":"Hanenberg 52",
    "sg:city":"Scherpenheuvel-zichem (testelt)",
    "sg:classifiers":[
        {
            "category":"Building & Trades",
            "subcategory":"Construction",
            "type":"Services"
        }
    ],
    "sg:phone":"+32 13 77 30 53",
    "sg:postcode":"3272",
    "sg:province":"Vlaams-Brabant",
    "sg:tags":[
        "stucco",
        "contractor"
    ],
    "wof:name":"House Trading Company Bvba",
    "wof:placetype":"venue"
},
  "geometry": {"coordinates":[4.9366259575,51.01222229],"type":"Point"}
}