{
  "type": "Feature",
  "properties": {
    "addr:full":"Nederstraat 33 Kruibeke Oost-Vlaanderen 9150",
    "addr:housenumber":"33",
    "addr:postcode":"9150",
    "addr:street":"Nederstraat",
    "iso:country":"BE",
    "sg:address":"Nederstraat 33",
    "sg:city":"Kruibeke",
    "sg:orig_category":"Artistes ind\u00e9pendants",
    "sg:phone":"+32 3 774 25 13",
    "sg:postcode":"9150",
    "sg:province":"Oost-Vlaanderen",
    "wof:name":"Ronald Verhelst",
    "wof:placetype":"venue"
},
  "geometry": {"coordinates":[4.2910609245,51.1256370544],"type":"Point"}
}