{
  "type": "Feature",
  "properties": {
    "addr:full":"Pontweg 5 Nazareth Oost-Vlaanderen 9810",
    "addr:housenumber":"5",
    "addr:postcode":"9810",
    "addr:street":"Pontweg",
    "iso:country":"BE",
    "sg:address":"Pontweg 5",
    "sg:city":"Nazareth",
    "sg:orig_category":"Varkenskwekers",
    "sg:phone":"+32 9 384 40 03",
    "sg:postcode":"9810",
    "sg:province":"Oost-Vlaanderen",
    "wof:name":"Christiaan De Keukelaere",
    "wof:placetype":"venue"
},
  "geometry": {"coordinates":[3.6426749229,50.9450073242],"type":"Point"}
}