{
  "type": "Feature",
  "properties": {
    "addr:full":"Berkenlaan 11 Veurne West-Vlaanderen 8630",
    "addr:housenumber":"11",
    "addr:postcode":"8630",
    "addr:street":"Berkenlaan",
    "iso:country":"BE",
    "sg:address":"Berkenlaan 11",
    "sg:city":"Veurne",
    "sg:classifiers":[
        {
            "category":"Wholesale",
            "subcategory":"Fruits & Vegetables",
            "type":"Manufacturing & Wholesale Goods"
        }
    ],
    "sg:phone":"+32 58 31 20 91",
    "sg:postcode":"8630",
    "sg:province":"West-Vlaanderen",
    "sg:tags":[
        "whol",
        "-"
    ],
    "wof:name":"Vlaemynck Nv",
    "wof:placetype":"venue"
},
  "geometry": {"coordinates":[2.672205925,51.075050354],"type":"Point"}
}