{
  "type": "Feature",
  "properties": {
    "addr:full":"Avenue De La Gare 7ba Nivelles Brabant Wallon 1401",
    "addr:housenumber":"1401",
    "addr:postcode":"7ba",
    "addr:street":"Avenue De La Gare",
    "iso:country":"BE",
    "sg:address":"Avenue De La Gare 7ba",
    "sg:city":"Nivelles",
    "sg:orig_category":"Instituts pour adultes moins valides",
    "sg:phone":"+32 67 21 51 04",
    "sg:postcode":"1401",
    "sg:province":"Brabant Wallon",
    "wof:name":"Centre De Jour Emeraude",
    "wof:placetype":"venue"
},
  "geometry": {"coordinates":[4.3506507874,50.6109695435],"type":"Point"}
}