{
  "type": "Feature",
  "properties": {
    "iso:country":"BE",
    "sg:address":"Bergemeersenstraat 103",
    "sg:city":"Aalst",
    "sg:classifiers":[
        {
            "category":"Shopping",
            "subcategory":"Florist",
            "type":"Retail Goods"
        }
    ],
    "sg:phone":"+32 53 70 95 25",
    "sg:postcode":"9300",
    "sg:province":"Oost-Vlaanderen",
    "sg:tags":[
        "-",
        "supply"
    ],
    "wof:name":"Buysse A",
    "wof:placetype":"venue"
},
  "geometry": {"coordinates":[4.0510182381,50.9389228821],"type":"Point"}
}