{
  "type": "Feature",
  "properties": {
    "addr:full":"Avenue De Saturne 4 Bruxelles (uccle) Bruxelles-Capitale 1180",
    "addr:housenumber":"4",
    "addr:postcode":"1180",
    "addr:street":"Avenue De Saturne",
    "iso:country":"BE",
    "sg:address":"Avenue De Saturne 4",
    "sg:city":"Bruxelles (uccle)",
    "sg:classifiers":[
        {
            "category":"Communications",
            "subcategory":"Film & Video Production",
            "type":"Services"
        }
    ],
    "sg:phone":"+32 2 375 05 51",
    "sg:postcode":"1180",
    "sg:province":"Bruxelles-Capitale",
    "sg:tags":[
        "realisation",
        "-"
    ],
    "wof:name":"Video Insurance-protection",
    "wof:placetype":"venue"
},
  "geometry": {"coordinates":[4.3599529266,50.8031425476],"type":"Point"}
}