{
  "type": "Feature",
  "properties": {
    "addr:full":"Av De La Briqueterie 22 Wavre Brabant Wallon 1300",
    "addr:housenumber":"22;1300",
    "addr:street":"Av De La Briqueterie",
    "iso:country":"BE",
    "sg:address":"Av De La Briqueterie 22",
    "sg:city":"Wavre",
    "sg:classifiers":[
        {
            "category":"Communications",
            "type":"Services"
        }
    ],
    "sg:phone":"+32 10 86 77 56",
    "sg:postcode":"1300",
    "sg:province":"Brabant Wallon",
    "sg:tags":[
        "translator"
    ],
    "wof:name":"Lexilian",
    "wof:placetype":"venue"
},
  "geometry": {"coordinates":[4.6293997765,50.7178115845],"type":"Point"}
}