{
  "type": "Feature",
  "properties": {
    "iso:country":"BE",
    "sg:address":"Heide 66",
    "sg:city":"Kelmis",
    "sg:classifiers":[
        {
            "category":"Arena",
            "subcategory":"Sports Club",
            "type":"Entertainment"
        }
    ],
    "sg:phone":"+32 87 63 02 45",
    "sg:postcode":"4720",
    "sg:province":"Li\u00e8ge",
    "sg:tags":[
        "de"
    ],
    "wof:name":"Country Tennis La Calamine",
    "wof:placetype":"venue"
},
  "geometry": {"coordinates":[6.003759861,50.7137413025],"type":"Point"}
}