{
  "type": "Feature",
  "properties": {
    "addr:full":"Nijverheidsstraat 12 Zottegem Oost-Vlaanderen 9620",
    "addr:housenumber":"12",
    "addr:postcode":"9620",
    "addr:street":"Nijverheidsstraat",
    "iso:country":"BE",
    "sg:address":"Nijverheidsstraat 12",
    "sg:city":"Zottegem",
    "sg:classifiers":[
        {
            "category":"Government",
            "subcategory":"Police Station",
            "type":"Public Place"
        }
    ],
    "sg:phone":"+32 9 364 64 32",
    "sg:postcode":"9620",
    "sg:province":"Oost-Vlaanderen",
    "sg:tags":[
        "gendarmerie"
    ],
    "wof:name":"Federale Politie",
    "wof:placetype":"venue"
},
  "geometry": {"coordinates":[3.8120610714,50.8715515137],"type":"Point"}
}