{
  "type": "Feature",
  "properties": {
    "iso:country":"BE",
    "sg:address":"Rue Tilia 7",
    "sg:city":"Beaumont",
    "sg:orig_category":"Entretien and r\u00e9parations de voitures",
    "sg:phone":"+32 71 53 34 63",
    "sg:postcode":"6511",
    "sg:province":"Hainaut",
    "wof:name":"Carrosserie Dereydt",
    "wof:placetype":"venue"
},
  "geometry": {"coordinates":[4.3023619652,50.2723121643],"type":"Point"}
}