{
  "type": "Feature",
  "properties": {
    "addr:full":"Rue Kessels 12 Bruxelles (schaerbeek) Bruxelles-Capitale 1030",
    "addr:housenumber":"12",
    "addr:postcode":"1030",
    "addr:street":"Rue Kessels",
    "iso:country":"BE",
    "sg:address":"Rue Kessels 12",
    "sg:city":"Bruxelles (schaerbeek)",
    "sg:classifiers":[
        {
            "category":"Professional",
            "subcategory":"Printing & Photocopies",
            "type":"Services"
        }
    ],
    "sg:phone":"+32 2 216 56 99",
    "sg:postcode":"1030",
    "sg:province":"Bruxelles-Capitale",
    "sg:tags":[
        "silkscreen",
        "-"
    ],
    "wof:name":"Now Screen Printing Sa",
    "wof:placetype":"venue"
},
  "geometry": {"coordinates":[4.3779611588,50.8614044189],"type":"Point"}
}