{
  "type": "Feature",
  "properties": {
    "addr:full":"Redingenhof 3 Leuven Vlaams-Brabant 3000",
    "addr:housenumber":"3",
    "addr:postcode":"3000",
    "addr:street":"Redingenhof",
    "iso:country":"BE",
    "sg:address":"Redingenhof 3",
    "sg:city":"Leuven",
    "sg:classifiers":[
        {
            "category":"Insurance",
            "subcategory":"Insurance Agent",
            "type":"Services"
        }
    ],
    "sg:phone":"+32 16 22 57 42",
    "sg:postcode":"3000",
    "sg:province":"Vlaams-Brabant",
    "sg:tags":[
        "verzekeringsmakelaars",
        "expert"
    ],
    "wof:name":"Bureau Assurova",
    "wof:placetype":"venue"
},
  "geometry": {"coordinates":[4.6956539154,50.874622345],"type":"Point"}
}