{
  "type": "Feature",
  "properties": {
    "addr:full":"Rue Devant L'etang 4 Malmedy Li\u00e8ge 4960",
    "addr:housenumber":"4",
    "addr:postcode":"4960",
    "addr:street":"Rue Devant L'Etang",
    "iso:country":"BE",
    "sg:address":"Rue Devant L'etang 4",
    "sg:city":"Malmedy",
    "sg:orig_category":"Cin\u00e9mas",
    "sg:phone":"+32 80 33 91 84",
    "sg:postcode":"4960",
    "sg:province":"Li\u00e8ge",
    "wof:name":"Salle Du Globe",
    "wof:placetype":"venue"
},
  "geometry": {"coordinates":[6.0264530182,50.4272842407],"type":"Point"}
}