{
  "type": "Feature",
  "properties": {
    "iso:country":"BE",
    "sg:address":"Lichtaartseweg 216-1",
    "sg:city":"Herentals",
    "sg:orig_category":"Non-Classified Establishments",
    "sg:phone":"+32 14 23 32 96",
    "sg:postcode":"2200",
    "sg:province":"Antwerpen",
    "wof:name":"A Sport-meeus A",
    "wof:placetype":"venue"
},
  "geometry": {"coordinates":[4.8580541611,51.1957931519],"type":"Point"}
}