{
  "type": "Feature",
  "properties": {
    "addr:full":"Avenue De Jemappes 173 Mons Hainaut 7000",
    "addr:housenumber":"173",
    "addr:postcode":"7000",
    "addr:street":"Avenue De Jemappes;Hainaut",
    "iso:country":"BE",
    "sg:address":"Avenue De Jemappes 173",
    "sg:city":"Mons",
    "sg:orig_category":"Charpentes and couvertures. Construction de maisons",
    "sg:phone":"+32 65 84 53 61",
    "sg:postcode":"7000",
    "sg:province":"Hainaut",
    "wof:name":"Villas & Demeures Constr.",
    "wof:placetype":"venue"
},
  "geometry": {"coordinates":[3.9309699535,50.4526100159],"type":"Point"}
}