{
  "type": "Feature",
  "properties": {
    "iso:country":"BE",
    "sg:address":"Kemphoekstraat 14",
    "sg:city":"Kruibeke",
    "sg:orig_category":"Herstellingen and onderhoud van auto's",
    "sg:phone":"+32 3 774 32 26",
    "sg:postcode":"9150",
    "sg:province":"Oost-Vlaanderen",
    "wof:name":"Garage Demaeyer",
    "wof:placetype":"venue"
},
  "geometry": {"coordinates":[4.3012828827,51.153678894],"type":"Point"}
}