{
  "type": "Feature",
  "properties": {
    "addr:full":"Vliegtuiglaan 5 Gent Oost-Vlaanderen 9000",
    "addr:housenumber":"5",
    "addr:postcode":"9000",
    "addr:street":"Vliegtuiglaan;Oost-Vlaanderen",
    "iso:country":"BE",
    "sg:address":"Vliegtuiglaan 5",
    "sg:city":"Gent",
    "sg:classifiers":[
        {
            "category":"Manufacturing",
            "subcategory":"Metals",
            "type":"Manufacturing & Wholesale Goods"
        }
    ],
    "sg:phone":"+32 9 258 19 95",
    "sg:postcode":"9000",
    "sg:province":"Oost-Vlaanderen",
    "sg:tags":[
        "work",
        "sheet"
    ],
    "wof:name":"Hacaro",
    "wof:placetype":"venue"
},
  "geometry": {"coordinates":[3.7430019379,51.0743789673],"type":"Point"}
}