{
  "type": "Feature",
  "properties": {
    "addr:full":"Ninoofsesteenweg 18 Haaltert (denderhoutem) Oost-Vlaanderen 9450",
    "addr:housenumber":"18",
    "addr:postcode":"9450",
    "addr:street":"Ninoofsesteenweg",
    "iso:country":"BE",
    "sg:address":"Ninoofsesteenweg 18",
    "sg:city":"Haaltert (denderhoutem)",
    "sg:classifiers":[
        {
            "category":"Health Services",
            "subcategory":"Dentist",
            "type":"Services"
        }
    ],
    "sg:phone":"+32 54 32 31 98",
    "sg:postcode":"9450",
    "sg:province":"Oost-Vlaanderen",
    "wof:name":"Van Molhem Sabine",
    "wof:placetype":"venue"
},
  "geometry": {"coordinates":[4.0180358887,50.8675422668],"type":"Point"}
}