{
  "type": "Feature",
  "properties": {
    "addr:full":"Bukkersstraat 38 Ieper West-Vlaanderen 8900",
    "addr:housenumber":"38",
    "addr:postcode":"8900",
    "addr:street":"Bukkersstraat",
    "iso:country":"BE",
    "sg:address":"Bukkersstraat 38",
    "sg:city":"Ieper",
    "sg:orig_category":"Non-Classified Establishments",
    "sg:phone":"+32 57 21 60 48",
    "sg:postcode":"8900",
    "sg:province":"West-Vlaanderen",
    "wof:name":"Vrij C.l.b.-ieper",
    "wof:placetype":"venue"
},
  "geometry": {"coordinates":[2.8912820816,50.8456687927],"type":"Point"}
}