{
  "type": "Feature",
  "properties": {
    "iso:country":"BE",
    "sg:address":"Rue Sainte-brigitte 90",
    "sg:city":"Beloeil",
    "sg:classifiers":[
        {
            "category":"Real Estate",
            "subcategory":"Developer",
            "type":"Services"
        }
    ],
    "sg:phone":"+32 69 78 05 03",
    "sg:postcode":"7971",
    "sg:province":"Hainaut",
    "sg:tags":[
        "plomberie",
        "chauffage",
        "mat\u00e9riel",
        "gr",
        "pour"
    ],
    "wof:name":"J.p.x.",
    "wof:placetype":"venue"
},
  "geometry": {"coordinates":[3.6194911003,50.5373954773],"type":"Point"}
}