{
  "type": "Feature",
  "properties": {
    "addr:full":"Groenstraat 10 Houthalen-helchteren (houthalen) Limburg 3530",
    "addr:housenumber":"10",
    "addr:postcode":"3530",
    "addr:street":"Groenstraat",
    "iso:country":"BE",
    "sg:address":"Groenstraat 10",
    "sg:city":"Houthalen-helchteren (houthalen)",
    "sg:classifiers":[
        {
            "category":"Health Services",
            "subcategory":"Health Practitioner",
            "type":"Services"
        }
    ],
    "sg:phone":"+32 11 60 50 90",
    "sg:postcode":"3530",
    "sg:province":"Limburg",
    "sg:tags":[
        "physiotherapist"
    ],
    "wof:name":"Claes Jean-marie",
    "wof:placetype":"venue"
},
  "geometry": {"coordinates":[5.3768358231,51.0247840881],"type":"Point"}
}