{
  "type": "Feature",
  "properties": {
    "addr:full":"Snikbergstraat 112 Dilbeek (itterbeek) Vlaams-Brabant 1701",
    "addr:housenumber":"112",
    "addr:postcode":"1701",
    "addr:street":"Snikbergstraat",
    "iso:country":"BE",
    "sg:address":"Snikbergstraat 112",
    "sg:city":"Dilbeek (itterbeek)",
    "sg:classifiers":[
        {
            "category":"Professional",
            "subcategory":"Management & Consulting",
            "type":"Services"
        }
    ],
    "sg:phone":"+32 2 567 20 87",
    "sg:postcode":"1701",
    "sg:province":"Vlaams-Brabant",
    "sg:tags":[
        "consultant"
    ],
    "wof:name":"Sb Marketing",
    "wof:placetype":"venue"
},
  "geometry": {"coordinates":[4.2289981842,50.8435707092],"type":"Point"}
}