{
  "type": "Feature",
  "properties": {
    "iso:country":"BE",
    "sg:address":"Place Du Ch\u00e2telain 24",
    "sg:city":"Bruxelles (ixelles)",
    "sg:classifiers":[
        {
            "category":"Professional",
            "subcategory":"Detective & Security Services",
            "type":"Services"
        }
    ],
    "sg:phone":"+32 2 534 58 40",
    "sg:postcode":"1050",
    "sg:province":"Bruxelles-Capitale",
    "sg:tags":[
        "agency"
    ],
    "wof:name":"Douglas & Delhez Detectives",
    "wof:placetype":"venue"
},
  "geometry": {"coordinates":[4.3597950935,50.8245010376],"type":"Point"}
}