{
  "type": "Feature",
  "properties": {
    "iso:country":"BE",
    "sg:address":"Avenue De G\u00c9radon 8",
    "sg:city":"Esneux",
    "sg:orig_category":"HERSTELLING ELEKTRISCHE HUISHOUDAPPARATEN",
    "sg:phone":"+32 4 388 37 74",
    "sg:postcode":"4130",
    "sg:province":"Li\u00e8ge",
    "wof:name":"Mondovision",
    "wof:placetype":"venue"
},
  "geometry": {"coordinates":[5.5852661133,50.5486984253],"type":"Point"}
}