{
  "type": "Feature",
  "properties": {
    "addr:full":"Akendoren 38 Nijlen (bevel) Antwerpen 2560",
    "addr:housenumber":"38",
    "addr:postcode":"2560",
    "addr:street":"Akendoren",
    "iso:country":"BE",
    "sg:address":"Akendoren 38",
    "sg:city":"Nijlen (bevel)",
    "sg:classifiers":[
        {
            "category":"Professional",
            "subcategory":"Accounting & Tax Preparation",
            "type":"Services"
        }
    ],
    "sg:phone":"+32 3 411 15 20",
    "sg:postcode":"2560",
    "sg:province":"Antwerpen",
    "sg:tags":[
        "accountant"
    ],
    "wof:name":"Horemans Johan Accountantskantoor Gcv",
    "wof:placetype":"venue"
},
  "geometry": {"coordinates":[4.6795721054,51.1390571594],"type":"Point"}
}