{
  "type": "Feature",
  "properties": {
    "addr:full":"Route De Spa 12 Ciney (grand) Namur 5590",
    "addr:housenumber":"12",
    "addr:postcode":"5590",
    "addr:street":"Route De Spa",
    "iso:country":"BE",
    "sg:address":"Route De Spa 12",
    "sg:city":"Ciney (grand)",
    "sg:orig_category":"Entretien and r\u00e9parations de voitures",
    "sg:phone":"+32 83 21 39 00",
    "sg:postcode":"5590",
    "sg:province":"Namur",
    "wof:name":"Carrosserie Lecomte",
    "wof:placetype":"venue"
},
  "geometry": {"coordinates":[5.1437492371,50.2727661133],"type":"Point"}
}