{
  "type": "Feature",
  "properties": {
    "iso:country":"BE",
    "sg:address":"Mechelse Steenweg 219",
    "sg:city":"Antwerpen",
    "sg:classifiers":[
        {
            "category":"Banks & Credit Unions",
            "subcategory":"Investment Brokerage",
            "type":"Services"
        }
    ],
    "sg:phone":"+32 3 288 00 16",
    "sg:postcode":"2018",
    "sg:province":"Antwerpen",
    "sg:tags":[
        "auditor"
    ],
    "wof:name":"Delahaye E",
    "wof:placetype":"venue"
},
  "geometry": {"coordinates":[4.4124908447,51.2026062012],"type":"Point"}
}