{
  "type": "Feature",
  "properties": {
    "addr:full":"Martelaarslaan 184 Gent Oost-Vlaanderen 9000",
    "addr:housenumber":"184",
    "addr:postcode":"9000",
    "addr:street":"Martelaarslaan;Oost-Vlaanderen",
    "iso:country":"BE",
    "sg:address":"Martelaarslaan 184",
    "sg:city":"Gent",
    "sg:classifiers":[
        {
            "category":"Real Estate",
            "subcategory":"Architect",
            "type":"Services"
        }
    ],
    "sg:phone":"+32 9 224 15 23",
    "sg:postcode":"9000",
    "sg:province":"Oost-Vlaanderen",
    "wof:name":"Blondeel N",
    "wof:placetype":"venue"
},
  "geometry": {"coordinates":[3.7124409676,51.0466766357],"type":"Point"}
}