{
  "type": "Feature",
  "properties": {
    "iso:country":"BE",
    "sg:address":"Chemin De Gomer\u00e9e 200",
    "sg:city":"Ham-sur-heure-nalinnes (ham-sur-heure)",
    "sg:classifiers":[
        {
            "category":"Government",
            "subcategory":"Department Of Motor Vehicles",
            "type":"Public Place"
        }
    ],
    "sg:phone":"+32 71 21 39 93",
    "sg:postcode":"6120",
    "sg:province":"Hainaut",
    "sg:tags":[
        "planing",
        "wood",
        "sawing"
    ],
    "wof:name":"Staquet A & F Sprl",
    "wof:placetype":"venue"
},
  "geometry": {"coordinates":[4.3992981911,50.3145904541],"type":"Point"}
}