{
  "type": "Feature",
  "properties": {
    "iso:country":"BE",
    "sg:address":"N\u00c9blon-le-pierreux 34",
    "sg:city":"Ouffet",
    "sg:orig_category":"Rundveehouders",
    "sg:phone":"+32 86 38 81 40",
    "sg:postcode":"4590",
    "sg:province":"Li\u00e8ge",
    "wof:name":"Nicole Englebert",
    "wof:placetype":"venue"
},
  "geometry": {"coordinates":[5.4990148544,50.4230995178],"type":"Point"}
}