{
  "type": "Feature",
  "properties": {
    "addr:full":"Hoogstraat 6 Aalst Oost-Vlaanderen 9300",
    "addr:housenumber":"6",
    "addr:postcode":"9300",
    "addr:street":"Hoogstraat",
    "iso:country":"BE",
    "sg:address":"Hoogstraat 6",
    "sg:city":"Aalst",
    "sg:classifiers":[
        {
            "category":"Banks & Credit Unions",
            "subcategory":"Investment Brokerage",
            "type":"Services"
        }
    ],
    "sg:phone":"+32 53 60 86 09",
    "sg:postcode":"9300",
    "sg:province":"Oost-Vlaanderen",
    "sg:tags":[
        "jean",
        "casual",
        "wear"
    ],
    "wof:name":"Classic Jeans",
    "wof:placetype":"venue"
},
  "geometry": {"coordinates":[4.0619997978,50.9491424561],"type":"Point"}
}