{
  "type": "Feature",
  "properties": {
    "addr:full":"Avenue Paul Dejaer 22b1 Sint-gillis/saint-gilles Bruxelles-Capitale 1060",
    "addr:housenumber":"22b1",
    "addr:postcode":"1060",
    "addr:street":"Avenue Paul Dejaer",
    "iso:country":"BE",
    "sg:address":"Avenue Paul Dejaer 22b1",
    "sg:city":"Sint-gillis/saint-gilles",
    "sg:orig_category":"Salons de coiffure. Centres de relaxation and bien-\u00eatre. Instituts de beaut\u00e9",
    "sg:phone":"+32 2 534 64 22",
    "sg:postcode":"1060",
    "sg:province":"Bruxelles-Capitale",
    "wof:name":"Santi's",
    "wof:placetype":"venue"
},
  "geometry": {"coordinates":[4.3452181816,50.8258476257],"type":"Point"}
}