{
  "type": "Feature",
  "properties": {
    "iso:country":"BE",
    "sg:address":"Oude Vest 114",
    "sg:city":"Dendermonde",
    "sg:classifiers":[
        {
            "category":"Personal",
            "subcategory":"Beauty Salon",
            "type":"Services"
        }
    ],
    "sg:phone":"+32 52 21 19 09",
    "sg:postcode":"9200",
    "sg:province":"Oost-Vlaanderen",
    "sg:tags":[
        "lady",
        "-",
        "hairdressing"
    ],
    "wof:name":"Elegance",
    "wof:placetype":"venue"
},
  "geometry": {"coordinates":[4.1033029556,51.0300331116],"type":"Point"}
}