{
  "type": "Feature",
  "properties": {
    "addr:full":"Lescours 51 Herve (bolland) Li\u00e8ge 4653",
    "addr:housenumber":"51",
    "addr:postcode":"4653",
    "addr:street":"Lescours;Bolland",
    "iso:country":"BE",
    "sg:address":"Lescours 51",
    "sg:city":"Herve (bolland)",
    "sg:classifiers":[
        {
            "category":"Professional",
            "subcategory":"Management & Consulting",
            "type":"Services"
        }
    ],
    "sg:phone":"+32 87 67 85 75",
    "sg:postcode":"4653",
    "sg:province":"Li\u00e8ge",
    "sg:tags":[
        "consultant"
    ],
    "wof:name":"Sogepom Sprl",
    "wof:placetype":"venue"
},
  "geometry": {"coordinates":[5.7643427849,50.6561546326],"type":"Point"}
}