{
  "type": "Feature",
  "properties": {
    "addr:full":"Boulevard Joseph Tirou 217 Charleroi Hainaut 6000",
    "addr:housenumber":"217",
    "addr:postcode":"6000",
    "addr:street":"Boulevard Joseph Tirou;Hainaut",
    "iso:country":"BE",
    "sg:address":"Boulevard Joseph Tirou 217",
    "sg:city":"Charleroi",
    "sg:orig_category":"IJzerwaren, bouw- and verfmaterialen Textiel Verlichting and huishoudartikelen Vloer- and muurbekled",
    "sg:phone":"+32 71 31 39 35",
    "sg:postcode":"6000",
    "sg:province":"Hainaut",
    "wof:name":"Gai D\u00c9cor",
    "wof:placetype":"venue"
},
  "geometry": {"coordinates":[4.4468941689,50.4064178467],"type":"Point"}
}