{
  "type": "Feature",
  "properties": {
    "addr:full":"Rijschoolstraat 67 Sint-truiden Limburg 3800",
    "addr:housenumber":"67",
    "addr:postcode":"3800",
    "addr:street":"Rijschoolstraat",
    "iso:country":"BE",
    "sg:address":"Rijschoolstraat 67",
    "sg:city":"Sint-truiden",
    "sg:orig_category":"Services fun\u00e9raires",
    "sg:phone":"+32 11 68 34 85",
    "sg:postcode":"3800",
    "sg:province":"Limburg",
    "wof:name":"Eraerts-stas",
    "wof:placetype":"venue"
},
  "geometry": {"coordinates":[5.1800317764,50.8163223267],"type":"Point"}
}