{
  "type": "Feature",
  "properties": {
    "iso:country":"BE",
    "sg:address":"Boeschepestraat 51",
    "sg:city":"Poperinge",
    "sg:classifiers":[
        {
            "category":"Personal",
            "subcategory":"Beauty Salon",
            "type":"Services"
        }
    ],
    "sg:phone":"+32 57 33 95 53",
    "sg:postcode":"8970",
    "sg:province":"West-Vlaanderen",
    "sg:tags":[
        "lady",
        "-",
        "hairdressing"
    ],
    "wof:name":"Sylvie",
    "wof:placetype":"venue"
},
  "geometry": {"coordinates":[2.722110033,50.8512268066],"type":"Point"}
}