{
  "type": "Feature",
  "properties": {
    "addr:full":"Grote Markt 2 Kortrijk West-Vlaanderen 8500",
    "addr:housenumber":"2",
    "addr:postcode":"8500",
    "addr:street":"Grote Markt",
    "iso:country":"BE",
    "sg:address":"Grote Markt 2",
    "sg:city":"Kortrijk",
    "sg:classifiers":[
        {
            "category":"Restaurant",
            "type":"Food & Drink"
        }
    ],
    "sg:phone":"+32 56 22 22 60",
    "sg:postcode":"8500",
    "sg:province":"West-Vlaanderen",
    "wof:name":"Brasserie C\u00c9sar",
    "wof:placetype":"venue"
},
  "geometry": {"coordinates":[3.2657520771,50.8280525208],"type":"Point"}
}