{
  "type": "Feature",
  "properties": {
    "addr:full":"Hazendries 16 Galmaarden Vlaams-Brabant 1570",
    "addr:housenumber":"16",
    "addr:postcode":"1570",
    "addr:street":"Hazendries",
    "iso:country":"BE",
    "sg:address":"Hazendries 16",
    "sg:city":"Galmaarden",
    "sg:orig_category":"Eleveurs de bovins",
    "sg:phone":"+32 54 58 80 60",
    "sg:postcode":"1570",
    "sg:province":"Vlaams-Brabant",
    "wof:name":"Maurice Bourguignon",
    "wof:placetype":"venue"
},
  "geometry": {"coordinates":[3.9717600346,50.7457427979],"type":"Point"}
}