{
  "type": "Feature",
  "properties": {
    "addr:full":"Battelsesteenweg 22 B4 Mechelen (groot) Antwerpen 2800",
    "addr:housenumber":"22 b4",
    "addr:postcode":"2800",
    "addr:street":"Battelsesteenweg;Groot Antwerpen",
    "iso:country":"BE",
    "sg:address":"Battelsesteenweg 22 B4",
    "sg:city":"Mechelen (groot)",
    "sg:orig_category":"Telecommunicatiesystemen",
    "sg:phone":"+32 15 29 18 48",
    "sg:postcode":"2800",
    "sg:province":"Antwerpen",
    "wof:name":"Jali",
    "wof:placetype":"venue"
},
  "geometry": {"coordinates":[4.4854397774,51.0289268494],"type":"Point"}
}