{
  "type": "Feature",
  "properties": {
    "iso:country":"BE",
    "sg:address":"Sint-denijslaan 251",
    "sg:city":"Gent",
    "sg:classifiers":[
        {
            "category":"Arena",
            "subcategory":"Sports Club",
            "type":"Entertainment"
        }
    ],
    "sg:phone":"+32 9 251 67 34",
    "sg:postcode":"9000",
    "sg:province":"Oost-Vlaanderen",
    "sg:tags":[
        "martial art",
        "accessory"
    ],
    "wof:name":"Aikido",
    "wof:placetype":"venue"
},
  "geometry": {"coordinates":[3.706111908,51.0356025696],"type":"Point"}
}