{
  "type": "Feature",
  "properties": {
    "addr:full":"Ontmijnersstraat 2-2 Staden West-Vlaanderen 8840",
    "addr:housenumber":"2-2",
    "addr:postcode":"8840",
    "addr:street":"Ontmijnersstraat",
    "iso:country":"BE",
    "sg:address":"Ontmijnersstraat 2-2",
    "sg:city":"Staden",
    "sg:classifiers":[
        {
            "category":"Food & Beverages",
            "subcategory":"Groceries & Convenience Stores",
            "type":"Retail Goods"
        }
    ],
    "sg:phone":"+32 51 70 49 06",
    "sg:postcode":"8840",
    "sg:province":"West-Vlaanderen",
    "sg:tags":[
        "grocer"
    ],
    "wof:name":"Voeding St-elooi",
    "wof:placetype":"venue"
},
  "geometry": {"coordinates":[2.9742920399,50.9497642517],"type":"Point"}
}