{
  "type": "Feature",
  "properties": {
    "iso:country":"BE",
    "sg:address":"Industrieweg 4",
    "sg:city":"Borgloon",
    "sg:classifiers":[
        {
            "category":"Autos & Motor Vehicles",
            "subcategory":"Automobile Sales",
            "type":"Retail Goods"
        }
    ],
    "sg:phone":"+32 12 74 21 58",
    "sg:postcode":"3840",
    "sg:province":"Limburg",
    "sg:tags":[
        "car",
        "used",
        "-"
    ],
    "wof:name":"Vanelderen Bvba",
    "wof:placetype":"venue"
},
  "geometry": {"coordinates":[5.3435330391,50.8120117188],"type":"Point"}
}