{
  "type": "Feature",
  "properties": {
    "iso:country":"BE",
    "sg:address":"Boulevard De L'h\u00d4pital 45",
    "sg:city":"Ath",
    "sg:orig_category":"Avocats and conseillers juridiques",
    "sg:phone":"+32 68 28 42 49",
    "sg:postcode":"7800",
    "sg:province":"Hainaut",
    "wof:name":"Ch. Jouret",
    "wof:placetype":"venue"
},
  "geometry": {"coordinates":[3.7847900391,50.6294555664],"type":"Point"}
}