{
  "type": "Feature",
  "properties": {
    "addr:full":"Rue Henri Belyn 47 Charleroi Hainaut 6041",
    "addr:housenumber":"47",
    "addr:postcode":"6041",
    "addr:street":"Rue Henri Belyn;Hainaut",
    "iso:country":"BE",
    "sg:address":"Rue Henri Belyn 47",
    "sg:city":"Charleroi",
    "sg:orig_category":"Woningbouw",
    "sg:phone":"+32 71 35 76 36",
    "sg:postcode":"6041",
    "sg:province":"Hainaut",
    "wof:name":"Mieczyslaw Agaciak",
    "wof:placetype":"venue"
},
  "geometry": {"coordinates":[4.4314317703,50.4685935974],"type":"Point"}
}