{
  "type": "Feature",
  "properties": {
    "iso:country":"BE",
    "sg:address":"Rue De La T\u00eate D'or 13",
    "sg:city":"Tournai",
    "sg:classifiers":[
        {
            "category":"Utilities",
            "subcategory":"Mobile Phone",
            "type":"Services"
        }
    ],
    "sg:phone":"+32 69 54 94 93",
    "sg:postcode":"7500",
    "sg:province":"Hainaut",
    "sg:tags":[
        "access",
        "gsm",
        "-",
        "apparatus"
    ],
    "wof:name":"Tronishop Import",
    "wof:placetype":"venue"
},
  "geometry": {"coordinates":[3.3932800293,50.5892715454],"type":"Point"}
}