{
  "type": "Feature",
  "properties": {
    "iso:country":"BE",
    "sg:address":"Toekomstlaan 113",
    "sg:city":"Schoten",
    "sg:classifiers":[
        {
            "category":"Manufacturing",
            "subcategory":"Rubber & Plastics",
            "type":"Manufacturing & Wholesale Goods"
        }
    ],
    "sg:phone":"+32 3 647 03 99",
    "sg:postcode":"2900",
    "sg:province":"Antwerpen",
    "wof:name":"Makubo Nv",
    "wof:placetype":"venue"
},
  "geometry": {"coordinates":[4.4564809799,51.2418518066],"type":"Point"}
}