{
  "type": "Feature",
  "properties": {
    "addr:full":"Theofiel Reynlaan 13 Mortsel Antwerpen 2640",
    "addr:housenumber":"13",
    "addr:postcode":"2640",
    "addr:street":"Theofiel Reynlaan",
    "iso:country":"BE",
    "sg:address":"Theofiel Reynlaan 13",
    "sg:city":"Mortsel",
    "sg:orig_category":"Enseignement maternel and primaire",
    "sg:phone":"+32 3 440 27 59",
    "sg:postcode":"2640",
    "sg:province":"Antwerpen",
    "wof:name":"B.s.g.o. Ten Dorpe",
    "wof:placetype":"venue"
},
  "geometry": {"coordinates":[4.4507641792,51.1759109497],"type":"Point"}
}