{
  "type": "Feature",
  "properties": {
    "iso:country":"BE",
    "sg:address":"Langestraat 15",
    "sg:city":"Blankenberge",
    "sg:orig_category":"Fleurs and plantes",
    "sg:phone":"+32 50 41 20 14",
    "sg:postcode":"8370",
    "sg:province":"West-Vlaanderen",
    "wof:name":"Floriste Sonja",
    "wof:placetype":"venue"
},
  "geometry": {"coordinates":[3.1275250912,51.3143196106],"type":"Point"}
}