{
  "type": "Feature",
  "properties": {
    "addr:full":"Sledderloweg 63 Genk Limburg 3600",
    "addr:housenumber":"63",
    "addr:postcode":"3600",
    "addr:street":"Sledderloweg",
    "iso:country":"BE",
    "sg:address":"Sledderloweg 63",
    "sg:city":"Genk",
    "sg:orig_category":"Entretien and r\u00e9parations de voitures",
    "sg:phone":"+32 89 30 68 87",
    "sg:postcode":"3600",
    "sg:province":"Limburg",
    "wof:name":"Car Wash Handrein",
    "wof:placetype":"venue"
},
  "geometry": {"coordinates":[5.5148539543,50.9483718872],"type":"Point"}
}