{
  "type": "Feature",
  "properties": {
    "addr:full":"Reggerstraat 56 Riemst (groot) Limburg 3770",
    "addr:housenumber":"56",
    "addr:postcode":"3770",
    "addr:street":"Reggerstraat;Groot Limburg",
    "iso:country":"BE",
    "sg:address":"Reggerstraat 56",
    "sg:city":"Riemst (groot)",
    "sg:orig_category":"Kapsalons",
    "sg:phone":"+32 12 45 54 55",
    "sg:postcode":"3770",
    "sg:province":"Limburg",
    "wof:name":"Trudie's Haarstudio",
    "wof:placetype":"venue"
},
  "geometry": {"coordinates":[5.5969901085,50.8109016418],"type":"Point"}
}