{
  "type": "Feature",
  "properties": {
    "addr:full":"Rue Baron Dubois De Chantraine 34a Mons (maisi\u00e8res) Hainaut 7020",
    "addr:housenumber":"34a",
    "addr:postcode":"7020",
    "addr:street":"Rue Baron Dubois De Chantraine",
    "iso:country":"BE",
    "sg:address":"Rue Baron Dubois De Chantraine 34a",
    "sg:city":"Mons (maisi\u00e8res)",
    "sg:classifiers":[
        {
            "category":"Health Services",
            "subcategory":"Health Practitioner",
            "type":"Services"
        }
    ],
    "sg:phone":"+32 495 52 25 48",
    "sg:postcode":"7020",
    "sg:province":"Hainaut",
    "sg:tags":[
        "therapist",
        "speech"
    ],
    "wof:name":"Bastin S",
    "wof:placetype":"venue"
},
  "geometry": {"coordinates":[3.9553449154,50.4761772156],"type":"Point"}
}