{
  "type": "Feature",
  "properties": {
    "addr:full":"Frans De L'arbrelaan 8 Antwerpen (merksem) Antwerpen 2170",
    "addr:housenumber":"8",
    "addr:postcode":"2170",
    "addr:street":"Frans De L'Arbrelaan",
    "iso:country":"BE",
    "sg:address":"Frans De L'arbrelaan 8",
    "sg:city":"Antwerpen (merksem)",
    "sg:classifiers":[
        {
            "category":"Personal",
            "subcategory":"Tattoo Parlor",
            "type":"Services"
        }
    ],
    "sg:phone":"+32 3 644 52 33",
    "sg:postcode":"2170",
    "sg:province":"Antwerpen",
    "sg:tags":[
        "tattooists"
    ],
    "wof:name":"Krijo's",
    "wof:placetype":"venue"
},
  "geometry": {"coordinates":[4.4394512177,51.2408752441],"type":"Point"}
}