{
  "type": "Feature",
  "properties": {
    "iso:country":"BE",
    "sg:address":"Rue Des Fontaines 6a",
    "sg:city":"Erquelinnes (hantes-wih\u00e9ries)",
    "sg:classifiers":[
        {
            "category":"Shopping",
            "subcategory":"Computers & Home Electronics",
            "type":"Retail Goods"
        }
    ],
    "sg:phone":"+32 71 55 33 57",
    "sg:postcode":"6560",
    "sg:province":"Hainaut",
    "sg:tags":[
        "sound",
        "equipment",
        "-",
        "system"
    ],
    "wof:name":"Delta Production",
    "wof:placetype":"venue"
},
  "geometry": {"coordinates":[4.1779260635,50.3073387146],"type":"Point"}
}