{
  "type": "Feature",
  "properties": {
    "iso:country":"BE",
    "sg:address":"Schoutskruisestraat 9",
    "sg:city":"Ruiselede",
    "sg:orig_category":"Varkenskwekers",
    "sg:phone":"+32 51 68 81 90",
    "sg:postcode":"8755",
    "sg:province":"West-Vlaanderen",
    "wof:name":"Gilbert Devolder",
    "wof:placetype":"venue"
},
  "geometry": {"coordinates":[3.3571949005,51.0453033447],"type":"Point"}
}