{
  "type": "Feature",
  "properties": {
    "addr:full":"Dorpsstraat 3 Sint-genesius-rode/rhode-saint-genese Vlaams-Brabant 1640",
    "addr:housenumber":"3",
    "addr:postcode":"1640",
    "addr:street":"Dorpsstraat",
    "iso:country":"BE",
    "sg:address":"Dorpsstraat 3",
    "sg:city":"Sint-genesius-rode/rhode-saint-genese",
    "sg:orig_category":"Serres and speciale beglazing",
    "sg:phone":"+32 2 380 16 49",
    "sg:postcode":"1640",
    "sg:province":"Vlaams-Brabant",
    "wof:name":"De Graeve",
    "wof:placetype":"venue"
},
  "geometry": {"coordinates":[4.3430290222,50.7441291809],"type":"Point"}
}