{
  "type": "Feature",
  "properties": {
    "addr:full":"Leuvensesteenweg 150 Aarschot Vlaams-Brabant 3200",
    "addr:housenumber":"150",
    "addr:postcode":"3200",
    "addr:street":"Leuvensesteenweg",
    "iso:country":"BE",
    "sg:address":"Leuvensesteenweg 150",
    "sg:city":"Aarschot",
    "sg:classifiers":[
        {
            "category":"Personal",
            "subcategory":"Beauty Salon",
            "type":"Services"
        }
    ],
    "sg:phone":"+32 16 56 52 62",
    "sg:postcode":"3200",
    "sg:province":"Vlaams-Brabant",
    "sg:tags":[
        "de",
        "coiffure"
    ],
    "wof:name":"Coiffure Nadine",
    "wof:placetype":"venue"
},
  "geometry": {"coordinates":[4.8289899826,50.9826087952],"type":"Point"}
}