{
  "type": "Feature",
  "properties": {
    "addr:full":"Reningelstseweg 18 Poperinge West-Vlaanderen 8970",
    "addr:housenumber":"18",
    "addr:postcode":"8970",
    "addr:street":"Reningelstseweg",
    "iso:country":"BE",
    "sg:address":"Reningelstseweg 18",
    "sg:city":"Poperinge",
    "sg:classifiers":[
        {
            "category":"Insurance",
            "subcategory":"Insurance Agent",
            "type":"Services"
        }
    ],
    "sg:phone":"+32 57 33 65 35",
    "sg:postcode":"8970",
    "sg:province":"West-Vlaanderen",
    "sg:tags":[
        "verzekeringsmakelaars",
        "expert"
    ],
    "wof:name":"Kantoor Decapmaker",
    "wof:placetype":"venue"
},
  "geometry": {"coordinates":[2.736634016,50.8440132141],"type":"Point"}
}