{
  "type": "Feature",
  "properties": {
    "iso:country":"BE",
    "sg:address":"Heerbaan 29",
    "sg:city":"Kortenaken",
    "sg:orig_category":"Producteurs de fruits",
    "sg:phone":"+32 16 77 81 54",
    "sg:postcode":"3472",
    "sg:province":"Vlaams-Brabant",
    "wof:name":"Jean Defrere",
    "wof:placetype":"venue"
},
  "geometry": {"coordinates":[4.9972519875,50.8863105774],"type":"Point"}
}