{
  "type": "Feature",
  "properties": {
    "iso:country":"BE",
    "sg:address":"Rijselstraat 16-18",
    "sg:city":"Menen",
    "sg:orig_category":"Chaussures",
    "sg:phone":"+32 56 53 21 02",
    "sg:postcode":"8930",
    "sg:province":"West-Vlaanderen",
    "wof:name":"Torfs",
    "wof:placetype":"venue"
},
  "geometry": {"coordinates":[3.1220319271,50.795715332],"type":"Point"}
}