{
  "type": "Feature",
  "properties": {
    "iso:country":"BE",
    "sg:address":"Groene Hofstraat 35",
    "sg:city":"Boom",
    "sg:orig_category":"Artsen and specialisten",
    "sg:phone":"+32 3 888 18 52",
    "sg:postcode":"2850",
    "sg:province":"Antwerpen",
    "wof:name":"W. Van Linden",
    "wof:placetype":"venue"
},
  "geometry": {"coordinates":[4.3641262054,51.0852851868],"type":"Point"}
}