{
  "type": "Feature",
  "properties": {
    "iso:country":"BE",
    "sg:address":"Rozendaalstraat 14",
    "sg:city":"Ieper",
    "sg:classifiers":[
        {
            "category":"Social Services",
            "subcategory":"Job Training",
            "type":"Services"
        }
    ],
    "sg:phone":"+32 57 20 66 29",
    "sg:postcode":"8900",
    "sg:province":"West-Vlaanderen",
    "sg:tags":[
        "condiment",
        "spice"
    ],
    "wof:name":"Euro Food Ingredients Bvba",
    "wof:placetype":"venue"
},
  "geometry": {"coordinates":[2.8823959827,50.8765983582],"type":"Point"}
}