{
  "type": "Feature",
  "properties": {
    "addr:full":"Jourdanstraat 19 Sint-gillis/saint-gilles Bruxelles-Capitale 1060",
    "addr:housenumber":"19",
    "addr:postcode":"1060",
    "addr:street":"Jourdanstraat",
    "iso:country":"BE",
    "sg:address":"Jourdanstraat 19",
    "sg:city":"Sint-gillis/saint-gilles",
    "sg:classifiers":[
        {
            "category":"Restaurant",
            "type":"Food & Drink"
        }
    ],
    "sg:phone":"+32 2 538 87 94",
    "sg:postcode":"1060",
    "sg:province":"Bruxelles-Capitale",
    "wof:name":"Al Piccolo Mondo",
    "wof:placetype":"venue"
},
  "geometry": {"coordinates":[4.3549880981,50.8346672058],"type":"Point"}
}