{
  "type": "Feature",
  "properties": {
    "addr:full":"Molenbergplein 1bw1 Lokeren Oost-Vlaanderen 9160",
    "addr:postcode":"9160",
    "addr:street":"Lokeren Oost-Vlaanderen",
    "iso:country":"BE",
    "sg:address":"Molenbergplein 1bw1",
    "sg:city":"Lokeren",
    "sg:orig_category":"Artsen and specialisten",
    "sg:phone":"+32 9 348 67 36",
    "sg:postcode":"9160",
    "sg:province":"Oost-Vlaanderen",
    "wof:name":"Jan Loomans",
    "wof:placetype":"venue"
},
  "geometry": {"coordinates":[3.9972031116,51.1014022827],"type":"Point"}
}