{
  "type": "Feature",
  "properties": {
    "addr:full":"Avenue De Merode 13 Rixensart Brabant Wallon 1330",
    "addr:housenumber":"13",
    "addr:postcode":"1330",
    "addr:street":"Avenue De Merode;Wallon",
    "iso:country":"BE",
    "sg:address":"Avenue De Merode 13",
    "sg:city":"Rixensart",
    "sg:classifiers":[
        {
            "category":"Insurance",
            "subcategory":"Insurance Agent",
            "type":"Services"
        }
    ],
    "sg:phone":"+32 2 652 16 60",
    "sg:postcode":"1330",
    "sg:province":"Brabant Wallon",
    "sg:tags":[
        "broker"
    ],
    "wof:name":"Belgassur",
    "wof:placetype":"venue"
},
  "geometry": {"coordinates":[4.5290751457,50.7125358582],"type":"Point"}
}