{
  "type": "Feature",
  "properties": {
    "addr:full":"Rue De La Gare-d'oret 43 Florennes Namur 5621",
    "addr:housenumber":"43",
    "addr:postcode":"5621",
    "addr:street":"Rue De La Gare-D'Oret",
    "iso:country":"BE",
    "sg:address":"Rue De La Gare-d'oret 43",
    "sg:city":"Florennes",
    "sg:orig_category":"Traitements param\u00e9dicaux",
    "sg:phone":"+32 71 68 97 47",
    "sg:postcode":"5621",
    "sg:province":"Namur",
    "wof:name":"I. Degand",
    "wof:placetype":"venue"
},
  "geometry": {"coordinates":[4.5649380684,50.2940788269],"type":"Point"}
}