{
  "type": "Feature",
  "properties": {
    "addr:full":"Gaverlanddam 6 Beveren Oost-Vlaanderen 9120",
    "addr:housenumber":"6",
    "addr:postcode":"9120",
    "addr:street":"Gaverlanddam",
    "iso:country":"BE",
    "sg:address":"Gaverlanddam 6",
    "sg:city":"Beveren",
    "sg:orig_category":"Epiceries",
    "sg:phone":"+32 3 775 17 39",
    "sg:postcode":"9120",
    "sg:province":"Oost-Vlaanderen",
    "wof:name":"Christien Maes",
    "wof:placetype":"venue"
},
  "geometry": {"coordinates":[4.2639989853,51.2237052917],"type":"Point"}
}