{
  "type": "Feature",
  "properties": {
    "iso:country":"BE",
    "sg:address":"Kattenstraat 47",
    "sg:city":"Roeselare",
    "sg:orig_category":"Plomberie, chauffage and installations sanitaires",
    "sg:phone":"+32 51 20 03 62",
    "sg:postcode":"8800",
    "sg:province":"West-Vlaanderen",
    "wof:name":"Gryffroy Piping",
    "wof:placetype":"venue"
},
  "geometry": {"coordinates":[3.1192030907,50.947227478],"type":"Point"}
}