{
  "type": "Feature",
  "properties": {
    "iso:country":"BE",
    "sg:address":"Vaart Linkeroever 96",
    "sg:city":"Deinze",
    "sg:orig_category":"Rundveehouders",
    "sg:phone":"+32 9 386 54 22",
    "sg:postcode":"9800",
    "sg:province":"Oost-Vlaanderen",
    "wof:name":"Hubert Dewitte",
    "wof:placetype":"venue"
},
  "geometry": {"coordinates":[3.5339150429,50.9978141785],"type":"Point"}
}