{
  "type": "Feature",
  "properties": {
    "iso:country":"BE",
    "sg:address":"Quai De L'ecluse 9",
    "sg:city":"Namur",
    "sg:orig_category":"M\u00e9decines alternatives",
    "sg:phone":"+32 81 73 32 00",
    "sg:postcode":"5000",
    "sg:province":"Namur",
    "wof:name":"Docteur Lievens Anne",
    "wof:placetype":"venue"
},
  "geometry": {"coordinates":[4.8523159027,50.4689483643],"type":"Point"}
}