{
  "type": "Feature",
  "properties": {
    "addr:full":"Rue D'aix La Chapelle 28 Eupen Li\u00e8ge 4700",
    "addr:housenumber":"28",
    "addr:postcode":"4700",
    "addr:street":"Rue D'Aix La Chapelle",
    "iso:country":"BE",
    "sg:address":"Rue D'aix La Chapelle 28",
    "sg:city":"Eupen",
    "sg:orig_category":"Pr\u00eats hypoth\u00e9caires and cr\u00e9dits immobiliers. Cr\u00e9dit \u00e0 la consommation. Banques and organismes de cr\u00e9",
    "sg:phone":"+32 87 74 22 77",
    "sg:postcode":"4700",
    "sg:province":"Li\u00e8ge",
    "wof:name":"Berufskredit",
    "wof:placetype":"venue"
},
  "geometry": {"coordinates":[6.1348800659,50.5989990234],"type":"Point"}
}