{
  "type": "Feature",
  "properties": {
    "addr:full":"Ooievaarsstraat 24 Wervik West-Vlaanderen 8940",
    "addr:housenumber":"24",
    "addr:postcode":"8940",
    "addr:street":"Ooievaarsstraat",
    "iso:country":"BE",
    "sg:address":"Ooievaarsstraat 24",
    "sg:city":"Wervik",
    "sg:orig_category":"Kapsalons",
    "sg:phone":"+32 56 31 14 85",
    "sg:postcode":"8940",
    "sg:province":"West-Vlaanderen",
    "wof:name":"Philippe Benoot",
    "wof:placetype":"venue"
},
  "geometry": {"coordinates":[3.0435481071,50.7780265808],"type":"Point"}
}