{
  "type": "Feature",
  "properties": {
    "addr:full":"Chemin De Botister 31 Dison Li\u00e8ge 4821",
    "addr:housenumber":"31",
    "addr:postcode":"4821",
    "addr:street":"Chemin De Botister",
    "iso:country":"BE",
    "sg:address":"Chemin De Botister 31",
    "sg:city":"Dison",
    "sg:orig_category":"Entretien and r\u00e9parations de voitures",
    "sg:phone":"+32 87 31 29 98",
    "sg:postcode":"4821",
    "sg:province":"Li\u00e8ge",
    "wof:name":"Jean-claude Englebert",
    "wof:placetype":"venue"
},
  "geometry": {"coordinates":[5.8683700562,50.606098175],"type":"Point"}
}