{
  "type": "Feature",
  "properties": {
    "addr:full":"Schaapsbaan 28 Essen Antwerpen 2910",
    "addr:housenumber":"28",
    "addr:postcode":"2910",
    "addr:street":"Schaapsbaan",
    "iso:country":"BE",
    "sg:address":"Schaapsbaan 28",
    "sg:city":"Essen",
    "sg:classifiers":[
        {
            "category":"Professional",
            "subcategory":"Management & Consulting",
            "type":"Services"
        }
    ],
    "sg:phone":"+32 3 667 65 76",
    "sg:postcode":"2910",
    "sg:province":"Antwerpen",
    "sg:tags":[
        "consultant"
    ],
    "wof:name":"Anba Bvba",
    "wof:placetype":"venue"
},
  "geometry": {"coordinates":[4.4630331993,51.4377937317],"type":"Point"}
}