{
  "type": "Feature",
  "properties": {
    "addr:full":"Rue Provost 11 Andenne Namur 5300",
    "addr:housenumber":"11",
    "addr:postcode":"5300",
    "addr:street":"Rue Provost",
    "iso:country":"BE",
    "sg:address":"Rue Provost 11",
    "sg:city":"Andenne",
    "sg:classifiers":[
        {
            "category":"Retail",
            "subcategory":"Veterinary Services",
            "type":"Services"
        }
    ],
    "sg:phone":"+32 85 84 18 78",
    "sg:postcode":"5300",
    "sg:province":"Namur",
    "sg:tags":[
        "veterinarian"
    ],
    "wof:name":"Ligot J",
    "wof:placetype":"venue"
},
  "geometry": {"coordinates":[5.1021261215,50.4889030457],"type":"Point"}
}