{
  "type": "Feature",
  "properties": {
    "addr:full":"Dr\u00e8ve De La Louve 9 Bruxelles (watermael-boitsfort) Bruxelles-Capitale 1170",
    "addr:housenumber":"9",
    "addr:postcode":"1170",
    "addr:street":"Dre\u0300Ve De La Louve",
    "iso:country":"BE",
    "sg:address":"Dr\u00e8ve De La Louve 9",
    "sg:city":"Bruxelles (watermael-boitsfort)",
    "sg:classifiers":[
        {
            "category":"Health Services",
            "subcategory":"Doctor",
            "type":"Services"
        }
    ],
    "sg:phone":"+32 2 673 56 99",
    "sg:postcode":"1170",
    "sg:province":"Bruxelles-Capitale",
    "sg:tags":[
        "medicinephysicians",
        "surgeon"
    ],
    "wof:name":"Bertin Christiane",
    "wof:placetype":"venue"
},
  "geometry": {"coordinates":[4.4253377914,50.7977142334],"type":"Point"}
}