{
  "type": "Feature",
  "properties": {
    "iso:country":"BE",
    "sg:address":"Av De La Closeraie 5",
    "sg:city":"Rocourt",
    "sg:classifiers":[
        {
            "category":"Professional",
            "subcategory":"Computer Services",
            "type":"Services"
        }
    ],
    "sg:phone":"+32 4 224 94 10",
    "sg:postcode":"4000",
    "sg:province":"Li\u00e8ge",
    "sg:tags":[
        "information",
        "technology",
        "software"
    ],
    "wof:name":"Medical Business Channel Sa",
    "wof:placetype":"venue"
},
  "geometry": {"coordinates":[5.5558481216,50.6671257019],"type":"Point"}
}