{
  "type": "Feature",
  "properties": {
    "iso:country":"BE",
    "sg:address":"Vrasenestraat 4",
    "sg:city":"Beveren",
    "sg:classifiers":[
        {
            "category":"Shopping",
            "subcategory":"Clothing, Apparel, & Fashions",
            "type":"Retail Goods"
        }
    ],
    "sg:phone":"+32 3 775 35 15",
    "sg:postcode":"9120",
    "sg:province":"Oost-Vlaanderen",
    "sg:tags":[
        "v\u00eatements",
        "pour",
        "dame"
    ],
    "wof:name":"Azul",
    "wof:placetype":"venue"
},
  "geometry": {"coordinates":[4.2538728714,51.2144165039],"type":"Point"}
}