{
  "type": "Feature",
  "properties": {
    "addr:full":"Sergeysstraat 71 Herent Vlaams-Brabant 3020",
    "addr:housenumber":"71",
    "addr:postcode":"3020",
    "addr:street":"Sergeysstraat",
    "iso:country":"BE",
    "sg:address":"Sergeysstraat 71",
    "sg:city":"Herent",
    "sg:classifiers":[
        {
            "category":"Health Services",
            "subcategory":"Health Practitioner",
            "type":"Services"
        }
    ],
    "sg:phone":"+32 16 23 95 16",
    "sg:postcode":"3020",
    "sg:province":"Vlaams-Brabant",
    "sg:tags":[
        "physiotherapist"
    ],
    "wof:name":"Meelberghs B",
    "wof:placetype":"venue"
},
  "geometry": {"coordinates":[4.6754980087,50.9021034241],"type":"Point"}
}