{
  "type": "Feature",
  "properties": {
    "addr:full":"Veldenstraat 7 Retie Antwerpen 2470",
    "addr:housenumber":"7",
    "addr:postcode":"2470",
    "addr:street":"Veldenstraat",
    "iso:country":"BE",
    "sg:address":"Veldenstraat 7",
    "sg:city":"Retie",
    "sg:orig_category":"Quincailleries. Bois Gr. Travail and traitement du bois",
    "sg:phone":"+32 14 37 71 85",
    "sg:postcode":"2470",
    "sg:province":"Antwerpen",
    "wof:name":"R & D Timber",
    "wof:placetype":"venue"
},
  "geometry": {"coordinates":[5.0774669647,51.2729721069],"type":"Point"}
}