{
  "type": "Feature",
  "properties": {
    "iso:country":"BE",
    "sg:address":"Avenue Prekelinden 131",
    "sg:city":"Sint-lambrechts-woluwe/woluwe-saint-lambert",
    "sg:orig_category":"Fruits and l\u00e9gumes. Epiceries",
    "sg:phone":"+32 2 733 38 08",
    "sg:postcode":"1200",
    "sg:province":"Bruxelles-Capitale",
    "wof:name":"Shoppy",
    "wof:placetype":"venue"
},
  "geometry": {"coordinates":[4.4079790115,50.8437728882],"type":"Point"}
}