{
  "type": "Feature",
  "properties": {
    "iso:country":"BE",
    "sg:address":"Malderendorp 27",
    "sg:city":"Londerzeel (groot)",
    "sg:orig_category":"Bierproductie and Brouwerijen",
    "sg:phone":"+32 52 33 24 11",
    "sg:postcode":"1840",
    "sg:province":"Vlaams-Brabant",
    "wof:name":"Brouwerij Vercauteren",
    "wof:placetype":"venue"
},
  "geometry": {"coordinates":[4.2457318306,51.0202674866],"type":"Point"}
}