{
  "type": "Feature",
  "properties": {
    "addr:full":"Rue De Beaumont 409 Charleroi Hainaut 6030",
    "addr:housenumber":"409",
    "addr:postcode":"6030",
    "addr:street":"Rue De Beaumont;Hainaut",
    "iso:country":"BE",
    "sg:address":"Rue De Beaumont 409",
    "sg:city":"Charleroi",
    "sg:orig_category":"Paramedische behandelingen",
    "sg:phone":"+32 71 51 93 69",
    "sg:postcode":"6030",
    "sg:province":"Hainaut",
    "wof:name":"M. Francotte",
    "wof:placetype":"venue"
},
  "geometry": {"coordinates":[4.3893108368,50.3946342468],"type":"Point"}
}