{
  "type": "Feature",
  "properties": {
    "addr:full":"Chemin Des Croix 20 Dour Hainaut 7370",
    "addr:housenumber":"20",
    "addr:postcode":"7370",
    "addr:street":"Chemin Des Croix;Hainaut",
    "iso:country":"BE",
    "sg:address":"Chemin Des Croix 20",
    "sg:city":"Dour",
    "sg:orig_category":"Dansscholen",
    "sg:phone":"+32 65 65 14 14",
    "sg:postcode":"7370",
    "sg:province":"Hainaut",
    "wof:name":"Assoignon Patricia",
    "wof:placetype":"venue"
},
  "geometry": {"coordinates":[3.7783210278,50.3934020996],"type":"Point"}
}