{
  "type": "Feature",
  "properties": {
    "addr:full":"Parkstraat 2 Zottegem Oost-Vlaanderen 9620",
    "addr:housenumber":"2",
    "addr:postcode":"9620",
    "addr:street":"Parkstraat",
    "iso:country":"BE",
    "sg:address":"Parkstraat 2",
    "sg:city":"Zottegem",
    "sg:orig_category":"Algemeen secundair onderwijs Kleuter- en basisonderwijs",
    "sg:phone":"+32 9 360 29 21",
    "sg:postcode":"9620",
    "sg:province":"Oost-Vlaanderen",
    "wof:name":"Bulo Bernadetteschool",
    "wof:placetype":"venue"
},
  "geometry": {"coordinates":[3.8112111092,50.871181488],"type":"Point"}
}