{
  "type": "Feature",
  "properties": {
    "addr:full":"Rue Du Tombeu 7 Hannut Li\u00e8ge 4280",
    "addr:housenumber":"7",
    "addr:postcode":"4280",
    "addr:street":"Rue Du Tombeu",
    "iso:country":"BE",
    "sg:address":"Rue Du Tombeu 7",
    "sg:city":"Hannut",
    "sg:orig_category":"Enseignement maternel and primaire",
    "sg:phone":"+32 19 69 81 16",
    "sg:postcode":"4280",
    "sg:province":"Li\u00e8ge",
    "wof:name":"Ecole Fond. Communale",
    "wof:placetype":"venue"
},
  "geometry": {"coordinates":[5.0820770264,50.6310577393],"type":"Point"}
}