{
  "type": "Feature",
  "properties": {
    "addr:full":"Chauss\u00c9e De Charleroi 136 Brussel/bruxelles Bruxelles-Capitale 1000",
    "addr:housenumber":"136",
    "addr:postcode":"1000",
    "addr:street":"Chausse\u0301E De Charleroi;/",
    "iso:country":"BE",
    "sg:address":"Chauss\u00c9e De Charleroi 136",
    "sg:city":"Brussel/bruxelles",
    "sg:orig_category":"Meubles D\u00e9taillants, Am\u00e9nagement de B\u00e2timents et de Cuisines",
    "sg:phone":"+32 2 538 38 16",
    "sg:postcode":"1000",
    "sg:province":"Bruxelles-Capitale",
    "wof:name":"Vibel L'architecte De L'enfant",
    "wof:placetype":"venue"
},
  "geometry": {"coordinates":[4.3571448326,50.8329811096],"type":"Point"}
}