{
  "type": "Feature",
  "properties": {
    "addr:full":"Ch D'ixelles 29-31 Gallerie De La Toison D'or Bruxelles Bruxelles-Capitale 1050",
    "addr:housenumber":"29-31",
    "addr:postcode":"1050",
    "addr:street":"Gallerie De La Toison D'Or",
    "iso:country":"BE",
    "sg:address":"Ch D'ixelles 29-31 Gallerie De La Toison D'or",
    "sg:city":"Bruxelles",
    "sg:classifiers":[
        {
            "category":"Professional",
            "subcategory":"Business Services",
            "type":"Services"
        }
    ],
    "sg:phone":"+32 2 511 01 09",
    "sg:postcode":"1050",
    "sg:province":"Bruxelles-Capitale",
    "sg:tags":[
        "training",
        "advice"
    ],
    "wof:name":"Ctre De Phonetique Appliquee De Bruxelles",
    "wof:placetype":"venue"
},
  "geometry": {"coordinates":[4.3571839333,50.836151123],"type":"Point"}
}