{
  "type": "Feature",
  "properties": {
    "addr:full":"Driesstraat 86 Tielt West-Vlaanderen 8700",
    "addr:housenumber":"86",
    "addr:postcode":"8700",
    "addr:street":"Driesstraat",
    "iso:country":"BE",
    "sg:address":"Driesstraat 86",
    "sg:city":"Tielt",
    "sg:orig_category":"Eleveurs de bovins",
    "sg:phone":"+32 51 40 03 77",
    "sg:postcode":"8700",
    "sg:province":"West-Vlaanderen",
    "wof:name":"Walter Cosman",
    "wof:placetype":"venue"
},
  "geometry": {"coordinates":[3.3428940773,50.9940643311],"type":"Point"}
}