{
  "type": "Feature",
  "properties": {
    "addr:full":"Sint-ambrosiuslaan 3 Dilbeek Vlaams-Brabant 1700",
    "addr:housenumber":"3",
    "addr:postcode":"1700",
    "addr:street":"Sint-Ambrosiuslaan",
    "iso:country":"BE",
    "sg:address":"Sint-ambrosiuslaan 3",
    "sg:city":"Dilbeek",
    "sg:classifiers":[
        {
            "category":"Personal",
            "subcategory":"Beauty Salon",
            "type":"Services"
        }
    ],
    "sg:phone":"+32 2 466 79 83",
    "sg:postcode":"1700",
    "sg:province":"Vlaams-Brabant",
    "sg:tags":[
        "de",
        "coiffure"
    ],
    "wof:name":"Natuurrsalon Haarkunst",
    "wof:placetype":"venue"
},
  "geometry": {"coordinates":[4.2646942139,50.8485527039],"type":"Point"}
}