{
  "type": "Feature",
  "properties": {
    "addr:full":"Place Nachez 10 Pont-a-celles Hainaut 6230",
    "addr:housenumber":"10",
    "addr:postcode":"6230",
    "addr:street":"Place Nachez",
    "iso:country":"BE",
    "sg:address":"Place Nachez 10",
    "sg:city":"Pont-a-celles",
    "sg:orig_category":"Enseignement maternel and primaire",
    "sg:phone":"+32 71 37 25 25",
    "sg:postcode":"6230",
    "sg:province":"Hainaut",
    "wof:name":"Ecole Fond. Communale",
    "wof:placetype":"venue"
},
  "geometry": {"coordinates":[4.3707361221,50.507106781],"type":"Point"}
}