{
  "type": "Feature",
  "properties": {
    "addr:full":"Rte De Gembloux 124 St. Servais Namur 5002",
    "addr:housenumber":"124",
    "addr:postcode":"5002",
    "addr:street":"Rte De Gembloux",
    "iso:country":"BE",
    "sg:address":"Rte De Gembloux 124",
    "sg:city":"St. Servais",
    "sg:classifiers":[
        {
            "category":"Banks & Credit Unions",
            "subcategory":"Bank",
            "type":"Services"
        }
    ],
    "sg:phone":"+32 81 73 06 39",
    "sg:postcode":"5002",
    "sg:province":"Namur",
    "wof:name":"Cr\u00e9dit Communal",
    "wof:placetype":"venue"
},
  "geometry": {"coordinates":[4.8491129875,50.4733848572],"type":"Point"}
}