{
  "type": "Feature",
  "properties": {
    "iso:country":"BE",
    "sg:address":"Avenue Des Chasseurs Ardennais 18",
    "sg:city":"Saint-hubert",
    "sg:classifiers":[
        {
            "category":"Retail",
            "subcategory":"Auto Repair",
            "type":"Services"
        }
    ],
    "sg:phone":"+32 61 61 14 32",
    "sg:postcode":"6870",
    "sg:province":"Luxembourg",
    "sg:tags":[
        "automobile-body"
    ],
    "wof:name":"Francois",
    "wof:placetype":"venue"
},
  "geometry": {"coordinates":[5.3658299446,50.0268096924],"type":"Point"}
}