{
  "type": "Feature",
  "properties": {
    "iso:country":"BE",
    "sg:address":"Rue Du Vivier 69",
    "sg:city":"Marche-en-famenne (aye)",
    "sg:classifiers":[
        {
            "category":"Health Services",
            "subcategory":"Doctor",
            "type":"Services"
        }
    ],
    "sg:phone":"+32 84 31 16 83",
    "sg:postcode":"6900",
    "sg:province":"Luxembourg",
    "sg:tags":[
        "medicinephysicians",
        "surgeon"
    ],
    "wof:name":"Bertho Maurice",
    "wof:placetype":"venue"
},
  "geometry": {"coordinates":[5.3271999359,50.2289581299],"type":"Point"}
}