{
  "type": "Feature",
  "properties": {
    "addr:full":"Avenue De La Lib\u00c9ration 95 Soumagne Li\u00e8ge 4630",
    "addr:housenumber":"95",
    "addr:postcode":"4630",
    "addr:street":"Avenue De La Libe\u0301Ration",
    "iso:country":"BE",
    "sg:address":"Avenue De La Lib\u00c9ration 95",
    "sg:city":"Soumagne",
    "sg:classifiers":[
        {
            "category":"Restaurant",
            "type":"Food & Drink"
        }
    ],
    "sg:phone":"+32 4 358 70 53",
    "sg:postcode":"4630",
    "sg:province":"Li\u00e8ge",
    "wof:name":"Restaurant La Mezzanine",
    "wof:placetype":"venue"
},
  "geometry": {"coordinates":[5.7073249817,50.61145401],"type":"Point"}
}