{
  "type": "Feature",
  "properties": {
    "addr:full":"Hoekstraat 29 Wichelen Oost-Vlaanderen 9260",
    "addr:housenumber":"29",
    "addr:postcode":"9260",
    "addr:street":"Hoekstraat",
    "iso:country":"BE",
    "sg:address":"Hoekstraat 29",
    "sg:city":"Wichelen",
    "sg:orig_category":"Installatie van houten of kunststof schrijnwerk MEUBELONTWERP AND -INSTALLATIE",
    "sg:phone":"+32 9 369 18 96",
    "sg:postcode":"9260",
    "sg:province":"Oost-Vlaanderen",
    "wof:name":"Andre De Schaepmeester",
    "wof:placetype":"venue"
},
  "geometry": {"coordinates":[3.9354569912,51.0057411194],"type":"Point"}
}