{
  "type": "Feature",
  "properties": {
    "addr:full":"Rue De La Justice 55 Oupeye Li\u00e8ge 4680",
    "addr:housenumber":"55",
    "addr:postcode":"4680",
    "addr:street":"Rue De La Justice",
    "iso:country":"BE",
    "sg:address":"Rue De La Justice 55",
    "sg:city":"Oupeye",
    "sg:orig_category":"Dakwerken Loodgieterij, verwarming and sanitaire installaties",
    "sg:phone":"+32 4 264 50 01",
    "sg:postcode":"4680",
    "sg:province":"Li\u00e8ge",
    "wof:name":"Guiseppe Muscato",
    "wof:placetype":"venue"
},
  "geometry": {"coordinates":[5.6391072273,50.7137641907],"type":"Point"}
}