{
  "type": "Feature",
  "properties": {
    "addr:full":"Koningin Astridlaan 38 Hasselt Limburg 3500",
    "addr:housenumber":"38",
    "addr:postcode":"3500",
    "addr:street":"Koningin Astridlaan",
    "iso:country":"BE",
    "sg:address":"Koningin Astridlaan 38",
    "sg:city":"Hasselt",
    "sg:classifiers":[
        {
            "category":"Local Transit",
            "type":"Transportation"
        }
    ],
    "sg:phone":"+32 11 22 31 91",
    "sg:postcode":"3500",
    "sg:province":"Limburg",
    "sg:tags":[
        "made-to-measure",
        "shirt"
    ],
    "wof:name":"Eugene Spaas En Cie B.v.b.a.",
    "wof:placetype":"venue"
},
  "geometry": {"coordinates":[5.3308291435,50.9316825867],"type":"Point"}
}