{
  "type": "Feature",
  "properties": {
    "iso:country":"BE",
    "sg:address":"Rue De La Station 3",
    "sg:city":"Soignies",
    "sg:classifiers":[
        {
            "category":"Shopping",
            "subcategory":"Books",
            "type":"Retail Goods"
        }
    ],
    "sg:phone":"+32 67 33 29 64",
    "sg:postcode":"7060",
    "sg:province":"Hainaut",
    "sg:tags":[
        "bookseller"
    ],
    "wof:name":"Cordovero J-c",
    "wof:placetype":"venue"
},
  "geometry": {"coordinates":[4.0715007782,50.5773582458],"type":"Point"}
}