{
  "type": "Feature",
  "properties": {
    "iso:country":"BE",
    "sg:address":"Avenue Lavoisier 7",
    "sg:city":"Wavre",
    "sg:classifiers":[
        {
            "category":"Home & Garden",
            "subcategory":"Home Furnishings",
            "type":"Retail Goods"
        }
    ],
    "sg:phone":"+32 10 23 51 11",
    "sg:postcode":"1300",
    "sg:province":"Brabant Wallon",
    "sg:tags":[
        "curtain",
        "-",
        "fixture"
    ],
    "wof:name":"Heytens",
    "wof:placetype":"venue"
},
  "geometry": {"coordinates":[4.5947828293,50.7361068726],"type":"Point"}
}