{
  "type": "Feature",
  "properties": {
    "addr:full":"Rabecqueplaats 1bb Komen-waasten/comines-warneton Hainaut 7782",
    "addr:postcode":"7782",
    "iso:country":"BE",
    "sg:address":"Rabecqueplaats 1bb",
    "sg:city":"Komen-waasten/comines-warneton",
    "sg:orig_category":"Kansspelen",
    "sg:phone":"+32 56 58 98 27",
    "sg:postcode":"7782",
    "sg:province":"Hainaut",
    "wof:name":"Ladbroke",
    "wof:placetype":"venue"
},
  "geometry": {"coordinates":[2.8795371056,50.7278747559],"type":"Point"}
}