{
  "type": "Feature",
  "properties": {
    "iso:country":"BE",
    "sg:address":"Chauss\u00c9e De Vleurgat 78",
    "sg:city":"Elsene/ixelles",
    "sg:orig_category":"Bedrijvencentra and kantoordiensten",
    "sg:phone":"+32 2 640 58 49",
    "sg:postcode":"1050",
    "sg:province":"Bruxelles-Capitale",
    "wof:name":"Bal S.",
    "wof:placetype":"venue"
},
  "geometry": {"coordinates":[4.3694357872,50.8252220154],"type":"Point"}
}