{
  "type": "Feature",
  "properties": {
    "iso:country":"BE",
    "sg:address":"Rue Des Deux Ponts 8",
    "sg:city":"Ottignies-louvain-la-neuve (ottignies)",
    "sg:classifiers":[
        {
            "category":"Shopping",
            "subcategory":"Florist",
            "type":"Retail Goods"
        }
    ],
    "sg:phone":"+32 10 40 09 50",
    "sg:postcode":"1340",
    "sg:province":"Brabant Wallon",
    "wof:name":"Arc En Fleur (l')",
    "wof:placetype":"venue"
},
  "geometry": {"coordinates":[4.5718431473,50.6674995422],"type":"Point"}
}