{
  "type": "Feature",
  "properties": {
    "iso:country":"BE",
    "sg:address":"Trinellestraat 13",
    "sg:city":"Riemst",
    "sg:orig_category":"Epiceries",
    "sg:phone":"+32 12 23 18 91",
    "sg:postcode":"3770",
    "sg:province":"Limburg",
    "wof:name":"Wilfried Coenegrachts",
    "wof:placetype":"venue"
},
  "geometry": {"coordinates":[5.5585842133,50.7840385437],"type":"Point"}
}