{
  "type": "Feature",
  "properties": {
    "addr:full":"Nieder Emmels 68 Sankt Vith (crombach) Li\u00e8ge 4784",
    "addr:housenumber":"68",
    "addr:postcode":"4784",
    "addr:street":"Nieder Emmels",
    "iso:country":"BE",
    "sg:address":"Nieder Emmels 68",
    "sg:city":"Sankt Vith (crombach)",
    "sg:classifiers":[
        {
            "category":"Autos & Motor Vehicles",
            "subcategory":"Fuel & Gas Station",
            "type":"Retail Goods"
        }
    ],
    "sg:phone":"+32 80 22 87 14",
    "sg:postcode":"4784",
    "sg:province":"Li\u00e8ge",
    "wof:name":"Peters N",
    "wof:placetype":"venue"
},
  "geometry": {"coordinates":[6.101006031,50.3058357239],"type":"Point"}
}