{
  "type": "Feature",
  "properties": {
    "iso:country":"BE",
    "sg:address":"Grande Place 55",
    "sg:city":"Ottignies-louvain-la-neuve",
    "sg:orig_category":"Cin\u00e9mas",
    "sg:phone":"+32 900 10 440",
    "sg:postcode":"1348",
    "sg:province":"Brabant Wallon",
    "wof:name":"Ugc - Louvain La Neuve",
    "wof:placetype":"venue"
},
  "geometry": {"coordinates":[4.6118011475,50.6692008972],"type":"Point"}
}