{
  "type": "Feature",
  "properties": {
    "iso:country":"BE",
    "sg:address":"Houtmarkt 89",
    "sg:city":"Haaltert",
    "sg:orig_category":"D\u00e9chets and d\u00e9bris Gr",
    "sg:phone":"+32 53 83 04 31",
    "sg:postcode":"9450",
    "sg:province":"Oost-Vlaanderen",
    "wof:name":"Gustaaf De Bruin",
    "wof:placetype":"venue"
},
  "geometry": {"coordinates":[4.0113501549,50.8984794617],"type":"Point"}
}