{
  "type": "Feature",
  "properties": {
    "addr:full":"Grimbergsesteenweg 151 Zemst (eppegem) Vlaams-Brabant 1980",
    "addr:housenumber":"151",
    "addr:postcode":"1980",
    "addr:street":"Grimbergsesteenweg",
    "iso:country":"BE",
    "sg:address":"Grimbergsesteenweg 151",
    "sg:city":"Zemst (eppegem)",
    "sg:classifiers":[
        {
            "category":"Freight",
            "type":"Transportation"
        }
    ],
    "sg:phone":"+32 2 251 73 04",
    "sg:postcode":"1980",
    "sg:province":"Vlaams-Brabant",
    "sg:tags":[
        "-",
        "transport"
    ],
    "wof:name":"Vandevelde D",
    "wof:placetype":"venue"
},
  "geometry": {"coordinates":[4.4439368248,50.9581871033],"type":"Point"}
}