{
  "type": "Feature",
  "properties": {
    "addr:full":"Roesdammestraat 32 Veurne West-Vlaanderen 8630",
    "addr:housenumber":"32",
    "addr:postcode":"8630",
    "addr:street":"Roesdammestraat",
    "iso:country":"BE",
    "sg:address":"Roesdammestraat 32",
    "sg:city":"Veurne",
    "sg:orig_category":"Rundveehouders Varkenskwekers",
    "sg:phone":"+32 51 55 52 28",
    "sg:postcode":"8630",
    "sg:province":"West-Vlaanderen",
    "wof:name":"Gery Debeuf",
    "wof:placetype":"venue"
},
  "geometry": {"coordinates":[2.7602028847,51.0632209778],"type":"Point"}
}