{
  "type": "Feature",
  "properties": {
    "iso:country":"BE",
    "sg:address":"Rue St-jean 14",
    "sg:city":"Jodoigne",
    "sg:orig_category":"HERSTELLING ELEKTRISCHE HUISHOUDAPPARATEN Huishoudapparaten, televisies and radio's Telecommunicatie",
    "sg:phone":"+32 10 81 34 90",
    "sg:postcode":"1370",
    "sg:province":"Brabant Wallon",
    "wof:name":"Alsteens Electro",
    "wof:placetype":"venue"
},
  "geometry": {"coordinates":[4.8703742027,50.7248344421],"type":"Point"}
}