{
  "type": "Feature",
  "properties": {
    "addr:full":"Rue Des Combattants 81 Verviers Li\u00e8ge 4800",
    "addr:housenumber":"81",
    "addr:postcode":"4800",
    "addr:street":"Rue Des Combattants",
    "iso:country":"BE",
    "sg:address":"Rue Des Combattants 81",
    "sg:city":"Verviers",
    "sg:classifiers":[
        {
            "category":"Insurance",
            "subcategory":"Insurance Agent",
            "type":"Services"
        }
    ],
    "sg:phone":"+32 87 33 51 22",
    "sg:postcode":"4800",
    "sg:province":"Li\u00e8ge",
    "sg:tags":[
        "verzekeringsmakelaars",
        "expert"
    ],
    "wof:name":"Simar Henri Jr",
    "wof:placetype":"venue"
},
  "geometry": {"coordinates":[5.8475799561,50.5951309204],"type":"Point"}
}