{
  "type": "Feature",
  "properties": {
    "addr:full":"Village 98 Olne Li\u00e8ge 4877",
    "addr:housenumber":"98",
    "addr:postcode":"4877",
    "iso:country":"BE",
    "sg:address":"Village 98",
    "sg:city":"Olne",
    "sg:orig_category":"Architectes",
    "sg:phone":"+32 87 26 91 89",
    "sg:postcode":"4877",
    "sg:province":"Li\u00e8ge",
    "wof:name":"Anne Schoonbroodt",
    "wof:placetype":"venue"
},
  "geometry": {"coordinates":[5.7508401871,50.5927772522],"type":"Point"}
}