{
  "type": "Feature",
  "properties": {
    "iso:country":"BE",
    "sg:address":"Sint-antoniusweg 21",
    "sg:city":"Neerpelt",
    "sg:orig_category":"Articles de jardin",
    "sg:phone":"+32 11 64 17 41",
    "sg:postcode":"3910",
    "sg:province":"Limburg",
    "wof:name":"Aegten Leon",
    "wof:placetype":"venue"
},
  "geometry": {"coordinates":[5.4457168579,51.2318000793],"type":"Point"}
}