{
  "type": "Feature",
  "properties": {
    "addr:full":"Rue Seutin 66 Bruxelles (schaerbeek) Bruxelles-Capitale 1030",
    "addr:housenumber":"66",
    "addr:postcode":"1030",
    "addr:street":"Rue Seutin",
    "iso:country":"BE",
    "sg:address":"Rue Seutin 66",
    "sg:city":"Bruxelles (schaerbeek)",
    "sg:classifiers":[
        {
            "category":"Building & Trades",
            "subcategory":"Plumbing",
            "type":"Services"
        }
    ],
    "sg:phone":"+32 2 215 15 24",
    "sg:postcode":"1030",
    "sg:province":"Bruxelles-Capitale",
    "sg:tags":[
        "contractor"
    ],
    "wof:name":"De Greef G",
    "wof:placetype":"venue"
},
  "geometry": {"coordinates":[4.3732919693,50.8585968018],"type":"Point"}
}