{
  "type": "Feature",
  "properties": {
    "iso:country":"BE",
    "sg:address":"Florimond Leirensstraat 54",
    "sg:city":"Wetteren",
    "sg:classifiers":[
        {
            "category":"Shopping",
            "subcategory":"Shoes",
            "type":"Retail Goods"
        }
    ],
    "sg:phone":"+32 9 369 08 30",
    "sg:postcode":"9230",
    "sg:province":"Oost-Vlaanderen",
    "sg:tags":[
        "slipper",
        "-"
    ],
    "wof:name":"Michiels J Bvba",
    "wof:placetype":"venue"
},
  "geometry": {"coordinates":[3.8837358952,51.0048828125],"type":"Point"}
}