{
  "type": "Feature",
  "properties": {
    "iso:country":"BE",
    "sg:address":"Rue Du Ch\u00c8ne 185",
    "sg:city":"Seraing",
    "sg:orig_category":"Boekhouders",
    "sg:phone":"+32 4 336 65 73",
    "sg:postcode":"4100",
    "sg:province":"Li\u00e8ge",
    "wof:name":"Renato Marchese",
    "wof:placetype":"venue"
},
  "geometry": {"coordinates":[5.5168809891,50.6017837524],"type":"Point"}
}