{
  "type": "Feature",
  "properties": {
    "addr:full":"Veurs 17 Voeren/fourons Limburg 3790",
    "addr:housenumber":"17",
    "addr:postcode":"3790",
    "addr:street":"Veurs",
    "iso:country":"BE",
    "sg:address":"Veurs 17",
    "sg:city":"Voeren/fourons",
    "sg:orig_category":"Woningbouw",
    "sg:phone":"+32 4 381 09 11",
    "sg:postcode":"3790",
    "sg:province":"Limburg",
    "wof:name":"Paul Laugs",
    "wof:placetype":"venue"
},
  "geometry": {"coordinates":[5.8393611908,50.7379188538],"type":"Point"}
}