{
  "type": "Feature",
  "properties": {
    "iso:country":"BE",
    "sg:address":"Rue Pierre Timmermans 28",
    "sg:city":"Bruxelles (jette)",
    "sg:classifiers":[
        {
            "category":"Place Of Worship",
            "subcategory":"Church",
            "type":"Public Place"
        }
    ],
    "sg:phone":"+32 2 426 24 94",
    "sg:postcode":"1090",
    "sg:province":"Bruxelles-Capitale",
    "sg:tags":[
        "article",
        "baptismal"
    ],
    "wof:name":"Coccinelle",
    "wof:placetype":"venue"
},
  "geometry": {"coordinates":[4.3239002228,50.8734512329],"type":"Point"}
}