{
  "type": "Feature",
  "properties": {
    "addr:full":"Rue Rocher-de-hourt 23 Vielsalm Luxembourg 6698",
    "addr:housenumber":"23",
    "addr:postcode":"6698",
    "addr:street":"Rue Rocher-De-Hourt",
    "iso:country":"BE",
    "sg:address":"Rue Rocher-de-hourt 23",
    "sg:city":"Vielsalm",
    "sg:orig_category":"Pain, p\u00e2tisseries and confiseries",
    "sg:phone":"+32 80 21 70 77",
    "sg:postcode":"6698",
    "sg:province":"Luxembourg",
    "wof:name":"Christelle Meurice",
    "wof:placetype":"venue"
},
  "geometry": {"coordinates":[5.9099740982,50.3147125244],"type":"Point"}
}