{
  "type": "Feature",
  "properties": {
    "addr:full":"Pottestraat 52 Poperinge West-Vlaanderen 8970",
    "addr:housenumber":"52",
    "addr:postcode":"8970",
    "addr:street":"Pottestraat",
    "iso:country":"BE",
    "sg:address":"Pottestraat 52",
    "sg:city":"Poperinge",
    "sg:orig_category":"Caf\u00e9s Kansspelen",
    "sg:phone":"+32 57 33 31 17",
    "sg:postcode":"8970",
    "sg:province":"West-Vlaanderen",
    "wof:name":"Pmu",
    "wof:placetype":"venue"
},
  "geometry": {"coordinates":[2.7221999168,50.8578071594],"type":"Point"}
}