{
  "type": "Feature",
  "properties": {
    "addr:full":"Grand'rue 50 Lessines Hainaut 7860",
    "addr:housenumber":"50",
    "addr:postcode":"7860",
    "addr:street":"Grand'Rue;Hainaut",
    "iso:country":"BE",
    "sg:address":"Grand'rue 50",
    "sg:city":"Lessines",
    "sg:classifiers":[
        {
            "category":"Home & Garden",
            "subcategory":"Kitchen Supply",
            "type":"Retail Goods"
        }
    ],
    "sg:phone":"+32 68 34 00 64",
    "sg:postcode":"7860",
    "sg:province":"Hainaut",
    "sg:tags":[
        "installation"
    ],
    "wof:name":"Espace Cuisine",
    "wof:placetype":"venue"
},
  "geometry": {"coordinates":[3.8290889263,50.7124633789],"type":"Point"}
}