{
  "type": "Feature",
  "properties": {
    "addr:full":"Sint-truidersteenweg 572 Hasselt Limburg 3500",
    "addr:housenumber":"572",
    "addr:postcode":"3500",
    "addr:street":"Sint-Truidersteenweg",
    "iso:country":"BE",
    "sg:address":"Sint-truidersteenweg 572",
    "sg:city":"Hasselt",
    "sg:classifiers":[
        {
            "category":"Building & Trades",
            "subcategory":"Construction",
            "type":"Services"
        }
    ],
    "sg:phone":"+32 11 31 10 06",
    "sg:postcode":"3500",
    "sg:province":"Limburg",
    "sg:tags":[
        "ceiling"
    ],
    "wof:name":"Reno-span-decor",
    "wof:placetype":"venue"
},
  "geometry": {"coordinates":[5.3266401291,50.9175415039],"type":"Point"}
}