{
  "type": "Feature",
  "properties": {
    "addr:full":"Au-buisson-martin 46 Libramont-chevigny Luxembourg 6800",
    "addr:housenumber":"46",
    "addr:postcode":"6800",
    "addr:street":"Au-Buisson-Martin",
    "iso:country":"BE",
    "sg:address":"Au-buisson-martin 46",
    "sg:city":"Libramont-chevigny",
    "sg:orig_category":"Brood, gebak and snoepgoed",
    "sg:phone":"+32 61 22 44 86",
    "sg:postcode":"6800",
    "sg:province":"Luxembourg",
    "wof:name":"Joseph Villance",
    "wof:placetype":"venue"
},
  "geometry": {"coordinates":[5.3632102013,49.9183006287],"type":"Point"}
}