{
  "type": "Feature",
  "properties": {
    "iso:country":"BE",
    "sg:address":"Kwartelstraat 7",
    "sg:city":"Gent",
    "sg:orig_category":"Artsen and specialisten",
    "sg:phone":"+32 9 221 61 64",
    "sg:postcode":"9000",
    "sg:province":"Oost-Vlaanderen",
    "wof:name":"Johan Panis",
    "wof:placetype":"venue"
},
  "geometry": {"coordinates":[3.6913089752,51.0368423462],"type":"Point"}
}