{
  "type": "Feature",
  "properties": {
    "addr:full":"Quinten Matsijsstraat 41 Schoten Antwerpen 2900",
    "addr:housenumber":"41",
    "addr:postcode":"2900",
    "addr:street":"Quinten Matsijsstraat",
    "iso:country":"BE",
    "sg:address":"Quinten Matsijsstraat 41",
    "sg:city":"Schoten",
    "sg:classifiers":[
        {
            "category":"Bars & Pubs",
            "type":"Food & Drink"
        }
    ],
    "sg:phone":"+32 3 645 02 69",
    "sg:postcode":"2900",
    "sg:province":"Antwerpen",
    "sg:tags":[
        "tavern"
    ],
    "wof:name":"De Leck",
    "wof:placetype":"venue"
},
  "geometry": {"coordinates":[4.4760308266,51.2443313599],"type":"Point"}
}