{
  "type": "Feature",
  "properties": {
    "addr:full":"Rue Haut Port 120 Silly Hainaut 7830",
    "addr:housenumber":"120",
    "addr:postcode":"7830",
    "addr:street":"Rue Haut Port",
    "iso:country":"BE",
    "sg:address":"Rue Haut Port 120",
    "sg:city":"Silly",
    "sg:classifiers":[
        {
            "category":"Manufacturing",
            "subcategory":"Tobacco Products",
            "type":"Manufacturing & Wholesale Goods"
        }
    ],
    "sg:phone":"+32 68 55 14 14",
    "sg:postcode":"7830",
    "sg:province":"Hainaut",
    "sg:tags":[
        "fertilizer",
        "merchant",
        "-"
    ],
    "wof:name":"Cannuyer (maison)",
    "wof:placetype":"venue"
},
  "geometry": {"coordinates":[3.9487009048,50.642906189],"type":"Point"}
}