{
  "type": "Feature",
  "properties": {
    "iso:country":"BE",
    "sg:address":"Stavelestraat 1",
    "sg:city":"Poperinge",
    "sg:orig_category":"Woningbouw",
    "sg:phone":"+32 57 30 09 74",
    "sg:postcode":"8972",
    "sg:province":"West-Vlaanderen",
    "wof:name":"Jan Menu",
    "wof:placetype":"venue"
},
  "geometry": {"coordinates":[2.6810500622,50.9164161682],"type":"Point"}
}