{
  "type": "Feature",
  "properties": {
    "addr:full":"Sint-rochusstraat 35 Antwerpen Antwerpen 2100",
    "addr:housenumber":"35",
    "addr:postcode":"2100",
    "addr:street":"Sint-Rochusstraat",
    "iso:country":"BE",
    "sg:address":"Sint-rochusstraat 35",
    "sg:city":"Antwerpen",
    "sg:orig_category":"Loodgieterij, verwarming and sanitaire installaties Woningbouw",
    "sg:phone":"+32 3 322 25 55",
    "sg:postcode":"2100",
    "sg:province":"Antwerpen",
    "wof:name":"Alvesan",
    "wof:placetype":"venue"
},
  "geometry": {"coordinates":[4.4005641937,51.2123947144],"type":"Point"}
}