{
  "type": "Feature",
  "properties": {
    "addr:full":"Route De Saint-antoine 12 Manhay Luxembourg 6960",
    "addr:housenumber":"12",
    "addr:postcode":"6960",
    "addr:street":"Route De Saint-Antoine",
    "iso:country":"BE",
    "sg:address":"Route De Saint-antoine 12",
    "sg:city":"Manhay",
    "sg:orig_category":"Mat\u00e9riel m\u00e9dical and orthop\u00e9dique and proth\u00e8ses Fab",
    "sg:phone":"+32 86 43 31 95",
    "sg:postcode":"6960",
    "sg:province":"Luxembourg",
    "wof:name":"Jean-pierre Clignet",
    "wof:placetype":"venue"
},
  "geometry": {"coordinates":[5.6373667717,50.3630828857],"type":"Point"}
}