{
  "type": "Feature",
  "properties": {
    "iso:country":"BE",
    "sg:address":"Oudenaardsestr 4",
    "sg:city":"Geraardsbergen",
    "sg:classifiers":[
        {
            "category":"Banks & Credit Unions",
            "subcategory":"Bank",
            "type":"Services"
        }
    ],
    "sg:phone":"+32 54 41 29 54",
    "sg:postcode":"9500",
    "sg:province":"Oost-Vlaanderen",
    "wof:name":"Gemeentekrediet",
    "wof:placetype":"venue"
},
  "geometry": {"coordinates":[3.8760349751,50.771648407],"type":"Point"}
}