{
  "type": "Feature",
  "properties": {
    "iso:country":"BE",
    "sg:address":"Stationsstraat 106",
    "sg:city":"Waarschoot",
    "sg:classifiers":[
        {
            "category":"Bars & Pubs",
            "type":"Food & Drink"
        }
    ],
    "sg:phone":"+32 9 327 04 50",
    "sg:postcode":"9950",
    "sg:province":"Oost-Vlaanderen",
    "wof:name":"Pandoerken",
    "wof:placetype":"venue"
},
  "geometry": {"coordinates":[3.6128230095,51.1525268555],"type":"Point"}
}