{
  "type": "Feature",
  "properties": {
    "iso:country":"BE",
    "sg:address":"Brusselstraat 167ba",
    "sg:city":"Dilbeek",
    "sg:orig_category":"Epiceries",
    "sg:phone":"+32 2 453 94 89",
    "sg:postcode":"1700",
    "sg:province":"Vlaams-Brabant",
    "wof:name":"Eddy De Metselaer",
    "wof:placetype":"venue"
},
  "geometry": {"coordinates":[4.2083501816,50.8759994507],"type":"Point"}
}