{
  "type": "Feature",
  "properties": {
    "addr:full":"Avenue Edouard Lacombl\u00c9 8 Etterbeek/etterbeek Bruxelles-Capitale 1040",
    "addr:housenumber":"8",
    "addr:postcode":"1040",
    "addr:street":"Avenue Edouard Lacomble\u0301",
    "iso:country":"BE",
    "sg:address":"Avenue Edouard Lacombl\u00c9 8",
    "sg:city":"Etterbeek/etterbeek",
    "sg:orig_category":"M\u00e9decins and sp\u00e9cialistes",
    "sg:phone":"+32 2 762 65 60",
    "sg:postcode":"1040",
    "sg:province":"Bruxelles-Capitale",
    "wof:name":"Christian Wouters",
    "wof:placetype":"venue"
},
  "geometry": {"coordinates":[4.4094061852,50.8328361511],"type":"Point"}
}