{
  "type": "Feature",
  "properties": {
    "iso:country":"BE",
    "sg:address":"Geraardsbergsestraat 21",
    "sg:city":"Ninove (groot)",
    "sg:classifiers":[
        {
            "category":"Manufacturing",
            "subcategory":"Textiles",
            "type":"Manufacturing & Wholesale Goods"
        }
    ],
    "sg:phone":"+32 54 33 39 07",
    "sg:postcode":"9400",
    "sg:province":"Oost-Vlaanderen",
    "wof:name":"Huis 't Krapken",
    "wof:placetype":"venue"
},
  "geometry": {"coordinates":[4.0178699493,50.8366317749],"type":"Point"}
}