{
  "type": "Feature",
  "properties": {
    "iso:country":"BE",
    "sg:address":"Rue Des Gaux 7-9",
    "sg:city":"Ham-sur-heure-nalinnes",
    "sg:orig_category":"Rev\u00eatements de sols and murs. Mat\u00e9riaux de construction Gr",
    "sg:phone":"+32 71 21 54 47",
    "sg:postcode":"6120",
    "sg:province":"Hainaut",
    "wof:name":"Entrepr. Julien Marlier",
    "wof:placetype":"venue"
},
  "geometry": {"coordinates":[4.4496312141,50.3260307312],"type":"Point"}
}