{
  "type": "Feature",
  "properties": {
    "addr:full":"Rue Hubert Larock 16 Hannut (poucet) Li\u00e8ge 4280",
    "addr:housenumber":"16",
    "addr:postcode":"4280",
    "addr:street":"Rue Hubert Larock;Poucet",
    "iso:country":"BE",
    "sg:address":"Rue Hubert Larock 16",
    "sg:city":"Hannut (poucet)",
    "sg:classifiers":[
        {
            "category":"Wholesale",
            "subcategory":"Wine & Distilled Alcoholic Beverages",
            "type":"Manufacturing & Wholesale Goods"
        }
    ],
    "sg:phone":"+32 19 51 10 12",
    "sg:postcode":"4280",
    "sg:province":"Li\u00e8ge",
    "sg:tags":[
        "whol",
        "-",
        "spirit",
        "mfg"
    ],
    "wof:name":"Petit Poucet (le)",
    "wof:placetype":"venue"
},
  "geometry": {"coordinates":[5.1192917824,50.6785545349],"type":"Point"}
}