{
  "type": "Feature",
  "properties": {
    "iso:country":"BE",
    "sg:address":"Torenstraat 14",
    "sg:city":"Lokeren",
    "sg:classifiers":[
        {
            "category":"Bars & Pubs",
            "type":"Food & Drink"
        }
    ],
    "sg:phone":"+32 9 348 83 09",
    "sg:postcode":"9160",
    "sg:province":"Oost-Vlaanderen",
    "wof:name":"Donkere Wolk (de)",
    "wof:placetype":"venue"
},
  "geometry": {"coordinates":[3.9910879135,51.1049118042],"type":"Point"}
}