{
  "type": "Feature",
  "properties": {
    "addr:full":"Rue De L'eglise 14 Frasnes-lez-anvaing Hainaut 7912",
    "addr:housenumber":"14",
    "addr:postcode":"7912",
    "addr:street":"Rue De L'Eglise",
    "iso:country":"BE",
    "sg:address":"Rue De L'eglise 14",
    "sg:city":"Frasnes-lez-anvaing",
    "sg:classifiers":[
        {
            "category":"Insurance",
            "subcategory":"Insurance Agent",
            "type":"Services"
        }
    ],
    "sg:phone":"+32 69 76 87 10",
    "sg:postcode":"7912",
    "sg:province":"Hainaut",
    "sg:tags":[
        "verzekeringsmakelaars",
        "expert"
    ],
    "wof:name":"Bureau Scholart",
    "wof:placetype":"venue"
},
  "geometry": {"coordinates":[3.5704910755,50.7131118774],"type":"Point"}
}