{
  "type": "Feature",
  "properties": {
    "addr:full":"Leuvenselaan 877 Tienen Vlaams-Brabant 3300",
    "addr:housenumber":"877",
    "addr:postcode":"3300",
    "addr:street":"Leuvenselaan",
    "iso:country":"BE",
    "sg:address":"Leuvenselaan 877",
    "sg:city":"Tienen",
    "sg:orig_category":"Supermarch\u00e9s",
    "sg:phone":"+32 16 82 20 20",
    "sg:postcode":"3300",
    "sg:province":"Vlaams-Brabant",
    "wof:name":"Spar",
    "wof:placetype":"venue"
},
  "geometry": {"coordinates":[4.9037599564,50.8178901672],"type":"Point"}
}