{
  "type": "Feature",
  "properties": {
    "addr:full":"Doornstraat 22 Dilbeek Vlaams-Brabant 1700",
    "addr:housenumber":"22",
    "addr:postcode":"1700",
    "addr:street":"Doornstraat",
    "iso:country":"BE",
    "sg:address":"Doornstraat 22",
    "sg:city":"Dilbeek",
    "sg:orig_category":"Promoteurs immobiliers",
    "sg:phone":"+32 2 569 04 57",
    "sg:postcode":"1700",
    "sg:province":"Vlaams-Brabant",
    "wof:name":"Juwet",
    "wof:placetype":"venue"
},
  "geometry": {"coordinates":[4.2549829483,50.8360061646],"type":"Point"}
}