{
  "type": "Feature",
  "properties": {
    "iso:country":"BE",
    "sg:address":"Rue De Burnaifontaine 79bd",
    "sg:city":"Daverdisse",
    "sg:orig_category":"Landbouwmachines Gh",
    "sg:phone":"+32 61 58 93 10",
    "sg:postcode":"6929",
    "sg:province":"Luxembourg",
    "wof:name":"Garage Genonceaux Luc",
    "wof:placetype":"venue"
},
  "geometry": {"coordinates":[5.0247898102,49.9987792969],"type":"Point"}
}