{
  "type": "Feature",
  "properties": {
    "addr:full":"Tervantstraat 2ba Beringen Limburg 3583",
    "addr:housenumber":"2ba",
    "addr:postcode":"3583",
    "addr:street":"Tervantstraat",
    "iso:country":"BE",
    "sg:address":"Tervantstraat 2ba",
    "sg:city":"Beringen",
    "sg:orig_category":"Ramassage and traitement des d\u00e9chets m\u00e9nagers",
    "sg:phone":"+32 11 45 30 94",
    "sg:postcode":"3583",
    "sg:province":"Limburg",
    "wof:name":"B & A Plastics",
    "wof:placetype":"venue"
},
  "geometry": {"coordinates":[5.1706700325,51.0389442444],"type":"Point"}
}