{
  "type": "Feature",
  "properties": {
    "iso:country":"BE",
    "sg:address":"Rue Armand Campenhout 23-25",
    "sg:city":"Bruxelles (ixelles)",
    "sg:classifiers":[
        {
            "category":"Social Services",
            "subcategory":"Job Training",
            "type":"Services"
        }
    ],
    "sg:phone":"+32 2 534 72 21",
    "sg:postcode":"1050",
    "sg:province":"Bruxelles-Capitale",
    "sg:tags":[
        "personnel"
    ],
    "wof:name":"Middle East Management Centre",
    "wof:placetype":"venue"
},
  "geometry": {"coordinates":[4.3615860939,50.8242912292],"type":"Point"}
}