{
  "type": "Feature",
  "properties": {
    "iso:country":"BE",
    "sg:address":"Heiligkruisstraat 12",
    "sg:city":"Mortsel",
    "sg:classifiers":[
        {
            "category":"Arena",
            "subcategory":"Sports Club",
            "type":"Entertainment"
        }
    ],
    "sg:phone":"+32 3 449 18 75",
    "sg:postcode":"2640",
    "sg:province":"Antwerpen",
    "sg:tags":[
        "de"
    ],
    "wof:name":"Turnkring Deugd En Volharding",
    "wof:placetype":"venue"
},
  "geometry": {"coordinates":[4.4472780228,51.1711463928],"type":"Point"}
}