{
  "type": "Feature",
  "properties": {
    "addr:full":"Molenstraat 89 Gent Oost-Vlaanderen 9032",
    "addr:housenumber":"89",
    "addr:postcode":"9032",
    "addr:street":"Molenstraat;Oost-Vlaanderen",
    "iso:country":"BE",
    "sg:address":"Molenstraat 89",
    "sg:city":"Gent",
    "sg:orig_category":"Diverse bouwafwerking and reiniging",
    "sg:phone":"+32 9 253 21 69",
    "sg:postcode":"9032",
    "sg:province":"Oost-Vlaanderen",
    "wof:name":"Jean De Neve",
    "wof:placetype":"venue"
},
  "geometry": {"coordinates":[3.7162549496,51.0900535583],"type":"Point"}
}