{
  "type": "Feature",
  "properties": {
    "iso:country":"BE",
    "sg:address":"Avenue Baudelaire 6",
    "sg:city":"Wavre",
    "sg:orig_category":"Loodgieterij, verwarming and sanitaire installaties",
    "sg:phone":"+32 10 24 45 53",
    "sg:postcode":"1300",
    "sg:province":"Brabant Wallon",
    "wof:name":"De La Plombe Express",
    "wof:placetype":"venue"
},
  "geometry": {"coordinates":[4.6333990097,50.7125740051],"type":"Point"}
}