{
  "type": "Feature",
  "properties": {
    "addr:full":"Rostynedreef 36ba Aalter Oost-Vlaanderen 9880",
    "addr:postcode":"9880",
    "addr:street":"Rostynedreef;Oost-Vlaanderen",
    "iso:country":"BE",
    "sg:address":"Rostynedreef 36ba",
    "sg:city":"Aalter",
    "sg:orig_category":"Boekhouders",
    "sg:phone":"+32 9 374 14 78",
    "sg:postcode":"9880",
    "sg:province":"Oost-Vlaanderen",
    "wof:name":"Kurt Almey",
    "wof:placetype":"venue"
},
  "geometry": {"coordinates":[3.4732310772,51.0765724182],"type":"Point"}
}