{
  "type": "Feature",
  "properties": {
    "addr:full":"Staatsbaan 51 Zulte Oost-Vlaanderen 9870",
    "addr:housenumber":"51",
    "addr:postcode":"9870",
    "addr:street":"Staatsbaan",
    "iso:country":"BE",
    "sg:address":"Staatsbaan 51",
    "sg:city":"Zulte",
    "sg:classifiers":[
        {
            "category":"Food & Beverages",
            "subcategory":"Fruits & Vegetables",
            "type":"Retail Goods"
        }
    ],
    "sg:phone":"+32 9 388 65 03",
    "sg:postcode":"9870",
    "sg:province":"Oost-Vlaanderen",
    "sg:tags":[
        "-"
    ],
    "wof:name":"Fruitpoort (de)",
    "wof:placetype":"venue"
},
  "geometry": {"coordinates":[3.4483420849,50.9244422913],"type":"Point"}
}