{
  "type": "Feature",
  "properties": {
    "iso:country":"BE",
    "sg:address":"Henri Cartonstraat 12",
    "sg:city":"Ieper",
    "sg:classifiers":[
        {
            "category":"Health Services",
            "subcategory":"Doctor",
            "type":"Services"
        }
    ],
    "sg:phone":"+32 57 20 12 40",
    "sg:postcode":"8900",
    "sg:province":"West-Vlaanderen",
    "sg:tags":[
        "medicinephysicians",
        "surgeon"
    ],
    "wof:name":"Bourgeois C.j.",
    "wof:placetype":"venue"
},
  "geometry": {"coordinates":[2.8880560398,50.8531608582],"type":"Point"}
}