{
  "type": "Feature",
  "properties": {
    "addr:full":"Dorpsstraat 15 Peer (grote Brogel) Limburg 3990",
    "addr:housenumber":"15",
    "addr:postcode":"3990",
    "addr:street":"Dorpsstraat;Grote Brogel Limburg",
    "iso:country":"BE",
    "sg:address":"Dorpsstraat 15",
    "sg:city":"Peer (grote Brogel)",
    "sg:classifiers":[
        {
            "category":"Fast Food",
            "type":"Food & Drink"
        }
    ],
    "sg:phone":"+32 11 63 37 23",
    "sg:postcode":"3990",
    "sg:province":"Limburg",
    "sg:tags":[
        "fried",
        "stand",
        "potato"
    ],
    "wof:name":"Brigitte",
    "wof:placetype":"venue"
},
  "geometry": {"coordinates":[5.5056462288,51.1536750793],"type":"Point"}
}