{
  "type": "Feature",
  "properties": {
    "addr:full":"Guido Gezellestraat 27 Oostkamp West-Vlaanderen 8020",
    "addr:housenumber":"27",
    "addr:postcode":"8020",
    "addr:street":"Guido Gezellestraat",
    "iso:country":"BE",
    "sg:address":"Guido Gezellestraat 27",
    "sg:city":"Oostkamp",
    "sg:classifiers":[
        {
            "category":"Utilities",
            "subcategory":"Telephone",
            "type":"Services"
        }
    ],
    "sg:phone":"+32 50 84 22 01",
    "sg:postcode":"8020",
    "sg:province":"West-Vlaanderen",
    "sg:tags":[
        "-",
        "internet"
    ],
    "wof:name":"Itecom Bvba",
    "wof:placetype":"venue"
},
  "geometry": {"coordinates":[3.2395620346,51.1564254761],"type":"Point"}
}