{
  "type": "Feature",
  "properties": {
    "addr:full":"J.b. Van Monsstraat 21 Leuven Vlaams-Brabant 3000",
    "addr:housenumber":"21",
    "addr:postcode":"3000",
    "addr:street":"J.B. Van Monsstraat",
    "iso:country":"BE",
    "sg:address":"J.b. Van Monsstraat 21",
    "sg:city":"Leuven",
    "sg:orig_category":"M\u00e9decins and sp\u00e9cialistes",
    "sg:phone":"+32 16 23 53 35",
    "sg:postcode":"3000",
    "sg:province":"Vlaams-Brabant",
    "wof:name":"Monique Raes",
    "wof:placetype":"venue"
},
  "geometry": {"coordinates":[4.7077140808,50.8829612732],"type":"Point"}
}