{
  "type": "Feature",
  "properties": {
    "iso:country":"BE",
    "sg:address":"Rostal 12",
    "sg:city":"Grobbendonk",
    "sg:orig_category":"Plomberie, chauffage and installations sanitaires",
    "sg:phone":"+32 14 50 29 41",
    "sg:postcode":"2288",
    "sg:province":"Antwerpen",
    "wof:name":"Onderh. Centr. Verw. 2000",
    "wof:placetype":"venue"
},
  "geometry": {"coordinates":[4.7584228516,51.161819458],"type":"Point"}
}