{
  "type": "Feature",
  "properties": {
    "addr:full":"Rue Des Mauvaises-vignes 59 Li\u00e8ge 1 (ch\u00ean\u00e9e) Li\u00e8ge 4032",
    "addr:housenumber":"59;1",
    "addr:postcode":"4032",
    "addr:street":"Rue Des Mauvaises-Vignes",
    "iso:country":"BE",
    "sg:address":"Rue Des Mauvaises-vignes 59",
    "sg:city":"Li\u00e8ge 1 (ch\u00ean\u00e9e)",
    "sg:classifiers":[
        {
            "category":"Health Services",
            "subcategory":"Doctor",
            "type":"Services"
        }
    ],
    "sg:phone":"+32 4 365 30 75",
    "sg:postcode":"4032",
    "sg:province":"Li\u00e8ge",
    "sg:tags":[
        "medicinephysicians",
        "surgeon"
    ],
    "wof:name":"Gouzou M",
    "wof:placetype":"venue"
},
  "geometry": {"coordinates":[5.6176729202,50.6168403625],"type":"Point"}
}