{
  "type": "Feature",
  "properties": {
    "addr:full":"Broekveldstraat 67 Erpe-mere (mere) Oost-Vlaanderen 9420",
    "addr:housenumber":"67",
    "addr:postcode":"9420",
    "addr:street":"Broekveldstraat;Mere Oost-Vlaanderen",
    "iso:country":"BE",
    "sg:address":"Broekveldstraat 67",
    "sg:city":"Erpe-mere (mere)",
    "sg:classifiers":[
        {
            "category":"Building & Trades",
            "subcategory":"Construction",
            "type":"Services"
        }
    ],
    "sg:phone":"+32 53 83 73 68",
    "sg:postcode":"9420",
    "sg:province":"Oost-Vlaanderen",
    "sg:tags":[
        "carpenter"
    ],
    "wof:name":"Vijverman E",
    "wof:placetype":"venue"
},
  "geometry": {"coordinates":[3.9685869217,50.9134521484],"type":"Point"}
}