{
  "type": "Feature",
  "properties": {
    "iso:country":"BE",
    "sg:address":"Groot-bijgaardenstraat 245",
    "sg:city":"Sint-agatha-berchem/berchem-sainte-agathe",
    "sg:orig_category":"Radioproductie and uitzendingen",
    "sg:phone":"+32 2 465 09 64",
    "sg:postcode":"1082",
    "sg:province":"Bruxelles-Capitale",
    "wof:name":"Radio Ring",
    "wof:placetype":"venue"
},
  "geometry": {"coordinates":[4.2957940102,50.8601646423],"type":"Point"}
}