{
  "type": "Feature",
  "properties": {
    "iso:country":"BE",
    "sg:address":"Rue Saint-martin 3",
    "sg:city":"Leuze-en-hainaut",
    "sg:orig_category":"Algemeen secundair onderwijs",
    "sg:phone":"+32 69 66 56 50",
    "sg:postcode":"7900",
    "sg:province":"Hainaut",
    "wof:name":"Ecole St.fran\u00c7ois Sales",
    "wof:placetype":"venue"
},
  "geometry": {"coordinates":[3.6261489391,50.5993309021],"type":"Point"}
}