{
  "type": "Feature",
  "properties": {
    "addr:full":"Rue Picard 68 Bruxelles (molenbeek-saint-jean) Bruxelles-Capitale 1080",
    "addr:housenumber":"68",
    "addr:postcode":"1080",
    "addr:street":"Rue Picard",
    "iso:country":"BE",
    "sg:address":"Rue Picard 68",
    "sg:city":"Bruxelles (molenbeek-saint-jean)",
    "sg:classifiers":[
        {
            "category":"Manufacturing",
            "subcategory":"Tools & Machinery",
            "type":"Manufacturing & Wholesale Goods"
        }
    ],
    "sg:phone":"+32 2 428 71 28",
    "sg:postcode":"1080",
    "sg:province":"Bruxelles-Capitale",
    "sg:tags":[
        "-"
    ],
    "wof:name":"Van Waasdijk Sa",
    "wof:placetype":"venue"
},
  "geometry": {"coordinates":[4.3452410698,50.8635368347],"type":"Point"}
}