{
  "type": "Feature",
  "properties": {
    "addr:full":"Latemstraat 68bb Sint-martens-latem Oost-Vlaanderen 9830",
    "addr:housenumber":"68bb",
    "addr:postcode":"9830",
    "addr:street":"Latemstraat",
    "iso:country":"BE",
    "sg:address":"Latemstraat 68bb",
    "sg:city":"Sint-martens-latem",
    "sg:orig_category":"Banques and organismes de cr\u00e9dit",
    "sg:phone":"+32 9 282 54 44",
    "sg:postcode":"9830",
    "sg:province":"Oost-Vlaanderen",
    "wof:name":"Kbc",
    "wof:placetype":"venue"
},
  "geometry": {"coordinates":[3.6321051121,51.0166397095],"type":"Point"}
}