{
  "type": "Feature",
  "properties": {
    "addr:full":"Avenue Des Pl\u00c9iades 19 Sint-lambrechts-woluwe/woluwe-saint-lambert Bruxelles-Capitale 1200",
    "addr:housenumber":"19",
    "addr:postcode":"1200",
    "addr:street":"Avenue Des Ple\u0301Iades",
    "iso:country":"BE",
    "sg:address":"Avenue Des Pl\u00c9iades 19",
    "sg:city":"Sint-lambrechts-woluwe/woluwe-saint-lambert",
    "sg:classifiers":[
        {
            "category":"Insurance",
            "subcategory":"Life Insurance",
            "type":"Services"
        }
    ],
    "sg:phone":"+32 2 772 58 58",
    "sg:postcode":"1200",
    "sg:province":"Bruxelles-Capitale",
    "sg:tags":[
        "assurance"
    ],
    "wof:name":"American Re-insurance Cy",
    "wof:placetype":"venue"
},
  "geometry": {"coordinates":[4.4190731049,50.8543243408],"type":"Point"}
}