{
  "type": "Feature",
  "properties": {
    "iso:country":"BE",
    "sg:address":"Groeneweg 29",
    "sg:city":"Lebbeke",
    "sg:orig_category":"Brood, gebak and snoepgoed",
    "sg:phone":"+32 53 77 51 42",
    "sg:postcode":"9280",
    "sg:province":"Oost-Vlaanderen",
    "wof:name":"Huis Dooms",
    "wof:placetype":"venue"
},
  "geometry": {"coordinates":[4.0880250931,50.9789505005],"type":"Point"}
}