{
  "type": "Feature",
  "properties": {
    "iso:country":"BE",
    "sg:address":"Nieuwbeekstraat 82",
    "sg:city":"Aalst",
    "sg:orig_category":"Plaatsen van vloer- and muurbekleding Schilders Verlichting and huishoudartikelen",
    "sg:phone":"+32 53 78 39 48",
    "sg:postcode":"9300",
    "sg:province":"Oost-Vlaanderen",
    "wof:name":"Tempera",
    "wof:placetype":"venue"
},
  "geometry": {"coordinates":[4.0317759514,50.934261322],"type":"Point"}
}