{
  "type": "Feature",
  "properties": {
    "addr:full":"Rue Evieux 51 Esneux Li\u00e8ge 4130",
    "addr:housenumber":"51",
    "addr:postcode":"4130",
    "addr:street":"Rue Evieux",
    "iso:country":"BE",
    "sg:address":"Rue Evieux 51",
    "sg:city":"Esneux",
    "sg:classifiers":[
        {
            "category":"Arena",
            "subcategory":"Sports Club",
            "type":"Entertainment"
        }
    ],
    "sg:phone":"+32 4 380 03 01",
    "sg:postcode":"4130",
    "sg:province":"Li\u00e8ge",
    "wof:name":"Club P\u00e9tanque Esneutois",
    "wof:placetype":"venue"
},
  "geometry": {"coordinates":[5.5711398125,50.524181366],"type":"Point"}
}