{
  "type": "Feature",
  "properties": {
    "iso:country":"BE",
    "sg:address":"Idegemplein 11",
    "sg:city":"Geraardsbergen",
    "sg:orig_category":"Dakwerken",
    "sg:phone":"+32 54 50 04 86",
    "sg:postcode":"9506",
    "sg:province":"Oost-Vlaanderen",
    "wof:name":"Danny Collyns",
    "wof:placetype":"venue"
},
  "geometry": {"coordinates":[3.8985300064,50.7987060547],"type":"Point"}
}