{
  "type": "Feature",
  "properties": {
    "iso:country":"BE",
    "sg:address":"Rue De La Tourette 26",
    "sg:city":"Gerpinnes",
    "sg:orig_category":"Installation \u00e9lectrique r\u00e9sidentielle",
    "sg:phone":"+32 71 50 58 74",
    "sg:postcode":"6280",
    "sg:province":"Hainaut",
    "wof:name":"Quentin De Rouck",
    "wof:placetype":"venue"
},
  "geometry": {"coordinates":[4.577922821,50.3548240662],"type":"Point"}
}