{
  "type": "Feature",
  "properties": {
    "addr:full":"Veldstraat 11 Meerhout Antwerpen 2450",
    "addr:housenumber":"11",
    "addr:postcode":"2450",
    "addr:street":"Veldstraat",
    "iso:country":"BE",
    "sg:address":"Veldstraat 11",
    "sg:city":"Meerhout",
    "sg:orig_category":"Brood, gebak and snoepgoed",
    "sg:phone":"+32 14 30 14 10",
    "sg:postcode":"2450",
    "sg:province":"Antwerpen",
    "wof:name":"Christine",
    "wof:placetype":"venue"
},
  "geometry": {"coordinates":[5.0792322159,51.1320648193],"type":"Point"}
}