{
  "type": "Feature",
  "properties": {
    "iso:country":"BE",
    "sg:address":"Ingooigemstraat 28",
    "sg:city":"Zwevegem (otegem)",
    "sg:classifiers":[
        {
            "category":"Building & Trades",
            "subcategory":"Landscaping Services",
            "type":"Services"
        }
    ],
    "sg:phone":"+32 56 77 51 34",
    "sg:postcode":"8553",
    "sg:province":"West-Vlaanderen",
    "sg:tags":[
        "gardening",
        "garden",
        "maintenance"
    ],
    "wof:name":"Vervaeke",
    "wof:placetype":"venue"
},
  "geometry": {"coordinates":[3.42831707,50.8088035583],"type":"Point"}
}