{
  "type": "Feature",
  "properties": {
    "addr:full":"Antoon Van Dijcklaan 28 Lier Antwerpen 2500",
    "addr:housenumber":"28",
    "addr:postcode":"2500",
    "addr:street":"Antoon Van Dijcklaan",
    "iso:country":"BE",
    "sg:address":"Antoon Van Dijcklaan 28",
    "sg:city":"Lier",
    "sg:classifiers":[
        {
            "category":"Cafe",
            "type":"Food & Drink"
        }
    ],
    "sg:phone":"+32 3 480 88 88",
    "sg:postcode":"2500",
    "sg:province":"Antwerpen",
    "sg:tags":[
        "caf\u00e9s"
    ],
    "wof:name":"Daniel Geuens",
    "wof:placetype":"venue"
},
  "geometry": {"coordinates":[4.5560951233,51.1310501099],"type":"Point"}
}