{
  "type": "Feature",
  "properties": {
    "addr:full":"Varkensmeersstraat 1 Ternat Vlaams-Brabant 1740",
    "addr:housenumber":"1",
    "addr:postcode":"1740",
    "addr:street":"Varkensmeersstraat",
    "iso:country":"BE",
    "sg:address":"Varkensmeersstraat 1",
    "sg:city":"Ternat",
    "sg:classifiers":[
        {
            "category":"Wholesale",
            "subcategory":"Sporting Goods",
            "type":"Manufacturing & Wholesale Goods"
        }
    ],
    "sg:phone":"+32 2 582 08 07",
    "sg:postcode":"1740",
    "sg:province":"Vlaams-Brabant",
    "sg:tags":[
        "sport-",
        "kampeermateriaal"
    ],
    "wof:name":"Cortes",
    "wof:placetype":"venue"
},
  "geometry": {"coordinates":[4.1778049469,50.8712501526],"type":"Point"}
}