{
  "type": "Feature",
  "properties": {
    "iso:country":"BE",
    "sg:address":"Kerkstraat 23",
    "sg:city":"Landen",
    "sg:classifiers":[
        {
            "category":"Health Services",
            "subcategory":"Health Practitioner",
            "type":"Services"
        }
    ],
    "sg:phone":"+32 11 88 14 67",
    "sg:postcode":"3400",
    "sg:province":"Vlaams-Brabant",
    "sg:tags":[
        "physiotherapist"
    ],
    "wof:name":"Vandermeulen Sigrid",
    "wof:placetype":"venue"
},
  "geometry": {"coordinates":[5.0801229477,50.75573349],"type":"Point"}
}