{
  "type": "Feature",
  "properties": {
    "addr:full":"Rue De Dampremy 67 Charleroi Hainaut 6000",
    "addr:housenumber":"67",
    "addr:postcode":"6000",
    "addr:street":"Rue De Dampremy;Hainaut",
    "iso:country":"BE",
    "sg:address":"Rue De Dampremy 67",
    "sg:city":"Charleroi",
    "sg:classifiers":[
        {
            "category":"Food & Beverages",
            "subcategory":"Cheese",
            "type":"Retail Goods"
        }
    ],
    "sg:phone":"+32 71 31 81 79",
    "sg:postcode":"6000",
    "sg:province":"Hainaut",
    "sg:tags":[
        "-"
    ],
    "wof:name":"Mandenac Sa",
    "wof:placetype":"venue"
},
  "geometry": {"coordinates":[4.4404392242,50.4092483521],"type":"Point"}
}