{
  "type": "Feature",
  "properties": {
    "iso:country":"BE",
    "sg:address":"Rue Des Cinq Etoiles 5ba",
    "sg:city":"Perwez",
    "sg:orig_category":"Plomberie, chauffage and installations sanitaires",
    "sg:phone":"+32 81 64 04 60",
    "sg:postcode":"1360",
    "sg:province":"Brabant Wallon",
    "wof:name":"Dewez & Fils",
    "wof:placetype":"venue"
},
  "geometry": {"coordinates":[4.7633099556,50.6038513184],"type":"Point"}
}