{
  "type": "Feature",
  "properties": {
    "addr:full":"Neerstraat 50 Brakel Oost-Vlaanderen 9660",
    "addr:housenumber":"50",
    "addr:postcode":"9660",
    "addr:street":"Neerstraat",
    "iso:country":"BE",
    "sg:address":"Neerstraat 50",
    "sg:city":"Brakel",
    "sg:orig_category":"Activit\u00e9s d\u00b4action sociale sans h\u00e9bergement. M\u00e9decins and sp\u00e9cialistes",
    "sg:phone":"+32 55 42 32 32",
    "sg:postcode":"9660",
    "sg:province":"Oost-Vlaanderen",
    "wof:name":"Willem Van Den Dooren",
    "wof:placetype":"venue"
},
  "geometry": {"coordinates":[3.7671580315,50.8045463562],"type":"Point"}
}