{
  "type": "Feature",
  "properties": {
    "addr:full":"Vaartstraat 126 Ranst Antwerpen 2520",
    "addr:housenumber":"126",
    "addr:postcode":"2520",
    "addr:street":"Vaartstraat",
    "iso:country":"BE",
    "sg:address":"Vaartstraat 126",
    "sg:city":"Ranst",
    "sg:orig_category":"Betonnen bouwelementen Fab",
    "sg:phone":"+32 3 457 00 08",
    "sg:postcode":"2520",
    "sg:province":"Antwerpen",
    "wof:name":"Socea",
    "wof:placetype":"venue"
},
  "geometry": {"coordinates":[4.579305172,51.2046928406],"type":"Point"}
}