{
  "type": "Feature",
  "properties": {
    "iso:country":"BE",
    "sg:address":"Rue De Li\u00c8ge 127",
    "sg:city":"Oupeye",
    "sg:orig_category":"Charpentes and couvertures",
    "sg:phone":"+32 4 379 30 35",
    "sg:postcode":"4684",
    "sg:province":"Li\u00e8ge",
    "wof:name":"Henquet Jean & Fils",
    "wof:placetype":"venue"
},
  "geometry": {"coordinates":[5.6688899994,50.7276992798],"type":"Point"}
}