{
  "type": "Feature",
  "properties": {
    "iso:country":"BE",
    "sg:address":"Oud Arenberg 38",
    "sg:city":"Beveren",
    "sg:orig_category":"Fietsen",
    "sg:phone":"+32 3 773 41 06",
    "sg:postcode":"9130",
    "sg:province":"Oost-Vlaanderen",
    "wof:name":"Hector Lambrechts",
    "wof:placetype":"venue"
},
  "geometry": {"coordinates":[4.1798682213,51.2886199951],"type":"Point"}
}