{
  "type": "Feature",
  "properties": {
    "iso:country":"BE",
    "sg:address":"Felix Verhaeghestraat 8",
    "sg:city":"Waregem",
    "sg:classifiers":[
        {
            "category":"Professional",
            "subcategory":"Management & Consulting",
            "type":"Services"
        }
    ],
    "sg:phone":"+32 56 60 64 19",
    "sg:postcode":"8790",
    "sg:province":"West-Vlaanderen",
    "sg:tags":[
        "-",
        "processing",
        "data",
        "consultant"
    ],
    "wof:name":"L V B Consulting Cv",
    "wof:placetype":"venue"
},
  "geometry": {"coordinates":[3.4409370422,50.882610321],"type":"Point"}
}