{
  "type": "Feature",
  "properties": {
    "addr:full":"Oude Baan 120 Beringen Limburg 3580",
    "addr:housenumber":"120",
    "addr:postcode":"3580",
    "addr:street":"Oude Baan",
    "iso:country":"BE",
    "sg:address":"Oude Baan 120",
    "sg:city":"Beringen",
    "sg:classifiers":[
        {
            "category":"Arena",
            "subcategory":"Sports Club",
            "type":"Entertainment"
        }
    ],
    "sg:phone":"+32 476 50 93 18",
    "sg:postcode":"3580",
    "sg:province":"Limburg",
    "sg:tags":[
        "de"
    ],
    "wof:name":"W.s.c. Molenheide",
    "wof:placetype":"venue"
},
  "geometry": {"coordinates":[5.2036738396,51.0416259766],"type":"Point"}
}