{
  "type": "Feature",
  "properties": {
    "iso:country":"BE",
    "sg:address":"Schurhovenveld 3844",
    "sg:city":"Sint-truiden",
    "sg:classifiers":[
        {
            "category":"Autos & Motor Vehicles",
            "subcategory":"Automobile Sales",
            "type":"Retail Goods"
        }
    ],
    "sg:phone":"+32 11 69 54 50",
    "sg:postcode":"3800",
    "sg:province":"Limburg",
    "sg:tags":[
        "car",
        "used",
        "-"
    ],
    "wof:name":"Lemmens Motors Nv",
    "wof:placetype":"venue"
},
  "geometry": {"coordinates":[5.1863641739,50.8153343201],"type":"Point"}
}