{
  "type": "Feature",
  "properties": {
    "iso:country":"BE",
    "sg:address":"Rue Belle Vue 7",
    "sg:city":"Anthisnes",
    "sg:orig_category":"Entretien and r\u00e9parations de voitures",
    "sg:phone":"+32 4 383 69 72",
    "sg:postcode":"4160",
    "sg:province":"Li\u00e8ge",
    "wof:name":"Pierre Philippe",
    "wof:placetype":"venue"
},
  "geometry": {"coordinates":[5.5232248306,50.4852485657],"type":"Point"}
}