{
  "type": "Feature",
  "properties": {
    "addr:full":"Vredelaan 27 Blankenberge West-Vlaanderen 8370",
    "addr:housenumber":"27",
    "addr:postcode":"8370",
    "addr:street":"Vredelaan",
    "iso:country":"BE",
    "sg:address":"Vredelaan 27",
    "sg:city":"Blankenberge",
    "sg:orig_category":"Protection civile",
    "sg:phone":"+32 50 41 10 46",
    "sg:postcode":"8370",
    "sg:province":"West-Vlaanderen",
    "wof:name":"Brandweerkazerne",
    "wof:placetype":"venue"
},
  "geometry": {"coordinates":[3.1221730709,51.3098754883],"type":"Point"}
}