{
  "type": "Feature",
  "properties": {
    "iso:country":"BE",
    "sg:address":"Meulebeeksesteenweg 22",
    "sg:city":"Tielt",
    "sg:classifiers":[
        {
            "category":"Home & Garden",
            "subcategory":"Building Materials",
            "type":"Retail Goods"
        }
    ],
    "sg:phone":"+32 51 40 70 72",
    "sg:postcode":"8700",
    "sg:province":"West-Vlaanderen",
    "sg:tags":[
        "window",
        "plastic"
    ],
    "wof:name":"Vertirama B.v.b.a.",
    "wof:placetype":"venue"
},
  "geometry": {"coordinates":[3.3135039806,50.9833297729],"type":"Point"}
}