{
  "type": "Feature",
  "properties": {
    "addr:full":"Broekstraat 27 Diest (molenstede) Vlaams-Brabant 3294",
    "addr:housenumber":"27",
    "addr:postcode":"3294",
    "addr:street":"Broekstraat",
    "iso:country":"BE",
    "sg:address":"Broekstraat 27",
    "sg:city":"Diest (molenstede)",
    "sg:classifiers":[
        {
            "category":"Social Services",
            "subcategory":"Job Training",
            "type":"Services"
        }
    ],
    "sg:phone":"+32 13 33 53 33",
    "sg:postcode":"3294",
    "sg:province":"Vlaams-Brabant",
    "sg:tags":[
        "condiment",
        "spice"
    ],
    "wof:name":"Hendrickx R Nv",
    "wof:placetype":"venue"
},
  "geometry": {"coordinates":[5.0149478912,51.0009651184],"type":"Point"}
}