{
  "type": "Feature",
  "properties": {
    "addr:full":"Botassart 14 Ucimont Luxembourg 6833",
    "addr:housenumber":"14",
    "addr:postcode":"6833",
    "addr:street":"Botassart",
    "iso:country":"BE",
    "sg:address":"Botassart 14",
    "sg:city":"Ucimont",
    "sg:classifiers":[
        {
            "category":"Building & Trades",
            "subcategory":"Construction",
            "type":"Services"
        }
    ],
    "sg:phone":"+32 61 46 67 82",
    "sg:postcode":"6833",
    "sg:province":"Luxembourg",
    "sg:tags":[
        "industrial",
        "timber"
    ],
    "wof:name":"Poncin J. S.a.",
    "wof:placetype":"venue"
},
  "geometry": {"coordinates":[5.0365228653,49.865940094],"type":"Point"}
}