{
  "type": "Feature",
  "properties": {
    "addr:full":"Bossenstraat 26 Lint Antwerpen 2547",
    "addr:housenumber":"26",
    "addr:postcode":"2547",
    "addr:street":"Bossenstraat",
    "iso:country":"BE",
    "sg:address":"Bossenstraat 26",
    "sg:city":"Lint",
    "sg:orig_category":"Diepvriesproducten Gh Vleesproductie and -conservering Fab",
    "sg:phone":"+32 3 454 04 20",
    "sg:postcode":"2547",
    "sg:province":"Antwerpen",
    "wof:name":"Lintor",
    "wof:placetype":"venue"
},
  "geometry": {"coordinates":[4.4870319366,51.1171150208],"type":"Point"}
}