{
  "type": "Feature",
  "properties": {
    "iso:country":"BE",
    "sg:address":"Krijgsbaan 46",
    "sg:city":"Wijnegem",
    "sg:orig_category":"Sportclubs",
    "sg:phone":"+32 3 354 06 68",
    "sg:postcode":"2110",
    "sg:province":"Antwerpen",
    "wof:name":"Kon. Minerva K.c.",
    "wof:placetype":"venue"
},
  "geometry": {"coordinates":[4.4969358444,51.2197113037],"type":"Point"}
}