{
  "type": "Feature",
  "properties": {
    "addr:full":"Kortrijkstraat 22 Zwevegem West-Vlaanderen 8550",
    "addr:housenumber":"22",
    "addr:postcode":"8550",
    "addr:street":"Kortrijkstraat",
    "iso:country":"BE",
    "sg:address":"Kortrijkstraat 22",
    "sg:city":"Zwevegem",
    "sg:classifiers":[
        {
            "category":"Autos & Motor Vehicles",
            "subcategory":"Automobile Sales",
            "type":"Retail Goods"
        }
    ],
    "sg:phone":"+32 56 75 87 00",
    "sg:postcode":"8550",
    "sg:province":"West-Vlaanderen",
    "sg:tags":[
        "ceremony",
        "car"
    ],
    "wof:name":"Gerrit Cars Bvba",
    "wof:placetype":"venue"
},
  "geometry": {"coordinates":[3.3299369812,50.812953949],"type":"Point"}
}