{
  "type": "Feature",
  "properties": {
    "addr:full":"Rue 113e Reg. Infanterie 123ba Musson Luxembourg 6750",
    "addr:postcode":"6750",
    "addr:street":"Rue 113E Reg. Infanterie 123Ba",
    "iso:country":"BE",
    "sg:address":"Rue 113e Reg. Infanterie 123ba",
    "sg:city":"Musson",
    "sg:classifiers":[
        {
            "category":"Arena",
            "subcategory":"Sports Club",
            "type":"Entertainment"
        }
    ],
    "sg:phone":"+32 63 58 36 97",
    "sg:postcode":"6750",
    "sg:province":"Luxembourg",
    "sg:tags":[
        "de"
    ],
    "wof:name":"V.c. Stabulois",
    "wof:placetype":"venue"
},
  "geometry": {"coordinates":[5.6432609558,49.5480155945],"type":"Point"}
}