{
  "type": "Feature",
  "properties": {
    "iso:country":"BE",
    "sg:address":"Ruitersweg 2-4",
    "sg:city":"Brugge (sint-michiels)",
    "sg:classifiers":[
        {
            "category":"Building & Trades",
            "subcategory":"Electrical",
            "type":"Services"
        }
    ],
    "sg:phone":"+32 50 40 65 01",
    "sg:postcode":"8200",
    "sg:province":"West-Vlaanderen",
    "sg:tags":[
        "-",
        "electric",
        "contractor"
    ],
    "wof:name":"Verbandt R",
    "wof:placetype":"venue"
},
  "geometry": {"coordinates":[3.1904699802,51.1992111206],"type":"Point"}
}