{
  "type": "Feature",
  "properties": {
    "iso:country":"BE",
    "sg:address":"Chauss\u00c9e De Soignies 12",
    "sg:city":"Silly",
    "sg:orig_category":"R\u00e9alisation de programmes and logiciels. Conseils en syst\u00e8mes informatiques",
    "sg:phone":"+32 2 395 46 26",
    "sg:postcode":"7830",
    "sg:province":"Hainaut",
    "wof:name":"Worldsites Brussels",
    "wof:placetype":"venue"
},
  "geometry": {"coordinates":[3.9024889469,50.6475601196],"type":"Point"}
}