{
  "type": "Feature",
  "properties": {
    "iso:country":"BE",
    "sg:address":"Brusselsesteenweg 281",
    "sg:city":"Wetteren",
    "sg:orig_category":"Fast food and meeneem restaurants Restaurants Ruimtes voor conferenties, recepties and feesten",
    "sg:phone":"+32 9 366 69 74",
    "sg:postcode":"9230",
    "sg:province":"Oost-Vlaanderen",
    "wof:name":"L. Da Vinci",
    "wof:placetype":"venue"
},
  "geometry": {"coordinates":[3.8486039639,50.9827003479],"type":"Point"}
}