{
  "type": "Feature",
  "properties": {
    "addr:full":"Hinnebilkstraat 1b3 Ingelmunster West-Vlaanderen 8770",
    "addr:housenumber":"1b3",
    "addr:postcode":"8770",
    "addr:street":"Hinnebilkstraat",
    "iso:country":"BE",
    "sg:address":"Hinnebilkstraat 1b3",
    "sg:city":"Ingelmunster",
    "sg:orig_category":"Sociale huisvestingsmaatschappijen",
    "sg:phone":"+32 51 30 25 45",
    "sg:postcode":"8770",
    "sg:province":"West-Vlaanderen",
    "wof:name":"De Mandelbeek",
    "wof:placetype":"venue"
},
  "geometry": {"coordinates":[3.2565500736,50.9230766296],"type":"Point"}
}