{
  "type": "Feature",
  "properties": {
    "iso:country":"BE",
    "sg:address":"Turkeijensteenweg 3",
    "sg:city":"Pittem",
    "sg:classifiers":[
        {
            "category":"Restaurant",
            "type":"Food & Drink"
        }
    ],
    "sg:phone":"+32 51 46 78 57",
    "sg:postcode":"8740",
    "sg:province":"West-Vlaanderen",
    "wof:name":"De Peerdekens",
    "wof:placetype":"venue"
},
  "geometry": {"coordinates":[3.2771000862,51.0147781372],"type":"Point"}
}