{
  "type": "Feature",
  "properties": {
    "addr:full":"Vrijheid 93 Arendonk Antwerpen 2370",
    "addr:housenumber":"93",
    "addr:postcode":"2370",
    "addr:street":"Vrijheid",
    "iso:country":"BE",
    "sg:address":"Vrijheid 93",
    "sg:city":"Arendonk",
    "sg:classifiers":[
        {
            "category":"Education",
            "subcategory":"School",
            "type":"Public Place"
        }
    ],
    "sg:phone":"+32 14 67 73 19",
    "sg:postcode":"2370",
    "sg:province":"Antwerpen",
    "sg:tags":[
        "supply"
    ],
    "wof:name":"Hulselmans A",
    "wof:placetype":"venue"
},
  "geometry": {"coordinates":[5.0910210609,51.3218307495],"type":"Point"}
}