{
  "type": "Feature",
  "properties": {
    "iso:country":"BE",
    "sg:address":"Chauss\u00c9e D'alsemberg 1069",
    "sg:city":"Ukkel/uccle",
    "sg:orig_category":"Assurances. Bureaux de poste",
    "sg:phone":"+32 2 332 09 46",
    "sg:postcode":"1180",
    "sg:province":"Bruxelles-Capitale",
    "wof:name":"La Poste",
    "wof:placetype":"venue"
},
  "geometry": {"coordinates":[4.3320169449,50.7909889221],"type":"Point"}
}