{
  "type": "Feature",
  "properties": {
    "iso:country":"BE",
    "sg:address":"Rue Abb\u00c9 Dossogne 69",
    "sg:city":"Stavelot",
    "sg:orig_category":"Jardinage",
    "sg:phone":"+32 87 27 55 91",
    "sg:postcode":"4970",
    "sg:province":"Li\u00e8ge",
    "wof:name":"Olivier Piette",
    "wof:placetype":"venue"
},
  "geometry": {"coordinates":[5.930850029,50.3942909241],"type":"Point"}
}