{
  "type": "Feature",
  "properties": {
    "addr:full":"Stationsstraat 10 De Pinte Oost-Vlaanderen 9840",
    "addr:housenumber":"10",
    "addr:postcode":"9840",
    "addr:street":"Stationsstraat",
    "iso:country":"BE",
    "sg:address":"Stationsstraat 10",
    "sg:city":"De Pinte",
    "sg:classifiers":[
        {
            "category":"Cafe",
            "type":"Food & Drink"
        }
    ],
    "sg:phone":"+32 9 282 74 99",
    "sg:postcode":"9840",
    "sg:province":"Oost-Vlaanderen",
    "sg:tags":[
        "caf\u00e9s"
    ],
    "wof:name":"Abdelkader Agourram",
    "wof:placetype":"venue"
},
  "geometry": {"coordinates":[3.6494429111,50.9961204529],"type":"Point"}
}