{
  "type": "Feature",
  "properties": {
    "addr:full":"Boulevard Piercot 15 Li\u00c8ge Li\u00e8ge 4000",
    "addr:housenumber":"15",
    "addr:postcode":"4000",
    "addr:street":"Boulevard Piercot",
    "iso:country":"BE",
    "sg:address":"Boulevard Piercot 15",
    "sg:city":"Li\u00c8ge",
    "sg:classifiers":[
        {
            "category":"Personal",
            "subcategory":"Beauty Salon",
            "type":"Services"
        }
    ],
    "sg:phone":"+32 4 223 68 59",
    "sg:postcode":"4000",
    "sg:province":"Li\u00e8ge",
    "sg:tags":[
        "de",
        "coiffure"
    ],
    "wof:name":"Coiffure K'zan",
    "wof:placetype":"venue"
},
  "geometry": {"coordinates":[5.5715827942,50.6355934143],"type":"Point"}
}