{
  "type": "Feature",
  "properties": {
    "addr:full":"Korenarenstraat 100 Overijse Vlaams-Brabant 3090",
    "addr:housenumber":"100",
    "addr:postcode":"3090",
    "addr:street":"Korenarenstraat",
    "iso:country":"BE",
    "sg:address":"Korenarenstraat 100",
    "sg:city":"Overijse",
    "sg:classifiers":[
        {
            "category":"Building & Trades",
            "subcategory":"Landscaping Services",
            "type":"Services"
        }
    ],
    "sg:phone":"+32 2 687 42 05",
    "sg:postcode":"3090",
    "sg:province":"Vlaams-Brabant",
    "sg:tags":[
        "forestry"
    ],
    "wof:name":"Van Horenbeke H",
    "wof:placetype":"venue"
},
  "geometry": {"coordinates":[4.5252728462,50.7799797058],"type":"Point"}
}