{
  "type": "Feature",
  "properties": {
    "iso:country":"BE",
    "sg:address":"Rozenaaksesteenweg 60",
    "sg:city":"Ronse",
    "sg:orig_category":"Informaticaconsulenten",
    "sg:phone":"+32 55 20 94 04",
    "sg:postcode":"9600",
    "sg:province":"Oost-Vlaanderen",
    "wof:name":"Tofri",
    "wof:placetype":"venue"
},
  "geometry": {"coordinates":[3.5554850101,50.7490158081],"type":"Point"}
}