{
  "type": "Feature",
  "properties": {
    "addr:full":"Pannebekestraat 85 Brugge West-Vlaanderen 8000",
    "addr:housenumber":"85",
    "addr:postcode":"8000",
    "addr:street":"Pannebekestraat",
    "iso:country":"BE",
    "sg:address":"Pannebekestraat 85",
    "sg:city":"Brugge",
    "sg:orig_category":"Slagers",
    "sg:phone":"+32 50 33 28 31",
    "sg:postcode":"8000",
    "sg:province":"West-Vlaanderen",
    "wof:name":"Marc Decoene",
    "wof:placetype":"venue"
},
  "geometry": {"coordinates":[3.2349920273,51.2264404297],"type":"Point"}
}