{
  "type": "Feature",
  "properties": {
    "iso:country":"BE",
    "sg:address":"Kardinaalsstraat 8",
    "sg:city":"Brussel/bruxelles",
    "sg:orig_category":"Zalen voor culturele evenementen",
    "sg:phone":"+32 2 230 69 76",
    "sg:postcode":"1000",
    "sg:province":"Bruxelles-Capitale",
    "wof:name":"Th\u00c9\u00c2tre Hardtmachin",
    "wof:placetype":"venue"
},
  "geometry": {"coordinates":[4.3791880608,50.8495483398],"type":"Point"}
}