{
  "type": "Feature",
  "properties": {
    "iso:country":"BE",
    "sg:address":"Rue Du Camp Romain 29",
    "sg:city":"Dinant (furfooz)",
    "sg:classifiers":[
        {
            "category":"Professional",
            "subcategory":"Management & Consulting",
            "type":"Services"
        }
    ],
    "sg:phone":"+32 82 22 97 47",
    "sg:postcode":"5500",
    "sg:province":"Namur",
    "sg:tags":[
        "-",
        "processing",
        "data",
        "consultant"
    ],
    "wof:name":"Heliopolis Bvba",
    "wof:placetype":"venue"
},
  "geometry": {"coordinates":[4.9119329453,50.2604866028],"type":"Point"}
}