{
  "type": "Feature",
  "properties": {
    "addr:full":"Rue D\u00b4en-haut 47 Chaumont-gistoux Brabant Wallon 1325",
    "addr:housenumber":"47",
    "addr:postcode":"1325",
    "addr:street":"Rue D\u00b4En-Haut",
    "iso:country":"BE",
    "sg:address":"Rue D\u00b4en-haut 47",
    "sg:city":"Chaumont-gistoux",
    "sg:classifiers":[
        {
            "category":"Cafe",
            "type":"Food & Drink"
        }
    ],
    "sg:phone":"+32 10 68 06 72",
    "sg:postcode":"1325",
    "sg:province":"Brabant Wallon",
    "sg:tags":[
        "caf\u00e9s"
    ],
    "wof:name":"Invest Connexion Group",
    "wof:placetype":"venue"
},
  "geometry": {"coordinates":[4.7223548889,50.6729545593],"type":"Point"}
}