{
  "type": "Feature",
  "properties": {
    "addr:full":"Paul Gilsonstraat 10 Brugge West-Vlaanderen 8200",
    "addr:housenumber":"10",
    "addr:postcode":"8200",
    "addr:street":"Gilsonstraat",
    "iso:country":"BE",
    "sg:address":"Paul Gilsonstraat 10",
    "sg:city":"Brugge",
    "sg:orig_category":"Imprimeries and copyshops",
    "sg:phone":"+32 50 31 38 89",
    "sg:postcode":"8200",
    "sg:province":"West-Vlaanderen",
    "wof:name":"Marc Serruys",
    "wof:placetype":"venue"
},
  "geometry": {"coordinates":[3.1986289024,51.2082633972],"type":"Point"}
}