{
  "type": "Feature",
  "properties": {
    "iso:country":"BE",
    "sg:address":"Mechelbaan 253",
    "sg:city":"Putte",
    "sg:orig_category":"P\u00e9pini\u00e9ristes",
    "sg:phone":"+32 15 75 54 74",
    "sg:postcode":"2580",
    "sg:province":"Antwerpen",
    "wof:name":"Hugo Schroven",
    "wof:placetype":"venue"
},
  "geometry": {"coordinates":[4.650853157,51.0603408813],"type":"Point"}
}