{
  "type": "Feature",
  "properties": {
    "iso:country":"BE",
    "sg:address":"Eudore Pirmez Laan 11",
    "sg:city":"Etterbeek",
    "sg:classifiers":[
        {
            "category":"Travel",
            "subcategory":"Travel Agent",
            "type":"Entertainment"
        }
    ],
    "sg:phone":"+32 2 649 90 20",
    "sg:postcode":"1040",
    "sg:province":"Bruxelles-Capitale",
    "sg:tags":[
        "flash",
        "reisbureaus"
    ],
    "wof:name":"Flash Travel",
    "wof:placetype":"venue"
},
  "geometry": {"coordinates":[4.3894901276,50.830581665],"type":"Point"}
}