{
  "type": "Feature",
  "properties": {
    "iso:country":"BE",
    "sg:address":"Westhoeklaan 33",
    "sg:city":"De Panne",
    "sg:classifiers":[
        {
            "category":"Real Estate",
            "subcategory":"Real Estate Services",
            "type":"Services"
        }
    ],
    "sg:phone":"+32 58 41 17 73",
    "sg:postcode":"8660",
    "sg:province":"West-Vlaanderen",
    "wof:name":"Seavani",
    "wof:placetype":"venue"
},
  "geometry": {"coordinates":[2.5824110508,51.0937728882],"type":"Point"}
}