{
  "type": "Feature",
  "properties": {
    "addr:full":"Zwevezelestraat 83 Lichtervelde West-Vlaanderen 8810",
    "addr:housenumber":"83",
    "addr:postcode":"8810",
    "addr:street":"Zwevezelestraat",
    "iso:country":"BE",
    "sg:address":"Zwevezelestraat 83",
    "sg:city":"Lichtervelde",
    "sg:classifiers":[
        {
            "category":"Building & Trades",
            "subcategory":"Cleaning & Sanitation",
            "type":"Services"
        }
    ],
    "sg:phone":"+32 51 72 62 64",
    "sg:postcode":"8810",
    "sg:province":"West-Vlaanderen",
    "sg:tags":[
        "machine",
        "street",
        "maintenance"
    ],
    "wof:name":"Cools Dirk Bvba",
    "wof:placetype":"venue"
},
  "geometry": {"coordinates":[3.150908947,51.031463623],"type":"Point"}
}