{
  "type": "Feature",
  "properties": {
    "iso:country":"BE",
    "sg:address":"Place De Roly 26",
    "sg:city":"Philippeville",
    "sg:orig_category":"Enseignement maternel and primaire",
    "sg:phone":"+32 60 31 15 30",
    "sg:postcode":"5600",
    "sg:province":"Namur",
    "wof:name":"Ecole Fond. Communale",
    "wof:placetype":"venue"
},
  "geometry": {"coordinates":[4.5386238098,50.1353149414],"type":"Point"}
}