{
  "type": "Feature",
  "properties": {
    "addr:full":"Brugstraat 33 Berlare Oost-Vlaanderen 9290",
    "addr:housenumber":"33",
    "addr:postcode":"9290",
    "addr:street":"Brugstraat",
    "iso:country":"BE",
    "sg:address":"Brugstraat 33",
    "sg:city":"Berlare",
    "sg:orig_category":"Benzinestations and brandstoffen",
    "sg:phone":"+32 52 42 48 31",
    "sg:postcode":"9290",
    "sg:province":"Oost-Vlaanderen",
    "wof:name":"Tamam",
    "wof:placetype":"venue"
},
  "geometry": {"coordinates":[4.0064911842,51.0111351013],"type":"Point"}
}