{
  "type": "Feature",
  "properties": {
    "addr:full":"Gentbruggeaard 31 Gent (gentbrugge) Oost-Vlaanderen 9050",
    "addr:housenumber":"31",
    "addr:postcode":"9050",
    "addr:street":"Gentbruggeaard",
    "iso:country":"BE",
    "sg:address":"Gentbruggeaard 31",
    "sg:city":"Gent (gentbrugge)",
    "sg:classifiers":[
        {
            "category":"Health Services",
            "subcategory":"Health Practitioner",
            "type":"Services"
        }
    ],
    "sg:phone":"+32 9 231 44 82",
    "sg:postcode":"9050",
    "sg:province":"Oost-Vlaanderen",
    "sg:tags":[
        "physiotherapist"
    ],
    "wof:name":"Masschelein H",
    "wof:placetype":"venue"
},
  "geometry": {"coordinates":[3.7583620548,51.0463294983],"type":"Point"}
}