{
  "type": "Feature",
  "properties": {
    "iso:country":"BE",
    "sg:address":"Place Werth 6",
    "sg:city":"Eupen",
    "sg:classifiers":[
        {
            "category":"Personal",
            "subcategory":"Beauty Salon",
            "type":"Services"
        }
    ],
    "sg:phone":"+32 87 55 38 80",
    "sg:postcode":"4700",
    "sg:province":"Li\u00e8ge",
    "sg:tags":[
        "de",
        "coiffure"
    ],
    "wof:name":"City Hair International",
    "wof:placetype":"venue"
},
  "geometry": {"coordinates":[6.0386109352,50.6328964233],"type":"Point"}
}