{
  "type": "Feature",
  "properties": {
    "iso:country":"BE",
    "sg:address":"Galloperstraat 78",
    "sg:city":"Koksijde",
    "sg:orig_category":"Wind Deflectors",
    "sg:phone":"+32 57 48 59 79",
    "sg:postcode":"8670",
    "sg:province":"West-Vlaanderen",
    "wof:name":"Avalo B.v.b.a.",
    "wof:placetype":"venue"
},
  "geometry": {"coordinates":[2.6590800285,51.1083984375],"type":"Point"}
}