{
  "type": "Feature",
  "properties": {
    "iso:country":"BE",
    "sg:address":"Wulfsdam 13",
    "sg:city":"Ledegem",
    "sg:orig_category":"Rev\u00eatements pour sols and murs. Peinture",
    "sg:phone":"+32 56 50 20 38",
    "sg:postcode":"8880",
    "sg:province":"West-Vlaanderen",
    "wof:name":"Eric Vandewalle",
    "wof:placetype":"venue"
},
  "geometry": {"coordinates":[3.1333448887,50.8565864563],"type":"Point"}
}