{
  "type": "Feature",
  "properties": {
    "addr:full":"Avenue Circulaire 128 Ukkel/uccle Bruxelles-Capitale 1180",
    "addr:housenumber":"128",
    "addr:postcode":"1180",
    "addr:street":"Avenue Circulaire;/",
    "iso:country":"BE",
    "sg:address":"Avenue Circulaire 128",
    "sg:city":"Ukkel/uccle",
    "sg:orig_category":"D\u00e9corateurs d'int\u00e9rieur",
    "sg:phone":"+32 2 375 46 30",
    "sg:postcode":"1180",
    "sg:province":"Bruxelles-Capitale",
    "wof:name":"Alexandre Dumont",
    "wof:placetype":"venue"
},
  "geometry": {"coordinates":[4.3580579758,50.7959327698],"type":"Point"}
}