{
  "type": "Feature",
  "properties": {
    "addr:full":"Rummenweg 15 Sint-truiden Limburg 3800",
    "addr:housenumber":"15",
    "addr:postcode":"3800",
    "addr:street":"Rummenweg",
    "iso:country":"BE",
    "sg:address":"Rummenweg 15",
    "sg:city":"Sint-truiden",
    "sg:orig_category":"Beautyfarms, relaxatie and lichamelijk welzijn Schoonheidssalons",
    "sg:phone":"+32 11 67 49 69",
    "sg:postcode":"3800",
    "sg:province":"Limburg",
    "wof:name":"Inst. Masculin Feminin",
    "wof:placetype":"venue"
},
  "geometry": {"coordinates":[5.1836180687,50.8228302002],"type":"Point"}
}