{
  "type": "Feature",
  "properties": {
    "iso:country":"BE",
    "sg:address":"Chauss\u00e9e Paul Houtart 370",
    "sg:city":"La Louvi\u00e8re (houdeng-goegnies)",
    "sg:classifiers":[
        {
            "category":"Wholesale",
            "subcategory":"Sporting Goods",
            "type":"Manufacturing & Wholesale Goods"
        }
    ],
    "sg:phone":"+32 64 26 19 75",
    "sg:postcode":"7110",
    "sg:province":"Hainaut",
    "sg:tags":[
        "windsurfing",
        "accessory"
    ],
    "wof:name":"Brasseur Ets",
    "wof:placetype":"venue"
},
  "geometry": {"coordinates":[4.1519289017,50.4894218445],"type":"Point"}
}