{
  "type": "Feature",
  "properties": {
    "iso:country":"BE",
    "sg:address":"Brandeh\u00f6vel 20",
    "sg:city":"Kelmis",
    "sg:classifiers":[
        {
            "category":"Health Services",
            "subcategory":"Health Practitioner",
            "type":"Services"
        }
    ],
    "sg:phone":"+32 87 65 79 58",
    "sg:postcode":"4720",
    "sg:province":"Li\u00e8ge",
    "sg:tags":[
        "therapist",
        "speech"
    ],
    "wof:name":"Renard B",
    "wof:placetype":"venue"
},
  "geometry": {"coordinates":[6.0091700554,50.7239837646],"type":"Point"}
}