{
  "type": "Feature",
  "properties": {
    "addr:full":"Chauss\u00e9e De Wemmel 44 Bruxelles (jette) Bruxelles-Capitale 1090",
    "addr:housenumber":"44",
    "addr:postcode":"1090",
    "addr:street":"Chausse\u0301E De Wemmel",
    "iso:country":"BE",
    "sg:address":"Chauss\u00e9e De Wemmel 44",
    "sg:city":"Bruxelles (jette)",
    "sg:classifiers":[
        {
            "category":"Home & Garden",
            "subcategory":"Hardware",
            "type":"Retail Goods"
        }
    ],
    "sg:phone":"+32 2 426 69 16",
    "sg:postcode":"1090",
    "sg:province":"Bruxelles-Capitale",
    "sg:tags":[
        "tarpaulin"
    ],
    "wof:name":"F.b.t. Baches Et Tentes",
    "wof:placetype":"venue"
},
  "geometry": {"coordinates":[4.3251051903,50.8742179871],"type":"Point"}
}