{
  "type": "Feature",
  "properties": {
    "iso:country":"BE",
    "sg:address":"Breendonkstraat 10",
    "sg:city":"Sint-truiden",
    "sg:orig_category":"Kleding Textiel",
    "sg:phone":"+32 11 67 27 34",
    "sg:postcode":"3800",
    "sg:province":"Limburg",
    "wof:name":"Huis Cr\u00c9ar",
    "wof:placetype":"venue"
},
  "geometry": {"coordinates":[5.1831059456,50.8164176941],"type":"Point"}
}