{
  "type": "Feature",
  "properties": {
    "addr:full":"Stationlaan 56 Bilzen Limburg 3740",
    "addr:housenumber":"56",
    "addr:postcode":"3740",
    "addr:street":"Stationlaan",
    "iso:country":"BE",
    "sg:address":"Stationlaan 56",
    "sg:city":"Bilzen",
    "sg:classifiers":[
        {
            "category":"Personal",
            "subcategory":"Barber",
            "type":"Services"
        }
    ],
    "sg:phone":"+32 89 41 23 13",
    "sg:postcode":"3740",
    "sg:province":"Limburg",
    "sg:tags":[
        "gentleman",
        "salon",
        "-",
        "hairdressing"
    ],
    "wof:name":"Gaston",
    "wof:placetype":"venue"
},
  "geometry": {"coordinates":[5.5102090836,50.8683433533],"type":"Point"}
}