{
  "type": "Feature",
  "properties": {
    "addr:full":"Pater Coninxlaan 19 Bree Limburg 3960",
    "addr:housenumber":"19",
    "addr:postcode":"3960",
    "addr:street":"Pater Coninxlaan",
    "iso:country":"BE",
    "sg:address":"Pater Coninxlaan 19",
    "sg:city":"Bree",
    "sg:orig_category":"Elektrische installaties voor woningen",
    "sg:phone":"+32 89 46 67 38",
    "sg:postcode":"3960",
    "sg:province":"Limburg",
    "wof:name":"Elfrico Electro",
    "wof:placetype":"venue"
},
  "geometry": {"coordinates":[5.5903911591,51.1289710999],"type":"Point"}
}