{
  "type": "Feature",
  "properties": {
    "iso:country":"BE",
    "sg:address":"Torhoutse Steenweg 16",
    "sg:city":"Brugge (sint-andries)",
    "sg:classifiers":[
        {
            "category":"Real Estate",
            "subcategory":"Architect",
            "type":"Services"
        }
    ],
    "sg:phone":"+32 50 67 91 17",
    "sg:postcode":"8200",
    "sg:province":"West-Vlaanderen",
    "wof:name":"Smalle J",
    "wof:placetype":"venue"
},
  "geometry": {"coordinates":[3.2081398964,51.2034912109],"type":"Point"}
}