{
  "type": "Feature",
  "properties": {
    "iso:country":"BE",
    "sg:address":"Rue Marengo 4",
    "sg:city":"Luik",
    "sg:orig_category":"Supermarkten",
    "sg:phone":"+32 4 227 76 85",
    "sg:postcode":"4000",
    "sg:province":"Li\u00e8ge",
    "wof:name":"Ad Delhaize",
    "wof:placetype":"venue"
},
  "geometry": {"coordinates":[5.5907578468,50.6487159729],"type":"Point"}
}