{
  "type": "Feature",
  "properties": {
    "addr:full":"Avenue Du Chaineux 48 Verviers (heusy) Li\u00e8ge 4802",
    "addr:housenumber":"48",
    "addr:postcode":"4802",
    "addr:street":"Avenue Du Chaineux",
    "iso:country":"BE",
    "sg:address":"Avenue Du Chaineux 48",
    "sg:city":"Verviers (heusy)",
    "sg:classifiers":[
        {
            "category":"Real Estate",
            "subcategory":"Architect",
            "type":"Services"
        }
    ],
    "sg:phone":"+32 87 22 71 81",
    "sg:postcode":"4802",
    "sg:province":"Li\u00e8ge",
    "wof:name":"Jennes C",
    "wof:placetype":"venue"
},
  "geometry": {"coordinates":[5.8671250343,50.5714111328],"type":"Point"}
}