{
  "type": "Feature",
  "properties": {
    "addr:full":"Route De L'ambleve 19 Stoumont Li\u00e8ge 4987",
    "addr:housenumber":"19",
    "addr:postcode":"4987",
    "addr:street":"Route De L'Ambleve",
    "iso:country":"BE",
    "sg:address":"Route De L'ambleve 19",
    "sg:city":"Stoumont",
    "sg:orig_category":"Openbare veiligheid",
    "sg:phone":"+32 80 78 52 86",
    "sg:postcode":"4987",
    "sg:province":"Li\u00e8ge",
    "wof:name":"Police F\u00c9d\u00c9rale",
    "wof:placetype":"venue"
},
  "geometry": {"coordinates":[5.8098058701,50.4055595398],"type":"Point"}
}