{
  "type": "Feature",
  "properties": {
    "iso:country":"BE",
    "sg:address":"E. Braunplein 11",
    "sg:city":"Gent",
    "sg:classifiers":[
        {
            "category":"Restaurant",
            "type":"Food & Drink"
        }
    ],
    "sg:phone":"+32 9 225 79 37",
    "sg:postcode":"9000",
    "sg:province":"Oost-Vlaanderen",
    "wof:name":"Mashrabiya",
    "wof:placetype":"venue"
},
  "geometry": {"coordinates":[3.7239201069,51.0535621643],"type":"Point"}
}