{
  "type": "Feature",
  "properties": {
    "addr:full":"Veelsebaan 55ba Aarschot Vlaams-Brabant 3201",
    "addr:housenumber":"55ba",
    "addr:postcode":"3201",
    "addr:street":"Veelsebaan",
    "iso:country":"BE",
    "sg:address":"Veelsebaan 55ba",
    "sg:city":"Aarschot",
    "sg:orig_category":"Woningbouw",
    "sg:phone":"+32 13 78 21 34",
    "sg:postcode":"3201",
    "sg:province":"Vlaams-Brabant",
    "wof:name":"Delta-bati",
    "wof:placetype":"venue"
},
  "geometry": {"coordinates":[4.924238205,51.0308418274],"type":"Point"}
}