{
  "type": "Feature",
  "properties": {
    "iso:country":"BE",
    "sg:address":"All\u00c9e Du Jaquemart 4b18",
    "sg:city":"Nivelles",
    "sg:orig_category":"Elektrische installaties voor woningen Industri\u00eble elektrische installaties",
    "sg:phone":"+32 67 89 49 29",
    "sg:postcode":"1400",
    "sg:province":"Brabant Wallon",
    "wof:name":"Transelec",
    "wof:placetype":"venue"
},
  "geometry": {"coordinates":[4.3376059532,50.5927658081],"type":"Point"}
}