{
  "type": "Feature",
  "properties": {
    "iso:country":"BE",
    "sg:address":"Rue Emile Vandervelde 52",
    "sg:city":"Nivelles",
    "sg:orig_category":"Non-Classified Establishments",
    "sg:phone":"+32 67 21 37 84",
    "sg:postcode":"1400",
    "sg:province":"Brabant Wallon",
    "wof:name":"Fastech-fastsport",
    "wof:placetype":"venue"
},
  "geometry": {"coordinates":[4.3310461044,50.5957527161],"type":"Point"}
}