{
  "type": "Feature",
  "properties": {
    "addr:full":"Langestraat 83 Blankenberge West-Vlaanderen 8370",
    "addr:housenumber":"83",
    "addr:postcode":"8370",
    "addr:street":"Langestraat",
    "iso:country":"BE",
    "sg:address":"Langestraat 83",
    "sg:city":"Blankenberge",
    "sg:classifiers":[
        {
            "category":"Food & Beverages",
            "subcategory":"Fruits & Vegetables",
            "type":"Retail Goods"
        }
    ],
    "sg:phone":"+32 50 41 15 51",
    "sg:postcode":"8370",
    "sg:province":"West-Vlaanderen",
    "sg:tags":[
        "groenten"
    ],
    "wof:name":"Mathilde Reubens",
    "wof:placetype":"venue"
},
  "geometry": {"coordinates":[3.1309669018,51.31590271],"type":"Point"}
}