{
  "type": "Feature",
  "properties": {
    "iso:country":"BE",
    "sg:address":"Opwijksestraat 105",
    "sg:city":"Lebbeke",
    "sg:classifiers":[
        {
            "category":"Building & Trades",
            "subcategory":"Construction",
            "type":"Services"
        }
    ],
    "sg:phone":"+32 52 41 03 81",
    "sg:postcode":"9280",
    "sg:province":"Oost-Vlaanderen",
    "sg:tags":[
        "carpenter"
    ],
    "wof:name":"Abekon Nv",
    "wof:placetype":"venue"
},
  "geometry": {"coordinates":[4.137983799,50.9922447205],"type":"Point"}
}