{
  "type": "Feature",
  "properties": {
    "addr:full":"Grand'rue 16 Chimay Hainaut 6460",
    "addr:housenumber":"16",
    "addr:postcode":"6460",
    "addr:street":"Grand'Rue",
    "iso:country":"BE",
    "sg:address":"Grand'rue 16",
    "sg:city":"Chimay",
    "sg:classifiers":[
        {
            "category":"Place Of Worship",
            "subcategory":"Church",
            "type":"Public Place"
        }
    ],
    "sg:phone":"+32 60 21 37 20",
    "sg:postcode":"6460",
    "sg:province":"Hainaut",
    "sg:tags":[
        "article",
        "baptismal"
    ],
    "wof:name":"Bambino",
    "wof:placetype":"venue"
},
  "geometry": {"coordinates":[4.3150072098,50.0489654541],"type":"Point"}
}