{
  "type": "Feature",
  "properties": {
    "iso:country":"BE",
    "sg:address":"Rue De Waroux 20",
    "sg:city":"Li\u00c8ge",
    "sg:orig_category":"Artiesten and kunstenaars Speciaalzaken Woningbouw",
    "sg:phone":"+32 4 226 16 03",
    "sg:postcode":"4000",
    "sg:province":"Li\u00e8ge",
    "wof:name":"Menchior",
    "wof:placetype":"venue"
},
  "geometry": {"coordinates":[5.556787014,50.6435928345],"type":"Point"}
}