{
  "type": "Feature",
  "properties": {
    "iso:country":"BE",
    "sg:address":"Rue De L\u00e9gendre 55",
    "sg:city":"Louveigne-sprimont",
    "sg:classifiers":[
        {
            "category":"Wholesale",
            "subcategory":"Medical Equipment & Supplies",
            "type":"Manufacturing & Wholesale Goods"
        }
    ],
    "sg:phone":"+32 4 360 92 91",
    "sg:postcode":"4141",
    "sg:province":"Li\u00e8ge",
    "sg:tags":[
        "instrument",
        "health",
        "-",
        "precision"
    ],
    "wof:name":"Lanaform Sa",
    "wof:placetype":"venue"
},
  "geometry": {"coordinates":[5.701417923,50.5193748474],"type":"Point"}
}