{
  "type": "Feature",
  "properties": {
    "iso:country":"BE",
    "sg:address":"Roeselarestraat 69",
    "sg:city":"Zonnebeke",
    "sg:orig_category":"Installation \u00e9lectrique r\u00e9sidentielle",
    "sg:phone":"+32 51 77 81 62",
    "sg:postcode":"8980",
    "sg:province":"West-Vlaanderen",
    "wof:name":"Roger Goemaere",
    "wof:placetype":"venue"
},
  "geometry": {"coordinates":[2.9984219074,50.8756713867],"type":"Point"}
}