{
  "type": "Feature",
  "properties": {
    "iso:country":"BE",
    "sg:address":"Vichtsesteenweg 127",
    "sg:city":"Deerlijk",
    "sg:orig_category":"Entretien and r\u00e9parations de voitures. Mat\u00e9riel de T\u00e9l\u00e9communication",
    "sg:phone":"+32 56 77 99 45",
    "sg:postcode":"8540",
    "sg:province":"West-Vlaanderen",
    "wof:name":"Mts Telecom Service",
    "wof:placetype":"venue"
},
  "geometry": {"coordinates":[3.3521909714,50.8535194397],"type":"Point"}
}