{
  "type": "Feature",
  "properties": {
    "addr:full":"Kattenbroekstraat 7 Aalst Oost-Vlaanderen 9310",
    "addr:housenumber":"7",
    "addr:postcode":"9310",
    "addr:street":"Kattenbroekstraat",
    "iso:country":"BE",
    "sg:address":"Kattenbroekstraat 7",
    "sg:city":"Aalst",
    "sg:orig_category":"Pain, p\u00e2tisseries and confiseries",
    "sg:phone":"+32 53 21 45 07",
    "sg:postcode":"9310",
    "sg:province":"Oost-Vlaanderen",
    "wof:name":"Bakkerij Bellekes",
    "wof:placetype":"venue"
},
  "geometry": {"coordinates":[4.0901618004,50.9535713196],"type":"Point"}
}