{
  "type": "Feature",
  "properties": {
    "addr:full":"Tiensestraat 16a Kortenaken Vlaams-Brabant 3470",
    "addr:housenumber":"16a",
    "addr:postcode":"3470",
    "addr:street":"Tiensestraat",
    "iso:country":"BE",
    "sg:address":"Tiensestraat 16a",
    "sg:city":"Kortenaken",
    "sg:classifiers":[
        {
            "category":"Insurance",
            "subcategory":"Insurance Agent",
            "type":"Services"
        }
    ],
    "sg:phone":"+32 11 58 20 70",
    "sg:postcode":"3470",
    "sg:province":"Vlaams-Brabant",
    "sg:tags":[
        "broker"
    ],
    "wof:name":"Marcoen O",
    "wof:placetype":"venue"
},
  "geometry": {"coordinates":[5.0598840714,50.9078063965],"type":"Point"}
}