{
  "type": "Feature",
  "properties": {
    "addr:full":"Vestinglaan 32 Mortsel Antwerpen 2640",
    "addr:housenumber":"32",
    "addr:postcode":"2640",
    "addr:street":"Vestinglaan",
    "iso:country":"BE",
    "sg:address":"Vestinglaan 32",
    "sg:city":"Mortsel",
    "sg:classifiers":[
        {
            "category":"Farming",
            "subcategory":"Fish & Marine Products",
            "type":"Manufacturing & Wholesale Goods"
        }
    ],
    "sg:phone":"+32 3 232 76 77",
    "sg:postcode":"2640",
    "sg:province":"Antwerpen",
    "sg:tags":[
        "surveyor",
        "-"
    ],
    "wof:name":"De Maeyer & Co Nv",
    "wof:placetype":"venue"
},
  "geometry": {"coordinates":[4.4586372375,51.1689949036],"type":"Point"}
}