{
  "type": "Feature",
  "properties": {
    "iso:country":"BE",
    "sg:address":"Helhoekweg 6",
    "sg:city":"Rijkevorsel",
    "sg:orig_category":"Kapsalons",
    "sg:phone":"+32 3 314 61 95",
    "sg:postcode":"2310",
    "sg:province":"Antwerpen",
    "wof:name":"Coiffure Verbist",
    "wof:placetype":"venue"
},
  "geometry": {"coordinates":[4.7553520203,51.3454093933],"type":"Point"}
}