{
  "type": "Feature",
  "properties": {
    "iso:country":"BE",
    "sg:address":"Rue De Saint-julien 51",
    "sg:city":"Ath",
    "sg:orig_category":"Belastingconsulenten Diverse juridische dienstverlening",
    "sg:phone":"+32 68 28 50 33",
    "sg:postcode":"7800",
    "sg:province":"Hainaut",
    "wof:name":"Fiduciaire Detournay",
    "wof:placetype":"venue"
},
  "geometry": {"coordinates":[3.7889039516,50.6250343323],"type":"Point"}
}