{
  "type": "Feature",
  "properties": {
    "iso:country":"BE",
    "sg:address":"Chauss\u00e9e De Bruxelles 671",
    "sg:city":"Les Bons Villers (frasnes-lez-gosselies)",
    "sg:classifiers":[
        {
            "category":"Building & Trades",
            "subcategory":"Electrical",
            "type":"Services"
        }
    ],
    "sg:phone":"+32 71 85 08 14",
    "sg:postcode":"6210",
    "sg:province":"Hainaut",
    "sg:tags":[
        "electric",
        "-",
        "housewiring",
        "contractor"
    ],
    "wof:name":"Deltenre Ph Sprl",
    "wof:placetype":"venue"
},
  "geometry": {"coordinates":[4.4511561394,50.5378227234],"type":"Point"}
}