{
  "type": "Feature",
  "properties": {
    "addr:full":"Rue De La Retraite 2 Bievre Namur 5555",
    "addr:housenumber":"2",
    "addr:postcode":"5555",
    "addr:street":"Rue De La Retraite",
    "iso:country":"BE",
    "sg:address":"Rue De La Retraite 2",
    "sg:city":"Bievre",
    "sg:orig_category":"G\u00e9om\u00e8tres",
    "sg:phone":"+32 61 51 11 43",
    "sg:postcode":"5555",
    "sg:province":"Namur",
    "wof:name":"Marcel Dony",
    "wof:placetype":"venue"
},
  "geometry": {"coordinates":[5.0172848701,49.9395751953],"type":"Point"}
}