{
  "type": "Feature",
  "properties": {
    "addr:full":"Leuvensesteenweg 837 Kortenberg (erps-kwerps) Vlaams-Brabant 3071",
    "addr:housenumber":"837",
    "addr:postcode":"3071",
    "addr:street":"Leuvensesteenweg",
    "iso:country":"BE",
    "sg:address":"Leuvensesteenweg 837",
    "sg:city":"Kortenberg (erps-kwerps)",
    "sg:classifiers":[
        {
            "category":"Retail",
            "subcategory":"Event Space",
            "type":"Services"
        }
    ],
    "sg:phone":"+32 495 92 15 99",
    "sg:postcode":"3071",
    "sg:province":"Vlaams-Brabant",
    "sg:tags":[
        "organisation"
    ],
    "wof:name":"C-fun",
    "wof:placetype":"venue"
},
  "geometry": {"coordinates":[4.5837311745,50.893032074],"type":"Point"}
}