{
  "type": "Feature",
  "properties": {
    "iso:country":"BE",
    "sg:address":"Molenstraat 81",
    "sg:city":"Herenthout",
    "sg:classifiers":[
        {
            "category":"Health Services",
            "subcategory":"Dentist",
            "type":"Services"
        }
    ],
    "sg:phone":"+32 14 51 39 12",
    "sg:postcode":"2270",
    "sg:province":"Antwerpen",
    "wof:name":"Haverhals D",
    "wof:placetype":"venue"
},
  "geometry": {"coordinates":[4.7615180016,51.1403656006],"type":"Point"}
}