{
  "type": "Feature",
  "properties": {
    "iso:country":"BE",
    "sg:address":"Rue De La Station 89-99",
    "sg:city":"Anderlues",
    "sg:classifiers":[
        {
            "category":"Retail",
            "subcategory":"Veterinary Services",
            "type":"Services"
        }
    ],
    "sg:phone":"+32 71 52 34 23",
    "sg:postcode":"6150",
    "sg:province":"Hainaut",
    "sg:tags":[
        "veterinarian"
    ],
    "wof:name":"Michel L",
    "wof:placetype":"venue"
},
  "geometry": {"coordinates":[4.2827987671,50.3999977112],"type":"Point"}
}