{
  "type": "Feature",
  "properties": {
    "iso:country":"BE",
    "sg:address":"Place De La Gare 3",
    "sg:city":"Momignies",
    "sg:orig_category":"Catering and organisation de f\u00eates",
    "sg:phone":"+32 60 51 25 60",
    "sg:postcode":"6590",
    "sg:province":"Hainaut",
    "wof:name":"Le Charmy",
    "wof:placetype":"venue"
},
  "geometry": {"coordinates":[4.1636967659,50.0265426636],"type":"Point"}
}