{
  "type": "Feature",
  "properties": {
    "iso:country":"BE",
    "sg:address":"Dennenstraat 76",
    "sg:city":"Westerlo (oevel)",
    "sg:classifiers":[
        {
            "category":"Bars & Pubs",
            "type":"Food & Drink"
        }
    ],
    "sg:phone":"+32 14 23 48 63",
    "sg:postcode":"2260",
    "sg:province":"Antwerpen",
    "wof:name":"Countryhome",
    "wof:placetype":"venue"
},
  "geometry": {"coordinates":[4.900660038,51.1330947876],"type":"Point"}
}