{
  "type": "Feature",
  "properties": {
    "addr:full":"Justus Lipsiusstraat 20-209 Leuven Vlaams-Brabant 3000",
    "addr:postcode":"20-209;3000",
    "addr:street":"Justus Lipsiusstraat",
    "iso:country":"BE",
    "sg:address":"Justus Lipsiusstraat 20-209",
    "sg:city":"Leuven",
    "sg:classifiers":[
        {
            "category":"Health Services",
            "subcategory":"Doctor",
            "type":"Services"
        }
    ],
    "sg:phone":"+32 16 23 99 85",
    "sg:postcode":"3000",
    "sg:province":"Vlaams-Brabant",
    "sg:tags":[
        "medicinephysicians",
        "surgeon"
    ],
    "wof:name":"De Vogelaer Jos",
    "wof:placetype":"venue"
},
  "geometry": {"coordinates":[4.711368084,50.8795204163],"type":"Point"}
}