{
  "type": "Feature",
  "properties": {
    "addr:full":"Chauss\u00c9e De Beaumont 429 Mons Hainaut 7022",
    "addr:housenumber":"429",
    "addr:postcode":"7022",
    "addr:street":"Chausse\u0301E De Beaumont;Hainaut",
    "iso:country":"BE",
    "sg:address":"Chauss\u00c9e De Beaumont 429",
    "sg:city":"Mons",
    "sg:orig_category":"WAPENS AND MUNITIE",
    "sg:phone":"+32 65 58 65 17",
    "sg:postcode":"7022",
    "sg:province":"Hainaut",
    "wof:name":"Fe. Muller",
    "wof:placetype":"venue"
},
  "geometry": {"coordinates":[4.0181078911,50.4045410156],"type":"Point"}
}