{
  "type": "Feature",
  "properties": {
    "addr:full":"Rue Du Gravier 67 Li\u00c8ge Li\u00e8ge 4032",
    "addr:housenumber":"67",
    "addr:postcode":"4032",
    "addr:street":"Rue Du Gravier",
    "iso:country":"BE",
    "sg:address":"Rue Du Gravier 67",
    "sg:city":"Li\u00c8ge",
    "sg:orig_category":"Caf\u00e9s Ruimtes voor conferenties, recepties and feesten",
    "sg:phone":"+32 4 365 14 79",
    "sg:postcode":"4032",
    "sg:province":"Li\u00e8ge",
    "wof:name":"Caf\u00c9 Sinatra",
    "wof:placetype":"venue"
},
  "geometry": {"coordinates":[5.619579792,50.6117401123],"type":"Point"}
}