{
  "type": "Feature",
  "properties": {
    "addr:full":"Meersstraat 3 Kortrijk West-Vlaanderen 8500",
    "addr:housenumber":"3",
    "addr:postcode":"8500",
    "addr:street":"Meersstraat",
    "iso:country":"BE",
    "sg:address":"Meersstraat 3",
    "sg:city":"Kortrijk",
    "sg:classifiers":[
        {
            "category":"Retail",
            "subcategory":"Auto Rental",
            "type":"Services"
        }
    ],
    "sg:phone":"+32 56 22 47 52",
    "sg:postcode":"8500",
    "sg:province":"West-Vlaanderen",
    "sg:tags":[
        "term",
        "van",
        "cars",
        "-",
        "long",
        "delivery",
        "truck"
    ],
    "wof:name":"Elease Nv",
    "wof:placetype":"venue"
},
  "geometry": {"coordinates":[3.2567028999,50.8282165527],"type":"Point"}
}