{
  "type": "Feature",
  "properties": {
    "iso:country":"BE",
    "sg:address":"Rue Berkendael 92",
    "sg:city":"Bruxelles (forest)",
    "sg:classifiers":[
        {
            "category":"Real Estate",
            "subcategory":"Architect",
            "type":"Services"
        }
    ],
    "sg:phone":"+32 2 343 74 25",
    "sg:postcode":"1190",
    "sg:province":"Bruxelles-Capitale",
    "wof:name":"Layachi S",
    "wof:placetype":"venue"
},
  "geometry": {"coordinates":[4.3508791924,50.817024231],"type":"Point"}
}