{
  "type": "Feature",
  "properties": {
    "addr:full":"Kerkstraat 28 Boutersem (kerkom) Vlaams-Brabant 3370",
    "addr:housenumber":"28",
    "addr:postcode":"3370",
    "addr:street":"Kerkstraat",
    "iso:country":"BE",
    "sg:address":"Kerkstraat 28",
    "sg:city":"Boutersem (kerkom)",
    "sg:classifiers":[
        {
            "category":"Professional",
            "subcategory":"Art Services",
            "type":"Services"
        }
    ],
    "sg:phone":"+32 16 73 36 37",
    "sg:postcode":"3370",
    "sg:province":"Vlaams-Brabant",
    "sg:tags":[
        "interior",
        "designer"
    ],
    "wof:name":"Smets R",
    "wof:placetype":"venue"
},
  "geometry": {"coordinates":[4.8719000816,50.8525009155],"type":"Point"}
}