{
  "type": "Feature",
  "properties": {
    "iso:country":"BE",
    "sg:address":"Jardin Martin V 29",
    "sg:city":"Sint-lambrechts-woluwe/woluwe-saint-lambert",
    "sg:orig_category":"Imprimeries and copyshops. Fournitures de bureau",
    "sg:phone":"+32 2 762 35 85",
    "sg:postcode":"1200",
    "sg:province":"Bruxelles-Capitale",
    "wof:name":"Ciaco Papeterie",
    "wof:placetype":"venue"
},
  "geometry": {"coordinates":[4.4531412125,50.8502426147],"type":"Point"}
}