{
  "type": "Feature",
  "properties": {
    "iso:country":"BE",
    "sg:address":"Steenweg 140",
    "sg:city":"Heers",
    "sg:orig_category":"Maatschappelijke dienstverlening",
    "sg:phone":"+32 11 48 66 04",
    "sg:postcode":"3870",
    "sg:province":"Limburg",
    "wof:name":"Rode Kruis Heers",
    "wof:placetype":"venue"
},
  "geometry": {"coordinates":[5.2946429253,50.7512283325],"type":"Point"}
}