{
  "type": "Feature",
  "properties": {
    "addr:full":"Leest 10 Box 7 Merksplas Antwerpen 2330",
    "addr:housenumber":"10;7",
    "addr:postcode":"2330",
    "addr:street":"Leest;Box",
    "iso:country":"BE",
    "sg:address":"Leest 10 Box 7",
    "sg:city":"Merksplas",
    "sg:classifiers":[
        {
            "category":"Building & Trades",
            "subcategory":"Construction",
            "type":"Services"
        }
    ],
    "sg:phone":"+32 14 63 12 93",
    "sg:postcode":"2330",
    "sg:province":"Antwerpen",
    "sg:tags":[
        "ceiling"
    ],
    "wof:name":"Van Den Dijck R",
    "wof:placetype":"venue"
},
  "geometry": {"coordinates":[4.8631081581,51.354801178],"type":"Point"}
}