{
  "type": "Feature",
  "properties": {
    "addr:full":"Schijfstraat 15 Antwerpen Antwerpen 2020",
    "addr:housenumber":"15",
    "addr:postcode":"2020",
    "addr:street":"Schijfstraat",
    "iso:country":"BE",
    "sg:address":"Schijfstraat 15",
    "sg:city":"Antwerpen",
    "sg:orig_category":"Electrom\u00e9nager, t\u00e9l\u00e9visions and radios",
    "sg:phone":"+32 3 238 79 87",
    "sg:postcode":"2020",
    "sg:province":"Antwerpen",
    "wof:name":"Paul Van Caudenberg",
    "wof:placetype":"venue"
},
  "geometry": {"coordinates":[4.3768639565,51.1897010803],"type":"Point"}
}