{
  "type": "Feature",
  "properties": {
    "iso:country":"BE",
    "sg:address":"Klemskerksestraat 7",
    "sg:city":"Oudenburg",
    "sg:orig_category":"Eleveurs de bovins",
    "sg:phone":"+32 50 81 10 56",
    "sg:postcode":"8460",
    "sg:province":"West-Vlaanderen",
    "wof:name":"Wilfried Van Loocke",
    "wof:placetype":"venue"
},
  "geometry": {"coordinates":[3.0414030552,51.2203903198],"type":"Point"}
}