{
  "type": "Feature",
  "properties": {
    "addr:full":"Karel Oomsstraat 29 Antwerpen Antwerpen 2018",
    "addr:housenumber":"29",
    "addr:postcode":"2018",
    "addr:street":"Karel Oomsstraat",
    "iso:country":"BE",
    "sg:address":"Karel Oomsstraat 29",
    "sg:city":"Antwerpen",
    "sg:classifiers":[
        {
            "category":"Communications",
            "subcategory":"Film & Video Production",
            "type":"Services"
        }
    ],
    "sg:phone":"+32 476 30 05 94",
    "sg:postcode":"2018",
    "sg:province":"Antwerpen",
    "sg:tags":[
        "sound",
        "recording",
        "studio"
    ],
    "wof:name":"Vandergoten P",
    "wof:placetype":"venue"
},
  "geometry": {"coordinates":[4.4094657898,51.1955871582],"type":"Point"}
}