{
  "type": "Feature",
  "properties": {
    "addr:full":"Rue Du Grand Courant 13 Cuesmes Hainaut 7033",
    "addr:housenumber":"13",
    "addr:postcode":"7033",
    "addr:street":"Rue Du Grand Courant",
    "iso:country":"BE",
    "sg:address":"Rue Du Grand Courant 13",
    "sg:city":"Cuesmes",
    "sg:classifiers":[
        {
            "category":"Autos & Motor Vehicles",
            "subcategory":"Fuel & Gas Station",
            "type":"Retail Goods"
        }
    ],
    "sg:phone":"+32 65 84 24 25",
    "sg:postcode":"7033",
    "sg:province":"Hainaut",
    "sg:tags":[
        "stations-service",
        "carburants"
    ],
    "wof:name":"Top Cars Services",
    "wof:placetype":"venue"
},
  "geometry": {"coordinates":[3.9247100353,50.4482688904],"type":"Point"}
}