{
  "type": "Feature",
  "properties": {
    "addr:full":"Begonialaan 86 Ternat Vlaams-Brabant 1740",
    "addr:housenumber":"86",
    "addr:postcode":"1740",
    "addr:street":"Begonialaan",
    "iso:country":"BE",
    "sg:address":"Begonialaan 86",
    "sg:city":"Ternat",
    "sg:orig_category":"HERSTELLING ELEKTRISCHE HUISHOUDAPPARATEN",
    "sg:phone":"+32 2 582 49 60",
    "sg:postcode":"1740",
    "sg:province":"Vlaams-Brabant",
    "wof:name":"Harry De Coninck",
    "wof:placetype":"venue"
},
  "geometry": {"coordinates":[4.1877760887,50.8725204468],"type":"Point"}
}