{
  "type": "Feature",
  "properties": {
    "iso:country":"BE",
    "sg:address":"Dorp 46",
    "sg:city":"Herselt",
    "sg:classifiers":[
        {
            "category":"Food & Beverages",
            "subcategory":"Fruits & Vegetables",
            "type":"Retail Goods"
        }
    ],
    "sg:phone":"+32 14 54 57 53",
    "sg:postcode":"2230",
    "sg:province":"Antwerpen",
    "sg:tags":[
        "-"
    ],
    "wof:name":"Primeurs",
    "wof:placetype":"venue"
},
  "geometry": {"coordinates":[4.8823800087,51.0533447266],"type":"Point"}
}