{
  "type": "Feature",
  "properties": {
    "iso:country":"BE",
    "sg:address":"Rue Saint-jaen 11",
    "sg:city":"Chi\u00c8vres (groot)",
    "sg:orig_category":"Kapsalons",
    "sg:phone":"+32 68 65 73 71",
    "sg:postcode":"7950",
    "sg:province":"Hainaut",
    "wof:name":"Coiffure Fabienne",
    "wof:placetype":"venue"
},
  "geometry": {"coordinates":[3.8074491024,50.5869522095],"type":"Point"}
}