{
  "type": "Feature",
  "properties": {
    "iso:country":"BE",
    "sg:address":"Kapelstraat 112",
    "sg:city":"Deerlijk",
    "sg:classifiers":[
        {
            "category":"Shopping",
            "subcategory":"Party Supplies",
            "type":"Retail Goods"
        }
    ],
    "sg:phone":"+32 56 77 73 44",
    "sg:postcode":"8540",
    "sg:province":"West-Vlaanderen",
    "sg:tags":[
        "technician",
        "equipment",
        "dental",
        "-",
        "dentist"
    ],
    "wof:name":"Rtmed",
    "wof:placetype":"venue"
},
  "geometry": {"coordinates":[3.3759450912,50.8180961609],"type":"Point"}
}