{
  "type": "Feature",
  "properties": {
    "addr:full":"Rue De Namur 10 Courcelles (souvret) Hainaut 6182",
    "addr:housenumber":"10",
    "addr:postcode":"6182",
    "addr:street":"Rue De Namur",
    "iso:country":"BE",
    "sg:address":"Rue De Namur 10",
    "sg:city":"Courcelles (souvret)",
    "sg:classifiers":[
        {
            "category":"Utilities",
            "subcategory":"Natural Gas",
            "type":"Services"
        }
    ],
    "sg:phone":"+32 71 34 63 16",
    "sg:postcode":"6182",
    "sg:province":"Hainaut",
    "sg:tags":[
        "industrial",
        "heating"
    ],
    "wof:name":"A C E S",
    "wof:placetype":"venue"
},
  "geometry": {"coordinates":[4.343462944,50.4542121887],"type":"Point"}
}