{
  "type": "Feature",
  "properties": {
    "iso:country":"BE",
    "sg:address":"Boekweitlaan 13",
    "sg:city":"Sint-katelijne-waver",
    "sg:orig_category":"M\u00e9decins and sp\u00e9cialistes",
    "sg:phone":"+32 15 75 31 21",
    "sg:postcode":"2861",
    "sg:province":"Antwerpen",
    "wof:name":"R. Stroobants",
    "wof:placetype":"venue"
},
  "geometry": {"coordinates":[4.5834941864,51.0593643188],"type":"Point"}
}