{
  "type": "Feature",
  "properties": {
    "addr:full":"Rue De Stimbert 34 Tubize Brabant Wallon 1480",
    "addr:housenumber":"34",
    "addr:postcode":"1480",
    "addr:street":"Rue De Stimbert;Wallon",
    "iso:country":"BE",
    "sg:address":"Rue De Stimbert 34",
    "sg:city":"Tubize",
    "sg:classifiers":[
        {
            "category":"Health Services",
            "subcategory":"Health Practitioner",
            "type":"Services"
        }
    ],
    "sg:phone":"+32 2 355 37 84",
    "sg:postcode":"1480",
    "sg:province":"Brabant Wallon",
    "sg:tags":[
        "physiotherapist"
    ],
    "wof:name":"Windfohr Roxanne",
    "wof:placetype":"venue"
},
  "geometry": {"coordinates":[4.1927728653,50.674282074],"type":"Point"}
}