{
  "type": "Feature",
  "properties": {
    "addr:full":"Rue De Soumagne 18 Herve Li\u00e8ge 4650",
    "addr:housenumber":"18",
    "addr:postcode":"4650",
    "addr:street":"Rue De Soumagne",
    "iso:country":"BE",
    "sg:address":"Rue De Soumagne 18",
    "sg:city":"Herve",
    "sg:classifiers":[
        {
            "category":"Food & Beverages",
            "subcategory":"Fruits & Vegetables",
            "type":"Retail Goods"
        }
    ],
    "sg:phone":"+32 87 67 56 55",
    "sg:postcode":"4650",
    "sg:province":"Li\u00e8ge",
    "sg:tags":[
        "-"
    ],
    "wof:name":"Fefkenne Br\u00fchl",
    "wof:placetype":"venue"
},
  "geometry": {"coordinates":[5.7857217789,50.6367416382],"type":"Point"}
}