{
  "type": "Feature",
  "properties": {
    "iso:country":"BE",
    "sg:address":"Pieter Reypenslei 19",
    "sg:city":"Mortsel",
    "sg:classifiers":[
        {
            "category":"Shopping",
            "subcategory":"Clothing, Apparel, & Fashions",
            "type":"Retail Goods"
        }
    ],
    "sg:phone":"+32 3 449 23 53",
    "sg:postcode":"2640",
    "sg:province":"Antwerpen",
    "sg:tags":[
        "hosiery"
    ],
    "wof:name":"Kousenboetiek",
    "wof:placetype":"venue"
},
  "geometry": {"coordinates":[4.4533810616,51.1696815491],"type":"Point"}
}