{
  "type": "Feature",
  "properties": {
    "addr:full":"Hanswijkvaart 59 Mechelen Antwerpen 2800",
    "addr:housenumber":"59",
    "addr:postcode":"2800",
    "addr:street":"Hanswijkvaart",
    "iso:country":"BE",
    "sg:address":"Hanswijkvaart 59",
    "sg:city":"Mechelen",
    "sg:orig_category":"DIVERSE RECREATIEVE ACTIVITEITEN",
    "sg:phone":"+32 15 41 62 07",
    "sg:postcode":"2800",
    "sg:province":"Antwerpen",
    "wof:name":"B.c. Forum",
    "wof:placetype":"venue"
},
  "geometry": {"coordinates":[4.4881119728,51.0118675232],"type":"Point"}
}