{
  "type": "Feature",
  "properties": {
    "addr:full":"Oudenaardsesteenweg 18 Kortrijk West-Vlaanderen 8500",
    "addr:housenumber":"18",
    "addr:postcode":"8500",
    "addr:street":"Oudenaardsesteenweg",
    "iso:country":"BE",
    "sg:address":"Oudenaardsesteenweg 18",
    "sg:city":"Kortrijk",
    "sg:orig_category":"Banques and organismes de cr\u00e9dit",
    "sg:phone":"+32 56 21 07 77",
    "sg:postcode":"8500",
    "sg:province":"West-Vlaanderen",
    "wof:name":"Bbl",
    "wof:placetype":"venue"
},
  "geometry": {"coordinates":[3.2790420055,50.8218765259],"type":"Point"}
}