{
  "type": "Feature",
  "properties": {
    "addr:full":"Vilvoordelaan 86 Zaventem Vlaams-Brabant 1930",
    "addr:housenumber":"86",
    "addr:postcode":"1930",
    "addr:street":"Vilvoordelaan",
    "iso:country":"BE",
    "sg:address":"Vilvoordelaan 86",
    "sg:city":"Zaventem",
    "sg:orig_category":"Drogueries",
    "sg:phone":"+32 2 720 17 73",
    "sg:postcode":"1930",
    "sg:province":"Vlaams-Brabant",
    "wof:name":"R. Lisson",
    "wof:placetype":"venue"
},
  "geometry": {"coordinates":[4.4710249901,50.8889884949],"type":"Point"}
}