{
  "type": "Feature",
  "properties": {
    "addr:full":"Rue Des Juifs 10 Helecine Brabant Wallon 1357",
    "addr:housenumber":"10",
    "addr:postcode":"1357",
    "addr:street":"Rue Des Juifs",
    "iso:country":"BE",
    "sg:address":"Rue Des Juifs 10",
    "sg:city":"Helecine",
    "sg:orig_category":"Dranken",
    "sg:phone":"+32 19 65 60 57",
    "sg:postcode":"1357",
    "sg:province":"Brabant Wallon",
    "wof:name":"Leon Thomas",
    "wof:placetype":"venue"
},
  "geometry": {"coordinates":[4.9869499207,50.7524909973],"type":"Point"}
}