{
  "type": "Feature",
  "properties": {
    "addr:full":"Lindelaan 30 Lebbeke Oost-Vlaanderen 9280",
    "addr:housenumber":"30",
    "addr:postcode":"9280",
    "addr:street":"Lindelaan",
    "iso:country":"BE",
    "sg:address":"Lindelaan 30",
    "sg:city":"Lebbeke",
    "sg:classifiers":[
        {
            "category":"Health Services",
            "subcategory":"Doctor",
            "type":"Services"
        }
    ],
    "sg:phone":"+32 477 65 99 84",
    "sg:postcode":"9280",
    "sg:province":"Oost-Vlaanderen",
    "sg:tags":[
        "medicinephysicians",
        "surgeon"
    ],
    "wof:name":"Eggermont Kristel",
    "wof:placetype":"venue"
},
  "geometry": {"coordinates":[4.1269302368,51.0040245056],"type":"Point"}
}