{
  "type": "Feature",
  "properties": {
    "iso:country":"BE",
    "sg:address":"Rue Du Temple 58",
    "sg:city":"La Louviere",
    "sg:orig_category":"Beautyfarms, relaxatie and lichamelijk welzijn Fitnesscentra",
    "sg:phone":"+32 64 26 54 26",
    "sg:postcode":"7100",
    "sg:province":"Hainaut",
    "wof:name":"Body'n Gym",
    "wof:placetype":"venue"
},
  "geometry": {"coordinates":[4.1867599487,50.4748306274],"type":"Point"}
}