{
  "type": "Feature",
  "properties": {
    "iso:country":"BE",
    "sg:address":"Rue De Rocroi 1",
    "sg:city":"Couvin",
    "sg:orig_category":"Mus\u00e9es and patrimoine culturel",
    "sg:phone":"+32 60 37 70 74",
    "sg:postcode":"5660",
    "sg:province":"Namur",
    "wof:name":"Mus\u00c9e Vie R\u00c9g.riezes-sarts",
    "wof:placetype":"venue"
},
  "geometry": {"coordinates":[4.4555568695,49.9614334106],"type":"Point"}
}