{
  "type": "Feature",
  "properties": {
    "addr:full":"Prinsenlaan 1 Ba Temse Oost-Vlaanderen 9140",
    "addr:housenumber":"1",
    "addr:postcode":"9140",
    "addr:street":"Prinsenlaan;Oost-Vlaanderen",
    "iso:country":"BE",
    "sg:address":"Prinsenlaan 1 Ba",
    "sg:city":"Temse",
    "sg:orig_category":"Auto-\u00e9coles",
    "sg:phone":"+32 3 771 28 50",
    "sg:postcode":"9140",
    "sg:province":"Oost-Vlaanderen",
    "wof:name":"Rijschool Baetens",
    "wof:placetype":"venue"
},
  "geometry": {"coordinates":[4.2221589088,51.1755447388],"type":"Point"}
}