{
  "type": "Feature",
  "properties": {
    "addr:full":"Tulpenlaan 6 A Grimbergen Vlaams-Brabant 1853",
    "addr:housenumber":"6 a",
    "addr:postcode":"1853",
    "addr:street":"Tulpenlaan",
    "iso:country":"BE",
    "sg:address":"Tulpenlaan 6 A",
    "sg:city":"Grimbergen",
    "sg:orig_category":"Mat\u00e9riaux de construction Construction de maisons. Rev\u00eatements pour sols and murs. Installation de m",
    "sg:phone":"+32 2 267 69 21",
    "sg:postcode":"1853",
    "sg:province":"Vlaams-Brabant",
    "wof:name":"Sartor B.",
    "wof:placetype":"venue"
},
  "geometry": {"coordinates":[4.3632760048,50.9108352661],"type":"Point"}
}