{
  "type": "Feature",
  "properties": {
    "iso:country":"BE",
    "sg:address":"Poststraat 28",
    "sg:city":"Wevelgem (gullegem)",
    "sg:classifiers":[
        {
            "category":"Bars & Pubs",
            "type":"Food & Drink"
        }
    ],
    "sg:phone":"+32 56 41 85 10",
    "sg:postcode":"8560",
    "sg:province":"West-Vlaanderen",
    "wof:name":"Las Palmas",
    "wof:placetype":"venue"
},
  "geometry": {"coordinates":[3.2046689987,50.8452415466],"type":"Point"}
}