{
  "type": "Feature",
  "properties": {
    "iso:country":"BE",
    "sg:address":"Kerkstraat 10",
    "sg:city":"Duffel",
    "sg:classifiers":[
        {
            "category":"Shopping",
            "subcategory":"Optician",
            "type":"Retail Goods"
        }
    ],
    "sg:phone":"+32 15 31 31 41",
    "sg:postcode":"2570",
    "sg:province":"Antwerpen",
    "sg:tags":[
        "-"
    ],
    "wof:name":"Van Bael Bvba",
    "wof:placetype":"venue"
},
  "geometry": {"coordinates":[4.5008029938,51.0952072144],"type":"Point"}
}