{
  "type": "Feature",
  "properties": {
    "iso:country":"BE",
    "sg:address":"Rue Du Lombard 5-9",
    "sg:city":"Bruxelles",
    "sg:classifiers":[
        {
            "category":"Government",
            "subcategory":"Post Office",
            "type":"Public Place"
        }
    ],
    "sg:phone":"+32 2 512 27 31",
    "sg:postcode":"1000",
    "sg:province":"Bruxelles-Capitale",
    "sg:tags":[
        "stamp"
    ],
    "wof:name":"Campo Rodan Sa",
    "wof:placetype":"venue"
},
  "geometry": {"coordinates":[4.3490538597,50.8461952209],"type":"Point"}
}