{
  "type": "Feature",
  "properties": {
    "iso:country":"BE",
    "sg:address":"Leiestraat 1",
    "sg:city":"Menen",
    "sg:orig_category":"Fleurs and plantes",
    "sg:phone":"+32 56 41 17 98",
    "sg:postcode":"8930",
    "sg:province":"West-Vlaanderen",
    "wof:name":"Bloemensierkunst Marleen",
    "wof:placetype":"venue"
},
  "geometry": {"coordinates":[3.1234331131,50.7923431396],"type":"Point"}
}