{
  "type": "Feature",
  "properties": {
    "iso:country":"BE",
    "sg:address":"Heideveld 52",
    "sg:city":"Huizingen",
    "sg:classifiers":[
        {
            "category":"Manufacturing",
            "subcategory":"Metals",
            "type":"Manufacturing & Wholesale Goods"
        }
    ],
    "sg:phone":"+32 2 356 38 70",
    "sg:postcode":"1654",
    "sg:province":"Vlaams-Brabant",
    "sg:tags":[
        "metallurgy",
        "steel",
        "metalworking"
    ],
    "wof:name":"Montefiore Nv",
    "wof:placetype":"venue"
},
  "geometry": {"coordinates":[4.2618050575,50.7551078796],"type":"Point"}
}