{
  "type": "Feature",
  "properties": {
    "iso:country":"BE",
    "sg:address":"Place Alphonse Favresse 61",
    "sg:city":"La Hulpe",
    "sg:classifiers":[
        {
            "category":"Insurance",
            "subcategory":"Insurance Agent",
            "type":"Services"
        }
    ],
    "sg:phone":"+32 2 653 43 75",
    "sg:postcode":"1310",
    "sg:province":"Brabant Wallon",
    "sg:tags":[
        "broker"
    ],
    "wof:name":"Dacofi Assurances Sprl",
    "wof:placetype":"venue"
},
  "geometry": {"coordinates":[4.4953570366,50.7373542786],"type":"Point"}
}