{
  "type": "Feature",
  "properties": {
    "iso:country":"BE",
    "sg:address":"Rue Joseph Durieux 58",
    "sg:city":"Namur (flawinne)",
    "sg:classifiers":[
        {
            "category":"Sports & Exercise",
            "subcategory":"Gym",
            "type":"Entertainment"
        }
    ],
    "sg:phone":"+32 81 73 28 55",
    "sg:postcode":"5020",
    "sg:province":"Namur",
    "sg:tags":[
        "fitness"
    ],
    "wof:name":"Freddy Building",
    "wof:placetype":"venue"
},
  "geometry": {"coordinates":[4.7952418327,50.4352035522],"type":"Point"}
}