{
  "type": "Feature",
  "properties": {
    "iso:country":"BE",
    "sg:address":"Industrieweg 25ba",
    "sg:city":"Roeselare",
    "sg:orig_category":"Elektrische installaties voor woningen",
    "sg:phone":"+32 51 26 40 26",
    "sg:postcode":"8800",
    "sg:province":"West-Vlaanderen",
    "wof:name":"Protech",
    "wof:placetype":"venue"
},
  "geometry": {"coordinates":[3.1302978992,50.9750213623],"type":"Point"}
}