{
  "type": "Feature",
  "properties": {
    "addr:full":"Rodendijk 20 Zoersel (groot) Antwerpen 2980",
    "addr:housenumber":"20",
    "addr:postcode":"2980",
    "addr:street":"Rodendijk;Groot Antwerpen",
    "iso:country":"BE",
    "sg:address":"Rodendijk 20",
    "sg:city":"Zoersel (groot)",
    "sg:orig_category":"Baby- and kinderkleding Dameskledingzaken Herenkledingzaken",
    "sg:phone":"+32 3 311 72 42",
    "sg:postcode":"2980",
    "sg:province":"Antwerpen",
    "wof:name":"Jbc Mode",
    "wof:placetype":"venue"
},
  "geometry": {"coordinates":[4.7083501816,51.2525596619],"type":"Point"}
}