{
  "type": "Feature",
  "properties": {
    "addr:full":"Meisestr 93 Strombeek-bever Vlaams-Brabant 1853",
    "addr:housenumber":"93;1853",
    "addr:street":"Meisestr;Vlaams-Brabant",
    "iso:country":"BE",
    "sg:address":"Meisestr 93",
    "sg:city":"Strombeek-bever",
    "sg:classifiers":[
        {
            "category":"Professional",
            "type":"Services"
        }
    ],
    "sg:phone":"+32 2 267 03 04",
    "sg:postcode":"1853",
    "sg:province":"Vlaams-Brabant",
    "sg:tags":[
        "transport",
        "road"
    ],
    "wof:name":"Easy Move Bvba",
    "wof:placetype":"venue"
},
  "geometry": {"coordinates":[4.3512730598,50.9112625122],"type":"Point"}
}