{
  "type": "Feature",
  "properties": {
    "addr:full":"Zusterstraat 1 Herenthout Antwerpen 2270",
    "addr:housenumber":"1",
    "addr:postcode":"2270",
    "addr:street":"Zusterstraat",
    "iso:country":"BE",
    "sg:address":"Zusterstraat 1",
    "sg:city":"Herenthout",
    "sg:orig_category":"Enseignement maternel and primaire",
    "sg:phone":"+32 14 51 30 78",
    "sg:postcode":"2270",
    "sg:province":"Antwerpen",
    "wof:name":"Vrije Kleuterschool",
    "wof:placetype":"venue"
},
  "geometry": {"coordinates":[4.7570271492,51.1367340088],"type":"Point"}
}