{
  "type": "Feature",
  "properties": {
    "addr:full":"Tramstraat 1 Houthalen-helchteren Limburg 3530",
    "addr:housenumber":"1",
    "addr:postcode":"3530",
    "addr:street":"Tramstraat",
    "iso:country":"BE",
    "sg:address":"Tramstraat 1",
    "sg:city":"Houthalen-helchteren",
    "sg:classifiers":[
        {
            "category":"Personal",
            "subcategory":"Beauty Salon",
            "type":"Services"
        }
    ],
    "sg:phone":"+32 11 52 33 89",
    "sg:postcode":"3530",
    "sg:province":"Limburg",
    "sg:tags":[
        "de",
        "coiffure"
    ],
    "wof:name":"Coiffure Nadia",
    "wof:placetype":"venue"
},
  "geometry": {"coordinates":[5.3594470024,51.0283279419],"type":"Point"}
}