{
  "type": "Feature",
  "properties": {
    "iso:country":"BE",
    "sg:address":"Leernsesteenweg 162",
    "sg:city":"Deinze",
    "sg:orig_category":"Bloemen and planten Fleurop Interflora",
    "sg:phone":"+32 9 282 07 58",
    "sg:postcode":"9800",
    "sg:province":"Oost-Vlaanderen",
    "wof:name":"Bloembinderij De Waele",
    "wof:placetype":"venue"
},
  "geometry": {"coordinates":[3.5786008835,51.0094871521],"type":"Point"}
}