{
  "type": "Feature",
  "properties": {
    "addr:full":"Begoniastraat 6a Nazareth (eke) Oost-Vlaanderen 9810",
    "addr:housenumber":"6a",
    "addr:postcode":"9810",
    "addr:street":"Begoniastraat",
    "iso:country":"BE",
    "sg:address":"Begoniastraat 6a",
    "sg:city":"Nazareth (eke)",
    "sg:orig_category":"Non-Classified Establishments",
    "sg:phone":"+32 9 385 63 19",
    "sg:postcode":"9810",
    "sg:province":"Oost-Vlaanderen",
    "wof:name":"Electro-handling Bvba",
    "wof:placetype":"venue"
},
  "geometry": {"coordinates":[3.6547989845,50.9717063904],"type":"Point"}
}