{
  "type": "Feature",
  "properties": {
    "addr:full":"Hendrik Consciencestraat 63 Gent Oost-Vlaanderen 9050",
    "addr:housenumber":"63",
    "addr:postcode":"9050",
    "addr:street":"Hendrik Consciencestraat;Oost-Vlaanderen",
    "iso:country":"BE",
    "sg:address":"Hendrik Consciencestraat 63",
    "sg:city":"Gent",
    "sg:classifiers":[
        {
            "category":"Cafe",
            "type":"Food & Drink"
        }
    ],
    "sg:phone":"+32 9 231 80 65",
    "sg:postcode":"9050",
    "sg:province":"Oost-Vlaanderen",
    "sg:tags":[
        "caf\u00e9s"
    ],
    "wof:name":"Willy Covent",
    "wof:placetype":"venue"
},
  "geometry": {"coordinates":[3.7615439892,51.0191192627],"type":"Point"}
}