{
  "type": "Feature",
  "properties": {
    "addr:full":"Spoorstraat 12 Kapellen Antwerpen 2950",
    "addr:housenumber":"12",
    "addr:postcode":"2950",
    "addr:street":"Spoorstraat",
    "iso:country":"BE",
    "sg:address":"Spoorstraat 12",
    "sg:city":"Kapellen",
    "sg:orig_category":"Installation \u00e9lectrique r\u00e9sidentielle",
    "sg:phone":"+32 3 664 13 62",
    "sg:postcode":"2950",
    "sg:province":"Antwerpen",
    "wof:name":"Freddy Van Gastel",
    "wof:placetype":"venue"
},
  "geometry": {"coordinates":[4.4372019768,51.3189964294],"type":"Point"}
}