{
  "type": "Feature",
  "properties": {
    "iso:country":"BE",
    "sg:address":"Kennipshoefstraat 31",
    "sg:city":"Genk",
    "sg:classifiers":[
        {
            "category":"Education",
            "subcategory":"Dance Studio",
            "type":"Public Place"
        }
    ],
    "sg:phone":"+32 89 35 10 08",
    "sg:postcode":"3600",
    "sg:province":"Limburg",
    "sg:tags":[
        "school",
        "dancing"
    ],
    "wof:name":"Tamoeree Dans & Levenskunst Vzw",
    "wof:placetype":"venue"
},
  "geometry": {"coordinates":[5.5221009254,50.9514541626],"type":"Point"}
}