{
  "type": "Feature",
  "properties": {
    "addr:full":"Grotekapellelaan 80 Lede Oost-Vlaanderen 9340",
    "addr:housenumber":"80",
    "addr:postcode":"9340",
    "addr:street":"Grotekapellelaan",
    "iso:country":"BE",
    "sg:address":"Grotekapellelaan 80",
    "sg:city":"Lede",
    "sg:classifiers":[
        {
            "category":"Cafe",
            "type":"Food & Drink"
        }
    ],
    "sg:phone":"+32 53 80 32 00",
    "sg:postcode":"9340",
    "sg:province":"Oost-Vlaanderen",
    "sg:tags":[
        "caf\u00e9s"
    ],
    "wof:name":"Lydie Nijs",
    "wof:placetype":"venue"
},
  "geometry": {"coordinates":[3.9737000465,50.9609947205],"type":"Point"}
}