{
  "type": "Feature",
  "properties": {
    "addr:full":"Rue Des Alli\u00c9s 103 Leuze-en-hainaut Hainaut 7900",
    "addr:housenumber":"103",
    "addr:postcode":"7900",
    "addr:street":"Rue Des Allie\u0301S",
    "iso:country":"BE",
    "sg:address":"Rue Des Alli\u00c9s 103",
    "sg:city":"Leuze-en-hainaut",
    "sg:orig_category":"V\u00e9t\u00e9rinaires",
    "sg:phone":"+32 69 66 35 08",
    "sg:postcode":"7900",
    "sg:province":"Hainaut",
    "wof:name":"Jacques Chenut",
    "wof:placetype":"venue"
},
  "geometry": {"coordinates":[3.6211650372,50.5938301086],"type":"Point"}
}