{
  "type": "Feature",
  "properties": {
    "iso:country":"BE",
    "sg:address":"Grote Markt 10",
    "sg:city":"Aalst",
    "sg:orig_category":"Articles de camping and de sport. V\u00eatements",
    "sg:phone":"+32 53 77 30 05",
    "sg:postcode":"9300",
    "sg:province":"Oost-Vlaanderen",
    "wof:name":"Jeaneration",
    "wof:placetype":"venue"
},
  "geometry": {"coordinates":[4.0278520584,50.9354743958],"type":"Point"}
}