{
  "type": "Feature",
  "properties": {
    "addr:full":"Koolmijnlaan 270 Beringen (koersel) Limburg 3582",
    "addr:housenumber":"270",
    "addr:postcode":"3582",
    "addr:street":"Koolmijnlaan",
    "iso:country":"BE",
    "sg:address":"Koolmijnlaan 270",
    "sg:city":"Beringen (koersel)",
    "sg:classifiers":[
        {
            "category":"Shopping",
            "subcategory":"Jewelry",
            "type":"Retail Goods"
        }
    ],
    "sg:phone":"+32 11 45 42 90",
    "sg:postcode":"3582",
    "sg:province":"Limburg",
    "sg:tags":[
        "jeweller",
        "-"
    ],
    "wof:name":"Gold Mine Nv",
    "wof:placetype":"venue"
},
  "geometry": {"coordinates":[5.2198619843,51.0737838745],"type":"Point"}
}