{
  "type": "Feature",
  "properties": {
    "iso:country":"BE",
    "sg:address":"Rue Bureau 33",
    "sg:city":"Fleron",
    "sg:classifiers":[
        {
            "category":"Fast Food",
            "type":"Food & Drink"
        }
    ],
    "sg:phone":"+32 4 355 03 97",
    "sg:postcode":"4621",
    "sg:province":"Li\u00e8ge",
    "sg:tags":[
        "meeneem",
        "restaurant"
    ],
    "wof:name":"Snack-bar Le Knossos",
    "wof:placetype":"venue"
},
  "geometry": {"coordinates":[5.6915640831,50.6140556335],"type":"Point"}
}