{
  "type": "Feature",
  "properties": {
    "addr:full":"Chemin De Wepion 36 Namur Namur 5020",
    "addr:housenumber":"36",
    "addr:postcode":"5020",
    "addr:street":"Chemin De Wepion",
    "iso:country":"BE",
    "sg:address":"Chemin De Wepion 36",
    "sg:city":"Namur",
    "sg:orig_category":"Architectes",
    "sg:phone":"+32 81 46 07 46",
    "sg:postcode":"5020",
    "sg:province":"Namur",
    "wof:name":"Dominique Bertrand",
    "wof:placetype":"venue"
},
  "geometry": {"coordinates":[4.7952418327,50.4352035522],"type":"Point"}
}