{
  "type": "Feature",
  "properties": {
    "iso:country":"BE",
    "sg:address":"Centrum Zuid 2407",
    "sg:city":"Houthalen-helchteren (houthalen)",
    "sg:classifiers":[
        {
            "category":"Retail",
            "subcategory":"Auto Repair",
            "type":"Services"
        }
    ],
    "sg:phone":"+32 11 53 18 43",
    "sg:postcode":"3530",
    "sg:province":"Limburg",
    "sg:tags":[
        "automobile-body"
    ],
    "wof:name":"All Car Repair",
    "wof:placetype":"venue"
},
  "geometry": {"coordinates":[5.3518128395,51.0194778442],"type":"Point"}
}