{
  "type": "Feature",
  "properties": {
    "addr:full":"Rue Du H\u00c9aume 9 Seneffe Hainaut 7180",
    "addr:housenumber":"9",
    "addr:postcode":"7180",
    "addr:street":"Rue Du He\u0301Aume",
    "iso:country":"BE",
    "sg:address":"Rue Du H\u00c9aume 9",
    "sg:city":"Seneffe",
    "sg:orig_category":"Eleveurs and marchands de porcs. Eleveurs de bovins",
    "sg:phone":"+32 64 54 19 73",
    "sg:postcode":"7180",
    "sg:province":"Hainaut",
    "wof:name":"Arille Laurent",
    "wof:placetype":"venue"
},
  "geometry": {"coordinates":[4.2736082077,50.5447006226],"type":"Point"}
}