{
  "type": "Feature",
  "properties": {
    "iso:country":"BE",
    "sg:address":"Stevinstraat 132",
    "sg:city":"Brussel/bruxelles",
    "sg:classifiers":[
        {
            "category":"Restaurant",
            "type":"Food & Drink"
        }
    ],
    "sg:phone":"+32 2 280 00 81",
    "sg:postcode":"1000",
    "sg:province":"Bruxelles-Capitale",
    "wof:name":"Las Castanuelas",
    "wof:placetype":"venue"
},
  "geometry": {"coordinates":[4.3817539215,50.8446960449],"type":"Point"}
}