{
  "type": "Feature",
  "properties": {
    "iso:country":"BE",
    "sg:address":"Oude Iepersestraat 131",
    "sg:city":"Izegem",
    "sg:classifiers":[
        {
            "category":"Recreation",
            "subcategory":"Arcade",
            "type":"Entertainment"
        }
    ],
    "sg:phone":"+32 51 30 88 59",
    "sg:postcode":"8870",
    "sg:province":"West-Vlaanderen",
    "sg:tags":[
        "machine",
        "amusement"
    ],
    "wof:name":"Juke-box House",
    "wof:placetype":"venue"
},
  "geometry": {"coordinates":[3.1817519665,50.9016952515],"type":"Point"}
}