{
  "type": "Feature",
  "properties": {
    "iso:country":"BE",
    "sg:address":"Chauss\u00e9e D'audenarde 44",
    "sg:city":"Pecq (h\u00e9rinnes-lez-pecq)",
    "sg:classifiers":[
        {
            "category":"Bars & Pubs",
            "type":"Food & Drink"
        }
    ],
    "sg:phone":"+32 69 55 61 95",
    "sg:postcode":"7742",
    "sg:province":"Hainaut",
    "wof:name":"Devos M",
    "wof:placetype":"venue"
},
  "geometry": {"coordinates":[3.3591370583,50.6776313782],"type":"Point"}
}