{
  "type": "Feature",
  "properties": {
    "iso:country":"BE",
    "sg:address":"Rue Des Pr\u00e9s 87",
    "sg:city":"Verviers (heusy)",
    "sg:classifiers":[
        {
            "category":"Professional",
            "subcategory":"Management & Consulting",
            "type":"Services"
        }
    ],
    "sg:phone":"+32 87 22 26 22",
    "sg:postcode":"4802",
    "sg:province":"Li\u00e8ge",
    "sg:tags":[
        "consultant"
    ],
    "wof:name":"Linc\u00e9 Sprl",
    "wof:placetype":"venue"
},
  "geometry": {"coordinates":[5.8794698715,50.572101593],"type":"Point"}
}