{
  "type": "Feature",
  "properties": {
    "addr:full":"Stationstraat 49 Komen-waasten/comines-warneton Hainaut 7780",
    "addr:housenumber":"49;7780",
    "addr:street":"Stationstraat",
    "iso:country":"BE",
    "sg:address":"Stationstraat 49",
    "sg:city":"Komen-waasten/comines-warneton",
    "sg:classifiers":[
        {
            "category":"Shopping",
            "subcategory":"Clothing, Apparel, & Fashions",
            "type":"Retail Goods"
        }
    ],
    "sg:phone":"+32 56 55 50 79",
    "sg:postcode":"7780",
    "sg:province":"Hainaut",
    "sg:tags":[
        "ondergoed",
        "lingerie"
    ],
    "wof:name":"Maison Agnes",
    "wof:placetype":"venue"
},
  "geometry": {"coordinates":[2.9984300137,50.7863311768],"type":"Point"}
}