{
  "type": "Feature",
  "properties": {
    "iso:country":"BE",
    "sg:address":"Oude Haachtsesteenweg 69",
    "sg:city":"Machelen",
    "sg:classifiers":[
        {
            "category":"Food & Beverages",
            "subcategory":"Fruits & Vegetables",
            "type":"Retail Goods"
        }
    ],
    "sg:phone":"+32 2 720 09 25",
    "sg:postcode":"1831",
    "sg:province":"Vlaams-Brabant",
    "sg:tags":[
        "l\u00e9gumes",
        "gr"
    ],
    "wof:name":"Fa. V. Weyenberge-stevens",
    "wof:placetype":"venue"
},
  "geometry": {"coordinates":[4.437789917,50.8992118835],"type":"Point"}
}