{
  "type": "Feature",
  "properties": {
    "iso:country":"BE",
    "sg:address":"Rue De L'egalit\u00c9 58",
    "sg:city":"Manage",
    "sg:orig_category":"Traitement and rev\u00eatement des m\u00e9taux",
    "sg:phone":"+32 64 55 81 10",
    "sg:postcode":"7170",
    "sg:province":"Hainaut",
    "wof:name":"Cabes F",
    "wof:placetype":"venue"
},
  "geometry": {"coordinates":[4.2164969444,50.4929122925],"type":"Point"}
}