{
  "type": "Feature",
  "properties": {
    "iso:country":"BE",
    "sg:address":"Nispert 1",
    "sg:city":"Eupen",
    "sg:classifiers":[
        {
            "category":"Home & Garden",
            "subcategory":"Furniture",
            "type":"Retail Goods"
        }
    ],
    "sg:phone":"+32 87 74 27 72",
    "sg:postcode":"4700",
    "sg:province":"Li\u00e8ge",
    "sg:tags":[
        "wood"
    ],
    "wof:name":"Gmbh Pankert P",
    "wof:placetype":"venue"
},
  "geometry": {"coordinates":[6.0475559235,50.6331672668],"type":"Point"}
}