{
  "type": "Feature",
  "properties": {
    "addr:full":"Rue De Villenval 91 Andenne Namur 5300",
    "addr:housenumber":"91",
    "addr:postcode":"5300",
    "addr:street":"Rue De Villenval",
    "iso:country":"BE",
    "sg:address":"Rue De Villenval 91",
    "sg:city":"Andenne",
    "sg:orig_category":"Artsen and specialisten",
    "sg:phone":"+32 81 58 92 52",
    "sg:postcode":"5300",
    "sg:province":"Namur",
    "wof:name":"Guy Mellaerts",
    "wof:placetype":"venue"
},
  "geometry": {"coordinates":[4.9755997658,50.4587211609],"type":"Point"}
}