{
  "type": "Feature",
  "properties": {
    "addr:full":"Vlaamsekaai 95 Gent Oost-Vlaanderen 9000",
    "addr:housenumber":"95",
    "addr:postcode":"9000",
    "addr:street":"Vlaamsekaai;Oost-Vlaanderen",
    "iso:country":"BE",
    "sg:address":"Vlaamsekaai 95",
    "sg:city":"Gent",
    "sg:classifiers":[
        {
            "category":"Professional",
            "subcategory":"Art Services",
            "type":"Services"
        }
    ],
    "sg:phone":"+32 9 233 50 71",
    "sg:postcode":"9000",
    "sg:province":"Oost-Vlaanderen",
    "sg:tags":[
        "sculptor"
    ],
    "wof:name":"Pollier Chantal",
    "wof:placetype":"venue"
},
  "geometry": {"coordinates":[3.7433559895,51.0452537537],"type":"Point"}
}