{
  "type": "Feature",
  "properties": {
    "addr:full":"Rue Des Champs 92 Etterbeek/etterbeek Bruxelles-Capitale 1040",
    "addr:housenumber":"92",
    "addr:postcode":"1040",
    "addr:street":"Rue Des Champs",
    "iso:country":"BE",
    "sg:address":"Rue Des Champs 92",
    "sg:city":"Etterbeek/etterbeek",
    "sg:classifiers":[
        {
            "category":"Cafe",
            "type":"Food & Drink"
        }
    ],
    "sg:phone":"+32 2 736 02 66",
    "sg:postcode":"1040",
    "sg:province":"Bruxelles-Capitale",
    "sg:tags":[
        "caf\u00e9s"
    ],
    "wof:name":"Caf\u00c9 L'alyssia",
    "wof:placetype":"venue"
},
  "geometry": {"coordinates":[4.3941640854,50.8307342529],"type":"Point"}
}