{
  "type": "Feature",
  "properties": {
    "addr:full":"Rue Grande 151 Dinant Namur 5500",
    "addr:housenumber":"151",
    "addr:postcode":"5500",
    "addr:street":"Rue Grande",
    "iso:country":"BE",
    "sg:address":"Rue Grande 151",
    "sg:city":"Dinant",
    "sg:classifiers":[
        {
            "category":"Arts & Performance",
            "subcategory":"Music",
            "type":"Entertainment"
        }
    ],
    "sg:phone":"+32 83 21 19 30",
    "sg:postcode":"5500",
    "sg:province":"Namur",
    "sg:tags":[
        "disc-jockeys"
    ],
    "wof:name":"Omega Sonorisation",
    "wof:placetype":"venue"
},
  "geometry": {"coordinates":[4.9130530357,50.260345459],"type":"Point"}
}