{
  "type": "Feature",
  "properties": {
    "addr:full":"Strandlaan 331 Koksijde West-Vlaanderen 8670",
    "addr:housenumber":"331",
    "addr:postcode":"8670",
    "addr:street":"Strandlaan",
    "iso:country":"BE",
    "sg:address":"Strandlaan 331",
    "sg:city":"Koksijde",
    "sg:classifiers":[
        {
            "category":"Real Estate",
            "subcategory":"Architect",
            "type":"Services"
        }
    ],
    "sg:phone":"+32 58 31 36 92",
    "sg:postcode":"8670",
    "sg:province":"West-Vlaanderen",
    "wof:name":"Dierendonck A",
    "wof:placetype":"venue"
},
  "geometry": {"coordinates":[2.6116609573,51.1101722717],"type":"Point"}
}