{
  "type": "Feature",
  "properties": {
    "iso:country":"BE",
    "sg:address":"Kleinesteenweg 2",
    "sg:city":"Begijnendijk",
    "sg:classifiers":[
        {
            "category":"Manufacturing",
            "subcategory":"Chemicals & Compounds",
            "type":"Manufacturing & Wholesale Goods"
        }
    ],
    "sg:phone":"+32 16 52 03 93",
    "sg:postcode":"3130",
    "sg:province":"Vlaams-Brabant",
    "sg:tags":[
        "pharmaceutical",
        "product"
    ],
    "wof:name":"Pagan Bvba",
    "wof:placetype":"venue"
},
  "geometry": {"coordinates":[4.7841501236,51.0178947449],"type":"Point"}
}