{
  "type": "Feature",
  "properties": {
    "addr:full":"Ave Ferdinand Nicolay 15 A Stavelot Li\u00e8ge 4970",
    "addr:housenumber":"15 a",
    "addr:postcode":"4970",
    "addr:street":"Ave Ferdinand Nicolay",
    "iso:country":"BE",
    "sg:address":"Ave Ferdinand Nicolay 15 A",
    "sg:city":"Stavelot",
    "sg:classifiers":[
        {
            "category":"Banks & Credit Unions",
            "subcategory":"Bank",
            "type":"Services"
        }
    ],
    "sg:phone":"+32 80 86 25 61",
    "sg:postcode":"4970",
    "sg:province":"Li\u00e8ge",
    "wof:name":"Aslk-cger Bank",
    "wof:placetype":"venue"
},
  "geometry": {"coordinates":[5.9313569069,50.394744873],"type":"Point"}
}