{
  "type": "Feature",
  "properties": {
    "addr:full":"Rue Des Chevaliers 20 Bruxelles (ixelles) Bruxelles-Capitale 1050",
    "addr:housenumber":"20",
    "addr:postcode":"1050",
    "addr:street":"Rue Des Chevaliers",
    "iso:country":"BE",
    "sg:address":"Rue Des Chevaliers 20",
    "sg:city":"Bruxelles (ixelles)",
    "sg:classifiers":[
        {
            "category":"Real Estate",
            "subcategory":"Architect",
            "type":"Services"
        }
    ],
    "sg:phone":"+32 2 502 86 16",
    "sg:postcode":"1050",
    "sg:province":"Bruxelles-Capitale",
    "wof:name":"Embise C",
    "wof:placetype":"venue"
},
  "geometry": {"coordinates":[4.3598427773,50.8363189697],"type":"Point"}
}