{
  "type": "Feature",
  "properties": {
    "addr:full":"Moortselestraat 7 Oosterzele Oost-Vlaanderen 9860",
    "addr:housenumber":"7",
    "addr:postcode":"9860",
    "addr:street":"Moortselestraat;Oost-Vlaanderen",
    "iso:country":"BE",
    "sg:address":"Moortselestraat 7",
    "sg:city":"Oosterzele",
    "sg:orig_category":"S\u00e9curit\u00e9 sociale",
    "sg:phone":"+32 9 362 62 53",
    "sg:postcode":"9860",
    "sg:province":"Oost-Vlaanderen",
    "wof:name":"Bond Moyson",
    "wof:placetype":"venue"
},
  "geometry": {"coordinates":[3.7804338932,50.9542808533],"type":"Point"}
}