{
  "type": "Feature",
  "properties": {
    "addr:full":"Lombardstraat 14 Nijlen Antwerpen 2560",
    "addr:housenumber":"14",
    "addr:postcode":"2560",
    "addr:street":"Lombardstraat",
    "iso:country":"BE",
    "sg:address":"Lombardstraat 14",
    "sg:city":"Nijlen",
    "sg:classifiers":[
        {
            "category":"Shopping",
            "subcategory":"Jewelry",
            "type":"Retail Goods"
        }
    ],
    "sg:phone":"+32 3 481 60 65",
    "sg:postcode":"2560",
    "sg:province":"Antwerpen",
    "sg:tags":[
        "fab",
        "bijou"
    ],
    "wof:name":"Belchin",
    "wof:placetype":"venue"
},
  "geometry": {"coordinates":[4.6998610497,51.1704673767],"type":"Point"}
}