{
  "type": "Feature",
  "properties": {
    "addr:full":"Koninginnelaan 190 Brussel/bruxelles Bruxelles-Capitale 1000",
    "addr:housenumber":"190",
    "addr:postcode":"1000",
    "addr:street":"Koninginnelaan;/",
    "iso:country":"BE",
    "sg:address":"Koninginnelaan 190",
    "sg:city":"Brussel/bruxelles",
    "sg:classifiers":[
        {
            "category":"Cafe",
            "type":"Food & Drink"
        }
    ],
    "sg:phone":"+32 2 201 50 62",
    "sg:postcode":"1000",
    "sg:province":"Bruxelles-Capitale",
    "sg:tags":[
        "caf\u00e9s"
    ],
    "wof:name":"Kalburidis Hristos",
    "wof:placetype":"venue"
},
  "geometry": {"coordinates":[4.3611721992,50.870765686],"type":"Point"}
}