{
  "type": "Feature",
  "properties": {
    "iso:country":"BE",
    "sg:address":"Romestraat 52",
    "sg:city":"Oostende",
    "sg:classifiers":[
        {
            "category":"Bakery",
            "type":"Food & Drink"
        }
    ],
    "sg:phone":"+32 59 80 52 63",
    "sg:postcode":"8400",
    "sg:province":"West-Vlaanderen",
    "sg:tags":[
        "confectioner",
        "baker"
    ],
    "wof:name":"Korenbloem (de)",
    "wof:placetype":"venue"
},
  "geometry": {"coordinates":[2.9165680408,51.2240943909],"type":"Point"}
}