{
  "type": "Feature",
  "properties": {
    "iso:country":"BE",
    "sg:address":"Fabriekstraat 9",
    "sg:city":"Ardooie",
    "sg:orig_category":"Non-Classified Establishments",
    "sg:phone":"+32 51 74 78 89",
    "sg:postcode":"8850",
    "sg:province":"West-Vlaanderen",
    "wof:name":"Strynck-dely Bvba",
    "wof:placetype":"venue"
},
  "geometry": {"coordinates":[3.2019469738,50.9881439209],"type":"Point"}
}