{
  "type": "Feature",
  "properties": {
    "addr:full":"Kerselarenstraat 2 Torhout West-Vlaanderen 8820",
    "addr:housenumber":"2",
    "addr:postcode":"8820",
    "addr:street":"Kerselarenstraat",
    "iso:country":"BE",
    "sg:address":"Kerselarenstraat 2",
    "sg:city":"Torhout",
    "sg:classifiers":[
        {
            "category":"Insurance",
            "subcategory":"Insurance Agent",
            "type":"Services"
        }
    ],
    "sg:phone":"+32 50 21 11 28",
    "sg:postcode":"8820",
    "sg:province":"West-Vlaanderen",
    "sg:tags":[
        "broker"
    ],
    "wof:name":"Lagae N",
    "wof:placetype":"venue"
},
  "geometry": {"coordinates":[3.0828630924,51.0684394836],"type":"Point"}
}