{
  "type": "Feature",
  "properties": {
    "iso:country":"BE",
    "sg:address":"Rue Omer Houssi\u00c8re 8",
    "sg:city":"La Louviere",
    "sg:orig_category":"Journaux. Biens d'occasion. Tabac",
    "sg:phone":"+32 64 66 44 87",
    "sg:postcode":"7110",
    "sg:province":"Hainaut",
    "wof:name":"Librairie Maison Vanninove",
    "wof:placetype":"venue"
},
  "geometry": {"coordinates":[4.1505050659,50.4826698303],"type":"Point"}
}