{
  "type": "Feature",
  "properties": {
    "iso:country":"BE",
    "sg:address":"Rue De Berneau 26",
    "sg:city":"Vis\u00e9",
    "sg:classifiers":[
        {
            "category":"Manufacturing",
            "subcategory":"Metals",
            "type":"Manufacturing & Wholesale Goods"
        }
    ],
    "sg:phone":"+32 4 379 56 99",
    "sg:postcode":"4600",
    "sg:province":"Li\u00e8ge",
    "sg:tags":[
        "ornamental",
        "work",
        "-"
    ],
    "wof:name":"Ats-thys Servais",
    "wof:placetype":"venue"
},
  "geometry": {"coordinates":[5.7068300247,50.7372093201],"type":"Point"}
}