{
  "type": "Feature",
  "properties": {
    "addr:full":"Quartier Du 150\u00c8me 4 Wellin Luxembourg 6920",
    "addr:housenumber":"4",
    "addr:postcode":"6920",
    "addr:street":"Du 150E\u0300Me",
    "iso:country":"BE",
    "sg:address":"Quartier Du 150\u00c8me 4",
    "sg:city":"Wellin",
    "sg:orig_category":"Sociale huisvestingsmaatschappijen",
    "sg:phone":"+32 84 38 90 27",
    "sg:postcode":"6920",
    "sg:province":"Luxembourg",
    "wof:name":"Ardenne Et Lesse",
    "wof:placetype":"venue"
},
  "geometry": {"coordinates":[5.1139631271,50.0823478699],"type":"Point"}
}