{
  "type": "Feature",
  "properties": {
    "addr:full":"Rue D'eghez\u00e9e 54 Jemeppe-sur-sambre Namur 5190",
    "addr:housenumber":"54",
    "addr:postcode":"5190",
    "addr:street":"Rue D'Egheze \u0301E",
    "iso:country":"BE",
    "sg:address":"Rue D'eghez\u00e9e 54",
    "sg:city":"Jemeppe-sur-sambre",
    "sg:classifiers":[
        {
            "category":"Home & Garden",
            "subcategory":"Kitchen Supply",
            "type":"Retail Goods"
        }
    ],
    "sg:phone":"+32 71 78 68 00",
    "sg:postcode":"5190",
    "sg:province":"Namur",
    "sg:tags":[
        "plate",
        "-",
        "miscellaneous"
    ],
    "wof:name":"Bouttens Sa",
    "wof:placetype":"venue"
},
  "geometry": {"coordinates":[4.668885231,50.4627342224],"type":"Point"}
}