{
  "type": "Feature",
  "properties": {
    "addr:full":"Maurits Sabbestraat 125 Mechelen Antwerpen 2800",
    "addr:housenumber":"125",
    "addr:postcode":"2800",
    "addr:street":"Maurits Sabbestraat",
    "iso:country":"BE",
    "sg:address":"Maurits Sabbestraat 125",
    "sg:city":"Mechelen",
    "sg:classifiers":[
        {
            "category":"Autos & Motor Vehicles",
            "subcategory":"Fuel & Gas Station",
            "type":"Retail Goods"
        }
    ],
    "sg:phone":"+32 15 28 62 23",
    "sg:postcode":"2800",
    "sg:province":"Antwerpen",
    "wof:name":"Esso-festraets Nv",
    "wof:placetype":"venue"
},
  "geometry": {"coordinates":[4.4736227989,51.0376281738],"type":"Point"}
}