{
  "type": "Feature",
  "properties": {
    "iso:country":"BE",
    "sg:address":"Rue De La Corderie 3",
    "sg:city":"Wavre",
    "sg:classifiers":[
        {
            "category":"Banks & Credit Unions",
            "subcategory":"Financial Services",
            "type":"Services"
        }
    ],
    "sg:postcode":"1300",
    "sg:province":"Brabant Wallon",
    "sg:tags":[
        "financing"
    ],
    "wof:name":"Ifn Finance T.a.v. E. Bakker Nv",
    "wof:placetype":"venue"
},
  "geometry": {"coordinates":[4.4784197807,51.9228897095],"type":"Point"}
}