{
  "type": "Feature",
  "properties": {
    "iso:country":"BE",
    "sg:address":"Diestsestraat 15",
    "sg:city":"Leuven",
    "sg:orig_category":"Catering and organisatie van feesten Slagers Voedingsspeciaalzaken",
    "sg:phone":"+32 16 22 17 07",
    "sg:postcode":"3000",
    "sg:province":"Vlaams-Brabant",
    "wof:name":"De Bontridder",
    "wof:placetype":"venue"
},
  "geometry": {"coordinates":[4.7025499344,50.8798179626],"type":"Point"}
}