{
  "type": "Feature",
  "properties": {
    "addr:full":"Av. Mozart 42 Mouscron Hainaut 7700",
    "addr:housenumber":"42",
    "addr:postcode":"7700",
    "addr:street":"Av. Mozart",
    "iso:country":"BE",
    "sg:address":"Av. Mozart 42",
    "sg:city":"Mouscron",
    "sg:orig_category":"Installation de menuiserie m\u00e9tallique. Rev\u00eatements de sols and murs",
    "sg:phone":"+32 56 84 24 84",
    "sg:postcode":"7700",
    "sg:province":"Hainaut",
    "wof:name":"A.v.m. Construct",
    "wof:placetype":"venue"
},
  "geometry": {"coordinates":[3.2145800591,50.7437934875],"type":"Point"}
}