{
  "type": "Feature",
  "properties": {
    "iso:country":"BE",
    "sg:address":"Moleken 54",
    "sg:city":"Wichelen",
    "sg:classifiers":[
        {
            "category":"Freight",
            "type":"Transportation"
        }
    ],
    "sg:phone":"+32 52 42 85 85",
    "sg:postcode":"9260",
    "sg:province":"Oost-Vlaanderen",
    "sg:tags":[
        "-",
        "transport"
    ],
    "wof:name":"Express Couriers European",
    "wof:placetype":"venue"
},
  "geometry": {"coordinates":[3.9663701057,51.0081481934],"type":"Point"}
}