{
  "type": "Feature",
  "properties": {
    "iso:country":"BE",
    "sg:address":"Kuhlmannlaan 36",
    "sg:city":"Gent (sint-kruis-winkel)",
    "sg:orig_category":"Non-Classified Establishments",
    "sg:phone":"+32 9 343 02 02",
    "sg:postcode":"9042",
    "sg:province":"Oost-Vlaanderen",
    "wof:name":"Fuji Oil Europe",
    "wof:placetype":"venue"
},
  "geometry": {"coordinates":[3.7919890881,51.1775779724],"type":"Point"}
}