{
  "type": "Feature",
  "properties": {
    "addr:full":"Rue Victor Libert 20 Marche-en-famenne Luxembourg 6900",
    "addr:housenumber":"20",
    "addr:postcode":"6900",
    "addr:street":"Rue Victor Libert",
    "iso:country":"BE",
    "sg:address":"Rue Victor Libert 20",
    "sg:city":"Marche-en-famenne",
    "sg:orig_category":"V\u00e9t\u00e9rinaires",
    "sg:phone":"+32 84 31 11 52",
    "sg:postcode":"6900",
    "sg:province":"Luxembourg",
    "wof:name":"Christian Massard",
    "wof:placetype":"venue"
},
  "geometry": {"coordinates":[5.3397250175,50.2279472351],"type":"Point"}
}