{
  "type": "Feature",
  "properties": {
    "addr:full":"Oregondreef 2 Poperinge West-Vlaanderen 8970",
    "addr:housenumber":"2",
    "addr:postcode":"8970",
    "addr:street":"Oregondreef",
    "iso:country":"BE",
    "sg:address":"Oregondreef 2",
    "sg:city":"Poperinge",
    "sg:classifiers":[
        {
            "category":"Professional",
            "subcategory":"Accounting & Tax Preparation",
            "type":"Services"
        }
    ],
    "sg:phone":"+32 57 33 62 41",
    "sg:postcode":"8970",
    "sg:province":"West-Vlaanderen",
    "sg:tags":[
        "bookkeeper"
    ],
    "wof:name":"Schelpe Chr",
    "wof:placetype":"venue"
},
  "geometry": {"coordinates":[2.7365911007,50.8483657837],"type":"Point"}
}