{
  "type": "Feature",
  "properties": {
    "addr:full":"Hoogstraat 28 Brugge West-Vlaanderen 8000",
    "addr:housenumber":"28",
    "addr:postcode":"8000",
    "addr:street":"Hoogstraat",
    "iso:country":"BE",
    "sg:address":"Hoogstraat 28",
    "sg:city":"Brugge",
    "sg:classifiers":[
        {
            "category":"Home & Garden",
            "subcategory":"Home Furnishings",
            "type":"Retail Goods"
        }
    ],
    "sg:phone":"+32 50 33 83 32",
    "sg:postcode":"8000",
    "sg:province":"West-Vlaanderen",
    "sg:tags":[
        "interior",
        "decoration"
    ],
    "wof:name":"De Clerck Decoratie",
    "wof:placetype":"venue"
},
  "geometry": {"coordinates":[3.2300429344,51.2097206116],"type":"Point"}
}