{
  "type": "Feature",
  "properties": {
    "iso:country":"BE",
    "sg:address":"Ninoofsesteenweg 47",
    "sg:city":"Lennik",
    "sg:orig_category":"Speciaalzaken",
    "sg:phone":"+32 2 582 25 31",
    "sg:postcode":"1750",
    "sg:province":"Vlaams-Brabant",
    "wof:name":"Sierschouwen Ooghe & Zoon",
    "wof:placetype":"venue"
},
  "geometry": {"coordinates":[4.1494488716,50.8353042603],"type":"Point"}
}