{
  "type": "Feature",
  "properties": {
    "addr:full":"Mechelsesteenweg 75bb Sint-katelijne-waver Antwerpen 2860",
    "addr:housenumber":"75bb",
    "addr:postcode":"2860",
    "addr:street":"Mechelsesteenweg",
    "iso:country":"BE",
    "sg:address":"Mechelsesteenweg 75bb",
    "sg:city":"Sint-katelijne-waver",
    "sg:orig_category":"V\u00e9hicules automobiles",
    "sg:phone":"+32 15 55 77 08",
    "sg:postcode":"2860",
    "sg:province":"Antwerpen",
    "wof:name":"Sab Export",
    "wof:placetype":"venue"
},
  "geometry": {"coordinates":[4.5269789696,51.0605316162],"type":"Point"}
}