{
  "type": "Feature",
  "properties": {
    "iso:country":"BE",
    "sg:address":"Kinderstraat 22",
    "sg:city":"Lommel",
    "sg:classifiers":[
        {
            "category":"Personal",
            "subcategory":"Beauty Salon",
            "type":"Services"
        }
    ],
    "sg:phone":"+32 11 54 47 29",
    "sg:postcode":"3920",
    "sg:province":"Limburg",
    "sg:tags":[
        "de",
        "coiffure"
    ],
    "wof:name":"Kapsalon Annita",
    "wof:placetype":"venue"
},
  "geometry": {"coordinates":[5.3384709358,51.2427444458],"type":"Point"}
}