{
  "type": "Feature",
  "properties": {
    "addr:full":"Chauss\u00e9e D'ath 244 Enghien (marcq) Hainaut 7850",
    "addr:housenumber":"244",
    "addr:postcode":"7850",
    "addr:street":"Chausse\u0301E D'Ath",
    "iso:country":"BE",
    "sg:address":"Chauss\u00e9e D'ath 244",
    "sg:city":"Enghien (marcq)",
    "sg:classifiers":[
        {
            "category":"Home & Garden",
            "subcategory":"Home Furnishings",
            "type":"Retail Goods"
        }
    ],
    "sg:phone":"+32 2 397 01 10",
    "sg:postcode":"7850",
    "sg:province":"Hainaut",
    "sg:tags":[
        "interior",
        "decoration"
    ],
    "wof:name":"Decor Team Sa",
    "wof:placetype":"venue"
},
  "geometry": {"coordinates":[3.9898118973,50.6813011169],"type":"Point"}
}