{
  "type": "Feature",
  "properties": {
    "iso:country":"BE",
    "sg:address":"Sint-anna 35",
    "sg:city":"Kortrijk",
    "sg:orig_category":"Eleveurs de bovins",
    "sg:phone":"+32 56 22 59 19",
    "sg:postcode":"8500",
    "sg:province":"West-Vlaanderen",
    "wof:name":"Bernard Blauwblomme",
    "wof:placetype":"venue"
},
  "geometry": {"coordinates":[3.2495379448,50.7919883728],"type":"Point"}
}