{
  "type": "Feature",
  "properties": {
    "iso:country":"BE",
    "sg:address":"Rue Vanderkindere 382",
    "sg:city":"Ukkel/uccle",
    "sg:orig_category":"Quincailleries. Plomberie, chauffage and installations sanitaires",
    "sg:phone":"+32 2 343 08 84",
    "sg:postcode":"1180",
    "sg:province":"Bruxelles-Capitale",
    "wof:name":"Brico-sanitaire Blogie",
    "wof:placetype":"venue"
},
  "geometry": {"coordinates":[4.3575959206,50.8143806458],"type":"Point"}
}