{
  "type": "Feature",
  "properties": {
    "iso:country":"BE",
    "sg:address":"Moeskroensesteenweg 94",
    "sg:city":"Kortrijk (aalbeke)",
    "sg:classifiers":[
        {
            "category":"Professional",
            "subcategory":"Management & Consulting",
            "type":"Services"
        }
    ],
    "sg:phone":"+32 56 42 69 25",
    "sg:postcode":"8511",
    "sg:province":"West-Vlaanderen",
    "sg:tags":[
        "consultant"
    ],
    "wof:name":"Clarysse M",
    "wof:placetype":"venue"
},
  "geometry": {"coordinates":[3.2286109924,50.7778587341],"type":"Point"}
}