{
  "type": "Feature",
  "properties": {
    "addr:full":"Rue Des Vennes 387 Li\u00e8ge 1 (li\u00e8ge 2) Li\u00e8ge 4020",
    "addr:housenumber":"387;1;2",
    "addr:postcode":"4020",
    "addr:street":"Rue Des Vennes",
    "iso:country":"BE",
    "sg:address":"Rue Des Vennes 387",
    "sg:city":"Li\u00e8ge 1 (li\u00e8ge 2)",
    "sg:classifiers":[
        {
            "category":"Health Services",
            "subcategory":"Health Practitioner",
            "type":"Services"
        }
    ],
    "sg:phone":"+32 4 344 32 22",
    "sg:postcode":"4020",
    "sg:province":"Li\u00e8ge",
    "sg:tags":[
        "physiotherapist"
    ],
    "wof:name":"Liebin B\u00e9n\u00e9dicte",
    "wof:placetype":"venue"
},
  "geometry": {"coordinates":[5.5841622353,50.6275177002],"type":"Point"}
}