{
  "type": "Feature",
  "properties": {
    "iso:country":"BE",
    "sg:address":"Wetstraat 43",
    "sg:city":"Antwerpen",
    "sg:classifiers":[
        {
            "category":"Health Services",
            "subcategory":"Health Practitioner",
            "type":"Services"
        }
    ],
    "sg:phone":"+32 3 235 66 12",
    "sg:postcode":"2060",
    "sg:province":"Antwerpen",
    "sg:tags":[
        "physiotherapist"
    ],
    "wof:name":"Mainil P",
    "wof:placetype":"venue"
},
  "geometry": {"coordinates":[4.4287772179,51.220451355],"type":"Point"}
}