{
  "type": "Feature",
  "properties": {
    "iso:country":"BE",
    "sg:address":"Westerlaan 27",
    "sg:city":"Waregem",
    "sg:orig_category":"Chemicali\u00ebn Gh",
    "sg:phone":"+32 56 61 36 63",
    "sg:postcode":"8790",
    "sg:province":"West-Vlaanderen",
    "wof:name":"Devimul",
    "wof:placetype":"venue"
},
  "geometry": {"coordinates":[3.4235680103,50.8855552673],"type":"Point"}
}