{
  "type": "Feature",
  "properties": {
    "iso:country":"BE",
    "sg:address":"Graaf De Fienneslaan 12",
    "sg:city":"Edegem",
    "sg:orig_category":"Fotografen and fotostudio's",
    "sg:phone":"+32 3 440 45 45",
    "sg:postcode":"2650",
    "sg:province":"Antwerpen",
    "wof:name":"Vivaria",
    "wof:placetype":"venue"
},
  "geometry": {"coordinates":[4.4322390556,51.1592102051],"type":"Point"}
}