{
  "type": "Feature",
  "properties": {
    "iso:country":"BE",
    "sg:address":"Dorpsstraat 43",
    "sg:city":"Zonhoven",
    "sg:orig_category":"Dansscholen",
    "sg:phone":"+32 11 81 73 73",
    "sg:postcode":"3520",
    "sg:province":"Limburg",
    "wof:name":"Cadans",
    "wof:placetype":"venue"
},
  "geometry": {"coordinates":[5.3672971725,50.9938964844],"type":"Point"}
}