{
  "type": "Feature",
  "properties": {
    "addr:full":"Kerkplein 5 Lommel Limburg 3920",
    "addr:housenumber":"5",
    "addr:postcode":"3920",
    "addr:street":"Kerkplein",
    "iso:country":"BE",
    "sg:address":"Kerkplein 5",
    "sg:city":"Lommel",
    "sg:orig_category":"Boucheries",
    "sg:phone":"+32 11 54 15 22",
    "sg:postcode":"3920",
    "sg:province":"Limburg",
    "wof:name":"Verheyen",
    "wof:placetype":"venue"
},
  "geometry": {"coordinates":[5.3101768494,51.2306976318],"type":"Point"}
}