{
  "type": "Feature",
  "properties": {
    "iso:country":"BE",
    "sg:address":"Rue Supexhe 88",
    "sg:city":"Blegny",
    "sg:orig_category":"Epiceries",
    "sg:phone":"+32 4 387 67 28",
    "sg:postcode":"4672",
    "sg:province":"Li\u00e8ge",
    "wof:name":"Luc Delnooz",
    "wof:placetype":"venue"
},
  "geometry": {"coordinates":[5.7018008232,50.6961021423],"type":"Point"}
}