{
  "type": "Feature",
  "properties": {
    "iso:country":"BE",
    "sg:address":"Loppemsestraat 1",
    "sg:city":"Zedelgem",
    "sg:classifiers":[
        {
            "category":"Bars & Pubs",
            "type":"Food & Drink"
        }
    ],
    "sg:phone":"+32 50 20 05 91",
    "sg:postcode":"8210",
    "sg:province":"West-Vlaanderen",
    "wof:name":"St-joris (cafe)",
    "wof:placetype":"venue"
},
  "geometry": {"coordinates":[3.1373949051,51.1424751282],"type":"Point"}
}