{
  "type": "Feature",
  "properties": {
    "iso:country":"BE",
    "sg:address":"Zandbergstraat 42",
    "sg:city":"Kortrijk",
    "sg:classifiers":[
        {
            "category":"Cafe",
            "type":"Food & Drink"
        }
    ],
    "sg:phone":"+32 56 20 50 47",
    "sg:postcode":"8500",
    "sg:province":"West-Vlaanderen",
    "sg:tags":[
        "caf\u00e9s"
    ],
    "wof:name":"Caf\u00c9 De Nieuwe Zandberg",
    "wof:placetype":"venue"
},
  "geometry": {"coordinates":[3.2861740589,50.8370056152],"type":"Point"}
}