{
  "type": "Feature",
  "properties": {
    "iso:country":"BE",
    "sg:address":"Waterloose Steenweg 124",
    "sg:city":"Sint-gillis/saint-gilles",
    "sg:orig_category":"Apotheken",
    "sg:phone":"+32 2 537 79 02",
    "sg:postcode":"1060",
    "sg:province":"Bruxelles-Capitale",
    "wof:name":"De Vriese Pharmacie",
    "wof:placetype":"venue"
},
  "geometry": {"coordinates":[4.3445549011,50.8284645081],"type":"Point"}
}