{
  "type": "Feature",
  "properties": {
    "iso:country":"BE",
    "sg:address":"Beekstraat 23",
    "sg:city":"Oud-heverlee (sint-joris-weert)",
    "sg:classifiers":[
        {
            "category":"Food & Beverages",
            "subcategory":"Supermarket",
            "type":"Retail Goods"
        }
    ],
    "sg:phone":"+32 16 47 15 14",
    "sg:postcode":"3051",
    "sg:province":"Vlaams-Brabant",
    "sg:tags":[
        "department",
        "store"
    ],
    "wof:name":"Spar Markt Bvba",
    "wof:placetype":"venue"
},
  "geometry": {"coordinates":[4.649532795,50.8026618958],"type":"Point"}
}