{
  "type": "Feature",
  "properties": {
    "iso:country":"BE",
    "sg:address":"Place De Chablis 20",
    "sg:city":"Ferrieres",
    "sg:orig_category":"Postkantoren Verzekeringsmakelaars and experts",
    "sg:phone":"+32 86 40 00 88",
    "sg:postcode":"4190",
    "sg:province":"Li\u00e8ge",
    "wof:name":"La Poste",
    "wof:placetype":"venue"
},
  "geometry": {"coordinates":[5.6053571701,50.4046974182],"type":"Point"}
}