{
  "type": "Feature",
  "properties": {
    "addr:full":"'s Gravenwinkelstraat 1 Torhout West-Vlaanderen 8820",
    "addr:housenumber":"1",
    "addr:postcode":"8820",
    "addr:street":"';Gravenwinkelstraat",
    "iso:country":"BE",
    "sg:address":"'s Gravenwinkelstraat 1",
    "sg:city":"Torhout",
    "sg:orig_category":"Belastingconsulenten Diverse juridische dienstverlening",
    "sg:phone":"+32 50 22 02 93",
    "sg:postcode":"8820",
    "sg:province":"West-Vlaanderen",
    "wof:name":"Dudal & Delie",
    "wof:placetype":"venue"
},
  "geometry": {"coordinates":[3.0988879204,51.0659179688],"type":"Point"}
}