{
  "type": "Feature",
  "properties": {
    "addr:full":"Opstalstraat 64 Zottegem (velzeke-ruddershove) Oost-Vlaanderen 9620",
    "addr:housenumber":"64",
    "addr:postcode":"9620",
    "addr:street":"Opstalstraat",
    "iso:country":"BE",
    "sg:address":"Opstalstraat 64",
    "sg:city":"Zottegem (velzeke-ruddershove)",
    "sg:classifiers":[
        {
            "category":"Professional",
            "subcategory":"Art Services",
            "type":"Services"
        }
    ],
    "sg:phone":"+32 9 360 99 10",
    "sg:postcode":"9620",
    "sg:province":"Oost-Vlaanderen",
    "sg:tags":[
        "graphic",
        "designer"
    ],
    "wof:name":"Vekeman E",
    "wof:placetype":"venue"
},
  "geometry": {"coordinates":[3.8112111092,50.871181488],"type":"Point"}
}