{
  "type": "Feature",
  "properties": {
    "addr:full":"Parkstraat 109 Vilvoorde (groot) Vlaams-Brabant 1800",
    "addr:housenumber":"109;1800",
    "addr:street":"Parkstraat;Groot Vlaams-Brabant",
    "iso:country":"BE",
    "sg:address":"Parkstraat 109",
    "sg:city":"Vilvoorde (groot)",
    "sg:orig_category":"Pain, p\u00e2tisseries and confiseries. Epiceries",
    "sg:phone":"+32 2 253 13 00",
    "sg:postcode":"1800",
    "sg:province":"Vlaams-Brabant",
    "wof:name":"Bij Jos",
    "wof:placetype":"venue"
},
  "geometry": {"coordinates":[4.4291329384,50.9216079712],"type":"Point"}
}