{
  "type": "Feature",
  "properties": {
    "iso:country":"BE",
    "sg:address":"Kuipersstraat 4",
    "sg:city":"Wevelgem",
    "sg:orig_category":"Meubelzaken, woning- and keukeninrichting",
    "sg:phone":"+32 56 40 25 73",
    "sg:postcode":"8560",
    "sg:province":"West-Vlaanderen",
    "wof:name":"Divani International",
    "wof:placetype":"venue"
},
  "geometry": {"coordinates":[3.1722199917,50.8028297424],"type":"Point"}
}