{
  "type": "Feature",
  "properties": {
    "iso:country":"BE",
    "sg:address":"Avenue De Spa 89",
    "sg:city":"Verviers",
    "sg:orig_category":"Plaatsen van vloer- and muurbekleding Schilders",
    "sg:phone":"+32 87 23 06 18",
    "sg:postcode":"4802",
    "sg:province":"Li\u00e8ge",
    "wof:name":"Vincent Fonsny",
    "wof:placetype":"venue"
},
  "geometry": {"coordinates":[5.8671250343,50.5714111328],"type":"Point"}
}