{
  "type": "Feature",
  "properties": {
    "iso:country":"BE",
    "sg:address":"Gaston Baertstraat 20",
    "sg:city":"Deinze (sint-martens-leerne)",
    "sg:classifiers":[
        {
            "category":"Health Services",
            "subcategory":"Health Practitioner",
            "type":"Services"
        }
    ],
    "sg:phone":"+32 9 281 03 22",
    "sg:postcode":"9800",
    "sg:province":"Oost-Vlaanderen",
    "sg:tags":[
        "dietitian"
    ],
    "wof:name":"Bogaert T",
    "wof:placetype":"venue"
},
  "geometry": {"coordinates":[3.5835080147,51.0153160095],"type":"Point"}
}