{
  "type": "Feature",
  "properties": {
    "iso:country":"BE",
    "sg:address":"Neerstraat 3",
    "sg:city":"Asse",
    "sg:orig_category":"Leisure articles",
    "sg:phone":"+32 2 453 03 76",
    "sg:postcode":"1730",
    "sg:province":"Vlaams-Brabant",
    "wof:name":"Hobby Kiekeboe",
    "wof:placetype":"venue"
},
  "geometry": {"coordinates":[4.1550168991,50.9159545898],"type":"Point"}
}