{
  "type": "Feature",
  "properties": {
    "addr:full":"Ambachtstraat 24 Torhout West-Vlaanderen 8820",
    "addr:housenumber":"24",
    "addr:postcode":"8820",
    "addr:street":"Ambachtstraat",
    "iso:country":"BE",
    "sg:address":"Ambachtstraat 24",
    "sg:city":"Torhout",
    "sg:classifiers":[
        {
            "category":"Mining & Drilling",
            "type":"Manufacturing & Wholesale Goods"
        }
    ],
    "sg:phone":"+32 50 21 62 27",
    "sg:postcode":"8820",
    "sg:province":"West-Vlaanderen",
    "sg:tags":[
        "concrete",
        "reinforced",
        "sawing"
    ],
    "wof:name":"Betonboringen Diamond Bvba",
    "wof:placetype":"venue"
},
  "geometry": {"coordinates":[3.1109039783,51.0795021057],"type":"Point"}
}