{
  "type": "Feature",
  "properties": {
    "iso:country":"BE",
    "sg:address":"Koophandelsplein 32",
    "sg:city":"Gent",
    "sg:orig_category":"Studios photographiques. Equipement photographique",
    "sg:phone":"+32 9 233 33 42",
    "sg:postcode":"9000",
    "sg:province":"Oost-Vlaanderen",
    "wof:name":"Flash One",
    "wof:placetype":"venue"
},
  "geometry": {"coordinates":[3.7211689949,51.0494689941],"type":"Point"}
}