{
  "type": "Feature",
  "properties": {
    "iso:country":"BE",
    "sg:address":"Hubert Fr\u00e8re-orbanlaan 644-649",
    "sg:city":"Gent",
    "sg:orig_category":"Newspapers, magazines, periodicals - Distribution",
    "sg:phone":"+32 9 224 43 87",
    "sg:postcode":"9000",
    "sg:province":"Oost-Vlaanderen",
    "wof:name":"Mode...information",
    "wof:placetype":"venue"
},
  "geometry": {"coordinates":[3.7364890575,51.0403404236],"type":"Point"}
}