{
  "type": "Feature",
  "properties": {
    "addr:full":"Steenweg Hulst-lessen 64 Temse (elversele) Oost-Vlaanderen 9140",
    "addr:housenumber":"64",
    "addr:postcode":"9140",
    "addr:street":"Steenweg Hulst-Lessen",
    "iso:country":"BE",
    "sg:address":"Steenweg Hulst-lessen 64",
    "sg:city":"Temse (elversele)",
    "sg:classifiers":[
        {
            "category":"Professional",
            "subcategory":"Management & Consulting",
            "type":"Services"
        }
    ],
    "sg:phone":"+32 52 46 35 81",
    "sg:postcode":"9140",
    "sg:province":"Oost-Vlaanderen",
    "sg:tags":[
        "tax-consultants"
    ],
    "wof:name":"De Cock H",
    "wof:placetype":"venue"
},
  "geometry": {"coordinates":[4.1438279152,51.1317596436],"type":"Point"}
}