{
  "type": "Feature",
  "properties": {
    "iso:country":"BE",
    "sg:address":"Houtweg 56",
    "sg:city":"Brussel",
    "sg:classifiers":[
        {
            "category":"Bus Stop",
            "subcategory":"None",
            "type":"Transportation"
        }
    ],
    "sg:phone":"+32 2 242 76 60",
    "sg:postcode":"1140",
    "sg:province":"Bruxelles-Capitale",
    "sg:tags":[
        "dimmer",
        "switch",
        "dimmers"
    ],
    "wof:name":"Sgl S.a.",
    "wof:placetype":"venue"
},
  "geometry": {"coordinates":[4.4065318108,50.882598877],"type":"Point"}
}