{
  "type": "Feature",
  "properties": {
    "addr:full":"Dorpsstraat 9a Zutendaal Limburg 3690",
    "addr:housenumber":"9a",
    "addr:postcode":"3690",
    "addr:street":"Dorpsstraat",
    "iso:country":"BE",
    "sg:address":"Dorpsstraat 9a",
    "sg:city":"Zutendaal",
    "sg:classifiers":[
        {
            "category":"Personal",
            "subcategory":"Beauty Salon",
            "type":"Services"
        }
    ],
    "sg:phone":"+32 89 61 41 11",
    "sg:postcode":"3690",
    "sg:province":"Limburg",
    "sg:tags":[
        "de",
        "coiffure"
    ],
    "wof:name":"Coiffure Stefan",
    "wof:placetype":"venue"
},
  "geometry": {"coordinates":[5.5732059479,50.9315986633],"type":"Point"}
}