{
  "type": "Feature",
  "properties": {
    "iso:country":"BE",
    "sg:address":"Rue Des Ixellois 3",
    "sg:city":"Li\u00e8ge 1",
    "sg:classifiers":[
        {
            "category":"Social Services",
            "type":"Services"
        }
    ],
    "sg:phone":"+32 4 253 28 24",
    "sg:postcode":"4000",
    "sg:province":"Li\u00e8ge",
    "wof:name":"Ligue Des Familles",
    "wof:placetype":"venue"
},
  "geometry": {"coordinates":[5.5668210983,50.629234314],"type":"Point"}
}