{
  "type": "Feature",
  "properties": {
    "addr:full":"Vinkemolenstraat 33 Oosterzele Oost-Vlaanderen 9860",
    "addr:housenumber":"33",
    "addr:postcode":"9860",
    "addr:street":"Vinkemolenstraat;Oost-Vlaanderen",
    "iso:country":"BE",
    "sg:address":"Vinkemolenstraat 33",
    "sg:city":"Oosterzele",
    "sg:classifiers":[
        {
            "category":"Food & Beverages",
            "subcategory":"Fruits & Vegetables",
            "type":"Retail Goods"
        }
    ],
    "sg:phone":"+32 9 362 05 31",
    "sg:postcode":"9860",
    "sg:province":"Oost-Vlaanderen",
    "sg:tags":[
        "l\u00e9gumes"
    ],
    "wof:name":"Hans Matthijs",
    "wof:placetype":"venue"
},
  "geometry": {"coordinates":[3.8085129261,50.9510765076],"type":"Point"}
}