{
  "type": "Feature",
  "properties": {
    "addr:full":"Kamershoek 207 Zele Oost-Vlaanderen 9240",
    "addr:housenumber":"207",
    "addr:postcode":"9240",
    "addr:street":"Kamershoek",
    "iso:country":"BE",
    "sg:address":"Kamershoek 207",
    "sg:city":"Zele",
    "sg:classifiers":[
        {
            "category":"Building & Trades",
            "subcategory":"Plumbing",
            "type":"Services"
        }
    ],
    "sg:phone":"+32 52 44 68 55",
    "sg:postcode":"9240",
    "sg:province":"Oost-Vlaanderen",
    "sg:tags":[
        "repair",
        "mainten",
        "-",
        "central",
        "heating"
    ],
    "wof:name":"Viesmann/ Van Hoye Patrick",
    "wof:placetype":"venue"
},
  "geometry": {"coordinates":[4.0087389946,51.0402297974],"type":"Point"}
}