{
  "type": "Feature",
  "properties": {
    "iso:country":"BE",
    "sg:address":"Korteboeken 62",
    "sg:city":"Zomergem",
    "sg:orig_category":"Dranken Gh",
    "sg:phone":"+32 9 372 75 76",
    "sg:postcode":"9930",
    "sg:province":"Oost-Vlaanderen",
    "wof:name":"Drankenhandel De Fruyt",
    "wof:placetype":"venue"
},
  "geometry": {"coordinates":[3.5862019062,51.1198196411],"type":"Point"}
}