{
  "type": "Feature",
  "properties": {
    "addr:full":"Lageweg 121 Hoboken Antwerpen 2660",
    "addr:housenumber":"121",
    "addr:postcode":"2660",
    "addr:street":"Lageweg",
    "iso:country":"BE",
    "sg:address":"Lageweg 121",
    "sg:city":"Hoboken",
    "sg:orig_category":"Pompes and compresseurs Fab. Constructions non r\u00e9sidentielles sp\u00e9cifiques",
    "sg:phone":"+32 3 827 91 13",
    "sg:postcode":"2660",
    "sg:province":"Antwerpen",
    "wof:name":"A.p.c.",
    "wof:placetype":"venue"
},
  "geometry": {"coordinates":[4.3584499359,51.1837234497],"type":"Point"}
}