{
  "type": "Feature",
  "properties": {
    "addr:full":"Hogebaan 62 Brecht (sint-job-in-'t Goor) Antwerpen 2960",
    "addr:housenumber":"62",
    "addr:postcode":"2960",
    "addr:street":"Hogebaan;' T Goor",
    "iso:country":"BE",
    "sg:address":"Hogebaan 62",
    "sg:city":"Brecht (sint-job-in-'t Goor)",
    "sg:classifiers":[
        {
            "category":"Animal Shelter",
            "type":"Public Place"
        }
    ],
    "sg:phone":"+32 3 636 17 32",
    "sg:postcode":"2960",
    "sg:province":"Antwerpen",
    "wof:name":"Dierenpension Woef",
    "wof:placetype":"venue"
},
  "geometry": {"coordinates":[4.5596542358,51.2944259644],"type":"Point"}
}