{
  "type": "Feature",
  "properties": {
    "iso:country":"BE",
    "sg:address":"Houtestraat 10",
    "sg:city":"Mechelen (hombeek)",
    "sg:classifiers":[
        {
            "category":"Manufacturing",
            "subcategory":"Tools & Machinery",
            "type":"Manufacturing & Wholesale Goods"
        }
    ],
    "sg:phone":"+32 15 42 38 22",
    "sg:postcode":"2811",
    "sg:province":"Antwerpen",
    "sg:tags":[
        "-"
    ],
    "wof:name":"Vloebergh L",
    "wof:placetype":"venue"
},
  "geometry": {"coordinates":[4.4349970818,51.0031509399],"type":"Point"}
}