{
  "type": "Feature",
  "properties": {
    "addr:full":"Dorpsstraat 59 Knokke-heist (westkapelle) West-Vlaanderen 8300",
    "addr:housenumber":"59",
    "addr:postcode":"8300",
    "addr:street":"Dorpsstraat",
    "iso:country":"BE",
    "sg:address":"Dorpsstraat 59",
    "sg:city":"Knokke-heist (westkapelle)",
    "sg:classifiers":[
        {
            "category":"Health Services",
            "subcategory":"Dentist",
            "type":"Services"
        }
    ],
    "sg:phone":"+32 50 60 26 94",
    "sg:postcode":"8300",
    "sg:province":"West-Vlaanderen",
    "wof:name":"Paridaen Mario",
    "wof:placetype":"venue"
},
  "geometry": {"coordinates":[3.287694931,51.3467254639],"type":"Point"}
}