{
  "type": "Feature",
  "properties": {
    "addr:full":"Laarstraat 41 Rumst (reet) Antwerpen 2840",
    "addr:housenumber":"41",
    "addr:postcode":"2840",
    "addr:street":"Laarstraat",
    "iso:country":"BE",
    "sg:address":"Laarstraat 41",
    "sg:city":"Rumst (reet)",
    "sg:classifiers":[
        {
            "category":"Shopping",
            "subcategory":"Bicycles & Sporting Goods",
            "type":"Retail Goods"
        }
    ],
    "sg:phone":"+32 3 888 78 50",
    "sg:postcode":"2840",
    "sg:province":"Antwerpen",
    "sg:tags":[
        "-"
    ],
    "wof:name":"De Zwaluw Nv",
    "wof:placetype":"venue"
},
  "geometry": {"coordinates":[4.4156918526,51.1009712219],"type":"Point"}
}