{
  "type": "Feature",
  "properties": {
    "iso:country":"BE",
    "sg:address":"Bredabaan 507",
    "sg:city":"Merksem",
    "sg:orig_category":"Disneyland Parijs Reisbureaus",
    "sg:phone":"+32 3 646 63 37",
    "sg:postcode":"2170",
    "sg:province":"Antwerpen",
    "wof:name":"Neckermann",
    "wof:placetype":"venue"
},
  "geometry": {"coordinates":[4.4479951859,51.245426178],"type":"Point"}
}