{
  "type": "Feature",
  "properties": {
    "addr:full":"Rue Du Vigneron 59 Charleroi Hainaut 6043",
    "addr:housenumber":"59",
    "addr:postcode":"6043",
    "addr:street":"Rue Du Vigneron;Hainaut",
    "iso:country":"BE",
    "sg:address":"Rue Du Vigneron 59",
    "sg:city":"Charleroi",
    "sg:orig_category":"Maisons de repos and r\u00e9sidences",
    "sg:phone":"+32 71 35 28 16",
    "sg:postcode":"6043",
    "sg:province":"Hainaut",
    "wof:name":"S\u00c9niorie Du Vigneron",
    "wof:placetype":"venue"
},
  "geometry": {"coordinates":[4.4839549065,50.4479637146],"type":"Point"}
}