{
  "type": "Feature",
  "properties": {
    "addr:full":"Opperstraat 41 Moerbeke Oost-Vlaanderen 9180",
    "addr:housenumber":"41",
    "addr:postcode":"9180",
    "addr:street":"Opperstraat",
    "iso:country":"BE",
    "sg:address":"Opperstraat 41",
    "sg:city":"Moerbeke",
    "sg:orig_category":"Kapsalons",
    "sg:phone":"+32 9 346 88 43",
    "sg:postcode":"9180",
    "sg:province":"Oost-Vlaanderen",
    "wof:name":"Coiffure Marleen",
    "wof:placetype":"venue"
},
  "geometry": {"coordinates":[3.9385299683,51.1742477417],"type":"Point"}
}