{
  "type": "Feature",
  "properties": {
    "iso:country":"BE",
    "sg:address":"Drielindenbaan 53",
    "sg:city":"Merchtem",
    "sg:classifiers":[
        {
            "category":"Professional",
            "subcategory":"Computer Services",
            "type":"Services"
        }
    ],
    "sg:phone":"+32 52 37 63 37",
    "sg:postcode":"1785",
    "sg:province":"Vlaams-Brabant",
    "sg:tags":[
        "-",
        "processing",
        "data",
        "software"
    ],
    "wof:name":"Jaar2k",
    "wof:placetype":"venue"
},
  "geometry": {"coordinates":[4.220536232,50.9507980347],"type":"Point"}
}