{
  "type": "Feature",
  "properties": {
    "iso:country":"BE",
    "sg:address":"Kamperbaan 16",
    "sg:city":"Hechtel-eksel (hechtel)",
    "sg:classifiers":[
        {
            "category":"Banks & Credit Unions",
            "subcategory":"Investment Brokerage",
            "type":"Services"
        }
    ],
    "sg:phone":"+32 11 73 47 91",
    "sg:postcode":"3940",
    "sg:province":"Limburg",
    "sg:tags":[
        "printing",
        "-"
    ],
    "wof:name":"Vrinzen A",
    "wof:placetype":"venue"
},
  "geometry": {"coordinates":[5.364795208,51.1255340576],"type":"Point"}
}