{
  "type": "Feature",
  "properties": {
    "iso:country":"BE",
    "sg:address":"Bevrijdingslaan 18 Bus 2",
    "sg:city":"Ninove",
    "sg:orig_category":"Travaux de pl\u00e2trage. Construction de maisons. Constructions r\u00e9sidentielles sp\u00e9cifiques. Travaux de f",
    "sg:phone":"+32 54 33 75 01",
    "sg:postcode":"9400",
    "sg:province":"Oost-Vlaanderen",
    "wof:name":"Neirincks - De Coster Voegwerken",
    "wof:placetype":"venue"
},
  "geometry": {"coordinates":[4.0193018913,50.8332214355],"type":"Point"}
}