{
  "type": "Feature",
  "properties": {
    "iso:country":"BE",
    "sg:address":"Rue De L'epinette 26",
    "sg:city":"Boussu (hornu)",
    "sg:classifiers":[
        {
            "category":"Professional",
            "subcategory":"Engineering",
            "type":"Services"
        }
    ],
    "sg:phone":"+32 65 79 57 25",
    "sg:postcode":"7301",
    "sg:province":"Hainaut",
    "sg:tags":[
        "-"
    ],
    "wof:name":"Medici Philippe",
    "wof:placetype":"venue"
},
  "geometry": {"coordinates":[3.822936058,50.4269294739],"type":"Point"}
}