{
  "type": "Feature",
  "properties": {
    "iso:country":"BE",
    "sg:address":"Chemin Du Pont De Pierre 10",
    "sg:city":"Komen-waasten/comines-warneton",
    "sg:orig_category":"Eleveurs de bovins",
    "sg:phone":"+32 56 58 88 24",
    "sg:postcode":"7784",
    "sg:province":"Hainaut",
    "wof:name":"Luc Leplat",
    "wof:placetype":"venue"
},
  "geometry": {"coordinates":[2.9148728848,50.7530822754],"type":"Point"}
}