{
  "type": "Feature",
  "properties": {
    "iso:country":"BE",
    "sg:address":"Chauss\u00c9e De Ghlin 6ba",
    "sg:city":"Mons",
    "sg:orig_category":"Transports terrestres de voyageurs. Agences de voyages",
    "sg:phone":"+32 65 36 14 37",
    "sg:postcode":"7000",
    "sg:province":"Hainaut",
    "wof:name":"Voyages Van Gyseghem",
    "wof:placetype":"venue"
},
  "geometry": {"coordinates":[3.939125061,50.4639930725],"type":"Point"}
}