{
  "type": "Feature",
  "properties": {
    "addr:full":"Pontweg 19 Lokeren (daknam) Oost-Vlaanderen 9160",
    "addr:housenumber":"19",
    "addr:postcode":"9160",
    "addr:street":"Pontweg",
    "iso:country":"BE",
    "sg:address":"Pontweg 19",
    "sg:city":"Lokeren (daknam)",
    "sg:classifiers":[
        {
            "category":"Shopping",
            "subcategory":"Clothing, Apparel, & Fashions",
            "type":"Retail Goods"
        }
    ],
    "sg:phone":"+32 9 348 97 18",
    "sg:postcode":"9160",
    "sg:province":"Oost-Vlaanderen",
    "sg:tags":[
        "purchase",
        "clothing",
        "-",
        "sale",
        "second-hand"
    ],
    "wof:name":"Shahed Trading",
    "wof:placetype":"venue"
},
  "geometry": {"coordinates":[3.9871389866,51.1305809021],"type":"Point"}
}