{
  "type": "Feature",
  "properties": {
    "iso:country":"BE",
    "sg:address":"Rue Basse M\u00e9hagne 4",
    "sg:city":"Chaudfontaine (embourg)",
    "sg:classifiers":[
        {
            "category":"Education",
            "subcategory":"School",
            "type":"Public Place"
        }
    ],
    "sg:phone":"+32 4 367 45 36",
    "sg:postcode":"4053",
    "sg:province":"Li\u00e8ge",
    "sg:tags":[
        "-",
        "private"
    ],
    "wof:name":"Ecole Jean Xxiii",
    "wof:placetype":"venue"
},
  "geometry": {"coordinates":[5.616147995,50.5996513367],"type":"Point"}
}