{
  "type": "Feature",
  "properties": {
    "addr:full":"Schoolstraat 10 Ham Limburg 3945",
    "addr:housenumber":"10",
    "addr:postcode":"3945",
    "addr:street":"Schoolstraat",
    "iso:country":"BE",
    "sg:address":"Schoolstraat 10",
    "sg:city":"Ham",
    "sg:orig_category":"Sportcentra",
    "sg:phone":"+32 11 34 49 94",
    "sg:postcode":"3945",
    "sg:province":"Limburg",
    "wof:name":"Sportinfrastruktuur",
    "wof:placetype":"venue"
},
  "geometry": {"coordinates":[5.1776199341,51.1046104431],"type":"Point"}
}