{
  "type": "Feature",
  "properties": {
    "iso:country":"BE",
    "sg:address":"Chauss\u00e9e De Bruxelles 408",
    "sg:city":"Charleroi (jumet)",
    "sg:classifiers":[
        {
            "category":"Professional",
            "subcategory":"Detective & Security Services",
            "type":"Services"
        }
    ],
    "sg:phone":"+32 71 35 45 33",
    "sg:postcode":"6040",
    "sg:province":"Hainaut",
    "sg:tags":[
        "-",
        "system",
        "apparatus",
        "surveillance"
    ],
    "wof:name":"Augen Sa",
    "wof:placetype":"venue"
},
  "geometry": {"coordinates":[4.4315619469,50.456325531],"type":"Point"}
}