{
  "type": "Feature",
  "properties": {
    "addr:full":"Dorpsstraat 85 Heusden-zolder (zolder) Limburg 3550",
    "addr:housenumber":"85",
    "addr:postcode":"3550",
    "addr:street":"Dorpsstraat",
    "iso:country":"BE",
    "sg:address":"Dorpsstraat 85",
    "sg:city":"Heusden-zolder (zolder)",
    "sg:classifiers":[
        {
            "category":"Health Services",
            "subcategory":"Dentist",
            "type":"Services"
        }
    ],
    "sg:phone":"+32 11 53 72 88",
    "sg:postcode":"3550",
    "sg:province":"Limburg",
    "wof:name":"Herremans Jean-marie",
    "wof:placetype":"venue"
},
  "geometry": {"coordinates":[5.3161969185,51.0236358643],"type":"Point"}
}