{
  "type": "Feature",
  "properties": {
    "iso:country":"BE",
    "sg:address":"Driehoekstraat 77",
    "sg:city":"Zandhoven",
    "sg:classifiers":[
        {
            "category":"Banks & Credit Unions",
            "subcategory":"Investment Brokerage",
            "type":"Services"
        }
    ],
    "sg:phone":"+32 3 484 60 72",
    "sg:postcode":"2240",
    "sg:province":"Antwerpen",
    "sg:tags":[
        "fence"
    ],
    "wof:name":"Luc D'hulst",
    "wof:placetype":"venue"
},
  "geometry": {"coordinates":[4.6720991135,51.2185783386],"type":"Point"}
}