{
  "type": "Feature",
  "properties": {
    "iso:country":"BE",
    "sg:address":"Rue Du Huit Mai",
    "sg:city":"Gembloux-sur-orneau (gembloux)",
    "sg:classifiers":[
        {
            "category":"Social Services",
            "type":"Services"
        }
    ],
    "sg:phone":"+32 81 62 63 30",
    "sg:postcode":"5030",
    "sg:province":"Namur",
    "wof:name":"Office Gembloutois Du Tourisme",
    "wof:placetype":"venue"
},
  "geometry": {"coordinates":[4.6948618889,50.5600013733],"type":"Point"}
}