{
  "type": "Feature",
  "properties": {
    "iso:country":"BE",
    "sg:address":"Beverstraat 4",
    "sg:city":"Ninove",
    "sg:classifiers":[
        {
            "category":"Shopping",
            "subcategory":"Clothing, Apparel, & Fashions",
            "type":"Retail Goods"
        }
    ],
    "sg:phone":"+32 54 33 63 12",
    "sg:postcode":"9400",
    "sg:province":"Oost-Vlaanderen",
    "sg:tags":[
        "boutique"
    ],
    "wof:name":"Bronx",
    "wof:placetype":"venue"
},
  "geometry": {"coordinates":[4.022192955,50.8355445862],"type":"Point"}
}