{
  "type": "Feature",
  "properties": {
    "iso:country":"BE",
    "sg:address":"Rue Du G\u00e9n\u00e9ral De Gaulle 28",
    "sg:city":"Courcelles",
    "sg:classifiers":[
        {
            "category":"Shopping",
            "subcategory":"Computers & Home Electronics",
            "type":"Retail Goods"
        }
    ],
    "sg:phone":"+32 71 45 13 11",
    "sg:postcode":"6180",
    "sg:province":"Hainaut",
    "sg:tags":[
        "equipment",
        "-"
    ],
    "wof:name":"Tcho (au) Scrl",
    "wof:placetype":"venue"
},
  "geometry": {"coordinates":[4.3794560432,50.4597625732],"type":"Point"}
}