{
  "type": "Feature",
  "properties": {
    "addr:full":"Rue De Jupille 125b6 Vis\u00c9 Li\u00e8ge 4600",
    "addr:housenumber":"125b6",
    "addr:postcode":"4600",
    "addr:street":"Rue De Jupille",
    "iso:country":"BE",
    "sg:address":"Rue De Jupille 125b6",
    "sg:city":"Vis\u00c9",
    "sg:orig_category":"Boekhouders",
    "sg:phone":"+32 4 379 15 30",
    "sg:postcode":"4600",
    "sg:province":"Li\u00e8ge",
    "wof:name":"A. Charlier",
    "wof:placetype":"venue"
},
  "geometry": {"coordinates":[5.6931061745,50.7232208252],"type":"Point"}
}