{
  "type": "Feature",
  "properties": {
    "addr:full":"Rue Joseph Wauters 19 Amay Li\u00e8ge 4540",
    "addr:housenumber":"19",
    "addr:postcode":"4540",
    "addr:street":"Rue Joseph Wauters",
    "iso:country":"BE",
    "sg:address":"Rue Joseph Wauters 19",
    "sg:city":"Amay",
    "sg:orig_category":"Avocats and conseillers juridiques",
    "sg:phone":"+32 85 31 42 42",
    "sg:postcode":"4540",
    "sg:province":"Li\u00e8ge",
    "wof:name":"Christophe Collignon",
    "wof:placetype":"venue"
},
  "geometry": {"coordinates":[5.3198170662,50.5475616455],"type":"Point"}
}