{
  "type": "Feature",
  "properties": {
    "iso:country":"BE",
    "sg:address":"Brugse Baan 90",
    "sg:city":"Gistel",
    "sg:orig_category":"Rundveehouders Varkenskwekers",
    "sg:phone":"+32 59 27 76 08",
    "sg:postcode":"8470",
    "sg:province":"West-Vlaanderen",
    "wof:name":"Maurits Depoorter",
    "wof:placetype":"venue"
},
  "geometry": {"coordinates":[2.9826610088,51.1573944092],"type":"Point"}
}