{
  "type": "Feature",
  "properties": {
    "iso:country":"BE",
    "sg:address":"Aambeeldstraat 35",
    "sg:city":"Gent",
    "sg:classifiers":[
        {
            "category":"Banks & Credit Unions",
            "subcategory":"Investment Brokerage",
            "type":"Services"
        }
    ],
    "sg:phone":"+32 9 236 39 45",
    "sg:postcode":"9000",
    "sg:province":"Oost-Vlaanderen",
    "sg:tags":[
        "aid",
        "rehabiliation",
        "apparatus"
    ],
    "wof:name":"Skil Nv",
    "wof:placetype":"venue"
},
  "geometry": {"coordinates":[3.7021501064,51.0590705872],"type":"Point"}
}