{
  "type": "Feature",
  "properties": {
    "iso:country":"BE",
    "sg:address":"Jan Onkelinxlaan 27",
    "sg:city":"Landen",
    "sg:orig_category":"Rev\u00eatements pour sols and murs. Peinture",
    "sg:phone":"+32 11 83 27 49",
    "sg:postcode":"3400",
    "sg:province":"Vlaams-Brabant",
    "wof:name":"Elen-decor",
    "wof:placetype":"venue"
},
  "geometry": {"coordinates":[5.0898537636,50.7548294067],"type":"Point"}
}