{
  "type": "Feature",
  "properties": {
    "addr:full":"Avenue De Hinnisdael 29 Bruxelles (woluwe-saint-pierre) Bruxelles-Capitale 1150",
    "addr:housenumber":"29",
    "addr:postcode":"1150",
    "addr:street":"Avenue De Hinnisdael",
    "iso:country":"BE",
    "sg:address":"Avenue De Hinnisdael 29",
    "sg:city":"Bruxelles (woluwe-saint-pierre)",
    "sg:classifiers":[
        {
            "category":"Health Services",
            "subcategory":"Health Practitioner",
            "type":"Services"
        }
    ],
    "sg:phone":"+32 2 779 02 62",
    "sg:postcode":"1150",
    "sg:province":"Bruxelles-Capitale",
    "sg:tags":[
        "physiotherapist"
    ],
    "wof:name":"Louwers",
    "wof:placetype":"venue"
},
  "geometry": {"coordinates":[4.4652380943,50.8416023254],"type":"Point"}
}