{
  "type": "Feature",
  "properties": {
    "addr:full":"Leon Spilliaertstraat 71 Oostende West-Vlaanderen 8400",
    "addr:housenumber":"71",
    "addr:postcode":"8400",
    "addr:street":"Leon Spilliaertstraat",
    "iso:country":"BE",
    "sg:address":"Leon Spilliaertstraat 71",
    "sg:city":"Oostende",
    "sg:classifiers":[
        {
            "category":"Health Services",
            "subcategory":"Health Practitioner",
            "type":"Services"
        }
    ],
    "sg:phone":"+32 59 51 47 49",
    "sg:postcode":"8400",
    "sg:province":"West-Vlaanderen",
    "sg:tags":[
        "physiotherapist"
    ],
    "wof:name":"Verheyde Annelies",
    "wof:placetype":"venue"
},
  "geometry": {"coordinates":[2.9134809971,51.2266082764],"type":"Point"}
}