{
  "type": "Feature",
  "properties": {
    "addr:full":"Frans Schachtstraat 29 Asse (zellik) Vlaams-Brabant 1731",
    "addr:housenumber":"29",
    "addr:postcode":"1731",
    "addr:street":"Frans Schachtstraat",
    "iso:country":"BE",
    "sg:address":"Frans Schachtstraat 29",
    "sg:city":"Asse (zellik)",
    "sg:classifiers":[
        {
            "category":"Home & Garden",
            "subcategory":"Home Furnishings",
            "type":"Retail Goods"
        }
    ],
    "sg:phone":"+32 2 332 25 35",
    "sg:postcode":"1731",
    "sg:province":"Vlaams-Brabant",
    "sg:tags":[
        "interior",
        "decoration"
    ],
    "wof:name":"Kingtrade",
    "wof:placetype":"venue"
},
  "geometry": {"coordinates":[4.2772259712,50.8795623779],"type":"Point"}
}