{
  "type": "Feature",
  "properties": {
    "addr:full":"Sur Le Bois 4 Dalhem Li\u00e8ge 4607",
    "addr:housenumber":"4",
    "addr:postcode":"4607",
    "addr:street":"Le Bois",
    "iso:country":"BE",
    "sg:address":"Sur Le Bois 4",
    "sg:city":"Dalhem",
    "sg:classifiers":[
        {
            "category":"Real Estate",
            "subcategory":"Surveying",
            "type":"Services"
        }
    ],
    "sg:phone":"+32 4 379 45 55",
    "sg:postcode":"4607",
    "sg:province":"Li\u00e8ge",
    "sg:tags":[
        "surveyor",
        "land"
    ],
    "wof:name":"Walth\u00e9ry V",
    "wof:placetype":"venue"
},
  "geometry": {"coordinates":[5.7180938721,50.7173957825],"type":"Point"}
}