{
  "type": "Feature",
  "properties": {
    "addr:full":"Oostmoerstraat 8 Jabbeke West-Vlaanderen 8490",
    "addr:housenumber":"8",
    "addr:postcode":"8490",
    "addr:street":"Oostmoerstraat",
    "iso:country":"BE",
    "sg:address":"Oostmoerstraat 8",
    "sg:city":"Jabbeke",
    "sg:orig_category":"Enseignement maternel and primaire",
    "sg:phone":"+32 50 81 31 45",
    "sg:postcode":"8490",
    "sg:province":"West-Vlaanderen",
    "wof:name":"Vrije Basisschool",
    "wof:placetype":"venue"
},
  "geometry": {"coordinates":[3.123570919,51.1681747437],"type":"Point"}
}