{
  "type": "Feature",
  "properties": {
    "iso:country":"BE",
    "sg:address":"Dorpsplein 8",
    "sg:city":"Melle",
    "sg:orig_category":"Articles de f\u00eate, farces and attrapes",
    "sg:phone":"+32 9 252 54 11",
    "sg:postcode":"9090",
    "sg:province":"Oost-Vlaanderen",
    "wof:name":"Kathleen",
    "wof:placetype":"venue"
},
  "geometry": {"coordinates":[3.8029060364,51.0037269592],"type":"Point"}
}