{
  "type": "Feature",
  "properties": {
    "iso:country":"BE",
    "sg:address":"Egelspoelstraat 29",
    "sg:city":"Beerse",
    "sg:classifiers":[
        {
            "category":"Travel",
            "subcategory":"Travel Agent",
            "type":"Entertainment"
        }
    ],
    "sg:phone":"+32 14 61 73 05",
    "sg:postcode":"2340",
    "sg:province":"Antwerpen",
    "sg:tags":[
        "accessory",
        "mountaineering"
    ],
    "wof:name":"De Wandelstok Bvba",
    "wof:placetype":"venue"
},
  "geometry": {"coordinates":[4.8501801491,51.3130989075],"type":"Point"}
}