{
  "type": "Feature",
  "properties": {
    "addr:full":"Place Du Louet 6 Sambreville Namur 5060",
    "addr:housenumber":"6",
    "addr:postcode":"5060",
    "addr:street":"Place Du Louet",
    "iso:country":"BE",
    "sg:address":"Place Du Louet 6",
    "sg:city":"Sambreville",
    "sg:orig_category":"Assurances. Bureaux de poste",
    "sg:phone":"+32 71 77 25 90",
    "sg:postcode":"5060",
    "sg:province":"Namur",
    "wof:name":"La Poste",
    "wof:placetype":"venue"
},
  "geometry": {"coordinates":[4.6285200119,50.4448738098],"type":"Point"}
}