{
  "type": "Feature",
  "properties": {
    "addr:full":"Oude Koornmarkt 15 Antwerpen Antwerpen 2000",
    "addr:housenumber":"15",
    "addr:postcode":"2000",
    "addr:street":"Oude Koornmarkt",
    "iso:country":"BE",
    "sg:address":"Oude Koornmarkt 15",
    "sg:city":"Antwerpen",
    "sg:classifiers":[
        {
            "category":"Restaurant",
            "type":"Food & Drink"
        }
    ],
    "sg:phone":"+32 3 232 34 78",
    "sg:postcode":"2000",
    "sg:province":"Antwerpen",
    "wof:name":"'t Spreeuwke",
    "wof:placetype":"venue"
},
  "geometry": {"coordinates":[4.3999061584,51.2203826904],"type":"Point"}
}