{
  "type": "Feature",
  "properties": {
    "iso:country":"BE",
    "sg:address":"Rue D'houdeng 220",
    "sg:city":"Le Roeulx",
    "sg:classifiers":[
        {
            "category":"Brewery",
            "type":"Food & Drink"
        }
    ],
    "sg:phone":"+32 64 66 21 51",
    "sg:postcode":"7070",
    "sg:province":"Hainaut",
    "wof:name":"Brasserie Saint Feuillien Sa",
    "wof:placetype":"venue"
},
  "geometry": {"coordinates":[4.126347065,50.4976806641],"type":"Point"}
}