{
  "type": "Feature",
  "properties": {
    "iso:country":"BE",
    "sg:address":"Korte Zilverstraat 3a",
    "sg:city":"Brugge",
    "sg:classifiers":[
        {
            "category":"Travel",
            "subcategory":"Hotels & Motels",
            "type":"Entertainment"
        }
    ],
    "sg:phone":"+32 50 34 44 11",
    "sg:postcode":"8000",
    "sg:province":"West-Vlaanderen",
    "sg:tags":[
        "hotels",
        "business",
        "restaurant"
    ],
    "wof:name":"Parisal Nv",
    "wof:placetype":"venue"
},
  "geometry": {"coordinates":[3.2220640182,51.208240509],"type":"Point"}
}