{
  "type": "Feature",
  "properties": {
    "iso:country":"BE",
    "sg:address":"Chauss\u00e9e D'enghien 294",
    "sg:city":"Tubize (saintes)",
    "sg:classifiers":[
        {
            "category":"Autos & Motor Vehicles",
            "subcategory":"Fuel & Gas Station",
            "type":"Retail Goods"
        }
    ],
    "sg:phone":"+32 2 355 58 07",
    "sg:postcode":"1480",
    "sg:province":"Brabant Wallon",
    "wof:name":"Octa Station",
    "wof:placetype":"venue"
},
  "geometry": {"coordinates":[4.1567549706,50.7054595947],"type":"Point"}
}