{
  "type": "Feature",
  "properties": {
    "addr:full":"Statielei 85 Mortsel Antwerpen 2640",
    "addr:housenumber":"85",
    "addr:postcode":"2640",
    "addr:street":"Statielei",
    "iso:country":"BE",
    "sg:address":"Statielei 85",
    "sg:city":"Mortsel",
    "sg:orig_category":"Microsoft. Journaux. Librairies",
    "sg:phone":"+32 3 449 46 88",
    "sg:postcode":"2640",
    "sg:province":"Antwerpen",
    "wof:name":"Standaard Boekhandel Mortsel",
    "wof:placetype":"venue"
},
  "geometry": {"coordinates":[4.4531269073,51.1706008911],"type":"Point"}
}