{
  "type": "Feature",
  "properties": {
    "addr:full":"Bergstraat 34 Merelbeke Oost-Vlaanderen 9820",
    "addr:housenumber":"34",
    "addr:postcode":"9820",
    "addr:street":"Bergstraat",
    "iso:country":"BE",
    "sg:address":"Bergstraat 34",
    "sg:city":"Merelbeke",
    "sg:orig_category":"Enseignement maternel and primaire",
    "sg:phone":"+32 9 230 71 88",
    "sg:postcode":"9820",
    "sg:province":"Oost-Vlaanderen",
    "wof:name":"Vrije Basisschool",
    "wof:placetype":"venue"
},
  "geometry": {"coordinates":[3.7596759796,51.0111846924],"type":"Point"}
}