{
  "type": "Feature",
  "properties": {
    "iso:country":"BE",
    "sg:address":"Chemin Royal 13",
    "sg:city":"Bernissart (blaton)",
    "sg:classifiers":[
        {
            "category":"Professional",
            "subcategory":"Accounting & Tax Preparation",
            "type":"Services"
        }
    ],
    "sg:phone":"+32 69 58 01 81",
    "sg:postcode":"7321",
    "sg:province":"Hainaut",
    "sg:tags":[
        "bookkeeper"
    ],
    "wof:name":"Francois I",
    "wof:placetype":"venue"
},
  "geometry": {"coordinates":[3.6769380569,50.4907455444],"type":"Point"}
}