{
  "type": "Feature",
  "properties": {
    "iso:country":"BE",
    "sg:address":"Borkelstraat 143",
    "sg:city":"Schoten",
    "sg:orig_category":"Landmeters and schatters",
    "sg:phone":"+32 3 658 65 54",
    "sg:postcode":"2900",
    "sg:province":"Antwerpen",
    "wof:name":"Expertise De Bock",
    "wof:placetype":"venue"
},
  "geometry": {"coordinates":[4.4872407913,51.2544555664],"type":"Point"}
}