{
  "type": "Feature",
  "properties": {
    "addr:full":"Rue Emile Bouilliot 31 Bruxelles (ixelles) Bruxelles-Capitale 1050",
    "addr:housenumber":"31",
    "addr:postcode":"1050",
    "addr:street":"Rue Emile Bouilliot",
    "iso:country":"BE",
    "sg:address":"Rue Emile Bouilliot 31",
    "sg:city":"Bruxelles (ixelles)",
    "sg:classifiers":[
        {
            "category":"Building & Trades",
            "subcategory":"Pest Control",
            "type":"Services"
        }
    ],
    "sg:phone":"+32 2 345 78 76",
    "sg:postcode":"1050",
    "sg:province":"Bruxelles-Capitale",
    "sg:tags":[
        "painting",
        "contractor"
    ],
    "wof:name":"Id3d Scrl",
    "wof:placetype":"venue"
},
  "geometry": {"coordinates":[4.354074955,50.8184547424],"type":"Point"}
}