{
  "type": "Feature",
  "properties": {
    "addr:full":"Vrouwkensblok 20 Rijkevorsel Antwerpen 2310",
    "addr:housenumber":"20",
    "addr:postcode":"2310",
    "addr:street":"Vrouwkensblok",
    "iso:country":"BE",
    "sg:address":"Vrouwkensblok 20",
    "sg:city":"Rijkevorsel",
    "sg:classifiers":[
        {
            "category":"Wholesale",
            "subcategory":"Scrap",
            "type":"Manufacturing & Wholesale Goods"
        }
    ],
    "sg:phone":"+32 3 311 59 89",
    "sg:postcode":"2310",
    "sg:province":"Antwerpen",
    "sg:tags":[
        "metal"
    ],
    "wof:name":"Colimetals Bvba",
    "wof:placetype":"venue"
},
  "geometry": {"coordinates":[4.725962162,51.3354110718],"type":"Point"}
}