{
  "type": "Feature",
  "properties": {
    "addr:full":"Rue Du Centre 107 Verviers Li\u00e8ge 4800",
    "addr:housenumber":"107",
    "addr:postcode":"4800",
    "addr:street":"Rue Du Centre",
    "iso:country":"BE",
    "sg:address":"Rue Du Centre 107",
    "sg:city":"Verviers",
    "sg:orig_category":"Experts-comptables",
    "sg:phone":"+32 87 23 00 57",
    "sg:postcode":"4800",
    "sg:province":"Li\u00e8ge",
    "wof:name":"Georges Christophe",
    "wof:placetype":"venue"
},
  "geometry": {"coordinates":[5.8612680435,50.5889282227],"type":"Point"}
}