{
  "type": "Feature",
  "properties": {
    "addr:full":"Peulisstraat 43 Putte Antwerpen 2580",
    "addr:housenumber":"43",
    "addr:postcode":"2580",
    "addr:street":"Peulisstraat",
    "iso:country":"BE",
    "sg:address":"Peulisstraat 43",
    "sg:city":"Putte",
    "sg:orig_category":"Schoenen",
    "sg:phone":"+32 15 75 64 80",
    "sg:postcode":"2580",
    "sg:province":"Antwerpen",
    "wof:name":"Shoe Discount",
    "wof:placetype":"venue"
},
  "geometry": {"coordinates":[4.5883040428,51.0384140015],"type":"Point"}
}