{
  "type": "Feature",
  "properties": {
    "iso:country":"BE",
    "sg:address":"Weertersteenweg 4",
    "sg:city":"Kinrooi",
    "sg:orig_category":"Epiceries",
    "sg:phone":"+32 89 56 59 40",
    "sg:postcode":"3640",
    "sg:province":"Limburg",
    "wof:name":"Leon Deuss",
    "wof:placetype":"venue"
},
  "geometry": {"coordinates":[5.7556800842,51.1363182068],"type":"Point"}
}