{
  "type": "Feature",
  "properties": {
    "addr:full":"Quatri\u00c8me Avenue 46 Herstal Li\u00e8ge 4040",
    "addr:housenumber":"46",
    "addr:postcode":"4040",
    "addr:street":"Quatrie\u0300Me Avenue",
    "iso:country":"BE",
    "sg:address":"Quatri\u00c8me Avenue 46",
    "sg:city":"Herstal",
    "sg:orig_category":"Bouwmaterialen Gh Installatie van metalen schrijnwerk",
    "sg:phone":"+32 4 240 67 11",
    "sg:postcode":"4040",
    "sg:province":"Li\u00e8ge",
    "wof:name":"Metal Profil Belgium",
    "wof:placetype":"venue"
},
  "geometry": {"coordinates":[5.6207761765,50.6997451782],"type":"Point"}
}