{
  "type": "Feature",
  "properties": {
    "addr:full":"Rue Edouard Dinot 21 Ciney Namur 5590",
    "addr:housenumber":"21",
    "addr:postcode":"5590",
    "addr:street":"Rue Edouard Dinot",
    "iso:country":"BE",
    "sg:address":"Rue Edouard Dinot 21",
    "sg:city":"Ciney",
    "sg:orig_category":"Agences de voyages",
    "sg:phone":"+32 83 21 24 51",
    "sg:postcode":"5590",
    "sg:province":"Namur",
    "wof:name":"Sens Inverse",
    "wof:placetype":"venue"
},
  "geometry": {"coordinates":[5.1006159782,50.2935562134],"type":"Point"}
}