{
  "type": "Feature",
  "properties": {
    "iso:country":"BE",
    "sg:address":"Veerstraat 2",
    "sg:city":"Wellen",
    "sg:orig_category":"Rundveehouders",
    "sg:phone":"+32 12 74 24 53",
    "sg:postcode":"3830",
    "sg:province":"Limburg",
    "wof:name":"August Neven",
    "wof:placetype":"venue"
},
  "geometry": {"coordinates":[5.3233861923,50.8441886902],"type":"Point"}
}