{
  "type": "Feature",
  "properties": {
    "addr:full":"Alfons Van Den Broeckstraat 17 Gent (oostakker) Oost-Vlaanderen 9041",
    "addr:housenumber":"17",
    "addr:postcode":"9041",
    "addr:street":"Alfons Van Den Broeckstraat",
    "iso:country":"BE",
    "sg:address":"Alfons Van Den Broeckstraat 17",
    "sg:city":"Gent (oostakker)",
    "sg:classifiers":[
        {
            "category":"Social Services",
            "subcategory":"Job Training",
            "type":"Services"
        }
    ],
    "sg:phone":"+32 9 228 68 99",
    "sg:postcode":"9041",
    "sg:province":"Oost-Vlaanderen",
    "sg:tags":[
        "interpreter"
    ],
    "wof:name":"Van Overstraeten E",
    "wof:placetype":"venue"
},
  "geometry": {"coordinates":[3.7741189003,51.0827713013],"type":"Point"}
}