{
  "type": "Feature",
  "properties": {
    "iso:country":"BE",
    "sg:address":"Rue Des Fermes 35",
    "sg:city":"Andenne (nam\u00eache)",
    "sg:classifiers":[
        {
            "category":"Utilities",
            "subcategory":"Telephone",
            "type":"Services"
        }
    ],
    "sg:phone":"+32 81 58 28 01",
    "sg:postcode":"5300",
    "sg:province":"Namur",
    "sg:tags":[
        "-",
        "internet"
    ],
    "wof:name":"Emaze Infosystems",
    "wof:placetype":"venue"
},
  "geometry": {"coordinates":[4.9942688942,50.4724655151],"type":"Point"}
}