{
  "type": "Feature",
  "properties": {
    "iso:country":"BE",
    "sg:address":"Regn\u00c9 24",
    "sg:city":"Vielsalm",
    "sg:classifiers":[
        {
            "category":"Wholesale",
            "subcategory":"Farm Supplies",
            "type":"Manufacturing & Wholesale Goods"
        }
    ],
    "sg:phone":"+32 80 41 87 19",
    "sg:postcode":"6690",
    "sg:province":"Luxembourg",
    "sg:tags":[
        "machine",
        "agricoles",
        "mat\u00e9riel",
        "gr"
    ],
    "wof:name":"Raymond Wiesen",
    "wof:placetype":"venue"
},
  "geometry": {"coordinates":[5.7855319977,50.2552642822],"type":"Point"}
}