{
  "type": "Feature",
  "properties": {
    "iso:country":"BE",
    "sg:address":"Casselrylaan 28",
    "sg:city":"Deinze (astene)",
    "sg:classifiers":[
        {
            "category":"Communications",
            "subcategory":"Film & Video Production",
            "type":"Services"
        }
    ],
    "sg:phone":"+32 9 281 21 08",
    "sg:postcode":"9800",
    "sg:province":"Oost-Vlaanderen",
    "sg:tags":[
        "realisation",
        "-"
    ],
    "wof:name":"Beeldtaal Bvba",
    "wof:placetype":"venue"
},
  "geometry": {"coordinates":[3.530174017,50.9863166809],"type":"Point"}
}