{
  "type": "Feature",
  "properties": {
    "addr:full":"Europarklaan 2048 Houthalen-helchteren (houthalen) Limburg 3530",
    "addr:postcode":"2048;3530",
    "addr:street":"Europarklaan",
    "iso:country":"BE",
    "sg:address":"Europarklaan 2048",
    "sg:city":"Houthalen-helchteren (houthalen)",
    "sg:classifiers":[
        {
            "category":"Retail",
            "subcategory":"Car Wash",
            "type":"Services"
        }
    ],
    "sg:phone":"+32 11 52 62 44",
    "sg:postcode":"3530",
    "sg:province":"Limburg",
    "sg:tags":[
        "automobile",
        "washing",
        "-",
        "truck"
    ],
    "wof:name":"Ed's Carwash",
    "wof:placetype":"venue"
},
  "geometry": {"coordinates":[5.3915300369,51.03565979],"type":"Point"}
}