{
  "type": "Feature",
  "properties": {
    "addr:full":"Rue Lebeau 5 Bruxelles Bruxelles-Capitale 1000",
    "addr:housenumber":"5",
    "addr:postcode":"1000",
    "addr:street":"Rue Lebeau",
    "iso:country":"BE",
    "sg:address":"Rue Lebeau 5",
    "sg:city":"Bruxelles",
    "sg:classifiers":[
        {
            "category":"Cafe",
            "type":"Food & Drink"
        }
    ],
    "sg:phone":"+32 2 503 27 79",
    "sg:postcode":"1000",
    "sg:province":"Bruxelles-Capitale",
    "sg:tags":[
        "snack-bars"
    ],
    "wof:name":"Dejeuners De Soleil (des)",
    "wof:placetype":"venue"
},
  "geometry": {"coordinates":[4.3544387817,50.8429603577],"type":"Point"}
}