{
  "type": "Feature",
  "properties": {
    "addr:full":"Route De Wallonie 4 Ghlin Hainaut 7011",
    "addr:housenumber":"4",
    "addr:postcode":"7011",
    "addr:street":"Route De Wallonie",
    "iso:country":"BE",
    "sg:address":"Route De Wallonie 4",
    "sg:city":"Ghlin",
    "sg:classifiers":[
        {
            "category":"Manufacturing",
            "subcategory":"Motor Vehicles & Parts",
            "type":"Manufacturing & Wholesale Goods"
        }
    ],
    "sg:phone":"+32 65 84 37 64",
    "sg:postcode":"7011",
    "sg:province":"Hainaut",
    "sg:tags":[
        "pallet",
        "recycling"
    ],
    "wof:name":"Pal-ahlec Sprl",
    "wof:placetype":"venue"
},
  "geometry": {"coordinates":[3.9049780369,50.4808235168],"type":"Point"}
}