{
  "type": "Feature",
  "properties": {
    "addr:full":"Brugsesteenweg 58 Middelkerke (mannekensvere) West-Vlaanderen 8433",
    "addr:housenumber":"58",
    "addr:postcode":"8433",
    "addr:street":"Brugsesteenweg",
    "iso:country":"BE",
    "sg:address":"Brugsesteenweg 58",
    "sg:city":"Middelkerke (mannekensvere)",
    "sg:classifiers":[
        {
            "category":"Building & Trades",
            "subcategory":"Equipment Rental",
            "type":"Services"
        }
    ],
    "sg:phone":"+32 58 24 00 27",
    "sg:postcode":"8433",
    "sg:province":"West-Vlaanderen",
    "sg:tags":[
        "crane",
        "-"
    ],
    "wof:name":"Depicker Kraanverhuur Nv",
    "wof:placetype":"venue"
},
  "geometry": {"coordinates":[2.8475210667,51.1547775269],"type":"Point"}
}