{
  "type": "Feature",
  "properties": {
    "iso:country":"BE",
    "sg:address":"Rue Du Bergeant 8",
    "sg:city":"Leuze-en-hainaut",
    "sg:classifiers":[
        {
            "category":"Insurance",
            "subcategory":"Life Insurance",
            "type":"Services"
        }
    ],
    "sg:phone":"+32 69 66 32 23",
    "sg:postcode":"7900",
    "sg:province":"Hainaut",
    "sg:tags":[
        "assurance"
    ],
    "wof:name":"Degauquier-l\u00c9onard",
    "wof:placetype":"venue"
},
  "geometry": {"coordinates":[3.6149840355,50.5959014893],"type":"Point"}
}