{
  "type": "Feature",
  "properties": {
    "addr:full":"Bevrijdingslaan 8 Meerhout Antwerpen 2450",
    "addr:housenumber":"8",
    "addr:postcode":"2450",
    "addr:street":"Bevrijdingslaan",
    "iso:country":"BE",
    "sg:address":"Bevrijdingslaan 8",
    "sg:city":"Meerhout",
    "sg:classifiers":[
        {
            "category":"Insurance",
            "subcategory":"Insurance Agent",
            "type":"Services"
        }
    ],
    "sg:phone":"+32 14 30 01 30",
    "sg:postcode":"2450",
    "sg:province":"Antwerpen",
    "sg:tags":[
        "verzekeringsmakelaars",
        "expert"
    ],
    "wof:name":"Bureau Rutten",
    "wof:placetype":"venue"
},
  "geometry": {"coordinates":[5.0743179321,51.1298217773],"type":"Point"}
}