{
  "type": "Feature",
  "properties": {
    "iso:country":"BE",
    "sg:address":"Handzamestraat 84",
    "sg:city":"Kortemark",
    "sg:orig_category":"Groenten and fruit Gh Groententeelt",
    "sg:phone":"+32 51 56 91 01",
    "sg:postcode":"8610",
    "sg:province":"West-Vlaanderen",
    "wof:name":"Segakor",
    "wof:placetype":"venue"
},
  "geometry": {"coordinates":[3.0285949707,51.0293579102],"type":"Point"}
}