{
  "type": "Feature",
  "properties": {
    "iso:country":"BE",
    "sg:address":"Av.de Sel. De Moranville 65",
    "sg:city":"Sint-agatha-berchem/berchem-sainte-agathe",
    "sg:orig_category":"M\u00e9decins and sp\u00e9cialistes",
    "sg:phone":"+32 2 465 56 17",
    "sg:postcode":"1082",
    "sg:province":"Bruxelles-Capitale",
    "wof:name":"B\u00c9atrice Nokerman",
    "wof:placetype":"venue"
},
  "geometry": {"coordinates":[4.2905712128,50.866569519],"type":"Point"}
}