{
  "type": "Feature",
  "properties": {
    "iso:country":"BE",
    "sg:address":"Bruggestraat 96",
    "sg:city":"Wingene",
    "sg:orig_category":"Location de v\u00e9hicules sauf voitures",
    "sg:phone":"+32 51 61 10 14",
    "sg:postcode":"8750",
    "sg:province":"West-Vlaanderen",
    "wof:name":"Pozzolo",
    "wof:placetype":"venue"
},
  "geometry": {"coordinates":[3.2688450813,51.0568885803],"type":"Point"}
}