{
  "type": "Feature",
  "properties": {
    "iso:country":"BE",
    "sg:address":"Zuidmoerstraat 49",
    "sg:city":"Eeklo",
    "sg:orig_category":"Parfumeries",
    "sg:phone":"+32 9 377 84 06",
    "sg:postcode":"9900",
    "sg:province":"Oost-Vlaanderen",
    "wof:name":"Saskia De Schryver",
    "wof:placetype":"venue"
},
  "geometry": {"coordinates":[3.571721077,51.1800422668],"type":"Point"}
}