{
  "type": "Feature",
  "properties": {
    "iso:country":"BE",
    "sg:address":"Rue De Cr\u00c9py 35",
    "sg:city":"Antoing",
    "sg:orig_category":"Entretien and r\u00e9parations de voitures",
    "sg:phone":"+32 69 44 11 50",
    "sg:postcode":"7640",
    "sg:province":"Hainaut",
    "wof:name":"Benoit Quievy",
    "wof:placetype":"venue"
},
  "geometry": {"coordinates":[3.4573099613,50.5640602112],"type":"Point"}
}