{
  "type": "Feature",
  "properties": {
    "iso:country":"BE",
    "sg:address":"Dorpsstraat 30",
    "sg:city":"Hasselt",
    "sg:classifiers":[
        {
            "category":"Food & Beverages",
            "subcategory":"Meat & Fish",
            "type":"Retail Goods"
        }
    ],
    "sg:phone":"+32 11 22 17 27",
    "sg:postcode":"3500",
    "sg:province":"Limburg",
    "sg:tags":[
        "poultry",
        "whol",
        "game",
        "-"
    ],
    "wof:name":"Theunissen",
    "wof:placetype":"venue"
},
  "geometry": {"coordinates":[5.3353037834,50.9325256348],"type":"Point"}
}