{
  "type": "Feature",
  "properties": {
    "iso:country":"BE",
    "sg:address":"Rue Joseph Wauters 4",
    "sg:city":"Anderlues",
    "sg:classifiers":[
        {
            "category":"Personal",
            "type":"Services"
        }
    ],
    "sg:phone":"+32 71 52 33 62",
    "sg:postcode":"6150",
    "sg:province":"Hainaut",
    "sg:tags":[
        "clothing",
        "men's",
        "tailor",
        "-"
    ],
    "wof:name":"Bailly J",
    "wof:placetype":"venue"
},
  "geometry": {"coordinates":[4.2700300217,50.4085388184],"type":"Point"}
}