{
  "type": "Feature",
  "properties": {
    "iso:country":"BE",
    "sg:address":"Smisstraat 4",
    "sg:city":"Riemst",
    "sg:orig_category":"Brood, gebak and snoepgoed",
    "sg:phone":"+32 12 45 15 67",
    "sg:postcode":"3770",
    "sg:province":"Limburg",
    "wof:name":"Stefan Bollen",
    "wof:placetype":"venue"
},
  "geometry": {"coordinates":[5.5909562111,50.8343658447],"type":"Point"}
}