{
  "type": "Feature",
  "properties": {
    "addr:full":"P.f. De Naeyerstraat 55 Lebbeke Oost-Vlaanderen 9280",
    "addr:housenumber":"55",
    "addr:postcode":"9280",
    "addr:street":"P.F. De Naeyerstraat",
    "iso:country":"BE",
    "sg:address":"P.f. De Naeyerstraat 55",
    "sg:city":"Lebbeke",
    "sg:orig_category":"Informaticaconsulenten Software ontwikkeling and ontwerp",
    "sg:phone":"+32 52 41 54 71",
    "sg:postcode":"9280",
    "sg:province":"Oost-Vlaanderen",
    "wof:name":"Serge Delporte",
    "wof:placetype":"venue"
},
  "geometry": {"coordinates":[4.1516160965,50.9966239929],"type":"Point"}
}