{
  "type": "Feature",
  "properties": {
    "addr:full":"Pierre Sorellaan 8 Koksijde West-Vlaanderen 8670",
    "addr:housenumber":"8",
    "addr:postcode":"8670",
    "addr:street":"Sorellaan",
    "iso:country":"BE",
    "sg:address":"Pierre Sorellaan 8",
    "sg:city":"Koksijde",
    "sg:orig_category":"H\u00f4tels. Restaurants",
    "sg:phone":"+32 58 52 04 51",
    "sg:postcode":"8670",
    "sg:province":"West-Vlaanderen",
    "wof:name":"The Prince Charles",
    "wof:placetype":"venue"
},
  "geometry": {"coordinates":[2.6370930672,51.1188964844],"type":"Point"}
}