{
  "type": "Feature",
  "properties": {
    "iso:country":"BE",
    "sg:address":"Avenue Jean Gouders 17a",
    "sg:city":"Jalhay",
    "sg:orig_category":"Fournitures de bureau. Tabac. Librairies. Journaux",
    "sg:phone":"+32 87 47 42 28",
    "sg:postcode":"4845",
    "sg:province":"Li\u00e8ge",
    "wof:name":"Pierre Boutet",
    "wof:placetype":"venue"
},
  "geometry": {"coordinates":[5.9332880974,50.5146217346],"type":"Point"}
}