{
  "type": "Feature",
  "properties": {
    "iso:country":"BE",
    "sg:address":"Leikensweg 1",
    "sg:city":"Eeklo",
    "sg:classifiers":[
        {
            "category":"Food & Beverages",
            "subcategory":"Meat & Fish",
            "type":"Retail Goods"
        }
    ],
    "sg:phone":"+32 9 377 01 88",
    "sg:postcode":"9900",
    "sg:province":"Oost-Vlaanderen",
    "sg:tags":[
        "-",
        "livestock"
    ],
    "wof:name":"Voeders De Craene",
    "wof:placetype":"venue"
},
  "geometry": {"coordinates":[3.5685229301,51.1757659912],"type":"Point"}
}