{
  "type": "Feature",
  "properties": {
    "iso:country":"BE",
    "sg:address":"Rue De Li\u00c8ge 209",
    "sg:city":"Kelmis/la Calamine",
    "sg:orig_category":"Antiquit\u00e9s",
    "sg:phone":"+32 87 65 82 78",
    "sg:postcode":"4721",
    "sg:province":"Li\u00e8ge",
    "wof:name":"Nathalie Schrymecker",
    "wof:placetype":"venue"
},
  "geometry": {"coordinates":[6.0136919022,50.7140808105],"type":"Point"}
}