{
  "type": "Feature",
  "properties": {
    "iso:country":"BE",
    "sg:address":"Rue Joseph Heusdens 77",
    "sg:city":"Grace-hollogne",
    "sg:orig_category":"Fleurs and plantes",
    "sg:phone":"+32 4 263 20 38",
    "sg:postcode":"4460",
    "sg:province":"Li\u00e8ge",
    "wof:name":"Amaryllis",
    "wof:placetype":"venue"
},
  "geometry": {"coordinates":[5.5058751106,50.642036438],"type":"Point"}
}