{
  "type": "Feature",
  "properties": {
    "addr:full":"Pr. Pattynstraat 13z Izegem West-Vlaanderen 8870",
    "addr:housenumber":"13z",
    "addr:postcode":"8870",
    "addr:street":"Pattynstraat",
    "iso:country":"BE",
    "sg:address":"Pr. Pattynstraat 13z",
    "sg:city":"Izegem",
    "sg:orig_category":"Sportcentra",
    "sg:phone":"+32 51 31 51 00",
    "sg:postcode":"8870",
    "sg:province":"West-Vlaanderen",
    "wof:name":"V.k. Kachtem",
    "wof:placetype":"venue"
},
  "geometry": {"coordinates":[3.2146790028,50.9205284119],"type":"Point"}
}