{
  "type": "Feature",
  "properties": {
    "addr:full":"Vergeldermolenstraat 25 Staden (oostnieuwkerke) West-Vlaanderen 8840",
    "addr:housenumber":"25",
    "addr:postcode":"8840",
    "addr:street":"Vergeldermolenstraat",
    "iso:country":"BE",
    "sg:address":"Vergeldermolenstraat 25",
    "sg:city":"Staden (oostnieuwkerke)",
    "sg:classifiers":[
        {
            "category":"Manufacturing",
            "subcategory":"Food",
            "type":"Manufacturing & Wholesale Goods"
        }
    ],
    "sg:phone":"+32 51 24 77 99",
    "sg:postcode":"8840",
    "sg:province":"West-Vlaanderen",
    "sg:tags":[
        "equipment"
    ],
    "wof:name":"'inno'x Bvba",
    "wof:placetype":"venue"
},
  "geometry": {"coordinates":[3.0731430054,50.9580764771],"type":"Point"}
}