{
  "type": "Feature",
  "properties": {
    "addr:full":"Rue De L'obus 154 Bruxelles (anderlecht) Bruxelles-Capitale 1070",
    "addr:housenumber":"154",
    "addr:postcode":"1070",
    "addr:street":"Rue De L'Obus",
    "iso:country":"BE",
    "sg:address":"Rue De L'obus 154",
    "sg:city":"Bruxelles (anderlecht)",
    "sg:classifiers":[
        {
            "category":"Social Services",
            "subcategory":"Child Care",
            "type":"Services"
        }
    ],
    "sg:phone":"+32 2 523 27 92",
    "sg:postcode":"1070",
    "sg:province":"Bruxelles-Capitale",
    "sg:tags":[
        "baby",
        "nursery",
        "day",
        "sitting"
    ],
    "wof:name":"Baby-home",
    "wof:placetype":"venue"
},
  "geometry": {"coordinates":[4.3063998222,50.8423843384],"type":"Point"}
}