{
  "type": "Feature",
  "properties": {
    "iso:country":"BE",
    "sg:address":"Rue Sohet 15",
    "sg:city":"Li\u00c8ge",
    "sg:orig_category":"Antiek",
    "sg:phone":"+32 4 254 05 67",
    "sg:postcode":"4000",
    "sg:province":"Li\u00e8ge",
    "wof:name":"Jean-fran\u00c7ois Langohr",
    "wof:placetype":"venue"
},
  "geometry": {"coordinates":[5.5678219795,50.6274871826],"type":"Point"}
}