{
  "type": "Feature",
  "properties": {
    "addr:full":"Kruitenbergstraat 16 Brugge West-Vlaanderen 8000",
    "addr:housenumber":"16",
    "addr:postcode":"8000",
    "addr:street":"Kruitenbergstraat",
    "iso:country":"BE",
    "sg:address":"Kruitenbergstraat 16",
    "sg:city":"Brugge",
    "sg:orig_category":"Artiesten and kunstenaars",
    "sg:phone":"+32 50 33 58 79",
    "sg:postcode":"8000",
    "sg:province":"West-Vlaanderen",
    "wof:name":"Van Walleghem",
    "wof:placetype":"venue"
},
  "geometry": {"coordinates":[3.2315940857,51.2077522278],"type":"Point"}
}