{
  "type": "Feature",
  "properties": {
    "iso:country":"BE",
    "sg:address":"Dorpsplein 11b6",
    "sg:city":"Wellen",
    "sg:orig_category":"S\u00e9lection de personnel and placement",
    "sg:phone":"+32 12 74 68 76",
    "sg:postcode":"3830",
    "sg:province":"Limburg",
    "wof:name":"Pwa Wellen",
    "wof:placetype":"venue"
},
  "geometry": {"coordinates":[5.3376188278,50.8407440186],"type":"Point"}
}