{
  "type": "Feature",
  "properties": {
    "addr:full":"Ijzerlaan 1 Scherpenheuvel-zichem Vlaams-Brabant 3270",
    "addr:housenumber":"1",
    "addr:postcode":"3270",
    "addr:street":"Ijzerlaan",
    "iso:country":"BE",
    "sg:address":"Ijzerlaan 1",
    "sg:city":"Scherpenheuvel-zichem",
    "sg:orig_category":"Elektrische installaties voor woningen Huishoudapparaten, televisies and radio's Industri\u00eble elektri",
    "sg:phone":"+32 13 77 31 44",
    "sg:postcode":"3270",
    "sg:province":"Vlaams-Brabant",
    "wof:name":"Famee",
    "wof:placetype":"venue"
},
  "geometry": {"coordinates":[4.947991848,50.977481842],"type":"Point"}
}