{
  "type": "Feature",
  "properties": {
    "addr:full":"Molenstraat 22 Scherpenheuvel-zichem Vlaams-Brabant 3270",
    "addr:housenumber":"22",
    "addr:postcode":"3270",
    "addr:street":"Molenstraat",
    "iso:country":"BE",
    "sg:address":"Molenstraat 22",
    "sg:city":"Scherpenheuvel-zichem",
    "sg:classifiers":[
        {
            "category":"Insurance",
            "subcategory":"Life Insurance",
            "type":"Services"
        }
    ],
    "sg:phone":"+32 13 73 12 80",
    "sg:postcode":"3270",
    "sg:province":"Vlaams-Brabant",
    "sg:tags":[
        "assurance"
    ],
    "wof:name":"Bureau De Clerck Koen",
    "wof:placetype":"venue"
},
  "geometry": {"coordinates":[4.9750552177,50.9805793762],"type":"Point"}
}