{
  "type": "Feature",
  "properties": {
    "iso:country":"BE",
    "sg:address":"Rue Des Tilleuls 5",
    "sg:city":"Harz\u00e9",
    "sg:classifiers":[
        {
            "category":"Sports & Exercise",
            "subcategory":"Climbing Gym",
            "type":"Entertainment"
        }
    ],
    "sg:phone":"+32 86 43 32 98",
    "sg:postcode":"4920",
    "sg:province":"Li\u00e8ge",
    "sg:tags":[
        "fastening",
        "mounting",
        "element"
    ],
    "wof:name":"Yvens-decroupet Anc. Ets S.a.",
    "wof:placetype":"venue"
},
  "geometry": {"coordinates":[5.6799812317,50.4243278503],"type":"Point"}
}