{
  "type": "Feature",
  "properties": {
    "addr:full":"Rue Neuvice 2 Li\u00c8ge Li\u00e8ge 4000",
    "addr:housenumber":"2",
    "addr:postcode":"4000",
    "addr:street":"Rue Neuvice",
    "iso:country":"BE",
    "sg:address":"Rue Neuvice 2",
    "sg:city":"Li\u00c8ge",
    "sg:orig_category":"Pain, p\u00e2tisseries and confiseries",
    "sg:phone":"+32 4 221 19 14",
    "sg:postcode":"4000",
    "sg:province":"Li\u00e8ge",
    "wof:name":"D\u00c9lices De Mon Village",
    "wof:placetype":"venue"
},
  "geometry": {"coordinates":[5.5763039589,50.6455993652],"type":"Point"}
}