{
  "type": "Feature",
  "properties": {
    "addr:full":"Bellestraat 9 Edingen/enghien Hainaut 7850",
    "addr:housenumber":"9",
    "addr:postcode":"7850",
    "addr:street":"Bellestraat",
    "iso:country":"BE",
    "sg:address":"Bellestraat 9",
    "sg:city":"Edingen/enghien",
    "sg:orig_category":"Landmeters",
    "sg:phone":"+32 2 395 61 52",
    "sg:postcode":"7850",
    "sg:province":"Hainaut",
    "wof:name":"Philip Devleminck",
    "wof:placetype":"venue"
},
  "geometry": {"coordinates":[4.0132780075,50.691734314],"type":"Point"}
}