{
  "type": "Feature",
  "properties": {
    "addr:full":"Rue Du Sart-hulet 71 Namur Namur 5100",
    "addr:housenumber":"71",
    "addr:postcode":"5100",
    "addr:street":"Rue Du Sart-Hulet",
    "iso:country":"BE",
    "sg:address":"Rue Du Sart-hulet 71",
    "sg:city":"Namur",
    "sg:orig_category":"Agences de presse",
    "sg:phone":"+32 81 30 62 67",
    "sg:postcode":"5100",
    "sg:province":"Namur",
    "wof:name":"Thierry Remacle",
    "wof:placetype":"venue"
},
  "geometry": {"coordinates":[4.8801970482,50.4352378845],"type":"Point"}
}