{
  "type": "Feature",
  "properties": {
    "addr:full":"Lossing 22 Westerlo Antwerpen 2260",
    "addr:housenumber":"22",
    "addr:postcode":"2260",
    "addr:street":"Lossing",
    "iso:country":"BE",
    "sg:address":"Lossing 22",
    "sg:city":"Westerlo",
    "sg:classifiers":[
        {
            "category":"Manufacturing",
            "subcategory":"Metals",
            "type":"Manufacturing & Wholesale Goods"
        }
    ],
    "sg:phone":"+32 15 22 49 10",
    "sg:postcode":"2260",
    "sg:province":"Antwerpen",
    "sg:tags":[
        "steel",
        "stainless"
    ],
    "wof:name":"Hertecant Nv",
    "wof:placetype":"venue"
},
  "geometry": {"coordinates":[4.8224868774,51.09324646],"type":"Point"}
}