{
  "type": "Feature",
  "properties": {
    "addr:full":"Chauss\u00c9e D'ixelles 141 Elsene/ixelles Bruxelles-Capitale 1050",
    "addr:housenumber":"141",
    "addr:postcode":"1050",
    "addr:street":"Chausse\u0301E D'Ixelles",
    "iso:country":"BE",
    "sg:address":"Chauss\u00c9e D'ixelles 141",
    "sg:city":"Elsene/ixelles",
    "sg:classifiers":[
        {
            "category":"Restaurant",
            "type":"Food & Drink"
        }
    ],
    "sg:phone":"+32 2 513 53 12",
    "sg:postcode":"1050",
    "sg:province":"Bruxelles-Capitale",
    "wof:name":"Yamayu Santatsu",
    "wof:placetype":"venue"
},
  "geometry": {"coordinates":[4.3654317856,50.8339042664],"type":"Point"}
}