{
  "type": "Feature",
  "properties": {
    "addr:full":"Gentseleenstraat 18 Houthulst West-Vlaanderen 8650",
    "addr:housenumber":"18",
    "addr:postcode":"8650",
    "addr:street":"Gentseleenstraat",
    "iso:country":"BE",
    "sg:address":"Gentseleenstraat 18",
    "sg:city":"Houthulst",
    "sg:classifiers":[
        {
            "category":"Food & Beverages",
            "subcategory":"Fruits & Vegetables",
            "type":"Retail Goods"
        }
    ],
    "sg:phone":"+32 51 70 39 13",
    "sg:postcode":"8650",
    "sg:province":"West-Vlaanderen",
    "sg:tags":[
        "-"
    ],
    "wof:name":"Fruitmandje (het)",
    "wof:placetype":"venue"
},
  "geometry": {"coordinates":[2.9549219608,50.9858016968],"type":"Point"}
}