{
  "type": "Feature",
  "properties": {
    "addr:full":"Okegem Dorp 21 Ninove (okegem) Oost-Vlaanderen 9400",
    "addr:housenumber":"21",
    "addr:postcode":"9400",
    "addr:street":"Dorp",
    "iso:country":"BE",
    "sg:address":"Okegem Dorp 21",
    "sg:city":"Ninove (okegem)",
    "sg:classifiers":[
        {
            "category":"Home & Garden",
            "subcategory":"Kitchen Supply",
            "type":"Retail Goods"
        }
    ],
    "sg:phone":"+32 54 32 32 39",
    "sg:postcode":"9400",
    "sg:province":"Oost-Vlaanderen",
    "sg:tags":[
        "installation"
    ],
    "wof:name":"Dhondt E",
    "wof:placetype":"venue"
},
  "geometry": {"coordinates":[4.0232000351,50.8349113464],"type":"Point"}
}