{
  "type": "Feature",
  "properties": {
    "iso:country":"BE",
    "sg:address":"Rue Saint-mortier 35",
    "sg:city":"Ellezelles",
    "sg:classifiers":[
        {
            "category":"Professional",
            "type":"Services"
        }
    ],
    "sg:phone":"+32 68 54 26 02",
    "sg:postcode":"7890",
    "sg:province":"Hainaut",
    "sg:tags":[
        "organisation",
        "de",
        "restaurants",
        "f\u00cates",
        "catering"
    ],
    "wof:name":"Ch\u00c2teau Du Mylord",
    "wof:placetype":"venue"
},
  "geometry": {"coordinates":[3.673470974,50.7295799255],"type":"Point"}
}