{
  "type": "Feature",
  "properties": {
    "addr:full":"Bd Brand Whitlock 87 Bruxelles Bruxelles-Capitale 1200",
    "addr:housenumber":"87",
    "addr:postcode":"1200",
    "addr:street":"Brand Whitlock",
    "iso:country":"BE",
    "sg:address":"Bd Brand Whitlock 87",
    "sg:city":"Bruxelles",
    "sg:classifiers":[
        {
            "category":"Professional",
            "subcategory":"Printing & Photocopies",
            "type":"Services"
        }
    ],
    "sg:phone":"+32 2 741 12 11",
    "sg:postcode":"1200",
    "sg:province":"Bruxelles-Capitale",
    "sg:tags":[
        "publishing"
    ],
    "wof:name":"Setr Dow Jones Publishing Cy",
    "wof:placetype":"venue"
},
  "geometry": {"coordinates":[4.4062371254,50.8416862488],"type":"Point"}
}