{
  "type": "Feature",
  "properties": {
    "addr:full":"Klinkaardstraat 97b4 Kapellen Antwerpen 2950",
    "addr:housenumber":"97b4",
    "addr:postcode":"2950",
    "addr:street":"Klinkaardstraat",
    "iso:country":"BE",
    "sg:address":"Klinkaardstraat 97b4",
    "sg:city":"Kapellen",
    "sg:orig_category":"Instituts de beaut\u00e9",
    "sg:phone":"+32 3 665 21 73",
    "sg:postcode":"2950",
    "sg:province":"Antwerpen",
    "wof:name":"Rita Rennen",
    "wof:placetype":"venue"
},
  "geometry": {"coordinates":[4.4101119041,51.3510322571],"type":"Point"}
}