{
  "type": "Feature",
  "properties": {
    "addr:full":"Ninoofsesteenweg 342 Dilbeek Vlaams-Brabant 1700",
    "addr:housenumber":"342",
    "addr:postcode":"1700",
    "addr:street":"Ninoofsesteenweg",
    "iso:country":"BE",
    "sg:address":"Ninoofsesteenweg 342",
    "sg:city":"Dilbeek",
    "sg:orig_category":"Banken and kredietinstellingen",
    "sg:phone":"+32 2 569 36 38",
    "sg:postcode":"1700",
    "sg:province":"Vlaams-Brabant",
    "wof:name":"Bbl",
    "wof:placetype":"venue"
},
  "geometry": {"coordinates":[4.2610030174,50.8435783386],"type":"Point"}
}