{
  "type": "Feature",
  "properties": {
    "iso:country":"BE",
    "sg:address":"Chemin D'ellignies 12",
    "sg:city":"Frasnes-lez-anvaing (frasnes - Lez - Buissenal)",
    "sg:classifiers":[
        {
            "category":"Health Services",
            "subcategory":"Doctor",
            "type":"Services"
        }
    ],
    "sg:phone":"+32 69 87 52 08",
    "sg:postcode":"7911",
    "sg:province":"Hainaut",
    "sg:tags":[
        "medicinephysicians",
        "surgeon"
    ],
    "wof:name":"Gustin M",
    "wof:placetype":"venue"
},
  "geometry": {"coordinates":[3.6120491028,50.6731262207],"type":"Point"}
}