{
  "type": "Feature",
  "properties": {
    "addr:full":"Pont Du Ch\u00eane 42 Verviers Li\u00e8ge 4800",
    "addr:housenumber":"42",
    "addr:postcode":"4800",
    "addr:street":"Pont Du Che\u0302Ne",
    "iso:country":"BE",
    "sg:address":"Pont Du Ch\u00eane 42",
    "sg:city":"Verviers",
    "sg:classifiers":[
        {
            "category":"Bakery",
            "type":"Food & Drink"
        }
    ],
    "sg:phone":"+32 87 33 25 89",
    "sg:postcode":"4800",
    "sg:province":"Li\u00e8ge",
    "sg:tags":[
        "confectioner",
        "baker"
    ],
    "wof:name":"P\u00e2tisserie St-antoine",
    "wof:placetype":"venue"
},
  "geometry": {"coordinates":[5.8551898003,50.592300415],"type":"Point"}
}