{
  "type": "Feature",
  "properties": {
    "iso:country":"BE",
    "sg:address":"Diepenbekerweg 65b2",
    "sg:city":"Hasselt",
    "sg:orig_category":"Belastingconsulenten Diverse juridische dienstverlening",
    "sg:phone":"+32 11 30 13 50",
    "sg:postcode":"3500",
    "sg:province":"Limburg",
    "wof:name":"Bureau Van Havermaet",
    "wof:placetype":"venue"
},
  "geometry": {"coordinates":[5.3699798584,50.923122406],"type":"Point"}
}