{
  "type": "Feature",
  "properties": {
    "addr:full":"Toekomststraat 6 Sint-jans-molenbeek/molenbeek-saint-jean Bruxelles-Capitale 1080",
    "addr:housenumber":"6",
    "addr:postcode":"1080",
    "addr:street":"Toekomststraat",
    "iso:country":"BE",
    "sg:address":"Toekomststraat 6",
    "sg:city":"Sint-jans-molenbeek/molenbeek-saint-jean",
    "sg:orig_category":"Artsen and specialisten",
    "sg:phone":"+32 2 411 74 69",
    "sg:postcode":"1080",
    "sg:province":"Bruxelles-Capitale",
    "wof:name":"Toni Abi Samra",
    "wof:placetype":"venue"
},
  "geometry": {"coordinates":[4.3405218124,50.8563766479],"type":"Point"}
}