{
  "type": "Feature",
  "properties": {
    "addr:full":"Klapstraat 33 Sint-martens-latem (deurle) Oost-Vlaanderen 9831",
    "addr:housenumber":"33",
    "addr:postcode":"9831",
    "addr:street":"Klapstraat",
    "iso:country":"BE",
    "sg:address":"Klapstraat 33",
    "sg:city":"Sint-martens-latem (deurle)",
    "sg:classifiers":[
        {
            "category":"Building & Trades",
            "subcategory":"Landscaping Services",
            "type":"Services"
        }
    ],
    "sg:phone":"+32 9 282 80 62",
    "sg:postcode":"9831",
    "sg:province":"Oost-Vlaanderen",
    "sg:tags":[
        "gardening",
        "garden",
        "maintenance"
    ],
    "wof:name":"Moerkens Guy Tuinen Bvba",
    "wof:placetype":"venue"
},
  "geometry": {"coordinates":[3.6078429222,50.994972229],"type":"Point"}
}