{
  "type": "Feature",
  "properties": {
    "iso:country":"BE",
    "sg:address":"Rue Basse 45a",
    "sg:city":"Mouscron (dottignies)",
    "sg:classifiers":[
        {
            "category":"Professional",
            "subcategory":"Advertising",
            "type":"Services"
        }
    ],
    "sg:phone":"+32 56 48 71 54",
    "sg:postcode":"7711",
    "sg:province":"Hainaut",
    "sg:tags":[
        "item",
        "-",
        "business",
        "gift",
        "promotional"
    ],
    "wof:name":"Delannois B Ets",
    "wof:placetype":"venue"
},
  "geometry": {"coordinates":[3.307363987,50.728313446],"type":"Point"}
}