{
  "type": "Feature",
  "properties": {
    "addr:full":"Katschotseweg 1 Zonhoven Limburg 3520",
    "addr:housenumber":"1",
    "addr:postcode":"3520",
    "addr:street":"Katschotseweg",
    "iso:country":"BE",
    "sg:address":"Katschotseweg 1",
    "sg:city":"Zonhoven",
    "sg:orig_category":"Entretien and r\u00e9parations de voitures. V\u00e9hicules automobiles",
    "sg:phone":"+32 11 81 44 30",
    "sg:postcode":"3520",
    "sg:province":"Limburg",
    "wof:name":"Abeko Auto's",
    "wof:placetype":"venue"
},
  "geometry": {"coordinates":[5.3838691711,50.9918708801],"type":"Point"}
}