{
  "type": "Feature",
  "properties": {
    "addr:full":"Rue Aux Fleurs 14 Bruxelles Bruxelles-Capitale 1000",
    "addr:housenumber":"14",
    "addr:postcode":"1000",
    "addr:street":"Rue Aux Fleurs",
    "iso:country":"BE",
    "sg:address":"Rue Aux Fleurs 14",
    "sg:city":"Bruxelles",
    "sg:classifiers":[
        {
            "category":"Wholesale",
            "subcategory":"Music Publishers",
            "type":"Manufacturing & Wholesale Goods"
        }
    ],
    "sg:phone":"+32 2 534 83 25",
    "sg:postcode":"1000",
    "sg:province":"Bruxelles-Capitale",
    "wof:name":"Gsp Music Company",
    "wof:placetype":"venue"
},
  "geometry": {"coordinates":[4.3523468971,50.8529052734],"type":"Point"}
}