{
  "type": "Feature",
  "properties": {
    "iso:country":"BE",
    "sg:address":"Haasstrasse 31",
    "sg:city":"Eupen",
    "sg:classifiers":[
        {
            "category":"Food & Beverages",
            "subcategory":"Groceries & Convenience Stores",
            "type":"Retail Goods"
        }
    ],
    "sg:phone":"+32 87 55 27 87",
    "sg:postcode":"4700",
    "sg:province":"Li\u00e8ge",
    "sg:tags":[
        "grocer"
    ],
    "wof:name":"Inbiss Istambul",
    "wof:placetype":"venue"
},
  "geometry": {"coordinates":[6.0379271507,50.6232261658],"type":"Point"}
}