{
  "type": "Feature",
  "properties": {
    "iso:country":"BE",
    "sg:address":"Akkerstraat 22",
    "sg:city":"Mol",
    "sg:orig_category":"Installation de menuiserie en bois and plastique",
    "sg:phone":"+32 14 31 17 10",
    "sg:postcode":"2400",
    "sg:province":"Antwerpen",
    "wof:name":"Andre Van Baelen",
    "wof:placetype":"venue"
},
  "geometry": {"coordinates":[5.0981497765,51.2029037476],"type":"Point"}
}