{
  "type": "Feature",
  "properties": {
    "iso:country":"BE",
    "sg:address":"Mageret 45",
    "sg:city":"Bastogne",
    "sg:orig_category":"Sportclubs Sportterreinen and installaties behalve sportcentra",
    "sg:phone":"+32 61 21 35 70",
    "sg:postcode":"6600",
    "sg:province":"Luxembourg",
    "wof:name":"J.s. Mageretoise",
    "wof:placetype":"venue"
},
  "geometry": {"coordinates":[5.7148199081,50.0007820129],"type":"Point"}
}