{
  "type": "Feature",
  "properties": {
    "iso:country":"BE",
    "sg:address":"Gaston Martensplein 2",
    "sg:city":"Zulte",
    "sg:orig_category":"Elektrische installaties voor woningen",
    "sg:phone":"+32 9 388 53 58",
    "sg:postcode":"9870",
    "sg:province":"Oost-Vlaanderen",
    "wof:name":"Stefan Cokelaere",
    "wof:placetype":"venue"
},
  "geometry": {"coordinates":[3.4429869652,50.9216423035],"type":"Point"}
}