{
  "type": "Feature",
  "properties": {
    "iso:country":"BE",
    "sg:address":"Stationsstraat 233",
    "sg:city":"Deerlijk",
    "sg:classifiers":[
        {
            "category":"Home & Garden",
            "subcategory":"Home Furnishings",
            "type":"Retail Goods"
        }
    ],
    "sg:phone":"+32 56 77 74 92",
    "sg:postcode":"8540",
    "sg:province":"West-Vlaanderen",
    "sg:tags":[
        "-",
        "furniture"
    ],
    "wof:name":"Gaverzicht",
    "wof:placetype":"venue"
},
  "geometry": {"coordinates":[3.349670887,50.8399124146],"type":"Point"}
}