{
  "type": "Feature",
  "properties": {
    "addr:full":"Rue Des Fiefs 10 Lasne Brabant Wallon 1380",
    "addr:housenumber":"10",
    "addr:postcode":"1380",
    "addr:street":"Rue Des Fiefs",
    "iso:country":"BE",
    "sg:address":"Rue Des Fiefs 10",
    "sg:city":"Lasne",
    "sg:orig_category":"Loodgieterij, verwarming and sanitaire installaties",
    "sg:phone":"+32 2 633 26 73",
    "sg:postcode":"1380",
    "sg:province":"Brabant Wallon",
    "wof:name":"Luc Vandenheede",
    "wof:placetype":"venue"
},
  "geometry": {"coordinates":[4.4973487854,50.6769294739],"type":"Point"}
}