{
  "type": "Feature",
  "properties": {
    "addr:full":"Stationssteenweg 202 Nijlen Antwerpen 2560",
    "addr:housenumber":"202",
    "addr:postcode":"2560",
    "addr:street":"Stationssteenweg",
    "iso:country":"BE",
    "sg:address":"Stationssteenweg 202",
    "sg:city":"Nijlen",
    "sg:orig_category":"Mat\u00e9riel m\u00e9dical and orthop\u00e9dique and proth\u00e8ses Fab",
    "sg:phone":"+32 3 480 80 99",
    "sg:postcode":"2560",
    "sg:province":"Antwerpen",
    "wof:name":"Ceulemans",
    "wof:placetype":"venue"
},
  "geometry": {"coordinates":[4.6219959259,51.1484680176],"type":"Point"}
}