{
  "type": "Feature",
  "properties": {
    "addr:full":"Holmanstraat Herzele (steenhuize-wijnhuize) Oost-Vlaanderen 9550",
    "addr:postcode":"9550",
    "addr:street":"Holmanstraat;Steenhuize-Wijnhuize",
    "iso:country":"BE",
    "sg:address":"Holmanstraat",
    "sg:city":"Herzele (steenhuize-wijnhuize)",
    "sg:orig_category":"Cafetarias and selfservice restaurants",
    "sg:phone":"+32 54 50 19 73",
    "sg:postcode":"9550",
    "sg:province":"Oost-Vlaanderen",
    "wof:name":"Amalrik",
    "wof:placetype":"venue"
},
  "geometry": {"coordinates":[3.8879890442,50.8435096741],"type":"Point"}
}