{
  "type": "Feature",
  "properties": {
    "addr:full":"'s Hertogendijk 97b Stabroek Antwerpen 2940",
    "addr:housenumber":"97b",
    "addr:postcode":"2940",
    "addr:street":"' S Hertogendijk",
    "iso:country":"BE",
    "sg:address":"'s Hertogendijk 97b",
    "sg:city":"Stabroek",
    "sg:orig_category":"Metaalbehandeling and -bekleding",
    "sg:phone":"+32 3 569 01 77",
    "sg:postcode":"2940",
    "sg:province":"Antwerpen",
    "wof:name":"Burgelman",
    "wof:placetype":"venue"
},
  "geometry": {"coordinates":[4.3843541145,51.3269996643],"type":"Point"}
}