{
  "type": "Feature",
  "properties": {
    "addr:full":"Kruisdijklaan 10 Beveren Oost-Vlaanderen 9120",
    "addr:housenumber":"10",
    "addr:postcode":"9120",
    "addr:street":"Kruisdijklaan",
    "iso:country":"BE",
    "sg:address":"Kruisdijklaan 10",
    "sg:city":"Beveren",
    "sg:orig_category":"Elektrische installaties voor woningen Woningbouw",
    "sg:phone":"+32 3 575 04 73",
    "sg:postcode":"9120",
    "sg:province":"Oost-Vlaanderen",
    "wof:name":"Bouwtechiek Invest",
    "wof:placetype":"venue"
},
  "geometry": {"coordinates":[4.2747631073,51.2510604858],"type":"Point"}
}