{
  "type": "Feature",
  "properties": {
    "iso:country":"BE",
    "sg:address":"Elsensesteenweg 28",
    "sg:city":"Elsene (brussel)",
    "sg:orig_category":"Kleding Textiel",
    "sg:phone":"+32 2 511 53 33",
    "sg:postcode":"1050",
    "sg:province":"Bruxelles-Capitale",
    "wof:name":"Veritas",
    "wof:placetype":"venue"
},
  "geometry": {"coordinates":[4.362279892,50.8374519348],"type":"Point"}
}