{
  "type": "Feature",
  "properties": {
    "addr:full":"Magnoliastraat 9b Houthalen-helchteren (houthalen) Limburg 3530",
    "addr:housenumber":"9b",
    "addr:postcode":"3530",
    "addr:street":"Magnoliastraat",
    "iso:country":"BE",
    "sg:address":"Magnoliastraat 9b",
    "sg:city":"Houthalen-helchteren (houthalen)",
    "sg:classifiers":[
        {
            "category":"Professional",
            "subcategory":"Management & Consulting",
            "type":"Services"
        }
    ],
    "sg:phone":"+32 89 38 52 31",
    "sg:postcode":"3530",
    "sg:province":"Limburg",
    "sg:tags":[
        "consultant"
    ],
    "wof:name":"Scrayen Johan Bedrijfsadvies Bvba",
    "wof:placetype":"venue"
},
  "geometry": {"coordinates":[5.4792690277,51.0197601318],"type":"Point"}
}