{
  "type": "Feature",
  "properties": {
    "addr:full":"Verbindingsstraat 18 Hamme Oost-Vlaanderen 9220",
    "addr:housenumber":"18",
    "addr:postcode":"9220",
    "addr:street":"Verbindingsstraat",
    "iso:country":"BE",
    "sg:address":"Verbindingsstraat 18",
    "sg:city":"Hamme",
    "sg:orig_category":"Fotografen and fotostudio's",
    "sg:phone":"+32 52 47 68 61",
    "sg:postcode":"9220",
    "sg:province":"Oost-Vlaanderen",
    "wof:name":"Dirk Van Lombergen",
    "wof:placetype":"venue"
},
  "geometry": {"coordinates":[4.1434597969,51.0917510986],"type":"Point"}
}