{
  "type": "Feature",
  "properties": {
    "addr:full":"Rue De Tilff 56 Li\u00e8ge 1 (angleur) Li\u00e8ge 4031",
    "addr:housenumber":"56;1",
    "addr:postcode":"4031",
    "addr:street":"Rue De Tilff",
    "iso:country":"BE",
    "sg:address":"Rue De Tilff 56",
    "sg:city":"Li\u00e8ge 1 (angleur)",
    "sg:classifiers":[
        {
            "category":"Retail",
            "subcategory":"Repair Shop",
            "type":"Services"
        }
    ],
    "sg:phone":"+32 4 367 42 83",
    "sg:postcode":"4031",
    "sg:province":"Li\u00e8ge",
    "sg:tags":[
        "radio",
        "television",
        "-",
        "maintenance"
    ],
    "wof:name":"S.k. Vision",
    "wof:placetype":"venue"
},
  "geometry": {"coordinates":[5.6010389328,50.6097412109],"type":"Point"}
}