{
  "type": "Feature",
  "properties": {
    "iso:country":"BE",
    "sg:address":"Burg. Portmanslaan 53",
    "sg:city":"Dendermonde",
    "sg:orig_category":"Industri\u00eble wasserijen and droogkuis",
    "sg:phone":"+32 52 21 26 42",
    "sg:postcode":"9200",
    "sg:province":"Oost-Vlaanderen",
    "wof:name":"Wasserij Moderne",
    "wof:placetype":"venue"
},
  "geometry": {"coordinates":[4.0983099937,51.0315208435],"type":"Point"}
}