{
  "type": "Feature",
  "properties": {
    "iso:country":"BE",
    "sg:address":"Huisheuvelstraat 58",
    "sg:city":"Wuustwezel",
    "sg:orig_category":"Eleveurs de bovins",
    "sg:phone":"+32 3 669 83 87",
    "sg:postcode":"2990",
    "sg:province":"Antwerpen",
    "wof:name":"Alexander Poels",
    "wof:placetype":"venue"
},
  "geometry": {"coordinates":[4.6030230522,51.4288749695],"type":"Point"}
}