{
  "type": "Feature",
  "properties": {
    "addr:full":"Square De La Qui\u00e9tude 20 Bruxelles (woluwe-saint-pierre) Bruxelles-Capitale 1150",
    "addr:housenumber":"20",
    "addr:postcode":"1150",
    "addr:street":"Square De La Quie\u0301Tude",
    "iso:country":"BE",
    "sg:address":"Square De La Qui\u00e9tude 20",
    "sg:city":"Bruxelles (woluwe-saint-pierre)",
    "sg:classifiers":[
        {
            "category":"Health Services",
            "subcategory":"Health Practitioner",
            "type":"Services"
        }
    ],
    "sg:phone":"+32 2 640 72 25",
    "sg:postcode":"1150",
    "sg:province":"Bruxelles-Capitale",
    "sg:tags":[
        "physiotherapist"
    ],
    "wof:name":"Ryelandt Diane",
    "wof:placetype":"venue"
},
  "geometry": {"coordinates":[4.4124670029,50.8278617859],"type":"Point"}
}