{
  "type": "Feature",
  "properties": {
    "iso:country":"BE",
    "sg:address":"Vossestraat 37",
    "sg:city":"Anzegem",
    "sg:classifiers":[
        {
            "category":"Restaurant",
            "type":"Food & Drink"
        }
    ],
    "sg:phone":"+32 56 77 10 96",
    "sg:postcode":"8570",
    "sg:province":"West-Vlaanderen",
    "wof:name":"De Vossenhoek",
    "wof:placetype":"venue"
},
  "geometry": {"coordinates":[3.4193849564,50.8224601746],"type":"Point"}
}