{
  "type": "Feature",
  "properties": {
    "iso:country":"BE",
    "sg:address":"Dorpsstraat 76",
    "sg:city":"Wuustwezel",
    "sg:orig_category":"Alimentation sp\u00e9cialis\u00e9e",
    "sg:phone":"+32 3 669 70 75",
    "sg:postcode":"2990",
    "sg:province":"Antwerpen",
    "wof:name":"Natuurwinkeltje",
    "wof:placetype":"venue"
},
  "geometry": {"coordinates":[4.597550869,51.3884277344],"type":"Point"}
}