{
  "type": "Feature",
  "properties": {
    "addr:full":"Rue De L\u00b4et\u00c9 81-83 Elsene/ixelles Bruxelles-Capitale 1050",
    "addr:housenumber":"81-83",
    "addr:postcode":"1050",
    "addr:street":"Rue De L\u00b4Ete\u0301",
    "iso:country":"BE",
    "sg:address":"Rue De L\u00b4et\u00c9 81-83",
    "sg:city":"Elsene/ixelles",
    "sg:classifiers":[
        {
            "category":"Shopping",
            "subcategory":"Gifts & Souvenirs",
            "type":"Retail Goods"
        }
    ],
    "sg:phone":"+32 2 644 09 44",
    "sg:postcode":"1050",
    "sg:province":"Bruxelles-Capitale",
    "sg:tags":[
        "geschenken"
    ],
    "wof:name":"H.p.b. Club",
    "wof:placetype":"venue"
},
  "geometry": {"coordinates":[4.3891887665,50.8183441162],"type":"Point"}
}