{
  "type": "Feature",
  "properties": {
    "addr:full":"Roterijstraat 60 Wevelgem West-Vlaanderen 8560",
    "addr:housenumber":"60",
    "addr:postcode":"8560",
    "addr:street":"Roterijstraat",
    "iso:country":"BE",
    "sg:address":"Roterijstraat 60",
    "sg:city":"Wevelgem",
    "sg:orig_category":"Non-Classified Establishments",
    "sg:phone":"+32 56 41 60 44",
    "sg:postcode":"8560",
    "sg:province":"West-Vlaanderen",
    "wof:name":"Lienard A & L",
    "wof:placetype":"venue"
},
  "geometry": {"coordinates":[3.1837389469,50.8150749207],"type":"Point"}
}