{
  "type": "Feature",
  "properties": {
    "addr:full":"Rue Du Coll\u00c8ge 19 Vise Li\u00e8ge 4600",
    "addr:housenumber":"19",
    "addr:postcode":"4600",
    "addr:street":"Rue Du Colle\u0300Ge",
    "iso:country":"BE",
    "sg:address":"Rue Du Coll\u00c8ge 19",
    "sg:city":"Vise",
    "sg:orig_category":"Baby- and kinderkleding",
    "sg:phone":"+32 4 379 43 98",
    "sg:postcode":"4600",
    "sg:province":"Li\u00e8ge",
    "wof:name":"Maison Ptilapin",
    "wof:placetype":"venue"
},
  "geometry": {"coordinates":[5.6946239471,50.7358016968],"type":"Point"}
}