{
  "type": "Feature",
  "properties": {
    "iso:country":"BE",
    "sg:address":"Mandellaan 353",
    "sg:city":"Roeselare",
    "sg:classifiers":[
        {
            "category":"Personal",
            "subcategory":"Beauty Salon",
            "type":"Services"
        }
    ],
    "sg:phone":"+32 51 20 46 63",
    "sg:postcode":"8800",
    "sg:province":"West-Vlaanderen",
    "sg:tags":[
        "child",
        "-",
        "hairdressing"
    ],
    "wof:name":"Dina",
    "wof:placetype":"venue"
},
  "geometry": {"coordinates":[3.1458489895,50.9456062317],"type":"Point"}
}