{
  "type": "Feature",
  "properties": {
    "addr:full":"Stevoortweg 26 Herk-de-stad Limburg 3540",
    "addr:housenumber":"26",
    "addr:postcode":"3540",
    "addr:street":"Stevoortweg",
    "iso:country":"BE",
    "sg:address":"Stevoortweg 26",
    "sg:city":"Herk-de-stad",
    "sg:classifiers":[
        {
            "category":"Health Services",
            "subcategory":"Health Practitioner",
            "type":"Services"
        }
    ],
    "sg:phone":"+32 13 55 41 17",
    "sg:postcode":"3540",
    "sg:province":"Limburg",
    "sg:tags":[
        "physiotherapist"
    ],
    "wof:name":"Graulus Gerda",
    "wof:placetype":"venue"
},
  "geometry": {"coordinates":[5.172372818,50.9390144348],"type":"Point"}
}