{
  "type": "Feature",
  "properties": {
    "iso:country":"BE",
    "sg:address":"Schriekstraat 139",
    "sg:city":"Schriek",
    "sg:classifiers":[
        {
            "category":"Structure",
            "subcategory":"Building",
            "type":"Public Place"
        }
    ],
    "sg:phone":"+32 15 75 59 65",
    "sg:postcode":"2223",
    "sg:province":"Antwerpen",
    "sg:tags":[
        "apartment"
    ],
    "wof:name":"Alfons Timmermans Nv",
    "wof:placetype":"venue"
},
  "geometry": {"coordinates":[4.6699519157,51.0394058228],"type":"Point"}
}