{
  "type": "Feature",
  "properties": {
    "iso:country":"BE",
    "sg:address":"Steenveldstraat 25",
    "sg:city":"Lubbeek",
    "sg:orig_category":"M\u00e9decins and sp\u00e9cialistes",
    "sg:phone":"+32 16 62 00 78",
    "sg:postcode":"3210",
    "sg:province":"Vlaams-Brabant",
    "wof:name":"Kathleen Gysemans",
    "wof:placetype":"venue"
},
  "geometry": {"coordinates":[4.7739062309,50.8993606567],"type":"Point"}
}