{
  "type": "Feature",
  "properties": {
    "addr:full":"Grote Steenweg 368 Linter Vlaams-Brabant 3350",
    "addr:housenumber":"368",
    "addr:postcode":"3350",
    "addr:street":"Grote Steenweg;Vlaams-Brabant",
    "iso:country":"BE",
    "sg:address":"Grote Steenweg 368",
    "sg:city":"Linter",
    "sg:orig_category":"Afbraak- and draineerwerken Elektrische installaties voor woningen Industri\u00eble elektrische installat",
    "sg:phone":"+32 11 78 23 53",
    "sg:postcode":"3350",
    "sg:province":"Vlaams-Brabant",
    "wof:name":"Hottat",
    "wof:placetype":"venue"
},
  "geometry": {"coordinates":[5.0559048653,50.848651886],"type":"Point"}
}