{
  "type": "Feature",
  "properties": {
    "iso:country":"BE",
    "sg:address":"Varenvelden 9",
    "sg:city":"Rijkevorsel",
    "sg:classifiers":[
        {
            "category":"Professional",
            "subcategory":"Secretarial Services",
            "type":"Services"
        }
    ],
    "sg:phone":"+32 3 314 24 04",
    "sg:postcode":"2310",
    "sg:province":"Antwerpen",
    "sg:tags":[
        "firm"
    ],
    "wof:name":"Stessens A",
    "wof:placetype":"venue"
},
  "geometry": {"coordinates":[4.7633700371,51.3393745422],"type":"Point"}
}