{
  "type": "Feature",
  "properties": {
    "addr:full":"Kanaalweg 18 Oostrozebeke West-Vlaanderen 8780",
    "addr:housenumber":"18",
    "addr:postcode":"8780",
    "addr:street":"Kanaalweg",
    "iso:country":"BE",
    "sg:address":"Kanaalweg 18",
    "sg:city":"Oostrozebeke",
    "sg:orig_category":"Artistes ind\u00e9pendants",
    "sg:phone":"+32 56 66 73 61",
    "sg:postcode":"8780",
    "sg:province":"West-Vlaanderen",
    "wof:name":"Georges Schelstraete",
    "wof:placetype":"venue"
},
  "geometry": {"coordinates":[3.3137280941,50.9063987732],"type":"Point"}
}