{
  "type": "Feature",
  "properties": {
    "iso:country":"BE",
    "sg:address":"Putstraat 26",
    "sg:city":"Gent",
    "sg:orig_category":"Boekhouders",
    "sg:phone":"+32 9 222 92 48",
    "sg:postcode":"9051",
    "sg:province":"Oost-Vlaanderen",
    "wof:name":"Maria Da Assuncao",
    "wof:placetype":"venue"
},
  "geometry": {"coordinates":[3.6843290329,51.0158500671],"type":"Point"}
}