{
  "type": "Feature",
  "properties": {
    "addr:full":"Rue Grand Aaz 39 Oupeye (herm\u00e9e) Li\u00e8ge 4680",
    "addr:housenumber":"39",
    "addr:postcode":"4680",
    "addr:street":"Rue Grand Aaz",
    "iso:country":"BE",
    "sg:address":"Rue Grand Aaz 39",
    "sg:city":"Oupeye (herm\u00e9e)",
    "sg:orig_category":"Non-Classified Establishments",
    "sg:phone":"+32 4 278 01 59",
    "sg:postcode":"4680",
    "sg:province":"Li\u00e8ge",
    "wof:name":"Balthasart",
    "wof:placetype":"venue"
},
  "geometry": {"coordinates":[5.6106500626,50.7157287598],"type":"Point"}
}