{
  "type": "Feature",
  "properties": {
    "addr:full":"Eupenerstrasse 7 Raeren/raeren Li\u00e8ge 4731",
    "addr:housenumber":"7",
    "addr:postcode":"4731",
    "addr:street":"Eupenerstrasse",
    "iso:country":"BE",
    "sg:address":"Eupenerstrasse 7",
    "sg:city":"Raeren/raeren",
    "sg:orig_category":"Kapsalons",
    "sg:phone":"+32 87 85 16 95",
    "sg:postcode":"4731",
    "sg:province":"Li\u00e8ge",
    "wof:name":"D. Schmitz",
    "wof:placetype":"venue"
},
  "geometry": {"coordinates":[6.0821890831,50.6913490295],"type":"Point"}
}