{
  "type": "Feature",
  "properties": {
    "addr:full":"Nationalestraat 114 Antwerpen Antwerpen 2000",
    "addr:housenumber":"114",
    "addr:postcode":"2000",
    "addr:street":"Nationalestraat",
    "iso:country":"BE",
    "sg:address":"Nationalestraat 114",
    "sg:city":"Antwerpen",
    "sg:classifiers":[
        {
            "category":"Shopping",
            "subcategory":"Clothing, Apparel, & Fashions",
            "type":"Retail Goods"
        }
    ],
    "sg:phone":"+32 3 231 94 23",
    "sg:postcode":"2000",
    "sg:province":"Antwerpen",
    "sg:tags":[
        "boutique"
    ],
    "wof:name":"Medusa",
    "wof:placetype":"venue"
},
  "geometry": {"coordinates":[4.3981041908,51.2141685486],"type":"Point"}
}