{
  "type": "Feature",
  "properties": {
    "addr:full":"Rue De Tourcoing 94b Mouscron Hainaut 7700",
    "addr:housenumber":"94b",
    "addr:postcode":"7700",
    "addr:street":"Rue De Tourcoing",
    "iso:country":"BE",
    "sg:address":"Rue De Tourcoing 94b",
    "sg:city":"Mouscron",
    "sg:classifiers":[
        {
            "category":"Professional",
            "subcategory":"Credit Reporting & Collection",
            "type":"Services"
        }
    ],
    "sg:phone":"+32 56 33 45 77",
    "sg:postcode":"7700",
    "sg:province":"Hainaut",
    "sg:tags":[
        "bailiff"
    ],
    "wof:name":"Mercier A",
    "wof:placetype":"venue"
},
  "geometry": {"coordinates":[3.2097899914,50.7441291809],"type":"Point"}
}