{
  "type": "Feature",
  "properties": {
    "iso:country":"BE",
    "sg:address":"Sint-maartenplein 1",
    "sg:city":"Hasselt",
    "sg:orig_category":"V\u00eatements pour Hommes",
    "sg:phone":"+32 11 31 23 10",
    "sg:postcode":"3512",
    "sg:province":"Limburg",
    "wof:name":"Bex Select Kleding",
    "wof:placetype":"venue"
},
  "geometry": {"coordinates":[5.2483258247,50.9166564941],"type":"Point"}
}