{
  "type": "Feature",
  "properties": {
    "addr:full":"Rue Macel Louis 23 Pietrebais Brabant Wallon 1315",
    "addr:housenumber":"23;1315",
    "addr:street":"Rue Macel Louis;Brabant Wallon",
    "iso:country":"BE",
    "sg:address":"Rue Macel Louis 23",
    "sg:city":"Pietrebais",
    "sg:orig_category":"Woningbouw",
    "sg:phone":"+32 10 84 18 86",
    "sg:postcode":"1315",
    "sg:province":"Brabant Wallon",
    "wof:name":"L'edifice",
    "wof:placetype":"venue"
},
  "geometry": {"coordinates":[4.7501821518,50.7311935425],"type":"Point"}
}