{
  "type": "Feature",
  "properties": {
    "addr:full":"Geraardsbergsesteenweg 124 Aalst Oost-Vlaanderen 9320",
    "addr:housenumber":"124",
    "addr:postcode":"9320",
    "addr:street":"Geraardsbergsesteenweg",
    "iso:country":"BE",
    "sg:address":"Geraardsbergsesteenweg 124",
    "sg:city":"Aalst",
    "sg:orig_category":"Art and fournitures artistiques",
    "sg:phone":"+32 53 83 48 49",
    "sg:postcode":"9320",
    "sg:province":"Oost-Vlaanderen",
    "wof:name":"Hubert Van Mulders",
    "wof:placetype":"venue"
},
  "geometry": {"coordinates":[4.0363049507,50.9318313599],"type":"Point"}
}