{
  "type": "Feature",
  "properties": {
    "iso:country":"BE",
    "sg:address":"Rue Ferrer 26",
    "sg:city":"Morlanwelz",
    "sg:orig_category":"Enseignement maternel and primaire",
    "sg:phone":"+32 64 44 44 37",
    "sg:postcode":"7141",
    "sg:province":"Hainaut",
    "wof:name":"Ecole Fond. Communale",
    "wof:placetype":"venue"
},
  "geometry": {"coordinates":[4.2615809441,50.4513206482],"type":"Point"}
}