{
  "type": "Feature",
  "properties": {
    "addr:full":"Boeyendaal 74 Herenthout Antwerpen 2270",
    "addr:housenumber":"74",
    "addr:postcode":"2270",
    "addr:street":"Boeyendaal",
    "iso:country":"BE",
    "sg:address":"Boeyendaal 74",
    "sg:city":"Herenthout",
    "sg:classifiers":[
        {
            "category":"Organizations",
            "subcategory":"Community Association",
            "type":"Services"
        }
    ],
    "sg:phone":"+32 14 51 40 41",
    "sg:postcode":"2270",
    "sg:province":"Antwerpen",
    "sg:tags":[
        "environment",
        "organisation",
        "-"
    ],
    "wof:name":"Vogelbescherming Vlaanderen",
    "wof:placetype":"venue"
},
  "geometry": {"coordinates":[4.7693881989,51.1375160217],"type":"Point"}
}