{
  "type": "Feature",
  "properties": {
    "addr:full":"Baron Robert De Vironlaan 108 Box 11 Dilbeek Vlaams-Brabant 1700",
    "addr:housenumber":"108 box 11",
    "addr:postcode":"1700",
    "addr:street":"Baron Robert De Vironlaan",
    "iso:country":"BE",
    "sg:address":"Baron Robert De Vironlaan 108 Box 11",
    "sg:city":"Dilbeek",
    "sg:classifiers":[
        {
            "category":"Professional",
            "subcategory":"Management & Consulting",
            "type":"Services"
        }
    ],
    "sg:phone":"+32 2 569 40 87",
    "sg:postcode":"1700",
    "sg:province":"Vlaams-Brabant",
    "sg:tags":[
        "-",
        "processing",
        "data",
        "consultant"
    ],
    "wof:name":"Golvers L",
    "wof:placetype":"venue"
},
  "geometry": {"coordinates":[4.2726712227,50.8460655212],"type":"Point"}
}