{
  "type": "Feature",
  "properties": {
    "addr:full":"Sint-antoniusweg 95 Neerpelt Limburg 3910",
    "addr:housenumber":"95",
    "addr:postcode":"3910",
    "addr:street":"Sint-Antoniusweg",
    "iso:country":"BE",
    "sg:address":"Sint-antoniusweg 95",
    "sg:city":"Neerpelt",
    "sg:classifiers":[
        {
            "category":"Shopping",
            "subcategory":"Pets & Pet Supplies",
            "type":"Retail Goods"
        }
    ],
    "sg:phone":"+32 11 64 38 27",
    "sg:postcode":"3910",
    "sg:province":"Limburg",
    "sg:tags":[
        "bird"
    ],
    "wof:name":"Hendrickx (filiaal Neerpelt)",
    "wof:placetype":"venue"
},
  "geometry": {"coordinates":[5.4574418068,51.2305374146],"type":"Point"}
}