{
  "type": "Feature",
  "properties": {
    "iso:country":"BE",
    "sg:address":"Wayenborgstraat 9",
    "sg:city":"Mechelen",
    "sg:orig_category":"Tijdelijke werkgelegenheid and uitzendkantoren",
    "sg:phone":"+32 15 27 40 16",
    "sg:postcode":"2800",
    "sg:province":"Antwerpen",
    "wof:name":"Euromatch",
    "wof:placetype":"venue"
},
  "geometry": {"coordinates":[4.4427142143,51.0496559143],"type":"Point"}
}