{
  "type": "Feature",
  "properties": {
    "addr:full":"Lotenhullestraat 30 Aalter Oost-Vlaanderen 9881",
    "addr:housenumber":"30",
    "addr:postcode":"9881",
    "addr:street":"Lotenhullestraat",
    "iso:country":"BE",
    "sg:address":"Lotenhullestraat 30",
    "sg:city":"Aalter",
    "sg:orig_category":"Enseignement maternel and primaire",
    "sg:phone":"+32 9 374 16 97",
    "sg:postcode":"9881",
    "sg:province":"Oost-Vlaanderen",
    "wof:name":"Vrije Lagere School",
    "wof:placetype":"venue"
},
  "geometry": {"coordinates":[3.486579895,51.0786094666],"type":"Point"}
}