{
  "type": "Feature",
  "properties": {
    "iso:country":"BE",
    "sg:address":"Eekloseweg 8",
    "sg:city":"Knesselare (ursel)",
    "sg:classifiers":[
        {
            "category":"Personal",
            "subcategory":"Beauty Salon",
            "type":"Services"
        }
    ],
    "sg:phone":"+32 9 374 39 83",
    "sg:postcode":"9910",
    "sg:province":"Oost-Vlaanderen",
    "wof:name":"Eva",
    "wof:placetype":"venue"
},
  "geometry": {"coordinates":[3.4858939648,51.1307106018],"type":"Point"}
}