{
  "type": "Feature",
  "properties": {
    "iso:country":"BE",
    "sg:address":"Sint-truidersteenweg 116",
    "sg:city":"Borgloon",
    "sg:classifiers":[
        {
            "category":"Autos & Motor Vehicles",
            "subcategory":"Fuel & Gas Station",
            "type":"Retail Goods"
        }
    ],
    "sg:phone":"+32 12 74 55 02",
    "sg:postcode":"3840",
    "sg:province":"Limburg",
    "sg:tags":[
        "stations-service",
        "carburants"
    ],
    "wof:name":"J.v.p. Sound Systems",
    "wof:placetype":"venue"
},
  "geometry": {"coordinates":[5.3292889595,50.8044586182],"type":"Point"}
}