{
  "type": "Feature",
  "properties": {
    "iso:country":"BE",
    "sg:address":"Avenue Raymond Vander Bruggen 36",
    "sg:city":"Bruxelles",
    "sg:classifiers":[
        {
            "category":"Community Center",
            "subcategory":"Senior",
            "type":"Public Place"
        }
    ],
    "sg:phone":"+32 2 521 04 54",
    "sg:postcode":"1070",
    "sg:province":"Bruxelles-Capitale",
    "sg:tags":[
        "steel",
        "metal",
        "part",
        "sheet"
    ],
    "wof:name":"Ateliers De Decolletage Et Construction Oudaert S.a.",
    "wof:placetype":"venue"
},
  "geometry": {"coordinates":[4.3154292107,50.8373069763],"type":"Point"}
}