{
  "type": "Feature",
  "properties": {
    "iso:country":"BE",
    "sg:address":"Fruitmarkt 12b6",
    "sg:city":"Genk",
    "sg:orig_category":"Kapsalons",
    "sg:phone":"+32 89 35 84 67",
    "sg:postcode":"3600",
    "sg:province":"Limburg",
    "wof:name":"Coiffure Silvana",
    "wof:placetype":"venue"
},
  "geometry": {"coordinates":[5.5000128746,50.9649162292],"type":"Point"}
}