{
  "type": "Feature",
  "properties": {
    "addr:full":"Brielken 28a Evergem Oost-Vlaanderen 9940",
    "addr:housenumber":"28a",
    "addr:postcode":"9940",
    "addr:street":"Brielken;Oost-Vlaanderen",
    "iso:country":"BE",
    "sg:address":"Brielken 28a",
    "sg:city":"Evergem",
    "sg:classifiers":[
        {
            "category":"Restaurant",
            "type":"Food & Drink"
        }
    ],
    "sg:phone":"+32 9 253 48 79",
    "sg:postcode":"9940",
    "sg:province":"Oost-Vlaanderen",
    "wof:name":"'t Gezegde",
    "wof:placetype":"venue"
},
  "geometry": {"coordinates":[3.6993699074,51.1108398438],"type":"Point"}
}