{
  "type": "Feature",
  "properties": {
    "iso:country":"BE",
    "sg:address":"Rue Saint-fiacre 23",
    "sg:city":"Fleurus",
    "sg:classifiers":[
        {
            "category":"Shopping",
            "subcategory":"Bicycles & Sporting Goods",
            "type":"Retail Goods"
        }
    ],
    "sg:phone":"+32 71 81 57 77",
    "sg:postcode":"6220",
    "sg:province":"Hainaut",
    "sg:tags":[
        "article",
        "de",
        "sport",
        "camping"
    ],
    "wof:name":"Kangourous Sports",
    "wof:placetype":"venue"
},
  "geometry": {"coordinates":[4.5153222084,50.4786262512],"type":"Point"}
}