{
  "type": "Feature",
  "properties": {
    "addr:full":"Kemmelstraat 92 Heuvelland (dranouter) West-Vlaanderen 8951",
    "addr:housenumber":"92",
    "addr:postcode":"8951",
    "addr:street":"Kemmelstraat",
    "iso:country":"BE",
    "sg:address":"Kemmelstraat 92",
    "sg:city":"Heuvelland (dranouter)",
    "sg:classifiers":[
        {
            "category":"Social Services",
            "type":"Services"
        }
    ],
    "sg:phone":"+32 56 41 40 60",
    "sg:postcode":"8951",
    "sg:province":"West-Vlaanderen",
    "wof:name":"'t Smessevier",
    "wof:placetype":"venue"
},
  "geometry": {"coordinates":[2.8306610584,50.7615509033],"type":"Point"}
}