{
  "type": "Feature",
  "properties": {
    "iso:country":"BE",
    "sg:address":"Rue Albert Ier 329",
    "sg:city":"Rixensart",
    "sg:orig_category":"Entretien and r\u00e9parations de voitures",
    "sg:phone":"+32 2 655 05 71",
    "sg:postcode":"1330",
    "sg:province":"Brabant Wallon",
    "wof:name":"Carrosserie Albert Ier",
    "wof:placetype":"venue"
},
  "geometry": {"coordinates":[4.5332751274,50.7153015137],"type":"Point"}
}