{
  "type": "Feature",
  "properties": {
    "iso:country":"BE",
    "sg:address":"Place De La Victoire 13",
    "sg:city":"Estaimpuis",
    "sg:orig_category":"Alimentation sp\u00e9cialis\u00e9e. Restaurants. Restaurants livraison \u00e0 domicile",
    "sg:phone":"+32 56 48 58 38",
    "sg:postcode":"7730",
    "sg:province":"Hainaut",
    "wof:name":"L\u00b4aubergine",
    "wof:placetype":"venue"
},
  "geometry": {"coordinates":[3.2606549263,50.7065048218],"type":"Point"}
}