{
  "type": "Feature",
  "properties": {
    "addr:full":"Grand'rue D'acren 38 Lessines Hainaut 7864",
    "addr:housenumber":"38",
    "addr:postcode":"7864",
    "addr:street":"Grand'Rue D'Acren;Hainaut",
    "iso:country":"BE",
    "sg:address":"Grand'rue D'acren 38",
    "sg:city":"Lessines",
    "sg:classifiers":[
        {
            "category":"Cafe",
            "type":"Food & Drink"
        }
    ],
    "sg:phone":"+32 68 33 20 89",
    "sg:postcode":"7864",
    "sg:province":"Hainaut",
    "sg:tags":[
        "caf\u00e9s"
    ],
    "wof:name":"Sylvie Cerisier",
    "wof:placetype":"venue"
},
  "geometry": {"coordinates":[3.8532040119,50.7295036316],"type":"Point"}
}