{
  "type": "Feature",
  "properties": {
    "addr:full":"Rue Saint-pierre 1bb Aywaille Li\u00e8ge 4920",
    "addr:housenumber":"1bb",
    "addr:postcode":"4920",
    "addr:street":"Rue Saint-Pierre",
    "iso:country":"BE",
    "sg:address":"Rue Saint-pierre 1bb",
    "sg:city":"Aywaille",
    "sg:orig_category":"Diensten voor huisdieren",
    "sg:phone":"+32 495 25 62 90",
    "sg:postcode":"4920",
    "sg:province":"Li\u00e8ge",
    "wof:name":"Doggy Look",
    "wof:placetype":"venue"
},
  "geometry": {"coordinates":[5.6761279106,50.4739952087],"type":"Point"}
}