{
  "type": "Feature",
  "properties": {
    "iso:country":"BE",
    "sg:address":"Rue De La Marsalle 16",
    "sg:city":"Hannut (merdorp)",
    "sg:classifiers":[
        {
            "category":"Recreation",
            "subcategory":"Gun Range",
            "type":"Entertainment"
        }
    ],
    "sg:phone":"+32 81 85 54 55",
    "sg:postcode":"4280",
    "sg:province":"Li\u00e8ge",
    "sg:tags":[
        "ammunition",
        "-",
        "retail"
    ],
    "wof:name":"Louis Tilman Sa",
    "wof:placetype":"venue"
},
  "geometry": {"coordinates":[5.002327919,50.6439666748],"type":"Point"}
}