{
  "type": "Feature",
  "properties": {
    "iso:country":"BE",
    "sg:address":"Rue Des Wallons 252",
    "sg:city":"Li\u00e8ge 1",
    "sg:classifiers":[
        {
            "category":"Health Services",
            "subcategory":"Doctor",
            "type":"Services"
        }
    ],
    "sg:phone":"+32 4 252 16 16",
    "sg:postcode":"4000",
    "sg:province":"Li\u00e8ge",
    "sg:tags":[
        "medicinephysicians",
        "surgeon"
    ],
    "wof:name":"Brixko Christian",
    "wof:placetype":"venue"
},
  "geometry": {"coordinates":[5.5546460152,50.6262550354],"type":"Point"}
}