{
  "type": "Feature",
  "properties": {
    "iso:country":"BE",
    "sg:address":"Rue Blanche Borne 148",
    "sg:city":"Chatelet",
    "sg:orig_category":"Herstellingen and onderhoud van auto's",
    "sg:phone":"+32 71 38 35 32",
    "sg:postcode":"6200",
    "sg:province":"Hainaut",
    "wof:name":"Garage Stancher",
    "wof:placetype":"venue"
},
  "geometry": {"coordinates":[4.4932069778,50.387348175],"type":"Point"}
}