{
  "type": "Feature",
  "properties": {
    "iso:country":"BE",
    "sg:address":"Vaartstraat 79",
    "sg:city":"Leuven",
    "sg:classifiers":[
        {
            "category":"Health Services",
            "subcategory":"Health Practitioner",
            "type":"Services"
        }
    ],
    "sg:phone":"+32 16 22 49 05",
    "sg:postcode":"3000",
    "sg:province":"Vlaams-Brabant",
    "sg:tags":[
        "psychologist"
    ],
    "wof:name":"Morreel S",
    "wof:placetype":"venue"
},
  "geometry": {"coordinates":[4.7007260323,50.8839378357],"type":"Point"}
}