{
  "type": "Feature",
  "properties": {
    "iso:country":"BE",
    "sg:address":"Dendermondsesteenweg",
    "sg:city":"Sint-amandsberg",
    "sg:orig_category":"Ordinateurs and \u00e9quipement informatique",
    "sg:phone":"+32 9 228 28 24",
    "sg:postcode":"9040",
    "sg:province":"Oost-Vlaanderen",
    "wof:name":"Computer Checkpoint",
    "wof:placetype":"venue"
},
  "geometry": {"coordinates":[3.7568340302,51.0517463684],"type":"Point"}
}