{
  "type": "Feature",
  "properties": {
    "iso:country":"BE",
    "sg:address":"Rue Pierre-thomas 6",
    "sg:city":"Bastogne",
    "sg:classifiers":[
        {
            "category":"Building & Trades",
            "subcategory":"Landscaping Services",
            "type":"Services"
        }
    ],
    "sg:phone":"+32 61 21 79 21",
    "sg:postcode":"6600",
    "sg:province":"Luxembourg",
    "sg:tags":[
        "nurseryman"
    ],
    "wof:name":"Savelli Sprl",
    "wof:placetype":"venue"
},
  "geometry": {"coordinates":[5.7216701508,50.0080871582],"type":"Point"}
}