{
  "type": "Feature",
  "properties": {
    "addr:full":"J Reusenlei 30 Borsbeek Antwerpen 2150",
    "addr:housenumber":"30",
    "addr:postcode":"2150",
    "iso:country":"BE",
    "sg:address":"J Reusenlei 30",
    "sg:city":"Borsbeek",
    "sg:orig_category":"V\u00eatements",
    "sg:phone":"+32 3 322 30 98",
    "sg:postcode":"2150",
    "sg:province":"Antwerpen",
    "wof:name":"Calypso Jeans",
    "wof:placetype":"venue"
},
  "geometry": {"coordinates":[4.4883108139,51.1939315796],"type":"Point"}
}