{
  "type": "Feature",
  "properties": {
    "addr:full":"Vosmeer 4 Dendermonde (sint-gillis-bij-dendermonde) Oost-Vlaanderen 9200",
    "addr:housenumber":"4",
    "addr:postcode":"9200",
    "addr:street":"Vosmeer",
    "iso:country":"BE",
    "sg:address":"Vosmeer 4",
    "sg:city":"Dendermonde (sint-gillis-bij-dendermonde)",
    "sg:classifiers":[
        {
            "category":"Manufacturing",
            "subcategory":"Textiles",
            "type":"Manufacturing & Wholesale Goods"
        }
    ],
    "sg:phone":"+32 52 20 04 55",
    "sg:postcode":"9200",
    "sg:province":"Oost-Vlaanderen",
    "sg:tags":[
        "finishing"
    ],
    "wof:name":"Technitex Bvba",
    "wof:placetype":"venue"
},
  "geometry": {"coordinates":[4.1325998306,51.0303001404],"type":"Point"}
}