{
  "type": "Feature",
  "properties": {
    "iso:country":"BE",
    "sg:address":"Place Du March\u00c9 32",
    "sg:city":"Saint-hubert",
    "sg:classifiers":[
        {
            "category":"Cafe",
            "type":"Food & Drink"
        }
    ],
    "sg:phone":"+32 61 61 12 25",
    "sg:postcode":"6870",
    "sg:province":"Luxembourg",
    "sg:tags":[
        "caf\u00e9s"
    ],
    "wof:name":"Caf\u00c9 Le Rimbaud",
    "wof:placetype":"venue"
},
  "geometry": {"coordinates":[5.3735728264,50.0255355835],"type":"Point"}
}