{
  "type": "Feature",
  "properties": {
    "addr:full":"Hengstenberg 6ba Overijse Vlaams-Brabant 3090",
    "addr:housenumber":"6ba",
    "addr:postcode":"3090",
    "addr:street":"Hengstenberg",
    "iso:country":"BE",
    "sg:address":"Hengstenberg 6ba",
    "sg:city":"Overijse",
    "sg:orig_category":"Boucheries",
    "sg:phone":"+32 2 687 90 01",
    "sg:postcode":"3090",
    "sg:province":"Vlaams-Brabant",
    "wof:name":"Lode Desmadryl",
    "wof:placetype":"venue"
},
  "geometry": {"coordinates":[4.5057048798,50.7711486816],"type":"Point"}
}