{
  "type": "Feature",
  "properties": {
    "addr:full":"Gaversesteenweg 575 Merelbeke Oost-Vlaanderen 9820",
    "addr:housenumber":"575",
    "addr:postcode":"9820",
    "addr:street":"Gaversesteenweg",
    "iso:country":"BE",
    "sg:address":"Gaversesteenweg 575",
    "sg:city":"Merelbeke",
    "sg:classifiers":[
        {
            "category":"Professional",
            "subcategory":"Lawyer & Legal Services",
            "type":"Services"
        }
    ],
    "sg:phone":"+32 9 362 93 34",
    "sg:postcode":"9820",
    "sg:province":"Oost-Vlaanderen",
    "wof:name":"Verburgt Marleen",
    "wof:placetype":"venue"
},
  "geometry": {"coordinates":[3.7207129002,50.9749069214],"type":"Point"}
}