{
  "type": "Feature",
  "properties": {
    "iso:country":"BE",
    "sg:address":"Kerkdreef 63",
    "sg:city":"Rijkevorsel",
    "sg:orig_category":"Enseignement maternel and primaire",
    "sg:phone":"+32 3 312 37 33",
    "sg:postcode":"2310",
    "sg:province":"Antwerpen",
    "wof:name":"Vrije Basisschool",
    "wof:placetype":"venue"
},
  "geometry": {"coordinates":[4.7827482224,51.3293037415],"type":"Point"}
}