{
  "type": "Feature",
  "properties": {
    "addr:full":"Rue De La Coupe 14 Mons Hainaut 7000",
    "addr:housenumber":"14",
    "addr:postcode":"7000",
    "addr:street":"Rue De La Coupe;Hainaut",
    "iso:country":"BE",
    "sg:address":"Rue De La Coupe 14",
    "sg:city":"Mons",
    "sg:classifiers":[
        {
            "category":"Shopping",
            "subcategory":"Clothing, Apparel, & Fashions",
            "type":"Retail Goods"
        }
    ],
    "sg:phone":"+32 65 84 88 13",
    "sg:postcode":"7000",
    "sg:province":"Hainaut",
    "sg:tags":[
        "boutique"
    ],
    "wof:name":"Evasion",
    "wof:placetype":"venue"
},
  "geometry": {"coordinates":[3.9519040585,50.4531707764],"type":"Point"}
}