{
  "type": "Feature",
  "properties": {
    "addr:full":"Knaptandstraat 16 Lokeren Oost-Vlaanderen 9160",
    "addr:housenumber":"16",
    "addr:postcode":"9160",
    "addr:street":"Knaptandstraat",
    "iso:country":"BE",
    "sg:address":"Knaptandstraat 16",
    "sg:city":"Lokeren",
    "sg:classifiers":[
        {
            "category":"Community Center",
            "type":"Public Place"
        }
    ],
    "sg:phone":"+32 9 348 37 73",
    "sg:postcode":"9160",
    "sg:province":"Oost-Vlaanderen",
    "sg:tags":[
        "medical"
    ],
    "wof:name":"Waas Revalidatiecentrum",
    "wof:placetype":"venue"
},
  "geometry": {"coordinates":[3.9846510887,51.1003875732],"type":"Point"}
}