{
  "type": "Feature",
  "properties": {
    "iso:country":"BE",
    "sg:address":"Oude Schrieksebaan 34",
    "sg:city":"Bonheiden",
    "sg:classifiers":[
        {
            "category":"Autos & Motor Vehicles",
            "subcategory":"Automobile Sales",
            "type":"Retail Goods"
        }
    ],
    "sg:phone":"+32 15 51 72 90",
    "sg:postcode":"2820",
    "sg:province":"Antwerpen",
    "sg:tags":[
        "motorhomes",
        "accessory"
    ],
    "wof:name":"Lenaerts Motorhomes Op Maat",
    "wof:placetype":"venue"
},
  "geometry": {"coordinates":[4.5856261253,51.0167045593],"type":"Point"}
}