{
  "type": "Feature",
  "properties": {
    "iso:country":"BE",
    "sg:address":"Vaartstraat 44",
    "sg:city":"Wielsbeke",
    "sg:classifiers":[
        {
            "category":"Retail",
            "subcategory":"Auto Repair",
            "type":"Services"
        }
    ],
    "sg:phone":"+32 56 66 51 01",
    "sg:postcode":"8710",
    "sg:province":"West-Vlaanderen",
    "sg:tags":[
        "garage",
        "mainten",
        "-",
        "truck"
    ],
    "wof:name":"Eeckhout-cardoen Bvba",
    "wof:placetype":"venue"
},
  "geometry": {"coordinates":[3.3425900936,50.9005508423],"type":"Point"}
}