{
  "type": "Feature",
  "properties": {
    "iso:country":"BE",
    "sg:address":"Chauss\u00e9e De Dinant 156a",
    "sg:city":"Profondeville (rivi\u00e8re)",
    "sg:classifiers":[
        {
            "category":"Autos & Motor Vehicles",
            "subcategory":"Fuel & Gas Station",
            "type":"Retail Goods"
        }
    ],
    "sg:phone":"+32 81 41 30 20",
    "sg:postcode":"5170",
    "sg:province":"Namur",
    "wof:name":"Texo Station",
    "wof:placetype":"venue"
},
  "geometry": {"coordinates":[4.8709058762,50.359703064],"type":"Point"}
}