{
  "type": "Feature",
  "properties": {
    "addr:full":"Drapstraat 2 Nazareth Oost-Vlaanderen 9810",
    "addr:housenumber":"2",
    "addr:postcode":"9810",
    "addr:street":"Drapstraat",
    "iso:country":"BE",
    "sg:address":"Drapstraat 2",
    "sg:city":"Nazareth",
    "sg:classifiers":[
        {
            "category":"Retail",
            "subcategory":"Auto Rental",
            "type":"Services"
        }
    ],
    "sg:phone":"+32 9 385 84 36",
    "sg:postcode":"9810",
    "sg:province":"Oost-Vlaanderen",
    "sg:tags":[
        "automobile",
        "-",
        "car",
        "self-drive"
    ],
    "wof:name":"Erwin's Renter Center",
    "wof:placetype":"venue"
},
  "geometry": {"coordinates":[3.5980670452,50.9595222473],"type":"Point"}
}