{
  "type": "Feature",
  "properties": {
    "addr:full":"Hoedenmakersstraat 40 Brussel/bruxelles Bruxelles-Capitale 1000",
    "addr:housenumber":"40",
    "addr:postcode":"1000",
    "addr:street":"Hoedenmakersstraat;/",
    "iso:country":"BE",
    "sg:address":"Hoedenmakersstraat 40",
    "sg:city":"Brussel/bruxelles",
    "sg:orig_category":"Brood, gebak and snoepgoed",
    "sg:phone":"+32 2 511 14 91",
    "sg:postcode":"1000",
    "sg:province":"Bruxelles-Capitale",
    "wof:name":"Drag\u00c9es Marchal",
    "wof:placetype":"venue"
},
  "geometry": {"coordinates":[4.3523812294,50.8454360962],"type":"Point"}
}