{
  "type": "Feature",
  "properties": {
    "addr:full":"De Borrekenslei 126 Brasschaat Antwerpen 2930",
    "addr:housenumber":"126",
    "addr:postcode":"2930",
    "iso:country":"BE",
    "sg:address":"De Borrekenslei 126",
    "sg:city":"Brasschaat",
    "sg:classifiers":[
        {
            "category":"Shopping",
            "subcategory":"Crafts & Fabrics",
            "type":"Retail Goods"
        }
    ],
    "sg:phone":"+32 3 651 90 95",
    "sg:postcode":"2930",
    "sg:province":"Antwerpen",
    "sg:tags":[
        "ceramic"
    ],
    "wof:name":"Wouters P",
    "wof:placetype":"venue"
},
  "geometry": {"coordinates":[4.5024580956,51.2935523987],"type":"Point"}
}