{
  "type": "Feature",
  "properties": {
    "iso:country":"BE",
    "sg:address":"Watermolenstraat 61",
    "sg:city":"Sint-niklaas",
    "sg:orig_category":"Architecten",
    "sg:phone":"+32 3 776 27 28",
    "sg:postcode":"9111",
    "sg:province":"Oost-Vlaanderen",
    "wof:name":"Verhaegen T.",
    "wof:placetype":"venue"
},
  "geometry": {"coordinates":[4.1196789742,51.1655960083],"type":"Point"}
}