{
  "type": "Feature",
  "properties": {
    "addr:full":"Boswachtersdreef 42 Kalmthout Antwerpen 2920",
    "addr:housenumber":"42",
    "addr:postcode":"2920",
    "addr:street":"Boswachtersdreef",
    "iso:country":"BE",
    "sg:address":"Boswachtersdreef 42",
    "sg:city":"Kalmthout",
    "sg:orig_category":"Beheer onroerend goed",
    "sg:phone":"+32 3 666 08 21",
    "sg:postcode":"2920",
    "sg:province":"Antwerpen",
    "wof:name":"Bieke",
    "wof:placetype":"venue"
},
  "geometry": {"coordinates":[4.4751439095,51.3605155945],"type":"Point"}
}