{
  "type": "Feature",
  "properties": {
    "iso:country":"BE",
    "sg:address":"Rue De Dour 551",
    "sg:city":"Boussu",
    "sg:classifiers":[
        {
            "category":"Health Services",
            "subcategory":"Health Practitioner",
            "type":"Services"
        }
    ],
    "sg:phone":"+32 65 65 38 28",
    "sg:postcode":"7300",
    "sg:province":"Hainaut",
    "sg:tags":[
        "physiotherapist"
    ],
    "wof:name":"Limmelette Ph",
    "wof:placetype":"venue"
},
  "geometry": {"coordinates":[3.7864499092,50.4198112488],"type":"Point"}
}