{
  "type": "Feature",
  "properties": {
    "addr:full":"Grand-rue 7 Manhay Luxembourg 6960",
    "addr:housenumber":"7",
    "addr:postcode":"6960",
    "addr:street":"Grand-Rue",
    "iso:country":"BE",
    "sg:address":"Grand-rue 7",
    "sg:city":"Manhay",
    "sg:orig_category":"Offices du tourisme",
    "sg:phone":"+32 86 45 56 67",
    "sg:postcode":"6960",
    "sg:province":"Luxembourg",
    "wof:name":"Syndicat D'initiative",
    "wof:placetype":"venue"
},
  "geometry": {"coordinates":[5.6570448875,50.2902412415],"type":"Point"}
}