{
  "type": "Feature",
  "properties": {
    "addr:full":"Rue Du Pont 75 Wandre Li\u00e8ge 4520",
    "addr:housenumber":"75",
    "addr:postcode":"4520",
    "addr:street":"Rue Du Pont",
    "iso:country":"BE",
    "sg:address":"Rue Du Pont 75",
    "sg:city":"Wandre",
    "sg:classifiers":[
        {
            "category":"Banks & Credit Unions",
            "subcategory":"Bank",
            "type":"Services"
        }
    ],
    "sg:phone":"+32 41624141",
    "sg:postcode":"4520",
    "sg:province":"Li\u00e8ge",
    "wof:name":"Aslk-cger Bank",
    "wof:placetype":"venue"
},
  "geometry": {"coordinates":[-8.5712966919,40.8876342773],"type":"Point"}
}