{
  "type": "Feature",
  "properties": {
    "iso:country":"BE",
    "sg:address":"Grepstraat 4",
    "sg:city":"Merelbeke",
    "sg:orig_category":"Brood, gebak and snoepgoed",
    "sg:phone":"+32 9 362 70 42",
    "sg:postcode":"9820",
    "sg:province":"Oost-Vlaanderen",
    "wof:name":"Yves Schepens",
    "wof:placetype":"venue"
},
  "geometry": {"coordinates":[3.715542078,50.9700088501],"type":"Point"}
}