{
  "type": "Feature",
  "properties": {
    "addr:full":"Jan Blockxlaan 75 Aartselaar Antwerpen 2630",
    "addr:housenumber":"75",
    "addr:postcode":"2630",
    "addr:street":"Jan Blockxlaan",
    "iso:country":"BE",
    "sg:address":"Jan Blockxlaan 75",
    "sg:city":"Aartselaar",
    "sg:orig_category":"Diverse organisaties and verenigingen",
    "sg:phone":"+32 3 844 30 86",
    "sg:postcode":"2630",
    "sg:province":"Antwerpen",
    "wof:name":"Chiro Jerubo",
    "wof:placetype":"venue"
},
  "geometry": {"coordinates":[4.3691539764,51.1114654541],"type":"Point"}
}