{
  "type": "Feature",
  "properties": {
    "iso:country":"BE",
    "sg:address":"Brugstraat 67",
    "sg:city":"Aalter",
    "sg:orig_category":"Elektrische huishoudapparaten, radio and televisie Gh HERSTELLING ELEKTRISCHE HUISHOUDAPPARATEN Huis",
    "sg:phone":"+32 9 374 33 32",
    "sg:postcode":"9880",
    "sg:province":"Oost-Vlaanderen",
    "wof:name":"Huys",
    "wof:placetype":"venue"
},
  "geometry": {"coordinates":[3.4464490414,51.0914573669],"type":"Point"}
}