{
  "type": "Feature",
  "properties": {
    "iso:country":"BE",
    "sg:address":"Doornhut 11",
    "sg:city":"Brugge (sint-kruis)",
    "sg:classifiers":[
        {
            "category":"Health Services",
            "subcategory":"Dentist",
            "type":"Services"
        }
    ],
    "sg:phone":"+32 50 35 01 00",
    "sg:postcode":"8310",
    "sg:province":"West-Vlaanderen",
    "wof:name":"Geers Vera",
    "wof:placetype":"venue"
},
  "geometry": {"coordinates":[3.2652230263,51.2132530212],"type":"Point"}
}