{
  "type": "Feature",
  "properties": {
    "addr:full":"Halleweg 294 Halle Vlaams-Brabant 1500",
    "addr:housenumber":"294",
    "addr:postcode":"1500",
    "addr:street":"Halleweg",
    "iso:country":"BE",
    "sg:address":"Halleweg 294",
    "sg:city":"Halle",
    "sg:orig_category":"Fa\u00e7ade covering",
    "sg:phone":"+32 2 356 24 14",
    "sg:postcode":"1500",
    "sg:province":"Vlaams-Brabant",
    "wof:name":"Schoonheydt",
    "wof:placetype":"venue"
},
  "geometry": {"coordinates":[4.2524371147,50.72423172],"type":"Point"}
}