{
  "type": "Feature",
  "properties": {
    "addr:full":"Nieuwpoortsteenweg 310 Koksijde (oostduinkerke) West-Vlaanderen 8670",
    "addr:housenumber":"310",
    "addr:postcode":"8670",
    "addr:street":"Nieuwpoortsteenweg",
    "iso:country":"BE",
    "sg:address":"Nieuwpoortsteenweg 310",
    "sg:city":"Koksijde (oostduinkerke)",
    "sg:classifiers":[
        {
            "category":"Professional",
            "subcategory":"Art Services",
            "type":"Services"
        }
    ],
    "sg:phone":"+32 58 23 88 44",
    "sg:postcode":"8670",
    "sg:province":"West-Vlaanderen",
    "sg:tags":[
        "graphic",
        "designer"
    ],
    "wof:name":"Soreyn R",
    "wof:placetype":"venue"
},
  "geometry": {"coordinates":[2.7317569256,51.1289787292],"type":"Point"}
}