{
  "type": "Feature",
  "properties": {
    "addr:full":"Kerkstraat 46 Beveren (vrasene) Oost-Vlaanderen 9120",
    "addr:housenumber":"46",
    "addr:postcode":"9120",
    "addr:street":"Kerkstraat",
    "iso:country":"BE",
    "sg:address":"Kerkstraat 46",
    "sg:city":"Beveren (vrasene)",
    "sg:classifiers":[
        {
            "category":"Real Estate",
            "subcategory":"Architect",
            "type":"Services"
        }
    ],
    "sg:phone":"+32 3 775 44 39",
    "sg:postcode":"9120",
    "sg:province":"Oost-Vlaanderen",
    "wof:name":"Hofman P",
    "wof:placetype":"venue"
},
  "geometry": {"coordinates":[4.1953001022,51.2184906006],"type":"Point"}
}