{
  "type": "Feature",
  "properties": {
    "iso:country":"BE",
    "sg:address":"Heirbaan 127",
    "sg:city":"Zwijndrecht",
    "sg:orig_category":"Boucheries",
    "sg:phone":"+32 3 252 72 81",
    "sg:postcode":"2070",
    "sg:province":"Antwerpen",
    "wof:name":"Dirk Rusch",
    "wof:placetype":"venue"
},
  "geometry": {"coordinates":[4.3341259956,51.2001533508],"type":"Point"}
}