{
  "type": "Feature",
  "properties": {
    "iso:country":"BE",
    "sg:address":"Rue Stevens-delannoy 119",
    "sg:city":"Brussel/bruxelles",
    "sg:orig_category":"Entretien and r\u00e9parations de voitures",
    "sg:phone":"+32 2 476 07 19",
    "sg:postcode":"1020",
    "sg:province":"Bruxelles-Capitale",
    "wof:name":"Garage Lahoucine",
    "wof:placetype":"venue"
},
  "geometry": {"coordinates":[4.3415379524,50.8904457092],"type":"Point"}
}