{
  "type": "Feature",
  "properties": {
    "addr:full":"Strijdersstraat 34 Edegem Antwerpen 2650",
    "addr:housenumber":"34",
    "addr:postcode":"2650",
    "addr:street":"Strijdersstraat",
    "iso:country":"BE",
    "sg:address":"Strijdersstraat 34",
    "sg:city":"Edegem",
    "sg:classifiers":[
        {
            "category":"Building & Trades",
            "subcategory":"Equipment Rental",
            "type":"Services"
        }
    ],
    "sg:phone":"+32 3 458 36 22",
    "sg:postcode":"2650",
    "sg:province":"Antwerpen",
    "sg:tags":[
        "safety",
        "collective",
        "individual",
        "-"
    ],
    "wof:name":"Schellekens Optiek",
    "wof:placetype":"venue"
},
  "geometry": {"coordinates":[4.4439558983,51.1573181152],"type":"Point"}
}