{
  "type": "Feature",
  "properties": {
    "addr:full":"Stationsstraat 87 Ledegem West-Vlaanderen 8880",
    "addr:housenumber":"87",
    "addr:postcode":"8880",
    "addr:street":"Stationsstraat",
    "iso:country":"BE",
    "sg:address":"Stationsstraat 87",
    "sg:city":"Ledegem",
    "sg:classifiers":[
        {
            "category":"Personal",
            "subcategory":"Beauty Salon",
            "type":"Services"
        }
    ],
    "sg:phone":"+32 56 50 98 85",
    "sg:postcode":"8880",
    "sg:province":"West-Vlaanderen",
    "sg:tags":[
        "lady",
        "-",
        "hairdressing"
    ],
    "wof:name":"Masschelein",
    "wof:placetype":"venue"
},
  "geometry": {"coordinates":[3.1224529743,50.8569221497],"type":"Point"}
}