{
  "type": "Feature",
  "properties": {
    "addr:full":"Halmaalweg 78 Sint-truiden Limburg 3800",
    "addr:housenumber":"78",
    "addr:postcode":"3800",
    "addr:street":"Halmaalweg",
    "iso:country":"BE",
    "sg:address":"Halmaalweg 78",
    "sg:city":"Sint-truiden",
    "sg:orig_category":"Brood, gebak and snoepgoed",
    "sg:phone":"+32 11 67 21 40",
    "sg:postcode":"3800",
    "sg:province":"Limburg",
    "wof:name":"Bakkerij An",
    "wof:placetype":"venue"
},
  "geometry": {"coordinates":[5.1691641808,50.8115577698],"type":"Point"}
}