{
  "type": "Feature",
  "properties": {
    "addr:full":"Rapenbrugstraat 1 Maldegem Oost-Vlaanderen 9990",
    "addr:housenumber":"1",
    "addr:postcode":"9990",
    "addr:street":"Rapenbrugstraat",
    "iso:country":"BE",
    "sg:address":"Rapenbrugstraat 1",
    "sg:city":"Maldegem",
    "sg:orig_category":"Jardinage",
    "sg:phone":"+32 50 71 61 10",
    "sg:postcode":"9990",
    "sg:province":"Oost-Vlaanderen",
    "wof:name":"Dutoict",
    "wof:placetype":"venue"
},
  "geometry": {"coordinates":[3.4473950863,51.2179756165],"type":"Point"}
}