{
  "type": "Feature",
  "properties": {
    "addr:full":"Brusselsepoortstraat 26 Mechelen Antwerpen 2800",
    "addr:housenumber":"26",
    "addr:postcode":"2800",
    "addr:street":"Brusselsepoortstraat",
    "iso:country":"BE",
    "sg:address":"Brusselsepoortstraat 26",
    "sg:city":"Mechelen",
    "sg:orig_category":"Avocats and conseillers juridiques",
    "sg:phone":"+32 15 41 38 29",
    "sg:postcode":"2800",
    "sg:province":"Antwerpen",
    "wof:name":"M. Van Battel",
    "wof:placetype":"venue"
},
  "geometry": {"coordinates":[4.4723348618,51.0214538574],"type":"Point"}
}