{
  "type": "Feature",
  "properties": {
    "addr:full":"Rue Du Presbytere 14 Houyet Namur 5562",
    "addr:housenumber":"14",
    "addr:postcode":"5562",
    "addr:street":"Rue Du Presbytere",
    "iso:country":"BE",
    "sg:address":"Rue Du Presbytere 14",
    "sg:city":"Houyet",
    "sg:orig_category":"Jardinage",
    "sg:phone":"+32 82 66 77 54",
    "sg:postcode":"5562",
    "sg:province":"Namur",
    "wof:name":"Stephane Mouchet",
    "wof:placetype":"venue"
},
  "geometry": {"coordinates":[5.0506510735,50.2102928162],"type":"Point"}
}