{
  "type": "Feature",
  "properties": {
    "iso:country":"BE",
    "sg:address":"Oude Brugstraat 4",
    "sg:city":"Dendermonde",
    "sg:orig_category":"Treinen and spoorwegen",
    "sg:phone":"+32 52 42 31 42",
    "sg:postcode":"9200",
    "sg:province":"Oost-Vlaanderen",
    "wof:name":"Station Schoonaarde",
    "wof:placetype":"venue"
},
  "geometry": {"coordinates":[4.0112681389,51.0040359497],"type":"Point"}
}