{
  "type": "Feature",
  "properties": {
    "addr:full":"Nieuwstraat 96 Wevelgem West-Vlaanderen 8560",
    "addr:housenumber":"96",
    "addr:postcode":"8560",
    "addr:street":"Nieuwstraat",
    "iso:country":"BE",
    "sg:address":"Nieuwstraat 96",
    "sg:city":"Wevelgem",
    "sg:orig_category":"Immobili\u00ebnkantoren",
    "sg:phone":"+32 56 41 28 02",
    "sg:postcode":"8560",
    "sg:province":"West-Vlaanderen",
    "wof:name":"Remos",
    "wof:placetype":"venue"
},
  "geometry": {"coordinates":[3.1754090786,50.8111572266],"type":"Point"}
}