{
  "type": "Feature",
  "properties": {
    "addr:full":"Eikenenpad 40 Zonhoven Limburg 3520",
    "addr:housenumber":"40",
    "addr:postcode":"3520",
    "addr:street":"Eikenenpad",
    "iso:country":"BE",
    "sg:address":"Eikenenpad 40",
    "sg:city":"Zonhoven",
    "sg:classifiers":[
        {
            "category":"Banks & Credit Unions",
            "subcategory":"Investment Brokerage",
            "type":"Services"
        }
    ],
    "sg:phone":"+32 11 82 35 65",
    "sg:postcode":"3520",
    "sg:province":"Limburg",
    "sg:tags":[
        "printing",
        "-"
    ],
    "wof:name":"Vanderheyden J",
    "wof:placetype":"venue"
},
  "geometry": {"coordinates":[5.3660979271,50.9979705811],"type":"Point"}
}