{
  "type": "Feature",
  "properties": {
    "iso:country":"BE",
    "sg:address":"Rue Du Puits Communal 114",
    "sg:city":"Farciennes",
    "sg:orig_category":"Technisch and beroeps secundair onderwijs",
    "sg:phone":"+32 71 38 40 54",
    "sg:postcode":"6240",
    "sg:province":"Hainaut",
    "wof:name":"I.p.e.t.p.",
    "wof:placetype":"venue"
},
  "geometry": {"coordinates":[4.5435948372,50.4290771484],"type":"Point"}
}