{
  "type": "Feature",
  "properties": {
    "addr:full":"Rue De Durbuy 9 Hotton Luxembourg 6990",
    "addr:housenumber":"9",
    "addr:postcode":"6990",
    "addr:street":"Rue De Durbuy",
    "iso:country":"BE",
    "sg:address":"Rue De Durbuy 9",
    "sg:city":"Hotton",
    "sg:classifiers":[
        {
            "category":"Health Services",
            "subcategory":"Health Practitioner",
            "type":"Services"
        }
    ],
    "sg:phone":"+32 476 26 67 48",
    "sg:postcode":"6990",
    "sg:province":"Luxembourg",
    "sg:tags":[
        "physiotherapist"
    ],
    "wof:name":"Du Bois Nathalie",
    "wof:placetype":"venue"
},
  "geometry": {"coordinates":[5.4356498718,50.2995681763],"type":"Point"}
}