{
  "type": "Feature",
  "properties": {
    "addr:full":"Place D'hanzinne 122a Florennes (hanzinne) Namur 5621",
    "addr:housenumber":"122a",
    "addr:postcode":"5621",
    "addr:street":"Place D'Hanzinne",
    "iso:country":"BE",
    "sg:address":"Place D'hanzinne 122a",
    "sg:city":"Florennes (hanzinne)",
    "sg:classifiers":[
        {
            "category":"Health Services",
            "subcategory":"Nursing And Care Facility",
            "type":"Services"
        }
    ],
    "sg:phone":"+32 71 50 47 81",
    "sg:postcode":"5621",
    "sg:province":"Namur",
    "sg:tags":[
        "home",
        "rest"
    ],
    "wof:name":"Residence La Grange",
    "wof:placetype":"venue"
},
  "geometry": {"coordinates":[4.5413198471,50.3093185425],"type":"Point"}
}