{
  "type": "Feature",
  "properties": {
    "addr:full":"Guido Gezellelaan 6 Mechelen Antwerpen 2800",
    "addr:housenumber":"6",
    "addr:postcode":"2800",
    "addr:street":"Guido Gezellelaan",
    "iso:country":"BE",
    "sg:address":"Guido Gezellelaan 6",
    "sg:city":"Mechelen",
    "sg:classifiers":[
        {
            "category":"Shopping",
            "subcategory":"Hobbies, Toys, & Games",
            "type":"Retail Goods"
        }
    ],
    "sg:phone":"+32 15 27 73 70",
    "sg:postcode":"2800",
    "sg:province":"Antwerpen",
    "sg:tags":[
        "computer",
        "video"
    ],
    "wof:name":"Golden Games",
    "wof:placetype":"venue"
},
  "geometry": {"coordinates":[4.4721550941,51.0322227478],"type":"Point"}
}