{
  "type": "Feature",
  "properties": {
    "iso:country":"BE",
    "sg:address":"Rue Petit-bertrand 49",
    "sg:city":"Oupeye",
    "sg:orig_category":"Sportclubs",
    "sg:phone":"+32 4 379 69 64",
    "sg:postcode":"4681",
    "sg:province":"Li\u00e8ge",
    "wof:name":"V.c. Sporting Hermalle",
    "wof:placetype":"venue"
},
  "geometry": {"coordinates":[5.6811299324,50.7161369324],"type":"Point"}
}