{
  "type": "Feature",
  "properties": {
    "iso:country":"BE",
    "sg:address":"Polbroeck 44-46",
    "sg:city":"Sint-lievens-houtem",
    "sg:orig_category":"Herstellingen and onderhoud van auto's Voertuigen",
    "sg:phone":"+32 53 62 22 64",
    "sg:postcode":"9520",
    "sg:province":"Oost-Vlaanderen",
    "wof:name":"Iveco Billiet",
    "wof:placetype":"venue"
},
  "geometry": {"coordinates":[3.852658987,50.9181518555],"type":"Point"}
}