{
  "type": "Feature",
  "properties": {
    "addr:full":"Chauss\u00c9e De Tirlemont Saint-jean-geest Brabant Wallon 1370",
    "addr:postcode":"1370",
    "addr:street":"Chausse\u0301E De Tirlemont;Wallon",
    "iso:country":"BE",
    "sg:address":"Chauss\u00c9e De Tirlemont",
    "sg:city":"Saint-jean-geest",
    "sg:orig_category":"Herstellingen and onderhoud van auto's Huisdieren and benodigdheden Royal Canin",
    "sg:phone":"+32 10 81 12 85",
    "sg:postcode":"1370",
    "sg:province":"Brabant Wallon",
    "wof:name":"Ets Dusart & Fils",
    "wof:placetype":"venue"
},
  "geometry": {"coordinates":[4.8806648254,50.7375030518],"type":"Point"}
}