{
  "type": "Feature",
  "properties": {
    "addr:full":"Brugse Mettenstraat 7 Brugge (sint-kruis) West-Vlaanderen 8310",
    "addr:housenumber":"7",
    "addr:postcode":"8310",
    "addr:street":"Brugse Mettenstraat",
    "iso:country":"BE",
    "sg:address":"Brugse Mettenstraat 7",
    "sg:city":"Brugge (sint-kruis)",
    "sg:classifiers":[
        {
            "category":"Shopping",
            "subcategory":"Clothing, Apparel, & Fashions",
            "type":"Retail Goods"
        }
    ],
    "sg:phone":"+32 50 35 08 13",
    "sg:postcode":"8310",
    "sg:province":"West-Vlaanderen",
    "sg:tags":[
        "lady",
        "clothing",
        "-"
    ],
    "wof:name":"Annie Laurie Of Scotland Bvba",
    "wof:placetype":"venue"
},
  "geometry": {"coordinates":[3.2434489727,51.2132644653],"type":"Point"}
}