{
  "type": "Feature",
  "properties": {
    "iso:country":"BE",
    "sg:address":"Maisstraat 4",
    "sg:city":"Gent",
    "sg:orig_category":"Pharmaciens",
    "sg:phone":"+32 9 226 13 82",
    "sg:postcode":"9000",
    "sg:province":"Oost-Vlaanderen",
    "wof:name":"Apoth.vansumere-de Preter",
    "wof:placetype":"venue"
},
  "geometry": {"coordinates":[3.7083148956,51.0681266785],"type":"Point"}
}