{
  "type": "Feature",
  "properties": {
    "iso:country":"BE",
    "sg:address":"Rodeland 22",
    "sg:city":"Wommelgem",
    "sg:orig_category":"Beheer onroerend goed",
    "sg:phone":"+32 3 322 30 00",
    "sg:postcode":"2160",
    "sg:province":"Antwerpen",
    "wof:name":"Investigation & Trad. Cy",
    "wof:placetype":"venue"
},
  "geometry": {"coordinates":[4.5010018349,51.1936264038],"type":"Point"}
}