{
  "type": "Feature",
  "properties": {
    "iso:country":"BE",
    "sg:address":"Rue De La Halle 14",
    "sg:city":"Namur",
    "sg:classifiers":[
        {
            "category":"Bakery",
            "type":"Food & Drink"
        }
    ],
    "sg:phone":"+32 81 22 30 31",
    "sg:postcode":"5000",
    "sg:province":"Namur",
    "sg:tags":[
        "confectioner",
        "baker"
    ],
    "wof:name":"Allard J-m",
    "wof:placetype":"venue"
},
  "geometry": {"coordinates":[4.8652629852,50.4627304077],"type":"Point"}
}