{
  "type": "Feature",
  "properties": {
    "iso:country":"BE",
    "sg:address":"Daknam Dorp 24",
    "sg:city":"Lokeren (daknam)",
    "sg:classifiers":[
        {
            "category":"Bakery",
            "type":"Food & Drink"
        }
    ],
    "sg:phone":"+32 9 348 31 11",
    "sg:postcode":"9160",
    "sg:province":"Oost-Vlaanderen",
    "sg:tags":[
        "confectioner",
        "baker"
    ],
    "wof:name":"Van Mieghem L",
    "wof:placetype":"venue"
},
  "geometry": {"coordinates":[3.9869589806,51.1131324768],"type":"Point"}
}