{
  "type": "Feature",
  "properties": {
    "iso:country":"BE",
    "sg:address":"Rue De Pintamont 2",
    "sg:city":"Ath",
    "sg:classifiers":[
        {
            "category":"Professional",
            "subcategory":"Testing Lab",
            "type":"Services"
        }
    ],
    "sg:phone":"+32 68 28 31 51",
    "sg:postcode":"7800",
    "sg:province":"Hainaut",
    "sg:tags":[
        "chemist"
    ],
    "wof:name":"Pharmacie Saint-julien",
    "wof:placetype":"venue"
},
  "geometry": {"coordinates":[3.7749400139,50.6290817261],"type":"Point"}
}