{
  "type": "Feature",
  "properties": {
    "addr:full":"Sint-reinhildisstraat 15bb Mortsel Antwerpen 2640",
    "addr:housenumber":"15bb",
    "addr:postcode":"2640",
    "addr:street":"Sint-Reinhildisstraat",
    "iso:country":"BE",
    "sg:address":"Sint-reinhildisstraat 15bb",
    "sg:city":"Mortsel",
    "sg:orig_category":"Enseignement maternel and primaire",
    "sg:phone":"+32 3 449 56 39",
    "sg:postcode":"2640",
    "sg:province":"Antwerpen",
    "wof:name":"Vrije Basisschool",
    "wof:placetype":"venue"
},
  "geometry": {"coordinates":[4.454018116,51.1801261902],"type":"Point"}
}