{
  "type": "Feature",
  "properties": {
    "iso:country":"BE",
    "sg:address":"Dorpstraat 41",
    "sg:city":"Mechelen (leest)",
    "sg:classifiers":[
        {
            "category":"Organizations",
            "subcategory":"Professional Association",
            "type":"Services"
        }
    ],
    "sg:phone":"+32 15 27 75 24",
    "sg:postcode":"2811",
    "sg:province":"Antwerpen",
    "sg:tags":[
        "trade-union",
        "federation"
    ],
    "wof:name":"Beroepsver Apotekers Mechelen",
    "wof:placetype":"venue"
},
  "geometry": {"coordinates":[4.4142508507,51.0310974121],"type":"Point"}
}