{
  "type": "Feature",
  "properties": {
    "iso:country":"BE",
    "sg:address":"Kasteelstraat 33",
    "sg:city":"Wervik",
    "sg:classifiers":[
        {
            "category":"Insurance",
            "subcategory":"Insurance Agent",
            "type":"Services"
        }
    ],
    "sg:phone":"+32 56 31 16 97",
    "sg:postcode":"8940",
    "sg:province":"West-Vlaanderen",
    "sg:tags":[
        "broker"
    ],
    "wof:name":"Vleirick W",
    "wof:placetype":"venue"
},
  "geometry": {"coordinates":[3.0371229649,50.7783546448],"type":"Point"}
}