{
  "type": "Feature",
  "properties": {
    "addr:full":"Mispelweg 44ba Willebroek Antwerpen 2830",
    "addr:housenumber":"44ba",
    "addr:postcode":"2830",
    "addr:street":"Mispelweg",
    "iso:country":"BE",
    "sg:address":"Mispelweg 44ba",
    "sg:city":"Willebroek",
    "sg:orig_category":"Entretien and r\u00e9parations de voitures",
    "sg:phone":"+32 3 886 75 95",
    "sg:postcode":"2830",
    "sg:province":"Antwerpen",
    "wof:name":"Henri Foque",
    "wof:placetype":"venue"
},
  "geometry": {"coordinates":[4.3564991951,51.0495414734],"type":"Point"}
}