{
  "type": "Feature",
  "properties": {
    "iso:country":"BE",
    "sg:address":"Marktplein 17ba",
    "sg:city":"Sint-lievens-houtem",
    "sg:classifiers":[
        {
            "category":"Insurance",
            "subcategory":"Insurance Agent",
            "type":"Services"
        }
    ],
    "sg:phone":"+32 53 63 02 48",
    "sg:postcode":"9520",
    "sg:province":"Oost-Vlaanderen",
    "sg:tags":[
        "verzekeringsmakelaars",
        "expert"
    ],
    "wof:name":"K. Van Puyvelde",
    "wof:placetype":"venue"
},
  "geometry": {"coordinates":[3.8576009274,50.9200897217],"type":"Point"}
}