{
  "type": "Feature",
  "properties": {
    "addr:full":"Beekweg 1 Tongeren Limburg 3700",
    "addr:housenumber":"1",
    "addr:postcode":"3700",
    "addr:street":"Beekweg",
    "iso:country":"BE",
    "sg:address":"Beekweg 1",
    "sg:city":"Tongeren",
    "sg:classifiers":[
        {
            "category":"Shopping",
            "subcategory":"Shoes",
            "type":"Retail Goods"
        }
    ],
    "sg:phone":"+32 12 23 31 43",
    "sg:postcode":"3700",
    "sg:province":"Limburg",
    "sg:tags":[
        "slipper",
        "-"
    ],
    "wof:name":"Descarto",
    "wof:placetype":"venue"
},
  "geometry": {"coordinates":[5.4782271385,50.7676124573],"type":"Point"}
}