{
  "type": "Feature",
  "properties": {
    "addr:full":"Albrechtlaan 13 Aalst Oost-Vlaanderen 9300",
    "addr:housenumber":"13",
    "addr:postcode":"9300",
    "addr:street":"Albrechtlaan",
    "iso:country":"BE",
    "sg:address":"Albrechtlaan 13",
    "sg:city":"Aalst",
    "sg:orig_category":"Installation de menuiserie en bois and plastique",
    "sg:phone":"+32 53 77 49 15",
    "sg:postcode":"9300",
    "sg:province":"Oost-Vlaanderen",
    "wof:name":"Fragil",
    "wof:placetype":"venue"
},
  "geometry": {"coordinates":[4.0551280975,50.934551239],"type":"Point"}
}