{
  "type": "Feature",
  "properties": {
    "iso:country":"BE",
    "sg:address":"Kamerijkstraat 35",
    "sg:city":"Gent",
    "sg:orig_category":"D\u00e9corateurs d'int\u00e9rieur",
    "sg:phone":"+32 9 251 66 28",
    "sg:postcode":"9041",
    "sg:province":"Oost-Vlaanderen",
    "wof:name":"Myriam Spelier",
    "wof:placetype":"venue"
},
  "geometry": {"coordinates":[3.7809200287,51.0989074707],"type":"Point"}
}