{
  "type": "Feature",
  "properties": {
    "addr:full":"Rue Ariste Caussin 83 Dinant Namur 5500",
    "addr:housenumber":"83",
    "addr:postcode":"5500",
    "addr:street":"Rue Ariste Caussin",
    "iso:country":"BE",
    "sg:address":"Rue Ariste Caussin 83",
    "sg:city":"Dinant",
    "sg:classifiers":[
        {
            "category":"Professional",
            "subcategory":"Testing Lab",
            "type":"Services"
        }
    ],
    "sg:phone":"+32 82 22 28 55",
    "sg:postcode":"5500",
    "sg:province":"Namur",
    "sg:tags":[
        "chemist"
    ],
    "wof:name":"Molle A",
    "wof:placetype":"venue"
},
  "geometry": {"coordinates":[4.9152369499,50.239025116],"type":"Point"}
}