{
  "type": "Feature",
  "properties": {
    "addr:full":"Duinenweg 9 Lille (wechelderzande) Antwerpen 2275",
    "addr:housenumber":"9",
    "addr:postcode":"2275",
    "addr:street":"Duinenweg",
    "iso:country":"BE",
    "sg:address":"Duinenweg 9",
    "sg:city":"Lille (wechelderzande)",
    "sg:classifiers":[
        {
            "category":"Wholesale",
            "subcategory":"Painting Supplies",
            "type":"Manufacturing & Wholesale Goods"
        }
    ],
    "sg:phone":"+32 3 312 54 51",
    "sg:postcode":"2275",
    "sg:province":"Antwerpen",
    "sg:tags":[
        "industrial",
        "-"
    ],
    "wof:name":"Aswek Bvba",
    "wof:placetype":"venue"
},
  "geometry": {"coordinates":[4.7973017693,51.2786102295],"type":"Point"}
}