{
  "type": "Feature",
  "properties": {
    "iso:country":"BE",
    "sg:address":"Leon Gilliotlaan 49",
    "sg:city":"Aartselaar",
    "sg:orig_category":"Artsen and specialisten",
    "sg:phone":"+32 3 887 08 20",
    "sg:postcode":"2630",
    "sg:province":"Antwerpen",
    "wof:name":"Ph. Saucez",
    "wof:placetype":"venue"
},
  "geometry": {"coordinates":[4.386742115,51.1310501099],"type":"Point"}
}