{
  "type": "Feature",
  "properties": {
    "iso:country":"BE",
    "sg:address":"Berenbroekstraat 93",
    "sg:city":"Genk",
    "sg:orig_category":"Woningbouw",
    "sg:phone":"+32 11 23 27 68",
    "sg:postcode":"3600",
    "sg:province":"Limburg",
    "wof:name":"Jacobus Jaeken",
    "wof:placetype":"venue"
},
  "geometry": {"coordinates":[5.4136219025,50.9485855103],"type":"Point"}
}