{
  "type": "Feature",
  "properties": {
    "addr:full":"Gentstraat 15 Bredene West-Vlaanderen 8450",
    "addr:housenumber":"15",
    "addr:postcode":"8450",
    "addr:street":"Gentstraat",
    "iso:country":"BE",
    "sg:address":"Gentstraat 15",
    "sg:city":"Bredene",
    "sg:orig_category":"Action sociale avec h\u00e9bergement",
    "sg:phone":"+32 59 33 24 72",
    "sg:postcode":"8450",
    "sg:province":"West-Vlaanderen",
    "wof:name":"De Brugge",
    "wof:placetype":"venue"
},
  "geometry": {"coordinates":[2.9634110928,51.2477035522],"type":"Point"}
}