{
  "type": "Feature",
  "properties": {
    "iso:country":"BE",
    "sg:address":"'t Nachtegaaltje 3",
    "sg:city":"Diksmuide",
    "sg:orig_category":"Rundveehouders Varkenskwekers",
    "sg:phone":"+32 51 50 14 08",
    "sg:postcode":"8600",
    "sg:province":"West-Vlaanderen",
    "wof:name":"Luc Houthoofd",
    "wof:placetype":"venue"
},
  "geometry": {"coordinates":[2.9162750244,51.0862083435],"type":"Point"}
}