{
  "type": "Feature",
  "properties": {
    "addr:full":"Kelfsstraat 73 Haacht Vlaams-Brabant 3150",
    "addr:housenumber":"73",
    "addr:postcode":"3150",
    "addr:street":"Kelfsstraat",
    "iso:country":"BE",
    "sg:address":"Kelfsstraat 73",
    "sg:city":"Haacht",
    "sg:orig_category":"Pain, p\u00e2tisseries and confiseries",
    "sg:phone":"+32 16 60 44 59",
    "sg:postcode":"3150",
    "sg:province":"Vlaams-Brabant",
    "wof:name":"Bakkerij Van Haacht",
    "wof:placetype":"venue"
},
  "geometry": {"coordinates":[4.6811108589,50.9496765137],"type":"Point"}
}