{
  "type": "Feature",
  "properties": {
    "iso:country":"BE",
    "sg:address":"Avenue Reine Astrid 29",
    "sg:city":"Huy",
    "sg:orig_category":"Herstelling and restauratie van meubelen Meubelzaken, woning- and keukeninrichting",
    "sg:phone":"+32 85 21 20 95",
    "sg:postcode":"4500",
    "sg:province":"Li\u00e8ge",
    "wof:name":"Fe. Degee",
    "wof:placetype":"venue"
},
  "geometry": {"coordinates":[5.2273898125,50.5256233215],"type":"Point"}
}