{
  "type": "Feature",
  "properties": {
    "addr:full":"Boulevard De L'eglise 32 Antoing Hainaut 7640",
    "addr:housenumber":"32",
    "addr:postcode":"7640",
    "addr:street":"Boulevard De L'Eglise",
    "iso:country":"BE",
    "sg:address":"Boulevard De L'eglise 32",
    "sg:city":"Antoing",
    "sg:classifiers":[
        {
            "category":"Health Services",
            "subcategory":"Doctor",
            "type":"Services"
        }
    ],
    "sg:phone":"+32 69 44 27 04",
    "sg:postcode":"7640",
    "sg:province":"Hainaut",
    "sg:tags":[
        "medicinephysicians",
        "surgeon"
    ],
    "wof:name":"Li\u00e8tar",
    "wof:placetype":"venue"
},
  "geometry": {"coordinates":[3.449903965,50.5679016113],"type":"Point"}
}