{
  "type": "Feature",
  "properties": {
    "iso:country":"BE",
    "sg:address":"Rijselsestraat 108",
    "sg:city":"Ieper",
    "sg:orig_category":"Industri\u00eble wasserijen and droogkuis Wasserijen, Reiniging and Droogkuis",
    "sg:phone":"+32 57 20 04 40",
    "sg:postcode":"8900",
    "sg:province":"West-Vlaanderen",
    "wof:name":"De Zon",
    "wof:placetype":"venue"
},
  "geometry": {"coordinates":[2.888215065,50.8472709656],"type":"Point"}
}