{
  "type": "Feature",
  "properties": {
    "iso:country":"BE",
    "sg:address":"Pelkemstr 14",
    "sg:city":"Waasmunster",
    "sg:classifiers":[
        {
            "category":"Manufacturing",
            "subcategory":"Metals",
            "type":"Manufacturing & Wholesale Goods"
        }
    ],
    "sg:phone":"+32 52 46 17 15",
    "sg:postcode":"9250",
    "sg:province":"Oost-Vlaanderen",
    "sg:tags":[
        "-",
        "machine",
        "equipment",
        "engineering",
        "machinery",
        "mechanical"
    ],
    "wof:name":"Hesilas Bvba",
    "wof:placetype":"venue"
},
  "geometry": {"coordinates":[4.1180548668,51.1164474487],"type":"Point"}
}