{
  "type": "Feature",
  "properties": {
    "addr:full":"Stationsstraat 25 Diksmuide West-Vlaanderen 8600",
    "addr:housenumber":"25",
    "addr:postcode":"8600",
    "addr:street":"Stationsstraat",
    "iso:country":"BE",
    "sg:address":"Stationsstraat 25",
    "sg:city":"Diksmuide",
    "sg:classifiers":[
        {
            "category":"Health Services",
            "subcategory":"Health Practitioner",
            "type":"Services"
        }
    ],
    "sg:phone":"+32 51 51 17 01",
    "sg:postcode":"8600",
    "sg:province":"West-Vlaanderen",
    "sg:tags":[
        "physiotherapist"
    ],
    "wof:name":"Delheye Willem",
    "wof:placetype":"venue"
},
  "geometry": {"coordinates":[2.8669281006,51.0334625244],"type":"Point"}
}