{
  "type": "Feature",
  "properties": {
    "addr:full":"Paardenmarktstraat 133 Tervuren Vlaams-Brabant 3080",
    "addr:housenumber":"133",
    "addr:postcode":"3080",
    "addr:street":"Paardenmarktstraat",
    "iso:country":"BE",
    "sg:address":"Paardenmarktstraat 133",
    "sg:city":"Tervuren",
    "sg:orig_category":"Sportclubs",
    "sg:phone":"+32 2 767 98 26",
    "sg:postcode":"3080",
    "sg:province":"Vlaams-Brabant",
    "wof:name":"De Gouden Witte Pen",
    "wof:placetype":"venue"
},
  "geometry": {"coordinates":[4.5064229965,50.8190917969],"type":"Point"}
}