{
  "type": "Feature",
  "properties": {
    "addr:full":"Stationsstraat 1 Zwevegem 8552",
    "addr:housenumber":"1",
    "addr:postcode":"8552",
    "addr:street":"Stationsstraat",
    "iso:country":"BE",
    "sg:address":"Stationsstraat 1",
    "sg:city":"Zwevegem",
    "sg:orig_category":"Pain, p\u00e2tisseries and confiseries",
    "sg:phone":"+32 56 64 54 05",
    "sg:postcode":"8552",
    "wof:name":"Bakkerij Christophe",
    "wof:placetype":"venue"
},
  "geometry": {"coordinates":[3.3971719742,50.7701148987],"type":"Point"}
}