{
  "type": "Feature",
  "properties": {
    "iso:country":"BE",
    "sg:address":"Pastoor Smitstraat 4",
    "sg:city":"Koksijde",
    "sg:classifiers":[
        {
            "category":"Restaurant",
            "type":"Food & Drink"
        }
    ],
    "sg:phone":"+32 58 51 32 57",
    "sg:postcode":"8670",
    "sg:province":"West-Vlaanderen",
    "wof:name":"Estaminet De Peerdevisscher",
    "wof:placetype":"venue"
},
  "geometry": {"coordinates":[2.6834609509,51.1163902283],"type":"Point"}
}