{
  "type": "Feature",
  "properties": {
    "addr:full":"Hilloweg 1ba Kalmthout Antwerpen 2920",
    "addr:housenumber":"1ba",
    "addr:postcode":"2920",
    "addr:street":"Hilloweg",
    "iso:country":"BE",
    "sg:address":"Hilloweg 1ba",
    "sg:city":"Kalmthout",
    "sg:orig_category":"Eleveurs de volaille",
    "sg:phone":"+32 3 666 28 48",
    "sg:postcode":"2920",
    "sg:province":"Antwerpen",
    "wof:name":"Fa. Van Aert",
    "wof:placetype":"venue"
},
  "geometry": {"coordinates":[4.4979639053,51.3880691528],"type":"Point"}
}