{
  "type": "Feature",
  "properties": {
    "iso:country":"BE",
    "sg:address":"Rue Provinciale 244",
    "sg:city":"Wavre",
    "sg:orig_category":"V\u00eatements pour Hommes",
    "sg:phone":"+32 10 40 10 10",
    "sg:postcode":"1301",
    "sg:province":"Brabant Wallon",
    "wof:name":"B. & P. Mode",
    "wof:placetype":"venue"
},
  "geometry": {"coordinates":[4.5893211365,50.7059822083],"type":"Point"}
}