{
  "type": "Feature",
  "properties": {
    "iso:country":"BE",
    "sg:address":"Rue Du Bac 10",
    "sg:city":"Waimes",
    "sg:orig_category":"Agences de publicit\u00e9",
    "sg:phone":"+32 80 67 20 50",
    "sg:postcode":"4950",
    "sg:province":"Li\u00e8ge",
    "wof:name":"Systeme D",
    "wof:placetype":"venue"
},
  "geometry": {"coordinates":[6.1073260307,50.4136543274],"type":"Point"}
}