{
  "type": "Feature",
  "properties": {
    "iso:country":"BE",
    "sg:address":"Rue De La Brasserie 10",
    "sg:city":"Drogenbos",
    "sg:classifiers":[
        {
            "category":"Restaurant",
            "type":"Food & Drink"
        }
    ],
    "sg:phone":"+32 2 331 32 26",
    "sg:postcode":"1620",
    "sg:province":"Vlaams-Brabant",
    "sg:tags":[
        "caf\u00e9s"
    ],
    "wof:name":"Tonneklinker",
    "wof:placetype":"venue"
},
  "geometry": {"coordinates":[4.3184337616,50.787727356],"type":"Point"}
}