{
  "type": "Feature",
  "properties": {
    "addr:full":"J. De Malchelaan 4 Temse Oost-Vlaanderen 9140",
    "addr:housenumber":"4",
    "addr:postcode":"9140",
    "addr:street":"J. De Malchelaan",
    "iso:country":"BE",
    "sg:address":"J. De Malchelaan 4",
    "sg:city":"Temse",
    "sg:orig_category":"V\u00eatements",
    "sg:phone":"+32 3 771 14 80",
    "sg:postcode":"9140",
    "sg:province":"Oost-Vlaanderen",
    "wof:name":"Livian",
    "wof:placetype":"venue"
},
  "geometry": {"coordinates":[4.198993206,51.1356887817],"type":"Point"}
}