{
  "type": "Feature",
  "properties": {
    "iso:country":"BE",
    "sg:address":"Lentelaan 2",
    "sg:city":"Halle",
    "sg:orig_category":"Sportclubs",
    "sg:phone":"+32 2 361 28 97",
    "sg:postcode":"1500",
    "sg:province":"Vlaams-Brabant",
    "wof:name":"Wielercl.halfoogstvriend.",
    "wof:placetype":"venue"
},
  "geometry": {"coordinates":[4.2435479164,50.7276153564],"type":"Point"}
}