{
  "type": "Feature",
  "properties": {
    "iso:country":"BE",
    "sg:address":"Avenue Grande Closi\u00e8re 4",
    "sg:city":"Braine L'alleud (lillois-witterz\u00e9e)",
    "sg:classifiers":[
        {
            "category":"Education",
            "subcategory":"Special Training",
            "type":"Public Place"
        }
    ],
    "sg:phone":"+32 2 384 11 70",
    "sg:postcode":"1428",
    "sg:province":"Brabant Wallon",
    "sg:tags":[
        "school",
        "sailing"
    ],
    "wof:name":"Ecole Belge De Navigation De Plaisance Eurovoile",
    "wof:placetype":"venue"
},
  "geometry": {"coordinates":[-0.7004899979,47.369140625],"type":"Point"}
}