{
  "type": "Feature",
  "properties": {
    "iso:country":"BE",
    "sg:address":"Chauss\u00c9e De Wavre 356",
    "sg:city":"Etterbeek",
    "sg:orig_category":"Alimentation sp\u00e9cialis\u00e9e",
    "sg:phone":"+32 2 230 01 31",
    "sg:postcode":"1040",
    "sg:province":"Bruxelles-Capitale",
    "wof:name":"Traiteur Jade",
    "wof:placetype":"venue"
},
  "geometry": {"coordinates":[4.3801951408,50.836605072],"type":"Point"}
}