{
  "type": "Feature",
  "properties": {
    "iso:country":"BE",
    "sg:address":"Ryckegemkouterstraat 19",
    "sg:city":"Tielt",
    "sg:orig_category":"Huisdierenkwekers",
    "sg:phone":"+32 51 40 72 58",
    "sg:postcode":"8700",
    "sg:province":"West-Vlaanderen",
    "wof:name":"Vincke",
    "wof:placetype":"venue"
},
  "geometry": {"coordinates":[3.3491048813,51.0193138123],"type":"Point"}
}