{
  "type": "Feature",
  "properties": {
    "iso:country":"BE",
    "sg:address":"Mechelsesteenweg 2",
    "sg:city":"Lier",
    "sg:classifiers":[
        {
            "category":"Insurance",
            "subcategory":"Insurance Agent",
            "type":"Services"
        }
    ],
    "sg:phone":"+32 3 480 67 36",
    "sg:postcode":"2500",
    "sg:province":"Antwerpen",
    "sg:tags":[
        "verzekeringsmakelaars",
        "expert"
    ],
    "wof:name":"Netevallei",
    "wof:placetype":"venue"
},
  "geometry": {"coordinates":[4.5619158745,51.1305427551],"type":"Point"}
}