{
  "type": "Feature",
  "properties": {
    "addr:full":"Rue De Beyseghem 141 Bruxelles Bruxelles-Capitale 1120",
    "addr:housenumber":"141",
    "addr:postcode":"1120",
    "addr:street":"Rue De Beyseghem",
    "iso:country":"BE",
    "sg:address":"Rue De Beyseghem 141",
    "sg:city":"Bruxelles",
    "sg:classifiers":[
        {
            "category":"Education",
            "subcategory":"School",
            "type":"Public Place"
        }
    ],
    "sg:phone":"+32 2 262 03 36",
    "sg:postcode":"1120",
    "sg:province":"Bruxelles-Capitale",
    "sg:tags":[
        "secondary"
    ],
    "wof:name":"Ath\u00e9n\u00e9e Communal Des Pagodes",
    "wof:placetype":"venue"
},
  "geometry": {"coordinates":[4.3709368706,50.8954734802],"type":"Point"}
}