{
  "type": "Feature",
  "properties": {
    "iso:country":"BE",
    "sg:address":"Rue Du Belv\u00c9d\u00c8re 11",
    "sg:city":"Namur",
    "sg:orig_category":"Imprimeries and copyshops",
    "sg:phone":"+32 81 73 64 35",
    "sg:postcode":"5000",
    "sg:province":"Namur",
    "wof:name":"Fe. Jandrain",
    "wof:placetype":"venue"
},
  "geometry": {"coordinates":[4.8448700905,50.4624671936],"type":"Point"}
}