{
  "type": "Feature",
  "properties": {
    "iso:country":"BE",
    "sg:address":"Rue D'houffalize 59",
    "sg:city":"Gouvy (limerl\u00e9)",
    "sg:classifiers":[
        {
            "category":"Professional",
            "subcategory":"Art Services",
            "type":"Services"
        }
    ],
    "sg:phone":"+32 80 51 01 78",
    "sg:postcode":"6670",
    "sg:province":"Luxembourg",
    "sg:tags":[
        "-",
        "furniture"
    ],
    "wof:name":"Meubles D'andr\u00e9 (les)",
    "wof:placetype":"venue"
},
  "geometry": {"coordinates":[5.9495549202,50.1876182556],"type":"Point"}
}