{
  "type": "Feature",
  "properties": {
    "iso:country":"BE",
    "sg:address":"Stationsstraat 16",
    "sg:city":"Haaltert",
    "sg:classifiers":[
        {
            "category":"Restaurant",
            "type":"Food & Drink"
        }
    ],
    "sg:phone":"+32 53 84 07 11",
    "sg:postcode":"9450",
    "sg:province":"Oost-Vlaanderen",
    "wof:name":"Sphinx",
    "wof:placetype":"venue"
},
  "geometry": {"coordinates":[4.0075559616,50.9018249512],"type":"Point"}
}