{
  "type": "Feature",
  "properties": {
    "addr:full":"Azaleastraat 49 Oostkamp West-Vlaanderen 8020",
    "addr:housenumber":"49",
    "addr:postcode":"8020",
    "addr:street":"Azaleastraat",
    "iso:country":"BE",
    "sg:address":"Azaleastraat 49",
    "sg:city":"Oostkamp",
    "sg:classifiers":[
        {
            "category":"Health Services",
            "subcategory":"Health Practitioner",
            "type":"Services"
        }
    ],
    "sg:phone":"+32 50 82 54 63",
    "sg:postcode":"8020",
    "sg:province":"West-Vlaanderen",
    "sg:tags":[
        "physiotherapist"
    ],
    "wof:name":"Delmotte Eric",
    "wof:placetype":"venue"
},
  "geometry": {"coordinates":[3.2324330807,51.159778595],"type":"Point"}
}