{
  "type": "Feature",
  "properties": {
    "addr:full":"Rue Adolphe Rectem 23 Courcelles (trazegnies) Hainaut 6183",
    "addr:housenumber":"23",
    "addr:postcode":"6183",
    "addr:street":"Rue Adolphe Rectem",
    "iso:country":"BE",
    "sg:address":"Rue Adolphe Rectem 23",
    "sg:city":"Courcelles (trazegnies)",
    "sg:classifiers":[
        {
            "category":"Shopping",
            "subcategory":"Florist",
            "type":"Retail Goods"
        }
    ],
    "sg:phone":"+32 71 46 02 19",
    "sg:postcode":"6183",
    "sg:province":"Hainaut",
    "wof:name":"Fil Des Saisons (au)",
    "wof:placetype":"venue"
},
  "geometry": {"coordinates":[4.3325400352,50.4640197754],"type":"Point"}
}