{
  "type": "Feature",
  "properties": {
    "iso:country":"BE",
    "sg:address":"Dorfstrasse 20a",
    "sg:city":"Sankt Vith (recht)",
    "sg:classifiers":[
        {
            "category":"Retail",
            "subcategory":"Veterinary Services",
            "type":"Services"
        }
    ],
    "sg:phone":"+32 80 22 82 04",
    "sg:postcode":"4780",
    "sg:province":"Li\u00e8ge",
    "sg:tags":[
        "veterinarian"
    ],
    "wof:name":"Felten P",
    "wof:placetype":"venue"
},
  "geometry": {"coordinates":[6.1256680489,50.2810821533],"type":"Point"}
}