{
  "type": "Feature",
  "properties": {
    "iso:country":"BE",
    "sg:address":"Langstraat 30",
    "sg:city":"Maasmechelen",
    "sg:orig_category":"Enseignement maternel and primaire",
    "sg:phone":"+32 89 76 41 76",
    "sg:postcode":"3630",
    "sg:province":"Limburg",
    "wof:name":"Vrije Basisschool",
    "wof:placetype":"venue"
},
  "geometry": {"coordinates":[5.7120409012,50.9859695435],"type":"Point"}
}