{
  "type": "Feature",
  "properties": {
    "iso:country":"BE",
    "sg:address":"Logiestraat 10",
    "sg:city":"Stekene",
    "sg:orig_category":"Non-Classified Establishments",
    "sg:phone":"+32 3 789 24 77",
    "sg:postcode":"9190",
    "sg:province":"Oost-Vlaanderen",
    "wof:name":"Ace",
    "wof:placetype":"venue"
},
  "geometry": {"coordinates":[4.0488362312,51.2002334595],"type":"Point"}
}