{
  "type": "Feature",
  "properties": {
    "iso:country":"BE",
    "sg:address":"Oostmalsesteenweg 54",
    "sg:city":"Ranst (emblem)",
    "sg:classifiers":[
        {
            "category":"Shopping",
            "subcategory":"Pets & Pet Supplies",
            "type":"Retail Goods"
        }
    ],
    "sg:phone":"+32 475 64 50 64",
    "sg:postcode":"2520",
    "sg:province":"Antwerpen",
    "sg:tags":[
        "shop",
        "-"
    ],
    "wof:name":"Het Xitahof",
    "wof:placetype":"venue"
},
  "geometry": {"coordinates":[4.6120262146,51.1658935547],"type":"Point"}
}