{
  "type": "Feature",
  "properties": {
    "addr:full":"Spaansemolenstr 44 Antwerpen Antwerpen 2040",
    "addr:housenumber":"44",
    "addr:postcode":"2040",
    "addr:street":"Spaansemolenstr",
    "iso:country":"BE",
    "sg:address":"Spaansemolenstr 44",
    "sg:city":"Antwerpen",
    "sg:classifiers":[
        {
            "category":"Travel",
            "subcategory":"Hotels & Motels",
            "type":"Entertainment"
        }
    ],
    "sg:phone":"+32 3 568 63 42",
    "sg:postcode":"2040",
    "sg:province":"Antwerpen",
    "sg:tags":[
        "hotels",
        "business",
        "restaurant"
    ],
    "wof:name":"Martinushoeve Bvba",
    "wof:placetype":"venue"
},
  "geometry": {"coordinates":[4.3141150475,51.3429756165],"type":"Point"}
}