{
  "type": "Feature",
  "properties": {
    "iso:country":"BE",
    "sg:address":"De Smet De Naeyerlaan 70",
    "sg:city":"Blankenberge",
    "sg:classifiers":[
        {
            "category":"Personal",
            "subcategory":"Shoe Repair & Shine",
            "type":"Services"
        }
    ],
    "sg:phone":"+32 50 41 56 88",
    "sg:postcode":"8370",
    "sg:province":"West-Vlaanderen",
    "sg:tags":[
        "shoemaker"
    ],
    "wof:name":"Marc Shoe Service",
    "wof:placetype":"venue"
},
  "geometry": {"coordinates":[3.1290330887,51.3121261597],"type":"Point"}
}