{
  "type": "Feature",
  "properties": {
    "addr:full":"Rue Du Parc 34 La Louviere Hainaut 7100",
    "addr:housenumber":"34",
    "addr:postcode":"7100",
    "addr:street":"Rue Du Parc",
    "iso:country":"BE",
    "sg:address":"Rue Du Parc 34",
    "sg:city":"La Louviere",
    "sg:orig_category":"Artistes ind\u00e9pendants",
    "sg:phone":"+32 64 22 59 53",
    "sg:postcode":"7100",
    "sg:province":"Hainaut",
    "wof:name":"Pol Deschamps",
    "wof:placetype":"venue"
},
  "geometry": {"coordinates":[4.192070961,50.4758796692],"type":"Point"}
}