{
  "type": "Feature",
  "properties": {
    "iso:country":"BE",
    "sg:address":"Gooikeveldstraat 28",
    "sg:city":"Gooik",
    "sg:classifiers":[
        {
            "category":"Building & Trades",
            "subcategory":"Electrical",
            "type":"Services"
        }
    ],
    "sg:phone":"+32 2 532 11 51",
    "sg:postcode":"1755",
    "sg:province":"Vlaams-Brabant",
    "sg:tags":[
        "electric",
        "-",
        "housewiring",
        "contractor"
    ],
    "wof:name":"Cosijns K Bvba",
    "wof:placetype":"venue"
},
  "geometry": {"coordinates":[4.1180720329,50.7930603027],"type":"Point"}
}