{
  "type": "Feature",
  "properties": {
    "addr:full":"Bree\u00cbrsteenweg 318 Kinrooi Limburg 3640",
    "addr:housenumber":"318",
    "addr:postcode":"3640",
    "addr:street":"Breee\u0308Rsteenweg",
    "iso:country":"BE",
    "sg:address":"Bree\u00cbrsteenweg 318",
    "sg:city":"Kinrooi",
    "sg:orig_category":"Gestion des d\u00e9charges and sites d\u00e9finitifs de stockage",
    "sg:phone":"+32 89 70 22 75",
    "sg:postcode":"3640",
    "sg:province":"Limburg",
    "wof:name":"Containerpark Kinrooi",
    "wof:placetype":"venue"
},
  "geometry": {"coordinates":[5.7353081703,51.1457443237],"type":"Point"}
}