{
  "type": "Feature",
  "properties": {
    "iso:country":"BE",
    "sg:address":"Rue Des Ailes 78",
    "sg:city":"Brussel/bruxelles",
    "sg:orig_category":"Production de films, t\u00e9l\u00e9films and vid\u00e9os",
    "sg:phone":"+32 2 216 29 16",
    "sg:postcode":"1030",
    "sg:province":"Bruxelles-Capitale",
    "wof:name":"Frederic Joblin",
    "wof:placetype":"venue"
},
  "geometry": {"coordinates":[4.3738598824,50.86901474],"type":"Point"}
}