{
  "type": "Feature",
  "properties": {
    "addr:full":"Hof Ter Varentstraat 2 A Lebbeke Oost-Vlaanderen 9280",
    "addr:housenumber":"2 a",
    "addr:postcode":"9280",
    "addr:street":"Hof Ter Varentstraat",
    "iso:country":"BE",
    "sg:address":"Hof Ter Varentstraat 2 A",
    "sg:city":"Lebbeke",
    "sg:orig_category":"Articles de jardin",
    "sg:phone":"+32 52 41 46 36",
    "sg:postcode":"9280",
    "sg:province":"Oost-Vlaanderen",
    "wof:name":"Tuincentrum \u00b4t Vaerenhof",
    "wof:placetype":"venue"
},
  "geometry": {"coordinates":[4.1281580925,50.993434906],"type":"Point"}
}