{
  "type": "Feature",
  "properties": {
    "iso:country":"BE",
    "sg:address":"\u00b4t Serclaesstraat 14",
    "sg:city":"Ternat",
    "sg:orig_category":"Entretien and r\u00e9parations de voitures",
    "sg:phone":"+32 2 582 52 39",
    "sg:postcode":"1740",
    "sg:province":"Vlaams-Brabant",
    "wof:name":"Deprez Michel Carrosserie",
    "wof:placetype":"venue"
},
  "geometry": {"coordinates":[4.1704702377,50.8683280945],"type":"Point"}
}