{
  "type": "Feature",
  "properties": {
    "addr:full":"Kleine Stadenstraat 61 Hooglede West-Vlaanderen 8830",
    "addr:housenumber":"61",
    "addr:postcode":"8830",
    "addr:street":"Kleine Stadenstraat",
    "iso:country":"BE",
    "sg:address":"Kleine Stadenstraat 61",
    "sg:city":"Hooglede",
    "sg:classifiers":[
        {
            "category":"Health Services",
            "subcategory":"Health Practitioner",
            "type":"Services"
        }
    ],
    "sg:phone":"+32 51 20 56 35",
    "sg:postcode":"8830",
    "sg:province":"West-Vlaanderen",
    "sg:tags":[
        "osteopath"
    ],
    "wof:name":"Dely Luc (d.o.)",
    "wof:placetype":"venue"
},
  "geometry": {"coordinates":[3.0775609016,50.9787750244],"type":"Point"}
}