{
  "type": "Feature",
  "properties": {
    "addr:full":"Rue Chant Des Oiseaux 2a Genappe (baisy-thy) Brabant Wallon 1470",
    "addr:housenumber":"2a",
    "addr:postcode":"1470",
    "addr:street":"Rue Chant Des Oiseaux",
    "iso:country":"BE",
    "sg:address":"Rue Chant Des Oiseaux 2a",
    "sg:city":"Genappe (baisy-thy)",
    "sg:classifiers":[
        {
            "category":"Building & Trades",
            "subcategory":"Plumbing",
            "type":"Services"
        }
    ],
    "sg:phone":"+32 67 79 04 48",
    "sg:postcode":"1470",
    "sg:province":"Brabant Wallon",
    "sg:tags":[
        "repair",
        "mainten",
        "-",
        "central",
        "heating"
    ],
    "wof:name":"Techno-flam",
    "wof:placetype":"venue"
},
  "geometry": {"coordinates":[4.4490060806,50.610458374],"type":"Point"}
}