{
  "type": "Feature",
  "properties": {
    "addr:full":"Sportlaan 22 Wuustwezel Antwerpen 2990",
    "addr:housenumber":"22",
    "addr:postcode":"2990",
    "addr:street":"Sportlaan",
    "iso:country":"BE",
    "sg:address":"Sportlaan 22",
    "sg:city":"Wuustwezel",
    "sg:classifiers":[
        {
            "category":"Professional",
            "subcategory":"Computer Services",
            "type":"Services"
        }
    ],
    "sg:phone":"+32 3 669 57 13",
    "sg:postcode":"2990",
    "sg:province":"Antwerpen",
    "sg:tags":[
        "-",
        "processing",
        "data",
        "software"
    ],
    "wof:name":"Real Computerstuff Bvba",
    "wof:placetype":"venue"
},
  "geometry": {"coordinates":[4.592689991,51.3957099915],"type":"Point"}
}