{
  "type": "Feature",
  "properties": {
    "addr:full":"Den Hert 14 Lille Antwerpen 2275",
    "addr:housenumber":"14",
    "addr:postcode":"2275",
    "addr:street":"Den Hert",
    "iso:country":"BE",
    "sg:address":"Den Hert 14",
    "sg:city":"Lille",
    "sg:orig_category":"Banques and organismes de cr\u00e9dit",
    "sg:phone":"+32 3 312 44 48",
    "sg:postcode":"2275",
    "sg:province":"Antwerpen",
    "wof:name":"Bankunie",
    "wof:placetype":"venue"
},
  "geometry": {"coordinates":[4.8245601654,51.2381668091],"type":"Point"}
}