{
  "type": "Feature",
  "properties": {
    "addr:full":"Rue De Dison 194 Verviers Li\u00e8ge 4800",
    "addr:housenumber":"194",
    "addr:postcode":"4800",
    "addr:street":"Rue De Dison",
    "iso:country":"BE",
    "sg:address":"Rue De Dison 194",
    "sg:city":"Verviers",
    "sg:orig_category":"Tweedehandsgoederen",
    "sg:phone":"+32 87 33 25 76",
    "sg:postcode":"4800",
    "sg:province":"Li\u00e8ge",
    "wof:name":"Boutique Terre",
    "wof:placetype":"venue"
},
  "geometry": {"coordinates":[5.8594508171,50.5917663574],"type":"Point"}
}