{
  "type": "Feature",
  "properties": {
    "iso:country":"BE",
    "sg:address":"Steenweg 208",
    "sg:city":"Diepenbeek",
    "sg:classifiers":[
        {
            "category":"Retail",
            "subcategory":"Auto Repair",
            "type":"Services"
        }
    ],
    "sg:phone":"+32 11 22 25 10",
    "sg:postcode":"3590",
    "sg:province":"Limburg",
    "sg:tags":[
        "garage"
    ],
    "wof:name":"Priemen Richard-r.p.d.",
    "wof:placetype":"venue"
},
  "geometry": {"coordinates":[5.3802847862,50.9222450256],"type":"Point"}
}