{
  "type": "Feature",
  "properties": {
    "addr:full":"Rue Jean Jaur\u00c8s 324 Ans Li\u00e8ge 4430",
    "addr:housenumber":"324",
    "addr:postcode":"4430",
    "addr:street":"Rue Jean Jaure\u0300S",
    "iso:country":"BE",
    "sg:address":"Rue Jean Jaur\u00c8s 324",
    "sg:city":"Ans",
    "sg:classifiers":[
        {
            "category":"Fast Food",
            "type":"Food & Drink"
        }
    ],
    "sg:phone":"+32 4 247 39 00",
    "sg:postcode":"4430",
    "sg:province":"Li\u00e8ge",
    "sg:tags":[
        "\u00c0",
        "restaurants",
        "emporter",
        "restaurant"
    ],
    "wof:name":"Pizza Hut",
    "wof:placetype":"venue"
},
  "geometry": {"coordinates":[5.5302968025,50.6556930542],"type":"Point"}
}