{
  "type": "Feature",
  "properties": {
    "iso:country":"BE",
    "sg:address":"Kerkstraat 18",
    "sg:city":"Avelgem",
    "sg:orig_category":"Banken and kredietinstellingen",
    "sg:phone":"+32 56 64 40 84",
    "sg:postcode":"8580",
    "sg:province":"West-Vlaanderen",
    "wof:name":"Bbl",
    "wof:placetype":"venue"
},
  "geometry": {"coordinates":[3.4460699558,50.7755775452],"type":"Point"}
}