{
  "type": "Feature",
  "properties": {
    "iso:country":"BE",
    "sg:address":"Kluizestraat 58",
    "sg:city":"Knesselare",
    "sg:orig_category":"Newspapers, magazines, periodicals - Distribution",
    "sg:phone":"+32 9 374 68 13",
    "sg:postcode":"9910",
    "sg:province":"Oost-Vlaanderen",
    "wof:name":"De Clercq F",
    "wof:placetype":"venue"
},
  "geometry": {"coordinates":[3.4126999378,51.1456336975],"type":"Point"}
}