{
  "type": "Feature",
  "properties": {
    "addr:full":"Rue Henri Maus 82 Li\u00c8ge Li\u00e8ge 4000",
    "addr:housenumber":"82",
    "addr:postcode":"4000",
    "addr:street":"Rue Henri Maus",
    "iso:country":"BE",
    "sg:address":"Rue Henri Maus 82",
    "sg:city":"Li\u00c8ge",
    "sg:orig_category":"Artistes ind\u00e9pendants",
    "sg:phone":"+32 4 254 12 97",
    "sg:postcode":"4000",
    "sg:province":"Li\u00e8ge",
    "wof:name":"Pascal Falisse",
    "wof:placetype":"venue"
},
  "geometry": {"coordinates":[5.5557451248,50.6328659058],"type":"Point"}
}