{
  "type": "Feature",
  "properties": {
    "addr:full":"Rue Emile Vandervelde 29 Courcelles Hainaut 6182",
    "addr:housenumber":"29",
    "addr:postcode":"6182",
    "addr:street":"Rue Emile Vandervelde",
    "iso:country":"BE",
    "sg:address":"Rue Emile Vandervelde 29",
    "sg:city":"Courcelles",
    "sg:orig_category":"Boekhouders",
    "sg:phone":"+32 71 46 18 01",
    "sg:postcode":"6182",
    "sg:province":"Hainaut",
    "wof:name":"Victor Gamache",
    "wof:placetype":"venue"
},
  "geometry": {"coordinates":[4.3542299271,50.4462013245],"type":"Point"}
}