{
  "type": "Feature",
  "properties": {
    "addr:full":"Grand-place 1 Bertrix Luxembourg 6880",
    "addr:housenumber":"1",
    "addr:postcode":"6880",
    "addr:street":"Grand-Place",
    "iso:country":"BE",
    "sg:address":"Grand-place 1",
    "sg:city":"Bertrix",
    "sg:orig_category":"Rijscholen",
    "sg:phone":"+32 61 23 01 70",
    "sg:postcode":"6880",
    "sg:province":"Luxembourg",
    "wof:name":"Auto-ecole Ardennes",
    "wof:placetype":"venue"
},
  "geometry": {"coordinates":[5.2525458336,49.8543701172],"type":"Point"}
}