{
  "type": "Feature",
  "properties": {
    "iso:country":"BE",
    "sg:address":"Zwevegemsestraat 51",
    "sg:city":"Kortrijk",
    "sg:orig_category":"Computers Fab Computers and computerapparatuur Kantoormateriaal Gh Onderhoud van kantoor- and comput",
    "sg:phone":"+32 56 22 99 40",
    "sg:postcode":"8500",
    "sg:province":"West-Vlaanderen",
    "wof:name":"Pc Support Bvba",
    "wof:placetype":"venue"
},
  "geometry": {"coordinates":[3.2730660439,50.8243675232],"type":"Point"}
}