{
  "type": "Feature",
  "properties": {
    "addr:full":"Koning Albertlaan 34 Lanaken Limburg 3620",
    "addr:housenumber":"34",
    "addr:postcode":"3620",
    "addr:street":"Koning Albertlaan",
    "iso:country":"BE",
    "sg:address":"Koning Albertlaan 34",
    "sg:city":"Lanaken",
    "sg:classifiers":[
        {
            "category":"Professional",
            "subcategory":"Management & Consulting",
            "type":"Services"
        }
    ],
    "sg:phone":"+32 89 71 32 35",
    "sg:postcode":"3620",
    "sg:province":"Limburg",
    "sg:tags":[
        "consultant",
        "law"
    ],
    "wof:name":"Claeys P",
    "wof:placetype":"venue"
},
  "geometry": {"coordinates":[5.6547250748,50.8909034729],"type":"Point"}
}