{
  "type": "Feature",
  "properties": {
    "addr:full":"Molenstraat 64 Gavere Oost-Vlaanderen 9890",
    "addr:housenumber":"64",
    "addr:postcode":"9890",
    "addr:street":"Molenstraat",
    "iso:country":"BE",
    "sg:address":"Molenstraat 64",
    "sg:city":"Gavere",
    "sg:classifiers":[
        {
            "category":"Building & Trades",
            "subcategory":"Electrical",
            "type":"Services"
        }
    ],
    "sg:phone":"+32 9 384 47 79",
    "sg:postcode":"9890",
    "sg:province":"Oost-Vlaanderen",
    "sg:tags":[
        "electric",
        "-",
        "housewiring",
        "contractor"
    ],
    "wof:name":"Algemene Elektriciteitswerken Coussement",
    "wof:placetype":"venue"
},
  "geometry": {"coordinates":[3.668389082,50.9264335632],"type":"Point"}
}