{
  "type": "Feature",
  "properties": {
    "addr:full":"Rue Du Planois 83 Braine-le-comte Hainaut 7090",
    "addr:housenumber":"83",
    "addr:postcode":"7090",
    "addr:street":"Rue Du Planois",
    "iso:country":"BE",
    "sg:address":"Rue Du Planois 83",
    "sg:city":"Braine-le-comte",
    "sg:orig_category":"Sportcentra",
    "sg:phone":"+32 67 56 13 91",
    "sg:postcode":"7090",
    "sg:province":"Hainaut",
    "wof:name":"Braine Sports",
    "wof:placetype":"venue"
},
  "geometry": {"coordinates":[4.1748270988,50.6398735046],"type":"Point"}
}