{
  "type": "Feature",
  "properties": {
    "addr:full":"Stationsstraat 124 Oostende West-Vlaanderen 8400",
    "addr:housenumber":"124",
    "addr:postcode":"8400",
    "addr:street":"Stationsstraat",
    "iso:country":"BE",
    "sg:address":"Stationsstraat 124",
    "sg:city":"Oostende",
    "sg:orig_category":"Woningbouw",
    "sg:phone":"+32 59 80 02 61",
    "sg:postcode":"8400",
    "sg:province":"West-Vlaanderen",
    "wof:name":"Johan Casteleyn",
    "wof:placetype":"venue"
},
  "geometry": {"coordinates":[2.9766869545,51.2080383301],"type":"Point"}
}