{
  "type": "Feature",
  "properties": {
    "addr:full":"Avenue De L'yser 7 Lens Hainaut 7870",
    "addr:housenumber":"7",
    "addr:postcode":"7870",
    "addr:street":"Avenue De L'Yser",
    "iso:country":"BE",
    "sg:address":"Avenue De L'yser 7",
    "sg:city":"Lens",
    "sg:orig_category":"Enseignement maternel and primaire",
    "sg:phone":"+32 68 45 56 04",
    "sg:postcode":"7870",
    "sg:province":"Hainaut",
    "wof:name":"Ecole Fondamentale Libre",
    "wof:placetype":"venue"
},
  "geometry": {"coordinates":[3.9347999096,50.6016426086],"type":"Point"}
}