{
  "type": "Feature",
  "properties": {
    "iso:country":"BE",
    "sg:address":"Route Du Condroz 133",
    "sg:city":"Li\u00c8ge",
    "sg:orig_category":"MEUBELONTWERP AND -INSTALLATIE",
    "sg:phone":"+32 4 365 54 72",
    "sg:postcode":"4031",
    "sg:province":"Li\u00e8ge",
    "wof:name":"M. Vanderschelden",
    "wof:placetype":"venue"
},
  "geometry": {"coordinates":[5.5800671577,50.6007232666],"type":"Point"}
}