{
  "type": "Feature",
  "properties": {
    "iso:country":"BE",
    "sg:address":"Statiestraat 165",
    "sg:city":"Lichtervelde",
    "sg:orig_category":"Artsen and specialisten",
    "sg:phone":"+32 51 72 20 92",
    "sg:postcode":"8810",
    "sg:province":"West-Vlaanderen",
    "wof:name":"Wouter Beele",
    "wof:placetype":"venue"
},
  "geometry": {"coordinates":[3.1318480968,51.0249099731],"type":"Point"}
}