{
  "type": "Feature",
  "properties": {
    "addr:full":"Kerkstraat 4 Destelbergen Oost-Vlaanderen 9070",
    "addr:housenumber":"4",
    "addr:postcode":"9070",
    "addr:street":"Kerkstraat",
    "iso:country":"BE",
    "sg:address":"Kerkstraat 4",
    "sg:city":"Destelbergen",
    "sg:orig_category":"Banken and kredietinstellingen",
    "sg:phone":"+32 9 228 50 33",
    "sg:postcode":"9070",
    "sg:province":"Oost-Vlaanderen",
    "wof:name":"Kbc",
    "wof:placetype":"venue"
},
  "geometry": {"coordinates":[3.798844099,51.0562973022],"type":"Point"}
}