{
  "type": "Feature",
  "properties": {
    "addr:full":"Rue Des Chateaux 24 Blegny Li\u00e8ge 4671",
    "addr:housenumber":"24",
    "addr:postcode":"4671",
    "addr:street":"Rue Des Chateaux",
    "iso:country":"BE",
    "sg:address":"Rue Des Chateaux 24",
    "sg:city":"Blegny",
    "sg:orig_category":"Krantenuitgeverijen Tijdschriftenuitgeverijen",
    "sg:phone":"+32 4 370 05 55",
    "sg:postcode":"4671",
    "sg:province":"Li\u00e8ge",
    "wof:name":"I.a.g.o.",
    "wof:placetype":"venue"
},
  "geometry": {"coordinates":[5.6820588112,50.6480712891],"type":"Point"}
}