{
  "type": "Feature",
  "properties": {
    "iso:country":"BE",
    "sg:address":"Stationstraat 82",
    "sg:city":"Turnhout",
    "sg:classifiers":[
        {
            "category":"Retail",
            "subcategory":"Repair Shop",
            "type":"Services"
        }
    ],
    "sg:phone":"+32 14 42 44 00",
    "sg:postcode":"2300",
    "sg:province":"Antwerpen",
    "wof:name":"Trektang (de) Vzw",
    "wof:placetype":"venue"
},
  "geometry": {"coordinates":[4.9403100014,51.3242111206],"type":"Point"}
}