{
  "type": "Feature",
  "properties": {
    "iso:country":"BE",
    "sg:address":"Van Dijcklaan 15",
    "sg:city":"Zaventem",
    "sg:classifiers":[
        {
            "category":"Bars & Pubs",
            "type":"Food & Drink"
        }
    ],
    "sg:phone":"+32 2 720 07 87",
    "sg:postcode":"1930",
    "sg:province":"Vlaams-Brabant",
    "wof:name":"Corner (the)",
    "wof:placetype":"venue"
},
  "geometry": {"coordinates":[4.473762989,50.8868637085],"type":"Point"}
}