{
  "type": "Feature",
  "properties": {
    "addr:full":"Chauss\u00e9e De Tournai 310 Ath (ligne) Hainaut 7812",
    "addr:housenumber":"310",
    "addr:postcode":"7812",
    "addr:street":"Chausse\u0301E De Tournai",
    "iso:country":"BE",
    "sg:address":"Chauss\u00e9e De Tournai 310",
    "sg:city":"Ath (ligne)",
    "sg:classifiers":[
        {
            "category":"Retail",
            "subcategory":"Auto Rental",
            "type":"Services"
        }
    ],
    "sg:phone":"+32 68 54 37 19",
    "sg:postcode":"7812",
    "sg:province":"Hainaut",
    "sg:tags":[
        "plant",
        "flower",
        "-"
    ],
    "wof:name":"I.d. Flo Sprl",
    "wof:placetype":"venue"
},
  "geometry": {"coordinates":[3.7079770565,50.6189002991],"type":"Point"}
}