{
  "type": "Feature",
  "properties": {
    "addr:full":"Rue Van Bortonne 102 Bruxelles (jette) Bruxelles-Capitale 1090",
    "addr:housenumber":"102",
    "addr:postcode":"1090",
    "addr:street":"Rue Van Bortonne",
    "iso:country":"BE",
    "sg:address":"Rue Van Bortonne 102",
    "sg:city":"Bruxelles (jette)",
    "sg:classifiers":[
        {
            "category":"Food & Beverages",
            "subcategory":"Groceries & Convenience Stores",
            "type":"Retail Goods"
        }
    ],
    "sg:phone":"+32 2 420 09 94",
    "sg:postcode":"1090",
    "sg:province":"Bruxelles-Capitale",
    "sg:tags":[
        "grocer"
    ],
    "wof:name":"Dafina",
    "wof:placetype":"venue"
},
  "geometry": {"coordinates":[4.3267560005,50.8772544861],"type":"Point"}
}