{
  "type": "Feature",
  "properties": {
    "addr:full":"Premi\u00c8re Rue Basse 62 Beloeil Hainaut 7970",
    "addr:housenumber":"62",
    "addr:postcode":"7970",
    "addr:street":"Rue Basse",
    "iso:country":"BE",
    "sg:address":"Premi\u00c8re Rue Basse 62",
    "sg:city":"Beloeil",
    "sg:orig_category":"Rundveehouders",
    "sg:phone":"+32 69 68 91 05",
    "sg:postcode":"7970",
    "sg:province":"Hainaut",
    "wof:name":"Michel Dubuisson",
    "wof:placetype":"venue"
},
  "geometry": {"coordinates":[3.7512130737,50.5420646667],"type":"Point"}
}