{
  "type": "Feature",
  "properties": {
    "addr:full":"Kwakkelhoekstraat 60 Sint-niklaas (nieuwkerken-waas) Oost-Vlaanderen 9100",
    "addr:housenumber":"60",
    "addr:postcode":"9100",
    "addr:street":"Kwakkelhoekstraat;Nieuwkerken-Waas",
    "iso:country":"BE",
    "sg:address":"Kwakkelhoekstraat 60",
    "sg:city":"Sint-niklaas (nieuwkerken-waas)",
    "sg:classifiers":[
        {
            "category":"Professional",
            "subcategory":"Engineering",
            "type":"Services"
        }
    ],
    "sg:phone":"+32 3 766 70 73",
    "sg:postcode":"9100",
    "sg:province":"Oost-Vlaanderen",
    "sg:tags":[
        "-"
    ],
    "wof:name":"Tinestim Bvba",
    "wof:placetype":"venue"
},
  "geometry": {"coordinates":[4.187582016,51.1931724548],"type":"Point"}
}