{
  "type": "Feature",
  "properties": {
    "addr:full":"Halenplein 1 Kortrijk West-Vlaanderen 8500",
    "addr:housenumber":"1",
    "addr:postcode":"8500",
    "addr:street":"Halenplein",
    "iso:country":"BE",
    "sg:address":"Halenplein 1",
    "sg:city":"Kortrijk",
    "sg:classifiers":[
        {
            "category":"Cafe",
            "type":"Food & Drink"
        }
    ],
    "sg:phone":"+32 56 22 38 97",
    "sg:postcode":"8500",
    "sg:province":"West-Vlaanderen",
    "sg:tags":[
        "caf\u00e9s"
    ],
    "wof:name":"Caf\u00c9 \u00b4t Pleintje",
    "wof:placetype":"venue"
},
  "geometry": {"coordinates":[3.2756121159,50.8155288696],"type":"Point"}
}