{
  "type": "Feature",
  "properties": {
    "iso:country":"BE",
    "sg:address":"Avenue Des Celtes 12",
    "sg:city":"Etterbeek",
    "sg:orig_category":"Motos",
    "sg:phone":"+32 2 735 68 60",
    "sg:postcode":"1040",
    "sg:province":"Bruxelles-Capitale",
    "wof:name":"Bike Zone (etterbeek)",
    "wof:placetype":"venue"
},
  "geometry": {"coordinates":[4.3983440399,50.8386764526],"type":"Point"}
}