{
  "type": "Feature",
  "properties": {
    "addr:full":"Emiel Van Winckellaan 36 Dendermonde Oost-Vlaanderen 9200",
    "addr:housenumber":"36",
    "addr:postcode":"9200",
    "addr:street":"Emiel Van Winckellaan;Oost-Vlaanderen",
    "iso:country":"BE",
    "sg:address":"Emiel Van Winckellaan 36",
    "sg:city":"Dendermonde",
    "sg:classifiers":[
        {
            "category":"Insurance",
            "subcategory":"Insurance Agent",
            "type":"Services"
        }
    ],
    "sg:phone":"+32 52 22 24 05",
    "sg:postcode":"9200",
    "sg:province":"Oost-Vlaanderen",
    "sg:tags":[
        "verzekeringsmakelaars",
        "expert"
    ],
    "wof:name":"Insural",
    "wof:placetype":"venue"
},
  "geometry": {"coordinates":[4.096159935,51.0306434631],"type":"Point"}
}