{
  "type": "Feature",
  "properties": {
    "addr:full":"Place Des Combattants 13 Paliseul Luxembourg 6852",
    "addr:housenumber":"13",
    "addr:postcode":"6852",
    "addr:street":"Place Des Combattants",
    "iso:country":"BE",
    "sg:address":"Place Des Combattants 13",
    "sg:city":"Paliseul",
    "sg:orig_category":"Supermarkten",
    "sg:phone":"+32 61 65 51 68",
    "sg:postcode":"6852",
    "sg:province":"Luxembourg",
    "wof:name":"Ad Delhaize",
    "wof:placetype":"venue"
},
  "geometry": {"coordinates":[5.1785240173,49.9646186829],"type":"Point"}
}