{
  "type": "Feature",
  "properties": {
    "iso:country":"BE",
    "sg:address":"Tieblokkenlaan 8",
    "sg:city":"Turnhout",
    "sg:orig_category":"Quincailleries",
    "sg:phone":"+32 14 44 20 30",
    "sg:postcode":"2300",
    "sg:province":"Antwerpen",
    "wof:name":"Fastinox",
    "wof:placetype":"venue"
},
  "geometry": {"coordinates":[4.9266262054,51.3035926819],"type":"Point"}
}