{
  "type": "Feature",
  "properties": {
    "addr:full":"Heirbaan 159 Lanaken (rekem) Limburg 3621",
    "addr:housenumber":"159",
    "addr:postcode":"3621",
    "addr:street":"Heirbaan",
    "iso:country":"BE",
    "sg:address":"Heirbaan 159",
    "sg:city":"Lanaken (rekem)",
    "sg:classifiers":[
        {
            "category":"Health Services",
            "subcategory":"Health Practitioner",
            "type":"Services"
        }
    ],
    "sg:phone":"+32 89 71 88 93",
    "sg:postcode":"3621",
    "sg:province":"Limburg",
    "sg:tags":[
        "physiotherapist"
    ],
    "wof:name":"Stifter Robert",
    "wof:placetype":"venue"
},
  "geometry": {"coordinates":[5.6853117943,50.9143829346],"type":"Point"}
}