{
  "type": "Feature",
  "properties": {
    "iso:country":"BE",
    "sg:address":"Rue De La R\u00c9gence 13",
    "sg:city":"Brussel",
    "sg:orig_category":"RESTAURANTS: LIBRAIRIES",
    "sg:phone":"+32 2 502 34 54",
    "sg:postcode":"1000",
    "sg:province":"Bruxelles-Capitale",
    "wof:name":"The Yellow Kid Cafe",
    "wof:placetype":"venue"
},
  "geometry": {"coordinates":[4.3555240631,50.8396186829],"type":"Point"}
}