{
  "type": "Feature",
  "properties": {
    "iso:country":"BE",
    "sg:address":"Kalendijk 4",
    "sg:city":"Dendermonde",
    "sg:orig_category":"Services pour animaux domestiques. Animaux domestiques and accessoires",
    "sg:phone":"+32 52 21 75 80",
    "sg:postcode":"9200",
    "sg:province":"Oost-Vlaanderen",
    "wof:name":"Scara",
    "wof:placetype":"venue"
},
  "geometry": {"coordinates":[4.1045570374,51.0239944458],"type":"Point"}
}