{
  "type": "Feature",
  "properties": {
    "addr:full":"Tuinwijk 25 Kortemark West-Vlaanderen 8610",
    "addr:housenumber":"25",
    "addr:postcode":"8610",
    "addr:street":"Tuinwijk",
    "iso:country":"BE",
    "sg:address":"Tuinwijk 25",
    "sg:city":"Kortemark",
    "sg:orig_category":"Assurances. Agences immobili\u00e8res",
    "sg:phone":"+32 51 56 86 93",
    "sg:postcode":"8610",
    "sg:province":"West-Vlaanderen",
    "wof:name":"Ronny Brackez",
    "wof:placetype":"venue"
},
  "geometry": {"coordinates":[3.0499699116,51.0305290222],"type":"Point"}
}