{
  "type": "Feature",
  "properties": {
    "addr:full":"Rue Reine Astrid 9 Charleroi Hainaut 6041",
    "addr:housenumber":"9",
    "addr:postcode":"6041",
    "addr:street":"Rue Reine Astrid;Hainaut",
    "iso:country":"BE",
    "sg:address":"Rue Reine Astrid 9",
    "sg:city":"Charleroi",
    "sg:orig_category":"Banques and organismes de cr\u00e9dit",
    "sg:phone":"+32 71 34 54 88",
    "sg:postcode":"6041",
    "sg:province":"Hainaut",
    "wof:name":"Bacob",
    "wof:placetype":"venue"
},
  "geometry": {"coordinates":[4.4208741188,50.41847229],"type":"Point"}
}