{
  "type": "Feature",
  "properties": {
    "addr:full":"Tempelstraat 81 Geraardsbergen Oost-Vlaanderen 9500",
    "addr:housenumber":"81",
    "addr:postcode":"9500",
    "addr:street":"Tempelstraat",
    "iso:country":"BE",
    "sg:address":"Tempelstraat 81",
    "sg:city":"Geraardsbergen",
    "sg:orig_category":"Eleveurs de bovins",
    "sg:phone":"+32 54 50 15 99",
    "sg:postcode":"9500",
    "sg:province":"Oost-Vlaanderen",
    "wof:name":"Paul Van Der Meeren",
    "wof:placetype":"venue"
},
  "geometry": {"coordinates":[3.8843801022,50.7716445923],"type":"Point"}
}