{
  "type": "Feature",
  "properties": {
    "iso:country":"BE",
    "sg:address":"Rue Achille Antoine",
    "sg:city":"Somme-leuze",
    "sg:orig_category":"Huisdieren and benodigdheden",
    "sg:phone":"+32 86 32 20 75",
    "sg:postcode":"5418",
    "wof:name":"Fortemps",
    "wof:placetype":"venue"
},
  "geometry": {"coordinates":[5.3719911575,50.3414154053],"type":"Point"}
}