{
  "type": "Feature",
  "properties": {
    "iso:country":"BE",
    "sg:address":"Avenue F. Nicolay 18",
    "sg:city":"Stavelot",
    "sg:orig_category":"Pensions de famille",
    "sg:phone":"+32 80 86 23 03",
    "sg:postcode":"4970",
    "sg:province":"Li\u00e8ge",
    "wof:name":"Luxen-chauveheid",
    "wof:placetype":"venue"
},
  "geometry": {"coordinates":[5.933617115,50.3956298828],"type":"Point"}
}