{
  "type": "Feature",
  "properties": {
    "addr:full":"Rue Des Combattants 13 Florennes (hanzinne) Namur 5621",
    "addr:housenumber":"13",
    "addr:postcode":"5621",
    "addr:street":"Rue Des Combattants",
    "iso:country":"BE",
    "sg:address":"Rue Des Combattants 13",
    "sg:city":"Florennes (hanzinne)",
    "sg:classifiers":[
        {
            "category":"Real Estate",
            "subcategory":"Architect",
            "type":"Services"
        }
    ],
    "sg:phone":"+32 71 50 41 24",
    "sg:postcode":"5621",
    "sg:province":"Namur",
    "wof:name":"Warolus P",
    "wof:placetype":"venue"
},
  "geometry": {"coordinates":[4.5442419052,50.3138694763],"type":"Point"}
}