{
  "type": "Feature",
  "properties": {
    "iso:country":"BE",
    "sg:address":"Hollandsveldlaan 17b2",
    "sg:city":"Hasselt",
    "sg:orig_category":"Elektrische installaties voor woningen Plaatsen van vloer- and muurbekleding",
    "sg:phone":"+32 11 27 10 42",
    "sg:postcode":"3500",
    "sg:province":"Limburg",
    "wof:name":"Jacques Voortmans Decor",
    "wof:placetype":"venue"
},
  "geometry": {"coordinates":[5.3421177864,50.9173202515],"type":"Point"}
}