{
  "type": "Feature",
  "properties": {
    "addr:full":"Stationstraat 46 Ardooie West-Vlaanderen 8850",
    "addr:housenumber":"46",
    "addr:postcode":"8850",
    "addr:street":"Stationstraat",
    "iso:country":"BE",
    "sg:address":"Stationstraat 46",
    "sg:city":"Ardooie",
    "sg:orig_category":"Producteurs de l\u00e9gumes",
    "sg:phone":"+32 51 74 78 14",
    "sg:postcode":"8850",
    "sg:province":"West-Vlaanderen",
    "wof:name":"Rapha\u00cbl Devos",
    "wof:placetype":"venue"
},
  "geometry": {"coordinates":[3.1998279095,50.9804153442],"type":"Point"}
}