{
  "type": "Feature",
  "properties": {
    "addr:full":"Rue De Luxembourg 2 Hannuit Li\u00e8ge 4280",
    "addr:housenumber":"2",
    "addr:postcode":"4280",
    "addr:street":"Rue De Luxembourg",
    "iso:country":"BE",
    "sg:address":"Rue De Luxembourg 2",
    "sg:city":"Hannuit",
    "sg:orig_category":"Timbres, monnaies and troph\u00e9es. Articles textiles and tissus de d\u00e9coration Fab",
    "sg:phone":"+32 19 51 29 20",
    "sg:postcode":"4280",
    "sg:province":"Li\u00e8ge",
    "wof:name":"Publi-ben",
    "wof:placetype":"venue"
},
  "geometry": {"coordinates":[5.0859889984,50.6776428223],"type":"Point"}
}