{
  "type": "Feature",
  "properties": {
    "iso:country":"BE",
    "sg:address":"Lostraat 86",
    "sg:city":"Nevele (merendree)",
    "sg:classifiers":[
        {
            "category":"Parking",
            "subcategory":"Lot",
            "type":"Transportation"
        }
    ],
    "sg:phone":"+32 9 371 65 02",
    "sg:postcode":"9850",
    "sg:province":"Oost-Vlaanderen",
    "sg:tags":[
        "parking-places",
        "laying-out"
    ],
    "wof:name":"Haesaert Willy Nv",
    "wof:placetype":"venue"
},
  "geometry": {"coordinates":[3.596421957,51.0882301331],"type":"Point"}
}