{
  "type": "Feature",
  "properties": {
    "iso:country":"BE",
    "sg:address":"Schendekouterstraat 25",
    "sg:city":"Wervik (geluwe)",
    "sg:classifiers":[
        {
            "category":"Home & Garden",
            "subcategory":"Carpets & Floor Coverings",
            "type":"Retail Goods"
        }
    ],
    "sg:phone":"+32 56 51 59 79",
    "sg:postcode":"8940",
    "sg:province":"West-Vlaanderen",
    "sg:tags":[
        "parquet"
    ],
    "wof:name":"Europ Parket",
    "wof:placetype":"venue"
},
  "geometry": {"coordinates":[3.0971159935,50.8208084106],"type":"Point"}
}