{
  "type": "Feature",
  "properties": {
    "iso:country":"BE",
    "sg:address":"Kardinaal Cardijnlaan 71",
    "sg:city":"Aartselaar",
    "sg:classifiers":[
        {
            "category":"Health Services",
            "subcategory":"Health Practitioner",
            "type":"Services"
        }
    ],
    "sg:phone":"+32 3 887 85 13",
    "sg:postcode":"2630",
    "sg:province":"Antwerpen",
    "sg:tags":[
        "physiotherapist"
    ],
    "wof:name":"Vandromme Kris",
    "wof:placetype":"venue"
},
  "geometry": {"coordinates":[4.3797459602,51.1333007812],"type":"Point"}
}