{
  "type": "Feature",
  "properties": {
    "iso:country":"BE",
    "sg:address":"Chauss\u00e9e De Namur 11",
    "sg:city":"Burdinne",
    "sg:classifiers":[
        {
            "category":"Autos & Motor Vehicles",
            "subcategory":"Automobile Sales",
            "type":"Retail Goods"
        }
    ],
    "sg:phone":"+32 81 83 44 28",
    "sg:postcode":"4210",
    "sg:province":"Li\u00e8ge",
    "sg:tags":[
        "car",
        "used",
        "-"
    ],
    "wof:name":"Pansaerts F Garage",
    "wof:placetype":"venue"
},
  "geometry": {"coordinates":[5.0582318306,50.5782661438],"type":"Point"}
}