{
  "type": "Feature",
  "properties": {
    "addr:full":"Stationstraat 35 Wichelen Oost-Vlaanderen 9260",
    "addr:housenumber":"35",
    "addr:postcode":"9260",
    "addr:street":"Stationstraat",
    "iso:country":"BE",
    "sg:address":"Stationstraat 35",
    "sg:city":"Wichelen",
    "sg:orig_category":"Fietsen",
    "sg:phone":"+32 9 369 54 75",
    "sg:postcode":"9260",
    "sg:province":"Oost-Vlaanderen",
    "wof:name":"Andy Rasschaert",
    "wof:placetype":"venue"
},
  "geometry": {"coordinates":[3.9259541035,51.0109367371],"type":"Point"}
}