{
  "type": "Feature",
  "properties": {
    "addr:full":"De Hoeven 15 Hamont-achel Limburg 3930",
    "addr:housenumber":"15",
    "addr:postcode":"3930",
    "addr:street":"De Hoeven",
    "iso:country":"BE",
    "sg:address":"De Hoeven 15",
    "sg:city":"Hamont-achel",
    "sg:orig_category":"Brood, gebak and snoepgoed",
    "sg:phone":"+32 11 44 59 95",
    "sg:postcode":"3930",
    "sg:province":"Limburg",
    "wof:name":"Theodoor Van Der Wielen",
    "wof:placetype":"venue"
},
  "geometry": {"coordinates":[5.4821119308,51.2505302429],"type":"Point"}
}