{
  "type": "Feature",
  "properties": {
    "addr:full":"Scottons 200 E Daverdisse Luxembourg 6929",
    "addr:housenumber":"200",
    "addr:postcode":"6929",
    "addr:street":"E",
    "iso:country":"BE",
    "sg:address":"Scottons 200 E",
    "sg:city":"Daverdisse",
    "sg:orig_category":"Charpentes and couvertures",
    "sg:phone":"+32 61 58 81 26",
    "sg:postcode":"6929",
    "sg:province":"Luxembourg",
    "wof:name":"Leyder Bernard",
    "wof:placetype":"venue"
},
  "geometry": {"coordinates":[5.1175727844,50.0223236084],"type":"Point"}
}