{
  "type": "Feature",
  "properties": {
    "iso:country":"BE",
    "sg:address":"Naamsesteenweg 355",
    "sg:city":"Leuven",
    "sg:orig_category":"Algemeen secundair onderwijs",
    "sg:phone":"+32 16 39 90 50",
    "sg:postcode":"3001",
    "sg:province":"Vlaams-Brabant",
    "wof:name":"Lyceum H.hartinstituut",
    "wof:placetype":"venue"
},
  "geometry": {"coordinates":[4.6964211464,50.8582878113],"type":"Point"}
}