{
  "type": "Feature",
  "properties": {
    "iso:country":"BE",
    "sg:address":"Charles De Costerlaan 2b13",
    "sg:city":"Antwerpen",
    "sg:orig_category":"Agences d'exp\u00e9dition",
    "sg:phone":"+32 3 219 08 11",
    "sg:postcode":"2050",
    "sg:province":"Antwerpen",
    "wof:name":"Fa. De Rijcke W. & Co",
    "wof:placetype":"venue"
},
  "geometry": {"coordinates":[4.3877048492,51.2279663086],"type":"Point"}
}