{
  "type": "Feature",
  "properties": {
    "addr:full":"Avenue De Roodebeek 70-74 Bruxelles (schaerbeek) Bruxelles-Capitale 1030",
    "addr:postcode":"70-74;1030",
    "addr:street":"Avenue De Roodebeek",
    "iso:country":"BE",
    "sg:address":"Avenue De Roodebeek 70-74",
    "sg:city":"Bruxelles (schaerbeek)",
    "sg:classifiers":[
        {
            "category":"Professional",
            "subcategory":"Art Services",
            "type":"Services"
        }
    ],
    "sg:phone":"+32 2 741 60 60",
    "sg:postcode":"1030",
    "sg:province":"Bruxelles-Capitale",
    "sg:tags":[
        "-",
        "valuer"
    ],
    "wof:name":"Hotel De Ventes Horta Sa",
    "wof:placetype":"venue"
},
  "geometry": {"coordinates":[4.4000358582,50.8484230042],"type":"Point"}
}