{
  "type": "Feature",
  "properties": {
    "iso:country":"BE",
    "sg:address":"Beekstraat 21",
    "sg:city":"Huldenberg (neerijse)",
    "sg:classifiers":[
        {
            "category":"Utilities",
            "subcategory":"Fuel Oil & Lpg",
            "type":"Services"
        }
    ],
    "sg:phone":"+32 16 47 73 75",
    "sg:postcode":"3040",
    "sg:province":"Vlaams-Brabant",
    "wof:name":"Jorge J",
    "wof:placetype":"venue"
},
  "geometry": {"coordinates":[4.5831818581,50.7890052795],"type":"Point"}
}