{
  "type": "Feature",
  "properties": {
    "addr:full":"Burgemeester Adriaensenlaan 6 Meerhout Antwerpen 2450",
    "addr:housenumber":"6",
    "addr:postcode":"2450",
    "addr:street":"Burgemeester Adriaensenlaan",
    "iso:country":"BE",
    "sg:address":"Burgemeester Adriaensenlaan 6",
    "sg:city":"Meerhout",
    "sg:classifiers":[
        {
            "category":"Bars & Pubs",
            "type":"Food & Drink"
        }
    ],
    "sg:phone":"+32 14 30 36 57",
    "sg:postcode":"2450",
    "sg:province":"Antwerpen",
    "wof:name":"Berg (den)",
    "wof:placetype":"venue"
},
  "geometry": {"coordinates":[5.088766098,51.129486084],"type":"Point"}
}