{
  "type": "Feature",
  "properties": {
    "addr:full":"Nijverheidslaan 38 Maasmechelen Limburg 3630",
    "addr:housenumber":"38",
    "addr:postcode":"3630",
    "addr:street":"Nijverheidslaan",
    "iso:country":"BE",
    "sg:address":"Nijverheidslaan 38",
    "sg:city":"Maasmechelen",
    "sg:orig_category":"V\u00e9hicules automobiles. Entretien and r\u00e9parations de voitures",
    "sg:phone":"+32 89 77 44 97",
    "sg:postcode":"3630",
    "sg:province":"Limburg",
    "wof:name":"Rema-cars",
    "wof:placetype":"venue"
},
  "geometry": {"coordinates":[5.6961350441,50.963848114],"type":"Point"}
}