{
  "type": "Feature",
  "properties": {
    "iso:country":"BE",
    "sg:address":"Paddevijverstraat 58",
    "sg:city":"Ieper",
    "sg:classifiers":[
        {
            "category":"Retail",
            "subcategory":"Auto Repair",
            "type":"Services"
        }
    ],
    "sg:phone":"+32 57 21 71 66",
    "sg:postcode":"8900",
    "sg:province":"West-Vlaanderen",
    "sg:tags":[
        "garage"
    ],
    "wof:name":"Bocar",
    "wof:placetype":"venue"
},
  "geometry": {"coordinates":[2.8845748901,50.8670349121],"type":"Point"}
}