{
  "type": "Feature",
  "properties": {
    "addr:full":"Grotestraat 5 Herne Vlaams-Brabant 1540",
    "addr:housenumber":"5",
    "addr:postcode":"1540",
    "addr:street":"Grotestraat",
    "iso:country":"BE",
    "sg:address":"Grotestraat 5",
    "sg:city":"Herne",
    "sg:orig_category":"Catering and organisation de f\u00eates",
    "sg:phone":"+32 2 396 12 11",
    "sg:postcode":"1540",
    "sg:province":"Vlaams-Brabant",
    "wof:name":"\u00b4t Kaasboetiekje",
    "wof:placetype":"venue"
},
  "geometry": {"coordinates":[4.0300331116,50.7242355347],"type":"Point"}
}