{
  "type": "Feature",
  "properties": {
    "iso:country":"BE",
    "sg:address":"Sparrenstraat 13bb",
    "sg:city":"Zulte",
    "sg:orig_category":"Kapsalons",
    "sg:phone":"+32 9 386 04 10",
    "sg:postcode":"9870",
    "sg:province":"Oost-Vlaanderen",
    "wof:name":"Coiffure Charmy",
    "wof:placetype":"venue"
},
  "geometry": {"coordinates":[3.5066759586,50.9478797913],"type":"Point"}
}