{
  "type": "Feature",
  "properties": {
    "iso:country":"BE",
    "sg:address":"Gentsesteenweg 80",
    "sg:city":"Dendermonde",
    "sg:orig_category":"Herstelling aan huis van elektrische huishoudapparaten",
    "sg:phone":"+32 52 21 53 14",
    "sg:postcode":"9200",
    "sg:province":"Oost-Vlaanderen",
    "wof:name":"Willy De Knop",
    "wof:placetype":"venue"
},
  "geometry": {"coordinates":[4.0869531631,51.0321426392],"type":"Point"}
}