{
  "type": "Feature",
  "properties": {
    "iso:country":"BE",
    "sg:address":"Rue De Marchienne 5",
    "sg:city":"Charleroi",
    "sg:orig_category":"Bagage and lederwaren",
    "sg:phone":"+32 71 30 23 43",
    "sg:postcode":"6000",
    "sg:province":"Hainaut",
    "wof:name":"Daoust-blanke",
    "wof:placetype":"venue"
},
  "geometry": {"coordinates":[4.4406619072,50.4079704285],"type":"Point"}
}