{
  "type": "Feature",
  "properties": {
    "addr:full":"Industriepark Noord 11 Sint-niklaas Oost-Vlaanderen 9100",
    "addr:housenumber":"11",
    "addr:postcode":"9100",
    "addr:street":"Industriepark Noord",
    "iso:country":"BE",
    "sg:address":"Industriepark Noord 11",
    "sg:city":"Sint-niklaas",
    "sg:classifiers":[
        {
            "category":"Freight",
            "type":"Transportation"
        }
    ],
    "sg:phone":"+32 3 780 77 87",
    "sg:postcode":"9100",
    "sg:province":"Oost-Vlaanderen",
    "sg:tags":[
        "-",
        "transport"
    ],
    "wof:name":"Tramaco",
    "wof:placetype":"venue"
},
  "geometry": {"coordinates":[4.1736950874,51.1461410522],"type":"Point"}
}