{
  "type": "Feature",
  "properties": {
    "addr:full":"J. Schranstraat 3 Gent Oost-Vlaanderen 9000",
    "addr:housenumber":"3",
    "addr:postcode":"9000",
    "addr:street":"Schranstraat;Oost-Vlaanderen",
    "iso:country":"BE",
    "sg:address":"J. Schranstraat 3",
    "sg:city":"Gent",
    "sg:orig_category":"Sportclubs",
    "sg:phone":"+32 9 227 81 09",
    "sg:postcode":"9000",
    "sg:province":"Oost-Vlaanderen",
    "wof:name":"Royal Belgian Sailing Club",
    "wof:placetype":"venue"
},
  "geometry": {"coordinates":[3.7015669346,51.0540084839],"type":"Point"}
}