{
  "type": "Feature",
  "properties": {
    "addr:full":"Avenue Du Ch\u00eane 26 Ottignies-louvain-la-neuve (ottignies) Brabant Wallon 1340",
    "addr:housenumber":"26",
    "addr:postcode":"ottignies-louvain-la-neuve;1340",
    "addr:street":"Avenue Du Che\u0302Ne",
    "iso:country":"BE",
    "sg:address":"Avenue Du Ch\u00eane 26",
    "sg:city":"Ottignies-louvain-la-neuve (ottignies)",
    "sg:classifiers":[
        {
            "category":"Professional",
            "subcategory":"Accounting & Tax Preparation",
            "type":"Services"
        }
    ],
    "sg:phone":"+32 10 41 32 70",
    "sg:postcode":"1340",
    "sg:province":"Brabant Wallon",
    "sg:tags":[
        "accountant"
    ],
    "wof:name":"Bpi-verhaeghe & Cie Scfa",
    "wof:placetype":"venue"
},
  "geometry": {"coordinates":[4.5792918205,50.6723594666],"type":"Point"}
}