{
  "type": "Feature",
  "properties": {
    "addr:full":"Vier Linden 1p Kortrijk (heule) West-Vlaanderen 8501",
    "addr:housenumber":"1p",
    "addr:postcode":"8501",
    "addr:street":"Linden",
    "iso:country":"BE",
    "sg:address":"Vier Linden 1p",
    "sg:city":"Kortrijk (heule)",
    "sg:classifiers":[
        {
            "category":"Restaurant",
            "type":"Food & Drink"
        }
    ],
    "sg:phone":"+32 56 35 97 71",
    "sg:postcode":"8501",
    "sg:province":"West-Vlaanderen",
    "sg:tags":[
        "industrial",
        "kitchen",
        "catering"
    ],
    "wof:name":"Hoste-delikor",
    "wof:placetype":"venue"
},
  "geometry": {"coordinates":[3.2419490814,50.8489646912],"type":"Point"}
}