{
  "type": "Feature",
  "properties": {
    "addr:full":"Campanileplein 28 Bruxelles (woluwe-saint-lambert) Bruxelles-Capitale 1200",
    "addr:housenumber":"28",
    "addr:postcode":"1200",
    "addr:street":"Campanileplein",
    "iso:country":"BE",
    "sg:address":"Campanileplein 28",
    "sg:city":"Bruxelles (woluwe-saint-lambert)",
    "sg:classifiers":[
        {
            "category":"Social Services",
            "type":"Services"
        }
    ],
    "sg:phone":"+32 2 771 91 14",
    "sg:postcode":"1200",
    "sg:province":"Bruxelles-Capitale",
    "sg:tags":[
        "handicapped",
        "-"
    ],
    "wof:name":"Famisol",
    "wof:placetype":"venue"
},
  "geometry": {"coordinates":[4.4504599571,50.8485908508],"type":"Point"}
}