{
  "type": "Feature",
  "properties": {
    "iso:country":"BE",
    "sg:address":"Huidevettersstraat 42b",
    "sg:city":"Antwerpen",
    "sg:orig_category":"V\u00eatements pour b\u00e9b\u00e9s and enfants. Maroquinerie and articles de voyage. Chaussures. Souvenirs and obj",
    "sg:phone":"+32 3 213 20 52",
    "sg:postcode":"2000",
    "sg:province":"Antwerpen",
    "wof:name":"I Am",
    "wof:placetype":"venue"
},
  "geometry": {"coordinates":[4.405313015,51.216758728],"type":"Point"}
}