{
  "type": "Feature",
  "properties": {
    "iso:country":"BE",
    "sg:address":"Frederik Burvenichstraat 158b",
    "sg:city":"Gent (gentbrugge)",
    "sg:classifiers":[
        {
            "category":"Manufacturing",
            "subcategory":"Rubber & Plastics",
            "type":"Manufacturing & Wholesale Goods"
        }
    ],
    "sg:phone":"+32 9 210 90 90",
    "sg:postcode":"9050",
    "sg:province":"Oost-Vlaanderen",
    "sg:tags":[
        "bag"
    ],
    "wof:name":"Marhill Bvba",
    "wof:placetype":"venue"
},
  "geometry": {"coordinates":[3.7489800453,51.0393600464],"type":"Point"}
}