{
  "type": "Feature",
  "properties": {
    "iso:country":"BE",
    "sg:address":"Olmenstraat 1",
    "sg:city":"Aalst (groot)",
    "sg:orig_category":"Architectes",
    "sg:phone":"+32 53 83 22 25",
    "sg:postcode":"9320",
    "sg:province":"Oost-Vlaanderen",
    "wof:name":"Verdoodt Johan & Partners Architectenbureau",
    "wof:placetype":"venue"
},
  "geometry": {"coordinates":[4.0553851128,50.9209976196],"type":"Point"}
}