{
  "type": "Feature",
  "properties": {
    "iso:country":"BE",
    "sg:address":"J Kennedylaan",
    "sg:city":"Gent",
    "sg:orig_category":"Afbraak- and draineerwerken",
    "sg:phone":"+32 9 342 67 67",
    "sg:postcode":"9042",
    "sg:province":"Oost-Vlaanderen",
    "wof:name":"De Paepe F",
    "wof:placetype":"venue"
},
  "geometry": {"coordinates":[3.8332400322,51.1831855774],"type":"Point"}
}