{
  "type": "Feature",
  "properties": {
    "addr:full":"Avenue Albert I 19 Li\u00e8ge 1 (grivegn\u00e9e) Li\u00e8ge 4030",
    "addr:housenumber":"19;1",
    "addr:postcode":"4030",
    "addr:street":"Avenue Albert I",
    "iso:country":"BE",
    "sg:address":"Avenue Albert I 19",
    "sg:city":"Li\u00e8ge 1 (grivegn\u00e9e)",
    "sg:classifiers":[
        {
            "category":"Retail",
            "subcategory":"Auto Repair",
            "type":"Services"
        }
    ],
    "sg:phone":"+32 4 342 22 47",
    "sg:postcode":"4030",
    "sg:province":"Li\u00e8ge",
    "sg:tags":[
        "garage"
    ],
    "wof:name":"Somville Jl Cars",
    "wof:placetype":"venue"
},
  "geometry": {"coordinates":[5.5982480049,50.6216888428],"type":"Point"}
}