{
  "type": "Feature",
  "properties": {
    "iso:country":"BE",
    "sg:address":"Roelstraat 17a",
    "sg:city":"Zoutleeuw",
    "sg:orig_category":"Goederenvervoer over de weg Huisvuilophaling and -verwerking",
    "sg:phone":"+32 11 58 14 61",
    "sg:postcode":"3440",
    "sg:province":"Vlaams-Brabant",
    "wof:name":"Robert Allard",
    "wof:placetype":"venue"
},
  "geometry": {"coordinates":[5.0791931152,50.8652687073],"type":"Point"}
}