{
  "type": "Feature",
  "properties": {
    "iso:country":"BE",
    "sg:address":"Nieuwe Abelestraat 9",
    "sg:city":"Roeselare",
    "sg:orig_category":"Varkenskwekers",
    "sg:phone":"+32 51 24 41 66",
    "sg:postcode":"8800",
    "sg:province":"West-Vlaanderen",
    "wof:name":"Marc Vermander",
    "wof:placetype":"venue"
},
  "geometry": {"coordinates":[3.1130011082,50.9392166138],"type":"Point"}
}