{
  "type": "Feature",
  "properties": {
    "addr:full":"7 Rue De La Bruy\u00e8re 1350 Orp-jauche 7",
    "addr:housenumber":"7",
    "addr:postcode":"1350",
    "addr:street":"Rue De La Bruye\u0300Re",
    "iso:country":"BE",
    "sg:address":"7",
    "sg:city":"Rue De La Bruy\u00e8re 1350 Orp-jauche",
    "sg:classifiers":[
        {
            "category":"Shopping",
            "subcategory":"Computers & Home Electronics",
            "type":"Retail Goods"
        }
    ],
    "sg:phone":"+32 19 63 38 33",
    "sg:postcode":"7",
    "sg:tags":[
        "equipment",
        "household",
        "electrical",
        "appliance",
        "electronic"
    ],
    "wof:name":"Dalcq Sa Frifri",
    "wof:placetype":"venue"
},
  "geometry": {"coordinates":[4.9241499901,50.6907653809],"type":"Point"}
}