{
  "type": "Feature",
  "properties": {
    "addr:full":"Carton De Wiartlaan 6 Jette/jette Bruxelles-Capitale 1090",
    "addr:housenumber":"6",
    "addr:postcode":"1090",
    "addr:street":"Carton De Wiartlaan",
    "iso:country":"BE",
    "sg:address":"Carton De Wiartlaan 6",
    "sg:city":"Jette/jette",
    "sg:orig_category":"Banken and kredietinstellingen",
    "sg:phone":"+32 2 425 98 46",
    "sg:postcode":"1090",
    "sg:province":"Bruxelles-Capitale",
    "wof:name":"Dexia",
    "wof:placetype":"venue"
},
  "geometry": {"coordinates":[4.3344159126,50.8677444458],"type":"Point"}
}