{
  "type": "Feature",
  "properties": {
    "iso:country":"BE",
    "sg:address":"Rue Des Bois-seigneur-isaac 40",
    "sg:city":"Braine-l`alleud",
    "sg:orig_category":"Diverse bedrijfsbeheeradviesbureaus",
    "sg:phone":"+32 2 386 46 13",
    "sg:postcode":"1421",
    "sg:province":"Brabant Wallon",
    "wof:name":"Polygestion",
    "wof:placetype":"venue"
},
  "geometry": {"coordinates":[4.3399348259,50.658996582],"type":"Point"}
}