{
  "type": "Feature",
  "properties": {
    "addr:full":"La Strale 264 Aubange Luxembourg 6792",
    "addr:housenumber":"264",
    "addr:postcode":"6792",
    "iso:country":"BE",
    "sg:address":"La Strale 264",
    "sg:city":"Aubange",
    "sg:orig_category":"Sportterreinen and installaties behalve sportcentra",
    "sg:phone":"+32 63 67 70 11",
    "sg:postcode":"6792",
    "sg:province":"Luxembourg",
    "wof:name":"Le Cerlce",
    "wof:placetype":"venue"
},
  "geometry": {"coordinates":[5.7251009941,49.591758728],"type":"Point"}
}