{
  "type": "Feature",
  "properties": {
    "addr:full":"Sint-laureysplein 6 Hove Antwerpen 2540",
    "addr:housenumber":"6",
    "addr:postcode":"2540",
    "addr:street":"Sint-Laureysplein",
    "iso:country":"BE",
    "sg:address":"Sint-laureysplein 6",
    "sg:city":"Hove",
    "sg:orig_category":"Postkantoren Verzekeringsmakelaars and experts",
    "sg:phone":"+32 3 455 29 08",
    "sg:postcode":"2540",
    "sg:province":"Antwerpen",
    "wof:name":"De Post",
    "wof:placetype":"venue"
},
  "geometry": {"coordinates":[4.4720392227,51.154258728],"type":"Point"}
}