{
  "type": "Feature",
  "properties": {
    "iso:country":"BE",
    "sg:address":"Hovenierstraat 40",
    "sg:city":"Sint-truiden",
    "sg:classifiers":[
        {
            "category":"Education",
            "subcategory":"Dance Studio",
            "type":"Public Place"
        }
    ],
    "sg:phone":"+32 11 68 56 00",
    "sg:postcode":"3800",
    "sg:province":"Limburg",
    "sg:tags":[
        "school",
        "dancing"
    ],
    "wof:name":"St-truidense Dansclub",
    "wof:placetype":"venue"
},
  "geometry": {"coordinates":[5.1812582016,50.8226013184],"type":"Point"}
}