{
  "type": "Feature",
  "properties": {
    "iso:country":"BE",
    "sg:address":"Rue Sart Laurent 39a-2",
    "sg:city":"Neupr\u00e9 (rotheux-rimi\u00e8re)",
    "sg:classifiers":[
        {
            "category":"Landmark",
            "subcategory":"Memorial",
            "type":"Public Place"
        }
    ],
    "sg:phone":"+32 4 371 41 56",
    "sg:postcode":"4120",
    "sg:province":"Li\u00e8ge",
    "sg:tags":[
        "-",
        "monument"
    ],
    "wof:name":"Haz\u00e9e R",
    "wof:placetype":"venue"
},
  "geometry": {"coordinates":[5.4864020348,50.5385971069],"type":"Point"}
}