{
  "type": "Feature",
  "properties": {
    "iso:country":"BE",
    "sg:address":"Rue Du Ruisseau 23",
    "sg:city":"Montigny-le-tilleul",
    "sg:classifiers":[
        {
            "category":"Professional",
            "subcategory":"Accounting & Tax Preparation",
            "type":"Services"
        }
    ],
    "sg:phone":"+32 71 21 59 66",
    "sg:postcode":"6110",
    "sg:province":"Hainaut",
    "sg:tags":[
        "accountant"
    ],
    "wof:name":"Plennevaux J",
    "wof:placetype":"venue"
},
  "geometry": {"coordinates":[4.4151740074,50.3611984253],"type":"Point"}
}