{
  "type": "Feature",
  "properties": {
    "iso:country":"BE",
    "sg:address":"Industriezone De Bruwaan Pb 75",
    "sg:city":"Oudenaarde",
    "sg:classifiers":[
        {
            "category":"Home & Garden",
            "subcategory":"Building Materials",
            "type":"Retail Goods"
        }
    ],
    "sg:phone":"+32 55 31 61 01",
    "sg:postcode":"9700",
    "sg:province":"Oost-Vlaanderen",
    "sg:tags":[
        "steel",
        "metal",
        "made",
        "door",
        "gate"
    ],
    "wof:name":"Nassau Door Nv",
    "wof:placetype":"venue"
},
  "geometry": {"coordinates":[3.6044800282,50.869430542],"type":"Point"}
}