{
  "type": "Feature",
  "properties": {
    "iso:country":"BE",
    "sg:address":"Koning Albertlaan 272",
    "sg:city":"Sint-agatha-berchem/berchem-sainte-agathe",
    "sg:classifiers":[
        {
            "category":"Bars & Pubs",
            "subcategory":"Nightclub",
            "type":"Food & Drink"
        }
    ],
    "sg:phone":"+32 2 469 37 16",
    "sg:postcode":"1082",
    "sg:province":"Bruxelles-Capitale",
    "sg:tags":[
        "nachtclubs",
        "dancing"
    ],
    "wof:name":"Le Diodon",
    "wof:placetype":"venue"
},
  "geometry": {"coordinates":[4.2820339203,50.8668365479],"type":"Point"}
}