{
  "type": "Feature",
  "properties": {
    "iso:country":"BE",
    "sg:address":"Avenue Des Gen\u00eats 2",
    "sg:city":"Beaumont (barben\u00e7on)",
    "sg:classifiers":[
        {
            "category":"Real Estate",
            "subcategory":"Real Estate Services",
            "type":"Services"
        }
    ],
    "sg:phone":"+32 71 65 19 36",
    "sg:postcode":"6500",
    "sg:province":"Hainaut",
    "wof:name":"Design Immo Sprl",
    "wof:placetype":"venue"
},
  "geometry": {"coordinates":[4.3062648773,50.226360321],"type":"Point"}
}