{
  "type": "Feature",
  "properties": {
    "iso:country":"BE",
    "sg:address":"Grand\u00b4route 98",
    "sg:city":"Braine-l\u00b4alleud",
    "sg:orig_category":"Eclairage et \u00e9quipements du foyer. Meubles D\u00e9taillants, Am\u00e9nagement de B\u00e2timents et de Cuisines",
    "sg:phone":"+32 2 384 44 97",
    "sg:postcode":"1428",
    "sg:province":"Brabant Wallon",
    "wof:name":"Aux Bois De Mai",
    "wof:placetype":"venue"
},
  "geometry": {"coordinates":[4.3644099236,50.6426200867],"type":"Point"}
}