{
  "type": "Feature",
  "properties": {
    "addr:full":"Chauss\u00e9e De Louvain 279 Box 1 Waterloo Brabant Wallon 1410",
    "addr:housenumber":"279;1",
    "addr:postcode":"1410",
    "addr:street":"Chausse\u0301E De Louvain;Box",
    "iso:country":"BE",
    "sg:address":"Chauss\u00e9e De Louvain 279 Box 1",
    "sg:city":"Waterloo",
    "sg:classifiers":[
        {
            "category":"Shopping",
            "subcategory":"Clothing, Apparel, & Fashions",
            "type":"Retail Goods"
        }
    ],
    "sg:phone":"+32 2 351 38 21",
    "sg:postcode":"1410",
    "sg:province":"Brabant Wallon",
    "sg:tags":[
        "lady",
        "clothing",
        "-"
    ],
    "wof:name":"Megalou",
    "wof:placetype":"venue"
},
  "geometry": {"coordinates":[4.4264512062,50.7017364502],"type":"Point"}
}