{
  "type": "Feature",
  "properties": {
    "addr:full":"Verheydenstraat 65 Dilbeek Vlaams-Brabant 1700",
    "addr:housenumber":"65",
    "addr:postcode":"1700",
    "addr:street":"Verheydenstraat",
    "iso:country":"BE",
    "sg:address":"Verheydenstraat 65",
    "sg:city":"Dilbeek",
    "sg:classifiers":[
        {
            "category":"Health Services",
            "subcategory":"Doctor",
            "type":"Services"
        }
    ],
    "sg:phone":"+32 2 569 45 54",
    "sg:postcode":"1700",
    "sg:province":"Vlaams-Brabant",
    "sg:tags":[
        "medicinephysicians",
        "surgeon"
    ],
    "wof:name":"De Smet Th",
    "wof:placetype":"venue"
},
  "geometry": {"coordinates":[4.2610721588,50.8438491821],"type":"Point"}
}