{
  "type": "Feature",
  "properties": {
    "addr:full":"Schoendonck 13 Borsbeek Antwerpen 2150",
    "addr:housenumber":"13",
    "addr:postcode":"2150",
    "addr:street":"Schoendonck",
    "iso:country":"BE",
    "sg:address":"Schoendonck 13",
    "sg:city":"Borsbeek",
    "sg:orig_category":"Producteurs de l\u00e9gumes",
    "sg:phone":"+32 3 321 11 95",
    "sg:postcode":"2150",
    "sg:province":"Antwerpen",
    "wof:name":"Herlian",
    "wof:placetype":"venue"
},
  "geometry": {"coordinates":[4.5035090446,51.1843833923],"type":"Point"}
}