{
  "type": "Feature",
  "properties": {
    "iso:country":"BE",
    "sg:address":"Rue Dieudonn\u00c9 Tossens 6",
    "sg:city":"Hannut",
    "sg:orig_category":"Woningbouw",
    "sg:phone":"+32 19 51 25 27",
    "sg:postcode":"4280",
    "sg:province":"Li\u00e8ge",
    "wof:name":"Czeslaw Zurawski",
    "wof:placetype":"venue"
},
  "geometry": {"coordinates":[5.1236400604,50.6980895996],"type":"Point"}
}