{
  "type": "Feature",
  "properties": {
    "iso:country":"BE",
    "sg:address":"Rue Du Calvaire 148",
    "sg:city":"Charleroi",
    "sg:orig_category":"Fleurs and plantes",
    "sg:phone":"+32 71 32 12 59",
    "sg:postcode":"6031",
    "sg:province":"Hainaut",
    "wof:name":"Ibiza",
    "wof:placetype":"venue"
},
  "geometry": {"coordinates":[4.4802131653,50.4075660706],"type":"Point"}
}