{
  "type": "Feature",
  "properties": {
    "addr:full":"N\u00c9blon-le-pierreux 25 Ouffet Li\u00e8ge 4590",
    "addr:housenumber":"25",
    "addr:postcode":"4590",
    "addr:street":"Ne\u0301Blon-Le-Pierreux",
    "iso:country":"BE",
    "sg:address":"N\u00c9blon-le-pierreux 25",
    "sg:city":"Ouffet",
    "sg:classifiers":[
        {
            "category":"Food & Beverages",
            "subcategory":"Fruits & Vegetables",
            "type":"Retail Goods"
        }
    ],
    "sg:phone":"+32 86 38 94 31",
    "sg:postcode":"4590",
    "sg:province":"Li\u00e8ge",
    "sg:tags":[
        "l\u00e9gumes",
        "gr"
    ],
    "wof:name":"Centrale Du Frais",
    "wof:placetype":"venue"
},
  "geometry": {"coordinates":[5.5063538551,50.4253120422],"type":"Point"}
}