{
  "type": "Feature",
  "properties": {
    "addr:full":"Baaistraat 74 Kortenaken Vlaams-Brabant 3470",
    "addr:housenumber":"74",
    "addr:postcode":"3470",
    "addr:street":"Baaistraat",
    "iso:country":"BE",
    "sg:address":"Baaistraat 74",
    "sg:city":"Kortenaken",
    "sg:orig_category":"Drukkerijen and copyshops",
    "sg:phone":"+32 11 58 73 00",
    "sg:postcode":"3470",
    "sg:province":"Vlaams-Brabant",
    "wof:name":"Drukkerij Hoebreckx",
    "wof:placetype":"venue"
},
  "geometry": {"coordinates":[5.0369138718,50.8902854919],"type":"Point"}
}