{
  "type": "Feature",
  "properties": {
    "addr:full":"Ottergemsesteenweg 28 Gent Oost-Vlaanderen 9000",
    "addr:housenumber":"28",
    "addr:postcode":"9000",
    "addr:street":"Ottergemsesteenweg;Oost-Vlaanderen",
    "iso:country":"BE",
    "sg:address":"Ottergemsesteenweg 28",
    "sg:city":"Gent",
    "sg:classifiers":[
        {
            "category":"Communications",
            "type":"Services"
        }
    ],
    "sg:phone":"+32 9 220 79 15",
    "sg:postcode":"9000",
    "sg:province":"Oost-Vlaanderen",
    "sg:tags":[
        "translator"
    ],
    "wof:name":"De Rycke R",
    "wof:placetype":"venue"
},
  "geometry": {"coordinates":[3.7271618843,51.0363197327],"type":"Point"}
}