{
  "type": "Feature",
  "properties": {
    "iso:country":"BE",
    "sg:address":"Meenseweg 401",
    "sg:city":"Ieper",
    "sg:orig_category":"Cr\u00e9meries. Eleveurs de bovins",
    "sg:phone":"+32 57 20 26 61",
    "sg:postcode":"8902",
    "sg:province":"West-Vlaanderen",
    "wof:name":"De Boterhoeve",
    "wof:placetype":"venue"
},
  "geometry": {"coordinates":[2.921049118,50.8484954834],"type":"Point"}
}