{
  "type": "Feature",
  "properties": {
    "addr:full":"Stationsstraat 39 Sint-niklaas Oost-Vlaanderen 9100",
    "addr:housenumber":"39",
    "addr:postcode":"9100",
    "addr:street":"Stationsstraat",
    "iso:country":"BE",
    "sg:address":"Stationsstraat 39",
    "sg:city":"Sint-niklaas",
    "sg:orig_category":"Eclairage et \u00e9quipements du foyer. Souvenirs and objets artisanaux",
    "sg:phone":"+32 3 776 89 08",
    "sg:postcode":"9100",
    "sg:province":"Oost-Vlaanderen",
    "wof:name":"Casa",
    "wof:placetype":"venue"
},
  "geometry": {"coordinates":[4.1418571472,51.1662902832],"type":"Point"}
}