{
  "type": "Feature",
  "properties": {
    "addr:full":"Breulstraat 84 Moorslede West-Vlaanderen 8890",
    "addr:housenumber":"84",
    "addr:postcode":"8890",
    "addr:street":"Breulstraat",
    "iso:country":"BE",
    "sg:address":"Breulstraat 84",
    "sg:city":"Moorslede",
    "sg:orig_category":"Instituts de beaut\u00e9",
    "sg:phone":"+32 51 77 70 68",
    "sg:postcode":"8890",
    "sg:province":"West-Vlaanderen",
    "wof:name":"Carine Beernaert",
    "wof:placetype":"venue"
},
  "geometry": {"coordinates":[3.072040081,50.8891983032],"type":"Point"}
}