{
  "type": "Feature",
  "properties": {
    "addr:full":"Grote Moerstraat 89 Brugge (sint-andries) West-Vlaanderen 8200",
    "addr:housenumber":"89",
    "addr:postcode":"8200",
    "addr:street":"Grote Moerstraat",
    "iso:country":"BE",
    "sg:address":"Grote Moerstraat 89",
    "sg:city":"Brugge (sint-andries)",
    "sg:classifiers":[
        {
            "category":"Professional",
            "subcategory":"Engineering",
            "type":"Services"
        }
    ],
    "sg:phone":"+32 50 32 03 71",
    "sg:postcode":"8200",
    "sg:province":"West-Vlaanderen",
    "sg:tags":[
        "technical",
        "equipment",
        "offices-"
    ],
    "wof:name":"De Klerck Nv",
    "wof:placetype":"venue"
},
  "geometry": {"coordinates":[3.1575660706,51.2068481445],"type":"Point"}
}