{
  "type": "Feature",
  "properties": {
    "iso:country":"BE",
    "sg:address":"Rue Des Carri\u00c8res 24",
    "sg:city":"Perwez",
    "sg:orig_category":"Ordinateurs and \u00e9quipement informatique. Entretien and r\u00e9parations de machines de bureau and ordinat",
    "sg:phone":"+32 81 65 92 28",
    "sg:postcode":"1360",
    "sg:province":"Brabant Wallon",
    "wof:name":"Acura Computer",
    "wof:placetype":"venue"
},
  "geometry": {"coordinates":[4.811548233,50.6260490417],"type":"Point"}
}