{
  "type": "Feature",
  "properties": {
    "addr:full":"Rue D'hasti\u00c8re 7 Houyet Namur 5560",
    "addr:housenumber":"7",
    "addr:postcode":"5560",
    "addr:street":"Rue D'Hastie \u0300Re",
    "iso:country":"BE",
    "sg:address":"Rue D'hasti\u00c8re 7",
    "sg:city":"Houyet",
    "sg:orig_category":"Pain, p\u00e2tisseries and confiseries",
    "sg:phone":"+32 82 74 43 91",
    "sg:postcode":"5560",
    "sg:province":"Namur",
    "wof:name":"Christian Plaquette",
    "wof:placetype":"venue"
},
  "geometry": {"coordinates":[4.8844442368,50.1679840088],"type":"Point"}
}