{
  "type": "Feature",
  "properties": {
    "addr:full":"Genebroekstraat 92 Beringen (beverlo) Limburg 3581",
    "addr:housenumber":"92",
    "addr:postcode":"3581",
    "addr:street":"Genebroekstraat",
    "iso:country":"BE",
    "sg:address":"Genebroekstraat 92",
    "sg:city":"Beringen (beverlo)",
    "sg:classifiers":[
        {
            "category":"Building & Trades",
            "subcategory":"Construction",
            "type":"Services"
        }
    ],
    "sg:phone":"+32 11 40 30 35",
    "sg:postcode":"3581",
    "sg:province":"Limburg",
    "sg:tags":[
        "ceiling"
    ],
    "wof:name":"Santermans Totaal-afwerking Bvba",
    "wof:placetype":"venue"
},
  "geometry": {"coordinates":[5.2228298187,51.0881996155],"type":"Point"}
}