{
  "type": "Feature",
  "properties": {
    "addr:full":"Omselweg 30 Bree Limburg 3960",
    "addr:housenumber":"30",
    "addr:postcode":"3960",
    "addr:street":"Omselweg",
    "iso:country":"BE",
    "sg:address":"Omselweg 30",
    "sg:city":"Bree",
    "sg:orig_category":"Loodgieterij, verwarming and sanitaire installaties",
    "sg:phone":"+32 89 86 83 43",
    "sg:postcode":"3960",
    "sg:province":"Limburg",
    "wof:name":"Winand Schulpen",
    "wof:placetype":"venue"
},
  "geometry": {"coordinates":[5.5944190025,51.1405677795],"type":"Point"}
}