{
  "type": "Feature",
  "properties": {
    "iso:country":"BE",
    "sg:address":"Rue Du Progr\u00e8s 55",
    "sg:city":"Bi\u00e8vre (graide)",
    "sg:classifiers":[
        {
            "category":"Professional",
            "subcategory":"Accounting & Tax Preparation",
            "type":"Services"
        }
    ],
    "sg:phone":"+32 61 29 22 77",
    "sg:postcode":"5555",
    "sg:province":"Namur",
    "sg:tags":[
        "bookkeeper"
    ],
    "wof:name":"Bureau Comptable & Fiscal Taquin Philippe",
    "wof:placetype":"venue"
},
  "geometry": {"coordinates":[5.0489249229,49.9380645752],"type":"Point"}
}