{
  "type": "Feature",
  "properties": {
    "addr:full":"Rue Du Centre 132 Frameries (eugies) Hainaut 7080",
    "addr:housenumber":"132",
    "addr:postcode":"7080",
    "addr:street":"Rue Du Centre",
    "iso:country":"BE",
    "sg:address":"Rue Du Centre 132",
    "sg:city":"Frameries (eugies)",
    "sg:classifiers":[
        {
            "category":"Retail",
            "subcategory":"Auto Repair",
            "type":"Services"
        }
    ],
    "sg:phone":"+32 65 67 30 82",
    "sg:postcode":"7080",
    "sg:province":"Hainaut",
    "sg:tags":[
        "garage"
    ],
    "wof:name":"Garage Du Centre Sa",
    "wof:placetype":"venue"
},
  "geometry": {"coordinates":[3.9013249874,50.4052352905],"type":"Point"}
}