{
  "type": "Feature",
  "properties": {
    "iso:country":"BE",
    "sg:address":"Boulevard Pierre Mayence 19",
    "sg:city":"Charleroi",
    "sg:orig_category":"Advocaten and juridische adviseurs",
    "sg:phone":"+32 71 30 00 66",
    "sg:postcode":"6000",
    "sg:province":"Hainaut",
    "wof:name":"Xavier Culot",
    "wof:placetype":"venue"
},
  "geometry": {"coordinates":[4.4524869919,50.40858078],"type":"Point"}
}