{
  "type": "Feature",
  "properties": {
    "addr:full":"Rue Des Martyrs 28 Verviers Li\u00e8ge 4800",
    "addr:housenumber":"28",
    "addr:postcode":"4800",
    "addr:street":"Rue Des Martyrs",
    "iso:country":"BE",
    "sg:address":"Rue Des Martyrs 28",
    "sg:city":"Verviers",
    "sg:orig_category":"Notaires",
    "sg:phone":"+32 87 33 13 92",
    "sg:postcode":"4800",
    "sg:province":"Li\u00e8ge",
    "wof:name":"S. Lilien",
    "wof:placetype":"venue"
},
  "geometry": {"coordinates":[5.8626050949,50.591758728],"type":"Point"}
}