{
  "type": "Feature",
  "properties": {
    "iso:country":"BE",
    "sg:address":"Izegemstraat 75 B",
    "sg:city":"Roeselare",
    "sg:orig_category":"HUISBRANDOLIE",
    "sg:phone":"+32 51 22 82 64",
    "sg:postcode":"8800",
    "sg:province":"West-Vlaanderen",
    "wof:name":"Hedwig Dewulf",
    "wof:placetype":"venue"
},
  "geometry": {"coordinates":[3.1647679806,50.9315605164],"type":"Point"}
}