{
  "type": "Feature",
  "properties": {
    "iso:country":"BE",
    "sg:address":"Avenue De L'expansion 14",
    "sg:city":"Ans",
    "sg:orig_category":"Pi\u00e8ces and accessoires de v\u00e9hicules automobiles Gr",
    "sg:phone":"+32 4 246 43 43",
    "sg:postcode":"4432",
    "sg:province":"Li\u00e8ge",
    "wof:name":"Verviers Freins",
    "wof:placetype":"venue"
},
  "geometry": {"coordinates":[5.5242800713,50.6659317017],"type":"Point"}
}