{
  "type": "Feature",
  "properties": {
    "addr:full":"Chauss\u00e9e De Namur 64 Nivelles Brabant Wallon 1400",
    "addr:housenumber":"64",
    "addr:postcode":"1400",
    "addr:street":"Chausse\u0301E De Namur",
    "iso:country":"BE",
    "sg:address":"Chauss\u00e9e De Namur 64",
    "sg:city":"Nivelles",
    "sg:classifiers":[
        {
            "category":"Transit Center",
            "subcategory":"Freight",
            "type":"Transportation"
        }
    ],
    "sg:postcode":"1400",
    "sg:province":"Brabant Wallon",
    "sg:tags":[
        "tackle"
    ],
    "wof:name":"Parmentier",
    "wof:placetype":"venue"
},
  "geometry": {"coordinates":[4.3647999763,50.5953292847],"type":"Point"}
}