{
  "type": "Feature",
  "properties": {
    "iso:country":"BE",
    "sg:address":"Avenue Joseph Abras 67",
    "sg:city":"Namur (belgrade)",
    "sg:classifiers":[
        {
            "category":"Banks & Credit Unions",
            "subcategory":"Financial Services",
            "type":"Services"
        }
    ],
    "sg:phone":"+32 81 73 49 00",
    "sg:postcode":"5001",
    "sg:province":"Namur",
    "sg:tags":[
        "loan",
        "mortgage"
    ],
    "wof:name":"Centra-finance Sa",
    "wof:placetype":"venue"
},
  "geometry": {"coordinates":[4.8257050514,50.4722557068],"type":"Point"}
}