{
  "type": "Feature",
  "properties": {
    "addr:full":"Henri Dunantlaan 5 Gent Oost-Vlaanderen 9000",
    "addr:housenumber":"5",
    "addr:postcode":"9000",
    "addr:street":"Henri Dunantlaan;Oost-Vlaanderen",
    "iso:country":"BE",
    "sg:address":"Henri Dunantlaan 5",
    "sg:city":"Gent",
    "sg:orig_category":"Ambulances. Cliniques and h\u00f4pitaux",
    "sg:phone":"+32 9 224 71 11",
    "sg:postcode":"9000",
    "sg:province":"Oost-Vlaanderen",
    "wof:name":"A.z. Jan Palfijn Gent",
    "wof:placetype":"venue"
},
  "geometry": {"coordinates":[3.7016739845,51.0497741699],"type":"Point"}
}