{
  "type": "Feature",
  "properties": {
    "iso:country":"BE",
    "sg:address":"Dodepaardenstraat 58",
    "sg:city":"Diksmuide",
    "sg:orig_category":"Eleveurs and marchands de porcs. Eleveurs de bovins",
    "sg:phone":"+32 51 50 12 04",
    "sg:postcode":"8600",
    "sg:province":"West-Vlaanderen",
    "wof:name":"'t Dishof",
    "wof:placetype":"venue"
},
  "geometry": {"coordinates":[2.8926780224,51.072933197],"type":"Point"}
}