{
  "type": "Feature",
  "properties": {
    "addr:full":"Overpoortstraat 17 Gent Oost-Vlaanderen 9000",
    "addr:housenumber":"17",
    "addr:postcode":"9000",
    "addr:street":"Overpoortstraat;Oost-Vlaanderen",
    "iso:country":"BE",
    "sg:address":"Overpoortstraat 17",
    "sg:city":"Gent",
    "sg:classifiers":[
        {
            "category":"Cafe",
            "type":"Food & Drink"
        }
    ],
    "sg:phone":"+32 9 221 62 52",
    "sg:postcode":"9000",
    "sg:province":"Oost-Vlaanderen",
    "sg:tags":[
        "caf\u00e9s"
    ],
    "wof:name":"P\u00c8re Total",
    "wof:placetype":"venue"
},
  "geometry": {"coordinates":[3.7257919312,51.0402145386],"type":"Point"}
}