{
  "type": "Feature",
  "properties": {
    "iso:country":"BE",
    "sg:address":"Leopoldsvaart-oost 1",
    "sg:city":"Damme",
    "sg:orig_category":"Gespecialiseerde niet-residenti\u00eble bouw Landbouwmachines Gh",
    "sg:phone":"+32 50 50 01 76",
    "sg:postcode":"8340",
    "sg:province":"West-Vlaanderen",
    "wof:name":"Patrick Debruyckere",
    "wof:placetype":"venue"
},
  "geometry": {"coordinates":[3.2657039165,51.2929496765],"type":"Point"}
}