{
  "type": "Feature",
  "properties": {
    "addr:full":"Begijnhoeve 6 Antwerpen Antwerpen 2040",
    "addr:housenumber":"6",
    "addr:postcode":"2040",
    "addr:street":"Begijnhoeve",
    "iso:country":"BE",
    "sg:address":"Begijnhoeve 6",
    "sg:city":"Antwerpen",
    "sg:orig_category":"Enseignement maternel and primaire",
    "sg:phone":"+32 3 568 78 02",
    "sg:postcode":"2040",
    "sg:province":"Antwerpen",
    "wof:name":"Vrije Lagere School",
    "wof:placetype":"venue"
},
  "geometry": {"coordinates":[4.3141150475,51.3429756165],"type":"Point"}
}