{
  "type": "Feature",
  "properties": {
    "iso:country":"BE",
    "sg:address":"Rue De Montegn\u00e9e 1",
    "sg:city":"Saint-nicolas",
    "sg:classifiers":[
        {
            "category":"Shopping",
            "subcategory":"Florist",
            "type":"Retail Goods"
        }
    ],
    "sg:phone":"+32 4 226 78 08",
    "sg:postcode":"4420",
    "sg:province":"Li\u00e8ge",
    "wof:name":"Karaman",
    "wof:placetype":"venue"
},
  "geometry": {"coordinates":[5.5356869698,50.6398925781],"type":"Point"}
}