{
  "type": "Feature",
  "properties": {
    "addr:full":"Rue Croix Renkin 9 Tellin Luxembourg 6927",
    "addr:housenumber":"9",
    "addr:postcode":"6927",
    "addr:street":"Rue Croix Renkin",
    "iso:country":"BE",
    "sg:address":"Rue Croix Renkin 9",
    "sg:city":"Tellin",
    "sg:orig_category":"Paardenfokkers",
    "sg:phone":"+32 84 36 63 59",
    "sg:postcode":"6927",
    "sg:province":"Luxembourg",
    "wof:name":"Lannoy M.",
    "wof:placetype":"venue"
},
  "geometry": {"coordinates":[5.2646131516,50.0859184265],"type":"Point"}
}