{
  "type": "Feature",
  "properties": {
    "iso:country":"BE",
    "sg:address":"Ter Eyckenstraat 2",
    "sg:city":"Zaventem (sint-stevens-woluwe)",
    "sg:classifiers":[
        {
            "category":"Home & Garden",
            "subcategory":"Home Furnishings",
            "type":"Retail Goods"
        }
    ],
    "sg:phone":"+32 2 721 36 53",
    "sg:postcode":"1932",
    "sg:province":"Vlaams-Brabant",
    "sg:tags":[
        "interior",
        "decoration"
    ],
    "wof:name":"Marzys D",
    "wof:placetype":"venue"
},
  "geometry": {"coordinates":[4.4572710991,50.8535270691],"type":"Point"}
}