{
  "type": "Feature",
  "properties": {
    "addr:full":"Rue Lambert Dewonck 202 Ans Li\u00e8ge 4432",
    "addr:housenumber":"202",
    "addr:postcode":"4432",
    "addr:street":"Rue Lambert Dewonck",
    "iso:country":"BE",
    "sg:address":"Rue Lambert Dewonck 202",
    "sg:city":"Ans",
    "sg:classifiers":[
        {
            "category":"Arena",
            "subcategory":"Sports Club",
            "type":"Entertainment"
        }
    ],
    "sg:phone":"+32 4 246 00 20",
    "sg:postcode":"4432",
    "sg:province":"Li\u00e8ge",
    "sg:tags":[
        "terrain",
        "hors",
        "de",
        "installation",
        "sportifs"
    ],
    "wof:name":"R. Hodeige Union",
    "wof:placetype":"venue"
},
  "geometry": {"coordinates":[5.512635231,50.6652336121],"type":"Point"}
}