{
  "type": "Feature",
  "properties": {
    "addr:full":"Weeltjens 9-2 Antwerpen Antwerpen 2040",
    "addr:housenumber":"9-2",
    "addr:postcode":"2040",
    "addr:street":"Weeltjens",
    "iso:country":"BE",
    "sg:address":"Weeltjens 9-2",
    "sg:city":"Antwerpen",
    "sg:classifiers":[
        {
            "category":"Building & Trades",
            "subcategory":"Electrical",
            "type":"Services"
        }
    ],
    "sg:phone":"+32 3 569 01 51",
    "sg:postcode":"2040",
    "sg:province":"Antwerpen",
    "sg:tags":[
        "electric",
        "-",
        "housewiring",
        "contractor"
    ],
    "wof:name":"Electro Hahn Patrick",
    "wof:placetype":"venue"
},
  "geometry": {"coordinates":[4.3328919411,51.3738708496],"type":"Point"}
}