{
  "type": "Feature",
  "properties": {
    "addr:full":"Place Verte 23 Florennes Namur 5620",
    "addr:housenumber":"23",
    "addr:postcode":"5620",
    "addr:street":"Place Verte",
    "iso:country":"BE",
    "sg:address":"Place Verte 23",
    "sg:city":"Florennes",
    "sg:classifiers":[
        {
            "category":"Health Services",
            "subcategory":"Hospital",
            "type":"Services"
        }
    ],
    "sg:phone":"+32 71 68 85 50",
    "sg:postcode":"5620",
    "sg:province":"Namur",
    "wof:name":"Centre Medical De Florennes",
    "wof:placetype":"venue"
},
  "geometry": {"coordinates":[4.6057500839,50.2494316101],"type":"Point"}
}