{
  "type": "Feature",
  "properties": {
    "addr:full":"Kruisekestraat 90 Wervik West-Vlaanderen 8940",
    "addr:housenumber":"90",
    "addr:postcode":"8940",
    "addr:street":"Kruisekestraat",
    "iso:country":"BE",
    "sg:address":"Kruisekestraat 90",
    "sg:city":"Wervik",
    "sg:orig_category":"Boucheries",
    "sg:phone":"+32 56 31 19 20",
    "sg:postcode":"8940",
    "sg:province":"West-Vlaanderen",
    "wof:name":"Francky Pannecoucque",
    "wof:placetype":"venue"
},
  "geometry": {"coordinates":[3.0227100849,50.814289093],"type":"Point"}
}