{
  "type": "Feature",
  "properties": {
    "iso:country":"BE",
    "sg:address":"Kunstdal 8",
    "sg:city":"Eeklo",
    "sg:classifiers":[
        {
            "category":"Home & Garden",
            "subcategory":"Building Materials",
            "type":"Retail Goods"
        }
    ],
    "sg:phone":"+32 53 83 09 57",
    "sg:postcode":"9900",
    "sg:province":"Oost-Vlaanderen",
    "sg:tags":[
        "aluminium",
        "window"
    ],
    "wof:name":"Devico Nv",
    "wof:placetype":"venue"
},
  "geometry": {"coordinates":[4.0326151848,50.9124679565],"type":"Point"}
}