{
  "type": "Feature",
  "properties": {
    "iso:country":"BE",
    "sg:address":"Rutterweg 16",
    "sg:city":"Tongeren",
    "sg:classifiers":[
        {
            "category":"Retail",
            "subcategory":"Auto Repair",
            "type":"Services"
        }
    ],
    "sg:phone":"+32 12 23 29 49",
    "sg:postcode":"3700",
    "sg:province":"Limburg",
    "sg:tags":[
        "automobile-body"
    ],
    "wof:name":"Smets B",
    "wof:placetype":"venue"
},
  "geometry": {"coordinates":[5.460837841,50.7711410522],"type":"Point"}
}