{
  "type": "Feature",
  "properties": {
    "addr:full":"Berkenmei 14a Vosselaar Antwerpen 2350",
    "addr:housenumber":"14a",
    "addr:postcode":"2350",
    "addr:street":"Berkenmei",
    "iso:country":"BE",
    "sg:address":"Berkenmei 14a",
    "sg:city":"Vosselaar",
    "sg:classifiers":[
        {
            "category":"Personal",
            "subcategory":"Beauty Salon",
            "type":"Services"
        }
    ],
    "sg:phone":"+32 14 61 40 46",
    "sg:postcode":"2350",
    "sg:province":"Antwerpen",
    "sg:tags":[
        "lady",
        "-",
        "hairdressing"
    ],
    "wof:name":"Diane",
    "wof:placetype":"venue"
},
  "geometry": {"coordinates":[4.8792572021,51.3188056946],"type":"Point"}
}