{
  "type": "Feature",
  "properties": {
    "addr:full":"Abdijstraat 86 Antwerpen Antwerpen 2020",
    "addr:housenumber":"86",
    "addr:postcode":"2020",
    "addr:street":"Abdijstraat",
    "iso:country":"BE",
    "sg:address":"Abdijstraat 86",
    "sg:city":"Antwerpen",
    "sg:orig_category":"Industri\u00eble wasserijen and droogkuis",
    "sg:phone":"+32 3 237 87 05",
    "sg:postcode":"2020",
    "sg:province":"Antwerpen",
    "wof:name":"Pressing No 1",
    "wof:placetype":"venue"
},
  "geometry": {"coordinates":[4.3808169365,51.1890830994],"type":"Point"}
}