{
  "type": "Feature",
  "properties": {
    "addr:full":"Rue Crouzet 2 Tournai (templeuve) Hainaut 7520",
    "addr:housenumber":"2",
    "addr:postcode":"7520",
    "addr:street":"Rue Crouzet",
    "iso:country":"BE",
    "sg:address":"Rue Crouzet 2",
    "sg:city":"Tournai (templeuve)",
    "sg:classifiers":[
        {
            "category":"Real Estate",
            "subcategory":"Architect",
            "type":"Services"
        }
    ],
    "sg:phone":"+32 69 35 19 70",
    "sg:postcode":"7520",
    "sg:province":"Hainaut",
    "wof:name":"Michel F",
    "wof:placetype":"venue"
},
  "geometry": {"coordinates":[3.3104109764,50.6597671509],"type":"Point"}
}