{
  "type": "Feature",
  "properties": {
    "iso:country":"BE",
    "sg:address":"Route D'agimont 83",
    "sg:city":"Doische",
    "sg:classifiers":[
        {
            "category":"Personal",
            "subcategory":"Beauty Salon",
            "type":"Services"
        }
    ],
    "sg:phone":"+32 82 67 84 94",
    "sg:postcode":"5680",
    "sg:province":"Namur",
    "sg:tags":[
        "de",
        "coiffure"
    ],
    "wof:name":"Joelle Henry",
    "wof:placetype":"venue"
},
  "geometry": {"coordinates":[4.7356820107,50.1675262451],"type":"Point"}
}