{
  "type": "Feature",
  "properties": {
    "addr:full":"Rue Du Tilleul 4 Rhode-saint-gen\u00e8se Vlaams-Brabant 1640",
    "addr:housenumber":"4",
    "addr:postcode":"1640",
    "addr:street":"Rue Du Tilleul",
    "iso:country":"BE",
    "sg:address":"Rue Du Tilleul 4",
    "sg:city":"Rhode-saint-gen\u00e8se",
    "sg:classifiers":[
        {
            "category":"Real Estate",
            "subcategory":"Architect",
            "type":"Services"
        }
    ],
    "sg:phone":"+32 2 380 98 03",
    "sg:postcode":"1640",
    "sg:province":"Vlaams-Brabant",
    "wof:name":"Favart G",
    "wof:placetype":"venue"
},
  "geometry": {"coordinates":[4.3479800224,50.7414512634],"type":"Point"}
}