{
  "type": "Feature",
  "properties": {
    "addr:full":"Grote Mereweg 57 Bilzen (eigenbilzen) Limburg 3740",
    "addr:housenumber":"57",
    "addr:postcode":"3740",
    "addr:street":"Grote Mereweg",
    "iso:country":"BE",
    "sg:address":"Grote Mereweg 57",
    "sg:city":"Bilzen (eigenbilzen)",
    "sg:classifiers":[
        {
            "category":"Building & Trades",
            "subcategory":"Landscaping Services",
            "type":"Services"
        }
    ],
    "sg:phone":"+32 89 41 77 53",
    "sg:postcode":"3740",
    "sg:province":"Limburg",
    "sg:tags":[
        "gardening",
        "garden",
        "maintenance"
    ],
    "wof:name":"Reyskens Tuinplanning",
    "wof:placetype":"venue"
},
  "geometry": {"coordinates":[5.5815930367,50.8724098206],"type":"Point"}
}