{
  "type": "Feature",
  "properties": {
    "addr:full":"Rue De L'eglise Saint-gilles 22 Bruxelles (saint-gilles) Bruxelles-Capitale 1060",
    "addr:housenumber":"22",
    "addr:postcode":"1060",
    "addr:street":"Rue De L'Eglise Saint-Gilles",
    "iso:country":"BE",
    "sg:address":"Rue De L'eglise Saint-gilles 22",
    "sg:city":"Bruxelles (saint-gilles)",
    "sg:classifiers":[
        {
            "category":"Shopping",
            "subcategory":"Computers & Home Electronics",
            "type":"Retail Goods"
        }
    ],
    "sg:phone":"+32 2 538 93 60",
    "sg:postcode":"1060",
    "sg:province":"Bruxelles-Capitale",
    "sg:tags":[
        "personal",
        "-",
        "processing",
        "data"
    ],
    "wof:name":"G\u00e9n\u00e9ration Amiga",
    "wof:placetype":"venue"
},
  "geometry": {"coordinates":[4.3425879478,50.8317565918],"type":"Point"}
}