{
  "type": "Feature",
  "properties": {
    "addr:full":"Rue De Brabant 112 Sint-joost-ten-node/saint-josse-ten-noode Bruxelles-Capitale 1210",
    "addr:housenumber":"112",
    "addr:postcode":"1210",
    "addr:street":"Rue De Brabant",
    "iso:country":"BE",
    "sg:address":"Rue De Brabant 112",
    "sg:city":"Sint-joost-ten-node/saint-josse-ten-noode",
    "sg:classifiers":[
        {
            "category":"Manufacturing",
            "subcategory":"Textiles",
            "type":"Manufacturing & Wholesale Goods"
        }
    ],
    "sg:phone":"+32 2 223 16 75",
    "sg:postcode":"1210",
    "sg:province":"Bruxelles-Capitale",
    "wof:name":"Cem Textile",
    "wof:placetype":"venue"
},
  "geometry": {"coordinates":[4.3627748489,50.8594284058],"type":"Point"}
}