{
  "type": "Feature",
  "properties": {
    "addr:full":"Oosterhoven 23a Herenthout Antwerpen 2270",
    "addr:housenumber":"23a",
    "addr:postcode":"2270",
    "addr:street":"Oosterhoven",
    "iso:country":"BE",
    "sg:address":"Oosterhoven 23a",
    "sg:city":"Herenthout",
    "sg:classifiers":[
        {
            "category":"Arena",
            "subcategory":"Sports Club",
            "type":"Entertainment"
        }
    ],
    "sg:phone":"+32 14 21 00 09",
    "sg:postcode":"2270",
    "sg:province":"Antwerpen",
    "wof:name":"Waterral Bvba (de)",
    "wof:placetype":"venue"
},
  "geometry": {"coordinates":[4.7916398048,51.1462020874],"type":"Point"}
}