{
  "type": "Feature",
  "properties": {
    "iso:country":"BE",
    "sg:address":"Rue Du Prieur\u00c9 17",
    "sg:city":"Yvoir",
    "sg:orig_category":"Woningbouw",
    "sg:phone":"+32 82 61 18 82",
    "sg:postcode":"5530",
    "sg:province":"Namur",
    "wof:name":"Karel Sap",
    "wof:placetype":"venue"
},
  "geometry": {"coordinates":[4.8686408997,50.3494415283],"type":"Point"}
}