{
  "type": "Feature",
  "properties": {
    "addr:full":"Rue Moris 21 Bruxelles (saint-gilles) Bruxelles-Capitale 1060",
    "addr:housenumber":"21",
    "addr:postcode":"1060",
    "addr:street":"Rue Moris",
    "iso:country":"BE",
    "sg:address":"Rue Moris 21",
    "sg:city":"Bruxelles (saint-gilles)",
    "sg:classifiers":[
        {
            "category":"Food & Beverages",
            "subcategory":"Groceries & Convenience Stores",
            "type":"Retail Goods"
        }
    ],
    "sg:phone":"+32 2 539 19 97",
    "sg:postcode":"1060",
    "sg:province":"Bruxelles-Capitale",
    "sg:tags":[
        "grocer"
    ],
    "wof:name":"Rusho Alimentation",
    "wof:placetype":"venue"
},
  "geometry": {"coordinates":[4.3520140648,50.824798584],"type":"Point"}
}