{
  "type": "Feature",
  "properties": {
    "addr:full":"Steegstraat 24 Balen Antwerpen 2490",
    "addr:housenumber":"24",
    "addr:postcode":"2490",
    "addr:street":"Steegstraat",
    "iso:country":"BE",
    "sg:address":"Steegstraat 24",
    "sg:city":"Balen",
    "sg:classifiers":[
        {
            "category":"Shopping",
            "subcategory":"Beauty & Cosmetics",
            "type":"Retail Goods"
        }
    ],
    "sg:phone":"+32 14 81 24 00",
    "sg:postcode":"2490",
    "sg:province":"Antwerpen",
    "sg:tags":[
        "-",
        "perfumery"
    ],
    "wof:name":"Vankan Rita Schoonheidsinstituut",
    "wof:placetype":"venue"
},
  "geometry": {"coordinates":[5.170088768,51.1689720154],"type":"Point"}
}