{
  "type": "Feature",
  "properties": {
    "iso:country":"BE",
    "sg:address":"Knollestraat 23",
    "sg:city":"Veurne",
    "sg:orig_category":"Rundveehouders Varkenskwekers",
    "sg:phone":"+32 58 31 16 65",
    "sg:postcode":"8630",
    "sg:province":"West-Vlaanderen",
    "wof:name":"Maurits Vaneecke",
    "wof:placetype":"venue"
},
  "geometry": {"coordinates":[2.7235879898,51.0461616516],"type":"Point"}
}