{
  "type": "Feature",
  "properties": {
    "addr:full":"Rue De La Vignette 96 Box 1 Bruxelles (auderghem) Bruxelles-Capitale 1160",
    "addr:housenumber":"96;1",
    "addr:postcode":"1160",
    "addr:street":"Rue De La Vignette;Box",
    "iso:country":"BE",
    "sg:address":"Rue De La Vignette 96 Box 1",
    "sg:city":"Bruxelles (auderghem)",
    "sg:classifiers":[
        {
            "category":"Professional",
            "subcategory":"Management & Consulting",
            "type":"Services"
        }
    ],
    "sg:phone":"+32 2 672 74 36",
    "sg:postcode":"1160",
    "sg:province":"Bruxelles-Capitale",
    "sg:tags":[
        "-",
        "processing",
        "data",
        "consultant"
    ],
    "wof:name":"Computer Methods",
    "wof:placetype":"venue"
},
  "geometry": {"coordinates":[4.422413826,50.8152275085],"type":"Point"}
}