{
  "type": "Feature",
  "properties": {
    "addr:full":"Rue De La Tourelle 37 Etterbeek Bruxelles-Capitale 1040",
    "addr:housenumber":"37",
    "addr:postcode":"1040",
    "addr:street":"Rue De La Tourelle",
    "iso:country":"BE",
    "sg:address":"Rue De La Tourelle 37",
    "sg:city":"Etterbeek",
    "sg:orig_category":"Diverse bedrijfsbeheeradviesbureaus",
    "sg:phone":"+32 2 231 18 84",
    "sg:postcode":"1040",
    "sg:province":"Bruxelles-Capitale",
    "wof:name":"Stavanger European Office",
    "wof:placetype":"venue"
},
  "geometry": {"coordinates":[4.3832402229,50.8381767273],"type":"Point"}
}