{
  "type": "Feature",
  "properties": {
    "iso:country":"BE",
    "sg:address":"Rue Du Tige 186",
    "sg:city":"Juprelle",
    "sg:orig_category":"Apotheken",
    "sg:phone":"+32 4 278 51 65",
    "sg:postcode":"4452",
    "sg:province":"Li\u00e8ge",
    "wof:name":"A. Dodrimont",
    "wof:placetype":"venue"
},
  "geometry": {"coordinates":[5.5260782242,50.7086715698],"type":"Point"}
}