{
  "type": "Feature",
  "properties": {
    "addr:full":"Pasteurlaan 10b6 Schoten Antwerpen 2900",
    "addr:housenumber":"10b6",
    "addr:postcode":"2900",
    "addr:street":"Pasteurlaan",
    "iso:country":"BE",
    "sg:address":"Pasteurlaan 10b6",
    "sg:city":"Schoten",
    "sg:orig_category":"Elektrische installaties voor woningen",
    "sg:phone":"+32 3 685 57 15",
    "sg:postcode":"2900",
    "sg:province":"Antwerpen",
    "wof:name":"Hermans Marnik",
    "wof:placetype":"venue"
},
  "geometry": {"coordinates":[4.5002160072,51.2537612915],"type":"Point"}
}