{
  "type": "Feature",
  "properties": {
    "iso:country":"BE",
    "sg:address":"Rue Vieille Voie De Li\u00e8ge 38",
    "sg:city":"Sprimont",
    "sg:classifiers":[
        {
            "category":"Health Services",
            "subcategory":"Dentist",
            "type":"Services"
        }
    ],
    "sg:phone":"+32 4 382 22 52",
    "sg:postcode":"4140",
    "sg:province":"Li\u00e8ge",
    "wof:name":"Ledure F",
    "wof:placetype":"venue"
},
  "geometry": {"coordinates":[5.6590099335,50.5073661804],"type":"Point"}
}