{
  "type": "Feature",
  "properties": {
    "addr:full":"Wijnegemsteenweg 26 Schilde Antwerpen 2970",
    "addr:housenumber":"26",
    "addr:postcode":"2970",
    "addr:street":"Wijnegemsteenweg",
    "iso:country":"BE",
    "sg:address":"Wijnegemsteenweg 26",
    "sg:city":"Schilde",
    "sg:orig_category":"Equipement photographique. Studios photographiques",
    "sg:phone":"+32 3 658 25 36",
    "sg:postcode":"2970",
    "sg:province":"Antwerpen",
    "wof:name":"Fotoprint-van Den Heuvel",
    "wof:placetype":"venue"
},
  "geometry": {"coordinates":[4.5507497787,51.2623596191],"type":"Point"}
}