{
  "type": "Feature",
  "properties": {
    "iso:country":"BE",
    "sg:address":"Zwartemolenstraat 21",
    "sg:city":"Zele",
    "sg:orig_category":"Kapsalons",
    "sg:phone":"+32 52 44 60 24",
    "sg:postcode":"9240",
    "sg:province":"Oost-Vlaanderen",
    "wof:name":"Coiffure Mieke",
    "wof:placetype":"venue"
},
  "geometry": {"coordinates":[4.0250740051,51.0613174438],"type":"Point"}
}