{
  "type": "Feature",
  "properties": {
    "addr:full":"Rue De Courtrai 6 Mouscron Hainaut 7700",
    "addr:housenumber":"6",
    "addr:postcode":"7700",
    "addr:street":"Rue De Courtrai",
    "iso:country":"BE",
    "sg:address":"Rue De Courtrai 6",
    "sg:city":"Mouscron",
    "sg:classifiers":[
        {
            "category":"Shopping",
            "subcategory":"Optician",
            "type":"Retail Goods"
        }
    ],
    "sg:phone":"+32 56 33 33 64",
    "sg:postcode":"7700",
    "sg:province":"Hainaut",
    "sg:tags":[
        "-"
    ],
    "wof:name":"Descamps J-p",
    "wof:placetype":"venue"
},
  "geometry": {"coordinates":[3.2163250446,50.7445335388],"type":"Point"}
}