{
  "type": "Feature",
  "properties": {
    "iso:country":"BE",
    "sg:address":"Stationsstraat 32",
    "sg:city":"Dilbeek (groot - Bijgaarden)",
    "sg:classifiers":[
        {
            "category":"Shopping",
            "subcategory":"Shoes",
            "type":"Retail Goods"
        }
    ],
    "sg:phone":"+32 2 466 24 23",
    "sg:postcode":"1702",
    "sg:province":"Vlaams-Brabant",
    "sg:tags":[
        "slipper",
        "-"
    ],
    "wof:name":"Abcd Sc",
    "wof:placetype":"venue"
},
  "geometry": {"coordinates":[4.2770547867,50.8710289001],"type":"Point"}
}