{
  "type": "Feature",
  "properties": {
    "iso:country":"BE",
    "sg:address":"Rue Albert De Meyer 1",
    "sg:city":"Bruxelles",
    "sg:classifiers":[
        {
            "category":"Utilities",
            "subcategory":"Fuel Oil & Lpg",
            "type":"Services"
        }
    ],
    "sg:phone":"+32 2 428 90 90",
    "sg:postcode":"1020",
    "sg:province":"Bruxelles-Capitale",
    "sg:tags":[
        "product"
    ],
    "wof:name":"Idem",
    "wof:placetype":"venue"
},
  "geometry": {"coordinates":[4.3408460617,50.8730621338],"type":"Point"}
}