{
  "type": "Feature",
  "properties": {
    "iso:country":"BE",
    "sg:address":"Karel Janssenslaan 25",
    "sg:city":"Oostende",
    "sg:orig_category":"M\u00e9decins and sp\u00e9cialistes",
    "sg:phone":"+32 59 55 20 33",
    "sg:postcode":"8400",
    "sg:province":"West-Vlaanderen",
    "wof:name":"R. Vercamer",
    "wof:placetype":"venue"
},
  "geometry": {"coordinates":[2.9125299454,51.2290725708],"type":"Point"}
}