{
  "type": "Feature",
  "properties": {
    "addr:full":"Weststraat 127 Blankenberge West-Vlaanderen 8370",
    "addr:housenumber":"127",
    "addr:postcode":"8370",
    "addr:street":"Weststraat",
    "iso:country":"BE",
    "sg:address":"Weststraat 127",
    "sg:city":"Blankenberge",
    "sg:orig_category":"Brood, gebak and snoepgoed",
    "sg:phone":"+32 50 41 15 72",
    "sg:postcode":"8370",
    "sg:province":"West-Vlaanderen",
    "wof:name":"Bakkerij Haers-coudeville",
    "wof:placetype":"venue"
},
  "geometry": {"coordinates":[3.130628109,51.3123931885],"type":"Point"}
}