{
  "type": "Feature",
  "properties": {
    "addr:full":"Sint-truidensesteenweg 573 Tienen Vlaams-Brabant 3300",
    "addr:housenumber":"573",
    "addr:postcode":"3300",
    "addr:street":"Sint-Truidensesteenweg",
    "iso:country":"BE",
    "sg:address":"Sint-truidensesteenweg 573",
    "sg:city":"Tienen",
    "sg:orig_category":"Benzinestations and brandstoffen",
    "sg:phone":"+32 16 78 80 03",
    "sg:postcode":"3300",
    "sg:province":"Vlaams-Brabant",
    "wof:name":"Shell",
    "wof:placetype":"venue"
},
  "geometry": {"coordinates":[4.9893159866,50.7974281311],"type":"Point"}
}