{
  "type": "Feature",
  "properties": {
    "iso:country":"BE",
    "sg:address":"Populierstraat 1",
    "sg:city":"Roeselare",
    "sg:orig_category":"Non-Classified Establishments",
    "sg:phone":"+32 51 26 40 40",
    "sg:postcode":"8800",
    "sg:province":"West-Vlaanderen",
    "wof:name":"Acomo Belgium Nv",
    "wof:placetype":"venue"
},
  "geometry": {"coordinates":[3.1562619209,50.9471588135],"type":"Point"}
}