{
  "type": "Feature",
  "properties": {
    "iso:country":"BE",
    "sg:address":"Diestsesteenweg 359",
    "sg:city":"Aarschot (rillaar)",
    "sg:classifiers":[
        {
            "category":"Food & Beverages",
            "subcategory":"Groceries & Convenience Stores",
            "type":"Retail Goods"
        }
    ],
    "sg:phone":"+32 16 50 01 06",
    "sg:postcode":"3202",
    "sg:province":"Vlaams-Brabant",
    "sg:tags":[
        "grocer"
    ],
    "wof:name":"Ingro",
    "wof:placetype":"venue"
},
  "geometry": {"coordinates":[4.8971848488,50.9740600586],"type":"Point"}
}