{
  "type": "Feature",
  "properties": {
    "addr:full":"Maalse Steenweg 101 Brugge West-Vlaanderen 8310",
    "addr:housenumber":"101",
    "addr:postcode":"8310",
    "addr:street":"Maalse Steenweg",
    "iso:country":"BE",
    "sg:address":"Maalse Steenweg 101",
    "sg:city":"Brugge",
    "sg:orig_category":"Fleurs and plantes",
    "sg:phone":"+32 50 34 39 69",
    "sg:postcode":"8310",
    "sg:province":"West-Vlaanderen",
    "wof:name":"Brochette De Fleurs",
    "wof:placetype":"venue"
},
  "geometry": {"coordinates":[3.2469871044,51.210231781],"type":"Point"}
}