{
  "type": "Feature",
  "properties": {
    "iso:country":"BE",
    "sg:address":"Avenue Marius Meur\u00e9e 9",
    "sg:city":"Charleroi (marcinelle)",
    "sg:classifiers":[
        {
            "category":"Social Services",
            "subcategory":"Job Training",
            "type":"Services"
        }
    ],
    "sg:phone":"+32 71 42 30 20",
    "sg:postcode":"6001",
    "sg:province":"Hainaut",
    "sg:tags":[
        "personnel",
        "-selection",
        "recruitment"
    ],
    "wof:name":"Lsi Consult",
    "wof:placetype":"venue"
},
  "geometry": {"coordinates":[4.4474439621,50.4003753662],"type":"Point"}
}