{
  "type": "Feature",
  "properties": {
    "iso:country":"BE",
    "sg:address":"Kouterstraat 17",
    "sg:city":"Huldenberg (loonbeek)",
    "sg:classifiers":[
        {
            "category":"Building & Trades",
            "subcategory":"Landscaping Services",
            "type":"Services"
        }
    ],
    "sg:phone":"+32 498 26 35 98",
    "sg:postcode":"3040",
    "sg:province":"Vlaams-Brabant",
    "sg:tags":[
        "architect",
        "landscape"
    ],
    "wof:name":"De Becker T",
    "wof:placetype":"venue"
},
  "geometry": {"coordinates":[4.6045951843,50.804271698],"type":"Point"}
}