{
  "type": "Feature",
  "properties": {
    "addr:full":"Jacques Sermonlaan 2b1 Ganshoren/ganshoren Bruxelles-Capitale 1083",
    "addr:housenumber":"2b1",
    "addr:postcode":"1083",
    "addr:street":"Jacques Sermonlaan",
    "iso:country":"BE",
    "sg:address":"Jacques Sermonlaan 2b1",
    "sg:city":"Ganshoren/ganshoren",
    "sg:orig_category":"Brood, gebak and snoepgoed",
    "sg:phone":"+32 2 427 32 29",
    "sg:postcode":"1083",
    "sg:province":"Bruxelles-Capitale",
    "wof:name":"Christian Maes",
    "wof:placetype":"venue"
},
  "geometry": {"coordinates":[4.3204421997,50.8678131104],"type":"Point"}
}