{
  "type": "Feature",
  "properties": {
    "iso:country":"BE",
    "sg:address":"Chauss\u00c9e D'alsemberg 859",
    "sg:city":"Ukkel/uccle",
    "sg:orig_category":"Boucheries",
    "sg:phone":"+32 2 332 28 66",
    "sg:postcode":"1180",
    "sg:province":"Bruxelles-Capitale",
    "wof:name":"Boucherie Le Veau D'or",
    "wof:placetype":"venue"
},
  "geometry": {"coordinates":[4.3363609314,50.8004608154],"type":"Point"}
}