{
  "type": "Feature",
  "properties": {
    "addr:full":"Markt 50b2 Deinze Oost-Vlaanderen 9800",
    "addr:housenumber":"50b2",
    "addr:postcode":"9800",
    "addr:street":"Markt",
    "iso:country":"BE",
    "sg:address":"Markt 50b2",
    "sg:city":"Deinze",
    "sg:orig_category":"Verplichte sociale verzekeringen",
    "sg:phone":"+32 9 386 13 48",
    "sg:postcode":"9800",
    "sg:province":"Oost-Vlaanderen",
    "wof:name":"Christelijke Mutualiteit",
    "wof:placetype":"venue"
},
  "geometry": {"coordinates":[3.5266370773,50.9839248657],"type":"Point"}
}