{
  "type": "Feature",
  "properties": {
    "iso:country":"BE",
    "sg:address":"Rue De L\u00b4aire 4",
    "sg:city":"Soignies",
    "sg:classifiers":[
        {
            "category":"Insurance",
            "subcategory":"Insurance Agent",
            "type":"Services"
        }
    ],
    "sg:phone":"+32 67 33 96 34",
    "sg:postcode":"7060",
    "sg:province":"Hainaut",
    "sg:tags":[
        "verzekeringsmakelaars",
        "expert"
    ],
    "wof:name":"S.n.c.i.",
    "wof:placetype":"venue"
},
  "geometry": {"coordinates":[4.0580787659,50.5828590393],"type":"Point"}
}