{
  "type": "Feature",
  "properties": {
    "addr:full":"Kesselsesteenweg 6 Lier Antwerpen 2500",
    "addr:housenumber":"6",
    "addr:postcode":"2500",
    "addr:street":"Kesselsesteenweg",
    "iso:country":"BE",
    "sg:address":"Kesselsesteenweg 6",
    "sg:city":"Lier",
    "sg:orig_category":"Installation de menuiserie m\u00e9tallique",
    "sg:phone":"+32 3 488 17 96",
    "sg:postcode":"2500",
    "sg:province":"Antwerpen",
    "wof:name":"Verandabouw De Winter",
    "wof:placetype":"venue"
},
  "geometry": {"coordinates":[4.5881052017,51.1295700073],"type":"Point"}
}