{
  "type": "Feature",
  "properties": {
    "addr:full":"Notaxlaan 16 Destelbergen Oost-Vlaanderen 9070",
    "addr:housenumber":"16",
    "addr:postcode":"9070",
    "addr:street":"Notaxlaan",
    "iso:country":"BE",
    "sg:address":"Notaxlaan 16",
    "sg:city":"Destelbergen",
    "sg:classifiers":[
        {
            "category":"Real Estate",
            "subcategory":"Architect",
            "type":"Services"
        }
    ],
    "sg:phone":"+32 9 228 55 85",
    "sg:postcode":"9070",
    "sg:province":"Oost-Vlaanderen",
    "wof:name":"Rawoens J",
    "wof:placetype":"venue"
},
  "geometry": {"coordinates":[3.7757530212,51.0595588684],"type":"Point"}
}