{
  "type": "Feature",
  "properties": {
    "iso:country":"BE",
    "sg:address":"Revinzestraat 22",
    "sg:city":"Torhout",
    "sg:orig_category":"D\u00e9molition d\u00b4immeubles and terrassements",
    "sg:phone":"+32 50 21 22 88",
    "sg:postcode":"8820",
    "sg:province":"West-Vlaanderen",
    "wof:name":"Beto",
    "wof:placetype":"venue"
},
  "geometry": {"coordinates":[3.0889239311,51.0664596558],"type":"Point"}
}