{
  "type": "Feature",
  "properties": {
    "iso:country":"BE",
    "sg:address":"Gouden Kruispunt 4b78",
    "sg:city":"Tielt-winge",
    "sg:orig_category":"Parfumeries",
    "sg:phone":"+32 16 63 18 35",
    "sg:postcode":"3390",
    "sg:province":"Vlaams-Brabant",
    "wof:name":"Reuk En Rookpotje",
    "wof:placetype":"venue"
},
  "geometry": {"coordinates":[4.8722681999,50.9039268494],"type":"Point"}
}