{
  "type": "Feature",
  "properties": {
    "addr:full":"Poststraat 37 Sint-joost-ten-node/saint-josse-ten-noode Bruxelles-Capitale 1210",
    "addr:housenumber":"37",
    "addr:postcode":"1210",
    "addr:street":"Poststraat",
    "iso:country":"BE",
    "sg:address":"Poststraat 37",
    "sg:city":"Sint-joost-ten-node/saint-josse-ten-noode",
    "sg:orig_category":"Artsen and specialisten",
    "sg:phone":"+32 2 219 12 42",
    "sg:postcode":"1210",
    "sg:province":"Bruxelles-Capitale",
    "wof:name":"Consultation Nourrissons",
    "wof:placetype":"venue"
},
  "geometry": {"coordinates":[4.3661389351,50.8565406799],"type":"Point"}
}