{
  "type": "Feature",
  "properties": {
    "iso:country":"BE",
    "sg:address":"Stijn Streuvelsstraat 26",
    "sg:city":"Brugge",
    "sg:classifiers":[
        {
            "category":"Shopping",
            "subcategory":"Baby Store",
            "type":"Retail Goods"
        }
    ],
    "sg:phone":"+32 50 34 78 25",
    "sg:postcode":"8000",
    "sg:province":"West-Vlaanderen",
    "sg:tags":[
        "midwife"
    ],
    "wof:name":"Verhoustraete M",
    "wof:placetype":"venue"
},
  "geometry": {"coordinates":[3.2363929749,51.2128868103],"type":"Point"}
}