{
  "type": "Feature",
  "properties": {
    "iso:country":"BE",
    "sg:address":"Rue Fontaine-au-biez 70",
    "sg:city":"Verviers (heusy)",
    "sg:classifiers":[
        {
            "category":"Building & Trades",
            "subcategory":"Pest Control",
            "type":"Services"
        }
    ],
    "sg:phone":"+32 87 23 07 03",
    "sg:postcode":"4802",
    "sg:province":"Li\u00e8ge",
    "sg:tags":[
        "painting",
        "contractor"
    ],
    "wof:name":"Henrard Paul & Fils",
    "wof:placetype":"venue"
},
  "geometry": {"coordinates":[5.8877649307,50.5784950256],"type":"Point"}
}