{
  "type": "Feature",
  "properties": {
    "addr:full":"Rue Ernest Cambier 35 Ath Hainaut 7800",
    "addr:housenumber":"35",
    "addr:postcode":"7800",
    "addr:street":"Rue Ernest Cambier",
    "iso:country":"BE",
    "sg:address":"Rue Ernest Cambier 35",
    "sg:city":"Ath",
    "sg:classifiers":[
        {
            "category":"Personal",
            "subcategory":"Beauty Salon",
            "type":"Services"
        }
    ],
    "sg:phone":"+32 68 28 50 00",
    "sg:postcode":"7800",
    "sg:province":"Hainaut",
    "sg:tags":[
        "de",
        "coiffure"
    ],
    "wof:name":"Coiffure Joelle",
    "wof:placetype":"venue"
},
  "geometry": {"coordinates":[3.7770121098,50.6290054321],"type":"Point"}
}