{
  "type": "Feature",
  "properties": {
    "iso:country":"BE",
    "sg:address":"Luikersteenweg 553",
    "sg:city":"Lommel",
    "sg:classifiers":[
        {
            "category":"Shopping",
            "subcategory":"Antiques",
            "type":"Retail Goods"
        }
    ],
    "sg:phone":"+32 11 64 01 06",
    "sg:postcode":"3920",
    "sg:province":"Limburg",
    "wof:name":"Willem's Antiek",
    "wof:placetype":"venue"
},
  "geometry": {"coordinates":[5.3755497932,51.2355194092],"type":"Point"}
}