{
  "type": "Feature",
  "properties": {
    "iso:country":"BE",
    "sg:address":"Venelle Des Pr\u00c9as 44",
    "sg:city":"Wavre",
    "sg:orig_category":"Landmeters and schatters",
    "sg:phone":"+32 10 22 44 29",
    "sg:postcode":"1300",
    "sg:province":"Brabant Wallon",
    "wof:name":"Michel Van Bockstaele",
    "wof:placetype":"venue"
},
  "geometry": {"coordinates":[4.6253042221,50.6883163452],"type":"Point"}
}