{
  "type": "Feature",
  "properties": {
    "addr:full":"Pastorijstraat 40 Box 3 Houthalen-helchteren (houthalen) Limburg 3530",
    "addr:housenumber":"40;3",
    "addr:postcode":"3530",
    "addr:street":"Pastorijstraat;Box",
    "iso:country":"BE",
    "sg:address":"Pastorijstraat 40 Box 3",
    "sg:city":"Houthalen-helchteren (houthalen)",
    "sg:classifiers":[
        {
            "category":"Education",
            "subcategory":"Special Training",
            "type":"Public Place"
        }
    ],
    "sg:phone":"+32 11 52 44 45",
    "sg:postcode":"3530",
    "sg:province":"Limburg",
    "sg:tags":[
        "professional"
    ],
    "wof:name":"Route Vzw",
    "wof:placetype":"venue"
},
  "geometry": {"coordinates":[5.3745150566,51.026802063],"type":"Point"}
}