{
  "type": "Feature",
  "properties": {
    "iso:country":"BE",
    "sg:address":"Groenstraat 10",
    "sg:city":"Horebeke",
    "sg:classifiers":[
        {
            "category":"Building & Trades",
            "subcategory":"Plumbing",
            "type":"Services"
        }
    ],
    "sg:phone":"+32 55 45 53 59",
    "sg:postcode":"9667",
    "sg:province":"Oost-Vlaanderen",
    "sg:tags":[
        "diver",
        "commerce",
        "gr",
        "pour",
        "equipement"
    ],
    "wof:name":"Felix De Wolf Ariel",
    "wof:placetype":"venue"
},
  "geometry": {"coordinates":[3.7037079334,50.8190574646],"type":"Point"}
}