{
  "type": "Feature",
  "properties": {
    "iso:country":"BE",
    "sg:address":"Stoomtuigstraat 11",
    "sg:city":"Hooglede (gits)",
    "sg:classifiers":[
        {
            "category":"Freight",
            "type":"Transportation"
        }
    ],
    "sg:phone":"+32 51 25 19 52",
    "sg:postcode":"8830",
    "sg:province":"West-Vlaanderen",
    "sg:tags":[
        "-",
        "transport"
    ],
    "wof:name":"Lokere Transport Nv",
    "wof:placetype":"venue"
},
  "geometry": {"coordinates":[3.1207370758,50.9836807251],"type":"Point"}
}