{
  "type": "Feature",
  "properties": {
    "addr:full":"Rue De Chaumont 4 Florennes Namur 5620",
    "addr:housenumber":"4",
    "addr:postcode":"5620",
    "addr:street":"Rue De Chaumont",
    "iso:country":"BE",
    "sg:address":"Rue De Chaumont 4",
    "sg:city":"Florennes",
    "sg:classifiers":[
        {
            "category":"Professional",
            "subcategory":"Accounting & Tax Preparation",
            "type":"Services"
        }
    ],
    "sg:phone":"+32 71 68 91 51",
    "sg:postcode":"5620",
    "sg:province":"Namur",
    "sg:tags":[
        "bookkeeper"
    ],
    "wof:name":"Hottiaux Cl",
    "wof:placetype":"venue"
},
  "geometry": {"coordinates":[4.6154808998,50.2380371094],"type":"Point"}
}