{
  "type": "Feature",
  "properties": {
    "addr:full":"Lokerseweg 43 Poperinge West-Vlaanderen 8970",
    "addr:housenumber":"43",
    "addr:postcode":"8970",
    "addr:street":"Lokerseweg",
    "iso:country":"BE",
    "sg:address":"Lokerseweg 43",
    "sg:city":"Poperinge",
    "sg:orig_category":"Eleveurs and marchands de porcs",
    "sg:phone":"+32 57 44 45 14",
    "sg:postcode":"8970",
    "sg:province":"West-Vlaanderen",
    "wof:name":"Gery Berghman",
    "wof:placetype":"venue"
},
  "geometry": {"coordinates":[2.771089077,50.7998580933],"type":"Point"}
}