{
  "type": "Feature",
  "properties": {
    "addr:full":"Valleilaan 32a Rotselaar Vlaams-Brabant 3110",
    "addr:housenumber":"32a",
    "addr:postcode":"3110",
    "addr:street":"Valleilaan",
    "iso:country":"BE",
    "sg:address":"Valleilaan 32a",
    "sg:city":"Rotselaar",
    "sg:classifiers":[
        {
            "category":"Real Estate",
            "subcategory":"Real Estate Services",
            "type":"Services"
        }
    ],
    "sg:phone":"+32 16 58 13 47",
    "sg:postcode":"3110",
    "sg:province":"Vlaams-Brabant",
    "wof:name":"Immobuild Consult",
    "wof:placetype":"venue"
},
  "geometry": {"coordinates":[4.7685189247,50.9636383057],"type":"Point"}
}