{
  "type": "Feature",
  "properties": {
    "addr:full":"Wijerdriesstraat 30 Genk Limburg 3600",
    "addr:housenumber":"30",
    "addr:postcode":"3600",
    "addr:street":"Wijerdriesstraat",
    "iso:country":"BE",
    "sg:address":"Wijerdriesstraat 30",
    "sg:city":"Genk",
    "sg:classifiers":[
        {
            "category":"Insurance",
            "subcategory":"Insurance Agent",
            "type":"Services"
        }
    ],
    "sg:phone":"+32 89 35 03 00",
    "sg:postcode":"3600",
    "sg:province":"Limburg",
    "sg:tags":[
        "verzekeringsmakelaars",
        "expert"
    ],
    "wof:name":"Verzekeringen Houben",
    "wof:placetype":"venue"
},
  "geometry": {"coordinates":[5.5504999161,50.9730072021],"type":"Point"}
}