{
  "type": "Feature",
  "properties": {
    "addr:full":"Duinenstraat 210 Oostende West-Vlaanderen 8400",
    "addr:housenumber":"210",
    "addr:postcode":"8400",
    "addr:street":"Duinenstraat",
    "iso:country":"BE",
    "sg:address":"Duinenstraat 210",
    "sg:city":"Oostende",
    "sg:orig_category":"Woningbouw",
    "sg:phone":"+32 59 70 55 09",
    "sg:postcode":"8400",
    "sg:province":"West-Vlaanderen",
    "wof:name":"Pylyser Gebroeders",
    "wof:placetype":"venue"
},
  "geometry": {"coordinates":[2.8595299721,51.2061500549],"type":"Point"}
}