{
  "type": "Feature",
  "properties": {
    "iso:country":"BE",
    "sg:address":"Place Verte 4",
    "sg:city":"Verviers",
    "sg:classifiers":[
        {
            "category":"Restaurant",
            "type":"Food & Drink"
        }
    ],
    "sg:phone":"+32 87 35 35 53",
    "sg:postcode":"4800",
    "sg:province":"Li\u00e8ge",
    "wof:name":"Le Chatel",
    "wof:placetype":"venue"
},
  "geometry": {"coordinates":[5.8608422279,50.5923995972],"type":"Point"}
}