{
  "type": "Feature",
  "properties": {
    "addr:full":"Rue Lloyd Georges 7 Chatelet Hainaut 6200",
    "addr:housenumber":"7",
    "addr:postcode":"6200",
    "addr:street":"Rue Lloyd Georges;Hainaut",
    "iso:country":"BE",
    "sg:address":"Rue Lloyd Georges 7",
    "sg:city":"Chatelet",
    "sg:orig_category":"Banques and organismes de cr\u00e9dit",
    "sg:phone":"+32 71 39 06 16",
    "sg:postcode":"6200",
    "sg:province":"Hainaut",
    "wof:name":"Citibank",
    "wof:placetype":"venue"
},
  "geometry": {"coordinates":[4.5190958977,50.4126853943],"type":"Point"}
}