{
  "type": "Feature",
  "properties": {
    "addr:full":"Rue Du Doyenn\u00e9 60 Bruxelles (uccle) Bruxelles-Capitale 1180",
    "addr:housenumber":"60",
    "addr:postcode":"1180",
    "addr:street":"Rue Du Doyenne\u0301",
    "iso:country":"BE",
    "sg:address":"Rue Du Doyenn\u00e9 60",
    "sg:city":"Bruxelles (uccle)",
    "sg:classifiers":[
        {
            "category":"Education",
            "subcategory":"School",
            "type":"Public Place"
        }
    ],
    "sg:phone":"+32 2 348 65 20",
    "sg:postcode":"1180",
    "sg:province":"Bruxelles-Capitale",
    "sg:tags":[
        "primary"
    ],
    "wof:name":"Ecole Du Centre",
    "wof:placetype":"venue"
},
  "geometry": {"coordinates":[4.3384828568,50.8058242798],"type":"Point"}
}