{
  "type": "Feature",
  "properties": {
    "iso:country":"BE",
    "sg:address":"Sint-amelbergalaan 22",
    "sg:city":"Temse",
    "sg:orig_category":"Fleurs and plantes",
    "sg:phone":"+32 3 711 20 76",
    "sg:postcode":"9140",
    "sg:province":"Oost-Vlaanderen",
    "wof:name":"Camille",
    "wof:placetype":"venue"
},
  "geometry": {"coordinates":[4.1987848282,51.1252288818],"type":"Point"}
}