{
  "type": "Feature",
  "properties": {
    "addr:full":"Route De Hamoir 7 Durbuy (tohogne) Luxembourg 6941",
    "addr:housenumber":"7",
    "addr:postcode":"6941",
    "addr:street":"Route De Hamoir",
    "iso:country":"BE",
    "sg:address":"Route De Hamoir 7",
    "sg:city":"Durbuy (tohogne)",
    "sg:classifiers":[
        {
            "category":"Health Services",
            "subcategory":"Health Practitioner",
            "type":"Services"
        }
    ],
    "sg:phone":"+32 86 21 22 16",
    "sg:postcode":"6941",
    "sg:province":"Luxembourg",
    "sg:tags":[
        "dietitian"
    ],
    "wof:name":"Lekeux I",
    "wof:placetype":"venue"
},
  "geometry": {"coordinates":[5.5069198608,50.4064331055],"type":"Point"}
}