{
  "type": "Feature",
  "properties": {
    "addr:full":"Rue Du Touquet 9 Sivry-rance (sautin) Hainaut 6470",
    "addr:housenumber":"9",
    "addr:postcode":"6470",
    "addr:street":"Rue Du Touquet",
    "iso:country":"BE",
    "sg:address":"Rue Du Touquet 9",
    "sg:city":"Sivry-rance (sautin)",
    "sg:classifiers":[
        {
            "category":"Retail",
            "subcategory":"Auto Repair",
            "type":"Services"
        }
    ],
    "sg:phone":"+32 60 45 60 54",
    "sg:postcode":"6470",
    "sg:province":"Hainaut",
    "sg:tags":[
        "garage"
    ],
    "wof:name":"Deutz Fahr-legros Fr\u00e8res",
    "wof:placetype":"venue"
},
  "geometry": {"coordinates":[4.2715301514,50.1426696777],"type":"Point"}
}