{
  "type": "Feature",
  "properties": {
    "iso:country":"BE",
    "sg:address":"Diksmuidestraat 74c",
    "sg:city":"Staden",
    "sg:orig_category":"Installation \u00e9lectrique industrielle",
    "sg:phone":"+32 51 70 37 84",
    "sg:postcode":"8840",
    "sg:province":"West-Vlaanderen",
    "wof:name":"Anseeuw Domotica",
    "wof:placetype":"venue"
},
  "geometry": {"coordinates":[3.0078639984,50.9802703857],"type":"Point"}
}