{
  "type": "Feature",
  "properties": {
    "iso:country":"BE",
    "sg:address":"Avenue Du Roi Soleil 52",
    "sg:city":"Waterloo",
    "sg:classifiers":[
        {
            "category":"Professional",
            "subcategory":"Computer Services",
            "type":"Services"
        }
    ],
    "sg:phone":"+32 477 64 61 38",
    "sg:postcode":"1410",
    "sg:province":"Brabant Wallon",
    "sg:tags":[
        "webdesign",
        "-",
        "internet"
    ],
    "wof:name":"Microtech",
    "wof:placetype":"venue"
},
  "geometry": {"coordinates":[4.3910331726,50.706413269],"type":"Point"}
}