{
  "type": "Feature",
  "properties": {
    "addr:full":"Rue Di\u00e9rain Patar 5 Gr\u00e2ce-hollogne (hollogne-aux-pierres) Li\u00e8ge 4460",
    "addr:housenumber":"5",
    "addr:postcode":"4460",
    "addr:street":"Rue Die\u0301Rain Patar;Hollogne-Aux-Pierres",
    "iso:country":"BE",
    "sg:address":"Rue Di\u00e9rain Patar 5",
    "sg:city":"Gr\u00e2ce-hollogne (hollogne-aux-pierres)",
    "sg:classifiers":[
        {
            "category":"Freight",
            "type":"Transportation"
        }
    ],
    "sg:phone":"+32 476 65 57 57",
    "sg:postcode":"4460",
    "sg:province":"Li\u00e8ge",
    "sg:tags":[
        "-",
        "transport"
    ],
    "wof:name":"Vi-tho Express",
    "wof:placetype":"venue"
},
  "geometry": {"coordinates":[5.4545807838,50.632900238],"type":"Point"}
}