{
  "type": "Feature",
  "properties": {
    "iso:country":"BE",
    "sg:address":"Peperstraat 8bb",
    "sg:city":"Sint-niklaas",
    "sg:orig_category":"Paramedische behandelingen",
    "sg:phone":"+32 3 766 86 22",
    "sg:postcode":"9100",
    "sg:province":"Oost-Vlaanderen",
    "wof:name":"M. Droogendijk",
    "wof:placetype":"venue"
},
  "geometry": {"coordinates":[4.1724019051,51.1938209534],"type":"Point"}
}