{
  "type": "Feature",
  "properties": {
    "addr:full":"Rue De La Station 23 Awans Li\u00e8ge 4340",
    "addr:housenumber":"23",
    "addr:postcode":"4340",
    "addr:street":"Rue De La Station",
    "iso:country":"BE",
    "sg:address":"Rue De La Station 23",
    "sg:city":"Awans",
    "sg:classifiers":[
        {
            "category":"Professional",
            "subcategory":"Accounting & Tax Preparation",
            "type":"Services"
        }
    ],
    "sg:phone":"+32 4 247 18 08",
    "sg:postcode":"4340",
    "sg:province":"Li\u00e8ge",
    "sg:tags":[
        "accountant"
    ],
    "wof:name":"Fiduciaire Lepage & Co Sc",
    "wof:placetype":"venue"
},
  "geometry": {"coordinates":[5.4618139267,50.6620292664],"type":"Point"}
}