{
  "type": "Feature",
  "properties": {
    "addr:full":"Kleine Reesdijk 98 Turnhout Antwerpen 2300",
    "addr:housenumber":"98",
    "addr:postcode":"2300",
    "addr:street":"Kleine Reesdijk",
    "iso:country":"BE",
    "sg:address":"Kleine Reesdijk 98",
    "sg:city":"Turnhout",
    "sg:classifiers":[
        {
            "category":"Home & Garden",
            "subcategory":"Building Materials",
            "type":"Retail Goods"
        }
    ],
    "sg:phone":"+32 14 43 96 31",
    "sg:postcode":"2300",
    "sg:province":"Antwerpen",
    "sg:tags":[
        "-",
        "fireplace",
        "open",
        "ornamental"
    ],
    "wof:name":"Vloerbedrijf G.hermans & Zn Bvba",
    "wof:placetype":"venue"
},
  "geometry": {"coordinates":[4.9548921585,51.28307724],"type":"Point"}
}