{
  "type": "Feature",
  "properties": {
    "iso:country":"BE",
    "sg:address":"Rue Vandervelde 12",
    "sg:city":"Morlanwelz (carni\u00e8res)",
    "sg:classifiers":[
        {
            "category":"Wholesale",
            "subcategory":"Sporting Goods",
            "type":"Manufacturing & Wholesale Goods"
        }
    ],
    "sg:phone":"+32 64 44 22 65",
    "sg:postcode":"7141",
    "sg:province":"Hainaut",
    "sg:tags":[
        "windsurfing",
        "accessory"
    ],
    "wof:name":"Depersenaire",
    "wof:placetype":"venue"
},
  "geometry": {"coordinates":[4.2588191032,50.4476547241],"type":"Point"}
}