{
  "type": "Feature",
  "properties": {
    "iso:country":"BE",
    "sg:address":"Rue Jules Des Essarts 47",
    "sg:city":"Ch\u00e2telet (ch\u00e2telineau)",
    "sg:classifiers":[
        {
            "category":"Insurance",
            "subcategory":"Insurance Agent",
            "type":"Services"
        }
    ],
    "sg:phone":"+32 71 38 12 20",
    "sg:postcode":"6200",
    "sg:province":"Hainaut",
    "sg:tags":[
        "broker"
    ],
    "wof:name":"Top Finance Sprl",
    "wof:placetype":"venue"
},
  "geometry": {"coordinates":[4.5198597908,50.4155082703],"type":"Point"}
}