{
  "type": "Feature",
  "properties": {
    "iso:country":"BE",
    "sg:address":"Statiestraat 5",
    "sg:city":"Dentergem",
    "sg:orig_category":"Benzinestations and brandstoffen",
    "sg:phone":"+32 51 63 42 47",
    "sg:postcode":"8720",
    "sg:province":"West-Vlaanderen",
    "wof:name":"Carine Arickx",
    "wof:placetype":"venue"
},
  "geometry": {"coordinates":[3.4160060883,50.9660415649],"type":"Point"}
}