{
  "type": "Feature",
  "properties": {
    "iso:country":"BE",
    "sg:address":"Van De Reydtlaan 62",
    "sg:city":"Brecht",
    "sg:classifiers":[
        {
            "category":"Food & Beverages",
            "subcategory":"Fruits & Vegetables",
            "type":"Retail Goods"
        }
    ],
    "sg:phone":"+32 3 636 36 14",
    "sg:postcode":"2960",
    "sg:province":"Antwerpen",
    "sg:tags":[
        "l\u00e9gumes",
        "gr"
    ],
    "wof:name":"Aavaca",
    "wof:placetype":"venue"
},
  "geometry": {"coordinates":[4.5975627899,51.327457428],"type":"Point"}
}