{
  "type": "Feature",
  "properties": {
    "addr:full":"Atomiumsq B 677 Trade Mart D 316 Bruxelles Bruxelles-Capitale 1020",
    "addr:housenumber":"677;316",
    "addr:postcode":"1020",
    "iso:country":"BE",
    "sg:address":"Atomiumsq B 677 Trade Mart D 316",
    "sg:city":"Bruxelles",
    "sg:classifiers":[
        {
            "category":"Manufacturing",
            "subcategory":"Paper Products",
            "type":"Manufacturing & Wholesale Goods"
        }
    ],
    "sg:phone":"+32 2 478 83 83",
    "sg:postcode":"1020",
    "sg:province":"Bruxelles-Capitale",
    "sg:tags":[
        "finished",
        "cardboard",
        "-"
    ],
    "wof:name":"Henzo Nv/sa",
    "wof:placetype":"venue"
},
  "geometry": {"coordinates":[4.3469200134,50.8988418579],"type":"Point"}
}