{
  "type": "Feature",
  "properties": {
    "iso:country":"BE",
    "sg:address":"Kukkelbosstraat 6",
    "sg:city":"Diepenbeek",
    "sg:orig_category":"Installation de menuiserie m\u00e9tallique",
    "sg:phone":"+32 11 33 15 43",
    "sg:postcode":"3590",
    "sg:province":"Limburg",
    "wof:name":"Vaes-rijmen",
    "wof:placetype":"venue"
},
  "geometry": {"coordinates":[5.4221630096,50.8879241943],"type":"Point"}
}