{
  "type": "Feature",
  "properties": {
    "addr:full":"Chemin Tribouriau 57 Ath Hainaut 7822",
    "addr:housenumber":"57",
    "addr:postcode":"7822",
    "addr:street":"Chemin Tribouriau",
    "iso:country":"BE",
    "sg:address":"Chemin Tribouriau 57",
    "sg:city":"Ath",
    "sg:orig_category":"Sportclubs",
    "sg:phone":"+32 68 28 26 02",
    "sg:postcode":"7822",
    "sg:province":"Hainaut",
    "wof:name":"Le Jeunes Amateurs",
    "wof:placetype":"venue"
},
  "geometry": {"coordinates":[3.8452620506,50.6482391357],"type":"Point"}
}