{
  "type": "Feature",
  "properties": {
    "iso:country":"BE",
    "sg:address":"Rue Du Ruisseau 42",
    "sg:city":"La Bruy\u00c8re",
    "sg:orig_category":"Artsen and specialisten",
    "sg:phone":"+32 81 56 67 97",
    "sg:postcode":"5081",
    "sg:province":"Namur",
    "wof:name":"Monique Decat",
    "wof:placetype":"venue"
},
  "geometry": {"coordinates":[4.7844319344,50.5152549744],"type":"Point"}
}