{
  "type": "Feature",
  "properties": {
    "addr:full":"Rue Du Bas De La Place 5 Jemeppe-sur-sambre Namur 5190",
    "addr:housenumber":"5",
    "addr:postcode":"5190",
    "addr:street":"Rue Du Bas De La Place",
    "iso:country":"BE",
    "sg:address":"Rue Du Bas De La Place 5",
    "sg:city":"Jemeppe-sur-sambre",
    "sg:classifiers":[
        {
            "category":"Personal",
            "subcategory":"Beauty Salon",
            "type":"Services"
        }
    ],
    "sg:phone":"+32 71 78 65 08",
    "sg:postcode":"5190",
    "sg:province":"Namur",
    "sg:tags":[
        "de",
        "coiffure"
    ],
    "wof:name":"Monique Deffense",
    "wof:placetype":"venue"
},
  "geometry": {"coordinates":[4.7038497925,50.4826316833],"type":"Point"}
}