{
  "type": "Feature",
  "properties": {
    "addr:full":"Ichtegemstraat 108 Kortemark West-Vlaanderen 8610",
    "addr:housenumber":"108",
    "addr:postcode":"8610",
    "addr:street":"Ichtegemstraat",
    "iso:country":"BE",
    "sg:address":"Ichtegemstraat 108",
    "sg:city":"Kortemark",
    "sg:classifiers":[
        {
            "category":"Home & Garden",
            "subcategory":"Garden Supply",
            "type":"Retail Goods"
        }
    ],
    "sg:phone":"+32 51 56 64 32",
    "sg:postcode":"8610",
    "sg:province":"West-Vlaanderen",
    "sg:tags":[
        "machine",
        "agricultural",
        "-"
    ],
    "wof:name":"Devako Bvba",
    "wof:placetype":"venue"
},
  "geometry": {"coordinates":[3.0315959454,51.0551147461],"type":"Point"}
}