{
  "type": "Feature",
  "properties": {
    "addr:full":"Rue Du Spinoy 26 La Bruy\u00e8re (rhisnes) Namur 5080",
    "addr:housenumber":"26",
    "addr:postcode":"5080",
    "addr:street":"Rue Du Spinoy",
    "iso:country":"BE",
    "sg:address":"Rue Du Spinoy 26",
    "sg:city":"La Bruy\u00e8re (rhisnes)",
    "sg:classifiers":[
        {
            "category":"Personal",
            "subcategory":"Beauty Salon",
            "type":"Services"
        }
    ],
    "sg:phone":"+32 81 56 62 96",
    "sg:postcode":"5080",
    "sg:province":"Namur",
    "sg:tags":[
        "lady",
        "-",
        "hairdressing"
    ],
    "wof:name":"Elle",
    "wof:placetype":"venue"
},
  "geometry": {"coordinates":[4.7994937897,50.5040130615],"type":"Point"}
}