{
  "type": "Feature",
  "properties": {
    "iso:country":"BE",
    "sg:address":"Dorp 7",
    "sg:city":"Sint-martens-latem",
    "sg:orig_category":"Non-Classified Establishments",
    "sg:phone":"+32 9 282 57 57",
    "sg:postcode":"9830",
    "sg:province":"Oost-Vlaanderen",
    "wof:name":"Gofact Bvba",
    "wof:placetype":"venue"
},
  "geometry": {"coordinates":[3.6403989792,51.0208053589],"type":"Point"}
}