{
  "type": "Feature",
  "properties": {
    "addr:full":"Stationsstraat 110 Nazareth (eke) Oost-Vlaanderen 9810",
    "addr:housenumber":"110",
    "addr:postcode":"9810",
    "addr:street":"Stationsstraat",
    "iso:country":"BE",
    "sg:address":"Stationsstraat 110",
    "sg:city":"Nazareth (eke)",
    "sg:classifiers":[
        {
            "category":"Manufacturing",
            "subcategory":"Rubber & Plastics",
            "type":"Manufacturing & Wholesale Goods"
        }
    ],
    "sg:phone":"+32 9 385 42 72",
    "sg:postcode":"9810",
    "sg:province":"Oost-Vlaanderen",
    "sg:tags":[
        "foam"
    ],
    "wof:name":"Mousse Shop",
    "wof:placetype":"venue"
},
  "geometry": {"coordinates":[3.6307089329,50.9598617554],"type":"Point"}
}