{
  "type": "Feature",
  "properties": {
    "addr:full":"Rue Du Monument 14-18 Ciney (grand) Namur 5590",
    "addr:housenumber":"14-18",
    "addr:postcode":"5590",
    "addr:street":"Rue Du Monument",
    "iso:country":"BE",
    "sg:address":"Rue Du Monument 14-18",
    "sg:city":"Ciney (grand)",
    "sg:classifiers":[
        {
            "category":"Personal",
            "subcategory":"Beauty Salon",
            "type":"Services"
        }
    ],
    "sg:phone":"+32 83 21 29 75",
    "sg:postcode":"5590",
    "sg:province":"Namur",
    "sg:tags":[
        "de",
        "coiffure"
    ],
    "wof:name":"Collignon I",
    "wof:placetype":"venue"
},
  "geometry": {"coordinates":[5.1715788841,50.2805595398],"type":"Point"}
}