{
  "type": "Feature",
  "properties": {
    "iso:country":"BE",
    "sg:address":"Jules Peurquaetstraat 80",
    "sg:city":"Oostende",
    "sg:classifiers":[
        {
            "category":"Banks & Credit Unions",
            "subcategory":"Investment Brokerage",
            "type":"Services"
        }
    ],
    "sg:phone":"+32 59 70 11 42",
    "sg:postcode":"8400",
    "sg:province":"West-Vlaanderen",
    "sg:tags":[
        "printing",
        "-"
    ],
    "wof:name":"Deprince",
    "wof:placetype":"venue"
},
  "geometry": {"coordinates":[2.9126570225,51.2248191833],"type":"Point"}
}