{
  "type": "Feature",
  "properties": {
    "iso:country":"BE",
    "sg:address":"Vieille-voie-de-tongres 181",
    "sg:city":"Li\u00e8ge 1",
    "sg:classifiers":[
        {
            "category":"Parking",
            "subcategory":"Bicycle",
            "type":"Transportation"
        }
    ],
    "sg:phone":"+32 4 235 99 43",
    "sg:postcode":"4000",
    "sg:province":"Li\u00e8ge",
    "sg:tags":[
        "chiropodist"
    ],
    "wof:name":"Melchor M",
    "wof:placetype":"venue"
},
  "geometry": {"coordinates":[5.5671029091,50.6644554138],"type":"Point"}
}