{
  "type": "Feature",
  "properties": {
    "addr:full":"Avenue Du Ch\u00c2teau De Beez 32 Namur Namur 5000",
    "addr:housenumber":"32",
    "addr:postcode":"5000",
    "addr:street":"Avenue Du Cha\u0302Teau De Beez",
    "iso:country":"BE",
    "sg:address":"Avenue Du Ch\u00c2teau De Beez 32",
    "sg:city":"Namur",
    "sg:orig_category":"Fleurs and plantes",
    "sg:phone":"+32 81 22 69 97",
    "sg:postcode":"5000",
    "sg:province":"Namur",
    "wof:name":"R. Massart",
    "wof:placetype":"venue"
},
  "geometry": {"coordinates":[4.8617630005,50.4657287598],"type":"Point"}
}