{
  "type": "Feature",
  "properties": {
    "iso:country":"BE",
    "sg:address":"Rue De Dinant 1",
    "sg:city":"Paliseul",
    "sg:orig_category":"Installation de menuiserie en bois and plastique",
    "sg:phone":"+32 61 53 45 32",
    "sg:postcode":"6850",
    "sg:province":"Luxembourg",
    "wof:name":"Moline Christian",
    "wof:placetype":"venue"
},
  "geometry": {"coordinates":[5.0645098686,49.8845100403],"type":"Point"}
}