{
  "type": "Feature",
  "properties": {
    "addr:full":"Avenue Hamoir 1 Bruxelles (uccle) Bruxelles-Capitale 1180",
    "addr:housenumber":"1",
    "addr:postcode":"1180",
    "addr:street":"Avenue Hamoir",
    "iso:country":"BE",
    "sg:address":"Avenue Hamoir 1",
    "sg:city":"Bruxelles (uccle)",
    "sg:classifiers":[
        {
            "category":"Social Services",
            "subcategory":"Retirement Home",
            "type":"Services"
        }
    ],
    "sg:phone":"+32 2 379 07 00",
    "sg:postcode":"1180",
    "sg:province":"Bruxelles-Capitale",
    "sg:tags":[
        "residence"
    ],
    "wof:name":"Hamoir (r\u00e9sidence)",
    "wof:placetype":"venue"
},
  "geometry": {"coordinates":[4.3746800423,50.7986679077],"type":"Point"}
}