{
  "type": "Feature",
  "properties": {
    "iso:country":"BE",
    "sg:address":"Rue Coup\u00e9e 100",
    "sg:city":"Li\u00e8ge 1",
    "sg:classifiers":[
        {
            "category":"Health Services",
            "subcategory":"Doctor",
            "type":"Services"
        }
    ],
    "sg:phone":"+32 4 227 50 44",
    "sg:postcode":"4000",
    "sg:province":"Li\u00e8ge",
    "sg:tags":[
        "medicinephysicians",
        "surgeon"
    ],
    "wof:name":"Dew\u00e9 Walthere",
    "wof:placetype":"venue"
},
  "geometry": {"coordinates":[5.5831198692,50.6609802246],"type":"Point"}
}