{
  "type": "Feature",
  "properties": {
    "iso:country":"BE",
    "sg:address":"Leuvensesteenweg 101",
    "sg:city":"Diest (groot)",
    "sg:orig_category":"V\u00eatements pour Dames. V\u00eatements pour b\u00e9b\u00e9s and enfants. V\u00eatements pour Hommes",
    "sg:phone":"+32 13 32 33 02",
    "sg:postcode":"3290",
    "sg:province":"Vlaams-Brabant",
    "wof:name":"Jbc Mode",
    "wof:placetype":"venue"
},
  "geometry": {"coordinates":[5.0452709198,50.9785194397],"type":"Point"}
}