{
  "type": "Feature",
  "properties": {
    "iso:country":"BE",
    "sg:address":"Noorderwijkseweg 11",
    "sg:city":"Olen",
    "sg:orig_category":"Kapsalons Mobiele kappers",
    "sg:phone":"+32 14 26 29 06",
    "sg:postcode":"2250",
    "sg:province":"Antwerpen",
    "wof:name":"Coiffure Jeannine",
    "wof:placetype":"venue"
},
  "geometry": {"coordinates":[4.8535909653,51.1426925659],"type":"Point"}
}