{
  "type": "Feature",
  "properties": {
    "addr:full":"Rue De La Cha\u00eene 46 Li\u00e8ge 1 Li\u00e8ge 4000",
    "addr:housenumber":"46;1",
    "addr:postcode":"4000",
    "addr:street":"Rue De La Chai\u0302Ne",
    "iso:country":"BE",
    "sg:address":"Rue De La Cha\u00eene 46",
    "sg:city":"Li\u00e8ge 1",
    "sg:classifiers":[
        {
            "category":"Health Services",
            "subcategory":"Doctor",
            "type":"Services"
        }
    ],
    "sg:phone":"+32 4 235 99 55",
    "sg:postcode":"4000",
    "sg:province":"Li\u00e8ge",
    "sg:tags":[
        "medicinephysicians",
        "surgeon"
    ],
    "wof:name":"Lacroix Nicole",
    "wof:placetype":"venue"
},
  "geometry": {"coordinates":[5.5777101517,50.6560707092],"type":"Point"}
}