{
  "type": "Feature",
  "properties": {
    "addr:full":"Rue Sauveni\u00c8re 26 Ouffet Li\u00e8ge 4590",
    "addr:housenumber":"26",
    "addr:postcode":"4590",
    "addr:street":"Rue Sauvenie\u0300Re",
    "iso:country":"BE",
    "sg:address":"Rue Sauveni\u00c8re 26",
    "sg:city":"Ouffet",
    "sg:orig_category":"Boekhandels Kantoormateriaal Krantenwinkels Rookartikelen",
    "sg:phone":"+32 86 36 65 06",
    "sg:postcode":"4590",
    "sg:province":"Li\u00e8ge",
    "wof:name":"Maison De Pery",
    "wof:placetype":"venue"
},
  "geometry": {"coordinates":[5.4636912346,50.4392738342],"type":"Point"}
}