{
  "type": "Feature",
  "properties": {
    "iso:country":"BE",
    "sg:address":"Diksmuidseweg 69",
    "sg:city":"Ieper",
    "sg:orig_category":"Dakwerken Loodgieterij, verwarming and sanitaire installaties Woningbouw",
    "sg:phone":"+32 57 20 07 27",
    "sg:postcode":"8900",
    "sg:province":"West-Vlaanderen",
    "wof:name":"Ch.van Eygen-duthoo",
    "wof:placetype":"venue"
},
  "geometry": {"coordinates":[2.8778870106,50.8600387573],"type":"Point"}
}