{
  "type": "Feature",
  "properties": {
    "addr:full":"Hoenderstraat 36 Wetteren Oost-Vlaanderen 9230",
    "addr:housenumber":"36",
    "addr:postcode":"9230",
    "addr:street":"Hoenderstraat",
    "iso:country":"BE",
    "sg:address":"Hoenderstraat 36",
    "sg:city":"Wetteren",
    "sg:classifiers":[
        {
            "category":"Retail",
            "subcategory":"Laundry & Dry Cleaning",
            "type":"Services"
        }
    ],
    "sg:phone":"+32 9 369 67 95",
    "sg:postcode":"9230",
    "sg:province":"Oost-Vlaanderen",
    "sg:tags":[
        "dyer",
        "cleaner"
    ],
    "wof:name":"Pressing Nr 1",
    "wof:placetype":"venue"
},
  "geometry": {"coordinates":[3.8823580742,51.0038337708],"type":"Point"}
}