{
  "type": "Feature",
  "properties": {
    "iso:country":"BE",
    "sg:address":"Spreeuwerstraat 46",
    "sg:city":"Maaseik (neeroeteren)",
    "sg:classifiers":[
        {
            "category":"Health Services",
            "subcategory":"Health Practitioner",
            "type":"Services"
        }
    ],
    "sg:phone":"+32 89 86 15 31",
    "sg:postcode":"3680",
    "sg:province":"Limburg",
    "sg:tags":[
        "physiotherapist"
    ],
    "wof:name":"Bollen Elvire",
    "wof:placetype":"venue"
},
  "geometry": {"coordinates":[5.791285038,51.0954208374],"type":"Point"}
}