{
  "type": "Feature",
  "properties": {
    "addr:full":"Schaluin 28 Aarschot Vlaams-Brabant 3200",
    "addr:housenumber":"28",
    "addr:postcode":"3200",
    "addr:street":"Schaluin",
    "iso:country":"BE",
    "sg:address":"Schaluin 28",
    "sg:city":"Aarschot",
    "sg:classifiers":[
        {
            "category":"Education",
            "subcategory":"School",
            "type":"Public Place"
        }
    ],
    "sg:phone":"+32 16 55 11 11",
    "sg:postcode":"3200",
    "sg:province":"Vlaams-Brabant",
    "sg:tags":[
        "secondary"
    ],
    "wof:name":"Sint-jozefscollege 1e 2e 3e Graad",
    "wof:placetype":"venue"
},
  "geometry": {"coordinates":[4.8405890465,50.9896202087],"type":"Point"}
}