{
  "type": "Feature",
  "properties": {
    "addr:full":"Scheldestraat 123 Gent Oost-Vlaanderen 9040",
    "addr:housenumber":"123",
    "addr:postcode":"9040",
    "addr:street":"Scheldestraat;Oost-Vlaanderen",
    "iso:country":"BE",
    "sg:address":"Scheldestraat 123",
    "sg:city":"Gent",
    "sg:orig_category":"Kapsalons",
    "sg:phone":"+32 9 228 67 72",
    "sg:postcode":"9040",
    "sg:province":"Oost-Vlaanderen",
    "wof:name":"Coiffure Freddy",
    "wof:placetype":"venue"
},
  "geometry": {"coordinates":[3.7505600452,51.0497207642],"type":"Point"}
}