{
  "type": "Feature",
  "properties": {
    "iso:country":"BE",
    "sg:address":"Chemin Du Bois D'ospot 15",
    "sg:city":"Neufch\u00e2teau",
    "sg:classifiers":[
        {
            "category":"Professional",
            "subcategory":"Business Services",
            "type":"Services"
        }
    ],
    "sg:phone":"+32 61 27 82 86",
    "sg:postcode":"6840",
    "sg:province":"Luxembourg",
    "sg:tags":[
        "firm"
    ],
    "wof:name":"Movi Consult Sprl",
    "wof:placetype":"venue"
},
  "geometry": {"coordinates":[5.4411611557,49.8371963501],"type":"Point"}
}