{
  "type": "Feature",
  "properties": {
    "addr:full":"Rue Trieu Kaisin 125 Charleroi (montignies-sur-sambre) Hainaut 6061",
    "addr:housenumber":"125",
    "addr:postcode":"6061",
    "addr:street":"Rue Trieu Kaisin",
    "iso:country":"BE",
    "sg:address":"Rue Trieu Kaisin 125",
    "sg:city":"Charleroi (montignies-sur-sambre)",
    "sg:classifiers":[
        {
            "category":"Shopping",
            "subcategory":"Books",
            "type":"Retail Goods"
        }
    ],
    "sg:phone":"+32 71 31 98 56",
    "sg:postcode":"6061",
    "sg:province":"Hainaut",
    "sg:tags":[
        "bookseller"
    ],
    "wof:name":"Devillers",
    "wof:placetype":"venue"
},
  "geometry": {"coordinates":[4.4757652283,50.4093589783],"type":"Point"}
}