{
  "type": "Feature",
  "properties": {
    "iso:country":"BE",
    "sg:address":"Rue Du Bocage 136",
    "sg:city":"Eghezee",
    "sg:classifiers":[
        {
            "category":"Personal",
            "subcategory":"Beauty Salon",
            "type":"Services"
        }
    ],
    "sg:phone":"+32 81 81 10 38",
    "sg:postcode":"5310",
    "sg:province":"Namur",
    "sg:tags":[
        "de",
        "coiffure"
    ],
    "wof:name":"Marie-rose Govaerts",
    "wof:placetype":"venue"
},
  "geometry": {"coordinates":[4.9044919014,50.5936851501],"type":"Point"}
}