{
  "type": "Feature",
  "properties": {
    "addr:full":"Driekoningestraat 11 Wielsbeke West-Vlaanderen 8710",
    "addr:housenumber":"11",
    "addr:postcode":"8710",
    "addr:street":"Driekoningestraat;West-Vlaanderen",
    "iso:country":"BE",
    "sg:address":"Driekoningestraat 11",
    "sg:city":"Wielsbeke",
    "sg:orig_category":"Jardinage",
    "sg:phone":"+32 56 60 75 52",
    "sg:postcode":"8710",
    "sg:province":"West-Vlaanderen",
    "wof:name":"Huysentruyt J",
    "wof:placetype":"venue"
},
  "geometry": {"coordinates":[3.3694550991,50.9095153809],"type":"Point"}
}