{
  "type": "Feature",
  "properties": {
    "iso:country":"BE",
    "sg:address":"Coupure Links 629",
    "sg:city":"Gent",
    "sg:orig_category":"Non-Classified Establishments",
    "sg:phone":"+32 9 266 18 18",
    "sg:postcode":"9000",
    "sg:province":"Oost-Vlaanderen",
    "wof:name":"Duet Cvba",
    "wof:placetype":"venue"
},
  "geometry": {"coordinates":[3.7093300819,51.0523147583],"type":"Point"}
}