{
  "type": "Feature",
  "properties": {
    "addr:full":"De Mosten 6 Hoogstraten Antwerpen 2321",
    "addr:housenumber":"6",
    "addr:postcode":"2321",
    "addr:street":"De Mosten",
    "iso:country":"BE",
    "sg:address":"De Mosten 6",
    "sg:city":"Hoogstraten",
    "sg:orig_category":"Fruitteelt Varkenskwekers",
    "sg:phone":"+32 3 315 76 16",
    "sg:postcode":"2321",
    "sg:province":"Antwerpen",
    "wof:name":"Jozef Braspening",
    "wof:placetype":"venue"
},
  "geometry": {"coordinates":[4.7366099358,51.442325592],"type":"Point"}
}