{
  "type": "Feature",
  "properties": {
    "iso:country":"BE",
    "sg:address":"Ossegemstraat 41",
    "sg:city":"Meise",
    "sg:classifiers":[
        {
            "category":"Home & Garden",
            "subcategory":"Building Materials",
            "type":"Retail Goods"
        }
    ],
    "sg:phone":"+32 2 269 45 42",
    "sg:postcode":"1860",
    "sg:province":"Vlaams-Brabant",
    "sg:tags":[
        "wall",
        "cupboard"
    ],
    "wof:name":"Cockaert Design",
    "wof:placetype":"venue"
},
  "geometry": {"coordinates":[4.3212099075,50.9640388489],"type":"Point"}
}