{
  "type": "Feature",
  "properties": {
    "iso:country":"BE",
    "sg:address":"Leon Dumortierstraat 190",
    "sg:city":"Hove",
    "sg:classifiers":[
        {
            "category":"Building & Trades",
            "subcategory":"Construction",
            "type":"Services"
        }
    ],
    "sg:phone":"+32 3 454 32 62",
    "sg:postcode":"2540",
    "sg:province":"Antwerpen",
    "sg:tags":[
        "installation",
        "-",
        "central",
        "heating"
    ],
    "wof:name":"Teunen-stabel Bvba",
    "wof:placetype":"venue"
},
  "geometry": {"coordinates":[4.4722399712,51.1504707336],"type":"Point"}
}