{
  "type": "Feature",
  "properties": {
    "iso:country":"BE",
    "sg:address":"Snapperstraat 19",
    "sg:city":"Hasselt",
    "sg:orig_category":"Quincailleries. Bois Gr. Fruits and l\u00e9gumes",
    "sg:phone":"+32 11 25 35 74",
    "sg:postcode":"3511",
    "sg:province":"Limburg",
    "wof:name":"Fruitloods",
    "wof:placetype":"venue"
},
  "geometry": {"coordinates":[5.3034238815,50.9432487488],"type":"Point"}
}