{
  "type": "Feature",
  "properties": {
    "addr:full":"Langstraat 104 Geel Antwerpen 2440",
    "addr:housenumber":"104",
    "addr:postcode":"2440",
    "addr:street":"Langstraat",
    "iso:country":"BE",
    "sg:address":"Langstraat 104",
    "sg:city":"Geel",
    "sg:classifiers":[
        {
            "category":"Real Estate",
            "subcategory":"Surveying",
            "type":"Services"
        }
    ],
    "sg:phone":"+32 14 23 02 35",
    "sg:postcode":"2440",
    "sg:province":"Antwerpen",
    "sg:tags":[
        "surveyor",
        "land"
    ],
    "wof:name":"Daems E",
    "wof:placetype":"venue"
},
  "geometry": {"coordinates":[4.9218969345,51.1700630188],"type":"Point"}
}