{
  "type": "Feature",
  "properties": {
    "addr:full":"Sint-antoniusstraat 13 Kampenhout Vlaams-Brabant 1910",
    "addr:housenumber":"13",
    "addr:postcode":"1910",
    "addr:street":"Sint-Antoniusstraat",
    "iso:country":"BE",
    "sg:address":"Sint-antoniusstraat 13",
    "sg:city":"Kampenhout",
    "sg:orig_category":"Groententeelt",
    "sg:phone":"+32 16 60 35 42",
    "sg:postcode":"1910",
    "sg:province":"Vlaams-Brabant",
    "wof:name":"Paul Vanderborght",
    "wof:placetype":"venue"
},
  "geometry": {"coordinates":[4.6152019501,50.9388656616],"type":"Point"}
}