{
  "type": "Feature",
  "properties": {
    "addr:full":"Rue De La Place 16 Soignies Hainaut 7062",
    "addr:housenumber":"16",
    "addr:postcode":"7062",
    "addr:street":"Rue De La Place",
    "iso:country":"BE",
    "sg:address":"Rue De La Place 16",
    "sg:city":"Soignies",
    "sg:orig_category":"HERSTELLING ELEKTRISCHE HUISHOUDAPPARATEN Huishoudapparaten, televisies and radio's",
    "sg:phone":"+32 67 33 28 14",
    "sg:postcode":"7062",
    "sg:province":"Hainaut",
    "wof:name":"Yves Lolivier",
    "wof:placetype":"venue"
},
  "geometry": {"coordinates":[4.0996851921,50.5541000366],"type":"Point"}
}