{
  "type": "Feature",
  "properties": {
    "iso:country":"BE",
    "sg:address":"Chauss\u00c9e De Nivelles 56",
    "sg:city":"Seneffe",
    "sg:orig_category":"Maisons de repos and r\u00e9sidences",
    "sg:phone":"+32 67 87 92 50",
    "sg:postcode":"7181",
    "sg:province":"Hainaut",
    "wof:name":"R\u00c9sidence Bon Conseil",
    "wof:placetype":"venue"
},
  "geometry": {"coordinates":[4.2589969635,50.5626296997],"type":"Point"}
}