{
  "type": "Feature",
  "properties": {
    "addr:full":"Galgestraat 21 Box 1 Tienen Vlaams-Brabant 3300",
    "addr:housenumber":"21;1",
    "addr:postcode":"3300",
    "addr:street":"Galgestraat;Box",
    "iso:country":"BE",
    "sg:address":"Galgestraat 21 Box 1",
    "sg:city":"Tienen",
    "sg:classifiers":[
        {
            "category":"Arena",
            "subcategory":"Sports Club",
            "type":"Entertainment"
        }
    ],
    "sg:phone":"+32 16 81 62 22",
    "sg:postcode":"3300",
    "sg:province":"Vlaams-Brabant",
    "sg:tags":[
        "federation"
    ],
    "wof:name":"Vlaamse Roller Bond",
    "wof:placetype":"venue"
},
  "geometry": {"coordinates":[4.9204511642,50.8132820129],"type":"Point"}
}