{
  "type": "Feature",
  "properties": {
    "addr:full":"Dokter Elie Lambottestr. 78 Schaarbeek/schaerbeek Bruxelles-Capitale 1030",
    "addr:housenumber":"78",
    "addr:postcode":"1030",
    "addr:street":"Dokter Elie Lambottestr.",
    "iso:country":"BE",
    "sg:address":"Dokter Elie Lambottestr. 78",
    "sg:city":"Schaarbeek/schaerbeek",
    "sg:orig_category":"Herstellingen and onderhoud van auto's",
    "sg:phone":"+32 2 216 88 38",
    "sg:postcode":"1030",
    "sg:province":"Bruxelles-Capitale",
    "wof:name":"Garage Lambotte",
    "wof:placetype":"venue"
},
  "geometry": {"coordinates":[4.3867931366,50.8718338013],"type":"Point"}
}