{
  "type": "Feature",
  "properties": {
    "iso:country":"BE",
    "sg:address":"Nieuwlandlaan 16b",
    "sg:city":"Aarschot",
    "sg:orig_category":"Non-Classified Establishments",
    "sg:phone":"+32 16 57 21 68",
    "sg:postcode":"3200",
    "sg:province":"Vlaams-Brabant",
    "wof:name":"Hatenboer-elektro Bv",
    "wof:placetype":"venue"
},
  "geometry": {"coordinates":[4.8159370422,50.9856872559],"type":"Point"}
}