{
  "type": "Feature",
  "properties": {
    "addr:full":"Rue De L'arsenal 1 Pont-\u00e0-celles Hainaut 6230",
    "addr:housenumber":"1",
    "addr:postcode":"6230",
    "addr:street":"Rue De L'Arsenal",
    "iso:country":"BE",
    "sg:address":"Rue De L'arsenal 1",
    "sg:city":"Pont-\u00e0-celles",
    "sg:classifiers":[
        {
            "category":"Health Services",
            "subcategory":"Dentist",
            "type":"Services"
        }
    ],
    "sg:phone":"+32 71 84 75 68",
    "sg:postcode":"6230",
    "sg:province":"Hainaut",
    "wof:name":"Mashshini K",
    "wof:placetype":"venue"
},
  "geometry": {"coordinates":[4.3839950562,50.5034637451],"type":"Point"}
}