{
  "type": "Feature",
  "properties": {
    "addr:full":"Nieuwpoortsteenweg 156 Koksijde West-Vlaanderen 8670",
    "addr:housenumber":"156",
    "addr:postcode":"8670",
    "addr:street":"Nieuwpoortsteenweg",
    "iso:country":"BE",
    "sg:address":"Nieuwpoortsteenweg 156",
    "sg:city":"Koksijde",
    "sg:classifiers":[
        {
            "category":"Arena",
            "subcategory":"Sports Club",
            "type":"Entertainment"
        }
    ],
    "sg:phone":"+32 58 23 72 66",
    "sg:postcode":"8670",
    "sg:province":"West-Vlaanderen",
    "sg:tags":[
        "de"
    ],
    "wof:name":"T.c. Den Espinette",
    "wof:placetype":"venue"
},
  "geometry": {"coordinates":[2.708523035,51.1222610474],"type":"Point"}
}