{
  "type": "Feature",
  "properties": {
    "iso:country":"BE",
    "sg:address":"Rue Docteur Henri Schaltin 43",
    "sg:city":"Spa",
    "sg:classifiers":[
        {
            "category":"Home & Garden",
            "subcategory":"Home Furnishings",
            "type":"Retail Goods"
        }
    ],
    "sg:phone":"+32 87 77 11 97",
    "sg:postcode":"4900",
    "sg:province":"Li\u00e8ge",
    "sg:tags":[
        "interior",
        "decoration"
    ],
    "wof:name":"Herman C",
    "wof:placetype":"venue"
},
  "geometry": {"coordinates":[5.8662471771,50.4910736084],"type":"Point"}
}