{
  "type": "Feature",
  "properties": {
    "addr:full":"Bosstraat 24 Lovendegem Oost-Vlaanderen 9920",
    "addr:housenumber":"24",
    "addr:postcode":"9920",
    "addr:street":"Bosstraat",
    "iso:country":"BE",
    "sg:address":"Bosstraat 24",
    "sg:city":"Lovendegem",
    "sg:classifiers":[
        {
            "category":"Farming",
            "subcategory":"Farm & Veterinary Services",
            "type":"Manufacturing & Wholesale Goods"
        }
    ],
    "sg:phone":"+32 9 357 42 56",
    "sg:postcode":"9920",
    "sg:province":"Oost-Vlaanderen",
    "sg:tags":[
        "agricultural",
        "contractor"
    ],
    "wof:name":"Cocquyt",
    "wof:placetype":"venue"
},
  "geometry": {"coordinates":[3.64595294,51.1213798523],"type":"Point"}
}