{
  "type": "Feature",
  "properties": {
    "addr:full":"Grote Markt 24 Menen West-Vlaanderen 8930",
    "addr:housenumber":"24",
    "addr:postcode":"8930",
    "addr:street":"Grote Markt",
    "iso:country":"BE",
    "sg:address":"Grote Markt 24",
    "sg:city":"Menen",
    "sg:classifiers":[
        {
            "category":"Cafe",
            "type":"Food & Drink"
        }
    ],
    "sg:phone":"+32 56 51 09 10",
    "sg:postcode":"8930",
    "sg:province":"West-Vlaanderen",
    "sg:tags":[
        "caf\u00e9s"
    ],
    "wof:name":"Caf\u00c9 't Zwaantje",
    "wof:placetype":"venue"
},
  "geometry": {"coordinates":[3.1211481094,50.7971000671],"type":"Point"}
}