{
  "type": "Feature",
  "properties": {
    "iso:country":"BE",
    "sg:address":"Meyerode 20",
    "sg:city":"Amel/ambl\u00c8ve",
    "sg:orig_category":"Toeristische diensten",
    "sg:phone":"+32 80 34 94 46",
    "sg:postcode":"4770",
    "sg:province":"Li\u00e8ge",
    "wof:name":"Syndicat D\u00b4initiative",
    "wof:placetype":"venue"
},
  "geometry": {"coordinates":[6.1876211166,50.3251914978],"type":"Point"}
}