{
  "type": "Feature",
  "properties": {
    "addr:full":"Appelmansstraat 25b20 Antwerpen Antwerpen 2018",
    "addr:housenumber":"25b20",
    "addr:postcode":"2018",
    "addr:street":"Appelmansstraat",
    "iso:country":"BE",
    "sg:address":"Appelmansstraat 25b20",
    "sg:city":"Antwerpen",
    "sg:orig_category":"Agences de voyages",
    "sg:phone":"+32 3 226 17 44",
    "sg:postcode":"2018",
    "sg:province":"Antwerpen",
    "wof:name":"Blitz Travel",
    "wof:placetype":"venue"
},
  "geometry": {"coordinates":[4.4175648689,51.2166061401],"type":"Point"}
}