{
  "type": "Feature",
  "properties": {
    "addr:full":"Rue D' Ath 5 Leuze-en-hainaut Hainaut 7900",
    "addr:housenumber":"5",
    "addr:postcode":"7900",
    "addr:street":"Rue D ' Ath",
    "iso:country":"BE",
    "sg:address":"Rue D' Ath 5",
    "sg:city":"Leuze-en-hainaut",
    "sg:orig_category":"Hoisiery Goods",
    "sg:phone":"+32 69 66 22 94",
    "sg:postcode":"7900",
    "sg:province":"Hainaut",
    "wof:name":"Fabrique De Bonneterie Fernand Dubois S.p.r.l.",
    "wof:placetype":"venue"
},
  "geometry": {"coordinates":[3.622893095,50.5998497009],"type":"Point"}
}