{
  "type": "Feature",
  "properties": {
    "addr:full":"Bergkapelstraat 4 Londerzeel Vlaams-Brabant 1840",
    "addr:housenumber":"4",
    "addr:postcode":"1840",
    "addr:street":"Bergkapelstraat",
    "iso:country":"BE",
    "sg:address":"Bergkapelstraat 4",
    "sg:city":"Londerzeel",
    "sg:orig_category":"Diensten voor huisdieren Huisdieren and benodigdheden Royal Canin",
    "sg:phone":"+32 52 30 05 03",
    "sg:postcode":"1840",
    "sg:province":"Vlaams-Brabant",
    "wof:name":"Verbesselt Yorki",
    "wof:placetype":"venue"
},
  "geometry": {"coordinates":[4.317920208,51.0076026917],"type":"Point"}
}