{
  "type": "Feature",
  "properties": {
    "iso:country":"BE",
    "sg:address":"Rue Des Canonniers 11a",
    "sg:city":"Nivelles",
    "sg:classifiers":[
        {
            "category":"Health Services",
            "subcategory":"Hospital",
            "type":"Services"
        }
    ],
    "sg:phone":"+32 67 21 28 44",
    "sg:postcode":"1400",
    "sg:province":"Brabant Wallon",
    "sg:tags":[
        "ambulance"
    ],
    "wof:name":"Ambulances Detournay",
    "wof:placetype":"venue"
},
  "geometry": {"coordinates":[4.3243308067,50.6002082825],"type":"Point"}
}