{
  "type": "Feature",
  "properties": {
    "addr:full":"Wijnbergstraat 121 Wevelgem West-Vlaanderen 8560",
    "addr:housenumber":"121",
    "addr:postcode":"8560",
    "addr:street":"Wijnbergstraat",
    "iso:country":"BE",
    "sg:address":"Wijnbergstraat 121",
    "sg:city":"Wevelgem",
    "sg:orig_category":"Pharmaciens",
    "sg:phone":"+32 56 42 34 07",
    "sg:postcode":"8560",
    "sg:province":"West-Vlaanderen",
    "wof:name":"Apotheek Wijnberg",
    "wof:placetype":"venue"
},
  "geometry": {"coordinates":[3.1696751118,50.8191566467],"type":"Point"}
}