{
  "type": "Feature",
  "properties": {
    "iso:country":"BE",
    "sg:address":"Heultjedorp 63",
    "sg:city":"Westerlo",
    "sg:classifiers":[
        {
            "category":"Personal",
            "subcategory":"Beauty Salon",
            "type":"Services"
        }
    ],
    "sg:phone":"+32 16 69 59 34",
    "sg:postcode":"2260",
    "sg:province":"Antwerpen",
    "sg:tags":[
        "lady",
        "-",
        "hairdressing"
    ],
    "wof:name":"Hippe Snitt",
    "wof:placetype":"venue"
},
  "geometry": {"coordinates":[4.8380699158,51.0920257568],"type":"Point"}
}