{
  "type": "Feature",
  "properties": {
    "addr:full":"Voskenslaan 27 Gent Oost-Vlaanderen 9000",
    "addr:housenumber":"27",
    "addr:postcode":"9000",
    "addr:street":"Voskenslaan;Oost-Vlaanderen",
    "iso:country":"BE",
    "sg:address":"Voskenslaan 27",
    "sg:city":"Gent",
    "sg:classifiers":[
        {
            "category":"Shopping",
            "subcategory":"Clothing, Apparel, & Fashions",
            "type":"Retail Goods"
        }
    ],
    "sg:phone":"+32 9 222 40 90",
    "sg:postcode":"9000",
    "sg:province":"Oost-Vlaanderen",
    "sg:tags":[
        "underwear",
        "lingerie",
        "-"
    ],
    "wof:name":"Alga Textieldepots Bvba",
    "wof:placetype":"venue"
},
  "geometry": {"coordinates":[3.7082839012,51.0345802307],"type":"Point"}
}