{
  "type": "Feature",
  "properties": {
    "iso:country":"BE",
    "sg:address":"Route Du Condroz 40a",
    "sg:city":"Seraing (boncelles)",
    "sg:classifiers":[
        {
            "category":"Shopping",
            "subcategory":"Optician",
            "type":"Retail Goods"
        }
    ],
    "sg:phone":"+32 4 338 26 40",
    "sg:postcode":"4100",
    "sg:province":"Li\u00e8ge",
    "sg:tags":[
        "-"
    ],
    "wof:name":"Torfs-optique & Acoustique",
    "wof:placetype":"venue"
},
  "geometry": {"coordinates":[5.5289258957,50.5566749573],"type":"Point"}
}