{
  "type": "Feature",
  "properties": {
    "iso:country":"BE",
    "sg:address":"Veldstraat 179",
    "sg:city":"Temse",
    "sg:classifiers":[
        {
            "category":"Cafe",
            "type":"Food & Drink"
        }
    ],
    "sg:phone":"+32 3 771 07 25",
    "sg:postcode":"9140",
    "sg:province":"Oost-Vlaanderen",
    "sg:tags":[
        "caf\u00e9s"
    ],
    "wof:name":"Quintelier-de Bock",
    "wof:placetype":"venue"
},
  "geometry": {"coordinates":[4.2211461067,51.138710022],"type":"Point"}
}