{
  "type": "Feature",
  "properties": {
    "addr:full":"Kerkhovensesteenweg 306 Lommel Limburg 3920",
    "addr:housenumber":"306",
    "addr:postcode":"3920",
    "addr:street":"Kerkhovensesteenweg",
    "iso:country":"BE",
    "sg:address":"Kerkhovensesteenweg 306",
    "sg:city":"Lommel",
    "sg:classifiers":[
        {
            "category":"Real Estate",
            "subcategory":"Real Estate Services",
            "type":"Services"
        }
    ],
    "sg:phone":"+32 11 34 03 60",
    "sg:postcode":"3920",
    "sg:province":"Limburg",
    "wof:name":"Savemak Cv",
    "wof:placetype":"venue"
},
  "geometry": {"coordinates":[5.2750639915,51.1670455933],"type":"Point"}
}