{
  "type": "Feature",
  "properties": {
    "addr:full":"Dendermondesteenweg 168 Destelbergen Oost-Vlaanderen 9070",
    "addr:housenumber":"168",
    "addr:postcode":"9070",
    "addr:street":"Dendermondesteenweg",
    "iso:country":"BE",
    "sg:address":"Dendermondesteenweg 168",
    "sg:city":"Destelbergen",
    "sg:classifiers":[
        {
            "category":"Autos & Motor Vehicles",
            "subcategory":"Motorcycle Sales",
            "type":"Retail Goods"
        }
    ],
    "sg:phone":"+32 9 228 61 98",
    "sg:postcode":"9070",
    "sg:province":"Oost-Vlaanderen",
    "sg:tags":[
        "motorbike"
    ],
    "wof:name":"A V R Racing",
    "wof:placetype":"venue"
},
  "geometry": {"coordinates":[3.7693710327,51.0531044006],"type":"Point"}
}