{
  "type": "Feature",
  "properties": {
    "addr:full":"Fonteinstraat 24 Menen (rekkem) West-Vlaanderen 8930",
    "addr:housenumber":"24",
    "addr:postcode":"8930",
    "addr:street":"Fonteinstraat",
    "iso:country":"BE",
    "sg:address":"Fonteinstraat 24",
    "sg:city":"Menen (rekkem)",
    "sg:classifiers":[
        {
            "category":"Farming",
            "subcategory":"Livestock Farm",
            "type":"Manufacturing & Wholesale Goods"
        }
    ],
    "sg:phone":"+32 56 41 62 38",
    "sg:postcode":"8930",
    "sg:province":"West-Vlaanderen",
    "sg:tags":[
        "buyer"
    ],
    "wof:name":"Lietaer A",
    "wof:placetype":"venue"
},
  "geometry": {"coordinates":[3.1209149361,50.7961845398],"type":"Point"}
}