{
  "type": "Feature",
  "properties": {
    "iso:country":"BE",
    "sg:address":"Beselarestraat 46",
    "sg:city":"Zonnebeke",
    "sg:orig_category":"Cr\u00e9meries",
    "sg:phone":"+32 51 77 81 93",
    "sg:postcode":"8980",
    "sg:province":"West-Vlaanderen",
    "wof:name":"Hubert Verbrugge",
    "wof:placetype":"venue"
},
  "geometry": {"coordinates":[3.0038709641,50.8691291809],"type":"Point"}
}