{
  "type": "Feature",
  "properties": {
    "iso:country":"BE",
    "sg:address":"Kapellestraat 30",
    "sg:city":"Evergem",
    "sg:orig_category":"Imprimeries and copyshops",
    "sg:phone":"+32 9 258 25 32",
    "sg:postcode":"9940",
    "sg:province":"Oost-Vlaanderen",
    "wof:name":"Lehoucq",
    "wof:placetype":"venue"
},
  "geometry": {"coordinates":[3.7103140354,51.110824585],"type":"Point"}
}