{
  "type": "Feature",
  "properties": {
    "iso:country":"BE",
    "sg:address":"Antwerpsesteenweg 346",
    "sg:city":"Kapellen",
    "sg:classifiers":[
        {
            "category":"Home & Garden",
            "subcategory":"Carpets & Floor Coverings",
            "type":"Retail Goods"
        }
    ],
    "sg:phone":"+32 3 660 11 22",
    "sg:postcode":"2950",
    "sg:province":"Antwerpen",
    "sg:tags":[
        "delivery",
        "-",
        "van"
    ],
    "wof:name":"Garage Rietje",
    "wof:placetype":"venue"
},
  "geometry": {"coordinates":[4.4395570755,51.2981948853],"type":"Point"}
}