{
  "type": "Feature",
  "properties": {
    "addr:full":"Chauss\u00c9e De Wavre 1089 Oudergem/auderghem Bruxelles-Capitale 1160",
    "addr:postcode":"1089;1160",
    "addr:street":"Chausse\u0301E De Wavre",
    "iso:country":"BE",
    "sg:address":"Chauss\u00c9e De Wavre 1089",
    "sg:city":"Oudergem/auderghem",
    "sg:orig_category":"Quincailleries",
    "sg:phone":"+32 2 649 16 48",
    "sg:postcode":"1160",
    "sg:province":"Bruxelles-Capitale",
    "wof:name":"Maison Wuyts",
    "wof:placetype":"venue"
},
  "geometry": {"coordinates":[4.3999581337,50.8242874146],"type":"Point"}
}