{
  "type": "Feature",
  "properties": {
    "iso:country":"BE",
    "sg:address":"Route De Valenciennes \u00e0 Mons 102",
    "sg:city":"Quaregnon (wasmuel)",
    "sg:classifiers":[
        {
            "category":"Retail",
            "subcategory":"Auto Repair",
            "type":"Services"
        }
    ],
    "sg:phone":"+32 65 78 56 40",
    "sg:postcode":"7390",
    "sg:province":"Hainaut",
    "sg:tags":[
        "garage"
    ],
    "wof:name":"Hallot Michel Sprl",
    "wof:placetype":"venue"
},
  "geometry": {"coordinates":[3.8651049137,50.4428939819],"type":"Point"}
}