{
  "type": "Feature",
  "properties": {
    "iso:country":"BE",
    "sg:address":"Rue Des Meuniers 10",
    "sg:city":"Remicourt (pousset)",
    "sg:classifiers":[
        {
            "category":"Real Estate",
            "subcategory":"Architect",
            "type":"Services"
        }
    ],
    "sg:phone":"+32 19 54 65 55",
    "sg:postcode":"4350",
    "sg:province":"Li\u00e8ge",
    "wof:name":"Fran\u00e7ois Navez H",
    "wof:placetype":"venue"
},
  "geometry": {"coordinates":[5.3025598526,50.6932601929],"type":"Point"}
}