{
  "type": "Feature",
  "properties": {
    "addr:full":"Gentstraat 57 Deinze Oost-Vlaanderen 9800",
    "addr:housenumber":"57",
    "addr:postcode":"9800",
    "addr:street":"Gentstraat",
    "iso:country":"BE",
    "sg:address":"Gentstraat 57",
    "sg:city":"Deinze",
    "sg:classifiers":[
        {
            "category":"Professional",
            "subcategory":"Management & Consulting",
            "type":"Services"
        }
    ],
    "sg:phone":"+32 9 380 35 11",
    "sg:postcode":"9800",
    "sg:province":"Oost-Vlaanderen",
    "sg:tags":[
        "consultant",
        "agency",
        "advertising"
    ],
    "wof:name":"Ferrum Advertising Bvba",
    "wof:placetype":"venue"
},
  "geometry": {"coordinates":[3.5342290401,50.9799118042],"type":"Point"}
}