{
  "type": "Feature",
  "properties": {
    "iso:country":"BE",
    "sg:address":"Place Th\u00c9odore Foguenne 8",
    "sg:city":"Chaudfontaine",
    "sg:classifiers":[
        {
            "category":"Cafe",
            "type":"Food & Drink"
        }
    ],
    "sg:phone":"+32 4 367 11 80",
    "sg:postcode":"4051",
    "sg:province":"Li\u00e8ge",
    "sg:tags":[
        "caf\u00e9s"
    ],
    "wof:name":"Caf\u00c9 Chez Georgette",
    "wof:placetype":"venue"
},
  "geometry": {"coordinates":[5.6325130463,50.6008796692],"type":"Point"}
}