{
  "type": "Feature",
  "properties": {
    "addr:full":"Iddergemstraat 61 Denderleeuw Oost-Vlaanderen 9470",
    "addr:housenumber":"61",
    "addr:postcode":"9470",
    "addr:street":"Iddergemstraat",
    "iso:country":"BE",
    "sg:address":"Iddergemstraat 61",
    "sg:city":"Denderleeuw",
    "sg:classifiers":[
        {
            "category":"Transit Center",
            "subcategory":"Freight",
            "type":"Transportation"
        }
    ],
    "sg:phone":"+32 53 68 12 72",
    "sg:postcode":"9470",
    "sg:province":"Oost-Vlaanderen",
    "sg:tags":[
        "import",
        "export",
        "-"
    ],
    "wof:name":"Toli Nv",
    "wof:placetype":"venue"
},
  "geometry": {"coordinates":[4.056137085,50.8759307861],"type":"Point"}
}