{
  "type": "Feature",
  "properties": {
    "addr:full":"Onze Lieve Vrouwstraat 10 Berchem Antwerpen 2600",
    "addr:housenumber":"10",
    "addr:postcode":"2600",
    "addr:street":"Onze Lieve Vrouwstraat;Antwerpen",
    "iso:country":"BE",
    "sg:address":"Onze Lieve Vrouwstraat 10",
    "sg:city":"Berchem",
    "sg:orig_category":"V\u00e9hicules automobiles",
    "sg:phone":"+32 3 287 30 30",
    "sg:postcode":"2600",
    "sg:province":"Antwerpen",
    "wof:name":"B.c.s. Toyota",
    "wof:placetype":"venue"
},
  "geometry": {"coordinates":[4.4167890549,51.1943092346],"type":"Point"}
}