{
  "type": "Feature",
  "properties": {
    "addr:full":"Edeschoolstraat 19 Wetteren Oost-Vlaanderen 9230",
    "addr:housenumber":"19",
    "addr:postcode":"9230",
    "addr:street":"Edeschoolstraat",
    "iso:country":"BE",
    "sg:address":"Edeschoolstraat 19",
    "sg:city":"Wetteren",
    "sg:orig_category":"Huishoudapparaten, televisies and radio's",
    "sg:phone":"+32 9 252 20 73",
    "sg:postcode":"9230",
    "sg:province":"Oost-Vlaanderen",
    "wof:name":"R De Roover Nadine-vereecke",
    "wof:placetype":"venue"
},
  "geometry": {"coordinates":[3.8399550915,51.0108833313],"type":"Point"}
}