{
  "type": "Feature",
  "properties": {
    "addr:full":"Rue De La-roche 42 Rendeux Luxembourg 6987",
    "addr:housenumber":"42",
    "addr:postcode":"6987",
    "addr:street":"Rue De La-Roche",
    "iso:country":"BE",
    "sg:address":"Rue De La-roche 42",
    "sg:city":"Rendeux",
    "sg:orig_category":"Epiceries",
    "sg:phone":"+32 84 47 71 53",
    "sg:postcode":"6987",
    "sg:province":"Luxembourg",
    "wof:name":"Gabrielle Bodson",
    "wof:placetype":"venue"
},
  "geometry": {"coordinates":[5.5134000778,50.2321205139],"type":"Point"}
}