{
  "type": "Feature",
  "properties": {
    "iso:country":"BE",
    "sg:address":"Knollestraat 13",
    "sg:city":"Veurne",
    "sg:classifiers":[
        {
            "category":"Shopping",
            "type":"Retail Goods"
        }
    ],
    "sg:phone":"+32 58 31 33 63",
    "sg:postcode":"8630",
    "sg:province":"West-Vlaanderen",
    "sg:tags":[
        "product",
        "cleaning",
        "maintenance"
    ],
    "wof:name":"Horecanet",
    "wof:placetype":"venue"
},
  "geometry": {"coordinates":[2.722028017,51.0494842529],"type":"Point"}
}