{
  "type": "Feature",
  "properties": {
    "addr:full":"Ducp\u00c9tiauxlaan 59 Sint-gillis/saint-gilles Bruxelles-Capitale 1060",
    "addr:housenumber":"59",
    "addr:postcode":"1060",
    "addr:street":"Ducpe\u0301Tiauxlaan",
    "iso:country":"BE",
    "sg:address":"Ducp\u00c9tiauxlaan 59",
    "sg:city":"Sint-gillis/saint-gilles",
    "sg:orig_category":"Herstelling and restauratie van meubelen",
    "sg:phone":"+32 2 538 66 90",
    "sg:postcode":"1060",
    "sg:province":"Bruxelles-Capitale",
    "wof:name":"H. Lopez",
    "wof:placetype":"venue"
},
  "geometry": {"coordinates":[4.3505349159,50.8233757019],"type":"Point"}
}