{
  "type": "Feature",
  "properties": {
    "iso:country":"BE",
    "sg:address":"Hameau Du Cocriamont 25",
    "sg:city":"Tournai",
    "sg:orig_category":"Eleveurs de bovins",
    "sg:phone":"+32 69 35 22 31",
    "sg:postcode":"7522",
    "sg:province":"Hainaut",
    "wof:name":"Bruno Bayart",
    "wof:placetype":"venue"
},
  "geometry": {"coordinates":[3.3053200245,50.6299591064],"type":"Point"}
}