{
  "type": "Feature",
  "properties": {
    "iso:country":"BE",
    "sg:address":"Avenue De La Grotte 47",
    "sg:city":"Esneux (tilff)",
    "sg:classifiers":[
        {
            "category":"Shopping",
            "subcategory":"Antiques",
            "type":"Retail Goods"
        }
    ],
    "sg:phone":"+32 4 388 28 12",
    "sg:postcode":"4130",
    "sg:province":"Li\u00e8ge",
    "sg:tags":[
        "restoration"
    ],
    "wof:name":"Duvivier A",
    "wof:placetype":"venue"
},
  "geometry": {"coordinates":[5.5788149834,50.5628814697],"type":"Point"}
}