{
  "type": "Feature",
  "properties": {
    "iso:country":"BE",
    "sg:address":"Sint-truidersteenweg 282",
    "sg:city":"Hasselt",
    "sg:classifiers":[
        {
            "category":"Real Estate",
            "subcategory":"Real Estate Services",
            "type":"Services"
        }
    ],
    "sg:phone":"+32 11 28 19 77",
    "sg:postcode":"3500",
    "sg:province":"Limburg",
    "wof:name":"Haumontex",
    "wof:placetype":"venue"
},
  "geometry": {"coordinates":[5.3274111748,50.9180641174],"type":"Point"}
}