{
  "type": "Feature",
  "properties": {
    "addr:full":"Laurierstraat 16 Gent (zwijnaarde) Oost-Vlaanderen 9052",
    "addr:housenumber":"16",
    "addr:postcode":"9052",
    "addr:street":"Laurierstraat",
    "iso:country":"BE",
    "sg:address":"Laurierstraat 16",
    "sg:city":"Gent (zwijnaarde)",
    "sg:classifiers":[
        {
            "category":"Health Services",
            "subcategory":"Dentist",
            "type":"Services"
        }
    ],
    "sg:phone":"+32 9 221 25 77",
    "sg:postcode":"9052",
    "sg:province":"Oost-Vlaanderen",
    "wof:name":"Huyghe Philippe",
    "wof:placetype":"venue"
},
  "geometry": {"coordinates":[3.7167270184,51.0002937317],"type":"Point"}
}