{
  "type": "Feature",
  "properties": {
    "iso:country":"BE",
    "sg:address":"Rue De Namur 12",
    "sg:city":"Nivelles",
    "sg:classifiers":[
        {
            "category":"Professional",
            "subcategory":"Employment Agencies",
            "type":"Services"
        }
    ],
    "sg:phone":"+32 67 22 14 40",
    "sg:postcode":"1400",
    "sg:province":"Brabant Wallon",
    "sg:tags":[
        "temping",
        "clerical",
        "-"
    ],
    "wof:name":"Amis Arrow Interim",
    "wof:placetype":"venue"
},
  "geometry": {"coordinates":[4.3255329132,50.5979042053],"type":"Point"}
}