{
  "type": "Feature",
  "properties": {
    "iso:country":"BE",
    "sg:address":"Rue De La Hestre 11",
    "sg:city":"Chapelle-lez-herlaimont",
    "sg:orig_category":"V\u00e9hicules automobiles. Entretien and r\u00e9parations de voitures",
    "sg:phone":"+32 64 45 01 18",
    "sg:postcode":"7160",
    "sg:province":"Hainaut",
    "wof:name":"Garage Chapelle Motor",
    "wof:placetype":"venue"
},
  "geometry": {"coordinates":[4.2832660675,50.4671478271],"type":"Point"}
}