{
  "type": "Feature",
  "properties": {
    "addr:full":"Rue Paul Pastur 264 Quaregnon Hainaut 7390",
    "addr:housenumber":"264",
    "addr:postcode":"7390",
    "addr:street":"Rue Paul Pastur",
    "iso:country":"BE",
    "sg:address":"Rue Paul Pastur 264",
    "sg:city":"Quaregnon",
    "sg:classifiers":[
        {
            "category":"Sports & Exercise",
            "subcategory":"Swimming Pool",
            "type":"Entertainment"
        }
    ],
    "sg:phone":"+32 65 78 29 03",
    "sg:postcode":"7390",
    "sg:province":"Hainaut",
    "sg:tags":[
        "tank",
        "septic"
    ],
    "wof:name":"Wery M",
    "wof:placetype":"venue"
},
  "geometry": {"coordinates":[3.8571479321,50.4482002258],"type":"Point"}
}