{
  "type": "Feature",
  "properties": {
    "addr:full":"Moorselbaan 86 Aalst Oost-Vlaanderen 9300",
    "addr:housenumber":"86",
    "addr:postcode":"9300",
    "addr:street":"Moorselbaan",
    "iso:country":"BE",
    "sg:address":"Moorselbaan 86",
    "sg:city":"Aalst",
    "sg:orig_category":"Electrom\u00e9nager, t\u00e9l\u00e9visions and radios. Mat\u00e9riel de T\u00e9l\u00e9communication",
    "sg:phone":"+32 53 21 24 75",
    "sg:postcode":"9300",
    "sg:province":"Oost-Vlaanderen",
    "wof:name":"Willocx",
    "wof:placetype":"venue"
},
  "geometry": {"coordinates":[4.0496821404,50.9417495728],"type":"Point"}
}