{
  "type": "Feature",
  "properties": {
    "addr:full":"Rue De Lizin 3 Ouffet Li\u00e8ge 4590",
    "addr:housenumber":"3",
    "addr:postcode":"4590",
    "addr:street":"Rue De Lizin",
    "iso:country":"BE",
    "sg:address":"Rue De Lizin 3",
    "sg:city":"Ouffet",
    "sg:classifiers":[
        {
            "category":"Mining & Drilling",
            "type":"Manufacturing & Wholesale Goods"
        }
    ],
    "sg:phone":"+32 86 36 67 84",
    "sg:postcode":"4590",
    "sg:province":"Li\u00e8ge",
    "sg:tags":[
        "quarry"
    ],
    "wof:name":"Carri\u00e8res Troydo Sa",
    "wof:placetype":"venue"
},
  "geometry": {"coordinates":[5.4621558189,50.4574775696],"type":"Point"}
}