{
  "type": "Feature",
  "properties": {
    "iso:country":"BE",
    "sg:address":"Rue Longue 98",
    "sg:city":"Beauvechain",
    "sg:classifiers":[
        {
            "category":"Professional",
            "subcategory":"Accounting & Tax Preparation",
            "type":"Services"
        }
    ],
    "sg:phone":"+32 10 86 81 26",
    "sg:postcode":"1320",
    "sg:province":"Brabant Wallon",
    "sg:tags":[
        "accountant"
    ],
    "wof:name":"Leheureux C",
    "wof:placetype":"venue"
},
  "geometry": {"coordinates":[4.7939090729,50.7677726746],"type":"Point"}
}