{
  "type": "Feature",
  "properties": {
    "iso:country":"BE",
    "sg:address":"Preachesdreef 4",
    "sg:city":"Moeskroen/mouscron",
    "sg:orig_category":"Rundveehouders",
    "sg:phone":"+32 56 48 83 57",
    "sg:postcode":"7711",
    "sg:province":"Hainaut",
    "wof:name":"Julien Vandewalle",
    "wof:placetype":"venue"
},
  "geometry": {"coordinates":[3.2873129845,50.7340736389],"type":"Point"}
}