{
  "type": "Feature",
  "properties": {
    "iso:country":"BE",
    "sg:address":"Ketelstraat 7",
    "sg:city":"Geetbets",
    "sg:orig_category":"Epiceries. Journaux",
    "sg:phone":"+32 11 58 77 84",
    "sg:postcode":"3454",
    "sg:province":"Vlaams-Brabant",
    "wof:name":"Vos - Knapen",
    "wof:placetype":"venue"
},
  "geometry": {"coordinates":[5.1588439941,50.8946838379],"type":"Point"}
}