{
  "type": "Feature",
  "properties": {
    "addr:full":"Kauwstraat 1007 Herzele Oost-Vlaanderen 9550",
    "addr:postcode":"1007;9550",
    "addr:street":"Kauwstraat;Oost-Vlaanderen",
    "iso:country":"BE",
    "sg:address":"Kauwstraat 1007",
    "sg:city":"Herzele",
    "sg:orig_category":"Voertuigen",
    "sg:phone":"+32 54 50 17 46",
    "sg:postcode":"9550",
    "sg:province":"Oost-Vlaanderen",
    "wof:name":"Fiat Turtelboom",
    "wof:placetype":"venue"
},
  "geometry": {"coordinates":[3.9222109318,50.8559875488],"type":"Point"}
}