{
  "type": "Feature",
  "properties": {
    "addr:full":"Slachthuisplein 12 Landen Vlaams-Brabant 3400",
    "addr:housenumber":"12",
    "addr:postcode":"3400",
    "addr:street":"Slachthuisplein",
    "iso:country":"BE",
    "sg:address":"Slachthuisplein 12",
    "sg:city":"Landen",
    "sg:orig_category":"Plomberie, chauffage and installations sanitaires",
    "sg:phone":"+32 11 83 15 95",
    "sg:postcode":"3400",
    "sg:province":"Vlaams-Brabant",
    "wof:name":"Goffings Patrick",
    "wof:placetype":"venue"
},
  "geometry": {"coordinates":[5.0798501968,50.7580184937],"type":"Point"}
}