{
  "type": "Feature",
  "properties": {
    "iso:country":"BE",
    "sg:address":"Joseph Dujardinstraat 8",
    "sg:city":"Anderlecht/anderlecht",
    "sg:orig_category":"Artsen and specialisten",
    "sg:phone":"+32 2 522 32 87",
    "sg:postcode":"1070",
    "sg:province":"Bruxelles-Capitale",
    "wof:name":"Claire Janssens",
    "wof:placetype":"venue"
},
  "geometry": {"coordinates":[4.3249650002,50.8363571167],"type":"Point"}
}