{
  "type": "Feature",
  "properties": {
    "addr:full":"Rue Rittweger 35 Ukkel/uccle Bruxelles-Capitale 1180",
    "addr:housenumber":"35",
    "addr:postcode":"1180",
    "addr:street":"Rue Rittweger;/",
    "iso:country":"BE",
    "sg:address":"Rue Rittweger 35",
    "sg:city":"Ukkel/uccle",
    "sg:orig_category":"Rev\u00eatements pour sols and murs. Eclairage et \u00e9quipements du foyer. Peinture",
    "sg:phone":"+32 2 376 65 41",
    "sg:postcode":"1180",
    "sg:province":"Bruxelles-Capitale",
    "wof:name":"Spyros D\u00c9cor",
    "wof:placetype":"venue"
},
  "geometry": {"coordinates":[4.3343749046,50.7986793518],"type":"Point"}
}