{
  "type": "Feature",
  "properties": {
    "addr:full":"Olenseweg 49 Geel Antwerpen 2440",
    "addr:housenumber":"49",
    "addr:postcode":"2440",
    "addr:street":"Olenseweg",
    "iso:country":"BE",
    "sg:address":"Olenseweg 49",
    "sg:city":"Geel",
    "sg:classifiers":[
        {
            "category":"Building & Trades",
            "subcategory":"Construction",
            "type":"Services"
        }
    ],
    "sg:phone":"+32 14 58 52 14",
    "sg:postcode":"2440",
    "sg:province":"Antwerpen",
    "sg:tags":[
        "work",
        "public"
    ],
    "wof:name":"Molse Bouwonderneming Nv",
    "wof:placetype":"venue"
},
  "geometry": {"coordinates":[4.9363298416,51.1664085388],"type":"Point"}
}