{
  "type": "Feature",
  "properties": {
    "iso:country":"BE",
    "sg:address":"Langestraat 82",
    "sg:city":"Denderleeuw (welle)",
    "sg:classifiers":[
        {
            "category":"Arena",
            "subcategory":"Sports Club",
            "type":"Entertainment"
        }
    ],
    "sg:phone":"+32 53 67 03 91",
    "sg:postcode":"9473",
    "sg:province":"Oost-Vlaanderen",
    "wof:name":"Snooker Time",
    "wof:placetype":"venue"
},
  "geometry": {"coordinates":[4.0507068634,50.8983612061],"type":"Point"}
}