{
  "type": "Feature",
  "properties": {
    "addr:full":"Ruisbroeksesteenweg 75 Vorst/forest Bruxelles-Capitale 1190",
    "addr:housenumber":"75",
    "addr:postcode":"1190",
    "addr:street":"Ruisbroeksesteenweg;/ Forest",
    "iso:country":"BE",
    "sg:address":"Ruisbroeksesteenweg 75",
    "sg:city":"Vorst/forest",
    "sg:orig_category":"Meubelzaken, woning- and keukeninrichting",
    "sg:phone":"+32 2 376 60 86",
    "sg:postcode":"1190",
    "sg:province":"Bruxelles-Capitale",
    "wof:name":"Polypal",
    "wof:placetype":"venue"
},
  "geometry": {"coordinates":[4.315308094,50.7993545532],"type":"Point"}
}