{
  "type": "Feature",
  "properties": {
    "addr:full":"Blekerijstraat 33 Gent Oost-Vlaanderen 9000",
    "addr:housenumber":"33",
    "addr:postcode":"9000",
    "addr:street":"Blekerijstraat;Oost-Vlaanderen",
    "iso:country":"BE",
    "sg:address":"Blekerijstraat 33",
    "sg:city":"Gent",
    "sg:orig_category":"Belastingconsulenten Diverse juridische dienstverlening",
    "sg:phone":"+32 9 223 44 09",
    "sg:postcode":"9000",
    "sg:province":"Oost-Vlaanderen",
    "wof:name":"Koenraad Van Acker",
    "wof:placetype":"venue"
},
  "geometry": {"coordinates":[3.731372118,51.0599555969],"type":"Point"}
}