{
  "type": "Feature",
  "properties": {
    "addr:full":"Rue Des Ecoliers 5 Oudergem Bruxelles-Capitale 1160",
    "addr:housenumber":"5",
    "addr:postcode":"1160",
    "addr:street":"Rue Des Ecoliers",
    "iso:country":"BE",
    "sg:address":"Rue Des Ecoliers 5",
    "sg:city":"Oudergem",
    "sg:orig_category":"Gestion des d\u00e9charges and sites d\u00e9finitifs de stockage",
    "sg:phone":"+32 2 676 48 62",
    "sg:postcode":"1160",
    "sg:province":"Bruxelles-Capitale",
    "wof:name":"Parc \u00c0 Conteneurs",
    "wof:placetype":"venue"
},
  "geometry": {"coordinates":[4.4223198891,50.8158988953],"type":"Point"}
}