{
  "type": "Feature",
  "properties": {
    "addr:full":"Rue De Cl\u00e9cy 59 Beyne-heusay (queue-du-bois) Li\u00e8ge 4610",
    "addr:housenumber":"59",
    "addr:postcode":"4610",
    "addr:street":"Rue De Cle\u0301Cy",
    "iso:country":"BE",
    "sg:address":"Rue De Cl\u00e9cy 59",
    "sg:city":"Beyne-heusay (queue-du-bois)",
    "sg:classifiers":[
        {
            "category":"Arts & Performance",
            "subcategory":"Symphony",
            "type":"Entertainment"
        }
    ],
    "sg:phone":"+32 4 362 12 61",
    "sg:postcode":"4610",
    "sg:province":"Li\u00e8ge",
    "sg:tags":[
        "orchestra"
    ],
    "wof:name":"Laredo",
    "wof:placetype":"venue"
},
  "geometry": {"coordinates":[5.6611189842,50.6181983948],"type":"Point"}
}