{
  "type": "Feature",
  "properties": {
    "addr:full":"Kerkplein 5b1 Beerse Antwerpen 2340",
    "addr:housenumber":"5b1",
    "addr:postcode":"2340",
    "addr:street":"Kerkplein",
    "iso:country":"BE",
    "sg:address":"Kerkplein 5b1",
    "sg:city":"Beerse",
    "sg:orig_category":"Boucheries",
    "sg:phone":"+32 14 61 10 31",
    "sg:postcode":"2340",
    "sg:province":"Antwerpen",
    "wof:name":"Jozef Knaeps",
    "wof:placetype":"venue"
},
  "geometry": {"coordinates":[4.8552918434,51.3195571899],"type":"Point"}
}