{
  "type": "Feature",
  "properties": {
    "addr:full":"Begoniastraat 1 Roeselare West-Vlaanderen 8800",
    "addr:housenumber":"1",
    "addr:postcode":"8800",
    "addr:street":"Begoniastraat",
    "iso:country":"BE",
    "sg:address":"Begoniastraat 1",
    "sg:city":"Roeselare",
    "sg:orig_category":"Woningbouw",
    "sg:phone":"+32 51 20 11 38",
    "sg:postcode":"8800",
    "sg:province":"West-Vlaanderen",
    "wof:name":"Caldugro",
    "wof:placetype":"venue"
},
  "geometry": {"coordinates":[3.1375639439,50.9392280579],"type":"Point"}
}