{
  "type": "Feature",
  "properties": {
    "iso:country":"BE",
    "sg:address":"Wingestraat 21",
    "sg:city":"Lubbeek",
    "sg:orig_category":"Kapsalons",
    "sg:phone":"+32 16 63 48 38",
    "sg:postcode":"3211",
    "sg:province":"Vlaams-Brabant",
    "wof:name":"Vera Nijs",
    "wof:placetype":"venue"
},
  "geometry": {"coordinates":[4.8792691231,50.8787612915],"type":"Point"}
}