{
  "type": "Feature",
  "properties": {
    "addr:full":"Rue Gilles Binchois 2 Binche Hainaut 7130",
    "addr:housenumber":"2",
    "addr:postcode":"7130",
    "addr:street":"Rue Gilles Binchois",
    "iso:country":"BE",
    "sg:address":"Rue Gilles Binchois 2",
    "sg:city":"Binche",
    "sg:orig_category":"Banques and organismes de cr\u00e9dit",
    "sg:phone":"+32 64 33 24 69",
    "sg:postcode":"7130",
    "sg:province":"Hainaut",
    "wof:name":"Bbl",
    "wof:placetype":"venue"
},
  "geometry": {"coordinates":[4.1712198257,50.4093513489],"type":"Point"}
}