{
  "type": "Feature",
  "properties": {
    "iso:country":"BE",
    "sg:address":"Rue Du Plit 7",
    "sg:city":"Frasnes-lez-anvaing",
    "sg:orig_category":"Dierenartsen",
    "sg:phone":"+32 69 86 73 30",
    "sg:postcode":"7910",
    "sg:province":"Hainaut",
    "wof:name":"Christian Fauconnier",
    "wof:placetype":"venue"
},
  "geometry": {"coordinates":[3.5601251125,50.6816482544],"type":"Point"}
}