{
  "type": "Feature",
  "properties": {
    "iso:country":"BE",
    "sg:address":"Vaartstraat 99",
    "sg:city":"Balen",
    "sg:orig_category":"Baby- and kinderkleding Babyspullen",
    "sg:phone":"+32 14 81 37 25",
    "sg:postcode":"2490",
    "sg:province":"Antwerpen",
    "wof:name":"Huis Bambino",
    "wof:placetype":"venue"
},
  "geometry": {"coordinates":[5.1606669426,51.1718101501],"type":"Point"}
}