{
  "type": "Feature",
  "properties": {
    "iso:country":"BE",
    "sg:address":"Gontrode Heirweg 142",
    "sg:city":"Melle",
    "sg:orig_category":"Diverse bouwafwerking and reiniging",
    "sg:phone":"+32 9 272 72 90",
    "sg:postcode":"9090",
    "sg:province":"Oost-Vlaanderen",
    "wof:name":"Resto Bouwspecialiteiten",
    "wof:placetype":"venue"
},
  "geometry": {"coordinates":[3.7919819355,50.9950561523],"type":"Point"}
}