{
  "type": "Feature",
  "properties": {
    "iso:country":"BE",
    "sg:address":"Chauss\u00e9e De Wavre 18",
    "sg:city":"Gembloux-sur-orneau (gembloux)",
    "sg:classifiers":[
        {
            "category":"Community Center",
            "subcategory":"Youth",
            "type":"Public Place"
        }
    ],
    "sg:phone":"+32 81 61 28 73",
    "sg:postcode":"5030",
    "sg:province":"Namur",
    "sg:tags":[
        "workshop",
        "sheltered"
    ],
    "wof:name":"Dauphins (les)",
    "wof:placetype":"venue"
},
  "geometry": {"coordinates":[4.6910791397,50.5723342896],"type":"Point"}
}