{
  "type": "Feature",
  "properties": {
    "addr:full":"Guldenroedestraat 20 Gent Oost-Vlaanderen 9030",
    "addr:housenumber":"20",
    "addr:postcode":"9030",
    "addr:street":"Guldenroedestraat;Oost-Vlaanderen",
    "iso:country":"BE",
    "sg:address":"Guldenroedestraat 20",
    "sg:city":"Gent",
    "sg:orig_category":"Instituts de beaut\u00e9",
    "sg:phone":"+32 9 226 58 02",
    "sg:postcode":"9030",
    "sg:province":"Oost-Vlaanderen",
    "wof:name":"P Fontaine",
    "wof:placetype":"venue"
},
  "geometry": {"coordinates":[3.6870799065,51.0758514404],"type":"Point"}
}