{
  "type": "Feature",
  "properties": {
    "addr:full":"Ninoofsesteenweg 22 Dilbeek Vlaams-Brabant 1700",
    "addr:housenumber":"22",
    "addr:postcode":"1700",
    "addr:street":"Ninoofsesteenweg",
    "iso:country":"BE",
    "sg:address":"Ninoofsesteenweg 22",
    "sg:city":"Dilbeek",
    "sg:orig_category":"Production de films, t\u00e9l\u00e9films and vid\u00e9os",
    "sg:phone":"+32 2 466 17 98",
    "sg:postcode":"1700",
    "sg:province":"Vlaams-Brabant",
    "wof:name":"Daniel Moerenhout",
    "wof:placetype":"venue"
},
  "geometry": {"coordinates":[4.2785201073,50.8451881409],"type":"Point"}
}