{
  "type": "Feature",
  "properties": {
    "iso:country":"BE",
    "sg:address":"Vrijheid 232",
    "sg:city":"Hoogstraten",
    "sg:classifiers":[
        {
            "category":"Shopping",
            "subcategory":"Shoes",
            "type":"Retail Goods"
        }
    ],
    "sg:phone":"+32 3 314 37 39",
    "sg:postcode":"2320",
    "sg:province":"Antwerpen",
    "sg:tags":[
        "slipper",
        "-"
    ],
    "wof:name":"Pompidon",
    "wof:placetype":"venue"
},
  "geometry": {"coordinates":[4.7596988678,51.3988685608],"type":"Point"}
}