{
  "type": "Feature",
  "properties": {
    "addr:full":"Rue Joseph Claes 48 Bruxelles (saint-gilles) Bruxelles-Capitale 1060",
    "addr:housenumber":"48",
    "addr:postcode":"1060",
    "addr:street":"Rue Joseph Claes",
    "iso:country":"BE",
    "sg:address":"Rue Joseph Claes 48",
    "sg:city":"Bruxelles (saint-gilles)",
    "sg:classifiers":[
        {
            "category":"Restaurant",
            "type":"Food & Drink"
        }
    ],
    "sg:phone":"+32 2 538 51 57",
    "sg:postcode":"1060",
    "sg:province":"Bruxelles-Capitale",
    "sg:tags":[
        "industrial",
        "kitchen",
        "catering"
    ],
    "wof:name":"Artivolaille",
    "wof:placetype":"venue"
},
  "geometry": {"coordinates":[4.3379979134,50.8329963684],"type":"Point"}
}