{
  "type": "Feature",
  "properties": {
    "iso:country":"BE",
    "sg:address":"Rue Arthur Maes 100",
    "sg:city":"Brussel/bruxelles",
    "sg:orig_category":"Pi\u00e8ces and accessoires de v\u00e9hicules automobiles D\u00e9taillants en pi\u00e8ces and accessoires de voitures. A",
    "sg:phone":"+32 2 724 90 90",
    "sg:postcode":"1130",
    "sg:province":"Bruxelles-Capitale",
    "wof:name":"Demimpex",
    "wof:placetype":"venue"
},
  "geometry": {"coordinates":[4.4233908653,50.8843765259],"type":"Point"}
}