{
  "type": "Feature",
  "properties": {
    "iso:country":"BE",
    "sg:address":"Avenue Houba De Strooper 73",
    "sg:city":"Brussel/bruxelles",
    "sg:orig_category":"RESTAURANTS: CAF\u00c9S",
    "sg:phone":"+32 2 478 66 44",
    "sg:postcode":"1020",
    "sg:province":"Bruxelles-Capitale",
    "wof:name":"Taverne L\u00b4aquarelle",
    "wof:placetype":"venue"
},
  "geometry": {"coordinates":[4.3396410942,50.8881492615],"type":"Point"}
}