{
  "type": "Feature",
  "properties": {
    "addr:full":"Onkerzelestraat 150 Geraardsbergen (onkerzele) Oost-Vlaanderen 9500",
    "addr:housenumber":"150",
    "addr:postcode":"9500",
    "addr:street":"Onkerzelestraat",
    "iso:country":"BE",
    "sg:address":"Onkerzelestraat 150",
    "sg:city":"Geraardsbergen (onkerzele)",
    "sg:classifiers":[
        {
            "category":"Health Services",
            "subcategory":"Doctor",
            "type":"Services"
        }
    ],
    "sg:phone":"+32 54 41 45 15",
    "sg:postcode":"9500",
    "sg:province":"Oost-Vlaanderen",
    "sg:tags":[
        "medicinephysicians",
        "surgeon"
    ],
    "wof:name":"Coug\u00e9 R",
    "wof:placetype":"venue"
},
  "geometry": {"coordinates":[3.8943850994,50.7744750977],"type":"Point"}
}