{
  "type": "Feature",
  "properties": {
    "iso:country":"BE",
    "sg:address":"Avenue Circulaire 144a",
    "sg:city":"Bruxelles (uccle)",
    "sg:classifiers":[
        {
            "category":"Personal",
            "subcategory":"Nail Salon",
            "type":"Services"
        }
    ],
    "sg:phone":"+32 2 374 35 48",
    "sg:postcode":"1180",
    "sg:province":"Bruxelles-Capitale",
    "sg:tags":[
        "pedicure"
    ],
    "wof:name":"Boussery M",
    "wof:placetype":"venue"
},
  "geometry": {"coordinates":[4.3559398651,50.7980308533],"type":"Point"}
}