{
  "type": "Feature",
  "properties": {
    "iso:country":"BE",
    "sg:address":"Blankenbergse Steenweg 45",
    "sg:city":"Zuienkerke",
    "sg:orig_category":"Installation de menuiserie en bois and plastique",
    "sg:phone":"+32 50 41 57 53",
    "sg:postcode":"8377",
    "sg:province":"West-Vlaanderen",
    "wof:name":"Vanhoutte",
    "wof:placetype":"venue"
},
  "geometry": {"coordinates":[3.1644880772,51.2854347229],"type":"Point"}
}