{
  "type": "Feature",
  "properties": {
    "addr:full":"Rue Boucart 2 Court-saint-etienne Brabant Wallon 1490",
    "addr:housenumber":"2;1490",
    "addr:street":"Rue Boucart",
    "iso:country":"BE",
    "sg:address":"Rue Boucart 2",
    "sg:city":"Court-saint-etienne",
    "sg:orig_category":"Plomberie, chauffage and installations sanitaires",
    "sg:phone":"+32 10 61 56 04",
    "sg:postcode":"1490",
    "sg:province":"Brabant Wallon",
    "wof:name":"Demortier Patrick",
    "wof:placetype":"venue"
},
  "geometry": {"coordinates":[4.5963010788,50.6459274292],"type":"Point"}
}