{
  "type": "Feature",
  "properties": {
    "iso:country":"BE",
    "sg:address":"Rue Erasme 31",
    "sg:city":"Bruxelles (anderlecht)",
    "sg:classifiers":[
        {
            "category":"Building & Trades",
            "subcategory":"Plumbing",
            "type":"Services"
        }
    ],
    "sg:phone":"+32 2 344 91 93",
    "sg:postcode":"1070",
    "sg:province":"Bruxelles-Capitale",
    "sg:tags":[
        "contractor"
    ],
    "wof:name":"Castelli (ets) Sprl",
    "wof:placetype":"venue"
},
  "geometry": {"coordinates":[4.3064289093,50.8379821777],"type":"Point"}
}