{
  "type": "Feature",
  "properties": {
    "iso:country":"BE",
    "sg:address":"Opitterstraat 3",
    "sg:city":"Bree",
    "sg:classifiers":[
        {
            "category":"Bars & Pubs",
            "type":"Food & Drink"
        }
    ],
    "sg:phone":"+32 89 46 35 02",
    "sg:postcode":"3960",
    "sg:province":"Limburg",
    "sg:tags":[
        "tavern"
    ],
    "wof:name":"Mistral Bistro",
    "wof:placetype":"venue"
},
  "geometry": {"coordinates":[5.5996069908,51.1414031982],"type":"Point"}
}