{
  "type": "Feature",
  "properties": {
    "iso:country":"BE",
    "sg:address":"Statieplaats 2",
    "sg:city":"Lichtervelde",
    "sg:classifiers":[
        {
            "category":"Personal",
            "subcategory":"Beauty Salon",
            "type":"Services"
        }
    ],
    "sg:phone":"+32 51 72 21 93",
    "sg:postcode":"8810",
    "sg:province":"West-Vlaanderen",
    "sg:tags":[
        "lady",
        "-",
        "hairdressing"
    ],
    "wof:name":"Coiffure Andr\u00e9 Bvba",
    "wof:placetype":"venue"
},
  "geometry": {"coordinates":[3.1411089897,51.0263137817],"type":"Point"}
}