{
  "type": "Feature",
  "properties": {
    "iso:country":"BE",
    "sg:address":"Impasse De La Couronne 9",
    "sg:city":"Liege",
    "sg:classifiers":[
        {
            "category":"Restaurant",
            "type":"Food & Drink"
        }
    ],
    "sg:phone":"+32 4 222 02 02",
    "sg:postcode":"4000",
    "sg:province":"Li\u00e8ge",
    "wof:name":"Le Th\u00c8me",
    "wof:placetype":"venue"
},
  "geometry": {"coordinates":[5.5796451569,50.6479225159],"type":"Point"}
}