{
  "type": "Feature",
  "properties": {
    "addr:full":"Boulevard Charlemagne 1 Brussel/bruxelles Bruxelles-Capitale 1000",
    "addr:housenumber":"1",
    "addr:postcode":"1000",
    "addr:street":"Boulevard Charlemagne;/",
    "iso:country":"BE",
    "sg:address":"Boulevard Charlemagne 1",
    "sg:city":"Brussel/bruxelles",
    "sg:orig_category":"Tabac. Journaux",
    "sg:phone":"+32 2 230 88 89",
    "sg:postcode":"1000",
    "sg:province":"Bruxelles-Capitale",
    "wof:name":"Librairie Charlemagne",
    "wof:placetype":"venue"
},
  "geometry": {"coordinates":[4.3823270798,50.8445777893],"type":"Point"}
}