{
  "type": "Feature",
  "properties": {
    "addr:full":"Melsensstraat 34 Brussel (brussel) Bruxelles-Capitale 1000",
    "addr:housenumber":"34",
    "addr:postcode":"1000",
    "addr:street":"Melsensstraat",
    "iso:country":"BE",
    "sg:address":"Melsensstraat 34",
    "sg:city":"Brussel (brussel)",
    "sg:orig_category":"Politieke organisaties",
    "sg:phone":"+32 2 549 00 20",
    "sg:postcode":"1000",
    "sg:province":"Bruxelles-Capitale",
    "wof:name":"Vld",
    "wof:placetype":"venue"
},
  "geometry": {"coordinates":[4.3486261368,50.8502731323],"type":"Point"}
}