{
  "type": "Feature",
  "properties": {
    "iso:country":"BE",
    "sg:address":"Pastoor Pitetlaan 30",
    "sg:city":"Begijnendijk",
    "sg:orig_category":"Sportcentra",
    "sg:phone":"+32 16 56 98 60",
    "sg:postcode":"3130",
    "sg:province":"Vlaams-Brabant",
    "wof:name":"De Tumkens",
    "wof:placetype":"venue"
},
  "geometry": {"coordinates":[4.7850999832,50.9867515564],"type":"Point"}
}