{
  "type": "Feature",
  "properties": {
    "addr:full":"Rue Emile Delcour 88 Saint-georges-sur-meuse Li\u00e8ge 4470",
    "addr:housenumber":"88",
    "addr:postcode":"4470",
    "addr:street":"Rue Emile Delcour",
    "iso:country":"BE",
    "sg:address":"Rue Emile Delcour 88",
    "sg:city":"Saint-georges-sur-meuse",
    "sg:orig_category":"Enseignement maternel and primaire",
    "sg:phone":"+32 4 275 10 23",
    "sg:postcode":"4470",
    "sg:province":"Li\u00e8ge",
    "wof:name":"E.f.c.f. Sur-les-bois",
    "wof:placetype":"venue"
},
  "geometry": {"coordinates":[5.3722500801,50.599521637],"type":"Point"}
}