{
  "type": "Feature",
  "properties": {
    "addr:full":"De Beukelaer Pareinlaan 1 Herentals Antwerpen 2200",
    "addr:housenumber":"1",
    "addr:postcode":"2200",
    "addr:street":"De Beukelaer Pareinlaan",
    "iso:country":"BE",
    "sg:address":"De Beukelaer Pareinlaan 1",
    "sg:city":"Herentals",
    "sg:orig_category":"Non-Classified Establishments",
    "sg:phone":"+32 14 24 12 11",
    "sg:postcode":"2200",
    "sg:province":"Antwerpen",
    "wof:name":"Lu, General Biscuits Belgi\u00eb Nv",
    "wof:placetype":"venue"
},
  "geometry": {"coordinates":[4.8081898689,51.1761817932],"type":"Point"}
}