{
  "type": "Feature",
  "properties": {
    "iso:country":"BE",
    "sg:address":"Route De Trois-ponts 175",
    "sg:city":"Stavelot",
    "sg:classifiers":[
        {
            "category":"Travel",
            "subcategory":"Resort",
            "type":"Entertainment"
        }
    ],
    "sg:phone":"+32 80 68 45 91",
    "sg:postcode":"4970",
    "sg:province":"Li\u00e8ge",
    "sg:tags":[
        "rental",
        "accomodation",
        "holiday",
        "-"
    ],
    "wof:name":"Domaine Long Pr\u00e9",
    "wof:placetype":"venue"
},
  "geometry": {"coordinates":[5.8905367851,50.3782424927],"type":"Point"}
}