{
  "type": "Feature",
  "properties": {
    "iso:country":"BE",
    "sg:address":"Ter Elstlei 8",
    "sg:city":"Duffel",
    "sg:orig_category":"Groenten and fruit Gh",
    "sg:phone":"+32 15 31 16 67",
    "sg:postcode":"2570",
    "sg:province":"Antwerpen",
    "wof:name":"Lodewijk Verlinden",
    "wof:placetype":"venue"
},
  "geometry": {"coordinates":[4.4971170425,51.0908927917],"type":"Point"}
}