{
  "type": "Feature",
  "properties": {
    "iso:country":"BE",
    "sg:address":"Chemin De Naast 35",
    "sg:city":"Braine-le-comte",
    "sg:orig_category":"Eleveurs de bovins",
    "sg:phone":"+32 67 33 31 65",
    "sg:postcode":"7090",
    "sg:province":"Hainaut",
    "wof:name":"Andre Desmet",
    "wof:placetype":"venue"
},
  "geometry": {"coordinates":[4.1247348785,50.5805015564],"type":"Point"}
}