{
  "type": "Feature",
  "properties": {
    "iso:country":"BE",
    "sg:address":"Mellestraat 144",
    "sg:city":"Kortrijk (heule)",
    "sg:classifiers":[
        {
            "category":"Recreation",
            "subcategory":"Arcade",
            "type":"Entertainment"
        }
    ],
    "sg:phone":"+32 56 35 58 85",
    "sg:postcode":"8501",
    "sg:province":"West-Vlaanderen",
    "sg:tags":[
        "machine",
        "amusement"
    ],
    "wof:name":"Mondial Automatic Corp",
    "wof:placetype":"venue"
},
  "geometry": {"coordinates":[3.2291030884,50.8508682251],"type":"Point"}
}