{
  "type": "Feature",
  "properties": {
    "addr:full":"Boomgaardstraat 101 Antwerpen Antwerpen 2018",
    "addr:housenumber":"101",
    "addr:postcode":"2018",
    "addr:street":"Boomgaardstraat",
    "iso:country":"BE",
    "sg:address":"Boomgaardstraat 101",
    "sg:city":"Antwerpen",
    "sg:orig_category":"Boekhouders",
    "sg:phone":"+32 475 60 10 16",
    "sg:postcode":"2018",
    "sg:province":"Antwerpen",
    "wof:name":"Timotheus Quaeyhaegens",
    "wof:placetype":"venue"
},
  "geometry": {"coordinates":[4.4237799644,51.2011642456],"type":"Point"}
}