{
  "type": "Feature",
  "properties": {
    "iso:country":"BE",
    "sg:address":"Zevenkavendreef 29",
    "sg:city":"Wevelgem",
    "sg:orig_category":"Hout and afgeleiden Gh Houtbewerking and -behandeling IJzerwaren, bouw- and verfmaterialen",
    "sg:phone":"+32 56 41 20 64",
    "sg:postcode":"8560",
    "sg:province":"West-Vlaanderen",
    "wof:name":"Vercruysse Houthandel",
    "wof:placetype":"venue"
},
  "geometry": {"coordinates":[3.2088880539,50.846950531],"type":"Point"}
}