{
  "type": "Feature",
  "properties": {
    "addr:full":"Oudenaardsesteenweg 15 Erpe-mere Oost-Vlaanderen 9420",
    "addr:housenumber":"15",
    "addr:postcode":"9420",
    "addr:street":"Oudenaardsesteenweg",
    "iso:country":"BE",
    "sg:address":"Oudenaardsesteenweg 15",
    "sg:city":"Erpe-mere",
    "sg:orig_category":"Sportclubs",
    "sg:phone":"+32 53 80 38 73",
    "sg:postcode":"9420",
    "sg:province":"Oost-Vlaanderen",
    "wof:name":"W.c. Sportkomitee Aalst",
    "wof:placetype":"venue"
},
  "geometry": {"coordinates":[3.9916300774,50.9412269592],"type":"Point"}
}