{
  "type": "Feature",
  "properties": {
    "addr:full":"De Keyserlei 59 Antwerpen Antwerpen 2018",
    "addr:housenumber":"59",
    "addr:postcode":"2018",
    "addr:street":"De Keyserlei",
    "iso:country":"BE",
    "sg:address":"De Keyserlei 59",
    "sg:city":"Antwerpen",
    "sg:orig_category":"H\u00f4tels",
    "sg:phone":"+32 3 232 14 43",
    "sg:postcode":"2018",
    "sg:province":"Antwerpen",
    "wof:name":"Hotel Florida",
    "wof:placetype":"venue"
},
  "geometry": {"coordinates":[4.4200801849,51.2173881531],"type":"Point"}
}