{
  "type": "Feature",
  "properties": {
    "addr:full":"Ruelle Fay 12 Namur (malonne) Namur 5020",
    "addr:housenumber":"12",
    "addr:postcode":"5020",
    "addr:street":"Ruelle Fay",
    "iso:country":"BE",
    "sg:address":"Ruelle Fay 12",
    "sg:city":"Namur (malonne)",
    "sg:classifiers":[
        {
            "category":"Manufacturing",
            "subcategory":"Metals",
            "type":"Manufacturing & Wholesale Goods"
        }
    ],
    "sg:phone":"+32 81 44 03 64",
    "sg:postcode":"5020",
    "sg:province":"Namur",
    "sg:tags":[
        "ironwork"
    ],
    "wof:name":"Henry Ets",
    "wof:placetype":"venue"
},
  "geometry": {"coordinates":[4.7952418327,50.4352035522],"type":"Point"}
}