{
  "type": "Feature",
  "properties": {
    "addr:full":"Chauss\u00e9e De Ruisbroek 111 Bruxelles (forest) Bruxelles-Capitale 1190",
    "addr:housenumber":"111",
    "addr:postcode":"1190",
    "addr:street":"Chausse\u0301E De Ruisbroek",
    "iso:country":"BE",
    "sg:address":"Chauss\u00e9e De Ruisbroek 111",
    "sg:city":"Bruxelles (forest)",
    "sg:classifiers":[
        {
            "category":"Manufacturing",
            "subcategory":"Buildings",
            "type":"Manufacturing & Wholesale Goods"
        }
    ],
    "sg:phone":"+32 2 333 01 20",
    "sg:postcode":"1190",
    "sg:province":"Bruxelles-Capitale",
    "sg:tags":[
        "platform",
        "work"
    ],
    "wof:name":"Petrus Neon",
    "wof:placetype":"venue"
},
  "geometry": {"coordinates":[4.3137540817,50.7988853455],"type":"Point"}
}