{
  "type": "Feature",
  "properties": {
    "addr:full":"Geraardsbergsestraat 18 Brakel Oost-Vlaanderen 9660",
    "addr:housenumber":"18",
    "addr:postcode":"9660",
    "addr:street":"Geraardsbergsestraat",
    "iso:country":"BE",
    "sg:address":"Geraardsbergsestraat 18",
    "sg:city":"Brakel",
    "sg:orig_category":"Slagers",
    "sg:phone":"+32 55 42 55 34",
    "sg:postcode":"9660",
    "sg:province":"Oost-Vlaanderen",
    "wof:name":"Renmans",
    "wof:placetype":"venue"
},
  "geometry": {"coordinates":[3.7594079971,50.7979507446],"type":"Point"}
}