{
  "type": "Feature",
  "properties": {
    "addr:full":"Graatakker 175b4 Turnhout Antwerpen 2300",
    "addr:housenumber":"175b4",
    "addr:postcode":"2300",
    "addr:street":"Graatakker",
    "iso:country":"BE",
    "sg:address":"Graatakker 175b4",
    "sg:city":"Turnhout",
    "sg:orig_category":"Artsen and specialisten",
    "sg:phone":"+32 14 43 62 83",
    "sg:postcode":"2300",
    "sg:province":"Antwerpen",
    "wof:name":"Werner Nagels",
    "wof:placetype":"venue"
},
  "geometry": {"coordinates":[4.9489398003,51.3134498596],"type":"Point"}
}