{
  "type": "Feature",
  "properties": {
    "addr:full":"Ichtegemstraat 8 Koekelare West-Vlaanderen 8680",
    "addr:housenumber":"8",
    "addr:postcode":"8680",
    "addr:street":"Ichtegemstraat",
    "iso:country":"BE",
    "sg:address":"Ichtegemstraat 8",
    "sg:city":"Koekelare",
    "sg:orig_category":"Advocaten and juridische adviseurs",
    "sg:phone":"+32 51 58 15 66",
    "sg:postcode":"8680",
    "sg:province":"West-Vlaanderen",
    "wof:name":"B. Dehullu",
    "wof:placetype":"venue"
},
  "geometry": {"coordinates":[2.9798500538,51.0893249512],"type":"Point"}
}