{
  "type": "Feature",
  "properties": {
    "addr:full":"Lange Zoutstraat 18 Aalst Oost-Vlaanderen 9300",
    "addr:housenumber":"18",
    "addr:postcode":"9300",
    "addr:street":"Lange Zoutstraat",
    "iso:country":"BE",
    "sg:address":"Lange Zoutstraat 18",
    "sg:city":"Aalst",
    "sg:classifiers":[
        {
            "category":"Shopping",
            "subcategory":"Shoes",
            "type":"Retail Goods"
        }
    ],
    "sg:phone":"+32 53 77 18 22",
    "sg:postcode":"9300",
    "sg:province":"Oost-Vlaanderen",
    "sg:tags":[
        "slipper",
        "-"
    ],
    "wof:name":"Tornado",
    "wof:placetype":"venue"
},
  "geometry": {"coordinates":[4.0394492149,50.9375],"type":"Point"}
}