{
  "type": "Feature",
  "properties": {
    "addr:full":"Nieuwstraat 28 Wervik West-Vlaanderen 8940",
    "addr:housenumber":"28",
    "addr:postcode":"8940",
    "addr:street":"Nieuwstraat",
    "iso:country":"BE",
    "sg:address":"Nieuwstraat 28",
    "sg:city":"Wervik",
    "sg:orig_category":"Alimentation sp\u00e9cialis\u00e9e",
    "sg:phone":"+32 56 31 11 03",
    "sg:postcode":"8940",
    "sg:province":"West-Vlaanderen",
    "wof:name":"Huis 't Korenveld",
    "wof:placetype":"venue"
},
  "geometry": {"coordinates":[3.0415410995,50.7786216736],"type":"Point"}
}