{
  "type": "Feature",
  "properties": {
    "addr:full":"Rue Du Bois Blanc 30 Leuze-en-hainaut Hainaut 7900",
    "addr:housenumber":"30",
    "addr:postcode":"7900",
    "addr:street":"Rue Du Bois Blanc",
    "iso:country":"BE",
    "sg:address":"Rue Du Bois Blanc 30",
    "sg:city":"Leuze-en-hainaut",
    "sg:orig_category":"Maatschappelijke dienstverlening",
    "sg:phone":"+32 69 66 17 28",
    "sg:postcode":"7900",
    "sg:province":"Hainaut",
    "wof:name":"Rhms",
    "wof:placetype":"venue"
},
  "geometry": {"coordinates":[3.6179740429,50.6029510498],"type":"Point"}
}