{
  "type": "Feature",
  "properties": {
    "iso:country":"BE",
    "sg:address":"Rue Du Commerce 210",
    "sg:city":"Dour",
    "sg:classifiers":[
        {
            "category":"Cafe",
            "type":"Food & Drink"
        }
    ],
    "sg:phone":"+32 65 63 28 91",
    "sg:postcode":"7370",
    "sg:province":"Hainaut",
    "sg:tags":[
        "caf\u00e9s"
    ],
    "wof:name":"Caf\u00c9 Le Gavroche",
    "wof:placetype":"venue"
},
  "geometry": {"coordinates":[3.7520399094,50.3984107971],"type":"Point"}
}