{
  "type": "Feature",
  "properties": {
    "addr:full":"Rue De Marcinelle 49 Ham-sur-heure-nalinnes (nalinnes) Hainaut 6120",
    "addr:housenumber":"49",
    "addr:postcode":"6120",
    "addr:street":"Rue De Marcinelle",
    "iso:country":"BE",
    "sg:address":"Rue De Marcinelle 49",
    "sg:city":"Ham-sur-heure-nalinnes (nalinnes)",
    "sg:classifiers":[
        {
            "category":"Banks & Credit Unions",
            "subcategory":"Financial Services",
            "type":"Services"
        }
    ],
    "sg:phone":"+32 71 21 32 74",
    "sg:postcode":"6120",
    "sg:province":"Hainaut",
    "sg:tags":[
        "loan",
        "mortgage"
    ],
    "wof:name":"Nicaise Assurances",
    "wof:placetype":"venue"
},
  "geometry": {"coordinates":[4.4416241646,50.3424682617],"type":"Point"}
}