{
  "type": "Feature",
  "properties": {
    "iso:country":"BE",
    "sg:address":"Lemanstraat 7",
    "sg:city":"Sint-katelijne-waver",
    "sg:classifiers":[
        {
            "category":"Bars & Pubs",
            "type":"Food & Drink"
        }
    ],
    "sg:phone":"+32 15 31 68 08",
    "sg:postcode":"2860",
    "sg:province":"Antwerpen",
    "wof:name":"Club (de)",
    "wof:placetype":"venue"
},
  "geometry": {"coordinates":[4.5332360268,51.0692977905],"type":"Point"}
}