{
  "type": "Feature",
  "properties": {
    "addr:full":"Luzernestraat 41 Schaarbeek/schaerbeek Bruxelles-Capitale 1030",
    "addr:housenumber":"41",
    "addr:postcode":"1030",
    "addr:street":"Luzernestraat",
    "iso:country":"BE",
    "sg:address":"Luzernestraat 41",
    "sg:city":"Schaarbeek/schaerbeek",
    "sg:orig_category":"Boekhouders",
    "sg:postcode":"1030",
    "sg:province":"Bruxelles-Capitale",
    "wof:name":"Eddy Vandevelde",
    "wof:placetype":"venue"
},
  "geometry": {"coordinates":[4.3929018974,50.8549842834],"type":"Point"}
}