{
  "type": "Feature",
  "properties": {
    "addr:full":"Tongersesteenweg 51 Sint-truiden Limburg 3800",
    "addr:housenumber":"51",
    "addr:postcode":"3800",
    "addr:street":"Tongersesteenweg",
    "iso:country":"BE",
    "sg:address":"Tongersesteenweg 51",
    "sg:city":"Sint-truiden",
    "sg:classifiers":[
        {
            "category":"Cafe",
            "type":"Food & Drink"
        }
    ],
    "sg:phone":"+32 11 69 14 99",
    "sg:postcode":"3800",
    "sg:province":"Limburg",
    "sg:tags":[
        "caf\u00e9s"
    ],
    "wof:name":"Anita Noens",
    "wof:placetype":"venue"
},
  "geometry": {"coordinates":[5.1946787834,50.8117752075],"type":"Point"}
}