{
  "type": "Feature",
  "properties": {
    "addr:full":"Rue De La Victoire 221 Bruxelles (saint-gilles) Bruxelles-Capitale 1060",
    "addr:housenumber":"221",
    "addr:postcode":"1060",
    "addr:street":"Rue De La Victoire",
    "iso:country":"BE",
    "sg:address":"Rue De La Victoire 221",
    "sg:city":"Bruxelles (saint-gilles)",
    "sg:classifiers":[
        {
            "category":"Banks & Credit Unions",
            "subcategory":"Investment Brokerage",
            "type":"Services"
        }
    ],
    "sg:phone":"+32 2 537 90 42",
    "sg:postcode":"1060",
    "sg:province":"Bruxelles-Capitale",
    "sg:tags":[
        "auditor"
    ],
    "wof:name":"Lamolle M",
    "wof:placetype":"venue"
},
  "geometry": {"coordinates":[4.3538398743,50.826007843],"type":"Point"}
}