{
  "type": "Feature",
  "properties": {
    "iso:country":"BE",
    "sg:address":"Herenweg 24",
    "sg:city":"Tongeren",
    "sg:classifiers":[
        {
            "category":"Professional",
            "subcategory":"Printing & Photocopies",
            "type":"Services"
        }
    ],
    "sg:phone":"+32 12 23 95 18",
    "sg:postcode":"3700",
    "sg:province":"Limburg",
    "sg:tags":[
        "-",
        "offset"
    ],
    "wof:name":"Moermans M",
    "wof:placetype":"venue"
},
  "geometry": {"coordinates":[5.4487118721,50.7762641907],"type":"Point"}
}