{
  "type": "Feature",
  "properties": {
    "iso:country":"BE",
    "sg:address":"Chauss\u00e9e De Gilly 99",
    "sg:city":"Charleroi (jumet)",
    "sg:classifiers":[
        {
            "category":"Insurance",
            "subcategory":"Insurance Agent",
            "type":"Services"
        }
    ],
    "sg:phone":"+32 71 35 27 98",
    "sg:postcode":"6040",
    "sg:province":"Hainaut",
    "sg:tags":[
        "broker"
    ],
    "wof:name":"Burton A",
    "wof:placetype":"venue"
},
  "geometry": {"coordinates":[4.4457678795,50.4418525696],"type":"Point"}
}