{
  "type": "Feature",
  "properties": {
    "iso:country":"BE",
    "sg:address":"Mechelsebaan 167",
    "sg:city":"Duffel",
    "sg:classifiers":[
        {
            "category":"Manufacturing",
            "subcategory":"Motor Vehicles & Parts",
            "type":"Manufacturing & Wholesale Goods"
        }
    ],
    "sg:phone":"+32 15 31 69 73",
    "sg:postcode":"2570",
    "sg:province":"Antwerpen",
    "sg:tags":[
        "machine",
        "-",
        "indivisible",
        "transport"
    ],
    "wof:name":"Cartrans Bvba",
    "wof:placetype":"venue"
},
  "geometry": {"coordinates":[4.4996418953,51.0823135376],"type":"Point"}
}