{
  "type": "Feature",
  "properties": {
    "addr:full":"Boterstraat 27 Ieper (groot) West-Vlaanderen 8900",
    "addr:housenumber":"27",
    "addr:postcode":"8900",
    "addr:street":"Boterstraat;Groot West-Vlaanderen",
    "iso:country":"BE",
    "sg:address":"Boterstraat 27",
    "sg:city":"Ieper (groot)",
    "sg:orig_category":"V\u00eatements. Textiles",
    "sg:phone":"+32 57 20 14 16",
    "sg:postcode":"8900",
    "sg:province":"West-Vlaanderen",
    "wof:name":"Veritas",
    "wof:placetype":"venue"
},
  "geometry": {"coordinates":[2.8832929134,50.8501434326],"type":"Point"}
}