{
  "type": "Feature",
  "properties": {
    "addr:full":"Chemin Du Pr\u00c9 Leftay 22 Spa Li\u00e8ge 4900",
    "addr:housenumber":"22",
    "addr:postcode":"4900",
    "addr:street":"Chemin Du Pre\u0301 Leftay",
    "iso:country":"BE",
    "sg:address":"Chemin Du Pr\u00c9 Leftay 22",
    "sg:city":"Spa",
    "sg:orig_category":"Vertalers and tolken",
    "sg:phone":"+32 87 77 35 60",
    "sg:postcode":"4900",
    "sg:province":"Li\u00e8ge",
    "wof:name":"Michel Rocour",
    "wof:placetype":"venue"
},
  "geometry": {"coordinates":[5.8806819916,50.4963684082],"type":"Point"}
}