{
  "type": "Feature",
  "properties": {
    "iso:country":"BE",
    "sg:address":"Hoenstraat 9",
    "sg:city":"Zonnebeke (beselare)",
    "sg:classifiers":[
        {
            "category":"Building & Trades",
            "subcategory":"Electrical",
            "type":"Services"
        }
    ],
    "sg:phone":"+32 57 46 67 37",
    "sg:postcode":"8980",
    "sg:province":"West-Vlaanderen",
    "sg:tags":[
        "electric",
        "-",
        "housewiring",
        "contractor"
    ],
    "wof:name":"Dedecker L",
    "wof:placetype":"venue"
},
  "geometry": {"coordinates":[3.0273139477,50.8536148071],"type":"Point"}
}