{
  "type": "Feature",
  "properties": {
    "addr:full":"Rue De Savoie 98a Sint-gillis/saint-gilles Bruxelles-Capitale 1060",
    "addr:housenumber":"98a",
    "addr:postcode":"1060",
    "addr:street":"Rue De Savoie",
    "iso:country":"BE",
    "sg:address":"Rue De Savoie 98a",
    "sg:city":"Sint-gillis/saint-gilles",
    "sg:orig_category":"Parfumeries",
    "sg:phone":"+32 2 539 29 42",
    "sg:postcode":"1060",
    "sg:province":"Bruxelles-Capitale",
    "wof:name":"Parfumerie De Bastogne",
    "wof:placetype":"venue"
},
  "geometry": {"coordinates":[4.3435769081,50.8235702515],"type":"Point"}
}