{
  "type": "Feature",
  "properties": {
    "iso:country":"BE",
    "sg:address":"Rue De La Station 32",
    "sg:city":"Tubize",
    "sg:orig_category":"D\u00e9molition d\u00b4immeubles and terrassements",
    "sg:phone":"+32 2 355 67 81",
    "sg:postcode":"1480",
    "sg:province":"Brabant Wallon",
    "wof:name":"Wastiau G. & Fils",
    "wof:placetype":"venue"
},
  "geometry": {"coordinates":[4.1570239067,50.7077598572],"type":"Point"}
}