{
  "type": "Feature",
  "properties": {
    "iso:country":"BE",
    "sg:address":"Moldergem 82",
    "sg:city":"Zwalm",
    "sg:orig_category":"Instituts de beaut\u00e9",
    "sg:phone":"+32 55 49 63 49",
    "sg:postcode":"9630",
    "sg:province":"Oost-Vlaanderen",
    "wof:name":"Karla Manssens",
    "wof:placetype":"venue"
},
  "geometry": {"coordinates":[3.7022418976,50.8628501892],"type":"Point"}
}