{
  "type": "Feature",
  "properties": {
    "iso:country":"BE",
    "sg:address":"Sint-gertrudisstraat 57",
    "sg:city":"Machelen",
    "sg:classifiers":[
        {
            "category":"Professional",
            "subcategory":"Engineering",
            "type":"Services"
        }
    ],
    "sg:phone":"+32 2 251 00 11",
    "sg:postcode":"1830",
    "sg:province":"Vlaams-Brabant",
    "sg:tags":[
        "civil",
        "offices-"
    ],
    "wof:name":"Romanus X & Partners",
    "wof:placetype":"venue"
},
  "geometry": {"coordinates":[4.4324550629,50.913318634],"type":"Point"}
}