{
  "type": "Feature",
  "properties": {
    "addr:full":"Rue De Landelies 50 Charleroi (monceau-sur-sambre) Hainaut 6031",
    "addr:housenumber":"50",
    "addr:postcode":"6031",
    "addr:street":"Rue De Landelies",
    "iso:country":"BE",
    "sg:address":"Rue De Landelies 50",
    "sg:city":"Charleroi (monceau-sur-sambre)",
    "sg:classifiers":[
        {
            "category":"Shopping",
            "subcategory":"Books",
            "type":"Retail Goods"
        }
    ],
    "sg:phone":"+32 71 32 63 38",
    "sg:postcode":"6031",
    "sg:province":"Hainaut",
    "sg:tags":[
        "bookseller"
    ],
    "wof:name":"Librairie Du Hameau",
    "wof:placetype":"venue"
},
  "geometry": {"coordinates":[4.38022995,50.4121742249],"type":"Point"}
}