{
  "type": "Feature",
  "properties": {
    "iso:country":"BE",
    "sg:address":"Luikerweg 3",
    "sg:city":"Opwijk",
    "sg:classifiers":[
        {
            "category":"Personal",
            "subcategory":"Beauty Salon",
            "type":"Services"
        }
    ],
    "sg:phone":"+32 52 35 56 02",
    "sg:postcode":"1745",
    "sg:province":"Vlaams-Brabant",
    "sg:tags":[
        "de",
        "coiffure"
    ],
    "wof:name":"Christel Van De Velde",
    "wof:placetype":"venue"
},
  "geometry": {"coordinates":[4.1533842087,50.9697380066],"type":"Point"}
}