{
  "type": "Feature",
  "properties": {
    "iso:country":"BE",
    "sg:address":"Alfons Moerenhoutstraat 17",
    "sg:city":"Overijse",
    "sg:classifiers":[
        {
            "category":"Building & Trades",
            "subcategory":"Construction",
            "type":"Services"
        }
    ],
    "sg:phone":"+32 2 687 49 97",
    "sg:postcode":"3090",
    "sg:province":"Vlaams-Brabant",
    "sg:tags":[
        "stucco",
        "contractor"
    ],
    "wof:name":"De Saveur J",
    "wof:placetype":"venue"
},
  "geometry": {"coordinates":[4.5281181335,50.7682342529],"type":"Point"}
}