{
  "type": "Feature",
  "properties": {
    "iso:country":"BE",
    "sg:address":"Sint-sebastiaansplein 6",
    "sg:city":"Brakel",
    "sg:orig_category":"Eleveurs de bovins",
    "sg:phone":"+32 55 42 29 11",
    "sg:postcode":"9660",
    "sg:province":"Oost-Vlaanderen",
    "wof:name":"Christian Backaert",
    "wof:placetype":"venue"
},
  "geometry": {"coordinates":[3.7665109634,50.8331680298],"type":"Point"}
}