{
  "type": "Feature",
  "properties": {
    "iso:country":"BE",
    "sg:address":"Rempart De La Vierge 18b14",
    "sg:city":"Namur",
    "sg:orig_category":"Advocaten and juridische adviseurs",
    "sg:phone":"+32 81 22 67 30",
    "sg:postcode":"5000",
    "sg:province":"Namur",
    "wof:name":"Michel Borgers",
    "wof:placetype":"venue"
},
  "geometry": {"coordinates":[4.8562278748,50.4652824402],"type":"Point"}
}