{
  "type": "Feature",
  "properties": {
    "iso:country":"BE",
    "sg:address":"Avenue Edmond Leburton 11",
    "sg:city":"Waremme",
    "sg:classifiers":[
        {
            "category":"Restaurant",
            "type":"Food & Drink"
        }
    ],
    "sg:phone":"+32 19 33 14 91",
    "sg:postcode":"4300",
    "sg:province":"Li\u00e8ge",
    "wof:name":"San Marco",
    "wof:placetype":"venue"
},
  "geometry": {"coordinates":[5.257294178,50.6980285645],"type":"Point"}
}