{
  "type": "Feature",
  "properties": {
    "addr:full":"Tipstraat 61 Bilzen Limburg 3740",
    "addr:housenumber":"61",
    "addr:postcode":"3740",
    "addr:street":"Tipstraat",
    "iso:country":"BE",
    "sg:address":"Tipstraat 61",
    "sg:city":"Bilzen",
    "sg:classifiers":[
        {
            "category":"Wholesale",
            "subcategory":"Sporting Goods",
            "type":"Manufacturing & Wholesale Goods"
        }
    ],
    "sg:phone":"+32 56 50 63 90",
    "sg:postcode":"3740",
    "sg:province":"Limburg",
    "sg:tags":[
        "sport-",
        "kampeermateriaal"
    ],
    "wof:name":"Jera",
    "wof:placetype":"venue"
},
  "geometry": {"coordinates":[-6.286108017,53.3615188599],"type":"Point"}
}