{
  "type": "Feature",
  "properties": {
    "iso:country":"BE",
    "sg:address":"Kerkstraat 55",
    "sg:city":"Dilbeek (itterbeek)",
    "sg:classifiers":[
        {
            "category":"Government",
            "subcategory":"Fire Station",
            "type":"Public Place"
        }
    ],
    "sg:phone":"+32 2 569 54 00",
    "sg:postcode":"1701",
    "sg:province":"Vlaams-Brabant",
    "sg:tags":[
        "extinguisher"
    ],
    "wof:name":"Ifec Com Va",
    "wof:placetype":"venue"
},
  "geometry": {"coordinates":[4.2508568764,50.8394088745],"type":"Point"}
}