{
  "type": "Feature",
  "properties": {
    "addr:full":"Terboekt 57 Genk Limburg 3600",
    "addr:housenumber":"57",
    "addr:postcode":"3600",
    "addr:street":"Terboekt",
    "iso:country":"BE",
    "sg:address":"Terboekt 57",
    "sg:city":"Genk",
    "sg:classifiers":[
        {
            "category":"Professional",
            "subcategory":"Art Services",
            "type":"Services"
        }
    ],
    "sg:phone":"+32 89 61 22 61",
    "sg:postcode":"3600",
    "sg:province":"Limburg",
    "sg:tags":[
        "photographer"
    ],
    "wof:name":"Veekmans N",
    "wof:placetype":"venue"
},
  "geometry": {"coordinates":[5.5333881378,50.9425354004],"type":"Point"}
}