{
  "type": "Feature",
  "properties": {
    "iso:country":"BE",
    "sg:address":"Zwevegemsestraat 72",
    "sg:city":"Kortrijk",
    "sg:classifiers":[
        {
            "category":"Restaurant",
            "type":"Food & Drink"
        }
    ],
    "sg:phone":"+32 56 20 03 50",
    "sg:postcode":"8500",
    "sg:province":"West-Vlaanderen",
    "wof:name":"Pizza Italia",
    "wof:placetype":"venue"
},
  "geometry": {"coordinates":[3.2728390694,50.8241920471],"type":"Point"}
}