{
  "type": "Feature",
  "properties": {
    "addr:full":"Wijnbergstraat 182 Wevelgem West-Vlaanderen 8560",
    "addr:housenumber":"182",
    "addr:postcode":"8560",
    "addr:street":"Wijnbergstraat",
    "iso:country":"BE",
    "sg:address":"Wijnbergstraat 182",
    "sg:city":"Wevelgem",
    "sg:orig_category":"Electrom\u00e9nager, t\u00e9l\u00e9visions and radios. Air conditionn\u00e9 and ventilation. Mat\u00e9riel de contr\u00f4le des pr",
    "sg:phone":"+32 56 41 93 28",
    "sg:postcode":"8560",
    "sg:province":"West-Vlaanderen",
    "wof:name":"Eldema",
    "wof:placetype":"venue"
},
  "geometry": {"coordinates":[3.1652500629,50.8191108704],"type":"Point"}
}