{
  "type": "Feature",
  "properties": {
    "iso:country":"BE",
    "sg:address":"Europawijk 29",
    "sg:city":"Geel",
    "sg:orig_category":"Loodgieterij, verwarming and sanitaire installaties Pleisterwerk Zwembadinstallatie",
    "sg:phone":"+32 14 58 94 47",
    "sg:postcode":"2440",
    "sg:province":"Antwerpen",
    "wof:name":"Fa. Remy",
    "wof:placetype":"venue"
},
  "geometry": {"coordinates":[5.0356869698,51.2008132935],"type":"Point"}
}