{
  "type": "Feature",
  "properties": {
    "addr:full":"Rodenbachlaan 33 Kortrijk West-Vlaanderen 8501",
    "addr:housenumber":"33",
    "addr:postcode":"8501",
    "addr:street":"Rodenbachlaan",
    "iso:country":"BE",
    "sg:address":"Rodenbachlaan 33",
    "sg:city":"Kortrijk",
    "sg:classifiers":[
        {
            "category":"Building & Trades",
            "subcategory":"Landscaping Services",
            "type":"Services"
        }
    ],
    "sg:phone":"+32 56 35 50 41",
    "sg:postcode":"8501",
    "sg:province":"West-Vlaanderen",
    "sg:tags":[
        "etude",
        "technique",
        "ing\u00e9nierie"
    ],
    "wof:name":"Ppc Consult",
    "wof:placetype":"venue"
},
  "geometry": {"coordinates":[3.2336709499,50.8435592651],"type":"Point"}
}