{
  "type": "Feature",
  "properties": {
    "iso:country":"BE",
    "sg:address":"Avenue Louise 208",
    "sg:city":"Brussel/bruxelles",
    "sg:orig_category":"Avocats and conseillers juridiques",
    "sg:phone":"+32 2 646 46 36",
    "sg:postcode":"1050",
    "sg:province":"Bruxelles-Capitale",
    "wof:name":"B\u00c9n\u00c9dicte Belvigne",
    "wof:placetype":"venue"
},
  "geometry": {"coordinates":[4.356962204,50.8341941833],"type":"Point"}
}