{
  "type": "Feature",
  "properties": {
    "iso:country":"BE",
    "sg:address":"Rue Fran\u00c7ois-hittelet 129",
    "sg:city":"Jemeppe-sur-sambre",
    "sg:orig_category":"Enseignement maternel and primaire",
    "sg:phone":"+32 71 78 60 81",
    "sg:postcode":"5190",
    "sg:province":"Namur",
    "wof:name":"E.f.c.f. Baudouin I",
    "wof:placetype":"venue"
},
  "geometry": {"coordinates":[4.662378788,50.4588737488],"type":"Point"}
}