{
  "type": "Feature",
  "properties": {
    "iso:country":"BE",
    "sg:address":"Jan Van Rijswijcklaan 229 Box 1",
    "sg:city":"Antwerpen",
    "sg:classifiers":[
        {
            "category":"Professional",
            "subcategory":"Art Services",
            "type":"Services"
        }
    ],
    "sg:phone":"+32 3 237 64 30",
    "sg:postcode":"2020",
    "sg:province":"Antwerpen",
    "sg:tags":[
        "interior",
        "designer"
    ],
    "wof:name":"Muller H",
    "wof:placetype":"venue"
},
  "geometry": {"coordinates":[4.3934898376,51.1870574951],"type":"Point"}
}