{
  "type": "Feature",
  "properties": {
    "iso:country":"BE",
    "sg:address":"Karel Oomsstraat 16",
    "sg:city":"Antwerpen",
    "sg:classifiers":[
        {
            "category":"Manufacturing",
            "subcategory":"Tools & Machinery",
            "type":"Manufacturing & Wholesale Goods"
        }
    ],
    "sg:phone":"+32 3 216 15 04",
    "sg:postcode":"2018",
    "sg:province":"Antwerpen",
    "sg:tags":[
        "diamond"
    ],
    "wof:name":"Sankyo Belgium",
    "wof:placetype":"venue"
},
  "geometry": {"coordinates":[4.4098649025,51.197177887],"type":"Point"}
}