{
  "type": "Feature",
  "properties": {
    "iso:country":"BE",
    "sg:address":"Koning Leopoldlaan 77",
    "sg:city":"Lommel",
    "sg:classifiers":[
        {
            "category":"Cafe",
            "type":"Food & Drink"
        }
    ],
    "sg:phone":"+32 11 54 38 54",
    "sg:postcode":"3920",
    "sg:province":"Limburg",
    "sg:tags":[
        "caf\u00e9s"
    ],
    "wof:name":"Beta Partners",
    "wof:placetype":"venue"
},
  "geometry": {"coordinates":[5.3212661743,51.2292556763],"type":"Point"}
}