{
  "type": "Feature",
  "properties": {
    "iso:country":"BE",
    "sg:address":"Vissersstraat 17",
    "sg:city":"Blankenberge",
    "sg:orig_category":"Binnenhuisarchitecten",
    "sg:phone":"+32 50 41 51 75",
    "sg:postcode":"8370",
    "sg:province":"West-Vlaanderen",
    "wof:name":"Carolina Piers",
    "wof:placetype":"venue"
},
  "geometry": {"coordinates":[3.1266300678,51.3147888184],"type":"Point"}
}