{
  "type": "Feature",
  "properties": {
    "addr:full":"Markgravelei 61 Antwerpen Antwerpen 2018",
    "addr:housenumber":"61",
    "addr:postcode":"2018",
    "addr:street":"Markgravelei",
    "iso:country":"BE",
    "sg:address":"Markgravelei 61",
    "sg:city":"Antwerpen",
    "sg:classifiers":[
        {
            "category":"Personal",
            "subcategory":"Beauty Salon",
            "type":"Services"
        }
    ],
    "sg:phone":"+32 3 238 96 44",
    "sg:postcode":"2018",
    "sg:province":"Antwerpen",
    "sg:tags":[
        "lady",
        "-",
        "hairdressing"
    ],
    "wof:name":"Renaud & Co",
    "wof:placetype":"venue"
},
  "geometry": {"coordinates":[4.4005889893,51.1997337341],"type":"Point"}
}