{
  "type": "Feature",
  "properties": {
    "addr:full":"Rue Basse 8 Walcourt Namur 5651",
    "addr:housenumber":"8",
    "addr:postcode":"5651",
    "addr:street":"Rue Basse",
    "iso:country":"BE",
    "sg:address":"Rue Basse 8",
    "sg:city":"Walcourt",
    "sg:orig_category":"Bloemen and planten Speelgoed Verlichting and huishoudartikelen",
    "sg:phone":"+32 71 21 85 29",
    "sg:postcode":"5651",
    "sg:province":"Namur",
    "wof:name":"Le Bambou",
    "wof:placetype":"venue"
},
  "geometry": {"coordinates":[4.4262080193,50.2824401855],"type":"Point"}
}