{
  "type": "Feature",
  "properties": {
    "iso:country":"BE",
    "sg:address":"Nobelstraat 211",
    "sg:city":"Tremelo",
    "sg:orig_category":"Woningbouw",
    "sg:phone":"+32 16 53 01 91",
    "sg:postcode":"3128",
    "sg:province":"Vlaams-Brabant",
    "wof:name":"Our Home",
    "wof:placetype":"venue"
},
  "geometry": {"coordinates":[4.7430281639,51.0167045593],"type":"Point"}
}