{
  "type": "Feature",
  "properties": {
    "addr:full":"Rue L\u00e9on Theodor 26 Bruxelles (jette) Bruxelles-Capitale 1090",
    "addr:housenumber":"26",
    "addr:postcode":"1090",
    "addr:street":"Rue Le\u0301On Theodor",
    "iso:country":"BE",
    "sg:address":"Rue L\u00e9on Theodor 26",
    "sg:city":"Bruxelles (jette)",
    "sg:classifiers":[
        {
            "category":"Home & Garden",
            "subcategory":"Home Furnishings",
            "type":"Retail Goods"
        }
    ],
    "sg:phone":"+32 2 426 70 84",
    "sg:postcode":"1090",
    "sg:province":"Bruxelles-Capitale",
    "sg:tags":[
        "curtain",
        "-",
        "fixture"
    ],
    "wof:name":"New Decor",
    "wof:placetype":"venue"
},
  "geometry": {"coordinates":[4.3259940147,50.8739929199],"type":"Point"}
}