{
  "type": "Feature",
  "properties": {
    "addr:full":"Rue Du March\u00e9 Aux Porcs 6 Bruxelles Bruxelles-Capitale 1000",
    "addr:housenumber":"6",
    "addr:postcode":"1000",
    "addr:street":"Rue Du Marche\u0301 Aux Porcs",
    "iso:country":"BE",
    "sg:address":"Rue Du March\u00e9 Aux Porcs 6",
    "sg:city":"Bruxelles",
    "sg:classifiers":[
        {
            "category":"Professional",
            "subcategory":"Art Services",
            "type":"Services"
        }
    ],
    "sg:phone":"+32 2 219 69 55",
    "sg:postcode":"1000",
    "sg:province":"Bruxelles-Capitale",
    "sg:tags":[
        "-",
        "painter",
        "artist"
    ],
    "wof:name":"Stroobants Y",
    "wof:placetype":"venue"
},
  "geometry": {"coordinates":[4.345553875,50.8530845642],"type":"Point"}
}