{
  "type": "Feature",
  "properties": {
    "addr:full":"Korte Braamstraat 19 Schoten Antwerpen 2900",
    "addr:housenumber":"19",
    "addr:postcode":"2900",
    "addr:street":"Korte Braamstraat",
    "iso:country":"BE",
    "sg:address":"Korte Braamstraat 19",
    "sg:city":"Schoten",
    "sg:classifiers":[
        {
            "category":"Shopping",
            "subcategory":"Crafts & Fabrics",
            "type":"Retail Goods"
        }
    ],
    "sg:phone":"+32 3 658 78 08",
    "sg:postcode":"2900",
    "sg:province":"Antwerpen",
    "sg:tags":[
        "upholstery",
        "-"
    ],
    "wof:name":"Svenco Bvba",
    "wof:placetype":"venue"
},
  "geometry": {"coordinates":[4.4919958115,51.2412338257],"type":"Point"}
}