{
  "type": "Feature",
  "properties": {
    "addr:full":"Rue Du Tilleul 1 Evere Bruxelles-Capitale 1140",
    "addr:housenumber":"1",
    "addr:postcode":"1140",
    "addr:street":"Rue Du Tilleul",
    "iso:country":"BE",
    "sg:address":"Rue Du Tilleul 1",
    "sg:city":"Evere",
    "sg:orig_category":"Quincailleries. Maroquinerie Fab",
    "sg:phone":"+32 2 216 51 13",
    "sg:postcode":"1140",
    "sg:province":"Bruxelles-Capitale",
    "wof:name":"Hepco Becker",
    "wof:placetype":"venue"
},
  "geometry": {"coordinates":[4.3915638924,50.877620697],"type":"Point"}
}