{
  "type": "Feature",
  "properties": {
    "addr:full":"Overwinningstraat 59 Willebroek Antwerpen 2830",
    "addr:housenumber":"59",
    "addr:postcode":"2830",
    "addr:street":"Overwinningstraat",
    "iso:country":"BE",
    "sg:address":"Overwinningstraat 59",
    "sg:city":"Willebroek",
    "sg:classifiers":[
        {
            "category":"Retail",
            "subcategory":"Laundry & Dry Cleaning",
            "type":"Services"
        }
    ],
    "sg:phone":"+32 3 886 68 50",
    "sg:postcode":"2830",
    "sg:province":"Antwerpen",
    "sg:tags":[
        "dyer",
        "cleaner"
    ],
    "wof:name":"Speed Shop",
    "wof:placetype":"venue"
},
  "geometry": {"coordinates":[4.3597297668,51.0587806702],"type":"Point"}
}