{
  "type": "Feature",
  "properties": {
    "addr:full":"Recul\u00e9mont 17a Malmedy (bellevaux-lignueville) Li\u00e8ge 4960",
    "addr:housenumber":"17a",
    "addr:postcode":"4960",
    "addr:street":"Recule\u0301Mont",
    "iso:country":"BE",
    "sg:address":"Recul\u00e9mont 17a",
    "sg:city":"Malmedy (bellevaux-lignueville)",
    "sg:classifiers":[
        {
            "category":"Building & Trades",
            "subcategory":"Construction",
            "type":"Services"
        }
    ],
    "sg:phone":"+32 80 57 07 48",
    "sg:postcode":"4960",
    "sg:province":"Li\u00e8ge",
    "sg:tags":[
        "carpenter"
    ],
    "wof:name":"Goffinet P",
    "wof:placetype":"venue"
},
  "geometry": {"coordinates":[6.0264730453,50.3808784485],"type":"Point"}
}