{
  "type": "Feature",
  "properties": {
    "iso:country":"BE",
    "sg:address":"Kwadestraat 50",
    "sg:city":"Roeselare",
    "sg:orig_category":"Schoonheidssalons",
    "sg:phone":"+32 51 24 47 97",
    "sg:postcode":"8800",
    "sg:province":"West-Vlaanderen",
    "wof:name":"Claudine O.",
    "wof:placetype":"venue"
},
  "geometry": {"coordinates":[3.1662631035,50.9264717102],"type":"Point"}
}