{
  "type": "Feature",
  "properties": {
    "addr:full":"Aatsesteenweg 116 Edingen/enghien Hainaut 7850",
    "addr:housenumber":"116",
    "addr:postcode":"7850",
    "addr:street":"Aatsesteenweg",
    "iso:country":"BE",
    "sg:address":"Aatsesteenweg 116",
    "sg:city":"Edingen/enghien",
    "sg:orig_category":"Herstellingen and onderhoud van auto's",
    "sg:phone":"+32 2 395 60 90",
    "sg:postcode":"7850",
    "sg:province":"Hainaut",
    "wof:name":"Carrosserie Decoster",
    "wof:placetype":"venue"
},
  "geometry": {"coordinates":[4.0334601402,50.6914787292],"type":"Point"}
}