{
  "type": "Feature",
  "properties": {
    "addr:full":"Rue Du Pont 13 Hamoir Li\u00e8ge 4180",
    "addr:housenumber":"13",
    "addr:postcode":"4180",
    "addr:street":"Rue Du Pont",
    "iso:country":"BE",
    "sg:address":"Rue Du Pont 13",
    "sg:city":"Hamoir",
    "sg:orig_category":"Postkantoren",
    "sg:phone":"+32 86 38 80 94",
    "sg:postcode":"4180",
    "sg:province":"Li\u00e8ge",
    "wof:name":"La Poste",
    "wof:placetype":"venue"
},
  "geometry": {"coordinates":[5.5351471901,50.4257659912],"type":"Point"}
}