{
  "type": "Feature",
  "properties": {
    "iso:country":"BE",
    "sg:address":"Jozef De Veusterstraat 73",
    "sg:city":"Edegem",
    "sg:classifiers":[
        {
            "category":"Professional",
            "subcategory":"Art Services",
            "type":"Services"
        }
    ],
    "sg:phone":"+32 3 440 34 48",
    "sg:postcode":"2650",
    "sg:province":"Antwerpen",
    "sg:tags":[
        "interior",
        "designer"
    ],
    "wof:name":"Follens V",
    "wof:placetype":"venue"
},
  "geometry": {"coordinates":[4.4218950272,51.1577949524],"type":"Point"}
}