{
  "type": "Feature",
  "properties": {
    "addr:full":"Noordstraat 48 Kortrijk West-Vlaanderen 8500",
    "addr:housenumber":"48",
    "addr:postcode":"8500",
    "addr:street":"Noordstraat",
    "iso:country":"BE",
    "sg:address":"Noordstraat 48",
    "sg:city":"Kortrijk",
    "sg:orig_category":"Elektrische huishoudapparaten, radio and televisie Gh",
    "sg:phone":"+32 56 35 06 16",
    "sg:postcode":"8500",
    "sg:province":"West-Vlaanderen",
    "wof:name":"Abitare-sun",
    "wof:placetype":"venue"
},
  "geometry": {"coordinates":[3.2554280758,50.8312301636],"type":"Point"}
}