{
  "type": "Feature",
  "properties": {
    "addr:full":"La Batte 10 Li\u00c8ge Li\u00e8ge 4000",
    "addr:housenumber":"10",
    "addr:postcode":"4000",
    "addr:street":"Batte",
    "iso:country":"BE",
    "sg:address":"La Batte 10",
    "sg:city":"Li\u00c8ge",
    "sg:orig_category":"Agences d'exp\u00e9dition",
    "sg:phone":"+32 4 222 28 94",
    "sg:postcode":"4000",
    "sg:province":"Li\u00e8ge",
    "wof:name":"Maas Navigat. Int\u00c9rieure",
    "wof:placetype":"venue"
},
  "geometry": {"coordinates":[5.5801968575,50.6456336975],"type":"Point"}
}