{
  "type": "Feature",
  "properties": {
    "iso:country":"BE",
    "sg:address":"Overwinningsstraat 43",
    "sg:city":"Willebroek",
    "sg:orig_category":"Baby- and kinderkleding",
    "sg:phone":"+32 3 886 75 52",
    "sg:postcode":"2830",
    "sg:province":"Antwerpen",
    "wof:name":"Huis Rosita",
    "wof:placetype":"venue"
},
  "geometry": {"coordinates":[4.3595900536,51.0588111877],"type":"Point"}
}