{
  "type": "Feature",
  "properties": {
    "iso:country":"BE",
    "sg:address":"Rue De L'ath\u00c9n\u00c9e 38",
    "sg:city":"Tournai",
    "sg:orig_category":"Avocats and conseillers juridiques",
    "sg:phone":"+32 69 21 43 07",
    "sg:postcode":"7500",
    "sg:province":"Hainaut",
    "wof:name":"B. Dapsens",
    "wof:placetype":"venue"
},
  "geometry": {"coordinates":[3.3956151009,50.60987854],"type":"Point"}
}