{
  "type": "Feature",
  "properties": {
    "addr:full":"Lange Molenstraat 114a Brugge (sint-andries) West-Vlaanderen 8200",
    "addr:housenumber":"114a",
    "addr:postcode":"8200",
    "addr:street":"Lange Molenstraat",
    "iso:country":"BE",
    "sg:address":"Lange Molenstraat 114a",
    "sg:city":"Brugge (sint-andries)",
    "sg:classifiers":[
        {
            "category":"Health Services",
            "subcategory":"Nursing And Care Facility",
            "type":"Services"
        }
    ],
    "sg:phone":"+32 50 38 98 34",
    "sg:postcode":"8200",
    "sg:province":"West-Vlaanderen",
    "sg:tags":[
        "home"
    ],
    "wof:name":"Lescrauwaet L",
    "wof:placetype":"venue"
},
  "geometry": {"coordinates":[3.1904699802,51.1992111206],"type":"Point"}
}