{
  "type": "Feature",
  "properties": {
    "addr:full":"Noordzandstraat 81 Brugge West-Vlaanderen 8000",
    "addr:housenumber":"81",
    "addr:postcode":"8000",
    "addr:street":"Noordzandstraat",
    "iso:country":"BE",
    "sg:address":"Noordzandstraat 81",
    "sg:city":"Brugge",
    "sg:classifiers":[
        {
            "category":"Shopping",
            "subcategory":"Clothing, Apparel, & Fashions",
            "type":"Retail Goods"
        }
    ],
    "sg:phone":"+32 50 34 00 64",
    "sg:postcode":"8000",
    "sg:province":"West-Vlaanderen",
    "sg:tags":[
        "v\u00eatements",
        "pour",
        "dame"
    ],
    "wof:name":"Huis Ivoire",
    "wof:placetype":"venue"
},
  "geometry": {"coordinates":[3.2186770439,51.2062835693],"type":"Point"}
}