{
  "type": "Feature",
  "properties": {
    "addr:full":"Schampbergstraat 34-38 Hasselt Limburg 3511",
    "addr:postcode":"34-38;3511",
    "addr:street":"Schampbergstraat",
    "iso:country":"BE",
    "sg:address":"Schampbergstraat 34-38",
    "sg:city":"Hasselt",
    "sg:orig_category":"Vitrage. Eclairage et \u00e9quipements du foyer. Installation de serres, double vitrage and fen\u00eatres",
    "sg:phone":"+32 11 85 85 85",
    "sg:postcode":"3511",
    "sg:province":"Limburg",
    "wof:name":"Boermans Glasindustrie",
    "wof:placetype":"venue"
},
  "geometry": {"coordinates":[5.3034238815,50.9432487488],"type":"Point"}
}