{
  "type": "Feature",
  "properties": {
    "iso:country":"BE",
    "sg:address":"Rue De Grammont 1",
    "sg:city":"Silly (bassilly)",
    "sg:classifiers":[
        {
            "category":"Wholesale",
            "subcategory":"Wine & Distilled Alcoholic Beverages",
            "type":"Manufacturing & Wholesale Goods"
        }
    ],
    "sg:phone":"+32 68 55 24 45",
    "sg:postcode":"7830",
    "sg:province":"Hainaut",
    "sg:tags":[
        "whol",
        "-",
        "spirit",
        "mfg"
    ],
    "wof:name":"Caves De Silly (les) Sprl",
    "wof:placetype":"venue"
},
  "geometry": {"coordinates":[3.9307498932,50.6788597107],"type":"Point"}
}