{
  "type": "Feature",
  "properties": {
    "addr:full":"En Marexhe 40 Herstal Li\u00e8ge 4040",
    "addr:housenumber":"40",
    "addr:postcode":"4040",
    "iso:country":"BE",
    "sg:address":"En Marexhe 40",
    "sg:city":"Herstal",
    "sg:orig_category":"Salons de coiffure. Centres de relaxation and bien-\u00eatre",
    "sg:phone":"+32 4 264 93 03",
    "sg:postcode":"4040",
    "sg:province":"Li\u00e8ge",
    "wof:name":"Coiff'fina",
    "wof:placetype":"venue"
},
  "geometry": {"coordinates":[5.6246500015,50.6592979431],"type":"Point"}
}