{
  "type": "Feature",
  "properties": {
    "iso:country":"BE",
    "sg:address":"Leuvensesteenweg 353",
    "sg:city":"Schaarbeek/schaerbeek",
    "sg:classifiers":[
        {
            "category":"Fast Food",
            "type":"Food & Drink"
        }
    ],
    "sg:phone":"+32 2 735 55 16",
    "sg:postcode":"1030",
    "sg:province":"Bruxelles-Capitale",
    "sg:tags":[
        "meeneem",
        "restaurant"
    ],
    "wof:name":"Restaurant Golden Phoenix",
    "wof:placetype":"venue"
},
  "geometry": {"coordinates":[4.3895168304,50.8529586792],"type":"Point"}
}