{
  "type": "Feature",
  "properties": {
    "iso:country":"BE",
    "sg:address":"Boulevard Du Centenaire 89",
    "sg:city":"Chaumont-gistoux (dion-valmont)",
    "sg:classifiers":[
        {
            "category":"Health Services",
            "subcategory":"Health Practitioner",
            "type":"Services"
        }
    ],
    "sg:phone":"+32 10 84 25 59",
    "sg:postcode":"1325",
    "sg:province":"Brabant Wallon",
    "sg:tags":[
        "physiotherapist"
    ],
    "wof:name":"Taheri A",
    "wof:placetype":"venue"
},
  "geometry": {"coordinates":[4.6598601341,50.7149009705],"type":"Point"}
}