{
  "type": "Feature",
  "properties": {
    "iso:country":"BE",
    "sg:address":"Westernieuwweg Noord 1",
    "sg:city":"Zuienkerke",
    "sg:orig_category":"Eleveurs and marchands de porcs",
    "sg:phone":"+32 50 41 22 84",
    "sg:postcode":"8377",
    "sg:province":"West-Vlaanderen",
    "wof:name":"Paul Van Eecke",
    "wof:placetype":"venue"
},
  "geometry": {"coordinates":[3.0901689529,51.2472648621],"type":"Point"}
}