{
  "type": "Feature",
  "properties": {
    "iso:country":"BE",
    "sg:address":"Rue Jules Philippe 160",
    "sg:city":"Libin (ochamps)",
    "sg:classifiers":[
        {
            "category":"Food & Beverages",
            "subcategory":"Meat & Fish",
            "type":"Retail Goods"
        }
    ],
    "sg:phone":"+32 61 22 27 24",
    "sg:postcode":"6890",
    "sg:province":"Luxembourg",
    "sg:tags":[
        "-",
        "livestock"
    ],
    "wof:name":"Gabriel J-m Scs",
    "wof:placetype":"venue"
},
  "geometry": {"coordinates":[5.2834420204,49.9233398438],"type":"Point"}
}