{
  "type": "Feature",
  "properties": {
    "addr:full":"Chauss\u00e9e De Marche 474 Namur (erpent) Namur 5101",
    "addr:housenumber":"474",
    "addr:postcode":"5101",
    "addr:street":"Chausse\u0301E De Marche",
    "iso:country":"BE",
    "sg:address":"Chauss\u00e9e De Marche 474",
    "sg:city":"Namur (erpent)",
    "sg:classifiers":[
        {
            "category":"Health Services",
            "subcategory":"Doctor",
            "type":"Services"
        }
    ],
    "sg:phone":"+32 81 30 47 56",
    "sg:postcode":"5101",
    "sg:province":"Namur",
    "sg:tags":[
        "medicinephysicians",
        "surgeon"
    ],
    "wof:name":"Houbart Robert",
    "wof:placetype":"venue"
},
  "geometry": {"coordinates":[4.8983712196,50.4460792542],"type":"Point"}
}