{
  "type": "Feature",
  "properties": {
    "iso:country":"BE",
    "sg:address":"Leinstraat 86",
    "sg:city":"Brakel (opbrakel)",
    "sg:classifiers":[
        {
            "category":"Farming",
            "subcategory":"Farm & Veterinary Services",
            "type":"Manufacturing & Wholesale Goods"
        }
    ],
    "sg:phone":"+32 55 42 39 94",
    "sg:postcode":"9660",
    "sg:province":"Oost-Vlaanderen",
    "sg:tags":[
        "agricultural",
        "contractor"
    ],
    "wof:name":"Eeman L",
    "wof:placetype":"venue"
},
  "geometry": {"coordinates":[3.7356460094,50.7805137634],"type":"Point"}
}