{
  "type": "Feature",
  "properties": {
    "addr:full":"Hoogleedsesteenweg 27 Roeselare West-Vlaanderen 8800",
    "addr:housenumber":"27",
    "addr:postcode":"8800",
    "addr:street":"Hoogleedsesteenweg",
    "iso:country":"BE",
    "sg:address":"Hoogleedsesteenweg 27",
    "sg:city":"Roeselare",
    "sg:classifiers":[
        {
            "category":"Health Services",
            "subcategory":"Health Practitioner",
            "type":"Services"
        }
    ],
    "sg:phone":"+32 51 22 94 66",
    "sg:postcode":"8800",
    "sg:province":"West-Vlaanderen",
    "sg:tags":[
        "physiotherapist"
    ],
    "wof:name":"Vergote Marc",
    "wof:placetype":"venue"
},
  "geometry": {"coordinates":[3.1193199158,50.9516868591],"type":"Point"}
}