{
  "type": "Feature",
  "properties": {
    "iso:country":"BE",
    "sg:address":"Wielewaalpark 3",
    "sg:city":"De Pinte",
    "sg:classifiers":[
        {
            "category":"Professional",
            "subcategory":"Computer Services",
            "type":"Services"
        }
    ],
    "sg:phone":"+32 9 329 92 78",
    "sg:postcode":"9840",
    "sg:province":"Oost-Vlaanderen",
    "sg:tags":[
        "-",
        "processing",
        "data",
        "software"
    ],
    "wof:name":"A.m.s.h.",
    "wof:placetype":"venue"
},
  "geometry": {"coordinates":[3.6312670708,50.989654541],"type":"Point"}
}