{
  "type": "Feature",
  "properties": {
    "iso:country":"BE",
    "sg:address":"Oude Steenovenweg 8",
    "sg:city":"Herselt (ramsel)",
    "sg:classifiers":[
        {
            "category":"Freight",
            "type":"Transportation"
        }
    ],
    "sg:phone":"+32 16 69 61 73",
    "sg:postcode":"2230",
    "sg:province":"Antwerpen",
    "sg:tags":[
        "-",
        "transport"
    ],
    "wof:name":"Crets P",
    "wof:placetype":"venue"
},
  "geometry": {"coordinates":[4.8341088295,51.0305480957],"type":"Point"}
}