{
  "type": "Feature",
  "properties": {
    "addr:full":"Grendelbaan 60 Diepenbeek Limburg 3590",
    "addr:housenumber":"60",
    "addr:postcode":"3590",
    "addr:street":"Grendelbaan",
    "iso:country":"BE",
    "sg:address":"Grendelbaan 60",
    "sg:city":"Diepenbeek",
    "sg:classifiers":[
        {
            "category":"Food & Beverages",
            "subcategory":"Fruits & Vegetables",
            "type":"Retail Goods"
        }
    ],
    "sg:phone":"+32 11 32 49 29",
    "sg:postcode":"3590",
    "sg:province":"Limburg",
    "sg:tags":[
        "-"
    ],
    "wof:name":"Jeike",
    "wof:placetype":"venue"
},
  "geometry": {"coordinates":[5.4357309341,50.9033088684],"type":"Point"}
}