{
  "type": "Feature",
  "properties": {
    "iso:country":"BE",
    "sg:address":"Rue D'horlebecq 5",
    "sg:city":"Braine-le-comte (steenkerque)",
    "sg:classifiers":[
        {
            "category":"Building & Trades",
            "subcategory":"Pest Control",
            "type":"Services"
        }
    ],
    "sg:phone":"+32 67 67 00 56",
    "sg:postcode":"7090",
    "sg:province":"Hainaut",
    "sg:tags":[
        "painting",
        "contractor"
    ],
    "wof:name":"Cantillon E",
    "wof:placetype":"venue"
},
  "geometry": {"coordinates":[4.1355600357,50.610748291],"type":"Point"}
}