{
  "type": "Feature",
  "properties": {
    "iso:country":"BE",
    "sg:address":"Rue Nazareth 25",
    "sg:city":"Herve (battice)",
    "sg:orig_category":"Non-Classified Establishments",
    "sg:phone":"+32 87 66 04 41",
    "sg:postcode":"4651",
    "sg:province":"Li\u00e8ge",
    "wof:name":"Mpc",
    "wof:placetype":"venue"
},
  "geometry": {"coordinates":[5.8018789291,50.6476020813],"type":"Point"}
}