{
  "type": "Feature",
  "properties": {
    "addr:full":"Demerstraat 9 Diepenbeek Limburg 3590",
    "addr:housenumber":"9",
    "addr:postcode":"3590",
    "addr:street":"Demerstraat",
    "iso:country":"BE",
    "sg:address":"Demerstraat 9",
    "sg:city":"Diepenbeek",
    "sg:classifiers":[
        {
            "category":"Insurance",
            "subcategory":"Insurance Agent",
            "type":"Services"
        }
    ],
    "sg:phone":"+32 11 33 26 33",
    "sg:postcode":"3590",
    "sg:province":"Limburg",
    "sg:tags":[
        "alcohol"
    ],
    "wof:name":"Sodiko Nv",
    "wof:placetype":"venue"
},
  "geometry": {"coordinates":[5.4288759232,50.9100761414],"type":"Point"}
}