{
  "type": "Feature",
  "properties": {
    "iso:country":"BE",
    "sg:address":"Tervuursesteenweg 726",
    "sg:city":"Zemst (elewijt)",
    "sg:classifiers":[
        {
            "category":"Real Estate",
            "subcategory":"Architect",
            "type":"Services"
        }
    ],
    "sg:phone":"+32 15 61 40 78",
    "sg:postcode":"1982",
    "sg:province":"Vlaams-Brabant",
    "wof:name":"Janssens H",
    "wof:placetype":"venue"
},
  "geometry": {"coordinates":[4.4957871437,50.9643478394],"type":"Point"}
}