{
  "type": "Feature",
  "properties": {
    "iso:country":"BE",
    "sg:address":"Terweidenstraat 56",
    "sg:city":"Zoutleeuw",
    "sg:orig_category":"Epiceries. Journaux",
    "sg:phone":"+32 11 58 74 18",
    "sg:postcode":"3440",
    "sg:province":"Vlaams-Brabant",
    "wof:name":"Julienne Vandeputte",
    "wof:placetype":"venue"
},
  "geometry": {"coordinates":[5.1124000549,50.8604011536],"type":"Point"}
}