{
  "type": "Feature",
  "properties": {
    "addr:full":"Koerseldorp 7 Beringen Limburg 3582",
    "addr:housenumber":"7",
    "addr:postcode":"3582",
    "addr:street":"Koerseldorp",
    "iso:country":"BE",
    "sg:address":"Koerseldorp 7",
    "sg:city":"Beringen",
    "sg:classifiers":[
        {
            "category":"Cafe",
            "type":"Food & Drink"
        }
    ],
    "sg:phone":"+32 11 42 16 95",
    "sg:postcode":"3582",
    "sg:province":"Limburg",
    "sg:tags":[
        "caf\u00e9s"
    ],
    "wof:name":"Pub Shamrock",
    "wof:placetype":"venue"
},
  "geometry": {"coordinates":[5.2708749771,51.0595359802],"type":"Point"}
}