{
  "type": "Feature",
  "properties": {
    "addr:full":"Zepperendorp 11 Sint-truiden Limburg 3800",
    "addr:housenumber":"11",
    "addr:postcode":"3800",
    "addr:street":"Zepperendorp",
    "iso:country":"BE",
    "sg:address":"Zepperendorp 11",
    "sg:city":"Sint-truiden",
    "sg:orig_category":"R\u00e9paration and restauration de meubles",
    "sg:phone":"+32 11 68 83 76",
    "sg:postcode":"3800",
    "sg:province":"Limburg",
    "wof:name":"J. Knapen",
    "wof:placetype":"venue"
},
  "geometry": {"coordinates":[5.2502961159,50.8222923279],"type":"Point"}
}