{
  "type": "Feature",
  "properties": {
    "addr:full":"Rue De Virginal 61 Tubize Brabant Wallon 1480",
    "addr:housenumber":"61",
    "addr:postcode":"1480",
    "addr:street":"Rue De Virginal;Wallon",
    "iso:country":"BE",
    "sg:address":"Rue De Virginal 61",
    "sg:city":"Tubize",
    "sg:classifiers":[
        {
            "category":"Building & Trades",
            "subcategory":"Plumbing",
            "type":"Services"
        }
    ],
    "sg:phone":"+32 2 355 83 96",
    "sg:postcode":"1480",
    "sg:province":"Brabant Wallon",
    "sg:tags":[
        "diver",
        "commerce",
        "gr",
        "pour",
        "equipement"
    ],
    "wof:name":"Georges Decorte",
    "wof:placetype":"venue"
},
  "geometry": {"coordinates":[4.2090277672,50.6776733398],"type":"Point"}
}