{
  "type": "Feature",
  "properties": {
    "addr:full":"Rue D'ophem 68 Brussel/bruxelles Bruxelles-Capitale 1000",
    "addr:housenumber":"68",
    "addr:postcode":"1000",
    "addr:street":"Rue D'Ophem;/",
    "iso:country":"BE",
    "sg:address":"Rue D'ophem 68",
    "sg:city":"Brussel/bruxelles",
    "sg:orig_category":"Pain, p\u00e2tisseries and confiseries",
    "sg:phone":"+32 2 217 08 68",
    "sg:postcode":"1000",
    "sg:province":"Bruxelles-Capitale",
    "wof:name":"Martiny",
    "wof:placetype":"venue"
},
  "geometry": {"coordinates":[4.3455710411,50.855091095],"type":"Point"}
}