{
  "type": "Feature",
  "properties": {
    "addr:full":"Mollei 147 Brasschaat Antwerpen 2930",
    "addr:housenumber":"147",
    "addr:postcode":"2930",
    "iso:country":"BE",
    "sg:address":"Mollei 147",
    "sg:city":"Brasschaat",
    "sg:classifiers":[
        {
            "category":"Health Services",
            "subcategory":"Health Practitioner",
            "type":"Services"
        }
    ],
    "sg:phone":"+32 3 651 41 66",
    "sg:postcode":"2930",
    "sg:province":"Antwerpen",
    "sg:tags":[
        "physiotherapist"
    ],
    "wof:name":"Cox Marjan",
    "wof:placetype":"venue"
},
  "geometry": {"coordinates":[4.4765968323,51.296459198],"type":"Point"}
}