{
  "type": "Feature",
  "properties": {
    "addr:full":"Industriezone Doornveld Asse (zellik) Vlaams-Brabant 1731",
    "addr:postcode":"1731",
    "addr:street":"Industriezone Doornveld",
    "iso:country":"BE",
    "sg:address":"Industriezone Doornveld",
    "sg:city":"Asse (zellik)",
    "sg:classifiers":[
        {
            "category":"Manufacturing",
            "subcategory":"Lumber",
            "type":"Manufacturing & Wholesale Goods"
        }
    ],
    "sg:phone":"+32 2 466 03 05",
    "sg:postcode":"1731",
    "sg:province":"Vlaams-Brabant",
    "sg:tags":[
        "timber"
    ],
    "wof:name":"Bomaco Nv",
    "wof:placetype":"venue"
},
  "geometry": {"coordinates":[4.2738099098,50.8845901489],"type":"Point"}
}