{
  "type": "Feature",
  "properties": {
    "addr:full":"12 Martinlaan 3670 Meeuwen-gruitrode 12",
    "addr:housenumber":"12;12",
    "addr:postcode":"3670",
    "addr:street":"Martinlaan",
    "iso:country":"BE",
    "sg:address":"12",
    "sg:city":"Martinlaan 3670 Meeuwen-gruitrode",
    "sg:classifiers":[
        {
            "category":"Wholesale",
            "subcategory":"Machinery & Supplies",
            "type":"Manufacturing & Wholesale Goods"
        }
    ],
    "sg:phone":"+32 89 46 23 29",
    "sg:postcode":"12",
    "sg:tags":[
        "food",
        "processing",
        "-",
        "machine",
        "equipment",
        "engineering",
        "mechanical"
    ],
    "wof:name":"Geusens Ghislain Jacobus M.",
    "wof:placetype":"venue"
},
  "geometry": {"coordinates":[5.5532698631,51.1099967957],"type":"Point"}
}