{
  "type": "Feature",
  "properties": {
    "addr:full":"Rue Docteur Emile Neuville 44 Villers-le-bouillet (vaux-et-borset) Li\u00e8ge 4530",
    "addr:housenumber":"44",
    "addr:postcode":"4530",
    "addr:street":"Rue Docteur Emile Neuville",
    "iso:country":"BE",
    "sg:address":"Rue Docteur Emile Neuville 44",
    "sg:city":"Villers-le-bouillet (vaux-et-borset)",
    "sg:classifiers":[
        {
            "category":"Food & Beverages",
            "subcategory":"Meat & Fish",
            "type":"Retail Goods"
        }
    ],
    "sg:phone":"+32 19 56 60 84",
    "sg:postcode":"4530",
    "sg:province":"Li\u00e8ge",
    "sg:tags":[
        "-",
        "livestock"
    ],
    "wof:name":"Eyckmans H",
    "wof:placetype":"venue"
},
  "geometry": {"coordinates":[5.2578449249,50.6104545593],"type":"Point"}
}