{
  "type": "Feature",
  "properties": {
    "addr:full":"Sint-truidersteenweg 37 Herk-de-stad Limburg 3540",
    "addr:housenumber":"37",
    "addr:postcode":"3540",
    "addr:street":"Sint-Truidersteenweg",
    "iso:country":"BE",
    "sg:address":"Sint-truidersteenweg 37",
    "sg:city":"Herk-de-stad",
    "sg:classifiers":[
        {
            "category":"Bars & Pubs",
            "type":"Food & Drink"
        }
    ],
    "sg:phone":"+32 13 55 11 59",
    "sg:postcode":"3540",
    "sg:province":"Limburg",
    "wof:name":"Kroegske ('t)",
    "wof:placetype":"venue"
},
  "geometry": {"coordinates":[5.169552803,50.9327392578],"type":"Point"}
}