{
  "type": "Feature",
  "properties": {
    "addr:full":"St Denijsplein 15 Veurne West-Vlaanderen 8630",
    "addr:housenumber":"15",
    "addr:postcode":"8630",
    "iso:country":"BE",
    "sg:address":"St Denijsplein 15",
    "sg:city":"Veurne",
    "sg:orig_category":"Sportterreinen and installaties behalve sportcentra",
    "sg:phone":"+32 58 33 05 67",
    "sg:postcode":"8630",
    "sg:province":"West-Vlaanderen",
    "wof:name":"Gemeentelijk Zwembad",
    "wof:placetype":"venue"
},
  "geometry": {"coordinates":[2.6608729362,51.0701599121],"type":"Point"}
}