{
  "type": "Feature",
  "properties": {
    "iso:country":"BE",
    "sg:address":"Dr\u00c8ve Emmanuelle 9",
    "sg:city":"Genappe",
    "sg:orig_category":"Public-relationsbureaus",
    "sg:phone":"+32 10 61 77 07",
    "sg:postcode":"1470",
    "sg:province":"Brabant Wallon",
    "wof:name":"Ac Communication",
    "wof:placetype":"venue"
},
  "geometry": {"coordinates":[4.5367941856,50.6438560486],"type":"Point"}
}