{
  "type": "Feature",
  "properties": {
    "addr:full":"Lijsterstraat 34 Nazareth Oost-Vlaanderen 9810",
    "addr:housenumber":"34",
    "addr:postcode":"9810",
    "addr:street":"Lijsterstraat",
    "iso:country":"BE",
    "sg:address":"Lijsterstraat 34",
    "sg:city":"Nazareth",
    "sg:classifiers":[
        {
            "category":"Arena",
            "subcategory":"Sports Club",
            "type":"Entertainment"
        }
    ],
    "sg:phone":"+32 9 385 55 37",
    "sg:postcode":"9810",
    "sg:province":"Oost-Vlaanderen",
    "sg:tags":[
        "de"
    ],
    "wof:name":"Navok Nazareth",
    "wof:placetype":"venue"
},
  "geometry": {"coordinates":[3.6229979992,50.9550476074],"type":"Point"}
}