{
  "type": "Feature",
  "properties": {
    "addr:full":"Route De Xhignesse 8 Hamoir Li\u00e8ge 4180",
    "addr:housenumber":"8",
    "addr:postcode":"4180",
    "addr:street":"Route De Xhignesse",
    "iso:country":"BE",
    "sg:address":"Route De Xhignesse 8",
    "sg:city":"Hamoir",
    "sg:classifiers":[
        {
            "category":"Professional",
            "subcategory":"Accounting & Tax Preparation",
            "type":"Services"
        }
    ],
    "sg:phone":"+32 86 38 86 02",
    "sg:postcode":"4180",
    "sg:province":"Li\u00e8ge",
    "sg:tags":[
        "bookkeeper"
    ],
    "wof:name":"Clitesse Y",
    "wof:placetype":"venue"
},
  "geometry": {"coordinates":[5.5416097641,50.4283561707],"type":"Point"}
}