{
  "type": "Feature",
  "properties": {
    "iso:country":"BE",
    "sg:address":"Bruulstraat 24bc",
    "sg:city":"Heist-op-den-berg",
    "sg:orig_category":"Animaux domestiques and accessoires. Eleveurs d'animaux domestiques",
    "sg:phone":"+32 15 25 00 86",
    "sg:postcode":"2222",
    "sg:province":"Antwerpen",
    "wof:name":"Cattery The Little Lions",
    "wof:placetype":"venue"
},
  "geometry": {"coordinates":[4.7292399406,51.1032218933],"type":"Point"}
}