{
  "type": "Feature",
  "properties": {
    "addr:full":"Brusselsestraat 74 Leuven Vlaams-Brabant 3000",
    "addr:housenumber":"74",
    "addr:postcode":"3000",
    "addr:street":"Brusselsestraat",
    "iso:country":"BE",
    "sg:address":"Brusselsestraat 74",
    "sg:city":"Leuven",
    "sg:classifiers":[
        {
            "category":"Fast Food",
            "type":"Food & Drink"
        }
    ],
    "sg:phone":"+32 16 23 99 64",
    "sg:postcode":"3000",
    "sg:province":"Vlaams-Brabant",
    "sg:tags":[
        "\u00c0",
        "restaurants",
        "emporter",
        "restaurant"
    ],
    "wof:name":"Istanbul",
    "wof:placetype":"venue"
},
  "geometry": {"coordinates":[4.6967258453,50.8803901672],"type":"Point"}
}