{
  "type": "Feature",
  "properties": {
    "iso:country":"BE",
    "sg:address":"Graaf Van Hoornstraat 10",
    "sg:city":"Oostkamp",
    "sg:classifiers":[
        {
            "category":"Insurance",
            "subcategory":"Life Insurance",
            "type":"Services"
        }
    ],
    "sg:phone":"+32 50 82 41 51",
    "sg:postcode":"8020",
    "sg:province":"West-Vlaanderen",
    "sg:tags":[
        "assurance"
    ],
    "wof:name":"D. Declerck",
    "wof:placetype":"venue"
},
  "geometry": {"coordinates":[3.2372210026,51.1424865723],"type":"Point"}
}