{
  "type": "Feature",
  "properties": {
    "addr:full":"Rue Chemin-rue 28 Malmedy Li\u00e8ge 4960",
    "addr:housenumber":"28",
    "addr:postcode":"4960",
    "addr:street":"Rue Chemin-Rue",
    "iso:country":"BE",
    "sg:address":"Rue Chemin-rue 28",
    "sg:city":"Malmedy",
    "sg:classifiers":[
        {
            "category":"Personal",
            "subcategory":"Beauty Salon",
            "type":"Services"
        }
    ],
    "sg:phone":"+32 80 33 96 40",
    "sg:postcode":"4960",
    "sg:province":"Li\u00e8ge",
    "sg:tags":[
        "lady",
        "-",
        "hairdressing"
    ],
    "wof:name":"Deg\u00e9e M",
    "wof:placetype":"venue"
},
  "geometry": {"coordinates":[6.0271558762,50.4254875183],"type":"Point"}
}