{
  "type": "Feature",
  "properties": {
    "iso:country":"BE",
    "sg:address":"Dennengaerdelaan 46",
    "sg:city":"As",
    "sg:classifiers":[
        {
            "category":"Banks & Credit Unions",
            "subcategory":"Investment Brokerage",
            "type":"Services"
        }
    ],
    "sg:phone":"+32 89 65 77 65",
    "sg:postcode":"3665",
    "sg:province":"Limburg",
    "sg:tags":[
        "repair",
        "-",
        "installation",
        "sanitary",
        "article"
    ],
    "wof:name":"Coolen R",
    "wof:placetype":"venue"
},
  "geometry": {"coordinates":[5.6150050163,51.0125961304],"type":"Point"}
}