{
  "type": "Feature",
  "properties": {
    "addr:full":"Vismijnlaan 14-11 Oostende West-Vlaanderen 8400",
    "addr:postcode":"14-11;8400",
    "addr:street":"Vismijnlaan",
    "iso:country":"BE",
    "sg:address":"Vismijnlaan 14-11",
    "sg:city":"Oostende",
    "sg:classifiers":[
        {
            "category":"Wholesale",
            "subcategory":"Seafood",
            "type":"Manufacturing & Wholesale Goods"
        }
    ],
    "sg:phone":"+32 59 32 01 96",
    "sg:postcode":"8400",
    "sg:province":"West-Vlaanderen",
    "sg:tags":[
        "whol",
        "fish",
        "-",
        "shellfish"
    ],
    "wof:name":"Verleye F & Zn",
    "wof:placetype":"venue"
},
  "geometry": {"coordinates":[2.9373478889,51.2288475037],"type":"Point"}
}