{
  "type": "Feature",
  "properties": {
    "iso:country":"BE",
    "sg:address":"Polder 4",
    "sg:city":"Dilbeek",
    "sg:orig_category":"Traitement and rev\u00eatement des m\u00e9taux",
    "sg:phone":"+32 3 888 08 88",
    "sg:postcode":"1701",
    "sg:province":"Vlaams-Brabant",
    "wof:name":"Almecon",
    "wof:placetype":"venue"
},
  "geometry": {"coordinates":[4.2116360664,50.8613357544],"type":"Point"}
}