{
  "type": "Feature",
  "properties": {
    "addr:full":"Puydt 23 Bi\u00e9v\u00e8ne Vlaams-Brabant 1547",
    "addr:housenumber":"23;1547",
    "addr:street":"Puydt;Vlaams-Brabant",
    "iso:country":"BE",
    "sg:address":"Puydt 23",
    "sg:city":"Bi\u00e9v\u00e8ne",
    "sg:classifiers":[
        {
            "category":"Shopping",
            "subcategory":"Crafts & Fabrics",
            "type":"Retail Goods"
        }
    ],
    "sg:phone":"+32 54 58 98 47",
    "sg:postcode":"1547",
    "sg:province":"Vlaams-Brabant",
    "sg:tags":[
        "plant",
        "flower",
        "artificial"
    ],
    "wof:name":"Francinette Kunstboeketjes",
    "wof:placetype":"venue"
},
  "geometry": {"coordinates":[3.9693090916,50.710357666],"type":"Point"}
}