{
  "type": "Feature",
  "properties": {
    "addr:full":"Oude Watertorenstraat 27 Hamont-achel (hamont) Limburg 3930",
    "addr:housenumber":"27",
    "addr:postcode":"3930",
    "addr:street":"Oude Watertorenstraat",
    "iso:country":"BE",
    "sg:address":"Oude Watertorenstraat 27",
    "sg:city":"Hamont-achel (hamont)",
    "sg:classifiers":[
        {
            "category":"Professional",
            "subcategory":"Printing & Photocopies",
            "type":"Services"
        }
    ],
    "sg:phone":"+32 11 44 03 60",
    "sg:postcode":"3930",
    "sg:province":"Limburg",
    "sg:tags":[
        "-",
        "offset"
    ],
    "wof:name":"Boonen Drukkerij",
    "wof:placetype":"venue"
},
  "geometry": {"coordinates":[5.5450549126,51.2511863708],"type":"Point"}
}