{
  "type": "Feature",
  "properties": {
    "addr:full":"Quai D'arona 17 Huy Li\u00e8ge 4500",
    "addr:housenumber":"17",
    "addr:postcode":"4500",
    "addr:street":"Quai D'Arona",
    "iso:country":"BE",
    "sg:address":"Quai D'arona 17",
    "sg:city":"Huy",
    "sg:orig_category":"Airconditioning and ventilatie Loodgieterij, verwarming and sanitaire installaties",
    "sg:phone":"+32 85 21 22 87",
    "sg:postcode":"4500",
    "sg:province":"Li\u00e8ge",
    "wof:name":"Doneux-huy",
    "wof:placetype":"venue"
},
  "geometry": {"coordinates":[5.251185894,50.5336914062],"type":"Point"}
}