{
  "type": "Feature",
  "properties": {
    "addr:full":"Wijkstraat 10 Box 2 Diepenbeek Limburg 3590",
    "addr:housenumber":"10;2",
    "addr:postcode":"3590",
    "addr:street":"Wijkstraat;Box",
    "iso:country":"BE",
    "sg:address":"Wijkstraat 10 Box 2",
    "sg:city":"Diepenbeek",
    "sg:classifiers":[
        {
            "category":"Banks & Credit Unions",
            "subcategory":"Bank",
            "type":"Services"
        }
    ],
    "sg:phone":"+32 11 35 10 87",
    "sg:postcode":"3590",
    "sg:province":"Limburg",
    "sg:tags":[
        "savings-banks"
    ],
    "wof:name":"Argenta Moris T",
    "wof:placetype":"venue"
},
  "geometry": {"coordinates":[5.4285168648,50.9061851501],"type":"Point"}
}