{
  "type": "Feature",
  "properties": {
    "addr:full":"Hof Te Bollebeeklaan 26 Asse Vlaams-Brabant 1730",
    "addr:housenumber":"26",
    "addr:postcode":"1730",
    "addr:street":"Hof;Bollebeeklaan",
    "iso:country":"BE",
    "sg:address":"Hof Te Bollebeeklaan 26",
    "sg:city":"Asse",
    "sg:orig_category":"Hout and afgeleiden Gh IJzerwaren, bouw- and verfmaterialen",
    "sg:phone":"+32 2 454 03 30",
    "sg:postcode":"1730",
    "sg:province":"Vlaams-Brabant",
    "wof:name":"Jonckheere Robert",
    "wof:placetype":"venue"
},
  "geometry": {"coordinates":[4.2334609032,50.9148979187],"type":"Point"}
}