{
  "type": "Feature",
  "properties": {
    "addr:full":"Vooruitgangstraat 42 Denderleeuw Oost-Vlaanderen 9473",
    "addr:housenumber":"42",
    "addr:postcode":"9473",
    "addr:street":"Vooruitgangstraat",
    "iso:country":"BE",
    "sg:address":"Vooruitgangstraat 42",
    "sg:city":"Denderleeuw",
    "sg:orig_category":"Boekhouders",
    "sg:phone":"+32 53 67 35 36",
    "sg:postcode":"9473",
    "sg:province":"Oost-Vlaanderen",
    "wof:name":"Anja Van Hedent",
    "wof:placetype":"venue"
},
  "geometry": {"coordinates":[4.0490322113,50.90076828],"type":"Point"}
}