{
  "type": "Feature",
  "properties": {
    "iso:country":"BE",
    "sg:address":"Rue Georges Leveau 8",
    "sg:city":"Tubize (clabecq)",
    "sg:classifiers":[
        {
            "category":"Personal",
            "subcategory":"Barber",
            "type":"Services"
        }
    ],
    "sg:phone":"+32 2 355 91 08",
    "sg:postcode":"1480",
    "sg:province":"Brabant Wallon",
    "sg:tags":[
        "gentleman",
        "salon",
        "-",
        "hairdressing"
    ],
    "wof:name":"Guy",
    "wof:placetype":"venue"
},
  "geometry": {"coordinates":[4.2229251862,50.6891441345],"type":"Point"}
}