{
  "type": "Feature",
  "properties": {
    "addr:full":"Handboogstraat 31 Roeselare West-Vlaanderen 8800",
    "addr:housenumber":"31",
    "addr:postcode":"8800",
    "addr:street":"Handboogstraat",
    "iso:country":"BE",
    "sg:address":"Handboogstraat 31",
    "sg:city":"Roeselare",
    "sg:orig_category":"Loodgieterij, verwarming and sanitaire installaties",
    "sg:phone":"+32 51 24 69 91",
    "sg:postcode":"8800",
    "sg:province":"West-Vlaanderen",
    "wof:name":"De Keyser Pedro",
    "wof:placetype":"venue"
},
  "geometry": {"coordinates":[3.1171059608,50.9517593384],"type":"Point"}
}