{
  "type": "Feature",
  "properties": {
    "addr:full":"Werkhuizenstraat 8 Gent (gentbrugge) Oost-Vlaanderen 9050",
    "addr:housenumber":"8",
    "addr:postcode":"9050",
    "addr:street":"Werkhuizenstraat",
    "iso:country":"BE",
    "sg:address":"Werkhuizenstraat 8",
    "sg:city":"Gent (gentbrugge)",
    "sg:classifiers":[
        {
            "category":"Utilities",
            "subcategory":"Fuel Oil & Lpg",
            "type":"Services"
        }
    ],
    "sg:phone":"+32 9 230 96 30",
    "sg:postcode":"9050",
    "sg:province":"Oost-Vlaanderen",
    "wof:name":"Star Oil",
    "wof:placetype":"venue"
},
  "geometry": {"coordinates":[3.7612218857,51.0271186829],"type":"Point"}
}