{
  "type": "Feature",
  "properties": {
    "iso:country":"BE",
    "sg:address":"Rue B\u00c8churon 4",
    "sg:city":"Chaudfontaine",
    "sg:orig_category":"Charpentes and couvertures. Installation de menuiserie en bois and plastique",
    "sg:phone":"+32 4 365 49 64",
    "sg:postcode":"4051",
    "sg:province":"Li\u00e8ge",
    "wof:name":"Jules Jacquet",
    "wof:placetype":"venue"
},
  "geometry": {"coordinates":[5.628636837,50.6081542969],"type":"Point"}
}