{
  "type": "Feature",
  "properties": {
    "addr:full":"Oude Boekhoutestraat 14 Assenede Oost-Vlaanderen 9968",
    "addr:housenumber":"14",
    "addr:postcode":"9968",
    "addr:street":"Oude Boekhoutestraat",
    "iso:country":"BE",
    "sg:address":"Oude Boekhoutestraat 14",
    "sg:city":"Assenede",
    "sg:orig_category":"Rundveehouders Varkenskwekers",
    "sg:phone":"+32 9 373 72 72",
    "sg:postcode":"9968",
    "sg:province":"Oost-Vlaanderen",
    "wof:name":"Frank Van Hoorebeke",
    "wof:placetype":"venue"
},
  "geometry": {"coordinates":[3.6895639896,51.2396736145],"type":"Point"}
}