{
  "type": "Feature",
  "properties": {
    "iso:country":"BE",
    "sg:address":"Singelstraat 99",
    "sg:city":"Ravels",
    "sg:orig_category":"Eleveurs de bovins",
    "sg:phone":"+32 14 65 60 79",
    "sg:postcode":"2381",
    "sg:province":"Antwerpen",
    "wof:name":"Paulussen",
    "wof:placetype":"venue"
},
  "geometry": {"coordinates":[5.006374836,51.4099845886],"type":"Point"}
}