{
  "type": "Feature",
  "properties": {
    "iso:country":"BE",
    "sg:address":"Heuvenstraat 104",
    "sg:city":"Zonhoven",
    "sg:classifiers":[
        {
            "category":"Autos & Motor Vehicles",
            "subcategory":"Fuel & Gas Station",
            "type":"Retail Goods"
        }
    ],
    "sg:phone":"+32 11 81 43 30",
    "sg:postcode":"3520",
    "sg:province":"Limburg",
    "sg:tags":[
        "stations-service",
        "carburants"
    ],
    "wof:name":"Immanis",
    "wof:placetype":"venue"
},
  "geometry": {"coordinates":[5.3664631844,50.9835891724],"type":"Point"}
}