{
  "type": "Feature",
  "properties": {
    "addr:full":"Doorniksesteenweg 4-6 Avelgem West-Vlaanderen 8580",
    "addr:housenumber":"4-6",
    "addr:postcode":"8580",
    "addr:street":"Doorniksesteenweg",
    "iso:country":"BE",
    "sg:address":"Doorniksesteenweg 4-6",
    "sg:city":"Avelgem",
    "sg:orig_category":"Verlichting and huishoudartikelen",
    "sg:phone":"+32 56 64 41 40",
    "sg:postcode":"8580",
    "sg:province":"West-Vlaanderen",
    "wof:name":"Vanwijnsberghe",
    "wof:placetype":"venue"
},
  "geometry": {"coordinates":[3.4454379082,50.7758750916],"type":"Point"}
}