{
  "type": "Feature",
  "properties": {
    "iso:country":"BE",
    "sg:address":"Nieuwplaats 16",
    "sg:city":"Hooglede",
    "sg:orig_category":"Catering and organisation de f\u00eates. Alimentation sp\u00e9cialis\u00e9e",
    "sg:phone":"+32 51 20 47 65",
    "sg:postcode":"8830",
    "sg:province":"West-Vlaanderen",
    "wof:name":"Huis Neptune",
    "wof:placetype":"venue"
},
  "geometry": {"coordinates":[3.0971910954,50.9967765808],"type":"Point"}
}