{
  "type": "Feature",
  "properties": {
    "addr:full":"Hoogstraat 7 Roeselare West-Vlaanderen 8800",
    "addr:housenumber":"7",
    "addr:postcode":"8800",
    "addr:street":"Hoogstraat",
    "iso:country":"BE",
    "sg:address":"Hoogstraat 7",
    "sg:city":"Roeselare",
    "sg:orig_category":"Banques and organismes de cr\u00e9dit",
    "sg:phone":"+32 51 20 71 01",
    "sg:postcode":"8800",
    "sg:province":"West-Vlaanderen",
    "wof:name":"Kbc",
    "wof:placetype":"venue"
},
  "geometry": {"coordinates":[3.1463499069,50.9309806824],"type":"Point"}
}