{
  "type": "Feature",
  "properties": {
    "iso:country":"BE",
    "sg:address":"Pieter Reypenslei 18b5",
    "sg:city":"Mortsel",
    "sg:orig_category":"Architecten",
    "sg:phone":"+32 3 440 87 16",
    "sg:postcode":"2640",
    "sg:province":"Antwerpen",
    "wof:name":"Veerle Gepts",
    "wof:placetype":"venue"
},
  "geometry": {"coordinates":[4.4530301094,51.169834137],"type":"Point"}
}