{
  "type": "Feature",
  "properties": {
    "addr:full":"Walckierslaan 11ba Oudergem/auderghem Bruxelles-Capitale 1160",
    "addr:housenumber":"11ba",
    "addr:postcode":"1160",
    "addr:street":"Walckierslaan;/",
    "iso:country":"BE",
    "sg:address":"Walckierslaan 11ba",
    "sg:city":"Oudergem/auderghem",
    "sg:orig_category":"Herstellingen and onderhoud van auto's",
    "sg:phone":"+32 2 672 20 93",
    "sg:postcode":"1160",
    "sg:province":"Bruxelles-Capitale",
    "wof:name":"Carrosserie Ben Car",
    "wof:placetype":"venue"
},
  "geometry": {"coordinates":[4.4346199036,50.8151779175],"type":"Point"}
}