{
  "type": "Feature",
  "properties": {
    "iso:country":"BE",
    "sg:address":"Rue De L\u00b4adoption 41",
    "sg:city":"Couvin",
    "sg:orig_category":"Tijdelijke werkgelegenheid and uitzendkantoren",
    "sg:phone":"+32 60 31 19 28",
    "sg:postcode":"5660",
    "sg:province":"Namur",
    "wof:name":"T-int\u00c9rim",
    "wof:placetype":"venue"
},
  "geometry": {"coordinates":[4.5237951279,50.0979537964],"type":"Point"}
}