{
  "type": "Feature",
  "properties": {
    "addr:full":"Albert Kanaalstraat 33ba Nijlen Antwerpen 2560",
    "addr:housenumber":"33ba",
    "addr:postcode":"2560",
    "addr:street":"Albert Kanaalstraat",
    "iso:country":"BE",
    "sg:address":"Albert Kanaalstraat 33ba",
    "sg:city":"Nijlen",
    "sg:orig_category":"Brood, gebak and snoepgoed",
    "sg:phone":"+32 3 481 86 69",
    "sg:postcode":"2560",
    "sg:province":"Antwerpen",
    "wof:name":"Banketbakkerij Van Eester",
    "wof:placetype":"venue"
},
  "geometry": {"coordinates":[4.6683979034,51.1618843079],"type":"Point"}
}