{
  "type": "Feature",
  "properties": {
    "addr:full":"Lintseheide 43 Duffel Antwerpen 2570",
    "addr:housenumber":"43",
    "addr:postcode":"2570",
    "addr:street":"Lintseheide",
    "iso:country":"BE",
    "sg:address":"Lintseheide 43",
    "sg:city":"Duffel",
    "sg:orig_category":"Gestion de portefeuilles and fortunes, conseils en placements",
    "sg:phone":"+32 15 31 52 30",
    "sg:postcode":"2570",
    "sg:province":"Antwerpen",
    "wof:name":"H.v.l.-constructions",
    "wof:placetype":"venue"
},
  "geometry": {"coordinates":[4.5416312218,51.085521698],"type":"Point"}
}