{
  "type": "Feature",
  "properties": {
    "iso:country":"BE",
    "sg:address":"Av H\u00e9l\u00e8ne 39",
    "sg:city":"Bruxelles",
    "sg:classifiers":[
        {
            "category":"Shopping",
            "subcategory":"Gifts & Souvenirs",
            "type":"Retail Goods"
        }
    ],
    "sg:phone":"+32 2 468 00 74",
    "sg:postcode":"1082",
    "sg:province":"Bruxelles-Capitale",
    "sg:tags":[
        "product",
        "miscellaneous"
    ],
    "wof:name":"Lattelais Louis Gustave M.",
    "wof:placetype":"venue"
},
  "geometry": {"coordinates":[4.3022041321,50.8648986816],"type":"Point"}
}