{
  "type": "Feature",
  "properties": {
    "iso:country":"BE",
    "sg:address":"Sterrebeekstraat 48ba",
    "sg:city":"Zaventem",
    "sg:orig_category":"Entretien and r\u00e9parations de voitures",
    "sg:phone":"+32 2 725 20 25",
    "sg:postcode":"1930",
    "sg:province":"Vlaams-Brabant",
    "wof:name":"Carrosserie St. Maarten",
    "wof:placetype":"venue"
},
  "geometry": {"coordinates":[4.4831709862,50.8797874451],"type":"Point"}
}