{
  "type": "Feature",
  "properties": {
    "iso:country":"BE",
    "sg:address":"Rue D'engihoul 46",
    "sg:city":"Nandrin",
    "sg:orig_category":"Eleveurs de bovins",
    "sg:phone":"+32 4 371 33 65",
    "sg:postcode":"4550",
    "sg:province":"Li\u00e8ge",
    "wof:name":"Joseph Fisenne",
    "wof:placetype":"venue"
},
  "geometry": {"coordinates":[5.4134879112,50.5277404785],"type":"Point"}
}