{
  "type": "Feature",
  "properties": {
    "addr:full":"Rue Bout De La Haut 27bb Walcourt Namur 5651",
    "addr:housenumber":"27bb",
    "addr:postcode":"5651",
    "addr:street":"Rue Bout De La Haut",
    "iso:country":"BE",
    "sg:address":"Rue Bout De La Haut 27bb",
    "sg:city":"Walcourt",
    "sg:orig_category":"Boekhouders Verzekeringsmakelaars and experts",
    "sg:phone":"+32 71 61 48 99",
    "sg:postcode":"5651",
    "sg:province":"Namur",
    "wof:name":"Bureau Vastenavond",
    "wof:placetype":"venue"
},
  "geometry": {"coordinates":[4.4030227661,50.2858161926],"type":"Point"}
}