{
  "type": "Feature",
  "properties": {
    "iso:country":"BE",
    "sg:address":"Stormestraat 95",
    "sg:city":"Waregem",
    "sg:orig_category":"Verlichting and huishoudartikelen",
    "sg:phone":"+32 56 60 25 26",
    "sg:postcode":"8790",
    "sg:province":"West-Vlaanderen",
    "wof:name":"Rogiers-woondecor",
    "wof:placetype":"venue"
},
  "geometry": {"coordinates":[3.4277210236,50.8851661682],"type":"Point"}
}