{
  "type": "Feature",
  "properties": {
    "iso:country":"BE",
    "sg:address":"Pullaarsteenweg 101",
    "sg:city":"Puurs",
    "sg:orig_category":"Installatie van metalen schrijnwerk",
    "sg:phone":"+32 3 886 74 53",
    "sg:postcode":"2870",
    "sg:province":"Antwerpen",
    "wof:name":"General Protect Lighting",
    "wof:placetype":"venue"
},
  "geometry": {"coordinates":[4.3238492012,51.0716934204],"type":"Point"}
}