{
  "type": "Feature",
  "properties": {
    "iso:country":"BE",
    "sg:address":"Dorpsstraat 39",
    "sg:city":"Zandhoven (pulle)",
    "sg:classifiers":[
        {
            "category":"Building & Trades",
            "subcategory":"Plumbing",
            "type":"Services"
        }
    ],
    "sg:phone":"+32 3 464 04 15",
    "sg:postcode":"2243",
    "sg:province":"Antwerpen",
    "sg:tags":[
        "repair",
        "mainten",
        "-",
        "central",
        "heating"
    ],
    "wof:name":"Van Der Schraelen G",
    "wof:placetype":"venue"
},
  "geometry": {"coordinates":[4.7150168419,51.2024841309],"type":"Point"}
}