{
  "type": "Feature",
  "properties": {
    "addr:full":"Rue Du Luxembourg 85 Marche-en-famenne Luxembourg 6900",
    "addr:housenumber":"85",
    "addr:postcode":"6900",
    "addr:street":"Rue Du Luxembourg",
    "iso:country":"BE",
    "sg:address":"Rue Du Luxembourg 85",
    "sg:city":"Marche-en-famenne",
    "sg:classifiers":[
        {
            "category":"Insurance",
            "subcategory":"Insurance Agent",
            "type":"Services"
        }
    ],
    "sg:phone":"+32 84 32 04 00",
    "sg:postcode":"6900",
    "sg:province":"Luxembourg",
    "sg:tags":[
        "broker"
    ],
    "wof:name":"Bureau Bouche (assurances) Sprl",
    "wof:placetype":"venue"
},
  "geometry": {"coordinates":[5.3454070091,50.220954895],"type":"Point"}
}