{
  "type": "Feature",
  "properties": {
    "addr:full":"Rue De La Costale 1ba Waremme Li\u00e8ge 4300",
    "addr:housenumber":"1ba",
    "addr:postcode":"4300",
    "addr:street":"Rue De La Costale",
    "iso:country":"BE",
    "sg:address":"Rue De La Costale 1ba",
    "sg:city":"Waremme",
    "sg:orig_category":"Epiceries",
    "sg:phone":"+32 19 32 21 02",
    "sg:postcode":"4300",
    "sg:province":"Li\u00e8ge",
    "wof:name":"Leon Strauven",
    "wof:placetype":"venue"
},
  "geometry": {"coordinates":[5.2533450127,50.7011604309],"type":"Point"}
}