{
  "type": "Feature",
  "properties": {
    "iso:country":"BE",
    "sg:address":"Breugelweg 140",
    "sg:city":"Overpelt",
    "sg:orig_category":"Rundveehouders",
    "sg:phone":"+32 11 64 13 29",
    "sg:postcode":"3900",
    "sg:province":"Limburg",
    "wof:name":"Jan Hendriks",
    "wof:placetype":"venue"
},
  "geometry": {"coordinates":[5.4293088913,51.1981925964],"type":"Point"}
}