{
  "type": "Feature",
  "properties": {
    "iso:country":"BE",
    "sg:address":"Koolskampstraat 51",
    "sg:city":"Pittem",
    "sg:classifiers":[
        {
            "category":"Professional",
            "subcategory":"Advertising",
            "type":"Services"
        }
    ],
    "sg:phone":"+32 51 46 67 45",
    "sg:postcode":"8740",
    "sg:province":"West-Vlaanderen",
    "sg:tags":[
        "painter"
    ],
    "wof:name":"Ateljee Maes",
    "wof:placetype":"venue"
},
  "geometry": {"coordinates":[3.2527589798,50.9968795776],"type":"Point"}
}