{
  "type": "Feature",
  "properties": {
    "addr:full":"Daalhofstraat 45 Borgloon (hoepertingen) Limburg 3840",
    "addr:housenumber":"45",
    "addr:postcode":"3840",
    "addr:street":"Daalhofstraat",
    "iso:country":"BE",
    "sg:address":"Daalhofstraat 45",
    "sg:city":"Borgloon (hoepertingen)",
    "sg:classifiers":[
        {
            "category":"Real Estate",
            "subcategory":"Developer",
            "type":"Services"
        }
    ],
    "sg:phone":"+32 12 74 15 71",
    "sg:postcode":"3840",
    "sg:province":"Limburg",
    "sg:tags":[
        "project"
    ],
    "wof:name":"Schoofs Sa",
    "wof:placetype":"venue"
},
  "geometry": {"coordinates":[5.3441700935,50.8012466431],"type":"Point"}
}