{
  "type": "Feature",
  "properties": {
    "iso:country":"BE",
    "sg:address":"Palingstraat 18",
    "sg:city":"Destelbergen",
    "sg:orig_category":"Brood, gebak and snoepgoed",
    "sg:phone":"+32 9 355 77 49",
    "sg:postcode":"9070",
    "sg:province":"Oost-Vlaanderen",
    "wof:name":"Hubert Rots",
    "wof:placetype":"venue"
},
  "geometry": {"coordinates":[3.8277590275,51.0614204407],"type":"Point"}
}