{
  "type": "Feature",
  "properties": {
    "iso:country":"BE",
    "sg:address":"Martelarenstraat 6",
    "sg:city":"Aarschot",
    "sg:orig_category":"Studios photographiques",
    "sg:phone":"+32 16 56 65 06",
    "sg:postcode":"3200",
    "sg:province":"Vlaams-Brabant",
    "wof:name":"Andre Matthyssens",
    "wof:placetype":"venue"
},
  "geometry": {"coordinates":[4.8356180191,50.9841003418],"type":"Point"}
}