{
  "type": "Feature",
  "properties": {
    "iso:country":"BE",
    "sg:address":"Petunialaan 27",
    "sg:city":"Kapellen",
    "sg:orig_category":"Instellingen voor mindervalide volwassenen",
    "sg:phone":"+32 3 651 92 88",
    "sg:postcode":"2950",
    "sg:province":"Antwerpen",
    "wof:name":"Tehuis De Vlier",
    "wof:placetype":"venue"
},
  "geometry": {"coordinates":[4.4472699165,51.3132362366],"type":"Point"}
}