{
  "type": "Feature",
  "properties": {
    "iso:country":"BE",
    "sg:address":"Rue De Namur 52",
    "sg:city":"Philippeville",
    "sg:orig_category":"Stations-service and carburants. V\u00e9hicules automobiles. Entretien and r\u00e9parations de voitures",
    "sg:phone":"+32 71 66 04 44",
    "sg:postcode":"5600",
    "sg:province":"Namur",
    "wof:name":"Delaire Motor",
    "wof:placetype":"venue"
},
  "geometry": {"coordinates":[4.5466899872,50.1983032227],"type":"Point"}
}