{
  "type": "Feature",
  "properties": {
    "iso:country":"BE",
    "sg:address":"Rue Des Coquelicots 1",
    "sg:city":"Li\u00e8ge 1 (bressoux)",
    "sg:classifiers":[
        {
            "category":"Retail",
            "subcategory":"Funeral Services",
            "type":"Services"
        }
    ],
    "sg:phone":"+32 4 342 68 63",
    "sg:postcode":"4020",
    "sg:province":"Li\u00e8ge",
    "sg:tags":[
        "director"
    ],
    "wof:name":"Cr\u00e9matorium De Li\u00e8ge",
    "wof:placetype":"venue"
},
  "geometry": {"coordinates":[5.6129360199,50.6366615295],"type":"Point"}
}