{
  "type": "Feature",
  "properties": {
    "iso:country":"BE",
    "sg:address":"Broekkantstraat 44b1",
    "sg:city":"Peer",
    "sg:orig_category":"Rundveehouders",
    "sg:phone":"+32 11 63 34 58",
    "sg:postcode":"3990",
    "sg:province":"Limburg",
    "wof:name":"Jan Winters",
    "wof:placetype":"venue"
},
  "geometry": {"coordinates":[5.497232914,51.1602973938],"type":"Point"}
}