{
  "type": "Feature",
  "properties": {
    "addr:full":"Grand'rue 143 Charleroi Hainaut 6000",
    "addr:housenumber":"143",
    "addr:postcode":"6000",
    "addr:street":"Grand'Rue;Hainaut",
    "iso:country":"BE",
    "sg:address":"Grand'rue 143",
    "sg:city":"Charleroi",
    "sg:orig_category":"Boekenuitgeverijen Boekhandels Kantoormateriaal",
    "sg:phone":"+32 71 48 61 84",
    "sg:postcode":"6000",
    "sg:province":"Hainaut",
    "wof:name":"Club",
    "wof:placetype":"venue"
},
  "geometry": {"coordinates":[4.4527988434,50.4181480408],"type":"Point"}
}