{
  "type": "Feature",
  "properties": {
    "iso:country":"BE",
    "sg:address":"Ijzerhandstraat 8",
    "sg:city":"Kortrijk",
    "sg:orig_category":"Installatie van houten of kunststof schrijnwerk Plaatsen van vloer- and muurbekleding Pleisterwerk W",
    "sg:phone":"+32 56 21 23 81",
    "sg:postcode":"8510",
    "sg:province":"West-Vlaanderen",
    "wof:name":"Bouwonderneming Decalf",
    "wof:placetype":"venue"
},
  "geometry": {"coordinates":[3.290199995,50.7641220093],"type":"Point"}
}