{
  "type": "Feature",
  "properties": {
    "iso:country":"BE",
    "sg:address":"Rue Raoul Warocqu\u00c9 14",
    "sg:city":"Morlanwelz",
    "sg:orig_category":"M\u00e9decins and sp\u00e9cialistes",
    "sg:phone":"+32 64 44 80 48",
    "sg:postcode":"7140",
    "sg:province":"Hainaut",
    "wof:name":"Claudy Dumont",
    "wof:placetype":"venue"
},
  "geometry": {"coordinates":[4.2427558899,50.4567565918],"type":"Point"}
}