{
  "type": "Feature",
  "properties": {
    "iso:country":"BE",
    "sg:address":"Rue Du Lavoir 32",
    "sg:city":"Brussel/bruxelles",
    "sg:orig_category":"Action sociale avec h\u00e9bergement",
    "sg:phone":"+32 2 512 15 89",
    "sg:postcode":"1000",
    "sg:province":"Bruxelles-Capitale",
    "wof:name":"Centre Contact Querelle",
    "wof:placetype":"venue"
},
  "geometry": {"coordinates":[4.3445510864,50.8386573792],"type":"Point"}
}