{
  "type": "Feature",
  "properties": {
    "iso:country":"BE",
    "sg:address":"Dendermondsesteenweg 21ba",
    "sg:city":"Laarne",
    "sg:orig_category":"Afval and schroot Gh",
    "sg:phone":"+32 9 367 72 64",
    "sg:postcode":"9270",
    "sg:province":"Oost-Vlaanderen",
    "wof:name":"A.s.a.",
    "wof:placetype":"venue"
},
  "geometry": {"coordinates":[3.9114449024,51.0431060791],"type":"Point"}
}