{
  "type": "Feature",
  "properties": {
    "iso:country":"BE",
    "sg:address":"Wijvestraat 138",
    "sg:city":"Zonhoven",
    "sg:classifiers":[
        {
            "category":"Manufacturing",
            "subcategory":"Lumber",
            "type":"Manufacturing & Wholesale Goods"
        }
    ],
    "sg:phone":"+32 11 81 54 09",
    "sg:postcode":"3520",
    "sg:province":"Limburg",
    "sg:tags":[
        "timber"
    ],
    "wof:name":"Schruers J & R Bvba",
    "wof:placetype":"venue"
},
  "geometry": {"coordinates":[5.3316140175,50.9897422791],"type":"Point"}
}