{
  "type": "Feature",
  "properties": {
    "addr:full":"Rue De La Station 47 Braine-le-comte Hainaut 7090",
    "addr:housenumber":"47",
    "addr:postcode":"7090",
    "addr:street":"Rue De La Station",
    "iso:country":"BE",
    "sg:address":"Rue De La Station 47",
    "sg:city":"Braine-le-comte",
    "sg:classifiers":[
        {
            "category":"Shopping",
            "subcategory":"Books",
            "type":"Retail Goods"
        }
    ],
    "sg:phone":"+32 67 55 29 54",
    "sg:postcode":"7090",
    "sg:province":"Hainaut",
    "sg:tags":[
        "bookseller"
    ],
    "wof:name":"Lembourg A",
    "wof:placetype":"venue"
},
  "geometry": {"coordinates":[4.1371197701,50.6085586548],"type":"Point"}
}