{
  "type": "Feature",
  "properties": {
    "iso:country":"BE",
    "sg:address":"Daaleindestraat 2",
    "sg:city":"Kortessem",
    "sg:orig_category":"Openbare bibliotheken and archieven",
    "sg:phone":"+32 11 37 80 32",
    "sg:postcode":"3720",
    "sg:province":"Limburg",
    "wof:name":"Openbare Bibliotheek",
    "wof:placetype":"venue"
},
  "geometry": {"coordinates":[5.3908519745,50.8596992493],"type":"Point"}
}