{
  "type": "Feature",
  "properties": {
    "addr:full":"De Peuthystraat 32 Huldenberg Vlaams-Brabant 3040",
    "addr:housenumber":"32",
    "addr:postcode":"3040",
    "addr:street":"De Peuthystraat",
    "iso:country":"BE",
    "sg:address":"De Peuthystraat 32",
    "sg:city":"Huldenberg",
    "sg:classifiers":[
        {
            "category":"Health Services",
            "subcategory":"Health Practitioner",
            "type":"Services"
        }
    ],
    "sg:phone":"+32 2 687 82 17",
    "sg:postcode":"3040",
    "sg:province":"Vlaams-Brabant",
    "sg:tags":[
        "physiotherapist"
    ],
    "wof:name":"Watticant Jacques",
    "wof:placetype":"venue"
},
  "geometry": {"coordinates":[4.578895092,50.7908668518],"type":"Point"}
}