{
  "type": "Feature",
  "properties": {
    "iso:country":"BE",
    "sg:address":"23",
    "sg:city":"Graaf Van Hoornestraat 9850 Nevele",
    "sg:classifiers":[
        {
            "category":"Home & Garden",
            "subcategory":"Furniture",
            "type":"Retail Goods"
        }
    ],
    "sg:phone":"+32 9 371 51 93",
    "sg:postcode":"23",
    "sg:tags":[
        "household",
        "wood"
    ],
    "wof:name":"Dsm Keukens Nv",
    "wof:placetype":"venue"
},
  "geometry": {"coordinates":[3.5347230434,51.0359649658],"type":"Point"}
}