{
  "type": "Feature",
  "properties": {
    "iso:country":"BE",
    "sg:address":"Rue Grande 29",
    "sg:city":"Tellin",
    "sg:orig_category":"Paramedische behandelingen",
    "sg:phone":"+32 84 36 68 35",
    "sg:postcode":"6927",
    "sg:province":"Luxembourg",
    "wof:name":"M. Perpete",
    "wof:placetype":"venue"
},
  "geometry": {"coordinates":[5.2209181786,50.0823326111],"type":"Point"}
}