{
  "type": "Feature",
  "properties": {
    "iso:country":"BE",
    "sg:address":"Alfons De Cockplein 29",
    "sg:city":"Machelen (diegem)",
    "sg:classifiers":[
        {
            "category":"Cafe",
            "type":"Food & Drink"
        }
    ],
    "sg:phone":"+32 2 720 80 01",
    "sg:postcode":"1831",
    "sg:province":"Vlaams-Brabant",
    "sg:tags":[
        "snack-bars"
    ],
    "wof:name":"Snackbreak",
    "wof:placetype":"venue"
},
  "geometry": {"coordinates":[4.4364938736,50.8954658508],"type":"Point"}
}