{
  "type": "Feature",
  "properties": {
    "addr:full":"Voordries 21a Oosterzele Oost-Vlaanderen 9860",
    "addr:housenumber":"21a",
    "addr:postcode":"9860",
    "addr:street":"Voordries;Oost-Vlaanderen",
    "iso:country":"BE",
    "sg:address":"Voordries 21a",
    "sg:city":"Oosterzele",
    "sg:orig_category":"Schoonmaakbedrijven and ongediertebestrijding",
    "sg:phone":"+32 9 362 87 21",
    "sg:postcode":"9860",
    "sg:province":"Oost-Vlaanderen",
    "wof:name":"Kilisan",
    "wof:placetype":"venue"
},
  "geometry": {"coordinates":[3.8059110641,50.9500160217],"type":"Point"}
}