{
  "type": "Feature",
  "properties": {
    "addr:full":"Loverstraat 52 Wielsbeke West-Vlaanderen 8710",
    "addr:housenumber":"52",
    "addr:postcode":"8710",
    "addr:street":"Loverstraat",
    "iso:country":"BE",
    "sg:address":"Loverstraat 52",
    "sg:city":"Wielsbeke",
    "sg:orig_category":"Mat\u00e9riaux de construction Gr",
    "sg:phone":"+32 56 60 36 48",
    "sg:postcode":"8710",
    "sg:province":"West-Vlaanderen",
    "wof:name":"Lura",
    "wof:placetype":"venue"
},
  "geometry": {"coordinates":[3.3979129791,50.9190177917],"type":"Point"}
}