{
  "type": "Feature",
  "properties": {
    "iso:country":"BE",
    "sg:address":"Sint-gillislaan 117",
    "sg:city":"Dendermonde",
    "sg:orig_category":"Apotheken",
    "sg:phone":"+32 52 21 11 87",
    "sg:postcode":"9200",
    "sg:province":"Oost-Vlaanderen",
    "wof:name":"Gratien Vercraeye",
    "wof:placetype":"venue"
},
  "geometry": {"coordinates":[4.1108207703,51.0195159912],"type":"Point"}
}