{
  "type": "Feature",
  "properties": {
    "addr:full":"Kruidtuinlaan 44 Brussel/bruxelles Bruxelles-Capitale 1000",
    "addr:housenumber":"44",
    "addr:postcode":"1000",
    "addr:street":"Kruidtuinlaan;/",
    "iso:country":"BE",
    "sg:address":"Kruidtuinlaan 44",
    "sg:city":"Brussel/bruxelles",
    "sg:orig_category":"CD's, cassettes and platen Openbare bibliotheken and archieven Verhuur video and audio",
    "sg:phone":"+32 2 218 26 35",
    "sg:postcode":"1000",
    "sg:province":"Bruxelles-Capitale",
    "wof:name":"M\u00c9diath. Comm. Fr. Belg.",
    "wof:placetype":"venue"
},
  "geometry": {"coordinates":[4.3628377914,50.8537750244],"type":"Point"}
}