{
  "type": "Feature",
  "properties": {
    "iso:country":"BE",
    "sg:address":"Rue De Robersart 56",
    "sg:city":"Floreffe (frani\u00e8re)",
    "sg:classifiers":[
        {
            "category":"Parking",
            "subcategory":"Lot",
            "type":"Transportation"
        }
    ],
    "sg:phone":"+32 81 44 07 05",
    "sg:postcode":"5150",
    "sg:province":"Namur",
    "sg:tags":[
        "parking-places",
        "laying-out"
    ],
    "wof:name":"Gorlier Sprl",
    "wof:placetype":"venue"
},
  "geometry": {"coordinates":[4.7487239838,50.429019928],"type":"Point"}
}