{
  "type": "Feature",
  "properties": {
    "iso:country":"BE",
    "sg:address":"Chauss\u00e9e De Mons 816",
    "sg:city":"Bruxelles (anderlecht)",
    "sg:orig_category":"Non-Classified Establishments",
    "sg:phone":"+32 2 521 24 22",
    "sg:postcode":"1070",
    "sg:province":"Bruxelles-Capitale",
    "wof:name":"Servitech Outillages Sa",
    "wof:placetype":"venue"
},
  "geometry": {"coordinates":[4.3029670715,50.8280754089],"type":"Point"}
}