{
  "type": "Feature",
  "properties": {
    "addr:full":"Lakensestraat 169 Brussel/bruxelles Bruxelles-Capitale 1000",
    "addr:housenumber":"169",
    "addr:postcode":"1000",
    "addr:street":"Lakensestraat;/",
    "iso:country":"BE",
    "sg:address":"Lakensestraat 169",
    "sg:city":"Brussel/bruxelles",
    "sg:orig_category":"Passagiersvervoer over de weg",
    "sg:phone":"+32 2 513 41 50",
    "sg:postcode":"1000",
    "sg:province":"Bruxelles-Capitale",
    "wof:name":"Voyages Starbus",
    "wof:placetype":"venue"
},
  "geometry": {"coordinates":[4.352602005,50.8558006287],"type":"Point"}
}