{
  "type": "Feature",
  "properties": {
    "addr:full":"Rue De Danemark 31ba Sint-gillis/saint-gilles Bruxelles-Capitale 1060",
    "addr:housenumber":"31ba",
    "addr:postcode":"1060",
    "addr:street":"Rue De Danemark",
    "iso:country":"BE",
    "sg:address":"Rue De Danemark 31ba",
    "sg:city":"Sint-gillis/saint-gilles",
    "sg:orig_category":"Plomberie, chauffage and installations sanitaires",
    "sg:phone":"+32 2 538 94 28",
    "sg:postcode":"1060",
    "sg:province":"Bruxelles-Capitale",
    "wof:name":"Manuel Da Silva Pereira",
    "wof:placetype":"venue"
},
  "geometry": {"coordinates":[4.3356018066,50.831993103],"type":"Point"}
}