{
  "type": "Feature",
  "properties": {
    "iso:country":"BE",
    "sg:address":"Rue Neuve 6b2",
    "sg:city":"Mons",
    "sg:orig_category":"Advocaten and juridische adviseurs",
    "sg:phone":"+32 477 77 21 10",
    "sg:postcode":"7000",
    "sg:province":"Hainaut",
    "wof:name":"Fr\u00c9d\u00c9rique Mathy",
    "wof:placetype":"venue"
},
  "geometry": {"coordinates":[3.9526269436,50.4555702209],"type":"Point"}
}