{
  "type": "Feature",
  "properties": {
    "iso:country":"BE",
    "sg:address":"Potaardestraat 2",
    "sg:city":"Meise",
    "sg:orig_category":"Groententeelt",
    "sg:phone":"+32 2 269 37 97",
    "sg:postcode":"1860",
    "sg:province":"Vlaams-Brabant",
    "wof:name":"Etienne Van Houtte",
    "wof:placetype":"venue"
},
  "geometry": {"coordinates":[4.3326368332,50.9601631165],"type":"Point"}
}