{
  "type": "Feature",
  "properties": {
    "addr:full":"Markt 1-3 Blankenberge West-Vlaanderen 8370",
    "addr:housenumber":"1-3",
    "addr:postcode":"8370",
    "addr:street":"Markt",
    "iso:country":"BE",
    "sg:address":"Markt 1-3",
    "sg:city":"Blankenberge",
    "sg:orig_category":"Huisdierenkwekers",
    "sg:phone":"+32 50 41 64 72",
    "sg:postcode":"8370",
    "sg:province":"West-Vlaanderen",
    "wof:name":"Dierenplezier",
    "wof:placetype":"venue"
},
  "geometry": {"coordinates":[3.1356759071,51.3131713867],"type":"Point"}
}