{
  "type": "Feature",
  "properties": {
    "addr:full":"Molenstraat 153 Kaprijke Oost-Vlaanderen 9970",
    "addr:housenumber":"153",
    "addr:postcode":"9970",
    "addr:street":"Molenstraat",
    "iso:country":"BE",
    "sg:address":"Molenstraat 153",
    "sg:city":"Kaprijke",
    "sg:orig_category":"Rundveehouders Varkenskwekers",
    "sg:phone":"+32 9 379 83 84",
    "sg:postcode":"9970",
    "sg:province":"Oost-Vlaanderen",
    "wof:name":"Denis De Sutter",
    "wof:placetype":"venue"
},
  "geometry": {"coordinates":[3.618021965,51.2349853516],"type":"Point"}
}