{
  "type": "Feature",
  "properties": {
    "addr:full":"Molendreef 11 Lovendegem Oost-Vlaanderen 9920",
    "addr:housenumber":"11",
    "addr:postcode":"9920",
    "addr:street":"Molendreef",
    "iso:country":"BE",
    "sg:address":"Molendreef 11",
    "sg:city":"Lovendegem",
    "sg:orig_category":"Banques and organismes de cr\u00e9dit",
    "sg:phone":"+32 9 372 07 06",
    "sg:postcode":"9920",
    "sg:province":"Oost-Vlaanderen",
    "wof:name":"Ippa",
    "wof:placetype":"venue"
},
  "geometry": {"coordinates":[3.6080989838,51.0965042114],"type":"Point"}
}