{
  "type": "Feature",
  "properties": {
    "addr:full":"Rue Des Fraisiers 19 Li\u00c8ge Li\u00e8ge 4000",
    "addr:housenumber":"19",
    "addr:postcode":"4000",
    "addr:street":"Rue Des Fraisiers",
    "iso:country":"BE",
    "sg:address":"Rue Des Fraisiers 19",
    "sg:city":"Li\u00c8ge",
    "sg:orig_category":"Woningbouw",
    "sg:phone":"+32 4 227 94 26",
    "sg:postcode":"4000",
    "sg:province":"Li\u00e8ge",
    "wof:name":"Vincenzo Miceli",
    "wof:placetype":"venue"
},
  "geometry": {"coordinates":[5.5635809898,50.6450462341],"type":"Point"}
}