{
  "type": "Feature",
  "properties": {
    "addr:full":"Driekruisenstraat 3 Tongeren Limburg 3700",
    "addr:housenumber":"3",
    "addr:postcode":"3700",
    "addr:street":"Driekruisenstraat",
    "iso:country":"BE",
    "sg:address":"Driekruisenstraat 3",
    "sg:city":"Tongeren",
    "sg:orig_category":"Traitement and fa\u00e7onnage de la pierre. Mat\u00e9riaux de construction Gr",
    "sg:phone":"+32 12 23 13 34",
    "sg:postcode":"3700",
    "sg:province":"Limburg",
    "wof:name":"Hauben-baeten",
    "wof:placetype":"venue"
},
  "geometry": {"coordinates":[5.4690718651,50.7851753235],"type":"Point"}
}