{
  "type": "Feature",
  "properties": {
    "iso:country":"BE",
    "sg:address":"Lage Avrijestraat 1a",
    "sg:city":"Evergem (ertvelde)",
    "sg:classifiers":[
        {
            "category":"Manufacturing",
            "subcategory":"Metals",
            "type":"Manufacturing & Wholesale Goods"
        }
    ],
    "sg:phone":"+32 9 344 69 69",
    "sg:postcode":"9940",
    "sg:province":"Oost-Vlaanderen",
    "sg:tags":[
        "alloy",
        "aluminium"
    ],
    "wof:name":"Demar-lux Bvba",
    "wof:placetype":"venue"
},
  "geometry": {"coordinates":[3.7615149021,51.167842865],"type":"Point"}
}