{
  "type": "Feature",
  "properties": {
    "addr:full":"Rue Du Paruck 20 Sint-jans-molenbeek/molenbeek-saint-jean Bruxelles-Capitale 1080",
    "addr:housenumber":"20",
    "addr:postcode":"1080",
    "addr:street":"Rue Du Paruck",
    "iso:country":"BE",
    "sg:address":"Rue Du Paruck 20",
    "sg:city":"Sint-jans-molenbeek/molenbeek-saint-jean",
    "sg:orig_category":"Enseignement maternel and primaire",
    "sg:phone":"+32 2 410 83 64",
    "sg:postcode":"1080",
    "sg:province":"Bruxelles-Capitale",
    "wof:name":"Vrije Kleuterschool",
    "wof:placetype":"venue"
},
  "geometry": {"coordinates":[4.3195958138,50.8587799072],"type":"Point"}
}