{
  "type": "Feature",
  "properties": {
    "iso:country":"BE",
    "sg:address":"Pieter Van Den Bemdenlaan 25",
    "sg:city":"Edegem",
    "sg:classifiers":[
        {
            "category":"Retail",
            "subcategory":"Veterinary Services",
            "type":"Services"
        }
    ],
    "sg:phone":"+32 3 289 82 02",
    "sg:postcode":"2650",
    "sg:province":"Antwerpen",
    "sg:tags":[
        "veterinarian"
    ],
    "wof:name":"Deveugle K",
    "wof:placetype":"venue"
},
  "geometry": {"coordinates":[4.4195251465,51.1588859558],"type":"Point"}
}