{
  "type": "Feature",
  "properties": {
    "addr:full":"Square Eug\u00c8ne Plasky 92-94 Brussel Bruxelles-Capitale 1030",
    "addr:postcode":"92-94;1030",
    "addr:street":"Square Euge\u0300Ne Plasky",
    "iso:country":"BE",
    "sg:address":"Square Eug\u00c8ne Plasky 92-94",
    "sg:city":"Brussel",
    "sg:orig_category":"Peinture. Rev\u00eatements pour sols and murs. Rev\u00eatements de sols and murs",
    "sg:phone":"+32 2 736 60 46",
    "sg:postcode":"1030",
    "sg:province":"Bruxelles-Capitale",
    "wof:name":"Belgium Services",
    "wof:placetype":"venue"
},
  "geometry": {"coordinates":[4.3958830833,50.8511657715],"type":"Point"}
}