{
  "type": "Feature",
  "properties": {
    "iso:country":"BE",
    "sg:address":"Rue De La Boucherie 4",
    "sg:city":"Li\u00e8ge 1",
    "sg:classifiers":[
        {
            "category":"Museum",
            "type":"Entertainment"
        }
    ],
    "sg:phone":"+32 4 221 94 16",
    "sg:postcode":"4000",
    "sg:province":"Li\u00e8ge",
    "wof:name":"Mus\u00e9e D'armes",
    "wof:placetype":"venue"
},
  "geometry": {"coordinates":[5.5780630112,50.6454811096],"type":"Point"}
}