{
  "type": "Feature",
  "properties": {
    "iso:country":"BE",
    "sg:address":"Rue Sainte-croix 1",
    "sg:city":"Arlon",
    "sg:classifiers":[
        {
            "category":"Shopping",
            "subcategory":"Crafts & Fabrics",
            "type":"Retail Goods"
        }
    ],
    "sg:phone":"+32 495 82 18 01",
    "sg:postcode":"6700",
    "sg:province":"Luxembourg",
    "sg:tags":[
        "upholstery",
        "-"
    ],
    "wof:name":"Lecoq & Lecoq",
    "wof:placetype":"venue"
},
  "geometry": {"coordinates":[5.8103709221,49.6899604797],"type":"Point"}
}