{
  "type": "Feature",
  "properties": {
    "iso:country":"BE",
    "sg:address":"Driemasten 50",
    "sg:city":"Wevelgem (gullegem)",
    "sg:classifiers":[
        {
            "category":"Professional",
            "subcategory":"Management & Consulting",
            "type":"Services"
        }
    ],
    "sg:phone":"+32 56 40 44 99",
    "sg:postcode":"8560",
    "sg:province":"West-Vlaanderen",
    "sg:tags":[
        "consultant"
    ],
    "wof:name":"Wytex",
    "wof:placetype":"venue"
},
  "geometry": {"coordinates":[3.1984930038,50.8482398987],"type":"Point"}
}