{
  "type": "Feature",
  "properties": {
    "iso:country":"BE",
    "sg:address":"Rue Du Cura 59",
    "sg:city":"Nivelles",
    "sg:orig_category":"Herstellingen and onderhoud van auto's",
    "sg:phone":"+32 67 84 08 13",
    "sg:postcode":"1400",
    "sg:province":"Brabant Wallon",
    "wof:name":"Carrosserie Fizaine",
    "wof:placetype":"venue"
},
  "geometry": {"coordinates":[4.3273868561,50.6010894775],"type":"Point"}
}