{
  "type": "Feature",
  "properties": {
    "addr:full":"Maurits Sabbestraat 80 Mechelen Antwerpen 2800",
    "addr:housenumber":"80",
    "addr:postcode":"2800",
    "addr:street":"Maurits Sabbestraat",
    "iso:country":"BE",
    "sg:address":"Maurits Sabbestraat 80",
    "sg:city":"Mechelen",
    "sg:classifiers":[
        {
            "category":"Health Services",
            "subcategory":"Health Practitioner",
            "type":"Services"
        }
    ],
    "sg:phone":"+32 15 34 35 33",
    "sg:postcode":"2800",
    "sg:province":"Antwerpen",
    "sg:tags":[
        "physiotherapist"
    ],
    "wof:name":"De Rademaeker E",
    "wof:placetype":"venue"
},
  "geometry": {"coordinates":[4.4755401611,51.0366706848],"type":"Point"}
}