{
  "type": "Feature",
  "properties": {
    "iso:country":"BE",
    "sg:address":"Stationsstraat 13",
    "sg:city":"Kortessem",
    "sg:orig_category":"Enseignement maternel and primaire",
    "sg:phone":"+32 11 37 65 41",
    "sg:postcode":"3722",
    "sg:province":"Limburg",
    "wof:name":"Vrije Kleuterschool",
    "wof:placetype":"venue"
},
  "geometry": {"coordinates":[5.4184751511,50.85364151],"type":"Point"}
}