{
  "type": "Feature",
  "properties": {
    "addr:full":"Houlteau 5 Thimister-clermont (thimister) Li\u00e8ge 4890",
    "addr:housenumber":"5",
    "addr:postcode":"4890",
    "addr:street":"Houlteau",
    "iso:country":"BE",
    "sg:address":"Houlteau 5",
    "sg:city":"Thimister-clermont (thimister)",
    "sg:classifiers":[
        {
            "category":"Autos & Motor Vehicles",
            "subcategory":"Motorcycle Sales",
            "type":"Retail Goods"
        }
    ],
    "sg:phone":"+32 87 34 17 11",
    "sg:postcode":"4890",
    "sg:province":"Li\u00e8ge",
    "sg:tags":[
        "motorbike"
    ],
    "wof:name":"Motos Shop Racing Sprl",
    "wof:placetype":"venue"
},
  "geometry": {"coordinates":[5.8637452126,50.6363334656],"type":"Point"}
}