{
  "type": "Feature",
  "properties": {
    "addr:full":"Oosterwennel 32 Genk Limburg 3600",
    "addr:housenumber":"32",
    "addr:postcode":"3600",
    "addr:street":"Oosterwennel",
    "iso:country":"BE",
    "sg:address":"Oosterwennel 32",
    "sg:city":"Genk",
    "sg:classifiers":[
        {
            "category":"Professional",
            "subcategory":"Advertising",
            "type":"Services"
        }
    ],
    "sg:phone":"+32 89 36 24 32",
    "sg:postcode":"3600",
    "sg:province":"Limburg",
    "sg:tags":[
        "aerial",
        "-"
    ],
    "wof:name":"De Weyer August",
    "wof:placetype":"venue"
},
  "geometry": {"coordinates":[5.4733729362,50.9664916992],"type":"Point"}
}