{
  "type": "Feature",
  "properties": {
    "addr:full":"Flamingostraat 7 Oostende (stene) West-Vlaanderen 8400",
    "addr:housenumber":"7",
    "addr:postcode":"8400",
    "addr:street":"Flamingostraat",
    "iso:country":"BE",
    "sg:address":"Flamingostraat 7",
    "sg:city":"Oostende (stene)",
    "sg:classifiers":[
        {
            "category":"Professional",
            "subcategory":"Computer Services",
            "type":"Services"
        }
    ],
    "sg:phone":"+32 59 43 41 35",
    "sg:postcode":"8400",
    "sg:province":"West-Vlaanderen",
    "sg:tags":[
        "-",
        "processing",
        "data",
        "software"
    ],
    "wof:name":"Owl & Partners",
    "wof:placetype":"venue"
},
  "geometry": {"coordinates":[2.9126999378,51.2312583923],"type":"Point"}
}