{
  "type": "Feature",
  "properties": {
    "addr:full":"Rue Baty De Fleurus 59 Gembloux Namur 5030",
    "addr:housenumber":"59",
    "addr:postcode":"5030",
    "addr:street":"Rue Baty De Fleurus;Namur",
    "iso:country":"BE",
    "sg:address":"Rue Baty De Fleurus 59",
    "sg:city":"Gembloux",
    "sg:orig_category":"Diverse bouwafwerking and reiniging Tuinen",
    "sg:phone":"+32 81 61 24 14",
    "sg:postcode":"5030",
    "sg:province":"Namur",
    "wof:name":"Dutrecq Anselme",
    "wof:placetype":"venue"
},
  "geometry": {"coordinates":[4.6977500916,50.5494689941],"type":"Point"}
}