{
  "type": "Feature",
  "properties": {
    "addr:full":"Doorniksewijk 66 Kortrijk West-Vlaanderen 8500",
    "addr:housenumber":"66",
    "addr:postcode":"8500",
    "addr:street":"Doorniksewijk",
    "iso:country":"BE",
    "sg:address":"Doorniksewijk 66",
    "sg:city":"Kortrijk",
    "sg:orig_category":"Advocaten and juridische adviseurs",
    "sg:phone":"+32 56 26 83 83",
    "sg:postcode":"8500",
    "sg:province":"West-Vlaanderen",
    "wof:name":"Hans Dhondt",
    "wof:placetype":"venue"
},
  "geometry": {"coordinates":[3.2686159611,50.8216285706],"type":"Point"}
}