{
  "type": "Feature",
  "properties": {
    "addr:full":"Rue Provinciale 470b73 Juprelle Li\u00e8ge 4458",
    "addr:postcode":"4458",
    "addr:street":"Rue Provinciale 470B73",
    "iso:country":"BE",
    "sg:address":"Rue Provinciale 470b73",
    "sg:city":"Juprelle",
    "sg:orig_category":"Apotheken",
    "sg:phone":"+32 4 278 50 05",
    "sg:postcode":"4458",
    "sg:province":"Li\u00e8ge",
    "wof:name":"M.j. Languenackers",
    "wof:placetype":"venue"
},
  "geometry": {"coordinates":[5.5669198036,50.7078514099],"type":"Point"}
}