{
  "type": "Feature",
  "properties": {
    "addr:full":"Paardsdemerstraat 21 Hasselt (groot) Limburg 3500",
    "addr:housenumber":"21",
    "addr:postcode":"3500",
    "addr:street":"Paardsdemerstraat;Groot Limburg",
    "iso:country":"BE",
    "sg:address":"Paardsdemerstraat 21",
    "sg:city":"Hasselt (groot)",
    "sg:classifiers":[
        {
            "category":"Restaurant",
            "type":"Food & Drink"
        }
    ],
    "sg:phone":"+32 11 20 14 11",
    "sg:postcode":"3500",
    "sg:province":"Limburg",
    "wof:name":"Preuverie",
    "wof:placetype":"venue"
},
  "geometry": {"coordinates":[5.3394579887,50.9320068359],"type":"Point"}
}