{
  "type": "Feature",
  "properties": {
    "iso:country":"BE",
    "sg:address":"Rue Du Centre 32",
    "sg:city":"Chaudfontaine",
    "sg:classifiers":[
        {
            "category":"Arena",
            "subcategory":"Sports Club",
            "type":"Entertainment"
        }
    ],
    "sg:phone":"+32 4 368 73 82",
    "sg:postcode":"4050",
    "sg:province":"Li\u00e8ge",
    "sg:tags":[
        "de"
    ],
    "wof:name":"Les Calidifontains",
    "wof:placetype":"venue"
},
  "geometry": {"coordinates":[5.6434249878,50.5857200623],"type":"Point"}
}