{
  "type": "Feature",
  "properties": {
    "iso:country":"BE",
    "sg:address":"Veldstraat 57",
    "sg:city":"Kinrooi (kessenich)",
    "sg:classifiers":[
        {
            "category":"Health Services",
            "subcategory":"Dentist",
            "type":"Services"
        }
    ],
    "sg:phone":"+32 89 56 75 80",
    "sg:postcode":"3640",
    "sg:province":"Limburg",
    "wof:name":"Linssen P",
    "wof:placetype":"venue"
},
  "geometry": {"coordinates":[5.8123130798,51.1520996094],"type":"Point"}
}