{
  "type": "Feature",
  "properties": {
    "iso:country":"BE",
    "sg:address":"Sint-jansstraat 78",
    "sg:city":"Herentals",
    "sg:orig_category":"M\u00e9decins and sp\u00e9cialistes",
    "sg:phone":"+32 14 21 01 35",
    "sg:postcode":"2200",
    "sg:province":"Antwerpen",
    "wof:name":"M. Vyncke",
    "wof:placetype":"venue"
},
  "geometry": {"coordinates":[4.8306918144,51.1747779846],"type":"Point"}
}