{
  "type": "Feature",
  "properties": {
    "iso:country":"BE",
    "sg:address":"Tongersesteenweg 28a",
    "sg:city":"Hoeselt",
    "sg:classifiers":[
        {
            "category":"Exhibition Hall",
            "type":"Public Place"
        }
    ],
    "sg:phone":"+32 89 50 15 67",
    "sg:postcode":"3730",
    "sg:province":"Limburg",
    "sg:tags":[
        "inflatable",
        "-"
    ],
    "wof:name":"Artisun",
    "wof:placetype":"venue"
},
  "geometry": {"coordinates":[5.4897041321,50.8483314514],"type":"Point"}
}