{
  "type": "Feature",
  "properties": {
    "iso:country":"BE",
    "sg:address":"Bruggestraat 233",
    "sg:city":"Beernem",
    "sg:orig_category":"Bloemen and planten Gh",
    "sg:phone":"+32 50 37 11 84",
    "sg:postcode":"8730",
    "sg:province":"West-Vlaanderen",
    "wof:name":"Coene",
    "wof:placetype":"venue"
},
  "geometry": {"coordinates":[3.2983489037,51.1858177185],"type":"Point"}
}