{
  "type": "Feature",
  "properties": {
    "iso:country":"BE",
    "sg:address":"Sint-elooistraat 21",
    "sg:city":"Staden",
    "sg:orig_category":"V\u00eatements pour Dames. V\u00eatements de mariage and c\u00e9r\u00e9monies",
    "sg:phone":"+32 51 77 07 37",
    "sg:postcode":"8840",
    "sg:province":"West-Vlaanderen",
    "wof:name":"Modehuis Christine",
    "wof:placetype":"venue"
},
  "geometry": {"coordinates":[2.9876549244,50.9422340393],"type":"Point"}
}