{
  "type": "Feature",
  "properties": {
    "addr:full":"Rijselstraat 237 Menen West-Vlaanderen 8930",
    "addr:housenumber":"237",
    "addr:postcode":"8930",
    "addr:street":"Rijselstraat",
    "iso:country":"BE",
    "sg:address":"Rijselstraat 237",
    "sg:city":"Menen",
    "sg:classifiers":[
        {
            "category":"Bars & Pubs",
            "type":"Food & Drink"
        }
    ],
    "sg:phone":"+32 56 53 08 04",
    "sg:postcode":"8930",
    "sg:province":"West-Vlaanderen",
    "wof:name":"Moka Palace",
    "wof:placetype":"venue"
},
  "geometry": {"coordinates":[3.1269381046,50.7875823975],"type":"Point"}
}