{
  "type": "Feature",
  "properties": {
    "addr:full":"Rue Alfred Lion 22 Marchin Li\u00e8ge 4570",
    "addr:housenumber":"22",
    "addr:postcode":"4570",
    "addr:street":"Rue Alfred Lion",
    "iso:country":"BE",
    "sg:address":"Rue Alfred Lion 22",
    "sg:city":"Marchin",
    "sg:orig_category":"V\u00e9hicules automobiles",
    "sg:phone":"+32 85 21 21 93",
    "sg:postcode":"4570",
    "sg:province":"Li\u00e8ge",
    "wof:name":"Garage Gils",
    "wof:placetype":"venue"
},
  "geometry": {"coordinates":[5.2376699448,50.4907302856],"type":"Point"}
}