{
  "type": "Feature",
  "properties": {
    "addr:full":"Boerenkrijglaan 27 Westerlo Antwerpen 2260",
    "addr:housenumber":"27",
    "addr:postcode":"2260",
    "addr:street":"Boerenkrijglaan",
    "iso:country":"BE",
    "sg:address":"Boerenkrijglaan 27",
    "sg:city":"Westerlo",
    "sg:orig_category":"Enseignement maternel and primaire",
    "sg:phone":"+32 14 54 51 48",
    "sg:postcode":"2260",
    "sg:province":"Antwerpen",
    "wof:name":"Vrije Lagere School",
    "wof:placetype":"venue"
},
  "geometry": {"coordinates":[4.9149799347,51.0879173279],"type":"Point"}
}