{
  "type": "Feature",
  "properties": {
    "iso:country":"BE",
    "sg:address":"Wijdhagestraat 46",
    "sg:city":"Harelbeke (groot)",
    "sg:classifiers":[
        {
            "category":"Personal",
            "subcategory":"Beauty Salon",
            "type":"Services"
        }
    ],
    "sg:phone":"+32 56 32 90 24",
    "sg:postcode":"8530",
    "sg:province":"West-Vlaanderen",
    "sg:tags":[
        "de",
        "coiffure"
    ],
    "wof:name":"Vanessa",
    "wof:placetype":"venue"
},
  "geometry": {"coordinates":[3.3151009083,50.8516654968],"type":"Point"}
}