{
  "type": "Feature",
  "properties": {
    "addr:full":"Boulevard G\u00e9n\u00e9ral Jacques 144 Bruxelles (ixelles) Bruxelles-Capitale 1050",
    "addr:housenumber":"144",
    "addr:postcode":"1050",
    "addr:street":"Boulevard Ge\u0301Ne\u0301Ral Jacques",
    "iso:country":"BE",
    "sg:address":"Boulevard G\u00e9n\u00e9ral Jacques 144",
    "sg:city":"Bruxelles (ixelles)",
    "sg:classifiers":[
        {
            "category":"Education",
            "subcategory":"Dance Studio",
            "type":"Public Place"
        }
    ],
    "sg:phone":"+32 2 779 23 38",
    "sg:postcode":"1050",
    "sg:province":"Bruxelles-Capitale",
    "sg:tags":[
        "school",
        "dancing"
    ],
    "wof:name":"Jazz Dance Studio Asbl",
    "wof:placetype":"venue"
},
  "geometry": {"coordinates":[4.3833150864,50.8202667236],"type":"Point"}
}