{
  "type": "Feature",
  "properties": {
    "addr:full":"Av. St. Pancrace 5 Kraainem Vlaams-Brabant 1950",
    "addr:housenumber":"5",
    "addr:postcode":"1950",
    "addr:street":"Av. St. Pancrace",
    "iso:country":"BE",
    "sg:address":"Av. St. Pancrace 5",
    "sg:city":"Kraainem",
    "sg:orig_category":"Diensten voor huisdieren",
    "sg:phone":"+32 2 721 65 67",
    "sg:postcode":"1950",
    "sg:province":"Vlaams-Brabant",
    "wof:name":"Bocabo",
    "wof:placetype":"venue"
},
  "geometry": {"coordinates":[4.4654560089,50.8617134094],"type":"Point"}
}