{
  "type": "Feature",
  "properties": {
    "iso:country":"BE",
    "sg:address":"Nederenheirweg 21c",
    "sg:city":"Gistel",
    "sg:classifiers":[
        {
            "category":"Personal",
            "subcategory":"Nail Salon",
            "type":"Services"
        }
    ],
    "sg:phone":"+32 59 27 43 63",
    "sg:postcode":"8470",
    "sg:province":"West-Vlaanderen",
    "sg:tags":[
        "pedicure"
    ],
    "wof:name":"Ghyselen M",
    "wof:placetype":"venue"
},
  "geometry": {"coordinates":[2.9560689926,51.152885437],"type":"Point"}
}