{
  "type": "Feature",
  "properties": {
    "iso:country":"BE",
    "sg:address":"Gentsesteenweg 42/1",
    "sg:city":"Zingem",
    "sg:orig_category":"Onderdelen and accessoires voor auto's Telecommunicatieapparaten",
    "sg:phone":"+32 9 384 92 82",
    "sg:postcode":"9750",
    "sg:province":"Oost-Vlaanderen",
    "wof:name":"Arc Oudenaarde",
    "wof:placetype":"venue"
},
  "geometry": {"coordinates":[3.6165370941,50.9030761719],"type":"Point"}
}