{
  "type": "Feature",
  "properties": {
    "addr:full":"Spanjaardhoek 10 Maldegem Oost-Vlaanderen 9991",
    "addr:housenumber":"10",
    "addr:postcode":"9991",
    "addr:street":"Spanjaardhoek",
    "iso:country":"BE",
    "sg:address":"Spanjaardhoek 10",
    "sg:city":"Maldegem",
    "sg:orig_category":"Installatie van houten of kunststof schrijnwerk",
    "sg:phone":"+32 50 71 65 82",
    "sg:postcode":"9991",
    "sg:province":"Oost-Vlaanderen",
    "wof:name":"De Sutter L",
    "wof:placetype":"venue"
},
  "geometry": {"coordinates":[3.4906170368,51.1983528137],"type":"Point"}
}