{
  "type": "Feature",
  "properties": {
    "iso:country":"BE",
    "sg:address":"Hogestraat 53",
    "sg:city":"Torhout",
    "sg:orig_category":"Woningbouw",
    "sg:phone":"+32 50 21 34 26",
    "sg:postcode":"8820",
    "sg:province":"West-Vlaanderen",
    "wof:name":"Fermettebouw Embo",
    "wof:placetype":"venue"
},
  "geometry": {"coordinates":[3.0882780552,51.0731315613],"type":"Point"}
}