{
  "type": "Feature",
  "properties": {
    "iso:country":"BE",
    "sg:address":"Rue Albert I 48",
    "sg:city":"Tubize",
    "sg:classifiers":[
        {
            "category":"Building & Trades",
            "subcategory":"Cleaning & Sanitation",
            "type":"Services"
        }
    ],
    "sg:phone":"+32 2 390 03 48",
    "sg:postcode":"1480",
    "sg:province":"Brabant Wallon",
    "sg:tags":[
        "cleaner",
        "window"
    ],
    "wof:name":"Pletinckx E",
    "wof:placetype":"venue"
},
  "geometry": {"coordinates":[4.204308033,50.6932029724],"type":"Point"}
}