{
  "type": "Feature",
  "properties": {
    "addr:full":"Statiestraat 135 Zwijndrecht Antwerpen 2070",
    "addr:housenumber":"135",
    "addr:postcode":"2070",
    "addr:street":"Statiestraat",
    "iso:country":"BE",
    "sg:address":"Statiestraat 135",
    "sg:city":"Zwijndrecht",
    "sg:orig_category":"Banques and organismes de cr\u00e9dit",
    "sg:phone":"+32 3 253 20 70",
    "sg:postcode":"2070",
    "sg:province":"Antwerpen",
    "wof:name":"Dexia",
    "wof:placetype":"venue"
},
  "geometry": {"coordinates":[4.3293271065,51.2150344849],"type":"Point"}
}