{
  "type": "Feature",
  "properties": {
    "addr:full":"Koningin Astridstraat 30 Scherpenheuvel-zichem Vlaams-Brabant 3270",
    "addr:housenumber":"30",
    "addr:postcode":"3270",
    "addr:street":"Koningin Astridstraat",
    "iso:country":"BE",
    "sg:address":"Koningin Astridstraat 30",
    "sg:city":"Scherpenheuvel-zichem",
    "sg:orig_category":"M\u00e9decins and sp\u00e9cialistes",
    "sg:phone":"+32 13 77 58 25",
    "sg:postcode":"3270",
    "sg:province":"Vlaams-Brabant",
    "wof:name":"Marc Verpoorten",
    "wof:placetype":"venue"
},
  "geometry": {"coordinates":[4.9776058197,50.9763145447],"type":"Point"}
}