{
  "type": "Feature",
  "properties": {
    "addr:full":"'t Zand 28 Brugge West-Vlaanderen 8000",
    "addr:housenumber":"28",
    "addr:postcode":"8000",
    "addr:street":"' T Zand",
    "iso:country":"BE",
    "sg:address":"'t Zand 28",
    "sg:city":"Brugge",
    "sg:classifiers":[
        {
            "category":"Restaurant",
            "type":"Food & Drink"
        }
    ],
    "sg:phone":"+32 50 34 01 77",
    "sg:postcode":"8000",
    "sg:province":"West-Vlaanderen",
    "wof:name":"Palieterke",
    "wof:placetype":"venue"
},
  "geometry": {"coordinates":[3.2182750702,51.2047538757],"type":"Point"}
}