{
  "type": "Feature",
  "properties": {
    "addr:full":"Prinsenlaan 2 Oostende West-Vlaanderen 8400",
    "addr:housenumber":"2",
    "addr:postcode":"8400",
    "addr:street":"Prinsenlaan",
    "iso:country":"BE",
    "sg:address":"Prinsenlaan 2",
    "sg:city":"Oostende",
    "sg:classifiers":[
        {
            "category":"Professional",
            "subcategory":"Lawyer & Legal Services",
            "type":"Services"
        }
    ],
    "sg:phone":"+32 59 51 88 37",
    "sg:postcode":"8400",
    "sg:province":"West-Vlaanderen",
    "wof:name":"De Wispelaere Sabine",
    "wof:placetype":"venue"
},
  "geometry": {"coordinates":[2.9106030464,51.2227325439],"type":"Point"}
}