{
  "type": "Feature",
  "properties": {
    "iso:country":"BE",
    "sg:address":"Rue Vandervelde 146",
    "sg:city":"Pont-a-celles",
    "sg:orig_category":"M\u00e9decins and sp\u00e9cialistes",
    "sg:phone":"+32 71 37 27 19",
    "sg:postcode":"6230",
    "sg:province":"Hainaut",
    "wof:name":"Agn\u00c8s Dohet",
    "wof:placetype":"venue"
},
  "geometry": {"coordinates":[4.3707361221,50.507106781],"type":"Point"}
}