{
  "type": "Feature",
  "properties": {
    "addr:full":"Rue De La Cambre 22bd9 Sint-lambrechts-woluwe/woluwe-saint-lambert Bruxelles-Capitale 1200",
    "addr:postcode":"1200",
    "addr:street":"Rue De La Cambre",
    "iso:country":"BE",
    "sg:address":"Rue De La Cambre 22bd9",
    "sg:city":"Sint-lambrechts-woluwe/woluwe-saint-lambert",
    "sg:orig_category":"Avocats and conseillers juridiques",
    "sg:phone":"+32 2 762 95 95",
    "sg:postcode":"1200",
    "sg:province":"Bruxelles-Capitale",
    "wof:name":"N. Lho\u00cbst",
    "wof:placetype":"venue"
},
  "geometry": {"coordinates":[4.4270591736,50.8394584656],"type":"Point"}
}