{
  "type": "Feature",
  "properties": {
    "iso:country":"BE",
    "sg:address":"Watermolen 1",
    "sg:city":"Aalst",
    "sg:orig_category":"Taxi's speciale diensten",
    "sg:phone":"+32 53 70 05 04",
    "sg:postcode":"9300",
    "sg:province":"Oost-Vlaanderen",
    "wof:name":"Huurhouderij Watermolen",
    "wof:placetype":"venue"
},
  "geometry": {"coordinates":[4.0407509804,50.9331169128],"type":"Point"}
}