{
  "type": "Feature",
  "properties": {
    "addr:full":"De Lochtstraat 39 Schaarbeek/schaerbeek Bruxelles-Capitale 1030",
    "addr:housenumber":"39",
    "addr:postcode":"1030",
    "addr:street":"De Lochtstraat",
    "iso:country":"BE",
    "sg:address":"De Lochtstraat 39",
    "sg:city":"Schaarbeek/schaerbeek",
    "sg:orig_category":"Woningbouw",
    "sg:phone":"+32 2 215 24 69",
    "sg:postcode":"1030",
    "sg:province":"Bruxelles-Capitale",
    "wof:name":"Antrabat",
    "wof:placetype":"venue"
},
  "geometry": {"coordinates":[4.3689432144,50.8642463684],"type":"Point"}
}