{
  "type": "Feature",
  "properties": {
    "addr:full":"Wiedauwlaan 5 Wingene West-Vlaanderen 8750",
    "addr:housenumber":"5",
    "addr:postcode":"8750",
    "addr:street":"Wiedauwlaan",
    "iso:country":"BE",
    "sg:address":"Wiedauwlaan 5",
    "sg:city":"Wingene",
    "sg:classifiers":[
        {
            "category":"Insurance",
            "subcategory":"Insurance Agent",
            "type":"Services"
        }
    ],
    "sg:phone":"+32 51 65 69 12",
    "sg:postcode":"8750",
    "sg:province":"West-Vlaanderen",
    "sg:tags":[
        "broker"
    ],
    "wof:name":"Van Cauwenberghe L",
    "wof:placetype":"venue"
},
  "geometry": {"coordinates":[3.270966053,51.0551948547],"type":"Point"}
}