{
  "type": "Feature",
  "properties": {
    "addr:full":"Kapelstraat 118 Kortessem Limburg 3720",
    "addr:housenumber":"118",
    "addr:postcode":"3720",
    "addr:street":"Kapelstraat;Limburg",
    "iso:country":"BE",
    "sg:address":"Kapelstraat 118",
    "sg:city":"Kortessem",
    "sg:classifiers":[
        {
            "category":"Manufacturing",
            "subcategory":"Textiles",
            "type":"Manufacturing & Wholesale Goods"
        }
    ],
    "sg:phone":"+32 11 37 80 67",
    "sg:postcode":"3720",
    "sg:province":"Limburg",
    "sg:tags":[
        "retail",
        "-"
    ],
    "wof:name":"Houben E",
    "wof:placetype":"venue"
},
  "geometry": {"coordinates":[5.3776059151,50.8728141785],"type":"Point"}
}