{
  "type": "Feature",
  "properties": {
    "iso:country":"BE",
    "sg:address":"Stationstraat 38",
    "sg:city":"Beveren",
    "sg:orig_category":"Fleurs and plantes",
    "sg:phone":"+32 3 775 02 50",
    "sg:postcode":"9120",
    "sg:province":"Oost-Vlaanderen",
    "wof:name":"De Bloemgaard",
    "wof:placetype":"venue"
},
  "geometry": {"coordinates":[4.257311821,51.2107086182],"type":"Point"}
}