{
  "type": "Feature",
  "properties": {
    "addr:full":"Rue De La Chapelle 46 Antoing (p\u00e9ronnes-lez-antoing) Hainaut 7640",
    "addr:housenumber":"46",
    "addr:postcode":"7640",
    "addr:street":"Rue De La Chapelle;Hainaut",
    "iso:country":"BE",
    "sg:address":"Rue De La Chapelle 46",
    "sg:city":"Antoing (p\u00e9ronnes-lez-antoing)",
    "sg:classifiers":[
        {
            "category":"Home & Garden",
            "subcategory":"Garden Supply",
            "type":"Retail Goods"
        }
    ],
    "sg:phone":"+32 69 44 41 30",
    "sg:postcode":"7640",
    "sg:province":"Hainaut",
    "wof:name":"Paradis Vert (au)",
    "wof:placetype":"venue"
},
  "geometry": {"coordinates":[3.4501149654,50.5554351807],"type":"Point"}
}