{
  "type": "Feature",
  "properties": {
    "addr:full":"Aaigemdorp 9 Erpe-mere Oost-Vlaanderen 9420",
    "addr:housenumber":"9",
    "addr:postcode":"9420",
    "addr:street":"Aaigemdorp",
    "iso:country":"BE",
    "sg:address":"Aaigemdorp 9",
    "sg:city":"Erpe-mere",
    "sg:orig_category":"Gespecialiseerde niet-residenti\u00eble bouw",
    "sg:phone":"+32 53 62 38 70",
    "sg:postcode":"9420",
    "sg:province":"Oost-Vlaanderen",
    "wof:name":"De Mulder",
    "wof:placetype":"venue"
},
  "geometry": {"coordinates":[3.9379808903,50.889591217],"type":"Point"}
}