{
  "type": "Feature",
  "properties": {
    "iso:country":"BE",
    "sg:address":"Avenue Schlogel 82",
    "sg:city":"Ciney",
    "sg:classifiers":[
        {
            "category":"Shopping",
            "subcategory":"Florist",
            "type":"Retail Goods"
        }
    ],
    "sg:phone":"+32 83 21 20 99",
    "sg:postcode":"5590",
    "sg:province":"Namur",
    "wof:name":"Fleurs Gille",
    "wof:placetype":"venue"
},
  "geometry": {"coordinates":[5.1101698875,50.2992591858],"type":"Point"}
}