{
  "type": "Feature",
  "properties": {
    "iso:country":"BE",
    "sg:address":"Kleinmolenstraat 151",
    "sg:city":"Overpelt",
    "sg:orig_category":"Non-Classified Establishments",
    "sg:phone":"+32 11 63 25 59",
    "sg:postcode":"3900",
    "sg:province":"Limburg",
    "wof:name":"Candle Delight",
    "wof:placetype":"venue"
},
  "geometry": {"coordinates":[5.4200081825,51.1802597046],"type":"Point"}
}