{
  "type": "Feature",
  "properties": {
    "iso:country":"BE",
    "sg:address":"Voie De L'ardenne 45",
    "sg:city":"Chaudfontaine (embourg)",
    "sg:classifiers":[
        {
            "category":"Shopping",
            "subcategory":"Crafts & Fabrics",
            "type":"Retail Goods"
        }
    ],
    "sg:phone":"+32 4 367 63 41",
    "sg:postcode":"4053",
    "sg:province":"Li\u00e8ge",
    "sg:tags":[
        "graphic",
        "art",
        "supply",
        "-",
        "painting",
        "drawing"
    ],
    "wof:name":"La Malle \u00e0 Papier",
    "wof:placetype":"venue"
},
  "geometry": {"coordinates":[5.6068840027,50.5948600769],"type":"Point"}
}