{
  "type": "Feature",
  "properties": {
    "addr:full":"Antwerpse Steenweg 107 Sint-niklaas Oost-Vlaanderen 9100",
    "addr:housenumber":"107",
    "addr:postcode":"9100",
    "addr:street":"Antwerpse Steenweg",
    "iso:country":"BE",
    "sg:address":"Antwerpse Steenweg 107",
    "sg:city":"Sint-niklaas",
    "sg:classifiers":[
        {
            "category":"Fast Food",
            "type":"Food & Drink"
        }
    ],
    "sg:phone":"+32 3 776 81 06",
    "sg:postcode":"9100",
    "sg:province":"Oost-Vlaanderen",
    "sg:tags":[
        "fried",
        "stand",
        "potato"
    ],
    "wof:name":"Tipzakje('t)",
    "wof:placetype":"venue"
},
  "geometry": {"coordinates":[4.1547040939,51.168548584],"type":"Point"}
}