{
  "type": "Feature",
  "properties": {
    "addr:full":"Dorp 86 Herselt Antwerpen 2230",
    "addr:housenumber":"86",
    "addr:postcode":"2230",
    "addr:street":"Dorp",
    "iso:country":"BE",
    "sg:address":"Dorp 86",
    "sg:city":"Herselt",
    "sg:orig_category":"Banques and organismes de cr\u00e9dit",
    "sg:phone":"+32 14 54 51 54",
    "sg:postcode":"2230",
    "sg:province":"Antwerpen",
    "wof:name":"Anhyp",
    "wof:placetype":"venue"
},
  "geometry": {"coordinates":[4.8842859268,51.0548591614],"type":"Point"}
}