{
  "type": "Feature",
  "properties": {
    "addr:full":"Nijverheidsstraat 13 Boechout Antwerpen 2530",
    "addr:housenumber":"13",
    "addr:postcode":"2530",
    "addr:street":"Nijverheidsstraat",
    "iso:country":"BE",
    "sg:address":"Nijverheidsstraat 13",
    "sg:city":"Boechout",
    "sg:classifiers":[
        {
            "category":"Social Services",
            "subcategory":"Child Care",
            "type":"Services"
        }
    ],
    "sg:phone":"+32 3 366 21 21",
    "sg:postcode":"2530",
    "sg:province":"Antwerpen",
    "sg:tags":[
        "baby",
        "food",
        "children's"
    ],
    "wof:name":"Oce-bio Bvba",
    "wof:placetype":"venue"
},
  "geometry": {"coordinates":[4.4894990921,51.1681137085],"type":"Point"}
}