{
  "type": "Feature",
  "properties": {
    "iso:country":"BE",
    "sg:address":"Deken Darraslaan 27",
    "sg:city":"Tielt",
    "sg:orig_category":"Medische and orthopedische apparaten",
    "sg:phone":"+32 51 40 30 63",
    "sg:postcode":"8700",
    "sg:province":"West-Vlaanderen",
    "wof:name":"Thuiszorgwinkel",
    "wof:placetype":"venue"
},
  "geometry": {"coordinates":[3.3180639744,50.9979972839],"type":"Point"}
}