{
  "type": "Feature",
  "properties": {
    "addr:full":"Hoogstraat 139 Brussel/bruxelles Bruxelles-Capitale 1000",
    "addr:housenumber":"139",
    "addr:postcode":"1000",
    "addr:street":"Hoogstraat;/",
    "iso:country":"BE",
    "sg:address":"Hoogstraat 139",
    "sg:city":"Brussel/bruxelles",
    "sg:orig_category":"Reclamebureaus",
    "sg:phone":"+32 2 514 20 20",
    "sg:postcode":"1000",
    "sg:province":"Bruxelles-Capitale",
    "wof:name":"Gv Company",
    "wof:placetype":"venue"
},
  "geometry": {"coordinates":[4.3501391411,50.8386421204],"type":"Point"}
}