{
  "type": "Feature",
  "properties": {
    "iso:country":"BE",
    "sg:address":"Zwevegemsestraat 5",
    "sg:city":"Kortrijk",
    "sg:classifiers":[
        {
            "category":"Personal",
            "subcategory":"Hair Removal",
            "type":"Services"
        }
    ],
    "sg:phone":"+32 56 20 50 22",
    "sg:postcode":"8500",
    "sg:province":"West-Vlaanderen",
    "sg:tags":[
        "-",
        "cap",
        "hat",
        "men"
    ],
    "wof:name":"Depraetere hoofd-zaken",
    "wof:placetype":"venue"
},
  "geometry": {"coordinates":[3.2721619606,50.8261299133],"type":"Point"}
}