{
  "type": "Feature",
  "properties": {
    "iso:country":"BE",
    "sg:address":"Bronstraat 9",
    "sg:city":"Bertem (leefdaal)",
    "sg:classifiers":[
        {
            "category":"Professional",
            "subcategory":"Accounting & Tax Preparation",
            "type":"Services"
        }
    ],
    "sg:phone":"+32 2 779 92 62",
    "sg:postcode":"3061",
    "sg:province":"Vlaams-Brabant",
    "sg:tags":[
        "accountant"
    ],
    "wof:name":"A.m.a. Bvba",
    "wof:placetype":"venue"
},
  "geometry": {"coordinates":[4.5823712349,50.8420028687],"type":"Point"}
}