{
  "type": "Feature",
  "properties": {
    "iso:country":"BE",
    "sg:address":"Rue Twyeninck 24",
    "sg:city":"Bruxelles",
    "sg:classifiers":[
        {
            "category":"Health Services",
            "subcategory":"Health Practitioner",
            "type":"Services"
        }
    ],
    "sg:phone":"+32 2 248 26 21",
    "sg:postcode":"1130",
    "sg:province":"Bruxelles-Capitale",
    "sg:tags":[
        "physiotherapist"
    ],
    "wof:name":"Diafas Jean",
    "wof:placetype":"venue"
},
  "geometry": {"coordinates":[4.4203028679,50.8969612122],"type":"Point"}
}