{
  "type": "Feature",
  "properties": {
    "addr:full":"Doelen 30 Zoersel Antwerpen 2980",
    "addr:housenumber":"30",
    "addr:postcode":"2980",
    "addr:street":"Doelen",
    "iso:country":"BE",
    "sg:address":"Doelen 30",
    "sg:city":"Zoersel",
    "sg:classifiers":[
        {
            "category":"Insurance",
            "subcategory":"Insurance Agent",
            "type":"Services"
        }
    ],
    "sg:phone":"+32 3 311 50 24",
    "sg:postcode":"2980",
    "sg:province":"Antwerpen",
    "sg:tags":[
        "verzekeringsmakelaars",
        "expert"
    ],
    "wof:name":"Z.z.v.k.",
    "wof:placetype":"venue"
},
  "geometry": {"coordinates":[4.711771965,51.2720527649],"type":"Point"}
}