{
  "type": "Feature",
  "properties": {
    "iso:country":"BE",
    "sg:address":"Avenue De La Faisanderie 14",
    "sg:city":"Bruxelles (woluwe-saint-pierre)",
    "sg:classifiers":[
        {
            "category":"Government",
            "subcategory":"Embassy",
            "type":"Public Place"
        }
    ],
    "sg:phone":"+32 2 762 94 00",
    "sg:postcode":"1150",
    "sg:province":"Bruxelles-Capitale",
    "sg:tags":[
        "consulate"
    ],
    "wof:name":"Trinidad & Tobago",
    "wof:placetype":"venue"
},
  "geometry": {"coordinates":[4.4492330551,50.8223304749],"type":"Point"}
}