{
  "type": "Feature",
  "properties": {
    "iso:country":"BE",
    "sg:address":"Herbesthaler Strasse 44",
    "sg:city":"Eupen/eupen",
    "sg:orig_category":"IJzerwaren, bouw- and verfmaterialen Tuinbenodigdheden",
    "sg:phone":"+32 87 74 07 49",
    "sg:postcode":"4700",
    "sg:province":"Li\u00e8ge",
    "wof:name":"Jardinex",
    "wof:placetype":"venue"
},
  "geometry": {"coordinates":[6.0480628014,50.6288833618],"type":"Point"}
}