{
  "type": "Feature",
  "properties": {
    "addr:full":"Klein Hoefblad 16 Dilbeek Vlaams-Brabant 1700",
    "addr:housenumber":"16",
    "addr:postcode":"1700",
    "addr:street":"Klein Hoefblad",
    "iso:country":"BE",
    "sg:address":"Klein Hoefblad 16",
    "sg:city":"Dilbeek",
    "sg:orig_category":"Peinture",
    "sg:phone":"+32 2 463 04 10",
    "sg:postcode":"1700",
    "sg:province":"Vlaams-Brabant",
    "wof:name":"Muyldermans",
    "wof:placetype":"venue"
},
  "geometry": {"coordinates":[4.239358902,50.8567428589],"type":"Point"}
}