{
  "type": "Feature",
  "properties": {
    "iso:country":"BE",
    "sg:address":"Rue Cottrel 13",
    "sg:city":"Tournai",
    "sg:orig_category":"Instituts de beaut\u00e9",
    "sg:phone":"+32 69 22 77 21",
    "sg:postcode":"7500",
    "sg:province":"Hainaut",
    "wof:name":"M.c. Lelong",
    "wof:placetype":"venue"
},
  "geometry": {"coordinates":[3.3835880756,50.6009483337],"type":"Point"}
}