{
  "type": "Feature",
  "properties": {
    "addr:full":"Gulden-vlieslaan 21 Elsene/ixelles Bruxelles-Capitale 1050",
    "addr:housenumber":"21",
    "addr:postcode":"1050",
    "addr:street":"Gulden-Vlieslaan",
    "iso:country":"BE",
    "sg:address":"Gulden-vlieslaan 21",
    "sg:city":"Elsene/ixelles",
    "sg:orig_category":"Luchtvaart volgens dienstregeling",
    "sg:phone":"+32 2 502 47 44",
    "sg:postcode":"1050",
    "sg:province":"Bruxelles-Capitale",
    "wof:name":"Thai Airways Intern. Ltd/thai Airways Int.",
    "wof:placetype":"venue"
},
  "geometry": {"coordinates":[4.3595509529,50.8371696472],"type":"Point"}
}