{
  "type": "Feature",
  "properties": {
    "iso:country":"BE",
    "sg:address":"Rue Des Haies 63",
    "sg:city":"Charleroi",
    "sg:orig_category":"Machines \u00e0 coudre and tricoter",
    "sg:phone":"+32 71 36 43 08",
    "sg:postcode":"6001",
    "sg:province":"Hainaut",
    "wof:name":"Francoise Louis",
    "wof:placetype":"venue"
},
  "geometry": {"coordinates":[4.4502768517,50.3972320557],"type":"Point"}
}