{
  "type": "Feature",
  "properties": {
    "iso:country":"BE",
    "sg:address":"Chauss\u00c9e De Waterloo 1384e",
    "sg:city":"Ukkel/uccle",
    "sg:orig_category":"Mat\u00e9riel de T\u00e9l\u00e9communication. Equipement photographique. Location de cassettes vid\u00e9o and audio. Ele",
    "sg:phone":"+32 2 374 99 66",
    "sg:postcode":"1180",
    "sg:province":"Bruxelles-Capitale",
    "wof:name":"Vid\u00c9otec",
    "wof:placetype":"venue"
},
  "geometry": {"coordinates":[4.3762331009,50.7875671387],"type":"Point"}
}