{
  "type": "Feature",
  "properties": {
    "addr:full":"Rue D'angleterre 17 Chimay Hainaut 6460",
    "addr:housenumber":"17",
    "addr:postcode":"6460",
    "addr:street":"Rue D'Angleterre",
    "iso:country":"BE",
    "sg:address":"Rue D'angleterre 17",
    "sg:city":"Chimay",
    "sg:classifiers":[
        {
            "category":"Restaurant",
            "type":"Food & Drink"
        }
    ],
    "sg:phone":"+32 60 21 18 68",
    "sg:postcode":"6460",
    "sg:province":"Hainaut",
    "sg:tags":[
        "organisatie",
        "feesten",
        "van",
        "catering"
    ],
    "wof:name":"Le Napoleon",
    "wof:placetype":"venue"
},
  "geometry": {"coordinates":[4.3146891594,50.0483436584],"type":"Point"}
}