{
  "type": "Feature",
  "properties": {
    "addr:full":"Saviolaan 4 Dilbeek 1710",
    "addr:housenumber":"4",
    "addr:postcode":"1710",
    "addr:street":"Saviolaan",
    "iso:country":"BE",
    "sg:address":"Saviolaan 4",
    "sg:city":"Dilbeek",
    "sg:classifiers":[
        {
            "category":"Banks & Credit Unions",
            "subcategory":"Bank",
            "type":"Services"
        }
    ],
    "sg:phone":"+32 2 466 53 70",
    "sg:postcode":"1710",
    "wof:name":"Aslk-cger Bank",
    "wof:placetype":"venue"
},
  "geometry": {"coordinates":[4.2624697685,50.8459281921],"type":"Point"}
}