{
  "type": "Feature",
  "properties": {
    "addr:full":"Chauss\u00e9e De La Grande Espinette 71 Rhode-saint-gen\u00e8se Vlaams-Brabant 1640",
    "addr:housenumber":"71",
    "addr:postcode":"1640",
    "addr:street":"Chausse\u0301E De La Grande Espinette",
    "iso:country":"BE",
    "sg:address":"Chauss\u00e9e De La Grande Espinette 71",
    "sg:city":"Rhode-saint-gen\u00e8se",
    "sg:classifiers":[
        {
            "category":"Health Services",
            "subcategory":"Health Practitioner",
            "type":"Services"
        }
    ],
    "sg:phone":"+32 2 358 53 02",
    "sg:postcode":"1640",
    "sg:province":"Vlaams-Brabant",
    "sg:tags":[
        "physiotherapist"
    ],
    "wof:name":"Van Impe Anne-marie",
    "wof:placetype":"venue"
},
  "geometry": {"coordinates":[4.3768649101,50.741733551],"type":"Point"}
}