{
  "type": "Feature",
  "properties": {
    "addr:full":"Chemin Du Paradis 12 Quaregnon Hainaut 7390",
    "addr:housenumber":"12",
    "addr:postcode":"7390",
    "addr:street":"Chemin Du Paradis",
    "iso:country":"BE",
    "sg:address":"Chemin Du Paradis 12",
    "sg:city":"Quaregnon",
    "sg:classifiers":[
        {
            "category":"Health Services",
            "subcategory":"Nursing And Care Facility",
            "type":"Services"
        }
    ],
    "sg:phone":"+32 65 78 27 22",
    "sg:postcode":"7390",
    "sg:province":"Hainaut",
    "sg:tags":[
        "home"
    ],
    "wof:name":"Honor\u00e9 M",
    "wof:placetype":"venue"
},
  "geometry": {"coordinates":[3.8705439568,50.4397888184],"type":"Point"}
}