{
  "type": "Feature",
  "properties": {
    "iso:country":"BE",
    "sg:address":"Ruisstraat 128",
    "sg:city":"Temse",
    "sg:orig_category":"Entretien and r\u00e9parations de voitures",
    "sg:phone":"+32 3 771 22 15",
    "sg:postcode":"9140",
    "sg:province":"Oost-Vlaanderen",
    "wof:name":"Franky Blommaert",
    "wof:placetype":"venue"
},
  "geometry": {"coordinates":[4.1805429459,51.1268348694],"type":"Point"}
}