{
  "type": "Feature",
  "properties": {
    "addr:full":"Passage 44-3 Brussel Bruxelles-Capitale 1000",
    "addr:housenumber":"44-3",
    "addr:postcode":"1000",
    "addr:street":"Passage",
    "iso:country":"BE",
    "sg:address":"Passage 44-3",
    "sg:city":"Brussel",
    "sg:classifiers":[
        {
            "category":"Travel",
            "subcategory":"Travel Agent",
            "type":"Entertainment"
        }
    ],
    "sg:phone":"+32 2 210 00 60",
    "sg:postcode":"1000",
    "sg:province":"Bruxelles-Capitale",
    "sg:tags":[
        "carlson",
        "holiday",
        "plus",
        "wagonlit"
    ],
    "wof:name":"Carlson Wagonlit Travel Brussel",
    "wof:placetype":"venue"
},
  "geometry": {"coordinates":[4.3496851921,50.8483848572],"type":"Point"}
}