{
  "type": "Feature",
  "properties": {
    "addr:full":"Rue Lintermans 8 Seneffe Hainaut 7180",
    "addr:housenumber":"8",
    "addr:postcode":"7180",
    "addr:street":"Rue Lintermans",
    "iso:country":"BE",
    "sg:address":"Rue Lintermans 8",
    "sg:city":"Seneffe",
    "sg:classifiers":[
        {
            "category":"Insurance",
            "subcategory":"Insurance Agent",
            "type":"Services"
        }
    ],
    "sg:phone":"+32 64 55 54 04",
    "sg:postcode":"7180",
    "sg:province":"Hainaut",
    "sg:tags":[
        "broker"
    ],
    "wof:name":"Pinoy Assurfinance",
    "wof:placetype":"venue"
},
  "geometry": {"coordinates":[4.2564930916,50.5299911499],"type":"Point"}
}