{
  "type": "Feature",
  "properties": {
    "iso:country":"BE",
    "sg:address":"De Rentfort 5",
    "sg:city":"Schilde",
    "sg:orig_category":"Experts-comptables",
    "sg:phone":"+32 3 383 04 87",
    "sg:postcode":"2970",
    "sg:province":"Antwerpen",
    "wof:name":"Karel Duchesne",
    "wof:placetype":"venue"
},
  "geometry": {"coordinates":[4.5792360306,51.2282485962],"type":"Point"}
}