{
  "type": "Feature",
  "properties": {
    "addr:full":"P. De Smet De Naeyerpln 13 Gent Oost-Vlaanderen 9000",
    "addr:housenumber":"13",
    "addr:postcode":"9000",
    "addr:street":"P. De Smet De Naeyerpln;Oost-Vlaanderen",
    "iso:country":"BE",
    "sg:address":"P. De Smet De Naeyerpln 13",
    "sg:city":"Gent",
    "sg:orig_category":"M\u00e9decins and sp\u00e9cialistes",
    "sg:phone":"+32 9 222 61 52",
    "sg:postcode":"9000",
    "sg:province":"Oost-Vlaanderen",
    "wof:name":"A. Kint",
    "wof:placetype":"venue"
},
  "geometry": {"coordinates":[3.71854496,51.0322608948],"type":"Point"}
}