{
  "type": "Feature",
  "properties": {
    "iso:country":"BE",
    "sg:address":"Frans Devoghellaan 39",
    "sg:city":"Lennik",
    "sg:orig_category":"Elektrische installaties voor woningen Loodgieterij, verwarming and sanitaire installaties",
    "sg:phone":"+32 2 532 30 43",
    "sg:postcode":"1750",
    "sg:province":"Vlaams-Brabant",
    "wof:name":"Ambitec",
    "wof:placetype":"venue"
},
  "geometry": {"coordinates":[4.1549358368,50.812828064],"type":"Point"}
}