{
  "type": "Feature",
  "properties": {
    "iso:country":"BE",
    "sg:address":"Rue Du Maquis 15",
    "sg:city":"Ronse/renaix",
    "sg:orig_category":"Studios photographiques",
    "sg:phone":"+32 55 21 17 18",
    "sg:postcode":"9600",
    "sg:province":"Oost-Vlaanderen",
    "wof:name":"Studio Kekenbosch D.",
    "wof:placetype":"venue"
},
  "geometry": {"coordinates":[3.5992999077,50.7470397949],"type":"Point"}
}