{
  "type": "Feature",
  "properties": {
    "iso:country":"BE",
    "sg:address":"Itegemsebaan 177",
    "sg:city":"Berlaar (groot)",
    "sg:classifiers":[
        {
            "category":"Personal",
            "subcategory":"Beauty Salon",
            "type":"Services"
        }
    ],
    "sg:phone":"+32 3 480 58 94",
    "sg:postcode":"2590",
    "sg:province":"Antwerpen",
    "sg:tags":[
        "de",
        "coiffure"
    ],
    "wof:name":"Coiffure Hermine",
    "wof:placetype":"venue"
},
  "geometry": {"coordinates":[4.6691460609,51.1111488342],"type":"Point"}
}