{
  "type": "Feature",
  "properties": {
    "addr:full":"Begoniastraat 3 Eke Oost-Vlaanderen 9810",
    "addr:housenumber":"3",
    "addr:postcode":"9810",
    "addr:street":"Begoniastraat",
    "iso:country":"BE",
    "sg:address":"Begoniastraat 3",
    "sg:city":"Eke",
    "sg:orig_category":"Belt Break Control - Equipment And Systems",
    "sg:phone":"+32 2 411 60 35",
    "sg:postcode":"9810",
    "sg:province":"Oost-Vlaanderen",
    "wof:name":"Sgs Bureau Nivelles Asbl/vzw",
    "wof:placetype":"venue"
},
  "geometry": {"coordinates":[4.2907037735,50.8376426697],"type":"Point"}
}