{
  "type": "Feature",
  "properties": {
    "addr:full":"Winston Churchilllaan 206 Ukkel/uccle Bruxelles-Capitale 1180",
    "addr:housenumber":"206",
    "addr:postcode":"1180",
    "addr:street":"Winston Churchilllaan;/",
    "iso:country":"BE",
    "sg:address":"Winston Churchilllaan 206",
    "sg:city":"Ukkel/uccle",
    "sg:orig_category":"Software ontwikkeling and ontwerp",
    "sg:phone":"+32 2 346 44 87",
    "sg:postcode":"1180",
    "sg:province":"Bruxelles-Capitale",
    "wof:name":"A.c.i.s.",
    "wof:placetype":"venue"
},
  "geometry": {"coordinates":[4.3629670143,50.8116531372],"type":"Point"}
}