{
  "type": "Feature",
  "properties": {
    "iso:country":"BE",
    "sg:address":"Steenweg Op Gierle 357",
    "sg:city":"Turnhout",
    "sg:orig_category":"Installatie van metalen schrijnwerk",
    "sg:phone":"+32 14 43 95 97",
    "sg:postcode":"2300",
    "sg:province":"Antwerpen",
    "wof:name":"Robberechts",
    "wof:placetype":"venue"
},
  "geometry": {"coordinates":[4.9188370705,51.3052635193],"type":"Point"}
}