{
  "type": "Feature",
  "properties": {
    "iso:country":"BE",
    "sg:address":"Jan Breydellaan 100",
    "sg:city":"Kortrijk",
    "sg:classifiers":[
        {
            "category":"Professional",
            "subcategory":"Management & Consulting",
            "type":"Services"
        }
    ],
    "sg:phone":"+32 56 21 00 57",
    "sg:postcode":"8500",
    "sg:province":"West-Vlaanderen",
    "sg:tags":[
        "consultant"
    ],
    "wof:name":"Stimulgro Cv",
    "wof:placetype":"venue"
},
  "geometry": {"coordinates":[3.2830839157,50.8298454285],"type":"Point"}
}