{
  "type": "Feature",
  "properties": {
    "addr:full":"Ooststraat 48 Veurne West-Vlaanderen 8630",
    "addr:housenumber":"48",
    "addr:postcode":"8630",
    "addr:street":"Ooststraat",
    "iso:country":"BE",
    "sg:address":"Ooststraat 48",
    "sg:city":"Veurne",
    "sg:classifiers":[
        {
            "category":"Shopping",
            "subcategory":"Clothing, Apparel, & Fashions",
            "type":"Retail Goods"
        }
    ],
    "sg:phone":"+32 58 31 32 77",
    "sg:postcode":"8630",
    "sg:province":"West-Vlaanderen",
    "sg:tags":[
        "underwear",
        "lingerie",
        "-"
    ],
    "wof:name":"Josy",
    "wof:placetype":"venue"
},
  "geometry": {"coordinates":[2.664896965,51.072971344],"type":"Point"}
}