{
  "type": "Feature",
  "properties": {
    "iso:country":"BE",
    "sg:address":"Blandenstraat 92",
    "sg:city":"Oud-heverlee (haasrode)",
    "sg:classifiers":[
        {
            "category":"Parking",
            "subcategory":"Lot",
            "type":"Transportation"
        }
    ],
    "sg:phone":"+32 16 40 83 36",
    "sg:postcode":"3053",
    "sg:province":"Vlaams-Brabant",
    "sg:tags":[
        "parking-places",
        "laying-out"
    ],
    "wof:name":"A.k.k.",
    "wof:placetype":"venue"
},
  "geometry": {"coordinates":[4.7289299965,50.8345909119],"type":"Point"}
}