{
  "type": "Feature",
  "properties": {
    "addr:full":"'t Vaartje 21 Knokke-heist West-Vlaanderen 8300",
    "addr:housenumber":"21",
    "addr:postcode":"8300",
    "addr:street":"' T Vaartje",
    "iso:country":"BE",
    "sg:address":"'t Vaartje 21",
    "sg:city":"Knokke-heist",
    "sg:orig_category":"Travaux de finition and nettoyage de b\u00e2timents",
    "sg:phone":"+32 50 62 19 49",
    "sg:postcode":"8300",
    "sg:province":"West-Vlaanderen",
    "wof:name":"Asuhyp",
    "wof:placetype":"venue"
},
  "geometry": {"coordinates":[3.2938389778,51.335357666],"type":"Point"}
}