{
  "type": "Feature",
  "properties": {
    "addr:full":"Larumsebrugweg 193 Geel Antwerpen 2440",
    "addr:housenumber":"193",
    "addr:postcode":"2440",
    "addr:street":"Larumsebrugweg",
    "iso:country":"BE",
    "sg:address":"Larumsebrugweg 193",
    "sg:city":"Geel",
    "sg:orig_category":"Installation de menuiserie en bois and plastique",
    "sg:phone":"+32 14 58 47 77",
    "sg:postcode":"2440",
    "sg:province":"Antwerpen",
    "wof:name":"Ferdinand Swinnen",
    "wof:placetype":"venue"
},
  "geometry": {"coordinates":[4.9355521202,51.1840896606],"type":"Point"}
}