{
  "type": "Feature",
  "properties": {
    "iso:country":"BE",
    "sg:address":"Bd Jules Graindor 41-43",
    "sg:city":"Bruxelles",
    "sg:classifiers":[
        {
            "category":"Food & Beverages",
            "subcategory":"Groceries & Convenience Stores",
            "type":"Retail Goods"
        }
    ],
    "sg:phone":"+32 2 522 19 57",
    "sg:postcode":"1070",
    "sg:province":"Bruxelles-Capitale",
    "sg:tags":[
        "product",
        "related"
    ],
    "wof:name":"Confiserie Leonidas Sa",
    "wof:placetype":"venue"
},
  "geometry": {"coordinates":[4.31686306,50.8443870544],"type":"Point"}
}