{
  "type": "Feature",
  "properties": {
    "iso:country":"BE",
    "sg:address":"Rue Boverie 11",
    "sg:city":"Verviers",
    "sg:orig_category":"Rundveehouders Woningbouw",
    "sg:phone":"+32 87 22 19 72",
    "sg:postcode":"4800",
    "sg:province":"Li\u00e8ge",
    "wof:name":"Rene Foguenne",
    "wof:placetype":"venue"
},
  "geometry": {"coordinates":[5.8958768845,50.56016922],"type":"Point"}
}