{
  "type": "Feature",
  "properties": {
    "iso:country":"BE",
    "sg:address":"Rue Chavannes 38",
    "sg:city":"Charleroi",
    "sg:classifiers":[
        {
            "category":"Bars & Pubs",
            "type":"Food & Drink"
        }
    ],
    "sg:phone":"+32 71 32 09 20",
    "sg:postcode":"6000",
    "sg:province":"Hainaut",
    "wof:name":"Mac\u00e9doine",
    "wof:placetype":"venue"
},
  "geometry": {"coordinates":[4.4453129768,50.414390564],"type":"Point"}
}