{
  "type": "Feature",
  "properties": {
    "addr:full":"Diestsebaan 41 Diest Vlaams-Brabant 3290",
    "addr:housenumber":"41",
    "addr:postcode":"3290",
    "addr:street":"Diestsebaan",
    "iso:country":"BE",
    "sg:address":"Diestsebaan 41",
    "sg:city":"Diest",
    "sg:orig_category":"Banken and kredietinstellingen",
    "sg:phone":"+32 13 33 32 39",
    "sg:postcode":"3290",
    "sg:province":"Vlaams-Brabant",
    "wof:name":"Kbc",
    "wof:placetype":"venue"
},
  "geometry": {"coordinates":[5.0793738365,50.998374939],"type":"Point"}
}