{
  "type": "Feature",
  "properties": {
    "addr:full":"R Du Moulin 27 St-denis-bovesse Namur 5081",
    "addr:housenumber":"27",
    "addr:postcode":"5081",
    "addr:street":"R Du Moulin;Namur",
    "iso:country":"BE",
    "sg:address":"R Du Moulin 27",
    "sg:city":"St-denis-bovesse",
    "sg:classifiers":[
        {
            "category":"Building & Trades",
            "subcategory":"Construction",
            "type":"Services"
        }
    ],
    "sg:phone":"+32 81 56 06 96",
    "sg:postcode":"5081",
    "sg:province":"Namur",
    "sg:tags":[
        "carpenter"
    ],
    "wof:name":"Challes P",
    "wof:placetype":"venue"
},
  "geometry": {"coordinates":[4.7813000679,50.5242195129],"type":"Point"}
}