{
  "type": "Feature",
  "properties": {
    "addr:full":"Liersesteenweg 67 Aarschot Vlaams-Brabant 3200",
    "addr:housenumber":"67",
    "addr:postcode":"3200",
    "addr:street":"Liersesteenweg",
    "iso:country":"BE",
    "sg:address":"Liersesteenweg 67",
    "sg:city":"Aarschot",
    "sg:classifiers":[
        {
            "category":"Shopping",
            "subcategory":"Discount & Variety Stores",
            "type":"Retail Goods"
        }
    ],
    "sg:phone":"+32 16 56 08 09",
    "sg:postcode":"3200",
    "sg:province":"Vlaams-Brabant",
    "sg:tags":[
        "shop",
        "clearers",
        "curiosity",
        "furniture"
    ],
    "wof:name":"Verbinnen Tweedehandswinkel",
    "wof:placetype":"venue"
},
  "geometry": {"coordinates":[4.8289937973,51.0015830994],"type":"Point"}
}