{
  "type": "Feature",
  "properties": {
    "iso:country":"BE",
    "sg:address":"Place Saint-denis 46",
    "sg:city":"Huy",
    "sg:orig_category":"Diverse grafische activiteiten",
    "sg:phone":"+32 85 25 00 60",
    "sg:postcode":"4500",
    "sg:province":"Li\u00e8ge",
    "wof:name":"Bureau Nuit Blanches",
    "wof:placetype":"venue"
},
  "geometry": {"coordinates":[5.2465701103,50.5187149048],"type":"Point"}
}