{
  "type": "Feature",
  "properties": {
    "addr:full":"Damburgstraat 8 Bocholt Limburg 3950",
    "addr:housenumber":"8",
    "addr:postcode":"3950",
    "addr:street":"Damburgstraat",
    "iso:country":"BE",
    "sg:address":"Damburgstraat 8",
    "sg:city":"Bocholt",
    "sg:classifiers":[
        {
            "category":"Arena",
            "subcategory":"Sports Club",
            "type":"Entertainment"
        }
    ],
    "sg:phone":"+32 89 47 22 00",
    "sg:postcode":"3950",
    "sg:province":"Limburg",
    "sg:tags":[
        "de"
    ],
    "wof:name":"V.c. Meubelcentr. Heylen",
    "wof:placetype":"venue"
},
  "geometry": {"coordinates":[5.5693278313,51.1725959778],"type":"Point"}
}