{
  "type": "Feature",
  "properties": {
    "iso:country":"BE",
    "sg:address":"Graystraat 167",
    "sg:city":"Elsene/ixelles",
    "sg:orig_category":"Fotografen and fotostudio's",
    "sg:phone":"+32 2 640 79 35",
    "sg:postcode":"1050",
    "sg:province":"Bruxelles-Capitale",
    "wof:name":"Frank Uyttenhove",
    "wof:placetype":"venue"
},
  "geometry": {"coordinates":[4.3764882088,50.8307342529],"type":"Point"}
}