{
  "type": "Feature",
  "properties": {
    "iso:country":"BE",
    "sg:address":"Grand Route 166",
    "sg:city":"Tournai (gaurain-ramecroix)",
    "sg:classifiers":[
        {
            "category":"Professional",
            "subcategory":"Art Services",
            "type":"Services"
        }
    ],
    "sg:phone":"+32 69 54 70 99",
    "sg:postcode":"7530",
    "sg:province":"Hainaut",
    "sg:tags":[
        "photographer"
    ],
    "wof:name":"Marie De Lenoil",
    "wof:placetype":"venue"
},
  "geometry": {"coordinates":[3.4670460224,50.5967559814],"type":"Point"}
}