{
  "type": "Feature",
  "properties": {
    "addr:full":"Rue D'yves Gomez\u00e9e 67 Florennes (saint-aubin) Namur 5620",
    "addr:housenumber":"67",
    "addr:postcode":"5620",
    "addr:street":"Rue D'Yves Gomeze\u0301E",
    "iso:country":"BE",
    "sg:address":"Rue D'yves Gomez\u00e9e 67",
    "sg:city":"Florennes (saint-aubin)",
    "sg:classifiers":[
        {
            "category":"Farming",
            "subcategory":"Fish & Marine Products",
            "type":"Manufacturing & Wholesale Goods"
        }
    ],
    "sg:phone":"+32 71 68 73 49",
    "sg:postcode":"5620",
    "sg:province":"Namur",
    "sg:tags":[
        "equipment",
        "fishery"
    ],
    "wof:name":"Etangs De La Vall\u00e9e Des Pr\u00e9s",
    "wof:placetype":"venue"
},
  "geometry": {"coordinates":[4.5523629189,50.2462387085],"type":"Point"}
}