{
  "type": "Feature",
  "properties": {
    "iso:country":"BE",
    "sg:address":"Rue Du Moulin 36",
    "sg:city":"Chatelet",
    "sg:orig_category":"Herstellingen and onderhoud van auto's",
    "sg:phone":"+32 71 38 05 95",
    "sg:postcode":"6200",
    "sg:province":"Hainaut",
    "wof:name":"Garage Dehan",
    "wof:placetype":"venue"
},
  "geometry": {"coordinates":[4.5166301727,50.4016647339],"type":"Point"}
}