{
  "type": "Feature",
  "properties": {
    "iso:country":"BE",
    "sg:address":"Rue Vanderstichelen 23",
    "sg:city":"Bruxelles (molenbeek-saint-jean)",
    "sg:classifiers":[
        {
            "category":"Retail",
            "subcategory":"Auto Rental",
            "type":"Services"
        }
    ],
    "sg:phone":"+32 2 427 86 89",
    "sg:postcode":"1080",
    "sg:province":"Bruxelles-Capitale",
    "sg:tags":[
        "term",
        "van",
        "cars",
        "-",
        "long",
        "delivery",
        "truck"
    ],
    "wof:name":"Ribcar",
    "wof:placetype":"venue"
},
  "geometry": {"coordinates":[4.3418898582,50.8619003296],"type":"Point"}
}