{
  "type": "Feature",
  "properties": {
    "addr:full":"Steenweg Naar As 14 Maasmechelen Limburg 3630",
    "addr:housenumber":"14",
    "addr:postcode":"3630",
    "addr:street":"Steenweg Naar As",
    "iso:country":"BE",
    "sg:address":"Steenweg Naar As 14",
    "sg:city":"Maasmechelen",
    "sg:orig_category":"Benzinestations and brandstoffen",
    "sg:phone":"+32 89 65 81 23",
    "sg:postcode":"3630",
    "sg:province":"Limburg",
    "wof:name":"Texaco",
    "wof:placetype":"venue"
},
  "geometry": {"coordinates":[5.6238160133,50.9922485352],"type":"Point"}
}