{
  "type": "Feature",
  "properties": {
    "addr:full":"Legeweg 299 Brugge West-Vlaanderen 8200",
    "addr:housenumber":"299",
    "addr:postcode":"8200",
    "addr:street":"Legeweg",
    "iso:country":"BE",
    "sg:address":"Legeweg 299",
    "sg:city":"Brugge",
    "sg:orig_category":"Transports routiers de marchandises",
    "sg:phone":"+32 50 31 55 27",
    "sg:postcode":"8200",
    "sg:province":"West-Vlaanderen",
    "wof:name":"Transport Quicke",
    "wof:placetype":"venue"
},
  "geometry": {"coordinates":[3.1957600117,51.2053184509],"type":"Point"}
}