{
  "type": "Feature",
  "properties": {
    "addr:full":"Rue Saint-laurent 47 Li\u00c8ge Li\u00e8ge 4000",
    "addr:housenumber":"47",
    "addr:postcode":"4000",
    "addr:street":"Rue Saint-Laurent",
    "iso:country":"BE",
    "sg:address":"Rue Saint-laurent 47",
    "sg:city":"Li\u00c8ge",
    "sg:orig_category":"Diverse opleidingen and onderwijs",
    "sg:phone":"+32 4 221 30 25",
    "sg:postcode":"4000",
    "sg:province":"Li\u00e8ge",
    "wof:name":"Microprof",
    "wof:placetype":"venue"
},
  "geometry": {"coordinates":[5.5606489182,50.6430931091],"type":"Point"}
}