{
  "type": "Feature",
  "properties": {
    "addr:full":"Stationstraat 49 Moeskroen/mouscron Hainaut 7700",
    "addr:housenumber":"49",
    "addr:postcode":"7700",
    "addr:street":"Stationstraat",
    "iso:country":"BE",
    "sg:address":"Stationstraat 49",
    "sg:city":"Moeskroen/mouscron",
    "sg:orig_category":"Verplichte sociale verzekeringen",
    "sg:phone":"+32 56 33 61 14",
    "sg:postcode":"7700",
    "sg:province":"Hainaut",
    "wof:name":"Mutualit\u00c9 Libre",
    "wof:placetype":"venue"
},
  "geometry": {"coordinates":[3.2323200703,50.7400932312],"type":"Point"}
}