{
  "type": "Feature",
  "properties": {
    "addr:full":"Sint-alfonsusstraat 11 Roeselare West-Vlaanderen 8800",
    "addr:housenumber":"11",
    "addr:postcode":"8800",
    "addr:street":"Sint-Alfonsusstraat",
    "iso:country":"BE",
    "sg:address":"Sint-alfonsusstraat 11",
    "sg:city":"Roeselare",
    "sg:classifiers":[
        {
            "category":"Shopping",
            "subcategory":"Clothing, Apparel, & Fashions",
            "type":"Retail Goods"
        }
    ],
    "sg:phone":"+32 51 22 22 23",
    "sg:postcode":"8800",
    "sg:province":"West-Vlaanderen",
    "sg:tags":[
        "v\u00eatements",
        "pour",
        "dame"
    ],
    "wof:name":"Area",
    "wof:placetype":"venue"
},
  "geometry": {"coordinates":[3.127532959,50.9456863403],"type":"Point"}
}