{
  "type": "Feature",
  "properties": {
    "iso:country":"BE",
    "sg:address":"Pedro Colomalaan 2",
    "sg:city":"Bornem",
    "sg:orig_category":"Imprimeries and copyshops",
    "sg:phone":"+32 3 889 44 05",
    "sg:postcode":"2880",
    "sg:province":"Antwerpen",
    "wof:name":"Hollywood",
    "wof:placetype":"venue"
},
  "geometry": {"coordinates":[4.2508301735,51.0916824341],"type":"Point"}
}