{
  "type": "Feature",
  "properties": {
    "iso:country":"BE",
    "sg:address":"Europastraat 13",
    "sg:city":"Heusden-zolder",
    "sg:orig_category":"Epiceries",
    "sg:phone":"+32 11 57 32 49",
    "sg:postcode":"3550",
    "sg:province":"Limburg",
    "wof:name":"Aquino And Company",
    "wof:placetype":"venue"
},
  "geometry": {"coordinates":[5.3186998367,51.0498771667],"type":"Point"}
}