{
  "type": "Feature",
  "properties": {
    "addr:full":"Rue Haute 54 Weismes/waimes Li\u00e8ge 4950",
    "addr:housenumber":"54",
    "addr:postcode":"4950",
    "addr:street":"Rue Haute",
    "iso:country":"BE",
    "sg:address":"Rue Haute 54",
    "sg:city":"Weismes/waimes",
    "sg:orig_category":"Dakwerken",
    "sg:phone":"+32 80 44 48 40",
    "sg:postcode":"4950",
    "sg:province":"Li\u00e8ge",
    "wof:name":"Langer Willy",
    "wof:placetype":"venue"
},
  "geometry": {"coordinates":[6.1150212288,50.4829444885],"type":"Point"}
}