{
  "type": "Feature",
  "properties": {
    "addr:full":"Vissersstraat 69 Damme West-Vlaanderen 8340",
    "addr:housenumber":"69",
    "addr:postcode":"8340",
    "addr:street":"Vissersstraat",
    "iso:country":"BE",
    "sg:address":"Vissersstraat 69",
    "sg:city":"Damme",
    "sg:orig_category":"Rev\u00eatements pour sols and murs. Peinture",
    "sg:phone":"+32 50 50 02 72",
    "sg:postcode":"8340",
    "sg:province":"West-Vlaanderen",
    "wof:name":"Hugo Van Meenen",
    "wof:placetype":"venue"
},
  "geometry": {"coordinates":[3.2815999985,51.2513160706],"type":"Point"}
}