{
  "type": "Feature",
  "properties": {
    "addr:full":"Jagersdreef 31 Kapellen (mariaburg) Antwerpen 2950",
    "addr:housenumber":"31",
    "addr:postcode":"2950",
    "addr:street":"Jagersdreef",
    "iso:country":"BE",
    "sg:address":"Jagersdreef 31",
    "sg:city":"Kapellen (mariaburg)",
    "sg:classifiers":[
        {
            "category":"Real Estate",
            "subcategory":"Developer",
            "type":"Services"
        }
    ],
    "sg:phone":"+32 3 605 91 95",
    "sg:postcode":"2950",
    "sg:province":"Antwerpen",
    "sg:tags":[
        "project"
    ],
    "wof:name":"Proverma",
    "wof:placetype":"venue"
},
  "geometry": {"coordinates":[4.4524011612,51.3035888672],"type":"Point"}
}