{
  "type": "Feature",
  "properties": {
    "addr:full":"Heilekamp 7 Maaseik Limburg 3680",
    "addr:housenumber":"7",
    "addr:postcode":"3680",
    "addr:street":"Heilekamp",
    "iso:country":"BE",
    "sg:address":"Heilekamp 7",
    "sg:city":"Maaseik",
    "sg:orig_category":"Installatie van houten of kunststof schrijnwerk",
    "sg:phone":"+32 89 57 20 83",
    "sg:postcode":"3680",
    "sg:province":"Limburg",
    "wof:name":"Wim Vankevelaer",
    "wof:placetype":"venue"
},
  "geometry": {"coordinates":[5.7990112305,51.0982627869],"type":"Point"}
}