{
  "type": "Feature",
  "properties": {
    "iso:country":"BE",
    "sg:address":"Grote Steenweg 177",
    "sg:city":"Linter (drieslinter)",
    "sg:classifiers":[
        {
            "category":"Home & Garden",
            "subcategory":"Kitchen Supply",
            "type":"Retail Goods"
        }
    ],
    "sg:phone":"+32 11 78 29 66",
    "sg:postcode":"3350",
    "sg:province":"Vlaams-Brabant",
    "sg:tags":[
        "installation"
    ],
    "wof:name":"Van Meerssche E",
    "wof:placetype":"venue"
},
  "geometry": {"coordinates":[5.0377869606,50.8416976929],"type":"Point"}
}