{
  "type": "Feature",
  "properties": {
    "iso:country":"BE",
    "sg:address":"Route Charlemagne 55ba",
    "sg:city":"Welkenraedt",
    "sg:orig_category":"M\u00e9decins and sp\u00e9cialistes",
    "sg:phone":"+32 87 89 01 98",
    "sg:postcode":"4841",
    "sg:province":"Li\u00e8ge",
    "wof:name":"G. Vondegracht",
    "wof:placetype":"venue"
},
  "geometry": {"coordinates":[5.9391531944,50.6800575256],"type":"Point"}
}