{
  "type": "Feature",
  "properties": {
    "addr:full":"Sint-niklaasstraat 37 Herne Vlaams-Brabant 1540",
    "addr:housenumber":"37",
    "addr:postcode":"1540",
    "addr:street":"Sint-Niklaasstraat",
    "iso:country":"BE",
    "sg:address":"Sint-niklaasstraat 37",
    "sg:city":"Herne",
    "sg:orig_category":"Banques and organismes de cr\u00e9dit",
    "sg:phone":"+32 54 56 64 19",
    "sg:postcode":"1540",
    "sg:province":"Vlaams-Brabant",
    "wof:name":"Landbouwkrediet",
    "wof:placetype":"venue"
},
  "geometry": {"coordinates":[4.0968317986,50.7484016418],"type":"Point"}
}