{
  "type": "Feature",
  "properties": {
    "addr:full":"Putsebaan 217 Keerbergen Vlaams-Brabant 3140",
    "addr:housenumber":"217",
    "addr:postcode":"3140",
    "addr:street":"Putsebaan",
    "iso:country":"BE",
    "sg:address":"Putsebaan 217",
    "sg:city":"Keerbergen",
    "sg:classifiers":[
        {
            "category":"Bars & Pubs",
            "type":"Food & Drink"
        }
    ],
    "sg:phone":"+32 15 23 49 74",
    "sg:postcode":"3140",
    "sg:province":"Vlaams-Brabant",
    "wof:name":"Klein Kontich",
    "wof:placetype":"venue"
},
  "geometry": {"coordinates":[4.6494550705,51.0121879578],"type":"Point"}
}