{
  "type": "Feature",
  "properties": {
    "addr:full":"Rue Josaphat 239 Bruxelles (schaerbeek) Bruxelles-Capitale 1030",
    "addr:housenumber":"239",
    "addr:postcode":"1030",
    "addr:street":"Rue Josaphat",
    "iso:country":"BE",
    "sg:address":"Rue Josaphat 239",
    "sg:city":"Bruxelles (schaerbeek)",
    "sg:classifiers":[
        {
            "category":"Personal",
            "subcategory":"Barber",
            "type":"Services"
        }
    ],
    "sg:phone":"+32 2 241 54 20",
    "sg:postcode":"1030",
    "sg:province":"Bruxelles-Capitale",
    "sg:tags":[
        "gentleman",
        "salon",
        "-",
        "hairdressing"
    ],
    "wof:name":"Jawamin",
    "wof:placetype":"venue"
},
  "geometry": {"coordinates":[4.3759789467,50.8625183105],"type":"Point"}
}