{
  "type": "Feature",
  "properties": {
    "iso:country":"BE",
    "sg:address":"Westlaan 73",
    "sg:city":"Roeselare",
    "sg:orig_category":"R\u00e9parations de chaussures and articles en cuir",
    "sg:phone":"+32 51 22 92 28",
    "sg:postcode":"8800",
    "sg:province":"West-Vlaanderen",
    "wof:name":"Huis Marc",
    "wof:placetype":"venue"
},
  "geometry": {"coordinates":[3.1180689335,50.937789917],"type":"Point"}
}