{
  "type": "Feature",
  "properties": {
    "addr:full":"Chauss\u00c9e De Wavre 1792 Oudergem/auderghem Bruxelles-Capitale 1160",
    "addr:postcode":"1792;1160",
    "addr:street":"Chausse\u0301E De Wavre",
    "iso:country":"BE",
    "sg:address":"Chauss\u00c9e De Wavre 1792",
    "sg:city":"Oudergem/auderghem",
    "sg:orig_category":"Blanchisseries and teintureries",
    "sg:phone":"+32 2 672 40 38",
    "sg:postcode":"1160",
    "sg:province":"Bruxelles-Capitale",
    "wof:name":"Nettoyage \u00c0 Sec Willems",
    "wof:placetype":"venue"
},
  "geometry": {"coordinates":[4.4332051277,50.8148345947],"type":"Point"}
}