{
  "type": "Feature",
  "properties": {
    "iso:country":"BE",
    "sg:address":"Avenue Du G\u00c9n\u00c9ral-patton 323",
    "sg:city":"Arlon",
    "sg:orig_category":"D\u00e9chets and d\u00e9bris Gr",
    "sg:phone":"+32 63 22 45 60",
    "sg:postcode":"6700",
    "sg:province":"Luxembourg",
    "wof:name":"Fe. Hoffman",
    "wof:placetype":"venue"
},
  "geometry": {"coordinates":[5.8218421936,49.6706695557],"type":"Point"}
}