{
  "type": "Feature",
  "properties": {
    "addr:full":"Quai De L'ecluse 31b Andenne Namur 5300",
    "addr:housenumber":"31b",
    "addr:postcode":"5300",
    "addr:street":"Quai De L'Ecluse",
    "iso:country":"BE",
    "sg:address":"Quai De L'ecluse 31b",
    "sg:city":"Andenne",
    "sg:classifiers":[
        {
            "category":"Personal",
            "subcategory":"Beauty Salon",
            "type":"Services"
        }
    ],
    "sg:phone":"+32 85 84 63 75",
    "sg:postcode":"5300",
    "sg:province":"Namur",
    "sg:tags":[
        "lady",
        "-",
        "hairdressing"
    ],
    "wof:name":"Demeure V",
    "wof:placetype":"venue"
},
  "geometry": {"coordinates":[5.1156229973,50.4972991943],"type":"Point"}
}