{
  "type": "Feature",
  "properties": {
    "addr:full":"Avenue Albert I 51 Namur Namur 5000",
    "addr:housenumber":"51",
    "addr:postcode":"5000",
    "addr:street":"Avenue Albert I",
    "iso:country":"BE",
    "sg:address":"Avenue Albert I 51",
    "sg:city":"Namur",
    "sg:classifiers":[
        {
            "category":"Personal",
            "subcategory":"Beauty Salon",
            "type":"Services"
        }
    ],
    "sg:phone":"+32 81 22 25 17",
    "sg:postcode":"5000",
    "sg:province":"Namur",
    "sg:tags":[
        "lady",
        "-",
        "hairdressing"
    ],
    "wof:name":"Philippe Coiffe",
    "wof:placetype":"venue"
},
  "geometry": {"coordinates":[4.8805470467,50.4664230347],"type":"Point"}
}