{
  "type": "Feature",
  "properties": {
    "iso:country":"BE",
    "sg:address":"Geluwestraat 45",
    "sg:city":"Zonnebeke (beselare)",
    "sg:classifiers":[
        {
            "category":"Manufacturing",
            "subcategory":"Wood Products",
            "type":"Manufacturing & Wholesale Goods"
        }
    ],
    "sg:phone":"+32 57 46 91 19",
    "sg:postcode":"8980",
    "sg:province":"West-Vlaanderen",
    "sg:tags":[
        "firewood"
    ],
    "wof:name":"Bruggeman Pedro",
    "wof:placetype":"venue"
},
  "geometry": {"coordinates":[3.0355529785,50.8421630859],"type":"Point"}
}