{
  "type": "Feature",
  "properties": {
    "addr:full":"Chemin D'impegnies 26 Ath Hainaut 7811",
    "addr:housenumber":"26",
    "addr:postcode":"7811",
    "addr:street":"Chemin D'Impegnies",
    "iso:country":"BE",
    "sg:address":"Chemin D'impegnies 26",
    "sg:city":"Ath",
    "sg:orig_category":"Eleveurs de bovins",
    "sg:phone":"+32 68 28 16 78",
    "sg:postcode":"7811",
    "sg:province":"Hainaut",
    "wof:name":"Guilmot",
    "wof:placetype":"venue"
},
  "geometry": {"coordinates":[3.8258869648,50.6199531555],"type":"Point"}
}