{
  "type": "Feature",
  "properties": {
    "iso:country":"BE",
    "sg:address":"Chemin Des Ecureuils 14",
    "sg:city":"Profondeville",
    "sg:classifiers":[
        {
            "category":"Education",
            "subcategory":"School",
            "type":"Public Place"
        }
    ],
    "sg:phone":"+32 81 22 46 00",
    "sg:postcode":"5170",
    "sg:province":"Namur",
    "sg:tags":[
        "-",
        "private"
    ],
    "wof:name":"Cedac Namur",
    "wof:placetype":"venue"
},
  "geometry": {"coordinates":[4.8610539436,50.3714904785],"type":"Point"}
}