{
  "type": "Feature",
  "properties": {
    "addr:full":"Sint-truidersteenweg 51 Herk-de-stad Limburg 3540",
    "addr:housenumber":"51",
    "addr:postcode":"3540",
    "addr:street":"Sint-Truidersteenweg",
    "iso:country":"BE",
    "sg:address":"Sint-truidersteenweg 51",
    "sg:city":"Herk-de-stad",
    "sg:orig_category":"Boekhouders",
    "sg:phone":"+32 13 55 19 73",
    "sg:postcode":"3540",
    "sg:province":"Limburg",
    "wof:name":"Luc Knaepen",
    "wof:placetype":"venue"
},
  "geometry": {"coordinates":[5.1703472137,50.9306793213],"type":"Point"}
}