{
  "type": "Feature",
  "properties": {
    "iso:country":"BE",
    "sg:address":"Rue Pr\u00e9s Champs 25b",
    "sg:city":"Bl\u00e9gny (barchon)",
    "sg:classifiers":[
        {
            "category":"Professional",
            "subcategory":"Computer Services",
            "type":"Services"
        }
    ],
    "sg:phone":"+32 4 387 93 93",
    "sg:postcode":"4671",
    "sg:province":"Li\u00e8ge",
    "sg:tags":[
        "-",
        "processing",
        "data",
        "software"
    ],
    "wof:name":"Sysmex Molis Sa",
    "wof:placetype":"venue"
},
  "geometry": {"coordinates":[5.6896700859,50.6630592346],"type":"Point"}
}