{
  "type": "Feature",
  "properties": {
    "iso:country":"BE",
    "sg:address":"Square De La Libert\u00c9 3",
    "sg:city":"Braine-le-comte",
    "sg:orig_category":"Boekhouders",
    "sg:phone":"+32 67 55 38 65",
    "sg:postcode":"7090",
    "sg:province":"Hainaut",
    "wof:name":"Robert Sartiaux",
    "wof:placetype":"venue"
},
  "geometry": {"coordinates":[4.1478328705,50.6073951721],"type":"Point"}
}