{
  "type": "Feature",
  "properties": {
    "iso:country":"BE",
    "sg:address":"Hoevestraat 3",
    "sg:city":"Heist-op-den-berg",
    "sg:orig_category":"Producteurs de l\u00e9gumes. Eleveurs de bovins",
    "sg:phone":"+32 15 73 05 63",
    "sg:postcode":"2220",
    "sg:province":"Antwerpen",
    "wof:name":"Joris Claes",
    "wof:placetype":"venue"
},
  "geometry": {"coordinates":[4.7297391891,51.0336112976],"type":"Point"}
}