{
  "type": "Feature",
  "properties": {
    "addr:full":"Rue D\u00b4erez\u00c9e 1 Manhay Luxembourg 6960",
    "addr:housenumber":"1",
    "addr:postcode":"6960",
    "addr:street":"Rue D\u00b4Ereze\u0301E",
    "iso:country":"BE",
    "sg:address":"Rue D\u00b4erez\u00c9e 1",
    "sg:city":"Manhay",
    "sg:orig_category":"Services fun\u00e9raires",
    "sg:phone":"+32 86 45 61 31",
    "sg:postcode":"6960",
    "sg:province":"Luxembourg",
    "wof:name":"Rochoises",
    "wof:placetype":"venue"
},
  "geometry": {"coordinates":[5.6745929718,50.2923851013],"type":"Point"}
}