{
  "type": "Feature",
  "properties": {
    "addr:full":"Nieuwpoortsesteenweg 23 Oostende West-Vlaanderen 8400",
    "addr:housenumber":"23",
    "addr:postcode":"8400",
    "addr:street":"Nieuwpoortsesteenweg",
    "iso:country":"BE",
    "sg:address":"Nieuwpoortsesteenweg 23",
    "sg:city":"Oostende",
    "sg:classifiers":[
        {
            "category":"Home & Garden",
            "subcategory":"Household Appliances",
            "type":"Retail Goods"
        }
    ],
    "sg:phone":"+32 59 70 13 98",
    "sg:postcode":"8400",
    "sg:province":"West-Vlaanderen",
    "sg:tags":[
        "repair",
        "mainten",
        "-",
        "electric"
    ],
    "wof:name":"Delanghe Nv",
    "wof:placetype":"venue"
},
  "geometry": {"coordinates":[2.9074249268,51.2237472534],"type":"Point"}
}