{
  "type": "Feature",
  "properties": {
    "iso:country":"BE",
    "sg:address":"Aumalestraat 110",
    "sg:city":"Anderlecht/anderlecht",
    "sg:orig_category":"Brood, gebak and snoepgoed",
    "sg:phone":"+32 2 521 66 30",
    "sg:postcode":"1070",
    "sg:province":"Bruxelles-Capitale",
    "wof:name":"Boulangerie Monsif",
    "wof:placetype":"venue"
},
  "geometry": {"coordinates":[4.3109512329,50.8389472961],"type":"Point"}
}