{
  "type": "Feature",
  "properties": {
    "iso:country":"BE",
    "sg:address":"Driftweg 9",
    "sg:city":"De Haan",
    "sg:classifiers":[
        {
            "category":"Insurance",
            "subcategory":"Insurance Agent",
            "type":"Services"
        }
    ],
    "sg:phone":"+32 59 23 61 61",
    "sg:postcode":"8420",
    "sg:province":"West-Vlaanderen",
    "sg:tags":[
        "verzekeringsmakelaars",
        "expert"
    ],
    "wof:name":"K. Joye",
    "wof:placetype":"venue"
},
  "geometry": {"coordinates":[3.0329070091,51.272026062],"type":"Point"}
}