{
  "type": "Feature",
  "properties": {
    "addr:full":"Zeelaan 65 Koksijde West-Vlaanderen 8670",
    "addr:housenumber":"65",
    "addr:postcode":"8670",
    "addr:street":"Zeelaan",
    "iso:country":"BE",
    "sg:address":"Zeelaan 65",
    "sg:city":"Koksijde",
    "sg:orig_category":"Pain, p\u00e2tisseries and confiseries",
    "sg:phone":"+32 58 51 58 79",
    "sg:postcode":"8670",
    "sg:province":"West-Vlaanderen",
    "wof:name":"Bakkerij Helvetia",
    "wof:placetype":"venue"
},
  "geometry": {"coordinates":[2.6484460831,51.1066513062],"type":"Point"}
}