{
  "type": "Feature",
  "properties": {
    "iso:country":"BE",
    "sg:address":"Spechtendrijf 24",
    "sg:city":"Zoersel",
    "sg:orig_category":"Diverse bedrijfsbeheeradviesbureaus",
    "sg:phone":"+32 3 384 30 04",
    "sg:postcode":"2980",
    "sg:province":"Antwerpen",
    "wof:name":"Retema",
    "wof:placetype":"venue"
},
  "geometry": {"coordinates":[4.713435173,51.269985199],"type":"Point"}
}