{
  "type": "Feature",
  "properties": {
    "addr:full":"Rue De Matignolle 5 Doische Namur 5680",
    "addr:housenumber":"5",
    "addr:postcode":"5680",
    "addr:street":"Rue De Matignolle",
    "iso:country":"BE",
    "sg:address":"Rue De Matignolle 5",
    "sg:city":"Doische",
    "sg:orig_category":"Herstellingen and onderhoud van auto's",
    "sg:phone":"+32 60 39 03 94",
    "sg:postcode":"5680",
    "sg:province":"Namur",
    "wof:name":"Garage Hayot",
    "wof:placetype":"venue"
},
  "geometry": {"coordinates":[4.6492199898,50.1127662659],"type":"Point"}
}