{
  "type": "Feature",
  "properties": {
    "iso:country":"BE",
    "sg:address":"La Hailleule 2",
    "sg:city":"Chiny",
    "sg:orig_category":"Hout and afgeleiden Gh IJzerwaren, bouw- and verfmaterialen",
    "sg:phone":"+32 61 32 95 26",
    "sg:postcode":"6810",
    "sg:province":"Luxembourg",
    "wof:name":"Fe. Genin F. & Ph.",
    "wof:placetype":"venue"
},
  "geometry": {"coordinates":[5.3405580521,49.7382736206],"type":"Point"}
}