{
  "type": "Feature",
  "properties": {
    "addr:full":"Beverestraat 54 Oudenaarde Oost-Vlaanderen 9700",
    "addr:housenumber":"54",
    "addr:postcode":"9700",
    "addr:street":"Beverestraat",
    "iso:country":"BE",
    "sg:address":"Beverestraat 54",
    "sg:city":"Oudenaarde",
    "sg:orig_category":"Slagers",
    "sg:phone":"+32 55 31 26 84",
    "sg:postcode":"9700",
    "sg:province":"Oost-Vlaanderen",
    "wof:name":"Beenhouwerij Frans",
    "wof:placetype":"venue"
},
  "geometry": {"coordinates":[3.5989239216,50.8489990234],"type":"Point"}
}