{
  "type": "Feature",
  "properties": {
    "addr:full":"Plantin En Moretuslei 97 Antwerpen Antwerpen 2018",
    "addr:housenumber":"97",
    "addr:postcode":"2018",
    "addr:street":"Plantin En Moretuslei",
    "iso:country":"BE",
    "sg:address":"Plantin En Moretuslei 97",
    "sg:city":"Antwerpen",
    "sg:classifiers":[
        {
            "category":"Personal",
            "subcategory":"Beauty Salon",
            "type":"Services"
        }
    ],
    "sg:phone":"+32 3 233 36 00",
    "sg:postcode":"2018",
    "sg:province":"Antwerpen",
    "sg:tags":[
        "de",
        "coiffure"
    ],
    "wof:name":"Jules Oomen",
    "wof:placetype":"venue"
},
  "geometry": {"coordinates":[4.4260058403,51.2105636597],"type":"Point"}
}