{
  "type": "Feature",
  "properties": {
    "addr:full":"Zandstraat 78 Middelkerke West-Vlaanderen 8434",
    "addr:housenumber":"78",
    "addr:postcode":"8434",
    "addr:street":"Zandstraat",
    "iso:country":"BE",
    "sg:address":"Zandstraat 78",
    "sg:city":"Middelkerke",
    "sg:orig_category":"Traitements param\u00e9dicaux",
    "sg:phone":"+32 58 23 51 70",
    "sg:postcode":"8434",
    "sg:province":"West-Vlaanderen",
    "wof:name":"A. Ameele",
    "wof:placetype":"venue"
},
  "geometry": {"coordinates":[2.7569050789,51.1488685608],"type":"Point"}
}