{
  "type": "Feature",
  "properties": {
    "addr:full":"Kloosterstraat 11ba Brecht Antwerpen 2960",
    "addr:housenumber":"11ba",
    "addr:postcode":"2960",
    "addr:street":"Kloosterstraat",
    "iso:country":"BE",
    "sg:address":"Kloosterstraat 11ba",
    "sg:city":"Brecht",
    "sg:orig_category":"Paramedische behandelingen",
    "sg:phone":"+32 3 313 83 20",
    "sg:postcode":"2960",
    "sg:province":"Antwerpen",
    "wof:name":"A. Bevers",
    "wof:placetype":"venue"
},
  "geometry": {"coordinates":[4.5579490662,51.3013458252],"type":"Point"}
}