{
  "type": "Feature",
  "properties": {
    "iso:country":"BE",
    "sg:address":"Cypriaan Verhavertstraat 99",
    "sg:city":"Halle",
    "sg:orig_category":"Artsen and specialisten",
    "sg:phone":"+32 2 361 79 29",
    "sg:postcode":"1500",
    "sg:province":"Vlaams-Brabant",
    "wof:name":"B. Van Butsele",
    "wof:placetype":"venue"
},
  "geometry": {"coordinates":[4.23021698,50.7412872314],"type":"Point"}
}