{
  "type": "Feature",
  "properties": {
    "addr:full":"Rue De La Montagne 20-22 Bruxelles Bruxelles-Capitale 1000",
    "addr:postcode":"20-22;1000",
    "addr:street":"Rue De La Montagne",
    "iso:country":"BE",
    "sg:address":"Rue De La Montagne 20-22",
    "sg:city":"Bruxelles",
    "sg:classifiers":[
        {
            "category":"Travel",
            "subcategory":"Hotels & Motels",
            "type":"Entertainment"
        }
    ],
    "sg:phone":"+32 2 513 29 73",
    "sg:postcode":"1000",
    "sg:province":"Bruxelles-Capitale",
    "sg:tags":[
        "hotels",
        "business",
        "restaurant"
    ],
    "wof:name":"Pierco Hotel International Sa",
    "wof:placetype":"venue"
},
  "geometry": {"coordinates":[4.3546938896,50.846824646],"type":"Point"}
}