{
  "type": "Feature",
  "properties": {
    "addr:full":"Steenovenstraat 51 Essen Antwerpen 2910",
    "addr:housenumber":"51",
    "addr:postcode":"2910",
    "addr:street":"Steenovenstraat",
    "iso:country":"BE",
    "sg:address":"Steenovenstraat 51",
    "sg:city":"Essen",
    "sg:classifiers":[
        {
            "category":"Health Services",
            "subcategory":"Health Practitioner",
            "type":"Services"
        }
    ],
    "sg:phone":"+32 3 667 45 35",
    "sg:postcode":"2910",
    "sg:province":"Antwerpen",
    "sg:tags":[
        "physiotherapist"
    ],
    "wof:name":"Willemot Vincent",
    "wof:placetype":"venue"
},
  "geometry": {"coordinates":[4.458671093,51.4279327393],"type":"Point"}
}