{
  "type": "Feature",
  "properties": {
    "iso:country":"BE",
    "sg:address":"Koedriesstraat 17",
    "sg:city":"Bocholt (kaulille)",
    "sg:classifiers":[
        {
            "category":"Building & Trades",
            "subcategory":"Landscaping Services",
            "type":"Services"
        }
    ],
    "sg:phone":"+32 11 62 14 30",
    "sg:postcode":"3950",
    "sg:province":"Limburg",
    "sg:tags":[
        "gardening",
        "garden",
        "maintenance"
    ],
    "wof:name":"Groenbureau",
    "wof:placetype":"venue"
},
  "geometry": {"coordinates":[5.5226950645,51.1883277893],"type":"Point"}
}