{
  "type": "Feature",
  "properties": {
    "addr:full":"Schuiferskapelsesteenweg 2 Tielt West-Vlaanderen 8700",
    "addr:housenumber":"2",
    "addr:postcode":"8700",
    "addr:street":"Schuiferskapelsesteenweg",
    "iso:country":"BE",
    "sg:address":"Schuiferskapelsesteenweg 2",
    "sg:city":"Tielt",
    "sg:classifiers":[
        {
            "category":"Professional",
            "subcategory":"Business Services",
            "type":"Services"
        }
    ],
    "sg:phone":"+32 51 40 56 94",
    "sg:postcode":"8700",
    "sg:province":"West-Vlaanderen",
    "sg:tags":[
        "firm"
    ],
    "wof:name":"Telkonex",
    "wof:placetype":"venue"
},
  "geometry": {"coordinates":[3.3261530399,51.0056800842],"type":"Point"}
}