{
  "type": "Feature",
  "properties": {
    "addr:full":"Place Du Vingt-ao\u00dbt 34 Li\u00c8ge Li\u00e8ge 4000",
    "addr:housenumber":"34",
    "addr:postcode":"4000",
    "addr:street":"Place Du Vingt-Aou\u0302T",
    "iso:country":"BE",
    "sg:address":"Place Du Vingt-ao\u00dbt 34",
    "sg:city":"Li\u00c8ge",
    "sg:orig_category":"Electrom\u00e9nager, t\u00e9l\u00e9visions and radios",
    "sg:phone":"+32 4 223 49 65",
    "sg:postcode":"4000",
    "sg:province":"Li\u00e8ge",
    "wof:name":"Hifi Video Must",
    "wof:placetype":"venue"
},
  "geometry": {"coordinates":[5.5756611824,50.6399383545],"type":"Point"}
}