{
  "type": "Feature",
  "properties": {
    "iso:country":"BE",
    "sg:address":"Avenue Paul Hartmann 1",
    "sg:city":"Tubize (saintes)",
    "sg:orig_category":"Non-Classified Establishments",
    "sg:phone":"+32 2 391 06 06",
    "sg:postcode":"1480",
    "sg:province":"Brabant Wallon",
    "wof:name":"Kneipp",
    "wof:placetype":"venue"
},
  "geometry": {"coordinates":[4.1734848022,50.7109107971],"type":"Point"}
}