{
  "type": "Feature",
  "properties": {
    "iso:country":"BE",
    "sg:address":"Rue Du Mar\u00c9chal 17bb",
    "sg:city":"Leuze-en-hainaut",
    "sg:orig_category":"Loodgieterij, verwarming and sanitaire installaties",
    "sg:phone":"+32 69 66 53 35",
    "sg:postcode":"7904",
    "sg:province":"Hainaut",
    "wof:name":"T'ben",
    "wof:placetype":"venue"
},
  "geometry": {"coordinates":[3.5816230774,50.5853652954],"type":"Point"}
}