{
  "type": "Feature",
  "properties": {
    "iso:country":"BE",
    "sg:address":"Oberhausen 1",
    "sg:city":"Burg-reuland/burg-reuland",
    "sg:classifiers":[
        {
            "category":"Travel",
            "subcategory":"Hotels & Motels",
            "type":"Entertainment"
        }
    ],
    "sg:phone":"+32 80 32 96 30",
    "sg:postcode":"4790",
    "sg:province":"Li\u00e8ge",
    "sg:tags":[
        "caf\u00e9s"
    ],
    "wof:name":"Hotel Weiss",
    "wof:placetype":"venue"
},
  "geometry": {"coordinates":[6.1415390968,50.1568412781],"type":"Point"}
}