{
  "type": "Feature",
  "properties": {
    "iso:country":"BE",
    "sg:address":"Chauss\u00e9e De Louvain 63",
    "sg:city":"Wavre",
    "sg:classifiers":[
        {
            "category":"Health Services",
            "subcategory":"Dentist",
            "type":"Services"
        }
    ],
    "sg:phone":"+32 10 22 20 44",
    "sg:postcode":"1300",
    "sg:province":"Brabant Wallon",
    "wof:name":"De Coster G",
    "wof:placetype":"venue"
},
  "geometry": {"coordinates":[4.6149902344,50.7143974304],"type":"Point"}
}