{
  "type": "Feature",
  "properties": {
    "iso:country":"BE",
    "sg:address":"Pereboom 6",
    "sg:city":"Lo-reninge",
    "sg:orig_category":"Eleveurs de bovins",
    "sg:phone":"+32 58 28 83 99",
    "sg:postcode":"8647",
    "sg:province":"West-Vlaanderen",
    "wof:name":"Albert Bulcke",
    "wof:placetype":"venue"
},
  "geometry": {"coordinates":[2.791369915,50.9759368896],"type":"Point"}
}