{
  "type": "Feature",
  "properties": {
    "addr:full":"Tulpenstraat 0 Vilvoorde Vlaams-Brabant 1800",
    "addr:housenumber":"0",
    "addr:postcode":"1800",
    "addr:street":"Tulpenstraat",
    "iso:country":"BE",
    "sg:address":"Tulpenstraat 0",
    "sg:city":"Vilvoorde",
    "sg:orig_category":"Sportterreinen and installaties behalve sportcentra",
    "sg:phone":"+32 2 252 04 70",
    "sg:postcode":"1800",
    "sg:province":"Vlaams-Brabant",
    "wof:name":"Zwembad Hazeweide",
    "wof:placetype":"venue"
},
  "geometry": {"coordinates":[4.4420990944,50.9295921326],"type":"Point"}
}