{
  "type": "Feature",
  "properties": {
    "iso:country":"BE",
    "sg:address":"Koningin Astrid Plein 8",
    "sg:city":"Jette",
    "sg:classifiers":[
        {
            "category":"Cafe",
            "type":"Food & Drink"
        }
    ],
    "sg:phone":"+32 2 426 89 63",
    "sg:postcode":"1090",
    "sg:province":"Bruxelles-Capitale",
    "sg:tags":[
        "caf\u00e9s"
    ],
    "wof:name":"Caf\u00c9 Sportwereld",
    "wof:placetype":"venue"
},
  "geometry": {"coordinates":[4.3252367973,50.8725891113],"type":"Point"}
}