{
  "type": "Feature",
  "properties": {
    "addr:full":"Transportln 4 Genk Limburg 3600",
    "addr:housenumber":"4",
    "addr:postcode":"3600",
    "addr:street":"Transportln",
    "iso:country":"BE",
    "sg:address":"Transportln 4",
    "sg:city":"Genk",
    "sg:classifiers":[
        {
            "category":"Banks & Credit Unions",
            "subcategory":"Investment Brokerage",
            "type":"Services"
        }
    ],
    "sg:phone":"+32 89 32 33 34",
    "sg:postcode":"3600",
    "sg:province":"Limburg",
    "sg:tags":[
        "-",
        "transport",
        "related"
    ],
    "wof:name":"Belstor Nv",
    "wof:placetype":"venue"
},
  "geometry": {"coordinates":[5.4629321098,50.9959144592],"type":"Point"}
}