{
  "type": "Feature",
  "properties": {
    "addr:full":"Rue Des Juifs 21 Mons Hainaut 7000",
    "addr:housenumber":"21",
    "addr:postcode":"7000",
    "addr:street":"Rue Des Juifs;Hainaut",
    "iso:country":"BE",
    "sg:address":"Rue Des Juifs 21",
    "sg:city":"Mons",
    "sg:classifiers":[
        {
            "category":"Fast Food",
            "type":"Food & Drink"
        }
    ],
    "sg:phone":"+32 65 31 93 68",
    "sg:postcode":"7000",
    "sg:province":"Hainaut",
    "sg:tags":[
        "de",
        "restaurant",
        "organisation",
        "\u00c0",
        "catering",
        "emporter",
        "f\u00cates",
        "restaurants"
    ],
    "wof:name":"Le Petit Bedon",
    "wof:placetype":"venue"
},
  "geometry": {"coordinates":[3.9503319263,50.4498138428],"type":"Point"}
}