{
  "type": "Feature",
  "properties": {
    "iso:country":"BE",
    "sg:address":"Perksesteenweg 59",
    "sg:city":"Kampenhout",
    "sg:orig_category":"Sportclubs",
    "sg:phone":"+32 16 65 10 74",
    "sg:postcode":"1910",
    "sg:province":"Vlaams-Brabant",
    "wof:name":"B.c. Kampenhout",
    "wof:placetype":"venue"
},
  "geometry": {"coordinates":[4.5414757729,50.943561554],"type":"Point"}
}