{
  "type": "Feature",
  "properties": {
    "iso:country":"BE",
    "sg:address":"Rue Du Moulin-\u00c0-vent 6",
    "sg:city":"Gembloux",
    "sg:orig_category":"Kapsalons",
    "sg:phone":"+32 81 64 07 98",
    "sg:postcode":"5031",
    "sg:province":"Namur",
    "wof:name":"Coiffure Nathalie",
    "wof:placetype":"venue"
},
  "geometry": {"coordinates":[4.7660121918,50.5800552368],"type":"Point"}
}