{
  "type": "Feature",
  "properties": {
    "addr:full":"Hundelgemsesteenweg 187 Gent Oost-Vlaanderen 9050",
    "addr:housenumber":"187",
    "addr:postcode":"9050",
    "addr:street":"Hundelgemsesteenweg;Oost-Vlaanderen",
    "iso:country":"BE",
    "sg:address":"Hundelgemsesteenweg 187",
    "sg:city":"Gent",
    "sg:orig_category":"Slagers",
    "sg:phone":"+32 9 231 23 85",
    "sg:postcode":"9050",
    "sg:province":"Oost-Vlaanderen",
    "wof:name":"Marc Crul",
    "wof:placetype":"venue"
},
  "geometry": {"coordinates":[3.7426810265,51.0330619812],"type":"Point"}
}