{
  "type": "Feature",
  "properties": {
    "iso:country":"BE",
    "sg:address":"Rue Cervant\u00e8s 72",
    "sg:city":"Bruxelles (forest)",
    "sg:classifiers":[
        {
            "category":"Real Estate",
            "subcategory":"Surveying",
            "type":"Services"
        }
    ],
    "sg:phone":"+32 2 345 96 75",
    "sg:postcode":"1190",
    "sg:province":"Bruxelles-Capitale",
    "sg:tags":[
        "surveyor",
        "land"
    ],
    "wof:name":"Van Eycken O",
    "wof:placetype":"venue"
},
  "geometry": {"coordinates":[4.3394570351,50.8181381226],"type":"Point"}
}