{
  "type": "Feature",
  "properties": {
    "iso:country":"BE",
    "sg:address":"Mechelsesteenweg 93",
    "sg:city":"Antwerpen",
    "sg:orig_category":"Kapsalons",
    "sg:phone":"+32 3 225 19 20",
    "sg:postcode":"2018",
    "sg:province":"Antwerpen",
    "wof:name":"Samuel",
    "wof:placetype":"venue"
},
  "geometry": {"coordinates":[4.4088778496,51.2080078125],"type":"Point"}
}