{
  "type": "Feature",
  "properties": {
    "addr:full":"Caignaardstraat 8 Wielsbeke West-Vlaanderen 8710",
    "addr:housenumber":"8",
    "addr:postcode":"8710",
    "addr:street":"Caignaardstraat;West-Vlaanderen",
    "iso:country":"BE",
    "sg:address":"Caignaardstraat 8",
    "sg:city":"Wielsbeke",
    "sg:orig_category":"Zuivelproducten",
    "sg:phone":"+32 56 66 73 62",
    "sg:postcode":"8710",
    "sg:province":"West-Vlaanderen",
    "wof:name":"Jeaninne Haerynck",
    "wof:placetype":"venue"
},
  "geometry": {"coordinates":[3.3813960552,50.9224052429],"type":"Point"}
}