{
  "type": "Feature",
  "properties": {
    "addr:full":"Schrijbergstraat 48 Waasmunster Oost-Vlaanderen 9250",
    "addr:housenumber":"48",
    "addr:postcode":"9250",
    "addr:street":"Schrijbergstraat",
    "iso:country":"BE",
    "sg:address":"Schrijbergstraat 48",
    "sg:city":"Waasmunster",
    "sg:classifiers":[
        {
            "category":"Health Services",
            "subcategory":"Doctor",
            "type":"Services"
        }
    ],
    "sg:phone":"+32 3 772 59 04",
    "sg:postcode":"9250",
    "sg:province":"Oost-Vlaanderen",
    "sg:tags":[
        "medicinephysicians",
        "surgeon"
    ],
    "wof:name":"Du Caju J",
    "wof:placetype":"venue"
},
  "geometry": {"coordinates":[4.0736408234,51.1359481812],"type":"Point"}
}