{
  "type": "Feature",
  "properties": {
    "iso:country":"BE",
    "sg:address":"Avenue De La Toison D'or 28",
    "sg:city":"Marche-en-famenne",
    "sg:orig_category":"Avocats and conseillers juridiques",
    "sg:phone":"+32 84 31 32 30",
    "sg:postcode":"6900",
    "sg:province":"Luxembourg",
    "wof:name":"M. Ghislain",
    "wof:placetype":"venue"
},
  "geometry": {"coordinates":[5.3430099487,50.2273483276],"type":"Point"}
}