{
  "type": "Feature",
  "properties": {
    "iso:country":"BE",
    "sg:address":"Rue Saint-jean 51",
    "sg:city":"Brussel/bruxelles",
    "sg:orig_category":"Librairies",
    "sg:phone":"+32 2 512 74 65",
    "sg:postcode":"1000",
    "sg:province":"Bruxelles-Capitale",
    "wof:name":"Van Look",
    "wof:placetype":"venue"
},
  "geometry": {"coordinates":[4.3537139893,50.8446235657],"type":"Point"}
}