{
  "type": "Feature",
  "properties": {
    "addr:full":"Rue De La Place 7 Jodoigne Brabant Wallon 1370",
    "addr:housenumber":"7",
    "addr:postcode":"1370",
    "addr:street":"Rue De La Place",
    "iso:country":"BE",
    "sg:address":"Rue De La Place 7",
    "sg:city":"Jodoigne",
    "sg:orig_category":"S\u00e9curit\u00e9 sociale",
    "sg:phone":"+32 10 81 41 02",
    "sg:postcode":"1370",
    "sg:province":"Brabant Wallon",
    "wof:name":"Mutualit\u00c9 Socialiste",
    "wof:placetype":"venue"
},
  "geometry": {"coordinates":[4.9161839485,50.7264099121],"type":"Point"}
}