{
  "type": "Feature",
  "properties": {
    "iso:country":"BE",
    "sg:address":"Chemin Des Carri\u00e8res 1",
    "sg:city":"Neufvilles",
    "sg:classifiers":[
        {
            "category":"Building & Trades",
            "subcategory":"Construction",
            "type":"Services"
        }
    ],
    "sg:phone":"+32 67 34 68 00",
    "sg:postcode":"7063",
    "sg:province":"Hainaut",
    "sg:tags":[
        "granite",
        "working"
    ],
    "wof:name":"Pierre Bleue Belge Sa",
    "wof:placetype":"venue"
},
  "geometry": {"coordinates":[4.012570858,50.5767784119],"type":"Point"}
}