{
  "type": "Feature",
  "properties": {
    "iso:country":"BE",
    "sg:address":"Oordegemsesteenweg 141",
    "sg:city":"Wetteren",
    "sg:classifiers":[
        {
            "category":"Shopping",
            "subcategory":"Clothing, Apparel, & Fashions",
            "type":"Retail Goods"
        }
    ],
    "sg:phone":"+32 9 366 02 35",
    "sg:postcode":"9230",
    "sg:province":"Oost-Vlaanderen",
    "sg:tags":[
        "ondergoed",
        "lingerie"
    ],
    "wof:name":"Marie-therese De Rho",
    "wof:placetype":"venue"
},
  "geometry": {"coordinates":[3.8860459328,50.9969711304],"type":"Point"}
}