{
  "type": "Feature",
  "properties": {
    "iso:country":"BE",
    "sg:address":"Langestraat 27b29",
    "sg:city":"Brugge",
    "sg:orig_category":"Antiek",
    "sg:phone":"+32 50 34 04 69",
    "sg:postcode":"8000",
    "sg:province":"West-Vlaanderen",
    "wof:name":"Huis Cursief",
    "wof:placetype":"venue"
},
  "geometry": {"coordinates":[3.2331049442,51.2097625732],"type":"Point"}
}