{
  "type": "Feature",
  "properties": {
    "addr:full":"Heikant 83 Vorselaar Antwerpen 2290",
    "addr:housenumber":"83",
    "addr:postcode":"2290",
    "addr:street":"Heikant",
    "iso:country":"BE",
    "sg:address":"Heikant 83",
    "sg:city":"Vorselaar",
    "sg:orig_category":"Dierentuinen, botanische tuinen, sterrenwachten and natuurreservaten",
    "sg:phone":"+32 14 51 29 83",
    "sg:postcode":"2290",
    "sg:province":"Antwerpen",
    "wof:name":"Groot Schupleer",
    "wof:placetype":"venue"
},
  "geometry": {"coordinates":[4.7574791908,51.201423645],"type":"Point"}
}