{
  "type": "Feature",
  "properties": {
    "addr:full":"Rue Sous La Garenne 20 P\u00c9ruwelz Hainaut 7608",
    "addr:housenumber":"20",
    "addr:postcode":"7608",
    "addr:street":"Rue Sous La Garenne",
    "iso:country":"BE",
    "sg:address":"Rue Sous La Garenne 20",
    "sg:city":"P\u00c9ruwelz",
    "sg:orig_category":"Fournitures de bureau",
    "sg:phone":"+32 69 78 11 47",
    "sg:postcode":"7608",
    "sg:province":"Hainaut",
    "wof:name":"Fa. Real D",
    "wof:placetype":"venue"
},
  "geometry": {"coordinates":[3.5474710464,50.5200881958],"type":"Point"}
}