{
  "type": "Feature",
  "properties": {
    "iso:country":"BE",
    "sg:address":"Jacob Van Maerlantstraat 59",
    "sg:city":"Brugge",
    "sg:orig_category":"Studios photographiques",
    "sg:phone":"+32 50 34 62 09",
    "sg:postcode":"8000",
    "sg:province":"West-Vlaanderen",
    "wof:name":"Luc Moerman",
    "wof:placetype":"venue"
},
  "geometry": {"coordinates":[3.2343099117,51.2279968262],"type":"Point"}
}