{
  "type": "Feature",
  "properties": {
    "iso:country":"BE",
    "sg:address":"Rue Warocqu\u00c9 14",
    "sg:city":"Chapelle-lez-herlaimont",
    "sg:orig_category":"Baby- and kinderkleding",
    "sg:phone":"+32 64 45 01 13",
    "sg:postcode":"7160",
    "sg:province":"Hainaut",
    "wof:name":"Les Sucettes \u00c0 L\u00b4anis",
    "wof:placetype":"venue"
},
  "geometry": {"coordinates":[4.2834558487,50.4686546326],"type":"Point"}
}