{
  "type": "Feature",
  "properties": {
    "addr:full":"Chauss\u00e9e De Bruxelles 148 Bruxelles (forest) Bruxelles-Capitale 1190",
    "addr:housenumber":"148",
    "addr:postcode":"1190",
    "addr:street":"Chausse\u0301E De Bruxelles",
    "iso:country":"BE",
    "sg:address":"Chauss\u00e9e De Bruxelles 148",
    "sg:city":"Bruxelles (forest)",
    "sg:classifiers":[
        {
            "category":"Retail",
            "subcategory":"Veterinary Services",
            "type":"Services"
        }
    ],
    "sg:phone":"+32 2 343 41 83",
    "sg:postcode":"1190",
    "sg:province":"Bruxelles-Capitale",
    "sg:tags":[
        "veterinarian"
    ],
    "wof:name":"Swaelus Ph",
    "wof:placetype":"venue"
},
  "geometry": {"coordinates":[4.3243031502,50.8133239746],"type":"Point"}
}