{
  "type": "Feature",
  "properties": {
    "iso:country":"BE",
    "sg:address":"Helpt Elkanderstraat 17",
    "sg:city":"Wuustwezel",
    "sg:classifiers":[
        {
            "category":"Professional",
            "subcategory":"Accounting & Tax Preparation",
            "type":"Services"
        }
    ],
    "sg:phone":"+32 3 633 02 36",
    "sg:postcode":"2990",
    "sg:province":"Antwerpen",
    "sg:tags":[
        "bookkeeper"
    ],
    "wof:name":"Verheyden N",
    "wof:placetype":"venue"
},
  "geometry": {"coordinates":[4.543366909,51.3559494019],"type":"Point"}
}