{
  "type": "Feature",
  "properties": {
    "addr:full":"Ieperstraat 10 Poperinge West-Vlaanderen 8970",
    "addr:housenumber":"10",
    "addr:postcode":"8970",
    "addr:street":"Ieperstraat",
    "iso:country":"BE",
    "sg:address":"Ieperstraat 10",
    "sg:city":"Poperinge",
    "sg:orig_category":"V\u00eatements",
    "sg:phone":"+32 57 33 87 99",
    "sg:postcode":"8970",
    "sg:province":"West-Vlaanderen",
    "wof:name":"Pantariba",
    "wof:placetype":"venue"
},
  "geometry": {"coordinates":[2.7278690338,50.8549041748],"type":"Point"}
}