{
  "type": "Feature",
  "properties": {
    "addr:full":"Rue Des Arsilliers 45 Malmedy Li\u00e8ge 4960",
    "addr:housenumber":"45",
    "addr:postcode":"4960",
    "addr:street":"Rue Des Arsilliers",
    "iso:country":"BE",
    "sg:address":"Rue Des Arsilliers 45",
    "sg:city":"Malmedy",
    "sg:orig_category":"Traitement and fa\u00e7onnage de la pierre",
    "sg:phone":"+32 80 33 02 35",
    "sg:postcode":"4960",
    "sg:province":"Li\u00e8ge",
    "wof:name":"Therer J",
    "wof:placetype":"venue"
},
  "geometry": {"coordinates":[6.0240850449,50.4248313904],"type":"Point"}
}