{
  "type": "Feature",
  "properties": {
    "iso:country":"BE",
    "sg:address":"Rijweg 91",
    "sg:city":"Herent",
    "sg:orig_category":"Autombile concessionaires",
    "sg:phone":"+32 16 23 86 26",
    "sg:postcode":"3020",
    "sg:province":"Vlaams-Brabant",
    "wof:name":"Gar Rapid Bvba",
    "wof:placetype":"venue"
},
  "geometry": {"coordinates":[4.6731491089,50.8993492126],"type":"Point"}
}