{
  "type": "Feature",
  "properties": {
    "addr:full":"Rue Fran\u00e7ois Bovesse 8 Montigny-le-tilleul Hainaut 6110",
    "addr:housenumber":"8",
    "addr:postcode":"6110",
    "addr:street":"Rue Franc\u0327Ois Bovesse",
    "iso:country":"BE",
    "sg:address":"Rue Fran\u00e7ois Bovesse 8",
    "sg:city":"Montigny-le-tilleul",
    "sg:classifiers":[
        {
            "category":"Shopping",
            "subcategory":"Pets & Pet Supplies",
            "type":"Retail Goods"
        }
    ],
    "sg:phone":"+32 71 51 60 31",
    "sg:postcode":"6110",
    "sg:province":"Hainaut",
    "sg:tags":[
        "shop",
        "-"
    ],
    "wof:name":"Chatterie Des Amours Bleues",
    "wof:placetype":"venue"
},
  "geometry": {"coordinates":[4.3919048309,50.3625602722],"type":"Point"}
}