{
  "type": "Feature",
  "properties": {
    "addr:full":"Dornestraat 3 Maaseik Limburg 3680",
    "addr:housenumber":"3",
    "addr:postcode":"3680",
    "addr:street":"Dornestraat",
    "iso:country":"BE",
    "sg:address":"Dornestraat 3",
    "sg:city":"Maaseik",
    "sg:orig_category":"Banques and organismes de cr\u00e9dit",
    "sg:phone":"+32 89 85 52 28",
    "sg:postcode":"3680",
    "sg:province":"Limburg",
    "wof:name":"Landbouwkrediet",
    "wof:placetype":"venue"
},
  "geometry": {"coordinates":[5.791285038,51.0954208374],"type":"Point"}
}