{
  "type": "Feature",
  "properties": {
    "addr:full":"Veldstraat 1 Waasmunster Oost-Vlaanderen 9250",
    "addr:housenumber":"1",
    "addr:postcode":"9250",
    "addr:street":"Veldstraat",
    "iso:country":"BE",
    "sg:address":"Veldstraat 1",
    "sg:city":"Waasmunster",
    "sg:classifiers":[
        {
            "category":"Shopping",
            "subcategory":"Florist",
            "type":"Retail Goods"
        }
    ],
    "sg:phone":"+32 52 46 38 03",
    "sg:postcode":"9250",
    "sg:province":"Oost-Vlaanderen",
    "wof:name":"Blommerije (de)",
    "wof:placetype":"venue"
},
  "geometry": {"coordinates":[4.125939846,51.1142539978],"type":"Point"}
}