{
  "type": "Feature",
  "properties": {
    "addr:full":"Chauss\u00e9e De Jette 450 Bruxelles (jette) Bruxelles-Capitale 1090",
    "addr:housenumber":"450",
    "addr:postcode":"1090",
    "addr:street":"Chausse\u0301E De Jette",
    "iso:country":"BE",
    "sg:address":"Chauss\u00e9e De Jette 450",
    "sg:city":"Bruxelles (jette)",
    "sg:classifiers":[
        {
            "category":"Manufacturing",
            "subcategory":"Paper Products",
            "type":"Manufacturing & Wholesale Goods"
        }
    ],
    "sg:phone":"+32 2 425 28 93",
    "sg:postcode":"1090",
    "sg:province":"Bruxelles-Capitale",
    "sg:tags":[
        "bookbinding"
    ],
    "wof:name":"Brochage P Vande Velde Sa",
    "wof:placetype":"venue"
},
  "geometry": {"coordinates":[4.3286027908,50.8684043884],"type":"Point"}
}