{
  "type": "Feature",
  "properties": {
    "iso:country":"BE",
    "sg:address":"Galgenstraat 15",
    "sg:city":"Waregem",
    "sg:orig_category":"Motos",
    "sg:phone":"+32 56 60 24 50",
    "sg:postcode":"8790",
    "sg:province":"West-Vlaanderen",
    "wof:name":"Pruvoost",
    "wof:placetype":"venue"
},
  "geometry": {"coordinates":[3.4314749241,50.8873558044],"type":"Point"}
}