{
  "type": "Feature",
  "properties": {
    "iso:country":"BE",
    "sg:address":"Windmolenstraat 9",
    "sg:city":"Leuven",
    "sg:classifiers":[
        {
            "category":"Organizations",
            "subcategory":"Community Association",
            "type":"Services"
        }
    ],
    "sg:phone":"+32 14 31 81 58",
    "sg:postcode":"3000",
    "sg:province":"Vlaams-Brabant",
    "sg:tags":[
        "organisation"
    ],
    "wof:name":"Chiromeisjes",
    "wof:placetype":"venue"
},
  "geometry": {"coordinates":[4.7111368179,50.8742980957],"type":"Point"}
}