{
  "type": "Feature",
  "properties": {
    "iso:country":"BE",
    "sg:address":"Hokelbeke 9",
    "sg:city":"Maarkedal (maarke-kerkem)",
    "sg:classifiers":[
        {
            "category":"Communications",
            "type":"Services"
        }
    ],
    "sg:phone":"+32 55 45 63 07",
    "sg:postcode":"9680",
    "sg:province":"Oost-Vlaanderen",
    "sg:tags":[
        "translator"
    ],
    "wof:name":"Wiegers W.e.",
    "wof:placetype":"venue"
},
  "geometry": {"coordinates":[3.6565361023,50.7996025085],"type":"Point"}
}