{
  "type": "Feature",
  "properties": {
    "iso:country":"BE",
    "sg:address":"Bondgenotenlaan 133",
    "sg:city":"Leuven",
    "sg:classifiers":[
        {
            "category":"Health Services",
            "subcategory":"Doctor",
            "type":"Services"
        }
    ],
    "sg:phone":"+32 16 22 21 38",
    "sg:postcode":"3000",
    "sg:province":"Vlaams-Brabant",
    "sg:tags":[
        "medicinephysicians",
        "surgeon"
    ],
    "wof:name":"Jooris M",
    "wof:placetype":"venue"
},
  "geometry": {"coordinates":[4.7115249634,50.8808097839],"type":"Point"}
}