{
  "type": "Feature",
  "properties": {
    "iso:country":"BE",
    "sg:address":"Jagersdreef 5",
    "sg:city":"Zoersel",
    "sg:classifiers":[
        {
            "category":"Wholesale",
            "subcategory":"Wine & Distilled Alcoholic Beverages",
            "type":"Manufacturing & Wholesale Goods"
        }
    ],
    "sg:phone":"+32 3 309 24 04",
    "sg:postcode":"2980",
    "sg:province":"Antwerpen",
    "sg:tags":[
        "whol",
        "-",
        "spirit",
        "mfg"
    ],
    "wof:name":"Enotria - Impact Products Nv",
    "wof:placetype":"venue"
},
  "geometry": {"coordinates":[4.700920105,51.2607002258],"type":"Point"}
}