{
  "type": "Feature",
  "properties": {
    "addr:full":"Wolfshaegen 172 Huldenberg (neerijse) Vlaams-Brabant 3040",
    "addr:housenumber":"172",
    "addr:postcode":"3040",
    "addr:street":"Wolfshaegen",
    "iso:country":"BE",
    "sg:address":"Wolfshaegen 172",
    "sg:city":"Huldenberg (neerijse)",
    "sg:classifiers":[
        {
            "category":"Health Services",
            "subcategory":"Health Practitioner",
            "type":"Services"
        }
    ],
    "sg:phone":"+32 16 47 23 69",
    "sg:postcode":"3040",
    "sg:province":"Vlaams-Brabant",
    "sg:tags":[
        "physiotherapist"
    ],
    "wof:name":"Vanhouche Mia",
    "wof:placetype":"venue"
},
  "geometry": {"coordinates":[4.6288962364,50.8053245544],"type":"Point"}
}