{
  "type": "Feature",
  "properties": {
    "iso:country":"BE",
    "sg:address":"Zeelaan 296",
    "sg:city":"Koksijde",
    "sg:classifiers":[
        {
            "category":"Bakery",
            "type":"Food & Drink"
        }
    ],
    "sg:phone":"+32 58 51 11 40",
    "sg:postcode":"8670",
    "sg:province":"West-Vlaanderen",
    "sg:tags":[
        "confectioner",
        "baker"
    ],
    "wof:name":"Flandria",
    "wof:placetype":"venue"
},
  "geometry": {"coordinates":[2.6345660686,51.1196556091],"type":"Point"}
}