{
  "type": "Feature",
  "properties": {
    "iso:country":"BE",
    "sg:address":"Steenpoort 10",
    "sg:city":"Kortrijk",
    "sg:classifiers":[
        {
            "category":"Shopping",
            "subcategory":"Music",
            "type":"Retail Goods"
        }
    ],
    "sg:phone":"+32 56 22 28 06",
    "sg:postcode":"8500",
    "sg:province":"West-Vlaanderen",
    "sg:tags":[
        "-",
        "cd's",
        "recorded",
        "cassette"
    ],
    "wof:name":"Billboard Kortrijk",
    "wof:placetype":"venue"
},
  "geometry": {"coordinates":[3.2695100307,50.8269805908],"type":"Point"}
}