{
  "type": "Feature",
  "properties": {
    "iso:country":"BE",
    "sg:address":"Borgveld 4",
    "sg:city":"Brakel",
    "sg:orig_category":"V\u00e9t\u00e9rinaires",
    "sg:phone":"+32 55 42 76 96",
    "sg:postcode":"9660",
    "sg:province":"Oost-Vlaanderen",
    "wof:name":"Veerle Zonnekeyn",
    "wof:placetype":"venue"
},
  "geometry": {"coordinates":[3.7516000271,50.8423118591],"type":"Point"}
}