{
  "type": "Feature",
  "properties": {
    "iso:country":"BE",
    "sg:address":"Grote Singel 88a",
    "sg:city":"Schoten",
    "sg:classifiers":[
        {
            "category":"Communications",
            "type":"Services"
        }
    ],
    "sg:phone":"+32 3 658 03 22",
    "sg:postcode":"2900",
    "sg:province":"Antwerpen",
    "sg:tags":[
        "translator"
    ],
    "wof:name":"Taalwinkel (de)",
    "wof:placetype":"venue"
},
  "geometry": {"coordinates":[4.5262508392,51.2591819763],"type":"Point"}
}