{
  "type": "Feature",
  "properties": {
    "addr:full":"Sint Jansplein 36 Antwerpen-sint-jansplein Antwerpen 2060",
    "addr:housenumber":"36",
    "addr:postcode":"2060",
    "addr:street":"Sint Jansplein",
    "iso:country":"BE",
    "sg:address":"Sint Jansplein 36",
    "sg:city":"Antwerpen-sint-jansplein",
    "sg:orig_category":"Agences de voyages",
    "sg:phone":"+32 3 233 63 36",
    "sg:postcode":"2060",
    "sg:province":"Antwerpen",
    "wof:name":"Mare Tours",
    "wof:placetype":"venue"
},
  "geometry": {"coordinates":[4.4181962013,51.2246055603],"type":"Point"}
}