{
  "type": "Feature",
  "properties": {
    "addr:full":"Van Langenhovenstraat 229 Dendermonde Oost-Vlaanderen 9200",
    "addr:housenumber":"229",
    "addr:postcode":"9200",
    "addr:street":"Langenhovenstraat;Oost-Vlaanderen",
    "iso:country":"BE",
    "sg:address":"Van Langenhovenstraat 229",
    "sg:city":"Dendermonde",
    "sg:orig_category":"Loodgieterij, verwarming and sanitaire installaties",
    "sg:phone":"+32 52 20 23 77",
    "sg:postcode":"9200",
    "sg:province":"Oost-Vlaanderen",
    "wof:name":"D.r.d.-san",
    "wof:placetype":"venue"
},
  "geometry": {"coordinates":[4.099615097,51.0173072815],"type":"Point"}
}