{
  "type": "Feature",
  "properties": {
    "addr:full":"Av. Bourg. Jean Materne 12 Namur Namur 5100",
    "addr:housenumber":"12",
    "addr:postcode":"5100",
    "addr:street":"Av. Bourg. Jean Materne",
    "iso:country":"BE",
    "sg:address":"Av. Bourg. Jean Materne 12",
    "sg:city":"Namur",
    "sg:classifiers":[
        {
            "category":"Shopping",
            "subcategory":"Bicycles & Sporting Goods",
            "type":"Retail Goods"
        }
    ],
    "sg:phone":"+32 81 30 00 61",
    "sg:postcode":"5100",
    "sg:province":"Namur",
    "sg:tags":[
        "article",
        "de",
        "sport",
        "camping"
    ],
    "wof:name":"Van Dooren Sports",
    "wof:placetype":"venue"
},
  "geometry": {"coordinates":[4.8713750839,50.4566345215],"type":"Point"}
}