{
  "type": "Feature",
  "properties": {
    "iso:country":"BE",
    "sg:address":"Markt 71",
    "sg:city":"Berlaar",
    "sg:orig_category":"Taxi's speciale diensten",
    "sg:phone":"+32 3 482 11 76",
    "sg:postcode":"2590",
    "sg:province":"Antwerpen",
    "wof:name":"Dream Cars",
    "wof:placetype":"venue"
},
  "geometry": {"coordinates":[4.656899929,51.1180725098],"type":"Point"}
}