{
  "type": "Feature",
  "properties": {
    "iso:country":"BE",
    "sg:address":"Dronckaertstraat 609",
    "sg:city":"Lauwe",
    "sg:orig_category":"Recycling Of Precious Metals",
    "sg:phone":"+32 56 84 33 66",
    "sg:postcode":"8930",
    "sg:province":"West-Vlaanderen",
    "wof:name":"Emeko Nv",
    "wof:placetype":"venue"
},
  "geometry": {"coordinates":[3.2082469463,50.7952232361],"type":"Point"}
}