{
  "type": "Feature",
  "properties": {
    "addr:full":"Meiberg 1 Meerhout Antwerpen 2450",
    "addr:housenumber":"1",
    "addr:postcode":"2450",
    "addr:street":"Meiberg",
    "iso:country":"BE",
    "sg:address":"Meiberg 1",
    "sg:city":"Meerhout",
    "sg:orig_category":"Fleurs and plantes. Souvenirs and objets artisanaux",
    "sg:phone":"+32 14 30 14 31",
    "sg:postcode":"2450",
    "sg:province":"Antwerpen",
    "wof:name":"Bloemenwinkeltje Florande",
    "wof:placetype":"venue"
},
  "geometry": {"coordinates":[5.0682439804,51.1339454651],"type":"Point"}
}