{
  "type": "Feature",
  "properties": {
    "addr:full":"Alcyonstraat 70 Sint-agatha-berchem/berchem-sainte-agathe Bruxelles-Capitale 1082",
    "addr:housenumber":"70",
    "addr:postcode":"1082",
    "addr:street":"Alcyonstraat",
    "iso:country":"BE",
    "sg:address":"Alcyonstraat 70",
    "sg:city":"Sint-agatha-berchem/berchem-sainte-agathe",
    "sg:orig_category":"Loodgieterij, verwarming and sanitaire installaties",
    "sg:phone":"+32 2 468 30 67",
    "sg:postcode":"1082",
    "sg:province":"Bruxelles-Capitale",
    "wof:name":"Fe. Tibodo",
    "wof:placetype":"venue"
},
  "geometry": {"coordinates":[4.292181015,50.8664932251],"type":"Point"}
}