{
  "type": "Feature",
  "properties": {
    "addr:full":"Boulevard D\u00b4herbatte 14 Bis Namur Namur 5000",
    "addr:housenumber":"14 bis",
    "addr:postcode":"5000",
    "addr:street":"Boulevard D\u00b4Herbatte",
    "iso:country":"BE",
    "sg:address":"Boulevard D\u00b4herbatte 14 Bis",
    "sg:city":"Namur",
    "sg:orig_category":"Huisdieren and benodigdheden",
    "sg:phone":"+32 81 22 39 00",
    "sg:postcode":"5000",
    "sg:province":"Namur",
    "wof:name":"Ets. De Munck",
    "wof:placetype":"venue"
},
  "geometry": {"coordinates":[4.8771181107,50.4681816101],"type":"Point"}
}