{
  "type": "Feature",
  "properties": {
    "addr:full":"Rue Georges Truffaut 37 Ans Li\u00e8ge 4432",
    "addr:housenumber":"37",
    "addr:postcode":"4432",
    "addr:street":"Rue Georges Truffaut",
    "iso:country":"BE",
    "sg:address":"Rue Georges Truffaut 37",
    "sg:city":"Ans",
    "sg:orig_category":"Enseignement maternel and primaire",
    "sg:phone":"+32 4 263 29 68",
    "sg:postcode":"4432",
    "sg:province":"Li\u00e8ge",
    "wof:name":"Ecole Fondamentale",
    "wof:placetype":"venue"
},
  "geometry": {"coordinates":[5.514318943,50.675075531],"type":"Point"}
}