{
  "type": "Feature",
  "properties": {
    "iso:country":"BE",
    "sg:address":"Tervuursesteenweg 216",
    "sg:city":"Leuven",
    "sg:orig_category":"Agences de publicit\u00e9",
    "sg:phone":"+32 16 22 47 26",
    "sg:postcode":"3001",
    "sg:province":"Vlaams-Brabant",
    "wof:name":"Huybrechts Reklame",
    "wof:placetype":"venue"
},
  "geometry": {"coordinates":[4.6895089149,50.8731384277],"type":"Point"}
}