{
  "type": "Feature",
  "properties": {
    "addr:full":"'s Wolfsdam 20 Beveren (vrasene) Oost-Vlaanderen 9120",
    "addr:housenumber":"20",
    "addr:postcode":"9120",
    "addr:street":"'",
    "iso:country":"BE",
    "sg:address":"'s Wolfsdam 20",
    "sg:city":"Beveren (vrasene)",
    "sg:classifiers":[
        {
            "category":"Communications",
            "subcategory":"Radio Station",
            "type":"Services"
        }
    ],
    "sg:phone":"+32 3 775 66 01",
    "sg:postcode":"9120",
    "sg:province":"Oost-Vlaanderen",
    "sg:tags":[
        "medium",
        "broker"
    ],
    "wof:name":"S.n.l. Advertising",
    "wof:placetype":"venue"
},
  "geometry": {"coordinates":[4.1951918602,51.2258377075],"type":"Point"}
}