{
  "type": "Feature",
  "properties": {
    "addr:full":"Lange Koepoortstraat 27 Antwerpen Antwerpen 2000",
    "addr:housenumber":"27",
    "addr:postcode":"2000",
    "addr:street":"Lange Koepoortstraat",
    "iso:country":"BE",
    "sg:address":"Lange Koepoortstraat 27",
    "sg:city":"Antwerpen",
    "sg:classifiers":[
        {
            "category":"Personal",
            "subcategory":"Beauty Salon",
            "type":"Services"
        }
    ],
    "sg:phone":"+32 3 232 73 32",
    "sg:postcode":"2000",
    "sg:province":"Antwerpen",
    "sg:tags":[
        "lady",
        "-",
        "hairdressing"
    ],
    "wof:name":"Onze Kapper",
    "wof:placetype":"venue"
},
  "geometry": {"coordinates":[4.4027080536,51.2228775024],"type":"Point"}
}