{
  "type": "Feature",
  "properties": {
    "addr:full":"Rue L\u00e9on Desmottes 78 Frasnes-lez-anvaing (frasnes - Lez - Buissenal) Hainaut 7911",
    "addr:housenumber":"78",
    "addr:postcode":"7911",
    "addr:street":"Rue Le\u0301On Desmottes",
    "iso:country":"BE",
    "sg:address":"Rue L\u00e9on Desmottes 78",
    "sg:city":"Frasnes-lez-anvaing (frasnes - Lez - Buissenal)",
    "sg:orig_category":"Non-Classified Establishments",
    "sg:phone":"+32 69 86 77 93",
    "sg:postcode":"7911",
    "sg:province":"Hainaut",
    "wof:name":"Fochler Bastien Ets",
    "wof:placetype":"venue"
},
  "geometry": {"coordinates":[3.6140360832,50.6642341614],"type":"Point"}
}