{
  "type": "Feature",
  "properties": {
    "iso:country":"BE",
    "sg:address":"Paleizenstraat 112",
    "sg:city":"Brussel/bruxelles",
    "sg:orig_category":"Diverse organisaties and verenigingen",
    "sg:phone":"+32 2 242 54 09",
    "sg:postcode":"1030",
    "sg:province":"Bruxelles-Capitale",
    "wof:name":"Jekino-film",
    "wof:placetype":"venue"
},
  "geometry": {"coordinates":[4.3670392036,50.862663269],"type":"Point"}
}