{
  "type": "Feature",
  "properties": {
    "iso:country":"BE",
    "sg:address":"Meidoornlaan 59",
    "sg:city":"Kapellen",
    "sg:classifiers":[
        {
            "category":"Insurance",
            "subcategory":"Life Insurance",
            "type":"Services"
        }
    ],
    "sg:phone":"+32 3 664 63 72",
    "sg:postcode":"2950",
    "sg:province":"Antwerpen",
    "sg:tags":[
        "assurance"
    ],
    "wof:name":"M. Van Hoydonck",
    "wof:placetype":"venue"
},
  "geometry": {"coordinates":[4.4384422302,51.3259429932],"type":"Point"}
}