{
  "type": "Feature",
  "properties": {
    "addr:full":"Leon Kreperlaan 18 Sint-pieters-leeuw Vlaams-Brabant 1600",
    "addr:housenumber":"18",
    "addr:postcode":"1600",
    "addr:street":"Kreperlaan",
    "iso:country":"BE",
    "sg:address":"Leon Kreperlaan 18",
    "sg:city":"Sint-pieters-leeuw",
    "sg:classifiers":[
        {
            "category":"Health Services",
            "subcategory":"Health Practitioner",
            "type":"Services"
        }
    ],
    "sg:phone":"+32 2 377 26 26",
    "sg:postcode":"1600",
    "sg:province":"Vlaams-Brabant",
    "sg:tags":[
        "physiotherapist"
    ],
    "wof:name":"Toussaint A",
    "wof:placetype":"venue"
},
  "geometry": {"coordinates":[4.2872018814,50.8058204651],"type":"Point"}
}