{
  "type": "Feature",
  "properties": {
    "iso:country":"BE",
    "sg:address":"Kalfvaart 5",
    "sg:city":"Ieper",
    "sg:orig_category":"Ordinateurs and \u00e9quipement informatique",
    "sg:phone":"+32 57 21 83 18",
    "sg:postcode":"8900",
    "sg:province":"West-Vlaanderen",
    "wof:name":"Advanced Projects & Prod.",
    "wof:placetype":"venue"
},
  "geometry": {"coordinates":[2.8903639317,50.8559799194],"type":"Point"}
}