{
  "type": "Feature",
  "properties": {
    "addr:full":"Stapstraat 7 Ranst (emblem) Antwerpen 2520",
    "addr:housenumber":"7",
    "addr:postcode":"2520",
    "addr:street":"Stapstraat",
    "iso:country":"BE",
    "sg:address":"Stapstraat 7",
    "sg:city":"Ranst (emblem)",
    "sg:classifiers":[
        {
            "category":"Shopping",
            "subcategory":"Clothing, Apparel, & Fashions",
            "type":"Retail Goods"
        }
    ],
    "sg:phone":"+32 3 489 35 13",
    "sg:postcode":"2520",
    "sg:province":"Antwerpen",
    "sg:tags":[
        "clothing",
        "-",
        "motorbike",
        "equipment"
    ],
    "wof:name":"Mjk-motorsport Imports",
    "wof:placetype":"venue"
},
  "geometry": {"coordinates":[4.6029839516,51.1628990173],"type":"Point"}
}