{
  "type": "Feature",
  "properties": {
    "addr:full":"Beelshoek 39 Ingelmunster West-Vlaanderen 8770",
    "addr:housenumber":"39",
    "addr:postcode":"8770",
    "addr:street":"Beelshoek",
    "iso:country":"BE",
    "sg:address":"Beelshoek 39",
    "sg:city":"Ingelmunster",
    "sg:orig_category":"Groententeelt",
    "sg:phone":"+32 56 66 76 80",
    "sg:postcode":"8770",
    "sg:province":"West-Vlaanderen",
    "wof:name":"Rogier Pickavet",
    "wof:placetype":"venue"
},
  "geometry": {"coordinates":[3.2920429707,50.9203796387],"type":"Point"}
}