{
  "type": "Feature",
  "properties": {
    "iso:country":"BE",
    "sg:address":"Onze-lieve-vrouwplein 62",
    "sg:city":"Herent",
    "sg:classifiers":[
        {
            "category":"Bakery",
            "type":"Food & Drink"
        }
    ],
    "sg:phone":"+32 16 20 41 96",
    "sg:postcode":"3020",
    "sg:province":"Vlaams-Brabant",
    "sg:tags":[
        "confectioner",
        "baker"
    ],
    "wof:name":"Stevens L",
    "wof:placetype":"venue"
},
  "geometry": {"coordinates":[4.6735091209,50.9071006775],"type":"Point"}
}