{
  "type": "Feature",
  "properties": {
    "addr:full":"Veldlaan 24 Overijse Vlaams-Brabant 3090",
    "addr:housenumber":"24",
    "addr:postcode":"3090",
    "addr:street":"Veldlaan",
    "iso:country":"BE",
    "sg:address":"Veldlaan 24",
    "sg:city":"Overijse",
    "sg:classifiers":[
        {
            "category":"Wholesale",
            "subcategory":"Meat",
            "type":"Manufacturing & Wholesale Goods"
        }
    ],
    "sg:phone":"+32 2 687 54 69",
    "sg:postcode":"3090",
    "sg:province":"Vlaams-Brabant",
    "sg:tags":[
        "machine",
        "product",
        "-",
        "supply"
    ],
    "wof:name":"Goossens Jean-pierre & Co Nv",
    "wof:placetype":"venue"
},
  "geometry": {"coordinates":[4.5648851395,50.7598114014],"type":"Point"}
}