{
  "type": "Feature",
  "properties": {
    "iso:country":"BE",
    "sg:address":"Langeheidestraat 21",
    "sg:city":"Huldenberg (ottenburg)",
    "sg:classifiers":[
        {
            "category":"Professional",
            "subcategory":"Accounting & Tax Preparation",
            "type":"Services"
        }
    ],
    "sg:phone":"+32 16 47 40 73",
    "sg:postcode":"3040",
    "sg:province":"Vlaams-Brabant",
    "sg:tags":[
        "bookkeeper"
    ],
    "wof:name":"Houyoux F",
    "wof:placetype":"venue"
},
  "geometry": {"coordinates":[4.6269831657,50.7502326965],"type":"Point"}
}