{
  "type": "Feature",
  "properties": {
    "addr:full":"Kievittenstraat 4 Knokke-heist West-Vlaanderen 8300",
    "addr:housenumber":"4",
    "addr:postcode":"8300",
    "addr:street":"Kievittenstraat",
    "iso:country":"BE",
    "sg:address":"Kievittenstraat 4",
    "sg:city":"Knokke-heist",
    "sg:classifiers":[
        {
            "category":"Recreation",
            "type":"Entertainment"
        }
    ],
    "sg:phone":"+32 50 60 64 42",
    "sg:postcode":"8300",
    "sg:province":"West-Vlaanderen",
    "sg:tags":[
        "diver",
        "amusement"
    ],
    "wof:name":"Magische Club",
    "wof:placetype":"venue"
},
  "geometry": {"coordinates":[3.287694931,51.3467254639],"type":"Point"}
}