{
  "type": "Feature",
  "properties": {
    "iso:country":"BE",
    "sg:address":"Rue Saint-etienne 17",
    "sg:city":"Marche-en-famenne",
    "sg:orig_category":"Landmeters",
    "sg:phone":"+32 84 31 24 08",
    "sg:postcode":"6900",
    "sg:province":"Luxembourg",
    "wof:name":"Claude Delvigne",
    "wof:placetype":"venue"
},
  "geometry": {"coordinates":[5.3331899643,50.2054748535],"type":"Point"}
}