{
  "type": "Feature",
  "properties": {
    "iso:country":"BE",
    "sg:address":"Troonstraat 18",
    "sg:city":"Maasmechelen",
    "sg:classifiers":[
        {
            "category":"Health Services",
            "subcategory":"Health Practitioner",
            "type":"Services"
        }
    ],
    "sg:phone":"+32 89 76 22 92",
    "sg:postcode":"3630",
    "sg:province":"Limburg",
    "sg:tags":[
        "therapist",
        "speech"
    ],
    "wof:name":"Logopediepraktijk Gorissen V",
    "wof:placetype":"venue"
},
  "geometry": {"coordinates":[5.70206213,50.959072113],"type":"Point"}
}