{
  "type": "Feature",
  "properties": {
    "iso:country":"BE",
    "sg:address":"Dendermondse Steenweg 75b",
    "sg:city":"Aalst",
    "sg:classifiers":[
        {
            "category":"Shopping",
            "subcategory":"Used Merchandise",
            "type":"Retail Goods"
        }
    ],
    "sg:phone":"+32 53 75 01 75",
    "sg:postcode":"9300",
    "sg:province":"Oost-Vlaanderen",
    "sg:tags":[
        "salvage",
        "surplus"
    ],
    "wof:name":"Paint & Go",
    "wof:placetype":"venue"
},
  "geometry": {"coordinates":[4.0465779305,50.9505729675],"type":"Point"}
}