{
  "type": "Feature",
  "properties": {
    "iso:country":"BE",
    "sg:address":"Deken Degryselaan 61",
    "sg:city":"Kortrijk",
    "sg:orig_category":"Apotheken",
    "sg:phone":"+32 56 21 66 87",
    "sg:postcode":"8500",
    "sg:province":"West-Vlaanderen",
    "wof:name":"Hans Sintobin",
    "wof:placetype":"venue"
},
  "geometry": {"coordinates":[3.281922102,50.8236427307],"type":"Point"}
}