{
  "type": "Feature",
  "properties": {
    "addr:full":"Industrielaan 3 Hoeselt Limburg 3730",
    "addr:housenumber":"3",
    "addr:postcode":"3730",
    "addr:street":"Industrielaan",
    "iso:country":"BE",
    "sg:address":"Industrielaan 3",
    "sg:city":"Hoeselt",
    "sg:classifiers":[
        {
            "category":"Communications",
            "subcategory":"Film & Video Production",
            "type":"Services"
        }
    ],
    "sg:phone":"+32 89 51 91 91",
    "sg:postcode":"3730",
    "sg:province":"Limburg",
    "sg:tags":[
        "warehouse",
        "storage",
        "cold",
        "-"
    ],
    "wof:name":"King Transport Sa",
    "wof:placetype":"venue"
},
  "geometry": {"coordinates":[5.4952301979,50.8581008911],"type":"Point"}
}