{
  "type": "Feature",
  "properties": {
    "addr:full":"Bokmolenstraat 8 Temse Oost-Vlaanderen 9140",
    "addr:housenumber":"8",
    "addr:postcode":"9140",
    "addr:street":"Bokmolenstraat",
    "iso:country":"BE",
    "sg:address":"Bokmolenstraat 8",
    "sg:city":"Temse",
    "sg:orig_category":"Installatie van houten of kunststof schrijnwerk",
    "sg:phone":"+32 52 46 04 67",
    "sg:postcode":"9140",
    "sg:province":"Oost-Vlaanderen",
    "wof:name":"Norbert Durinck",
    "wof:placetype":"venue"
},
  "geometry": {"coordinates":[4.1360139847,51.1149635315],"type":"Point"}
}