{
  "type": "Feature",
  "properties": {
    "iso:country":"BE",
    "sg:address":"Rue De P\u00c2turages 89",
    "sg:city":"Quevy",
    "sg:orig_category":"Forge, Moulage and Profilage des M\u00e9taux",
    "sg:phone":"+32 65 58 67 94",
    "sg:postcode":"7041",
    "sg:province":"Hainaut",
    "wof:name":"Vdv Soudage",
    "wof:placetype":"venue"
},
  "geometry": {"coordinates":[4.0217518806,50.3789329529],"type":"Point"}
}