{
  "type": "Feature",
  "properties": {
    "iso:country":"BE",
    "sg:address":"Bredabaan 746",
    "sg:city":"Wuustwezel",
    "sg:orig_category":"Electrom\u00e9nager, t\u00e9l\u00e9visions and radios",
    "sg:phone":"+32 3 633 01 16",
    "sg:postcode":"2990",
    "sg:province":"Antwerpen",
    "wof:name":"Johannes Dekkers",
    "wof:placetype":"venue"
},
  "geometry": {"coordinates":[4.5548419952,51.3602523804],"type":"Point"}
}