{
  "type": "Feature",
  "properties": {
    "addr:full":"Rue Lens 20 Bruxelles (ixelles) Bruxelles-Capitale 1050",
    "addr:housenumber":"20",
    "addr:postcode":"1050",
    "addr:street":"Rue Lens",
    "iso:country":"BE",
    "sg:address":"Rue Lens 20",
    "sg:city":"Bruxelles (ixelles)",
    "sg:classifiers":[
        {
            "category":"Health Services",
            "subcategory":"Health Practitioner",
            "type":"Services"
        }
    ],
    "sg:phone":"+32 2 648 22 54",
    "sg:postcode":"1050",
    "sg:province":"Bruxelles-Capitale",
    "sg:tags":[
        "physiotherapist"
    ],
    "wof:name":"De Keyser L",
    "wof:placetype":"venue"
},
  "geometry": {"coordinates":[4.3657398224,50.8271026611],"type":"Point"}
}