{
  "type": "Feature",
  "properties": {
    "addr:full":"Rue Alphonse Lenoir 17 Leuze-en-hainaut Hainaut 7900",
    "addr:housenumber":"17",
    "addr:postcode":"7900",
    "addr:street":"Rue Alphonse Lenoir",
    "iso:country":"BE",
    "sg:address":"Rue Alphonse Lenoir 17",
    "sg:city":"Leuze-en-hainaut",
    "sg:orig_category":"Salles de conf\u00e9rences and de r\u00e9ceptions",
    "sg:phone":"+32 69 66 28 76",
    "sg:postcode":"7900",
    "sg:province":"Hainaut",
    "wof:name":"Ch\u00c2teau De Grandmetz",
    "wof:placetype":"venue"
},
  "geometry": {"coordinates":[3.6228199005,50.5999794006],"type":"Point"}
}