{
  "type": "Feature",
  "properties": {
    "iso:country":"BE",
    "sg:address":"Rijksweg 15a",
    "sg:city":"Bornem",
    "sg:classifiers":[
        {
            "category":"Wholesale",
            "subcategory":"Wine & Distilled Alcoholic Beverages",
            "type":"Manufacturing & Wholesale Goods"
        }
    ],
    "sg:phone":"+32 3 889 74 12",
    "sg:postcode":"2880",
    "sg:province":"Antwerpen",
    "sg:tags":[
        "whol",
        "-",
        "spirit",
        "mfg"
    ],
    "wof:name":"Interwine Bvba",
    "wof:placetype":"venue"
},
  "geometry": {"coordinates":[4.2638149261,51.0936470032],"type":"Point"}
}