{
  "type": "Feature",
  "properties": {
    "addr:full":"Gevaertlaan 49 Westerlo Antwerpen 2260",
    "addr:housenumber":"49",
    "addr:postcode":"2260",
    "addr:street":"Gevaertlaan",
    "iso:country":"BE",
    "sg:address":"Gevaertlaan 49",
    "sg:city":"Westerlo",
    "sg:orig_category":"Kapsalons",
    "sg:phone":"+32 14 54 58 29",
    "sg:postcode":"2260",
    "sg:province":"Antwerpen",
    "wof:name":"Coiffure Gwennie",
    "wof:placetype":"venue"
},
  "geometry": {"coordinates":[4.8619451523,51.0881729126],"type":"Point"}
}