{
  "type": "Feature",
  "properties": {
    "addr:full":"Avenue Eug\u00c8ne Mascaux 124 Charleroi Hainaut 6001",
    "addr:housenumber":"124",
    "addr:postcode":"6001",
    "addr:street":"Avenue Euge\u0300Ne Mascaux;Hainaut",
    "iso:country":"BE",
    "sg:address":"Avenue Eug\u00c8ne Mascaux 124",
    "sg:city":"Charleroi",
    "sg:orig_category":"Foto-uitrusting Fotografen and fotostudio's",
    "sg:phone":"+32 71 43 43 92",
    "sg:postcode":"6001",
    "sg:province":"Hainaut",
    "wof:name":"Art Color (pro-labo-photo)",
    "wof:placetype":"venue"
},
  "geometry": {"coordinates":[4.4439640045,50.3968315125],"type":"Point"}
}