{
  "type": "Feature",
  "properties": {
    "iso:country":"BE",
    "sg:address":"Boulevard D'ypres 20",
    "sg:city":"Bruxelles",
    "sg:classifiers":[
        {
            "category":"Home & Garden",
            "subcategory":"Kitchen Supply",
            "type":"Retail Goods"
        }
    ],
    "sg:phone":"+32 2 223 00 87",
    "sg:postcode":"1000",
    "sg:province":"Bruxelles-Capitale",
    "sg:tags":[
        "installation"
    ],
    "wof:name":"Kitchen By Kitchen",
    "wof:placetype":"venue"
},
  "geometry": {"coordinates":[4.3466391563,50.8560333252],"type":"Point"}
}