{
  "type": "Feature",
  "properties": {
    "addr:full":"Rue De Molenbeek 105-109 Bruxelles Bruxelles-Capitale 1020",
    "addr:postcode":"105-109;1020",
    "addr:street":"Rue De Molenbeek",
    "iso:country":"BE",
    "sg:address":"Rue De Molenbeek 105-109",
    "sg:city":"Bruxelles",
    "sg:classifiers":[
        {
            "category":"Utilities",
            "subcategory":"Mobile Phone",
            "type":"Services"
        }
    ],
    "sg:phone":"+32 2 425 49 15",
    "sg:postcode":"1020",
    "sg:province":"Bruxelles-Capitale",
    "sg:tags":[
        "access",
        "gsm",
        "-",
        "apparatus"
    ],
    "wof:name":"Elveren Sa",
    "wof:placetype":"venue"
},
  "geometry": {"coordinates":[4.3549590111,50.8742485046],"type":"Point"}
}