{
  "type": "Feature",
  "properties": {
    "addr:full":"Rue Provinciale 65 Celles Hainaut 7760",
    "addr:housenumber":"65",
    "addr:postcode":"7760",
    "addr:street":"Rue Provinciale",
    "iso:country":"BE",
    "sg:address":"Rue Provinciale 65",
    "sg:city":"Celles",
    "sg:classifiers":[
        {
            "category":"Personal",
            "subcategory":"Beauty Salon",
            "type":"Services"
        }
    ],
    "sg:phone":"+32 69 45 48 03",
    "sg:postcode":"7760",
    "sg:province":"Hainaut",
    "sg:tags":[
        "de",
        "coiffure"
    ],
    "wof:name":"Eveline Soyez",
    "wof:placetype":"venue"
},
  "geometry": {"coordinates":[3.4587600231,50.7127494812],"type":"Point"}
}