{
  "type": "Feature",
  "properties": {
    "addr:full":"Rue Du Faing 14 Chiny Luxembourg 6810",
    "addr:housenumber":"14",
    "addr:postcode":"6810",
    "addr:street":"Rue Du Faing",
    "iso:country":"BE",
    "sg:address":"Rue Du Faing 14",
    "sg:city":"Chiny",
    "sg:orig_category":"Installation de menuiserie m\u00e9tallique. Rev\u00eatements pour sols and murs. B\u00e9ton pr\u00eat \u00e0 l'emploi Fab. Ma",
    "sg:phone":"+32 61 31 15 20",
    "sg:postcode":"6810",
    "sg:province":"Luxembourg",
    "wof:name":"Goffette",
    "wof:placetype":"venue"
},
  "geometry": {"coordinates":[5.3405580521,49.7382736206],"type":"Point"}
}