{
  "type": "Feature",
  "properties": {
    "iso:country":"BE",
    "sg:address":"Place Peter Benoit 38",
    "sg:city":"Bruxelles",
    "sg:classifiers":[
        {
            "category":"Shopping",
            "subcategory":"Computers & Home Electronics",
            "type":"Retail Goods"
        }
    ],
    "sg:phone":"+32 2 268 38 62",
    "sg:postcode":"1120",
    "sg:province":"Bruxelles-Capitale",
    "sg:tags":[
        "personal",
        "-",
        "processing",
        "data"
    ],
    "wof:name":"I.n.s. Bvba-sprl",
    "wof:placetype":"venue"
},
  "geometry": {"coordinates":[4.3888292313,50.8955039978],"type":"Point"}
}