{
  "type": "Feature",
  "properties": {
    "iso:country":"BE",
    "sg:address":"Arenbergstraat 16",
    "sg:city":"Antwerpen",
    "sg:orig_category":"Antiquit\u00e9s",
    "sg:phone":"+32 3 232 05 67",
    "sg:postcode":"2000",
    "sg:province":"Antwerpen",
    "wof:name":"Edmond Golbert Zagrai",
    "wof:placetype":"venue"
},
  "geometry": {"coordinates":[4.4065961838,51.2151374817],"type":"Point"}
}