{
  "type": "Feature",
  "properties": {
    "addr:full":"Rue De Jemeppe 215 Ans (loncin) Li\u00e8ge 4431",
    "addr:housenumber":"215",
    "addr:postcode":"4431",
    "addr:street":"Rue De Jemeppe",
    "iso:country":"BE",
    "sg:address":"Rue De Jemeppe 215",
    "sg:city":"Ans (loncin)",
    "sg:classifiers":[
        {
            "category":"Home & Garden",
            "subcategory":"Carpets & Floor Coverings",
            "type":"Retail Goods"
        }
    ],
    "sg:phone":"+32 4 246 43 62",
    "sg:postcode":"4431",
    "sg:province":"Li\u00e8ge",
    "sg:tags":[
        "tile"
    ],
    "wof:name":"Di Stefano",
    "wof:placetype":"venue"
},
  "geometry": {"coordinates":[5.4978098869,50.6602630615],"type":"Point"}
}