{
  "type": "Feature",
  "properties": {
    "addr:full":"Eikstraat 4 Aalst Oost-Vlaanderen 9300",
    "addr:housenumber":"4",
    "addr:postcode":"9300",
    "addr:street":"Eikstraat",
    "iso:country":"BE",
    "sg:address":"Eikstraat 4",
    "sg:city":"Aalst",
    "sg:orig_category":"Technisch and beroeps secundair onderwijs",
    "sg:phone":"+32 53 77 86 57",
    "sg:postcode":"9300",
    "sg:province":"Oost-Vlaanderen",
    "wof:name":"St.lutgardisinstituut",
    "wof:placetype":"venue"
},
  "geometry": {"coordinates":[4.0375170708,50.9327583313],"type":"Point"}
}