{
  "type": "Feature",
  "properties": {
    "addr:full":"Place Des Bienfaiteurs 20 Schaarbeek/schaerbeek Bruxelles-Capitale 1030",
    "addr:housenumber":"20",
    "addr:postcode":"1030",
    "addr:street":"Place Des Bienfaiteurs",
    "iso:country":"BE",
    "sg:address":"Place Des Bienfaiteurs 20",
    "sg:city":"Schaarbeek/schaerbeek",
    "sg:orig_category":"RESTAURANTS: CAF\u00c9S",
    "sg:phone":"+32 2 245 90 66",
    "sg:postcode":"1030",
    "sg:province":"Bruxelles-Capitale",
    "wof:name":"Taverne Le Galion",
    "wof:placetype":"venue"
},
  "geometry": {"coordinates":[4.3848929405,50.8581390381],"type":"Point"}
}