{
  "type": "Feature",
  "properties": {
    "addr:full":"Rue Africaine 27 Bruxelles (saint-gilles) Bruxelles-Capitale 1060",
    "addr:housenumber":"27",
    "addr:postcode":"1060",
    "addr:street":"Rue Africaine",
    "iso:country":"BE",
    "sg:address":"Rue Africaine 27",
    "sg:city":"Bruxelles (saint-gilles)",
    "sg:classifiers":[
        {
            "category":"Real Estate",
            "subcategory":"Architect",
            "type":"Services"
        }
    ],
    "sg:phone":"+32 2 534 35 05",
    "sg:postcode":"1060",
    "sg:province":"Bruxelles-Capitale",
    "wof:name":"Terlinden B",
    "wof:placetype":"venue"
},
  "geometry": {"coordinates":[4.3571572304,50.8246040344],"type":"Point"}
}