{
  "type": "Feature",
  "properties": {
    "addr:full":"Rue Bonne-nouvelle 84 Li\u00c8ge Li\u00e8ge 4000",
    "addr:housenumber":"84",
    "addr:postcode":"4000",
    "addr:street":"Rue Bonne-Nouvelle",
    "iso:country":"BE",
    "sg:address":"Rue Bonne-nouvelle 84",
    "sg:city":"Li\u00c8ge",
    "sg:orig_category":"M\u00e9decins and sp\u00e9cialistes",
    "sg:phone":"+32 4 227 28 70",
    "sg:postcode":"4000",
    "sg:province":"Li\u00e8ge",
    "wof:name":"Pierre Zaeytydt",
    "wof:placetype":"venue"
},
  "geometry": {"coordinates":[5.597823143,50.654460907],"type":"Point"}
}