{
  "type": "Feature",
  "properties": {
    "iso:country":"BE",
    "sg:address":"Grondwetlaan 9",
    "sg:city":"Gent",
    "sg:orig_category":"Diverse kredietdiensten",
    "sg:postcode":"9040",
    "sg:province":"Oost-Vlaanderen",
    "wof:name":"Bancontact-mister Cash",
    "wof:placetype":"venue"
},
  "geometry": {"coordinates":[3.7527480125,51.0661048889],"type":"Point"}
}