{
  "type": "Feature",
  "properties": {
    "addr:full":"Kuipersakkerstraat 147 Schoten Antwerpen 2900",
    "addr:housenumber":"147",
    "addr:postcode":"2900",
    "addr:street":"Kuipersakkerstraat",
    "iso:country":"BE",
    "sg:address":"Kuipersakkerstraat 147",
    "sg:city":"Schoten",
    "sg:classifiers":[
        {
            "category":"Wholesale",
            "subcategory":"Wine & Distilled Alcoholic Beverages",
            "type":"Manufacturing & Wholesale Goods"
        }
    ],
    "sg:phone":"+32 3 658 18 35",
    "sg:postcode":"2900",
    "sg:province":"Antwerpen",
    "sg:tags":[
        "whol",
        "-",
        "spirit",
        "mfg"
    ],
    "wof:name":"Vinotr@de",
    "wof:placetype":"venue"
},
  "geometry": {"coordinates":[4.5111508369,51.2485198975],"type":"Point"}
}