{
  "type": "Feature",
  "properties": {
    "addr:full":"Albert I Laan 171a Nieuwpoort West-Vlaanderen 8620",
    "addr:housenumber":"171a",
    "addr:postcode":"8620",
    "addr:street":"Albert I Laan",
    "iso:country":"BE",
    "sg:address":"Albert I Laan 171a",
    "sg:city":"Nieuwpoort",
    "sg:classifiers":[
        {
            "category":"Shopping",
            "subcategory":"Shoes",
            "type":"Retail Goods"
        }
    ],
    "sg:phone":"+32 58 23 51 96",
    "sg:postcode":"8620",
    "sg:province":"West-Vlaanderen",
    "sg:tags":[
        "slipper",
        "-"
    ],
    "wof:name":"Verdievel W",
    "wof:placetype":"venue"
},
  "geometry": {"coordinates":[2.7191340923,51.1495361328],"type":"Point"}
}