{
  "type": "Feature",
  "properties": {
    "iso:country":"BE",
    "sg:address":"Vennestraat 36",
    "sg:city":"Genk",
    "sg:orig_category":"Fitnesscentra",
    "sg:phone":"+32 89 35 09 84",
    "sg:postcode":"3600",
    "sg:province":"Limburg",
    "wof:name":"Eurogym",
    "wof:placetype":"venue"
},
  "geometry": {"coordinates":[5.4959602356,50.9827690125],"type":"Point"}
}