{
  "type": "Feature",
  "properties": {
    "addr:full":"Avenue Du Pont De Luttre 73 Bruxelles (forest) Bruxelles-Capitale 1190",
    "addr:housenumber":"73",
    "addr:postcode":"1190",
    "addr:street":"Avenue Du Pont De Luttre",
    "iso:country":"BE",
    "sg:address":"Avenue Du Pont De Luttre 73",
    "sg:city":"Bruxelles (forest)",
    "sg:classifiers":[
        {
            "category":"Professional",
            "subcategory":"Testing Lab",
            "type":"Services"
        }
    ],
    "sg:phone":"+32 2 344 84 59",
    "sg:postcode":"1190",
    "sg:province":"Bruxelles-Capitale",
    "sg:tags":[
        "chemist"
    ],
    "wof:name":"Pharmacie Du Pont De Luttre",
    "wof:placetype":"venue"
},
  "geometry": {"coordinates":[4.3229031563,50.8221969604],"type":"Point"}
}