{
  "type": "Feature",
  "properties": {
    "iso:country":"BE",
    "sg:address":"Chauss\u00c9e De Tubize 206",
    "sg:city":"Wauthier-braine",
    "sg:classifiers":[
        {
            "category":"Restaurant",
            "type":"Food & Drink"
        }
    ],
    "sg:phone":"+32 2 366 09 02",
    "sg:postcode":"1440",
    "sg:province":"Brabant Wallon",
    "wof:name":"Castelli Romani",
    "wof:placetype":"venue"
},
  "geometry": {"coordinates":[4.3138189316,50.6881713867],"type":"Point"}
}