{
  "type": "Feature",
  "properties": {
    "addr:full":"Lessensestraat 5 Geraardsbergen Oost-Vlaanderen 9500",
    "addr:housenumber":"5",
    "addr:postcode":"9500",
    "addr:street":"Lessensestraat",
    "iso:country":"BE",
    "sg:address":"Lessensestraat 5",
    "sg:city":"Geraardsbergen",
    "sg:orig_category":"Geschenken and souvenirs Verlichting and huishoudartikelen",
    "sg:phone":"+32 54 41 05 48",
    "sg:postcode":"9500",
    "sg:province":"Oost-Vlaanderen",
    "wof:name":"Casa",
    "wof:placetype":"venue"
},
  "geometry": {"coordinates":[3.8758969307,50.7715873718],"type":"Point"}
}