{
  "type": "Feature",
  "properties": {
    "addr:full":"Kapellei 186 Zoersel Antwerpen 2980",
    "addr:housenumber":"186",
    "addr:postcode":"2980",
    "addr:street":"Kapellei",
    "iso:country":"BE",
    "sg:address":"Kapellei 186",
    "sg:city":"Zoersel",
    "sg:orig_category":"V\u00eatements",
    "sg:phone":"+32 3 384 02 14",
    "sg:postcode":"2980",
    "sg:province":"Antwerpen",
    "wof:name":"Marc Furs",
    "wof:placetype":"venue"
},
  "geometry": {"coordinates":[4.6225581169,51.2571105957],"type":"Point"}
}