{
  "type": "Feature",
  "properties": {
    "addr:full":"Baasrodestraat 143a Lebbeke Oost-Vlaanderen 9280",
    "addr:housenumber":"143a",
    "addr:postcode":"9280",
    "addr:street":"Baasrodestraat",
    "iso:country":"BE",
    "sg:address":"Baasrodestraat 143a",
    "sg:city":"Lebbeke",
    "sg:classifiers":[
        {
            "category":"Building & Trades",
            "subcategory":"Construction",
            "type":"Services"
        }
    ],
    "sg:phone":"+32 52 41 18 40",
    "sg:postcode":"9280",
    "sg:province":"Oost-Vlaanderen",
    "sg:tags":[
        "carpenter"
    ],
    "wof:name":"De Vriendt G",
    "wof:placetype":"venue"
},
  "geometry": {"coordinates":[4.1449079514,51.014629364],"type":"Point"}
}