{
  "type": "Feature",
  "properties": {
    "iso:country":"BE",
    "sg:address":"Verbrande Brugsesteenweg 145",
    "sg:city":"Grimbergen",
    "sg:classifiers":[
        {
            "category":"Home & Garden",
            "subcategory":"Home Furnishings",
            "type":"Retail Goods"
        }
    ],
    "sg:phone":"+32 2 253 65 80",
    "sg:postcode":"1850",
    "sg:province":"Vlaams-Brabant",
    "sg:tags":[
        "interior",
        "decoration"
    ],
    "wof:name":"Eulexis",
    "wof:placetype":"venue"
},
  "geometry": {"coordinates":[4.4110321999,50.9459724426],"type":"Point"}
}