{
  "type": "Feature",
  "properties": {
    "iso:country":"BE",
    "sg:address":"Rue W. Dew\u00c9 30",
    "sg:city":"Liege",
    "sg:orig_category":"M\u00e9decines alternatives",
    "sg:phone":"+32 4 227 72 07",
    "sg:postcode":"4000",
    "sg:province":"Li\u00e8ge",
    "wof:name":"Maloir Didier",
    "wof:placetype":"venue"
},
  "geometry": {"coordinates":[5.5950188637,50.6631546021],"type":"Point"}
}