{
  "type": "Feature",
  "properties": {
    "addr:full":"Vlierstraat 3 Gent Oost-Vlaanderen 9000",
    "addr:housenumber":"3",
    "addr:postcode":"9000",
    "addr:street":"Vlierstraat;Oost-Vlaanderen",
    "iso:country":"BE",
    "sg:address":"Vlierstraat 3",
    "sg:city":"Gent",
    "sg:classifiers":[
        {
            "category":"Health Services",
            "subcategory":"Doctor",
            "type":"Services"
        }
    ],
    "sg:phone":"+32 9 222 65 24",
    "sg:postcode":"9000",
    "sg:province":"Oost-Vlaanderen",
    "sg:tags":[
        "psychotherapist",
        "psychoanalyst"
    ],
    "wof:name":"Martein R",
    "wof:placetype":"venue"
},
  "geometry": {"coordinates":[3.7260229588,51.0342788696],"type":"Point"}
}