{
  "type": "Feature",
  "properties": {
    "iso:country":"BE",
    "sg:address":"Oude Koornmarkt 59",
    "sg:city":"Antwerpen",
    "sg:classifiers":[
        {
            "category":"Restaurant",
            "type":"Food & Drink"
        }
    ],
    "sg:phone":"+32 3 226 43 42",
    "sg:postcode":"2000",
    "sg:province":"Antwerpen",
    "wof:name":"Garden Of India",
    "wof:placetype":"venue"
},
  "geometry": {"coordinates":[4.4006829262,51.2194213867],"type":"Point"}
}