{
  "type": "Feature",
  "properties": {
    "addr:full":"Rue De Herstal 41 Oupeye (herm\u00e9e) Li\u00e8ge 4680",
    "addr:housenumber":"41",
    "addr:postcode":"4680",
    "addr:street":"Rue De Herstal",
    "iso:country":"BE",
    "sg:address":"Rue De Herstal 41",
    "sg:city":"Oupeye (herm\u00e9e)",
    "sg:classifiers":[
        {
            "category":"Professional",
            "subcategory":"Management & Consulting",
            "type":"Services"
        }
    ],
    "sg:phone":"+32 4 278 49 54",
    "sg:postcode":"4680",
    "sg:province":"Li\u00e8ge",
    "sg:tags":[
        "tax-consultants"
    ],
    "wof:name":"Theunissen J",
    "wof:placetype":"venue"
},
  "geometry": {"coordinates":[5.6444120407,50.7089729309],"type":"Point"}
}