{
  "type": "Feature",
  "properties": {
    "iso:country":"BE",
    "sg:address":"Rue De Bruxelles 57",
    "sg:city":"Edingen/enghien",
    "sg:classifiers":[
        {
            "category":"Cafe",
            "type":"Food & Drink"
        }
    ],
    "sg:phone":"+32 2 395 74 24",
    "sg:postcode":"7850",
    "sg:province":"Hainaut",
    "sg:tags":[
        "caf\u00e9s"
    ],
    "wof:name":"Dehaen-mosselmans",
    "wof:placetype":"venue"
},
  "geometry": {"coordinates":[4.0415639877,50.6945571899],"type":"Point"}
}