{
  "type": "Feature",
  "properties": {
    "addr:full":"Pl Albert I 2 Sambreville Namur 5060",
    "addr:housenumber":"2",
    "addr:postcode":"5060",
    "addr:street":"Pl Albert I",
    "iso:country":"BE",
    "sg:address":"Pl Albert I 2",
    "sg:city":"Sambreville",
    "sg:orig_category":"Kapsalons",
    "sg:phone":"+32 71 77 52 22",
    "sg:postcode":"5060",
    "sg:province":"Namur",
    "wof:name":"Coiffure Jos\u00c9-walry",
    "wof:placetype":"venue"
},
  "geometry": {"coordinates":[4.6213169098,50.4186019897],"type":"Point"}
}