{
  "type": "Feature",
  "properties": {
    "iso:country":"BE",
    "sg:address":"Chemin De La Brire 5",
    "sg:city":"Lasne (ohain)",
    "sg:classifiers":[
        {
            "category":"Home & Garden",
            "subcategory":"Hardware",
            "type":"Retail Goods"
        }
    ],
    "sg:phone":"+32 2 653 85 54",
    "sg:postcode":"1380",
    "sg:province":"Brabant Wallon",
    "sg:tags":[
        "machine",
        "horticultural"
    ],
    "wof:name":"Van Den Abeele",
    "wof:placetype":"venue"
},
  "geometry": {"coordinates":[4.4887461662,50.6988105774],"type":"Point"}
}