{
  "type": "Feature",
  "properties": {
    "addr:full":"Oostmoerstraat 45 Jabbeke (snellegem) West-Vlaanderen 8490",
    "addr:housenumber":"45",
    "addr:postcode":"8490",
    "addr:street":"Oostmoerstraat",
    "iso:country":"BE",
    "sg:address":"Oostmoerstraat 45",
    "sg:city":"Jabbeke (snellegem)",
    "sg:classifiers":[
        {
            "category":"Health Services",
            "subcategory":"Doctor",
            "type":"Services"
        }
    ],
    "sg:phone":"+32 50 81 53 20",
    "sg:postcode":"8490",
    "sg:province":"West-Vlaanderen",
    "sg:tags":[
        "medicinephysicians",
        "surgeon"
    ],
    "wof:name":"Cochez Alfons",
    "wof:placetype":"venue"
},
  "geometry": {"coordinates":[3.1365399361,51.1659812927],"type":"Point"}
}