{
  "type": "Feature",
  "properties": {
    "iso:country":"BE",
    "sg:address":"Nieuwstraat 48",
    "sg:city":"Asse",
    "sg:orig_category":"Newspapers, magazines, periodicals - Distribution",
    "sg:phone":"+32 2 452 62 26",
    "sg:postcode":"1730",
    "sg:province":"Vlaams-Brabant",
    "wof:name":"Geert",
    "wof:placetype":"venue"
},
  "geometry": {"coordinates":[4.1943187714,50.9102516174],"type":"Point"}
}