{
  "type": "Feature",
  "properties": {
    "addr:full":"Av Louise 135 Bruxelles Bruxelles-Capitale 1050",
    "addr:housenumber":"135",
    "addr:postcode":"1050",
    "addr:street":"Av Louise",
    "iso:country":"BE",
    "sg:address":"Av Louise 135",
    "sg:city":"Bruxelles",
    "sg:orig_category":"Kapsalons",
    "sg:phone":"+32 2 534 00 14",
    "sg:postcode":"1050",
    "sg:province":"Bruxelles-Capitale",
    "wof:name":"Rodolphe",
    "wof:placetype":"venue"
},
  "geometry": {"coordinates":[4.3610949516,50.8294067383],"type":"Point"}
}