{
  "type": "Feature",
  "properties": {
    "addr:full":"Gandastraat 57 Gent Oost-Vlaanderen 9000",
    "addr:housenumber":"57",
    "addr:postcode":"9000",
    "addr:street":"Gandastraat;Oost-Vlaanderen",
    "iso:country":"BE",
    "sg:address":"Gandastraat 57",
    "sg:city":"Gent",
    "sg:classifiers":[
        {
            "category":"Manufacturing",
            "subcategory":"Electronics",
            "type":"Manufacturing & Wholesale Goods"
        }
    ],
    "sg:phone":"+32 9 233 11 08",
    "sg:postcode":"9000",
    "sg:province":"Oost-Vlaanderen",
    "sg:tags":[
        "telecommunication",
        "system"
    ],
    "wof:name":"Alcatel Networks",
    "wof:placetype":"venue"
},
  "geometry": {"coordinates":[3.7392399311,51.0539512634],"type":"Point"}
}