{
  "type": "Feature",
  "properties": {
    "addr:full":"Rue Fran\u00c7ois Libert 28 Waterloo Brabant Wallon 1410",
    "addr:housenumber":"28",
    "addr:postcode":"1410",
    "addr:street":"Rue Franc\u0327Ois Libert",
    "iso:country":"BE",
    "sg:address":"Rue Fran\u00c7ois Libert 28",
    "sg:city":"Waterloo",
    "sg:orig_category":"Werk and personeelsselectie",
    "sg:phone":"+32 2 352 99 55",
    "sg:postcode":"1410",
    "sg:province":"Brabant Wallon",
    "wof:name":"Ale",
    "wof:placetype":"venue"
},
  "geometry": {"coordinates":[4.3964591026,50.7153244019],"type":"Point"}
}