{
  "type": "Feature",
  "properties": {
    "iso:country":"BE",
    "sg:address":"Schautenstraat 250",
    "sg:city":"Maldegem",
    "sg:orig_category":"Rundveehouders",
    "sg:phone":"+32 50 71 17 44",
    "sg:postcode":"9990",
    "sg:province":"Oost-Vlaanderen",
    "wof:name":"Degrande",
    "wof:placetype":"venue"
},
  "geometry": {"coordinates":[3.4189839363,51.1952552795],"type":"Point"}
}