{
  "type": "Feature",
  "properties": {
    "addr:full":"Dronckaertstraat 434 Menen West-Vlaanderen 8930",
    "addr:housenumber":"434",
    "addr:postcode":"8930",
    "addr:street":"Dronckaertstraat",
    "iso:country":"BE",
    "sg:address":"Dronckaertstraat 434",
    "sg:city":"Menen",
    "sg:orig_category":"Kunststofrecipi\u00ebnten and -verpakkingen Fab",
    "sg:phone":"+32 56 41 25 76",
    "sg:postcode":"8930",
    "sg:province":"West-Vlaanderen",
    "wof:name":"Gherardyn Plastics",
    "wof:placetype":"venue"
},
  "geometry": {"coordinates":[3.1636819839,50.7693557739],"type":"Point"}
}