{
  "type": "Feature",
  "properties": {
    "addr:full":"Nervi\u00ebrsstraat 138 Box 1 Asse Vlaams-Brabant 1730",
    "addr:housenumber":"138;1",
    "addr:postcode":"1730",
    "addr:street":"Nervie\u0308Rsstraat;Box",
    "iso:country":"BE",
    "sg:address":"Nervi\u00ebrsstraat 138 Box 1",
    "sg:city":"Asse",
    "sg:classifiers":[
        {
            "category":"Food & Beverages",
            "subcategory":"Fruits & Vegetables",
            "type":"Retail Goods"
        }
    ],
    "sg:phone":"+32 474 75 62 78",
    "sg:postcode":"1730",
    "sg:province":"Vlaams-Brabant",
    "sg:tags":[
        "-"
    ],
    "wof:name":"Banana (la)",
    "wof:placetype":"venue"
},
  "geometry": {"coordinates":[4.1868400574,50.9189186096],"type":"Point"}
}