{
  "type": "Feature",
  "properties": {
    "addr:full":"Charlottalei 13 Antwerpen Antwerpen 2018",
    "addr:housenumber":"13",
    "addr:postcode":"2018",
    "addr:street":"Charlottalei",
    "iso:country":"BE",
    "sg:address":"Charlottalei 13",
    "sg:city":"Antwerpen",
    "sg:orig_category":"Pi\u00e8ces and accessoires de v\u00e9hicules automobiles Gr",
    "sg:phone":"+32 3 239 69 04",
    "sg:postcode":"2018",
    "sg:province":"Antwerpen",
    "wof:name":"Car Equipment",
    "wof:placetype":"venue"
},
  "geometry": {"coordinates":[4.4190001488,51.2088661194],"type":"Point"}
}