{
  "type": "Feature",
  "properties": {
    "iso:country":"BE",
    "sg:address":"Spangerede 20",
    "sg:city":"Destelbergen (heusden)",
    "sg:classifiers":[
        {
            "category":"Freight",
            "type":"Transportation"
        }
    ],
    "sg:phone":"+32 475 49 06 69",
    "sg:postcode":"9070",
    "sg:province":"Oost-Vlaanderen",
    "sg:tags":[
        "-",
        "transport"
    ],
    "wof:name":"Gilo Trans Cvba",
    "wof:placetype":"venue"
},
  "geometry": {"coordinates":[3.8036439419,51.0260848999],"type":"Point"}
}