{
  "type": "Feature",
  "properties": {
    "addr:full":"Large Voie 130 Herstal Li\u00e8ge 4040",
    "addr:housenumber":"130",
    "addr:postcode":"4040",
    "addr:street":"Large Voie",
    "iso:country":"BE",
    "sg:address":"Large Voie 130",
    "sg:city":"Herstal",
    "sg:classifiers":[
        {
            "category":"Fast Food",
            "type":"Food & Drink"
        }
    ],
    "sg:phone":"+32 4 264 56 50",
    "sg:postcode":"4040",
    "sg:province":"Li\u00e8ge",
    "sg:tags":[
        "\u00c0",
        "restaurants",
        "emporter",
        "restaurant"
    ],
    "wof:name":"Restaurant Cr\u00cate",
    "wof:placetype":"venue"
},
  "geometry": {"coordinates":[5.635433197,50.667350769],"type":"Point"}
}