{
  "type": "Feature",
  "properties": {
    "iso:country":"BE",
    "sg:address":"Markt 61b2",
    "sg:city":"Deinze",
    "sg:orig_category":"Pain, p\u00e2tisseries and confiseries",
    "sg:phone":"+32 9 386 11 87",
    "sg:postcode":"9800",
    "sg:province":"Oost-Vlaanderen",
    "wof:name":"Philippe Dhondt",
    "wof:placetype":"venue"
},
  "geometry": {"coordinates":[3.5262770653,50.9854469299],"type":"Point"}
}