{
  "type": "Feature",
  "properties": {
    "iso:country":"BE",
    "sg:address":"Rue De Saintes 11bb",
    "sg:city":"Nivelles",
    "sg:orig_category":"Librairies. Editeurs de livres",
    "sg:phone":"+32 67 84 09 61",
    "sg:postcode":"1400",
    "sg:province":"Brabant Wallon",
    "wof:name":"A Livre Ouvert",
    "wof:placetype":"venue"
},
  "geometry": {"coordinates":[4.325070858,50.5968894958],"type":"Point"}
}