{
  "type": "Feature",
  "properties": {
    "iso:country":"BE",
    "sg:address":"Rue Alexandre-daoust 74",
    "sg:city":"Dinant",
    "sg:orig_category":"Alternatieve geneeskunde",
    "sg:phone":"+32 82 22 86 74",
    "sg:postcode":"5500",
    "sg:province":"Namur",
    "wof:name":"J.l. Leheureux",
    "wof:placetype":"venue"
},
  "geometry": {"coordinates":[4.9175748825,50.2524871826],"type":"Point"}
}