{
  "type": "Feature",
  "properties": {
    "iso:country":"BE",
    "sg:address":"De Laks 23",
    "sg:city":"Oud-turnhout",
    "sg:orig_category":"Groententeelt",
    "sg:phone":"+32 14 41 14 06",
    "sg:postcode":"2360",
    "sg:province":"Antwerpen",
    "wof:name":"Peter Vervoort",
    "wof:placetype":"venue"
},
  "geometry": {"coordinates":[4.9949197769,51.3532028198],"type":"Point"}
}