{
  "type": "Feature",
  "properties": {
    "iso:country":"BE",
    "sg:address":"Lac Du Prince",
    "sg:city":"Antoing",
    "sg:orig_category":"Sportclubs",
    "sg:phone":"+32 69 34 64 83",
    "sg:postcode":"7640",
    "sg:province":"Hainaut",
    "wof:name":"High Performance Skiing - H.p.s.",
    "wof:placetype":"venue"
},
  "geometry": {"coordinates":[3.4519898891,50.565738678],"type":"Point"}
}