{
  "type": "Feature",
  "properties": {
    "iso:country":"BE",
    "sg:address":"Domentstraat 58",
    "sg:city":"Affligem",
    "sg:orig_category":"Installatie van houten of kunststof schrijnwerk",
    "sg:phone":"+32 2 452 95 09",
    "sg:postcode":"1790",
    "sg:province":"Vlaams-Brabant",
    "wof:name":"Willy Van Den Bossche",
    "wof:placetype":"venue"
},
  "geometry": {"coordinates":[4.1366391182,50.9205856323],"type":"Point"}
}