{
  "type": "Feature",
  "properties": {
    "addr:full":"127 Rue De Tournai 7740 Pecq 127",
    "addr:housenumber":"127;127",
    "addr:postcode":"7740",
    "addr:street":"Rue De Tournai;Pecq",
    "iso:country":"BE",
    "sg:address":"127",
    "sg:city":"Rue De Tournai 7740 Pecq",
    "sg:classifiers":[
        {
            "category":"Travel",
            "subcategory":"Hotels & Motels",
            "type":"Entertainment"
        }
    ],
    "sg:phone":"+32 69 55 85 03",
    "sg:postcode":"127",
    "sg:tags":[
        "hotels",
        "business",
        "restaurant"
    ],
    "wof:name":"Goldven Vegas Sa",
    "wof:placetype":"venue"
},
  "geometry": {"coordinates":[3.33968997,50.6774787903],"type":"Point"}
}