{
  "type": "Feature",
  "properties": {
    "addr:full":"Oudenaardsestraat 3 Brakel Oost-Vlaanderen 9660",
    "addr:housenumber":"3",
    "addr:postcode":"9660",
    "addr:street":"Oudenaardsestraat",
    "iso:country":"BE",
    "sg:address":"Oudenaardsestraat 3",
    "sg:city":"Brakel",
    "sg:classifiers":[
        {
            "category":"Shopping",
            "subcategory":"Clothing, Apparel, & Fashions",
            "type":"Retail Goods"
        }
    ],
    "sg:phone":"+32 55 42 65 52",
    "sg:postcode":"9660",
    "sg:province":"Oost-Vlaanderen",
    "sg:tags":[
        "lingerie",
        "sous-v\u00eatements"
    ],
    "wof:name":"Martine Bruneel",
    "wof:placetype":"venue"
},
  "geometry": {"coordinates":[3.7310299873,50.8146018982],"type":"Point"}
}