{
  "type": "Feature",
  "properties": {
    "iso:country":"BE",
    "sg:address":"Rue Du Champ De Mars 6",
    "sg:city":"Elsene/ixelles",
    "sg:classifiers":[
        {
            "category":"Restaurant",
            "type":"Food & Drink"
        }
    ],
    "sg:phone":"+32 2 502 85 20",
    "sg:postcode":"1050",
    "sg:province":"Bruxelles-Capitale",
    "wof:name":"Le R\u00c9gal",
    "wof:placetype":"venue"
},
  "geometry": {"coordinates":[4.3628959656,50.8383712769],"type":"Point"}
}