{
  "type": "Feature",
  "properties": {
    "addr:full":"Michielsplein 20 Box 1 Hamont-achel (achel) Limburg 3930",
    "addr:housenumber":"20;1",
    "addr:postcode":"3930",
    "addr:street":"Michielsplein;Box",
    "iso:country":"BE",
    "sg:address":"Michielsplein 20 Box 1",
    "sg:city":"Hamont-achel (achel)",
    "sg:classifiers":[
        {
            "category":"Home & Garden",
            "subcategory":"Building Materials",
            "type":"Retail Goods"
        }
    ],
    "sg:phone":"+32 477 96 65 07",
    "sg:postcode":"3930",
    "sg:province":"Limburg",
    "sg:tags":[
        "window"
    ],
    "wof:name":"T&t",
    "wof:placetype":"venue"
},
  "geometry": {"coordinates":[5.4803071022,51.2538719177],"type":"Point"}
}