{
  "type": "Feature",
  "properties": {
    "addr:full":"Sint-jansplein 16 Sint-niklaas Oost-Vlaanderen 9100",
    "addr:housenumber":"16",
    "addr:postcode":"9100",
    "addr:street":"Sint-Jansplein",
    "iso:country":"BE",
    "sg:address":"Sint-jansplein 16",
    "sg:city":"Sint-niklaas",
    "sg:orig_category":"Artsen and specialisten",
    "sg:phone":"+32 3 777 39 21",
    "sg:postcode":"9100",
    "sg:province":"Oost-Vlaanderen",
    "wof:name":"Patrick Dedoncker",
    "wof:placetype":"venue"
},
  "geometry": {"coordinates":[4.1362838745,51.1585006714],"type":"Point"}
}