{
  "type": "Feature",
  "properties": {
    "addr:full":"Rue Du Moulin 29 Courcelles (gouy-lez-pi\u00e9ton) Hainaut 6181",
    "addr:housenumber":"29",
    "addr:postcode":"6181",
    "addr:street":"Rue Du Moulin",
    "iso:country":"BE",
    "sg:address":"Rue Du Moulin 29",
    "sg:city":"Courcelles (gouy-lez-pi\u00e9ton)",
    "sg:classifiers":[
        {
            "category":"Retail",
            "subcategory":"Repair Shop",
            "type":"Services"
        }
    ],
    "sg:phone":"+32 478 97 59 52",
    "sg:postcode":"6181",
    "sg:province":"Hainaut",
    "sg:tags":[
        "radio",
        "television",
        "-",
        "maintenance"
    ],
    "wof:name":"Techni Compta",
    "wof:placetype":"venue"
},
  "geometry": {"coordinates":[4.3264088631,50.4934844971],"type":"Point"}
}