{
  "type": "Feature",
  "properties": {
    "addr:full":"Gentsesteenweg 45 Lierde (hemelveerdegem) Oost-Vlaanderen 9571",
    "addr:housenumber":"45",
    "addr:postcode":"9571",
    "addr:street":"Gentsesteenweg",
    "iso:country":"BE",
    "sg:address":"Gentsesteenweg 45",
    "sg:city":"Lierde (hemelveerdegem)",
    "sg:orig_category":"Non-Classified Establishments",
    "sg:phone":"+32 54 50 07 81",
    "sg:postcode":"9571",
    "sg:province":"Oost-Vlaanderen",
    "wof:name":"Beke (vloeren) Nv",
    "wof:placetype":"venue"
},
  "geometry": {"coordinates":[3.8575649261,50.8069763184],"type":"Point"}
}