{
  "type": "Feature",
  "properties": {
    "addr:full":"Rue Neuve 135 Pepinster Li\u00e8ge 4860",
    "addr:housenumber":"135",
    "addr:postcode":"4860",
    "addr:street":"Rue Neuve",
    "iso:country":"BE",
    "sg:address":"Rue Neuve 135",
    "sg:city":"Pepinster",
    "sg:orig_category":"Enseignement maternel and primaire",
    "sg:phone":"+32 87 46 05 19",
    "sg:postcode":"4860",
    "sg:province":"Li\u00e8ge",
    "wof:name":"Ecole Fondamentale Libre",
    "wof:placetype":"venue"
},
  "geometry": {"coordinates":[5.80377388,50.5639228821],"type":"Point"}
}