{
  "type": "Feature",
  "properties": {
    "addr:full":"Paalstraat 69 Schoten Antwerpen 2900",
    "addr:housenumber":"69",
    "addr:postcode":"2900",
    "addr:street":"Paalstraat",
    "iso:country":"BE",
    "sg:address":"Paalstraat 69",
    "sg:city":"Schoten",
    "sg:orig_category":"RESTAURANTS: CAF\u00c9S",
    "sg:phone":"+32 3 685 00 44",
    "sg:postcode":"2900",
    "sg:province":"Antwerpen",
    "wof:name":"Taverne Den Eekhoorn",
    "wof:placetype":"venue"
},
  "geometry": {"coordinates":[4.5006651878,51.2523994446],"type":"Point"}
}