{
  "type": "Feature",
  "properties": {
    "iso:country":"BE",
    "sg:address":"Rue Du Berceau 105",
    "sg:city":"Fleurus",
    "sg:classifiers":[
        {
            "category":"Health Services",
            "subcategory":"Health Practitioner",
            "type":"Services"
        }
    ],
    "sg:phone":"+32 71 81 43 69",
    "sg:postcode":"6220",
    "sg:province":"Hainaut",
    "sg:tags":[
        "therapist",
        "speech"
    ],
    "wof:name":"Lobefaro Carmen",
    "wof:placetype":"venue"
},
  "geometry": {"coordinates":[4.5478730202,50.4862174988],"type":"Point"}
}