{
  "type": "Feature",
  "properties": {
    "iso:country":"BE",
    "sg:address":"Seulestraat 74",
    "sg:city":"Heuvelland",
    "sg:orig_category":"HUISBRANDOLIE",
    "sg:phone":"+32 57 44 41 06",
    "sg:postcode":"8950",
    "sg:province":"West-Vlaanderen",
    "wof:name":"Lucien Poiriez",
    "wof:placetype":"venue"
},
  "geometry": {"coordinates":[2.8249499798,50.7459411621],"type":"Point"}
}