{
  "type": "Feature",
  "properties": {
    "addr:full":"Dokter Eduard Moreauxln 43 Oostende West-Vlaanderen 8400",
    "addr:housenumber":"43",
    "addr:postcode":"8400",
    "addr:street":"Dokter Eduard Moreauxln",
    "iso:country":"BE",
    "sg:address":"Dokter Eduard Moreauxln 43",
    "sg:city":"Oostende",
    "sg:classifiers":[
        {
            "category":"Cafe",
            "type":"Food & Drink"
        }
    ],
    "sg:phone":"+32 59 32 17 83",
    "sg:postcode":"8400",
    "sg:province":"West-Vlaanderen",
    "sg:tags":[
        "caf\u00e9s"
    ],
    "wof:name":"Caf\u00c9 Stella",
    "wof:placetype":"venue"
},
  "geometry": {"coordinates":[2.941865921,51.224445343],"type":"Point"}
}