{
  "type": "Feature",
  "properties": {
    "iso:country":"BE",
    "sg:address":"Quai Taille Pierres 13",
    "sg:city":"Tournai",
    "sg:classifiers":[
        {
            "category":"Retail",
            "subcategory":"Laundry & Dry Cleaning",
            "type":"Services"
        }
    ],
    "sg:phone":"+32 69 21 59 22",
    "sg:postcode":"7500",
    "sg:province":"Hainaut",
    "sg:tags":[
        "self",
        "-"
    ],
    "wof:name":"A La Claire Fontaine",
    "wof:placetype":"venue"
},
  "geometry": {"coordinates":[3.3970079422,50.6035690308],"type":"Point"}
}