{
  "type": "Feature",
  "properties": {
    "addr:full":"Breedstraat 23 Sint-niklaas Oost-Vlaanderen 9100",
    "addr:housenumber":"23",
    "addr:postcode":"9100",
    "addr:street":"Breedstraat",
    "iso:country":"BE",
    "sg:address":"Breedstraat 23",
    "sg:city":"Sint-niklaas",
    "sg:classifiers":[
        {
            "category":"Building & Trades",
            "subcategory":"Cleaning & Sanitation",
            "type":"Services"
        }
    ],
    "sg:phone":"+32 3 296 45 74",
    "sg:postcode":"9100",
    "sg:province":"Oost-Vlaanderen",
    "sg:tags":[
        "cleaner",
        "window"
    ],
    "wof:name":"Sdc",
    "wof:placetype":"venue"
},
  "geometry": {"coordinates":[4.1594457626,51.1692771912],"type":"Point"}
}