{
  "type": "Feature",
  "properties": {
    "addr:full":"Watermolendreef 84 Sint-niklaas Oost-Vlaanderen 9100",
    "addr:housenumber":"84",
    "addr:postcode":"9100",
    "addr:street":"Watermolendreef",
    "iso:country":"BE",
    "sg:address":"Watermolendreef 84",
    "sg:city":"Sint-niklaas",
    "sg:orig_category":"Mat\u00e9riel de contr\u00f4le des processus industriels Fab",
    "sg:phone":"+32 3 789 12 43",
    "sg:postcode":"9100",
    "sg:province":"Oost-Vlaanderen",
    "wof:name":"Bracke Industries",
    "wof:placetype":"venue"
},
  "geometry": {"coordinates":[4.125992775,51.1683006287],"type":"Point"}
}