{
  "type": "Feature",
  "properties": {
    "iso:country":"BE",
    "sg:address":"Rue De La Semois 29",
    "sg:city":"Etalle",
    "sg:orig_category":"Eleveurs de bovins",
    "sg:phone":"+32 63 45 56 20",
    "sg:postcode":"6741",
    "sg:province":"Luxembourg",
    "wof:name":"Roger Bouvy",
    "wof:placetype":"venue"
},
  "geometry": {"coordinates":[5.6635560989,49.6696166992],"type":"Point"}
}