{
  "type": "Feature",
  "properties": {
    "iso:country":"BE",
    "sg:address":"Rue De Jeumont 14",
    "sg:city":"Courcelles (gouy-lez-pi\u00e9ton)",
    "sg:classifiers":[
        {
            "category":"Building & Trades",
            "subcategory":"Landscaping Services",
            "type":"Services"
        }
    ],
    "sg:phone":"+32 71 84 31 13",
    "sg:postcode":"6181",
    "sg:province":"Hainaut",
    "sg:tags":[
        "gardening",
        "garden",
        "maintenance"
    ],
    "wof:name":"Garden 2000",
    "wof:placetype":"venue"
},
  "geometry": {"coordinates":[4.3112998009,50.4860191345],"type":"Point"}
}