{
  "type": "Feature",
  "properties": {
    "addr:full":"Rue Leon Parent 84 Beauraing Namur 5570",
    "addr:housenumber":"84",
    "addr:postcode":"5570",
    "addr:street":"Rue Leon Parent",
    "iso:country":"BE",
    "sg:address":"Rue Leon Parent 84",
    "sg:city":"Beauraing",
    "sg:orig_category":"Boomkwekerijen Loodgieterij, verwarming and sanitaire installaties",
    "sg:phone":"+32 82 71 38 51",
    "sg:postcode":"5570",
    "sg:province":"Namur",
    "wof:name":"Leon Arbulot",
    "wof:placetype":"venue"
},
  "geometry": {"coordinates":[4.9725461006,50.0599098206],"type":"Point"}
}