{
  "type": "Feature",
  "properties": {
    "iso:country":"BE",
    "sg:address":"Joris Van Severenlaan 8",
    "sg:city":"Dentergem",
    "sg:orig_category":"Services pour animaux domestiques",
    "sg:phone":"+32 56 60 84 34",
    "sg:postcode":"8720",
    "sg:province":"West-Vlaanderen",
    "wof:name":"Boemer",
    "wof:placetype":"venue"
},
  "geometry": {"coordinates":[3.4005589485,50.9353485107],"type":"Point"}
}