{
  "type": "Feature",
  "properties": {
    "iso:country":"BE",
    "sg:address":"Hekkeniersstraat 18",
    "sg:city":"Waregem (beveren-leie)",
    "sg:classifiers":[
        {
            "category":"Professional",
            "subcategory":"Management & Consulting",
            "type":"Services"
        }
    ],
    "sg:phone":"+32 56 32 50 15",
    "sg:postcode":"8791",
    "sg:province":"West-Vlaanderen",
    "sg:tags":[
        "consultant"
    ],
    "wof:name":"Dastim Nv",
    "wof:placetype":"venue"
},
  "geometry": {"coordinates":[3.3343958855,50.8770675659],"type":"Point"}
}