{
  "type": "Feature",
  "properties": {
    "addr:full":"Rue Joseph Wauters 48b8 Saint-georges-sur-meuse Li\u00e8ge 4470",
    "addr:housenumber":"48b8",
    "addr:postcode":"4470",
    "addr:street":"Rue Joseph Wauters",
    "iso:country":"BE",
    "sg:address":"Rue Joseph Wauters 48b8",
    "sg:city":"Saint-georges-sur-meuse",
    "sg:orig_category":"S\u00e9curit\u00e9 sociale",
    "sg:phone":"+32 4 275 67 29",
    "sg:postcode":"4470",
    "sg:province":"Li\u00e8ge",
    "wof:name":"Mutualitt Socialiste",
    "wof:placetype":"venue"
},
  "geometry": {"coordinates":[5.3610901833,50.578289032],"type":"Point"}
}