{
  "type": "Feature",
  "properties": {
    "addr:full":"Herbesthaler Strasse 132ba Eupen Li\u00e8ge 4700",
    "addr:postcode":"4700",
    "addr:street":"Herbesthaler Strasse",
    "iso:country":"BE",
    "sg:address":"Herbesthaler Strasse 132ba",
    "sg:city":"Eupen",
    "sg:orig_category":"Baby- and kinderkleding Dameskledingzaken Herenkledingzaken",
    "sg:phone":"+32 87 56 01 96",
    "sg:postcode":"4700",
    "sg:province":"Li\u00e8ge",
    "wof:name":"Superconfex",
    "wof:placetype":"venue"
},
  "geometry": {"coordinates":[6.0154972076,50.6396446228],"type":"Point"}
}