{
  "type": "Feature",
  "properties": {
    "addr:full":"Wenduinesteenweg 17 De Haan (klemskerke) West-Vlaanderen 8420",
    "addr:housenumber":"17",
    "addr:postcode":"8420",
    "addr:street":"Wenduinesteenweg",
    "iso:country":"BE",
    "sg:address":"Wenduinesteenweg 17",
    "sg:city":"De Haan (klemskerke)",
    "sg:classifiers":[
        {
            "category":"Fast Food",
            "type":"Food & Drink"
        }
    ],
    "sg:phone":"+32 59 23 64 22",
    "sg:postcode":"8420",
    "sg:province":"West-Vlaanderen",
    "sg:tags":[
        "fried",
        "stand",
        "potato"
    ],
    "wof:name":"Smulmarkt (de)",
    "wof:placetype":"venue"
},
  "geometry": {"coordinates":[3.0352249146,51.2725524902],"type":"Point"}
}