{
  "type": "Feature",
  "properties": {
    "addr:full":"Rue Des Fran\u00c7ais 305 Ans Li\u00e8ge 4430",
    "addr:housenumber":"305",
    "addr:postcode":"4430",
    "addr:street":"Rue Des Franc\u0327Ais",
    "iso:country":"BE",
    "sg:address":"Rue Des Fran\u00c7ais 305",
    "sg:city":"Ans",
    "sg:orig_category":"Voertuigen",
    "sg:phone":"+32 4 263 83 53",
    "sg:postcode":"4430",
    "sg:province":"Li\u00e8ge",
    "wof:name":"Garage Ren\u00c9",
    "wof:placetype":"venue"
},
  "geometry": {"coordinates":[5.5376238823,50.6655883789],"type":"Point"}
}