{
  "type": "Feature",
  "properties": {
    "addr:full":"Waterloosesteenweg 566 Elsene Bruxelles-Capitale 1050",
    "addr:housenumber":"566",
    "addr:postcode":"1050",
    "addr:street":"Waterloosesteenweg",
    "iso:country":"BE",
    "sg:address":"Waterloosesteenweg 566",
    "sg:city":"Elsene",
    "sg:classifiers":[
        {
            "category":"Retail",
            "subcategory":"Auto Rental",
            "type":"Services"
        }
    ],
    "sg:phone":"+32 2 344 49 24",
    "sg:postcode":"1050",
    "sg:province":"Bruxelles-Capitale",
    "sg:tags":[
        "mazda",
        "automobile",
        "v\u00e9hicules"
    ],
    "wof:name":"Soci\u00c9te G\u00c9n\u00c9rale Distrib.automobile",
    "wof:placetype":"venue"
},
  "geometry": {"coordinates":[4.3624157906,50.8189926147],"type":"Point"}
}