{
  "type": "Feature",
  "properties": {
    "iso:country":"BE",
    "sg:address":"Avenue Baron Albert D'huart 28",
    "sg:city":"Bruxelles (woluwe-saint-pierre)",
    "sg:classifiers":[
        {
            "category":"Military Area",
            "subcategory":"Armory",
            "type":"Public Place"
        }
    ],
    "sg:phone":"+32 2 763 03 49",
    "sg:postcode":"1150",
    "sg:province":"Bruxelles-Capitale",
    "sg:tags":[
        "good",
        "police"
    ],
    "wof:name":"Ffe International Belgium Sa",
    "wof:placetype":"venue"
},
  "geometry": {"coordinates":[4.4663949013,50.8389625549],"type":"Point"}
}