{
  "type": "Feature",
  "properties": {
    "iso:country":"BE",
    "sg:address":"Grand'rue 181",
    "sg:city":"Trooz",
    "sg:orig_category":"Installatie van houten of kunststof schrijnwerk",
    "sg:phone":"+32 4 351 73 57",
    "sg:postcode":"4870",
    "sg:province":"Li\u00e8ge",
    "wof:name":"Henri Falla",
    "wof:placetype":"venue"
},
  "geometry": {"coordinates":[5.6895260811,50.5719566345],"type":"Point"}
}