{
  "type": "Feature",
  "properties": {
    "iso:country":"BE",
    "sg:address":"Remi Vanmeerhaeghestraat 44",
    "sg:city":"Waregem",
    "sg:orig_category":"Peinture. Rev\u00eatements pour sols and murs. Architectes",
    "sg:phone":"+32 56 60 29 03",
    "sg:postcode":"8790",
    "sg:province":"West-Vlaanderen",
    "wof:name":"Home Finishing",
    "wof:placetype":"venue"
},
  "geometry": {"coordinates":[3.4011909962,50.8652992249],"type":"Point"}
}