{
  "type": "Feature",
  "properties": {
    "iso:country":"BE",
    "sg:address":"Rue Perdue 27",
    "sg:city":"Tournai",
    "sg:classifiers":[
        {
            "category":"Organizations",
            "subcategory":"Professional Association",
            "type":"Services"
        }
    ],
    "sg:phone":"+32 69 22 05 54",
    "sg:postcode":"7500",
    "sg:province":"Hainaut",
    "sg:tags":[
        "trade-union",
        "federation"
    ],
    "wof:name":"F\u00e9d\u00e9ration Des M\u00e9tallurgistes Du Hainaut Occidental",
    "wof:placetype":"venue"
},
  "geometry": {"coordinates":[3.3834459782,50.6067466736],"type":"Point"}
}