{
  "type": "Feature",
  "properties": {
    "addr:full":"Eugeen Van De Vellaan 98 Schilde Antwerpen 2970",
    "addr:housenumber":"98",
    "addr:postcode":"2970",
    "addr:street":"Eugeen Van De Vellaan",
    "iso:country":"BE",
    "sg:address":"Eugeen Van De Vellaan 98",
    "sg:city":"Schilde",
    "sg:classifiers":[
        {
            "category":"Shopping Center",
            "type":"Public Place"
        }
    ],
    "sg:phone":"+32 3 383 26 59",
    "sg:postcode":"2970",
    "sg:province":"Antwerpen",
    "sg:tags":[
        "aluminium",
        "casting"
    ],
    "wof:name":"C & C Engineering B.v.b.a.",
    "wof:placetype":"venue"
},
  "geometry": {"coordinates":[4.5711150169,51.2453308105],"type":"Point"}
}