{
  "type": "Feature",
  "properties": {
    "addr:full":"Rue D\u00b4artois 65 Brussel/bruxelles Bruxelles-Capitale 1000",
    "addr:housenumber":"65",
    "addr:postcode":"1000",
    "addr:street":"Rue D\u00b4Artois;/",
    "iso:country":"BE",
    "sg:address":"Rue D\u00b4artois 65",
    "sg:city":"Brussel/bruxelles",
    "sg:orig_category":"Instruments de musique",
    "sg:phone":"+32 2 512 36 83",
    "sg:postcode":"1000",
    "sg:province":"Bruxelles-Capitale",
    "wof:name":"Accord\u00c9ons Hamelrijk L.",
    "wof:placetype":"venue"
},
  "geometry": {"coordinates":[4.3406248093,50.8425331116],"type":"Point"}
}