{
  "type": "Feature",
  "properties": {
    "iso:country":"BE",
    "sg:address":"Horionweg 12",
    "sg:city":"Heusden-zolder",
    "sg:orig_category":"Groententeelt",
    "sg:phone":"+32 11 42 47 79",
    "sg:postcode":"3550",
    "sg:province":"Limburg",
    "wof:name":"Maurice Schepers",
    "wof:placetype":"venue"
},
  "geometry": {"coordinates":[5.2563991547,51.0197601318],"type":"Point"}
}