{
  "type": "Feature",
  "properties": {
    "iso:country":"BE",
    "sg:address":"Hoenstraat 25",
    "sg:city":"Zonnebeke",
    "sg:orig_category":"Rundveehouders",
    "sg:phone":"+32 57 46 61 42",
    "sg:postcode":"8980",
    "sg:province":"West-Vlaanderen",
    "wof:name":"Geert Mesure",
    "wof:placetype":"venue"
},
  "geometry": {"coordinates":[3.0394530296,50.8593025208],"type":"Point"}
}