{
  "type": "Feature",
  "properties": {
    "addr:full":"Sint-jorislaan 108 Herk-de-stad (schulen) Limburg 3540",
    "addr:housenumber":"108",
    "addr:postcode":"3540",
    "addr:street":"Sint-Jorislaan",
    "iso:country":"BE",
    "sg:address":"Sint-jorislaan 108",
    "sg:city":"Herk-de-stad (schulen)",
    "sg:orig_category":"Newspapers, magazines, periodicals - Distribution",
    "sg:phone":"+32 13 55 43 97",
    "sg:postcode":"3540",
    "sg:province":"Limburg",
    "wof:name":"Krantje ('t)",
    "wof:placetype":"venue"
},
  "geometry": {"coordinates":[5.197740078,50.9491119385],"type":"Point"}
}