{
  "type": "Feature",
  "properties": {
    "addr:full":"Rue Castelain 2 Nivelles Brabant Wallon 1400",
    "addr:housenumber":"2",
    "addr:postcode":"1400",
    "addr:street":"Rue Castelain",
    "iso:country":"BE",
    "sg:address":"Rue Castelain 2",
    "sg:city":"Nivelles",
    "sg:classifiers":[
        {
            "category":"Real Estate",
            "subcategory":"Architect",
            "type":"Services"
        }
    ],
    "sg:phone":"+32 67 22 02 00",
    "sg:postcode":"1400",
    "sg:province":"Brabant Wallon",
    "wof:name":"Cuisset P",
    "wof:placetype":"venue"
},
  "geometry": {"coordinates":[4.3321790695,50.5997657776],"type":"Point"}
}