{
  "type": "Feature",
  "properties": {
    "iso:country":"BE",
    "sg:address":"Duindistellaan 24",
    "sg:city":"Blankenberge (uitkerke)",
    "sg:classifiers":[
        {
            "category":"Health Services",
            "subcategory":"Health Practitioner",
            "type":"Services"
        }
    ],
    "sg:phone":"+32 50 41 71 15",
    "sg:postcode":"8370",
    "sg:province":"West-Vlaanderen",
    "sg:tags":[
        "physiotherapist"
    ],
    "wof:name":"Bulcke Kim",
    "wof:placetype":"venue"
},
  "geometry": {"coordinates":[3.1359989643,51.3032035828],"type":"Point"}
}