{
  "type": "Feature",
  "properties": {
    "iso:country":"BE",
    "sg:address":"Rue L\u00e9on Lef\u00e8vre 30",
    "sg:city":"Namur (champion - Cognel\u00e9e)",
    "sg:classifiers":[
        {
            "category":"Retail",
            "subcategory":"Event Space",
            "type":"Services"
        }
    ],
    "sg:phone":"+32 81 21 52 44",
    "sg:postcode":"5020",
    "sg:province":"Namur",
    "sg:tags":[
        "rental",
        "-",
        "hall"
    ],
    "wof:name":"Salle Paroissiale",
    "wof:placetype":"venue"
},
  "geometry": {"coordinates":[4.9040198326,50.4987297058],"type":"Point"}
}