{
  "type": "Feature",
  "properties": {
    "addr:full":"Avenue Du Pont De Luttre 55 Bruxelles (forest) Bruxelles-Capitale 1190",
    "addr:housenumber":"55",
    "addr:postcode":"1190",
    "addr:street":"Avenue Du Pont De Luttre",
    "iso:country":"BE",
    "sg:address":"Avenue Du Pont De Luttre 55",
    "sg:city":"Bruxelles (forest)",
    "sg:classifiers":[
        {
            "category":"Shopping",
            "subcategory":"Discount & Variety Stores",
            "type":"Retail Goods"
        }
    ],
    "sg:phone":"+32 2 344 16 23",
    "sg:postcode":"1190",
    "sg:province":"Bruxelles-Capitale",
    "sg:tags":[
        "shop",
        "clearers",
        "curiosity",
        "furniture"
    ],
    "wof:name":"Ach\u00e8te Tout",
    "wof:placetype":"venue"
},
  "geometry": {"coordinates":[4.3223958015,50.8216743469],"type":"Point"}
}