{
  "type": "Feature",
  "properties": {
    "iso:country":"BE",
    "sg:address":"Rue De La Rausch 39",
    "sg:city":"Arlon",
    "sg:orig_category":"Rundveehouders",
    "sg:phone":"+32 63 22 73 38",
    "sg:postcode":"6704",
    "sg:province":"Luxembourg",
    "wof:name":"Marc Conter",
    "wof:placetype":"venue"
},
  "geometry": {"coordinates":[5.8503890038,49.7173995972],"type":"Point"}
}