{
  "type": "Feature",
  "properties": {
    "iso:country":"BE",
    "sg:address":"Rue Du Laveu 236",
    "sg:city":"Li\u00e8ge 1",
    "sg:classifiers":[
        {
            "category":"Autos & Motor Vehicles",
            "subcategory":"Auto Supplies",
            "type":"Retail Goods"
        }
    ],
    "sg:phone":"+32 4 252 92 02",
    "sg:postcode":"4000",
    "sg:province":"Li\u00e8ge",
    "sg:tags":[
        "access",
        "automobile",
        "part",
        "-"
    ],
    "wof:name":"4wd Center",
    "wof:placetype":"venue"
},
  "geometry": {"coordinates":[5.5569500923,50.630241394],"type":"Point"}
}