{
  "type": "Feature",
  "properties": {
    "iso:country":"BE",
    "sg:address":"Grand'place 19-20",
    "sg:city":"Ath",
    "sg:orig_category":"Mat\u00e9riel de T\u00e9l\u00e9communication. Electrom\u00e9nager, t\u00e9l\u00e9visions and radios",
    "sg:phone":"+32 68 28 61 09",
    "sg:postcode":"7800",
    "sg:province":"Hainaut",
    "wof:name":"Legaye Electromenager",
    "wof:placetype":"venue"
},
  "geometry": {"coordinates":[3.7767679691,50.6313171387],"type":"Point"}
}