{
  "type": "Feature",
  "properties": {
    "addr:full":"Geraardsbergsesteenweg 263 Ninove (aspelare) Oost-Vlaanderen 9404",
    "addr:housenumber":"263",
    "addr:postcode":"9404",
    "addr:street":"Geraardsbergsesteenweg",
    "iso:country":"BE",
    "sg:address":"Geraardsbergsesteenweg 263",
    "sg:city":"Ninove (aspelare)",
    "sg:classifiers":[
        {
            "category":"Shopping",
            "subcategory":"Bicycles & Sporting Goods",
            "type":"Retail Goods"
        }
    ],
    "sg:phone":"+32 54 33 85 87",
    "sg:postcode":"9404",
    "sg:province":"Oost-Vlaanderen",
    "sg:tags":[
        "-"
    ],
    "wof:name":"Ar-se Sport",
    "wof:placetype":"venue"
},
  "geometry": {"coordinates":[3.9570000172,50.8419036865],"type":"Point"}
}