{
  "type": "Feature",
  "properties": {
    "iso:country":"BE",
    "sg:address":"Jachthoornlaan 32",
    "sg:city":"Schilde ('s Gravenwezel)",
    "sg:classifiers":[
        {
            "category":"Real Estate",
            "subcategory":"Architect",
            "type":"Services"
        }
    ],
    "sg:phone":"+32 3 658 90 08",
    "sg:postcode":"2970",
    "sg:province":"Antwerpen",
    "wof:name":"Verhelst P",
    "wof:placetype":"venue"
},
  "geometry": {"coordinates":[4.5534801483,51.257900238],"type":"Point"}
}