{
  "type": "Feature",
  "properties": {
    "iso:country":"BE",
    "sg:address":"Bld Frere Orban 25",
    "sg:city":"Li\u00e8ge",
    "sg:classifiers":[
        {
            "category":"Professional",
            "subcategory":"Computer Services",
            "type":"Services"
        }
    ],
    "sg:phone":"+32 4 254 49 00",
    "sg:postcode":"4000",
    "sg:province":"Li\u00e8ge",
    "sg:tags":[
        "development",
        "software"
    ],
    "wof:name":"Vanenburg Business Systems S.a.",
    "wof:placetype":"venue"
},
  "geometry": {"coordinates":[5.5704808235,50.6316261292],"type":"Point"}
}