{
  "type": "Feature",
  "properties": {
    "addr:full":"Oude Staatsbaan 44 Zomergem Oost-Vlaanderen 9930",
    "addr:housenumber":"44",
    "addr:postcode":"9930",
    "addr:street":"Oude Staatsbaan",
    "iso:country":"BE",
    "sg:address":"Oude Staatsbaan 44",
    "sg:city":"Zomergem",
    "sg:orig_category":"Banques and organismes de cr\u00e9dit",
    "sg:phone":"+32 9 372 76 61",
    "sg:postcode":"9930",
    "sg:province":"Oost-Vlaanderen",
    "wof:name":"Landbouwkrediet",
    "wof:placetype":"venue"
},
  "geometry": {"coordinates":[3.6004939079,51.1335067749],"type":"Point"}
}