{
  "type": "Feature",
  "properties": {
    "addr:full":"Pastorijstraat 4 Lille Antwerpen 2275",
    "addr:housenumber":"4",
    "addr:postcode":"2275",
    "addr:street":"Pastorijstraat",
    "iso:country":"BE",
    "sg:address":"Pastorijstraat 4",
    "sg:city":"Lille",
    "sg:classifiers":[
        {
            "category":"Fast Food",
            "type":"Food & Drink"
        }
    ],
    "sg:phone":"+32 3 312 17 46",
    "sg:postcode":"2275",
    "sg:province":"Antwerpen",
    "sg:tags":[
        "meeneem",
        "restaurant"
    ],
    "wof:name":"Frituur Dreesen",
    "wof:placetype":"venue"
},
  "geometry": {"coordinates":[4.7885890007,51.2647895813],"type":"Point"}
}