{
  "type": "Feature",
  "properties": {
    "iso:country":"BE",
    "sg:address":"Oude Dreef 2",
    "sg:city":"Berlare",
    "sg:classifiers":[
        {
            "category":"Cafe",
            "type":"Food & Drink"
        }
    ],
    "sg:phone":"+32 9 367 97 70",
    "sg:postcode":"9290",
    "sg:province":"Oost-Vlaanderen",
    "sg:tags":[
        "caf\u00e9s"
    ],
    "wof:name":"Caf\u00c9 De Kalvaar",
    "wof:placetype":"venue"
},
  "geometry": {"coordinates":[3.9885098934,51.0412597656],"type":"Point"}
}