{
  "type": "Feature",
  "properties": {
    "addr:full":"Rue Hospice Communal 28 Watermael-boitsfort Bruxelles-Capitale 1170",
    "addr:housenumber":"28",
    "addr:postcode":"1170",
    "addr:street":"Rue Hospice Communal",
    "iso:country":"BE",
    "sg:address":"Rue Hospice Communal 28",
    "sg:city":"Watermael-boitsfort",
    "sg:orig_category":"Astrologen, grafologen and mediums",
    "sg:phone":"+32 2 673 73 93",
    "sg:postcode":"1170",
    "sg:province":"Bruxelles-Capitale",
    "wof:name":"Fallon Astrid",
    "wof:placetype":"venue"
},
  "geometry": {"coordinates":[4.4185900688,50.7999076843],"type":"Point"}
}