{
  "type": "Feature",
  "properties": {
    "iso:country":"BE",
    "sg:address":"Wakkensesteenweg 33",
    "sg:city":"Tielt",
    "sg:classifiers":[
        {
            "category":"Utilities",
            "subcategory":"Water",
            "type":"Services"
        }
    ],
    "sg:phone":"+32 51 40 05 60",
    "sg:postcode":"8700",
    "sg:province":"West-Vlaanderen",
    "sg:tags":[
        "purification"
    ],
    "wof:name":"Betonwerkerij Verhulst Nv",
    "wof:placetype":"venue"
},
  "geometry": {"coordinates":[3.339206934,50.9852180481],"type":"Point"}
}