{
  "type": "Feature",
  "properties": {
    "addr:full":"Rue De Mariembourg 47 Philippeville (neuville) Namur 5600",
    "addr:housenumber":"47",
    "addr:postcode":"5600",
    "addr:street":"Rue De Mariembourg",
    "iso:country":"BE",
    "sg:address":"Rue De Mariembourg 47",
    "sg:city":"Philippeville (neuville)",
    "sg:classifiers":[
        {
            "category":"Recreation",
            "subcategory":"Campground",
            "type":"Entertainment"
        }
    ],
    "sg:phone":"+32 71 66 72 03",
    "sg:postcode":"5600",
    "sg:province":"Namur",
    "sg:tags":[
        "site",
        "camping"
    ],
    "wof:name":"Camping La For\u00eat Sc",
    "wof:placetype":"venue"
},
  "geometry": {"coordinates":[4.5301628113,50.1932601929],"type":"Point"}
}