{
  "type": "Feature",
  "properties": {
    "addr:full":"Rue Du Cul De Sac 2 Clavier Li\u00e8ge 4560",
    "addr:housenumber":"2",
    "addr:postcode":"4560",
    "addr:street":"Rue Du Cul De Sac",
    "iso:country":"BE",
    "sg:address":"Rue Du Cul De Sac 2",
    "sg:city":"Clavier",
    "sg:orig_category":"Dierenartsen",
    "sg:phone":"+32 86 34 47 41",
    "sg:postcode":"4560",
    "sg:province":"Li\u00e8ge",
    "wof:name":"Karine Onclin",
    "wof:placetype":"venue"
},
  "geometry": {"coordinates":[5.3671860695,50.4320030212],"type":"Point"}
}