{
  "type": "Feature",
  "properties": {
    "addr:full":"Rue Couture D'orroir 3 Mont-de-l'enclus (amougies) Hainaut 7750",
    "addr:housenumber":"3",
    "addr:postcode":"7750",
    "addr:street":"Rue Couture D'Orroir;Amougies Hainaut",
    "iso:country":"BE",
    "sg:address":"Rue Couture D'orroir 3",
    "sg:city":"Mont-de-l'enclus (amougies)",
    "sg:classifiers":[
        {
            "category":"Professional",
            "subcategory":"Testing Lab",
            "type":"Services"
        }
    ],
    "sg:phone":"+32 69 76 80 76",
    "sg:postcode":"7750",
    "sg:province":"Hainaut",
    "sg:tags":[
        "chemist"
    ],
    "wof:name":"Vromant A-m",
    "wof:placetype":"venue"
},
  "geometry": {"coordinates":[-0.2632879913,47.0404434204],"type":"Point"}
}