{
  "type": "Feature",
  "properties": {
    "iso:country":"BE",
    "sg:address":"Bellemstraat 24",
    "sg:city":"Aalter",
    "sg:orig_category":"Epiceries",
    "sg:phone":"+32 9 374 05 67",
    "sg:postcode":"9880",
    "sg:province":"Oost-Vlaanderen",
    "wof:name":"Spar",
    "wof:placetype":"venue"
},
  "geometry": {"coordinates":[3.4509971142,51.084186554],"type":"Point"}
}