{
  "type": "Feature",
  "properties": {
    "iso:country":"BE",
    "sg:address":"Rijselstraat 110",
    "sg:city":"Menen",
    "sg:orig_category":"Artsen and specialisten",
    "sg:phone":"+32 56 51 39 30",
    "sg:postcode":"8930",
    "sg:province":"West-Vlaanderen",
    "wof:name":"Gilberte De Prins",
    "wof:placetype":"venue"
},
  "geometry": {"coordinates":[3.124628067,50.7914924622],"type":"Point"}
}