{
  "type": "Feature",
  "properties": {
    "addr:full":"Beukenstraat 17 Bilzen Limburg 3740",
    "addr:housenumber":"17",
    "addr:postcode":"3740",
    "addr:street":"Beukenstraat",
    "iso:country":"BE",
    "sg:address":"Beukenstraat 17",
    "sg:city":"Bilzen",
    "sg:orig_category":"Instellingen voor mindervalide volwassenen",
    "sg:phone":"+32 89 41 66 30",
    "sg:postcode":"3740",
    "sg:province":"Limburg",
    "wof:name":"Elkon",
    "wof:placetype":"venue"
},
  "geometry": {"coordinates":[5.5150198936,50.8669700623],"type":"Point"}
}