{
  "type": "Feature",
  "properties": {
    "addr:full":"Rue Croisette 42 Mons (jemappes) Hainaut 7012",
    "addr:housenumber":"42",
    "addr:postcode":"7012",
    "addr:street":"Rue Croisette",
    "iso:country":"BE",
    "sg:address":"Rue Croisette 42",
    "sg:city":"Mons (jemappes)",
    "sg:classifiers":[
        {
            "category":"Building & Trades",
            "subcategory":"Construction",
            "type":"Services"
        }
    ],
    "sg:phone":"+32 65 88 64 23",
    "sg:postcode":"7012",
    "sg:province":"Hainaut",
    "sg:tags":[
        "installation",
        "-",
        "central",
        "heating"
    ],
    "wof:name":"Charlier A",
    "wof:placetype":"venue"
},
  "geometry": {"coordinates":[3.8894600868,50.4481964111],"type":"Point"}
}