{
  "type": "Feature",
  "properties": {
    "iso:country":"BE",
    "sg:address":"Noordstraat 11-13",
    "sg:city":"Veurne",
    "sg:classifiers":[
        {
            "category":"Arts & Performance",
            "subcategory":"Art Gallery",
            "type":"Entertainment"
        }
    ],
    "sg:phone":"+32 58 31 15 05",
    "sg:postcode":"8630",
    "sg:province":"West-Vlaanderen",
    "wof:name":"Dino Bureaus 1575",
    "wof:placetype":"venue"
},
  "geometry": {"coordinates":[2.6625850201,51.0731735229],"type":"Point"}
}