{
  "type": "Feature",
  "properties": {
    "addr:full":"Kallestraat 37 Alveringem West-Vlaanderen 8691",
    "addr:housenumber":"37",
    "addr:postcode":"8691",
    "addr:street":"Kallestraat",
    "iso:country":"BE",
    "sg:address":"Kallestraat 37",
    "sg:city":"Alveringem",
    "sg:orig_category":"Varkenskwekers",
    "sg:phone":"+32 57 30 05 30",
    "sg:postcode":"8691",
    "sg:province":"West-Vlaanderen",
    "wof:name":"Joseph De Vos",
    "wof:placetype":"venue"
},
  "geometry": {"coordinates":[2.6479859352,50.9521255493],"type":"Point"}
}