{
  "type": "Feature",
  "properties": {
    "iso:country":"BE",
    "sg:address":"Visserijstraat 42",
    "sg:city":"Diepenbeek",
    "sg:orig_category":"R\u00e9alisation de programmes and logiciels",
    "sg:phone":"+32 11 35 03 20",
    "sg:postcode":"3590",
    "sg:province":"Limburg",
    "wof:name":"Iquality",
    "wof:placetype":"venue"
},
  "geometry": {"coordinates":[5.4470648766,50.918182373],"type":"Point"}
}