{
  "type": "Feature",
  "properties": {
    "iso:country":"BE",
    "sg:address":"Rue De La Broque 22",
    "sg:city":"Fernelmont (cortil-wodon)",
    "sg:classifiers":[
        {
            "category":"Home & Garden",
            "subcategory":"Garden Supply",
            "type":"Retail Goods"
        }
    ],
    "sg:phone":"+32 81 83 54 73",
    "sg:postcode":"5380",
    "sg:province":"Namur",
    "sg:tags":[
        "lawn",
        "mower"
    ],
    "wof:name":"Promeca (tondeuses)",
    "wof:placetype":"venue"
},
  "geometry": {"coordinates":[4.9861078262,50.5531463623],"type":"Point"}
}