{
  "type": "Feature",
  "properties": {
    "iso:country":"BE",
    "sg:address":"Dieweg 48",
    "sg:city":"Ukkel/uccle",
    "sg:classifiers":[
        {
            "category":"Insurance",
            "subcategory":"Life Insurance",
            "type":"Services"
        }
    ],
    "sg:phone":"+32 2 374 37 79",
    "sg:postcode":"1180",
    "sg:province":"Bruxelles-Capitale",
    "sg:tags":[
        "assurance"
    ],
    "wof:name":"R. Stercq",
    "wof:placetype":"venue"
},
  "geometry": {"coordinates":[4.3389949799,50.7935066223],"type":"Point"}
}