{
  "type": "Feature",
  "properties": {
    "iso:country":"BE",
    "sg:address":"Rue Arthur Warocqu\u00c9 2",
    "sg:city":"La Louviere",
    "sg:orig_category":"M\u00e9decins and sp\u00e9cialistes",
    "sg:phone":"+32 64 44 47 00",
    "sg:postcode":"7100",
    "sg:province":"Hainaut",
    "wof:name":"Pierre Strebelle",
    "wof:placetype":"venue"
},
  "geometry": {"coordinates":[4.1901049614,50.4777755737],"type":"Point"}
}