{
  "type": "Feature",
  "properties": {
    "addr:full":"Rue De La Maison D' Orbais 17 Gembloux-sur-orneau (corroy-le-ch\u00e2teau) Namur 5032",
    "addr:housenumber":"17",
    "addr:postcode":"5032",
    "addr:street":"Rue De La Maison D ' Orbais;Corroy-Le-Cha\u0302Teau",
    "iso:country":"BE",
    "sg:address":"Rue De La Maison D' Orbais 17",
    "sg:city":"Gembloux-sur-orneau (corroy-le-ch\u00e2teau)",
    "sg:classifiers":[
        {
            "category":"Building & Trades",
            "subcategory":"Plumbing",
            "type":"Services"
        }
    ],
    "sg:phone":"+32 81 63 48 74",
    "sg:postcode":"5032",
    "sg:province":"Namur",
    "sg:tags":[
        "contractor"
    ],
    "wof:name":"Fenaux",
    "wof:placetype":"venue"
},
  "geometry": {"coordinates":[4.6599869728,50.5358314514],"type":"Point"}
}