{
  "type": "Feature",
  "properties": {
    "iso:country":"BE",
    "sg:address":"Rue Des D\u00c9port\u00c9s 142",
    "sg:city":"Charleroi",
    "sg:orig_category":"Assurances. Evaluation and estimation de biens immobiliers",
    "sg:phone":"+32 71 30 74 66",
    "sg:postcode":"6032",
    "sg:province":"Hainaut",
    "wof:name":"Van Eesbeeck Bureau",
    "wof:placetype":"venue"
},
  "geometry": {"coordinates":[4.4183130264,50.387840271],"type":"Point"}
}