{
  "type": "Feature",
  "properties": {
    "addr:full":"Bredabaan 179 Brasschaat Antwerpen 2930",
    "addr:housenumber":"179",
    "addr:postcode":"2930",
    "addr:street":"Bredabaan",
    "iso:country":"BE",
    "sg:address":"Bredabaan 179",
    "sg:city":"Brasschaat",
    "sg:classifiers":[
        {
            "category":"Real Estate",
            "subcategory":"Architect",
            "type":"Services"
        }
    ],
    "sg:phone":"+32 3 651 71 77",
    "sg:postcode":"2930",
    "sg:province":"Antwerpen",
    "wof:name":"Simons F",
    "wof:placetype":"venue"
},
  "geometry": {"coordinates":[4.4849748611,51.2859725952],"type":"Point"}
}