{
  "type": "Feature",
  "properties": {
    "addr:full":"Halensebaan 493b Box 6 Diest Vlaams-Brabant 3290",
    "addr:housenumber":"493b;6",
    "addr:postcode":"3290",
    "addr:street":"Halensebaan;Box",
    "iso:country":"BE",
    "sg:address":"Halensebaan 493b Box 6",
    "sg:city":"Diest",
    "sg:classifiers":[
        {
            "category":"Building & Trades",
            "subcategory":"Electrical",
            "type":"Services"
        }
    ],
    "sg:phone":"+32 13 31 47 54",
    "sg:postcode":"3290",
    "sg:province":"Vlaams-Brabant",
    "sg:tags":[
        "electric",
        "-",
        "housewiring",
        "contractor"
    ],
    "wof:name":"Blue Star Bvba",
    "wof:placetype":"venue"
},
  "geometry": {"coordinates":[5.0782198906,50.9655303955],"type":"Point"}
}