{
  "type": "Feature",
  "properties": {
    "addr:full":"Waterschransweg 1b4 Lier Antwerpen 2500",
    "addr:housenumber":"1b4",
    "addr:postcode":"2500",
    "addr:street":"Waterschransweg",
    "iso:country":"BE",
    "sg:address":"Waterschransweg 1b4",
    "sg:city":"Lier",
    "sg:orig_category":"Activit\u00e9s diverses d'imprimerie",
    "sg:phone":"+32 3 480 21 34",
    "sg:postcode":"2500",
    "sg:province":"Antwerpen",
    "wof:name":"D.s.p. Graphics",
    "wof:placetype":"venue"
},
  "geometry": {"coordinates":[4.5483298302,51.1227760315],"type":"Point"}
}