{
  "type": "Feature",
  "properties": {
    "addr:full":"Rue De La Fourchin\u00c9e 20 Momignies Hainaut 6596",
    "addr:housenumber":"20",
    "addr:postcode":"6596",
    "addr:street":"Rue De La Fourchine\u0301E;Hainaut",
    "iso:country":"BE",
    "sg:address":"Rue De La Fourchin\u00c9e 20",
    "sg:city":"Momignies",
    "sg:orig_category":"Meubelzaken, woning- and keukeninrichting",
    "sg:phone":"+32 60 51 13 17",
    "sg:postcode":"6596",
    "sg:province":"Hainaut",
    "wof:name":"Meubles Honor\u00c9",
    "wof:placetype":"venue"
},
  "geometry": {"coordinates":[4.2488131523,49.9992027283],"type":"Point"}
}