{
  "type": "Feature",
  "properties": {
    "addr:full":"Shopping I Genk Limburg 3600",
    "addr:postcode":"3600",
    "addr:street":"Limburg",
    "iso:country":"BE",
    "sg:address":"Shopping I",
    "sg:city":"Genk",
    "sg:classifiers":[
        {
            "category":"Shopping",
            "subcategory":"Clothing, Apparel, & Fashions",
            "type":"Retail Goods"
        }
    ],
    "sg:phone":"+32 89 35 08 54",
    "sg:postcode":"3600",
    "sg:province":"Limburg",
    "sg:tags":[
        "lady",
        "clothing",
        "-"
    ],
    "wof:name":"Indra",
    "wof:placetype":"venue"
},
  "geometry": {"coordinates":[5.4931697845,50.9654083252],"type":"Point"}
}