{
  "type": "Feature",
  "properties": {
    "addr:full":"Volksstraat 57 Diepenbeek Limburg 3590",
    "addr:housenumber":"57",
    "addr:postcode":"3590",
    "addr:street":"Volksstraat",
    "iso:country":"BE",
    "sg:address":"Volksstraat 57",
    "sg:city":"Diepenbeek",
    "sg:classifiers":[
        {
            "category":"Bakery",
            "type":"Food & Drink"
        }
    ],
    "sg:phone":"+32 11 33 15 34",
    "sg:postcode":"3590",
    "sg:province":"Limburg",
    "sg:tags":[
        "confectioner",
        "baker"
    ],
    "wof:name":"St-antonius",
    "wof:placetype":"venue"
},
  "geometry": {"coordinates":[5.4593229294,50.9145927429],"type":"Point"}
}