{
  "type": "Feature",
  "properties": {
    "addr:full":"Rue Defacqz 115 Elsene/ixelles Bruxelles-Capitale 1050",
    "addr:housenumber":"115",
    "addr:postcode":"1050",
    "addr:street":"Rue Defacqz",
    "iso:country":"BE",
    "sg:address":"Rue Defacqz 115",
    "sg:city":"Elsene/ixelles",
    "sg:orig_category":"Parfumeries",
    "sg:phone":"+32 2 537 02 35",
    "sg:postcode":"1050",
    "sg:province":"Bruxelles-Capitale",
    "wof:name":"Gilette Belgium",
    "wof:placetype":"venue"
},
  "geometry": {"coordinates":[4.3583698273,50.8274002075],"type":"Point"}
}