{
  "type": "Feature",
  "properties": {
    "addr:full":"Rue Provinciale 424 Box 2 Juprelle (fexhe-slins) Li\u00e8ge 4458",
    "addr:housenumber":"424;2",
    "addr:postcode":"4458",
    "addr:street":"Rue Provinciale;Box;Fexhe-Slins",
    "iso:country":"BE",
    "sg:address":"Rue Provinciale 424 Box 2",
    "sg:city":"Juprelle (fexhe-slins)",
    "sg:classifiers":[
        {
            "category":"Building & Trades",
            "subcategory":"Construction",
            "type":"Services"
        }
    ],
    "sg:phone":"+32 4 278 16 21",
    "sg:postcode":"4458",
    "sg:province":"Li\u00e8ge",
    "sg:tags":[
        "stucco",
        "contractor"
    ],
    "wof:name":"Jpl Plafonnage",
    "wof:placetype":"venue"
},
  "geometry": {"coordinates":[5.5669198036,50.7078514099],"type":"Point"}
}