{
  "type": "Feature",
  "properties": {
    "iso:country":"BE",
    "sg:address":"Puttestraat 15",
    "sg:city":"Zottegem",
    "sg:orig_category":"Rundveehouders",
    "sg:phone":"+32 9 360 26 75",
    "sg:postcode":"9620",
    "sg:province":"Oost-Vlaanderen",
    "wof:name":"Sylvain De Buyst",
    "wof:placetype":"venue"
},
  "geometry": {"coordinates":[3.7808740139,50.8946380615],"type":"Point"}
}