{
  "type": "Feature",
  "properties": {
    "addr:full":"Rue Du Marotin 1 Tintigny Luxembourg 6730",
    "addr:housenumber":"1",
    "addr:postcode":"6730",
    "addr:street":"Rue Du Marotin",
    "iso:country":"BE",
    "sg:address":"Rue Du Marotin 1",
    "sg:city":"Tintigny",
    "sg:classifiers":[
        {
            "category":"Arena",
            "subcategory":"Sports Club",
            "type":"Entertainment"
        }
    ],
    "sg:phone":"+32 63 44 40 12",
    "sg:postcode":"6730",
    "sg:province":"Luxembourg",
    "sg:tags":[
        "terrain",
        "hors",
        "de",
        "installation",
        "sportifs"
    ],
    "wof:name":"F.c. Tintigny",
    "wof:placetype":"venue"
},
  "geometry": {"coordinates":[5.5146050453,49.6830673218],"type":"Point"}
}