{
  "type": "Feature",
  "properties": {
    "addr:full":"Jagershoek 4 Anzegem West-Vlaanderen 8570",
    "addr:housenumber":"4",
    "addr:postcode":"8570",
    "addr:street":"Jagershoek",
    "iso:country":"BE",
    "sg:address":"Jagershoek 4",
    "sg:city":"Anzegem",
    "sg:orig_category":"Winkelinrichting and handelsuitrusting Gh Zuivelproducten",
    "sg:phone":"+32 56 77 77 76",
    "sg:postcode":"8570",
    "sg:province":"West-Vlaanderen",
    "wof:name":"Kortrijks Koffiehuis",
    "wof:placetype":"venue"
},
  "geometry": {"coordinates":[3.3877639771,50.8416404724],"type":"Point"}
}