{
  "type": "Feature",
  "properties": {
    "iso:country":"BE",
    "sg:address":"Rue Neerveld 109",
    "sg:city":"Bruxelles (woluwe-saint-lambert)",
    "sg:orig_category":"Newspapers, magazines, periodicals - Publishers",
    "sg:phone":"+32 2 776 26 40",
    "sg:postcode":"1200",
    "sg:province":"Bruxelles-Capitale",
    "wof:name":"Marie Claire (editeur Sbpp)",
    "wof:placetype":"venue"
},
  "geometry": {"coordinates":[4.4424629211,50.8534355164],"type":"Point"}
}