{
  "type": "Feature",
  "properties": {
    "addr:full":"Heestertplaats 1 Zwevegem West-Vlaanderen 8551",
    "addr:housenumber":"1",
    "addr:postcode":"8551",
    "addr:street":"Heestertplaats",
    "iso:country":"BE",
    "sg:address":"Heestertplaats 1",
    "sg:city":"Zwevegem",
    "sg:orig_category":"Banken and kredietinstellingen",
    "sg:phone":"+32 56 64 43 04",
    "sg:postcode":"8551",
    "sg:province":"West-Vlaanderen",
    "wof:name":"Kbc",
    "wof:placetype":"venue"
},
  "geometry": {"coordinates":[3.4109840393,50.782283783],"type":"Point"}
}