{
  "type": "Feature",
  "properties": {
    "iso:country":"BE",
    "sg:address":"Rue De Hombroux 45",
    "sg:city":"Ans (alleur)",
    "sg:classifiers":[
        {
            "category":"Structure",
            "subcategory":"Office Building",
            "type":"Public Place"
        }
    ],
    "sg:phone":"+32 4 246 51 92",
    "sg:postcode":"4432",
    "sg:province":"Li\u00e8ge",
    "sg:tags":[
        "drawing"
    ],
    "wof:name":"Montigny J",
    "wof:placetype":"venue"
},
  "geometry": {"coordinates":[5.5198631287,50.6770935059],"type":"Point"}
}