{
  "type": "Feature",
  "properties": {
    "iso:country":"BE",
    "sg:address":"Vlierboomstraat 146",
    "sg:city":"Tervuren",
    "sg:orig_category":"Entretien and r\u00e9parations de voitures",
    "sg:phone":"+32 2 767 67 75",
    "sg:postcode":"3080",
    "sg:province":"Vlaams-Brabant",
    "wof:name":"F. Selvais",
    "wof:placetype":"venue"
},
  "geometry": {"coordinates":[4.5075101852,50.8171691895],"type":"Point"}
}