{
  "type": "Feature",
  "properties": {
    "iso:country":"BE",
    "sg:address":"Eernegemsestraat 28a Box 1-1",
    "sg:city":"Zedelgem (aartrijke)",
    "sg:classifiers":[
        {
            "category":"Banks & Credit Unions",
            "subcategory":"Bank",
            "type":"Services"
        }
    ],
    "sg:phone":"+32 50 24 05 71",
    "sg:postcode":"8211",
    "sg:province":"West-Vlaanderen",
    "sg:tags":[
        "savings-banks"
    ],
    "wof:name":"Hbk Spaarbank",
    "wof:placetype":"venue"
},
  "geometry": {"coordinates":[3.0889649391,51.1200408936],"type":"Point"}
}