{
  "type": "Feature",
  "properties": {
    "addr:full":"Dorpsplein 21 Kortenaken Vlaams-Brabant 3470",
    "addr:housenumber":"21",
    "addr:postcode":"3470",
    "addr:street":"Dorpsplein",
    "iso:country":"BE",
    "sg:address":"Dorpsplein 21",
    "sg:city":"Kortenaken",
    "sg:classifiers":[
        {
            "category":"Building & Trades",
            "subcategory":"Construction",
            "type":"Services"
        }
    ],
    "sg:phone":"+32 11 58 43 21",
    "sg:postcode":"3470",
    "sg:province":"Vlaams-Brabant",
    "sg:tags":[
        "carpenter"
    ],
    "wof:name":"Vanhove & Zn Bvba",
    "wof:placetype":"venue"
},
  "geometry": {"coordinates":[5.0587677956,50.9092941284],"type":"Point"}
}