{
  "type": "Feature",
  "properties": {
    "addr:full":"Rue Lucien Burnotte 3 Neufch\u00e2teau Luxembourg 6840",
    "addr:housenumber":"3",
    "addr:postcode":"6840",
    "addr:street":"Rue Lucien Burnotte",
    "iso:country":"BE",
    "sg:address":"Rue Lucien Burnotte 3",
    "sg:city":"Neufch\u00e2teau",
    "sg:classifiers":[
        {
            "category":"Arts & Performance",
            "subcategory":"Art Gallery",
            "type":"Entertainment"
        }
    ],
    "sg:phone":"+32 61 27 80 86",
    "sg:postcode":"6840",
    "sg:province":"Luxembourg",
    "wof:name":"Capucine Galerie",
    "wof:placetype":"venue"
},
  "geometry": {"coordinates":[5.4359340668,49.8407363892],"type":"Point"}
}