{
  "type": "Feature",
  "properties": {
    "iso:country":"BE",
    "sg:address":"Blijdorpstraat 1",
    "sg:city":"Buggenhout",
    "sg:classifiers":[
        {
            "category":"Freight",
            "type":"Transportation"
        }
    ],
    "sg:phone":"+32 52 33 05 74",
    "sg:postcode":"9255",
    "sg:province":"Oost-Vlaanderen",
    "sg:tags":[
        "-",
        "transport"
    ],
    "wof:name":"Imfitra Nv",
    "wof:placetype":"venue"
},
  "geometry": {"coordinates":[4.1722698212,51.0239448547],"type":"Point"}
}