{
  "type": "Feature",
  "properties": {
    "iso:country":"BE",
    "sg:address":"Halve Weg 62",
    "sg:city":"Zonhoven",
    "sg:orig_category":"Bloemen and planten Fleurop Interflora",
    "sg:phone":"+32 11 81 36 17",
    "sg:postcode":"3520",
    "sg:province":"Limburg",
    "wof:name":"Bruggen",
    "wof:placetype":"venue"
},
  "geometry": {"coordinates":[5.343047142,50.9934158325],"type":"Point"}
}