{
  "type": "Feature",
  "properties": {
    "addr:full":"Mechelsesteenweg 110 Wezembeek-oppem/wezembeek-oppem Vlaams-Brabant 1970",
    "addr:housenumber":"110",
    "addr:postcode":"1970",
    "addr:street":"Mechelsesteenweg",
    "iso:country":"BE",
    "sg:address":"Mechelsesteenweg 110",
    "sg:city":"Wezembeek-oppem/wezembeek-oppem",
    "sg:orig_category":"Speelgoed",
    "sg:phone":"+32 2 731 80 91",
    "sg:postcode":"1970",
    "sg:province":"Vlaams-Brabant",
    "wof:name":"Christiaensen",
    "wof:placetype":"venue"
},
  "geometry": {"coordinates":[4.4944500923,50.8403167725],"type":"Point"}
}