{
  "type": "Feature",
  "properties": {
    "iso:country":"BE",
    "sg:address":"Tienne De Bouge 6",
    "sg:city":"Namur",
    "sg:orig_category":"Cr\u00e9meries",
    "sg:phone":"+32 81 21 41 06",
    "sg:postcode":"5004",
    "sg:province":"Namur",
    "wof:name":"Maison Pirard",
    "wof:placetype":"venue"
},
  "geometry": {"coordinates":[4.8821229935,50.4769592285],"type":"Point"}
}