{
  "type": "Feature",
  "properties": {
    "addr:full":"Rue Muller-tesch 38 Messancy Luxembourg 6780",
    "addr:housenumber":"38",
    "addr:postcode":"6780",
    "addr:street":"Rue Muller-Tesch",
    "iso:country":"BE",
    "sg:address":"Rue Muller-tesch 38",
    "sg:city":"Messancy",
    "sg:orig_category":"Diverse organisaties and verenigingen",
    "sg:phone":"+32 63 38 64 50",
    "sg:postcode":"6780",
    "sg:province":"Luxembourg",
    "wof:name":"La Cassine",
    "wof:placetype":"venue"
},
  "geometry": {"coordinates":[5.8106918335,49.5961685181],"type":"Point"}
}