{
  "type": "Feature",
  "properties": {
    "addr:full":"Oliedamstraat 10 Ieper West-Vlaanderen 8900",
    "addr:housenumber":"10",
    "addr:postcode":"8900",
    "addr:street":"Oliedamstraat",
    "iso:country":"BE",
    "sg:address":"Oliedamstraat 10",
    "sg:city":"Ieper",
    "sg:classifiers":[
        {
            "category":"Food & Beverages",
            "subcategory":"Meat & Fish",
            "type":"Retail Goods"
        }
    ],
    "sg:phone":"+32 57 21 94 06",
    "sg:postcode":"8900",
    "sg:province":"West-Vlaanderen",
    "sg:tags":[
        "bedspread",
        "blanket",
        "-"
    ],
    "wof:name":"Limlijn (de)",
    "wof:placetype":"venue"
},
  "geometry": {"coordinates":[2.869797945,50.8563194275],"type":"Point"}
}