{
  "type": "Feature",
  "properties": {
    "iso:country":"BE",
    "sg:address":"Rue Provinciale 67",
    "sg:city":"Herstal",
    "sg:classifiers":[
        {
            "category":"Cafe",
            "type":"Food & Drink"
        }
    ],
    "sg:phone":"+32 4 278 46 44",
    "sg:postcode":"4042",
    "sg:province":"Li\u00e8ge",
    "sg:tags":[
        "caf\u00e9s"
    ],
    "wof:name":"Caf\u00c9 Le Central",
    "wof:placetype":"venue"
},
  "geometry": {"coordinates":[5.5639448166,50.69373703],"type":"Point"}
}