{
  "type": "Feature",
  "properties": {
    "addr:full":"Hoogveld 23 Dendermonde (sint-gillis-bij-dendermonde) Oost-Vlaanderen 9200",
    "addr:housenumber":"23",
    "addr:postcode":"9200",
    "addr:street":"Hoogveld",
    "iso:country":"BE",
    "sg:address":"Hoogveld 23",
    "sg:city":"Dendermonde (sint-gillis-bij-dendermonde)",
    "sg:classifiers":[
        {
            "category":"Retail",
            "subcategory":"Auto Repair",
            "type":"Services"
        }
    ],
    "sg:phone":"+32 52 21 19 05",
    "sg:postcode":"9200",
    "sg:province":"Oost-Vlaanderen",
    "sg:tags":[
        "garage"
    ],
    "wof:name":"Dendermotors Bvba",
    "wof:placetype":"venue"
},
  "geometry": {"coordinates":[4.1374249458,51.0314598083],"type":"Point"}
}