{
  "type": "Feature",
  "properties": {
    "addr:full":"Chauss\u00c9e De Mons 243 Sint-pieters-leeuw Vlaams-Brabant 1600",
    "addr:housenumber":"243",
    "addr:postcode":"1600",
    "addr:street":"Chausse\u0301E De Mons",
    "iso:country":"BE",
    "sg:address":"Chauss\u00c9e De Mons 243",
    "sg:city":"Sint-pieters-leeuw",
    "sg:classifiers":[
        {
            "category":"Fast Food",
            "type":"Food & Drink"
        }
    ],
    "sg:phone":"+32 2 378 01 08",
    "sg:postcode":"1600",
    "sg:province":"Vlaams-Brabant",
    "sg:tags":[
        "\u00c0",
        "emporter",
        "restaurants"
    ],
    "wof:name":"Yan - Yan",
    "wof:placetype":"venue"
},
  "geometry": {"coordinates":[4.2845067978,50.7947540283],"type":"Point"}
}