{
  "type": "Feature",
  "properties": {
    "addr:full":"L. De Brouck\u00c8rlaan 44 Ganshoren Bruxelles-Capitale 1083",
    "addr:housenumber":"44",
    "addr:postcode":"1083",
    "addr:street":"L.;Broucke\u0300Rlaan",
    "iso:country":"BE",
    "sg:address":"L. De Brouck\u00c8rlaan 44",
    "sg:city":"Ganshoren",
    "sg:orig_category":"Dakwerken Industri\u00eble and commerci\u00eble bouw Woningbouw",
    "sg:phone":"+32 2 426 49 57",
    "sg:postcode":"1083",
    "sg:province":"Bruxelles-Capitale",
    "wof:name":"Bouwonderneming Demesmaeker",
    "wof:placetype":"venue"
},
  "geometry": {"coordinates":[4.3165178299,50.873878479],"type":"Point"}
}