{
  "type": "Feature",
  "properties": {
    "iso:country":"BE",
    "sg:address":"Hagelandkaai 2",
    "sg:city":"Gent",
    "sg:classifiers":[
        {
            "category":"Real Estate",
            "subcategory":"Architect",
            "type":"Services"
        }
    ],
    "sg:phone":"+32 9 225 74 33",
    "sg:postcode":"9000",
    "sg:province":"Oost-Vlaanderen",
    "wof:name":"Paelinck P",
    "wof:placetype":"venue"
},
  "geometry": {"coordinates":[3.7369699478,51.0564804077],"type":"Point"}
}