{
  "type": "Feature",
  "properties": {
    "addr:full":"Rue De L'h\u00f4tel De Ville 6 Habay (habay-la-neuve) Luxembourg 6720",
    "addr:housenumber":"6",
    "addr:postcode":"6720",
    "addr:street":"Rue De L'Ho \u0302Tel De Ville",
    "iso:country":"BE",
    "sg:address":"Rue De L'h\u00f4tel De Ville 6",
    "sg:city":"Habay (habay-la-neuve)",
    "sg:classifiers":[
        {
            "category":"Shopping",
            "subcategory":"Shoes",
            "type":"Retail Goods"
        }
    ],
    "sg:phone":"+32 63 42 22 08",
    "sg:postcode":"6720",
    "sg:province":"Luxembourg",
    "sg:tags":[
        "slipper",
        "-"
    ],
    "wof:name":"Escarmelle",
    "wof:placetype":"venue"
},
  "geometry": {"coordinates":[5.6485447884,49.7289009094],"type":"Point"}
}