{
  "type": "Feature",
  "properties": {
    "iso:country":"BE",
    "sg:address":"Bruggesteenweg 155b",
    "sg:city":"Hooglede (gits)",
    "sg:classifiers":[
        {
            "category":"Shopping",
            "subcategory":"Computers & Home Electronics",
            "type":"Retail Goods"
        }
    ],
    "sg:phone":"+32 51 20 32 64",
    "sg:postcode":"8830",
    "sg:province":"West-Vlaanderen",
    "sg:tags":[
        "automobile",
        "-",
        "navigation",
        "system"
    ],
    "wof:name":"Caro/spriet Roeland",
    "wof:placetype":"venue"
},
  "geometry": {"coordinates":[3.1184489727,50.9829063416],"type":"Point"}
}