{
  "type": "Feature",
  "properties": {
    "iso:country":"BE",
    "sg:address":"Rue Du Becquereau 23",
    "sg:city":"Celles (escanaffles)",
    "sg:classifiers":[
        {
            "category":"Manufacturing",
            "subcategory":"Tools & Machinery",
            "type":"Manufacturing & Wholesale Goods"
        }
    ],
    "sg:phone":"+32 69 76 61 10",
    "sg:postcode":"7760",
    "sg:province":"Hainaut",
    "sg:tags":[
        "-"
    ],
    "wof:name":"Covaner Sprl",
    "wof:placetype":"venue"
},
  "geometry": {"coordinates":[3.4694399834,50.7320289612],"type":"Point"}
}