{
  "type": "Feature",
  "properties": {
    "addr:full":"Schietschijfstraat 48 Schaarbeek/schaerbeek Bruxelles-Capitale 1030",
    "addr:housenumber":"48",
    "addr:postcode":"1030",
    "addr:street":"Schietschijfstraat",
    "iso:country":"BE",
    "sg:address":"Schietschijfstraat 48",
    "sg:city":"Schaarbeek/schaerbeek",
    "sg:orig_category":"Krantenuitgeverijen Tijdschriftenuitgeverijen",
    "sg:phone":"+32 2 734 80 55",
    "sg:postcode":"1030",
    "sg:province":"Bruxelles-Capitale",
    "wof:name":"Editions Pol\u00c9mique",
    "wof:placetype":"venue"
},
  "geometry": {"coordinates":[4.3822898865,50.8518066406],"type":"Point"}
}