{
  "type": "Feature",
  "properties": {
    "addr:full":"Groenstraat 64a Aalst (erembodegem) Oost-Vlaanderen 9320",
    "addr:housenumber":"64a",
    "addr:postcode":"9320",
    "addr:street":"Groenstraat",
    "iso:country":"BE",
    "sg:address":"Groenstraat 64a",
    "sg:city":"Aalst (erembodegem)",
    "sg:classifiers":[
        {
            "category":"Personal",
            "subcategory":"Beauty Salon",
            "type":"Services"
        }
    ],
    "sg:phone":"+32 53 77 21 08",
    "sg:postcode":"9320",
    "sg:province":"Oost-Vlaanderen",
    "sg:tags":[
        "lady",
        "-",
        "hairdressing"
    ],
    "wof:name":"De Rijcke",
    "wof:placetype":"venue"
},
  "geometry": {"coordinates":[4.050866127,50.9435043335],"type":"Point"}
}