{
  "type": "Feature",
  "properties": {
    "iso:country":"BE",
    "sg:address":"Rue Fourneau 23",
    "sg:city":"Saint-l\u00e9ger (ch\u00e2tillon)",
    "sg:classifiers":[
        {
            "category":"Farming",
            "subcategory":"Fish & Marine Products",
            "type":"Manufacturing & Wholesale Goods"
        }
    ],
    "sg:phone":"+32 63 23 70 02",
    "sg:postcode":"6747",
    "sg:province":"Luxembourg",
    "sg:tags":[
        "equipment",
        "fishery"
    ],
    "wof:name":"Pecherie Du Fourneau David",
    "wof:placetype":"venue"
},
  "geometry": {"coordinates":[5.6813139915,49.6244850159],"type":"Point"}
}