{
  "type": "Feature",
  "properties": {
    "addr:full":"Bc Reg Aalst3 Industriezone Aalst Oost-Vlaanderen 9320",
    "addr:postcode":"9320",
    "addr:street":"Industriezone",
    "iso:country":"BE",
    "sg:address":"Bc Reg Aalst3 Industriezone",
    "sg:city":"Aalst",
    "sg:orig_category":"Produits pharmaceutiques Gr",
    "sg:phone":"+32 53 85 35 36",
    "sg:postcode":"9320",
    "sg:province":"Oost-Vlaanderen",
    "wof:name":"Pharma Support",
    "wof:placetype":"venue"
},
  "geometry": {"coordinates":[4.0553851128,50.9209976196],"type":"Point"}
}