{
  "type": "Feature",
  "properties": {
    "iso:country":"BE",
    "sg:address":"Weynesbaan 185",
    "sg:city":"Putte",
    "sg:classifiers":[
        {
            "category":"Bakery",
            "type":"Food & Drink"
        }
    ],
    "sg:phone":"+32 15 75 51 01",
    "sg:postcode":"2580",
    "sg:province":"Antwerpen",
    "sg:tags":[
        "confectioner",
        "baker"
    ],
    "wof:name":"Bakkerij Vloeberghs",
    "wof:placetype":"venue"
},
  "geometry": {"coordinates":[4.5916337967,51.0350532532],"type":"Point"}
}