{
  "type": "Feature",
  "properties": {
    "addr:full":"Edith Cavellstraat 185 Ukkel/uccle Bruxelles-Capitale 1180",
    "addr:housenumber":"185",
    "addr:postcode":"1180",
    "addr:street":"Edith Cavellstraat;/",
    "iso:country":"BE",
    "sg:address":"Edith Cavellstraat 185",
    "sg:city":"Ukkel/uccle",
    "sg:orig_category":"Drukkerijen and copyshops",
    "sg:phone":"+32 2 374 32 86",
    "sg:postcode":"1180",
    "sg:province":"Bruxelles-Capitale",
    "wof:name":"Atelier Vertical",
    "wof:placetype":"venue"
},
  "geometry": {"coordinates":[4.3583140373,50.8049583435],"type":"Point"}
}