{
  "type": "Feature",
  "properties": {
    "addr:full":"Chauss\u00c9e De Bruxelles 271 Charleroi Hainaut 6040",
    "addr:housenumber":"271",
    "addr:postcode":"6040",
    "addr:street":"Chausse\u0301E De Bruxelles;Hainaut",
    "iso:country":"BE",
    "sg:address":"Chauss\u00c9e De Bruxelles 271",
    "sg:city":"Charleroi",
    "sg:orig_category":"Herstellingen and onderhoud aan huis voor voertuigen Herstellingen and onderhoud van auto's Metaalaf",
    "sg:phone":"+32 71 35 20 41",
    "sg:postcode":"6040",
    "sg:province":"Hainaut",
    "wof:name":"A.d.d.",
    "wof:placetype":"venue"
},
  "geometry": {"coordinates":[4.4360852242,50.4447555542],"type":"Point"}
}