{
  "type": "Feature",
  "properties": {
    "addr:full":"Heirstraat 218b2 Maasmechelen Limburg 3630",
    "addr:housenumber":"218b2",
    "addr:postcode":"3630",
    "addr:street":"Heirstraat",
    "iso:country":"BE",
    "sg:address":"Heirstraat 218b2",
    "sg:city":"Maasmechelen",
    "sg:orig_category":"Promoteurs immobiliers",
    "sg:phone":"+32 89 76 11 41",
    "sg:postcode":"3630",
    "sg:province":"Limburg",
    "wof:name":"Alsoco",
    "wof:placetype":"venue"
},
  "geometry": {"coordinates":[5.6974577904,50.9642066956],"type":"Point"}
}