{
  "type": "Feature",
  "properties": {
    "addr:full":"Oudstrijderslaan 60 Zoersel Antwerpen 2980",
    "addr:housenumber":"60",
    "addr:postcode":"2980",
    "addr:street":"Oudstrijderslaan",
    "iso:country":"BE",
    "sg:address":"Oudstrijderslaan 60",
    "sg:city":"Zoersel",
    "sg:classifiers":[
        {
            "category":"Professional",
            "subcategory":"Art Services",
            "type":"Services"
        }
    ],
    "sg:phone":"+32 3 385 87 98",
    "sg:postcode":"2980",
    "sg:province":"Antwerpen",
    "sg:tags":[
        "designer",
        "display"
    ],
    "wof:name":"Etalages Nadine",
    "wof:placetype":"venue"
},
  "geometry": {"coordinates":[4.6535568237,51.2607803345],"type":"Point"}
}