{
  "type": "Feature",
  "properties": {
    "addr:full":"Route De Henri Chapelle 88 Dison (andrimont) Li\u00e8ge 4821",
    "addr:housenumber":"88",
    "addr:postcode":"4821",
    "addr:street":"Route De Henri Chapelle",
    "iso:country":"BE",
    "sg:address":"Route De Henri Chapelle 88",
    "sg:city":"Dison (andrimont)",
    "sg:classifiers":[
        {
            "category":"Food & Beverages",
            "subcategory":"Meat & Fish",
            "type":"Retail Goods"
        }
    ],
    "sg:phone":"+32 87 31 55 05",
    "sg:postcode":"4821",
    "sg:province":"Li\u00e8ge",
    "sg:tags":[
        "-",
        "livestock"
    ],
    "wof:name":"Royen Agri Sprl",
    "wof:placetype":"venue"
},
  "geometry": {"coordinates":[5.8875408173,50.620010376],"type":"Point"}
}