{
  "type": "Feature",
  "properties": {
    "iso:country":"BE",
    "sg:address":"Groenstraat 85",
    "sg:city":"Lint",
    "sg:classifiers":[
        {
            "category":"Professional",
            "subcategory":"Accounting & Tax Preparation",
            "type":"Services"
        }
    ],
    "sg:phone":"+32 3 454 22 22",
    "sg:postcode":"2547",
    "sg:province":"Antwerpen",
    "sg:tags":[
        "accountant"
    ],
    "wof:name":"Dons H",
    "wof:placetype":"venue"
},
  "geometry": {"coordinates":[4.484418869,51.1346740723],"type":"Point"}
}