{
  "type": "Feature",
  "properties": {
    "addr:full":"Heembeeksestraat 157 Brussel/bruxelles Bruxelles-Capitale 1120",
    "addr:housenumber":"157",
    "addr:postcode":"1120",
    "addr:street":"Heembeeksestraat;/",
    "iso:country":"BE",
    "sg:address":"Heembeeksestraat 157",
    "sg:city":"Brussel/bruxelles",
    "sg:orig_category":"Artsen and specialisten",
    "sg:phone":"+32 2 245 53 15",
    "sg:postcode":"1120",
    "sg:province":"Bruxelles-Capitale",
    "wof:name":"James Frecourt",
    "wof:placetype":"venue"
},
  "geometry": {"coordinates":[4.3803868294,50.890953064],"type":"Point"}
}