{
  "type": "Feature",
  "properties": {
    "iso:country":"BE",
    "sg:address":"Rue Du Pr\u00c9ay 123",
    "sg:city":"Li\u00c8ge",
    "sg:orig_category":"Artsen and specialisten",
    "sg:phone":"+32 4 227 04 64",
    "sg:postcode":"4000",
    "sg:province":"Li\u00e8ge",
    "wof:name":"M. Deneufbourg",
    "wof:placetype":"venue"
},
  "geometry": {"coordinates":[5.5929398537,50.6645507812],"type":"Point"}
}