{
  "type": "Feature",
  "properties": {
    "iso:country":"BE",
    "sg:address":"Ankerstraat 56",
    "sg:city":"Sint-niklaas",
    "sg:orig_category":"Mat\u00e9riel \u00e9lectrique and \u00e9lectronique Gr",
    "sg:phone":"+32 3 776 08 92",
    "sg:postcode":"9100",
    "sg:province":"Oost-Vlaanderen",
    "wof:name":"Electro Hilco",
    "wof:placetype":"venue"
},
  "geometry": {"coordinates":[4.1468992233,51.1663551331],"type":"Point"}
}