{
  "type": "Feature",
  "properties": {
    "iso:country":"BE",
    "sg:address":"Stationstraat 4b75",
    "sg:city":"Turnhout",
    "sg:orig_category":"S\u00e9curit\u00e9 sociale",
    "sg:phone":"+32 14 41 70 99",
    "sg:postcode":"2300",
    "sg:province":"Antwerpen",
    "wof:name":"Liberale Mutualiteit",
    "wof:placetype":"venue"
},
  "geometry": {"coordinates":[4.9386119843,51.3221855164],"type":"Point"}
}