{
  "type": "Feature",
  "properties": {
    "iso:country":"BE",
    "sg:address":"Hoogstraatsebaan 176",
    "sg:city":"Malle",
    "sg:orig_category":"Groententeelt",
    "sg:phone":"+32 3 311 71 26",
    "sg:postcode":"2390",
    "sg:province":"Antwerpen",
    "wof:name":"Frans Mertens",
    "wof:placetype":"venue"
},
  "geometry": {"coordinates":[4.737642765,51.3127975464],"type":"Point"}
}