{
  "type": "Feature",
  "properties": {
    "iso:country":"BE",
    "sg:address":"Dreef 15",
    "sg:city":"Mol",
    "sg:orig_category":"Artsen and specialisten",
    "sg:phone":"+32 14 31 84 24",
    "sg:postcode":"2400",
    "sg:province":"Antwerpen",
    "wof:name":"H. Verwimp",
    "wof:placetype":"venue"
},
  "geometry": {"coordinates":[5.1528630257,51.1911087036],"type":"Point"}
}