{
  "type": "Feature",
  "properties": {
    "iso:country":"BE",
    "sg:address":"Visesteenweg 207bb",
    "sg:city":"Riemst",
    "sg:orig_category":"Epiceries",
    "sg:phone":"+32 12 45 55 55",
    "sg:postcode":"3770",
    "sg:province":"Limburg",
    "wof:name":"Superette L. & L.",
    "wof:placetype":"venue"
},
  "geometry": {"coordinates":[5.6054201126,50.8047485352],"type":"Point"}
}