{
  "type": "Feature",
  "properties": {
    "addr:full":"Rue De Lorrene 51 Chiny Luxembourg 6810",
    "addr:housenumber":"51",
    "addr:postcode":"6810",
    "addr:street":"Rue De Lorrene",
    "iso:country":"BE",
    "sg:address":"Rue De Lorrene 51",
    "sg:city":"Chiny",
    "sg:classifiers":[
        {
            "category":"Utilities",
            "subcategory":"Cable",
            "type":"Services"
        }
    ],
    "sg:phone":"+32 61 32 07 20",
    "sg:postcode":"6810",
    "sg:province":"Luxembourg",
    "sg:tags":[
        "forestry"
    ],
    "wof:name":"Transcobois S.c.r.l.",
    "wof:placetype":"venue"
},
  "geometry": {"coordinates":[5.3423981667,49.7396430969],"type":"Point"}
}