{
  "type": "Feature",
  "properties": {
    "addr:full":"Rue Du Moulin-de-roly 21 Philippeville Namur 5600",
    "addr:housenumber":"21",
    "addr:postcode":"5600",
    "addr:street":"Rue Du Moulin-De-Roly",
    "iso:country":"BE",
    "sg:address":"Rue Du Moulin-de-roly 21",
    "sg:city":"Philippeville",
    "sg:orig_category":"Sportclubs",
    "sg:phone":"+32 60 31 17 30",
    "sg:postcode":"5600",
    "sg:province":"Namur",
    "wof:name":"Badminton Club Couvin",
    "wof:placetype":"venue"
},
  "geometry": {"coordinates":[4.5354270935,50.1356964111],"type":"Point"}
}