{
  "type": "Feature",
  "properties": {
    "iso:country":"BE",
    "sg:address":"Grijze -zustersstraat 1-1",
    "sg:city":"Kortrijk",
    "sg:classifiers":[
        {
            "category":"Shopping",
            "subcategory":"Clothing, Apparel, & Fashions",
            "type":"Retail Goods"
        }
    ],
    "sg:phone":"+32 56 22 82 14",
    "sg:postcode":"8500",
    "sg:province":"West-Vlaanderen",
    "sg:tags":[
        "lady",
        "clothing",
        "-"
    ],
    "wof:name":"Natan",
    "wof:placetype":"venue"
},
  "geometry": {"coordinates":[3.2687849998,50.8272743225],"type":"Point"}
}