{
  "type": "Feature",
  "properties": {
    "addr:full":"Avenue De L\u00b4europe 18 Charleroi Hainaut 6000",
    "addr:housenumber":"18",
    "addr:postcode":"6000",
    "addr:street":"Avenue De L\u00b4Europe;Hainaut",
    "iso:country":"BE",
    "sg:address":"Avenue De L\u00b4europe 18",
    "sg:city":"Charleroi",
    "sg:classifiers":[
        {
            "category":"Fast Food",
            "type":"Food & Drink"
        }
    ],
    "sg:phone":"+32 71 31 72 45",
    "sg:postcode":"6000",
    "sg:province":"Hainaut",
    "sg:tags":[
        "restaurant",
        "\u00c0",
        "domicile",
        "o",
        "catering",
        "emporter",
        "livraison",
        "restaurants"
    ],
    "wof:name":"Restaurant De L\u00b4 Europe",
    "wof:placetype":"venue"
},
  "geometry": {"coordinates":[4.4420380592,50.4127960205],"type":"Point"}
}