{
  "type": "Feature",
  "properties": {
    "iso:country":"BE",
    "sg:address":"Kromvendreef 81",
    "sg:city":"Schoten",
    "sg:classifiers":[
        {
            "category":"Building & Trades",
            "subcategory":"Cleaning & Sanitation",
            "type":"Services"
        }
    ],
    "sg:phone":"+32 3 685 31 63",
    "sg:postcode":"2900",
    "sg:province":"Antwerpen",
    "sg:tags":[
        "blast"
    ],
    "wof:name":"Cover Bvba",
    "wof:placetype":"venue"
},
  "geometry": {"coordinates":[4.5275268555,51.2748260498],"type":"Point"}
}