{
  "type": "Feature",
  "properties": {
    "iso:country":"BE",
    "sg:address":"Rue De Charleroi 44",
    "sg:city":"Genappe",
    "sg:orig_category":"HERSTELLING ELEKTRISCHE HUISHOUDAPPARATEN Huishoudapparaten, televisies and radio's",
    "sg:phone":"+32 67 77 32 62",
    "sg:postcode":"1470",
    "sg:province":"Brabant Wallon",
    "wof:name":"Maison Cartrysse",
    "wof:placetype":"venue"
},
  "geometry": {"coordinates":[4.4501900673,50.6092262268],"type":"Point"}
}