{
  "type": "Feature",
  "properties": {
    "iso:country":"BE",
    "sg:address":"Eduard Robeynslaan 52",
    "sg:city":"Diest",
    "sg:orig_category":"Artsen and specialisten",
    "sg:phone":"+32 13 33 35 95",
    "sg:postcode":"3290",
    "sg:province":"Vlaams-Brabant",
    "wof:name":"Rita Jacquemijn",
    "wof:placetype":"venue"
},
  "geometry": {"coordinates":[5.0591650009,50.9778862],"type":"Point"}
}