{
  "type": "Feature",
  "properties": {
    "iso:country":"BE",
    "sg:address":"Riemenstraat 55",
    "sg:city":"Vorselaar",
    "sg:classifiers":[
        {
            "category":"Personal",
            "subcategory":"Beauty Salon",
            "type":"Services"
        }
    ],
    "sg:phone":"+32 14 50 08 62",
    "sg:postcode":"2290",
    "sg:province":"Antwerpen",
    "wof:name":"Schoonheidshuisje ('t)",
    "wof:placetype":"venue"
},
  "geometry": {"coordinates":[4.7767977715,51.2045936584],"type":"Point"}
}