{
  "type": "Feature",
  "properties": {
    "iso:country":"BE",
    "sg:address":"Rue Emile Urbain 132",
    "sg:city":"La Louvi\u00e8re",
    "sg:classifiers":[
        {
            "category":"Community Center",
            "type":"Public Place"
        }
    ],
    "sg:phone":"+32 64 26 13 00",
    "sg:postcode":"7100",
    "sg:province":"Hainaut",
    "sg:tags":[
        "medical"
    ],
    "wof:name":"Institut Medico-sportif",
    "wof:placetype":"venue"
},
  "geometry": {"coordinates":[4.1696357727,50.4662742615],"type":"Point"}
}