{
  "type": "Feature",
  "properties": {
    "addr:full":"Rue Du Brou 46 Verviers Li\u00e8ge 4800",
    "addr:housenumber":"46",
    "addr:postcode":"4800",
    "addr:street":"Rue Du Brou",
    "iso:country":"BE",
    "sg:address":"Rue Du Brou 46",
    "sg:city":"Verviers",
    "sg:orig_category":"Dameskledingzaken",
    "sg:phone":"+32 87 31 71 21",
    "sg:postcode":"4800",
    "sg:province":"Li\u00e8ge",
    "wof:name":"Etam",
    "wof:placetype":"venue"
},
  "geometry": {"coordinates":[5.8585867882,50.5924797058],"type":"Point"}
}