{
  "type": "Feature",
  "properties": {
    "addr:full":"Dreef Ter Walle 19 Wevelgem (gullegem) West-Vlaanderen 8560",
    "addr:housenumber":"19",
    "addr:postcode":"8560",
    "addr:street":"Dreef Ter Walle",
    "iso:country":"BE",
    "sg:address":"Dreef Ter Walle 19",
    "sg:city":"Wevelgem (gullegem)",
    "sg:classifiers":[
        {
            "category":"Arts & Performance",
            "subcategory":"Music",
            "type":"Entertainment"
        }
    ],
    "sg:phone":"+32 56 41 58 55",
    "sg:postcode":"8560",
    "sg:province":"West-Vlaanderen",
    "sg:tags":[
        "disc-jockeys"
    ],
    "wof:name":"Midi Music",
    "wof:placetype":"venue"
},
  "geometry": {"coordinates":[3.2170488834,50.8384017944],"type":"Point"}
}