{
  "type": "Feature",
  "properties": {
    "addr:full":"Stokkelse Steenweg 205 Sint-lambrechts-woluwe/woluwe-saint-lambert Bruxelles-Capitale 1200",
    "addr:housenumber":"205;/",
    "addr:postcode":"1200",
    "addr:street":"Stokkelse Steenweg;Sint-Lambrechts-Woluwe",
    "iso:country":"BE",
    "sg:address":"Stokkelse Steenweg 205",
    "sg:city":"Sint-lambrechts-woluwe/woluwe-saint-lambert",
    "sg:orig_category":"Sportclubs",
    "sg:phone":"+32 2 771 36 67",
    "sg:postcode":"1200",
    "sg:province":"Bruxelles-Capitale",
    "wof:name":"Royal Linthout Bc W.s.l.",
    "wof:placetype":"venue"
},
  "geometry": {"coordinates":[4.4461832047,50.8410797119],"type":"Point"}
}