{
  "type": "Feature",
  "properties": {
    "iso:country":"BE",
    "sg:address":"Rue Des Puits L'eau 32-34",
    "sg:city":"Tournai",
    "sg:classifiers":[
        {
            "category":"Shopping",
            "subcategory":"Jewelry",
            "type":"Retail Goods"
        }
    ],
    "sg:phone":"+32 69 23 62 11",
    "sg:postcode":"7500",
    "sg:province":"Hainaut",
    "sg:tags":[
        "jeweller",
        "-"
    ],
    "wof:name":"Delrue",
    "wof:placetype":"venue"
},
  "geometry": {"coordinates":[3.392031908,50.6057853699],"type":"Point"}
}