{
  "type": "Feature",
  "properties": {
    "addr:full":"Moorstr 25a Nevele Oost-Vlaanderen 9850",
    "addr:housenumber":"25a",
    "addr:postcode":"9850",
    "addr:street":"Moorstr",
    "iso:country":"BE",
    "sg:address":"Moorstr 25a",
    "sg:city":"Nevele",
    "sg:classifiers":[
        {
            "category":"Professional",
            "subcategory":"Engineering",
            "type":"Services"
        }
    ],
    "sg:phone":"+32 9 282 22 07",
    "sg:postcode":"9850",
    "sg:province":"Oost-Vlaanderen",
    "sg:tags":[
        "machine",
        "-",
        "mechanical"
    ],
    "wof:name":"Ldl Nv",
    "wof:placetype":"venue"
},
  "geometry": {"coordinates":[3.5898940563,51.0447845459],"type":"Point"}
}