{
  "type": "Feature",
  "properties": {
    "iso:country":"BE",
    "sg:address":"Rue Neuve Chauss\u00e9e 79",
    "sg:city":"P\u00e9ruwelz",
    "sg:classifiers":[
        {
            "category":"Food & Beverages",
            "subcategory":"Fruits & Vegetables",
            "type":"Retail Goods"
        }
    ],
    "sg:phone":"+32 69 77 47 07",
    "sg:postcode":"7600",
    "sg:province":"Hainaut",
    "sg:tags":[
        "-"
    ],
    "wof:name":"Jardin D'eden (le)",
    "wof:placetype":"venue"
},
  "geometry": {"coordinates":[3.5996980667,50.5157165527],"type":"Point"}
}