{
  "type": "Feature",
  "properties": {
    "addr:full":"Rue Du Bois 284 Tournai Hainaut 7531",
    "addr:housenumber":"284",
    "addr:postcode":"7531",
    "addr:street":"Rue Du Bois",
    "iso:country":"BE",
    "sg:address":"Rue Du Bois 284",
    "sg:city":"Tournai",
    "sg:orig_category":"Eleveurs de bovins. Installations and terrains de sport hors centres sportifs",
    "sg:phone":"+32 69 54 62 74",
    "sg:postcode":"7531",
    "sg:province":"Hainaut",
    "wof:name":"Francis Delobel",
    "wof:placetype":"venue"
},
  "geometry": {"coordinates":[3.4616699219,50.6152877808],"type":"Point"}
}