{
  "type": "Feature",
  "properties": {
    "iso:country":"BE",
    "sg:address":"Meensesteenweg 583",
    "sg:city":"Roeselare",
    "sg:orig_category":"Fotografen and fotostudio's",
    "sg:phone":"+32 51 20 05 70",
    "sg:postcode":"8800",
    "sg:province":"West-Vlaanderen",
    "wof:name":"Koenraad Keirsschieter",
    "wof:placetype":"venue"
},
  "geometry": {"coordinates":[3.1183900833,50.9258003235],"type":"Point"}
}