{
  "type": "Feature",
  "properties": {
    "iso:country":"BE",
    "sg:address":"Watermolenstraat 33",
    "sg:city":"Lierde",
    "sg:orig_category":"Woningbouw",
    "sg:phone":"+32 54 41 12 15",
    "sg:postcode":"9570",
    "sg:province":"Oost-Vlaanderen",
    "wof:name":"Noel Cosyns",
    "wof:placetype":"venue"
},
  "geometry": {"coordinates":[3.8422870636,50.7965011597],"type":"Point"}
}