{
  "type": "Feature",
  "properties": {
    "addr:full":"Jan Palfynlaan 104 Bruxelles (jette) Bruxelles-Capitale 1090",
    "addr:housenumber":"104",
    "addr:postcode":"1090",
    "addr:street":"Jan Palfynlaan",
    "iso:country":"BE",
    "sg:address":"Jan Palfynlaan 104",
    "sg:city":"Bruxelles (jette)",
    "sg:classifiers":[
        {
            "category":"Health Services",
            "subcategory":"Dentist",
            "type":"Services"
        }
    ],
    "sg:phone":"+32 2 478 84 22",
    "sg:postcode":"1090",
    "sg:province":"Bruxelles-Capitale",
    "wof:name":"Vander Stichele K",
    "wof:placetype":"venue"
},
  "geometry": {"coordinates":[4.3269309998,50.8935775757],"type":"Point"}
}