{
  "type": "Feature",
  "properties": {
    "addr:full":"Stationsstraat 190 Lanaken Limburg 3620",
    "addr:housenumber":"190",
    "addr:postcode":"3620",
    "addr:street":"Stationsstraat",
    "iso:country":"BE",
    "sg:address":"Stationsstraat 190",
    "sg:city":"Lanaken",
    "sg:classifiers":[
        {
            "category":"Cafe",
            "type":"Food & Drink"
        }
    ],
    "sg:phone":"+32 89 71 72 95",
    "sg:postcode":"3620",
    "sg:province":"Limburg",
    "sg:tags":[
        "caf\u00e9s"
    ],
    "wof:name":"Caf\u00c9 Bierhuis",
    "wof:placetype":"venue"
},
  "geometry": {"coordinates":[5.6420998573,50.8859214783],"type":"Point"}
}