{
  "type": "Feature",
  "properties": {
    "addr:full":"Route De Trazegnies 87 Charleroi Hainaut 6031",
    "addr:housenumber":"87",
    "addr:postcode":"6031",
    "addr:street":"Route De Trazegnies;Hainaut",
    "iso:country":"BE",
    "sg:address":"Route De Trazegnies 87",
    "sg:city":"Charleroi",
    "sg:orig_category":"Artistes ind\u00e9pendants",
    "sg:phone":"+32 71 31 13 51",
    "sg:postcode":"6031",
    "sg:province":"Hainaut",
    "wof:name":"Salvatore Gucciardo",
    "wof:placetype":"venue"
},
  "geometry": {"coordinates":[4.38022995,50.4121742249],"type":"Point"}
}