{
  "type": "Feature",
  "properties": {
    "iso:country":"BE",
    "sg:address":"Route De Charleroi 317",
    "sg:city":"Binche (leval-trahegnies)",
    "sg:classifiers":[
        {
            "category":"Personal",
            "subcategory":"Beauty Salon",
            "type":"Services"
        }
    ],
    "sg:phone":"+32 64 33 61 77",
    "sg:postcode":"7134",
    "sg:province":"Hainaut",
    "sg:tags":[
        "lady",
        "-",
        "hairdressing"
    ],
    "wof:name":"Dominique",
    "wof:placetype":"venue"
},
  "geometry": {"coordinates":[4.2194561958,50.4081993103],"type":"Point"}
}