{
  "type": "Feature",
  "properties": {
    "addr:full":"Rue De Castagne 2 Box 1 Profondeville (rivi\u00e8re) Namur 5170",
    "addr:housenumber":"2;1",
    "addr:postcode":"5170",
    "addr:street":"Rue De Castagne;Box",
    "iso:country":"BE",
    "sg:address":"Rue De Castagne 2 Box 1",
    "sg:city":"Profondeville (rivi\u00e8re)",
    "sg:classifiers":[
        {
            "category":"Retail",
            "subcategory":"Repair Shop",
            "type":"Services"
        }
    ],
    "sg:phone":"+32 81 41 41 79",
    "sg:postcode":"5170",
    "sg:province":"Namur",
    "sg:tags":[
        "radio",
        "television",
        "-",
        "maintenance"
    ],
    "wof:name":"A.c. Electronics",
    "wof:placetype":"venue"
},
  "geometry": {"coordinates":[4.8674049377,50.3786392212],"type":"Point"}
}