{
  "type": "Feature",
  "properties": {
    "addr:full":"Vestingstraat 13-15 Halle Vlaams-Brabant 1500",
    "addr:housenumber":"13-15",
    "addr:postcode":"1500",
    "addr:street":"Vestingstraat",
    "iso:country":"BE",
    "sg:address":"Vestingstraat 13-15",
    "sg:city":"Halle",
    "sg:classifiers":[
        {
            "category":"Wholesale",
            "subcategory":"Beer",
            "type":"Manufacturing & Wholesale Goods"
        }
    ],
    "sg:phone":"+32 2 356 58 12",
    "sg:postcode":"1500",
    "sg:province":"Vlaams-Brabant",
    "sg:tags":[
        "ale",
        "-"
    ],
    "wof:name":"Dedobbeleer M",
    "wof:placetype":"venue"
},
  "geometry": {"coordinates":[4.2353701591,50.737449646],"type":"Point"}
}