{
  "type": "Feature",
  "properties": {
    "iso:country":"BE",
    "sg:address":"Steenweg Linde 27",
    "sg:city":"Peer",
    "sg:orig_category":"Woningbouw",
    "sg:phone":"+32 11 79 14 91",
    "sg:postcode":"3990",
    "sg:province":"Limburg",
    "wof:name":"Hendrik Scheelen",
    "wof:placetype":"venue"
},
  "geometry": {"coordinates":[5.4488530159,51.1052360535],"type":"Point"}
}