{
  "type": "Feature",
  "properties": {
    "addr:full":"Rue Des Canadiens 182 La Louvi\u00e8re (str\u00e9py-bracquegnies) Hainaut 7110",
    "addr:housenumber":"182",
    "addr:postcode":"7110",
    "addr:street":"Rue Des Canadiens",
    "iso:country":"BE",
    "sg:address":"Rue Des Canadiens 182",
    "sg:city":"La Louvi\u00e8re (str\u00e9py-bracquegnies)",
    "sg:classifiers":[
        {
            "category":"Food & Beverages",
            "subcategory":"Groceries & Convenience Stores",
            "type":"Retail Goods"
        }
    ],
    "sg:phone":"+32 64 66 47 34",
    "sg:postcode":"7110",
    "sg:province":"Hainaut",
    "sg:tags":[
        "grocer"
    ],
    "wof:name":"Deham G",
    "wof:placetype":"venue"
},
  "geometry": {"coordinates":[4.1505050659,50.4826698303],"type":"Point"}
}