{
  "type": "Feature",
  "properties": {
    "iso:country":"BE",
    "sg:address":"Kolmenstraat 49",
    "sg:city":"Hasselt",
    "sg:orig_category":"Loodgieterij, verwarming and sanitaire installaties",
    "sg:phone":"+32 11 31 12 85",
    "sg:postcode":"3512",
    "sg:province":"Limburg",
    "wof:name":"Douce",
    "wof:placetype":"venue"
},
  "geometry": {"coordinates":[5.2411608696,50.9173278809],"type":"Point"}
}