{
  "type": "Feature",
  "properties": {
    "iso:country":"BE",
    "sg:address":"Ganzendries 77",
    "sg:city":"Lubbeek",
    "sg:orig_category":"Quincailleries. Mat\u00e9riaux de construction Gr",
    "sg:phone":"+32 16 46 12 90",
    "sg:postcode":"3212",
    "sg:province":"Vlaams-Brabant",
    "wof:name":"Fa. Wauters",
    "wof:placetype":"venue"
},
  "geometry": {"coordinates":[4.7945699692,50.8717346191],"type":"Point"}
}