{
  "type": "Feature",
  "properties": {
    "iso:country":"BE",
    "sg:address":"Leopold Ii Laan 271",
    "sg:city":"Koekelberg/koekelberg",
    "sg:orig_category":"Artsen and specialisten",
    "sg:phone":"+32 2 428 66 33",
    "sg:postcode":"1081",
    "sg:province":"Bruxelles-Capitale",
    "wof:name":"Tetadelozege Tepatondele",
    "wof:placetype":"venue"
},
  "geometry": {"coordinates":[4.3318390846,50.8631286621],"type":"Point"}
}