{
  "type": "Feature",
  "properties": {
    "addr:full":"Rue De La Dr\u00eave 76 Clavier Li\u00e8ge 4560",
    "addr:housenumber":"76",
    "addr:postcode":"4560",
    "addr:street":"Rue De La Dre\u0302Ve",
    "iso:country":"BE",
    "sg:address":"Rue De La Dr\u00eave 76",
    "sg:city":"Clavier",
    "sg:classifiers":[
        {
            "category":"Social Services",
            "subcategory":"Job Training",
            "type":"Services"
        }
    ],
    "sg:phone":"+32 495 20 92 10",
    "sg:postcode":"4560",
    "sg:province":"Li\u00e8ge",
    "sg:tags":[
        "personnel"
    ],
    "wof:name":"Guilmain V",
    "wof:placetype":"venue"
},
  "geometry": {"coordinates":[5.3575191498,50.4288978577],"type":"Point"}
}