{
  "type": "Feature",
  "properties": {
    "iso:country":"BE",
    "sg:address":"Teewisstraat 10",
    "sg:city":"Opglabbeek",
    "sg:classifiers":[
        {
            "category":"Building & Trades",
            "subcategory":"Locksmith",
            "type":"Services"
        }
    ],
    "sg:phone":"+32 89 85 20 29",
    "sg:postcode":"3660",
    "sg:province":"Limburg",
    "sg:tags":[
        "material",
        "road"
    ],
    "wof:name":"Kasseike ('t)",
    "wof:placetype":"venue"
},
  "geometry": {"coordinates":[5.5731592178,51.038394928],"type":"Point"}
}