{
  "type": "Feature",
  "properties": {
    "addr:full":"Grote Markt 40 Sint-truiden Limburg 3800",
    "addr:housenumber":"40",
    "addr:postcode":"3800",
    "addr:street":"Grote Markt",
    "iso:country":"BE",
    "sg:address":"Grote Markt 40",
    "sg:city":"Sint-truiden",
    "sg:classifiers":[
        {
            "category":"Bars & Pubs",
            "type":"Food & Drink"
        }
    ],
    "sg:phone":"+32 11 68 02 83",
    "sg:postcode":"3800",
    "sg:province":"Limburg",
    "sg:tags":[
        "tavern"
    ],
    "wof:name":"Bacchus",
    "wof:placetype":"venue"
},
  "geometry": {"coordinates":[5.1849808693,50.815120697],"type":"Point"}
}