{
  "type": "Feature",
  "properties": {
    "iso:country":"BE",
    "sg:address":"Watermaalse Steenweg 15",
    "sg:city":"Oudergem/auderghem",
    "sg:orig_category":"Verhuur cateringmateriaal and evenementuitrusting Winkelinrichting and handelsuitrusting Gh",
    "sg:phone":"+32 2 673 36 28",
    "sg:postcode":"1160",
    "sg:province":"Bruxelles-Capitale",
    "wof:name":"J.m. Location",
    "wof:placetype":"venue"
},
  "geometry": {"coordinates":[4.419547081,50.8174057007],"type":"Point"}
}