{
  "type": "Feature",
  "properties": {
    "iso:country":"BE",
    "sg:address":"Groenstraat 12",
    "sg:city":"Sint-niklaas",
    "sg:orig_category":"GROENTEN AND FRUIT Groenten and fruit Gh",
    "sg:phone":"+32 3 772 26 90",
    "sg:postcode":"9111",
    "sg:province":"Oost-Vlaanderen",
    "wof:name":"Citrus-vruchten",
    "wof:placetype":"venue"
},
  "geometry": {"coordinates":[4.0922698975,51.1616477966],"type":"Point"}
}