{
  "type": "Feature",
  "properties": {
    "addr:full":"Schatting 64ba Zedelgem West-Vlaanderen 8210",
    "addr:housenumber":"64ba",
    "addr:postcode":"8210",
    "addr:street":"Schatting",
    "iso:country":"BE",
    "sg:address":"Schatting 64ba",
    "sg:city":"Zedelgem",
    "sg:orig_category":"Bouwmaterialen Gh Serres and speciale beglazing",
    "sg:phone":"+32 50 24 13 74",
    "sg:postcode":"8210",
    "sg:province":"West-Vlaanderen",
    "wof:name":"Fa. Vervaecke F.",
    "wof:placetype":"venue"
},
  "geometry": {"coordinates":[3.1428699493,51.1376419067],"type":"Point"}
}