{
  "type": "Feature",
  "properties": {
    "iso:country":"BE",
    "sg:address":"Rue De Waremme 17",
    "sg:city":"Villers-le-bouillet",
    "sg:orig_category":"Openbare veiligheid",
    "sg:phone":"+32 85 24 00 94",
    "sg:postcode":"4530",
    "sg:province":"Li\u00e8ge",
    "wof:name":"Police F\u00c9d\u00c9rale",
    "wof:placetype":"venue"
},
  "geometry": {"coordinates":[5.2683959007,50.5686683655],"type":"Point"}
}