{
  "type": "Feature",
  "properties": {
    "iso:country":"BE",
    "sg:address":"Dorpskring 10",
    "sg:city":"Lubbeek",
    "sg:orig_category":"Apotheken",
    "sg:phone":"+32 16 63 46 07",
    "sg:postcode":"3210",
    "sg:province":"Vlaams-Brabant",
    "wof:name":"Celis",
    "wof:placetype":"venue"
},
  "geometry": {"coordinates":[4.8418560028,50.8818664551],"type":"Point"}
}