{
  "type": "Feature",
  "properties": {
    "addr:full":"Rue De Gibraltar 146 Estaimpuis Hainaut 7730",
    "addr:housenumber":"146",
    "addr:postcode":"7730",
    "addr:street":"Rue De Gibraltar;Hainaut",
    "iso:country":"BE",
    "sg:address":"Rue De Gibraltar 146",
    "sg:city":"Estaimpuis",
    "sg:orig_category":"Boucheries",
    "sg:phone":"+32 69 35 20 26",
    "sg:postcode":"7730",
    "sg:province":"Hainaut",
    "wof:name":"Bernard Derouf",
    "wof:placetype":"venue"
},
  "geometry": {"coordinates":[3.2549259663,50.6734733582],"type":"Point"}
}