{
  "type": "Feature",
  "properties": {
    "iso:country":"BE",
    "sg:address":"Rue De L'argili\u00c8re 86",
    "sg:city":"Mons",
    "sg:orig_category":"Installatie van houten of kunststof schrijnwerk",
    "sg:phone":"+32 65 88 42 51",
    "sg:postcode":"7012",
    "sg:province":"Hainaut",
    "wof:name":"Michel Delattre",
    "wof:placetype":"venue"
},
  "geometry": {"coordinates":[3.8934109211,50.4393501282],"type":"Point"}
}