{
  "type": "Feature",
  "properties": {
    "iso:country":"BE",
    "sg:address":"Rue Saint-lambert 76",
    "sg:city":"Brussel/bruxelles",
    "sg:orig_category":"Animations diverses",
    "sg:phone":"+32 2 771 36 69",
    "sg:postcode":"1200",
    "sg:province":"Bruxelles-Capitale",
    "wof:name":"Mc's Sonorisation",
    "wof:placetype":"venue"
},
  "geometry": {"coordinates":[4.4357390404,50.8429489136],"type":"Point"}
}