{
  "type": "Feature",
  "properties": {
    "iso:country":"BE",
    "sg:address":"Rue De La Gare 29",
    "sg:city":"Bi\u00e8vre (graide)",
    "sg:classifiers":[
        {
            "category":"Farming",
            "subcategory":"Livestock Farm",
            "type":"Manufacturing & Wholesale Goods"
        }
    ],
    "sg:phone":"+32 61 51 12 52",
    "sg:postcode":"5555",
    "sg:province":"Namur",
    "sg:tags":[
        "breeding"
    ],
    "wof:name":"Comes J & S",
    "wof:placetype":"venue"
},
  "geometry": {"coordinates":[5.0255022049,49.937713623],"type":"Point"}
}