{
  "type": "Feature",
  "properties": {
    "iso:country":"BE",
    "sg:address":"Rue Roua 53",
    "sg:city":"Amay",
    "sg:orig_category":"Installation de menuiserie en bois and plastique",
    "sg:phone":"+32 85 31 45 92",
    "sg:postcode":"4540",
    "sg:province":"Li\u00e8ge",
    "wof:name":"Christian Hanosset",
    "wof:placetype":"venue"
},
  "geometry": {"coordinates":[5.3143591881,50.5516204834],"type":"Point"}
}