{
  "type": "Feature",
  "properties": {
    "iso:country":"BE",
    "sg:address":"Rue Joseph-marvel 19",
    "sg:city":"Gembloux",
    "sg:orig_category":"Artsen and specialisten",
    "sg:phone":"+32 81 63 42 52",
    "sg:postcode":"5032",
    "sg:province":"Namur",
    "wof:name":"Thierry Verhaegen",
    "wof:placetype":"venue"
},
  "geometry": {"coordinates":[4.6453461647,50.5367546082],"type":"Point"}
}