{
  "type": "Feature",
  "properties": {
    "addr:full":"Kleistraat 12 Sint-katelijne-waver Antwerpen 2860",
    "addr:housenumber":"12",
    "addr:postcode":"2860",
    "addr:street":"Kleistraat",
    "iso:country":"BE",
    "sg:address":"Kleistraat 12",
    "sg:city":"Sint-katelijne-waver",
    "sg:orig_category":"Woningbouw",
    "sg:phone":"+32 15 55 53 00",
    "sg:postcode":"2860",
    "sg:province":"Antwerpen",
    "wof:name":"Frans Verrept",
    "wof:placetype":"venue"
},
  "geometry": {"coordinates":[4.5087900162,51.0646781921],"type":"Point"}
}