{
  "type": "Feature",
  "properties": {
    "addr:full":"Vleugelsstraat 29 Schaarbeek/schaerbeek Bruxelles-Capitale 1030",
    "addr:housenumber":"29",
    "addr:postcode":"1030",
    "addr:street":"Vleugelsstraat",
    "iso:country":"BE",
    "sg:address":"Vleugelsstraat 29",
    "sg:city":"Schaarbeek/schaerbeek",
    "sg:orig_category":"Kapsalons",
    "sg:phone":"+32 2 215 84 74",
    "sg:postcode":"1030",
    "sg:province":"Bruxelles-Capitale",
    "wof:name":"Coiff Mode Mimoun",
    "wof:placetype":"venue"
},
  "geometry": {"coordinates":[4.3758158684,50.867931366],"type":"Point"}
}