{
  "type": "Feature",
  "properties": {
    "iso:country":"BE",
    "sg:address":"Tiensestraat 215a",
    "sg:city":"Leuven",
    "sg:classifiers":[
        {
            "category":"Insurance",
            "subcategory":"Insurance Agent",
            "type":"Services"
        }
    ],
    "sg:phone":"+32 16 22 56 51",
    "sg:postcode":"3000",
    "sg:province":"Vlaams-Brabant",
    "sg:tags":[
        "broker"
    ],
    "wof:name":"Sobimo Bvba",
    "wof:placetype":"venue"
},
  "geometry": {"coordinates":[4.7121419907,50.8744354248],"type":"Point"}
}