{
  "type": "Feature",
  "properties": {
    "addr:full":"Gobbelsrode 49a Holsbeek (kortrijk-dutsel) Vlaams-Brabant 3220",
    "addr:housenumber":"49a",
    "addr:postcode":"3220",
    "addr:street":"Gobbelsrode",
    "iso:country":"BE",
    "sg:address":"Gobbelsrode 49a",
    "sg:city":"Holsbeek (kortrijk-dutsel)",
    "sg:classifiers":[
        {
            "category":"Shopping",
            "subcategory":"Pets & Pet Supplies",
            "type":"Retail Goods"
        }
    ],
    "sg:phone":"+32 16 62 42 06",
    "sg:postcode":"3220",
    "sg:province":"Vlaams-Brabant",
    "sg:tags":[
        "shop",
        "-"
    ],
    "wof:name":"Cattery Sweet Dream",
    "wof:placetype":"venue"
},
  "geometry": {"coordinates":[4.7575721741,50.9207267761],"type":"Point"}
}