{
  "type": "Feature",
  "properties": {
    "addr:full":"Carillolei 12 Aartselaar Antwerpen 2630",
    "addr:housenumber":"12",
    "addr:postcode":"2630",
    "addr:street":"Carillolei",
    "iso:country":"BE",
    "sg:address":"Carillolei 12",
    "sg:city":"Aartselaar",
    "sg:orig_category":"Non-Classified Establishments",
    "sg:phone":"+32 3 877 22 25",
    "sg:postcode":"2630",
    "sg:province":"Antwerpen",
    "wof:name":"Multiple Choice Bvba",
    "wof:placetype":"venue"
},
  "geometry": {"coordinates":[4.3854460716,51.1329193115],"type":"Point"}
}