{
  "type": "Feature",
  "properties": {
    "iso:country":"BE",
    "sg:address":"Oude Brusselsestraat 2",
    "sg:city":"Mechelen",
    "sg:classifiers":[
        {
            "category":"Shopping",
            "subcategory":"Baby Store",
            "type":"Retail Goods"
        }
    ],
    "sg:phone":"+32 15 41 71 45",
    "sg:postcode":"2800",
    "sg:province":"Antwerpen",
    "sg:tags":[
        "-",
        "accessory"
    ],
    "wof:name":"Wanetje",
    "wof:placetype":"venue"
},
  "geometry": {"coordinates":[4.4818968773,51.0222358704],"type":"Point"}
}