{
  "type": "Feature",
  "properties": {
    "addr:full":"Steenweg 100 Gingelom Limburg 3890",
    "addr:housenumber":"100",
    "addr:postcode":"3890",
    "addr:street":"Steenweg",
    "iso:country":"BE",
    "sg:address":"Steenweg 100",
    "sg:city":"Gingelom",
    "sg:orig_category":"Postkantoren Verzekeringsmakelaars and experts",
    "sg:phone":"+32 11 88 10 48",
    "sg:postcode":"3890",
    "sg:province":"Limburg",
    "wof:name":"De Post",
    "wof:placetype":"venue"
},
  "geometry": {"coordinates":[5.1352567673,50.7536048889],"type":"Point"}
}