{
  "type": "Feature",
  "properties": {
    "addr:full":"Casinoplein 6 Blankenberge (groot) West-Vlaanderen 8370",
    "addr:housenumber":"6",
    "addr:postcode":"8370",
    "addr:street":"Casinoplein;Groot West-Vlaanderen",
    "iso:country":"BE",
    "sg:address":"Casinoplein 6",
    "sg:city":"Blankenberge (groot)",
    "sg:classifiers":[
        {
            "category":"Bars & Pubs",
            "subcategory":"Nightclub",
            "type":"Food & Drink"
        }
    ],
    "sg:phone":"+32 50 41 16 53",
    "sg:postcode":"8370",
    "sg:province":"West-Vlaanderen",
    "sg:tags":[
        "nachtclubs",
        "dancing"
    ],
    "wof:name":"The Beatles",
    "wof:placetype":"venue"
},
  "geometry": {"coordinates":[3.1289820671,51.3160362244],"type":"Point"}
}