{
  "type": "Feature",
  "properties": {
    "addr:full":"Avenue C. De Gerlache 40 Liege Li\u00e8ge 4000",
    "addr:housenumber":"40",
    "addr:postcode":"4000",
    "addr:street":"Avenue C. De Gerlache",
    "iso:country":"BE",
    "sg:address":"Avenue C. De Gerlache 40",
    "sg:city":"Liege",
    "sg:orig_category":"Woningbouw",
    "sg:phone":"+32 4 252 56 59",
    "sg:postcode":"4000",
    "sg:province":"Li\u00e8ge",
    "wof:name":"Adv",
    "wof:placetype":"venue"
},
  "geometry": {"coordinates":[5.5724301338,50.6170768738],"type":"Point"}
}