{
  "type": "Feature",
  "properties": {
    "addr:full":"Rue Trapp\u00e9 9 Li\u00e8ge 1 Li\u00e8ge 4000",
    "addr:housenumber":"9;1",
    "addr:postcode":"4000",
    "addr:street":"Rue Trappe\u0301",
    "iso:country":"BE",
    "sg:address":"Rue Trapp\u00e9 9",
    "sg:city":"Li\u00e8ge 1",
    "sg:classifiers":[
        {
            "category":"Shopping",
            "subcategory":"Pets & Pet Supplies",
            "type":"Retail Goods"
        }
    ],
    "sg:phone":"+32 4 220 88 30",
    "sg:postcode":"4000",
    "sg:province":"Li\u00e8ge",
    "sg:tags":[
        "telecopiers"
    ],
    "wof:name":"Bureautique Heens Marcel",
    "wof:placetype":"venue"
},
  "geometry": {"coordinates":[5.5650892258,50.6398696899],"type":"Point"}
}