{
  "type": "Feature",
  "properties": {
    "addr:full":"Stationsstraat 160 Essen Antwerpen 2910",
    "addr:housenumber":"160",
    "addr:postcode":"2910",
    "addr:street":"Stationsstraat",
    "iso:country":"BE",
    "sg:address":"Stationsstraat 160",
    "sg:city":"Essen",
    "sg:orig_category":"Schoonheidssalons",
    "sg:phone":"+32 3 677 14 08",
    "sg:postcode":"2910",
    "sg:province":"Antwerpen",
    "wof:name":"Instituut Chantalle",
    "wof:placetype":"venue"
},
  "geometry": {"coordinates":[4.4582791328,51.4645767212],"type":"Point"}
}