{
  "type": "Feature",
  "properties": {
    "addr:full":"Rue Du Marais 25 Antoing Hainaut 7640",
    "addr:housenumber":"25",
    "addr:postcode":"7640",
    "addr:street":"Rue Du Marais",
    "iso:country":"BE",
    "sg:address":"Rue Du Marais 25",
    "sg:city":"Antoing",
    "sg:orig_category":"Enseignement maternel and primaire",
    "sg:phone":"+32 69 44 26 44",
    "sg:postcode":"7640",
    "sg:province":"Hainaut",
    "wof:name":"Ecole Fondamentale Libre",
    "wof:placetype":"venue"
},
  "geometry": {"coordinates":[3.4519898891,50.565738678],"type":"Point"}
}