{
  "type": "Feature",
  "properties": {
    "iso:country":"BE",
    "sg:address":"Weg Naar As 159",
    "sg:city":"Genk",
    "sg:classifiers":[
        {
            "category":"Utilities",
            "subcategory":"Electric",
            "type":"Services"
        }
    ],
    "sg:phone":"+32 89 35 35 35",
    "sg:postcode":"3600",
    "sg:province":"Limburg",
    "sg:tags":[
        "generator"
    ],
    "wof:name":"Autostuc Nv",
    "wof:placetype":"venue"
},
  "geometry": {"coordinates":[5.5156521797,50.9723243713],"type":"Point"}
}