{
  "type": "Feature",
  "properties": {
    "addr:full":"Voie Des Ma\u00e7ons 43 Soumagne Li\u00e8ge 4630",
    "addr:housenumber":"43",
    "addr:postcode":"4630",
    "addr:street":"Voie Des Mac\u0327Ons",
    "iso:country":"BE",
    "sg:address":"Voie Des Ma\u00e7ons 43",
    "sg:city":"Soumagne",
    "sg:classifiers":[
        {
            "category":"Professional",
            "subcategory":"Secretarial Services",
            "type":"Services"
        }
    ],
    "sg:phone":"+32 4 377 41 43",
    "sg:postcode":"4630",
    "sg:province":"Li\u00e8ge",
    "sg:tags":[
        "firm"
    ],
    "wof:name":"Provoost Y",
    "wof:placetype":"venue"
},
  "geometry": {"coordinates":[5.7550082207,50.6202659607],"type":"Point"}
}