{
  "type": "Feature",
  "properties": {
    "iso:country":"BE",
    "sg:address":"Koralenhoeve 25",
    "sg:city":"Wommelgem",
    "sg:classifiers":[
        {
            "category":"Banks & Credit Unions",
            "subcategory":"Investment Brokerage",
            "type":"Services"
        }
    ],
    "sg:phone":"+32 3 355 25 15",
    "sg:postcode":"2160",
    "sg:province":"Antwerpen",
    "sg:tags":[
        "-",
        "transport",
        "related"
    ],
    "wof:name":"Exel Nv",
    "wof:placetype":"venue"
},
  "geometry": {"coordinates":[4.5253839493,51.210723877],"type":"Point"}
}