{
  "type": "Feature",
  "properties": {
    "iso:country":"BE",
    "sg:address":"Avenue Fernand Desonay 91",
    "sg:city":"Verviers (stembert)",
    "sg:classifiers":[
        {
            "category":"Food & Beverages",
            "subcategory":"Fruits & Vegetables",
            "type":"Retail Goods"
        }
    ],
    "sg:phone":"+32 87 22 87 15",
    "sg:postcode":"4801",
    "sg:province":"Li\u00e8ge",
    "sg:tags":[
        "-"
    ],
    "wof:name":"Donneau J",
    "wof:placetype":"venue"
},
  "geometry": {"coordinates":[5.8891220093,50.5880584717],"type":"Point"}
}