{
  "type": "Feature",
  "properties": {
    "iso:country":"BE",
    "sg:address":"Schaagstraat 98",
    "sg:city":"Anzegem",
    "sg:orig_category":"Eleveurs de bovins",
    "sg:phone":"+32 56 60 27 22",
    "sg:postcode":"8570",
    "sg:province":"West-Vlaanderen",
    "wof:name":"Gerard Maes",
    "wof:placetype":"venue"
},
  "geometry": {"coordinates":[3.4321210384,50.8594970703],"type":"Point"}
}