{
  "type": "Feature",
  "properties": {
    "addr:full":"Stationsstraat 46 Waarschoot Oost-Vlaanderen 9950",
    "addr:housenumber":"46",
    "addr:postcode":"9950",
    "addr:street":"Stationsstraat",
    "iso:country":"BE",
    "sg:address":"Stationsstraat 46",
    "sg:city":"Waarschoot",
    "sg:orig_category":"Banken and kredietinstellingen",
    "sg:phone":"+32 9 377 46 03",
    "sg:postcode":"9950",
    "sg:province":"Oost-Vlaanderen",
    "wof:name":"Fortis",
    "wof:placetype":"venue"
},
  "geometry": {"coordinates":[3.6095929146,51.1517486572],"type":"Point"}
}