{
  "type": "Feature",
  "properties": {
    "iso:country":"BE",
    "sg:address":"Hoogstraatsebaan 20",
    "sg:city":"Malle",
    "sg:orig_category":"Boucheries",
    "sg:phone":"+32 3 312 01 64",
    "sg:postcode":"2390",
    "sg:province":"Antwerpen",
    "wof:name":"J. Storms",
    "wof:placetype":"venue"
},
  "geometry": {"coordinates":[4.7353382111,51.3029975891],"type":"Point"}
}