{
  "type": "Feature",
  "properties": {
    "addr:full":"Saunierlei 36 Hemiksem Antwerpen 2620",
    "addr:housenumber":"36",
    "addr:postcode":"2620",
    "addr:street":"Saunierlei",
    "iso:country":"BE",
    "sg:address":"Saunierlei 36",
    "sg:city":"Hemiksem",
    "sg:orig_category":"Instituts de beaut\u00e9",
    "sg:phone":"+32 3 887 71 10",
    "sg:postcode":"2620",
    "sg:province":"Antwerpen",
    "wof:name":"Instituut Di Donna",
    "wof:placetype":"venue"
},
  "geometry": {"coordinates":[4.3370437622,51.1385612488],"type":"Point"}
}