{
  "type": "Feature",
  "properties": {
    "iso:country":"BE",
    "sg:address":"Guylei 15",
    "sg:city":"Brasschaat",
    "sg:orig_category":"Editeurs de livres",
    "sg:phone":"+32 3 651 51 88",
    "sg:postcode":"2930",
    "sg:province":"Antwerpen",
    "wof:name":"Music Marketing",
    "wof:placetype":"venue"
},
  "geometry": {"coordinates":[4.4572319984,51.2881126404],"type":"Point"}
}