{
  "type": "Feature",
  "properties": {
    "iso:country":"BE",
    "sg:address":"Chauss\u00c9e D'alsemberg 719",
    "sg:city":"Ukkel/uccle",
    "sg:orig_category":"Editeurs de livres",
    "sg:phone":"+32 2 345 63 26",
    "sg:postcode":"1180",
    "sg:province":"Bruxelles-Capitale",
    "wof:name":"Computer Accounting",
    "wof:placetype":"venue"
},
  "geometry": {"coordinates":[4.3365569115,50.8047103882],"type":"Point"}
}