{
  "type": "Feature",
  "properties": {
    "iso:country":"BE",
    "sg:address":"Rue De La Casmaterie 31",
    "sg:city":"Chaudfontaine",
    "sg:classifiers":[
        {
            "category":"Manufacturing",
            "subcategory":"Musical Instruments",
            "type":"Manufacturing & Wholesale Goods"
        }
    ],
    "sg:phone":"+32 4 221 42 41",
    "sg:postcode":"4050",
    "sg:province":"Li\u00e8ge",
    "sg:tags":[
        "scientific",
        "apparatus"
    ],
    "wof:name":"Sedd",
    "wof:placetype":"venue"
},
  "geometry": {"coordinates":[5.63372612,50.592754364],"type":"Point"}
}