{
  "type": "Feature",
  "properties": {
    "addr:full":"Dambruggestraat 174 Antwerpen Antwerpen 2060",
    "addr:housenumber":"174",
    "addr:postcode":"2060",
    "addr:street":"Dambruggestraat",
    "iso:country":"BE",
    "sg:address":"Dambruggestraat 174",
    "sg:city":"Antwerpen",
    "sg:classifiers":[
        {
            "category":"Personal",
            "subcategory":"Adult",
            "type":"Services"
        }
    ],
    "sg:phone":"+32 3 266 91 51",
    "sg:postcode":"2060",
    "sg:province":"Antwerpen",
    "sg:tags":[
        "sex-shops"
    ],
    "wof:name":"Adonis Gay Video Club - Erotheek",
    "wof:placetype":"venue"
},
  "geometry": {"coordinates":[4.4217448235,51.223274231],"type":"Point"}
}