{
  "type": "Feature",
  "properties": {
    "addr:full":"Basketbalstraat 4 Lovendegem Oost-Vlaanderen 9920",
    "addr:housenumber":"4",
    "addr:postcode":"9920",
    "addr:street":"Basketbalstraat",
    "iso:country":"BE",
    "sg:address":"Basketbalstraat 4",
    "sg:city":"Lovendegem",
    "sg:classifiers":[
        {
            "category":"Retail",
            "subcategory":"Animal Services",
            "type":"Services"
        }
    ],
    "sg:phone":"+32 9 372 44 43",
    "sg:postcode":"9920",
    "sg:province":"Oost-Vlaanderen",
    "sg:tags":[
        "grooming",
        "-",
        "dog"
    ],
    "wof:name":"Pardoes",
    "wof:placetype":"venue"
},
  "geometry": {"coordinates":[3.6131079197,51.1020317078],"type":"Point"}
}