{
  "type": "Feature",
  "properties": {
    "addr:full":"Rue Sous Ghoy 49 Merbes-le-ch\u00c2teau Hainaut 6567",
    "addr:housenumber":"49",
    "addr:postcode":"6567",
    "addr:street":"Rue Sous Ghoy",
    "iso:country":"BE",
    "sg:address":"Rue Sous Ghoy 49",
    "sg:city":"Merbes-le-ch\u00c2teau",
    "sg:orig_category":"Sportclubs",
    "sg:phone":"+32 71 55 73 85",
    "sg:postcode":"6567",
    "sg:province":"Hainaut",
    "wof:name":"Tennis Club Haute Sambre",
    "wof:placetype":"venue"
},
  "geometry": {"coordinates":[4.1852750778,50.3154411316],"type":"Point"}
}