{
  "type": "Feature",
  "properties": {
    "iso:country":"BE",
    "sg:address":"Regentiestraat 81",
    "sg:city":"Denderleeuw",
    "sg:orig_category":"Farmaceutische producten Gh",
    "sg:phone":"+32 53 66 93 82",
    "sg:postcode":"9473",
    "sg:province":"Oost-Vlaanderen",
    "wof:name":"Bracke Medische Techniek",
    "wof:placetype":"venue"
},
  "geometry": {"coordinates":[4.0499558449,50.899974823],"type":"Point"}
}