{
  "type": "Feature",
  "properties": {
    "addr:full":"Landwaartslaan 97 Genk Limburg 3600",
    "addr:housenumber":"97",
    "addr:postcode":"3600",
    "addr:street":"Landwaartslaan",
    "iso:country":"BE",
    "sg:address":"Landwaartslaan 97",
    "sg:city":"Genk",
    "sg:classifiers":[
        {
            "category":"Fast Food",
            "type":"Food & Drink"
        }
    ],
    "sg:phone":"+32 89 30 39 42",
    "sg:postcode":"3600",
    "sg:province":"Limburg",
    "sg:tags":[
        "meeneem",
        "restaurant"
    ],
    "wof:name":"Myriam Beertens",
    "wof:placetype":"venue"
},
  "geometry": {"coordinates":[5.4487447739,50.9688606262],"type":"Point"}
}