{
  "type": "Feature",
  "properties": {
    "iso:country":"BE",
    "sg:address":"Lakenmakersstraat 21",
    "sg:city":"Mol",
    "sg:classifiers":[
        {
            "category":"Personal",
            "subcategory":"Barber",
            "type":"Services"
        }
    ],
    "sg:phone":"+32 14 31 65 85",
    "sg:postcode":"2400",
    "sg:province":"Antwerpen",
    "sg:tags":[
        "gentleman",
        "salon",
        "-",
        "hairdressing"
    ],
    "wof:name":"Wine-art",
    "wof:placetype":"venue"
},
  "geometry": {"coordinates":[5.1180109978,51.1879425049],"type":"Point"}
}