{
  "type": "Feature",
  "properties": {
    "iso:country":"BE",
    "sg:address":"Wouters-lefebvreplein 6",
    "sg:city":"Willebroek",
    "sg:orig_category":"Slagers",
    "sg:phone":"+32 3 886 62 56",
    "sg:postcode":"2830",
    "sg:province":"Antwerpen",
    "wof:name":"Louis Mertens",
    "wof:placetype":"venue"
},
  "geometry": {"coordinates":[4.3721389771,51.0567817688],"type":"Point"}
}