{
  "type": "Feature",
  "properties": {
    "iso:country":"BE",
    "sg:address":"Avenue Joseph Wauters 5",
    "sg:city":"Frameries",
    "sg:orig_category":"Architectes. D\u00e9corateurs d'int\u00e9rieur",
    "sg:phone":"+32 65 66 53 76",
    "sg:postcode":"7080",
    "sg:province":"Hainaut",
    "wof:name":"Atelier D'architecture Bernard Poulet",
    "wof:placetype":"venue"
},
  "geometry": {"coordinates":[3.8969750404,50.4052734375],"type":"Point"}
}