{
  "type": "Feature",
  "properties": {
    "iso:country":"BE",
    "sg:address":"Rupsenstraat 16",
    "sg:city":"Wingene (zwevezele)",
    "sg:classifiers":[
        {
            "category":"Home & Garden",
            "subcategory":"Building Materials",
            "type":"Retail Goods"
        }
    ],
    "sg:phone":"+32 51 61 22 98",
    "sg:postcode":"8750",
    "sg:province":"West-Vlaanderen",
    "sg:tags":[
        "bathroom",
        "installation",
        "accessory"
    ],
    "wof:name":"Lievens Keukens",
    "wof:placetype":"venue"
},
  "geometry": {"coordinates":[3.2231440544,51.0409317017],"type":"Point"}
}