{
  "type": "Feature",
  "properties": {
    "addr:full":"Kempenstraat 70b Diepenbeek Limburg 3590",
    "addr:housenumber":"70b",
    "addr:postcode":"3590",
    "addr:street":"Kempenstraat",
    "iso:country":"BE",
    "sg:address":"Kempenstraat 70b",
    "sg:city":"Diepenbeek",
    "sg:classifiers":[
        {
            "category":"Organizations",
            "subcategory":"Community Association",
            "type":"Services"
        }
    ],
    "sg:phone":"+32 11 35 19 14",
    "sg:postcode":"3590",
    "sg:province":"Limburg",
    "sg:tags":[
        "cultural"
    ],
    "wof:name":"Culturen In Beweging (kundabuffi) Vzw",
    "wof:placetype":"venue"
},
  "geometry": {"coordinates":[5.4267368317,50.9227371216],"type":"Point"}
}