{
  "type": "Feature",
  "properties": {
    "addr:full":"Schoolstraat 11 Beersel Vlaams-Brabant 1650",
    "addr:housenumber":"11",
    "addr:postcode":"1650",
    "addr:street":"Schoolstraat",
    "iso:country":"BE",
    "sg:address":"Schoolstraat 11",
    "sg:city":"Beersel",
    "sg:classifiers":[
        {
            "category":"Building & Trades",
            "subcategory":"Construction",
            "type":"Services"
        }
    ],
    "sg:phone":"+32 486 55 66 42",
    "sg:postcode":"1650",
    "sg:province":"Vlaams-Brabant",
    "sg:tags":[
        "installation",
        "-",
        "central",
        "heating"
    ],
    "wof:name":"L.v.d.l.",
    "wof:placetype":"venue"
},
  "geometry": {"coordinates":[4.3097271919,50.7670860291],"type":"Point"}
}