{
  "type": "Feature",
  "properties": {
    "addr:full":"Rue Du Ch\u00c2teau 25 Grace-hollogne Li\u00e8ge 4460",
    "addr:housenumber":"25",
    "addr:postcode":"4460",
    "addr:street":"Rue Du Cha\u0302Teau",
    "iso:country":"BE",
    "sg:address":"Rue Du Ch\u00c2teau 25",
    "sg:city":"Grace-hollogne",
    "sg:classifiers":[
        {
            "category":"Personal",
            "subcategory":"Beauty Salon",
            "type":"Services"
        }
    ],
    "sg:phone":"+32 4 263 01 43",
    "sg:postcode":"4460",
    "sg:province":"Li\u00e8ge",
    "sg:tags":[
        "de",
        "coiffure"
    ],
    "wof:name":"Jean-marc Remouchamps",
    "wof:placetype":"venue"
},
  "geometry": {"coordinates":[5.5044469833,50.6412277222],"type":"Point"}
}