{
  "type": "Feature",
  "properties": {
    "addr:full":"Rue D'enhaive 302 Namur (jambes) Namur 5100",
    "addr:housenumber":"302",
    "addr:postcode":"5100",
    "addr:street":"Rue D'Enhaive",
    "iso:country":"BE",
    "sg:address":"Rue D'enhaive 302",
    "sg:city":"Namur (jambes)",
    "sg:classifiers":[
        {
            "category":"Health Services",
            "subcategory":"Health Practitioner",
            "type":"Services"
        }
    ],
    "sg:phone":"+32 478 39 99 26",
    "sg:postcode":"5100",
    "sg:province":"Namur",
    "sg:tags":[
        "physiotherapist"
    ],
    "wof:name":"Chavancy Nicolas",
    "wof:placetype":"venue"
},
  "geometry": {"coordinates":[4.8833780289,50.4616622925],"type":"Point"}
}