{
  "type": "Feature",
  "properties": {
    "addr:full":"Kerkstraat 48 De Haan (wenduine) West-Vlaanderen 8420",
    "addr:housenumber":"48",
    "addr:postcode":"8420",
    "addr:street":"Kerkstraat",
    "iso:country":"BE",
    "sg:address":"Kerkstraat 48",
    "sg:city":"De Haan (wenduine)",
    "sg:classifiers":[
        {
            "category":"Professional",
            "subcategory":"Computer Services",
            "type":"Services"
        }
    ],
    "sg:phone":"+32 50 41 51 28",
    "sg:postcode":"8420",
    "sg:province":"West-Vlaanderen",
    "sg:tags":[
        "-",
        "processing",
        "data"
    ],
    "wof:name":"All-com",
    "wof:placetype":"venue"
},
  "geometry": {"coordinates":[3.0810630322,51.2998085022],"type":"Point"}
}