{
  "type": "Feature",
  "properties": {
    "addr:full":"Rue De Hamme Mille 96 Grez-doiceau Brabant Wallon 1390",
    "addr:housenumber":"96",
    "addr:postcode":"1390",
    "addr:street":"Rue De Hamme Mille",
    "iso:country":"BE",
    "sg:address":"Rue De Hamme Mille 96",
    "sg:city":"Grez-doiceau",
    "sg:orig_category":"Ordinateurs and \u00e9quipement informatique",
    "sg:phone":"+32 95226854",
    "sg:postcode":"1390",
    "sg:province":"Brabant Wallon",
    "wof:name":"Pc Maclog Sprl",
    "wof:placetype":"venue"
},
  "geometry": {"coordinates":[4.6821289062,50.7834320068],"type":"Point"}
}