{
  "type": "Feature",
  "properties": {
    "iso:country":"BE",
    "sg:address":"Rue De La Salle 5",
    "sg:city":"Malmedy",
    "sg:orig_category":"Charpentes and couvertures",
    "sg:phone":"+32 80 33 98 04",
    "sg:postcode":"4960",
    "sg:province":"Li\u00e8ge",
    "wof:name":"G\u00c9rard Schmidt",
    "wof:placetype":"venue"
},
  "geometry": {"coordinates":[6.0567131042,50.4095191956],"type":"Point"}
}