{
  "type": "Feature",
  "properties": {
    "iso:country":"BE",
    "sg:address":"De Schaaf 36",
    "sg:city":"Malle",
    "sg:orig_category":"Dakwerken",
    "sg:phone":"+32 3 312 54 49",
    "sg:postcode":"2390",
    "sg:province":"Antwerpen",
    "wof:name":"Fons Verryckt",
    "wof:placetype":"venue"
},
  "geometry": {"coordinates":[4.7184901237,51.2847900391],"type":"Point"}
}