{
  "type": "Feature",
  "properties": {
    "addr:full":"Drie Bomenstraat 54 Ukkel/uccle Bruxelles-Capitale 1180",
    "addr:housenumber":"54",
    "addr:postcode":"1180",
    "addr:street":"Drie Bomenstraat;/",
    "iso:country":"BE",
    "sg:address":"Drie Bomenstraat 54",
    "sg:city":"Ukkel/uccle",
    "sg:orig_category":"Farmaceutische bereidingen and geneesmiddelen Fab",
    "sg:phone":"+32 2 370 47 33",
    "sg:postcode":"1180",
    "sg:province":"Bruxelles-Capitale",
    "wof:name":"Laboratoires Perfecta",
    "wof:placetype":"venue"
},
  "geometry": {"coordinates":[4.3337869644,50.7957954407],"type":"Point"}
}