{
  "type": "Feature",
  "properties": {
    "addr:full":"Rue Wouters 50 Andenne Namur 5300",
    "addr:housenumber":"50",
    "addr:postcode":"5300",
    "addr:street":"Rue Wouters",
    "iso:country":"BE",
    "sg:address":"Rue Wouters 50",
    "sg:city":"Andenne",
    "sg:orig_category":"Pain, p\u00e2tisseries and confiseries",
    "sg:phone":"+32 85 84 17 31",
    "sg:postcode":"5300",
    "sg:province":"Namur",
    "wof:name":"Boulangerie Dopagne",
    "wof:placetype":"venue"
},
  "geometry": {"coordinates":[5.0921411514,50.4896812439],"type":"Point"}
}