{
  "type": "Feature",
  "properties": {
    "addr:full":"Chauss\u00c9e De Waremme 808 Wanze Li\u00e8ge 4520",
    "addr:housenumber":"808",
    "addr:postcode":"4520",
    "addr:street":"Chausse\u0301E De Waremme",
    "iso:country":"BE",
    "sg:address":"Chauss\u00c9e De Waremme 808",
    "sg:city":"Wanze",
    "sg:orig_category":"Banken and kredietinstellingen",
    "sg:phone":"+32 85 23 48 85",
    "sg:postcode":"4520",
    "sg:province":"Li\u00e8ge",
    "wof:name":"Anhyp",
    "wof:placetype":"venue"
},
  "geometry": {"coordinates":[5.2499108315,50.5376396179],"type":"Point"}
}