{
  "type": "Feature",
  "properties": {
    "iso:country":"BE",
    "sg:address":"Borrekent 118e",
    "sg:city":"Haaltert (denderhoutem)",
    "sg:classifiers":[
        {
            "category":"Manufacturing",
            "subcategory":"Pottery",
            "type":"Manufacturing & Wholesale Goods"
        }
    ],
    "sg:phone":"+32 54 32 62 01",
    "sg:postcode":"9450",
    "sg:province":"Oost-Vlaanderen",
    "sg:tags":[
        "facing",
        "brick"
    ],
    "wof:name":"Van Den Broeck Bvba",
    "wof:placetype":"venue"
},
  "geometry": {"coordinates":[4.0036730766,50.8741569519],"type":"Point"}
}