{
  "type": "Feature",
  "properties": {
    "iso:country":"BE",
    "sg:address":"Rue De L'etat 80",
    "sg:city":"Chimay",
    "sg:orig_category":"Herstellingen and onderhoud van auto's",
    "sg:phone":"+32 60 21 23 27",
    "sg:postcode":"6460",
    "sg:province":"Hainaut",
    "wof:name":"Garage Brousmiche",
    "wof:placetype":"venue"
},
  "geometry": {"coordinates":[4.2644510269,50.0261917114],"type":"Point"}
}