{
  "type": "Feature",
  "properties": {
    "addr:full":"Rue Namur-perwez 92 La Bruyere Namur 5080",
    "addr:housenumber":"92",
    "addr:postcode":"5080",
    "addr:street":"Rue Namur-Perwez;La Bruyere",
    "iso:country":"BE",
    "sg:address":"Rue Namur-perwez 92",
    "sg:city":"La Bruyere",
    "sg:orig_category":"Herstellingen and onderhoud van auto's Voertuigen",
    "sg:phone":"+32 81 51 15 37",
    "sg:postcode":"5080",
    "sg:province":"Namur",
    "wof:name":"Luigi Valente",
    "wof:placetype":"venue"
},
  "geometry": {"coordinates":[4.8435678482,50.5395507812],"type":"Point"}
}