{
  "type": "Feature",
  "properties": {
    "iso:country":"BE",
    "sg:address":"Andr\u00c9 Dumontlaan 10b1",
    "sg:city":"Genk",
    "sg:orig_category":"Plaatsen van vloer- and muurbekleding Schilders Textiel Verlichting and huishoudartikelen Vloer- and",
    "sg:phone":"+32 89 38 31 87",
    "sg:postcode":"3600",
    "sg:province":"Limburg",
    "wof:name":"Seerden",
    "wof:placetype":"venue"
},
  "geometry": {"coordinates":[5.5301628113,50.995803833],"type":"Point"}
}