{
  "type": "Feature",
  "properties": {
    "iso:country":"BE",
    "sg:address":"Graaf Jansdijk 25b5",
    "sg:city":"Blankenberge",
    "sg:classifiers":[
        {
            "category":"Arena",
            "subcategory":"Sports Club",
            "type":"Entertainment"
        }
    ],
    "sg:phone":"+32 50 41 40 77",
    "sg:postcode":"8370",
    "sg:province":"West-Vlaanderen",
    "sg:tags":[
        "de"
    ],
    "wof:name":"Vlaamse Vereniging Hengelsport Verbonden",
    "wof:placetype":"venue"
},
  "geometry": {"coordinates":[3.1337320805,51.3170814514],"type":"Point"}
}