{
  "type": "Feature",
  "properties": {
    "addr:full":"Goudbloemstraat 2 Antwerpen Antwerpen 2060",
    "addr:housenumber":"2",
    "addr:postcode":"2060",
    "addr:street":"Goudbloemstraat",
    "iso:country":"BE",
    "sg:address":"Goudbloemstraat 2",
    "sg:city":"Antwerpen",
    "sg:orig_category":"Diverse zakelijke dienstverlening",
    "sg:phone":"+32 3 232 71 14",
    "sg:postcode":"2060",
    "sg:province":"Antwerpen",
    "wof:name":"Acrea",
    "wof:placetype":"venue"
},
  "geometry": {"coordinates":[4.416536808,51.2226867676],"type":"Point"}
}