{
  "type": "Feature",
  "properties": {
    "addr:full":"Ericalaan 11 Vosselaar Antwerpen 2350",
    "addr:housenumber":"11",
    "addr:postcode":"2350",
    "addr:street":"Ericalaan",
    "iso:country":"BE",
    "sg:address":"Ericalaan 11",
    "sg:city":"Vosselaar",
    "sg:orig_category":"Hout and afgeleiden Gh IJzerwaren, bouw- and verfmaterialen Landbouwmachines Gh",
    "sg:phone":"+32 14 61 33 38",
    "sg:postcode":"2350",
    "sg:province":"Antwerpen",
    "wof:name":"Guido Van Gansen",
    "wof:placetype":"venue"
},
  "geometry": {"coordinates":[4.8748421669,51.3000717163],"type":"Point"}
}