{
  "type": "Feature",
  "properties": {
    "iso:country":"BE",
    "sg:address":"Viekevorststraat 5",
    "sg:city":"Beringen (beverlo)",
    "sg:classifiers":[
        {
            "category":"Shopping",
            "subcategory":"Baby Store",
            "type":"Retail Goods"
        }
    ],
    "sg:phone":"+32 11 34 12 03",
    "sg:postcode":"3581",
    "sg:province":"Limburg",
    "sg:tags":[
        "midwife"
    ],
    "wof:name":"Vaes W",
    "wof:placetype":"venue"
},
  "geometry": {"coordinates":[5.2059621811,51.085483551],"type":"Point"}
}