{
  "type": "Feature",
  "properties": {
    "iso:country":"BE",
    "sg:address":"Scharestraat 40-42",
    "sg:city":"Oostkamp (ruddervoorde)",
    "sg:classifiers":[
        {
            "category":"Manufacturing",
            "subcategory":"Wood Products",
            "type":"Manufacturing & Wholesale Goods"
        }
    ],
    "sg:phone":"+32 50 27 62 38",
    "sg:postcode":"8020",
    "sg:province":"West-Vlaanderen",
    "sg:tags":[
        "firewood"
    ],
    "wof:name":"Carels-bogaert",
    "wof:placetype":"venue"
},
  "geometry": {"coordinates":[3.2472510338,51.0939788818],"type":"Point"}
}