{
  "type": "Feature",
  "properties": {
    "addr:full":"Rue Alex Bouvy 4 Li\u00c8ge Li\u00e8ge 4020",
    "addr:housenumber":"4",
    "addr:postcode":"4020",
    "addr:street":"Rue Alex Bouvy",
    "iso:country":"BE",
    "sg:address":"Rue Alex Bouvy 4",
    "sg:city":"Li\u00c8ge",
    "sg:orig_category":"Herstellingen and onderhoud van auto's",
    "sg:phone":"+32 4 343 50 13",
    "sg:postcode":"4020",
    "sg:province":"Li\u00e8ge",
    "wof:name":"Garage Limet",
    "wof:placetype":"venue"
},
  "geometry": {"coordinates":[5.5905680656,50.6462669373],"type":"Point"}
}