{
  "type": "Feature",
  "properties": {
    "iso:country":"BE",
    "sg:address":"Lesbroussartstraat 68",
    "sg:city":"Elsene/ixelles",
    "sg:orig_category":"Fitnesscentra",
    "sg:phone":"+32 2 640 93 44",
    "sg:postcode":"1050",
    "sg:province":"Bruxelles-Capitale",
    "wof:name":"California Gym",
    "wof:placetype":"venue"
},
  "geometry": {"coordinates":[4.3675909042,50.8275337219],"type":"Point"}
}