{
  "type": "Feature",
  "properties": {
    "addr:full":"Place De Brus 1 Bassenge Li\u00e8ge 4690",
    "addr:housenumber":"1",
    "addr:postcode":"4690",
    "addr:street":"Place De Brus",
    "iso:country":"BE",
    "sg:address":"Place De Brus 1",
    "sg:city":"Bassenge",
    "sg:orig_category":"M\u00e9decins and sp\u00e9cialistes",
    "sg:phone":"+32 4 286 17 12",
    "sg:postcode":"4690",
    "sg:province":"Li\u00e8ge",
    "wof:name":"Jean Raskinet",
    "wof:placetype":"venue"
},
  "geometry": {"coordinates":[5.5518507957,50.7478065491],"type":"Point"}
}