{
  "type": "Feature",
  "properties": {
    "iso:country":"BE",
    "sg:address":"Schoenlapperstraat 3",
    "sg:city":"Gent",
    "sg:orig_category":"Non-Classified Establishments",
    "sg:phone":"+32 9 224 02 81",
    "sg:postcode":"9000",
    "sg:province":"Oost-Vlaanderen",
    "wof:name":"Potent",
    "wof:placetype":"venue"
},
  "geometry": {"coordinates":[3.7232139111,51.0564994812],"type":"Point"}
}