{
  "type": "Feature",
  "properties": {
    "iso:country":"BE",
    "sg:address":"Kerkstraat 59",
    "sg:city":"Nieuwerkerken",
    "sg:orig_category":"Traitements param\u00e9dicaux",
    "sg:phone":"+32 11 69 53 84",
    "sg:postcode":"3850",
    "sg:province":"Limburg",
    "wof:name":"Thuisz. Lib. Mutualiteit",
    "wof:placetype":"venue"
},
  "geometry": {"coordinates":[5.1910738945,50.860534668],"type":"Point"}
}