{
  "type": "Feature",
  "properties": {
    "addr:full":"Rue De Biefnot 5 Seraing Li\u00e8ge 4100",
    "addr:housenumber":"5",
    "addr:postcode":"4100",
    "addr:street":"Rue De Biefnot",
    "iso:country":"BE",
    "sg:address":"Rue De Biefnot 5",
    "sg:city":"Seraing",
    "sg:classifiers":[
        {
            "category":"Manufacturing",
            "subcategory":"Tools & Machinery",
            "type":"Manufacturing & Wholesale Goods"
        }
    ],
    "sg:phone":"+32 4 336 71 71",
    "sg:postcode":"4100",
    "sg:province":"Li\u00e8ge",
    "sg:tags":[
        "-"
    ],
    "wof:name":"Import Stock Tools",
    "wof:placetype":"venue"
},
  "geometry": {"coordinates":[5.5018072128,50.5991134644],"type":"Point"}
}