{
  "type": "Feature",
  "properties": {
    "iso:country":"BE",
    "sg:address":"Gaverstraat 29",
    "sg:city":"Destelbergen (heusden)",
    "sg:classifiers":[
        {
            "category":"Sports & Exercise",
            "subcategory":"Stables",
            "type":"Entertainment"
        }
    ],
    "sg:phone":"+32 9 230 69 67",
    "sg:postcode":"9070",
    "sg:province":"Oost-Vlaanderen",
    "sg:tags":[
        "riding",
        "school"
    ],
    "wof:name":"Artevelderuiters",
    "wof:placetype":"venue"
},
  "geometry": {"coordinates":[3.8198459148,51.0442733765],"type":"Point"}
}