{
  "type": "Feature",
  "properties": {
    "addr:full":"Rue De Barvaux 6 Durbuy Luxembourg 6941",
    "addr:housenumber":"6",
    "addr:postcode":"6941",
    "addr:street":"Rue De Barvaux",
    "iso:country":"BE",
    "sg:address":"Rue De Barvaux 6",
    "sg:city":"Durbuy",
    "sg:orig_category":"Produits pharmaceutiques Fab",
    "sg:phone":"+32 86 21 45 52",
    "sg:postcode":"6941",
    "sg:province":"Luxembourg",
    "wof:name":"Tilman Et Cie",
    "wof:placetype":"venue"
},
  "geometry": {"coordinates":[5.524184227,50.3770332336],"type":"Point"}
}