{
  "type": "Feature",
  "properties": {
    "addr:full":"Spinnerijkaai 67 Kortrijk West-Vlaanderen 8500",
    "addr:housenumber":"67",
    "addr:postcode":"8500",
    "addr:street":"Spinnerijkaai",
    "iso:country":"BE",
    "sg:address":"Spinnerijkaai 67",
    "sg:city":"Kortrijk",
    "sg:orig_category":"Herstellingen and onderhoud van auto's Onderdelen and accessoires voor auto's",
    "sg:phone":"+32 56 25 53 00",
    "sg:postcode":"8500",
    "sg:province":"West-Vlaanderen",
    "wof:name":"Autoglas West",
    "wof:placetype":"venue"
},
  "geometry": {"coordinates":[3.2849171162,50.8315048218],"type":"Point"}
}