{
  "type": "Feature",
  "properties": {
    "addr:full":"Kapellestraat 40 Zele Oost-Vlaanderen 9240",
    "addr:housenumber":"40",
    "addr:postcode":"9240",
    "addr:street":"Kapellestraat",
    "iso:country":"BE",
    "sg:address":"Kapellestraat 40",
    "sg:city":"Zele",
    "sg:orig_category":"Boekhouders",
    "sg:phone":"+32 52 44 53 72",
    "sg:postcode":"9240",
    "sg:province":"Oost-Vlaanderen",
    "wof:name":"Piet Pas",
    "wof:placetype":"venue"
},
  "geometry": {"coordinates":[4.0390739441,51.0663452148],"type":"Point"}
}