{
  "type": "Feature",
  "properties": {
    "iso:country":"BE",
    "sg:address":"Nijvelsebaan 250",
    "sg:city":"Overijse",
    "sg:orig_category":"Diensten voor huisdieren",
    "sg:phone":"+32 2 687 51 31",
    "sg:postcode":"3090",
    "sg:province":"Vlaams-Brabant",
    "wof:name":"Pento",
    "wof:placetype":"venue"
},
  "geometry": {"coordinates":[4.5671730042,50.7714500427],"type":"Point"}
}