{
  "type": "Feature",
  "properties": {
    "addr:full":"Rue Pierre Hap Lema\u00eetre 32 Bruxelles (etterbeek) Bruxelles-Capitale 1040",
    "addr:housenumber":"32",
    "addr:postcode":"1040",
    "addr:street":"Rue Pierre Hap Lemai\u0302Tre",
    "iso:country":"BE",
    "sg:address":"Rue Pierre Hap Lema\u00eetre 32",
    "sg:city":"Bruxelles (etterbeek)",
    "sg:classifiers":[
        {
            "category":"Professional",
            "subcategory":"Computer Services",
            "type":"Services"
        }
    ],
    "sg:phone":"+32 2 644 62 27",
    "sg:postcode":"1040",
    "sg:province":"Bruxelles-Capitale",
    "sg:tags":[
        "-",
        "processing",
        "data",
        "software"
    ],
    "wof:name":"P.c. Softline",
    "wof:placetype":"venue"
},
  "geometry": {"coordinates":[4.3861351013,50.8266525269],"type":"Point"}
}