{
  "type": "Feature",
  "properties": {
    "addr:full":"Koning Albertlaan 128 Gent-centrum Oost-Vlaanderen 9000",
    "addr:housenumber":"128",
    "addr:postcode":"9000",
    "addr:street":"Koning Albertlaan;Oost-Vlaanderen",
    "iso:country":"BE",
    "sg:address":"Koning Albertlaan 128",
    "sg:city":"Gent-centrum",
    "sg:orig_category":"Advocaten and juridische adviseurs Balie van Gent",
    "sg:phone":"+32 9 222 94 31",
    "sg:postcode":"9000",
    "sg:province":"Oost-Vlaanderen",
    "wof:name":"Van Severen Liesbet",
    "wof:placetype":"venue"
},
  "geometry": {"coordinates":[3.7285690308,51.0556335449],"type":"Point"}
}