{
  "type": "Feature",
  "properties": {
    "iso:country":"BE",
    "sg:address":"Rue Des Piges 109",
    "sg:city":"Charleroi",
    "sg:orig_category":"Rundveehouders",
    "sg:phone":"+32 71 32 60 17",
    "sg:postcode":"6031",
    "sg:province":"Hainaut",
    "wof:name":"Marc Petit",
    "wof:placetype":"venue"
},
  "geometry": {"coordinates":[4.4387049675,50.3964996338],"type":"Point"}
}