{
  "type": "Feature",
  "properties": {
    "iso:country":"BE",
    "sg:address":"Lucien Reychlerstraat 3",
    "sg:city":"Waasmunster",
    "sg:classifiers":[
        {
            "category":"Bars & Pubs",
            "type":"Food & Drink"
        }
    ],
    "sg:phone":"+32 52 46 20 93",
    "sg:postcode":"9250",
    "sg:province":"Oost-Vlaanderen",
    "wof:name":"Marnix",
    "wof:placetype":"venue"
},
  "geometry": {"coordinates":[4.1014838219,51.1156654358],"type":"Point"}
}