{
  "type": "Feature",
  "properties": {
    "addr:full":"Rue Marvis 88 Tournai Hainaut 7500",
    "addr:housenumber":"88",
    "addr:postcode":"7500",
    "addr:street":"Rue Marvis",
    "iso:country":"BE",
    "sg:address":"Rue Marvis 88",
    "sg:city":"Tournai",
    "sg:orig_category":"Fietsen Motorfietsen",
    "sg:phone":"+32 69 21 36 04",
    "sg:postcode":"7500",
    "sg:province":"Hainaut",
    "wof:name":"Cycles Henrard",
    "wof:placetype":"venue"
},
  "geometry": {"coordinates":[3.4022240639,50.6069908142],"type":"Point"}
}