{
  "type": "Feature",
  "properties": {
    "iso:country":"BE",
    "sg:address":"Rue De La Loge 113",
    "sg:city":"Lessines (bois-de-lessines)",
    "sg:classifiers":[
        {
            "category":"Building & Trades",
            "subcategory":"Plumbing",
            "type":"Services"
        }
    ],
    "sg:phone":"+32 68 33 99 00",
    "sg:postcode":"7866",
    "sg:province":"Hainaut",
    "sg:tags":[
        "repair",
        "mainten",
        "-",
        "central",
        "heating"
    ],
    "wof:name":"Leroy Ets",
    "wof:placetype":"venue"
},
  "geometry": {"coordinates":[3.8668351173,50.7021903992],"type":"Point"}
}