{
  "type": "Feature",
  "properties": {
    "addr:full":"Priester Coulonstraat 63 Menen West-Vlaanderen 8930",
    "addr:housenumber":"63",
    "addr:postcode":"8930",
    "addr:street":"Priester Coulonstraat",
    "iso:country":"BE",
    "sg:address":"Priester Coulonstraat 63",
    "sg:city":"Menen",
    "sg:orig_category":"Rev\u00eatements pour sols and murs. Construction de maisons",
    "sg:phone":"+32 56 41 07 73",
    "sg:postcode":"8930",
    "sg:province":"West-Vlaanderen",
    "wof:name":"Fa. Vanthournout A.",
    "wof:placetype":"venue"
},
  "geometry": {"coordinates":[3.1690719128,50.785118103],"type":"Point"}
}