{
  "type": "Feature",
  "properties": {
    "addr:full":"Rue Fief De Rognon 13 Nivelles Brabant Wallon 1400",
    "addr:housenumber":"13",
    "addr:postcode":"1400",
    "addr:street":"Rue Fief De Rognon",
    "iso:country":"BE",
    "sg:address":"Rue Fief De Rognon 13",
    "sg:city":"Nivelles",
    "sg:classifiers":[
        {
            "category":"Education",
            "subcategory":"School",
            "type":"Public Place"
        }
    ],
    "sg:phone":"+32 67 21 44 97",
    "sg:postcode":"1400",
    "sg:province":"Brabant Wallon",
    "sg:tags":[
        "boarding"
    ],
    "wof:name":"Internat Autonome De La Communaut\u00e9 Fran\u00e7aise",
    "wof:placetype":"venue"
},
  "geometry": {"coordinates":[4.3330540657,50.5926971436],"type":"Point"}
}