{
  "type": "Feature",
  "properties": {
    "iso:country":"BE",
    "sg:address":"Rembert Dodoensstraat 114",
    "sg:city":"Mechelen",
    "sg:classifiers":[
        {
            "category":"Professional",
            "subcategory":"Detective & Security Services",
            "type":"Services"
        }
    ],
    "sg:phone":"+32 15 41 83 33",
    "sg:postcode":"2800",
    "sg:province":"Antwerpen",
    "sg:tags":[
        "consultant"
    ],
    "wof:name":"Maijinckx E",
    "wof:placetype":"venue"
},
  "geometry": {"coordinates":[4.4678010941,51.0219421387],"type":"Point"}
}