{
  "type": "Feature",
  "properties": {
    "iso:country":"BE",
    "sg:address":"Place Albert I 42a",
    "sg:city":"Florenville",
    "sg:classifiers":[
        {
            "category":"Arts & Performance",
            "subcategory":"Art Gallery",
            "type":"Entertainment"
        }
    ],
    "sg:phone":"+32 61 23 34 14",
    "sg:postcode":"6820",
    "sg:province":"Luxembourg",
    "wof:name":"Caf\u00e9 Des Arts",
    "wof:placetype":"venue"
},
  "geometry": {"coordinates":[5.310500145,49.6980400085],"type":"Point"}
}