{
  "type": "Feature",
  "properties": {
    "addr:full":"G Gezellelaan 113 Roeselare West-Vlaanderen 8800",
    "addr:housenumber":"113",
    "addr:postcode":"8800",
    "addr:street":"G Gezellelaan",
    "iso:country":"BE",
    "sg:address":"G Gezellelaan 113",
    "sg:city":"Roeselare",
    "sg:orig_category":"Traitement and rev\u00eatement des m\u00e9taux",
    "sg:phone":"+32 51 22 02 73",
    "sg:postcode":"8800",
    "sg:province":"West-Vlaanderen",
    "wof:name":"R.m.c. Nv",
    "wof:placetype":"venue"
},
  "geometry": {"coordinates":[3.1517860889,50.9370994568],"type":"Point"}
}