{
  "type": "Feature",
  "properties": {
    "addr:full":"Rue De L'argonne 12 Sint-gillis/saint-gilles Bruxelles-Capitale 1060",
    "addr:housenumber":"12",
    "addr:postcode":"1060",
    "addr:street":"Rue De L'Argonne",
    "iso:country":"BE",
    "sg:address":"Rue De L'argonne 12",
    "sg:city":"Sint-gillis/saint-gilles",
    "sg:orig_category":"Epiceries",
    "sg:phone":"+32 2 520 84 76",
    "sg:postcode":"1060",
    "sg:province":"Bruxelles-Capitale",
    "wof:name":"Maison Sunshine",
    "wof:placetype":"venue"
},
  "geometry": {"coordinates":[4.3382048607,50.8384933472],"type":"Point"}
}