{
  "type": "Feature",
  "properties": {
    "iso:country":"BE",
    "sg:address":"Westerring 33",
    "sg:city":"Oudenaarde",
    "sg:classifiers":[
        {
            "category":"Structure",
            "subcategory":"Office Building",
            "type":"Public Place"
        }
    ],
    "sg:phone":"+32 55 31 99 10",
    "sg:postcode":"9700",
    "sg:province":"Oost-Vlaanderen",
    "sg:tags":[
        "-",
        "type",
        "door",
        "sliding",
        "overhead"
    ],
    "wof:name":"Idem Nv",
    "wof:placetype":"venue"
},
  "geometry": {"coordinates":[3.6073288918,50.8692359924],"type":"Point"}
}