{
  "type": "Feature",
  "properties": {
    "addr:full":"Joseph Smeetslaan 33 Maasmechelen Limburg 3630",
    "addr:housenumber":"33",
    "addr:postcode":"3630",
    "addr:street":"Joseph Smeetslaan",
    "iso:country":"BE",
    "sg:address":"Joseph Smeetslaan 33",
    "sg:city":"Maasmechelen",
    "sg:classifiers":[
        {
            "category":"Bars & Pubs",
            "type":"Food & Drink"
        }
    ],
    "sg:phone":"+32 89 76 43 82",
    "sg:postcode":"3630",
    "sg:province":"Limburg",
    "wof:name":"Metropole",
    "wof:placetype":"venue"
},
  "geometry": {"coordinates":[5.6931138039,50.9653816223],"type":"Point"}
}