{
  "type": "Feature",
  "properties": {
    "iso:country":"BE",
    "sg:address":"Breulstraat 85",
    "sg:city":"Moorslede",
    "sg:classifiers":[
        {
            "category":"Metro Station",
            "type":"Transportation"
        }
    ],
    "sg:phone":"+32 51 77 75 91",
    "sg:postcode":"8890",
    "sg:province":"West-Vlaanderen",
    "sg:tags":[
        "packing",
        "marine",
        "transport",
        "air"
    ],
    "wof:name":"Lauwers Herman",
    "wof:placetype":"venue"
},
  "geometry": {"coordinates":[3.0921330452,50.8825798035],"type":"Point"}
}