{
  "type": "Feature",
  "properties": {
    "addr:full":"Smederijstraat 15 Brecht (sint-job-in-'t Goor) Antwerpen 2960",
    "addr:housenumber":"15",
    "addr:postcode":"2960",
    "addr:street":"Smederijstraat;' T Goor",
    "iso:country":"BE",
    "sg:address":"Smederijstraat 15",
    "sg:city":"Brecht (sint-job-in-'t Goor)",
    "sg:classifiers":[
        {
            "category":"Manufacturing",
            "subcategory":"Rubber & Plastics",
            "type":"Manufacturing & Wholesale Goods"
        }
    ],
    "sg:phone":"+32 3 633 00 00",
    "sg:postcode":"2960",
    "sg:province":"Antwerpen",
    "sg:tags":[
        "pipe",
        "-"
    ],
    "wof:name":"Civiele Techniek Belgi\u00eb Nv",
    "wof:placetype":"venue"
},
  "geometry": {"coordinates":[4.552781105,51.3020591736],"type":"Point"}
}