{
  "type": "Feature",
  "properties": {
    "addr:full":"Liefkenshage 27 Denderleeuw Oost-Vlaanderen 9470",
    "addr:housenumber":"27",
    "addr:postcode":"9470",
    "addr:street":"Liefkenshage",
    "iso:country":"BE",
    "sg:address":"Liefkenshage 27",
    "sg:city":"Denderleeuw",
    "sg:orig_category":"Gespecialiseerde residenti\u00eble bouw",
    "sg:phone":"+32 53 66 25 30",
    "sg:postcode":"9470",
    "sg:province":"Oost-Vlaanderen",
    "wof:name":"Jozef Van Isterdael",
    "wof:placetype":"venue"
},
  "geometry": {"coordinates":[4.0574040413,50.8892211914],"type":"Point"}
}