{
  "type": "Feature",
  "properties": {
    "addr:full":"7620 Brunehaut (groot) Hainaut 7620",
    "addr:postcode":"7620;7620",
    "addr:street":"Groot Hainaut",
    "iso:country":"BE",
    "sg:address":"7620",
    "sg:city":"Brunehaut (groot)",
    "sg:orig_category":"Pharmaciens",
    "sg:phone":"+32 900 10 500",
    "sg:postcode":"7620",
    "sg:province":"Hainaut",
    "wof:name":"Pharmacies De Garde",
    "wof:placetype":"venue"
},
  "geometry": {"coordinates":[3.3927299976,50.5330581665],"type":"Point"}
}