{
  "type": "Feature",
  "properties": {
    "iso:country":"BE",
    "sg:address":"Elsakker 12",
    "sg:city":"Vosselaar",
    "sg:orig_category":"Installation \u00e9lectrique r\u00e9sidentielle",
    "sg:phone":"+32 14 61 80 16",
    "sg:postcode":"2350",
    "sg:province":"Antwerpen",
    "wof:name":"Luc Lenaerts",
    "wof:placetype":"venue"
},
  "geometry": {"coordinates":[4.8954491615,51.3089485168],"type":"Point"}
}