{
  "type": "Feature",
  "properties": {
    "addr:full":"Kapellstrasse 7ba Kelmis/la Calamine Li\u00e8ge 4720",
    "addr:housenumber":"7ba",
    "addr:postcode":"4720",
    "addr:street":"Kapellstrasse",
    "iso:country":"BE",
    "sg:address":"Kapellstrasse 7ba",
    "sg:city":"Kelmis/la Calamine",
    "sg:orig_category":"Artsen and specialisten",
    "sg:phone":"+32 87 65 89 00",
    "sg:postcode":"4720",
    "sg:province":"Li\u00e8ge",
    "wof:name":"Alexandre-miche Reichardt",
    "wof:placetype":"venue"
},
  "geometry": {"coordinates":[6.013630867,50.7148284912],"type":"Point"}
}