{
  "type": "Feature",
  "properties": {
    "addr:full":"Sinaaidorp 11 Sint-niklaas Oost-Vlaanderen 9112",
    "addr:housenumber":"11",
    "addr:postcode":"9112",
    "addr:street":"Sinaaidorp",
    "iso:country":"BE",
    "sg:address":"Sinaaidorp 11",
    "sg:city":"Sint-niklaas",
    "sg:orig_category":"Artiesten and kunstenaars Diverse grafische activiteiten Reclamebureaus",
    "sg:phone":"+32 3 772 45 13",
    "sg:postcode":"9112",
    "sg:province":"Oost-Vlaanderen",
    "wof:name":"Fa. Janck",
    "wof:placetype":"venue"
},
  "geometry": {"coordinates":[4.0394802094,51.1572608948],"type":"Point"}
}