{
  "type": "Feature",
  "properties": {
    "iso:country":"BE",
    "sg:address":"Rue De L'abbaye 29",
    "sg:city":"Gesves",
    "sg:orig_category":"Charpentes and couvertures",
    "sg:phone":"+32 81 57 07 31",
    "sg:postcode":"5340",
    "sg:province":"Namur",
    "wof:name":"Claude Bouchat",
    "wof:placetype":"venue"
},
  "geometry": {"coordinates":[5.0223588943,50.4254264832],"type":"Point"}
}