{
  "type": "Feature",
  "properties": {
    "addr:full":"All\u00c9e Verte 37 La Louviere Hainaut 7100",
    "addr:housenumber":"37",
    "addr:postcode":"7100",
    "addr:street":"Alle\u0301E Verte",
    "iso:country":"BE",
    "sg:address":"All\u00c9e Verte 37",
    "sg:city":"La Louviere",
    "sg:classifiers":[
        {
            "category":"Insurance",
            "subcategory":"Life Insurance",
            "type":"Services"
        }
    ],
    "sg:phone":"+32 64 21 33 17",
    "sg:postcode":"7100",
    "sg:province":"Hainaut",
    "sg:tags":[
        "assurance"
    ],
    "wof:name":"Immo Fisc",
    "wof:placetype":"venue"
},
  "geometry": {"coordinates":[4.1911149025,50.4793319702],"type":"Point"}
}