{
  "type": "Feature",
  "properties": {
    "addr:full":"Oudstrijderslaan 18 Lochristi Oost-Vlaanderen 9080",
    "addr:housenumber":"18",
    "addr:postcode":"9080",
    "addr:street":"Oudstrijderslaan",
    "iso:country":"BE",
    "sg:address":"Oudstrijderslaan 18",
    "sg:city":"Lochristi",
    "sg:classifiers":[
        {
            "category":"Wholesale",
            "subcategory":"Construction Materials",
            "type":"Manufacturing & Wholesale Goods"
        }
    ],
    "sg:phone":"+32 9 355 97 23",
    "sg:postcode":"9080",
    "sg:province":"Oost-Vlaanderen",
    "sg:tags":[
        "nail"
    ],
    "wof:name":"De Somere",
    "wof:placetype":"venue"
},
  "geometry": {"coordinates":[3.8325428963,51.1046638489],"type":"Point"}
}