{
  "type": "Feature",
  "properties": {
    "addr:full":"Rue Sainte-v\u00c9ronique 27 Li\u00c8ge Li\u00e8ge 4000",
    "addr:housenumber":"27",
    "addr:postcode":"4000",
    "addr:street":"Rue Sainte-Ve\u0301Ronique",
    "iso:country":"BE",
    "sg:address":"Rue Sainte-v\u00c9ronique 27",
    "sg:city":"Li\u00c8ge",
    "sg:orig_category":"Avocats and conseillers juridiques",
    "sg:phone":"+32 4 254 38 20",
    "sg:postcode":"4000",
    "sg:province":"Li\u00e8ge",
    "wof:name":"O. Hamal",
    "wof:placetype":"venue"
},
  "geometry": {"coordinates":[5.5659008026,50.6315574646],"type":"Point"}
}