{
  "type": "Feature",
  "properties": {
    "addr:full":"Waterlozeweg 54 Maaseik (neeroeteren) Limburg 3680",
    "addr:housenumber":"54",
    "addr:postcode":"3680",
    "addr:street":"Waterlozeweg",
    "iso:country":"BE",
    "sg:address":"Waterlozeweg 54",
    "sg:city":"Maaseik (neeroeteren)",
    "sg:classifiers":[
        {
            "category":"Health Services",
            "subcategory":"Nursing And Care Facility",
            "type":"Services"
        }
    ],
    "sg:phone":"+32 89 56 59 05",
    "sg:postcode":"3680",
    "sg:province":"Limburg",
    "sg:tags":[
        "home"
    ],
    "wof:name":"Thuisverpleging B.t.",
    "wof:placetype":"venue"
},
  "geometry": {"coordinates":[5.791285038,51.0954208374],"type":"Point"}
}