{
  "type": "Feature",
  "properties": {
    "addr:full":"Krommestraat 27 Lennik Vlaams-Brabant 1750",
    "addr:housenumber":"27;1750",
    "addr:street":"Krommestraat;Vlaams-Brabant",
    "iso:country":"BE",
    "sg:address":"Krommestraat 27",
    "sg:city":"Lennik",
    "sg:orig_category":"Installation \u00e9lectrique r\u00e9sidentielle",
    "sg:phone":"+32 2 532 06 05",
    "sg:postcode":"1750",
    "sg:province":"Vlaams-Brabant",
    "wof:name":"Marc De Leener",
    "wof:placetype":"venue"
},
  "geometry": {"coordinates":[4.149889946,50.8081283569],"type":"Point"}
}