{
  "type": "Feature",
  "properties": {
    "iso:country":"BE",
    "sg:address":"Rue Des Graffes 80",
    "sg:city":"Courcelles",
    "sg:classifiers":[
        {
            "category":"Retail",
            "subcategory":"Auto Repair",
            "type":"Services"
        }
    ],
    "sg:phone":"+32 71 45 65 88",
    "sg:postcode":"6180",
    "sg:province":"Hainaut",
    "sg:tags":[
        "garage"
    ],
    "wof:name":"D'ignoti S",
    "wof:placetype":"venue"
},
  "geometry": {"coordinates":[4.3554329872,50.44140625],"type":"Point"}
}