{
  "type": "Feature",
  "properties": {
    "addr:full":"Grote Baan 48 Waasmunster Oost-Vlaanderen 9250",
    "addr:housenumber":"48",
    "addr:postcode":"9250",
    "addr:street":"Grote Baan",
    "iso:country":"BE",
    "sg:address":"Grote Baan 48",
    "sg:city":"Waasmunster",
    "sg:orig_category":"SMEEDWERK, METAALBEWERKING AND POEDERMETALLURGIE",
    "sg:phone":"+32 3 772 35 16",
    "sg:postcode":"9250",
    "sg:province":"Oost-Vlaanderen",
    "wof:name":"Veldeman",
    "wof:placetype":"venue"
},
  "geometry": {"coordinates":[4.0626921654,51.1357040405],"type":"Point"}
}