{
  "type": "Feature",
  "properties": {
    "iso:country":"BE",
    "sg:address":"Bruinbekestraat 46",
    "sg:city":"Wichelen",
    "sg:orig_category":"Boucheries",
    "sg:phone":"+32 9 369 87 74",
    "sg:postcode":"9260",
    "sg:province":"Oost-Vlaanderen",
    "wof:name":"Luc De Deyn",
    "wof:placetype":"venue"
},
  "geometry": {"coordinates":[3.948513031,50.9997177124],"type":"Point"}
}