{
  "type": "Feature",
  "properties": {
    "iso:country":"BE",
    "sg:address":"Chauss\u00c9e De Namur 91",
    "sg:city":"Nivelles",
    "sg:classifiers":[
        {
            "category":"Cafe",
            "type":"Food & Drink"
        }
    ],
    "sg:phone":"+32 67 84 40 71",
    "sg:postcode":"1402",
    "sg:province":"Brabant Wallon",
    "sg:tags":[
        "caf\u00e9s"
    ],
    "wof:name":"Manon De Boeck",
    "wof:placetype":"venue"
},
  "geometry": {"coordinates":[4.3705148697,50.5940322876],"type":"Point"}
}