{
  "type": "Feature",
  "properties": {
    "iso:country":"BE",
    "sg:address":"Rue Aimeries 112",
    "sg:city":"Dour",
    "sg:classifiers":[
        {
            "category":"Professional",
            "subcategory":"Secretarial Services",
            "type":"Services"
        }
    ],
    "sg:phone":"+32 65 65 39 31",
    "sg:postcode":"7370",
    "sg:province":"Hainaut",
    "sg:tags":[
        "delivery",
        "messenger"
    ],
    "wof:name":"Lijsen C",
    "wof:placetype":"venue"
},
  "geometry": {"coordinates":[3.7909231186,50.4012756348],"type":"Point"}
}