{
  "type": "Feature",
  "properties": {
    "iso:country":"BE",
    "sg:address":"Baron Tibbautstraat 41ba",
    "sg:city":"Berlare",
    "sg:classifiers":[
        {
            "category":"Arena",
            "subcategory":"Sports Club",
            "type":"Entertainment"
        }
    ],
    "sg:phone":"+32 9 367 71 35",
    "sg:postcode":"9290",
    "sg:province":"Oost-Vlaanderen",
    "sg:tags":[
        "terrain",
        "hors",
        "de",
        "installation",
        "sportifs"
    ],
    "wof:name":"S.k. Kalken",
    "wof:placetype":"venue"
},
  "geometry": {"coordinates":[3.9430499077,51.045501709],"type":"Point"}
}