{
  "type": "Feature",
  "properties": {
    "addr:full":"Kerkstraat 35 Heusden-zolder Limburg 3550",
    "addr:housenumber":"35",
    "addr:postcode":"3550",
    "addr:street":"Kerkstraat",
    "iso:country":"BE",
    "sg:address":"Kerkstraat 35",
    "sg:city":"Heusden-zolder",
    "sg:orig_category":"Artsen and specialisten",
    "sg:phone":"+32 11 43 53 45",
    "sg:postcode":"3550",
    "sg:province":"Limburg",
    "wof:name":"Suzanne Van Assche",
    "wof:placetype":"venue"
},
  "geometry": {"coordinates":[5.2488789558,50.996131897],"type":"Point"}
}