{
  "type": "Feature",
  "properties": {
    "addr:full":"Rue Du Village 36 Bassenge (eben-emael) Li\u00e8ge 4690",
    "addr:housenumber":"36",
    "addr:postcode":"4690",
    "addr:street":"Rue Du Village;Eben-Emael",
    "iso:country":"BE",
    "sg:address":"Rue Du Village 36",
    "sg:city":"Bassenge (eben-emael)",
    "sg:classifiers":[
        {
            "category":"Health Services",
            "subcategory":"Dentist",
            "type":"Services"
        }
    ],
    "sg:phone":"+32 4 286 14 87",
    "sg:postcode":"4690",
    "sg:province":"Li\u00e8ge",
    "wof:name":"Delile Hubert",
    "wof:placetype":"venue"
},
  "geometry": {"coordinates":[5.6558299065,50.7804794312],"type":"Point"}
}