{
  "type": "Feature",
  "properties": {
    "addr:full":"Bosterhoutstraat 11 Meulebeke West-Vlaanderen 8760",
    "addr:housenumber":"11",
    "addr:postcode":"8760",
    "addr:street":"Bosterhoutstraat",
    "iso:country":"BE",
    "sg:address":"Bosterhoutstraat 11",
    "sg:city":"Meulebeke",
    "sg:orig_category":"Groententeelt Varkenskwekers",
    "sg:phone":"+32 51 48 83 73",
    "sg:postcode":"8760",
    "sg:province":"West-Vlaanderen",
    "wof:name":"Eric Vermeulen",
    "wof:placetype":"venue"
},
  "geometry": {"coordinates":[3.2947840691,50.9697036743],"type":"Point"}
}