{
  "type": "Feature",
  "properties": {
    "addr:full":"Rue De Biesmes 33 Gerpinnes Hainaut 6280",
    "addr:housenumber":"33",
    "addr:postcode":"6280",
    "addr:street":"Rue De Biesmes;Hainaut",
    "iso:country":"BE",
    "sg:address":"Rue De Biesmes 33",
    "sg:city":"Gerpinnes",
    "sg:orig_category":"Informaticaconsulenten",
    "sg:phone":"+32 71 50 58 82",
    "sg:postcode":"6280",
    "sg:province":"Hainaut",
    "wof:name":"M.s. Informatique",
    "wof:placetype":"venue"
},
  "geometry": {"coordinates":[4.5276851654,50.3365364075],"type":"Point"}
}