{
  "type": "Feature",
  "properties": {
    "addr:full":"Burgemeester Lemmensstraat 51 Hamme (moerzeke) Oost-Vlaanderen 9220",
    "addr:housenumber":"51",
    "addr:postcode":"9220",
    "addr:street":"Burgemeester Lemmensstraat",
    "iso:country":"BE",
    "sg:address":"Burgemeester Lemmensstraat 51",
    "sg:city":"Hamme (moerzeke)",
    "sg:classifiers":[
        {
            "category":"Health Services",
            "subcategory":"Doctor",
            "type":"Services"
        }
    ],
    "sg:phone":"+32 52 47 78 26",
    "sg:postcode":"9220",
    "sg:province":"Oost-Vlaanderen",
    "sg:tags":[
        "medicinephysicians",
        "surgeon"
    ],
    "wof:name":"Beysens Bruno",
    "wof:placetype":"venue"
},
  "geometry": {"coordinates":[4.1548128128,51.0654640198],"type":"Point"}
}