{
  "type": "Feature",
  "properties": {
    "addr:full":"Veldstraat 23 Buggenhout-opdorp Oost-Vlaanderen 9255",
    "addr:housenumber":"23",
    "addr:postcode":"9255",
    "addr:street":"Veldstraat;Oost-Vlaanderen",
    "iso:country":"BE",
    "sg:address":"Veldstraat 23",
    "sg:city":"Buggenhout-opdorp",
    "sg:classifiers":[
        {
            "category":"Restaurant",
            "type":"Food & Drink"
        }
    ],
    "sg:phone":"+32 475 91 85 77",
    "sg:postcode":"9255",
    "sg:province":"Oost-Vlaanderen",
    "wof:name":"Eetcaf\u00c9 't Middelpunt",
    "wof:placetype":"venue"
},
  "geometry": {"coordinates":[4.2208619118,51.0252380371],"type":"Point"}
}