{
  "type": "Feature",
  "properties": {
    "iso:country":"BE",
    "sg:address":"Rue De Marchienne 13",
    "sg:city":"Charleroi",
    "sg:orig_category":"Voedingsspeciaalzaken",
    "sg:phone":"+32 71 34 25 03",
    "sg:postcode":"6040",
    "sg:province":"Hainaut",
    "wof:name":"Bo\u00cete \u00c0 Farine",
    "wof:placetype":"venue"
},
  "geometry": {"coordinates":[4.4145531654,50.433467865],"type":"Point"}
}