{
  "type": "Feature",
  "properties": {
    "addr:full":"Ranstsestweg 135 Ranst Antwerpen 2520",
    "addr:housenumber":"135",
    "addr:postcode":"2520",
    "iso:country":"BE",
    "sg:address":"Ranstsestweg 135",
    "sg:city":"Ranst",
    "sg:orig_category":"Tuinen",
    "sg:phone":"+32 3 485 56 54",
    "sg:postcode":"2520",
    "sg:province":"Antwerpen",
    "wof:name":"Van Gelderen",
    "wof:placetype":"venue"
},
  "geometry": {"coordinates":[4.5617351532,51.1849060059],"type":"Point"}
}