{
  "type": "Feature",
  "properties": {
    "addr:full":"Ringlaan 55 Ichtegem West-Vlaanderen 8480",
    "addr:housenumber":"55",
    "addr:postcode":"8480",
    "addr:street":"Ringlaan",
    "iso:country":"BE",
    "sg:address":"Ringlaan 55",
    "sg:city":"Ichtegem",
    "sg:classifiers":[
        {
            "category":"Organizations",
            "subcategory":"Community Association",
            "type":"Services"
        }
    ],
    "sg:phone":"+32 51 59 11 50",
    "sg:postcode":"8480",
    "sg:province":"West-Vlaanderen",
    "sg:tags":[
        "work",
        "assembly"
    ],
    "wof:name":"Vulsteke Rik Industrial Nv",
    "wof:placetype":"venue"
},
  "geometry": {"coordinates":[3.0215830803,51.0996513367],"type":"Point"}
}