{
  "type": "Feature",
  "properties": {
    "addr:full":"Sint-michielslaan 37a Brugge (sint-michiels) West-Vlaanderen 8200",
    "addr:housenumber":"37a",
    "addr:postcode":"8200",
    "addr:street":"Sint-Michielslaan",
    "iso:country":"BE",
    "sg:address":"Sint-michielslaan 37a",
    "sg:city":"Brugge (sint-michiels)",
    "sg:classifiers":[
        {
            "category":"Health Services",
            "subcategory":"Dentist",
            "type":"Services"
        }
    ],
    "sg:phone":"+32 50 39 32 31",
    "sg:postcode":"8200",
    "sg:province":"West-Vlaanderen",
    "wof:name":"Van Moerbeke Geert",
    "wof:placetype":"venue"
},
  "geometry": {"coordinates":[3.1904699802,51.1992111206],"type":"Point"}
}