{
  "type": "Feature",
  "properties": {
    "addr:full":"Moeskroenstraat 730 Box 7 Menen (rekkem) West-Vlaanderen 8930",
    "addr:housenumber":"730;7",
    "addr:postcode":"8930",
    "addr:street":"Moeskroenstraat;Box",
    "iso:country":"BE",
    "sg:address":"Moeskroenstraat 730 Box 7",
    "sg:city":"Menen (rekkem)",
    "sg:classifiers":[
        {
            "category":"Health Services",
            "subcategory":"Health Practitioner",
            "type":"Services"
        }
    ],
    "sg:phone":"+32 56 42 69 66",
    "sg:postcode":"8930",
    "sg:province":"West-Vlaanderen",
    "sg:tags":[
        "physiotherapist"
    ],
    "wof:name":"Herman Anthony",
    "wof:placetype":"venue"
},
  "geometry": {"coordinates":[3.1548678875,50.7887992859],"type":"Point"}
}