{
  "type": "Feature",
  "properties": {
    "addr:full":"Rue Des Munos 59 Bertrix Luxembourg 6880",
    "addr:housenumber":"59",
    "addr:postcode":"6880",
    "addr:street":"Rue Des Munos",
    "iso:country":"BE",
    "sg:address":"Rue Des Munos 59",
    "sg:city":"Bertrix",
    "sg:classifiers":[
        {
            "category":"Health Services",
            "subcategory":"Doctor",
            "type":"Services"
        }
    ],
    "sg:phone":"+32 61 41 21 31",
    "sg:postcode":"6880",
    "sg:province":"Luxembourg",
    "sg:tags":[
        "medicinephysicians",
        "surgeon"
    ],
    "wof:name":"Goffin L",
    "wof:placetype":"venue"
},
  "geometry": {"coordinates":[5.2509670258,49.8462944031],"type":"Point"}
}