{
  "type": "Feature",
  "properties": {
    "addr:full":"Chauss\u00e9e De Givet 66 Couvin (mariembourg) Namur 5660",
    "addr:housenumber":"66",
    "addr:postcode":"5660",
    "addr:street":"Chausse\u0301E De Givet",
    "iso:country":"BE",
    "sg:address":"Chauss\u00e9e De Givet 66",
    "sg:city":"Couvin (mariembourg)",
    "sg:classifiers":[
        {
            "category":"Parking",
            "subcategory":"Lot",
            "type":"Transportation"
        }
    ],
    "sg:phone":"+32 60 31 21 40",
    "sg:postcode":"5660",
    "sg:province":"Namur",
    "sg:tags":[
        "parking-places",
        "laying-out"
    ],
    "wof:name":"Riche Pascal",
    "wof:placetype":"venue"
},
  "geometry": {"coordinates":[4.4966731071,50.0532150269],"type":"Point"}
}