{
  "type": "Feature",
  "properties": {
    "addr:full":"Torhoutsesteenweg 610 Oostende West-Vlaanderen 8400",
    "addr:housenumber":"610",
    "addr:postcode":"8400",
    "addr:street":"Torhoutsesteenweg",
    "iso:country":"BE",
    "sg:address":"Torhoutsesteenweg 610",
    "sg:city":"Oostende",
    "sg:orig_category":"Slagers",
    "sg:phone":"+32 59 51 19 81",
    "sg:postcode":"8400",
    "sg:province":"West-Vlaanderen",
    "wof:name":"Renmans",
    "wof:placetype":"venue"
},
  "geometry": {"coordinates":[2.9064500332,51.2142601013],"type":"Point"}
}