{
  "type": "Feature",
  "properties": {
    "addr:full":"Rue Des D\u00c9port\u00c9s 0 Vis\u00c9 Li\u00e8ge 4600",
    "addr:housenumber":"0",
    "addr:postcode":"4600",
    "addr:street":"Rue Des De\u0301Porte\u0301S",
    "iso:country":"BE",
    "sg:address":"Rue Des D\u00c9port\u00c9s 0",
    "sg:city":"Vis\u00c9",
    "sg:orig_category":"Enseignement maternel and primaire",
    "sg:phone":"+32 4 374 01 15",
    "sg:postcode":"4600",
    "sg:province":"Li\u00e8ge",
    "wof:name":"E.f.l. St.hadelin",
    "wof:placetype":"venue"
},
  "geometry": {"coordinates":[5.6939997673,50.7390136719],"type":"Point"}
}