{
  "type": "Feature",
  "properties": {
    "addr:full":"Generaal Jacqueslaan 107 Elsene/ixelles Bruxelles-Capitale 1050",
    "addr:housenumber":"107",
    "addr:postcode":"1050",
    "addr:street":"Generaal Jacqueslaan",
    "iso:country":"BE",
    "sg:address":"Generaal Jacqueslaan 107",
    "sg:city":"Elsene/ixelles",
    "sg:orig_category":"Drukkerijen and copyshops Kantoormateriaal",
    "sg:phone":"+32 2 649 46 45",
    "sg:postcode":"1050",
    "sg:province":"Bruxelles-Capitale",
    "wof:name":"Uni Buro",
    "wof:placetype":"venue"
},
  "geometry": {"coordinates":[4.3818922043,50.8194351196],"type":"Point"}
}