{
  "type": "Feature",
  "properties": {
    "addr:full":"Place Joseph Thiry 17 Aywaille Li\u00e8ge 4920",
    "addr:housenumber":"17",
    "addr:postcode":"4920",
    "addr:street":"Place Joseph Thiry",
    "iso:country":"BE",
    "sg:address":"Place Joseph Thiry 17",
    "sg:city":"Aywaille",
    "sg:classifiers":[
        {
            "category":"Cafe",
            "type":"Food & Drink"
        }
    ],
    "sg:phone":"+32 4 384 69 42",
    "sg:postcode":"4920",
    "sg:province":"Li\u00e8ge",
    "sg:tags":[
        "caf\u00e9s"
    ],
    "wof:name":"Caf\u00c9 Rallye",
    "wof:placetype":"venue"
},
  "geometry": {"coordinates":[5.6750540733,50.4740753174],"type":"Point"}
}