{
  "type": "Feature",
  "properties": {
    "addr:full":"Forumlaan 4 Brussel/bruxelles Bruxelles-Capitale 1020",
    "addr:housenumber":"4",
    "addr:postcode":"1020",
    "addr:street":"Forumlaan;/",
    "iso:country":"BE",
    "sg:address":"Forumlaan 4",
    "sg:city":"Brussel/bruxelles",
    "sg:orig_category":"Sportcentra",
    "sg:phone":"+32 2 262 33 27",
    "sg:postcode":"1020",
    "sg:province":"Bruxelles-Capitale",
    "wof:name":"Sportz. Van Ruusbroeckc.",
    "wof:placetype":"venue"
},
  "geometry": {"coordinates":[4.3554282188,50.897403717],"type":"Point"}
}