{
  "type": "Feature",
  "properties": {
    "addr:full":"Stationsstraat 276 Dilbeek Vlaams-Brabant 1700",
    "addr:housenumber":"276",
    "addr:postcode":"1700",
    "addr:street":"Stationsstraat",
    "iso:country":"BE",
    "sg:address":"Stationsstraat 276",
    "sg:city":"Dilbeek",
    "sg:classifiers":[
        {
            "category":"Cafe",
            "type":"Food & Drink"
        }
    ],
    "sg:phone":"+32 2 466 70 97",
    "sg:postcode":"1700",
    "sg:province":"Vlaams-Brabant",
    "sg:tags":[
        "caf\u00e9s"
    ],
    "wof:name":"Caf\u00c9 Het Schuurtje",
    "wof:placetype":"venue"
},
  "geometry": {"coordinates":[4.2452697754,50.8647270203],"type":"Point"}
}