{
  "type": "Feature",
  "properties": {
    "iso:country":"BE",
    "sg:address":"Dr\u00e8ve De L'infante 65",
    "sg:city":"Waterloo",
    "sg:classifiers":[
        {
            "category":"Health Services",
            "subcategory":"Health Practitioner",
            "type":"Services"
        }
    ],
    "sg:phone":"+32 2 354 26 45",
    "sg:postcode":"1410",
    "sg:province":"Brabant Wallon",
    "sg:tags":[
        "osteopath"
    ],
    "wof:name":"Bockstael M",
    "wof:placetype":"venue"
},
  "geometry": {"coordinates":[4.3868088722,50.7182312012],"type":"Point"}
}