{
  "type": "Feature",
  "properties": {
    "addr:full":"Rue De Belle Vue 23 La Louvi\u00e8re Hainaut 7100",
    "addr:housenumber":"23",
    "addr:postcode":"7100",
    "addr:street":"Rue De Belle Vue",
    "iso:country":"BE",
    "sg:address":"Rue De Belle Vue 23",
    "sg:city":"La Louvi\u00e8re",
    "sg:classifiers":[
        {
            "category":"Arts & Performance",
            "subcategory":"Theater",
            "type":"Entertainment"
        }
    ],
    "sg:phone":"+32 64 65 24 19",
    "sg:postcode":"7100",
    "sg:province":"Hainaut",
    "sg:tags":[
        "theatrical",
        "agency"
    ],
    "wof:name":"Productions Du Dragon Sa",
    "wof:placetype":"venue"
},
  "geometry": {"coordinates":[4.1874790192,50.4743080139],"type":"Point"}
}