{
  "type": "Feature",
  "properties": {
    "iso:country":"BE",
    "sg:address":"Rue Pont D'avroy 17",
    "sg:city":"Li\u00e8ge 1",
    "sg:classifiers":[
        {
            "category":"Food & Beverages",
            "subcategory":"Chocolate",
            "type":"Retail Goods"
        }
    ],
    "sg:phone":"+32 4 223 52 55",
    "sg:postcode":"4000",
    "sg:province":"Li\u00e8ge",
    "sg:tags":[
        "confectionery",
        "-"
    ],
    "wof:name":"Kiwi (confiserie)",
    "wof:placetype":"venue"
},
  "geometry": {"coordinates":[5.570098877,50.6405220032],"type":"Point"}
}