{
  "type": "Feature",
  "properties": {
    "addr:full":"Wolfshaegen 5 Huldenberg Vlaams-Brabant 3040",
    "addr:housenumber":"5",
    "addr:postcode":"3040",
    "addr:street":"Wolfshaegen",
    "iso:country":"BE",
    "sg:address":"Wolfshaegen 5",
    "sg:city":"Huldenberg",
    "sg:orig_category":"Eleveurs and marchands de porcs. Eleveurs de bovins",
    "sg:phone":"+32 16 47 72 24",
    "sg:postcode":"3040",
    "sg:province":"Vlaams-Brabant",
    "wof:name":"Willy Vanacker",
    "wof:placetype":"venue"
},
  "geometry": {"coordinates":[4.6256599426,50.7909088135],"type":"Point"}
}