{
  "type": "Feature",
  "properties": {
    "iso:country":"BE",
    "sg:address":"Boulevard International 55b11",
    "sg:city":"Anderlecht/anderlecht",
    "sg:orig_category":"Agences de marketing. Bureaux d'\u00e9tudes de march\u00e9",
    "sg:phone":"+32 2 558 05 58",
    "sg:postcode":"1070",
    "sg:province":"Bruxelles-Capitale",
    "wof:name":"G.f.k. Belgium",
    "wof:placetype":"venue"
},
  "geometry": {"coordinates":[4.3070678711,50.8159446716],"type":"Point"}
}