{
  "type": "Feature",
  "properties": {
    "addr:full":"Rue De L'h\u00f4pital 23 Andenne Namur 5300",
    "addr:housenumber":"23",
    "addr:postcode":"5300",
    "addr:street":"Rue De L'Ho \u0302Pital",
    "iso:country":"BE",
    "sg:address":"Rue De L'h\u00f4pital 23",
    "sg:city":"Andenne",
    "sg:classifiers":[
        {
            "category":"Health Services",
            "subcategory":"Hospital",
            "type":"Services"
        }
    ],
    "sg:phone":"+32 85 84 94 80",
    "sg:postcode":"5300",
    "sg:province":"Namur",
    "wof:name":"Centre De Sant\u00e9 Provincial",
    "wof:placetype":"venue"
},
  "geometry": {"coordinates":[5.0982599258,50.4863700867],"type":"Point"}
}