{
  "type": "Feature",
  "properties": {
    "iso:country":"BE",
    "sg:address":"Korenmarkt 20",
    "sg:city":"Gent",
    "sg:classifiers":[
        {
            "category":"Banks & Credit Unions",
            "subcategory":"Bank",
            "type":"Services"
        }
    ],
    "sg:phone":"+32 3 231 49 60",
    "sg:postcode":"9000",
    "sg:province":"Oost-Vlaanderen",
    "wof:name":"Banque Paribas Belgique Sa",
    "wof:placetype":"venue"
},
  "geometry": {"coordinates":[4.4105420113,51.2182235718],"type":"Point"}
}