{
  "type": "Feature",
  "properties": {
    "addr:full":"Rue Du Buisson 8 Bruxelles (ixelles) Bruxelles-Capitale 1050",
    "addr:housenumber":"8",
    "addr:postcode":"1050",
    "addr:street":"Rue Du Buisson",
    "iso:country":"BE",
    "sg:address":"Rue Du Buisson 8",
    "sg:city":"Bruxelles (ixelles)",
    "sg:classifiers":[
        {
            "category":"Professional",
            "subcategory":"Management & Consulting",
            "type":"Services"
        }
    ],
    "sg:phone":"+32 2 647 50 70",
    "sg:postcode":"1050",
    "sg:province":"Bruxelles-Capitale",
    "sg:tags":[
        "consultant",
        "relation",
        "public"
    ],
    "wof:name":"Sponsart",
    "wof:placetype":"venue"
},
  "geometry": {"coordinates":[4.3724517822,50.8221893311],"type":"Point"}
}