{
  "type": "Feature",
  "properties": {
    "iso:country":"BE",
    "sg:address":"Henri Spillemaeckersstraat 5",
    "sg:city":"Boom",
    "sg:classifiers":[
        {
            "category":"Social Services",
            "subcategory":"Job Training",
            "type":"Services"
        }
    ],
    "sg:phone":"+32 3 844 86 16",
    "sg:postcode":"2850",
    "sg:province":"Antwerpen",
    "sg:tags":[
        "personnel"
    ],
    "wof:name":"Vokans Vzw",
    "wof:placetype":"venue"
},
  "geometry": {"coordinates":[4.3631978035,51.0866088867],"type":"Point"}
}