{
  "type": "Feature",
  "properties": {
    "addr:full":"Roeselaarseweg 5 Torhout West-Vlaanderen 8820",
    "addr:housenumber":"5",
    "addr:postcode":"8820",
    "addr:street":"Roeselaarseweg",
    "iso:country":"BE",
    "sg:address":"Roeselaarseweg 5",
    "sg:city":"Torhout",
    "sg:classifiers":[
        {
            "category":"Autos & Motor Vehicles",
            "subcategory":"Automobile Sales",
            "type":"Retail Goods"
        }
    ],
    "sg:phone":"+32 495 10 22 87",
    "sg:postcode":"8820",
    "sg:province":"West-Vlaanderen",
    "sg:tags":[
        "car",
        "used",
        "-"
    ],
    "wof:name":"Claeys - Van Belle A",
    "wof:placetype":"venue"
},
  "geometry": {"coordinates":[3.1045889854,51.0511054993],"type":"Point"}
}