{
  "type": "Feature",
  "properties": {
    "iso:country":"BE",
    "sg:address":"Zeelaan 16",
    "sg:city":"Koksijde",
    "sg:orig_category":"Zuivelproducten",
    "sg:phone":"+32 58 51 41 01",
    "sg:postcode":"8670",
    "sg:province":"West-Vlaanderen",
    "wof:name":"Huis De Finesse",
    "wof:placetype":"venue"
},
  "geometry": {"coordinates":[2.6501400471,51.1053695679],"type":"Point"}
}