{
  "type": "Feature",
  "properties": {
    "iso:country":"BE",
    "sg:address":"Rue Mauvinage 94",
    "sg:city":"Silly",
    "sg:orig_category":"V\u00e9los. Articles de jardin",
    "sg:phone":"+32 68 55 17 19",
    "sg:postcode":"7830",
    "sg:province":"Hainaut",
    "wof:name":"Fe. Deraux Andr\u00c9 & Fils",
    "wof:placetype":"venue"
},
  "geometry": {"coordinates":[3.9437260628,50.630531311],"type":"Point"}
}