{
  "type": "Feature",
  "properties": {
    "addr:full":"Rue D'achet 18 Hamois Namur 5360",
    "addr:housenumber":"18",
    "addr:postcode":"5360",
    "addr:street":"Rue D'Achet",
    "iso:country":"BE",
    "sg:address":"Rue D'achet 18",
    "sg:city":"Hamois",
    "sg:orig_category":"Kapsalons",
    "sg:phone":"+32 83 61 23 21",
    "sg:postcode":"5360",
    "sg:province":"Namur",
    "wof:name":"Pierre Jadot",
    "wof:placetype":"venue"
},
  "geometry": {"coordinates":[5.1583957672,50.3400611877],"type":"Point"}
}