{
  "type": "Feature",
  "properties": {
    "iso:country":"BE",
    "sg:address":"Boulevard Audent 15",
    "sg:city":"Charleroi",
    "sg:classifiers":[
        {
            "category":"Professional",
            "subcategory":"Lawyer & Legal Services",
            "type":"Services"
        }
    ],
    "sg:phone":"+32 71 31 41 43",
    "sg:postcode":"6000",
    "sg:province":"Hainaut",
    "wof:name":"Chiaravalle Vanessa",
    "wof:placetype":"venue"
},
  "geometry": {"coordinates":[4.4441518784,50.4101333618],"type":"Point"}
}