{
  "type": "Feature",
  "properties": {
    "addr:full":"Fruitmarkt 18 Hasselt Limburg 3500",
    "addr:housenumber":"18",
    "addr:postcode":"3500",
    "addr:street":"Fruitmarkt",
    "iso:country":"BE",
    "sg:address":"Fruitmarkt 18",
    "sg:city":"Hasselt",
    "sg:orig_category":"S\u00e9curit\u00e9 sociale",
    "sg:phone":"+32 11 28 03 24",
    "sg:postcode":"3500",
    "sg:province":"Limburg",
    "wof:name":"Christelijke Mutualiteit",
    "wof:placetype":"venue"
},
  "geometry": {"coordinates":[5.3386149406,50.9302215576],"type":"Point"}
}