{
  "type": "Feature",
  "properties": {
    "addr:full":"Steendam 24 Gent Oost-Vlaanderen 9000",
    "addr:housenumber":"24",
    "addr:postcode":"9000",
    "addr:street":"Steendam;Oost-Vlaanderen",
    "iso:country":"BE",
    "sg:address":"Steendam 24",
    "sg:city":"Gent",
    "sg:orig_category":"Antiquit\u00e9s",
    "sg:phone":"+32 9 224 30 65",
    "sg:postcode":"9000",
    "sg:province":"Oost-Vlaanderen",
    "wof:name":"Huis De Bekoring",
    "wof:placetype":"venue"
},
  "geometry": {"coordinates":[3.7293460369,51.0569114685],"type":"Point"}
}