{
  "type": "Feature",
  "properties": {
    "addr:full":"Molenstraat 8 Wuustwezel Antwerpen 2990",
    "addr:housenumber":"8",
    "addr:postcode":"2990",
    "addr:street":"Molenstraat",
    "iso:country":"BE",
    "sg:address":"Molenstraat 8",
    "sg:city":"Wuustwezel",
    "sg:orig_category":"Pluimveekwekers Rundveehouders Varkenskwekers",
    "sg:phone":"+32 3 669 64 01",
    "sg:postcode":"2990",
    "sg:province":"Antwerpen",
    "wof:name":"Jan Rombouts",
    "wof:placetype":"venue"
},
  "geometry": {"coordinates":[4.586933136,51.4006538391],"type":"Point"}
}