{
  "type": "Feature",
  "properties": {
    "addr:full":"Rue Des Alli\u00c9s 22 Chapelle-lez-herlaimont Hainaut 7160",
    "addr:housenumber":"22",
    "addr:postcode":"7160",
    "addr:street":"Rue Des Allie\u0301S",
    "iso:country":"BE",
    "sg:address":"Rue Des Alli\u00c9s 22",
    "sg:city":"Chapelle-lez-herlaimont",
    "sg:orig_category":"M\u00e9decins and sp\u00e9cialistes",
    "sg:phone":"+32 64 45 18 38",
    "sg:postcode":"7160",
    "sg:province":"Hainaut",
    "wof:name":"Marthe Guissard",
    "wof:placetype":"venue"
},
  "geometry": {"coordinates":[4.2781090736,50.4700393677],"type":"Point"}
}