{
  "type": "Feature",
  "properties": {
    "iso:country":"BE",
    "sg:address":"Diestsesteenweg 389",
    "sg:city":"Aarschot",
    "sg:orig_category":"Chaussures. Maroquinerie and articles de voyage",
    "sg:phone":"+32 16 50 10 99",
    "sg:postcode":"3202",
    "sg:province":"Vlaams-Brabant",
    "wof:name":"Huis Mario",
    "wof:placetype":"venue"
},
  "geometry": {"coordinates":[4.899242878,50.9743690491],"type":"Point"}
}