{
  "type": "Feature",
  "properties": {
    "addr:full":"Weldadigheidstraat 60 Gent Oost-Vlaanderen 9050",
    "addr:housenumber":"60",
    "addr:postcode":"9050",
    "addr:street":"Weldadigheidstraat;Oost-Vlaanderen",
    "iso:country":"BE",
    "sg:address":"Weldadigheidstraat 60",
    "sg:city":"Gent",
    "sg:orig_category":"Parfumeries",
    "sg:phone":"+32 9 231 91 87",
    "sg:postcode":"9050",
    "sg:province":"Oost-Vlaanderen",
    "wof:name":"Jean Delporte",
    "wof:placetype":"venue"
},
  "geometry": {"coordinates":[3.7444999218,51.0340080261],"type":"Point"}
}