{
  "type": "Feature",
  "properties": {
    "iso:country":"BE",
    "sg:address":"Rue De La Baronne 34",
    "sg:city":"Seneffe",
    "sg:classifiers":[
        {
            "category":"Personal",
            "subcategory":"Beauty Salon",
            "type":"Services"
        }
    ],
    "sg:phone":"+32 67 87 83 39",
    "sg:postcode":"7181",
    "sg:province":"Hainaut",
    "sg:tags":[
        "de",
        "coiffure"
    ],
    "wof:name":"Anne Dejean",
    "wof:placetype":"venue"
},
  "geometry": {"coordinates":[4.2705111504,50.5660934448],"type":"Point"}
}