{
  "type": "Feature",
  "properties": {
    "iso:country":"BE",
    "sg:address":"Wespelaarsebaan 43-45",
    "sg:city":"Boortmeerbeek",
    "sg:classifiers":[
        {
            "category":"Home & Garden",
            "subcategory":"Garden Supply",
            "type":"Retail Goods"
        }
    ],
    "sg:phone":"+32 15 51 38 27",
    "sg:postcode":"3190",
    "sg:province":"Vlaams-Brabant",
    "wof:name":"Van Parijs-crauwels",
    "wof:placetype":"venue"
},
  "geometry": {"coordinates":[4.577644825,50.9788818359],"type":"Point"}
}