{
  "type": "Feature",
  "properties": {
    "addr:full":"Pol Heynsstraat 41 Box 4 Herentals Antwerpen 2200",
    "addr:housenumber":"41;4",
    "addr:postcode":"2200",
    "addr:street":"Heynsstraat;Box",
    "iso:country":"BE",
    "sg:address":"Pol Heynsstraat 41 Box 4",
    "sg:city":"Herentals",
    "sg:classifiers":[
        {
            "category":"Real Estate",
            "subcategory":"Architect",
            "type":"Services"
        }
    ],
    "sg:phone":"+32 14 36 82 92",
    "sg:postcode":"2200",
    "sg:province":"Antwerpen",
    "wof:name":"Hens S",
    "wof:placetype":"venue"
},
  "geometry": {"coordinates":[4.8386940956,51.1698608398],"type":"Point"}
}