{
  "type": "Feature",
  "properties": {
    "iso:country":"BE",
    "sg:address":"Chauss\u00e9e De Li\u00e8ge 508",
    "sg:city":"Namur (jambes)",
    "sg:classifiers":[
        {
            "category":"Recreation",
            "subcategory":"Arcade",
            "type":"Entertainment"
        }
    ],
    "sg:phone":"+32 81 30 35 12",
    "sg:postcode":"5100",
    "sg:province":"Namur",
    "sg:tags":[
        "machine",
        "amusement"
    ],
    "wof:name":"Automatique G\u00e9n\u00e9rale Namur",
    "wof:placetype":"venue"
},
  "geometry": {"coordinates":[4.8713750839,50.4566345215],"type":"Point"}
}