{
  "type": "Feature",
  "properties": {
    "iso:country":"BE",
    "sg:address":"Rue Des Rouges Foss\u00c9s 35",
    "sg:city":"Huy",
    "sg:orig_category":"Diverse bouwafwerking and reiniging Woningbouw",
    "sg:phone":"+32 85 21 12 83",
    "sg:postcode":"4500",
    "sg:province":"Li\u00e8ge",
    "wof:name":"Roger Gilson",
    "wof:placetype":"venue"
},
  "geometry": {"coordinates":[5.2400307655,50.5178337097],"type":"Point"}
}