{
  "type": "Feature",
  "properties": {
    "addr:full":"Zottegemsestweg 12 Zwalm Oost-Vlaanderen 9630",
    "addr:housenumber":"12",
    "addr:postcode":"9630",
    "addr:street":"Zottegemsestweg;Oost-Vlaanderen",
    "iso:country":"BE",
    "sg:address":"Zottegemsestweg 12",
    "sg:city":"Zwalm",
    "sg:orig_category":"Herstellingen and onderhoud van auto's",
    "sg:phone":"+32 55 49 70 94",
    "sg:postcode":"9630",
    "sg:province":"Oost-Vlaanderen",
    "wof:name":"V.d.r.",
    "wof:placetype":"venue"
},
  "geometry": {"coordinates":[3.7622990608,50.8624763489],"type":"Point"}
}