{
  "type": "Feature",
  "properties": {
    "iso:country":"BE",
    "sg:address":"Kortrijksestraat 321",
    "sg:city":"Wevelgem",
    "sg:orig_category":"Diepvriesproducten Gh",
    "sg:phone":"+32 56 41 27 26",
    "sg:postcode":"8560",
    "sg:province":"West-Vlaanderen",
    "wof:name":"O' Cool",
    "wof:placetype":"venue"
},
  "geometry": {"coordinates":[3.2036430836,50.8150939941],"type":"Point"}
}