{
  "type": "Feature",
  "properties": {
    "addr:full":"Rue De Pousset 18 Oreye Li\u00e8ge 4360",
    "addr:housenumber":"18",
    "addr:postcode":"4360",
    "addr:street":"Rue De Pousset",
    "iso:country":"BE",
    "sg:address":"Rue De Pousset 18",
    "sg:city":"Oreye",
    "sg:classifiers":[
        {
            "category":"Freight",
            "type":"Transportation"
        }
    ],
    "sg:phone":"+32 19 67 84 11",
    "sg:postcode":"4360",
    "sg:province":"Li\u00e8ge",
    "sg:tags":[
        "-",
        "transport"
    ],
    "wof:name":"Claude J-p",
    "wof:placetype":"venue"
},
  "geometry": {"coordinates":[5.3260941505,50.7130317688],"type":"Point"}
}