{
  "type": "Feature",
  "properties": {
    "addr:full":"All\u00c9e Du Pr\u00c9-lorette 5 Nivelles Brabant Wallon 1400",
    "addr:housenumber":"5",
    "addr:postcode":"1400",
    "addr:street":"Alle\u0301E Du Pre\u0301-Lorette",
    "iso:country":"BE",
    "sg:address":"All\u00c9e Du Pr\u00c9-lorette 5",
    "sg:city":"Nivelles",
    "sg:orig_category":"Krantenuitgeverijen Tijdschriftenuitgeverijen",
    "sg:phone":"+32 67 21 37 21",
    "sg:postcode":"1400",
    "sg:province":"Brabant Wallon",
    "wof:name":"Tribal",
    "wof:placetype":"venue"
},
  "geometry": {"coordinates":[4.3181772232,50.6036758423],"type":"Point"}
}