{
  "type": "Feature",
  "properties": {
    "iso:country":"BE",
    "sg:address":"Rue Du Point-d'arret 12",
    "sg:city":"Nassogne",
    "sg:orig_category":"Paramedische behandelingen",
    "sg:phone":"+32 84 36 72 27",
    "sg:postcode":"6953",
    "sg:province":"Luxembourg",
    "wof:name":"M. Merveille",
    "wof:placetype":"venue"
},
  "geometry": {"coordinates":[5.280796051,50.1118431091],"type":"Point"}
}