{
  "type": "Feature",
  "properties": {
    "addr:full":"Petit Barvaux 4 Durbuy (barvaux-sur-ourthe) Luxembourg 6940",
    "addr:housenumber":"4",
    "addr:postcode":"6940",
    "addr:street":"Petit Barvaux",
    "iso:country":"BE",
    "sg:address":"Petit Barvaux 4",
    "sg:city":"Durbuy (barvaux-sur-ourthe)",
    "sg:classifiers":[
        {
            "category":"Health Services",
            "subcategory":"Dentist",
            "type":"Services"
        }
    ],
    "sg:phone":"+32 86 21 27 90",
    "sg:postcode":"6940",
    "sg:province":"Luxembourg",
    "wof:name":"Gilson Jacques",
    "wof:placetype":"venue"
},
  "geometry": {"coordinates":[5.4543361664,50.3515777588],"type":"Point"}
}