{
  "type": "Feature",
  "properties": {
    "addr:full":"Rue Cornelis Debruyn 37 Charleroi (lodelinsart) Hainaut 6042",
    "addr:housenumber":"37",
    "addr:postcode":"6042",
    "addr:street":"Rue Cornelis Debruyn",
    "iso:country":"BE",
    "sg:address":"Rue Cornelis Debruyn 37",
    "sg:city":"Charleroi (lodelinsart)",
    "sg:classifiers":[
        {
            "category":"Professional",
            "subcategory":"Art Services",
            "type":"Services"
        }
    ],
    "sg:phone":"+32 71 32 63 13",
    "sg:postcode":"6042",
    "sg:province":"Hainaut",
    "sg:tags":[
        "decorative",
        "joinery"
    ],
    "wof:name":"Jackowska R",
    "wof:placetype":"venue"
},
  "geometry": {"coordinates":[4.4244709015,50.4251708984],"type":"Point"}
}