{
  "type": "Feature",
  "properties": {
    "addr:full":"Rue De Mertenne 19 Walcourt Namur 5650",
    "addr:housenumber":"19",
    "addr:postcode":"5650",
    "addr:street":"Rue De Mertenne",
    "iso:country":"BE",
    "sg:address":"Rue De Mertenne 19",
    "sg:city":"Walcourt",
    "sg:orig_category":"Eleveurs de bovins",
    "sg:phone":"+32 71 63 30 48",
    "sg:postcode":"5650",
    "sg:province":"Namur",
    "wof:name":"Gerard Vanderhaeghen",
    "wof:placetype":"venue"
},
  "geometry": {"coordinates":[4.4313349724,50.2514762878],"type":"Point"}
}