{
  "type": "Feature",
  "properties": {
    "iso:country":"BE",
    "sg:address":"Renier Sniedersstraat 7",
    "sg:city":"Merksplas",
    "sg:orig_category":"Architecten",
    "sg:phone":"+32 14 63 41 30",
    "sg:postcode":"2330",
    "sg:province":"Antwerpen",
    "wof:name":"Joan Van Bavel",
    "wof:placetype":"venue"
},
  "geometry": {"coordinates":[4.8521251678,51.3583564758],"type":"Point"}
}