{
  "type": "Feature",
  "properties": {
    "addr:full":"Prins Boudewijnlaan 135 Edegem Antwerpen 2650",
    "addr:housenumber":"135",
    "addr:postcode":"2650",
    "addr:street":"Prins Boudewijnlaan",
    "iso:country":"BE",
    "sg:address":"Prins Boudewijnlaan 135",
    "sg:city":"Edegem",
    "sg:classifiers":[
        {
            "category":"Professional",
            "subcategory":"Management & Consulting",
            "type":"Services"
        }
    ],
    "sg:phone":"+32 3 288 44 75",
    "sg:postcode":"2650",
    "sg:province":"Antwerpen",
    "sg:tags":[
        "consultant"
    ],
    "wof:name":"The Alchemist",
    "wof:placetype":"venue"
},
  "geometry": {"coordinates":[4.434196949,51.1525421143],"type":"Point"}
}