{
  "type": "Feature",
  "properties": {
    "addr:full":"Rue D'eghez\u00e9e 58 Jemeppe-sur-sambre Namur 5190",
    "addr:housenumber":"58",
    "addr:postcode":"5190",
    "addr:street":"Rue D'Egheze \u0301E",
    "iso:country":"BE",
    "sg:address":"Rue D'eghez\u00e9e 58",
    "sg:city":"Jemeppe-sur-sambre",
    "sg:classifiers":[
        {
            "category":"Retail",
            "subcategory":"Auto Repair",
            "type":"Services"
        }
    ],
    "sg:postcode":"5190",
    "sg:province":"Namur",
    "sg:tags":[
        "automobile-body"
    ],
    "wof:name":"Polet (carrosserie)",
    "wof:placetype":"venue"
},
  "geometry": {"coordinates":[4.6697611809,50.4630661011],"type":"Point"}
}