{
  "type": "Feature",
  "properties": {
    "addr:full":"Rue Chapuis 25 Seraing Li\u00e8ge 4100",
    "addr:housenumber":"25",
    "addr:postcode":"4100",
    "addr:street":"Rue Chapuis",
    "iso:country":"BE",
    "sg:address":"Rue Chapuis 25",
    "sg:city":"Seraing",
    "sg:classifiers":[
        {
            "category":"Bars & Pubs",
            "type":"Food & Drink"
        }
    ],
    "sg:phone":"+32 4 385 09 79",
    "sg:postcode":"4100",
    "sg:province":"Li\u00e8ge",
    "wof:name":"Chapuis (le)",
    "wof:placetype":"venue"
},
  "geometry": {"coordinates":[5.5100498199,50.5985717773],"type":"Point"}
}