{
  "type": "Feature",
  "properties": {
    "addr:full":"Turnhoutsebaan 221 Schilde Antwerpen 2970",
    "addr:housenumber":"221",
    "addr:postcode":"2970",
    "addr:street":"Turnhoutsebaan",
    "iso:country":"BE",
    "sg:address":"Turnhoutsebaan 221",
    "sg:city":"Schilde",
    "sg:orig_category":"Loodgieterij, verwarming and sanitaire installaties Meubelzaken, woning- and keukeninrichting Zwemba",
    "sg:phone":"+32 3 383 06 69",
    "sg:postcode":"2970",
    "sg:province":"Antwerpen",
    "wof:name":"Bourbon-sleeckx",
    "wof:placetype":"venue"
},
  "geometry": {"coordinates":[4.5852627754,51.2417755127],"type":"Point"}
}