{
  "type": "Feature",
  "properties": {
    "addr:full":"All\u00c9e Des Cerisiers 20bb Vise Li\u00e8ge 4601",
    "addr:housenumber":"20bb",
    "addr:postcode":"4601",
    "addr:street":"Alle\u0301E Des Cerisiers",
    "iso:country":"BE",
    "sg:address":"All\u00c9e Des Cerisiers 20bb",
    "sg:city":"Vise",
    "sg:orig_category":"Traitements param\u00e9dicaux",
    "sg:phone":"+32 4 379 69 62",
    "sg:postcode":"4601",
    "sg:province":"Li\u00e8ge",
    "wof:name":"M. Pireaux",
    "wof:placetype":"venue"
},
  "geometry": {"coordinates":[5.6874017715,50.6957092285],"type":"Point"}
}