{
  "type": "Feature",
  "properties": {
    "addr:full":"Acacialaan 80 Harelbeke West-Vlaanderen 8530",
    "addr:housenumber":"80",
    "addr:postcode":"8530",
    "addr:street":"Acacialaan",
    "iso:country":"BE",
    "sg:address":"Acacialaan 80",
    "sg:city":"Harelbeke",
    "sg:classifiers":[
        {
            "category":"Retail",
            "subcategory":"Repair Shop",
            "type":"Services"
        }
    ],
    "sg:phone":"+32 56 70 49 66",
    "sg:postcode":"8530",
    "sg:province":"West-Vlaanderen",
    "sg:tags":[
        "radio",
        "television",
        "-",
        "maintenance"
    ],
    "wof:name":"Samaey P",
    "wof:placetype":"venue"
},
  "geometry": {"coordinates":[3.3012421131,50.8392524719],"type":"Point"}
}