{
  "type": "Feature",
  "properties": {
    "addr:full":"Mari\u00cbndaalstraat 35 Diest Vlaams-Brabant 3290",
    "addr:housenumber":"35",
    "addr:postcode":"3290",
    "addr:street":"Marie\u0308Ndaalstraat",
    "iso:country":"BE",
    "sg:address":"Mari\u00cbndaalstraat 35",
    "sg:city":"Diest",
    "sg:orig_category":"Activit\u00e9s d\u00b4action sociale sans h\u00e9bergement",
    "sg:phone":"+32 13 31 27 29",
    "sg:postcode":"3290",
    "sg:province":"Vlaams-Brabant",
    "wof:name":"Vclb-centrum",
    "wof:placetype":"venue"
},
  "geometry": {"coordinates":[5.056830883,50.9831924438],"type":"Point"}
}