{
  "type": "Feature",
  "properties": {
    "addr:full":"Leuvensestraat 8 Aarschot Vlaams-Brabant 3200",
    "addr:housenumber":"8",
    "addr:postcode":"3200",
    "addr:street":"Leuvensestraat",
    "iso:country":"BE",
    "sg:address":"Leuvensestraat 8",
    "sg:city":"Aarschot",
    "sg:orig_category":"Kapsalons",
    "sg:phone":"+32 16 56 63 62",
    "sg:postcode":"3200",
    "sg:province":"Vlaams-Brabant",
    "wof:name":"Karel Braes",
    "wof:placetype":"venue"
},
  "geometry": {"coordinates":[4.8322401047,50.9837989807],"type":"Point"}
}