{
  "type": "Feature",
  "properties": {
    "addr:full":"Rue Bertrand Janquin 151 Namur Namur 5100",
    "addr:housenumber":"151",
    "addr:postcode":"5100",
    "addr:street":"Rue Bertrand Janquin",
    "iso:country":"BE",
    "sg:address":"Rue Bertrand Janquin 151",
    "sg:city":"Namur",
    "sg:classifiers":[
        {
            "category":"Arena",
            "subcategory":"Sports Club",
            "type":"Entertainment"
        }
    ],
    "sg:phone":"+32 81 30 14 60",
    "sg:postcode":"5100",
    "sg:province":"Namur",
    "sg:tags":[
        "terrain",
        "hors",
        "de",
        "installation",
        "sportifs"
    ],
    "wof:name":"F.c. Naninnois",
    "wof:placetype":"venue"
},
  "geometry": {"coordinates":[4.8713750839,50.4566345215],"type":"Point"}
}