{
  "type": "Feature",
  "properties": {
    "iso:country":"BE",
    "sg:address":"Ruiffelaarswegel 2",
    "sg:city":"Kaprijke",
    "sg:orig_category":"Rundveehouders",
    "sg:phone":"+32 9 377 50 85",
    "sg:postcode":"9971",
    "sg:province":"Oost-Vlaanderen",
    "wof:name":"Goethals Tonny En Dirk",
    "wof:placetype":"venue"
},
  "geometry": {"coordinates":[3.6295061111,51.200088501],"type":"Point"}
}