{
  "type": "Feature",
  "properties": {
    "addr:full":"Chauss\u00e9e De Louvain 293 Waterloo Brabant Wallon 1410",
    "addr:housenumber":"293",
    "addr:postcode":"1410",
    "addr:street":"Chausse\u0301E De Louvain",
    "iso:country":"BE",
    "sg:address":"Chauss\u00e9e De Louvain 293",
    "sg:city":"Waterloo",
    "sg:classifiers":[
        {
            "category":"Professional",
            "subcategory":"Printing & Photocopies",
            "type":"Services"
        }
    ],
    "sg:phone":"+32 2 351 31 33",
    "sg:postcode":"1410",
    "sg:province":"Brabant Wallon",
    "sg:tags":[
        "engraving"
    ],
    "wof:name":"Graphitechnic Sprl",
    "wof:placetype":"venue"
},
  "geometry": {"coordinates":[4.4284591675,50.7030105591],"type":"Point"}
}