{
  "type": "Feature",
  "properties": {
    "addr:full":"Paul Van Ostaijenlaan 2 Hove Antwerpen 2540",
    "addr:housenumber":"2",
    "addr:postcode":"2540",
    "addr:street":"Paul Van Ostaijenlaan",
    "iso:country":"BE",
    "sg:address":"Paul Van Ostaijenlaan 2",
    "sg:city":"Hove",
    "sg:classifiers":[
        {
            "category":"Restaurant",
            "type":"Food & Drink"
        }
    ],
    "sg:phone":"+32 3 454 28 82",
    "sg:postcode":"2540",
    "sg:province":"Antwerpen",
    "sg:tags":[
        "caf\u00e9s"
    ],
    "wof:name":"Cafetaria Sporthal",
    "wof:placetype":"venue"
},
  "geometry": {"coordinates":[4.4752168655,51.1474571228],"type":"Point"}
}