{
  "type": "Feature",
  "properties": {
    "iso:country":"BE",
    "sg:address":"Solwaster 88",
    "sg:city":"Jalhay (sart)",
    "sg:classifiers":[
        {
            "category":"Bars & Pubs",
            "type":"Food & Drink"
        }
    ],
    "sg:phone":"+32 87 47 41 07",
    "sg:postcode":"4845",
    "sg:province":"Li\u00e8ge",
    "wof:name":"Cagna (la)",
    "wof:placetype":"venue"
},
  "geometry": {"coordinates":[5.967151165,50.5330314636],"type":"Point"}
}