{
  "type": "Feature",
  "properties": {
    "iso:country":"BE",
    "sg:address":"Urselseweg 26",
    "sg:city":"Knesselare",
    "sg:classifiers":[
        {
            "category":"Insurance",
            "subcategory":"Insurance Agent",
            "type":"Services"
        }
    ],
    "sg:phone":"+32 9 374 18 81",
    "sg:postcode":"9910",
    "sg:province":"Oost-Vlaanderen",
    "sg:tags":[
        "verzekeringsmakelaars",
        "expert"
    ],
    "wof:name":"P. Standaert",
    "wof:placetype":"venue"
},
  "geometry": {"coordinates":[3.4202179909,51.1363601685],"type":"Point"}
}