{
  "type": "Feature",
  "properties": {
    "iso:country":"BE",
    "sg:address":"Av De Tyras 51",
    "sg:city":"Bruxelles",
    "sg:classifiers":[
        {
            "category":"Professional",
            "subcategory":"Engineering",
            "type":"Services"
        }
    ],
    "sg:phone":"+32 2 262 10 10",
    "sg:postcode":"1120",
    "sg:province":"Bruxelles-Capitale",
    "sg:tags":[
        "machine",
        "-",
        "mechanical"
    ],
    "wof:name":"Mpe Npr Sa",
    "wof:placetype":"venue"
},
  "geometry": {"coordinates":[4.3973507881,50.9083557129],"type":"Point"}
}