{
  "type": "Feature",
  "properties": {
    "addr:full":"Hoogstraat 59 Deerlijk West-Vlaanderen 8540",
    "addr:housenumber":"59",
    "addr:postcode":"8540",
    "addr:street":"Hoogstraat",
    "iso:country":"BE",
    "sg:address":"Hoogstraat 59",
    "sg:city":"Deerlijk",
    "sg:classifiers":[
        {
            "category":"Shopping",
            "subcategory":"Clothing, Apparel, & Fashions",
            "type":"Retail Goods"
        }
    ],
    "sg:phone":"+32 56 72 90 50",
    "sg:postcode":"8540",
    "sg:province":"West-Vlaanderen",
    "sg:tags":[
        "boutique"
    ],
    "wof:name":"Feeling Good",
    "wof:placetype":"venue"
},
  "geometry": {"coordinates":[3.3564729691,50.8540840149],"type":"Point"}
}