{
  "type": "Feature",
  "properties": {
    "addr:full":"'t Lindeke 13 Ledegem (sint-eloois-winkel) West-Vlaanderen 8880",
    "addr:housenumber":"13",
    "addr:postcode":"8880",
    "addr:street":"' T Lindeke",
    "iso:country":"BE",
    "sg:address":"'t Lindeke 13",
    "sg:city":"Ledegem (sint-eloois-winkel)",
    "sg:classifiers":[
        {
            "category":"Professional",
            "subcategory":"Engineering",
            "type":"Services"
        }
    ],
    "sg:phone":"+32 56 50 30 43",
    "sg:postcode":"8880",
    "sg:province":"West-Vlaanderen",
    "sg:tags":[
        "environmental",
        "technique",
        "-"
    ],
    "wof:name":"Diepsonderingen Verbeke",
    "wof:placetype":"venue"
},
  "geometry": {"coordinates":[3.1801860332,50.8657913208],"type":"Point"}
}