{
  "type": "Feature",
  "properties": {
    "iso:country":"BE",
    "sg:address":"Rue Des Charbonnages 2",
    "sg:city":"Saint-nicolas",
    "sg:classifiers":[
        {
            "category":"Cafe",
            "type":"Food & Drink"
        }
    ],
    "sg:phone":"+32 4 239 12 89",
    "sg:postcode":"4420",
    "sg:province":"Li\u00e8ge",
    "sg:tags":[
        "caf\u00e9s"
    ],
    "wof:name":"Caf\u00c9 Chez Claude Perugino",
    "wof:placetype":"venue"
},
  "geometry": {"coordinates":[5.5293321609,50.6449165344],"type":"Point"}
}