{
  "type": "Feature",
  "properties": {
    "addr:full":"Hoefijzerstraat 2 Ichtegem West-Vlaanderen 8480",
    "addr:housenumber":"2",
    "addr:postcode":"8480",
    "addr:street":"Hoefijzerstraat",
    "iso:country":"BE",
    "sg:address":"Hoefijzerstraat 2",
    "sg:city":"Ichtegem",
    "sg:classifiers":[
        {
            "category":"Autos & Motor Vehicles",
            "subcategory":"Automobile Sales",
            "type":"Retail Goods"
        }
    ],
    "sg:phone":"+32 50 81 62 39",
    "sg:postcode":"8480",
    "sg:province":"West-Vlaanderen",
    "sg:tags":[
        "car",
        "used",
        "-"
    ],
    "wof:name":"Cd Motors",
    "wof:placetype":"venue"
},
  "geometry": {"coordinates":[3.0475749969,51.0907974243],"type":"Point"}
}