{
  "type": "Feature",
  "properties": {
    "iso:country":"BE",
    "sg:address":"Rue De La Poste 16",
    "sg:city":"Orp-jauche",
    "sg:orig_category":"Isolatiewerk",
    "sg:phone":"+32 19 63 70 93",
    "sg:postcode":"1350",
    "sg:province":"Brabant Wallon",
    "wof:name":"Vincent Crombe",
    "wof:placetype":"venue"
},
  "geometry": {"coordinates":[4.97920084,50.6738891602],"type":"Point"}
}