{
  "type": "Feature",
  "properties": {
    "iso:country":"BE",
    "sg:address":"Rue Fonds De Wartet 21",
    "sg:city":"Namur",
    "sg:orig_category":"Herstellingen and onderhoud van auto's",
    "sg:phone":"+32 81 58 93 95",
    "sg:postcode":"5024",
    "sg:province":"Namur",
    "wof:name":"A. Moreau",
    "wof:placetype":"venue"
},
  "geometry": {"coordinates":[4.9728078842,50.493221283],"type":"Point"}
}