{
  "type": "Feature",
  "properties": {
    "addr:full":"Zavelvennestraat 120 Hasselt Limburg 3500",
    "addr:housenumber":"120",
    "addr:postcode":"3500",
    "addr:street":"Zavelvennestraat",
    "iso:country":"BE",
    "sg:address":"Zavelvennestraat 120",
    "sg:city":"Hasselt",
    "sg:classifiers":[
        {
            "category":"Real Estate",
            "subcategory":"Surveying",
            "type":"Services"
        }
    ],
    "sg:phone":"+32 11 21 10 43",
    "sg:postcode":"3500",
    "sg:province":"Limburg",
    "sg:tags":[
        "surveyor",
        "land"
    ],
    "wof:name":"Schols A",
    "wof:placetype":"venue"
},
  "geometry": {"coordinates":[5.3749752045,50.9686164856],"type":"Point"}
}