{
  "type": "Feature",
  "properties": {
    "iso:country":"BE",
    "sg:address":"Lossingstraat 148",
    "sg:city":"Schoten",
    "sg:classifiers":[
        {
            "category":"Landmark",
            "subcategory":"Scenic View",
            "type":"Public Place"
        }
    ],
    "sg:phone":"+32 3 680 28 30",
    "sg:postcode":"2900",
    "sg:province":"Antwerpen",
    "sg:tags":[
        "setting",
        "photographic"
    ],
    "wof:name":"Artwork-studio V D Bempt Bvba",
    "wof:placetype":"venue"
},
  "geometry": {"coordinates":[4.5095100403,51.2554969788],"type":"Point"}
}