{
  "type": "Feature",
  "properties": {
    "iso:country":"BE",
    "sg:address":"Kouterwagenstraat 53",
    "sg:city":"Wetteren",
    "sg:classifiers":[
        {
            "category":"Organizations",
            "subcategory":"Professional Association",
            "type":"Services"
        }
    ],
    "sg:phone":"+32 9 211 07 08",
    "sg:postcode":"9230",
    "sg:province":"Oost-Vlaanderen",
    "sg:tags":[
        "customer",
        "software",
        "management",
        "relationship",
        "crm"
    ],
    "wof:name":"Ciel Software Support B.v.b.a.",
    "wof:placetype":"venue"
},
  "geometry": {"coordinates":[3.8407740593,51.0110015869],"type":"Point"}
}