{
  "type": "Feature",
  "properties": {
    "iso:country":"BE",
    "sg:address":"Jettelaan 286",
    "sg:city":"Jette",
    "sg:orig_category":"Alimentation sp\u00e9cialis\u00e9e",
    "sg:phone":"+32 2 425 39 57",
    "sg:postcode":"1090",
    "sg:province":"Bruxelles-Capitale",
    "wof:name":"Green Point",
    "wof:placetype":"venue"
},
  "geometry": {"coordinates":[4.3241019249,50.8721313477],"type":"Point"}
}