{
  "type": "Feature",
  "properties": {
    "iso:country":"BE",
    "sg:address":"Kleine Molenweg 26",
    "sg:city":"Stabroek",
    "sg:orig_category":"Kapsalons",
    "sg:phone":"+32 3 568 71 66",
    "sg:postcode":"2940",
    "sg:province":"Antwerpen",
    "wof:name":"Luc Maas",
    "wof:placetype":"venue"
},
  "geometry": {"coordinates":[4.3673591614,51.3307762146],"type":"Point"}
}