{
  "type": "Feature",
  "properties": {
    "iso:country":"BE",
    "sg:address":"Place De La Hestre 32",
    "sg:city":"Manage",
    "sg:classifiers":[
        {
            "category":"Restaurant",
            "type":"Food & Drink"
        }
    ],
    "sg:phone":"+32 64 84 25 84",
    "sg:postcode":"7170",
    "sg:province":"Hainaut",
    "wof:name":"Au Petit Creux",
    "wof:placetype":"venue"
},
  "geometry": {"coordinates":[4.2366042137,50.4746131897],"type":"Point"}
}