{
  "type": "Feature",
  "properties": {
    "addr:full":"Grand'rue 56-58 Aubange Luxembourg 6791",
    "addr:postcode":"56-58;6791",
    "addr:street":"Grand'Rue",
    "iso:country":"BE",
    "sg:address":"Grand'rue 56-58",
    "sg:city":"Aubange",
    "sg:orig_category":"Schoenen",
    "sg:phone":"+32 63 38 86 13",
    "sg:postcode":"6791",
    "sg:province":"Luxembourg",
    "wof:name":"Shoes In The Box",
    "wof:placetype":"venue"
},
  "geometry": {"coordinates":[5.8356189728,49.5628623962],"type":"Point"}
}