{
  "type": "Feature",
  "properties": {
    "iso:country":"BE",
    "sg:address":"Fays Village 48",
    "sg:city":"Sprimont",
    "sg:classifiers":[
        {
            "category":"Arena",
            "subcategory":"Sports Club",
            "type":"Entertainment"
        }
    ],
    "sg:phone":"+32 4 382 14 20",
    "sg:postcode":"4140",
    "sg:province":"Li\u00e8ge",
    "sg:tags":[
        "de"
    ],
    "wof:name":"Gym Club Essor Sprimont.",
    "wof:placetype":"venue"
},
  "geometry": {"coordinates":[5.6018538475,50.5110206604],"type":"Point"}
}