{
  "type": "Feature",
  "properties": {
    "iso:country":"BE",
    "sg:address":"Rue Du Moulin 1",
    "sg:city":"Virton",
    "sg:classifiers":[
        {
            "category":"Travel",
            "subcategory":"Hotels & Motels",
            "type":"Entertainment"
        }
    ],
    "sg:phone":"+32 63 57 89 35",
    "sg:postcode":"6760",
    "sg:province":"Luxembourg",
    "wof:name":"Cheval Blanc (h\u00f4tel Le)",
    "wof:placetype":"venue"
},
  "geometry": {"coordinates":[5.5338840485,49.5665092468],"type":"Point"}
}