{
  "type": "Feature",
  "properties": {
    "iso:country":"BE",
    "sg:address":"Rue De La Gare 8",
    "sg:city":"Assesse",
    "sg:classifiers":[
        {
            "category":"Personal",
            "subcategory":"Beauty Salon",
            "type":"Services"
        }
    ],
    "sg:phone":"+32 83 65 54 54",
    "sg:postcode":"5330",
    "sg:province":"Namur",
    "wof:name":"Cox",
    "wof:placetype":"venue"
},
  "geometry": {"coordinates":[5.0231509209,50.369468689],"type":"Point"}
}