{
  "type": "Feature",
  "properties": {
    "addr:full":"Oude Zandstraat 62 Beveren (beveren-waas) Oost-Vlaanderen 9120",
    "addr:housenumber":"62",
    "addr:postcode":"9120",
    "addr:street":"Oude Zandstraat;Oost-Vlaanderen",
    "iso:country":"BE",
    "sg:address":"Oude Zandstraat 62",
    "sg:city":"Beveren (beveren-waas)",
    "sg:classifiers":[
        {
            "category":"Bars & Pubs",
            "type":"Food & Drink"
        }
    ],
    "sg:phone":"+32 3 755 01 50",
    "sg:postcode":"9120",
    "sg:province":"Oost-Vlaanderen",
    "sg:tags":[
        "tavern"
    ],
    "wof:name":"New Wembley",
    "wof:placetype":"venue"
},
  "geometry": {"coordinates":[4.2518239021,51.2113456726],"type":"Point"}
}