{
  "type": "Feature",
  "properties": {
    "iso:country":"BE",
    "sg:address":"Chauss\u00c9e De Charleroi 222",
    "sg:city":"Namur",
    "sg:orig_category":"Supermarch\u00e9s",
    "sg:phone":"+32 81 74 56 16",
    "sg:postcode":"5000",
    "sg:province":"Namur",
    "wof:name":"Champion",
    "wof:placetype":"venue"
},
  "geometry": {"coordinates":[4.8352599144,50.457950592],"type":"Point"}
}