{
  "type": "Feature",
  "properties": {
    "iso:country":"BE",
    "sg:address":"Frayenhofstraat 22",
    "sg:city":"Lanaken",
    "sg:orig_category":"Afbraak- and draineerwerken",
    "sg:phone":"+32 89 71 22 27",
    "sg:postcode":"3620",
    "sg:province":"Limburg",
    "wof:name":"Leopold Claessens",
    "wof:placetype":"venue"
},
  "geometry": {"coordinates":[5.6255469322,50.8872795105],"type":"Point"}
}