{
  "type": "Feature",
  "properties": {
    "iso:country":"BE",
    "sg:address":"Van Overstraetenlaan 17",
    "sg:city":"Ternat",
    "sg:classifiers":[
        {
            "category":"Health Services",
            "subcategory":"Health Practitioner",
            "type":"Services"
        }
    ],
    "sg:phone":"+32 2 582 27 09",
    "sg:postcode":"1740",
    "sg:province":"Vlaams-Brabant",
    "sg:tags":[
        "physiotherapist"
    ],
    "wof:name":"Defever R",
    "wof:placetype":"venue"
},
  "geometry": {"coordinates":[4.1726298332,50.8730735779],"type":"Point"}
}