{
  "type": "Feature",
  "properties": {
    "iso:country":"BE",
    "sg:address":"Heppensesteenweg 116",
    "sg:city":"Beringen",
    "sg:orig_category":"Woningbouw",
    "sg:phone":"+32 11 34 44 29",
    "sg:postcode":"3581",
    "sg:province":"Limburg",
    "wof:name":"Biesemans G",
    "wof:placetype":"venue"
},
  "geometry": {"coordinates":[5.2256250381,51.0966529846],"type":"Point"}
}