{
  "type": "Feature",
  "properties": {
    "addr:full":"Bruul 108 Mechelen Antwerpen 2800",
    "addr:housenumber":"108",
    "addr:postcode":"2800",
    "addr:street":"Bruul",
    "iso:country":"BE",
    "sg:address":"Bruul 108",
    "sg:city":"Mechelen",
    "sg:classifiers":[
        {
            "category":"Real Estate",
            "subcategory":"Real Estate Services",
            "type":"Services"
        }
    ],
    "sg:phone":"+32 15 20 25 25",
    "sg:postcode":"2800",
    "sg:province":"Antwerpen",
    "wof:name":"I.m.o. Woningbureau Bvba",
    "wof:placetype":"venue"
},
  "geometry": {"coordinates":[4.4816889763,51.0240821838],"type":"Point"}
}