{
  "type": "Feature",
  "properties": {
    "iso:country":"BE",
    "sg:address":"Rue Des Bruy\u00e8res 4",
    "sg:city":"Namur (jambes)",
    "sg:classifiers":[
        {
            "category":"Building & Trades",
            "subcategory":"Landscaping Services",
            "type":"Services"
        }
    ],
    "sg:phone":"+32 81 30 36 84",
    "sg:postcode":"5100",
    "sg:province":"Namur",
    "sg:tags":[
        "architect",
        "landscape"
    ],
    "wof:name":"Van Serveyt J",
    "wof:placetype":"venue"
},
  "geometry": {"coordinates":[4.884745121,50.4383277893],"type":"Point"}
}