{
  "type": "Feature",
  "properties": {
    "iso:country":"BE",
    "sg:address":"Feynend 75",
    "sg:city":"Mol",
    "sg:classifiers":[
        {
            "category":"Real Estate",
            "subcategory":"Architect",
            "type":"Services"
        }
    ],
    "sg:phone":"+32 14 31 63 43",
    "sg:postcode":"2400",
    "sg:province":"Antwerpen",
    "wof:name":"Waumans B",
    "wof:placetype":"venue"
},
  "geometry": {"coordinates":[5.0719227791,51.1963539124],"type":"Point"}
}