{
  "type": "Feature",
  "properties": {
    "addr:full":"Brugseweg 58 Ieper West-Vlaanderen 8900",
    "addr:housenumber":"58",
    "addr:postcode":"8900",
    "addr:street":"Brugseweg",
    "iso:country":"BE",
    "sg:address":"Brugseweg 58",
    "sg:city":"Ieper",
    "sg:classifiers":[
        {
            "category":"Shopping",
            "subcategory":"Florist",
            "type":"Retail Goods"
        }
    ],
    "sg:phone":"+32 57 21 68 41",
    "sg:postcode":"8900",
    "sg:province":"West-Vlaanderen",
    "wof:name":"Caminus Flowers",
    "wof:placetype":"venue"
},
  "geometry": {"coordinates":[2.8901441097,50.8581466675],"type":"Point"}
}