{
  "type": "Feature",
  "properties": {
    "addr:full":"Leuvensesteenweg 343 Boutersem Vlaams-Brabant 3370",
    "addr:housenumber":"343",
    "addr:postcode":"3370",
    "addr:street":"Leuvensesteenweg",
    "iso:country":"BE",
    "sg:address":"Leuvensesteenweg 343",
    "sg:city":"Boutersem",
    "sg:orig_category":"Slagers",
    "sg:phone":"+32 16 73 56 66",
    "sg:postcode":"3370",
    "sg:province":"Vlaams-Brabant",
    "wof:name":"Julien Deputter",
    "wof:placetype":"venue"
},
  "geometry": {"coordinates":[4.8334240913,50.8418235779],"type":"Point"}
}