{
  "type": "Feature",
  "properties": {
    "iso:country":"BE",
    "sg:address":"Geluwestraat 124",
    "sg:city":"Wervik",
    "sg:orig_category":"Woningbouw",
    "sg:phone":"+32 56 31 17 87",
    "sg:postcode":"8940",
    "sg:province":"West-Vlaanderen",
    "wof:name":"Gerard Dumont",
    "wof:placetype":"venue"
},
  "geometry": {"coordinates":[3.050080061,50.787021637],"type":"Point"}
}