{
  "type": "Feature",
  "properties": {
    "addr:full":"Eliksemstraat 15 Linter Vlaams-Brabant 3350",
    "addr:housenumber":"15",
    "addr:postcode":"3350",
    "addr:street":"Eliksemstraat;Vlaams-Brabant",
    "iso:country":"BE",
    "sg:address":"Eliksemstraat 15",
    "sg:city":"Linter",
    "sg:orig_category":"Kapsalons",
    "sg:phone":"+32 16 78 85 65",
    "sg:postcode":"3350",
    "sg:province":"Vlaams-Brabant",
    "wof:name":"Philippe Gillaer",
    "wof:placetype":"venue"
},
  "geometry": {"coordinates":[5.0172858238,50.8068275452],"type":"Point"}
}