{
  "type": "Feature",
  "properties": {
    "addr:full":"Oudestraat 73 Boortmeerbeek Vlaams-Brabant 3190",
    "addr:housenumber":"73",
    "addr:postcode":"3190",
    "addr:street":"Oudestraat",
    "iso:country":"BE",
    "sg:address":"Oudestraat 73",
    "sg:city":"Boortmeerbeek",
    "sg:orig_category":"M\u00e9decins and sp\u00e9cialistes",
    "sg:phone":"+32 16 60 94 84",
    "sg:postcode":"3190",
    "sg:province":"Vlaams-Brabant",
    "wof:name":"Narine Rajkishan",
    "wof:placetype":"venue"
},
  "geometry": {"coordinates":[4.5930080414,50.9650726318],"type":"Point"}
}