{
  "type": "Feature",
  "properties": {
    "iso:country":"BE",
    "sg:address":"Vrasenestraat 156",
    "sg:city":"Sint-niklaas (nieuwkerken-waas)",
    "sg:classifiers":[
        {
            "category":"Health Services",
            "subcategory":"Nursing And Care Facility",
            "type":"Services"
        }
    ],
    "sg:phone":"+32 3 776 85 37",
    "sg:postcode":"9100",
    "sg:province":"Oost-Vlaanderen",
    "sg:tags":[
        "home"
    ],
    "wof:name":"De Rop M",
    "wof:placetype":"venue"
},
  "geometry": {"coordinates":[4.188680172,51.2021827698],"type":"Point"}
}