{
  "type": "Feature",
  "properties": {
    "iso:country":"BE",
    "sg:address":"Toekomststraat 33",
    "sg:city":"Herentals",
    "sg:orig_category":"Messageries",
    "sg:phone":"+32 14 59 40 40",
    "sg:postcode":"2100",
    "sg:province":"Antwerpen",
    "wof:name":"Transport Dockx",
    "wof:placetype":"venue"
},
  "geometry": {"coordinates":[4.797973156,51.1644172668],"type":"Point"}
}