{
  "type": "Feature",
  "properties": {
    "addr:full":"Vrijheidstraat 309 Boom Antwerpen 2850",
    "addr:housenumber":"309",
    "addr:postcode":"2850",
    "addr:street":"Vrijheidstraat",
    "iso:country":"BE",
    "sg:address":"Vrijheidstraat 309",
    "sg:city":"Boom",
    "sg:orig_category":"Loodgieterij and centrale verwarming Gh",
    "sg:phone":"+32 3 888 68 88",
    "sg:postcode":"2850",
    "sg:province":"Antwerpen",
    "wof:name":"Frateur",
    "wof:placetype":"venue"
},
  "geometry": {"coordinates":[4.3589601517,51.0891799927],"type":"Point"}
}