{
  "type": "Feature",
  "properties": {
    "addr:full":"Chauss\u00e9e De Bruxelles 255 Wemmel Vlaams-Brabant 1780",
    "addr:housenumber":"255",
    "addr:postcode":"1780",
    "addr:street":"Chausse\u0301E De Bruxelles;Vlaams-Brabant",
    "iso:country":"BE",
    "sg:address":"Chauss\u00e9e De Bruxelles 255",
    "sg:city":"Wemmel",
    "sg:classifiers":[
        {
            "category":"Home & Garden",
            "subcategory":"Building Materials",
            "type":"Retail Goods"
        }
    ],
    "sg:phone":"+32 2 461 25 25",
    "sg:postcode":"1780",
    "sg:province":"Vlaams-Brabant",
    "sg:tags":[
        "veranda"
    ],
    "wof:name":"Seby Veranda's Bvba",
    "wof:placetype":"venue"
},
  "geometry": {"coordinates":[4.3096590042,50.899772644],"type":"Point"}
}