{
  "type": "Feature",
  "properties": {
    "iso:country":"BE",
    "sg:address":"Papiermolenstraat 10",
    "sg:city":"Geraardsbergen",
    "sg:orig_category":"Boissons",
    "sg:phone":"+32 54 41 37 73",
    "sg:postcode":"9500",
    "sg:province":"Oost-Vlaanderen",
    "wof:name":"Marc D'hulst",
    "wof:placetype":"venue"
},
  "geometry": {"coordinates":[3.8705670834,50.7694396973],"type":"Point"}
}