{
  "type": "Feature",
  "properties": {
    "iso:country":"BE",
    "sg:address":"Rue Trieu Robin 1",
    "sg:city":"Beaumont",
    "sg:orig_category":"Transports routiers de marchandises. D\u00e9molition d\u00b4immeubles and terrassements",
    "sg:phone":"+32 60 45 53 14",
    "sg:postcode":"6500",
    "sg:province":"Hainaut",
    "wof:name":"Albin Dalpiaz",
    "wof:placetype":"venue"
},
  "geometry": {"coordinates":[4.2692570686,50.1900024414],"type":"Point"}
}