{
  "type": "Feature",
  "properties": {
    "iso:country":"BE",
    "sg:address":"Avenue Carton De Wiart 105",
    "sg:city":"Bruxelles (jette)",
    "sg:classifiers":[
        {
            "category":"Wholesale",
            "subcategory":"Medical Equipment & Supplies",
            "type":"Manufacturing & Wholesale Goods"
        }
    ],
    "sg:phone":"+32 2 420 62 10",
    "sg:postcode":"1090",
    "sg:province":"Bruxelles-Capitale",
    "sg:tags":[
        "instrument",
        "apparatus"
    ],
    "wof:name":"Weinmann: Belgien",
    "wof:placetype":"venue"
},
  "geometry": {"coordinates":[4.3272099495,50.8677825928],"type":"Point"}
}