{
  "type": "Feature",
  "properties": {
    "addr:full":"Langendamdreef 38a Aalter Oost-Vlaanderen 9880",
    "addr:housenumber":"38a",
    "addr:postcode":"9880",
    "addr:street":"Langendamdreef",
    "iso:country":"BE",
    "sg:address":"Langendamdreef 38a",
    "sg:city":"Aalter",
    "sg:classifiers":[
        {
            "category":"Health Services",
            "subcategory":"Medical Lab",
            "type":"Services"
        }
    ],
    "sg:phone":"+32 9 374 29 32",
    "sg:postcode":"9880",
    "sg:province":"Oost-Vlaanderen",
    "sg:tags":[
        "laboratory",
        "dental"
    ],
    "wof:name":"Neirynck-bonami Bvba",
    "wof:placetype":"venue"
},
  "geometry": {"coordinates":[3.4672350883,51.0733833313],"type":"Point"}
}