{
  "type": "Feature",
  "properties": {
    "addr:full":"Rue Emile Parfonry 5 Hotton Luxembourg 6990",
    "addr:housenumber":"5",
    "addr:postcode":"6990",
    "addr:street":"Rue Emile Parfonry",
    "iso:country":"BE",
    "sg:address":"Rue Emile Parfonry 5",
    "sg:city":"Hotton",
    "sg:classifiers":[
        {
            "category":"Personal",
            "subcategory":"Barber",
            "type":"Services"
        }
    ],
    "sg:phone":"+32 84 46 60 35",
    "sg:postcode":"6990",
    "sg:province":"Luxembourg",
    "sg:tags":[
        "gentleman",
        "salon",
        "-",
        "hairdressing"
    ],
    "wof:name":"Art & Beaut\u00e9",
    "wof:placetype":"venue"
},
  "geometry": {"coordinates":[5.4462919235,50.2673950195],"type":"Point"}
}