{
  "type": "Feature",
  "properties": {
    "iso:country":"BE",
    "sg:address":"Steentjemolenstraat 43",
    "sg:city":"Ieper",
    "sg:orig_category":"Varkenskwekers",
    "sg:phone":"+32 57 42 21 92",
    "sg:postcode":"8906",
    "sg:province":"West-Vlaanderen",
    "wof:name":"Joseph Cardoen",
    "wof:placetype":"venue"
},
  "geometry": {"coordinates":[2.7819719315,50.8792419434],"type":"Point"}
}