{
  "type": "Feature",
  "properties": {
    "addr:full":"Oude Molenweg 20 Zuienkerke (meetkerke) West-Vlaanderen 8377",
    "addr:housenumber":"20",
    "addr:postcode":"8377",
    "addr:street":"Oude Molenweg",
    "iso:country":"BE",
    "sg:address":"Oude Molenweg 20",
    "sg:city":"Zuienkerke (meetkerke)",
    "sg:classifiers":[
        {
            "category":"Utilities",
            "subcategory":"Water",
            "type":"Services"
        }
    ],
    "sg:phone":"+32 50 31 10 29",
    "sg:postcode":"8377",
    "sg:province":"West-Vlaanderen",
    "sg:tags":[
        "warm",
        "-",
        "heating",
        "air"
    ],
    "wof:name":"Multiclima Bvba",
    "wof:placetype":"venue"
},
  "geometry": {"coordinates":[3.1512649059,51.2358970642],"type":"Point"}
}