{
  "type": "Feature",
  "properties": {
    "iso:country":"BE",
    "sg:address":"Sanatoriumstraat 256",
    "sg:city":"Beersel",
    "sg:orig_category":"Alimentation sp\u00e9cialis\u00e9e",
    "sg:phone":"+32 2 380 15 78",
    "sg:postcode":"1652",
    "sg:province":"Vlaams-Brabant",
    "wof:name":"Jo Musiek",
    "wof:placetype":"venue"
},
  "geometry": {"coordinates":[4.3074550629,50.7574157715],"type":"Point"}
}