{
  "type": "Feature",
  "properties": {
    "iso:country":"BE",
    "sg:address":"Markt 34",
    "sg:city":"Lokeren",
    "sg:classifiers":[
        {
            "category":"Communications",
            "subcategory":"Film & Video Production",
            "type":"Services"
        }
    ],
    "sg:phone":"+32 9 348 24 03",
    "sg:postcode":"9160",
    "sg:province":"Oost-Vlaanderen",
    "sg:tags":[
        "hiring",
        "-"
    ],
    "wof:name":"Videoland",
    "wof:placetype":"venue"
},
  "geometry": {"coordinates":[3.9902451038,51.104259491],"type":"Point"}
}