{
  "type": "Feature",
  "properties": {
    "addr:full":"Bevegemstraat 7 Zottegem Oost-Vlaanderen 9620",
    "addr:housenumber":"7",
    "addr:postcode":"9620",
    "addr:street":"Bevegemstraat",
    "iso:country":"BE",
    "sg:address":"Bevegemstraat 7",
    "sg:city":"Zottegem",
    "sg:orig_category":"Begrafeniswezen",
    "sg:phone":"+32 9 360 56 45",
    "sg:postcode":"9620",
    "sg:province":"Oost-Vlaanderen",
    "wof:name":"Begrafenissen Porrez",
    "wof:placetype":"venue"
},
  "geometry": {"coordinates":[3.826734066,50.8641357422],"type":"Point"}
}