{
  "type": "Feature",
  "properties": {
    "iso:country":"BE",
    "sg:address":"Gentstraat 147",
    "sg:city":"Sint-niklaas",
    "sg:orig_category":"Rundveehouders",
    "sg:phone":"+32 3 776 47 36",
    "sg:postcode":"9111",
    "sg:province":"Oost-Vlaanderen",
    "wof:name":"Jozef Van Puyvelde",
    "wof:placetype":"venue"
},
  "geometry": {"coordinates":[4.0966300964,51.1768684387],"type":"Point"}
}