{
  "type": "Feature",
  "properties": {
    "iso:country":"BE",
    "sg:address":"Vagevuurstraat 21",
    "sg:city":"Zuienkerke",
    "sg:classifiers":[
        {
            "category":"Health Services",
            "subcategory":"Doctor",
            "type":"Services"
        }
    ],
    "sg:phone":"+32 50 55 14 88",
    "sg:postcode":"8377",
    "sg:province":"West-Vlaanderen",
    "sg:tags":[
        "medicinephysicians",
        "surgeon"
    ],
    "wof:name":"Hespel Geert",
    "wof:placetype":"venue"
},
  "geometry": {"coordinates":[3.1532449722,51.2647247314],"type":"Point"}
}