{
  "type": "Feature",
  "properties": {
    "addr:full":"Kolonel Dusartplein 34b9 Hasselt Limburg 3500",
    "addr:housenumber":"34b9",
    "addr:postcode":"3500",
    "addr:street":"Kolonel Dusartplein",
    "iso:country":"BE",
    "sg:address":"Kolonel Dusartplein 34b9",
    "sg:city":"Hasselt",
    "sg:orig_category":"M\u00e9decins and sp\u00e9cialistes",
    "sg:phone":"+32 11 22 72 94",
    "sg:postcode":"3500",
    "sg:province":"Limburg",
    "wof:name":"Hugo Velkeneers",
    "wof:placetype":"venue"
},
  "geometry": {"coordinates":[5.3426971436,50.9315795898],"type":"Point"}
}