{
  "type": "Feature",
  "properties": {
    "addr:full":"Rue Haute 31 Vis\u00e9 Li\u00e8ge 4600",
    "addr:housenumber":"31",
    "addr:postcode":"4600",
    "addr:street":"Rue Haute",
    "iso:country":"BE",
    "sg:address":"Rue Haute 31",
    "sg:city":"Vis\u00e9",
    "sg:classifiers":[
        {
            "category":"Shopping",
            "subcategory":"Crafts & Fabrics",
            "type":"Retail Goods"
        }
    ],
    "sg:phone":"+32 4 379 80 80",
    "sg:postcode":"4600",
    "sg:province":"Li\u00e8ge",
    "sg:tags":[
        "hi-fi",
        "equipment",
        "stereophonic",
        "-"
    ],
    "wof:name":"Digit'home",
    "wof:placetype":"venue"
},
  "geometry": {"coordinates":[5.6962451935,50.734249115],"type":"Point"}
}