{
  "type": "Feature",
  "properties": {
    "addr:full":"Kapellaan 9 Kalmthout Antwerpen 2920",
    "addr:housenumber":"9",
    "addr:postcode":"2920",
    "addr:street":"Kapellaan",
    "iso:country":"BE",
    "sg:address":"Kapellaan 9",
    "sg:city":"Kalmthout",
    "sg:classifiers":[
        {
            "category":"Professional",
            "subcategory":"Lawyer & Legal Services",
            "type":"Services"
        }
    ],
    "sg:phone":"+32 3 666 56 67",
    "sg:postcode":"2920",
    "sg:province":"Antwerpen",
    "wof:name":"Exelmans Iris",
    "wof:placetype":"venue"
},
  "geometry": {"coordinates":[4.4689979553,51.393913269],"type":"Point"}
}