{
  "type": "Feature",
  "properties": {
    "iso:country":"BE",
    "sg:address":"Rue Des Bons Buveurs 10",
    "sg:city":"Saint-nicolas",
    "sg:classifiers":[
        {
            "category":"Real Estate",
            "subcategory":"Architect",
            "type":"Services"
        }
    ],
    "sg:phone":"+32 4 224 02 36",
    "sg:postcode":"4420",
    "sg:province":"Li\u00e8ge",
    "wof:name":"Tek M",
    "wof:placetype":"venue"
},
  "geometry": {"coordinates":[5.5354199409,50.6397514343],"type":"Point"}
}