{
  "type": "Feature",
  "properties": {
    "iso:country":"BE",
    "sg:address":"Rozenlaan 23",
    "sg:city":"Bredene",
    "sg:orig_category":"Kampeerterreinen",
    "sg:phone":"+32 59 32 38 71",
    "sg:postcode":"8450",
    "sg:province":"West-Vlaanderen",
    "wof:name":"Duinzicht 17",
    "wof:placetype":"venue"
},
  "geometry": {"coordinates":[2.9669411182,51.2489547729],"type":"Point"}
}