{
  "type": "Feature",
  "properties": {
    "addr:full":"Rue De La Sucrerie 6 Ath Hainaut 7800",
    "addr:housenumber":"6",
    "addr:postcode":"7800",
    "addr:street":"Rue De La Sucrerie",
    "iso:country":"BE",
    "sg:address":"Rue De La Sucrerie 6",
    "sg:city":"Ath",
    "sg:classifiers":[
        {
            "category":"Utilities",
            "subcategory":"Refuse",
            "type":"Services"
        }
    ],
    "sg:phone":"+32 68 26 88 40",
    "sg:postcode":"7800",
    "sg:province":"Hainaut",
    "sg:tags":[
        "catering"
    ],
    "wof:name":"Sorest Depoitre Sprl",
    "wof:placetype":"venue"
},
  "geometry": {"coordinates":[3.7766499519,50.6245803833],"type":"Point"}
}