{
  "type": "Feature",
  "properties": {
    "iso:country":"BE",
    "sg:address":"Rue Gustave Linet 27",
    "sg:city":"Villers-la-ville",
    "sg:orig_category":"Eleveurs de bovins",
    "sg:phone":"+32 71 87 73 66",
    "sg:postcode":"1495",
    "sg:province":"Brabant Wallon",
    "wof:name":"Marc Deconinck",
    "wof:placetype":"venue"
},
  "geometry": {"coordinates":[4.4877209663,50.5623512268],"type":"Point"}
}