{
  "type": "Feature",
  "properties": {
    "iso:country":"BE",
    "sg:address":"Meenselstraat 16",
    "sg:city":"Lubbeek",
    "sg:orig_category":"Producteurs de fruits",
    "sg:phone":"+32 16 63 47 64",
    "sg:postcode":"3211",
    "sg:province":"Vlaams-Brabant",
    "wof:name":"Octavie Verbiest",
    "wof:placetype":"venue"
},
  "geometry": {"coordinates":[4.8836650848,50.8762702942],"type":"Point"}
}