{
  "type": "Feature",
  "properties": {
    "addr:full":"Dijkstraat 13 Steenokkerzeel Vlaams-Brabant 1820",
    "addr:housenumber":"13",
    "addr:postcode":"1820",
    "addr:street":"Dijkstraat",
    "iso:country":"BE",
    "sg:address":"Dijkstraat 13",
    "sg:city":"Steenokkerzeel",
    "sg:orig_category":"Dakwerken",
    "sg:phone":"+32 2 757 65 58",
    "sg:postcode":"1820",
    "sg:province":"Vlaams-Brabant",
    "wof:name":"Marc De Bont",
    "wof:placetype":"venue"
},
  "geometry": {"coordinates":[4.5158572197,50.9059257507],"type":"Point"}
}