{
  "type": "Feature",
  "properties": {
    "iso:country":"BE",
    "sg:address":"Rue Gabrielle Petit 4 Box 11",
    "sg:city":"Bruxelles (molenbeek-saint-jean)",
    "sg:classifiers":[
        {
            "category":"Professional",
            "subcategory":"Advertising",
            "type":"Services"
        }
    ],
    "sg:phone":"+32 2 519 22 11",
    "sg:postcode":"1080",
    "sg:province":"Bruxelles-Capitale",
    "sg:tags":[
        "telemarketing"
    ],
    "wof:name":"B-connected Nv",
    "wof:placetype":"venue"
},
  "geometry": {"coordinates":[4.3405170441,50.8681182861],"type":"Point"}
}