{
  "type": "Feature",
  "properties": {
    "iso:country":"BE",
    "sg:address":"Lierbaan 295",
    "sg:city":"Putte",
    "sg:orig_category":"P\u00e9pini\u00e9ristes",
    "sg:phone":"+32 15 75 33 41",
    "sg:postcode":"2580",
    "sg:province":"Antwerpen",
    "wof:name":"Hedwig Goossens",
    "wof:placetype":"venue"
},
  "geometry": {"coordinates":[4.6159467697,51.0817108154],"type":"Point"}
}