{
  "type": "Feature",
  "properties": {
    "addr:full":"Jozef Hermanslei 78 Mortsel Antwerpen 2640",
    "addr:housenumber":"78",
    "addr:postcode":"2640",
    "addr:street":"Jozef Hermanslei",
    "iso:country":"BE",
    "sg:address":"Jozef Hermanslei 78",
    "sg:city":"Mortsel",
    "sg:classifiers":[
        {
            "category":"Structure",
            "subcategory":"Warehouse",
            "type":"Public Place"
        }
    ],
    "sg:phone":"+32 3 449 68 01",
    "sg:postcode":"2640",
    "sg:province":"Antwerpen",
    "sg:tags":[
        "system",
        "high-bay"
    ],
    "wof:name":"Elvedi A.g. D.b. Racks",
    "wof:placetype":"venue"
},
  "geometry": {"coordinates":[4.4351201057,51.1744422913],"type":"Point"}
}