{
  "type": "Feature",
  "properties": {
    "addr:full":"Voskenslaan 372 Gent Oost-Vlaanderen 9000",
    "addr:housenumber":"372",
    "addr:postcode":"9000",
    "addr:street":"Voskenslaan;Oost-Vlaanderen",
    "iso:country":"BE",
    "sg:address":"Voskenslaan 372",
    "sg:city":"Gent",
    "sg:classifiers":[
        {
            "category":"Autos & Motor Vehicles",
            "subcategory":"Automobile Sales",
            "type":"Retail Goods"
        }
    ],
    "sg:phone":"+32 9 245 08 06",
    "sg:postcode":"9000",
    "sg:province":"Oost-Vlaanderen",
    "sg:tags":[
        "car",
        "used",
        "-"
    ],
    "wof:name":"Vander Haeghen M (garage)",
    "wof:placetype":"venue"
},
  "geometry": {"coordinates":[3.7064290047,51.0285186768],"type":"Point"}
}