{
  "type": "Feature",
  "properties": {
    "iso:country":"BE",
    "sg:address":"Schubbeekstraat 3",
    "sg:city":"Holsbeek",
    "sg:orig_category":"Eleveurs de bovins",
    "sg:phone":"+32 16 62 28 05",
    "sg:postcode":"3220",
    "sg:province":"Vlaams-Brabant",
    "wof:name":"Jean Tollet",
    "wof:placetype":"venue"
},
  "geometry": {"coordinates":[4.7575721741,50.9207267761],"type":"Point"}
}