{
  "type": "Feature",
  "properties": {
    "addr:full":"Route De La Roche 21 Tenneville Luxembourg 6970",
    "addr:housenumber":"21",
    "addr:postcode":"6970",
    "addr:street":"Route De La",
    "iso:country":"BE",
    "sg:address":"Route De La Roche 21",
    "sg:city":"Tenneville",
    "sg:classifiers":[
        {
            "category":"Health Services",
            "subcategory":"Nursing And Care Facility",
            "type":"Services"
        }
    ],
    "sg:phone":"+32 84 45 52 51",
    "sg:postcode":"6970",
    "sg:province":"Luxembourg",
    "sg:tags":[
        "home"
    ],
    "wof:name":"Borrey-picard V",
    "wof:placetype":"venue"
},
  "geometry": {"coordinates":[5.5386691093,50.0882110596],"type":"Point"}
}