{
  "type": "Feature",
  "properties": {
    "iso:country":"BE",
    "sg:address":"Helzoldstraat 6",
    "sg:city":"Houthalen-helchteren",
    "sg:orig_category":"Boucheries",
    "sg:phone":"+32 11 52 16 67",
    "sg:postcode":"3530",
    "sg:province":"Limburg",
    "wof:name":"Stephaan Kenens",
    "wof:placetype":"venue"
},
  "geometry": {"coordinates":[5.3578147888,51.0458145142],"type":"Point"}
}