{
  "type": "Feature",
  "properties": {
    "addr:full":"Rue Henri Maus 40 Li\u00e8ge 1 Li\u00e8ge 4000",
    "addr:housenumber":"40;1",
    "addr:postcode":"4000",
    "addr:street":"Rue Henri Maus",
    "iso:country":"BE",
    "sg:address":"Rue Henri Maus 40",
    "sg:city":"Li\u00e8ge 1",
    "sg:classifiers":[
        {
            "category":"Professional",
            "subcategory":"Accounting & Tax Preparation",
            "type":"Services"
        }
    ],
    "sg:phone":"+32 4 252 96 11",
    "sg:postcode":"4000",
    "sg:province":"Li\u00e8ge",
    "sg:tags":[
        "bookkeeper"
    ],
    "wof:name":"L\u00e9onard P",
    "wof:placetype":"venue"
},
  "geometry": {"coordinates":[5.5572209358,50.6335601807],"type":"Point"}
}