{
  "type": "Feature",
  "properties": {
    "iso:country":"BE",
    "sg:address":"Beverlosesteenweg 427",
    "sg:city":"Beringen (koersel)",
    "sg:classifiers":[
        {
            "category":"Bakery",
            "type":"Food & Drink"
        }
    ],
    "sg:phone":"+32 11 42 00 42",
    "sg:postcode":"3582",
    "sg:province":"Limburg",
    "sg:tags":[
        "confectioner",
        "baker"
    ],
    "wof:name":"Reynders R",
    "wof:placetype":"venue"
},
  "geometry": {"coordinates":[5.2107992172,51.0719490051],"type":"Point"}
}