{
  "type": "Feature",
  "properties": {
    "addr:full":"Rue De La Lib\u00e9ration 9 Qu\u00e9vy (qu\u00e9vy-le-grand) Hainaut 7040",
    "addr:housenumber":"9",
    "addr:postcode":"7040",
    "addr:street":"Rue De La Libe\u0301Ration;Que\u0301Vy-Le-Grand Hainaut",
    "iso:country":"BE",
    "sg:address":"Rue De La Lib\u00e9ration 9",
    "sg:city":"Qu\u00e9vy (qu\u00e9vy-le-grand)",
    "sg:classifiers":[
        {
            "category":"Insurance",
            "subcategory":"Insurance Agent",
            "type":"Services"
        }
    ],
    "sg:phone":"+32 65 56 95 26",
    "sg:postcode":"7040",
    "sg:province":"Hainaut",
    "sg:tags":[
        "broker"
    ],
    "wof:name":"Dupont G",
    "wof:placetype":"venue"
},
  "geometry": {"coordinates":[3.9525499344,50.3589439392],"type":"Point"}
}