{
  "type": "Feature",
  "properties": {
    "addr:full":"Chauss\u00e9e De Ninove 158 Bruxelles (molenbeek-saint-jean) Bruxelles-Capitale 1080",
    "addr:housenumber":"158",
    "addr:postcode":"1080",
    "addr:street":"Chausse\u0301E De Ninove",
    "iso:country":"BE",
    "sg:address":"Chauss\u00e9e De Ninove 158",
    "sg:city":"Bruxelles (molenbeek-saint-jean)",
    "sg:classifiers":[
        {
            "category":"Bakery",
            "type":"Food & Drink"
        }
    ],
    "sg:phone":"+32 2 410 65 05",
    "sg:postcode":"1080",
    "sg:province":"Bruxelles-Capitale",
    "sg:tags":[
        "confectioner",
        "baker"
    ],
    "wof:name":"La Galette Sprl",
    "wof:placetype":"venue"
},
  "geometry": {"coordinates":[4.3243570328,50.8489227295],"type":"Point"}
}