{
  "type": "Feature",
  "properties": {
    "iso:country":"BE",
    "sg:address":"Rue C\u00e9sar Depaepe 88",
    "sg:city":"Quaregnon",
    "sg:classifiers":[
        {
            "category":"Personal",
            "subcategory":"Beauty Salon",
            "type":"Services"
        }
    ],
    "sg:phone":"+32 65 78 52 56",
    "sg:postcode":"7390",
    "sg:province":"Hainaut",
    "sg:tags":[
        "lady",
        "-",
        "hairdressing"
    ],
    "wof:name":"Coiffure Micka\u00ebl",
    "wof:placetype":"venue"
},
  "geometry": {"coordinates":[3.8593580723,50.4336166382],"type":"Point"}
}