{
  "type": "Feature",
  "properties": {
    "addr:full":"Rue Du Moulin 40 Tubize Brabant Wallon 1480",
    "addr:housenumber":"40",
    "addr:postcode":"1480",
    "addr:street":"Rue Du Moulin;Wallon",
    "iso:country":"BE",
    "sg:address":"Rue Du Moulin 40",
    "sg:city":"Tubize",
    "sg:classifiers":[
        {
            "category":"Sports & Exercise",
            "subcategory":"Stables",
            "type":"Entertainment"
        }
    ],
    "sg:phone":"+32 2 355 86 34",
    "sg:postcode":"1480",
    "sg:province":"Brabant Wallon",
    "sg:tags":[
        "riding",
        "school"
    ],
    "wof:name":"Relais Equestre De Ripain Asbl",
    "wof:placetype":"venue"
},
  "geometry": {"coordinates":[4.1812062263,50.680896759],"type":"Point"}
}