{
  "type": "Feature",
  "properties": {
    "addr:full":"Kortrijkstraat 404 Wevelgem West-Vlaanderen 8560",
    "addr:housenumber":"404",
    "addr:postcode":"8560",
    "addr:street":"Kortrijkstraat",
    "iso:country":"BE",
    "sg:address":"Kortrijkstraat 404",
    "sg:city":"Wevelgem",
    "sg:classifiers":[
        {
            "category":"Restaurant",
            "type":"Food & Drink"
        }
    ],
    "sg:phone":"+32 56 40 28 13",
    "sg:postcode":"8560",
    "sg:province":"West-Vlaanderen",
    "wof:name":"\u00b4t Vliegerke",
    "wof:placetype":"venue"
},
  "geometry": {"coordinates":[3.2138860226,50.817363739],"type":"Point"}
}