{
  "type": "Feature",
  "properties": {
    "addr:full":"Rue Edith Cavell 123 Bruxelles (uccle) Bruxelles-Capitale 1180",
    "addr:housenumber":"123",
    "addr:postcode":"1180",
    "addr:street":"Rue Edith Cavell",
    "iso:country":"BE",
    "sg:address":"Rue Edith Cavell 123",
    "sg:city":"Bruxelles (uccle)",
    "sg:classifiers":[
        {
            "category":"Retail",
            "subcategory":"Veterinary Services",
            "type":"Services"
        }
    ],
    "sg:phone":"+32 2 347 47 86",
    "sg:postcode":"1180",
    "sg:province":"Bruxelles-Capitale",
    "sg:tags":[
        "veterinarian"
    ],
    "wof:name":"Beck Y",
    "wof:placetype":"venue"
},
  "geometry": {"coordinates":[4.357363224,50.8087692261],"type":"Point"}
}