{
  "type": "Feature",
  "properties": {
    "iso:country":"BE",
    "sg:address":"Rue De Sugy 10",
    "sg:city":"Vaux-sur-s\u00fbre (sibret)",
    "sg:classifiers":[
        {
            "category":"Communications",
            "subcategory":"Radio Station",
            "type":"Services"
        }
    ],
    "sg:phone":"+32 61 26 69 53",
    "sg:postcode":"6640",
    "sg:province":"Luxembourg",
    "sg:tags":[
        "local"
    ],
    "wof:name":"Studio 's' Asbl",
    "wof:placetype":"venue"
},
  "geometry": {"coordinates":[5.5671000481,49.91065979],"type":"Point"}
}