{
  "type": "Feature",
  "properties": {
    "addr:full":"Spijkersdreef 2 Melle Oost-Vlaanderen 9090",
    "addr:housenumber":"2",
    "addr:postcode":"9090",
    "addr:street":"Spijkersdreef",
    "iso:country":"BE",
    "sg:address":"Spijkersdreef 2",
    "sg:city":"Melle",
    "sg:orig_category":"Diverse meubelen Fab Meubelzaken, woning- and keukeninrichting",
    "sg:phone":"+32 9 230 94 39",
    "sg:postcode":"9090",
    "sg:province":"Oost-Vlaanderen",
    "wof:name":"Alex Diffusion",
    "wof:placetype":"venue"
},
  "geometry": {"coordinates":[3.7933299541,51.0104598999],"type":"Point"}
}