{
  "type": "Feature",
  "properties": {
    "iso:country":"BE",
    "sg:address":"Duitslandstraat 11",
    "sg:city":"Temse",
    "sg:classifiers":[
        {
            "category":"Shopping",
            "type":"Retail Goods"
        }
    ],
    "sg:phone":"+32 3 771 91 91",
    "sg:postcode":"9140",
    "sg:province":"Oost-Vlaanderen",
    "sg:tags":[
        "product",
        "cleaning",
        "maintenance"
    ],
    "wof:name":"M.i.c.",
    "wof:placetype":"venue"
},
  "geometry": {"coordinates":[4.1994462013,51.1432304382],"type":"Point"}
}