{
  "type": "Feature",
  "properties": {
    "addr:full":"Walemstraat 143 Sint-katelijne-waver Antwerpen 2860",
    "addr:housenumber":"143",
    "addr:postcode":"2860",
    "addr:street":"Walemstraat",
    "iso:country":"BE",
    "sg:address":"Walemstraat 143",
    "sg:city":"Sint-katelijne-waver",
    "sg:orig_category":"Groententeelt",
    "sg:phone":"+32 15 21 14 05",
    "sg:postcode":"2860",
    "sg:province":"Antwerpen",
    "wof:name":"Bert De Keyser",
    "wof:placetype":"venue"
},
  "geometry": {"coordinates":[4.4687857628,51.0558052063],"type":"Point"}
}