{
  "type": "Feature",
  "properties": {
    "iso:country":"BE",
    "sg:address":"Cav\u00c9e 52",
    "sg:city":"Erquelinnes",
    "sg:orig_category":"Eleveurs de bovins",
    "sg:phone":"+32 71 55 50 67",
    "sg:postcode":"6560",
    "sg:province":"Hainaut",
    "wof:name":"Amatus Goessens",
    "wof:placetype":"venue"
},
  "geometry": {"coordinates":[4.1623001099,50.3083190918],"type":"Point"}
}