{
  "type": "Feature",
  "properties": {
    "addr:full":"Passage De La Bourse 7 Charleroi Hainaut 6000",
    "addr:housenumber":"7",
    "addr:postcode":"6000",
    "addr:street":"Passage De La Bourse;Hainaut",
    "iso:country":"BE",
    "sg:address":"Passage De La Bourse 7",
    "sg:city":"Charleroi",
    "sg:classifiers":[
        {
            "category":"Shopping",
            "subcategory":"Optician",
            "type":"Retail Goods"
        }
    ],
    "sg:phone":"+32 71 31 48 54",
    "sg:postcode":"6000",
    "sg:province":"Hainaut",
    "sg:tags":[
        "-"
    ],
    "wof:name":"Scory",
    "wof:placetype":"venue"
},
  "geometry": {"coordinates":[4.4402899742,50.4071502686],"type":"Point"}
}