{
  "type": "Feature",
  "properties": {
    "iso:country":"BE",
    "sg:address":"Rue Du Pont 53",
    "sg:city":"Tintigny",
    "sg:classifiers":[
        {
            "category":"Government",
            "subcategory":"Department Of Motor Vehicles",
            "type":"Public Place"
        }
    ],
    "sg:phone":"+32 63 44 41 77",
    "sg:postcode":"6730",
    "sg:province":"Luxembourg",
    "sg:tags":[
        "planing",
        "wood",
        "sawing"
    ],
    "wof:name":"Henry & Fils Sprl",
    "wof:placetype":"venue"
},
  "geometry": {"coordinates":[5.4938402176,49.6918716431],"type":"Point"}
}