{
  "type": "Feature",
  "properties": {
    "iso:country":"BE",
    "sg:address":"Guido Gezellestraat 109",
    "sg:city":"Beersel",
    "sg:orig_category":"Huisvuilophaling and -verwerking",
    "sg:phone":"+32 2 361 78 42",
    "sg:postcode":"1654",
    "sg:province":"Vlaams-Brabant",
    "wof:name":"Vierendeels R.",
    "wof:placetype":"venue"
},
  "geometry": {"coordinates":[4.2692408562,50.7535095215],"type":"Point"}
}