{
  "type": "Feature",
  "properties": {
    "iso:country":"BE",
    "sg:address":"Profeetstraat 60ba",
    "sg:city":"Ranst",
    "sg:classifiers":[
        {
            "category":"Restaurant",
            "type":"Food & Drink"
        }
    ],
    "sg:phone":"+32 3 485 83 03",
    "sg:postcode":"2520",
    "sg:province":"Antwerpen",
    "sg:tags":[
        "caf\u00e9s"
    ],
    "wof:name":"Taverne Milleghemveld",
    "wof:placetype":"venue"
},
  "geometry": {"coordinates":[4.549975872,51.1875686646],"type":"Point"}
}