{
  "type": "Feature",
  "properties": {
    "addr:full":"Kammenstraat 41 Antwerpen Antwerpen 2000",
    "addr:housenumber":"41",
    "addr:postcode":"2000",
    "addr:street":"Kammenstraat",
    "iso:country":"BE",
    "sg:address":"Kammenstraat 41",
    "sg:city":"Antwerpen",
    "sg:orig_category":"Librairies",
    "sg:phone":"+32 3 234 39 35",
    "sg:postcode":"2000",
    "sg:province":"Antwerpen",
    "wof:name":"Bries",
    "wof:placetype":"venue"
},
  "geometry": {"coordinates":[4.4008412361,51.2173118591],"type":"Point"}
}