{
  "type": "Feature",
  "properties": {
    "addr:full":"Rue Fontaine-michaux 24 Nivelles Brabant Wallon 1400",
    "addr:housenumber":"24",
    "addr:postcode":"1400",
    "addr:street":"Rue Fontaine-Michaux",
    "iso:country":"BE",
    "sg:address":"Rue Fontaine-michaux 24",
    "sg:city":"Nivelles",
    "sg:orig_category":"Kapsalons",
    "sg:phone":"+32 67 21 93 89",
    "sg:postcode":"1400",
    "sg:province":"Brabant Wallon",
    "wof:name":"Coiffure Berjonneau",
    "wof:placetype":"venue"
},
  "geometry": {"coordinates":[4.3416881561,50.5936660767],"type":"Point"}
}