{
  "type": "Feature",
  "properties": {
    "iso:country":"BE",
    "sg:address":"Brugsesteenweg 123",
    "sg:city":"Kortrijk",
    "sg:classifiers":[
        {
            "category":"Restaurant",
            "type":"Food & Drink"
        }
    ],
    "sg:phone":"+32 56 35 17 71",
    "sg:postcode":"8500",
    "sg:province":"West-Vlaanderen",
    "wof:name":"T Hemelhof Restaurant",
    "wof:placetype":"venue"
},
  "geometry": {"coordinates":[3.2630209923,50.8389625549],"type":"Point"}
}