{
  "type": "Feature",
  "properties": {
    "addr:full":". Ichtegem (groot) West-Vlaanderen 8480",
    "addr:postcode":"8480",
    "addr:street":"Groot West-Vlaanderen",
    "iso:country":"BE",
    "sg:address":".",
    "sg:city":"Ichtegem (groot)",
    "sg:orig_category":"Apotheken",
    "sg:phone":"+32 900 10 500",
    "sg:postcode":"8480",
    "sg:province":"West-Vlaanderen",
    "wof:name":"Apothekers Van Wacht",
    "wof:placetype":"venue"
},
  "geometry": {"coordinates":[3.010445118,51.0919189453],"type":"Point"}
}