{
  "type": "Feature",
  "properties": {
    "addr:full":"Rue De La Genette 19 Beauraing Namur 5570",
    "addr:housenumber":"19",
    "addr:postcode":"5570",
    "addr:street":"Rue De La Genette",
    "iso:country":"BE",
    "sg:address":"Rue De La Genette 19",
    "sg:city":"Beauraing",
    "sg:orig_category":"Drogueries",
    "sg:phone":"+32 82 71 12 68",
    "sg:postcode":"5570",
    "sg:province":"Namur",
    "wof:name":"Droguerie De La Genette",
    "wof:placetype":"venue"
},
  "geometry": {"coordinates":[4.9583759308,50.1103134155],"type":"Point"}
}