{
  "type": "Feature",
  "properties": {
    "addr:full":"Vossenpad 6 Stabroek Antwerpen 2940",
    "addr:housenumber":"6",
    "addr:postcode":"2940",
    "addr:street":"Vossenpad",
    "iso:country":"BE",
    "sg:address":"Vossenpad 6",
    "sg:city":"Stabroek",
    "sg:orig_category":"Industri\u00eble and commerci\u00eble bouw",
    "sg:phone":"+32 3 568 70 00",
    "sg:postcode":"2940",
    "sg:province":"Antwerpen",
    "wof:name":"Bilfinger & Berger",
    "wof:placetype":"venue"
},
  "geometry": {"coordinates":[4.3716111183,51.3302116394],"type":"Point"}
}