{
  "type": "Feature",
  "properties": {
    "iso:country":"BE",
    "sg:address":"Ganzestraat 37",
    "sg:city":"Diepenbeek",
    "sg:orig_category":"Fleurs and plantes. Plantes and fleurs Gr",
    "sg:phone":"+32 11 32 43 72",
    "sg:postcode":"3590",
    "sg:province":"Limburg",
    "wof:name":"Willy Daniels",
    "wof:placetype":"venue"
},
  "geometry": {"coordinates":[5.3904771805,50.8937759399],"type":"Point"}
}