{
  "type": "Feature",
  "properties": {
    "iso:country":"BE",
    "sg:address":"Rodelijvekensstraat 4",
    "sg:city":"Gent",
    "sg:classifiers":[
        {
            "category":"Cafe",
            "type":"Food & Drink"
        }
    ],
    "sg:phone":"+32 9 233 68 46",
    "sg:postcode":"9000",
    "sg:province":"Oost-Vlaanderen",
    "sg:tags":[
        "snack-bars"
    ],
    "wof:name":"Nostalgie",
    "wof:placetype":"venue"
},
  "geometry": {"coordinates":[3.7248120308,51.0603904724],"type":"Point"}
}