{
  "type": "Feature",
  "properties": {
    "iso:country":"BE",
    "sg:address":"Koning Albertlaan 42",
    "sg:city":"Lochristi",
    "sg:classifiers":[
        {
            "category":"Professional",
            "subcategory":"Art Services",
            "type":"Services"
        }
    ],
    "sg:phone":"+32 9 356 91 06",
    "sg:postcode":"9080",
    "sg:province":"Oost-Vlaanderen",
    "sg:tags":[
        "photographer"
    ],
    "wof:name":"Guarda La Fotografia-filip Naudts",
    "wof:placetype":"venue"
},
  "geometry": {"coordinates":[3.8305981159,51.0987014771],"type":"Point"}
}