{
  "type": "Feature",
  "properties": {
    "iso:country":"BE",
    "sg:address":"President Kennedypark 11bc",
    "sg:city":"Kortrijk",
    "sg:orig_category":"Projectontwikkelaars Woningbouw",
    "sg:phone":"+32 56 22 01 07",
    "sg:postcode":"8500",
    "sg:province":"West-Vlaanderen",
    "wof:name":"Korprobel",
    "wof:placetype":"venue"
},
  "geometry": {"coordinates":[3.274559021,50.8030395508],"type":"Point"}
}