{
  "type": "Feature",
  "properties": {
    "addr:full":"Steenweg Deinze 84a Nazareth Oost-Vlaanderen 9810",
    "addr:housenumber":"84a",
    "addr:postcode":"9810",
    "addr:street":"Steenweg Deinze",
    "iso:country":"BE",
    "sg:address":"Steenweg Deinze 84a",
    "sg:city":"Nazareth",
    "sg:classifiers":[
        {
            "category":"Retail",
            "subcategory":"Auto Repair",
            "type":"Services"
        }
    ],
    "sg:phone":"+32 9 386 76 27",
    "sg:postcode":"9810",
    "sg:province":"Oost-Vlaanderen",
    "sg:tags":[
        "garage"
    ],
    "wof:name":"De Sloovere L",
    "wof:placetype":"venue"
},
  "geometry": {"coordinates":[3.5810360909,50.9474639893],"type":"Point"}
}