{
  "type": "Feature",
  "properties": {
    "iso:country":"BE",
    "sg:address":"Amerikalei 196 Box 4",
    "sg:city":"Antwerpen",
    "sg:classifiers":[
        {
            "category":"Professional",
            "subcategory":"Lawyer & Legal Services",
            "type":"Services"
        }
    ],
    "sg:phone":"+32 3 213 32 20",
    "sg:postcode":"2000",
    "sg:province":"Antwerpen",
    "wof:name":"Van Raemdonck Alfred",
    "wof:placetype":"venue"
},
  "geometry": {"coordinates":[4.3912081718,51.2055587769],"type":"Point"}
}