{
  "type": "Feature",
  "properties": {
    "addr:full":"Antwerpsesteenweg 224 Antwerpen Antwerpen 2660",
    "addr:housenumber":"224",
    "addr:postcode":"2660",
    "addr:street":"Antwerpsesteenweg",
    "iso:country":"BE",
    "sg:address":"Antwerpsesteenweg 224",
    "sg:city":"Antwerpen",
    "sg:orig_category":"Herstellingen and onderhoud van auto's",
    "sg:phone":"+32 3 827 51 55",
    "sg:postcode":"2660",
    "sg:province":"Antwerpen",
    "wof:name":"Garage Ghijsels",
    "wof:placetype":"venue"
},
  "geometry": {"coordinates":[4.320166111,51.3489608765],"type":"Point"}
}