{
  "type": "Feature",
  "properties": {
    "iso:country":"BE",
    "sg:address":"Stedemolenstraat 39",
    "sg:city":"Tielt",
    "sg:classifiers":[
        {
            "category":"Shopping",
            "type":"Retail Goods"
        }
    ],
    "sg:phone":"+32 51 40 63 62",
    "sg:postcode":"8700",
    "sg:province":"West-Vlaanderen",
    "sg:tags":[
        "product",
        "cleaning",
        "maintenance"
    ],
    "wof:name":"Wildy",
    "wof:placetype":"venue"
},
  "geometry": {"coordinates":[3.3191030025,50.9962692261],"type":"Point"}
}