{
  "type": "Feature",
  "properties": {
    "addr:full":"Jeneverplein 1 Box 1 Hasselt Limburg 3500",
    "addr:housenumber":"1;1",
    "addr:postcode":"3500",
    "addr:street":"Jeneverplein;Box",
    "iso:country":"BE",
    "sg:address":"Jeneverplein 1 Box 1",
    "sg:city":"Hasselt",
    "sg:classifiers":[
        {
            "category":"Utilities",
            "subcategory":"Mobile Phone",
            "type":"Services"
        }
    ],
    "sg:phone":"+32 11 23 22 61",
    "sg:postcode":"3500",
    "sg:province":"Limburg",
    "sg:tags":[
        "-",
        "gsm"
    ],
    "wof:name":"Bkm Nv",
    "wof:placetype":"venue"
},
  "geometry": {"coordinates":[5.3414030075,50.933139801],"type":"Point"}
}