{
  "type": "Feature",
  "properties": {
    "addr:full":"Luikersteenweg 191 Hasselt Limburg 3500",
    "addr:housenumber":"191",
    "addr:postcode":"3500",
    "addr:street":"Luikersteenweg",
    "iso:country":"BE",
    "sg:address":"Luikersteenweg 191",
    "sg:city":"Hasselt",
    "sg:classifiers":[
        {
            "category":"Real Estate",
            "subcategory":"Architect",
            "type":"Services"
        }
    ],
    "sg:phone":"+32 11 27 22 02",
    "sg:postcode":"3500",
    "sg:province":"Limburg",
    "wof:name":"Baert E",
    "wof:placetype":"venue"
},
  "geometry": {"coordinates":[5.34608078,50.9173316956],"type":"Point"}
}