{
  "type": "Feature",
  "properties": {
    "iso:country":"BE",
    "sg:address":"Dorpsplaats 29-1",
    "sg:city":"Malle (oostmalle)",
    "sg:classifiers":[
        {
            "category":"Health Services",
            "subcategory":"Dentist",
            "type":"Services"
        }
    ],
    "sg:phone":"+32 3 312 48 54",
    "sg:postcode":"2390",
    "sg:province":"Antwerpen",
    "wof:name":"Rosiers J",
    "wof:placetype":"venue"
},
  "geometry": {"coordinates":[4.733602047,51.3023529053],"type":"Point"}
}