{
  "type": "Feature",
  "properties": {
    "addr:full":"Vijfweg 2 Oudenaarde Oost-Vlaanderen 9700",
    "addr:housenumber":"2",
    "addr:postcode":"9700",
    "addr:street":"Vijfweg",
    "iso:country":"BE",
    "sg:address":"Vijfweg 2",
    "sg:city":"Oudenaarde",
    "sg:classifiers":[
        {
            "category":"Professional",
            "type":"Services"
        }
    ],
    "sg:phone":"+32 2 582 94 93",
    "sg:postcode":"9700",
    "sg:province":"Oost-Vlaanderen",
    "sg:tags":[
        "transport",
        "road"
    ],
    "wof:name":"Distribution Book Paper Nv",
    "wof:placetype":"venue"
},
  "geometry": {"coordinates":[3.6633000374,50.8362312317],"type":"Point"}
}