{
  "type": "Feature",
  "properties": {
    "addr:full":"Leopoldlaan 48a Ninove Oost-Vlaanderen 9400",
    "addr:housenumber":"48a",
    "addr:postcode":"9400",
    "addr:street":"Leopoldlaan",
    "iso:country":"BE",
    "sg:address":"Leopoldlaan 48a",
    "sg:city":"Ninove",
    "sg:classifiers":[
        {
            "category":"Health Services",
            "subcategory":"Health Practitioner",
            "type":"Services"
        }
    ],
    "sg:phone":"+32 54 33 36 68",
    "sg:postcode":"9400",
    "sg:province":"Oost-Vlaanderen",
    "sg:tags":[
        "physiotherapist"
    ],
    "wof:name":"Smesman Jeroen - Janssens Liesbeth",
    "wof:placetype":"venue"
},
  "geometry": {"coordinates":[4.0220332146,50.8264465332],"type":"Point"}
}