{
  "type": "Feature",
  "properties": {
    "addr:full":"Boulevard De L'ourthe 100 Chaudfontaine (embourg) Li\u00e8ge 4053",
    "addr:housenumber":"100",
    "addr:postcode":"4053",
    "addr:street":"Boulevard De L'Ourthe",
    "iso:country":"BE",
    "sg:address":"Boulevard De L'ourthe 100",
    "sg:city":"Chaudfontaine (embourg)",
    "sg:classifiers":[
        {
            "category":"Professional",
            "subcategory":"Computer Services",
            "type":"Services"
        }
    ],
    "sg:phone":"+32 4 367 64 34",
    "sg:postcode":"4053",
    "sg:province":"Li\u00e8ge",
    "sg:tags":[
        "-",
        "processing",
        "data"
    ],
    "wof:name":"Celem Sa",
    "wof:placetype":"venue"
},
  "geometry": {"coordinates":[5.6108150482,50.6033096313],"type":"Point"}
}