{
  "type": "Feature",
  "properties": {
    "addr:full":"Rue De L'abbaye 124 Ath Hainaut 7800",
    "addr:housenumber":"124",
    "addr:postcode":"7800",
    "addr:street":"Rue De L'Abbaye",
    "iso:country":"BE",
    "sg:address":"Rue De L'abbaye 124",
    "sg:city":"Ath",
    "sg:orig_category":"M\u00e9decines alternatives. M\u00e9decins and sp\u00e9cialistes",
    "sg:phone":"+32 68 28 59 28",
    "sg:postcode":"7800",
    "sg:province":"Hainaut",
    "wof:name":"Delattre Mich\u00c8le",
    "wof:placetype":"venue"
},
  "geometry": {"coordinates":[3.7845621109,50.6279716492],"type":"Point"}
}