{
  "type": "Feature",
  "properties": {
    "iso:country":"BE",
    "sg:address":"Rue Bosquet 2a",
    "sg:city":"Bruxelles",
    "sg:classifiers":[
        {
            "category":"Banks & Credit Unions",
            "subcategory":"Investment Brokerage",
            "type":"Services"
        }
    ],
    "sg:phone":"+32 2 538 72 80",
    "sg:postcode":"1060",
    "sg:province":"Bruxelles-Capitale",
    "sg:tags":[
        "training",
        "application",
        "processing",
        "consulting",
        "course",
        "data"
    ],
    "wof:name":"Ariane Ii S.a.",
    "wof:placetype":"venue"
},
  "geometry": {"coordinates":[4.3567008972,50.8328399658],"type":"Point"}
}