{
  "type": "Feature",
  "properties": {
    "addr:full":"Broeder Mareslaan 23 Zottegem Oost-Vlaanderen 9620",
    "addr:housenumber":"23",
    "addr:postcode":"9620",
    "addr:street":"Mareslaan",
    "iso:country":"BE",
    "sg:address":"Broeder Mareslaan 23",
    "sg:city":"Zottegem",
    "sg:classifiers":[
        {
            "category":"Health Services",
            "subcategory":"Doctor",
            "type":"Services"
        }
    ],
    "sg:phone":"+32 9 361 09 50",
    "sg:postcode":"9620",
    "sg:province":"Oost-Vlaanderen",
    "sg:tags":[
        "medicinephysicians",
        "surgeon"
    ],
    "wof:name":"De Both D",
    "wof:placetype":"venue"
},
  "geometry": {"coordinates":[3.815294981,50.8676452637],"type":"Point"}
}