{
  "type": "Feature",
  "properties": {
    "addr:full":"Zavelstraat 75 Kortenberg (erps-kwerps) Vlaams-Brabant 3071",
    "addr:housenumber":"75",
    "addr:postcode":"3071",
    "addr:street":"Zavelstraat",
    "iso:country":"BE",
    "sg:address":"Zavelstraat 75",
    "sg:city":"Kortenberg (erps-kwerps)",
    "sg:classifiers":[
        {
            "category":"Health Services",
            "subcategory":"Doctor",
            "type":"Services"
        }
    ],
    "sg:phone":"+32 2 759 73 78",
    "sg:postcode":"3071",
    "sg:province":"Vlaams-Brabant",
    "sg:tags":[
        "medicinephysicians",
        "surgeon"
    ],
    "wof:name":"Cornelis G",
    "wof:placetype":"venue"
},
  "geometry": {"coordinates":[4.5625691414,50.8990821838],"type":"Point"}
}