{
  "type": "Feature",
  "properties": {
    "iso:country":"BE",
    "sg:address":"Rue Ariste-caussin 77",
    "sg:city":"Dinant",
    "sg:orig_category":"Kapsalons",
    "sg:phone":"+32 82 22 27 80",
    "sg:postcode":"5500",
    "sg:province":"Namur",
    "wof:name":"Coiffure Mireille",
    "wof:placetype":"venue"
},
  "geometry": {"coordinates":[4.9156780243,50.2390785217],"type":"Point"}
}