{
  "type": "Feature",
  "properties": {
    "addr:full":"Rue D'enhaive 188 Namur (jambes) Namur 5100",
    "addr:housenumber":"188",
    "addr:postcode":"5100",
    "addr:street":"Rue D'Enhaive",
    "iso:country":"BE",
    "sg:address":"Rue D'enhaive 188",
    "sg:city":"Namur (jambes)",
    "sg:orig_category":"Non-Classified Establishments",
    "sg:phone":"+32 81 30 40 50",
    "sg:postcode":"5100",
    "sg:province":"Namur",
    "wof:name":"Givord Sa",
    "wof:placetype":"venue"
},
  "geometry": {"coordinates":[4.8799672127,50.4613227844],"type":"Point"}
}