{
  "type": "Feature",
  "properties": {
    "addr:full":"Rue Saint-s\u00c9verin 35 Li\u00c8ge Li\u00e8ge 4000",
    "addr:housenumber":"35",
    "addr:postcode":"4000",
    "addr:street":"Rue Saint-Se\u0301Verin",
    "iso:country":"BE",
    "sg:address":"Rue Saint-s\u00c9verin 35",
    "sg:city":"Li\u00c8ge",
    "sg:orig_category":"Kapsalons",
    "sg:phone":"+32 4 223 57 69",
    "sg:postcode":"4000",
    "sg:province":"Li\u00e8ge",
    "wof:name":"Jean-claude Gillis",
    "wof:placetype":"venue"
},
  "geometry": {"coordinates":[5.5673980713,50.6452674866],"type":"Point"}
}