{
  "type": "Feature",
  "properties": {
    "addr:full":"Rue De Cuesmes 210 Mons Hainaut 7012",
    "addr:housenumber":"210",
    "addr:postcode":"7012",
    "addr:street":"Rue De Cuesmes;Hainaut",
    "iso:country":"BE",
    "sg:address":"Rue De Cuesmes 210",
    "sg:city":"Mons",
    "sg:orig_category":"Sportclubs",
    "sg:phone":"+32 65 88 58 08",
    "sg:postcode":"7012",
    "sg:province":"Hainaut",
    "wof:name":"Borina",
    "wof:placetype":"venue"
},
  "geometry": {"coordinates":[3.9390869141,50.4481620789],"type":"Point"}
}