{
  "type": "Feature",
  "properties": {
    "addr:full":"Dokter J. Geensstraat 26 Tienen Vlaams-Brabant 3300",
    "addr:housenumber":"26",
    "addr:postcode":"3300",
    "addr:street":"Dokter J. Geensstraat",
    "iso:country":"BE",
    "sg:address":"Dokter J. Geensstraat 26",
    "sg:city":"Tienen",
    "sg:classifiers":[
        {
            "category":"Professional",
            "subcategory":"Engineering",
            "type":"Services"
        }
    ],
    "sg:phone":"+32 16 81 79 30",
    "sg:postcode":"3300",
    "sg:province":"Vlaams-Brabant",
    "sg:tags":[
        "civil",
        "offices-"
    ],
    "wof:name":"Caubergs I.b.c.",
    "wof:placetype":"venue"
},
  "geometry": {"coordinates":[4.9343018532,50.8074684143],"type":"Point"}
}