{
  "type": "Feature",
  "properties": {
    "iso:country":"BE",
    "sg:address":"Hoogstraat 15",
    "sg:city":"Denderleeuw",
    "sg:orig_category":"Slagers",
    "sg:phone":"+32 53 66 72 17",
    "sg:postcode":"9472",
    "sg:province":"Oost-Vlaanderen",
    "wof:name":"Frans De Deyn",
    "wof:placetype":"venue"
},
  "geometry": {"coordinates":[4.0537800789,50.8752937317],"type":"Point"}
}