{
  "type": "Feature",
  "properties": {
    "addr:full":"Avenue Bouvier 41 Virton Luxembourg 6760",
    "addr:housenumber":"41",
    "addr:postcode":"6760",
    "addr:street":"Avenue Bouvier",
    "iso:country":"BE",
    "sg:address":"Avenue Bouvier 41",
    "sg:city":"Virton",
    "sg:orig_category":"Advocaten and juridische adviseurs",
    "sg:phone":"+32 63 57 88 60",
    "sg:postcode":"6760",
    "sg:province":"Luxembourg",
    "wof:name":"Pascal Bouvy",
    "wof:placetype":"venue"
},
  "geometry": {"coordinates":[5.5270390511,49.5656166077],"type":"Point"}
}