{
  "type": "Feature",
  "properties": {
    "addr:full":"Rue De Sedan 7 Vresse-sur-semois Namur 5550",
    "addr:housenumber":"7",
    "addr:postcode":"vresse-sur-semois;5550",
    "addr:street":"Rue De Sedan",
    "iso:country":"BE",
    "sg:address":"Rue De Sedan 7",
    "sg:city":"Vresse-sur-semois",
    "sg:orig_category":"Entretien and r\u00e9parations de voitures",
    "sg:phone":"+32 61 50 08 69",
    "sg:postcode":"5550",
    "sg:province":"Namur",
    "wof:name":"Carrosserie Poncelet",
    "wof:placetype":"venue"
},
  "geometry": {"coordinates":[4.9682350159,49.801448822],"type":"Point"}
}