{
  "type": "Feature",
  "properties": {
    "iso:country":"BE",
    "sg:address":"Serskampsteenweg 293",
    "sg:city":"Wetteren",
    "sg:orig_category":"P\u00e9pini\u00e9ristes. Producteurs de fruits",
    "sg:phone":"+32 9 369 46 60",
    "sg:postcode":"9230",
    "sg:province":"Oost-Vlaanderen",
    "wof:name":"Gerard Bracke",
    "wof:placetype":"venue"
},
  "geometry": {"coordinates":[3.9050469398,50.9990882874],"type":"Point"}
}