{
  "type": "Feature",
  "properties": {
    "iso:country":"BE",
    "sg:address":"Lange Lobroekstraat 36",
    "sg:city":"Antwerpen",
    "sg:orig_category":"Non-Classified Establishments",
    "sg:phone":"+32 3 236 58 72",
    "sg:postcode":"2060",
    "sg:province":"Antwerpen",
    "wof:name":"Horecameubel 2000",
    "wof:placetype":"venue"
},
  "geometry": {"coordinates":[4.4364681244,51.2278633118],"type":"Point"}
}