{
  "type": "Feature",
  "properties": {
    "iso:country":"BE",
    "sg:address":"Peerstalvoetweg 2",
    "sg:city":"Wingene",
    "sg:classifiers":[
        {
            "category":"Shopping",
            "subcategory":"Party Supplies",
            "type":"Retail Goods"
        }
    ],
    "sg:phone":"+32 51 65 63 42",
    "sg:postcode":"8750",
    "sg:province":"West-Vlaanderen",
    "sg:tags":[
        "rental",
        "-"
    ],
    "wof:name":"Warnez",
    "wof:placetype":"venue"
},
  "geometry": {"coordinates":[3.2804379463,51.0626602173],"type":"Point"}
}