{
  "type": "Feature",
  "properties": {
    "iso:country":"BE",
    "sg:address":"Moorputstraat 22",
    "sg:city":"Begijnendijk",
    "sg:orig_category":"Transports routiers de marchandises",
    "sg:phone":"+32 16 56 99 74",
    "sg:postcode":"3130",
    "sg:province":"Vlaams-Brabant",
    "wof:name":"Varolem",
    "wof:placetype":"venue"
},
  "geometry": {"coordinates":[4.7977161407,51.0238456726],"type":"Point"}
}