{
  "type": "Feature",
  "properties": {
    "addr:full":"Stationsstraat 73 Destelbergen Oost-Vlaanderen 9070",
    "addr:housenumber":"73",
    "addr:postcode":"9070",
    "addr:street":"Stationsstraat",
    "iso:country":"BE",
    "sg:address":"Stationsstraat 73",
    "sg:city":"Destelbergen",
    "sg:orig_category":"M\u00e9decins and sp\u00e9cialistes",
    "sg:phone":"+32 9 238 13 82",
    "sg:postcode":"9070",
    "sg:province":"Oost-Vlaanderen",
    "wof:name":"Ignace Hanoulle",
    "wof:placetype":"venue"
},
  "geometry": {"coordinates":[3.7983779907,51.0673217773],"type":"Point"}
}