{
  "type": "Feature",
  "properties": {
    "addr:full":"Rue Du Louvy 90 Charleroi Hainaut 6060",
    "addr:housenumber":"90",
    "addr:postcode":"6060",
    "addr:street":"Rue Du Louvy;Hainaut",
    "iso:country":"BE",
    "sg:address":"Rue Du Louvy 90",
    "sg:city":"Charleroi",
    "sg:classifiers":[
        {
            "category":"Cafe",
            "type":"Food & Drink"
        }
    ],
    "sg:phone":"+32 71 41 21 53",
    "sg:postcode":"6060",
    "sg:province":"Hainaut",
    "sg:tags":[
        "caf\u00e9s"
    ],
    "wof:name":"Theodoros Papas",
    "wof:placetype":"venue"
},
  "geometry": {"coordinates":[4.4880981445,50.4251937866],"type":"Point"}
}