{
  "type": "Feature",
  "properties": {
    "iso:country":"BE",
    "sg:address":"Chauss\u00c9e De Dinant 1086",
    "sg:city":"Namur",
    "sg:orig_category":"Herstellingen and onderhoud aan huis voor voertuigen Herstellingen and onderhoud van auto's Metaalaf",
    "sg:phone":"+32 81 46 08 41",
    "sg:postcode":"5100",
    "sg:province":"Namur",
    "wof:name":"Auto-wepion",
    "wof:placetype":"venue"
},
  "geometry": {"coordinates":[4.8792109489,50.4160690308],"type":"Point"}
}