{
  "type": "Feature",
  "properties": {
    "iso:country":"BE",
    "sg:address":"Avenue Des Hortensias 31",
    "sg:city":"Kraainem",
    "sg:classifiers":[
        {
            "category":"Real Estate",
            "subcategory":"Real Estate Services",
            "type":"Services"
        }
    ],
    "sg:phone":"+32 2 731 36 43",
    "sg:postcode":"1950",
    "sg:province":"Vlaams-Brabant",
    "wof:name":"Arnould Management",
    "wof:placetype":"venue"
},
  "geometry": {"coordinates":[4.4780077934,50.835319519],"type":"Point"}
}