{
  "type": "Feature",
  "properties": {
    "addr:full":"Aarschotsesteenweg 80-1 Leuven (wilsele) Vlaams-Brabant 3012",
    "addr:housenumber":"80-1",
    "addr:postcode":"3012",
    "addr:street":"Aarschotsesteenweg",
    "iso:country":"BE",
    "sg:address":"Aarschotsesteenweg 80-1",
    "sg:city":"Leuven (wilsele)",
    "sg:classifiers":[
        {
            "category":"Professional",
            "subcategory":"Engineering",
            "type":"Services"
        }
    ],
    "sg:phone":"+32 16 24 02 11",
    "sg:postcode":"3012",
    "sg:province":"Vlaams-Brabant",
    "sg:tags":[
        "industrial",
        "-",
        "automation"
    ],
    "wof:name":"Ensysta Nv",
    "wof:placetype":"venue"
},
  "geometry": {"coordinates":[4.7072200775,50.8955497742],"type":"Point"}
}