{
  "type": "Feature",
  "properties": {
    "addr:full":"Avenue Jules Destree 58 Verviers Li\u00e8ge 4801",
    "addr:housenumber":"58",
    "addr:postcode":"4801",
    "addr:street":"Avenue Jules Destree",
    "iso:country":"BE",
    "sg:address":"Avenue Jules Destree 58",
    "sg:city":"Verviers",
    "sg:orig_category":"Gespecialiseerde residenti\u00eble bouw Plaatsen van vloer- and muurbekleding",
    "sg:phone":"+32 87 22 18 07",
    "sg:postcode":"4801",
    "sg:province":"Li\u00e8ge",
    "wof:name":"Leonardi",
    "wof:placetype":"venue"
},
  "geometry": {"coordinates":[5.8930549622,50.5922393799],"type":"Point"}
}