{
  "type": "Feature",
  "properties": {
    "iso:country":"BE",
    "sg:address":"Rue D'h\u00e9denge 22",
    "sg:city":"Ramillies (mont-saint-andr\u00e9)",
    "sg:classifiers":[
        {
            "category":"Farming",
            "subcategory":"Crops",
            "type":"Manufacturing & Wholesale Goods"
        }
    ],
    "sg:phone":"+32 81 87 81 52",
    "sg:postcode":"1367",
    "sg:province":"Brabant Wallon",
    "sg:tags":[
        "vegetable",
        "fruit",
        "-",
        "grower"
    ],
    "wof:name":"Vandenberghe U",
    "wof:placetype":"venue"
},
  "geometry": {"coordinates":[4.9063911438,50.674030304],"type":"Point"}
}