{
  "type": "Feature",
  "properties": {
    "addr:full":"Rue A. Pahaux 46 Perwez Brabant Wallon 1360",
    "addr:housenumber":"46",
    "addr:postcode":"1360",
    "addr:street":"Rue A. Pahaux",
    "iso:country":"BE",
    "sg:address":"Rue A. Pahaux 46",
    "sg:city":"Perwez",
    "sg:classifiers":[
        {
            "category":"Health Services",
            "subcategory":"Health Practitioner",
            "type":"Services"
        }
    ],
    "sg:phone":"+32 81 65 67 55",
    "sg:postcode":"1360",
    "sg:province":"Brabant Wallon",
    "sg:tags":[
        "physiotherapist"
    ],
    "wof:name":"Hemptinne B\u00e9atrice",
    "wof:placetype":"venue"
},
  "geometry": {"coordinates":[4.8154559135,50.6260948181],"type":"Point"}
}