{
  "type": "Feature",
  "properties": {
    "iso:country":"BE",
    "sg:address":"Gehuchtveldstraat 14",
    "sg:city":"Lebbeke (wieze)",
    "sg:classifiers":[
        {
            "category":"Cafe",
            "type":"Food & Drink"
        }
    ],
    "sg:phone":"+32 53 75 03 50",
    "sg:postcode":"9280",
    "sg:province":"Oost-Vlaanderen",
    "sg:tags":[
        "snack-bars"
    ],
    "wof:name":"Krok'line",
    "wof:placetype":"venue"
},
  "geometry": {"coordinates":[4.10850811,50.9810333252],"type":"Point"}
}