{
  "type": "Feature",
  "properties": {
    "addr:full":"Gr\u00fcfflingen 39 Burg-reuland (thommen) Li\u00e8ge 4791",
    "addr:housenumber":"39",
    "addr:postcode":"4791",
    "addr:street":"Gruefflingen;Thommen",
    "iso:country":"BE",
    "sg:address":"Gr\u00fcfflingen 39",
    "sg:city":"Burg-reuland (thommen)",
    "sg:classifiers":[
        {
            "category":"Bars & Pubs",
            "type":"Food & Drink"
        }
    ],
    "sg:phone":"+32 80 32 91 06",
    "sg:postcode":"4791",
    "sg:province":"Li\u00e8ge",
    "wof:name":"Windhof",
    "wof:placetype":"venue"
},
  "geometry": {"coordinates":[6.0877599716,50.2253112793],"type":"Point"}
}