{
  "type": "Feature",
  "properties": {
    "addr:full":"Pieter Pauwel Rubenspln 11 Kortrijk West-Vlaanderen 8500",
    "addr:housenumber":"11",
    "addr:postcode":"8500",
    "addr:street":"Pieter Pauwel Rubenspln",
    "iso:country":"BE",
    "sg:address":"Pieter Pauwel Rubenspln 11",
    "sg:city":"Kortrijk",
    "sg:orig_category":"Elektrische installaties voor woningen",
    "sg:phone":"+32 56 37 24 76",
    "sg:postcode":"8500",
    "sg:province":"West-Vlaanderen",
    "wof:name":"Pascal Blondeel",
    "wof:placetype":"venue"
},
  "geometry": {"coordinates":[3.2670190334,50.8377418518],"type":"Point"}
}