{
  "type": "Feature",
  "properties": {
    "addr:full":"Rue Du Warichet 9 Walhain (nil-saint-vincent-saint-martin) Brabant Wallon 1457",
    "addr:housenumber":"9",
    "addr:postcode":"1457",
    "addr:street":"Rue Du Warichet;Wallon",
    "iso:country":"BE",
    "sg:address":"Rue Du Warichet 9",
    "sg:city":"Walhain (nil-saint-vincent-saint-martin)",
    "sg:classifiers":[
        {
            "category":"Wholesale",
            "subcategory":"Books, Periodicals, & Newspapers",
            "type":"Manufacturing & Wholesale Goods"
        }
    ],
    "sg:phone":"+32 10 65 45 90",
    "sg:postcode":"1457",
    "sg:province":"Brabant Wallon",
    "sg:tags":[
        "publisher"
    ],
    "wof:name":"Claire Vision Editions Sprl",
    "wof:placetype":"venue"
},
  "geometry": {"coordinates":[4.665017128,50.6358070374],"type":"Point"}
}