{
  "type": "Feature",
  "properties": {
    "addr:full":"Rue De L'athenee 8 Esneux Li\u00e8ge 4130",
    "addr:housenumber":"8",
    "addr:postcode":"4130",
    "addr:street":"Rue De L'Athenee",
    "iso:country":"BE",
    "sg:address":"Rue De L'athenee 8",
    "sg:city":"Esneux",
    "sg:classifiers":[
        {
            "category":"Education",
            "subcategory":"School",
            "type":"Public Place"
        }
    ],
    "sg:phone":"+32 4 380 24 55",
    "sg:postcode":"4130",
    "sg:province":"Li\u00e8ge",
    "sg:tags":[
        "primary"
    ],
    "wof:name":"Ath\u00e9n\u00e9e Royal",
    "wof:placetype":"venue"
},
  "geometry": {"coordinates":[5.5661802292,50.532913208],"type":"Point"}
}