{
  "type": "Feature",
  "properties": {
    "addr:full":"De Villegas Clercampstr. 79 Grimbergen Vlaams-Brabant 1853",
    "addr:housenumber":"79",
    "addr:postcode":"1853",
    "addr:street":"De Villegas Clercampstr.",
    "iso:country":"BE",
    "sg:address":"De Villegas Clercampstr. 79",
    "sg:city":"Grimbergen",
    "sg:orig_category":"Rev\u00eatements pour sols and murs. Conception d'\u00e9talages and de showrooms. Peinture",
    "sg:phone":"+32 2 267 56 60",
    "sg:postcode":"1853",
    "sg:province":"Vlaams-Brabant",
    "wof:name":"Dekor",
    "wof:placetype":"venue"
},
  "geometry": {"coordinates":[4.3510341644,50.908870697],"type":"Point"}
}