{
  "type": "Feature",
  "properties": {
    "addr:full":"Poelkveldstraat 41 Roosdaal Vlaams-Brabant 1760",
    "addr:housenumber":"41",
    "addr:postcode":"1760",
    "addr:street":"Poelkveldstraat",
    "iso:country":"BE",
    "sg:address":"Poelkveldstraat 41",
    "sg:city":"Roosdaal",
    "sg:classifiers":[
        {
            "category":"Professional",
            "subcategory":"Accounting & Tax Preparation",
            "type":"Services"
        }
    ],
    "sg:phone":"+32 54 33 84 07",
    "sg:postcode":"1760",
    "sg:province":"Vlaams-Brabant",
    "sg:tags":[
        "accountant"
    ],
    "wof:name":"Luc Agneessens",
    "wof:placetype":"venue"
},
  "geometry": {"coordinates":[4.0744271278,50.8435707092],"type":"Point"}
}