{
  "type": "Feature",
  "properties": {
    "addr:full":"A. Walraevensstraat 2a Grimbergen Vlaams-Brabant 1850",
    "addr:housenumber":"2a",
    "addr:postcode":"1850",
    "addr:street":"Walraevensstraat",
    "iso:country":"BE",
    "sg:address":"A. Walraevensstraat 2a",
    "sg:city":"Grimbergen",
    "sg:orig_category":"Informaticaconsulenten",
    "sg:phone":"+32 2 253 84 12",
    "sg:postcode":"1850",
    "sg:province":"Vlaams-Brabant",
    "wof:name":"Information Architect",
    "wof:placetype":"venue"
},
  "geometry": {"coordinates":[4.4076981544,50.9268722534],"type":"Point"}
}