{
  "type": "Feature",
  "properties": {
    "addr:full":"Lichterstr 65 Puurs Antwerpen 2870",
    "addr:housenumber":"65",
    "addr:postcode":"2870",
    "addr:street":"Lichterstr",
    "iso:country":"BE",
    "sg:address":"Lichterstr 65",
    "sg:city":"Puurs",
    "sg:classifiers":[
        {
            "category":"Professional",
            "type":"Services"
        }
    ],
    "sg:phone":"+32 3 889 24 06",
    "sg:postcode":"2870",
    "sg:province":"Antwerpen",
    "sg:tags":[
        "transport",
        "road"
    ],
    "wof:name":"Elpers Emile Maurice Julien M.",
    "wof:placetype":"venue"
},
  "geometry": {"coordinates":[4.3167200089,51.0600090027],"type":"Point"}
}