{
  "type": "Feature",
  "properties": {
    "iso:country":"BE",
    "sg:address":"Rue Des Ardennes 88",
    "sg:city":"Messancy",
    "sg:classifiers":[
        {
            "category":"Building & Trades",
            "subcategory":"Cleaning & Sanitation",
            "type":"Services"
        }
    ],
    "sg:phone":"+32 63 22 05 96",
    "sg:postcode":"6780",
    "sg:province":"Luxembourg",
    "sg:tags":[
        "equipment",
        "industrial",
        "maintenance"
    ],
    "wof:name":"Roloux E Sa",
    "wof:placetype":"venue"
},
  "geometry": {"coordinates":[5.8100361824,49.6213035583],"type":"Point"}
}