{
  "type": "Feature",
  "properties": {
    "addr:full":"Diamantlaan 71 Brussel/bruxelles Bruxelles-Capitale 1030",
    "addr:housenumber":"71",
    "addr:postcode":"1030",
    "addr:street":"Diamantlaan;/",
    "iso:country":"BE",
    "sg:address":"Diamantlaan 71",
    "sg:city":"Brussel/bruxelles",
    "sg:classifiers":[
        {
            "category":"Professional",
            "subcategory":"Business Services",
            "type":"Services"
        }
    ],
    "sg:phone":"+32 2 735 34 31",
    "sg:postcode":"1030",
    "sg:province":"Bruxelles-Capitale",
    "sg:tags":[
        "aux",
        "diver",
        "entreprises"
    ],
    "wof:name":"Rebo Consult",
    "wof:placetype":"venue"
},
  "geometry": {"coordinates":[4.3941040039,50.8515357971],"type":"Point"}
}