{
  "type": "Feature",
  "properties": {
    "addr:full":"Rue Des Hougnes 128 Verviers Li\u00e8ge 4800",
    "addr:housenumber":"128",
    "addr:postcode":"4800",
    "addr:street":"Rue Des Hougnes",
    "iso:country":"BE",
    "sg:address":"Rue Des Hougnes 128",
    "sg:city":"Verviers",
    "sg:orig_category":"Activit\u00e9s r\u00e9cr\u00e9atives diverses",
    "sg:phone":"+32 87 77 28 54",
    "sg:postcode":"4800",
    "sg:province":"Li\u00e8ge",
    "wof:name":"Cercle Royal Des Echecs Vervi\u00c9tois",
    "wof:placetype":"venue"
},
  "geometry": {"coordinates":[5.8665218353,50.5857810974],"type":"Point"}
}