{
  "type": "Feature",
  "properties": {
    "iso:country":"BE",
    "sg:address":"Rue Albert I 342",
    "sg:city":"Erquelinnes",
    "sg:classifiers":[
        {
            "category":"Manufacturing",
            "subcategory":"Textiles",
            "type":"Manufacturing & Wholesale Goods"
        }
    ],
    "sg:phone":"+32 71 55 51 63",
    "sg:postcode":"6560",
    "sg:province":"Hainaut",
    "sg:tags":[
        "retail",
        "-"
    ],
    "wof:name":"Justepri",
    "wof:placetype":"venue"
},
  "geometry": {"coordinates":[4.1207499504,50.3097915649],"type":"Point"}
}