{
  "type": "Feature",
  "properties": {
    "addr:full":"Place Des Tilleuls 48 Andenne Namur 5300",
    "addr:housenumber":"48",
    "addr:postcode":"5300",
    "addr:street":"Place Des Tilleuls",
    "iso:country":"BE",
    "sg:address":"Place Des Tilleuls 48",
    "sg:city":"Andenne",
    "sg:classifiers":[
        {
            "category":"Banks & Credit Unions",
            "subcategory":"Investment Brokerage",
            "type":"Services"
        }
    ],
    "sg:phone":"+32 85 84 14 75",
    "sg:postcode":"5300",
    "sg:province":"Namur",
    "sg:tags":[
        "development",
        "economic",
        "institution"
    ],
    "wof:name":"Promandenne",
    "wof:placetype":"venue"
},
  "geometry": {"coordinates":[5.0961427689,50.4897384644],"type":"Point"}
}