{
  "type": "Feature",
  "properties": {
    "addr:full":"Rue D'h\u00c9rinnes 55 Edingen/enghien Hainaut 7850",
    "addr:housenumber":"55",
    "addr:postcode":"7850",
    "addr:street":"Rue D'He \u0301Rinnes",
    "iso:country":"BE",
    "sg:address":"Rue D'h\u00c9rinnes 55",
    "sg:city":"Edingen/enghien",
    "sg:orig_category":"Pr\u00eats hypoth\u00e9caires and cr\u00e9dits immobiliers. Cr\u00e9dit \u00e0 la consommation. Location de logements sociaux",
    "sg:phone":"+32 2 395 86 54",
    "sg:postcode":"7850",
    "sg:province":"Hainaut",
    "wof:name":"De Familiale Woonst/le Logis Familial",
    "wof:placetype":"venue"
},
  "geometry": {"coordinates":[4.038274765,50.6951675415],"type":"Point"}
}