{
  "type": "Feature",
  "properties": {
    "addr:full":"F. Depuydtlaan 4 Ichtegem West-Vlaanderen 8480",
    "addr:housenumber":"4",
    "addr:postcode":"8480",
    "addr:street":"Depuydtlaan",
    "iso:country":"BE",
    "sg:address":"F. Depuydtlaan 4",
    "sg:city":"Ichtegem",
    "sg:orig_category":"Boekhouders",
    "sg:phone":"+32 59 29 99 69",
    "sg:postcode":"8480",
    "sg:province":"West-Vlaanderen",
    "wof:name":"Debussche",
    "wof:placetype":"venue"
},
  "geometry": {"coordinates":[3.010445118,51.0919189453],"type":"Point"}
}