{
  "type": "Feature",
  "properties": {
    "addr:full":"Mandemakerstraat 100b Hamme Oost-Vlaanderen 9220",
    "addr:housenumber":"100b",
    "addr:postcode":"9220",
    "addr:street":"Mandemakerstraat",
    "iso:country":"BE",
    "sg:address":"Mandemakerstraat 100b",
    "sg:city":"Hamme",
    "sg:classifiers":[
        {
            "category":"Health Services",
            "subcategory":"Nursing And Care Facility",
            "type":"Services"
        }
    ],
    "sg:phone":"+32 52 48 00 01",
    "sg:postcode":"9220",
    "sg:province":"Oost-Vlaanderen",
    "sg:tags":[
        "home"
    ],
    "wof:name":"Thuisverpleging Pauwels Marleen Bvba",
    "wof:placetype":"venue"
},
  "geometry": {"coordinates":[4.1418910027,51.0999794006],"type":"Point"}
}