{
  "type": "Feature",
  "properties": {
    "addr:full":"Rue Du Cayaux 5ba Florennes Namur 5620",
    "addr:housenumber":"5ba",
    "addr:postcode":"5620",
    "addr:street":"Rue Du Cayaux",
    "iso:country":"BE",
    "sg:address":"Rue Du Cayaux 5ba",
    "sg:city":"Florennes",
    "sg:orig_category":"V\u00e9hicules automobiles",
    "sg:phone":"+32 82 68 85 60",
    "sg:postcode":"5620",
    "sg:province":"Namur",
    "wof:name":"Garage Delta",
    "wof:placetype":"venue"
},
  "geometry": {"coordinates":[4.7232208252,50.2515106201],"type":"Point"}
}