{
  "type": "Feature",
  "properties": {
    "addr:full":"Dorpsstraat 103 Overpelt Limburg 3900",
    "addr:housenumber":"103",
    "addr:postcode":"3900",
    "addr:street":"Dorpsstraat",
    "iso:country":"BE",
    "sg:address":"Dorpsstraat 103",
    "sg:city":"Overpelt",
    "sg:orig_category":"M\u00e9decins and sp\u00e9cialistes",
    "sg:phone":"+32 11 64 10 25",
    "sg:postcode":"3900",
    "sg:province":"Limburg",
    "wof:name":"Paul Finoulst",
    "wof:placetype":"venue"
},
  "geometry": {"coordinates":[5.4207701683,51.2097358704],"type":"Point"}
}