{
  "type": "Feature",
  "properties": {
    "iso:country":"BE",
    "sg:address":"Rue De La Sucrerie 123",
    "sg:city":"Thuin (donstiennes)",
    "sg:classifiers":[
        {
            "category":"Retail",
            "subcategory":"Storage",
            "type":"Services"
        }
    ],
    "sg:phone":"+32 71 53 57 39",
    "sg:postcode":"6536",
    "sg:province":"Hainaut",
    "sg:tags":[
        "rack",
        "system"
    ],
    "wof:name":"Cusenza R",
    "wof:placetype":"venue"
},
  "geometry": {"coordinates":[4.3164329529,50.2814559937],"type":"Point"}
}