{
  "type": "Feature",
  "properties": {
    "iso:country":"BE",
    "sg:address":"Geldenaaksestraat 20",
    "sg:city":"Oud-heverlee (haasrode)",
    "sg:classifiers":[
        {
            "category":"Professional",
            "subcategory":"Management & Consulting",
            "type":"Services"
        }
    ],
    "sg:phone":"+32 16 40 89 40",
    "sg:postcode":"3053",
    "sg:province":"Vlaams-Brabant",
    "sg:tags":[
        "-",
        "processing",
        "data",
        "consultant"
    ],
    "wof:name":"Windekind Bvba",
    "wof:placetype":"venue"
},
  "geometry": {"coordinates":[4.7402567863,50.8327102661],"type":"Point"}
}