{
  "type": "Feature",
  "properties": {
    "addr:full":"Schoolstraat 63 Buggenhout Oost-Vlaanderen 9255",
    "addr:housenumber":"63",
    "addr:postcode":"9255",
    "addr:street":"Schoolstraat",
    "iso:country":"BE",
    "sg:address":"Schoolstraat 63",
    "sg:city":"Buggenhout",
    "sg:orig_category":"Paramedische behandelingen",
    "sg:phone":"+32 52 33 64 03",
    "sg:postcode":"9255",
    "sg:province":"Oost-Vlaanderen",
    "wof:name":"Hilde Hermans",
    "wof:placetype":"venue"
},
  "geometry": {"coordinates":[4.1956930161,51.0137252808],"type":"Point"}
}