{
  "type": "Feature",
  "properties": {
    "addr:full":"Turnhoutsebaan 345 Antwerpen Antwerpen 2140",
    "addr:housenumber":"345",
    "addr:postcode":"2140",
    "addr:street":"Turnhoutsebaan",
    "iso:country":"BE",
    "sg:address":"Turnhoutsebaan 345",
    "sg:city":"Antwerpen",
    "sg:orig_category":"Entretien and r\u00e9parations de machines de bureau and ordinateurs. Ordinateurs and \u00e9quipement informat",
    "sg:phone":"+32 3 272 55 93",
    "sg:postcode":"2140",
    "sg:province":"Antwerpen",
    "wof:name":"F & F Systems",
    "wof:placetype":"venue"
},
  "geometry": {"coordinates":[4.4332199097,51.2137565613],"type":"Point"}
}