{
  "type": "Feature",
  "properties": {
    "iso:country":"BE",
    "sg:address":"Weg Naar As 160 Box 2",
    "sg:city":"Genk",
    "sg:classifiers":[
        {
            "category":"Building & Trades",
            "subcategory":"Construction",
            "type":"Services"
        }
    ],
    "sg:phone":"+32 89 30 72 39",
    "sg:postcode":"3600",
    "sg:province":"Limburg",
    "sg:tags":[
        "truss-makers"
    ],
    "wof:name":"Orthomed Bvba-martina Lemmens",
    "wof:placetype":"venue"
},
  "geometry": {"coordinates":[5.5162491798,50.9722900391],"type":"Point"}
}