{
  "type": "Feature",
  "properties": {
    "iso:country":"BE",
    "sg:address":"Schrieksesteenweg 52",
    "sg:city":"Putte",
    "sg:orig_category":"Transports routiers de marchandises",
    "sg:phone":"+32 15 75 61 22",
    "sg:postcode":"2580",
    "sg:province":"Antwerpen",
    "wof:name":"Hentri",
    "wof:placetype":"venue"
},
  "geometry": {"coordinates":[4.64848423,51.0415840149],"type":"Point"}
}