{
  "type": "Feature",
  "properties": {
    "iso:country":"BE",
    "sg:address":"Stationsstraat 40",
    "sg:city":"Ardooie",
    "sg:classifiers":[
        {
            "category":"Shopping",
            "subcategory":"Gifts & Souvenirs",
            "type":"Retail Goods"
        }
    ],
    "sg:phone":"+32 51 74 42 72",
    "sg:postcode":"8850",
    "sg:province":"West-Vlaanderen",
    "sg:tags":[
        "-"
    ],
    "wof:name":"Metallux Geurden Markey",
    "wof:placetype":"venue"
},
  "geometry": {"coordinates":[3.1996901035,50.9802322388],"type":"Point"}
}