{
  "type": "Feature",
  "properties": {
    "addr:full":"Rue Des Coteaux 312 Bruxelles (schaerbeek) Bruxelles-Capitale 1030",
    "addr:housenumber":"312",
    "addr:postcode":"1030",
    "addr:street":"Rue Des Coteaux",
    "iso:country":"BE",
    "sg:address":"Rue Des Coteaux 312",
    "sg:city":"Bruxelles (schaerbeek)",
    "sg:classifiers":[
        {
            "category":"Wholesale",
            "subcategory":"Home Furnishings",
            "type":"Manufacturing & Wholesale Goods"
        }
    ],
    "sg:phone":"+32 2 241 35 90",
    "sg:postcode":"1030",
    "sg:province":"Bruxelles-Capitale",
    "sg:tags":[
        "storage",
        "-",
        "furniture"
    ],
    "wof:name":"Act Maison Erkens",
    "wof:placetype":"venue"
},
  "geometry": {"coordinates":[4.3800501823,50.8628349304],"type":"Point"}
}