{
  "type": "Feature",
  "properties": {
    "iso:country":"BE",
    "sg:address":"Torenhoflaan 68",
    "sg:city":"Rotselaar",
    "sg:classifiers":[
        {
            "category":"Retail",
            "subcategory":"Event Space",
            "type":"Services"
        }
    ],
    "sg:phone":"+32 16 44 84 55",
    "sg:postcode":"3110",
    "sg:province":"Vlaams-Brabant",
    "sg:tags":[
        "rental",
        "-",
        "hall"
    ],
    "wof:name":"Torenhoeve",
    "wof:placetype":"venue"
},
  "geometry": {"coordinates":[4.7216029167,50.9574623108],"type":"Point"}
}