{
  "type": "Feature",
  "properties": {
    "addr:full":"Meersstraat 13 Wachtebeke Oost-Vlaanderen 9185",
    "addr:housenumber":"13",
    "addr:postcode":"9185",
    "addr:street":"Meersstraat",
    "iso:country":"BE",
    "sg:address":"Meersstraat 13",
    "sg:city":"Wachtebeke",
    "sg:orig_category":"Supermarch\u00e9s",
    "sg:phone":"+32 9 345 52 86",
    "sg:postcode":"9185",
    "sg:province":"Oost-Vlaanderen",
    "wof:name":"Unic",
    "wof:placetype":"venue"
},
  "geometry": {"coordinates":[3.8593440056,51.168056488],"type":"Point"}
}