{
  "type": "Feature",
  "properties": {
    "iso:country":"BE",
    "sg:address":"Adegemstraat 107",
    "sg:city":"Mechelen",
    "sg:orig_category":"Slagers",
    "sg:phone":"+32 15 20 26 30",
    "sg:postcode":"2800",
    "sg:province":"Antwerpen",
    "wof:name":"Jozef De Bie",
    "wof:placetype":"venue"
},
  "geometry": {"coordinates":[4.4726729393,51.0268783569],"type":"Point"}
}