{
  "type": "Feature",
  "properties": {
    "iso:country":"BE",
    "sg:address":"Rue De Corenne 24",
    "sg:city":"Florennes",
    "sg:orig_category":"Sportclubs",
    "sg:phone":"+32 71 68 92 22",
    "sg:postcode":"5620",
    "sg:province":"Namur",
    "wof:name":"T.c. Ermeton",
    "wof:placetype":"venue"
},
  "geometry": {"coordinates":[4.6118311882,50.2487449646],"type":"Point"}
}