{
  "type": "Feature",
  "properties": {
    "iso:country":"BE",
    "sg:address":"Slagveldstraat 22",
    "sg:city":"Lokeren",
    "sg:orig_category":"Boekhouders",
    "sg:phone":"+32 9 348 67 91",
    "sg:postcode":"9160",
    "sg:province":"Oost-Vlaanderen",
    "wof:name":"Hans Van Duysen",
    "wof:placetype":"venue"
},
  "geometry": {"coordinates":[3.9868540764,51.1145591736],"type":"Point"}
}