{
  "type": "Feature",
  "properties": {
    "iso:country":"BE",
    "sg:address":"Hekslaan 108",
    "sg:city":"Heers",
    "sg:orig_category":"Traitements param\u00e9dicaux",
    "sg:phone":"+32 12 74 62 33",
    "sg:postcode":"3870",
    "sg:province":"Limburg",
    "wof:name":"K. Daniels",
    "wof:placetype":"venue"
},
  "geometry": {"coordinates":[5.355096817,50.7731781006],"type":"Point"}
}