{
  "type": "Feature",
  "properties": {
    "iso:country":"BE",
    "sg:address":"Rue Du Centre 35",
    "sg:city":"Braives (latinne)",
    "sg:orig_category":"Cafetarias and selfservice restaurants",
    "sg:phone":"+32 19 69 97 02",
    "sg:postcode":"4261",
    "sg:province":"Li\u00e8ge",
    "wof:name":"Troubadour (le)",
    "wof:placetype":"venue"
},
  "geometry": {"coordinates":[5.1580500603,50.6231918335],"type":"Point"}
}