{
  "type": "Feature",
  "properties": {
    "addr:full":"Kruiswegestraat 48 Ruiselede West-Vlaanderen 8755",
    "addr:housenumber":"48",
    "addr:postcode":"8755",
    "addr:street":"Kruiswegestraat",
    "iso:country":"BE",
    "sg:address":"Kruiswegestraat 48",
    "sg:city":"Ruiselede",
    "sg:classifiers":[
        {
            "category":"Real Estate",
            "subcategory":"Real Estate Services",
            "type":"Services"
        }
    ],
    "sg:phone":"+32 51 68 68 38",
    "sg:postcode":"8755",
    "sg:province":"West-Vlaanderen",
    "wof:name":"Bouwonderneming Chrigabo Nv",
    "wof:placetype":"venue"
},
  "geometry": {"coordinates":[3.3872361183,51.0390625],"type":"Point"}
}