{
  "type": "Feature",
  "properties": {
    "iso:country":"BE",
    "sg:address":"Lange Nieuwstraat 126",
    "sg:city":"Antwerpen",
    "sg:classifiers":[
        {
            "category":"Banks & Credit Unions",
            "subcategory":"Investment Brokerage",
            "type":"Services"
        }
    ],
    "sg:phone":"+32 3 233 82 41",
    "sg:postcode":"2000",
    "sg:province":"Antwerpen",
    "sg:tags":[
        "printing",
        "-"
    ],
    "wof:name":"Janssens & Zonen",
    "wof:placetype":"venue"
},
  "geometry": {"coordinates":[4.4139790535,51.2195167542],"type":"Point"}
}