{
  "type": "Feature",
  "properties": {
    "addr:full":"Betonweg 13 Bilzen (mopertingen) Limburg 3740",
    "addr:housenumber":"13",
    "addr:postcode":"3740",
    "addr:street":"Betonweg",
    "iso:country":"BE",
    "sg:address":"Betonweg 13",
    "sg:city":"Bilzen (mopertingen)",
    "sg:classifiers":[
        {
            "category":"Personal",
            "subcategory":"Beauty Salon",
            "type":"Services"
        }
    ],
    "sg:phone":"+32 89 41 50 63",
    "sg:postcode":"3740",
    "sg:province":"Limburg",
    "sg:tags":[
        "lady",
        "-",
        "hairdressing"
    ],
    "wof:name":"Jans L",
    "wof:placetype":"venue"
},
  "geometry": {"coordinates":[5.5774512291,50.8638725281],"type":"Point"}
}