{
  "type": "Feature",
  "properties": {
    "iso:country":"BE",
    "sg:address":"Doornplasstraat 91",
    "sg:city":"Gent (drongen)",
    "sg:classifiers":[
        {
            "category":"Building & Trades",
            "subcategory":"Landscaping Services",
            "type":"Services"
        }
    ],
    "sg:phone":"+32 9 226 44 76",
    "sg:postcode":"9031",
    "sg:province":"Oost-Vlaanderen",
    "sg:tags":[
        "access",
        "pond",
        "laying-out",
        "-"
    ],
    "wof:name":"Quality Koi",
    "wof:placetype":"venue"
},
  "geometry": {"coordinates":[3.6247310638,51.0608444214],"type":"Point"}
}