{
  "type": "Feature",
  "properties": {
    "addr:full":"Avenue Edouard Cordonnier 129 Verviers Li\u00e8ge 4800",
    "addr:housenumber":"129",
    "addr:postcode":"4800",
    "addr:street":"Avenue Edouard Cordonnier",
    "iso:country":"BE",
    "sg:address":"Avenue Edouard Cordonnier 129",
    "sg:city":"Verviers",
    "sg:classifiers":[
        {
            "category":"Building & Trades",
            "subcategory":"Plumbing",
            "type":"Services"
        }
    ],
    "sg:phone":"+32 87 22 52 01",
    "sg:postcode":"4800",
    "sg:province":"Li\u00e8ge",
    "sg:tags":[
        "repair",
        "mainten",
        "-",
        "central",
        "heating"
    ],
    "wof:name":"Bmg Services Sprl",
    "wof:placetype":"venue"
},
  "geometry": {"coordinates":[5.888048172,50.5719795227],"type":"Point"}
}