{
  "type": "Feature",
  "properties": {
    "iso:country":"BE",
    "sg:address":"Victor Braeckmanlaan 26",
    "sg:city":"Gent",
    "sg:orig_category":"Banques and organismes de cr\u00e9dit",
    "sg:phone":"+32 9 238 28 50",
    "sg:postcode":"9040",
    "sg:province":"Oost-Vlaanderen",
    "wof:name":"Centea",
    "wof:placetype":"venue"
},
  "geometry": {"coordinates":[3.7506599426,51.0591392517],"type":"Point"}
}