{
  "type": "Feature",
  "properties": {
    "iso:country":"BE",
    "sg:address":"Basilieklaan 327",
    "sg:city":"Koekelberg/koekelberg",
    "sg:orig_category":"Artsen and specialisten",
    "sg:phone":"+32 2 469 03 40",
    "sg:postcode":"1081",
    "sg:province":"Bruxelles-Capitale",
    "wof:name":"Denise De Weert",
    "wof:placetype":"venue"
},
  "geometry": {"coordinates":[4.3075470924,50.8645973206],"type":"Point"}
}