{
  "type": "Feature",
  "properties": {
    "iso:country":"BE",
    "sg:address":"Oudstrijderslaan 10",
    "sg:city":"Lendelede",
    "sg:classifiers":[
        {
            "category":"Banks & Credit Unions",
            "subcategory":"Investment Brokerage",
            "type":"Services"
        }
    ],
    "sg:phone":"+32 51 30 50 88",
    "sg:postcode":"8860",
    "sg:province":"West-Vlaanderen",
    "sg:tags":[
        "printing",
        "-"
    ],
    "wof:name":"Press-clusief",
    "wof:placetype":"venue"
},
  "geometry": {"coordinates":[3.2318339348,50.8860015869],"type":"Point"}
}