{
  "type": "Feature",
  "properties": {
    "addr:full":"Karel Janssenslaan 33b10 Oostende West-Vlaanderen 8400",
    "addr:housenumber":"33b10",
    "addr:postcode":"8400",
    "addr:street":"Karel Janssenslaan",
    "iso:country":"BE",
    "sg:address":"Karel Janssenslaan 33b10",
    "sg:city":"Oostende",
    "sg:orig_category":"M\u00e9decins and sp\u00e9cialistes",
    "sg:phone":"+32 59 70 23 42",
    "sg:postcode":"8400",
    "sg:province":"West-Vlaanderen",
    "wof:name":"Joseph Crauwels",
    "wof:placetype":"venue"
},
  "geometry": {"coordinates":[2.9121069908,51.2289085388],"type":"Point"}
}