{
  "type": "Feature",
  "properties": {
    "iso:country":"BE",
    "sg:address":"Rue Des Aduatiques 94",
    "sg:city":"Bruxelles (etterbeek)",
    "sg:orig_category":"Non-Classified Establishments",
    "sg:phone":"+32 2 732 57 93",
    "sg:postcode":"1040",
    "sg:province":"Bruxelles-Capitale",
    "wof:name":"Pro Performance",
    "wof:placetype":"venue"
},
  "geometry": {"coordinates":[4.4052920341,50.8364906311],"type":"Point"}
}