{
  "type": "Feature",
  "properties": {
    "iso:country":"BE",
    "sg:address":"Rue De La Grande Veine 15",
    "sg:city":"Dour",
    "sg:orig_category":"Bloemen and planten",
    "sg:phone":"+32 65 65 55 96",
    "sg:postcode":"7370",
    "sg:province":"Hainaut",
    "wof:name":"Le Vert Bocage",
    "wof:placetype":"venue"
},
  "geometry": {"coordinates":[3.7530789375,50.3993034363],"type":"Point"}
}