{
  "type": "Feature",
  "properties": {
    "iso:country":"BE",
    "sg:address":"Velodroomstraat 66",
    "sg:city":"Oostende",
    "sg:classifiers":[
        {
            "category":"Building & Trades",
            "subcategory":"Cleaning & Sanitation",
            "type":"Services"
        }
    ],
    "sg:phone":"+32 59 70 17 22",
    "sg:postcode":"8400",
    "sg:province":"West-Vlaanderen",
    "sg:tags":[
        "fa\u00e7ade",
        "maintenance"
    ],
    "wof:name":"Mechele R.",
    "wof:placetype":"venue"
},
  "geometry": {"coordinates":[2.9040169716,51.223487854],"type":"Point"}
}