{
  "type": "Feature",
  "properties": {
    "iso:country":"BE",
    "sg:address":"Quai De Rome 56",
    "sg:city":"Li\u00c8ge",
    "sg:orig_category":"Architecten",
    "sg:phone":"+32 4 252 14 24",
    "sg:postcode":"4000",
    "sg:province":"Li\u00e8ge",
    "wof:name":"Mohammed Sbaghi",
    "wof:placetype":"venue"
},
  "geometry": {"coordinates":[5.5770421028,50.6218643188],"type":"Point"}
}