{
  "type": "Feature",
  "properties": {
    "iso:country":"BE",
    "sg:address":"Heuvelstraat 49a",
    "sg:city":"Zemst (hofstade)",
    "sg:classifiers":[
        {
            "category":"Health Services",
            "subcategory":"Doctor",
            "type":"Services"
        }
    ],
    "sg:phone":"+32 15 41 22 69",
    "sg:postcode":"1981",
    "sg:province":"Vlaams-Brabant",
    "sg:tags":[
        "medicinephysicians",
        "surgeon"
    ],
    "wof:name":"Buts E",
    "wof:placetype":"venue"
},
  "geometry": {"coordinates":[4.4967670441,51.0033493042],"type":"Point"}
}