{
  "type": "Feature",
  "properties": {
    "addr:full":"Diestersteenweg 21 Nieuwerkerken Limburg 3850",
    "addr:housenumber":"21",
    "addr:postcode":"3850",
    "addr:street":"Diestersteenweg",
    "iso:country":"BE",
    "sg:address":"Diestersteenweg 21",
    "sg:city":"Nieuwerkerken",
    "sg:classifiers":[
        {
            "category":"Professional",
            "subcategory":"Lawyer & Legal Services",
            "type":"Services"
        }
    ],
    "sg:phone":"+32 11 69 24 56",
    "sg:postcode":"3850",
    "sg:province":"Limburg",
    "wof:name":"Sneyers Ludwig",
    "wof:placetype":"venue"
},
  "geometry": {"coordinates":[5.1885251999,50.8563423157],"type":"Point"}
}