{
  "type": "Feature",
  "properties": {
    "iso:country":"BE",
    "sg:address":"Rue Des R\u00e9collets 21",
    "sg:city":"Vis\u00e9",
    "sg:classifiers":[
        {
            "category":"Retail",
            "subcategory":"Animal Services",
            "type":"Services"
        }
    ],
    "sg:phone":"+32 4 379 68 78",
    "sg:postcode":"4600",
    "sg:province":"Li\u00e8ge",
    "sg:tags":[
        "grooming",
        "-",
        "dog"
    ],
    "wof:name":"Happy Doggy",
    "wof:placetype":"venue"
},
  "geometry": {"coordinates":[5.6932449341,50.7355155945],"type":"Point"}
}