{
  "type": "Feature",
  "properties": {
    "addr:full":"Bredabaan 427 Brasschaat Antwerpen 2930",
    "addr:housenumber":"427",
    "addr:postcode":"2930",
    "addr:street":"Bredabaan",
    "iso:country":"BE",
    "sg:address":"Bredabaan 427",
    "sg:city":"Brasschaat",
    "sg:classifiers":[
        {
            "category":"Shopping",
            "subcategory":"Clothing, Apparel, & Fashions",
            "type":"Retail Goods"
        }
    ],
    "sg:phone":"+32 3 653 51 81",
    "sg:postcode":"2930",
    "sg:province":"Antwerpen",
    "sg:tags":[
        "lady",
        "clothing",
        "-"
    ],
    "wof:name":"Tintoretto Bvba",
    "wof:placetype":"venue"
},
  "geometry": {"coordinates":[4.4938549995,51.291633606],"type":"Point"}
}