{
  "type": "Feature",
  "properties": {
    "iso:country":"BE",
    "sg:address":"Marienplatz 10",
    "sg:city":"Eupen/eupen",
    "sg:orig_category":"Woningbouw",
    "sg:phone":"+32 87 55 30 22",
    "sg:postcode":"4701",
    "sg:province":"Li\u00e8ge",
    "wof:name":"Leonard Vlekken",
    "wof:placetype":"venue"
},
  "geometry": {"coordinates":[6.0461649895,50.6460838318],"type":"Point"}
}