{
  "type": "Feature",
  "properties": {
    "addr:full":"Waterleliestraat 2 Bonheiden Antwerpen 2820",
    "addr:housenumber":"2",
    "addr:postcode":"2820",
    "addr:street":"Waterleliestraat",
    "iso:country":"BE",
    "sg:address":"Waterleliestraat 2",
    "sg:city":"Bonheiden",
    "sg:orig_category":"Artistes ind\u00e9pendants",
    "sg:phone":"+32 15 51 72 20",
    "sg:postcode":"2820",
    "sg:province":"Antwerpen",
    "wof:name":"Jaak Van Assche",
    "wof:placetype":"venue"
},
  "geometry": {"coordinates":[4.5496602058,51.0218009949],"type":"Point"}
}