{
  "type": "Feature",
  "properties": {
    "addr:full":"Chauss\u00c9e De Namur 2 Moignelee Namur 5060",
    "addr:housenumber":"2",
    "addr:postcode":"5060",
    "addr:street":"Chausse\u0301E De Namur;Namur",
    "iso:country":"BE",
    "sg:address":"Chauss\u00c9e De Namur 2",
    "sg:city":"Moignelee",
    "sg:orig_category":"Entretien et r\u00e9parations de v\u00e9hicules \u00e0 domicile",
    "sg:phone":"+32 71 74 40 84",
    "sg:postcode":"5060",
    "sg:province":"Namur",
    "wof:name":"D\u00c9pannage Fabrice Et Garage Antoine",
    "wof:placetype":"venue"
},
  "geometry": {"coordinates":[4.5925898552,50.4432868958],"type":"Point"}
}