{
  "type": "Feature",
  "properties": {
    "addr:full":"Rue Fernand Bernier 40 Sint-gillis/saint-gilles Bruxelles-Capitale 1060",
    "addr:housenumber":"40",
    "addr:postcode":"1060",
    "addr:street":"Rue Fernand Bernier",
    "iso:country":"BE",
    "sg:address":"Rue Fernand Bernier 40",
    "sg:city":"Sint-gillis/saint-gilles",
    "sg:orig_category":"Mus\u00e9es and patrimoine culturel",
    "sg:phone":"+32 2 348 50 05",
    "sg:postcode":"1060",
    "sg:province":"Bruxelles-Capitale",
    "wof:name":"Musee Vie Saint-gilloise",
    "wof:placetype":"venue"
},
  "geometry": {"coordinates":[4.3361649513,50.8287124634],"type":"Point"}
}