{
  "type": "Feature",
  "properties": {
    "addr:full":"Boulevard Louis Mettewie 50b3c7 Sint-jans-molenbeek/molenbeek-saint-jean Bruxelles-Capitale 1080",
    "addr:postcode":"50b3c7;1080",
    "addr:street":"Boulevard Louis Mettewie",
    "iso:country":"BE",
    "sg:address":"Boulevard Louis Mettewie 50b3c7",
    "sg:city":"Sint-jans-molenbeek/molenbeek-saint-jean",
    "sg:orig_category":"Artistes ind\u00e9pendants",
    "sg:phone":"+32 2 414 43 08",
    "sg:postcode":"1080",
    "sg:province":"Bruxelles-Capitale",
    "wof:name":"Marie-jeanne Nyl",
    "wof:placetype":"venue"
},
  "geometry": {"coordinates":[4.3107280731,50.8577346802],"type":"Point"}
}