{
  "type": "Feature",
  "properties": {
    "iso:country":"BE",
    "sg:address":"Wijnendalestraat 16",
    "sg:city":"Kortemark",
    "sg:orig_category":"Eleveurs de bovins",
    "sg:phone":"+32 50 21 10 28",
    "sg:postcode":"8610",
    "sg:province":"West-Vlaanderen",
    "wof:name":"Freddy Vandemoortel",
    "wof:placetype":"venue"
},
  "geometry": {"coordinates":[3.0486299992,51.0549278259],"type":"Point"}
}