{
  "type": "Feature",
  "properties": {
    "addr:full":"Rue Emile Tumelaire 71 Charleroi Hainaut 6000",
    "addr:housenumber":"71",
    "addr:postcode":"6000",
    "addr:street":"Rue Emile Tumelaire;Hainaut",
    "iso:country":"BE",
    "sg:address":"Rue Emile Tumelaire 71",
    "sg:city":"Charleroi",
    "sg:orig_category":"Avocats and conseillers juridiques",
    "sg:phone":"+32 71 32 59 18",
    "sg:postcode":"6000",
    "sg:province":"Hainaut",
    "wof:name":"Vincent Grevy",
    "wof:placetype":"venue"
},
  "geometry": {"coordinates":[4.450442791,50.4095878601],"type":"Point"}
}