{
  "type": "Feature",
  "properties": {
    "iso:country":"BE",
    "sg:address":"Kolveniersvest 20",
    "sg:city":"Lier",
    "sg:orig_category":"M\u00e9decins and sp\u00e9cialistes",
    "sg:phone":"+32 3 491 38 30",
    "sg:postcode":"2500",
    "sg:province":"Antwerpen",
    "wof:name":"Consultatiebur.jonge Kind",
    "wof:placetype":"venue"
},
  "geometry": {"coordinates":[4.5665869713,51.13230896],"type":"Point"}
}