{
  "type": "Feature",
  "properties": {
    "addr:full":"Rue Vincent Van Gogh 2 Mons Hainaut 7033",
    "addr:housenumber":"2",
    "addr:postcode":"7033",
    "addr:street":"Rue Vincent Van Gogh;Hainaut",
    "iso:country":"BE",
    "sg:address":"Rue Vincent Van Gogh 2",
    "sg:city":"Mons",
    "sg:orig_category":"M\u00e9decins and sp\u00e9cialistes",
    "sg:phone":"+32 65 33 68 06",
    "sg:postcode":"7033",
    "sg:province":"Hainaut",
    "wof:name":"Jean Moreaux",
    "wof:placetype":"venue"
},
  "geometry": {"coordinates":[3.9253261089,50.4366378784],"type":"Point"}
}