{
  "type": "Feature",
  "properties": {
    "iso:country":"BE",
    "sg:address":"Driftweg 40",
    "sg:city":"Zuienkerke",
    "sg:classifiers":[
        {
            "category":"Social Services",
            "subcategory":"Job Training",
            "type":"Services"
        }
    ],
    "sg:phone":"+32 50 41 42 06",
    "sg:postcode":"8377",
    "sg:province":"West-Vlaanderen",
    "sg:tags":[
        "de",
        "terrain",
        "camping"
    ],
    "wof:name":"Gilbert Lems",
    "wof:placetype":"venue"
},
  "geometry": {"coordinates":[3.0657351017,51.2884483337],"type":"Point"}
}