{
  "type": "Feature",
  "properties": {
    "addr:full":"Asbroekstraat 99 Zoutleeuw (halle-booienhoven) Vlaams-Brabant 3440",
    "addr:housenumber":"99",
    "addr:postcode":"3440",
    "addr:street":"Asbroekstraat",
    "iso:country":"BE",
    "sg:address":"Asbroekstraat 99",
    "sg:city":"Zoutleeuw (halle-booienhoven)",
    "sg:classifiers":[
        {
            "category":"Food & Beverages",
            "subcategory":"Groceries & Convenience Stores",
            "type":"Retail Goods"
        }
    ],
    "sg:phone":"+32 11 78 29 06",
    "sg:postcode":"3440",
    "sg:province":"Vlaams-Brabant",
    "sg:tags":[
        "grocer"
    ],
    "wof:name":"Herbots B",
    "wof:placetype":"venue"
},
  "geometry": {"coordinates":[5.1187701225,50.807220459],"type":"Point"}
}