{
  "type": "Feature",
  "properties": {
    "addr:full":"Rue De L'ath\u00c9n\u00c9e 56 Soumagne Li\u00e8ge 4630",
    "addr:housenumber":"56",
    "addr:postcode":"4630",
    "addr:street":"Rue De L'Athe \u0301Ne\u0301E",
    "iso:country":"BE",
    "sg:address":"Rue De L'ath\u00c9n\u00c9e 56",
    "sg:city":"Soumagne",
    "sg:orig_category":"Parfumeries",
    "sg:phone":"+32 4 377 30 93",
    "sg:postcode":"4630",
    "sg:province":"Li\u00e8ge",
    "wof:name":"Jean-pierre Boudry",
    "wof:placetype":"venue"
},
  "geometry": {"coordinates":[5.7330889702,50.6261711121],"type":"Point"}
}