{
  "type": "Feature",
  "properties": {
    "iso:country":"BE",
    "sg:address":"Deken Adamsstraat 14",
    "sg:city":"Turnhout",
    "sg:classifiers":[
        {
            "category":"Professional",
            "subcategory":"Engineering",
            "type":"Services"
        }
    ],
    "sg:phone":"+32 14 42 85 69",
    "sg:postcode":"2300",
    "sg:province":"Antwerpen",
    "sg:tags":[
        "-"
    ],
    "wof:name":"Van Hoorickx Studiebureau Bvba",
    "wof:placetype":"venue"
},
  "geometry": {"coordinates":[4.9461312294,51.3206291199],"type":"Point"}
}