{
  "type": "Feature",
  "properties": {
    "iso:country":"BE",
    "sg:address":"Eug\u00c8ne Gilbertstraat 4",
    "sg:city":"Leuven",
    "sg:orig_category":"Avocats and conseillers juridiques",
    "sg:phone":"+32 16 22 23 76",
    "sg:postcode":"3000",
    "sg:province":"Vlaams-Brabant",
    "wof:name":"Peter Van Breusegem",
    "wof:placetype":"venue"
},
  "geometry": {"coordinates":[4.6997709274,50.8698501587],"type":"Point"}
}