{
  "type": "Feature",
  "properties": {
    "addr:full":"Oude Kortrijkstraat 87 Zonnebeke (geluveld) West-Vlaanderen 8980",
    "addr:housenumber":"87",
    "addr:postcode":"8980",
    "addr:street":"Oude Kortrijkstraat",
    "iso:country":"BE",
    "sg:address":"Oude Kortrijkstraat 87",
    "sg:city":"Zonnebeke (geluveld)",
    "sg:classifiers":[
        {
            "category":"Farming",
            "subcategory":"Livestock Farm",
            "type":"Manufacturing & Wholesale Goods"
        }
    ],
    "sg:phone":"+32 57 46 73 68",
    "sg:postcode":"8980",
    "sg:province":"West-Vlaanderen",
    "sg:tags":[
        "buyer"
    ],
    "wof:name":"Fogeva",
    "wof:placetype":"venue"
},
  "geometry": {"coordinates":[2.9872100353,50.8487968445],"type":"Point"}
}