{
  "type": "Feature",
  "properties": {
    "addr:full":"Avenue Des Statuaires 88 Ukkel/uccle Bruxelles-Capitale 1180",
    "addr:housenumber":"88",
    "addr:postcode":"1180",
    "addr:street":"Avenue Des Statuaires;/",
    "iso:country":"BE",
    "sg:address":"Avenue Des Statuaires 88",
    "sg:city":"Ukkel/uccle",
    "sg:orig_category":"Plantes and fleurs Fruits and l\u00e9gumes Jardinage",
    "sg:phone":"+32 2 374 68 34",
    "sg:postcode":"1180",
    "sg:province":"Bruxelles-Capitale",
    "wof:name":"Observatoire (horticole De L')",
    "wof:placetype":"venue"
},
  "geometry": {"coordinates":[4.3542451859,50.7992935181],"type":"Point"}
}