{
  "type": "Feature",
  "properties": {
    "addr:full":"Gaston Biernauxstraat 14 Jette Bruxelles-Capitale 1090",
    "addr:housenumber":"14",
    "addr:postcode":"1090",
    "addr:street":"Gaston Biernauxstraat",
    "iso:country":"BE",
    "sg:address":"Gaston Biernauxstraat 14",
    "sg:city":"Jette",
    "sg:orig_category":"Kapsalons",
    "sg:phone":"+32 2 428 01 74",
    "sg:postcode":"1090",
    "sg:province":"Bruxelles-Capitale",
    "wof:name":"Coiffure Vogue",
    "wof:placetype":"venue"
},
  "geometry": {"coordinates":[4.320909977,50.8797683716],"type":"Point"}
}