{
  "type": "Feature",
  "properties": {
    "iso:country":"BE",
    "sg:address":"Place Mar\u00c9chal Foch 1",
    "sg:city":"Liege-centre",
    "sg:orig_category":"Boekhandels CD's, cassettes and platen Microsoft",
    "sg:phone":"+32 4 232 71 49",
    "sg:postcode":"4000",
    "sg:province":"Li\u00e8ge",
    "wof:name":"Fnac Li\u00c8ge",
    "wof:placetype":"venue"
},
  "geometry": {"coordinates":[6.2250900269,44.0888595581],"type":"Point"}
}