{
  "type": "Feature",
  "properties": {
    "addr:full":"Avenue Du Ch\u00e2teau 31 Brugelette (attre) Hainaut 7941",
    "addr:housenumber":"31",
    "addr:postcode":"7941",
    "addr:street":"Avenue Du Cha\u0302Teau",
    "iso:country":"BE",
    "sg:address":"Avenue Du Ch\u00e2teau 31",
    "sg:city":"Brugelette (attre)",
    "sg:classifiers":[
        {
            "category":"Fast Food",
            "type":"Food & Drink"
        }
    ],
    "sg:phone":"+32 68 45 53 58",
    "sg:postcode":"7941",
    "sg:province":"Hainaut",
    "sg:tags":[
        "fried",
        "stand",
        "potato"
    ],
    "wof:name":"Chez Pat & Ben",
    "wof:placetype":"venue"
},
  "geometry": {"coordinates":[3.8416099548,50.6104316711],"type":"Point"}
}