{
  "type": "Feature",
  "properties": {
    "addr:full":"Leopold Iii-laan 12-2c Oostende West-Vlaanderen 8400",
    "addr:housenumber":"12-2c",
    "addr:postcode":"8400",
    "addr:street":"Leopold Iii-Laan",
    "iso:country":"BE",
    "sg:address":"Leopold Iii-laan 12-2c",
    "sg:city":"Oostende",
    "sg:classifiers":[
        {
            "category":"Shopping",
            "subcategory":"Gifts & Souvenirs",
            "type":"Retail Goods"
        }
    ],
    "sg:phone":"+32 59 50 27 63",
    "sg:postcode":"8400",
    "sg:province":"West-Vlaanderen",
    "wof:name":"Kermans",
    "wof:placetype":"venue"
},
  "geometry": {"coordinates":[2.9208080769,51.2262992859],"type":"Point"}
}