{
  "type": "Feature",
  "properties": {
    "iso:country":"BE",
    "sg:address":"Morenhoekstraat 19",
    "sg:city":"Rumst",
    "sg:orig_category":"Producteurs de l\u00e9gumes",
    "sg:phone":"+32 15 31 05 97",
    "sg:postcode":"2840",
    "sg:province":"Antwerpen",
    "wof:name":"Josephus Weckhuysen",
    "wof:placetype":"venue"
},
  "geometry": {"coordinates":[4.4459757805,51.0887985229],"type":"Point"}
}