{
  "type": "Feature",
  "properties": {
    "addr:full":"Steenweg 109 Alken Limburg 3570",
    "addr:housenumber":"109",
    "addr:postcode":"3570",
    "addr:street":"Steenweg",
    "iso:country":"BE",
    "sg:address":"Steenweg 109",
    "sg:city":"Alken",
    "sg:orig_category":"Betonnen bouwelementen Fab Bouwmaterialen Gh",
    "sg:phone":"+32 11 31 20 47",
    "sg:postcode":"3570",
    "sg:province":"Limburg",
    "wof:name":"Max Pels",
    "wof:placetype":"venue"
},
  "geometry": {"coordinates":[5.2918357849,50.8898048401],"type":"Point"}
}