{
  "type": "Feature",
  "properties": {
    "addr:full":"H. Torleylaan 16 Beersel (huizingen) Vlaams-Brabant 1654",
    "addr:housenumber":"16",
    "addr:postcode":"1654",
    "addr:street":"Torleylaan",
    "iso:country":"BE",
    "sg:address":"H. Torleylaan 16",
    "sg:city":"Beersel (huizingen)",
    "sg:classifiers":[
        {
            "category":"Professional",
            "subcategory":"Computer Services",
            "type":"Services"
        }
    ],
    "sg:phone":"+32 2 305 94 32",
    "sg:postcode":"1654",
    "sg:province":"Vlaams-Brabant",
    "sg:tags":[
        "-",
        "processing",
        "data",
        "software"
    ],
    "wof:name":"Computer Service & Consultancy",
    "wof:placetype":"venue"
},
  "geometry": {"coordinates":[4.2750711441,50.7470932007],"type":"Point"}
}