{
  "type": "Feature",
  "properties": {
    "addr:full":"Rue Du Bord De L'eau 250 Andenne Namur 5300",
    "addr:housenumber":"250",
    "addr:postcode":"5300",
    "addr:street":"Rue Du Bord De L'Eau",
    "iso:country":"BE",
    "sg:address":"Rue Du Bord De L'eau 250",
    "sg:city":"Andenne",
    "sg:orig_category":"Epiceries",
    "sg:phone":"+32 81 58 82 97",
    "sg:postcode":"5300",
    "sg:province":"Namur",
    "wof:name":"Delory Smits",
    "wof:placetype":"venue"
},
  "geometry": {"coordinates":[5.029323101,50.4916610718],"type":"Point"}
}