{
  "type": "Feature",
  "properties": {
    "iso:country":"BE",
    "sg:address":"Rue Basse Henne 47",
    "sg:city":"Chaudfontaine (vaux-sous-ch\u00e8vremont)",
    "sg:classifiers":[
        {
            "category":"Health Services",
            "subcategory":"Doctor",
            "type":"Services"
        }
    ],
    "sg:phone":"+32 4 361 10 24",
    "sg:postcode":"4051",
    "sg:province":"Li\u00e8ge",
    "sg:tags":[
        "medicinephysicians",
        "surgeon"
    ],
    "wof:name":"Delwaide J",
    "wof:placetype":"venue"
},
  "geometry": {"coordinates":[5.6299161911,50.6007423401],"type":"Point"}
}