{
  "type": "Feature",
  "properties": {
    "addr:full":"Rue Pont L\u00c9opold 13 Verviers Li\u00e8ge 4800",
    "addr:housenumber":"13",
    "addr:postcode":"4800",
    "addr:street":"Rue Pont Le\u0301Opold",
    "iso:country":"BE",
    "sg:address":"Rue Pont L\u00c9opold 13",
    "sg:city":"Verviers",
    "sg:orig_category":"Technische and wetenschappelijke instrumenten Fab",
    "sg:phone":"+32 87 34 08 30",
    "sg:postcode":"4800",
    "sg:province":"Li\u00e8ge",
    "wof:name":"Aquatel",
    "wof:placetype":"venue"
},
  "geometry": {"coordinates":[5.8474822044,50.5950775146],"type":"Point"}
}