{
  "type": "Feature",
  "properties": {
    "addr:full":"Chauss\u00c9e Paul Houtart 270 La Louviere Hainaut 7110",
    "addr:housenumber":"270",
    "addr:postcode":"7110",
    "addr:street":"Chausse\u0301E Paul Houtart",
    "iso:country":"BE",
    "sg:address":"Chauss\u00c9e Paul Houtart 270",
    "sg:city":"La Louviere",
    "sg:orig_category":"M\u00e9decins and sp\u00e9cialistes",
    "sg:phone":"+32 64 22 52 49",
    "sg:postcode":"7110",
    "sg:province":"Hainaut",
    "wof:name":"Marie-louise Sevrin",
    "wof:placetype":"venue"
},
  "geometry": {"coordinates":[4.1580758095,50.486541748],"type":"Point"}
}