{
  "type": "Feature",
  "properties": {
    "iso:country":"BE",
    "sg:address":"Schapendries 9",
    "sg:city":"Wommelgem",
    "sg:classifiers":[
        {
            "category":"Structure",
            "subcategory":"Office Building",
            "type":"Public Place"
        }
    ],
    "sg:phone":"+32 3 353 26 41",
    "sg:postcode":"2160",
    "sg:province":"Antwerpen",
    "sg:tags":[
        "roofing",
        "slate"
    ],
    "wof:name":"Algemene Dakwerken Paul Aerden",
    "wof:placetype":"venue"
},
  "geometry": {"coordinates":[4.5225038528,51.1969680786],"type":"Point"}
}