{
  "type": "Feature",
  "properties": {
    "iso:country":"BE",
    "sg:address":"Leguit 21",
    "sg:city":"Antwerpen",
    "sg:orig_category":"Activit\u00e9s diverses d'imprimerie",
    "sg:phone":"+32 3 226 59 25",
    "sg:postcode":"2000",
    "sg:province":"Antwerpen",
    "wof:name":"Vos Pleun Ontwerp",
    "wof:placetype":"venue"
},
  "geometry": {"coordinates":[4.4035549164,51.2257232666],"type":"Point"}
}