{
  "type": "Feature",
  "properties": {
    "iso:country":"BE",
    "sg:address":"Rue Cocher 2",
    "sg:city":"Grez-doiceau",
    "sg:classifiers":[
        {
            "category":"Communications",
            "subcategory":"Television Station",
            "type":"Services"
        }
    ],
    "sg:phone":"+32 10 84 62 31",
    "sg:postcode":"1390",
    "sg:province":"Brabant Wallon",
    "sg:tags":[
        "organ"
    ],
    "wof:name":"De Grunne T",
    "wof:placetype":"venue"
},
  "geometry": {"coordinates":[4.7200322151,50.7213478088],"type":"Point"}
}