{
  "type": "Feature",
  "properties": {
    "iso:country":"BE",
    "sg:address":"Vijfhoek 12",
    "sg:city":"Mechelen",
    "sg:classifiers":[
        {
            "category":"Shopping",
            "subcategory":"Optician",
            "type":"Retail Goods"
        }
    ],
    "sg:phone":"+32 15 41 45 67",
    "sg:postcode":"2800",
    "sg:province":"Antwerpen",
    "sg:tags":[
        "-"
    ],
    "wof:name":"Fleeracker",
    "wof:placetype":"venue"
},
  "geometry": {"coordinates":[4.4819808006,51.0225944519],"type":"Point"}
}