{
  "type": "Feature",
  "properties": {
    "iso:country":"BE",
    "sg:address":"Place Ernest Dubois 4a",
    "sg:city":"Grez-doiceau",
    "sg:classifiers":[
        {
            "category":"Professional",
            "subcategory":"Art Services",
            "type":"Services"
        }
    ],
    "sg:phone":"+32 10 84 32 74",
    "sg:postcode":"1390",
    "sg:province":"Brabant Wallon",
    "sg:tags":[
        "photographer"
    ],
    "wof:name":"Grez Photo",
    "wof:placetype":"venue"
},
  "geometry": {"coordinates":[4.6958250999,50.7385177612],"type":"Point"}
}