{
  "type": "Feature",
  "properties": {
    "addr:full":"Rue Wauters 67 Chapelle-lez-herlaimont Hainaut 7160",
    "addr:housenumber":"67",
    "addr:postcode":"7160",
    "addr:street":"Rue Wauters",
    "iso:country":"BE",
    "sg:address":"Rue Wauters 67",
    "sg:city":"Chapelle-lez-herlaimont",
    "sg:classifiers":[
        {
            "category":"Insurance",
            "subcategory":"Life Insurance",
            "type":"Services"
        }
    ],
    "sg:phone":"+32 64 45 19 88",
    "sg:postcode":"7160",
    "sg:province":"Hainaut",
    "sg:tags":[
        "assurance"
    ],
    "wof:name":"V. Popadinec",
    "wof:placetype":"venue"
},
  "geometry": {"coordinates":[4.2829709053,50.4752044678],"type":"Point"}
}