{
  "type": "Feature",
  "properties": {
    "addr:full":"Sint-truidersteenweg 296 Hasselt Limburg 3500",
    "addr:housenumber":"296",
    "addr:postcode":"3500",
    "addr:street":"Sint-Truidersteenweg",
    "iso:country":"BE",
    "sg:address":"Sint-truidersteenweg 296",
    "sg:city":"Hasselt",
    "sg:orig_category":"Non-Classified Establishments",
    "sg:phone":"+32 11 28 98 11",
    "sg:postcode":"3500",
    "sg:province":"Limburg",
    "wof:name":"Recor Nv",
    "wof:placetype":"venue"
},
  "geometry": {"coordinates":[5.3256449699,50.9163093567],"type":"Point"}
}