{
  "type": "Feature",
  "properties": {
    "iso:country":"BE",
    "sg:address":"Wijnheuvelenstraat 134",
    "sg:city":"Schaarbeek/schaerbeek",
    "sg:orig_category":"Boekhouders",
    "sg:phone":"+32 2 216 04 24",
    "sg:postcode":"1030",
    "sg:province":"Bruxelles-Capitale",
    "wof:name":"Abdelmajid El Khalidy",
    "wof:placetype":"venue"
},
  "geometry": {"coordinates":[4.3766260147,50.8581237793],"type":"Point"}
}