{
  "type": "Feature",
  "properties": {
    "iso:country":"BE",
    "sg:address":"Van Den Nestlaan 63",
    "sg:city":"Ranst (broechem)",
    "sg:classifiers":[
        {
            "category":"Health Services",
            "subcategory":"Health Practitioner",
            "type":"Services"
        }
    ],
    "sg:phone":"+32 3 475 95 99",
    "sg:postcode":"2520",
    "sg:province":"Antwerpen",
    "sg:tags":[
        "physiotherapist"
    ],
    "wof:name":"Dierckx Raf",
    "wof:placetype":"venue"
},
  "geometry": {"coordinates":[4.5856308937,51.1792793274],"type":"Point"}
}