{
  "type": "Feature",
  "properties": {
    "iso:country":"BE",
    "sg:address":"Rue De Lo\u00cbn 30",
    "sg:city":"Vise",
    "sg:classifiers":[
        {
            "category":"Professional",
            "subcategory":"Accounting & Tax Preparation",
            "type":"Services"
        }
    ],
    "sg:phone":"+32 4 379 36 37",
    "sg:postcode":"4600",
    "sg:province":"Li\u00e8ge",
    "sg:tags":[
        "accountant"
    ],
    "wof:name":"Joseph Dejardin",
    "wof:placetype":"venue"
},
  "geometry": {"coordinates":[5.6630749702,50.7579116821],"type":"Point"}
}