{
  "type": "Feature",
  "properties": {
    "addr:full":"Goedlevenstraat 101 Gent Oost-Vlaanderen 9041",
    "addr:housenumber":"101",
    "addr:postcode":"9041",
    "addr:street":"Goedlevenstraat;Oost-Vlaanderen",
    "iso:country":"BE",
    "sg:address":"Goedlevenstraat 101",
    "sg:city":"Gent",
    "sg:classifiers":[
        {
            "category":"Cafe",
            "type":"Food & Drink"
        }
    ],
    "sg:phone":"+32 9 251 31 40",
    "sg:postcode":"9041",
    "sg:province":"Oost-Vlaanderen",
    "sg:tags":[
        "caf\u00e9s"
    ],
    "wof:name":"Caf\u00c9 Het Witte Paard",
    "wof:placetype":"venue"
},
  "geometry": {"coordinates":[3.7669110298,51.0772323608],"type":"Point"}
}