{
  "type": "Feature",
  "properties": {
    "addr:full":"Appelstraat 3 Tielt West-Vlaanderen 8700",
    "addr:housenumber":"3",
    "addr:postcode":"8700",
    "addr:street":"Appelstraat",
    "iso:country":"BE",
    "sg:address":"Appelstraat 3",
    "sg:city":"Tielt",
    "sg:orig_category":"Eleveurs and marchands de porcs. Eleveurs de bovins",
    "sg:phone":"+32 51 63 40 42",
    "sg:postcode":"8700",
    "sg:province":"West-Vlaanderen",
    "wof:name":"Frans Verbrugge",
    "wof:placetype":"venue"
},
  "geometry": {"coordinates":[3.4139869213,50.9843978882],"type":"Point"}
}