{
  "type": "Feature",
  "properties": {
    "addr:full":"Kluizendijkstraat 60 Sint-gillis-waas Oost-Vlaanderen 9170",
    "addr:housenumber":"60",
    "addr:postcode":"9170",
    "addr:street":"Kluizendijkstraat",
    "iso:country":"BE",
    "sg:address":"Kluizendijkstraat 60",
    "sg:city":"Sint-gillis-waas",
    "sg:orig_category":"Brood, gebak and snoepgoed",
    "sg:phone":"+32 3 770 56 30",
    "sg:postcode":"9170",
    "sg:province":"Oost-Vlaanderen",
    "wof:name":"Bakkerij Van Duyse",
    "wof:placetype":"venue"
},
  "geometry": {"coordinates":[4.1018300056,51.2335281372],"type":"Point"}
}