{
  "type": "Feature",
  "properties": {
    "iso:country":"BE",
    "sg:address":"Koningin Astrid Plein 25",
    "sg:city":"Jette/jette",
    "sg:classifiers":[
        {
            "category":"Cafe",
            "type":"Food & Drink"
        }
    ],
    "sg:phone":"+32 2 424 10 20",
    "sg:postcode":"1090",
    "sg:province":"Bruxelles-Capitale",
    "sg:tags":[
        "caf\u00e9s"
    ],
    "wof:name":"Caf\u00c9 Baudouin",
    "wof:placetype":"venue"
},
  "geometry": {"coordinates":[4.3236608505,50.872882843],"type":"Point"}
}