{
  "type": "Feature",
  "properties": {
    "iso:country":"BE",
    "sg:address":"Chauss\u00c9e De Mariemont 18",
    "sg:city":"Morlanwelz",
    "sg:orig_category":"Artsen and specialisten",
    "sg:phone":"+32 64 45 15 66",
    "sg:postcode":"7140",
    "sg:province":"Hainaut",
    "wof:name":"P. Caise",
    "wof:placetype":"venue"
},
  "geometry": {"coordinates":[4.2347760201,50.4554824829],"type":"Point"}
}