{
  "type": "Feature",
  "properties": {
    "addr:full":"Chauss\u00e9e Du Roi Albert 3b Ans (loncin) Li\u00e8ge 4431",
    "addr:housenumber":"3b",
    "addr:postcode":"4431",
    "addr:street":"Chausse\u0301E Du Roi Albert",
    "iso:country":"BE",
    "sg:address":"Chauss\u00e9e Du Roi Albert 3b",
    "sg:city":"Ans (loncin)",
    "sg:classifiers":[
        {
            "category":"Personal",
            "subcategory":"Beauty Salon",
            "type":"Services"
        }
    ],
    "sg:phone":"+32 4 263 40 46",
    "sg:postcode":"4431",
    "sg:province":"Li\u00e8ge",
    "sg:tags":[
        "lady",
        "-",
        "hairdressing"
    ],
    "wof:name":"Selec-tif Coiffure",
    "wof:placetype":"venue"
},
  "geometry": {"coordinates":[5.5056052208,50.66614151],"type":"Point"}
}