{
  "type": "Feature",
  "properties": {
    "addr:full":"Heldergemstraat 143 Haaltert (heldergem) Oost-Vlaanderen 9450",
    "addr:housenumber":"143",
    "addr:postcode":"9450",
    "addr:street":"Heldergemstraat",
    "iso:country":"BE",
    "sg:address":"Heldergemstraat 143",
    "sg:city":"Haaltert (heldergem)",
    "sg:classifiers":[
        {
            "category":"Professional",
            "subcategory":"Accounting & Tax Preparation",
            "type":"Services"
        }
    ],
    "sg:phone":"+32 53 62 88 83",
    "sg:postcode":"9450",
    "sg:province":"Oost-Vlaanderen",
    "sg:tags":[
        "bookkeeper"
    ],
    "wof:name":"Haelterman E",
    "wof:placetype":"venue"
},
  "geometry": {"coordinates":[3.9554479122,50.879447937],"type":"Point"}
}