{
  "type": "Feature",
  "properties": {
    "iso:country":"BE",
    "sg:address":"L\u00c9opold Sturbautstraat 11",
    "sg:city":"Ronse/renaix",
    "sg:orig_category":"Dranken",
    "sg:phone":"+32 55 23 92 32",
    "sg:postcode":"9600",
    "sg:province":"Oost-Vlaanderen",
    "wof:name":"Luc De Smet",
    "wof:placetype":"venue"
},
  "geometry": {"coordinates":[3.5968470573,50.7422294617],"type":"Point"}
}