{
  "type": "Feature",
  "properties": {
    "addr:full":"Peter Benoitlaan 15 Leuven (kessel-lo) Vlaams-Brabant 3010",
    "addr:housenumber":"15",
    "addr:postcode":"3010",
    "addr:street":"Peter Benoitlaan",
    "iso:country":"BE",
    "sg:address":"Peter Benoitlaan 15",
    "sg:city":"Leuven (kessel-lo)",
    "sg:orig_category":"Non-Classified Establishments",
    "sg:phone":"+32 16 25 35 16",
    "sg:postcode":"3010",
    "sg:province":"Vlaams-Brabant",
    "wof:name":"Alpam Bvba",
    "wof:placetype":"venue"
},
  "geometry": {"coordinates":[4.7227768898,50.8754234314],"type":"Point"}
}