{
  "type": "Feature",
  "properties": {
    "iso:country":"BE",
    "sg:address":"Rue Wagner 93",
    "sg:city":"Boncelles",
    "sg:classifiers":[
        {
            "category":"Professional",
            "subcategory":"Computer Services",
            "type":"Services"
        }
    ],
    "sg:phone":"+32 4 338 03 68",
    "sg:postcode":"4100",
    "sg:province":"Li\u00e8ge",
    "sg:tags":[
        "development",
        "software"
    ],
    "wof:name":"Manex S.p.r.l.",
    "wof:placetype":"venue"
},
  "geometry": {"coordinates":[5.5389099121,50.5679893494],"type":"Point"}
}