{
  "type": "Feature",
  "properties": {
    "iso:country":"BE",
    "sg:address":"Guldendelle 20",
    "sg:city":"Zaventem (nossegem)",
    "sg:classifiers":[
        {
            "category":"Building & Trades",
            "subcategory":"Landscaping Services",
            "type":"Services"
        }
    ],
    "sg:phone":"+32 2 759 44 33",
    "sg:postcode":"1930",
    "sg:province":"Vlaams-Brabant",
    "sg:tags":[
        "gardening",
        "garden",
        "maintenance"
    ],
    "wof:name":"Wauters Alain Bvba",
    "wof:placetype":"venue"
},
  "geometry": {"coordinates":[4.5105957985,50.8824539185],"type":"Point"}
}