{
  "type": "Feature",
  "properties": {
    "addr:full":"Rue Vanderborght 66 Bruxelles (jette) Bruxelles-Capitale 1090",
    "addr:housenumber":"66",
    "addr:postcode":"1090",
    "addr:street":"Rue Vanderborght",
    "iso:country":"BE",
    "sg:address":"Rue Vanderborght 66",
    "sg:city":"Bruxelles (jette)",
    "sg:classifiers":[
        {
            "category":"Food & Beverages",
            "subcategory":"Groceries & Convenience Stores",
            "type":"Retail Goods"
        }
    ],
    "sg:phone":"+32 2 426 32 88",
    "sg:postcode":"1090",
    "sg:province":"Bruxelles-Capitale",
    "sg:tags":[
        "grocer"
    ],
    "wof:name":"Van De Velde D",
    "wof:placetype":"venue"
},
  "geometry": {"coordinates":[4.3251299858,50.8676986694],"type":"Point"}
}