{
  "type": "Feature",
  "properties": {
    "addr:full":"Diestsesteenweg 111-113 Leuven (kessel-lo) Vlaams-Brabant 3010",
    "addr:housenumber":"111-113",
    "addr:postcode":"3010",
    "addr:street":"Diestsesteenweg",
    "iso:country":"BE",
    "sg:address":"Diestsesteenweg 111-113",
    "sg:city":"Leuven (kessel-lo)",
    "sg:classifiers":[
        {
            "category":"Building & Trades",
            "subcategory":"Construction",
            "type":"Services"
        }
    ],
    "sg:phone":"+32 16 25 59 22",
    "sg:postcode":"3010",
    "sg:province":"Vlaams-Brabant",
    "sg:tags":[
        "glazier"
    ],
    "wof:name":"Vloebergs Bvba",
    "wof:placetype":"venue"
},
  "geometry": {"coordinates":[4.7101149559,50.8854637146],"type":"Point"}
}