{
  "type": "Feature",
  "properties": {
    "iso:country":"BE",
    "sg:address":"Blarenberglaan 21",
    "sg:city":"Mechelen",
    "sg:classifiers":[
        {
            "category":"Manufacturing",
            "subcategory":"Food",
            "type":"Manufacturing & Wholesale Goods"
        }
    ],
    "sg:phone":"+32 15 29 49 50",
    "sg:postcode":"2800",
    "sg:province":"Antwerpen",
    "sg:tags":[
        "industry",
        "-",
        "ingredient"
    ],
    "wof:name":"Internatio Sa",
    "wof:placetype":"venue"
},
  "geometry": {"coordinates":[4.4509840012,51.0521621704],"type":"Point"}
}