{
  "type": "Feature",
  "properties": {
    "addr:full":"Palais Des Congres De Liege Liege Li\u00e8ge 4020",
    "addr:postcode":"4020",
    "iso:country":"BE",
    "sg:address":"Palais Des Congres De Liege",
    "sg:city":"Liege",
    "sg:classifiers":[
        {
            "category":"Shopping",
            "subcategory":"Computers & Home Electronics",
            "type":"Retail Goods"
        }
    ],
    "sg:phone":"+32 4 343 92 92",
    "sg:postcode":"4020",
    "sg:province":"Li\u00e8ge",
    "sg:tags":[
        "chamber",
        "commerce"
    ],
    "wof:name":"Liege Chamber Of Commerce And Industry",
    "wof:placetype":"venue"
},
  "geometry": {"coordinates":[5.6203680038,50.643661499],"type":"Point"}
}