{
  "type": "Feature",
  "properties": {
    "iso:country":"BE",
    "sg:address":"August Vermeylenlaan 21",
    "sg:city":"Torhout",
    "sg:orig_category":"Art and fournitures artistiques",
    "sg:phone":"+32 50 21 51 60",
    "sg:postcode":"8820",
    "sg:province":"West-Vlaanderen",
    "wof:name":"Fa. Annicart",
    "wof:placetype":"venue"
},
  "geometry": {"coordinates":[3.1091930866,51.0627288818],"type":"Point"}
}