{
  "type": "Feature",
  "properties": {
    "iso:country":"BE",
    "sg:address":"Violettestraat 1",
    "sg:city":"Aalst",
    "sg:classifiers":[
        {
            "category":"Autos & Motor Vehicles",
            "subcategory":"Auto Supplies",
            "type":"Retail Goods"
        }
    ],
    "sg:phone":"+32 53 77 97 58",
    "sg:postcode":"9300",
    "sg:province":"Oost-Vlaanderen",
    "sg:tags":[
        "access",
        "automobile",
        "part",
        "-"
    ],
    "wof:name":"Autoparts Luc",
    "wof:placetype":"venue"
},
  "geometry": {"coordinates":[4.044315815,50.9434890747],"type":"Point"}
}