{
  "type": "Feature",
  "properties": {
    "iso:country":"BE",
    "sg:address":"Place Masson 4",
    "sg:city":"Honnelles (montignies-sur-roc)",
    "sg:classifiers":[
        {
            "category":"Education",
            "subcategory":"School",
            "type":"Public Place"
        }
    ],
    "sg:phone":"+32 65 75 96 37",
    "sg:postcode":"7387",
    "sg:province":"Hainaut",
    "sg:tags":[
        "primary"
    ],
    "wof:name":"Ecole Communale De Montignies-sur-roc",
    "wof:placetype":"venue"
},
  "geometry": {"coordinates":[3.734513998,50.3687019348],"type":"Point"}
}