{
  "type": "Feature",
  "properties": {
    "addr:full":"Chauss\u00e9e D'asse 126 Enghien (petit-enghien) Hainaut 7850",
    "addr:housenumber":"126",
    "addr:postcode":"7850",
    "addr:street":"Chausse\u0301E D'Asse",
    "iso:country":"BE",
    "sg:address":"Chauss\u00e9e D'asse 126",
    "sg:city":"Enghien (petit-enghien)",
    "sg:classifiers":[
        {
            "category":"Autos & Motor Vehicles",
            "subcategory":"Automobile Sales",
            "type":"Retail Goods"
        }
    ],
    "sg:phone":"+32 2 395 39 70",
    "sg:postcode":"7850",
    "sg:province":"Hainaut",
    "sg:tags":[
        "distributor",
        "independent",
        "-"
    ],
    "wof:name":"Ford-botman",
    "wof:placetype":"venue"
},
  "geometry": {"coordinates":[4.0529770851,50.6991348267],"type":"Point"}
}