{
  "type": "Feature",
  "properties": {
    "addr:full":"Kruisbaan 3 B102 Mechelen Antwerpen 2800",
    "addr:housenumber":"3 b102",
    "addr:postcode":"2800",
    "addr:street":"Kruisbaan",
    "iso:country":"BE",
    "sg:address":"Kruisbaan 3 B102",
    "sg:city":"Mechelen",
    "sg:orig_category":"Software ontwikkeling and ontwerp",
    "sg:phone":"+32 15 28 56 50",
    "sg:postcode":"2800",
    "sg:province":"Antwerpen",
    "wof:name":"Graitec Benelux",
    "wof:placetype":"venue"
},
  "geometry": {"coordinates":[4.4854397774,51.0289268494],"type":"Point"}
}