{
  "type": "Feature",
  "properties": {
    "iso:country":"BE",
    "sg:address":"Rue Paul Janson 2",
    "sg:city":"Amay",
    "sg:classifiers":[
        {
            "category":"Bars & Pubs",
            "type":"Food & Drink"
        }
    ],
    "sg:phone":"+32 85 31 18 52",
    "sg:postcode":"4540",
    "sg:province":"Li\u00e8ge",
    "wof:name":"Bl\u00e9s D'or (aux)",
    "wof:placetype":"venue"
},
  "geometry": {"coordinates":[5.3173851967,50.5482635498],"type":"Point"}
}