{
  "type": "Feature",
  "properties": {
    "addr:full":"Rue Du Vallon 81 Rixensart Brabant Wallon 1332",
    "addr:housenumber":"81",
    "addr:postcode":"1332",
    "addr:street":"Rue Du Vallon;Wallon",
    "iso:country":"BE",
    "sg:address":"Rue Du Vallon 81",
    "sg:city":"Rixensart",
    "sg:orig_category":"Artsen and specialisten",
    "sg:phone":"+32 2 654 14 87",
    "sg:postcode":"1332",
    "sg:province":"Brabant Wallon",
    "wof:name":"G. Belinne",
    "wof:placetype":"venue"
},
  "geometry": {"coordinates":[4.5056958199,50.7217636108],"type":"Point"}
}