{
  "type": "Feature",
  "properties": {
    "addr:full":"Chauss\u00e9e De Marche 878 Namur (jambes) Namur 5100",
    "addr:housenumber":"878",
    "addr:postcode":"5100",
    "addr:street":"Chausse\u0301E De Marche",
    "iso:country":"BE",
    "sg:address":"Chauss\u00e9e De Marche 878",
    "sg:city":"Namur (jambes)",
    "sg:classifiers":[
        {
            "category":"Home & Garden",
            "subcategory":"Home Furnishings",
            "type":"Retail Goods"
        }
    ],
    "sg:phone":"+32 81 40 32 31",
    "sg:postcode":"5100",
    "sg:province":"Namur",
    "sg:tags":[
        "-",
        "furniture"
    ],
    "wof:name":"Meubles Superstar Sprl",
    "wof:placetype":"venue"
},
  "geometry": {"coordinates":[4.8713750839,50.4566345215],"type":"Point"}
}