{
  "type": "Feature",
  "properties": {
    "addr:full":"Hasseltsesteenweg 10 Beringen Limburg 3580",
    "addr:housenumber":"10",
    "addr:postcode":"3580",
    "addr:street":"Hasseltsesteenweg",
    "iso:country":"BE",
    "sg:address":"Hasseltsesteenweg 10",
    "sg:city":"Beringen",
    "sg:classifiers":[
        {
            "category":"Building & Trades",
            "subcategory":"Plumbing",
            "type":"Services"
        }
    ],
    "sg:phone":"+32 11 43 22 58",
    "sg:postcode":"3580",
    "sg:province":"Limburg",
    "sg:tags":[
        "repair",
        "mainten",
        "-",
        "central",
        "heating"
    ],
    "wof:name":"Oeyen W",
    "wof:placetype":"venue"
},
  "geometry": {"coordinates":[5.2256660461,51.0474472046],"type":"Point"}
}