{
  "type": "Feature",
  "properties": {
    "addr:full":"Berkelei 126 Sint-katelijne-waver Antwerpen 2860",
    "addr:housenumber":"126",
    "addr:postcode":"2860",
    "addr:street":"Berkelei",
    "iso:country":"BE",
    "sg:address":"Berkelei 126",
    "sg:city":"Sint-katelijne-waver",
    "sg:classifiers":[
        {
            "category":"Shopping",
            "subcategory":"Bicycles & Sporting Goods",
            "type":"Retail Goods"
        }
    ],
    "sg:phone":"+32 15 55 81 26",
    "sg:postcode":"2860",
    "sg:province":"Antwerpen",
    "sg:tags":[
        "article",
        "de",
        "sport",
        "camping"
    ],
    "wof:name":"Jorge Biljartkeu's",
    "wof:placetype":"venue"
},
  "geometry": {"coordinates":[4.5174088478,51.0438766479],"type":"Point"}
}