{
  "type": "Feature",
  "properties": {
    "iso:country":"BE",
    "sg:address":"Antwerpsesteenweg 59",
    "sg:city":"Ranst",
    "sg:classifiers":[
        {
            "category":"Restaurant",
            "type":"Food & Drink"
        }
    ],
    "sg:phone":"+32 3 475 19 37",
    "sg:postcode":"2520",
    "sg:province":"Antwerpen",
    "sg:tags":[
        "caf\u00e9s"
    ],
    "wof:name":"Taverne Het Loo",
    "wof:placetype":"venue"
},
  "geometry": {"coordinates":[4.5884141922,51.1849517822],"type":"Point"}
}