{
  "type": "Feature",
  "properties": {
    "addr:full":"Veldstraat 99 Zoersel Antwerpen 2980",
    "addr:housenumber":"99",
    "addr:postcode":"2980",
    "addr:street":"Veldstraat",
    "iso:country":"BE",
    "sg:address":"Veldstraat 99",
    "sg:city":"Zoersel",
    "sg:classifiers":[
        {
            "category":"Arena",
            "subcategory":"Sports Club",
            "type":"Entertainment"
        }
    ],
    "sg:phone":"+32 3 309 18 61",
    "sg:postcode":"2980",
    "sg:province":"Antwerpen",
    "sg:tags":[
        "de"
    ],
    "wof:name":"Karabijnclub De Moedige Schutters Wechelderzande",
    "wof:placetype":"venue"
},
  "geometry": {"coordinates":[4.6953001022,51.2735595703],"type":"Point"}
}