{
  "type": "Feature",
  "properties": {
    "iso:country":"BE",
    "sg:address":"Gentse Baan 55",
    "sg:city":"Sint-niklaas",
    "sg:orig_category":"Voertuigen",
    "sg:phone":"+32 3 776 73 35",
    "sg:postcode":"9100",
    "sg:province":"Oost-Vlaanderen",
    "wof:name":"Hugo Floin",
    "wof:placetype":"venue"
},
  "geometry": {"coordinates":[4.1270198822,51.1495094299],"type":"Point"}
}