{
  "type": "Feature",
  "properties": {
    "addr:full":"Rue Des Buissons 6 Ans (loncin) Li\u00e8ge 4431",
    "addr:housenumber":"6",
    "addr:postcode":"4431",
    "addr:street":"Rue Des Buissons",
    "iso:country":"BE",
    "sg:address":"Rue Des Buissons 6",
    "sg:city":"Ans (loncin)",
    "sg:classifiers":[
        {
            "category":"Health Services",
            "subcategory":"Health Practitioner",
            "type":"Services"
        }
    ],
    "sg:phone":"+32 4 263 42 19",
    "sg:postcode":"4431",
    "sg:province":"Li\u00e8ge",
    "sg:tags":[
        "physiotherapist"
    ],
    "wof:name":"W\u00e9ry D",
    "wof:placetype":"venue"
},
  "geometry": {"coordinates":[5.5008268356,50.6639060974],"type":"Point"}
}