{
  "type": "Feature",
  "properties": {
    "addr:full":"Place Du Rinsdelle 2 Bruxelles (etterbeek) Bruxelles-Capitale 1040",
    "addr:housenumber":"2",
    "addr:postcode":"1040",
    "addr:street":"Place Du Rinsdelle",
    "iso:country":"BE",
    "sg:address":"Place Du Rinsdelle 2",
    "sg:city":"Bruxelles (etterbeek)",
    "sg:classifiers":[
        {
            "category":"Health Services",
            "subcategory":"Nursing And Care Facility",
            "type":"Services"
        }
    ],
    "sg:phone":"+32 2 740 26 10",
    "sg:postcode":"1040",
    "sg:province":"Bruxelles-Capitale",
    "sg:tags":[
        "home",
        "rest"
    ],
    "wof:name":"Rinsdel Sprl",
    "wof:placetype":"venue"
},
  "geometry": {"coordinates":[4.3955101967,50.8343086243],"type":"Point"}
}