{
  "type": "Feature",
  "properties": {
    "iso:country":"BE",
    "sg:address":"Tempelstraat 22",
    "sg:city":"Ieper",
    "sg:classifiers":[
        {
            "category":"Recreation",
            "subcategory":"Dog Park",
            "type":"Entertainment"
        }
    ],
    "sg:phone":"+32 57 20 88 30",
    "sg:postcode":"8900",
    "sg:province":"West-Vlaanderen",
    "sg:tags":[
        "dame",
        "lingerie",
        "v\u00eatements",
        "pour",
        "sous-v\u00eatements"
    ],
    "wof:name":"Huis Papillon",
    "wof:placetype":"venue"
},
  "geometry": {"coordinates":[2.8814840317,50.8494606018],"type":"Point"}
}