{
  "type": "Feature",
  "properties": {
    "addr:full":"Ikaroslaan 73 Zaventem Vlaams-Brabant 1930",
    "addr:housenumber":"73",
    "addr:postcode":"1930",
    "addr:street":"Ikaroslaan",
    "iso:country":"BE",
    "sg:address":"Ikaroslaan 73",
    "sg:city":"Zaventem",
    "sg:classifiers":[
        {
            "category":"Professional",
            "subcategory":"Management & Consulting",
            "type":"Services"
        }
    ],
    "sg:phone":"+32 2 749 94 00",
    "sg:postcode":"1930",
    "sg:province":"Vlaams-Brabant",
    "sg:tags":[
        "-",
        "processing",
        "data",
        "consultant"
    ],
    "wof:name":"Global Continuity",
    "wof:placetype":"venue"
},
  "geometry": {"coordinates":[4.4924879074,50.8773841858],"type":"Point"}
}