{
  "type": "Feature",
  "properties": {
    "addr:full":"Veurnestraat 28 Poperinge West-Vlaanderen 8970",
    "addr:housenumber":"28",
    "addr:postcode":"8970",
    "addr:street":"Veurnestraat",
    "iso:country":"BE",
    "sg:address":"Veurnestraat 28",
    "sg:city":"Poperinge",
    "sg:orig_category":"Journaux. Tabac",
    "sg:phone":"+32 57 33 72 19",
    "sg:postcode":"8970",
    "sg:province":"West-Vlaanderen",
    "wof:name":"Worm-six",
    "wof:placetype":"venue"
},
  "geometry": {"coordinates":[2.7272119522,50.8573493958],"type":"Point"}
}