{
  "type": "Feature",
  "properties": {
    "iso:country":"BE",
    "sg:address":"Rue Albert Ier 33",
    "sg:city":"Erquelinnes",
    "sg:orig_category":"Boucheries",
    "sg:phone":"+32 71 55 55 06",
    "sg:postcode":"6560",
    "sg:province":"Hainaut",
    "wof:name":"Wairy Charles Et Fils",
    "wof:placetype":"venue"
},
  "geometry": {"coordinates":[4.1207499504,50.3097915649],"type":"Point"}
}