{
  "type": "Feature",
  "properties": {
    "iso:country":"BE",
    "sg:address":"Staatsbaan 196",
    "sg:city":"Bekkevoort",
    "sg:orig_category":"Herstellingen and onderhoud van auto's",
    "sg:phone":"+32 13 32 17 06",
    "sg:postcode":"3460",
    "sg:province":"Vlaams-Brabant",
    "wof:name":"Jan Matterne",
    "wof:placetype":"venue"
},
  "geometry": {"coordinates":[4.9663648605,50.9422454834],"type":"Point"}
}