{
  "type": "Feature",
  "properties": {
    "iso:country":"BE",
    "sg:address":"Rue De La Citadelle 37",
    "sg:city":"Hensies (montroeul-sur-haine)",
    "sg:classifiers":[
        {
            "category":"Bars & Pubs",
            "type":"Food & Drink"
        }
    ],
    "sg:phone":"+32 65 45 78 08",
    "sg:postcode":"7350",
    "sg:province":"Hainaut",
    "wof:name":"Amiti\u00e9(de L')",
    "wof:placetype":"venue"
},
  "geometry": {"coordinates":[3.684994936,50.4326210022],"type":"Point"}
}