{
  "type": "Feature",
  "properties": {
    "addr:full":"Gompelbaan 60 Mol Antwerpen 2400",
    "addr:housenumber":"60",
    "addr:postcode":"2400",
    "addr:street":"Gompelbaan",
    "iso:country":"BE",
    "sg:address":"Gompelbaan 60",
    "sg:city":"Mol",
    "sg:orig_category":"Artsen and specialisten",
    "sg:phone":"+32 14 32 00 95",
    "sg:postcode":"2400",
    "sg:province":"Antwerpen",
    "wof:name":"Reinhilde Dirckx",
    "wof:placetype":"venue"
},
  "geometry": {"coordinates":[5.1504178047,51.197265625],"type":"Point"}
}