{
  "type": "Feature",
  "properties": {
    "iso:country":"BE",
    "sg:address":"Boekhoutedorp 12",
    "sg:city":"Assenede",
    "sg:orig_category":"Verplichte sociale verzekeringen",
    "sg:phone":"+32 9 373 81 04",
    "sg:postcode":"9961",
    "sg:province":"Oost-Vlaanderen",
    "wof:name":"Christelijke Mutualiteit",
    "wof:placetype":"venue"
},
  "geometry": {"coordinates":[3.7533829212,51.2274360657],"type":"Point"}
}