{
  "type": "Feature",
  "properties": {
    "iso:country":"BE",
    "sg:address":"Waterwildlaan 9",
    "sg:city":"Watermaal-bosvoorde/watermael-boitsfort",
    "sg:orig_category":"Artsen and specialisten",
    "sg:phone":"+32 2 672 92 05",
    "sg:postcode":"1170",
    "sg:province":"Bruxelles-Capitale",
    "wof:name":"Bernard Gilon",
    "wof:placetype":"venue"
},
  "geometry": {"coordinates":[4.4021902084,50.8103904724],"type":"Point"}
}