{
  "type": "Feature",
  "properties": {
    "addr:full":"Avenue Jean De La Hoese 26 Sint-jans-molenbeek/molenbeek-saint-jean Bruxelles-Capitale 1080",
    "addr:housenumber":"26",
    "addr:postcode":"1080",
    "addr:street":"Avenue Jean De La Hoese",
    "iso:country":"BE",
    "sg:address":"Avenue Jean De La Hoese 26",
    "sg:city":"Sint-jans-molenbeek/molenbeek-saint-jean",
    "sg:orig_category":"Artistes ind\u00e9pendants",
    "sg:phone":"+32 2 414 59 45",
    "sg:postcode":"1080",
    "sg:province":"Bruxelles-Capitale",
    "wof:name":"I. Wellens",
    "wof:placetype":"venue"
},
  "geometry": {"coordinates":[4.3161168098,50.8593101501],"type":"Point"}
}