{
  "type": "Feature",
  "properties": {
    "iso:country":"BE",
    "sg:address":"Hallebaan 152",
    "sg:city":"Malle",
    "sg:orig_category":"Eleveurs de bovins",
    "sg:phone":"+32 3 312 10 69",
    "sg:postcode":"2390",
    "sg:province":"Antwerpen",
    "wof:name":"Carolus De Prins",
    "wof:placetype":"venue"
},
  "geometry": {"coordinates":[4.6787238121,51.281879425],"type":"Point"}
}