{
  "type": "Feature",
  "properties": {
    "iso:country":"BE",
    "sg:address":"Manitobaplein 3",
    "sg:city":"Blankenberge",
    "sg:classifiers":[
        {
            "category":"Fast Food",
            "type":"Food & Drink"
        }
    ],
    "sg:phone":"+32 50 41 18 00",
    "sg:postcode":"8370",
    "sg:province":"West-Vlaanderen",
    "sg:tags":[
        "restaurant",
        "\u00c0",
        "domicile",
        "emporter",
        "livraison",
        "restaurants"
    ],
    "wof:name":"Pizza Club",
    "wof:placetype":"venue"
},
  "geometry": {"coordinates":[3.1279559135,51.3145217896],"type":"Point"}
}