{
  "type": "Feature",
  "properties": {
    "iso:country":"BE",
    "sg:address":"Wontergemstraat 51",
    "sg:city":"Dentergem",
    "sg:orig_category":"Pain, p\u00e2tisseries and confiseries",
    "sg:phone":"+32 51 63 47 23",
    "sg:postcode":"8720",
    "sg:province":"West-Vlaanderen",
    "wof:name":"Yvan Tack",
    "wof:placetype":"venue"
},
  "geometry": {"coordinates":[3.4215500355,50.9640007019],"type":"Point"}
}