{
  "type": "Feature",
  "properties": {
    "iso:country":"BE",
    "sg:address":"Bergstraat",
    "sg:city":"Hoeselt",
    "sg:classifiers":[
        {
            "category":"Arena",
            "subcategory":"Sports Club",
            "type":"Entertainment"
        }
    ],
    "sg:phone":"+32 89 41 31 66",
    "sg:postcode":"3730",
    "sg:province":"Limburg",
    "wof:name":"Hoeselt V V",
    "wof:placetype":"venue"
},
  "geometry": {"coordinates":[5.485929966,50.8530883789],"type":"Point"}
}