{
  "type": "Feature",
  "properties": {
    "addr:full":"Hasseltsesteenweg 65 Sint-truiden Limburg 3800",
    "addr:housenumber":"65",
    "addr:postcode":"3800",
    "addr:street":"Hasseltsesteenweg",
    "iso:country":"BE",
    "sg:address":"Hasseltsesteenweg 65",
    "sg:city":"Sint-truiden",
    "sg:orig_category":"Benzinestations and brandstoffen",
    "sg:phone":"+32 11 68 78 46",
    "sg:postcode":"3800",
    "sg:province":"Limburg",
    "wof:name":"Jet",
    "wof:placetype":"venue"
},
  "geometry": {"coordinates":[5.2017889023,50.82837677],"type":"Point"}
}