{
  "type": "Feature",
  "properties": {
    "iso:country":"BE",
    "sg:address":"Avenue De La Lib\u00e9ration. Dai. 160",
    "sg:city":"Couvin (dailly)",
    "sg:classifiers":[
        {
            "category":"Retail",
            "subcategory":"Auto Repair",
            "type":"Services"
        }
    ],
    "sg:phone":"+32 60 34 42 81",
    "sg:postcode":"5660",
    "sg:province":"Namur",
    "sg:tags":[
        "garage"
    ],
    "wof:name":"Magotteaux L",
    "wof:placetype":"venue"
},
  "geometry": {"coordinates":[4.484940052,50.0546989441],"type":"Point"}
}