{
  "type": "Feature",
  "properties": {
    "addr:full":"Rue De La Gare 4 Heron Li\u00e8ge 4217",
    "addr:housenumber":"4",
    "addr:postcode":"4217",
    "addr:street":"Rue De La Gare;Heron Lie\u0300Ge",
    "iso:country":"BE",
    "sg:address":"Rue De La Gare 4",
    "sg:city":"Heron",
    "sg:classifiers":[
        {
            "category":"Personal",
            "subcategory":"Beauty Salon",
            "type":"Services"
        }
    ],
    "sg:phone":"+32 85 71 25 69",
    "sg:postcode":"4217",
    "sg:province":"Li\u00e8ge",
    "sg:tags":[
        "de",
        "coiffure"
    ],
    "wof:name":"Jo\u00cbl Davin",
    "wof:placetype":"venue"
},
  "geometry": {"coordinates":[5.0947799683,50.5480041504],"type":"Point"}
}