{
  "type": "Feature",
  "properties": {
    "addr:full":"Eksaardedorp 116 Lokeren Oost-Vlaanderen 9160",
    "addr:housenumber":"116",
    "addr:postcode":"9160",
    "addr:street":"Lokeren Oost-Vlaanderen",
    "iso:country":"BE",
    "sg:address":"Eksaardedorp 116",
    "sg:city":"Lokeren",
    "sg:orig_category":"Banques and organismes de cr\u00e9dit",
    "sg:phone":"+32 9 346 82 79",
    "sg:postcode":"9160",
    "sg:province":"Oost-Vlaanderen",
    "wof:name":"Dexia",
    "wof:placetype":"venue"
},
  "geometry": {"coordinates":[3.9604680538,51.1260070801],"type":"Point"}
}