{
  "type": "Feature",
  "properties": {
    "addr:full":"Rue G\u00e9rardrie 9 Li\u00e8ge 1 Li\u00e8ge 4000",
    "addr:housenumber":"9;1",
    "addr:postcode":"4000",
    "addr:street":"Rue Ge\u0301Rardrie",
    "iso:country":"BE",
    "sg:address":"Rue G\u00e9rardrie 9",
    "sg:city":"Li\u00e8ge 1",
    "sg:orig_category":"Ice-cream parlours",
    "sg:phone":"+32 4 223 55 33",
    "sg:postcode":"4000",
    "sg:province":"Li\u00e8ge",
    "wof:name":"Bouquet V\u00e9nitien",
    "wof:placetype":"venue"
},
  "geometry": {"coordinates":[5.5742440224,50.6446800232],"type":"Point"}
}