{
  "type": "Feature",
  "properties": {
    "addr:full":"Rue Aux Terrasses 2ba Amay Li\u00e8ge 4540",
    "addr:housenumber":"2ba",
    "addr:postcode":"4540",
    "addr:street":"Rue Aux Terrasses",
    "iso:country":"BE",
    "sg:address":"Rue Aux Terrasses 2ba",
    "sg:city":"Amay",
    "sg:orig_category":"Dierenartsen",
    "sg:phone":"+32 85 31 59 59",
    "sg:postcode":"4540",
    "sg:province":"Li\u00e8ge",
    "wof:name":"Annick Gabriel",
    "wof:placetype":"venue"
},
  "geometry": {"coordinates":[5.3188438416,50.5505523682],"type":"Point"}
}