{
  "type": "Feature",
  "properties": {
    "iso:country":"BE",
    "sg:address":"Rue Reckem 22",
    "sg:city":"Mouscron",
    "sg:orig_category":"Forge, Moulage and Profilage des M\u00e9taux",
    "sg:phone":"+32 56 33 27 80",
    "sg:postcode":"7700",
    "sg:province":"Hainaut",
    "wof:name":"Theuninck L.",
    "wof:placetype":"venue"
},
  "geometry": {"coordinates":[3.197067976,50.7523803711],"type":"Point"}
}