{
  "type": "Feature",
  "properties": {
    "iso:country":"BE",
    "sg:address":"Schietbaanstraat 50",
    "sg:city":"Oostende",
    "sg:classifiers":[
        {
            "category":"Manufacturing",
            "subcategory":"Metals",
            "type":"Manufacturing & Wholesale Goods"
        }
    ],
    "sg:phone":"+32 59 32 04 88",
    "sg:postcode":"8400",
    "sg:province":"West-Vlaanderen",
    "sg:tags":[
        "ornamental",
        "work",
        "-"
    ],
    "wof:name":"Schockaert O & Co Nv",
    "wof:placetype":"venue"
},
  "geometry": {"coordinates":[2.9565420151,51.231967926],"type":"Point"}
}