{
  "type": "Feature",
  "properties": {
    "iso:country":"BE",
    "sg:address":"Place Duchesse De Brabant 19",
    "sg:city":"Sint-jans-molenbeek/molenbeek-saint-jean",
    "sg:orig_category":"Epiceries",
    "sg:phone":"+32 2 410 88 53",
    "sg:postcode":"1080",
    "sg:province":"Bruxelles-Capitale",
    "wof:name":"Maison Mantione & Cie",
    "wof:placetype":"venue"
},
  "geometry": {"coordinates":[4.3289351463,50.8491134644],"type":"Point"}
}