{
  "type": "Feature",
  "properties": {
    "iso:country":"BE",
    "sg:address":"Buurtspoorweglaan 20",
    "sg:city":"Steenokkerzeel",
    "sg:orig_category":"Installation de menuiserie en bois and plastique",
    "sg:phone":"+32 16 65 69 17",
    "sg:postcode":"1820",
    "sg:province":"Vlaams-Brabant",
    "wof:name":"Myllecan C",
    "wof:placetype":"venue"
},
  "geometry": {"coordinates":[4.5213518143,50.9240684509],"type":"Point"}
}