{
  "type": "Feature",
  "properties": {
    "addr:full":"Nobelstraat 9 Tremelo Vlaams-Brabant 3128",
    "addr:housenumber":"9",
    "addr:postcode":"3128",
    "addr:street":"Nobelstraat",
    "iso:country":"BE",
    "sg:address":"Nobelstraat 9",
    "sg:city":"Tremelo",
    "sg:orig_category":"Fietsen Fietsen Fab Herstellingen and onderhoud van auto's Watersport-, Sport- and Kampeerbenodigdhe",
    "sg:phone":"+32 16 53 12 76",
    "sg:postcode":"3128",
    "sg:province":"Vlaams-Brabant",
    "wof:name":"Huis Maurice",
    "wof:placetype":"venue"
},
  "geometry": {"coordinates":[4.7502880096,50.9999771118],"type":"Point"}
}