{
  "type": "Feature",
  "properties": {
    "addr:full":"Orchideestraat 67 Gent (oostakker) Oost-Vlaanderen 9041",
    "addr:housenumber":"67",
    "addr:postcode":"9041",
    "addr:street":"Orchideestraat",
    "iso:country":"BE",
    "sg:address":"Orchideestraat 67",
    "sg:city":"Gent (oostakker)",
    "sg:classifiers":[
        {
            "category":"Personal",
            "subcategory":"Beauty Salon",
            "type":"Services"
        }
    ],
    "sg:phone":"+32 9 330 38 16",
    "sg:postcode":"9041",
    "sg:province":"Oost-Vlaanderen",
    "sg:tags":[
        "lady",
        "-",
        "hairdressing"
    ],
    "wof:name":"Hairstyling 4u",
    "wof:placetype":"venue"
},
  "geometry": {"coordinates":[3.797907114,51.0756034851],"type":"Point"}
}