{
  "type": "Feature",
  "properties": {
    "iso:country":"BE",
    "sg:address":"Industrieweg 8",
    "sg:city":"Dendermonde",
    "sg:orig_category":"Hout and afgeleiden Gh IJzerwaren, bouw- and verfmaterialen Installatie van houten of kunststof schr",
    "sg:phone":"+32 52 21 95 71",
    "sg:postcode":"9200",
    "sg:province":"Oost-Vlaanderen",
    "wof:name":"B.g.",
    "wof:placetype":"venue"
},
  "geometry": {"coordinates":[4.141600132,51.031124115],"type":"Point"}
}