{
  "type": "Feature",
  "properties": {
    "addr:full":"Gaupinlaan 18 Koksijde (oostduinkerke) West-Vlaanderen 8670",
    "addr:housenumber":"18",
    "addr:postcode":"8670",
    "addr:street":"Gaupinlaan",
    "iso:country":"BE",
    "sg:address":"Gaupinlaan 18",
    "sg:city":"Koksijde (oostduinkerke)",
    "sg:classifiers":[
        {
            "category":"Wholesale",
            "subcategory":"Wine & Distilled Alcoholic Beverages",
            "type":"Manufacturing & Wholesale Goods"
        }
    ],
    "sg:phone":"+32 58 51 96 06",
    "sg:postcode":"8670",
    "sg:province":"West-Vlaanderen",
    "sg:tags":[
        "whol",
        "-",
        "spirit",
        "mfg"
    ],
    "wof:name":"Guyvin",
    "wof:placetype":"venue"
},
  "geometry": {"coordinates":[2.6674439907,51.1248168945],"type":"Point"}
}