{
  "type": "Feature",
  "properties": {
    "addr:full":"Smetsstraat 7 Antwerpen Antwerpen 2100",
    "addr:housenumber":"7",
    "addr:postcode":"2100",
    "addr:street":"Smetsstraat",
    "iso:country":"BE",
    "sg:address":"Smetsstraat 7",
    "sg:city":"Antwerpen",
    "sg:orig_category":"Architecten",
    "sg:phone":"+32 3 321 35 21",
    "sg:postcode":"2100",
    "sg:province":"Antwerpen",
    "wof:name":"Louis Wouters",
    "wof:placetype":"venue"
},
  "geometry": {"coordinates":[4.4586100578,51.2203941345],"type":"Point"}
}