{
  "type": "Feature",
  "properties": {
    "addr:full":"De Billemontstraat 58 Geel Antwerpen 2440",
    "addr:housenumber":"58",
    "addr:postcode":"2440",
    "addr:street":"De Billemontstraat",
    "iso:country":"BE",
    "sg:address":"De Billemontstraat 58",
    "sg:city":"Geel",
    "sg:orig_category":"Geblazen glas Fab Technische and wetenschappelijke instrumenten Fab Verlichting and huishoudartikele",
    "sg:phone":"+32 14 56 02 21",
    "sg:postcode":"2440",
    "sg:province":"Antwerpen",
    "wof:name":"Glasatelier Saillart",
    "wof:placetype":"venue"
},
  "geometry": {"coordinates":[4.9979481697,51.1632957458],"type":"Point"}
}