{
  "type": "Feature",
  "properties": {
    "addr:full":"Rue Du Cornet 47 Estaimpuis Hainaut 7730",
    "addr:housenumber":"47",
    "addr:postcode":"7730",
    "addr:street":"Rue Du Cornet;Hainaut",
    "iso:country":"BE",
    "sg:address":"Rue Du Cornet 47",
    "sg:city":"Estaimpuis",
    "sg:orig_category":"Enseignement secondaire g\u00e9n\u00e9ral",
    "sg:phone":"+32 56 48 89 46",
    "sg:postcode":"7730",
    "sg:province":"Hainaut",
    "wof:name":"Ecole Les Trieux",
    "wof:placetype":"venue"
},
  "geometry": {"coordinates":[3.262059927,50.6873168945],"type":"Point"}
}