{
  "type": "Feature",
  "properties": {
    "addr:full":"Centre Commercial Cora La Louvi\u00e8re Hainaut 7100",
    "addr:postcode":"7100",
    "iso:country":"BE",
    "sg:address":"Centre Commercial Cora",
    "sg:city":"La Louvi\u00e8re",
    "sg:classifiers":[
        {
            "category":"Travel",
            "subcategory":"Travel Agent",
            "type":"Entertainment"
        }
    ],
    "sg:phone":"+32 64 22 50 16",
    "sg:postcode":"7100",
    "sg:province":"Hainaut",
    "sg:tags":[
        "agency"
    ],
    "wof:name":"Eole",
    "wof:placetype":"venue"
},
  "geometry": {"coordinates":[4.1850848198,50.4748649597],"type":"Point"}
}