{
  "type": "Feature",
  "properties": {
    "addr:full":"Lange Dreef 12 Ichtegem West-Vlaanderen 8480",
    "addr:housenumber":"12",
    "addr:postcode":"8480",
    "addr:street":"Lange Dreef",
    "iso:country":"BE",
    "sg:address":"Lange Dreef 12",
    "sg:city":"Ichtegem",
    "sg:orig_category":"Rundveehouders Varkenskwekers",
    "sg:phone":"+32 59 29 93 82",
    "sg:postcode":"8480",
    "sg:province":"West-Vlaanderen",
    "wof:name":"Rene Vandewaetere",
    "wof:placetype":"venue"
},
  "geometry": {"coordinates":[3.0594129562,51.1312446594],"type":"Point"}
}