{
  "type": "Feature",
  "properties": {
    "iso:country":"BE",
    "sg:address":"Chauss\u00e9e Napol\u00e9on 5-9",
    "sg:city":"Huy",
    "sg:classifiers":[
        {
            "category":"Travel",
            "subcategory":"Hotels & Motels",
            "type":"Entertainment"
        }
    ],
    "sg:phone":"+32 85 21 24 03",
    "sg:postcode":"4500",
    "sg:province":"Li\u00e8ge",
    "wof:name":"H\u00f4tel Du Fort",
    "wof:placetype":"venue"
},
  "geometry": {"coordinates":[5.2351517677,50.5165939331],"type":"Point"}
}