{
  "type": "Feature",
  "properties": {
    "addr:full":"Kasteelstraat 35 Zwevegem West-Vlaanderen 8550",
    "addr:housenumber":"35",
    "addr:postcode":"8550",
    "addr:street":"Kasteelstraat",
    "iso:country":"BE",
    "sg:address":"Kasteelstraat 35",
    "sg:city":"Zwevegem",
    "sg:orig_category":"Architectes",
    "sg:phone":"+32 56 75 42 89",
    "sg:postcode":"8550",
    "sg:province":"West-Vlaanderen",
    "wof:name":"Pol Sileghem",
    "wof:placetype":"venue"
},
  "geometry": {"coordinates":[3.3312571049,50.8105430603],"type":"Point"}
}