{
  "type": "Feature",
  "properties": {
    "addr:full":"Albert Biesmanslaan 26 Hoeilaart Vlaams-Brabant 1560",
    "addr:housenumber":"26",
    "addr:postcode":"1560",
    "addr:street":"Albert Biesmanslaan",
    "iso:country":"BE",
    "sg:address":"Albert Biesmanslaan 26",
    "sg:city":"Hoeilaart",
    "sg:classifiers":[
        {
            "category":"Travel",
            "subcategory":"Travel Agent",
            "type":"Entertainment"
        }
    ],
    "sg:phone":"+32 2 657 49 49",
    "sg:postcode":"1560",
    "sg:province":"Vlaams-Brabant",
    "sg:tags":[
        "agency"
    ],
    "wof:name":"Full Service Travel",
    "wof:placetype":"venue"
},
  "geometry": {"coordinates":[4.4769082069,50.7680892944],"type":"Point"}
}