{
  "type": "Feature",
  "properties": {
    "iso:country":"BE",
    "sg:address":"Provincialebaan 130",
    "sg:city":"Buggenhout",
    "sg:classifiers":[
        {
            "category":"Shopping",
            "subcategory":"Bicycles & Sporting Goods",
            "type":"Retail Goods"
        }
    ],
    "sg:phone":"+32 52 33 20 28",
    "sg:postcode":"9255",
    "sg:province":"Oost-Vlaanderen",
    "sg:tags":[
        "tyre"
    ],
    "wof:name":"Cosyns Autogamma Nv",
    "wof:placetype":"venue"
},
  "geometry": {"coordinates":[4.191008091,51.0306243896],"type":"Point"}
}