{
  "type": "Feature",
  "properties": {
    "addr:full":"Avenue Paul Brien 4 Hannut Li\u00e8ge 4280",
    "addr:housenumber":"4",
    "addr:postcode":"4280",
    "addr:street":"Avenue Paul Brien",
    "iso:country":"BE",
    "sg:address":"Avenue Paul Brien 4",
    "sg:city":"Hannut",
    "sg:orig_category":"Algemeen secundair onderwijs",
    "sg:phone":"+32 19 51 21 61",
    "sg:postcode":"4280",
    "sg:province":"Li\u00e8ge",
    "wof:name":"Inst. St.coeur De Marie",
    "wof:placetype":"venue"
},
  "geometry": {"coordinates":[5.0732111931,50.6706581116],"type":"Point"}
}