{
  "type": "Feature",
  "properties": {
    "iso:country":"BE",
    "sg:address":"Honsfeld 115",
    "sg:city":"B\u00dcllingen/bullange",
    "sg:orig_category":"Enseignement maternel and primaire",
    "sg:phone":"+32 80 64 77 43",
    "sg:postcode":"4760",
    "sg:province":"Li\u00e8ge",
    "wof:name":"Offizielle Grundschule",
    "wof:placetype":"venue"
},
  "geometry": {"coordinates":[6.2817721367,50.3822288513],"type":"Point"}
}