{
  "type": "Feature",
  "properties": {
    "iso:country":"BE",
    "sg:address":"Merellaan 13",
    "sg:city":"Vorselaar",
    "sg:orig_category":"Bloemen and planten",
    "sg:phone":"+32 14 51 59 54",
    "sg:postcode":"2290",
    "sg:province":"Antwerpen",
    "wof:name":"Maria Janssens",
    "wof:placetype":"venue"
},
  "geometry": {"coordinates":[4.7743349075,51.1994514465],"type":"Point"}
}