{
  "type": "Feature",
  "properties": {
    "addr:full":"Chauss\u00e9e De Wavre 174-176 Bruxelles (ixelles) Bruxelles-Capitale 1050",
    "addr:postcode":"174-176;1050",
    "addr:street":"Chausse\u0301E De Wavre",
    "iso:country":"BE",
    "sg:address":"Chauss\u00e9e De Wavre 174-176",
    "sg:city":"Bruxelles (ixelles)",
    "sg:classifiers":[
        {
            "category":"Wholesale",
            "subcategory":"Beer",
            "type":"Manufacturing & Wholesale Goods"
        }
    ],
    "sg:phone":"+32 2 512 17 88",
    "sg:postcode":"1050",
    "sg:province":"Bruxelles-Capitale",
    "sg:tags":[
        "ale",
        "-"
    ],
    "wof:name":"Bieres Artisanales",
    "wof:placetype":"venue"
},
  "geometry": {"coordinates":[4.37059021,50.8358001709],"type":"Point"}
}