{
  "type": "Feature",
  "properties": {
    "addr:full":"Chauss\u00c9e D'alsemberg 740 Ukkel/uccle Bruxelles-Capitale 1180",
    "addr:housenumber":"740",
    "addr:postcode":"1180",
    "addr:street":"Chausse\u0301E D'Alsemberg;/",
    "iso:country":"BE",
    "sg:address":"Chauss\u00c9e D'alsemberg 740",
    "sg:city":"Ukkel/uccle",
    "sg:orig_category":"Rev\u00eatements de sols and murs. Meubles D\u00e9taillants, Am\u00e9nagement de B\u00e2timents et de Cuisines. Eclairag",
    "sg:phone":"+32 2 344 43 34",
    "sg:postcode":"1180",
    "sg:province":"Bruxelles-Capitale",
    "wof:name":"Tapiclub/tapiclub Interieur",
    "wof:placetype":"venue"
},
  "geometry": {"coordinates":[4.3368020058,50.801158905],"type":"Point"}
}