{
  "type": "Feature",
  "properties": {
    "addr:full":"Chauss\u00c9e Verte 44 Saint-georges-sur-meuse Li\u00e8ge 4470",
    "addr:housenumber":"44",
    "addr:postcode":"4470",
    "addr:street":"Chausse\u0301E Verte",
    "iso:country":"BE",
    "sg:address":"Chauss\u00c9e Verte 44",
    "sg:city":"Saint-georges-sur-meuse",
    "sg:classifiers":[
        {
            "category":"Insurance",
            "subcategory":"Insurance Agent",
            "type":"Services"
        }
    ],
    "sg:phone":"+32 4 259 56 11",
    "sg:postcode":"4470",
    "sg:province":"Li\u00e8ge",
    "sg:tags":[
        "verzekeringsmakelaars",
        "expert"
    ],
    "wof:name":"Abraham-colard",
    "wof:placetype":"venue"
},
  "geometry": {"coordinates":[5.3421897888,50.594291687],"type":"Point"}
}