{
  "type": "Feature",
  "properties": {
    "iso:country":"BE",
    "sg:address":"Pl. De L'h\u00d4tel De Ville 16",
    "sg:city":"Chapelle-lez-herlaimont",
    "sg:orig_category":"Openbare veiligheid",
    "sg:phone":"+32 64 43 12 10",
    "sg:postcode":"7160",
    "sg:province":"Hainaut",
    "wof:name":"Police F\u00c9d\u00c9rale",
    "wof:placetype":"venue"
},
  "geometry": {"coordinates":[4.2810001373,50.4714698792],"type":"Point"}
}