{
  "type": "Feature",
  "properties": {
    "addr:full":"Rue De Baudecet 3 Walhain Brabant Wallon 1457",
    "addr:housenumber":"3;1457",
    "addr:street":"Rue De Baudecet",
    "iso:country":"BE",
    "sg:address":"Rue De Baudecet 3",
    "sg:city":"Walhain",
    "sg:orig_category":"Artsen and specialisten",
    "sg:phone":"+32 10 65 70 13",
    "sg:postcode":"1457",
    "sg:province":"Brabant Wallon",
    "wof:name":"Sophie Leonard",
    "wof:placetype":"venue"
},
  "geometry": {"coordinates":[4.6964430809,50.6114578247],"type":"Point"}
}