{
  "type": "Feature",
  "properties": {
    "iso:country":"BE",
    "sg:address":"L. Carr\u00e9straat 45",
    "sg:city":"Heist-op-den-berg (hallaar)",
    "sg:classifiers":[
        {
            "category":"Retail",
            "subcategory":"Funeral Services",
            "type":"Services"
        }
    ],
    "sg:phone":"+32 15 24 16 32",
    "sg:postcode":"2220",
    "sg:province":"Antwerpen",
    "sg:tags":[
        "director"
    ],
    "wof:name":"Wyns-van Dyck",
    "wof:placetype":"venue"
},
  "geometry": {"coordinates":[4.7306852341,51.0862503052],"type":"Point"}
}