{
  "type": "Feature",
  "properties": {
    "iso:country":"BE",
    "sg:address":"Steenweg 172",
    "sg:city":"Diepenbeek",
    "sg:classifiers":[
        {
            "category":"Professional",
            "subcategory":"Accounting & Tax Preparation",
            "type":"Services"
        }
    ],
    "sg:phone":"+32 11 85 90 85",
    "sg:postcode":"3590",
    "sg:province":"Limburg",
    "sg:tags":[
        "bookkeeper"
    ],
    "wof:name":"Haenen E",
    "wof:placetype":"venue"
},
  "geometry": {"coordinates":[5.3864979744,50.9199523926],"type":"Point"}
}