{
  "type": "Feature",
  "properties": {
    "iso:country":"BE",
    "sg:address":"Molenhoek 36",
    "sg:city":"Lede",
    "sg:orig_category":"Groenten and fruit Gh",
    "sg:phone":"+32 9 369 08 60",
    "sg:postcode":"9340",
    "sg:province":"Oost-Vlaanderen",
    "wof:name":"Van De Velde Willy",
    "wof:placetype":"venue"
},
  "geometry": {"coordinates":[3.9259479046,50.9651527405],"type":"Point"}
}