{
  "type": "Feature",
  "properties": {
    "iso:country":"BE",
    "sg:address":"Welvaartstraat 35",
    "sg:city":"Aalst",
    "sg:classifiers":[
        {
            "category":"Autos & Motor Vehicles",
            "subcategory":"Recreational Vehicle Sales",
            "type":"Retail Goods"
        }
    ],
    "sg:phone":"+32 53 77 39 83",
    "sg:postcode":"9300",
    "sg:province":"Oost-Vlaanderen",
    "sg:tags":[
        "saw"
    ],
    "wof:name":"Eeckhout F",
    "wof:placetype":"venue"
},
  "geometry": {"coordinates":[4.0201368332,50.9409408569],"type":"Point"}
}