{
  "type": "Feature",
  "properties": {
    "iso:country":"BE",
    "sg:address":"Rue Du Grand Pr\u00c9",
    "sg:city":"Comblain-au-pont",
    "sg:orig_category":"Organisations and associations. Jardins botaniques, zoologiques, observatoires and r\u00e9serves naturell",
    "sg:phone":"+32 4 369 41 33",
    "sg:postcode":"4170",
    "sg:province":"Li\u00e8ge",
    "wof:name":"Clie",
    "wof:placetype":"venue"
},
  "geometry": {"coordinates":[5.5797419548,50.4730453491],"type":"Point"}
}