{
  "type": "Feature",
  "properties": {
    "addr:full":"Rue Du Marais 23 Burdinne Li\u00e8ge 4210",
    "addr:housenumber":"23",
    "addr:postcode":"4210",
    "addr:street":"Rue Du Marais",
    "iso:country":"BE",
    "sg:address":"Rue Du Marais 23",
    "sg:city":"Burdinne",
    "sg:orig_category":"Assurances. Bureaux de poste",
    "sg:phone":"+32 85 71 13 60",
    "sg:postcode":"4210",
    "sg:province":"Li\u00e8ge",
    "wof:name":"La Poste",
    "wof:placetype":"venue"
},
  "geometry": {"coordinates":[5.0664081573,50.581199646],"type":"Point"}
}