{
  "type": "Feature",
  "properties": {
    "iso:country":"BE",
    "sg:address":"Rue De La Station 39",
    "sg:city":"Orp-jauche",
    "sg:orig_category":"S\u00e9curit\u00e9 sociale",
    "sg:phone":"+32 19 63 50 30",
    "sg:postcode":"1350",
    "sg:province":"Brabant Wallon",
    "wof:name":"Mutualit\u00c9 Socialiste",
    "wof:placetype":"venue"
},
  "geometry": {"coordinates":[4.9870929718,50.6967658997],"type":"Point"}
}