{
  "type": "Feature",
  "properties": {
    "addr:full":"Balansstraat 4 Antwerpen Antwerpen 2018",
    "addr:housenumber":"4",
    "addr:postcode":"2018",
    "addr:street":"Balansstraat",
    "iso:country":"BE",
    "sg:address":"Balansstraat 4",
    "sg:city":"Antwerpen",
    "sg:classifiers":[
        {
            "category":"Fast Food",
            "type":"Food & Drink"
        }
    ],
    "sg:phone":"+32 3 238 58 61",
    "sg:postcode":"2018",
    "sg:province":"Antwerpen",
    "sg:tags":[
        "\u00c0",
        "emporter",
        "restaurants"
    ],
    "wof:name":"Riviera",
    "wof:placetype":"venue"
},
  "geometry": {"coordinates":[4.3957009315,51.2045936584],"type":"Point"}
}