{
  "type": "Feature",
  "properties": {
    "iso:country":"BE",
    "sg:address":"Rue Fran\u00c7ois-hittelet 120",
    "sg:city":"Jemeppe-sur-sambre",
    "sg:classifiers":[
        {
            "category":"Restaurant",
            "type":"Food & Drink"
        }
    ],
    "sg:phone":"+32 71 78 03 43",
    "sg:postcode":"5190",
    "sg:province":"Namur",
    "wof:name":"Les Freschaux",
    "wof:placetype":"venue"
},
  "geometry": {"coordinates":[4.6627120972,50.4586715698],"type":"Point"}
}