{
  "type": "Feature",
  "properties": {
    "addr:full":"Doortstraat 65 Opwijk Vlaams-Brabant 1745",
    "addr:housenumber":"65",
    "addr:postcode":"1745",
    "addr:street":"Doortstraat",
    "iso:country":"BE",
    "sg:address":"Doortstraat 65",
    "sg:city":"Opwijk",
    "sg:orig_category":"Entretien and r\u00e9parations de voitures",
    "sg:phone":"+32 52 35 12 28",
    "sg:postcode":"1745",
    "sg:province":"Vlaams-Brabant",
    "wof:name":"Michel Dieleman",
    "wof:placetype":"venue"
},
  "geometry": {"coordinates":[4.1937551498,50.975528717],"type":"Point"}
}