{
  "type": "Feature",
  "properties": {
    "addr:full":"Plein 19 Kaprijke Oost-Vlaanderen 9970",
    "addr:housenumber":"19",
    "addr:postcode":"9970",
    "addr:street":"Plein",
    "iso:country":"BE",
    "sg:address":"Plein 19",
    "sg:city":"Kaprijke",
    "sg:classifiers":[
        {
            "category":"Cafe",
            "type":"Food & Drink"
        }
    ],
    "sg:phone":"+32 9 373 57 87",
    "sg:postcode":"9970",
    "sg:province":"Oost-Vlaanderen",
    "sg:tags":[
        "caf\u00e9s"
    ],
    "wof:name":"Caf\u00c9 Dreadzone",
    "wof:placetype":"venue"
},
  "geometry": {"coordinates":[3.6189339161,51.2190628052],"type":"Point"}
}