{
  "type": "Feature",
  "properties": {
    "addr:full":"Ninoofsesteenweg 26 Haaltert Oost-Vlaanderen 9450",
    "addr:housenumber":"26",
    "addr:postcode":"9450",
    "addr:street":"Ninoofsesteenweg",
    "iso:country":"BE",
    "sg:address":"Ninoofsesteenweg 26",
    "sg:city":"Haaltert",
    "sg:orig_category":"Installation de menuiserie en bois and plastique",
    "sg:phone":"+32 54 34 16 54",
    "sg:postcode":"9450",
    "sg:province":"Oost-Vlaanderen",
    "wof:name":"Elie Heyse",
    "wof:placetype":"venue"
},
  "geometry": {"coordinates":[4.0182290077,50.8671188354],"type":"Point"}
}