{
  "type": "Feature",
  "properties": {
    "addr:full":"Zandstraat 39 Zoersel Antwerpen 2980",
    "addr:housenumber":"39",
    "addr:postcode":"2980",
    "addr:street":"Zandstraat",
    "iso:country":"BE",
    "sg:address":"Zandstraat 39",
    "sg:city":"Zoersel",
    "sg:classifiers":[
        {
            "category":"Education",
            "subcategory":"School",
            "type":"Public Place"
        }
    ],
    "sg:phone":"+32 3 312 03 52",
    "sg:postcode":"2980",
    "sg:province":"Antwerpen",
    "sg:tags":[
        "primary"
    ],
    "wof:name":"Kievitje (het)",
    "wof:placetype":"venue"
},
  "geometry": {"coordinates":[4.7123551369,51.2644538879],"type":"Point"}
}