{
  "type": "Feature",
  "properties": {
    "addr:full":"Kapellensteenweg 272 Kalmthout Antwerpen 2920",
    "addr:housenumber":"272",
    "addr:postcode":"2920",
    "addr:street":"Kapellensteenweg",
    "iso:country":"BE",
    "sg:address":"Kapellensteenweg 272",
    "sg:city":"Kalmthout",
    "sg:orig_category":"Art and fournitures artistiques. Salles de spectacles",
    "sg:phone":"+32 3 666 27 26",
    "sg:postcode":"2920",
    "sg:province":"Antwerpen",
    "wof:name":"Galerie Mas",
    "wof:placetype":"venue"
},
  "geometry": {"coordinates":[4.4743041992,51.3780899048],"type":"Point"}
}