{
  "type": "Feature",
  "properties": {
    "addr:full":"Rue L\u00c9on Theodor 49 Jette/jette Bruxelles-Capitale 1090",
    "addr:housenumber":"49",
    "addr:postcode":"1090",
    "addr:street":"Rue Le\u0301On Theodor",
    "iso:country":"BE",
    "sg:address":"Rue L\u00c9on Theodor 49",
    "sg:city":"Jette/jette",
    "sg:orig_category":"Notaires",
    "sg:phone":"+32 2 425 18 41",
    "sg:postcode":"1090",
    "sg:province":"Bruxelles-Capitale",
    "wof:name":"P. Van Haverbeke",
    "wof:placetype":"venue"
},
  "geometry": {"coordinates":[4.3266859055,50.874294281],"type":"Point"}
}