{
  "type": "Feature",
  "properties": {
    "addr:full":"Doornstraat 71a Sint-gillis-waas Oost-Vlaanderen 9170",
    "addr:housenumber":"71a",
    "addr:postcode":"9170",
    "addr:street":"Doornstraat",
    "iso:country":"BE",
    "sg:address":"Doornstraat 71a",
    "sg:city":"Sint-gillis-waas",
    "sg:classifiers":[
        {
            "category":"Health Services",
            "subcategory":"Nursing And Care Facility",
            "type":"Services"
        }
    ],
    "sg:phone":"+32 3 707 02 10",
    "sg:postcode":"9170",
    "sg:province":"Oost-Vlaanderen",
    "sg:tags":[
        "home"
    ],
    "wof:name":"De Gauw Chantal",
    "wof:placetype":"venue"
},
  "geometry": {"coordinates":[4.1238188744,51.2095336914],"type":"Point"}
}