{
  "type": "Feature",
  "properties": {
    "iso:country":"BE",
    "sg:address":"Stuivenberstr 91",
    "sg:city":"Izegem",
    "sg:classifiers":[
        {
            "category":"Shopping",
            "type":"Retail Goods"
        }
    ],
    "sg:phone":"+32 51 30 20 65",
    "sg:postcode":"8870",
    "sg:province":"West-Vlaanderen",
    "sg:tags":[
        "metallurgy",
        "finished",
        "-",
        "metalworking",
        "metallic"
    ],
    "wof:name":"Dubaere Bvba",
    "wof:placetype":"venue"
},
  "geometry": {"coordinates":[3.1963760853,50.9236907959],"type":"Point"}
}