{
  "type": "Feature",
  "properties": {
    "iso:country":"BE",
    "sg:address":"Route Napol\u00c9on 367",
    "sg:city":"Fl\u00c9malle",
    "sg:orig_category":"Afbraak- and draineerwerken Gespecialiseerde residenti\u00eble bouw Verhuur bouwmachines Woningbouw",
    "sg:phone":"+32 4 372 08 54",
    "sg:postcode":"4400",
    "sg:province":"Li\u00e8ge",
    "wof:name":"Robert Mean",
    "wof:placetype":"venue"
},
  "geometry": {"coordinates":[5.4576430321,50.5693130493],"type":"Point"}
}