{
  "type": "Feature",
  "properties": {
    "addr:full":"Kriekelstraat 14a Gingelom Limburg 3890",
    "addr:housenumber":"14a",
    "addr:postcode":"3890",
    "addr:street":"Kriekelstraat",
    "iso:country":"BE",
    "sg:address":"Kriekelstraat 14a",
    "sg:city":"Gingelom",
    "sg:classifiers":[
        {
            "category":"Wholesale",
            "subcategory":"Beer",
            "type":"Manufacturing & Wholesale Goods"
        }
    ],
    "sg:phone":"+32 11 83 26 41",
    "sg:postcode":"3890",
    "sg:province":"Limburg",
    "sg:tags":[
        "ale",
        "-"
    ],
    "wof:name":"De Chokier Bvba",
    "wof:placetype":"venue"
},
  "geometry": {"coordinates":[5.1383810043,50.7512283325],"type":"Point"}
}