{
  "type": "Feature",
  "properties": {
    "iso:country":"BE",
    "sg:address":"Devant Staneux 25",
    "sg:city":"Theux",
    "sg:orig_category":"Pain, p\u00e2tisseries and confiseries",
    "sg:phone":"+32 87 54 12 68",
    "sg:postcode":"4910",
    "sg:province":"Li\u00e8ge",
    "wof:name":"Anne Piette",
    "wof:placetype":"venue"
},
  "geometry": {"coordinates":[5.8269271851,50.5194473267],"type":"Point"}
}