{
  "type": "Feature",
  "properties": {
    "iso:country":"BE",
    "sg:address":"Sint-antoniuswijk 29",
    "sg:city":"Rotselaar",
    "sg:orig_category":"Avocats and conseillers juridiques",
    "sg:phone":"+32 16 44 68 34",
    "sg:postcode":"3110",
    "sg:province":"Vlaams-Brabant",
    "wof:name":"Ilse Nys",
    "wof:placetype":"venue"
},
  "geometry": {"coordinates":[4.7215328217,50.9517784119],"type":"Point"}
}