{
  "type": "Feature",
  "properties": {
    "addr:full":"Rue De Bruxelles 54 Wavre Brabant Wallon 1300",
    "addr:housenumber":"54;1300",
    "addr:street":"Rue De Bruxelles",
    "iso:country":"BE",
    "sg:address":"Rue De Bruxelles 54",
    "sg:city":"Wavre",
    "sg:classifiers":[
        {
            "category":"Shopping",
            "subcategory":"Stationery & Office Supplies",
            "type":"Retail Goods"
        }
    ],
    "sg:phone":"+32 10 22 32 88",
    "sg:postcode":"1300",
    "sg:province":"Brabant Wallon",
    "wof:name":"Michotte Papeterie",
    "wof:placetype":"venue"
},
  "geometry": {"coordinates":[4.6127038002,50.7186775208],"type":"Point"}
}