{
  "type": "Feature",
  "properties": {
    "iso:country":"BE",
    "sg:address":"J Lijsenstraat 57",
    "sg:city":"Hoogstraten",
    "sg:orig_category":"Plantes and fleurs Gr",
    "sg:phone":"+32 3 315 09 81",
    "sg:postcode":"2321",
    "sg:province":"Antwerpen",
    "wof:name":"Vita Nova",
    "wof:placetype":"venue"
},
  "geometry": {"coordinates":[4.7366099358,51.442325592],"type":"Point"}
}