{
  "type": "Feature",
  "properties": {
    "iso:country":"BE",
    "sg:address":"Vullaertstraat 33",
    "sg:city":"Beernem",
    "sg:classifiers":[
        {
            "category":"Arena",
            "subcategory":"Sports Club",
            "type":"Entertainment"
        }
    ],
    "sg:phone":"+32 50 79 03 25",
    "sg:postcode":"8730",
    "sg:province":"West-Vlaanderen",
    "sg:tags":[
        "de"
    ],
    "wof:name":"Uilenspiegels Oedelem",
    "wof:placetype":"venue"
},
  "geometry": {"coordinates":[3.329241991,51.169719696],"type":"Point"}
}