{
  "type": "Feature",
  "properties": {
    "addr:full":"Herbuchenne 61 Dinant Namur 5500",
    "addr:housenumber":"61",
    "addr:postcode":"5500",
    "addr:street":"Herbuchenne",
    "iso:country":"BE",
    "sg:address":"Herbuchenne 61",
    "sg:city":"Dinant",
    "sg:classifiers":[
        {
            "category":"Health Services",
            "subcategory":"Doctor",
            "type":"Services"
        }
    ],
    "sg:phone":"+32 82 22 34 18",
    "sg:postcode":"5500",
    "sg:province":"Namur",
    "sg:tags":[
        "medicinephysicians",
        "surgeon"
    ],
    "wof:name":"Kurz C",
    "wof:placetype":"venue"
},
  "geometry": {"coordinates":[4.9254198074,50.2498512268],"type":"Point"}
}