{
  "type": "Feature",
  "properties": {
    "addr:full":"Place De L'universit\u00e9 12 Ottignies-louvain-la-neuve (louvain-la-neuve) Brabant Wallon 1348",
    "addr:housenumber":"12",
    "addr:postcode":"1348",
    "addr:street":"Place De L'Universite \u0301",
    "iso:country":"BE",
    "sg:address":"Place De L'universit\u00e9 12",
    "sg:city":"Ottignies-louvain-la-neuve (louvain-la-neuve)",
    "sg:classifiers":[
        {
            "category":"Utilities",
            "subcategory":"Telephone",
            "type":"Services"
        }
    ],
    "sg:phone":"+32 10 45 27 88",
    "sg:postcode":"1348",
    "sg:province":"Brabant Wallon",
    "sg:tags":[
        "-",
        "internet"
    ],
    "wof:name":"R\u00e9seau (le)",
    "wof:placetype":"venue"
},
  "geometry": {"coordinates":[4.6150960922,50.6702728271],"type":"Point"}
}