{
  "type": "Feature",
  "properties": {
    "iso:country":"BE",
    "sg:address":"Ch De Namur 248",
    "sg:city":"Wavre",
    "sg:classifiers":[
        {
            "category":"Home & Garden",
            "subcategory":"Furniture",
            "type":"Retail Goods"
        }
    ],
    "sg:phone":"+32 10 45 27 25",
    "sg:postcode":"1300",
    "sg:province":"Brabant Wallon",
    "sg:tags":[
        "household",
        "wood"
    ],
    "wof:name":"Mi-bois S.a.",
    "wof:placetype":"venue"
},
  "geometry": {"coordinates":[4.6158699989,50.6923713684],"type":"Point"}
}