{
  "type": "Feature",
  "properties": {
    "addr:full":"Dokter Eduard Moreauxlaan 101 Oostende West-Vlaanderen 8400",
    "addr:housenumber":"101",
    "addr:postcode":"8400",
    "addr:street":"Dokter Eduard Moreauxlaan",
    "iso:country":"BE",
    "sg:address":"Dokter Eduard Moreauxlaan 101",
    "sg:city":"Oostende",
    "sg:classifiers":[
        {
            "category":"Bars & Pubs",
            "type":"Food & Drink"
        }
    ],
    "sg:phone":"+32 59 32 08 82",
    "sg:postcode":"8400",
    "sg:province":"West-Vlaanderen",
    "wof:name":"Tivoli",
    "wof:placetype":"venue"
},
  "geometry": {"coordinates":[2.941865921,51.224445343],"type":"Point"}
}