{
  "type": "Feature",
  "properties": {
    "addr:full":"Bedevaartstraat 22 Tielt West-Vlaanderen 8700",
    "addr:housenumber":"22",
    "addr:postcode":"8700",
    "addr:street":"Bedevaartstraat",
    "iso:country":"BE",
    "sg:address":"Bedevaartstraat 22",
    "sg:city":"Tielt",
    "sg:classifiers":[
        {
            "category":"Food & Beverages",
            "subcategory":"Groceries & Convenience Stores",
            "type":"Retail Goods"
        }
    ],
    "sg:phone":"+32 51 40 17 86",
    "sg:postcode":"8700",
    "sg:province":"West-Vlaanderen",
    "sg:tags":[
        "grocer"
    ],
    "wof:name":"Soenens W",
    "wof:placetype":"venue"
},
  "geometry": {"coordinates":[3.3324580193,50.9898033142],"type":"Point"}
}