{
  "type": "Feature",
  "properties": {
    "iso:country":"BE",
    "sg:address":"Vrijheidslaan 1",
    "sg:city":"Bree",
    "sg:classifiers":[
        {
            "category":"Health Services",
            "subcategory":"Health Practitioner",
            "type":"Services"
        }
    ],
    "sg:phone":"+32 89 47 23 46",
    "sg:postcode":"3960",
    "sg:province":"Limburg",
    "sg:tags":[
        "physiotherapist"
    ],
    "wof:name":"Roets Helga",
    "wof:placetype":"venue"
},
  "geometry": {"coordinates":[5.6012411118,51.1480331421],"type":"Point"}
}