{
  "type": "Feature",
  "properties": {
    "iso:country":"BE",
    "sg:address":"Avenue De L'observatoire 347",
    "sg:city":"Li\u00c8ge",
    "sg:orig_category":"Brood, gebak and snoepgoed",
    "sg:phone":"+32 4 252 09 33",
    "sg:postcode":"4000",
    "sg:province":"Li\u00e8ge",
    "wof:name":"Joseph Ahn",
    "wof:placetype":"venue"
},
  "geometry": {"coordinates":[5.5619659424,50.6294975281],"type":"Point"}
}