{
  "type": "Feature",
  "properties": {
    "addr:full":"Het Hazepad 15 Aarschot (langdorp) Vlaams-Brabant 3201",
    "addr:housenumber":"15",
    "addr:postcode":"3201",
    "addr:street":"Het Hazepad",
    "iso:country":"BE",
    "sg:address":"Het Hazepad 15",
    "sg:city":"Aarschot (langdorp)",
    "sg:classifiers":[
        {
            "category":"Professional",
            "subcategory":"Engineering",
            "type":"Services"
        }
    ],
    "sg:phone":"+32 16 56 16 77",
    "sg:postcode":"3201",
    "sg:province":"Vlaams-Brabant",
    "sg:tags":[
        "precision"
    ],
    "wof:name":"Mechelmans",
    "wof:placetype":"venue"
},
  "geometry": {"coordinates":[4.8677759171,51.0036010742],"type":"Point"}
}