{
  "type": "Feature",
  "properties": {
    "addr:full":"Les Taillettes 13 Momignies (seloignes) Hainaut 6596",
    "addr:housenumber":"13",
    "addr:postcode":"6596",
    "addr:street":"Taillettes;Seloignes Hainaut",
    "iso:country":"BE",
    "sg:address":"Les Taillettes 13",
    "sg:city":"Momignies (seloignes)",
    "sg:classifiers":[
        {
            "category":"Building & Trades",
            "subcategory":"Pest Control",
            "type":"Services"
        }
    ],
    "sg:phone":"+32 60 51 16 31",
    "sg:postcode":"6596",
    "sg:province":"Hainaut",
    "sg:tags":[
        "painting",
        "contractor"
    ],
    "wof:name":"Bourguignon M",
    "wof:placetype":"venue"
},
  "geometry": {"coordinates":[4.2471852303,49.9943084717],"type":"Point"}
}