{
  "type": "Feature",
  "properties": {
    "addr:full":"Rue Du Peuple 14 Dour Hainaut 7370",
    "addr:housenumber":"14",
    "addr:postcode":"7370",
    "addr:street":"Rue Du Peuple;Hainaut",
    "iso:country":"BE",
    "sg:address":"Rue Du Peuple 14",
    "sg:city":"Dour",
    "sg:orig_category":"Pharmaciens",
    "sg:phone":"+32 65 65 28 34",
    "sg:postcode":"7370",
    "sg:province":"Hainaut",
    "wof:name":"Multipharma",
    "wof:placetype":"venue"
},
  "geometry": {"coordinates":[3.7862370014,50.3993835449],"type":"Point"}
}