{
  "type": "Feature",
  "properties": {
    "addr:full":"Chemin Du Roua 15 Esneux Li\u00e8ge 4130",
    "addr:housenumber":"15",
    "addr:postcode":"4130",
    "addr:street":"Chemin Du Roua",
    "iso:country":"BE",
    "sg:address":"Chemin Du Roua 15",
    "sg:city":"Esneux",
    "sg:orig_category":"Boekhouders",
    "sg:phone":"+32 4 380 19 02",
    "sg:postcode":"4130",
    "sg:province":"Li\u00e8ge",
    "wof:name":"Alain Bosson",
    "wof:placetype":"venue"
},
  "geometry": {"coordinates":[5.5918130875,50.5288467407],"type":"Point"}
}