{
  "type": "Feature",
  "properties": {
    "iso:country":"BE",
    "sg:address":"Wespelaarsebaan 294",
    "sg:city":"Boortmeerbeek",
    "sg:orig_category":"Avocats and conseillers juridiques",
    "sg:phone":"+32 16 60 26 06",
    "sg:postcode":"3190",
    "sg:province":"Vlaams-Brabant",
    "wof:name":"Dirk Bogaerts",
    "wof:placetype":"venue"
},
  "geometry": {"coordinates":[4.6047739983,50.9651374817],"type":"Point"}
}