{
  "type": "Feature",
  "properties": {
    "addr:full":"Dorp West 52-54 Zwijndrecht Antwerpen 2070",
    "addr:postcode":"2070",
    "addr:street":"Dorp West 52-54",
    "iso:country":"BE",
    "sg:address":"Dorp West 52-54",
    "sg:city":"Zwijndrecht",
    "sg:classifiers":[
        {
            "category":"Home & Garden",
            "subcategory":"Household Appliances",
            "type":"Retail Goods"
        }
    ],
    "sg:phone":"+32 3 252 71 87",
    "sg:postcode":"2070",
    "sg:province":"Antwerpen",
    "sg:tags":[
        "repair",
        "mainten",
        "-",
        "electric"
    ],
    "wof:name":"Van Den Broeck G",
    "wof:placetype":"venue"
},
  "geometry": {"coordinates":[4.322991848,51.2189331055],"type":"Point"}
}