{
  "type": "Feature",
  "properties": {
    "addr:full":"Chauss\u00e9e De Wavre 1308 Bruxelles (auderghem) Bruxelles-Capitale 1160",
    "addr:postcode":"1308;1160",
    "addr:street":"Chausse\u0301E De Wavre",
    "iso:country":"BE",
    "sg:address":"Chauss\u00e9e De Wavre 1308",
    "sg:city":"Bruxelles (auderghem)",
    "sg:classifiers":[
        {
            "category":"Retail",
            "subcategory":"Auto Repair",
            "type":"Services"
        }
    ],
    "sg:phone":"+32 2 675 00 00",
    "sg:postcode":"1160",
    "sg:province":"Bruxelles-Capitale",
    "sg:tags":[
        "garage"
    ],
    "wof:name":"Hanciaux",
    "wof:placetype":"venue"
},
  "geometry": {"coordinates":[4.4114689827,50.8202056885],"type":"Point"}
}