{
  "type": "Feature",
  "properties": {
    "addr:full":"Koekelarestraat 78 Kortemark (groot) West-Vlaanderen 8610",
    "addr:housenumber":"78",
    "addr:postcode":"8610",
    "addr:street":"Koekelarestraat;Groot West-Vlaanderen",
    "iso:country":"BE",
    "sg:address":"Koekelarestraat 78",
    "sg:city":"Kortemark (groot)",
    "sg:orig_category":"Diverse bouwafwerking and reiniging Gespecialiseerde residenti\u00eble bouw Hout and afgeleiden Gh IJzerw",
    "sg:phone":"+32 51 56 74 29",
    "sg:postcode":"8610",
    "sg:province":"West-Vlaanderen",
    "wof:name":"Vermeersch F",
    "wof:placetype":"venue"
},
  "geometry": {"coordinates":[3.0178599358,51.0503807068],"type":"Point"}
}