{
  "type": "Feature",
  "properties": {
    "addr:full":"Avenue De L'observatoire 353 Li\u00c8ge Li\u00e8ge 4000",
    "addr:housenumber":"353",
    "addr:postcode":"4000",
    "addr:street":"Avenue De L'Observatoire",
    "iso:country":"BE",
    "sg:address":"Avenue De L'observatoire 353",
    "sg:city":"Li\u00c8ge",
    "sg:orig_category":"M\u00e9decins and sp\u00e9cialistes",
    "sg:phone":"+32 4 254 16 86",
    "sg:postcode":"4000",
    "sg:province":"Li\u00e8ge",
    "wof:name":"Nathalie Bredohl Sampoux",
    "wof:placetype":"venue"
},
  "geometry": {"coordinates":[5.5619659424,50.6294975281],"type":"Point"}
}