{
  "type": "Feature",
  "properties": {
    "iso:country":"BE",
    "sg:address":"Devant Le Bois 6",
    "sg:city":"Lierneux",
    "sg:orig_category":"Eleveurs de bovins",
    "sg:phone":"+32 80 31 90 42",
    "sg:postcode":"4990",
    "sg:province":"Li\u00e8ge",
    "wof:name":"Stephane Foguenne",
    "wof:placetype":"venue"
},
  "geometry": {"coordinates":[5.8464927673,50.3032455444],"type":"Point"}
}