{
  "type": "Feature",
  "properties": {
    "addr:full":"Rue Saint Denis 355 Vorst/forest Bruxelles-Capitale 1190",
    "addr:housenumber":"355",
    "addr:postcode":"1190",
    "addr:street":"Rue Saint Denis;/ Forest",
    "iso:country":"BE",
    "sg:address":"Rue Saint Denis 355",
    "sg:city":"Vorst/forest",
    "sg:classifiers":[
        {
            "category":"Cafe",
            "type":"Food & Drink"
        }
    ],
    "sg:phone":"+32 2 346 23 08",
    "sg:postcode":"1190",
    "sg:province":"Bruxelles-Capitale",
    "sg:tags":[
        "caf\u00e9s"
    ],
    "wof:name":"El Gibo",
    "wof:placetype":"venue"
},
  "geometry": {"coordinates":[4.3210201263,50.8204917908],"type":"Point"}
}