{
  "type": "Feature",
  "properties": {
    "iso:country":"BE",
    "sg:address":"Terlinden 131",
    "sg:city":"Merchtem",
    "sg:orig_category":"Eleveurs de bovins",
    "sg:phone":"+32 52 37 42 39",
    "sg:postcode":"1785",
    "sg:province":"Vlaams-Brabant",
    "wof:name":"Eduard Meskens",
    "wof:placetype":"venue"
},
  "geometry": {"coordinates":[4.2464470863,50.9747200012],"type":"Point"}
}