{
  "type": "Feature",
  "properties": {
    "addr:full":"Kruindersweg 85 Maasmechelen Limburg 3630",
    "addr:housenumber":"85",
    "addr:postcode":"3630",
    "addr:street":"Kruindersweg",
    "iso:country":"BE",
    "sg:address":"Kruindersweg 85",
    "sg:city":"Maasmechelen",
    "sg:orig_category":"Schoenen",
    "sg:phone":"+32 89 76 68 46",
    "sg:postcode":"3630",
    "sg:province":"Limburg",
    "wof:name":"Timmers P.",
    "wof:placetype":"venue"
},
  "geometry": {"coordinates":[5.6961350441,50.963848114],"type":"Point"}
}