{
  "type": "Feature",
  "properties": {
    "iso:country":"BE",
    "sg:address":"Rue Rincheval 1",
    "sg:city":"Chievres",
    "sg:orig_category":"Woningbouw",
    "sg:phone":"+32 68 65 88 21",
    "sg:postcode":"7950",
    "sg:province":"Hainaut",
    "wof:name":"Rodolphe Grumiau",
    "wof:placetype":"venue"
},
  "geometry": {"coordinates":[3.8121399879,50.5504989624],"type":"Point"}
}