{
  "type": "Feature",
  "properties": {
    "addr:full":"Neerveldstraat 225 Opwijk Vlaams-Brabant 1745",
    "addr:housenumber":"225",
    "addr:postcode":"1745",
    "addr:street":"Neerveldstraat",
    "iso:country":"BE",
    "sg:address":"Neerveldstraat 225",
    "sg:city":"Opwijk",
    "sg:classifiers":[
        {
            "category":"Insurance",
            "subcategory":"Insurance Agent",
            "type":"Services"
        }
    ],
    "sg:phone":"+32 52 35 89 18",
    "sg:postcode":"1745",
    "sg:province":"Vlaams-Brabant",
    "sg:tags":[
        "broker"
    ],
    "wof:name":"Verhaevert L",
    "wof:placetype":"venue"
},
  "geometry": {"coordinates":[4.1767578125,50.9823646545],"type":"Point"}
}