{
  "type": "Feature",
  "properties": {
    "iso:country":"BE",
    "sg:address":"G. Van Der Lindenlaan 61",
    "sg:city":"Duffel",
    "sg:orig_category":"Herstellingen and onderhoud van auto's",
    "sg:phone":"+32 15 32 17 36",
    "sg:postcode":"2570",
    "sg:province":"Antwerpen",
    "wof:name":"Car Wash Akhtar",
    "wof:placetype":"venue"
},
  "geometry": {"coordinates":[4.5065422058,51.098613739],"type":"Point"}
}