{
  "type": "Feature",
  "properties": {
    "addr:full":"Kraanweg 9 Bornem Antwerpen 2880",
    "addr:housenumber":"9",
    "addr:postcode":"2880",
    "addr:street":"Kraanweg",
    "iso:country":"BE",
    "sg:address":"Kraanweg 9",
    "sg:city":"Bornem",
    "sg:orig_category":"Animations diverses. Services divers aux personnes. Location de mat\u00e9riel pour banquets and \u00e9v\u00e9nement",
    "sg:phone":"+32 3 889 67 35",
    "sg:postcode":"2880",
    "sg:province":"Antwerpen",
    "wof:name":"Mdh All Round Animatie",
    "wof:placetype":"venue"
},
  "geometry": {"coordinates":[4.248570919,51.0950584412],"type":"Point"}
}