{
  "type": "Feature",
  "properties": {
    "iso:country":"BE",
    "sg:address":"Itterbeeksebaan 195",
    "sg:city":"Dilbeek",
    "sg:orig_category":"Tuinen",
    "sg:phone":"+32 2 466 14 09",
    "sg:postcode":"1701",
    "sg:province":"Vlaams-Brabant",
    "wof:name":"J P De Visscher",
    "wof:placetype":"venue"
},
  "geometry": {"coordinates":[4.2586808205,50.8364715576],"type":"Point"}
}