{
  "type": "Feature",
  "properties": {
    "addr:full":"Fransmanstraat 8 Brussel/bruxelles Bruxelles-Capitale 1020",
    "addr:housenumber":"8",
    "addr:postcode":"1020",
    "addr:street":"Fransmanstraat;/",
    "iso:country":"BE",
    "sg:address":"Fransmanstraat 8",
    "sg:city":"Brussel/bruxelles",
    "sg:orig_category":"Dameskledingzaken",
    "sg:phone":"+32 2 428 66 89",
    "sg:postcode":"1020",
    "sg:province":"Bruxelles-Capitale",
    "wof:name":"Boutique Chris",
    "wof:placetype":"venue"
},
  "geometry": {"coordinates":[4.3463392258,50.8776855469],"type":"Point"}
}