{
  "type": "Feature",
  "properties": {
    "addr:full":"Beerveldedorp 62 Lochristi Oost-Vlaanderen 9080",
    "addr:housenumber":"62",
    "addr:postcode":"9080",
    "addr:street":"Beerveldedorp",
    "iso:country":"BE",
    "sg:address":"Beerveldedorp 62",
    "sg:city":"Lochristi",
    "sg:classifiers":[
        {
            "category":"Personal",
            "subcategory":"Beauty Salon",
            "type":"Services"
        }
    ],
    "sg:phone":"+32 9 355 99 39",
    "sg:postcode":"9080",
    "sg:province":"Oost-Vlaanderen",
    "sg:tags":[
        "de",
        "coiffure"
    ],
    "wof:name":"Coiffure Lutgarde",
    "wof:placetype":"venue"
},
  "geometry": {"coordinates":[3.8785049915,51.0799102783],"type":"Point"}
}