{
  "type": "Feature",
  "properties": {
    "iso:country":"BE",
    "sg:address":"Kortrijksestraat 180",
    "sg:city":"Kuurne",
    "sg:orig_category":"Epiceries",
    "sg:phone":"+32 56 35 43 48",
    "sg:postcode":"8520",
    "sg:province":"West-Vlaanderen",
    "wof:name":"Huis Farell",
    "wof:placetype":"venue"
},
  "geometry": {"coordinates":[3.2745049,50.8449668884],"type":"Point"}
}