{
  "type": "Feature",
  "properties": {
    "addr:full":"Serskampsteenweg 255 Wetteren Oost-Vlaanderen 9230",
    "addr:housenumber":"255",
    "addr:postcode":"9230",
    "addr:street":"Serskampsteenweg",
    "iso:country":"BE",
    "sg:address":"Serskampsteenweg 255",
    "sg:city":"Wetteren",
    "sg:classifiers":[
        {
            "category":"Banks & Credit Unions",
            "subcategory":"Investment Brokerage",
            "type":"Services"
        }
    ],
    "sg:phone":"+32 9 369 07 06",
    "sg:postcode":"9230",
    "sg:province":"Oost-Vlaanderen",
    "sg:tags":[
        "fence"
    ],
    "wof:name":"Bruyninx J",
    "wof:placetype":"venue"
},
  "geometry": {"coordinates":[3.9028310776,50.9993095398],"type":"Point"}
}