{
  "type": "Feature",
  "properties": {
    "addr:full":"Dorpstraat 105 Bertem Vlaams-Brabant 3060",
    "addr:housenumber":"105",
    "addr:postcode":"3060",
    "addr:street":"Dorpstraat",
    "iso:country":"BE",
    "sg:address":"Dorpstraat 105",
    "sg:city":"Bertem",
    "sg:classifiers":[
        {
            "category":"Freight",
            "type":"Transportation"
        }
    ],
    "sg:phone":"+32 16 48 92 47",
    "sg:postcode":"3060",
    "sg:province":"Vlaams-Brabant",
    "sg:tags":[
        "-",
        "transport"
    ],
    "wof:name":"Appel's Trans",
    "wof:placetype":"venue"
},
  "geometry": {"coordinates":[4.6190991402,50.8590965271],"type":"Point"}
}