{
  "type": "Feature",
  "properties": {
    "addr:full":"Kerkstraat 110ba Evergem Oost-Vlaanderen 9940",
    "addr:housenumber":"110ba",
    "addr:postcode":"9940",
    "addr:street":"Kerkstraat;Oost-Vlaanderen",
    "iso:country":"BE",
    "sg:address":"Kerkstraat 110ba",
    "sg:city":"Evergem",
    "sg:orig_category":"Produits \u00e0 base de pommes de terre Articles de jardin. Fruits and l\u00e9gumes Gr",
    "sg:phone":"+32 9 357 31 41",
    "sg:postcode":"9940",
    "sg:province":"Oost-Vlaanderen",
    "wof:name":"Roger Van Beveren",
    "wof:placetype":"venue"
},
  "geometry": {"coordinates":[3.6908099651,51.1406745911],"type":"Point"}
}