{
  "type": "Feature",
  "properties": {
    "iso:country":"BE",
    "sg:address":"Rue Saint-remacle 5",
    "sg:city":"Li\u00e8ge 1 (li\u00e8ge 2)",
    "sg:classifiers":[
        {
            "category":"Food & Beverages",
            "subcategory":"Groceries & Convenience Stores",
            "type":"Retail Goods"
        }
    ],
    "sg:phone":"+32 4 343 02 35",
    "sg:postcode":"4020",
    "sg:province":"Li\u00e8ge",
    "sg:tags":[
        "baker",
        "-",
        "ingredient"
    ],
    "wof:name":"Jamin Marcel Sa",
    "wof:placetype":"venue"
},
  "geometry": {"coordinates":[5.5893149376,50.6370277405],"type":"Point"}
}