{
  "type": "Feature",
  "properties": {
    "iso:country":"BE",
    "sg:address":"11",
    "sg:city":"Grote Markt 3000 Leuven",
    "sg:classifiers":[
        {
            "category":"Travel",
            "subcategory":"Hotels & Motels",
            "type":"Entertainment"
        }
    ],
    "sg:phone":"+32 16 22 37 62",
    "sg:postcode":"11",
    "sg:tags":[
        "hotels",
        "business",
        "restaurant"
    ],
    "wof:name":"De Notre-dame Nv",
    "wof:placetype":"venue"
},
  "geometry": {"coordinates":[4.7001547813,50.8791160583],"type":"Point"}
}