{
  "type": "Feature",
  "properties": {
    "iso:country":"BE",
    "sg:address":"Nestor De Ti\u00e8restraat 189",
    "sg:city":"Oudenaarde",
    "sg:classifiers":[
        {
            "category":"Shopping",
            "subcategory":"Clothing, Apparel, & Fashions",
            "type":"Retail Goods"
        }
    ],
    "sg:phone":"+32 55 31 26 11",
    "sg:postcode":"9700",
    "sg:province":"Oost-Vlaanderen",
    "sg:tags":[
        "boutique"
    ],
    "wof:name":"Ohio Clean",
    "wof:placetype":"venue"
},
  "geometry": {"coordinates":[3.6208219528,50.8690261841],"type":"Point"}
}