{
  "type": "Feature",
  "properties": {
    "addr:full":"Tweekerkenstraat 1 Erpe-mere Oost-Vlaanderen 9420",
    "addr:housenumber":"1",
    "addr:postcode":"9420",
    "addr:street":"Tweekerkenstraat",
    "iso:country":"BE",
    "sg:address":"Tweekerkenstraat 1",
    "sg:city":"Erpe-mere",
    "sg:orig_category":"Woningbouw",
    "sg:phone":"+32 53 62 86 33",
    "sg:postcode":"9420",
    "sg:province":"Oost-Vlaanderen",
    "wof:name":"Van Boxstael Steven",
    "wof:placetype":"venue"
},
  "geometry": {"coordinates":[3.9213650227,50.9160385132],"type":"Point"}
}