{
  "type": "Feature",
  "properties": {
    "addr:full":"Schaarbeekstraat 25 Beveren (melsele) Oost-Vlaanderen 9120",
    "addr:housenumber":"25",
    "addr:postcode":"9120",
    "addr:street":"Schaarbeekstraat",
    "iso:country":"BE",
    "sg:address":"Schaarbeekstraat 25",
    "sg:city":"Beveren (melsele)",
    "sg:classifiers":[
        {
            "category":"Building & Trades",
            "subcategory":"Equipment Rental",
            "type":"Services"
        }
    ],
    "sg:phone":"+32 3 254 15 19",
    "sg:postcode":"9120",
    "sg:province":"Oost-Vlaanderen",
    "sg:tags":[
        "use",
        "apparatus",
        "tool",
        "-",
        "professional",
        "machines"
    ],
    "wof:name":"Mdu",
    "wof:placetype":"venue"
},
  "geometry": {"coordinates":[4.314622879,51.2013969421],"type":"Point"}
}