{
  "type": "Feature",
  "properties": {
    "iso:country":"BE",
    "sg:address":"Hekkestraat 14b",
    "sg:city":"Aalst (hofstade)",
    "sg:classifiers":[
        {
            "category":"Government",
            "subcategory":"Department Of Motor Vehicles",
            "type":"Public Place"
        }
    ],
    "sg:phone":"+32 53 78 02 15",
    "sg:postcode":"9308",
    "sg:province":"Oost-Vlaanderen",
    "sg:tags":[
        "planing",
        "wood",
        "sawing"
    ],
    "wof:name":"Buekens P",
    "wof:placetype":"venue"
},
  "geometry": {"coordinates":[4.0347590446,50.9603500366],"type":"Point"}
}