{
  "type": "Feature",
  "properties": {
    "iso:country":"BE",
    "sg:address":"Klauwaartslaan 14",
    "sg:city":"Elsene/ixelles",
    "sg:orig_category":"Artsen and specialisten",
    "sg:phone":"+32 2 647 42 01",
    "sg:postcode":"1050",
    "sg:province":"Bruxelles-Capitale",
    "wof:name":"Gilbert Lyon",
    "wof:placetype":"venue"
},
  "geometry": {"coordinates":[4.3749880791,50.8218154907],"type":"Point"}
}