{
  "type": "Feature",
  "properties": {
    "addr:full":"Av. De For\u00cat De Soignes 304 Sint-genesius-rode/rhode-saint-genese Vlaams-Brabant 1640",
    "addr:housenumber":"304",
    "addr:postcode":"1640",
    "addr:street":"Av. De Fore\u0302T De Soignes",
    "iso:country":"BE",
    "sg:address":"Av. De For\u00cat De Soignes 304",
    "sg:city":"Sint-genesius-rode/rhode-saint-genese",
    "sg:orig_category":"Entretien and r\u00e9parations de voitures",
    "sg:phone":"+32 2 358 42 99",
    "sg:postcode":"1640",
    "sg:province":"Vlaams-Brabant",
    "wof:name":"Willem De Greef",
    "wof:placetype":"venue"
},
  "geometry": {"coordinates":[4.3784108162,50.7563591003],"type":"Point"}
}