{
  "type": "Feature",
  "properties": {
    "addr:full":"Kerkstraat 108 Ghent 9050",
    "addr:housenumber":"108",
    "addr:postcode":"9050",
    "addr:street":"Kerkstraat",
    "iso:country":"BE",
    "sg:address":"Kerkstraat 108",
    "sg:city":"Ghent",
    "sg:classifiers":[
        {
            "category":"Professional",
            "subcategory":"Computer Services",
            "type":"Services"
        }
    ],
    "sg:postcode":"9050",
    "sg:tags":[
        "navigation",
        "routes",
        "route-search",
        "route-database",
        "walking",
        "cycling",
        "route-planning",
        "outdoor-navigation"
    ],
    "sg:website":"http://www.routeyou.com",
    "wof:name":"RouteYou",
    "wof:placetype":"venue"
},
  "geometry": {"coordinates":[3.75144,51.044163],"type":"Point"}
}