{
  "type": "Feature",
  "properties": {
    "iso:country":"BE",
    "sg:address":"Dries 19",
    "sg:city":"Oordegem",
    "sg:classifiers":[
        {
            "category":"Bars & Pubs",
            "type":"Food & Drink"
        }
    ],
    "sg:phone":"+32 9 366 15 75",
    "sg:postcode":"9340",
    "sg:province":"Oost-Vlaanderen",
    "sg:tags":[
        "tavern"
    ],
    "wof:name":"In Den Appel",
    "wof:placetype":"venue"
},
  "geometry": {"coordinates":[3.8968648911,50.962310791],"type":"Point"}
}