{
  "type": "Feature",
  "properties": {
    "addr:full":"Hertenstraat 12a Wellen Limburg 3830",
    "addr:housenumber":"12a",
    "addr:postcode":"3830",
    "addr:street":"Hertenstraat",
    "iso:country":"BE",
    "sg:address":"Hertenstraat 12a",
    "sg:city":"Wellen",
    "sg:classifiers":[
        {
            "category":"Insurance",
            "subcategory":"Insurance Agent",
            "type":"Services"
        }
    ],
    "sg:phone":"+32 12 74 40 53",
    "sg:postcode":"3830",
    "sg:province":"Limburg",
    "sg:tags":[
        "broker"
    ],
    "wof:name":"Manshoven M",
    "wof:placetype":"venue"
},
  "geometry": {"coordinates":[5.3372302055,50.8350105286],"type":"Point"}
}