{
  "type": "Feature",
  "properties": {
    "addr:full":"Varkensmarkt 50b11 Diepenbeek Limburg 3590",
    "addr:housenumber":"50b11",
    "addr:postcode":"3590",
    "addr:street":"Varkensmarkt",
    "iso:country":"BE",
    "sg:address":"Varkensmarkt 50b11",
    "sg:city":"Diepenbeek",
    "sg:orig_category":"Rev\u00eatements de sols and murs",
    "sg:phone":"+32 11 35 22 04",
    "sg:postcode":"3590",
    "sg:province":"Limburg",
    "wof:name":"G. Berx",
    "wof:placetype":"venue"
},
  "geometry": {"coordinates":[5.4173002243,50.9069404602],"type":"Point"}
}