{
  "type": "Feature",
  "properties": {
    "iso:country":"BE",
    "sg:address":"Place Gustave Rome 3",
    "sg:city":"Amay",
    "sg:classifiers":[
        {
            "category":"Restaurant",
            "type":"Food & Drink"
        }
    ],
    "sg:phone":"+32 85 31 32 82",
    "sg:postcode":"4540",
    "sg:province":"Li\u00e8ge",
    "sg:tags":[
        "caf\u00e9s"
    ],
    "wof:name":"R\u00c9tro Taverne",
    "wof:placetype":"venue"
},
  "geometry": {"coordinates":[5.3205637932,50.5466041565],"type":"Point"}
}