{
  "type": "Feature",
  "properties": {
    "addr:full":"Rue Des Allies 274 Bruxelles Bruxelles-Capitale 1190",
    "addr:housenumber":"274",
    "addr:postcode":"1190",
    "addr:street":"Rue Des Allies",
    "iso:country":"BE",
    "sg:address":"Rue Des Allies 274",
    "sg:city":"Bruxelles",
    "sg:classifiers":[
        {
            "category":"Landmark",
            "subcategory":"Square",
            "type":"Public Place"
        }
    ],
    "sg:phone":"+32 2 344 08 03",
    "sg:postcode":"1190",
    "sg:province":"Bruxelles-Capitale",
    "sg:tags":[
        "creation",
        "presentation",
        "enterprise"
    ],
    "wof:name":"Tissoth\u00e8que (la) S.a.",
    "wof:placetype":"venue"
},
  "geometry": {"coordinates":[4.3272490501,50.8224105835],"type":"Point"}
}