{
  "type": "Feature",
  "properties": {
    "addr:full":"Opperije 45 Oudenaarde Oost-Vlaanderen 9700",
    "addr:housenumber":"45",
    "addr:postcode":"9700",
    "addr:street":"Opperije",
    "iso:country":"BE",
    "sg:address":"Opperije 45",
    "sg:city":"Oudenaarde",
    "sg:classifiers":[
        {
            "category":"Wholesale",
            "subcategory":"Wine & Distilled Alcoholic Beverages",
            "type":"Manufacturing & Wholesale Goods"
        }
    ],
    "sg:phone":"+32 55 31 47 68",
    "sg:postcode":"9700",
    "sg:province":"Oost-Vlaanderen",
    "sg:tags":[
        "whol",
        "-",
        "spirit",
        "mfg"
    ],
    "wof:name":"Vinilux Wijnimport Bvba",
    "wof:placetype":"venue"
},
  "geometry": {"coordinates":[3.630038023,50.8453063965],"type":"Point"}
}