{
  "type": "Feature",
  "properties": {
    "addr:full":"Wichelsesteenweg 3 Lede Oost-Vlaanderen 9340",
    "addr:housenumber":"3",
    "addr:postcode":"9340",
    "addr:street":"Wichelsesteenweg",
    "iso:country":"BE",
    "sg:address":"Wichelsesteenweg 3",
    "sg:city":"Lede",
    "sg:orig_category":"Art and fournitures artistiques. Equipement photographique",
    "sg:phone":"+32 53 80 86 85",
    "sg:postcode":"9340",
    "sg:province":"Oost-Vlaanderen",
    "wof:name":"Foto-ateljee Hein",
    "wof:placetype":"venue"
},
  "geometry": {"coordinates":[3.974545002,50.9802284241],"type":"Point"}
}