{
  "type": "Feature",
  "properties": {
    "addr:full":"Panhovenstraat 3 Peer Limburg 3990",
    "addr:housenumber":"3",
    "addr:postcode":"3990",
    "addr:street":"Panhovenstraat",
    "iso:country":"BE",
    "sg:address":"Panhovenstraat 3",
    "sg:city":"Peer",
    "sg:classifiers":[
        {
            "category":"Home & Garden",
            "subcategory":"Garden Supply",
            "type":"Retail Goods"
        }
    ],
    "sg:phone":"+32 11 63 13 34",
    "sg:postcode":"3990",
    "sg:province":"Limburg",
    "wof:name":"Partoens Y",
    "wof:placetype":"venue"
},
  "geometry": {"coordinates":[5.4814009666,51.1475067139],"type":"Point"}
}