{
  "type": "Feature",
  "properties": {
    "iso:country":"BE",
    "sg:address":"Molendijk 20",
    "sg:city":"Retie",
    "sg:orig_category":"Afbraak- and draineerwerken Huisvuilophaling and -verwerking",
    "sg:phone":"+32 14 37 85 33",
    "sg:postcode":"2470",
    "sg:province":"Antwerpen",
    "wof:name":"Paul Smets",
    "wof:placetype":"venue"
},
  "geometry": {"coordinates":[5.0666031837,51.2386054993],"type":"Point"}
}