{
  "type": "Feature",
  "properties": {
    "iso:country":"BE",
    "sg:address":"Vijve-dreef 73",
    "sg:city":"Wielsbeke",
    "sg:orig_category":"Diverse bedrijfsbeheeradviesbureaus",
    "sg:phone":"+32 56 60 00 45",
    "sg:postcode":"8710",
    "sg:province":"West-Vlaanderen",
    "wof:name":"Wijnhoven J.",
    "wof:placetype":"venue"
},
  "geometry": {"coordinates":[3.396780014,50.9272842407],"type":"Point"}
}