{
  "type": "Feature",
  "properties": {
    "addr:full":"13 Vliegveld 8560 Wevelgem 13",
    "addr:housenumber":"13;13",
    "addr:postcode":"8560",
    "addr:street":"Vliegveld",
    "iso:country":"BE",
    "sg:address":"13",
    "sg:city":"Vliegveld 8560 Wevelgem",
    "sg:classifiers":[
        {
            "category":"Home & Garden",
            "subcategory":"Furniture",
            "type":"Retail Goods"
        }
    ],
    "sg:phone":"+32 56 43 93 93",
    "sg:postcode":"13",
    "sg:tags":[
        "household",
        "wood"
    ],
    "wof:name":"Inoxytech Bvba",
    "wof:placetype":"venue"
},
  "geometry": {"coordinates":[3.2057549953,50.8186912537],"type":"Point"}
}