{
  "type": "Feature",
  "properties": {
    "iso:country":"BE",
    "sg:address":"Constantin Meunierstraat 80",
    "sg:city":"Leuven",
    "sg:classifiers":[
        {
            "category":"Professional",
            "subcategory":"Accounting & Tax Preparation",
            "type":"Services"
        }
    ],
    "sg:phone":"+32 16 22 58 52",
    "sg:postcode":"3000",
    "sg:province":"Vlaams-Brabant",
    "sg:tags":[
        "accountant"
    ],
    "wof:name":"De Groeve B",
    "wof:placetype":"venue"
},
  "geometry": {"coordinates":[4.7017650604,50.8705215454],"type":"Point"}
}