{
  "type": "Feature",
  "properties": {
    "iso:country":"BE",
    "sg:address":"Rue Du Centenaire 31",
    "sg:city":"Soumagne (cerexhe-heuseux)",
    "sg:classifiers":[
        {
            "category":"Health Services",
            "subcategory":"Health Practitioner",
            "type":"Services"
        }
    ],
    "sg:phone":"+32 4 377 02 47",
    "sg:postcode":"4632",
    "sg:province":"Li\u00e8ge",
    "sg:tags":[
        "physiotherapist"
    ],
    "wof:name":"Trillet Carole",
    "wof:placetype":"venue"
},
  "geometry": {"coordinates":[5.7279520035,50.6513252258],"type":"Point"}
}