{
  "type": "Feature",
  "properties": {
    "iso:country":"BE",
    "sg:address":"Kerkstraat 283",
    "sg:city":"Blankenberge",
    "sg:classifiers":[
        {
            "category":"Shopping",
            "subcategory":"Pets & Pet Supplies",
            "type":"Retail Goods"
        }
    ],
    "sg:phone":"+32 50 42 59 79",
    "sg:postcode":"8370",
    "sg:province":"West-Vlaanderen",
    "sg:tags":[
        "shop",
        "-"
    ],
    "wof:name":"Johnny's Dierenzaak",
    "wof:placetype":"venue"
},
  "geometry": {"coordinates":[3.1380369663,51.3075942993],"type":"Point"}
}