{
  "type": "Feature",
  "properties": {
    "iso:country":"BE",
    "sg:address":"Ballewijerweg 50",
    "sg:city":"Zonhoven",
    "sg:classifiers":[
        {
            "category":"Personal",
            "subcategory":"Beauty Salon",
            "type":"Services"
        }
    ],
    "sg:phone":"+32 11 82 37 21",
    "sg:postcode":"3520",
    "sg:province":"Limburg",
    "sg:tags":[
        "de",
        "coiffure"
    ],
    "wof:name":"Coiffure Viviane",
    "wof:placetype":"venue"
},
  "geometry": {"coordinates":[5.3938398361,50.9874534607],"type":"Point"}
}