{
  "type": "Feature",
  "properties": {
    "iso:country":"BE",
    "sg:address":"Opwijkstraat 3a",
    "sg:city":"Aalst (baardegem)",
    "sg:classifiers":[
        {
            "category":"Food & Beverages",
            "subcategory":"Groceries & Convenience Stores",
            "type":"Retail Goods"
        }
    ],
    "sg:phone":"+32 52 35 53 56",
    "sg:postcode":"9310",
    "sg:province":"Oost-Vlaanderen",
    "sg:tags":[
        "grocer"
    ],
    "wof:name":"Van Londersele",
    "wof:placetype":"venue"
},
  "geometry": {"coordinates":[4.1449699402,50.9577827454],"type":"Point"}
}