{
  "type": "Feature",
  "properties": {
    "iso:country":"BE",
    "sg:address":"Kloosterstraat 30",
    "sg:city":"Zele",
    "sg:orig_category":"Brood, gebak and snoepgoed",
    "sg:phone":"+32 52 52 01 14",
    "sg:postcode":"9240",
    "sg:province":"Oost-Vlaanderen",
    "wof:name":"'t Suikerhuisje",
    "wof:placetype":"venue"
},
  "geometry": {"coordinates":[4.0422101021,51.0693626404],"type":"Point"}
}