{
  "type": "Feature",
  "properties": {
    "addr:full":"Spoorweglaan 26 Boom Antwerpen 2850",
    "addr:housenumber":"26",
    "addr:postcode":"2850",
    "addr:street":"Spoorweglaan",
    "iso:country":"BE",
    "sg:address":"Spoorweglaan 26",
    "sg:city":"Boom",
    "sg:orig_category":"Enseignement maternel and primaire",
    "sg:phone":"+32 3 888 10 03",
    "sg:postcode":"2850",
    "sg:province":"Antwerpen",
    "wof:name":"Vrije Basisschool",
    "wof:placetype":"venue"
},
  "geometry": {"coordinates":[4.3693289757,51.0998725891],"type":"Point"}
}