{
  "type": "Feature",
  "properties": {
    "iso:country":"BE",
    "sg:address":"Richard Neyberghlaan 160",
    "sg:city":"Brussel/bruxelles",
    "sg:orig_category":"Kinderopvang",
    "sg:phone":"+32 2 284 24 11",
    "sg:postcode":"1020",
    "sg:province":"Bruxelles-Capitale",
    "wof:name":"Kidcare",
    "wof:placetype":"venue"
},
  "geometry": {"coordinates":[4.3427262306,50.8740730286],"type":"Point"}
}