{
  "type": "Feature",
  "properties": {
    "iso:country":"BE",
    "sg:address":"Berkenlaan 35",
    "sg:city":"Kapellen",
    "sg:orig_category":"Fleurs and plantes",
    "sg:phone":"+32 3 605 36 24",
    "sg:postcode":"2950",
    "sg:province":"Antwerpen",
    "wof:name":"Frans Ollevier",
    "wof:placetype":"venue"
},
  "geometry": {"coordinates":[4.4321432114,51.3204460144],"type":"Point"}
}