{
  "type": "Feature",
  "properties": {
    "iso:country":"BE",
    "sg:address":"Engelbeekstraat 34",
    "sg:city":"Diest",
    "sg:orig_category":"Boissons",
    "sg:phone":"+32 13 33 63 19",
    "sg:postcode":"3290",
    "sg:province":"Vlaams-Brabant",
    "wof:name":"Bierhandel Jannes",
    "wof:placetype":"venue"
},
  "geometry": {"coordinates":[5.0801911354,51.0134468079],"type":"Point"}
}