{
  "type": "Feature",
  "properties": {
    "iso:country":"BE",
    "sg:address":"Rue Grande 19",
    "sg:city":"Florenville",
    "sg:classifiers":[
        {
            "category":"Fast Food",
            "type":"Food & Drink"
        }
    ],
    "sg:phone":"+32 61 31 16 53",
    "sg:postcode":"6820",
    "sg:province":"Luxembourg",
    "sg:tags":[
        "meeneem",
        "restaurant"
    ],
    "wof:name":"Friterie Le Corner",
    "wof:placetype":"venue"
},
  "geometry": {"coordinates":[5.1749000549,49.7162094116],"type":"Point"}
}