{
  "type": "Feature",
  "properties": {
    "addr:full":"Grand-rue 225 Florennes Namur 5621",
    "addr:housenumber":"225",
    "addr:postcode":"5621",
    "addr:street":"Grand-Rue",
    "iso:country":"BE",
    "sg:address":"Grand-rue 225",
    "sg:city":"Florennes",
    "sg:orig_category":"Woningbouw",
    "sg:phone":"+32 71 68 93 24",
    "sg:postcode":"5621",
    "sg:province":"Namur",
    "wof:name":"Gillain Richard & Cie",
    "wof:placetype":"venue"
},
  "geometry": {"coordinates":[4.5655431747,50.2760696411],"type":"Point"}
}