{
  "type": "Feature",
  "properties": {
    "addr:full":"Chauss\u00c9e D\u00b4arlon 6 Bastogne Luxembourg 6600",
    "addr:housenumber":"6",
    "addr:postcode":"6600",
    "addr:street":"Chausse\u0301E D\u00b4Arlon",
    "iso:country":"BE",
    "sg:address":"Chauss\u00c9e D\u00b4arlon 6",
    "sg:city":"Bastogne",
    "sg:orig_category":"Fleurs and plantes. Meubles D\u00e9taillants, Am\u00e9nagement de B\u00e2timents et de Cuisines. Textiles. Eclairag",
    "sg:phone":"+32 61 21 60 96",
    "sg:postcode":"6600",
    "sg:province":"Luxembourg",
    "wof:name":"Espace D\u00c9coration",
    "wof:placetype":"venue"
},
  "geometry": {"coordinates":[5.717854023,49.997051239],"type":"Point"}
}