{
  "type": "Feature",
  "properties": {
    "addr:full":"Av. Du P\u00e9age 68 Bruxelles Bruxelles-Capitale 1200",
    "addr:housenumber":"68",
    "addr:postcode":"1200",
    "addr:street":"Av. Du Pe\u0301Age",
    "iso:country":"BE",
    "sg:address":"Av. Du P\u00e9age 68",
    "sg:city":"Bruxelles",
    "sg:classifiers":[
        {
            "category":"Autos & Motor Vehicles",
            "subcategory":"Automobile Sales",
            "type":"Retail Goods"
        }
    ],
    "sg:phone":"+32 2 724 12 11",
    "sg:postcode":"1200",
    "sg:province":"Bruxelles-Capitale",
    "sg:tags":[
        "equipment",
        "motor-cars",
        "transport"
    ],
    "wof:name":"Daimlerchrysler Belgium Luxembourg Sa",
    "wof:placetype":"venue"
},
  "geometry": {"coordinates":[4.4303731918,50.8608322144],"type":"Point"}
}