{
  "type": "Feature",
  "properties": {
    "addr:full":"En Haute Marexhe 150 Herstal Li\u00e8ge 4040",
    "addr:housenumber":"150",
    "addr:postcode":"4040",
    "iso:country":"BE",
    "sg:address":"En Haute Marexhe 150",
    "sg:city":"Herstal",
    "sg:orig_category":"Enseignement maternel and primaire",
    "sg:phone":"+32 4 264 28 27",
    "sg:postcode":"4040",
    "sg:province":"Li\u00e8ge",
    "wof:name":"Ecole Prim. Communale",
    "wof:placetype":"venue"
},
  "geometry": {"coordinates":[5.6252288818,50.6580085754],"type":"Point"}
}