{
  "type": "Feature",
  "properties": {
    "iso:country":"BE",
    "sg:address":"Vogelzangwijk 5",
    "sg:city":"Boortmeerbeek",
    "sg:orig_category":"Medische apparatuur, orthopedische artikelen and prothesen Fab",
    "sg:phone":"+32 15 51 46 84",
    "sg:postcode":"3190",
    "sg:province":"Vlaams-Brabant",
    "wof:name":"Eddy Rosbach",
    "wof:placetype":"venue"
},
  "geometry": {"coordinates":[4.5811901093,50.9724121094],"type":"Point"}
}