{
  "type": "Feature",
  "properties": {
    "iso:country":"BE",
    "sg:address":"Steenweg 300",
    "sg:city":"Alken",
    "sg:orig_category":"Ruimtes voor conferenties, recepties and feesten",
    "sg:phone":"+32 11 31 28 07",
    "sg:postcode":"3570",
    "sg:province":"Limburg",
    "wof:name":"Traiteur Paul",
    "wof:placetype":"venue"
},
  "geometry": {"coordinates":[5.2643852234,50.8751602173],"type":"Point"}
}