{
  "type": "Feature",
  "properties": {
    "iso:country":"BE",
    "sg:address":"Lijneveldstraat 42",
    "sg:city":"Buggenhout",
    "sg:classifiers":[
        {
            "category":"Real Estate",
            "subcategory":"Real Estate Services",
            "type":"Services"
        }
    ],
    "sg:phone":"+32 52 34 05 37",
    "sg:postcode":"9255",
    "sg:province":"Oost-Vlaanderen",
    "wof:name":"Knarf Cv",
    "wof:placetype":"venue"
},
  "geometry": {"coordinates":[4.2244358063,51.0250930786],"type":"Point"}
}