{
  "type": "Feature",
  "properties": {
    "iso:country":"BE",
    "sg:address":"Village 37",
    "sg:city":"Olne",
    "sg:orig_category":"Artsen and specialisten",
    "sg:phone":"+32 87 26 82 64",
    "sg:postcode":"4877",
    "sg:province":"Li\u00e8ge",
    "wof:name":"Jean Moutschen",
    "wof:placetype":"venue"
},
  "geometry": {"coordinates":[5.7473530769,50.5906181335],"type":"Point"}
}