{
  "type": "Feature",
  "properties": {
    "addr:full":"Th. Van Cauwenberghslei 111 Schoten Antwerpen 2900",
    "addr:housenumber":"111",
    "addr:postcode":"2900",
    "addr:street":"Th. Van Cauwenberghslei",
    "iso:country":"BE",
    "sg:address":"Th. Van Cauwenberghslei 111",
    "sg:city":"Schoten",
    "sg:orig_category":"Bouwmaterialen Gh Dakwerken",
    "sg:phone":"+32 3 685 46 86",
    "sg:postcode":"2900",
    "sg:province":"Antwerpen",
    "wof:name":"A-vier",
    "wof:placetype":"venue"
},
  "geometry": {"coordinates":[4.5064768791,51.2527236938],"type":"Point"}
}