{
  "type": "Feature",
  "properties": {
    "addr:full":"Rue De Philippeville 107 Nalinnes Hainaut 6120",
    "addr:housenumber":"107",
    "addr:postcode":"6120",
    "addr:street":"Rue De Philippeville",
    "iso:country":"BE",
    "sg:address":"Rue De Philippeville 107",
    "sg:city":"Nalinnes",
    "sg:orig_category":"Joinery Supraregional",
    "sg:phone":"+32 71 84 52 59",
    "sg:postcode":"6120",
    "sg:province":"Hainaut",
    "wof:name":"Revat Jean-pierre",
    "wof:placetype":"venue"
},
  "geometry": {"coordinates":[4.4511561394,50.5378227234],"type":"Point"}
}