{
  "type": "Feature",
  "properties": {
    "iso:country":"BE",
    "sg:address":"Alfons Gossetlaan 3 Box 10",
    "sg:city":"Dilbeek (groot - Bijgaarden)",
    "sg:classifiers":[
        {
            "category":"Real Estate",
            "subcategory":"Developer",
            "type":"Services"
        }
    ],
    "sg:phone":"+32 2 466 04 68",
    "sg:postcode":"1702",
    "sg:province":"Vlaams-Brabant",
    "sg:tags":[
        "project"
    ],
    "wof:name":"Seconim Nv",
    "wof:placetype":"venue"
},
  "geometry": {"coordinates":[4.2849087715,50.8734283447],"type":"Point"}
}