{
  "type": "Feature",
  "properties": {
    "iso:country":"BE",
    "sg:address":"Werviksestr 94",
    "sg:city":"Ieper",
    "sg:classifiers":[
        {
            "category":"Building & Trades",
            "subcategory":"Construction",
            "type":"Services"
        }
    ],
    "sg:phone":"+32 57 20 23 49",
    "sg:postcode":"8902",
    "sg:province":"West-Vlaanderen",
    "sg:tags":[
        "work",
        "public"
    ],
    "wof:name":"Verfaillie-leroy & Co Nv",
    "wof:placetype":"venue"
},
  "geometry": {"coordinates":[2.9278280735,50.828742981],"type":"Point"}
}