{
  "type": "Feature",
  "properties": {
    "addr:full":"Rue Des Goutteaux 67 Charleroi Hainaut 6043",
    "addr:housenumber":"67",
    "addr:postcode":"6043",
    "addr:street":"Rue Des Goutteaux;Hainaut",
    "iso:country":"BE",
    "sg:address":"Rue Des Goutteaux 67",
    "sg:city":"Charleroi",
    "sg:orig_category":"Travaux de pl\u00e2trage",
    "sg:phone":"+32 71 35 69 04",
    "sg:postcode":"6043",
    "sg:province":"Hainaut",
    "wof:name":"Serra Mario Construct",
    "wof:placetype":"venue"
},
  "geometry": {"coordinates":[4.4086070061,50.3880081177],"type":"Point"}
}