{
  "type": "Feature",
  "properties": {
    "addr:full":"Avenue Albert I 143 Box 102 Ottignies-louvain-la-neuve (limelette) Brabant Wallon 1342",
    "addr:housenumber":"143",
    "addr:postcode":"1342",
    "addr:street":"Avenue Albert I;Box 102 Ottignies-Louvain-La-Neuve",
    "iso:country":"BE",
    "sg:address":"Avenue Albert I 143 Box 102",
    "sg:city":"Ottignies-louvain-la-neuve (limelette)",
    "sg:classifiers":[
        {
            "category":"Building & Trades",
            "subcategory":"Landscaping Services",
            "type":"Services"
        }
    ],
    "sg:phone":"+32 10 41 36 93",
    "sg:postcode":"1342",
    "sg:province":"Brabant Wallon",
    "sg:tags":[
        "gardening",
        "garden",
        "maintenance"
    ],
    "wof:name":"Art Du Jardin (l')",
    "wof:placetype":"venue"
},
  "geometry": {"coordinates":[4.5728960037,50.6801300049],"type":"Point"}
}