{
  "type": "Feature",
  "properties": {
    "addr:full":"Chauss\u00c9e De Charleroi 74 Lasne Brabant Wallon 1380",
    "addr:housenumber":"74",
    "addr:postcode":"1380",
    "addr:street":"Chausse\u0301E De Charleroi",
    "iso:country":"BE",
    "sg:address":"Chauss\u00c9e De Charleroi 74",
    "sg:city":"Lasne",
    "sg:orig_category":"Diensten voor huisdieren Huisdierenkwekers",
    "sg:phone":"+32 2 387 11 57",
    "sg:postcode":"1380",
    "sg:province":"Brabant Wallon",
    "wof:name":"La Maison Du Chien",
    "wof:placetype":"venue"
},
  "geometry": {"coordinates":[4.4127998352,50.65599823],"type":"Point"}
}