{
  "type": "Feature",
  "properties": {
    "iso:country":"BE",
    "sg:address":"Staakskenstraat 42",
    "sg:city":"Gent",
    "sg:classifiers":[
        {
            "category":"Bakery",
            "type":"Food & Drink"
        }
    ],
    "sg:phone":"+32 9 227 11 51",
    "sg:postcode":"9000",
    "sg:province":"Oost-Vlaanderen",
    "sg:tags":[
        "confectioner",
        "baker"
    ],
    "wof:name":"Yes (bakkerij)",
    "wof:placetype":"venue"
},
  "geometry": {"coordinates":[3.6957509518,51.0712547302],"type":"Point"}
}