{
  "type": "Feature",
  "properties": {
    "addr:full":"Rue Du Respois 21 Anhee Namur 5537",
    "addr:housenumber":"21",
    "addr:postcode":"5537",
    "addr:street":"Rue Du Respois;Namur",
    "iso:country":"BE",
    "sg:address":"Rue Du Respois 21",
    "sg:city":"Anhee",
    "sg:orig_category":"V\u00e9t\u00e9rinaires",
    "sg:phone":"+32 82 61 46 57",
    "sg:postcode":"5537",
    "sg:province":"Namur",
    "wof:name":"Daniel Wauthier",
    "wof:placetype":"venue"
},
  "geometry": {"coordinates":[4.8732728958,50.3098678589],"type":"Point"}
}