{
  "type": "Feature",
  "properties": {
    "addr:full":"Tongersesteenweg 25 Hoeselt Limburg 3730",
    "addr:housenumber":"25",
    "addr:postcode":"3730",
    "addr:street":"Tongersesteenweg",
    "iso:country":"BE",
    "sg:address":"Tongersesteenweg 25",
    "sg:city":"Hoeselt",
    "sg:classifiers":[
        {
            "category":"Restaurant",
            "type":"Food & Drink"
        }
    ],
    "sg:phone":"+32 89 41 19 41",
    "sg:postcode":"3730",
    "sg:province":"Limburg",
    "wof:name":"Maurice",
    "wof:placetype":"venue"
},
  "geometry": {"coordinates":[5.4896302223,50.8483085632],"type":"Point"}
}