{
  "type": "Feature",
  "properties": {
    "addr:full":"Rue De La Promenade 38 Aubange (athus) Luxembourg 6791",
    "addr:housenumber":"38",
    "addr:postcode":"6791",
    "addr:street":"Rue De La Promenade",
    "iso:country":"BE",
    "sg:address":"Rue De La Promenade 38",
    "sg:city":"Aubange (athus)",
    "sg:classifiers":[
        {
            "category":"Health Services",
            "subcategory":"Doctor",
            "type":"Services"
        }
    ],
    "sg:phone":"+32 63 38 48 55",
    "sg:postcode":"6791",
    "sg:province":"Luxembourg",
    "sg:tags":[
        "medicinephysicians",
        "surgeon"
    ],
    "wof:name":"De Houck Yvette",
    "wof:placetype":"venue"
},
  "geometry": {"coordinates":[5.8368301392,49.5627288818],"type":"Point"}
}