{
  "type": "Feature",
  "properties": {
    "iso:country":"BE",
    "sg:address":"Luchtstraat 3",
    "sg:city":"Torhout",
    "sg:orig_category":"Groententeelt",
    "sg:phone":"+32 50 21 52 20",
    "sg:postcode":"8820",
    "sg:province":"West-Vlaanderen",
    "wof:name":"Geert Van Hulle",
    "wof:placetype":"venue"
},
  "geometry": {"coordinates":[3.1433539391,51.0853691101],"type":"Point"}
}