{
  "type": "Feature",
  "properties": {
    "iso:country":"BE",
    "sg:address":"Industrieweg-noord 1111",
    "sg:city":"Opglabbeek",
    "sg:classifiers":[
        {
            "category":"Building & Trades",
            "subcategory":"Electrical",
            "type":"Services"
        }
    ],
    "sg:phone":"+32 89 85 36 36",
    "sg:postcode":"3660",
    "sg:province":"Limburg",
    "sg:tags":[
        "plants",
        "plant",
        "industrial",
        "buildings",
        "construction"
    ],
    "wof:name":"Industriebouw I 3 Nv",
    "wof:placetype":"venue"
},
  "geometry": {"coordinates":[5.5345897675,51.0350112915],"type":"Point"}
}