{
  "type": "Feature",
  "properties": {
    "iso:country":"BE",
    "sg:address":"Kapelstraat 38",
    "sg:city":"Balen",
    "sg:classifiers":[
        {
            "category":"Professional",
            "subcategory":"Management & Consulting",
            "type":"Services"
        }
    ],
    "sg:phone":"+32 14 81 42 07",
    "sg:postcode":"2490",
    "sg:province":"Antwerpen",
    "sg:tags":[
        "-",
        "processing",
        "data",
        "consultant"
    ],
    "wof:name":"Gypen B",
    "wof:placetype":"venue"
},
  "geometry": {"coordinates":[5.26086092,51.1824226379],"type":"Point"}
}