{
  "type": "Feature",
  "properties": {
    "iso:country":"BE",
    "sg:address":"Steenweg Op Waterloo 602",
    "sg:city":"Elsene",
    "sg:classifiers":[
        {
            "category":"Travel",
            "subcategory":"Travel Agent",
            "type":"Entertainment"
        }
    ],
    "sg:phone":"+32 2 345 98 48",
    "sg:postcode":"1050",
    "sg:province":"Bruxelles-Capitale",
    "sg:tags":[
        "holiday",
        "flash",
        "plus",
        "reisbureaus"
    ],
    "wof:name":"Flash Travel",
    "wof:placetype":"venue"
},
  "geometry": {"coordinates":[4.3643932343,50.8181114197],"type":"Point"}
}