{
  "type": "Feature",
  "properties": {
    "iso:country":"BE",
    "sg:address":"Rue Des Graffes 100bb",
    "sg:city":"Courcelles",
    "sg:classifiers":[
        {
            "category":"Insurance",
            "subcategory":"Insurance Agent",
            "type":"Services"
        }
    ],
    "sg:phone":"+32 71 46 09 42",
    "sg:postcode":"6182",
    "sg:province":"Hainaut",
    "sg:tags":[
        "verzekeringsmakelaars",
        "expert"
    ],
    "wof:name":"P.m.e. Financinvest",
    "wof:placetype":"venue"
},
  "geometry": {"coordinates":[4.3544812202,50.4422836304],"type":"Point"}
}