{
  "type": "Feature",
  "properties": {
    "addr:full":"Place Joseph Thiry 43 Aywaille Li\u00e8ge 4920",
    "addr:housenumber":"43",
    "addr:postcode":"4920",
    "addr:street":"Place Joseph Thiry",
    "iso:country":"BE",
    "sg:address":"Place Joseph Thiry 43",
    "sg:city":"Aywaille",
    "sg:orig_category":"Banken and kredietinstellingen",
    "sg:phone":"+32 4 384 40 66",
    "sg:postcode":"4920",
    "sg:province":"Li\u00e8ge",
    "wof:name":"Bbl",
    "wof:placetype":"venue"
},
  "geometry": {"coordinates":[5.6753001213,50.4745407104],"type":"Point"}
}