{
  "type": "Feature",
  "properties": {
    "addr:full":"Eendrachtstraat 66 Gent Oost-Vlaanderen 9000",
    "addr:housenumber":"66",
    "addr:postcode":"9000",
    "addr:street":"Eendrachtstraat;Oost-Vlaanderen",
    "iso:country":"BE",
    "sg:address":"Eendrachtstraat 66",
    "sg:city":"Gent",
    "sg:orig_category":"Boekbinderijen and afwerking Drukkerijen and copyshops Technische studies and ingenieursactiviteiten",
    "sg:phone":"+32 9 225 51 76",
    "sg:postcode":"9000",
    "sg:province":"Oost-Vlaanderen",
    "wof:name":"Rob-grafiek",
    "wof:placetype":"venue"
},
  "geometry": {"coordinates":[3.7424049377,51.0488700867],"type":"Point"}
}