{
  "type": "Feature",
  "properties": {
    "iso:country":"BE",
    "sg:address":"Rue De Corbeau 75",
    "sg:city":"Courcelles",
    "sg:orig_category":"Entretien and r\u00e9parations de voitures. V\u00e9hicules automobiles",
    "sg:phone":"+32 71 45 30 72",
    "sg:postcode":"6183",
    "sg:province":"Hainaut",
    "wof:name":"Garage Moriconi",
    "wof:placetype":"venue"
},
  "geometry": {"coordinates":[4.3369469643,50.4709358215],"type":"Point"}
}