{
  "type": "Feature",
  "properties": {
    "iso:country":"BE",
    "sg:address":"Markt 22",
    "sg:city":"Londerzeel",
    "sg:orig_category":"Artsen and specialisten",
    "sg:phone":"+32 52 30 98 60",
    "sg:postcode":"1840",
    "sg:province":"Vlaams-Brabant",
    "wof:name":"J. Vanlievendael",
    "wof:placetype":"venue"
},
  "geometry": {"coordinates":[4.3022217751,51.0019454956],"type":"Point"}
}