{
  "type": "Feature",
  "properties": {
    "iso:country":"BE",
    "sg:address":"Rue De La Quemogne 38",
    "sg:city":"Chievres",
    "sg:orig_category":"Fleurs and plantes",
    "sg:phone":"+32 69 68 81 74",
    "sg:postcode":"7950",
    "sg:province":"Hainaut",
    "wof:name":"Maison Cr\u00c9a Caro",
    "wof:placetype":"venue"
},
  "geometry": {"coordinates":[3.7471721172,50.5590324402],"type":"Point"}
}