{
  "type": "Feature",
  "properties": {
    "iso:country":"BE",
    "sg:address":"Egemsebinnenweg 23",
    "sg:city":"Pittem",
    "sg:classifiers":[
        {
            "category":"Wholesale",
            "subcategory":"Plants",
            "type":"Manufacturing & Wholesale Goods"
        }
    ],
    "sg:phone":"+32 51 46 67 63",
    "sg:postcode":"8740",
    "sg:province":"West-Vlaanderen",
    "sg:tags":[
        "whol",
        "flower",
        "-",
        "grower"
    ],
    "wof:name":"Cool W",
    "wof:placetype":"venue"
},
  "geometry": {"coordinates":[3.2540960312,51.0025215149],"type":"Point"}
}