{
  "type": "Feature",
  "properties": {
    "addr:full":"Chauss\u00c9e De Waterloo 35 Sint-genesius-rode/rhode-saint-genese Vlaams-Brabant 1640",
    "addr:housenumber":"35",
    "addr:postcode":"1640",
    "addr:street":"Chausse\u0301E De Waterloo",
    "iso:country":"BE",
    "sg:address":"Chauss\u00c9e De Waterloo 35",
    "sg:city":"Sint-genesius-rode/rhode-saint-genese",
    "sg:orig_category":"Meubles D\u00e9taillants, Am\u00e9nagement de B\u00e2timents et de Cuisines",
    "sg:phone":"+32 2 358 40 07",
    "sg:postcode":"1640",
    "sg:province":"Vlaams-Brabant",
    "wof:name":"Cosy Corner",
    "wof:placetype":"venue"
},
  "geometry": {"coordinates":[4.3950901031,50.7466201782],"type":"Point"}
}