{
  "type": "Feature",
  "properties": {
    "addr:full":"Champs Elys\u00e9es 24 Ciney Namur 5590",
    "addr:housenumber":"24",
    "addr:postcode":"5590",
    "iso:country":"BE",
    "sg:address":"Champs Elys\u00e9es 24",
    "sg:city":"Ciney",
    "sg:classifiers":[
        {
            "category":"Retail",
            "subcategory":"Auto Repair",
            "type":"Services"
        }
    ],
    "sg:phone":"+32 83 21 19 24",
    "sg:postcode":"5590",
    "sg:province":"Namur",
    "sg:tags":[
        "garage"
    ],
    "wof:name":"Hennau Garage",
    "wof:placetype":"venue"
},
  "geometry": {"coordinates":[5.0996251106,50.3148384094],"type":"Point"}
}