{
  "type": "Feature",
  "properties": {
    "iso:country":"BE",
    "sg:address":"Heikantstraat 216",
    "sg:city":"Kalmthout",
    "sg:classifiers":[
        {
            "category":"Retail",
            "subcategory":"Veterinary Services",
            "type":"Services"
        }
    ],
    "sg:phone":"+32 3 666 06 55",
    "sg:postcode":"2920",
    "sg:province":"Antwerpen",
    "sg:tags":[
        "veterinarian"
    ],
    "wof:name":"Buschman D",
    "wof:placetype":"venue"
},
  "geometry": {"coordinates":[4.5042090416,51.3726158142],"type":"Point"}
}