{
  "type": "Feature",
  "properties": {
    "addr:full":"Pacificatiestraat 31ba Antwerpen Antwerpen 2000",
    "addr:housenumber":"31ba",
    "addr:postcode":"2000",
    "addr:street":"Pacificatiestraat",
    "iso:country":"BE",
    "sg:address":"Pacificatiestraat 31ba",
    "sg:city":"Antwerpen",
    "sg:orig_category":"Artistes ind\u00e9pendants",
    "sg:phone":"+32 3 248 35 86",
    "sg:postcode":"2000",
    "sg:province":"Antwerpen",
    "wof:name":"Isabel Leybaert",
    "wof:placetype":"venue"
},
  "geometry": {"coordinates":[4.388906002,51.206325531],"type":"Point"}
}