{
  "type": "Feature",
  "properties": {
    "addr:full":"Route De L'abbaye 62 Chaudfontaine Li\u00e8ge 4052",
    "addr:housenumber":"62",
    "addr:postcode":"4052",
    "addr:street":"Route De L'Abbaye",
    "iso:country":"BE",
    "sg:address":"Route De L'abbaye 62",
    "sg:city":"Chaudfontaine",
    "sg:orig_category":"Secr\u00e9tariats",
    "sg:phone":"+32 4 368 59 14",
    "sg:postcode":"4052",
    "sg:province":"Li\u00e8ge",
    "wof:name":"Bureau C Piriet",
    "wof:placetype":"venue"
},
  "geometry": {"coordinates":[5.643974781,50.5642662048],"type":"Point"}
}