{
  "type": "Feature",
  "properties": {
    "iso:country":"BE",
    "sg:address":"Kerkstraat 35",
    "sg:city":"Schilde",
    "sg:classifiers":[
        {
            "category":"Restaurant",
            "type":"Food & Drink"
        }
    ],
    "sg:phone":"+32 3 685 32 52",
    "sg:postcode":"2970",
    "sg:province":"Antwerpen",
    "wof:name":"Wombles",
    "wof:placetype":"venue"
},
  "geometry": {"coordinates":[4.5550518036,51.2633247375],"type":"Point"}
}