{
  "type": "Feature",
  "properties": {
    "addr:full":"Driesstraat 13 Kampenhout (nederokkerzeel) Vlaams-Brabant 1910",
    "addr:housenumber":"13",
    "addr:postcode":"1910",
    "addr:street":"Driesstraat",
    "iso:country":"BE",
    "sg:address":"Driesstraat 13",
    "sg:city":"Kampenhout (nederokkerzeel)",
    "sg:classifiers":[
        {
            "category":"Home & Garden",
            "subcategory":"Building Materials",
            "type":"Retail Goods"
        }
    ],
    "sg:phone":"+32 16 65 15 23",
    "sg:postcode":"1910",
    "sg:province":"Vlaams-Brabant",
    "sg:tags":[
        "wall",
        "cupboard"
    ],
    "wof:name":"Hubrechts B",
    "wof:placetype":"venue"
},
  "geometry": {"coordinates":[4.5688381195,50.9226837158],"type":"Point"}
}