{
  "type": "Feature",
  "properties": {
    "iso:country":"BE",
    "sg:address":"Kapellenstrasse 12",
    "sg:city":"B\u00dctgenbach/b\u00dctgenbach",
    "sg:orig_category":"Installation de menuiserie m\u00e9tallique",
    "sg:phone":"+32 80 44 73 79",
    "sg:postcode":"4750",
    "sg:province":"Li\u00e8ge",
    "wof:name":"Andreas Kuepper",
    "wof:placetype":"venue"
},
  "geometry": {"coordinates":[6.2206501961,50.457408905],"type":"Point"}
}