{
  "type": "Feature",
  "properties": {
    "iso:country":"BE",
    "sg:address":"Alsembloemlaan 10",
    "sg:city":"Beersel (alsemberg)",
    "sg:classifiers":[
        {
            "category":"Insurance",
            "subcategory":"Insurance Agent",
            "type":"Services"
        }
    ],
    "sg:phone":"+32 2 381 04 59",
    "sg:postcode":"1652",
    "sg:province":"Vlaams-Brabant",
    "sg:tags":[
        "broker"
    ],
    "wof:name":"Sleewaegen Raymond Cvoha",
    "wof:placetype":"venue"
},
  "geometry": {"coordinates":[4.3370480537,50.7415122986],"type":"Point"}
}