{
  "type": "Feature",
  "properties": {
    "iso:country":"BE",
    "sg:address":"Korte Kruisstraat 1",
    "sg:city":"Gent",
    "sg:classifiers":[
        {
            "category":"Cafe",
            "type":"Food & Drink"
        }
    ],
    "sg:phone":"+32 9 225 19 79",
    "sg:postcode":"9000",
    "sg:province":"Oost-Vlaanderen",
    "sg:tags":[
        "snack-bars"
    ],
    "wof:name":"De Ruyck Bvba",
    "wof:placetype":"venue"
},
  "geometry": {"coordinates":[3.7251019478,51.052444458],"type":"Point"}
}