{
  "type": "Feature",
  "properties": {
    "iso:country":"BE",
    "sg:address":"Paul Deschanellaan 86b14",
    "sg:city":"Schaarbeek/schaerbeek",
    "sg:orig_category":"Zalen voor culturele evenementen",
    "sg:phone":"+32 2 216 15 10",
    "sg:postcode":"1030",
    "sg:province":"Bruxelles-Capitale",
    "wof:name":"Th\u00c9\u00c2tre Traverse",
    "wof:placetype":"venue"
},
  "geometry": {"coordinates":[4.3796520233,50.8601264954],"type":"Point"}
}