{
  "type": "Feature",
  "properties": {
    "addr:full":"Avenue Joseph Wauters 77 Beyne-heusay Li\u00e8ge 4610",
    "addr:housenumber":"77",
    "addr:postcode":"4610",
    "addr:street":"Avenue Joseph Wauters",
    "iso:country":"BE",
    "sg:address":"Avenue Joseph Wauters 77",
    "sg:city":"Beyne-heusay",
    "sg:orig_category":"Artsen and specialisten",
    "sg:phone":"+32 4 365 10 41",
    "sg:postcode":"4610",
    "sg:province":"Li\u00e8ge",
    "wof:name":"Mich\u00c8le Gerard",
    "wof:placetype":"venue"
},
  "geometry": {"coordinates":[5.6548938751,50.6264762878],"type":"Point"}
}