{
  "type": "Feature",
  "properties": {
    "iso:country":"BE",
    "sg:address":"Brusselsesteenweg 123",
    "sg:city":"Melle",
    "sg:classifiers":[
        {
            "category":"Professional",
            "subcategory":"Advertising",
            "type":"Services"
        }
    ],
    "sg:phone":"+32 9 230 23 23",
    "sg:postcode":"9090",
    "sg:province":"Oost-Vlaanderen",
    "sg:tags":[
        "studio"
    ],
    "wof:name":"Aqui",
    "wof:placetype":"venue"
},
  "geometry": {"coordinates":[3.7798349857,51.019367218],"type":"Point"}
}