{
  "type": "Feature",
  "properties": {
    "iso:country":"BE",
    "sg:address":"Avenue Commandant Lachouque 7",
    "sg:city":"Waterloo",
    "sg:classifiers":[
        {
            "category":"Building & Trades",
            "subcategory":"Pest Control",
            "type":"Services"
        }
    ],
    "sg:phone":"+32 2 384 57 35",
    "sg:postcode":"1410",
    "sg:province":"Brabant Wallon",
    "sg:tags":[
        "painting",
        "contractor"
    ],
    "wof:name":"Lupant G",
    "wof:placetype":"venue"
},
  "geometry": {"coordinates":[4.4034237862,50.6883850098],"type":"Point"}
}