{
  "type": "Feature",
  "properties": {
    "iso:country":"BE",
    "sg:address":"Avenue Victor Jacobs 78",
    "sg:city":"Bruxelles (etterbeek)",
    "sg:classifiers":[
        {
            "category":"Building & Trades",
            "subcategory":"Cleaning & Sanitation",
            "type":"Services"
        }
    ],
    "sg:phone":"+32 2 646 97 46",
    "sg:postcode":"1040",
    "sg:province":"Bruxelles-Capitale",
    "sg:tags":[
        "fa\u00e7ade",
        "maintenance"
    ],
    "wof:name":"Metamorphose Sprl",
    "wof:placetype":"venue"
},
  "geometry": {"coordinates":[4.3816947937,50.8300285339],"type":"Point"}
}