{
  "type": "Feature",
  "properties": {
    "iso:country":"BE",
    "sg:address":"Bondgenotenlaan 49",
    "sg:city":"Leuven",
    "sg:orig_category":"Baby- and kinderkleding",
    "sg:phone":"+32 16 23 74 96",
    "sg:postcode":"3000",
    "sg:province":"Vlaams-Brabant",
    "wof:name":"Jacadi",
    "wof:placetype":"venue"
},
  "geometry": {"coordinates":[4.7064509392,50.8799705505],"type":"Point"}
}