{
  "type": "Feature",
  "properties": {
    "iso:country":"BE",
    "sg:address":"Rue Des Steppes 24",
    "sg:city":"Liege",
    "sg:orig_category":"Astrologen, grafologen and mediums",
    "sg:phone":"+32 4 227 78 00",
    "sg:postcode":"4000",
    "sg:province":"Li\u00e8ge",
    "wof:name":"Arterre-c. Balsacg, J.-m.delhaye, C. Mercenier",
    "wof:placetype":"venue"
},
  "geometry": {"coordinates":[5.6020021439,50.6549034119],"type":"Point"}
}