{
  "type": "Feature",
  "properties": {
    "addr:full":"Rue De La Gare 81 Chapelle-lez-herlaimont Hainaut 7160",
    "addr:housenumber":"81",
    "addr:postcode":"7160",
    "addr:street":"Rue De La Gare;Hainaut",
    "iso:country":"BE",
    "sg:address":"Rue De La Gare 81",
    "sg:city":"Chapelle-lez-herlaimont",
    "sg:classifiers":[
        {
            "category":"Retail",
            "subcategory":"Auto Repair",
            "type":"Services"
        }
    ],
    "sg:phone":"+32 64 44 46 94",
    "sg:postcode":"7160",
    "sg:province":"Hainaut",
    "sg:tags":[
        "garage"
    ],
    "wof:name":"Mr Polito",
    "wof:placetype":"venue"
},
  "geometry": {"coordinates":[4.2735300064,50.4659385681],"type":"Point"}
}