{
  "type": "Feature",
  "properties": {
    "addr:full":"Pastoor Pennestraat 38 Berlare (overmere) Oost-Vlaanderen 9290",
    "addr:housenumber":"38",
    "addr:postcode":"9290",
    "addr:street":"Pastoor Pennestraat",
    "iso:country":"BE",
    "sg:address":"Pastoor Pennestraat 38",
    "sg:city":"Berlare (overmere)",
    "sg:classifiers":[
        {
            "category":"Health Services",
            "subcategory":"Health Practitioner",
            "type":"Services"
        }
    ],
    "sg:phone":"+32 9 367 75 57",
    "sg:postcode":"9290",
    "sg:province":"Oost-Vlaanderen",
    "sg:tags":[
        "physiotherapist"
    ],
    "wof:name":"Borgelioen J",
    "wof:placetype":"venue"
},
  "geometry": {"coordinates":[3.9515099525,51.0447921753],"type":"Point"}
}