{
  "type": "Feature",
  "properties": {
    "iso:country":"BE",
    "sg:address":"Rentestraat 6",
    "sg:city":"Maldegem",
    "sg:classifiers":[
        {
            "category":"Arena",
            "subcategory":"Sports Club",
            "type":"Entertainment"
        }
    ],
    "sg:phone":"+32 50 71 05 07",
    "sg:postcode":"9992",
    "sg:province":"Oost-Vlaanderen",
    "sg:tags":[
        "de"
    ],
    "wof:name":"De Grensvliegers",
    "wof:placetype":"venue"
},
  "geometry": {"coordinates":[3.4166600704,51.2572631836],"type":"Point"}
}