{
  "type": "Feature",
  "properties": {
    "iso:country":"BE",
    "sg:address":"Rue De La Pott\u00e9r\u00e9e 1",
    "sg:city":"Braine-le-ch\u00e2teau",
    "sg:classifiers":[
        {
            "category":"Sports & Exercise",
            "subcategory":"Stables",
            "type":"Entertainment"
        }
    ],
    "sg:phone":"+32 2 366 02 92",
    "sg:postcode":"1440",
    "sg:province":"Brabant Wallon",
    "sg:tags":[
        "riding",
        "school"
    ],
    "wof:name":"Ecuries De La Poterie (les)",
    "wof:placetype":"venue"
},
  "geometry": {"coordinates":[4.2461819649,50.6791992188],"type":"Point"}
}