{
  "type": "Feature",
  "properties": {
    "addr:full":"Windekekouter 84 Oosterzele Oost-Vlaanderen 9860",
    "addr:housenumber":"84",
    "addr:postcode":"9860",
    "addr:street":"Windekekouter;Oost-Vlaanderen",
    "iso:country":"BE",
    "sg:address":"Windekekouter 84",
    "sg:city":"Oosterzele",
    "sg:classifiers":[
        {
            "category":"Wholesale",
            "subcategory":"Plants",
            "type":"Manufacturing & Wholesale Goods"
        }
    ],
    "sg:phone":"+32 9 362 56 39",
    "sg:postcode":"9860",
    "sg:province":"Oost-Vlaanderen",
    "sg:tags":[
        "whol",
        "flower",
        "-",
        "grower"
    ],
    "wof:name":"De Moor L & Zn Boomkwekerijen",
    "wof:placetype":"venue"
},
  "geometry": {"coordinates":[3.7967059612,50.9433021545],"type":"Point"}
}