{
  "type": "Feature",
  "properties": {
    "iso:country":"BE",
    "sg:address":"Peperstraat 19",
    "sg:city":"Kortenberg (erps-kwerps)",
    "sg:classifiers":[
        {
            "category":"Building & Trades",
            "subcategory":"Equipment Rental",
            "type":"Services"
        }
    ],
    "sg:phone":"+32 2 759 72 52",
    "sg:postcode":"3071",
    "sg:province":"Vlaams-Brabant",
    "sg:tags":[
        "lighting",
        "-",
        "fixture"
    ],
    "wof:name":"H D Light Equipment",
    "wof:placetype":"venue"
},
  "geometry": {"coordinates":[4.5589637756,50.9044303894],"type":"Point"}
}