{
  "type": "Feature",
  "properties": {
    "addr:full":"Rue Des Jolis-bois 61 Marche-en-famenne Luxembourg 6900",
    "addr:housenumber":"61",
    "addr:postcode":"6900",
    "addr:street":"Rue Des Jolis-Bois",
    "iso:country":"BE",
    "sg:address":"Rue Des Jolis-bois 61",
    "sg:city":"Marche-en-famenne",
    "sg:orig_category":"Postkantoren Verzekeringsmakelaars and experts",
    "sg:phone":"+32 84 31 17 26",
    "sg:postcode":"6900",
    "sg:province":"Luxembourg",
    "wof:name":"La Poste",
    "wof:placetype":"venue"
},
  "geometry": {"coordinates":[5.2926678658,50.223575592],"type":"Point"}
}