{
  "type": "Feature",
  "properties": {
    "addr:full":"Moorselbaan 449 Aalst Oost-Vlaanderen 9300",
    "addr:housenumber":"449",
    "addr:postcode":"9300",
    "addr:street":"Moorselbaan",
    "iso:country":"BE",
    "sg:address":"Moorselbaan 449",
    "sg:city":"Aalst",
    "sg:orig_category":"Brood, gebak and snoepgoed",
    "sg:phone":"+32 53 77 51 53",
    "sg:postcode":"9300",
    "sg:province":"Oost-Vlaanderen",
    "wof:name":"Hubert Van Driessche",
    "wof:placetype":"venue"
},
  "geometry": {"coordinates":[4.0691947937,50.9446754456],"type":"Point"}
}