{
  "type": "Feature",
  "properties": {
    "addr:full":"Chauss\u00c9e Paul Houtart 166 La Louviere Hainaut 7110",
    "addr:housenumber":"166",
    "addr:postcode":"7110",
    "addr:street":"Chausse\u0301E Paul Houtart",
    "iso:country":"BE",
    "sg:address":"Chauss\u00c9e Paul Houtart 166",
    "sg:city":"La Louviere",
    "sg:orig_category":"Belastingconsulenten Diverse juridische dienstverlening",
    "sg:phone":"+32 64 26 04 81",
    "sg:postcode":"7110",
    "sg:province":"Hainaut",
    "wof:name":"La Financi\u00c8re",
    "wof:placetype":"venue"
},
  "geometry": {"coordinates":[4.1623911858,50.4845046997],"type":"Point"}
}