{
  "type": "Feature",
  "properties": {
    "addr:full":"Borgstraat 102 Sint-amands Antwerpen 2890",
    "addr:housenumber":"102",
    "addr:postcode":"2890",
    "addr:street":"Borgstraat",
    "iso:country":"BE",
    "sg:address":"Borgstraat 102",
    "sg:city":"Sint-amands",
    "sg:orig_category":"Elektrische installaties voor woningen",
    "sg:phone":"+32 52 33 35 70",
    "sg:postcode":"2890",
    "sg:province":"Antwerpen",
    "wof:name":"Amede De Nijn",
    "wof:placetype":"venue"
},
  "geometry": {"coordinates":[4.204023838,51.0540733337],"type":"Point"}
}