{
  "type": "Feature",
  "properties": {
    "addr:full":"Bergensesteenweg 375 Sint-pieters-leeuw Vlaams-Brabant 1600",
    "addr:housenumber":"375",
    "addr:postcode":"1600",
    "addr:street":"Bergensesteenweg",
    "iso:country":"BE",
    "sg:address":"Bergensesteenweg 375",
    "sg:city":"Sint-pieters-leeuw",
    "sg:orig_category":"Installatie van houten of kunststof schrijnwerk",
    "sg:phone":"+32 2 377 39 97",
    "sg:postcode":"1600",
    "sg:province":"Vlaams-Brabant",
    "wof:name":"Jacobs-tierens",
    "wof:placetype":"venue"
},
  "geometry": {"coordinates":[4.2804598808,50.7899513245],"type":"Point"}
}