{
  "type": "Feature",
  "properties": {
    "iso:country":"BE",
    "sg:address":"Rue D'oultremont 24",
    "sg:city":"Etterbeek",
    "sg:orig_category":"Rusthuizen and serviceflats",
    "sg:phone":"+32 2 736 43 00",
    "sg:postcode":"1040",
    "sg:province":"Bruxelles-Capitale",
    "wof:name":"R\u00c9sidence D'oultremont",
    "wof:placetype":"venue"
},
  "geometry": {"coordinates":[4.3979167938,50.8416786194],"type":"Point"}
}