{
  "type": "Feature",
  "properties": {
    "addr:full":"Kapelstraat 7 Hasselt Limburg 3500",
    "addr:housenumber":"7",
    "addr:postcode":"3500",
    "addr:street":"Kapelstraat",
    "iso:country":"BE",
    "sg:address":"Kapelstraat 7",
    "sg:city":"Hasselt",
    "sg:classifiers":[
        {
            "category":"Fast Food",
            "type":"Food & Drink"
        }
    ],
    "sg:phone":"+32 11 22 15 59",
    "sg:postcode":"3500",
    "sg:province":"Limburg",
    "sg:tags":[
        "de",
        "restaurant",
        "organisation",
        "\u00e0",
        "catering",
        "emporter",
        "f\u00eates"
    ],
    "wof:name":"Het Groene Huis",
    "wof:placetype":"venue"
},
  "geometry": {"coordinates":[5.3369541168,50.9299087524],"type":"Point"}
}