{
  "type": "Feature",
  "properties": {
    "addr:full":"Rue De Mangombroux 201 Verviers Li\u00e8ge 4800",
    "addr:housenumber":"201",
    "addr:postcode":"4800",
    "addr:street":"Rue De Mangombroux",
    "iso:country":"BE",
    "sg:address":"Rue De Mangombroux 201",
    "sg:city":"Verviers",
    "sg:orig_category":"Plomberie, chauffage and installations sanitaires",
    "sg:phone":"+32 87 35 50 63",
    "sg:postcode":"4800",
    "sg:province":"Li\u00e8ge",
    "wof:name":"H. Baumans",
    "wof:placetype":"venue"
},
  "geometry": {"coordinates":[5.873488903,50.5874023438],"type":"Point"}
}