{
  "type": "Feature",
  "properties": {
    "iso:country":"BE",
    "sg:address":"Heldenplein 35",
    "sg:city":"Gent",
    "sg:classifiers":[
        {
            "category":"Utilities",
            "subcategory":"Natural Gas",
            "type":"Services"
        }
    ],
    "sg:phone":"+32 9 236 12 95",
    "sg:postcode":"9000",
    "sg:province":"Oost-Vlaanderen",
    "sg:tags":[
        "welding"
    ],
    "wof:name":"Dierickx D",
    "wof:placetype":"venue"
},
  "geometry": {"coordinates":[3.6944959164,51.0527915955],"type":"Point"}
}