{
  "type": "Feature",
  "properties": {
    "addr:full":"Rue Rogier 53 Verviers Li\u00e8ge 4800",
    "addr:housenumber":"53",
    "addr:postcode":"4800",
    "addr:street":"Rue Rogier",
    "iso:country":"BE",
    "sg:address":"Rue Rogier 53",
    "sg:city":"Verviers",
    "sg:orig_category":"M\u00e9decins and sp\u00e9cialistes",
    "sg:phone":"+32 87 22 83 83",
    "sg:postcode":"4800",
    "sg:province":"Li\u00e8ge",
    "wof:name":"M. Van Laer",
    "wof:placetype":"venue"
},
  "geometry": {"coordinates":[5.8537421227,50.5844841003],"type":"Point"}
}