{
  "type": "Feature",
  "properties": {
    "addr:full":"Kazernestraat 32 Heist-op-den-berg (schriek) Antwerpen 2223",
    "addr:housenumber":"32",
    "addr:postcode":"2223",
    "addr:street":"Kazernestraat",
    "iso:country":"BE",
    "sg:address":"Kazernestraat 32",
    "sg:city":"Heist-op-den-berg (schriek)",
    "sg:orig_category":"Nuts, Custom Manufactured",
    "sg:phone":"+32 53 77 01 02",
    "sg:postcode":"2223",
    "sg:province":"Antwerpen",
    "wof:name":"Alcoa",
    "wof:placetype":"venue"
},
  "geometry": {"coordinates":[4.0566449165,50.9211578369],"type":"Point"}
}