{
  "type": "Feature",
  "properties": {
    "iso:country":"BE",
    "sg:address":"Jan Van Rijswijcklaan 260r Box 21",
    "sg:city":"Antwerpen",
    "sg:classifiers":[
        {
            "category":"Social Services",
            "subcategory":"Job Training",
            "type":"Services"
        }
    ],
    "sg:phone":"+32 3 294 33 86",
    "sg:postcode":"2020",
    "sg:province":"Antwerpen",
    "sg:tags":[
        "interpreter"
    ],
    "wof:name":"Carraltec",
    "wof:placetype":"venue"
},
  "geometry": {"coordinates":[4.3923478127,51.1867256165],"type":"Point"}
}