{
  "type": "Feature",
  "properties": {
    "iso:country":"BE",
    "sg:address":"Kersendaelstraat 11",
    "sg:city":"Kortessem",
    "sg:orig_category":"Maisons de repos and r\u00e9sidences",
    "sg:phone":"+32 12 39 18 00",
    "sg:postcode":"3724",
    "sg:province":"Limburg",
    "wof:name":"Huyse Fliedermael",
    "wof:placetype":"venue"
},
  "geometry": {"coordinates":[5.4302148819,50.838760376],"type":"Point"}
}