{
  "type": "Feature",
  "properties": {
    "iso:country":"BE",
    "sg:address":"Rue Nouvelle 28",
    "sg:city":"Habay",
    "sg:orig_category":"Artsen and specialisten",
    "sg:phone":"+32 63 41 12 03",
    "sg:postcode":"6724",
    "sg:province":"Luxembourg",
    "wof:name":"Didier Guebs",
    "wof:placetype":"venue"
},
  "geometry": {"coordinates":[5.5597100258,49.7180557251],"type":"Point"}
}