{
  "type": "Feature",
  "properties": {
    "iso:country":"BE",
    "sg:address":"Holvenstraat 129",
    "sg:city":"Overpelt",
    "sg:orig_category":"Artsen and specialisten",
    "sg:phone":"+32 11 64 34 91",
    "sg:postcode":"3900",
    "sg:province":"Limburg",
    "wof:name":"Albric Vandorpe",
    "wof:placetype":"venue"
},
  "geometry": {"coordinates":[5.3769478798,51.2061653137],"type":"Point"}
}