{
  "type": "Feature",
  "properties": {
    "iso:country":"BE",
    "sg:address":"Rue D\u00e9sir\u00e9 Dejardin 20",
    "sg:city":"Wanze (vinalmont)",
    "sg:classifiers":[
        {
            "category":"Building & Trades",
            "subcategory":"Landscaping Services",
            "type":"Services"
        }
    ],
    "sg:phone":"+32 85 23 15 97",
    "sg:postcode":"4520",
    "sg:province":"Li\u00e8ge",
    "sg:tags":[
        "gardening",
        "garden",
        "maintenance"
    ],
    "wof:name":"Dethier M",
    "wof:placetype":"venue"
},
  "geometry": {"coordinates":[5.2117958069,50.5641174316],"type":"Point"}
}