{
  "type": "Feature",
  "properties": {
    "addr:full":"Vossekotstraat 26 Sint-niklaas Oost-Vlaanderen 9100",
    "addr:housenumber":"26",
    "addr:postcode":"9100",
    "addr:street":"Vossekotstraat",
    "iso:country":"BE",
    "sg:address":"Vossekotstraat 26",
    "sg:city":"Sint-niklaas",
    "sg:orig_category":"Woningbouw",
    "sg:phone":"+32 3 778 01 05",
    "sg:postcode":"9100",
    "sg:province":"Oost-Vlaanderen",
    "wof:name":"Luc Van Roeyen",
    "wof:placetype":"venue"
},
  "geometry": {"coordinates":[4.19480896,51.1777496338],"type":"Point"}
}