{
  "type": "Feature",
  "properties": {
    "addr:full":"Rue Rodenbach 78-80 Bruxelles (forest) Bruxelles-Capitale 1190",
    "addr:housenumber":"78-80",
    "addr:postcode":"1190",
    "addr:street":"Rue Rodenbach",
    "iso:country":"BE",
    "sg:address":"Rue Rodenbach 78-80",
    "sg:city":"Bruxelles (forest)",
    "sg:classifiers":[
        {
            "category":"Building & Trades",
            "subcategory":"Construction",
            "type":"Services"
        }
    ],
    "sg:phone":"+32 2 343 60 05",
    "sg:postcode":"1190",
    "sg:province":"Bruxelles-Capitale",
    "sg:tags":[
        "stucco",
        "contractor"
    ],
    "wof:name":"Serbat Sa",
    "wof:placetype":"venue"
},
  "geometry": {"coordinates":[4.3445219994,50.8178062439],"type":"Point"}
}