{
  "type": "Feature",
  "properties": {
    "addr:full":"Mastenbaan 14 Zandhoven Antwerpen 2242",
    "addr:housenumber":"14",
    "addr:postcode":"2242",
    "addr:street":"Mastenbaan",
    "iso:country":"BE",
    "sg:address":"Mastenbaan 14",
    "sg:city":"Zandhoven",
    "sg:orig_category":"Sportclubs Sportterreinen and installaties behalve sportcentra",
    "sg:phone":"+32 3 484 36 20",
    "sg:postcode":"2242",
    "sg:province":"Antwerpen",
    "wof:name":"Heidebloem Fc",
    "wof:placetype":"venue"
},
  "geometry": {"coordinates":[4.7044758797,51.2249412537],"type":"Point"}
}