{
  "type": "Feature",
  "properties": {
    "iso:country":"BE",
    "sg:address":"Rue De L'int\u00e9rieur 29",
    "sg:city":"Perwez (thorembais-saint-trond)",
    "sg:classifiers":[
        {
            "category":"Food & Beverages",
            "subcategory":"Meat & Fish",
            "type":"Retail Goods"
        }
    ],
    "sg:phone":"+32 81 65 59 30",
    "sg:postcode":"1360",
    "sg:province":"Brabant Wallon",
    "sg:tags":[
        "-",
        "livestock"
    ],
    "wof:name":"Alin John Sprl",
    "wof:placetype":"venue"
},
  "geometry": {"coordinates":[4.7822270393,50.6341056824],"type":"Point"}
}