{
  "type": "Feature",
  "properties": {
    "addr:full":"Rue De La Chauss\u00c9e 52 Quevy Hainaut 7040",
    "addr:housenumber":"52",
    "addr:postcode":"7040",
    "addr:street":"Rue De La Chausse\u0301E;Hainaut",
    "iso:country":"BE",
    "sg:address":"Rue De La Chauss\u00c9e 52",
    "sg:city":"Quevy",
    "sg:orig_category":"RESTAURANTS: CAF\u00c9S",
    "sg:phone":"+32 65 56 83 96",
    "sg:postcode":"7040",
    "sg:province":"Hainaut",
    "wof:name":"Taverne Le Brunehault",
    "wof:placetype":"venue"
},
  "geometry": {"coordinates":[3.94688797,50.3603591919],"type":"Point"}
}