{
  "type": "Feature",
  "properties": {
    "iso:country":"BE",
    "sg:address":"Loksbergenstraat 61",
    "sg:city":"Halen",
    "sg:classifiers":[
        {
            "category":"Professional",
            "subcategory":"Testing Lab",
            "type":"Services"
        }
    ],
    "sg:phone":"+32 13 44 19 86",
    "sg:postcode":"3545",
    "sg:province":"Limburg",
    "sg:tags":[
        "chemist"
    ],
    "wof:name":"Bollen-moria",
    "wof:placetype":"venue"
},
  "geometry": {"coordinates":[5.066008091,50.9325828552],"type":"Point"}
}