{
  "type": "Feature",
  "properties": {
    "iso:country":"BE",
    "sg:address":"Rue Du Temple 137",
    "sg:city":"Mons",
    "sg:orig_category":"Belastingconsulenten Boekhouders Diverse juridische dienstverlening Verzekeringsmakelaars and expert",
    "sg:phone":"+32 65 33 56 56",
    "sg:postcode":"7011",
    "sg:province":"Hainaut",
    "wof:name":"Daniel Masseaux",
    "wof:placetype":"venue"
},
  "geometry": {"coordinates":[3.912539959,50.4712982178],"type":"Point"}
}