{
  "type": "Feature",
  "properties": {
    "iso:country":"BE",
    "sg:address":"Ondernemersstraat 4",
    "sg:city":"Hamont-achel",
    "sg:orig_category":"Industri\u00eble and commerci\u00eble bouw",
    "sg:phone":"+32 11 62 24 07",
    "sg:postcode":"3930",
    "sg:province":"Limburg",
    "wof:name":"Alfa Bouw-projecten",
    "wof:placetype":"venue"
},
  "geometry": {"coordinates":[5.5450549126,51.2511863708],"type":"Point"}
}