{
  "type": "Feature",
  "properties": {
    "iso:country":"BE",
    "sg:address":"Vieille Rue Du Moulin 85bb",
    "sg:city":"Ukkel/uccle",
    "sg:orig_category":"Architectes",
    "sg:phone":"+32 2 374 32 72",
    "sg:postcode":"1180",
    "sg:province":"Bruxelles-Capitale",
    "wof:name":"Fran\u00c7ois Vaneetvelde",
    "wof:placetype":"venue"
},
  "geometry": {"coordinates":[4.3648099899,50.7894706726],"type":"Point"}
}