{
  "type": "Feature",
  "properties": {
    "addr:full":"Enclos De Warelles 1 Qu\u00e9vy (qu\u00e9vy-le-grand) Hainaut 7040",
    "addr:housenumber":"1",
    "addr:postcode":"7040",
    "addr:street":"Enclos;Warelles;Que\u0301Vy-Le-Grand Hainaut",
    "iso:country":"BE",
    "sg:address":"Enclos De Warelles 1",
    "sg:city":"Qu\u00e9vy (qu\u00e9vy-le-grand)",
    "sg:classifiers":[
        {
            "category":"Manufacturing",
            "subcategory":"Chemicals & Compounds",
            "type":"Manufacturing & Wholesale Goods"
        }
    ],
    "sg:phone":"+32 65 56 80 19",
    "sg:postcode":"7040",
    "sg:province":"Hainaut",
    "sg:tags":[
        "agricultural"
    ],
    "wof:name":"Ewbank T",
    "wof:placetype":"venue"
},
  "geometry": {"coordinates":[3.9624550343,50.3746948242],"type":"Point"}
}