{
  "type": "Feature",
  "properties": {
    "addr:full":"Naamsesteenweg 52 Leuven (heverlee) Vlaams-Brabant 3001",
    "addr:housenumber":"52",
    "addr:postcode":"3001",
    "addr:street":"Naamsesteenweg",
    "iso:country":"BE",
    "sg:address":"Naamsesteenweg 52",
    "sg:city":"Leuven (heverlee)",
    "sg:classifiers":[
        {
            "category":"Professional",
            "subcategory":"Management & Consulting",
            "type":"Services"
        }
    ],
    "sg:phone":"+32 16 20 74 21",
    "sg:postcode":"3001",
    "sg:province":"Vlaams-Brabant",
    "sg:tags":[
        "consultant"
    ],
    "wof:name":"Sports \u00a7 Entertainement Management",
    "wof:placetype":"venue"
},
  "geometry": {"coordinates":[4.6970767975,50.8671722412],"type":"Point"}
}