{
  "type": "Feature",
  "properties": {
    "iso:country":"BE",
    "sg:address":"Iepersteenweg 1",
    "sg:city":"Houthulst",
    "sg:orig_category":"Eleveurs and marchands de porcs. Eleveurs de bovins",
    "sg:phone":"+32 51 54 58 25",
    "sg:postcode":"8650",
    "sg:province":"West-Vlaanderen",
    "wof:name":"Robert Ryckewaert",
    "wof:placetype":"venue"
},
  "geometry": {"coordinates":[2.8693199158,50.9711914062],"type":"Point"}
}