{
  "type": "Feature",
  "properties": {
    "iso:country":"BE",
    "sg:address":"Rue De La Station 70",
    "sg:city":"H\u00e9l\u00e9cine (neerheylissem)",
    "sg:classifiers":[
        {
            "category":"Health Services",
            "subcategory":"Health Practitioner",
            "type":"Services"
        }
    ],
    "sg:phone":"+32 19 65 55 22",
    "sg:postcode":"1357",
    "sg:province":"Brabant Wallon",
    "sg:tags":[
        "physiotherapist"
    ],
    "wof:name":"Verbrugghe Ief",
    "wof:placetype":"venue"
},
  "geometry": {"coordinates":[4.9904499054,50.761302948],"type":"Point"}
}