{
  "type": "Feature",
  "properties": {
    "iso:country":"BE",
    "sg:address":"Flamisoul 882",
    "sg:city":"Bertogne (longchamps)",
    "sg:classifiers":[
        {
            "category":"Health Services",
            "subcategory":"Health Practitioner",
            "type":"Services"
        }
    ],
    "sg:phone":"+32 61 21 79 61",
    "sg:postcode":"6688",
    "sg:province":"Luxembourg",
    "sg:tags":[
        "physiotherapist"
    ],
    "wof:name":"Lef\u00e8vre H",
    "wof:placetype":"venue"
},
  "geometry": {"coordinates":[5.689948082,50.0525741577],"type":"Point"}
}