{
  "type": "Feature",
  "properties": {
    "iso:country":"BE",
    "sg:address":"Herentalsebaan 498",
    "sg:city":"Wommelgem",
    "sg:classifiers":[
        {
            "category":"Building & Trades",
            "subcategory":"Construction",
            "type":"Services"
        }
    ],
    "sg:phone":"+32 3 354 29 10",
    "sg:postcode":"2160",
    "sg:province":"Antwerpen",
    "sg:tags":[
        "surveyor",
        "-"
    ],
    "wof:name":"Verstreken Expertisekantoor Bvba",
    "wof:placetype":"venue"
},
  "geometry": {"coordinates":[4.5108289719,51.196647644],"type":"Point"}
}