{
  "type": "Feature",
  "properties": {
    "addr:full":"Chauss\u00c9e De Gand 1191 Sint-agatha-berchem/berchem-sainte-agathe Bruxelles-Capitale 1082",
    "addr:housenumber":"1191",
    "addr:postcode":"1082",
    "addr:street":"Chausse\u0301E De Gand;/",
    "iso:country":"BE",
    "sg:address":"Chauss\u00c9e De Gand 1191",
    "sg:city":"Sint-agatha-berchem/berchem-sainte-agathe",
    "sg:classifiers":[
        {
            "category":"Personal",
            "subcategory":"Beauty Salon",
            "type":"Services"
        }
    ],
    "sg:phone":"+32 2 468 31 05",
    "sg:postcode":"1082",
    "sg:province":"Bruxelles-Capitale",
    "sg:tags":[
        "de",
        "coiffure"
    ],
    "wof:name":"Coiffure Michel Olivier",
    "wof:placetype":"venue"
},
  "geometry": {"coordinates":[4.2999858856,50.8630905151],"type":"Point"}
}