{
  "type": "Feature",
  "properties": {
    "iso:country":"BE",
    "sg:address":"Bellestraat 4",
    "sg:city":"Heuvelland",
    "sg:orig_category":"Pain, p\u00e2tisseries and confiseries",
    "sg:phone":"+32 57 44 44 74",
    "sg:postcode":"8954",
    "sg:province":"West-Vlaanderen",
    "wof:name":"Walther Taillieu",
    "wof:placetype":"venue"
},
  "geometry": {"coordinates":[2.7459011078,50.7849006653],"type":"Point"}
}