{
  "type": "Feature",
  "properties": {
    "iso:country":"BE",
    "sg:address":"Neerstraat 13",
    "sg:city":"Brakel",
    "sg:orig_category":"Agences de voyages",
    "sg:phone":"+32 55 42 70 80",
    "sg:postcode":"9660",
    "sg:province":"Oost-Vlaanderen",
    "wof:name":"Fiesta Reizen",
    "wof:placetype":"venue"
},
  "geometry": {"coordinates":[3.7657210827,50.8041267395],"type":"Point"}
}