{
  "type": "Feature",
  "properties": {
    "iso:country":"BE",
    "sg:address":"Kabuize 3",
    "sg:city":"Maarkedal",
    "sg:orig_category":"Eleveurs de bovins",
    "sg:phone":"+32 55 45 53 93",
    "sg:postcode":"9680",
    "sg:province":"Oost-Vlaanderen",
    "wof:name":"Etienne Vandenabeele",
    "wof:placetype":"venue"
},
  "geometry": {"coordinates":[3.6668150425,50.8164253235],"type":"Point"}
}