{
  "type": "Feature",
  "properties": {
    "addr:full":"Hoksentstraat 11 Hechtel-eksel Limburg 3941",
    "addr:housenumber":"11",
    "addr:postcode":"3941",
    "addr:street":"Hoksentstraat",
    "iso:country":"BE",
    "sg:address":"Hoksentstraat 11",
    "sg:city":"Hechtel-eksel",
    "sg:classifiers":[
        {
            "category":"Personal",
            "subcategory":"Beauty Salon",
            "type":"Services"
        }
    ],
    "sg:phone":"+32 11 63 28 35",
    "sg:postcode":"3941",
    "sg:province":"Limburg",
    "sg:tags":[
        "de",
        "coiffure"
    ],
    "wof:name":"Rita Waelburgs",
    "wof:placetype":"venue"
},
  "geometry": {"coordinates":[5.4141998291,51.1537780762],"type":"Point"}
}