{
  "type": "Feature",
  "properties": {
    "addr:full":"Rue Des Grives 51 Anderlecht Bruxelles-Capitale 1070",
    "addr:housenumber":"51",
    "addr:postcode":"1070",
    "addr:street":"Rue Des Grives",
    "iso:country":"BE",
    "sg:address":"Rue Des Grives 51",
    "sg:city":"Anderlecht",
    "sg:classifiers":[
        {
            "category":"Sports & Exercise",
            "subcategory":"Sports Center",
            "type":"Entertainment"
        }
    ],
    "sg:phone":"+32 2 523 11 65",
    "sg:postcode":"1070",
    "sg:province":"Bruxelles-Capitale",
    "sg:tags":[
        "terrain",
        "hors",
        "de",
        "installation",
        "sportifs"
    ],
    "wof:name":"Complexe Sportif Provincial",
    "wof:placetype":"venue"
},
  "geometry": {"coordinates":[4.2951288223,50.8170585632],"type":"Point"}
}