{
  "type": "Feature",
  "properties": {
    "addr:full":"Leopold Ii Laan 213 Koksijde (oostduinkerke) West-Vlaanderen 8670",
    "addr:housenumber":"213",
    "addr:postcode":"8670",
    "addr:street":"Leopold Ii Laan",
    "iso:country":"BE",
    "sg:address":"Leopold Ii Laan 213",
    "sg:city":"Koksijde (oostduinkerke)",
    "sg:classifiers":[
        {
            "category":"Shopping",
            "subcategory":"Clothing, Apparel, & Fashions",
            "type":"Retail Goods"
        }
    ],
    "sg:phone":"+32 58 52 04 29",
    "sg:postcode":"8670",
    "sg:province":"West-Vlaanderen",
    "sg:tags":[
        "lady",
        "clothing",
        "-"
    ],
    "wof:name":"Vue Sur Mer Oberon",
    "wof:placetype":"venue"
},
  "geometry": {"coordinates":[2.6729578972,51.1299781799],"type":"Point"}
}