{
  "type": "Feature",
  "properties": {
    "iso:country":"BE",
    "sg:address":"Hoog Heultje 69",
    "sg:city":"Westerlo",
    "sg:classifiers":[
        {
            "category":"Personal",
            "subcategory":"Beauty Salon",
            "type":"Services"
        }
    ],
    "sg:phone":"+32 16 69 99 14",
    "sg:postcode":"2260",
    "sg:province":"Antwerpen",
    "sg:tags":[
        "de",
        "coiffure"
    ],
    "wof:name":"Annick Gouwkens",
    "wof:placetype":"venue"
},
  "geometry": {"coordinates":[4.8352189064,51.0663032532],"type":"Point"}
}