{
  "type": "Feature",
  "properties": {
    "addr:full":"Rue De La Grande Haie 100 Etterbeek Bruxelles-Capitale 1040",
    "addr:housenumber":"100",
    "addr:postcode":"1040",
    "addr:street":"Rue De La Grande Haie",
    "iso:country":"BE",
    "sg:address":"Rue De La Grande Haie 100",
    "sg:city":"Etterbeek",
    "sg:classifiers":[
        {
            "category":"Government",
            "subcategory":"Fire Station",
            "type":"Public Place"
        }
    ],
    "sg:phone":"+32 2 732 13 88",
    "sg:postcode":"1040",
    "sg:province":"Bruxelles-Capitale",
    "sg:tags":[
        "packard",
        "nec",
        "bell"
    ],
    "wof:name":"Photo-hall Etterbeek",
    "wof:placetype":"venue"
},
  "geometry": {"coordinates":[4.3986721039,50.8349266052],"type":"Point"}
}