{
  "type": "Feature",
  "properties": {
    "addr:full":"Avenue Joseph Baeck 70 Bruxelles (molenbeek-saint-jean) Bruxelles-Capitale 1080",
    "addr:housenumber":"70",
    "addr:postcode":"1080",
    "addr:street":"Avenue Joseph Baeck",
    "iso:country":"BE",
    "sg:address":"Avenue Joseph Baeck 70",
    "sg:city":"Bruxelles (molenbeek-saint-jean)",
    "sg:classifiers":[
        {
            "category":"Autos & Motor Vehicles",
            "subcategory":"Automobile Sales",
            "type":"Retail Goods"
        }
    ],
    "sg:phone":"+32 2 410 00 73",
    "sg:postcode":"1080",
    "sg:province":"Bruxelles-Capitale",
    "sg:tags":[
        "ceremony",
        "car"
    ],
    "wof:name":"Brussels-limo",
    "wof:placetype":"venue"
},
  "geometry": {"coordinates":[4.3165988922,50.8514900208],"type":"Point"}
}