{
  "type": "Feature",
  "properties": {
    "iso:country":"BE",
    "sg:address":"Nationale Straat 151",
    "sg:city":"Antwerpen",
    "sg:classifiers":[
        {
            "category":"Restaurant",
            "type":"Food & Drink"
        }
    ],
    "sg:phone":"+32 3 231 64 31",
    "sg:postcode":"2000",
    "sg:province":"Antwerpen",
    "wof:name":"Dubrovnik",
    "wof:placetype":"venue"
},
  "geometry": {"coordinates":[4.397767067,51.2129020691],"type":"Point"}
}