{
  "type": "Feature",
  "properties": {
    "iso:country":"BE",
    "sg:address":"Koningin Astridlaan 17ba",
    "sg:city":"Maldegem",
    "sg:orig_category":"Installatie van houten of kunststof schrijnwerk",
    "sg:phone":"+32 50 71 63 41",
    "sg:postcode":"9990",
    "sg:province":"Oost-Vlaanderen",
    "wof:name":"Pascal Storm",
    "wof:placetype":"venue"
},
  "geometry": {"coordinates":[3.4454360008,51.2038154602],"type":"Point"}
}