{
  "type": "Feature",
  "properties": {
    "addr:full":"Grand-rue 24 Arlon Luxembourg 6700",
    "addr:housenumber":"24",
    "addr:postcode":"6700",
    "addr:street":"Grand-Rue",
    "iso:country":"BE",
    "sg:address":"Grand-rue 24",
    "sg:city":"Arlon",
    "sg:orig_category":"Warenhuizen",
    "sg:phone":"+32 63 23 05 10",
    "sg:postcode":"6700",
    "sg:province":"Luxembourg",
    "wof:name":"Hema",
    "wof:placetype":"venue"
},
  "geometry": {"coordinates":[5.8144350052,49.6839904785],"type":"Point"}
}