{
  "type": "Feature",
  "properties": {
    "iso:country":"BE",
    "sg:address":"Albert I Promenade 66",
    "sg:city":"Oostende",
    "sg:classifiers":[
        {
            "category":"Restaurant",
            "type":"Food & Drink"
        }
    ],
    "sg:phone":"+32 59 70 58 74",
    "sg:postcode":"8400",
    "sg:province":"West-Vlaanderen",
    "wof:name":"Le Chevalier",
    "wof:placetype":"venue"
},
  "geometry": {"coordinates":[2.9100680351,51.23021698],"type":"Point"}
}