{
  "type": "Feature",
  "properties": {
    "addr:full":"Kapelsesteenweg 364 Brasschaat Antwerpen 2930",
    "addr:housenumber":"364",
    "addr:postcode":"2930",
    "addr:street":"Kapelsesteenweg",
    "iso:country":"BE",
    "sg:address":"Kapelsesteenweg 364",
    "sg:city":"Brasschaat",
    "sg:classifiers":[
        {
            "category":"Utilities",
            "subcategory":"Natural Gas",
            "type":"Services"
        }
    ],
    "sg:phone":"+32 3 664 78 98",
    "sg:postcode":"2930",
    "sg:province":"Antwerpen",
    "sg:tags":[
        "extraction",
        "-",
        "smoke",
        "equipment"
    ],
    "wof:name":"Cosdep Luchtreinigers",
    "wof:placetype":"venue"
},
  "geometry": {"coordinates":[4.4445519447,51.2920303345],"type":"Point"}
}