{
  "type": "Feature",
  "properties": {
    "iso:country":"BE",
    "sg:address":"Natienlaan 8",
    "sg:city":"Damme",
    "sg:orig_category":"Rundveehouders",
    "sg:phone":"+32 50 60 60 33",
    "sg:postcode":"8340",
    "sg:province":"West-Vlaanderen",
    "wof:name":"Willy Stroo",
    "wof:placetype":"venue"
},
  "geometry": {"coordinates":[3.330065012,51.299331665],"type":"Point"}
}