{
  "type": "Feature",
  "properties": {
    "iso:country":"BE",
    "sg:address":"Ronsaardbekestraat 82",
    "sg:city":"Brugge",
    "sg:classifiers":[
        {
            "category":"Shopping",
            "subcategory":"Optician",
            "type":"Retail Goods"
        }
    ],
    "sg:phone":"+32 50 34 53 36",
    "sg:postcode":"8000",
    "sg:province":"West-Vlaanderen",
    "sg:tags":[
        "-"
    ],
    "wof:name":"Acke Optiek",
    "wof:placetype":"venue"
},
  "geometry": {"coordinates":[3.2328429222,51.2249755859],"type":"Point"}
}