{
  "type": "Feature",
  "properties": {
    "addr:full":"Chauss\u00e9e Ch\u00e2teau De La Bawette 5 Wavre Brabant Wallon 1300",
    "addr:housenumber":"5;1300",
    "addr:street":"Chausse\u0301E Cha\u0302Teau De La Bawette",
    "iso:country":"BE",
    "sg:address":"Chauss\u00e9e Ch\u00e2teau De La Bawette 5",
    "sg:city":"Wavre",
    "sg:classifiers":[
        {
            "category":"Arena",
            "subcategory":"Sports Club",
            "type":"Entertainment"
        }
    ],
    "sg:phone":"+32 10 22 70 85",
    "sg:postcode":"1300",
    "sg:province":"Brabant Wallon",
    "wof:name":"Golfinger Sa",
    "wof:placetype":"venue"
},
  "geometry": {"coordinates":[4.5978078842,50.7298774719],"type":"Point"}
}