{
  "type": "Feature",
  "properties": {
    "addr:full":"Chauss\u00e9e Du Roeulx 173 Mons Hainaut 7000",
    "addr:housenumber":"173",
    "addr:postcode":"7000",
    "addr:street":"Chausse\u0301E Du Roeulx;Hainaut",
    "iso:country":"BE",
    "sg:address":"Chauss\u00e9e Du Roeulx 173",
    "sg:city":"Mons",
    "sg:classifiers":[
        {
            "category":"Social Services",
            "subcategory":"Child Care",
            "type":"Services"
        }
    ],
    "sg:phone":"+32 65 31 34 45",
    "sg:postcode":"7000",
    "sg:province":"Hainaut",
    "sg:tags":[
        "baby",
        "nursery",
        "day",
        "sitting"
    ],
    "wof:name":"Maison De Snoopy (la)",
    "wof:placetype":"venue"
},
  "geometry": {"coordinates":[3.9744699001,50.4566612244],"type":"Point"}
}