{
  "type": "Feature",
  "properties": {
    "iso:country":"BE",
    "sg:address":"Ninoofsesteenweg 234b",
    "sg:city":"Dilbeek",
    "sg:orig_category":"IJzerwaren, bouw- and verfmaterialen MEUBELONTWERP AND -INSTALLATIE",
    "sg:phone":"+32 2 567 00 44",
    "sg:postcode":"1700",
    "sg:province":"Vlaams-Brabant",
    "wof:name":"Coordisan",
    "wof:placetype":"venue"
},
  "geometry": {"coordinates":[4.2684941292,50.8442001343],"type":"Point"}
}