{
  "type": "Feature",
  "properties": {
    "iso:country":"BE",
    "sg:address":"Henry Fordlaan 66",
    "sg:city":"Genk",
    "sg:orig_category":"Upholstered Benches",
    "sg:phone":"+32 89 30 16 70",
    "sg:postcode":"3600",
    "sg:province":"Limburg",
    "wof:name":"Jongform Nv",
    "wof:placetype":"venue"
},
  "geometry": {"coordinates":[5.4755511284,50.9298820496],"type":"Point"}
}