{
  "type": "Feature",
  "properties": {
    "iso:country":"BE",
    "sg:address":"Rue Pech\u00e8re 9",
    "sg:city":"Lasne (lasne-chapelle-saint-lambert)",
    "sg:classifiers":[
        {
            "category":"Professional",
            "type":"Services"
        }
    ],
    "sg:phone":"+32 2 633 42 07",
    "sg:postcode":"1380",
    "sg:province":"Brabant Wallon",
    "sg:tags":[
        "entertainer"
    ],
    "wof:name":"Seresia Poucette",
    "wof:placetype":"venue"
},
  "geometry": {"coordinates":[4.4636950493,50.6858444214],"type":"Point"}
}