{
  "type": "Feature",
  "properties": {
    "iso:country":"BE",
    "sg:address":"Ten Berg 3",
    "sg:city":"Aalst",
    "sg:classifiers":[
        {
            "category":"Insurance",
            "subcategory":"Life Insurance",
            "type":"Services"
        }
    ],
    "sg:phone":"+32 53 70 03 42",
    "sg:postcode":"9300",
    "sg:province":"Oost-Vlaanderen",
    "sg:tags":[
        "assurance"
    ],
    "wof:name":"Bureau Snel-de Petter",
    "wof:placetype":"venue"
},
  "geometry": {"coordinates":[4.0642490387,50.9354438782],"type":"Point"}
}