{
  "type": "Feature",
  "properties": {
    "addr:full":"Rue De La Station 43 Doische Namur 5680",
    "addr:housenumber":"43",
    "addr:postcode":"5680",
    "addr:street":"Rue De La Station",
    "iso:country":"BE",
    "sg:address":"Rue De La Station 43",
    "sg:city":"Doische",
    "sg:classifiers":[
        {
            "category":"Cafe",
            "type":"Food & Drink"
        }
    ],
    "sg:phone":"+32 60 39 90 33",
    "sg:postcode":"5680",
    "sg:province":"Namur",
    "sg:tags":[
        "caf\u00e9s"
    ],
    "wof:name":"Maria Bourtembourg",
    "wof:placetype":"venue"
},
  "geometry": {"coordinates":[4.6179871559,50.1236343384],"type":"Point"}
}