{
  "type": "Feature",
  "properties": {
    "iso:country":"BE",
    "sg:address":"Weg Op Bree 73",
    "sg:city":"Meeuwen-gruitrode",
    "sg:classifiers":[
        {
            "category":"Personal",
            "subcategory":"Beauty Salon",
            "type":"Services"
        }
    ],
    "sg:phone":"+32 11 79 34 66",
    "sg:postcode":"3670",
    "sg:province":"Limburg",
    "sg:tags":[
        "de",
        "coiffure"
    ],
    "wof:name":"Studio Garnier",
    "wof:placetype":"venue"
},
  "geometry": {"coordinates":[5.5295858383,51.1006813049],"type":"Point"}
}