{
  "type": "Feature",
  "properties": {
    "addr:full":"Place D\u00b4armes 2 Philippeville Namur 5600",
    "addr:housenumber":"2",
    "addr:postcode":"5600",
    "addr:street":"Place D\u00b4Armes",
    "iso:country":"BE",
    "sg:address":"Place D\u00b4armes 2",
    "sg:city":"Philippeville",
    "sg:orig_category":"Avocats and conseillers juridiques",
    "sg:phone":"+32 71 66 74 74",
    "sg:postcode":"5600",
    "sg:province":"Namur",
    "wof:name":"St\u00c9phanie Thirifays",
    "wof:placetype":"venue"
},
  "geometry": {"coordinates":[4.5431241989,50.1964607239],"type":"Point"}
}