{
  "type": "Feature",
  "properties": {
    "addr:full":"Molenberglaan 14 Lochristi (beervelde) Oost-Vlaanderen 9080",
    "addr:housenumber":"14",
    "addr:postcode":"9080",
    "addr:street":"Molenberglaan",
    "iso:country":"BE",
    "sg:address":"Molenberglaan 14",
    "sg:city":"Lochristi (beervelde)",
    "sg:classifiers":[
        {
            "category":"Building & Trades",
            "subcategory":"Electrical",
            "type":"Services"
        }
    ],
    "sg:phone":"+32 495 31 57 43",
    "sg:postcode":"9080",
    "sg:province":"Oost-Vlaanderen",
    "sg:tags":[
        "electric",
        "-",
        "housewiring",
        "contractor"
    ],
    "wof:name":"Elektriciteitswerken Stein",
    "wof:placetype":"venue"
},
  "geometry": {"coordinates":[3.8880040646,51.0781135559],"type":"Point"}
}