{
  "type": "Feature",
  "properties": {
    "addr:full":"Poperingseweg 53 Ieper West-Vlaanderen 8900",
    "addr:housenumber":"53",
    "addr:postcode":"8900",
    "addr:street":"Poperingseweg",
    "iso:country":"BE",
    "sg:address":"Poperingseweg 53",
    "sg:city":"Ieper",
    "sg:orig_category":"SMEEDWERK, METAALBEWERKING AND POEDERMETALLURGIE",
    "sg:phone":"+32 57 20 33 48",
    "sg:postcode":"8900",
    "sg:province":"West-Vlaanderen",
    "wof:name":"Depuydt Kunstsmederij",
    "wof:placetype":"venue"
},
  "geometry": {"coordinates":[2.8714709282,50.8491249084],"type":"Point"}
}