{
  "type": "Feature",
  "properties": {
    "addr:full":"Place Du March\u00c9 3 Eupen/eupen Li\u00e8ge 4700",
    "addr:housenumber":"3",
    "addr:postcode":"4700",
    "addr:street":"Place Du Marche\u0301",
    "iso:country":"BE",
    "sg:address":"Place Du March\u00c9 3",
    "sg:city":"Eupen/eupen",
    "sg:orig_category":"Cr\u00e9meries",
    "sg:phone":"+32 87 74 33 42",
    "sg:postcode":"4700",
    "sg:province":"Li\u00e8ge",
    "wof:name":"Zampolli",
    "wof:placetype":"venue"
},
  "geometry": {"coordinates":[6.0313639641,50.6303443909],"type":"Point"}
}