{
  "type": "Feature",
  "properties": {
    "addr:full":"Baron Brugmann De Walzinplein 18 Zaventem (sterrebeek) Vlaams-Brabant 1933",
    "addr:housenumber":"18",
    "addr:postcode":"1933",
    "addr:street":"Baron Brugmann De Walzinplein",
    "iso:country":"BE",
    "sg:address":"Baron Brugmann De Walzinplein 18",
    "sg:city":"Zaventem (sterrebeek)",
    "sg:classifiers":[
        {
            "category":"Bars & Pubs",
            "type":"Food & Drink"
        }
    ],
    "sg:phone":"+32 2 767 42 79",
    "sg:postcode":"1933",
    "sg:province":"Vlaams-Brabant",
    "wof:name":"Derby",
    "wof:placetype":"venue"
},
  "geometry": {"coordinates":[4.5118842125,50.8443984985],"type":"Point"}
}