{
  "type": "Feature",
  "properties": {
    "iso:country":"BE",
    "sg:address":"Dijkzijde 21",
    "sg:city":"Oud-turnhout",
    "sg:classifiers":[
        {
            "category":"Health Services",
            "subcategory":"Hospital",
            "type":"Services"
        }
    ],
    "sg:phone":"+32 14 45 43 59",
    "sg:postcode":"2360",
    "sg:province":"Antwerpen",
    "sg:tags":[
        "ambulance"
    ],
    "wof:name":"E.h.b.o.-sport",
    "wof:placetype":"venue"
},
  "geometry": {"coordinates":[4.9747819901,51.3188056946],"type":"Point"}
}