{
  "type": "Feature",
  "properties": {
    "addr:full":"Rue De La Libert\u00c9 50 Li\u00c8ge Li\u00e8ge 4020",
    "addr:housenumber":"50",
    "addr:postcode":"4020",
    "addr:street":"Rue De La Liberte\u0301",
    "iso:country":"BE",
    "sg:address":"Rue De La Libert\u00c9 50",
    "sg:city":"Li\u00c8ge",
    "sg:orig_category":"M\u00e9decines alternatives. M\u00e9decins and sp\u00e9cialistes",
    "sg:phone":"+32 4 341 40 00",
    "sg:postcode":"4020",
    "sg:province":"Li\u00e8ge",
    "wof:name":"Philippe Leroy",
    "wof:placetype":"venue"
},
  "geometry": {"coordinates":[5.5871582031,50.6393432617],"type":"Point"}
}