{
  "type": "Feature",
  "properties": {
    "addr:full":"Walenpot 1 Bertem Vlaams-Brabant 3060",
    "addr:housenumber":"1",
    "addr:postcode":"3060",
    "addr:street":"Walenpot",
    "iso:country":"BE",
    "sg:address":"Walenpot 1",
    "sg:city":"Bertem",
    "sg:classifiers":[
        {
            "category":"Shopping",
            "subcategory":"Computers & Home Electronics",
            "type":"Retail Goods"
        }
    ],
    "sg:phone":"+32 16 49 90 26",
    "sg:postcode":"3060",
    "sg:province":"Vlaams-Brabant",
    "sg:tags":[
        "computerapparatuur",
        "microsoft"
    ],
    "wof:name":"Betec",
    "wof:placetype":"venue"
},
  "geometry": {"coordinates":[4.613284111,50.869052887],"type":"Point"}
}