{
  "type": "Feature",
  "properties": {
    "addr:full":"Avenue J. Wauters 31 Grace-hollogne Li\u00e8ge 4460",
    "addr:housenumber":"31",
    "addr:postcode":"4460",
    "addr:street":"Avenue J. Wauters",
    "iso:country":"BE",
    "sg:address":"Avenue J. Wauters 31",
    "sg:city":"Grace-hollogne",
    "sg:orig_category":"Woningbouw",
    "sg:phone":"+32 4 246 12 63",
    "sg:postcode":"4460",
    "sg:province":"Li\u00e8ge",
    "wof:name":"Cavaleri A.",
    "wof:placetype":"venue"
},
  "geometry": {"coordinates":[5.5062351227,50.646446228],"type":"Point"}
}