{
  "type": "Feature",
  "properties": {
    "iso:country":"BE",
    "sg:address":"Rue Des Combattants 45",
    "sg:city":"Virton",
    "sg:classifiers":[
        {
            "category":"Recreation",
            "subcategory":"Dance Hall",
            "type":"Entertainment"
        }
    ],
    "sg:phone":"+32 63 57 63 54",
    "sg:postcode":"6760",
    "sg:province":"Luxembourg",
    "sg:tags":[
        "discotheque"
    ],
    "wof:name":"Las Palmas Disco",
    "wof:placetype":"venue"
},
  "geometry": {"coordinates":[5.5310811996,49.5698509216],"type":"Point"}
}