{
  "type": "Feature",
  "properties": {
    "addr:full":"Zuid - Oostwijk 12 Bredene West-Vlaanderen 8450",
    "addr:housenumber":"12",
    "addr:postcode":"8450",
    "addr:street":"Oostwijk",
    "iso:country":"BE",
    "sg:address":"Zuid - Oostwijk 12",
    "sg:city":"Bredene",
    "sg:orig_category":"Boucheries",
    "sg:phone":"+32 59 32 04 80",
    "sg:postcode":"8450",
    "sg:province":"West-Vlaanderen",
    "wof:name":"Hans De Ruyter",
    "wof:placetype":"venue"
},
  "geometry": {"coordinates":[2.9947829247,51.2351531982],"type":"Point"}
}