{
  "type": "Feature",
  "properties": {
    "addr:full":"Liebaardstraat 154 Waregem West-Vlaanderen 8792",
    "addr:housenumber":"154",
    "addr:postcode":"8792",
    "addr:street":"Liebaardstraat",
    "iso:country":"BE",
    "sg:address":"Liebaardstraat 154",
    "sg:city":"Waregem",
    "sg:orig_category":"Pharmaciens",
    "sg:phone":"+32 56 71 22 66",
    "sg:postcode":"8792",
    "sg:province":"West-Vlaanderen",
    "wof:name":"L. Vandendriessche",
    "wof:placetype":"venue"
},
  "geometry": {"coordinates":[3.3547620773,50.8826065063],"type":"Point"}
}