{
  "type": "Feature",
  "properties": {
    "iso:country":"BE",
    "sg:address":"Tenaertslaan 22",
    "sg:city":"Machelen",
    "sg:orig_category":"Voertuigen",
    "sg:phone":"+32 2 720 28 44",
    "sg:postcode":"1831",
    "sg:province":"Vlaams-Brabant",
    "wof:name":"Jan Tielemans",
    "wof:placetype":"venue"
},
  "geometry": {"coordinates":[4.4448170662,50.8922615051],"type":"Point"}
}