{
  "type": "Feature",
  "properties": {
    "addr:full":"Rue Du Ch\u00e2teau 1 Box 35 Sombreffe Namur 5140",
    "addr:housenumber":"1 box 35",
    "addr:postcode":"5140",
    "addr:street":"Rue Du Cha\u0302Teau",
    "iso:country":"BE",
    "sg:address":"Rue Du Ch\u00e2teau 1 Box 35",
    "sg:city":"Sombreffe",
    "sg:classifiers":[
        {
            "category":"Health Services",
            "subcategory":"Doctor",
            "type":"Services"
        }
    ],
    "sg:phone":"+32 71 88 78 97",
    "sg:postcode":"5140",
    "sg:province":"Namur",
    "sg:tags":[
        "medicinephysicians",
        "surgeon"
    ],
    "wof:name":"Geerts P",
    "wof:placetype":"venue"
},
  "geometry": {"coordinates":[4.5968179703,50.5313339233],"type":"Point"}
}