{
  "type": "Feature",
  "properties": {
    "iso:country":"BE",
    "sg:address":"Waregemsesteenweg 117",
    "sg:city":"Kruishoutem",
    "sg:classifiers":[
        {
            "category":"Building & Trades",
            "subcategory":"Pest Control",
            "type":"Services"
        }
    ],
    "sg:phone":"+32 475 96 79 70",
    "sg:postcode":"9770",
    "sg:province":"Oost-Vlaanderen",
    "sg:tags":[
        "painting",
        "contractor"
    ],
    "wof:name":"Vandaele Rudy",
    "wof:placetype":"venue"
},
  "geometry": {"coordinates":[3.5081999302,50.9010658264],"type":"Point"}
}