{
  "type": "Feature",
  "properties": {
    "addr:full":"Place Verte 2 Huy Li\u00e8ge 4500",
    "addr:housenumber":"2",
    "addr:postcode":"4500",
    "addr:street":"Place Verte",
    "iso:country":"BE",
    "sg:address":"Place Verte 2",
    "sg:city":"Huy",
    "sg:classifiers":[
        {
            "category":"Manufacturing",
            "subcategory":"Printing",
            "type":"Manufacturing & Wholesale Goods"
        }
    ],
    "sg:phone":"+32 85 23 17 70",
    "sg:postcode":"4500",
    "sg:province":"Li\u00e8ge",
    "sg:tags":[
        "textile",
        "-"
    ],
    "wof:name":"Foxtiles Sa",
    "wof:placetype":"venue"
},
  "geometry": {"coordinates":[5.2418599129,50.5183868408],"type":"Point"}
}