{
  "type": "Feature",
  "properties": {
    "iso:country":"BE",
    "sg:address":"Keizerstraat 52",
    "sg:city":"Mechelen",
    "sg:orig_category":"Boekhouders",
    "sg:phone":"+32 15 21 61 82",
    "sg:postcode":"2800",
    "sg:province":"Antwerpen",
    "wof:name":"Jan Lauwers",
    "wof:placetype":"venue"
},
  "geometry": {"coordinates":[4.4877181053,51.0288619995],"type":"Point"}
}