{
  "type": "Feature",
  "properties": {
    "iso:country":"BE",
    "sg:address":"Merksplassesteenweg 104",
    "sg:city":"Rijkevorsel",
    "sg:classifiers":[
        {
            "category":"Food & Beverages",
            "subcategory":"Meat & Fish",
            "type":"Retail Goods"
        }
    ],
    "sg:phone":"+32 3 314 07 29",
    "sg:postcode":"2310",
    "sg:province":"Antwerpen",
    "sg:tags":[
        "bedspread",
        "blanket",
        "-"
    ],
    "wof:name":"Bio Sleepworld",
    "wof:placetype":"venue"
},
  "geometry": {"coordinates":[4.7773098946,51.3453598022],"type":"Point"}
}