{
  "type": "Feature",
  "properties": {
    "iso:country":"BE",
    "sg:address":"Rue Du Calvaire 62",
    "sg:city":"Beloeil (stambruges)",
    "sg:classifiers":[
        {
            "category":"Health Services",
            "subcategory":"Health Practitioner",
            "type":"Services"
        }
    ],
    "sg:phone":"+32 69 56 28 42",
    "sg:postcode":"7973",
    "sg:province":"Hainaut",
    "sg:tags":[
        "therapist",
        "speech"
    ],
    "wof:name":"Cnudde S",
    "wof:placetype":"venue"
},
  "geometry": {"coordinates":[3.7229731083,50.5073738098],"type":"Point"}
}