{
  "type": "Feature",
  "properties": {
    "iso:country":"BE",
    "sg:address":"Laurent Delvauxstraat 1",
    "sg:city":"Gent",
    "sg:classifiers":[
        {
            "category":"Shopping",
            "subcategory":"Antiques",
            "type":"Retail Goods"
        }
    ],
    "sg:phone":"+32 9 225 22 99",
    "sg:postcode":"9000",
    "sg:province":"Oost-Vlaanderen",
    "wof:name":"Violet",
    "wof:placetype":"venue"
},
  "geometry": {"coordinates":[3.7194430828,51.042224884],"type":"Point"}
}