{
  "type": "Feature",
  "properties": {
    "iso:country":"BE",
    "sg:address":"Rue Sur Les Heids 39",
    "sg:city":"Bl\u00c9gny",
    "sg:classifiers":[
        {
            "category":"Arena",
            "subcategory":"Sports Club",
            "type":"Entertainment"
        }
    ],
    "sg:phone":"+32 4 370 02 87",
    "sg:postcode":"4671",
    "sg:province":"Li\u00e8ge",
    "sg:tags":[
        "de"
    ],
    "wof:name":"J.c. Olympic Blegny",
    "wof:placetype":"venue"
},
  "geometry": {"coordinates":[5.6820588112,50.6480712891],"type":"Point"}
}