{
  "type": "Feature",
  "properties": {
    "iso:country":"BE",
    "sg:address":"Europalaan 2a",
    "sg:city":"Poperinge",
    "sg:orig_category":"V\u00eatements",
    "sg:phone":"+32 57 33 57 91",
    "sg:postcode":"8970",
    "sg:province":"West-Vlaanderen",
    "wof:name":"Jeans Point",
    "wof:placetype":"venue"
},
  "geometry": {"coordinates":[2.745331049,50.8530426025],"type":"Point"}
}