{
  "type": "Feature",
  "properties": {
    "iso:country":"BE",
    "sg:address":"Gasmeterstraat 1",
    "sg:city":"Knokke-heist",
    "sg:orig_category":"Caf\u00e9s Loodgieterij and centrale verwarming Gh Restaurants",
    "sg:phone":"+32 50 60 35 69",
    "sg:postcode":"8300",
    "sg:province":"West-Vlaanderen",
    "wof:name":"Bot-kill",
    "wof:placetype":"venue"
},
  "geometry": {"coordinates":[3.2836699486,51.342414856],"type":"Point"}
}