{
  "type": "Feature",
  "properties": {
    "addr:full":"Nederstraat 37 Oudenaarde Oost-Vlaanderen 9700",
    "addr:housenumber":"37",
    "addr:postcode":"9700",
    "addr:street":"Nederstraat",
    "iso:country":"BE",
    "sg:address":"Nederstraat 37",
    "sg:city":"Oudenaarde",
    "sg:classifiers":[
        {
            "category":"Building & Trades",
            "subcategory":"Locksmith",
            "type":"Services"
        }
    ],
    "sg:phone":"+32 55 30 38 60",
    "sg:postcode":"9700",
    "sg:province":"Oost-Vlaanderen",
    "sg:tags":[
        "lock",
        "key"
    ],
    "wof:name":"Freddy",
    "wof:placetype":"venue"
},
  "geometry": {"coordinates":[3.6033771038,50.8449859619],"type":"Point"}
}