{
  "type": "Feature",
  "properties": {
    "addr:full":"Rue De Fexhe 1c Li\u00e8ge 1 Li\u00e8ge 4000",
    "addr:housenumber":"1c;1",
    "addr:postcode":"4000",
    "addr:street":"Rue De Fexhe",
    "iso:country":"BE",
    "sg:address":"Rue De Fexhe 1c",
    "sg:city":"Li\u00e8ge 1",
    "sg:classifiers":[
        {
            "category":"Home & Garden",
            "subcategory":"Home Furnishings",
            "type":"Retail Goods"
        }
    ],
    "sg:phone":"+32 4 234 58 76",
    "sg:postcode":"4000",
    "sg:province":"Li\u00e8ge",
    "sg:tags":[
        "interior",
        "decoration"
    ],
    "wof:name":"Interdecor One Sprl",
    "wof:placetype":"venue"
},
  "geometry": {"coordinates":[5.5576930046,50.6463813782],"type":"Point"}
}