{
  "type": "Feature",
  "properties": {
    "iso:country":"BE",
    "sg:address":"Place De Baulers 4",
    "sg:city":"Nivelles",
    "sg:orig_category":"Alimentation sp\u00e9cialis\u00e9e. Catering and organisation de f\u00eates",
    "sg:phone":"+32 67 21 29 25",
    "sg:postcode":"1401",
    "sg:province":"Brabant Wallon",
    "wof:name":"L'atelier Traiteur",
    "wof:placetype":"venue"
},
  "geometry": {"coordinates":[4.353181839,50.6134986877],"type":"Point"}
}