{
  "type": "Feature",
  "properties": {
    "iso:country":"BE",
    "sg:address":"Nieuwe Kaai 27",
    "sg:city":"Turnhout",
    "sg:classifiers":[
        {
            "category":"Professional",
            "subcategory":"Management & Consulting",
            "type":"Services"
        }
    ],
    "sg:phone":"+32 14 43 73 84",
    "sg:postcode":"2300",
    "sg:province":"Antwerpen",
    "sg:tags":[
        "consultant"
    ],
    "wof:name":"A.f.o. Advies",
    "wof:placetype":"venue"
},
  "geometry": {"coordinates":[4.9315872192,51.3258018494],"type":"Point"}
}