{
  "type": "Feature",
  "properties": {
    "iso:country":"BE",
    "sg:address":"Stadiumlaan 3",
    "sg:city":"Zedelgem",
    "sg:orig_category":"Sportclubs",
    "sg:phone":"+32 50 20 96 09",
    "sg:postcode":"8210",
    "sg:province":"West-Vlaanderen",
    "wof:name":"Wtc De Kolaardtrappers-gistel",
    "wof:placetype":"venue"
},
  "geometry": {"coordinates":[3.1471750736,51.1374473572],"type":"Point"}
}