{
  "type": "Feature",
  "properties": {
    "iso:country":"BE",
    "sg:address":"Avenue Brugmann 467",
    "sg:city":"Ukkel/uccle",
    "sg:orig_category":"Secr\u00e9tariats",
    "sg:phone":"+32 2 347 35 47",
    "sg:postcode":"1180",
    "sg:province":"Bruxelles-Capitale",
    "wof:name":"Daniel Collette Product.",
    "wof:placetype":"venue"
},
  "geometry": {"coordinates":[4.342124939,50.8048248291],"type":"Point"}
}