{
  "type": "Feature",
  "properties": {
    "iso:country":"BE",
    "sg:address":"Kerkelei 19a",
    "sg:city":"Kontich (waarloos)",
    "sg:classifiers":[
        {
            "category":"Communications",
            "subcategory":"Television Station",
            "type":"Services"
        }
    ],
    "sg:phone":"+32 15 31 58 56",
    "sg:postcode":"2550",
    "sg:province":"Antwerpen",
    "sg:tags":[
        "report",
        "video"
    ],
    "wof:name":"D H Productions",
    "wof:placetype":"venue"
},
  "geometry": {"coordinates":[4.4530510902,51.1044197083],"type":"Point"}
}