{
  "type": "Feature",
  "properties": {
    "addr:full":"Gentsestraat 5 Harelbeke West-Vlaanderen 8530",
    "addr:housenumber":"5",
    "addr:postcode":"8530",
    "addr:street":"Gentsestraat",
    "iso:country":"BE",
    "sg:address":"Gentsestraat 5",
    "sg:city":"Harelbeke",
    "sg:orig_category":"Brood, gebak and snoepgoed Rookartikelen",
    "sg:phone":"+32 56 71 05 80",
    "sg:postcode":"8530",
    "sg:province":"West-Vlaanderen",
    "wof:name":"Rik Dendooven",
    "wof:placetype":"venue"
},
  "geometry": {"coordinates":[3.3137340546,50.8580932617],"type":"Point"}
}