{
  "type": "Feature",
  "properties": {
    "iso:country":"BE",
    "sg:address":"Chauss\u00e9e De Namur 69",
    "sg:city":"Hamois (natoye)",
    "sg:classifiers":[
        {
            "category":"Retail",
            "subcategory":"Auto Repair",
            "type":"Services"
        }
    ],
    "sg:phone":"+32 83 21 23 66",
    "sg:postcode":"5360",
    "sg:province":"Namur",
    "sg:tags":[
        "garage"
    ],
    "wof:name":"Technique & Passion Sprl",
    "wof:placetype":"venue"
},
  "geometry": {"coordinates":[5.0527467728,50.3459205627],"type":"Point"}
}