{
  "type": "Feature",
  "properties": {
    "iso:country":"BE",
    "sg:address":"Kouterstraat 5",
    "sg:city":"Beveren (vrasene)",
    "sg:classifiers":[
        {
            "category":"Food & Beverages",
            "subcategory":"Chocolate",
            "type":"Retail Goods"
        }
    ],
    "sg:phone":"+32 3 775 84 14",
    "sg:postcode":"9120",
    "sg:province":"Oost-Vlaanderen",
    "sg:tags":[
        "confectionery",
        "-"
    ],
    "wof:name":"Van Dooren-vijt",
    "wof:placetype":"venue"
},
  "geometry": {"coordinates":[4.1883611679,51.2185897827],"type":"Point"}
}