{
  "type": "Feature",
  "properties": {
    "addr:full":"Poverstraat 4 Dilbeek Vlaams-Brabant 1700",
    "addr:housenumber":"4",
    "addr:postcode":"1700",
    "addr:street":"Poverstraat",
    "iso:country":"BE",
    "sg:address":"Poverstraat 4",
    "sg:city":"Dilbeek",
    "sg:classifiers":[
        {
            "category":"Professional",
            "subcategory":"Accounting & Tax Preparation",
            "type":"Services"
        }
    ],
    "sg:phone":"+32 2 582 27 69",
    "sg:postcode":"1700",
    "sg:province":"Vlaams-Brabant",
    "sg:tags":[
        "accountant"
    ],
    "wof:name":"Michel Deboeck",
    "wof:placetype":"venue"
},
  "geometry": {"coordinates":[4.2128939629,50.8603134155],"type":"Point"}
}