{
  "type": "Feature",
  "properties": {
    "iso:country":"BE",
    "sg:address":"Taille Aux Joncs 3",
    "sg:city":"Namur",
    "sg:orig_category":"Artsen and specialisten",
    "sg:phone":"+32 81 46 16 13",
    "sg:postcode":"5100",
    "sg:province":"Namur",
    "wof:name":"G. Colinet",
    "wof:placetype":"venue"
},
  "geometry": {"coordinates":[4.8604130745,50.4019165039],"type":"Point"}
}