{
  "type": "Feature",
  "properties": {
    "addr:full":"Antwerpsesteenweg 62 Rumst Antwerpen 2840",
    "addr:housenumber":"62",
    "addr:postcode":"2840",
    "addr:street":"Antwerpsesteenweg",
    "iso:country":"BE",
    "sg:address":"Antwerpsesteenweg 62",
    "sg:city":"Rumst",
    "sg:classifiers":[
        {
            "category":"Retail",
            "subcategory":"Repair Shop",
            "type":"Services"
        }
    ],
    "sg:phone":"+32 15 31 78 99",
    "sg:postcode":"2840",
    "sg:province":"Antwerpen",
    "sg:tags":[
        "upholsterer"
    ],
    "wof:name":"Sitwell",
    "wof:placetype":"venue"
},
  "geometry": {"coordinates":[4.4538679123,51.0913085938],"type":"Point"}
}