{
  "type": "Feature",
  "properties": {
    "iso:country":"BE",
    "sg:address":"Menenstraat 2",
    "sg:city":"Wervik",
    "sg:orig_category":"Banques and organismes de cr\u00e9dit",
    "sg:phone":"+32 56 51 17 74",
    "sg:postcode":"8940",
    "sg:province":"West-Vlaanderen",
    "wof:name":"Bank Van Roeselare",
    "wof:placetype":"venue"
},
  "geometry": {"coordinates":[3.0789439678,50.8100814819],"type":"Point"}
}