{
  "type": "Feature",
  "properties": {
    "addr:full":"Ledigheid 31 Lubbeek Vlaams-Brabant 3210",
    "addr:housenumber":"31",
    "addr:postcode":"3210",
    "addr:street":"Ledigheid",
    "iso:country":"BE",
    "sg:address":"Ledigheid 31",
    "sg:city":"Lubbeek",
    "sg:orig_category":"Sportclubs Sportterreinen and installaties behalve sportcentra",
    "sg:phone":"+32 16 62 12 95",
    "sg:postcode":"3210",
    "sg:province":"Vlaams-Brabant",
    "wof:name":"Lubbeek St.martinus Sport",
    "wof:placetype":"venue"
},
  "geometry": {"coordinates":[4.8129792213,50.8913040161],"type":"Point"}
}