{
  "type": "Feature",
  "properties": {
    "iso:country":"BE",
    "sg:address":"Centraleweg 14",
    "sg:city":"Nijlen",
    "sg:classifiers":[
        {
            "category":"Professional",
            "subcategory":"Computer Services",
            "type":"Services"
        }
    ],
    "sg:phone":"+32 3 411 12 05",
    "sg:postcode":"2560",
    "sg:province":"Antwerpen",
    "sg:tags":[
        "webdesign",
        "-",
        "internet"
    ],
    "wof:name":"Lares",
    "wof:placetype":"venue"
},
  "geometry": {"coordinates":[4.7038030624,51.1656951904],"type":"Point"}
}