{
  "type": "Feature",
  "properties": {
    "iso:country":"BE",
    "sg:address":"Brugsesteenweg 528",
    "sg:city":"Roeselare",
    "sg:classifiers":[
        {
            "category":"Home & Garden",
            "subcategory":"Garden Supply",
            "type":"Retail Goods"
        }
    ],
    "sg:phone":"+32 51 20 45 81",
    "sg:postcode":"8800",
    "sg:province":"West-Vlaanderen",
    "sg:tags":[
        "lawn",
        "mower"
    ],
    "wof:name":"Cluyse Christian",
    "wof:placetype":"venue"
},
  "geometry": {"coordinates":[3.1191000938,50.9758415222],"type":"Point"}
}