{
  "type": "Feature",
  "properties": {
    "addr:full":"St-katelijnevest 54b10 Antwerpen Antwerpen 2000",
    "addr:housenumber":"54b10",
    "addr:postcode":"2000",
    "addr:street":"St-Katelijnevest",
    "iso:country":"BE",
    "sg:address":"St-katelijnevest 54b10",
    "sg:city":"Antwerpen",
    "sg:orig_category":"Agences d'exp\u00e9dition. Produits c\u00e9r\u00e9aliers Fab",
    "sg:phone":"+32 3 232 23 33",
    "sg:postcode":"2000",
    "sg:province":"Antwerpen",
    "wof:name":"United Belgian Mills",
    "wof:placetype":"venue"
},
  "geometry": {"coordinates":[4.4049730301,51.2192459106],"type":"Point"}
}