{
  "type": "Feature",
  "properties": {
    "addr:full":"Leon Bekaertstraat 1 Ingelmunster West-Vlaanderen 8770",
    "addr:housenumber":"1",
    "addr:postcode":"8770",
    "addr:street":"Bekaertstraat",
    "iso:country":"BE",
    "sg:address":"Leon Bekaertstraat 1",
    "sg:city":"Ingelmunster",
    "sg:orig_category":"Loodgieterij, verwarming and sanitaire installaties Zwembadinstallatie",
    "sg:phone":"+32 51 48 64 43",
    "sg:postcode":"8770",
    "sg:province":"West-Vlaanderen",
    "wof:name":"Demeyere R. & Zoon",
    "wof:placetype":"venue"
},
  "geometry": {"coordinates":[3.2673499584,50.936290741],"type":"Point"}
}