{
  "type": "Feature",
  "properties": {
    "addr:full":"56 Woluwedal 1200 Bruxelles 56",
    "addr:housenumber":"56",
    "addr:postcode":"1200;56",
    "addr:street":"Woluwedal",
    "iso:country":"BE",
    "sg:address":"56",
    "sg:city":"Woluwedal 1200 Bruxelles",
    "sg:classifiers":[
        {
            "category":"Banks & Credit Unions",
            "subcategory":"Financial Services",
            "type":"Services"
        }
    ],
    "sg:phone":"+32 2 775 02 10",
    "sg:postcode":"56",
    "sg:tags":[
        "banking",
        "insurance",
        "institution",
        "finance"
    ],
    "wof:name":"Ahold Belgie Nv",
    "wof:placetype":"venue"
},
  "geometry": {"coordinates":[4.4458751678,50.8559799194],"type":"Point"}
}