{
  "type": "Feature",
  "properties": {
    "addr:full":"Rue De Forri\u00e8re 217 Courcelles Hainaut 6180",
    "addr:housenumber":"217",
    "addr:postcode":"6180",
    "addr:street":"Rue De Forrie\u0300Re",
    "iso:country":"BE",
    "sg:address":"Rue De Forri\u00e8re 217",
    "sg:city":"Courcelles",
    "sg:classifiers":[
        {
            "category":"Professional",
            "subcategory":"Accounting & Tax Preparation",
            "type":"Services"
        }
    ],
    "sg:phone":"+32 71 45 81 05",
    "sg:postcode":"6180",
    "sg:province":"Hainaut",
    "sg:tags":[
        "bookkeeper"
    ],
    "wof:name":"Baude J-m",
    "wof:placetype":"venue"
},
  "geometry": {"coordinates":[4.3612031937,50.4456520081],"type":"Point"}
}