{
  "type": "Feature",
  "properties": {
    "addr:full":"Rue Insepre 10 Namen Namur 5020",
    "addr:housenumber":"10",
    "addr:postcode":"5020",
    "addr:street":"Rue Insepre",
    "iso:country":"BE",
    "sg:address":"Rue Insepre 10",
    "sg:city":"Namen",
    "sg:orig_category":"Sportclubs",
    "sg:phone":"+32 81 44 01 83",
    "sg:postcode":"5020",
    "sg:province":"Namur",
    "wof:name":"Cyclo Audax Sambrien 2000",
    "wof:placetype":"venue"
},
  "geometry": {"coordinates":[4.7952418327,50.4352035522],"type":"Point"}
}