{
  "type": "Feature",
  "properties": {
    "addr:full":"Kazernestraat 107 Lokeren Oost-Vlaanderen 9160",
    "addr:housenumber":"107",
    "addr:postcode":"9160",
    "addr:street":"Kazernestraat",
    "iso:country":"BE",
    "sg:address":"Kazernestraat 107",
    "sg:city":"Lokeren",
    "sg:orig_category":"Astrologen, grafologen and mediums",
    "sg:phone":"+32 9 349 32 32",
    "sg:postcode":"9160",
    "sg:province":"Oost-Vlaanderen",
    "wof:name":"Leonard",
    "wof:placetype":"venue"
},
  "geometry": {"coordinates":[3.9896409512,51.0985832214],"type":"Point"}
}