{
  "type": "Feature",
  "properties": {
    "iso:country":"BE",
    "sg:address":"Wingepark 59",
    "sg:city":"Rotselaar",
    "sg:orig_category":"Non-Classified Establishments",
    "sg:phone":"+32 16 44 21 21",
    "sg:postcode":"3110",
    "sg:province":"Vlaams-Brabant",
    "wof:name":"Godwin Bvba",
    "wof:placetype":"venue"
},
  "geometry": {"coordinates":[4.7493991852,50.9414672852],"type":"Point"}
}