{
  "type": "Feature",
  "properties": {
    "addr:full":"Doggenhoutstraat 55bb Ranst Antwerpen 2520",
    "addr:housenumber":"55bb",
    "addr:postcode":"2520",
    "addr:street":"Doggenhoutstraat",
    "iso:country":"BE",
    "sg:address":"Doggenhoutstraat 55bb",
    "sg:city":"Ranst",
    "sg:orig_category":"R\u00e9parations de chaussures and articles en cuir",
    "sg:phone":"+32 3 485 56 51",
    "sg:postcode":"2520",
    "sg:province":"Antwerpen",
    "wof:name":"Jan Van Den Broek",
    "wof:placetype":"venue"
},
  "geometry": {"coordinates":[4.5625557899,51.187915802],"type":"Point"}
}