{
  "type": "Feature",
  "properties": {
    "iso:country":"BE",
    "sg:address":"Stationsstraat 58",
    "sg:city":"Galmaarden",
    "sg:orig_category":"Schoonheidssalons",
    "sg:phone":"+32 54 58 60 69",
    "sg:postcode":"1570",
    "sg:province":"Vlaams-Brabant",
    "wof:name":"Ann Vande Maele",
    "wof:placetype":"venue"
},
  "geometry": {"coordinates":[3.9688940048,50.7455444336],"type":"Point"}
}