{
  "type": "Feature",
  "properties": {
    "iso:country":"BE",
    "sg:address":"Steenweg Op Waasten 366",
    "sg:city":"Komen-waasten/comines-warneton",
    "sg:orig_category":"Installatie van houten of kunststof schrijnwerk Installatie van metalen schrijnwerk",
    "sg:phone":"+32 56 55 78 93",
    "sg:postcode":"7784",
    "sg:province":"Hainaut",
    "wof:name":"Philippe Lahousse",
    "wof:placetype":"venue"
},
  "geometry": {"coordinates":[2.9706449509,50.76304245],"type":"Point"}
}