{
  "type": "Feature",
  "properties": {
    "iso:country":"BE",
    "sg:address":"Potaardestraat 74",
    "sg:city":"Niel",
    "sg:classifiers":[
        {
            "category":"Manufacturing",
            "subcategory":"Metals",
            "type":"Manufacturing & Wholesale Goods"
        }
    ],
    "sg:phone":"+32 3 844 41 64",
    "sg:postcode":"2845",
    "sg:province":"Antwerpen",
    "sg:tags":[
        "machinery",
        "working"
    ],
    "wof:name":"Sks Machines",
    "wof:placetype":"venue"
},
  "geometry": {"coordinates":[4.3609418869,51.1059036255],"type":"Point"}
}