{
  "type": "Feature",
  "properties": {
    "addr:full":"Rue Des Coquelicots 5 Charleroi Hainaut 6030",
    "addr:housenumber":"5",
    "addr:postcode":"6030",
    "addr:street":"Rue Des Coquelicots;Hainaut",
    "iso:country":"BE",
    "sg:address":"Rue Des Coquelicots 5",
    "sg:city":"Charleroi",
    "sg:orig_category":"Enseignement maternel and primaire",
    "sg:phone":"+32 71 52 73 64",
    "sg:postcode":"6030",
    "sg:province":"Hainaut",
    "wof:name":"Ecole Fond. Communale",
    "wof:placetype":"venue"
},
  "geometry": {"coordinates":[4.356110096,50.4137916565],"type":"Point"}
}