{
  "type": "Feature",
  "properties": {
    "addr:full":"Vandaleplein 5 Kortrijk West-Vlaanderen 8500",
    "addr:housenumber":"5",
    "addr:postcode":"8500",
    "addr:street":"Vandaleplein",
    "iso:country":"BE",
    "sg:address":"Vandaleplein 5",
    "sg:city":"Kortrijk",
    "sg:orig_category":"V\u00eatements. V\u00eatements pour Dames",
    "sg:phone":"+32 56 22 65 06",
    "sg:postcode":"8500",
    "sg:province":"West-Vlaanderen",
    "wof:name":"Claryss",
    "wof:placetype":"venue"
},
  "geometry": {"coordinates":[3.2684869766,50.8270225525],"type":"Point"}
}