{
  "type": "Feature",
  "properties": {
    "iso:country":"BE",
    "sg:address":"Rue Lambert Crickx 5",
    "sg:city":"Bruxelles",
    "sg:classifiers":[
        {
            "category":"Shopping",
            "subcategory":"Clothing, Apparel, & Fashions",
            "type":"Retail Goods"
        }
    ],
    "sg:phone":"+32 2 511 90 29",
    "sg:postcode":"1070",
    "sg:province":"Bruxelles-Capitale",
    "sg:tags":[
        "textile",
        "clothing",
        "clothes"
    ],
    "wof:name":"Grupi Sa",
    "wof:placetype":"venue"
},
  "geometry": {"coordinates":[4.3383440971,50.8409309387],"type":"Point"}
}