{
  "type": "Feature",
  "properties": {
    "addr:full":"Rue Du Roi Albert 166 Seraing (ougr\u00e9e) Li\u00e8ge 4102",
    "addr:housenumber":"166",
    "addr:postcode":"4102",
    "addr:street":"Rue Du Roi Albert",
    "iso:country":"BE",
    "sg:address":"Rue Du Roi Albert 166",
    "sg:city":"Seraing (ougr\u00e9e)",
    "sg:classifiers":[
        {
            "category":"Shopping",
            "type":"Retail Goods"
        }
    ],
    "sg:phone":"+32 4 337 06 37",
    "sg:postcode":"4102",
    "sg:province":"Li\u00e8ge",
    "sg:tags":[
        "product",
        "cleaning",
        "maintenance"
    ],
    "wof:name":"Ha-ra Dubois M",
    "wof:placetype":"venue"
},
  "geometry": {"coordinates":[5.5400800705,50.6010246277],"type":"Point"}
}