{
  "type": "Feature",
  "properties": {
    "addr:full":"Place De La Patrie 42 Schaarbeek/schaerbeek Bruxelles-Capitale 1030",
    "addr:housenumber":"42",
    "addr:postcode":"1030",
    "addr:street":"Place De La Patrie",
    "iso:country":"BE",
    "sg:address":"Place De La Patrie 42",
    "sg:city":"Schaarbeek/schaerbeek",
    "sg:orig_category":"Magasins de r\u00e9parations d'articles personnels et m\u00e9nagers divers",
    "sg:phone":"+32 2 241 02 89",
    "sg:postcode":"1030",
    "sg:province":"Bruxelles-Capitale",
    "wof:name":"Patrie Couture",
    "wof:placetype":"venue"
},
  "geometry": {"coordinates":[4.3918819427,50.8565826416],"type":"Point"}
}