{
  "type": "Feature",
  "properties": {
    "iso:country":"BE",
    "sg:address":"Schuttershofstraat 21",
    "sg:city":"Antwerpen",
    "sg:orig_category":"Antiek",
    "sg:phone":"+32 3 213 39 16",
    "sg:postcode":"2000",
    "sg:province":"Antwerpen",
    "wof:name":"Werner & Veldman Antiek",
    "wof:placetype":"venue"
},
  "geometry": {"coordinates":[4.4070620537,51.2165908813],"type":"Point"}
}