{
  "type": "Feature",
  "properties": {
    "iso:country":"BE",
    "sg:address":"Oude Kortrijkstraat 84",
    "sg:city":"Zonnebeke (beselare)",
    "sg:classifiers":[
        {
            "category":"Transit Center",
            "subcategory":"Passenger",
            "type":"Transportation"
        }
    ],
    "sg:phone":"+32 57 46 68 63",
    "sg:postcode":"8980",
    "sg:province":"West-Vlaanderen",
    "sg:tags":[
        "car",
        "trailer"
    ],
    "wof:name":"Pattyn L",
    "wof:placetype":"venue"
},
  "geometry": {"coordinates":[3.0058379173,50.8501243591],"type":"Point"}
}