{
  "type": "Feature",
  "properties": {
    "addr:full":"Quai Edouard Van Beneden 10 Box 51 Li\u00e8ge 1 (li\u00e8ge 2) Li\u00e8ge 4020",
    "addr:housenumber":"10 box 51;1;2",
    "addr:postcode":"4020",
    "addr:street":"Quai Edouard Van Beneden;Lie\u0300Ge",
    "iso:country":"BE",
    "sg:address":"Quai Edouard Van Beneden 10 Box 51",
    "sg:city":"Li\u00e8ge 1 (li\u00e8ge 2)",
    "sg:classifiers":[
        {
            "category":"Structure",
            "subcategory":"Office Building",
            "type":"Public Place"
        }
    ],
    "sg:phone":"+32 4 343 23 04",
    "sg:postcode":"4020",
    "sg:province":"Li\u00e8ge",
    "sg:tags":[
        "drawing"
    ],
    "wof:name":"Data-steel Sprl",
    "wof:placetype":"venue"
},
  "geometry": {"coordinates":[5.5788369179,50.6402740479],"type":"Point"}
}