{
  "type": "Feature",
  "properties": {
    "iso:country":"BE",
    "sg:address":"Rue De L'orniat 0",
    "sg:city":"Jemeppe-sur-sambre",
    "sg:orig_category":"Supermarch\u00e9s",
    "sg:phone":"+32 71 78 50 06",
    "sg:postcode":"5190",
    "sg:province":"Namur",
    "wof:name":"Mestdagh",
    "wof:placetype":"venue"
},
  "geometry": {"coordinates":[4.703482151,50.4776382446],"type":"Point"}
}