{
  "type": "Feature",
  "properties": {
    "addr:full":"Industrialaan 25 Groot-bijgaarden Vlaams-Brabant 1702",
    "addr:housenumber":"25",
    "addr:postcode":"1702",
    "addr:street":"Industrialaan",
    "iso:country":"BE",
    "sg:address":"Industrialaan 25",
    "sg:city":"Groot-bijgaarden",
    "sg:orig_category":"Bakery Improvers",
    "sg:phone":"+32 2 481 44 44",
    "sg:postcode":"1702",
    "sg:province":"Vlaams-Brabant",
    "wof:name":"Puratos Nv",
    "wof:placetype":"venue"
},
  "geometry": {"coordinates":[4.2700800896,50.8810081482],"type":"Point"}
}