{
  "type": "Feature",
  "properties": {
    "addr:full":"Ooststraat 23 Assenede Oost-Vlaanderen 9961",
    "addr:housenumber":"23",
    "addr:postcode":"9961",
    "addr:street":"Ooststraat",
    "iso:country":"BE",
    "sg:address":"Ooststraat 23",
    "sg:city":"Assenede",
    "sg:orig_category":"Artsen and specialisten",
    "sg:phone":"+32 9 373 71 38",
    "sg:postcode":"9961",
    "sg:province":"Oost-Vlaanderen",
    "wof:name":"V. Lammens",
    "wof:placetype":"venue"
},
  "geometry": {"coordinates":[3.6970720291,51.1955871582],"type":"Point"}
}