{
  "type": "Feature",
  "properties": {
    "addr:full":"Rue L. Dewonck 246 Ans Li\u00e8ge 4430",
    "addr:housenumber":"246",
    "addr:postcode":"4430",
    "addr:street":"Rue L. Dewonck",
    "iso:country":"BE",
    "sg:address":"Rue L. Dewonck 246",
    "sg:city":"Ans",
    "sg:orig_category":"Opticiens. Articles m\u00e9dicaux and orthop\u00e9diques",
    "sg:phone":"+32 4 263 79 14",
    "sg:postcode":"4430",
    "sg:province":"Li\u00e8ge",
    "wof:name":"Optique Alain C & Fils",
    "wof:placetype":"venue"
},
  "geometry": {"coordinates":[5.5113501549,50.6638908386],"type":"Point"}
}