{
  "type": "Feature",
  "properties": {
    "addr:full":"Dendermondsesteenweg 66 Willebroek Antwerpen 2830",
    "addr:housenumber":"66",
    "addr:postcode":"2830",
    "addr:street":"Dendermondsesteenweg",
    "iso:country":"BE",
    "sg:address":"Dendermondsesteenweg 66",
    "sg:city":"Willebroek",
    "sg:classifiers":[
        {
            "category":"Professional",
            "subcategory":"Management & Consulting",
            "type":"Services"
        }
    ],
    "sg:phone":"+32 3 860 96 76",
    "sg:postcode":"2830",
    "sg:province":"Antwerpen",
    "sg:tags":[
        "consultant",
        "law"
    ],
    "wof:name":"Haesmans D",
    "wof:placetype":"venue"
},
  "geometry": {"coordinates":[4.3555212021,51.060256958],"type":"Point"}
}