{
  "type": "Feature",
  "properties": {
    "iso:country":"BE",
    "sg:address":"130",
    "sg:city":"Rue De Herbesthal 4700 Eupen",
    "sg:classifiers":[
        {
            "category":"Home & Garden",
            "subcategory":"Furniture",
            "type":"Retail Goods"
        }
    ],
    "sg:phone":"+32 87 56 00 63",
    "sg:postcode":"130",
    "sg:tags":[
        "wood"
    ],
    "wof:name":"Lance Sprl",
    "wof:placetype":"venue"
},
  "geometry": {"coordinates":[6.0205597878,50.6365661621],"type":"Point"}
}