{
  "type": "Feature",
  "properties": {
    "addr:full":"Rue De L' Etang 35 Gembloux Namur 5031",
    "addr:housenumber":"35",
    "addr:postcode":"5031",
    "addr:street":"Rue De L ' Etang;Namur",
    "iso:country":"BE",
    "sg:address":"Rue De L' Etang 35",
    "sg:city":"Gembloux",
    "sg:orig_category":"Installation \u00e9lectrique r\u00e9sidentielle. Eclairage et \u00e9quipements du foyer",
    "sg:phone":"+32 81 64 01 09",
    "sg:postcode":"5031",
    "sg:province":"Namur",
    "wof:name":"Duelec",
    "wof:placetype":"venue"
},
  "geometry": {"coordinates":[4.768020153,50.5778884888],"type":"Point"}
}