{
  "type": "Feature",
  "properties": {
    "addr:full":"Chauss\u00e9e De Chastre 131 Sombreffe Namur 5140",
    "addr:housenumber":"131",
    "addr:postcode":"5140",
    "addr:street":"Chausse\u0301E De Chastre",
    "iso:country":"BE",
    "sg:address":"Chauss\u00e9e De Chastre 131",
    "sg:city":"Sombreffe",
    "sg:classifiers":[
        {
            "category":"Home & Garden",
            "subcategory":"Carpets & Floor Coverings",
            "type":"Retail Goods"
        }
    ],
    "sg:phone":"+32 71 88 50 84",
    "sg:postcode":"5140",
    "sg:province":"Namur",
    "sg:tags":[
        "tile"
    ],
    "wof:name":"Petit M",
    "wof:placetype":"venue"
},
  "geometry": {"coordinates":[4.5970358849,50.538318634],"type":"Point"}
}