{
  "type": "Feature",
  "properties": {
    "iso:country":"BE",
    "sg:address":"Wouters Lefebvreplein 4",
    "sg:city":"Willebroek (blaasveld)",
    "sg:classifiers":[
        {
            "category":"Personal",
            "subcategory":"Beauty Salon",
            "type":"Services"
        }
    ],
    "sg:phone":"+32 3 886 66 72",
    "sg:postcode":"2830",
    "sg:province":"Antwerpen",
    "sg:tags":[
        "lady",
        "-",
        "hairdressing"
    ],
    "wof:name":"Sonja Kapsalon",
    "wof:placetype":"venue"
},
  "geometry": {"coordinates":[4.3716268539,51.0568466187],"type":"Point"}
}