{
  "type": "Feature",
  "properties": {
    "iso:country":"BE",
    "sg:address":"Herdersstraat 35",
    "sg:city":"Zulte (olsene)",
    "sg:classifiers":[
        {
            "category":"Bars & Pubs",
            "type":"Food & Drink"
        }
    ],
    "sg:phone":"+32 9 388 75 42",
    "sg:postcode":"9870",
    "sg:province":"Oost-Vlaanderen",
    "wof:name":"De Drie Schaapherders",
    "wof:placetype":"venue"
},
  "geometry": {"coordinates":[3.4631679058,50.9438438416],"type":"Point"}
}