{
  "type": "Feature",
  "properties": {
    "iso:country":"BE",
    "sg:address":"Honor\u00c9 Drubbelstraat 29",
    "sg:city":"Gent",
    "sg:orig_category":"Installation \u00e9lectrique r\u00e9sidentielle",
    "sg:phone":"+32 9 251 64 34",
    "sg:postcode":"9041",
    "sg:province":"Oost-Vlaanderen",
    "wof:name":"De Backer-van St.",
    "wof:placetype":"venue"
},
  "geometry": {"coordinates":[3.7616798878,51.0991210938],"type":"Point"}
}