{
  "type": "Feature",
  "properties": {
    "addr:full":"Rue D'avelgem 11 Espierres-helchin (helchin) West-Vlaanderen 8587",
    "addr:housenumber":"11",
    "addr:postcode":"8587",
    "addr:street":"Rue D'Avelgem;Helchin",
    "iso:country":"BE",
    "sg:address":"Rue D'avelgem 11",
    "sg:city":"Espierres-helchin (helchin)",
    "sg:classifiers":[
        {
            "category":"Education",
            "subcategory":"Library",
            "type":"Public Place"
        }
    ],
    "sg:phone":"+32 56 45 75 74",
    "sg:postcode":"8587",
    "sg:province":"West-Vlaanderen",
    "wof:name":"Openbare Bibliotheek",
    "wof:placetype":"venue"
},
  "geometry": {"coordinates":[3.3828570843,50.7330627441],"type":"Point"}
}