{
  "type": "Feature",
  "properties": {
    "addr:full":"Rue Alfred Moitroux 55-1 La Louvi\u00e8re Hainaut 7100",
    "addr:housenumber":"55-1",
    "addr:postcode":"7100",
    "addr:street":"Rue Alfred Moitroux",
    "iso:country":"BE",
    "sg:address":"Rue Alfred Moitroux 55-1",
    "sg:city":"La Louvi\u00e8re",
    "sg:classifiers":[
        {
            "category":"Health Services",
            "subcategory":"Health Practitioner",
            "type":"Services"
        }
    ],
    "sg:phone":"+32 64 22 16 93",
    "sg:postcode":"7100",
    "sg:province":"Hainaut",
    "sg:tags":[
        "physiotherapist"
    ],
    "wof:name":"Parmentier Isabelle",
    "wof:placetype":"venue"
},
  "geometry": {"coordinates":[4.198797226,50.4780845642],"type":"Point"}
}