{
  "type": "Feature",
  "properties": {
    "addr:full":"Rue De Fays 7 Aubange Luxembourg 6792",
    "addr:housenumber":"7",
    "addr:postcode":"6792",
    "addr:street":"Rue De Fays",
    "iso:country":"BE",
    "sg:address":"Rue De Fays 7",
    "sg:city":"Aubange",
    "sg:orig_category":"SMEEDWERK, METAALBEWERKING AND POEDERMETALLURGIE",
    "sg:phone":"+32 63 67 58 85",
    "sg:postcode":"6792",
    "sg:province":"Luxembourg",
    "wof:name":"Petrement O.",
    "wof:placetype":"venue"
},
  "geometry": {"coordinates":[5.7499527931,49.555973053],"type":"Point"}
}