{
  "type": "Feature",
  "properties": {
    "addr:full":"Nationalestraat 55 Antwerpen Antwerpen 2000",
    "addr:housenumber":"55",
    "addr:postcode":"2000",
    "addr:street":"Nationalestraat",
    "iso:country":"BE",
    "sg:address":"Nationalestraat 55",
    "sg:city":"Antwerpen",
    "sg:orig_category":"Herstelling leer and schoeisel Herstellingswinkels voor diverse persoonlijke and huishoudartikelen",
    "sg:phone":"+32 3 226 25 90",
    "sg:postcode":"2000",
    "sg:province":"Antwerpen",
    "wof:name":"Alfa",
    "wof:placetype":"venue"
},
  "geometry": {"coordinates":[4.399160862,51.2158889771],"type":"Point"}
}