{
  "type": "Feature",
  "properties": {
    "addr:full":"Rue Nicolas Lambercy 23 Aywaille Li\u00e8ge 4920",
    "addr:housenumber":"23",
    "addr:postcode":"4920",
    "addr:street":"Rue Nicolas Lambercy",
    "iso:country":"BE",
    "sg:address":"Rue Nicolas Lambercy 23",
    "sg:city":"Aywaille",
    "sg:orig_category":"Jeux and jouets",
    "sg:phone":"+32 4 384 42 75",
    "sg:postcode":"4920",
    "sg:province":"Li\u00e8ge",
    "wof:name":"Christiaensen",
    "wof:placetype":"venue"
},
  "geometry": {"coordinates":[5.6763558388,50.4715042114],"type":"Point"}
}