{
  "type": "Feature",
  "properties": {
    "iso:country":"BE",
    "sg:address":"Vismijnlaan 137",
    "sg:city":"Oostende",
    "sg:classifiers":[
        {
            "category":"Food & Beverages",
            "subcategory":"Fruits & Vegetables",
            "type":"Retail Goods"
        }
    ],
    "sg:phone":"+32 59 32 39 53",
    "sg:postcode":"8400",
    "sg:province":"West-Vlaanderen",
    "sg:tags":[
        "l\u00e9gumes"
    ],
    "wof:name":"Verpakking Center",
    "wof:placetype":"venue"
},
  "geometry": {"coordinates":[2.9373478889,51.2288475037],"type":"Point"}
}