{
  "type": "Feature",
  "properties": {
    "iso:country":"BE",
    "sg:address":"Smissestraat 34",
    "sg:city":"Meerhout",
    "sg:classifiers":[
        {
            "category":"Shopping",
            "subcategory":"Bicycles & Sporting Goods",
            "type":"Retail Goods"
        }
    ],
    "sg:phone":"+32 14 36 82 08",
    "sg:postcode":"2450",
    "sg:province":"Antwerpen",
    "sg:tags":[
        "-"
    ],
    "wof:name":"Fietswereld",
    "wof:placetype":"venue"
},
  "geometry": {"coordinates":[5.0736689568,51.1353607178],"type":"Point"}
}