{
  "type": "Feature",
  "properties": {
    "iso:country":"BE",
    "sg:address":"Langstraat 90",
    "sg:city":"Gingelom",
    "sg:orig_category":"Rev\u00eatements de sols and murs",
    "sg:phone":"+32 11 83 21 53",
    "sg:postcode":"3890",
    "sg:province":"Limburg",
    "wof:name":"Lis Tegels",
    "wof:placetype":"venue"
},
  "geometry": {"coordinates":[5.1404571533,50.7207069397],"type":"Point"}
}