{
  "type": "Feature",
  "properties": {
    "iso:country":"BE",
    "sg:address":"Boulevard De Waterloo 10",
    "sg:city":"Bruxelles",
    "sg:classifiers":[
        {
            "category":"Shopping",
            "subcategory":"Jewelry",
            "type":"Retail Goods"
        }
    ],
    "sg:phone":"+32 2 512 38 63",
    "sg:postcode":"1000",
    "sg:province":"Bruxelles-Capitale",
    "sg:tags":[
        "purchase",
        "-",
        "sale",
        "gold"
    ],
    "wof:name":"La Maison Du Diamant Sa",
    "wof:placetype":"venue"
},
  "geometry": {"coordinates":[4.360229969,50.8383712769],"type":"Point"}
}