{
  "type": "Feature",
  "properties": {
    "iso:country":"BE",
    "sg:address":"Ketelstraat 11",
    "sg:city":"Diest",
    "sg:classifiers":[
        {
            "category":"Shopping",
            "subcategory":"Clothing, Apparel, & Fashions",
            "type":"Retail Goods"
        }
    ],
    "sg:phone":"+32 13 33 41 29",
    "sg:postcode":"3290",
    "sg:province":"Vlaams-Brabant",
    "sg:tags":[
        "-",
        "clothing",
        "child"
    ],
    "wof:name":"Puzzels",
    "wof:placetype":"venue"
},
  "geometry": {"coordinates":[5.0521140099,50.9838905334],"type":"Point"}
}