{
  "type": "Feature",
  "properties": {
    "addr:full":"Breestraat 25 Deerlijk West-Vlaanderen 8540",
    "addr:housenumber":"25",
    "addr:postcode":"8540",
    "addr:street":"Breestraat",
    "iso:country":"BE",
    "sg:address":"Breestraat 25",
    "sg:city":"Deerlijk",
    "sg:classifiers":[
        {
            "category":"Manufacturing",
            "subcategory":"Textiles",
            "type":"Manufacturing & Wholesale Goods"
        }
    ],
    "sg:phone":"+32 56 78 22 70",
    "sg:postcode":"8540",
    "sg:province":"West-Vlaanderen",
    "sg:tags":[
        "finishing"
    ],
    "wof:name":"Ovelacq Bvba",
    "wof:placetype":"venue"
},
  "geometry": {"coordinates":[3.3801438808,50.855255127],"type":"Point"}
}