{
  "type": "Feature",
  "properties": {
    "addr:full":"Rue De Rendarche 2a Assesse Namur 5336",
    "addr:housenumber":"2a",
    "addr:postcode":"5336",
    "addr:street":"Rue De Rendarche",
    "iso:country":"BE",
    "sg:address":"Rue De Rendarche 2a",
    "sg:city":"Assesse",
    "sg:orig_category":"Entretien et r\u00e9parations de v\u00e9hicules \u00e0 domicile. R\u00e9cup\u00e9ration de mati\u00e8res m\u00e9talliques recyclables a",
    "sg:phone":"+32 83 65 64 45",
    "sg:postcode":"5336",
    "sg:province":"Namur",
    "wof:name":"D\u00c9pannage Loriers",
    "wof:placetype":"venue"
},
  "geometry": {"coordinates":[4.9862360954,50.3803253174],"type":"Point"}
}