{
  "type": "Feature",
  "properties": {
    "addr:full":"Rue De L'industrie 15 Manage (la Hestre) Hainaut 7170",
    "addr:housenumber":"15",
    "addr:postcode":"7170",
    "addr:street":"Rue De L'Industrie;La;Hainaut",
    "iso:country":"BE",
    "sg:address":"Rue De L'industrie 15",
    "sg:city":"Manage (la Hestre)",
    "sg:classifiers":[
        {
            "category":"Professional",
            "subcategory":"Computer Services",
            "type":"Services"
        }
    ],
    "sg:phone":"+32 64 65 26 70",
    "sg:postcode":"7170",
    "sg:province":"Hainaut",
    "sg:tags":[
        "-",
        "processing",
        "data"
    ],
    "wof:name":"Chips & Mouses",
    "wof:placetype":"venue"
},
  "geometry": {"coordinates":[4.2253680229,50.477596283],"type":"Point"}
}