{
  "type": "Feature",
  "properties": {
    "addr:full":"Buizemontstraat 70 Geraardsbergen Oost-Vlaanderen 9500",
    "addr:housenumber":"70",
    "addr:postcode":"9500",
    "addr:street":"Buizemontstraat",
    "iso:country":"BE",
    "sg:address":"Buizemontstraat 70",
    "sg:city":"Geraardsbergen",
    "sg:orig_category":"Enseignement maternel and primaire",
    "sg:phone":"+32 54 41 22 74",
    "sg:postcode":"9500",
    "sg:province":"Oost-Vlaanderen",
    "wof:name":"Basisschool",
    "wof:placetype":"venue"
},
  "geometry": {"coordinates":[3.8830749989,50.7693023682],"type":"Point"}
}