{
  "type": "Feature",
  "properties": {
    "addr:full":"Sint-maartenstraat 55 Box 3 Leuven Vlaams-Brabant 3000",
    "addr:housenumber":"55;3",
    "addr:postcode":"3000",
    "addr:street":"Sint-Maartenstraat;Box",
    "iso:country":"BE",
    "sg:address":"Sint-maartenstraat 55 Box 3",
    "sg:city":"Leuven",
    "sg:classifiers":[
        {
            "category":"Arena",
            "subcategory":"Sports Club",
            "type":"Entertainment"
        }
    ],
    "sg:phone":"+32 16 29 63 78",
    "sg:postcode":"3000",
    "sg:province":"Vlaams-Brabant",
    "sg:tags":[
        "federation"
    ],
    "wof:name":"F.r.o.s.-brabant",
    "wof:placetype":"venue"
},
  "geometry": {"coordinates":[4.7037467957,50.882774353],"type":"Point"}
}