{
  "type": "Feature",
  "properties": {
    "iso:country":"BE",
    "sg:address":"Rue Croix-rouge 91",
    "sg:city":"Tinlot",
    "sg:orig_category":"Benzinestations and brandstoffen",
    "sg:phone":"+32 85 51 12 05",
    "sg:postcode":"4557",
    "sg:province":"Li\u00e8ge",
    "wof:name":"Marie Leclere",
    "wof:placetype":"venue"
},
  "geometry": {"coordinates":[5.4150938988,50.4851722717],"type":"Point"}
}