{
  "type": "Feature",
  "properties": {
    "addr:full":"Nieuwe Beggaardenstraat 50 Mechelen Antwerpen 2800",
    "addr:housenumber":"50",
    "addr:postcode":"2800",
    "addr:street":"Nieuwe Beggaardenstraat",
    "iso:country":"BE",
    "sg:address":"Nieuwe Beggaardenstraat 50",
    "sg:city":"Mechelen",
    "sg:orig_category":"Enseignement maternel and primaire",
    "sg:phone":"+32 15 21 86 23",
    "sg:postcode":"2800",
    "sg:province":"Antwerpen",
    "wof:name":"Vrije Basisschool",
    "wof:placetype":"venue"
},
  "geometry": {"coordinates":[4.4735560417,51.0297088623],"type":"Point"}
}