{
  "type": "Feature",
  "properties": {
    "iso:country":"BE",
    "sg:address":"Eedverbondkaai 40ba",
    "sg:city":"Gent",
    "sg:classifiers":[
        {
            "category":"Insurance",
            "subcategory":"Insurance Agent",
            "type":"Services"
        }
    ],
    "sg:phone":"+32 9 244 71 71",
    "sg:postcode":"9000",
    "sg:province":"Oost-Vlaanderen",
    "sg:tags":[
        "verzekeringsmakelaars",
        "expert"
    ],
    "wof:name":"Devriese",
    "wof:placetype":"venue"
},
  "geometry": {"coordinates":[3.7169380188,51.0420417786],"type":"Point"}
}