{
  "type": "Feature",
  "properties": {
    "iso:country":"BE",
    "sg:address":"Rue Haute 101",
    "sg:city":"Brussel/bruxelles",
    "sg:orig_category":"Eclairage et \u00e9quipements du foyer",
    "sg:phone":"+32 2 502 15 75",
    "sg:postcode":"1000",
    "sg:province":"Bruxelles-Capitale",
    "wof:name":"Maison Sortil\u00c8ges",
    "wof:placetype":"venue"
},
  "geometry": {"coordinates":[4.35060215,50.8394432068],"type":"Point"}
}