{
  "type": "Feature",
  "properties": {
    "iso:country":"BE",
    "sg:address":"Handelstraat 20",
    "sg:city":"Ingelmunster",
    "sg:orig_category":"Polishing, Dust, And Dish Cloths",
    "sg:phone":"+32 51 30 18 28",
    "sg:postcode":"8770",
    "sg:province":"West-Vlaanderen",
    "wof:name":"Bogatex Nv",
    "wof:placetype":"venue"
},
  "geometry": {"coordinates":[3.2576560974,50.9143028259],"type":"Point"}
}