{
  "type": "Feature",
  "properties": {
    "addr:full":"Rue Malibran 49 Elsene/ixelles Bruxelles-Capitale 1050",
    "addr:housenumber":"49",
    "addr:postcode":"1050",
    "addr:street":"Rue Malibran",
    "iso:country":"BE",
    "sg:address":"Rue Malibran 49",
    "sg:city":"Elsene/ixelles",
    "sg:orig_category":"Centres sportifs",
    "sg:phone":"+32 2 380 36 27",
    "sg:postcode":"1050",
    "sg:province":"Bruxelles-Capitale",
    "wof:name":"Biogym",
    "wof:placetype":"venue"
},
  "geometry": {"coordinates":[4.3734397888,50.8302879333],"type":"Point"}
}