{
  "type": "Feature",
  "properties": {
    "addr:full":"Avenue D'huart 20 Ciney Namur 5590",
    "addr:housenumber":"20",
    "addr:postcode":"5590",
    "addr:street":"Avenue D'Huart",
    "iso:country":"BE",
    "sg:address":"Avenue D'huart 20",
    "sg:city":"Ciney",
    "sg:classifiers":[
        {
            "category":"Health Services",
            "subcategory":"Health Practitioner",
            "type":"Services"
        }
    ],
    "sg:phone":"+32 83 21 37 15",
    "sg:postcode":"5590",
    "sg:province":"Namur",
    "sg:tags":[
        "physiotherapist"
    ],
    "wof:name":"Generet G",
    "wof:placetype":"venue"
},
  "geometry": {"coordinates":[5.0904111862,50.2901115417],"type":"Point"}
}