{
  "type": "Feature",
  "properties": {
    "addr:full":"Eikenstraat 250 Rumst Antwerpen 2840",
    "addr:housenumber":"250",
    "addr:postcode":"2840",
    "addr:street":"Eikenstraat",
    "iso:country":"BE",
    "sg:address":"Eikenstraat 250",
    "sg:city":"Rumst",
    "sg:classifiers":[
        {
            "category":"Building & Trades",
            "subcategory":"Construction",
            "type":"Services"
        }
    ],
    "sg:phone":"+32 3 888 02 27",
    "sg:postcode":"2840",
    "sg:province":"Antwerpen",
    "sg:tags":[
        "en",
        "la",
        "el\u00e9ments",
        "pour",
        "fab",
        "b\u00e9ton"
    ],
    "wof:name":"Wijckmans J.",
    "wof:placetype":"venue"
},
  "geometry": {"coordinates":[4.4048881531,51.1152763367],"type":"Point"}
}