{
  "type": "Feature",
  "properties": {
    "iso:country":"BE",
    "sg:address":"Ruidenbergstraat 2",
    "sg:city":"Kortemark",
    "sg:classifiers":[
        {
            "category":"Building & Trades",
            "subcategory":"Plumbing",
            "type":"Services"
        }
    ],
    "sg:phone":"+32 51 58 12 66",
    "sg:postcode":"8610",
    "sg:province":"West-Vlaanderen",
    "sg:tags":[
        "contractor"
    ],
    "wof:name":"Van Rijckeghem",
    "wof:placetype":"venue"
},
  "geometry": {"coordinates":[3.0424449444,51.028503418],"type":"Point"}
}