{
  "type": "Feature",
  "properties": {
    "iso:country":"BE",
    "sg:address":"Manitobalaan 28 Box 1",
    "sg:city":"Brugge (sint-andries)",
    "sg:classifiers":[
        {
            "category":"Insurance",
            "subcategory":"Insurance Agent",
            "type":"Services"
        }
    ],
    "sg:phone":"+32 50 39 37 58",
    "sg:postcode":"8200",
    "sg:province":"West-Vlaanderen",
    "sg:tags":[
        "-",
        "representative"
    ],
    "wof:name":"Reyngout A",
    "wof:placetype":"venue"
},
  "geometry": {"coordinates":[3.1970069408,51.1990776062],"type":"Point"}
}