{
  "type": "Feature",
  "properties": {
    "iso:country":"BE",
    "sg:address":"Bilzersteenweg 46bc",
    "sg:city":"Hoeselt",
    "sg:orig_category":"Fleurs and plantes",
    "sg:phone":"+32 89 41 10 67",
    "sg:postcode":"3730",
    "sg:province":"Limburg",
    "wof:name":"Catharina Bart",
    "wof:placetype":"venue"
},
  "geometry": {"coordinates":[5.4962081909,50.8552360535],"type":"Point"}
}