{
  "type": "Feature",
  "properties": {
    "addr:full":"Hufengasse 4 Eupen Li\u00e8ge 4700",
    "addr:housenumber":"4",
    "addr:postcode":"4700",
    "addr:street":"Hufengasse",
    "iso:country":"BE",
    "sg:address":"Hufengasse 4",
    "sg:city":"Eupen",
    "sg:classifiers":[
        {
            "category":"Professional",
            "subcategory":"Testing Lab",
            "type":"Services"
        }
    ],
    "sg:phone":"+32 87 59 96 30",
    "sg:postcode":"4700",
    "sg:province":"Li\u00e8ge",
    "sg:tags":[
        "laboratory",
        "medical"
    ],
    "wof:name":"H\u00f4pital Saint Nicolas-laboratoire D'analyses M\u00e9dicales",
    "wof:placetype":"venue"
},
  "geometry": {"coordinates":[6.0297698975,50.6291999817],"type":"Point"}
}