{
  "type": "Feature",
  "properties": {
    "addr:full":"Paalstraat 205 Schoten Antwerpen 2900",
    "addr:housenumber":"205",
    "addr:postcode":"2900",
    "addr:street":"Paalstraat",
    "iso:country":"BE",
    "sg:address":"Paalstraat 205",
    "sg:city":"Schoten",
    "sg:classifiers":[
        {
            "category":"Bars & Pubs",
            "type":"Food & Drink"
        }
    ],
    "sg:phone":"+32 3 658 46 57",
    "sg:postcode":"2900",
    "sg:province":"Antwerpen",
    "wof:name":"Derby",
    "wof:placetype":"venue"
},
  "geometry": {"coordinates":[4.5043478012,51.2565078735],"type":"Point"}
}