{
  "type": "Feature",
  "properties": {
    "iso:country":"BE",
    "sg:address":"Noordlaan 148",
    "sg:city":"Dendermonde",
    "sg:orig_category":"Secr\u00e9tariats sociaux",
    "sg:phone":"+32 52 21 92 11",
    "sg:postcode":"9200",
    "sg:province":"Oost-Vlaanderen",
    "wof:name":"A.s.k.z.-a.p.z.",
    "wof:placetype":"venue"
},
  "geometry": {"coordinates":[4.092487812,51.0337677002],"type":"Point"}
}