{
  "type": "Feature",
  "properties": {
    "iso:country":"BE",
    "sg:address":"Kruisbergstraat 36",
    "sg:city":"Ruiselede",
    "sg:orig_category":"Varkenskwekers",
    "sg:phone":"+32 51 68 86 92",
    "sg:postcode":"8755",
    "sg:province":"West-Vlaanderen",
    "wof:name":"Robert Kint",
    "wof:placetype":"venue"
},
  "geometry": {"coordinates":[3.3769879341,51.0762557983],"type":"Point"}
}