{
  "type": "Feature",
  "properties": {
    "addr:full":"Rue L\u00e9opold Et Victorien Barr\u00e9 24 Dinant Namur 5500",
    "addr:housenumber":"24",
    "addr:postcode":"5500",
    "addr:street":"Rue Le\u0301Opold Et Victorien Barre\u0301",
    "iso:country":"BE",
    "sg:address":"Rue L\u00e9opold Et Victorien Barr\u00e9 24",
    "sg:city":"Dinant",
    "sg:classifiers":[
        {
            "category":"Insurance",
            "subcategory":"Insurance Agent",
            "type":"Services"
        }
    ],
    "sg:phone":"+32 82 22 52 22",
    "sg:postcode":"5500",
    "sg:province":"Namur",
    "sg:tags":[
        "broker"
    ],
    "wof:name":"Pauchet Th",
    "wof:placetype":"venue"
},
  "geometry": {"coordinates":[4.9086909294,50.2635955811],"type":"Point"}
}