{
  "type": "Feature",
  "properties": {
    "iso:country":"BE",
    "sg:address":"Kapelveldstraat 25",
    "sg:city":"Zutendaal",
    "sg:orig_category":"Installatie van houten of kunststof schrijnwerk",
    "sg:phone":"+32 89 61 37 10",
    "sg:postcode":"3690",
    "sg:province":"Limburg",
    "wof:name":"D.f.i.d.",
    "wof:placetype":"venue"
},
  "geometry": {"coordinates":[5.5731167793,50.9314651489],"type":"Point"}
}