{
  "type": "Feature",
  "properties": {
    "iso:country":"BE",
    "sg:address":"Rue Sainte-anne 13 Box 1",
    "sg:city":"Huy",
    "sg:classifiers":[
        {
            "category":"Arts & Performance",
            "subcategory":"Symphony",
            "type":"Entertainment"
        }
    ],
    "sg:phone":"+32 85 51 48 83",
    "sg:postcode":"4500",
    "sg:province":"Li\u00e8ge",
    "sg:tags":[
        "orchestra"
    ],
    "wof:name":"Coktail Music",
    "wof:placetype":"venue"
},
  "geometry": {"coordinates":[5.2571959496,50.5141983032],"type":"Point"}
}