{
  "type": "Feature",
  "properties": {
    "addr:full":"Place Froissart 22 Chimay Hainaut 6460",
    "addr:housenumber":"22",
    "addr:postcode":"6460",
    "addr:street":"Place Froissart",
    "iso:country":"BE",
    "sg:address":"Place Froissart 22",
    "sg:city":"Chimay",
    "sg:classifiers":[
        {
            "category":"Real Estate",
            "subcategory":"Architect",
            "type":"Services"
        }
    ],
    "sg:phone":"+32 60 21 17 77",
    "sg:postcode":"6460",
    "sg:province":"Hainaut",
    "wof:name":"Hubert J",
    "wof:placetype":"venue"
},
  "geometry": {"coordinates":[4.31291008,50.0471496582],"type":"Point"}
}