{
  "type": "Feature",
  "properties": {
    "iso:country":"BE",
    "sg:address":"Avenue De Hinnisdael 51",
    "sg:city":"Bruxelles (woluwe-saint-pierre)",
    "sg:classifiers":[
        {
            "category":"Real Estate",
            "subcategory":"Surveying",
            "type":"Services"
        }
    ],
    "sg:phone":"+32 2 779 04 10",
    "sg:postcode":"1150",
    "sg:province":"Bruxelles-Capitale",
    "sg:tags":[
        "raw",
        "material",
        "-",
        "plastic"
    ],
    "wof:name":"Thuysbaert Nv",
    "wof:placetype":"venue"
},
  "geometry": {"coordinates":[4.4648799896,50.8426589966],"type":"Point"}
}