{
  "type": "Feature",
  "properties": {
    "addr:full":"Rue Neuve 36 Ch\u00e2telet Hainaut 6200",
    "addr:housenumber":"36",
    "addr:postcode":"6200",
    "addr:street":"Rue Neuve",
    "iso:country":"BE",
    "sg:address":"Rue Neuve 36",
    "sg:city":"Ch\u00e2telet",
    "sg:classifiers":[
        {
            "category":"Professional",
            "subcategory":"Testing Lab",
            "type":"Services"
        }
    ],
    "sg:phone":"+32 71 38 10 99",
    "sg:postcode":"6200",
    "sg:province":"Hainaut",
    "sg:tags":[
        "chemist"
    ],
    "wof:name":"Eupharma",
    "wof:placetype":"venue"
},
  "geometry": {"coordinates":[4.522796154,50.4046707153],"type":"Point"}
}