{
  "type": "Feature",
  "properties": {
    "iso:country":"BE",
    "sg:address":"Rue Des Trois Rois 4",
    "sg:city":"Charleroi",
    "sg:orig_category":"Speelgoed",
    "sg:phone":"+32 71 33 36 90",
    "sg:postcode":"6000",
    "sg:province":"Hainaut",
    "wof:name":"Les Trois Rois",
    "wof:placetype":"venue"
},
  "geometry": {"coordinates":[4.4450612068,50.4122810364],"type":"Point"}
}