{
  "type": "Feature",
  "properties": {
    "addr:full":"Rue Des Archers 41 Mons Hainaut 7000",
    "addr:housenumber":"41",
    "addr:postcode":"7000",
    "addr:street":"Rue Des Archers;Hainaut",
    "iso:country":"BE",
    "sg:address":"Rue Des Archers 41",
    "sg:city":"Mons",
    "sg:classifiers":[
        {
            "category":"Shopping",
            "subcategory":"Bicycles & Sporting Goods",
            "type":"Retail Goods"
        }
    ],
    "sg:phone":"+32 65 31 27 64",
    "sg:postcode":"7000",
    "sg:province":"Hainaut",
    "sg:tags":[
        "-"
    ],
    "wof:name":"Coupain J-m",
    "wof:placetype":"venue"
},
  "geometry": {"coordinates":[3.9572279453,50.4516105652],"type":"Point"}
}