{
  "type": "Feature",
  "properties": {
    "addr:full":"Kattevennen 15 Genk Limburg 3600",
    "addr:housenumber":"15",
    "addr:postcode":"3600",
    "addr:street":"Kattevennen",
    "iso:country":"BE",
    "sg:address":"Kattevennen 15",
    "sg:city":"Genk",
    "sg:classifiers":[
        {
            "category":"Sports & Exercise",
            "subcategory":"Sports Center",
            "type":"Entertainment"
        }
    ],
    "sg:phone":"+32 89 35 68 06",
    "sg:postcode":"3600",
    "sg:province":"Limburg",
    "sg:tags":[
        "terrain",
        "hors",
        "de",
        "installation",
        "sportifs"
    ],
    "wof:name":"Bloso",
    "wof:placetype":"venue"
},
  "geometry": {"coordinates":[5.5295801163,50.9545516968],"type":"Point"}
}