{
  "type": "Feature",
  "properties": {
    "iso:country":"BE",
    "sg:address":"Grote Markt 29",
    "sg:city":"Roeselare",
    "sg:orig_category":"Woningbouw",
    "sg:phone":"+32 51 22 91 69",
    "sg:postcode":"8800",
    "sg:province":"West-Vlaanderen",
    "wof:name":"Hyfibo",
    "wof:placetype":"venue"
},
  "geometry": {"coordinates":[3.1246728897,50.9450645447],"type":"Point"}
}