{
  "type": "Feature",
  "properties": {
    "iso:country":"BE",
    "sg:address":"Theod. Sevenslaan 184",
    "sg:city":"Kortrijk",
    "sg:orig_category":"Erotische Etablissementen",
    "sg:phone":"+32 479 85 69 41",
    "sg:postcode":"8500",
    "sg:province":"West-Vlaanderen",
    "wof:name":"Prive Ontvangst Beatrice",
    "wof:placetype":"venue"
},
  "geometry": {"coordinates":[3.2881391048,50.8297195435],"type":"Point"}
}