{
  "type": "Feature",
  "properties": {
    "addr:full":"Avenue Ch. Et L. Godin 6 Huy Li\u00e8ge 4500",
    "addr:housenumber":"6",
    "addr:postcode":"4500",
    "addr:street":"Avenue Ch. Et L. Godin",
    "iso:country":"BE",
    "sg:address":"Avenue Ch. Et L. Godin 6",
    "sg:city":"Huy",
    "sg:classifiers":[
        {
            "category":"Professional",
            "subcategory":"Lawyer & Legal Services",
            "type":"Services"
        }
    ],
    "sg:phone":"+32 85 21 69 68",
    "sg:postcode":"4500",
    "sg:province":"Li\u00e8ge",
    "wof:name":"Louis Bernard",
    "wof:placetype":"venue"
},
  "geometry": {"coordinates":[5.2427949905,50.5228347778],"type":"Point"}
}