{
  "type": "Feature",
  "properties": {
    "addr:full":"Avenue Houba De Strooper 123 Bruxelles Bruxelles-Capitale 1020",
    "addr:housenumber":"123",
    "addr:postcode":"1020",
    "addr:street":"Avenue Houba De Strooper",
    "iso:country":"BE",
    "sg:address":"Avenue Houba De Strooper 123",
    "sg:city":"Bruxelles",
    "sg:classifiers":[
        {
            "category":"Shopping",
            "subcategory":"Crafts & Fabrics",
            "type":"Retail Goods"
        }
    ],
    "sg:phone":"+32 2 478 20 07",
    "sg:postcode":"1020",
    "sg:province":"Bruxelles-Capitale",
    "sg:tags":[
        "needlework",
        "lady"
    ],
    "wof:name":"Mary Laines",
    "wof:placetype":"venue"
},
  "geometry": {"coordinates":[4.3380331993,50.8894271851],"type":"Point"}
}