{
  "type": "Feature",
  "properties": {
    "iso:country":"BE",
    "sg:address":"Morsehan 33",
    "sg:city":"Bouillon",
    "sg:classifiers":[
        {
            "category":"Education",
            "subcategory":"School",
            "type":"Public Place"
        }
    ],
    "sg:phone":"+32 61 46 72 95",
    "sg:postcode":"6830",
    "sg:province":"Luxembourg",
    "sg:tags":[
        "boarding"
    ],
    "wof:name":"Ath\u00e9n\u00e9e Royal Bouillon-paliseul",
    "wof:placetype":"venue"
},
  "geometry": {"coordinates":[5.0707578659,49.7873916626],"type":"Point"}
}