{
  "type": "Feature",
  "properties": {
    "addr:full":"Tieblokkenln 8 Turnhout Antwerpen 2300",
    "addr:housenumber":"8",
    "addr:postcode":"2300",
    "addr:street":"Tieblokkenln",
    "iso:country":"BE",
    "sg:address":"Tieblokkenln 8",
    "sg:city":"Turnhout",
    "sg:classifiers":[
        {
            "category":"Professional",
            "type":"Services"
        }
    ],
    "sg:phone":"+32 14 47 14 70",
    "sg:postcode":"2300",
    "sg:province":"Antwerpen",
    "sg:tags":[
        "transport",
        "road"
    ],
    "wof:name":"Gilis - Driesen Nv",
    "wof:placetype":"venue"
},
  "geometry": {"coordinates":[4.9266262054,51.3035926819],"type":"Point"}
}