{
  "type": "Feature",
  "properties": {
    "iso:country":"BE",
    "sg:address":"Zeedijk 354",
    "sg:city":"Oostende",
    "sg:orig_category":"Rusthuizen and serviceflats",
    "sg:phone":"+32 59 70 21 38",
    "sg:postcode":"8400",
    "sg:province":"West-Vlaanderen",
    "wof:name":"Fa. Royal Midland",
    "wof:placetype":"venue"
},
  "geometry": {"coordinates":[2.8595368862,51.2072486877],"type":"Point"}
}