{
  "type": "Feature",
  "properties": {
    "addr:full":"Augustijnslei 46 Brasschaat Antwerpen 2930",
    "addr:housenumber":"46",
    "addr:postcode":"2930",
    "addr:street":"Augustijnslei",
    "iso:country":"BE",
    "sg:address":"Augustijnslei 46",
    "sg:city":"Brasschaat",
    "sg:classifiers":[
        {
            "category":"Health Services",
            "subcategory":"Dentist",
            "type":"Services"
        }
    ],
    "sg:phone":"+32 3 652 05 04",
    "sg:postcode":"2930",
    "sg:province":"Antwerpen",
    "wof:name":"Heymans Karine",
    "wof:placetype":"venue"
},
  "geometry": {"coordinates":[4.4905152321,51.2921142578],"type":"Point"}
}