{
  "type": "Feature",
  "properties": {
    "iso:country":"BE",
    "sg:address":"Industrieweg 16",
    "sg:city":"Grobbendonk",
    "sg:orig_category":"Huisvuilophaling and -verwerking",
    "sg:phone":"+32 14 51 59 15",
    "sg:postcode":"2280",
    "sg:province":"Antwerpen",
    "wof:name":"Van Den Heuvel Recyclage",
    "wof:placetype":"venue"
},
  "geometry": {"coordinates":[4.7343120575,51.1789665222],"type":"Point"}
}