{
  "type": "Feature",
  "properties": {
    "addr:full":"Turnhoutsebaan 237 Antwerpen (borgerhout) Antwerpen 2140",
    "addr:housenumber":"237",
    "addr:postcode":"2140",
    "addr:street":"Turnhoutsebaan",
    "iso:country":"BE",
    "sg:address":"Turnhoutsebaan 237",
    "sg:city":"Antwerpen (borgerhout)",
    "sg:classifiers":[
        {
            "category":"Health Services",
            "subcategory":"Dentist",
            "type":"Services"
        }
    ],
    "sg:phone":"+32 3 236 04 82",
    "sg:postcode":"2140",
    "sg:province":"Antwerpen",
    "sg:tags":[
        "dental",
        "clinic"
    ],
    "wof:name":"Tandheelkundig Centrum Bvba",
    "wof:placetype":"venue"
},
  "geometry": {"coordinates":[4.4332199097,51.2137565613],"type":"Point"}
}