{
  "type": "Feature",
  "properties": {
    "addr:full":"Kauwakkerstraat 1 Heuvelland (nieuwkerke) West-Vlaanderen 8950",
    "addr:housenumber":"1",
    "addr:postcode":"8950",
    "addr:street":"Kauwakkerstraat",
    "iso:country":"BE",
    "sg:address":"Kauwakkerstraat 1",
    "sg:city":"Heuvelland (nieuwkerke)",
    "sg:classifiers":[
        {
            "category":"Bars & Pubs",
            "type":"Food & Drink"
        }
    ],
    "sg:phone":"+32 57 44 74 90",
    "sg:postcode":"8950",
    "sg:province":"West-Vlaanderen",
    "wof:name":"De Kauwackers",
    "wof:placetype":"venue"
},
  "geometry": {"coordinates":[2.8022110462,50.7487792969],"type":"Point"}
}