{
  "type": "Feature",
  "properties": {
    "addr:full":"Place E Vandervelde 32 Charleroi Hainaut 6061",
    "addr:housenumber":"32",
    "addr:postcode":"6061",
    "addr:street":"Place E Vandervelde;Hainaut",
    "iso:country":"BE",
    "sg:address":"Place E Vandervelde 32",
    "sg:city":"Charleroi",
    "sg:orig_category":"Natuursteenbewerking",
    "sg:phone":"+32 71 41 28 96",
    "sg:postcode":"6061",
    "sg:province":"Hainaut",
    "wof:name":"Bertinchamps",
    "wof:placetype":"venue"
},
  "geometry": {"coordinates":[4.4795150757,50.4009437561],"type":"Point"}
}