{
  "type": "Feature",
  "properties": {
    "addr:full":"Lombaardstraat 26 Ieper West-Vlaanderen 8900",
    "addr:housenumber":"26",
    "addr:postcode":"8900",
    "addr:street":"Lombaardstraat",
    "iso:country":"BE",
    "sg:address":"Lombaardstraat 26",
    "sg:city":"Ieper",
    "sg:orig_category":"Advocaten and juridische adviseurs",
    "sg:phone":"+32 57 20 53 07",
    "sg:postcode":"8900",
    "sg:province":"West-Vlaanderen",
    "wof:name":"Johan Houtman",
    "wof:placetype":"venue"
},
  "geometry": {"coordinates":[2.8846809864,50.847618103],"type":"Point"}
}