{
  "type": "Feature",
  "properties": {
    "iso:country":"BE",
    "sg:address":"Ru Du Mail",
    "sg:city":"Brussels",
    "sg:classifiers":[
        {
            "category":"Industrial Area",
            "type":"Public Place"
        }
    ],
    "sg:phone":"+32 2 536 51 30",
    "sg:postcode":"1050",
    "sg:province":"Bruxelles-Capitale",
    "sg:tags":[
        "large",
        "private"
    ],
    "wof:name":"D' Ieteren S.a.",
    "wof:placetype":"venue"
},
  "geometry": {"coordinates":[4.3595142365,50.8218078613],"type":"Point"}
}