{
  "type": "Feature",
  "properties": {
    "addr:full":"Sint-michielsplein 11 Westerlo (oevel) Antwerpen 2260",
    "addr:housenumber":"11",
    "addr:postcode":"2260",
    "addr:street":"Sint-Michielsplein",
    "iso:country":"BE",
    "sg:address":"Sint-michielsplein 11",
    "sg:city":"Westerlo (oevel)",
    "sg:classifiers":[
        {
            "category":"Health Services",
            "subcategory":"Health Practitioner",
            "type":"Services"
        }
    ],
    "sg:phone":"+32 14 23 00 35",
    "sg:postcode":"2260",
    "sg:province":"Antwerpen",
    "sg:tags":[
        "physiotherapist"
    ],
    "wof:name":"Vermeulen S",
    "wof:placetype":"venue"
},
  "geometry": {"coordinates":[4.9053039551,51.1391906738],"type":"Point"}
}