{
  "type": "Feature",
  "properties": {
    "addr:full":"Rue Alfred Bequet 3 Namur Namur 5000",
    "addr:housenumber":"3",
    "addr:postcode":"5000",
    "addr:street":"Rue Alfred Bequet",
    "iso:country":"BE",
    "sg:address":"Rue Alfred Bequet 3",
    "sg:city":"Namur",
    "sg:classifiers":[
        {
            "category":"Food & Beverages",
            "subcategory":"Specialty",
            "type":"Retail Goods"
        }
    ],
    "sg:phone":"+32 81 74 65 95",
    "sg:postcode":"5000",
    "sg:province":"Namur",
    "sg:tags":[
        "health",
        "dietary",
        "-",
        "biological"
    ],
    "wof:name":"Nature & Saveurs",
    "wof:placetype":"venue"
},
  "geometry": {"coordinates":[4.8385500908,50.4611473083],"type":"Point"}
}