{
  "type": "Feature",
  "properties": {
    "iso:country":"BE",
    "sg:address":"Perreveld 13",
    "sg:city":"Opwijk",
    "sg:orig_category":"Diverse bouwafwerking and reiniging Huisdierenkwekers",
    "sg:phone":"+32 52 35 43 89",
    "sg:postcode":"1745",
    "sg:province":"Vlaams-Brabant",
    "wof:name":"Hendrik De Bleser",
    "wof:placetype":"venue"
},
  "geometry": {"coordinates":[4.1705150604,50.9644241333],"type":"Point"}
}