{
  "type": "Feature",
  "properties": {
    "addr:full":"Rue Du Lac 10 Chimay Hainaut 6461",
    "addr:housenumber":"10",
    "addr:postcode":"6461",
    "addr:street":"Rue Du Lac",
    "iso:country":"BE",
    "sg:address":"Rue Du Lac 10",
    "sg:city":"Chimay",
    "sg:orig_category":"Textiel",
    "sg:phone":"+32 60 21 22 64",
    "sg:postcode":"6461",
    "sg:province":"Hainaut",
    "wof:name":"Phildar",
    "wof:placetype":"venue"
},
  "geometry": {"coordinates":[4.3356871605,50.0661354065],"type":"Point"}
}