{
  "type": "Feature",
  "properties": {
    "addr:full":"Rte De Hannut 78-80 Namur Namur 5004",
    "addr:postcode":"78-80;5004",
    "addr:street":"Rte De Hannut",
    "iso:country":"BE",
    "sg:address":"Rte De Hannut 78-80",
    "sg:city":"Namur",
    "sg:classifiers":[
        {
            "category":"Autos & Motor Vehicles",
            "subcategory":"Automobile Sales",
            "type":"Retail Goods"
        }
    ],
    "sg:phone":"+32 81 21 42 32",
    "sg:postcode":"5004",
    "sg:province":"Namur",
    "sg:tags":[
        "equipment",
        "motor-cars",
        "transport"
    ],
    "wof:name":"Carrosserie Desbuleux & Pignataro Sprl",
    "wof:placetype":"venue"
},
  "geometry": {"coordinates":[4.9050722122,50.4740638733],"type":"Point"}
}