{
  "type": "Feature",
  "properties": {
    "iso:country":"BE",
    "sg:address":"Brandstraat 3",
    "sg:city":"Boom",
    "sg:classifiers":[
        {
            "category":"Professional",
            "subcategory":"Computer Services",
            "type":"Services"
        }
    ],
    "sg:phone":"+32 3 290 75 99",
    "sg:postcode":"2850",
    "sg:province":"Antwerpen",
    "sg:tags":[
        "-",
        "processing",
        "data"
    ],
    "wof:name":"Compoint",
    "wof:placetype":"venue"
},
  "geometry": {"coordinates":[4.3671078682,51.0866622925],"type":"Point"}
}