{
  "type": "Feature",
  "properties": {
    "addr:full":"Rue Du Molinay 67 Seraing Li\u00e8ge 4100",
    "addr:housenumber":"67",
    "addr:postcode":"4100",
    "addr:street":"Rue Du Molinay",
    "iso:country":"BE",
    "sg:address":"Rue Du Molinay 67",
    "sg:city":"Seraing",
    "sg:classifiers":[
        {
            "category":"Autos & Motor Vehicles",
            "subcategory":"Automobile Sales",
            "type":"Retail Goods"
        }
    ],
    "sg:phone":"+32 4 337 27 00",
    "sg:postcode":"4100",
    "sg:province":"Li\u00e8ge",
    "sg:tags":[
        "car",
        "used",
        "-"
    ],
    "wof:name":"Car Consult Service",
    "wof:placetype":"venue"
},
  "geometry": {"coordinates":[5.5140762329,50.6071853638],"type":"Point"}
}