{
  "type": "Feature",
  "properties": {
    "iso:country":"BE",
    "sg:address":"Rue Berckmans 96",
    "sg:city":"Sint-gillis/saint-gilles",
    "sg:orig_category":"M\u00e9decins and sp\u00e9cialistes",
    "sg:phone":"+32 2 539 20 04",
    "sg:postcode":"1060",
    "sg:province":"Bruxelles-Capitale",
    "wof:name":"M. Zizi/martin Zizi",
    "wof:placetype":"venue"
},
  "geometry": {"coordinates":[4.3522758484,50.8319358826],"type":"Point"}
}