{
  "type": "Feature",
  "properties": {
    "iso:country":"BE",
    "sg:address":"Waterloostraat 12a",
    "sg:city":"Herentals",
    "sg:orig_category":"Installation \u00e9lectrique industrielle",
    "sg:phone":"+32 486 30 78 08",
    "sg:postcode":"2200",
    "sg:province":"Antwerpen",
    "wof:name":"Mobiele Slotenmaker",
    "wof:placetype":"venue"
},
  "geometry": {"coordinates":[4.8267998695,51.1747245789],"type":"Point"}
}