{
  "type": "Feature",
  "properties": {
    "addr:full":"Melkerijstraat 59 Wachtebeke Oost-Vlaanderen 9185",
    "addr:housenumber":"59",
    "addr:postcode":"9185",
    "addr:street":"Melkerijstraat",
    "iso:country":"BE",
    "sg:address":"Melkerijstraat 59",
    "sg:city":"Wachtebeke",
    "sg:orig_category":"Animations diverses",
    "sg:phone":"+32 9 345 99 07",
    "sg:postcode":"9185",
    "sg:province":"Oost-Vlaanderen",
    "wof:name":"Disco Exotic",
    "wof:placetype":"venue"
},
  "geometry": {"coordinates":[3.8603820801,51.1764526367],"type":"Point"}
}