{
  "type": "Feature",
  "properties": {
    "addr:full":"Kanaalweg 63 Tessenderlo Limburg 3980",
    "addr:housenumber":"63",
    "addr:postcode":"3980",
    "addr:street":"Kanaalweg",
    "iso:country":"BE",
    "sg:address":"Kanaalweg 63",
    "sg:city":"Tessenderlo",
    "sg:orig_category":"Herstellingen and onderhoud van auto's Voertuigen",
    "sg:phone":"+32 13 66 40 49",
    "sg:postcode":"3980",
    "sg:province":"Limburg",
    "wof:name":"Powercars",
    "wof:placetype":"venue"
},
  "geometry": {"coordinates":[5.154820919,51.0753135681],"type":"Point"}
}