{
  "type": "Feature",
  "properties": {
    "addr:full":"Koningsstraat 11 Leopoldsburg Limburg 3970",
    "addr:housenumber":"11",
    "addr:postcode":"3970",
    "addr:street":"Koningsstraat",
    "iso:country":"BE",
    "sg:address":"Koningsstraat 11",
    "sg:city":"Leopoldsburg",
    "sg:orig_category":"Dameskledingzaken",
    "sg:phone":"+32 11 34 37 41",
    "sg:postcode":"3970",
    "sg:province":"Limburg",
    "wof:name":"Huis Caprice",
    "wof:placetype":"venue"
},
  "geometry": {"coordinates":[5.2607622147,51.1164169312],"type":"Point"}
}