{
  "type": "Feature",
  "properties": {
    "addr:full":"Affligemdreef 115 Aalst Oost-Vlaanderen 9300",
    "addr:housenumber":"115",
    "addr:postcode":"9300",
    "addr:street":"Affligemdreef",
    "iso:country":"BE",
    "sg:address":"Affligemdreef 115",
    "sg:city":"Aalst",
    "sg:orig_category":"Woningbouw",
    "sg:phone":"+32 53 77 10 18",
    "sg:postcode":"9300",
    "sg:province":"Oost-Vlaanderen",
    "wof:name":"Herman Temmerman",
    "wof:placetype":"venue"
},
  "geometry": {"coordinates":[4.0691862106,50.9354667664],"type":"Point"}
}