{
  "type": "Feature",
  "properties": {
    "addr:full":"Sint-gillislaan 54 Dendermonde Oost-Vlaanderen 9200",
    "addr:housenumber":"54",
    "addr:postcode":"9200",
    "addr:street":"Sint-Gillislaan;Oost-Vlaanderen",
    "iso:country":"BE",
    "sg:address":"Sint-gillislaan 54",
    "sg:city":"Dendermonde",
    "sg:orig_category":"Agences immobili\u00e8res. Assurances. Maisons de vacances",
    "sg:phone":"+32 52 22 32 92",
    "sg:postcode":"9200",
    "sg:province":"Oost-Vlaanderen",
    "wof:name":"Zakenkantoor - Immo Wim",
    "wof:placetype":"venue"
},
  "geometry": {"coordinates":[4.1096482277,51.020072937],"type":"Point"}
}