{
  "type": "Feature",
  "properties": {
    "addr:full":"Sticheldreef 3 Nazareth Oost-Vlaanderen 9810",
    "addr:housenumber":"3",
    "addr:postcode":"9810",
    "addr:street":"Sticheldreef",
    "iso:country":"BE",
    "sg:address":"Sticheldreef 3",
    "sg:city":"Nazareth",
    "sg:orig_category":"Advocaten and juridische adviseurs",
    "sg:phone":"+32 9 385 40 65",
    "sg:postcode":"9810",
    "sg:province":"Oost-Vlaanderen",
    "wof:name":"F. Rogge",
    "wof:placetype":"venue"
},
  "geometry": {"coordinates":[3.5991148949,50.9658432007],"type":"Point"}
}