{
  "type": "Feature",
  "properties": {
    "iso:country":"BE",
    "sg:address":"Meirbrug 1 Box 2",
    "sg:city":"Antwerpen",
    "sg:classifiers":[
        {
            "category":"Banks & Credit Unions",
            "subcategory":"Investment Brokerage",
            "type":"Services"
        }
    ],
    "sg:phone":"+32 3 225 14 68",
    "sg:postcode":"2000",
    "sg:province":"Antwerpen",
    "sg:tags":[
        "auditor"
    ],
    "wof:name":"De Lille, Grare & Co",
    "wof:placetype":"venue"
},
  "geometry": {"coordinates":[4.4047470093,51.2186164856],"type":"Point"}
}