{
  "type": "Feature",
  "properties": {
    "addr:full":"Rue De L'h\u00d4tel Communal 74 Grace-hollogne Li\u00e8ge 4460",
    "addr:housenumber":"74",
    "addr:postcode":"4460",
    "addr:street":"Rue De L'Ho \u0302Tel Communal",
    "iso:country":"BE",
    "sg:address":"Rue De L'h\u00d4tel Communal 74",
    "sg:city":"Grace-hollogne",
    "sg:orig_category":"D\u00e9chets and d\u00e9bris Gr",
    "sg:phone":"+32 4 231 12 25",
    "sg:postcode":"4460",
    "sg:province":"Li\u00e8ge",
    "wof:name":"Alfred Van Der Jeucht",
    "wof:placetype":"venue"
},
  "geometry": {"coordinates":[5.4812321663,50.6317825317],"type":"Point"}
}