{
  "type": "Feature",
  "properties": {
    "iso:country":"BE",
    "sg:address":"Schaapsdijk 55",
    "sg:city":"Wuustwezel",
    "sg:classifiers":[
        {
            "category":"Retail",
            "subcategory":"Auto Repair",
            "type":"Services"
        }
    ],
    "sg:phone":"+32 3 669 65 32",
    "sg:postcode":"2990",
    "sg:province":"Antwerpen",
    "sg:tags":[
        "garage"
    ],
    "wof:name":"Vermeeren R",
    "wof:placetype":"venue"
},
  "geometry": {"coordinates":[4.6036090851,51.3780403137],"type":"Point"}
}