{
  "type": "Feature",
  "properties": {
    "iso:country":"BE",
    "sg:address":"Meistraat 37",
    "sg:city":"Evergem",
    "sg:orig_category":"Rundveehouders Varkenskwekers",
    "sg:phone":"+32 9 357 37 41",
    "sg:postcode":"9940",
    "sg:province":"Oost-Vlaanderen",
    "wof:name":"Antoine Van Acker",
    "wof:placetype":"venue"
},
  "geometry": {"coordinates":[3.653331995,51.1204528809],"type":"Point"}
}