{
  "type": "Feature",
  "properties": {
    "iso:country":"BE",
    "sg:address":"Gouv. Verwilghensingel 5",
    "sg:city":"Hasselt",
    "sg:orig_category":"Volwassenenonderwijs",
    "sg:phone":"+32 11 26 73 51",
    "sg:postcode":"3500",
    "sg:province":"Limburg",
    "wof:name":"Prov.centr.moderne Talen",
    "wof:placetype":"venue"
},
  "geometry": {"coordinates":[5.3526930809,50.9375686646],"type":"Point"}
}