{
  "type": "Feature",
  "properties": {
    "iso:country":"BE",
    "sg:address":"Magdalena Vermeeschlaan 24",
    "sg:city":"Hove",
    "sg:orig_category":"M\u00e9decins and sp\u00e9cialistes",
    "sg:phone":"+32 3 455 82 68",
    "sg:postcode":"2540",
    "sg:province":"Antwerpen",
    "wof:name":"M. Langenhaeck",
    "wof:placetype":"venue"
},
  "geometry": {"coordinates":[4.4793810844,51.1433105469],"type":"Point"}
}