{
  "type": "Feature",
  "properties": {
    "addr:full":"Roeselarestraat 92 Diksmuide West-Vlaanderen 8600",
    "addr:housenumber":"92",
    "addr:postcode":"8600",
    "addr:street":"Roeselarestraat",
    "iso:country":"BE",
    "sg:address":"Roeselarestraat 92",
    "sg:city":"Diksmuide",
    "sg:classifiers":[
        {
            "category":"Utilities",
            "subcategory":"Fuel Oil & Lpg",
            "type":"Services"
        }
    ],
    "sg:phone":"+32 51 50 00 87",
    "sg:postcode":"8600",
    "sg:province":"West-Vlaanderen",
    "wof:name":"Broucke Bvba",
    "wof:placetype":"venue"
},
  "geometry": {"coordinates":[2.9181659222,51.024181366],"type":"Point"}
}