{
  "type": "Feature",
  "properties": {
    "addr:full":"Rue Medaets 64 Sint-pieters-woluwe/woluwe-saint-pierre Bruxelles-Capitale 1150",
    "addr:housenumber":"64",
    "addr:postcode":"1150",
    "addr:street":"Rue Medaets;/",
    "iso:country":"BE",
    "sg:address":"Rue Medaets 64",
    "sg:city":"Sint-pieters-woluwe/woluwe-saint-pierre",
    "sg:orig_category":"Architectes",
    "sg:phone":"+32 2 762 55 08",
    "sg:postcode":"1150",
    "sg:province":"Bruxelles-Capitale",
    "wof:name":"Philippe Sacre",
    "wof:placetype":"venue"
},
  "geometry": {"coordinates":[4.4229578972,50.8387336731],"type":"Point"}
}