{
  "type": "Feature",
  "properties": {
    "addr:full":"Marie-jos\u00c9laan 36 Sint-lambrechts-woluwe/woluwe-saint-lambert Bruxelles-Capitale 1200",
    "addr:housenumber":"36",
    "addr:postcode":"1200",
    "addr:street":"Marie-Jose\u0301Laan",
    "iso:country":"BE",
    "sg:address":"Marie-jos\u00c9laan 36",
    "sg:city":"Sint-lambrechts-woluwe/woluwe-saint-lambert",
    "sg:orig_category":"Landmeters and schatters",
    "sg:phone":"+32 2 734 57 44",
    "sg:postcode":"1200",
    "sg:province":"Bruxelles-Capitale",
    "wof:name":"Bureau Servac",
    "wof:placetype":"venue"
},
  "geometry": {"coordinates":[4.4124269485,50.8458786011],"type":"Point"}
}