{
  "type": "Feature",
  "properties": {
    "addr:full":"Th. De Beckerstraat 6 Aarschot Vlaams-Brabant 3200",
    "addr:housenumber":"6",
    "addr:postcode":"3200",
    "addr:street":"Th. De Beckerstraat",
    "iso:country":"BE",
    "sg:address":"Th. De Beckerstraat 6",
    "sg:city":"Aarschot",
    "sg:classifiers":[
        {
            "category":"Shopping",
            "subcategory":"Luggage & Leather Goods",
            "type":"Retail Goods"
        }
    ],
    "sg:phone":"+32 16 56 13 00",
    "sg:postcode":"3200",
    "sg:province":"Vlaams-Brabant",
    "sg:tags":[
        "-"
    ],
    "wof:name":"Alco Bvba",
    "wof:placetype":"venue"
},
  "geometry": {"coordinates":[4.8366799355,50.9846801758],"type":"Point"}
}