{
  "type": "Feature",
  "properties": {
    "addr:full":"Rinkhout 176 Zele Oost-Vlaanderen 9240",
    "addr:housenumber":"176",
    "addr:postcode":"9240",
    "addr:street":"Rinkhout",
    "iso:country":"BE",
    "sg:address":"Rinkhout 176",
    "sg:city":"Zele",
    "sg:orig_category":"Afbraak- and draineerwerken",
    "sg:phone":"+32 52 45 09 30",
    "sg:postcode":"9240",
    "sg:province":"Oost-Vlaanderen",
    "wof:name":"B.t.k.m.",
    "wof:placetype":"venue"
},
  "geometry": {"coordinates":[4.0585999489,51.0716133118],"type":"Point"}
}