{
  "type": "Feature",
  "properties": {
    "iso:country":"BE",
    "sg:address":"Rue Alphonse-eloy 1",
    "sg:city":"Durbuy",
    "sg:orig_category":"H\u00f4tels",
    "sg:phone":"+32 86 21 26 66",
    "sg:postcode":"6940",
    "sg:province":"Luxembourg",
    "wof:name":"H\u00d4tel La Falize",
    "wof:placetype":"venue"
},
  "geometry": {"coordinates":[5.457005024,50.3520393372],"type":"Point"}
}