{
  "type": "Feature",
  "properties": {
    "addr:full":"Rue Edouard Dereume 1b6 Rixensart Brabant Wallon 1330",
    "addr:housenumber":"1b6",
    "addr:postcode":"1330",
    "addr:street":"Rue Edouard Dereume;Wallon",
    "iso:country":"BE",
    "sg:address":"Rue Edouard Dereume 1b6",
    "sg:city":"Rixensart",
    "sg:orig_category":"Administration d'immeubles",
    "sg:phone":"+32 2 653 56 70",
    "sg:postcode":"1330",
    "sg:province":"Brabant Wallon",
    "wof:name":"D. Boland",
    "wof:placetype":"venue"
},
  "geometry": {"coordinates":[4.5249099731,50.7172966003],"type":"Point"}
}