{
  "type": "Feature",
  "properties": {
    "iso:country":"BE",
    "sg:address":"Rue Chauny 6",
    "sg:city":"Tournai",
    "sg:orig_category":"Varkenskwekers",
    "sg:phone":"+32 69 35 24 38",
    "sg:postcode":"7520",
    "sg:province":"Hainaut",
    "wof:name":"Andre Glorieux",
    "wof:placetype":"venue"
},
  "geometry": {"coordinates":[3.2988340855,50.6522369385],"type":"Point"}
}