{
  "type": "Feature",
  "properties": {
    "addr:full":"Rue Du March\u00e9 Aux Poulets 55 Bruxelles Bruxelles-Capitale 1000",
    "addr:housenumber":"55",
    "addr:postcode":"1000",
    "addr:street":"Rue Du Marche\u0301 Aux Poulets",
    "iso:country":"BE",
    "sg:address":"Rue Du March\u00e9 Aux Poulets 55",
    "sg:city":"Bruxelles",
    "sg:classifiers":[
        {
            "category":"Bars & Pubs",
            "type":"Food & Drink"
        }
    ],
    "sg:phone":"+32 2 514 22 69",
    "sg:postcode":"1000",
    "sg:province":"Bruxelles-Capitale",
    "sg:tags":[
        "tavern"
    ],
    "wof:name":"Celtica",
    "wof:placetype":"venue"
},
  "geometry": {"coordinates":[4.3512530327,50.8483467102],"type":"Point"}
}