{
  "type": "Feature",
  "properties": {
    "addr:full":"Rue Barre Saint-brice 8 Tournai Hainaut 7500",
    "addr:housenumber":"8",
    "addr:postcode":"7500",
    "addr:street":"Rue Barre Saint-Brice",
    "iso:country":"BE",
    "sg:address":"Rue Barre Saint-brice 8",
    "sg:city":"Tournai",
    "sg:orig_category":"Fotogravure and zetwerk Secretariaatsdiensten",
    "sg:phone":"+32 69 84 16 16",
    "sg:postcode":"7500",
    "sg:province":"Hainaut",
    "wof:name":"Dege",
    "wof:placetype":"venue"
},
  "geometry": {"coordinates":[3.394397974,50.6079177856],"type":"Point"}
}